Workbook
Name Annual_Data: '$template-default'!$A$1:$A$2

Sheet Chart Data
A1: Changes to PSNBX forecast | I1: Impact on tax revenues of income tax & NICs decisions | S1: Real government spending across fiscal events | BI1: Real government spending across fiscal events | DG1: Interest rates - gilts | DL1: Interest rates - market expectations | DR1: Interest rates - gilts | DV1: Interest rates - short rates
S2: Real PSCE in RDEL per head (2024-2025=100) | Z2: Real PSGI in RDEL per head (2024-2025=100) | AG2: Real PSCE in RDEL per head (2023-2024 prices) | AM2: Real PSGI in RDEL per head (2023-2024 prices) | AS2: PSCE in RDEL per head | AY2: PSGI in RDEL per head | BI2: Real PSCE in RDEL (2024-2025=100) | BP2: Real PSGI in RDEL (2024-2025=100) | BW2: Real PSCE in RDEL (2023-2024 prices) | CC2: Real PSGI in RDEL (2023-2024 prices) | CI2: PSCE in RDEL | CO2: PSGI in RDEL | CU2: GDP deflator (2023-2024 = 100) | DA2: GDP deflator (raw)
B3: 2023- 2024 | C3: 2024- 2025 | D3: 2025- 2026 | E3: 2026- 2027 | F3: 2027- 2028 | G3: 2028- 2029 | J3: =OBR_NOV23_T3.A!D6 -> 2022-23 | K3: =OBR_NOV23_T3.A!E6 -> 2023-24 | L3: =OBR_NOV23_T3.A!F6 -> 2024-25 | M3: =OBR_NOV23_T3.A!G6 -> 2025-26 | N3: =OBR_NOV23_T3.A!H6 -> 2026-27 | O3: =OBR_NOV23_T3.A!I6 -> 2027-28 | P3: =OBR_NOV23_T3.A!J6 -> 2028-29 | S3: 44621 | T3: 44866 | U3: 44986 | V3: 45231 | W3: 45352 | X3: 100 LINE | Z3: 44621 | AA3: 44866 | AB3: 44986 | AC3: 45231 | AD3: 45352 | AE3: 100 LINE | AG3: 44621 | AH3: 44866 | AI3: 44986 | AJ3: 45231 | AK3: 45352 | AM3: 44621 | AN3: 44866 | AO3: 44986 | AP3: 45231 | AQ3: 45352 | AS3: SS22 | AT3: AS22 | AU3: Budget23 | AV3: AS23 | AW3: Budget24 | AY3: SS22 | AZ3: AS22 | BA3: Budget23 | BB3: AS23 | BC3: Budget24 | BF3: Population | BI3: 44621 | BJ3: 44866 | BK3: 44986 | BL3: 45231 | BM3: 45352 | BN3: 100 LINE | BP3: 44621 | BQ3: 44866 | BR3: 44986 | BS3: 45231 | BT3: 45352 | BU3: 100 LINE | BW3: 44621 | BX3: 44866 | BY3: 44986 | BZ3: 45231 | CA3: 45352 | CC3: 44621 | CD3: 44866 | CE3: 44986 | CF3: 45231 | CG3: 45352 | CI3: SS22 | CJ3: AS22 | CK3: Budget23 | CL3: AS23 | CM3: Budget24 | CO3: SS22 | CP3: AS22 | CQ3: Budget23 | CR3: AS23 | CS3: Budget24 | CU3: SS22 | CV3: AS22 | CW3: Budget23 | CX3: AS23 | CY3: Budget24 | DA3: SS22 | DB3: AS22 | DC3: Budget23 | DD3: AS23 | DE3: Budget24 | DH3: Autumn Statement 2023 | DI3: Budget 24 | DJ3: 10 days to 5th March | DM3: AS 2023 | DN3: Budget 24 | DO3: 10 days to 5th March | DR3: OBR gilt | DS3: OE gilt | DT3: Impact | DV3: OBR RCB | DW3: OE RCB | DX3: Impact
A4: Underlying forecast changes | B4: =OBR_MAR24_T4.12!D11 -> -10.148123 | C4: =OBR_MAR24_T4.12!E11 -> -10.012101 | D4: =OBR_MAR24_T4.12!F11 -> -9.721845 | E4: =OBR_MAR24_T4.12!G11 -> -6.171292 | F4: =OBR_MAR24_T4.12!H11 -> -3.6160179 | G4: =OBR_MAR24_T4.12!I11 -> -0.77357379 | I4: Income tax threshold freezes | J4: =-SUM(OBR_MAR24_T3.8!C8:C9) -> 2.99 | K4: =-SUM(OBR_MAR24_T3.8!D8:D9) -> 13.99 | L4: =-SUM(OBR_MAR24_T3.8!E8:E9) -> 24.045 | M4: =-SUM(OBR_MAR24_T3.8!F8:F9) -> 27.86 | N4: =-SUM(OBR_MAR24_T3.8!G8:G9) -> 30.205 | O4: =-SUM(OBR_MAR24_T3.8!H8:H9) -> 33.16 | P4: =-SUM(OBR_MAR24_T3.8!I8:I9) -> 34.555 | R4: 2019-20 | S4: =100*(AG4/AG$9) -> 90.373881 | X4: 100 | Z4: =100*(AM4/AM$9) -> 71.911288 | AE4: 100 | AG4: =100*(AS4/CU4) -> 5.3545791 | AM4: =100*(AY4/CU4) -> 0.9643959 | AS4: =CI4/($BF4/1000) -> 4.7966918 | AY4: =CO4/($BF4/1000) -> 0.86391662 | BE4: 202001 | BF4: =VLOOKUP(BE4,Data!$A$7:$C$318,3,FALSE) -> 67010 | BH4: 2019-20 | BI4: =100*(BW4/BW$9) -> 87.201559 | BN4: 100 | BP4: =100*(CC4/CC$9) -> 69.387043 | BU4: 100 | BW4: =100*(CI4/CU4) -> 358.81034 | CC4: =100*(CO4/CU4) -> 64.624169 | CI4: {=TRANSPOSE(OBR_MAR22_T3.16!C8:J8)} -> 321.42632 | CO4: {=TRANSPOSE(OBR_MAR22_T3.16!C31:J31)} -> 57.891053 | CU4: =100*(DA4/DA$8) -> 89.581117 | CV4: =100*(DB4/DB$8) -> 87.221869 | CW4: =100*(DC4/DC$8) -> 87.485684 | CX4: =100*(DD4/DD$8) -> 84.464903 | CY4: =100*(DE4/DE$8) -> 84.011728 | DA4: =OBR_MAR22_1.2!X112 -> 100.74871 | DB4: =OBR_NOV22_1.2!X117 -> 100.88484 | DC4: =OBR_MAR23_1.2!X117 -> 100.88484 | DD4: =OBR_NOV23_1.2!X122 -> 100.73409 | DE4: =OBR_MAR24_1.2!X122 -> 100.73409 | DG4: 2 | DH4: {=TRANSPOSE(HAVERD!B318:G318)} -> 4.8863636 | DI4: {=TRANSPOSE(HAVERD!B319:G319)} -> 4.2618182 | DJ4: {=TRANSPOSE(HAVERD!B321:G321)} -> 4.358 | DL4: 2024 | DM4: {=TRANSPOSE(HAVERD!H318:L318)} -> 5.1774546 | DN4: {=TRANSPOSE(HAVERD!H319:L319)} -> 4.0490152 | DO4: {=TRANSPOSE(HAVERD!H321:L321)} -> 4.4681172 | DQ4: FY2022/23 | DR4: 3.1333693 | DS4: =DR4 -> 3.1333693 | DV4: 2.30915 | DW4: =AVERAGE([2]CSV!AG207:AG210) -> 2.3120337
A5: Policy decisions - NICs cut | B5: =OBR_MAR24_T4.12!D21 -> 0 | C5: =OBR_MAR24_T4.12!E21 -> 10.196025 | D5: =OBR_MAR24_T4.12!F21 -> 10.329817 | E5: =OBR_MAR24_T4.12!G21 -> 10.465234 | F5: =OBR_MAR24_T4.12!H21 -> 10.705217 | G5: =OBR_MAR24_T4.12!I21 -> 11.037294 | I5: NICs threshold freezes | J5: =-SUM(OBR_MAR24_T3.8!C10:C12) -> -6.72 | K5: =-SUM(OBR_MAR24_T3.8!D10:D12) -> -2.12 | L5: =-SUM(OBR_MAR24_T3.8!E10:E12) -> 2.66 | M5: =-SUM(OBR_MAR24_T3.8!F10:F12) -> 4.105 | N5: =-SUM(OBR_MAR24_T3.8!G10:G12) -> 5.145 | O5: =-SUM(OBR_MAR24_T3.8!H10:H12) -> 6.34 | P5: =-SUM(OBR_MAR24_T3.8!I10:I12) -> 6.57 | R5: 2020-21 | S5: =100*(AG5/AG$9) -> 115.53143 | X5: 100 | Z5: =100*(AM5/AM$9) -> 85.311714 | AE5: 100 | AG5: =100*(AS5/CU5) -> 6.8451431 | AM5: =100*(AY5/CU5) -> 1.1441078 | AS5: =CI5/($BF5/1000) -> 6.4814935 | AY5: =CO5/($BF5/1000) -> 1.0833269 | BE5: =+BE4+100 -> 202101 | BF5: =VLOOKUP(BE5,Data!$A$7:$C$318,3,FALSE) -> 67039.75 | BH5: 2020-21 | BI5: =100*(BW5/BW$9) -> 111.52551 | BN5: 100 | BP5: =100*(CC5/CC$9) -> 82.353631 | BU5: 100 | BW5: =100*(CI5/CU5) -> 458.89668 | CC5: =100*(CO5/CU5) -> 76.700702 | CI5: 434.5177 | CO5: 72.625962 | CU5: =100*(DA5/DA$8) -> 94.68748 | CV5: =100*(DB5/DB$8) -> 92.72465 | CW5: =100*(DC5/DC$8) -> 92.876405 | CX5: =100*(DD5/DD$8) -> 88.965576 | CY5: =100*(DE5/DE$8) -> 88.488253 | DA5: =OBR_MAR22_1.2!X113 -> 106.49166 | DB5: =OBR_NOV22_1.2!X118 -> 107.24961 | DC5: =OBR_MAR23_1.2!X118 -> 107.10119 | DD5: =OBR_NOV23_1.2!X123 -> 106.10166 | DE5: =OBR_MAR24_1.2!X123 -> 106.10166 | DG5: 5 | DH5: 4.5309091 | DI5: 3.7881818 | DJ5: 4.065 | DL5: 2025 | DM5: 4.5591652 | DN5: 3.3800845 | DO5: 3.8999436 | DQ5: FY2023/24 | DR5: 4.2044264 | DS5: =DR5+0.05 -> 4.2544264 | DT5: ='OBR RR Oct23 - Debt interest'!C8*(DS5-DR5) -> 55.397924 | DV5: 5.0075041 | DW5: =DV5 -> 5.0075041 | DX5: ='OBR RR Oct23 - Debt interest'!C13*(DW5-DV5) -> 0
A6: Policy decisions - other tax | B6: =OBR_MAR24_T4.12!D22+OBR_MAR24_T4.12!D23 -> 0.18808678 | C6: =OBR_MAR24_T4.12!E22+OBR_MAR24_T4.12!E23 -> 3.3254114 | D6: =OBR_MAR24_T4.12!F22+OBR_MAR24_T4.12!F23 -> -0.084666271 | E6: =OBR_MAR24_T4.12!G22+OBR_MAR24_T4.12!G23 -> -3.2535558 | F6: =OBR_MAR24_T4.12!H22+OBR_MAR24_T4.12!H23 -> -5.1248695 | G6: =OBR_MAR24_T4.12!I22+OBR_MAR24_T4.12!I23 -> -5.1179031 | I6: NICs rate cut (AS 23) | J6: =-OBR_MAR24_T3.8!C15 -> 0 | K6: =-OBR_MAR24_T3.8!D15 -> -2.3828955 | L6: =-OBR_MAR24_T3.8!E15 -> -9.9944842 | M6: =-OBR_MAR24_T3.8!F15 -> -10.141012 | N6: =-OBR_MAR24_T3.8!G15 -> -10.17163 | O6: =-OBR_MAR24_T3.8!H15 -> -10.385803 | P6: =-OBR_MAR24_T3.8!I15 -> -10.66816 | R6: 2021-22 | S6: =100*(AG6/AG$9) -> 107.90585 | T6: =100*(AH6/AH$9) -> 110.60751 | U6: =100*(AI6/AI$9) -> 109.75831 | X6: 100 | Z6: =100*(AM6/AM$9) -> 81.457188 | AA6: =100*(AN6/AN$9) -> 91.691086 | AB6: =100*(AO6/AO$9) -> 89.933662 | AE6: 100 | AG6: =100*(AS6/CU6) -> 6.3933339 | AH6: =100*(AT6/CV6) -> 6.6337119 | AI6: =100*(AU6/CW6) -> 6.6388806 | AM6: =100*(AY6/CU6) -> 1.0924151 | AN6: =100*(AZ6/CV6) -> 1.234348 | AO6: =100*(BA6/CW6) -> 1.2353097 | AS6: =CI6/($BF6/1000) -> 6.0001556 | AT6: =CJ6/($BF6/1000) -> 6.1295229 | AU6: =CK6/($BF6/1000) -> 6.1295229 | AY6: =CO6/($BF6/1000) -> 1.0252336 | AZ6: =CP6/($BF6/1000) -> 1.1405325 | BA6: =CQ6/($BF6/1000) -> 1.1405325 | BE6: =+BE5+100 -> 202201 | BF6: =VLOOKUP(BE6,Data!$A$7:$C$318,3,FALSE) -> 67502.88 | BH6: 2021-22 | BI6: =100*(BW6/BW$9) -> 104.88394 | BJ6: =100*(BX6/BX$9) -> 107.50994 | BK6: =100*(BY6/BY$9) -> 106.68452 | BN6: 100 | BP6: =100*(CC6/CC$9) -> 79.175973 | BQ6: =100*(CD6/CD$9) -> 89.123271 | BR6: =100*(CE6/CE$9) -> 87.415063 | BU6: 100 | BW6: =100*(CI6/CU6) -> 431.56845 | BX6: =100*(CJ6/CV6) -> 447.79466 | BY6: =100*(CK6/CW6) -> 448.14356 | CC6: =100*(CO6/CU6) -> 73.741166 | CD6: =100*(CP6/CV6) -> 83.322042 | CE6: =100*(CQ6/CW6) -> 83.386964 | CI6: 405.02778 | CJ6: {=TRANSPOSE(OBR_NOV22_TA.8!C8:I8)} -> 413.76045 | CK6: {=TRANSPOSE(OBR_MAR23_TA.7!D8:J8)} -> 413.76045 | CO6: 69.20622 | CP6: {=TRANSPOSE(OBR_NOV22_TA.8!C30:I30)} -> 76.989229 | CQ6: {=TRANSPOSE(OBR_MAR23_TA.7!D32:J32)} -> 76.989229 | CU6: =100*(DA6/DA$8) -> 93.850184 | CV6: =100*(DB6/DB$8) -> 92.399594 | CW6: =100*(DC6/DC$8) -> 92.327656 | CX6: =100*(DD6/DD$8) -> 88.374124 | CY6: =100*(DE6/DE$8) -> 87.880815 | DA6: =OBR_MAR22_1.2!X114 -> 105.54998 | DB6: =OBR_NOV22_1.2!X119 -> 106.87364 | DC6: =OBR_MAR23_1.2!X119 -> 106.4684 | DD6: =OBR_NOV23_1.2!X124 -> 105.39629 | DE6: =OBR_MAR24_1.2!X124 -> 105.37331 | DG6: 10 | DH6: 4.4927273 | DI6: 3.8763636 | DJ6: 4.12 | DL6: 2026 | DM6: 4.2005259 | DN6: 3.2100345 | DO6: 3.6148366 | DQ6: FY2024/25 | DR6: 3.8713343 | DS6: =DR6+0.05 -> 3.9213343 | DT6: ='OBR RR Oct23 - Debt interest'!D9*(DS6-DR6)+'OBR RR Oct23 - Debt interest'!D8*(DS5-DR5) -> 167.11496 | DV6: 4.3665594 | DW6: =DV6+(DO4-DN4) -> 4.7856613 | DX6: ='OBR RR Oct23 - Debt interest'!D14*(DW6-DV6)+'OBR RR Oct23 - Debt interest'!D13*(DW5-DV5) -> 4172.2539 | DZ6: =DX6+DT6 -> 4339.3688
A7: Policy decisions - spending | B7: =OBR_MAR24_T4.12!D24 -> -0.13021465 | C7: =OBR_MAR24_T4.12!E24 -> 0.3781002 | D7: =OBR_MAR24_T4.12!F24 -> -0.1288523 | E7: =OBR_MAR24_T4.12!G24 -> 0.47131558 | F7: =OBR_MAR24_T4.12!H24 -> 0.7581139 | G7: =OBR_MAR24_T4.12!I24 -> 0.017641508 | I7: NICs rate cut (Budget 24) | J7: =-OBR_MAR24_T3.8!C16 -> 0 | K7: =-OBR_MAR24_T3.8!D16 -> 0 | L7: =-OBR_MAR24_T3.8!E16 -> -10.070957 | M7: =-OBR_MAR24_T3.8!F16 -> -10.145467 | N7: =-OBR_MAR24_T3.8!G16 -> -10.226379 | O7: =-OBR_MAR24_T3.8!H16 -> -10.44633 | P7: =-OBR_MAR24_T3.8!I16 -> -10.749149 | R7: 2022-23 | S7: =100*(AG7/AG$9) -> 103.17708 | T7: =100*(AH7/AH$9) -> 104.89353 | U7: =100*(AI7/AI$9) -> 103.31983 | V7: =100*(AJ7/AJ$9) -> 103.83787 | W7: =100*(AK7/AK$9) -> 103.61763 | X7: 100 | Z7: =100*(AM7/AM$9) -> 96.315408 | AA7: =100*(AN7/AN$9) -> 99.895826 | AB7: =100*(AO7/AO$9) -> 94.520759 | AC7: =100*(AP7/AP$9) -> 99.455563 | AD7: =100*(AQ7/AQ$9) -> 99.024219 | AE7: 100 | AG7: =100*(AS7/CU7) -> 6.1131583 | AH7: =100*(AT7/CV7) -> 6.2910147 | AI7: =100*(AU7/CW7) -> 6.2494401 | AJ7: =100*(AV7/CX7) -> 6.4037004 | AK7: =100*(AW7/CY7) -> 6.3681662 | AM7: =100*(AY7/CU7) -> 1.2916774 | AN7: =100*(AZ7/CV7) -> 1.3448004 | AO7: =100*(BA7/CW7) -> 1.2983171 | AP7: =100*(BB7/CX7) -> 1.3972027 | AQ7: =100*(BC7/CY7) -> 1.4033571 | AS7: =CI7/($BF7/1000) -> 5.9692921 | AT7: =CJ7/($BF7/1000) -> 6.0939635 | AU7: =CK7/($BF7/1000) -> 6.0939603 | AV7: =CL7/($BF7/1000) -> 6.0361903 | AW7: =CM7/($BF7/1000) -> 5.9763705 | AY7: =CO7/($BF7/1000) -> 1.2612792 | AZ7: =CP7/($BF7/1000) -> 1.3026777 | BA7: =CQ7/($BF7/1000) -> 1.2660163 | BB7: =CR7/($BF7/1000) -> 1.3170169 | BC7: =CS7/($BF7/1000) -> 1.3170169 | BE7: =+BE6+100 -> 202301 | BF7: =VLOOKUP(BE7,Data!$A$7:$C$318,3,FALSE) -> 68178.12 | BH7: 2022-23 | BI7: =100*(BW7/BW$9) -> 101.29079 | BJ7: =100*(BX7/BX$9) -> 102.97586 | BK7: =100*(BY7/BY$9) -> 101.43092 | BL7: =100*(BZ7/BZ$9) -> 101.93949 | BM7: =100*(CA7/CA$9) -> 101.72329 | BN7: 100 | BP7: =100*(CC7/CC$9) -> 94.554562 | BQ7: =100*(CD7/CD$9) -> 98.069522 | BR7: =100*(CE7/CE$9) -> 92.792723 | BS7: =100*(CF7/CF$9) -> 97.637308 | BT7: =100*(CG7/CG$9) -> 97.21385 | BU7: 100 | BW7: =100*(CI7/CU7) -> 416.78364 | BX7: =100*(CJ7/CV7) -> 428.90955 | BY7: =100*(CK7/CW7) -> 426.07508 | BZ7: =100*(CL7/CX7) -> 436.59226 | CA7: =100*(CM7/CY7) -> 434.1696 | CC7: =100*(CO7/CU7) -> 88.064136 | CD7: =100*(CP7/CV7) -> 91.685962 | CE7: =100*(CQ7/CW7) -> 88.51682 | CF7: =100*(CR7/CX7) -> 95.258654 | CG7: =100*(CS7/CY7) -> 95.678252 | CI7: 406.97511 | CJ7: 415.47497 | CK7: 415.47476 | CL7: {=TRANSPOSE(OBR_NOV23_TA.7!C8:I8)} -> 411.5361 | CM7: {=TRANSPOSE(OBR_MAR24_TA.7!C8:I8)} -> 407.4577 | CO7: 85.991647 | CP7: 88.814116 | CQ7: 86.31461 | CR7: {=TRANSPOSE(OBR_NOV23_TA.7!C32:I32)} -> 89.791733 | CS7: {=TRANSPOSE(OBR_MAR24_TA.7!C32:I32)} -> 89.791733 | CU7: =100*(DA7/DA$8) -> 97.646614 | CV7: =100*(DB7/DB$8) -> 96.867736 | CW7: =100*(DC7/DC$8) -> 97.5121 | CX7: =100*(DD7/DD$8) -> 94.260972 | CY7: =100*(DE7/DE$8) -> 93.847589 | DA7: =OBR_MAR22_1.2!X115 -> 109.81969 | DB7: =OBR_NOV22_1.2!X120 -> 112.0417 | DC7: =OBR_MAR23_1.2!X120 -> 112.44689 | DD7: =OBR_NOV23_1.2!X125 -> 112.41703 | DE7: =OBR_MAR24_1.2!X125 -> 112.52776 | DG7: 15 | DH7: 4.8027273 | DI7: 4.2445455 | DJ7: 4.415 | DL7: 2027 | DM7: 4.0434114 | DN7: 3.1959024 | DO7: 3.4910066 | DQ7: FY2025/26 | DR7: 3.9037698 | DS7: =DR7+0.05 -> 3.9537698 | DT7: ='OBR RR Oct23 - Debt interest'!E10*(DS7-DR7)+'OBR RR Oct23 - Debt interest'!E9*(DS6-DR6)+'OBR RR Oct23 - Debt interest'!E8*(DS5-DR5) -> 275.76327 | DV7: 3.4904092 | DW7: =DV7+(DO5-DN5) -> 4.0102683 | DX7: ='OBR RR Oct23 - Debt interest'!E15*(DW7-DV7)+'OBR RR Oct23 - Debt interest'!E14*(DW6-DV6) -> 4843.9166 | DZ7: =DX7+DT7 -> 5119.6799
A8: Other | B8: =OBR_MAR24_T4.12!D25 -> 0.26529421 | C8: =OBR_MAR24_T4.12!E25 -> -1.2311794 | D8: =OBR_MAR24_T4.12!F25 -> 0.25222169 | E8: =OBR_MAR24_T4.12!G25 -> -1.2566479 | F8: =OBR_MAR24_T4.12!H25 -> -1.2189023 | G8: =OBR_MAR24_T4.12!I25 -> -0.73269675 | I8: Total impact | J8: =SUM(J4:J7) -> -3.73 | K8: =SUM(K4:K7) -> 9.4871045 | L8: =SUM(L4:L7) -> 6.639559 | M8: =SUM(M4:M7) -> 11.678521 | N8: =SUM(N4:N7) -> 14.951991 | O8: =SUM(O4:O7) -> 18.667867 | P8: =SUM(P4:P7) -> 19.707692 | R8: 2023-24 | S8: =100*(AG8/AG$9) -> 100.02575 | T8: =100*(AH8/AH$9) -> 101.64064 | U8: =100*(AI8/AI$9) -> 101.26212 | V8: =100*(AJ8/AJ$9) -> 100.45562 | W8: =100*(AK8/AK$9) -> 99.957754 | X8: 100 | Z8: =100*(AM8/AM$9) -> 102.50842 | AA8: =100*(AN8/AN$9) -> 101.90418 | AB8: =100*(AO8/AO$9) -> 101.63336 | AC8: =100*(AP8/AP$9) -> 99.255834 | AD8: =100*(AQ8/AQ$9) -> 97.965078 | AE8: 100 | AG8: =100*(AS8/CU8) -> 5.9264446 | AH8: =100*(AT8/CV8) -> 6.0959215 | AI8: =100*(AU8/CW8) -> 6.124977 | AJ8: =100*(AV8/CX8) -> 6.1951164 | AK8: =100*(AW8/CY8) -> 6.1432362 | AM8: =100*(AY8/CU8) -> 1.3747314 | AN8: =100*(AZ8/CV8) -> 1.3718369 | AO8: =100*(BA8/CW8) -> 1.3960143 | AP8: =100*(BB8/CX8) -> 1.3943968 | AQ8: =100*(BC8/CY8) -> 1.3883471 | AS8: =CI8/($BF8/1000) -> 5.9264446 | AT8: =CJ8/($BF8/1000) -> 6.0959215 | AU8: =CK8/($BF8/1000) -> 6.124977 | AV8: =CL8/($BF8/1000) -> 6.1951164 | AW8: =CM8/($BF8/1000) -> 6.1432362 | AY8: =CO8/($BF8/1000) -> 1.3747314 | AZ8: =CP8/($BF8/1000) -> 1.3718369 | BA8: =CQ8/($BF8/1000) -> 1.3960143 | BB8: =CR8/($BF8/1000) -> 1.3943968 | BC8: =CS8/($BF8/1000) -> 1.3883471 | BE8: =+BE7+100 -> 202401 | BF8: =VLOOKUP(BE8,Data!$A$7:$C$318,3,FALSE) -> 68847.18 | BH8: 2023-24 | BI8: =100*(BW8/BW$9) -> 99.160721 | BJ8: =100*(BX8/BX$9) -> 100.76164 | BK8: =100*(BY8/BY$9) -> 100.3864 | BL8: =100*(BZ8/BZ$9) -> 99.586867 | BM8: =100*(CA8/CA$9) -> 99.093311 | BN8: 100 | BP8: =100*(CC8/CC$9) -> 101.62192 | BQ8: =100*(CD8/CD$9) -> 101.0229 | BR8: =100*(CE8/CE$9) -> 100.75443 | BS8: =100*(CF8/CF$9) -> 98.397461 | BT8: =100*(CG8/CG$9) -> 97.117868 | BU8: 100 | BW8: =100*(CI8/CU8) -> 408.019 | BX8: =100*(CJ8/CV8) -> 419.68701 | BY8: =100*(CK8/CW8) -> 421.6874 | BZ8: =100*(CL8/CX8) -> 426.51629 | CA8: =100*(CM8/CY8) -> 422.94449 | CC8: =100*(CO8/CU8) -> 94.646379 | CD8: =100*(CP8/CV8) -> 94.447103 | CE8: =100*(CQ8/CW8) -> 96.111651 | CF8: =100*(CR8/CX8) -> 96.000288 | CG8: =100*(CS8/CY8) -> 95.583786 | CI8: 408.019 | CJ8: 419.68701 | CK8: 421.6874 | CL8: 426.51629 | CM8: 422.94449 | CO8: 94.646379 | CP8: 94.447103 | CQ8: 96.111651 | CR8: 96.000288 | CS8: 95.583786 | CU8: =100*(DA8/DA$8) -> 100 | CV8: =100*(DB8/DB$8) -> 100 | CW8: =100*(DC8/DC$8) -> 100 | CX8: =100*(DD8/DD$8) -> 100 | CY8: =100*(DE8/DE$8) -> 100 | DA8: =OBR_MAR22_1.2!X116 -> 112.46646 | DB8: =OBR_NOV22_1.2!X121 -> 115.66462 | DC8: =OBR_MAR23_1.2!X121 -> 115.31583 | DD8: =OBR_NOV23_1.2!X126 -> 119.26148 | DE8: =OBR_MAR24_1.2!X126 -> 119.9048 | DG8: 20 | DH8: 4.8945455 | DI8: 4.4172727 | DJ8: 4.561 | DL8: 2028 | DM8: 3.9784684 | DN8: 3.2529278 | DO8: 3.4607663 | DQ8: FY2026/27 | DR8: 4.028261 | DS8: =DR8+0.05 -> 4.078261 | DT8: ='OBR RR Oct23 - Debt interest'!F11*(DS8-DR8)+'OBR RR Oct23 - Debt interest'!F10*(DS7-DR7)+'OBR RR Oct23 - Debt interest'!F9*(DS6-DR6)+'OBR RR Oct23 - Debt interest'!F8*(DS5-DR5) -> 361.99077 | DV8: 3.2404348 | DW8: =DV8+(DO6-DN6) -> 3.6452369 | DX8: ='OBR RR Oct23 - Debt interest'!F16*(DW8-DV8)+'OBR RR Oct23 - Debt interest'!F15*(DW7-DV7) -> 3548.3844 | DZ8: =DX8+DT8 -> 3910.3752
A9: Change to PSNB forecast | B9: =SUM(B4:B8) -> -9.8249571 | C9: =SUM(C4:C8) -> 2.6562558 | D9: =SUM(D4:D8) -> 0.64667534 | E9: =SUM(E4:E8) -> 0.2550542 | F9: =SUM(F4:F8) -> 1.5035416 | G9: =SUM(G4:G8) -> 4.4307623 | R9: 2024-25 | S9: =100*(AG9/AG$9) -> 100 | T9: =100*(AH9/AH$9) -> 100 | U9: =100*(AI9/AI$9) -> 100 | V9: =100*(AJ9/AJ$9) -> 100 | W9: =100*(AK9/AK$9) -> 100 | X9: 100 | Z9: =100*(AM9/AM$9) -> 100 | AA9: =100*(AN9/AN$9) -> 100 | AB9: =100*(AO9/AO$9) -> 100 | AC9: =100*(AP9/AP$9) -> 100 | AD9: =100*(AQ9/AQ$9) -> 100 | AE9: 100 | AG9: =100*(AS9/CU9) -> 5.9249188 | AH9: =100*(AT9/CV9) -> 5.9975238 | AI9: =100*(AU9/CW9) -> 6.0486359 | AJ9: =100*(AV9/CX9) -> 6.1670185 | AK9: =100*(AW9/CY9) -> 6.1458326 | AM9: =100*(AY9/CU9) -> 1.3410911 | AN9: =100*(AZ9/CV9) -> 1.3462028 | AO9: =100*(BA9/CW9) -> 1.3735788 | AP9: =100*(BB9/CX9) -> 1.4048512 | AQ9: =100*(BC9/CY9) -> 1.4171858 | AS9: =CI9/($BF9/1000) -> 6.0347252 | AT9: =CJ9/($BF9/1000) -> 6.0765288 | AU9: =CK9/($BF9/1000) -> 6.1435572 | AV9: =CL9/($BF9/1000) -> 6.2702082 | AW9: =CM9/($BF9/1000) -> 6.1945168 | AY9: =CO9/($BF9/1000) -> 1.3659455 | AZ9: =CP9/($BF9/1000) -> 1.3639362 | BA9: =CQ9/($BF9/1000) -> 1.3951344 | BB9: =CR9/($BF9/1000) -> 1.4283579 | BC9: =CS9/($BF9/1000) -> 1.428412 | BE9: =+BE8+100 -> 202501 | BF9: =VLOOKUP(BE9,Data!$A$7:$C$318,3,FALSE) -> 69447.77 | BH9: 2024-25 | BI9: =100*(BW9/BW$9) -> 100 | BJ9: =100*(BX9/BX$9) -> 100 | BK9: =100*(BY9/BY$9) -> 100 | BL9: =100*(BZ9/BZ$9) -> 100 | BM9: =100*(CA9/CA$9) -> 100 | BN9: 100 | BP9: =100*(CC9/CC$9) -> 100 | BQ9: =100*(CD9/CD$9) -> 100 | BR9: =100*(CE9/CE$9) -> 100 | BS9: =100*(CF9/CF$9) -> 100 | BT9: =100*(CG9/CG$9) -> 100 | BU9: 100 | BW9: =100*(CI9/CU9) -> 411.4724 | BX9: =100*(CJ9/CV9) -> 416.51465 | BY9: =100*(CK9/CW9) -> 420.06427 | BZ9: =100*(CL9/CX9) -> 428.28568 | CA9: =100*(CM9/CY9) -> 426.81437 | CC9: =100*(CO9/CU9) -> 93.135788 | CD9: =100*(CP9/CV9) -> 93.490781 | CE9: =100*(CQ9/CW9) -> 95.391985 | CF9: =100*(CR9/CX9) -> 97.563786 | CG9: =100*(CS9/CY9) -> 98.420392 | CI9: 419.09821 | CJ9: 422.00137 | CK9: 426.65635 | CL9: 435.45198 | CM9: 430.19538 | CO9: 94.861872 | CP9: 94.722329 | CQ9: 96.888973 | CR9: 99.196273 | CS9: 99.20003 | CU9: =100*(DA9/DA$8) -> 101.8533 | CV9: =100*(DB9/DB$8) -> 101.31729 | CW9: =100*(DC9/DC$8) -> 101.5693 | CX9: =100*(DD9/DD$8) -> 101.67325 | CY9: =100*(DE9/DE$8) -> 100.79215 | DA9: =OBR_MAR22_1.2!X117 -> 114.5508 | DB9: =OBR_NOV22_1.2!X122 -> 117.18826 | DC9: =OBR_MAR23_1.2!X122 -> 117.12548 | DD9: =OBR_NOV23_1.2!X127 -> 121.25702 | DE9: =OBR_MAR24_1.2!X127 -> 120.85462 | DG9: 30 | DH9: 4.9418182 | DI9: 4.5090909 | DJ9: 4.596 | DQ9: FY2027/28 | DR9: 4.2057432 | DS9: =DR9+0.05 -> 4.2557432 | DT9: ='OBR RR Oct23 - Debt interest'!G12*(DS9-DR9)+'OBR RR Oct23 - Debt interest'!G11*(DS8-DR8)+'OBR RR Oct23 - Debt interest'!G10*(DS7-DR7)+'OBR RR Oct23 - Debt interest'!G9*(DS6-DR6)+'OBR RR Oct23 - Debt interest'!G8*(DS5-DR5) -> 443.03413 | DV9: 3.2030148 | DW9: =DV9+(DO7-DN7) -> 3.498119 | DX9: ='OBR RR Oct23 - Debt interest'!G17*(DW9-DV9)+'OBR RR Oct23 - Debt interest'!G16*(DW8-DV8) -> 2351.8635 | DZ9: =DX9+DT9 -> 2794.8976
R10: 2025-26 | S10: =100*(AG10/AG$9) -> 101.14957 | T10: =100*(AH10/AH$9) -> 100.68932 | U10: =100*(AI10/AI$9) -> 100.43593 | V10: =100*(AJ10/AJ$9) -> 99.792219 | W10: =100*(AK10/AK$9) -> 100.184 | X10: 100 | Z10: =100*(AM10/AM$9) -> 101.87877 | AA10: =100*(AN10/AN$9) -> 99.661585 | AB10: =100*(AO10/AO$9) -> 98.510929 | AC10: =100*(AP10/AP$9) -> 95.650971 | AD10: =100*(AQ10/AQ$9) -> 96.820909 | AE10: 100 | AG10: =100*(AS10/CU10) -> 5.9930301 | AH10: =100*(AT10/CV10) -> 6.0388659 | AI10: =100*(AU10/CW10) -> 6.0750035 | AJ10: =100*(AV10/CX10) -> 6.1542047 | AK10: =100*(AW10/CY10) -> 6.157141 | AM10: =100*(AY10/CU10) -> 1.3662872 | AN10: =100*(AZ10/CV10) -> 1.341647 | AO10: =100*(BA10/CW10) -> 1.3531252 | AP10: =100*(BB10/CX10) -> 1.3437538 | AQ10: =100*(BC10/CY10) -> 1.3721322 | AS10: =CI10/($BF10/1000) -> 6.2233038 | AT10: =CJ10/($BF10/1000) -> 6.1508593 | AU10: =CK10/($BF10/1000) -> 6.2297609 | AV10: =CL10/($BF10/1000) -> 6.364352 | AW10: =CM10/($BF10/1000) -> 6.2896463 | AY10: =CO10/($BF10/1000) -> 1.4187848 | AZ10: =CP10/($BF10/1000) -> 1.3665285 | BA10: =CQ10/($BF10/1000) -> 1.3875954 | BB10: =CR10/($BF10/1000) -> 1.3896389 | BC10: =CS10/($BF10/1000) -> 1.4016612 | BE10: =+BE9+100 -> 202601 | BF10: =VLOOKUP(BE10,Data!$A$7:$C$318,3,FALSE) -> 69961.86 | BH10: 2025-26 | BI10: =100*(BW10/BW$9) -> 101.89834 | BJ10: =100*(BX10/BX$9) -> 101.43468 | BK10: =100*(BY10/BY$9) -> 101.17941 | BL10: =100*(BZ10/BZ$9) -> 100.53094 | BM10: =100*(CA10/CA$9) -> 100.92562 | BN10: 100 | BP10: =100*(CC10/CC$9) -> 102.63294 | BQ10: =100*(CD10/CD$9) -> 100.39933 | BR10: =100*(CE10/CE$9) -> 99.24016 | BS10: =100*(CF10/CF$9) -> 96.359031 | BT10: =100*(CG10/CG$9) -> 97.53763 | BU10: 100 | BW10: =100*(CI10/CU10) -> 419.28353 | BX10: =100*(CJ10/CV10) -> 422.49029 | BY10: =100*(CK10/CW10) -> 425.01855 | BZ10: =100*(CL10/CX10) -> 430.5596 | CA10: =100*(CM10/CY10) -> 430.76503 | CC10: =100*(CO10/CU10) -> 95.587994 | CD10: =100*(CP10/CV10) -> 93.864122 | CE10: =100*(CQ10/CW10) -> 94.667158 | CF10: =100*(CR10/CX10) -> 94.011519 | CG10: =100*(CS10/CY10) -> 95.996918 | CI10: 435.39391 | CJ10: 430.32556 | CK10: 435.84566 | CL10: 445.2619 | CM10: 440.03535 | CO10: 99.260827 | CP10: 95.604873 | CQ10: 97.078752 | CR10: 97.221725 | CS10: 98.062828 | CU10: =100*(DA10/DA$8) -> 103.84236 | CV10: =100*(DB10/DB$8) -> 101.85454 | CW10: =100*(DC10/DC$8) -> 102.54745 | CX10: =100*(DD10/DD$8) -> 103.4147 | CY10: =100*(DE10/DE$8) -> 102.15206 | DA10: =OBR_MAR22_1.2!X118 -> 116.78782 | DB10: =OBR_NOV22_1.2!X123 -> 117.80967 | DC10: =OBR_MAR23_1.2!X123 -> 118.25344 | DD10: =OBR_NOV23_1.2!X128 -> 123.33389 | DE10: =OBR_MAR24_1.2!X128 -> 122.48522 | DQ10: FY2028/29 | DR10: 4.4042974 | DS10: =DR10+0.05 -> 4.4542974 | DT10: ='OBR RR Oct23 - Debt interest'!J12*(DS10-DR10)+'OBR RR Oct23 - Debt interest'!H12*(DS9-DR9)+'OBR RR Oct23 - Debt interest'!H11*(DS8-DR8)+'OBR RR Oct23 - Debt interest'!H10*(DS7-DR7)+'OBR RR Oct23 - Debt interest'!H9*(DS6-DR6)+'OBR RR Oct23 - Debt interest'!H8*(DS5-DR5) -> 534.18895 | DV10: 3.2471111 | DW10: =DV10+(DO8-DN8) -> 3.4549496 | DX10: ='OBR RR Oct23 - Debt interest'!J17*(DW10-DV10)+'OBR RR Oct23 - Debt interest'!H17*(DW9-DV9) -> 1496.5704 | DZ10: =DX10+DT10 -> 2030.7594
A11: Check | B11: =OBR_MAR24_T4.12!D9 -> -9.8249571 | C11: =OBR_MAR24_T4.12!E9 -> 2.6562558 | D11: =OBR_MAR24_T4.12!F9 -> 0.64667534 | E11: =OBR_MAR24_T4.12!G9 -> 0.2550542 | F11: =OBR_MAR24_T4.12!H9 -> 1.5035416 | G11: =OBR_MAR24_T4.12!I9 -> 4.4307623 | R11: 2026-27 | S11: =100*(AG11/AG$9) -> 102.23065 | T11: =100*(AH11/AH$9) -> 101.08757 | U11: =100*(AI11/AI$9) -> 100.97993 | V11: =100*(AJ11/AJ$9) -> 100.1588 | W11: =100*(AK11/AK$9) -> 100.59628 | X11: 100 | Z11: =100*(AM11/AM$9) -> 102.96029 | AA11: =100*(AN11/AN$9) -> 98.290207 | AB11: =100*(AO11/AO$9) -> 97.156218 | AC11: =100*(AP11/AP$9) -> 93.829829 | AD11: =100*(AQ11/AQ$9) -> 94.862307 | AE11: 100 | AG11: =100*(AS11/CU11) -> 6.0570831 | AH11: =100*(AT11/CV11) -> 6.0627513 | AI11: =100*(AU11/CW11) -> 6.1079084 | AJ11: =100*(AV11/CX11) -> 6.1768118 | AK11: =100*(AW11/CY11) -> 6.1824787 | AM11: =100*(AY11/CU11) -> 1.3807914 | AN11: =100*(AZ11/CV11) -> 1.3231855 | AO11: =100*(BA11/CW11) -> 1.3345172 | AP11: =100*(BB11/CX11) -> 1.3181695 | AQ11: =100*(BC11/CY11) -> 1.3443751 | AS11: =CI11/($BF11/1000) -> 6.4156649 | AT11: =CJ11/($BF11/1000) -> 6.2504132 | AU11: =CK11/($BF11/1000) -> 6.3385519 | AV11: =CL11/($BF11/1000) -> 6.4915223 | AW11: =CM11/($BF11/1000) -> 6.4256475 | AY11: =CO11/($BF11/1000) -> 1.4625348 | AZ11: =CP11/($BF11/1000) -> 1.3641424 | BA11: =CQ11/($BF11/1000) -> 1.3849105 | BB11: =CR11/($BF11/1000) -> 1.3853307 | BC11: =CS11/($BF11/1000) -> 1.397252 | BE11: =+BE10+100 -> 202701 | BF11: =VLOOKUP(BE11,Data!$A$7:$C$318,3,FALSE) -> 70386.82 | BH11: 2026-27 | BI11: =100*(BW11/BW$9) -> 103.61298 | BJ11: =100*(BX11/BX$9) -> 102.45445 | BK11: =100*(BY11/BY$9) -> 102.34535 | BL11: =100*(BZ11/BZ$9) -> 101.51312 | BM11: =100*(CA11/CA$9) -> 101.95651 | BN11: 100 | BP11: =100*(CC11/CC$9) -> 104.35249 | BQ11: =100*(CD11/CD$9) -> 99.619255 | BR11: =100*(CE11/CE$9) -> 98.469932 | BS11: =100*(CF11/CF$9) -> 95.098565 | BT11: =100*(CG11/CG$9) -> 96.145004 | BU11: 100 | BW11: =100*(CI11/CU11) -> 426.33882 | BX11: =100*(CJ11/CV11) -> 426.73778 | BY11: =100*(CK11/CW11) -> 429.91625 | BZ11: =100*(CL11/CX11) -> 434.76614 | CA11: =100*(CM11/CY11) -> 435.16502 | CC11: =100*(CO11/CU11) -> 97.189513 | CD11: =100*(CP11/CV11) -> 93.13482 | CE11: =100*(CQ11/CW11) -> 93.932423 | CF11: =100*(CR11/CX11) -> 92.78176 | CG11: =100*(CS11/CY11) -> 94.62629 | CI11: 451.57825 | CJ11: 439.94671 | CK11: 446.15051 | CL11: 456.91761 | CM11: 452.28089 | CO11: 102.94317 | CP11: 96.017646 | CQ11: 97.479447 | CR11: 97.50902 | CS11: 98.348124 | CU11: =100*(DA11/DA$8) -> 105.92004 | CV11: =100*(DB11/DB$8) -> 103.09533 | CW11: =100*(DC11/DC$8) -> 103.77614 | CX11: =100*(DD11/DD$8) -> 105.09503 | CY11: =100*(DE11/DE$8) -> 103.93319 | DA11: =OBR_MAR22_1.2!X119 -> 119.12452 | DB11: =OBR_NOV22_1.2!X124 -> 119.24482 | DC11: =OBR_MAR23_1.2!X124 -> 119.67032 | DD11: =OBR_NOV23_1.2!X129 -> 125.33789 | DE11: =OBR_MAR24_1.2!X129 -> 124.62088 | DG11: Av | DH11: =AVERAGE(DH4:DH9) -> 4.7581818 | DI11: =AVERAGE(DI4:DI9) -> 4.1828788 | DJ11: =AVERAGE(DJ4:DJ9) -> 4.3525 | DM11: =AVERAGE(DM4:DM9) -> 4.3918051 | DN11: =AVERAGE(DN4:DN9) -> 3.4175929 | DO11: =AVERAGE(DO4:DO9) -> 3.7869341
R12: 2027-28 | T12: =100*(AH12/AH$9) -> 101.69253 | U12: =100*(AI12/AI$9) -> 101.69878 | V12: =100*(AJ12/AJ$9) -> 100.73998 | W12: =100*(AK12/AK$9) -> 101.16569 | X12: 100 | AA12: =100*(AN12/AN$9) -> 96.280174 | AB12: =100*(AO12/AO$9) -> 95.270105 | AC12: =100*(AP12/AP$9) -> 91.841724 | AD12: =100*(AQ12/AQ$9) -> 92.670727 | AE12: 100 | AH12: =100*(AT12/CV12) -> 6.0990339 | AI12: =100*(AU12/CW12) -> 6.1513887 | AJ12: =100*(AV12/CX12) -> 6.2126532 | AK12: =100*(AW12/CY12) -> 6.2174741 | AN12: =100*(AZ12/CV12) -> 1.2961264 | AO12: =100*(BA12/CW12) -> 1.30861 | AP12: =100*(BB12/CX12) -> 1.2902396 | AQ12: =100*(BC12/CY12) -> 1.3133164 | AT12: =CJ12/($BF12/1000) -> 6.4007685 | AU12: =CK12/($BF12/1000) -> 6.4891469 | AV12: =CL12/($BF12/1000) -> 6.6450309 | AW12: =CM12/($BF12/1000) -> 6.5830388 | AZ12: =CP12/($BF12/1000) -> 1.360249 | BA12: =CQ12/($BF12/1000) -> 1.3804626 | BB12: =CR12/($BF12/1000) -> 1.3800355 | BC12: =CS12/($BF12/1000) -> 1.3905346 | BE12: =+BE11+100 -> 202801 | BF12: =VLOOKUP(BE12,Data!$A$7:$C$318,3,FALSE) -> 70720.8 | BH12: 2027-28 | BJ12: =100*(BX12/BX$9) -> 103.55663 | BK12: =100*(BY12/BY$9) -> 103.56299 | BL12: =100*(BZ12/BZ$9) -> 102.58662 | BM12: =100*(CA12/CA$9) -> 103.02014 | BN12: 100 | BQ12: =100*(CD12/CD$9) -> 98.045062 | BR12: =100*(CE12/CE$9) -> 97.016478 | BS12: =100*(CF12/CF$9) -> 93.525252 | BT12: =100*(CG12/CG$9) -> 94.369451 | BU12: 100 | BX12: =100*(CJ12/CV12) -> 431.32856 | BY12: =100*(CK12/CW12) -> 435.03113 | BZ12: =100*(CL12/CX12) -> 439.3638 | CA12: =100*(CM12/CY12) -> 439.70474 | CD12: =100*(CP12/CV12) -> 91.663094 | CE12: =100*(CQ12/CW12) -> 92.545944 | CF12: =100*(CR12/CX12) -> 91.246777 | CG12: =100*(CS12/CY12) -> 92.878783 | CJ12: 452.66747 | CK12: 458.91766 | CL12: 469.9419 | CM12: 465.55777 | CP12: 96.197899 | CQ12: 97.627423 | CR12: 97.597216 | CS12: 98.339717 | CV12: =100*(DB12/DB$8) -> 104.94725 | CW12: =100*(DC12/DC$8) -> 105.49076 | CX12: =100*(DD12/DD$8) -> 106.95963 | CY12: =100*(DE12/DE$8) -> 105.87963 | DB12: =OBR_NOV22_1.2!X125 -> 121.38684 | DC12: =OBR_MAR23_1.2!X125 -> 121.64755 | DD12: =OBR_NOV23_1.2!X130 -> 127.56164 | DE12: =OBR_MAR24_1.2!X130 -> 126.95476 | DG12: Diff | DI12: =DI11-$DH$11 -> -0.57530303 | DJ12: =DJ11-$DH$11 -> -0.40568182 | DN12: =DN11-$DM$11 -> -0.97421222 | DO12: =DO11-$DM$11 -> -0.60487104
R13: 2028-29 | V13: =100*(AJ13/AJ$9) -> 101.32775 | W13: =100*(AK13/AK$9) -> 101.70919 | X13: 100 | AC13: =100*(AP13/AP$9) -> 89.539507 | AD13: =100*(AQ13/AQ$9) -> 89.620305 | AE13: 100 | AJ13: =100*(AV13/CX13) -> 6.248901 | AK13: =100*(AW13/CY13) -> 6.2508762 | AP13: =100*(BB13/CX13) -> 1.2578969 | AQ13: =100*(BC13/CY13) -> 1.2700862 | AV13: =CL13/($BF13/1000) -> 6.8095063 | AW13: =CM13/($BF13/1000) -> 6.7463195 | BB13: =CR13/($BF13/1000) -> 1.3707461 | BC13: =CS13/($BF13/1000) -> 1.370753 | BE13: =+BE12+100 -> 202901 | BF13: =VLOOKUP(BE13,Data!$A$7:$C$318,3,FALSE) -> 71025.23 | BH13: 2028-29 | BL13: =100*(BZ13/BZ$9) -> 103.62934 | BM13: =100*(CA13/CA$9) -> 104.01944 | BN13: 100 | BS13: =100*(CF13/CF$9) -> 91.573337 | BT13: =100*(CG13/CG$9) -> 91.65597 | BU13: 100 | BZ13: =100*(CL13/CX13) -> 443.82963 | CA13: =100*(CM13/CY13) -> 443.96992 | CF13: =100*(CR13/CX13) -> 89.342414 | CG13: =100*(CS13/CY13) -> 90.208165 | CL13: 483.64675 | CM13: 479.15889 | CR13: 97.357557 | CS13: 97.358047 | CX13: =100*(DD13/DD$8) -> 108.97126 | CY13: =100*(DE13/DE$8) -> 107.92598 | DD13: =OBR_NOV23_1.2!X131 -> 129.96074 | DE13: =OBR_MAR24_1.2!X131 -> 129.40843 | DJ13: =-DI12+DJ12 -> 0.16962121 | DO13: =-DN12+DO12 -> 0.36934118

Sheet OBR_MAR24_C1.5
A1: Back to contents
B2: Chart 1.5: Public sector net borrowing: change since November
C25: 2023-24 | D25: 2024-25 | E25: 2025-26 | F25: 2026-27 | G25: 2027-28 | H25: 2028-29
B26: Effects of policy | C26: 0.32316634 | D26: 12.668357 | E26: 10.36852 | F26: 6.4263462 | G26: 5.1195595 | H26: 5.2043361
B27: Receipts | C27: 0.78696365 | D27: 5.2325724 | E27: 8.7181301 | F27: 10.354385 | G27: 12.288382 | H27: 14.770554
B28: Other spending | C28: 0.060529746 | D28: 2.2845351 | E28: 0.80306501 | F28: 0.63733687 | G28: -0.020847638 | H28: 0.19608465
B29: Debt interest spending | C29: -11.477824 | D29: -16.173451 | E29: -14.680019 | F29: -13.834613 | G29: -13.306391 | H29: -14.193449
B30: Welfare spending | C30: 0.48220721 | D30: -1.3557579 | E30: -4.5630214 | F30: -3.3284018 | G30: -2.5771608 | H30: -1.5467628
B31: Change in post-measures borrowing | C31: -9.8249571 | D31: 2.6562558 | E31: 0.64667534 | F31: 0.2550542 | G31: 1.5035416 | H31: 4.4307623
B32: Change in pre-measures borrowing | C32: -10.148123 | D32: -10.012101 | E32: -9.721845 | F32: -6.171292 | G32: -3.6160179 | H32: -0.77357379

Sheet OBR_MAR24_T3.8
A1: Back to contents
B2: Table 3.8: Latest costings of personal tax measures
C4: £ billion
C5: Forecast
C6: 2022-23 | D6: 2023-24 | E6: 2024-25 | F6: 2025-26 | G6: 2026-27 | H6: 2027-28 | I6: 2028-29
B7: Changes to thresholds
B8: PA and HRT freezes | C8: -2.91 | D8: -13.545 | E8: -23.23 | F8: -27.045 | G8: -29.36 | H8: -32.265 | I8: -33.61
B9: Additional rate threshold: reduction | C9: -0.08 | D9: -0.445 | E9: -0.815 | F9: -0.815 | G9: -0.845 | H9: -0.895 | I9: -0.945
B10: NICs: rise in primary threshold | C10: 6.645 | D10: 5.365 | E10: 2.98 | F10: 2.31 | G10: 2.42 | H10: 2.47 | I10: 2.49
B11: Class 2 NICs: threshold rise | C11: 0.075 | D11: 0.085 | E11: 0.075 | F11: 0.07 | G11: 0.075 | H11: 0.085 | I11: 0.085
B12: Class 1 NICs: threshold freezes | C12: 0 | D12: -3.33 | E12: -5.715 | F12: -6.485 | G12: -7.64 | H12: -8.895 | I12: -9.145
B13: Total | C13: 3.73 | D13: -11.87 | E13: -26.705 | F13: -31.965 | G13: -35.35 | H13: -39.5 | I13: -41.125
B14: Rate cuts
B15: Autumn Statement 2023 NICs | C15: 0 | D15: 2.3828955 | E15: 9.9944842 | F15: 10.141012 | G15: 10.17163 | H15: 10.385803 | I15: 10.66816
B16: Budget 2024 measures | C16: 0 | D16: 0 | E16: 10.070957 | F16: 10.145467 | G16: 10.226379 | H16: 10.44633 | I16: 10.749149
B17: Total | C17: 0 | D17: 2.3828955 | E17: 20.065441 | F17: 20.286479 | G17: 20.398009 | H17: 20.832133 | I17: 21.417308

Sheet OBR_MAR24_T4.12
A1: Back to contents
B2: Table 4.12: Public sector net borrowing: changes since November 2023
C4: £ billion
C5: Outturn | D5: Forecast | E5: 0 | F5: 0 | G5: 0 | H5: 0 | I5: 0
C6: 2022-23 | D6: 2023-24 | E6: 2024-25 | F6: 2025-26 | G6: 2026-27 | H6: 2027-28 | I6: 2028-29
B7: November 2023 forecast | C7: 128.266 | D7: 123.90988 | E7: 84.570326 | F7: 76.83564 | G7: 68.405587 | H7: 49.05861 | I7: 35.003998
B8: March 2024 forecast | C8: 128.682 | D8: 114.08493 | E8: 87.226582 | F8: 77.482315 | G8: 68.660641 | H8: 50.562152 | I8: 39.43476
B9: Difference | C9: 0.416 | D9: -9.8249571 | E9: 2.6562558 | F9: 0.64667534 | G9: 0.2550542 | H9: 1.5035416 | I9: 4.4307623
B10: of which:
B11: Underlying differences | D11: -10.148123 | E11: -10.012101 | F11: -9.721845 | G11: -6.171292 | H11: -3.6160179 | I11: -0.77357379
B12: of which:
B13: Receipts | D13: 0.78696365 | E13: 5.2325724 | F13: 8.7181301 | G13: 10.354385 | H13: 12.288382 | I13: 14.770554
B14: Spending | D14: -10.935087 | E14: -15.244674 | F14: -18.439975 | G14: -16.525677 | H14: -15.9044 | I14: -15.544128
B15: of which:
B16: Debt interest spending | D16: -11.477824 | E16: -16.173451 | F16: -14.680019 | G16: -13.834613 | H16: -13.306391 | I16: -14.193449
B17: Welfare spending | D17: 0.48220721 | E17: -1.3557579 | F17: -4.5630214 | G17: -3.3284018 | H17: -2.5771608 | I17: -1.5467628
B18: Other spending | D18: 0.060529746 | E18: 2.2845351 | F18: 0.80306501 | G18: 0.63733687 | H18: -0.020847638 | I18: 0.19608465
B19: Direct effect of policy decisions | D19: 0.057872132 | E19: 13.899537 | F19: 10.116299 | G19: 7.6829941 | H19: 6.3384618 | I19: 5.9370328
B20: of which:
B21: National insurance contributions cut | D21: 0 | E21: 10.196025 | F21: 10.329817 | G21: 10.465234 | H21: 10.705217 | I21: 11.037294
B22: Reform of non-domicile regime | D22: 0 | E22: 0 | F22: -0.186 | G22: -2.733 | H22: -3.557 | I22: -2.643
B23: Other receipts decisions | D23: 0.18808678 | E23: 3.3254114 | F23: 0.10133373 | G23: -0.52055575 | H23: -1.5678695 | I23: -2.4749031
B24: Spending decisions | D24: -0.13021465 | E24: 0.3781002 | F24: -0.1288523 | G24: 0.47131558 | H24: 0.7581139 | I24: 0.017641508
B25: Indirect effect of decisions | D25: 0.26529421 | E25: -1.2311794 | F25: 0.25222169 | G25: -1.2566479 | H25: -1.2189023 | I25: -0.73269675
B26: of which:
B27: Debt interest spending | D27: 0.0038115824 | E27: -1.0457675 | F27: 1.6753159 | G27: 1.1899314 | H27: 1.1847893 | I27: 1.3482743
B28: Other economic effects | D28: 0.26148263 | E28: -0.1854119 | F28: -1.4230943 | G28: -2.4465793 | H28: -2.4036915 | I28: -2.0809711
B29: Note: This table uses the convention that a negative figure means a reduction in PSNB i.e. an increase in receipts or a reduction in spending will have a negative effect on PSNB. It does not include the effects of changes in our underlying forecasts for most environmental levies, VAT refunds or depreciation, as each change both receipts and spending by equal amounts and therefore do not change borrowing.

Sheet OBR_MAR24_TA.7
A1: Back to contents
B2: Table A.7: Total managed expenditure
C4: £ billion
C5: Outturn | D5: Forecast
C6: 2022-23 | D6: 2023-24 | E6: 2024-25 | F6: 2025-26 | G6: 2026-27 | H6: 2027-28 | I6: 2028-29
B7: Public sector current expenditure (PSCE)
B8: PSCE in RDEL | C8: 407.4577 | D8: 422.94449 | E8: 430.19538 | F8: 440.03535 | G8: 452.28089 | H8: 465.55777 | I8: 479.15889
B9: PSCE in AME | C9: 643.6143 | D9: 659.96315 | E9: 660.1941 | F9: 679.56195 | G9: 705.7294 | H9: 725.75804 | I9: 751.95568
B10: of which:
B11: Welfare spending | C11: 261.4874 | D11: 295.84845 | E11: 315.14089 | F11: 329.00886 | G11: 339.72754 | H11: 348.2333 | I11: 360.06887
B12: Locally financed current expenditure | C12: 60.137438 | D12: 62.063371 | E12: 64.070522 | F12: 66.14117 | G12: 69.311315 | H12: 72.175566 | I12: 75.387203
B13: Central government debt interest, net of APF1 | C13: 111.481 | D13: 104.74828 | E13: 88.955775 | F13: 88.888563 | G13: 96.20421 | H13: 103.044 | I13: 109.63575
B14: Scottish Government's current spending | C14: 39.586038 | D14: 42.618447 | E14: 44.427363 | F14: 45.138799 | G14: 46.302917 | H14: 47.157818 | I14: 49.134058
B15: EU financial settlement | C15: 8.8096667 | D15: 7.7514634 | E15: 1.135536 | F15: 1.0637573 | G15: 0.5381457 | H15: 0.18596545 | I15: 0.52161233
B16: Unfunded public service pensions | C16: 3.5806935 | D16: 4.5721668 | E16: 3.4392333 | F16: 4.1530844 | G16: 3.100412 | H16: 2.231031 | I16: 0.64376789
B17: Company and other tax credits | C17: 9.2172361 | D17: 9.3808388 | E17: 9.6580323 | F17: 10.166965 | G17: 10.582 | H17: 10.989011 | I17: 11.355334
B18: BBC current expenditure | C18: 4.2246768 | D18: 4.1788233 | E18: 4.3327533 | F18: 4.1190666 | G18: 4.270332 | H18: 4.355332 | I18: 4.4052235
B19: National Lottery current grants | C19: 1.28536 | D19: 1.2437495 | E19: 1.414753 | F19: 1.4105405 | G19: 1.318127 | H19: 1.2435335 | I19: 1.2428825
B20: General government imputed pensions | C20: 3.3853899 | D20: 1.6987073 | E20: 1.7594719 | F20: 1.8057996 | G20: 1.85605 | H20: 1.9100249 | I20: 1.9688475
B21: Public corporations' debt interest | C21: 0.544 | D21: 0.54 | E21: 0.54 | F21: 0.54 | G21: 0.54 | H21: 0.54 | I21: 0.54
B22: Non-domestic energy support | C22: 7.48 | D22: 0.621 | E22: 0 | F22: 0 | G22: 0 | H22: 0 | I22: 0
... B30: Total public sector current expenditure | C30: 1051.072 | D30: 1082.9076 | E30: 1090.3895 | F30: 1119.5973 | G30: 1158.0103 | H30: 1191.3158 | I30: 1231.1146
B31: Public sector gross investment (PSGI)
B32: PSGI in CDEL | C32: 89.791733 | D32: 95.583786 | E32: 99.20003 | F32: 98.062828 | G32: 98.348124 | H32: 98.339717 | I32: 97.358047
B33: PSGI in AME | C33: 16.548267 | D33: 37.78248 | E33: 36.758702 | F33: 33.997042 | G33: 33.894631 | H33: 33.406167 | I33: 33.203153
B34: of which:
B35: Locally financed capital expenditure | C35: 10.835605 | D35: 8.8351359 | E35: 8.2751924 | F35: 7.5499586 | G35: 8.1494607 | H35: 8.1407231 | I35: 8.2007894
B36: Public corporations' capital expenditure | C36: 11.556757 | D36: 11.199767 | E36: 11.740905 | F36: 11.617591 | G36: 11.610803 | H36: 11.667161 | I36: 11.740328
B37: Student loans | C37: 0.488 | D37: 9.8426785 | E37: 8.9549482 | F37: 8.1280841 | G37: 7.5164923 | H37: 7.2257973 | I37: 7.0930287
B38: Funded public sector pension schemes | C38: -4.854 | D38: 0.71152891 | E38: 0.71152891 | F38: 0.71152891 | G38: 0.71152891 | H38: 0.71152891 | I38: 0.71152891
B39: Scottish Government's capital spending | C39: 4.569481 | D39: 5.6714916 | E39: 5.4709199 | F39: 5.2342224 | G39: 5.2275066 | H39: 5.2113555 | I39: 5.1460268
B40: Tax litigation | C40: 0 | D40: 0.8235 | E40: 1.203396 | F40: 0.63406325 | G40: 0.63406325 | H40: 0.63406325 | I40: 0.63406325
B41: Other PSGI items in AME | C41: 0.38561146 | D41: 1.2091956 | E41: 0.89061083 | F41: 0.81662252 | G41: 0.72455505 | H41: 0.56602273 | I41: 0.52125924
B42: Other National Accounts adjustments | C42: -6.4331875 | D42: -0.5108177 | E42: -0.48879946 | F42: -0.69502831 | G42: -0.6797789 | H42: -0.75048428 | I42: -0.84387143
B43: Total public sector gross investment | C43: 106.34 | D43: 133.36627 | E43: 135.95873 | F43: 132.05987 | G43: 132.24276 | H43: 131.74588 | I43: 130.5612
B44: Less public sector depreciation | C44: -60.341 | D44: -66.227455 | E44: -69.392239 | F44: -71.109614 | G44: -73.128371 | H44: -75.412565 | I44: -77.50292
B45: Public sector net investment | C45: 45.999 | D45: 67.138811 | E45: 66.566493 | F45: 60.950257 | G45: 59.114384 | H45: 56.333319 | I45: 53.05828
B46: Total managed expenditure | C46: 1157.412 | D46: 1216.2739 | E46: 1226.3482 | F46: 1251.6572 | G46: 1290.253 | H46: 1323.0617 | I46: 1361.6758
B47: 1 Includes increases in debt interest payments due to the APF.

Sheet OBR_MAR24_C4.10
A1: Back to contents
B2: Chart 4.10: Real departmental spending per person (2023-24 prices)
C25: 2021-22 | D25: 2022-23 | E25: 2023-24 | F25: 2024-25 | G25: 2025-26 | H25: 2026-27 | I25: 2027-28 | J25: 2028-29
B26: Initial October 2021 SR plans | C26: 8058.0943 | D26: 7886.165 | E26: 7924.843 | F26: 7936.6873 | G26: 8093.8952 | H26: 8213.0077
B27: Effect of policy since October 2021 | C27: 8096.5237 | D27: 8161.9941 | E27: 8294.4252 | F27: 8283.4996 | G27: 8231.465 | H27: 8230.5647
B28: Effect of policy and higher inflation since October 2021 | C28: 8096.5237 | D28: 7848.2929 | E28: 7650.2726 | F28: 7722.1683 | G28: 7722.1878 | H28: 7745.8693
B29: Effect of policy, hihger inflation and population since October 2021 (March 2024 forecast) | C29: 8088.1605 | D29: 7786.1672 | E29: 7547.7841 | F29: 7583.7687 | G29: 7563.5996 | H29: 7568.7853 | I29: 7569.1965 | J29: 7552.703

Sheet OBR_MAR24_1.1
A1: Back to contents
B2: 1.1 GDP expenditure components (£ billion chain-linked volumes, seasonally adjusted)
C3: Private consumption | D3: Government consumption | E3: Fixed investment | J3: Net acquisition of valuables | K3: Final domestic demand | L3: Change in inventories | M3: Total domestic demand | N3: Exports | O3: Total final expenditure | P3: Imports | Q3: Statistical discrepancy | R3: Real GDP | S3: Non-oil GVA
E4: of which: | F4: Business investment | G4: Private dwellings | H4: General government | I4: Public corps dwellings
B5: 2008Q1 | C5: 308.104 | D5: 93.323 | E5: 84.847 | F5: 45.209 | G5: 24.954 | H5: 13.732 | I5: 1.494 | J5: 0.253 | K5: 486.527 | L5: -2.688 | M5: 483.839 | N5: 140.286 | O5: 626.489 | P5: 137.103 | Q5: 0 | R5: 489.783 | S5: 426.405
B6: 2008Q2 | C6: 304.494 | D6: 92.738 | E6: 85.799 | F6: 46.925 | G6: 23.782 | H6: 14.129 | I6: 1.45 | J6: -0.422 | K6: 482.609 | L6: -1.231 | M6: 481.378 | N6: 140.305 | O6: 623.241 | P6: 136.253 | Q6: 0 | R6: 487.386 | S6: 424.841
B7: 2008Q3 | C7: 299.633 | D7: 94.397 | E7: 81.323 | F7: 45.148 | G7: 19.58 | H7: 14.145 | I7: 2.775 | J7: -0.984 | K7: 474.369 | L7: -3.213 | M7: 471.156 | N7: 140.846 | O7: 613.272 | P7: 133.811 | Q7: 0 | R7: 479.872 | S7: 418.251
B8: 2008Q4 | C8: 292.373 | D8: 95.402 | E8: 79.978 | F8: 43.617 | G8: 18.727 | H8: 15.192 | I8: 2.722 | J8: 0.11 | K8: 467.863 | L8: -5.656 | M8: 462.207 | N8: 135.424 | O8: 596.031 | P8: 126.724 | Q8: 0 | R8: 469.694 | S8: 409.321
B9: 2009Q1 | C9: 291.284 | D9: 94.802 | E9: 75.261 | F9: 39.697 | G9: 17.619 | H9: 15.489 | I9: 2.681 | J9: 1.308 | K9: 462.655 | L9: -9.394 | M9: 453.261 | N9: 126.723 | O9: 581.258 | P9: 121.718 | Q9: 0 | R9: 460.105 | S9: 401.251
B10: 2009Q2 | C10: 291.11 | D10: 94.564 | E10: 72.063 | F10: 37.614 | G10: 17.124 | H10: 14.824 | I10: 2.644 | J10: 0.617 | K10: 458.354 | L10: -8.962 | M10: 449.392 | N10: 125.42 | O10: 580.028 | P10: 122.009 | Q10: 0 | R10: 458.599 | S10: 399.499
B11: 2009Q3 | C11: 292.732 | D11: 95.362 | E11: 72.551 | F11: 36.801 | G11: 17.177 | H11: 16.069 | I11: 2.675 | J11: 1.036 | K11: 461.681 | L11: -9.269 | M11: 452.412 | N11: 124.828 | O11: 583.709 | P11: 125.311 | Q11: 0 | R11: 458.875 | S11: 400.202
B12: 2009Q4 | C12: 294.909 | D12: 96.11 | E12: 71.335 | F12: 36.482 | G12: 16.394 | H12: 15.851 | I12: 2.728 | J12: -0.228 | K12: 462.126 | L12: -7.406 | M12: 454.72 | N12: 130.663 | O12: 587.166 | P12: 127.35 | Q12: 0 | R12: 460.238 | S12: 401.681
B13: 2010Q1 | C13: 293.465 | D13: 94.805 | E13: 75.138 | F13: 38.204 | G13: 17.617 | H13: 16.792 | I13: 2.709 | J13: -0.366 | K13: 463.042 | L13: -2.196 | M13: 460.846 | N13: 130.582 | O13: 593.834 | P13: 129.677 | Q13: 0 | R13: 464.543 | S13: 405.884
B14: 2010Q2 | C14: 300.592 | D14: 95.123 | E14: 74.022 | F14: 37.63 | G14: 18.596 | H14: 15.355 | I14: 2.698 | J14: -0.577 | K14: 469.16 | L14: -1.663 | M14: 467.497 | N14: 134.894 | O14: 603.085 | P14: 133.785 | Q14: 0 | R14: 469.606 | S14: 410.793
B15: 2010Q3 | C15: 300.841 | D15: 95.137 | E15: 76.899 | F15: 39.313 | G15: 19.56 | H15: 15.628 | I15: 2.678 | J15: 0.524 | K15: 473.401 | L15: -0.658 | M15: 472.743 | N15: 136.309 | O15: 610.106 | P15: 138.104 | Q15: 0 | R15: 472.199 | S15: 413.478
B16: 2010Q4 | C16: 300.342 | D16: 95.696 | E16: 78.973 | F16: 41.914 | G16: 19.064 | H16: 15.547 | I16: 2.618 | J16: 0.418 | K16: 475.429 | L16: -4.046 | M16: 471.383 | N16: 139.076 | O16: 611.773 | P16: 139.318 | Q16: 0 | R16: 472.612 | S16: 414.371
... B89: 2029Q1 | C89: 386.99075 | D89: 130.50646 | E89: 108.5662 | F89: 61.292345 | G89: 28.99537 | H89: 16.60913 | I89: 1.6693576 | J89: -1.2825 | K89: 624.78092 | L89: 0.76566173 | M89: 625.54658 | N89: 181.1219 | O89: 806.66848 | P89: 187.91993 | Q89: 4.757 | R89: 623.50554 | S89: 554.78657
B90: 2008 | C90: 1204.604 | D90: 375.86 | E90: 331.947 | F90: 180.899 | G90: 87.043 | H90: 57.198 | I90: 8.441 | J90: -1.043 | K90: 1911.368 | L90: -12.788 | M90: 1898.58 | N90: 556.861 | O90: 2459.033 | P90: 533.891 | Q90: 0 | R90: 1926.735 | S90: 1678.818
B91: 2009 | C91: 1170.035 | D91: 380.838 | E91: 291.21 | F91: 150.594 | G91: 68.314 | H91: 62.233 | I91: 10.728 | J91: 2.733 | K91: 1844.816 | L91: -35.031 | M91: 1809.785 | N91: 507.634 | O91: 2332.161 | P91: 496.388 | Q91: 0 | R91: 1837.817 | S91: 1602.633
B92: 2010 | C92: 1195.24 | D92: 380.761 | E92: 305.032 | F92: 157.061 | G92: 74.837 | H92: 63.322 | I92: 10.703 | J92: -0.001 | K92: 1881.032 | L92: -8.563 | M92: 1872.469 | N92: 540.861 | O92: 2418.798 | P92: 540.884 | Q92: 0 | R92: 1878.96 | S92: 1644.526
B93: 2011 | C93: 1191.27 | D93: 380.515 | E93: 305.354 | F93: 166.465 | G93: 71.386 | H93: 57.955 | I93: 9.969 | J93: -0.705 | K93: 1876.434 | L93: -3.784 | M93: 1872.65 | N93: 578.333 | O93: 2456.555 | P93: 556.723 | Q93: 0 | R93: 1900.476 | S93: 1672.213
B94: 2012 | C94: 1211.807 | D94: 386.188 | E94: 310.222 | F94: 178.179 | G94: 69.926 | H94: 53.007 | I94: 9.042 | J94: -1.036 | K94: 1907.181 | L94: 6.378 | M94: 1913.559 | N94: 582.729 | O94: 2499.35 | P94: 570.385 | Q94: 0 | R94: 1929.229 | S94: 1706.911
B95: 2013 | C95: 1242.448 | D95: 387.05 | E95: 320.303 | F95: 184.651 | G95: 77.388 | H95: 49.603 | I95: 8.512 | J95: 7.022 | K95: 1956.823 | L95: 6.784 | M95: 1963.607 | N95: 584.387 | O95: 2552.855 | P95: 588.884 | Q95: 0 | R95: 1963.807 | S95: 1740.343
B96: 2014 | C96: 1276.097 | D96: 397.069 | E96: 342.84 | F96: 194.883 | G96: 82.424 | H96: 55.58 | I96: 9.862 | J96: 6.071 | K96: 2022.077 | L96: 15.349 | M96: 2037.426 | N96: 590.26 | O96: 2646.112 | P96: 618.888 | Q96: 0 | R96: 2026.566 | S96: 1797.211
B97: 2015 | C97: 1312.213 | D97: 402.148 | E97: 367.34 | F97: 213.281 | G97: 87.743 | H97: 56.548 | I97: 9.646 | J97: 0.393 | K97: 2082.094 | L97: 12.105 | M97: 2094.199 | N97: 612.533 | O97: 2721.787 | P97: 649.558 | Q97: 0 | R97: 2071.561 | S97: 1831.364
B98: 2016 | C98: 1360.504 | D98: 404.984 | E98: 386.225 | F98: 227.965 | G98: 93.928 | H98: 54.579 | I98: 9.742 | J98: 1.599 | K98: 2153.312 | L98: 5.036 | M98: 2158.348 | N98: 629.527 | O98: 2786.771 | P98: 675.388 | Q98: 0 | R98: 2111.357 | S98: 1867.008
B99: 2017 | C99: 1385.378 | D99: 407.632 | E99: 399.752 | F99: 227.445 | G99: 102.153 | H99: 60.512 | I99: 9.612 | J99: 0.606 | K99: 2193.368 | L99: 13.307 | M99: 2206.675 | N99: 672.118 | O99: 2864.105 | P99: 696.761 | Q99: 0 | R99: 2167.415 | S99: 1919.054
B100: 2018 | C100: 1412.6 | D100: 410.171 | E100: 397.838 | F100: 223.77 | G100: 108.26 | H100: 60.511 | I100: 5.347 | J100: 3.137 | K100: 2223.746 | L100: 0.941 | M100: 2224.687 | N100: 692.86 | O100: 2916.14 | P100: 718.347 | Q100: 0 | R100: 2197.841 | S100: 1943.493
B101: 2019 | C101: 1427.94 | D101: 426.592 | E101: 406.423 | F101: 228.581 | G101: 109.909 | H101: 62.14 | I101: 5.7435985 | J101: 2.88 | K101: 2263.835 | L101: 1.262 | M101: 2265.097 | N101: 706.696 | O101: 2971.793 | P101: 737.872 | Q101: 0 | R101: 2233.921 | S101: 1978.192
... B110: 2028 | C110: 1529.7754 | D110: 516.75272 | E110: 431.27728 | F110: 243.67744 | G110: 113.25735 | H110: 67.827732 | I110: 6.5147616 | J110: -5.13 | K110: 2472.6754 | L110: 2.5476196 | M110: 2475.223 | N110: 721.5985 | O110: 3196.8215 | P110: 747.55672 | Q110: 19.028 | R110: 2468.2928 | S110: 2195.7429
B111: 2008-09 | C111: 1187.784 | D111: 377.339 | E111: 322.361 | F111: 175.387 | G111: 79.708 | H111: 58.955 | I111: 9.628 | J111: 0.012 | K111: 1887.496 | L111: -19.494 | M111: 1868.002 | N111: 543.298 | O111: 2413.802 | P111: 518.506 | Q111: 0 | R111: 1897.057 | S111: 1653.664
B112: 2009-10 | C112: 1172.216 | D112: 380.841 | E112: 291.087 | F112: 149.101 | G112: 68.312 | H112: 63.536 | I112: 10.756 | J112: 1.059 | K112: 1845.203 | L112: -27.833 | M112: 1817.37 | N112: 511.493 | O112: 2344.737 | P112: 504.347 | Q112: 0 | R112: 1842.255 | S112: 1607.266
B113: 2010-11 | C113: 1199.499 | D113: 382.218 | E113: 305.816 | F113: 157.857 | G113: 75.328 | H113: 62.987 | I113: 10.618 | J113: -1.944 | K113: 1885.589 | L113: -8.626 | M113: 1876.963 | N113: 555.074 | O113: 2434.524 | P113: 547.238 | Q113: 0 | R113: 1888.236 | S113: 1654.774
B114: 2011-12 | C114: 1192.115 | D114: 382.481 | E114: 308.087 | F114: 172.739 | G114: 70.143 | H114: 55.594 | I114: 9.64 | J114: -0.36 | K114: 1882.323 | L114: -6.242 | M114: 1876.081 | N114: 583.603 | O114: 2469.395 | P114: 562.558 | Q114: 0 | R114: 1907.289 | S114: 1680.39
B115: 2012-13 | C115: 1219.509 | D115: 383.864 | E115: 308.262 | F115: 177.636 | G115: 71.051 | H115: 50.724 | I115: 8.845 | J115: 1.689 | K115: 1913.324 | L115: 12.249 | M115: 1925.573 | N115: 578.781 | O115: 2503.373 | P115: 569.73 | Q115: 0 | R115: 1934.006 | S115: 1713.037
B116: 2013-14 | C116: 1251.056 | D116: 389.959 | E116: 328.218 | F116: 187.917 | G116: 79.759 | H116: 51.897 | I116: 8.542 | J116: 7.843 | K116: 1977.076 | L116: 4.264 | M116: 1981.34 | N116: 582.917 | O116: 2576.023 | P116: 596.666 | Q116: 0 | R116: 1978.95 | S116: 1753.086
B117: 2014-15 | C117: 1286.09 | D117: 397.794 | E117: 349.357 | F117: 200.346 | G117: 82.466 | H117: 56.077 | I117: 10.342 | J117: 7.428 | K117: 2040.669 | L117: 21.859 | M117: 2062.528 | N117: 596.564 | O117: 2674.223 | P117: 633.483 | Q117: 0 | R117: 2039.864 | S117: 1809.444
B118: 2015-16 | C118: 1323.968 | D118: 403.76 | E118: 371.051 | F118: 216.768 | G118: 89.667 | H118: 55.113 | I118: 9.42 | J118: -1.311 | K118: 2097.468 | L118: 7.486 | M118: 2104.954 | N118: 616.107 | O118: 2733.568 | P118: 651.515 | Q118: 0 | R118: 2081.524 | S118: 1838.471
B119: 2016-17 | C119: 1368.575 | D119: 405.169 | E119: 390.464 | F119: 228.363 | G119: 96.898 | H119: 55.373 | I119: 9.834 | J119: -0.129 | K119: 2164.079 | L119: 9.618 | M119: 2173.697 | N119: 638.633 | O119: 2805.016 | P119: 680.972 | Q119: 0 | R119: 2124.11 | S119: 1879.97
B120: 2017-18 | C120: 1391.8 | D120: 408.182 | E120: 401.053 | F120: 226.789 | G120: 103.486 | H120: 62.242 | I120: 8.527 | J120: 1.596 | K120: 2202.631 | L120: 7.439 | M120: 2210.07 | N120: 680.185 | O120: 2880.648 | P120: 702.211 | Q120: 0 | R120: 2178.537 | S120: 1927.785
B121: 2018-19 | C121: 1418.455 | D121: 413.55 | E121: 399.565 | F121: 223.66 | G121: 109.414 | H121: 61.167 | I121: 5.3704693 | J121: 14.691 | K121: 2246.261 | L121: 8.426 | M121: 2254.687 | N121: 692.696 | O121: 2945.466 | P121: 740.157 | Q121: 0 | R121: 2205.294 | S121: 1950.519
B122: 2019-20 | C122: 1416.634 | D122: 424.902 | E122: 401.509 | F122: 227.994 | G122: 107.276 | H122: 60.56 | I122: 5.6087288 | J122: -8.545 | K122: 2234.5 | L122: -7.512 | M122: 2226.988 | N122: 705.479 | O122: 2933.523 | P122: 709.213 | Q122: 0 | R122: 2224.377 | S122: 1971.447
... B131: 2028-29 | C131: 1537.0274 | D131: 518.88095 | E131: 432.44724 | F131: 244.27561 | G131: 114.33206 | H131: 67.261722 | I131: 6.5778504 | J131: -5.13 | K131: 2483.2256 | L131: 2.6817125 | M131: 2485.9073 | N131: 722.77921 | O131: 3208.6865 | P131: 749.14675 | Q131: 19.028 | R131: 2478.5677 | S131: 2205.0915
B132: Definitions:
B133: Household and non-profit institutions serving households final consumption expenditure (ONS Economic Accounts Table 1.1.2, identifier: ABJR + HAYO)
B134: General government final consumption (ONS Economic Accounts Table 1.1.2, identifier: NMRY)
B135: Total gross fixed capital formation (ONS Economic Accounts Table 1.1.2, identifier: NPQT)
B136: Business investment (ONS Economic Accounts Table 1.1.8, identifier: NPEL)
B137: Private sector investment in dwellings, including transfer costs (ONS Economic Accounts Table 1.1.8, identifier: L636 + L637)
B138: General government gross fixed capital formation (ONS Economic Accounts Table 1.1.8, identifier: DLWF)
B139: Public corporations investment in dwellings, including transfer costs (ONS Economic Accounts Table 1.1.8, identifier: L634 + L635)
B140: Net acquisitions of valuables (ONS Economic Accounts Table 1.1.2, identifier: NPJR)
B141: Final domestic demand is the sum of private consumption, government consumption, fixed investment and net acquisition of valuables
B142: Change in inventories (ONS Economic Accounts Table 1.1.2, identifier: CAFU)
B143: Total domestic demand is the sum of final domestic demand and change in inventories
... B148: Gross domestic product at market prices (ONS Economic Accounts Table 1.1.2, identifier: ABMI)

Sheet OBR_MAR24_1.2
A1: Back to contents
B2: 1.2 GDP expenditure components (£ billion current prices, seasonally adjusted) | S2: Deflators
C3: Private consumption | D3: Government consumption | E3: Fixed investment | G3: Net acquisition of valuables | H3: Final domestic demand | I3: Change in inventories | J3: Total domestic demand | K3: Exports | L3: Total final expenditure | M3: Imports | N3: Statistical discrepancy | O3: GDP at market prices | P3: Gross national income | S3: C | T3: GC | U3: IF | V3: X | W3: M | X3: GDP | Z3: C | AA3: GC | AB3: IF | AC3: X | AD3: M | AE3: GDP
E4: of which: | F4: General government
B5: 2008Q1 | C5: 255.438 | D5: 80.007 | E5: 71.229 | F5: 12.058 | G5: 0.277 | H5: 406.951 | I5: -0.163 | J5: 406.788 | K5: 104.955 | L5: 511.743 | M5: 114.195 | N5: 0 | O5: 397.548 | P5: 396.936 | S5: =100*(C5/OBR_MAR24_1.1!C5) -> 82.906421 | T5: =100*(D5/OBR_MAR24_1.1!D5) -> 85.731277 | U5: =100*(E5/OBR_MAR24_1.1!E5) -> 83.949933 | V5: =100*(K5/OBR_MAR24_1.1!N5) -> 74.815021 | W5: =100*(M5/OBR_MAR24_1.1!P5) -> 83.291394 | X5: =100*(O5/OBR_MAR24_1.1!R5) -> 81.168191
B6: 2008Q2 | C6: 256.141 | D6: 80.199 | E6: 72.373 | F6: 11.633 | G6: -0.087 | H6: 408.626 | I6: 0.83 | J6: 409.456 | K6: 110.409 | L6: 519.865 | M6: 118.984 | N6: 0 | O6: 400.881 | P6: 396.091 | S6: =100*(C6/OBR_MAR24_1.1!C6) -> 84.120213 | T6: =100*(D6/OBR_MAR24_1.1!D6) -> 86.479113 | U6: =100*(E6/OBR_MAR24_1.1!E6) -> 84.351799 | V6: =100*(K6/OBR_MAR24_1.1!N6) -> 78.692135 | W6: =100*(M6/OBR_MAR24_1.1!P6) -> 87.325784 | X6: =100*(O6/OBR_MAR24_1.1!R6) -> 82.251234 | AA6: =100*((T6/T5)-1) -> 0.87230219
B7: 2008Q3 | C7: 255.819 | D7: 81.155 | E7: 69.19 | F7: 11.875 | G7: -0.658 | H7: 405.506 | I7: 0.855 | J7: 406.361 | K7: 113.34 | L7: 519.701 | M7: 119.731 | N7: 0 | O7: 399.97 | P7: 395.566 | S7: =100*(C7/OBR_MAR24_1.1!C7) -> 85.377445 | T7: =100*(D7/OBR_MAR24_1.1!D7) -> 85.972012 | U7: =100*(E7/OBR_MAR24_1.1!E7) -> 85.080482 | V7: =100*(K7/OBR_MAR24_1.1!N7) -> 80.470869 | W7: =100*(M7/OBR_MAR24_1.1!P7) -> 89.477696 | X7: =100*(O7/OBR_MAR24_1.1!R7) -> 83.34931 | AA7: =100*((T7/T6)-1) -> -0.58638596
B8: 2008Q4 | C8: 247.924 | D8: 83.414 | E8: 68.46 | F8: 12.733 | G8: 0.279 | H8: 400.077 | I8: -2.203 | J8: 397.874 | K8: 109.631 | L8: 507.505 | M8: 112.304 | N8: 0 | O8: 395.201 | P8: 383.976 | S8: =100*(C8/OBR_MAR24_1.1!C8) -> 84.79716 | T8: =100*(D8/OBR_MAR24_1.1!D8) -> 87.434226 | U8: =100*(E8/OBR_MAR24_1.1!E8) -> 85.59854 | V8: =100*(K8/OBR_MAR24_1.1!N8) -> 80.953893 | W8: =100*(M8/OBR_MAR24_1.1!P8) -> 88.62094 | X8: =100*(O8/OBR_MAR24_1.1!R8) -> 84.1401 | AA8: =100*((T8/T7)-1) -> 1.7008022
B9: 2009Q1 | C9: 247.707 | D9: 84.238 | E9: 65.081 | F9: 13.271 | G9: 1.281 | H9: 398.307 | I9: -6.857 | J9: 391.45 | K9: 103.636 | L9: 495.086 | M9: 108.347 | N9: 0 | O9: 386.739 | P9: 379.763 | S9: =100*(C9/OBR_MAR24_1.1!C9) -> 85.039686 | T9: =100*(D9/OBR_MAR24_1.1!D9) -> 88.856775 | U9: =100*(E9/OBR_MAR24_1.1!E9) -> 86.473738 | V9: =100*(K9/OBR_MAR24_1.1!N9) -> 81.781523 | W9: =100*(M9/OBR_MAR24_1.1!P9) -> 89.014772 | X9: =100*(O9/OBR_MAR24_1.1!R9) -> 84.054509 | AA9: =100*((T9/T8)-1) -> 1.6269939
B10: 2009Q2 | C10: 248.136 | D10: 84.184 | E10: 62.025 | F10: 12.265 | G10: 0.516 | H10: 394.861 | I10: -3.785 | J10: 391.076 | K10: 101.716 | L10: 492.792 | M10: 106.228 | N10: 0 | O10: 386.564 | P10: 380.724 | S10: =100*(C10/OBR_MAR24_1.1!C10) -> 85.237883 | T10: =100*(D10/OBR_MAR24_1.1!D10) -> 89.023307 | U10: =100*(E10/OBR_MAR24_1.1!E10) -> 86.070522 | V10: =100*(K10/OBR_MAR24_1.1!N10) -> 81.100303 | W10: =100*(M10/OBR_MAR24_1.1!P10) -> 87.065708 | X10: =100*(O10/OBR_MAR24_1.1!R10) -> 84.292377 | AA10: =100*((T10/T9)-1) -> 0.18741598
B11: 2009Q3 | C11: 249.481 | D11: 86.207 | E11: 62.265 | F11: 13.498 | G11: 0.57 | H11: 398.523 | I11: -3.917 | J11: 394.606 | K11: 102.632 | L11: 497.238 | M11: 108.614 | N11: 0 | O11: 388.624 | P11: 389.479 | S11: =100*(C11/OBR_MAR24_1.1!C11) -> 85.225052 | T11: =100*(D11/OBR_MAR24_1.1!D11) -> 90.39974 | U11: =100*(E11/OBR_MAR24_1.1!E11) -> 85.822387 | V11: =100*(K11/OBR_MAR24_1.1!N11) -> 82.218733 | W11: =100*(M11/OBR_MAR24_1.1!P11) -> 86.675551 | X11: =100*(O11/OBR_MAR24_1.1!R11) -> 84.690602 | AA11: =100*((T11/T10)-1) -> 1.546149
B12: 2009Q4 | C12: 250.34 | D12: 85.942 | E12: 60.697 | F12: 13.189 | G12: -0.013 | H12: 396.966 | I12: -6.071 | J12: 390.895 | K12: 108.358 | L12: 499.253 | M12: 112.378 | N12: 0 | O12: 386.875 | P12: 385.824 | S12: =100*(C12/OBR_MAR24_1.1!C12) -> 84.887202 | T12: =100*(D12/OBR_MAR24_1.1!D12) -> 89.420456 | U12: =100*(E12/OBR_MAR24_1.1!E12) -> 85.087264 | V12: =100*(K12/OBR_MAR24_1.1!N12) -> 82.929368 | W12: =100*(M12/OBR_MAR24_1.1!P12) -> 88.243424 | X12: =100*(O12/OBR_MAR24_1.1!R12) -> 84.059769 | AA12: =100*((T12/T11)-1) -> -1.0832821
B13: 2010Q1 | C13: 249.159 | D13: 86.856 | E13: 63.512 | F13: 13.272 | G13: -0.221 | H13: 399.306 | I13: 1.601 | J13: 400.907 | K13: 110.685 | L13: 511.592 | M13: 115.479 | N13: 0 | O13: 396.113 | P13: 396.248 | S13: =100*(C13/OBR_MAR24_1.1!C13) -> 84.902459 | T13: =100*(D13/OBR_MAR24_1.1!D13) -> 91.615421 | U13: =100*(E13/OBR_MAR24_1.1!E13) -> 84.527137 | V13: =100*(K13/OBR_MAR24_1.1!N13) -> 84.762831 | W13: =100*(M13/OBR_MAR24_1.1!P13) -> 89.051258 | X13: =100*(O13/OBR_MAR24_1.1!R13) -> 85.269394 | AA13: =100*((T13/T12)-1) -> 2.4546569
B14: 2010Q2 | C14: 257.449 | D14: 86.19 | E14: 62.846 | F14: 12.714 | G14: -0.362 | H14: 406.123 | I14: 0.261 | J14: 406.384 | K14: 115.919 | L14: 522.303 | M14: 120.992 | N14: 0 | O14: 401.311 | P14: 401.775 | S14: =100*(C14/OBR_MAR24_1.1!C14) -> 85.647323 | T14: =100*(D14/OBR_MAR24_1.1!D14) -> 90.609001 | U14: =100*(E14/OBR_MAR24_1.1!E14) -> 84.901786 | V14: =100*(K14/OBR_MAR24_1.1!N14) -> 85.9334 | W14: =100*(M14/OBR_MAR24_1.1!P14) -> 90.437642 | X14: =100*(O14/OBR_MAR24_1.1!R14) -> 85.456958 | AA14: =100*((T14/T13)-1) -> -1.098527
B15: 2010Q3 | C15: 259.351 | D15: 85.911 | E15: 65.226 | F15: 13.003 | G15: 0.447 | H15: 410.935 | I15: 1.096 | J15: 412.031 | K15: 116.698 | L15: 528.729 | M15: 124.53 | N15: 0 | O15: 404.199 | P15: 403.675 | S15: =100*(C15/OBR_MAR24_1.1!C15) -> 86.208662 | T15: =100*(D15/OBR_MAR24_1.1!D15) -> 90.302406 | U15: =100*(E15/OBR_MAR24_1.1!E15) -> 84.820349 | V15: =100*(K15/OBR_MAR24_1.1!N15) -> 85.612836 | W15: =100*(M15/OBR_MAR24_1.1!P15) -> 90.171175 | X15: =100*(O15/OBR_MAR24_1.1!R15) -> 85.599292 | AA15: =100*((T15/T14)-1) -> -0.33837143
B16: 2010Q4 | C16: 261.157 | D16: 87.359 | E16: 66.706 | F16: 12.588 | G16: 0.574 | H16: 415.796 | I16: -1.483 | J16: 414.313 | K16: 120.874 | L16: 535.187 | M16: 128.257 | N16: 0 | O16: 406.93 | P16: 407.562 | S16: =100*(C16/OBR_MAR24_1.1!C16) -> 86.953207 | T16: =100*(D16/OBR_MAR24_1.1!D16) -> 91.288037 | U16: =100*(E16/OBR_MAR24_1.1!E16) -> 84.466843 | V16: =100*(K16/OBR_MAR24_1.1!N16) -> 86.912192 | W16: =100*(M16/OBR_MAR24_1.1!P16) -> 92.06061 | X16: =100*(O16/OBR_MAR24_1.1!R16) -> 86.102342 | AA16: =100*((T16/T15)-1) -> 1.0914782
B17: 2011Q1 | C17: 263.602 | D17: 89.47 | E17: 64.274 | F17: 13.122 | G17: -1.752 | H17: 415.594 | I17: -1.655 | J17: 413.939 | K17: 128.717 | L17: 542.656 | M17: 127.924 | N17: 0 | O17: 414.732 | P17: 416.433 | S17: =100*(C17/OBR_MAR24_1.1!C17) -> 88.53905 | T17: =100*(D17/OBR_MAR24_1.1!D17) -> 92.944256 | U17: =100*(E17/OBR_MAR24_1.1!E17) -> 84.657938 | V17: =100*(K17/OBR_MAR24_1.1!N17) -> 88.896025 | W17: =100*(M17/OBR_MAR24_1.1!P17) -> 94.040329 | X17: =100*(O17/OBR_MAR24_1.1!R17) -> 87.529626 | AA17: =100*((T17/T16)-1) -> 1.8142784
... B55: 2020Q3 | C55: 319.136 | D55: 121.322 | E55: 92.349 | F55: 16.901 | G55: 1.172 | H55: 533.979 | I55: -0.951 | J55: 533.028 | K55: 147.825 | L55: 680.853 | M55: 147.185 | N55: 0 | O55: 533.668 | P55: 527.792 | S55: =100*(C55/OBR_MAR24_1.1!C55) -> 100.72307 | T55: =100*(D55/OBR_MAR24_1.1!D55) -> 121.40213 | U55: =100*(E55/OBR_MAR24_1.1!E55) -> 101.75526 | V55: =100*(K55/OBR_MAR24_1.1!N55) -> 99.277372 | W55: =100*(M55/OBR_MAR24_1.1!P55) -> 97.882542 | X55: =100*(O55/OBR_MAR24_1.1!R55) -> 105.12663 | AA55: =100*((T55/T54)-1) -> -15.407269
B56: 2020Q4 | C56: 314.018 | D56: 123.948 | E56: 96.772 | F56: 17.161 | G56: 7.662 | H56: 542.4 | I56: 10.552 | J56: 552.952 | K56: 158.181 | L56: 711.133 | M56: 172.439 | N56: 0 | O56: 538.694 | P56: 530.241 | S56: =100*(C56/OBR_MAR24_1.1!C56) -> 100.71814 | T56: =100*(D56/OBR_MAR24_1.1!D56) -> 118.23151 | U56: =100*(E56/OBR_MAR24_1.1!E56) -> 100.65005 | V56: =100*(K56/OBR_MAR24_1.1!N56) -> 100.37439 | W56: =100*(M56/OBR_MAR24_1.1!P56) -> 100.12774 | X56: =100*(O56/OBR_MAR24_1.1!R56) -> 104.69612 | Z56: =100*((S56/S55)-1) -> -0.0048942098 | AA56: =100*((T56/T55)-1) -> -2.6116666
B57: 2021Q1 | C57: 306.507 | D57: 129.099 | E57: 95.16 | F57: 18.039 | G57: 8.584 | H57: 539.35 | I57: -1.153 | J57: 538.197 | K57: 156.517 | L57: 694.714 | M57: 156.702 | N57: 0 | O57: 538.012 | P57: 537.213 | S57: =100*(C57/OBR_MAR24_1.1!C57) -> 101.83633 | T57: =100*(D57/OBR_MAR24_1.1!D57) -> 121.94797 | U57: =100*(E57/OBR_MAR24_1.1!E57) -> 101.47478 | V57: =100*(K57/OBR_MAR24_1.1!N57) -> 101.16995 | W57: =100*(M57/OBR_MAR24_1.1!P57) -> 100.66617 | X57: =100*(O57/OBR_MAR24_1.1!R57) -> 105.64563 | Z57: =100*((S57/S56)-1) -> 1.1102248 | AA57: =100*((T57/T56)-1) -> 3.143379
B58: 2021Q2 | C58: 342.73 | D58: 126.02 | E58: 99.19 | F58: 17.679 | G58: -0.583 | H58: 567.357 | I58: -7.639 | J58: 559.718 | K58: 170.177 | L58: 729.895 | M58: 162.008 | N58: 0 | O58: 567.887 | P58: 569.781 | S58: =100*(C58/OBR_MAR24_1.1!C58) -> 101.86625 | T58: =100*(D58/OBR_MAR24_1.1!D58) -> 110.45085 | U58: =100*(E58/OBR_MAR24_1.1!E58) -> 100.32163 | V58: =100*(K58/OBR_MAR24_1.1!N58) -> 102.03253 | W58: =100*(M58/OBR_MAR24_1.1!P58) -> 100.23697 | X58: =100*(O58/OBR_MAR24_1.1!R58) -> 103.89843 | Z58: =100*((S58/S57)-1) -> 0.02937102 | AA58: =100*((T58/T57)-1) -> -9.4278916
B59: 2021Q3 | C59: 357.103 | D59: 126.347 | E59: 104.563 | F59: 18.066 | G59: 3.684 | H59: 591.697 | I59: 0.585 | J59: 592.282 | K59: 163.01 | L59: 755.292 | M59: 173.786 | N59: 0 | O59: 581.506 | P59: 583.95 | S59: =100*(C59/OBR_MAR24_1.1!C59) -> 103.10675 | T59: =100*(D59/OBR_MAR24_1.1!D59) -> 109.72765 | U59: =100*(E59/OBR_MAR24_1.1!E59) -> 106.44386 | V59: =100*(K59/OBR_MAR24_1.1!N59) -> 102.20255 | W59: =100*(M59/OBR_MAR24_1.1!P59) -> 103.14383 | X59: =100*(O59/OBR_MAR24_1.1!R59) -> 104.59569 | Z59: =100*((S59/S58)-1) -> 1.2177751 | AA59: =100*((T59/T58)-1) -> -0.65476934
B60: 2021Q4 | C60: 362.996 | D60: 127.25 | E60: 104.934 | F60: 17.928 | G60: -2.959 | H60: 592.221 | I60: 5.179 | J60: 597.4 | K60: 186.322 | L60: 783.722 | M60: 187.048 | N60: 0 | O60: 596.674 | P60: 605.668 | S60: =100*(C60/OBR_MAR24_1.1!C60) -> 104.51011 | T60: =100*(D60/OBR_MAR24_1.1!D60) -> 109.31755 | U60: =100*(E60/OBR_MAR24_1.1!E60) -> 106.24076 | V60: =100*(K60/OBR_MAR24_1.1!N60) -> 106.12828 | W60: =100*(M60/OBR_MAR24_1.1!P60) -> 108.69575 | X60: =100*(O60/OBR_MAR24_1.1!R60) -> 105.71697 | Z60: =100*((S60/S59)-1) -> 1.3610751 | AA60: =100*((T60/T59)-1) -> -0.37374435
B61: 2022Q1 | C61: 373.512 | D61: 133.146 | E61: 110.419 | F61: 19.375 | G61: 8.494 | H61: 625.571 | I61: 9.731 | J61: 635.302 | K61: 179.132 | L61: 814.434 | M61: 212.54 | N61: 6.435 | O61: 608.329 | P61: 601.96 | S61: =100*(C61/OBR_MAR24_1.1!C61) -> 106.71863 | T61: =100*(D61/OBR_MAR24_1.1!D61) -> 113.21939 | U61: =100*(E61/OBR_MAR24_1.1!E61) -> 106.34288 | V61: =100*(K61/OBR_MAR24_1.1!N61) -> 110.4628 | W61: =100*(M61/OBR_MAR24_1.1!P61) -> 112.7599 | X61: =100*(O61/OBR_MAR24_1.1!R61) -> 107.21419 | Z61: =100*((S61/S60)-1) -> 2.1132137 | AA61: =100*((T61/T60)-1) -> 3.56927
B62: 2022Q2 | C62: 385.746 | D62: 128.435 | E62: 113.29 | F62: 18.267 | G62: 2.581 | H62: 630.052 | I62: 10.918 | J62: 640.97 | K62: 199.081 | L62: 840.051 | M62: 226.693 | N62: 7.914 | O62: 621.272 | P62: 630.944 | S62: =100*(C62/OBR_MAR24_1.1!C62) -> 109.78154 | T62: =100*(D62/OBR_MAR24_1.1!D62) -> 112.12134 | U62: =100*(E62/OBR_MAR24_1.1!E62) -> 108.62562 | V62: =100*(K62/OBR_MAR24_1.1!N62) -> 116.02403 | W62: =100*(M62/OBR_MAR24_1.1!P62) -> 117.94334 | X62: =100*(O62/OBR_MAR24_1.1!R62) -> 109.40025 | Z62: =100*((S62/S61)-1) -> 2.8700852 | AA62: =100*((T62/T61)-1) -> -0.96983687
B63: 2022Q3 | C63: 391.169 | D63: 132.118 | E63: 116.934 | F63: 19.225 | G63: -11.955 | H63: 628.266 | I63: 2.705 | J63: 630.971 | K63: 227.423 | L63: 858.394 | M63: 235.017 | N63: 7.198 | O63: 630.575 | P63: 631.386 | S63: =100*(C63/OBR_MAR24_1.1!C63) -> 112.34193 | T63: =100*(D63/OBR_MAR24_1.1!D63) -> 114.79139 | U63: =100*(E63/OBR_MAR24_1.1!E63) -> 110.22567 | V63: =100*(K63/OBR_MAR24_1.1!N63) -> 119.36649 | W63: =100*(M63/OBR_MAR24_1.1!P63) -> 126.24666 | X63: =100*(O63/OBR_MAR24_1.1!R63) -> 111.12531 | Z63: =100*((S63/S62)-1) -> 2.3322593 | AA63: =100*((T63/T62)-1) -> 2.3813874
B64: 2022Q4 | C64: 399.839 | D64: 132.493 | E64: 118.785 | F64: 20.726 | G64: -17.267 | H64: 633.85 | I64: 1.563 | J64: 635.413 | K64: 232.125 | L64: 867.538 | M64: 230.339 | N64: 8.606 | O64: 645.805 | P64: 654.041 | S64: =100*(C64/OBR_MAR24_1.1!C64) -> 114.92797 | T64: =100*(D64/OBR_MAR24_1.1!D64) -> 115.77508 | U64: =100*(E64/OBR_MAR24_1.1!E64) -> 111.33763 | V64: =100*(K64/OBR_MAR24_1.1!N64) -> 121.42144 | W64: =100*(M64/OBR_MAR24_1.1!P64) -> 123.10286 | X64: =100*(O64/OBR_MAR24_1.1!R64) -> 113.69126 | Z64: =100*((S64/S63)-1) -> 2.301931 | AA64: =100*((T64/T63)-1) -> 0.85693775
B65: 2023Q1 | C65: 410.541 | D65: 133.133 | E65: 122.62 | F65: 22.13 | G65: -5.396 | H65: 660.898 | I65: 0.511 | J65: 661.409 | K65: 219.303 | L65: 880.712 | M65: 226.301 | N65: 5.513 | O65: 659.924 | P65: 656.49 | S65: =100*(C65/OBR_MAR24_1.1!C65) -> 117.06831 | T65: =100*(D65/OBR_MAR24_1.1!D65) -> 117.58996 | U65: =100*(E65/OBR_MAR24_1.1!E65) -> 112.19691 | V65: =100*(K65/OBR_MAR24_1.1!N65) -> 122.23362 | W65: =100*(M65/OBR_MAR24_1.1!P65) -> 122.88882 | X65: =100*(O65/OBR_MAR24_1.1!R65) -> 115.88349 | Z65: =100*((S65/S64)-1) -> 1.8623322 | AA65: =100*((T65/T64)-1) -> 1.5675917
B66: 2023Q2 | C66: 417.479 | D66: 140.103 | E66: 122.306 | F66: 21.342 | G66: -3.106 | H66: 676.782 | I66: 0.953 | J66: 677.735 | K66: 217.528 | L66: 895.263 | M66: 225.085 | N66: 5.65 | O66: 675.828 | P66: 664.433 | S66: =100*(C66/OBR_MAR24_1.1!C66) -> 118.46165 | T66: =100*(D66/OBR_MAR24_1.1!D66) -> 120.66714 | U66: =100*(E66/OBR_MAR24_1.1!E66) -> 112.98998 | V66: =100*(K66/OBR_MAR24_1.1!N66) -> 121.75597 | W66: =100*(M66/OBR_MAR24_1.1!P66) -> 119.88932 | X66: =100*(O66/OBR_MAR24_1.1!R66) -> 118.63146 | Z66: =100*((S66/S65)-1) -> 1.1901964 | AA66: =100*((T66/T65)-1) -> 2.6168765
B67: 2023Q3 | C67: 418.482 | D67: 140.138 | E67: 121.398 | F67: 22.404 | G67: -0.429 | H67: 679.589 | I67: 5.026 | J67: 684.615 | K67: 214.137 | L67: 898.752 | M67: 219.277 | N67: 5.729 | O67: 685.204 | P67: 678.129 | S67: =100*(C67/OBR_MAR24_1.1!C67) -> 119.28341 | T67: =100*(D67/OBR_MAR24_1.1!D67) -> 119.78221 | U67: =100*(E67/OBR_MAR24_1.1!E67) -> 113.99301 | V67: =100*(K67/OBR_MAR24_1.1!N67) -> 120.58146 | W67: =100*(M67/OBR_MAR24_1.1!P67) -> 117.96443 | X67: =100*(O67/OBR_MAR24_1.1!R67) -> 120.43244 | Z67: =100*((S67/S66)-1) -> 0.69369424 | AA67: =100*((T67/T66)-1) -> -0.73336632
... B82: 2027Q2 | C82: 477.26562 | D82: 155.79582 | E82: 128.21766 | F82: 22.647836 | G82: -1.5443202 | H82: 759.73478 | I82: 0.47822681 | J82: 760.21301 | K82: 215.19555 | L82: 975.40856 | M82: 218.15676 | N82: 5.9965926 | O82: 763.24838 | P82: 749.99375 | S82: =100*(C82/OBR_MAR24_1.1!C82) -> 127.48319 | T82: =100*(D82/OBR_MAR24_1.1!D82) -> 122.8143 | U82: =100*(E82/OBR_MAR24_1.1!E82) -> 120.41483 | V82: =100*(K82/OBR_MAR24_1.1!N82) -> 120.25595 | W82: =100*(M82/OBR_MAR24_1.1!P82) -> 117.72371 | X82: =100*(O82/OBR_MAR24_1.1!R82) -> 126.05828 | Z82: =100*((S82/S81)-1) -> 0.4976757 | AA82: =100*((T82/T81)-1) -> 0.37090564
B83: 2027Q3 | C83: 481.93232 | D83: 156.98568 | E83: 129.06608 | F83: 22.650407 | G83: -1.5501806 | H83: 766.43391 | I83: 0.52823318 | J83: 766.96214 | K83: 216.37029 | L83: 983.33243 | M83: 219.2437 | N83: 6.0244182 | O83: 770.11315 | P83: 756.79869 | S83: =100*(C83/OBR_MAR24_1.1!C83) -> 128.11902 | T83: =100*(D83/OBR_MAR24_1.1!D83) -> 123.28151 | U83: =100*(E83/OBR_MAR24_1.1!E83) -> 120.87178 | V83: =100*(K83/OBR_MAR24_1.1!N83) -> 120.69167 | W83: =100*(M83/OBR_MAR24_1.1!P83) -> 118.09581 | X83: =100*(O83/OBR_MAR24_1.1!R83) -> 126.64322 | Z83: =100*((S83/S82)-1) -> 0.49875372 | AA83: =100*((T83/T82)-1) -> 0.38041416 | AB83: =100*((U83/U82)-1) -> 0.37947824 | AC83: =100*((V83/V82)-1) -> 0.36233 | AD83: =100*((W83/W82)-1) -> 0.31607466 | AE83: =100*((X83/X82)-1) -> 0.4640231
B84: 2027Q4 | C84: 486.64846 | D84: 158.238 | E84: 129.90604 | F84: 22.628453 | G84: -1.5561473 | H84: 773.23635 | I84: 0.52121442 | J84: 773.75757 | K84: 217.62977 | L84: 991.38734 | M84: 220.39025 | N84: 6.053019 | O84: 777.05011 | P84: 763.67307 | S84: =100*(C84/OBR_MAR24_1.1!C84) -> 128.75969 | T84: =100*(D84/OBR_MAR24_1.1!D84) -> 123.77128 | U84: =100*(E84/OBR_MAR24_1.1!E84) -> 121.33702 | V84: =100*(K84/OBR_MAR24_1.1!N84) -> 121.15862 | W84: =100*(M84/OBR_MAR24_1.1!P84) -> 118.49693 | X84: =100*(O84/OBR_MAR24_1.1!R84) -> 127.24446 | Z84: =100*((S84/S83)-1) -> 0.50006463 | AA84: =100*((T84/T83)-1) -> 0.39727849 | AB84: =100*((U84/U83)-1) -> 0.38490416 | AC84: =100*((V84/V83)-1) -> 0.38689145 | AD84: =100*((W84/W83)-1) -> 0.33965403 | AE84: =100*((X84/X83)-1) -> 0.47474917
B85: 2028Q1 | C85: 491.40143 | D85: 159.55276 | E85: 130.81399 | F85: 22.581976 | G85: -1.562149 | H85: 780.20603 | I85: 0.46942919 | J85: 780.67546 | K85: 218.87999 | L85: 999.55545 | M85: 221.55901 | N85: 6.0823162 | O85: 784.07876 | P85: 770.6732 | S85: =100*(C85/OBR_MAR24_1.1!C85) -> 129.40511 | T85: =100*(D85/OBR_MAR24_1.1!D85) -> 124.28334 | U85: =100*(E85/OBR_MAR24_1.1!E85) -> 121.80499 | V85: =100*(K85/OBR_MAR24_1.1!N85) -> 121.63973 | W85: =100*(M85/OBR_MAR24_1.1!P85) -> 118.90684 | X85: =100*(O85/OBR_MAR24_1.1!R85) -> 127.86034 | Z85: =100*((S85/S84)-1) -> 0.50125865 | AA85: =100*((T85/T84)-1) -> 0.41372066 | AB85: =100*((U85/U84)-1) -> 0.38567762 | AC85: =100*((V85/V84)-1) -> 0.39709688 | AD85: =100*((W85/W84)-1) -> 0.34593097 | AE85: =100*((X85/X84)-1) -> 0.48400827
B86: 2028Q2 | C86: 496.19731 | D86: 160.99326 | E86: 131.65745 | F86: 22.523952 | G86: -1.568168 | H86: 787.27985 | I86: 0.43292256 | J86: 787.71278 | K86: 220.15422 | L86: 1007.867 | M86: 222.76385 | N86: 6.1121338 | O86: 791.21528 | P86: 777.79842 | S86: =100*(C86/OBR_MAR24_1.1!C86) -> 130.05204 | T86: =100*(D86/OBR_MAR24_1.1!D86) -> 124.84186 | U86: =100*(E86/OBR_MAR24_1.1!E86) -> 122.27431 | V86: =100*(K86/OBR_MAR24_1.1!N86) -> 122.13004 | W86: =100*(M86/OBR_MAR24_1.1!P86) -> 119.32155 | X86: =100*(O86/OBR_MAR24_1.1!R86) -> 128.48715 | Z86: =100*((S86/S85)-1) -> 0.49992844 | AA86: =100*((T86/T85)-1) -> 0.44938828 | AB86: =100*((U86/U85)-1) -> 0.38529941 | AC86: =100*((V86/V85)-1) -> 0.40308259 | AD86: =100*((W86/W85)-1) -> 0.34876426 | AE86: =100*((X86/X85)-1) -> 0.49023535
B87: 2028Q3 | C87: 501.03375 | D87: 162.22282 | E87: 132.50564 | F87: 22.466085 | G87: -1.5742034 | H87: 794.18801 | I87: 0.48894231 | J87: 794.67696 | K87: 221.39457 | L87: 1016.0715 | M87: 223.99872 | N87: 6.1407033 | O87: 798.21351 | P87: 784.70093 | S87: =100*(C87/OBR_MAR24_1.1!C87) -> 130.70058 | T87: =100*(D87/OBR_MAR24_1.1!D87) -> 125.31678 | U87: =100*(E87/OBR_MAR24_1.1!E87) -> 122.74491 | V87: =100*(K87/OBR_MAR24_1.1!N87) -> 122.6214 | W87: =100*(M87/OBR_MAR24_1.1!P87) -> 119.73758 | X87: =100*(O87/OBR_MAR24_1.1!R87) -> 129.08773 | Z87: =100*((S87/S86)-1) -> 0.498675 | AA87: =100*((T87/T86)-1) -> 0.38041381 | AB87: =100*((U87/U86)-1) -> 0.38487293 | AC87: =100*((V87/V86)-1) -> 0.40232242 | AD87: =100*((W87/W86)-1) -> 0.34866134 | AE87: =100*((X87/X86)-1) -> 0.46742241
B88: 2028Q4 | C88: 505.91618 | D88: 163.51691 | E88: 133.38957 | F88: 22.408375 | G88: -1.5802679 | H88: 801.24239 | I88: 0.51639848 | J88: 801.75879 | K88: 222.67912 | L88: 1024.4379 | M88: 225.24219 | N88: 6.170086 | O88: 805.36581 | P88: 791.79657 | S88: =100*(C88/OBR_MAR24_1.1!C88) -> 131.35411 | T88: =100*(D88/OBR_MAR24_1.1!D88) -> 125.81463 | U88: =100*(E88/OBR_MAR24_1.1!E88) -> 123.21777 | V88: =100*(K88/OBR_MAR24_1.1!N88) -> 123.13337 | W88: =100*(M88/OBR_MAR24_1.1!P88) -> 120.15477 | X88: =100*(O88/OBR_MAR24_1.1!R88) -> 129.7054 | Z88: =100*((S88/S87)-1) -> 0.500023 | AA88: =100*((T88/T87)-1) -> 0.3972785 | AB88: =100*((U88/U87)-1) -> 0.38524236 | AC88: =100*((V88/V87)-1) -> 0.41752017 | AD88: =100*((W88/W87)-1) -> 0.3484248 | AE88: =100*((X88/X87)-1) -> 0.47849088
B89: 2029Q1 | C89: 510.87639 | D89: 164.87554 | E89: 134.28893 | F89: 22.366625 | G89: -1.5863643 | H89: 808.4545 | I89: 0.58018475 | J89: 809.03468 | K89: 224.07548 | L89: 1033.1102 | M89: 226.6295 | N89: 6.2003031 | O89: 812.68097 | P89: 799.06561 | S89: =100*(C89/OBR_MAR24_1.1!C89) -> 132.01256 | T89: =100*(D89/OBR_MAR24_1.1!D89) -> 126.33515 | U89: =100*(E89/OBR_MAR24_1.1!E89) -> 123.69313 | V89: =100*(K89/OBR_MAR24_1.1!N89) -> 123.71529 | W89: =100*(M89/OBR_MAR24_1.1!P89) -> 120.59897 | X89: =100*(O89/OBR_MAR24_1.1!R89) -> 130.34062 | Z89: =100*((S89/S88)-1) -> 0.50127396 | AA89: =100*((T89/T88)-1) -> 0.41372138 | AB89: =100*((U89/U88)-1) -> 0.38578441 | AC89: =100*((V89/V88)-1) -> 0.4725927 | AD89: =100*((W89/W88)-1) -> 0.369687 | AE89: =100*((X89/X88)-1) -> 0.48973537
B90: 2008 | C90: 1015.322 | D90: 324.775 | E90: 281.252 | F90: 48.299 | G90: -0.189 | H90: 1621.16 | I90: -0.681 | J90: 1620.479 | K90: 438.335 | L90: 2058.814 | M90: 465.214 | N90: 0 | O90: 1593.6 | P90: 1572.569 | S90: =100*(C90/OBR_MAR24_1.1!C90) -> 84.286786 | T90: =100*(D90/OBR_MAR24_1.1!D90) -> 86.408503 | U90: =100*(E90/OBR_MAR24_1.1!E90) -> 84.727984 | V90: =100*(K90/OBR_MAR24_1.1!N90) -> 78.715335 | W90: =100*(M90/OBR_MAR24_1.1!P90) -> 87.136513 | X90: =100*(O90/OBR_MAR24_1.1!R90) -> 82.709869
B91: 2009 | C91: 995.664 | D91: 340.571 | E91: 250.068 | F91: 52.223 | G91: 2.354 | H91: 1588.657 | I91: -20.63 | J91: 1568.027 | K91: 416.342 | L91: 1984.369 | M91: 435.567 | N91: 0 | O91: 1548.802 | P91: 1535.79 | S91: =100*(C91/OBR_MAR24_1.1!C91) -> 85.096942 | T91: =100*(D91/OBR_MAR24_1.1!D91) -> 89.426738 | U91: =100*(E91/OBR_MAR24_1.1!E91) -> 85.872051 | V91: =100*(K91/OBR_MAR24_1.1!N91) -> 82.016177 | W91: =100*(M91/OBR_MAR24_1.1!P91) -> 87.747286 | X91: =100*(O91/OBR_MAR24_1.1!R91) -> 84.274006 | Z91: =100*((S91/S90)-1) -> 0.96118884 | AA91: =100*((T91/T90)-1) -> 3.4929834 | AB91: =100*((U91/U90)-1) -> 1.3502828 | AC91: =100*((V91/V90)-1) -> 4.1933917 | AD91: =100*((W91/W90)-1) -> 0.70093867 | AE91: =100*((X91/X90)-1) -> 1.891112
B92: 2010 | C92: 1027.116 | D92: 346.316 | E92: 258.29 | F92: 51.577 | G92: 0.438 | H92: 1632.16 | I92: 1.475 | J92: 1633.635 | K92: 464.176 | L92: 2097.811 | M92: 489.258 | N92: 0 | O92: 1608.553 | P92: 1609.26 | S92: =100*(C92/OBR_MAR24_1.1!C92) -> 85.933871 | T92: =100*(D92/OBR_MAR24_1.1!D92) -> 90.953643 | U92: =100*(E92/OBR_MAR24_1.1!E92) -> 84.676362 | V92: =100*(K92/OBR_MAR24_1.1!N92) -> 85.821681 | W92: =100*(M92/OBR_MAR24_1.1!P92) -> 90.455255 | X92: =100*(O92/OBR_MAR24_1.1!R92) -> 85.608688 | Z92: =100*((S92/S91)-1) -> 0.98350124 | AA92: =100*((T92/T91)-1) -> 1.7074367 | AB92: =100*((U92/U91)-1) -> -1.392408 | AC92: =100*((V92/V91)-1) -> 4.6399427 | AD92: =100*((W92/W91)-1) -> 3.0860992 | AE92: =100*((X92/X91)-1) -> 1.5837413
B93: 2011 | C93: 1063.466 | D93: 347.419 | E93: 261.22 | F93: 48.039 | G93: 0.676 | H93: 1672.781 | I93: 2.947 | J93: 1675.728 | K93: 521.847 | L93: 2197.575 | M93: 534.985 | N93: 0 | O93: 1662.59 | P93: 1669.535 | S93: =100*(C93/OBR_MAR24_1.1!C93) -> 89.271618 | T93: =100*(D93/OBR_MAR24_1.1!D93) -> 91.302314 | U93: =100*(E93/OBR_MAR24_1.1!E93) -> 85.546611 | V93: =100*(K93/OBR_MAR24_1.1!N93) -> 90.232963 | W93: =100*(M93/OBR_MAR24_1.1!P93) -> 96.095365 | X93: =100*(O93/OBR_MAR24_1.1!R93) -> 87.48282 | Z93: =100*((S93/S92)-1) -> 3.8840874 | AA93: =100*((T93/T92)-1) -> 0.38335038 | AB93: =100*((U93/U92)-1) -> 1.0277362 | AC93: =100*((V93/V92)-1) -> 5.1400555 | AD93: =100*((W93/W92)-1) -> 6.2352491 | AE93: =100*((X93/X92)-1) -> 2.1891847
B94: 2012 | C94: 1100.051 | D94: 355.384 | E94: 270.019 | F94: 45.252 | G94: 0.352 | H94: 1725.806 | I94: 4.855 | J94: 1730.661 | K94: 524.715 | L94: 2255.376 | M94: 541.661 | N94: 0 | O94: 1713.715 | P94: 1697.755 | S94: =100*(C94/OBR_MAR24_1.1!C94) -> 90.777739 | T94: =100*(D94/OBR_MAR24_1.1!D94) -> 92.023574 | U94: =100*(E94/OBR_MAR24_1.1!E94) -> 87.040571 | V94: =100*(K94/OBR_MAR24_1.1!N94) -> 90.044429 | W94: =100*(M94/OBR_MAR24_1.1!P94) -> 94.964103 | X94: =100*(O94/OBR_MAR24_1.1!R94) -> 88.829009 | Z94: =100*((S94/S93)-1) -> 1.6871226 | AA94: =100*((T94/T93)-1) -> 0.78996907 | AB94: =100*((U94/U93)-1) -> 1.746369 | AC94: =100*((V94/V93)-1) -> -0.20894114 | AD94: =100*((W94/W93)-1) -> -1.1772285 | AE94: =100*((X94/X93)-1) -> 1.5388036
B95: 2013 | C95: 1153.092 | D95: 358.572 | E95: 284.444 | F95: 43.568 | G95: 7.215 | H95: 1803.323 | I95: 3.338 | J95: 1806.661 | K95: 539.564 | L95: 2346.225 | M95: 564.864 | N95: 0 | O95: 1781.361 | P95: 1749.792 | S95: =100*(C95/OBR_MAR24_1.1!C95) -> 92.808069 | T95: =100*(D95/OBR_MAR24_1.1!D95) -> 92.642294 | U95: =100*(E95/OBR_MAR24_1.1!E95) -> 88.804663 | V95: =100*(K95/OBR_MAR24_1.1!N95) -> 92.329912 | W95: =100*(M95/OBR_MAR24_1.1!P95) -> 95.921098 | X95: =100*(O95/OBR_MAR24_1.1!R95) -> 90.709576 | Z95: =100*((S95/S94)-1) -> 2.2365944 | AA95: =100*((T95/T94)-1) -> 0.67234975 | AB95: =100*((U95/U94)-1) -> 2.026747 | AC95: =100*((V95/V94)-1) -> 2.5381722 | AD95: =100*((W95/W94)-1) -> 1.007744 | AE95: =100*((X95/X94)-1) -> 2.117064
B96: 2014 | C96: 1198.685 | D96: 370.011 | E96: 308.662 | F96: 50.194 | G96: 6.103 | H96: 1883.461 | I96: 15.23 | J96: 1898.691 | K96: 532.236 | L96: 2430.927 | M96: 568.413 | N96: 0 | O96: 1862.514 | P96: 1829.242 | S96: =100*(C96/OBR_MAR24_1.1!C96) -> 93.93369 | T96: =100*(D96/OBR_MAR24_1.1!D96) -> 93.185567 | U96: =100*(E96/OBR_MAR24_1.1!E96) -> 90.030918 | V96: =100*(K96/OBR_MAR24_1.1!N96) -> 90.169756 | W96: =100*(M96/OBR_MAR24_1.1!P96) -> 91.844243 | X96: =100*(O96/OBR_MAR24_1.1!R96) -> 91.904927 | Z96: =100*((S96/S95)-1) -> 1.2128479 | AA96: =100*((T96/T95)-1) -> 0.58642003 | AB96: =100*((U96/U95)-1) -> 1.3808454 | AC96: =100*((V96/V95)-1) -> -2.3396056 | AD96: =100*((W96/W95)-1) -> -4.2502172 | AE96: =100*((X96/X95)-1) -> 1.3177782
B97: 2015 | C97: 1228.325 | D97: 374.638 | E97: 332.973 | F97: 51.665 | G97: 0.879 | H97: 1936.815 | I97: 8.606 | J97: 1945.421 | K97: 533.654 | L97: 2479.075 | M97: 562.624 | N97: 0 | O97: 1916.451 | P97: 1874.682 | S97: =100*(C97/OBR_MAR24_1.1!C97) -> 93.607135 | T97: =100*(D97/OBR_MAR24_1.1!D97) -> 93.159235 | U97: =100*(E97/OBR_MAR24_1.1!E97) -> 90.644362 | V97: =100*(K97/OBR_MAR24_1.1!N97) -> 87.12249 | W97: =100*(M97/OBR_MAR24_1.1!P97) -> 86.616438 | X97: =100*(O97/OBR_MAR24_1.1!R97) -> 92.51241 | Z97: =100*((S97/S96)-1) -> -0.34764371 | AA97: =100*((T97/T96)-1) -> -0.028257955 | AB97: =100*((U97/U96)-1) -> 0.68137032 | AC97: =100*((V97/V96)-1) -> -3.3794768 | AD97: =100*((W97/W96)-1) -> -5.692034 | AE97: =100*((X97/X96)-1) -> 0.66099053
B98: 2016 | C98: 1289.445 | D98: 382.76 | E98: 356.602 | F98: 51.474 | G98: 1.502 | H98: 2030.309 | I98: -0.908 | J98: 2029.401 | K98: 575.632 | L98: 2605.033 | M98: 613.388 | N98: 0 | O98: 1991.645 | P98: 1944.912 | S98: =100*(C98/OBR_MAR24_1.1!C98) -> 94.777009 | T98: =100*(D98/OBR_MAR24_1.1!D98) -> 94.512376 | U98: =100*(E98/OBR_MAR24_1.1!E98) -> 92.330118 | V98: =100*(K98/OBR_MAR24_1.1!N98) -> 91.43881 | W98: =100*(M98/OBR_MAR24_1.1!P98) -> 90.820092 | X98: =100*(O98/OBR_MAR24_1.1!R98) -> 94.330092 | Z98: =100*((S98/S97)-1) -> 1.2497698 | AA98: =100*((T98/T97)-1) -> 1.4525032 | AB98: =100*((U98/U97)-1) -> 1.8597475 | AC98: =100*((V98/V97)-1) -> 4.9543128 | AD98: =100*((W98/W97)-1) -> 4.8531826 | AE98: =100*((X98/X97)-1) -> 1.9647983
B99: 2017 | C99: 1336.921 | D99: 388.577 | E99: 380.012 | F99: 57.4 | G99: 0.842 | H99: 2106.352 | I99: 4.055 | J99: 2110.407 | K99: 643.286 | L99: 2753.693 | M99: 671.211 | N99: 0 | O99: 2082.482 | P99: 2060.075 | S99: =100*(C99/OBR_MAR24_1.1!C99) -> 96.502254 | T99: =100*(D99/OBR_MAR24_1.1!D99) -> 95.325441 | U99: =100*(E99/OBR_MAR24_1.1!E99) -> 95.061938 | V99: =100*(K99/OBR_MAR24_1.1!N99) -> 95.710277 | W99: =100*(M99/OBR_MAR24_1.1!P99) -> 96.333032 | X99: =100*(O99/OBR_MAR24_1.1!R99) -> 96.081369 | Z99: =100*((S99/S98)-1) -> 1.8203203 | AA99: =100*((T99/T98)-1) -> 0.86027337 | AB99: =100*((U99/U98)-1) -> 2.9587528 | AC99: =100*((V99/V98)-1) -> 4.6713935 | AD99: =100*((W99/W98)-1) -> 6.0701776 | AE99: =100*((X99/X98)-1) -> 1.856541
B100: 2018 | C100: 1391.673 | D100: 399.065 | E100: 387.324 | F100: 58.446 | G100: 2.826 | H100: 2180.888 | I100: 1.17 | J100: 2182.058 | K100: 679.7 | L100: 2861.758 | M100: 709.454 | N100: 0 | O100: 2152.304 | P100: 2123.051 | S100: =100*(C100/OBR_MAR24_1.1!C100) -> 98.518547 | T100: =100*(D100/OBR_MAR24_1.1!D100) -> 97.292349 | U100: =100*(E100/OBR_MAR24_1.1!E100) -> 97.357216 | V100: =100*(K100/OBR_MAR24_1.1!N100) -> 98.100626 | W100: =100*(M100/OBR_MAR24_1.1!P100) -> 98.762019 | X100: =100*(O100/OBR_MAR24_1.1!R100) -> 97.928103 | Z100: =100*((S100/S99)-1) -> 2.0893741 | AA100: =100*((T100/T99)-1) -> 2.0633613 | AB100: =100*((U100/U99)-1) -> 2.4145072 | AC100: =100*((V100/V99)-1) -> 2.4974845 | AD100: =100*((W100/W99)-1) -> 2.5214471 | AE100: =100*((X100/X99)-1) -> 1.9220524
B101: 2019 | C101: 1427.94 | D101: 426.592 | E101: 406.423 | F101: 62.139 | G101: 2.88 | H101: 2263.835 | I101: 1.262 | J101: 2265.097 | K101: 706.696 | L101: 2971.793 | M101: 737.872 | N101: 0 | O101: 2233.921 | P101: 2231.667 | S101: =100*(C101/OBR_MAR24_1.1!C101) -> 100 | T101: =100*(D101/OBR_MAR24_1.1!D101) -> 100 | U101: =100*(E101/OBR_MAR24_1.1!E101) -> 100 | V101: =100*(K101/OBR_MAR24_1.1!N101) -> 100 | W101: =100*(M101/OBR_MAR24_1.1!P101) -> 100 | X101: =100*(O101/OBR_MAR24_1.1!R101) -> 100 | Z101: =100*((S101/S100)-1) -> 1.5037297 | AA101: =100*((T101/T100)-1) -> 2.7830053 | AB101: =100*((U101/U100)-1) -> 2.7145232 | AC101: =100*((V101/V100)-1) -> 1.9361483 | AD101: =100*((W101/W100)-1) -> 1.2534992 | AE101: =100*((X101/X100)-1) -> 2.1157327
B102: 2020 | C102: 1246.073 | D102: 475.618 | E102: 367.488 | F102: 66.087 | G102: 0.969 | H102: 2090.148 | I102: 1.316 | J102: 2091.464 | K102: 624.805 | L102: 2716.269 | M102: 611.981 | N102: 0 | O102: 2104.288 | P102: 2059.457 | S102: =100*(C102/OBR_MAR24_1.1!C102) -> 100.57573 | T102: =100*(D102/OBR_MAR24_1.1!D102) -> 121.03255 | U102: =100*(E102/OBR_MAR24_1.1!E102) -> 101.33211 | V102: =100*(K102/OBR_MAR24_1.1!N102) -> 99.866537 | W102: =100*(M102/OBR_MAR24_1.1!P102) -> 98.739579 | X102: =100*(O102/OBR_MAR24_1.1!R102) -> 105.08362 | Z102: =100*((S102/S101)-1) -> 0.5757341 | AA102: =100*((T102/T101)-1) -> 21.032555 | AB102: =100*((U102/U101)-1) -> 1.3321127 | AC102: =100*((V102/V101)-1) -> -0.13346333 | AD102: =100*((W102/W101)-1) -> -1.2604208 | AE102: =100*((X102/X101)-1) -> 5.0836234
... B110: 2028 | C110: 1994.5487 | D110: 646.28576 | E110: 528.36665 | F110: 89.980388 | G110: -6.2847884 | H110: 3162.9163 | I110: 1.9076925 | J110: 3164.824 | K110: 883.1079 | L110: 4047.9319 | M110: 893.56377 | N110: 24.505239 | O110: 3178.8734 | P110: 3124.9691 | S110: =100*(C110/OBR_MAR24_1.1!C110) -> 130.3818 | T110: =100*(D110/OBR_MAR24_1.1!D110) -> 125.06673 | U110: =100*(E110/OBR_MAR24_1.1!E110) -> 122.51205 | V110: =100*(K110/OBR_MAR24_1.1!N110) -> 122.38217 | W110: =100*(M110/OBR_MAR24_1.1!P110) -> 119.53123 | X110: =100*(O110/OBR_MAR24_1.1!R110) -> 128.78834 | Z110: =100*((S110/S109)-1) -> 2.0144111 | AA110: =100*((T110/T109)-1) -> 1.631406 | AB110: =100*((U110/U109)-1) -> 1.5448238 | AC110: =100*((V110/V109)-1) -> 1.5651939 | AD110: =100*((W110/W109)-1) -> 1.3574075 | AE110: =100*((X110/X109)-1) -> 1.923023
B111: 2008-09 | C111: 1007.591 | D111: 329.006 | E111: 275.104 | F111: 49.512 | G111: 0.815 | H111: 1612.516 | I111: -7.375 | J111: 1605.141 | K111: 437.016 | L111: 2042.157 | M111: 459.366 | N111: 0 | O111: 1582.791 | P111: 1555.396 | S111: =100*(C111/OBR_MAR24_1.1!C111) -> 84.829481 | T111: =100*(D111/OBR_MAR24_1.1!D111) -> 87.191093 | U111: =100*(E111/OBR_MAR24_1.1!E111) -> 85.340348 | V111: =100*(K111/OBR_MAR24_1.1!N111) -> 80.437624 | W111: =100*(M111/OBR_MAR24_1.1!P111) -> 88.594153 | X111: =100*(O111/OBR_MAR24_1.1!R111) -> 83.434024
B112: 2009-10 | C112: 997.116 | D112: 343.189 | E112: 248.499 | F112: 52.224 | G112: 0.852 | H112: 1589.656 | I112: -12.172 | J112: 1577.484 | K112: 423.391 | L112: 2000.875 | M112: 442.699 | N112: 0 | O112: 1558.176 | P112: 1552.275 | S112: =100*(C112/OBR_MAR24_1.1!C112) -> 85.06248 | T112: =100*(D112/OBR_MAR24_1.1!D112) -> 90.113459 | U112: =100*(E112/OBR_MAR24_1.1!E112) -> 85.369323 | V112: =100*(K112/OBR_MAR24_1.1!N112) -> 82.775522 | W112: =100*(M112/OBR_MAR24_1.1!P112) -> 87.77667 | X112: =100*(O112/OBR_MAR24_1.1!R112) -> 84.579822
B113: 2010-11 | C113: 1041.559 | D113: 348.93 | E113: 259.052 | F113: 51.427 | G113: -1.093 | H113: 1648.448 | I113: -1.781 | J113: 1646.667 | K113: 482.208 | L113: 2128.875 | M113: 501.703 | N113: 0 | O113: 1627.172 | P113: 1629.445 | S113: =100*(C113/OBR_MAR24_1.1!C113) -> 86.832836 | T113: =100*(D113/OBR_MAR24_1.1!D113) -> 91.290834 | U113: =100*(E113/OBR_MAR24_1.1!E113) -> 84.708452 | V113: =100*(K113/OBR_MAR24_1.1!N113) -> 86.872741 | W113: =100*(M113/OBR_MAR24_1.1!P113) -> 91.679123 | X113: =100*(O113/OBR_MAR24_1.1!R113) -> 86.174186
B114: 2011-12 | C114: 1069.406 | D114: 348.529 | E114: 265.089 | F114: 46.627 | G114: 1.279 | H114: 1684.303 | I114: 2.483 | J114: 1686.786 | K114: 529.028 | L114: 2215.814 | M114: 543.252 | N114: 0 | O114: 1672.562 | P114: 1675.315 | S114: =100*(C114/OBR_MAR24_1.1!C114) -> 89.706614 | T114: =100*(D114/OBR_MAR24_1.1!D114) -> 91.123219 | U114: =100*(E114/OBR_MAR24_1.1!E114) -> 86.043553 | V114: =100*(K114/OBR_MAR24_1.1!N114) -> 90.648609 | W114: =100*(M114/OBR_MAR24_1.1!P114) -> 96.568176 | X114: =100*(O114/OBR_MAR24_1.1!R114) -> 87.69316
B115: 2012-13 | C115: 1113.172 | D115: 354.138 | E115: 269.372 | F115: 43.658 | G115: 2.369 | H115: 1739.051 | I115: 6.262 | J115: 1745.313 | K115: 524.297 | L115: 2269.61 | M115: 542.496 | N115: 0 | O115: 1727.114 | P115: 1702.767 | S115: =100*(C115/OBR_MAR24_1.1!C115) -> 91.280343 | T115: =100*(D115/OBR_MAR24_1.1!D115) -> 92.256112 | U115: =100*(E115/OBR_MAR24_1.1!E115) -> 87.384108 | V115: =100*(K115/OBR_MAR24_1.1!N115) -> 90.586422 | W115: =100*(M115/OBR_MAR24_1.1!P115) -> 95.219841 | X115: =100*(O115/OBR_MAR24_1.1!R115) -> 89.302412
B116: 2013-14 | C116: 1164.913 | D116: 362.069 | E116: 292.68 | F116: 45.912 | G116: 7.745 | H116: 1827.407 | I116: 4.435 | J116: 1831.842 | K116: 536.091 | L116: 2367.933 | M116: 566.683 | N116: 0 | O116: 1801.25 | P116: 1774.7 | S116: =100*(C116/OBR_MAR24_1.1!C116) -> 93.114377 | T116: =100*(D116/OBR_MAR24_1.1!D116) -> 92.847966 | U116: =100*(E116/OBR_MAR24_1.1!E116) -> 89.17244 | V116: =100*(K116/OBR_MAR24_1.1!N116) -> 91.966952 | W116: =100*(M116/OBR_MAR24_1.1!P116) -> 94.974911 | X116: =100*(O116/OBR_MAR24_1.1!R116) -> 91.020491
B117: 2014-15 | C117: 1207.424 | D117: 370.792 | E117: 315.035 | F117: 50.626 | G117: 7.169 | H117: 1900.42 | I117: 18.933 | J117: 1919.353 | K117: 533.25 | L117: 2452.603 | M117: 573.343 | N117: 0 | O117: 1879.26 | P117: 1841.848 | S117: =100*(C117/OBR_MAR24_1.1!C117) -> 93.883321 | T117: =100*(D117/OBR_MAR24_1.1!D117) -> 93.212065 | U117: =100*(E117/OBR_MAR24_1.1!E117) -> 90.175666 | V117: =100*(K117/OBR_MAR24_1.1!N117) -> 89.386889 | W117: =100*(M117/OBR_MAR24_1.1!P117) -> 90.506454 | X117: =100*(O117/OBR_MAR24_1.1!R117) -> 92.12673
B118: 2015-16 | C118: 1241.449 | D118: 376.402 | E118: 337.155 | F118: 51.402 | G118: -0.866 | H118: 1954.14 | I118: 3.232 | J118: 1957.372 | K118: 536.701 | L118: 2494.073 | M118: 562.63 | N118: 0 | O118: 1931.443 | P118: 1884.888 | S118: =100*(C118/OBR_MAR24_1.1!C118) -> 93.767296 | T118: =100*(D118/OBR_MAR24_1.1!D118) -> 93.224193 | U118: =100*(E118/OBR_MAR24_1.1!E118) -> 90.864868 | V118: =100*(K118/OBR_MAR24_1.1!N118) -> 87.111654 | W118: =100*(M118/OBR_MAR24_1.1!P118) -> 86.357183 | X118: =100*(O118/OBR_MAR24_1.1!R118) -> 92.78985
B119: 2016-17 | C119: 1302.659 | D119: 384.469 | E119: 363.126 | F119: 51.719 | G119: 0.071 | H119: 2050.325 | I119: 2.36 | J119: 2052.685 | K119: 597.001 | L119: 2649.686 | M119: 633.845 | N119: 0 | O119: 2015.841 | P119: 1979.375 | S119: =100*(C119/OBR_MAR24_1.1!C119) -> 95.183603 | T119: =100*(D119/OBR_MAR24_1.1!D119) -> 94.891021 | U119: =100*(E119/OBR_MAR24_1.1!E119) -> 92.998586 | V119: =100*(K119/OBR_MAR24_1.1!N119) -> 93.481076 | W119: =100*(M119/OBR_MAR24_1.1!P119) -> 93.079451 | X119: =100*(O119/OBR_MAR24_1.1!R119) -> 94.902853
B120: 2017-18 | C120: 1351.001 | D120: 390.245 | E120: 383.328 | F120: 58.796 | G120: 1.727 | H120: 2126.301 | I120: 1.959 | J120: 2128.26 | K120: 650.894 | L120: 2779.154 | M120: 679.332 | N120: 0 | O120: 2099.822 | P120: 2073.281 | S120: =100*(C120/OBR_MAR24_1.1!C120) -> 97.068616 | T120: =100*(D120/OBR_MAR24_1.1!D120) -> 95.605637 | U120: =100*(E120/OBR_MAR24_1.1!E120) -> 95.580385 | V120: =100*(K120/OBR_MAR24_1.1!N120) -> 95.693672 | W120: =100*(M120/OBR_MAR24_1.1!P120) -> 96.741862 | X120: =100*(O120/OBR_MAR24_1.1!R120) -> 96.386795
B121: 2018-19 | C121: 1402.695 | D121: 403.105 | E121: 392.489 | F121: 59.888 | G121: 14.068 | H121: 2212.357 | I121: 7.126 | J121: 2219.483 | K121: 684.736 | L121: 2904.219 | M121: 733.787 | N121: 0 | O121: 2170.432 | P121: 2149.137 | S121: =100*(C121/OBR_MAR24_1.1!C121) -> 98.888932 | T121: =100*(D121/OBR_MAR24_1.1!D121) -> 97.474308 | U121: =100*(E121/OBR_MAR24_1.1!E121) -> 98.229074 | V121: =100*(K121/OBR_MAR24_1.1!N121) -> 98.850867 | W121: =100*(M121/OBR_MAR24_1.1!P121) -> 99.139372 | X121: =100*(O121/OBR_MAR24_1.1!R121) -> 98.419168
B122: 2019-20 | C122: 1419.343 | D122: 432.7 | E122: 403.355 | F122: 61.6 | G122: -7.744 | H122: 2247.654 | I122: -6.062 | J122: 2241.592 | K122: 708.194 | L122: 2949.786 | M122: 709.08 | N122: 0 | O122: 2240.706 | P122: 2230.23 | S122: =100*(C122/OBR_MAR24_1.1!C122) -> 100.19123 | T122: =100*(D122/OBR_MAR24_1.1!D122) -> 101.83525 | U122: =100*(E122/OBR_MAR24_1.1!E122) -> 100.45977 | V122: =100*(K122/OBR_MAR24_1.1!N122) -> 100.38484 | W122: =100*(M122/OBR_MAR24_1.1!P122) -> 99.981247 | X122: =100*(O122/OBR_MAR24_1.1!R122) -> 100.73409
... B131: 2028-29 | C131: 2014.0236 | D131: 651.60853 | E131: 531.84159 | F131: 89.765037 | G131: -6.3090037 | H131: 3191.1648 | I131: 2.0184481 | J131: 3193.1832 | K131: 888.30339 | L131: 4081.4866 | M131: 898.63426 | N131: 24.623226 | O131: 3207.4756 | P131: 3153.3615 | S131: =100*(C131/OBR_MAR24_1.1!C131) -> 131.03369 | T131: =100*(D131/OBR_MAR24_1.1!D131) -> 125.57958 | U131: =100*(E131/OBR_MAR24_1.1!E131) -> 122.98416 | V131: =100*(K131/OBR_MAR24_1.1!N131) -> 122.90107 | W131: =100*(M131/OBR_MAR24_1.1!P131) -> 119.95437 | X131: =100*(O131/OBR_MAR24_1.1!R131) -> 129.40843
B132: Definitions:
B133: Household and non-profit institutions serving households final consumption expenditure (ONS Economic Accounts Table 1.1.2, identifier: ABJQ + HAYE)
B134: General government final consumption (ONS Economic Accounts Table 1.1.2, identifier: NMRP)
B135: Total gross fixed capital formation (ONS Economic Accounts Table 1.1.2, identifier: NPQS)
B136: General government investment (ONS Economic Accounts Table 1.1.8, identifier: RPZG)
B137: Net acquisitions of valuables (ONS Economic Accounts Table 1.1.2, identifier: NPJQ)
B138: Final domestic demand is the sum of private consumption, government consumption, fixed investment and net acquisition of valuables
B139: Change in inventories (ONS Economic Accounts Table 1.1.2, identifier: CAEX)
B140: Total domestic demand is the sum of final domestic demand and change in inventories
B141: Total exports (ONS Economic Accounts Table 1.1.2, identifier: IKBH)
B142: Total final expenditure (ONS Economic Accounts Table 1.1.2, identifier: ABMF)
B143: Total imports (ONS Economic Accounts Table 1.1.2, identifier: IKBI)
... B146: Gross national income at market prices (ONS Economic Accounts Table 1.1.1, identifier: ABMZ)

Sheet OBR - Nov23 - T4.13
A1: Back to contents
B2: Table 4.13: Public sector net borrowing: changes since March 2023
C4: £ billion
C5: Outturn | D5: Forecast | E5: 0 | F5: 0 | G5: 0 | H5: 0 | I5: 0
C6: 2022-23 | D6: 2023-24 | E6: 2024-25 | F6: 2025-26 | G6: 2026-27 | H6: 2027-28 | I6: 2028-29
B7: March 2023 forecast | C7: 152.3724 | D7: 131.56568 | E7: 85.397916 | F7: 76.684304 | G7: 63.459509 | H7: 49.258256
B8: November 2023 forecast | C8: 128.266 | D8: 123.90988 | E8: 84.570326 | F8: 76.83564 | G8: 68.405587 | H8: 49.05861 | I8: 35.003998
B9: Difference | C9: -24.106404 | D9: -7.6557978 | E9: -0.82758967 | F9: 0.15133623 | G9: 4.9460783 | H9: -0.19964623
B10: of which:
B11: Underlying differences | D11: -15.785405 | E11: -14.49991 | F11: -14.194092 | G11: -17.203792 | H11: -26.799841
B12: of which:
B13: Receipts | D13: -35.285578 | E13: -47.828252 | F13: -47.781126 | G13: -50.576044 | H13: -58.976223
B14: of which:
B15: Income tax | D15: -9.1813689 | E15: -14.369356 | F15: -16.649604 | G15: -19.136824 | H15: -21.991093
B16: VAT | D16: -11.00941 | E16: -10.995215 | F16: -11.29193 | G16: -14.129677 | H16: -17.29647
B17: Onshore corporation tax | D17: -16.630544 | E17: -14.804216 | F17: -12.754222 | G17: -12.133243 | H17: -13.429391
B18: National insurance contributions | D18: -6.3948332 | E18: -8.9259856 | F18: -9.17716 | G18: -9.917178 | H18: -10.687479
B19: Other receipts | D19: 7.9305779 | E19: 1.2665204 | F19: 2.0917894 | G19: 4.740878 | H19: 4.4282102
B20: Spending | D20: 19.500173 | E20: 33.328342 | F20: 33.587034 | G20: 33.372253 | H20: 32.176381
B21: of which:
B22: Welfare spending | D22: 0.86219488 | E22: 8.0883119 | F22: 16.319932 | G22: 19.195299 | H22: 20.182547
B23: Debt interest spending | D23: 21.749906 | E23: 27.846747 | F23: 23.093265 | G23: 17.451 | H23: 15.117308
B24: Other spending | D24: -3.1119284 | E24: -2.6067169 | F24: -5.8261627 | G24: -3.2740465 | H24: -3.1234737
B25: Direct effect of policy decisions | D25: 8.6595925 | E25: 16.302486 | F25: 17.001633 | G25: 23.026596 | H25: 25.096357 | I25: 17.289845
B26: of which:
B27: National insurance contributions cut | D27: 2.3661522 | E27: 9.9900783 | F27: 10.09817 | G27: 10.157374 | H27: 10.399557 | I27: 10.704058
B28: Capital allowances: full expensing | D28: 0 | E28: 0 | F28: 1.9791954 | G28: 6.892057 | H28: 9.0532562 | I28: 9.1515753
B29: Labour supply measures | D29: 0 | E29: 0.35419455 | F29: 0.68276799 | G29: 0.071426334 | H29: -0.55391898 | I29: -0.93152654
B30: Other receipts decisions | D30: -0.55350193 | E30: 0.59325153 | F30: -2.4792355 | G30: -2.2468389 | H30: -2.0316988 | I30: -2.0248792
B31: Other spending decisions | D31: 6.8469423 | E31: 5.364962 | F31: 6.7207357 | G31: 8.1525776 | H31: 8.2291616 | I31: 0.39061799
B32: Indirect effect of decisions | D32: -0.52998483 | E32: -2.630166 | F32: -2.6562056 | G32: -0.87672602 | H32: 1.503838 | I32: 2.2389896
B33: of which:
B34: Debt interest spending | D34: 0.49409704 | E34: 1.0269607 | F34: 1.9455222 | G34: 2.7262622 | H34: 3.5938173 | I34: 4.463013
B35: Other economic effects | D35: -1.0240819 | E35: -3.6571268 | F35: -4.6017277 | G35: -3.6029882 | H35: -2.0899793 | I35: -2.2240234
B36: Note: This table uses the convention that a negative figure means a reduction in PSNB i.e. an increase in receipts or a reduction in spending will have a negative effect on PSNB. It does not include the effects of changes in our underlying forecasts for environmental levies, VAT refunds or general government depreciation, as each change both receipts and spending by equal amounts and therefore do not change borrowing. We have not included any effects of the SCAPE pensions change within underlying spending (which it decreases) or the direct effects of policy decisions (which it increases) as the change has no effect on overall borrowing. These effects are described in more detail in Box 4.4 and shown in Table 4.14.

Sheet OBR_NOV23_T3.2
A1: Back to contents
B2: Table 3.2: Costing of reductions in the rates of employee and self-employed NICs
C4: £ billion
C5: Forecast
C6: 2023-24 | D6: 2024-25 | E6: 2025-26 | F6: 2026-27 | G6: 2027-28 | H6: 2028-29
B7: Static costing | C7: 2.3594776 | D7: 9.8890471 | E7: 10.082538 | F7: 10.351162 | G7: 10.700065 | H7: 11.087513
B8: Direct behavioural response:
B9: Reduced incentive to incorporate | C9: 0.0066745684 | D9: 0.10103123 | E9: 0.015632086 | F9: -0.19378795 | G9: -0.30050785 | H9: -0.38345548
B10: Post-direct-behavioural costing | C10: 2.3661522 | D10: 9.9900783 | E10: 10.09817 | F10: 10.157374 | G10: 10.399557 | H10: 10.704058
B11: Indirect behavioural response:
B12: Increase in employment and hours worked | C12: -0.13692656 | D12: -0.54424413 | E12: -0.60345177 | F12: -0.61077273 | G12: -0.63664486 | H12: -0.66539104
B13: Post-indirect-behavioural costing | C13: 2.2292256 | D13: 9.4458342 | E13: 9.494718 | F13: 9.5466013 | G13: 9.7629123 | H13: 10.038667

Sheet OBR_NOV23_T3.A
A1: Back to contents
B2: Table 3.A: Latest costings of personal tax threshold measures
D4: £ billion
D5: Forecast
C6: Announcement | D6: 2022-23 | E6: 2023-24 | F6: 2024-25 | G6: 2025-26 | H6: 2026-27 | I6: 2027-28 | J6: 2028-29
B7: Income tax policies
B8: PA and HRT freeze | C8: March 2021 | D8: 2.905 | E8: 13.52 | F8: 23.25 | G8: 28.745 | H8: 29.87 | I8: 30.415 | J8: 31.32
B9: PA and HRT freeze extension | C9: November 2022 | D9: 0 | E9: 0 | F9: 0 | G9: 0 | H9: 1.73 | I9: 3.88 | J9: 4.375
B10: Lowering the additional rate | C10: November 2022 | D10: 0.075 | E10: 0.44 | F10: 0.83 | G10: 0.83 | H10: 0.865 | I10: 0.925 | J10: 0.975
B11: NICs policies
B12: NICs rise in the primary threshold | C12: March 2022 | D12: -6.355 | E12: -4.795 | F12: -2.645 | G12: -1.445 | H12: -1.46 | I12: -1.555 | J12: -1.61
B13: Class 2 NICs | C13: March 2022 | D13: -0.075 | E13: -0.085 | F13: -0.08 | G13: -0.08 | H13: -0.085 | I13: -0.085 | J13: -0.085
B14: NICs threshold freezes (employer) | C14: November 2022 | D14: 0 | E14: 3.315 | F14: 5.68 | G14: 6.975 | H14: 7.605 | I14: 8.245 | J14: 8.475
B15: NICs threshold freezes (employee) | C15: November 2022 | D15: 0 | E15: 0 | F15: 0 | G15: 0 | H15: 0.575 | I15: 1.09 | J15: 1.1
B16: Total | D16: -3.45 | E16: 12.395 | F16: 27.035 | G16: 35.025 | H16: 39.1 | I16: 42.915 | J16: 44.55

Sheet OBR_NOV23_TA.7
A1: Back to contents
B2: Table A.7: Total managed expenditure
C4: £ billion
C5: Outturn | D5: Forecast
C6: 2022-23 | D6: 2023-24 | E6: 2024-25 | F6: 2025-26 | G6: 2026-27 | H6: 2027-28 | I6: 2028-29
B7: Public sector current expenditure (PSCE)
B8: PSCE in RDEL | C8: 411.5361 | D8: 426.51629 | E8: 435.45198 | F8: 445.2619 | G8: 456.91761 | H8: 469.9419 | I8: 483.64675
B9: PSCE in AME | C9: 634.9669 | D9: 662.97387 | E9: 667.08865 | F9: 688.98558 | G9: 713.8149 | H9: 733.02481 | I9: 758.82234
B10: of which:
B11: Welfare spending | C11: 261.47909 | D11: 295.36919 | E11: 316.42806 | F11: 333.90157 | G11: 343.16005 | H11: 350.86962 | I11: 361.68412
B12: Locally financed current expenditure | C12: 60.346917 | D12: 62.207691 | E12: 63.778229 | F12: 66.255645 | G12: 69.335173 | H12: 72.128506 | I12: 75.287812
B13: Central government debt interest, net of APF1 | C13: 111.20812 | D13: 116.22229 | E13: 106.17499 | F13: 101.89327 | G13: 108.84889 | H13: 115.1656 | I13: 122.48093
B14: Scottish Government's current spending | C14: 39.586038 | D14: 42.030645 | E14: 43.521798 | F14: 44.891365 | G14: 45.940014 | H14: 47.173894 | I14: 48.799638
B15: EU financial settlement | C15: 8.8096667 | D15: 7.7611439 | E15: 0.84577798 | F15: 0.76194184 | G15: 0.46893936 | H15: 0.35241557 | I15: 0.76366702
B16: Unfunded public service pensions | C16: 3.6085466 | D16: 5.5954102 | E16: 3.1840667 | F16: 4.1450654 | G16: 3.2702939 | H16: 2.3657091 | I16: 0.80981287
B17: Company and other tax credits | C17: 9.2172946 | D17: 10.06353 | E17: 10.338588 | F17: 10.456469 | G17: 10.69962 | H17: 11.02155 | I17: 11.194049
B18: BBC current expenditure | C18: 4.2258646 | D18: 4.2019715 | E18: 4.3593487 | F18: 4.3736451 | G18: 4.6555976 | H18: 4.6323025 | I18: 4.6833085
B19: National Lottery current grants | C19: 1.28536 | D19: 1.387704 | E19: 1.595109 | F19: 1.607932 | G19: 1.479318 | H19: 1.402302 | I19: 1.408294
B20: General government imputed pensions | C20: 3.3853899 | D20: 1.6944179 | E20: 1.7547382 | F20: 1.7991861 | G20: 1.8532571 | H20: 1.9139111 | I20: 1.9772928
B21: Public corporations' debt interest | C21: 0.539 | D21: 0.528 | E21: 0.528 | F21: 0.528 | G21: 0.528 | H21: 0.528 | I21: 0.528
B22: Non-domestic energy support | C22: 6.663 | D22: 0.552 | E22: 0 | F22: 0 | G22: 0 | H22: 0 | I22: 0
... B30: Total public sector current expenditure | C30: 1046.503 | D30: 1089.4902 | E30: 1102.5406 | F30: 1134.2475 | G30: 1170.7325 | H30: 1202.9667 | I30: 1242.4691
B31: Public sector gross investment (PSGI)
B32: PSGI in CDEL | C32: 89.791733 | D32: 96.000288 | E32: 99.196273 | F32: 97.221725 | G32: 97.50902 | H32: 97.597216 | I32: 97.357557
B33: PSGI in AME | C33: 15.130267 | D33: 36.842212 | E33: 35.019618 | F33: 33.05696 | G33: 33.067782 | H33: 33.000513 | I33: 33.210587
B34: of which:
B35: Locally financed capital expenditure | C35: 8.9063424 | D35: 8.0009834 | E35: 7.7546753 | F35: 7.6208402 | G35: 7.5367127 | H35: 7.5805601 | I35: 7.6676734
B36: Public corporations' capital expenditure | C36: 11.217757 | D36: 10.965825 | E36: 11.529719 | F36: 11.833013 | G36: 11.953604 | H36: 12.038981 | I36: 12.139002
B37: Student loans | C37: 0.488 | D37: 10.399782 | E37: 9.1567832 | F37: 7.9688424 | G37: 7.2013316 | H37: 7.17412 | I37: 7.2242776
B38: Funded public sector pension schemes | C38: -4.854 | D38: 0.71152891 | E38: 0.71152891 | F38: 0.71152891 | G38: 0.71152891 | H38: 0.71152891 | I38: 0.71152891
B39: Scottish Government's capital spending | C39: 4.569481 | D39: 5.3680799 | E39: 5.2630167 | F39: 5.1607518 | G39: 5.154036 | H39: 5.1460268 | I39: 5.1238011
B40: Tax litigation | C40: 0 | D40: 0.8235 | E40: 1.203396 | F40: 0.63406325 | G40: 0.63406325 | H40: 0.63406325 | I40: 0.63406325
B41: Other PSGI items in AME | C41: 0.3897293 | D41: 1.4051943 | E41: 0.95227045 | F41: 0.91446001 | G41: 0.8307078 | H41: 0.67033175 | I41: 0.60671338
B42: Other National Accounts adjustments | C42: -5.5870428 | D42: -0.83268205 | E42: -1.5517716 | F42: -1.78654 | G42: -0.95420291 | H42: -0.95509948 | I42: -0.89647224
B43: Total public sector gross investment | C43: 104.922 | D43: 132.8425 | E43: 134.21589 | F43: 130.27869 | G43: 130.5768 | H43: 130.59773 | I43: 130.56814
B44: Less public sector depreciation | C44: -57.23 | D44: -61.200498 | E44: -64.313705 | F44: -66.657309 | G44: -69.002934 | H44: -71.467377 | I44: -73.760378
B45: Public sector net investment | C45: 47.692 | D45: 71.642002 | E45: 69.902186 | F45: 63.621376 | G45: 61.573868 | H45: 59.130352 | I45: 56.807767
B46: Total managed expenditure | C46: 1151.425 | D46: 1222.3327 | E46: 1236.7565 | F46: 1264.5262 | G46: 1301.3093 | H46: 1333.5644 | I46: 1373.0372
B47: 1 Includes increases in debt interest payments due to the APF.

Sheet OBR_NOV23_T4.7
A1: Back to contents
B2: Table 4.7: Departmental resource spending: changes since March 2023
C4: £ billion
C5: Outturn | D5: Forecast
C6: 2022-23 | D6: 2023-24 | E6: 2024-25 | F6: 2025-26 | G6: 2026-27 | H6: 2027-28 | I6: 2028-29
B7: March 2023 forecast
B8: Limits | C8: 420.15245 | D8: 425.4426 | E8: 430.47265 | F8: 439.39675 | G8: 449.49646 | H8: 462.04931
B9: Assumed underspend | C9: -8.6163428 | D9: -3.7552079 | E9: -3.816302 | F9: -3.5510896 | G9: -3.3459442 | H9: -3.1316577
B10: Actual spending | C10: 411.5361 | D10: 421.6874 | E10: 426.65635 | F10: 435.84566 | G10: 446.15051 | H10: 458.91766
B11: November 2023 forecast (excluding SCAPE)
B12: Limits | C12: 420.15245 | D12: 429.38316 | E12: 433.03271 | F12: 439.86059 | G12: 451.322 | H12: 464.1614 | I12: 477.64559
B13: Assumed underspend | C13: -8.6163428 | D13: -2.8668699 | E13: -2.9261304 | F13: 0 | G13: 0 | H13: 0 | I13: 0
B14: Actual spending | C14: 411.5361 | D14: 426.51629 | E14: 430.10658 | F14: 439.86059 | G14: 451.322 | H14: 464.1614 | I14: 477.64559
B15: Difference
B16: Limits | D16: 3.94056 | E16: 2.5600597 | F16: 0.4638403 | G16: 1.825548 | H16: 2.1120863
B17: of which:
B18: Pay measures | D18: 4.357782 | E18: 1.42 | F18: 1.245 | G18: 1.15 | H18: 1.14
B19: Labour supply measures | D19: 0 | E19: 0.33569112 | F19: 0.8211444 | G19: 0.66747214 | H19: 0.53294257
B20: Business rates measures | D20: 0.016357787 | E20: 1.9366578 | F20: -0.31041431 | G20: -0.28386959 | H20: -0.28785448
B21: Post-Spending Review update | D21: 0 | E21: 0 | F21: 1.7632349 | G21: 3.1077002 | H21: 3.2798002
B22: Change due to underspend | D22: 0 | E22: 0 | F22: -3.5510896 | G22: -3.3459442 | H22: -3.1316577
B23: Rail subsidies reclassification | D23: -1.748377 | E23: -1.008339 | F23: 0 | G23: 0 | H23: 0
B24: Other | D24: 1.3147973 | E24: -0.12395021 | F24: 0.49596496 | G24: 0.5301894 | H24: 0.57885574
B25: Assumed underspend | D25: 0.88833808 | E25: 0.89017161 | F25: 3.5510896 | G25: 3.3459442 | H25: 3.1316577
B26: Actual spending | D26: 4.8288981 | E26: 3.4502313 | F26: 4.0149299 | G26: 5.1714921 | H26: 5.243744
B27: Memo: DEL funding for SCAPE rate change | D27: 0 | E27: 5.3453969 | F27: 5.4013125 | G27: 5.5956087 | H27: 5.7805005 | I27: 6.0011695
B28: November 2023 forecast inc SCAPE | D28: 426.51629 | E28: 435.45198 | F28: 445.2619 | G28: 456.91761 | H28: 469.9419 | I28: 483.64675

Sheet OBR_NOV23_T4.8
A1: Back to contents
B2: Table 4.8: Departmental capital spending: changes since March 2023
C4: £ billion
C5: Outturn | D5: Forecast
C6: 2022-23 | D6: 2023-24 | E6: 2024-25 | F6: 2025-26 | G6: 2026-27 | H6: 2027-28 | I6: 2028-29
B7: March 2023 forecast
B8: Limits | C8: 95.190651 | D8: 105.03452 | E8: 105.1718 | F8: 104.86564 | G8: 104.71854 | H8: 104.12457
B9: Assumed underspend | C9: -5.3989177 | D9: -8.9228712 | E9: -8.2828263 | F9: -7.7868864 | G9: -7.23909 | H9: -6.4971457
B10: Actual spending | C10: 89.791733 | D10: 96.111651 | E10: 96.888973 | F10: 97.078752 | G10: 97.479447 | H10: 97.627423
B11: November 2023 forecast
B12: Limits | C12: 95.190651 | D12: 104.92376 | E12: 105.58611 | F12: 97.221725 | G12: 97.50902 | H12: 97.597216 | I12: 97.357557
B13: Assumed underspend | C13: -5.3989177 | D13: -8.9234712 | E13: -6.3898335 | F13: 0 | G13: 0 | H13: 0 | I13: 0
B14: Actual spending | C14: 89.791733 | D14: 96.000288 | E14: 99.196273 | F14: 97.221725 | G14: 97.50902 | H14: 97.597216 | I14: 97.357557
B15: Difference
B16: Limits | D16: -0.11076287 | E16: 0.41430669 | F16: -7.6439134 | G16: -7.209517 | H16: -6.5273527
B17: of which:
B18: Policies | D18: 0.97541598 | E18: 2.6840674 | F18: 0.142973 | G18: 0.029573 | H18: -0.030207
B19: Change due to underspend | D19: 0 | E19: 0 | F19: -7.7868864 | G19: -7.23909 | H19: -6.4971457
B20: Other | D20: -1.0861789 | E20: -2.2697607 | F20: 0 | G20: 0 | H20: -1.8651747e-14
B21: Assumed underspend | D21: -0.0006 | E21: 1.8929928 | F21: 7.7868864 | G21: 7.23909 | H21: 6.4971457
B22: Actual spending | D22: -0.11136287 | E22: 2.3072995 | F22: 0.142973 | G22: 0.029573 | H22: -0.030207

Sheet OBR_NOV23_1.1
A1: Back to contents
B2: 1.1 GDP expenditure components (£ billion chain-linked volumes, seasonally adjusted)
C3: Private consumption | D3: Government consumption | E3: Fixed investment | J3: Net acquisition of valuables | K3: Final domestic demand | L3: Change in inventories | M3: Total domestic demand | N3: Exports | O3: Total final expenditure | P3: Imports | Q3: Statistical discrepancy | R3: Real GDP | S3: Non-oil GVA
E4: of which: | F4: Business investment | G4: Private dwellings | H4: General government | I4: Public corps dwellings
B5: 2008Q1 | C5: 308.104 | D5: 93.323 | E5: 84.847 | F5: 45.209 | G5: 24.954 | H5: 13.732 | I5: 1.494 | J5: 0.253 | K5: 486.527 | L5: -2.688 | M5: 483.839 | N5: 140.286 | O5: 626.489 | P5: 137.103 | Q5: 0 | R5: 489.783 | S5: 426.405
B6: 2008Q2 | C6: 304.494 | D6: 92.738 | E6: 85.799 | F6: 46.925 | G6: 23.782 | H6: 14.129 | I6: 1.45 | J6: -0.422 | K6: 482.609 | L6: -1.231 | M6: 481.378 | N6: 140.305 | O6: 623.241 | P6: 136.253 | Q6: 0 | R6: 487.386 | S6: 424.841
B7: 2008Q3 | C7: 299.633 | D7: 94.397 | E7: 81.323 | F7: 45.148 | G7: 19.58 | H7: 14.145 | I7: 2.775 | J7: -0.984 | K7: 474.369 | L7: -3.213 | M7: 471.156 | N7: 140.846 | O7: 613.272 | P7: 133.811 | Q7: 0 | R7: 479.872 | S7: 418.251
B8: 2008Q4 | C8: 292.373 | D8: 95.402 | E8: 79.978 | F8: 43.617 | G8: 18.727 | H8: 15.192 | I8: 2.722 | J8: 0.11 | K8: 467.863 | L8: -5.656 | M8: 462.207 | N8: 135.424 | O8: 596.031 | P8: 126.724 | Q8: 0 | R8: 469.694 | S8: 409.321
B9: 2009Q1 | C9: 291.284 | D9: 94.802 | E9: 75.261 | F9: 39.697 | G9: 17.619 | H9: 15.489 | I9: 2.681 | J9: 1.308 | K9: 462.655 | L9: -9.394 | M9: 453.261 | N9: 126.723 | O9: 581.258 | P9: 121.718 | Q9: 0 | R9: 460.105 | S9: 401.251
B10: 2009Q2 | C10: 291.11 | D10: 94.564 | E10: 72.063 | F10: 37.614 | G10: 17.124 | H10: 14.824 | I10: 2.644 | J10: 0.617 | K10: 458.354 | L10: -8.962 | M10: 449.392 | N10: 125.42 | O10: 580.028 | P10: 122.009 | Q10: 0 | R10: 458.599 | S10: 399.499
B11: 2009Q3 | C11: 292.732 | D11: 95.362 | E11: 72.551 | F11: 36.801 | G11: 17.177 | H11: 16.069 | I11: 2.675 | J11: 1.036 | K11: 461.681 | L11: -9.269 | M11: 452.412 | N11: 124.828 | O11: 583.709 | P11: 125.311 | Q11: 0 | R11: 458.875 | S11: 400.202
B12: 2009Q4 | C12: 294.909 | D12: 96.11 | E12: 71.335 | F12: 36.482 | G12: 16.394 | H12: 15.851 | I12: 2.728 | J12: -0.228 | K12: 462.126 | L12: -7.406 | M12: 454.72 | N12: 130.663 | O12: 587.166 | P12: 127.35 | Q12: 0 | R12: 460.238 | S12: 401.681
B13: 2010Q1 | C13: 293.465 | D13: 94.805 | E13: 75.138 | F13: 38.204 | G13: 17.617 | H13: 16.792 | I13: 2.709 | J13: -0.366 | K13: 463.042 | L13: -2.196 | M13: 460.846 | N13: 130.582 | O13: 593.834 | P13: 129.677 | Q13: 0 | R13: 464.543 | S13: 405.884
B14: 2010Q2 | C14: 300.592 | D14: 95.123 | E14: 74.022 | F14: 37.63 | G14: 18.596 | H14: 15.355 | I14: 2.698 | J14: -0.577 | K14: 469.16 | L14: -1.663 | M14: 467.497 | N14: 134.894 | O14: 603.085 | P14: 133.785 | Q14: 0 | R14: 469.606 | S14: 410.793
B15: 2010Q3 | C15: 300.841 | D15: 95.137 | E15: 76.899 | F15: 39.313 | G15: 19.56 | H15: 15.628 | I15: 2.678 | J15: 0.524 | K15: 473.401 | L15: -0.658 | M15: 472.743 | N15: 136.309 | O15: 610.106 | P15: 138.104 | Q15: 0 | R15: 472.199 | S15: 413.478
B16: 2010Q4 | C16: 300.342 | D16: 95.696 | E16: 78.973 | F16: 41.914 | G16: 19.064 | H16: 15.547 | I16: 2.618 | J16: 0.418 | K16: 475.429 | L16: -4.046 | M16: 471.383 | N16: 139.076 | O16: 611.773 | P16: 139.318 | Q16: 0 | R16: 472.612 | S16: 414.371
... B40: 2016Q4 | C40: 342.261 | D40: 101.092 | E40: 97.427 | F40: 56.045 | G40: 25.056 | H40: 13.886 | I40: 2.447 | J40: -1.924 | K40: 538.856 | L40: 2.783 | M40: 541.639 | N40: 160.974 | O40: 701.262 | P40: 169.132 | Q40: 0 | R40: 532.082 | S40: 471.394
B41: 2017Q1 | C41: 344.698 | D41: 101.335 | E41: 99.077 | F41: 57.345 | G41: 25.297 | H41: 13.963 | I41: 2.474 | J41: -0.493 | K41: 544.617 | L41: 5.107 | M41: 549.724 | N41: 163.631 | O41: 707.728 | P41: 171.129 | Q41: 0 | R41: 536.566 | S41: 475.48 | U41: =D41*1000 -> 101335 | V41: =H41*1000 -> 13963
B42: 2017Q2 | C42: 344.758 | D42: 101.859 | E42: 100.304 | F42: 57.03 | G42: 24.944 | H42: 15.742 | I42: 2.576 | J42: 0.203 | K42: 547.124 | L42: 6.2 | M42: 553.324 | N42: 168.016 | O42: 715.658 | P42: 175.707 | Q42: 0 | R42: 540.02 | S42: 478.45 | U42: =D42*1000 -> 101859 | V42: =H42*1000 -> 15742
B43: 2017Q3 | C43: 347.006 | D43: 102.258 | E43: 99.419 | F43: 56.048 | G43: 25.459 | H43: 15.337 | I43: 2.562 | J43: 0.017 | K43: 548.7 | L43: 1.73 | M43: 550.43 | N43: 172.089 | O43: 719.947 | P43: 176.567 | Q43: 0 | R43: 543.452 | S43: 481.044 | U43: =D43*1000 -> 102258 | V43: =H43*1000 -> 15337
B44: 2017Q4 | C44: 348.916 | D44: 102.18 | E44: 100.952 | F44: 57.022 | G44: 26.453 | H44: 15.47 | I44: 2 | J44: 0.879 | K44: 552.927 | L44: 0.27 | M44: 553.197 | N44: 168.382 | O44: 720.772 | P44: 173.358 | Q44: 0 | R44: 547.377 | S44: 484.08 | U44: =D44*1000 -> 102180 | V44: =H44*1000 -> 15470
B45: 2018Q1 | C45: 351.12 | D45: 101.885 | E45: 100.378 | F45: 56.689 | G45: 26.63 | H45: 15.693 | I45: 1.389 | J45: 0.497 | K45: 553.88 | L45: -0.761 | M45: 553.119 | N45: 171.698 | O45: 724.271 | P45: 176.579 | Q45: 0 | R45: 547.688 | S45: 484.211 | U45: =D45*1000 -> 101885 | V45: =H45*1000 -> 15693
B46: 2018Q2 | C46: 350.706 | D46: 101.964 | E46: 99.211 | F46: 55.519 | G46: 27.801 | H46: 14.55 | I46: 1.369 | J46: 1.223 | K46: 553.104 | L46: 3.242 | M46: 556.346 | N46: 172.688 | O46: 726.363 | P46: 177.776 | Q46: 0 | R46: 548.6 | S46: 484.943 | U46: =D46*1000 -> 101964 | V46: =H46*1000 -> 14550
B47: 2018Q3 | C47: 353.468 | D47: 102.537 | E47: 99.191 | F47: 55.578 | G47: 27.063 | H47: 15.198 | I47: 1.351 | J47: 1.09 | K47: 556.286 | L47: -2.465 | M47: 553.821 | N47: 174.981 | O47: 729.075 | P47: 178.674 | Q47: 0 | R47: 550.425 | S47: 486.833 | U47: =D47*1000 -> 102537 | V47: =H47*1000 -> 15198
B48: 2018Q4 | C48: 357.306 | D48: 103.785 | E48: 99.058 | F48: 55.984 | G48: 26.766 | H48: 15.07 | I48: 1.238 | J48: 0.327 | K48: 560.476 | L48: 0.925 | M48: 561.401 | N48: 173.493 | O48: 736.431 | P48: 185.318 | Q48: 0 | R48: 551.128 | S48: 487.506 | U48: =D48*1000 -> 103785 | V48: =H48*1000 -> 15070
B49: 2019Q1 | C49: 356.975 | D49: 105.264 | E49: 102.105 | F49: 56.579 | G49: 27.784 | H49: 16.349 | I49: 1.4124693 | J49: 12.051 | K49: 576.395 | L49: 6.724 | M49: 583.119 | N49: 171.534 | O49: 753.597 | P49: 198.389 | Q49: 0 | R49: 555.141 | S49: 491.237 | U49: =D49*1000 -> 105264 | V49: =H49*1000 -> 16349
B50: 2019Q2 | C50: 357.952 | D50: 107.139 | E50: 101.275 | F50: 57.469 | G50: 27.184 | H50: 15.196 | I50: 1.4153618 | J50: 1.776 | K50: 568.142 | L50: -3.714 | M50: 564.428 | N50: 169.396 | O50: 736.856 | P50: 179.954 | Q50: 0 | R50: 556.932 | S50: 492.94 | U50: =D50*1000 -> 107139 | V50: =H50*1000 -> 15196
B51: 2019Q3 | C51: 357.25 | D51: 106.851 | E51: 102.1 | F51: 57.24 | G51: 28.12 | H51: 15.266 | I51: 1.449035 | J51: 1.024 | K51: 567.225 | L51: -1.014 | M51: 566.211 | N51: 179.408 | O51: 743.601 | P51: 182.622 | Q51: 0 | R51: 560.987 | S51: 496.984 | U51: =D51*1000 -> 106851 | V51: =H51*1000 -> 15266
B52: 2019Q4 | C52: 355.763 | D52: 107.338 | E52: 100.943 | F52: 57.293 | G52: 26.821 | H52: 15.329 | I52: 1.4667325 | J52: -11.971 | K52: 552.073 | L52: -0.734 | M52: 551.339 | N52: 186.358 | O52: 737.739 | P52: 176.907 | Q52: 0 | R52: 560.861 | S52: 497.031 | U52: =D52*1000 -> 107338 | V52: =H52*1000 -> 15329
... B89: 2029Q1 | C89: 382.50506 | D89: 130.86273 | E89: 107.45163 | F89: 60.357372 | G89: 28.674677 | H89: 16.778488 | I89: 1.6410895 | J89: -1.59175 | K89: 619.22767 | L89: 1.3880982 | M89: 620.61577 | N89: 178.52035 | O89: 799.13612 | P89: 184.02832 | Q89: 7.677 | R89: 622.7848 | S89: 554.48151 | U89: =D89*1000 -> 130862.73 | V89: =H89*1000 -> 16778.488
B90: 2008 | C90: 1204.604 | D90: 375.86 | E90: 331.947 | F90: 180.899 | G90: 87.043 | H90: 57.198 | I90: 8.441 | J90: -1.043 | K90: 1911.368 | L90: -12.788 | M90: 1898.58 | N90: 556.861 | O90: 2459.033 | P90: 533.891 | Q90: 0 | R90: 1926.735 | S90: 1678.818
B91: 2009 | C91: 1170.035 | D91: 380.838 | E91: 291.21 | F91: 150.594 | G91: 68.314 | H91: 62.233 | I91: 10.728 | J91: 2.733 | K91: 1844.816 | L91: -35.031 | M91: 1809.785 | N91: 507.634 | O91: 2332.161 | P91: 496.388 | Q91: 0 | R91: 1837.817 | S91: 1602.633
B92: 2010 | C92: 1195.24 | D92: 380.761 | E92: 305.032 | F92: 157.061 | G92: 74.837 | H92: 63.322 | I92: 10.703 | J92: -0.001 | K92: 1881.032 | L92: -8.563 | M92: 1872.469 | N92: 540.861 | O92: 2418.798 | P92: 540.884 | Q92: 0 | R92: 1878.96 | S92: 1644.526
B93: 2011 | C93: 1191.27 | D93: 380.515 | E93: 305.354 | F93: 166.465 | G93: 71.386 | H93: 57.955 | I93: 9.969 | J93: -0.705 | K93: 1876.434 | L93: -3.784 | M93: 1872.65 | N93: 578.333 | O93: 2456.555 | P93: 556.723 | Q93: 0 | R93: 1900.476 | S93: 1672.213
B94: 2012 | C94: 1211.807 | D94: 386.188 | E94: 310.222 | F94: 178.179 | G94: 69.926 | H94: 53.007 | I94: 9.042 | J94: -1.036 | K94: 1907.181 | L94: 6.378 | M94: 1913.559 | N94: 582.729 | O94: 2499.35 | P94: 570.385 | Q94: 0 | R94: 1929.229 | S94: 1706.911
B95: 2013 | C95: 1242.448 | D95: 387.05 | E95: 320.303 | F95: 184.651 | G95: 77.388 | H95: 49.603 | I95: 8.512 | J95: 7.022 | K95: 1956.823 | L95: 6.784 | M95: 1963.607 | N95: 584.387 | O95: 2552.855 | P95: 588.884 | Q95: 0 | R95: 1963.807 | S95: 1740.343
B96: 2014 | C96: 1276.097 | D96: 397.069 | E96: 342.84 | F96: 194.883 | G96: 82.424 | H96: 55.58 | I96: 9.862 | J96: 6.071 | K96: 2022.077 | L96: 15.349 | M96: 2037.426 | N96: 590.26 | O96: 2646.112 | P96: 618.888 | Q96: 0 | R96: 2026.566 | S96: 1797.211
B97: 2015 | C97: 1312.213 | D97: 402.148 | E97: 367.34 | F97: 213.281 | G97: 87.743 | H97: 56.548 | I97: 9.646 | J97: 0.393 | K97: 2082.094 | L97: 12.105 | M97: 2094.199 | N97: 612.533 | O97: 2721.787 | P97: 649.558 | Q97: 0 | R97: 2071.561 | S97: 1831.364
B98: 2016 | C98: 1360.504 | D98: 404.984 | E98: 386.225 | F98: 227.965 | G98: 93.928 | H98: 54.579 | I98: 9.742 | J98: 1.599 | K98: 2153.312 | L98: 5.036 | M98: 2158.348 | N98: 629.527 | O98: 2786.771 | P98: 675.388 | Q98: 0 | R98: 2111.357 | S98: 1867.008
B99: 2017 | C99: 1385.378 | D99: 407.632 | E99: 399.752 | F99: 227.445 | G99: 102.153 | H99: 60.512 | I99: 9.612 | J99: 0.606 | K99: 2193.368 | L99: 13.307 | M99: 2206.675 | N99: 672.118 | O99: 2864.105 | P99: 696.761 | Q99: 0 | R99: 2167.415 | S99: 1919.054
B100: 2018 | C100: 1412.6 | D100: 410.171 | E100: 397.838 | F100: 223.77 | G100: 108.26 | H100: 60.511 | I100: 5.347 | J100: 3.137 | K100: 2223.746 | L100: 0.941 | M100: 2224.687 | N100: 692.86 | O100: 2916.14 | P100: 718.347 | Q100: 0 | R100: 2197.841 | S100: 1943.493
B101: 2019 | C101: 1427.94 | D101: 426.592 | E101: 406.423 | F101: 228.581 | G101: 109.909 | H101: 62.14 | I101: 5.7435985 | J101: 2.88 | K101: 2263.835 | L101: 1.262 | M101: 2265.097 | N101: 706.696 | O101: 2971.793 | P101: 737.872 | Q101: 0 | R101: 2233.921 | S101: 1978.192
... B110: 2028 | C110: 1511.8087 | D110: 518.17504 | E110: 427.18384 | F110: 240.89732 | G110: 111.8335 | H110: 68.04975 | I110: 6.4032704 | J110: -6.367 | K110: 2450.8005 | L110: 4.8033498 | M110: 2455.6039 | N110: 711.81774 | O110: 3167.4216 | P110: 731.99986 | Q110: 30.708 | R110: 2466.1298 | S110: 2195.1629
B111: 2008-09 | C111: 1187.784 | D111: 377.339 | E111: 322.361 | F111: 175.387 | G111: 79.708 | H111: 58.955 | I111: 9.628 | J111: 0.012 | K111: 1887.496 | L111: -19.494 | M111: 1868.002 | N111: 543.298 | O111: 2413.802 | P111: 518.506 | Q111: 0 | R111: 1897.057 | S111: 1653.664
B112: 2009-10 | C112: 1172.216 | D112: 380.841 | E112: 291.087 | F112: 149.101 | G112: 68.312 | H112: 63.536 | I112: 10.756 | J112: 1.059 | K112: 1845.203 | L112: -27.833 | M112: 1817.37 | N112: 511.493 | O112: 2344.737 | P112: 504.347 | Q112: 0 | R112: 1842.255 | S112: 1607.266
B113: 2010-11 | C113: 1199.499 | D113: 382.218 | E113: 305.816 | F113: 157.857 | G113: 75.328 | H113: 62.987 | I113: 10.618 | J113: -1.944 | K113: 1885.589 | L113: -8.626 | M113: 1876.963 | N113: 555.074 | O113: 2434.524 | P113: 547.238 | Q113: 0 | R113: 1888.236 | S113: 1654.774
B114: 2011-12 | C114: 1192.115 | D114: 382.481 | E114: 308.087 | F114: 172.739 | G114: 70.143 | H114: 55.594 | I114: 9.64 | J114: -0.36 | K114: 1882.323 | L114: -6.242 | M114: 1876.081 | N114: 583.603 | O114: 2469.395 | P114: 562.558 | Q114: 0 | R114: 1907.289 | S114: 1680.39
B115: 2012-13 | C115: 1219.509 | D115: 383.864 | E115: 308.262 | F115: 177.636 | G115: 71.051 | H115: 50.724 | I115: 8.845 | J115: 1.689 | K115: 1913.324 | L115: 12.249 | M115: 1925.573 | N115: 578.781 | O115: 2503.373 | P115: 569.73 | Q115: 0 | R115: 1934.006 | S115: 1713.037
B116: 2013-14 | C116: 1251.056 | D116: 389.959 | E116: 328.218 | F116: 187.917 | G116: 79.759 | H116: 51.897 | I116: 8.542 | J116: 7.843 | K116: 1977.076 | L116: 4.264 | M116: 1981.34 | N116: 582.917 | O116: 2576.023 | P116: 596.666 | Q116: 0 | R116: 1978.95 | S116: 1753.086
B117: 2014-15 | C117: 1286.09 | D117: 397.794 | E117: 349.357 | F117: 200.346 | G117: 82.466 | H117: 56.077 | I117: 10.342 | J117: 7.428 | K117: 2040.669 | L117: 21.859 | M117: 2062.528 | N117: 596.564 | O117: 2674.223 | P117: 633.483 | Q117: 0 | R117: 2039.864 | S117: 1809.444
B118: 2015-16 | C118: 1323.968 | D118: 403.76 | E118: 371.051 | F118: 216.768 | G118: 89.667 | H118: 55.113 | I118: 9.42 | J118: -1.311 | K118: 2097.468 | L118: 7.486 | M118: 2104.954 | N118: 616.107 | O118: 2733.568 | P118: 651.515 | Q118: 0 | R118: 2081.524 | S118: 1838.471
B119: 2016-17 | C119: 1368.575 | D119: 405.169 | E119: 390.464 | F119: 228.363 | G119: 96.898 | H119: 55.373 | I119: 9.834 | J119: -0.129 | K119: 2164.079 | L119: 9.618 | M119: 2173.697 | N119: 638.633 | O119: 2805.016 | P119: 680.972 | Q119: 0 | R119: 2124.11 | S119: 1879.97
B120: 2017-18 | C120: 1391.8 | D120: 408.182 | E120: 401.053 | F120: 226.789 | G120: 103.486 | H120: 62.242 | I120: 8.527 | J120: 1.596 | K120: 2202.631 | L120: 7.439 | M120: 2210.07 | N120: 680.185 | O120: 2880.648 | P120: 702.211 | Q120: 0 | R120: 2178.537 | S120: 1927.785
B121: 2018-19 | C121: 1418.455 | D121: 413.55 | E121: 399.565 | F121: 223.66 | G121: 109.414 | H121: 61.167 | I121: 5.3704693 | J121: 14.691 | K121: 2246.261 | L121: 8.426 | M121: 2254.687 | N121: 692.696 | O121: 2945.466 | P121: 740.157 | Q121: 0 | R121: 2205.294 | S121: 1950.519
B122: 2019-20 | C122: 1416.634 | D122: 424.902 | E122: 401.509 | F122: 227.994 | G122: 107.276 | H122: 60.56 | I122: 5.6087288 | J122: -8.545 | K122: 2234.5 | L122: -7.512 | M122: 2226.988 | N122: 705.479 | O122: 2933.523 | P122: 709.213 | Q122: 0 | R122: 2224.377 | S122: 1971.447
... B131: 2028-29 | C131: 1519.075 | D131: 520.28338 | E131: 428.23221 | F131: 241.16097 | G131: 112.94875 | H131: 67.65686 | I131: 6.4656249 | J131: -6.367 | K131: 2461.2236 | L131: 5.0936937 | M131: 2466.3173 | N131: 712.75893 | O131: 3179.0762 | P131: 733.53489 | Q131: 30.708 | R131: 2476.2493 | S131: 2204.3738
B132: Definitions:
B133: Household and non-profit institutions serving households final consumption expenditure (ONS Economic Accounts Table 1.1.2, identifier: ABJR + HAYO)
B134: General government final consumption (ONS Economic Accounts Table 1.1.2, identifier: NMRY)
B135: Total gross fixed capital formation (ONS Economic Accounts Table 1.1.2, identifier: NPQT)
B136: Business investment (ONS Economic Accounts Table 1.1.8, identifier: NPEL)
B137: Private sector investment in dwellings, including transfer costs (ONS Economic Accounts Table 1.1.8, identifier: L636 + L637)
B138: General government gross fixed capital formation (ONS Economic Accounts Table 1.1.8, identifier: DLWF)
B139: Public corporations investment in dwellings, including transfer costs (ONS Economic Accounts Table 1.1.8, identifier: L634 + L635)
B140: Net acquisitions of valuables (ONS Economic Accounts Table 1.1.2, identifier: NPJR)
B141: Final domestic demand is the sum of private consumption, government consumption, fixed investment and net acquisition of valuables
B142: Change in inventories (ONS Economic Accounts Table 1.1.2, identifier: CAFU)
B143: Total domestic demand is the sum of final domestic demand and change in inventories
... B148: Gross domestic product at market prices (ONS Economic Accounts Table 1.1.2, identifier: ABMI)

Sheet OBR_NOV23_1.2
A1: Back to contents
B2: 1.2 GDP expenditure components (£ billion current prices, seasonally adjusted) | S2: Deflators
C3: Private consumption | D3: Government consumption | E3: Fixed investment | G3: Net acquisition of valuables | H3: Final domestic demand | I3: Change in inventories | J3: Total domestic demand | K3: Exports | L3: Total final expenditure | M3: Imports | N3: Statistical discrepancy | O3: GDP at market prices | P3: Gross national income | S3: C | T3: GC | U3: IF | V3: X | W3: M | X3: GDP | Z3: C | AA3: GC | AB3: IF | AC3: X | AD3: M | AE3: GDP
E4: of which: | F4: General government
B5: 2008Q1 | C5: 255.438 | D5: 80.007 | E5: 71.229 | F5: 12.058 | G5: 0.277 | H5: 406.951 | I5: -0.163 | J5: 406.788 | K5: 104.955 | L5: 511.743 | M5: 114.195 | N5: 0 | O5: 397.548 | P5: 396.936 | S5: =100*(C5/OBR_NOV23_1.1!C5) -> 82.906421 | T5: =100*(D5/OBR_NOV23_1.1!D5) -> 85.731277 | U5: =100*(E5/OBR_NOV23_1.1!E5) -> 83.949933 | V5: =100*(K5/OBR_NOV23_1.1!N5) -> 74.815021 | W5: =100*(M5/OBR_NOV23_1.1!P5) -> 83.291394 | X5: =100*(O5/OBR_NOV23_1.1!R5) -> 81.168191
B6: 2008Q2 | C6: 256.141 | D6: 80.199 | E6: 72.373 | F6: 11.633 | G6: -0.087 | H6: 408.626 | I6: 0.83 | J6: 409.456 | K6: 110.409 | L6: 519.865 | M6: 118.984 | N6: 0 | O6: 400.881 | P6: 396.091 | S6: =100*(C6/OBR_NOV23_1.1!C6) -> 84.120213 | T6: =100*(D6/OBR_NOV23_1.1!D6) -> 86.479113 | U6: =100*(E6/OBR_NOV23_1.1!E6) -> 84.351799 | V6: =100*(K6/OBR_NOV23_1.1!N6) -> 78.692135 | W6: =100*(M6/OBR_NOV23_1.1!P6) -> 87.325784 | X6: =100*(O6/OBR_NOV23_1.1!R6) -> 82.251234 | AA6: =100*((T6/T5)-1) -> 0.87230219
B7: 2008Q3 | C7: 255.819 | D7: 81.155 | E7: 69.19 | F7: 11.875 | G7: -0.658 | H7: 405.506 | I7: 0.855 | J7: 406.361 | K7: 113.34 | L7: 519.701 | M7: 119.731 | N7: 0 | O7: 399.97 | P7: 395.566 | S7: =100*(C7/OBR_NOV23_1.1!C7) -> 85.377445 | T7: =100*(D7/OBR_NOV23_1.1!D7) -> 85.972012 | U7: =100*(E7/OBR_NOV23_1.1!E7) -> 85.080482 | V7: =100*(K7/OBR_NOV23_1.1!N7) -> 80.470869 | W7: =100*(M7/OBR_NOV23_1.1!P7) -> 89.477696 | X7: =100*(O7/OBR_NOV23_1.1!R7) -> 83.34931 | AA7: =100*((T7/T6)-1) -> -0.58638596
B8: 2008Q4 | C8: 247.924 | D8: 83.414 | E8: 68.46 | F8: 12.733 | G8: 0.279 | H8: 400.077 | I8: -2.203 | J8: 397.874 | K8: 109.631 | L8: 507.505 | M8: 112.304 | N8: 0 | O8: 395.201 | P8: 383.976 | S8: =100*(C8/OBR_NOV23_1.1!C8) -> 84.79716 | T8: =100*(D8/OBR_NOV23_1.1!D8) -> 87.434226 | U8: =100*(E8/OBR_NOV23_1.1!E8) -> 85.59854 | V8: =100*(K8/OBR_NOV23_1.1!N8) -> 80.953893 | W8: =100*(M8/OBR_NOV23_1.1!P8) -> 88.62094 | X8: =100*(O8/OBR_NOV23_1.1!R8) -> 84.1401 | AA8: =100*((T8/T7)-1) -> 1.7008022
B9: 2009Q1 | C9: 247.707 | D9: 84.238 | E9: 65.081 | F9: 13.271 | G9: 1.281 | H9: 398.307 | I9: -6.857 | J9: 391.45 | K9: 103.636 | L9: 495.086 | M9: 108.347 | N9: 0 | O9: 386.739 | P9: 379.763 | S9: =100*(C9/OBR_NOV23_1.1!C9) -> 85.039686 | T9: =100*(D9/OBR_NOV23_1.1!D9) -> 88.856775 | U9: =100*(E9/OBR_NOV23_1.1!E9) -> 86.473738 | V9: =100*(K9/OBR_NOV23_1.1!N9) -> 81.781523 | W9: =100*(M9/OBR_NOV23_1.1!P9) -> 89.014772 | X9: =100*(O9/OBR_NOV23_1.1!R9) -> 84.054509 | AA9: =100*((T9/T8)-1) -> 1.6269939
B10: 2009Q2 | C10: 248.136 | D10: 84.184 | E10: 62.025 | F10: 12.265 | G10: 0.516 | H10: 394.861 | I10: -3.785 | J10: 391.076 | K10: 101.716 | L10: 492.792 | M10: 106.228 | N10: 0 | O10: 386.564 | P10: 380.724 | S10: =100*(C10/OBR_NOV23_1.1!C10) -> 85.237883 | T10: =100*(D10/OBR_NOV23_1.1!D10) -> 89.023307 | U10: =100*(E10/OBR_NOV23_1.1!E10) -> 86.070522 | V10: =100*(K10/OBR_NOV23_1.1!N10) -> 81.100303 | W10: =100*(M10/OBR_NOV23_1.1!P10) -> 87.065708 | X10: =100*(O10/OBR_NOV23_1.1!R10) -> 84.292377 | AA10: =100*((T10/T9)-1) -> 0.18741598
B11: 2009Q3 | C11: 249.481 | D11: 86.207 | E11: 62.265 | F11: 13.498 | G11: 0.57 | H11: 398.523 | I11: -3.917 | J11: 394.606 | K11: 102.632 | L11: 497.238 | M11: 108.614 | N11: 0 | O11: 388.624 | P11: 389.479 | S11: =100*(C11/OBR_NOV23_1.1!C11) -> 85.225052 | T11: =100*(D11/OBR_NOV23_1.1!D11) -> 90.39974 | U11: =100*(E11/OBR_NOV23_1.1!E11) -> 85.822387 | V11: =100*(K11/OBR_NOV23_1.1!N11) -> 82.218733 | W11: =100*(M11/OBR_NOV23_1.1!P11) -> 86.675551 | X11: =100*(O11/OBR_NOV23_1.1!R11) -> 84.690602 | AA11: =100*((T11/T10)-1) -> 1.546149
B12: 2009Q4 | C12: 250.34 | D12: 85.942 | E12: 60.697 | F12: 13.189 | G12: -0.013 | H12: 396.966 | I12: -6.071 | J12: 390.895 | K12: 108.358 | L12: 499.253 | M12: 112.378 | N12: 0 | O12: 386.875 | P12: 385.824 | S12: =100*(C12/OBR_NOV23_1.1!C12) -> 84.887202 | T12: =100*(D12/OBR_NOV23_1.1!D12) -> 89.420456 | U12: =100*(E12/OBR_NOV23_1.1!E12) -> 85.087264 | V12: =100*(K12/OBR_NOV23_1.1!N12) -> 82.929368 | W12: =100*(M12/OBR_NOV23_1.1!P12) -> 88.243424 | X12: =100*(O12/OBR_NOV23_1.1!R12) -> 84.059769 | AA12: =100*((T12/T11)-1) -> -1.0832821
B13: 2010Q1 | C13: 249.159 | D13: 86.856 | E13: 63.512 | F13: 13.272 | G13: -0.221 | H13: 399.306 | I13: 1.601 | J13: 400.907 | K13: 110.685 | L13: 511.592 | M13: 115.479 | N13: 0 | O13: 396.113 | P13: 396.248 | S13: =100*(C13/OBR_NOV23_1.1!C13) -> 84.902459 | T13: =100*(D13/OBR_NOV23_1.1!D13) -> 91.615421 | U13: =100*(E13/OBR_NOV23_1.1!E13) -> 84.527137 | V13: =100*(K13/OBR_NOV23_1.1!N13) -> 84.762831 | W13: =100*(M13/OBR_NOV23_1.1!P13) -> 89.051258 | X13: =100*(O13/OBR_NOV23_1.1!R13) -> 85.269394 | AA13: =100*((T13/T12)-1) -> 2.4546569
B14: 2010Q2 | C14: 257.449 | D14: 86.19 | E14: 62.846 | F14: 12.714 | G14: -0.362 | H14: 406.123 | I14: 0.261 | J14: 406.384 | K14: 115.919 | L14: 522.303 | M14: 120.992 | N14: 0 | O14: 401.311 | P14: 401.775 | S14: =100*(C14/OBR_NOV23_1.1!C14) -> 85.647323 | T14: =100*(D14/OBR_NOV23_1.1!D14) -> 90.609001 | U14: =100*(E14/OBR_NOV23_1.1!E14) -> 84.901786 | V14: =100*(K14/OBR_NOV23_1.1!N14) -> 85.9334 | W14: =100*(M14/OBR_NOV23_1.1!P14) -> 90.437642 | X14: =100*(O14/OBR_NOV23_1.1!R14) -> 85.456958 | AA14: =100*((T14/T13)-1) -> -1.098527
B15: 2010Q3 | C15: 259.351 | D15: 85.911 | E15: 65.226 | F15: 13.003 | G15: 0.447 | H15: 410.935 | I15: 1.096 | J15: 412.031 | K15: 116.698 | L15: 528.729 | M15: 124.53 | N15: 0 | O15: 404.199 | P15: 403.675 | S15: =100*(C15/OBR_NOV23_1.1!C15) -> 86.208662 | T15: =100*(D15/OBR_NOV23_1.1!D15) -> 90.302406 | U15: =100*(E15/OBR_NOV23_1.1!E15) -> 84.820349 | V15: =100*(K15/OBR_NOV23_1.1!N15) -> 85.612836 | W15: =100*(M15/OBR_NOV23_1.1!P15) -> 90.171175 | X15: =100*(O15/OBR_NOV23_1.1!R15) -> 85.599292 | AA15: =100*((T15/T14)-1) -> -0.33837143
B16: 2010Q4 | C16: 261.157 | D16: 87.359 | E16: 66.706 | F16: 12.588 | G16: 0.574 | H16: 415.796 | I16: -1.483 | J16: 414.313 | K16: 120.874 | L16: 535.187 | M16: 128.257 | N16: 0 | O16: 406.93 | P16: 407.562 | S16: =100*(C16/OBR_NOV23_1.1!C16) -> 86.953207 | T16: =100*(D16/OBR_NOV23_1.1!D16) -> 91.288037 | U16: =100*(E16/OBR_NOV23_1.1!E16) -> 84.466843 | V16: =100*(K16/OBR_NOV23_1.1!N16) -> 86.912192 | W16: =100*(M16/OBR_NOV23_1.1!P16) -> 92.06061 | X16: =100*(O16/OBR_NOV23_1.1!R16) -> 86.102342 | AA16: =100*((T16/T15)-1) -> 1.0914782
B17: 2011Q1 | C17: 263.602 | D17: 89.47 | E17: 64.274 | F17: 13.122 | G17: -1.752 | H17: 415.594 | I17: -1.655 | J17: 413.939 | K17: 128.717 | L17: 542.656 | M17: 127.924 | N17: 0 | O17: 414.732 | P17: 416.433 | S17: =100*(C17/OBR_NOV23_1.1!C17) -> 88.53905 | T17: =100*(D17/OBR_NOV23_1.1!D17) -> 92.944256 | U17: =100*(E17/OBR_NOV23_1.1!E17) -> 84.657938 | V17: =100*(K17/OBR_NOV23_1.1!N17) -> 88.896025 | W17: =100*(M17/OBR_NOV23_1.1!P17) -> 94.040329 | X17: =100*(O17/OBR_NOV23_1.1!R17) -> 87.529626 | AA17: =100*((T17/T16)-1) -> 1.8142784
... B55: 2020Q3 | C55: 319.136 | D55: 121.322 | E55: 92.349 | F55: 16.901 | G55: 1.172 | H55: 533.979 | I55: -0.951 | J55: 533.028 | K55: 147.825 | L55: 680.853 | M55: 147.185 | N55: 0 | O55: 533.668 | P55: 527.792 | S55: =100*(C55/OBR_NOV23_1.1!C55) -> 100.72307 | T55: =100*(D55/OBR_NOV23_1.1!D55) -> 121.40213 | U55: =100*(E55/OBR_NOV23_1.1!E55) -> 101.75526 | V55: =100*(K55/OBR_NOV23_1.1!N55) -> 99.277372 | W55: =100*(M55/OBR_NOV23_1.1!P55) -> 97.882542 | X55: =100*(O55/OBR_NOV23_1.1!R55) -> 105.12663 | AA55: =100*((T55/T54)-1) -> -15.407269
B56: 2020Q4 | C56: 314.018 | D56: 123.948 | E56: 96.772 | F56: 17.161 | G56: 7.662 | H56: 542.4 | I56: 10.552 | J56: 552.952 | K56: 158.181 | L56: 711.133 | M56: 172.439 | N56: 0 | O56: 538.694 | P56: 530.241 | S56: =100*(C56/OBR_NOV23_1.1!C56) -> 100.71814 | T56: =100*(D56/OBR_NOV23_1.1!D56) -> 118.23151 | U56: =100*(E56/OBR_NOV23_1.1!E56) -> 100.65005 | V56: =100*(K56/OBR_NOV23_1.1!N56) -> 100.37439 | W56: =100*(M56/OBR_NOV23_1.1!P56) -> 100.12774 | X56: =100*(O56/OBR_NOV23_1.1!R56) -> 104.69612 | Z56: =100*((S56/S55)-1) -> -0.0048942098 | AA56: =100*((T56/T55)-1) -> -2.6116666
B57: 2021Q1 | C57: 306.507 | D57: 129.099 | E57: 95.16 | F57: 18.039 | G57: 8.584 | H57: 539.35 | I57: -1.153 | J57: 538.197 | K57: 156.517 | L57: 694.714 | M57: 156.702 | N57: 0 | O57: 538.012 | P57: 537.213 | S57: =100*(C57/OBR_NOV23_1.1!C57) -> 101.83633 | T57: =100*(D57/OBR_NOV23_1.1!D57) -> 121.94797 | U57: =100*(E57/OBR_NOV23_1.1!E57) -> 101.47478 | V57: =100*(K57/OBR_NOV23_1.1!N57) -> 101.16995 | W57: =100*(M57/OBR_NOV23_1.1!P57) -> 100.66617 | X57: =100*(O57/OBR_NOV23_1.1!R57) -> 105.64563 | Z57: =100*((S57/S56)-1) -> 1.1102248 | AA57: =100*((T57/T56)-1) -> 3.143379
B58: 2021Q2 | C58: 342.73 | D58: 126.02 | E58: 99.19 | F58: 17.679 | G58: -0.583 | H58: 567.357 | I58: -7.639 | J58: 559.718 | K58: 170.177 | L58: 729.895 | M58: 162.008 | N58: 0 | O58: 567.887 | P58: 569.781 | S58: =100*(C58/OBR_NOV23_1.1!C58) -> 101.86625 | T58: =100*(D58/OBR_NOV23_1.1!D58) -> 110.45085 | U58: =100*(E58/OBR_NOV23_1.1!E58) -> 100.32163 | V58: =100*(K58/OBR_NOV23_1.1!N58) -> 102.03253 | W58: =100*(M58/OBR_NOV23_1.1!P58) -> 100.23697 | X58: =100*(O58/OBR_NOV23_1.1!R58) -> 103.89843 | Z58: =100*((S58/S57)-1) -> 0.02937102 | AA58: =100*((T58/T57)-1) -> -9.4278916
B59: 2021Q3 | C59: 357.103 | D59: 126.347 | E59: 104.563 | F59: 18.066 | G59: 3.684 | H59: 591.697 | I59: 0.585 | J59: 592.282 | K59: 163.01 | L59: 755.292 | M59: 173.786 | N59: 0 | O59: 581.506 | P59: 583.95 | S59: =100*(C59/OBR_NOV23_1.1!C59) -> 103.10675 | T59: =100*(D59/OBR_NOV23_1.1!D59) -> 109.72765 | U59: =100*(E59/OBR_NOV23_1.1!E59) -> 106.44386 | V59: =100*(K59/OBR_NOV23_1.1!N59) -> 102.20255 | W59: =100*(M59/OBR_NOV23_1.1!P59) -> 103.14383 | X59: =100*(O59/OBR_NOV23_1.1!R59) -> 104.59569 | Z59: =100*((S59/S58)-1) -> 1.2177751 | AA59: =100*((T59/T58)-1) -> -0.65476934
B60: 2021Q4 | C60: 362.996 | D60: 127.25 | E60: 104.934 | F60: 17.928 | G60: -2.959 | H60: 592.221 | I60: 5.179 | J60: 597.4 | K60: 186.322 | L60: 783.722 | M60: 187.048 | N60: 0 | O60: 596.674 | P60: 605.668 | S60: =100*(C60/OBR_NOV23_1.1!C60) -> 104.51011 | T60: =100*(D60/OBR_NOV23_1.1!D60) -> 109.31755 | U60: =100*(E60/OBR_NOV23_1.1!E60) -> 106.24076 | V60: =100*(K60/OBR_NOV23_1.1!N60) -> 106.12828 | W60: =100*(M60/OBR_NOV23_1.1!P60) -> 108.69575 | X60: =100*(O60/OBR_NOV23_1.1!R60) -> 105.71697 | Z60: =100*((S60/S59)-1) -> 1.3610751 | AA60: =100*((T60/T59)-1) -> -0.37374435
B61: 2022Q1 | C61: 373.514 | D61: 132.92 | E61: 111.264 | F61: 19.449 | G61: 8.153 | H61: 625.851 | I61: 9.891 | J61: 635.742 | K61: 178.657 | L61: 814.399 | M61: 212.558 | N61: 6.976 | O61: 608.817 | P61: 602.02 | S61: =100*(C61/OBR_NOV23_1.1!C61) -> 106.59889 | T61: =100*(D61/OBR_NOV23_1.1!D61) -> 113.31918 | U61: =100*(E61/OBR_NOV23_1.1!E61) -> 106.53084 | V61: =100*(K61/OBR_NOV23_1.1!N61) -> 110.35431 | W61: =100*(M61/OBR_NOV23_1.1!P61) -> 113.00626 | X61: =100*(O61/OBR_NOV23_1.1!R61) -> 107.30473 | Z61: =100*((S61/S60)-1) -> 1.9986468 | AA61: =100*((T61/T60)-1) -> 3.6605577
B62: 2022Q2 | C62: 386.969 | D62: 127.91 | E62: 113.771 | F62: 18.346 | G62: 2.133 | H62: 630.783 | I62: 11.807 | J62: 642.59 | K62: 198.285 | L62: 840.875 | M62: 226.886 | N62: 8.022 | O62: 622.011 | P62: 631.397 | S62: =100*(C62/OBR_NOV23_1.1!C62) -> 109.98656 | T62: =100*(D62/OBR_NOV23_1.1!D62) -> 111.31514 | U62: =100*(E62/OBR_NOV23_1.1!E62) -> 108.85927 | V62: =100*(K62/OBR_NOV23_1.1!N62) -> 116.02603 | W62: =100*(M62/OBR_NOV23_1.1!P62) -> 118.41711 | X62: =100*(O62/OBR_NOV23_1.1!R62) -> 109.53251 | Z62: =100*((S62/S61)-1) -> 3.1779515 | AA62: =100*((T62/T61)-1) -> -1.7684933
B63: 2022Q3 | C63: 391.81 | D63: 131.996 | E63: 116.792 | F63: 19.339 | G63: -12.442 | H63: 628.156 | I63: 1.768 | J63: 629.924 | K63: 226.14 | L63: 856.064 | M63: 232.789 | N63: 7.376 | O63: 630.651 | P63: 632.494 | S63: =100*(C63/OBR_NOV23_1.1!C63) -> 112.30155 | T63: =100*(D63/OBR_NOV23_1.1!D63) -> 114.03739 | U63: =100*(E63/OBR_NOV23_1.1!E63) -> 110.38107 | V63: =100*(K63/OBR_NOV23_1.1!N63) -> 119.1471 | W63: =100*(M63/OBR_NOV23_1.1!P63) -> 125.71094 | X63: =100*(O63/OBR_NOV23_1.1!R63) -> 111.14908 | Z63: =100*((S63/S62)-1) -> 2.1047969 | AA63: =100*((T63/T62)-1) -> 2.4455366
B64: 2022Q4 | C64: 400.138 | D64: 132.218 | E64: 117.906 | F64: 20.813 | G64: -17.868 | H64: 632.394 | I64: 2.436 | J64: 634.83 | K64: 230.776 | L64: 865.606 | M64: 229.577 | N64: 8.662 | O64: 644.691 | P64: 652.941 | S64: =100*(C64/OBR_NOV23_1.1!C64) -> 114.7879 | T64: =100*(D64/OBR_NOV23_1.1!D64) -> 115.07624 | U64: =100*(E64/OBR_NOV23_1.1!E64) -> 111.40233 | V64: =100*(K64/OBR_NOV23_1.1!N64) -> 121.3646 | W64: =100*(M64/OBR_NOV23_1.1!P64) -> 123.39267 | X64: =100*(O64/OBR_NOV23_1.1!R64) -> 113.47177 | Z64: =100*((S64/S63)-1) -> 2.2139964 | AA64: =100*((T64/T63)-1) -> 0.91097426
B65: 2023Q1 | C65: 409.068 | D65: 132.831 | E65: 121.751 | F65: 22.072 | G65: -6.036 | H65: 657.614 | I65: -0.479 | J65: 657.135 | K65: 217.553 | L65: 874.688 | M65: 225.208 | N65: 8.849 | O65: 658.329 | P65: 655.033 | S65: =100*(C65/OBR_NOV23_1.1!C65) -> 116.56152 | T65: =100*(D65/OBR_NOV23_1.1!D65) -> 116.98431 | U65: =100*(E65/OBR_NOV23_1.1!E65) -> 112.2367 | V65: =100*(K65/OBR_NOV23_1.1!N65) -> 122.26956 | W65: =100*(M65/OBR_NOV23_1.1!P65) -> 123.2416 | X65: =100*(O65/OBR_NOV23_1.1!R65) -> 115.50179 | Z65: =100*((S65/S64)-1) -> 1.5451282 | AA65: =100*((T65/T64)-1) -> 1.658086
B66: 2023Q2 | C66: 416.891 | D66: 140.658 | E66: 123.542 | F66: 21.444 | G66: -3.62 | H66: 677.471 | I66: -1.521 | J66: 675.95 | K66: 214.787 | L66: 890.737 | M66: 224.704 | N66: 9.076 | O66: 675.109 | P66: 664.776 | S66: =100*(C66/OBR_NOV23_1.1!C66) -> 118.37139 | T66: =100*(D66/OBR_NOV23_1.1!D66) -> 120.82567 | U66: =100*(E66/OBR_NOV23_1.1!E66) -> 112.95785 | V66: =100*(K66/OBR_NOV23_1.1!N66) -> 121.81106 | W66: =100*(M66/OBR_NOV23_1.1!P66) -> 120.2983 | X66: =100*(O66/OBR_NOV23_1.1!R66) -> 118.22385 | Z66: =100*((S66/S65)-1) -> 1.552711 | AA66: =100*((T66/T65)-1) -> 3.2836609
B67: 2023Q3 | C67: 420.86997 | D67: 140.83718 | E67: 121.32137 | F67: 22.597005 | G67: -1.8074975 | H67: 681.22102 | I67: -0.42457749 | J67: 680.79644 | K67: 210.70522 | L67: 891.50166 | M67: 220.76988 | N67: 9.1420114 | O67: 679.87379 | P67: 665.2316 | S67: =100*(C67/OBR_NOV23_1.1!C67) -> 119.61955 | T67: =100*(D67/OBR_NOV23_1.1!D67) -> 120.01943 | U67: =100*(E67/OBR_NOV23_1.1!E67) -> 113.55411 | V67: =100*(K67/OBR_NOV23_1.1!N67) -> 120.1584 | W67: =100*(M67/OBR_NOV23_1.1!P67) -> 118.70417 | X67: =100*(O67/OBR_NOV23_1.1!R67) -> 119.08312 | Z67: =100*((S67/S66)-1) -> 1.0544501 | AA67: =100*((T67/T66)-1) -> -0.66727457
... B82: 2027Q2 | C82: 477.59985 | D82: 155.83619 | E82: 127.09898 | F82: 22.305446 | G82: -1.9129969 | H82: 758.62202 | I82: 0.79086567 | J82: 759.41289 | K82: 212.49216 | L82: 971.90505 | M82: 215.59925 | N82: 9.7261993 | O82: 766.03199 | P82: 753.12272 | S82: =100*(C82/OBR_NOV23_1.1!C82) -> 129.17746 | T82: =100*(D82/OBR_NOV23_1.1!D82) -> 122.45722 | U82: =100*(E82/OBR_NOV23_1.1!E82) -> 120.182 | V82: =100*(K82/OBR_NOV23_1.1!N82) -> 120.22103 | W82: =100*(M82/OBR_NOV23_1.1!P82) -> 118.51594 | X82: =100*(O82/OBR_NOV23_1.1!R82) -> 126.69271 | Z82: =100*((S82/S81)-1) -> 0.46072153 | AA82: =100*((T82/T81)-1) -> 0.35823171
B83: 2027Q3 | C83: 482.28924 | D83: 157.00326 | E83: 127.85695 | F83: 22.318423 | G83: -1.9204314 | H83: 765.22902 | I83: 0.82688514 | J83: 766.0559 | K83: 213.29818 | L83: 979.35409 | M83: 216.16686 | N83: 9.7696067 | O83: 772.95684 | P83: 760.21186 | S83: =100*(C83/OBR_NOV23_1.1!C83) -> 129.78996 | T83: =100*(D83/OBR_NOV23_1.1!D83) -> 122.91405 | U83: =100*(E83/OBR_NOV23_1.1!E83) -> 120.64906 | V83: =100*(K83/OBR_NOV23_1.1!N83) -> 120.47955 | W83: =100*(M83/OBR_NOV23_1.1!P83) -> 118.73765 | X83: =100*(O83/OBR_NOV23_1.1!R83) -> 127.25813 | Z83: =100*((S83/S82)-1) -> 0.47415397 | AA83: =100*((T83/T82)-1) -> 0.37305716 | AB83: =100*((U83/U82)-1) -> 0.38862961 | AC83: =100*((V83/V82)-1) -> 0.21503257 | AD83: =100*((W83/W82)-1) -> 0.1870717 | AE83: =100*((X83/X82)-1) -> 0.4462935
B84: 2027Q4 | C84: 487.01895 | D84: 158.22993 | E84: 128.58193 | F84: 22.324584 | G84: -1.9278972 | H84: 771.90292 | I84: 0.86694757 | J84: 772.76986 | K84: 214.12265 | L84: 986.89252 | M84: 216.8026 | N84: 9.8144587 | O84: 779.90438 | P84: 767.34876 | S84: =100*(C84/OBR_NOV23_1.1!C84) -> 130.42187 | T84: =100*(D84/OBR_NOV23_1.1!D84) -> 123.39235 | U84: =100*(E84/OBR_NOV23_1.1!E84) -> 121.11809 | V84: =100*(K84/OBR_NOV23_1.1!N84) -> 120.74519 | W84: =100*(M84/OBR_NOV23_1.1!P84) -> 118.96112 | X84: =100*(O84/OBR_NOV23_1.1!R84) -> 127.84237 | Z84: =100*((S84/S83)-1) -> 0.48686832 | AA84: =100*((T84/T83)-1) -> 0.38913074 | AB84: =100*((U84/U83)-1) -> 0.38875677 | AC84: =100*((V84/V83)-1) -> 0.22048555 | AD84: =100*((W84/W83)-1) -> 0.18820272 | AE84: =100*((X84/X83)-1) -> 0.45909705
B85: 2028Q1 | C85: 491.80917 | D85: 159.5162 | E85: 129.37404 | F85: 22.323929 | G85: -1.9353836 | H85: 778.76402 | I85: 0.89797263 | J85: 779.66199 | K85: 214.89175 | L85: 994.55374 | M85: 217.50358 | N85: 9.8603804 | O85: 786.91054 | P85: 774.29508 | S85: =100*(C85/OBR_NOV23_1.1!C85) -> 131.06569 | T85: =100*(D85/OBR_NOV23_1.1!D85) -> 123.89185 | U85: =100*(E85/OBR_NOV23_1.1!E85) -> 121.58842 | V85: =100*(K85/OBR_NOV23_1.1!N85) -> 121.0118 | W85: =100*(M85/OBR_NOV23_1.1!P85) -> 119.18443 | X85: =100*(O85/OBR_NOV23_1.1!R85) -> 128.44054 | Z85: =100*((S85/S84)-1) -> 0.49364565 | AA85: =100*((T85/T84)-1) -> 0.40480927 | AB85: =100*((U85/U84)-1) -> 0.38831953 | AC85: =100*((V85/V84)-1) -> 0.22080191 | AD85: =100*((W85/W84)-1) -> 0.18771904 | AE85: =100*((X85/X84)-1) -> 0.46789807
B86: 2028Q2 | C86: 496.63614 | D86: 160.82218 | E86: 130.18416 | F86: 22.322766 | G86: -1.9428984 | H86: 785.69958 | I86: 0.98994083 | J86: 786.68952 | K86: 215.68491 | L86: 1002.3744 | M86: 218.30248 | N86: 9.9061964 | O86: 793.97815 | P86: 781.2253 | S86: =100*(C86/OBR_NOV23_1.1!C86) -> 131.71645 | T86: =100*(D86/OBR_NOV23_1.1!D86) -> 124.39695 | U86: =100*(E86/OBR_NOV23_1.1!E86) -> 122.06053 | V86: =100*(K86/OBR_NOV23_1.1!N86) -> 121.28901 | W86: =100*(M86/OBR_NOV23_1.1!P86) -> 119.4251 | X86: =100*(O86/OBR_NOV23_1.1!R86) -> 129.03734 | Z86: =100*((S86/S85)-1) -> 0.49651596 | AA86: =100*((T86/T85)-1) -> 0.40768979 | AB86: =100*((U86/U85)-1) -> 0.38828724 | AC86: =100*((V86/V85)-1) -> 0.22908006 | AD86: =100*((W86/W85)-1) -> 0.20192718 | AE86: =100*((X86/X85)-1) -> 0.46464766
B87: 2028Q3 | C87: 501.50366 | D87: 162.12734 | E87: 131.04079 | F87: 22.305769 | G87: -1.9504625 | H87: 792.72134 | I87: 1.0162129 | J87: 793.73755 | K87: 216.49268 | L87: 1010.2302 | M87: 219.15973 | N87: 9.9530407 | O87: 801.02354 | P87: 788.18305 | S87: =100*(C87/OBR_NOV23_1.1!C87) -> 132.37306 | T87: =100*(D87/OBR_NOV23_1.1!D87) -> 124.89968 | U87: =100*(E87/OBR_NOV23_1.1!E87) -> 122.53573 | V87: =100*(K87/OBR_NOV23_1.1!N87) -> 121.57149 | W87: =100*(M87/OBR_NOV23_1.1!P87) -> 119.66102 | X87: =100*(O87/OBR_NOV23_1.1!R87) -> 129.64753 | Z87: =100*((S87/S86)-1) -> 0.49850041 | AA87: =100*((T87/T86)-1) -> 0.40413657 | AB87: =100*((U87/U86)-1) -> 0.3893198 | AC87: =100*((V87/V86)-1) -> 0.23290041 | AD87: =100*((W87/W86)-1) -> 0.1975516 | AE87: =100*((X87/X86)-1) -> 0.47287831
B88: 2028Q4 | C88: 506.418 | D88: 163.44404 | E88: 131.85205 | F88: 22.311978 | G88: -1.9580808 | H88: 799.75601 | I88: 1.0540861 | J88: 800.8101 | K88: 217.31284 | L88: 1018.1229 | M88: 220.07987 | N88: 10.000426 | O88: 808.0435 | P88: 795.26332 | S88: =100*(C88/OBR_NOV23_1.1!C88) -> 133.03535 | T88: =100*(D88/OBR_NOV23_1.1!D88) -> 125.40481 | U88: =100*(E88/OBR_NOV23_1.1!E88) -> 123.01434 | V88: =100*(K88/OBR_NOV23_1.1!N88) -> 121.85801 | W88: =100*(M88/OBR_NOV23_1.1!P88) -> 119.89427 | X88: =100*(O88/OBR_NOV23_1.1!R88) -> 130.26477 | Z88: =100*((S88/S87)-1) -> 0.50032673 | AA88: =100*((T88/T87)-1) -> 0.40442845 | AB88: =100*((U88/U87)-1) -> 0.39058832 | AC88: =100*((V88/V87)-1) -> 0.23568089 | AD88: =100*((W88/W87)-1) -> 0.19492368 | AE88: =100*((X88/X87)-1) -> 0.47609137
B89: 2029Q1 | C89: 511.41618 | D89: 164.77229 | E89: 132.69855 | F89: 22.341391 | G89: -1.9657488 | H89: 806.92127 | I89: 1.1572351 | J89: 808.0785 | K89: 218.05435 | L89: 1026.1328 | M89: 221.07381 | N89: 10.047732 | O89: 815.10678 | P89: 802.32649 | S89: =100*(C89/OBR_NOV23_1.1!C89) -> 133.70181 | T89: =100*(D89/OBR_NOV23_1.1!D89) -> 125.91231 | U89: =100*(E89/OBR_NOV23_1.1!E89) -> 123.49608 | V89: =100*(K89/OBR_NOV23_1.1!N89) -> 122.14537 | W89: =100*(M89/OBR_NOV23_1.1!P89) -> 120.13032 | X89: =100*(O89/OBR_NOV23_1.1!R89) -> 130.88097 | Z89: =100*((S89/S88)-1) -> 0.50096013 | AA89: =100*((T89/T88)-1) -> 0.40468625 | AB89: =100*((U89/U88)-1) -> 0.39160816 | AC89: =100*((V89/V88)-1) -> 0.23581497 | AD89: =100*((W89/W88)-1) -> 0.1968825 | AE89: =100*((X89/X88)-1) -> 0.47303637
B90: 2008 | C90: 1015.322 | D90: 324.775 | E90: 281.252 | F90: 48.299 | G90: -0.189 | H90: 1621.16 | I90: -0.681 | J90: 1620.479 | K90: 438.335 | L90: 2058.814 | M90: 465.214 | N90: 0 | O90: 1593.6 | P90: 1572.569 | S90: =100*(C90/OBR_NOV23_1.1!C90) -> 84.286786 | T90: =100*(D90/OBR_NOV23_1.1!D90) -> 86.408503 | U90: =100*(E90/OBR_NOV23_1.1!E90) -> 84.727984 | V90: =100*(K90/OBR_NOV23_1.1!N90) -> 78.715335 | W90: =100*(M90/OBR_NOV23_1.1!P90) -> 87.136513 | X90: =100*(O90/OBR_NOV23_1.1!R90) -> 82.709869
B91: 2009 | C91: 995.664 | D91: 340.571 | E91: 250.068 | F91: 52.223 | G91: 2.354 | H91: 1588.657 | I91: -20.63 | J91: 1568.027 | K91: 416.342 | L91: 1984.369 | M91: 435.567 | N91: 0 | O91: 1548.802 | P91: 1535.79 | S91: =100*(C91/OBR_NOV23_1.1!C91) -> 85.096942 | T91: =100*(D91/OBR_NOV23_1.1!D91) -> 89.426738 | U91: =100*(E91/OBR_NOV23_1.1!E91) -> 85.872051 | V91: =100*(K91/OBR_NOV23_1.1!N91) -> 82.016177 | W91: =100*(M91/OBR_NOV23_1.1!P91) -> 87.747286 | X91: =100*(O91/OBR_NOV23_1.1!R91) -> 84.274006 | Z91: =100*((S91/S90)-1) -> 0.96118884 | AA91: =100*((T91/T90)-1) -> 3.4929834 | AB91: =100*((U91/U90)-1) -> 1.3502828 | AC91: =100*((V91/V90)-1) -> 4.1933917 | AD91: =100*((W91/W90)-1) -> 0.70093867 | AE91: =100*((X91/X90)-1) -> 1.891112
B92: 2010 | C92: 1027.116 | D92: 346.316 | E92: 258.29 | F92: 51.577 | G92: 0.438 | H92: 1632.16 | I92: 1.475 | J92: 1633.635 | K92: 464.176 | L92: 2097.811 | M92: 489.258 | N92: 0 | O92: 1608.553 | P92: 1609.26 | S92: =100*(C92/OBR_NOV23_1.1!C92) -> 85.933871 | T92: =100*(D92/OBR_NOV23_1.1!D92) -> 90.953643 | U92: =100*(E92/OBR_NOV23_1.1!E92) -> 84.676362 | V92: =100*(K92/OBR_NOV23_1.1!N92) -> 85.821681 | W92: =100*(M92/OBR_NOV23_1.1!P92) -> 90.455255 | X92: =100*(O92/OBR_NOV23_1.1!R92) -> 85.608688 | Z92: =100*((S92/S91)-1) -> 0.98350124 | AA92: =100*((T92/T91)-1) -> 1.7074367 | AB92: =100*((U92/U91)-1) -> -1.392408 | AC92: =100*((V92/V91)-1) -> 4.6399427 | AD92: =100*((W92/W91)-1) -> 3.0860992 | AE92: =100*((X92/X91)-1) -> 1.5837413
B93: 2011 | C93: 1063.466 | D93: 347.419 | E93: 261.22 | F93: 48.039 | G93: 0.676 | H93: 1672.781 | I93: 2.947 | J93: 1675.728 | K93: 521.847 | L93: 2197.575 | M93: 534.985 | N93: 0 | O93: 1662.59 | P93: 1669.535 | S93: =100*(C93/OBR_NOV23_1.1!C93) -> 89.271618 | T93: =100*(D93/OBR_NOV23_1.1!D93) -> 91.302314 | U93: =100*(E93/OBR_NOV23_1.1!E93) -> 85.546611 | V93: =100*(K93/OBR_NOV23_1.1!N93) -> 90.232963 | W93: =100*(M93/OBR_NOV23_1.1!P93) -> 96.095365 | X93: =100*(O93/OBR_NOV23_1.1!R93) -> 87.48282 | Z93: =100*((S93/S92)-1) -> 3.8840874 | AA93: =100*((T93/T92)-1) -> 0.38335038 | AB93: =100*((U93/U92)-1) -> 1.0277362 | AC93: =100*((V93/V92)-1) -> 5.1400555 | AD93: =100*((W93/W92)-1) -> 6.2352491 | AE93: =100*((X93/X92)-1) -> 2.1891847
B94: 2012 | C94: 1100.051 | D94: 355.384 | E94: 270.019 | F94: 45.252 | G94: 0.352 | H94: 1725.806 | I94: 4.855 | J94: 1730.661 | K94: 524.715 | L94: 2255.376 | M94: 541.661 | N94: 0 | O94: 1713.715 | P94: 1697.755 | S94: =100*(C94/OBR_NOV23_1.1!C94) -> 90.777739 | T94: =100*(D94/OBR_NOV23_1.1!D94) -> 92.023574 | U94: =100*(E94/OBR_NOV23_1.1!E94) -> 87.040571 | V94: =100*(K94/OBR_NOV23_1.1!N94) -> 90.044429 | W94: =100*(M94/OBR_NOV23_1.1!P94) -> 94.964103 | X94: =100*(O94/OBR_NOV23_1.1!R94) -> 88.829009 | Z94: =100*((S94/S93)-1) -> 1.6871226 | AA94: =100*((T94/T93)-1) -> 0.78996907 | AB94: =100*((U94/U93)-1) -> 1.746369 | AC94: =100*((V94/V93)-1) -> -0.20894114 | AD94: =100*((W94/W93)-1) -> -1.1772285 | AE94: =100*((X94/X93)-1) -> 1.5388036
B95: 2013 | C95: 1153.092 | D95: 358.572 | E95: 284.444 | F95: 43.568 | G95: 7.215 | H95: 1803.323 | I95: 3.338 | J95: 1806.661 | K95: 539.564 | L95: 2346.225 | M95: 564.864 | N95: 0 | O95: 1781.361 | P95: 1749.792 | S95: =100*(C95/OBR_NOV23_1.1!C95) -> 92.808069 | T95: =100*(D95/OBR_NOV23_1.1!D95) -> 92.642294 | U95: =100*(E95/OBR_NOV23_1.1!E95) -> 88.804663 | V95: =100*(K95/OBR_NOV23_1.1!N95) -> 92.329912 | W95: =100*(M95/OBR_NOV23_1.1!P95) -> 95.921098 | X95: =100*(O95/OBR_NOV23_1.1!R95) -> 90.709576 | Z95: =100*((S95/S94)-1) -> 2.2365944 | AA95: =100*((T95/T94)-1) -> 0.67234975 | AB95: =100*((U95/U94)-1) -> 2.026747 | AC95: =100*((V95/V94)-1) -> 2.5381722 | AD95: =100*((W95/W94)-1) -> 1.007744 | AE95: =100*((X95/X94)-1) -> 2.117064
B96: 2014 | C96: 1198.685 | D96: 370.011 | E96: 308.662 | F96: 50.194 | G96: 6.103 | H96: 1883.461 | I96: 15.23 | J96: 1898.691 | K96: 532.236 | L96: 2430.927 | M96: 568.413 | N96: 0 | O96: 1862.514 | P96: 1829.242 | S96: =100*(C96/OBR_NOV23_1.1!C96) -> 93.93369 | T96: =100*(D96/OBR_NOV23_1.1!D96) -> 93.185567 | U96: =100*(E96/OBR_NOV23_1.1!E96) -> 90.030918 | V96: =100*(K96/OBR_NOV23_1.1!N96) -> 90.169756 | W96: =100*(M96/OBR_NOV23_1.1!P96) -> 91.844243 | X96: =100*(O96/OBR_NOV23_1.1!R96) -> 91.904927 | Z96: =100*((S96/S95)-1) -> 1.2128479 | AA96: =100*((T96/T95)-1) -> 0.58642003 | AB96: =100*((U96/U95)-1) -> 1.3808454 | AC96: =100*((V96/V95)-1) -> -2.3396056 | AD96: =100*((W96/W95)-1) -> -4.2502172 | AE96: =100*((X96/X95)-1) -> 1.3177782
B97: 2015 | C97: 1228.325 | D97: 374.638 | E97: 332.973 | F97: 51.665 | G97: 0.879 | H97: 1936.815 | I97: 8.606 | J97: 1945.421 | K97: 533.654 | L97: 2479.075 | M97: 562.624 | N97: 0 | O97: 1916.451 | P97: 1874.682 | S97: =100*(C97/OBR_NOV23_1.1!C97) -> 93.607135 | T97: =100*(D97/OBR_NOV23_1.1!D97) -> 93.159235 | U97: =100*(E97/OBR_NOV23_1.1!E97) -> 90.644362 | V97: =100*(K97/OBR_NOV23_1.1!N97) -> 87.12249 | W97: =100*(M97/OBR_NOV23_1.1!P97) -> 86.616438 | X97: =100*(O97/OBR_NOV23_1.1!R97) -> 92.51241 | Z97: =100*((S97/S96)-1) -> -0.34764371 | AA97: =100*((T97/T96)-1) -> -0.028257955 | AB97: =100*((U97/U96)-1) -> 0.68137032 | AC97: =100*((V97/V96)-1) -> -3.3794768 | AD97: =100*((W97/W96)-1) -> -5.692034 | AE97: =100*((X97/X96)-1) -> 0.66099053
B98: 2016 | C98: 1289.445 | D98: 382.76 | E98: 356.602 | F98: 51.474 | G98: 1.502 | H98: 2030.309 | I98: -0.908 | J98: 2029.401 | K98: 575.632 | L98: 2605.033 | M98: 613.388 | N98: 0 | O98: 1991.645 | P98: 1944.912 | S98: =100*(C98/OBR_NOV23_1.1!C98) -> 94.777009 | T98: =100*(D98/OBR_NOV23_1.1!D98) -> 94.512376 | U98: =100*(E98/OBR_NOV23_1.1!E98) -> 92.330118 | V98: =100*(K98/OBR_NOV23_1.1!N98) -> 91.43881 | W98: =100*(M98/OBR_NOV23_1.1!P98) -> 90.820092 | X98: =100*(O98/OBR_NOV23_1.1!R98) -> 94.330092 | Z98: =100*((S98/S97)-1) -> 1.2497698 | AA98: =100*((T98/T97)-1) -> 1.4525032 | AB98: =100*((U98/U97)-1) -> 1.8597475 | AC98: =100*((V98/V97)-1) -> 4.9543128 | AD98: =100*((W98/W97)-1) -> 4.8531826 | AE98: =100*((X98/X97)-1) -> 1.9647983
B99: 2017 | C99: 1336.921 | D99: 388.577 | E99: 380.012 | F99: 57.4 | G99: 0.842 | H99: 2106.352 | I99: 4.055 | J99: 2110.407 | K99: 643.286 | L99: 2753.693 | M99: 671.211 | N99: 0 | O99: 2082.482 | P99: 2060.075 | S99: =100*(C99/OBR_NOV23_1.1!C99) -> 96.502254 | T99: =100*(D99/OBR_NOV23_1.1!D99) -> 95.325441 | U99: =100*(E99/OBR_NOV23_1.1!E99) -> 95.061938 | V99: =100*(K99/OBR_NOV23_1.1!N99) -> 95.710277 | W99: =100*(M99/OBR_NOV23_1.1!P99) -> 96.333032 | X99: =100*(O99/OBR_NOV23_1.1!R99) -> 96.081369 | Z99: =100*((S99/S98)-1) -> 1.8203203 | AA99: =100*((T99/T98)-1) -> 0.86027337 | AB99: =100*((U99/U98)-1) -> 2.9587528 | AC99: =100*((V99/V98)-1) -> 4.6713935 | AD99: =100*((W99/W98)-1) -> 6.0701776 | AE99: =100*((X99/X98)-1) -> 1.856541
B100: 2018 | C100: 1391.673 | D100: 399.065 | E100: 387.324 | F100: 58.446 | G100: 2.826 | H100: 2180.888 | I100: 1.17 | J100: 2182.058 | K100: 679.7 | L100: 2861.758 | M100: 709.454 | N100: 0 | O100: 2152.304 | P100: 2123.051 | S100: =100*(C100/OBR_NOV23_1.1!C100) -> 98.518547 | T100: =100*(D100/OBR_NOV23_1.1!D100) -> 97.292349 | U100: =100*(E100/OBR_NOV23_1.1!E100) -> 97.357216 | V100: =100*(K100/OBR_NOV23_1.1!N100) -> 98.100626 | W100: =100*(M100/OBR_NOV23_1.1!P100) -> 98.762019 | X100: =100*(O100/OBR_NOV23_1.1!R100) -> 97.928103 | Z100: =100*((S100/S99)-1) -> 2.0893741 | AA100: =100*((T100/T99)-1) -> 2.0633613 | AB100: =100*((U100/U99)-1) -> 2.4145072 | AC100: =100*((V100/V99)-1) -> 2.4974845 | AD100: =100*((W100/W99)-1) -> 2.5214471 | AE100: =100*((X100/X99)-1) -> 1.9220524
B101: 2019 | C101: 1427.94 | D101: 426.592 | E101: 406.423 | F101: 62.139 | G101: 2.88 | H101: 2263.835 | I101: 1.262 | J101: 2265.097 | K101: 706.696 | L101: 2971.793 | M101: 737.872 | N101: 0 | O101: 2233.921 | P101: 2231.667 | S101: =100*(C101/OBR_NOV23_1.1!C101) -> 100 | T101: =100*(D101/OBR_NOV23_1.1!D101) -> 100 | U101: =100*(E101/OBR_NOV23_1.1!E101) -> 100 | V101: =100*(K101/OBR_NOV23_1.1!N101) -> 100 | W101: =100*(M101/OBR_NOV23_1.1!P101) -> 100 | X101: =100*(O101/OBR_NOV23_1.1!R101) -> 100 | Z101: =100*((S101/S100)-1) -> 1.5037297 | AA101: =100*((T101/T100)-1) -> 2.7830053 | AB101: =100*((U101/U100)-1) -> 2.7145232 | AC101: =100*((V101/V100)-1) -> 1.9361483 | AD101: =100*((W101/W100)-1) -> 1.2534992 | AE101: =100*((X101/X100)-1) -> 2.1157327
B102: 2020 | C102: 1246.073 | D102: 475.618 | E102: 367.488 | F102: 66.087 | G102: 0.969 | H102: 2090.148 | I102: 1.316 | J102: 2091.464 | K102: 624.805 | L102: 2716.269 | M102: 611.981 | N102: 0 | O102: 2104.288 | P102: 2059.457 | S102: =100*(C102/OBR_NOV23_1.1!C102) -> 100.57573 | T102: =100*(D102/OBR_NOV23_1.1!D102) -> 121.03255 | U102: =100*(E102/OBR_NOV23_1.1!E102) -> 101.33211 | V102: =100*(K102/OBR_NOV23_1.1!N102) -> 99.866537 | W102: =100*(M102/OBR_NOV23_1.1!P102) -> 98.739579 | X102: =100*(O102/OBR_NOV23_1.1!R102) -> 105.08362 | Z102: =100*((S102/S101)-1) -> 0.5757341 | AA102: =100*((T102/T101)-1) -> 21.032555 | AB102: =100*((U102/U101)-1) -> 1.3321127 | AC102: =100*((V102/V101)-1) -> -0.13346333 | AD102: =100*((W102/W101)-1) -> -1.2604208 | AE102: =100*((X102/X101)-1) -> 5.0836234
... B110: 2028 | C110: 1996.367 | D110: 645.90976 | E110: 522.45104 | F110: 89.264441 | G110: -7.7868254 | H110: 3156.9409 | I110: 3.9582125 | J110: 3160.8992 | K110: 864.38218 | L110: 4025.2813 | M110: 875.04566 | N110: 39.720044 | O110: 3189.9557 | P110: 3138.9668 | S110: =100*(C110/OBR_NOV23_1.1!C110) -> 132.05156 | T110: =100*(D110/OBR_NOV23_1.1!D110) -> 124.65088 | U110: =100*(E110/OBR_NOV23_1.1!E110) -> 122.30122 | V110: =100*(K110/OBR_NOV23_1.1!N110) -> 121.43308 | W110: =100*(M110/OBR_NOV23_1.1!P110) -> 119.54178 | X110: =100*(O110/OBR_NOV23_1.1!R110) -> 129.35068 | Z110: =100*((S110/S109)-1) -> 1.9723189 | AA110: =100*((T110/T109)-1) -> 1.5915587 | AB110: =100*((U110/U109)-1) -> 1.5613646 | AC110: =100*((V110/V109)-1) -> 0.89618152 | AD110: =100*((W110/W109)-1) -> 0.77008356 | AE110: =100*((X110/X109)-1) -> 1.8605552
B111: 2008-09 | C111: 1007.591 | D111: 329.006 | E111: 275.104 | F111: 49.512 | G111: 0.815 | H111: 1612.516 | I111: -7.375 | J111: 1605.141 | K111: 437.016 | L111: 2042.157 | M111: 459.366 | N111: 0 | O111: 1582.791 | P111: 1555.396 | S111: =100*(C111/OBR_NOV23_1.1!C111) -> 84.829481 | T111: =100*(D111/OBR_NOV23_1.1!D111) -> 87.191093 | U111: =100*(E111/OBR_NOV23_1.1!E111) -> 85.340348 | V111: =100*(K111/OBR_NOV23_1.1!N111) -> 80.437624 | W111: =100*(M111/OBR_NOV23_1.1!P111) -> 88.594153 | X111: =100*(O111/OBR_NOV23_1.1!R111) -> 83.434024
B112: 2009-10 | C112: 997.116 | D112: 343.189 | E112: 248.499 | F112: 52.224 | G112: 0.852 | H112: 1589.656 | I112: -12.172 | J112: 1577.484 | K112: 423.391 | L112: 2000.875 | M112: 442.699 | N112: 0 | O112: 1558.176 | P112: 1552.275 | S112: =100*(C112/OBR_NOV23_1.1!C112) -> 85.06248 | T112: =100*(D112/OBR_NOV23_1.1!D112) -> 90.113459 | U112: =100*(E112/OBR_NOV23_1.1!E112) -> 85.369323 | V112: =100*(K112/OBR_NOV23_1.1!N112) -> 82.775522 | W112: =100*(M112/OBR_NOV23_1.1!P112) -> 87.77667 | X112: =100*(O112/OBR_NOV23_1.1!R112) -> 84.579822
B113: 2010-11 | C113: 1041.559 | D113: 348.93 | E113: 259.052 | F113: 51.427 | G113: -1.093 | H113: 1648.448 | I113: -1.781 | J113: 1646.667 | K113: 482.208 | L113: 2128.875 | M113: 501.703 | N113: 0 | O113: 1627.172 | P113: 1629.445 | S113: =100*(C113/OBR_NOV23_1.1!C113) -> 86.832836 | T113: =100*(D113/OBR_NOV23_1.1!D113) -> 91.290834 | U113: =100*(E113/OBR_NOV23_1.1!E113) -> 84.708452 | V113: =100*(K113/OBR_NOV23_1.1!N113) -> 86.872741 | W113: =100*(M113/OBR_NOV23_1.1!P113) -> 91.679123 | X113: =100*(O113/OBR_NOV23_1.1!R113) -> 86.174186
B114: 2011-12 | C114: 1069.406 | D114: 348.529 | E114: 265.089 | F114: 46.627 | G114: 1.279 | H114: 1684.303 | I114: 2.483 | J114: 1686.786 | K114: 529.028 | L114: 2215.814 | M114: 543.252 | N114: 0 | O114: 1672.562 | P114: 1675.315 | S114: =100*(C114/OBR_NOV23_1.1!C114) -> 89.706614 | T114: =100*(D114/OBR_NOV23_1.1!D114) -> 91.123219 | U114: =100*(E114/OBR_NOV23_1.1!E114) -> 86.043553 | V114: =100*(K114/OBR_NOV23_1.1!N114) -> 90.648609 | W114: =100*(M114/OBR_NOV23_1.1!P114) -> 96.568176 | X114: =100*(O114/OBR_NOV23_1.1!R114) -> 87.69316
B115: 2012-13 | C115: 1113.172 | D115: 354.138 | E115: 269.372 | F115: 43.658 | G115: 2.369 | H115: 1739.051 | I115: 6.262 | J115: 1745.313 | K115: 524.297 | L115: 2269.61 | M115: 542.496 | N115: 0 | O115: 1727.114 | P115: 1702.767 | S115: =100*(C115/OBR_NOV23_1.1!C115) -> 91.280343 | T115: =100*(D115/OBR_NOV23_1.1!D115) -> 92.256112 | U115: =100*(E115/OBR_NOV23_1.1!E115) -> 87.384108 | V115: =100*(K115/OBR_NOV23_1.1!N115) -> 90.586422 | W115: =100*(M115/OBR_NOV23_1.1!P115) -> 95.219841 | X115: =100*(O115/OBR_NOV23_1.1!R115) -> 89.302412
B116: 2013-14 | C116: 1164.913 | D116: 362.069 | E116: 292.68 | F116: 45.912 | G116: 7.745 | H116: 1827.407 | I116: 4.435 | J116: 1831.842 | K116: 536.091 | L116: 2367.933 | M116: 566.683 | N116: 0 | O116: 1801.25 | P116: 1774.7 | S116: =100*(C116/OBR_NOV23_1.1!C116) -> 93.114377 | T116: =100*(D116/OBR_NOV23_1.1!D116) -> 92.847966 | U116: =100*(E116/OBR_NOV23_1.1!E116) -> 89.17244 | V116: =100*(K116/OBR_NOV23_1.1!N116) -> 91.966952 | W116: =100*(M116/OBR_NOV23_1.1!P116) -> 94.974911 | X116: =100*(O116/OBR_NOV23_1.1!R116) -> 91.020491
B117: 2014-15 | C117: 1207.424 | D117: 370.792 | E117: 315.035 | F117: 50.626 | G117: 7.169 | H117: 1900.42 | I117: 18.933 | J117: 1919.353 | K117: 533.25 | L117: 2452.603 | M117: 573.343 | N117: 0 | O117: 1879.26 | P117: 1841.848 | S117: =100*(C117/OBR_NOV23_1.1!C117) -> 93.883321 | T117: =100*(D117/OBR_NOV23_1.1!D117) -> 93.212065 | U117: =100*(E117/OBR_NOV23_1.1!E117) -> 90.175666 | V117: =100*(K117/OBR_NOV23_1.1!N117) -> 89.386889 | W117: =100*(M117/OBR_NOV23_1.1!P117) -> 90.506454 | X117: =100*(O117/OBR_NOV23_1.1!R117) -> 92.12673
B118: 2015-16 | C118: 1241.449 | D118: 376.402 | E118: 337.155 | F118: 51.402 | G118: -0.866 | H118: 1954.14 | I118: 3.232 | J118: 1957.372 | K118: 536.701 | L118: 2494.073 | M118: 562.63 | N118: 0 | O118: 1931.443 | P118: 1884.888 | S118: =100*(C118/OBR_NOV23_1.1!C118) -> 93.767296 | T118: =100*(D118/OBR_NOV23_1.1!D118) -> 93.224193 | U118: =100*(E118/OBR_NOV23_1.1!E118) -> 90.864868 | V118: =100*(K118/OBR_NOV23_1.1!N118) -> 87.111654 | W118: =100*(M118/OBR_NOV23_1.1!P118) -> 86.357183 | X118: =100*(O118/OBR_NOV23_1.1!R118) -> 92.78985
B119: 2016-17 | C119: 1302.659 | D119: 384.469 | E119: 363.126 | F119: 51.719 | G119: 0.071 | H119: 2050.325 | I119: 2.36 | J119: 2052.685 | K119: 597.001 | L119: 2649.686 | M119: 633.845 | N119: 0 | O119: 2015.841 | P119: 1979.375 | S119: =100*(C119/OBR_NOV23_1.1!C119) -> 95.183603 | T119: =100*(D119/OBR_NOV23_1.1!D119) -> 94.891021 | U119: =100*(E119/OBR_NOV23_1.1!E119) -> 92.998586 | V119: =100*(K119/OBR_NOV23_1.1!N119) -> 93.481076 | W119: =100*(M119/OBR_NOV23_1.1!P119) -> 93.079451 | X119: =100*(O119/OBR_NOV23_1.1!R119) -> 94.902853
B120: 2017-18 | C120: 1351.001 | D120: 390.245 | E120: 383.328 | F120: 58.796 | G120: 1.727 | H120: 2126.301 | I120: 1.959 | J120: 2128.26 | K120: 650.894 | L120: 2779.154 | M120: 679.332 | N120: 0 | O120: 2099.822 | P120: 2073.281 | S120: =100*(C120/OBR_NOV23_1.1!C120) -> 97.068616 | T120: =100*(D120/OBR_NOV23_1.1!D120) -> 95.605637 | U120: =100*(E120/OBR_NOV23_1.1!E120) -> 95.580385 | V120: =100*(K120/OBR_NOV23_1.1!N120) -> 95.693672 | W120: =100*(M120/OBR_NOV23_1.1!P120) -> 96.741862 | X120: =100*(O120/OBR_NOV23_1.1!R120) -> 96.386795
B121: 2018-19 | C121: 1402.695 | D121: 403.105 | E121: 392.489 | F121: 59.888 | G121: 14.068 | H121: 2212.357 | I121: 7.126 | J121: 2219.483 | K121: 684.736 | L121: 2904.219 | M121: 733.787 | N121: 0 | O121: 2170.432 | P121: 2149.137 | S121: =100*(C121/OBR_NOV23_1.1!C121) -> 98.888932 | T121: =100*(D121/OBR_NOV23_1.1!D121) -> 97.474308 | U121: =100*(E121/OBR_NOV23_1.1!E121) -> 98.229074 | V121: =100*(K121/OBR_NOV23_1.1!N121) -> 98.850867 | W121: =100*(M121/OBR_NOV23_1.1!P121) -> 99.139372 | X121: =100*(O121/OBR_NOV23_1.1!R121) -> 98.419168
B122: 2019-20 | C122: 1419.343 | D122: 432.7 | E122: 403.355 | F122: 61.6 | G122: -7.744 | H122: 2247.654 | I122: -6.062 | J122: 2241.592 | K122: 708.194 | L122: 2949.786 | M122: 709.08 | N122: 0 | O122: 2240.706 | P122: 2230.23 | S122: =100*(C122/OBR_NOV23_1.1!C122) -> 100.19123 | T122: =100*(D122/OBR_NOV23_1.1!D122) -> 101.83525 | U122: =100*(E122/OBR_NOV23_1.1!E122) -> 100.45977 | V122: =100*(K122/OBR_NOV23_1.1!N122) -> 100.38484 | W122: =100*(M122/OBR_NOV23_1.1!P122) -> 99.981247 | X122: =100*(O122/OBR_NOV23_1.1!R122) -> 100.73409
... B131: 2028-29 | C131: 2015.974 | D131: 651.16585 | E131: 525.77555 | F131: 89.281903 | G131: -7.8171906 | H131: 3185.0982 | I131: 4.2174749 | J131: 3189.3157 | K131: 867.54479 | L131: 4056.8605 | M131: 878.61588 | N131: 39.907395 | O131: 3218.152 | P131: 3166.9982 | S131: =100*(C131/OBR_NOV23_1.1!C131) -> 132.71063 | T131: =100*(D131/OBR_NOV23_1.1!D131) -> 125.156 | U131: =100*(E131/OBR_NOV23_1.1!E131) -> 122.77814 | V131: =100*(K131/OBR_NOV23_1.1!N131) -> 121.71644 | W131: =100*(M131/OBR_NOV23_1.1!P131) -> 119.77834 | X131: =100*(O131/OBR_NOV23_1.1!R131) -> 129.96074
B132: Definitions:
B133: Household and non-profit institutions serving households final consumption expenditure (ONS Economic Accounts Table 1.1.2, identifier: ABJQ + HAYE)
B134: General government final consumption (ONS Economic Accounts Table 1.1.2, identifier: NMRP)
B135: Total gross fixed capital formation (ONS Economic Accounts Table 1.1.2, identifier: NPQS)
B136: General government investment (ONS Economic Accounts Table 1.1.8, identifier: RPZG)
B137: Net acquisitions of valuables (ONS Economic Accounts Table 1.1.2, identifier: NPJQ)
B138: Final domestic demand is the sum of private consumption, government consumption, fixed investment and net acquisition of valuables
B139: Change in inventories (ONS Economic Accounts Table 1.1.2, identifier: CAEX)
B140: Total domestic demand is the sum of final domestic demand and change in inventories
B141: Total exports (ONS Economic Accounts Table 1.1.2, identifier: IKBH)
B142: Total final expenditure (ONS Economic Accounts Table 1.1.2, identifier: ABMF)
B143: Total imports (ONS Economic Accounts Table 1.1.2, identifier: IKBI)
... B146: Gross national income at market prices (ONS Economic Accounts Table 1.1.1, identifier: ABMZ)

Sheet OBR_MAR23_T4.7
A1: Back to contents
B2: Table 4.7: Departmental resource spending: changes since November
C4: £ billion
C5: Outturn | D5: Forecast
C6: 2021-22 | D6: 2022-23 | E6: 2023-24 | F6: 2024-25 | G6: 2025-26 | H6: 2026-27 | I6: 2027-28
B7: November 2022 forecast
B8: Limits | C8: 426.79126 | D8: 417.84485 | E8: 423.34465 | F8: 425.61016 | G8: 433.58602 | H8: 442.96597 | I8: 455.47005
B9: Assumed underspend | C9: -13.030816 | D9: -2.3698402 | E9: -3.6576436 | F9: -3.6087903 | G9: -3.2604683 | H9: -3.0192623 | I9: -2.802585
B10: Actual spending | C10: 413.76045 | D10: 415.47497 | E10: 419.68701 | F10: 422.00137 | G10: 430.32556 | H10: 439.94671 | I10: 452.66747
B11: March 2023 forecast
B12: Limits | C12: 426.79126 | D12: 420.15245 | E12: 425.4426 | F12: 430.47265 | G12: 439.39675 | H12: 449.49646 | I12: 462.04931
B13: Assumed underspend | C13: -13.030816 | D13: -4.6776901 | E13: -3.7552079 | F13: -3.816302 | G13: -3.5510896 | H13: -3.3459442 | I13: -3.1316577
B14: Actual spending | C14: 413.76045 | D14: 415.47476 | E14: 421.6874 | F14: 426.65635 | G14: 435.84566 | H14: 446.15051 | I14: 458.91766
B15: Difference
B16: Limits | D16: 2.3075982 | E16: 2.0979547 | F16: 4.8624896 | G16: 5.8107253 | H16: 6.5304869 | I16: 6.5792638
B17: of which:
B18: Childcare | D18: 0 | E18: 0.28509229 | F18: 2.4917468 | G18: 4.4073707 | H18: 5.2248104 | I18: 5.2902789
B19: Defence | D19: 0 | E19: 0.5 | F19: 0.75 | G19: 0.509867 | H19: 0.521131 | I19: 0.535039
B20: Other | D20: 2.3075982 | E20: 1.3128624 | F20: 1.6207427 | G20: 0.89348754 | H20: 0.78454549 | I20: 0.75394596
B21: Assumed underspend | D21: -2.3078499 | E21: -0.097564306 | F21: -0.2075117 | G21: -0.29062133 | H21: -0.32668186 | I21: -0.32907272
B22: Actual spending | D22: -0.00021762775 | E22: 2.0003898 | F22: 4.654977 | G22: 5.520103 | H22: 6.203804 | I22: 6.2501901

Sheet OBR_MAR23_T4.8
A1: Back to contents
B2: Table 4.8: Departmental capital spending: changes since November
C4: £ billion
C5: Outturn | D5: Forecast
C6: 2021-22 | D6: 2022-23 | E6: 2023-24 | F6: 2024-25 | G6: 2025-26 | H6: 2026-27 | I6: 2027-28
B7: November 2022 forecast
B8: Limits | C8: 79.706465 | D8: 98.747495 | E8: 103.23546 | F8: 102.88533 | G8: 103.3036 | H8: 103.17539 | I8: 102.62189
B9: Assumed underspend | C9: -2.717236 | D9: -9.9339895 | E9: -8.7882909 | F9: -8.1631575 | G9: -7.6987288 | H9: -7.157745 | I9: -6.4239921
B10: Actual spending | C10: 76.989229 | D10: 88.814116 | E10: 94.447103 | F10: 94.722329 | G10: 95.604873 | H10: 96.017646 | I10: 96.197899
B11: March 2023 forecast
B12: Limits | C12: 79.706465 | D12: 95.190651 | E12: 105.03452 | F12: 105.1718 | G12: 104.86564 | H12: 104.71854 | I12: 104.12457
B13: Assumed underspend | C13: -2.717236 | D13: -8.8760404 | E13: -8.9228712 | F13: -8.2828263 | G13: -7.7868864 | H13: -7.23909 | I13: -6.4971457
B14: Actual spending | C14: 76.989229 | D14: 86.31461 | E14: 96.111651 | F14: 96.888973 | G14: 97.078752 | H14: 97.479447 | I14: 97.627423
B15: Difference
B16: Limits | D16: -3.5568444 | E16: 1.7990657 | F16: 2.2864741 | G16: 1.5620371 | H16: 1.543146 | I16: 1.5026776
B17: of which:
B18: Defence | D18: 0 | E18: 1.5 | F18: 2.25 | G18: 1.5 | H18: 1.5 | I18: 1.5
B19: Other | D19: -3.5568444 | E19: 0.29906573 | F19: 0.036474096 | G19: 0.062037084 | H19: 0.043145982 | I19: 0.0026776207
B20: Assumed underspend | D20: 1.0579491 | E20: -0.13458036 | F20: -0.11966878 | G20: -0.088157603 | H20: -0.08134497 | I20: -0.073153664
B21: Actual spending | D21: -2.4995057 | E21: 1.6645479 | F21: 2.1666439 | G21: 1.4738794 | H21: 1.4618009 | I21: 1.4295238

Sheet OBR_MAR23_TA.7
A1: Back to contents
B2: Table A.7: Total managed expenditure
C4: £ billion
C5: Outturn | E5: Forecast
C6: 2020-21 | D6: 2021-22 | E6: 2022-23 | F6: 2023-24 | G6: 2024-25 | H6: 2025-26 | I6: 2026-27 | J6: 2027-28
B7: Public sector current expenditure (PSCE)
B8: PSCE in RDEL | C8: 429.36841 | D8: 413.76045 | E8: 415.47476 | F8: 421.6874 | G8: 426.65635 | H8: 435.84566 | I8: 446.15051 | J8: 458.91766
B9: PSCE in AME | C9: 551.55859 | D9: 521.92355 | E9: 640.33843 | F9: 633.89555 | G9: 629.00131 | H9: 644.33519 | I9: 669.49407 | J9: 688.95594
B10: of which:
B11: Welfare spending | C11: 245.3503 | D11: 244.25912 | E11: 261.54466 | F11: 294.52692 | G11: 307.00843 | H11: 316.75335 | I11: 323.33639 | J11: 330.52335
B12: Locally financed current expenditure | C12: 38.822766 | D12: 45.323893 | E12: 56.608499 | F12: 60.305432 | G12: 63.944544 | H12: 64.542884 | I12: 67.33233 | J12: 69.961319
B13: Central government debt interest, net of APF1 | C13: 23.628589 | D13: 56.368 | E13: 114.66959 | F13: 93.97829 | G13: 77.301285 | H13: 76.854479 | I13: 88.671628 | J13: 96.454479
B14: Scottish Government's current spending | C14: 41.556794 | D14: 41.207814 | E14: 39.933787 | F14: 41.428104 | G14: 42.022118 | H14: 42.505071 | I14: 43.409018 | J14: 44.893457
B15: EU financial settlement | C15: 10.394602 | D15: 8.3148337 | E15: 8.8002068 | F15: 6.4978516 | G15: 1.0350846 | H15: 1.3717661 | I15: 0.75919731 | J15: 0.40546123
B16: Net public service pension payments | C16: 4.0942838 | D16: 3.30175 | E16: 4.2426581 | F16: 7.8629687 | G16: 9.8161396 | H16: 9.9414512 | I16: 8.9964145 | J16: 7.9121836
B17: Company and other tax credits | C17: 8.1708173 | D17: 7.9632969 | E17: 9.4610239 | F17: 10.150987 | G17: 10.637222 | H17: 10.903094 | I17: 11.350454 | J17: 11.883478
B18: BBC current expenditure | C18: 3.4859318 | D18: 3.8786685 | E18: 4.240303 | F18: 4.1873379 | G18: 4.3785597 | H18: 4.2498597 | I18: 4.5110376 | J18: 4.494909
B19: National Lottery current grants | C19: 1.45918 | D19: 1.389417 | E19: 1.28536 | F19: 1.352781 | G19: 1.419556 | H19: 1.410414 | I19: 1.396095 | J19: 1.286178
B20: General government imputed pensions | C20: 0.7867552 | D20: 1.0527288 | E20: 0.79940576 | F20: 0.84382206 | G20: 0.86935578 | H20: 0.88729253 | I20: 0.90860496 | J20: 0.93324455
B21: Public corporations' debt interest | C21: 0.175 | D21: 0.528 | E21: 0.534 | F21: 0.532 | G21: 0.532 | H21: 0.532 | I21: 0.532 | J21: 0.532
B22: Non-domestic energy support | D22: 0 | E22: 6.7 | F22: 1.097 | G22: 0 | H22: 0 | I22: 0 | J22: 0
B23: Domestic energy support | D23: 0 | E23: 23.0334 | F23: 4.3443029 | G23: 0 | H23: 0 | I23: 0 | J23: 0
B24: Funded public sector pension schemes | C24: 19.111 | D24: 19.239958 | E24: 20.198628 | F24: 21.188301 | G24: 22.04058 | H24: 22.929072 | I24: 23.854989 | J24: 24.81968
B25: General government depreciation | C25: 46.815 | D25: 48.306 | E25: 50.390413 | F25: 52.591357 | G25: 55.094585 | H25: 57.301697 | I25: 59.5871 | J25: 62.061328
B26: Current VAT refunds | C26: 17.459072 | D26: 20.040968 | E26: 21.324195 | F26: 22.065576 | G26: 22.653231 | H26: 23.385001 | I26: 24.084167 | J26: 24.918122
B27: Environmental levies | C27: 10.437 | D27: 8.4465027 | E27: 8.5738001 | F27: 8.7851615 | G27: 9.0650802 | H27: 9.6896729 | I27: 9.7283303 | J27: 6.8262883
B28: Other PSCE items in AME | C28: 2.303794 | D28: 19.022885 | E28: 5.0883456 | F28: 1.3502585 | G28: 1.2658205 | H28: 1.3249852 | I28: 1.3737342 | J28: 1.4288322
B29: Other National Accounts adjustments | C29: -0.70729615 | D29: -6.720287 | E29: 2.9101452 | F29: 0.80710188 | G29: -0.082273906 | H29: -0.24690493 | I29: -0.33742634 | J29: -0.3783672
B30: Total public sector current expenditure | C30: 980.927 | D30: 935.684 | E30: 1055.8132 | F30: 1055.5829 | G30: 1055.6577 | H30: 1080.1808 | I30: 1115.6446 | J30: 1147.8736
B31: Public sector gross investment (PSGI)
B32: PSGI in CDEL | C32: 75.520266 | D32: 76.989229 | E32: 86.31461 | F32: 96.111651 | G32: 96.888973 | H32: 97.078752 | I32: 97.479447 | J32: 97.627423
B33: PSGI in AME | C33: 50.185734 | D33: 27.397771 | E33: 29.895362 | F33: 37.47543 | G33: 36.593392 | H33: 36.354933 | I33: 34.04122 | J33: 34.038546
B34: of which:
B35: Locally financed capital expenditure | C35: 11.642489 | D35: 10.671308 | E35: 9.6670463 | F35: 9.5887362 | G35: 9.270553 | H35: 9.1425737 | I35: 9.1421356 | J35: 9.2356768
B36: Public corporations' capital expenditure | C36: 9.711 | D36: 10.456 | E36: 11.576624 | F36: 11.576604 | G36: 11.92557 | H36: 12.096742 | I36: 12.090336 | J36: 12.179427
B37: Student loans | C37: 10.608892 | D37: 12.739809 | E37: 2.035617 | F37: 10.122447 | G37: 8.9751348 | H37: 7.9026439 | I37: 7.2489492 | J37: 7.0160355
B38: Funded public sector pension schemes | C38: -0.319 | D38: 0.59546591 | E38: 0.29546591 | F38: 0.29546591 | G38: 0.29546591 | H38: 0.29546591 | I38: 0.29546591 | J38: 0.095465909
B39: Scottish Government's capital spending | C39: 4.454373 | D39: 4.504728 | E39: 5.3930195 | F39: 5.3283926 | G39: 5.2533361 | H39: 5.1607518 | I39: 5.154036 | J39: 5.1460268
B40: Tax litigation | C40: 0 | D40: 0 | E40: 0.220945 | F40: 0.218402 | G40: 1.214589 | H40: 2.362967 | I40: 0 | J40: 0.409745
B41: Other PSGI items in AME | C41: 20.789873 | D41: -5.394568 | E41: 1.7544321 | F41: 0.73165555 | G41: 0.78222933 | H41: 0.79359654 | I41: 0.72523678 | J41: 0.5738511
B42: Other National Accounts adjustments | C42: -6.7018924 | D42: -6.1749724 | E42: -1.0477875 | F42: -0.38627317 | G42: -1.1234861 | H42: -1.3998082 | I42: -0.61493994 | J42: -0.61768255
B43: Total public sector gross investment | C43: 125.706 | D43: 104.387 | E43: 116.20997 | F43: 133.58708 | G43: 133.48237 | H43: 133.43368 | I43: 131.52067 | J43: 131.66597
B44: Less public sector depreciation | C44: -53.613 | D44: -55.052 | E44: -57.521984 | F44: -59.937334 | G44: -62.534762 | H44: -64.773863 | I44: -67.060786 | J44: -69.541624
B45: Public sector net investment | C45: 72.093 | D45: 49.335 | E45: 58.687989 | F45: 73.649747 | G45: 70.947604 | H45: 68.659822 | I45: 64.459881 | J45: 62.124345
B46: Total managed expenditure | C46: 1106.633 | D46: 1040.071 | E46: 1172.0232 | F46: 1189.17 | G46: 1189.14 | H46: 1213.6145 | I46: 1247.1652 | J46: 1279.5396
B47: 1 Includes increases in debt interest payments due to the APF.

Sheet OBR_MAR23_1.1
A1: Back to contents
B2: 1.1 GDP expenditure components (£ billion chain-linked volumes, seasonally adjusted)
C3: Private consumption | D3: Government consumption | E3: Fixed investment | J3: Net acquisition of valuables | K3: Final domestic demand | L3: Change in inventories | M3: Total domestic demand | N3: Exports | O3: Total final expenditure | P3: Imports | Q3: Statistical discrepancy | R3: Real GDP | S3: Non-oil GVA
E4: of which: | F4: Business investment | G4: Private dwellings | H4: General government | I4: Public corps dwellings
B5: 2008Q1 | C5: 308.382 | D5: 93.519 | E5: 87.028 | F5: 46.96 | G5: 25.19 | H5: 13.757 | I5: 1.474 | J5: 0.134 | K5: 489.063 | L5: -2.343 | M5: 486.72 | N5: 137.71 | O5: 625.943 | P5: 138.585 | Q5: 0 | R5: 487.601 | S5: 425.714
B6: 2008Q2 | C6: 304.769 | D6: 93.288 | E6: 87.538 | F6: 48.736 | G6: 23.885 | H6: 13.889 | I6: 1.412 | J6: -0.059 | K6: 485.536 | L6: -1.748 | M6: 483.788 | N6: 138.398 | O6: 622.869 | P6: 137.84 | Q6: 0 | R6: 485.278 | S6: 423.75
B7: 2008Q3 | C7: 299.674 | D7: 94.934 | E7: 83.063 | F7: 46.893 | G7: 19.352 | H7: 14.375 | I7: 2.767 | J7: -1.5 | K7: 476.171 | L7: -3.107 | M7: 473.064 | N7: 138.531 | O7: 613.231 | P7: 135.572 | Q7: 0 | R7: 477.935 | S7: 416.166
B8: 2008Q4 | C8: 292.608 | D8: 95.891 | E8: 81.585 | F8: 45.311 | G8: 18.413 | H8: 15.473 | I8: 2.717 | J8: 0.385 | K8: 470.469 | L8: -5.387 | M8: 465.082 | N8: 132.975 | O8: 595.31 | P8: 128.236 | Q8: 0 | R8: 467.25 | S8: 405.983
B9: 2009Q1 | C9: 291.571 | D9: 95.338 | E9: 76.32 | F9: 41.006 | G9: 17.385 | H9: 15.467 | I9: 2.667 | J9: 1.395 | K9: 464.624 | L9: -8.57 | M9: 456.054 | N9: 124.391 | O9: 580.956 | P9: 123.084 | Q9: 0 | R9: 458.181 | S9: 398.405
B10: 2009Q2 | C10: 291.016 | D10: 95.229 | E10: 73.206 | F10: 39.114 | G10: 16.991 | H10: 14.569 | I10: 2.621 | J10: 0.756 | K10: 460.207 | L10: -9.225 | M10: 450.982 | N10: 123.427 | O10: 579.437 | P10: 122.932 | Q10: 0 | R10: 456.867 | S10: 397.594
B11: 2009Q3 | C11: 292.43 | D11: 95.789 | E11: 74.047 | F11: 38.306 | G11: 16.926 | H11: 16.286 | I11: 2.664 | J11: 0.694 | K11: 462.96 | L11: -8.464 | M11: 454.496 | N11: 122.499 | O11: 583.271 | P11: 126.124 | Q11: 0 | R11: 457.471 | S11: 399.763
B12: 2009Q4 | C12: 294.785 | D12: 96.559 | E12: 72.917 | F12: 38.165 | G12: 16.131 | H12: 15.993 | I12: 2.717 | J12: -0.099 | K12: 464.162 | L12: -6.907 | M12: 457.255 | N12: 127.955 | O12: 586.782 | P12: 128.052 | Q12: 0 | R12: 459.031 | S12: 401.924
B13: 2010Q1 | C13: 293.14 | D13: 95.478 | E13: 75.936 | F13: 39.649 | G13: 17.351 | H13: 16.42 | I13: 2.697 | J13: -0.16 | K13: 464.394 | L13: -0.629 | M13: 463.765 | N13: 128.239 | O13: 593.475 | P13: 130.363 | Q13: 0 | R13: 463.391 | S13: 405.931
B14: 2010Q2 | C14: 299.974 | D14: 95.764 | E14: 75.577 | F14: 39.513 | G14: 18.383 | H14: 15.231 | I14: 2.675 | J14: -0.541 | K14: 470.774 | L14: -1.965 | M14: 468.809 | N14: 133.048 | O14: 602.684 | P14: 134.22 | Q14: 0 | R14: 468.691 | S14: 410.496
B15: 2010Q3 | C15: 300.046 | D15: 95.778 | E15: 78.355 | F15: 40.874 | G15: 19.266 | H15: 15.804 | I15: 2.659 | J15: 0.149 | K15: 474.328 | L15: 0.042 | M15: 474.37 | N15: 133.844 | O15: 609.557 | P15: 138.052 | Q15: 0 | R15: 471.664 | S15: 413.479
B16: 2010Q4 | C16: 299.875 | D16: 96.488 | E16: 80.277 | F16: 43.603 | G16: 18.92 | H16: 15.325 | I16: 2.607 | J16: 0.558 | K16: 477.198 | L16: -3.714 | M16: 473.484 | N16: 137.188 | O16: 611.128 | P16: 138.95 | Q16: 0 | R16: 472.312 | S16: 414.628
... B40: 2016Q4 | C40: 342.819 | D40: 101.384 | E40: 95.826 | F40: 54.364 | G40: 24.775 | H40: 14.038 | I40: 2.469 | J40: -0.849 | K40: 539.18 | L40: 1.839 | M40: 541.019 | N40: 159.797 | O40: 701.459 | P40: 168.206 | Q40: 0 | R40: 533.173 | S40: 472.138
B41: 2017Q1 | C41: 345.765 | D41: 101.379 | E41: 97.75 | F41: 55.84 | G41: 25.469 | H41: 13.945 | I41: 2.466 | J41: -0.674 | K41: 544.22 | L41: 4.57 | M41: 548.79 | N41: 161.982 | O41: 706.414 | P41: 169.217 | Q41: 0 | R41: 537.114 | S41: 475.864 | U41: =D41*1000 -> 101379 | V41: =F41*1000 -> 55840 | W41: =H41*1000 -> 13945
B42: 2017Q2 | C42: 345.922 | D42: 101.822 | E42: 99.356 | F42: 56.661 | G42: 25.261 | H42: 14.812 | I42: 2.605 | J42: 0.068 | K42: 547.168 | L42: 6.806 | M42: 553.974 | N42: 166.236 | O42: 714.807 | P42: 174.871 | Q42: 0 | R42: 539.994 | S42: 478.151 | U42: =D42*1000 -> 101822 | V42: =F42*1000 -> 56661 | W42: =H42*1000 -> 14812
B43: 2017Q3 | C43: 348.463 | D43: 102.143 | E43: 99.163 | F43: 56.21 | G43: 26.015 | H43: 14.422 | I43: 2.503 | J43: -0.689 | K43: 549.08 | L43: 2.416 | M43: 551.496 | N43: 171.203 | O43: 719.511 | P43: 176.831 | Q43: 0 | R43: 542.78 | S43: 480.811 | U43: =D43*1000 -> 102143 | V43: =F43*1000 -> 56210 | W43: =H43*1000 -> 14422
B44: 2017Q4 | C44: 350.532 | D44: 101.957 | E44: 100.638 | F44: 56.964 | G44: 27.063 | H44: 14.577 | I44: 2.03 | J44: 1.907 | K44: 555.034 | L44: -1.121 | M44: 553.913 | N44: 167.43 | O44: 719.258 | P44: 173.056 | Q44: 0 | R44: 546.185 | S44: 483.293 | U44: =D44*1000 -> 101957 | V44: =F44*1000 -> 56964 | W44: =H44*1000 -> 14577
B45: 2018Q1 | C45: 353.38 | D45: 101.629 | E45: 98.919 | F45: 56.481 | G45: 27.099 | H45: 14.017 | I45: 1.377 | J45: 0.482 | K45: 554.41 | L45: -2.722 | M45: 551.688 | N45: 171.025 | O45: 723.162 | P45: 176.153 | Q45: 0 | R45: 547.003 | S45: 484.19 | U45: =D45*1000 -> 101629 | V45: =F45*1000 -> 56481 | W45: =H45*1000 -> 14017
B46: 2018Q2 | C46: 353.669 | D46: 101.698 | E46: 98.831 | F46: 55.124 | G46: 27.954 | H46: 14.409 | I46: 1.41 | J46: 1.269 | K46: 555.467 | L46: 0.754 | M46: 556.221 | N46: 171.63 | O46: 727.342 | P46: 177.86 | Q46: 0 | R46: 549.491 | S46: 486.07 | U46: =D46*1000 -> 101698 | V46: =F46*1000 -> 55124 | W46: =H46*1000 -> 14409
B47: 2018Q3 | C47: 356.836 | D47: 102.181 | E47: 99.335 | F47: 55.252 | G47: 27.766 | H47: 15.044 | I47: 1.306 | J47: 1.074 | K47: 559.426 | L47: 0.105 | M47: 559.531 | N47: 173.916 | O47: 731.184 | P47: 178.659 | Q47: 0 | R47: 552.545 | S47: 488.438 | U47: =D47*1000 -> 102181 | V47: =F47*1000 -> 55252 | W47: =H47*1000 -> 15044
B48: 2018Q4 | C48: 361.038 | D48: 103.117 | E48: 98.882 | F48: 55.493 | G48: 27.28 | H48: 14.897 | I48: 1.257 | J48: 0.307 | K48: 563.344 | L48: 3.18 | M48: 566.524 | N48: 171.285 | O48: 738.417 | P48: 184.463 | Q48: 0 | R48: 553.966 | S48: 489.54 | U48: =D48*1000 -> 103117 | V48: =F48*1000 -> 55493 | W48: =H48*1000 -> 14897
B49: 2019Q1 | C49: 359.662 | D49: 104.633 | E49: 101.096 | F49: 55.769 | G49: 28.555 | H49: 15.529 | I49: 1.2721094 | J49: 12.096 | K49: 577.487 | L49: 8.382 | M49: 585.869 | N49: 170.409 | O49: 754.818 | P49: 197.317 | Q49: 0 | R49: 557.458 | S49: 492.714 | U49: =D49*1000 -> 104633 | V49: =F49*1000 -> 55769 | W49: =H49*1000 -> 15529
B50: 2019Q2 | C50: 361.294 | D50: 106.675 | E50: 99.966 | F50: 55.923 | G50: 27.869 | H50: 14.865 | I50: 1.2866447 | J50: 1.782 | K50: 569.717 | L50: -1.872 | M50: 567.845 | N50: 167.62 | O50: 738.029 | P50: 179.982 | Q50: 0 | R50: 558.071 | S50: 493.64 | U50: =D50*1000 -> 106675 | V50: =F50*1000 -> 55923 | W50: =H50*1000 -> 14865
B51: 2019Q3 | C51: 360.291 | D51: 106.539 | E51: 101.637 | F51: 56.569 | G51: 28.495 | H51: 15.273 | I51: 1.3006638 | J51: 1.029 | K51: 569.496 | L51: -2.338 | M51: 567.158 | N51: 177.348 | O51: 743.234 | P51: 181.759 | Q51: 0 | R51: 561.48 | S51: 497.69 | U51: =D51*1000 -> 106539 | V51: =F51*1000 -> 56569 | W51: =H51*1000 -> 15273
B52: 2019Q4 | C52: 358.794 | D52: 107.732 | E52: 100.666 | F52: 56.999 | G52: 27.131 | H52: 15.181 | I52: 1.3168873 | J52: -12.027 | K52: 555.165 | L52: -1.541 | M52: 553.624 | N52: 184.277 | O52: 738.069 | P52: 176.744 | Q52: 0 | R52: 561.339 | S52: 497.911 | U52: =D52*1000 -> 107732 | V52: =F52*1000 -> 56999 | W52: =H52*1000 -> 15181
... B85: 2028Q1 | C85: 375.36498 | D85: 126.0461 | E85: 108.55032 | F85: 58.191273 | G85: 30.542127 | H85: 18.106857 | I85: 1.7100585 | J85: 0.72 | K85: 610.6814 | L85: 1.131594 | M85: 611.813 | N85: 165.35899 | O85: 777.17199 | P85: 171.5524 | Q85: 4.554 | R85: 610.17359 | S85: 547.22792 | U85: =D85*1000 -> 126046.1 | V85: =F85*1000 -> 58191.273 | W85: =H85*1000 -> 18106.857
B86: 2008 | C86: 1205.433 | D86: 377.632 | E86: 339.214 | F86: 187.9 | G86: 86.84 | H86: 57.494 | I86: 8.37 | J86: -1.04 | K86: 1921.239 | L86: -12.585 | M86: 1908.654 | N86: 547.614 | O86: 2457.353 | P86: 540.233 | Q86: 0 | R86: 1918.064 | S86: 1671.613
B87: 2009 | C87: 1169.802 | D87: 382.915 | E87: 296.49 | F87: 156.591 | G87: 67.433 | H87: 62.315 | I87: 10.669 | J87: 2.746 | K87: 1851.953 | L87: -33.166 | M87: 1818.787 | N87: 498.272 | O87: 2330.446 | P87: 500.192 | Q87: 0 | R87: 1831.55 | S87: 1597.686
B88: 2010 | C88: 1193.035 | D88: 383.508 | E88: 310.145 | F88: 163.639 | G88: 73.92 | H88: 62.78 | I88: 10.638 | J88: 0.006 | K88: 1886.694 | L88: -6.266 | M88: 1880.428 | N88: 532.319 | O88: 2416.844 | P88: 541.585 | Q88: 0 | R88: 1876.058 | S88: 1644.534
B89: 2011 | C89: 1188.95 | D89: 384.209 | E89: 308.777 | F89: 169.751 | G89: 70.591 | H89: 58.983 | I89: 9.913 | J89: -0.694 | K89: 1881.242 | L89: -3.532 | M89: 1877.71 | N89: 569.215 | O89: 2451.374 | P89: 555.79 | Q89: 0 | R89: 1896.087 | S89: 1671.9
B90: 2012 | C90: 1209.305 | D90: 389.496 | E90: 311.133 | F90: 178.74 | G90: 69.106 | H90: 54.469 | I90: 8.992 | J90: -1.029 | K90: 1908.905 | L90: 5.181 | M90: 1914.086 | N90: 573.794 | O90: 2489.967 | P90: 566.722 | Q90: 0 | R90: 1923.551 | S90: 1704.175
B91: 2013 | C91: 1240.91 | D91: 389.323 | E91: 321.785 | F91: 184.513 | G91: 76.533 | H91: 52.197 | I91: 8.457 | J91: 7.024 | K91: 1959.042 | L91: 6.926 | M91: 1965.968 | N91: 574.985 | O91: 2545.206 | P91: 586.462 | Q91: 0 | R91: 1958.557 | S91: 1736.245
B92: 2014 | C92: 1276.648 | D92: 397.73 | E92: 343.158 | F92: 195.628 | G92: 81.49 | H92: 56.145 | I92: 9.808 | J92: 6.063 | K92: 2023.599 | L92: 14.259 | M92: 2037.858 | N92: 581.483 | O92: 2637.203 | P92: 615.357 | Q92: 0 | R92: 2021.225 | S92: 1792.823
B93: 2015 | C93: 1316.612 | D93: 402.467 | E93: 365.569 | F93: 213.221 | G93: 87.131 | H93: 55.548 | I93: 9.603 | J93: 0.408 | K93: 2085.056 | L93: 11.775 | M93: 2096.831 | N93: 604.67 | O93: 2716.081 | P93: 645.838 | Q93: 0 | R93: 2069.595 | S93: 1831.193
B94: 2016 | C94: 1364.268 | D94: 405.583 | E94: 383.449 | F94: 223.246 | G94: 94.107 | H94: 55.694 | I94: 9.719 | J94: 1.609 | K94: 2154.909 | L94: 8.203 | M94: 2163.112 | N94: 624.134 | O94: 2786.046 | P94: 671.533 | Q94: 0 | R94: 2114.406 | S94: 1869.814
B95: 2017 | C95: 1390.682 | D95: 407.301 | E95: 396.907 | F95: 225.675 | G95: 103.808 | H95: 57.756 | I95: 9.604 | J95: 0.612 | K95: 2195.502 | L95: 12.671 | M95: 2208.173 | N95: 666.851 | O95: 2859.99 | P95: 693.975 | Q95: 0 | R95: 2166.073 | S95: 1918.119
B96: 2018 | C96: 1424.923 | D96: 408.625 | E96: 395.967 | F96: 222.35 | G96: 110.099 | H96: 58.367 | I96: 5.35 | J96: 3.132 | K96: 2232.647 | L96: 1.317 | M96: 2233.964 | N96: 687.856 | O96: 2920.105 | P96: 717.135 | Q96: 0 | R96: 2203.005 | S96: 1948.238
B97: 2019 | C97: 1440.041 | D97: 425.579 | E97: 403.365 | F97: 225.26 | G97: 112.05 | H97: 60.848 | I97: 5.1763052 | J97: 2.88 | K97: 2271.865 | L97: 2.631 | M97: 2274.496 | N97: 699.654 | O97: 2974.15 | P97: 735.802 | Q97: 0 | R97: 2238.348 | S97: 1981.955
... B105: 2027 | C105: 1486.2718 | D105: 498.66013 | E105: 430.56766 | F105: 229.77995 | G105: 120.78732 | H105: 73.229735 | I105: 6.7706588 | J105: 2.88 | K105: 2418.3796 | L105: 4.4458618 | M105: 2422.8254 | N105: 660.56175 | O105: 3083.3872 | P105: 687.38973 | Q105: 18.216 | R105: 2414.2135 | S105: 2164.4356
B106: 2008-09 | C106: 1188.622 | D106: 379.451 | E106: 328.506 | F106: 181.946 | G106: 79.035 | H106: 59.204 | I106: 9.563 | J106: 0.221 | K106: 1896.8 | L106: -18.812 | M106: 1877.988 | N106: 534.295 | O106: 2412.366 | P106: 524.732 | Q106: 0 | R106: 1888.644 | S106: 1644.304
B107: 2009-10 | C107: 1171.371 | D107: 383.055 | E107: 296.106 | F107: 155.234 | G107: 67.399 | H107: 63.268 | I107: 10.699 | J107: 1.191 | K107: 1851.723 | L107: -25.225 | M107: 1826.498 | N107: 502.12 | O107: 2342.965 | P107: 507.471 | Q107: 0 | R107: 1836.76 | S107: 1605.212
B108: 2010-11 | C108: 1197.005 | D108: 385.065 | E108: 310.745 | F108: 163.871 | G108: 74.538 | H108: 62.659 | I108: 10.56 | J108: -1.435 | K108: 1891.38 | L108: -6.668 | M108: 1884.712 | N108: 546.561 | O108: 2432.704 | P108: 547.287 | Q108: 0 | R108: 1886.177 | S108: 1655.504
B109: 2011-12 | C109: 1189.672 | D109: 386.31 | E109: 312.028 | F109: 175.603 | G109: 70.101 | H109: 56.972 | I109: 9.608 | J109: -0.442 | K109: 1887.568 | L109: -5.545 | M109: 1882.023 | N109: 574.831 | O109: 2461.197 | P109: 560.727 | Q109: 0 | R109: 1900.819 | S109: 1678.682
B110: 2012-13 | C110: 1217.443 | D110: 387.838 | E110: 307.724 | F110: 177.479 | G110: 69.422 | H110: 52.103 | I110: 8.817 | J110: 1.321 | K110: 1914.326 | L110: 9.278 | M110: 1923.604 | N110: 569.225 | O110: 2495.758 | P110: 566.33 | Q110: 0 | R110: 1929.864 | S110: 1710.751
B111: 2013-14 | C111: 1249.984 | D111: 390.889 | E111: 330.4 | F111: 187.624 | G111: 78.746 | H111: 55.508 | I111: 8.505 | J111: 7.386 | K111: 1978.659 | L111: 3.996 | M111: 1982.655 | N111: 573.964 | O111: 2568.016 | P111: 594.249 | Q111: 0 | R111: 1973.296 | S111: 1747.463
B112: 2014-15 | C112: 1287.305 | D112: 398.201 | E112: 349.151 | F112: 200.871 | G112: 82.146 | H112: 55.742 | I112: 10.284 | J112: 7.213 | K112: 2041.87 | L112: 22.856 | M112: 2064.726 | N112: 587.819 | O112: 2665.646 | P112: 629.983 | Q112: 0 | R112: 2034.826 | S112: 1805.489
B113: 2015-16 | C113: 1328.582 | D113: 404.282 | E113: 369.134 | F113: 216.402 | G113: 89.078 | H113: 54.097 | I113: 9.327 | J113: -1.128 | K113: 2100.87 | L113: 6.306 | M113: 2107.176 | N113: 609.207 | O113: 2728.783 | P113: 647.507 | Q113: 0 | R113: 2080.802 | S113: 1839.766
B114: 2016-17 | C114: 1372.362 | D114: 405.632 | E114: 386.648 | F114: 223.079 | G114: 96.965 | H114: 56.26 | I114: 9.798 | J114: -0.042 | K114: 2164.6 | L114: 11.522 | M114: 2176.122 | N114: 632.736 | O114: 2803.556 | P114: 676.058 | Q114: 0 | R114: 2127.418 | S114: 1882.962
B115: 2017-18 | C115: 1398.297 | D115: 407.551 | E115: 398.076 | F115: 226.316 | G115: 105.438 | H115: 57.828 | I115: 8.515 | J115: 1.768 | K115: 2205.692 | L115: 5.379 | M115: 2211.071 | N115: 675.894 | O115: 2876.738 | P115: 700.911 | Q115: 0 | R115: 2175.962 | S115: 1926.445
B116: 2018-19 | C116: 1431.205 | D116: 411.629 | E116: 398.144 | F116: 221.638 | G116: 111.555 | H116: 59.879 | I116: 5.2451094 | J116: 14.746 | K116: 2255.724 | L116: 12.421 | M116: 2268.145 | N116: 687.24 | O116: 2951.761 | P116: 738.299 | Q116: 0 | R116: 2213.46 | S116: 1956.762
B117: 2019-20 | C117: 1428.71 | D117: 425.034 | E117: 399.094 | F117: 224.968 | G117: 109.43 | H117: 59.445 | I117: 5.1833992 | J117: -8.432 | K117: 2244.406 | L117: -9.231 | M117: 2235.175 | N117: 696.896 | O117: 2933.531 | P117: 706.169 | Q117: 0 | R117: 2227.405 | S117: 1975.013
... B125: 2027-28 | C125: 1492.3882 | D125: 500.88599 | E125: 432.0972 | F125: 231.01376 | G125: 121.37388 | H125: 72.909381 | I125: 6.8001734 | J125: 2.88 | K125: 2428.2514 | L125: 4.1684978 | M125: 2432.4199 | N125: 661.03261 | O125: 3093.4525 | P125: 686.79944 | Q125: 18.216 | R125: 2424.8691 | S125: 2174.2862
B126: Definitions:
B127: Household and non-profit institutions serving households final consumption expenditure (ONS Economic Accounts Table 1.1.2, identifier: ABJR + HAYO)
B128: General government final consumption (ONS Economic Accounts Table 1.1.2, identifier: NMRY)
B129: Total gross fixed capital formation (ONS Economic Accounts Table 1.1.2, identifier: NPQT)
B130: Business investment (ONS Economic Accounts Table 1.1.8, identifier: NPEL)
B131: Private sector investment in dwellings, including transfer costs (ONS Economic Accounts Table 1.1.8, identifier: L636 + L637)
B132: General government gross fixed capital formation (ONS Economic Accounts Table 1.1.8, identifier: DLWF)
B133: Public corporations investment in dwellings, including transfer costs (ONS Economic Accounts Table 1.1.8, identifier: L634 + L635)
B134: Net acquisitions of valuables (ONS Economic Accounts Table 1.1.2, identifier: NPJR)
B135: Final domestic demand is the sum of private consumption, government consumption, fixed investment and net acquisition of valuables
B136: Change in inventories (ONS Economic Accounts Table 1.1.2, identifier: CAFU)
B137: Total domestic demand is the sum of final domestic demand and change in inventories
... B142: Gross domestic product at market prices (ONS Economic Accounts Table 1.1.2, identifier: ABMI)

Sheet OBR_MAR23_1.2
A1: Back to contents
B2: 1.2 GDP expenditure components (£ billion current prices, seasonally adjusted) | S2: Deflators
C3: Private consumption | D3: Government consumption | E3: Fixed investment | G3: Net acquisition of valuables | H3: Final domestic demand | I3: Change in inventories | J3: Total domestic demand | K3: Exports | L3: Total final expenditure | M3: Imports | N3: Statistical discrepancy | O3: GDP at market prices | P3: Gross national income | S3: C | T3: GC | U3: IF | V3: X | W3: M | X3: GDP | Z3: C | AA3: GC | AB3: IF | AC3: X | AD3: M | AE3: GDP
E4: of which: | F4: General government
B5: 2008Q1 | C5: 256.262 | D5: 80.113 | E5: 70.975 | F5: 11.187 | G5: 0.083 | H5: 407.433 | I5: -0.106 | J5: 407.327 | K5: 103.927 | L5: 511.254 | M5: 113.981 | N5: 0 | O5: 397.273 | P5: 396.644 | S5: =100*(C5/OBR_MAR23_1.1!C5) -> 83.098884 | T5: =100*(D5/OBR_MAR23_1.1!D5) -> 85.664945 | U5: =100*(E5/OBR_MAR23_1.1!E5) -> 81.554212 | V5: =100*(K5/OBR_MAR23_1.1!N5) -> 75.468012 | W5: =100*(M5/OBR_MAR23_1.1!P5) -> 82.246275 | X5: =100*(O5/OBR_MAR23_1.1!R5) -> 81.475017
B6: 2008Q2 | C6: 257.037 | D6: 80.391 | E6: 71.776 | F6: 11.23 | G6: 0.235 | H6: 409.439 | I6: 0.379 | J6: 409.818 | K6: 109.9 | L6: 519.718 | M6: 118.702 | N6: 0 | O6: 401.016 | P6: 396.209 | S6: =100*(C6/OBR_MAR23_1.1!C6) -> 84.338302 | T6: =100*(D6/OBR_MAR23_1.1!D6) -> 86.175071 | U6: =100*(E6/OBR_MAR23_1.1!E6) -> 81.994105 | V6: =100*(K6/OBR_MAR23_1.1!N6) -> 79.408662 | W6: =100*(M6/OBR_MAR23_1.1!P6) -> 86.115786 | X6: =100*(O6/OBR_MAR23_1.1!R6) -> 82.636345 | AA6: =100*((T6/T5)-1) -> 0.59548939
B7: 2008Q3 | C7: 256.698 | D7: 81.316 | E7: 68.904 | F7: 11.844 | G7: -0.896 | H7: 406.022 | I7: 1.672 | J7: 407.694 | K7: 112.577 | L7: 520.271 | M7: 119.412 | N7: 0 | O7: 400.859 | P7: 396.438 | S7: =100*(C7/OBR_MAR23_1.1!C7) -> 85.659083 | T7: =100*(D7/OBR_MAR23_1.1!D7) -> 85.655297 | U7: =100*(E7/OBR_MAR23_1.1!E7) -> 82.953902 | V7: =100*(K7/OBR_MAR23_1.1!N7) -> 81.264843 | W7: =100*(M7/OBR_MAR23_1.1!P7) -> 88.080135 | X7: =100*(O7/OBR_MAR23_1.1!R7) -> 83.873121 | AA7: =100*((T7/T6)-1) -> -0.6031598
B8: 2008Q4 | C8: 248.979 | D8: 83.542 | E8: 67.898 | F8: 12.594 | G8: 0.389 | H8: 400.808 | I8: -2.392 | J8: 398.416 | K8: 109.095 | L8: 507.511 | M8: 111.922 | N8: 0 | O8: 395.589 | P8: 384.35 | S8: =100*(C8/OBR_MAR23_1.1!C8) -> 85.089608 | T8: =100*(D8/OBR_MAR23_1.1!D8) -> 87.121836 | U8: =100*(E8/OBR_MAR23_1.1!E8) -> 83.223632 | V8: =100*(K8/OBR_MAR23_1.1!N8) -> 82.041737 | W8: =100*(M8/OBR_MAR23_1.1!P8) -> 87.278143 | X8: =100*(O8/OBR_MAR23_1.1!R8) -> 84.663242 | AA8: =100*((T8/T7)-1) -> 1.7121403
B9: 2009Q1 | C9: 248.741 | D9: 84.362 | E9: 64.424 | F9: 12.677 | G9: 1.227 | H9: 398.754 | I9: -5.687 | J9: 393.067 | K9: 102.555 | L9: 495.623 | M9: 108.547 | N9: 0 | O9: 387.076 | P9: 380.087 | S9: =100*(C9/OBR_MAR23_1.1!C9) -> 85.31061 | T9: =100*(D9/OBR_MAR23_1.1!D9) -> 88.487277 | U9: =100*(E9/OBR_MAR23_1.1!E9) -> 84.412998 | V9: =100*(K9/OBR_MAR23_1.1!N9) -> 82.445675 | W9: =100*(M9/OBR_MAR23_1.1!P9) -> 88.189367 | X9: =100*(O9/OBR_MAR23_1.1!R9) -> 84.481024 | AA9: =100*((T9/T8)-1) -> 1.5672771
B10: 2009Q2 | C10: 248.849 | D10: 84.466 | E10: 61.696 | F10: 11.955 | G10: 0.708 | H10: 395.719 | I10: -4.218 | J10: 391.501 | K10: 101.19 | L10: 492.692 | M10: 105.796 | N10: 0 | O10: 386.896 | P10: 381.044 | S10: =100*(C10/OBR_MAR23_1.1!C10) -> 85.510419 | T10: =100*(D10/OBR_MAR23_1.1!D10) -> 88.697771 | U10: =100*(E10/OBR_MAR23_1.1!E10) -> 84.277245 | V10: =100*(K10/OBR_MAR23_1.1!N10) -> 81.983683 | W10: =100*(M10/OBR_MAR23_1.1!P10) -> 86.060586 | X10: =100*(O10/OBR_MAR23_1.1!R10) -> 84.684602 | AA10: =100*((T10/T9)-1) -> 0.23788029
B11: 2009Q3 | C11: 250.141 | D11: 86.323 | E11: 62.079 | F11: 13.279 | G11: 0.429 | H11: 398.972 | I11: -3.074 | J11: 395.898 | K11: 101.927 | L11: 497.825 | M11: 107.965 | N11: 0 | O11: 389.86 | P11: 390.703 | S11: =100*(C11/OBR_MAR23_1.1!C11) -> 85.538761 | T11: =100*(D11/OBR_MAR23_1.1!D11) -> 90.117863 | U11: =100*(E11/OBR_MAR23_1.1!E11) -> 83.837293 | V11: =100*(K11/OBR_MAR23_1.1!N11) -> 83.206394 | W11: =100*(M11/OBR_MAR23_1.1!P11) -> 85.602264 | X11: =100*(O11/OBR_MAR23_1.1!R11) -> 85.220703 | AA11: =100*((T11/T10)-1) -> 1.6010465
B12: 2009Q4 | C12: 251.117 | D12: 86.12 | E12: 60.582 | F12: 12.822 | G12: -0.012 | H12: 397.807 | I12: -5.721 | J12: 392.086 | K12: 107.582 | L12: 499.668 | M12: 111.618 | N12: 0 | O12: 388.05 | P12: 386.988 | S12: =100*(C12/OBR_MAR23_1.1!C12) -> 85.186492 | T12: =100*(D12/OBR_MAR23_1.1!D12) -> 89.188993 | U12: =100*(E12/OBR_MAR23_1.1!E12) -> 83.083506 | V12: =100*(K12/OBR_MAR23_1.1!N12) -> 84.077996 | W12: =100*(M12/OBR_MAR23_1.1!P12) -> 87.166151 | X12: =100*(O12/OBR_MAR23_1.1!R12) -> 84.536774 | AA12: =100*((T12/T11)-1) -> -1.0307279
B13: 2010Q1 | C13: 249.975 | D13: 87.108 | E13: 62.645 | F13: 12.868 | G13: -0.053 | H13: 399.675 | I13: 3.211 | J13: 402.886 | K13: 109.599 | L13: 512.484 | M13: 115.348 | N13: 0 | O13: 397.136 | P13: 397.26 | S13: =100*(C13/OBR_MAR23_1.1!C13) -> 85.274954 | T13: =100*(D13/OBR_MAR23_1.1!D13) -> 91.233583 | U13: =100*(E13/OBR_MAR23_1.1!E13) -> 82.497103 | V13: =100*(K13/OBR_MAR23_1.1!N13) -> 85.46464 | W13: =100*(M13/OBR_MAR23_1.1!P13) -> 88.482161 | X13: =100*(O13/OBR_MAR23_1.1!R13) -> 85.702139 | AA13: =100*((T13/T12)-1) -> 2.2924234
B14: 2010Q2 | C14: 258.212 | D14: 86.411 | E14: 63.088 | F14: 12.547 | G14: -0.413 | H14: 407.298 | I14: 0.691 | J14: 407.989 | K14: 115.067 | L14: 523.055 | M14: 120.664 | N14: 0 | O14: 402.391 | P14: 402.845 | S14: =100*(C14/OBR_MAR23_1.1!C14) -> 86.078127 | T14: =100*(D14/OBR_MAR23_1.1!D14) -> 90.233282 | U14: =100*(E14/OBR_MAR23_1.1!E14) -> 83.475131 | V14: =100*(K14/OBR_MAR23_1.1!N14) -> 86.485329 | W14: =100*(M14/OBR_MAR23_1.1!P14) -> 89.900164 | X14: =100*(O14/OBR_MAR23_1.1!R14) -> 85.85422 | AA14: =100*((T14/T13)-1) -> -1.0964173
B15: 2010Q3 | C15: 260.179 | D15: 86.135 | E15: 65.112 | F15: 12.736 | G15: 0.502 | H15: 411.928 | I15: 1.746 | J15: 413.674 | K15: 115.566 | L15: 529.24 | M15: 124.011 | N15: 0 | O15: 405.229 | P15: 404.696 | S15: =100*(C15/OBR_MAR23_1.1!C15) -> 86.713037 | T15: =100*(D15/OBR_MAR23_1.1!D15) -> 89.931926 | U15: =100*(E15/OBR_MAR23_1.1!E15) -> 83.098717 | V15: =100*(K15/OBR_MAR23_1.1!N15) -> 86.343803 | W15: =100*(M15/OBR_MAR23_1.1!P15) -> 89.829195 | X15: =100*(O15/OBR_MAR23_1.1!R15) -> 85.914761 | AA15: =100*((T15/T14)-1) -> -0.33397423
B16: 2010Q4 | C16: 262.215 | D16: 87.58 | E16: 66.631 | F16: 12.387 | G16: 0.404 | H16: 416.83 | I16: -1.789 | J16: 415.041 | K16: 120.258 | L16: 535.299 | M16: 127.674 | N16: 0 | O16: 407.625 | P16: 408.248 | S16: =100*(C16/OBR_MAR23_1.1!C16) -> 87.441434 | T16: =100*(D16/OBR_MAR23_1.1!D16) -> 90.767764 | U16: =100*(E16/OBR_MAR23_1.1!E16) -> 83.001358 | V16: =100*(K16/OBR_MAR23_1.1!N16) -> 87.65927 | W16: =100*(M16/OBR_MAR23_1.1!P16) -> 91.884851 | X16: =100*(O16/OBR_MAR23_1.1!R16) -> 86.30418 | AA16: =100*((T16/T15)-1) -> 0.92941183
B17: 2011Q1 | C17: 264.269 | D17: 89.676 | E17: 63.852 | F17: 12.884 | G17: -1.261 | H17: 416.536 | I17: -0.775 | J17: 415.761 | K17: 127.172 | L17: 542.933 | M17: 127.452 | N17: 0 | O17: 415.481 | P17: 417.18 | S17: =100*(C17/OBR_MAR23_1.1!C17) -> 88.946518 | T17: =100*(D17/OBR_MAR23_1.1!D17) -> 92.416139 | U17: =100*(E17/OBR_MAR23_1.1!E17) -> 83.427407 | V17: =100*(K17/OBR_MAR23_1.1!N17) -> 89.255409 | W17: =100*(M17/OBR_MAR23_1.1!P17) -> 93.669937 | X17: =100*(O17/OBR_MAR23_1.1!R17) -> 87.744926 | AA17: =100*((T17/T16)-1) -> 1.8160353
... B55: 2020Q3 | C55: 322.92 | D55: 121.224 | E55: 92.277 | F55: 16.75 | G55: 1.218 | H55: 537.639 | I55: -2.672 | J55: 534.967 | K55: 146.334 | L55: 681.302 | M55: 147.131 | N55: 0 | O55: 534.171 | P55: 525.918 | S55: =100*(C55/OBR_MAR23_1.1!C55) -> 101.17873 | T55: =100*(D55/OBR_MAR23_1.1!D55) -> 120.42558 | U55: =100*(E55/OBR_MAR23_1.1!E55) -> 101.17094 | V55: =100*(K55/OBR_MAR23_1.1!N55) -> 100.1924 | W55: =100*(M55/OBR_MAR23_1.1!P55) -> 98.131165 | X55: =100*(O55/OBR_MAR23_1.1!R55) -> 106.08966 | AA55: =100*((T55/T54)-1) -> -15.431548
B56: 2020Q4 | C56: 318.576 | D56: 123.7 | E56: 95.192 | F56: 17.269 | G56: 7.618 | H56: 545.086 | I56: 9.625 | J56: 554.711 | K56: 156.266 | L56: 710.977 | M56: 171.311 | N56: 0 | O56: 539.666 | P56: 526.934 | S56: =100*(C56/OBR_MAR23_1.1!C56) -> 101.18149 | T56: =100*(D56/OBR_MAR23_1.1!D56) -> 118.33923 | U56: =100*(E56/OBR_MAR23_1.1!E56) -> 101.1003 | V56: =100*(K56/OBR_MAR23_1.1!N56) -> 100.89554 | W56: =100*(M56/OBR_MAR23_1.1!P56) -> 99.367177 | X56: =100*(O56/OBR_MAR23_1.1!R56) -> 105.89556 | Z56: =100*((S56/S55)-1) -> 0.0027337443 | AA56: =100*((T56/T55)-1) -> -1.7324772
B57: 2021Q1 | C57: 310.285 | D57: 128.685 | E57: 93.412 | F57: 17.344 | G57: 8.496 | H57: 540.878 | I57: 3.91 | J57: 544.788 | K57: 150.916 | L57: 695.704 | M57: 156.818 | N57: -0.979 | O57: 537.907 | P57: 537.029 | S57: =100*(C57/OBR_MAR23_1.1!C57) -> 102.21874 | T57: =100*(D57/OBR_MAR23_1.1!D57) -> 123.28866 | U57: =100*(E57/OBR_MAR23_1.1!E57) -> 100.87253 | V57: =100*(K57/OBR_MAR23_1.1!N57) -> 101.71941 | W57: =100*(M57/OBR_MAR23_1.1!P57) -> 101.03536 | X57: =100*(O57/OBR_MAR23_1.1!R57) -> 106.67361 | Z57: =100*((S57/S56)-1) -> 1.0251404 | AA57: =100*((T57/T56)-1) -> 4.1824023
