Workbook
Name Annual_Data: '$template-default'!$A$1:$A$2

Sheet $template-default

Sheet >> CHARTS

Sheet >> DATA

Sheet Chart Data
B1: GDP levels | I1: Public sector net debt (ex BoE) | L1: Change year-to-year | V1: Real government spending across fiscal events | CM1: Public sector net investment | CR1: Public sector current budget | CW1: Cyclically-adjusted current budget | DD1: Higher growth scenario | DQ1: >> NOT USED | DT1: Real government spending per head across fiscal events | EU1: Cyclically-adjusted current budget
V2: Real PSCE in RDEL per head (2023-2024=100) | AC2: Real PSGI in RDEL per head (2023-2024=100) | AJ2: Real PSCE in RDEL per head (2023-2024 prices) | AP2: Real PSGI in RDEL per head (2023-2024 prices) | AV2: PSCE in RDEL per head | BB2: PSGI in RDEL per head | BH2: PSCE in RDEL | BN2: PSGI in RDEL | BT2: GDP deflator (2023-2024 = 100) | BZ2: GDP deflator (raw) | CF2: Population | DA2: Output gap | DE2: GDP | DI2: PSNDX | DM2: CACB | DT2: Real PSCE in RDEL per head (2023-2024=100) | EA2: Real PSGI in RDEL per head (2023-2024=100) | EI2: Real PSCE in RDEL per capita | EO2: Real PSGI in CDEL per capita | EZ2: CACB - baseline | FC2: CACB - scenario
B3: Current baseline | C3: New fiscal rules scenario | D3: 100 LINE | F3: Diff | I3: Current baseline | J3: New fiscal rules scenario | L3: Current baseline | M3: New fiscal rules scenario | O3: Current baseline | P3: New fiscal rules scenario | R3: BoE | S3: APF valuation losses | V3: 44621 | W3: 44866 | X3: 44986 | Y3: 45231 | Z3: 45352 | AA3: 100 LINE | AC3: 44621 | AD3: 44866 | AE3: 44986 | AF3: 45231 | AG3: 45352 | AH3: 100 LINE | AJ3: 44621 | AK3: 44866 | AL3: 44986 | AM3: 45231 | AN3: 45352 | AP3: 44621 | AQ3: 44866 | AR3: 44986 | AS3: 45231 | AT3: 45352 | AV3: SS22 | AW3: AS22 | AX3: Budget23 | AY3: AS23 | AZ3: Budget24 | BB3: SS22 | BC3: AS22 | BD3: Budget23 | BE3: AS23 | BF3: Budget24 | BH3: SS22 | BI3: AS22 | BJ3: Budget23 | BK3: AS23 | BL3: Budget24 | BN3: SS22 | BO3: AS22 | BP3: Budget23 | BQ3: AS23 | BR3: Budget24 | BT3: SS22 | BU3: AS22 | BV3: Budget23 | BW3: AS23 | BX3: Budget24 | BZ3: SS22 | CA3: AS22 | CB3: Budget23 | CC3: AS23 | CD3: Budget24 | CF3: SS22 | CG3: AS22 | CH3: Budget23 | CI3: AS23 | CJ3: Budget24 | CM3: Current baseline | CN3: New fiscal rules scenario | CO3: 3% LINE | CR3: Current baseline | CS3: New fiscal rules scenario | CT3: ZERO LINE | CW3: Current baseline | CX3: New fiscal rules scenario | CY3: ZERO LINE | DA3: Current baseline | DB3: New fiscal rules scenario | DE3: Current baseline | DF3: New fiscal rules | DG3: New fiscal rules & higher growth | DI3: Current baseline | DJ3: New fiscal rules | DK3: New fiscal rules & higher growth | DM3: Current baseline | DN3: New fiscal rules | DO3: New fiscal rules & higher growth | DT3: 44621 | DU3: 44866 | DV3: 44986 | DW3: 45231 | DX3: 45352 | DY3: 100 LINE | EA3: 44621 | EB3: 44866 | EC3: 44986 | ED3: 45231 | EE3: 45352 | EF3: 100 LINE | EI3: 44621 | EJ3: 44866 | EK3: 44986 | EL3: 45231 | EM3: 45352 | EO3: 44621 | EP3: 44866 | EQ3: 44986 | ER3: 45231 | ES3: 45352 | EV3: Current baseline | EW3: New fiscal rules scenario | EX3: ZERO LINE | EZ3: Structural revenue | FA3: Structural expenditure | FC3: Structural revenue | FD3: Structural expenditure
A4: 2000 | B4: =100*(Data!BO27/Data!BO$46) -> 73.434314 | C4: =100*(Data!CH27/Data!CH$46) -> 73.434314 | D4: 100 | F4: =100*((C4/B4)-1) -> 0 | H4: 2000 | I4: =100*(O4/Data!$BW27) -> 30.093194 | J4: =100*(P4/Data!$CP27) -> 30.093194 | O4: =Data!BV27-$R4 -> 334500 | P4: =Data!CO27-$R4 -> 334500 | R4: ='GNDBTX ex BoE'!D120 -> -12500 | U4: 2019-20 | V4: =100*(AJ4/AJ$9) -> 88.103473 | AA4: 100 | AC4: =100*(AP4/AP$9) -> 70.104704 | AH4: 100 | AJ4: =100*(AV4/BT4) -> 5.3631027 | AP4: =100*(BB4/BT4) -> 0.96593107 | AV4: =BH4/(CF4/1000) -> 4.8043274 | BB4: =BN4/(CF4/1000) -> 0.86529185 | BH4: {=TRANSPOSE(OBR_MAR22_T3.16!C8:J8)} -> 321.42632 | BN4: {=TRANSPOSE(OBR_MAR22_T3.16!C31:J31)} -> 57.891053 | BT4: =100*(BZ4/BZ$8) -> 89.581117 | BU4: =100*(CA4/CA$8) -> 87.221869 | BV4: =100*(CB4/CB$8) -> 87.485684 | BW4: =100*(CC4/CC$8) -> 84.464903 | BX4: =100*(CD4/CD$8) -> 84.011728 | BZ4: =OBR_MAR22_1.2!X112 -> 100.74871 | CA4: =OBR_NOV22_1.2!X117 -> 100.88484 | CB4: =OBR_MAR23_1.2!X117 -> 100.88484 | CC4: =OBR_NOV23_1.2!X122 -> 100.73409 | CD4: =OBR_MAR24_1.2!X122 -> 100.73409 | CF4: {=TRANSPOSE(OBR_MAR22_ST3.3!Q34:X34)} -> 66903.5 | CG4: {=TRANSPOSE(OBR_NOV22_ST3.3!Q34:Y34)} -> 66903.5 | CH4: {=TRANSPOSE(OBR_MAR23_ST3.3!Q34:Y34)} -> 66903.5 | CI4: {=TRANSPOSE(OBR_NOV23_ST3.3!Q34:Z34)} -> 66903.5 | CJ4: {=TRANSPOSE(OBR_MAR24_ST4.3!Q34:Z34)} -> 66903.5 | CL4: 2000 | CM4: =100*(Data!BS27/Data!$BW27) -> 0.40583079 | CN4: =100*(Data!CL27/Data!$CP27) -> 0.40583079 | CO4: 3 | CQ4: 2000 | CR4: =100*(Data!BQ27/Data!$BW27) -> 1.8496744 | CS4: =100*(Data!CJ27/Data!$CP27) -> 1.8496744 | CT4: 0 | CV4: 2000 | CW4: =CR4-DA4 -> -1.7681846 | CX4: =CS4-DB4 -> -1.7681846 | CY4: 0 | DA4: =Data!CF27 -> 3.617859 | DB4: =Data!CY27 -> 3.617859 | DD4: 2000 | DE4: =100*(Data!BO27/Data!BO$46) -> 73.434314 | DF4: =100*(Data!CH27/Data!CH$46) -> 73.434314 | DG4: =100*(Data!DA27/Data!DA$46) -> 73.434314 | DI4: =I4 -> 30.093194 | DJ4: =J4 -> 30.093194 | DK4: =100*(Data!DH27-$R4)/Data!DI27 -> 30.093194 | DM4: =CW4 -> -1.7681846 | DN4: =CX4 -> -1.7681846 | DO4: =(100*(Data!DC27/Data!$DI27))-Data!$DR27 -> -1.7681846 | DS4: 2007-08 | DT4: =100*(EI4/EI$20) -> 95.558492 | DU4: =100*(EJ4/EJ$20) -> 96.229945 | DV4: =100*(EK4/EK$20) -> 95.912198 | DW4: =100*(EL4/EL$20) -> 99.049288 | DX4: =100*(EM4/EM$20) -> 100.43541 | DY4: 100 | EA4: =100*(EO4/EO$20) -> 77.851095 | EB4: =100*(EP4/EP$20) -> 80.810199 | EC4: =100*(EQ4/EQ$20) -> 98.927543 | ED4: =100*(ER4/ER$20) -> 83.163642 | EE4: =100*(ES4/ES$20) -> 83.985641 | EF4: 100 | EH4: 2007-08 | EI4: {=TRANSPOSE(OBR_MAR22_ST3.3!E11:X11)} -> 5424.4566 | EJ4: {=TRANSPOSE(OBR_NOV22_ST3.3!E11:Y11)} -> 5758.8387 | EK4: {=TRANSPOSE(OBR_MAR23_ST3.3!E11:Y11)} -> 5781.014 | EL4: {=TRANSPOSE(OBR_NOV23_ST3.3!E11:Z11)} -> 5806.2508 | EM4: {=TRANSPOSE(OBR_MAR24_ST4.3!E11:Z11)} -> 6193.1143 | EO4: {=TRANSPOSE(OBR_MAR22_ST3.3!E17:X17)} -> 1025.1214 | EP4: {=TRANSPOSE(OBR_NOV22_ST3.3!E17:Y17)} -> 1088.3134 | EQ4: {=TRANSPOSE(OBR_MAR23_ST3.3!E17:Y17)} -> 1092.5041 | ER4: {=TRANSPOSE(OBR_NOV23_ST3.3!E17:Z17)} -> 1097.2734 | ES4: {=TRANSPOSE(OBR_MAR24_ST4.3!E17:Z17)} -> 1170.3834 | EU4: 2000 | EV4: =100*((EZ4-FA4)/Data!BX27*Data!BY27*0.01) -> 0.85646479 | EW4: =100*((FC4-FD4)/Data!CQ27*Data!CR27*0.01) -> 0.85646479 | EX4: 0 | EZ4: =Data!BU27*(Data!BX27*Data!BY27*0.01/Data!BW27)^1 -> 392499.41 | FA4: =(Data!BR27+Data!BT27)*(Data!BX27*Data!BY27*0.01/Data!BW27)^1 -> 372671.58 | FC4: =Data!CN27*(Data!CQ27*Data!CR27*0.01/Data!CP27)^1 -> 392499.41 | FD4: =(Data!CK27+Data!CM27)*(Data!CQ27*Data!CR27*0.01/Data!CP27)^1 -> 372671.58
A5: 2001 | B5: =100*(Data!BO28/Data!BO$46) -> 75.074594 | C5: =100*(Data!CH28/Data!CH$46) -> 75.074594 | D5: 100 | F5: =100*((C5/B5)-1) -> 0 | H5: 2001 | I5: =100*(O5/Data!$BW28) -> 29.144049 | J5: =100*(P5/Data!$CP28) -> 29.144049 | O5: =Data!BV28-$R5 -> 336800 | P5: =Data!CO28-$R5 -> 336800 | R5: ='GNDBTX ex BoE'!D121 -> -6200 | U5: 2020-21 | V5: =100*(AJ5/AJ$9) -> 112.38525 | AA5: 100 | AC5: =100*(AP5/AP$9) -> 82.988486 | AH5: 100 | AJ5: =100*(AV5/BT5) -> 6.8412017 | AP5: =100*(BB5/BT5) -> 1.1434491 | AV5: =BH5/(CF5/1000) -> 6.4777615 | BB5: =BN5/(CF5/1000) -> 1.0827031 | BH5: 434.5177 | BN5: 72.625962 | BT5: =100*(BZ5/BZ$8) -> 94.68748 | BU5: =100*(CA5/CA$8) -> 92.72465 | BV5: =100*(CB5/CB$8) -> 92.876405 | BW5: =100*(CC5/CC$8) -> 88.965576 | BX5: =100*(CD5/CD$8) -> 88.488253 | BZ5: =OBR_MAR22_1.2!X113 -> 106.49166 | CA5: =OBR_NOV22_1.2!X118 -> 107.24961 | CB5: =OBR_MAR23_1.2!X118 -> 107.10119 | CC5: =OBR_NOV23_1.2!X123 -> 106.10166 | CD5: =OBR_MAR24_1.2!X123 -> 106.10166 | CF5: 67078.373 | CG5: 67249.5 | CH5: 67182 | CI5: 67060.5 | CJ5: 67060.5 | CL5: 2001 | CM5: =100*(Data!BS28/Data!$BW28) -> 1.0938537 | CN5: =100*(Data!CL28/Data!$CP28) -> 1.0938537 | CO5: 3 | CQ5: 2001 | CR5: =100*(Data!BQ28/Data!$BW28) -> 0.57820825 | CS5: =100*(Data!CJ28/Data!$CP28) -> 0.57820825 | CT5: 0 | CV5: 2001 | CW5: =CR5-DA5 -> -1.9299548 | CX5: =CS5-DB5 -> -1.9299548 | CY5: 0 | DA5: =Data!CF28 -> 2.508163 | DB5: =Data!CY28 -> 2.508163 | DD5: 2001 | DE5: =100*(Data!BO28/Data!BO$46) -> 75.074594 | DF5: =100*(Data!CH28/Data!CH$46) -> 75.074594 | DG5: =100*(Data!DA28/Data!DA$46) -> 75.074594 | DI5: =I5 -> 29.144049 | DJ5: =J5 -> 29.144049 | DK5: =100*(Data!DH28-$R5)/Data!DI28 -> 29.144049 | DM5: =CW5 -> -1.9299548 | DN5: =CX5 -> -1.9299548 | DO5: =(100*(Data!DC28/Data!$DI28))-Data!$DR28 -> -1.9299548 | DS5: 2008-09 | DT5: =100*(EI5/EI$20) -> 96.378326 | DU5: =100*(EJ5/EJ$20) -> 96.4484 | DV5: =100*(EK5/EK$20) -> 96.129932 | DW5: =100*(EL5/EL$20) -> 99.274143 | DX5: =100*(EM5/EM$20) -> 100.66341 | DY5: 100 | EA5: =100*(EO5/EO$20) -> 80.930504 | EB5: =100*(EP5/EP$20) -> 83.481145 | EC5: =100*(EQ5/EQ$20) -> 102.19731 | ED5: =100*(ER5/ER$20) -> 85.912375 | EE5: =100*(ES5/ES$20) -> 86.761543 | EF5: 100 | EH5: 2008-09 | EI5: 5470.9951 | EJ5: 5771.9121 | EK5: 5794.1376 | EL5: 5819.4318 | EM5: 6207.1735 | EO5: 1065.6702 | EP5: 1124.2844 | EQ5: 1128.6136 | ER5: 1133.5406 | ES5: 1209.067 | EU5: 2001 | EV5: =100*((EZ5-FA5)/Data!BX28*Data!BY28*0.01) -> 0.2768968 | EW5: =100*((FC5-FD5)/Data!CQ28*Data!CR28*0.01) -> 0.2768968 | EX5: 0 | EZ5: =Data!BU28*(Data!BX28*Data!BY28*0.01/Data!BW28)^1 -> 401136.14 | FA5: =(Data!BR28+Data!BT28)*(Data!BX28*Data!BY28*0.01/Data!BW28)^1 -> 394644.22 | FC5: =Data!CN28*(Data!CQ28*Data!CR28*0.01/Data!CP28)^1 -> 401136.14 | FD5: =(Data!CK28+Data!CM28)*(Data!CQ28*Data!CR28*0.01/Data!CP28)^1 -> 394644.22
A6: 2002 | B6: =100*(Data!BO29/Data!BO$46) -> 76.631299 | C6: =100*(Data!CH29/Data!CH$46) -> 76.631299 | D6: 100 | F6: =100*((C6/B6)-1) -> 0 | H6: 2002 | I6: =100*(O6/Data!$BW29) -> 30.651608 | J6: =100*(P6/Data!$CP29) -> 30.651608 | O6: =Data!BV29-$R6 -> 369800 | P6: =Data!CO29-$R6 -> 369800 | R6: ='GNDBTX ex BoE'!D122 -> -600 | U6: 2021-22 | V6: =100*(AJ6/AJ$9) -> 105.64515 | W6: =100*(AK6/AK$9) -> 108.48135 | X6: =100*(AL6/AL$9) -> 108.36459 | AA6: 100 | AC6: =100*(AP6/AP$9) -> 79.750604 | AD6: =100*(AQ6/AQ$9) -> 89.928544 | AE6: =100*(AR6/AR$9) -> 88.791675 | AH6: 100 | AJ6: =100*(AV6/BT6) -> 6.4309131 | AK6: =100*(AW6/BU6) -> 6.6285693 | AL6: =100*(AX6/BV6) -> 6.6412055 | AP6: =100*(BB6/BT6) -> 1.0988362 | AQ6: =100*(BC6/BU6) -> 1.2333911 | AR6: =100*(BD6/BV6) -> 1.2357423 | AV6: =BH6/(CF6/1000) -> 6.0354237 | AW6: =BI6/(CG6/1000) -> 6.1247712 | AX6: =BJ6/(CH6/1000) -> 6.1316693 | BB6: =BN6/(CF6/1000) -> 1.0312598 | BC6: =BO6/(CG6/1000) -> 1.1396483 | BD6: =BP6/(CH6/1000) -> 1.1409319 | BH6: 405.02778 | BI6: {=TRANSPOSE(OBR_NOV22_TA.8!C8:I8)} -> 413.76045 | BJ6: {=TRANSPOSE(OBR_MAR23_TA.7!D8:J8)} -> 413.76045 | BN6: 69.20622 | BO6: {=TRANSPOSE(OBR_NOV22_TA.8!C30:I30)} -> 76.989229 | BP6: {=TRANSPOSE(OBR_MAR23_TA.7!D32:J32)} -> 76.989229 | BT6: =100*(BZ6/BZ$8) -> 93.850184 | BU6: =100*(CA6/CA$8) -> 92.399594 | BV6: =100*(CB6/CB$8) -> 92.327656 | BW6: =100*(CC6/CC$8) -> 88.374124 | BX6: =100*(CD6/CD$8) -> 87.880815 | BZ6: =OBR_MAR22_1.2!X114 -> 105.54998 | CA6: =OBR_NOV22_1.2!X119 -> 106.87364 | CB6: =OBR_MAR23_1.2!X119 -> 106.4684 | CC6: =OBR_NOV23_1.2!X124 -> 105.39629 | CD6: =OBR_MAR24_1.2!X124 -> 105.37331 | CF6: 67108.425 | CG6: 67555.25 | CH6: 67479.25 | CI6: 67313.25 | CJ6: 67313.25 | CL6: 2002 | CM6: =100*(Data!BS29/Data!$BW29) -> 1.4477041 | CN6: =100*(Data!CL29/Data!$CP29) -> 1.4477041 | CO6: 3 | CQ6: 2002 | CR6: =100*(Data!BQ29/Data!$BW29) -> -1.5019122 | CS6: =100*(Data!CJ29/Data!$CP29) -> -1.5019122 | CT6: 0 | CV6: 2002 | CW6: =CR6-DA6 -> -4.1614242 | CX6: =CS6-DB6 -> -4.1614242 | CY6: 0 | DA6: =Data!CF29 -> 2.659512 | DB6: =Data!CY29 -> 2.659512 | DD6: 2002 | DE6: =100*(Data!BO29/Data!BO$46) -> 76.631299 | DF6: =100*(Data!CH29/Data!CH$46) -> 76.631299 | DG6: =100*(Data!DA29/Data!DA$46) -> 76.631299 | DI6: =I6 -> 30.651608 | DJ6: =J6 -> 30.651608 | DK6: =100*(Data!DH29-$R6)/Data!DI29 -> 30.651608 | DM6: =CW6 -> -4.1614242 | DN6: =CX6 -> -4.1614242 | DO6: =(100*(Data!DC29/Data!$DI29))-Data!$DR29 -> -4.1614242 | DS6: 2009-10 | DT6: =100*(EI6/EI$20) -> 100.24105 | DU6: =100*(EJ6/EJ$20) -> 100.55955 | DV6: =100*(EK6/EK$20) -> 100.22751 | DW6: =100*(EL6/EL$20) -> 103.50574 | DX6: =100*(EM6/EM$20) -> 104.95422 | DY6: 100 | EA6: =100*(EO6/EO$20) -> 90.013179 | EB6: =100*(EP6/EP$20) -> 93.077417 | EC6: =100*(EQ6/EQ$20) -> 113.94503 | ED6: =100*(ER6/ER$20) -> 95.78812 | EE6: =100*(ES6/ES$20) -> 96.7349 | EF6: 100 | EH6: 2009-10 | EI6: 5690.2657 | EJ6: 6017.9419 | EK6: 6041.1149 | EL6: 6067.4872 | EM6: 6471.7565 | EO6: 1185.2683 | EP6: 1253.5225 | EQ6: 1258.3493 | ER6: 1263.8426 | ES6: 1348.0509 | EU6: 2002 | EV6: =100*((EZ6-FA6)/Data!BX29*Data!BY29*0.01) -> -0.7523072 | EW6: =100*((FC6-FD6)/Data!CQ29*Data!CR29*0.01) -> -0.7523072 | EX6: 0 | EZ6: =Data!BU29*(Data!BX29*Data!BY29*0.01/Data!BW29)^1 -> 407851.25 | FA6: =(Data!BR29+Data!BT29)*(Data!BX29*Data!BY29*0.01/Data!BW29)^1 -> 425514.24 | FC6: =Data!CN29*(Data!CQ29*Data!CR29*0.01/Data!CP29)^1 -> 407851.25 | FD6: =(Data!CK29+Data!CM29)*(Data!CQ29*Data!CR29*0.01/Data!CP29)^1 -> 425514.24
A7: 2003 | B7: =100*(Data!BO30/Data!BO$46) -> 79.104037 | C7: =100*(Data!CH30/Data!CH$46) -> 79.104037 | D7: 100 | F7: =100*((C7/B7)-1) -> 0 | H7: 2003 | I7: =100*(O7/Data!$BW30) -> 31.868562 | J7: =100*(P7/Data!$CP30) -> 31.868562 | O7: =Data!BV30-$R7 -> 405900 | P7: =Data!CO30-$R7 -> 405900 | R7: ='GNDBTX ex BoE'!D123 -> -1400 | U7: 2022-23 | V7: =100*(AJ7/AJ$9) -> 101.74477 | W7: =100*(AK7/AK$9) -> 103.7007 | X7: =100*(AL7/AL$9) -> 102.44555 | Y7: =100*(AM7/AM$9) -> 103.34926 | Z7: =100*(AN7/AN$9) -> 103.4887 | AA7: 100 | AC7: =100*(AP7/AP$9) -> 94.978351 | AD7: =100*(AQ7/AQ$9) -> 98.759829 | AE7: =100*(AR7/AR$9) -> 93.720941 | AF7: =100*(AS7/AS$9) -> 98.987577 | AG7: =100*(AT7/AT$9) -> 98.901005 | AH7: 100 | AJ7: =100*(AV7/BT7) -> 6.1934863 | AK7: =100*(AW7/BU7) -> 6.3364562 | AL7: =100*(AX7/BV7) -> 6.2784528 | AM7: =100*(AY7/BW7) -> 6.4180282 | AN7: =100*(AZ7/BX7) -> 6.3887696 | AP7: =100*(BB7/BT7) -> 1.3086503 | AQ7: =100*(BC7/BU7) -> 1.3545142 | AR7: =100*(BD7/BV7) -> 1.3043445 | AS7: =100*(BE7/BW7) -> 1.4003288 | AT7: =100*(BF7/BX7) -> 1.4078975 | AV7: =BH7/(CF7/1000) -> 6.0477297 | AW7: =BI7/(CG7/1000) -> 6.1379817 | AX7: =BJ7/(CH7/1000) -> 6.1222512 | AY7: =BK7/(CI7/1000) -> 6.0496958 | AZ7: =BL7/(CJ7/1000) -> 5.9957062 | BB7: =BN7/(CF7/1000) -> 1.2778527 | BC7: =BO7/(CG7/1000) -> 1.3120873 | BD7: =BP7/(CH7/1000) -> 1.2718937 | BE7: =BQ7/(CI7/1000) -> 1.3199636 | BF7: =BR7/(CJ7/1000) -> 1.3212779 | BH7: 406.97511 | BI7: 415.47497 | BJ7: 415.47476 | BK7: {=TRANSPOSE(OBR_NOV23_TA.7!C8:I8)} -> 411.5361 | BL7: {=TRANSPOSE(OBR_MAR24_TA.7!C8:I8)} -> 407.4577 | BN7: 85.991647 | BO7: 88.814116 | BP7: 86.31461 | BQ7: {=TRANSPOSE(OBR_NOV23_TA.7!C32:I32)} -> 89.791733 | BR7: {=TRANSPOSE(OBR_MAR24_TA.7!C32:I32)} -> 89.791733 | BT7: =100*(BZ7/BZ$8) -> 97.646614 | BU7: =100*(CA7/CA$8) -> 96.867736 | BV7: =100*(CB7/CB$8) -> 97.5121 | BW7: =100*(CC7/CC$8) -> 94.260972 | BX7: =100*(CD7/CD$8) -> 93.847589 | BZ7: =OBR_MAR22_1.2!X115 -> 109.81969 | CA7: =OBR_NOV22_1.2!X120 -> 112.0417 | CB7: =OBR_MAR23_1.2!X120 -> 112.44689 | CC7: =OBR_NOV23_1.2!X125 -> 112.41703 | CD7: =OBR_MAR24_1.2!X125 -> 112.52776 | CF7: 67293.866 | CG7: 67689.184 | CH7: 67863.07 | CI7: 68025.917 | CJ7: 67958.25 | CL7: 2003 | CM7: =100*(Data!BS30/Data!$BW30) -> 1.6907847 | CN7: =100*(Data!CL30/Data!$CP30) -> 1.6907847 | CO7: 3 | CQ7: 2003 | CR7: =100*(Data!BQ30/Data!$BW30) -> -1.7829593 | CS7: =100*(Data!CJ30/Data!$CP30) -> -1.7829593 | CT7: 0 | CV7: 2003 | CW7: =CR7-DA7 -> -4.8384363 | CX7: =CS7-DB7 -> -4.8384363 | CY7: 0 | DA7: =Data!CF30 -> 3.055477 | DB7: =Data!CY30 -> 3.055477 | DD7: 2003 | DE7: =100*(Data!BO30/Data!BO$46) -> 79.104037 | DF7: =100*(Data!CH30/Data!CH$46) -> 79.104037 | DG7: =100*(Data!DA30/Data!DA$46) -> 79.104037 | DI7: =I7 -> 31.868562 | DJ7: =J7 -> 31.868562 | DK7: =100*(Data!DH30-$R7)/Data!DI30 -> 31.868562 | DM7: =CW7 -> -4.8384363 | DN7: =CX7 -> -4.8384363 | DO7: =(100*(Data!DC30/Data!$DI30))-Data!$DR30 -> -4.8384363 | DS7: 2010-11 | DT7: =100*(EI7/EI$20) -> 99.949353 | DU7: =100*(EJ7/EJ$20) -> 100.27327 | DV7: =100*(EK7/EK$20) -> 229.83438 | DW7: =100*(EL7/EL$20) -> 102.88886 | DX7: =100*(EM7/EM$20) -> 104.32871 | DY7: 100 | EA7: =100*(EO7/EO$20) -> 75.30368 | EB7: =100*(EP7/EP$20) -> 77.8721 | EC7: =100*(EQ7/EQ$20) -> 95.330733 | ED7: =100*(ER7/ER$20) -> 79.993858 | EE7: =100*(ES7/ES$20) -> 80.784526 | EF7: 100 | EH7: 2010-11 | EI7: 5673.7075 | EJ7: 6000.8097 | EK7: 13853.042 | EL7: 6031.3257 | EM7: 6433.1857 | EO7: 991.57774 | EP7: 1048.7445 | EQ7: 1052.7828 | ER7: 1055.4508 | ES7: 1125.7742 | EU7: 2003 | EV7: =100*((EZ7-FA7)/Data!BX30*Data!BY30*0.01) -> -0.93415157 | EW7: =100*((FC7-FD7)/Data!CQ30*Data!CR30*0.01) -> -0.93415157 | EX7: 0 | EZ7: =Data!BU30*(Data!BX30*Data!BY30*0.01/Data!BW30)^1 -> 437050.61 | FA7: =(Data!BR30+Data!BT30)*(Data!BX30*Data!BY30*0.01/Data!BW30)^1 -> 459047.22 | FC7: =Data!CN30*(Data!CQ30*Data!CR30*0.01/Data!CP30)^1 -> 437050.61 | FD7: =(Data!CK30+Data!CM30)*(Data!CQ30*Data!CR30*0.01/Data!CP30)^1 -> 459047.22
A8: 2004 | B8: =100*(Data!BO31/Data!BO$46) -> 80.870374 | C8: =100*(Data!CH31/Data!CH$46) -> 80.870374 | D8: 100 | F8: =100*((C8/B8)-1) -> 0 | H8: 2004 | I8: =100*(O8/Data!$BW31) -> 34.684374 | J8: =100*(P8/Data!$CP31) -> 34.684374 | O8: =Data!BV31-$R8 -> 465200 | P8: =Data!CO31-$R8 -> 465200 | R8: ='GNDBTX ex BoE'!D124 -> -4300 | U8: 2023-24 | V8: =100*(AJ8/AJ$9) -> 99.372895 | W8: =100*(AK8/AK$9) -> 101.1059 | X8: =100*(AL8/AL$9) -> 100.83213 | Y8: =100*(AM8/AM$9) -> 100.15211 | Z8: =100*(AN8/AN$9) -> 99.88447 | AA8: 100 | AC8: =100*(AP8/AP$9) -> 101.83936 | AD8: =100*(AQ8/AQ$9) -> 101.36806 | AE8: =100*(AR8/AR$9) -> 101.20179 | AF8: =100*(AS8/AS$9) -> 98.955955 | AG8: =100*(AT8/AT$9) -> 97.893255 | AH8: 100 | AJ8: =100*(AV8/BT8) -> 6.0491038 | AK8: =100*(AW8/BU8) -> 6.1779053 | AL8: =100*(AX8/BV8) -> 6.1795727 | AM8: =100*(AY8/BW8) -> 6.2194842 | AN8: =100*(AZ8/BX8) -> 6.1662659 | AP8: =100*(BB8/BT8) -> 1.4031841 | AQ8: =100*(BC8/BU8) -> 1.3902867 | AR8: =100*(BD8/BV8) -> 1.4084579 | AS8: =100*(BE8/BW8) -> 1.3998815 | AT8: =100*(BF8/BX8) -> 1.3935518 | AV8: =BH8/(CF8/1000) -> 6.0491038 | AW8: =BI8/(CG8/1000) -> 6.1779053 | AX8: =BJ8/(CH8/1000) -> 6.1795727 | AY8: =BK8/(CI8/1000) -> 6.2194842 | AZ8: =BL8/(CJ8/1000) -> 6.1662659 | BB8: =BN8/(CF8/1000) -> 1.4031841 | BC8: =BO8/(CG8/1000) -> 1.3902867 | BD8: =BP8/(CH8/1000) -> 1.4084579 | BE8: =BQ8/(CI8/1000) -> 1.3998815 | BF8: =BR8/(CJ8/1000) -> 1.3935518 | BH8: 408.019 | BI8: 419.68701 | BJ8: 421.6874 | BK8: 426.51629 | BL8: 422.94449 | BN8: 94.646379 | BO8: 94.447103 | BP8: 96.111651 | BQ8: 96.000288 | BR8: 95.583786 | BT8: =100*(BZ8/BZ$8) -> 100 | BU8: =100*(CA8/CA$8) -> 100 | BV8: =100*(CB8/CB$8) -> 100 | BW8: =100*(CC8/CC$8) -> 100 | BX8: =100*(CD8/CD$8) -> 100 | BZ8: =OBR_MAR22_1.2!X116 -> 112.46646 | CA8: =OBR_NOV22_1.2!X121 -> 115.66462 | CB8: =OBR_MAR23_1.2!X121 -> 115.31583 | CC8: =OBR_NOV23_1.2!X126 -> 119.26148 | CD8: =OBR_MAR24_1.2!X126 -> 119.9048 | CF8: 67451.149 | CG8: 67933.545 | CH8: 68238.924 | CI8: 68577.439 | CJ8: 68590.05 | CL8: 2004 | CM8: =100*(Data!BS31/Data!$BW31) -> 2.0473622 | CN8: =100*(Data!CL31/Data!$CP31) -> 2.0473622 | CO8: 3 | CQ8: 2004 | CR8: =100*(Data!BQ31/Data!$BW31) -> -1.8647697 | CS8: =100*(Data!CJ31/Data!$CP31) -> -1.8647697 | CT8: 0 | CV8: 2004 | CW8: =CR8-DA8 -> -4.1531117 | CX8: =CS8-DB8 -> -4.1531117 | CY8: 0 | DA8: =Data!CF31 -> 2.288342 | DB8: =Data!CY31 -> 2.288342 | DD8: 2004 | DE8: =100*(Data!BO31/Data!BO$46) -> 80.870374 | DF8: =100*(Data!CH31/Data!CH$46) -> 80.870374 | DG8: =100*(Data!DA31/Data!DA$46) -> 80.870374 | DI8: =I8 -> 34.684374 | DJ8: =J8 -> 34.684374 | DK8: =100*(Data!DH31-$R8)/Data!DI31 -> 34.684374 | DM8: =CW8 -> -4.1531117 | DN8: =CX8 -> -4.1531117 | DO8: =(100*(Data!DC31/Data!$DI31))-Data!$DR31 -> -4.1531117 | DS8: 2011-12 | DT8: =100*(EI8/EI$20) -> 96.213761 | DU8: =100*(EJ8/EJ$20) -> 96.256732 | DV8: =100*(EK8/EK$20) -> 95.938897 | DW8: =100*(EL8/EL$20) -> 98.94705 | DX8: =100*(EM8/EM$20) -> 100.33174 | DY8: 100 | EA8: =100*(EO8/EO$20) -> 63.587319 | EB8: =100*(EP8/EP$20) -> 65.572983 | EC8: =100*(EQ8/EQ$20) -> 80.2742 | ED8: =100*(ER8/ER$20) -> 67.394256 | EE8: =100*(ES8/ES$20) -> 68.060388 | EF8: 100 | EH8: 2011-12 | EI8: 5461.6535 | EJ8: 5760.4418 | EK8: 5782.6232 | EL8: 5800.2577 | EM8: 6186.7218 | EO8: 837.29999 | EP8: 883.10579 | EQ8: 886.50632 | ER8: 889.20978 | ES8: 948.45675 | EU8: 2004 | EV8: =100*((EZ8-FA8)/Data!BX31*Data!BY31*0.01) -> -1.0365719 | EW8: =100*((FC8-FD8)/Data!CQ31*Data!CR31*0.01) -> -1.0365719 | EX8: 0 | EZ8: =Data!BU31*(Data!BX31*Data!BY31*0.01/Data!BW31)^1 -> 470566.16 | FA8: =(Data!BR31+Data!BT31)*(Data!BX31*Data!BY31*0.01/Data!BW31)^1 -> 494904.83 | FC8: =Data!CN31*(Data!CQ31*Data!CR31*0.01/Data!CP31)^1 -> 470566.16 | FD8: =(Data!CK31+Data!CM31)*(Data!CQ31*Data!CR31*0.01/Data!CP31)^1 -> 494904.83
A9: 2005 | B9: =100*(Data!BO32/Data!BO$46) -> 83.258503 | C9: =100*(Data!CH32/Data!CH$46) -> 83.258503 | D9: 100 | F9: =100*((C9/B9)-1) -> 0 | H9: 2005 | I9: =100*(O9/Data!$BW32) -> 35.640119 | J9: =100*(P9/Data!$CP32) -> 35.640119 | O9: =Data!BV32-$R9 -> 505600 | P9: =Data!CO32-$R9 -> 505600 | R9: ='GNDBTX ex BoE'!D125 -> -6200 | U9: 2024-25 | V9: =100*(AJ9/AJ$9) -> 100 | W9: =100*(AK9/AK$9) -> 100 | X9: =100*(AL9/AL$9) -> 100 | Y9: =100*(AM9/AM$9) -> 100 | Z9: =100*(AN9/AN$9) -> 100 | AA9: 100 | AC9: =100*(AP9/AP$9) -> 100 | AD9: =100*(AQ9/AQ$9) -> 100 | AE9: =100*(AR9/AR$9) -> 100 | AF9: =100*(AS9/AS$9) -> 100 | AG9: =100*(AT9/AT$9) -> 100 | AH9: 100 | AJ9: =100*(AV9/BT9) -> 6.0872774 | AK9: =100*(AW9/BU9) -> 6.110331 | AL9: =100*(AX9/BV9) -> 6.1285753 | AM9: =100*(AY9/BW9) -> 6.210038 | AN9: =100*(AZ9/BX9) -> 6.173398 | AP9: =100*(BB9/BT9) -> 1.3778406 | AQ9: =100*(BC9/BU9) -> 1.3715235 | AR9: =100*(BD9/BV9) -> 1.3917322 | AS9: =100*(BE9/BW9) -> 1.4146511 | AT9: =100*(BF9/BX9) -> 1.4235422 | AV9: =BH9/(CF9/1000) -> 6.2000928 | AW9: =BI9/(CG9/1000) -> 6.1908219 | AX9: =BJ9/(CH9/1000) -> 6.2247511 | AY9: =BK9/(CI9/1000) -> 6.3139475 | AZ9: =BL9/(CJ9/1000) -> 6.2223006 | BB9: =BN9/(CF9/1000) -> 1.4033761 | BC9: =BO9/(CG9/1000) -> 1.3895904 | BD9: =BP9/(CH9/1000) -> 1.4135726 | BE9: =BQ9/(CI9/1000) -> 1.4383218 | BF9: =BR9/(CJ9/1000) -> 1.4348188 | BH9: 419.09821 | BI9: 422.00137 | BJ9: 426.65635 | BK9: 435.45198 | BL9: 430.19538 | BN9: 94.861872 | BO9: 94.722329 | BP9: 96.888973 | BQ9: 99.196273 | BR9: 99.20003 | BT9: =100*(BZ9/BZ$8) -> 101.8533 | BU9: =100*(CA9/CA$8) -> 101.31729 | BV9: =100*(CB9/CB$8) -> 101.5693 | BW9: =100*(CC9/CC$8) -> 101.67325 | BX9: =100*(CD9/CD$8) -> 100.79215 | BZ9: =OBR_MAR22_1.2!X117 -> 114.5508 | CA9: =OBR_NOV22_1.2!X122 -> 117.18826 | CB9: =OBR_MAR23_1.2!X122 -> 117.12548 | CC9: =OBR_NOV23_1.2!X127 -> 121.25702 | CD9: =OBR_MAR24_1.2!X127 -> 120.85462 | CF9: 67595.474 | CG9: 68165.646 | CH9: 68541.913 | CI9: 68966.677 | CJ9: 69137.672 | CL9: 2005 | CM9: =100*(Data!BS32/Data!$BW32) -> 1.8518623 | CN9: =100*(Data!CL32/Data!$CP32) -> 1.8518623 | CO9: 3 | CQ9: 2005 | CR9: =100*(Data!BQ32/Data!$BW32) -> -1.4213753 | CS9: =100*(Data!CJ32/Data!$CP32) -> -1.4213753 | CT9: 0 | CV9: 2005 | CW9: =CR9-DA9 -> -4.0404513 | CX9: =CS9-DB9 -> -4.0404513 | CY9: 0 | DA9: =Data!CF32 -> 2.619076 | DB9: =Data!CY32 -> 2.619076 | DD9: 2005 | DE9: =100*(Data!BO32/Data!BO$46) -> 83.258503 | DF9: =100*(Data!CH32/Data!CH$46) -> 83.258503 | DG9: =100*(Data!DA32/Data!DA$46) -> 83.258503 | DI9: =I9 -> 35.640119 | DJ9: =J9 -> 35.640119 | DK9: =100*(Data!DH32-$R9)/Data!DI32 -> 35.640119 | DM9: =CW9 -> -4.0404513 | DN9: =CX9 -> -4.0404513 | DO9: =(100*(Data!DC32/Data!$DI32))-Data!$DR32 -> -4.0404513 | DS9: 2012-13 | DT9: =100*(EI9/EI$20) -> 92.421101 | DU9: =100*(EJ9/EJ$20) -> 92.75854 | DV9: =100*(EK9/EK$20) -> 92.452256 | DW9: =100*(EL9/EL$20) -> 95.211701 | DX9: =100*(EM9/EM$20) -> 96.544117 | DY9: 100 | EA9: =100*(EO9/EO$20) -> 59.985971 | EB9: =100*(EP9/EP$20) -> 62.057312 | EC9: =100*(EQ9/EQ$20) -> 75.970329 | ED9: =100*(ER9/ER$20) -> 63.687703 | EE9: =100*(ES9/ES$20) -> 64.3172 | EF9: 100 | EH9: 2012-13 | EI9: 5246.36 | EJ9: 5551.094 | EK9: 5572.4693 | EL9: 5581.2922 | EM9: 5953.1669 | EO9: 789.87844 | EP9: 835.75841 | EQ9: 838.97662 | ER9: 840.30497 | ES9: 896.29347 | EU9: 2005 | EV9: =100*((EZ9-FA9)/Data!BX32*Data!BY32*0.01) -> -0.83393975 | EW9: =100*((FC9-FD9)/Data!CQ32*Data!CR32*0.01) -> -0.83393975 | EX9: 0 | EZ9: =Data!BU32*(Data!BX32*Data!BY32*0.01/Data!BW32)^1 -> 506398.14 | FA9: =(Data!BR32+Data!BT32)*(Data!BX32*Data!BY32*0.01/Data!BW32)^1 -> 526030.96 | FC9: =Data!CN32*(Data!CQ32*Data!CR32*0.01/Data!CP32)^1 -> 506398.14 | FD9: =(Data!CK32+Data!CM32)*(Data!CQ32*Data!CR32*0.01/Data!CP32)^1 -> 526030.96
A10: 2006 | B10: =100*(Data!BO33/Data!BO$46) -> 85.047094 | C10: =100*(Data!CH33/Data!CH$46) -> 85.047094 | D10: 100 | F10: =100*((C10/B10)-1) -> 0 | H10: 2006 | I10: =100*(O10/Data!$BW33) -> 36.36195 | J10: =100*(P10/Data!$CP33) -> 36.36195 | O10: =Data!BV33-$R10 -> 541000 | P10: =Data!CO33-$R10 -> 541000 | R10: ='GNDBTX ex BoE'!D126 -> -5800 | U10: 2025-26 | V10: =100*(AJ10/AJ$9) -> 101.70071 | W10: =100*(AK10/AK$9) -> 101.11258 | X10: =100*(AL10/AL$9) -> 100.76934 | Y10: =100*(AM10/AM$9) -> 100.0921 | Z10: =100*(AN10/AN$9) -> 100.36343 | AA10: 100 | AC10: =100*(AP10/AP$9) -> 102.43388 | AD10: =100*(AQ10/AQ$9) -> 100.08052 | AE10: =100*(AR10/AR$9) -> 98.837947 | AF10: =100*(AS10/AS$9) -> 95.93841 | AG10: =100*(AT10/AT$9) -> 96.994319 | AH10: 100 | AJ10: =100*(AV10/BT10) -> 6.1908042 | AK10: =100*(AW10/BU10) -> 6.1783131 | AL10: =100*(AX10/BV10) -> 6.1757246 | AM10: =100*(AY10/BW10) -> 6.2157576 | AN10: =100*(AZ10/BX10) -> 6.1958343 | AP10: =100*(BB10/BT10) -> 1.4113756 | AQ10: =100*(BC10/BU10) -> 1.3726278 | AR10: =100*(BD10/BV10) -> 1.3755595 | AS10: =100*(BE10/BW10) -> 1.3571938 | AT10: =100*(BF10/BX10) -> 1.380755 | AV10: =BH10/(CF10/1000) -> 6.4286771 | AW10: =BI10/(CG10/1000) -> 6.2928926 | AX10: =BJ10/(CH10/1000) -> 6.3330478 | AY10: =BK10/(CI10/1000) -> 6.4280068 | AZ10: =BL10/(CJ10/1000) -> 6.3291723 | BB10: =BN10/(CF10/1000) -> 1.4656057 | BC10: =BO10/(CG10/1000) -> 1.3980838 | BD10: =BP10/(CH10/1000) -> 1.4106011 | BE10: =BQ10/(CI10/1000) -> 1.4035378 | BF10: =BR10/(CJ10/1000) -> 1.4104697 | BH10: 435.39391 | BI10: 430.32556 | BJ10: 435.84566 | BK10: 445.2619 | BL10: 440.03535 | BN10: 99.260827 | BO10: 95.604873 | BP10: 97.078752 | BQ10: 97.221725 | BR10: 98.062828 | BT10: =100*(BZ10/BZ$8) -> 103.84236 | BU10: =100*(CA10/CA$8) -> 101.85454 | BV10: =100*(CB10/CB$8) -> 102.54745 | BW10: =100*(CC10/CC$8) -> 103.4147 | BX10: =100*(CD10/CD$8) -> 102.15206 | BZ10: =OBR_MAR22_1.2!X118 -> 116.78782 | CA10: =OBR_NOV22_1.2!X123 -> 117.80967 | CB10: =OBR_MAR23_1.2!X123 -> 118.25344 | CC10: =OBR_NOV23_1.2!X128 -> 123.33389 | CD10: =OBR_MAR24_1.2!X128 -> 122.48522 | CF10: 67726.828 | CG10: 68382.791 | CH10: 68820.839 | CI10: 69269.047 | CJ10: 69524.944 | CL10: 2006 | CM10: =100*(Data!BS33/Data!$BW33) -> 1.814468 | CN10: =100*(Data!CL33/Data!$CP33) -> 1.814468 | CO10: 3 | CQ10: 2006 | CR10: =100*(Data!BQ33/Data!$BW33) -> -1.0067085 | CS10: =100*(Data!CJ33/Data!$CP33) -> -1.0067085 | CT10: 0 | CV10: 2006 | CW10: =CR10-DA10 -> -3.3480745 | CX10: =CS10-DB10 -> -3.3480745 | CY10: 0 | DA10: =Data!CF33 -> 2.341366 | DB10: =Data!CY33 -> 2.341366 | DD10: 2006 | DE10: =100*(Data!BO33/Data!BO$46) -> 85.047094 | DF10: =100*(Data!CH33/Data!CH$46) -> 85.047094 | DG10: =100*(Data!DA33/Data!DA$46) -> 85.047094 | DI10: =I10 -> 36.36195 | DJ10: =J10 -> 36.36195 | DK10: =100*(Data!DH33-$R10)/Data!DI33 -> 36.36195 | DM10: =CW10 -> -3.3480745 | DN10: =CX10 -> -3.3480745 | DO10: =(100*(Data!DC33/Data!$DI33))-Data!$DR33 -> -3.3480745 | DS10: 2013-14 | DT10: =100*(EI10/EI$20) -> 91.214232 | DU10: =100*(EJ10/EJ$20) -> 91.729503 | DV10: =100*(EK10/EK$20) -> 91.426616 | DW10: =100*(EL10/EL$20) -> 94.306273 | DX10: =100*(EM10/EM$20) -> 95.557909 | DY10: 100 | EA10: =100*(EO10/EO$20) -> 62.953306 | EB10: =100*(EP10/EP$20) -> 65.256755 | EC10: =100*(EQ10/EQ$20) -> 79.887075 | ED10: =100*(ER10/ER$20) -> 67.078482 | EE10: =100*(ES10/ES$20) -> 67.741493 | EF10: 100 | EH10: 2013-14 | EI10: 5177.8511 | EJ10: 5489.5117 | EK10: 5510.6499 | EL10: 5528.2162 | EM10: 5892.3547 | EO10: 828.95148 | EP10: 878.84699 | EQ10: 882.23112 | ER10: 885.04341 | ES10: 944.01278 | EU10: 2006 | EV10: =100*((EZ10-FA10)/Data!BX33*Data!BY33*0.01) -> -0.62266181 | EW10: =100*((FC10-FD10)/Data!CQ33*Data!CR33*0.01) -> -0.62266181 | EX10: 0 | EZ10: =Data!BU33*(Data!BX33*Data!BY33*0.01/Data!BW33)^1 -> 539810.92 | FA10: =(Data!BR33+Data!BT33)*(Data!BX33*Data!BY33*0.01/Data!BW33)^1 -> 554473 | FC10: =Data!CN33*(Data!CQ33*Data!CR33*0.01/Data!CP33)^1 -> 539810.92 | FD10: =(Data!CK33+Data!CM33)*(Data!CQ33*Data!CR33*0.01/Data!CP33)^1 -> 554473
A11: 2007 | B11: =100*(Data!BO34/Data!BO$46) -> 87.352728 | C11: =100*(Data!CH34/Data!CH$46) -> 87.352728 | D11: 100 | F11: =100*((C11/B11)-1) -> 0 | H11: 2007 | I11: =100*(O11/Data!$BW34) -> 36.846638 | J11: =100*(P11/Data!$CP34) -> 36.846638 | O11: =Data!BV34-$R11 -> 576700 | P11: =Data!CO34-$R11 -> 576700 | R11: ='GNDBTX ex BoE'!D127 -> -9500 | U11: 2026-27 | V11: =100*(AJ11/AJ$9) -> 103.22797 | W11: =100*(AK11/AK$9) -> 101.83027 | X11: =100*(AL11/AL$9) -> 101.55697 | Y11: =100*(AM11/AM$9) -> 100.70195 | Z11: =100*(AN11/AN$9) -> 100.87705 | AA11: 100 | AC11: =100*(AP11/AP$9) -> 103.96473 | AD11: =100*(AQ11/AQ$9) -> 99.012347 | AE11: =100*(AR11/AR$9) -> 97.711402 | AF11: =100*(AS11/AS$9) -> 94.338659 | AG11: =100*(AT11/AT$9) -> 95.127077 | AH11: 100 | AJ11: =100*(AV11/BT11) -> 6.2837726 | AK11: =100*(AW11/BU11) -> 6.2221663 | AL11: =100*(AX11/BV11) -> 6.2239951 | AM11: =100*(AY11/BW11) -> 6.2536295 | AN11: =100*(AZ11/BX11) -> 6.2275418 | AP11: =100*(BB11/BT11) -> 1.4324682 | AQ11: =100*(BC11/BU11) -> 1.3579776 | AR11: =100*(BD11/BV11) -> 1.359881 | AS11: =100*(BE11/BW11) -> 1.3345629 | AT11: =100*(BF11/BX11) -> 1.3541741 | AV11: =BH11/(CF11/1000) -> 6.6557745 | AW11: =BI11/(CG11/1000) -> 6.4147626 | AX11: =BJ11/(CH11/1000) -> 6.4590222 | AY11: =BK11/(CI11/1000) -> 6.5722539 | AZ11: =BL11/(CJ11/1000) -> 6.472483 | BB11: =BN11/(CF11/1000) -> 1.5172709 | BC11: =BO11/(CG11/1000) -> 1.4000114 | BD11: =BP11/(CH11/1000) -> 1.4112321 | BE11: =BQ11/(CI11/1000) -> 1.4025593 | BF11: =BR11/(CJ11/1000) -> 1.4074363 | BH11: 451.57825 | BI11: 439.94671 | BJ11: 446.15051 | BK11: 456.91761 | BL11: 452.28089 | BN11: 102.94317 | BO11: 96.017646 | BP11: 97.479447 | BQ11: 97.50902 | BR11: 98.348124 | BT11: =100*(BZ11/BZ$8) -> 105.92004 | BU11: =100*(CA11/CA$8) -> 103.09533 | BV11: =100*(CB11/CB$8) -> 103.77614 | BW11: =100*(CC11/CC$8) -> 105.09503 | BX11: =100*(CD11/CD$8) -> 103.93319 | BZ11: =OBR_MAR22_1.2!X119 -> 119.12452 | CA11: =OBR_NOV22_1.2!X124 -> 119.24482 | CB11: =OBR_MAR23_1.2!X124 -> 119.67032 | CC11: =OBR_NOV23_1.2!X129 -> 125.33789 | CD11: =OBR_MAR24_1.2!X129 -> 124.62088 | CF11: 67847.589 | CG11: 68583.475 | CH11: 69074.002 | CI11: 69522.21 | CJ11: 69877.494 | CL11: 2007 | CM11: =100*(Data!BS34/Data!$BW34) -> 1.7932627 | CN11: =100*(Data!CL34/Data!$CP34) -> 1.7932627 | CO11: 3 | CQ11: 2007 | CR11: =100*(Data!BQ34/Data!$BW34) -> -1.1465457 | CS11: =100*(Data!CJ34/Data!$CP34) -> -1.1465457 | CT11: 0 | CV11: 2007 | CW11: =CR11-DA11 -> -3.2130627 | CX11: =CS11-DB11 -> -3.2130627 | CY11: 0 | DA11: =Data!CF34 -> 2.066517 | DB11: =Data!CY34 -> 2.066517 | DD11: 2007 | DE11: =100*(Data!BO34/Data!BO$46) -> 87.352728 | DF11: =100*(Data!CH34/Data!CH$46) -> 87.352728 | DG11: =100*(Data!DA34/Data!DA$46) -> 87.352728 | DI11: =I11 -> 36.846638 | DJ11: =J11 -> 36.846638 | DK11: =100*(Data!DH34-$R11)/Data!DI34 -> 36.846638 | DM11: =CW11 -> -3.2130627 | DN11: =CX11 -> -3.2130627 | DO11: =(100*(Data!DC34/Data!$DI34))-Data!$DR34 -> -3.2130627 | DS11: 2014-15 | DT11: =100*(EI11/EI$20) -> 90.185995 | DU11: =100*(EJ11/EJ$20) -> 90.696836 | DV11: =100*(EK11/EK$20) -> 90.397359 | DW11: =100*(EL11/EL$20) -> 93.164712 | DX11: =100*(EM11/EM$20) -> 94.289963 | DY11: 100 | EA11: =100*(EO11/EO$20) -> 66.999319 | EB11: =100*(EP11/EP$20) -> 69.451866 | EC11: =100*(EQ11/EQ$20) -> 85.022714 | ED11: =100*(ER11/ER$20) -> 71.329543 | EE11: =100*(ES11/ES$20) -> 72.034572 | EF11: 100 | EH11: 2014-15 | EI11: 5119.4824 | EJ11: 5427.7122 | EK11: 5448.6124 | EL11: 5461.2981 | EM11: 5814.1698 | EO11: 882.22824 | EP11: 935.34475 | EQ11: 938.94643 | ER11: 941.13253 | ES11: 1003.839 | EU11: 2007 | EV11: =100*((EZ11-FA11)/Data!BX34*Data!BY34*0.01) -> -0.74388266 | EW11: =100*((FC11-FD11)/Data!CQ34*Data!CR34*0.01) -> -0.74388266 | EX11: 0 | EZ11: =Data!BU34*(Data!BX34*Data!BY34*0.01/Data!BW34)^1 -> 570389.09 | FA11: =(Data!BR34+Data!BT34)*(Data!BX34*Data!BY34*0.01/Data!BW34)^1 -> 587905.9 | FC11: =Data!CN34*(Data!CQ34*Data!CR34*0.01/Data!CP34)^1 -> 570389.09 | FD11: =(Data!CK34+Data!CM34)*(Data!CQ34*Data!CR34*0.01/Data!CP34)^1 -> 587905.9
A12: 2008 | B12: =100*(Data!BO35/Data!BO$46) -> 85.284869 | C12: =100*(Data!CH35/Data!CH$46) -> 85.284869 | D12: 100 | F12: =100*((C12/B12)-1) -> 0 | H12: 2008 | I12: =100*(O12/Data!$BW35) -> 47.561554 | J12: =100*(P12/Data!$CP35) -> 47.561554 | O12: =Data!BV35-$R12 -> 752800 | P12: =Data!CO35-$R12 -> 752800 | R12: ='GNDBTX ex BoE'!D128 -> 34400 | U12: 2027-28 | W12: =100*(AK12/AK$9) -> 102.64759 | X12: =100*(AL12/AL$9) -> 102.41965 | Y12: =100*(AM12/AM$9) -> 101.42685 | Z12: =100*(AN12/AN$9) -> 101.39982 | AA12: 100 | AD12: =100*(AQ12/AQ$9) -> 97.184404 | AE12: =100*(AR12/AR$9) -> 95.945409 | AF12: =100*(AS12/AS$9) -> 92.467929 | AG12: =100*(AT12/AT$9) -> 92.88519 | AH12: 100 | AK12: =100*(AW12/BU12) -> 6.2721077 | AL12: =100*(AX12/BV12) -> 6.2768653 | AM12: =100*(AY12/BW12) -> 6.2986462 | AN12: =100*(AZ12/BX12) -> 6.2598142 | AQ12: =100*(BC12/BU12) -> 1.3329069 | AR12: =100*(BD12/BV12) -> 1.3353031 | AS12: =100*(BE12/BW12) -> 1.3080986 | AT12: =100*(BF12/BX12) -> 1.3222599 | AW12: =BI12/(CG12/1000) -> 6.5824047 | AX12: =BJ12/(CH12/1000) -> 6.6215131 | AY12: =BK12/(CI12/1000) -> 6.7370087 | AZ12: =BL12/(CJ12/1000) -> 6.6278684 | BC12: =BO12/(CG12/1000) -> 1.3988492 | BD12: =BP12/(CH12/1000) -> 1.4086214 | BE12: =BQ12/(CI12/1000) -> 1.3991374 | BF12: =BR12/(CJ12/1000) -> 1.4000039 | BI12: 452.66747 | BJ12: 458.91766 | BK12: 469.9419 | BL12: 465.55777 | BO12: 96.197899 | BP12: 97.627423 | BQ12: 97.597216 | BR12: 98.339717 | BU12: =100*(CA12/CA$8) -> 104.94725 | BV12: =100*(CB12/CB$8) -> 105.49076 | BW12: =100*(CC12/CC$8) -> 106.95963 | BX12: =100*(CD12/CD$8) -> 105.87963 | CA12: =OBR_NOV22_1.2!X125 -> 121.38684 | CB12: =OBR_MAR23_1.2!X125 -> 121.64755 | CC12: =OBR_NOV23_1.2!X130 -> 127.56164 | CD12: =OBR_MAR24_1.2!X130 -> 126.95476 | CG12: 68769.315 | CH12: 69307.068 | CI12: 69755.276 | CJ12: 70242.459 | CL12: 2008 | CM12: =100*(Data!BS35/Data!$BW35) -> 3.0057032 | CN12: =100*(Data!CL35/Data!$CP35) -> 3.0057032 | CO12: 3 | CQ12: 2008 | CR12: =100*(Data!BQ35/Data!$BW35) -> -4.4357088 | CS12: =100*(Data!CJ35/Data!$CP35) -> -4.4357088 | CT12: 0 | CV12: 2008 | CW12: =CR12-DA12 -> 0.11064718 | CX12: =CS12-DB12 -> 0.11064718 | CY12: 0 | DA12: =Data!CF35 -> -4.546356 | DB12: =Data!CY35 -> -4.546356 | DD12: 2008 | DE12: =100*(Data!BO35/Data!BO$46) -> 85.284869 | DF12: =100*(Data!CH35/Data!CH$46) -> 85.284869 | DG12: =100*(Data!DA35/Data!DA$46) -> 85.284869 | DI12: =I12 -> 47.561554 | DJ12: =J12 -> 47.561554 | DK12: =100*(Data!DH35-$R12)/Data!DI35 -> 47.561554 | DM12: =CW12 -> 0.11064718 | DN12: =CX12 -> 0.11064718 | DO12: =(100*(Data!DC35/Data!$DI35))-Data!$DR35 -> 0.11064718 | DS12: 2015-16 | DT12: =100*(EI12/EI$20) -> 88.493824 | DU12: =100*(EJ12/EJ$20) -> 88.876336 | DV12: =100*(EK12/EK$20) -> 88.58287 | DW12: =100*(EL12/EL$20) -> 91.317221 | DX12: =100*(EM12/EM$20) -> 92.40396 | DY12: 100 | EA12: =100*(EO12/EO$20) -> 63.589313 | EB12: =100*(EP12/EP$20) -> 65.829084 | EC12: =100*(EQ12/EQ$20) -> 80.587718 | ED12: =100*(ER12/ER$20) -> 67.625512 | EE12: =100*(ES12/ES$20) -> 68.29393 | EF12: 100 | EH12: 2015-16 | EI12: 5023.4249 | EJ12: 5318.7652 | EK12: 5339.2459 | EL12: 5352.9985 | EM12: 5697.8739 | EO12: 837.32625 | EP12: 886.55485 | EQ12: 889.96866 | ER12: 892.261 | ES12: 951.71127 | EU12: 2008 | EV12: =100*((EZ12-FA12)/Data!BX35*Data!BY35*0.01) -> -3.0888948 | EW12: =100*((FC12-FD12)/Data!CQ35*Data!CR35*0.01) -> -3.0888948 | EX12: 0 | EZ12: =Data!BU35*(Data!BX35*Data!BY35*0.01/Data!BW35)^1 -> 578702.88 | FA12: =(Data!BR35+Data!BT35)*(Data!BX35*Data!BY35*0.01/Data!BW35)^1 -> 649965.95 | FC12: =Data!CN35*(Data!CQ35*Data!CR35*0.01/Data!CP35)^1 -> 578702.88 | FD12: =(Data!CK35+Data!CM35)*(Data!CQ35*Data!CR35*0.01/Data!CP35)^1 -> 649965.95
A13: 2009 | B13: =100*(Data!BO36/Data!BO$46) -> 82.821167 | C13: =100*(Data!CH36/Data!CH$46) -> 82.821167 | D13: 100 | F13: =100*((C13/B13)-1) -> 0 | H13: 2009 | I13: =100*(O13/Data!$BW36) -> 60.590075 | J13: =100*(P13/Data!$CP36) -> 60.590075 | O13: =Data!BV36-$R13 -> 944100 | P13: =Data!CO36-$R13 -> 944100 | R13: ='GNDBTX ex BoE'!D129 -> 83800 | U13: 2028-29 | Y13: =100*(AM13/AM$9) -> 102.13089 | Z13: =100*(AN13/AN$9) -> 101.85455 | AA13: 100 | AF13: =100*(AS13/AS$9) -> 90.249216 | AG13: =100*(AT13/AT$9) -> 89.74839 | AH13: 100 | AM13: =100*(AY13/BW13) -> 6.3423672 | AN13: =100*(AZ13/BX13) -> 6.2878867 | AS13: =100*(BE13/BW13) -> 1.2767115 | AT13: =100*(BF13/BX13) -> 1.2776062 | AY13: =BK13/(CI13/1000) -> 6.9113577 | AZ13: =BL13/(CJ13/1000) -> 6.7862634 | BE13: =BQ13/(CI13/1000) -> 1.3912487 | BF13: =BR13/(CJ13/1000) -> 1.378869 | BK13: 483.64675 | BL13: 479.15889 | BQ13: 97.357557 | BR13: 97.358047 | BW13: =100*(CC13/CC$8) -> 108.97126 | BX13: =100*(CD13/CD$8) -> 107.92598 | CC13: =OBR_NOV23_1.2!X131 -> 129.96074 | CD13: =OBR_MAR24_1.2!X131 -> 129.40843 | CI13: 69978.545 | CJ13: 70607.176 | CL13: 2009 | CM13: =100*(Data!BS36/Data!$BW36) -> 3.000688 | CN13: =100*(Data!CL36/Data!$CP36) -> 3.000688 | CO13: 3 | CQ13: 2009 | CR13: =100*(Data!BQ36/Data!$BW36) -> -7.3260017 | CS13: =100*(Data!CJ36/Data!$CP36) -> -7.3260017 | CT13: 0 | CV13: 2009 | CW13: =CR13-DA13 -> -3.1070417 | CX13: =CS13-DB13 -> -3.1070417 | CY13: 0 | DA13: =Data!CF36 -> -4.21896 | DB13: =Data!CY36 -> -4.21896 | DD13: 2009 | DE13: =100*(Data!BO36/Data!BO$46) -> 82.821167 | DF13: =100*(Data!CH36/Data!CH$46) -> 82.821167 | DG13: =100*(Data!DA36/Data!DA$46) -> 82.821167 | DI13: =I13 -> 60.590075 | DJ13: =J13 -> 60.590075 | DK13: =100*(Data!DH36-$R13)/Data!DI36 -> 60.590075 | DM13: =CW13 -> -3.1070417 | DN13: =CX13 -> -3.1070417 | DO13: =(100*(Data!DC36/Data!$DI36))-Data!$DR36 -> -3.1070417 | DS13: 2016-17 | DT13: =100*(EI13/EI$20) -> 86.896166 | DU13: =100*(EJ13/EJ$20) -> 87.437668 | DV13: =100*(EK13/EK$20) -> 87.148953 | DW13: =100*(EL13/EL$20) -> 89.643912 | DX13: =100*(EM13/EM$20) -> 90.751464 | DY13: 100 | EA13: =100*(EO13/EO$20) -> 63.052092 | EB13: =100*(EP13/EP$20) -> 65.397019 | EC13: =100*(EQ13/EQ$20) -> 80.058785 | ED13: =100*(ER13/ER$20) -> 67.035737 | EE13: =100*(ES13/ES$20) -> 67.698326 | EF13: 100 | EH13: 2016-17 | EI13: 4932.7325 | EJ13: 5232.6688 | EK13: 5252.8179 | EL13: 5254.9094 | EM13: 5595.9765 | EO13: 830.25226 | EP13: 880.73599 | EQ13: 884.12739 | ER13: 884.47943 | ES13: 943.41122 | EU13: 2009 | EV13: =100*((EZ13-FA13)/Data!BX36*Data!BY36*0.01) -> -5.2406143 | EW13: =100*((FC13-FD13)/Data!CQ36*Data!CR36*0.01) -> -5.2406143 | EX13: 0 | EZ13: =Data!BU36*(Data!BX36*Data!BY36*0.01/Data!BW36)^1 -> 590368.18 | FA13: =(Data!BR36+Data!BT36)*(Data!BX36*Data!BY36*0.01/Data!BW36)^1 -> 710195.9 | FC13: =Data!CN36*(Data!CQ36*Data!CR36*0.01/Data!CP36)^1 -> 590368.18 | FD13: =(Data!CK36+Data!CM36)*(Data!CQ36*Data!CR36*0.01/Data!CP36)^1 -> 710195.9
A14: 2010 | B14: =100*(Data!BO37/Data!BO$46) -> 84.888308 | C14: =100*(Data!CH37/Data!CH$46) -> 84.888308 | D14: 100 | F14: =100*((C14/B14)-1) -> 0 | H14: 2010 | I14: =100*(O14/Data!$BW37) -> 70.398212 | J14: =100*(P14/Data!$CP37) -> 70.398212 | O14: =Data!BV37-$R14 -> 1145500 | P14: =Data!CO37-$R14 -> 1145500 | R14: ='GNDBTX ex BoE'!D130 -> 23200 | CL14: 2010 | CM14: =100*(Data!BS37/Data!$BW37) -> 2.4455927 | CN14: =100*(Data!CL37/Data!$CP37) -> 2.4455927 | CO14: 3 | CQ14: 2010 | CR14: =100*(Data!BQ37/Data!$BW37) -> -6.2858137 | CS14: =100*(Data!CJ37/Data!$CP37) -> -6.2858137 | CT14: 0 | CV14: 2010 | CW14: =CR14-DA14 -> -2.5273837 | CX14: =CS14-DB14 -> -2.5273837 | CY14: 0 | DA14: =Data!CF37 -> -3.75843 | DB14: =Data!CY37 -> -3.75843 | DD14: 2010 | DE14: =100*(Data!BO37/Data!BO$46) -> 84.888308 | DF14: =100*(Data!CH37/Data!CH$46) -> 84.888308 | DG14: =100*(Data!DA37/Data!DA$46) -> 84.888308 | DI14: =I14 -> 70.398212 | DJ14: =J14 -> 70.398212 | DK14: =100*(Data!DH37-$R14)/Data!DI37 -> 70.398212 | DM14: =CW14 -> -2.5273837 | DN14: =CX14 -> -2.5273837 | DO14: =(100*(Data!DC37/Data!$DI37))-Data!$DR37 -> -2.5273837 | DS14: 2017-18 | DT14: =100*(EI14/EI$20) -> 86.306349 | DU14: =100*(EJ14/EJ$20) -> 86.890298 | DV14: =100*(EK14/EK$20) -> 86.60339 | DW14: =100*(EL14/EL$20) -> 88.89911 | DX14: =100*(EM14/EM$20) -> 89.829709 | DY14: 100 | EA14: =100*(EO14/EO$20) -> 65.948945 | EB14: =100*(EP14/EP$20) -> 68.437934 | EC14: =100*(EQ14/EQ$20) -> 83.781463 | ED14: =100*(ER14/ER$20) -> 70.232475 | EE14: =100*(ES14/ES$20) -> 70.926661 | EF14: 100 | EH14: 2017-18 | EI14: 4899.2511 | EJ14: 5199.9116 | EK14: 5219.9347 | EL14: 5211.2493 | EM14: 5539.1387 | EO14: 868.39721 | EP14: 921.6896 | EQ14: 925.2387 | ER14: 926.65766 | ES14: 988.39974 | EU14: 2010 | EV14: =100*((EZ14-FA14)/Data!BX37*Data!BY37*0.01) -> -4.6676078 | EW14: =100*((FC14-FD14)/Data!CQ37*Data!CR37*0.01) -> -4.6676078 | EX14: 0 | EZ14: =Data!BU37*(Data!BX37*Data!BY37*0.01/Data!BW37)^1 -> 625002.14 | FA14: =(Data!BR37+Data!BT37)*(Data!BX37*Data!BY37*0.01/Data!BW37)^1 -> 731109.29 | FC14: =Data!CN37*(Data!CQ37*Data!CR37*0.01/Data!CP37)^1 -> 625002.14 | FD14: =(Data!CK37+Data!CM37)*(Data!CQ37*Data!CR37*0.01/Data!CP37)^1 -> 731109.29
A15: 2011 | B15: =100*(Data!BO38/Data!BO$46) -> 85.744862 | C15: =100*(Data!CH38/Data!CH$46) -> 85.744862 | D15: 100 | F15: =100*((C15/B15)-1) -> 0 | H15: 2011 | I15: =100*(O15/Data!$BW38) -> 74.897074 | J15: =100*(P15/Data!$CP38) -> 74.897074 | O15: =Data!BV38-$R15 -> 1252700 | P15: =Data!CO38-$R15 -> 1252700 | R15: ='GNDBTX ex BoE'!D131 -> 8500 | CL15: 2011 | CM15: =100*(Data!BS38/Data!$BW38) -> 1.8428614 | CN15: =100*(Data!CL38/Data!$CP38) -> 1.8428614 | CO15: 3 | CQ15: 2011 | CR15: =100*(Data!BQ38/Data!$BW38) -> -5.4081104 | CS15: =100*(Data!CJ38/Data!$CP38) -> -5.4081104 | CT15: 0 | CV15: 2011 | CW15: =CR15-DA15 -> -2.1343374 | CX15: =CS15-DB15 -> -2.1343374 | CY15: 0 | DA15: =Data!CF38 -> -3.273773 | DB15: =Data!CY38 -> -3.273773 | DD15: 2011 | DE15: =100*(Data!BO38/Data!BO$46) -> 85.744862 | DF15: =100*(Data!CH38/Data!CH$46) -> 85.744862 | DG15: =100*(Data!DA38/Data!DA$46) -> 85.744862 | DI15: =I15 -> 74.897074 | DJ15: =J15 -> 74.897074 | DK15: =100*(Data!DH38-$R15)/Data!DI38 -> 74.897074 | DM15: =CW15 -> -2.1343374 | DN15: =CX15 -> -2.1343374 | DO15: =(100*(Data!DC38/Data!$DI38))-Data!$DR38 -> -2.1343374 | DS15: 2018-19 | DT15: =100*(EI15/EI$20) -> 86.315066 | DU15: =100*(EJ15/EJ$20) -> 86.987854 | DV15: =100*(EK15/EK$20) -> 86.700624 | DW15: =100*(EL15/EL$20) -> 88.679068 | DX15: =100*(EM15/EM$20) -> 89.519645 | DY15: 100 | EA15: =100*(EO15/EO$20) -> 68.732334 | EB15: =100*(EP15/EP$20) -> 71.399242 | EC15: =100*(EQ15/EQ$20) -> 87.406685 | ED15: =100*(ER15/ER$20) -> 73.081639 | EE15: =100*(ES15/ES$20) -> 73.803986 | EF15: 100 | EH15: 2018-19 | EI15: 4899.7459 | EJ15: 5205.7498 | EK15: 5225.7953 | EL15: 5198.3505 | EM15: 5520.0193 | EO15: 905.0481 | EP15: 961.57109 | EQ15: 965.27376 | ER15: 964.24995 | ES15: 1028.4968 | EU15: 2011 | EV15: =100*((EZ15-FA15)/Data!BX38*Data!BY38*0.01) -> -4.1586588 | EW15: =100*((FC15-FD15)/Data!CQ38*Data!CR38*0.01) -> -4.1586588 | EX15: 0 | EZ15: =Data!BU38*(Data!BX38*Data!BY38*0.01/Data!BW38)^1 -> 645977.61 | FA15: =(Data!BR38+Data!BT38)*(Data!BX38*Data!BY38*0.01/Data!BW38)^1 -> 739571.55 | FC15: =Data!CN38*(Data!CQ38*Data!CR38*0.01/Data!CP38)^1 -> 645977.61 | FD15: =(Data!CK38+Data!CM38)*(Data!CQ38*Data!CR38*0.01/Data!CP38)^1 -> 739571.55
A16: 2012 | B16: =100*(Data!BO39/Data!BO$46) -> 86.945963 | C16: =100*(Data!CH39/Data!CH$46) -> 86.945963 | D16: 100 | F16: =100*((C16/B16)-1) -> 0 | H16: 2012 | I16: =100*(O16/Data!$BW39) -> 77.586077 | J16: =100*(P16/Data!$CP39) -> 77.586077 | O16: =Data!BV39-$R16 -> 1340000 | P16: =Data!CO39-$R16 -> 1340000 | R16: ='GNDBTX ex BoE'!D132 -> 26200 | V16: =V5-DT17 -> -1.1894328 | CL16: 2012 | CM16: =100*(Data!BS39/Data!$BW39) -> 1.8779305 | CN16: =100*(Data!CL39/Data!$CP39) -> 1.8779305 | CO16: 3 | CQ16: 2012 | CR16: =100*(Data!BQ39/Data!$BW39) -> -5.3302214 | CS16: =100*(Data!CJ39/Data!$CP39) -> -5.3302214 | CT16: 0 | CV16: 2012 | CW16: =CR16-DA16 -> -1.2041494 | CX16: =CS16-DB16 -> -1.2041494 | CY16: 0 | DA16: =Data!CF39 -> -4.126072 | DB16: =Data!CY39 -> -4.126072 | DD16: 2012 | DE16: =100*(Data!BO39/Data!BO$46) -> 86.945963 | DF16: =100*(Data!CH39/Data!CH$46) -> 86.945963 | DG16: =100*(Data!DA39/Data!DA$46) -> 86.945963 | DI16: =I16 -> 77.586077 | DJ16: =J16 -> 77.586077 | DK16: =100*(Data!DH39-$R16)/Data!DI39 -> 77.586077 | DM16: =CW16 -> -1.2041494 | DN16: =CX16 -> -1.2041494 | DO16: =(100*(Data!DC39/Data!$DI39))-Data!$DR39 -> -1.2041494 | DS16: 2019-20 | DT16: =100*(EI16/EI$20) -> 90.213486 | DU16: =100*(EJ16/EJ$20) -> 90.712326 | DV16: =100*(EK16/EK$20) -> 90.412798 | DW16: =100*(EL16/EL$20) -> 92.725512 | DX16: =100*(EM16/EM$20) -> 93.503228 | DY16: 100 | EA16: =100*(EO16/EO$20) -> 70.119281 | EB16: =100*(EP16/EP$20) -> 72.676298 | EC16: =100*(EQ16/EQ$20) -> 88.970051 | ED16: =100*(ER16/ER$20) -> 74.548298 | EE16: =100*(ES16/ES$20) -> 75.285142 | EF16: 100 | EH16: 2019-20 | EI16: 5121.0429 | EJ16: 5428.6392 | EK16: 5449.543 | EL16: 5435.5523 | EM16: 5765.6577 | EO16: 923.31103 | EP16: 978.76987 | EQ16: 982.53876 | ER16: 983.60127 | ES16: 1049.1374 | EU16: 2012 | EV16: =100*((EZ16-FA16)/Data!BX39*Data!BY39*0.01) -> -4.250604 | EW16: =100*((FC16-FD16)/Data!CQ39*Data!CR39*0.01) -> -4.250604 | EX16: 0 | EZ16: =Data!BU39*(Data!BX39*Data!BY39*0.01/Data!BW39)^1 -> 661512.16 | FA16: =(Data!BR39+Data!BT39)*(Data!BX39*Data!BY39*0.01/Data!BW39)^1 -> 757323.47 | FC16: =Data!CN39*(Data!CQ39*Data!CR39*0.01/Data!CP39)^1 -> 661512.16 | FD16: =(Data!CK39+Data!CM39)*(Data!CQ39*Data!CR39*0.01/Data!CP39)^1 -> 757323.47
A17: 2013 | B17: =100*(Data!BO40/Data!BO$46) -> 88.966484 | C17: =100*(Data!CH40/Data!CH$46) -> 88.966484 | D17: 100 | F17: =100*((C17/B17)-1) -> 0 | H17: 2013 | I17: =100*(O17/Data!$BW40) -> 78.251214 | J17: =100*(P17/Data!$CP40) -> 78.251214 | O17: =Data!BV40-$R17 -> 1409500 | P17: =Data!CO40-$R17 -> 1409500 | R17: ='GNDBTX ex BoE'!D133 -> 51600 | V17: =V6-DT18 -> -0.6762853 | W17: =W6-DU18 -> 1.1633951 | X17: =X6-DV18 -> 0.85289492 | CL17: 2013 | CM17: =100*(Data!BS40/Data!$BW40) -> 1.4547675 | CN17: =100*(Data!CL40/Data!$CP40) -> 1.4547675 | CO17: 3 | CQ17: 2013 | CR17: =100*(Data!BQ40/Data!$BW40) -> -4.3294934 | CS17: =100*(Data!CJ40/Data!$CP40) -> -4.3294934 | CT17: 0 | CV17: 2013 | CW17: =CR17-DA17 -> -1.5670804 | CX17: =CS17-DB17 -> -1.5670804 | CY17: 0 | DA17: =Data!CF40 -> -2.762413 | DB17: =Data!CY40 -> -2.762413 | DD17: 2013 | DE17: =100*(Data!BO40/Data!BO$46) -> 88.966484 | DF17: =100*(Data!CH40/Data!CH$46) -> 88.966484 | DG17: =100*(Data!DA40/Data!DA$46) -> 88.966484 | DI17: =I17 -> 78.251214 | DJ17: =J17 -> 78.251214 | DK17: =100*(Data!DH40-$R17)/Data!DI40 -> 78.251214 | DM17: =CW17 -> -1.5670804 | DN17: =CX17 -> -1.5670804 | DO17: =(100*(Data!DC40/Data!$DI40))-Data!$DR40 -> -1.5670804 | DS17: 2020-21 | DT17: =100*(EI17/EI$20) -> 113.57468 | DU17: =100*(EJ17/EJ$20) -> 111.97582 | DV17: =100*(EK17/EK$20) -> 111.84845 | DW17: =100*(EL17/EL$20) -> 113.97779 | DX17: =100*(EM17/EM$20) -> 112.15508 | DY17: 100 | EA17: =100*(EO17/EO$20) -> 81.384706 | EB17: =100*(EP17/EP$20) -> 87.029466 | EC17: =100*(EQ17/EQ$20) -> 106.77252 | ED17: =100*(ER17/ER$20) -> 90.335461 | EE17: =100*(ES17/ES$20) -> 91.228347 | EF17: 100 | EH17: 2020-21 | EI17: 6447.1604 | EJ17: 6701.1436 | EK17: 6741.556 | EL17: 6681.3569 | EM17: 6915.7804 | EO17: 1071.651 | EP17: 1172.0715 | EQ17: 1179.1399 | ER17: 1191.8994 | ES17: 1271.3142 | EU17: 2013 | EV17: =100*((EZ17-FA17)/Data!BX40*Data!BY40*0.01) -> -3.5866227 | EW17: =100*((FC17-FD17)/Data!CQ40*Data!CR40*0.01) -> -3.5866227 | EX17: 0 | EZ17: =Data!BU40*(Data!BX40*Data!BY40*0.01/Data!BW40)^1 -> 684946.87 | FA17: =(Data!BR40+Data!BT40)*(Data!BX40*Data!BY40*0.01/Data!BW40)^1 -> 765565.65 | FC17: =Data!CN40*(Data!CQ40*Data!CR40*0.01/Data!CP40)^1 -> 684946.87 | FD17: =(Data!CK40+Data!CM40)*(Data!CQ40*Data!CR40*0.01/Data!CP40)^1 -> 765565.65
A18: 2014 | B18: =100*(Data!BO41/Data!BO$46) -> 91.704958 | C18: =100*(Data!CH41/Data!CH$46) -> 91.704958 | D18: 100 | F18: =100*((C18/B18)-1) -> 0 | H18: 2014 | I18: =100*(O18/Data!$BW41) -> 80.228388 | J18: =100*(P18/Data!$CP41) -> 80.228388 | O18: =Data!BV41-$R18 -> 1507700 | P18: =Data!CO41-$R18 -> 1507700 | R18: ='GNDBTX ex BoE'!D134 -> 45200 | V18: =V7-DT19 -> -0.64218983 | W18: =W7-DU19 -> 1.1352963 | X18: =X7-DV19 -> 0.87192324 | Y18: =Y7-DW19 -> 0.14702494 | Z18: =Z7-DX19 -> -0.10865682 | CL18: 2014 | CM18: =100*(Data!BS41/Data!$BW41) -> 1.9251727 | CN18: =100*(Data!CL41/Data!$CP41) -> 1.9251727 | CO18: 3 | CQ18: 2014 | CR18: =100*(Data!BQ41/Data!$BW41) -> -3.3486053 | CS18: =100*(Data!CJ41/Data!$CP41) -> -3.3486053 | CT18: 0 | CV18: 2014 | CW18: =CR18-DA18 -> -1.7708463 | CX18: =CS18-DB18 -> -1.7708463 | CY18: 0 | DA18: =Data!CF41 -> -1.577759 | DB18: =Data!CY41 -> -1.577759 | DD18: 2014 | DE18: =100*(Data!BO41/Data!BO$46) -> 91.704958 | DF18: =100*(Data!CH41/Data!CH$46) -> 91.704958 | DG18: =100*(Data!DA41/Data!DA$46) -> 91.704958 | DI18: =I18 -> 80.228388 | DJ18: =J18 -> 80.228388 | DK18: =100*(Data!DH41-$R18)/Data!DI41 -> 80.228388 | DM18: =CW18 -> -1.7708463 | DN18: =CX18 -> -1.7708463 | DO18: =(100*(Data!DC41/Data!$DI41))-Data!$DR41 -> -1.7708463 | DS18: 2021-22 | DT18: =100*(EI18/EI$20) -> 106.32143 | DU18: =100*(EJ18/EJ$20) -> 107.31795 | DV18: =100*(EK18/EK$20) -> 107.51169 | DW18: =100*(EL18/EL$20) -> 110.49503 | DX18: =100*(EM18/EM$20) -> 110.01328 | DY18: 100 | EA18: =100*(EO18/EO$20) -> 78.317265 | EB18: =100*(EP18/EP$20) -> 88.73404 | EC18: =100*(EQ18/EQ$20) -> 109.18451 | ED18: =100*(ER18/ER$20) -> 92.667949 | EE18: =100*(ES18/ES$20) -> 93.606097 | EF18: 100 | EH18: 2021-22 | EI18: 6035.4237 | EJ18: 6422.3956 | EK18: 6480.1623 | EL18: 6477.1981 | EM18: 6783.7111 | EO18: 1031.2598 | EP18: 1195.0279 | EQ18: 1205.7767 | ER18: 1222.6746 | ES18: 1304.4494 | EU18: 2014 | EV18: =100*((EZ18-FA18)/Data!BX41*Data!BY41*0.01) -> -2.8419416 | EW18: =100*((FC18-FD18)/Data!CQ41*Data!CR41*0.01) -> -2.8419416 | EX18: 0 | EZ18: =Data!BU41*(Data!BX41*Data!BY41*0.01/Data!BW41)^1 -> 701959.34 | FA18: =(Data!BR41+Data!BT41)*(Data!BX41*Data!BY41*0.01/Data!BW41)^1 -> 766045.55 | FC18: =Data!CN41*(Data!CQ41*Data!CR41*0.01/Data!CP41)^1 -> 701959.34 | FD18: =(Data!CK41+Data!CM41)*(Data!CQ41*Data!CR41*0.01/Data!CP41)^1 -> 766045.55
A19: 2015 | B19: =100*(Data!BO42/Data!BO$46) -> 93.577842 | C19: =100*(Data!CH42/Data!CH$46) -> 93.577842 | D19: 100 | F19: =100*((C19/B19)-1) -> 0 | H19: 2015 | I19: =100*(O19/Data!$BW42) -> 80.613303 | J19: =100*(P19/Data!$CP42) -> 80.613303 | O19: =Data!BV42-$R19 -> 1557000 | P19: =Data!CO42-$R19 -> 1557000 | R19: ='GNDBTX ex BoE'!D135 -> 42700 | V19: =V8-DT20 -> -0.62710491 | W19: =W8-DU20 -> 1.1059032 | X19: =X8-DV20 -> 0.83212605 | Y19: =Y8-DW20 -> 0.15211225 | Z19: =Z8-DX20 -> -0.11553016 | CL19: 2015 | CM19: =100*(Data!BS42/Data!$BW42) -> 1.669736 | CN19: =100*(Data!CL42/Data!$CP42) -> 1.669736 | CO19: 3 | CQ19: 2015 | CR19: =100*(Data!BQ42/Data!$BW42) -> -2.5887381 | CS19: =100*(Data!CJ42/Data!$CP42) -> -2.5887381 | CT19: 0 | CV19: 2015 | CW19: =CR19-DA19 -> -1.2133491 | CX19: =CS19-DB19 -> -1.2133491 | CY19: 0 | DA19: =Data!CF42 -> -1.375389 | DB19: =Data!CY42 -> -1.375389 | DD19: 2015 | DE19: =100*(Data!BO42/Data!BO$46) -> 93.577842 | DF19: =100*(Data!CH42/Data!CH$46) -> 93.577842 | DG19: =100*(Data!DA42/Data!DA$46) -> 93.577842 | DI19: =I19 -> 80.613303 | DJ19: =J19 -> 80.613303 | DK19: =100*(Data!DH42-$R19)/Data!DI42 -> 80.613303 | DM19: =CW19 -> -1.2133491 | DN19: =CX19 -> -1.2133491 | DO19: =(100*(Data!DC42/Data!$DI42))-Data!$DR42 -> -1.2133491 | DS19: 2022-23 | DT19: =100*(EI19/EI$20) -> 102.38696 | DU19: =100*(EJ19/EJ$20) -> 102.56541 | DV19: =100*(EK19/EK$20) -> 101.57363 | DW19: =100*(EL19/EL$20) -> 103.20223 | DX19: =100*(EM19/EM$20) -> 103.59736 | DY19: 100 | EA19: =100*(EO19/EO$20) -> 93.263013 | EB19: =100*(EP19/EP$20) -> 97.426011 | EC19: =100*(EQ19/EQ$20) -> 115.17148 | ED19: =100*(ER19/ER$20) -> 100.04159 | EE19: =100*(ES19/ES$20) -> 101.01867 | EF19: 100 | EH19: 2022-23 | EI19: 5812.0802 | EJ19: 6137.9817 | EK19: 6122.2512 | EL19: 6049.6958 | EM19: 6388.0887 | EO19: 1228.0612 | EP19: 1312.0873 | EQ19: 1271.8937 | ER19: 1319.9636 | ES19: 1407.7475 | EU19: 2015 | EV19: =100*((EZ19-FA19)/Data!BX42*Data!BY42*0.01) -> -2.228772 | EW19: =100*((FC19-FD19)/Data!CQ42*Data!CR42*0.01) -> -2.228772 | EX19: 0 | EZ19: =Data!BU42*(Data!BX42*Data!BY42*0.01/Data!BW42)^1 -> 723785 | FA19: =(Data!BR42+Data!BT42)*(Data!BX42*Data!BY42*0.01/Data!BW42)^1 -> 774468.87 | FC19: =Data!CN42*(Data!CQ42*Data!CR42*0.01/Data!CP42)^1 -> 723785 | FD19: =(Data!CK42+Data!CM42)*(Data!CQ42*Data!CR42*0.01/Data!CP42)^1 -> 774468.87
A20: 2016 | B20: =100*(Data!BO43/Data!BO$46) -> 95.492356 | C20: =100*(Data!CH43/Data!CH$46) -> 95.492356 | D20: 100 | F20: =100*((C20/B20)-1) -> 0 | H20: 2016 | I20: =100*(O20/Data!$BW43) -> 79.619375 | J20: =100*(P20/Data!$CP43) -> 79.619375 | O20: =Data!BV43-$R20 -> 1605000 | P20: =Data!CO43-$R20 -> 1605000 | R20: ='GNDBTX ex BoE'!D136 -> 113000 | V20: =V9-DT21 -> -0.63004636 | W20: =W9-DU21 -> 1.0919213 | X20: =X9-DV21 -> 0.82546009 | Y20: =Y9-DW21 -> 0.15577301 | Z20: =Z9-DX21 -> -0.10404915 | CL20: 2016 | CM20: =100*(Data!BS43/Data!$BW43) -> 1.8081783 | CN20: =100*(Data!CL43/Data!$CP43) -> 1.8081783 | CO20: 3 | CQ20: 2016 | CR20: =100*(Data!BQ43/Data!$BW43) -> -1.0794502 | CS20: =100*(Data!CJ43/Data!$CP43) -> -1.0794502 | CT20: 0 | CV20: 2016 | CW20: =CR20-DA20 -> -0.26176981 | CX20: =CS20-DB20 -> -0.26176981 | CY20: 0 | DA20: =Data!CF43 -> -0.8176804 | DB20: =Data!CY43 -> -0.8176804 | DD20: 2016 | DE20: =100*(Data!BO43/Data!BO$46) -> 95.492356 | DF20: =100*(Data!CH43/Data!CH$46) -> 95.492356 | DG20: =100*(Data!DA43/Data!DA$46) -> 95.492356 | DI20: =I20 -> 79.619375 | DJ20: =J20 -> 79.619375 | DK20: =100*(Data!DH43-$R20)/Data!DI43 -> 79.619375 | DM20: =CW20 -> -0.26176981 | DN20: =CX20 -> -0.26176981 | DO20: =(100*(Data!DC43/Data!$DI43))-Data!$DR43 -> -0.26176981 | DS20: 2023-24 | DT20: =100*(EI20/EI$20) -> 100 | DU20: =100*(EJ20/EJ$20) -> 100 | DV20: =100*(EK20/EK$20) -> 100 | DW20: =100*(EL20/EL$20) -> 100 | DX20: =100*(EM20/EM$20) -> 100 | DY20: 100 | EA20: =100*(EO20/EO$20) -> 100 | EB20: =100*(EP20/EP$20) -> 100 | EC20: =100*(EQ20/EQ$20) -> 100 | ED20: =100*(ER20/ER$20) -> 100 | EE20: =100*(ES20/ES$20) -> 100 | EF20: 100 | EH20: 2023-24 | EI20: 5676.5825 | EJ20: 5984.456 | EK20: 6027.4022 | EL20: 5861.9814 | EM20: 6166.2659 | EO20: 1316.772 | EP20: 1346.7525 | EQ20: 1104.3477 | ER20: 1319.4148 | ES20: 1393.5518 | EU20: 2016 | EV20: =100*((EZ20-FA20)/Data!BX43*Data!BY43*0.01) -> -0.97210959 | EW20: =100*((FC20-FD20)/Data!CQ43*Data!CR43*0.01) -> -0.97210959 | EX20: 0 | EZ20: =Data!BU43*(Data!BX43*Data!BY43*0.01/Data!BW43)^1 -> 763326.22 | FA20: =(Data!BR43+Data!BT43)*(Data!BX43*Data!BY43*0.01/Data!BW43)^1 -> 785317.42 | FC20: =Data!CN43*(Data!CQ43*Data!CR43*0.01/Data!CP43)^1 -> 763326.22 | FD20: =(Data!CK43+Data!CM43)*(Data!CQ43*Data!CR43*0.01/Data!CP43)^1 -> 785317.42
A21: 2017 | B21: =100*(Data!BO44/Data!BO$46) -> 97.939198 | C21: =100*(Data!CH44/Data!CH$46) -> 97.939198 | D21: 100 | F21: =100*((C21/B21)-1) -> 0 | H21: 2017 | I21: =100*(O21/Data!$BW44) -> 75.096842 | J21: =100*(P21/Data!$CP44) -> 75.096842 | O21: =Data!BV44-$R21 -> 1576900 | P21: =Data!CO44-$R21 -> 1576900 | R21: ='GNDBTX ex BoE'!D137 -> 180400 | V21: =V10-DT22 -> -0.64054795 | W21: =W10-DU22 -> 1.1057325 | X21: =X10-DV22 -> 0.83243957 | Y21: =Y10-DW22 -> 0.15521239 | Z21: =Z10-DX22 -> -0.1054679 | CL21: 2017 | CM21: =100*(Data!BS44/Data!$BW44) -> 2.2078538 | CN21: =100*(Data!CL44/Data!$CP44) -> 2.2078538 | CO21: 3 | CQ21: 2017 | CR21: =100*(Data!BQ44/Data!$BW44) -> -0.66162746 | CS21: =100*(Data!CJ44/Data!$CP44) -> -0.66162746 | CT21: 0 | CV21: 2017 | CW21: =CR21-DA21 -> -0.80048246 | CX21: =CS21-DB21 -> -0.80048246 | CY21: 0 | DA21: =Data!CF44 -> 0.138855 | DB21: =Data!CY44 -> 0.138855 | DD21: 2017 | DE21: =100*(Data!BO44/Data!BO$46) -> 97.939198 | DF21: =100*(Data!CH44/Data!CH$46) -> 97.939198 | DG21: =100*(Data!DA44/Data!DA$46) -> 97.939198 | DI21: =I21 -> 75.096842 | DJ21: =J21 -> 75.096842 | DK21: =100*(Data!DH44-$R21)/Data!DI44 -> 75.096842 | DM21: =CW21 -> -0.80048246 | DN21: =CX21 -> -0.80048246 | DO21: =(100*(Data!DC44/Data!$DI44))-Data!$DR44 -> -0.80048246 | DS21: 2024-25 | DT21: =100*(EI21/EI$20) -> 100.63005 | DU21: =100*(EJ21/EJ$20) -> 98.908079 | DV21: =100*(EK21/EK$20) -> 99.17454 | DW21: =100*(EL21/EL$20) -> 99.844227 | DX21: =100*(EM21/EM$20) -> 100.10405 | DY21: 100 | EA21: =100*(EO21/EO$20) -> 98.192867 | EB21: =100*(EP21/EP$20) -> 98.652286 | EC21: =100*(EQ21/EQ$20) -> 122.91946 | ED21: =100*(ER21/ER$20) -> 101.05112 | EE21: =100*(ES21/ES$20) -> 102.14023 | EF21: 100 | EH21: 2024-25 | EI21: 5712.3476 | EJ21: 5919.1104 | EK21: 5977.6484 | EL21: 5852.85 | EM21: 6172.6818 | EO21: 1292.9761 | EP21: 1328.6021 | EQ21: 1357.4583 | ER21: 1333.2834 | ES21: 1423.377 | EU21: 2017 | EV21: =100*((EZ21-FA21)/Data!BX44*Data!BY44*0.01) -> -0.61464397 | EW21: =100*((FC21-FD21)/Data!CQ44*Data!CR44*0.01) -> -0.61464397 | EX21: 0 | EZ21: =Data!BU44*(Data!BX44*Data!BY44*0.01/Data!BW44)^1 -> 779852.73 | FA21: =(Data!BR44+Data!BT44)*(Data!BX44*Data!BY44*0.01/Data!BW44)^1 -> 793738.21 | FC21: =Data!CN44*(Data!CQ44*Data!CR44*0.01/Data!CP44)^1 -> 779852.73 | FD21: =(Data!CK44+Data!CM44)*(Data!CQ44*Data!CR44*0.01/Data!CP44)^1 -> 793738.21
A22: 2018 | B22: =100*(Data!BO45/Data!BO$46) -> 99.142097 | C22: =100*(Data!CH45/Data!CH$46) -> 99.142097 | D22: 100 | F22: =100*((C22/B22)-1) -> 0 | H22: 2018 | I22: =100*(O22/Data!$BW45) -> 74.045167 | J22: =100*(P22/Data!$CP45) -> 74.045167 | O22: =Data!BV45-$R22 -> 1607100 | P22: =Data!CO45-$R22 -> 1607100 | R22: ='GNDBTX ex BoE'!D138 -> 169800 | V22: =V11-DT23 -> -0.65042913 | W22: =W11-DU23 -> 1.1111692 | X22: =X11-DV23 -> 0.83805439 | Y22: =Y11-DW23 -> 0.15578703 | Z22: =Z11-DX23 -> -0.10609401 | CL22: 2018 | CM22: =100*(Data!BS45/Data!$BW45) -> 2.1032679 | CN22: =100*(Data!CL45/Data!$CP45) -> 2.1032679 | CO22: 3 | CQ22: 2018 | CR22: =100*(Data!BQ45/Data!$BW45) -> 0.030408693 | CS22: =100*(Data!CJ45/Data!$CP45) -> 0.030408693 | CT22: 0 | CV22: 2018 | CW22: =CR22-DA22 -> 0.55121019 | CX22: =CS22-DB22 -> 0.55121019 | CY22: 0 | DA22: =Data!CF45 -> -0.5208015 | DB22: =Data!CY45 -> -0.5208015 | DD22: 2018 | DE22: =100*(Data!BO45/Data!BO$46) -> 99.142097 | DF22: =100*(Data!CH45/Data!CH$46) -> 99.142097 | DG22: =100*(Data!DA45/Data!DA$46) -> 99.142097 | DI22: =I22 -> 74.045167 | DJ22: =J22 -> 74.045167 | DK22: =100*(Data!DH45-$R22)/Data!DI45 -> 74.045167 | DM22: =CW22 -> 0.55121019 | DN22: =CX22 -> 0.55121019 | DO22: =(100*(Data!DC45/Data!$DI45))-Data!$DR45 -> 0.55121019 | DS22: 2025-26 | DT22: =100*(EI22/EI$20) -> 102.34126 | DU22: =100*(EJ22/EJ$20) -> 100.00684 | DV22: =100*(EK22/EK$20) -> 99.936896 | DW22: =100*(EL22/EL$20) -> 99.936891 | DX22: =100*(EM22/EM$20) -> 100.4689 | DY22: 100 | EA22: =100*(EO22/EO$20) -> 100.58256 | EB22: =100*(EP22/EP$20) -> 98.730082 | EC22: =100*(EQ22/EQ$20) -> 121.49031 | ED22: =100*(ER22/ER$20) -> 96.947522 | EE22: =100*(ES22/ES$20) -> 99.07125 | EF22: 100 | EH22: 2025-26 | EI22: 5809.4858 | EJ22: 5984.8656 | EK22: 6023.5987 | EL22: 5858.282 | EM22: 6195.1797 | EO22: 1324.4429 | EP22: 1329.6499 | EQ22: 1341.6755 | ER22: 1279.1399 | ES22: 1380.6092 | EU22: 2018 | EV22: =100*((EZ22-FA22)/Data!BX45*Data!BY45*0.01) -> 0.029453681 | EW22: =100*((FC22-FD22)/Data!CQ45*Data!CR45*0.01) -> 0.029453681 | EX22: 0 | EZ22: =Data!BU45*(Data!BX45*Data!BY45*0.01/Data!BW45)^1 -> 815940.38 | FA22: =(Data!BR45+Data!BT45)*(Data!BX45*Data!BY45*0.01/Data!BW45)^1 -> 815277.88 | FC22: =Data!CN45*(Data!CQ45*Data!CR45*0.01/Data!CP45)^1 -> 815940.38 | FD22: =(Data!CK45+Data!CM45)*(Data!CQ45*Data!CR45*0.01/Data!CP45)^1 -> 815277.88
A23: 2019 | B23: =100*(Data!BO46/Data!BO$46) -> 100 | C23: =100*(Data!CH46/Data!CH$46) -> 100 | D23: 100 | F23: =100*((C23/B23)-1) -> 0 | H23: 2019 | I23: =100*(O23/Data!$BW46) -> 73.771392 | J23: =100*(P23/Data!$CP46) -> 73.771392 | O23: =Data!BV46-$R23 -> 1653000 | P23: =Data!CO46-$R23 -> 1653000 | R23: ='GNDBTX ex BoE'!D139 -> 162000 | W23: =W12-DU24 -> 1.1205447 | X23: =X12-DV24 -> 0.84519509 | Y23: =Y12-DW24 -> 0.15709247 | Z23: =Z12-DX24 -> -0.10651861 | CL23: 2019 | CM23: =100*(Data!BS46/Data!$BW46) -> 1.8992228 | CN23: =100*(Data!CL46/Data!$CP46) -> 1.8992228 | CO23: 3 | CQ23: 2019 | CR23: =100*(Data!BQ46/Data!$BW46) -> -0.80416619 | CS23: =100*(Data!CJ46/Data!$CP46) -> -0.80416619 | CT23: 0 | CV23: 2019 | CW23: =CR23-DA23 -> 1.0973648 | CX23: =CS23-DB23 -> 1.0973648 | CY23: 0 | DA23: =Data!CF46 -> -1.901531 | DB23: =Data!CY46 -> -1.901531 | DD23: 2019 | DE23: =100*(Data!BO46/Data!BO$46) -> 100 | DF23: =100*(Data!CH46/Data!CH$46) -> 100 | DG23: =100*(Data!DA46/Data!DA$46) -> 100 | DI23: =I23 -> 73.771392 | DJ23: =J23 -> 73.771392 | DK23: =100*(Data!DH46-$R23)/Data!DI46 -> 73.771392 | DM23: =CW23 -> 1.0973648 | DN23: =CX23 -> 1.0973648 | DO23: =(100*(Data!DC46/Data!$DI46))-Data!$DR46 -> 1.0973648 | DS23: 2026-27 | DT23: =100*(EI23/EI$20) -> 103.8784 | DU23: =100*(EJ23/EJ$20) -> 100.7191 | DV23: =100*(EK23/EK$20) -> 100.71891 | DW23: =100*(EL23/EL$20) -> 100.54617 | DX23: =100*(EM23/EM$20) -> 100.98314 | DY23: 100 | EA23: =100*(EO23/EO$20) -> 102.08599 | EB23: =100*(EP23/EP$20) -> 97.678659 | EC23: =100*(EQ23/EQ$20) -> 120.10664 | ED23: =100*(ER23/ER$20) -> 95.331296 | EE23: =100*(ES23/ES$20) -> 97.164108 | EF23: 100 | EH23: 2026-27 | EI23: 5896.7428 | EJ23: 6027.49 | EK23: 6070.7339 | EL23: 5893.9975 | EM23: 6226.8892 | EO23: 1344.2397 | EP23: 1315.4898 | EQ23: 1326.395 | ER23: 1257.8152 | ES23: 1354.0321 | EU23: 2019 | EV23: =100*((EZ23-FA23)/Data!BX46*Data!BY46*0.01) -> -0.81612331 | EW23: =100*((FC23-FD23)/Data!CQ46*Data!CR46*0.01) -> -0.81612331 | EX23: 0 | EZ23: =Data!BU46*(Data!BX46*Data!BY46*0.01/Data!BW46)^1 -> 832220.21 | FA23: =(Data!BR46+Data!BT46)*(Data!BX46*Data!BY46*0.01/Data!BW46)^1 -> 850341.78 | FC23: =Data!CN46*(Data!CQ46*Data!CR46*0.01/Data!CP46)^1 -> 832220.21 | FD23: =(Data!CK46+Data!CM46)*(Data!CQ46*Data!CR46*0.01/Data!CP46)^1 -> 850341.78
A24: 2020 | B24: =100*(Data!BO47/Data!BO$46) -> 88.391176 | C24: =100*(Data!CH47/Data!CH$46) -> 88.391176 | D24: 100 | F24: =100*((C24/B24)-1) -> 0 | H24: 2020 | I24: =100*(O24/Data!$BW47) -> 91.648567 | J24: =100*(P24/Data!$CP47) -> 91.648567 | O24: =Data!BV47-$R24 -> 1911900 | P24: =Data!CO47-$R24 -> 1911900 | R24: ='GNDBTX ex BoE'!D140 -> 240100 | Y24: =Y13-DW25 -> 0.1583165 | Z24: =Z13-DX25 -> -0.1069622 | CL24: 2020 | CM24: =100*(Data!BS47/Data!$BW47) -> 3.4502793 | CN24: =100*(Data!CL47/Data!$CP47) -> 3.4502793 | CO24: 3 | CQ24: 2020 | CR24: =100*(Data!BQ47/Data!$BW47) -> -11.636861 | CS24: =100*(Data!CJ47/Data!$CP47) -> -11.636861 | CT24: 0 | CV24: 2020 | CW24: =CR24-DA24 -> -7.9484299 | CX24: =CS24-DB24 -> -7.9484299 | CY24: 0 | DA24: =Data!CF47 -> -3.688431 | DB24: =Data!CY47 -> -3.688431 | DD24: 2020 | DE24: =100*(Data!BO47/Data!BO$46) -> 88.391176 | DF24: =100*(Data!CH47/Data!CH$46) -> 88.391176 | DG24: =100*(Data!DA47/Data!DA$46) -> 88.391176 | DI24: =I24 -> 91.648567 | DJ24: =J24 -> 91.648567 | DK24: =100*(Data!DH47-$R24)/Data!DI47 -> 91.648567 | DM24: =CW24 -> -7.9484299 | DN24: =CX24 -> -7.9484299 | DO24: =(100*(Data!DC47/Data!$DI47))-Data!$DR47 -> -7.9484299 | DS24: 2027-28 | DU24: =100*(EJ24/EJ$20) -> 101.52705 | DV24: =100*(EK24/EK$20) -> 101.57445 | DW24: =100*(EL24/EL$20) -> 101.26976 | DX24: =100*(EM24/EM$20) -> 101.50633 | DY24: 100 | EB24: =100*(EP24/EP$20) -> 95.874906 | EC24: =100*(EQ24/EQ$20) -> 117.93586 | ED24: =100*(ER24/ER$20) -> 93.440712 | EE24: =100*(ES24/ES$20) -> 94.874097 | EF24: 100 | EH24: 2027-28 | EJ24: 6075.8416 | EK24: 6122.3009 | EL24: 5936.4146 | EM24: 6259.1505 | EP24: 1291.1977 | EQ24: 1302.422 | ER24: 1232.8706 | ES24: 1322.1197 | EU24: 2020 | EV24: =100*((EZ24-FA24)/Data!BX47*Data!BY47*0.01) -> -13.131139 | EW24: =100*((FC24-FD24)/Data!CQ47*Data!CR47*0.01) -> -13.131139 | EX24: 0 | EZ24: =Data!BU47*(Data!BX47*Data!BY47*0.01/Data!BW47)^1 -> 833756.38 | FA24: =(Data!BR47+Data!BT47)*(Data!BX47*Data!BY47*0.01/Data!BW47)^1 -> 1089262.3 | FC24: =Data!CN47*(Data!CQ47*Data!CR47*0.01/Data!CP47)^1 -> 833756.38 | FD24: =(Data!CK47+Data!CM47)*(Data!CQ47*Data!CR47*0.01/Data!CP47)^1 -> 1089262.3
A25: 2021 | B25: =100*(Data!BO48/Data!BO$46) -> 100.44781 | C25: =100*(Data!CH48/Data!CH$46) -> 100.44781 | D25: 100 | F25: =100*((C25/B25)-1) -> 0 | H25: 2021 | I25: =100*(O25/Data!$BW48) -> 86.816321 | J25: =100*(P25/Data!$CP48) -> 86.816321 | O25: =Data!BV48-$R25 -> 2044000 | P25: =Data!CO48-$R25 -> 2044000 | R25: ='GNDBTX ex BoE'!D141 -> 337100 | CL25: 2021 | CM25: =100*(Data!BS48/Data!$BW48) -> 2.309637 | CN25: =100*(Data!CL48/Data!$CP48) -> 2.309637 | CO25: 3 | CQ25: 2021 | CR25: =100*(Data!BQ48/Data!$BW48) -> -3.0537344 | CS25: =100*(Data!CJ48/Data!$CP48) -> -3.0537344 | CT25: 0 | CV25: 2021 | CW25: =CR25-DA25 -> -4.3287974 | CX25: =CS25-DB25 -> -4.3287974 | CY25: 0 | DA25: =Data!CF48 -> 1.275063 | DB25: =Data!CY48 -> 1.275063 | DD25: 2021 | DE25: =100*(Data!BO48/Data!BO$46) -> 100.44781 | DF25: =100*(Data!CH48/Data!CH$46) -> 100.44781 | DG25: =100*(Data!DA48/Data!DA$46) -> 100.44781 | DI25: =I25 -> 86.816321 | DJ25: =J25 -> 86.816321 | DK25: =100*(Data!DH48-$R25)/Data!DI48 -> 86.816321 | DM25: =CW25 -> -4.3287974 | DN25: =CX25 -> -4.3287974 | DO25: =(100*(Data!DC48/Data!$DI48))-Data!$DR48 -> -4.3287974 | DS25: 2028-29 | DW25: =100*(EL25/EL$20) -> 101.97258 | DX25: =100*(EM25/EM$20) -> 101.96151 | DY25: 100 | ED25: =100*(ER25/ER$20) -> 91.198538 | EE25: =100*(ES25/ES$20) -> 91.6701 | EF25: 100 | EH25: 2028-29 | EL25: 5977.6135 | EM25: 6287.2179 | ER25: 1203.287 | ES25: 1277.4703 | EU25: 2021 | EV25: =100*((EZ25-FA25)/Data!BX48*Data!BY48*0.01) -> -3.3896315 | EW25: =100*((FC25-FD25)/Data!CQ48*Data!CR48*0.01) -> -3.3896315 | EX25: 0 | EZ25: =Data!BU48*(Data!BX48*Data!BY48*0.01/Data!BW48)^1 -> 913006.06 | FA25: =(Data!BR48+Data!BT48)*(Data!BX48*Data!BY48*0.01/Data!BW48)^1 -> 984352.15 | FC25: =Data!CN48*(Data!CQ48*Data!CR48*0.01/Data!CP48)^1 -> 913006.06 | FD25: =(Data!CK48+Data!CM48)*(Data!CQ48*Data!CR48*0.01/Data!CP48)^1 -> 984352.15
A26: 2022 | B26: =100*(Data!BO49/Data!BO$46) -> 102.17261 | C26: =100*(Data!CH49/Data!CH$46) -> 102.17261 | D26: 100 | F26: =100*((C26/B26)-1) -> 0 | H26: 2022 | I26: =100*(O26/Data!$BW49) -> 86.745747 | J26: =100*(P26/Data!$CP49) -> 86.745747 | O26: =Data!BV49-$R26 -> 2217400 | P26: =Data!CO49-$R26 -> 2217400 | R26: ='GNDBTX ex BoE'!D142 -> 322400 | CL26: 2022 | CM26: =100*(Data!BS49/Data!$BW49) -> 1.7970383 | CN26: =100*(Data!CL49/Data!$CP49) -> 1.7970383 | CO26: 3 | CQ26: 2022 | CR26: =100*(Data!BQ49/Data!$BW49) -> -3.2370631 | CS26: =100*(Data!CJ49/Data!$CP49) -> -3.2370631 | CT26: 0 | CV26: 2022 | CW26: =CR26-DA26 -> -3.616244 | CX26: =CS26-DB26 -> -3.616244 | CY26: 0 | DA26: =Data!CF49 -> 0.3791809 | DB26: =Data!CY49 -> 0.3791809 | DD26: 2022 | DE26: =100*(Data!BO49/Data!BO$46) -> 102.17261 | DF26: =100*(Data!CH49/Data!CH$46) -> 102.17261 | DG26: =100*(Data!DA49/Data!DA$46) -> 102.17261 | DI26: =I26 -> 86.745747 | DJ26: =J26 -> 86.745747 | DK26: =100*(Data!DH49-$R26)/Data!DI49 -> 86.745747 | DM26: =CW26 -> -3.616244 | DN26: =CX26 -> -3.616244 | DO26: =(100*(Data!DC49/Data!$DI49))-Data!$DR49 -> -3.616244 | EU26: 2022 | EV26: =100*((EZ26-FA26)/Data!BX49*Data!BY49*0.01) -> -4.0948579 | EW26: =100*((FC26-FD26)/Data!CQ49*Data!CR49*0.01) -> -4.0948579 | EX26: 0 | EZ26: =Data!BU49*(Data!BX49*Data!BY49*0.01/Data!BW49)^1 -> 1019098.9 | FA26: =(Data!BR49+Data!BT49)*(Data!BX49*Data!BY49*0.01/Data!BW49)^1 -> 1101070.3 | FC26: =Data!CN49*(Data!CQ49*Data!CR49*0.01/Data!CP49)^1 -> 1019098.9 | FD26: =(Data!CK49+Data!CM49)*(Data!CQ49*Data!CR49*0.01/Data!CP49)^1 -> 1101070.3
A27: 2023 | B27: =100*(Data!BO50/Data!BO$46) -> 102.18647 | C27: =100*(Data!CH50/Data!CH$46) -> 102.18647 | D27: 100 | F27: =100*((C27/B27)-1) -> 0 | H27: 2023 | I27: =100*(O27/Data!$BW50) -> 88.799638 | J27: =100*(P27/Data!$CP50) -> 88.799638 | O27: =Data!BV50-$R27 -> 2411901.1 | P27: =Data!CO50-$R27 -> 2411901.1 | R27: =R26+'GNDBTX ex BoE'!J143 -> 278170.92 | CL27: 2023 | CM27: =100*(Data!BS50/Data!$BW50) -> 2.4718684 | CN27: =100*(Data!CL50/Data!$CP50) -> 2.4718684 | CO27: 3 | CQ27: 2023 | CR27: =100*(Data!BQ50/Data!$BW50) -> -1.7066138 | CS27: =100*(Data!CJ50/Data!$CP50) -> -1.7066138 | CT27: 0 | CV27: 2023 | CW27: =CR27-DA27 -> -1.7571586 | CX27: =CS27-DB27 -> -1.7571586 | CY27: 0 | DA27: =Data!CF50 -> 0.05054474 | DB27: =Data!CY50 -> 0.05054474 | DD27: 2023 | DE27: =100*(Data!BO50/Data!BO$46) -> 102.18647 | DF27: =100*(Data!CH50/Data!CH$46) -> 102.18647 | DG27: =100*(Data!DA50/Data!DA$46) -> 102.18647 | DI27: =I27 -> 88.799638 | DJ27: =J27 -> 88.799638 | DK27: =100*(Data!DH50-$R27)/Data!DI50 -> 88.799638 | DM27: =CW27 -> -1.7571586 | DN27: =CX27 -> -1.7571586 | DO27: =(100*(Data!DC50/Data!$DI50))-Data!$DR50 -> -1.7571586 | EU27: 2023 | EV27: =100*((EZ27-FA27)/Data!BX50*Data!BY50*0.01) -> -2.4368695 | EW27: =100*((FC27-FD27)/Data!CQ50*Data!CR50*0.01) -> -2.4368695 | EX27: 0 | EZ27: =Data!BU50*(Data!BX50*Data!BY50*0.01/Data!BW50)^1 -> 1098776.8 | FA27: =(Data!BR50+Data!BT50)*(Data!BX50*Data!BY50*0.01/Data!BW50)^1 -> 1144961.7 | FC27: =Data!CN50*(Data!CQ50*Data!CR50*0.01/Data!CP50)^1 -> 1098776.8 | FD27: =(Data!CK50+Data!CM50)*(Data!CQ50*Data!CR50*0.01/Data!CP50)^1 -> 1144961.7
A28: 2024 | B28: =100*(Data!BO51/Data!BO$46) -> 103.21198 | C28: =100*(Data!CH51/Data!CH$46) -> 103.21199 | D28: 100 | F28: =100*((C28/B28)-1) -> 4.3557354e-06 | H28: 2024 | I28: =100*(O28/Data!$BW51) -> 91.652723 | J28: =100*(P28/Data!$CP51) -> 91.65271 | L28: =I28-I27 -> 2.8530856 | M28: =J28-J27 -> 2.8530725 | O28: =Data!BV51-$R28 -> 2559911.6 | P28: =Data!CO51-$R28 -> 2559911.6 | R28: =R27+'GNDBTX ex BoE'!J144 -> 234882.39 | S28: {=TRANSPOSE(OBR_MAR24_ST6.6!O10:W10)*1000} -> -19049.878 | CL28: 2024 | CM28: =100*(Data!BS51/Data!$BW51) -> 2.3832862 | CN28: =100*(Data!CL51/Data!$CP51) -> 2.3832844 | CO28: 3 | CQ28: 2024 | CR28: =100*(Data!BQ51/Data!$BW51) -> -0.82800669 | CS28: =100*(Data!CJ51/Data!$CP51) -> -0.82800464 | CT28: 0 | CV28: 2024 | CW28: =CR28-DA28 -> -0.7544784 | CX28: =CS28-DB28 -> -0.75447635 | CY28: 0 | DA28: =Data!CF51 -> -0.07352829 | DB28: =Data!CY51 -> -0.07352829 | DD28: 2024 | DE28: =100*(Data!BO51/Data!BO$46) -> 103.21198 | DF28: =100*(Data!CH51/Data!CH$46) -> 103.21199 | DG28: =100*(Data!DA51/Data!DA$46) -> 103.21197 | DI28: =I28 -> 91.652723 | DJ28: =J28 -> 91.65271 | DK28: =100*(Data!DH51-$R28)/Data!DI51 -> 91.65273 | DM28: =CW28 -> -0.7544784 | DN28: =CX28 -> -0.75447635 | DO28: =(100*(Data!DC51/Data!$DI51))-Data!$DR51 -> -0.75447978 | EU28: 2024 | EV28: =100*((EZ28-FA28)/Data!BX51*Data!BY51*0.01) -> -1.2254448 | EW28: =100*((FC28-FD28)/Data!CQ51*Data!CR51*0.01) -> -1.2254394 | EX28: 0 | EZ28: =Data!BU51*(Data!BX51*Data!BY51*0.01/Data!BW51)^1 -> 1148242.4 | FA28: =(Data!BR51+Data!BT51)*(Data!BX51*Data!BY51*0.01/Data!BW51)^1 -> 1171389.6 | FC28: =Data!CN51*(Data!CQ51*Data!CR51*0.01/Data!CP51)^1 -> 1148242.3 | FD28: =(Data!CK51+Data!CM51)*(Data!CQ51*Data!CR51*0.01/Data!CP51)^1 -> 1171389.4
A29: 2025 | B29: =100*(Data!BO52/Data!BO$46) -> 105.40033 | C29: =100*(Data!CH52/Data!CH$46) -> 105.71734 | D29: 100 | F29: =100*((C29/B29)-1) -> 0.30075912 | H29: 2025 | I29: =100*(O29/Data!$BW52) -> 92.195191 | J29: =100*(P29/Data!$CP52) -> 91.564639 | L29: =I29-I28 -> 0.54246768 | M29: =J29-J28 -> -0.088071709 | O29: =Data!BV52-$R29 -> 2677756.8 | P29: =Data!CO52-$R29 -> 2673288.8 | R29: =R28+'GNDBTX ex BoE'!J145 -> 139677.23 | S29: -9152.3991 | CL29: 2025 | CM29: =100*(Data!BS52/Data!$BW52) -> 2.0985208 | CN29: =100*(Data!CL52/Data!$CP52) -> 2.2915636 | CO29: 3 | CQ29: 2025 | CR29: =100*(Data!BQ52/Data!$BW52) -> -0.41490957 | CS29: =100*(Data!CJ52/Data!$CP52) -> -0.055874496 | CT29: 0 | CV29: 2025 | CW29: =CR29-DA29 -> -0.53373737 | CX29: =CS29-DB29 -> -0.333203 | CY29: 0 | DA29: =Data!CF52 -> 0.1188278 | DB29: =Data!CY52 -> 0.2773285 | DD29: 2025 | DE29: =100*(Data!BO52/Data!BO$46) -> 105.40033 | DF29: =100*(Data!CH52/Data!CH$46) -> 105.71734 | DG29: =100*(Data!DA52/Data!DA$46) -> 105.77883 | DI29: =I29 -> 92.195191 | DJ29: =J29 -> 91.564639 | DK29: =100*(Data!DH52-$R29)/Data!DI52 -> 91.545091 | DM29: =CW29 -> -0.53373737 | DN29: =CX29 -> -0.333203 | DO29: =(100*(Data!DC52/Data!$DI52))-Data!$DR52 -> -0.11836514 | EU29: 2025 | EV29: =100*((EZ29-FA29)/Data!BX52*Data!BY52*0.01) -> -0.63672173 | EW29: =100*((FC29-FD29)/Data!CQ52*Data!CR52*0.01) -> -0.086122791 | EX29: 0 | EZ29: =Data!BU52*(Data!BX52*Data!BY52*0.01/Data!BW52)^1 -> 1190287.8 | FA29: =(Data!BR52+Data!BT52)*(Data!BX52*Data!BY52*0.01/Data!BW52)^1 -> 1202329 | FC29: =Data!CN52*(Data!CQ52*Data!CR52*0.01/Data!CP52)^1 -> 1201769.8 | FD29: =(Data!CK52+Data!CM52)*(Data!CQ52*Data!CR52*0.01/Data!CP52)^1 -> 1203395.3
A30: 2026 | B30: =100*(Data!BO53/Data!BO$46) -> 107.33501 | C30: =100*(Data!CH53/Data!CH$46) -> 107.39147 | D30: 100 | F30: =100*((C30/B30)-1) -> 0.052602364 | H30: 2026 | I30: =100*(O30/Data!$BW53) -> 91.94825 | J30: =100*(P30/Data!$CP53) -> 91.405074 | L30: =I30-I29 -> -0.24694087 | M30: =J30-J29 -> -0.15956483 | O30: =Data!BV53-$R30 -> 2778532.9 | P30: =Data!CO53-$R30 -> 2771172.9 | R30: =R29+'GNDBTX ex BoE'!J146 -> 104997.13 | S30: -15970.596 | CL30: 2026 | CM30: =100*(Data!BS53/Data!$BW53) -> 1.9562405 | CN30: =100*(Data!CL53/Data!$CP53) -> 2.1493286 | CO30: 3 | CQ30: 2026 | CR30: =100*(Data!BQ53/Data!$BW53) -> 0.23527603 | CS30: =100*(Data!CJ53/Data!$CP53) -> 0.52935261 | CT30: 0 | CV30: 2026 | CW30: =CR30-DA30 -> 0.2389 | CX30: =CS30-DB30 -> 0.59124607 | CY30: 0 | DA30: =Data!CF53 -> -0.003623962 | DB30: =Data!CY53 -> -0.06189346 | DD30: 2026 | DE30: =100*(Data!BO53/Data!BO$46) -> 107.33501 | DF30: =100*(Data!CH53/Data!CH$46) -> 107.39147 | DG30: =100*(Data!DA53/Data!DA$46) -> 107.65917 | DI30: =I30 -> 91.94825 | DJ30: =J30 -> 91.405074 | DK30: =100*(Data!DH53-$R30)/Data!DI53 -> 91.160225 | DM30: =CW30 -> 0.2389 | DN30: =CX30 -> 0.59124607 | DO30: =(100*(Data!DC53/Data!$DI53))-Data!$DR53 -> 0.97334051 | EU30: 2026 | EV30: =100*((EZ30-FA30)/Data!BX53*Data!BY53*0.01) -> 0.37687953 | EW30: =100*((FC30-FD30)/Data!CQ53*Data!CR53*0.01) -> 0.85260264 | EX30: 0 | EZ30: =Data!BU53*(Data!BX53*Data!BY53*0.01/Data!BW53)^1 -> 1242427.2 | FA30: =(Data!BR53+Data!BT53)*(Data!BX53*Data!BY53*0.01/Data!BW53)^1 -> 1235320.2 | FC30: =Data!CN53*(Data!CQ53*Data!CR53*0.01/Data!CP53)^1 -> 1256846 | FD30: =(Data!CK53+Data!CM53)*(Data!CQ53*Data!CR53*0.01/Data!CP53)^1 -> 1240797.9
A31: 2027 | B31: =100*(Data!BO54/Data!BO$46) -> 109.07912 | C31: =100*(Data!CH54/Data!CH$46) -> 109.36994 | D31: 100 | F31: =100*((C31/B31)-1) -> 0.26661657 | H31: 2027 | I31: =100*(O31/Data!$BW54) -> 91.322221 | J31: =100*(P31/Data!$CP54) -> 90.839101 | L31: =I31-I30 -> -0.62602943 | M31: =J31-J30 -> -0.56597234 | O31: =Data!BV54-$R31 -> 2864232.2 | P31: =Data!CO54-$R31 -> 2862738.2 | R31: =R30+'GNDBTX ex BoE'!J147 -> 93382.767 | S31: -17644.314 | CL31: 2027 | CM31: =100*(Data!BS54/Data!$BW54) -> 1.7961152 | CN31: =100*(Data!CL54/Data!$CP54) -> 2.2083126 | CO31: 3 | CQ31: 2027 | CR31: =100*(Data!BQ54/Data!$BW54) -> 0.76086301 | CS31: =100*(Data!CJ54/Data!$CP54) -> 0.99193908 | CT31: 0 | CV31: 2027 | CW31: =CR31-DA31 -> 0.78565854 | CX31: =CS31-DB31 -> 0.87559078 | CY31: 0 | DA31: =Data!CF54 -> -0.02479553 | DB31: =Data!CY54 -> 0.1163483 | DD31: 2027 | DE31: =100*(Data!BO54/Data!BO$46) -> 109.07912 | DF31: =100*(Data!CH54/Data!CH$46) -> 109.36994 | DG31: =100*(Data!DA54/Data!DA$46) -> 109.90996 | DI31: =I31 -> 91.322221 | DJ31: =J31 -> 90.839101 | DK31: =100*(Data!DH54-$R31)/Data!DI54 -> 90.193377 | DM31: =CW31 -> 0.78565854 | DN31: =CX31 -> 0.87559078 | DO31: =(100*(Data!DC54/Data!$DI54))-Data!$DR54 -> 1.4281759 | EU31: 2027 | EV31: =100*((EZ31-FA31)/Data!BX54*Data!BY54*0.01) -> 1.2712935 | EW31: =100*((FC31-FD31)/Data!CQ54*Data!CR54*0.01) -> 1.6644306 | EX31: 0 | EZ31: =Data!BU54*(Data!BX54*Data!BY54*0.01/Data!BW54)^1 -> 1295128.6 | FA31: =(Data!BR54+Data!BT54)*(Data!BX54*Data!BY54*0.01/Data!BW54)^1 -> 1271260.9 | FC31: =Data!CN54*(Data!CQ54*Data!CR54*0.01/Data!CP54)^1 -> 1308484.9 | FD31: =(Data!CK54+Data!CM54)*(Data!CQ54*Data!CR54*0.01/Data!CP54)^1 -> 1277228.7
A32: 2028 | B32: =100*(Data!BO55/Data!BO$46) -> 110.82129 | C32: =100*(Data!CH55/Data!CH$46) -> 112.08807 | D32: 100 | F32: =100*((C32/B32)-1) -> 1.1430851 | H32: 2028 | I32: =100*(O32/Data!$BW55) -> 90.492805 | J32: =100*(P32/Data!$CP55) -> 89.7675 | L32: =I32-I31 -> -0.82941531 | M32: =J32-J31 -> -1.0716011 | O32: =Data!BV55-$R32 -> 2942563.2 | P32: =Data!CO55-$R32 -> 2961905.2 | R32: =R31+'GNDBTX ex BoE'!J148 -> 79550.758 | S32: -20408.856 | CL32: 2028 | CM32: =100*(Data!BS55/Data!$BW55) -> 1.6317106 | CN32: =100*(Data!CL55/Data!$CP55) -> 2.582599 | CO32: 3 | CQ32: 2028 | CR32: =100*(Data!BQ55/Data!$BW55) -> 0.99337997 | CS32: =100*(Data!CJ55/Data!$CP55) -> 1.3220974 | CT32: 0 | CV32: 2028 | CW32: =CR32-DA32 -> 1.0489792 | CX32: =CS32-DB32 -> 0.7627674 | CY32: 0 | DA32: =Data!CF55 -> -0.05559921 | DB32: =Data!CY55 -> 0.55933 | DD32: 2028 | DE32: =100*(Data!BO55/Data!BO$46) -> 110.82129 | DF32: =100*(Data!CH55/Data!CH$46) -> 112.08807 | DG32: =100*(Data!DA55/Data!DA$46) -> 112.96211 | DI32: =I32 -> 90.492805 | DJ32: =J32 -> 89.7675 | DK32: =100*(Data!DH55-$R32)/Data!DI55 -> 88.637895 | DM32: =CW32 -> 1.0489792 | DN32: =CX32 -> 0.7627674 | DO32: =(100*(Data!DC55/Data!$DI55))-Data!$DR55 -> 1.4577138 | EU32: 2028 | EV32: =100*((EZ32-FA32)/Data!BX55*Data!BY55*0.01) -> 1.7284442 | EW32: =100*((FC32-FD32)/Data!CQ55*Data!CR55*0.01) -> 2.3153099 | EX32: 0 | EZ32: =Data!BU55*(Data!BX55*Data!BY55*0.01/Data!BW55)^1 -> 1345952.8 | FA32: =(Data!BR55+Data!BT55)*(Data!BX55*Data!BY55*0.01/Data!BW55)^1 -> 1313638.9 | FC32: =Data!CN55*(Data!CQ55*Data!CR55*0.01/Data!CP55)^1 -> 1358716.4 | FD32: =(Data!CK55+Data!CM55)*(Data!CQ55*Data!CR55*0.01/Data!CP55)^1 -> 1315389.8
A33: 2029 | B33: =100*(Data!BO56/Data!BO$46) -> 112.52648 | C33: =100*(Data!CH56/Data!CH$46) -> 113.3837 | D33: 100 | F33: =100*((C33/B33)-1) -> 0.76179386 | H33: 2029 | I33: =100*(O33/Data!$BW56) -> 88.546782 | J33: =100*(P33/Data!$CP56) -> 88.673455 | L33: =I33-I32 -> -1.9460235 | M33: =J33-J32 -> -1.0940455 | O33: =Data!BV56-$R33 -> 2983991.9 | P33: =Data!CO56-$R33 -> 3023337.9 | R33: =R32+($R$36-$R$32)*1/4 -> 59663.068 | S33: -18108.531 | CL33: 2029 | CM33: =100*(Data!BS56/Data!$BW56) -> 1.6315884 | CN33: =100*(Data!CL56/Data!$CP56) -> 2.5028214 | CO33: 3 | CQ33: 2029 | CR33: =100*(Data!BQ56/Data!$BW56) -> 0.99236816 | CS33: =100*(Data!CJ56/Data!$CP56) -> 1.2843339 | CT33: 0 | CV33: 2029 | CW33: =CR33-DA33 -> 1.0284171 | CX33: =CS33-DB33 -> 1.4580934 | CY33: 0 | DA33: =Data!CF56 -> -0.03604889 | DB33: =Data!CY56 -> -0.1737595 | DD33: 2029 | DE33: =100*(Data!BO56/Data!BO$46) -> 112.52648 | DF33: =100*(Data!CH56/Data!CH$46) -> 113.3837 | DG33: =100*(Data!DA56/Data!DA$46) -> 114.63759 | DI33: =I33 -> 88.546782 | DJ33: =J33 -> 88.673455 | DK33: =100*(Data!DH56-$R33)/Data!DI56 -> 86.905736 | DM33: =CW33 -> 1.0284171 | DN33: =CX33 -> 1.4580934 | DO33: =(100*(Data!DC56/Data!$DI56))-Data!$DR56 -> 2.3166077 | EU33: 2029 | EV33: =100*((EZ33-FA33)/Data!BX56*Data!BY56*0.01) -> 1.798765 | EW33: =100*((FC33-FD33)/Data!CQ56*Data!CR56*0.01) -> 2.3470958 | EX33: 0 | EZ33: =Data!BU56*(Data!BX56*Data!BY56*0.01/Data!BW56)^1 -> 1394991.7 | FA33: =(Data!BR56+Data!BT56)*(Data!BX56*Data!BY56*0.01/Data!BW56)^1 -> 1361534.9 | FC33: =Data!CN56*(Data!CQ56*Data!CR56*0.01/Data!CP56)^1 -> 1418415.6 | FD33: =(Data!CK56+Data!CM56)*(Data!CQ56*Data!CR56*0.01/Data!CP56)^1 -> 1374629.8
A34: 2030 | B34: =100*(Data!BO57/Data!BO$46) -> 114.25522 | C34: =100*(Data!CH57/Data!CH$46) -> 115.23642 | D34: 100 | F34: =100*((C34/B34)-1) -> 0.85877569 | H34: 2030 | I34: =100*(O34/Data!$BW57) -> 86.490421 | J34: =100*(P34/Data!$CP57) -> 87.254761 | L34: =I34-I33 -> -2.0563611 | M34: =J34-J33 -> -1.4186936 | O34: =Data!BV57-$R34 -> 3023054.6 | P34: =Data!CO57-$R34 -> 3087505.6 | R34: =R33+($R$36-$R$32)*1/4 -> 39775.379 | S34: -20731.681 | CL34: 2030 | CM34: =100*(Data!BS57/Data!$BW57) -> 1.6314568 | CN34: =100*(Data!CL57/Data!$CP57) -> 2.5548224 | CO34: 3 | CQ34: 2030 | CR34: =100*(Data!BQ57/Data!$BW57) -> 1.0828752 | CS34: =100*(Data!CJ57/Data!$CP57) -> 1.3034306 | CT34: 0 | CV34: 2030 | CW34: =CR34-DA34 -> 1.092698 | CX34: =CS34-DB34 -> 1.3593159 | CY34: 0 | DA34: =Data!CF57 -> -0.009822845 | DB34: =Data!CY57 -> -0.05588531 | DD34: 2030 | DE34: =100*(Data!BO57/Data!BO$46) -> 114.25522 | DF34: =100*(Data!CH57/Data!CH$46) -> 115.23642 | DG34: =100*(Data!DA57/Data!DA$46) -> 116.87633 | DI34: =I34 -> 86.490421 | DJ34: =J34 -> 87.254761 | DK34: =100*(Data!DH57-$R34)/Data!DI57 -> 84.740354 | DM34: =CW34 -> 1.092698 | DN34: =CX34 -> 1.3593159 | DO34: =(100*(Data!DC57/Data!$DI57))-Data!$DR57 -> 2.39638 | EU34: 2030 | EV34: =100*((EZ34-FA34)/Data!BX57*Data!BY57*0.01) -> 2.0480716 | EW34: =100*((FC34-FD34)/Data!CQ57*Data!CR57*0.01) -> 2.4837315 | EX34: 0 | EZ34: =Data!BU57*(Data!BX57*Data!BY57*0.01/Data!BW57)^1 -> 1446454.2 | FA34: =(Data!BR57+Data!BT57)*(Data!BX57*Data!BY57*0.01/Data!BW57)^1 -> 1408599.2 | FC34: =Data!CN57*(Data!CQ57*Data!CR57*0.01/Data!CP57)^1 -> 1472089.2 | FD34: =(Data!CK57+Data!CM57)*(Data!CQ57*Data!CR57*0.01/Data!CP57)^1 -> 1425929.2
A35: 2031 | B35: =100*(Data!BO58/Data!BO$46) -> 116.00029 | C35: =100*(Data!CH58/Data!CH$46) -> 117.28271 | D35: 100 | F35: =100*((C35/B35)-1) -> 1.1055373 | H35: 2031 | I35: =100*(O35/Data!$BW58) -> 84.491544 | J35: =100*(P35/Data!$CP58) -> 85.258537 | L35: =I35-I34 -> -1.998877 | M35: =J35-J34 -> -1.9962241 | O35: =Data!BV58-$R35 -> 3063287.3 | P35: =Data!CO58-$R35 -> 3139624.3 | R35: =R34+($R$36-$R$32)*1/4 -> 19887.689 | S35: -18383.694 | CL35: 2031 | CM35: =100*(Data!BS58/Data!$BW58) -> 1.6314689 | CN35: =100*(Data!CL58/Data!$CP58) -> 2.2989481 | CO35: 3 | CQ35: 2031 | CR35: =100*(Data!BQ58/Data!$BW58) -> 1.0702965 | CS35: =100*(Data!CJ58/Data!$CP58) -> 1.4237171 | CT35: 0 | CV35: 2031 | CW35: =CR35-DA35 -> 1.0790703 | CX35: =CS35-DB35 -> 1.4162785 | CY35: 0 | DA35: =Data!CF58 -> -0.008773804 | DB35: =Data!CY58 -> 0.00743866 | DD35: 2031 | DE35: =100*(Data!BO58/Data!BO$46) -> 116.00029 | DF35: =100*(Data!CH58/Data!CH$46) -> 117.28271 | DG35: =100*(Data!DA58/Data!DA$46) -> 119.32975 | DI35: =I35 -> 84.491544 | DJ35: =J35 -> 85.258537 | DK35: =100*(Data!DH58-$R35)/Data!DI58 -> 81.938968 | DM35: =CW35 -> 1.0790703 | DN35: =CX35 -> 1.4162785 | DO35: =(100*(Data!DC58/Data!$DI58))-Data!$DR58 -> 2.6207657 | EU35: 2031 | EV35: =100*((EZ35-FA35)/Data!BX58*Data!BY58*0.01) -> 2.1129801 | EW35: =100*((FC35-FD35)/Data!CQ58*Data!CR58*0.01) -> 2.8365728 | EX35: 0 | EZ35: =Data!BU58*(Data!BX58*Data!BY58*0.01/Data!BW58)^1 -> 1500389 | FA35: =(Data!BR58+Data!BT58)*(Data!BX58*Data!BY58*0.01/Data!BW58)^1 -> 1461582.7 | FC35: =Data!CN58*(Data!CQ58*Data!CR58*0.01/Data!CP58)^1 -> 1532044 | FD35: =(Data!CK58+Data!CM58)*(Data!CQ58*Data!CR58*0.01/Data!CP58)^1 -> 1479611.5
A36: 2032 | B36: =100*(Data!BO59/Data!BO$46) -> 117.74414 | C36: =100*(Data!CH59/Data!CH$46) -> 119.04614 | D36: 100 | F36: =100*((C36/B36)-1) -> 1.1057879 | H36: 2032 | I36: =100*(O36/Data!$BW59) -> 82.572466 | J36: =100*(P36/Data!$CP59) -> 83.390561 | L36: =I36-I35 -> -1.9190776 | M36: =J36-J35 -> -1.8679764 | O36: =Data!BV59-$R36 -> 3104759 | P36: =Data!CO59-$R36 -> 3186612 | R36: 0 | S36: -594.46007 | CL36: 2032 | CM36: =100*(Data!BS59/Data!$BW59) -> 1.6314118 | CN36: =100*(Data!CL59/Data!$CP59) -> 2.1349301 | CO36: 3 | CQ36: 2032 | CR36: =100*(Data!BQ59/Data!$BW59) -> 1.0573801 | CS36: =100*(Data!CJ59/Data!$CP59) -> 1.4257396 | CT36: 0 | CV36: 2032 | CW36: =CR36-DA36 -> 1.0618624 | CX36: =CS36-DB36 -> 1.5332187 | CY36: 0 | DA36: =Data!CF59 -> -0.004482269 | DB36: =Data!CY59 -> -0.1074791 | DD36: 2032 | DE36: =100*(Data!BO59/Data!BO$46) -> 117.74414 | DF36: =100*(Data!CH59/Data!CH$46) -> 119.04614 | DG36: =100*(Data!DA59/Data!DA$46) -> 121.52504 | DI36: =I36 -> 82.572466 | DJ36: =J36 -> 83.390561 | DK36: =100*(Data!DH59-$R36)/Data!DI59 -> 79.183811 | DM36: =CW36 -> 1.0618624 | DN36: =CX36 -> 1.5332187 | DO36: =(100*(Data!DC59/Data!$DI59))-Data!$DR59 -> 2.910705 | EU36: 2032 | EV36: =100*((EZ36-FA36)/Data!BX59*Data!BY59*0.01) -> 2.179218 | EW36: =100*((FC36-FD36)/Data!CQ59*Data!CR59*0.01) -> 2.9689091 | EX36: 0 | EZ36: =Data!BU59*(Data!BX59*Data!BY59*0.01/Data!BW59)^1 -> 1556124.4 | FA36: =(Data!BR59+Data!BT59)*(Data!BX59*Data!BY59*0.01/Data!BW59)^1 -> 1516365.8 | FC36: =Data!CN59*(Data!CQ59*Data!CR59*0.01/Data!CP59)^1 -> 1593107.2 | FD36: =(Data!CK59+Data!CM59)*(Data!CQ59*Data!CR59*0.01/Data!CP59)^1 -> 1538564
A38: 2023-2032 | B38: =100*((Data!BO59/Data!BO49)^(1/10)-1) -> 1.4286121 | C38: =100*((Data!CH59/Data!CH49)^(1/10)-1) -> 1.5402164 | DD38: 2023-2032 | DE38: =100*((DE36/DE26)^(1/10)-1) -> 1.4286121 | DF38: =100*((DF36/DF26)^(1/10)-1) -> 1.5402164 | DG38: =100*((DG36/DG26)^(1/10)-1) -> 1.7496979 | DI38: =DI36-DI26 -> -4.1732811 | DJ38: =DJ36-DJ26 -> -3.3551868 | DK38: =DK36-DK26 -> -7.5619366 | DM38: =AVERAGE(DM27:DM36) -> 0.32902111 | DN38: =AVERAGE(DN27:DN36) -> 0.51516728 | DO38: =AVERAGE(DO27:DO36) -> 1.1473685

Sheet OBR_MAR24_ST6.6
A1: Back to contents
B2: 6.6 Lifetime cost of the Asset Puchase Facility
C3: £ billion
C4: Outturn | N4: Forecast
C5: 2012-13 | D5: 2013-14 | E5: 2014-15 | F5: 2015-16 | G5: 2016-17 | H5: 2017-18 | I5: 2018-19 | J5: 2019-20 | K5: 2020-21 | L5: 2021-22 | M5: 2022-23 | N5: 2023-24 | O5: 2024-25 | P5: 2025-26 | Q5: 2026-27 | R5: 2027-28 | S5: 2028-29 | T5: 2029-30 | U5: 2030-31 | V5: 2031-32 | W5: 2032-33
B6: Cash transfers from BoE to HM Treasury | C6: 11.271 | D6: 31.102 | E6: 10.739 | F6: 8.529 | G6: 10.316 | H6: 10.028 | I6: 9.686 | J6: 7.137 | K6: 13.663 | L6: 7.218 | M6: 4.164
B7: Cash transfers from HM Treasury to BoE | C7: 0 | D7: 0 | E7: 0 | F7: 0 | G7: 0 | H7: 0 | I7: 0 | J7: 0 | K7: 0 | L7: 0 | M7: -5.01 | N7: -44.23055 | O7: -34.548515 | P7: -17.225492 | Q7: -20.982494 | R7: -21.179047 | S7: -23.105014 | T7: -20.414836 | U7: -21.847455 | V7: -18.890357 | W7: -0.56619975
B8: of which:
B9: APF interest losses | O9: -15.498637 | P9: -8.0730926 | Q9: -5.0118975 | R9: -3.5347326 | S9: -2.696158 | T9: -2.3063046 | U9: -1.1157742 | V9: -0.50666314 | W9: 0.028260315
B10: APF valuation losses | O10: -19.049878 | P10: -9.1523991 | Q10: -15.970596 | R10: -17.644314 | S10: -20.408856 | T10: -18.108531 | U10: -20.731681 | V10: -18.383694 | W10: -0.59446007
B11: The ONS has not published a breakdown of valuation losses made by the APF, so we cannot fully decompose the transfers between the APF and Treasury which have occurred to date. Our forecast splits out future interest and valuation losses.

Sheet OBR_MAR24_ST6.11
A1: Back to contents
B2: 6.11 Public sector net debt: changes since November 2023
C3: £ billion
C4: Outturn | D4: Forecast
C5: 2022-23 | D5: 2023-24 | E5: 2024-25 | F5: 2025-26 | G5: 2026-27 | H5: 2027-28 | I5: 2028-29
B6: November 2023 forecast | C6: 95.789462 | D6: 97.869671 | E6: 98.626745 | F6: 96.281813 | G6: 95.509908 | H6: 95.000759 | I6: 94.105503
B7: March 2024 forecast | C7: 95.726818 | D7: 97.589333 | E7: 98.777579 | F7: 96.357307 | G7: 95.479822 | H7: 95.061625 | I7: 94.29872
B8: Difference | C8: -0.062644438 | D8: -0.28033877 | E8: 0.15083448 | F8: 0.075494151 | G8: -0.03008655 | H8: 0.060865992 | I8: 0.193217
B9: of which:
B10: Difference in nominal GDP1 | D10: 0.13647466 | E10: 0.47358113 | F10: 0.36883822 | G10: 0.32428083 | H10: 0.33949803 | I10: 0.29462178
B11: Difference in cash level of net debt | D11: -0.41681343 | E11: -0.32274664 | F11: -0.29334406 | G11: -0.35436738 | H11: -0.27863204 | I11: -0.10140478
B12: Memo: PSND excluding Bank of England | C12: 84.875668 | D12: 88.751485 | E12: 91.690627 | F12: 92.763531 | G12: 93.161002 | H12: 93.192662 | I12: 92.918595
C13: £ billion | D13: 0 | E13: 0 | F13: 0 | G13: 0 | H13: 0
B14: November 2023 forecast | C14: 2538.439 | D14: 2702.1566 | E14: 2802.0451 | F14: 2828.626 | G14: 2913.5665 | H14: 3003.7498 | I14: 3081.4583
B15: March 2024 forecast | C15: 2539.8 | D15: 2690.6645 | E15: 2792.9195 | F15: 2820.0409 | G15: 2902.793 | H15: 2994.9713 | I15: 3078.1482
B16: Difference | C16: 1.361 | D16: -11.492087 | E16: -9.1256072 | F16: -8.5851533 | G16: -10.773535 | H16: -8.7784631 | I16: -3.310108
B17: of which:
B18: Underlying PSNB forecast revisions | D18: -10.148123 | E18: -20.160225 | F18: -29.88207 | G18: -36.053362 | H18: -39.66938 | I18: -40.442954
B19: Overall effect of policy measures | D19: 0.35520834 | E19: 13.031566 | F19: 23.527086 | G19: 29.981432 | H19: 35.131992 | I19: 40.386328
B20: Financial transactions and valuation effects | D20: -1.6991718 | E20: -1.9969479 | F20: -2.2301693 | G20: -4.7016047 | H20: -4.2410749 | I20: -3.2534821
B21: Memo: PSND excluding Bank of England | C21: 2251.9 | D21: 2446.9936 | E21: 2592.5371 | F21: 2714.8636 | G21: 2832.2959 | H21: 2936.0885 | I21: 3033.0974
B22: 1 Non-seasonally-adjusted GDP centred end-March.

Sheet OBR_MAR24_TA.7
A1: Back to contents
B2: Table A.7: Total managed expenditure
C4: £ billion
C5: Outturn | D5: Forecast
C6: 2022-23 | D6: 2023-24 | E6: 2024-25 | F6: 2025-26 | G6: 2026-27 | H6: 2027-28 | I6: 2028-29
B7: Public sector current expenditure (PSCE)
B8: PSCE in RDEL | C8: 407.4577 | D8: 422.94449 | E8: 430.19538 | F8: 440.03535 | G8: 452.28089 | H8: 465.55777 | I8: 479.15889
B9: PSCE in AME | C9: 643.6143 | D9: 659.96315 | E9: 660.1941 | F9: 679.56195 | G9: 705.7294 | H9: 725.75804 | I9: 751.95568
B10: of which:
B11: Welfare spending | C11: 261.4874 | D11: 295.84845 | E11: 315.14089 | F11: 329.00886 | G11: 339.72754 | H11: 348.2333 | I11: 360.06887
B12: Locally financed current expenditure | C12: 60.137438 | D12: 62.063371 | E12: 64.070522 | F12: 66.14117 | G12: 69.311315 | H12: 72.175566 | I12: 75.387203
B13: Central government debt interest, net of APF1 | C13: 111.481 | D13: 104.74828 | E13: 88.955775 | F13: 88.888563 | G13: 96.20421 | H13: 103.044 | I13: 109.63575
B14: Scottish Government's current spending | C14: 39.586038 | D14: 42.618447 | E14: 44.427363 | F14: 45.138799 | G14: 46.302917 | H14: 47.157818 | I14: 49.134058
B15: EU financial settlement | C15: 8.8096667 | D15: 7.7514634 | E15: 1.135536 | F15: 1.0637573 | G15: 0.5381457 | H15: 0.18596545 | I15: 0.52161233
B16: Unfunded public service pensions | C16: 3.5806935 | D16: 4.5721668 | E16: 3.4392333 | F16: 4.1530844 | G16: 3.100412 | H16: 2.231031 | I16: 0.64376789
B17: Company and other tax credits | C17: 9.2172361 | D17: 9.3808388 | E17: 9.6580323 | F17: 10.166965 | G17: 10.582 | H17: 10.989011 | I17: 11.355334
B18: BBC current expenditure | C18: 4.2246768 | D18: 4.1788233 | E18: 4.3327533 | F18: 4.1190666 | G18: 4.270332 | H18: 4.355332 | I18: 4.4052235
B19: National Lottery current grants | C19: 1.28536 | D19: 1.2437495 | E19: 1.414753 | F19: 1.4105405 | G19: 1.318127 | H19: 1.2435335 | I19: 1.2428825
B20: General government imputed pensions | C20: 3.3853899 | D20: 1.6987073 | E20: 1.7594719 | F20: 1.8057996 | G20: 1.85605 | H20: 1.9100249 | I20: 1.9688475
B21: Public corporations' debt interest | C21: 0.544 | D21: 0.54 | E21: 0.54 | F21: 0.54 | G21: 0.54 | H21: 0.54 | I21: 0.54
B22: Non-domestic energy support | C22: 7.48 | D22: 0.621 | E22: 0 | F22: 0 | G22: 0 | H22: 0 | I22: 0
... B30: Total public sector current expenditure | C30: 1051.072 | D30: 1082.9076 | E30: 1090.3895 | F30: 1119.5973 | G30: 1158.0103 | H30: 1191.3158 | I30: 1231.1146
B31: Public sector gross investment (PSGI)
B32: PSGI in CDEL | C32: 89.791733 | D32: 95.583786 | E32: 99.20003 | F32: 98.062828 | G32: 98.348124 | H32: 98.339717 | I32: 97.358047
B33: PSGI in AME | C33: 16.548267 | D33: 37.78248 | E33: 36.758702 | F33: 33.997042 | G33: 33.894631 | H33: 33.406167 | I33: 33.203153
B34: of which:
B35: Locally financed capital expenditure | C35: 10.835605 | D35: 8.8351359 | E35: 8.2751924 | F35: 7.5499586 | G35: 8.1494607 | H35: 8.1407231 | I35: 8.2007894
B36: Public corporations' capital expenditure | C36: 11.556757 | D36: 11.199767 | E36: 11.740905 | F36: 11.617591 | G36: 11.610803 | H36: 11.667161 | I36: 11.740328
B37: Student loans | C37: 0.488 | D37: 9.8426785 | E37: 8.9549482 | F37: 8.1280841 | G37: 7.5164923 | H37: 7.2257973 | I37: 7.0930287
B38: Funded public sector pension schemes | C38: -4.854 | D38: 0.71152891 | E38: 0.71152891 | F38: 0.71152891 | G38: 0.71152891 | H38: 0.71152891 | I38: 0.71152891
B39: Scottish Government's capital spending | C39: 4.569481 | D39: 5.6714916 | E39: 5.4709199 | F39: 5.2342224 | G39: 5.2275066 | H39: 5.2113555 | I39: 5.1460268
B40: Tax litigation | C40: 0 | D40: 0.8235 | E40: 1.203396 | F40: 0.63406325 | G40: 0.63406325 | H40: 0.63406325 | I40: 0.63406325
B41: Other PSGI items in AME | C41: 0.38561146 | D41: 1.2091956 | E41: 0.89061083 | F41: 0.81662252 | G41: 0.72455505 | H41: 0.56602273 | I41: 0.52125924
B42: Other National Accounts adjustments | C42: -6.4331875 | D42: -0.5108177 | E42: -0.48879946 | F42: -0.69502831 | G42: -0.6797789 | H42: -0.75048428 | I42: -0.84387143
B43: Total public sector gross investment | C43: 106.34 | D43: 133.36627 | E43: 135.95873 | F43: 132.05987 | G43: 132.24276 | H43: 131.74588 | I43: 130.5612
B44: Less public sector depreciation | C44: -60.341 | D44: -66.227455 | E44: -69.392239 | F44: -71.109614 | G44: -73.128371 | H44: -75.412565 | I44: -77.50292
B45: Public sector net investment | C45: 45.999 | D45: 67.138811 | E45: 66.566493 | F45: 60.950257 | G45: 59.114384 | H45: 56.333319 | I45: 53.05828
B46: Total managed expenditure | C46: 1157.412 | D46: 1216.2739 | E46: 1226.3482 | F46: 1251.6572 | G46: 1290.253 | H46: 1323.0617 | I46: 1361.6758
B47: 1 Includes increases in debt interest payments due to the APF.

Sheet OBR_MAR24_1.1
A1: Back to contents
B2: 1.1 GDP expenditure components (£ billion chain-linked volumes, seasonally adjusted)
C3: Private consumption | D3: Government consumption | E3: Fixed investment | J3: Net acquisition of valuables | K3: Final domestic demand | L3: Change in inventories | M3: Total domestic demand | N3: Exports | O3: Total final expenditure | P3: Imports | Q3: Statistical discrepancy | R3: Real GDP | S3: Non-oil GVA
E4: of which: | F4: Business investment | G4: Private dwellings | H4: General government | I4: Public corps dwellings
B5: 2008Q1 | C5: 308.104 | D5: 93.323 | E5: 84.847 | F5: 45.209 | G5: 24.954 | H5: 13.732 | I5: 1.494 | J5: 0.253 | K5: 486.527 | L5: -2.688 | M5: 483.839 | N5: 140.286 | O5: 626.489 | P5: 137.103 | Q5: 0 | R5: 489.783 | S5: 426.405
B6: 2008Q2 | C6: 304.494 | D6: 92.738 | E6: 85.799 | F6: 46.925 | G6: 23.782 | H6: 14.129 | I6: 1.45 | J6: -0.422 | K6: 482.609 | L6: -1.231 | M6: 481.378 | N6: 140.305 | O6: 623.241 | P6: 136.253 | Q6: 0 | R6: 487.386 | S6: 424.841
B7: 2008Q3 | C7: 299.633 | D7: 94.397 | E7: 81.323 | F7: 45.148 | G7: 19.58 | H7: 14.145 | I7: 2.775 | J7: -0.984 | K7: 474.369 | L7: -3.213 | M7: 471.156 | N7: 140.846 | O7: 613.272 | P7: 133.811 | Q7: 0 | R7: 479.872 | S7: 418.251
B8: 2008Q4 | C8: 292.373 | D8: 95.402 | E8: 79.978 | F8: 43.617 | G8: 18.727 | H8: 15.192 | I8: 2.722 | J8: 0.11 | K8: 467.863 | L8: -5.656 | M8: 462.207 | N8: 135.424 | O8: 596.031 | P8: 126.724 | Q8: 0 | R8: 469.694 | S8: 409.321
B9: 2009Q1 | C9: 291.284 | D9: 94.802 | E9: 75.261 | F9: 39.697 | G9: 17.619 | H9: 15.489 | I9: 2.681 | J9: 1.308 | K9: 462.655 | L9: -9.394 | M9: 453.261 | N9: 126.723 | O9: 581.258 | P9: 121.718 | Q9: 0 | R9: 460.105 | S9: 401.251
B10: 2009Q2 | C10: 291.11 | D10: 94.564 | E10: 72.063 | F10: 37.614 | G10: 17.124 | H10: 14.824 | I10: 2.644 | J10: 0.617 | K10: 458.354 | L10: -8.962 | M10: 449.392 | N10: 125.42 | O10: 580.028 | P10: 122.009 | Q10: 0 | R10: 458.599 | S10: 399.499
B11: 2009Q3 | C11: 292.732 | D11: 95.362 | E11: 72.551 | F11: 36.801 | G11: 17.177 | H11: 16.069 | I11: 2.675 | J11: 1.036 | K11: 461.681 | L11: -9.269 | M11: 452.412 | N11: 124.828 | O11: 583.709 | P11: 125.311 | Q11: 0 | R11: 458.875 | S11: 400.202
B12: 2009Q4 | C12: 294.909 | D12: 96.11 | E12: 71.335 | F12: 36.482 | G12: 16.394 | H12: 15.851 | I12: 2.728 | J12: -0.228 | K12: 462.126 | L12: -7.406 | M12: 454.72 | N12: 130.663 | O12: 587.166 | P12: 127.35 | Q12: 0 | R12: 460.238 | S12: 401.681
B13: 2010Q1 | C13: 293.465 | D13: 94.805 | E13: 75.138 | F13: 38.204 | G13: 17.617 | H13: 16.792 | I13: 2.709 | J13: -0.366 | K13: 463.042 | L13: -2.196 | M13: 460.846 | N13: 130.582 | O13: 593.834 | P13: 129.677 | Q13: 0 | R13: 464.543 | S13: 405.884
B14: 2010Q2 | C14: 300.592 | D14: 95.123 | E14: 74.022 | F14: 37.63 | G14: 18.596 | H14: 15.355 | I14: 2.698 | J14: -0.577 | K14: 469.16 | L14: -1.663 | M14: 467.497 | N14: 134.894 | O14: 603.085 | P14: 133.785 | Q14: 0 | R14: 469.606 | S14: 410.793
B15: 2010Q3 | C15: 300.841 | D15: 95.137 | E15: 76.899 | F15: 39.313 | G15: 19.56 | H15: 15.628 | I15: 2.678 | J15: 0.524 | K15: 473.401 | L15: -0.658 | M15: 472.743 | N15: 136.309 | O15: 610.106 | P15: 138.104 | Q15: 0 | R15: 472.199 | S15: 413.478
B16: 2010Q4 | C16: 300.342 | D16: 95.696 | E16: 78.973 | F16: 41.914 | G16: 19.064 | H16: 15.547 | I16: 2.618 | J16: 0.418 | K16: 475.429 | L16: -4.046 | M16: 471.383 | N16: 139.076 | O16: 611.773 | P16: 139.318 | Q16: 0 | R16: 472.612 | S16: 414.371
... B89: 2029Q1 | C89: 386.99075 | D89: 130.50646 | E89: 108.5662 | F89: 61.292345 | G89: 28.99537 | H89: 16.60913 | I89: 1.6693576 | J89: -1.2825 | K89: 624.78092 | L89: 0.76566173 | M89: 625.54658 | N89: 181.1219 | O89: 806.66848 | P89: 187.91993 | Q89: 4.757 | R89: 623.50554 | S89: 554.78657
B90: 2008 | C90: 1204.604 | D90: 375.86 | E90: 331.947 | F90: 180.899 | G90: 87.043 | H90: 57.198 | I90: 8.441 | J90: -1.043 | K90: 1911.368 | L90: -12.788 | M90: 1898.58 | N90: 556.861 | O90: 2459.033 | P90: 533.891 | Q90: 0 | R90: 1926.735 | S90: 1678.818
B91: 2009 | C91: 1170.035 | D91: 380.838 | E91: 291.21 | F91: 150.594 | G91: 68.314 | H91: 62.233 | I91: 10.728 | J91: 2.733 | K91: 1844.816 | L91: -35.031 | M91: 1809.785 | N91: 507.634 | O91: 2332.161 | P91: 496.388 | Q91: 0 | R91: 1837.817 | S91: 1602.633
B92: 2010 | C92: 1195.24 | D92: 380.761 | E92: 305.032 | F92: 157.061 | G92: 74.837 | H92: 63.322 | I92: 10.703 | J92: -0.001 | K92: 1881.032 | L92: -8.563 | M92: 1872.469 | N92: 540.861 | O92: 2418.798 | P92: 540.884 | Q92: 0 | R92: 1878.96 | S92: 1644.526
B93: 2011 | C93: 1191.27 | D93: 380.515 | E93: 305.354 | F93: 166.465 | G93: 71.386 | H93: 57.955 | I93: 9.969 | J93: -0.705 | K93: 1876.434 | L93: -3.784 | M93: 1872.65 | N93: 578.333 | O93: 2456.555 | P93: 556.723 | Q93: 0 | R93: 1900.476 | S93: 1672.213
B94: 2012 | C94: 1211.807 | D94: 386.188 | E94: 310.222 | F94: 178.179 | G94: 69.926 | H94: 53.007 | I94: 9.042 | J94: -1.036 | K94: 1907.181 | L94: 6.378 | M94: 1913.559 | N94: 582.729 | O94: 2499.35 | P94: 570.385 | Q94: 0 | R94: 1929.229 | S94: 1706.911
B95: 2013 | C95: 1242.448 | D95: 387.05 | E95: 320.303 | F95: 184.651 | G95: 77.388 | H95: 49.603 | I95: 8.512 | J95: 7.022 | K95: 1956.823 | L95: 6.784 | M95: 1963.607 | N95: 584.387 | O95: 2552.855 | P95: 588.884 | Q95: 0 | R95: 1963.807 | S95: 1740.343
B96: 2014 | C96: 1276.097 | D96: 397.069 | E96: 342.84 | F96: 194.883 | G96: 82.424 | H96: 55.58 | I96: 9.862 | J96: 6.071 | K96: 2022.077 | L96: 15.349 | M96: 2037.426 | N96: 590.26 | O96: 2646.112 | P96: 618.888 | Q96: 0 | R96: 2026.566 | S96: 1797.211
B97: 2015 | C97: 1312.213 | D97: 402.148 | E97: 367.34 | F97: 213.281 | G97: 87.743 | H97: 56.548 | I97: 9.646 | J97: 0.393 | K97: 2082.094 | L97: 12.105 | M97: 2094.199 | N97: 612.533 | O97: 2721.787 | P97: 649.558 | Q97: 0 | R97: 2071.561 | S97: 1831.364
B98: 2016 | C98: 1360.504 | D98: 404.984 | E98: 386.225 | F98: 227.965 | G98: 93.928 | H98: 54.579 | I98: 9.742 | J98: 1.599 | K98: 2153.312 | L98: 5.036 | M98: 2158.348 | N98: 629.527 | O98: 2786.771 | P98: 675.388 | Q98: 0 | R98: 2111.357 | S98: 1867.008
B99: 2017 | C99: 1385.378 | D99: 407.632 | E99: 399.752 | F99: 227.445 | G99: 102.153 | H99: 60.512 | I99: 9.612 | J99: 0.606 | K99: 2193.368 | L99: 13.307 | M99: 2206.675 | N99: 672.118 | O99: 2864.105 | P99: 696.761 | Q99: 0 | R99: 2167.415 | S99: 1919.054
B100: 2018 | C100: 1412.6 | D100: 410.171 | E100: 397.838 | F100: 223.77 | G100: 108.26 | H100: 60.511 | I100: 5.347 | J100: 3.137 | K100: 2223.746 | L100: 0.941 | M100: 2224.687 | N100: 692.86 | O100: 2916.14 | P100: 718.347 | Q100: 0 | R100: 2197.841 | S100: 1943.493
B101: 2019 | C101: 1427.94 | D101: 426.592 | E101: 406.423 | F101: 228.581 | G101: 109.909 | H101: 62.14 | I101: 5.7435985 | J101: 2.88 | K101: 2263.835 | L101: 1.262 | M101: 2265.097 | N101: 706.696 | O101: 2971.793 | P101: 737.872 | Q101: 0 | R101: 2233.921 | S101: 1978.192
... B110: 2028 | C110: 1529.7754 | D110: 516.75272 | E110: 431.27728 | F110: 243.67744 | G110: 113.25735 | H110: 67.827732 | I110: 6.5147616 | J110: -5.13 | K110: 2472.6754 | L110: 2.5476196 | M110: 2475.223 | N110: 721.5985 | O110: 3196.8215 | P110: 747.55672 | Q110: 19.028 | R110: 2468.2928 | S110: 2195.7429
B111: 2008-09 | C111: 1187.784 | D111: 377.339 | E111: 322.361 | F111: 175.387 | G111: 79.708 | H111: 58.955 | I111: 9.628 | J111: 0.012 | K111: 1887.496 | L111: -19.494 | M111: 1868.002 | N111: 543.298 | O111: 2413.802 | P111: 518.506 | Q111: 0 | R111: 1897.057 | S111: 1653.664
B112: 2009-10 | C112: 1172.216 | D112: 380.841 | E112: 291.087 | F112: 149.101 | G112: 68.312 | H112: 63.536 | I112: 10.756 | J112: 1.059 | K112: 1845.203 | L112: -27.833 | M112: 1817.37 | N112: 511.493 | O112: 2344.737 | P112: 504.347 | Q112: 0 | R112: 1842.255 | S112: 1607.266
B113: 2010-11 | C113: 1199.499 | D113: 382.218 | E113: 305.816 | F113: 157.857 | G113: 75.328 | H113: 62.987 | I113: 10.618 | J113: -1.944 | K113: 1885.589 | L113: -8.626 | M113: 1876.963 | N113: 555.074 | O113: 2434.524 | P113: 547.238 | Q113: 0 | R113: 1888.236 | S113: 1654.774
B114: 2011-12 | C114: 1192.115 | D114: 382.481 | E114: 308.087 | F114: 172.739 | G114: 70.143 | H114: 55.594 | I114: 9.64 | J114: -0.36 | K114: 1882.323 | L114: -6.242 | M114: 1876.081 | N114: 583.603 | O114: 2469.395 | P114: 562.558 | Q114: 0 | R114: 1907.289 | S114: 1680.39
B115: 2012-13 | C115: 1219.509 | D115: 383.864 | E115: 308.262 | F115: 177.636 | G115: 71.051 | H115: 50.724 | I115: 8.845 | J115: 1.689 | K115: 1913.324 | L115: 12.249 | M115: 1925.573 | N115: 578.781 | O115: 2503.373 | P115: 569.73 | Q115: 0 | R115: 1934.006 | S115: 1713.037
B116: 2013-14 | C116: 1251.056 | D116: 389.959 | E116: 328.218 | F116: 187.917 | G116: 79.759 | H116: 51.897 | I116: 8.542 | J116: 7.843 | K116: 1977.076 | L116: 4.264 | M116: 1981.34 | N116: 582.917 | O116: 2576.023 | P116: 596.666 | Q116: 0 | R116: 1978.95 | S116: 1753.086
B117: 2014-15 | C117: 1286.09 | D117: 397.794 | E117: 349.357 | F117: 200.346 | G117: 82.466 | H117: 56.077 | I117: 10.342 | J117: 7.428 | K117: 2040.669 | L117: 21.859 | M117: 2062.528 | N117: 596.564 | O117: 2674.223 | P117: 633.483 | Q117: 0 | R117: 2039.864 | S117: 1809.444
B118: 2015-16 | C118: 1323.968 | D118: 403.76 | E118: 371.051 | F118: 216.768 | G118: 89.667 | H118: 55.113 | I118: 9.42 | J118: -1.311 | K118: 2097.468 | L118: 7.486 | M118: 2104.954 | N118: 616.107 | O118: 2733.568 | P118: 651.515 | Q118: 0 | R118: 2081.524 | S118: 1838.471
B119: 2016-17 | C119: 1368.575 | D119: 405.169 | E119: 390.464 | F119: 228.363 | G119: 96.898 | H119: 55.373 | I119: 9.834 | J119: -0.129 | K119: 2164.079 | L119: 9.618 | M119: 2173.697 | N119: 638.633 | O119: 2805.016 | P119: 680.972 | Q119: 0 | R119: 2124.11 | S119: 1879.97
B120: 2017-18 | C120: 1391.8 | D120: 408.182 | E120: 401.053 | F120: 226.789 | G120: 103.486 | H120: 62.242 | I120: 8.527 | J120: 1.596 | K120: 2202.631 | L120: 7.439 | M120: 2210.07 | N120: 680.185 | O120: 2880.648 | P120: 702.211 | Q120: 0 | R120: 2178.537 | S120: 1927.785
B121: 2018-19 | C121: 1418.455 | D121: 413.55 | E121: 399.565 | F121: 223.66 | G121: 109.414 | H121: 61.167 | I121: 5.3704693 | J121: 14.691 | K121: 2246.261 | L121: 8.426 | M121: 2254.687 | N121: 692.696 | O121: 2945.466 | P121: 740.157 | Q121: 0 | R121: 2205.294 | S121: 1950.519
B122: 2019-20 | C122: 1416.634 | D122: 424.902 | E122: 401.509 | F122: 227.994 | G122: 107.276 | H122: 60.56 | I122: 5.6087288 | J122: -8.545 | K122: 2234.5 | L122: -7.512 | M122: 2226.988 | N122: 705.479 | O122: 2933.523 | P122: 709.213 | Q122: 0 | R122: 2224.377 | S122: 1971.447
... B131: 2028-29 | C131: 1537.0274 | D131: 518.88095 | E131: 432.44724 | F131: 244.27561 | G131: 114.33206 | H131: 67.261722 | I131: 6.5778504 | J131: -5.13 | K131: 2483.2256 | L131: 2.6817125 | M131: 2485.9073 | N131: 722.77921 | O131: 3208.6865 | P131: 749.14675 | Q131: 19.028 | R131: 2478.5677 | S131: 2205.0915
B132: Definitions:
B133: Household and non-profit institutions serving households final consumption expenditure (ONS Economic Accounts Table 1.1.2, identifier: ABJR + HAYO)
B134: General government final consumption (ONS Economic Accounts Table 1.1.2, identifier: NMRY)
B135: Total gross fixed capital formation (ONS Economic Accounts Table 1.1.2, identifier: NPQT)
B136: Business investment (ONS Economic Accounts Table 1.1.8, identifier: NPEL)
B137: Private sector investment in dwellings, including transfer costs (ONS Economic Accounts Table 1.1.8, identifier: L636 + L637)
B138: General government gross fixed capital formation (ONS Economic Accounts Table 1.1.8, identifier: DLWF)
B139: Public corporations investment in dwellings, including transfer costs (ONS Economic Accounts Table 1.1.8, identifier: L634 + L635)
B140: Net acquisitions of valuables (ONS Economic Accounts Table 1.1.2, identifier: NPJR)
B141: Final domestic demand is the sum of private consumption, government consumption, fixed investment and net acquisition of valuables
B142: Change in inventories (ONS Economic Accounts Table 1.1.2, identifier: CAFU)
B143: Total domestic demand is the sum of final domestic demand and change in inventories
... B148: Gross domestic product at market prices (ONS Economic Accounts Table 1.1.2, identifier: ABMI)

Sheet OBR_MAR24_1.2
A1: Back to contents
B2: 1.2 GDP expenditure components (£ billion current prices, seasonally adjusted) | S2: Deflators
C3: Private consumption | D3: Government consumption | E3: Fixed investment | G3: Net acquisition of valuables | H3: Final domestic demand | I3: Change in inventories | J3: Total domestic demand | K3: Exports | L3: Total final expenditure | M3: Imports | N3: Statistical discrepancy | O3: GDP at market prices | P3: Gross national income | S3: C | T3: GC | U3: IF | V3: X | W3: M | X3: GDP | Z3: C | AA3: GC | AB3: IF | AC3: X | AD3: M | AE3: GDP
E4: of which: | F4: General government
B5: 2008Q1 | C5: 255.438 | D5: 80.007 | E5: 71.229 | F5: 12.058 | G5: 0.277 | H5: 406.951 | I5: -0.163 | J5: 406.788 | K5: 104.955 | L5: 511.743 | M5: 114.195 | N5: 0 | O5: 397.548 | P5: 396.936 | S5: =100*(C5/OBR_MAR24_1.1!C5) -> 82.906421 | T5: =100*(D5/OBR_MAR24_1.1!D5) -> 85.731277 | U5: =100*(E5/OBR_MAR24_1.1!E5) -> 83.949933 | V5: =100*(K5/OBR_MAR24_1.1!N5) -> 74.815021 | W5: =100*(M5/OBR_MAR24_1.1!P5) -> 83.291394 | X5: =100*(O5/OBR_MAR24_1.1!R5) -> 81.168191
B6: 2008Q2 | C6: 256.141 | D6: 80.199 | E6: 72.373 | F6: 11.633 | G6: -0.087 | H6: 408.626 | I6: 0.83 | J6: 409.456 | K6: 110.409 | L6: 519.865 | M6: 118.984 | N6: 0 | O6: 400.881 | P6: 396.091 | S6: =100*(C6/OBR_MAR24_1.1!C6) -> 84.120213 | T6: =100*(D6/OBR_MAR24_1.1!D6) -> 86.479113 | U6: =100*(E6/OBR_MAR24_1.1!E6) -> 84.351799 | V6: =100*(K6/OBR_MAR24_1.1!N6) -> 78.692135 | W6: =100*(M6/OBR_MAR24_1.1!P6) -> 87.325784 | X6: =100*(O6/OBR_MAR24_1.1!R6) -> 82.251234 | AA6: =100*((T6/T5)-1) -> 0.87230219
B7: 2008Q3 | C7: 255.819 | D7: 81.155 | E7: 69.19 | F7: 11.875 | G7: -0.658 | H7: 405.506 | I7: 0.855 | J7: 406.361 | K7: 113.34 | L7: 519.701 | M7: 119.731 | N7: 0 | O7: 399.97 | P7: 395.566 | S7: =100*(C7/OBR_MAR24_1.1!C7) -> 85.377445 | T7: =100*(D7/OBR_MAR24_1.1!D7) -> 85.972012 | U7: =100*(E7/OBR_MAR24_1.1!E7) -> 85.080482 | V7: =100*(K7/OBR_MAR24_1.1!N7) -> 80.470869 | W7: =100*(M7/OBR_MAR24_1.1!P7) -> 89.477696 | X7: =100*(O7/OBR_MAR24_1.1!R7) -> 83.34931 | AA7: =100*((T7/T6)-1) -> -0.58638596
B8: 2008Q4 | C8: 247.924 | D8: 83.414 | E8: 68.46 | F8: 12.733 | G8: 0.279 | H8: 400.077 | I8: -2.203 | J8: 397.874 | K8: 109.631 | L8: 507.505 | M8: 112.304 | N8: 0 | O8: 395.201 | P8: 383.976 | S8: =100*(C8/OBR_MAR24_1.1!C8) -> 84.79716 | T8: =100*(D8/OBR_MAR24_1.1!D8) -> 87.434226 | U8: =100*(E8/OBR_MAR24_1.1!E8) -> 85.59854 | V8: =100*(K8/OBR_MAR24_1.1!N8) -> 80.953893 | W8: =100*(M8/OBR_MAR24_1.1!P8) -> 88.62094 | X8: =100*(O8/OBR_MAR24_1.1!R8) -> 84.1401 | AA8: =100*((T8/T7)-1) -> 1.7008022
B9: 2009Q1 | C9: 247.707 | D9: 84.238 | E9: 65.081 | F9: 13.271 | G9: 1.281 | H9: 398.307 | I9: -6.857 | J9: 391.45 | K9: 103.636 | L9: 495.086 | M9: 108.347 | N9: 0 | O9: 386.739 | P9: 379.763 | S9: =100*(C9/OBR_MAR24_1.1!C9) -> 85.039686 | T9: =100*(D9/OBR_MAR24_1.1!D9) -> 88.856775 | U9: =100*(E9/OBR_MAR24_1.1!E9) -> 86.473738 | V9: =100*(K9/OBR_MAR24_1.1!N9) -> 81.781523 | W9: =100*(M9/OBR_MAR24_1.1!P9) -> 89.014772 | X9: =100*(O9/OBR_MAR24_1.1!R9) -> 84.054509 | AA9: =100*((T9/T8)-1) -> 1.6269939
B10: 2009Q2 | C10: 248.136 | D10: 84.184 | E10: 62.025 | F10: 12.265 | G10: 0.516 | H10: 394.861 | I10: -3.785 | J10: 391.076 | K10: 101.716 | L10: 492.792 | M10: 106.228 | N10: 0 | O10: 386.564 | P10: 380.724 | S10: =100*(C10/OBR_MAR24_1.1!C10) -> 85.237883 | T10: =100*(D10/OBR_MAR24_1.1!D10) -> 89.023307 | U10: =100*(E10/OBR_MAR24_1.1!E10) -> 86.070522 | V10: =100*(K10/OBR_MAR24_1.1!N10) -> 81.100303 | W10: =100*(M10/OBR_MAR24_1.1!P10) -> 87.065708 | X10: =100*(O10/OBR_MAR24_1.1!R10) -> 84.292377 | AA10: =100*((T10/T9)-1) -> 0.18741598
B11: 2009Q3 | C11: 249.481 | D11: 86.207 | E11: 62.265 | F11: 13.498 | G11: 0.57 | H11: 398.523 | I11: -3.917 | J11: 394.606 | K11: 102.632 | L11: 497.238 | M11: 108.614 | N11: 0 | O11: 388.624 | P11: 389.479 | S11: =100*(C11/OBR_MAR24_1.1!C11) -> 85.225052 | T11: =100*(D11/OBR_MAR24_1.1!D11) -> 90.39974 | U11: =100*(E11/OBR_MAR24_1.1!E11) -> 85.822387 | V11: =100*(K11/OBR_MAR24_1.1!N11) -> 82.218733 | W11: =100*(M11/OBR_MAR24_1.1!P11) -> 86.675551 | X11: =100*(O11/OBR_MAR24_1.1!R11) -> 84.690602 | AA11: =100*((T11/T10)-1) -> 1.546149
B12: 2009Q4 | C12: 250.34 | D12: 85.942 | E12: 60.697 | F12: 13.189 | G12: -0.013 | H12: 396.966 | I12: -6.071 | J12: 390.895 | K12: 108.358 | L12: 499.253 | M12: 112.378 | N12: 0 | O12: 386.875 | P12: 385.824 | S12: =100*(C12/OBR_MAR24_1.1!C12) -> 84.887202 | T12: =100*(D12/OBR_MAR24_1.1!D12) -> 89.420456 | U12: =100*(E12/OBR_MAR24_1.1!E12) -> 85.087264 | V12: =100*(K12/OBR_MAR24_1.1!N12) -> 82.929368 | W12: =100*(M12/OBR_MAR24_1.1!P12) -> 88.243424 | X12: =100*(O12/OBR_MAR24_1.1!R12) -> 84.059769 | AA12: =100*((T12/T11)-1) -> -1.0832821
B13: 2010Q1 | C13: 249.159 | D13: 86.856 | E13: 63.512 | F13: 13.272 | G13: -0.221 | H13: 399.306 | I13: 1.601 | J13: 400.907 | K13: 110.685 | L13: 511.592 | M13: 115.479 | N13: 0 | O13: 396.113 | P13: 396.248 | S13: =100*(C13/OBR_MAR24_1.1!C13) -> 84.902459 | T13: =100*(D13/OBR_MAR24_1.1!D13) -> 91.615421 | U13: =100*(E13/OBR_MAR24_1.1!E13) -> 84.527137 | V13: =100*(K13/OBR_MAR24_1.1!N13) -> 84.762831 | W13: =100*(M13/OBR_MAR24_1.1!P13) -> 89.051258 | X13: =100*(O13/OBR_MAR24_1.1!R13) -> 85.269394 | AA13: =100*((T13/T12)-1) -> 2.4546569
B14: 2010Q2 | C14: 257.449 | D14: 86.19 | E14: 62.846 | F14: 12.714 | G14: -0.362 | H14: 406.123 | I14: 0.261 | J14: 406.384 | K14: 115.919 | L14: 522.303 | M14: 120.992 | N14: 0 | O14: 401.311 | P14: 401.775 | S14: =100*(C14/OBR_MAR24_1.1!C14) -> 85.647323 | T14: =100*(D14/OBR_MAR24_1.1!D14) -> 90.609001 | U14: =100*(E14/OBR_MAR24_1.1!E14) -> 84.901786 | V14: =100*(K14/OBR_MAR24_1.1!N14) -> 85.9334 | W14: =100*(M14/OBR_MAR24_1.1!P14) -> 90.437642 | X14: =100*(O14/OBR_MAR24_1.1!R14) -> 85.456958 | AA14: =100*((T14/T13)-1) -> -1.098527
B15: 2010Q3 | C15: 259.351 | D15: 85.911 | E15: 65.226 | F15: 13.003 | G15: 0.447 | H15: 410.935 | I15: 1.096 | J15: 412.031 | K15: 116.698 | L15: 528.729 | M15: 124.53 | N15: 0 | O15: 404.199 | P15: 403.675 | S15: =100*(C15/OBR_MAR24_1.1!C15) -> 86.208662 | T15: =100*(D15/OBR_MAR24_1.1!D15) -> 90.302406 | U15: =100*(E15/OBR_MAR24_1.1!E15) -> 84.820349 | V15: =100*(K15/OBR_MAR24_1.1!N15) -> 85.612836 | W15: =100*(M15/OBR_MAR24_1.1!P15) -> 90.171175 | X15: =100*(O15/OBR_MAR24_1.1!R15) -> 85.599292 | AA15: =100*((T15/T14)-1) -> -0.33837143
B16: 2010Q4 | C16: 261.157 | D16: 87.359 | E16: 66.706 | F16: 12.588 | G16: 0.574 | H16: 415.796 | I16: -1.483 | J16: 414.313 | K16: 120.874 | L16: 535.187 | M16: 128.257 | N16: 0 | O16: 406.93 | P16: 407.562 | S16: =100*(C16/OBR_MAR24_1.1!C16) -> 86.953207 | T16: =100*(D16/OBR_MAR24_1.1!D16) -> 91.288037 | U16: =100*(E16/OBR_MAR24_1.1!E16) -> 84.466843 | V16: =100*(K16/OBR_MAR24_1.1!N16) -> 86.912192 | W16: =100*(M16/OBR_MAR24_1.1!P16) -> 92.06061 | X16: =100*(O16/OBR_MAR24_1.1!R16) -> 86.102342 | AA16: =100*((T16/T15)-1) -> 1.0914782
B17: 2011Q1 | C17: 263.602 | D17: 89.47 | E17: 64.274 | F17: 13.122 | G17: -1.752 | H17: 415.594 | I17: -1.655 | J17: 413.939 | K17: 128.717 | L17: 542.656 | M17: 127.924 | N17: 0 | O17: 414.732 | P17: 416.433 | S17: =100*(C17/OBR_MAR24_1.1!C17) -> 88.53905 | T17: =100*(D17/OBR_MAR24_1.1!D17) -> 92.944256 | U17: =100*(E17/OBR_MAR24_1.1!E17) -> 84.657938 | V17: =100*(K17/OBR_MAR24_1.1!N17) -> 88.896025 | W17: =100*(M17/OBR_MAR24_1.1!P17) -> 94.040329 | X17: =100*(O17/OBR_MAR24_1.1!R17) -> 87.529626 | AA17: =100*((T17/T16)-1) -> 1.8142784
... B55: 2020Q3 | C55: 319.136 | D55: 121.322 | E55: 92.349 | F55: 16.901 | G55: 1.172 | H55: 533.979 | I55: -0.951 | J55: 533.028 | K55: 147.825 | L55: 680.853 | M55: 147.185 | N55: 0 | O55: 533.668 | P55: 527.792 | S55: =100*(C55/OBR_MAR24_1.1!C55) -> 100.72307 | T55: =100*(D55/OBR_MAR24_1.1!D55) -> 121.40213 | U55: =100*(E55/OBR_MAR24_1.1!E55) -> 101.75526 | V55: =100*(K55/OBR_MAR24_1.1!N55) -> 99.277372 | W55: =100*(M55/OBR_MAR24_1.1!P55) -> 97.882542 | X55: =100*(O55/OBR_MAR24_1.1!R55) -> 105.12663 | AA55: =100*((T55/T54)-1) -> -15.407269
B56: 2020Q4 | C56: 314.018 | D56: 123.948 | E56: 96.772 | F56: 17.161 | G56: 7.662 | H56: 542.4 | I56: 10.552 | J56: 552.952 | K56: 158.181 | L56: 711.133 | M56: 172.439 | N56: 0 | O56: 538.694 | P56: 530.241 | S56: =100*(C56/OBR_MAR24_1.1!C56) -> 100.71814 | T56: =100*(D56/OBR_MAR24_1.1!D56) -> 118.23151 | U56: =100*(E56/OBR_MAR24_1.1!E56) -> 100.65005 | V56: =100*(K56/OBR_MAR24_1.1!N56) -> 100.37439 | W56: =100*(M56/OBR_MAR24_1.1!P56) -> 100.12774 | X56: =100*(O56/OBR_MAR24_1.1!R56) -> 104.69612 | Z56: =100*((S56/S55)-1) -> -0.0048942098 | AA56: =100*((T56/T55)-1) -> -2.6116666
B57: 2021Q1 | C57: 306.507 | D57: 129.099 | E57: 95.16 | F57: 18.039 | G57: 8.584 | H57: 539.35 | I57: -1.153 | J57: 538.197 | K57: 156.517 | L57: 694.714 | M57: 156.702 | N57: 0 | O57: 538.012 | P57: 537.213 | S57: =100*(C57/OBR_MAR24_1.1!C57) -> 101.83633 | T57: =100*(D57/OBR_MAR24_1.1!D57) -> 121.94797 | U57: =100*(E57/OBR_MAR24_1.1!E57) -> 101.47478 | V57: =100*(K57/OBR_MAR24_1.1!N57) -> 101.16995 | W57: =100*(M57/OBR_MAR24_1.1!P57) -> 100.66617 | X57: =100*(O57/OBR_MAR24_1.1!R57) -> 105.64563 | Z57: =100*((S57/S56)-1) -> 1.1102248 | AA57: =100*((T57/T56)-1) -> 3.143379
B58: 2021Q2 | C58: 342.73 | D58: 126.02 | E58: 99.19 | F58: 17.679 | G58: -0.583 | H58: 567.357 | I58: -7.639 | J58: 559.718 | K58: 170.177 | L58: 729.895 | M58: 162.008 | N58: 0 | O58: 567.887 | P58: 569.781 | S58: =100*(C58/OBR_MAR24_1.1!C58) -> 101.86625 | T58: =100*(D58/OBR_MAR24_1.1!D58) -> 110.45085 | U58: =100*(E58/OBR_MAR24_1.1!E58) -> 100.32163 | V58: =100*(K58/OBR_MAR24_1.1!N58) -> 102.03253 | W58: =100*(M58/OBR_MAR24_1.1!P58) -> 100.23697 | X58: =100*(O58/OBR_MAR24_1.1!R58) -> 103.89843 | Z58: =100*((S58/S57)-1) -> 0.02937102 | AA58: =100*((T58/T57)-1) -> -9.4278916
B59: 2021Q3 | C59: 357.103 | D59: 126.347 | E59: 104.563 | F59: 18.066 | G59: 3.684 | H59: 591.697 | I59: 0.585 | J59: 592.282 | K59: 163.01 | L59: 755.292 | M59: 173.786 | N59: 0 | O59: 581.506 | P59: 583.95 | S59: =100*(C59/OBR_MAR24_1.1!C59) -> 103.10675 | T59: =100*(D59/OBR_MAR24_1.1!D59) -> 109.72765 | U59: =100*(E59/OBR_MAR24_1.1!E59) -> 106.44386 | V59: =100*(K59/OBR_MAR24_1.1!N59) -> 102.20255 | W59: =100*(M59/OBR_MAR24_1.1!P59) -> 103.14383 | X59: =100*(O59/OBR_MAR24_1.1!R59) -> 104.59569 | Z59: =100*((S59/S58)-1) -> 1.2177751 | AA59: =100*((T59/T58)-1) -> -0.65476934
B60: 2021Q4 | C60: 362.996 | D60: 127.25 | E60: 104.934 | F60: 17.928 | G60: -2.959 | H60: 592.221 | I60: 5.179 | J60: 597.4 | K60: 186.322 | L60: 783.722 | M60: 187.048 | N60: 0 | O60: 596.674 | P60: 605.668 | S60: =100*(C60/OBR_MAR24_1.1!C60) -> 104.51011 | T60: =100*(D60/OBR_MAR24_1.1!D60) -> 109.31755 | U60: =100*(E60/OBR_MAR24_1.1!E60) -> 106.24076 | V60: =100*(K60/OBR_MAR24_1.1!N60) -> 106.12828 | W60: =100*(M60/OBR_MAR24_1.1!P60) -> 108.69575 | X60: =100*(O60/OBR_MAR24_1.1!R60) -> 105.71697 | Z60: =100*((S60/S59)-1) -> 1.3610751 | AA60: =100*((T60/T59)-1) -> -0.37374435
B61: 2022Q1 | C61: 373.512 | D61: 133.146 | E61: 110.419 | F61: 19.375 | G61: 8.494 | H61: 625.571 | I61: 9.731 | J61: 635.302 | K61: 179.132 | L61: 814.434 | M61: 212.54 | N61: 6.435 | O61: 608.329 | P61: 601.96 | S61: =100*(C61/OBR_MAR24_1.1!C61) -> 106.71863 | T61: =100*(D61/OBR_MAR24_1.1!D61) -> 113.21939 | U61: =100*(E61/OBR_MAR24_1.1!E61) -> 106.34288 | V61: =100*(K61/OBR_MAR24_1.1!N61) -> 110.4628 | W61: =100*(M61/OBR_MAR24_1.1!P61) -> 112.7599 | X61: =100*(O61/OBR_MAR24_1.1!R61) -> 107.21419 | Z61: =100*((S61/S60)-1) -> 2.1132137 | AA61: =100*((T61/T60)-1) -> 3.56927
B62: 2022Q2 | C62: 385.746 | D62: 128.435 | E62: 113.29 | F62: 18.267 | G62: 2.581 | H62: 630.052 | I62: 10.918 | J62: 640.97 | K62: 199.081 | L62: 840.051 | M62: 226.693 | N62: 7.914 | O62: 621.272 | P62: 630.944 | S62: =100*(C62/OBR_MAR24_1.1!C62) -> 109.78154 | T62: =100*(D62/OBR_MAR24_1.1!D62) -> 112.12134 | U62: =100*(E62/OBR_MAR24_1.1!E62) -> 108.62562 | V62: =100*(K62/OBR_MAR24_1.1!N62) -> 116.02403 | W62: =100*(M62/OBR_MAR24_1.1!P62) -> 117.94334 | X62: =100*(O62/OBR_MAR24_1.1!R62) -> 109.40025 | Z62: =100*((S62/S61)-1) -> 2.8700852 | AA62: =100*((T62/T61)-1) -> -0.96983687
B63: 2022Q3 | C63: 391.169 | D63: 132.118 | E63: 116.934 | F63: 19.225 | G63: -11.955 | H63: 628.266 | I63: 2.705 | J63: 630.971 | K63: 227.423 | L63: 858.394 | M63: 235.017 | N63: 7.198 | O63: 630.575 | P63: 631.386 | S63: =100*(C63/OBR_MAR24_1.1!C63) -> 112.34193 | T63: =100*(D63/OBR_MAR24_1.1!D63) -> 114.79139 | U63: =100*(E63/OBR_MAR24_1.1!E63) -> 110.22567 | V63: =100*(K63/OBR_MAR24_1.1!N63) -> 119.36649 | W63: =100*(M63/OBR_MAR24_1.1!P63) -> 126.24666 | X63: =100*(O63/OBR_MAR24_1.1!R63) -> 111.12531 | Z63: =100*((S63/S62)-1) -> 2.3322593 | AA63: =100*((T63/T62)-1) -> 2.3813874
B64: 2022Q4 | C64: 399.839 | D64: 132.493 | E64: 118.785 | F64: 20.726 | G64: -17.267 | H64: 633.85 | I64: 1.563 | J64: 635.413 | K64: 232.125 | L64: 867.538 | M64: 230.339 | N64: 8.606 | O64: 645.805 | P64: 654.041 | S64: =100*(C64/OBR_MAR24_1.1!C64) -> 114.92797 | T64: =100*(D64/OBR_MAR24_1.1!D64) -> 115.77508 | U64: =100*(E64/OBR_MAR24_1.1!E64) -> 111.33763 | V64: =100*(K64/OBR_MAR24_1.1!N64) -> 121.42144 | W64: =100*(M64/OBR_MAR24_1.1!P64) -> 123.10286 | X64: =100*(O64/OBR_MAR24_1.1!R64) -> 113.69126 | Z64: =100*((S64/S63)-1) -> 2.301931 | AA64: =100*((T64/T63)-1) -> 0.85693775
B65: 2023Q1 | C65: 410.541 | D65: 133.133 | E65: 122.62 | F65: 22.13 | G65: -5.396 | H65: 660.898 | I65: 0.511 | J65: 661.409 | K65: 219.303 | L65: 880.712 | M65: 226.301 | N65: 5.513 | O65: 659.924 | P65: 656.49 | S65: =100*(C65/OBR_MAR24_1.1!C65) -> 117.06831 | T65: =100*(D65/OBR_MAR24_1.1!D65) -> 117.58996 | U65: =100*(E65/OBR_MAR24_1.1!E65) -> 112.19691 | V65: =100*(K65/OBR_MAR24_1.1!N65) -> 122.23362 | W65: =100*(M65/OBR_MAR24_1.1!P65) -> 122.88882 | X65: =100*(O65/OBR_MAR24_1.1!R65) -> 115.88349 | Z65: =100*((S65/S64)-1) -> 1.8623322 | AA65: =100*((T65/T64)-1) -> 1.5675917
B66: 2023Q2 | C66: 417.479 | D66: 140.103 | E66: 122.306 | F66: 21.342 | G66: -3.106 | H66: 676.782 | I66: 0.953 | J66: 677.735 | K66: 217.528 | L66: 895.263 | M66: 225.085 | N66: 5.65 | O66: 675.828 | P66: 664.433 | S66: =100*(C66/OBR_MAR24_1.1!C66) -> 118.46165 | T66: =100*(D66/OBR_MAR24_1.1!D66) -> 120.66714 | U66: =100*(E66/OBR_MAR24_1.1!E66) -> 112.98998 | V66: =100*(K66/OBR_MAR24_1.1!N66) -> 121.75597 | W66: =100*(M66/OBR_MAR24_1.1!P66) -> 119.88932 | X66: =100*(O66/OBR_MAR24_1.1!R66) -> 118.63146 | Z66: =100*((S66/S65)-1) -> 1.1901964 | AA66: =100*((T66/T65)-1) -> 2.6168765
B67: 2023Q3 | C67: 418.482 | D67: 140.138 | E67: 121.398 | F67: 22.404 | G67: -0.429 | H67: 679.589 | I67: 5.026 | J67: 684.615 | K67: 214.137 | L67: 898.752 | M67: 219.277 | N67: 5.729 | O67: 685.204 | P67: 678.129 | S67: =100*(C67/OBR_MAR24_1.1!C67) -> 119.28341 | T67: =100*(D67/OBR_MAR24_1.1!D67) -> 119.78221 | U67: =100*(E67/OBR_MAR24_1.1!E67) -> 113.99301 | V67: =100*(K67/OBR_MAR24_1.1!N67) -> 120.58146 | W67: =100*(M67/OBR_MAR24_1.1!P67) -> 117.96443 | X67: =100*(O67/OBR_MAR24_1.1!R67) -> 120.43244 | Z67: =100*((S67/S66)-1) -> 0.69369424 | AA67: =100*((T67/T66)-1) -> -0.73336632
... B82: 2027Q2 | C82: 477.26562 | D82: 155.79582 | E82: 128.21766 | F82: 22.647836 | G82: -1.5443202 | H82: 759.73478 | I82: 0.47822681 | J82: 760.21301 | K82: 215.19555 | L82: 975.40856 | M82: 218.15676 | N82: 5.9965926 | O82: 763.24838 | P82: 749.99375 | S82: =100*(C82/OBR_MAR24_1.1!C82) -> 127.48319 | T82: =100*(D82/OBR_MAR24_1.1!D82) -> 122.8143 | U82: =100*(E82/OBR_MAR24_1.1!E82) -> 120.41483 | V82: =100*(K82/OBR_MAR24_1.1!N82) -> 120.25595 | W82: =100*(M82/OBR_MAR24_1.1!P82) -> 117.72371 | X82: =100*(O82/OBR_MAR24_1.1!R82) -> 126.05828 | Z82: =100*((S82/S81)-1) -> 0.4976757 | AA82: =100*((T82/T81)-1) -> 0.37090564
B83: 2027Q3 | C83: 481.93232 | D83: 156.98568 | E83: 129.06608 | F83: 22.650407 | G83: -1.5501806 | H83: 766.43391 | I83: 0.52823318 | J83: 766.96214 | K83: 216.37029 | L83: 983.33243 | M83: 219.2437 | N83: 6.0244182 | O83: 770.11315 | P83: 756.79869 | S83: =100*(C83/OBR_MAR24_1.1!C83) -> 128.11902 | T83: =100*(D83/OBR_MAR24_1.1!D83) -> 123.28151 | U83: =100*(E83/OBR_MAR24_1.1!E83) -> 120.87178 | V83: =100*(K83/OBR_MAR24_1.1!N83) -> 120.69167 | W83: =100*(M83/OBR_MAR24_1.1!P83) -> 118.09581 | X83: =100*(O83/OBR_MAR24_1.1!R83) -> 126.64322 | Z83: =100*((S83/S82)-1) -> 0.49875372 | AA83: =100*((T83/T82)-1) -> 0.38041416 | AB83: =100*((U83/U82)-1) -> 0.37947824 | AC83: =100*((V83/V82)-1) -> 0.36233 | AD83: =100*((W83/W82)-1) -> 0.31607466 | AE83: =100*((X83/X82)-1) -> 0.4640231
B84: 2027Q4 | C84: 486.64846 | D84: 158.238 | E84: 129.90604 | F84: 22.628453 | G84: -1.5561473 | H84: 773.23635 | I84: 0.52121442 | J84: 773.75757 | K84: 217.62977 | L84: 991.38734 | M84: 220.39025 | N84: 6.053019 | O84: 777.05011 | P84: 763.67307 | S84: =100*(C84/OBR_MAR24_1.1!C84) -> 128.75969 | T84: =100*(D84/OBR_MAR24_1.1!D84) -> 123.77128 | U84: =100*(E84/OBR_MAR24_1.1!E84) -> 121.33702 | V84: =100*(K84/OBR_MAR24_1.1!N84) -> 121.15862 | W84: =100*(M84/OBR_MAR24_1.1!P84) -> 118.49693 | X84: =100*(O84/OBR_MAR24_1.1!R84) -> 127.24446 | Z84: =100*((S84/S83)-1) -> 0.50006463 | AA84: =100*((T84/T83)-1) -> 0.39727849 | AB84: =100*((U84/U83)-1) -> 0.38490416 | AC84: =100*((V84/V83)-1) -> 0.38689145 | AD84: =100*((W84/W83)-1) -> 0.33965403 | AE84: =100*((X84/X83)-1) -> 0.47474917
B85: 2028Q1 | C85: 491.40143 | D85: 159.55276 | E85: 130.81399 | F85: 22.581976 | G85: -1.562149 | H85: 780.20603 | I85: 0.46942919 | J85: 780.67546 | K85: 218.87999 | L85: 999.55545 | M85: 221.55901 | N85: 6.0823162 | O85: 784.07876 | P85: 770.6732 | S85: =100*(C85/OBR_MAR24_1.1!C85) -> 129.40511 | T85: =100*(D85/OBR_MAR24_1.1!D85) -> 124.28334 | U85: =100*(E85/OBR_MAR24_1.1!E85) -> 121.80499 | V85: =100*(K85/OBR_MAR24_1.1!N85) -> 121.63973 | W85: =100*(M85/OBR_MAR24_1.1!P85) -> 118.90684 | X85: =100*(O85/OBR_MAR24_1.1!R85) -> 127.86034 | Z85: =100*((S85/S84)-1) -> 0.50125865 | AA85: =100*((T85/T84)-1) -> 0.41372066 | AB85: =100*((U85/U84)-1) -> 0.38567762 | AC85: =100*((V85/V84)-1) -> 0.39709688 | AD85: =100*((W85/W84)-1) -> 0.34593097 | AE85: =100*((X85/X84)-1) -> 0.48400827
B86: 2028Q2 | C86: 496.19731 | D86: 160.99326 | E86: 131.65745 | F86: 22.523952 | G86: -1.568168 | H86: 787.27985 | I86: 0.43292256 | J86: 787.71278 | K86: 220.15422 | L86: 1007.867 | M86: 222.76385 | N86: 6.1121338 | O86: 791.21528 | P86: 777.79842 | S86: =100*(C86/OBR_MAR24_1.1!C86) -> 130.05204 | T86: =100*(D86/OBR_MAR24_1.1!D86) -> 124.84186 | U86: =100*(E86/OBR_MAR24_1.1!E86) -> 122.27431 | V86: =100*(K86/OBR_MAR24_1.1!N86) -> 122.13004 | W86: =100*(M86/OBR_MAR24_1.1!P86) -> 119.32155 | X86: =100*(O86/OBR_MAR24_1.1!R86) -> 128.48715 | Z86: =100*((S86/S85)-1) -> 0.49992844 | AA86: =100*((T86/T85)-1) -> 0.44938828 | AB86: =100*((U86/U85)-1) -> 0.38529941 | AC86: =100*((V86/V85)-1) -> 0.40308259 | AD86: =100*((W86/W85)-1) -> 0.34876426 | AE86: =100*((X86/X85)-1) -> 0.49023535
B87: 2028Q3 | C87: 501.03375 | D87: 162.22282 | E87: 132.50564 | F87: 22.466085 | G87: -1.5742034 | H87: 794.18801 | I87: 0.48894231 | J87: 794.67696 | K87: 221.39457 | L87: 1016.0715 | M87: 223.99872 | N87: 6.1407033 | O87: 798.21351 | P87: 784.70093 | S87: =100*(C87/OBR_MAR24_1.1!C87) -> 130.70058 | T87: =100*(D87/OBR_MAR24_1.1!D87) -> 125.31678 | U87: =100*(E87/OBR_MAR24_1.1!E87) -> 122.74491 | V87: =100*(K87/OBR_MAR24_1.1!N87) -> 122.6214 | W87: =100*(M87/OBR_MAR24_1.1!P87) -> 119.73758 | X87: =100*(O87/OBR_MAR24_1.1!R87) -> 129.08773 | Z87: =100*((S87/S86)-1) -> 0.498675 | AA87: =100*((T87/T86)-1) -> 0.38041381 | AB87: =100*((U87/U86)-1) -> 0.38487293 | AC87: =100*((V87/V86)-1) -> 0.40232242 | AD87: =100*((W87/W86)-1) -> 0.34866134 | AE87: =100*((X87/X86)-1) -> 0.46742241
B88: 2028Q4 | C88: 505.91618 | D88: 163.51691 | E88: 133.38957 | F88: 22.408375 | G88: -1.5802679 | H88: 801.24239 | I88: 0.51639848 | J88: 801.75879 | K88: 222.67912 | L88: 1024.4379 | M88: 225.24219 | N88: 6.170086 | O88: 805.36581 | P88: 791.79657 | S88: =100*(C88/OBR_MAR24_1.1!C88) -> 131.35411 | T88: =100*(D88/OBR_MAR24_1.1!D88) -> 125.81463 | U88: =100*(E88/OBR_MAR24_1.1!E88) -> 123.21777 | V88: =100*(K88/OBR_MAR24_1.1!N88) -> 123.13337 | W88: =100*(M88/OBR_MAR24_1.1!P88) -> 120.15477 | X88: =100*(O88/OBR_MAR24_1.1!R88) -> 129.7054 | Z88: =100*((S88/S87)-1) -> 0.500023 | AA88: =100*((T88/T87)-1) -> 0.3972785 | AB88: =100*((U88/U87)-1) -> 0.38524236 | AC88: =100*((V88/V87)-1) -> 0.41752017 | AD88: =100*((W88/W87)-1) -> 0.3484248 | AE88: =100*((X88/X87)-1) -> 0.47849088
B89: 2029Q1 | C89: 510.87639 | D89: 164.87554 | E89: 134.28893 | F89: 22.366625 | G89: -1.5863643 | H89: 808.4545 | I89: 0.58018475 | J89: 809.03468 | K89: 224.07548 | L89: 1033.1102 | M89: 226.6295 | N89: 6.2003031 | O89: 812.68097 | P89: 799.06561 | S89: =100*(C89/OBR_MAR24_1.1!C89) -> 132.01256 | T89: =100*(D89/OBR_MAR24_1.1!D89) -> 126.33515 | U89: =100*(E89/OBR_MAR24_1.1!E89) -> 123.69313 | V89: =100*(K89/OBR_MAR24_1.1!N89) -> 123.71529 | W89: =100*(M89/OBR_MAR24_1.1!P89) -> 120.59897 | X89: =100*(O89/OBR_MAR24_1.1!R89) -> 130.34062 | Z89: =100*((S89/S88)-1) -> 0.50127396 | AA89: =100*((T89/T88)-1) -> 0.41372138 | AB89: =100*((U89/U88)-1) -> 0.38578441 | AC89: =100*((V89/V88)-1) -> 0.4725927 | AD89: =100*((W89/W88)-1) -> 0.369687 | AE89: =100*((X89/X88)-1) -> 0.48973537
B90: 2008 | C90: 1015.322 | D90: 324.775 | E90: 281.252 | F90: 48.299 | G90: -0.189 | H90: 1621.16 | I90: -0.681 | J90: 1620.479 | K90: 438.335 | L90: 2058.814 | M90: 465.214 | N90: 0 | O90: 1593.6 | P90: 1572.569 | S90: =100*(C90/OBR_MAR24_1.1!C90) -> 84.286786 | T90: =100*(D90/OBR_MAR24_1.1!D90) -> 86.408503 | U90: =100*(E90/OBR_MAR24_1.1!E90) -> 84.727984 | V90: =100*(K90/OBR_MAR24_1.1!N90) -> 78.715335 | W90: =100*(M90/OBR_MAR24_1.1!P90) -> 87.136513 | X90: =100*(O90/OBR_MAR24_1.1!R90) -> 82.709869
B91: 2009 | C91: 995.664 | D91: 340.571 | E91: 250.068 | F91: 52.223 | G91: 2.354 | H91: 1588.657 | I91: -20.63 | J91: 1568.027 | K91: 416.342 | L91: 1984.369 | M91: 435.567 | N91: 0 | O91: 1548.802 | P91: 1535.79 | S91: =100*(C91/OBR_MAR24_1.1!C91) -> 85.096942 | T91: =100*(D91/OBR_MAR24_1.1!D91) -> 89.426738 | U91: =100*(E91/OBR_MAR24_1.1!E91) -> 85.872051 | V91: =100*(K91/OBR_MAR24_1.1!N91) -> 82.016177 | W91: =100*(M91/OBR_MAR24_1.1!P91) -> 87.747286 | X91: =100*(O91/OBR_MAR24_1.1!R91) -> 84.274006 | Z91: =100*((S91/S90)-1) -> 0.96118884 | AA91: =100*((T91/T90)-1) -> 3.4929834 | AB91: =100*((U91/U90)-1) -> 1.3502828 | AC91: =100*((V91/V90)-1) -> 4.1933917 | AD91: =100*((W91/W90)-1) -> 0.70093867 | AE91: =100*((X91/X90)-1) -> 1.891112
B92: 2010 | C92: 1027.116 | D92: 346.316 | E92: 258.29 | F92: 51.577 | G92: 0.438 | H92: 1632.16 | I92: 1.475 | J92: 1633.635 | K92: 464.176 | L92: 2097.811 | M92: 489.258 | N92: 0 | O92: 1608.553 | P92: 1609.26 | S92: =100*(C92/OBR_MAR24_1.1!C92) -> 85.933871 | T92: =100*(D92/OBR_MAR24_1.1!D92) -> 90.953643 | U92: =100*(E92/OBR_MAR24_1.1!E92) -> 84.676362 | V92: =100*(K92/OBR_MAR24_1.1!N92) -> 85.821681 | W92: =100*(M92/OBR_MAR24_1.1!P92) -> 90.455255 | X92: =100*(O92/OBR_MAR24_1.1!R92) -> 85.608688 | Z92: =100*((S92/S91)-1) -> 0.98350124 | AA92: =100*((T92/T91)-1) -> 1.7074367 | AB92: =100*((U92/U91)-1) -> -1.392408 | AC92: =100*((V92/V91)-1) -> 4.6399427 | AD92: =100*((W92/W91)-1) -> 3.0860992 | AE92: =100*((X92/X91)-1) -> 1.5837413
B93: 2011 | C93: 1063.466 | D93: 347.419 | E93: 261.22 | F93: 48.039 | G93: 0.676 | H93: 1672.781 | I93: 2.947 | J93: 1675.728 | K93: 521.847 | L93: 2197.575 | M93: 534.985 | N93: 0 | O93: 1662.59 | P93: 1669.535 | S93: =100*(C93/OBR_MAR24_1.1!C93) -> 89.271618 | T93: =100*(D93/OBR_MAR24_1.1!D93) -> 91.302314 | U93: =100*(E93/OBR_MAR24_1.1!E93) -> 85.546611 | V93: =100*(K93/OBR_MAR24_1.1!N93) -> 90.232963 | W93: =100*(M93/OBR_MAR24_1.1!P93) -> 96.095365 | X93: =100*(O93/OBR_MAR24_1.1!R93) -> 87.48282 | Z93: =100*((S93/S92)-1) -> 3.8840874 | AA93: =100*((T93/T92)-1) -> 0.38335038 | AB93: =100*((U93/U92)-1) -> 1.0277362 | AC93: =100*((V93/V92)-1) -> 5.1400555 | AD93: =100*((W93/W92)-1) -> 6.2352491 | AE93: =100*((X93/X92)-1) -> 2.1891847
B94: 2012 | C94: 1100.051 | D94: 355.384 | E94: 270.019 | F94: 45.252 | G94: 0.352 | H94: 1725.806 | I94: 4.855 | J94: 1730.661 | K94: 524.715 | L94: 2255.376 | M94: 541.661 | N94: 0 | O94: 1713.715 | P94: 1697.755 | S94: =100*(C94/OBR_MAR24_1.1!C94) -> 90.777739 | T94: =100*(D94/OBR_MAR24_1.1!D94) -> 92.023574 | U94: =100*(E94/OBR_MAR24_1.1!E94) -> 87.040571 | V94: =100*(K94/OBR_MAR24_1.1!N94) -> 90.044429 | W94: =100*(M94/OBR_MAR24_1.1!P94) -> 94.964103 | X94: =100*(O94/OBR_MAR24_1.1!R94) -> 88.829009 | Z94: =100*((S94/S93)-1) -> 1.6871226 | AA94: =100*((T94/T93)-1) -> 0.78996907 | AB94: =100*((U94/U93)-1) -> 1.746369 | AC94: =100*((V94/V93)-1) -> -0.20894114 | AD94: =100*((W94/W93)-1) -> -1.1772285 | AE94: =100*((X94/X93)-1) -> 1.5388036
B95: 2013 | C95: 1153.092 | D95: 358.572 | E95: 284.444 | F95: 43.568 | G95: 7.215 | H95: 1803.323 | I95: 3.338 | J95: 1806.661 | K95: 539.564 | L95: 2346.225 | M95: 564.864 | N95: 0 | O95: 1781.361 | P95: 1749.792 | S95: =100*(C95/OBR_MAR24_1.1!C95) -> 92.808069 | T95: =100*(D95/OBR_MAR24_1.1!D95) -> 92.642294 | U95: =100*(E95/OBR_MAR24_1.1!E95) -> 88.804663 | V95: =100*(K95/OBR_MAR24_1.1!N95) -> 92.329912 | W95: =100*(M95/OBR_MAR24_1.1!P95) -> 95.921098 | X95: =100*(O95/OBR_MAR24_1.1!R95) -> 90.709576 | Z95: =100*((S95/S94)-1) -> 2.2365944 | AA95: =100*((T95/T94)-1) -> 0.67234975 | AB95: =100*((U95/U94)-1) -> 2.026747 | AC95: =100*((V95/V94)-1) -> 2.5381722 | AD95: =100*((W95/W94)-1) -> 1.007744 | AE95: =100*((X95/X94)-1) -> 2.117064
B96: 2014 | C96: 1198.685 | D96: 370.011 | E96: 308.662 | F96: 50.194 | G96: 6.103 | H96: 1883.461 | I96: 15.23 | J96: 1898.691 | K96: 532.236 | L96: 2430.927 | M96: 568.413 | N96: 0 | O96: 1862.514 | P96: 1829.242 | S96: =100*(C96/OBR_MAR24_1.1!C96) -> 93.93369 | T96: =100*(D96/OBR_MAR24_1.1!D96) -> 93.185567 | U96: =100*(E96/OBR_MAR24_1.1!E96) -> 90.030918 | V96: =100*(K96/OBR_MAR24_1.1!N96) -> 90.169756 | W96: =100*(M96/OBR_MAR24_1.1!P96) -> 91.844243 | X96: =100*(O96/OBR_MAR24_1.1!R96) -> 91.904927 | Z96: =100*((S96/S95)-1) -> 1.2128479 | AA96: =100*((T96/T95)-1) -> 0.58642003 | AB96: =100*((U96/U95)-1) -> 1.3808454 | AC96: =100*((V96/V95)-1) -> -2.3396056 | AD96: =100*((W96/W95)-1) -> -4.2502172 | AE96: =100*((X96/X95)-1) -> 1.3177782
B97: 2015 | C97: 1228.325 | D97: 374.638 | E97: 332.973 | F97: 51.665 | G97: 0.879 | H97: 1936.815 | I97: 8.606 | J97: 1945.421 | K97: 533.654 | L97: 2479.075 | M97: 562.624 | N97: 0 | O97: 1916.451 | P97: 1874.682 | S97: =100*(C97/OBR_MAR24_1.1!C97) -> 93.607135 | T97: =100*(D97/OBR_MAR24_1.1!D97) -> 93.159235 | U97: =100*(E97/OBR_MAR24_1.1!E97) -> 90.644362 | V97: =100*(K97/OBR_MAR24_1.1!N97) -> 87.12249 | W97: =100*(M97/OBR_MAR24_1.1!P97) -> 86.616438 | X97: =100*(O97/OBR_MAR24_1.1!R97) -> 92.51241 | Z97: =100*((S97/S96)-1) -> -0.34764371 | AA97: =100*((T97/T96)-1) -> -0.028257955 | AB97: =100*((U97/U96)-1) -> 0.68137032 | AC97: =100*((V97/V96)-1) -> -3.3794768 | AD97: =100*((W97/W96)-1) -> -5.692034 | AE97: =100*((X97/X96)-1) -> 0.66099053
B98: 2016 | C98: 1289.445 | D98: 382.76 | E98: 356.602 | F98: 51.474 | G98: 1.502 | H98: 2030.309 | I98: -0.908 | J98: 2029.401 | K98: 575.632 | L98: 2605.033 | M98: 613.388 | N98: 0 | O98: 1991.645 | P98: 1944.912 | S98: =100*(C98/OBR_MAR24_1.1!C98) -> 94.777009 | T98: =100*(D98/OBR_MAR24_1.1!D98) -> 94.512376 | U98: =100*(E98/OBR_MAR24_1.1!E98) -> 92.330118 | V98: =100*(K98/OBR_MAR24_1.1!N98) -> 91.43881 | W98: =100*(M98/OBR_MAR24_1.1!P98) -> 90.820092 | X98: =100*(O98/OBR_MAR24_1.1!R98) -> 94.330092 | Z98: =100*((S98/S97)-1) -> 1.2497698 | AA98: =100*((T98/T97)-1) -> 1.4525032 | AB98: =100*((U98/U97)-1) -> 1.8597475 | AC98: =100*((V98/V97)-1) -> 4.9543128 | AD98: =100*((W98/W97)-1) -> 4.8531826 | AE98: =100*((X98/X97)-1) -> 1.9647983
B99: 2017 | C99: 1336.921 | D99: 388.577 | E99: 380.012 | F99: 57.4 | G99: 0.842 | H99: 2106.352 | I99: 4.055 | J99: 2110.407 | K99: 643.286 | L99: 2753.693 | M99: 671.211 | N99: 0 | O99: 2082.482 | P99: 2060.075 | S99: =100*(C99/OBR_MAR24_1.1!C99) -> 96.502254 | T99: =100*(D99/OBR_MAR24_1.1!D99) -> 95.325441 | U99: =100*(E99/OBR_MAR24_1.1!E99) -> 95.061938 | V99: =100*(K99/OBR_MAR24_1.1!N99) -> 95.710277 | W99: =100*(M99/OBR_MAR24_1.1!P99) -> 96.333032 | X99: =100*(O99/OBR_MAR24_1.1!R99) -> 96.081369 | Z99: =100*((S99/S98)-1) -> 1.8203203 | AA99: =100*((T99/T98)-1) -> 0.86027337 | AB99: =100*((U99/U98)-1) -> 2.9587528 | AC99: =100*((V99/V98)-1) -> 4.6713935 | AD99: =100*((W99/W98)-1) -> 6.0701776 | AE99: =100*((X99/X98)-1) -> 1.856541
B100: 2018 | C100: 1391.673 | D100: 399.065 | E100: 387.324 | F100: 58.446 | G100: 2.826 | H100: 2180.888 | I100: 1.17 | J100: 2182.058 | K100: 679.7 | L100: 2861.758 | M100: 709.454 | N100: 0 | O100: 2152.304 | P100: 2123.051 | S100: =100*(C100/OBR_MAR24_1.1!C100) -> 98.518547 | T100: =100*(D100/OBR_MAR24_1.1!D100) -> 97.292349 | U100: =100*(E100/OBR_MAR24_1.1!E100) -> 97.357216 | V100: =100*(K100/OBR_MAR24_1.1!N100) -> 98.100626 | W100: =100*(M100/OBR_MAR24_1.1!P100) -> 98.762019 | X100: =100*(O100/OBR_MAR24_1.1!R100) -> 97.928103 | Z100: =100*((S100/S99)-1) -> 2.0893741 | AA100: =100*((T100/T99)-1) -> 2.0633613 | AB100: =100*((U100/U99)-1) -> 2.4145072 | AC100: =100*((V100/V99)-1) -> 2.4974845 | AD100: =100*((W100/W99)-1) -> 2.5214471 | AE100: =100*((X100/X99)-1) -> 1.9220524
B101: 2019 | C101: 1427.94 | D101: 426.592 | E101: 406.423 | F101: 62.139 | G101: 2.88 | H101: 2263.835 | I101: 1.262 | J101: 2265.097 | K101: 706.696 | L101: 2971.793 | M101: 737.872 | N101: 0 | O101: 2233.921 | P101: 2231.667 | S101: =100*(C101/OBR_MAR24_1.1!C101) -> 100 | T101: =100*(D101/OBR_MAR24_1.1!D101) -> 100 | U101: =100*(E101/OBR_MAR24_1.1!E101) -> 100 | V101: =100*(K101/OBR_MAR24_1.1!N101) -> 100 | W101: =100*(M101/OBR_MAR24_1.1!P101) -> 100 | X101: =100*(O101/OBR_MAR24_1.1!R101) -> 100 | Z101: =100*((S101/S100)-1) -> 1.5037297 | AA101: =100*((T101/T100)-1) -> 2.7830053 | AB101: =100*((U101/U100)-1) -> 2.7145232 | AC101: =100*((V101/V100)-1) -> 1.9361483 | AD101: =100*((W101/W100)-1) -> 1.2534992 | AE101: =100*((X101/X100)-1) -> 2.1157327
B102: 2020 | C102: 1246.073 | D102: 475.618 | E102: 367.488 | F102: 66.087 | G102: 0.969 | H102: 2090.148 | I102: 1.316 | J102: 2091.464 | K102: 624.805 | L102: 2716.269 | M102: 611.981 | N102: 0 | O102: 2104.288 | P102: 2059.457 | S102: =100*(C102/OBR_MAR24_1.1!C102) -> 100.57573 | T102: =100*(D102/OBR_MAR24_1.1!D102) -> 121.03255 | U102: =100*(E102/OBR_MAR24_1.1!E102) -> 101.33211 | V102: =100*(K102/OBR_MAR24_1.1!N102) -> 99.866537 | W102: =100*(M102/OBR_MAR24_1.1!P102) -> 98.739579 | X102: =100*(O102/OBR_MAR24_1.1!R102) -> 105.08362 | Z102: =100*((S102/S101)-1) -> 0.5757341 | AA102: =100*((T102/T101)-1) -> 21.032555 | AB102: =100*((U102/U101)-1) -> 1.3321127 | AC102: =100*((V102/V101)-1) -> -0.13346333 | AD102: =100*((W102/W101)-1) -> -1.2604208 | AE102: =100*((X102/X101)-1) -> 5.0836234
... B110: 2028 | C110: 1994.5487 | D110: 646.28576 | E110: 528.36665 | F110: 89.980388 | G110: -6.2847884 | H110: 3162.9163 | I110: 1.9076925 | J110: 3164.824 | K110: 883.1079 | L110: 4047.9319 | M110: 893.56377 | N110: 24.505239 | O110: 3178.8734 | P110: 3124.9691 | S110: =100*(C110/OBR_MAR24_1.1!C110) -> 130.3818 | T110: =100*(D110/OBR_MAR24_1.1!D110) -> 125.06673 | U110: =100*(E110/OBR_MAR24_1.1!E110) -> 122.51205 | V110: =100*(K110/OBR_MAR24_1.1!N110) -> 122.38217 | W110: =100*(M110/OBR_MAR24_1.1!P110) -> 119.53123 | X110: =100*(O110/OBR_MAR24_1.1!R110) -> 128.78834 | Z110: =100*((S110/S109)-1) -> 2.0144111 | AA110: =100*((T110/T109)-1) -> 1.631406 | AB110: =100*((U110/U109)-1) -> 1.5448238 | AC110: =100*((V110/V109)-1) -> 1.5651939 | AD110: =100*((W110/W109)-1) -> 1.3574075 | AE110: =100*((X110/X109)-1) -> 1.923023
B111: 2008-09 | C111: 1007.591 | D111: 329.006 | E111: 275.104 | F111: 49.512 | G111: 0.815 | H111: 1612.516 | I111: -7.375 | J111: 1605.141 | K111: 437.016 | L111: 2042.157 | M111: 459.366 | N111: 0 | O111: 1582.791 | P111: 1555.396 | S111: =100*(C111/OBR_MAR24_1.1!C111) -> 84.829481 | T111: =100*(D111/OBR_MAR24_1.1!D111) -> 87.191093 | U111: =100*(E111/OBR_MAR24_1.1!E111) -> 85.340348 | V111: =100*(K111/OBR_MAR24_1.1!N111) -> 80.437624 | W111: =100*(M111/OBR_MAR24_1.1!P111) -> 88.594153 | X111: =100*(O111/OBR_MAR24_1.1!R111) -> 83.434024
B112: 2009-10 | C112: 997.116 | D112: 343.189 | E112: 248.499 | F112: 52.224 | G112: 0.852 | H112: 1589.656 | I112: -12.172 | J112: 1577.484 | K112: 423.391 | L112: 2000.875 | M112: 442.699 | N112: 0 | O112: 1558.176 | P112: 1552.275 | S112: =100*(C112/OBR_MAR24_1.1!C112) -> 85.06248 | T112: =100*(D112/OBR_MAR24_1.1!D112) -> 90.113459 | U112: =100*(E112/OBR_MAR24_1.1!E112) -> 85.369323 | V112: =100*(K112/OBR_MAR24_1.1!N112) -> 82.775522 | W112: =100*(M112/OBR_MAR24_1.1!P112) -> 87.77667 | X112: =100*(O112/OBR_MAR24_1.1!R112) -> 84.579822
B113: 2010-11 | C113: 1041.559 | D113: 348.93 | E113: 259.052 | F113: 51.427 | G113: -1.093 | H113: 1648.448 | I113: -1.781 | J113: 1646.667 | K113: 482.208 | L113: 2128.875 | M113: 501.703 | N113: 0 | O113: 1627.172 | P113: 1629.445 | S113: =100*(C113/OBR_MAR24_1.1!C113) -> 86.832836 | T113: =100*(D113/OBR_MAR24_1.1!D113) -> 91.290834 | U113: =100*(E113/OBR_MAR24_1.1!E113) -> 84.708452 | V113: =100*(K113/OBR_MAR24_1.1!N113) -> 86.872741 | W113: =100*(M113/OBR_MAR24_1.1!P113) -> 91.679123 | X113: =100*(O113/OBR_MAR24_1.1!R113) -> 86.174186
B114: 2011-12 | C114: 1069.406 | D114: 348.529 | E114: 265.089 | F114: 46.627 | G114: 1.279 | H114: 1684.303 | I114: 2.483 | J114: 1686.786 | K114: 529.028 | L114: 2215.814 | M114: 543.252 | N114: 0 | O114: 1672.562 | P114: 1675.315 | S114: =100*(C114/OBR_MAR24_1.1!C114) -> 89.706614 | T114: =100*(D114/OBR_MAR24_1.1!D114) -> 91.123219 | U114: =100*(E114/OBR_MAR24_1.1!E114) -> 86.043553 | V114: =100*(K114/OBR_MAR24_1.1!N114) -> 90.648609 | W114: =100*(M114/OBR_MAR24_1.1!P114) -> 96.568176 | X114: =100*(O114/OBR_MAR24_1.1!R114) -> 87.69316
B115: 2012-13 | C115: 1113.172 | D115: 354.138 | E115: 269.372 | F115: 43.658 | G115: 2.369 | H115: 1739.051 | I115: 6.262 | J115: 1745.313 | K115: 524.297 | L115: 2269.61 | M115: 542.496 | N115: 0 | O115: 1727.114 | P115: 1702.767 | S115: =100*(C115/OBR_MAR24_1.1!C115) -> 91.280343 | T115: =100*(D115/OBR_MAR24_1.1!D115) -> 92.256112 | U115: =100*(E115/OBR_MAR24_1.1!E115) -> 87.384108 | V115: =100*(K115/OBR_MAR24_1.1!N115) -> 90.586422 | W115: =100*(M115/OBR_MAR24_1.1!P115) -> 95.219841 | X115: =100*(O115/OBR_MAR24_1.1!R115) -> 89.302412
B116: 2013-14 | C116: 1164.913 | D116: 362.069 | E116: 292.68 | F116: 45.912 | G116: 7.745 | H116: 1827.407 | I116: 4.435 | J116: 1831.842 | K116: 536.091 | L116: 2367.933 | M116: 566.683 | N116: 0 | O116: 1801.25 | P116: 1774.7 | S116: =100*(C116/OBR_MAR24_1.1!C116) -> 93.114377 | T116: =100*(D116/OBR_MAR24_1.1!D116) -> 92.847966 | U116: =100*(E116/OBR_MAR24_1.1!E116) -> 89.17244 | V116: =100*(K116/OBR_MAR24_1.1!N116) -> 91.966952 | W116: =100*(M116/OBR_MAR24_1.1!P116) -> 94.974911 | X116: =100*(O116/OBR_MAR24_1.1!R116) -> 91.020491
B117: 2014-15 | C117: 1207.424 | D117: 370.792 | E117: 315.035 | F117: 50.626 | G117: 7.169 | H117: 1900.42 | I117: 18.933 | J117: 1919.353 | K117: 533.25 | L117: 2452.603 | M117: 573.343 | N117: 0 | O117: 1879.26 | P117: 1841.848 | S117: =100*(C117/OBR_MAR24_1.1!C117) -> 93.883321 | T117: =100*(D117/OBR_MAR24_1.1!D117) -> 93.212065 | U117: =100*(E117/OBR_MAR24_1.1!E117) -> 90.175666 | V117: =100*(K117/OBR_MAR24_1.1!N117) -> 89.386889 | W117: =100*(M117/OBR_MAR24_1.1!P117) -> 90.506454 | X117: =100*(O117/OBR_MAR24_1.1!R117) -> 92.12673
B118: 2015-16 | C118: 1241.449 | D118: 376.402 | E118: 337.155 | F118: 51.402 | G118: -0.866 | H118: 1954.14 | I118: 3.232 | J118: 1957.372 | K118: 536.701 | L118: 2494.073 | M118: 562.63 | N118: 0 | O118: 1931.443 | P118: 1884.888 | S118: =100*(C118/OBR_MAR24_1.1!C118) -> 93.767296 | T118: =100*(D118/OBR_MAR24_1.1!D118) -> 93.224193 | U118: =100*(E118/OBR_MAR24_1.1!E118) -> 90.864868 | V118: =100*(K118/OBR_MAR24_1.1!N118) -> 87.111654 | W118: =100*(M118/OBR_MAR24_1.1!P118) -> 86.357183 | X118: =100*(O118/OBR_MAR24_1.1!R118) -> 92.78985
B119: 2016-17 | C119: 1302.659 | D119: 384.469 | E119: 363.126 | F119: 51.719 | G119: 0.071 | H119: 2050.325 | I119: 2.36 | J119: 2052.685 | K119: 597.001 | L119: 2649.686 | M119: 633.845 | N119: 0 | O119: 2015.841 | P119: 1979.375 | S119: =100*(C119/OBR_MAR24_1.1!C119) -> 95.183603 | T119: =100*(D119/OBR_MAR24_1.1!D119) -> 94.891021 | U119: =100*(E119/OBR_MAR24_1.1!E119) -> 92.998586 | V119: =100*(K119/OBR_MAR24_1.1!N119) -> 93.481076 | W119: =100*(M119/OBR_MAR24_1.1!P119) -> 93.079451 | X119: =100*(O119/OBR_MAR24_1.1!R119) -> 94.902853
B120: 2017-18 | C120: 1351.001 | D120: 390.245 | E120: 383.328 | F120: 58.796 | G120: 1.727 | H120: 2126.301 | I120: 1.959 | J120: 2128.26 | K120: 650.894 | L120: 2779.154 | M120: 679.332 | N120: 0 | O120: 2099.822 | P120: 2073.281 | S120: =100*(C120/OBR_MAR24_1.1!C120) -> 97.068616 | T120: =100*(D120/OBR_MAR24_1.1!D120) -> 95.605637 | U120: =100*(E120/OBR_MAR24_1.1!E120) -> 95.580385 | V120: =100*(K120/OBR_MAR24_1.1!N120) -> 95.693672 | W120: =100*(M120/OBR_MAR24_1.1!P120) -> 96.741862 | X120: =100*(O120/OBR_MAR24_1.1!R120) -> 96.386795
B121: 2018-19 | C121: 1402.695 | D121: 403.105 | E121: 392.489 | F121: 59.888 | G121: 14.068 | H121: 2212.357 | I121: 7.126 | J121: 2219.483 | K121: 684.736 | L121: 2904.219 | M121: 733.787 | N121: 0 | O121: 2170.432 | P121: 2149.137 | S121: =100*(C121/OBR_MAR24_1.1!C121) -> 98.888932 | T121: =100*(D121/OBR_MAR24_1.1!D121) -> 97.474308 | U121: =100*(E121/OBR_MAR24_1.1!E121) -> 98.229074 | V121: =100*(K121/OBR_MAR24_1.1!N121) -> 98.850867 | W121: =100*(M121/OBR_MAR24_1.1!P121) -> 99.139372 | X121: =100*(O121/OBR_MAR24_1.1!R121) -> 98.419168
B122: 2019-20 | C122: 1419.343 | D122: 432.7 | E122: 403.355 | F122: 61.6 | G122: -7.744 | H122: 2247.654 | I122: -6.062 | J122: 2241.592 | K122: 708.194 | L122: 2949.786 | M122: 709.08 | N122: 0 | O122: 2240.706 | P122: 2230.23 | S122: =100*(C122/OBR_MAR24_1.1!C122) -> 100.19123 | T122: =100*(D122/OBR_MAR24_1.1!D122) -> 101.83525 | U122: =100*(E122/OBR_MAR24_1.1!E122) -> 100.45977 | V122: =100*(K122/OBR_MAR24_1.1!N122) -> 100.38484 | W122: =100*(M122/OBR_MAR24_1.1!P122) -> 99.981247 | X122: =100*(O122/OBR_MAR24_1.1!R122) -> 100.73409
... B131: 2028-29 | C131: 2014.0236 | D131: 651.60853 | E131: 531.84159 | F131: 89.765037 | G131: -6.3090037 | H131: 3191.1648 | I131: 2.0184481 | J131: 3193.1832 | K131: 888.30339 | L131: 4081.4866 | M131: 898.63426 | N131: 24.623226 | O131: 3207.4756 | P131: 3153.3615 | S131: =100*(C131/OBR_MAR24_1.1!C131) -> 131.03369 | T131: =100*(D131/OBR_MAR24_1.1!D131) -> 125.57958 | U131: =100*(E131/OBR_MAR24_1.1!E131) -> 122.98416 | V131: =100*(K131/OBR_MAR24_1.1!N131) -> 122.90107 | W131: =100*(M131/OBR_MAR24_1.1!P131) -> 119.95437 | X131: =100*(O131/OBR_MAR24_1.1!R131) -> 129.40843
B132: Definitions:
B133: Household and non-profit institutions serving households final consumption expenditure (ONS Economic Accounts Table 1.1.2, identifier: ABJQ + HAYE)
B134: General government final consumption (ONS Economic Accounts Table 1.1.2, identifier: NMRP)
B135: Total gross fixed capital formation (ONS Economic Accounts Table 1.1.2, identifier: NPQS)
B136: General government investment (ONS Economic Accounts Table 1.1.8, identifier: RPZG)
B137: Net acquisitions of valuables (ONS Economic Accounts Table 1.1.2, identifier: NPJQ)
B138: Final domestic demand is the sum of private consumption, government consumption, fixed investment and net acquisition of valuables
B139: Change in inventories (ONS Economic Accounts Table 1.1.2, identifier: CAEX)
B140: Total domestic demand is the sum of final domestic demand and change in inventories
B141: Total exports (ONS Economic Accounts Table 1.1.2, identifier: IKBH)
B142: Total final expenditure (ONS Economic Accounts Table 1.1.2, identifier: ABMF)
B143: Total imports (ONS Economic Accounts Table 1.1.2, identifier: IKBI)
... B146: Gross national income at market prices (ONS Economic Accounts Table 1.1.1, identifier: ABMZ)

Sheet OBR_MAR24_ST4.3
A1: Back to contents
B2: 4.3 Consistent historical RDEL and CDEL series
E3: Outturn | U3: Forecast
E4: 2007-08 | F4: 2008-09 | G4: 2009-10 | H4: 2010-11 | I4: 2011-12 | J4: 2012-13 | K4: 2013-14 | L4: 2014-15 | M4: 2015-16 | N4: 2016-17 | O4: 2017-18 | P4: 2018-19 | Q4: 2019-20 | R4: 2020-21 | S4: 2021-22 | T4: 2022-23 | U4: 2023-24 | V4: 2024-25 | W4: 2025-26 | X4: 2026-27 | Y4: 2027-28 | Z4: 2028-29
B6: PSCE in RDEL adjusted to remove historical discontinuities
D7: PSCE in RDEL (£ billion) | E7: 256.0776 | F7: 267.99918 | G7: 285.18699 | H7: 291.11867 | I7: 287.03644 | J7: 283.14997 | K7: 287.61511 | L7: 289.46 | M7: 288.05418 | N7: 291.44417 | O7: 294.71997 | P7: 301.60796 | Q7: 324.08233 | R7: 410.82123 | S7: 401.25719 | T7: 407.4577 | U7: 422.94449 | V7: 430.19538 | W7: 440.03535 | X7: 452.28089 | Y7: 465.55777 | Z7: 479.15889
D8: PSCE in RDEL (£ billion, 2023-24 prices) | E8: 380.92762 | F8: 384.76717 | G8: 404.14663 | H8: 405.01246 | I8: 392.5011 | J8: 380.14096 | K8: 378.81801 | L8: 376.6957 | M8: 372.13954 | N8: 368.18728 | O8: 366.62728 | P8: 367.47458 | Q8: 385.74268 | R8: 463.77569 | S8: 456.63364 | T8: 434.12333 | U8: 422.94449 | V8: 426.76485 | W8: 430.71952 | X8: 435.11941 | Y8: 439.65812 | Z8: 443.9227
D9: Real PSCE in RDEL growth rate (per cent) | F9: 1.007946 | G9: 5.0366735 | H9: 0.21423626 | I9: -3.0891301 | J9: -3.1490707 | K9: -0.3480157 | L9: -0.56024558 | M9: -1.2095077 | N9: -1.0620373 | O9: -0.42369544 | P9: 0.23110693 | Q9: 4.9712533 | R9: 20.229292 | S9: -1.5399793 | T9: -4.9296216 | U9: -2.5750382 | V9: 0.90327775 | W9: 0.92666254 | X9: 1.0215207 | Y9: 1.0430945 | Z9: 0.96997677
D10: PSCE in RDEL (per cent of GDP) | E10: 16.34162 | F10: 16.925615 | G10: 18.265633 | H10: 17.883927 | I10: 17.154488 | J10: 16.411266 | K10: 15.944487 | L10: 15.434541 | M10: 14.908865 | N10: 14.473751 | O10: 14.042255 | P10: 13.875473 | Q10: 14.438896 | R10: 19.702863 | S10: 16.988602 | T10: 15.961439 | U10: 15.483994 | V10: 15.443467 | W10: 15.30525 | X10: 15.152641 | Y10: 15.044731 | Z10: 14.938817
D11: Real PSCE in RDEL per capita | E11: 6193.1143 | F11: 6207.1735 | G11: 6471.7565 | H11: 6433.1857 | I11: 6186.7218 | J11: 5953.1669 | K11: 5892.3547 | L11: 5814.1698 | M11: 5697.8739 | N11: 5595.9765 | O11: 5539.1387 | P11: 5520.0193 | Q11: 5765.6577 | R11: 6915.7804 | S11: 6783.7111 | T11: 6388.0887 | U11: 6166.2659 | V11: 6172.6818 | W11: 6195.1797 | X11: 6226.8892 | Y11: 6259.1505 | Z11: 6287.2179
B12: PSGI in CDEL adjusted to remove historical discontinuities
D13: PSGI in CDEL (£ billion) | E13: 48.393903 | F13: 52.202338 | G13: 59.403747 | H13: 50.944261 | I13: 44.004185 | J13: 42.630329 | K13: 46.07875 | L13: 49.976395 | M13: 48.113457 | N13: 49.13382 | O13: 52.589609 | P13: 56.195964 | Q13: 58.971053 | R13: 75.520456 | S13: 77.158314 | T13: 89.791733 | U13: 95.583786 | V13: 99.20003 | W13: 98.062828 | X13: 98.348124 | Y13: 98.339717 | Z13: 97.358047
D14: PSGI in CDEL (£ billion, 2023-24 prices) | E14: 71.988234 | F14: 74.947041 | G14: 84.182747 | H14: 70.875084 | I14: 60.172467 | J14: 57.233044 | K14: 60.690346 | L14: 65.037979 | M14: 62.158167 | N14: 62.071741 | O14: 65.420696 | P14: 68.468315 | Q14: 70.190966 | R14: 85.254969 | S14: 87.80673 | T14: 95.668055 | U14: 95.583786 | V14: 98.408974 | W14: 95.986775 | X14: 94.616373 | Y14: 92.868935 | Z14: 90.19857
D15: Real PSGI in CDEL growth rate (per cent) | F15: 4.1101265 | G15: 12.322975 | H15: -15.808064 | I15: -15.100676 | J15: -4.8849975 | K15: 6.0407444 | L15: 7.1636329 | M15: -4.4278934 | N15: -0.13904125 | O15: 5.3952971 | P15: 4.658493 | Q15: 2.5159832 | R15: 21.461455 | S15: 2.9930934 | T15: 8.9529874 | U15: -0.088084844 | V15: 2.955719 | W15: -2.4613599 | X15: -1.4276985 | Y15: -1.8468666 | Z15: -2.8754127
D16: PSGI in CDEL (per cent of GDP) | E16: 3.0882622 | F16: 3.2968634 | G16: 3.8046863 | H16: 3.1295946 | I16: 2.6298726 | J16: 2.4708379 | K16: 2.5544626 | L16: 2.6648336 | M16: 2.4902157 | N16: 2.4400923 | O16: 2.5056894 | P16: 2.585295 | Q16: 2.6273476 | R16: 3.6219383 | S16: 3.2667624 | T16: 3.5174332 | U16: 3.4993215 | V16: 3.5611549 | W16: 3.4108079 | X16: 3.2949299 | Y16: 3.177897 | Z16: 3.0353481
D17: Real PSGI in CDEL per capita | E17: 1170.3834 | F17: 1209.067 | G17: 1348.0509 | H17: 1125.7742 | I17: 948.45675 | J17: 896.29347 | K17: 944.01278 | L17: 1003.839 | M17: 951.71127 | N17: 943.41122 | O17: 988.39974 | P17: 1028.4968 | Q17: 1049.1374 | R17: 1271.3142 | S17: 1304.4494 | T17: 1407.7475 | U17: 1393.5518 | V17: 1423.377 | W17: 1380.6092 | X17: 1354.0321 | Y17: 1322.1197 | Z17: 1277.4703
B18: Unadjusted aggregate spending series (£ billion)
D19: PSCE in RDEL | E19: 286.76629 | F19: 299.94735 | G19: 318.08264 | H19: 324.94499 | I19: 313.2674 | J19: 309.98999 | K19: 308.71881 | L19: 310.64617 | M19: 309.74896 | N19: 286.70991 | O19: 288.21221 | P19: 294.38957 | Q19: 320.2342 | R19: 420.93294 | S19: 408.75118 | T19: 407.4577 | U19: 422.94449 | V19: 430.19538 | W19: 440.03535 | X19: 452.28089 | Y19: 465.55777 | Z19: 479.15889
D20: PSGI in CDEL | E20: 43.189293 | F20: 47.242335 | G20: 54.660402 | H20: 42.333613 | I20: 42.325888 | J20: 39.479622 | K20: 41.356102 | L20: 45.53985 | M20: 44.195856 | N20: 42.526187 | O20: 44.997352 | P20: 50.808509 | Q20: 57.891053 | R20: 75.520456 | S20: 77.158314 | T20: 89.791733 | U20: 95.583786 | V20: 99.20003 | W20: 98.062828 | X20: 98.348124 | Y20: 98.339717 | Z20: 97.358047
D21: TME in DEL | E21: 329.95559 | F21: 347.18969 | G21: 372.74304 | H21: 367.2786 | I21: 355.59329 | J21: 349.46961 | K21: 350.07491 | L21: 356.18602 | M21: 353.94481 | N21: 329.23609 | O21: 333.20956 | P21: 345.19808 | Q21: 378.12525 | R21: 496.4534 | S21: 485.90949 | T21: 497.24944 | U21: 518.52827 | V21: 529.39541 | W21: 538.09818 | X21: 550.62902 | Y21: 563.89749 | Z21: 576.51694
D22: PSCE in AME | E22: 278.13771 | F22: 299.39165 | G22: 315.68136 | H22: 337.63501 | I22: 357.9896 | J22: 372.96901 | K22: 385.90519 | L22: 394.50183 | M22: 406.19304 | N22: 440.75109 | O22: 455.58079 | P22: 466.81843 | Q22: 472.7258 | R22: 560.34306 | S22: 527.92882 | T22: 643.6143 | U22: 659.96315 | V22: 660.1941 | W22: 679.56195 | X22: 705.7294 | Y22: 725.75804 | Z22: 751.95568
D23: PSGI in AME1 | E23: 19.994707 | F23: 38.893665 | G23: 32.560598 | H23: 39.626387 | I23: 32.000112 | J23: 28.462378 | K23: 30.778898 | L23: 37.70415 | M23: 36.131144 | N23: 43.523813 | O23: 51.738648 | P23: 45.841491 | Q23: 37.233947 | R23: 50.100544 | S23: 32.492686 | T23: 16.548267 | U23: 37.78248 | V23: 36.758702 | W23: 33.997042 | X23: 33.894631 | Y23: 33.406167 | Z23: 33.203153
D24: TME in AME1 | E24: 298.13241 | F24: 338.28531 | G24: 348.24196 | H24: 377.2614 | I24: 389.98971 | J24: 401.43139 | K24: 416.68409 | L24: 432.20598 | M24: 442.32419 | N24: 484.27491 | O24: 507.31944 | P24: 512.65992 | Q24: 509.95975 | R24: 610.4436 | S24: 560.42151 | T24: 660.16256 | U24: 697.74563 | V24: 696.9528 | W24: 713.55899 | X24: 739.62403 | Y24: 759.16421 | Z24: 785.15883
D25: PSCE | E25: 564.904 | F25: 599.339 | G25: 633.764 | H25: 662.58 | I25: 671.257 | J25: 682.959 | K25: 694.624 | L25: 705.148 | M25: 715.942 | N25: 727.461 | O25: 743.793 | P25: 761.208 | Q25: 792.96 | R25: 981.276 | S25: 936.68 | T25: 1051.072 | U25: 1082.9076 | V25: 1090.3895 | W25: 1119.5973 | X25: 1158.0103 | Y25: 1191.3158 | Z25: 1231.1146
D26: PSGI1 | E26: 63.184 | F26: 86.136 | G26: 87.221 | H26: 81.96 | I26: 74.326 | J26: 67.942 | K26: 72.135 | L26: 83.244 | M26: 80.327 | N26: 86.05 | O26: 96.736 | P26: 96.65 | Q26: 95.125 | R26: 125.621 | S26: 109.651 | T26: 106.34 | U26: 133.36627 | V26: 135.95873 | W26: 132.05987 | X26: 132.24276 | Y26: 131.74588 | Z26: 130.5612
D27: TME1 | E27: 628.088 | F27: 685.475 | G27: 720.985 | H27: 744.54 | I27: 745.583 | J27: 750.901 | K27: 766.759 | L27: 788.392 | M27: 796.269 | N27: 813.511 | O27: 840.529 | P27: 857.858 | Q27: 888.085 | R27: 1106.897 | S27: 1046.331 | T27: 1157.412 | U27: 1216.2739 | V27: 1226.3482 | W27: 1251.6572 | X27: 1290.253 | Y27: 1323.0617 | Z27: 1361.6758
B28: Nominal GDP, GDP deflator and population figures
E29: Outturn | U29: Forecast
E30: 2007-08 | F30: 2008-09 | G30: 2009-10 | H30: 2010-11 | I30: 2011-12 | J30: 2012-13 | K30: 2013-14 | L30: 2014-15 | M30: 2015-16 | N30: 2016-17 | O30: 2017-18 | P30: 2018-19 | Q30: 2019-20 | R30: 2020-21 | S30: 2021-22 | T30: 2022-23 | U30: 2023-24 | V30: 2024-25 | W30: 2025-26 | X30: 2026-27 | Y30: 2027-28
B31: Nominal GDP (£ billion) | E31: 1567.027 | F31: 1583.394 | G31: 1561.331 | H31: 1627.823 | I31: 1673.244 | J31: 1725.339 | K31: 1803.853 | L31: 1875.404 | M31: 1932.1 | N31: 2013.605 | O31: 2098.808 | P31: 2173.677 | Q31: 2244.509 | R31: 2085.084 | S31: 2361.92 | T31: 2552.763 | U31: 2731.4948 | V31: 2785.614 | W31: 2875.0616 | X31: 2984.8321 | Y31: 3094.4904 | Z31: 3207.4756
B32: GDP deflator | E32: 2.3696682 | F32: 3.6111111 | G32: 1.3106941 | H32: 1.8617021 | I32: 1.740644 | J32: 1.853436 | K32: 1.9316909 | L32: 1.2084592 | M32: 0.73270014 | N32: 2.262931 | O32: 1.5542677 | P32: 2.1011673 | Q32: 2.3628049 | R32: 5.435592 | S32: -0.80037665 | T32: 6.8106312 | U32: 6.544391 | V32: 0.80384499 | W32: 1.3481709 | X32: 1.7435226 | Y32: 1.872908 | Z32: 1.9327438
E33: Estimates | U33: Projections
B34: Population (thousand)2 | E34: 61508.25 | F34: 61987.5 | G34: 62447.75 | H34: 62956.75 | I34: 63442.5 | J34: 63855.25 | K34: 64289.75 | L34: 64789.25 | M34: 65312 | N34: 65795 | O34: 66188.5 | P34: 66571.25 | Q34: 66903.5 | R34: 67060.5 | S34: 67313.25 | T34: 67958.25 | U34: 68590.05 | V34: 69137.672 | W34: 69524.944 | X34: 69877.494 | Y34: 70242.459 | Z34: 70607.176
B35: Note: This table removes series discontinuities, where possible, so that the adjusted historical series are consistent with the latest forecast. This includes the major ONS classification changes and Treasury policy decisions to switch spending between DEL and AME.
B36: 1 Excluding the one-off adjustment for Royal Mail transfers in 2012-13.
B37: 2 Consistent with our economic forecast, the figures shown are based on the ONS's latest (2018-based) principal migration population estimates and projections.

Sheet OBR_NOV23_ST3.3
A1: Back to contents
B2: 3.3 Consistent historical RDEL and CDEL series
E3: Outturn | U3: Forecast
E4: 2007-08 | F4: 2008-09 | G4: 2009-10 | H4: 2010-11 | I4: 2011-12 | J4: 2012-13 | K4: 2013-14 | L4: 2014-15 | M4: 2015-16 | N4: 2016-17 | O4: 2017-18 | P4: 2018-19 | Q4: 2019-20 | R4: 2020-21 | S4: 2021-22 | T4: 2022-23 | U4: 2023-24 | V4: 2024-25 | W4: 2025-26 | X4: 2026-27 | Y4: 2027-28 | Z4: 2028-29
B6: PSCE in RDEL adjusted to remove historical discontinuities
D7: PSCE in RDEL (£ billion) | E7: 256.0776 | F7: 267.99918 | G7: 285.18699 | H7: 291.11867 | I7: 287.03644 | J7: 283.14997 | K7: 287.82011 | L7: 290.00803 | M7: 288.65014 | N7: 291.91609 | O7: 295.74844 | P7: 302.95704 | Q7: 325.88433 | R7: 423.34035 | S7: 408.75118 | T7: 411.5361 | U7: 426.51629 | V7: 435.45198 | W7: 445.2619 | X7: 456.91761 | Y7: 469.9419 | Z7: 483.64675
D8: PSCE in RDEL (£ billion, 2022-23 prices) | E8: 357.13233 | F8: 360.73203 | G8: 378.90092 | H8: 379.71267 | I8: 367.98285 | J8: 356.39481 | K8: 355.40764 | L8: 353.83341 | M8: 349.61504 | N8: 345.74677 | O8: 344.92477 | P8: 346.06069 | Q8: 363.65747 | R8: 448.05513 | S8: 436.00125 | T8: 411.5361 | U8: 401.99967 | V8: 403.65162 | W8: 405.79761 | X8: 409.76373 | Y8: 414.09624 | Z8: 418.3047
D9: Real PSCE in RDEL growth rate (per cent) | F9: 1.007946 | G9: 5.0366735 | H9: 0.21423626 | I9: -3.0891301 | J9: -3.1490707 | K9: -0.27698794 | L9: -0.44293643 | M9: -1.1921904 | N9: -1.1064379 | O9: -0.23774389 | P9: 0.32932261 | Q9: 5.0848836 | R9: 23.20801 | S9: -2.6902669 | T9: -5.6112569 | U9: -2.3172776 | V9: 0.41093293 | W9: 0.53164376 | X9: 0.97736535 | Y9: 1.0573185 | Z9: 1.0162987
D10: PSCE in RDEL (per cent of GDP) | E10: 16.34162 | F10: 16.925615 | G10: 18.265633 | H10: 17.883927 | I10: 17.154488 | J10: 16.411266 | K10: 15.955852 | L10: 15.463763 | M10: 14.93971 | N10: 14.497187 | O10: 14.091258 | P10: 13.937537 | Q10: 14.519181 | R10: 20.303275 | S10: 17.309315 | T10: 16.124595 | U10: 15.643395 | V10: 15.56348 | W10: 15.422815 | X10: 15.255742 | Y10: 15.131088 | Z10: 15.028711
D11: Real PSCE in RDEL per capita | E11: 5806.2508 | F11: 5819.4318 | G11: 6067.4872 | H11: 6031.3257 | I11: 5800.2577 | J11: 5581.2922 | K11: 5528.2162 | L11: 5461.2981 | M11: 5352.9985 | N11: 5254.9094 | O11: 5211.2493 | P11: 5198.3505 | Q11: 5435.5523 | R11: 6681.3569 | S11: 6477.1981 | T11: 6049.6958 | U11: 5861.9814 | V11: 5852.85 | W11: 5858.282 | X11: 5893.9975 | Y11: 5936.4146 | Z11: 5977.6135
B12: PSGI in CDEL adjusted to remove historical discontinuities
D13: PSGI in CDEL (£ billion) | E13: 48.393903 | F13: 52.202338 | G13: 59.403747 | H13: 50.944261 | I13: 44.004185 | J13: 42.630329 | K13: 46.07875 | L13: 49.976395 | M13: 48.113457 | N13: 49.13382 | O13: 52.589609 | P13: 56.195964 | Q13: 58.971053 | R13: 75.520456 | S13: 77.158314 | T13: 89.791733 | U13: 96.000288 | V13: 99.196273 | W13: 97.221725 | X13: 97.50902 | Y13: 97.597216 | Z13: 97.357557
D14: PSGI in CDEL (£ billion, 2022-23 prices) | E14: 67.491366 | F14: 70.265346 | G14: 78.924128 | H14: 66.447751 | I14: 56.413691 | J14: 53.657884 | K14: 56.899219 | L14: 60.975271 | M14: 58.275351 | N14: 58.194324 | O14: 61.334081 | P14: 64.191324 | Q14: 65.806367 | R14: 79.929372 | S14: 82.302202 | T14: 89.791733 | U14: 90.482086 | V14: 91.952128 | W14: 88.604804 | X14: 87.446093 | Y14: 85.999227 | Z14: 84.204273
D15: Real PSGI in CDEL growth rate (per cent) | F15: 4.1101265 | G15: 12.322975 | H15: -15.808064 | I15: -15.100676 | J15: -4.8849975 | K15: 6.0407444 | L15: 7.1636329 | M15: -4.4278934 | N15: -0.13904125 | O15: 5.3952971 | P15: 4.658493 | Q15: 2.5159832 | R15: 21.461455 | S15: 2.9686585 | T15: 9.1000377 | U15: 0.76883812 | V15: 1.6246773 | W15: -3.6402899 | X15: -1.3077293 | Y15: -1.6545808 | Z15: -2.0871743
D16: PSGI in CDEL (per cent of GDP) | E16: 3.0882622 | F16: 3.2968634 | G16: 3.8046863 | H16: 3.1295946 | I16: 2.6298726 | J16: 2.4708379 | K16: 2.5544626 | L16: 2.6648336 | M16: 2.4902157 | N16: 2.4400923 | O16: 2.5056894 | P16: 2.585295 | Q16: 2.6273476 | R16: 3.6219383 | S16: 3.2674098 | T16: 3.5181733 | U16: 3.5210154 | V16: 3.545372 | W16: 3.3675297 | X16: 3.2556689 | Y16: 3.1424141 | Z16: 3.0252629
D17: Real PSGI in CDEL per capita | E17: 1097.2734 | F17: 1133.5406 | G17: 1263.8426 | H17: 1055.4508 | I17: 889.20978 | J17: 840.30497 | K17: 885.04341 | L17: 941.13253 | M17: 892.261 | N17: 884.47943 | O17: 926.65766 | P17: 964.24995 | Q17: 983.60127 | R17: 1191.8994 | S17: 1222.6746 | T17: 1319.9636 | U17: 1319.4148 | V17: 1333.2834 | W17: 1279.1399 | X17: 1257.8152 | Y17: 1232.8706 | Z17: 1203.287
B18: Unadjusted aggregate spending series (£ billion)
D19: PSCE in RDEL | E19: 286.76629 | F19: 299.94735 | G19: 318.08264 | H19: 324.94499 | I19: 313.2674 | J19: 309.98999 | K19: 308.71881 | L19: 310.64617 | M19: 309.74896 | N19: 286.70991 | O19: 288.21221 | P19: 294.38957 | Q19: 320.2342 | R19: 420.93294 | S19: 408.75118 | T19: 411.5361 | U19: 426.51629 | V19: 435.45198 | W19: 445.2619 | X19: 456.91761 | Y19: 469.9419 | Z19: 483.64675
D20: PSGI in CDEL | E20: 43.189293 | F20: 47.242335 | G20: 54.660402 | H20: 42.333613 | I20: 42.325888 | J20: 39.479622 | K20: 41.356102 | L20: 45.53985 | M20: 44.195856 | N20: 42.526187 | O20: 44.997352 | P20: 50.808509 | Q20: 57.891053 | R20: 75.520456 | S20: 77.158314 | T20: 89.791733 | U20: 96.000288 | V20: 99.196273 | W20: 97.221725 | X20: 97.50902 | Y20: 97.597216 | Z20: 97.357557
D21: TME in DEL | E21: 329.95559 | F21: 347.18969 | G21: 372.74304 | H21: 367.2786 | I21: 355.59329 | J21: 349.46961 | K21: 350.07491 | L21: 356.18602 | M21: 353.94481 | N21: 329.23609 | O21: 333.20956 | P21: 345.19808 | Q21: 378.12525 | R21: 496.4534 | S21: 485.90949 | T21: 501.32784 | U21: 522.51658 | V21: 534.64825 | W21: 542.48363 | X21: 554.42663 | Y21: 567.53912 | Z21: 581.00431
D22: PSCE in AME | E22: 278.13771 | F22: 299.39165 | G22: 315.68136 | H22: 337.63501 | I22: 357.9896 | J22: 372.96901 | K22: 385.90519 | L22: 394.50183 | M22: 406.19304 | N22: 440.75109 | O22: 455.58079 | P22: 466.81843 | Q22: 472.7258 | R22: 560.34306 | S22: 527.62882 | T22: 634.9669 | U22: 662.97387 | V22: 667.08865 | W22: 688.98558 | X22: 713.8149 | Y22: 733.02481 | Z22: 758.82234
D23: PSGI in AME1 | E23: 19.994707 | F23: 38.893665 | G23: 32.560598 | H23: 39.626387 | I23: 32.000112 | J23: 28.462378 | K23: 30.778898 | L23: 37.70415 | M23: 36.131144 | N23: 43.523813 | O23: 51.738648 | P23: 45.841491 | Q23: 37.233947 | R23: 50.107544 | S23: 31.167686 | T23: 15.130267 | U23: 36.842212 | V23: 35.019618 | W23: 33.05696 | X23: 33.067782 | Y23: 33.000513 | Z23: 33.210587
D24: TME in AME1 | E24: 298.13241 | F24: 338.28531 | G24: 348.24196 | H24: 377.2614 | I24: 389.98971 | J24: 401.43139 | K24: 416.68409 | L24: 432.20598 | M24: 442.32419 | N24: 484.27491 | O24: 507.31944 | P24: 512.65992 | Q24: 509.95975 | R24: 610.4506 | S24: 558.79651 | T24: 650.09716 | U24: 699.81608 | V24: 702.10826 | W24: 722.04254 | X24: 746.88268 | Y24: 766.02532 | Z24: 792.03292
D25: PSCE | E25: 564.904 | F25: 599.339 | G25: 633.764 | H25: 662.58 | I25: 671.257 | J25: 682.959 | K25: 694.624 | L25: 705.148 | M25: 715.942 | N25: 727.461 | O25: 743.793 | P25: 761.208 | Q25: 792.96 | R25: 981.276 | S25: 936.38 | T25: 1046.503 | U25: 1089.4902 | V25: 1102.5406 | W25: 1134.2475 | X25: 1170.7325 | Y25: 1202.9667 | Z25: 1242.4691
D26: PSGI1 | E26: 63.184 | F26: 86.136 | G26: 87.221 | H26: 81.96 | I26: 74.326 | J26: 67.942 | K26: 72.135 | L26: 83.244 | M26: 80.327 | N26: 86.05 | O26: 96.736 | P26: 96.65 | Q26: 95.125 | R26: 125.628 | S26: 108.326 | T26: 104.922 | U26: 132.8425 | V26: 134.21589 | W26: 130.27869 | X26: 130.5768 | Y26: 130.59773 | Z26: 130.56814
D27: TME1 | E27: 628.088 | F27: 685.475 | G27: 720.985 | H27: 744.54 | I27: 745.583 | J27: 750.901 | K27: 766.759 | L27: 788.392 | M27: 796.269 | N27: 813.511 | O27: 840.529 | P27: 857.858 | Q27: 888.085 | R27: 1106.904 | S27: 1044.706 | T27: 1151.425 | U27: 1222.3327 | V27: 1236.7565 | W27: 1264.5262 | X27: 1301.3093 | Y27: 1333.5644 | Z27: 1373.0372
B28: Nominal GDP, GDP deflator and population figures
E29: Outturn | U29: Forecast
E30: 2007-08 | F30: 2008-09 | G30: 2009-10 | H30: 2010-11 | I30: 2011-12 | J30: 2012-13 | K30: 2013-14 | L30: 2014-15 | M30: 2015-16 | N30: 2016-17 | O30: 2017-18 | P30: 2018-19 | Q30: 2019-20 | R30: 2020-21 | S30: 2021-22 | T30: 2022-23 | U30: 2023-24 | V30: 2024-25 | W30: 2025-26 | X30: 2026-27 | Y30: 2027-28
B31: Nominal GDP (£ billion) | E31: 1567.027 | F31: 1583.394 | G31: 1561.331 | H31: 1627.823 | I31: 1673.244 | J31: 1725.339 | K31: 1803.853 | L31: 1875.404 | M31: 1932.1 | N31: 2013.605 | O31: 2098.808 | P31: 2173.677 | Q31: 2244.509 | R31: 2085.084 | S31: 2361.452 | T31: 2552.226 | U31: 2726.4944 | V31: 2797.9087 | W31: 2887.034 | X31: 2995.0533 | Y31: 3105.8037 | Z31: 3218.152
B32: GDP deflator | E32: 2.3696682 | F32: 3.6111111 | G32: 1.3106941 | H32: 1.8617021 | I32: 1.740644 | J32: 1.853436 | K32: 1.9316909 | L32: 1.2084592 | M32: 0.73270014 | N32: 2.262931 | O32: 1.5542677 | P32: 2.1011673 | Q32: 2.3628049 | R32: 5.435592 | S32: -0.77683616 | T32: 6.6666667 | U32: 6.0986679 | V32: 1.6772141 | W32: 1.7120683 | X32: 1.6244776 | Y32: 1.7743882 | Z32: 1.8808728
E33: Estimates | R33: Projections
B34: Population (thousand)2 | E34: 61508.25 | F34: 61987.5 | G34: 62447.75 | H34: 62956.75 | I34: 63442.5 | J34: 63855.25 | K34: 64289.75 | L34: 64789.25 | M34: 65312 | N34: 65795 | O34: 66188.5 | P34: 66571.25 | Q34: 66903.5 | R34: 67060.5 | S34: 67313.25 | T34: 68025.917 | U34: 68577.439 | V34: 68966.677 | W34: 69269.047 | X34: 69522.21 | Y34: 69755.276 | Z34: 69978.545
B35: Note: This table removes series discontinuities, where possible, so that the adjusted historical series are consistent with the latest forecast. This includes the major ONS classification changes and Treasury policy decisions to switch spending between DEL and AME.
B36: 1 Excluding the one-off adjustment for Royal Mail transfers in 2012-13.
B37: 2 Consistent with our economic forecast, the figures shown are based on the ONS's latest (2020-based) year ending June 2022 estimated international migration variant estimates and projections.

Sheet OBR_MAR23_ST3.3
A1: Back to contents
B2: 3.3 Consistent historical RDEL and CDEL series
E3: Outturn | T3: Forecast
E4: 2007-08 | F4: 2008-09 | G4: 2009-10 | H4: 2010-11 | I4: 2011-12 | J4: 2012-13 | K4: 2013-14 | L4: 2014-15 | M4: 2015-16 | N4: 2016-17 | O4: 2017-18 | P4: 2018-19 | Q4: 2019-20 | R4: 2020-21 | S4: 2021-22 | T4: 2022-23 | U4: 2023-24 | V4: 2024-25 | W4: 2025-26 | X4: 2026-27 | Y4: 2027-28
B6: PSCE in RDEL adjusted to remove historical discontinuities
D7: PSCE in RDEL (£ billion) | E7: 256.0776 | F7: 267.99918 | G7: 285.18699 | H7: 670.35004 | I7: 287.03644 | J7: 283.14997 | K7: 287.82011 | L7: 290.00803 | M7: 288.65014 | N7: 291.91609 | O7: 296.73851 | P7: 304.20241 | Q7: 327.07645 | R7: 431.77582 | S7: 413.76045 | T7: 415.47476 | U7: 421.6874 | V7: 426.65635 | W7: 435.84566 | X7: 446.15051 | Y7: 458.91766
D8: PSCE in RDEL (£ billion, 2022-23 prices) | E8: 355.58005 | F8: 359.16411 | G8: 377.25403 | H8: 872.14252 | I8: 366.86407 | J8: 355.83142 | K8: 354.2783 | L8: 353.01151 | M8: 348.71683 | N8: 345.60915 | O8: 345.49964 | P8: 347.88773 | Q8: 364.5935 | R8: 452.91122 | S8: 437.27649 | T8: 415.47476 | U8: 411.30344 | V8: 409.71946 | W8: 414.54911 | X8: 419.32989 | Y8: 424.31872
D9: Real PSCE in RDEL growth rate (per cent) | F9: 1.007946 | G9: 5.0366735 | H9: 131.18176 | I9: -57.935307 | J9: -3.0072856 | K9: -0.43647559 | L9: -0.3575699 | M9: -1.2165847 | N9: -0.8911739 | O9: -0.031685752 | P9: 0.69119658 | Q9: 4.8020586 | R9: 24.223613 | S9: -3.4520512 | T9: -4.9858006 | U9: -1.0039871 | V9: -0.38511361 | W9: 1.1787713 | X9: 1.1532469 | Y9: 1.1897161
D10: PSCE in RDEL (per cent of GDP) | E10: 16.34162 | F10: 16.925615 | G10: 18.265633 | H10: 41.113814 | I10: 17.173907 | J10: 16.395643 | K10: 15.936036 | L10: 15.459699 | M10: 14.897533 | N10: 14.430353 | O10: 14.110751 | P10: 13.972044 | Q10: 14.54046 | R10: 20.706646 | S10: 17.699036 | T10: 16.589725 | U10: 16.387469 | V10: 15.987334 | W10: 15.795726 | X10: 15.656245 | Y10: 15.557619
D11: Real PSCE in RDEL per capita | E11: 5781.014 | F11: 5794.1376 | G11: 6041.1149 | H11: 13853.042 | I11: 5782.6232 | J11: 5572.4693 | K11: 5510.6499 | L11: 5448.6124 | M11: 5339.2459 | N11: 5252.8179 | O11: 5219.9347 | P11: 5225.7953 | Q11: 5449.543 | R11: 6741.556 | S11: 6480.1623 | T11: 6122.2512 | U11: 6027.4022 | V11: 5977.6484 | W11: 6023.5987 | X11: 6070.7339 | Y11: 6122.3009
B12: PSGI in CDEL adjusted to remove historical discontinuities
D13: PSGI in CDEL (£ billion) | E13: 48.393903 | F13: 52.202338 | G13: 59.403747 | H13: 50.944261 | I13: 44.004185 | J13: 42.630329 | K13: 46.07875 | L13: 49.976395 | M13: 48.113457 | N13: 49.13382 | O13: 52.597202 | P13: 56.190224 | Q13: 58.971053 | R13: 75.520266 | S13: 76.989229 | T13: 86.31461 | U13: 96.111651 | V13: 96.888973 | W13: 97.078752 | X13: 97.479447 | Y13: 97.627423
D14: PSGI in CDEL (£ billion, 2022-23 prices) | E14: 67.198015 | F14: 69.959938 | G14: 78.581084 | H14: 66.279784 | I14: 56.242177 | J14: 53.573062 | K14: 56.718418 | L14: 60.833635 | M14: 58.125633 | N14: 58.171162 | O14: 61.240161 | P14: 64.259481 | Q14: 65.735282 | R14: 79.216978 | S14: 81.364906 | T14: 86.31461 | U14: 93.744924 | V14: 93.042791 | W14: 92.335233 | X14: 91.619408 | Y14: 90.267051
D15: Real PSGI in CDEL growth rate (per cent) | F15: 4.1101265 | G15: 12.322975 | H15: -15.654276 | I15: -15.144296 | J15: -4.7457537 | K15: 5.8711527 | L15: 7.2555218 | M15: -4.4514888 | N15: 0.078328505 | O15: 5.2758095 | P15: 4.9302927 | Q15: 2.2966282 | R15: 20.509071 | S15: 2.7114489 | T15: 6.0833408 | U15: 8.6084079 | V15: -0.74898257 | W15: -0.76046455 | X15: -0.77524654 | Y15: -1.4760596
D16: PSGI in CDEL (per cent of GDP) | E16: 3.0882622 | F16: 3.2968634 | G16: 3.8046863 | H16: 3.1245062 | I16: 2.6328496 | J16: 2.4684858 | K16: 2.5512902 | L16: 2.6641332 | M16: 2.4831855 | N16: 2.4288431 | O16: 2.5011449 | P16: 2.580822 | Q16: 2.621608 | R16: 3.6217208 | S16: 3.2932948 | T16: 3.4465046 | U16: 41.5079 | V16: 3.630548 | W16: 3.5182852 | X16: 3.4207338 | Y16: 3.3096356
D17: Real PSGI in CDEL per capita | E17: 1092.5041 | F17: 1128.6136 | G17: 1258.3493 | H17: 1052.7828 | I17: 886.50632 | J17: 838.97662 | K17: 882.23112 | L17: 938.94643 | M17: 889.96866 | N17: 884.12739 | O17: 925.2387 | P17: 965.27376 | Q17: 982.53876 | R17: 1179.1399 | S17: 1205.7767 | T17: 1271.8937 | U17: 1104.3477 | V17: 1357.4583 | W17: 1341.6755 | X17: 1326.395 | Y17: 1302.422
B18: Unadjusted aggregate spending series (£ billion)
D19: PSCE in RDEL | E19: 286.76629 | F19: 299.94735 | G19: 318.08264 | H19: 324.94499 | I19: 313.2674 | J19: 309.98999 | K19: 308.71881 | L19: 310.64617 | M19: 309.74896 | N19: 286.70991 | O19: 289.20228 | P19: 295.63494 | Q19: 321.42632 | R19: 429.36841 | S19: 413.76045 | T19: 415.47476 | U19: 421.6874 | V19: 426.65635 | W19: 435.84566 | X19: 446.15051 | Y19: 458.91766
D20: PSGI in CDEL | E20: 43.189293 | F20: 47.242335 | G20: 54.660402 | H20: 42.333613 | I20: 42.325888 | J20: 39.479622 | K20: 41.356102 | L20: 45.53985 | M20: 44.195856 | N20: 42.526187 | O20: 45.004945 | P20: 50.802769 | Q20: 57.891053 | R20: 75.520266 | S20: 76.989229 | T20: 86.31461 | U20: 96.111651 | V20: 96.888973 | W20: 97.078752 | X20: 97.479447 | Y20: 97.627423
D21: TME in DEL | E21: 329.95559 | F21: 347.18969 | G21: 372.74304 | H21: 367.2786 | I21: 355.59329 | J21: 349.46961 | K21: 350.07491 | L21: 356.18602 | M21: 353.94481 | N21: 329.23609 | O21: 334.20722 | P21: 346.43771 | Q21: 379.31737 | R21: 504.88868 | S21: 490.74968 | T21: 501.78937 | U21: 517.79905 | V21: 523.54532 | W21: 532.92441 | X21: 543.62996 | Y21: 556.54508
D22: PSCE in AME | E22: 278.13771 | F22: 299.39165 | G22: 315.68136 | H22: 315.52936 | I22: 336.94285 | J22: 350.62778 | K22: 385.44019 | L22: 394.04783 | M22: 405.40704 | N22: 439.69709 | O22: 453.85772 | P22: 465.15806 | Q22: 468.22068 | R22: 551.06659 | S22: 521.92355 | T22: 640.33843 | U22: 633.89555 | V22: 629.00131 | W22: 644.33519 | X22: 669.49407 | Y22: 688.95594
D23: PSGI in AME1 | E23: 19.994707 | F23: 38.893665 | G23: 32.560598 | H23: 38.647387 | I23: 32.495112 | J23: 29.727378 | K23: 33.230898 | L23: 36.92915 | M23: 35.535144 | N23: 44.887813 | O23: 48.384055 | P23: 45.720231 | Q23: 36.349947 | R23: 50.128734 | S23: 27.397771 | T23: 29.895362 | U23: 37.47543 | V23: 36.593392 | W23: 36.354933 | X23: 34.04122 | Y23: 34.038546
D24: TME in AME1 | E24: 298.13241 | F24: 338.28531 | G24: 348.24196 | H24: 354.17675 | I24: 369.43796 | J24: 380.35516 | K24: 418.67109 | L24: 430.97698 | M24: 440.94219 | N24: 484.58491 | O24: 502.24178 | P24: 510.87829 | Q24: 504.57063 | R24: 601.19532 | S24: 549.32132 | T24: 670.23379 | U24: 671.37098 | V24: 665.59471 | W24: 680.69012 | X24: 703.53529 | Y24: 722.99449
D25: PSCE | E25: 564.904 | F25: 599.339 | G25: 633.764 | H25: 640.47435 | I25: 650.21025 | J25: 660.61776 | K25: 694.159 | L25: 704.694 | M25: 715.156 | N25: 726.407 | O25: 743.06 | P25: 760.793 | Q25: 789.647 | R25: 980.435 | S25: 935.684 | T25: 1055.8132 | U25: 1055.5829 | V25: 1055.6577 | W25: 1080.1808 | X25: 1115.6446 | Y25: 1147.8736
D26: PSGI1 | E26: 63.184 | F26: 86.136 | G26: 87.221 | H26: 80.981 | I26: 74.821 | J26: 69.207 | K26: 74.587 | L26: 82.469 | M26: 79.731 | N26: 87.414 | O26: 93.389 | P26: 96.523 | Q26: 94.241 | R26: 125.649 | S26: 104.387 | T26: 116.20997 | U26: 133.58708 | V26: 133.48237 | W26: 133.43368 | X26: 131.52067 | Y26: 131.66597
D27: TME1 | E27: 628.088 | F27: 685.475 | G27: 720.985 | H27: 721.45535 | I27: 725.03125 | J27: 729.82476 | K27: 768.746 | L27: 787.163 | M27: 794.887 | N27: 813.821 | O27: 836.449 | P27: 857.316 | Q27: 883.888 | R27: 1106.084 | S27: 1040.071 | T27: 1172.0232 | U27: 1189.17 | V27: 1189.14 | W27: 1213.6145 | X27: 1247.1652 | Y27: 1279.5396
B28: Nominal GDP, GDP deflator and population figures
E29: Outturn | T29: Forecast
E30: 2007-08 | F30: 2008-09 | G30: 2009-10 | H30: 2010-11 | I30: 2011-12 | J30: 2012-13 | K30: 2013-14 | L30: 2014-15 | M30: 2015-16 | N30: 2016-17 | O30: 2017-18 | P30: 2018-19 | Q30: 2019-20 | R30: 2020-21 | S30: 2021-22 | T30: 2022-23 | U30: 2023-24 | V30: 2024-25 | W30: 2025-26 | X30: 2026-27 | Y30: 2027-28
B31: Nominal GDP (£ billion) | E31: 1567.027 | F31: 1583.394 | G31: 1561.331 | H31: 1630.474 | I31: 1671.352 | J31: 1726.983 | K31: 1806.096 | L31: 1875.897 | M31: 1937.57 | N31: 2022.931 | O31: 2102.925 | P31: 2177.222 | Q31: 2249.423 | R31: 2085.204 | S31: 2337.757 | T31: 2504.4101 | U31: 2573.2308 | V31: 2668.7148 | W31: 2759.2633 | X31: 2849.6648 | Y31: 2949.7937
B32: GDP deflator | E32: 2.3696682 | F32: 3.6111111 | G32: 1.3106941 | H32: 1.6759777 | I32: 1.7929439 | J32: 1.7045455 | K32: 2.0949721 | L32: 1.121751 | M32: 0.75757576 | N32: 2.0408163 | O32: 1.6842105 | P32: 1.8115942 | Q32: 2.5927809 | R32: 6.2685828 | S32: -0.74609466 | T32: 5.6834921 | U32: 2.5246453 | V32: 1.569508 | W32: 0.96366577 | X32: 1.1972805 | Y32: 1.6522497
E33: Estimates | R33: Projections
B34: Population (thousand)2 | E34: 61508.25 | F34: 61987.5 | G34: 62447.75 | H34: 62956.75 | I34: 63442.5 | J34: 63855.25 | K34: 64289.75 | L34: 64789.25 | M34: 65312 | N34: 65795 | O34: 66188.5 | P34: 66571.25 | Q34: 66903.5 | R34: 67182 | S34: 67479.25 | T34: 67863.07 | U34: 68238.924 | V34: 68541.913 | W34: 68820.839 | X34: 69074.002 | Y34: 69307.068
B35: Note: This table removes series discontinuities, where possible, so that the adjusted historical series are consistent with the latest forecast. This includes the major ONS classification changes and Treasury policy decisions to switch spending between DEL and AME.
B36: 1 Excluding the one-off adjustment for Royal Mail transfers in 2012-13.
B37: 2 Consistent with our economic forecast, the figures shown are based on the ONS's latest (2018-based) principal migration population estimates and projections.

Sheet OBR_NOV22_ST3.3
A1: Back to contents
B2: 3.3 Consistent historical RDEL and CDEL series
E3: Outturn | T3: Forecast
E4: 2007-08 | F4: 2008-09 | G4: 2009-10 | H4: 2010-11 | I4: 2011-12 | J4: 2012-13 | K4: 2013-14 | L4: 2014-15 | M4: 2015-16 | N4: 2016-17 | O4: 2017-18 | P4: 2018-19 | Q4: 2019-20 | R4: 2020-21 | S4: 2021-22 | T4: 2022-23 | U4: 2023-24 | V4: 2024-25 | W4: 2025-26 | X4: 2026-27 | Y4: 2027-28
B6: PSCE in RDEL adjusted to remove historical discontinuities
D7: PSCE in RDEL (£ billion) | E7: 256.0776 | F7: 267.99918 | G7: 285.18699 | H7: 291.49791 | I7: 287.03644 | J7: 283.14997 | K7: 287.82011 | L7: 290.00803 | M7: 288.65014 | N7: 291.91609 | O7: 296.73851 | P7: 304.20241 | Q7: 327.07645 | R7: 431.77582 | S7: 413.76045 | T7: 415.47497 | U7: 419.68701 | V7: 422.00137 | W7: 430.32556 | X7: 439.94671 | Y7: 452.66747
D8: PSCE in RDEL (£ billion, 2022-23 prices) | E8: 354.21609 | F8: 357.7864 | G8: 375.80693 | H8: 377.79147 | I8: 365.45683 | J8: 354.4665 | K8: 352.91934 | L8: 351.6574 | M8: 347.37919 | N8: 344.28344 | O8: 344.17435 | P8: 346.55327 | Q8: 363.19496 | R8: 450.64855 | S8: 433.86654 | T8: 415.47497 | U8: 406.54531 | V8: 403.47998 | W8: 409.26181 | X8: 413.38621 | Y8: 417.83147
D9: Real PSCE in RDEL growth rate (per cent) | F9: =(F8/E8-1)*100 -> 1.007946 | G9: =(G8/F8-1)*100 -> 5.0366735 | H9: =(H8/G8-1)*100 -> 0.52807515 | I9: =(I8/H8-1)*100 -> -3.2649355 | J9: =(J8/I8-1)*100 -> -3.0072856 | K9: =(K8/J8-1)*100 -> -0.43647559 | L9: =(L8/K8-1)*100 -> -0.3575699 | M9: =(M8/L8-1)*100 -> -1.2165847 | ... Y9: =(Y8/X8-1)*100 -> 1.0753286
D10: PSCE in RDEL (per cent of GDP) | E10: 16.34162 | F10: 16.925615 | G10: 18.265633 | H10: 17.878108 | I10: 17.173907 | J10: 16.395643 | K10: 15.936036 | L10: 15.459699 | M10: 14.897533 | N10: 14.430353 | O10: 14.110751 | P10: 13.972044 | Q10: 14.54046 | R10: 20.693388 | S10: 17.662717 | T10: 16.638437 | U10: 16.509954 | V10: 16.057803 | W10: 15.860113 | X10: 15.619432 | Y10: 15.463106
D11: Real PSCE in RDEL per capita | E11: 5758.8387 | F11: 5771.9121 | G11: 6017.9419 | H11: 6000.8097 | I11: 5760.4418 | J11: 5551.094 | K11: 5489.5117 | L11: 5427.7122 | M11: 5318.7652 | N11: 5232.6688 | O11: 5199.9116 | P11: 5205.7498 | Q11: 5428.6392 | R11: 6701.1436 | S11: 6422.3956 | T11: 6137.9817 | U11: 5984.456 | V11: 5919.1104 | W11: 5984.8656 | X11: 6027.49 | Y11: 6075.8416
B12: PSGI in CDEL adjusted to remove historical discontinuities
D13: PSGI in CDEL (£ billion) | E13: 48.393903 | F13: 52.202338 | G13: 59.403747 | H13: 50.944261 | I13: 44.004185 | J13: 42.630329 | K13: 46.07875 | L13: 49.976395 | M13: 48.113457 | N13: 49.13382 | O13: 52.597202 | P13: 56.190224 | Q13: 58.971053 | R13: 75.520266 | S13: 76.989229 | T13: 88.814116 | U13: 94.447103 | V13: 94.722329 | W13: 95.604873 | X13: 96.017646 | Y13: 96.197899
D14: PSGI in CDEL (£ billion, 2022-23 prices) | E14: 66.940252 | F14: 69.691581 | G14: 78.279657 | H14: 66.025543 | I14: 56.026439 | J14: 53.367562 | K14: 56.500853 | L14: 60.600285 | M14: 57.90267 | N14: 57.948025 | O14: 61.005252 | P14: 64.012989 | Q14: 65.48313 | R14: 78.821224 | S14: 80.73041 | T14: 88.814116 | U14: 91.489672 | V14: 90.565023 | W14: 90.925168 | X14: 90.220861 | Y14: 88.794783
D15: Real PSGI in CDEL growth rate (per cent) | F15: 4.765496 | G15: 12.048625 | H15: -15.659611 | I15: -14.907299 | J15: -5.0498851 | K15: 5.6608202 | L15: 7.253892 | M15: -4.3238304 | N15: -0.11155099 | O15: 5.2199279 | P15: 4.8232005 | Q15: 2.5270567 | R15: 16.369462 | S15: -3.7259505 | T15: 19.412657 | U15: 7.4742509 | V15: -1.5970302 | W15: 2.6327222 | Y15: 1.6756967
D16: PSGI in CDEL (per cent of GDP) | E16: 3.0882622 | F16: 3.2968634 | G16: 3.8046863 | H16: 3.1245062 | I16: 2.6328496 | J16: 2.4684858 | K16: 2.5512902 | L16: 2.6641332 | M16: 2.4831855 | N16: 2.4288431 | O16: 2.5011449 | P16: 2.580822 | Q16: 2.621608 | R16: 3.6194018 | S16: 3.2865368 | T16: 3.5567198 | U16: 3.7154292 | V16: 3.6043307 | W16: 3.5236209 | X16: 3.4089154 | Y16: 3.286117
D17: Real PSGI in CDEL per capita | E17: 1088.3134 | F17: 1124.2844 | G17: 1253.5225 | H17: 1048.7445 | I17: 883.10579 | J17: 835.75841 | K17: 878.84699 | L17: 935.34475 | M17: 886.55485 | N17: 880.73599 | O17: 921.6896 | P17: 961.57109 | Q17: 978.76987 | R17: 1172.0715 | S17: 1195.0279 | T17: 1312.0873 | U17: 1346.7525 | V17: 1328.6021 | W17: 1329.6499 | X17: 1315.4898 | Y17: 1291.1977
B18: Unadjusted aggregate spending series (£ billion)
D19: PSCE in RDEL | E19: 286.76629 | F19: 299.94735 | G19: 318.08264 | H19: 324.94499 | I19: 313.2674 | J19: 309.98999 | K19: 308.71881 | L19: 310.64617 | M19: 309.74896 | N19: 286.70991 | O19: 289.20228 | P19: 295.63494 | Q19: 321.42632 | R19: 429.36841 | S19: 413.76045 | T19: 415.47497 | U19: 419.68701 | V19: 422.00137 | W19: 430.32556 | X19: 439.94671 | Y19: 452.66747
D20: PSGI in CDEL | E20: 43.189293 | F20: 47.242335 | G20: 54.660402 | H20: 42.333613 | I20: 42.325888 | J20: 39.479622 | K20: 41.356102 | L20: 45.53985 | M20: 44.195856 | N20: 42.526187 | O20: 45.004945 | P20: 50.802769 | Q20: 57.891053 | R20: 75.520266 | S20: 76.989229 | T20: 88.814116 | U20: 94.447103 | V20: 94.722329 | W20: 95.604873 | X20: 96.017646 | Y20: 96.197899
D21: TME in DEL | E21: 329.95559 | F21: 347.18969 | G21: 372.74304 | H21: 367.2786 | I21: 355.59329 | J21: 349.46961 | K21: 350.07491 | L21: 356.18602 | M21: 353.94481 | N21: 329.23609 | O21: 334.20722 | P21: 346.43771 | Q21: 379.31737 | R21: 504.88868 | S21: 490.74968 | T21: 504.28909 | U21: 514.13411 | V21: 516.7237 | W21: 525.93043 | X21: 535.96435 | Y21: 548.86537
D22: PSCE in AME | E22: 278.13771 | F22: 299.39165 | G22: 315.68136 | H22: 315.52936 | I22: 336.94285 | J22: 350.62778 | K22: 385.44019 | L22: 394.04783 | M22: 405.40704 | N22: 439.69709 | O22: 453.85772 | P22: 465.15806 | Q22: 468.22068 | R22: 551.55859 | S22: 524.14755 | T22: 646.66197 | U22: 643.94931 | V22: 625.57912 | W22: 636.80002 | X22: 667.8867 | Y22: 686.57579
D23: PSGI in AME1 | E23: 19.994707 | F23: 38.893665 | G23: 32.560598 | H23: 38.647387 | I23: 32.495112 | J23: 29.727378 | K23: 33.230898 | L23: 36.92915 | M23: 35.535144 | N23: 44.887813 | O23: 48.384055 | P23: 45.720231 | Q23: 36.349947 | R23: 50.185734 | S23: 32.638771 | T23: 30.941352 | U23: 40.690722 | V23: 38.038656 | W23: 36.470671 | X23: 35.859996 | Y23: 35.708127
D24: TME in AME1 | E24: 298.13241 | F24: 338.28531 | G24: 348.24196 | H24: 354.17675 | I24: 369.43796 | J24: 380.35516 | K24: 418.67109 | L24: 430.97698 | M24: 440.94219 | N24: 484.58491 | O24: 502.24178 | P24: 510.87829 | Q24: 504.57063 | R24: 601.74432 | S24: 556.78632 | T24: 677.60333 | U24: 684.64003 | V24: 663.61777 | W24: 673.27069 | X24: 703.7467 | Y24: 722.28392
D25: PSCE | E25: 564.904 | F25: 599.339 | G25: 633.764 | H25: 640.47435 | I25: 650.21025 | J25: 660.61776 | K25: 694.159 | L25: 704.694 | M25: 715.156 | N25: 726.407 | O25: 743.06 | P25: 760.793 | Q25: 789.647 | R25: 980.927 | S25: 937.908 | T25: 1062.1369 | U25: 1063.6363 | V25: 1047.5805 | W25: 1067.1256 | X25: 1107.8334 | Y25: 1139.2433
D26: PSGI1 | E26: 63.184 | F26: 86.136 | G26: 87.221 | H26: 80.981 | I26: 74.821 | J26: 69.207 | K26: 74.587 | L26: 82.469 | M26: 79.731 | N26: 87.414 | O26: 93.389 | P26: 96.523 | Q26: 94.241 | R26: 125.706 | S26: 109.628 | T26: 119.75547 | U26: 135.13783 | V26: 132.76099 | W26: 132.07554 | X26: 131.87764 | Y26: 131.90603
D27: TME1 | E27: 628.088 | F27: 685.475 | G27: 720.985 | H27: 721.45535 | I27: 725.03125 | J27: 729.82476 | K27: 768.746 | L27: 787.163 | M27: 794.887 | N27: 813.821 | O27: 836.449 | P27: 857.316 | Q27: 883.888 | R27: 1106.633 | S27: 1047.276 | T27: 1181.8924 | U27: 1198.7741 | V27: 1180.3415 | W27: 1199.2011 | X27: 1239.7111 | Y27: 1271.1493
B28: Nominal GDP, GDP deflator and population figures
E29: Outturn | T29: Forecast
E30: 2007-08 | F30: 2008-09 | G30: 2009-10 | H30: 2010-11 | I30: 2011-12 | J30: 2012-13 | K30: 2013-14 | L30: 2014-15 | M30: 2015-16 | N30: 2016-17 | O30: 2017-18 | P30: 2018-19 | Q30: 2019-20 | R30: 2020-21 | S30: 2021-22 | T30: 2022-23 | U30: 2023-24 | V30: 2024-25 | W30: 2025-26 | X30: 2026-27 | Y30: 2027-28
B31: Nominal GDP (£ billion) | E31: 1567.027 | F31: 1583.394 | G31: 1561.331 | H31: 1630.474 | I31: 1671.352 | J31: 1726.983 | K31: 1806.096 | L31: 1875.897 | M31: 1937.57 | N31: 2022.931 | O31: 2102.925 | P31: 2177.222 | Q31: 2249.423 | R31: 2086.54 | S31: 2342.564 | T31: 2497.0793 | U31: 2542.024 | V31: 2628.0144 | W31: 2713.2565 | X31: 2816.6627 | Y31: 2927.4033
B32: GDP deflator | E32: 2.3696682 | F32: 3.6111111 | G32: 1.3106941 | H32: 1.6759777 | I32: 1.7929439 | J32: 1.7045455 | K32: 2.0949721 | L32: 1.121751 | M32: 0.75757576 | N32: 2.0408163 | O32: 1.6842105 | P32: 1.8115942 | Q32: 2.5927809 | R32: 6.3924678 | S32: -0.46576619 | T32: 4.8593559 | U32: 3.2325295 | V32: 1.3153619 | W32: 0.53193643 | X32: 1.2157672 | Y32: 1.7967819
E33: Estimates | R33: Projections
B34: Population (thousand)2 | E34: 61508.25 | F34: 61987.5 | G34: 62447.75 | H34: 62956.75 | I34: 63442.5 | J34: 63855.25 | K34: 64289.75 | L34: 64789.25 | M34: 65312 | N34: 65795 | O34: 66188.5 | P34: 66571.25 | Q34: 66903.5 | R34: 67249.5 | S34: 67555.25 | T34: 67689.184 | U34: 67933.545 | V34: 68165.646 | W34: 68382.791 | X34: 68583.475 | Y34: 68769.315
B35: Note: This table removes series discontinuities, where possible, so that the adjusted historical series are consistent with the latest forecast. This includes the major ONS classification changes and Treasury policy decisions to switch spending between DEL and AME.
B36: 1 Excluding the one-off adjustment for Royal Mail transfers in 2012-13.
B37: 2 Consistent with our economic forecast, the figures shown are based on the ONS's latest (2018-based) principal migration population estimates and projections.

Sheet OBR_MAR22_ST3.3
A1: Back to contents
B2: 3.3 Consistent historical RDEL and CDEL series
E3: Outturn | S3: Forecast
E4: 2007-08 | F4: 2008-09 | G4: 2009-10 | H4: 2010-11 | I4: 2011-12 | J4: 2012-13 | K4: 2013-14 | L4: 2014-15 | M4: 2015-16 | N4: 2016-17 | O4: 2017-18 | P4: 2018-19 | Q4: 2019-20 | R4: 2020-21 | S4: 2021-22 | T4: 2022-23 | U4: 2023-24 | V4: 2024-25 | W4: 2025-26 | X4: 2026-27
B6: PSCE in RDEL adjusted to remove historical discontinuities
D7: PSCE in RDEL (£ billion) | E7: 256.0776 | F7: 267.99918 | G7: 285.18699 | H7: 291.49791 | I7: 287.03644 | J7: 283.14997 | K7: 287.82011 | L7: 290.00803 | M7: 288.65014 | N7: 291.91609 | O7: 296.73851 | P7: 304.20241 | Q7: 327.07645 | R7: 436.92511 | S7: 405.02778 | T7: 406.97511 | U7: 408.019 | V7: 419.09821 | W7: 435.39391 | X7: 451.57825
D8: PSCE in RDEL (£ billion, 2021-22 prices) | E8: 333.64883 | F8: 339.13331 | G8: 355.34429 | H8: 357.19818 | I8: 346.50095 | J8: 335.00763 | K8: 332.88275 | L8: 331.68742 | M8: 328.08993 | N8: 324.54914 | O8: 324.27408 | P8: 326.18221 | Q8: 342.61569 | R8: 432.46503 | S8: 405.02778 | T8: 391.11735 | U8: 382.89201 | V8: 386.12884 | W8: 393.45805 | X8: 400.07978
D9: Real PSCE in RDEL growth rate (per cent) | F9: 1.6437873 | G9: 4.7801197 | H9: 0.5217173 | I9: -2.9947601 | J9: -3.3169676 | K9: -0.63427685 | L9: -0.35908404 | M9: -1.0846043 | N9: -1.0792139 | O9: -0.084750121 | P9: 0.58843079 | Q9: 5.0381307 | R9: 26.224524 | S9: -6.3443856 | T9: -3.4344399 | U9: -2.1030358 | V9: 0.84536433 | W9: 1.8981244 | X9: 1.6829578
D10: PSCE in RDEL (per cent of GDP) | E10: 16.281928 | F10: 16.920753 | G10: 18.202805 | H10: 17.869888 | I10: 17.09797 | J10: 16.32375 | K10: 15.832743 | L10: 15.357422 | M10: 14.777064 | N10: 14.311008 | O10: 14.051862 | P10: 13.829243 | Q10: 14.464729 | R10: 20.39936 | S10: 17.130243 | T10: 16.193691 | U10: 15.564132 | V10: 15.37317 | W10: 15.405783 | X10: 15.405783
D11: Real PSCE in RDEL per capita | E11: 5424.4566 | F11: 5470.9951 | G11: 5690.2657 | H11: 5673.7075 | I11: 5461.6535 | J11: 5246.36 | K11: 5177.8511 | L11: 5119.4824 | M11: 5023.4249 | N11: 4932.7325 | O11: 4899.2511 | P11: 4899.7459 | Q11: 5121.0429 | R11: 6447.1604 | S11: 6035.4237 | T11: 5812.0802 | U11: 5676.5825 | V11: 5712.3476 | W11: 5809.4858 | X11: 5896.7428
B12: PSGI in CDEL adjusted to remove historical discontinuities
D13: PSGI in CDEL (£ billion) | E13: 48.393903 | F13: 52.202338 | G13: 59.403747 | H13: 50.944261 | I13: 44.004185 | J13: 42.630329 | K13: 46.07875 | L13: 49.976395 | M13: 48.113457 | N13: 49.13382 | O13: 52.597202 | P13: 56.190224 | Q13: 58.971053 | R13: 72.625962 | S13: 69.20622 | T13: 85.991647 | U13: 94.646379 | V13: 94.861872 | W13: 99.260827 | X13: 102.94317
D14: PSGI in CDEL (£ billion, 2021-22 prices) | E14: 63.053422 | F14: 66.058231 | G14: 74.017339 | H14: 62.426512 | I14: 53.120405 | J14: 50.437885 | K14: 53.293083 | L14: 57.158906 | M14: 54.687452 | N14: 54.626448 | O14: 57.477909 | P14: 60.250183 | Q14: 61.77274 | R14: 71.884605 | S14: 69.20622 | T14: 82.640986 | U14: 88.817781 | V14: 87.399334 | W14: 89.700316 | X14: 91.203421
D15: Real PSGI in CDEL growth rate (per cent) | F15: 4.765496 | G15: 12.048625 | H15: -15.659611 | I15: -14.907299 | J15: -5.0498851 | K15: 5.6608202 | L15: 7.253892 | M15: -4.3238304 | N15: -0.11155099 | O15: 5.2199279 | P15: 4.8232005 | Q15: 2.5270567 | R15: 16.369462 | S15: -3.7259505 | T15: 19.412657 | U15: 7.4742509 | V15: -1.5970302 | W15: 2.6327222 | X15: 1.6756967
D16: PSGI in CDEL (per cent of GDP) | E16: 3.0769815 | F16: 3.2959163 | G16: 3.7915995 | H16: 3.1230696 | I16: 2.621208 | J16: 2.4576617 | K16: 2.5347534 | L16: 2.6465081 | M16: 2.4631051 | N16: 2.4087555 | O16: 2.4907068 | P16: 2.5544448 | Q16: 2.6079539 | R16: 3.3907942 | S16: 2.9270075 | T16: 3.4216395 | U16: 3.6103434 | V16: 3.4796799 | W16: 3.5122006 | X16: 3.5119498
D17: Real PSGI in CDEL per capita | E17: 1025.1214 | F17: 1065.6702 | G17: 1185.2683 | H17: 991.57774 | I17: 837.29999 | J17: 789.87844 | K17: 828.95148 | L17: 882.22824 | M17: 837.32625 | N17: 830.25226 | O17: 868.39721 | P17: 905.0481 | Q17: 923.31103 | R17: 1071.651 | S17: 1031.2598 | T17: 1228.0612 | U17: 1316.772 | V17: 1292.9761 | W17: 1324.4429 | X17: 1344.2397
B18: Unadjusted aggregate spending series (£ billion)
D19: PSCE in RDEL | E19: 286.76629 | F19: 299.94735 | G19: 318.08264 | H19: 324.94499 | I19: 313.2674 | J19: 309.98999 | K19: 308.71881 | L19: 310.64617 | M19: 309.74896 | N19: 286.70991 | O19: 289.20228 | P19: 295.63494 | Q19: 321.42632 | R19: 434.5177 | S19: 405.02778 | T19: 406.97511 | U19: 408.019 | V19: 419.09821 | W19: 435.39391 | X19: 451.57825
D20: PSGI in CDEL | E20: 43.189293 | F20: 47.242335 | G20: 54.660402 | H20: 42.333613 | I20: 42.325888 | J20: 39.479622 | K20: 41.356102 | L20: 45.53985 | M20: 44.195856 | N20: 42.526187 | O20: 45.004945 | P20: 50.802769 | Q20: 57.891053 | R20: 72.625962 | S20: 69.20622 | T20: 85.991647 | U20: 94.646379 | V20: 94.861872 | W20: 99.260827 | X20: 102.94317
D21: TME in DEL | E21: 329.95559 | F21: 347.18969 | G21: 372.74304 | H21: 367.2786 | I21: 355.59329 | J21: 349.46961 | K21: 350.07491 | L21: 356.18602 | M21: 353.94481 | N21: 329.23609 | O21: 334.20722 | P21: 346.43771 | Q21: 379.31737 | R21: 507.14367 | S21: 474.234 | T21: 492.96676 | U21: 502.66538 | V21: 513.96008 | W21: 534.65473 | X21: 554.52142
D22: PSCE in AME | E22: 278.13771 | F22: 299.39165 | G22: 315.68136 | H22: 337.97801 | I22: 358.4656 | J22: 373.44901 | K22: 385.44019 | L22: 394.04783 | M22: 405.40704 | N22: 439.69709 | O22: 453.85772 | P22: 465.15806 | Q22: 468.22068 | R22: 555.2933 | S22: 528.79131 | T22: 565.99556 | U22: 560.75258 | V22: 578.07423 | W22: 595.4697 | X22: 616.12205
D23: PSGI in AME1 | E23: 19.994707 | F23: 38.893665 | G23: 32.560598 | H23: 38.647387 | I23: 32.495112 | J23: 29.727378 | K23: 33.230898 | L23: 36.92915 | M23: 35.535144 | N23: 44.887813 | O23: 48.384055 | P23: 45.720231 | Q23: 36.349947 | R23: 52.525038 | S23: 24.295071 | T23: 27.646958 | U23: 36.871409 | V23: 34.908594 | W23: 35.526963 | X23: 35.480859
D24: TME in AME1 | E24: 298.13241 | F24: 338.28531 | G24: 348.24196 | H24: 376.6254 | I24: 390.96071 | J24: 403.17639 | K24: 418.67109 | L24: 430.97698 | M24: 440.94219 | N24: 484.58491 | O24: 502.24178 | P24: 510.87829 | Q24: 504.57063 | R24: 607.81833 | S24: 553.08638 | T24: 593.64252 | U24: 597.62399 | V24: 612.98282 | W24: 630.99667 | X24: 651.60291
D25: PSCE | E25: 564.904 | F25: 599.339 | G25: 633.764 | H25: 662.923 | I25: 671.733 | J25: 683.439 | K25: 694.159 | L25: 704.694 | M25: 715.156 | N25: 726.407 | O25: 743.06 | P25: 760.793 | Q25: 789.647 | R25: 989.811 | S25: 933.81909 | T25: 972.97067 | U25: 968.77158 | V25: 997.17244 | W25: 1030.8636 | X25: 1067.7003
D26: PSGI1 | E26: 63.184 | F26: 86.136 | G26: 87.221 | H26: 80.981 | I26: 74.821 | J26: 69.207 | K26: 74.587 | L26: 82.469 | M26: 79.731 | N26: 87.414 | O26: 93.389 | P26: 96.523 | Q26: 94.241 | R26: 125.151 | S26: 93.501291 | T26: 113.63861 | U26: 131.51779 | V26: 129.77047 | W26: 134.78779 | X26: 138.42403
D27: TME1 | E27: 628.088 | F27: 685.475 | G27: 720.985 | H27: 743.904 | I27: 746.554 | J27: 752.646 | K27: 768.746 | L27: 787.163 | M27: 794.887 | N27: 813.821 | O27: 836.449 | P27: 857.316 | Q27: 883.888 | R27: 1114.962 | S27: 1027.3204 | T27: 1086.6093 | U27: 1100.2894 | V27: 1126.9429 | W27: 1165.6514 | X27: 1206.1243
B28: Nominal GDP, GDP deflator and population figures
E29: Outturn | S29: Forecast
E30: 2007-08 | F30: 2008-09 | G30: 2009-10 | H30: 2010-11 | I30: 2011-12 | J30: 2012-13 | K30: 2013-14 | L30: 2014-15 | M30: 2015-16 | N30: 2016-17 | O30: 2017-18 | P30: 2018-19 | Q30: 2019-20 | R30: 2020-21 | S30: 2021-22 | T30: 2022-23 | U30: 2023-24 | V30: 2024-25 | W30: 2025-26 | X30: 2026-27
B31: Nominal GDP (£ billion) | E31: 1572.772 | F31: 1583.849 | G31: 1566.72 | H31: 1631.224 | I31: 1678.775 | J31: 1734.589 | K31: 1817.879 | L31: 1888.39 | M31: 1953.366 | N31: 2039.801 | O31: 2111.738 | P31: 2199.704 | Q31: 2261.2 | R31: 2141.857 | S31: 2364.4018 | T31: 2513.1709 | U31: 2621.5339 | V31: 2726.1666 | W31: 2826.1719 | X31: 2931.2256
B32: GDP deflator | E32: 2.7918782 | F32: 2.962963 | G32: 1.558753 | H32: 1.6824085 | I32: 1.509434 | J32: 2.0303117 | K32: 2.2982063 | L32: 1.1232877 | M32: 0.62313736 | N32: 2.2347873 | O32: 1.7382144 | P32: 1.9156096 | Q32: 2.3622047 | R32: 5.8312655 | S32: -1.0207881 | T32: 4.054478 | U32: 2.4102219 | V32: 1.8543271 | W32: 1.9530798 | X32: 2.000546
E33: Estimates | R33: Projections
B34: Population (thousands)2 | E34: 61508.25 | F34: 61987.5 | G34: 62447.75 | H34: 62956.75 | I34: 63442.5 | J34: 63855.25 | K34: 64289.75 | L34: 64789.25 | M34: 65312 | N34: 65795 | O34: 66188.5 | P34: 66571.25 | Q34: 66903.5 | R34: 67078.373 | S34: 67108.425 | T34: 67293.866 | U34: 67451.149 | V34: 67595.474 | W34: 67726.828 | X34: 67847.589
B35: Note: This table removes series discontinuities, where possible, so that the adjusted historical series are consistent with the latest forecast. This includes the major ONS classification changes and Treasury policy decisions to switch spending between DEL and AME.
B36: 1 Excluding the one-off adjustment for Royal Mail transfers in 2012-13.
B37: 2 Consistent with our economic forecast, the figures shown are based on the ONS's latest (2018-based) principal migration population estimates and projections.

Sheet OBR_NOV23_TA.7
A1: Back to contents
B2: Table A.7: Total managed expenditure
C4: £ billion
C5: Outturn | D5: Forecast
C6: 2022-23 | D6: 2023-24 | E6: 2024-25 | F6: 2025-26 | G6: 2026-27 | H6: 2027-28 | I6: 2028-29
B7: Public sector current expenditure (PSCE)
B8: PSCE in RDEL | C8: 411.5361 | D8: 426.51629 | E8: 435.45198 | F8: 445.2619 | G8: 456.91761 | H8: 469.9419 | I8: 483.64675
B9: PSCE in AME | C9: 634.9669 | D9: 662.97387 | E9: 667.08865 | F9: 688.98558 | G9: 713.8149 | H9: 733.02481 | I9: 758.82234
B10: of which:
B11: Welfare spending | C11: 261.47909 | D11: 295.36919 | E11: 316.42806 | F11: 333.90157 | G11: 343.16005 | H11: 350.86962 | I11: 361.68412
B12: Locally financed current expenditure | C12: 60.346917 | D12: 62.207691 | E12: 63.778229 | F12: 66.255645 | G12: 69.335173 | H12: 72.128506 | I12: 75.287812
B13: Central government debt interest, net of APF1 | C13: 111.20812 | D13: 116.22229 | E13: 106.17499 | F13: 101.89327 | G13: 108.84889 | H13: 115.1656 | I13: 122.48093
B14: Scottish Government's current spending | C14: 39.586038 | D14: 42.030645 | E14: 43.521798 | F14: 44.891365 | G14: 45.940014 | H14: 47.173894 | I14: 48.799638
B15: EU financial settlement | C15: 8.8096667 | D15: 7.7611439 | E15: 0.84577798 | F15: 0.76194184 | G15: 0.46893936 | H15: 0.35241557 | I15: 0.76366702
B16: Unfunded public service pensions | C16: 3.6085466 | D16: 5.5954102 | E16: 3.1840667 | F16: 4.1450654 | G16: 3.2702939 | H16: 2.3657091 | I16: 0.80981287
B17: Company and other tax credits | C17: 9.2172946 | D17: 10.06353 | E17: 10.338588 | F17: 10.456469 | G17: 10.69962 | H17: 11.02155 | I17: 11.194049
B18: BBC current expenditure | C18: 4.2258646 | D18: 4.2019715 | E18: 4.3593487 | F18: 4.3736451 | G18: 4.6555976 | H18: 4.6323025 | I18: 4.6833085
B19: National Lottery current grants | C19: 1.28536 | D19: 1.387704 | E19: 1.595109 | F19: 1.607932 | G19: 1.479318 | H19: 1.402302 | I19: 1.408294
B20: General government imputed pensions | C20: 3.3853899 | D20: 1.6944179 | E20: 1.7547382 | F20: 1.7991861 | G20: 1.8532571 | H20: 1.9139111 | I20: 1.9772928
B21: Public corporations' debt interest | C21: 0.539 | D21: 0.528 | E21: 0.528 | F21: 0.528 | G21: 0.528 | H21: 0.528 | I21: 0.528
B22: Non-domestic energy support | C22: 6.663 | D22: 0.552 | E22: 0 | F22: 0 | G22: 0 | H22: 0 | I22: 0
... B30: Total public sector current expenditure | C30: 1046.503 | D30: 1089.4902 | E30: 1102.5406 | F30: 1134.2475 | G30: 1170.7325 | H30: 1202.9667 | I30: 1242.4691
B31: Public sector gross investment (PSGI)
B32: PSGI in CDEL | C32: 89.791733 | D32: 96.000288 | E32: 99.196273 | F32: 97.221725 | G32: 97.50902 | H32: 97.597216 | I32: 97.357557
B33: PSGI in AME | C33: 15.130267 | D33: 36.842212 | E33: 35.019618 | F33: 33.05696 | G33: 33.067782 | H33: 33.000513 | I33: 33.210587
B34: of which:
B35: Locally financed capital expenditure | C35: 8.9063424 | D35: 8.0009834 | E35: 7.7546753 | F35: 7.6208402 | G35: 7.5367127 | H35: 7.5805601 | I35: 7.6676734
B36: Public corporations' capital expenditure | C36: 11.217757 | D36: 10.965825 | E36: 11.529719 | F36: 11.833013 | G36: 11.953604 | H36: 12.038981 | I36: 12.139002
B37: Student loans | C37: 0.488 | D37: 10.399782 | E37: 9.1567832 | F37: 7.9688424 | G37: 7.2013316 | H37: 7.17412 | I37: 7.2242776
B38: Funded public sector pension schemes | C38: -4.854 | D38: 0.71152891 | E38: 0.71152891 | F38: 0.71152891 | G38: 0.71152891 | H38: 0.71152891 | I38: 0.71152891
B39: Scottish Government's capital spending | C39: 4.569481 | D39: 5.3680799 | E39: 5.2630167 | F39: 5.1607518 | G39: 5.154036 | H39: 5.1460268 | I39: 5.1238011
B40: Tax litigation | C40: 0 | D40: 0.8235 | E40: 1.203396 | F40: 0.63406325 | G40: 0.63406325 | H40: 0.63406325 | I40: 0.63406325
B41: Other PSGI items in AME | C41: 0.3897293 | D41: 1.4051943 | E41: 0.95227045 | F41: 0.91446001 | G41: 0.8307078 | H41: 0.67033175 | I41: 0.60671338
B42: Other National Accounts adjustments | C42: -5.5870428 | D42: -0.83268205 | E42: -1.5517716 | F42: -1.78654 | G42: -0.95420291 | H42: -0.95509948 | I42: -0.89647224
B43: Total public sector gross investment | C43: 104.922 | D43: 132.8425 | E43: 134.21589 | F43: 130.27869 | G43: 130.5768 | H43: 130.59773 | I43: 130.56814
B44: Less public sector depreciation | C44: -57.23 | D44: -61.200498 | E44: -64.313705 | F44: -66.657309 | G44: -69.002934 | H44: -71.467377 | I44: -73.760378
B45: Public sector net investment | C45: 47.692 | D45: 71.642002 | E45: 69.902186 | F45: 63.621376 | G45: 61.573868 | H45: 59.130352 | I45: 56.807767
B46: Total managed expenditure | C46: 1151.425 | D46: 1222.3327 | E46: 1236.7565 | F46: 1264.5262 | G46: 1301.3093 | H46: 1333.5644 | I46: 1373.0372
