Workbook
Name _1_: #REF!
Name _1_: #REF!
Name _2ecm: #REF!
Name _2ecm: #REF!
Name _3ecw: #REF!
Name _3ecw: #REF!
Name _bot1: #REF!
Name _bot1: #REF!
Name _bot1: #REF!
Name _bot2: #REF!
Name _bot2: #REF!
Name _bot2: #REF!
Name _bot3: #REF!
Name _bot3: #REF!
Name _bot3: #REF!
Name _bot4: #REF!
Name _bot4: #REF!
Name _bot4: #REF!
Name _bot5: #REF!
Name _bot5: #REF!
Name _bot5: #REF!
Name _bot6: #REF!
Name _bot6: #REF!
Name _bot6: #REF!
Name _DLX1.INC: HAVERM!$A$1:$G$6
Name _DLX2.INC: #REF!
Name _DLX3.INC: #REF!
Name _I2: #REF!
Name _MYE4: #REF!
Name _MYE5: #REF!
Name _MYE6: #REF!
Name _top1: #REF!
Name _top1: #REF!
Name _top1: #REF!
Name _top2: #REF!
Name _top2: #REF!
Name _top2: #REF!
Name _top3: #REF!
Name _top3: #REF!
Name _top3: #REF!
Name _top4: #REF!
Name _top4: #REF!
Name _top4: #REF!
Name _top5: #REF!
Name _top5: #REF!
Name _top5: #REF!
Name _top6: #REF!
Name _top6: #REF!
Name _top6: #REF!
Name a: 'May24 MPR Chart 3.10'!SERIES1s:'May24 MPR Chart 3.10'!SERIES1e
Name a: SERIES1s:SERIES1e
Name AllNSAData: #REF!
Name AllSAData: #REF!
Name AME: OFFSET(#REF!,0,0,MAX(#REF!),1)
Name AME: OFFSET(#REF!,0,0,MAX(#REF!),1)
Name Amytest: #REF!
Name Ann: #REF!
Name Ann_chg: #REF!
Name Ann_chg: #REF!
Name Apr_50: #REF!

Sheet Chart Data
A1: Services inflation | F1: Private sector pay growth
B2: Outturn | C2: BoE forecast (Feb) | D2: BoE forecast (May) | G2: Outturn | H2: BoE forecast (Feb) | I2: BoE forecast (May)
A3: 44562 | B3: =100*((HAVERM!C151/HAVERM!C139)-1) -> 3.2685512 | F3: 44562 | G3: =HAVERM!D151 -> 4.2
A4: 44593 | B4: =100*((HAVERM!C152/HAVERM!C140)-1) -> 3.4391534 | F4: 44593 | G4: =HAVERM!D152 -> 4.6
A5: 44621 | B5: =100*((HAVERM!C153/HAVERM!C141)-1) -> 3.9612676 | F5: 44621 | G5: =HAVERM!D153 -> 4.9
A6: 44652 | B6: =100*((HAVERM!C154/HAVERM!C142)-1) -> 4.7244094 | F6: 44652 | G6: =HAVERM!D154 -> 4.8
A7: 44682 | B7: =100*((HAVERM!C155/HAVERM!C143)-1) -> 4.886562 | F7: 44682 | G7: =HAVERM!D155 -> 5.1
A8: 44713 | B8: =100*((HAVERM!C156/HAVERM!C144)-1) -> 5.2173913 | F8: 44713 | G8: =HAVERM!D156 -> 5.4
A9: 44743 | B9: =100*((HAVERM!C157/HAVERM!C145)-1) -> 5.7241977 | F9: 44743 | G9: =HAVERM!D157 -> 6
A10: 44774 | B10: =100*((HAVERM!C158/HAVERM!C146)-1) -> 5.9585492 | F10: 44774 | G10: =HAVERM!D158 -> 6.2
A11: 44805 | B11: =100*((HAVERM!C159/HAVERM!C147)-1) -> 6.1312608 | F11: 44805 | G11: =HAVERM!D159 -> 6.6
A12: 44835 | B12: =100*((HAVERM!C160/HAVERM!C148)-1) -> 6.2660944 | F12: 44835 | G12: =HAVERM!D160 -> 6.9
A13: 44866 | B13: =100*((HAVERM!C161/HAVERM!C149)-1) -> 6.3464837 | F13: 44866 | G13: =HAVERM!D161 -> 7.3
A14: 44896 | B14: =100*((HAVERM!C162/HAVERM!C150)-1) -> 6.8376068 | F14: 44896 | G14: =HAVERM!D162 -> 7.3
... A26: 45261 | B26: =100*((HAVERM!C174/HAVERM!C162)-1) -> 6.4 | F26: 45261 | G26: =HAVERM!D174 -> 6.2
A27: 45292 | B27: =100*((HAVERM!C175/HAVERM!C163)-1) -> 6.542811 | C27: ='Feb24 MPR - Chart 2.18'!H55 -> 6.6 | F27: 45292 | G27: =HAVERM!D175 -> 6.1
A28: 45323 | B28: =100*((HAVERM!C176/HAVERM!C164)-1) -> 6.0751399 | C28: ='Feb24 MPR - Chart 2.18'!H56 -> 6.1 | F28: 45323 | G28: =HAVERM!D176 -> 6
A29: 45352 | B29: =100*((HAVERM!C177/HAVERM!C165)-1) -> 5.952381 | C29: ='Feb24 MPR - Chart 2.18'!H57 -> 5.8 | F29: 45352 | G29: =HAVERM!D177 -> 5.9 | H29: ='Feb24 MPR - Chart 2.16'!B31 -> 5.7 | I29: ='May24 MPR Chart 3.10'!B15 -> 6
A30: 45383 | C30: ='Feb24 MPR - Chart 2.18'!H58 -> 5.3 | D30: ='May24 MPR - Chart 2.16'!L70 -> 5.52 | F30: 45383
A31: 45413 | C31: ='Feb24 MPR - Chart 2.18'!H59 -> 4.9 | D31: ='May24 MPR - Chart 2.16'!L71 -> 5.258 | F31: 45413
A32: 45444 | C32: ='Feb24 MPR - Chart 2.18'!H60 -> 4.9 | D32: ='May24 MPR - Chart 2.16'!L72 -> 5.134 | F32: 45444 | H32: ='Feb24 MPR - Chart 2.16'!B32 -> 4.7 | I32: ='May24 MPR Chart 3.10'!B16 -> 5.1
A33: 45474 | D33: ='May24 MPR - Chart 2.16'!L73 -> 4.949 | F33: 45474
A34: 45505 | D34: ='May24 MPR - Chart 2.16'!L74 -> 5.001 | F34: 45505
A35: 45536 | D35: ='May24 MPR - Chart 2.16'!L75 -> 4.728 | F35: 45536 | I35: ='May24 MPR Chart 3.10'!B17 -> 4.8

Sheet Feb24 MPR - Chart 2.16
A1: Section 2: Current economic conditions
A3: Chart 2.16 - Measures of annual private sector wage growth
A5: Date | B5: ONS private sector regular pay | C5: KPMG/REC (advanced 12 months) | D5: HMRC RTI | E5: Indeed | F5: DMP | G5: Agents' pay survey
A6: 44592 | B6: 3.8 | C6: No permission | D6: 6.5 | E6: 4.2 | F6: n.a. | G6: n.a.
A7: 44620 | B7: 4.1 | D7: 6.5 | E7: 4.7 | F7: n.a. | G7: n.a.
A8: 44651 | B8: 4.3 | D8: 6.7 | E8: 5.6 | F8: n.a. | G8: n.a.
A9: 44681 | B9: 4.8 | D9: 6.6 | E9: 6.3 | F9: n.a. | G9: n.a.
A10: 44712 | B10: 5.1 | D10: 6.8 | E10: 6.2 | F10: 5.5 | G10: n.a.
A11: 44742 | B11: 5.4 | D11: 6.9 | E11: 6.2 | F11: 5.6 | G11: n.a.
A12: 44773 | B12: 6 | D12: 7.1 | E12: 5.9 | F12: 5.5 | G12: n.a.
A13: 44804 | B13: 6.2 | D13: 7.1 | E13: 6.1 | F13: 5.8 | G13: n.a.
A14: 44834 | B14: 6.6 | D14: 7.1 | E14: 6.2 | F14: 6.1 | G14: n.a.
A15: 44865 | B15: 6.9 | D15: 7 | E15: 6 | F15: 6.3 | G15: n.a.
A16: 44895 | B16: 7.3 | D16: 6.9 | E16: 5.8 | F16: 6.2 | G16: n.a.
A17: 44926 | B17: 7.3 | D17: 6.9 | E17: 5.9 | F17: 6.3 | G17: n.a.
A18: 44957 | B18: 7.1 | D18: 7.2 | E18: 6.3 | F18: 6.3 | G18: n.a.
A19: 44985 | B19: 7 | D19: 7.4 | E19: 6.5 | F19: 6.5 | G19: n.a.
A20: 45016 | B20: 7.1 | D20: 7.4 | E20: 7 | F20: 6.5 | G20: n.a.
A21: 45046 | B21: 7.7 | D21: 7.3 | E21: 7.5 | F21: 6.6 | G21: n.a.
... A28: 45260 | B28: 6.5 | D28: 6.5 | E28: 6.5 | F28: 7 | G28: n.a.
A29: 45291 | B29: n.a. | D29: 6.3 | E29: 6.5 | F29: 6.9 | G29: n.a.
A30: 45322 | B30: n.a. | D30: n.a. | E30: n.a. | F30: 6.8 | G30: n.a.
A31: 2024 Q1 (Bank staff projection) | B31: 5.7 | D31: n.a. | E31: n.a. | F31: n.a. | G31: n.a.
A32: 2024 Q2 (Bank staff projection) | B32: 4.7 | D32: n.a. | E32: n.a. | F32: n.a. | G32: n.a.
A33: 2024 Q3 (Bank staff projection) | B33: 4.4 | D33: n.a. | E33: n.a. | F33: n.a. | G33: n.a.
A34: 2024 Q4 (Bank staff projection) | B34: 4.8 | D34: n.a. | E34: n.a. | F34: 5.2 | G34: 5.4

Sheet Feb24 MPR - Chart 2.18
A1: Section 2: Current economic conditions
A3: 2.18 - Contributions to CPI inflation
B5: Contributions | H5: Inflation rates
A6: Date | B6: Services | C6: Food | D6: Electricity and gas | E6: Fuels and lubricants | F6: Other goods | H6: Services | I6: Food | J6: Electricity and gas | K6: Fuels and lubricants | L6: Other goods | M6: CPI
A7: 43831 | B7: 1.1 | C7: 0.1 | D7: 0.2 | E7: 0.1 | F7: 0.2 | H7: 2.3 | I7: 1.4 | J7: 4.9 | K7: 4.7 | L7: 0.6 | M7: 1.8
A8: 43862 | B8: 1.2 | C8: 0.1 | D8: 0.1 | E8: 0.1 | F8: 0.2 | H8: 2.5 | I8: 1.2 | J8: 4.4 | K8: 2.8 | L8: 0.5 | M8: 1.7
A9: 43891 | B9: 1.2 | C9: 0.1 | D9: 0.1 | E9: -0.1 | F9: 0.1 | H9: 2.5 | I9: 1.3 | J9: 3.9 | K9: -2.4 | L9: 0.4 | M9: 1.5
A10: 43922 | B10: 1 | C10: 0.1 | D10: -0.2 | E10: -0.4 | F10: 0.3 | H10: 2 | I10: 1.3 | J10: -6.8 | K10: -12.2 | L10: 0.7 | M10: 0.8
A11: 43952 | B11: 0.9 | C11: 0.2 | D11: -0.2 | E11: -0.5 | F11: 0.1 | H11: 1.9 | I11: 1.8 | J11: -7 | K11: -16.7 | L11: 0.4 | M11: 0.5
A12: 43983 | B12: 0.9 | C12: 0.1 | D12: -0.2 | E12: -0.5 | F12: 0.4 | H12: 1.8 | I12: 1.1 | J12: -6.6 | K12: -16.4 | L12: 1 | M12: 0.6
A13: 44013 | B13: 1 | C13: 0.1 | D13: -0.2 | E13: -0.4 | F13: 0.5 | H13: 2.1 | I13: 0.8 | J13: -6.6 | K13: -12 | L13: 1.5 | M13: 1
A14: 44044 | B14: 0.3 | C14: 0 | D14: -0.2 | E14: -0.4 | F14: 0.5 | H14: 0.6 | I14: 0.4 | J14: -6.7 | K14: -11.4 | L14: 1.3 | M14: 0.2
A15: 44075 | B15: 0.7 | C15: 0 | D15: -0.2 | E15: -0.3 | F15: 0.4 | H15: 1.4 | I15: -0.1 | J15: -6.8 | K15: -10.6 | L15: 1.1 | M15: 0.5
A16: 44105 | B16: 0.7 | C16: 0.1 | D16: -0.3 | E16: -0.3 | F16: 0.6 | H16: 1.4 | I16: 0.6 | J16: -8.8 | K16: -10.2 | L16: 1.6 | M16: 0.7
A17: 44136 | B17: 0.7 | C17: -0.1 | D17: -0.3 | E17: -0.3 | F17: 0.3 | H17: 1.4 | I17: -0.6 | J17: -8.8 | K17: -10 | L17: 0.8 | M17: 0.3
A18: 44166 | B18: 0.7 | C18: -0.1 | D18: -0.3 | E18: -0.3 | F18: 0.5 | H18: 1.5 | I18: -1.4 | J18: -8.5 | K18: -8.3 | L18: 1.5 | M18: 0.6
... A54: 45261 | B54: 3 | C54: 0.9 | D54: -1 | E54: -0.3 | F54: 1.4 | H54: 6.4 | I54: 8 | J54: -21.5 | K54: -10.8 | L54: 4.3 | M54: 4
A55: Jan 2024 (Bank staff projections) | B55: 3.1 | C55: 0.8 | D55: -0.9 | E55: -0.3 | F55: 1.4 | H55: 6.6 | I55: 7 | J55: -17.8 | K55: -9.2 | L55: 4.1 | M55: 4.1
A56: Feb 2024 (Bank staff projections) | B56: 2.9 | C56: 0.6 | D56: -0.8 | E56: -0.2 | F56: 1.1 | H56: 6.1 | I56: 5 | J56: -17.7 | K56: -7 | L56: 3.3 | M56: 3.5
A57: Mar 2024 (Bank staff projections) | B57: 2.7 | C57: 0.4 | D57: -0.8 | E57: -0.1 | F57: 1 | H57: 5.8 | I57: 3.3 | J57: -17.6 | K57: -4.2 | L57: 2.9 | M57: 3.1
A58: Apr 2024 (Bank staff projections) | B58: 2.5 | C58: 0.2 | D58: -1.3 | E58: 0.1 | F58: 0.6 | H58: 5.3 | I58: 1.9 | J58: -27.3 | K58: 3.3 | L58: 1.7 | M58: 2.1
A59: May 2024 (Bank staff projections) | B59: 2.3 | C59: 0.1 | D59: -1.3 | E59: 0.2 | F59: 0.5 | H59: 4.9 | I59: 1 | J59: -27.2 | K59: 6.5 | L59: 1.5 | M59: 1.9
A60: Jun 2024 (Bank staff projections) | B60: 2.3 | C60: 0.1 | D60: -1.3 | E60: 0.3 | F60: 0.5 | H60: 4.9 | I60: 0.7 | J60: -27.1 | K60: 9.8 | L60: 1.5 | M60: 1.9
A61: 2024 Q3 (Bank staff projections) | B61: n.a. | C61: n.a. | D61: n.a. | E61: n.a. | F61: n.a. | H61: n.a. | I61: n.a. | J61: n.a. | K61: n.a. | L61: n.a. | M61: 2.2
A62: 2024 Q4 (Bank staff projections) | B62: n.a. | C62: n.a. | D62: n.a. | E62: n.a. | F62: n.a. | H62: n.a. | I62: n.a. | J62: n.a. | K62: n.a. | L62: n.a. | M62: 2.7

Sheet May24 MPR - Chart 2.16
A1: Section 2: Current economic conditions
A3: Chart 2.16 - Contributions to CPI inflation
B5: Contributions | H5: Inflation rates
A6: Date | B6: Food | C6: Electricity and gas | D6: Fuels and lubricants | E6: Other goods | F6: Services | H6: Food | I6: Electricity and gas | J6: Fuels and lubricants | K6: Other goods | L6: Services | M6: CPI
A7: 43496 | B7: 0.1 | C7: 0.1 | D7: 0 | E7: 0.5 | F7: 1.2 | H7: 0.9 | I7: 1.4 | J7: 0.7 | K7: 1.4 | L7: 2.5 | M7: 1.8
A8: 43524 | B8: 0.1 | C8: 0.1 | D8: 0 | E8: 0.5 | F8: 1.2 | H8: 1.1 | I8: 1.6 | J8: 0.5 | K8: 1.4 | L8: 2.5 | M8: 1.9
A9: 43555 | B9: 0.1 | C9: 0.1 | D9: 0.1 | E9: 0.5 | F9: 1.2 | H9: 0.8 | I9: 1.5 | J9: 2.9 | K9: 1.3 | L9: 2.5 | M9: 1.9
A10: 43585 | B10: 0.1 | C10: 0.3 | D10: 0.1 | E10: 0.2 | F10: 1.4 | H10: 0.7 | I10: 10.5 | J10: 4.3 | K10: 0.5 | L10: 2.9 | M10: 2.1
A11: 43616 | B11: 0.1 | C11: 0.3 | D11: 0.1 | E11: 0.2 | F11: 1.2 | H11: 1 | I11: 10.4 | J11: 3.4 | K11: 0.7 | L11: 2.6 | M11: 2
A12: 43646 | B12: 0.2 | C12: 0.3 | D12: 0 | E12: 0.3 | F12: 1.2 | H12: 1.6 | I12: 7.9 | J12: 0.7 | K12: 1 | L12: 2.5 | M12: 2
A13: 43677 | B13: 0.1 | C13: 0.2 | D13: 0 | E13: 0.5 | F13: 1.2 | H13: 1.4 | I13: 6.5 | J13: 0.2 | K13: 1.5 | L13: 2.5 | M13: 2.1
A14: 43708 | B14: 0.2 | C14: 0.2 | D14: 0 | E14: 0.3 | F14: 1.1 | H14: 1.8 | I14: 6.5 | J14: -0.1 | K14: 0.8 | L14: 2.2 | M14: 1.7
A15: 43738 | B15: 0.2 | C15: 0.2 | D15: -0.1 | E15: 0.2 | F15: 1.2 | H15: 1.8 | I15: 4.9 | J15: -2.1 | K15: 0.7 | L15: 2.5 | M15: 1.7
A16: 43769 | B16: 0.1 | C16: -0.1 | D16: -0.1 | E16: 0.3 | F16: 1.2 | H16: 1.3 | I16: -1.9 | J16: -3.3 | K16: 0.8 | L16: 2.6 | M16: 1.5
A17: 43799 | B17: 0.2 | C17: -0.1 | D17: -0.1 | E17: 0.2 | F17: 1.2 | H17: 2.1 | I17: -1.7 | J17: -2.9 | K17: 0.7 | L17: 2.5 | M17: 1.5
A18: 43830 | B18: 0.2 | C18: -0.1 | D18: 0 | E18: 0.2 | F18: 1 | H18: 1.7 | I18: -1.6 | J18: 1 | K18: 0.4 | L18: 2.1 | M18: 1.3
... A69: 45352 | B69: 0.5 | C69: -0.9 | D69: -0.1 | E69: 0.9 | F69: 2.8 | H69: 4 | I69: -18.2 | J69: -3.7 | K69: 2.7 | L69: 6 | M69: 3.2
A70: Apr 2024 (Bank staff projections) | B70: 0.306 | C70: -1.262 | D70: 0.007 | E70: 0.416 | F70: 2.598 | H70: 2.529 | I70: -26.609 | J70: -0.274 | K70: 1.24 | L70: 5.52 | M70: 2.064
A71: May 2024 (Bank staff projections) | B71: 0.164 | C71: -1.245 | D71: 0.127 | E71: 0.405 | F71: 2.486 | H71: 1.334 | I71: -26.457 | J71: 3.782 | K71: 1.229 | L71: 5.258 | M71: 1.938
A72: Jun 2024 (Bank staff projections) | B72: 0.171 | C72: -1.239 | D72: 0.235 | E72: 0.377 | F72: 2.442 | H72: 1.423 | I72: -26.397 | J72: 7.722 | K72: 1.143 | L72: 5.134 | M72: 1.987
A73: Jul 2024 (Bank staff projections) | B73: 0.142 | C73: -0.814 | D73: 0.26 | E73: 0.406 | F73: 2.4 | H73: 1.166 | I73: -19.79 | J73: 8.5 | K73: 1.215 | L73: 4.949 | M73: 2.394
A74: Aug 2024 (Bank staff projections) | B74: 0.137 | C74: -0.825 | D74: 0.167 | E74: 0.359 | F74: 2.418 | H74: 1.145 | I74: -20.067 | J74: 4.878 | K74: 1.084 | L74: 5.001 | M74: 2.256
A75: Sep 2024 (Bank staff projections) | B75: 0.125 | C75: -0.828 | D75: 0.068 | E75: 0.334 | F75: 2.285 | H75: 1.033 | I75: -20.207 | J75: 1.339 | K75: 1.024 | L75: 4.728 | M75: 1.984

Sheet May24 MPR Chart 3.10
A1: Section 3: Developments in the persistence of UK inflation
A3: Chart 3.10 - Projections for private sector regular average weekly earnings four-quarter growth
C5: Swathe of wage models
A6: Date | B6: May MPR | C6: Min | D6: Max
A7: 2022 Q1 | B7: 4.9 | C7: 4.6 | D7: 5.4
A8: 2022 Q2 | B8: 5.4 | C8: 5.3 | D8: 7.1
A9: 2022 Q3 | B9: 6.6 | C9: 5.9 | D9: 8.9
A10: 2022 Q4 | B10: 7.3 | C10: 5.8 | D10: 9.2
A11: 2023 Q1 | B11: 7.2 | C11: 5.1 | D11: 8.5
A12: 2023 Q2 | B12: 8.2 | C12: 4.3 | D12: 7.5
A13: 2023 Q3 | B13: 7.9 | C13: 4.2 | D13: 6.1
A14: 2023 Q4 | B14: 6.2 | C14: 4.1 | D14: 5.2
A15: 2024 Q1 (Bank staff projections) | B15: 6 | C15: 3.7 | D15: 4.6
A16: 2024 Q2 (Bank staff projections) | B16: 5.1 | C16: 3.6 | D16: 4.2
A17: 2024 Q3 (Bank staff projections) | B17: 4.8 | C17: 3.3 | D17: 3.9
A18: 2024 Q4 (Bank staff projections) | B18: 5 | C18: 3.3 | D18: 3.7
... A28: 2027 Q2 (Bank staff projections) | B28: 2.7 | C28: 2.5 | D28: 2.8

Sheet HAVERM
A1: 201001 !M | B1: D7BT@UK | C1: D7F5@UK | D1: KAJ4@UK
A2: .DESC | B2: UK: Consumer Price Index: All Items (NSA, 2015=100) | C2: UK: Consumer Price Index: All Services (NSA, 2015=100) | D2: Great Britain: AWE, Regular Pay: Private Sector [3Mo Mvg Avg vs Yr Ago] (SA, %)
A3: .T1 | B3: Jan-1988 | C3: Jan-1988 | D3: Mar-2001
A4: .TN | B4: Mar-2024 | C4: Mar-2024 | D4: Mar-2024
A5: .LSOURCE | B5: Office for National Statistics | C5: Office for National Statistics | D5: Office for National Statistics
A6: .DTLM | B6: Apr-17-2024 07:09 | C6: Apr-17-2024 07:09 | D6: May-14-2024 07:04
A7: 201001 | B7: 87.8 | C7: 83.9 | D7: 0.5
A8: 201002 | B8: 88.2 | C8: 84.1 | D8: 0.7
A9: 201003 | B9: 88.7 | C9: 84.4 | D9: 1
A10: 201004 | B10: 89.2 | C10: 84.9 | D10: 0.9
A11: 201005 | B11: 89.4 | C11: 85.2 | D11: 0.8
A12: 201006 | B12: 89.5 | C12: 85.7 | D12: 0.6
A13: 201007 | B13: 89.3 | C13: 86.1 | D13: 1
A14: 201008 | B14: 89.8 | C14: 86.7 | D14: 1.6
A15: 201009 | B15: 89.8 | C15: 85.9 | D15: 2
A16: 201010 | B16: 90 | C16: 86.3 | D16: 2
A17: 201011 | B17: 90.3 | C17: 86.1 | D17: 2
A18: 201012 | B18: 91.2 | C18: 87.2 | D18: 1.9
... A177: 202403 | B177: 133 | C177: 133.5 | D177: 5.9
