Workbook
Name Annual_Data: GMWA!$A$1:$A$2
Name Annual_Data: GMWQ!$A$1:$A$2

Sheet >>CHARTS
A2: * Start with how inflation is set to be much lower than previously expected - only want a few sentences, and then link to inflation RB. Could possibly include an inflation chart as the opener but that wouldn’t be ideal
A4: * Pay growth has remained strong, can link to various RBs and Penta stuff. January pay settlements still fairly high and NLW uplift in Jan is pretty big
A6: * Therefore, real pay growth now looks stronger
A8: * However, when fiscal drag is taken into account, real pay is set to rise but are still much lower than in 2021 - make a chart with pre vs post tax/NICs real wages to demonstrate this.
A10: * While smaller than previously expected given the fall back in swap/mortgage rates, net interest reciepts will be negative this year (rent inflation has also been high), which adds to households' cost burdens, so eats into disposable incomes
B12: - there's lots in previous RB's about this dymanic as well as the RF's 2024 Q1 macroeconomic policy outlook
A14: * Large part of it is that real income last year looks articifically strong given energy support payments, so looking at calendar year averages is a bit meaningless.
A16: * As a result, disposable income growth will fall on calendar year average terms this year, but this masks a pickup throughout the year and because there's no energy payments.
A18: * Finish with a comment or two on this meaning that we expect consumption to gather pace throughout this year - maybe our consumer spending breakdown forecast chart

Sheet >> DATA

Sheet Chart Data
A1: Real post-tax wages & salaries (2021=100) | M1: Contributions to real income v1 | AB1: Contributions to real income v2 | AP1: Debt interest payments & interest rates | AU1: Debt interest receipts & payments | AZ1: Pay and inflation | BE1: Contributions to consumption growth (annual)
B3: Gross | C3: Post-tax | D3: 100 LINE | F3: Gross salaries | G3: Post-tax salaries | H3: Prices | J3: Gross salaries per head | K3: Post-tax salaries per head | N3: Price inflation | O3: Income tax & NICs | P3: Other income | Q3: Employment growth | R3: Wage inflation | S3: Social benefits | T3: Real income | V3: PEDY! | W3: PC | X3: PEWFP cont | Y3: ER | Z3: PEWFP if EE flat | AC3: Price inflation | AD3: Income tax & NICs | AE3: Wages & salaries | AF3: Other income | AG3: Net interest | AH3: Social benefits | AI3: Real income | AQ3: Personal sector debt interest payments (LHS) | AR3: Average mortgage interest rates (RHS) | AS3: Bank Rate (RHS) | AV3: Interest receipts | AW3: Debt interest payments | AX3: Net interest receipts | BA3: CPI inflation | BB3: Nominal pay growth (incl bonus) | BC3: Real earnings growth | BF3: Nominal income | BG3: Inflation | BH3: Savings | BI3: Consumer spending growth
A4: 2015 | B4: =100*(F4/$H4) -> 93.409403 | C4: =100*(G4/$H4) -> 96.798299 | D4: 100 | F4: =100*(J4/AVERAGE($J$28:$J$31)) -> 84.940761 | G4: =100*(K4/AVERAGE($K$28:$K$31)) -> 88.022415 | H4: =100*(DataQ!I175/AVERAGE(DataQ!I$199:I$202)) -> 90.933844 | J4: =DataQ!F175/DataQ!J175 -> 7.1960317 | K4: =(DataQ!F175-DataQ!G175-DataQ!H175)/DataQ!J175 -> 5.0742929 | M4: 2019 | V4: =100*((DataA!B53/DataA!B52)-1) -> 3.6025096 | W4: =100*((DataA!J53+DataA!K53)/(DataA!L53+DataA!M53)) -> 100 | X4: =100*((DataA!C53-DataA!C52)/DataA!B52) -> 2.1285774 | Y4: =1000*(DataA!C53/DataA!D53) -> 32271.156 | Z4: =(Y4*DataA!$D$53)/1000 -> 892362 | AB4: 2019 | AP4: 2000 | AQ4: =(DataQ!N115/DataQ!P115)*100 -> 5.7792893 | AR4: =DataQ!Q115 -> 7.056667 | AS4: =DataQ!AF115 -> 5.861538 | AU4: 2000 | AV4: =(DataQ!O115/DataQ!P115)*100 -> 5.3684872 | AW4: =(DataQ!N115/DataQ!P115)*100 -> 5.7792893 | AX4: =(DataQ!AG115/DataQ!P115)*100 -> -0.41080207 | AZ4: 2013 | BA4: =((DataQ!E167/DataQ!E163)-1)*100 -> 2.7709541 | BB4: =((DataQ!D167/DataQ!D163)-1)*100 -> 0.51056893 | BC4: =BB4-BA4 -> -2.2603852 | BE4: 2010 | BF4: =((DataA!B44/DataA!B43)-1)*100 -> 1.9526692 | BG4: =-((DataA!E44/DataA!E43)-1)*100 -> -0.92666224 | BH4: =BI4-BF4-BG4 -> 1.150294 | BI4: =((DataA!L44/DataA!L43)-1)*100 -> 2.1763009
B5: =100*(F5/$H5) -> 93.708519 | C5: =100*(G5/H5) -> 96.664998 | D5: 100 | F5: =100*(J5/AVERAGE($J$28:$J$31)) -> 85.411708 | G5: =100*(K5/AVERAGE($K$28:$K$31)) -> 88.106425 | H5: =100*(DataQ!I176/AVERAGE(DataQ!I$199:I$202)) -> 91.146151 | J5: =DataQ!F176/DataQ!J176 -> 7.2359295 | K5: =(DataQ!F176-DataQ!G176-DataQ!H176)/DataQ!J176 -> 5.0791359 | M5: 2020 | N5: =-100*((W5/W4)-1) -> -0.5757341 | O5: =-100*((DataA!F54+DataA!G54)-(DataA!F53+DataA!G53))/DataA!$B53 -> 0.042946753 | P5: =V5-O5-Q5-R5-S5 -> -1.5864145 | Q5: =X5-R5 -> 0.22180141 | R5: =100*((Z5-Z4)/DataA!$B53) -> -0.08422039 | S5: =100*((DataA!H54-DataA!H53)/DataA!$B53) -> 1.4681045 | T5: =SUM(N5:S5) -> -0.51351636 | V5: =100*((DataA!B54/DataA!B53)-1) -> 0.062217732 | W5: =100*((DataA!J54+DataA!K54)/(DataA!L54+DataA!M54)) -> 100.57573 | X5: =100*((DataA!C54-DataA!C53)/DataA!B53) -> 0.13758102 | Y5: =1000*(DataA!C54/DataA!D54) -> 32226.903 | Z5: =(Y5*DataA!$D$53)/1000 -> 891138.31 | AB5: 2020 | AC5: =N5 -> -0.5757341 | AD5: =O5 -> 0.042946753 | AE5: =X5 -> 0.13758102 | AF5: =V5-AD5-AE5-AG5-AH5 -> -1.6659761 | AG5: =100*((DataA!I54-DataA!I53)/DataA!$B53) -> 0.079561613 | AH5: =S5 -> 1.4681045 | AI5: =SUM(AC5:AH5) -> -0.51351636 | AQ5: =(DataQ!N116/DataQ!P116)*100 -> 5.9470557 | AR5: =DataQ!Q116 -> 7.143333 | AS5: =DataQ!AF116 -> 6 | AV5: =(DataQ!O116/DataQ!P116)*100 -> 5.447434 | AW5: =(DataQ!N116/DataQ!P116)*100 -> 5.9470557 | AX5: =(DataQ!AG116/DataQ!P116)*100 -> -0.49962167 | BA5: =((DataQ!E168/DataQ!E164)-1)*100 -> 2.6791962 | BB5: =((DataQ!D168/DataQ!D164)-1)*100 -> 2.0983935 | BC5: =BB5-BA5 -> -0.58080276 | BE5: 2011 | BF5: =((DataA!B45/DataA!B44)-1)*100 -> 1.5023932 | BG5: =-((DataA!E45/DataA!E44)-1)*100 -> -3.9932641 | BH5: =BI5-BF5-BG5 -> 2.1250135 | BI5: =((DataA!L45/DataA!L44)-1)*100 -> -0.36585748
B6: =100*(F6/$H6) -> 94.123382 | C6: =100*(G6/H6) -> 97.664794 | D6: 100 | F6: =100*(J6/AVERAGE($J$28:$J$31)) -> 86.01187 | G6: =100*(K6/AVERAGE($K$28:$K$31)) -> 89.248084 | H6: =100*(DataQ!I177/AVERAGE(DataQ!I$199:I$202)) -> 91.382043 | J6: =DataQ!F177/DataQ!J177 -> 7.2867741 | K6: =(DataQ!F177-DataQ!G177-DataQ!H177)/DataQ!J177 -> 5.1449499 | M6: 2021 | N6: =-100*((W6/W5)-1) -> -2.2832455 | O6: =-100*((DataA!F55+DataA!G55)-(DataA!F54+DataA!G54))/DataA!$B54 -> -2.3153441 | P6: =V6-O6-Q6-R6-S6 -> 1.7245056 | Q6: =X6-R6 -> 0.64316052 | R6: =100*((Z6-Z5)/DataA!$B54) -> 3.1641367 | S6: =100*((DataA!H55-DataA!H54)/DataA!$B54) -> 0.52205637 | T6: =SUM(N6:S6) -> 1.4552696 | V6: =100*((DataA!B55/DataA!B54)-1) -> 3.7385151 | W6: =100*((DataA!J55+DataA!K55)/(DataA!L55+DataA!M55)) -> 102.87213 | X6: =100*((DataA!C55-DataA!C54)/DataA!B54) -> 3.8072972 | Y6: =1000*(DataA!C55/DataA!D55) -> 33890.519 | Z6: =(Y6*DataA!$D$53)/1000 -> 937140.62 | AB6: 2021 | AC6: =N6 -> -2.2832455 | AD6: =O6 -> -2.3153441 | AE6: =X6 -> 3.8072972 | AF6: =V6-AD6-AE6-AG6-AH6 -> 1.6145917 | AG6: =100*((DataA!I55-DataA!I54)/DataA!$B54) -> 0.10991384 | AH6: =S6 -> 0.52205637 | AI6: =SUM(AC6:AH6) -> 1.4552696 | AQ6: =(DataQ!N117/DataQ!P117)*100 -> 5.7773877 | AR6: =DataQ!Q117 -> 7.113333 | AS6: =DataQ!AF117 -> 6 | AV6: =(DataQ!O117/DataQ!P117)*100 -> 5.3145206 | AW6: =(DataQ!N117/DataQ!P117)*100 -> 5.7773877 | AX6: =(DataQ!AG117/DataQ!P117)*100 -> -0.46286705 | BA6: =((DataQ!E169/DataQ!E165)-1)*100 -> 2.7411484 | BB6: =((DataQ!D169/DataQ!D165)-1)*100 -> 0.64794816 | BC6: =BB6-BA6 -> -2.0932002 | BE6: 2012 | BF6: =((DataA!B46/DataA!B45)-1)*100 -> 4.1771019 | BG6: =-((DataA!E46/DataA!E45)-1)*100 -> -1.6745382 | BH6: =BI6-BF6-BG6 -> -0.73697644 | BI6: =((DataA!L46/DataA!L45)-1)*100 -> 1.7655873
B7: =100*(F7/$H7) -> 94.093175 | C7: =100*(G7/H7) -> 97.359528 | D7: 100 | F7: =100*(J7/AVERAGE($J$28:$J$31)) -> 86.08397 | G7: =100*(K7/AVERAGE($K$28:$K$31)) -> 89.072291 | H7: =100*(DataQ!I178/AVERAGE(DataQ!I$199:I$202)) -> 91.488006 | J7: =DataQ!F178/DataQ!J178 -> 7.2928823 | K7: =(DataQ!F178-DataQ!G178-DataQ!H178)/DataQ!J178 -> 5.1348159 | M7: 2022 | N7: =-100*((W7/W6)-1) -> -7.8364037 | O7: =-100*((DataA!F56+DataA!G56)-(DataA!F55+DataA!G55))/DataA!$B55 -> -2.1384825 | P7: =V7-O7-Q7-R7-S7 -> 2.7025916 | Q7: =X7-R7 -> 1.0550845 | R7: =100*((Z7-Z6)/DataA!$B55) -> 3.5800513 | S7: =100*((DataA!H56-DataA!H55)/DataA!$B55) -> 1.1564634 | T7: =SUM(N7:S7) -> -1.4806955 | V7: =100*((DataA!B56/DataA!B55)-1) -> 6.3557083 | W7: =100*((DataA!J56+DataA!K56)/(DataA!L56+DataA!M56)) -> 110.9336 | X7: =100*((DataA!C56-DataA!C55)/DataA!B55) -> 4.6351359 | Y7: =1000*(DataA!C56/DataA!D56) -> 35843.181 | Z7: =(Y7*DataA!$D$53)/1000 -> 991135.63 | AB7: 2022 | AC7: =N7 -> -7.8364037 | AD7: =O7 -> -2.1384825 | AE7: =X7 -> 4.6351359 | AF7: =V7-AD7-AE7-AG7-AH7 -> 2.5175389 | AG7: =100*((DataA!I56-DataA!I55)/DataA!$B55) -> 0.1850527 | AH7: =S7 -> 1.1564634 | AI7: =SUM(AC7:AH7) -> -1.4806955 | AQ7: =(DataQ!N118/DataQ!P118)*100 -> 5.7499034 | AR7: =DataQ!Q118 -> 7.056667 | AS7: =DataQ!AF118 -> 6 | AV7: =(DataQ!O118/DataQ!P118)*100 -> 4.552141 | AW7: =(DataQ!N118/DataQ!P118)*100 -> 5.7499034 | AX7: =(DataQ!AG118/DataQ!P118)*100 -> -1.1977623 | BA7: =((DataQ!E170/DataQ!E166)-1)*100 -> 2.0904694 | BB7: =((DataQ!D170/DataQ!D166)-1)*100 -> 1.0101082 | BC7: =BB7-BA7 -> -1.0803612 | BE7: 2013 | BF7: =((DataA!B47/DataA!B46)-1)*100 -> 4.1516968 | BG7: =-((DataA!E47/DataA!E46)-1)*100 -> -2.2226271 | BH7: =BI7-BF7-BG7 -> 0.89945054 | BI7: =((DataA!L47/DataA!L46)-1)*100 -> 2.8285203
A8: 2016 | B8: =100*(F8/$H8) -> 95.072928 | C8: =100*(G8/H8) -> 98.647093 | D8: 100 | F8: =100*(J8/AVERAGE($J$28:$J$31)) -> 87.090292 | G8: =100*(K8/AVERAGE($K$28:$K$31)) -> 90.364358 | H8: =100*(DataQ!I179/AVERAGE(DataQ!I$199:I$202)) -> 91.603671 | J8: =DataQ!F179/DataQ!J179 -> 7.3781361 | K8: =(DataQ!F179-DataQ!G179-DataQ!H179)/DataQ!J179 -> 5.2093006 | M8: 2023 | N8: =-100*((W8/W7)-1) -> -7.0184089 | O8: =-100*((DataA!F57+DataA!G57)-(DataA!F56+DataA!G56))/DataA!$B56 -> -1.7420286 | P8: =V8-O8-Q8-R8-S8 -> 3.9911164 | Q8: =X8-R8 -> 0.64331081 | R8: =100*((Z8-Z7)/DataA!$B56) -> 4.1668698 | S8: =100*((DataA!H57-DataA!H56)/DataA!$B56) -> 1.7838233 | T8: =SUM(N8:S8) -> 1.8246828 | V8: =100*((DataA!B57/DataA!B56)-1) -> 8.8430917 | W8: =100*((DataA!J57+DataA!K57)/(DataA!L57+DataA!M57)) -> 118.71937 | X8: =100*((DataA!C57-DataA!C56)/DataA!B56) -> 4.8101806 | Y8: =1000*(DataA!C57/DataA!D57) -> 38260.358 | Z8: =(Y8*DataA!$D$53)/1000 -> 1057975.4 | AB8: 2023 | AC8: =N8 -> -7.0184089 | AD8: =O8 -> -1.7420286 | AE8: =X8 -> 4.8101806 | AF8: =V8-AD8-AE8-AG8-AH8 -> 3.7295051 | AG8: =100*((DataA!I57-DataA!I56)/DataA!$B56) -> 0.26161126 | AH8: =S8 -> 1.7838233 | AI8: =SUM(AC8:AH8) -> 1.8246828 | AP8: 2001 | AQ8: =(DataQ!N119/DataQ!P119)*100 -> 5.7614058 | AR8: =DataQ!Q119 -> 6.936666 | AS8: =DataQ!AF119 -> 5.857692 | AU8: 2001 | AV8: =(DataQ!O119/DataQ!P119)*100 -> 5.2053466 | AW8: =(DataQ!N119/DataQ!P119)*100 -> 5.7614058 | AX8: =(DataQ!AG119/DataQ!P119)*100 -> -0.5560592 | AZ8: 2014 | BA8: =((DataQ!E171/DataQ!E167)-1)*100 -> 1.774751 | BB8: =((DataQ!D171/DataQ!D167)-1)*100 -> 1.7416547 | BC8: =BB8-BA8 -> -0.033096276 | BE8: 2014 | BF8: =((DataA!B48/DataA!B47)-1)*100 -> 3.4994719 | BG8: =-((DataA!E48/DataA!E47)-1)*100 -> -1.1496394 | BH8: =BI8-BF8-BG8 -> 0.67155499 | BI8: =((DataA!L48/DataA!L47)-1)*100 -> 3.0213874
B9: =100*(F9/$H9) -> 95.152912 | C9: =100*(G9/H9) -> 98.218701 | D9: 100 | F9: =100*(J9/AVERAGE($J$28:$J$31)) -> 87.562415 | G9: =100*(K9/AVERAGE($K$28:$K$31)) -> 90.383641 | H9: =100*(DataQ!I180/AVERAGE(DataQ!I$199:I$202)) -> 92.022843 | J9: =DataQ!F180/DataQ!J180 -> 7.4181336 | K9: =(DataQ!F180-DataQ!G180-DataQ!H180)/DataQ!J180 -> 5.2104122 | M9: 2024 | N9: =-100*((W9/W8)-1) -> -2.1814376 | O9: =-100*((DataA!F58+DataA!G58)-(DataA!F57+DataA!G57))/DataA!$B57 -> -1.0384226 | P9: =V9-O9-Q9-R9-S9 -> 0.034566165 | Q9: =X9-R9 -> 0.16863956 | R9: =100*((Z9-Z8)/DataA!$B57) -> 2.4975658 | S9: =100*((DataA!H58-DataA!H57)/DataA!$B57) -> 1.6195752 | T9: =SUM(N9:S9) -> 1.1004866 | V9: =100*((DataA!B58/DataA!B57)-1) -> 3.2819242 | W9: =100*((DataA!J58+DataA!K58)/(DataA!L58+DataA!M58)) -> 121.30916 | X9: =100*((DataA!C58-DataA!C57)/DataA!B57) -> 2.6662054 | Y9: =1000*(DataA!C58/DataA!D58) -> 39837.303 | Z9: =(Y9*DataA!$D$53)/1000 -> 1101581.1 | AB9: 2024 | AC9: =N9 -> -2.1814376 | AD9: =O9 -> -1.0384226 | AE9: =X9 -> 2.6662054 | AF9: =V9-AD9-AE9-AG9-AH9 -> 0.53764934 | AG9: =100*((DataA!I58-DataA!I57)/DataA!$B57) -> -0.50308318 | AH9: =S9 -> 1.6195752 | AI9: =SUM(AC9:AH9) -> 1.1004866 | AQ9: =(DataQ!N120/DataQ!P120)*100 -> 5.5112776 | AR9: =DataQ!Q120 -> 6.613333 | AS9: =DataQ!AF120 -> 5.369231 | AV9: =(DataQ!O120/DataQ!P120)*100 -> 4.4893574 | AW9: =(DataQ!N120/DataQ!P120)*100 -> 5.5112776 | AX9: =(DataQ!AG120/DataQ!P120)*100 -> -1.0219202 | BA9: =((DataQ!E172/DataQ!E168)-1)*100 -> 1.7621111 | BB9: =((DataQ!D172/DataQ!D168)-1)*100 -> -0.21261518 | BC9: =BB9-BA9 -> -1.9747263 | BE9: 2015 | BF9: =((DataA!B49/DataA!B48)-1)*100 -> 5.6910168 | BG9: =-((DataA!E49/DataA!E48)-1)*100 -> 0.369247 | BH9: =BI9-BF9-BG9 -> -3.1744905 | BI9: =((DataA!L49/DataA!L48)-1)*100 -> 2.8857733
B10: =100*(F10/$H10) -> 94.882419 | C10: =100*(G10/H10) -> 97.505549 | D10: 100 | F10: =100*(J10/AVERAGE($J$28:$J$31)) -> 87.998975 | G10: =100*(K10/AVERAGE($K$28:$K$31)) -> 90.431804 | H10: =100*(DataQ!I181/AVERAGE(DataQ!I$199:I$202)) -> 92.74529 | J10: =DataQ!F181/DataQ!J181 -> 7.4551182 | K10: =(DataQ!F181-DataQ!G181-DataQ!H181)/DataQ!J181 -> 5.2131887 | M10: 2025 | N10: =-100*((W10/W9)-1) -> -2.1173979 | O10: =-100*((DataA!F59+DataA!G59)-(DataA!F58+DataA!G58))/DataA!$B58 -> -1.2373822 | P10: =V10-O10-Q10-R10-S10 -> 1.7286071 | Q10: =X10-R10 -> 0.73105149 | R10: =100*((Z10-Z9)/DataA!$B58) -> 1.7142868 | S10: =100*((DataA!H59-DataA!H58)/DataA!$B58) -> 1.1545468 | T10: =SUM(N10:S10) -> 1.973712 | V10: =100*((DataA!B59/DataA!B58)-1) -> 4.09111 | W10: =100*((DataA!J59+DataA!K59)/(DataA!L59+DataA!M59)) -> 123.87776 | X10: =100*((DataA!C59-DataA!C58)/DataA!B58) -> 2.4453383 | Y10: =1000*(DataA!C59/DataA!D59) -> 40955.214 | Z10: =(Y10*DataA!$D$53)/1000 -> 1132493.6 | AB10: 2025 | AC10: =N10 -> -2.1173979 | AD10: =O10 -> -1.2373822 | AE10: =X10 -> 2.4453383 | AF10: =V10-AD10-AE10-AG10-AH10 -> 2.1122255 | AG10: =100*((DataA!I59-DataA!I58)/DataA!$B58) -> -0.38361842 | AH10: =S10 -> 1.1545468 | AI10: =SUM(AC10:AH10) -> 1.973712 | AQ10: =(DataQ!N121/DataQ!P121)*100 -> 5.2109808 | AR10: =DataQ!Q121 -> 6.35 | AS10: =DataQ!AF121 -> 5.053846 | AV10: =(DataQ!O121/DataQ!P121)*100 -> 4.1985677 | AW10: =(DataQ!N121/DataQ!P121)*100 -> 5.2109808 | AX10: =(DataQ!AG121/DataQ!P121)*100 -> -1.0124131 | BA10: =((DataQ!E173/DataQ!E169)-1)*100 -> 1.4521783 | BB10: =((DataQ!D173/DataQ!D169)-1)*100 -> 0.8583691 | BC10: =BB10-BA10 -> -0.59380922 | BE10: 2016 | BF10: =((DataA!B50/DataA!B49)-1)*100 -> 1.9559014 | BG10: =-((DataA!E50/DataA!E49)-1)*100 -> -1.2654209 | BH10: =BI10-BF10-BG10 -> 3.1532951 | BI10: =((DataA!L50/DataA!L49)-1)*100 -> 3.8437757
B11: =100*(F11/$H11) -> 94.397398 | C11: =100*(G11/H11) -> 96.787262 | D11: 100 | F11: =100*(J11/AVERAGE($J$28:$J$31)) -> 87.974981 | G11: =100*(K11/AVERAGE($K$28:$K$31)) -> 90.202248 | H11: =100*(DataQ!I182/AVERAGE(DataQ!I$199:I$202)) -> 93.196404 | J11: =DataQ!F182/DataQ!J182 -> 7.4530854 | K11: =(DataQ!F182-DataQ!G182-DataQ!H182)/DataQ!J182 -> 5.1999553 | M11: 2026 | N11: =-100*((W11/W10)-1) -> -2.2077422 | O11: =-100*((DataA!F60+DataA!G60)-(DataA!F59+DataA!G59))/DataA!$B59 -> -1.1740971 | P11: =V11-O11-Q11-R11-S11 -> 1.9262978 | Q11: =X11-R11 -> 0.71122178 | R11: =100*((Z11-Z10)/DataA!$B59) -> 1.6353431 | S11: =100*((DataA!H60-DataA!H59)/DataA!$B59) -> 1.0661806 | T11: =SUM(N11:S11) -> 1.9572041 | V11: =100*((DataA!B60/DataA!B59)-1) -> 4.1649463 | W11: =100*((DataA!J60+DataA!K60)/(DataA!L60+DataA!M60)) -> 126.61266 | X11: =100*((DataA!C60-DataA!C59)/DataA!B59) -> 2.3465649 | Y11: =1000*(DataA!C60/DataA!D60) -> 42065.274 | Z11: =(Y11*DataA!$D$53)/1000 -> 1163189 | AB11: 2026 | AC11: =N11 -> -2.2077422 | AD11: =O11 -> -1.1740971 | AE11: =X11 -> 2.3465649 | AF11: =V11-AD11-AE11-AG11-AH11 -> 2.3162431 | AG11: =100*((DataA!I60-DataA!I59)/DataA!$B59) -> -0.38994533 | AH11: =S11 -> 1.0661806 | AI11: =SUM(AC11:AH11) -> 1.9572041 | AQ11: =(DataQ!N122/DataQ!P122)*100 -> 4.6413811 | AR11: =DataQ!Q122 -> 5.846667 | AS11: =DataQ!AF122 -> 4.223485 | AV11: =(DataQ!O122/DataQ!P122)*100 -> 3.0958216 | AW11: =(DataQ!N122/DataQ!P122)*100 -> 4.6413811 | AX11: =(DataQ!AG122/DataQ!P122)*100 -> -1.5455595 | BA11: =((DataQ!E174/DataQ!E170)-1)*100 -> 0.90634441 | BB11: =((DataQ!D174/DataQ!D170)-1)*100 -> 1.9999927 | BC11: =BB11-BA11 -> 1.0936483 | BE11: 2017 | BF11: =((DataA!B51/DataA!B50)-1)*100 -> 2.7228076 | BG11: =-((DataA!E51/DataA!E50)-1)*100 -> -1.8555014 | BH11: =BI11-BF11-BG11 -> 0.86674481 | BI11: =((DataA!L51/DataA!L50)-1)*100 -> 1.734051
A12: 2017 | B12: =100*(F12/$H12) -> 95.632551 | C12: =100*(G12/H12) -> 96.90261 | D12: 100 | F12: =100*(J12/AVERAGE($J$28:$J$31)) -> 89.145083 | G12: =100*(K12/AVERAGE($K$28:$K$31)) -> 90.328985 | H12: =100*(DataQ!I183/AVERAGE(DataQ!I$199:I$202)) -> 93.216255 | J12: =DataQ!F183/DataQ!J183 -> 7.5522144 | K12: =(DataQ!F183-DataQ!G183-DataQ!H183)/DataQ!J183 -> 5.2072614 | AP12: 2002 | AQ12: =(DataQ!N123/DataQ!P123)*100 -> 4.5625929 | AR12: =DataQ!Q123 -> 5.513333 | AS12: =DataQ!AF123 -> 4 | AU12: 2002 | AV12: =(DataQ!O123/DataQ!P123)*100 -> 3.2817748 | AW12: =(DataQ!N123/DataQ!P123)*100 -> 4.5625929 | AX12: =(DataQ!AG123/DataQ!P123)*100 -> -1.2808181 | AZ12: 2015 | BA12: =((DataQ!E175/DataQ!E171)-1)*100 -> 0.10060362 | BB12: =((DataQ!D175/DataQ!D171)-1)*100 -> 2.2824609 | BC12: =BB12-BA12 -> 2.1818573 | BE12: 2018 | BF12: =((DataA!B52/DataA!B51)-1)*100 -> 4.1100965 | BG12: =-((DataA!E52/DataA!E51)-1)*100 -> -2.1055293 | BH12: =BI12-BF12-BG12 -> -0.34808905 | BI12: =((DataA!L52/DataA!L51)-1)*100 -> 1.6564782
B13: =100*(F13/$H13) -> 95.780085 | C13: =100*(G13/H13) -> 98.678979 | D13: 100 | F13: =100*(J13/AVERAGE($J$28:$J$31)) -> 89.967229 | G13: =100*(K13/AVERAGE($K$28:$K$31)) -> 92.690189 | H13: =100*(DataQ!I184/AVERAGE(DataQ!I$199:I$202)) -> 93.931039 | J13: =DataQ!F184/DataQ!J184 -> 7.6218652 | K13: =(DataQ!F184-DataQ!G184-DataQ!H184)/DataQ!J184 -> 5.3433795 | AQ13: =(DataQ!N124/DataQ!P124)*100 -> 4.6749902 | AR13: =DataQ!Q124 -> 5.436666 | AS13: =DataQ!AF124 -> 4 | AV13: =(DataQ!O124/DataQ!P124)*100 -> 3.4325677 | AW13: =(DataQ!N124/DataQ!P124)*100 -> 4.6749902 | AX13: =(DataQ!AG124/DataQ!P124)*100 -> -1.2424225 | BA13: =((DataQ!E176/DataQ!E172)-1)*100 -> -0.033266733 | BB13: =((DataQ!D176/DataQ!D172)-1)*100 -> 2.5568184 | BC13: =BB13-BA13 -> 2.5900851 | BE13: 2019 | BF13: =((DataA!B53/DataA!B52)-1)*100 -> 3.6025096 | BG13: =-((DataA!E53/DataA!E52)-1)*100 -> -1.4697096 | BH13: =BI13-BF13-BG13 -> -1.0170161 | BI13: =((DataA!L53/DataA!L52)-1)*100 -> 1.1157839
B14: =100*(F14/$H14) -> 96.107743 | C14: =100*(G14/H14) -> 99.286748 | D14: 100 | F14: =100*(J14/AVERAGE($J$28:$J$31)) -> 90.677718 | G14: =100*(K14/AVERAGE($K$28:$K$31)) -> 93.677112 | H14: =100*(DataQ!I185/AVERAGE(DataQ!I$199:I$202)) -> 94.350065 | J14: =DataQ!F185/DataQ!J185 -> 7.6820566 | K14: =(DataQ!F185-DataQ!G185-DataQ!H185)/DataQ!J185 -> 5.4002733 | AQ14: =(DataQ!N125/DataQ!P125)*100 -> 4.7875188 | AR14: =DataQ!Q125 -> 5.313334 | AS14: =DataQ!AF125 -> 4 | AV14: =(DataQ!O125/DataQ!P125)*100 -> 3.5414383 | AW14: =(DataQ!N125/DataQ!P125)*100 -> 4.7875188 | AX14: =(DataQ!AG125/DataQ!P125)*100 -> -1.2460805 | BA14: =((DataQ!E177/DataQ!E173)-1)*100 -> 0.033355537 | BB14: =((DataQ!D177/DataQ!D173)-1)*100 -> 2.9078085 | BC14: =BB14-BA14 -> 2.874453 | BE14: 2020 | BF14: =((DataA!B54/DataA!B53)-1)*100 -> 0.062217732 | BG14: =-((DataA!E54/DataA!E53)-1)*100 -> -0.15584022 | BH14: =BI14-BF14-BG14 -> -12.872187 | BI14: =((DataA!L54/DataA!L53)-1)*100 -> -12.965809
B15: =100*(F15/$H15) -> 95.865558 | C15: =100*(G15/H15) -> 97.828059 | D15: 100 | F15: =100*(J15/AVERAGE($J$28:$J$31)) -> 91.003414 | G15: =100*(K15/AVERAGE($K$28:$K$31)) -> 92.86638 | H15: =100*(DataQ!I186/AVERAGE(DataQ!I$199:I$202)) -> 94.928163 | J15: =DataQ!F186/DataQ!J186 -> 7.7096489 | K15: =(DataQ!F186-DataQ!G186-DataQ!H186)/DataQ!J186 -> 5.3535365 | AQ15: =(DataQ!N126/DataQ!P126)*100 -> 4.8748014 | AR15: =DataQ!Q126 -> 5.296667 | AS15: =DataQ!AF126 -> 4 | AV15: =(DataQ!O126/DataQ!P126)*100 -> 3.5554883 | AW15: =(DataQ!N126/DataQ!P126)*100 -> 4.8748014 | AX15: =(DataQ!AG126/DataQ!P126)*100 -> -1.3193131 | BA15: =((DataQ!E178/DataQ!E174)-1)*100 -> 0.099800399 | BB15: =((DataQ!D178/DataQ!D174)-1)*100 -> 1.8907563 | BC15: =BB15-BA15 -> 1.7909559 | BE15: 2021 | BF15: =((DataA!B55/DataA!B54)-1)*100 -> 3.7385151 | BG15: =-((DataA!E55/DataA!E54)-1)*100 -> -2.4044563 | BH15: =BI15-BF15-BG15 -> 6.1160868 | BI15: =((DataA!L55/DataA!L54)-1)*100 -> 7.4501457
A16: 2018 | B16: =100*(F16/$H16) -> 96.253213 | C16: =100*(G16/H16) -> 99.998493 | D16: 100 | F16: =100*(J16/AVERAGE($J$28:$J$31)) -> 91.876651 | G16: =100*(K16/AVERAGE($K$28:$K$31)) -> 95.451636 | H16: =100*(DataQ!I187/AVERAGE(DataQ!I$199:I$202)) -> 95.453075 | J16: =DataQ!F187/DataQ!J187 -> 7.7836281 | K16: =(DataQ!F187-DataQ!G187-DataQ!H187)/DataQ!J187 -> 5.5025706 | M16: Quarterly contributions to real income v1 | AB16: Quarterly contributions to real income v2 | AP16: 2003 | AQ16: =(DataQ!N127/DataQ!P127)*100 -> 4.8844779 | AR16: =DataQ!Q127 -> 5.173333 | AS16: =DataQ!AF127 -> 3.851563 | AU16: 2003 | AV16: =(DataQ!O127/DataQ!P127)*100 -> 3.5844799 | AW16: =(DataQ!N127/DataQ!P127)*100 -> 4.8844779 | AX16: =(DataQ!AG127/DataQ!P127)*100 -> -1.299998 | AZ16: 2016 | BA16: =((DataQ!E179/DataQ!E175)-1)*100 -> 0.33501508 | BB16: =((DataQ!D179/DataQ!D175)-1)*100 -> 2.1617782 | BC16: =BB16-BA16 -> 1.8267632 | BE16: 2022 | BF16: =((DataA!B56/DataA!B55)-1)*100 -> 6.3557083 | BG16: =-((DataA!E56/DataA!E55)-1)*100 -> -8.3294415 | BH16: =BI16-BF16-BG16 -> 6.7243323 | BI16: =((DataA!L56/DataA!L55)-1)*100 -> 4.7505992
B17: =100*(F17/$H17) -> 95.583106 | C17: =100*(G17/H17) -> 98.256227 | D17: 100 | F17: =100*(J17/AVERAGE($J$28:$J$31)) -> 91.516259 | G17: =100*(K17/AVERAGE($K$28:$K$31)) -> 94.075645 | H17: =100*(DataQ!I188/AVERAGE(DataQ!I$199:I$202)) -> 95.745224 | J17: =DataQ!F188/DataQ!J188 -> 7.7530963 | K17: =(DataQ!F188-DataQ!G188-DataQ!H188)/DataQ!J188 -> 5.4232479 | N17: Price inflation | O17: Income tax & NICs | P17: Other income | Q17: Employment growth | R17: Wage inflation | S17: Social benefits | T17: Real income | V17: PEDY! | W17: PC | X17: PEWFP cont | Y17: ER | Z17: PEWFP if EE flat | AC17: Price inflation | AD17: Income tax & NICs | AE17: Wages & salaries | AF17: Other income | AG17: Net interest | AH17: Social benefits | AI17: Real income | AQ17: =(DataQ!N128/DataQ!P128)*100 -> 4.8031426 | AR17: =DataQ!Q128 -> 5.01 | AS17: =DataQ!AF128 -> 3.75 | AV17: =(DataQ!O128/DataQ!P128)*100 -> 3.5924372 | AW17: =(DataQ!N128/DataQ!P128)*100 -> 4.8031426 | AX17: =(DataQ!AG128/DataQ!P128)*100 -> -1.2107054 | BA17: =((DataQ!E180/DataQ!E176)-1)*100 -> 0.33307784 | BB17: =((DataQ!D180/DataQ!D176)-1)*100 -> 2.5623409 | BC17: =BB17-BA17 -> 2.2292631 | BE17: 2023 | BF17: =((DataA!B57/DataA!B56)-1)*100 -> 8.8430917 | BG17: =-((DataA!E57/DataA!E56)-1)*100 -> -7.1222399 | BH17: =BI17-BF17-BG17 -> -1.4000169 | BI17: =((DataA!L57/DataA!L56)-1)*100 -> 0.32083487
B18: =100*(F18/$H18) -> 96.548701 | C18: =100*(G18/H18) -> 98.813666 | D18: 100 | F18: =100*(J18/AVERAGE($J$28:$J$31)) -> 92.973104 | G18: =100*(K18/AVERAGE($K$28:$K$31)) -> 95.154189 | H18: =100*(DataQ!I189/AVERAGE(DataQ!I$199:I$202)) -> 96.296588 | J18: =DataQ!F189/DataQ!J189 -> 7.8765176 | K18: =(DataQ!F189-DataQ!G189-DataQ!H189)/DataQ!J189 -> 5.4854235 | M18: 2019 01 | N18: =((W22/W18)-1)*-100 -> -1.514639 | O18: =-100*((DataQ!AN191+DataQ!AO191)-(DataQ!AN187+DataQ!AO187))/DataQ!AI187 -> -1.4634455 | S18: =100*((DataQ!AQ191-DataQ!AQ187)/DataQ!AI187) -> 0.53976954 | V18: =((DataQ!AI191/DataQ!AI187)-1)*100 -> 2.4265186 | W18: =100*((DataQ!AR187+DataQ!AS187)/(DataQ!AT187+DataQ!AU187)) -> 97.869959 | X18: =100*((DataQ!AK191-DataQ!AK187)/DataQ!AI187) -> 2.0776958 | Y18: =1000*(DataQ!AK191/DataQ!AM191) -> 7998.0792 | Z18: =(Y18*DataQ!AM191)/1000 -> 220691 | AQ18: =(DataQ!N129/DataQ!P129)*100 -> 4.5972279 | AR18: =DataQ!Q129 -> 4.85 | AS18: =DataQ!AF129 -> 3.526515 | AV18: =(DataQ!O129/DataQ!P129)*100 -> 3.3464683 | AW18: =(DataQ!N129/DataQ!P129)*100 -> 4.5972279 | AX18: =(DataQ!AG129/DataQ!P129)*100 -> -1.2507597 | BA18: =((DataQ!E181/DataQ!E177)-1)*100 -> 0.69883504 | BB18: =((DataQ!D181/DataQ!D177)-1)*100 -> 2.3432045 | BC18: =BB18-BA18 -> 1.6443695 | BE18: 2024 | BF18: =((DataA!B58/DataA!B57)-1)*100 -> 3.2819242 | BG18: =-((DataA!E58/DataA!E57)-1)*100 -> -2.1686235 | BH18: =BI18-BF18-BG18 -> -0.5142773 | BI18: =((DataA!L58/DataA!L57)-1)*100 -> 0.59902338
B19: =100*(F19/$H19) -> 96.966791 | C19: =100*(G19/H19) -> 98.824912 | D19: 100 | F19: =100*(J19/AVERAGE($J$28:$J$31)) -> 93.918557 | G19: =100*(K19/AVERAGE($K$28:$K$31)) -> 95.718266 | H19: =100*(DataQ!I190/AVERAGE(DataQ!I$199:I$202)) -> 96.856414 | J19: =DataQ!F190/DataQ!J190 -> 7.9566147 | K19: =(DataQ!F190-DataQ!G190-DataQ!H190)/DataQ!J190 -> 5.5179413 | M19: 2019 02 | N19: =((W23/W19)-1)*-100 -> -1.7494537 | O19: =-100*((DataQ!AN192+DataQ!AO192)-(DataQ!AN188+DataQ!AO188))/DataQ!AI188 -> -1.053786 | P19: =V19-O19-Q19-R19-S19 -> 1.8844952 | Q19: =X19-R19 -> 2.2863411 | R19: =100*((Z19-Z18)/DataQ!AI190) -> 0.98007874 | S19: =100*((DataQ!AQ192-DataQ!AQ188)/DataQ!AI188) -> 0.5578359 | T19: =SUM(N19:S19) -> 2.9055112 | V19: =((DataQ!AI192/DataQ!AI188)-1)*100 -> 4.654965 | W19: =100*((DataQ!AR188+DataQ!AS188)/(DataQ!AT188+DataQ!AU188)) -> 98.162564 | X19: =100*((DataQ!AK192-DataQ!AK188)/DataQ!AI188) -> 3.2664199 | Y19: =1000*(DataQ!AK192/DataQ!AM192) -> 8102.4251 | Z19: =(Y19*DataQ!AM192)/1000 -> 224186 | AC19: =N19 -> -1.7494537 | AD19: =O19 -> -1.053786 | AE19: =X19 -> 3.2664199 | AF19: =V19-AD19-AE19-AG19-AH19 -> 1.839939 | AG19: =100*((DataQ!AP192-DataQ!AP188)/DataQ!AI192) -> 0.044556171 | AH19: =S19 -> 0.5578359 | AI19: =SUM(AC19:AH19) -> 2.9055112 | AQ19: =(DataQ!N130/DataQ!P130)*100 -> 4.7074177 | AR19: =DataQ!Q130 -> 4.806667 | AS19: =DataQ!AF130 -> 3.651515 | AV19: =(DataQ!O130/DataQ!P130)*100 -> 3.6046058 | AW19: =(DataQ!N130/DataQ!P130)*100 -> 4.7074177 | AX19: =(DataQ!AG130/DataQ!P130)*100 -> -1.1028119 | BA19: =((DataQ!E182/DataQ!E178)-1)*100 -> 1.1964108 | BB19: =((DataQ!D182/DataQ!D178)-1)*100 -> 2.4742268 | BC19: =BB19-BA19 -> 1.277816 | BE19: 2025 | BF19: =((DataA!B59/DataA!B58)-1)*100 -> 4.09111 | BG19: =-((DataA!E59/DataA!E58)-1)*100 -> -2.1044183 | BH19: =BI19-BF19-BG19 -> 0.188089 | BI19: =((DataA!L59/DataA!L58)-1)*100 -> 2.1747807
A20: 2019 | B20: =100*(F20/$H20) -> 97.389031 | C20: =100*(G20/H20) -> 99.251344 | D20: 100 | F20: =100*(J20/AVERAGE($J$28:$J$31)) -> 94.407997 | G20: =100*(K20/AVERAGE($K$28:$K$31)) -> 96.213306 | H20: =100*(DataQ!I191/AVERAGE(DataQ!I$199:I$202)) -> 96.939046 | J20: =DataQ!F191/DataQ!J191 -> 7.9980792 | K20: =(DataQ!F191-DataQ!G191-DataQ!H191)/DataQ!J191 -> 5.5464792 | M20: 2019 03 | N20: =((W24/W20)-1)*-100 -> -1.5658765 | O20: =-100*((DataQ!AN193+DataQ!AO193)-(DataQ!AN189+DataQ!AO189))/DataQ!AI189 -> -0.6113836 | P20: =V20-O20-Q20-R20-S20 -> 2.2436409 | Q20: =X20-R20 -> 2.1367662 | R20: =100*((Z20-Z19)/DataQ!AI191) -> -0.17800039 | S20: =100*((DataQ!AQ193-DataQ!AQ189)/DataQ!AI189) -> 0.55919927 | T20: =SUM(N20:S20) -> 2.5843459 | V20: =((DataQ!AI193/DataQ!AI189)-1)*100 -> 4.1502224 | W20: =100*((DataQ!AR189+DataQ!AS189)/(DataQ!AT189+DataQ!AU189)) -> 98.74048 | X20: =100*((DataQ!AK193-DataQ!AK189)/DataQ!AI189) -> 1.9587658 | Y20: =1000*(DataQ!AK193/DataQ!AM193) -> 8093.845 | Z20: =(Y20*DataQ!AM193)/1000 -> 223552 | AC20: =N20 -> -1.5658765 | AD20: =O20 -> -0.6113836 | AE20: =X20 -> 1.9587658 | AF20: =V20-AD20-AE20-AG20-AH20 -> 2.2524024 | AG20: =100*((DataQ!AP193-DataQ!AP189)/DataQ!AI193) -> -0.0087615063 | AH20: =S20 -> 0.55919927 | AI20: =SUM(AC20:AH20) -> 2.5843459 | AP20: 2004 | AQ20: =(DataQ!N131/DataQ!P131)*100 -> 5.2115924 | AR20: =DataQ!Q131 -> 4.983333 | AS20: =DataQ!AF131 -> 3.903846 | AU20: 2004 | AV20: =(DataQ!O131/DataQ!P131)*100 -> 3.8180392 | AW20: =(DataQ!N131/DataQ!P131)*100 -> 5.2115924 | AX20: =(DataQ!AG131/DataQ!P131)*100 -> -1.3935532 | AZ20: 2017 | BA20: =((DataQ!E183/DataQ!E179)-1)*100 -> 2.170277 | BB20: =((DataQ!D183/DataQ!D179)-1)*100 -> 2.1843073 | BC20: =BB20-BA20 -> 0.014030333 | BE20: 2026 | BF20: =((DataA!B60/DataA!B59)-1)*100 -> 4.1649463 | BG20: =-((DataA!E60/DataA!E59)-1)*100 -> -2.1990121 | BH20: =BI20-BF20-BG20 -> 0.26466546 | BI20: =((DataA!L60/DataA!L59)-1)*100 -> 2.2305997
B21: =100*(F21/$H21) -> 98.207555 | C21: =100*(G21/H21) -> 100.79257 | D21: 100 | F21: =100*(J21/AVERAGE($J$28:$J$31)) -> 95.639678 | G21: =100*(K21/AVERAGE($K$28:$K$31)) -> 98.157105 | H21: =100*(DataQ!I192/AVERAGE(DataQ!I$199:I$202)) -> 97.385255 | J21: =DataQ!F192/DataQ!J192 -> 8.1024251 | K21: =(DataQ!F192-DataQ!G192-DataQ!H192)/DataQ!J192 -> 5.6585348 | M21: 2019 04 | N21: =((W25/W21)-1)*-100 -> -1.2057514 | O21: =-100*((DataQ!AN194+DataQ!AO194)-(DataQ!AN190+DataQ!AO190))/DataQ!AI190 -> 0.0075714238 | P21: =V21-O21-Q21-R21-S21 -> 1.5468138 | Q21: =X21-R21 -> 1.1318764 | R21: =100*((Z21-Z20)/DataQ!AI192) -> 0.10478951 | S21: =100*((DataQ!AQ194-DataQ!AQ190)/DataQ!AI190) -> 0.39427488 | T21: =SUM(N21:S21) -> 1.9795746 | V21: =((DataQ!AI194/DataQ!AI190)-1)*100 -> 3.185326 | W21: =100*((DataQ!AR190+DataQ!AS190)/(DataQ!AT190+DataQ!AU190)) -> 99.285766 | X21: =100*((DataQ!AK194-DataQ!AK190)/DataQ!AI190) -> 1.2366659 | Y21: =1000*(DataQ!AK194/DataQ!AM194) -> 8076.6429 | Z21: =(Y21*DataQ!AM194)/1000 -> 223933 | AC21: =N21 -> -1.2057514 | AD21: =O21 -> 0.0075714238 | AE21: =X21 -> 1.2366659 | AF21: =V21-AD21-AE21-AG21-AH21 -> 1.4739804 | AG21: =100*((DataQ!AP194-DataQ!AP190)/DataQ!AI194) -> 0.07283341 | AH21: =S21 -> 0.39427488 | AI21: =SUM(AC21:AH21) -> 1.9795746 | AQ21: =(DataQ!N132/DataQ!P132)*100 -> 5.6404989 | AR21: =DataQ!Q132 -> 5.103333 | AS21: =DataQ!AF132 -> 4.211538 | AV21: =(DataQ!O132/DataQ!P132)*100 -> 4.2882115 | AW21: =(DataQ!N132/DataQ!P132)*100 -> 5.6404989 | AX21: =(DataQ!AG132/DataQ!P132)*100 -> -1.3522873 | BA21: =((DataQ!E184/DataQ!E180)-1)*100 -> 2.7556773 | BB21: =((DataQ!D184/DataQ!D180)-1)*100 -> 2.1606886 | BC21: =BB21-BA21 -> -0.59498871
B22: =100*(F22/$H22) -> 97.728172 | C22: =100*(G22/H22) -> 99.983057 | D22: 100 | F22: =100*(J22/AVERAGE($J$28:$J$31)) -> 95.538401 | G22: =100*(K22/AVERAGE($K$28:$K$31)) -> 97.742761 | H22: =100*(DataQ!I193/AVERAGE(DataQ!I$199:I$202)) -> 97.759324 | J22: =DataQ!F193/DataQ!J193 -> 8.093845 | K22: =(DataQ!F193-DataQ!G193-DataQ!H193)/DataQ!J193 -> 5.6346488 | M22: 2020 01 | N22: =((W26/W22)-1)*-100 -> -0.76748488 | O22: =-100*((DataQ!AN195+DataQ!AO195)-(DataQ!AN191+DataQ!AO191))/DataQ!AI191 -> -0.26531603 | P22: =V22-O22-Q22-R22-S22 -> -0.34308592 | Q22: =X22-R22 -> 0.91936277 | R22: =100*((Z22-Z21)/DataQ!AI193) -> 0.35976935 | S22: =100*((DataQ!AQ195-DataQ!AQ191)/DataQ!AI191) -> 0.99528608 | T22: =SUM(N22:S22) -> 0.89853136 | V22: =((DataQ!AI195/DataQ!AI191)-1)*100 -> 1.6660162 | W22: =100*((DataQ!AR191+DataQ!AS191)/(DataQ!AT191+DataQ!AU191)) -> 99.352336 | X22: =100*((DataQ!AK195-DataQ!AK191)/DataQ!AI191) -> 1.2791321 | Y22: =1000*(DataQ!AK195/DataQ!AM195) -> 8091.6406 | Z22: =(Y22*DataQ!AM195)/1000 -> 225247 | AB22: 2020 | AC22: =N26 -> -1.71951 | AD22: =O22 -> -0.26531603 | AE22: =X22 -> 1.2791321 | AF22: =V22-AD22-AE22-AG22-AH22 -> -0.44940632 | AG22: =100*((DataQ!AP195-DataQ!AP191)/DataQ!AI195) -> 0.1063204 | AH22: =S22 -> 0.99528608 | AI22: =SUM(AC22:AH22) -> -0.053493787 | AQ22: =(DataQ!N133/DataQ!P133)*100 -> 6.2995609 | AR22: =DataQ!Q133 -> 5.463333 | AS22: =DataQ!AF133 -> 4.655303 | AV22: =(DataQ!O133/DataQ!P133)*100 -> 4.9669167 | AW22: =(DataQ!N133/DataQ!P133)*100 -> 6.2995609 | AX22: =(DataQ!AG133/DataQ!P133)*100 -> -1.3326442 | BA22: =((DataQ!E185/DataQ!E181)-1)*100 -> 2.8089548 | BB22: =((DataQ!D185/DataQ!D181)-1)*100 -> 2.3569091 | BC22: =BB22-BA22 -> -0.4520457
B23: =100*(F23/$H23) -> 97.363932 | C23: =100*(G23/H23) -> 100.11057 | D23: 100 | F23: =100*(J23/AVERAGE($J$28:$J$31)) -> 95.335349 | G23: =100*(K23/AVERAGE($K$28:$K$31)) -> 98.024758 | H23: =100*(DataQ!I194/AVERAGE(DataQ!I$199:I$202)) -> 97.916495 | J23: =DataQ!F194/DataQ!J194 -> 8.0766429 | K23: =(DataQ!F194-DataQ!G194-DataQ!H194)/DataQ!J194 -> 5.6509053 | M23: 2020 02 | N23: =((W27/W23)-1)*-100 -> -0.95483806 | O23: =-100*((DataQ!AN196+DataQ!AO196)-(DataQ!AN192+DataQ!AO192))/DataQ!AI192 -> 0.96785905 | P23: =V23-O23-Q23-R23-S23 -> -2.6783209 | Q23: =X23-R23 -> 0.26676448 | R23: =100*((Z23-Z22)/DataQ!AI194) -> -2.0809157 | S23: =100*((DataQ!AQ196-DataQ!AQ192)/DataQ!AI192) -> 1.494282 | T23: =SUM(N23:S23) -> -2.9851693 | V23: =((DataQ!AI196/DataQ!AI192)-1)*100 -> -2.0303312 | W23: =100*((DataQ!AR192+DataQ!AS192)/(DataQ!AT192+DataQ!AU192)) -> 99.879872 | X23: =100*((DataQ!AK196-DataQ!AK192)/DataQ!AI192) -> -1.8141513 | Y23: =1000*(DataQ!AK196/DataQ!AM196) -> 7847.5854 | Z23: =(Y23*DataQ!AM196)/1000 -> 217590 | AB23: 2020 02 | AC23: =N27 -> -1.0241449 | AD23: =O23 -> 0.96785905 | AE23: =X23 -> -1.8141513 | AF23: =V23-AD23-AE23-AG23-AH23 -> -2.7656305 | AG23: =100*((DataQ!AP196-DataQ!AP192)/DataQ!AI196) -> 0.087309519 | AH23: =S23 -> 1.494282 | AI23: =SUM(AC23:AH23) -> -3.0544761 | AQ23: =(DataQ!N134/DataQ!P134)*100 -> 6.4537855 | AR23: =DataQ!Q134 -> 5.573333 | AS23: =DataQ!AF134 -> 4.75 | AV23: =(DataQ!O134/DataQ!P134)*100 -> 5.0730722 | AW23: =(DataQ!N134/DataQ!P134)*100 -> 6.4537855 | AX23: =(DataQ!AG134/DataQ!P134)*100 -> -1.3807134 | BA23: =((DataQ!E186/DataQ!E182)-1)*100 -> 3.0213793 | BB23: =((DataQ!D186/DataQ!D182)-1)*100 -> 2.6827565 | BC23: =BB23-BA23 -> -0.33862277
A24: 2020 | B24: =100*(F24/$H24) -> 98.083586 | C24: =100*(G24/H24) -> 100.24812 | D24: 100 | F24: =100*(J24/AVERAGE($J$28:$J$31)) -> 95.51238 | G24: =100*(K24/AVERAGE($K$28:$K$31)) -> 97.620175 | H24: =100*(DataQ!I195/AVERAGE(DataQ!I$199:I$202)) -> 97.378557 | J24: =DataQ!F195/DataQ!J195 -> 8.0916406 | K24: =(DataQ!F195-DataQ!G195-DataQ!H195)/DataQ!J195 -> 5.627582 | M24: 2020 03 | N24: =((W28/W24)-1)*-100 -> -0.43518509 | O24: =-100*((DataQ!AN197+DataQ!AO197)-(DataQ!AN193+DataQ!AO193))/DataQ!AI193 -> 0.86656773 | P24: =V24-O24-Q24-R24-S24 -> -1.7060296 | Q24: =X24-R24 -> -1.6441631 | R24: =100*((Z24-Z23)/DataQ!AI195) -> 1.3791275 | S24: =100*((DataQ!AQ197-DataQ!AQ193)/DataQ!AI193) -> 1.669067 | T24: =SUM(N24:S24) -> 0.12938448 | V24: =((DataQ!AI197/DataQ!AI193)-1)*100 -> 0.56456956 | W24: =100*((DataQ!AR193+DataQ!AS193)/(DataQ!AT193+DataQ!AU193)) -> 100.28663 | X24: =100*((DataQ!AK197-DataQ!AK193)/DataQ!AI193) -> -0.26503557 | Y24: =1000*(DataQ!AK197/DataQ!AM197) -> 8025.9619 | Z24: =(Y24*DataQ!AM197)/1000 -> 222584 | AB24: 2020 03 | AC24: =N28 -> -2.3665684 | AD24: =O24 -> 0.86656773 | AE24: =X24 -> -0.26503557 | AF24: =V24-AD24-AE24-AG24-AH24 -> -1.8465157 | AG24: =100*((DataQ!AP197-DataQ!AP193)/DataQ!AI197) -> 0.14048615 | AH24: =S24 -> 1.669067 | AI24: =SUM(AC24:AH24) -> -1.8019989 | AP24: 2005 | AQ24: =(DataQ!N135/DataQ!P135)*100 -> 6.3325732 | AR24: =DataQ!Q135 -> 5.53 | AS24: =DataQ!AF135 -> 4.75 | AU24: 2005 | AV24: =(DataQ!O135/DataQ!P135)*100 -> 4.6846509 | AW24: =(DataQ!N135/DataQ!P135)*100 -> 6.3325732 | AX24: =(DataQ!AG135/DataQ!P135)*100 -> -1.6479223 | AZ24: 2018 | BA24: =((DataQ!E187/DataQ!E183)-1)*100 -> 2.712451 | BB24: =((DataQ!D187/DataQ!D183)-1)*100 -> 2.6052104 | BC24: =BB24-BA24 -> -0.10724056
B25: =100*(F25/$H25) -> 95.074737 | C25: =100*(G25/H25) -> 98.559417 | D25: 100 | F25: =100*(J25/AVERAGE($J$28:$J$31)) -> 92.631593 | G25: =100*(K25/AVERAGE($K$28:$K$31)) -> 96.026726 | H25: =100*(DataQ!I196/AVERAGE(DataQ!I$199:I$202)) -> 97.43029 | J25: =DataQ!F196/DataQ!J196 -> 7.8475854 | K25: =(DataQ!F196-DataQ!G196-DataQ!H196)/DataQ!J196 -> 5.5357233 | M25: 2020 04 | N25: =((W29/W25)-1)*-100 -> -0.23410065 | O25: =-100*((DataQ!AN198+DataQ!AO198)-(DataQ!AN194+DataQ!AO194))/DataQ!AI194 -> -1.3900854 | P25: =V25-O25-Q25-R25-S25 -> -1.5922797 | Q25: =X25-R25 -> -0.42363611 | R25: =100*((Z25-Z24)/DataQ!AI196) -> 1.7843708 | S25: =100*((DataQ!AQ198-DataQ!AQ194)/DataQ!AI194) -> 1.7004427 | T25: =SUM(N25:S25) -> -0.15528837 | V25: =((DataQ!AI198/DataQ!AI194)-1)*100 -> 0.078812272 | W25: =100*((DataQ!AR194+DataQ!AS194)/(DataQ!AT194+DataQ!AU194)) -> 100.48291 | X25: =100*((DataQ!AK198-DataQ!AK194)/DataQ!AI194) -> 1.3607346 | Y25: =1000*(DataQ!AK198/DataQ!AM198) -> 8261.7011 | Z25: =(Y25*DataQ!AM198)/1000 -> 228940 | AB25: 2020 04 | AC25: =N29 -> -3.7649328 | AD25: =O25 -> -1.3900854 | AE25: =X25 -> 1.3607346 | AF25: =V25-AD25-AE25-AG25-AH25 -> -1.5770727 | AG25: =100*((DataQ!AP198-DataQ!AP194)/DataQ!AI198) -> -0.015206937 | AH25: =S25 -> 1.7004427 | AI25: =SUM(AC25:AH25) -> -3.6861205 | AQ25: =(DataQ!N136/DataQ!P136)*100 -> 6.670821 | AR25: =DataQ!Q136 -> 5.503334 | AS25: =DataQ!AF136 -> 4.75 | AV25: =(DataQ!O136/DataQ!P136)*100 -> 4.8799541 | AW25: =(DataQ!N136/DataQ!P136)*100 -> 6.670821 | AX25: =(DataQ!AG136/DataQ!P136)*100 -> -1.7908668 | BA25: =((DataQ!E188/DataQ!E184)-1)*100 -> 2.4232625 | BB25: =((DataQ!D188/DataQ!D184)-1)*100 -> 2.445486 | BC25: =BB25-BA25 -> 0.022223406
B26: =100*(F26/$H26) -> 96.799624 | C26: =100*(G26/H26) -> 100.86789 | D26: 100 | F26: =100*(J26/AVERAGE($J$28:$J$31)) -> 94.737119 | G26: =100*(K26/AVERAGE($K$28:$K$31)) -> 98.718705 | H26: =100*(DataQ!I197/AVERAGE(DataQ!I$199:I$202)) -> 97.869304 | J26: =DataQ!F197/DataQ!J197 -> 8.0259619 | K26: =(DataQ!F197-DataQ!G197-DataQ!H197)/DataQ!J197 -> 5.6909097 | M26: 2021 01 | N26: =((W30/W26)-1)*-100 -> -1.71951 | O26: =-100*((DataQ!AN199+DataQ!AO199)-(DataQ!AN195+DataQ!AO195))/DataQ!AI195 -> -1.0858489 | P26: =V26-O26-Q26-R26-S26 -> 1.5456501 | Q26: =X26-R26 -> 1.0227545 | R26: =100*((Z26-Z25)/DataQ!AI197) -> 0.20310594 | S26: =100*((DataQ!AQ199-DataQ!AQ195)/DataQ!AI195) -> 1.5194152 | T26: =SUM(N26:S26) -> 1.4855668 | V26: =((DataQ!AI199/DataQ!AI195)-1)*100 -> 3.2050769 | W26: =100*((DataQ!AR195+DataQ!AS195)/(DataQ!AT195+DataQ!AU195)) -> 100.11485 | X26: =100*((DataQ!AK199-DataQ!AK195)/DataQ!AI195) -> 1.2258604 | Y26: =1000*(DataQ!AK199/DataQ!AM199) -> 8270.7141 | Z26: =(Y26*DataQ!AM199)/1000 -> 229686 | AB26: 2021 | AC26: =N30 -> -4.7942558 | AD26: =O26 -> -1.0858489 | AE26: =X26 -> 1.2258604 | AF26: =V26-AD26-AE26-AG26-AH26 -> 1.5036399 | AG26: =100*((DataQ!AP199-DataQ!AP195)/DataQ!AI199) -> 0.042010173 | AH26: =S26 -> 1.5194152 | AI26: =SUM(AC26:AH26) -> -1.5891789 | AQ26: =(DataQ!N137/DataQ!P137)*100 -> 6.6230333 | AR26: =DataQ!Q137 -> 5.476666 | AS26: =DataQ!AF137 -> 4.590909 | AV26: =(DataQ!O137/DataQ!P137)*100 -> 5.0670329 | AW26: =(DataQ!N137/DataQ!P137)*100 -> 6.6230333 | AX26: =(DataQ!AG137/DataQ!P137)*100 -> -1.5560004 | BA26: =((DataQ!E189/DataQ!E185)-1)*100 -> 2.5072324 | BB26: =((DataQ!D189/DataQ!D185)-1)*100 -> 3.0920919 | BC26: =BB26-BA26 -> 0.5848595
B27: =100*(F27/$H27) -> 99.581324 | C27: =100*(G27/H27) -> 100.08216 | D27: 100 | F27: =100*(J27/AVERAGE($J$28:$J$31)) -> 97.519746 | G27: =100*(K27/AVERAGE($K$28:$K$31)) -> 98.010212 | H27: =100*(DataQ!I198/AVERAGE(DataQ!I$199:I$202)) -> 97.929755 | J27: =DataQ!F198/DataQ!J198 -> 8.2617011 | K27: =(DataQ!F198-DataQ!G198-DataQ!H198)/DataQ!J198 -> 5.6500668 | M27: 2021 02 | N27: =((W31/W27)-1)*-100 -> -1.0241449 | O27: =-100*((DataQ!AN200+DataQ!AO200)-(DataQ!AN196+DataQ!AO196))/DataQ!AI196 -> -3.2051858 | P27: =V27-O27-Q27-R27-S27 -> 2.9109724 | Q27: =X27-R27 -> 3.4589209 | R27: =100*((Z27-Z26)/DataQ!AI198) -> 1.8658368 | S27: =100*((DataQ!AQ200-DataQ!AQ196)/DataQ!AI196) -> 0.40819306 | T27: =SUM(N27:S27) -> 4.4145924 | V27: =((DataQ!AI200/DataQ!AI196)-1)*100 -> 5.4387374 | W27: =100*((DataQ!AR196+DataQ!AS196)/(DataQ!AT196+DataQ!AU196)) -> 100.83356 | X27: =100*((DataQ!AK200-DataQ!AK196)/DataQ!AI196) -> 5.3247577 | Y27: =1000*(DataQ!AK200/DataQ!AM200) -> 8477.8339 | Z27: =(Y27*DataQ!AM200)/1000 -> 236557 | AB27: 2021 02 | AC27: =N31 -> -7.770287 | AD27: =O27 -> -3.2051858 | AE27: =X27 -> 5.3247577 | AF27: =V27-AD27-AE27-AG27-AH27 -> 2.81938 | AG27: =100*((DataQ!AP200-DataQ!AP196)/DataQ!AI200) -> 0.091592403 | AH27: =S27 -> 0.40819306 | AI27: =SUM(AC27:AH27) -> -2.3315496 | AQ27: =(DataQ!N138/DataQ!P138)*100 -> 6.5978371 | AR27: =DataQ!Q138 -> 5.35 | AS27: =DataQ!AF138 -> 4.5 | AV27: =(DataQ!O138/DataQ!P138)*100 -> 4.78819 | AW27: =(DataQ!N138/DataQ!P138)*100 -> 6.5978371 | AX27: =(DataQ!AG138/DataQ!P138)*100 -> -1.809647 | BA27: =((DataQ!E190/DataQ!E186)-1)*100 -> 2.2632444 | BB27: =((DataQ!D190/DataQ!D186)-1)*100 -> 3.4617964 | BC27: =BB27-BA27 -> 1.198552
A28: 2021 | B28: =100*(F28/$H28) -> 98.762031 | C28: =100*(G28/H28) -> 99.31108 | D28: 100 | F28: =100*(J28/AVERAGE($J$28:$J$31)) -> 97.626133 | G28: =100*(K28/AVERAGE($K$28:$K$31)) -> 98.168867 | H28: =100*(DataQ!I199/AVERAGE(DataQ!I$199:I$202)) -> 98.849864 | J28: =DataQ!F199/DataQ!J199 -> 8.2707141 | K28: =(DataQ!F199-DataQ!G199-DataQ!H199)/DataQ!J199 -> 5.6592128 | M28: 2021 03 | N28: =((W32/W28)-1)*-100 -> -2.3665684 | O28: =-100*((DataQ!AN201+DataQ!AO201)-(DataQ!AN197+DataQ!AO197))/DataQ!AI197 -> -3.1527705 | P28: =V28-O28-Q28-R28-S28 -> 1.1846032 | Q28: =X28-R28 -> 3.8196132 | R28: =100*((Z28-Z27)/DataQ!AI199) -> 0.87632687 | S28: =100*((DataQ!AQ201-DataQ!AQ197)/DataQ!AI197) -> 0.238772 | T28: =SUM(N28:S28) -> 0.59997626 | V28: =((DataQ!AI201/DataQ!AI197)-1)*100 -> 2.9665447 | W28: =100*((DataQ!AR197+DataQ!AS197)/(DataQ!AT197+DataQ!AU197)) -> 100.72307 | X28: =100*((DataQ!AK201-DataQ!AK197)/DataQ!AI197) -> 4.6959401 | Y28: =1000*(DataQ!AK201/DataQ!AM201) -> 8512.8314 | Z28: =(Y28*DataQ!AM201)/1000 -> 239832 | AB28: 2021 03 | AC28: =N32 -> -8.9569193 | AD28: =O28 -> -3.1527705 | AE28: =X28 -> 4.6959401 | AF28: =V28-AD28-AE28-AG28-AH28 -> 1.0973459 | AG28: =100*((DataQ!AP201-DataQ!AP197)/DataQ!AI201) -> 0.087257266 | AH28: =S28 -> 0.238772 | AI28: =SUM(AC28:AH28) -> -5.9903746 | AP28: 2006 | AQ28: =(DataQ!N139/DataQ!P139)*100 -> 6.624246 | AR28: =DataQ!Q139 -> 5.326667 | AS28: =DataQ!AF139 -> 4.5 | AU28: 2006 | AV28: =(DataQ!O139/DataQ!P139)*100 -> 4.7810343 | AW28: =(DataQ!N139/DataQ!P139)*100 -> 6.624246 | AX28: =(DataQ!AG139/DataQ!P139)*100 -> -1.8432117 | AZ28: 2019 | BA28: =((DataQ!E191/DataQ!E187)-1)*100 -> 1.8453383 | BB28: =((DataQ!D191/DataQ!D187)-1)*100 -> 3.2552148 | BC28: =BB28-BA28 -> 1.4098766
B29: =100*(F29/$H29) -> 100.97484 | C29: =100*(G29/H29) -> 101.01901 | D29: 100 | F29: =100*(J29/AVERAGE($J$28:$J$31)) -> 100.07094 | G29: =100*(K29/AVERAGE($K$28:$K$31)) -> 100.11472 | H29: =100*(DataQ!I200/AVERAGE(DataQ!I$199:I$202)) -> 99.104827 | J29: =DataQ!F200/DataQ!J200 -> 8.4778339 | K29: =(DataQ!F200-DataQ!G200-DataQ!H200)/DataQ!J200 -> 5.7713866 | M29: 2021 04 | N29: =((W33/W29)-1)*-100 -> -3.7649328 | O29: =-100*((DataQ!AN202+DataQ!AO202)-(DataQ!AN198+DataQ!AO198))/DataQ!AI198 -> -1.8283626 | P29: =V29-O29-Q29-R29-S29 -> 1.2912318 | Q29: =X29-R29 -> 2.9779089 | R29: =100*((Z29-Z28)/DataQ!AI200) -> 1.0136403 | S29: =100*((DataQ!AQ202-DataQ!AQ198)/DataQ!AI198) -> -0.065987242 | T29: =SUM(N29:S29) -> -0.37650149 | V29: =((DataQ!AI202/DataQ!AI198)-1)*100 -> 3.3884313 | W29: =100*((DataQ!AR198+DataQ!AS198)/(DataQ!AT198+DataQ!AU198)) -> 100.71814 | X29: =100*((DataQ!AK202-DataQ!AK198)/DataQ!AI198) -> 3.9915493 | Y29: =1000*(DataQ!AK202/DataQ!AM202) -> 8625.9161 | Z29: =(Y29*DataQ!AM202)/1000 -> 243639 | AB29: 2021 04 | AC29: =N33 -> -9.9682814 | AD29: =O29 -> -1.8283626 | AE29: =X29 -> 3.9915493 | AF29: =V29-AD29-AE29-AG29-AH29 -> 1.0897773 | AG29: =100*((DataQ!AP202-DataQ!AP198)/DataQ!AI202) -> 0.20145457 | AH29: =S29 -> -0.065987242 | AI29: =SUM(AC29:AH29) -> -6.5798501 | AQ29: =(DataQ!N140/DataQ!P140)*100 -> 6.6959106 | AR29: =DataQ!Q140 -> 5.31 | AS29: =DataQ!AF140 -> 4.5 | AV29: =(DataQ!O140/DataQ!P140)*100 -> 4.7506287 | AW29: =(DataQ!N140/DataQ!P140)*100 -> 6.6959106 | AX29: =(DataQ!AG140/DataQ!P140)*100 -> -1.9452819 | BA29: =((DataQ!E192/DataQ!E188)-1)*100 -> 2.0188953 | BB29: =((DataQ!D192/DataQ!D188)-1)*100 -> 3.9354772 | BC29: =BB29-BA29 -> 1.9165819
B30: =100*(F30/$H30) -> 100.14798 | C30: =100*(G30/H30) -> 100.33017 | D30: 100 | F30: =100*(J30/AVERAGE($J$28:$J$31)) -> 100.48405 | G30: =100*(K30/AVERAGE($K$28:$K$31)) -> 100.66685 | H30: =100*(DataQ!I201/AVERAGE(DataQ!I$199:I$202)) -> 100.33557 | J30: =DataQ!F201/DataQ!J201 -> 8.5128314 | K30: =(DataQ!F201-DataQ!G201-DataQ!H201)/DataQ!J201 -> 5.8032158 | M30: 2022 01 | N30: =((W34/W30)-1)*-100 -> -4.7942558 | O30: =-100*((DataQ!AN203+DataQ!AO203)-(DataQ!AN199+DataQ!AO199))/DataQ!AI199 -> -2.4406038 | P30: =V30-O30-Q30-R30-S30 -> 1.1182198 | Q30: =X30-R30 -> 3.7522512 | R30: =100*((Z30-Z29)/DataQ!AI201) -> 1.5621695 | S30: =100*((DataQ!AQ203-DataQ!AQ199)/DataQ!AI199) -> -0.064754535 | T30: =SUM(N30:S30) -> -0.86697353 | V30: =((DataQ!AI203/DataQ!AI199)-1)*100 -> 3.9272823 | W30: =100*((DataQ!AR199+DataQ!AS199)/(DataQ!AT199+DataQ!AU199)) -> 101.83633 | X30: =100*((DataQ!AK203-DataQ!AK199)/DataQ!AI199) -> 5.3144207 | Y30: =1000*(DataQ!AK203/DataQ!AM203) -> 8834.7731 | Z30: =(Y30*DataQ!AM203)/1000 -> 249547 | AB30: 2022 | AC30: =N34 -> -9.6638336 | AD30: =O30 -> -2.4406038 | AE30: =X30 -> 5.3144207 | AF30: =V30-AD30-AE30-AG30-AH30 -> 0.90349054 | AG30: =100*((DataQ!AP203-DataQ!AP199)/DataQ!AI203) -> 0.2147293 | AH30: =S30 -> -0.064754535 | AI30: =SUM(AC30:AH30) -> -5.7365513 | AQ30: =(DataQ!N141/DataQ!P141)*100 -> 6.8891299 | AR30: =DataQ!Q141 -> 5.33 | AS30: =DataQ!AF141 -> 4.661539 | AV30: =(DataQ!O141/DataQ!P141)*100 -> 5.2905637 | AW30: =(DataQ!N141/DataQ!P141)*100 -> 6.8891299 | AX30: =(DataQ!AG141/DataQ!P141)*100 -> -1.5985662 | BA30: =((DataQ!E193/DataQ!E189)-1)*100 -> 1.8501411 | BB30: =((DataQ!D193/DataQ!D189)-1)*100 -> 3.8289728 | BC30: =BB30-BA30 -> 1.9788317
B31: =100*(F31/$H31) -> 100.10731 | C31: =100*(G31/H31) -> 99.350928 | D31: 100 | F31: =100*(J31/AVERAGE($J$28:$J$31)) -> 101.81888 | G31: =100*(K31/AVERAGE($K$28:$K$31)) -> 101.04957 | H31: =100*(DataQ!I202/AVERAGE(DataQ!I$199:I$202)) -> 101.70974 | J31: =DataQ!F202/DataQ!J202 -> 8.6259161 | K31: =(DataQ!F202-DataQ!G202-DataQ!H202)/DataQ!J202 -> 5.8252788 | M31: 2022 02 | N31: =((W35/W31)-1)*-100 -> -7.770287 | O31: =-100*((DataQ!AN204+DataQ!AO204)-(DataQ!AN200+DataQ!AO200))/DataQ!AI200 -> -1.7594262 | P31: =V31-O31-Q31-R31-S31 -> 2.1747871 | Q31: =X31-R31 -> 3.4664636 | R31: =100*((Z31-Z30)/DataQ!AI202) -> 0.56732969 | S31: =100*((DataQ!AQ204-DataQ!AQ200)/DataQ!AI200) -> 0.69067062 | T31: =SUM(N31:S31) -> -2.6304621 | V31: =((DataQ!AI204/DataQ!AI200)-1)*100 -> 5.1398249 | W31: =100*((DataQ!AR200+DataQ!AS200)/(DataQ!AT200+DataQ!AU200)) -> 101.86625 | X31: =100*((DataQ!AK204-DataQ!AK200)/DataQ!AI200) -> 4.0337933 | Y31: =1000*(DataQ!AK204/DataQ!AM204) -> 8870.4187 | Z31: =(Y31*DataQ!AM204)/1000 -> 251707 | AB31: 2022 02 | AC31: =N35 -> -8.0213928 | AD31: =O31 -> -1.7594262 | AE31: =X31 -> 4.0337933 | AF31: =V31-AD31-AE31-AG31-AH31 -> 2.0628546 | AG31: =100*((DataQ!AP204-DataQ!AP200)/DataQ!AI204) -> 0.11193246 | AH31: =S31 -> 0.69067062 | AI31: =SUM(AC31:AH31) -> -2.881568 | AQ31: =(DataQ!N142/DataQ!P142)*100 -> 7.2942365 | AR31: =DataQ!Q142 -> 5.45 | AS31: =DataQ!AF142 -> 4.892308 | AV31: =(DataQ!O142/DataQ!P142)*100 -> 5.5256178 | AW31: =(DataQ!N142/DataQ!P142)*100 -> 7.2942365 | AX31: =(DataQ!AG142/DataQ!P142)*100 -> -1.7686187 | BA31: =((DataQ!E194/DataQ!E190)-1)*100 -> 1.4027436 | BB31: =((DataQ!D194/DataQ!D190)-1)*100 -> 2.7146402 | BC31: =BB31-BA31 -> 1.3118966
A32: 2022 | B32: =100*(F32/$H32) -> 100.20082 | C32: =100*(G32/H32) -> 99.076225 | D32: 100 | F32: =100*(J32/AVERAGE($J$28:$J$31)) -> 104.28419 | G32: =100*(K32/AVERAGE($K$28:$K$31)) -> 103.11377 | H32: =100*(DataQ!I203/AVERAGE(DataQ!I$199:I$202)) -> 104.07519 | J32: =DataQ!F203/DataQ!J203 -> 8.8347731 | K32: =(DataQ!F203-DataQ!G203-DataQ!H203)/DataQ!J203 -> 5.9442753 | M32: 2022 03 | N32: =((W36/W32)-1)*-100 -> -8.9569193 | O32: =-100*((DataQ!AN205+DataQ!AO205)-(DataQ!AN201+DataQ!AO201))/DataQ!AI201 -> -2.3437831 | P32: =V32-O32-Q32-R32-S32 -> 2.3049139 | Q32: =X32-R32 -> 3.171853 | R32: =100*((Z32-Z31)/DataQ!AI203) -> 1.1828134 | S32: =100*((DataQ!AQ205-DataQ!AQ201)/DataQ!AI201) -> 2.0746076 | T32: =SUM(N32:S32) -> -2.5665144 | V32: =((DataQ!AI205/DataQ!AI201)-1)*100 -> 6.3904049 | W32: =100*((DataQ!AR201+DataQ!AS201)/(DataQ!AT201+DataQ!AU201)) -> 103.10675 | X32: =100*((DataQ!AK205-DataQ!AK201)/DataQ!AI201) -> 4.3546664 | Y32: =1000*(DataQ!AK205/DataQ!AM205) -> 8982.9314 | Z32: =(Y32*DataQ!AM205)/1000 -> 256301 | AB32: 2022 03 | AC32: =N36 -> -6.2151367 | AD32: =O32 -> -2.3437831 | AE32: =X32 -> 4.3546664 | AF32: =V32-AD32-AE32-AG32-AH32 -> 2.2390525 | AG32: =100*((DataQ!AP205-DataQ!AP201)/DataQ!AI205) -> 0.065861418 | AH32: =S32 -> 2.0746076 | AI32: =SUM(AC32:AH32) -> 0.17526817 | AP32: 2007 | AQ32: =(DataQ!N143/DataQ!P143)*100 -> 7.5613869 | AR32: =DataQ!Q143 -> 5.623333 | AS32: =DataQ!AF143 -> 5.219231 | AU32: 2007 | AV32: =(DataQ!O143/DataQ!P143)*100 -> 5.4106856 | AW32: =(DataQ!N143/DataQ!P143)*100 -> 7.5613869 | AX32: =(DataQ!AG143/DataQ!P143)*100 -> -2.1507013 | AZ32: 2020 | BA32: =((DataQ!E195/DataQ!E191)-1)*100 -> 1.6557638 | BB32: =((DataQ!D195/DataQ!D191)-1)*100 -> 2.2067968 | BC32: =BB32-BA32 -> 0.55103301
B33: =100*(F33/$H33) -> 97.676192 | C33: =100*(G33/H33) -> 96.708642 | D33: 100 | F33: =100*(J33/AVERAGE($J$28:$J$31)) -> 104.70495 | G33: =100*(K33/AVERAGE($K$28:$K$31)) -> 103.66777 | H33: =100*(DataQ!I204/AVERAGE(DataQ!I$199:I$202)) -> 107.19598 | J33: =DataQ!F204/DataQ!J204 -> 8.8704187 | K33: =(DataQ!F204-DataQ!G204-DataQ!H204)/DataQ!J204 -> 5.9762123 | M33: 2022 04 | N33: =((W37/W33)-1)*-100 -> -9.9682814 | O33: =-100*((DataQ!AN206+DataQ!AO206)-(DataQ!AN202+DataQ!AO202))/DataQ!AI202 -> -2.0119192 | P33: =V33-O33-Q33-R33-S33 -> 5.1734689 | Q33: =X33-R33 -> 3.379976 | R33: =100*((Z33-Z32)/DataQ!AI204) -> 1.4601867 | S33: =100*((DataQ!AQ206-DataQ!AQ202)/DataQ!AI202) -> 1.9026557 | T33: =SUM(N33:S33) -> -0.063913221 | V33: =((DataQ!AI206/DataQ!AI202)-1)*100 -> 9.9043682 | W33: =100*((DataQ!AR202+DataQ!AS202)/(DataQ!AT202+DataQ!AU202)) -> 104.51011 | X33: =100*((DataQ!AK206-DataQ!AK202)/DataQ!AI202) -> 4.8401627 | Y33: =1000*(DataQ!AK206/DataQ!AM206) -> 9152.6211 | Z33: =(Y33*DataQ!AM206)/1000 -> 262067 | AB33: 2022 04 | AC33: =N37 -> -4.3632095 | AD33: =O33 -> -2.0119192 | AE33: =X33 -> 4.8401627 | AF33: =V33-AD33-AE33-AG33-AH33 -> 4.8747403 | AG33: =100*((DataQ!AP206-DataQ!AP202)/DataQ!AI206) -> 0.29872861 | AH33: =S33 -> 1.9026557 | AI33: =SUM(AC33:AH33) -> 5.5411586 | AQ33: =(DataQ!N144/DataQ!P144)*100 -> 7.9824457 | AR33: =DataQ!Q144 -> 5.703333 | AS33: =DataQ!AF144 -> 5.392308 | AV33: =(DataQ!O144/DataQ!P144)*100 -> 5.7448088 | AW33: =(DataQ!N144/DataQ!P144)*100 -> 7.9824457 | AX33: =(DataQ!AG144/DataQ!P144)*100 -> -2.237637 | BA33: =((DataQ!E196/DataQ!E192)-1)*100 -> 0.68024119 | BB33: =((DataQ!D196/DataQ!D192)-1)*100 -> -1.1173184 | BC33: =BB33-BA33 -> -1.7975596
B34: =100*(F34/$H34) -> 96.62801 | C34: =100*(G34/H34) -> 94.797061 | D34: 100 | F34: =100*(J34/AVERAGE($J$28:$J$31)) -> 106.03303 | G34: =100*(K34/AVERAGE($K$28:$K$31)) -> 104.02387 | H34: =100*(DataQ!I205/AVERAGE(DataQ!I$199:I$202)) -> 109.73322 | J34: =DataQ!F205/DataQ!J205 -> 8.9829314 | K34: =(DataQ!F205-DataQ!G205-DataQ!H205)/DataQ!J205 -> 5.9967405 | M34: 2023 01 | N34: =((W38/W34)-1)*-100 -> -9.6638336 | O34: =-100*((DataQ!AN207+DataQ!AO207)-(DataQ!AN203+DataQ!AO203))/DataQ!AI203 -> -2.61048 | P34: =V34-O34-Q34-R34-S34 -> 6.1921338 | Q34: =X34-R34 -> 3.2713014 | R34: =100*((Z34-Z33)/DataQ!AI205) -> 1.329158 | S34: =100*((DataQ!AQ207-DataQ!AQ203)/DataQ!AI203) -> 0.96113245 | T34: =SUM(N34:S34) -> -0.520588 | V34: =((DataQ!AI207/DataQ!AI203)-1)*100 -> 9.1432456 | W34: =100*((DataQ!AR203+DataQ!AS203)/(DataQ!AT203+DataQ!AU203)) -> 106.71863 | X34: =100*((DataQ!AK207-DataQ!AK203)/DataQ!AI203) -> 4.6004593 | Y34: =1000*(DataQ!AK207/DataQ!AM207) -> 9328.6472 | Z34: =(Y34*DataQ!AM207)/1000 -> 267415 | AB34: 2023 | AC34: =N38 -> -2.9376676 | AD34: =O34 -> -2.61048 | AE34: =X34 -> 4.6004593 | AF34: =V34-AD34-AE34-AG34-AH34 -> 5.8953713 | AG34: =100*((DataQ!AP207-DataQ!AP203)/DataQ!AI207) -> 0.29676251 | AH34: =S34 -> 0.96113245 | AI34: =SUM(AC34:AH34) -> 6.205578 | AQ34: =(DataQ!N145/DataQ!P145)*100 -> 8.1673707 | AR34: =DataQ!Q145 -> 5.883333 | AS34: =DataQ!AF145 -> 5.738461 | AV34: =(DataQ!O145/DataQ!P145)*100 -> 6.2496989 | AW34: =(DataQ!N145/DataQ!P145)*100 -> 8.1673707 | AX34: =(DataQ!AG145/DataQ!P145)*100 -> -1.9176718 | BA34: =((DataQ!E197/DataQ!E193)-1)*100 -> 0.61570178 | BB34: =((DataQ!D197/DataQ!D193)-1)*100 -> 1.4751077 | BC34: =BB34-BA34 -> 0.85940587
B35: =100*(F35/$H35) -> 96.191591 | C35: =100*(G35/H35) -> 94.560288 | D35: 100 | F35: =100*(J35/AVERAGE($J$28:$J$31)) -> 108.03602 | G35: =100*(K35/AVERAGE($K$28:$K$31)) -> 106.20385 | H35: =100*(DataQ!I206/AVERAGE(DataQ!I$199:I$202)) -> 112.31337 | J35: =DataQ!F206/DataQ!J206 -> 9.1526211 | K35: =(DataQ!F206-DataQ!G206-DataQ!H206)/DataQ!J206 -> 6.1224112 | M35: 2023 02 | N35: =((W39/W35)-1)*-100 -> -8.0213928 | O35: =-100*((DataQ!AN208+DataQ!AO208)-(DataQ!AN204+DataQ!AO204))/DataQ!AI204 -> -1.5457821 | P35: =V35-O35-Q35-R35-S35 -> 4.1516305 | Q35: =X35-R35 -> 4.0574809 | R35: =100*((Z35-Z34)/DataQ!AI206) -> 1.3337635 | S35: =100*((DataQ!AQ208-DataQ!AQ204)/DataQ!AI204) -> 3.0216698 | T35: =SUM(N35:S35) -> 2.9973698 | V35: =((DataQ!AI208/DataQ!AI204)-1)*100 -> 11.018763 | W35: =100*((DataQ!AR204+DataQ!AS204)/(DataQ!AT204+DataQ!AU204)) -> 109.78154 | X35: =100*((DataQ!AK208-DataQ!AK204)/DataQ!AI204) -> 5.3912445 | Y35: =1000*(DataQ!AK208/DataQ!AM208) -> 9516.0346 | Z35: =(Y35*DataQ!AM208)/1000 -> 272996 | AB35: 2023 02 | AC35: =N39 -> -2.0465873 | AD35: =O35 -> -1.5457821 | AE35: =X35 -> 5.3912445 | AF35: =V35-AD35-AE35-AG35-AH35 -> 3.8959233 | AG35: =100*((DataQ!AP208-DataQ!AP204)/DataQ!AI208) -> 0.25570722 | AH35: =S35 -> 3.0216698 | AI35: =SUM(AC35:AH35) -> 8.9721753 | AQ35: =(DataQ!N146/DataQ!P146)*100 -> 8.8841006 | AR35: =DataQ!Q146 -> 5.95 | AS35: =DataQ!AF146 -> 5.681818 | AV35: =(DataQ!O146/DataQ!P146)*100 -> 6.1089706 | AW35: =(DataQ!N146/DataQ!P146)*100 -> 8.8841006 | AX35: =(DataQ!AG146/DataQ!P146)*100 -> -2.7751296 | BA35: =((DataQ!E198/DataQ!E194)-1)*100 -> 0.5841379 | BB35: =((DataQ!D198/DataQ!D194)-1)*100 -> 4.5482547 | BC35: =BB35-BA35 -> 3.9641168
A36: 2023 | B36: =100*(F36/$H36) -> 96.255397 | C36: =100*(G36/H36) -> 92.904162 | D36: 100 | F36: =100*(J36/AVERAGE($J$28:$J$31)) -> 110.1138 | G36: =100*(K36/AVERAGE($K$28:$K$31)) -> 106.28007 | H36: =100*(DataQ!I207/AVERAGE(DataQ!I$199:I$202)) -> 114.39753 | J36: =DataQ!F207/DataQ!J207 -> 9.3286472 | K36: =(DataQ!F207-DataQ!G207-DataQ!H207)/DataQ!J207 -> 6.1268053 | M36: 2023 03 | N36: =((W40/W36)-1)*-100 -> -6.2151367 | O36: =-100*((DataQ!AN209+DataQ!AO209)-(DataQ!AN205+DataQ!AO205))/DataQ!AI205 -> -1.4971667 | P36: =V36-O36-Q36-R36-S36 -> 4.9505418 | Q36: =X36-R36 -> 4.2076736 | R36: =100*((Z36-Z35)/DataQ!AI207) -> 1.0905668 | S36: =100*((DataQ!AQ209-DataQ!AQ205)/DataQ!AI205) -> 1.3656924 | T36: =SUM(N36:S36) -> 3.9021712 | V36: =((DataQ!AI209/DataQ!AI205)-1)*100 -> 10.117308 | W36: =100*((DataQ!AR205+DataQ!AS205)/(DataQ!AT205+DataQ!AU205)) -> 112.34193 | X36: =100*((DataQ!AK209-DataQ!AK205)/DataQ!AI205) -> 5.2982404 | Y36: =1000*(DataQ!AK209/DataQ!AM209) -> 9695.7706 | Z36: =(Y36*DataQ!AM209)/1000 -> 277619 | AB36: 2023 03 | AC36: =N40 -> -1.8774803 | AD36: =O36 -> -1.4971667 | AE36: =X36 -> 5.2982404 | AF36: =V36-AD36-AE36-AG36-AH36 -> 4.5975486 | AG36: =100*((DataQ!AP209-DataQ!AP205)/DataQ!AI209) -> 0.35299322 | AH36: =S36 -> 1.3656924 | AI36: =SUM(AC36:AH36) -> 8.2398276 | AP36: 2008 | AQ36: =(DataQ!N147/DataQ!P147)*100 -> 9.2970603 | AR36: =DataQ!Q147 -> 5.856667 | AS36: =DataQ!AF147 -> 5.353846 | AU36: 2008 | AV36: =(DataQ!O147/DataQ!P147)*100 -> 6.7445888 | AW36: =(DataQ!N147/DataQ!P147)*100 -> 9.2970603 | AX36: =(DataQ!AG147/DataQ!P147)*100 -> -2.5524715 | AZ36: 2021 | BA36: =((DataQ!E199/DataQ!E195)-1)*100 -> 0.64535936 | BB36: =((DataQ!D199/DataQ!D195)-1)*100 -> 4.1949478 | BC36: =BB36-BA36 -> 3.5495885
B37: =100*(F37/$H37) -> 96.896549 | C37: =100*(G37/H37) -> 96.375967 | D37: 100 | F37: =100*(J37/AVERAGE($J$28:$J$31)) -> 112.32569 | G37: =100*(K37/AVERAGE($K$28:$K$31)) -> 111.72221 | H37: =100*(DataQ!I208/AVERAGE(DataQ!I$199:I$202)) -> 115.92331 | J37: =DataQ!F208/DataQ!J208 -> 9.5160346 | K37: =(DataQ!F208-DataQ!G208-DataQ!H208)/DataQ!J208 -> 6.4405326 | M37: 2023 04 | N37: =((W41/W37)-1)*-100 -> -4.3632095 | O37: =-100*((DataQ!AN210+DataQ!AO210)-(DataQ!AN206+DataQ!AO206))/DataQ!AI206 -> -1.356584 | P37: =V37-O37-Q37-R37-S37 -> 0.87420658 | Q37: =X37-R37 -> 3.7289687 | R37: =100*((Z37-Z36)/DataQ!AI208) -> 0.25810234 | S37: =100*((DataQ!AQ210-DataQ!AQ206)/DataQ!AI206) -> 1.781345 | T37: =SUM(N37:S37) -> 0.92282908 | V37: =((DataQ!AI210/DataQ!AI206)-1)*100 -> 5.2860386 | W37: =100*((DataQ!AR206+DataQ!AS206)/(DataQ!AT206+DataQ!AU206)) -> 114.92797 | X37: =100*((DataQ!AK210-DataQ!AK206)/DataQ!AI206) -> 3.987071 | Y37: =1000*(DataQ!AK210/DataQ!AM210) -> 9720.0119 | Z37: =(Y37*DataQ!AM210)/1000 -> 278750.5 | AB37: 2023 04 | AC37: =N41 -> -1.8625328 | AD37: =O37 -> -1.356584 | AE37: =X37 -> 3.987071 | AF37: =V37-AD37-AE37-AG37-AH37 -> 0.81667829 | AG37: =100*((DataQ!AP210-DataQ!AP206)/DataQ!AI210) -> 0.05752829 | AH37: =S37 -> 1.781345 | AI37: =SUM(AC37:AH37) -> 3.4235059 | AQ37: =(DataQ!N148/DataQ!P148)*100 -> 8.8889149 | AR37: =DataQ!Q148 -> 5.763333 | AS37: =DataQ!AF148 -> 5.026923 | AV37: =(DataQ!O148/DataQ!P148)*100 -> 6.464488 | AW37: =(DataQ!N148/DataQ!P148)*100 -> 8.8889149 | AX37: =(DataQ!AG148/DataQ!P148)*100 -> -2.4244269 | BA37: =((DataQ!E200/DataQ!E196)-1)*100 -> 2.0270276 | BB37: =((DataQ!D200/DataQ!D196)-1)*100 -> 8.8512241 | BC37: =BB37-BA37 -> 6.8241965
B38: =100*(F38/$H38) -> 98.122922 | C38: =100*(G38/H38) -> 96.815647 | D38: 100 | F38: =100*(J38/AVERAGE($J$28:$J$31)) -> 114.44726 | G38: =100*(K38/AVERAGE($K$28:$K$31)) -> 112.9225 | H38: =100*(DataQ!I209/AVERAGE(DataQ!I$199:I$202)) -> 116.63662 | J38: =DataQ!F209/DataQ!J209 -> 9.6957706 | K38: =(DataQ!F209-DataQ!G209-DataQ!H209)/DataQ!J209 -> 6.5097265 | M38: 2024 01 | N38: =((W42/W38)-1)*-100 -> -2.9376676 | O38: =-100*((DataQ!AN211+DataQ!AO211)-(DataQ!AN207+DataQ!AO207))/DataQ!AI207 -> -0.27815469 | P38: =V38-O38-Q38-R38-S38 -> -0.87247705 | Q38: =X38-R38 -> 2.690006 | R38: =100*((Z38-Z37)/DataQ!AI209) -> 0.3530835 | S38: =100*((DataQ!AQ211-DataQ!AQ207)/DataQ!AI207) -> 2.5089689 | T38: =SUM(N38:S38) -> 1.4637591 | V38: =((DataQ!AI211/DataQ!AI207)-1)*100 -> 4.4014267 | W38: =100*((DataQ!AR207+DataQ!AS207)/(DataQ!AT207+DataQ!AU207)) -> 117.03174 | X38: =100*((DataQ!AK211-DataQ!AK207)/DataQ!AI207) -> 3.0430895 | Y38: =1000*(DataQ!AK211/DataQ!AM211) -> 9797.7705 | Z38: =(Y38*DataQ!AM211)/1000 -> 280314.9 | AB38: 2024 | AC38: =N42 -> -1.9749801 | AD38: =O38 -> -0.27815469 | AE38: =X38 -> 3.0430895 | AF38: =V38-AD38-AE38-AG38-AH38 -> -0.57148598 | AG38: =100*((DataQ!AP211-DataQ!AP207)/DataQ!AI211) -> -0.30099107 | AH38: =S38 -> 2.5089689 | AI38: =SUM(AC38:AH38) -> 2.4264467 | AQ38: =(DataQ!N149/DataQ!P149)*100 -> 8.9038713 | AR38: =DataQ!Q149 -> 5.796667 | AS38: =DataQ!AF149 -> 5 | AV38: =(DataQ!O149/DataQ!P149)*100 -> 6.6541596 | AW38: =(DataQ!N149/DataQ!P149)*100 -> 8.9038713 | AX38: =(DataQ!AG149/DataQ!P149)*100 -> -2.2497118 | BA38: =((DataQ!E201/DataQ!E197)-1)*100 -> 2.7539788 | BB38: =((DataQ!D201/DataQ!D197)-1)*100 -> 6.0569477 | BC38: =BB38-BA38 -> 3.3029689
B39: =100*(F39/$H39) -> 97.877091 | C39: =100*(G39/H39) -> 96.13826 | D39: 100 | F39: =100*(J39/AVERAGE($J$28:$J$31)) -> 114.7334 | G39: =100*(K39/AVERAGE($K$28:$K$31)) -> 112.69511 | H39: =100*(DataQ!I210/AVERAGE(DataQ!I$199:I$202)) -> 117.22192 | J39: =DataQ!F210/DataQ!J210 -> 9.7200119 | K39: =(DataQ!F210-DataQ!G210-DataQ!H210)/DataQ!J210 -> 6.496618 | M39: 2024 02 | N39: =((W43/W39)-1)*-100 -> -2.0465873 | O39: =-100*((DataQ!AN212+DataQ!AO212)-(DataQ!AN208+DataQ!AO208))/DataQ!AI208 -> -1.5668694 | P39: =V39-O39-Q39-R39-S39 -> 0.37814559 | Q39: =X39-R39 -> 1.6748098 | R39: =100*((Z39-Z38)/DataQ!AI210) -> 1.0767459 | S39: =100*((DataQ!AQ212-DataQ!AQ208)/DataQ!AI208) -> 1.2169177 | T39: =SUM(N39:S39) -> 0.73316236 | V39: =((DataQ!AI212/DataQ!AI208)-1)*100 -> 2.7797496 | W39: =100*((DataQ!AR208+DataQ!AS208)/(DataQ!AT208+DataQ!AU208)) -> 118.58755 | X39: =100*((DataQ!AK212-DataQ!AK208)/DataQ!AI208) -> 2.7515557 | Y39: =1000*(DataQ!AK212/DataQ!AM212) -> 9944.7395 | Z39: =(Y39*DataQ!AM212)/1000 -> 285058.6 | AB39: 2024 02 | AC39: =N43 -> -2.0775588 | AD39: =O39 -> -1.5668694 | AE39: =X39 -> 2.7515557 | AF39: =V39-AD39-AE39-AG39-AH39 -> 0.79118248 | AG39: =100*((DataQ!AP212-DataQ!AP208)/DataQ!AI212) -> -0.41303689 | AH39: =S39 -> 1.2169177 | AI39: =SUM(AC39:AH39) -> 0.70219083 | AQ39: =(DataQ!N150/DataQ!P150)*100 -> 8.5040794 | AR39: =DataQ!Q150 -> 5.386667 | AS39: =DataQ!AF150 -> 3.325758 | AV39: =(DataQ!O150/DataQ!P150)*100 -> 6.0811855 | AW39: =(DataQ!N150/DataQ!P150)*100 -> 8.5040794 | AX39: =(DataQ!AG150/DataQ!P150)*100 -> -2.4228939 | BA39: =((DataQ!E202/DataQ!E198)-1)*100 -> 4.8899435 | BB39: =((DataQ!D202/DataQ!D198)-1)*100 -> 4.5267549 | BC39: =BB39-BA39 -> -0.36318864
A40: 2024 | B40: =100*(F40/$H40) -> 98.218131 | C40: =100*(G40/H40) -> 96.471265 | D40: 100 | F40: =100*(J40/AVERAGE($J$28:$J$31)) -> 115.65125 | G40: =100*(K40/AVERAGE($K$28:$K$31)) -> 113.59433 | H40: =100*(DataQ!I211/AVERAGE(DataQ!I$199:I$202)) -> 117.74939 | J40: =DataQ!F211/DataQ!J211 -> 9.7977705 | K40: =(DataQ!F211-DataQ!G211-DataQ!H211)/DataQ!J211 -> 6.5484558 | M40: 2024 03 | N40: =((W44/W40)-1)*-100 -> -1.8774803 | O40: =-100*((DataQ!AN213+DataQ!AO213)-(DataQ!AN209+DataQ!AO209))/DataQ!AI209 -> -1.1148131 | P40: =V40-O40-Q40-R40-S40 -> -0.21396039 | Q40: =X40-R40 -> 1.6784581 | R40: =100*((Z40-Z39)/DataQ!AI211) -> 0.57555257 | S40: =100*((DataQ!AQ213-DataQ!AQ209)/DataQ!AI209) -> 1.3202195 | T40: =SUM(N40:S40) -> 0.36797642 | V40: =((DataQ!AI213/DataQ!AI209)-1)*100 -> 2.2454567 | W40: =100*((DataQ!AR209+DataQ!AS209)/(DataQ!AT209+DataQ!AU209)) -> 119.32414 | X40: =100*((DataQ!AK213-DataQ!AK209)/DataQ!AI209) -> 2.2540107 | Y40: =1000*(DataQ!AK213/DataQ!AM213) -> 10014.349 | Z40: =(Y40*DataQ!AM213)/1000 -> 287605.8 | AB40: 2024 03 | AC40: =N44 -> -2.1780261 | AD40: =O40 -> -1.1148131 | AE40: =X40 -> 2.2540107 | AF40: =V40-AD40-AE40-AG40-AH40 -> 0.39837218 | AG40: =100*((DataQ!AP213-DataQ!AP209)/DataQ!AI213) -> -0.61233256 | AH40: =S40 -> 1.3202195 | AI40: =SUM(AC40:AH40) -> 0.067430536 | AP40: 2009 | AQ40: =(DataQ!N151/DataQ!P151)*100 -> 4.6442684 | AR40: =DataQ!Q151 -> 4.083333 | AS40: =DataQ!AF151 -> 1.085938 | AU40: 2009 | AV40: =(DataQ!O151/DataQ!P151)*100 -> 2.9443086 | AW40: =(DataQ!N151/DataQ!P151)*100 -> 4.6442684 | AX40: =(DataQ!AG151/DataQ!P151)*100 -> -1.6999598 | AZ40: 2022 | BA40: =((DataQ!E203/DataQ!E199)-1)*100 -> 6.1984103 | BB40: =((DataQ!D203/DataQ!D199)-1)*100 -> 6.9863766 | BC40: =BB40-BA40 -> 0.78796623
B41: =100*(F41/$H41) -> 99.244791 | C41: =100*(G41/H41) -> 97.191754 | D41: 100 | F41: =100*(J41/AVERAGE($J$28:$J$31)) -> 117.38605 | G41: =100*(K41/AVERAGE($K$28:$K$31)) -> 114.95773 | H41: =100*(DataQ!I212/AVERAGE(DataQ!I$199:I$202)) -> 118.27931 | J41: =DataQ!F212/DataQ!J212 -> 9.9447395 | K41: =(DataQ!F212-DataQ!G212-DataQ!H212)/DataQ!J212 -> 6.627053 | M41: 2024 04 | N41: =((W45/W41)-1)*-100 -> -1.8625328 | O41: =-100*((DataQ!AN214+DataQ!AO214)-(DataQ!AN210+DataQ!AO210))/DataQ!AI210 -> -1.1672832 | P41: =V41-O41-Q41-R41-S41 -> 0.81528259 | Q41: =X41-R41 -> 2.0238745 | R41: =100*((Z41-Z40)/DataQ!AI212) -> 0.60941697 | S41: =100*((DataQ!AQ214-DataQ!AQ210)/DataQ!AI210) -> 1.4655407 | T41: =SUM(N41:S41) -> 1.8842988 | V41: =((DataQ!AI214/DataQ!AI210)-1)*100 -> 3.7468316 | W41: =100*((DataQ!AR210+DataQ!AS210)/(DataQ!AT210+DataQ!AU210)) -> 119.94252 | X41: =100*((DataQ!AK214-DataQ!AK210)/DataQ!AI210) -> 2.6332915 | Y41: =1000*(DataQ!AK214/DataQ!AM214) -> 10079.441 | Z41: =(Y41*DataQ!AM214)/1000 -> 290351.7 | AB41: 2024 04 | AC41: =N45 -> -2.2281678 | AD41: =O41 -> -1.1672832 | AE41: =X41 -> 2.6332915 | AF41: =V41-AD41-AE41-AG41-AH41 -> 1.4314642 | AG41: =100*((DataQ!AP214-DataQ!AP210)/DataQ!AI214) -> -0.61618161 | AH41: =S41 -> 1.4655407 | AI41: =SUM(AC41:AH41) -> 1.5186638 | AQ41: =(DataQ!N152/DataQ!P152)*100 -> 3.4285671 | AR41: =DataQ!Q152 -> 3.6 | AS41: =DataQ!AF152 -> 0.5 | AV41: =(DataQ!O152/DataQ!P152)*100 -> 2.2093274 | AW41: =(DataQ!N152/DataQ!P152)*100 -> 3.4285671 | AX41: =(DataQ!AG152/DataQ!P152)*100 -> -1.2192397 | BA41: =((DataQ!E204/DataQ!E200)-1)*100 -> 9.1511767 | BB41: =((DataQ!D204/DataQ!D200)-1)*100 -> 5.1326471 | BC41: =BB41-BA41 -> -4.0185297
B42: =100*(F42/$H42) -> 99.49176 | C42: =100*(G42/H42) -> 97.323513 | D42: 100 | F42: =100*(J42/AVERAGE($J$28:$J$31)) -> 118.20771 | G42: =100*(K42/AVERAGE($K$28:$K$31)) -> 115.63159 | H42: =100*(DataQ!I213/AVERAGE(DataQ!I$199:I$202)) -> 118.81156 | J42: =DataQ!F213/DataQ!J213 -> 10.014349 | K42: =(DataQ!F213-DataQ!G213-DataQ!H213)/DataQ!J213 -> 6.665899 | M42: 2025 01 | N42: =((W46/W42)-1)*-100 -> -1.9749801 | O42: =-100*((DataQ!AN215+DataQ!AO215)-(DataQ!AN211+DataQ!AO211))/DataQ!AI211 -> -1.4036573 | P42: =V42-O42-Q42-R42-S42 -> 1.2958225 | Q42: =X42-R42 -> 2.2810287 | R42: =100*((Z42-Z41)/DataQ!AI213) -> 0.55744057 | S42: =100*((DataQ!AQ215-DataQ!AQ211)/DataQ!AI211) -> 1.6581572 | T42: =SUM(N42:S42) -> 2.4138117 | V42: =((DataQ!AI215/DataQ!AI211)-1)*100 -> 4.3887917 | W42: =100*((DataQ!AR211+DataQ!AS211)/(DataQ!AT211+DataQ!AU211)) -> 120.46974 | X42: =100*((DataQ!AK215-DataQ!AK211)/DataQ!AI211) -> 2.8384693 | Y42: =1000*(DataQ!AK215/DataQ!AM215) -> 10142.94 | Z42: =(Y42*DataQ!AM215)/1000 -> 292877 | AB42: 2025 | AC42: =N46 -> 0 | AD42: =O42 -> -1.4036573 | AE42: =X42 -> 2.8384693 | AF42: =V42-AD42-AE42-AG42-AH42 -> 1.6898037 | AG42: =100*((DataQ!AP215-DataQ!AP211)/DataQ!AI215) -> -0.39398117 | AH42: =S42 -> 1.6581572 | AI42: =SUM(AC42:AH42) -> 4.3887917 | AQ42: =(DataQ!N153/DataQ!P153)*100 -> 3.0123072 | AR42: =DataQ!Q153 -> 3.576667 | AS42: =DataQ!AF153 -> 0.5 | AV42: =(DataQ!O153/DataQ!P153)*100 -> 1.8767001 | AW42: =(DataQ!N153/DataQ!P153)*100 -> 3.0123072 | AX42: =(DataQ!AG153/DataQ!P153)*100 -> -1.1356071 | BA42: =((DataQ!E205/DataQ!E201)-1)*100 -> 10.005959 | BB42: =((DataQ!D205/DataQ!D201)-1)*100 -> 5.8823469 | BC42: =BB42-BA42 -> -4.123612
B43: =100*(F43/$H43) -> 99.64023 | C43: =100*(G43/H43) -> 97.216818 | D43: 100 | F43: =100*(J43/AVERAGE($J$28:$J$31)) -> 118.97604 | G43: =100*(K43/AVERAGE($K$28:$K$31)) -> 116.08235 | H43: =100*(DataQ!I214/AVERAGE(DataQ!I$199:I$202)) -> 119.40563 | J43: =DataQ!F214/DataQ!J214 -> 10.079441 | K43: =(DataQ!F214-DataQ!G214-DataQ!H214)/DataQ!J214 -> 6.6918847 | M43: 2025 02 | N43: =((W47/W43)-1)*-100 -> -2.0775588 | O43: =-100*((DataQ!AN216+DataQ!AO216)-(DataQ!AN212+DataQ!AO212))/DataQ!AI212 -> -1.1544899 | P43: =V43-O43-Q43-R43-S43 -> 1.525562 | Q43: =X43-R43 -> 1.7433007 | R43: =100*((Z43-Z42)/DataQ!AI214) -> 0.56311355 | S43: =100*((DataQ!AQ216-DataQ!AQ212)/DataQ!AI212) -> 0.84245754 | T43: =SUM(N43:S43) -> 1.4423851 | V43: =((DataQ!AI216/DataQ!AI212)-1)*100 -> 3.5199439 | W43: =100*((DataQ!AR212+DataQ!AS212)/(DataQ!AT212+DataQ!AU212)) -> 121.01455 | X43: =100*((DataQ!AK216-DataQ!AK212)/DataQ!AI212) -> 2.3064143 | Y43: =1000*(DataQ!AK216/DataQ!AM216) -> 10204.19 | Z43: =(Y43*DataQ!AM216)/1000 -> 295450.8 | AB43: 2025 02 | AC43: =N47 -> 0 | AD43: =O43 -> -1.1544899 | AE43: =X43 -> 2.3064143 | AF43: =V43-AD43-AE43-AG43-AH43 -> 1.8932636 | AG43: =100*((DataQ!AP216-DataQ!AP212)/DataQ!AI216) -> -0.36770154 | AH43: =S43 -> 0.84245754 | AI43: =SUM(AC43:AH43) -> 3.5199439 | AQ43: =(DataQ!N154/DataQ!P154)*100 -> 2.7580877 | AR43: =DataQ!Q154 -> 3.573333 | AS43: =DataQ!AF154 -> 0.5 | AV43: =(DataQ!O154/DataQ!P154)*100 -> 1.7707832 | AW43: =(DataQ!N154/DataQ!P154)*100 -> 2.7580877 | AX43: =(DataQ!AG154/DataQ!P154)*100 -> -0.98730446 | BA43: =((DataQ!E206/DataQ!E202)-1)*100 -> 10.751748 | BB43: =((DataQ!D206/DataQ!D202)-1)*100 -> 6.4116982 | BC43: =BB43-BA43 -> -4.3400501
A44: 2025 | B44: =100*(F44/$H44) -> 99.719553 | C44: =100*(G44/H44) -> 96.922211 | D44: 100 | F44: =100*(J44/AVERAGE($J$28:$J$31)) -> 119.72558 | G44: =100*(K44/AVERAGE($K$28:$K$31)) -> 116.36703 | H44: =100*(DataQ!I215/AVERAGE(DataQ!I$199:I$202)) -> 120.06229 | J44: =DataQ!F215/DataQ!J215 -> 10.14294 | K44: =(DataQ!F215-DataQ!G215-DataQ!H215)/DataQ!J215 -> 6.7082957 | M44: 2025 03 | N44: =((W48/W44)-1)*-100 -> -2.1780261 | O44: =-100*((DataQ!AN217+DataQ!AO217)-(DataQ!AN213+DataQ!AO213))/DataQ!AI213 -> -1.20505 | P44: =V44-O44-Q44-R44-S44 -> 1.9032999 | Q44: =X44-R44 -> 1.7434268 | R44: =100*((Z44-Z43)/DataQ!AI215) -> 0.59090113 | S44: =100*((DataQ!AQ217-DataQ!AQ213)/DataQ!AI213) -> 1.091595 | T44: =SUM(N44:S44) -> 1.9461467 | V44: =((DataQ!AI217/DataQ!AI213)-1)*100 -> 4.1241729 | W44: =100*((DataQ!AR213+DataQ!AS213)/(DataQ!AT213+DataQ!AU213)) -> 121.56443 | X44: =100*((DataQ!AK217-DataQ!AK213)/DataQ!AI213) -> 2.3343279 | Y44: =1000*(DataQ!AK217/DataQ!AM217) -> 10269.522 | Z44: =(Y44*DataQ!AM217)/1000 -> 298180.7 | AB44: 2025 03 | AC44: =N48 -> 0 | AD44: =O44 -> -1.20505 | AE44: =X44 -> 2.3343279 | AF44: =V44-AD44-AE44-AG44-AH44 -> 2.246686 | AG44: =100*((DataQ!AP217-DataQ!AP213)/DataQ!AI217) -> -0.34338619 | AH44: =S44 -> 1.091595 | AI44: =SUM(AC44:AH44) -> 4.1241729 | AP44: 2010 | AQ44: =(DataQ!N155/DataQ!P155)*100 -> 1.9245763 | AR44: =DataQ!Q155 -> 3.666667 | AS44: =DataQ!AF155 -> 0.5 | AU44: 2010 | AV44: =(DataQ!O155/DataQ!P155)*100 -> 1.5430674 | AW44: =(DataQ!N155/DataQ!P155)*100 -> 1.9245763 | AX44: =(DataQ!AG155/DataQ!P155)*100 -> -0.38150893 | AZ44: 2023 | BA44: =((DataQ!E207/DataQ!E203)-1)*100 -> 10.178266 | BB44: =((DataQ!D207/DataQ!D203)-1)*100 -> 6.1981298 | BC44: =BB44-BA44 -> -3.9801365
B45: =100*(F45/$H45) -> 99.772954 | C45: =100*(G45/H45) -> 96.847996 | D45: 100 | F45: =100*(J45/AVERAGE($J$28:$J$31)) -> 120.44857 | G45: =100*(K45/AVERAGE($K$28:$K$31)) -> 116.91748 | H45: =100*(DataQ!I216/AVERAGE(DataQ!I$199:I$202)) -> 120.72266 | J45: =DataQ!F216/DataQ!J216 -> 10.20419 | K45: =(DataQ!F216-DataQ!G216-DataQ!H216)/DataQ!J216 -> 6.7400278 | M45: 2025 04 | N45: =((W49/W45)-1)*-100 -> -2.2281678 | O45: =-100*((DataQ!AN218+DataQ!AO218)-(DataQ!AN214+DataQ!AO214))/DataQ!AI214 -> -1.1901369 | P45: =V45-O45-Q45-R45-S45 -> 2.1747236 | Q45: =X45-R45 -> 1.7249128 | R45: =100*((Z45-Z44)/DataQ!AI216) -> 0.58670139 | S45: =100*((DataQ!AQ218-DataQ!AQ214)/DataQ!AI214) -> 1.0369599 | T45: =SUM(N45:S45) -> 2.104993 | V45: =((DataQ!AI218/DataQ!AI214)-1)*100 -> 4.3331607 | W45: =100*((DataQ!AR214+DataQ!AS214)/(DataQ!AT214+DataQ!AU214)) -> 122.17649 | X45: =100*((DataQ!AK218-DataQ!AK214)/DataQ!AI214) -> 2.3116141 | Y45: =1000*(DataQ!AK218/DataQ!AM218) -> 10337.682 | Z45: =(Y45*DataQ!AM218)/1000 -> 300917.3 | AB45: 2025 04 | AC45: =N49 -> 0 | AD45: =O45 -> -1.1901369 | AE45: =X45 -> 2.3116141 | AF45: =V45-AD45-AE45-AG45-AH45 -> 2.5443216 | AG45: =100*((DataQ!AP218-DataQ!AP214)/DataQ!AI218) -> -0.36959804 | AH45: =S45 -> 1.0369599 | AI45: =SUM(AC45:AH45) -> 4.3331607 | AQ45: =(DataQ!N156/DataQ!P156)*100 -> 2.029287 | AR45: =DataQ!Q156 -> 3.66 | AS45: =DataQ!AF156 -> 0.5 | AV45: =(DataQ!O156/DataQ!P156)*100 -> 1.6921949 | AW45: =(DataQ!N156/DataQ!P156)*100 -> 2.029287 | AX45: =(DataQ!AG156/DataQ!P156)*100 -> -0.3370921 | BA45: =((DataQ!E208/DataQ!E204)-1)*100 -> 8.439049 | BB45: =((DataQ!D208/DataQ!D204)-1)*100 -> 8.3927587 | BC45: =BB45-BA45 -> -0.046290241
B46: =100*(F46/$H46) -> 99.862497 | C46: =100*(G46/H46) -> 96.739624 | D46: 100 | F46: =100*(J46/AVERAGE($J$28:$J$31)) -> 121.21973 | G46: =100*(K46/AVERAGE($K$28:$K$31)) -> 117.42898 | H46: =100*(DataQ!I217/AVERAGE(DataQ!I$199:I$202)) -> 121.38664 | J46: =DataQ!F217/DataQ!J217 -> 10.269522 | K46: =(DataQ!F217-DataQ!G217-DataQ!H217)/DataQ!J217 -> 6.7695146 | V46: =((DataQ!AI219/DataQ!AI215)-1)*100 -> 4.3966386 | W46: =100*((DataQ!AR215+DataQ!AS215)/(DataQ!AT215+DataQ!AU215)) -> 122.849 | X46: =100*((DataQ!AK219-DataQ!AK215)/DataQ!AI215) -> 2.3205083 | Y46: =1000*(DataQ!AK219/DataQ!AM219) -> 10408.503 | Z46: =(Y46*DataQ!AM219)/1000 -> 303597.5 | AQ46: =(DataQ!N157/DataQ!P157)*100 -> 1.9944083 | AR46: =DataQ!Q157 -> 3.57 | AS46: =DataQ!AF157 -> 0.5 | AV46: =(DataQ!O157/DataQ!P157)*100 -> 1.717065 | AW46: =(DataQ!N157/DataQ!P157)*100 -> 1.9944083 | AX46: =(DataQ!AG157/DataQ!P157)*100 -> -0.27734333 | BA46: =((DataQ!E209/DataQ!E205)-1)*100 -> 6.7136185 | BB46: =((DataQ!D209/DataQ!D205)-1)*100 -> 7.9827346 | BC46: =BB46-BA46 -> 1.2691161
B47: =100*(F47/$H47) -> 99.975384 | C47: =100*(G47/H47) -> 96.621636 | D47: 100 | F47: =100*(J47/AVERAGE($J$28:$J$31)) -> 122.02427 | G47: =100*(K47/AVERAGE($K$28:$K$31)) -> 117.93088 | H47: =100*(DataQ!I218/AVERAGE(DataQ!I$199:I$202)) -> 122.05432 | J47: =DataQ!F218/DataQ!J218 -> 10.337682 | K47: =(DataQ!F218-DataQ!G218-DataQ!H218)/DataQ!J218 -> 6.7984481 | V47: =((DataQ!AI220/DataQ!AI216)-1)*100 -> 4.2590413 | W47: =100*((DataQ!AR216+DataQ!AS216)/(DataQ!AT216+DataQ!AU216)) -> 123.5287 | X47: =100*((DataQ!AK220-DataQ!AK216)/DataQ!AI216) -> 2.3495926 | Y47: =1000*(DataQ!AK220/DataQ!AM220) -> 10479.582 | Z47: =(Y47*DataQ!AM220)/1000 -> 306410.2 | AQ47: =(DataQ!N158/DataQ!P158)*100 -> 2.2473167 | AR47: =DataQ!Q158 -> 3.506667 | AS47: =DataQ!AF158 -> 0.5 | AV47: =(DataQ!O158/DataQ!P158)*100 -> 1.9050744 | AW47: =(DataQ!N158/DataQ!P158)*100 -> 2.2473167 | AX47: =(DataQ!AG158/DataQ!P158)*100 -> -0.34224232 | BA47: =((DataQ!E210/DataQ!E206)-1)*100 -> 4.1568272 | BB47: =((DataQ!D210/DataQ!D206)-1)*100 -> 5.7082449 | BC47: =BB47-BA47 -> 1.5514178
A48: 2026 | B48: =100*(F48/$H48) -> 100.1097 | C48: =100*(G48/H48) -> 96.479464 | D48: 100 | F48: =100*(J48/AVERAGE($J$28:$J$31)) -> 122.86024 | G48: =100*(K48/AVERAGE($K$28:$K$31)) -> 118.40501 | H48: =100*(DataQ!I219/AVERAGE(DataQ!I$199:I$202)) -> 122.72561 | J48: =DataQ!F219/DataQ!J219 -> 10.408503 | K48: =(DataQ!F219-DataQ!G219-DataQ!H219)/DataQ!J219 -> 6.8257806 | V48: =((DataQ!AI221/DataQ!AI217)-1)*100 -> 4.0913708 | W48: =100*((DataQ!AR217+DataQ!AS217)/(DataQ!AT217+DataQ!AU217)) -> 124.21213 | X48: =100*((DataQ!AK221-DataQ!AK217)/DataQ!AI217) -> 2.3508793 | Y48: =1000*(DataQ!AK221/DataQ!AM221) -> 10551.88 | Z48: =(Y48*DataQ!AM221)/1000 -> 309269.8 | AP48: 2011 | AQ48: =(DataQ!N159/DataQ!P159)*100 -> 2.1920798 | AR48: =DataQ!Q159 -> 3.496667 | AS48: =DataQ!AF159 -> 0.5 | AU48: 2011 | AV48: =(DataQ!O159/DataQ!P159)*100 -> 1.9670774 | AW48: =(DataQ!N159/DataQ!P159)*100 -> 2.1920798 | AX48: =(DataQ!AG159/DataQ!P159)*100 -> -0.22500235 | AZ48: 2024 | BA48: =((DataQ!E211/DataQ!E207)-1)*100 -> 3.4202514 | BB48: =((DataQ!D211/DataQ!D207)-1)*100 -> 5.3302446 | BC48: =BB48-BA48 -> 1.9099932
B49: =100*(F49/$H49) -> 100.24201 | C49: =100*(G49/H49) -> 96.465523 | D49: 100 | F49: =100*(J49/AVERAGE($J$28:$J$31)) -> 123.69925 | G49: =100*(K49/AVERAGE($K$28:$K$31)) -> 119.03904 | H49: =100*(DataQ!I220/AVERAGE(DataQ!I$199:I$202)) -> 123.4006 | J49: =DataQ!F220/DataQ!J220 -> 10.479582 | K49: =(DataQ!F220-DataQ!G220-DataQ!H220)/DataQ!J220 -> 6.8623308 | V49: =((DataQ!AI222/DataQ!AI218)-1)*100 -> 3.9212257 | W49: =100*((DataQ!AR218+DataQ!AS218)/(DataQ!AT218+DataQ!AU218)) -> 124.89878 | X49: =100*((DataQ!AK222-DataQ!AK218)/DataQ!AI218) -> 2.3645583 | Y49: =1000*(DataQ!AK222/DataQ!AM222) -> 10624.41 | Z49: =(Y49*DataQ!AM222)/1000 -> 312193.2 | AQ49: =(DataQ!N160/DataQ!P160)*100 -> 2.1242872 | AR49: =DataQ!Q160 -> 3.47 | AS49: =DataQ!AF160 -> 0.5 | AV49: =(DataQ!O160/DataQ!P160)*100 -> 1.8765827 | AW49: =(DataQ!N160/DataQ!P160)*100 -> 2.1242872 | AX49: =(DataQ!AG160/DataQ!P160)*100 -> -0.24770449 | BA49: =((DataQ!E212/DataQ!E208)-1)*100 -> 1.5831634 | BB49: =((DataQ!D212/DataQ!D208)-1)*100 -> 3.8262447 | BC49: =BB49-BA49 -> 2.2430814
B50: =100*(F50/$H50) -> 100.40649 | C50: =100*(G50/H50) -> 96.412526 | D50: 100 | F50: =100*(J50/AVERAGE($J$28:$J$31)) -> 124.55264 | G50: =100*(K50/AVERAGE($K$28:$K$31)) -> 119.59819 | H50: =100*(DataQ!I221/AVERAGE(DataQ!I$199:I$202)) -> 124.04839 | J50: =DataQ!F221/DataQ!J221 -> 10.55188 | K50: =(DataQ!F221-DataQ!G221-DataQ!H221)/DataQ!J221 -> 6.8945647 | AB50: Annual | AQ50: =(DataQ!N161/DataQ!P161)*100 -> 2.1448516 | AR50: =DataQ!Q161 -> 3.4 | AS50: =DataQ!AF161 -> 0.5 | AV50: =(DataQ!O161/DataQ!P161)*100 -> 1.8799015 | AW50: =(DataQ!N161/DataQ!P161)*100 -> 2.1448516 | AX50: =(DataQ!AG161/DataQ!P161)*100 -> -0.2649501 | BA50: =((DataQ!E213/DataQ!E209)-1)*100 -> 1.7656012 | BB50: =((DataQ!D213/DataQ!D209)-1)*100 -> 3.195165 | BC50: =BB50-BA50 -> 1.4295638
B51: =100*(F51/$H51) -> 100.56863 | C51: =100*(G51/H51) -> 96.334141 | D51: 100 | F51: =100*(J51/AVERAGE($J$28:$J$31)) -> 125.40877 | G51: =100*(K51/AVERAGE($K$28:$K$31)) -> 120.12838 | H51: =100*(DataQ!I222/AVERAGE(DataQ!I$199:I$202)) -> 124.69969 | J51: =DataQ!F222/DataQ!J222 -> 10.62441 | K51: =(DataQ!F222-DataQ!G222-DataQ!H222)/DataQ!J222 -> 6.9251289 | AB51: 2022 | AC51: =AC7 -> -7.8364037 | AD51: =AD7 -> -2.1384825 | AE51: =AE7 -> 4.6351359 | AF51: =AF7 -> 2.5175389 | AG51: =AG7 -> 0.1850527 | AH51: =AH7 -> 1.1564634 | AI51: =AI7 -> -1.4806955 | AQ51: =(DataQ!N162/DataQ!P162)*100 -> 2.3691672 | AR51: =DataQ!Q162 -> 3.366667 | AS51: =DataQ!AF162 -> 0.5 | AV51: =(DataQ!O162/DataQ!P162)*100 -> 2.1145439 | AW51: =(DataQ!N162/DataQ!P162)*100 -> 2.3691672 | AX51: =(DataQ!AG162/DataQ!P162)*100 -> -0.25462328 | BA51: =((DataQ!E214/DataQ!E210)-1)*100 -> 1.8293251 | BB51: =((DataQ!D214/DataQ!D210)-1)*100 -> 3.9698098 | BC51: =BB51-BA51 -> 2.1404847
AB52: 2023 | AC52: =AC8 -> -7.0184089 | AD52: =AD8 -> -1.7420286 | AE52: =AE8 -> 4.8101806 | AF52: =AF8 -> 3.7295051 | AG52: =AG8 -> 0.26161126 | AH52: =AH8 -> 1.7838233 | AI52: =AI8 -> 1.8246828 | AP52: 2012 | AQ52: =(DataQ!N163/DataQ!P163)*100 -> 2.5747862 | AR52: =DataQ!Q163 -> 3.366667 | AS52: =DataQ!AF163 -> 0.5 | AU52: 2012 | AV52: =(DataQ!O163/DataQ!P163)*100 -> 2.1957095 | AW52: =(DataQ!N163/DataQ!P163)*100 -> 2.5747862 | AX52: =(DataQ!AG163/DataQ!P163)*100 -> -0.37907669 | AZ52: 2025 | BA52: =((DataQ!E215/DataQ!E211)-1)*100 -> 1.8615904 | BB52: =((DataQ!D215/DataQ!D211)-1)*100 -> 3.5229328 | BC52: =BB52-BA52 -> 1.6613424
AB53: 2024 | AC53: =AC9 -> -2.1814376 | AD53: =AD9 -> -1.0384226 | AE53: =AE9 -> 2.6662054 | AF53: =AF9 -> 0.53764934 | AG53: =AG9 -> -0.50308318 | AH53: =AH9 -> 1.6195752 | AI53: =AI9 -> 1.1004866 | AQ53: =(DataQ!N164/DataQ!P164)*100 -> 2.3986209 | AR53: =DataQ!Q164 -> 3.38 | AS53: =DataQ!AF164 -> 0.5 | AV53: =(DataQ!O164/DataQ!P164)*100 -> 2.0989696 | AW53: =(DataQ!N164/DataQ!P164)*100 -> 2.3986209 | AX53: =(DataQ!AG164/DataQ!P164)*100 -> -0.29965135 | BA53: =((DataQ!E216/DataQ!E212)-1)*100 -> 2.0916813 | BB53: =((DataQ!D216/DataQ!D212)-1)*100 -> 2.6089357 | BC53: =BB53-BA53 -> 0.51725445
AQ54: =(DataQ!N165/DataQ!P165)*100 -> 2.1103344 | AR54: =DataQ!Q165 -> 3.373333 | AS54: =DataQ!AF165 -> 0.5 | AV54: =(DataQ!O165/DataQ!P165)*100 -> 1.8150364 | AW54: =(DataQ!N165/DataQ!P165)*100 -> 2.1103344 | AX54: =(DataQ!AG165/DataQ!P165)*100 -> -0.29529792 | BA54: =((DataQ!E217/DataQ!E213)-1)*100 -> 2.2163476 | BB54: =((DataQ!D217/DataQ!D213)-1)*100 -> 2.5480948 | BC54: =BB54-BA54 -> 0.3317472
AQ55: =(DataQ!N166/DataQ!P166)*100 -> 2.0058346 | AR55: =DataQ!Q166 -> 3.38 | AS55: =DataQ!AF166 -> 0.5 | AV55: =(DataQ!O166/DataQ!P166)*100 -> 1.8092325 | AW55: =(DataQ!N166/DataQ!P166)*100 -> 2.0058346 | AX55: =(DataQ!AG166/DataQ!P166)*100 -> -0.1966021 | BA55: =((DataQ!E218/DataQ!E214)-1)*100 -> 2.2792691 | BB55: =((DataQ!D218/DataQ!D214)-1)*100 -> 2.5619936 | BC55: =BB55-BA55 -> 0.28272453
AB56: Quarterly | AP56: 2013 | AQ56: =(DataQ!N167/DataQ!P167)*100 -> 2.1740201 | AR56: =DataQ!Q167 -> 3.366667 | AS56: =DataQ!AF167 -> 0.5 | AU56: 2013 | AV56: =(DataQ!O167/DataQ!P167)*100 -> 1.8562571 | AW56: =(DataQ!N167/DataQ!P167)*100 -> 2.1740201 | AX56: =(DataQ!AG167/DataQ!P167)*100 -> -0.31776303 | AZ56: 2026 | BA56: =((DataQ!E219/DataQ!E215)-1)*100 -> 2.3100252 | BB56: =((DataQ!D219/DataQ!D215)-1)*100 -> 2.6181411 | BC56: =BB56-BA56 -> 0.30811584
AB57: 2022 | AC57: =AVERAGE(AC30:AC33) -> -7.0658932 | AD57: =AVERAGE(AD30:AD33) -> -2.138933 | AE57: =AVERAGE(AE30:AE33) -> 4.6357608 | AF57: =AVERAGE(AF30:AF33) -> 2.5200345 | AG57: =AVERAGE(AG30:AG33) -> 0.17281295 | AH57: =AVERAGE(AH30:AH33) -> 1.1507948 | AI57: =AVERAGE(AI30:AI33) -> -0.72542311 | AQ57: =(DataQ!N168/DataQ!P168)*100 -> 2.0038312 | AR57: =DataQ!Q168 -> 3.343333 | AS57: =DataQ!AF168 -> 0.5 | AV57: =(DataQ!O168/DataQ!P168)*100 -> 1.7267565 | AW57: =(DataQ!N168/DataQ!P168)*100 -> 2.0038312 | AX57: =(DataQ!AG168/DataQ!P168)*100 -> -0.27707464 | BA57: =((DataQ!E220/DataQ!E216)-1)*100 -> 2.2356183 | BB57: =((DataQ!D220/DataQ!D216)-1)*100 -> 2.6988334 | BC57: =BB57-BA57 -> 0.46321505
AB58: 2023 | AC58: =AVERAGE(AC34:AC37) -> -2.181067 | AD58: =AVERAGE(AD34:AD37) -> -1.7525032 | AE58: =AVERAGE(AE34:AE37) -> 4.8192538 | AF58: =AVERAGE(AF34:AF37) -> 3.8013804 | AG58: =AVERAGE(AG34:AG37) -> 0.24074781 | AH58: =AVERAGE(AH34:AH37) -> 1.7824599 | AI58: =AVERAGE(AI34:AI37) -> 6.7102717 | AQ58: =(DataQ!N169/DataQ!P169)*100 -> 1.8608439 | AR58: =DataQ!Q169 -> 3.316667 | AS58: =DataQ!AF169 -> 0.5 | AV58: =(DataQ!O169/DataQ!P169)*100 -> 1.5766739 | AW58: =(DataQ!N169/DataQ!P169)*100 -> 1.8608439 | AX58: =(DataQ!AG169/DataQ!P169)*100 -> -0.28416993 | BA58: =((DataQ!E221/DataQ!E217)-1)*100 -> 2.2091149 | BB58: =((DataQ!D221/DataQ!D217)-1)*100 -> 2.7494632 | BC58: =BB58-BA58 -> 0.54034831
AB59: 2024 | AC59: =AVERAGE(AC38:AC41) -> -2.1146832 | AD59: =AVERAGE(AD38:AD41) -> -1.0317801 | AE59: =AVERAGE(AE38:AE41) -> 2.6704868 | AF59: =AVERAGE(AF38:AF41) -> 0.51238322 | AG59: =AVERAGE(AG38:AG41) -> -0.48563553 | AH59: =AVERAGE(AH38:AH41) -> 1.6279117 | AI59: =AVERAGE(AI38:AI41) -> 1.178683 | AQ59: =(DataQ!N170/DataQ!P170)*100 -> 1.6691095 | AR59: =DataQ!Q170 -> 3.28 | AS59: =DataQ!AF170 -> 0.5 | AV59: =(DataQ!O170/DataQ!P170)*100 -> 1.4085396 | AW59: =(DataQ!N170/DataQ!P170)*100 -> 1.6691095 | AX59: =(DataQ!AG170/DataQ!P170)*100 -> -0.26056986 | BA59: =((DataQ!E222/DataQ!E218)-1)*100 -> 2.1487344 | BB59: =((DataQ!D222/DataQ!D218)-1)*100 -> 2.7736636 | BC59: =BB59-BA59 -> 0.62492925
AP60: 2014 | AQ60: =(DataQ!N171/DataQ!P171)*100 -> 2.0413172 | AR60: =DataQ!Q171 -> 3.25 | AS60: =DataQ!AF171 -> 0.5 | AU60: 2014 | AV60: =(DataQ!O171/DataQ!P171)*100 -> 1.7123185 | AW60: =(DataQ!N171/DataQ!P171)*100 -> 2.0413172 | AX60: =(DataQ!AG171/DataQ!P171)*100 -> -0.32899864
AQ61: =(DataQ!N172/DataQ!P172)*100 -> 2.3954732 | AR61: =DataQ!Q172 -> 3.233333 | AS61: =DataQ!AF172 -> 0.5 | AV61: =(DataQ!O172/DataQ!P172)*100 -> 2.0540608 | AW61: =(DataQ!N172/DataQ!P172)*100 -> 2.3954732 | AX61: =(DataQ!AG172/DataQ!P172)*100 -> -0.34141244
AE62: =AB30 -> 2022 | AF62: =AF30 -> 0.90349054 | AG62: =AF62/4 -> 0.22587264 | AH62: =AG62/AI65 -> 0.089630772 | AQ62: =(DataQ!N173/DataQ!P173)*100 -> 2.4329235 | AR62: =DataQ!Q173 -> 3.213333 | AS62: =DataQ!AF173 -> 0.5 | AV62: =(DataQ!O173/DataQ!P173)*100 -> 2.1462519 | AW62: =(DataQ!N173/DataQ!P173)*100 -> 2.4329235 | AX62: =(DataQ!AG173/DataQ!P173)*100 -> -0.28667155
AE63: =AB31 -> 2022 02 | AF63: =AF31 -> 2.0628546 | AG63: =AF63/4 -> 0.51571365 | AH63: =AG63/AI65 -> 0.20464547 | AQ63: =(DataQ!N174/DataQ!P174)*100 -> 2.3851521 | AR63: =DataQ!Q174 -> 3.186667 | AS63: =DataQ!AF174 -> 0.5 | AV63: =(DataQ!O174/DataQ!P174)*100 -> 2.1098296 | AW63: =(DataQ!N174/DataQ!P174)*100 -> 2.3851521 | AX63: =(DataQ!AG174/DataQ!P174)*100 -> -0.27532251
AE64: =AB32 -> 2022 03 | AF64: =AF32 -> 2.2390525 | AG64: =AF64/4 -> 0.55976312 | AH64: =AG64/AI65 -> 0.22212518 | AP64: 2015 | AQ64: =(DataQ!N175/DataQ!P175)*100 -> 2.2008293 | AR64: =DataQ!Q175 -> 3.153333 | AS64: =DataQ!AF175 -> 0.5 | AU64: 2015 | AV64: =(DataQ!O175/DataQ!P175)*100 -> 1.9115756 | AW64: =(DataQ!N175/DataQ!P175)*100 -> 2.2008293 | AX64: =(DataQ!AG175/DataQ!P175)*100 -> -0.28925368
AE65: =AB33 -> 2022 04 | AF65: =AF33 -> 4.8747403 | AG65: =AF65/4 -> 1.2186851 | AH65: =AG65/AI65 -> 0.48359857 | AI65: =AVERAGE(AF62:AF65) -> 2.5200345 | AQ65: =(DataQ!N176/DataQ!P176)*100 -> 2.2225558 | AR65: =DataQ!Q176 -> 3.106667 | AS65: =DataQ!AF176 -> 0.5 | AV65: =(DataQ!O176/DataQ!P176)*100 -> 1.9998624 | AW65: =(DataQ!N176/DataQ!P176)*100 -> 2.2225558 | AX65: =(DataQ!AG176/DataQ!P176)*100 -> -0.22269346
AE66: =AB34 -> 2023 | AF66: =AF34 -> 5.8953713 | AG66: =AF66/4 -> 1.4738428 | AH66: =AG66/AI69 -> 0.38771254 | AQ66: =(DataQ!N177/DataQ!P177)*100 -> 2.1345908 | AR66: =DataQ!Q177 -> 3.056667 | AS66: =DataQ!AF177 -> 0.5 | AV66: =(DataQ!O177/DataQ!P177)*100 -> 1.9787366 | AW66: =(DataQ!N177/DataQ!P177)*100 -> 2.1345908 | AX66: =(DataQ!AG177/DataQ!P177)*100 -> -0.15585416
AE67: =AB35 -> 2023 02 | AF67: =AF35 -> 3.8959233 | AG67: =AF67/4 -> 0.97398082 | AH67: =AG67/AI69 -> 0.25621767 | AQ67: =(DataQ!N178/DataQ!P178)*100 -> 2.1919724 | AR67: =DataQ!Q178 -> 3.01 | AS67: =DataQ!AF178 -> 0.5 | AV67: =(DataQ!O178/DataQ!P178)*100 -> 1.9797081 | AW67: =(DataQ!N178/DataQ!P178)*100 -> 2.1919724 | AX67: =(DataQ!AG178/DataQ!P178)*100 -> -0.2122643
AE68: =AB36 -> 2023 03 | AF68: =AF36 -> 4.5975486 | AG68: =AF68/4 -> 1.1493871 | AH68: =AG68/AI69 -> 0.30236047 | AP68: 2016 | AQ68: =(DataQ!N179/DataQ!P179)*100 -> 2.1006035 | AR68: =DataQ!Q179 -> 2.95 | AS68: =DataQ!AF179 -> 0.5 | AU68: 2016 | AV68: =(DataQ!O179/DataQ!P179)*100 -> 1.8166222 | AW68: =(DataQ!N179/DataQ!P179)*100 -> 2.1006035 | AX68: =(DataQ!AG179/DataQ!P179)*100 -> -0.28398122
AE69: =AB37 -> 2023 04 | AF69: =AF37 -> 0.81667829 | AG69: =AF69/4 -> 0.20416957 | AH69: =AG69/AI69 -> 0.053709325 | AI69: =AVERAGE(AF66:AF69) -> 3.8013804 | AQ69: =(DataQ!N180/DataQ!P180)*100 -> 2.2455418 | AR69: =DataQ!Q180 -> 2.903333 | AS69: =DataQ!AF180 -> 0.5 | AV69: =(DataQ!O180/DataQ!P180)*100 -> 1.9696453 | AW69: =(DataQ!N180/DataQ!P180)*100 -> 2.2455418 | AX69: =(DataQ!AG180/DataQ!P180)*100 -> -0.27589651
AE70: =AB38 -> 2024 | AF70: =AF38 -> -0.57148598 | AG70: =AF70/4 -> -0.14287149 | AH70: =AG70/AI73 -> -0.27883719 | AQ70: =(DataQ!N181/DataQ!P181)*100 -> 2.2269147 | AR70: =DataQ!Q181 -> 2.82 | AS70: =DataQ!AF181 -> 0.3409091 | AV70: =(DataQ!O181/DataQ!P181)*100 -> 1.9655511 | AW70: =(DataQ!N181/DataQ!P181)*100 -> 2.2269147 | AX70: =(DataQ!AG181/DataQ!P181)*100 -> -0.26136353
AE71: =AB39 -> 2024 02 | AF71: =AF39 -> 0.79118248 | AG71: =AF71/4 -> 0.19779562 | AH71: =AG71/AI73 -> 0.38603064 | AQ71: =(DataQ!N182/DataQ!P182)*100 -> 2.1754114 | AR71: =DataQ!Q182 -> 2.686667 | AS71: =DataQ!AF182 -> 0.25 | AV71: =(DataQ!O182/DataQ!P182)*100 -> 1.8490845 | AW71: =(DataQ!N182/DataQ!P182)*100 -> 2.1754114 | AX71: =(DataQ!AG182/DataQ!P182)*100 -> -0.32632696
AE72: =AB40 -> 2024 03 | AF72: =AF40 -> 0.39837218 | AG72: =AF72/4 -> 0.099593045 | AH72: =AG72/AI73 -> 0.19437218 | AP72: 2017 | AQ72: =(DataQ!N183/DataQ!P183)*100 -> 1.8634146 | AR72: =DataQ!Q183 -> 2.626667 | AS72: =DataQ!AF183 -> 0.25 | AU72: 2017 | AV72: =(DataQ!O183/DataQ!P183)*100 -> 1.5893293 | AW72: =(DataQ!N183/DataQ!P183)*100 -> 1.8634146 | AX72: =(DataQ!AG183/DataQ!P183)*100 -> -0.27408537
AE73: =AB41 -> 2024 04 | AF73: =AF41 -> 1.4314642 | AG73: =AF73/4 -> 0.35786605 | AH73: =AG73/AI73 -> 0.69843437 | AI73: =AVERAGE(AF70:AF73) -> 0.51238322 | AQ73: =(DataQ!N184/DataQ!P184)*100 -> 1.80594 | AR73: =DataQ!Q184 -> 2.586667 | AS73: =DataQ!AF184 -> 0.25 | AV73: =(DataQ!O184/DataQ!P184)*100 -> 1.4915156 | AW73: =(DataQ!N184/DataQ!P184)*100 -> 1.80594 | AX73: =(DataQ!AG184/DataQ!P184)*100 -> -0.3144244
AQ74: =(DataQ!N185/DataQ!P185)*100 -> 1.6171237 | AR74: =DataQ!Q185 -> 2.533333 | AS74: =DataQ!AF185 -> 0.25 | AV74: =(DataQ!O185/DataQ!P185)*100 -> 1.3863584 | AW74: =(DataQ!N185/DataQ!P185)*100 -> 1.6171237 | AX74: =(DataQ!AG185/DataQ!P185)*100 -> -0.23076538
AQ75: =(DataQ!N186/DataQ!P186)*100 -> 1.7777544 | AR75: =DataQ!Q186 -> 2.516667 | AS75: =DataQ!AF186 -> 0.4115385 | AV75: =(DataQ!O186/DataQ!P186)*100 -> 1.4680074 | AW75: =(DataQ!N186/DataQ!P186)*100 -> 1.7777544 | AX75: =(DataQ!AG186/DataQ!P186)*100 -> -0.30974694
AP76: 2018 | AQ76: =(DataQ!N187/DataQ!P187)*100 -> 1.9511648 | AR76: =DataQ!Q187 -> 2.52 | AS76: =DataQ!AF187 -> 0.5 | AU76: 2018 | AV76: =(DataQ!O187/DataQ!P187)*100 -> 1.6825741 | AW76: =(DataQ!N187/DataQ!P187)*100 -> 1.9511648 | AX76: =(DataQ!AG187/DataQ!P187)*100 -> -0.2685907
AQ77: =(DataQ!N188/DataQ!P188)*100 -> 2.140098 | AR77: =DataQ!Q188 -> 2.483333 | AS77: =DataQ!AF188 -> 0.5 | AV77: =(DataQ!O188/DataQ!P188)*100 -> 1.8004456 | AW77: =(DataQ!N188/DataQ!P188)*100 -> 2.140098 | AX77: =(DataQ!AG188/DataQ!P188)*100 -> -0.3396524
AQ78: =(DataQ!N189/DataQ!P189)*100 -> 2.2034333 | AR78: =DataQ!Q189 -> 2.48 | AS78: =DataQ!AF189 -> 0.6615385 | AV78: =(DataQ!O189/DataQ!P189)*100 -> 1.9370936 | AW78: =(DataQ!N189/DataQ!P189)*100 -> 2.2034333 | AX78: =(DataQ!AG189/DataQ!P189)*100 -> -0.26633968
AQ79: =(DataQ!N190/DataQ!P190)*100 -> 2.3244271 | AR79: =DataQ!Q190 -> 2.493333 | AS79: =DataQ!AF190 -> 0.75 | AV79: =(DataQ!O190/DataQ!P190)*100 -> 2.0400781 | AW79: =(DataQ!N190/DataQ!P190)*100 -> 2.3244271 | AX79: =(DataQ!AG190/DataQ!P190)*100 -> -0.28434903
AP80: 2019 | AQ80: =(DataQ!N191/DataQ!P191)*100 -> 2.2126515 | AR80: =DataQ!Q191 -> 2.463333 | AS80: =DataQ!AF191 -> 0.75 | AU80: 2019 | AV80: =(DataQ!O191/DataQ!P191)*100 -> 1.8499125 | AW80: =(DataQ!N191/DataQ!P191)*100 -> 2.2126515 | AX80: =(DataQ!AG191/DataQ!P191)*100 -> -0.36273896
AQ81: =(DataQ!N192/DataQ!P192)*100 -> 1.8862112 | AR81: =DataQ!Q192 -> 2.436667 | AS81: =DataQ!AF192 -> 0.75 | AV81: =(DataQ!O192/DataQ!P192)*100 -> 1.6062225 | AW81: =(DataQ!N192/DataQ!P192)*100 -> 1.8862112 | AX81: =(DataQ!AG192/DataQ!P192)*100 -> -0.27998878
AQ82: =(DataQ!N193/DataQ!P193)*100 -> 1.811989 | AR82: =DataQ!Q193 -> 2.413333 | AS82: =DataQ!AF193 -> 0.75 | AV82: =(DataQ!O193/DataQ!P193)*100 -> 1.5475011 | AW82: =(DataQ!N193/DataQ!P193)*100 -> 1.811989 | AX82: =(DataQ!AG193/DataQ!P193)*100 -> -0.26448797
AQ83: =(DataQ!N194/DataQ!P194)*100 -> 1.7254452 | AR83: =DataQ!Q194 -> 2.386667 | AS83: =DataQ!AF194 -> 0.75 | AV83: =(DataQ!O194/DataQ!P194)*100 -> 1.5227074 | AW83: =(DataQ!N194/DataQ!P194)*100 -> 1.7254452 | AX83: =(DataQ!AG194/DataQ!P194)*100 -> -0.20273778
AP84: 2020 | AQ84: =(DataQ!N195/DataQ!P195)*100 -> 1.6006053 | AR84: =DataQ!Q195 -> 2.356667 | AS84: =DataQ!AF195 -> 0.6138462 | AU84: 2020 | AV84: =(DataQ!O195/DataQ!P195)*100 -> 1.350131 | AW84: =(DataQ!N195/DataQ!P195)*100 -> 1.6006053 | AX84: =(DataQ!AG195/DataQ!P195)*100 -> -0.2504743
AQ85: =(DataQ!N196/DataQ!P196)*100 -> 1.2082964 | AR85: =DataQ!Q196 -> 2.183333 | AS85: =DataQ!AF196 -> 0.1 | AV85: =(DataQ!O196/DataQ!P196)*100 -> 1.0098146 | AW85: =(DataQ!N196/DataQ!P196)*100 -> 1.2082964 | AX85: =(DataQ!AG196/DataQ!P196)*100 -> -0.19848177
AQ86: =(DataQ!N197/DataQ!P197)*100 -> 1.2191802 | AR86: =DataQ!Q197 -> 2.143333 | AS86: =DataQ!AF197 -> 0.1 | AV86: =(DataQ!O197/DataQ!P197)*100 -> 1.0966632 | AW86: =(DataQ!N197/DataQ!P197)*100 -> 1.2191802 | AX86: =(DataQ!AG197/DataQ!P197)*100 -> -0.12251699
AQ87: =(DataQ!N198/DataQ!P198)*100 -> 1.302637 | AR87: =DataQ!Q198 -> 2.12 | AS87: =DataQ!AF198 -> 0.1 | AV87: =(DataQ!O198/DataQ!P198)*100 -> 1.084852 | AW87: =(DataQ!N198/DataQ!P198)*100 -> 1.302637 | AX87: =(DataQ!AG198/DataQ!P198)*100 -> -0.21778506
AP88: 2021 | AQ88: =(DataQ!N199/DataQ!P199)*100 -> 1.456977 | AR88: =DataQ!Q199 -> 2.09 | AS88: =DataQ!AF199 -> 0.1 | AU88: 2021 | AV88: =(DataQ!O199/DataQ!P199)*100 -> 1.2562915 | AW88: =(DataQ!N199/DataQ!P199)*100 -> 1.456977 | AX88: =(DataQ!AG199/DataQ!P199)*100 -> -0.20068554
AQ89: =(DataQ!N200/DataQ!P200)*100 -> 1.4146234 | AR89: =DataQ!Q200 -> 2.073333 | AS89: =DataQ!AF200 -> 0.1 | AV89: =(DataQ!O200/DataQ!P200)*100 -> 1.3179721 | AW89: =(DataQ!N200/DataQ!P200)*100 -> 1.4146234 | AX89: =(DataQ!AG200/DataQ!P200)*100 -> -0.096651286
AQ90: =(DataQ!N201/DataQ!P201)*100 -> 1.3345073 | AR90: =DataQ!Q201 -> 2.053333 | AS90: =DataQ!AF201 -> 0.1 | AV90: =(DataQ!O201/DataQ!P201)*100 -> 1.3027774 | AW90: =(DataQ!N201/DataQ!P201)*100 -> 1.3345073 | AX90: =(DataQ!AG201/DataQ!P201)*100 -> -0.031729915
AQ91: =(DataQ!N202/DataQ!P202)*100 -> 1.490291 | AR91: =DataQ!Q202 -> 2.02 | AS91: =DataQ!AF202 -> 0.1272727 | AV91: =(DataQ!O202/DataQ!P202)*100 -> 1.4810982 | AW91: =(DataQ!N202/DataQ!P202)*100 -> 1.490291 | AX91: =(DataQ!AG202/DataQ!P202)*100 -> -0.0091928422
AP92: 2022 | AQ92: =(DataQ!N203/DataQ!P203)*100 -> 1.8913686 | AR92: =DataQ!Q203 -> 2.026667 | AS92: =DataQ!AF203 -> 0.453125 | AU92: 2022 | AV92: =(DataQ!O203/DataQ!P203)*100 -> 1.912996 | AW92: =(DataQ!N203/DataQ!P203)*100 -> 1.8913686 | AX92: =(DataQ!AG203/DataQ!P203)*100 -> 0.021627411
AQ93: =(DataQ!N204/DataQ!P204)*100 -> 2.3442505 | AR93: =DataQ!Q204 -> 2.083333 | AS93: =DataQ!AF204 -> 0.95 | AV93: =(DataQ!O204/DataQ!P204)*100 -> 2.3642566 | AW93: =(DataQ!N204/DataQ!P204)*100 -> 2.3442505 | AX93: =(DataQ!AG204/DataQ!P204)*100 -> 0.020006027
AQ94: =(DataQ!N205/DataQ!P205)*100 -> 2.821354 | AR94: =DataQ!Q205 -> 2.186667 | AS94: =DataQ!AF205 -> 1.621212 | AV94: =(DataQ!O205/DataQ!P205)*100 -> 2.8573914 | AW94: =(DataQ!N205/DataQ!P205)*100 -> 2.821354 | AX94: =(DataQ!AG205/DataQ!P205)*100 -> 0.036037379
AQ95: =(DataQ!N206/DataQ!P206)*100 -> 3.6320619 | AR95: =DataQ!Q206 -> 2.396667 | AS95: =DataQ!AF206 -> 2.826923 | AV95: =(DataQ!O206/DataQ!P206)*100 -> 3.9224262 | AW95: =(DataQ!N206/DataQ!P206)*100 -> 3.6320619 | AX95: =(DataQ!AG206/DataQ!P206)*100 -> 0.29036421
AP96: 2023 | AQ96: =(DataQ!N207/DataQ!P207)*100 -> 4.7809902 | AR96: =DataQ!Q207 -> 2.65 | AS96: =DataQ!AF207 -> 3.85 | AU96: 2023 | AV96: =(DataQ!O207/DataQ!P207)*100 -> 5.0975683 | AW96: =(DataQ!N207/DataQ!P207)*100 -> 4.7809902 | AX96: =(DataQ!AG207/DataQ!P207)*100 -> 0.31657813
AQ97: =(DataQ!N208/DataQ!P208)*100 -> 4.853647 | AR97: =DataQ!Q208 -> 2.84 | AS97: =DataQ!AF208 -> 4.446154 | AV97: =(DataQ!O208/DataQ!P208)*100 -> 5.1273746 | AW97: =(DataQ!N208/DataQ!P208)*100 -> 4.853647 | AX97: =(DataQ!AG208/DataQ!P208)*100 -> 0.27372762
AQ98: =(DataQ!N209/DataQ!P209)*100 -> 5.3296559 | AR98: =DataQ!Q209 -> 3.07 | AS98: =DataQ!AF209 -> 5.161539 | AV98: =(DataQ!O209/DataQ!P209)*100 -> 5.7153755 | AW98: =(DataQ!N209/DataQ!P209)*100 -> 5.3296559 | AX98: =(DataQ!AG209/DataQ!P209)*100 -> 0.38571957
AQ99: =(DataQ!N210/DataQ!P210)*100 -> 5.6218113 | AR99: =DataQ!Q210 -> 3.29 | AS99: =DataQ!AF210 -> 5.25 | AV99: =(DataQ!O210/DataQ!P210)*100 -> 5.9551265 | AW99: =(DataQ!N210/DataQ!P210)*100 -> 5.6218113 | AX99: =(DataQ!AG210/DataQ!P210)*100 -> 0.33331434
AP100: 2024 | AQ100: =(DataQ!N211/DataQ!P211)*100 -> 5.7809931 | AR100: =DataQ!Q211 -> 3.46 | AS100: =DataQ!AF211 -> 5.25 | AU100: 2024 | AV100: =(DataQ!O211/DataQ!P211)*100 -> 5.7832346 | AW100: =(DataQ!N211/DataQ!P211)*100 -> 5.7809931 | AX100: =(DataQ!AG211/DataQ!P211)*100 -> 0.0022405397
AQ101: =(DataQ!N212/DataQ!P212)*100 -> 5.7663353 | AR101: =DataQ!Q212 -> 3.610189 | AS101: =DataQ!AF212 -> 5.223077 | AV101: =(DataQ!O212/DataQ!P212)*100 -> 5.6196216 | AW101: =(DataQ!N212/DataQ!P212)*100 -> 5.7663353 | AX101: =(DataQ!AG212/DataQ!P212)*100 -> -0.14671242
...

Sheet DataQ
C1: =GMWQ!$LR$14 -> FEB016J.db | D1: =$C$1 -> FEB016J.db | E1: =$C$1 -> FEB016J.db | F1: =$C$1 -> FEB016J.db | G1: =$C$1 -> FEB016J.db | H1: =$C$1 -> FEB016J.db | I1: =$C$1 -> FEB016J.db | J1: =$C$1 -> FEB016J.db | K1: =$C$1 -> FEB016J.db | ... AG1: =$C$1 -> FEB016J.db | AI1: =$C$1 -> FEB016J.db | AJ1: =$C$1 -> FEB016J.db | AK1: =$C$1 -> FEB016J.db | AL1: =$C$1 -> FEB016J.db | AM1: =$C$1 -> FEB016J.db | AN1: =$C$1 -> FEB016J.db | AO1: =$C$1 -> FEB016J.db | AP1: =$C$1 -> FEB016J.db | ... AU1: =$C$1 -> FEB016J.db
C2: UK | D2: UK | E2: UK | F2: UK | G2: UK | H2: UK | I2: UK | J2: UK | K2: UK | L2: UK | M2: UK | N2: UK | O2: UK | P2: UK | Q2: UK | R2: UK | S2: UK | T2: UK | U2: UK | V2: UK | W2: UK | X2: UK | Y2: UK | Z2: UK | AA2: UK | AB2: UK | AC2: UK | AD2: UK | AE2: UK | AF2: UK | AG2: UK | AI2: UK | AJ2: UK | AK2: UK | AL2: UK | AM2: UK | AN2: UK | AO2: UK | AP2: UK | AQ2: UK | AR2: UK | AS2: UK | AT2: UK | AU2: UK
C3: GDP | D3: WAGEWKLY | E3: CPI | F3: PEWFP | G3: TY | H3: TSS | I3: PC | J3: EE | K3: RCBEOP | L3: UPILO | M3: PH | N3: PEDIP | O3: PEDIR | P3: PEDY! | Q3: RBM | R3: MAPP | S3: RPT | T3: GLMRT | U3: NADV | V3: LQRTUK | W3: CGEAR | X3: COMP | Y3: PGDP | Z3: YHAT | AA3: GREVX | AB3: PSCEX | AC3: PSNIX | AD3: DEPX | AE3: GDP! | AF3: RCB | AG3: PENIR | AI3: PEDY! | AJ3: PC | AK3: PEWFP | AL3: ER | AM3: EE | AN3: TY | AO3: TSS | AP3: PENIR | AQ3: GCGPE | AR3: C! | AS3: CNPI! | AT3: C | AU3: CNPI
C4: GBR | D4: GBR | E4: GBR | F4: GBR | G4: GBR | H4: GBR | I4: GBR | J4: GBR | K4: GBR | L4: GBR | M4: GBR | N4: GBR | O4: GBR | P4: GBR | Q4: GBR | R4: GBR | S4: GBR | T4: GBR | U4: GBR | V4: GBR | W4: GBR | X4: GBR | Y4: GBR | Z4: GBR | AA4: GBR | AB4: GBR | AC4: GBR | AD4: GBR | AE4: GBR | AF4: GBR | AG4: GBR | AI4: GBR | AJ4: GBR | AK4: GBR | AL4: GBR | AM4: GBR | AN4: GBR | AO4: GBR | AP4: GBR | AQ4: GBR | AR4: GBR | AS4: GBR | AT4: GBR | AU4: GBR
C5: L | D5: L | E5: L | F5: L | G5: L | H5: L | I5: L | J5: L | K5: L | L5: L | M5: L | N5: L | O5: L | P5: L | Q5: L | R5: L | S5: L | T5: L | U5: L | V5: L | W5: L | X5: L | Y5: L | Z5: L | AA5: L | AB5: L | AC5: L | AD5: L | AE5: L | AF5: L | AG5: L | AI5: L | AJ5: L | AK5: L | AL5: L | AM5: L | AN5: L | AO5: L | AP5: L | AQ5: L | AR5: L | AS5: L | AT5: L | AU5: L
B6: =B318+5 -> 2289 | C6: {=_xlfn.CONCAT(INDEX(GMWQ!$A$2:$LR$60,MATCH(1,(GMWQ!$LQ$2:$LQ$60=C$3)*(GMWQ!$LP$2:$LP$60=C$4)*(GMWQ!$LR$2:$LR$60=C$1),0),$B6-1966),"0",(INDEX(GMWQ!$A$2:$LR$60,MATCH(1,(GMWQ!$LQ$2:$LQ$60=C$3)*(GMWQ!$LP$2:$LP$60=C$4)*(GMWQ!$LR$2:$LR$60=C$1),0),$B6-1965)))} -> 202304 | D6: {=_xlfn.CONCAT(INDEX(GMWQ!$A$2:$LR$60,MATCH(1,(GMWQ!$LQ$2:$LQ$60=D$3)*(GMWQ!$LP$2:$LP$60=D$4)*(GMWQ!$LR$2:$LR$60=D$1),0),$B6-1966),"0",(INDEX(GMWQ!$A$2:$LR$60,MATCH(1,(GMWQ!$LQ$2:$LQ$60=D$3)*(GMWQ!$LP$2:$LP$60=D$4)*(GMWQ!$LR$2:$LR$60=D$1),0),$B6-1965)))} -> 202304 | E6: {=_xlfn.CONCAT(INDEX(GMWQ!$A$2:$LR$60,MATCH(1,(GMWQ!$LQ$2:$LQ$60=E$3)*(GMWQ!$LP$2:$LP$60=E$4)*(GMWQ!$LR$2:$LR$60=E$1),0),$B6-1966),"0",(INDEX(GMWQ!$A$2:$LR$60,MATCH(1,(GMWQ!$LQ$2:$LQ$60=E$3)*(GMWQ!$LP$2:$LP$60=E$4)*(GMWQ!$LR$2:$LR$60=E$1),0),$B6-1965)))} -> 202304 | F6: {=_xlfn.CONCAT(INDEX(GMWQ!$A$2:$LR$60,MATCH(1,(GMWQ!$LQ$2:$LQ$60=F$3)*(GMWQ!$LP$2:$LP$60=F$4)*(GMWQ!$LR$2:$LR$60=F$1),0),$B6-1966),"0",(INDEX(GMWQ!$A$2:$LR$60,MATCH(1,(GMWQ!$LQ$2:$LQ$60=F$3)*(GMWQ!$LP$2:$LP$60=F$4)*(GMWQ!$LR$2:$LR$60=F$1),0),$B6-1965)))} -> 202303 | G6: {=_xlfn.CONCAT(INDEX(GMWQ!$A$2:$LR$60,MATCH(1,(GMWQ!$LQ$2:$LQ$60=G$3)*(GMWQ!$LP$2:$LP$60=G$4)*(GMWQ!$LR$2:$LR$60=G$1),0),$B6-1966),"0",(INDEX(GMWQ!$A$2:$LR$60,MATCH(1,(GMWQ!$LQ$2:$LQ$60=G$3)*(GMWQ!$LP$2:$LP$60=G$4)*(GMWQ!$LR$2:$LR$60=G$1),0),$B6-1965)))} -> 202303 | H6: {=_xlfn.CONCAT(INDEX(GMWQ!$A$2:$LR$60,MATCH(1,(GMWQ!$LQ$2:$LQ$60=H$3)*(GMWQ!$LP$2:$LP$60=H$4)*(GMWQ!$LR$2:$LR$60=H$1),0),$B6-1966),"0",(INDEX(GMWQ!$A$2:$LR$60,MATCH(1,(GMWQ!$LQ$2:$LQ$60=H$3)*(GMWQ!$LP$2:$LP$60=H$4)*(GMWQ!$LR$2:$LR$60=H$1),0),$B6-1965)))} -> 202303 | I6: {=_xlfn.CONCAT(INDEX(GMWQ!$A$2:$LR$60,MATCH(1,(GMWQ!$LQ$2:$LQ$60=I$3)*(GMWQ!$LP$2:$LP$60=I$4)*(GMWQ!$LR$2:$LR$60=I$1),0),$B6-1966),"0",(INDEX(GMWQ!$A$2:$LR$60,MATCH(1,(GMWQ!$LQ$2:$LQ$60=I$3)*(GMWQ!$LP$2:$LP$60=I$4)*(GMWQ!$LR$2:$LR$60=I$1),0),$B6-1965)))} -> 202304 | J6: {=_xlfn.CONCAT(INDEX(GMWQ!$A$2:$LR$60,MATCH(1,(GMWQ!$LQ$2:$LQ$60=J$3)*(GMWQ!$LP$2:$LP$60=J$4)*(GMWQ!$LR$2:$LR$60=J$1),0),$B6-1966),"0",(INDEX(GMWQ!$A$2:$LR$60,MATCH(1,(GMWQ!$LQ$2:$LQ$60=J$3)*(GMWQ!$LP$2:$LP$60=J$4)*(GMWQ!$LR$2:$LR$60=J$1),0),$B6-1965)))} -> 202304 | ... AG6: {=_xlfn.CONCAT(INDEX(GMWQ!$A$2:$LR$60,MATCH(1,(GMWQ!$LQ$2:$LQ$60=AG$3)*(GMWQ!$LP$2:$LP$60=AG$4)*(GMWQ!$LR$2:$LR$60=AG$1),0),$B6-1966),"0",(INDEX(GMWQ!$A$2:$LR$60,MATCH(1,(GMWQ!$LQ$2:$LQ$60=AG$3)*(GMWQ!$LP$2:$LP$60=AG$4)*(GMWQ!$LR$2:$LR$60=AG$1),0),$B6-1965)))} -> 202303 | AI6: {=_xlfn.CONCAT(INDEX(GMWQ!$A$2:$LR$60,MATCH(1,(GMWQ!$LQ$2:$LQ$60=AI$3)*(GMWQ!$LP$2:$LP$60=AI$4)*(GMWQ!$LR$2:$LR$60=AI$1),0),$B6-1966),"0",(INDEX(GMWQ!$A$2:$LR$60,MATCH(1,(GMWQ!$LQ$2:$LQ$60=AI$3)*(GMWQ!$LP$2:$LP$60=AI$4)*(GMWQ!$LR$2:$LR$60=AI$1),0),$B6-1965)))} -> 202303 | AJ6: {=_xlfn.CONCAT(INDEX(GMWQ!$A$2:$LR$60,MATCH(1,(GMWQ!$LQ$2:$LQ$60=AJ$3)*(GMWQ!$LP$2:$LP$60=AJ$4)*(GMWQ!$LR$2:$LR$60=AJ$1),0),$B6-1966),"0",(INDEX(GMWQ!$A$2:$LR$60,MATCH(1,(GMWQ!$LQ$2:$LQ$60=AJ$3)*(GMWQ!$LP$2:$LP$60=AJ$4)*(GMWQ!$LR$2:$LR$60=AJ$1),0),$B6-1965)))} -> 202304 | AK6: {=_xlfn.CONCAT(INDEX(GMWQ!$A$2:$LR$60,MATCH(1,(GMWQ!$LQ$2:$LQ$60=AK$3)*(GMWQ!$LP$2:$LP$60=AK$4)*(GMWQ!$LR$2:$LR$60=AK$1),0),$B6-1966),"0",(INDEX(GMWQ!$A$2:$LR$60,MATCH(1,(GMWQ!$LQ$2:$LQ$60=AK$3)*(GMWQ!$LP$2:$LP$60=AK$4)*(GMWQ!$LR$2:$LR$60=AK$1),0),$B6-1965)))} -> 202303 | AL6: {=_xlfn.CONCAT(INDEX(GMWQ!$A$2:$LR$60,MATCH(1,(GMWQ!$LQ$2:$LQ$60=AL$3)*(GMWQ!$LP$2:$LP$60=AL$4)*(GMWQ!$LR$2:$LR$60=AL$1),0),$B6-1966),"0",(INDEX(GMWQ!$A$2:$LR$60,MATCH(1,(GMWQ!$LQ$2:$LQ$60=AL$3)*(GMWQ!$LP$2:$LP$60=AL$4)*(GMWQ!$LR$2:$LR$60=AL$1),0),$B6-1965)))} -> 202303 | AM6: {=_xlfn.CONCAT(INDEX(GMWQ!$A$2:$LR$60,MATCH(1,(GMWQ!$LQ$2:$LQ$60=AM$3)*(GMWQ!$LP$2:$LP$60=AM$4)*(GMWQ!$LR$2:$LR$60=AM$1),0),$B6-1966),"0",(INDEX(GMWQ!$A$2:$LR$60,MATCH(1,(GMWQ!$LQ$2:$LQ$60=AM$3)*(GMWQ!$LP$2:$LP$60=AM$4)*(GMWQ!$LR$2:$LR$60=AM$1),0),$B6-1965)))} -> 202304 | AN6: {=_xlfn.CONCAT(INDEX(GMWQ!$A$2:$LR$60,MATCH(1,(GMWQ!$LQ$2:$LQ$60=AN$3)*(GMWQ!$LP$2:$LP$60=AN$4)*(GMWQ!$LR$2:$LR$60=AN$1),0),$B6-1966),"0",(INDEX(GMWQ!$A$2:$LR$60,MATCH(1,(GMWQ!$LQ$2:$LQ$60=AN$3)*(GMWQ!$LP$2:$LP$60=AN$4)*(GMWQ!$LR$2:$LR$60=AN$1),0),$B6-1965)))} -> 202303 | AO6: {=_xlfn.CONCAT(INDEX(GMWQ!$A$2:$LR$60,MATCH(1,(GMWQ!$LQ$2:$LQ$60=AO$3)*(GMWQ!$LP$2:$LP$60=AO$4)*(GMWQ!$LR$2:$LR$60=AO$1),0),$B6-1966),"0",(INDEX(GMWQ!$A$2:$LR$60,MATCH(1,(GMWQ!$LQ$2:$LQ$60=AO$3)*(GMWQ!$LP$2:$LP$60=AO$4)*(GMWQ!$LR$2:$LR$60=AO$1),0),$B6-1965)))} -> 202303 | AP6: {=_xlfn.CONCAT(INDEX(GMWQ!$A$2:$LR$60,MATCH(1,(GMWQ!$LQ$2:$LQ$60=AP$3)*(GMWQ!$LP$2:$LP$60=AP$4)*(GMWQ!$LR$2:$LR$60=AP$1),0),$B6-1966),"0",(INDEX(GMWQ!$A$2:$LR$60,MATCH(1,(GMWQ!$LQ$2:$LQ$60=AP$3)*(GMWQ!$LP$2:$LP$60=AP$4)*(GMWQ!$LR$2:$LR$60=AP$1),0),$B6-1965)))} -> 202303 | ... AU6: {=_xlfn.CONCAT(INDEX(GMWQ!$A$2:$LR$60,MATCH(1,(GMWQ!$LQ$2:$LQ$60=AU$3)*(GMWQ!$LP$2:$LP$60=AU$4)*(GMWQ!$LR$2:$LR$60=AU$1),0),$B6-1966),"0",(INDEX(GMWQ!$A$2:$LR$60,MATCH(1,(GMWQ!$LQ$2:$LQ$60=AU$3)*(GMWQ!$LP$2:$LP$60=AU$4)*(GMWQ!$LR$2:$LR$60=AU$1),0),$B6-1965)))} -> 202304
A7: 1973 | B7: 1973 | C7: {=INDEX(GMWQ!$A$2:$LR$60,MATCH(1,(GMWQ!$LQ$2:$LQ$60=C$3)*(GMWQ!$LP$2:$LP$60=C$4)*(GMWQ!$LR$2:$LR$60=C$1),0),$B7-1966)} -> 223780 | D7: {=INDEX(GMWQ!$A$2:$LR$60,MATCH(1,(GMWQ!$LQ$2:$LQ$60=D$3)*(GMWQ!$LP$2:$LP$60=D$4)*(GMWQ!$LR$2:$LR$60=D$1),0),$B7-1966)} -> 14.85115 | E7: {=INDEX(GMWQ!$A$2:$LR$60,MATCH(1,(GMWQ!$LQ$2:$LQ$60=E$3)*(GMWQ!$LP$2:$LP$60=E$4)*(GMWQ!$LR$2:$LR$60=E$1),0),$B7-1966)} -> 11.88749 | F7: {=INDEX(GMWQ!$A$2:$LR$60,MATCH(1,(GMWQ!$LQ$2:$LQ$60=F$3)*(GMWQ!$LP$2:$LP$60=F$4)*(GMWQ!$LR$2:$LR$60=F$1),0),$B7-1966)} -> 9375 | G7: {=INDEX(GMWQ!$A$2:$LR$60,MATCH(1,(GMWQ!$LQ$2:$LQ$60=G$3)*(GMWQ!$LP$2:$LP$60=G$4)*(GMWQ!$LR$2:$LR$60=G$1),0),$B7-1966)} -> 1814.938 | H7: {=INDEX(GMWQ!$A$2:$LR$60,MATCH(1,(GMWQ!$LQ$2:$LQ$60=H$3)*(GMWQ!$LP$2:$LP$60=H$4)*(GMWQ!$LR$2:$LR$60=H$1),0),$B7-1966)} -> 481.4688 | I7: {=INDEX(GMWQ!$A$2:$LR$60,MATCH(1,(GMWQ!$LQ$2:$LQ$60=I$3)*(GMWQ!$LP$2:$LP$60=I$4)*(GMWQ!$LR$2:$LR$60=I$1),0),$B7-1966)} -> 10.26345 | J7: {=INDEX(GMWQ!$A$2:$LR$60,MATCH(1,(GMWQ!$LQ$2:$LQ$60=J$3)*(GMWQ!$LP$2:$LP$60=J$4)*(GMWQ!$LR$2:$LR$60=J$1),0),$B7-1966)} -> 22166.19 | ... AG7: {=INDEX(GMWQ!$A$2:$LR$60,MATCH(1,(GMWQ!$LQ$2:$LQ$60=AG$3)*(GMWQ!$LP$2:$LP$60=AG$4)*(GMWQ!$LR$2:$LR$60=AG$1),0),$B7-1966)} -> -77.03071 | AI7: {=INDEX(GMWQ!$A$2:$LR$60,MATCH(1,(GMWQ!$LQ$2:$LQ$60=AI$3)*(GMWQ!$LP$2:$LP$60=AI$4)*(GMWQ!$LR$2:$LR$60=AI$1),0),$B7-1966)} -> 12419 | AJ7: {=INDEX(GMWQ!$A$2:$LR$60,MATCH(1,(GMWQ!$LQ$2:$LQ$60=AJ$3)*(GMWQ!$LP$2:$LP$60=AJ$4)*(GMWQ!$LR$2:$LR$60=AJ$1),0),$B7-1966)} -> 10.26345 | AK7: {=INDEX(GMWQ!$A$2:$LR$60,MATCH(1,(GMWQ!$LQ$2:$LQ$60=AK$3)*(GMWQ!$LP$2:$LP$60=AK$4)*(GMWQ!$LR$2:$LR$60=AK$1),0),$B7-1966)} -> 9375 | AL7: {=INDEX(GMWQ!$A$2:$LR$60,MATCH(1,(GMWQ!$LQ$2:$LQ$60=AL$3)*(GMWQ!$LP$2:$LP$60=AL$4)*(GMWQ!$LR$2:$LR$60=AL$1),0),$B7-1966)} -> 422.9413 | AM7: {=INDEX(GMWQ!$A$2:$LR$60,MATCH(1,(GMWQ!$LQ$2:$LQ$60=AM$3)*(GMWQ!$LP$2:$LP$60=AM$4)*(GMWQ!$LR$2:$LR$60=AM$1),0),$B7-1966)} -> 22166.19 | AN7: {=INDEX(GMWQ!$A$2:$LR$60,MATCH(1,(GMWQ!$LQ$2:$LQ$60=AN$3)*(GMWQ!$LP$2:$LP$60=AN$4)*(GMWQ!$LR$2:$LR$60=AN$1),0),$B7-1966)} -> 1814.938 | AO7: {=INDEX(GMWQ!$A$2:$LR$60,MATCH(1,(GMWQ!$LQ$2:$LQ$60=AO$3)*(GMWQ!$LP$2:$LP$60=AO$4)*(GMWQ!$LR$2:$LR$60=AO$1),0),$B7-1966)} -> 481.4688 | AP7: {=INDEX(GMWQ!$A$2:$LR$60,MATCH(1,(GMWQ!$LQ$2:$LQ$60=AP$3)*(GMWQ!$LP$2:$LP$60=AP$4)*(GMWQ!$LR$2:$LR$60=AP$1),0),$B7-1966)} -> -77.03071 | ... AU7: {=INDEX(GMWQ!$A$2:$LR$60,MATCH(1,(GMWQ!$LQ$2:$LQ$60=AU$3)*(GMWQ!$LP$2:$LP$60=AU$4)*(GMWQ!$LR$2:$LR$60=AU$1),0),$B7-1966)} -> 3611
B8: =+B7+1 -> 1974 | C8: {=INDEX(GMWQ!$A$2:$LR$60,MATCH(1,(GMWQ!$LQ$2:$LQ$60=C$3)*(GMWQ!$LP$2:$LP$60=C$4)*(GMWQ!$LR$2:$LR$60=C$1),0),$B8-1966)} -> 224213 | D8: {=INDEX(GMWQ!$A$2:$LR$60,MATCH(1,(GMWQ!$LQ$2:$LQ$60=D$3)*(GMWQ!$LP$2:$LP$60=D$4)*(GMWQ!$LR$2:$LR$60=D$1),0),$B8-1966)} -> 15.59743 | E8: {=INDEX(GMWQ!$A$2:$LR$60,MATCH(1,(GMWQ!$LQ$2:$LQ$60=E$3)*(GMWQ!$LP$2:$LP$60=E$4)*(GMWQ!$LR$2:$LR$60=E$1),0),$B8-1966)} -> 12.3046 | F8: {=INDEX(GMWQ!$A$2:$LR$60,MATCH(1,(GMWQ!$LQ$2:$LQ$60=F$3)*(GMWQ!$LP$2:$LP$60=F$4)*(GMWQ!$LR$2:$LR$60=F$1),0),$B8-1966)} -> 9711 | G8: {=INDEX(GMWQ!$A$2:$LR$60,MATCH(1,(GMWQ!$LQ$2:$LQ$60=G$3)*(GMWQ!$LP$2:$LP$60=G$4)*(GMWQ!$LR$2:$LR$60=G$1),0),$B8-1966)} -> 1958.352 | H8: {=INDEX(GMWQ!$A$2:$LR$60,MATCH(1,(GMWQ!$LQ$2:$LQ$60=H$3)*(GMWQ!$LP$2:$LP$60=H$4)*(GMWQ!$LR$2:$LR$60=H$1),0),$B8-1966)} -> 483.5805 | I8: {=INDEX(GMWQ!$A$2:$LR$60,MATCH(1,(GMWQ!$LQ$2:$LQ$60=I$3)*(GMWQ!$LP$2:$LP$60=I$4)*(GMWQ!$LR$2:$LR$60=I$1),0),$B8-1966)} -> 10.39237 | J8: {=INDEX(GMWQ!$A$2:$LR$60,MATCH(1,(GMWQ!$LQ$2:$LQ$60=J$3)*(GMWQ!$LP$2:$LP$60=J$4)*(GMWQ!$LR$2:$LR$60=J$1),0),$B8-1966)} -> 22172.06 | ... AG8: {=INDEX(GMWQ!$A$2:$LR$60,MATCH(1,(GMWQ!$LQ$2:$LQ$60=AG$3)*(GMWQ!$LP$2:$LP$60=AG$4)*(GMWQ!$LR$2:$LR$60=AG$1),0),$B8-1966)} -> -108.96 | AI8: {=INDEX(GMWQ!$A$2:$LR$60,MATCH(1,(GMWQ!$LQ$2:$LQ$60=AI$3)*(GMWQ!$LP$2:$LP$60=AI$4)*(GMWQ!$LR$2:$LR$60=AI$1),0),$B8-1966)} -> 12849 | AJ8: {=INDEX(GMWQ!$A$2:$LR$60,MATCH(1,(GMWQ!$LQ$2:$LQ$60=AJ$3)*(GMWQ!$LP$2:$LP$60=AJ$4)*(GMWQ!$LR$2:$LR$60=AJ$1),0),$B8-1966)} -> 10.39237 | AK8: {=INDEX(GMWQ!$A$2:$LR$60,MATCH(1,(GMWQ!$LQ$2:$LQ$60=AK$3)*(GMWQ!$LP$2:$LP$60=AK$4)*(GMWQ!$LR$2:$LR$60=AK$1),0),$B8-1966)} -> 9711 | AL8: {=INDEX(GMWQ!$A$2:$LR$60,MATCH(1,(GMWQ!$LQ$2:$LQ$60=AL$3)*(GMWQ!$LP$2:$LP$60=AL$4)*(GMWQ!$LR$2:$LR$60=AL$1),0),$B8-1966)} -> 437.9837 | AM8: {=INDEX(GMWQ!$A$2:$LR$60,MATCH(1,(GMWQ!$LQ$2:$LQ$60=AM$3)*(GMWQ!$LP$2:$LP$60=AM$4)*(GMWQ!$LR$2:$LR$60=AM$1),0),$B8-1966)} -> 22172.06 | AN8: {=INDEX(GMWQ!$A$2:$LR$60,MATCH(1,(GMWQ!$LQ$2:$LQ$60=AN$3)*(GMWQ!$LP$2:$LP$60=AN$4)*(GMWQ!$LR$2:$LR$60=AN$1),0),$B8-1966)} -> 1958.352 | AO8: {=INDEX(GMWQ!$A$2:$LR$60,MATCH(1,(GMWQ!$LQ$2:$LQ$60=AO$3)*(GMWQ!$LP$2:$LP$60=AO$4)*(GMWQ!$LR$2:$LR$60=AO$1),0),$B8-1966)} -> 483.5805 | AP8: {=INDEX(GMWQ!$A$2:$LR$60,MATCH(1,(GMWQ!$LQ$2:$LQ$60=AP$3)*(GMWQ!$LP$2:$LP$60=AP$4)*(GMWQ!$LR$2:$LR$60=AP$1),0),$B8-1966)} -> -108.96 | ... AU8: {=INDEX(GMWQ!$A$2:$LR$60,MATCH(1,(GMWQ!$LQ$2:$LQ$60=AU$3)*(GMWQ!$LP$2:$LP$60=AU$4)*(GMWQ!$LR$2:$LR$60=AU$1),0),$B8-1966)} -> 3553
B9: =+B8+1 -> 1975 | C9: {=INDEX(GMWQ!$A$2:$LR$60,MATCH(1,(GMWQ!$LQ$2:$LQ$60=C$3)*(GMWQ!$LP$2:$LP$60=C$4)*(GMWQ!$LR$2:$LR$60=C$1),0),$B9-1966)} -> 222122 | D9: {=INDEX(GMWQ!$A$2:$LR$60,MATCH(1,(GMWQ!$LQ$2:$LQ$60=D$3)*(GMWQ!$LP$2:$LP$60=D$4)*(GMWQ!$LR$2:$LR$60=D$1),0),$B9-1966)} -> 16.40707 | E9: {=INDEX(GMWQ!$A$2:$LR$60,MATCH(1,(GMWQ!$LQ$2:$LQ$60=E$3)*(GMWQ!$LP$2:$LP$60=E$4)*(GMWQ!$LR$2:$LR$60=E$1),0),$B9-1966)} -> 12.51315 | F9: {=INDEX(GMWQ!$A$2:$LR$60,MATCH(1,(GMWQ!$LQ$2:$LQ$60=F$3)*(GMWQ!$LP$2:$LP$60=F$4)*(GMWQ!$LR$2:$LR$60=F$1),0),$B9-1966)} -> 10012 | G9: {=INDEX(GMWQ!$A$2:$LR$60,MATCH(1,(GMWQ!$LQ$2:$LQ$60=G$3)*(GMWQ!$LP$2:$LP$60=G$4)*(GMWQ!$LR$2:$LR$60=G$1),0),$B9-1966)} -> 1917.801 | H9: {=INDEX(GMWQ!$A$2:$LR$60,MATCH(1,(GMWQ!$LQ$2:$LQ$60=H$3)*(GMWQ!$LP$2:$LP$60=H$4)*(GMWQ!$LR$2:$LR$60=H$1),0),$B9-1966)} -> 509.9768 | I9: {=INDEX(GMWQ!$A$2:$LR$60,MATCH(1,(GMWQ!$LQ$2:$LQ$60=I$3)*(GMWQ!$LP$2:$LP$60=I$4)*(GMWQ!$LR$2:$LR$60=I$1),0),$B9-1966)} -> 10.63164 | J9: {=INDEX(GMWQ!$A$2:$LR$60,MATCH(1,(GMWQ!$LQ$2:$LQ$60=J$3)*(GMWQ!$LP$2:$LP$60=J$4)*(GMWQ!$LR$2:$LR$60=J$1),0),$B9-1966)} -> 22214.1 | ... AG9: {=INDEX(GMWQ!$A$2:$LR$60,MATCH(1,(GMWQ!$LQ$2:$LQ$60=AG$3)*(GMWQ!$LP$2:$LP$60=AG$4)*(GMWQ!$LR$2:$LR$60=AG$1),0),$B9-1966)} -> -122.3405 | AI9: {=INDEX(GMWQ!$A$2:$LR$60,MATCH(1,(GMWQ!$LQ$2:$LQ$60=AI$3)*(GMWQ!$LP$2:$LP$60=AI$4)*(GMWQ!$LR$2:$LR$60=AI$1),0),$B9-1966)} -> 13247 | AJ9: {=INDEX(GMWQ!$A$2:$LR$60,MATCH(1,(GMWQ!$LQ$2:$LQ$60=AJ$3)*(GMWQ!$LP$2:$LP$60=AJ$4)*(GMWQ!$LR$2:$LR$60=AJ$1),0),$B9-1966)} -> 10.63164 | AK9: {=INDEX(GMWQ!$A$2:$LR$60,MATCH(1,(GMWQ!$LQ$2:$LQ$60=AK$3)*(GMWQ!$LP$2:$LP$60=AK$4)*(GMWQ!$LR$2:$LR$60=AK$1),0),$B9-1966)} -> 10012 | AL9: {=INDEX(GMWQ!$A$2:$LR$60,MATCH(1,(GMWQ!$LQ$2:$LQ$60=AL$3)*(GMWQ!$LP$2:$LP$60=AL$4)*(GMWQ!$LR$2:$LR$60=AL$1),0),$B9-1966)} -> 450.7047 | AM9: {=INDEX(GMWQ!$A$2:$LR$60,MATCH(1,(GMWQ!$LQ$2:$LQ$60=AM$3)*(GMWQ!$LP$2:$LP$60=AM$4)*(GMWQ!$LR$2:$LR$60=AM$1),0),$B9-1966)} -> 22214.1 | AN9: {=INDEX(GMWQ!$A$2:$LR$60,MATCH(1,(GMWQ!$LQ$2:$LQ$60=AN$3)*(GMWQ!$LP$2:$LP$60=AN$4)*(GMWQ!$LR$2:$LR$60=AN$1),0),$B9-1966)} -> 1917.801 | AO9: {=INDEX(GMWQ!$A$2:$LR$60,MATCH(1,(GMWQ!$LQ$2:$LQ$60=AO$3)*(GMWQ!$LP$2:$LP$60=AO$4)*(GMWQ!$LR$2:$LR$60=AO$1),0),$B9-1966)} -> 509.9768 | AP9: {=INDEX(GMWQ!$A$2:$LR$60,MATCH(1,(GMWQ!$LQ$2:$LQ$60=AP$3)*(GMWQ!$LP$2:$LP$60=AP$4)*(GMWQ!$LR$2:$LR$60=AP$1),0),$B9-1966)} -> -122.3405 | ... AU9: {=INDEX(GMWQ!$A$2:$LR$60,MATCH(1,(GMWQ!$LQ$2:$LQ$60=AU$3)*(GMWQ!$LP$2:$LP$60=AU$4)*(GMWQ!$LR$2:$LR$60=AU$1),0),$B9-1966)} -> 3684
B10: =+B9+1 -> 1976 | C10: {=INDEX(GMWQ!$A$2:$LR$60,MATCH(1,(GMWQ!$LQ$2:$LQ$60=C$3)*(GMWQ!$LP$2:$LP$60=C$4)*(GMWQ!$LR$2:$LR$60=C$1),0),$B10-1966)} -> 221266 | D10: {=INDEX(GMWQ!$A$2:$LR$60,MATCH(1,(GMWQ!$LQ$2:$LQ$60=D$3)*(GMWQ!$LP$2:$LP$60=D$4)*(GMWQ!$LR$2:$LR$60=D$1),0),$B10-1966)} -> 16.90761 | E10: {=INDEX(GMWQ!$A$2:$LR$60,MATCH(1,(GMWQ!$LQ$2:$LQ$60=E$3)*(GMWQ!$LP$2:$LP$60=E$4)*(GMWQ!$LR$2:$LR$60=E$1),0),$B10-1966)} -> 13.00846 | F10: {=INDEX(GMWQ!$A$2:$LR$60,MATCH(1,(GMWQ!$LQ$2:$LQ$60=F$3)*(GMWQ!$LP$2:$LP$60=F$4)*(GMWQ!$LR$2:$LR$60=F$1),0),$B10-1966)} -> 10380 | G10: {=INDEX(GMWQ!$A$2:$LR$60,MATCH(1,(GMWQ!$LQ$2:$LQ$60=G$3)*(GMWQ!$LP$2:$LP$60=G$4)*(GMWQ!$LR$2:$LR$60=G$1),0),$B10-1966)} -> 1950.44 | H10: {=INDEX(GMWQ!$A$2:$LR$60,MATCH(1,(GMWQ!$LQ$2:$LQ$60=H$3)*(GMWQ!$LP$2:$LP$60=H$4)*(GMWQ!$LR$2:$LR$60=H$1),0),$B10-1966)} -> 513.1444 | I10: {=INDEX(GMWQ!$A$2:$LR$60,MATCH(1,(GMWQ!$LQ$2:$LQ$60=I$3)*(GMWQ!$LP$2:$LP$60=I$4)*(GMWQ!$LR$2:$LR$60=I$1),0),$B10-1966)} -> 11.13748 | J10: {=INDEX(GMWQ!$A$2:$LR$60,MATCH(1,(GMWQ!$LQ$2:$LQ$60=J$3)*(GMWQ!$LP$2:$LP$60=J$4)*(GMWQ!$LR$2:$LR$60=J$1),0),$B10-1966)} -> 22247.34 | ... AG10: {=INDEX(GMWQ!$A$2:$LR$60,MATCH(1,(GMWQ!$LQ$2:$LQ$60=AG$3)*(GMWQ!$LP$2:$LP$60=AG$4)*(GMWQ!$LR$2:$LR$60=AG$1),0),$B10-1966)} -> -178.7535 | AI10: {=INDEX(GMWQ!$A$2:$LR$60,MATCH(1,(GMWQ!$LQ$2:$LQ$60=AI$3)*(GMWQ!$LP$2:$LP$60=AI$4)*(GMWQ!$LR$2:$LR$60=AI$1),0),$B10-1966)} -> 13917 | AJ10: {=INDEX(GMWQ!$A$2:$LR$60,MATCH(1,(GMWQ!$LQ$2:$LQ$60=AJ$3)*(GMWQ!$LP$2:$LP$60=AJ$4)*(GMWQ!$LR$2:$LR$60=AJ$1),0),$B10-1966)} -> 11.13748 | AK10: {=INDEX(GMWQ!$A$2:$LR$60,MATCH(1,(GMWQ!$LQ$2:$LQ$60=AK$3)*(GMWQ!$LP$2:$LP$60=AK$4)*(GMWQ!$LR$2:$LR$60=AK$1),0),$B10-1966)} -> 10380 | AL10: {=INDEX(GMWQ!$A$2:$LR$60,MATCH(1,(GMWQ!$LQ$2:$LQ$60=AL$3)*(GMWQ!$LP$2:$LP$60=AL$4)*(GMWQ!$LR$2:$LR$60=AL$1),0),$B10-1966)} -> 466.5726 | AM10: {=INDEX(GMWQ!$A$2:$LR$60,MATCH(1,(GMWQ!$LQ$2:$LQ$60=AM$3)*(GMWQ!$LP$2:$LP$60=AM$4)*(GMWQ!$LR$2:$LR$60=AM$1),0),$B10-1966)} -> 22247.34 | AN10: {=INDEX(GMWQ!$A$2:$LR$60,MATCH(1,(GMWQ!$LQ$2:$LQ$60=AN$3)*(GMWQ!$LP$2:$LP$60=AN$4)*(GMWQ!$LR$2:$LR$60=AN$1),0),$B10-1966)} -> 1950.44 | AO10: {=INDEX(GMWQ!$A$2:$LR$60,MATCH(1,(GMWQ!$LQ$2:$LQ$60=AO$3)*(GMWQ!$LP$2:$LP$60=AO$4)*(GMWQ!$LR$2:$LR$60=AO$1),0),$B10-1966)} -> 513.1444 | AP10: {=INDEX(GMWQ!$A$2:$LR$60,MATCH(1,(GMWQ!$LQ$2:$LQ$60=AP$3)*(GMWQ!$LP$2:$LP$60=AP$4)*(GMWQ!$LR$2:$LR$60=AP$1),0),$B10-1966)} -> -178.7535 | ... AU10: {=INDEX(GMWQ!$A$2:$LR$60,MATCH(1,(GMWQ!$LQ$2:$LQ$60=AU$3)*(GMWQ!$LP$2:$LP$60=AU$4)*(GMWQ!$LR$2:$LR$60=AU$1),0),$B10-1966)} -> 3556
A11: 1974 | B11: =+B10+1 -> 1977 | C11: {=INDEX(GMWQ!$A$2:$LR$60,MATCH(1,(GMWQ!$LQ$2:$LQ$60=C$3)*(GMWQ!$LP$2:$LP$60=C$4)*(GMWQ!$LR$2:$LR$60=C$1),0),$B11-1966)} -> 215122 | D11: {=INDEX(GMWQ!$A$2:$LR$60,MATCH(1,(GMWQ!$LQ$2:$LQ$60=D$3)*(GMWQ!$LP$2:$LP$60=D$4)*(GMWQ!$LR$2:$LR$60=D$1),0),$B11-1966)} -> 16.78086 | E11: {=INDEX(GMWQ!$A$2:$LR$60,MATCH(1,(GMWQ!$LQ$2:$LQ$60=E$3)*(GMWQ!$LP$2:$LP$60=E$4)*(GMWQ!$LR$2:$LR$60=E$1),0),$B11-1966)} -> 13.47771 | F11: {=INDEX(GMWQ!$A$2:$LR$60,MATCH(1,(GMWQ!$LQ$2:$LQ$60=F$3)*(GMWQ!$LP$2:$LP$60=F$4)*(GMWQ!$LR$2:$LR$60=F$1),0),$B11-1966)} -> 10596 | G11: {=INDEX(GMWQ!$A$2:$LR$60,MATCH(1,(GMWQ!$LQ$2:$LQ$60=G$3)*(GMWQ!$LP$2:$LP$60=G$4)*(GMWQ!$LR$2:$LR$60=G$1),0),$B11-1966)} -> 2131.439 | H11: {=INDEX(GMWQ!$A$2:$LR$60,MATCH(1,(GMWQ!$LQ$2:$LQ$60=H$3)*(GMWQ!$LP$2:$LP$60=H$4)*(GMWQ!$LR$2:$LR$60=H$1),0),$B11-1966)} -> 541.6524 | I11: {=INDEX(GMWQ!$A$2:$LR$60,MATCH(1,(GMWQ!$LQ$2:$LQ$60=I$3)*(GMWQ!$LP$2:$LP$60=I$4)*(GMWQ!$LR$2:$LR$60=I$1),0),$B11-1966)} -> 11.73601 | J11: {=INDEX(GMWQ!$A$2:$LR$60,MATCH(1,(GMWQ!$LQ$2:$LQ$60=J$3)*(GMWQ!$LP$2:$LP$60=J$4)*(GMWQ!$LR$2:$LR$60=J$1),0),$B11-1966)} -> 22211.17 | ... AG11: {=INDEX(GMWQ!$A$2:$LR$60,MATCH(1,(GMWQ!$LQ$2:$LQ$60=AG$3)*(GMWQ!$LP$2:$LP$60=AG$4)*(GMWQ!$LR$2:$LR$60=AG$1),0),$B11-1966)} -> -154.5488 | AI11: {=INDEX(GMWQ!$A$2:$LR$60,MATCH(1,(GMWQ!$LQ$2:$LQ$60=AI$3)*(GMWQ!$LP$2:$LP$60=AI$4)*(GMWQ!$LR$2:$LR$60=AI$1),0),$B11-1966)} -> 14267 | AJ11: {=INDEX(GMWQ!$A$2:$LR$60,MATCH(1,(GMWQ!$LQ$2:$LQ$60=AJ$3)*(GMWQ!$LP$2:$LP$60=AJ$4)*(GMWQ!$LR$2:$LR$60=AJ$1),0),$B11-1966)} -> 11.73601 | AK11: {=INDEX(GMWQ!$A$2:$LR$60,MATCH(1,(GMWQ!$LQ$2:$LQ$60=AK$3)*(GMWQ!$LP$2:$LP$60=AK$4)*(GMWQ!$LR$2:$LR$60=AK$1),0),$B11-1966)} -> 10596 | AL11: {=INDEX(GMWQ!$A$2:$LR$60,MATCH(1,(GMWQ!$LQ$2:$LQ$60=AL$3)*(GMWQ!$LP$2:$LP$60=AL$4)*(GMWQ!$LR$2:$LR$60=AL$1),0),$B11-1966)} -> 477.0573 | AM11: {=INDEX(GMWQ!$A$2:$LR$60,MATCH(1,(GMWQ!$LQ$2:$LQ$60=AM$3)*(GMWQ!$LP$2:$LP$60=AM$4)*(GMWQ!$LR$2:$LR$60=AM$1),0),$B11-1966)} -> 22211.17 | AN11: {=INDEX(GMWQ!$A$2:$LR$60,MATCH(1,(GMWQ!$LQ$2:$LQ$60=AN$3)*(GMWQ!$LP$2:$LP$60=AN$4)*(GMWQ!$LR$2:$LR$60=AN$1),0),$B11-1966)} -> 2131.439 | AO11: {=INDEX(GMWQ!$A$2:$LR$60,MATCH(1,(GMWQ!$LQ$2:$LQ$60=AO$3)*(GMWQ!$LP$2:$LP$60=AO$4)*(GMWQ!$LR$2:$LR$60=AO$1),0),$B11-1966)} -> 541.6524 | AP11: {=INDEX(GMWQ!$A$2:$LR$60,MATCH(1,(GMWQ!$LQ$2:$LQ$60=AP$3)*(GMWQ!$LP$2:$LP$60=AP$4)*(GMWQ!$LR$2:$LR$60=AP$1),0),$B11-1966)} -> -154.5488 | ... AU11: {=INDEX(GMWQ!$A$2:$LR$60,MATCH(1,(GMWQ!$LQ$2:$LQ$60=AU$3)*(GMWQ!$LP$2:$LP$60=AU$4)*(GMWQ!$LR$2:$LR$60=AU$1),0),$B11-1966)} -> 3577
B12: =+B11+1 -> 1978 | C12: {=INDEX(GMWQ!$A$2:$LR$60,MATCH(1,(GMWQ!$LQ$2:$LQ$60=C$3)*(GMWQ!$LP$2:$LP$60=C$4)*(GMWQ!$LR$2:$LR$60=C$1),0),$B12-1966)} -> 218215 | D12: {=INDEX(GMWQ!$A$2:$LR$60,MATCH(1,(GMWQ!$LQ$2:$LQ$60=D$3)*(GMWQ!$LP$2:$LP$60=D$4)*(GMWQ!$LR$2:$LR$60=D$1),0),$B12-1966)} -> 18.25341 | E12: {=INDEX(GMWQ!$A$2:$LR$60,MATCH(1,(GMWQ!$LQ$2:$LQ$60=E$3)*(GMWQ!$LP$2:$LP$60=E$4)*(GMWQ!$LR$2:$LR$60=E$1),0),$B12-1966)} -> 14.23371 | F12: {=INDEX(GMWQ!$A$2:$LR$60,MATCH(1,(GMWQ!$LQ$2:$LQ$60=F$3)*(GMWQ!$LP$2:$LP$60=F$4)*(GMWQ!$LR$2:$LR$60=F$1),0),$B12-1966)} -> 11121 | G12: {=INDEX(GMWQ!$A$2:$LR$60,MATCH(1,(GMWQ!$LQ$2:$LQ$60=G$3)*(GMWQ!$LP$2:$LP$60=G$4)*(GMWQ!$LR$2:$LR$60=G$1),0),$B12-1966)} -> 2461.787 | H12: {=INDEX(GMWQ!$A$2:$LR$60,MATCH(1,(GMWQ!$LQ$2:$LQ$60=H$3)*(GMWQ!$LP$2:$LP$60=H$4)*(GMWQ!$LR$2:$LR$60=H$1),0),$B12-1966)} -> 544.8199 | I12: {=INDEX(GMWQ!$A$2:$LR$60,MATCH(1,(GMWQ!$LQ$2:$LQ$60=I$3)*(GMWQ!$LP$2:$LP$60=I$4)*(GMWQ!$LR$2:$LR$60=I$1),0),$B12-1966)} -> 12.21319 | J12: {=INDEX(GMWQ!$A$2:$LR$60,MATCH(1,(GMWQ!$LQ$2:$LQ$60=J$3)*(GMWQ!$LP$2:$LP$60=J$4)*(GMWQ!$LR$2:$LR$60=J$1),0),$B12-1966)} -> 22296.23 | ... AG12: {=INDEX(GMWQ!$A$2:$LR$60,MATCH(1,(GMWQ!$LQ$2:$LQ$60=AG$3)*(GMWQ!$LP$2:$LP$60=AG$4)*(GMWQ!$LR$2:$LR$60=AG$1),0),$B12-1966)} -> -159.6465 | AI12: {=INDEX(GMWQ!$A$2:$LR$60,MATCH(1,(GMWQ!$LQ$2:$LQ$60=AI$3)*(GMWQ!$LP$2:$LP$60=AI$4)*(GMWQ!$LR$2:$LR$60=AI$1),0),$B12-1966)} -> 14694 | AJ12: {=INDEX(GMWQ!$A$2:$LR$60,MATCH(1,(GMWQ!$LQ$2:$LQ$60=AJ$3)*(GMWQ!$LP$2:$LP$60=AJ$4)*(GMWQ!$LR$2:$LR$60=AJ$1),0),$B12-1966)} -> 12.21319 | AK12: {=INDEX(GMWQ!$A$2:$LR$60,MATCH(1,(GMWQ!$LQ$2:$LQ$60=AK$3)*(GMWQ!$LP$2:$LP$60=AK$4)*(GMWQ!$LR$2:$LR$60=AK$1),0),$B12-1966)} -> 11121 | AL12: {=INDEX(GMWQ!$A$2:$LR$60,MATCH(1,(GMWQ!$LQ$2:$LQ$60=AL$3)*(GMWQ!$LP$2:$LP$60=AL$4)*(GMWQ!$LR$2:$LR$60=AL$1),0),$B12-1966)} -> 498.784 | AM12: {=INDEX(GMWQ!$A$2:$LR$60,MATCH(1,(GMWQ!$LQ$2:$LQ$60=AM$3)*(GMWQ!$LP$2:$LP$60=AM$4)*(GMWQ!$LR$2:$LR$60=AM$1),0),$B12-1966)} -> 22296.23 | AN12: {=INDEX(GMWQ!$A$2:$LR$60,MATCH(1,(GMWQ!$LQ$2:$LQ$60=AN$3)*(GMWQ!$LP$2:$LP$60=AN$4)*(GMWQ!$LR$2:$LR$60=AN$1),0),$B12-1966)} -> 2461.787 | AO12: {=INDEX(GMWQ!$A$2:$LR$60,MATCH(1,(GMWQ!$LQ$2:$LQ$60=AO$3)*(GMWQ!$LP$2:$LP$60=AO$4)*(GMWQ!$LR$2:$LR$60=AO$1),0),$B12-1966)} -> 544.8199 | AP12: {=INDEX(GMWQ!$A$2:$LR$60,MATCH(1,(GMWQ!$LQ$2:$LQ$60=AP$3)*(GMWQ!$LP$2:$LP$60=AP$4)*(GMWQ!$LR$2:$LR$60=AP$1),0),$B12-1966)} -> -159.6465 | ... AU12: {=INDEX(GMWQ!$A$2:$LR$60,MATCH(1,(GMWQ!$LQ$2:$LQ$60=AU$3)*(GMWQ!$LP$2:$LP$60=AU$4)*(GMWQ!$LR$2:$LR$60=AU$1),0),$B12-1966)} -> 3483
B13: =+B12+1 -> 1979 | C13: {=INDEX(GMWQ!$A$2:$LR$60,MATCH(1,(GMWQ!$LQ$2:$LQ$60=C$3)*(GMWQ!$LP$2:$LP$60=C$4)*(GMWQ!$LR$2:$LR$60=C$1),0),$B13-1966)} -> 219517 | D13: {=INDEX(GMWQ!$A$2:$LR$60,MATCH(1,(GMWQ!$LQ$2:$LQ$60=D$3)*(GMWQ!$LP$2:$LP$60=D$4)*(GMWQ!$LR$2:$LR$60=D$1),0),$B13-1966)} -> 20.2429 | E13: {=INDEX(GMWQ!$A$2:$LR$60,MATCH(1,(GMWQ!$LQ$2:$LQ$60=E$3)*(GMWQ!$LP$2:$LP$60=E$4)*(GMWQ!$LR$2:$LR$60=E$1),0),$B13-1966)} -> 14.57261 | F13: {=INDEX(GMWQ!$A$2:$LR$60,MATCH(1,(GMWQ!$LQ$2:$LQ$60=F$3)*(GMWQ!$LP$2:$LP$60=F$4)*(GMWQ!$LR$2:$LR$60=F$1),0),$B13-1966)} -> 12083 | G13: {=INDEX(GMWQ!$A$2:$LR$60,MATCH(1,(GMWQ!$LQ$2:$LQ$60=G$3)*(GMWQ!$LP$2:$LP$60=G$4)*(GMWQ!$LR$2:$LR$60=G$1),0),$B13-1966)} -> 2713.01 | H13: {=INDEX(GMWQ!$A$2:$LR$60,MATCH(1,(GMWQ!$LQ$2:$LQ$60=H$3)*(GMWQ!$LP$2:$LP$60=H$4)*(GMWQ!$LR$2:$LR$60=H$1),0),$B13-1966)} -> 594.4451 | I13: {=INDEX(GMWQ!$A$2:$LR$60,MATCH(1,(GMWQ!$LQ$2:$LQ$60=I$3)*(GMWQ!$LP$2:$LP$60=I$4)*(GMWQ!$LR$2:$LR$60=I$1),0),$B13-1966)} -> 12.76206 | J13: {=INDEX(GMWQ!$A$2:$LR$60,MATCH(1,(GMWQ!$LQ$2:$LQ$60=J$3)*(GMWQ!$LP$2:$LP$60=J$4)*(GMWQ!$LR$2:$LR$60=J$1),0),$B13-1966)} -> 22384.22 | ... AG13: {=INDEX(GMWQ!$A$2:$LR$60,MATCH(1,(GMWQ!$LQ$2:$LQ$60=AG$3)*(GMWQ!$LP$2:$LP$60=AG$4)*(GMWQ!$LR$2:$LR$60=AG$1),0),$B13-1966)} -> -184.5023 | AI13: {=INDEX(GMWQ!$A$2:$LR$60,MATCH(1,(GMWQ!$LQ$2:$LQ$60=AI$3)*(GMWQ!$LP$2:$LP$60=AI$4)*(GMWQ!$LR$2:$LR$60=AI$1),0),$B13-1966)} -> 15881 | AJ13: {=INDEX(GMWQ!$A$2:$LR$60,MATCH(1,(GMWQ!$LQ$2:$LQ$60=AJ$3)*(GMWQ!$LP$2:$LP$60=AJ$4)*(GMWQ!$LR$2:$LR$60=AJ$1),0),$B13-1966)} -> 12.76206 | AK13: {=INDEX(GMWQ!$A$2:$LR$60,MATCH(1,(GMWQ!$LQ$2:$LQ$60=AK$3)*(GMWQ!$LP$2:$LP$60=AK$4)*(GMWQ!$LR$2:$LR$60=AK$1),0),$B13-1966)} -> 12083 | AL13: {=INDEX(GMWQ!$A$2:$LR$60,MATCH(1,(GMWQ!$LQ$2:$LQ$60=AL$3)*(GMWQ!$LP$2:$LP$60=AL$4)*(GMWQ!$LR$2:$LR$60=AL$1),0),$B13-1966)} -> 539.7999 | AM13: {=INDEX(GMWQ!$A$2:$LR$60,MATCH(1,(GMWQ!$LQ$2:$LQ$60=AM$3)*(GMWQ!$LP$2:$LP$60=AM$4)*(GMWQ!$LR$2:$LR$60=AM$1),0),$B13-1966)} -> 22384.22 | AN13: {=INDEX(GMWQ!$A$2:$LR$60,MATCH(1,(GMWQ!$LQ$2:$LQ$60=AN$3)*(GMWQ!$LP$2:$LP$60=AN$4)*(GMWQ!$LR$2:$LR$60=AN$1),0),$B13-1966)} -> 2713.01 | AO13: {=INDEX(GMWQ!$A$2:$LR$60,MATCH(1,(GMWQ!$LQ$2:$LQ$60=AO$3)*(GMWQ!$LP$2:$LP$60=AO$4)*(GMWQ!$LR$2:$LR$60=AO$1),0),$B13-1966)} -> 594.4451 | AP13: {=INDEX(GMWQ!$A$2:$LR$60,MATCH(1,(GMWQ!$LQ$2:$LQ$60=AP$3)*(GMWQ!$LP$2:$LP$60=AP$4)*(GMWQ!$LR$2:$LR$60=AP$1),0),$B13-1966)} -> -184.5023 | ... AU13: {=INDEX(GMWQ!$A$2:$LR$60,MATCH(1,(GMWQ!$LQ$2:$LQ$60=AU$3)*(GMWQ!$LP$2:$LP$60=AU$4)*(GMWQ!$LR$2:$LR$60=AU$1),0),$B13-1966)} -> 3607
B14: =+B13+1 -> 1980 | C14: {=INDEX(GMWQ!$A$2:$LR$60,MATCH(1,(GMWQ!$LQ$2:$LQ$60=C$3)*(GMWQ!$LP$2:$LP$60=C$4)*(GMWQ!$LR$2:$LR$60=C$1),0),$B14-1966)} -> 216301 | D14: {=INDEX(GMWQ!$A$2:$LR$60,MATCH(1,(GMWQ!$LQ$2:$LQ$60=D$3)*(GMWQ!$LP$2:$LP$60=D$4)*(GMWQ!$LR$2:$LR$60=D$1),0),$B14-1966)} -> 21.92424 | E14: {=INDEX(GMWQ!$A$2:$LR$60,MATCH(1,(GMWQ!$LQ$2:$LQ$60=E$3)*(GMWQ!$LP$2:$LP$60=E$4)*(GMWQ!$LR$2:$LR$60=E$1),0),$B14-1966)} -> 15.2504 | F14: {=INDEX(GMWQ!$A$2:$LR$60,MATCH(1,(GMWQ!$LQ$2:$LQ$60=F$3)*(GMWQ!$LP$2:$LP$60=F$4)*(GMWQ!$LR$2:$LR$60=F$1),0),$B14-1966)} -> 12912 | G14: {=INDEX(GMWQ!$A$2:$LR$60,MATCH(1,(GMWQ!$LQ$2:$LQ$60=G$3)*(GMWQ!$LP$2:$LP$60=G$4)*(GMWQ!$LR$2:$LR$60=G$1),0),$B14-1966)} -> 2997.862 | H14: {=INDEX(GMWQ!$A$2:$LR$60,MATCH(1,(GMWQ!$LQ$2:$LQ$60=H$3)*(GMWQ!$LP$2:$LP$60=H$4)*(GMWQ!$LR$2:$LR$60=H$1),0),$B14-1966)} -> 651.4611 | I14: {=INDEX(GMWQ!$A$2:$LR$60,MATCH(1,(GMWQ!$LQ$2:$LQ$60=I$3)*(GMWQ!$LP$2:$LP$60=I$4)*(GMWQ!$LR$2:$LR$60=I$1),0),$B14-1966)} -> 13.47489 | J14: {=INDEX(GMWQ!$A$2:$LR$60,MATCH(1,(GMWQ!$LQ$2:$LQ$60=J$3)*(GMWQ!$LP$2:$LP$60=J$4)*(GMWQ!$LR$2:$LR$60=J$1),0),$B14-1966)} -> 22334.36 | ... AG14: {=INDEX(GMWQ!$A$2:$LR$60,MATCH(1,(GMWQ!$LQ$2:$LQ$60=AG$3)*(GMWQ!$LP$2:$LP$60=AG$4)*(GMWQ!$LR$2:$LR$60=AG$1),0),$B14-1966)} -> -221.5256 | AI14: {=INDEX(GMWQ!$A$2:$LR$60,MATCH(1,(GMWQ!$LQ$2:$LQ$60=AI$3)*(GMWQ!$LP$2:$LP$60=AI$4)*(GMWQ!$LR$2:$LR$60=AI$1),0),$B14-1966)} -> 16728 | AJ14: {=INDEX(GMWQ!$A$2:$LR$60,MATCH(1,(GMWQ!$LQ$2:$LQ$60=AJ$3)*(GMWQ!$LP$2:$LP$60=AJ$4)*(GMWQ!$LR$2:$LR$60=AJ$1),0),$B14-1966)} -> 13.47489 | AK14: {=INDEX(GMWQ!$A$2:$LR$60,MATCH(1,(GMWQ!$LQ$2:$LQ$60=AK$3)*(GMWQ!$LP$2:$LP$60=AK$4)*(GMWQ!$LR$2:$LR$60=AK$1),0),$B14-1966)} -> 12912 | AL14: {=INDEX(GMWQ!$A$2:$LR$60,MATCH(1,(GMWQ!$LQ$2:$LQ$60=AL$3)*(GMWQ!$LP$2:$LP$60=AL$4)*(GMWQ!$LR$2:$LR$60=AL$1),0),$B14-1966)} -> 578.1227 | AM14: {=INDEX(GMWQ!$A$2:$LR$60,MATCH(1,(GMWQ!$LQ$2:$LQ$60=AM$3)*(GMWQ!$LP$2:$LP$60=AM$4)*(GMWQ!$LR$2:$LR$60=AM$1),0),$B14-1966)} -> 22334.36 | AN14: {=INDEX(GMWQ!$A$2:$LR$60,MATCH(1,(GMWQ!$LQ$2:$LQ$60=AN$3)*(GMWQ!$LP$2:$LP$60=AN$4)*(GMWQ!$LR$2:$LR$60=AN$1),0),$B14-1966)} -> 2997.862 | AO14: {=INDEX(GMWQ!$A$2:$LR$60,MATCH(1,(GMWQ!$LQ$2:$LQ$60=AO$3)*(GMWQ!$LP$2:$LP$60=AO$4)*(GMWQ!$LR$2:$LR$60=AO$1),0),$B14-1966)} -> 651.4611 | AP14: {=INDEX(GMWQ!$A$2:$LR$60,MATCH(1,(GMWQ!$LQ$2:$LQ$60=AP$3)*(GMWQ!$LP$2:$LP$60=AP$4)*(GMWQ!$LR$2:$LR$60=AP$1),0),$B14-1966)} -> -221.5256 | ... AU14: {=INDEX(GMWQ!$A$2:$LR$60,MATCH(1,(GMWQ!$LQ$2:$LQ$60=AU$3)*(GMWQ!$LP$2:$LP$60=AU$4)*(GMWQ!$LR$2:$LR$60=AU$1),0),$B14-1966)} -> 3553
A15: 1975 | B15: =+B14+1 -> 1981 | C15: {=INDEX(GMWQ!$A$2:$LR$60,MATCH(1,(GMWQ!$LQ$2:$LQ$60=C$3)*(GMWQ!$LP$2:$LP$60=C$4)*(GMWQ!$LR$2:$LR$60=C$1),0),$B15-1966)} -> 216390 | D15: {=INDEX(GMWQ!$A$2:$LR$60,MATCH(1,(GMWQ!$LQ$2:$LQ$60=D$3)*(GMWQ!$LP$2:$LP$60=D$4)*(GMWQ!$LR$2:$LR$60=D$1),0),$B15-1966)} -> 23.39659 | E15: {=INDEX(GMWQ!$A$2:$LR$60,MATCH(1,(GMWQ!$LQ$2:$LQ$60=E$3)*(GMWQ!$LP$2:$LP$60=E$4)*(GMWQ!$LR$2:$LR$60=E$1),0),$B15-1966)} -> 16.05854 | F15: {=INDEX(GMWQ!$A$2:$LR$60,MATCH(1,(GMWQ!$LQ$2:$LQ$60=F$3)*(GMWQ!$LP$2:$LP$60=F$4)*(GMWQ!$LR$2:$LR$60=F$1),0),$B15-1966)} -> 14391 | G15: {=INDEX(GMWQ!$A$2:$LR$60,MATCH(1,(GMWQ!$LQ$2:$LQ$60=G$3)*(GMWQ!$LP$2:$LP$60=G$4)*(GMWQ!$LR$2:$LR$60=G$1),0),$B15-1966)} -> 3275.789 | H15: {=INDEX(GMWQ!$A$2:$LR$60,MATCH(1,(GMWQ!$LQ$2:$LQ$60=H$3)*(GMWQ!$LP$2:$LP$60=H$4)*(GMWQ!$LR$2:$LR$60=H$1),0),$B15-1966)} -> 693.6952 | I15: {=INDEX(GMWQ!$A$2:$LR$60,MATCH(1,(GMWQ!$LQ$2:$LQ$60=I$3)*(GMWQ!$LP$2:$LP$60=I$4)*(GMWQ!$LR$2:$LR$60=I$1),0),$B15-1966)} -> 14.38688 | J15: {=INDEX(GMWQ!$A$2:$LR$60,MATCH(1,(GMWQ!$LQ$2:$LQ$60=J$3)*(GMWQ!$LP$2:$LP$60=J$4)*(GMWQ!$LR$2:$LR$60=J$1),0),$B15-1966)} -> 22239.52 | ... AG15: {=INDEX(GMWQ!$A$2:$LR$60,MATCH(1,(GMWQ!$LQ$2:$LQ$60=AG$3)*(GMWQ!$LP$2:$LP$60=AG$4)*(GMWQ!$LR$2:$LR$60=AG$1),0),$B15-1966)} -> -126.2512 | AI15: {=INDEX(GMWQ!$A$2:$LR$60,MATCH(1,(GMWQ!$LQ$2:$LQ$60=AI$3)*(GMWQ!$LP$2:$LP$60=AI$4)*(GMWQ!$LR$2:$LR$60=AI$1),0),$B15-1966)} -> 18231 | AJ15: {=INDEX(GMWQ!$A$2:$LR$60,MATCH(1,(GMWQ!$LQ$2:$LQ$60=AJ$3)*(GMWQ!$LP$2:$LP$60=AJ$4)*(GMWQ!$LR$2:$LR$60=AJ$1),0),$B15-1966)} -> 14.38688 | AK15: {=INDEX(GMWQ!$A$2:$LR$60,MATCH(1,(GMWQ!$LQ$2:$LQ$60=AK$3)*(GMWQ!$LP$2:$LP$60=AK$4)*(GMWQ!$LR$2:$LR$60=AK$1),0),$B15-1966)} -> 14391 | AL15: {=INDEX(GMWQ!$A$2:$LR$60,MATCH(1,(GMWQ!$LQ$2:$LQ$60=AL$3)*(GMWQ!$LP$2:$LP$60=AL$4)*(GMWQ!$LR$2:$LR$60=AL$1),0),$B15-1966)} -> 647.0913 | AM15: {=INDEX(GMWQ!$A$2:$LR$60,MATCH(1,(GMWQ!$LQ$2:$LQ$60=AM$3)*(GMWQ!$LP$2:$LP$60=AM$4)*(GMWQ!$LR$2:$LR$60=AM$1),0),$B15-1966)} -> 22239.52 | AN15: {=INDEX(GMWQ!$A$2:$LR$60,MATCH(1,(GMWQ!$LQ$2:$LQ$60=AN$3)*(GMWQ!$LP$2:$LP$60=AN$4)*(GMWQ!$LR$2:$LR$60=AN$1),0),$B15-1966)} -> 3275.789 | AO15: {=INDEX(GMWQ!$A$2:$LR$60,MATCH(1,(GMWQ!$LQ$2:$LQ$60=AO$3)*(GMWQ!$LP$2:$LP$60=AO$4)*(GMWQ!$LR$2:$LR$60=AO$1),0),$B15-1966)} -> 693.6952 | AP15: {=INDEX(GMWQ!$A$2:$LR$60,MATCH(1,(GMWQ!$LQ$2:$LQ$60=AP$3)*(GMWQ!$LP$2:$LP$60=AP$4)*(GMWQ!$LR$2:$LR$60=AP$1),0),$B15-1966)} -> -126.2512 | ... AU15: {=INDEX(GMWQ!$A$2:$LR$60,MATCH(1,(GMWQ!$LQ$2:$LQ$60=AU$3)*(GMWQ!$LP$2:$LP$60=AU$4)*(GMWQ!$LR$2:$LR$60=AU$1),0),$B15-1966)} -> 3486
B16: =+B15+1 -> 1982 | C16: {=INDEX(GMWQ!$A$2:$LR$60,MATCH(1,(GMWQ!$LQ$2:$LQ$60=C$3)*(GMWQ!$LP$2:$LP$60=C$4)*(GMWQ!$LR$2:$LR$60=C$1),0),$B16-1966)} -> 212882 | D16: {=INDEX(GMWQ!$A$2:$LR$60,MATCH(1,(GMWQ!$LQ$2:$LQ$60=D$3)*(GMWQ!$LP$2:$LP$60=D$4)*(GMWQ!$LR$2:$LR$60=D$1),0),$B16-1966)} -> 24.96419 | E16: {=INDEX(GMWQ!$A$2:$LR$60,MATCH(1,(GMWQ!$LQ$2:$LQ$60=E$3)*(GMWQ!$LP$2:$LP$60=E$4)*(GMWQ!$LR$2:$LR$60=E$1),0),$B16-1966)} -> 17.46627 | F16: {=INDEX(GMWQ!$A$2:$LR$60,MATCH(1,(GMWQ!$LQ$2:$LQ$60=F$3)*(GMWQ!$LP$2:$LP$60=F$4)*(GMWQ!$LR$2:$LR$60=F$1),0),$B16-1966)} -> 14659 | G16: {=INDEX(GMWQ!$A$2:$LR$60,MATCH(1,(GMWQ!$LQ$2:$LQ$60=G$3)*(GMWQ!$LP$2:$LP$60=G$4)*(GMWQ!$LR$2:$LR$60=G$1),0),$B16-1966)} -> 3594.269 | H16: {=INDEX(GMWQ!$A$2:$LR$60,MATCH(1,(GMWQ!$LQ$2:$LQ$60=H$3)*(GMWQ!$LP$2:$LP$60=H$4)*(GMWQ!$LR$2:$LR$60=H$1),0),$B16-1966)} -> 713.7564 | I16: {=INDEX(GMWQ!$A$2:$LR$60,MATCH(1,(GMWQ!$LQ$2:$LQ$60=I$3)*(GMWQ!$LP$2:$LP$60=I$4)*(GMWQ!$LR$2:$LR$60=I$1),0),$B16-1966)} -> 15.16818 | J16: {=INDEX(GMWQ!$A$2:$LR$60,MATCH(1,(GMWQ!$LQ$2:$LQ$60=J$3)*(GMWQ!$LP$2:$LP$60=J$4)*(GMWQ!$LR$2:$LR$60=J$1),0),$B16-1966)} -> 22216.06 | ... AG16: {=INDEX(GMWQ!$A$2:$LR$60,MATCH(1,(GMWQ!$LQ$2:$LQ$60=AG$3)*(GMWQ!$LP$2:$LP$60=AG$4)*(GMWQ!$LR$2:$LR$60=AG$1),0),$B16-1966)} -> -125.7674 | AI16: {=INDEX(GMWQ!$A$2:$LR$60,MATCH(1,(GMWQ!$LQ$2:$LQ$60=AI$3)*(GMWQ!$LP$2:$LP$60=AI$4)*(GMWQ!$LR$2:$LR$60=AI$1),0),$B16-1966)} -> 18613 | AJ16: {=INDEX(GMWQ!$A$2:$LR$60,MATCH(1,(GMWQ!$LQ$2:$LQ$60=AJ$3)*(GMWQ!$LP$2:$LP$60=AJ$4)*(GMWQ!$LR$2:$LR$60=AJ$1),0),$B16-1966)} -> 15.16818 | AK16: {=INDEX(GMWQ!$A$2:$LR$60,MATCH(1,(GMWQ!$LQ$2:$LQ$60=AK$3)*(GMWQ!$LP$2:$LP$60=AK$4)*(GMWQ!$LR$2:$LR$60=AK$1),0),$B16-1966)} -> 14659 | AL16: {=INDEX(GMWQ!$A$2:$LR$60,MATCH(1,(GMWQ!$LQ$2:$LQ$60=AL$3)*(GMWQ!$LP$2:$LP$60=AL$4)*(GMWQ!$LR$2:$LR$60=AL$1),0),$B16-1966)} -> 659.8381 | AM16: {=INDEX(GMWQ!$A$2:$LR$60,MATCH(1,(GMWQ!$LQ$2:$LQ$60=AM$3)*(GMWQ!$LP$2:$LP$60=AM$4)*(GMWQ!$LR$2:$LR$60=AM$1),0),$B16-1966)} -> 22216.06 | AN16: {=INDEX(GMWQ!$A$2:$LR$60,MATCH(1,(GMWQ!$LQ$2:$LQ$60=AN$3)*(GMWQ!$LP$2:$LP$60=AN$4)*(GMWQ!$LR$2:$LR$60=AN$1),0),$B16-1966)} -> 3594.269 | AO16: {=INDEX(GMWQ!$A$2:$LR$60,MATCH(1,(GMWQ!$LQ$2:$LQ$60=AO$3)*(GMWQ!$LP$2:$LP$60=AO$4)*(GMWQ!$LR$2:$LR$60=AO$1),0),$B16-1966)} -> 713.7564 | AP16: {=INDEX(GMWQ!$A$2:$LR$60,MATCH(1,(GMWQ!$LQ$2:$LQ$60=AP$3)*(GMWQ!$LP$2:$LP$60=AP$4)*(GMWQ!$LR$2:$LR$60=AP$1),0),$B16-1966)} -> -125.7674 | ... AU16: {=INDEX(GMWQ!$A$2:$LR$60,MATCH(1,(GMWQ!$LQ$2:$LQ$60=AU$3)*(GMWQ!$LP$2:$LP$60=AU$4)*(GMWQ!$LR$2:$LR$60=AU$1),0),$B16-1966)} -> 3451
B17: =+B16+1 -> 1983 | C17: {=INDEX(GMWQ!$A$2:$LR$60,MATCH(1,(GMWQ!$LQ$2:$LQ$60=C$3)*(GMWQ!$LP$2:$LP$60=C$4)*(GMWQ!$LR$2:$LR$60=C$1),0),$B17-1966)} -> 212192 | D17: {=INDEX(GMWQ!$A$2:$LR$60,MATCH(1,(GMWQ!$LQ$2:$LQ$60=D$3)*(GMWQ!$LP$2:$LP$60=D$4)*(GMWQ!$LR$2:$LR$60=D$1),0),$B17-1966)} -> 27.02938 | E17: {=INDEX(GMWQ!$A$2:$LR$60,MATCH(1,(GMWQ!$LQ$2:$LQ$60=E$3)*(GMWQ!$LP$2:$LP$60=E$4)*(GMWQ!$LR$2:$LR$60=E$1),0),$B17-1966)} -> 18.22228 | F17: {=INDEX(GMWQ!$A$2:$LR$60,MATCH(1,(GMWQ!$LQ$2:$LQ$60=F$3)*(GMWQ!$LP$2:$LP$60=F$4)*(GMWQ!$LR$2:$LR$60=F$1),0),$B17-1966)} -> 15563 | G17: {=INDEX(GMWQ!$A$2:$LR$60,MATCH(1,(GMWQ!$LQ$2:$LQ$60=G$3)*(GMWQ!$LP$2:$LP$60=G$4)*(GMWQ!$LR$2:$LR$60=G$1),0),$B17-1966)} -> 3998.797 | H17: {=INDEX(GMWQ!$A$2:$LR$60,MATCH(1,(GMWQ!$LQ$2:$LQ$60=H$3)*(GMWQ!$LP$2:$LP$60=H$4)*(GMWQ!$LR$2:$LR$60=H$1),0),$B17-1966)} -> 752.8229 | I17: {=INDEX(GMWQ!$A$2:$LR$60,MATCH(1,(GMWQ!$LQ$2:$LQ$60=I$3)*(GMWQ!$LP$2:$LP$60=I$4)*(GMWQ!$LR$2:$LR$60=I$1),0),$B17-1966)} -> 15.7707 | J17: {=INDEX(GMWQ!$A$2:$LR$60,MATCH(1,(GMWQ!$LQ$2:$LQ$60=J$3)*(GMWQ!$LP$2:$LP$60=J$4)*(GMWQ!$LR$2:$LR$60=J$1),0),$B17-1966)} -> 22168.15 | ... AG17: {=INDEX(GMWQ!$A$2:$LR$60,MATCH(1,(GMWQ!$LQ$2:$LQ$60=AG$3)*(GMWQ!$LP$2:$LP$60=AG$4)*(GMWQ!$LR$2:$LR$60=AG$1),0),$B17-1966)} -> -168.8186 | AI17: {=INDEX(GMWQ!$A$2:$LR$60,MATCH(1,(GMWQ!$LQ$2:$LQ$60=AI$3)*(GMWQ!$LP$2:$LP$60=AI$4)*(GMWQ!$LR$2:$LR$60=AI$1),0),$B17-1966)} -> 19564 | AJ17: {=INDEX(GMWQ!$A$2:$LR$60,MATCH(1,(GMWQ!$LQ$2:$LQ$60=AJ$3)*(GMWQ!$LP$2:$LP$60=AJ$4)*(GMWQ!$LR$2:$LR$60=AJ$1),0),$B17-1966)} -> 15.7707 | AK17: {=INDEX(GMWQ!$A$2:$LR$60,MATCH(1,(GMWQ!$LQ$2:$LQ$60=AK$3)*(GMWQ!$LP$2:$LP$60=AK$4)*(GMWQ!$LR$2:$LR$60=AK$1),0),$B17-1966)} -> 15563 | AL17: {=INDEX(GMWQ!$A$2:$LR$60,MATCH(1,(GMWQ!$LQ$2:$LQ$60=AL$3)*(GMWQ!$LP$2:$LP$60=AL$4)*(GMWQ!$LR$2:$LR$60=AL$1),0),$B17-1966)} -> 702.0433 | AM17: {=INDEX(GMWQ!$A$2:$LR$60,MATCH(1,(GMWQ!$LQ$2:$LQ$60=AM$3)*(GMWQ!$LP$2:$LP$60=AM$4)*(GMWQ!$LR$2:$LR$60=AM$1),0),$B17-1966)} -> 22168.15 | AN17: {=INDEX(GMWQ!$A$2:$LR$60,MATCH(1,(GMWQ!$LQ$2:$LQ$60=AN$3)*(GMWQ!$LP$2:$LP$60=AN$4)*(GMWQ!$LR$2:$LR$60=AN$1),0),$B17-1966)} -> 3998.797 | AO17: {=INDEX(GMWQ!$A$2:$LR$60,MATCH(1,(GMWQ!$LQ$2:$LQ$60=AO$3)*(GMWQ!$LP$2:$LP$60=AO$4)*(GMWQ!$LR$2:$LR$60=AO$1),0),$B17-1966)} -> 752.8229 | AP17: {=INDEX(GMWQ!$A$2:$LR$60,MATCH(1,(GMWQ!$LQ$2:$LQ$60=AP$3)*(GMWQ!$LP$2:$LP$60=AP$4)*(GMWQ!$LR$2:$LR$60=AP$1),0),$B17-1966)} -> -168.8186 | ... AU17: {=INDEX(GMWQ!$A$2:$LR$60,MATCH(1,(GMWQ!$LQ$2:$LQ$60=AU$3)*(GMWQ!$LP$2:$LP$60=AU$4)*(GMWQ!$LR$2:$LR$60=AU$1),0),$B17-1966)} -> 3501
B18: =+B17+1 -> 1984 | C18: {=INDEX(GMWQ!$A$2:$LR$60,MATCH(1,(GMWQ!$LQ$2:$LQ$60=C$3)*(GMWQ!$LP$2:$LP$60=C$4)*(GMWQ!$LR$2:$LR$60=C$1),0),$B18-1966)} -> 214585 | D18: {=INDEX(GMWQ!$A$2:$LR$60,MATCH(1,(GMWQ!$LQ$2:$LQ$60=D$3)*(GMWQ!$LP$2:$LP$60=D$4)*(GMWQ!$LR$2:$LR$60=D$1),0),$B18-1966)} -> 28.37567 | E18: {=INDEX(GMWQ!$A$2:$LR$60,MATCH(1,(GMWQ!$LQ$2:$LQ$60=E$3)*(GMWQ!$LP$2:$LP$60=E$4)*(GMWQ!$LR$2:$LR$60=E$1),0),$B18-1966)} -> 18.84793 | F18: {=INDEX(GMWQ!$A$2:$LR$60,MATCH(1,(GMWQ!$LQ$2:$LQ$60=F$3)*(GMWQ!$LP$2:$LP$60=F$4)*(GMWQ!$LR$2:$LR$60=F$1),0),$B18-1966)} -> 15848 | G18: {=INDEX(GMWQ!$A$2:$LR$60,MATCH(1,(GMWQ!$LQ$2:$LQ$60=G$3)*(GMWQ!$LP$2:$LP$60=G$4)*(GMWQ!$LR$2:$LR$60=G$1),0),$B18-1966)} -> 4008.688 | H18: {=INDEX(GMWQ!$A$2:$LR$60,MATCH(1,(GMWQ!$LQ$2:$LQ$60=H$3)*(GMWQ!$LP$2:$LP$60=H$4)*(GMWQ!$LR$2:$LR$60=H$1),0),$B18-1966)} -> 774.9958 | I18: {=INDEX(GMWQ!$A$2:$LR$60,MATCH(1,(GMWQ!$LQ$2:$LQ$60=I$3)*(GMWQ!$LP$2:$LP$60=I$4)*(GMWQ!$LR$2:$LR$60=I$1),0),$B18-1966)} -> 16.59767 | J18: {=INDEX(GMWQ!$A$2:$LR$60,MATCH(1,(GMWQ!$LQ$2:$LQ$60=J$3)*(GMWQ!$LP$2:$LP$60=J$4)*(GMWQ!$LR$2:$LR$60=J$1),0),$B18-1966)} -> 22108.51 | ... AG18: {=INDEX(GMWQ!$A$2:$LR$60,MATCH(1,(GMWQ!$LQ$2:$LQ$60=AG$3)*(GMWQ!$LP$2:$LP$60=AG$4)*(GMWQ!$LR$2:$LR$60=AG$1),0),$B18-1966)} -> -178.3814 | AI18: {=INDEX(GMWQ!$A$2:$LR$60,MATCH(1,(GMWQ!$LQ$2:$LQ$60=AI$3)*(GMWQ!$LP$2:$LP$60=AI$4)*(GMWQ!$LR$2:$LR$60=AI$1),0),$B18-1966)} -> 20194 | AJ18: {=INDEX(GMWQ!$A$2:$LR$60,MATCH(1,(GMWQ!$LQ$2:$LQ$60=AJ$3)*(GMWQ!$LP$2:$LP$60=AJ$4)*(GMWQ!$LR$2:$LR$60=AJ$1),0),$B18-1966)} -> 16.59767 | AK18: {=INDEX(GMWQ!$A$2:$LR$60,MATCH(1,(GMWQ!$LQ$2:$LQ$60=AK$3)*(GMWQ!$LP$2:$LP$60=AK$4)*(GMWQ!$LR$2:$LR$60=AK$1),0),$B18-1966)} -> 15848 | AL18: {=INDEX(GMWQ!$A$2:$LR$60,MATCH(1,(GMWQ!$LQ$2:$LQ$60=AL$3)*(GMWQ!$LP$2:$LP$60=AL$4)*(GMWQ!$LR$2:$LR$60=AL$1),0),$B18-1966)} -> 716.8281 | AM18: {=INDEX(GMWQ!$A$2:$LR$60,MATCH(1,(GMWQ!$LQ$2:$LQ$60=AM$3)*(GMWQ!$LP$2:$LP$60=AM$4)*(GMWQ!$LR$2:$LR$60=AM$1),0),$B18-1966)} -> 22108.51 | AN18: {=INDEX(GMWQ!$A$2:$LR$60,MATCH(1,(GMWQ!$LQ$2:$LQ$60=AN$3)*(GMWQ!$LP$2:$LP$60=AN$4)*(GMWQ!$LR$2:$LR$60=AN$1),0),$B18-1966)} -> 4008.688 | AO18: {=INDEX(GMWQ!$A$2:$LR$60,MATCH(1,(GMWQ!$LQ$2:$LQ$60=AO$3)*(GMWQ!$LP$2:$LP$60=AO$4)*(GMWQ!$LR$2:$LR$60=AO$1),0),$B18-1966)} -> 774.9958 | AP18: {=INDEX(GMWQ!$A$2:$LR$60,MATCH(1,(GMWQ!$LQ$2:$LQ$60=AP$3)*(GMWQ!$LP$2:$LP$60=AP$4)*(GMWQ!$LR$2:$LR$60=AP$1),0),$B18-1966)} -> -178.3814 | ... AU18: {=INDEX(GMWQ!$A$2:$LR$60,MATCH(1,(GMWQ!$LQ$2:$LQ$60=AU$3)*(GMWQ!$LP$2:$LP$60=AU$4)*(GMWQ!$LR$2:$LR$60=AU$1),0),$B18-1966)} -> 3533
A19: 1976 | B19: =+B18+1 -> 1985 | C19: {=INDEX(GMWQ!$A$2:$LR$60,MATCH(1,(GMWQ!$LQ$2:$LQ$60=C$3)*(GMWQ!$LP$2:$LP$60=C$4)*(GMWQ!$LR$2:$LR$60=C$1),0),$B19-1966)} -> 218180 | D19: {=INDEX(GMWQ!$A$2:$LR$60,MATCH(1,(GMWQ!$LQ$2:$LQ$60=D$3)*(GMWQ!$LP$2:$LP$60=D$4)*(GMWQ!$LR$2:$LR$60=D$1),0),$B19-1966)} -> 29.35714 | E19: {=INDEX(GMWQ!$A$2:$LR$60,MATCH(1,(GMWQ!$LQ$2:$LQ$60=E$3)*(GMWQ!$LP$2:$LP$60=E$4)*(GMWQ!$LR$2:$LR$60=E$1),0),$B19-1966)} -> 19.42145 | F19: {=INDEX(GMWQ!$A$2:$LR$60,MATCH(1,(GMWQ!$LQ$2:$LQ$60=F$3)*(GMWQ!$LP$2:$LP$60=F$4)*(GMWQ!$LR$2:$LR$60=F$1),0),$B19-1966)} -> 16278 | G19: {=INDEX(GMWQ!$A$2:$LR$60,MATCH(1,(GMWQ!$LQ$2:$LQ$60=G$3)*(GMWQ!$LP$2:$LP$60=G$4)*(GMWQ!$LR$2:$LR$60=G$1),0),$B19-1966)} -> 4188.698 | H19: {=INDEX(GMWQ!$A$2:$LR$60,MATCH(1,(GMWQ!$LQ$2:$LQ$60=H$3)*(GMWQ!$LP$2:$LP$60=H$4)*(GMWQ!$LR$2:$LR$60=H$1),0),$B19-1966)} -> 767.6049 | I19: {=INDEX(GMWQ!$A$2:$LR$60,MATCH(1,(GMWQ!$LQ$2:$LQ$60=I$3)*(GMWQ!$LP$2:$LP$60=I$4)*(GMWQ!$LR$2:$LR$60=I$1),0),$B19-1966)} -> 17.22878 | J19: {=INDEX(GMWQ!$A$2:$LR$60,MATCH(1,(GMWQ!$LQ$2:$LQ$60=J$3)*(GMWQ!$LP$2:$LP$60=J$4)*(GMWQ!$LR$2:$LR$60=J$1),0),$B19-1966)} -> 22054.74 | ... AG19: {=INDEX(GMWQ!$A$2:$LR$60,MATCH(1,(GMWQ!$LQ$2:$LQ$60=AG$3)*(GMWQ!$LP$2:$LP$60=AG$4)*(GMWQ!$LR$2:$LR$60=AG$1),0),$B19-1966)} -> -181.1721 | AI19: {=INDEX(GMWQ!$A$2:$LR$60,MATCH(1,(GMWQ!$LQ$2:$LQ$60=AI$3)*(GMWQ!$LP$2:$LP$60=AI$4)*(GMWQ!$LR$2:$LR$60=AI$1),0),$B19-1966)} -> 21295 | AJ19: {=INDEX(GMWQ!$A$2:$LR$60,MATCH(1,(GMWQ!$LQ$2:$LQ$60=AJ$3)*(GMWQ!$LP$2:$LP$60=AJ$4)*(GMWQ!$LR$2:$LR$60=AJ$1),0),$B19-1966)} -> 17.22878 | AK19: {=INDEX(GMWQ!$A$2:$LR$60,MATCH(1,(GMWQ!$LQ$2:$LQ$60=AK$3)*(GMWQ!$LP$2:$LP$60=AK$4)*(GMWQ!$LR$2:$LR$60=AK$1),0),$B19-1966)} -> 16278 | AL19: {=INDEX(GMWQ!$A$2:$LR$60,MATCH(1,(GMWQ!$LQ$2:$LQ$60=AL$3)*(GMWQ!$LP$2:$LP$60=AL$4)*(GMWQ!$LR$2:$LR$60=AL$1),0),$B19-1966)} -> 738.0728 | AM19: {=INDEX(GMWQ!$A$2:$LR$60,MATCH(1,(GMWQ!$LQ$2:$LQ$60=AM$3)*(GMWQ!$LP$2:$LP$60=AM$4)*(GMWQ!$LR$2:$LR$60=AM$1),0),$B19-1966)} -> 22054.74 | AN19: {=INDEX(GMWQ!$A$2:$LR$60,MATCH(1,(GMWQ!$LQ$2:$LQ$60=AN$3)*(GMWQ!$LP$2:$LP$60=AN$4)*(GMWQ!$LR$2:$LR$60=AN$1),0),$B19-1966)} -> 4188.698 | AO19: {=INDEX(GMWQ!$A$2:$LR$60,MATCH(1,(GMWQ!$LQ$2:$LQ$60=AO$3)*(GMWQ!$LP$2:$LP$60=AO$4)*(GMWQ!$LR$2:$LR$60=AO$1),0),$B19-1966)} -> 767.6049 | AP19: {=INDEX(GMWQ!$A$2:$LR$60,MATCH(1,(GMWQ!$LQ$2:$LQ$60=AP$3)*(GMWQ!$LP$2:$LP$60=AP$4)*(GMWQ!$LR$2:$LR$60=AP$1),0),$B19-1966)} -> -181.1721 | ... AU19: {=INDEX(GMWQ!$A$2:$LR$60,MATCH(1,(GMWQ!$LQ$2:$LQ$60=AU$3)*(GMWQ!$LP$2:$LP$60=AU$4)*(GMWQ!$LR$2:$LR$60=AU$1),0),$B19-1966)} -> 3515
B20: =+B19+1 -> 1986 | C20: {=INDEX(GMWQ!$A$2:$LR$60,MATCH(1,(GMWQ!$LQ$2:$LQ$60=C$3)*(GMWQ!$LP$2:$LP$60=C$4)*(GMWQ!$LR$2:$LR$60=C$1),0),$B20-1966)} -> 217883 | D20: {=INDEX(GMWQ!$A$2:$LR$60,MATCH(1,(GMWQ!$LQ$2:$LQ$60=D$3)*(GMWQ!$LP$2:$LP$60=D$4)*(GMWQ!$LR$2:$LR$60=D$1),0),$B20-1966)} -> 30.79358 | E20: {=INDEX(GMWQ!$A$2:$LR$60,MATCH(1,(GMWQ!$LQ$2:$LQ$60=E$3)*(GMWQ!$LP$2:$LP$60=E$4)*(GMWQ!$LR$2:$LR$60=E$1),0),$B20-1966)} -> 20.12532 | F20: {=INDEX(GMWQ!$A$2:$LR$60,MATCH(1,(GMWQ!$LQ$2:$LQ$60=F$3)*(GMWQ!$LP$2:$LP$60=F$4)*(GMWQ!$LR$2:$LR$60=F$1),0),$B20-1966)} -> 16723 | G20: {=INDEX(GMWQ!$A$2:$LR$60,MATCH(1,(GMWQ!$LQ$2:$LQ$60=G$3)*(GMWQ!$LP$2:$LP$60=G$4)*(GMWQ!$LR$2:$LR$60=G$1),0),$B20-1966)} -> 4475.527 | H20: {=INDEX(GMWQ!$A$2:$LR$60,MATCH(1,(GMWQ!$LQ$2:$LQ$60=H$3)*(GMWQ!$LP$2:$LP$60=H$4)*(GMWQ!$LR$2:$LR$60=H$1),0),$B20-1966)} -> 895.363 | I20: {=INDEX(GMWQ!$A$2:$LR$60,MATCH(1,(GMWQ!$LQ$2:$LQ$60=I$3)*(GMWQ!$LP$2:$LP$60=I$4)*(GMWQ!$LR$2:$LR$60=I$1),0),$B20-1966)} -> 17.65541 | J20: {=INDEX(GMWQ!$A$2:$LR$60,MATCH(1,(GMWQ!$LQ$2:$LQ$60=J$3)*(GMWQ!$LP$2:$LP$60=J$4)*(GMWQ!$LR$2:$LR$60=J$1),0),$B20-1966)} -> 22034.21 | ... AG20: {=INDEX(GMWQ!$A$2:$LR$60,MATCH(1,(GMWQ!$LQ$2:$LQ$60=AG$3)*(GMWQ!$LP$2:$LP$60=AG$4)*(GMWQ!$LR$2:$LR$60=AG$1),0),$B20-1966)} -> -112.8186 | AI20: {=INDEX(GMWQ!$A$2:$LR$60,MATCH(1,(GMWQ!$LQ$2:$LQ$60=AI$3)*(GMWQ!$LP$2:$LP$60=AI$4)*(GMWQ!$LR$2:$LR$60=AI$1),0),$B20-1966)} -> 21568 | AJ20: {=INDEX(GMWQ!$A$2:$LR$60,MATCH(1,(GMWQ!$LQ$2:$LQ$60=AJ$3)*(GMWQ!$LP$2:$LP$60=AJ$4)*(GMWQ!$LR$2:$LR$60=AJ$1),0),$B20-1966)} -> 17.65541 | AK20: {=INDEX(GMWQ!$A$2:$LR$60,MATCH(1,(GMWQ!$LQ$2:$LQ$60=AK$3)*(GMWQ!$LP$2:$LP$60=AK$4)*(GMWQ!$LR$2:$LR$60=AK$1),0),$B20-1966)} -> 16723 | AL20: {=INDEX(GMWQ!$A$2:$LR$60,MATCH(1,(GMWQ!$LQ$2:$LQ$60=AL$3)*(GMWQ!$LP$2:$LP$60=AL$4)*(GMWQ!$LR$2:$LR$60=AL$1),0),$B20-1966)} -> 758.9564 | AM20: {=INDEX(GMWQ!$A$2:$LR$60,MATCH(1,(GMWQ!$LQ$2:$LQ$60=AM$3)*(GMWQ!$LP$2:$LP$60=AM$4)*(GMWQ!$LR$2:$LR$60=AM$1),0),$B20-1966)} -> 22034.21 | AN20: {=INDEX(GMWQ!$A$2:$LR$60,MATCH(1,(GMWQ!$LQ$2:$LQ$60=AN$3)*(GMWQ!$LP$2:$LP$60=AN$4)*(GMWQ!$LR$2:$LR$60=AN$1),0),$B20-1966)} -> 4475.527 | AO20: {=INDEX(GMWQ!$A$2:$LR$60,MATCH(1,(GMWQ!$LQ$2:$LQ$60=AO$3)*(GMWQ!$LP$2:$LP$60=AO$4)*(GMWQ!$LR$2:$LR$60=AO$1),0),$B20-1966)} -> 895.363 | AP20: {=INDEX(GMWQ!$A$2:$LR$60,MATCH(1,(GMWQ!$LQ$2:$LQ$60=AP$3)*(GMWQ!$LP$2:$LP$60=AP$4)*(GMWQ!$LR$2:$LR$60=AP$1),0),$B20-1966)} -> -112.8186 | ... AU20: {=INDEX(GMWQ!$A$2:$LR$60,MATCH(1,(GMWQ!$LQ$2:$LQ$60=AU$3)*(GMWQ!$LP$2:$LP$60=AU$4)*(GMWQ!$LR$2:$LR$60=AU$1),0),$B20-1966)} -> 3538
B21: =+B20+1 -> 1987 | C21: {=INDEX(GMWQ!$A$2:$LR$60,MATCH(1,(GMWQ!$LQ$2:$LQ$60=C$3)*(GMWQ!$LP$2:$LP$60=C$4)*(GMWQ!$LR$2:$LR$60=C$1),0),$B21-1966)} -> 220587 | D21: {=INDEX(GMWQ!$A$2:$LR$60,MATCH(1,(GMWQ!$LQ$2:$LQ$60=D$3)*(GMWQ!$LP$2:$LP$60=D$4)*(GMWQ!$LR$2:$LR$60=D$1),0),$B21-1966)} -> 32.30147 | E21: {=INDEX(GMWQ!$A$2:$LR$60,MATCH(1,(GMWQ!$LQ$2:$LQ$60=E$3)*(GMWQ!$LP$2:$LP$60=E$4)*(GMWQ!$LR$2:$LR$60=E$1),0),$B21-1966)} -> 20.59456 | F21: {=INDEX(GMWQ!$A$2:$LR$60,MATCH(1,(GMWQ!$LQ$2:$LQ$60=F$3)*(GMWQ!$LP$2:$LP$60=F$4)*(GMWQ!$LR$2:$LR$60=F$1),0),$B21-1966)} -> 17202 | G21: {=INDEX(GMWQ!$A$2:$LR$60,MATCH(1,(GMWQ!$LQ$2:$LQ$60=G$3)*(GMWQ!$LP$2:$LP$60=G$4)*(GMWQ!$LR$2:$LR$60=G$1),0),$B21-1966)} -> 4155.07 | H21: {=INDEX(GMWQ!$A$2:$LR$60,MATCH(1,(GMWQ!$LQ$2:$LQ$60=H$3)*(GMWQ!$LP$2:$LP$60=H$4)*(GMWQ!$LR$2:$LR$60=H$1),0),$B21-1966)} -> 928.0945 | I21: {=INDEX(GMWQ!$A$2:$LR$60,MATCH(1,(GMWQ!$LQ$2:$LQ$60=I$3)*(GMWQ!$LP$2:$LP$60=I$4)*(GMWQ!$LR$2:$LR$60=I$1),0),$B21-1966)} -> 18.13524 | J21: {=INDEX(GMWQ!$A$2:$LR$60,MATCH(1,(GMWQ!$LQ$2:$LQ$60=J$3)*(GMWQ!$LP$2:$LP$60=J$4)*(GMWQ!$LR$2:$LR$60=J$1),0),$B21-1966)} -> 22052.78 | ... AG21: {=INDEX(GMWQ!$A$2:$LR$60,MATCH(1,(GMWQ!$LQ$2:$LQ$60=AG$3)*(GMWQ!$LP$2:$LP$60=AG$4)*(GMWQ!$LR$2:$LR$60=AG$1),0),$B21-1966)} -> -186.0837 | AI21: {=INDEX(GMWQ!$A$2:$LR$60,MATCH(1,(GMWQ!$LQ$2:$LQ$60=AI$3)*(GMWQ!$LP$2:$LP$60=AI$4)*(GMWQ!$LR$2:$LR$60=AI$1),0),$B21-1966)} -> 22876 | AJ21: {=INDEX(GMWQ!$A$2:$LR$60,MATCH(1,(GMWQ!$LQ$2:$LQ$60=AJ$3)*(GMWQ!$LP$2:$LP$60=AJ$4)*(GMWQ!$LR$2:$LR$60=AJ$1),0),$B21-1966)} -> 18.13524 | AK21: {=INDEX(GMWQ!$A$2:$LR$60,MATCH(1,(GMWQ!$LQ$2:$LQ$60=AK$3)*(GMWQ!$LP$2:$LP$60=AK$4)*(GMWQ!$LR$2:$LR$60=AK$1),0),$B21-1966)} -> 17202 | AL21: {=INDEX(GMWQ!$A$2:$LR$60,MATCH(1,(GMWQ!$LQ$2:$LQ$60=AL$3)*(GMWQ!$LP$2:$LP$60=AL$4)*(GMWQ!$LR$2:$LR$60=AL$1),0),$B21-1966)} -> 780.0377 | AM21: {=INDEX(GMWQ!$A$2:$LR$60,MATCH(1,(GMWQ!$LQ$2:$LQ$60=AM$3)*(GMWQ!$LP$2:$LP$60=AM$4)*(GMWQ!$LR$2:$LR$60=AM$1),0),$B21-1966)} -> 22052.78 | AN21: {=INDEX(GMWQ!$A$2:$LR$60,MATCH(1,(GMWQ!$LQ$2:$LQ$60=AN$3)*(GMWQ!$LP$2:$LP$60=AN$4)*(GMWQ!$LR$2:$LR$60=AN$1),0),$B21-1966)} -> 4155.07 | AO21: {=INDEX(GMWQ!$A$2:$LR$60,MATCH(1,(GMWQ!$LQ$2:$LQ$60=AO$3)*(GMWQ!$LP$2:$LP$60=AO$4)*(GMWQ!$LR$2:$LR$60=AO$1),0),$B21-1966)} -> 928.0945 | AP21: {=INDEX(GMWQ!$A$2:$LR$60,MATCH(1,(GMWQ!$LQ$2:$LQ$60=AP$3)*(GMWQ!$LP$2:$LP$60=AP$4)*(GMWQ!$LR$2:$LR$60=AP$1),0),$B21-1966)} -> -186.0837 | ... AU21: {=INDEX(GMWQ!$A$2:$LR$60,MATCH(1,(GMWQ!$LQ$2:$LQ$60=AU$3)*(GMWQ!$LP$2:$LP$60=AU$4)*(GMWQ!$LR$2:$LR$60=AU$1),0),$B21-1966)} -> 3516
B22: =+B21+1 -> 1988 | C22: {=INDEX(GMWQ!$A$2:$LR$60,MATCH(1,(GMWQ!$LQ$2:$LQ$60=C$3)*(GMWQ!$LP$2:$LP$60=C$4)*(GMWQ!$LR$2:$LR$60=C$1),0),$B22-1966)} -> 225228 | D22: {=INDEX(GMWQ!$A$2:$LR$60,MATCH(1,(GMWQ!$LQ$2:$LQ$60=D$3)*(GMWQ!$LP$2:$LP$60=D$4)*(GMWQ!$LR$2:$LR$60=D$1),0),$B22-1966)} -> 33.18535 | E22: {=INDEX(GMWQ!$A$2:$LR$60,MATCH(1,(GMWQ!$LQ$2:$LQ$60=E$3)*(GMWQ!$LP$2:$LP$60=E$4)*(GMWQ!$LR$2:$LR$60=E$1),0),$B22-1966)} -> 21.50698 | F22: {=INDEX(GMWQ!$A$2:$LR$60,MATCH(1,(GMWQ!$LQ$2:$LQ$60=F$3)*(GMWQ!$LP$2:$LP$60=F$4)*(GMWQ!$LR$2:$LR$60=F$1),0),$B22-1966)} -> 17685 | G22: {=INDEX(GMWQ!$A$2:$LR$60,MATCH(1,(GMWQ!$LQ$2:$LQ$60=G$3)*(GMWQ!$LP$2:$LP$60=G$4)*(GMWQ!$LR$2:$LR$60=G$1),0),$B22-1966)} -> 4412.227 | H22: {=INDEX(GMWQ!$A$2:$LR$60,MATCH(1,(GMWQ!$LQ$2:$LQ$60=H$3)*(GMWQ!$LP$2:$LP$60=H$4)*(GMWQ!$LR$2:$LR$60=H$1),0),$B22-1966)} -> 953.4349 | I22: {=INDEX(GMWQ!$A$2:$LR$60,MATCH(1,(GMWQ!$LQ$2:$LQ$60=I$3)*(GMWQ!$LP$2:$LP$60=I$4)*(GMWQ!$LR$2:$LR$60=I$1),0),$B22-1966)} -> 19.08728 | J22: {=INDEX(GMWQ!$A$2:$LR$60,MATCH(1,(GMWQ!$LQ$2:$LQ$60=J$3)*(GMWQ!$LP$2:$LP$60=J$4)*(GMWQ!$LR$2:$LR$60=J$1),0),$B22-1966)} -> 22081.13 | ... AG22: {=INDEX(GMWQ!$A$2:$LR$60,MATCH(1,(GMWQ!$LQ$2:$LQ$60=AG$3)*(GMWQ!$LP$2:$LP$60=AG$4)*(GMWQ!$LR$2:$LR$60=AG$1),0),$B22-1966)} -> -245.2465 | AI22: {=INDEX(GMWQ!$A$2:$LR$60,MATCH(1,(GMWQ!$LQ$2:$LQ$60=AI$3)*(GMWQ!$LP$2:$LP$60=AI$4)*(GMWQ!$LR$2:$LR$60=AI$1),0),$B22-1966)} -> 23450 | AJ22: {=INDEX(GMWQ!$A$2:$LR$60,MATCH(1,(GMWQ!$LQ$2:$LQ$60=AJ$3)*(GMWQ!$LP$2:$LP$60=AJ$4)*(GMWQ!$LR$2:$LR$60=AJ$1),0),$B22-1966)} -> 19.08728 | AK22: {=INDEX(GMWQ!$A$2:$LR$60,MATCH(1,(GMWQ!$LQ$2:$LQ$60=AK$3)*(GMWQ!$LP$2:$LP$60=AK$4)*(GMWQ!$LR$2:$LR$60=AK$1),0),$B22-1966)} -> 17685 | AL22: {=INDEX(GMWQ!$A$2:$LR$60,MATCH(1,(GMWQ!$LQ$2:$LQ$60=AL$3)*(GMWQ!$LP$2:$LP$60=AL$4)*(GMWQ!$LR$2:$LR$60=AL$1),0),$B22-1966)} -> 800.9099 | AM22: {=INDEX(GMWQ!$A$2:$LR$60,MATCH(1,(GMWQ!$LQ$2:$LQ$60=AM$3)*(GMWQ!$LP$2:$LP$60=AM$4)*(GMWQ!$LR$2:$LR$60=AM$1),0),$B22-1966)} -> 22081.13 | AN22: {=INDEX(GMWQ!$A$2:$LR$60,MATCH(1,(GMWQ!$LQ$2:$LQ$60=AN$3)*(GMWQ!$LP$2:$LP$60=AN$4)*(GMWQ!$LR$2:$LR$60=AN$1),0),$B22-1966)} -> 4412.227 | AO22: {=INDEX(GMWQ!$A$2:$LR$60,MATCH(1,(GMWQ!$LQ$2:$LQ$60=AO$3)*(GMWQ!$LP$2:$LP$60=AO$4)*(GMWQ!$LR$2:$LR$60=AO$1),0),$B22-1966)} -> 953.4349 | AP22: {=INDEX(GMWQ!$A$2:$LR$60,MATCH(1,(GMWQ!$LQ$2:$LQ$60=AP$3)*(GMWQ!$LP$2:$LP$60=AP$4)*(GMWQ!$LR$2:$LR$60=AP$1),0),$B22-1966)} -> -245.2465 | ... AU22: {=INDEX(GMWQ!$A$2:$LR$60,MATCH(1,(GMWQ!$LQ$2:$LQ$60=AU$3)*(GMWQ!$LP$2:$LP$60=AU$4)*(GMWQ!$LR$2:$LR$60=AU$1),0),$B22-1966)} -> 3507
A23: 1977 | B23: =+B22+1 -> 1989 | C23: {=INDEX(GMWQ!$A$2:$LR$60,MATCH(1,(GMWQ!$LQ$2:$LQ$60=C$3)*(GMWQ!$LP$2:$LP$60=C$4)*(GMWQ!$LR$2:$LR$60=C$1),0),$B23-1966)} -> 225362 | D23: {=INDEX(GMWQ!$A$2:$LR$60,MATCH(1,(GMWQ!$LQ$2:$LQ$60=D$3)*(GMWQ!$LP$2:$LP$60=D$4)*(GMWQ!$LR$2:$LR$60=D$1),0),$B23-1966)} -> 33.54049 | E23: {=INDEX(GMWQ!$A$2:$LR$60,MATCH(1,(GMWQ!$LQ$2:$LQ$60=E$3)*(GMWQ!$LP$2:$LP$60=E$4)*(GMWQ!$LR$2:$LR$60=E$1),0),$B23-1966)} -> 22.47153 | F23: {=INDEX(GMWQ!$A$2:$LR$60,MATCH(1,(GMWQ!$LQ$2:$LQ$60=F$3)*(GMWQ!$LP$2:$LP$60=F$4)*(GMWQ!$LR$2:$LR$60=F$1),0),$B23-1966)} -> 18192 | G23: {=INDEX(GMWQ!$A$2:$LR$60,MATCH(1,(GMWQ!$LQ$2:$LQ$60=G$3)*(GMWQ!$LP$2:$LP$60=G$4)*(GMWQ!$LR$2:$LR$60=G$1),0),$B23-1966)} -> 4594.215 | H23: {=INDEX(GMWQ!$A$2:$LR$60,MATCH(1,(GMWQ!$LQ$2:$LQ$60=H$3)*(GMWQ!$LP$2:$LP$60=H$4)*(GMWQ!$LR$2:$LR$60=H$1),0),$B23-1966)} -> 958.7142 | I23: {=INDEX(GMWQ!$A$2:$LR$60,MATCH(1,(GMWQ!$LQ$2:$LQ$60=I$3)*(GMWQ!$LP$2:$LP$60=I$4)*(GMWQ!$LR$2:$LR$60=I$1),0),$B23-1966)} -> 19.9885 | J23: {=INDEX(GMWQ!$A$2:$LR$60,MATCH(1,(GMWQ!$LQ$2:$LQ$60=J$3)*(GMWQ!$LP$2:$LP$60=J$4)*(GMWQ!$LR$2:$LR$60=J$1),0),$B23-1966)} -> 22102.64 | ... AG23: {=INDEX(GMWQ!$A$2:$LR$60,MATCH(1,(GMWQ!$LQ$2:$LQ$60=AG$3)*(GMWQ!$LP$2:$LP$60=AG$4)*(GMWQ!$LR$2:$LR$60=AG$1),0),$B23-1966)} -> -136.4837 | AI23: {=INDEX(GMWQ!$A$2:$LR$60,MATCH(1,(GMWQ!$LQ$2:$LQ$60=AI$3)*(GMWQ!$LP$2:$LP$60=AI$4)*(GMWQ!$LR$2:$LR$60=AI$1),0),$B23-1966)} -> 23884 | AJ23: {=INDEX(GMWQ!$A$2:$LR$60,MATCH(1,(GMWQ!$LQ$2:$LQ$60=AJ$3)*(GMWQ!$LP$2:$LP$60=AJ$4)*(GMWQ!$LR$2:$LR$60=AJ$1),0),$B23-1966)} -> 19.9885 | AK23: {=INDEX(GMWQ!$A$2:$LR$60,MATCH(1,(GMWQ!$LQ$2:$LQ$60=AK$3)*(GMWQ!$LP$2:$LP$60=AK$4)*(GMWQ!$LR$2:$LR$60=AK$1),0),$B23-1966)} -> 18192 | AL23: {=INDEX(GMWQ!$A$2:$LR$60,MATCH(1,(GMWQ!$LQ$2:$LQ$60=AL$3)*(GMWQ!$LP$2:$LP$60=AL$4)*(GMWQ!$LR$2:$LR$60=AL$1),0),$B23-1966)} -> 823.069 | AM23: {=INDEX(GMWQ!$A$2:$LR$60,MATCH(1,(GMWQ!$LQ$2:$LQ$60=AM$3)*(GMWQ!$LP$2:$LP$60=AM$4)*(GMWQ!$LR$2:$LR$60=AM$1),0),$B23-1966)} -> 22102.64 | AN23: {=INDEX(GMWQ!$A$2:$LR$60,MATCH(1,(GMWQ!$LQ$2:$LQ$60=AN$3)*(GMWQ!$LP$2:$LP$60=AN$4)*(GMWQ!$LR$2:$LR$60=AN$1),0),$B23-1966)} -> 4594.215 | AO23: {=INDEX(GMWQ!$A$2:$LR$60,MATCH(1,(GMWQ!$LQ$2:$LQ$60=AO$3)*(GMWQ!$LP$2:$LP$60=AO$4)*(GMWQ!$LR$2:$LR$60=AO$1),0),$B23-1966)} -> 958.7142 | AP23: {=INDEX(GMWQ!$A$2:$LR$60,MATCH(1,(GMWQ!$LQ$2:$LQ$60=AP$3)*(GMWQ!$LP$2:$LP$60=AP$4)*(GMWQ!$LR$2:$LR$60=AP$1),0),$B23-1966)} -> -136.4837 | ... AU23: {=INDEX(GMWQ!$A$2:$LR$60,MATCH(1,(GMWQ!$LQ$2:$LQ$60=AU$3)*(GMWQ!$LP$2:$LP$60=AU$4)*(GMWQ!$LR$2:$LR$60=AU$1),0),$B23-1966)} -> 3661
B24: =+B23+1 -> 1990 | C24: {=INDEX(GMWQ!$A$2:$LR$60,MATCH(1,(GMWQ!$LQ$2:$LQ$60=C$3)*(GMWQ!$LP$2:$LP$60=C$4)*(GMWQ!$LR$2:$LR$60=C$1),0),$B24-1966)} -> 223815 | D24: {=INDEX(GMWQ!$A$2:$LR$60,MATCH(1,(GMWQ!$LQ$2:$LQ$60=D$3)*(GMWQ!$LP$2:$LP$60=D$4)*(GMWQ!$LR$2:$LR$60=D$1),0),$B24-1966)} -> 34.54346 | E24: {=INDEX(GMWQ!$A$2:$LR$60,MATCH(1,(GMWQ!$LQ$2:$LQ$60=E$3)*(GMWQ!$LP$2:$LP$60=E$4)*(GMWQ!$LR$2:$LR$60=E$1),0),$B24-1966)} -> 23.41002 | F24: {=INDEX(GMWQ!$A$2:$LR$60,MATCH(1,(GMWQ!$LQ$2:$LQ$60=F$3)*(GMWQ!$LP$2:$LP$60=F$4)*(GMWQ!$LR$2:$LR$60=F$1),0),$B24-1966)} -> 18494 | G24: {=INDEX(GMWQ!$A$2:$LR$60,MATCH(1,(GMWQ!$LQ$2:$LQ$60=G$3)*(GMWQ!$LP$2:$LP$60=G$4)*(GMWQ!$LR$2:$LR$60=G$1),0),$B24-1966)} -> 4792.029 | H24: {=INDEX(GMWQ!$A$2:$LR$60,MATCH(1,(GMWQ!$LQ$2:$LQ$60=H$3)*(GMWQ!$LP$2:$LP$60=H$4)*(GMWQ!$LR$2:$LR$60=H$1),0),$B24-1966)} -> 992.5015 | I24: {=INDEX(GMWQ!$A$2:$LR$60,MATCH(1,(GMWQ!$LQ$2:$LQ$60=I$3)*(GMWQ!$LP$2:$LP$60=I$4)*(GMWQ!$LR$2:$LR$60=I$1),0),$B24-1966)} -> 20.62976 | J24: {=INDEX(GMWQ!$A$2:$LR$60,MATCH(1,(GMWQ!$LQ$2:$LQ$60=J$3)*(GMWQ!$LP$2:$LP$60=J$4)*(GMWQ!$LR$2:$LR$60=J$1),0),$B24-1966)} -> 22114.38 | ... AG24: {=INDEX(GMWQ!$A$2:$LR$60,MATCH(1,(GMWQ!$LQ$2:$LQ$60=AG$3)*(GMWQ!$LP$2:$LP$60=AG$4)*(GMWQ!$LR$2:$LR$60=AG$1),0),$B24-1966)} -> -132.0186 | AI24: {=INDEX(GMWQ!$A$2:$LR$60,MATCH(1,(GMWQ!$LQ$2:$LQ$60=AI$3)*(GMWQ!$LP$2:$LP$60=AI$4)*(GMWQ!$LR$2:$LR$60=AI$1),0),$B24-1966)} -> 24509 | AJ24: {=INDEX(GMWQ!$A$2:$LR$60,MATCH(1,(GMWQ!$LQ$2:$LQ$60=AJ$3)*(GMWQ!$LP$2:$LP$60=AJ$4)*(GMWQ!$LR$2:$LR$60=AJ$1),0),$B24-1966)} -> 20.62976 | AK24: {=INDEX(GMWQ!$A$2:$LR$60,MATCH(1,(GMWQ!$LQ$2:$LQ$60=AK$3)*(GMWQ!$LP$2:$LP$60=AK$4)*(GMWQ!$LR$2:$LR$60=AK$1),0),$B24-1966)} -> 18494 | AL24: {=INDEX(GMWQ!$A$2:$LR$60,MATCH(1,(GMWQ!$LQ$2:$LQ$60=AL$3)*(GMWQ!$LP$2:$LP$60=AL$4)*(GMWQ!$LR$2:$LR$60=AL$1),0),$B24-1966)} -> 836.2886 | AM24: {=INDEX(GMWQ!$A$2:$LR$60,MATCH(1,(GMWQ!$LQ$2:$LQ$60=AM$3)*(GMWQ!$LP$2:$LP$60=AM$4)*(GMWQ!$LR$2:$LR$60=AM$1),0),$B24-1966)} -> 22114.38 | AN24: {=INDEX(GMWQ!$A$2:$LR$60,MATCH(1,(GMWQ!$LQ$2:$LQ$60=AN$3)*(GMWQ!$LP$2:$LP$60=AN$4)*(GMWQ!$LR$2:$LR$60=AN$1),0),$B24-1966)} -> 4792.029 | AO24: {=INDEX(GMWQ!$A$2:$LR$60,MATCH(1,(GMWQ!$LQ$2:$LQ$60=AO$3)*(GMWQ!$LP$2:$LP$60=AO$4)*(GMWQ!$LR$2:$LR$60=AO$1),0),$B24-1966)} -> 992.5015 | AP24: {=INDEX(GMWQ!$A$2:$LR$60,MATCH(1,(GMWQ!$LQ$2:$LQ$60=AP$3)*(GMWQ!$LP$2:$LP$60=AP$4)*(GMWQ!$LR$2:$LR$60=AP$1),0),$B24-1966)} -> -132.0186 | ... AU24: {=INDEX(GMWQ!$A$2:$LR$60,MATCH(1,(GMWQ!$LQ$2:$LQ$60=AU$3)*(GMWQ!$LP$2:$LP$60=AU$4)*(GMWQ!$LR$2:$LR$60=AU$1),0),$B24-1966)} -> 3288
B25: =+B24+1 -> 1991 | C25: {=INDEX(GMWQ!$A$2:$LR$60,MATCH(1,(GMWQ!$LQ$2:$LQ$60=C$3)*(GMWQ!$LP$2:$LP$60=C$4)*(GMWQ!$LR$2:$LR$60=C$1),0),$B25-1966)} -> 225295 | D25: {=INDEX(GMWQ!$A$2:$LR$60,MATCH(1,(GMWQ!$LQ$2:$LQ$60=D$3)*(GMWQ!$LP$2:$LP$60=D$4)*(GMWQ!$LR$2:$LR$60=D$1),0),$B25-1966)} -> 35.59764 | E25: {=INDEX(GMWQ!$A$2:$LR$60,MATCH(1,(GMWQ!$LQ$2:$LQ$60=E$3)*(GMWQ!$LP$2:$LP$60=E$4)*(GMWQ!$LR$2:$LR$60=E$1),0),$B25-1966)} -> 23.82713 | F25: {=INDEX(GMWQ!$A$2:$LR$60,MATCH(1,(GMWQ!$LQ$2:$LQ$60=F$3)*(GMWQ!$LP$2:$LP$60=F$4)*(GMWQ!$LR$2:$LR$60=F$1),0),$B25-1966)} -> 18884 | G25: {=INDEX(GMWQ!$A$2:$LR$60,MATCH(1,(GMWQ!$LQ$2:$LQ$60=G$3)*(GMWQ!$LP$2:$LP$60=G$4)*(GMWQ!$LR$2:$LR$60=G$1),0),$B25-1966)} -> 4454.757 | H25: {=INDEX(GMWQ!$A$2:$LR$60,MATCH(1,(GMWQ!$LQ$2:$LQ$60=H$3)*(GMWQ!$LP$2:$LP$60=H$4)*(GMWQ!$LR$2:$LR$60=H$1),0),$B25-1966)} -> 1017.842 | I25: {=INDEX(GMWQ!$A$2:$LR$60,MATCH(1,(GMWQ!$LQ$2:$LQ$60=I$3)*(GMWQ!$LP$2:$LP$60=I$4)*(GMWQ!$LR$2:$LR$60=I$1),0),$B25-1966)} -> 21.00216 | J25: {=INDEX(GMWQ!$A$2:$LR$60,MATCH(1,(GMWQ!$LQ$2:$LQ$60=J$3)*(GMWQ!$LP$2:$LP$60=J$4)*(GMWQ!$LR$2:$LR$60=J$1),0),$B25-1966)} -> 22131 | ... AG25: {=INDEX(GMWQ!$A$2:$LR$60,MATCH(1,(GMWQ!$LQ$2:$LQ$60=AG$3)*(GMWQ!$LP$2:$LP$60=AG$4)*(GMWQ!$LR$2:$LR$60=AG$1),0),$B25-1966)} -> -130.4186 | AI25: {=INDEX(GMWQ!$A$2:$LR$60,MATCH(1,(GMWQ!$LQ$2:$LQ$60=AI$3)*(GMWQ!$LP$2:$LP$60=AI$4)*(GMWQ!$LR$2:$LR$60=AI$1),0),$B25-1966)} -> 25439 | AJ25: {=INDEX(GMWQ!$A$2:$LR$60,MATCH(1,(GMWQ!$LQ$2:$LQ$60=AJ$3)*(GMWQ!$LP$2:$LP$60=AJ$4)*(GMWQ!$LR$2:$LR$60=AJ$1),0),$B25-1966)} -> 21.00216 | AK25: {=INDEX(GMWQ!$A$2:$LR$60,MATCH(1,(GMWQ!$LQ$2:$LQ$60=AK$3)*(GMWQ!$LP$2:$LP$60=AK$4)*(GMWQ!$LR$2:$LR$60=AK$1),0),$B25-1966)} -> 18884 | AL25: {=INDEX(GMWQ!$A$2:$LR$60,MATCH(1,(GMWQ!$LQ$2:$LQ$60=AL$3)*(GMWQ!$LP$2:$LP$60=AL$4)*(GMWQ!$LR$2:$LR$60=AL$1),0),$B25-1966)} -> 853.2828 | AM25: {=INDEX(GMWQ!$A$2:$LR$60,MATCH(1,(GMWQ!$LQ$2:$LQ$60=AM$3)*(GMWQ!$LP$2:$LP$60=AM$4)*(GMWQ!$LR$2:$LR$60=AM$1),0),$B25-1966)} -> 22131 | AN25: {=INDEX(GMWQ!$A$2:$LR$60,MATCH(1,(GMWQ!$LQ$2:$LQ$60=AN$3)*(GMWQ!$LP$2:$LP$60=AN$4)*(GMWQ!$LR$2:$LR$60=AN$1),0),$B25-1966)} -> 4454.757 | AO25: {=INDEX(GMWQ!$A$2:$LR$60,MATCH(1,(GMWQ!$LQ$2:$LQ$60=AO$3)*(GMWQ!$LP$2:$LP$60=AO$4)*(GMWQ!$LR$2:$LR$60=AO$1),0),$B25-1966)} -> 1017.842 | AP25: {=INDEX(GMWQ!$A$2:$LR$60,MATCH(1,(GMWQ!$LQ$2:$LQ$60=AP$3)*(GMWQ!$LP$2:$LP$60=AP$4)*(GMWQ!$LR$2:$LR$60=AP$1),0),$B25-1966)} -> -130.4186 | ... AU25: {=INDEX(GMWQ!$A$2:$LR$60,MATCH(1,(GMWQ!$LQ$2:$LQ$60=AU$3)*(GMWQ!$LP$2:$LP$60=AU$4)*(GMWQ!$LR$2:$LR$60=AU$1),0),$B25-1966)} -> 3260
B26: =+B25+1 -> 1992 | C26: {=INDEX(GMWQ!$A$2:$LR$60,MATCH(1,(GMWQ!$LQ$2:$LQ$60=C$3)*(GMWQ!$LP$2:$LP$60=C$4)*(GMWQ!$LR$2:$LR$60=C$1),0),$B26-1966)} -> 229115 | D26: {=INDEX(GMWQ!$A$2:$LR$60,MATCH(1,(GMWQ!$LQ$2:$LQ$60=D$3)*(GMWQ!$LP$2:$LP$60=D$4)*(GMWQ!$LR$2:$LR$60=D$1),0),$B26-1966)} -> 36.68552 | E26: {=INDEX(GMWQ!$A$2:$LR$60,MATCH(1,(GMWQ!$LQ$2:$LQ$60=E$3)*(GMWQ!$LP$2:$LP$60=E$4)*(GMWQ!$LR$2:$LR$60=E$1),0),$B26-1966)} -> 24.13995 | F26: {=INDEX(GMWQ!$A$2:$LR$60,MATCH(1,(GMWQ!$LQ$2:$LQ$60=F$3)*(GMWQ!$LP$2:$LP$60=F$4)*(GMWQ!$LR$2:$LR$60=F$1),0),$B26-1966)} -> 19532 | G26: {=INDEX(GMWQ!$A$2:$LR$60,MATCH(1,(GMWQ!$LQ$2:$LQ$60=G$3)*(GMWQ!$LP$2:$LP$60=G$4)*(GMWQ!$LR$2:$LR$60=G$1),0),$B26-1966)} -> 4109.573 | H26: {=INDEX(GMWQ!$A$2:$LR$60,MATCH(1,(GMWQ!$LQ$2:$LQ$60=H$3)*(GMWQ!$LP$2:$LP$60=H$4)*(GMWQ!$LR$2:$LR$60=H$1),0),$B26-1966)} -> 1052.685 | I26: {=INDEX(GMWQ!$A$2:$LR$60,MATCH(1,(GMWQ!$LQ$2:$LQ$60=I$3)*(GMWQ!$LP$2:$LP$60=I$4)*(GMWQ!$LR$2:$LR$60=I$1),0),$B26-1966)} -> 21.35981 | J26: {=INDEX(GMWQ!$A$2:$LR$60,MATCH(1,(GMWQ!$LQ$2:$LQ$60=J$3)*(GMWQ!$LP$2:$LP$60=J$4)*(GMWQ!$LR$2:$LR$60=J$1),0),$B26-1966)} -> 22135.88 | ... AG26: {=INDEX(GMWQ!$A$2:$LR$60,MATCH(1,(GMWQ!$LQ$2:$LQ$60=AG$3)*(GMWQ!$LP$2:$LP$60=AG$4)*(GMWQ!$LR$2:$LR$60=AG$1),0),$B26-1966)} -> -205.1349 | AI26: {=INDEX(GMWQ!$A$2:$LR$60,MATCH(1,(GMWQ!$LQ$2:$LQ$60=AI$3)*(GMWQ!$LP$2:$LP$60=AI$4)*(GMWQ!$LR$2:$LR$60=AI$1),0),$B26-1966)} -> 26940 | AJ26: {=INDEX(GMWQ!$A$2:$LR$60,MATCH(1,(GMWQ!$LQ$2:$LQ$60=AJ$3)*(GMWQ!$LP$2:$LP$60=AJ$4)*(GMWQ!$LR$2:$LR$60=AJ$1),0),$B26-1966)} -> 21.35981 | AK26: {=INDEX(GMWQ!$A$2:$LR$60,MATCH(1,(GMWQ!$LQ$2:$LQ$60=AK$3)*(GMWQ!$LP$2:$LP$60=AK$4)*(GMWQ!$LR$2:$LR$60=AK$1),0),$B26-1966)} -> 19532 | AL26: {=INDEX(GMWQ!$A$2:$LR$60,MATCH(1,(GMWQ!$LQ$2:$LQ$60=AL$3)*(GMWQ!$LP$2:$LP$60=AL$4)*(GMWQ!$LR$2:$LR$60=AL$1),0),$B26-1966)} -> 882.3682 | AM26: {=INDEX(GMWQ!$A$2:$LR$60,MATCH(1,(GMWQ!$LQ$2:$LQ$60=AM$3)*(GMWQ!$LP$2:$LP$60=AM$4)*(GMWQ!$LR$2:$LR$60=AM$1),0),$B26-1966)} -> 22135.88 | AN26: {=INDEX(GMWQ!$A$2:$LR$60,MATCH(1,(GMWQ!$LQ$2:$LQ$60=AN$3)*(GMWQ!$LP$2:$LP$60=AN$4)*(GMWQ!$LR$2:$LR$60=AN$1),0),$B26-1966)} -> 4109.573 | AO26: {=INDEX(GMWQ!$A$2:$LR$60,MATCH(1,(GMWQ!$LQ$2:$LQ$60=AO$3)*(GMWQ!$LP$2:$LP$60=AO$4)*(GMWQ!$LR$2:$LR$60=AO$1),0),$B26-1966)} -> 1052.685 | AP26: {=INDEX(GMWQ!$A$2:$LR$60,MATCH(1,(GMWQ!$LQ$2:$LQ$60=AP$3)*(GMWQ!$LP$2:$LP$60=AP$4)*(GMWQ!$LR$2:$LR$60=AP$1),0),$B26-1966)} -> -205.1349 | ... AU26: {=INDEX(GMWQ!$A$2:$LR$60,MATCH(1,(GMWQ!$LQ$2:$LQ$60=AU$3)*(GMWQ!$LP$2:$LP$60=AU$4)*(GMWQ!$LR$2:$LR$60=AU$1),0),$B26-1966)} -> 3269
A27: 1978 | B27: =+B26+1 -> 1993 | C27: {=INDEX(GMWQ!$A$2:$LR$60,MATCH(1,(GMWQ!$LQ$2:$LQ$60=C$3)*(GMWQ!$LP$2:$LP$60=C$4)*(GMWQ!$LR$2:$LR$60=C$1),0),$B27-1966)} -> 231258 | D27: {=INDEX(GMWQ!$A$2:$LR$60,MATCH(1,(GMWQ!$LQ$2:$LQ$60=D$3)*(GMWQ!$LP$2:$LP$60=D$4)*(GMWQ!$LR$2:$LR$60=D$1),0),$B27-1966)} -> 37.64326 | E27: {=INDEX(GMWQ!$A$2:$LR$60,MATCH(1,(GMWQ!$LQ$2:$LQ$60=E$3)*(GMWQ!$LP$2:$LP$60=E$4)*(GMWQ!$LR$2:$LR$60=E$1),0),$B27-1966)} -> 24.45278 | F27: {=INDEX(GMWQ!$A$2:$LR$60,MATCH(1,(GMWQ!$LQ$2:$LQ$60=F$3)*(GMWQ!$LP$2:$LP$60=F$4)*(GMWQ!$LR$2:$LR$60=F$1),0),$B27-1966)} -> 20334 | G27: {=INDEX(GMWQ!$A$2:$LR$60,MATCH(1,(GMWQ!$LQ$2:$LQ$60=G$3)*(GMWQ!$LP$2:$LP$60=G$4)*(GMWQ!$LR$2:$LR$60=G$1),0),$B27-1966)} -> 4647.625 | H27: {=INDEX(GMWQ!$A$2:$LR$60,MATCH(1,(GMWQ!$LQ$2:$LQ$60=H$3)*(GMWQ!$LP$2:$LP$60=H$4)*(GMWQ!$LR$2:$LR$60=H$1),0),$B27-1966)} -> 1074.858 | I27: {=INDEX(GMWQ!$A$2:$LR$60,MATCH(1,(GMWQ!$LQ$2:$LQ$60=I$3)*(GMWQ!$LP$2:$LP$60=I$4)*(GMWQ!$LR$2:$LR$60=I$1),0),$B27-1966)} -> 22.0437 | J27: {=INDEX(GMWQ!$A$2:$LR$60,MATCH(1,(GMWQ!$LQ$2:$LQ$60=J$3)*(GMWQ!$LP$2:$LP$60=J$4)*(GMWQ!$LR$2:$LR$60=J$1),0),$B27-1966)} -> 22211.17 | ... AG27: {=INDEX(GMWQ!$A$2:$LR$60,MATCH(1,(GMWQ!$LQ$2:$LQ$60=AG$3)*(GMWQ!$LP$2:$LP$60=AG$4)*(GMWQ!$LR$2:$LR$60=AG$1),0),$B27-1966)} -> -166.3628 | AI27: {=INDEX(GMWQ!$A$2:$LR$60,MATCH(1,(GMWQ!$LQ$2:$LQ$60=AI$3)*(GMWQ!$LP$2:$LP$60=AI$4)*(GMWQ!$LR$2:$LR$60=AI$1),0),$B27-1966)} -> 27797 | AJ27: {=INDEX(GMWQ!$A$2:$LR$60,MATCH(1,(GMWQ!$LQ$2:$LQ$60=AJ$3)*(GMWQ!$LP$2:$LP$60=AJ$4)*(GMWQ!$LR$2:$LR$60=AJ$1),0),$B27-1966)} -> 22.0437 | AK27: {=INDEX(GMWQ!$A$2:$LR$60,MATCH(1,(GMWQ!$LQ$2:$LQ$60=AK$3)*(GMWQ!$LP$2:$LP$60=AK$4)*(GMWQ!$LR$2:$LR$60=AK$1),0),$B27-1966)} -> 20334 | AL27: {=INDEX(GMWQ!$A$2:$LR$60,MATCH(1,(GMWQ!$LQ$2:$LQ$60=AL$3)*(GMWQ!$LP$2:$LP$60=AL$4)*(GMWQ!$LR$2:$LR$60=AL$1),0),$B27-1966)} -> 915.4854 | AM27: {=INDEX(GMWQ!$A$2:$LR$60,MATCH(1,(GMWQ!$LQ$2:$LQ$60=AM$3)*(GMWQ!$LP$2:$LP$60=AM$4)*(GMWQ!$LR$2:$LR$60=AM$1),0),$B27-1966)} -> 22211.17 | AN27: {=INDEX(GMWQ!$A$2:$LR$60,MATCH(1,(GMWQ!$LQ$2:$LQ$60=AN$3)*(GMWQ!$LP$2:$LP$60=AN$4)*(GMWQ!$LR$2:$LR$60=AN$1),0),$B27-1966)} -> 4647.625 | AO27: {=INDEX(GMWQ!$A$2:$LR$60,MATCH(1,(GMWQ!$LQ$2:$LQ$60=AO$3)*(GMWQ!$LP$2:$LP$60=AO$4)*(GMWQ!$LR$2:$LR$60=AO$1),0),$B27-1966)} -> 1074.858 | AP27: {=INDEX(GMWQ!$A$2:$LR$60,MATCH(1,(GMWQ!$LQ$2:$LQ$60=AP$3)*(GMWQ!$LP$2:$LP$60=AP$4)*(GMWQ!$LR$2:$LR$60=AP$1),0),$B27-1966)} -> -166.3628 | ... AU27: {=INDEX(GMWQ!$A$2:$LR$60,MATCH(1,(GMWQ!$LQ$2:$LQ$60=AU$3)*(GMWQ!$LP$2:$LP$60=AU$4)*(GMWQ!$LR$2:$LR$60=AU$1),0),$B27-1966)} -> 2976
B28: =+B27+1 -> 1994 | C28: {=INDEX(GMWQ!$A$2:$LR$60,MATCH(1,(GMWQ!$LQ$2:$LQ$60=C$3)*(GMWQ!$LP$2:$LP$60=C$4)*(GMWQ!$LR$2:$LR$60=C$1),0),$B28-1966)} -> 233910 | D28: {=INDEX(GMWQ!$A$2:$LR$60,MATCH(1,(GMWQ!$LQ$2:$LQ$60=D$3)*(GMWQ!$LP$2:$LP$60=D$4)*(GMWQ!$LR$2:$LR$60=D$1),0),$B28-1966)} -> 39.86473 | E28: {=INDEX(GMWQ!$A$2:$LR$60,MATCH(1,(GMWQ!$LQ$2:$LQ$60=E$3)*(GMWQ!$LP$2:$LP$60=E$4)*(GMWQ!$LR$2:$LR$60=E$1),0),$B28-1966)} -> 25.07844 | F28: {=INDEX(GMWQ!$A$2:$LR$60,MATCH(1,(GMWQ!$LQ$2:$LQ$60=F$3)*(GMWQ!$LP$2:$LP$60=F$4)*(GMWQ!$LR$2:$LR$60=F$1),0),$B28-1966)} -> 21257 | G28: {=INDEX(GMWQ!$A$2:$LR$60,MATCH(1,(GMWQ!$LQ$2:$LQ$60=G$3)*(GMWQ!$LP$2:$LP$60=G$4)*(GMWQ!$LR$2:$LR$60=G$1),0),$B28-1966)} -> 5305.354 | H28: {=INDEX(GMWQ!$A$2:$LR$60,MATCH(1,(GMWQ!$LQ$2:$LQ$60=H$3)*(GMWQ!$LP$2:$LP$60=H$4)*(GMWQ!$LR$2:$LR$60=H$1),0),$B28-1966)} -> 1004.116 | I28: {=INDEX(GMWQ!$A$2:$LR$60,MATCH(1,(GMWQ!$LQ$2:$LQ$60=I$3)*(GMWQ!$LP$2:$LP$60=I$4)*(GMWQ!$LR$2:$LR$60=I$1),0),$B28-1966)} -> 22.54001 | J28: {=INDEX(GMWQ!$A$2:$LR$60,MATCH(1,(GMWQ!$LQ$2:$LQ$60=J$3)*(GMWQ!$LP$2:$LP$60=J$4)*(GMWQ!$LR$2:$LR$60=J$1),0),$B28-1966)} -> 22172.78 | ... AG28: {=INDEX(GMWQ!$A$2:$LR$60,MATCH(1,(GMWQ!$LQ$2:$LQ$60=AG$3)*(GMWQ!$LP$2:$LP$60=AG$4)*(GMWQ!$LR$2:$LR$60=AG$1),0),$B28-1966)} -> -305.786 | AI28: {=INDEX(GMWQ!$A$2:$LR$60,MATCH(1,(GMWQ!$LQ$2:$LQ$60=AI$3)*(GMWQ!$LP$2:$LP$60=AI$4)*(GMWQ!$LR$2:$LR$60=AI$1),0),$B28-1966)} -> 29144 | AJ28: {=INDEX(GMWQ!$A$2:$LR$60,MATCH(1,(GMWQ!$LQ$2:$LQ$60=AJ$3)*(GMWQ!$LP$2:$LP$60=AJ$4)*(GMWQ!$LR$2:$LR$60=AJ$1),0),$B28-1966)} -> 22.54001 | AK28: {=INDEX(GMWQ!$A$2:$LR$60,MATCH(1,(GMWQ!$LQ$2:$LQ$60=AK$3)*(GMWQ!$LP$2:$LP$60=AK$4)*(GMWQ!$LR$2:$LR$60=AK$1),0),$B28-1966)} -> 21257 | AL28: {=INDEX(GMWQ!$A$2:$LR$60,MATCH(1,(GMWQ!$LQ$2:$LQ$60=AL$3)*(GMWQ!$LP$2:$LP$60=AL$4)*(GMWQ!$LR$2:$LR$60=AL$1),0),$B28-1966)} -> 958.6979 | AM28: {=INDEX(GMWQ!$A$2:$LR$60,MATCH(1,(GMWQ!$LQ$2:$LQ$60=AM$3)*(GMWQ!$LP$2:$LP$60=AM$4)*(GMWQ!$LR$2:$LR$60=AM$1),0),$B28-1966)} -> 22172.78 | AN28: {=INDEX(GMWQ!$A$2:$LR$60,MATCH(1,(GMWQ!$LQ$2:$LQ$60=AN$3)*(GMWQ!$LP$2:$LP$60=AN$4)*(GMWQ!$LR$2:$LR$60=AN$1),0),$B28-1966)} -> 5305.354 | AO28: {=INDEX(GMWQ!$A$2:$LR$60,MATCH(1,(GMWQ!$LQ$2:$LQ$60=AO$3)*(GMWQ!$LP$2:$LP$60=AO$4)*(GMWQ!$LR$2:$LR$60=AO$1),0),$B28-1966)} -> 1004.116 | AP28: {=INDEX(GMWQ!$A$2:$LR$60,MATCH(1,(GMWQ!$LQ$2:$LQ$60=AP$3)*(GMWQ!$LP$2:$LP$60=AP$4)*(GMWQ!$LR$2:$LR$60=AP$1),0),$B28-1966)} -> -305.786 | ... AU28: {=INDEX(GMWQ!$A$2:$LR$60,MATCH(1,(GMWQ!$LQ$2:$LQ$60=AU$3)*(GMWQ!$LP$2:$LP$60=AU$4)*(GMWQ!$LR$2:$LR$60=AU$1),0),$B28-1966)} -> 3668
B29: =+B28+1 -> 1995 | C29: {=INDEX(GMWQ!$A$2:$LR$60,MATCH(1,(GMWQ!$LQ$2:$LQ$60=C$3)*(GMWQ!$LP$2:$LP$60=C$4)*(GMWQ!$LR$2:$LR$60=C$1),0),$B29-1966)} -> 237107 | D29: {=INDEX(GMWQ!$A$2:$LR$60,MATCH(1,(GMWQ!$LQ$2:$LQ$60=D$3)*(GMWQ!$LP$2:$LP$60=D$4)*(GMWQ!$LR$2:$LR$60=D$1),0),$B29-1966)} -> 42.09901 | E29: {=INDEX(GMWQ!$A$2:$LR$60,MATCH(1,(GMWQ!$LQ$2:$LQ$60=E$3)*(GMWQ!$LP$2:$LP$60=E$4)*(GMWQ!$LR$2:$LR$60=E$1),0),$B29-1966)} -> 25.46948 | F29: {=INDEX(GMWQ!$A$2:$LR$60,MATCH(1,(GMWQ!$LQ$2:$LQ$60=F$3)*(GMWQ!$LP$2:$LP$60=F$4)*(GMWQ!$LR$2:$LR$60=F$1),0),$B29-1966)} -> 21798 | G29: {=INDEX(GMWQ!$A$2:$LR$60,MATCH(1,(GMWQ!$LQ$2:$LQ$60=G$3)*(GMWQ!$LP$2:$LP$60=G$4)*(GMWQ!$LR$2:$LR$60=G$1),0),$B29-1966)} -> 4553.664 | H29: {=INDEX(GMWQ!$A$2:$LR$60,MATCH(1,(GMWQ!$LQ$2:$LQ$60=H$3)*(GMWQ!$LP$2:$LP$60=H$4)*(GMWQ!$LR$2:$LR$60=H$1),0),$B29-1966)} -> 1063.244 | I29: {=INDEX(GMWQ!$A$2:$LR$60,MATCH(1,(GMWQ!$LQ$2:$LQ$60=I$3)*(GMWQ!$LP$2:$LP$60=I$4)*(GMWQ!$LR$2:$LR$60=I$1),0),$B29-1966)} -> 22.95705 | J29: {=INDEX(GMWQ!$A$2:$LR$60,MATCH(1,(GMWQ!$LQ$2:$LQ$60=J$3)*(GMWQ!$LP$2:$LP$60=J$4)*(GMWQ!$LR$2:$LR$60=J$1),0),$B29-1966)} -> 22261.89 | ... AG29: {=INDEX(GMWQ!$A$2:$LR$60,MATCH(1,(GMWQ!$LQ$2:$LQ$60=AG$3)*(GMWQ!$LP$2:$LP$60=AG$4)*(GMWQ!$LR$2:$LR$60=AG$1),0),$B29-1966)} -> -244.9488 | AI29: {=INDEX(GMWQ!$A$2:$LR$60,MATCH(1,(GMWQ!$LQ$2:$LQ$60=AI$3)*(GMWQ!$LP$2:$LP$60=AI$4)*(GMWQ!$LR$2:$LR$60=AI$1),0),$B29-1966)} -> 30465 | AJ29: {=INDEX(GMWQ!$A$2:$LR$60,MATCH(1,(GMWQ!$LQ$2:$LQ$60=AJ$3)*(GMWQ!$LP$2:$LP$60=AJ$4)*(GMWQ!$LR$2:$LR$60=AJ$1),0),$B29-1966)} -> 22.95705 | AK29: {=INDEX(GMWQ!$A$2:$LR$60,MATCH(1,(GMWQ!$LQ$2:$LQ$60=AK$3)*(GMWQ!$LP$2:$LP$60=AK$4)*(GMWQ!$LR$2:$LR$60=AK$1),0),$B29-1966)} -> 21798 | AL29: {=INDEX(GMWQ!$A$2:$LR$60,MATCH(1,(GMWQ!$LQ$2:$LQ$60=AL$3)*(GMWQ!$LP$2:$LP$60=AL$4)*(GMWQ!$LR$2:$LR$60=AL$1),0),$B29-1966)} -> 979.1619 | AM29: {=INDEX(GMWQ!$A$2:$LR$60,MATCH(1,(GMWQ!$LQ$2:$LQ$60=AM$3)*(GMWQ!$LP$2:$LP$60=AM$4)*(GMWQ!$LR$2:$LR$60=AM$1),0),$B29-1966)} -> 22261.89 | AN29: {=INDEX(GMWQ!$A$2:$LR$60,MATCH(1,(GMWQ!$LQ$2:$LQ$60=AN$3)*(GMWQ!$LP$2:$LP$60=AN$4)*(GMWQ!$LR$2:$LR$60=AN$1),0),$B29-1966)} -> 4553.664 | AO29: {=INDEX(GMWQ!$A$2:$LR$60,MATCH(1,(GMWQ!$LQ$2:$LQ$60=AO$3)*(GMWQ!$LP$2:$LP$60=AO$4)*(GMWQ!$LR$2:$LR$60=AO$1),0),$B29-1966)} -> 1063.244 | AP29: {=INDEX(GMWQ!$A$2:$LR$60,MATCH(1,(GMWQ!$LQ$2:$LQ$60=AP$3)*(GMWQ!$LP$2:$LP$60=AP$4)*(GMWQ!$LR$2:$LR$60=AP$1),0),$B29-1966)} -> -244.9488 | ... AU29: {=INDEX(GMWQ!$A$2:$LR$60,MATCH(1,(GMWQ!$LQ$2:$LQ$60=AU$3)*(GMWQ!$LP$2:$LP$60=AU$4)*(GMWQ!$LR$2:$LR$60=AU$1),0),$B29-1966)} -> 3504
B30: =+B29+1 -> 1996 | C30: {=INDEX(GMWQ!$A$2:$LR$60,MATCH(1,(GMWQ!$LQ$2:$LQ$60=C$3)*(GMWQ!$LP$2:$LP$60=C$4)*(GMWQ!$LR$2:$LR$60=C$1),0),$B30-1966)} -> 239186 | D30: {=INDEX(GMWQ!$A$2:$LR$60,MATCH(1,(GMWQ!$LQ$2:$LQ$60=D$3)*(GMWQ!$LP$2:$LP$60=D$4)*(GMWQ!$LR$2:$LR$60=D$1),0),$B30-1966)} -> 43.30621 | E30: {=INDEX(GMWQ!$A$2:$LR$60,MATCH(1,(GMWQ!$LQ$2:$LQ$60=E$3)*(GMWQ!$LP$2:$LP$60=E$4)*(GMWQ!$LR$2:$LR$60=E$1),0),$B30-1966)} -> 25.86051 | F30: {=INDEX(GMWQ!$A$2:$LR$60,MATCH(1,(GMWQ!$LQ$2:$LQ$60=F$3)*(GMWQ!$LP$2:$LP$60=F$4)*(GMWQ!$LR$2:$LR$60=F$1),0),$B30-1966)} -> 22479 | G30: {=INDEX(GMWQ!$A$2:$LR$60,MATCH(1,(GMWQ!$LQ$2:$LQ$60=G$3)*(GMWQ!$LP$2:$LP$60=G$4)*(GMWQ!$LR$2:$LR$60=G$1),0),$B30-1966)} -> 4740.597 | H30: {=INDEX(GMWQ!$A$2:$LR$60,MATCH(1,(GMWQ!$LQ$2:$LQ$60=H$3)*(GMWQ!$LP$2:$LP$60=H$4)*(GMWQ!$LR$2:$LR$60=H$1),0),$B30-1966)} -> 1114.98 | I30: {=INDEX(GMWQ!$A$2:$LR$60,MATCH(1,(GMWQ!$LQ$2:$LQ$60=I$3)*(GMWQ!$LP$2:$LP$60=I$4)*(GMWQ!$LR$2:$LR$60=I$1),0),$B30-1966)} -> 23.74508 | J30: {=INDEX(GMWQ!$A$2:$LR$60,MATCH(1,(GMWQ!$LQ$2:$LQ$60=J$3)*(GMWQ!$LP$2:$LP$60=J$4)*(GMWQ!$LR$2:$LR$60=J$1),0),$B30-1966)} -> 22426.62 | ... AG30: {=INDEX(GMWQ!$A$2:$LR$60,MATCH(1,(GMWQ!$LQ$2:$LQ$60=AG$3)*(GMWQ!$LP$2:$LP$60=AG$4)*(GMWQ!$LR$2:$LR$60=AG$1),0),$B30-1966)} -> -304.2605 | AI30: {=INDEX(GMWQ!$A$2:$LR$60,MATCH(1,(GMWQ!$LQ$2:$LQ$60=AI$3)*(GMWQ!$LP$2:$LP$60=AI$4)*(GMWQ!$LR$2:$LR$60=AI$1),0),$B30-1966)} -> 31463 | AJ30: {=INDEX(GMWQ!$A$2:$LR$60,MATCH(1,(GMWQ!$LQ$2:$LQ$60=AJ$3)*(GMWQ!$LP$2:$LP$60=AJ$4)*(GMWQ!$LR$2:$LR$60=AJ$1),0),$B30-1966)} -> 23.74508 | AK30: {=INDEX(GMWQ!$A$2:$LR$60,MATCH(1,(GMWQ!$LQ$2:$LQ$60=AK$3)*(GMWQ!$LP$2:$LP$60=AK$4)*(GMWQ!$LR$2:$LR$60=AK$1),0),$B30-1966)} -> 22479 | AL30: {=INDEX(GMWQ!$A$2:$LR$60,MATCH(1,(GMWQ!$LQ$2:$LQ$60=AL$3)*(GMWQ!$LP$2:$LP$60=AL$4)*(GMWQ!$LR$2:$LR$60=AL$1),0),$B30-1966)} -> 1002.336 | AM30: {=INDEX(GMWQ!$A$2:$LR$60,MATCH(1,(GMWQ!$LQ$2:$LQ$60=AM$3)*(GMWQ!$LP$2:$LP$60=AM$4)*(GMWQ!$LR$2:$LR$60=AM$1),0),$B30-1966)} -> 22426.62 | AN30: {=INDEX(GMWQ!$A$2:$LR$60,MATCH(1,(GMWQ!$LQ$2:$LQ$60=AN$3)*(GMWQ!$LP$2:$LP$60=AN$4)*(GMWQ!$LR$2:$LR$60=AN$1),0),$B30-1966)} -> 4740.597 | AO30: {=INDEX(GMWQ!$A$2:$LR$60,MATCH(1,(GMWQ!$LQ$2:$LQ$60=AO$3)*(GMWQ!$LP$2:$LP$60=AO$4)*(GMWQ!$LR$2:$LR$60=AO$1),0),$B30-1966)} -> 1114.98 | AP30: {=INDEX(GMWQ!$A$2:$LR$60,MATCH(1,(GMWQ!$LQ$2:$LQ$60=AP$3)*(GMWQ!$LP$2:$LP$60=AP$4)*(GMWQ!$LR$2:$LR$60=AP$1),0),$B30-1966)} -> -304.2605 | ... AU30: {=INDEX(GMWQ!$A$2:$LR$60,MATCH(1,(GMWQ!$LQ$2:$LQ$60=AU$3)*(GMWQ!$LP$2:$LP$60=AU$4)*(GMWQ!$LR$2:$LR$60=AU$1),0),$B30-1966)} -> 3663
A31: 1979 | B31: =+B30+1 -> 1997 | C31: {=INDEX(GMWQ!$A$2:$LR$60,MATCH(1,(GMWQ!$LQ$2:$LQ$60=C$3)*(GMWQ!$LP$2:$LP$60=C$4)*(GMWQ!$LR$2:$LR$60=C$1),0),$B31-1966)} -> 238472 | D31: {=INDEX(GMWQ!$A$2:$LR$60,MATCH(1,(GMWQ!$LQ$2:$LQ$60=D$3)*(GMWQ!$LP$2:$LP$60=D$4)*(GMWQ!$LR$2:$LR$60=D$1),0),$B31-1966)} -> 43.96501 | E31: {=INDEX(GMWQ!$A$2:$LR$60,MATCH(1,(GMWQ!$LQ$2:$LQ$60=E$3)*(GMWQ!$LP$2:$LP$60=E$4)*(GMWQ!$LR$2:$LR$60=E$1),0),$B31-1966)} -> 26.43403 | F31: {=INDEX(GMWQ!$A$2:$LR$60,MATCH(1,(GMWQ!$LQ$2:$LQ$60=F$3)*(GMWQ!$LP$2:$LP$60=F$4)*(GMWQ!$LR$2:$LR$60=F$1),0),$B31-1966)} -> 23365 | G31: {=INDEX(GMWQ!$A$2:$LR$60,MATCH(1,(GMWQ!$LQ$2:$LQ$60=G$3)*(GMWQ!$LP$2:$LP$60=G$4)*(GMWQ!$LR$2:$LR$60=G$1),0),$B31-1966)} -> 5114.465 | H31: {=INDEX(GMWQ!$A$2:$LR$60,MATCH(1,(GMWQ!$LQ$2:$LQ$60=H$3)*(GMWQ!$LP$2:$LP$60=H$4)*(GMWQ!$LR$2:$LR$60=H$1),0),$B31-1966)} -> 1131.874 | I31: {=INDEX(GMWQ!$A$2:$LR$60,MATCH(1,(GMWQ!$LQ$2:$LQ$60=I$3)*(GMWQ!$LP$2:$LP$60=I$4)*(GMWQ!$LR$2:$LR$60=I$1),0),$B31-1966)} -> 24.39153 | J31: {=INDEX(GMWQ!$A$2:$LR$60,MATCH(1,(GMWQ!$LQ$2:$LQ$60=J$3)*(GMWQ!$LP$2:$LP$60=J$4)*(GMWQ!$LR$2:$LR$60=J$1),0),$B31-1966)} -> 22454.52 | ... AG31: {=INDEX(GMWQ!$A$2:$LR$60,MATCH(1,(GMWQ!$LQ$2:$LQ$60=AG$3)*(GMWQ!$LP$2:$LP$60=AG$4)*(GMWQ!$LR$2:$LR$60=AG$1),0),$B31-1966)} -> -272 | AI31: {=INDEX(GMWQ!$A$2:$LR$60,MATCH(1,(GMWQ!$LQ$2:$LQ$60=AI$3)*(GMWQ!$LP$2:$LP$60=AI$4)*(GMWQ!$LR$2:$LR$60=AI$1),0),$B31-1966)} -> 32879 | AJ31: {=INDEX(GMWQ!$A$2:$LR$60,MATCH(1,(GMWQ!$LQ$2:$LQ$60=AJ$3)*(GMWQ!$LP$2:$LP$60=AJ$4)*(GMWQ!$LR$2:$LR$60=AJ$1),0),$B31-1966)} -> 24.39153 | AK31: {=INDEX(GMWQ!$A$2:$LR$60,MATCH(1,(GMWQ!$LQ$2:$LQ$60=AK$3)*(GMWQ!$LP$2:$LP$60=AK$4)*(GMWQ!$LR$2:$LR$60=AK$1),0),$B31-1966)} -> 23365 | AL31: {=INDEX(GMWQ!$A$2:$LR$60,MATCH(1,(GMWQ!$LQ$2:$LQ$60=AL$3)*(GMWQ!$LP$2:$LP$60=AL$4)*(GMWQ!$LR$2:$LR$60=AL$1),0),$B31-1966)} -> 1040.548 | AM31: {=INDEX(GMWQ!$A$2:$LR$60,MATCH(1,(GMWQ!$LQ$2:$LQ$60=AM$3)*(GMWQ!$LP$2:$LP$60=AM$4)*(GMWQ!$LR$2:$LR$60=AM$1),0),$B31-1966)} -> 22454.52 | AN31: {=INDEX(GMWQ!$A$2:$LR$60,MATCH(1,(GMWQ!$LQ$2:$LQ$60=AN$3)*(GMWQ!$LP$2:$LP$60=AN$4)*(GMWQ!$LR$2:$LR$60=AN$1),0),$B31-1966)} -> 5114.465 | AO31: {=INDEX(GMWQ!$A$2:$LR$60,MATCH(1,(GMWQ!$LQ$2:$LQ$60=AO$3)*(GMWQ!$LP$2:$LP$60=AO$4)*(GMWQ!$LR$2:$LR$60=AO$1),0),$B31-1966)} -> 1131.874 | AP31: {=INDEX(GMWQ!$A$2:$LR$60,MATCH(1,(GMWQ!$LQ$2:$LQ$60=AP$3)*(GMWQ!$LP$2:$LP$60=AP$4)*(GMWQ!$LR$2:$LR$60=AP$1),0),$B31-1966)} -> -272 | ... AU31: {=INDEX(GMWQ!$A$2:$LR$60,MATCH(1,(GMWQ!$LQ$2:$LQ$60=AU$3)*(GMWQ!$LP$2:$LP$60=AU$4)*(GMWQ!$LR$2:$LR$60=AU$1),0),$B31-1966)} -> 3099
B32: =+B31+1 -> 1998 | C32: {=INDEX(GMWQ!$A$2:$LR$60,MATCH(1,(GMWQ!$LQ$2:$LQ$60=C$3)*(GMWQ!$LP$2:$LP$60=C$4)*(GMWQ!$LR$2:$LR$60=C$1),0),$B32-1966)} -> 248867 | D32: {=INDEX(GMWQ!$A$2:$LR$60,MATCH(1,(GMWQ!$LQ$2:$LQ$60=D$3)*(GMWQ!$LP$2:$LP$60=D$4)*(GMWQ!$LR$2:$LR$60=D$1),0),$B32-1966)} -> 46.83842 | E32: {=INDEX(GMWQ!$A$2:$LR$60,MATCH(1,(GMWQ!$LQ$2:$LQ$60=E$3)*(GMWQ!$LP$2:$LP$60=E$4)*(GMWQ!$LR$2:$LR$60=E$1),0),$B32-1966)} -> 27.26824 | F32: {=INDEX(GMWQ!$A$2:$LR$60,MATCH(1,(GMWQ!$LQ$2:$LQ$60=F$3)*(GMWQ!$LP$2:$LP$60=F$4)*(GMWQ!$LR$2:$LR$60=F$1),0),$B32-1966)} -> 24427 | G32: {=INDEX(GMWQ!$A$2:$LR$60,MATCH(1,(GMWQ!$LQ$2:$LQ$60=G$3)*(GMWQ!$LP$2:$LP$60=G$4)*(GMWQ!$LR$2:$LR$60=G$1),0),$B32-1966)} -> 5656.473 | H32: {=INDEX(GMWQ!$A$2:$LR$60,MATCH(1,(GMWQ!$LQ$2:$LQ$60=H$3)*(GMWQ!$LP$2:$LP$60=H$4)*(GMWQ!$LR$2:$LR$60=H$1),0),$B32-1966)} -> 1176.22 | I32: {=INDEX(GMWQ!$A$2:$LR$60,MATCH(1,(GMWQ!$LQ$2:$LQ$60=I$3)*(GMWQ!$LP$2:$LP$60=I$4)*(GMWQ!$LR$2:$LR$60=I$1),0),$B32-1966)} -> 24.95965 | J32: {=INDEX(GMWQ!$A$2:$LR$60,MATCH(1,(GMWQ!$LQ$2:$LQ$60=J$3)*(GMWQ!$LP$2:$LP$60=J$4)*(GMWQ!$LR$2:$LR$60=J$1),0),$B32-1966)} -> 22553.54 | ... AG32: {=INDEX(GMWQ!$A$2:$LR$60,MATCH(1,(GMWQ!$LQ$2:$LQ$60=AG$3)*(GMWQ!$LP$2:$LP$60=AG$4)*(GMWQ!$LR$2:$LR$60=AG$1),0),$B32-1966)} -> -314.4558 | AI32: {=INDEX(GMWQ!$A$2:$LR$60,MATCH(1,(GMWQ!$LQ$2:$LQ$60=AI$3)*(GMWQ!$LP$2:$LP$60=AI$4)*(GMWQ!$LR$2:$LR$60=AI$1),0),$B32-1966)} -> 34157 | AJ32: {=INDEX(GMWQ!$A$2:$LR$60,MATCH(1,(GMWQ!$LQ$2:$LQ$60=AJ$3)*(GMWQ!$LP$2:$LP$60=AJ$4)*(GMWQ!$LR$2:$LR$60=AJ$1),0),$B32-1966)} -> 24.95965 | AK32: {=INDEX(GMWQ!$A$2:$LR$60,MATCH(1,(GMWQ!$LQ$2:$LQ$60=AK$3)*(GMWQ!$LP$2:$LP$60=AK$4)*(GMWQ!$LR$2:$LR$60=AK$1),0),$B32-1966)} -> 24427 | AL32: {=INDEX(GMWQ!$A$2:$LR$60,MATCH(1,(GMWQ!$LQ$2:$LQ$60=AL$3)*(GMWQ!$LP$2:$LP$60=AL$4)*(GMWQ!$LR$2:$LR$60=AL$1),0),$B32-1966)} -> 1083.067 | AM32: {=INDEX(GMWQ!$A$2:$LR$60,MATCH(1,(GMWQ!$LQ$2:$LQ$60=AM$3)*(GMWQ!$LP$2:$LP$60=AM$4)*(GMWQ!$LR$2:$LR$60=AM$1),0),$B32-1966)} -> 22553.54 | AN32: {=INDEX(GMWQ!$A$2:$LR$60,MATCH(1,(GMWQ!$LQ$2:$LQ$60=AN$3)*(GMWQ!$LP$2:$LP$60=AN$4)*(GMWQ!$LR$2:$LR$60=AN$1),0),$B32-1966)} -> 5656.473 | AO32: {=INDEX(GMWQ!$A$2:$LR$60,MATCH(1,(GMWQ!$LQ$2:$LQ$60=AO$3)*(GMWQ!$LP$2:$LP$60=AO$4)*(GMWQ!$LR$2:$LR$60=AO$1),0),$B32-1966)} -> 1176.22 | AP32: {=INDEX(GMWQ!$A$2:$LR$60,MATCH(1,(GMWQ!$LQ$2:$LQ$60=AP$3)*(GMWQ!$LP$2:$LP$60=AP$4)*(GMWQ!$LR$2:$LR$60=AP$1),0),$B32-1966)} -> -314.4558 | ... AU32: {=INDEX(GMWQ!$A$2:$LR$60,MATCH(1,(GMWQ!$LQ$2:$LQ$60=AU$3)*(GMWQ!$LP$2:$LP$60=AU$4)*(GMWQ!$LR$2:$LR$60=AU$1),0),$B32-1966)} -> 3513
B33: =+B32+1 -> 1999 | C33: {=INDEX(GMWQ!$A$2:$LR$60,MATCH(1,(GMWQ!$LQ$2:$LQ$60=C$3)*(GMWQ!$LP$2:$LP$60=C$4)*(GMWQ!$LR$2:$LR$60=C$1),0),$B33-1966)} -> 243369 | D33: {=INDEX(GMWQ!$A$2:$LR$60,MATCH(1,(GMWQ!$LQ$2:$LQ$60=D$3)*(GMWQ!$LP$2:$LP$60=D$4)*(GMWQ!$LR$2:$LR$60=D$1),0),$B33-1966)} -> 50.12706 | E33: {=INDEX(GMWQ!$A$2:$LR$60,MATCH(1,(GMWQ!$LQ$2:$LQ$60=E$3)*(GMWQ!$LP$2:$LP$60=E$4)*(GMWQ!$LR$2:$LR$60=E$1),0),$B33-1966)} -> 28.91059 | F33: {=INDEX(GMWQ!$A$2:$LR$60,MATCH(1,(GMWQ!$LQ$2:$LQ$60=F$3)*(GMWQ!$LP$2:$LP$60=F$4)*(GMWQ!$LR$2:$LR$60=F$1),0),$B33-1966)} -> 25749 | G33: {=INDEX(GMWQ!$A$2:$LR$60,MATCH(1,(GMWQ!$LQ$2:$LQ$60=G$3)*(GMWQ!$LP$2:$LP$60=G$4)*(GMWQ!$LR$2:$LR$60=G$1),0),$B33-1966)} -> 5382.502 | H33: {=INDEX(GMWQ!$A$2:$LR$60,MATCH(1,(GMWQ!$LQ$2:$LQ$60=H$3)*(GMWQ!$LP$2:$LP$60=H$4)*(GMWQ!$LR$2:$LR$60=H$1),0),$B33-1966)} -> 1258.576 | I33: {=INDEX(GMWQ!$A$2:$LR$60,MATCH(1,(GMWQ!$LQ$2:$LQ$60=I$3)*(GMWQ!$LP$2:$LP$60=I$4)*(GMWQ!$LR$2:$LR$60=I$1),0),$B33-1966)} -> 26.6988 | J33: {=INDEX(GMWQ!$A$2:$LR$60,MATCH(1,(GMWQ!$LQ$2:$LQ$60=J$3)*(GMWQ!$LP$2:$LP$60=J$4)*(GMWQ!$LR$2:$LR$60=J$1),0),$B33-1966)} -> 22593.14 | ... AG33: {=INDEX(GMWQ!$A$2:$LR$60,MATCH(1,(GMWQ!$LQ$2:$LQ$60=AG$3)*(GMWQ!$LP$2:$LP$60=AG$4)*(GMWQ!$LR$2:$LR$60=AG$1),0),$B33-1966)} -> -339.0139 | AI33: {=INDEX(GMWQ!$A$2:$LR$60,MATCH(1,(GMWQ!$LQ$2:$LQ$60=AI$3)*(GMWQ!$LP$2:$LP$60=AI$4)*(GMWQ!$LR$2:$LR$60=AI$1),0),$B33-1966)} -> 36483 | AJ33: {=INDEX(GMWQ!$A$2:$LR$60,MATCH(1,(GMWQ!$LQ$2:$LQ$60=AJ$3)*(GMWQ!$LP$2:$LP$60=AJ$4)*(GMWQ!$LR$2:$LR$60=AJ$1),0),$B33-1966)} -> 26.6988 | AK33: {=INDEX(GMWQ!$A$2:$LR$60,MATCH(1,(GMWQ!$LQ$2:$LQ$60=AK$3)*(GMWQ!$LP$2:$LP$60=AK$4)*(GMWQ!$LR$2:$LR$60=AK$1),0),$B33-1966)} -> 25749 | AL33: {=INDEX(GMWQ!$A$2:$LR$60,MATCH(1,(GMWQ!$LQ$2:$LQ$60=AL$3)*(GMWQ!$LP$2:$LP$60=AL$4)*(GMWQ!$LR$2:$LR$60=AL$1),0),$B33-1966)} -> 1139.682 | AM33: {=INDEX(GMWQ!$A$2:$LR$60,MATCH(1,(GMWQ!$LQ$2:$LQ$60=AM$3)*(GMWQ!$LP$2:$LP$60=AM$4)*(GMWQ!$LR$2:$LR$60=AM$1),0),$B33-1966)} -> 22593.14 | AN33: {=INDEX(GMWQ!$A$2:$LR$60,MATCH(1,(GMWQ!$LQ$2:$LQ$60=AN$3)*(GMWQ!$LP$2:$LP$60=AN$4)*(GMWQ!$LR$2:$LR$60=AN$1),0),$B33-1966)} -> 5382.502 | AO33: {=INDEX(GMWQ!$A$2:$LR$60,MATCH(1,(GMWQ!$LQ$2:$LQ$60=AO$3)*(GMWQ!$LP$2:$LP$60=AO$4)*(GMWQ!$LR$2:$LR$60=AO$1),0),$B33-1966)} -> 1258.576 | AP33: {=INDEX(GMWQ!$A$2:$LR$60,MATCH(1,(GMWQ!$LQ$2:$LQ$60=AP$3)*(GMWQ!$LP$2:$LP$60=AP$4)*(GMWQ!$LR$2:$LR$60=AP$1),0),$B33-1966)} -> -339.0139 | ... AU33: {=INDEX(GMWQ!$A$2:$LR$60,MATCH(1,(GMWQ!$LQ$2:$LQ$60=AU$3)*(GMWQ!$LP$2:$LP$60=AU$4)*(GMWQ!$LR$2:$LR$60=AU$1),0),$B33-1966)} -> 3857
B34: =+B33+1 -> 2000 | C34: {=INDEX(GMWQ!$A$2:$LR$60,MATCH(1,(GMWQ!$LQ$2:$LQ$60=C$3)*(GMWQ!$LP$2:$LP$60=C$4)*(GMWQ!$LR$2:$LR$60=C$1),0),$B34-1966)} -> 245858 | D34: {=INDEX(GMWQ!$A$2:$LR$60,MATCH(1,(GMWQ!$LQ$2:$LQ$60=D$3)*(GMWQ!$LP$2:$LP$60=D$4)*(GMWQ!$LR$2:$LR$60=D$1),0),$B34-1966)} -> 52.64415 | E34: {=INDEX(GMWQ!$A$2:$LR$60,MATCH(1,(GMWQ!$LQ$2:$LQ$60=E$3)*(GMWQ!$LP$2:$LP$60=E$4)*(GMWQ!$LR$2:$LR$60=E$1),0),$B34-1966)} -> 29.71873 | F34: {=INDEX(GMWQ!$A$2:$LR$60,MATCH(1,(GMWQ!$LQ$2:$LQ$60=F$3)*(GMWQ!$LP$2:$LP$60=F$4)*(GMWQ!$LR$2:$LR$60=F$1),0),$B34-1966)} -> 27095 | G34: {=INDEX(GMWQ!$A$2:$LR$60,MATCH(1,(GMWQ!$LQ$2:$LQ$60=G$3)*(GMWQ!$LP$2:$LP$60=G$4)*(GMWQ!$LR$2:$LR$60=G$1),0),$B34-1966)} -> 5196.557 | H34: {=INDEX(GMWQ!$A$2:$LR$60,MATCH(1,(GMWQ!$LQ$2:$LQ$60=H$3)*(GMWQ!$LP$2:$LP$60=H$4)*(GMWQ!$LR$2:$LR$60=H$1),0),$B34-1966)} -> 1329.318 | I34: {=INDEX(GMWQ!$A$2:$LR$60,MATCH(1,(GMWQ!$LQ$2:$LQ$60=I$3)*(GMWQ!$LP$2:$LP$60=I$4)*(GMWQ!$LR$2:$LR$60=I$1),0),$B34-1966)} -> 27.82758 | J34: {=INDEX(GMWQ!$A$2:$LR$60,MATCH(1,(GMWQ!$LQ$2:$LQ$60=J$3)*(GMWQ!$LP$2:$LP$60=J$4)*(GMWQ!$LR$2:$LR$60=J$1),0),$B34-1966)} -> 22610.24 | ... AG34: {=INDEX(GMWQ!$A$2:$LR$60,MATCH(1,(GMWQ!$LQ$2:$LQ$60=AG$3)*(GMWQ!$LP$2:$LP$60=AG$4)*(GMWQ!$LR$2:$LR$60=AG$1),0),$B34-1966)} -> -410.7907 | AI34: {=INDEX(GMWQ!$A$2:$LR$60,MATCH(1,(GMWQ!$LQ$2:$LQ$60=AI$3)*(GMWQ!$LP$2:$LP$60=AI$4)*(GMWQ!$LR$2:$LR$60=AI$1),0),$B34-1966)} -> 39802 | AJ34: {=INDEX(GMWQ!$A$2:$LR$60,MATCH(1,(GMWQ!$LQ$2:$LQ$60=AJ$3)*(GMWQ!$LP$2:$LP$60=AJ$4)*(GMWQ!$LR$2:$LR$60=AJ$1),0),$B34-1966)} -> 27.82758 | AK34: {=INDEX(GMWQ!$A$2:$LR$60,MATCH(1,(GMWQ!$LQ$2:$LQ$60=AK$3)*(GMWQ!$LP$2:$LP$60=AK$4)*(GMWQ!$LR$2:$LR$60=AK$1),0),$B34-1966)} -> 27095 | AL34: {=INDEX(GMWQ!$A$2:$LR$60,MATCH(1,(GMWQ!$LQ$2:$LQ$60=AL$3)*(GMWQ!$LP$2:$LP$60=AL$4)*(GMWQ!$LR$2:$LR$60=AL$1),0),$B34-1966)} -> 1198.351 | AM34: {=INDEX(GMWQ!$A$2:$LR$60,MATCH(1,(GMWQ!$LQ$2:$LQ$60=AM$3)*(GMWQ!$LP$2:$LP$60=AM$4)*(GMWQ!$LR$2:$LR$60=AM$1),0),$B34-1966)} -> 22610.24 | AN34: {=INDEX(GMWQ!$A$2:$LR$60,MATCH(1,(GMWQ!$LQ$2:$LQ$60=AN$3)*(GMWQ!$LP$2:$LP$60=AN$4)*(GMWQ!$LR$2:$LR$60=AN$1),0),$B34-1966)} -> 5196.557 | AO34: {=INDEX(GMWQ!$A$2:$LR$60,MATCH(1,(GMWQ!$LQ$2:$LQ$60=AO$3)*(GMWQ!$LP$2:$LP$60=AO$4)*(GMWQ!$LR$2:$LR$60=AO$1),0),$B34-1966)} -> 1329.318 | AP34: {=INDEX(GMWQ!$A$2:$LR$60,MATCH(1,(GMWQ!$LQ$2:$LQ$60=AP$3)*(GMWQ!$LP$2:$LP$60=AP$4)*(GMWQ!$LR$2:$LR$60=AP$1),0),$B34-1966)} -> -410.7907 | ... AU34: {=INDEX(GMWQ!$A$2:$LR$60,MATCH(1,(GMWQ!$LQ$2:$LQ$60=AU$3)*(GMWQ!$LP$2:$LP$60=AU$4)*(GMWQ!$LR$2:$LR$60=AU$1),0),$B34-1966)} -> 3563
A35: 1980 | B35: =+B34+1 -> 2001 | C35: {=INDEX(GMWQ!$A$2:$LR$60,MATCH(1,(GMWQ!$LQ$2:$LQ$60=C$3)*(GMWQ!$LP$2:$LP$60=C$4)*(GMWQ!$LR$2:$LR$60=C$1),0),$B35-1966)} -> 243513 | D35: {=INDEX(GMWQ!$A$2:$LR$60,MATCH(1,(GMWQ!$LQ$2:$LQ$60=D$3)*(GMWQ!$LP$2:$LP$60=D$4)*(GMWQ!$LR$2:$LR$60=D$1),0),$B35-1966)} -> 54.9067 | E35: {=INDEX(GMWQ!$A$2:$LR$60,MATCH(1,(GMWQ!$LQ$2:$LQ$60=E$3)*(GMWQ!$LP$2:$LP$60=E$4)*(GMWQ!$LR$2:$LR$60=E$1),0),$B35-1966)} -> 30.60508 | F35: {=INDEX(GMWQ!$A$2:$LR$60,MATCH(1,(GMWQ!$LQ$2:$LQ$60=F$3)*(GMWQ!$LP$2:$LP$60=F$4)*(GMWQ!$LR$2:$LR$60=F$1),0),$B35-1966)} -> 28290 | G35: {=INDEX(GMWQ!$A$2:$LR$60,MATCH(1,(GMWQ!$LQ$2:$LQ$60=G$3)*(GMWQ!$LP$2:$LP$60=G$4)*(GMWQ!$LR$2:$LR$60=G$1),0),$B35-1966)} -> 5988.8 | H35: {=INDEX(GMWQ!$A$2:$LR$60,MATCH(1,(GMWQ!$LQ$2:$LQ$60=H$3)*(GMWQ!$LP$2:$LP$60=H$4)*(GMWQ!$LR$2:$LR$60=H$1),0),$B35-1966)} -> 1354.659 | I35: {=INDEX(GMWQ!$A$2:$LR$60,MATCH(1,(GMWQ!$LQ$2:$LQ$60=I$3)*(GMWQ!$LP$2:$LP$60=I$4)*(GMWQ!$LR$2:$LR$60=I$1),0),$B35-1966)} -> 28.8795 | J35: {=INDEX(GMWQ!$A$2:$LR$60,MATCH(1,(GMWQ!$LQ$2:$LQ$60=J$3)*(GMWQ!$LP$2:$LP$60=J$4)*(GMWQ!$LR$2:$LR$60=J$1),0),$B35-1966)} -> 22512.13 | ... AG35: {=INDEX(GMWQ!$A$2:$LR$60,MATCH(1,(GMWQ!$LQ$2:$LQ$60=AG$3)*(GMWQ!$LP$2:$LP$60=AG$4)*(GMWQ!$LR$2:$LR$60=AG$1),0),$B35-1966)} -> -373.9535 | AI35: {=INDEX(GMWQ!$A$2:$LR$60,MATCH(1,(GMWQ!$LQ$2:$LQ$60=AI$3)*(GMWQ!$LP$2:$LP$60=AI$4)*(GMWQ!$LR$2:$LR$60=AI$1),0),$B35-1966)} -> 40290 | AJ35: {=INDEX(GMWQ!$A$2:$LR$60,MATCH(1,(GMWQ!$LQ$2:$LQ$60=AJ$3)*(GMWQ!$LP$2:$LP$60=AJ$4)*(GMWQ!$LR$2:$LR$60=AJ$1),0),$B35-1966)} -> 28.8795 | AK35: {=INDEX(GMWQ!$A$2:$LR$60,MATCH(1,(GMWQ!$LQ$2:$LQ$60=AK$3)*(GMWQ!$LP$2:$LP$60=AK$4)*(GMWQ!$LR$2:$LR$60=AK$1),0),$B35-1966)} -> 28290 | AL35: {=INDEX(GMWQ!$A$2:$LR$60,MATCH(1,(GMWQ!$LQ$2:$LQ$60=AL$3)*(GMWQ!$LP$2:$LP$60=AL$4)*(GMWQ!$LR$2:$LR$60=AL$1),0),$B35-1966)} -> 1256.656 | AM35: {=INDEX(GMWQ!$A$2:$LR$60,MATCH(1,(GMWQ!$LQ$2:$LQ$60=AM$3)*(GMWQ!$LP$2:$LP$60=AM$4)*(GMWQ!$LR$2:$LR$60=AM$1),0),$B35-1966)} -> 22512.13 | AN35: {=INDEX(GMWQ!$A$2:$LR$60,MATCH(1,(GMWQ!$LQ$2:$LQ$60=AN$3)*(GMWQ!$LP$2:$LP$60=AN$4)*(GMWQ!$LR$2:$LR$60=AN$1),0),$B35-1966)} -> 5988.8 | AO35: {=INDEX(GMWQ!$A$2:$LR$60,MATCH(1,(GMWQ!$LQ$2:$LQ$60=AO$3)*(GMWQ!$LP$2:$LP$60=AO$4)*(GMWQ!$LR$2:$LR$60=AO$1),0),$B35-1966)} -> 1354.659 | AP35: {=INDEX(GMWQ!$A$2:$LR$60,MATCH(1,(GMWQ!$LQ$2:$LQ$60=AP$3)*(GMWQ!$LP$2:$LP$60=AP$4)*(GMWQ!$LR$2:$LR$60=AP$1),0),$B35-1966)} -> -373.9535 | ... AU35: {=INDEX(GMWQ!$A$2:$LR$60,MATCH(1,(GMWQ!$LQ$2:$LQ$60=AU$3)*(GMWQ!$LP$2:$LP$60=AU$4)*(GMWQ!$LR$2:$LR$60=AU$1),0),$B35-1966)} -> 3435
B36: =+B35+1 -> 2002 | C36: {=INDEX(GMWQ!$A$2:$LR$60,MATCH(1,(GMWQ!$LQ$2:$LQ$60=C$3)*(GMWQ!$LP$2:$LP$60=C$4)*(GMWQ!$LR$2:$LR$60=C$1),0),$B36-1966)} -> 238722 | D36: {=INDEX(GMWQ!$A$2:$LR$60,MATCH(1,(GMWQ!$LQ$2:$LQ$60=D$3)*(GMWQ!$LP$2:$LP$60=D$4)*(GMWQ!$LR$2:$LR$60=D$1),0),$B36-1966)} -> 59.1701 | E36: {=INDEX(GMWQ!$A$2:$LR$60,MATCH(1,(GMWQ!$LQ$2:$LQ$60=E$3)*(GMWQ!$LP$2:$LP$60=E$4)*(GMWQ!$LR$2:$LR$60=E$1),0),$B36-1966)} -> 32.24743 | F36: {=INDEX(GMWQ!$A$2:$LR$60,MATCH(1,(GMWQ!$LQ$2:$LQ$60=F$3)*(GMWQ!$LP$2:$LP$60=F$4)*(GMWQ!$LR$2:$LR$60=F$1),0),$B36-1966)} -> 29578 | G36: {=INDEX(GMWQ!$A$2:$LR$60,MATCH(1,(GMWQ!$LQ$2:$LQ$60=G$3)*(GMWQ!$LP$2:$LP$60=G$4)*(GMWQ!$LR$2:$LR$60=G$1),0),$B36-1966)} -> 6311.235 | H36: {=INDEX(GMWQ!$A$2:$LR$60,MATCH(1,(GMWQ!$LQ$2:$LQ$60=H$3)*(GMWQ!$LP$2:$LP$60=H$4)*(GMWQ!$LR$2:$LR$60=H$1),0),$B36-1966)} -> 1520.428 | I36: {=INDEX(GMWQ!$A$2:$LR$60,MATCH(1,(GMWQ!$LQ$2:$LQ$60=I$3)*(GMWQ!$LP$2:$LP$60=I$4)*(GMWQ!$LR$2:$LR$60=I$1),0),$B36-1966)} -> 29.97508 | J36: {=INDEX(GMWQ!$A$2:$LR$60,MATCH(1,(GMWQ!$LQ$2:$LQ$60=J$3)*(GMWQ!$LP$2:$LP$60=J$4)*(GMWQ!$LR$2:$LR$60=J$1),0),$B36-1966)} -> 22394.21 | ... AG36: {=INDEX(GMWQ!$A$2:$LR$60,MATCH(1,(GMWQ!$LQ$2:$LQ$60=AG$3)*(GMWQ!$LP$2:$LP$60=AG$4)*(GMWQ!$LR$2:$LR$60=AG$1),0),$B36-1966)} -> -549.9536 | AI36: {=INDEX(GMWQ!$A$2:$LR$60,MATCH(1,(GMWQ!$LQ$2:$LQ$60=AI$3)*(GMWQ!$LP$2:$LP$60=AI$4)*(GMWQ!$LR$2:$LR$60=AI$1),0),$B36-1966)} -> 41818 | AJ36: {=INDEX(GMWQ!$A$2:$LR$60,MATCH(1,(GMWQ!$LQ$2:$LQ$60=AJ$3)*(GMWQ!$LP$2:$LP$60=AJ$4)*(GMWQ!$LR$2:$LR$60=AJ$1),0),$B36-1966)} -> 29.97508 | AK36: {=INDEX(GMWQ!$A$2:$LR$60,MATCH(1,(GMWQ!$LQ$2:$LQ$60=AK$3)*(GMWQ!$LP$2:$LP$60=AK$4)*(GMWQ!$LR$2:$LR$60=AK$1),0),$B36-1966)} -> 29578 | AL36: {=INDEX(GMWQ!$A$2:$LR$60,MATCH(1,(GMWQ!$LQ$2:$LQ$60=AL$3)*(GMWQ!$LP$2:$LP$60=AL$4)*(GMWQ!$LR$2:$LR$60=AL$1),0),$B36-1966)} -> 1320.788 | AM36: {=INDEX(GMWQ!$A$2:$LR$60,MATCH(1,(GMWQ!$LQ$2:$LQ$60=AM$3)*(GMWQ!$LP$2:$LP$60=AM$4)*(GMWQ!$LR$2:$LR$60=AM$1),0),$B36-1966)} -> 22394.21 | AN36: {=INDEX(GMWQ!$A$2:$LR$60,MATCH(1,(GMWQ!$LQ$2:$LQ$60=AN$3)*(GMWQ!$LP$2:$LP$60=AN$4)*(GMWQ!$LR$2:$LR$60=AN$1),0),$B36-1966)} -> 6311.235 | AO36: {=INDEX(GMWQ!$A$2:$LR$60,MATCH(1,(GMWQ!$LQ$2:$LQ$60=AO$3)*(GMWQ!$LP$2:$LP$60=AO$4)*(GMWQ!$LR$2:$LR$60=AO$1),0),$B36-1966)} -> 1520.428 | AP36: {=INDEX(GMWQ!$A$2:$LR$60,MATCH(1,(GMWQ!$LQ$2:$LQ$60=AP$3)*(GMWQ!$LP$2:$LP$60=AP$4)*(GMWQ!$LR$2:$LR$60=AP$1),0),$B36-1966)} -> -549.9536 | ... AU36: {=INDEX(GMWQ!$A$2:$LR$60,MATCH(1,(GMWQ!$LQ$2:$LQ$60=AU$3)*(GMWQ!$LP$2:$LP$60=AU$4)*(GMWQ!$LR$2:$LR$60=AU$1),0),$B36-1966)} -> 3591
B37: =+B36+1 -> 2003 | C37: {=INDEX(GMWQ!$A$2:$LR$60,MATCH(1,(GMWQ!$LQ$2:$LQ$60=C$3)*(GMWQ!$LP$2:$LP$60=C$4)*(GMWQ!$LR$2:$LR$60=C$1),0),$B37-1966)} -> 238432 | D37: {=INDEX(GMWQ!$A$2:$LR$60,MATCH(1,(GMWQ!$LQ$2:$LQ$60=D$3)*(GMWQ!$LP$2:$LP$60=D$4)*(GMWQ!$LR$2:$LR$60=D$1),0),$B37-1966)} -> 63.64214 | E37: {=INDEX(GMWQ!$A$2:$LR$60,MATCH(1,(GMWQ!$LQ$2:$LQ$60=E$3)*(GMWQ!$LP$2:$LP$60=E$4)*(GMWQ!$LR$2:$LR$60=E$1),0),$B37-1966)} -> 32.9513 | F37: {=INDEX(GMWQ!$A$2:$LR$60,MATCH(1,(GMWQ!$LQ$2:$LQ$60=F$3)*(GMWQ!$LP$2:$LP$60=F$4)*(GMWQ!$LR$2:$LR$60=F$1),0),$B37-1966)} -> 30485 | G37: {=INDEX(GMWQ!$A$2:$LR$60,MATCH(1,(GMWQ!$LQ$2:$LQ$60=G$3)*(GMWQ!$LP$2:$LP$60=G$4)*(GMWQ!$LR$2:$LR$60=G$1),0),$B37-1966)} -> 6455.639 | H37: {=INDEX(GMWQ!$A$2:$LR$60,MATCH(1,(GMWQ!$LQ$2:$LQ$60=H$3)*(GMWQ!$LP$2:$LP$60=H$4)*(GMWQ!$LR$2:$LR$60=H$1),0),$B37-1966)} -> 1585.891 | I37: {=INDEX(GMWQ!$A$2:$LR$60,MATCH(1,(GMWQ!$LQ$2:$LQ$60=I$3)*(GMWQ!$LP$2:$LP$60=I$4)*(GMWQ!$LR$2:$LR$60=I$1),0),$B37-1966)} -> 30.613 | J37: {=INDEX(GMWQ!$A$2:$LR$60,MATCH(1,(GMWQ!$LQ$2:$LQ$60=J$3)*(GMWQ!$LP$2:$LP$60=J$4)*(GMWQ!$LR$2:$LR$60=J$1),0),$B37-1966)} -> 22125.98 | ... AG37: {=INDEX(GMWQ!$A$2:$LR$60,MATCH(1,(GMWQ!$LQ$2:$LQ$60=AG$3)*(GMWQ!$LP$2:$LP$60=AG$4)*(GMWQ!$LR$2:$LR$60=AG$1),0),$B37-1966)} -> -447.6279 | AI37: {=INDEX(GMWQ!$A$2:$LR$60,MATCH(1,(GMWQ!$LQ$2:$LQ$60=AI$3)*(GMWQ!$LP$2:$LP$60=AI$4)*(GMWQ!$LR$2:$LR$60=AI$1),0),$B37-1966)} -> 43433 | AJ37: {=INDEX(GMWQ!$A$2:$LR$60,MATCH(1,(GMWQ!$LQ$2:$LQ$60=AJ$3)*(GMWQ!$LP$2:$LP$60=AJ$4)*(GMWQ!$LR$2:$LR$60=AJ$1),0),$B37-1966)} -> 30.613 | AK37: {=INDEX(GMWQ!$A$2:$LR$60,MATCH(1,(GMWQ!$LQ$2:$LQ$60=AK$3)*(GMWQ!$LP$2:$LP$60=AK$4)*(GMWQ!$LR$2:$LR$60=AK$1),0),$B37-1966)} -> 30485 | AL37: {=INDEX(GMWQ!$A$2:$LR$60,MATCH(1,(GMWQ!$LQ$2:$LQ$60=AL$3)*(GMWQ!$LP$2:$LP$60=AL$4)*(GMWQ!$LR$2:$LR$60=AL$1),0),$B37-1966)} -> 1377.792 | AM37: {=INDEX(GMWQ!$A$2:$LR$60,MATCH(1,(GMWQ!$LQ$2:$LQ$60=AM$3)*(GMWQ!$LP$2:$LP$60=AM$4)*(GMWQ!$LR$2:$LR$60=AM$1),0),$B37-1966)} -> 22125.98 | AN37: {=INDEX(GMWQ!$A$2:$LR$60,MATCH(1,(GMWQ!$LQ$2:$LQ$60=AN$3)*(GMWQ!$LP$2:$LP$60=AN$4)*(GMWQ!$LR$2:$LR$60=AN$1),0),$B37-1966)} -> 6455.639 | AO37: {=INDEX(GMWQ!$A$2:$LR$60,MATCH(1,(GMWQ!$LQ$2:$LQ$60=AO$3)*(GMWQ!$LP$2:$LP$60=AO$4)*(GMWQ!$LR$2:$LR$60=AO$1),0),$B37-1966)} -> 1585.891 | AP37: {=INDEX(GMWQ!$A$2:$LR$60,MATCH(1,(GMWQ!$LQ$2:$LQ$60=AP$3)*(GMWQ!$LP$2:$LP$60=AP$4)*(GMWQ!$LR$2:$LR$60=AP$1),0),$B37-1966)} -> -447.6279 | ... AU37: {=INDEX(GMWQ!$A$2:$LR$60,MATCH(1,(GMWQ!$LQ$2:$LQ$60=AU$3)*(GMWQ!$LP$2:$LP$60=AU$4)*(GMWQ!$LR$2:$LR$60=AU$1),0),$B37-1966)} -> 3465
B38: =+B37+1 -> 2004 | C38: {=INDEX(GMWQ!$A$2:$LR$60,MATCH(1,(GMWQ!$LQ$2:$LQ$60=C$3)*(GMWQ!$LP$2:$LP$60=C$4)*(GMWQ!$LR$2:$LR$60=C$1),0),$B38-1966)} -> 235866 | D38: {=INDEX(GMWQ!$A$2:$LR$60,MATCH(1,(GMWQ!$LQ$2:$LQ$60=D$3)*(GMWQ!$LP$2:$LP$60=D$4)*(GMWQ!$LR$2:$LR$60=D$1),0),$B38-1966)} -> 66.77174 | E38: {=INDEX(GMWQ!$A$2:$LR$60,MATCH(1,(GMWQ!$LQ$2:$LQ$60=E$3)*(GMWQ!$LP$2:$LP$60=E$4)*(GMWQ!$LR$2:$LR$60=E$1),0),$B38-1966)} -> 33.55088 | F38: {=INDEX(GMWQ!$A$2:$LR$60,MATCH(1,(GMWQ!$LQ$2:$LQ$60=F$3)*(GMWQ!$LP$2:$LP$60=F$4)*(GMWQ!$LR$2:$LR$60=F$1),0),$B38-1966)} -> 30980 | G38: {=INDEX(GMWQ!$A$2:$LR$60,MATCH(1,(GMWQ!$LQ$2:$LQ$60=G$3)*(GMWQ!$LP$2:$LP$60=G$4)*(GMWQ!$LR$2:$LR$60=G$1),0),$B38-1966)} -> 6646.529 | H38: {=INDEX(GMWQ!$A$2:$LR$60,MATCH(1,(GMWQ!$LQ$2:$LQ$60=H$3)*(GMWQ!$LP$2:$LP$60=H$4)*(GMWQ!$LR$2:$LR$60=H$1),0),$B38-1966)} -> 1588.002 | I38: {=INDEX(GMWQ!$A$2:$LR$60,MATCH(1,(GMWQ!$LQ$2:$LQ$60=I$3)*(GMWQ!$LP$2:$LP$60=I$4)*(GMWQ!$LR$2:$LR$60=I$1),0),$B38-1966)} -> 31.95255 | J38: {=INDEX(GMWQ!$A$2:$LR$60,MATCH(1,(GMWQ!$LQ$2:$LQ$60=J$3)*(GMWQ!$LP$2:$LP$60=J$4)*(GMWQ!$LR$2:$LR$60=J$1),0),$B38-1966)} -> 21831.63 | ... AG38: {=INDEX(GMWQ!$A$2:$LR$60,MATCH(1,(GMWQ!$LQ$2:$LQ$60=AG$3)*(GMWQ!$LP$2:$LP$60=AG$4)*(GMWQ!$LR$2:$LR$60=AG$1),0),$B38-1966)} -> -132.093 | AI38: {=INDEX(GMWQ!$A$2:$LR$60,MATCH(1,(GMWQ!$LQ$2:$LQ$60=AI$3)*(GMWQ!$LP$2:$LP$60=AI$4)*(GMWQ!$LR$2:$LR$60=AI$1),0),$B38-1966)} -> 44864 | AJ38: {=INDEX(GMWQ!$A$2:$LR$60,MATCH(1,(GMWQ!$LQ$2:$LQ$60=AJ$3)*(GMWQ!$LP$2:$LP$60=AJ$4)*(GMWQ!$LR$2:$LR$60=AJ$1),0),$B38-1966)} -> 31.95255 | AK38: {=INDEX(GMWQ!$A$2:$LR$60,MATCH(1,(GMWQ!$LQ$2:$LQ$60=AK$3)*(GMWQ!$LP$2:$LP$60=AK$4)*(GMWQ!$LR$2:$LR$60=AK$1),0),$B38-1966)} -> 30980 | AL38: {=INDEX(GMWQ!$A$2:$LR$60,MATCH(1,(GMWQ!$LQ$2:$LQ$60=AL$3)*(GMWQ!$LP$2:$LP$60=AL$4)*(GMWQ!$LR$2:$LR$60=AL$1),0),$B38-1966)} -> 1419.042 | AM38: {=INDEX(GMWQ!$A$2:$LR$60,MATCH(1,(GMWQ!$LQ$2:$LQ$60=AM$3)*(GMWQ!$LP$2:$LP$60=AM$4)*(GMWQ!$LR$2:$LR$60=AM$1),0),$B38-1966)} -> 21831.63 | AN38: {=INDEX(GMWQ!$A$2:$LR$60,MATCH(1,(GMWQ!$LQ$2:$LQ$60=AN$3)*(GMWQ!$LP$2:$LP$60=AN$4)*(GMWQ!$LR$2:$LR$60=AN$1),0),$B38-1966)} -> 6646.529 | AO38: {=INDEX(GMWQ!$A$2:$LR$60,MATCH(1,(GMWQ!$LQ$2:$LQ$60=AO$3)*(GMWQ!$LP$2:$LP$60=AO$4)*(GMWQ!$LR$2:$LR$60=AO$1),0),$B38-1966)} -> 1588.002 | AP38: {=INDEX(GMWQ!$A$2:$LR$60,MATCH(1,(GMWQ!$LQ$2:$LQ$60=AP$3)*(GMWQ!$LP$2:$LP$60=AP$4)*(GMWQ!$LR$2:$LR$60=AP$1),0),$B38-1966)} -> -132.093 | ... AU38: {=INDEX(GMWQ!$A$2:$LR$60,MATCH(1,(GMWQ!$LQ$2:$LQ$60=AU$3)*(GMWQ!$LP$2:$LP$60=AU$4)*(GMWQ!$LR$2:$LR$60=AU$1),0),$B38-1966)} -> 3626
A39: 1981 | B39: =+B38+1 -> 2005 | C39: {=INDEX(GMWQ!$A$2:$LR$60,MATCH(1,(GMWQ!$LQ$2:$LQ$60=C$3)*(GMWQ!$LP$2:$LP$60=C$4)*(GMWQ!$LR$2:$LR$60=C$1),0),$B39-1966)} -> 235712 | D39: {=INDEX(GMWQ!$A$2:$LR$60,MATCH(1,(GMWQ!$LQ$2:$LQ$60=D$3)*(GMWQ!$LP$2:$LP$60=D$4)*(GMWQ!$LR$2:$LR$60=D$1),0),$B39-1966)} -> 67.32769 | E39: {=INDEX(GMWQ!$A$2:$LR$60,MATCH(1,(GMWQ!$LQ$2:$LQ$60=E$3)*(GMWQ!$LP$2:$LP$60=E$4)*(GMWQ!$LR$2:$LR$60=E$1),0),$B39-1966)} -> 34.3851 | F39: {=INDEX(GMWQ!$A$2:$LR$60,MATCH(1,(GMWQ!$LQ$2:$LQ$60=F$3)*(GMWQ!$LP$2:$LP$60=F$4)*(GMWQ!$LR$2:$LR$60=F$1),0),$B39-1966)} -> 31183 | G39: {=INDEX(GMWQ!$A$2:$LR$60,MATCH(1,(GMWQ!$LQ$2:$LQ$60=G$3)*(GMWQ!$LP$2:$LP$60=G$4)*(GMWQ!$LR$2:$LR$60=G$1),0),$B39-1966)} -> 6531.797 | H39: {=INDEX(GMWQ!$A$2:$LR$60,MATCH(1,(GMWQ!$LQ$2:$LQ$60=H$3)*(GMWQ!$LP$2:$LP$60=H$4)*(GMWQ!$LR$2:$LR$60=H$1),0),$B39-1966)} -> 1571.109 | I39: {=INDEX(GMWQ!$A$2:$LR$60,MATCH(1,(GMWQ!$LQ$2:$LQ$60=I$3)*(GMWQ!$LP$2:$LP$60=I$4)*(GMWQ!$LR$2:$LR$60=I$1),0),$B39-1966)} -> 32.74662 | J39: {=INDEX(GMWQ!$A$2:$LR$60,MATCH(1,(GMWQ!$LQ$2:$LQ$60=J$3)*(GMWQ!$LP$2:$LP$60=J$4)*(GMWQ!$LR$2:$LR$60=J$1),0),$B39-1966)} -> 21568.8 | ... AG39: {=INDEX(GMWQ!$A$2:$LR$60,MATCH(1,(GMWQ!$LQ$2:$LQ$60=AG$3)*(GMWQ!$LP$2:$LP$60=AG$4)*(GMWQ!$LR$2:$LR$60=AG$1),0),$B39-1966)} -> -440.2605 | AI39: {=INDEX(GMWQ!$A$2:$LR$60,MATCH(1,(GMWQ!$LQ$2:$LQ$60=AI$3)*(GMWQ!$LP$2:$LP$60=AI$4)*(GMWQ!$LR$2:$LR$60=AI$1),0),$B39-1966)} -> 46552 | AJ39: {=INDEX(GMWQ!$A$2:$LR$60,MATCH(1,(GMWQ!$LQ$2:$LQ$60=AJ$3)*(GMWQ!$LP$2:$LP$60=AJ$4)*(GMWQ!$LR$2:$LR$60=AJ$1),0),$B39-1966)} -> 32.74662 | AK39: {=INDEX(GMWQ!$A$2:$LR$60,MATCH(1,(GMWQ!$LQ$2:$LQ$60=AK$3)*(GMWQ!$LP$2:$LP$60=AK$4)*(GMWQ!$LR$2:$LR$60=AK$1),0),$B39-1966)} -> 31183 | AL39: {=INDEX(GMWQ!$A$2:$LR$60,MATCH(1,(GMWQ!$LQ$2:$LQ$60=AL$3)*(GMWQ!$LP$2:$LP$60=AL$4)*(GMWQ!$LR$2:$LR$60=AL$1),0),$B39-1966)} -> 1445.746 | AM39: {=INDEX(GMWQ!$A$2:$LR$60,MATCH(1,(GMWQ!$LQ$2:$LQ$60=AM$3)*(GMWQ!$LP$2:$LP$60=AM$4)*(GMWQ!$LR$2:$LR$60=AM$1),0),$B39-1966)} -> 21568.8 | AN39: {=INDEX(GMWQ!$A$2:$LR$60,MATCH(1,(GMWQ!$LQ$2:$LQ$60=AN$3)*(GMWQ!$LP$2:$LP$60=AN$4)*(GMWQ!$LR$2:$LR$60=AN$1),0),$B39-1966)} -> 6531.797 | AO39: {=INDEX(GMWQ!$A$2:$LR$60,MATCH(1,(GMWQ!$LQ$2:$LQ$60=AO$3)*(GMWQ!$LP$2:$LP$60=AO$4)*(GMWQ!$LR$2:$LR$60=AO$1),0),$B39-1966)} -> 1571.109 | AP39: {=INDEX(GMWQ!$A$2:$LR$60,MATCH(1,(GMWQ!$LQ$2:$LQ$60=AP$3)*(GMWQ!$LP$2:$LP$60=AP$4)*(GMWQ!$LR$2:$LR$60=AP$1),0),$B39-1966)} -> -440.2605 | ... AU39: {=INDEX(GMWQ!$A$2:$LR$60,MATCH(1,(GMWQ!$LQ$2:$LQ$60=AU$3)*(GMWQ!$LP$2:$LP$60=AU$4)*(GMWQ!$LR$2:$LR$60=AU$1),0),$B39-1966)} -> 3256
B40: =+B39+1 -> 2006 | C40: {=INDEX(GMWQ!$A$2:$LR$60,MATCH(1,(GMWQ!$LQ$2:$LQ$60=C$3)*(GMWQ!$LP$2:$LP$60=C$4)*(GMWQ!$LR$2:$LR$60=C$1),0),$B40-1966)} -> 236272 | D40: {=INDEX(GMWQ!$A$2:$LR$60,MATCH(1,(GMWQ!$LQ$2:$LQ$60=D$3)*(GMWQ!$LP$2:$LP$60=D$4)*(GMWQ!$LR$2:$LR$60=D$1),0),$B40-1966)} -> 69.61449 | E40: {=INDEX(GMWQ!$A$2:$LR$60,MATCH(1,(GMWQ!$LQ$2:$LQ$60=E$3)*(GMWQ!$LP$2:$LP$60=E$4)*(GMWQ!$LR$2:$LR$60=E$1),0),$B40-1966)} -> 36.07959 | F40: {=INDEX(GMWQ!$A$2:$LR$60,MATCH(1,(GMWQ!$LQ$2:$LQ$60=F$3)*(GMWQ!$LP$2:$LP$60=F$4)*(GMWQ!$LR$2:$LR$60=F$1),0),$B40-1966)} -> 31633 | G40: {=INDEX(GMWQ!$A$2:$LR$60,MATCH(1,(GMWQ!$LQ$2:$LQ$60=G$3)*(GMWQ!$LP$2:$LP$60=G$4)*(GMWQ!$LR$2:$LR$60=G$1),0),$B40-1966)} -> 7261.729 | H40: {=INDEX(GMWQ!$A$2:$LR$60,MATCH(1,(GMWQ!$LQ$2:$LQ$60=H$3)*(GMWQ!$LP$2:$LP$60=H$4)*(GMWQ!$LR$2:$LR$60=H$1),0),$B40-1966)} -> 1901.591 | I40: {=INDEX(GMWQ!$A$2:$LR$60,MATCH(1,(GMWQ!$LQ$2:$LQ$60=I$3)*(GMWQ!$LP$2:$LP$60=I$4)*(GMWQ!$LR$2:$LR$60=I$1),0),$B40-1966)} -> 33.66289 | J40: {=INDEX(GMWQ!$A$2:$LR$60,MATCH(1,(GMWQ!$LQ$2:$LQ$60=J$3)*(GMWQ!$LP$2:$LP$60=J$4)*(GMWQ!$LR$2:$LR$60=J$1),0),$B40-1966)} -> 21358.17 | ... AG40: {=INDEX(GMWQ!$A$2:$LR$60,MATCH(1,(GMWQ!$LQ$2:$LQ$60=AG$3)*(GMWQ!$LP$2:$LP$60=AG$4)*(GMWQ!$LR$2:$LR$60=AG$1),0),$B40-1966)} -> -510.2141 | AI40: {=INDEX(GMWQ!$A$2:$LR$60,MATCH(1,(GMWQ!$LQ$2:$LQ$60=AI$3)*(GMWQ!$LP$2:$LP$60=AI$4)*(GMWQ!$LR$2:$LR$60=AI$1),0),$B40-1966)} -> 47036 | AJ40: {=INDEX(GMWQ!$A$2:$LR$60,MATCH(1,(GMWQ!$LQ$2:$LQ$60=AJ$3)*(GMWQ!$LP$2:$LP$60=AJ$4)*(GMWQ!$LR$2:$LR$60=AJ$1),0),$B40-1966)} -> 33.66289 | AK40: {=INDEX(GMWQ!$A$2:$LR$60,MATCH(1,(GMWQ!$LQ$2:$LQ$60=AK$3)*(GMWQ!$LP$2:$LP$60=AK$4)*(GMWQ!$LR$2:$LR$60=AK$1),0),$B40-1966)} -> 31633 | AL40: {=INDEX(GMWQ!$A$2:$LR$60,MATCH(1,(GMWQ!$LQ$2:$LQ$60=AL$3)*(GMWQ!$LP$2:$LP$60=AL$4)*(GMWQ!$LR$2:$LR$60=AL$1),0),$B40-1966)} -> 1481.073 | AM40: {=INDEX(GMWQ!$A$2:$LR$60,MATCH(1,(GMWQ!$LQ$2:$LQ$60=AM$3)*(GMWQ!$LP$2:$LP$60=AM$4)*(GMWQ!$LR$2:$LR$60=AM$1),0),$B40-1966)} -> 21358.17 | AN40: {=INDEX(GMWQ!$A$2:$LR$60,MATCH(1,(GMWQ!$LQ$2:$LQ$60=AN$3)*(GMWQ!$LP$2:$LP$60=AN$4)*(GMWQ!$LR$2:$LR$60=AN$1),0),$B40-1966)} -> 7261.729 | AO40: {=INDEX(GMWQ!$A$2:$LR$60,MATCH(1,(GMWQ!$LQ$2:$LQ$60=AO$3)*(GMWQ!$LP$2:$LP$60=AO$4)*(GMWQ!$LR$2:$LR$60=AO$1),0),$B40-1966)} -> 1901.591 | AP40: {=INDEX(GMWQ!$A$2:$LR$60,MATCH(1,(GMWQ!$LQ$2:$LQ$60=AP$3)*(GMWQ!$LP$2:$LP$60=AP$4)*(GMWQ!$LR$2:$LR$60=AP$1),0),$B40-1966)} -> -510.2141 | ... AU40: {=INDEX(GMWQ!$A$2:$LR$60,MATCH(1,(GMWQ!$LQ$2:$LQ$60=AU$3)*(GMWQ!$LP$2:$LP$60=AU$4)*(GMWQ!$LR$2:$LR$60=AU$1),0),$B40-1966)} -> 3654
B41: =+B40+1 -> 2007 | C41: {=INDEX(GMWQ!$A$2:$LR$60,MATCH(1,(GMWQ!$LQ$2:$LQ$60=C$3)*(GMWQ!$LP$2:$LP$60=C$4)*(GMWQ!$LR$2:$LR$60=C$1),0),$B41-1966)} -> 238846 | D41: {=INDEX(GMWQ!$A$2:$LR$60,MATCH(1,(GMWQ!$LQ$2:$LQ$60=D$3)*(GMWQ!$LP$2:$LP$60=D$4)*(GMWQ!$LR$2:$LR$60=D$1),0),$B41-1966)} -> 73.35294 | E41: {=INDEX(GMWQ!$A$2:$LR$60,MATCH(1,(GMWQ!$LQ$2:$LQ$60=E$3)*(GMWQ!$LP$2:$LP$60=E$4)*(GMWQ!$LR$2:$LR$60=E$1),0),$B41-1966)} -> 36.73131 | F41: {=INDEX(GMWQ!$A$2:$LR$60,MATCH(1,(GMWQ!$LQ$2:$LQ$60=F$3)*(GMWQ!$LP$2:$LP$60=F$4)*(GMWQ!$LR$2:$LR$60=F$1),0),$B41-1966)} -> 32287 | G41: {=INDEX(GMWQ!$A$2:$LR$60,MATCH(1,(GMWQ!$LQ$2:$LQ$60=G$3)*(GMWQ!$LP$2:$LP$60=G$4)*(GMWQ!$LR$2:$LR$60=G$1),0),$B41-1966)} -> 7530.755 | H41: {=INDEX(GMWQ!$A$2:$LR$60,MATCH(1,(GMWQ!$LQ$2:$LQ$60=H$3)*(GMWQ!$LP$2:$LP$60=H$4)*(GMWQ!$LR$2:$LR$60=H$1),0),$B41-1966)} -> 1979.724 | I41: {=INDEX(GMWQ!$A$2:$LR$60,MATCH(1,(GMWQ!$LQ$2:$LQ$60=I$3)*(GMWQ!$LP$2:$LP$60=I$4)*(GMWQ!$LR$2:$LR$60=I$1),0),$B41-1966)} -> 34.45231 | J41: {=INDEX(GMWQ!$A$2:$LR$60,MATCH(1,(GMWQ!$LQ$2:$LQ$60=J$3)*(GMWQ!$LP$2:$LP$60=J$4)*(GMWQ!$LR$2:$LR$60=J$1),0),$B41-1966)} -> 21247.46 | ... AG41: {=INDEX(GMWQ!$A$2:$LR$60,MATCH(1,(GMWQ!$LQ$2:$LQ$60=AG$3)*(GMWQ!$LP$2:$LP$60=AG$4)*(GMWQ!$LR$2:$LR$60=AG$1),0),$B41-1966)} -> -453.6558 | AI41: {=INDEX(GMWQ!$A$2:$LR$60,MATCH(1,(GMWQ!$LQ$2:$LQ$60=AI$3)*(GMWQ!$LP$2:$LP$60=AI$4)*(GMWQ!$LR$2:$LR$60=AI$1),0),$B41-1966)} -> 47924 | AJ41: {=INDEX(GMWQ!$A$2:$LR$60,MATCH(1,(GMWQ!$LQ$2:$LQ$60=AJ$3)*(GMWQ!$LP$2:$LP$60=AJ$4)*(GMWQ!$LR$2:$LR$60=AJ$1),0),$B41-1966)} -> 34.45231 | AK41: {=INDEX(GMWQ!$A$2:$LR$60,MATCH(1,(GMWQ!$LQ$2:$LQ$60=AK$3)*(GMWQ!$LP$2:$LP$60=AK$4)*(GMWQ!$LR$2:$LR$60=AK$1),0),$B41-1966)} -> 32287 | AL41: {=INDEX(GMWQ!$A$2:$LR$60,MATCH(1,(GMWQ!$LQ$2:$LQ$60=AL$3)*(GMWQ!$LP$2:$LP$60=AL$4)*(GMWQ!$LR$2:$LR$60=AL$1),0),$B41-1966)} -> 1519.57 | AM41: {=INDEX(GMWQ!$A$2:$LR$60,MATCH(1,(GMWQ!$LQ$2:$LQ$60=AM$3)*(GMWQ!$LP$2:$LP$60=AM$4)*(GMWQ!$LR$2:$LR$60=AM$1),0),$B41-1966)} -> 21247.46 | AN41: {=INDEX(GMWQ!$A$2:$LR$60,MATCH(1,(GMWQ!$LQ$2:$LQ$60=AN$3)*(GMWQ!$LP$2:$LP$60=AN$4)*(GMWQ!$LR$2:$LR$60=AN$1),0),$B41-1966)} -> 7530.755 | AO41: {=INDEX(GMWQ!$A$2:$LR$60,MATCH(1,(GMWQ!$LQ$2:$LQ$60=AO$3)*(GMWQ!$LP$2:$LP$60=AO$4)*(GMWQ!$LR$2:$LR$60=AO$1),0),$B41-1966)} -> 1979.724 | AP41: {=INDEX(GMWQ!$A$2:$LR$60,MATCH(1,(GMWQ!$LQ$2:$LQ$60=AP$3)*(GMWQ!$LP$2:$LP$60=AP$4)*(GMWQ!$LR$2:$LR$60=AP$1),0),$B41-1966)} -> -453.6558 | ... AU41: {=INDEX(GMWQ!$A$2:$LR$60,MATCH(1,(GMWQ!$LQ$2:$LQ$60=AU$3)*(GMWQ!$LP$2:$LP$60=AU$4)*(GMWQ!$LR$2:$LR$60=AU$1),0),$B41-1966)} -> 3941
B42: =+B41+1 -> 2008 | C42: {=INDEX(GMWQ!$A$2:$LR$60,MATCH(1,(GMWQ!$LQ$2:$LQ$60=C$3)*(GMWQ!$LP$2:$LP$60=C$4)*(GMWQ!$LR$2:$LR$60=C$1),0),$B42-1966)} -> 239131 | D42: {=INDEX(GMWQ!$A$2:$LR$60,MATCH(1,(GMWQ!$LQ$2:$LQ$60=D$3)*(GMWQ!$LP$2:$LP$60=D$4)*(GMWQ!$LR$2:$LR$60=D$1),0),$B42-1966)} -> 76.17709 | E42: {=INDEX(GMWQ!$A$2:$LR$60,MATCH(1,(GMWQ!$LQ$2:$LQ$60=E$3)*(GMWQ!$LP$2:$LP$60=E$4)*(GMWQ!$LR$2:$LR$60=E$1),0),$B42-1966)} -> 37.43518 | F42: {=INDEX(GMWQ!$A$2:$LR$60,MATCH(1,(GMWQ!$LQ$2:$LQ$60=F$3)*(GMWQ!$LP$2:$LP$60=F$4)*(GMWQ!$LR$2:$LR$60=F$1),0),$B42-1966)} -> 32870 | G42: {=INDEX(GMWQ!$A$2:$LR$60,MATCH(1,(GMWQ!$LQ$2:$LQ$60=G$3)*(GMWQ!$LP$2:$LP$60=G$4)*(GMWQ!$LR$2:$LR$60=G$1),0),$B42-1966)} -> 7308.215 | H42: {=INDEX(GMWQ!$A$2:$LR$60,MATCH(1,(GMWQ!$LQ$2:$LQ$60=H$3)*(GMWQ!$LP$2:$LP$60=H$4)*(GMWQ!$LR$2:$LR$60=H$1),0),$B42-1966)} -> 2046.242 | I42: {=INDEX(GMWQ!$A$2:$LR$60,MATCH(1,(GMWQ!$LQ$2:$LQ$60=I$3)*(GMWQ!$LP$2:$LP$60=I$4)*(GMWQ!$LR$2:$LR$60=I$1),0),$B42-1966)} -> 35.56507 | J42: {=INDEX(GMWQ!$A$2:$LR$60,MATCH(1,(GMWQ!$LQ$2:$LQ$60=J$3)*(GMWQ!$LP$2:$LP$60=J$4)*(GMWQ!$LR$2:$LR$60=J$1),0),$B42-1966)} -> 21063.83 | ... AG42: {=INDEX(GMWQ!$A$2:$LR$60,MATCH(1,(GMWQ!$LQ$2:$LQ$60=AG$3)*(GMWQ!$LP$2:$LP$60=AG$4)*(GMWQ!$LR$2:$LR$60=AG$1),0),$B42-1966)} -> -637.8419 | AI42: {=INDEX(GMWQ!$A$2:$LR$60,MATCH(1,(GMWQ!$LQ$2:$LQ$60=AI$3)*(GMWQ!$LP$2:$LP$60=AI$4)*(GMWQ!$LR$2:$LR$60=AI$1),0),$B42-1966)} -> 49843 | AJ42: {=INDEX(GMWQ!$A$2:$LR$60,MATCH(1,(GMWQ!$LQ$2:$LQ$60=AJ$3)*(GMWQ!$LP$2:$LP$60=AJ$4)*(GMWQ!$LR$2:$LR$60=AJ$1),0),$B42-1966)} -> 35.56507 | AK42: {=INDEX(GMWQ!$A$2:$LR$60,MATCH(1,(GMWQ!$LQ$2:$LQ$60=AK$3)*(GMWQ!$LP$2:$LP$60=AK$4)*(GMWQ!$LR$2:$LR$60=AK$1),0),$B42-1966)} -> 32870 | AL42: {=INDEX(GMWQ!$A$2:$LR$60,MATCH(1,(GMWQ!$LQ$2:$LQ$60=AL$3)*(GMWQ!$LP$2:$LP$60=AL$4)*(GMWQ!$LR$2:$LR$60=AL$1),0),$B42-1966)} -> 1560.495 | AM42: {=INDEX(GMWQ!$A$2:$LR$60,MATCH(1,(GMWQ!$LQ$2:$LQ$60=AM$3)*(GMWQ!$LP$2:$LP$60=AM$4)*(GMWQ!$LR$2:$LR$60=AM$1),0),$B42-1966)} -> 21063.83 | AN42: {=INDEX(GMWQ!$A$2:$LR$60,MATCH(1,(GMWQ!$LQ$2:$LQ$60=AN$3)*(GMWQ!$LP$2:$LP$60=AN$4)*(GMWQ!$LR$2:$LR$60=AN$1),0),$B42-1966)} -> 7308.215 | AO42: {=INDEX(GMWQ!$A$2:$LR$60,MATCH(1,(GMWQ!$LQ$2:$LQ$60=AO$3)*(GMWQ!$LP$2:$LP$60=AO$4)*(GMWQ!$LR$2:$LR$60=AO$1),0),$B42-1966)} -> 2046.242 | AP42: {=INDEX(GMWQ!$A$2:$LR$60,MATCH(1,(GMWQ!$LQ$2:$LQ$60=AP$3)*(GMWQ!$LP$2:$LP$60=AP$4)*(GMWQ!$LR$2:$LR$60=AP$1),0),$B42-1966)} -> -637.8419 | ... AU42: {=INDEX(GMWQ!$A$2:$LR$60,MATCH(1,(GMWQ!$LQ$2:$LQ$60=AU$3)*(GMWQ!$LP$2:$LP$60=AU$4)*(GMWQ!$LR$2:$LR$60=AU$1),0),$B42-1966)} -> 4019
A43: 1982 | B43: =+B42+1 -> 2009 | C43: {=INDEX(GMWQ!$A$2:$LR$60,MATCH(1,(GMWQ!$LQ$2:$LQ$60=C$3)*(GMWQ!$LP$2:$LP$60=C$4)*(GMWQ!$LR$2:$LR$60=C$1),0),$B43-1966)} -> 239578 | D43: {=INDEX(GMWQ!$A$2:$LR$60,MATCH(1,(GMWQ!$LQ$2:$LQ$60=D$3)*(GMWQ!$LP$2:$LP$60=D$4)*(GMWQ!$LR$2:$LR$60=D$1),0),$B43-1966)} -> 76.58652 | E43: {=INDEX(GMWQ!$A$2:$LR$60,MATCH(1,(GMWQ!$LQ$2:$LQ$60=E$3)*(GMWQ!$LP$2:$LP$60=E$4)*(GMWQ!$LR$2:$LR$60=E$1),0),$B43-1966)} -> 37.87835 | F43: {=INDEX(GMWQ!$A$2:$LR$60,MATCH(1,(GMWQ!$LQ$2:$LQ$60=F$3)*(GMWQ!$LP$2:$LP$60=F$4)*(GMWQ!$LR$2:$LR$60=F$1),0),$B43-1966)} -> 33383 | G43: {=INDEX(GMWQ!$A$2:$LR$60,MATCH(1,(GMWQ!$LQ$2:$LQ$60=G$3)*(GMWQ!$LP$2:$LP$60=G$4)*(GMWQ!$LR$2:$LR$60=G$1),0),$B43-1966)} -> 7852.202 | H43: {=INDEX(GMWQ!$A$2:$LR$60,MATCH(1,(GMWQ!$LQ$2:$LQ$60=H$3)*(GMWQ!$LP$2:$LP$60=H$4)*(GMWQ!$LR$2:$LR$60=H$1),0),$B43-1966)} -> 2010.343 | I43: {=INDEX(GMWQ!$A$2:$LR$60,MATCH(1,(GMWQ!$LQ$2:$LQ$60=I$3)*(GMWQ!$LP$2:$LP$60=I$4)*(GMWQ!$LR$2:$LR$60=I$1),0),$B43-1966)} -> 36.35804 | J43: {=INDEX(GMWQ!$A$2:$LR$60,MATCH(1,(GMWQ!$LQ$2:$LQ$60=J$3)*(GMWQ!$LP$2:$LP$60=J$4)*(GMWQ!$LR$2:$LR$60=J$1),0),$B43-1966)} -> 21012.52 | ... AG43: {=INDEX(GMWQ!$A$2:$LR$60,MATCH(1,(GMWQ!$LQ$2:$LQ$60=AG$3)*(GMWQ!$LP$2:$LP$60=AG$4)*(GMWQ!$LR$2:$LR$60=AG$1),0),$B43-1966)} -> -414.3256 | AI43: {=INDEX(GMWQ!$A$2:$LR$60,MATCH(1,(GMWQ!$LQ$2:$LQ$60=AI$3)*(GMWQ!$LP$2:$LP$60=AI$4)*(GMWQ!$LR$2:$LR$60=AI$1),0),$B43-1966)} -> 50837 | AJ43: {=INDEX(GMWQ!$A$2:$LR$60,MATCH(1,(GMWQ!$LQ$2:$LQ$60=AJ$3)*(GMWQ!$LP$2:$LP$60=AJ$4)*(GMWQ!$LR$2:$LR$60=AJ$1),0),$B43-1966)} -> 36.35804 | AK43: {=INDEX(GMWQ!$A$2:$LR$60,MATCH(1,(GMWQ!$LQ$2:$LQ$60=AK$3)*(GMWQ!$LP$2:$LP$60=AK$4)*(GMWQ!$LR$2:$LR$60=AK$1),0),$B43-1966)} -> 33383 | AL43: {=INDEX(GMWQ!$A$2:$LR$60,MATCH(1,(GMWQ!$LQ$2:$LQ$60=AL$3)*(GMWQ!$LP$2:$LP$60=AL$4)*(GMWQ!$LR$2:$LR$60=AL$1),0),$B43-1966)} -> 1588.719 | AM43: {=INDEX(GMWQ!$A$2:$LR$60,MATCH(1,(GMWQ!$LQ$2:$LQ$60=AM$3)*(GMWQ!$LP$2:$LP$60=AM$4)*(GMWQ!$LR$2:$LR$60=AM$1),0),$B43-1966)} -> 21012.52 | AN43: {=INDEX(GMWQ!$A$2:$LR$60,MATCH(1,(GMWQ!$LQ$2:$LQ$60=AN$3)*(GMWQ!$LP$2:$LP$60=AN$4)*(GMWQ!$LR$2:$LR$60=AN$1),0),$B43-1966)} -> 7852.202 | AO43: {=INDEX(GMWQ!$A$2:$LR$60,MATCH(1,(GMWQ!$LQ$2:$LQ$60=AO$3)*(GMWQ!$LP$2:$LP$60=AO$4)*(GMWQ!$LR$2:$LR$60=AO$1),0),$B43-1966)} -> 2010.343 | AP43: {=INDEX(GMWQ!$A$2:$LR$60,MATCH(1,(GMWQ!$LQ$2:$LQ$60=AP$3)*(GMWQ!$LP$2:$LP$60=AP$4)*(GMWQ!$LR$2:$LR$60=AP$1),0),$B43-1966)} -> -414.3256 | ... AU43: {=INDEX(GMWQ!$A$2:$LR$60,MATCH(1,(GMWQ!$LQ$2:$LQ$60=AU$3)*(GMWQ!$LP$2:$LP$60=AU$4)*(GMWQ!$LR$2:$LR$60=AU$1),0),$B43-1966)} -> 3241
B44: =+B43+1 -> 2010 | C44: {=INDEX(GMWQ!$A$2:$LR$60,MATCH(1,(GMWQ!$LQ$2:$LQ$60=C$3)*(GMWQ!$LP$2:$LP$60=C$4)*(GMWQ!$LR$2:$LR$60=C$1),0),$B44-1966)} -> 242095 | D44: {=INDEX(GMWQ!$A$2:$LR$60,MATCH(1,(GMWQ!$LQ$2:$LQ$60=D$3)*(GMWQ!$LP$2:$LP$60=D$4)*(GMWQ!$LR$2:$LR$60=D$1),0),$B44-1966)} -> 78.91912 | E44: {=INDEX(GMWQ!$A$2:$LR$60,MATCH(1,(GMWQ!$LQ$2:$LQ$60=E$3)*(GMWQ!$LP$2:$LP$60=E$4)*(GMWQ!$LR$2:$LR$60=E$1),0),$B44-1966)} -> 39.1818 | F44: {=INDEX(GMWQ!$A$2:$LR$60,MATCH(1,(GMWQ!$LQ$2:$LQ$60=F$3)*(GMWQ!$LP$2:$LP$60=F$4)*(GMWQ!$LR$2:$LR$60=F$1),0),$B44-1966)} -> 33923 | G44: {=INDEX(GMWQ!$A$2:$LR$60,MATCH(1,(GMWQ!$LQ$2:$LQ$60=G$3)*(GMWQ!$LP$2:$LP$60=G$4)*(GMWQ!$LR$2:$LR$60=G$1),0),$B44-1966)} -> 7675.159 | H44: {=INDEX(GMWQ!$A$2:$LR$60,MATCH(1,(GMWQ!$LQ$2:$LQ$60=H$3)*(GMWQ!$LP$2:$LP$60=H$4)*(GMWQ!$LR$2:$LR$60=H$1),0),$B44-1966)} -> 2374.613 | I44: {=INDEX(GMWQ!$A$2:$LR$60,MATCH(1,(GMWQ!$LQ$2:$LQ$60=I$3)*(GMWQ!$LP$2:$LP$60=I$4)*(GMWQ!$LR$2:$LR$60=I$1),0),$B44-1966)} -> 36.98296 | J44: {=INDEX(GMWQ!$A$2:$LR$60,MATCH(1,(GMWQ!$LQ$2:$LQ$60=J$3)*(GMWQ!$LP$2:$LP$60=J$4)*(GMWQ!$LR$2:$LR$60=J$1),0),$B44-1966)} -> 20916.21 | ... AG44: {=INDEX(GMWQ!$A$2:$LR$60,MATCH(1,(GMWQ!$LQ$2:$LQ$60=AG$3)*(GMWQ!$LP$2:$LP$60=AG$4)*(GMWQ!$LR$2:$LR$60=AG$1),0),$B44-1966)} -> -734.3257 | AI44: {=INDEX(GMWQ!$A$2:$LR$60,MATCH(1,(GMWQ!$LQ$2:$LQ$60=AI$3)*(GMWQ!$LP$2:$LP$60=AI$4)*(GMWQ!$LR$2:$LR$60=AI$1),0),$B44-1966)} -> 52380 | AJ44: {=INDEX(GMWQ!$A$2:$LR$60,MATCH(1,(GMWQ!$LQ$2:$LQ$60=AJ$3)*(GMWQ!$LP$2:$LP$60=AJ$4)*(GMWQ!$LR$2:$LR$60=AJ$1),0),$B44-1966)} -> 36.98296 | AK44: {=INDEX(GMWQ!$A$2:$LR$60,MATCH(1,(GMWQ!$LQ$2:$LQ$60=AK$3)*(GMWQ!$LP$2:$LP$60=AK$4)*(GMWQ!$LR$2:$LR$60=AK$1),0),$B44-1966)} -> 33923 | AL44: {=INDEX(GMWQ!$A$2:$LR$60,MATCH(1,(GMWQ!$LQ$2:$LQ$60=AL$3)*(GMWQ!$LP$2:$LP$60=AL$4)*(GMWQ!$LR$2:$LR$60=AL$1),0),$B44-1966)} -> 1621.852 | AM44: {=INDEX(GMWQ!$A$2:$LR$60,MATCH(1,(GMWQ!$LQ$2:$LQ$60=AM$3)*(GMWQ!$LP$2:$LP$60=AM$4)*(GMWQ!$LR$2:$LR$60=AM$1),0),$B44-1966)} -> 20916.21 | AN44: {=INDEX(GMWQ!$A$2:$LR$60,MATCH(1,(GMWQ!$LQ$2:$LQ$60=AN$3)*(GMWQ!$LP$2:$LP$60=AN$4)*(GMWQ!$LR$2:$LR$60=AN$1),0),$B44-1966)} -> 7675.159 | AO44: {=INDEX(GMWQ!$A$2:$LR$60,MATCH(1,(GMWQ!$LQ$2:$LQ$60=AO$3)*(GMWQ!$LP$2:$LP$60=AO$4)*(GMWQ!$LR$2:$LR$60=AO$1),0),$B44-1966)} -> 2374.613 | AP44: {=INDEX(GMWQ!$A$2:$LR$60,MATCH(1,(GMWQ!$LQ$2:$LQ$60=AP$3)*(GMWQ!$LP$2:$LP$60=AP$4)*(GMWQ!$LR$2:$LR$60=AP$1),0),$B44-1966)} -> -734.3257 | ... AU44: {=INDEX(GMWQ!$A$2:$LR$60,MATCH(1,(GMWQ!$LQ$2:$LQ$60=AU$3)*(GMWQ!$LP$2:$LP$60=AU$4)*(GMWQ!$LR$2:$LR$60=AU$1),0),$B44-1966)} -> 4141
