Workbook
Name _DLX1.INC: HAVERM!$A$1:$W$6
Name _DLX2.INC: HAVERQ!$A$1:$S$6
Name Annual_Data: GMWA!$A$1:$A$2

Sheet >> CHARTS

Sheet >> DATA

Sheet Chart Data
A1: Potential output | L1: GDP by decade | O1: Migration | V1: Working age population | AC1: Population ageing | AN1: Employment change by age band since Q4 2009 | AX1: Inactivity | BE1: Output per hour worked long-term (5yr ma) | BQ1: Output per worker long-term (5yr ma) | CC1: Potential output vs BoE/OBR - 2024-2028 | CH1: GDP forecasts - LT
W2: Working age population (LHS) | Z2: State pension age - males (RHS) | AA2: State pension age - females (RHS) | BB2: Levels | CO2: growth rates
B3: ESTAR * AVHR | C3: EDUC / POP15_64 | D3: K | E3: TREND | F3: YHAT | G3: GDP | I3: Potential output | J3: GDP | M3: Decade average | P3: Historical | Q3: OE baseline (ONS low migration variant) | R3: ONS principal projection | S3: ONS high migration variant | T3: Average 2010-2019 | W3: Working age population | X3: Rolling 10 year average | Y3: ZERO LINE | Z3: State pension age - males | AA3: State pension age - females | AD3: 2023 | AE3: 2030 | AF3: 2040 | AG3: 2050 | AJ3: {=TRANSPOSE('ONS pop proj 2021-based'!B230:B232)} -> 0-15 | AK3: 16-64 | AL3: 65+ | AO3: 16-24 | AP3: 25-34 | AQ3: 35-49 | AR3: 50-64 | AS3: 65+ | AT3: Total | AV3: Check | AY3: % of inactive | AZ3: Average 1993-2023 | BB3: LT sick | BC3: Other | BF3: 5yr ma | BG3: 1972-2007 average | BH3: 2008-2019 average | BI3: ZERO LINE | BL3: Pre-GFC trend calc | BO3: GFC-pandemic | BR3: 5yr ma | BS3: 1972-2007 average | BT3: 2008-2019 average | BU3: ZERO LINE | BX3: Pre-GFC trend calc | CA3: GFC-pandemic | CD3: Oxford Economics | CE3: Office for Budget Responsibility | CF3: Bank of England * | CI3: OE | CJ3: OBR | CK3: 100 LINE | CM3: Difference | CO3: OBR
A4: 1980 | B4: =DataA!F14*DataA!G14 -> 24.76553 | C4: =DataA!H14/DataA!I14 -> 8.4961659 | D4: =DataA!E14 -> 1149523 | E4: =DataA!J14 -> -1.978074 | F4: =DataA!D14 -> 975762 | G4: =DataA!B14 -> 956533 | L4: 1910 | M4: =100*(('BoE A8. UK Real GDP(A)'!D237/'BoE A8. UK Real GDP(A)'!D227)^(1/10)-1) -> 1.4233534 | O4: 2000 | P4: ='[1]2021-based'!H7 -> 139.3 | V4: 1974 | W4: =100*((DataA!M8/DataA!M7)-1) -> 0.028023783 | Y4: 0 | Z4: 65 | AA4: 60 | AC4: 0 | AD4: ='ONS pop proj 2021-based'!E2+'ONS pop proj 2021-based'!E109 -> 665729 | AE4: ='ONS pop proj 2021-based'!L2+'ONS pop proj 2021-based'!L109 -> 730321 | AF4: ='ONS pop proj 2021-based'!V2+'ONS pop proj 2021-based'!V109 -> 751416 | AG4: ='ONS pop proj 2021-based'!AF2+'ONS pop proj 2021-based'!AF109 -> 747150 | AI4: 2010 | AJ4: =('ONS pop est 2010'!B9+'ONS pop est 2010'!B16+'ONS pop est 2010'!B23+'ONS pop est 2010'!B31)/'ONS pop est 2010'!B7 -> 0.18643956 | AK4: =1-AL4-AJ4 -> 0.6480566 | AL4: =('ONS pop est 2010'!G37+'ONS pop est 2010'!G44+'ONS pop est 2010'!G51+'ONS pop est 2010'!G58+'ONS pop est 2010'!G65+'ONS pop est 2010'!G72)/'ONS pop est 2010'!B7 -> 0.16550384 | AN4: 40179 | AO4: =HAVERQ!F167-HAVERQ!F$166 -> -21 | AP4: =HAVERQ!G167-HAVERQ!G$166 -> -35 | AQ4: =HAVERQ!H167-HAVERQ!H$166 -> -87 | AR4: =HAVERQ!I167-HAVERQ!I$166 -> 44 | AS4: =HAVERQ!J167-HAVERQ!J$166 -> 10 | AT4: =SUM(AO4:AS4) -> -89 | AV4: =HAVERQ!D167-HAVERQ!D$166-'Chart Data'!AT4 -> 0 | AX4: 33970 | AZ4: =AVERAGE($AY$7:$AY$374) -> 24.595806 | BE4: 1971 | BG4: =$BL$6 -> 2.2155011 | BI4: 0 | BK4: 1971 | BL4: =AVERAGE(HAVERQ!B11:B14) -> 43.675 | BN4: 2007 | BO4: =AVERAGE(HAVERQ!B155:B158) -> 96.125 | BQ4: 1971 | BS4: =$BX$6 -> 1.9448021 | BU4: 0 | BW4: 1971 | BX4: =AVERAGE(HAVERQ!C11:C14) -> 47.975 | BZ4: 2007 | CA4: =AVERAGE(HAVERQ!C155:C158) -> 95.975 | CC4: Labour | CD4: =0.65*(100*((B52/B47)^(1/5)-1)) -> 0.83941879 | CE4: ='OBR AS23 - C2.7'!C35+'OBR AS23 - C2.7'!D35 -> 0.66521683 | CF4: =AVERAGE('MPR Feb24 - Chart 3.1'!D10:D12) -> 0.46666667 | CH4: 2015 | CI4: =100*(DataA!B49/DataA!$B$53) -> 92.732062 | CJ4: =CI4 -> 92.732062 | CK4: 100 | CM4: =100*((CJ4/CI4)-1) -> 0
A5: 1981 | B5: =DataA!F15*DataA!G15 -> 24.65965 | C5: =DataA!H15/DataA!I15 -> 8.5228971 | D5: =DataA!E15 -> 1157411 | E5: =DataA!J15 -> -1.965721 | F5: =DataA!D15 -> 990112 | G5: =DataA!B15 -> 949961 | I5: =100*((F5/F4)-1) -> 1.4706455 | J5: =100*((G5/G4)-1) -> -0.68706464 | L5: 1920 | M5: =100*(('BoE A8. UK Real GDP(A)'!D247/'BoE A8. UK Real GDP(A)'!D237)^(1/10)-1) -> 0.79533427 | O5: 2001 | P5: ='[1]2021-based'!H8 -> 153.2 | V5: 1975 | W5: =100*((DataA!M9/DataA!M8)-1) -> -0.015228704 | Y5: 0 | Z5: 65 | AA5: 60 | AC5: 1 | AD5: ='ONS pop proj 2021-based'!E3+'ONS pop proj 2021-based'!E110 -> 700228 | AE5: ='ONS pop proj 2021-based'!L3+'ONS pop proj 2021-based'!L110 -> 734201 | AF5: ='ONS pop proj 2021-based'!V3+'ONS pop proj 2021-based'!V110 -> 751454 | AG5: ='ONS pop proj 2021-based'!AF3+'ONS pop proj 2021-based'!AF110 -> 754216 | AN5: 40269 | AO5: =HAVERQ!F168-HAVERQ!F$166 -> 26 | AP5: =HAVERQ!G168-HAVERQ!G$166 -> 52 | AQ5: =HAVERQ!H168-HAVERQ!H$166 -> -72 | AR5: =HAVERQ!I168-HAVERQ!I$166 -> 32 | AS5: =HAVERQ!J168-HAVERQ!J$166 -> 54 | AT5: =SUM(AO5:AS5) -> 92 | AV5: =HAVERQ!D168-HAVERQ!D$166-'Chart Data'!AT5 -> -2 | AX5: 34001 | AZ5: =AVERAGE($AY$7:$AY$374) -> 24.595806 | BG5: =$BL$6 -> 2.2155011 | BI5: 0 | BK5: 2007 | BL5: =AVERAGE(HAVERQ!B155:B158) -> 96.125 | BN5: 2023 | BO5: =AVERAGE(HAVERQ!B219:B222) -> 102.26825 | BS5: =$BX$6 -> 1.9448021 | BU5: 0 | BW5: 2007 | BX5: =AVERAGE(HAVERQ!C155:C158) -> 95.975 | BZ5: 2019 | CA5: =AVERAGE(HAVERQ!C203:C206) -> 99.975 | CC5: Productivity | CD5: =CD6-CD4 -> 0.77999694 | CE5: =+'OBR AS23 - C2.7'!E35+'OBR AS23 - C2.7'!F35 -> 0.95453827 | CF5: =AVERAGE('MPR Feb24 - Chart 3.1'!C10:C12) -> 0.7 | CH5: 2016 | CI5: =100*(DataA!B50/DataA!$B$53) -> 94.513503 | CJ5: =CI5 -> 94.513503 | CK5: 100 | CM5: =100*((CJ5/CI5)-1) -> 0
A6: 1982 | B6: =DataA!F16*DataA!G16 -> 24.29771 | C6: =DataA!H16/DataA!I16 -> 8.5398108 | D6: =DataA!E16 -> 1167835 | E6: =DataA!J16 -> -1.953444 | F6: =DataA!D16 -> 996004.9 | G6: =DataA!B16 -> 968629 | I6: =100*((F6/F5)-1) -> 0.59517509 | J6: =100*((G6/G5)-1) -> 1.9651333 | L6: 1930 | M6: =100*(('BoE A8. UK Real GDP(A)'!D257/'BoE A8. UK Real GDP(A)'!D247)^(1/10)-1) -> 2.0461093 | O6: 2002 | P6: ='[1]2021-based'!H9 -> 190.9 | V6: 1976 | W6: =100*((DataA!M10/DataA!M9)-1) -> 0.10264916 | Y6: 0 | Z6: 65 | AA6: 60 | AC6: 2 | AD6: ='ONS pop proj 2021-based'!E4+'ONS pop proj 2021-based'!E111 -> 691721 | AE6: ='ONS pop proj 2021-based'!L4+'ONS pop proj 2021-based'!L111 -> 739401 | AF6: ='ONS pop proj 2021-based'!V4+'ONS pop proj 2021-based'!V111 -> 752653 | AG6: ='ONS pop proj 2021-based'!AF4+'ONS pop proj 2021-based'!AF111 -> 762458 | AI6: {=TRANSPOSE('ONS pop proj 2021-based'!E1:AF1)} -> 2023 | AJ6: {=TRANSPOSE('ONS pop proj 2021-based'!E230:AF232)} -> 0.17987297 | AK6: 0.63099918 | AL6: 0.18912785 | AN6: 40360 | AO6: =HAVERQ!F169-HAVERQ!F$166 -> 75 | AP6: =HAVERQ!G169-HAVERQ!G$166 -> 97 | AQ6: =HAVERQ!H169-HAVERQ!H$166 -> -83 | AR6: =HAVERQ!I169-HAVERQ!I$166 -> 107 | AS6: =HAVERQ!J169-HAVERQ!J$166 -> 88 | AT6: =SUM(AO6:AS6) -> 284 | AV6: =HAVERQ!D169-HAVERQ!D$166-'Chart Data'!AT6 -> -1 | AX6: 34029 | AZ6: =AVERAGE($AY$7:$AY$374) -> 24.595806 | BG6: =$BL$6 -> 2.2155011 | BI6: 0 | BK6: y/y | BL6: =100*((BL5/BL4)^(1/36)-1) -> 2.2155011 | BN6: y/y | BO6: =100*((BO5/BO4)^(1/16)-1) -> 0.38793701 | BS6: =$BX$6 -> 1.9448021 | BU6: 0 | BW6: y/y | BX6: =100*((BX5/BX4)^(1/36)-1) -> 1.9448021 | BZ6: y/y | CA6: =100*((CA5/CA4)^(1/12)-1) -> 0.34084969 | CC6: Potential output | CD6: =100*((DataA!D62/DataA!D57)^(1/5)-1) -> 1.6194157 | CE6: ='OBR AS23 - C2.7'!G35 -> 1.6197551 | CF6: =AVERAGE('MPR Feb24 - Chart 3.1'!B10:B12) -> 1.1666667 | CH6: 2017 | CI6: =100*(DataA!B51/DataA!$B$53) -> 97.022903 | CJ6: =CI6 -> 97.022903 | CK6: 100 | CM6: =100*((CJ6/CI6)-1) -> 0
A7: 1983 | B7: =DataA!F17*DataA!G17 -> 24.30468 | C7: =DataA!H17/DataA!I17 -> 8.5563186 | D7: =DataA!E17 -> 1180230 | E7: =DataA!J17 -> -1.941244 | F7: =DataA!D17 -> 1012416 | G7: =DataA!B17 -> 1008981 | I7: =100*((F7/F6)-1) -> 1.6476927 | J7: =100*((G7/G6)-1) -> 4.1658881 | L7: 1940 | M7: =100*(('BoE A8. UK Real GDP(A)'!D267/'BoE A8. UK Real GDP(A)'!D257)^(1/10)-1) -> 1.4936364 | O7: 2003 | P7: ='[1]2021-based'!H10 -> 194.3 | V7: 1977 | W7: =100*((DataA!M11/DataA!M10)-1) -> 0.58379587 | Y7: 0 | Z7: 65 | AA7: 60 | AC7: 3 | AD7: ='ONS pop proj 2021-based'!E5+'ONS pop proj 2021-based'!E112 -> 719113 | AE7: ='ONS pop proj 2021-based'!L5+'ONS pop proj 2021-based'!L112 -> 742134 | AF7: ='ONS pop proj 2021-based'!V5+'ONS pop proj 2021-based'!V112 -> 751976 | AG7: ='ONS pop proj 2021-based'!AF5+'ONS pop proj 2021-based'!AF112 -> 768470 | AI7: 2024 | AJ7: 0.17770521 | AK7: 0.63152053 | AL7: 0.19077426 | AN7: 40452 | AO7: =HAVERQ!F170-HAVERQ!F$166 -> -8 | AP7: =HAVERQ!G170-HAVERQ!G$166 -> 142 | AQ7: =HAVERQ!H170-HAVERQ!H$166 -> -103 | AR7: =HAVERQ!I170-HAVERQ!I$166 -> 84 | AS7: =HAVERQ!J170-HAVERQ!J$166 -> 109 | AT7: =SUM(AO7:AS7) -> 224 | AV7: =HAVERQ!D170-HAVERQ!D$166-'Chart Data'!AT7 -> -2 | AX7: 34060 | AY7: =100*(HAVERM!C46/HAVERM!B46) -> 21.187332 | AZ7: =AVERAGE($AY$7:$AY$374) -> 24.595806 | BB7: =HAVERM!C46 -> 1813 | BC7: =HAVERM!B46-HAVERM!C46 -> 6744 | BG7: =$BL$6 -> 2.2155011 | BI7: 0 | BK7: q/q | BL7: =100*((BL5/BL4)^(1/144)-1) -> 0.5493322 | BN7: q/q | BO7: =100*((BO5/BO4)^(1/64)-1) -> 0.096843481 | BS7: =$BX$6 -> 1.9448021 | BU7: 0 | BW7: q/q | BX7: =100*((BX5/BX4)^(1/144)-1) -> 0.48269436 | BZ7: q/q | CA7: =100*((CA5/CA4)^(1/48)-1) -> 0.085103722 | CF7: =+CD6-CF6 -> 0.45274907 | CH7: 2018 | CI7: =100*(DataA!B52/DataA!$B$53) -> 98.384903 | CJ7: =CI7 -> 98.384903 | CK7: 100 | CM7: =100*((CJ7/CI7)-1) -> 0
A8: 1984 | B8: =DataA!F18*DataA!G18 -> 24.9108 | C8: =DataA!H18/DataA!I18 -> 8.5981658 | D8: =DataA!E18 -> 1202767 | E8: =DataA!J18 -> -1.929121 | F8: =DataA!D18 -> 1047849 | G8: =DataA!B18 -> 1031385 | I8: =100*((F8/F7)-1) -> 3.4998459 | J8: =100*((G8/G7)-1) -> 2.2204581 | L8: 1950 | M8: =100*(('BoE A8. UK Real GDP(A)'!D277/'BoE A8. UK Real GDP(A)'!D267)^(1/10)-1) -> 3.1113357 | O8: 2004 | P8: ='[1]2021-based'!H11 -> 209.5 | V8: 1978 | W8: =100*((DataA!M12/DataA!M11)-1) -> 0.62030177 | Y8: 0 | Z8: 65 | AA8: 60 | AC8: 4 | AD8: ='ONS pop proj 2021-based'!E6+'ONS pop proj 2021-based'!E113 -> 732580 | AE8: ='ONS pop proj 2021-based'!L6+'ONS pop proj 2021-based'!L113 -> 743188 | AF8: ='ONS pop proj 2021-based'!V6+'ONS pop proj 2021-based'!V113 -> 750860 | AG8: ='ONS pop proj 2021-based'!AF6+'ONS pop proj 2021-based'!AF113 -> 773414 | AI8: 2025 | AJ8: 0.17578298 | AK8: 0.63154095 | AL8: 0.19267607 | AN8: 40544 | AO8: =HAVERQ!F171-HAVERQ!F$166 -> -2 | AP8: =HAVERQ!G171-HAVERQ!G$166 -> 180 | AQ8: =HAVERQ!H171-HAVERQ!H$166 -> -100 | AR8: =HAVERQ!I171-HAVERQ!I$166 -> 144 | AS8: =HAVERQ!J171-HAVERQ!J$166 -> 118 | AT8: =SUM(AO8:AS8) -> 340 | AV8: =HAVERQ!D171-HAVERQ!D$166-'Chart Data'!AT8 -> -1 | AX8: 34090 | AY8: =100*(HAVERM!C47/HAVERM!B47) -> 21.412726 | AZ8: =AVERAGE($AY$7:$AY$374) -> 24.595806 | BB8: =HAVERM!C47 -> 1834 | BC8: =HAVERM!B47-HAVERM!C47 -> 6731 | BE8: 1972 | BG8: =$BL$6 -> 2.2155011 | BI8: 0 | BQ8: 1972 | BS8: =$BX$6 -> 1.9448021 | BU8: 0 | CH8: 2019 | CI8: =100*(DataA!B53/DataA!$B$53) -> 100 | CJ8: =CI8 -> 100 | CK8: 100 | CM8: =100*((CJ8/CI8)-1) -> 0
A9: 1985 | B9: =DataA!F19*DataA!G19 -> 25.10787 | C9: =DataA!H19/DataA!I19 -> 8.6987754 | D9: =DataA!E19 -> 1226994 | E9: =DataA!J19 -> -1.917073 | F9: =DataA!D19 -> 1076968 | G9: =DataA!B19 -> 1073547 | I9: =100*((F9/F8)-1) -> 2.7789309 | J9: =100*((G9/G8)-1) -> 4.0879012 | L9: 1960 | M9: =100*(('BoE A8. UK Real GDP(A)'!D287/'BoE A8. UK Real GDP(A)'!D277)^(1/10)-1) -> 3.4155468 | O9: 2005 | P9: ='[1]2021-based'!H12 -> 335.6 | V9: 1979 | W9: =100*((DataA!M13/DataA!M12)-1) -> 0.61644762 | Y9: 0 | Z9: 65 | AA9: 60 | AC9: 5 | AD9: ='ONS pop proj 2021-based'!E7+'ONS pop proj 2021-based'!E114 -> 744262 | AE9: ='ONS pop proj 2021-based'!L7+'ONS pop proj 2021-based'!L114 -> 743139 | AF9: ='ONS pop proj 2021-based'!V7+'ONS pop proj 2021-based'!V114 -> 751083 | AG9: ='ONS pop proj 2021-based'!AF7+'ONS pop proj 2021-based'!AF114 -> 777784 | AI9: 2026 | AJ9: 0.17389989 | AK9: 0.63106006 | AL9: 0.19504004 | AN9: 40634 | AO9: =HAVERQ!F172-HAVERQ!F$166 -> 11 | AP9: =HAVERQ!G172-HAVERQ!G$166 -> 165 | AQ9: =HAVERQ!H172-HAVERQ!H$166 -> -109 | AR9: =HAVERQ!I172-HAVERQ!I$166 -> 162 | AS9: =HAVERQ!J172-HAVERQ!J$166 -> 117 | AT9: =SUM(AO9:AS9) -> 346 | AV9: =HAVERQ!D172-HAVERQ!D$166-'Chart Data'!AT9 -> -1 | AX9: 34121 | AY9: =100*(HAVERM!C48/HAVERM!B48) -> 21.681261 | AZ9: =AVERAGE($AY$7:$AY$374) -> 24.595806 | BB9: =HAVERM!C48 -> 1857 | BC9: =HAVERM!B48-HAVERM!C48 -> 6708 | BG9: =$BL$6 -> 2.2155011 | BI9: 0 | BS9: =$BX$6 -> 1.9448021 | BU9: 0 | CH9: 2020 | CI9: =100*(DataA!B54/DataA!$B$53) -> 89.640099 | CJ9: =CI9 -> 89.640099 | CK9: 100 | CM9: =100*((CJ9/CI9)-1) -> 0
A10: 1986 | B10: =DataA!F20*DataA!G20 -> 846672.61 | C10: =DataA!H20/DataA!I20 -> 8.8112396 | D10: =DataA!E20 -> 1246573 | E10: =DataA!J20 -> -1.905234 | F10: =DataA!D20 -> 1104492 | G10: =DataA!B20 -> 1106912 | I10: =100*((F10/F9)-1) -> 2.5556934 | J10: =100*((G10/G9)-1) -> 3.1079217 | L10: 1970 | M10: =100*(('BoE A8. UK Real GDP(A)'!D297/'BoE A8. UK Real GDP(A)'!D287)^(1/10)-1) -> 2.6038111 | O10: 2006 | P10: ='[1]2021-based'!H13 -> 254.5 | V10: 1980 | W10: =100*((DataA!M14/DataA!M13)-1) -> 0.61267083 | Y10: 0 | Z10: 65 | AA10: 60 | AC10: 6 | AD10: ='ONS pop proj 2021-based'!E8+'ONS pop proj 2021-based'!E115 -> 762489 | AE10: ='ONS pop proj 2021-based'!L8+'ONS pop proj 2021-based'!L115 -> 738873 | AF10: ='ONS pop proj 2021-based'!V8+'ONS pop proj 2021-based'!V115 -> 752658 | AG10: ='ONS pop proj 2021-based'!AF8+'ONS pop proj 2021-based'!AF115 -> 780457 | AI10: 2027 | AJ10: 0.17190755 | AK10: 0.63027351 | AL10: 0.19781894 | AN10: 40725 | AO10: =HAVERQ!F173-HAVERQ!F$166 -> -87 | AP10: =HAVERQ!G173-HAVERQ!G$166 -> 142 | AQ10: =HAVERQ!H173-HAVERQ!H$166 -> -138 | AR10: =HAVERQ!I173-HAVERQ!I$166 -> 182 | AS10: =HAVERQ!J173-HAVERQ!J$166 -> 83 | AT10: =SUM(AO10:AS10) -> 182 | AV10: =HAVERQ!D173-HAVERQ!D$166-'Chart Data'!AT10 -> -1 | AX10: 34151 | AY10: =100*(HAVERM!C49/HAVERM!B49) -> 21.949802 | AZ10: =AVERAGE($AY$7:$AY$374) -> 24.595806 | BB10: =HAVERM!C49 -> 1889 | BC10: =HAVERM!B49-HAVERM!C49 -> 6717 | BG10: =$BL$6 -> 2.2155011 | BI10: 0 | BS10: =$BX$6 -> 1.9448021 | BU10: 0 | CH10: 2021 | CI10: =100*(DataA!B55/DataA!$B$53) -> 97.416292 | CJ10: =CI10 -> 97.416292 | CK10: 100 | CM10: =100*((CJ10/CI10)-1) -> 0
A11: 1987 | B11: =DataA!F21*DataA!G21 -> 854924.91 | C11: =DataA!H21/DataA!I21 -> 8.9162753 | D11: =DataA!E21 -> 1274603 | E11: =DataA!J21 -> -1.894 | F11: =DataA!D21 -> 1135284 | G11: =DataA!B21 -> 1166905 | I11: =100*((F11/F10)-1) -> 2.787888 | J11: =100*((G11/G10)-1) -> 5.4198527 | L11: 1980 | M11: =100*((DataA!B23/DataA!B13)^(1/10)-1) -> 2.5744037 | O11: 2007 | P11: ='[1]2021-based'!H14 -> 304.6 | V11: 1981 | W11: =100*((DataA!M15/DataA!M14)-1) -> 0.57075665 | Y11: 0 | Z11: 65 | AA11: 60 | AC11: 7 | AD11: ='ONS pop proj 2021-based'!E9+'ONS pop proj 2021-based'!E116 -> 785492 | AE11: ='ONS pop proj 2021-based'!L9+'ONS pop proj 2021-based'!L116 -> 696386 | AF11: ='ONS pop proj 2021-based'!V9+'ONS pop proj 2021-based'!V116 -> 754625 | AG11: ='ONS pop proj 2021-based'!AF9+'ONS pop proj 2021-based'!AF116 -> 781599 | AI11: 2028 | AJ11: 0.17002282 | AK11: 0.62909493 | AL11: 0.20088225 | AN11: 40817 | AO11: =HAVERQ!F174-HAVERQ!F$166 -> -81 | AP11: =HAVERQ!G174-HAVERQ!G$166 -> 159 | AQ11: =HAVERQ!H174-HAVERQ!H$166 -> -137 | AR11: =HAVERQ!I174-HAVERQ!I$166 -> 197 | AS11: =HAVERQ!J174-HAVERQ!J$166 -> 109 | AT11: =SUM(AO11:AS11) -> 247 | AV11: =HAVERQ!D174-HAVERQ!D$166-'Chart Data'!AT11 -> 0 | AX11: 34182 | AY11: =100*(HAVERM!C50/HAVERM!B50) -> 21.950367 | AZ11: =AVERAGE($AY$7:$AY$374) -> 24.595806 | BB11: =HAVERM!C50 -> 1884 | BC11: =HAVERM!B50-HAVERM!C50 -> 6699 | BG11: =$BL$6 -> 2.2155011 | BI11: 0 | BS11: =$BX$6 -> 1.9448021 | BU11: 0 | CH11: 2022 | CI11: =100*(DataA!B56/DataA!$B$53) -> 101.64925 | CJ11: =CJ10*(1+CO11/100) -> 101.65055 | CK11: 100 | CM11: =100*((CJ11/CI11)-1) -> 0.0012771032 | CO11: {=TRANSPOSE('OBR AS23 - TA.1'!C8:I8)} -> 4.3465614
A12: 1988 | B12: =DataA!F22*DataA!G22 -> 869416.83 | C12: =DataA!H22/DataA!I22 -> 9.0335852 | D12: =DataA!E22 -> 1314888 | E12: =DataA!J22 -> -1.882876 | F12: =DataA!D22 -> 1175653 | G12: =DataA!B22 -> 1229650 | I12: =100*((F12/F11)-1) -> 3.5558503 | J12: =100*((G12/G11)-1) -> 5.3770444 | L12: 1990 | M12: =100*((DataA!B33/DataA!B23)^(1/10)-1) -> 2.1292548 | O12: 2008 | P12: ='[1]2021-based'!H15 -> 283.6 | V12: 1982 | W12: =100*((DataA!M16/DataA!M15)-1) -> 0.4752789 | Y12: 0 | Z12: 65 | AA12: 60 | AC12: 8 | AD12: ='ONS pop proj 2021-based'!E10+'ONS pop proj 2021-based'!E117 -> 780395 | AE12: ='ONS pop proj 2021-based'!L10+'ONS pop proj 2021-based'!L117 -> 729840 | AF12: ='ONS pop proj 2021-based'!V10+'ONS pop proj 2021-based'!V117 -> 756645 | AG12: ='ONS pop proj 2021-based'!AF10+'ONS pop proj 2021-based'!AF117 -> 782305 | AI12: 2029 | AJ12: 0.16845782 | AK12: 0.62750419 | AL12: 0.20403798 | AN12: 40909 | AO12: =HAVERQ!F175-HAVERQ!F$166 -> -62 | AP12: =HAVERQ!G175-HAVERQ!G$166 -> 204 | AQ12: =HAVERQ!H175-HAVERQ!H$166 -> -142 | AR12: =HAVERQ!I175-HAVERQ!I$166 -> 232 | AS12: =HAVERQ!J175-HAVERQ!J$166 -> 131 | AT12: =SUM(AO12:AS12) -> 363 | AV12: =HAVERQ!D175-HAVERQ!D$166-'Chart Data'!AT12 -> -1 | AX12: 34213 | AY12: =100*(HAVERM!C51/HAVERM!B51) -> 22.187282 | AZ12: =AVERAGE($AY$7:$AY$374) -> 24.595806 | BB12: =HAVERM!C51 -> 1905 | BC12: =HAVERM!B51-HAVERM!C51 -> 6681 | BE12: 1973 | BG12: =$BL$6 -> 2.2155011 | BI12: 0 | BQ12: 1973 | BS12: =$BX$6 -> 1.9448021 | BU12: 0 | CH12: 2023 | CI12: =100*(DataA!B57/DataA!$B$53) -> 101.79635 | CJ12: =CJ11*(1+CO12/100) -> 102.21375 | CK12: 100 | CM12: =100*((CJ12/CI12)-1) -> 0.41003534 | CO12: 0.55405353
A13: 1989 | B13: =DataA!F23*DataA!G23 -> 881201.46 | C13: =DataA!H23/DataA!I23 -> 9.1558688 | D13: =DataA!E23 -> 1362920 | E13: =DataA!J23 -> -1.871818 | F13: =DataA!D23 -> 1217964 | G13: =DataA!B23 -> 1259191 | I13: =100*((F13/F12)-1) -> 3.5989361 | J13: =100*((G13/G12)-1) -> 2.4023909 | L13: 2000 | M13: =100*((DataA!B43/DataA!B33)^(1/10)-1) -> 1.6882802 | O13: 2009 | P13: ='[1]2021-based'!H16 -> 219.8 | V13: 1983 | W13: =100*((DataA!M17/DataA!M16)-1) -> 0.70478951 | X13: =AVERAGE(W4:W13) -> 0.42994854 | Y13: 0 | Z13: 65 | AA13: 60 | AC13: 9 | AD13: ='ONS pop proj 2021-based'!E11+'ONS pop proj 2021-based'!E118 -> 785418 | AE13: ='ONS pop proj 2021-based'!L11+'ONS pop proj 2021-based'!L118 -> 718056 | AF13: ='ONS pop proj 2021-based'!V11+'ONS pop proj 2021-based'!V118 -> 758544 | AG13: ='ONS pop proj 2021-based'!AF11+'ONS pop proj 2021-based'!AF118 -> 782577 | AI13: 2030 | AJ13: 0.16717205 | AK13: 0.62564887 | AL13: 0.20717908 | AN13: 41000 | AO13: =HAVERQ!F176-HAVERQ!F$166 -> 4 | AP13: =HAVERQ!G176-HAVERQ!G$166 -> 231 | AQ13: =HAVERQ!H176-HAVERQ!H$166 -> -128 | AR13: =HAVERQ!I176-HAVERQ!I$166 -> 296 | AS13: =HAVERQ!J176-HAVERQ!J$166 -> 176 | AT13: =SUM(AO13:AS13) -> 579 | AV13: =HAVERQ!D176-HAVERQ!D$166-'Chart Data'!AT13 -> 0 | AX13: 34243 | AY13: =100*(HAVERM!C52/HAVERM!B52) -> 22.563744 | AZ13: =AVERAGE($AY$7:$AY$374) -> 24.595806 | BB13: =HAVERM!C52 -> 1938 | BC13: =HAVERM!B52-HAVERM!C52 -> 6651 | BG13: =$BL$6 -> 2.2155011 | BI13: 0 | BS13: =$BX$6 -> 1.9448021 | BU13: 0 | CH13: 2024 | CI13: =100*(DataA!B58/DataA!$B$53) -> 102.18522 | CJ13: =CJ12*(1+CO13/100) -> 102.93622 | CK13: 100 | CM13: =100*((CJ13/CI13)-1) -> 0.73494613 | CO13: 0.70682576
A14: 1990 | B14: =DataA!F24*DataA!G24 -> 879722.49 | C14: =DataA!H24/DataA!I24 -> 9.2673112 | D14: =DataA!E24 -> 1416727 | E14: =DataA!J24 -> -1.860825 | F14: =DataA!D24 -> 1250609 | G14: =DataA!B24 -> 1266248 | I14: =100*((F14/F13)-1) -> 2.6802927 | J14: =100*((G14/G13)-1) -> 0.5604392 | L14: 2010 | M14: =100*((DataA!B53/DataA!B43)^(1/10)-1) -> 1.970971 | O14: 2010 | P14: ='[1]2021-based'!H17 -> 255.4 | T14: =AVERAGE($P$14:$P$23) -> 240.77 | V14: 1984 | W14: =100*((DataA!M18/DataA!M17)-1) -> 0.697956 | X14: =AVERAGE(W5:W14) -> 0.49694176 | Y14: 0 | Z14: 65 | AA14: 60 | AC14: 10 | AD14: ='ONS pop proj 2021-based'!E12+'ONS pop proj 2021-based'!E119 -> 805383 | AE14: ='ONS pop proj 2021-based'!L12+'ONS pop proj 2021-based'!L119 -> 744196 | AF14: ='ONS pop proj 2021-based'!V12+'ONS pop proj 2021-based'!V119 -> 760801 | AG14: ='ONS pop proj 2021-based'!AF12+'ONS pop proj 2021-based'!AF119 -> 781989 | AI14: 2031 | AJ14: 0.1659553 | AK14: 0.62397312 | AL14: 0.21007159 | AN14: 41091 | AO14: =HAVERQ!F177-HAVERQ!F$166 -> 1 | AP14: =HAVERQ!G177-HAVERQ!G$166 -> 275 | AQ14: =HAVERQ!H177-HAVERQ!H$166 -> -124 | AR14: =HAVERQ!I177-HAVERQ!I$166 -> 346 | AS14: =HAVERQ!J177-HAVERQ!J$166 -> 177 | AT14: =SUM(AO14:AS14) -> 675 | AV14: =HAVERQ!D177-HAVERQ!D$166-'Chart Data'!AT14 -> 1 | AX14: 34274 | AY14: =100*(HAVERM!C53/HAVERM!B53) -> 22.481072 | AZ14: =AVERAGE($AY$7:$AY$374) -> 24.595806 | BB14: =HAVERM!C53 -> 1930 | BC14: =HAVERM!B53-HAVERM!C53 -> 6655 | BG14: =$BL$6 -> 2.2155011 | BI14: 0 | BS14: =$BX$6 -> 1.9448021 | BU14: 0 | CH14: 2025 | CI14: =100*(DataA!B59/DataA!$B$53) -> 104.04012 | CJ14: =CJ13*(1+CO14/100) -> 104.35675 | CK14: 100 | CM14: =100*((CJ14/CI14)-1) -> 0.30433561 | CO14: 1.3800048
A15: 1991 | B15: =DataA!F25*DataA!G25 -> 861885.45 | C15: =DataA!H25/DataA!I25 -> 9.3754123 | D15: =DataA!E25 -> 1462646 | E15: =DataA!J25 -> -1.849896 | F15: =DataA!D25 -> 1267882 | G15: =DataA!B25 -> 1248461 | I15: =100*((F15/F14)-1) -> 1.3811671 | J15: =100*((G15/G14)-1) -> -1.4047011 | O15: 2011 | P15: ='[1]2021-based'!H18 -> 270.3 | T15: =AVERAGE($P$14:$P$23) -> 240.77 | V15: 1985 | W15: =100*((DataA!M19/DataA!M18)-1) -> 0.49341661 | X15: =AVERAGE(W6:W15) -> 0.54780629 | Y15: 0 | Z15: 65 | AA15: 60 | AC15: 11 | AD15: ='ONS pop proj 2021-based'!E13+'ONS pop proj 2021-based'!E120 -> 827802 | AE15: ='ONS pop proj 2021-based'!L13+'ONS pop proj 2021-based'!L120 -> 757155 | AF15: ='ONS pop proj 2021-based'!V13+'ONS pop proj 2021-based'!V120 -> 763215 | AG15: ='ONS pop proj 2021-based'!AF13+'ONS pop proj 2021-based'!AF120 -> 780531 | AI15: 2032 | AJ15: 0.16466727 | AK15: 0.62248656 | AL15: 0.21284617 | AN15: 41183 | AO15: =HAVERQ!F178-HAVERQ!F$166 -> 13 | AP15: =HAVERQ!G178-HAVERQ!G$166 -> 321 | AQ15: =HAVERQ!H178-HAVERQ!H$166 -> -148 | AR15: =HAVERQ!I178-HAVERQ!I$166 -> 430 | AS15: =HAVERQ!J178-HAVERQ!J$166 -> 208 | AT15: =SUM(AO15:AS15) -> 824 | AV15: =HAVERQ!D178-HAVERQ!D$166-'Chart Data'!AT15 -> 6 | AX15: 34304 | AY15: =100*(HAVERM!C54/HAVERM!B54) -> 22.434479 | AZ15: =AVERAGE($AY$7:$AY$374) -> 24.595806 | BB15: =HAVERM!C54 -> 1926 | BC15: =HAVERM!B54-HAVERM!C54 -> 6659 | BG15: =$BL$6 -> 2.2155011 | BI15: 0 | BS15: =$BX$6 -> 1.9448021 | BU15: 0 | CH15: 2026 | CI15: =100*(DataA!B60/DataA!$B$53) -> 106.12784 | CJ15: =CJ14*(1+CO15/100) -> 106.41169 | CK15: 100 | CM15: =100*((CJ15/CI15)-1) -> 0.26746493 | CO15: 1.969152
A16: 1992 | B16: =DataA!F26*DataA!G26 -> 848974.43 | C16: =DataA!H26/DataA!I26 -> 9.4785328 | D16: =DataA!E26 -> 1490253 | E16: =DataA!J26 -> -1.839032 | F16: =DataA!D26 -> 1285429 | G16: =DataA!B26 -> 1251525 | I16: =100*((F16/F15)-1) -> 1.3839616 | J16: =100*((G16/G15)-1) -> 0.24542216 | O16: 2012 | P16: ='ONS migration estimates'!C96/1000 -> 162 | T16: =AVERAGE($P$14:$P$23) -> 240.77 | V16: 1986 | W16: =100*((DataA!M20/DataA!M19)-1) -> 0.41478282 | X16: =AVERAGE(W7:W16) -> 0.57901966 | Y16: 0 | Z16: 65 | AA16: 60 | AC16: 12 | AD16: ='ONS pop proj 2021-based'!E14+'ONS pop proj 2021-based'!E121 -> 831944 | AE16: ='ONS pop proj 2021-based'!L14+'ONS pop proj 2021-based'!L121 -> 768410 | AF16: ='ONS pop proj 2021-based'!V14+'ONS pop proj 2021-based'!V121 -> 765547 | AG16: ='ONS pop proj 2021-based'!AF14+'ONS pop proj 2021-based'!AF121 -> 778853 | AI16: 2033 | AJ16: 0.16369371 | AK16: 0.62091942 | AL16: 0.21538687 | AN16: 41275 | AO16: =HAVERQ!F179-HAVERQ!F$166 -> -30 | AP16: =HAVERQ!G179-HAVERQ!G$166 -> 332 | AQ16: =HAVERQ!H179-HAVERQ!H$166 -> -204 | AR16: =HAVERQ!I179-HAVERQ!I$166 -> 435 | AS16: =HAVERQ!J179-HAVERQ!J$166 -> 224 | AT16: =SUM(AO16:AS16) -> 757 | AV16: =HAVERQ!D179-HAVERQ!D$166-'Chart Data'!AT16 -> 10 | AX16: 34335 | AY16: =100*(HAVERM!C55/HAVERM!B55) -> 22.336089 | AZ16: =AVERAGE($AY$7:$AY$374) -> 24.595806 | BB16: =HAVERM!C55 -> 1918 | BC16: =HAVERM!B55-HAVERM!C55 -> 6669 | BE16: 1974 | BG16: =$BL$6 -> 2.2155011 | BI16: 0 | BQ16: 1974 | BS16: =$BX$6 -> 1.9448021 | BU16: 0 | CH16: 2027 | CI16: =100*(DataA!B61/DataA!$B$53) -> 107.96505 | CJ16: =CJ15*(1+CO16/100) -> 108.50375 | CK16: 100 | CM16: =100*((CJ16/CI16)-1) -> 0.49895658 | CO16: 1.9660077
A17: 1993 | B17: =DataA!F27*DataA!G27 -> 843846.96 | C17: =DataA!H27/DataA!I27 -> 9.5656692 | D17: =DataA!E27 -> 1518284 | E17: =DataA!J27 -> -1.828231 | F17: =DataA!D27 -> 1306377 | G17: =DataA!B27 -> 1279802 | I17: =100*((F17/F16)-1) -> 1.6296505 | J17: =100*((G17/G16)-1) -> 2.2594035 | O17: 2013 | P17: ='ONS migration estimates'!C100/1000 -> 215 | T17: =AVERAGE($P$14:$P$23) -> 240.77 | V17: 1987 | W17: =100*((DataA!M21/DataA!M20)-1) -> 0.4090401 | X17: =AVERAGE(W8:W17) -> 0.56154408 | Y17: 0 | Z17: 65 | AA17: 60 | AC17: 13 | AD17: ='ONS pop proj 2021-based'!E15+'ONS pop proj 2021-based'!E122 -> 819595 | AE17: ='ONS pop proj 2021-based'!L15+'ONS pop proj 2021-based'!L122 -> 786414 | AF17: ='ONS pop proj 2021-based'!V15+'ONS pop proj 2021-based'!V122 -> 767453 | AG17: ='ONS pop proj 2021-based'!AF15+'ONS pop proj 2021-based'!AF122 -> 777340 | AI17: 2034 | AJ17: 0.16296485 | AK17: 0.61924143 | AL17: 0.21779372 | AN17: 41365 | AO17: =HAVERQ!F180-HAVERQ!F$166 -> -95 | AP17: =HAVERQ!G180-HAVERQ!G$166 -> 398 | AQ17: =HAVERQ!H180-HAVERQ!H$166 -> -204 | AR17: =HAVERQ!I180-HAVERQ!I$166 -> 504 | AS17: =HAVERQ!J180-HAVERQ!J$166 -> 254 | AT17: =SUM(AO17:AS17) -> 857 | AV17: =HAVERQ!D180-HAVERQ!D$166-'Chart Data'!AT17 -> 15 | AX17: 34366 | AY17: =100*(HAVERM!C56/HAVERM!B56) -> 22.272727 | AZ17: =AVERAGE($AY$7:$AY$374) -> 24.595806 | BB17: =HAVERM!C56 -> 1911 | BC17: =HAVERM!B56-HAVERM!C56 -> 6669 | BG17: =$BL$6 -> 2.2155011 | BI17: 0 | BS17: =$BX$6 -> 1.9448021 | BU17: 0 | CH17: 2028 | CI17: =100*(DataA!B62/DataA!$B$53) -> 109.75191 | CJ17: =CJ16*(1+CO17/100) -> 110.39467 | CK17: 100 | CM17: =100*((CJ17/CI17)-1) -> 0.58564887 | CO17: 1.7427234
A18: 1994 | B18: =DataA!F28*DataA!G28 -> 851546.12 | C18: =DataA!H28/DataA!I28 -> 9.6325984 | D18: =DataA!E28 -> 1551666 | E18: =DataA!J28 -> -1.817494 | F18: =DataA!D28 -> 1340362 | G18: =DataA!B28 -> 1323443 | I18: =100*((F18/F17)-1) -> 2.6014696 | J18: =100*((G18/G17)-1) -> 3.4099806 | O18: 2014 | P18: ='ONS migration estimates'!C104/1000 -> 248 | T18: =AVERAGE($P$14:$P$23) -> 240.77 | V18: 1988 | W18: =100*((DataA!M22/DataA!M21)-1) -> 0.30865471 | X18: =AVERAGE(W9:W18) -> 0.53037937 | Y18: 0 | Z18: 65 | AA18: 60 | AC18: 14 | AD18: ='ONS pop proj 2021-based'!E16+'ONS pop proj 2021-based'!E123 -> 816974 | AE18: ='ONS pop proj 2021-based'!L16+'ONS pop proj 2021-based'!L123 -> 809733 | AF18: ='ONS pop proj 2021-based'!V16+'ONS pop proj 2021-based'!V123 -> 769049 | AG18: ='ONS pop proj 2021-based'!AF16+'ONS pop proj 2021-based'!AF123 -> 776764 | AI18: 2035 | AJ18: 0.16239107 | AK18: 0.6178263 | AL18: 0.21978263 | AN18: 41456 | AO18: =HAVERQ!F181-HAVERQ!F$166 -> -36 | AP18: =HAVERQ!G181-HAVERQ!G$166 -> 431 | AQ18: =HAVERQ!H181-HAVERQ!H$166 -> -223 | AR18: =HAVERQ!I181-HAVERQ!I$166 -> 579 | AS18: =HAVERQ!J181-HAVERQ!J$166 -> 275 | AT18: =SUM(AO18:AS18) -> 1026 | AV18: =HAVERQ!D181-HAVERQ!D$166-'Chart Data'!AT18 -> 16 | AX18: 34394 | AY18: =100*(HAVERM!C57/HAVERM!B57) -> 22.571628 | AZ18: =AVERAGE($AY$7:$AY$374) -> 24.595806 | BB18: =HAVERM!C57 -> 1938 | BC18: =HAVERM!B57-HAVERM!C57 -> 6648 | BG18: =$BL$6 -> 2.2155011 | BI18: 0 | BS18: =$BX$6 -> 1.9448021 | BU18: 0 | CH18: 2029 | CI18: =100*(DataA!B63/DataA!$B$53) -> 111.474 | CJ18: =CJ17*(1+CO18/100) -> 112.42767 | CK18: 100 | CM18: =100*((CJ18/CI18)-1) -> 0.85551576 | CO18: {=TRANSPOSE('OBR LT economic determinants'!J7:AE7)} -> 1.8415752
A19: 1995 | B19: =DataA!F29*DataA!G29 -> 858185.82 | C19: =DataA!H29/DataA!I29 -> 9.6889063 | D19: =DataA!E29 -> 1589698 | E19: =DataA!J29 -> -1.806819 | F19: =DataA!D29 -> 1374846 | G19: =DataA!B29 -> 1355023 | I19: =100*((F19/F18)-1) -> 2.5727378 | J19: =100*((G19/G18)-1) -> 2.3862002 | O19: 2015 | P19: ='ONS migration estimates'!C108/1000 -> 296 | T19: =AVERAGE($P$14:$P$23) -> 240.77 | V19: 1989 | W19: =100*((DataA!M23/DataA!M22)-1) -> 0.26095485 | X19: =AVERAGE(W10:W19) -> 0.4948301 | Y19: 0 | Z19: 65 | AA19: 60 | AC19: 15 | AD19: ='ONS pop proj 2021-based'!E17+'ONS pop proj 2021-based'!E124 -> 825235 | AE19: ='ONS pop proj 2021-based'!L17+'ONS pop proj 2021-based'!L124 -> 805672 | AF19: ='ONS pop proj 2021-based'!V17+'ONS pop proj 2021-based'!V124 -> 770439 | AG19: ='ONS pop proj 2021-based'!AF17+'ONS pop proj 2021-based'!AF124 -> 778431 | AI19: 2036 | AJ19: 0.16200698 | AK19: 0.61606488 | AL19: 0.22192813 | AN19: 41548 | AO19: =HAVERQ!F182-HAVERQ!F$166 -> -4 | AP19: =HAVERQ!G182-HAVERQ!G$166 -> 463 | AQ19: =HAVERQ!H182-HAVERQ!H$166 -> -220 | AR19: =HAVERQ!I182-HAVERQ!I$166 -> 674 | AS19: =HAVERQ!J182-HAVERQ!J$166 -> 298 | AT19: =SUM(AO19:AS19) -> 1211 | AV19: =HAVERQ!D182-HAVERQ!D$166-'Chart Data'!AT19 -> 17 | AX19: 34425 | AY19: =100*(HAVERM!C58/HAVERM!B58) -> 22.539793 | AZ19: =AVERAGE($AY$7:$AY$374) -> 24.595806 | BB19: =HAVERM!C58 -> 1940 | BC19: =HAVERM!B58-HAVERM!C58 -> 6667 | BG19: =$BL$6 -> 2.2155011 | BI19: 0 | BS19: =$BX$6 -> 1.9448021 | BU19: 0 | CH19: 2030 | CI19: =100*(DataA!B64/DataA!$B$53) -> 113.17808 | CJ19: =CJ18*(1+CO19/100) -> 114.55137 | CK19: 100 | CM19: =100*((CJ19/CI19)-1) -> 1.2133812 | CO19: 1.8889414
A20: 1996 | B20: =DataA!F30*DataA!G30 -> 866753.2 | C20: =DataA!H30/DataA!I30 -> 9.720396 | D20: =DataA!E30 -> 1628714 | E20: =DataA!J30 -> -1.796208 | F20: =DataA!D30 -> 1411804 | G20: =DataA!B30 -> 1390010 | I20: =100*((F20/F19)-1) -> 2.6881556 | J20: =100*((G20/G19)-1) -> 2.5820226 | O20: 2016 | P20: ='ONS migration estimates'!C112/1000 -> 321 | T20: =AVERAGE($P$14:$P$23) -> 240.77 | V20: 1990 | W20: =100*((DataA!M24/DataA!M23)-1) -> 0.1888224 | X20: =AVERAGE(W11:W20) -> 0.45244525 | Y20: 0 | Z20: 65 | AA20: 60 | AC20: 16 | AD20: ='ONS pop proj 2021-based'!E18+'ONS pop proj 2021-based'!E125 -> 794768 | AE20: ='ONS pop proj 2021-based'!L18+'ONS pop proj 2021-based'!L125 -> 812369 | AF20: ='ONS pop proj 2021-based'!V18+'ONS pop proj 2021-based'!V125 -> 768164 | AG20: ='ONS pop proj 2021-based'!AF18+'ONS pop proj 2021-based'!AF125 -> 782003 | AI20: 2037 | AJ20: 0.1620056 | AK20: 0.61447081 | AL20: 0.22352359 | AN20: 41640 | AO20: =HAVERQ!F183-HAVERQ!F$166 -> 15 | AP20: =HAVERQ!G183-HAVERQ!G$166 -> 534 | AQ20: =HAVERQ!H183-HAVERQ!H$166 -> -140 | AR20: =HAVERQ!I183-HAVERQ!I$166 -> 717 | AS20: =HAVERQ!J183-HAVERQ!J$166 -> 328 | AT20: =SUM(AO20:AS20) -> 1454 | AV20: =HAVERQ!D183-HAVERQ!D$166-'Chart Data'!AT20 -> 17 | AX20: 34455 | AY20: =100*(HAVERM!C59/HAVERM!B59) -> 22.62926 | AZ20: =AVERAGE($AY$7:$AY$374) -> 24.595806 | BB20: =HAVERM!C59 -> 1952 | BC20: =HAVERM!B59-HAVERM!C59 -> 6674 | BE20: 1975 | BG20: =$BL$6 -> 2.2155011 | BI20: 0 | BQ20: 1975 | BS20: =$BX$6 -> 1.9448021 | BU20: 0 | CH20: 2031 | CI20: =100*(DataA!B65/DataA!$B$53) -> 114.90823 | CJ20: =CJ19*(1+CO20/100) -> 116.65136 | CK20: 100 | CM20: =100*((CJ20/CI20)-1) -> 1.5169821 | CO20: 1.8332364
A21: 1997 | B21: =DataA!F31*DataA!G31 -> 877828.41 | C21: =DataA!H31/DataA!I31 -> 9.7395726 | D21: =DataA!E31 -> 1679000 | E21: =DataA!J31 -> -1.786856 | F21: =DataA!D31 -> 1451153 | G21: =DataA!B31 -> 1458467 | I21: =100*((F21/F20)-1) -> 2.7871433 | J21: =100*((G21/G20)-1) -> 4.9249286 | O21: 2017 | P21: ='ONS migration estimates'!C116/1000 -> 200 | T21: =AVERAGE($P$14:$P$23) -> 240.77 | V21: 1991 | W21: =100*((DataA!M25/DataA!M24)-1) -> 0.1228944 | X21: =AVERAGE(W12:W21) -> 0.40765903 | Y21: 0 | Z21: 65 | AA21: 60 | AC21: 17 | AD21: ='ONS pop proj 2021-based'!E19+'ONS pop proj 2021-based'!E126 -> 780765 | AE21: ='ONS pop proj 2021-based'!L19+'ONS pop proj 2021-based'!L126 -> 835043 | AF21: ='ONS pop proj 2021-based'!V19+'ONS pop proj 2021-based'!V126 -> 728702 | AG21: ='ONS pop proj 2021-based'!AF19+'ONS pop proj 2021-based'!AF126 -> 786972 | AI21: 2038 | AJ21: 0.16187525 | AK21: 0.61354371 | AL21: 0.22458104 | AN21: 41730 | AO21: =HAVERQ!F184-HAVERQ!F$166 -> 92 | AP21: =HAVERQ!G184-HAVERQ!G$166 -> 556 | AQ21: =HAVERQ!H184-HAVERQ!H$166 -> -88 | AR21: =HAVERQ!I184-HAVERQ!I$166 -> 739 | AS21: =HAVERQ!J184-HAVERQ!J$166 -> 328 | AT21: =SUM(AO21:AS21) -> 1627 | AV21: =HAVERQ!D184-HAVERQ!D$166-'Chart Data'!AT21 -> 18 | AX21: 34486 | AY21: =100*(HAVERM!C60/HAVERM!B60) -> 22.55814 | AZ21: =AVERAGE($AY$7:$AY$374) -> 24.595806 | BB21: =HAVERM!C60 -> 1940 | BC21: =HAVERM!B60-HAVERM!C60 -> 6660 | BG21: =$BL$6 -> 2.2155011 | BI21: 0 | BS21: =$BX$6 -> 1.9448021 | BU21: 0 | CH21: 2032 | CI21: =100*(DataA!B66/DataA!$B$53) -> 116.65314 | CJ21: =CJ20*(1+CO21/100) -> 118.75425 | CK21: 100 | CM21: =100*((CJ21/CI21)-1) -> 1.8011571 | CO21: 1.8027076
A22: 1998 | B22: =DataA!F32*DataA!G32 -> 884900.46 | C22: =DataA!H32/DataA!I32 -> 9.7651529 | D22: =DataA!E32 -> 1730000 | E22: =DataA!J32 -> -1.782333 | F22: =DataA!D32 -> 1482073 | G22: =DataA!B32 -> 1508263 | I22: =100*((F22/F21)-1) -> 2.1307195 | J22: =100*((G22/G21)-1) -> 3.4142699 | O22: 2018 | P22: ='ONS migration estimates'!C120/1000 -> 216 | T22: =AVERAGE($P$14:$P$23) -> 240.77 | V22: 1992 | W22: =100*((DataA!M26/DataA!M25)-1) -> 0.029350485 | X22: =AVERAGE(W13:W22) -> 0.36306619 | Y22: 0 | Z22: 65 | AA22: 60 | AC22: 18 | AD22: ='ONS pop proj 2021-based'!E20+'ONS pop proj 2021-based'!E127 -> 788007 | AE22: ='ONS pop proj 2021-based'!L20+'ONS pop proj 2021-based'!L127 -> 864795 | AF22: ='ONS pop proj 2021-based'!V20+'ONS pop proj 2021-based'!V127 -> 769670 | AG22: ='ONS pop proj 2021-based'!AF20+'ONS pop proj 2021-based'!AF127 -> 796533 | AI22: 2039 | AJ22: 0.16222178 | AK22: 0.61265417 | AL22: 0.22512405 | AN22: 41821 | AO22: =HAVERQ!F185-HAVERQ!F$166 -> 106 | AP22: =HAVERQ!G185-HAVERQ!G$166 -> 565 | AQ22: =HAVERQ!H185-HAVERQ!H$166 -> -74 | AR22: =HAVERQ!I185-HAVERQ!I$166 -> 820 | AS22: =HAVERQ!J185-HAVERQ!J$166 -> 338 | AT22: =SUM(AO22:AS22) -> 1755 | AV22: =HAVERQ!D185-HAVERQ!D$166-'Chart Data'!AT22 -> 16 | AX22: 34516 | AY22: =100*(HAVERM!C61/HAVERM!B61) -> 22.628161 | AZ22: =AVERAGE($AY$7:$AY$374) -> 24.595806 | BB22: =HAVERM!C61 -> 1951 | BC22: =HAVERM!B61-HAVERM!C61 -> 6671 | BG22: =$BL$6 -> 2.2155011 | BI22: 0 | BS22: =$BX$6 -> 1.9448021 | BU22: 0 | CH22: 2033 | CI22: =100*(DataA!B67/DataA!$B$53) -> 118.35248 | CJ22: =CJ21*(1+CO22/100) -> 120.86934 | CK22: 100 | CM22: =100*((CJ22/CI22)-1) -> 2.1265778 | CO22: 1.7810692
A23: 1999 | B23: =DataA!F33*DataA!G33 -> 895986.1 | C23: =DataA!H33/DataA!I33 -> 9.832806 | D23: =DataA!E33 -> 1817000 | E23: =DataA!J33 -> -1.778219 | F23: =DataA!D33 -> 1523159 | G23: =DataA!B33 -> 1554509 | I23: =100*((F23/F22)-1) -> 2.7721981 | J23: =100*((G23/G22)-1) -> 3.0661761 | O23: 2019 | P23: ='ONS migration estimates'!C124/1000 -> 224 | T23: =AVERAGE($P$14:$P$23) -> 240.77 | V23: 1993 | W23: =100*((DataA!M27/DataA!M26)-1) -> 0.031557426 | X23: =AVERAGE(W14:W23) -> 0.29574298 | Y23: 0 | Z23: 65 | AA23: 60 | AC23: 19 | AD23: ='ONS pop proj 2021-based'!E21+'ONS pop proj 2021-based'!E128 -> 804525 | AE23: ='ONS pop proj 2021-based'!L21+'ONS pop proj 2021-based'!L128 -> 886517 | AF23: ='ONS pop proj 2021-based'!V21+'ONS pop proj 2021-based'!V128 -> 775509 | AG23: ='ONS pop proj 2021-based'!AF21+'ONS pop proj 2021-based'!AF128 -> 816057 | AI23: 2040 | AJ23: 0.16202365 | AK23: 0.61252084 | AL23: 0.22545551 | AN23: 41913 | AO23: =HAVERQ!F186-HAVERQ!F$166 -> 114 | AP23: =HAVERQ!G186-HAVERQ!G$166 -> 575 | AQ23: =HAVERQ!H186-HAVERQ!H$166 -> -47 | AR23: =HAVERQ!I186-HAVERQ!I$166 -> 876 | AS23: =HAVERQ!J186-HAVERQ!J$166 -> 345 | AT23: =SUM(AO23:AS23) -> 1863 | AV23: =HAVERQ!D186-HAVERQ!D$166-'Chart Data'!AT23 -> 16 | AX23: 34547 | AY23: =100*(HAVERM!C62/HAVERM!B62) -> 22.804582 | AZ23: =AVERAGE($AY$7:$AY$374) -> 24.595806 | BB23: =HAVERM!C62 -> 1971 | BC23: =HAVERM!B62-HAVERM!C62 -> 6672 | BG23: =$BL$6 -> 2.2155011 | BI23: 0 | BS23: =$BX$6 -> 1.9448021 | BU23: 0 | CH23: 2034 | CI23: =100*(DataA!B68/DataA!$B$53) -> 120.0482 | CJ23: =CJ22*(1+CO23/100) -> 122.98949 | CK23: 100 | CM23: =100*((CJ23/CI23)-1) -> 2.4500857 | CO23: 1.7540793
A24: 2000 | B24: =DataA!F34*DataA!G34 -> 897004.65 | C24: =DataA!H34/DataA!I34 -> 9.9743903 | D24: =DataA!E34 -> 1891000 | E24: =DataA!J34 -> -1.774115 | F24: =DataA!D34 -> 1561852 | G24: =DataA!B34 -> 1621644 | I24: =100*((F24/F23)-1) -> 2.5403126 | J24: =100*((G24/G23)-1) -> 4.318727 | O24: 2020 | P24: ='ONS migration estimates'!C128/1000 -> 111 | V24: 1994 | W24: =100*((DataA!M28/DataA!M27)-1) -> 0.16043493 | X24: =AVERAGE(W15:W24) -> 0.24199087 | Y24: 0 | Z24: 65 | AA24: 60 | AC24: 20 | AD24: ='ONS pop proj 2021-based'!E22+'ONS pop proj 2021-based'!E129 -> 814061 | AE24: ='ONS pop proj 2021-based'!L22+'ONS pop proj 2021-based'!L129 -> 894682 | AF24: ='ONS pop proj 2021-based'!V22+'ONS pop proj 2021-based'!V129 -> 822003 | AG24: ='ONS pop proj 2021-based'!AF22+'ONS pop proj 2021-based'!AF129 -> 838704 | AI24: 2041 | AJ24: 0.16178482 | AK24: 0.61268007 | AL24: 0.22553511 | AN24: 42005 | AO24: =HAVERQ!F187-HAVERQ!F$166 -> 157 | AP24: =HAVERQ!G187-HAVERQ!G$166 -> 611 | AQ24: =HAVERQ!H187-HAVERQ!H$166 -> -55 | AR24: =HAVERQ!I187-HAVERQ!I$166 -> 934 | AS24: =HAVERQ!J187-HAVERQ!J$166 -> 424 | AT24: =SUM(AO24:AS24) -> 2071 | AV24: =HAVERQ!D187-HAVERQ!D$166-'Chart Data'!AT24 -> 15 | AX24: 34578 | AY24: =100*(HAVERM!C63/HAVERM!B63) -> 22.978576 | AZ24: =AVERAGE($AY$7:$AY$374) -> 24.595806 | BB24: =HAVERM!C63 -> 1995 | BC24: =HAVERM!B63-HAVERM!C63 -> 6687 | BE24: 1976 | BG24: =$BL$6 -> 2.2155011 | BI24: 0 | BQ24: 1976 | BS24: =$BX$6 -> 1.9448021 | BU24: 0 | CH24: 2035 | CI24: =100*(DataA!B69/DataA!$B$53) -> 121.76827 | CJ24: =CJ23*(1+CO24/100) -> 125.12677 | CK24: 100 | CM24: =100*((CJ24/CI24)-1) -> 2.7581029 | CO24: 1.7377747
A25: 2001 | B25: =DataA!F35*DataA!G35 -> 906197.99 | C25: =DataA!H35/DataA!I35 -> 10.222141 | D25: =DataA!E35 -> 1959000 | E25: =DataA!J35 -> -1.77002 | F25: =DataA!D35 -> 1611689 | G25: =DataA!B35 -> 1663462 | I25: =100*((F25/F24)-1) -> 3.1908913 | J25: =100*((G25/G24)-1) -> 2.5787411 | O25: 2021 | P25: ='ONS migration estimates'!C132/1000 -> 221 | V25: 1995 | W25: =100*((DataA!M29/DataA!M28)-1) -> 0.31204932 | X25: =AVERAGE(W16:W25) -> 0.22385414 | Y25: 0 | Z25: 65 | AA25: 60 | AC25: 21 | AD25: ='ONS pop proj 2021-based'!E23+'ONS pop proj 2021-based'!E130 -> 819436 | AE25: ='ONS pop proj 2021-based'!L23+'ONS pop proj 2021-based'!L130 -> 905811 | AF25: ='ONS pop proj 2021-based'!V23+'ONS pop proj 2021-based'!V130 -> 848567 | AG25: ='ONS pop proj 2021-based'!AF23+'ONS pop proj 2021-based'!AF130 -> 854757 | AI25: 2042 | AJ25: 0.16154952 | AK25: 0.61310503 | AL25: 0.22534545 | AN25: 42095 | AO25: =HAVERQ!F188-HAVERQ!F$166 -> 172 | AP25: =HAVERQ!G188-HAVERQ!G$166 -> 607 | AQ25: =HAVERQ!H188-HAVERQ!H$166 -> -99 | AR25: =HAVERQ!I188-HAVERQ!I$166 -> 980 | AS25: =HAVERQ!J188-HAVERQ!J$166 -> 363 | AT25: =SUM(AO25:AS25) -> 2023 | AV25: =HAVERQ!D188-HAVERQ!D$166-'Chart Data'!AT25 -> 15 | AX25: 34608 | AY25: =100*(HAVERM!C64/HAVERM!B64) -> 23.105148 | AZ25: =AVERAGE($AY$7:$AY$374) -> 24.595806 | BB25: =HAVERM!C64 -> 2015 | BC25: =HAVERM!B64-HAVERM!C64 -> 6706 | BG25: =$BL$6 -> 2.2155011 | BI25: 0 | BS25: =$BX$6 -> 1.9448021 | BU25: 0 | CH25: 2036 | CI25: =100*(DataA!B70/DataA!$B$53) -> 123.56265 | CJ25: =CJ24*(1+CO25/100) -> 127.46356 | CK25: 100 | CM25: =100*((CJ25/CI25)-1) -> 3.1570302 | CO25: 1.8675416
A26: 2002 | B26: =DataA!F36*DataA!G36 -> 905078.99 | C26: =DataA!H36/DataA!I36 -> 10.553831 | D26: =DataA!E36 -> 2015000 | E26: =DataA!J36 -> -1.765935 | F26: =DataA!D36 -> 1651285 | G26: =DataA!B36 -> 1693271 | I26: =100*((F26/F25)-1) -> 2.4568015 | J26: =100*((G26/G25)-1) -> 1.7919856 | O26: 2022 | P26: ='ONS migration estimates'!C136/1000 -> 607 | V26: 1996 | W26: =100*((DataA!M30/DataA!M29)-1) -> 0.36678279 | X26: =AVERAGE(W17:W26) -> 0.21905414 | Y26: 0 | Z26: 65 | AA26: 60 | AC26: 22 | AD26: ='ONS pop proj 2021-based'!E24+'ONS pop proj 2021-based'!E131 -> 823721 | AE26: ='ONS pop proj 2021-based'!L24+'ONS pop proj 2021-based'!L131 -> 925826 | AF26: ='ONS pop proj 2021-based'!V24+'ONS pop proj 2021-based'!V131 -> 870793 | AG26: ='ONS pop proj 2021-based'!AF24+'ONS pop proj 2021-based'!AF131 -> 868097 | AI26: 2043 | AJ26: 0.16132481 | AK26: 0.61336626 | AL26: 0.22530894 | AN26: 42186 | AO26: =HAVERQ!F189-HAVERQ!F$166 -> 259 | AP26: =HAVERQ!G189-HAVERQ!G$166 -> 681 | AQ26: =HAVERQ!H189-HAVERQ!H$166 -> -140 | AR26: =HAVERQ!I189-HAVERQ!I$166 -> 1056 | AS26: =HAVERQ!J189-HAVERQ!J$166 -> 387 | AT26: =SUM(AO26:AS26) -> 2243 | AV26: =HAVERQ!D189-HAVERQ!D$166-'Chart Data'!AT26 -> 16 | AX26: 34639 | AY26: =100*(HAVERM!C65/HAVERM!B65) -> 23.182285 | AZ26: =AVERAGE($AY$7:$AY$374) -> 24.595806 | BB26: =HAVERM!C65 -> 2031 | BC26: =HAVERM!B65-HAVERM!C65 -> 6730 | BG26: =$BL$6 -> 2.2155011 | BI26: 0 | BS26: =$BX$6 -> 1.9448021 | BU26: 0 | CH26: 2037 | CI26: =100*(DataA!B71/DataA!$B$53) -> 125.41061 | CJ26: =CJ25*(1+CO26/100) -> 129.80908 | CK26: 100 | CM26: =100*((CJ26/CI26)-1) -> 3.5072509 | CO26: 1.8401465
A27: 2003 | B27: =DataA!F37*DataA!G37 -> 907433.11 | C27: =DataA!H37/DataA!I37 -> 10.921335 | D27: =DataA!E37 -> 2062000 | E27: =DataA!J37 -> -1.761859 | F27: =DataA!D37 -> 1693448 | G27: =DataA!B37 -> 1746551 | I27: =100*((F27/F26)-1) -> 2.5533448 | J27: =100*((G27/G26)-1) -> 3.1465725 | O27: 2023 | P27: ='ONS migration estimates'!C140/1000 -> 672 | Q27: ='ONS pop proj migration'!B8/1000 -> 670 | R27: ='ONS pop proj migration'!C8/1000 -> 670 | S27: ='ONS pop proj migration'!D8/1000 -> 670 | V27: 1997 | W27: =100*((DataA!M31/DataA!M30)-1) -> 0.35389738 | X27: =AVERAGE(W18:W27) -> 0.21353987 | Y27: 0 | Z27: 65 | AA27: 60 | AC27: 23 | AD27: ='ONS pop proj 2021-based'!E25+'ONS pop proj 2021-based'!E132 -> 841152 | AE27: ='ONS pop proj 2021-based'!L25+'ONS pop proj 2021-based'!L132 -> 910149 | AF27: ='ONS pop proj 2021-based'!V25+'ONS pop proj 2021-based'!V132 -> 901140 | AG27: ='ONS pop proj 2021-based'!AF25+'ONS pop proj 2021-based'!AF132 -> 882396 | AI27: 2044 | AJ27: 0.16111701 | AK27: 0.6129077 | AL27: 0.22597529 | AN27: 42278 | AO27: =HAVERQ!F190-HAVERQ!F$166 -> 251 | AP27: =HAVERQ!G190-HAVERQ!G$166 -> 735 | AQ27: =HAVERQ!H190-HAVERQ!H$166 -> -100 | AR27: =HAVERQ!I190-HAVERQ!I$166 -> 1144 | AS27: =HAVERQ!J190-HAVERQ!J$166 -> 418 | AT27: =SUM(AO27:AS27) -> 2448 | AV27: =HAVERQ!D190-HAVERQ!D$166-'Chart Data'!AT27 -> 19 | AX27: 34669 | AY27: =100*(HAVERM!C66/HAVERM!B66) -> 23.554798 | AZ27: =AVERAGE($AY$7:$AY$374) -> 24.595806 | BB27: =HAVERM!C66 -> 2074 | BC27: =HAVERM!B66-HAVERM!C66 -> 6731 | BF27: =100*((AVERAGE(HAVERQ!B15:B34)/AVERAGE(HAVERQ!B11:B30))-1) -> 2.0347883 | BG27: =$BL$6 -> 2.2155011 | BI27: 0 | BR27: =100*((AVERAGE(HAVERQ!C15:C34)/AVERAGE(HAVERQ!C11:C30))-1) -> 1.7352504 | BS27: =$BX$6 -> 1.9448021 | BU27: 0 | CH27: 2038 | CI27: =100*(DataA!B72/DataA!$B$53) -> 127.32474 | CJ27: =CJ26*(1+CO27/100) -> 132.14613 | CK27: 100 | CM27: =100*((CJ27/CI27)-1) -> 3.7866942 | CO27: 1.8003801
A28: 2004 | B28: =DataA!F38*DataA!G38 -> 912728.12 | C28: =DataA!H38/DataA!I38 -> 11.276552 | D28: =DataA!E38 -> 2113000 | E28: =DataA!J38 -> -1.757793 | F28: =DataA!D38 -> 1737570 | G28: =DataA!B38 -> 1788931 | I28: =100*((F28/F27)-1) -> 2.6054535 | J28: =100*((G28/G27)-1) -> 2.4264966 | O28: 2024 | Q28: ='ONS pop proj migration'!B9/1000 -> 586.6 | R28: ='ONS pop proj migration'!C9/1000 -> 599 | S28: ='ONS pop proj migration'!D9/1000 -> 611.8 | V28: 1998 | W28: =100*((DataA!M32/DataA!M31)-1) -> 0.37481621 | X28: =AVERAGE(W19:W28) -> 0.22015602 | Y28: 0 | Z28: 65 | AA28: 60 | AC28: 24 | AD28: ='ONS pop proj 2021-based'!E26+'ONS pop proj 2021-based'!E133 -> 867946 | AE28: ='ONS pop proj 2021-based'!L26+'ONS pop proj 2021-based'!L133 -> 903921 | AF28: ='ONS pop proj 2021-based'!V26+'ONS pop proj 2021-based'!V133 -> 928929 | AG28: ='ONS pop proj 2021-based'!AF26+'ONS pop proj 2021-based'!AF133 -> 888523 | AI28: 2045 | AJ28: 0.16091588 | AK28: 0.61201421 | AL28: 0.22706991 | AN28: 42370 | AO28: =HAVERQ!F191-HAVERQ!F$166 -> 241 | AP28: =HAVERQ!G191-HAVERQ!G$166 -> 752 | AQ28: =HAVERQ!H191-HAVERQ!H$166 -> -78 | AR28: =HAVERQ!I191-HAVERQ!I$166 -> 1162 | AS28: =HAVERQ!J191-HAVERQ!J$166 -> 403 | AT28: =SUM(AO28:AS28) -> 2480 | AV28: =HAVERQ!D191-HAVERQ!D$166-'Chart Data'!AT28 -> 21 | AX28: 34700 | AY28: =100*(HAVERM!C67/HAVERM!B67) -> 23.656895 | AZ28: =AVERAGE($AY$7:$AY$374) -> 24.595806 | BB28: =HAVERM!C67 -> 2074 | BC28: =HAVERM!B67-HAVERM!C67 -> 6693 | BE28: 1977 | BF28: =100*((AVERAGE(HAVERQ!B16:B35)/AVERAGE(HAVERQ!B12:B31))-1) -> 2.0013052 | BG28: =$BL$6 -> 2.2155011 | BI28: 0 | BQ28: 1977 | BR28: =100*((AVERAGE(HAVERQ!C16:C35)/AVERAGE(HAVERQ!C12:C31))-1) -> 1.7067877 | BS28: =$BX$6 -> 1.9448021 | BU28: 0 | CH28: 2039 | CI28: =100*(DataA!B73/DataA!$B$53) -> 129.29701 | CJ28: =CJ27*(1+CO28/100) -> 134.48301 | CK28: 100 | CM28: =100*((CJ28/CI28)-1) -> 4.010921 | CO28: 1.7684017
A29: 2005 | B29: =DataA!F39*DataA!G39 -> 926585.3 | C29: =DataA!H39/DataA!I39 -> 11.571259 | D29: =DataA!E39 -> 2168000 | E29: =DataA!J39 -> -1.753736 | F29: =DataA!D39 -> 1791043 | G29: =DataA!B39 -> 1837927 | I29: =100*((F29/F28)-1) -> 3.0774587 | J29: =100*((G29/G28)-1) -> 2.7388424 | O29: 2025 | Q29: ='ONS pop proj migration'!B10/1000 -> 503.2 | R29: ='ONS pop proj migration'!C10/1000 -> 528 | S29: ='ONS pop proj migration'!D10/1000 -> 553.6 | V29: 1999 | W29: =100*((DataA!M33/DataA!M32)-1) -> 0.51355263 | X29: =AVERAGE(W20:W29) -> 0.2454158 | Y29: 0 | Z29: 65 | AA29: 60 | AC29: 25 | AD29: ='ONS pop proj 2021-based'!E27+'ONS pop proj 2021-based'!E134 -> 867168 | AE29: ='ONS pop proj 2021-based'!L27+'ONS pop proj 2021-based'!L134 -> 908515 | AF29: ='ONS pop proj 2021-based'!V27+'ONS pop proj 2021-based'!V134 -> 923106 | AG29: ='ONS pop proj 2021-based'!AF27+'ONS pop proj 2021-based'!AF134 -> 888175 | AI29: 2046 | AJ29: 0.16070322 | AK29: 0.61117682 | AL29: 0.22811996 | AN29: 42461 | AO29: =HAVERQ!F192-HAVERQ!F$166 -> 223 | AP29: =HAVERQ!G192-HAVERQ!G$166 -> 814 | AQ29: =HAVERQ!H192-HAVERQ!H$166 -> -83 | AR29: =HAVERQ!I192-HAVERQ!I$166 -> 1277 | AS29: =HAVERQ!J192-HAVERQ!J$166 -> 424 | AT29: =SUM(AO29:AS29) -> 2655 | AV29: =HAVERQ!D192-HAVERQ!D$166-'Chart Data'!AT29 -> 21 | AX29: 34731 | AY29: =100*(HAVERM!C68/HAVERM!B68) -> 23.809524 | AZ29: =AVERAGE($AY$7:$AY$374) -> 24.595806 | BB29: =HAVERM!C68 -> 2080 | BC29: =HAVERM!B68-HAVERM!C68 -> 6656 | BF29: =100*((AVERAGE(HAVERQ!B17:B36)/AVERAGE(HAVERQ!B13:B32))-1) -> 1.9159991 | BG29: =$BL$6 -> 2.2155011 | BI29: 0 | BR29: =100*((AVERAGE(HAVERQ!C17:C36)/AVERAGE(HAVERQ!C13:C32))-1) -> 1.5916683 | BS29: =$BX$6 -> 1.9448021 | BU29: 0 | CH29: 2040 | CI29: =100*(DataA!B74/DataA!$B$53) -> 131.30961 | CJ29: =CJ28*(1+CO29/100) -> 136.80817 | CK29: 100 | CM29: =100*((CJ29/CI29)-1) -> 4.1874784 | CO29: 1.7289661
A30: 2006 | B30: =DataA!F40*DataA!G40 -> 938041.64 | C30: =DataA!H40/DataA!I40 -> 11.80839 | D30: =DataA!E40 -> 2230000 | E30: =DataA!J40 -> -1.749689 | F30: =DataA!D40 -> 1840881 | G30: =DataA!B40 -> 1881785 | I30: =100*((F30/F29)-1) -> 2.7826244 | J30: =100*((G30/G29)-1) -> 2.3862754 | O30: 2026 | Q30: ='ONS pop proj migration'!B11/1000 -> 419.8 | R30: ='ONS pop proj migration'!C11/1000 -> 457 | S30: ='ONS pop proj migration'!D11/1000 -> 495.4 | V30: 2000 | W30: =100*((DataA!M34/DataA!M33)-1) -> 0.6089928 | X30: =AVERAGE(W21:W30) -> 0.28743284 | Y30: 0 | Z30: 65 | AA30: 60 | AC30: 26 | AD30: ='ONS pop proj 2021-based'!E28+'ONS pop proj 2021-based'!E135 -> 884339 | AE30: ='ONS pop proj 2021-based'!L28+'ONS pop proj 2021-based'!L135 -> 915404 | AF30: ='ONS pop proj 2021-based'!V28+'ONS pop proj 2021-based'!V135 -> 932764 | AG30: ='ONS pop proj 2021-based'!AF28+'ONS pop proj 2021-based'!AF135 -> 888908 | AI30: 2047 | AJ30: 0.16047403 | AK30: 0.61045971 | AL30: 0.22906626 | AN30: 42552 | AO30: =HAVERQ!F193-HAVERQ!F$166 -> 196 | AP30: =HAVERQ!G193-HAVERQ!G$166 -> 811 | AQ30: =HAVERQ!H193-HAVERQ!H$166 -> -77 | AR30: =HAVERQ!I193-HAVERQ!I$166 -> 1338 | AS30: =HAVERQ!J193-HAVERQ!J$166 -> 450 | AT30: =SUM(AO30:AS30) -> 2718 | AV30: =HAVERQ!D193-HAVERQ!D$166-'Chart Data'!AT30 -> 23 | AX30: 34759 | AY30: =100*(HAVERM!C69/HAVERM!B69) -> 23.821539 | AZ30: =AVERAGE($AY$7:$AY$374) -> 24.595806 | BB30: =HAVERM!C69 -> 2077 | BC30: =HAVERM!B69-HAVERM!C69 -> 6642 | BF30: =100*((AVERAGE(HAVERQ!B18:B37)/AVERAGE(HAVERQ!B14:B33))-1) -> 1.8642241 | BG30: =$BL$6 -> 2.2155011 | BI30: 0 | BR30: =100*((AVERAGE(HAVERQ!C18:C37)/AVERAGE(HAVERQ!C14:C33))-1) -> 1.5172279 | BS30: =$BX$6 -> 1.9448021 | BU30: 0 | CH30: 2041 | CI30: =100*(DataA!B75/DataA!$B$53) -> 133.32826 | CJ30: =CJ29*(1+CO30/100) -> 139.13269 | CK30: 100 | CM30: =100*((CJ30/CI30)-1) -> 4.3534917 | CO30: 1.6991097
A31: 2007 | B31: =DataA!F41*DataA!G41 -> 945614.3 | C31: =DataA!H41/DataA!I41 -> 12.020055 | D31: =DataA!E41 -> 2305000 | E31: =DataA!J41 -> -1.747736 | F31: =DataA!D41 -> 1883737 | G31: =DataA!B41 -> 1931094 | I31: =100*((F31/F30)-1) -> 2.3280158 | J31: =100*((G31/G30)-1) -> 2.6203312 | O31: 2027 | Q31: ='ONS pop proj migration'!B12/1000 -> 336.4 | R31: ='ONS pop proj migration'!C12/1000 -> 386 | S31: ='ONS pop proj migration'!D12/1000 -> 437.2 | V31: 2001 | W31: =100*((DataA!M35/DataA!M34)-1) -> 0.72055167 | X31: =AVERAGE(W22:W31) -> 0.34719856 | Y31: 0 | Z31: 65 | AA31: 60 | AC31: 27 | AD31: ='ONS pop proj 2021-based'!E29+'ONS pop proj 2021-based'!E136 -> 879278 | AE31: ='ONS pop proj 2021-based'!L29+'ONS pop proj 2021-based'!L136 -> 915443 | AF31: ='ONS pop proj 2021-based'!V29+'ONS pop proj 2021-based'!V136 -> 960740 | AG31: ='ONS pop proj 2021-based'!AF29+'ONS pop proj 2021-based'!AF136 -> 854905 | AI31: 2048 | AJ31: 0.16022167 | AK31: 0.60972283 | AL31: 0.2300555 | AN31: 42644 | AO31: =HAVERQ!F194-HAVERQ!F$166 -> 217 | AP31: =HAVERQ!G194-HAVERQ!G$166 -> 829 | AQ31: =HAVERQ!H194-HAVERQ!H$166 -> -86 | AR31: =HAVERQ!I194-HAVERQ!I$166 -> 1377 | AS31: =HAVERQ!J194-HAVERQ!J$166 -> 416 | AT31: =SUM(AO31:AS31) -> 2753 | AV31: =HAVERQ!D194-HAVERQ!D$166-'Chart Data'!AT31 -> 22 | AX31: 34790 | AY31: =100*(HAVERM!C70/HAVERM!B70) -> 24.216328 | AZ31: =AVERAGE($AY$7:$AY$374) -> 24.595806 | BB31: =HAVERM!C70 -> 2109 | BC31: =HAVERM!B70-HAVERM!C70 -> 6600 | BF31: =100*((AVERAGE(HAVERQ!B19:B38)/AVERAGE(HAVERQ!B15:B34))-1) -> 1.7797791 | BG31: =$BL$6 -> 2.2155011 | BI31: 0 | BR31: =100*((AVERAGE(HAVERQ!C19:C38)/AVERAGE(HAVERQ!C15:C34))-1) -> 1.4035088 | BS31: =$BX$6 -> 1.9448021 | BU31: 0 | CH31: 2042 | CI31: =100*(DataA!B76/DataA!$B$53) -> 135.35788 | CJ31: =CJ30*(1+CO31/100) -> 141.44641 | CK31: 100 | CM31: =100*((CJ31/CI31)-1) -> 4.4981049 | CO31: 1.662959
A32: 2008 | B32: =DataA!F42*DataA!G42 -> 954262.22 | C32: =DataA!H42/DataA!I42 -> 12.201911 | D32: =DataA!E42 -> 2365000 | E32: =DataA!J42 -> -1.747867 | F32: =DataA!D42 -> 1923485 | G32: =DataA!B42 -> 1926735 | I32: =100*((F32/F31)-1) -> 2.110061 | J32: =100*((G32/G31)-1) -> -0.22572697 | O32: 2028 | Q32: ='ONS pop proj migration'!B13/1000 -> 253 | R32: ='ONS pop proj migration'!C13/1000 -> 315 | S32: ='ONS pop proj migration'!D13/1000 -> 379 | V32: 2002 | W32: =100*((DataA!M36/DataA!M35)-1) -> 0.68498715 | X32: =AVERAGE(W23:W32) -> 0.41276223 | Y32: 0 | Z32: 65 | AA32: 60 | AC32: 28 | AD32: ='ONS pop proj 2021-based'!E30+'ONS pop proj 2021-based'!E137 -> 897977 | AE32: ='ONS pop proj 2021-based'!L30+'ONS pop proj 2021-based'!L137 -> 920518 | AF32: ='ONS pop proj 2021-based'!V30+'ONS pop proj 2021-based'!V137 -> 992214 | AG32: ='ONS pop proj 2021-based'!AF30+'ONS pop proj 2021-based'!AF137 -> 897638 | AI32: 2049 | AJ32: 0.15994334 | AK32: 0.60901183 | AL32: 0.23104483 | AN32: 42736 | AO32: =HAVERQ!F195-HAVERQ!F$166 -> 209 | AP32: =HAVERQ!G195-HAVERQ!G$166 -> 873 | AQ32: =HAVERQ!H195-HAVERQ!H$166 -> -87 | AR32: =HAVERQ!I195-HAVERQ!I$166 -> 1445 | AS32: =HAVERQ!J195-HAVERQ!J$166 -> 414 | AT32: =SUM(AO32:AS32) -> 2854 | AV32: =HAVERQ!D195-HAVERQ!D$166-'Chart Data'!AT32 -> 22 | AX32: 34820 | AY32: =100*(HAVERM!C71/HAVERM!B71) -> 24.320294 | AZ32: =AVERAGE($AY$7:$AY$374) -> 24.595806 | BB32: =HAVERM!C71 -> 2120 | BC32: =HAVERM!B71-HAVERM!C71 -> 6597 | BE32: 1978 | BF32: =100*((AVERAGE(HAVERQ!B20:B39)/AVERAGE(HAVERQ!B16:B35))-1) -> 1.5035189 | BG32: =$BL$6 -> 2.2155011 | BI32: 0 | BQ32: 1978 | BR32: =100*((AVERAGE(HAVERQ!C20:C39)/AVERAGE(HAVERQ!C16:C35))-1) -> 1.0864293 | BS32: =$BX$6 -> 1.9448021 | BU32: 0 | CH32: 2043 | CI32: =100*(DataA!B77/DataA!$B$53) -> 137.41148 | CJ32: =CJ31*(1+CO32/100) -> 143.74677 | CK32: 100 | CM32: =100*((CJ32/CI32)-1) -> 4.6104502 | CO32: 1.6263103
A33: 2009 | B33: =DataA!F43*DataA!G43 -> 945894.56 | C33: =DataA!H43/DataA!I43 -> 12.349724 | D33: =DataA!E43 -> 2387000 | E33: =DataA!J43 -> -1.74876 | F33: =DataA!D43 -> 1930839 | G33: =DataA!B43 -> 1837817 | I33: =100*((F33/F32)-1) -> 0.38232687 | J33: =100*((G33/G32)-1) -> -4.6149574 | O33: 2029 | Q33: ='ONS pop proj migration'!B14/1000 -> 253 | R33: ='ONS pop proj migration'!C14/1000 -> 315 | S33: ='ONS pop proj migration'!D14/1000 -> 379 | V33: 2003 | W33: =100*((DataA!M37/DataA!M36)-1) -> 0.63017067 | X33: =AVERAGE(W24:W33) -> 0.47262356 | Y33: 0 | Z33: 65 | AA33: 60 | AC33: 29 | AD33: ='ONS pop proj 2021-based'!E31+'ONS pop proj 2021-based'!E138 -> 925149 | AE33: ='ONS pop proj 2021-based'!L31+'ONS pop proj 2021-based'!L138 -> 926072 | AF33: ='ONS pop proj 2021-based'!V31+'ONS pop proj 2021-based'!V138 -> 1005597 | AG33: ='ONS pop proj 2021-based'!AF31+'ONS pop proj 2021-based'!AF138 -> 895214 | AI33: 2050 | AJ33: 0.15963834 | AK33: 0.60796284 | AL33: 0.23239882 | AN33: 42826 | AO33: =HAVERQ!F196-HAVERQ!F$166 -> 181 | AP33: =HAVERQ!G196-HAVERQ!G$166 -> 958 | AQ33: =HAVERQ!H196-HAVERQ!H$166 -> -33 | AR33: =HAVERQ!I196-HAVERQ!I$166 -> 1493 | AS33: =HAVERQ!J196-HAVERQ!J$166 -> 376 | AT33: =SUM(AO33:AS33) -> 2975 | AV33: =HAVERQ!D196-HAVERQ!D$166-'Chart Data'!AT33 -> 21 | AX33: 34851 | AY33: =100*(HAVERM!C72/HAVERM!B72) -> 24.358532 | AZ33: =AVERAGE($AY$7:$AY$374) -> 24.595806 | BB33: =HAVERM!C72 -> 2117 | BC33: =HAVERM!B72-HAVERM!C72 -> 6574 | BF33: =100*((AVERAGE(HAVERQ!B21:B40)/AVERAGE(HAVERQ!B17:B36))-1) -> 1.4232608 | BG33: =$BL$6 -> 2.2155011 | BI33: 0 | BR33: =100*((AVERAGE(HAVERQ!C21:C40)/AVERAGE(HAVERQ!C17:C36))-1) -> 0.98646035 | BS33: =$BX$6 -> 1.9448021 | BU33: 0 | CH33: 2044 | CI33: =100*(DataA!B78/DataA!$B$53) -> 139.48765 | CJ33: =CJ32*(1+CO33/100) -> 146.03948 | CK33: 100 | CM33: =100*((CJ33/CI33)-1) -> 4.6970682 | CO33: 1.5949661
A34: 2010 | B34: =DataA!F44*DataA!G44 -> 952641.9 | C34: =DataA!H44/DataA!I44 -> 12.459158 | D34: =DataA!E44 -> 2416000 | E34: =DataA!J44 -> -1.748997 | F34: =DataA!D44 -> 1951515 | G34: =DataA!B44 -> 1878960 | I34: =100*((F34/F33)-1) -> 1.0708298 | J34: =100*((G34/G33)-1) -> 2.2386886 | O34: 2030 | Q34: ='ONS pop proj migration'!B15/1000 -> 253 | R34: ='ONS pop proj migration'!C15/1000 -> 315 | S34: ='ONS pop proj migration'!D15/1000 -> 379 | V34: 2004 | W34: =100*((DataA!M38/DataA!M37)-1) -> 0.75987743 | X34: =AVERAGE(W25:W34) -> 0.53256781 | Y34: 0 | Z34: 65 | AA34: 60 | AC34: 30 | AD34: ='ONS pop proj 2021-based'!E32+'ONS pop proj 2021-based'!E139 -> 930732 | AE34: ='ONS pop proj 2021-based'!L32+'ONS pop proj 2021-based'!L139 -> 938301 | AF34: ='ONS pop proj 2021-based'!V32+'ONS pop proj 2021-based'!V139 -> 1002002 | AG34: ='ONS pop proj 2021-based'!AF32+'ONS pop proj 2021-based'!AF139 -> 929885 | AN34: 42917 | AO34: =HAVERQ!F197-HAVERQ!F$166 -> 103 | AP34: =HAVERQ!G197-HAVERQ!G$166 -> 987 | AQ34: =HAVERQ!H197-HAVERQ!H$166 -> -49 | AR34: =HAVERQ!I197-HAVERQ!I$166 -> 1534 | AS34: =HAVERQ!J197-HAVERQ!J$166 -> 394 | AT34: =SUM(AO34:AS34) -> 2969 | AV34: =HAVERQ!D197-HAVERQ!D$166-'Chart Data'!AT34 -> 22 | AX34: 34881 | AY34: =100*(HAVERM!C73/HAVERM!B73) -> 24.500404 | AZ34: =AVERAGE($AY$7:$AY$374) -> 24.595806 | BB34: =HAVERM!C73 -> 2121 | BC34: =HAVERM!B73-HAVERM!C73 -> 6536 | BF34: =100*((AVERAGE(HAVERQ!B22:B41)/AVERAGE(HAVERQ!B18:B37))-1) -> 1.4492754 | BG34: =$BL$6 -> 2.2155011 | BI34: 0 | BR34: =100*((AVERAGE(HAVERQ!C22:C41)/AVERAGE(HAVERQ!C18:C37))-1) -> 1.0027963 | BS34: =$BX$6 -> 1.9448021 | BU34: 0 | CH34: 2045 | CI34: =100*(DataA!B79/DataA!$B$53) -> 141.58598 | CJ34: =CJ33*(1+CO34/100) -> 148.33897 | CK34: 100 | CM34: =100*((CJ34/CI34)-1) -> 4.7695292 | CO34: 1.5745626
A35: 2011 | B35: =DataA!F45*DataA!G45 -> 956189.83 | C35: =DataA!H45/DataA!I45 -> 12.56887 | D35: =DataA!E45 -> 2443000 | E35: =DataA!J45 -> -1.749272 | F35: =DataA!D45 -> 1968889 | G35: =DataA!B45 -> 1900476 | I35: =100*((F35/F34)-1) -> 0.89028268 | J35: =100*((G35/G34)-1) -> 1.1451015 | O35: 2031 | Q35: =Q34 -> 253 | R35: =R34 -> 315 | S35: =S34 -> 379 | V35: 2005 | W35: =100*((DataA!M39/DataA!M38)-1) -> 0.97276662 | X35: =AVERAGE(W26:W35) -> 0.59863954 | Y35: 0 | Z35: 65 | AA35: 60 | AC35: 31 | AD35: ='ONS pop proj 2021-based'!E33+'ONS pop proj 2021-based'!E140 -> 961261 | AE35: ='ONS pop proj 2021-based'!L33+'ONS pop proj 2021-based'!L140 -> 964364 | AF35: ='ONS pop proj 2021-based'!V33+'ONS pop proj 2021-based'!V140 -> 1007491 | AG35: ='ONS pop proj 2021-based'!AF33+'ONS pop proj 2021-based'!AF140 -> 950808 | AN35: 43009 | AO35: =HAVERQ!F198-HAVERQ!F$166 -> 103 | AP35: =HAVERQ!G198-HAVERQ!G$166 -> 985 | AQ35: =HAVERQ!H198-HAVERQ!H$166 -> -12 | AR35: =HAVERQ!I198-HAVERQ!I$166 -> 1584 | AS35: =HAVERQ!J198-HAVERQ!J$166 -> 396 | AT35: =SUM(AO35:AS35) -> 3056 | AV35: =HAVERQ!D198-HAVERQ!D$166-'Chart Data'!AT35 -> 21 | AX35: 34912 | AY35: =100*(HAVERM!C74/HAVERM!B74) -> 24.667515 | AZ35: =AVERAGE($AY$7:$AY$374) -> 24.595806 | BB35: =HAVERM!C74 -> 2133 | BC35: =HAVERM!B74-HAVERM!C74 -> 6514 | BF35: =100*((AVERAGE(HAVERQ!B23:B42)/AVERAGE(HAVERQ!B19:B38))-1) -> 1.485305 | BG35: =$BL$6 -> 2.2155011 | BI35: 0 | BR35: =100*((AVERAGE(HAVERQ!C23:C42)/AVERAGE(HAVERQ!C19:C38))-1) -> 1.047674 | BS35: =$BX$6 -> 1.9448021 | BU35: 0 | CH35: 2046 | CI35: =100*(DataA!B80/DataA!$B$53) -> 143.70651 | CJ35: =CJ34*(1+CO35/100) -> 150.65784 | CK35: 100 | CM35: =100*((CJ35/CI35)-1) -> 4.8371654 | CO35: 1.5632227
A36: 2012 | B36: =DataA!F46*DataA!G46 -> 973104.43 | C36: =DataA!H46/DataA!I46 -> 12.676121 | D36: =DataA!E46 -> 2469000 | E36: =DataA!J46 -> -1.749547 | F36: =DataA!D46 -> 2003656 | G36: =DataA!B46 -> 1929229 | I36: =100*((F36/F35)-1) -> 1.7658182 | J36: =100*((G36/G35)-1) -> 1.5129368 | O36: 2032 | Q36: =Q35 -> 253 | R36: =R35 -> 315 | S36: =S35 -> 379 | V36: 2006 | W36: =100*((DataA!M40/DataA!M39)-1) -> 0.84869501 | X36: =AVERAGE(W27:W36) -> 0.64683076 | Y36: 0 | Z36: 65 | AA36: 60 | AC36: 32 | AD36: ='ONS pop proj 2021-based'!E34+'ONS pop proj 2021-based'!E141 -> 972793 | AE36: ='ONS pop proj 2021-based'!L34+'ONS pop proj 2021-based'!L141 -> 968296 | AF36: ='ONS pop proj 2021-based'!V34+'ONS pop proj 2021-based'!V141 -> 1023231 | AG36: ='ONS pop proj 2021-based'!AF34+'ONS pop proj 2021-based'!AF141 -> 968790 | AN36: 43101 | AO36: =HAVERQ!F199-HAVERQ!F$166 -> 137 | AP36: =HAVERQ!G199-HAVERQ!G$166 -> 995 | AQ36: =HAVERQ!H199-HAVERQ!H$166 -> 46 | AR36: =HAVERQ!I199-HAVERQ!I$166 -> 1655 | AS36: =HAVERQ!J199-HAVERQ!J$166 -> 408 | AT36: =SUM(AO36:AS36) -> 3241 | AV36: =HAVERQ!D199-HAVERQ!D$166-'Chart Data'!AT36 -> 21 | AX36: 34943 | AY36: =100*(HAVERM!C75/HAVERM!B75) -> 24.702209 | AZ36: =AVERAGE($AY$7:$AY$374) -> 24.595806 | BB36: =HAVERM!C75 -> 2136 | BC36: =HAVERM!B75-HAVERM!C75 -> 6511 | BE36: 1979 | BF36: =100*((AVERAGE(HAVERQ!B24:B43)/AVERAGE(HAVERQ!B20:B39))-1) -> 1.7438807 | BG36: =$BL$6 -> 2.2155011 | BI36: 0 | BQ36: 1979 | BR36: =100*((AVERAGE(HAVERQ!C24:C43)/AVERAGE(HAVERQ!C20:C39))-1) -> 1.3242491 | BS36: =$BX$6 -> 1.9448021 | BU36: 0 | CH36: 2047 | CI36: =100*(DataA!B81/DataA!$B$53) -> 145.84956 | CJ36: =CJ35*(1+CO36/100) -> 152.97304 | CK36: 100 | CM36: =100*((CJ36/CI36)-1) -> 4.8841239 | CO36: 1.536727
A37: 2013 | B37: =DataA!F47*DataA!G47 -> 988293.16 | C37: =DataA!H47/DataA!I47 -> 12.780522 | D37: =DataA!E47 -> 2507000 | E37: =DataA!J47 -> -1.749822 | F37: =DataA!D47 -> 2037139 | G37: =DataA!B47 -> 1963807 | I37: =100*((F37/F36)-1) -> 1.6710952 | J37: =100*((G37/G36)-1) -> 1.7923222 | O37: 2033 | Q37: =Q36 -> 253 | R37: =R36 -> 315 | S37: =S36 -> 379 | V37: 2007 | W37: =100*((DataA!M41/DataA!M40)-1) -> 0.69772108 | X37: =AVERAGE(W28:W37) -> 0.68121313 | Y37: 0 | Z37: 65 | AA37: 60 | AC37: 33 | AD37: ='ONS pop proj 2021-based'!E35+'ONS pop proj 2021-based'!E142 -> 967075 | AE37: ='ONS pop proj 2021-based'!L35+'ONS pop proj 2021-based'!L142 -> 983931 | AF37: ='ONS pop proj 2021-based'!V35+'ONS pop proj 2021-based'!V142 -> 1000254 | AG37: ='ONS pop proj 2021-based'!AF35+'ONS pop proj 2021-based'!AF142 -> 991725 | AN37: 43191 | AO37: =HAVERQ!F200-HAVERQ!F$166 -> 124 | AP37: =HAVERQ!G200-HAVERQ!G$166 -> 987 | AQ37: =HAVERQ!H200-HAVERQ!H$166 -> 23 | AR37: =HAVERQ!I200-HAVERQ!I$166 -> 1708 | AS37: =HAVERQ!J200-HAVERQ!J$166 -> 437 | AT37: =SUM(AO37:AS37) -> 3279 | AV37: =HAVERQ!D200-HAVERQ!D$166-'Chart Data'!AT37 -> 22 | AX37: 34973 | AY37: =100*(HAVERM!C76/HAVERM!B76) -> 24.708329 | AZ37: =AVERAGE($AY$7:$AY$374) -> 24.595806 | BB37: =HAVERM!C76 -> 2139 | BC37: =HAVERM!B76-HAVERM!C76 -> 6518 | BF37: =100*((AVERAGE(HAVERQ!B25:B44)/AVERAGE(HAVERQ!B21:B40))-1) -> 2.0944602 | BG37: =$BL$6 -> 2.2155011 | BI37: 0 | BR37: =100*((AVERAGE(HAVERQ!C25:C44)/AVERAGE(HAVERQ!C21:C40))-1) -> 1.7046543 | BS37: =$BX$6 -> 1.9448021 | BU37: 0 | CH37: 2048 | CI37: =100*(DataA!B82/DataA!$B$53) -> 148.01544 | CJ37: =CJ36*(1+CO37/100) -> 155.28329 | CK37: 100 | CM37: =100*((CJ37/CI37)-1) -> 4.9101998 | CO37: 1.5102389
A38: 2014 | B38: =DataA!F48*DataA!G48 -> 1000770.9 | C38: =DataA!H48/DataA!I48 -> 12.882332 | D38: =DataA!E48 -> 2553000 | E38: =DataA!J48 -> -1.750097 | F38: =DataA!D48 -> 2069974 | G38: =DataA!B48 -> 2026566 | I38: =100*((F38/F37)-1) -> 1.6118193 | J38: =100*((G38/G37)-1) -> 3.1957825 | O38: 2034 | Q38: =Q37 -> 253 | R38: =R37 -> 315 | S38: =S37 -> 379 | V38: 2008 | W38: =100*((DataA!M42/DataA!M41)-1) -> 0.60565971 | X38: =AVERAGE(W29:W38) -> 0.70429748 | Y38: 0 | Z38: 65 | AA38: 60 | AC38: 34 | AD38: ='ONS pop proj 2021-based'!E36+'ONS pop proj 2021-based'!E143 -> 959467 | AE38: ='ONS pop proj 2021-based'!L36+'ONS pop proj 2021-based'!L143 -> 973589 | AF38: ='ONS pop proj 2021-based'!V36+'ONS pop proj 2021-based'!V143 -> 993333 | AG38: ='ONS pop proj 2021-based'!AF36+'ONS pop proj 2021-based'!AF143 -> 1018721 | AN38: 43282 | AO38: =HAVERQ!F201-HAVERQ!F$166 -> 90 | AP38: =HAVERQ!G201-HAVERQ!G$166 -> 1007 | AQ38: =HAVERQ!H201-HAVERQ!H$166 -> -11 | AR38: =HAVERQ!I201-HAVERQ!I$166 -> 1773 | AS38: =HAVERQ!J201-HAVERQ!J$166 -> 463 | AT38: =SUM(AO38:AS38) -> 3322 | AV38: =HAVERQ!D201-HAVERQ!D$166-'Chart Data'!AT38 -> 24 | AX38: 35004 | AY38: =100*(HAVERM!C77/HAVERM!B77) -> 24.898762 | AZ38: =AVERAGE($AY$7:$AY$374) -> 24.595806 | BB38: =HAVERM!C77 -> 2152 | BC38: =HAVERM!B77-HAVERM!C77 -> 6491 | BF38: =100*((AVERAGE(HAVERQ!B26:B45)/AVERAGE(HAVERQ!B22:B41))-1) -> 2.1793535 | BG38: =$BL$6 -> 2.2155011 | BI38: 0 | BR38: =100*((AVERAGE(HAVERQ!C26:C45)/AVERAGE(HAVERQ!C22:C41))-1) -> 1.8329356 | BS38: =$BX$6 -> 1.9448021 | BU38: 0 | CH38: 2049 | CI38: =100*(DataA!B83/DataA!$B$53) -> 150.20424 | CJ38: =CJ37*(1+CO38/100) -> 157.58305 | CK38: 100 | CM38: =100*((CJ38/CI38)-1) -> 4.9125183 | CO38: 1.4810054
A39: 2015 | B39: =DataA!F49*DataA!G49 -> 1009839.7 | C39: =DataA!H49/DataA!I49 -> 12.98167 | D39: =DataA!E49 -> 2612000 | E39: =DataA!J49 -> -1.750372 | F39: =DataA!D49 -> 2101006 | G39: =DataA!B49 -> 2071561 | I39: =100*((F39/F38)-1) -> 1.4991493 | J39: =100*((G39/G38)-1) -> 2.2202583 | O39: 2035 | Q39: =Q38 -> 253 | R39: =R38 -> 315 | S39: =S38 -> 379 | V39: 2009 | W39: =100*((DataA!M43/DataA!M42)-1) -> 0.51968981 | X39: =AVERAGE(W30:W39) -> 0.7049112 | Y39: 0 | Z39: 65 | AA39: 60 | AC39: 35 | AD39: ='ONS pop proj 2021-based'!E37+'ONS pop proj 2021-based'!E144 -> 968453 | AE39: ='ONS pop proj 2021-based'!L37+'ONS pop proj 2021-based'!L144 -> 985117 | AF39: ='ONS pop proj 2021-based'!V37+'ONS pop proj 2021-based'!V144 -> 1001988 | AG39: ='ONS pop proj 2021-based'!AF37+'ONS pop proj 2021-based'!AF144 -> 1017045 | AN39: 43374 | AO39: =HAVERQ!F202-HAVERQ!F$166 -> 119 | AP39: =HAVERQ!G202-HAVERQ!G$166 -> 1066 | AQ39: =HAVERQ!H202-HAVERQ!H$166 -> 16 | AR39: =HAVERQ!I202-HAVERQ!I$166 -> 1791 | AS39: =HAVERQ!J202-HAVERQ!J$166 -> 499 | AT39: =SUM(AO39:AS39) -> 3491 | AV39: =HAVERQ!D202-HAVERQ!D$166-'Chart Data'!AT39 -> 25 | AX39: 35034 | AY39: =100*(HAVERM!C78/HAVERM!B78) -> 24.886878 | AZ39: =AVERAGE($AY$7:$AY$374) -> 24.595806 | BB39: =HAVERM!C78 -> 2145 | BC39: =HAVERM!B78-HAVERM!C78 -> 6474 | BF39: =100*((AVERAGE(HAVERQ!B27:B46)/AVERAGE(HAVERQ!B23:B42))-1) -> 2.3250986 | BG39: =$BL$6 -> 2.2155011 | BI39: 0 | BR39: =100*((AVERAGE(HAVERQ!C27:C46)/AVERAGE(HAVERQ!C23:C42))-1) -> 2.0070389 | BS39: =$BX$6 -> 1.9448021 | BU39: 0 | CH39: 2050 | CI39: =100*(DataA!B84/DataA!$B$53) -> 152.41569 | CJ39: =CJ38*(1+CO39/100) -> 159.89163 | CK39: 100 | CM39: =100*((CJ39/CI39)-1) -> 4.9049689 | CO39: 1.4649921
A40: 2016 | B40: =DataA!F50*DataA!G50 -> 1020225.9 | C40: =DataA!H50/DataA!I50 -> 13.078864 | D40: =DataA!E50 -> 2679000 | E40: =DataA!J50 -> -1.750647 | F40: =DataA!D50 -> 2136889 | G40: =DataA!B50 -> 2111357 | I40: =100*((F40/F39)-1) -> 1.7078961 | J40: =100*((G40/G39)-1) -> 1.9210634 | O40: 2036 | Q40: =Q39 -> 253 | R40: =R39 -> 315 | S40: =S39 -> 379 | V40: 2010 | W40: =100*((DataA!M44/DataA!M43)-1) -> 0.79323743 | X40: =AVERAGE(W31:W40) -> 0.72333566 | Y40: 0 | Z40: 65 | AA40: 60 | AC40: 36 | AD40: ='ONS pop proj 2021-based'!E38+'ONS pop proj 2021-based'!E145 -> 944985 | AE40: ='ONS pop proj 2021-based'!L38+'ONS pop proj 2021-based'!L145 -> 1004030 | AF40: ='ONS pop proj 2021-based'!V38+'ONS pop proj 2021-based'!V145 -> 1006690 | AG40: ='ONS pop proj 2021-based'!AF38+'ONS pop proj 2021-based'!AF145 -> 1024537 | AN40: 43466 | AO40: =HAVERQ!F203-HAVERQ!F$166 -> 128 | AP40: =HAVERQ!G203-HAVERQ!G$166 -> 1108 | AQ40: =HAVERQ!H203-HAVERQ!H$166 -> -8 | AR40: =HAVERQ!I203-HAVERQ!I$166 -> 1872 | AS40: =HAVERQ!J203-HAVERQ!J$166 -> 490 | AT40: =SUM(AO40:AS40) -> 3590 | AV40: =HAVERQ!D203-HAVERQ!D$166-'Chart Data'!AT40 -> 29 | AX40: 35065 | AY40: =100*(HAVERM!C79/HAVERM!B79) -> 24.979762 | AZ40: =AVERAGE($AY$7:$AY$374) -> 24.595806 | BB40: =HAVERM!C79 -> 2160 | BC40: =HAVERM!B79-HAVERM!C79 -> 6487 | BE40: 1980 | BF40: =100*((AVERAGE(HAVERQ!B28:B47)/AVERAGE(HAVERQ!B24:B43))-1) -> 2.3128549 | BG40: =$BL$6 -> 2.2155011 | BI40: 0 | BQ40: 1980 | BR40: =100*((AVERAGE(HAVERQ!C28:C47)/AVERAGE(HAVERQ!C24:C43))-1) -> 2.0361777 | BS40: =$BX$6 -> 1.9448021 | BU40: 0
A41: 2017 | B41: =DataA!F51*DataA!G51 -> 1028849 | C41: =DataA!H51/DataA!I51 -> 13.174425 | D41: =DataA!E51 -> 2744000 | E41: =DataA!J51 -> -1.750923 | F41: =DataA!D51 -> 2171464 | G41: =DataA!B51 -> 2167415 | I41: =100*((F41/F40)-1) -> 1.6180064 | J41: =100*((G41/G40)-1) -> 2.6550697 | O41: 2037 | Q41: =Q40 -> 253 | R41: =R40 -> 315 | S41: =S40 -> 379 | V41: 2011 | W41: =100*((DataA!M45/DataA!M44)-1) -> 0.96544909 | X41: =AVERAGE(W32:W41) -> 0.7478254 | Y41: 0 | Z41: 65 | AA41: =AA40+($AA$48-$AA$40)*1/8 -> 60.625 | AC41: 37 | AD41: ='ONS pop proj 2021-based'!E39+'ONS pop proj 2021-based'!E146 -> 935686 | AE41: ='ONS pop proj 2021-based'!L39+'ONS pop proj 2021-based'!L146 -> 1001147 | AF41: ='ONS pop proj 2021-based'!V39+'ONS pop proj 2021-based'!V146 -> 1000281 | AG41: ='ONS pop proj 2021-based'!AF39+'ONS pop proj 2021-based'!AF146 -> 1045960 | AN41: 43556 | AO41: =HAVERQ!F204-HAVERQ!F$166 -> 99 | AP41: =HAVERQ!G204-HAVERQ!G$166 -> 1126 | AQ41: =HAVERQ!H204-HAVERQ!H$166 -> -16 | AR41: =HAVERQ!I204-HAVERQ!I$166 -> 1925 | AS41: =HAVERQ!J204-HAVERQ!J$166 -> 571 | AT41: =SUM(AO41:AS41) -> 3705 | AV41: =HAVERQ!D204-HAVERQ!D$166-'Chart Data'!AT41 -> 32 | AX41: 35096 | AY41: =100*(HAVERM!C80/HAVERM!B80) -> 24.919429 | AZ41: =AVERAGE($AY$7:$AY$374) -> 24.595806 | BB41: =HAVERM!C80 -> 2165 | BC41: =HAVERM!B80-HAVERM!C80 -> 6523 | BF41: =100*((AVERAGE(HAVERQ!B29:B48)/AVERAGE(HAVERQ!B25:B44))-1) -> 2.1848395 | BG41: =$BL$6 -> 2.2155011 | BI41: 0 | BR41: =100*((AVERAGE(HAVERQ!C29:C48)/AVERAGE(HAVERQ!C25:C44))-1) -> 1.9303202 | BS41: =$BX$6 -> 1.9448021 | BU41: 0
A42: 2018 | B42: =DataA!F52*DataA!G52 -> 1036150.7 | C42: =DataA!H52/DataA!I52 -> 13.268473 | D42: =DataA!E52 -> 2797000 | E42: =DataA!J52 -> -1.751199 | F42: =DataA!D52 -> 2202562 | G42: =DataA!B52 -> 2197841 | I42: =100*((F42/F41)-1) -> 1.4321214 | J42: =100*((G42/G41)-1) -> 1.4037921 | O42: 2038 | Q42: =Q41 -> 253 | R42: =R41 -> 315 | S42: =S41 -> 379 | V42: 2012 | W42: =100*((DataA!M46/DataA!M45)-1) -> 0.56942504 | X42: =AVERAGE(W33:W42) -> 0.73626919 | Y42: 0 | Z42: 65 | AA42: =AA41+($AA$48-$AA$40)*1/8 -> 61.25 | AC42: 38 | AD42: ='ONS pop proj 2021-based'!E40+'ONS pop proj 2021-based'!E147 -> 929941 | AE42: ='ONS pop proj 2021-based'!L40+'ONS pop proj 2021-based'!L147 -> 1022754 | AF42: ='ONS pop proj 2021-based'!V40+'ONS pop proj 2021-based'!V147 -> 997054 | AG42: ='ONS pop proj 2021-based'!AF40+'ONS pop proj 2021-based'!AF147 -> 1069010 | AN42: 43647 | AO42: =HAVERQ!F205-HAVERQ!F$166 -> -2 | AP42: =HAVERQ!G205-HAVERQ!G$166 -> 1153 | AQ42: =HAVERQ!H205-HAVERQ!H$166 -> 24 | AR42: =HAVERQ!I205-HAVERQ!I$166 -> 1953 | AS42: =HAVERQ!J205-HAVERQ!J$166 -> 517 | AT42: =SUM(AO42:AS42) -> 3645 | AV42: =HAVERQ!D205-HAVERQ!D$166-'Chart Data'!AT42 -> 32 | AX42: 35125 | AY42: =100*(HAVERM!C81/HAVERM!B81) -> 24.92219 | AZ42: =AVERAGE($AY$7:$AY$374) -> 24.595806 | BB42: =HAVERM!C81 -> 2162 | BC42: =HAVERM!B81-HAVERM!C81 -> 6513 | BF42: =100*((AVERAGE(HAVERQ!B30:B49)/AVERAGE(HAVERQ!B26:B45))-1) -> 2.2655373 | BG42: =$BL$6 -> 2.2155011 | BI42: 0 | BR42: =100*((AVERAGE(HAVERQ!C30:C49)/AVERAGE(HAVERQ!C26:C45))-1) -> 1.9968126 | BS42: =$BX$6 -> 1.9448021 | BU42: 0
A43: 2019 | B43: =DataA!F53*DataA!G53 -> 1048820.4 | C43: =DataA!H53/DataA!I53 -> 13.361084 | D43: =DataA!E53 -> 2850000 | E43: =DataA!J53 -> -1.751474 | F43: =DataA!D53 -> 2238861 | G43: =DataA!B53 -> 2233921 | I43: =100*((F43/F42)-1) -> 1.6480353 | J43: =100*((G43/G42)-1) -> 1.641611 | O43: 2039 | Q43: =Q42 -> 253 | R43: =R42 -> 315 | S43: =S42 -> 379 | V43: 2013 | W43: =100*((DataA!M47/DataA!M46)-1) -> 0.67568201 | X43: =AVERAGE(W34:W43) -> 0.74082032 | Y43: 0 | Z43: 65 | AA43: =AA42+($AA$48-$AA$40)*1/8 -> 61.875 | AC43: 39 | AD43: ='ONS pop proj 2021-based'!E41+'ONS pop proj 2021-based'!E148 -> 899504 | AE43: ='ONS pop proj 2021-based'!L41+'ONS pop proj 2021-based'!L148 -> 1026230 | AF43: ='ONS pop proj 2021-based'!V41+'ONS pop proj 2021-based'!V148 -> 993811 | AG43: ='ONS pop proj 2021-based'!AF41+'ONS pop proj 2021-based'!AF148 -> 1073571 | AN43: 43739 | AO43: =HAVERQ!F206-HAVERQ!F$166 -> 79 | AP43: =HAVERQ!G206-HAVERQ!G$166 -> 1178 | AQ43: =HAVERQ!H206-HAVERQ!H$166 -> 49 | AR43: =HAVERQ!I206-HAVERQ!I$166 -> 2015 | AS43: =HAVERQ!J206-HAVERQ!J$166 -> 501 | AT43: =SUM(AO43:AS43) -> 3822 | AV43: =HAVERQ!D206-HAVERQ!D$166-'Chart Data'!AT43 -> 30 | AX43: 35156 | AY43: =100*(HAVERM!C82/HAVERM!B82) -> 25.349186 | AZ43: =AVERAGE($AY$7:$AY$374) -> 24.595806 | BB43: =HAVERM!C82 -> 2196 | BC43: =HAVERM!B82-HAVERM!C82 -> 6467 | BF43: =100*((AVERAGE(HAVERQ!B31:B50)/AVERAGE(HAVERQ!B27:B46))-1) -> 2.1809698 | BG43: =$BL$6 -> 2.2155011 | BI43: 0 | BR43: =100*((AVERAGE(HAVERQ!C31:C50)/AVERAGE(HAVERQ!C27:C46))-1) -> 1.8649758 | BS43: =$BX$6 -> 1.9448021 | BU43: 0
A44: 2020 | B44: =DataA!F54*DataA!G54 -> 945814.45 | C44: =DataA!H54/DataA!I54 -> 13.452379 | D44: =DataA!E54 -> 2869000 | E44: =DataA!J54 -> -1.757496 | F44: =DataA!D54 -> 2094635 | G44: =DataA!B54 -> 2002489 | I44: =100*((F44/F43)-1) -> -6.4419363 | J44: =100*((G44/G43)-1) -> -10.359901 | O44: 2040 | Q44: =Q43 -> 253 | R44: =R43 -> 315 | S44: =S43 -> 379 | V44: 2014 | W44: =100*((DataA!M48/DataA!M47)-1) -> 0.83441757 | X44: =AVERAGE(W35:W44) -> 0.74827434 | Y44: 0 | Z44: 65 | AA44: =AA43+($AA$48-$AA$40)*1/8 -> 62.5 | AC44: 40 | AD44: ='ONS pop proj 2021-based'!E42+'ONS pop proj 2021-based'!E149 -> 899204 | AE44: ='ONS pop proj 2021-based'!L42+'ONS pop proj 2021-based'!L149 -> 1013809 | AF44: ='ONS pop proj 2021-based'!V42+'ONS pop proj 2021-based'!V149 -> 997297 | AG44: ='ONS pop proj 2021-based'!AF42+'ONS pop proj 2021-based'!AF149 -> 1061365 | AN44: 43831 | AO44: =HAVERQ!F207-HAVERQ!F$166 -> 81 | AP44: =HAVERQ!G207-HAVERQ!G$166 -> 1186 | AQ44: =HAVERQ!H207-HAVERQ!H$166 -> -6 | AR44: =HAVERQ!I207-HAVERQ!I$166 -> 1995 | AS44: =HAVERQ!J207-HAVERQ!J$166 -> 614 | AT44: =SUM(AO44:AS44) -> 3870 | AV44: =HAVERQ!D207-HAVERQ!D$166-'Chart Data'!AT44 -> 28 | AX44: 35186 | AY44: =100*(HAVERM!C83/HAVERM!B83) -> 25.288284 | AZ44: =AVERAGE($AY$7:$AY$374) -> 24.595806 | BB44: =HAVERM!C83 -> 2193 | BC44: =HAVERM!B83-HAVERM!C83 -> 6479 | BE44: 1981 | BF44: =100*((AVERAGE(HAVERQ!B32:B51)/AVERAGE(HAVERQ!B28:B47))-1) -> 2.1596528 | BG44: =$BL$6 -> 2.2155011 | BI44: 0 | BQ44: 1981 | BR44: =100*((AVERAGE(HAVERQ!C32:C51)/AVERAGE(HAVERQ!C28:C47))-1) -> 1.7542231 | BS44: =$BX$6 -> 1.9448021 | BU44: 0
A45: 2021 | B45: =DataA!F55*DataA!G55 -> 1011126.5 | C45: =DataA!H55/DataA!I55 -> 13.542331 | D45: =DataA!E55 -> 2894000 | E45: =DataA!J55 -> -1.763263 | F45: =DataA!D55 -> 2185763 | G45: =DataA!B55 -> 2176203 | I45: =100*((F45/F44)-1) -> 4.3505432 | J45: =100*((G45/G44)-1) -> 8.6749041 | O45: 2041 | Q45: =Q44 -> 253 | R45: =R44 -> 315 | S45: =S44 -> 379 | V45: 2015 | W45: =100*((DataA!M49/DataA!M48)-1) -> 0.97231427 | X45: =AVERAGE(W36:W45) -> 0.7482291 | Y45: 0 | Z45: 65 | AA45: =AA44+($AA$48-$AA$40)*1/8 -> 63.125 | AC45: 41 | AD45: ='ONS pop proj 2021-based'!E43+'ONS pop proj 2021-based'!E150 -> 894686 | AE45: ='ONS pop proj 2021-based'!L43+'ONS pop proj 2021-based'!L150 -> 999549 | AF45: ='ONS pop proj 2021-based'!V43+'ONS pop proj 2021-based'!V150 -> 1014515 | AG45: ='ONS pop proj 2021-based'!AF43+'ONS pop proj 2021-based'!AF150 -> 1058170 | AN45: 43922 | AO45: =HAVERQ!F208-HAVERQ!F$166 -> -44 | AP45: =HAVERQ!G208-HAVERQ!G$166 -> 1145 | AQ45: =HAVERQ!H208-HAVERQ!H$166 -> -80 | AR45: =HAVERQ!I208-HAVERQ!I$166 -> 1951 | AS45: =HAVERQ!J208-HAVERQ!J$166 -> 471 | AT45: =SUM(AO45:AS45) -> 3443 | AV45: =HAVERQ!D208-HAVERQ!D$166-'Chart Data'!AT45 -> 26 | AX45: 35217 | AY45: =100*(HAVERM!C84/HAVERM!B84) -> 25.490646 | AZ45: =AVERAGE($AY$7:$AY$374) -> 24.595806 | BB45: =HAVERM!C84 -> 2221 | BC45: =HAVERM!B84-HAVERM!C84 -> 6492 | BF45: =100*((AVERAGE(HAVERQ!B33:B52)/AVERAGE(HAVERQ!B29:B48))-1) -> 2.21843 | BG45: =$BL$6 -> 2.2155011 | BI45: 0 | BR45: =100*((AVERAGE(HAVERQ!C33:C52)/AVERAGE(HAVERQ!C29:C48))-1) -> 1.6997691 | BS45: =$BX$6 -> 1.9448021 | BU45: 0
A46: 2022 | B46: =DataA!F56*DataA!G56 -> 1044464.3 | C46: =DataA!H56/DataA!I56 -> 13.631032 | D46: =DataA!E56 -> 2939000 | E46: =DataA!J56 -> -1.76374 | F46: =DataA!D56 -> 2244500 | G46: =DataA!B56 -> 2270764 | I46: =100*((F46/F45)-1) -> 2.6872538 | J46: =100*((G46/G45)-1) -> 4.3452288 | O46: 2042 | Q46: =Q45 -> 253 | R46: =R45 -> 315 | S46: =S45 -> 379 | V46: 2016 | W46: =100*((DataA!M50/DataA!M49)-1) -> 0.98796051 | X46: =AVERAGE(W37:W46) -> 0.76215565 | Y46: 0 | Z46: 65 | AA46: =AA45+($AA$48-$AA$40)*1/8 -> 63.75 | AC46: 42 | AD46: ='ONS pop proj 2021-based'!E44+'ONS pop proj 2021-based'!E151 -> 901588 | AE46: ='ONS pop proj 2021-based'!L44+'ONS pop proj 2021-based'!L151 -> 1002175 | AF46: ='ONS pop proj 2021-based'!V44+'ONS pop proj 2021-based'!V151 -> 1010607 | AG46: ='ONS pop proj 2021-based'!AF44+'ONS pop proj 2021-based'!AF151 -> 1066021 | AN46: 44013 | AO46: =HAVERQ!F209-HAVERQ!F$166 -> -231 | AP46: =HAVERQ!G209-HAVERQ!G$166 -> 1155 | AQ46: =HAVERQ!H209-HAVERQ!H$166 -> -142 | AR46: =HAVERQ!I209-HAVERQ!I$166 -> 1919 | AS46: =HAVERQ!J209-HAVERQ!J$166 -> 521 | AT46: =SUM(AO46:AS46) -> 3222 | AV46: =HAVERQ!D209-HAVERQ!D$166-'Chart Data'!AT46 -> 30 | AX46: 35247 | AY46: =100*(HAVERM!C85/HAVERM!B85) -> 25.680487 | AZ46: =AVERAGE($AY$7:$AY$374) -> 24.595806 | BB46: =HAVERM!C85 -> 2236 | BC46: =HAVERM!B85-HAVERM!C85 -> 6471 | BF46: =100*((AVERAGE(HAVERQ!B34:B53)/AVERAGE(HAVERQ!B30:B49))-1) -> 2.2552639 | BG46: =$BL$6 -> 2.2155011 | BI46: 0 | BR46: =100*((AVERAGE(HAVERQ!C34:C53)/AVERAGE(HAVERQ!C30:C49))-1) -> 1.6360294 | BS46: =$BX$6 -> 1.9448021 | BU46: 0
A47: 2023 | B47: =DataA!F57*DataA!G57 -> 1046264.5 | C47: =DataA!H57/DataA!I57 -> 13.718335 | D47: =DataA!E57 -> 2992629 | E47: =DataA!J57 -> -1.764016 | F47: =DataA!D57 -> 2263783 | G47: =DataA!B57 -> 2274050 | I47: =100*((F47/F46)-1) -> 0.8591223 | J47: =100*((G47/G46)-1) -> 0.14470901 | O47: 2043 | Q47: =Q46 -> 253 | R47: =R46 -> 315 | S47: =S46 -> 379 | V47: 2017 | W47: =100*((DataA!M51/DataA!M50)-1) -> 0.89560836 | X47: =AVERAGE(W38:W47) -> 0.78194438 | Y47: 0 | Z47: 65 | AA47: =AA46+($AA$48-$AA$40)*1/8 -> 64.375 | AC47: 43 | AD47: ='ONS pop proj 2021-based'!E45+'ONS pop proj 2021-based'!E152 -> 903123 | AE47: ='ONS pop proj 2021-based'!L45+'ONS pop proj 2021-based'!L152 -> 973435 | AF47: ='ONS pop proj 2021-based'!V45+'ONS pop proj 2021-based'!V152 -> 1019475 | AG47: ='ONS pop proj 2021-based'!AF45+'ONS pop proj 2021-based'!AF152 -> 1036643 | AN47: 44105 | AO47: =HAVERQ!F210-HAVERQ!F$166 -> -250 | AP47: =HAVERQ!G210-HAVERQ!G$166 -> 1109 | AQ47: =HAVERQ!H210-HAVERQ!H$166 -> -193 | AR47: =HAVERQ!I210-HAVERQ!I$166 -> 1879 | AS47: =HAVERQ!J210-HAVERQ!J$166 -> 511 | AT47: =SUM(AO47:AS47) -> 3056 | AV47: =HAVERQ!D210-HAVERQ!D$166-'Chart Data'!AT47 -> 40 | AX47: 35278 | AY47: =100*(HAVERM!C86/HAVERM!B86) -> 25.992655 | AZ47: =AVERAGE($AY$7:$AY$374) -> 24.595806 | BB47: =HAVERM!C86 -> 2265 | BC47: =HAVERM!B86-HAVERM!C86 -> 6449 | BF47: =100*((AVERAGE(HAVERQ!B35:B54)/AVERAGE(HAVERQ!B31:B50))-1) -> 2.3329693 | BG47: =$BL$6 -> 2.2155011 | BI47: 0 | BR47: =100*((AVERAGE(HAVERQ!C35:C54)/AVERAGE(HAVERQ!C31:C50))-1) -> 1.6385939 | BS47: =$BX$6 -> 1.9448021 | BU47: 0
A48: 2024 | B48: =DataA!F58*DataA!G58 -> 1050052 | C48: =DataA!H58/DataA!I58 -> 13.804291 | D48: =DataA!E58 -> 3033028 | E48: =DataA!J58 -> -1.764119 | F48: =DataA!D58 -> 2286365 | G48: =DataA!B58 -> 2282737 | I48: =100*((F48/F47)-1) -> 0.99753377 | J48: =100*((G48/G47)-1) -> 0.38200567 | O48: 2044 | Q48: =Q47 -> 253 | R48: =R47 -> 315 | S48: =S47 -> 379 | V48: 2018 | W48: =100*((DataA!M52/DataA!M51)-1) -> 0.92352953 | X48: =AVERAGE(W39:W48) -> 0.81373136 | Y48: 0 | Z48: 65 | AA48: 65 | AC48: 44 | AD48: ='ONS pop proj 2021-based'!E46+'ONS pop proj 2021-based'!E153 -> 865257 | AE48: ='ONS pop proj 2021-based'!L46+'ONS pop proj 2021-based'!L153 -> 959296 | AF48: ='ONS pop proj 2021-based'!V46+'ONS pop proj 2021-based'!V153 -> 1002855 | AG48: ='ONS pop proj 2021-based'!AF46+'ONS pop proj 2021-based'!AF153 -> 1023434 | AN48: 44197 | AO48: =HAVERQ!F211-HAVERQ!F$166 -> -273 | AP48: =HAVERQ!G211-HAVERQ!G$166 -> 1100 | AQ48: =HAVERQ!H211-HAVERQ!H$166 -> -140 | AR48: =HAVERQ!I211-HAVERQ!I$166 -> 1886 | AS48: =HAVERQ!J211-HAVERQ!J$166 -> 498 | AT48: =SUM(AO48:AS48) -> 3071 | AV48: =HAVERQ!D211-HAVERQ!D$166-'Chart Data'!AT48 -> 48 | AX48: 35309 | AY48: =100*(HAVERM!C87/HAVERM!B87) -> 26.176742 | AZ48: =AVERAGE($AY$7:$AY$374) -> 24.595806 | BB48: =HAVERM!C87 -> 2269 | BC48: =HAVERM!B87-HAVERM!C87 -> 6399 | BE48: 1982 | BF48: =100*((AVERAGE(HAVERQ!B36:B55)/AVERAGE(HAVERQ!B32:B51))-1) -> 2.4399881 | BG48: =$BL$6 -> 2.2155011 | BI48: 0 | BQ48: 1982 | BR48: =100*((AVERAGE(HAVERQ!C36:C55)/AVERAGE(HAVERQ!C32:C51))-1) -> 1.6783727 | BS48: =$BX$6 -> 1.9448021 | BU48: 0
A49: 2025 | B49: =DataA!F59*DataA!G59 -> 1069293.8 | C49: =DataA!H59/DataA!I59 -> 13.888946 | D49: =DataA!E59 -> 3069852 | E49: =DataA!J59 -> -1.763976 | F49: =DataA!D59 -> 2328245 | G49: =DataA!B59 -> 2324174 | I49: =100*((F49/F48)-1) -> 1.8317285 | J49: =100*((G49/G48)-1) -> 1.8152332 | O49: 2045 | Q49: =Q48 -> 253 | R49: =R48 -> 315 | S49: =S48 -> 379 | V49: 2019 | W49: =100*((DataA!M53/DataA!M52)-1) -> 1.0746008 | X49: =AVERAGE(W40:W49) -> 0.86922247 | Y49: 0 | Z49: =Z48+($Z$51-$Z$48)*1/3 -> 65.333333 | AA49: =AA48+($AA$51-$AA$48)*1/3 -> 65.333333 | AC49: 45 | AD49: ='ONS pop proj 2021-based'!E47+'ONS pop proj 2021-based'!E154 -> 804759 | AE49: ='ONS pop proj 2021-based'!L47+'ONS pop proj 2021-based'!L154 -> 949279 | AF49: ='ONS pop proj 2021-based'!V47+'ONS pop proj 2021-based'!V154 -> 1008236 | AG49: ='ONS pop proj 2021-based'!AF47+'ONS pop proj 2021-based'!AF154 -> 1026023 | AN49: 44287 | AO49: =HAVERQ!F212-HAVERQ!F$166 -> -186 | AP49: =HAVERQ!G212-HAVERQ!G$166 -> 1094 | AQ49: =HAVERQ!H212-HAVERQ!H$166 -> -108 | AR49: =HAVERQ!I212-HAVERQ!I$166 -> 1934 | AS49: =HAVERQ!J212-HAVERQ!J$166 -> 485 | AT49: =SUM(AO49:AS49) -> 3219 | AV49: =HAVERQ!D212-HAVERQ!D$166-'Chart Data'!AT49 -> 56 | AX49: 35339 | AY49: =100*(HAVERM!C88/HAVERM!B88) -> 26.235389 | AZ49: =AVERAGE($AY$7:$AY$374) -> 24.595806 | BB49: =HAVERM!C88 -> 2267 | BC49: =HAVERM!B88-HAVERM!C88 -> 6374 | BF49: =100*((AVERAGE(HAVERQ!B37:B56)/AVERAGE(HAVERQ!B33:B52))-1) -> 2.5925562 | BG49: =$BL$6 -> 2.2155011 | BI49: 0 | BR49: =100*((AVERAGE(HAVERQ!C37:C56)/AVERAGE(HAVERQ!C33:C52))-1) -> 1.7985285 | BS49: =$BX$6 -> 1.9448021 | BU49: 0
A50: 2026 | B50: =DataA!F60*DataA!G60 -> 1088761.3 | C50: =DataA!H60/DataA!I60 -> 13.972031 | D50: =DataA!E60 -> 3109861 | E50: =DataA!J60 -> -1.763193 | F50: =DataA!D60 -> 2372045 | G50: =DataA!B60 -> 2370812 | I50: =100*((F50/F49)-1) -> 1.8812453 | J50: =100*((G50/G49)-1) -> 2.0066484 | O50: 2046 | Q50: =Q49 -> 253 | R50: =R49 -> 315 | S50: =S49 -> 379 | V50: 2020 | W50: =100*((DataA!M54/DataA!M53)-1) -> 1.0825298 | X50: =AVERAGE(W41:W50) -> 0.8981517 | Y50: 0 | Z50: =Z49+($Z$51-$Z$48)*1/3 -> 65.666667 | AA50: =AA49+($AA$51-$AA$48)*1/3 -> 65.666667 | AC50: 46 | AD50: ='ONS pop proj 2021-based'!E48+'ONS pop proj 2021-based'!E155 -> 789146 | AE50: ='ONS pop proj 2021-based'!L48+'ONS pop proj 2021-based'!L155 -> 915240 | AF50: ='ONS pop proj 2021-based'!V48+'ONS pop proj 2021-based'!V155 -> 1021663 | AG50: ='ONS pop proj 2021-based'!AF48+'ONS pop proj 2021-based'!AF155 -> 1025481 | AN50: 44378 | AO50: =HAVERQ!F213-HAVERQ!F$166 -> -97 | AP50: =HAVERQ!G213-HAVERQ!G$166 -> 1107 | AQ50: =HAVERQ!H213-HAVERQ!H$166 -> -21 | AR50: =HAVERQ!I213-HAVERQ!I$166 -> 1955 | AS50: =HAVERQ!J213-HAVERQ!J$166 -> 581 | AT50: =SUM(AO50:AS50) -> 3525 | AV50: =HAVERQ!D213-HAVERQ!D$166-'Chart Data'!AT50 -> 60 | AX50: 35370 | AY50: =100*(HAVERM!C89/HAVERM!B89) -> 26.570439 | AZ50: =AVERAGE($AY$7:$AY$374) -> 24.595806 | BB50: =HAVERM!C89 -> 2301 | BC50: =HAVERM!B89-HAVERM!C89 -> 6359 | BF50: =100*((AVERAGE(HAVERQ!B38:B57)/AVERAGE(HAVERQ!B34:B53))-1) -> 2.742266 | BG50: =$BL$6 -> 2.2155011 | BI50: 0 | BR50: =100*((AVERAGE(HAVERQ!C38:C57)/AVERAGE(HAVERQ!C34:C53))-1) -> 1.917164 | BS50: =$BX$6 -> 1.9448021 | BU50: 0
A51: 2027 | B51: =DataA!F61*DataA!G61 -> 1103605.1 | C51: =DataA!H61/DataA!I61 -> 14.053089 | D51: =DataA!E61 -> 3151246 | E51: =DataA!J61 -> -1.7611 | F51: =DataA!D61 -> 2413245 | G51: =DataA!B61 -> 2411854 | I51: =100*((F51/F50)-1) -> 1.7368979 | J51: =100*((G51/G50)-1) -> 1.7311368 | O51: 2047 | Q51: =Q50 -> 253 | R51: =R50 -> 315 | S51: =S50 -> 379 | V51: 2021 | W51: =100*((DataA!M55/DataA!M54)-1) -> 0.95539866 | X51: =AVERAGE(W42:W51) -> 0.89714666 | Y51: 0 | Z51: {=TRANSPOSE('[1]2021 calcs'!$B$33:$AE$33)} -> 66 | AA51: {=TRANSPOSE('[1]2021 calcs'!$B$33:$AE$33)} -> 66 | AC51: 47 | AD51: ='ONS pop proj 2021-based'!E49+'ONS pop proj 2021-based'!E156 -> 807012 | AE51: ='ONS pop proj 2021-based'!L49+'ONS pop proj 2021-based'!L156 -> 911454 | AF51: ='ONS pop proj 2021-based'!V49+'ONS pop proj 2021-based'!V156 -> 1014160 | AG51: ='ONS pop proj 2021-based'!AF49+'ONS pop proj 2021-based'!AF156 -> 1014572 | AN51: 44470 | AO51: =HAVERQ!F214-HAVERQ!F$166 -> -14 | AP51: =HAVERQ!G214-HAVERQ!G$166 -> 1100 | AQ51: =HAVERQ!H214-HAVERQ!H$166 -> -43 | AR51: =HAVERQ!I214-HAVERQ!I$166 -> 1962 | AS51: =HAVERQ!J214-HAVERQ!J$166 -> 513 | AT51: =SUM(AO51:AS51) -> 3518 | AV51: =HAVERQ!D214-HAVERQ!D$166-'Chart Data'!AT51 -> 66 | AX51: 35400 | AY51: =100*(HAVERM!C90/HAVERM!B90) -> 26.725929 | AZ51: =AVERAGE($AY$7:$AY$374) -> 24.595806 | BB51: =HAVERM!C90 -> 2315 | BC51: =HAVERM!B90-HAVERM!C90 -> 6347 | BF51: =100*((AVERAGE(HAVERQ!B39:B58)/AVERAGE(HAVERQ!B35:B54))-1) -> 2.9200621 | BG51: =$BL$6 -> 2.2155011 | BI51: 0 | BR51: =100*((AVERAGE(HAVERQ!C39:C58)/AVERAGE(HAVERQ!C35:C54))-1) -> 2.0625056 | BS51: =$BX$6 -> 1.9448021 | BU51: 0
A52: 2028 | B52: =DataA!F62*DataA!G62 -> 1115590.1 | C52: =DataA!H62/DataA!I62 -> 14.131915 | D52: =DataA!E62 -> 3192697 | E52: =DataA!J62 -> -1.75802 | F52: =DataA!D62 -> 2453117 | G52: =DataA!B62 -> 2451771 | I52: =100*((F52/F51)-1) -> 1.6522152 | J52: =100*((G52/G51)-1) -> 1.6550338 | O52: 2048 | Q52: =Q51 -> 253 | R52: =R51 -> 315 | S52: =S51 -> 379 | V52: 2022 | W52: =100*((DataA!M56/DataA!M55)-1) -> 0.95418562 | X52: =AVERAGE(W43:W52) -> 0.93562271 | Y52: 0 | Z52: 66 | AA52: 66 | AC52: 48 | AD52: ='ONS pop proj 2021-based'!E50+'ONS pop proj 2021-based'!E157 -> 822021 | AE52: ='ONS pop proj 2021-based'!L50+'ONS pop proj 2021-based'!L157 -> 903918 | AF52: ='ONS pop proj 2021-based'!V50+'ONS pop proj 2021-based'!V157 -> 1031347 | AG52: ='ONS pop proj 2021-based'!AF50+'ONS pop proj 2021-based'!AF157 -> 1007407 | AN52: 44562 | AO52: =HAVERQ!F215-HAVERQ!F$166 -> -4 | AP52: =HAVERQ!G215-HAVERQ!G$166 -> 1134 | AQ52: =HAVERQ!H215-HAVERQ!H$166 -> -31 | AR52: =HAVERQ!I215-HAVERQ!I$166 -> 2002 | AS52: =HAVERQ!J215-HAVERQ!J$166 -> 501 | AT52: =SUM(AO52:AS52) -> 3602 | AV52: =HAVERQ!D215-HAVERQ!D$166-'Chart Data'!AT52 -> 71 | AX52: 35431 | AY52: =100*(HAVERM!C91/HAVERM!B91) -> 26.81603 | AZ52: =AVERAGE($AY$7:$AY$374) -> 24.595806 | BB52: =HAVERM!C91 -> 2322 | BC52: =HAVERM!B91-HAVERM!C91 -> 6337 | BE52: 1983 | BF52: =100*((AVERAGE(HAVERQ!B40:B59)/AVERAGE(HAVERQ!B36:B55))-1) -> 3.2015429 | BG52: =$BL$6 -> 2.2155011 | BI52: 0 | BQ52: 1983 | BR52: =100*((AVERAGE(HAVERQ!C40:C59)/AVERAGE(HAVERQ!C36:C55))-1) -> 2.3234951 | BS52: =$BX$6 -> 1.9448021 | BU52: 0
A53: 2029 | B53: =DataA!F63*DataA!G63 -> 1126078.4 | C53: =DataA!H63/DataA!I63 -> 14.208334 | D53: =DataA!E63 -> 3234931 | E53: =DataA!J63 -> -1.754507 | F53: =DataA!D63 -> 2492142 | G53: =DataA!B63 -> 2490241 | I53: =100*((F53/F52)-1) -> 1.5908332 | J53: =100*((G53/G52)-1) -> 1.5690699 | O53: 2049 | Q53: =Q52 -> 253 | R53: =R52 -> 315 | S53: =S52 -> 379 | V53: 2023 | W53: =100*((DataA!M57/DataA!M56)-1) -> 1.3889482 | X53: =AVERAGE(W44:W53) -> 1.0069493 | Y53: 0 | Z53: 66 | AA53: 66 | AC53: 49 | AD53: ='ONS pop proj 2021-based'!E51+'ONS pop proj 2021-based'!E158 -> 832476 | AE53: ='ONS pop proj 2021-based'!L51+'ONS pop proj 2021-based'!L158 -> 907950 | AF53: ='ONS pop proj 2021-based'!V51+'ONS pop proj 2021-based'!V158 -> 1030976 | AG53: ='ONS pop proj 2021-based'!AF51+'ONS pop proj 2021-based'!AF158 -> 1000549 | AN53: 44652 | AO53: =HAVERQ!F216-HAVERQ!F$166 -> -3 | AP53: =HAVERQ!G216-HAVERQ!G$166 -> 1114 | AQ53: =HAVERQ!H216-HAVERQ!H$166 -> 17 | AR53: =HAVERQ!I216-HAVERQ!I$166 -> 1975 | AS53: =HAVERQ!J216-HAVERQ!J$166 -> 678 | AT53: =SUM(AO53:AS53) -> 3781 | AV53: =HAVERQ!D216-HAVERQ!D$166-'Chart Data'!AT53 -> 75 | AX53: 35462 | AY53: =100*(HAVERM!C92/HAVERM!B92) -> 26.766744 | AZ53: =AVERAGE($AY$7:$AY$374) -> 24.595806 | BB53: =HAVERM!C92 -> 2318 | BC53: =HAVERM!B92-HAVERM!C92 -> 6342 | BF53: =100*((AVERAGE(HAVERQ!B41:B60)/AVERAGE(HAVERQ!B37:B56))-1) -> 3.3119556 | BG53: =$BL$6 -> 2.2155011 | BI53: 0 | BR53: =100*((AVERAGE(HAVERQ!C41:C60)/AVERAGE(HAVERQ!C37:C56))-1) -> 2.4181315 | BS53: =$BX$6 -> 1.9448021 | BU53: 0
A54: 2030 | B54: =DataA!F64*DataA!G64 -> 1134874.6 | C54: =DataA!H64/DataA!I64 -> 14.282156 | D54: =DataA!E64 -> 3279805 | E54: =DataA!J64 -> -1.750716 | F54: =DataA!D64 -> 2529998 | G54: =DataA!B64 -> 2528309 | I54: =100*((F54/F53)-1) -> 1.5190146 | J54: =100*((G54/G53)-1) -> 1.5286874 | O54: 2050 | Q54: =Q53 -> 253 | R54: =R53 -> 315 | S54: =S53 -> 379 | V54: 2024 | W54: =100*((DataA!M58/DataA!M57)-1) -> 1.0562067 | X54: =AVERAGE(W45:W54) -> 1.0291282 | Y54: 0 | Z54: 66 | AA54: 66 | AC54: 50 | AD54: ='ONS pop proj 2021-based'!E52+'ONS pop proj 2021-based'!E159 -> 865808 | AE54: ='ONS pop proj 2021-based'!L52+'ONS pop proj 2021-based'!L159 -> 906850 | AF54: ='ONS pop proj 2021-based'!V52+'ONS pop proj 2021-based'!V159 -> 1015307 | AG54: ='ONS pop proj 2021-based'!AF52+'ONS pop proj 2021-based'!AF159 -> 1000627 | AN54: 44743 | AO54: =HAVERQ!F217-HAVERQ!F$166 -> 61 | AP54: =HAVERQ!G217-HAVERQ!G$166 -> 1163 | AQ54: =HAVERQ!H217-HAVERQ!H$166 -> 16 | AR54: =HAVERQ!I217-HAVERQ!I$166 -> 2006 | AS54: =HAVERQ!J217-HAVERQ!J$166 -> 568 | AT54: =SUM(AO54:AS54) -> 3814 | AV54: =HAVERQ!D217-HAVERQ!D$166-'Chart Data'!AT54 -> 0 | AX54: 35490 | AY54: =100*(HAVERM!C93/HAVERM!B93) -> 26.701329 | AZ54: =AVERAGE($AY$7:$AY$374) -> 24.595806 | BB54: =HAVERM!C93 -> 2311 | BC54: =HAVERM!B93-HAVERM!C93 -> 6344 | BF54: =100*((AVERAGE(HAVERQ!B42:B61)/AVERAGE(HAVERQ!B38:B57))-1) -> 3.3529635 | BG54: =$BL$6 -> 2.2155011 | BI54: 0 | BR54: =100*((AVERAGE(HAVERQ!C42:C61)/AVERAGE(HAVERQ!C38:C57))-1) -> 2.4489796 | BS54: =$BX$6 -> 1.9448021 | BU54: 0
A55: 2031 | B55: =DataA!F65*DataA!G65 -> 1143209 | C55: =DataA!H65/DataA!I65 -> 14.352806 | D55: =DataA!E65 -> 3327676 | E55: =DataA!J65 -> -1.746868 | F55: =DataA!D65 -> 2568239 | G55: =DataA!B65 -> 2566959 | I55: =100*((F55/F54)-1) -> 1.5115032 | J55: =100*((G55/G54)-1) -> 1.5286897 | V55: 2025 | W55: =100*((DataA!M59/DataA!M58)-1) -> 0.88249438 | X55: =AVERAGE(W46:W55) -> 1.0201463 | Y55: 0 | Z55: 66 | AA55: 66 | AC55: 51 | AD55: ='ONS pop proj 2021-based'!E53+'ONS pop proj 2021-based'!E160 -> 899257 | AE55: ='ONS pop proj 2021-based'!L53+'ONS pop proj 2021-based'!L160 -> 867026 | AF55: ='ONS pop proj 2021-based'!V53+'ONS pop proj 2021-based'!V160 -> 998085 | AG55: ='ONS pop proj 2021-based'!AF53+'ONS pop proj 2021-based'!AF160 -> 1014474 | AN55: 44835 | AO55: =HAVERQ!F218-HAVERQ!F$166 -> 61 | AP55: =HAVERQ!G218-HAVERQ!G$166 -> 1230 | AQ55: =HAVERQ!H218-HAVERQ!H$166 -> 34 | AR55: =HAVERQ!I218-HAVERQ!I$166 -> 2046 | AS55: =HAVERQ!J218-HAVERQ!J$166 -> 596 | AT55: =SUM(AO55:AS55) -> 3967 | AV55: =HAVERQ!D218-HAVERQ!D$166-'Chart Data'!AT55 -> -2 | AX55: 35521 | AY55: =100*(HAVERM!C94/HAVERM!B94) -> 26.704414 | AZ55: =AVERAGE($AY$7:$AY$374) -> 24.595806 | BB55: =HAVERM!C94 -> 2311 | BC55: =HAVERM!B94-HAVERM!C94 -> 6343 | BF55: =100*((AVERAGE(HAVERQ!B43:B62)/AVERAGE(HAVERQ!B39:B58))-1) -> 3.3744934 | BG55: =$BL$6 -> 2.2155011 | BI55: 0 | BR55: =100*((AVERAGE(HAVERQ!C43:C62)/AVERAGE(HAVERQ!C39:C58))-1) -> 2.4620544 | BS55: =$BX$6 -> 1.9448021 | BU55: 0
A56: 2032 | B56: =DataA!F66*DataA!G66 -> 1150943 | C56: =DataA!H66/DataA!I66 -> 14.419019 | D56: =DataA!E66 -> 3378419 | E56: =DataA!J66 -> -1.742989 | F56: =DataA!D66 -> 2606529 | G56: =DataA!B66 -> 2605939 | I56: =100*((F56/F55)-1) -> 1.4909049 | J56: =100*((G56/G55)-1) -> 1.5185283 | V56: 2026 | W56: =100*((DataA!M60/DataA!M59)-1) -> 1.0149921 | X56: =AVERAGE(W47:W56) -> 1.0228494 | Y56: 0 | Z56: 66.153005 | AA56: 66.153005 | AC56: 52 | AD56: ='ONS pop proj 2021-based'!E54+'ONS pop proj 2021-based'!E161 -> 931846 | AE56: ='ONS pop proj 2021-based'!L54+'ONS pop proj 2021-based'!L161 -> 805145 | AF56: ='ONS pop proj 2021-based'!V54+'ONS pop proj 2021-based'!V161 -> 997603 | AG56: ='ONS pop proj 2021-based'!AF54+'ONS pop proj 2021-based'!AF161 -> 1007672 | AN56: 44927 | AO56: =HAVERQ!F219-HAVERQ!F$166 -> 137 | AP56: =HAVERQ!G219-HAVERQ!G$166 -> 1263 | AQ56: =HAVERQ!H219-HAVERQ!H$166 -> 55 | AR56: =HAVERQ!I219-HAVERQ!I$166 -> 1987 | AS56: =HAVERQ!J219-HAVERQ!J$166 -> 658 | AT56: =SUM(AO56:AS56) -> 4100 | AV56: =HAVERQ!D219-HAVERQ!D$166-'Chart Data'!AT56 -> -1 | AX56: 35551 | AY56: =100*(HAVERM!C95/HAVERM!B95) -> 26.505464 | AZ56: =AVERAGE($AY$7:$AY$374) -> 24.595806 | BB56: =HAVERM!C95 -> 2280 | BC56: =HAVERM!B95-HAVERM!C95 -> 6322 | BE56: 1984 | BF56: =100*((AVERAGE(HAVERQ!B44:B63)/AVERAGE(HAVERQ!B40:B59))-1) -> 3.3358251 | BG56: =$BL$6 -> 2.2155011 | BI56: 0 | BQ56: 1984 | BR56: =100*((AVERAGE(HAVERQ!C44:C63)/AVERAGE(HAVERQ!C40:C59))-1) -> 2.4285464 | BS56: =$BX$6 -> 1.9448021 | BU56: 0
A57: 2033 | B57: =DataA!F67*DataA!G67 -> 1157282.9 | C57: =DataA!H67/DataA!I67 -> 14.480461 | D57: =DataA!E67 -> 3432026 | E57: =DataA!J67 -> -1.738871 | F57: =DataA!D67 -> 2644184 | G57: =DataA!B67 -> 2643901 | I57: =100*((F57/F56)-1) -> 1.4446415 | J57: =100*((G57/G56)-1) -> 1.4567494 | V57: 2027 | W57: =100*((DataA!M61/DataA!M60)-1) -> 1.2676459 | X57: =AVERAGE(W48:W57) -> 1.0600532 | Y57: 0 | Z57: 66.649315 | AA57: 66.649315 | AC57: 53 | AD57: ='ONS pop proj 2021-based'!E55+'ONS pop proj 2021-based'!E162 -> 908492 | AE57: ='ONS pop proj 2021-based'!L55+'ONS pop proj 2021-based'!L162 -> 787520 | AF57: ='ONS pop proj 2021-based'!V55+'ONS pop proj 2021-based'!V162 -> 966444 | AG57: ='ONS pop proj 2021-based'!AF55+'ONS pop proj 2021-based'!AF162 -> 1013481 | AN57: 45017 | AO57: =HAVERQ!F220-HAVERQ!F$166 -> 87 | AP57: =HAVERQ!G220-HAVERQ!G$166 -> 1184 | AQ57: =HAVERQ!H220-HAVERQ!H$166 -> 83 | AR57: =HAVERQ!I220-HAVERQ!I$166 -> 2073 | AS57: =HAVERQ!J220-HAVERQ!J$166 -> 634 | AT57: =SUM(AO57:AS57) -> 4061 | AV57: =HAVERQ!D220-HAVERQ!D$166-'Chart Data'!AT57 -> 0 | AX57: 35582 | AY57: =100*(HAVERM!C96/HAVERM!B96) -> 26.59698 | AZ57: =AVERAGE($AY$7:$AY$374) -> 24.595806 | BB57: =HAVERM!C96 -> 2290 | BC57: =HAVERM!B96-HAVERM!C96 -> 6320 | BF57: =100*((AVERAGE(HAVERQ!B45:B64)/AVERAGE(HAVERQ!B41:B60))-1) -> 3.0297415 | BG57: =$BL$6 -> 2.2155011 | BI57: 0 | BR57: =100*((AVERAGE(HAVERQ!C45:C64)/AVERAGE(HAVERQ!C41:C60))-1) -> 2.1345182 | BS57: =$BX$6 -> 1.9448021 | BU57: 0
A58: 2034 | B58: =DataA!F68*DataA!G68 -> 1162638.9 | C58: =DataA!H68/DataA!I68 -> 14.536953 | D58: =DataA!E68 -> 3488402 | E58: =DataA!J68 -> -1.734484 | F58: =DataA!D68 -> 2681838 | G58: =DataA!B68 -> 2681782 | I58: =100*((F58/F57)-1) -> 1.424031 | J58: =100*((G58/G57)-1) -> 1.4327692 | V58: 2028 | W58: =100*((DataA!M62/DataA!M61)-1) -> 0.82652998 | X58: =AVERAGE(W49:W58) -> 1.0503532 | Y58: 0 | Z58: 67 | AA58: 67 | AC58: 54 | AD58: ='ONS pop proj 2021-based'!E56+'ONS pop proj 2021-based'!E163 -> 929212 | AE58: ='ONS pop proj 2021-based'!L56+'ONS pop proj 2021-based'!L163 -> 802693 | AF58: ='ONS pop proj 2021-based'!V56+'ONS pop proj 2021-based'!V163 -> 949617 | AG58: ='ONS pop proj 2021-based'!AF56+'ONS pop proj 2021-based'!AF163 -> 994339 | AN58: 45108 | AO58: =HAVERQ!F221-HAVERQ!F$166 -> -70 | AP58: =HAVERQ!G221-HAVERQ!G$166 -> 1274 | AQ58: =HAVERQ!H221-HAVERQ!H$166 -> -3 | AR58: =HAVERQ!I221-HAVERQ!I$166 -> 2122 | AS58: =HAVERQ!J221-HAVERQ!J$166 -> 678 | AT58: =SUM(AO58:AS58) -> 4001 | AV58: =HAVERQ!D221-HAVERQ!D$166-'Chart Data'!AT58 -> -1 | AX58: 35612 | AY58: =100*(HAVERM!C97/HAVERM!B97) -> 26.724337 | AZ58: =AVERAGE($AY$7:$AY$374) -> 24.595806 | BB58: =HAVERM!C97 -> 2317 | BC58: =HAVERM!B97-HAVERM!C97 -> 6353 | BF58: =100*((AVERAGE(HAVERQ!B46:B65)/AVERAGE(HAVERQ!B42:B61))-1) -> 2.8398125 | BG58: =$BL$6 -> 2.2155011 | BI58: 0 | BR58: =100*((AVERAGE(HAVERQ!C46:C65)/AVERAGE(HAVERQ!C42:C61))-1) -> 1.9833709 | BS58: =$BX$6 -> 1.9448021 | BU58: 0
A59: 2035 | B59: =DataA!F69*DataA!G69 -> 1167395.3 | C59: =DataA!H69/DataA!I69 -> 14.588458 | D59: =DataA!E69 -> 3547459 | E59: =DataA!J69 -> -1.729763 | F59: =DataA!D69 -> 2720205 | G59: =DataA!B69 -> 2720207 | I59: =100*((F59/F58)-1) -> 1.4306233 | J59: =100*((G59/G58)-1) -> 1.4328159 | V59: 2029 | W59: =100*((DataA!M63/DataA!M62)-1) -> 0.2433849 | X59: =AVERAGE(W50:W59) -> 0.96723162 | Y59: 0 | Z59: 67 | AA59: 67 | AC59: 55 | AD59: ='ONS pop proj 2021-based'!E57+'ONS pop proj 2021-based'!E164 -> 926887 | AE59: ='ONS pop proj 2021-based'!L57+'ONS pop proj 2021-based'!L164 -> 814992 | AF59: ='ONS pop proj 2021-based'!V57+'ONS pop proj 2021-based'!V164 -> 936952 | AG59: ='ONS pop proj 2021-based'!AF57+'ONS pop proj 2021-based'!AF164 -> 996863 | AN59: 45200 | AO59: =HAVERQ!F222-HAVERQ!F$166 -> -33 | AP59: =HAVERQ!G222-HAVERQ!G$166 -> 1139 | AQ59: =HAVERQ!H222-HAVERQ!H$166 -> 106 | AR59: =HAVERQ!I222-HAVERQ!I$166 -> 2213 | AS59: =HAVERQ!J222-HAVERQ!J$166 -> 648 | AT59: =SUM(AO59:AS59) -> 4073 | AV59: =HAVERQ!D222-HAVERQ!D$166-'Chart Data'!AT59 -> -1 | AX59: 35643 | AY59: =100*(HAVERM!C98/HAVERM!B98) -> 26.786331 | AZ59: =AVERAGE($AY$7:$AY$374) -> 24.595806 | BB59: =HAVERM!C98 -> 2328 | BC59: =HAVERM!B98-HAVERM!C98 -> 6363 | BF59: =100*((AVERAGE(HAVERQ!B47:B66)/AVERAGE(HAVERQ!B43:B62))-1) -> 2.6990061 | BG59: =$BL$6 -> 2.2155011 | BI59: 0 | BR59: =100*((AVERAGE(HAVERQ!C47:C66)/AVERAGE(HAVERQ!C43:C62))-1) -> 1.91198 | BS59: =$BX$6 -> 1.9448021 | BU59: 0
A60: 2036 | B60: =DataA!F70*DataA!G70 -> 1172190 | C60: =DataA!H70/DataA!I70 -> 14.635706 | D60: =DataA!E70 -> 3609279 | E60: =DataA!J70 -> -1.724708 | F60: =DataA!D70 -> 2760292 | G60: =DataA!B70 -> 2760292 | I60: =100*((F60/F59)-1) -> 1.4736757 | J60: =100*((G60/G59)-1) -> 1.4736011 | V60: 2030 | W60: =100*((DataA!M64/DataA!M63)-1) -> 0.13633002 | X60: =AVERAGE(W51:W60) -> 0.87261165 | Y60: 0 | Z60: 67 | AA60: 67 | AC60: 56 | AD60: ='ONS pop proj 2021-based'!E58+'ONS pop proj 2021-based'!E165 -> 931407 | AE60: ='ONS pop proj 2021-based'!L58+'ONS pop proj 2021-based'!L165 -> 822810 | AF60: ='ONS pop proj 2021-based'!V58+'ONS pop proj 2021-based'!V165 -> 900907 | AG60: ='ONS pop proj 2021-based'!AF58+'ONS pop proj 2021-based'!AF165 -> 1007209 | AX60: 35674 | AY60: =100*(HAVERM!C99/HAVERM!B99) -> 26.678912 | AZ60: =AVERAGE($AY$7:$AY$374) -> 24.595806 | BB60: =HAVERM!C99 -> 2324 | BC60: =HAVERM!B99-HAVERM!C99 -> 6387 | BE60: 1985 | BF60: =100*((AVERAGE(HAVERQ!B48:B67)/AVERAGE(HAVERQ!B44:B63))-1) -> 2.5951714 | BG60: =$BL$6 -> 2.2155011 | BI60: 0 | BQ60: 1985 | BR60: =100*((AVERAGE(HAVERQ!C48:C67)/AVERAGE(HAVERQ!C44:C63))-1) -> 1.883078 | BS60: =$BX$6 -> 1.9448021 | BU60: 0
A61: 2037 | B61: =DataA!F71*DataA!G71 -> 1176984 | C61: =DataA!H71/DataA!I71 -> 14.680409 | D61: =DataA!E71 -> 3673876 | E61: =DataA!J71 -> -1.71954 | F61: =DataA!D71 -> 2801571 | G61: =DataA!B71 -> 2801574 | I61: =100*((F61/F60)-1) -> 1.4954577 | J61: =100*((G61/G60)-1) -> 1.4955664 | V61: 2031 | W61: =100*((DataA!M65/DataA!M64)-1) -> 0.1021784 | X61: =AVERAGE(W52:W61) -> 0.78728962 | Y61: 0 | Z61: 67 | AA61: 67 | AC61: 57 | AD61: ='ONS pop proj 2021-based'!E59+'ONS pop proj 2021-based'!E166 -> 926238 | AE61: ='ONS pop proj 2021-based'!L59+'ONS pop proj 2021-based'!L166 -> 852852 | AF61: ='ONS pop proj 2021-based'!V59+'ONS pop proj 2021-based'!V166 -> 894290 | AG61: ='ONS pop proj 2021-based'!AF59+'ONS pop proj 2021-based'!AF166 -> 996990 | AS61: =+AR59+AS59 -> 2861 | AT61: =AS61/AT59 -> 0.70243064 | AX61: 35704 | AY61: =100*(HAVERM!C100/HAVERM!B100) -> 26.736191 | AZ61: =AVERAGE($AY$7:$AY$374) -> 24.595806 | BB61: =HAVERM!C100 -> 2333 | BC61: =HAVERM!B100-HAVERM!C100 -> 6393 | BF61: =100*((AVERAGE(HAVERQ!B49:B68)/AVERAGE(HAVERQ!B45:B64))-1) -> 2.9136691 | BG61: =$BL$6 -> 2.2155011 | BI61: 0 | BR61: =100*((AVERAGE(HAVERQ!C49:C68)/AVERAGE(HAVERQ!C45:C64))-1) -> 2.2946345 | BS61: =$BX$6 -> 1.9448021 | BU61: 0
A62: 2038 | B62: =DataA!F72*DataA!G72 -> 1181777.3 | C62: =DataA!H72/DataA!I72 -> 14.723075 | D62: =DataA!E72 -> 3741310 | E62: =DataA!J72 -> -1.714174 | F62: =DataA!D72 -> 2844332 | G62: =DataA!B72 -> 2844334 | I62: =100*((F62/F61)-1) -> 1.5263222 | J62: =100*((G62/G61)-1) -> 1.5262849 | V62: 2032 | W62: =100*((DataA!M66/DataA!M65)-1) -> 0.094253732 | X62: =AVERAGE(W53:W62) -> 0.70129643 | Y62: 0 | Z62: 67 | AA62: 67 | AC62: 58 | AD62: ='ONS pop proj 2021-based'!E60+'ONS pop proj 2021-based'!E167 -> 930308 | AE62: ='ONS pop proj 2021-based'!L60+'ONS pop proj 2021-based'!L167 -> 882880 | AF62: ='ONS pop proj 2021-based'!V60+'ONS pop proj 2021-based'!V167 -> 883968 | AG62: ='ONS pop proj 2021-based'!AF60+'ONS pop proj 2021-based'!AF167 -> 1010776 | AX62: 35735 | AY62: =100*(HAVERM!C101/HAVERM!B101) -> 26.839034 | AZ62: =AVERAGE($AY$7:$AY$374) -> 24.595806 | BB62: =HAVERM!C101 -> 2346 | BC62: =HAVERM!B101-HAVERM!C101 -> 6395 | BF62: =100*((AVERAGE(HAVERQ!B50:B69)/AVERAGE(HAVERQ!B46:B65))-1) -> 3.0831099 | BG62: =$BL$6 -> 2.2155011 | BI62: 0 | BR62: =100*((AVERAGE(HAVERQ!C50:C69)/AVERAGE(HAVERQ!C46:C65))-1) -> 2.5647558 | BS62: =$BX$6 -> 1.9448021 | BU62: 0
A63: 2039 | B63: =DataA!F73*DataA!G73 -> 1186570 | C63: =DataA!H73/DataA!I73 -> 14.764299 | D63: =DataA!E73 -> 3811608 | E63: =DataA!J73 -> -1.708694 | F63: =DataA!D73 -> 2888392 | G63: =DataA!B73 -> 2888393 | I63: =100*((F63/F62)-1) -> 1.5490456 | J63: =100*((G63/G62)-1) -> 1.5490094 | V63: 2033 | W63: =100*((DataA!M67/DataA!M66)-1) -> 0.068444487 | X63: =AVERAGE(W54:W63) -> 0.56924606 | Y63: 0 | Z63: 67 | AA63: 67 | AC63: 59 | AD63: ='ONS pop proj 2021-based'!E61+'ONS pop proj 2021-based'!E168 -> 916262 | AE63: ='ONS pop proj 2021-based'!L61+'ONS pop proj 2021-based'!L168 -> 911963 | AF63: ='ONS pop proj 2021-based'!V61+'ONS pop proj 2021-based'!V168 -> 884810 | AG63: ='ONS pop proj 2021-based'!AF61+'ONS pop proj 2021-based'!AF168 -> 1007333 | AX63: 35765 | AY63: =100*(HAVERM!C102/HAVERM!B102) -> 26.506024 | AZ63: =AVERAGE($AY$7:$AY$374) -> 24.595806 | BB63: =HAVERM!C102 -> 2332 | BC63: =HAVERM!B102-HAVERM!C102 -> 6466 | BF63: =100*((AVERAGE(HAVERQ!B51:B70)/AVERAGE(HAVERQ!B47:B66))-1) -> 3.2140637 | BG63: =$BL$6 -> 2.2155011 | BI63: 0 | BR63: =100*((AVERAGE(HAVERQ!C51:C70)/AVERAGE(HAVERQ!C47:C66))-1) -> 2.7972619 | BS63: =$BX$6 -> 1.9448021 | BU63: 0
A64: 2040 | B64: =DataA!F74*DataA!G74 -> 1191362.2 | C64: =DataA!H74/DataA!I74 -> 14.80454 | D64: =DataA!E74 -> 3883890 | E64: =DataA!J74 -> -1.703233 | F64: =DataA!D74 -> 2933352 | G64: =DataA!B74 -> 2933353 | I64: =100*((F64/F63)-1) -> 1.5565754 | J64: =100*((G64/G63)-1) -> 1.5565749 | V64: 2034 | W64: =100*((DataA!M68/DataA!M67)-1) -> 0.040522395 | X64: =AVERAGE(W55:W64) -> 0.46767763 | Y64: 0 | Z64: 67 | AA64: 67 | AC64: 60 | AD64: ='ONS pop proj 2021-based'!E62+'ONS pop proj 2021-based'!E169 -> 894112 | AE64: ='ONS pop proj 2021-based'!L62+'ONS pop proj 2021-based'!L169 -> 886473 | AF64: ='ONS pop proj 2021-based'!V62+'ONS pop proj 2021-based'!V169 -> 880471 | AG64: ='ONS pop proj 2021-based'!AF62+'ONS pop proj 2021-based'!AF169 -> 988914 | AX64: 35796 | AY64: =100*(HAVERM!C103/HAVERM!B103) -> 26.853434 | AZ64: =AVERAGE($AY$7:$AY$374) -> 24.595806 | BB64: =HAVERM!C103 -> 2358 | BC64: =HAVERM!B103-HAVERM!C103 -> 6423 | BE64: 1986 | BF64: =100*((AVERAGE(HAVERQ!B52:B71)/AVERAGE(HAVERQ!B48:B67))-1) -> 3.2258065 | BG64: =$BL$6 -> 2.2155011 | BI64: 0 | BQ64: 1986 | BR64: =100*((AVERAGE(HAVERQ!C52:C71)/AVERAGE(HAVERQ!C48:C67))-1) -> 2.9236327 | BS64: =$BX$6 -> 1.9448021 | BU64: 0
A65: 2041 | B65: =DataA!F75*DataA!G75 -> 1195838.9 | C65: =DataA!H75/DataA!I75 -> 14.843972 | D65: =DataA!E75 -> 3957557 | E65: =DataA!J75 -> -1.697789 | F65: =DataA!D75 -> 2978445 | G65: =DataA!B75 -> 2978448 | I65: =100*((F65/F64)-1) -> 1.5372516 | J65: =100*((G65/G64)-1) -> 1.5373192 | V65: 2035 | W65: =100*((DataA!M69/DataA!M68)-1) -> 0.033023984 | X65: =AVERAGE(W56:W65) -> 0.38273059 | Y65: 0 | Z65: 67 | AA65: 67 | AC65: 61 | AD65: ='ONS pop proj 2021-based'!E63+'ONS pop proj 2021-based'!E170 -> 871127 | AE65: ='ONS pop proj 2021-based'!L63+'ONS pop proj 2021-based'!L170 -> 903684 | AF65: ='ONS pop proj 2021-based'!V63+'ONS pop proj 2021-based'!V170 -> 838748 | AG65: ='ONS pop proj 2021-based'!AF63+'ONS pop proj 2021-based'!AF170 -> 968941 | AX65: 35827 | AY65: =100*(HAVERM!C104/HAVERM!B104) -> 27.028259 | AZ65: =AVERAGE($AY$7:$AY$374) -> 24.595806 | BB65: =HAVERM!C104 -> 2372 | BC65: =HAVERM!B104-HAVERM!C104 -> 6404 | BF65: =100*((AVERAGE(HAVERQ!B53:B72)/AVERAGE(HAVERQ!B49:B68))-1) -> 3.0758476 | BG65: =$BL$6 -> 2.2155011 | BI65: 0 | BR65: =100*((AVERAGE(HAVERQ!C53:C72)/AVERAGE(HAVERQ!C49:C68))-1) -> 2.8769179 | BS65: =$BX$6 -> 1.9448021 | BU65: 0
A66: 2042 | B66: =DataA!F76*DataA!G76 -> 1200126.7 | C66: =DataA!H76/DataA!I76 -> 14.882652 | D66: =DataA!E76 -> 4032567 | E66: =DataA!J76 -> -1.692363 | F66: =DataA!D76 -> 3023788 | G66: =DataA!B76 -> 3023788 | I66: =100*((F66/F65)-1) -> 1.5223716 | J66: =100*((G66/G65)-1) -> 1.5222693 | V66: 2036 | W66: =100*((DataA!M70/DataA!M69)-1) -> 0.017280285 | X66: =AVERAGE(W57:W66) -> 0.28295941 | Y66: 0 | Z66: 67 | AA66: 67 | AC66: 62 | AD66: ='ONS pop proj 2021-based'!E64+'ONS pop proj 2021-based'!E171 -> 838309 | AE66: ='ONS pop proj 2021-based'!L64+'ONS pop proj 2021-based'!L171 -> 898388 | AF66: ='ONS pop proj 2021-based'!V64+'ONS pop proj 2021-based'!V171 -> 776017 | AG66: ='ONS pop proj 2021-based'!AF64+'ONS pop proj 2021-based'!AF171 -> 965055 | AX66: 35855 | AY66: =100*(HAVERM!C105/HAVERM!B105) -> 27.16921 | AZ66: =AVERAGE($AY$7:$AY$374) -> 24.595806 | BB66: =HAVERM!C105 -> 2386 | BC66: =HAVERM!B105-HAVERM!C105 -> 6396 | BF66: =100*((AVERAGE(HAVERQ!B54:B73)/AVERAGE(HAVERQ!B50:B69))-1) -> 2.9388817 | BG66: =$BL$6 -> 2.2155011 | BI66: 0 | BR66: =100*((AVERAGE(HAVERQ!C54:C73)/AVERAGE(HAVERQ!C50:C69))-1) -> 2.8235489 | BS66: =$BX$6 -> 1.9448021 | BU66: 0
A67: 2043 | B67: =DataA!F77*DataA!G77 -> 1204413.4 | C67: =DataA!H77/DataA!I77 -> 14.920513 | D67: =DataA!E77 -> 4108883 | E67: =DataA!J77 -> -1.686954 | F67: =DataA!D77 -> 3069663 | G67: =DataA!B77 -> 3069664 | I67: =100*((F67/F66)-1) -> 1.5171368 | J67: =100*((G67/G66)-1) -> 1.5171699 | V67: 2037 | W67: =100*((DataA!M71/DataA!M70)-1) -> 0.01126033 | X67: =AVERAGE(W58:W67) -> 0.15732085 | Y67: 0 | Z67: 67 | AA67: 67 | AC67: 63 | AD67: ='ONS pop proj 2021-based'!E65+'ONS pop proj 2021-based'!E172 -> 802214 | AE67: ='ONS pop proj 2021-based'!L65+'ONS pop proj 2021-based'!L172 -> 899341 | AF67: ='ONS pop proj 2021-based'!V65+'ONS pop proj 2021-based'!V172 -> 755747 | AG67: ='ONS pop proj 2021-based'!AF65+'ONS pop proj 2021-based'!AF172 -> 931445 | AX67: 35886 | AY67: =100*(HAVERM!C106/HAVERM!B106) -> 26.942299 | AZ67: =AVERAGE($AY$7:$AY$374) -> 24.595806 | BB67: =HAVERM!C106 -> 2372 | BC67: =HAVERM!B106-HAVERM!C106 -> 6432 | BF67: =100*((AVERAGE(HAVERQ!B55:B74)/AVERAGE(HAVERQ!B51:B70))-1) -> 2.8387097 | BG67: =$BL$6 -> 2.2155011 | BI67: 0 | BR67: =100*((AVERAGE(HAVERQ!C55:C74)/AVERAGE(HAVERQ!C51:C70))-1) -> 2.7786912 | BS67: =$BX$6 -> 1.9448021 | BU67: 0
A68: 2044 | B68: =DataA!F78*DataA!G78 -> 1208699.5 | C68: =DataA!H78/DataA!I78 -> 14.957306 | D68: =DataA!E78 -> 4186484 | E68: =DataA!J78 -> -1.681562 | F68: =DataA!D78 -> 3116042 | G68: =DataA!B78 -> 3116044 | I68: =100*((F68/F67)-1) -> 1.5108825 | J68: =100*((G68/G67)-1) -> 1.5109145 | V68: 2038 | W68: =100*((DataA!M72/DataA!M71)-1) -> 0.0034163947 | X68: =AVERAGE(W59:W68) -> 0.075009492 | Y68: 0 | Z68: 67 | AA68: 67 | AC68: 64 | AD68: ='ONS pop proj 2021-based'!E66+'ONS pop proj 2021-based'!E173 -> 780003 | AE68: ='ONS pop proj 2021-based'!L66+'ONS pop proj 2021-based'!L173 -> 890783 | AF68: ='ONS pop proj 2021-based'!V66+'ONS pop proj 2021-based'!V173 -> 766638 | AG68: ='ONS pop proj 2021-based'!AF66+'ONS pop proj 2021-based'!AF173 -> 911499 | AX68: 35916 | AY68: =100*(HAVERM!C107/HAVERM!B107) -> 26.867196 | AZ68: =AVERAGE($AY$7:$AY$374) -> 24.595806 | BB68: =HAVERM!C107 -> 2367 | BC68: =HAVERM!B107-HAVERM!C107 -> 6443 | BE68: 1987 | BF68: =100*((AVERAGE(HAVERQ!B56:B75)/AVERAGE(HAVERQ!B52:B71))-1) -> 2.7578552 | BG68: =$BL$6 -> 2.2155011 | BI68: 0 | BQ68: 1987 | BR68: =100*((AVERAGE(HAVERQ!C56:C75)/AVERAGE(HAVERQ!C52:C71))-1) -> 2.7263081 | BS68: =$BX$6 -> 1.9448021 | BU68: 0
A69: 2045 | B69: =DataA!F79*DataA!G79 -> 1212984.4 | C69: =DataA!H79/DataA!I79 -> 14.9929 | D69: =DataA!E79 -> 4265376 | E69: =DataA!J79 -> -1.676188 | F69: =DataA!D79 -> 3162919 | G69: =DataA!B79 -> 3162919 | I69: =100*((F69/F68)-1) -> 1.5043764 | J69: =100*((G69/G68)-1) -> 1.5043112 | V69: 2039 | W69: =100*((DataA!M73/DataA!M72)-1) -> 0.035494913 | X69: =AVERAGE(W60:W69) -> 0.054220493 | Y69: 0 | Z69: 67 | AA69: 67 | AC69: 65 | AD69: ='ONS pop proj 2021-based'!E67+'ONS pop proj 2021-based'!E174 -> 755810 | AE69: ='ONS pop proj 2021-based'!L67+'ONS pop proj 2021-based'!L174 -> 890721 | AF69: ='ONS pop proj 2021-based'!V67+'ONS pop proj 2021-based'!V174 -> 774520 | AG69: ='ONS pop proj 2021-based'!AF67+'ONS pop proj 2021-based'!AF174 -> 895467 | AX69: 35947 | AY69: =100*(HAVERM!C108/HAVERM!B108) -> 27.210418 | AZ69: =AVERAGE($AY$7:$AY$374) -> 24.595806 | BB69: =HAVERM!C108 -> 2382 | BC69: =HAVERM!B108-HAVERM!C108 -> 6372 | BF69: =100*((AVERAGE(HAVERQ!B57:B76)/AVERAGE(HAVERQ!B53:B72))-1) -> 2.6788742 | BG69: =$BL$6 -> 2.2155011 | BI69: 0 | BR69: =100*((AVERAGE(HAVERQ!C57:C76)/AVERAGE(HAVERQ!C53:C72))-1) -> 2.6667747 | BS69: =$BX$6 -> 1.9448021 | BU69: 0
A70: 2046 | B70: =DataA!F80*DataA!G80 -> 1217268.2 | C70: =DataA!H80/DataA!I80 -> 15.027346 | D70: =DataA!E80 -> 4345567 | E70: =DataA!J80 -> -1.67083 | F70: =DataA!D80 -> 3210289 | G70: =DataA!B80 -> 3210290 | I70: =100*((F70/F69)-1) -> 1.4976672 | J70: =100*((G70/G69)-1) -> 1.4976988 | V70: 2040 | W70: =100*((DataA!M74/DataA!M73)-1) -> 0.17466236 | X70: =AVERAGE(W61:W70) -> 0.058053728 | Y70: 0 | Z70: 67 | AA70: 67 | AC70: 66 | AD70: ='ONS pop proj 2021-based'!E68+'ONS pop proj 2021-based'!E175 -> 722831 | AE70: ='ONS pop proj 2021-based'!L68+'ONS pop proj 2021-based'!L175 -> 873165 | AF70: ='ONS pop proj 2021-based'!V68+'ONS pop proj 2021-based'!V175 -> 777733 | AG70: ='ONS pop proj 2021-based'!AF68+'ONS pop proj 2021-based'!AF175 -> 857070 | AX70: 35977 | AY70: =100*(HAVERM!C109/HAVERM!B109) -> 27.210024 | AZ70: =AVERAGE($AY$7:$AY$374) -> 24.595806 | BB70: =HAVERM!C109 -> 2367 | BC70: =HAVERM!B109-HAVERM!C109 -> 6332 | BF70: =100*((AVERAGE(HAVERQ!B58:B77)/AVERAGE(HAVERQ!B54:B73))-1) -> 2.6612767 | BG70: =$BL$6 -> 2.2155011 | BI70: 0 | BR70: =100*((AVERAGE(HAVERQ!C58:C77)/AVERAGE(HAVERQ!C54:C73))-1) -> 2.6654856 | BS70: =$BX$6 -> 1.9448021 | BU70: 0
A71: 2047 | B71: =DataA!F81*DataA!G81 -> 1221551.5 | C71: =DataA!H81/DataA!I81 -> 15.060735 | D71: =DataA!E81 -> 4427064 | E71: =DataA!J81 -> -1.66549 | F71: =DataA!D81 -> 3258161 | G71: =DataA!B81 -> 3258164 | I71: =100*((F71/F70)-1) -> 1.4912053 | J71: =100*((G71/G70)-1) -> 1.4912671 | V71: 2041 | W71: =100*((DataA!M75/DataA!M74)-1) -> 0.25025879 | X71: =AVERAGE(W62:W71) -> 0.072861767 | Y71: 0 | Z71: 67 | AA71: 67 | AC71: 67 | AD71: ='ONS pop proj 2021-based'!E69+'ONS pop proj 2021-based'!E176 -> 692602 | AE71: ='ONS pop proj 2021-based'!L69+'ONS pop proj 2021-based'!L176 -> 847752 | AF71: ='ONS pop proj 2021-based'!V69+'ONS pop proj 2021-based'!V176 -> 801291 | AG71: ='ONS pop proj 2021-based'!AF69+'ONS pop proj 2021-based'!AF176 -> 846386 | AX71: 36008 | AY71: =100*(HAVERM!C110/HAVERM!B110) -> 27.164316 | AZ71: =AVERAGE($AY$7:$AY$374) -> 24.595806 | BB71: =HAVERM!C110 -> 2369 | BC71: =HAVERM!B110-HAVERM!C110 -> 6352 | BF71: =100*((AVERAGE(HAVERQ!B59:B78)/AVERAGE(HAVERQ!B55:B74))-1) -> 2.5679632 | BG71: =$BL$6 -> 2.2155011 | BI71: 0 | BR71: =100*((AVERAGE(HAVERQ!C59:C78)/AVERAGE(HAVERQ!C55:C74))-1) -> 2.5995841 | BS71: =$BX$6 -> 1.9448021 | BU71: 0
A72: 2048 | B72: =DataA!F82*DataA!G82 -> 1225834 | C72: =DataA!H82/DataA!I82 -> 15.093198 | D72: =DataA!E82 -> 4509879 | E72: =DataA!J82 -> -1.660167 | F72: =DataA!D82 -> 3306547 | G72: =DataA!B82 -> 3306548 | I72: =100*((F72/F71)-1) -> 1.4850709 | J72: =100*((G72/G71)-1) -> 1.4850081 | V72: 2042 | W72: =100*((DataA!M76/DataA!M75)-1) -> 0.28008976 | X72: =AVERAGE(W63:W72) -> 0.09144537 | Y72: 0 | Z72: 67 | AA72: 67 | AC72: 68 | AD72: ='ONS pop proj 2021-based'!E70+'ONS pop proj 2021-based'!E177 -> 661499 | AE72: ='ONS pop proj 2021-based'!L70+'ONS pop proj 2021-based'!L177 -> 821386 | AF72: ='ONS pop proj 2021-based'!V70+'ONS pop proj 2021-based'!V177 -> 824066 | AG72: ='ONS pop proj 2021-based'!AF70+'ONS pop proj 2021-based'!AF177 -> 831846 | AX72: 36039 | AY72: =100*(HAVERM!C111/HAVERM!B111) -> 27.236146 | AZ72: =AVERAGE($AY$7:$AY$374) -> 24.595806 | BB72: =HAVERM!C111 -> 2369 | BC72: =HAVERM!B111-HAVERM!C111 -> 6329 | BE72: 1988 | BF72: =100*((AVERAGE(HAVERQ!B60:B79)/AVERAGE(HAVERQ!B56:B75))-1) -> 2.3764022 | BG72: =$BL$6 -> 2.2155011 | BI72: 0 | BQ72: 1988 | BR72: =100*((AVERAGE(HAVERQ!C60:C79)/AVERAGE(HAVERQ!C56:C75))-1) -> 2.447358 | BS72: =$BX$6 -> 1.9448021 | BU72: 0
A73: 2049 | B73: =DataA!F83*DataA!G83 -> 1230116.3 | C73: =DataA!H83/DataA!I83 -> 15.124732 | D73: =DataA!E83 -> 4594021 | E73: =DataA!J83 -> -1.65486 | F73: =DataA!D83 -> 3355443 | G73: =DataA!B83 -> 3355444 | I73: =100*((F73/F72)-1) -> 1.4787632 | J73: =100*((G73/G72)-1) -> 1.4787627 | V73: 2043 | W73: =100*((DataA!M77/DataA!M76)-1) -> 0.35619377 | X73: =AVERAGE(W64:W73) -> 0.1202203 | Y73: 0 | Z73: 67 | AA73: 67 | AC73: 69 | AD73: ='ONS pop proj 2021-based'!E71+'ONS pop proj 2021-based'!E178 -> 658027 | AE73: ='ONS pop proj 2021-based'!L71+'ONS pop proj 2021-based'!L178 -> 785627 | AF73: ='ONS pop proj 2021-based'!V71+'ONS pop proj 2021-based'!V178 -> 845203 | AG73: ='ONS pop proj 2021-based'!AF71+'ONS pop proj 2021-based'!AF178 -> 827449 | AX73: 36069 | AY73: =100*(HAVERM!C112/HAVERM!B112) -> 27.096551 | AZ73: =AVERAGE($AY$7:$AY$374) -> 24.595806 | BB73: =HAVERM!C112 -> 2349 | BC73: =HAVERM!B112-HAVERM!C112 -> 6320 | BF73: =100*((AVERAGE(HAVERQ!B61:B80)/AVERAGE(HAVERQ!B57:B76))-1) -> 2.1879128 | BG73: =$BL$6 -> 2.2155011 | BI73: 0 | BR73: =100*((AVERAGE(HAVERQ!C61:C80)/AVERAGE(HAVERQ!C57:C76))-1) -> 2.2895942 | BS73: =$BX$6 -> 1.9448021 | BU73: 0
A74: 2050 | B74: =DataA!F84*DataA!G84 -> 1234396.8 | C74: =DataA!H84/DataA!I84 -> 15.155262 | D74: =DataA!E84 -> 4679501 | E74: =DataA!J84 -> -1.649572 | F74: =DataA!D84 -> 3404844 | G74: =DataA!B84 -> 3404846 | I74: =100*((F74/F73)-1) -> 1.4722646 | J74: =100*((G74/G73)-1) -> 1.472294 | V74: 2044 | W74: =100*((DataA!M78/DataA!M77)-1) -> 0.65983188 | X74: =AVERAGE(W65:W74) -> 0.18215125 | Y74: 0 | Z74: 67.153425 | AA74: 67.153425 | AC74: 70 | AD74: ='ONS pop proj 2021-based'!E72+'ONS pop proj 2021-based'!E179 -> 642129 | AE74: ='ONS pop proj 2021-based'!L72+'ONS pop proj 2021-based'!L179 -> 746812 | AF74: ='ONS pop proj 2021-based'!V72+'ONS pop proj 2021-based'!V179 -> 815289 | AG74: ='ONS pop proj 2021-based'!AF72+'ONS pop proj 2021-based'!AF179 -> 817712 | AX74: 36100 | AY74: =100*(HAVERM!C113/HAVERM!B113) -> 27.014874 | AZ74: =AVERAGE($AY$7:$AY$374) -> 24.595806 | BB74: =HAVERM!C113 -> 2343 | BC74: =HAVERM!B113-HAVERM!C113 -> 6330 | BF74: =100*((AVERAGE(HAVERQ!B62:B81)/AVERAGE(HAVERQ!B58:B77))-1) -> 1.9934372 | BG74: =$BL$6 -> 2.2155011 | BI74: 0 | BR74: =100*((AVERAGE(HAVERQ!C62:C81)/AVERAGE(HAVERQ!C58:C77))-1) -> 2.1256569 | BS74: =$BX$6 -> 1.9448021 | BU74: 0
V75: 2045 | W75: =100*((DataA!M79/DataA!M78)-1) -> 1.0177159 | X75: =AVERAGE(W66:W75) -> 0.28062044 | Y75: 0 | Z75: 67.649315 | AA75: 67.649315 | AC75: 71 | AD75: ='ONS pop proj 2021-based'!E73+'ONS pop proj 2021-based'!E180 -> 617886 | AE75: ='ONS pop proj 2021-based'!L73+'ONS pop proj 2021-based'!L180 -> 720708 | AF75: ='ONS pop proj 2021-based'!V73+'ONS pop proj 2021-based'!V180 -> 823910 | AG75: ='ONS pop proj 2021-based'!AF73+'ONS pop proj 2021-based'!AF180 -> 773078 | AX75: 36130 | AY75: =100*(HAVERM!C114/HAVERM!B114) -> 27.00603 | AZ75: =AVERAGE($AY$7:$AY$374) -> 24.595806 | BB75: =HAVERM!C114 -> 2329 | BC75: =HAVERM!B114-HAVERM!C114 -> 6295 | BF75: =100*((AVERAGE(HAVERQ!B63:B82)/AVERAGE(HAVERQ!B59:B78))-1) -> 1.8675583 | BG75: =$BL$6 -> 2.2155011 | BI75: 0 | BR75: =100*((AVERAGE(HAVERQ!C63:C82)/AVERAGE(HAVERQ!C59:C78))-1) -> 2.0191783 | BS75: =$BX$6 -> 1.9448021 | BU75: 0
A76: Contributions to growth | V76: 2046 | W76: =100*((DataA!M80/DataA!M79)-1) -> 0.74065358 | X76: =AVERAGE(W67:W76) -> 0.35295777 | Y76: 0 | Z76: 68 | AA76: 68 | AC76: 72 | AD76: ='ONS pop proj 2021-based'!E74+'ONS pop proj 2021-based'!E181 -> 616223 | AE76: ='ONS pop proj 2021-based'!L74+'ONS pop proj 2021-based'!L181 -> 692511 | AF76: ='ONS pop proj 2021-based'!V74+'ONS pop proj 2021-based'!V181 -> 811297 | AG76: ='ONS pop proj 2021-based'!AF74+'ONS pop proj 2021-based'!AF181 -> 709334 | AX76: 36161 | AY76: =100*(HAVERM!C115/HAVERM!B115) -> 26.93958 | AZ76: =AVERAGE($AY$7:$AY$374) -> 24.595806 | BB76: =HAVERM!C115 -> 2323 | BC76: =HAVERM!B115-HAVERM!C115 -> 6300 | BE76: 1989 | BF76: =100*((AVERAGE(HAVERQ!B64:B83)/AVERAGE(HAVERQ!B60:B79))-1) -> 1.8018018 | BG76: =$BL$6 -> 2.2155011 | BI76: 0 | BQ76: 1989 | BR76: =100*((AVERAGE(HAVERQ!C64:C83)/AVERAGE(HAVERQ!C60:C79))-1) -> 1.9700613 | BS76: =$BX$6 -> 1.9448021 | BU76: 0
B77: Labour supply | C77: Human capital | D77: Capital stock | E77: Total factor productivity | F77: Potential output | G77: GDP | V77: 2047 | W77: =100*((DataA!M81/DataA!M80)-1) -> 0.21144654 | X77: =AVERAGE(W68:W77) -> 0.37297639 | Y77: 0 | Z77: 68 | AA77: 68 | AC77: 73 | AD77: ='ONS pop proj 2021-based'!E75+'ONS pop proj 2021-based'!E182 -> 618518 | AE77: ='ONS pop proj 2021-based'!L75+'ONS pop proj 2021-based'!L182 -> 656098 | AF77: ='ONS pop proj 2021-based'!V75+'ONS pop proj 2021-based'!V182 -> 803511 | AG77: ='ONS pop proj 2021-based'!AF75+'ONS pop proj 2021-based'!AF182 -> 684268 | AX77: 36192 | AY77: =100*(HAVERM!C116/HAVERM!B116) -> 27.032967 | AZ77: =AVERAGE($AY$7:$AY$374) -> 24.595806 | BB77: =HAVERM!C116 -> 2337 | BC77: =HAVERM!B116-HAVERM!C116 -> 6308 | BF77: =100*((AVERAGE(HAVERQ!B65:B84)/AVERAGE(HAVERQ!B61:B80))-1) -> 1.8421265 | BG77: =$BL$6 -> 2.2155011 | BI77: 0 | BR77: =100*((AVERAGE(HAVERQ!C65:C84)/AVERAGE(HAVERQ!C61:C80))-1) -> 2.0222291 | BS77: =$BX$6 -> 1.9448021 | BU77: 0
A78: 1990s | B78: =0.65*(100*((B23/B13)^(1/10)-1)) -> 0.10824108 | C78: =0.3*(100*((C23/C13)^(1/10)-1)) -> 0.21475281 | D78: =0.35*(100*((D23/D13)^(1/10)-1)) -> 1.021061 | E78: =F78-B78-C78-D78 -> 0.91719085 | F78: =100*((F23/F13)^(1/10)-1) -> 2.2612457 | G78: =100*((G23/G13)^(1/10)-1) -> 2.1292548 | V78: 2048 | W78: =100*((DataA!M82/DataA!M81)-1) -> 0.11512688 | X78: =AVERAGE(W69:W78) -> 0.38414743 | Y78: 0 | Z78: 68 | AA78: 68 | AC78: 74 | AD78: ='ONS pop proj 2021-based'!E76+'ONS pop proj 2021-based'!E183 -> 625529 | AE78: ='ONS pop proj 2021-based'!L76+'ONS pop proj 2021-based'!L183 -> 621966 | AF78: ='ONS pop proj 2021-based'!V76+'ONS pop proj 2021-based'!V183 -> 786480 | AG78: ='ONS pop proj 2021-based'!AF76+'ONS pop proj 2021-based'!AF183 -> 686677 | AX78: 36220 | AY78: =100*(HAVERM!C117/HAVERM!B117) -> 27.221325 | AZ78: =AVERAGE($AY$7:$AY$374) -> 24.595806 | BB78: =HAVERM!C117 -> 2359 | BC78: =HAVERM!B117-HAVERM!C117 -> 6307 | BF78: =100*((AVERAGE(HAVERQ!B66:B85)/AVERAGE(HAVERQ!B62:B81))-1) -> 1.882088 | BG78: =$BL$6 -> 2.2155011 | BI78: 0 | BR78: =100*((AVERAGE(HAVERQ!C66:C85)/AVERAGE(HAVERQ!C62:C81))-1) -> 2.0583717 | BS78: =$BX$6 -> 1.9448021 | BU78: 0
A79: 2000s | B79: =0.65*(100*((B33/B23)^(1/10)-1)) -> 0.35329699 | C79: =0.3*(100*((C33/C23)^(1/10)-1)) -> 0.69157895 | D79: =0.35*(100*((D33/D23)^(1/10)-1)) -> 0.96812456 | E79: =F79-B79-C79-D79 -> 0.38702909 | F79: =100*((F33/F23)^(1/10)-1) -> 2.4000296 | G79: =100*((G33/G23)^(1/10)-1) -> 1.6882802 | V79: 2049 | W79: =100*((DataA!M83/DataA!M82)-1) -> 0.11234761 | X79: =AVERAGE(W70:W79) -> 0.3918327 | Y79: 0 | Z79: 68 | AA79: 68 | AC79: 75 | AD79: ='ONS pop proj 2021-based'!E77+'ONS pop proj 2021-based'!E184 -> 650328 | AE79: ='ONS pop proj 2021-based'!L77+'ONS pop proj 2021-based'!L184 -> 587019 | AF79: ='ONS pop proj 2021-based'!V77+'ONS pop proj 2021-based'!V184 -> 775787 | AG79: ='ONS pop proj 2021-based'!AF77+'ONS pop proj 2021-based'!AF184 -> 685405 | AX79: 36251 | AY79: =100*(HAVERM!C118/HAVERM!B118) -> 27.108503 | AZ79: =AVERAGE($AY$7:$AY$374) -> 24.595806 | BB79: =HAVERM!C118 -> 2356 | BC79: =HAVERM!B118-HAVERM!C118 -> 6335 | BF79: =100*((AVERAGE(HAVERQ!B67:B86)/AVERAGE(HAVERQ!B63:B82))-1) -> 1.8493315 | BG79: =$BL$6 -> 2.2155011 | BI79: 0 | BR79: =100*((AVERAGE(HAVERQ!C67:C86)/AVERAGE(HAVERQ!C63:C82))-1) -> 2.0097814 | BS79: =$BX$6 -> 1.9448021 | BU79: 0
A80: 2010s | B80: =0.65*(100*((B43/B33)^(1/10)-1)) -> 0.67486636 | C80: =0.3*(100*((C43/C33)^(1/10)-1)) -> 0.2370697 | D80: =0.35*(100*((D43/D33)^(1/10)-1)) -> 0.62601845 | E80: =F80-B80-C80-D80 -> -0.046820081 | F80: =100*((F43/F33)^(1/10)-1) -> 1.4911344 | G80: =100*((G43/G33)^(1/10)-1) -> 1.970971 | V80: 2050 | W80: =100*((DataA!M84/DataA!M83)-1) -> 0.11699296 | X80: =AVERAGE(W71:W80) -> 0.38606576 | Y80: 0 | Z80: 68 | AA80: 68 | AC80: 76 | AD80: ='ONS pop proj 2021-based'!E78+'ONS pop proj 2021-based'!E185 -> 692882 | AE80: ='ONS pop proj 2021-based'!L78+'ONS pop proj 2021-based'!L185 -> 576085 | AF80: ='ONS pop proj 2021-based'!V78+'ONS pop proj 2021-based'!V185 -> 748989 | AG80: ='ONS pop proj 2021-based'!AF78+'ONS pop proj 2021-based'!AF185 -> 678886 | AX80: 36281 | AY80: =100*(HAVERM!C119/HAVERM!B119) -> 27.049747 | AZ80: =AVERAGE($AY$7:$AY$374) -> 24.595806 | BB80: =HAVERM!C119 -> 2349 | BC80: =HAVERM!B119-HAVERM!C119 -> 6335 | BE80: 1990 | BF80: =100*((AVERAGE(HAVERQ!B68:B87)/AVERAGE(HAVERQ!B64:B83))-1) -> 1.8496372 | BG80: =$BL$6 -> 2.2155011 | BI80: 0 | BQ80: 1990 | BR80: =100*((AVERAGE(HAVERQ!C68:C87)/AVERAGE(HAVERQ!C64:C83))-1) -> 1.9776375 | BS80: =$BX$6 -> 1.9448021 | BU80: 0
A81: 2020s | B81: =0.65*(100*((B53/B43)^(1/10)-1)) -> 0.46363364 | C81: =0.3*(100*((C53/C43)^(1/10)-1)) -> 0.18501538 | D81: =0.35*(100*((D53/D43)^(1/10)-1)) -> 0.44623076 | E81: =F81-B81-C81-D81 -> -0.01736266 | F81: =100*((F53/F43)^(1/10)-1) -> 1.0775171 | G81: =100*((G53/G43)^(1/10)-1) -> 1.0921323 | AC81: 77 | AD81: ='ONS pop proj 2021-based'!E79+'ONS pop proj 2021-based'!E186 -> 521929 | AE81: ='ONS pop proj 2021-based'!L79+'ONS pop proj 2021-based'!L186 -> 553641 | AF81: ='ONS pop proj 2021-based'!V79+'ONS pop proj 2021-based'!V186 -> 714705 | AG81: ='ONS pop proj 2021-based'!AF79+'ONS pop proj 2021-based'!AF186 -> 688677 | AX81: 36312 | AY81: =100*(HAVERM!C120/HAVERM!B120) -> 26.93502 | AZ81: =AVERAGE($AY$7:$AY$374) -> 24.595806 | BB81: =HAVERM!C120 -> 2342 | BC81: =HAVERM!B120-HAVERM!C120 -> 6353 | BF81: =100*((AVERAGE(HAVERQ!B69:B88)/AVERAGE(HAVERQ!B65:B84))-1) -> 1.7056724 | BG81: =$BL$6 -> 2.2155011 | BI81: 0 | BR81: =100*((AVERAGE(HAVERQ!C69:C88)/AVERAGE(HAVERQ!C65:C84))-1) -> 1.7930095 | BS81: =$BX$6 -> 1.9448021 | BU81: 0
A82: 2030s | B82: =0.65*(100*((B63/B53)^(1/10)-1)) -> 0.34100758 | C82: =0.3*(100*((C63/C53)^(1/10)-1)) -> 0.11537114 | D82: =0.35*(100*((D63/D53)^(1/10)-1)) -> 0.57888758 | E82: =F82-B82-C82-D82 -> 0.45124768 | F82: =100*((F63/F53)^(1/10)-1) -> 1.486514 | G82: =100*((G63/G53)^(1/10)-1) -> 1.4942621 | V82: 2013-2023 | W82: =100*((DataA!M57/DataA!M47)^(1/10)-1) -> 1.0068444 | AC82: 78 | AD82: ='ONS pop proj 2021-based'!E80+'ONS pop proj 2021-based'!E187 -> 494882 | AE82: ='ONS pop proj 2021-based'!L80+'ONS pop proj 2021-based'!L187 -> 523757 | AF82: ='ONS pop proj 2021-based'!V80+'ONS pop proj 2021-based'!V187 -> 679118 | AG82: ='ONS pop proj 2021-based'!AF80+'ONS pop proj 2021-based'!AF187 -> 695986 | AX82: 36342 | AY82: =100*(HAVERM!C121/HAVERM!B121) -> 26.837134 | AZ82: =AVERAGE($AY$7:$AY$374) -> 24.595806 | BB82: =HAVERM!C121 -> 2330 | BC82: =HAVERM!B121-HAVERM!C121 -> 6352 | BF82: =100*((AVERAGE(HAVERQ!B70:B89)/AVERAGE(HAVERQ!B66:B85))-1) -> 1.5552222 | BG82: =$BL$6 -> 2.2155011 | BI82: 0 | BR82: =100*((AVERAGE(HAVERQ!C70:C89)/AVERAGE(HAVERQ!C66:C85))-1) -> 1.5954244 | BS82: =$BX$6 -> 1.9448021 | BU82: 0
A83: 2040s | B83: =0.65*(100*((B73/B63)^(1/10)-1)) -> 0.23469562 | C83: =0.3*(100*((C73/C63)^(1/10)-1)) -> 0.072445103 | D83: =0.35*(100*((D73/D63)^(1/10)-1)) -> 0.65960424 | E83: =F83-B83-C83-D83 -> 0.54338253 | F83: =100*((F73/F63)^(1/10)-1) -> 1.5101275 | G83: =100*((G73/G63)^(1/10)-1) -> 1.510127 | V83: 2023-2033 | W83: =100*((DataA!M67/DataA!M57)^(1/10)-1) -> 0.56821436 | AC83: 79 | AD83: ='ONS pop proj 2021-based'!E81+'ONS pop proj 2021-based'!E188 -> 481370 | AE83: ='ONS pop proj 2021-based'!L81+'ONS pop proj 2021-based'!L188 -> 512218 | AF83: ='ONS pop proj 2021-based'!V81+'ONS pop proj 2021-based'!V188 -> 635301 | AG83: ='ONS pop proj 2021-based'!AF81+'ONS pop proj 2021-based'!AF188 -> 700022 | AX83: 36373 | AY83: =100*(HAVERM!C122/HAVERM!B122) -> 27.015477 | AZ83: =AVERAGE($AY$7:$AY$374) -> 24.595806 | BB83: =HAVERM!C122 -> 2339 | BC83: =HAVERM!B122-HAVERM!C122 -> 6319 | BF83: =100*((AVERAGE(HAVERQ!B71:B90)/AVERAGE(HAVERQ!B67:B86))-1) -> 1.5013363 | BG83: =$BL$6 -> 2.2155011 | BI83: 0 | BR83: =100*((AVERAGE(HAVERQ!C71:C90)/AVERAGE(HAVERQ!C67:C86))-1) -> 1.4832572 | BS83: =$BX$6 -> 1.9448021 | BU83: 0
V84: 2033-2043 | W84: =100*((DataA!M77/DataA!M67)^(1/10)-1) -> 0.12014126 | AC84: 80 | AD84: ='ONS pop proj 2021-based'!E82+'ONS pop proj 2021-based'!E189 -> 434985 | AE84: ='ONS pop proj 2021-based'!L82+'ONS pop proj 2021-based'!L189 -> 502933 | AF84: ='ONS pop proj 2021-based'!V82+'ONS pop proj 2021-based'!V189 -> 588990 | AG84: ='ONS pop proj 2021-based'!AF82+'ONS pop proj 2021-based'!AF189 -> 660332 | AX84: 36404 | AY84: =100*(HAVERM!C123/HAVERM!B123) -> 26.7288 | AZ84: =AVERAGE($AY$7:$AY$374) -> 24.595806 | BB84: =HAVERM!C123 -> 2323 | BC84: =HAVERM!B123-HAVERM!C123 -> 6368 | BE84: 1991 | BF84: =100*((AVERAGE(HAVERQ!B72:B91)/AVERAGE(HAVERQ!B68:B87))-1) -> 1.4637965 | BG84: =$BL$6 -> 2.2155011 | BI84: 0 | BQ84: 1991 | BR84: =100*((AVERAGE(HAVERQ!C72:C91)/AVERAGE(HAVERQ!C68:C87))-1) -> 1.3798762 | BS84: =$BX$6 -> 1.9448021 | BU84: 0
A85: diff vs 10-19 | AC85: 81 | AD85: ='ONS pop proj 2021-based'!E83+'ONS pop proj 2021-based'!E190 -> 377338 | AE85: ='ONS pop proj 2021-based'!L83+'ONS pop proj 2021-based'!L190 -> 495885 | AF85: ='ONS pop proj 2021-based'!V83+'ONS pop proj 2021-based'!V190 -> 552412 | AG85: ='ONS pop proj 2021-based'!AF83+'ONS pop proj 2021-based'!AF190 -> 650515 | AX85: 36434 | AY85: =100*(HAVERM!C124/HAVERM!B124) -> 26.648161 | AZ85: =AVERAGE($AY$7:$AY$374) -> 24.595806 | BB85: =HAVERM!C124 -> 2304 | BC85: =HAVERM!B124-HAVERM!C124 -> 6342 | BF85: =100*((AVERAGE(HAVERQ!B73:B92)/AVERAGE(HAVERQ!B69:B88))-1) -> 1.5210608 | BG85: =$BL$6 -> 2.2155011 | BI85: 0 | BR85: =100*((AVERAGE(HAVERQ!C73:C92)/AVERAGE(HAVERQ!C69:C88))-1) -> 1.3600892 | BS85: =$BX$6 -> 1.9448021 | BU85: 0
A86: 2020-30 | B86: =B81-B$79 -> 0.11033665 | C86: =C81-C$79 -> -0.50656358 | D86: =D81-D$79 -> -0.52189379 | E86: =E81-E$79 -> -0.40439175 | F86: =F81-F$79 -> -1.3225125 | G86: =G81-G$79 -> -0.59614794 | AC86: 82 | AD86: ='ONS pop proj 2021-based'!E84+'ONS pop proj 2021-based'!E191 -> 325837 | AE86: ='ONS pop proj 2021-based'!L84+'ONS pop proj 2021-based'!L191 -> 500858 | AF86: ='ONS pop proj 2021-based'!V84+'ONS pop proj 2021-based'!V191 -> 513750 | AG86: ='ONS pop proj 2021-based'!AF84+'ONS pop proj 2021-based'!AF191 -> 622182 | AX86: 36465 | AY86: =100*(HAVERM!C125/HAVERM!B125) -> 26.485923 | AZ86: =AVERAGE($AY$7:$AY$374) -> 24.595806 | BB86: =HAVERM!C125 -> 2286 | BC86: =HAVERM!B125-HAVERM!C125 -> 6345 | BF86: =100*((AVERAGE(HAVERQ!B74:B93)/AVERAGE(HAVERQ!B70:B89))-1) -> 1.6169154 | BG86: =$BL$6 -> 2.2155011 | BI86: 0 | BR86: =100*((AVERAGE(HAVERQ!C74:C93)/AVERAGE(HAVERQ!C70:C89))-1) -> 1.3851852 | BS86: =$BX$6 -> 1.9448021 | BU86: 0
A87: 2030-40 | B87: =B82-B$79 -> -0.012289415 | C87: =C82-C$79 -> -0.57620781 | D87: =D82-D$79 -> -0.38923698 | E87: =E82-E$79 -> 0.064218594 | F87: =F82-F$79 -> -0.91351561 | G87: =G82-G$79 -> -0.19401809 | AC87: 83 | AD87: ='ONS pop proj 2021-based'!E85+'ONS pop proj 2021-based'!E192 -> 322874 | AE87: ='ONS pop proj 2021-based'!L85+'ONS pop proj 2021-based'!L192 -> 516007 | AF87: ='ONS pop proj 2021-based'!V85+'ONS pop proj 2021-based'!V192 -> 468878 | AG87: ='ONS pop proj 2021-based'!AF85+'ONS pop proj 2021-based'!AF192 -> 595918 | AX87: 36495 | AY87: =100*(HAVERM!C126/HAVERM!B126) -> 26.500868 | AZ87: =AVERAGE($AY$7:$AY$374) -> 24.595806 | BB87: =HAVERM!C126 -> 2291 | BC87: =HAVERM!B126-HAVERM!C126 -> 6354 | BF87: =100*((AVERAGE(HAVERQ!B75:B94)/AVERAGE(HAVERQ!B71:B90))-1) -> 1.6649888 | BG87: =$BL$6 -> 2.2155011 | BI87: 0 | BR87: =100*((AVERAGE(HAVERQ!C75:C94)/AVERAGE(HAVERQ!C71:C90))-1) -> 1.3729977 | BS87: =$BX$6 -> 1.9448021 | BU87: 0
A88: 2040-50 | B88: =B83-B$79 -> -0.11860137 | C88: =C83-C$79 -> -0.61913385 | D88: =D83-D$79 -> -0.30852032 | E88: =E83-E$79 -> 0.15635344 | F88: =F83-F$79 -> -0.8899021 | G88: =G83-G$79 -> -0.17815319 | AC88: 84 | AD88: ='ONS pop proj 2021-based'!E86+'ONS pop proj 2021-based'!E193 -> 304153 | AE88: ='ONS pop proj 2021-based'!L86+'ONS pop proj 2021-based'!L193 -> 374112 | AF88: ='ONS pop proj 2021-based'!V86+'ONS pop proj 2021-based'!V193 -> 425734 | AG88: ='ONS pop proj 2021-based'!AF86+'ONS pop proj 2021-based'!AF193 -> 561448 | AX88: 36526 | AY88: =100*(HAVERM!C127/HAVERM!B127) -> 26.437046 | AZ88: =AVERAGE($AY$7:$AY$374) -> 24.595806 | BB88: =HAVERM!C127 -> 2295 | BC88: =HAVERM!B127-HAVERM!C127 -> 6386 | BE88: 1992 | BF88: =100*((AVERAGE(HAVERQ!B76:B95)/AVERAGE(HAVERQ!B72:B91))-1) -> 1.7204135 | BG88: =$BL$6 -> 2.2155011 | BI88: 0 | BQ88: 1992 | BR88: =100*((AVERAGE(HAVERQ!C76:C95)/AVERAGE(HAVERQ!C72:C91))-1) -> 1.3831666 | BS88: =$BX$6 -> 1.9448021 | BU88: 0
A89: diff | AC89: 85 | AD89: ='ONS pop proj 2021-based'!E87+'ONS pop proj 2021-based'!E194 -> 279115 | AE89: ='ONS pop proj 2021-based'!L87+'ONS pop proj 2021-based'!L194 -> 339359 | AF89: ='ONS pop proj 2021-based'!V87+'ONS pop proj 2021-based'!V194 -> 382553 | AG89: ='ONS pop proj 2021-based'!AF87+'ONS pop proj 2021-based'!AF194 -> 529763 | AX89: 36557 | AY89: =100*(HAVERM!C128/HAVERM!B128) -> 26.65896 | AZ89: =AVERAGE($AY$7:$AY$374) -> 24.595806 | BB89: =HAVERM!C128 -> 2306 | BC89: =HAVERM!B128-HAVERM!C128 -> 6344 | BF89: =100*((AVERAGE(HAVERQ!B77:B96)/AVERAGE(HAVERQ!B73:B92))-1) -> 1.6980407 | BG89: =$BL$6 -> 2.2155011 | BI89: 0 | BR89: =100*((AVERAGE(HAVERQ!C77:C96)/AVERAGE(HAVERQ!C73:C92))-1) -> 1.3565039 | BS89: =$BX$6 -> 1.9448021 | BU89: 0
AC90: 86 | AD90: ='ONS pop proj 2021-based'!E88+'ONS pop proj 2021-based'!E195 -> 248204 | AE90: ='ONS pop proj 2021-based'!L88+'ONS pop proj 2021-based'!L195 -> 313602 | AF90: ='ONS pop proj 2021-based'!V88+'ONS pop proj 2021-based'!V195 -> 354793 | AG90: ='ONS pop proj 2021-based'!AF88+'ONS pop proj 2021-based'!AF195 -> 486170 | AX90: 36586 | AY90: =100*(HAVERM!C129/HAVERM!B129) -> 26.722145 | AZ90: =AVERAGE($AY$7:$AY$374) -> 24.595806 | BB90: =HAVERM!C129 -> 2312 | BC90: =HAVERM!B129-HAVERM!C129 -> 6340 | BF90: =100*((AVERAGE(HAVERQ!B78:B97)/AVERAGE(HAVERQ!B74:B93))-1) -> 1.6600367 | BG90: =$BL$6 -> 2.2155011 | BI90: 0 | BR90: =100*((AVERAGE(HAVERQ!C78:C97)/AVERAGE(HAVERQ!C74:C93))-1) -> 1.2931979 | BS90: =$BX$6 -> 1.9448021 | BU90: 0
AC91: 87 | AD91: ='ONS pop proj 2021-based'!E89+'ONS pop proj 2021-based'!E196 -> 217915 | AE91: ='ONS pop proj 2021-based'!L89+'ONS pop proj 2021-based'!L196 -> 267540 | AF91: ='ONS pop proj 2021-based'!V89+'ONS pop proj 2021-based'!V196 -> 319562 | AG91: ='ONS pop proj 2021-based'!AF89+'ONS pop proj 2021-based'!AF196 -> 437593 | AX91: 36617 | AY91: =100*(HAVERM!C130/HAVERM!B130) -> 26.646603 | AZ91: =AVERAGE($AY$7:$AY$374) -> 24.595806 | BB91: =HAVERM!C130 -> 2302 | BC91: =HAVERM!B130-HAVERM!C130 -> 6337 | BF91: =100*((AVERAGE(HAVERQ!B79:B98)/AVERAGE(HAVERQ!B75:B94))-1) -> 1.713894 | BG91: =$BL$6 -> 2.2155011 | BI91: 0 | BR91: =100*((AVERAGE(HAVERQ!C79:C98)/AVERAGE(HAVERQ!C75:C94))-1) -> 1.3179932 | BS91: =$BX$6 -> 1.9448021 | BU91: 0
AC92: 88 | AD92: ='ONS pop proj 2021-based'!E90+'ONS pop proj 2021-based'!E197 -> 189527 | AE92: ='ONS pop proj 2021-based'!L90+'ONS pop proj 2021-based'!L197 -> 217481 | AF92: ='ONS pop proj 2021-based'!V90+'ONS pop proj 2021-based'!V197 -> 280948 | AG92: ='ONS pop proj 2021-based'!AF90+'ONS pop proj 2021-based'!AF197 -> 389014 | AX92: 36647 | AY92: =100*(HAVERM!C131/HAVERM!B131) -> 26.412918 | AZ92: =AVERAGE($AY$7:$AY$374) -> 24.595806 | BB92: =HAVERM!C131 -> 2290 | BC92: =HAVERM!B131-HAVERM!C131 -> 6380 | BE92: 1993 | BF92: =100*((AVERAGE(HAVERQ!B80:B99)/AVERAGE(HAVERQ!B76:B95))-1) -> 1.7595753 | BG92: =$BL$6 -> 2.2155011 | BI92: 0 | BQ92: 1993 | BR92: =100*((AVERAGE(HAVERQ!C80:C99)/AVERAGE(HAVERQ!C76:C95))-1) -> 1.3352685 | BS92: =$BX$6 -> 1.9448021 | BU92: 0
AC93: 89 | AD93: ='ONS pop proj 2021-based'!E91+'ONS pop proj 2021-based'!E198 -> 159316 | AE93: ='ONS pop proj 2021-based'!L91+'ONS pop proj 2021-based'!L198 -> 174613 | AF93: ='ONS pop proj 2021-based'!V91+'ONS pop proj 2021-based'!V198 -> 252697 | AG93: ='ONS pop proj 2021-based'!AF91+'ONS pop proj 2021-based'!AF198 -> 337231 | AX93: 36678 | AY93: =100*(HAVERM!C132/HAVERM!B132) -> 26.359447 | AZ93: =AVERAGE($AY$7:$AY$374) -> 24.595806 | BB93: =HAVERM!C132 -> 2288 | BC93: =HAVERM!B132-HAVERM!C132 -> 6392 | BF93: =100*((AVERAGE(HAVERQ!B81:B100)/AVERAGE(HAVERQ!B77:B96))-1) -> 1.8887882 | BG93: =$BL$6 -> 2.2155011 | BI93: 0 | BR93: =100*((AVERAGE(HAVERQ!C81:C100)/AVERAGE(HAVERQ!C77:C96))-1) -> 1.4179266 | BS93: =$BX$6 -> 1.9448021 | BU93: 0
AC94: 90 | AD94: ='ONS pop proj 2021-based'!E92+'ONS pop proj 2021-based'!E199 -> 135366 | AE94: ='ONS pop proj 2021-based'!L92+'ONS pop proj 2021-based'!L199 -> 159559 | AF94: ='ONS pop proj 2021-based'!V92+'ONS pop proj 2021-based'!V199 -> 225858 | AG94: ='ONS pop proj 2021-based'!AF92+'ONS pop proj 2021-based'!AF199 -> 286876 | AX94: 36708 | AY94: =100*(HAVERM!C133/HAVERM!B133) -> 26.535315 | AZ94: =AVERAGE($AY$7:$AY$374) -> 24.595806 | BB94: =HAVERM!C133 -> 2303 | BC94: =HAVERM!B133-HAVERM!C133 -> 6376 | BF94: =100*((AVERAGE(HAVERQ!B82:B101)/AVERAGE(HAVERQ!B78:B97))-1) -> 2.0317556 | BG94: =$BL$6 -> 2.2155011 | BI94: 0 | BR94: =100*((AVERAGE(HAVERQ!C82:C101)/AVERAGE(HAVERQ!C78:C97))-1) -> 1.5363531 | BS94: =$BX$6 -> 1.9448021 | BU94: 0
AC95: 91 | AD95: ='ONS pop proj 2021-based'!E93+'ONS pop proj 2021-based'!E200 -> 115669 | AE95: ='ONS pop proj 2021-based'!L93+'ONS pop proj 2021-based'!L200 -> 137345 | AF95: ='ONS pop proj 2021-based'!V93+'ONS pop proj 2021-based'!V200 -> 200163 | AG95: ='ONS pop proj 2021-based'!AF93+'ONS pop proj 2021-based'!AF200 -> 244073 | AX95: 36739 | AY95: =100*(HAVERM!C134/HAVERM!B134) -> 26.61597 | AZ95: =AVERAGE($AY$7:$AY$374) -> 24.595806 | BB95: =HAVERM!C134 -> 2310 | BC95: =HAVERM!B134-HAVERM!C134 -> 6369 | BF95: =100*((AVERAGE(HAVERQ!B83:B102)/AVERAGE(HAVERQ!B79:B98))-1) -> 2.1268629 | BG95: =$BL$6 -> 2.2155011 | BI95: 0 | BR95: =100*((AVERAGE(HAVERQ!C83:C102)/AVERAGE(HAVERQ!C79:C98))-1) -> 1.6098893 | BS95: =$BX$6 -> 1.9448021 | BU95: 0
AC96: 92 | AD96: ='ONS pop proj 2021-based'!E94+'ONS pop proj 2021-based'!E201 -> 94447 | AE96: ='ONS pop proj 2021-based'!L94+'ONS pop proj 2021-based'!L201 -> 113990 | AF96: ='ONS pop proj 2021-based'!V94+'ONS pop proj 2021-based'!V201 -> 179448 | AG96: ='ONS pop proj 2021-based'!AF94+'ONS pop proj 2021-based'!AF201 -> 203245 | AX96: 36770 | AY96: =100*(HAVERM!C135/HAVERM!B135) -> 26.619201 | AZ96: =AVERAGE($AY$7:$AY$374) -> 24.595806 | BB96: =HAVERM!C135 -> 2318 | BC96: =HAVERM!B135-HAVERM!C135 -> 6390 | BE96: 1994 | BF96: =100*((AVERAGE(HAVERQ!B84:B103)/AVERAGE(HAVERQ!B80:B99))-1) -> 2.258329 | BG96: =$BL$6 -> 2.2155011 | BI96: 0 | BQ96: 1994 | BR96: =100*((AVERAGE(HAVERQ!C84:C103)/AVERAGE(HAVERQ!C80:C99))-1) -> 1.7330278 | BS96: =$BX$6 -> 1.9448021 | BU96: 0
AC97: 93 | AD97: ='ONS pop proj 2021-based'!E95+'ONS pop proj 2021-based'!E202 -> 75449 | AE97: ='ONS pop proj 2021-based'!L95+'ONS pop proj 2021-based'!L202 -> 90699 | AF97: ='ONS pop proj 2021-based'!V95+'ONS pop proj 2021-based'!V202 -> 161665 | AG97: ='ONS pop proj 2021-based'!AF95+'ONS pop proj 2021-based'!AF202 -> 163791 | AX97: 36800 | AY97: =100*(HAVERM!C136/HAVERM!B136) -> 26.831491 | AZ97: =AVERAGE($AY$7:$AY$374) -> 24.595806 | BB97: =HAVERM!C136 -> 2355 | BC97: =HAVERM!B136-HAVERM!C136 -> 6422 | BF97: =100*((AVERAGE(HAVERQ!B85:B104)/AVERAGE(HAVERQ!B81:B100))-1) -> 2.3876613 | BG97: =$BL$6 -> 2.2155011 | BI97: 0 | BR97: =100*((AVERAGE(HAVERQ!C85:C104)/AVERAGE(HAVERQ!C81:C100))-1) -> 1.8546259 | BS97: =$BX$6 -> 1.9448021 | BU97: 0
AC98: 94 | AD98: ='ONS pop proj 2021-based'!E96+'ONS pop proj 2021-based'!E203 -> 57268 | AE98: ='ONS pop proj 2021-based'!L96+'ONS pop proj 2021-based'!L203 -> 70383 | AF98: ='ONS pop proj 2021-based'!V96+'ONS pop proj 2021-based'!V203 -> 100955 | AG98: ='ONS pop proj 2021-based'!AF96+'ONS pop proj 2021-based'!AF203 -> 129275 | AX98: 36831 | AY98: =100*(HAVERM!C137/HAVERM!B137) -> 26.675023 | AZ98: =AVERAGE($AY$7:$AY$374) -> 24.595806 | BB98: =HAVERM!C137 -> 2341 | BC98: =HAVERM!B137-HAVERM!C137 -> 6435 | BF98: =100*((AVERAGE(HAVERQ!B86:B105)/AVERAGE(HAVERQ!B82:B101))-1) -> 2.485434 | BG98: =$BL$6 -> 2.2155011 | BI98: 0 | BR98: =100*((AVERAGE(HAVERQ!C86:C105)/AVERAGE(HAVERQ!C82:C101))-1) -> 1.9748526 | BS98: =$BX$6 -> 1.9448021 | BU98: 0
AC99: 95 | AD99: ='ONS pop proj 2021-based'!E97+'ONS pop proj 2021-based'!E204 -> 42595 | AE99: ='ONS pop proj 2021-based'!L97+'ONS pop proj 2021-based'!L204 -> 53384 | AF99: ='ONS pop proj 2021-based'!V97+'ONS pop proj 2021-based'!V204 -> 77617 | AG99: ='ONS pop proj 2021-based'!AF97+'ONS pop proj 2021-based'!AF204 -> 99401 | AX99: 36861 | AY99: =100*(HAVERM!C138/HAVERM!B138) -> 26.80436 | AZ99: =AVERAGE($AY$7:$AY$374) -> 24.595806 | BB99: =HAVERM!C138 -> 2336 | BC99: =HAVERM!B138-HAVERM!C138 -> 6379 | BF99: =100*((AVERAGE(HAVERQ!B87:B106)/AVERAGE(HAVERQ!B83:B102))-1) -> 2.5298819 | BG99: =$BL$6 -> 2.2155011 | BI99: 0 | BR99: =100*((AVERAGE(HAVERQ!C87:C106)/AVERAGE(HAVERQ!C83:C102))-1) -> 2.0936483 | BS99: =$BX$6 -> 1.9448021 | BU99: 0
AC100: 96 | AD100: ='ONS pop proj 2021-based'!E98+'ONS pop proj 2021-based'!E205 -> 31264 | AE100: ='ONS pop proj 2021-based'!L98+'ONS pop proj 2021-based'!L205 -> 38606 | AF100: ='ONS pop proj 2021-based'!V98+'ONS pop proj 2021-based'!V205 -> 59671 | AG100: ='ONS pop proj 2021-based'!AF98+'ONS pop proj 2021-based'!AF205 -> 77453 | AX100: 36892 | AY100: =100*(HAVERM!C139/HAVERM!B139) -> 26.73913 | AZ100: =AVERAGE($AY$7:$AY$374) -> 24.595806 | BB100: =HAVERM!C139 -> 2337 | BC100: =HAVERM!B139-HAVERM!C139 -> 6403 | BE100: 1995 | BF100: =100*((AVERAGE(HAVERQ!B88:B107)/AVERAGE(HAVERQ!B84:B103))-1) -> 2.5364431 | BG100: =$BL$6 -> 2.2155011 | BI100: 0 | BQ100: 1995 | BR100: =100*((AVERAGE(HAVERQ!C88:C107)/AVERAGE(HAVERQ!C84:C103))-1) -> 2.1540194 | BS100: =$BX$6 -> 1.9448021 | BU100: 0
...

Sheet HAVERQ
A1: 19701 !Q | B1: LZVBQ@UK | C1: A4YMQ@UK | D1: MGRZQ@UK | E1: LF2GQ@UK | F1: MGUQQ@UK | G1: YBTUQ@UK | H1: YBTXQ@UK | I1: LF26Q@UK | J1: LFK4Q@UK
A2: .DESC | B2: U.K.: Output per Hour Worked: Whole Economy (SA, 2019=100) | C2: UK: Output per Worker: Whole Economy (SA, 2019=100) | D2: UK: LFS: Employment: Aged 16 and Over (SA, Thous) | E2: UK: LFS: Employment: Aged 16 to 64 (SA, Thous) | F2: UK: LFS: Employment: Aged 16 to 24 (SA, Thous) | G2: UK: LFS: Employment: Aged 25 to 34 (SA, Thous) | H2: UK: LFS: Employment: Aged 35 to 49 (SA, Thous) | I2: UK: LFS: Employment: Aged 50 to 64 (SA, Thous) | J2: UK: LFS: Employment: Aged 65+ (SA, Thous)
A3: .T1 | B3: Q1-1971 | C3: Q3-1959 | D3: Q1-1971 | E3: Q1-1971 | F3: Q2-1992 | G3: Q2-1992 | H3: Q2-1992 | I3: Q2-1992 | J3: Q2-1992
A4: .TN | B4: Q3-2023 | C4: Q3-2023 | D4: Q4-2023 | E4: Q4-2023 | F4: Q4-2023 | G4: Q4-2023 | H4: Q4-2023 | I4: Q4-2023 | J4: Q4-2023
A5: .LSOURCE | B5: Office for National Statistics | C5: Office for National Statistics | D5: Office for National Statistics | E5: Office for National Statistics | F5: Office for National Statistics | G5: Office for National Statistics | H5: Office for National Statistics | I5: Office for National Statistics | J5: Office for National Statistics
A6: .DTLM | B6: Feb-15-2024 07:05 | C6: Feb-15-2024 07:05 | D6: Feb-13-2024 08:01 | E6: Feb-13-2024 08:01 | F6: Feb-13-2024 08:01 | G6: Feb-13-2024 08:01 | H6: Feb-13-2024 08:01 | I6: Feb-13-2024 08:01 | J6: Feb-13-2024 08:01
A7: 19701 | B7: #N/A | C7: 44.3 | D7: #N/A | E7: #N/A | F7: #N/A | G7: #N/A | H7: #N/A | I7: #N/A | J7: #N/A
A8: 19702 | B8: #N/A | C8: 45.4 | D8: #N/A | E8: #N/A | F8: #N/A | G8: #N/A | H8: #N/A | I8: #N/A | J8: #N/A
A9: 19703 | B9: #N/A | C9: 45.8 | D9: #N/A | E9: #N/A | F9: #N/A | G9: #N/A | H9: #N/A | I9: #N/A | J9: #N/A
A10: 19704 | B10: #N/A | C10: 46.6 | D10: #N/A | E10: #N/A | F10: #N/A | G10: #N/A | H10: #N/A | I10: #N/A | J10: #N/A
A11: 19711 | B11: 42.6 | C11: 46.7 | D11: 24613 | E11: 24219 | F11: #N/A | G11: #N/A | H11: #N/A | I11: #N/A | J11: #N/A
A12: 19712 | B12: 43.4 | C12: 47.6 | D12: 24556 | E12: 24168 | F12: #N/A | G12: #N/A | H12: #N/A | I12: #N/A | J12: #N/A
A13: 19713 | B13: 44.2 | C13: 48.6 | D13: 24464 | E13: 24085 | F13: #N/A | G13: #N/A | H13: #N/A | I13: #N/A | J13: #N/A
A14: 19714 | B14: 44.5 | C14: 49 | D14: 24395 | E14: 24017 | F14: #N/A | G14: #N/A | H14: #N/A | I14: #N/A | J14: #N/A
A15: 19721 | B15: 44.2 | C15: 48.8 | D15: 24501 | E15: 24115 | F15: #N/A | G15: #N/A | H15: #N/A | I15: #N/A | J15: #N/A
A16: 19722 | B16: 45 | C16: 49.9 | D16: 24542 | E16: 24155 | F16: #N/A | G16: #N/A | H16: #N/A | I16: #N/A | J16: #N/A
A17: 19723 | B17: 45.1 | C17: 50.2 | D17: 24585 | E17: 24192 | F17: #N/A | G17: #N/A | H17: #N/A | I17: #N/A | J17: #N/A
A18: 19724 | B18: 45.6 | C18: 50.8 | D18: 24689 | E18: 24288 | F18: #N/A | G18: #N/A | H18: #N/A | I18: #N/A | J18: #N/A
A19: 19731 | B19: 47.4 | C19: 52.8 | D19: 24903 | E19: 24488 | F19: #N/A | G19: #N/A | H19: #N/A | I19: #N/A | J19: #N/A
A20: 19732 | B20: 47.4 | C20: 52.8 | D20: 24986 | E20: 24564 | F20: #N/A | G20: #N/A | H20: #N/A | I20: #N/A | J20: #N/A
A21: 19733 | B21: 46.9 | C21: 52.3 | D21: 24972 | E21: 24554 | F21: #N/A | G21: #N/A | H21: #N/A | I21: #N/A | J21: #N/A
A22: 19734 | B22: 46.7 | C22: 52 | D22: 24999 | E22: 24580 | F22: #N/A | G22: #N/A | H22: #N/A | I22: #N/A | J22: #N/A
... A95: 19921 | B95: 69.2 | C95: 71.1 | D95: 25710 | E95: 25243 | F95: #N/A | G95: #N/A | H95: #N/A | I95: #N/A | J95: #N/A
A96: 19922 | B96: 69.2 | C96: 71.4 | D96: 25605 | E96: 25122 | F96: 4439 | G96: 6562 | H96: 9155 | I96: 4966 | J96: 484
A97: 19923 | B97: 70.1 | C97: 72 | D97: 25509 | E97: 25051 | F97: 4349 | G97: 6586 | H97: 9155 | I97: 4961 | J97: 458
A98: 19924 | B98: 71.3 | C98: 73.1 | D98: 25336 | E98: 24905 | F98: 4270 | G98: 6566 | H98: 9151 | I98: 4917 | J98: 431
A99: 19931 | B99: 71.6 | C99: 73.5 | D99: 25282 | E99: 24847 | F99: 4190 | G99: 6592 | H99: 9128 | I99: 4937 | J99: 435
A100: 19932 | B100: 72 | C100: 73.9 | D100: 25293 | E100: 24872 | F100: 4127 | G100: 6648 | H100: 9158 | I100: 4939 | J100: 421
A101: 19933 | B101: 72.7 | C101: 74.6 | D101: 25316 | E101: 24893 | F101: 4088 | G101: 6667 | H101: 9201 | I101: 4937 | J101: 423
A102: 19934 | B102: 73.3 | C102: 75 | D102: 25320 | E102: 24899 | F102: 4041 | G102: 6668 | H102: 9200 | I102: 4989 | J102: 422
A103: 19941 | B103: 73.4 | C103: 75.4 | D103: 25408 | E103: 24997 | F103: 4031 | G103: 6744 | H103: 9221 | I103: 5001 | J103: 411
A104: 19942 | B104: 73.8 | C104: 75.9 | D104: 25451 | E104: 25028 | F104: 3985 | G104: 6738 | H104: 9247 | I104: 5059 | J104: 423
A105: 19943 | B105: 73.8 | C105: 76.2 | D105: 25559 | E105: 25128 | F105: 3957 | G105: 6777 | H105: 9284 | I105: 5110 | J105: 431
A106: 19944 | B106: 73.6 | C106: 76.4 | D106: 25600 | E106: 25149 | F106: 3928 | G106: 6808 | H106: 9294 | I106: 5120 | J106: 450
A107: 19951 | B107: 74 | C107: 76.6 | D107: 25670 | E107: 25220 | F107: 3911 | G107: 6833 | H107: 9334 | I107: 5143 | J107: 450
... A221: 20233 | B221: 103 | C221: 100.9 | D221: 33102 | E221: 31654 | F221: 3641 | G221: 7664 | H221: 10954 | I221: 9394 | J221: 1449
A222: 20234 | B222: =B221*0.991 -> 102.073 | D222: 33174 | E222: 31755 | F222: 3678 | G222: 7529 | H222: 11063 | I222: 9485 | J222: 1419

Sheet HAVERM
A1: 199001 !M | B1: LF2M@UK | C1: LF69@UK | D1: LF2S@UK
A2: .DESC | B2: UK: LFS: Economically Inactive: Aged 16 to 64 (SA, Thous) | C2: UK: LFS: Economically Inactive: Long Term Sick (SA, Thous) | D2: UK: LFS: Economic Inactivity Rate: Aged 16 to 64 (SA, %)
A3: .T1 | B3: Feb-1971 | C3: Apr-1993 | D3: Feb-1971
A4: .TN | B4: Nov-2023 | C4: Nov-2023 | D4: Nov-2023
A5: .LSOURCE | B5: Office for National Statistics | C5: Office for National Statistics | D5: Office for National Statistics
A6: .DTLM | B6: Feb-13-2024 07:26 | C6: Feb-13-2024 08:01 | D6: Feb-13-2024 07:26
A7: 199001 | B7: 7890 | C7: #N/A | D7: 21.7
A8: 199002 | B8: 7897 | C8: #N/A | D8: 21.8
A9: 199003 | B9: 7892 | C9: #N/A | D9: 21.7
A10: 199004 | B10: 7883 | C10: #N/A | D10: 21.7
A11: 199005 | B11: 7877 | C11: #N/A | D11: 21.7
A12: 199006 | B12: 7875 | C12: #N/A | D12: 21.7
A13: 199007 | B13: 7874 | C13: #N/A | D13: 21.7
A14: 199008 | B14: 7889 | C14: #N/A | D14: 21.7
A15: 199009 | B15: 7906 | C15: #N/A | D15: 21.8
A16: 199010 | B16: 7919 | C16: #N/A | D16: 21.8
A17: 199011 | B17: 7934 | C17: #N/A | D17: 21.8
A18: 199012 | B18: 7965 | C18: #N/A | D18: 21.9
... A45: 199303 | B45: 8557 | C45: #N/A | D45: 23.5
A46: 199304 | B46: 8557 | C46: 1813 | D46: 23.5
A47: 199305 | B47: 8565 | C47: 1834 | D47: 23.6
A48: 199306 | B48: 8565 | C48: 1857 | D48: 23.6
A49: 199307 | B49: 8606 | C49: 1889 | D49: 23.7
A50: 199308 | B50: 8583 | C50: 1884 | D50: 23.6
A51: 199309 | B51: 8586 | C51: 1905 | D51: 23.6
A52: 199310 | B52: 8589 | C52: 1938 | D52: 23.6
A53: 199311 | B53: 8585 | C53: 1930 | D53: 23.6
A54: 199312 | B54: 8585 | C54: 1926 | D54: 23.6
A55: 199401 | B55: 8587 | C55: 1918 | D55: 23.6
A56: 199402 | B56: 8580 | C56: 1911 | D56: 23.6
A57: 199403 | B57: 8586 | C57: 1938 | D57: 23.6
... A413: 202311 | B413: 9278 | C413: 2800 | D413: 21.9

Sheet DataA
B1: =GMWA!$CR$2 -> FEB019C.db | C1: =$B$1 -> FEB019C.db | D1: =$B$1 -> FEB019C.db | E1: =$B$1 -> FEB019C.db | F1: =$B$1 -> FEB019C.db | G1: =$B$1 -> FEB019C.db | H1: =$B$1 -> FEB019C.db | I1: =$B$1 -> FEB019C.db | J1: =$B$1 -> FEB019C.db | ... P1: =$B$1 -> FEB019C.db
B2: UK | C2: UK | D2: UK | E2: UK | F2: UK | G2: UK | H2: UK | I2: UK | J2: UK | K2: UK | L2: UK | M2: UK | N2: UK | O2: UK | P2: UK
B3: GDP | C3: UPILO | D3: YHAT | E3: K | F3: ESTAR | G3: AVHR | H3: EDUC | I3: POP15_64 | J3: TREND | K3: ETILO | L3: POP | M3: POPW | N3: PSNBX | O3: GNDBTX | P3: GDP!
B4: GBR | C4: GBR | D4: GBR | E4: GBR | F4: GBR | G4: GBR | H4: GBR | I4: GBR | J4: GBR | K4: GBR | L4: GBR | M4: GBR | N4: GBR | O4: GBR | P4: GBR
B5: L | C5: L | D5: L | E5: L | F5: L | G5: L | H5: L | I5: L | J5: L | K5: L | L5: L | M5: L | N5: L | O5: L | P5: L
A6: =A84+5 -> 2055 | B6: {=_xlfn.CONCAT(INDEX(GMWA!$A$2:$CR$60,MATCH(1,(GMWA!$CQ$2:$CQ$60=B$3)*(GMWA!$CR$2:$CR$60=B$1),0),$A6-1966),"0",(INDEX(GMWA!$A$2:$CR$60,MATCH(1,(GMWA!$CQ$2:$CQ$60=B$3)*(GMWA!$CR$2:$CR$60=B$1),0),$A6-1965)))} -> 202304 | C6: {=_xlfn.CONCAT(INDEX(GMWA!$A$2:$CR$60,MATCH(1,(GMWA!$CQ$2:$CQ$60=C$3)*(GMWA!$CR$2:$CR$60=C$1),0),$A6-1966),"0",(INDEX(GMWA!$A$2:$CR$60,MATCH(1,(GMWA!$CQ$2:$CQ$60=C$3)*(GMWA!$CR$2:$CR$60=C$1),0),$A6-1965)))} -> 202304 | D6: {=_xlfn.CONCAT(INDEX(GMWA!$A$2:$CR$60,MATCH(1,(GMWA!$CQ$2:$CQ$60=D$3)*(GMWA!$CR$2:$CR$60=D$1),0),$A6-1966),"0",(INDEX(GMWA!$A$2:$CR$60,MATCH(1,(GMWA!$CQ$2:$CQ$60=D$3)*(GMWA!$CR$2:$CR$60=D$1),0),$A6-1965)))} -> 202102 | E6: {=_xlfn.CONCAT(INDEX(GMWA!$A$2:$CR$60,MATCH(1,(GMWA!$CQ$2:$CQ$60=E$3)*(GMWA!$CR$2:$CR$60=E$1),0),$A6-1966),"0",(INDEX(GMWA!$A$2:$CR$60,MATCH(1,(GMWA!$CQ$2:$CQ$60=E$3)*(GMWA!$CR$2:$CR$60=E$1),0),$A6-1965)))} -> 202204 | F6: {=_xlfn.CONCAT(INDEX(GMWA!$A$2:$CR$60,MATCH(1,(GMWA!$CQ$2:$CQ$60=F$3)*(GMWA!$CR$2:$CR$60=F$1),0),$A6-1966),"0",(INDEX(GMWA!$A$2:$CR$60,MATCH(1,(GMWA!$CQ$2:$CQ$60=F$3)*(GMWA!$CR$2:$CR$60=F$1),0),$A6-1965)))} -> 202102 | G6: {=_xlfn.CONCAT(INDEX(GMWA!$A$2:$CR$60,MATCH(1,(GMWA!$CQ$2:$CQ$60=G$3)*(GMWA!$CR$2:$CR$60=G$1),0),$A6-1966),"0",(INDEX(GMWA!$A$2:$CR$60,MATCH(1,(GMWA!$CQ$2:$CQ$60=G$3)*(GMWA!$CR$2:$CR$60=G$1),0),$A6-1965)))} -> 202304 | H6: {=_xlfn.CONCAT(INDEX(GMWA!$A$2:$CR$60,MATCH(1,(GMWA!$CQ$2:$CQ$60=H$3)*(GMWA!$CR$2:$CR$60=H$1),0),$A6-1966),"0",(INDEX(GMWA!$A$2:$CR$60,MATCH(1,(GMWA!$CQ$2:$CQ$60=H$3)*(GMWA!$CR$2:$CR$60=H$1),0),$A6-1965)))} -> 201004 | I6: {=_xlfn.CONCAT(INDEX(GMWA!$A$2:$CR$60,MATCH(1,(GMWA!$CQ$2:$CQ$60=I$3)*(GMWA!$CR$2:$CR$60=I$1),0),$A6-1966),"0",(INDEX(GMWA!$A$2:$CR$60,MATCH(1,(GMWA!$CQ$2:$CQ$60=I$3)*(GMWA!$CR$2:$CR$60=I$1),0),$A6-1965)))} -> 202102 | ... P6: {=_xlfn.CONCAT(INDEX(GMWA!$A$2:$CR$60,MATCH(1,(GMWA!$CQ$2:$CQ$60=P$3)*(GMWA!$CR$2:$CR$60=P$1),0),$A6-1966),"0",(INDEX(GMWA!$A$2:$CR$60,MATCH(1,(GMWA!$CQ$2:$CQ$60=P$3)*(GMWA!$CR$2:$CR$60=P$1),0),$A6-1965)))} -> 202304
A7: 1973 | B7: {=INDEX(GMWA!$A$2:$CR$60,MATCH(1,(GMWA!$CQ$2:$CQ$60=B$3)*(GMWA!$CR$2:$CR$60=B$1),0),$A7-1966)} -> 891381 | C7: {=INDEX(GMWA!$A$2:$CR$60,MATCH(1,(GMWA!$CQ$2:$CQ$60=C$3)*(GMWA!$CR$2:$CR$60=C$1),0),$A7-1966)} -> 3.65 | D7: {=INDEX(GMWA!$A$2:$CR$60,MATCH(1,(GMWA!$CQ$2:$CQ$60=D$3)*(GMWA!$CR$2:$CR$60=D$1),0),$A7-1966)} -> 898803.2 | E7: {=INDEX(GMWA!$A$2:$CR$60,MATCH(1,(GMWA!$CQ$2:$CQ$60=E$3)*(GMWA!$CR$2:$CR$60=E$1),0),$A7-1966)} -> 983736.3 | F7: {=INDEX(GMWA!$A$2:$CR$60,MATCH(1,(GMWA!$CQ$2:$CQ$60=F$3)*(GMWA!$CR$2:$CR$60=F$1),0),$A7-1966)} -> 24874.8 | G7: {=INDEX(GMWA!$A$2:$CR$60,MATCH(1,(GMWA!$CQ$2:$CQ$60=G$3)*(GMWA!$CR$2:$CR$60=G$1),0),$A7-1966)} -> 0.001 | H7: {=INDEX(GMWA!$A$2:$CR$60,MATCH(1,(GMWA!$CQ$2:$CQ$60=H$3)*(GMWA!$CR$2:$CR$60=H$1),0),$A7-1966)} -> 286021.4 | I7: {=INDEX(GMWA!$A$2:$CR$60,MATCH(1,(GMWA!$CQ$2:$CQ$60=I$3)*(GMWA!$CR$2:$CR$60=I$1),0),$A7-1966)} -> 35322.81 | ... P7: {=INDEX(GMWA!$A$2:$CR$60,MATCH(1,(GMWA!$CQ$2:$CQ$60=P$3)*(GMWA!$CR$2:$CR$60=P$1),0),$A7-1966)} -> 81793
A8: =+A7+1 -> 1974 | B8: {=INDEX(GMWA!$A$2:$CR$60,MATCH(1,(GMWA!$CQ$2:$CQ$60=B$3)*(GMWA!$CR$2:$CR$60=B$1),0),$A8-1966)} -> 869155 | C8: {=INDEX(GMWA!$A$2:$CR$60,MATCH(1,(GMWA!$CQ$2:$CQ$60=C$3)*(GMWA!$CR$2:$CR$60=C$1),0),$A8-1966)} -> 3.65 | D8: {=INDEX(GMWA!$A$2:$CR$60,MATCH(1,(GMWA!$CQ$2:$CQ$60=D$3)*(GMWA!$CR$2:$CR$60=D$1),0),$A8-1966)} -> 909717.9 | E8: {=INDEX(GMWA!$A$2:$CR$60,MATCH(1,(GMWA!$CQ$2:$CQ$60=E$3)*(GMWA!$CR$2:$CR$60=E$1),0),$A8-1966)} -> 1010781 | F8: {=INDEX(GMWA!$A$2:$CR$60,MATCH(1,(GMWA!$CQ$2:$CQ$60=F$3)*(GMWA!$CR$2:$CR$60=F$1),0),$A8-1966)} -> 24938.64 | G8: {=INDEX(GMWA!$A$2:$CR$60,MATCH(1,(GMWA!$CQ$2:$CQ$60=G$3)*(GMWA!$CR$2:$CR$60=G$1),0),$A8-1966)} -> 0.001 | H8: {=INDEX(GMWA!$A$2:$CR$60,MATCH(1,(GMWA!$CQ$2:$CQ$60=H$3)*(GMWA!$CR$2:$CR$60=H$1),0),$A8-1966)} -> 288869 | I8: {=INDEX(GMWA!$A$2:$CR$60,MATCH(1,(GMWA!$CQ$2:$CQ$60=I$3)*(GMWA!$CR$2:$CR$60=I$1),0),$A8-1966)} -> 35332.71 | ... P8: {=INDEX(GMWA!$A$2:$CR$60,MATCH(1,(GMWA!$CQ$2:$CQ$60=P$3)*(GMWA!$CR$2:$CR$60=P$1),0),$A8-1966)} -> 92673
A9: =+A8+1 -> 1975 | B9: {=INDEX(GMWA!$A$2:$CR$60,MATCH(1,(GMWA!$CQ$2:$CQ$60=B$3)*(GMWA!$CR$2:$CR$60=B$1),0),$A9-1966)} -> 856049 | C9: {=INDEX(GMWA!$A$2:$CR$60,MATCH(1,(GMWA!$CQ$2:$CQ$60=C$3)*(GMWA!$CR$2:$CR$60=C$1),0),$A9-1966)} -> 4.5 | D9: {=INDEX(GMWA!$A$2:$CR$60,MATCH(1,(GMWA!$CQ$2:$CQ$60=D$3)*(GMWA!$CR$2:$CR$60=D$1),0),$A9-1966)} -> 917020.3 | E9: {=INDEX(GMWA!$A$2:$CR$60,MATCH(1,(GMWA!$CQ$2:$CQ$60=E$3)*(GMWA!$CR$2:$CR$60=E$1),0),$A9-1966)} -> 1037121 | F9: {=INDEX(GMWA!$A$2:$CR$60,MATCH(1,(GMWA!$CQ$2:$CQ$60=F$3)*(GMWA!$CR$2:$CR$60=F$1),0),$A9-1966)} -> 24932.05 | G9: {=INDEX(GMWA!$A$2:$CR$60,MATCH(1,(GMWA!$CQ$2:$CQ$60=G$3)*(GMWA!$CR$2:$CR$60=G$1),0),$A9-1966)} -> 0.001 | H9: {=INDEX(GMWA!$A$2:$CR$60,MATCH(1,(GMWA!$CQ$2:$CQ$60=H$3)*(GMWA!$CR$2:$CR$60=H$1),0),$A9-1966)} -> 291532.5 | I9: {=INDEX(GMWA!$A$2:$CR$60,MATCH(1,(GMWA!$CQ$2:$CQ$60=I$3)*(GMWA!$CR$2:$CR$60=I$1),0),$A9-1966)} -> 35327.33 | ... P9: {=INDEX(GMWA!$A$2:$CR$60,MATCH(1,(GMWA!$CQ$2:$CQ$60=P$3)*(GMWA!$CR$2:$CR$60=P$1),0),$A9-1966)} -> 115093
A10: =+A9+1 -> 1976 | B10: {=INDEX(GMWA!$A$2:$CR$60,MATCH(1,(GMWA!$CQ$2:$CQ$60=B$3)*(GMWA!$CR$2:$CR$60=B$1),0),$A10-1966)} -> 881878 | C10: {=INDEX(GMWA!$A$2:$CR$60,MATCH(1,(GMWA!$CQ$2:$CQ$60=C$3)*(GMWA!$CR$2:$CR$60=C$1),0),$A10-1966)} -> 5.425 | D10: {=INDEX(GMWA!$A$2:$CR$60,MATCH(1,(GMWA!$CQ$2:$CQ$60=D$3)*(GMWA!$CR$2:$CR$60=D$1),0),$A10-1966)} -> 921384.1 | E10: {=INDEX(GMWA!$A$2:$CR$60,MATCH(1,(GMWA!$CQ$2:$CQ$60=E$3)*(GMWA!$CR$2:$CR$60=E$1),0),$A10-1966)} -> 1061489 | F10: {=INDEX(GMWA!$A$2:$CR$60,MATCH(1,(GMWA!$CQ$2:$CQ$60=F$3)*(GMWA!$CR$2:$CR$60=F$1),0),$A10-1966)} -> 24850.21 | G10: {=INDEX(GMWA!$A$2:$CR$60,MATCH(1,(GMWA!$CQ$2:$CQ$60=G$3)*(GMWA!$CR$2:$CR$60=G$1),0),$A10-1966)} -> 0.001 | H10: {=INDEX(GMWA!$A$2:$CR$60,MATCH(1,(GMWA!$CQ$2:$CQ$60=H$3)*(GMWA!$CR$2:$CR$60=H$1),0),$A10-1966)} -> 293842.9 | I10: {=INDEX(GMWA!$A$2:$CR$60,MATCH(1,(GMWA!$CQ$2:$CQ$60=I$3)*(GMWA!$CR$2:$CR$60=I$1),0),$A10-1966)} -> 35352.08 | ... P10: {=INDEX(GMWA!$A$2:$CR$60,MATCH(1,(GMWA!$CQ$2:$CQ$60=P$3)*(GMWA!$CR$2:$CR$60=P$1),0),$A10-1966)} -> 136999
A11: =+A10+1 -> 1977 | B11: {=INDEX(GMWA!$A$2:$CR$60,MATCH(1,(GMWA!$CQ$2:$CQ$60=B$3)*(GMWA!$CR$2:$CR$60=B$1),0),$A11-1966)} -> 903587 | C11: {=INDEX(GMWA!$A$2:$CR$60,MATCH(1,(GMWA!$CQ$2:$CQ$60=C$3)*(GMWA!$CR$2:$CR$60=C$1),0),$A11-1966)} -> 5.6 | D11: {=INDEX(GMWA!$A$2:$CR$60,MATCH(1,(GMWA!$CQ$2:$CQ$60=D$3)*(GMWA!$CR$2:$CR$60=D$1),0),$A11-1966)} -> 924484.8 | E11: {=INDEX(GMWA!$A$2:$CR$60,MATCH(1,(GMWA!$CQ$2:$CQ$60=E$3)*(GMWA!$CR$2:$CR$60=E$1),0),$A11-1966)} -> 1083744 | F11: {=INDEX(GMWA!$A$2:$CR$60,MATCH(1,(GMWA!$CQ$2:$CQ$60=F$3)*(GMWA!$CR$2:$CR$60=F$1),0),$A11-1966)} -> 24800.74 | G11: {=INDEX(GMWA!$A$2:$CR$60,MATCH(1,(GMWA!$CQ$2:$CQ$60=G$3)*(GMWA!$CR$2:$CR$60=G$1),0),$A11-1966)} -> 0.001 | H11: {=INDEX(GMWA!$A$2:$CR$60,MATCH(1,(GMWA!$CQ$2:$CQ$60=H$3)*(GMWA!$CR$2:$CR$60=H$1),0),$A11-1966)} -> 295875.2 | I11: {=INDEX(GMWA!$A$2:$CR$60,MATCH(1,(GMWA!$CQ$2:$CQ$60=I$3)*(GMWA!$CR$2:$CR$60=I$1),0),$A11-1966)} -> 35501.05 | ... P11: {=INDEX(GMWA!$A$2:$CR$60,MATCH(1,(GMWA!$CQ$2:$CQ$60=P$3)*(GMWA!$CR$2:$CR$60=P$1),0),$A11-1966)} -> 159786
A12: =+A11+1 -> 1978 | B12: {=INDEX(GMWA!$A$2:$CR$60,MATCH(1,(GMWA!$CQ$2:$CQ$60=B$3)*(GMWA!$CR$2:$CR$60=B$1),0),$A12-1966)} -> 941461 | C12: {=INDEX(GMWA!$A$2:$CR$60,MATCH(1,(GMWA!$CQ$2:$CQ$60=C$3)*(GMWA!$CR$2:$CR$60=C$1),0),$A12-1966)} -> 5.525 | D12: {=INDEX(GMWA!$A$2:$CR$60,MATCH(1,(GMWA!$CQ$2:$CQ$60=D$3)*(GMWA!$CR$2:$CR$60=D$1),0),$A12-1966)} -> 932047.9 | E12: {=INDEX(GMWA!$A$2:$CR$60,MATCH(1,(GMWA!$CQ$2:$CQ$60=E$3)*(GMWA!$CR$2:$CR$60=E$1),0),$A12-1966)} -> 1111352 | F12: {=INDEX(GMWA!$A$2:$CR$60,MATCH(1,(GMWA!$CQ$2:$CQ$60=F$3)*(GMWA!$CR$2:$CR$60=F$1),0),$A12-1966)} -> 24703.73 | G12: {=INDEX(GMWA!$A$2:$CR$60,MATCH(1,(GMWA!$CQ$2:$CQ$60=G$3)*(GMWA!$CR$2:$CR$60=G$1),0),$A12-1966)} -> 0.001 | H12: {=INDEX(GMWA!$A$2:$CR$60,MATCH(1,(GMWA!$CQ$2:$CQ$60=H$3)*(GMWA!$CR$2:$CR$60=H$1),0),$A12-1966)} -> 297883.1 | I12: {=INDEX(GMWA!$A$2:$CR$60,MATCH(1,(GMWA!$CQ$2:$CQ$60=I$3)*(GMWA!$CR$2:$CR$60=I$1),0),$A12-1966)} -> 35670.84 | ... P12: {=INDEX(GMWA!$A$2:$CR$60,MATCH(1,(GMWA!$CQ$2:$CQ$60=P$3)*(GMWA!$CR$2:$CR$60=P$1),0),$A12-1966)} -> 186158
A13: =+A12+1 -> 1979 | B13: {=INDEX(GMWA!$A$2:$CR$60,MATCH(1,(GMWA!$CQ$2:$CQ$60=B$3)*(GMWA!$CR$2:$CR$60=B$1),0),$A13-1966)} -> 976566 | C13: {=INDEX(GMWA!$A$2:$CR$60,MATCH(1,(GMWA!$CQ$2:$CQ$60=C$3)*(GMWA!$CR$2:$CR$60=C$1),0),$A13-1966)} -> 5.4 | D13: {=INDEX(GMWA!$A$2:$CR$60,MATCH(1,(GMWA!$CQ$2:$CQ$60=D$3)*(GMWA!$CR$2:$CR$60=D$1),0),$A13-1966)} -> 951947.9 | E13: {=INDEX(GMWA!$A$2:$CR$60,MATCH(1,(GMWA!$CQ$2:$CQ$60=E$3)*(GMWA!$CR$2:$CR$60=E$1),0),$A13-1966)} -> 1132762 | F13: {=INDEX(GMWA!$A$2:$CR$60,MATCH(1,(GMWA!$CQ$2:$CQ$60=F$3)*(GMWA!$CR$2:$CR$60=F$1),0),$A13-1966)} -> 24709.44 | G13: {=INDEX(GMWA!$A$2:$CR$60,MATCH(1,(GMWA!$CQ$2:$CQ$60=G$3)*(GMWA!$CR$2:$CR$60=G$1),0),$A13-1966)} -> 0.001 | H13: {=INDEX(GMWA!$A$2:$CR$60,MATCH(1,(GMWA!$CQ$2:$CQ$60=H$3)*(GMWA!$CR$2:$CR$60=H$1),0),$A13-1966)} -> 300120.3 | I13: {=INDEX(GMWA!$A$2:$CR$60,MATCH(1,(GMWA!$CQ$2:$CQ$60=I$3)*(GMWA!$CR$2:$CR$60=I$1),0),$A13-1966)} -> 35882.96 | ... P13: {=INDEX(GMWA!$A$2:$CR$60,MATCH(1,(GMWA!$CQ$2:$CQ$60=P$3)*(GMWA!$CR$2:$CR$60=P$1),0),$A13-1966)} -> 220981
A14: =+A13+1 -> 1980 | B14: {=INDEX(GMWA!$A$2:$CR$60,MATCH(1,(GMWA!$CQ$2:$CQ$60=B$3)*(GMWA!$CR$2:$CR$60=B$1),0),$A14-1966)} -> 956533 | C14: {=INDEX(GMWA!$A$2:$CR$60,MATCH(1,(GMWA!$CQ$2:$CQ$60=C$3)*(GMWA!$CR$2:$CR$60=C$1),0),$A14-1966)} -> 6.8 | D14: {=INDEX(GMWA!$A$2:$CR$60,MATCH(1,(GMWA!$CQ$2:$CQ$60=D$3)*(GMWA!$CR$2:$CR$60=D$1),0),$A14-1966)} -> 975762 | E14: {=INDEX(GMWA!$A$2:$CR$60,MATCH(1,(GMWA!$CQ$2:$CQ$60=E$3)*(GMWA!$CR$2:$CR$60=E$1),0),$A14-1966)} -> 1149523 | F14: {=INDEX(GMWA!$A$2:$CR$60,MATCH(1,(GMWA!$CQ$2:$CQ$60=F$3)*(GMWA!$CR$2:$CR$60=F$1),0),$A14-1966)} -> 24765.53 | G14: {=INDEX(GMWA!$A$2:$CR$60,MATCH(1,(GMWA!$CQ$2:$CQ$60=G$3)*(GMWA!$CR$2:$CR$60=G$1),0),$A14-1966)} -> 0.001 | H14: {=INDEX(GMWA!$A$2:$CR$60,MATCH(1,(GMWA!$CQ$2:$CQ$60=H$3)*(GMWA!$CR$2:$CR$60=H$1),0),$A14-1966)} -> 306731.3 | I14: {=INDEX(GMWA!$A$2:$CR$60,MATCH(1,(GMWA!$CQ$2:$CQ$60=I$3)*(GMWA!$CR$2:$CR$60=I$1),0),$A14-1966)} -> 36102.32 | ... P14: {=INDEX(GMWA!$A$2:$CR$60,MATCH(1,(GMWA!$CQ$2:$CQ$60=P$3)*(GMWA!$CR$2:$CR$60=P$1),0),$A14-1966)} -> 259970
A15: =+A14+1 -> 1981 | B15: {=INDEX(GMWA!$A$2:$CR$60,MATCH(1,(GMWA!$CQ$2:$CQ$60=B$3)*(GMWA!$CR$2:$CR$60=B$1),0),$A15-1966)} -> 949961 | C15: {=INDEX(GMWA!$A$2:$CR$60,MATCH(1,(GMWA!$CQ$2:$CQ$60=C$3)*(GMWA!$CR$2:$CR$60=C$1),0),$A15-1966)} -> 9.65 | D15: {=INDEX(GMWA!$A$2:$CR$60,MATCH(1,(GMWA!$CQ$2:$CQ$60=D$3)*(GMWA!$CR$2:$CR$60=D$1),0),$A15-1966)} -> 990112 | E15: {=INDEX(GMWA!$A$2:$CR$60,MATCH(1,(GMWA!$CQ$2:$CQ$60=E$3)*(GMWA!$CR$2:$CR$60=E$1),0),$A15-1966)} -> 1157411 | F15: {=INDEX(GMWA!$A$2:$CR$60,MATCH(1,(GMWA!$CQ$2:$CQ$60=F$3)*(GMWA!$CR$2:$CR$60=F$1),0),$A15-1966)} -> 24659.65 | G15: {=INDEX(GMWA!$A$2:$CR$60,MATCH(1,(GMWA!$CQ$2:$CQ$60=G$3)*(GMWA!$CR$2:$CR$60=G$1),0),$A15-1966)} -> 0.001 | H15: {=INDEX(GMWA!$A$2:$CR$60,MATCH(1,(GMWA!$CQ$2:$CQ$60=H$3)*(GMWA!$CR$2:$CR$60=H$1),0),$A15-1966)} -> 309382.7 | I15: {=INDEX(GMWA!$A$2:$CR$60,MATCH(1,(GMWA!$CQ$2:$CQ$60=I$3)*(GMWA!$CR$2:$CR$60=I$1),0),$A15-1966)} -> 36300.18 | ... P15: {=INDEX(GMWA!$A$2:$CR$60,MATCH(1,(GMWA!$CQ$2:$CQ$60=P$3)*(GMWA!$CR$2:$CR$60=P$1),0),$A15-1966)} -> 290180
A16: =+A15+1 -> 1982 | B16: {=INDEX(GMWA!$A$2:$CR$60,MATCH(1,(GMWA!$CQ$2:$CQ$60=B$3)*(GMWA!$CR$2:$CR$60=B$1),0),$A16-1966)} -> 968629 | C16: {=INDEX(GMWA!$A$2:$CR$60,MATCH(1,(GMWA!$CQ$2:$CQ$60=C$3)*(GMWA!$CR$2:$CR$60=C$1),0),$A16-1966)} -> 10.725 | D16: {=INDEX(GMWA!$A$2:$CR$60,MATCH(1,(GMWA!$CQ$2:$CQ$60=D$3)*(GMWA!$CR$2:$CR$60=D$1),0),$A16-1966)} -> 996004.9 | E16: {=INDEX(GMWA!$A$2:$CR$60,MATCH(1,(GMWA!$CQ$2:$CQ$60=E$3)*(GMWA!$CR$2:$CR$60=E$1),0),$A16-1966)} -> 1167835 | F16: {=INDEX(GMWA!$A$2:$CR$60,MATCH(1,(GMWA!$CQ$2:$CQ$60=F$3)*(GMWA!$CR$2:$CR$60=F$1),0),$A16-1966)} -> 24297.71 | G16: {=INDEX(GMWA!$A$2:$CR$60,MATCH(1,(GMWA!$CQ$2:$CQ$60=G$3)*(GMWA!$CR$2:$CR$60=G$1),0),$A16-1966)} -> 0.001 | H16: {=INDEX(GMWA!$A$2:$CR$60,MATCH(1,(GMWA!$CQ$2:$CQ$60=H$3)*(GMWA!$CR$2:$CR$60=H$1),0),$A16-1966)} -> 311708.9 | I16: {=INDEX(GMWA!$A$2:$CR$60,MATCH(1,(GMWA!$CQ$2:$CQ$60=I$3)*(GMWA!$CR$2:$CR$60=I$1),0),$A16-1966)} -> 36500.68 | ... P16: {=INDEX(GMWA!$A$2:$CR$60,MATCH(1,(GMWA!$CQ$2:$CQ$60=P$3)*(GMWA!$CR$2:$CR$60=P$1),0),$A16-1966)} -> 319558
A17: =+A16+1 -> 1983 | B17: {=INDEX(GMWA!$A$2:$CR$60,MATCH(1,(GMWA!$CQ$2:$CQ$60=B$3)*(GMWA!$CR$2:$CR$60=B$1),0),$A17-1966)} -> 1008981 | C17: {=INDEX(GMWA!$A$2:$CR$60,MATCH(1,(GMWA!$CQ$2:$CQ$60=C$3)*(GMWA!$CR$2:$CR$60=C$1),0),$A17-1966)} -> 11.475 | D17: {=INDEX(GMWA!$A$2:$CR$60,MATCH(1,(GMWA!$CQ$2:$CQ$60=D$3)*(GMWA!$CR$2:$CR$60=D$1),0),$A17-1966)} -> 1012416 | E17: {=INDEX(GMWA!$A$2:$CR$60,MATCH(1,(GMWA!$CQ$2:$CQ$60=E$3)*(GMWA!$CR$2:$CR$60=E$1),0),$A17-1966)} -> 1180230 | F17: {=INDEX(GMWA!$A$2:$CR$60,MATCH(1,(GMWA!$CQ$2:$CQ$60=F$3)*(GMWA!$CR$2:$CR$60=F$1),0),$A17-1966)} -> 24304.68 | G17: {=INDEX(GMWA!$A$2:$CR$60,MATCH(1,(GMWA!$CQ$2:$CQ$60=G$3)*(GMWA!$CR$2:$CR$60=G$1),0),$A17-1966)} -> 0.001 | H17: {=INDEX(GMWA!$A$2:$CR$60,MATCH(1,(GMWA!$CQ$2:$CQ$60=H$3)*(GMWA!$CR$2:$CR$60=H$1),0),$A17-1966)} -> 314668.8 | I17: {=INDEX(GMWA!$A$2:$CR$60,MATCH(1,(GMWA!$CQ$2:$CQ$60=I$3)*(GMWA!$CR$2:$CR$60=I$1),0),$A17-1966)} -> 36776.19 | ... P17: {=INDEX(GMWA!$A$2:$CR$60,MATCH(1,(GMWA!$CQ$2:$CQ$60=P$3)*(GMWA!$CR$2:$CR$60=P$1),0),$A17-1966)} -> 351347
A18: =+A17+1 -> 1984 | B18: {=INDEX(GMWA!$A$2:$CR$60,MATCH(1,(GMWA!$CQ$2:$CQ$60=B$3)*(GMWA!$CR$2:$CR$60=B$1),0),$A18-1966)} -> 1031385 | C18: {=INDEX(GMWA!$A$2:$CR$60,MATCH(1,(GMWA!$CQ$2:$CQ$60=C$3)*(GMWA!$CR$2:$CR$60=C$1),0),$A18-1966)} -> 11.75 | D18: {=INDEX(GMWA!$A$2:$CR$60,MATCH(1,(GMWA!$CQ$2:$CQ$60=D$3)*(GMWA!$CR$2:$CR$60=D$1),0),$A18-1966)} -> 1047849 | E18: {=INDEX(GMWA!$A$2:$CR$60,MATCH(1,(GMWA!$CQ$2:$CQ$60=E$3)*(GMWA!$CR$2:$CR$60=E$1),0),$A18-1966)} -> 1202767 | F18: {=INDEX(GMWA!$A$2:$CR$60,MATCH(1,(GMWA!$CQ$2:$CQ$60=F$3)*(GMWA!$CR$2:$CR$60=F$1),0),$A18-1966)} -> 24910.8 | G18: {=INDEX(GMWA!$A$2:$CR$60,MATCH(1,(GMWA!$CQ$2:$CQ$60=G$3)*(GMWA!$CR$2:$CR$60=G$1),0),$A18-1966)} -> 0.001 | H18: {=INDEX(GMWA!$A$2:$CR$60,MATCH(1,(GMWA!$CQ$2:$CQ$60=H$3)*(GMWA!$CR$2:$CR$60=H$1),0),$A18-1966)} -> 318382.6 | I18: {=INDEX(GMWA!$A$2:$CR$60,MATCH(1,(GMWA!$CQ$2:$CQ$60=I$3)*(GMWA!$CR$2:$CR$60=I$1),0),$A18-1966)} -> 37029.13 | ... P18: {=INDEX(GMWA!$A$2:$CR$60,MATCH(1,(GMWA!$CQ$2:$CQ$60=P$3)*(GMWA!$CR$2:$CR$60=P$1),0),$A18-1966)} -> 377920
A19: =+A18+1 -> 1985 | B19: {=INDEX(GMWA!$A$2:$CR$60,MATCH(1,(GMWA!$CQ$2:$CQ$60=B$3)*(GMWA!$CR$2:$CR$60=B$1),0),$A19-1966)} -> 1073547 | C19: {=INDEX(GMWA!$A$2:$CR$60,MATCH(1,(GMWA!$CQ$2:$CQ$60=C$3)*(GMWA!$CR$2:$CR$60=C$1),0),$A19-1966)} -> 11.375 | D19: {=INDEX(GMWA!$A$2:$CR$60,MATCH(1,(GMWA!$CQ$2:$CQ$60=D$3)*(GMWA!$CR$2:$CR$60=D$1),0),$A19-1966)} -> 1076968 | E19: {=INDEX(GMWA!$A$2:$CR$60,MATCH(1,(GMWA!$CQ$2:$CQ$60=E$3)*(GMWA!$CR$2:$CR$60=E$1),0),$A19-1966)} -> 1226994 | F19: {=INDEX(GMWA!$A$2:$CR$60,MATCH(1,(GMWA!$CQ$2:$CQ$60=F$3)*(GMWA!$CR$2:$CR$60=F$1),0),$A19-1966)} -> 25107.87 | G19: {=INDEX(GMWA!$A$2:$CR$60,MATCH(1,(GMWA!$CQ$2:$CQ$60=G$3)*(GMWA!$CR$2:$CR$60=G$1),0),$A19-1966)} -> 0.001 | H19: {=INDEX(GMWA!$A$2:$CR$60,MATCH(1,(GMWA!$CQ$2:$CQ$60=H$3)*(GMWA!$CR$2:$CR$60=H$1),0),$A19-1966)} -> 322872.1 | I19: {=INDEX(GMWA!$A$2:$CR$60,MATCH(1,(GMWA!$CQ$2:$CQ$60=I$3)*(GMWA!$CR$2:$CR$60=I$1),0),$A19-1966)} -> 37116.96 | ... P19: {=INDEX(GMWA!$A$2:$CR$60,MATCH(1,(GMWA!$CQ$2:$CQ$60=P$3)*(GMWA!$CR$2:$CR$60=P$1),0),$A19-1966)} -> 414630
... A84: =+A83+1 -> 2050 | B84: {=INDEX(GMWA!$A$2:$CR$60,MATCH(1,(GMWA!$CQ$2:$CQ$60=B$3)*(GMWA!$CR$2:$CR$60=B$1),0),$A84-1966)} -> 3404846 | C84: {=INDEX(GMWA!$A$2:$CR$60,MATCH(1,(GMWA!$CQ$2:$CQ$60=C$3)*(GMWA!$CR$2:$CR$60=C$1),0),$A84-1966)} -> 3.750001 | D84: {=INDEX(GMWA!$A$2:$CR$60,MATCH(1,(GMWA!$CQ$2:$CQ$60=D$3)*(GMWA!$CR$2:$CR$60=D$1),0),$A84-1966)} -> 3404844 | E84: {=INDEX(GMWA!$A$2:$CR$60,MATCH(1,(GMWA!$CQ$2:$CQ$60=E$3)*(GMWA!$CR$2:$CR$60=E$1),0),$A84-1966)} -> 4679501 | F84: {=INDEX(GMWA!$A$2:$CR$60,MATCH(1,(GMWA!$CQ$2:$CQ$60=F$3)*(GMWA!$CR$2:$CR$60=F$1),0),$A84-1966)} -> 38637.94 | G84: {=INDEX(GMWA!$A$2:$CR$60,MATCH(1,(GMWA!$CQ$2:$CQ$60=G$3)*(GMWA!$CR$2:$CR$60=G$1),0),$A84-1966)} -> 31.94779 | H84: {=INDEX(GMWA!$A$2:$CR$60,MATCH(1,(GMWA!$CQ$2:$CQ$60=H$3)*(GMWA!$CR$2:$CR$60=H$1),0),$A84-1966)} -> 706899.9 | I84: {=INDEX(GMWA!$A$2:$CR$60,MATCH(1,(GMWA!$CQ$2:$CQ$60=I$3)*(GMWA!$CR$2:$CR$60=I$1),0),$A84-1966)} -> 46643.86 | ... P84: {=INDEX(GMWA!$A$2:$CR$60,MATCH(1,(GMWA!$CQ$2:$CQ$60=P$3)*(GMWA!$CR$2:$CR$60=P$1),0),$A84-1966)} -> 7173901

Sheet GMWA
A1: Location | B1: Indicator | C1: Scenario | D1: Units | E1: Scale | F1: Measurement | G1: 1973 | H1: 1974 | I1: 1975 | J1: 1976 | K1: 1977 | L1: 1978 | M1: 1979 | N1: 1980 | O1: 1981 | P1: 1982 | Q1: 1983 | R1: 1984 | S1: 1985 | T1: 1986 | U1: 1987 | V1: 1988 | W1: 1989 | X1: 1990 | Y1: 1991 | Z1: 1992 | AA1: 1993 | AB1: 1994 | AC1: 1995 | AD1: 1996 | AE1: 1997 | AF1: 1998 | AG1: 1999 | AH1: 2000 | AI1: 2001 | AJ1: 2002 | AK1: 2003 | AL1: 2004 | AM1: 2005 | AN1: 2006 | AO1: 2007 | AP1: 2008 | AQ1: 2009 | AR1: 2010 | AS1: 2011 | AT1: 2012 | AU1: 2013 | AV1: 2014 | AW1: 2015 | AX1: 2016 | AY1: 2017 | AZ1: 2018 | BA1: 2019 | BB1: 2020 | BC1: 2021 | BD1: 2022 | BE1: 2023 | BF1: 2024 | BG1: 2025 | BH1: 2026 | BI1: 2027 | BJ1: 2028 | BK1: 2029 | BL1: 2030 | BM1: 2031 | BN1: 2032 | BO1: 2033 | BP1: 2034 | BQ1: 2035 | BR1: 2036 | BS1: 2037 | BT1: 2038 | BU1: 2039 | BV1: 2040 | BW1: 2041 | BX1: 2042 | BY1: 2043 | BZ1: 2044 | CA1: 2045 | CB1: 2046 | CC1: 2047 | CD1: 2048 | CE1: 2049 | CF1: 2050 | CG1: Source | CH1: Seasonally adjusted | CI1: Base year price | CJ1: Base year index | CK1: Historical end year | CL1: Historical end quarter | CM1: Date of last update | CN1: Source details | CO1: Additional source details | CP1: Location code | CQ1: Indicator code | CR1: Databank code
A2: United Kingdom | B2: GDP, real, LCU | C2: FEB019C | D2: Pound | E2: Millions | F2: Level | G2: 891381 | H2: 869155 | I2: 856049 | J2: 881878 | K2: 903587 | L2: 941461 | M2: 976566 | N2: 956533 | O2: 949961 | P2: 968629 | Q2: 1008981 | R2: 1031385 | S2: 1073547 | T2: 1106912 | U2: 1166905 | V2: 1229650 | W2: 1259191 | X2: 1266248 | Y2: 1248461 | Z2: 1251525 | AA2: 1279802 | AB2: 1323443 | AC2: 1355023 | AD2: 1390010 | AE2: 1458467 | AF2: 1508263 | AG2: 1554509 | AH2: 1621644 | AI2: 1663462 | AJ2: 1693271 | AK2: 1746551 | AL2: 1788931 | AM2: 1837927 | AN2: 1881785 | AO2: 1931094 | AP2: 1926735 | AQ2: 1837817 | AR2: 1878960 | AS2: 1900476 | AT2: 1929229 | AU2: 1963807 | AV2: 2026566 | AW2: 2071561 | AX2: 2111357 | AY2: 2167415 | AZ2: 2197841 | BA2: 2233921 | BB2: 2002489 | BC2: 2176203 | BD2: 2270764 | BE2: 2274050 | BF2: 2282737 | BG2: 2324174 | BH2: 2370812 | BI2: 2411854 | BJ2: 2451771 | BK2: 2490241 | BL2: 2528309 | BM2: 2566959 | BN2: 2605939 | BO2: 2643901 | BP2: 2681782 | BQ2: 2720207 | BR2: 2760292 | BS2: 2801574 | BT2: 2844334 | BU2: 2888393 | BV2: 2933353 | BW2: 2978448 | BX2: 3023788 | BY2: 3069664 | BZ2: 3116044 | CA2: 3162919 | CB2: 3210290 | CC2: 3258164 | CD2: 3306548 | CE2: 3355444 | CF2: 3404846 | CG2: Office for National Statistics\Haver Analytics | CH2: True | CI2: chained 2019 | CJ2: NA | CK2: 2023 | CL2: 4 | CM2: NA | CN2: ABMIQ@UK | CO2: U.K.: Real Gross Domestic Product (SA, Mil.Chn.2019.GBP) | CP2: GBR | CQ2: GDP | CR2: FEB019C.db
A3: United Kingdom | B3: Unemployment rate, ILO definition | C3: FEB019C | D3: % | E3: NA | F3: Level | G3: 3.65 | H3: 3.65 | I3: 4.5 | J3: 5.425 | K3: 5.6 | L3: 5.525 | M3: 5.4 | N3: 6.8 | O3: 9.65 | P3: 10.725 | Q3: 11.475 | R3: 11.75 | S3: 11.375 | T3: 11.325 | U3: 10.425 | V3: 8.575 | W3: 7.225 | X3: 7.1 | Y3: 8.85 | Z3: 9.95 | AA3: 10.375 | AB3: 9.5 | AC3: 8.625 | AD3: 8.1 | AE3: 6.95 | AF3: 6.25 | AG3: 5.975 | AH3: 5.45 | AI3: 5.1 | AJ3: 5.2 | AK3: 5 | AL3: 4.75 | AM3: 4.825 | AN3: 5.425 | AO3: 5.35 | AP3: 5.725 | AQ3: 7.625 | AR3: 7.9 | AS3: 8.1 | AT3: 7.975 | AU3: 7.625 | AV3: 6.2 | AW3: 5.425 | AX3: 4.925 | AY3: 4.45 | AZ3: 4.175 | BA3: 3.9 | BB3: 4.625 | BC3: 4.625 | BD3: 3.875 | BE3: 4 | BF3: 4.045302 | BG3: 3.940181 | BH3: 3.753717 | BI3: 3.750103 | BJ3: 3.750109 | BK3: 3.750107 | BL3: 3.750116 | BM3: 3.75011 | BN3: 3.750106 | BO3: 3.750114 | BP3: 3.750075 | BQ3: 3.750005 | BR3: 3.750008 | BS3: 3.749997 | BT3: 3.749995 | BU3: 3.749998 | BV3: 3.749999 | BW3: 3.750006 | BX3: 3.750009 | BY3: 3.75 | BZ3: 3.750012 | CA3: 3.750002 | CB3: 3.750004 | CC3: 3.750008 | CD3: 3.749995 | CE3: 3.750007 | CF3: 3.750001 | CG3: Office for National Statistics\Haver Analytics | CH3: True | CI3: NA | CJ3: NA | CK3: 2023 | CL3: 4 | CM3: NA | CN3: MGSXQ@UK | CO3: UK: LFS: Unemployment Rate: Aged 16 and Over (SA, %) | CP3: GBR | CQ3: UPILO | CR3: FEB019C.db
A4: United Kingdom | B4: Population, total | C4: FEB019C | D4: NA | E4: Thousands | F4: Level | G4: 56217.56 | H4: 56233.31 | I4: 56224.75 | J4: 56211.75 | K4: 56189.38 | L4: 56190.38 | M4: 56253 | N4: 56329.63 | O4: 56343.69 | P4: 56299.88 | Q4: 56331.88 | R4: 56430.38 | S4: 56569.31 | T4: 56698.38 | U4: 56817.5 | V4: 56939.19 | W4: 57097.13 | X4: 57265.63 | Y4: 57453.81 | Z4: 57600.06 | AA4: 57733.69 | AB4: 57883.31 | AC4: 58040.88 | AD4: 58183.44 | AE4: 58334.81 | AF4: 58504.13 | AG4: 58708.81 | AH4: 58915.94 | AI4: 59146.25 | AJ4: 59401 | AK4: 59678.75 | AL4: 60017.25 | AM4: 60461.69 | AN4: 60893.38 | AO4: 61382.94 | AP4: 61874.38 | AQ4: 62327.25 | AR4: 62827.25 | AS4: 63330.94 | AT4: 63753.94 | AU4: 64173 | AV4: 64662.5 | AW4: 65178.81 | AX4: 65687.88 | AY4: 66089.75 | AZ4: 66478.94 | BA4: 66827.69 | BB4: 67052.94 | BC4: 67148.73 | BD4: 67751.13 | BE4: 68431.44 | BF4: 69080.14 | BG4: 69648.78 | BH4: 70129.62 | BI4: 70520.64 | BJ4: 70835.8 | BK4: 71136.84 | BL4: 71428.86 | BM4: 71711.97 | BN4: 71986.43 | BO4: 72252.36 | BP4: 72510.1 | BQ4: 72760.48 | BR4: 73005.31 | BS4: 73246.3 | BT4: 73484.3 | BU4: 73719.86 | BV4: 73953.14 | BW4: 74183.78 | BX4: 74411.36 | BY4: 74635.8 | BZ4: 74856.69 | CA4: 75072.63 | CB4: 75282.19 | CC4: 75484.82 | CD4: 75680.09 | CE4: 75867.55 | CF4: 76047.09 | CG4: Office for National Statistics\Haver Analytics | CH4: False | CI4: NA | CJ4: NA | CK4: 2021 | CL4: 2 | CM4: NA | CN4: DYAYA@UK | CO4: U.K.: Population: Midyear Estimates (Thous.Persons) | CP4: GBR | CQ4: POP | CR4: FEB019C.db
A5: United Kingdom | B5: Population of working age | C5: FEB019C | D5: NA | E5: Thousands | F5: Level | G5: 32757.89 | H5: 32767.07 | I5: 32762.08 | J5: 32795.71 | K5: 32987.17 | L5: 33191.79 | M5: 33396.4 | N5: 33601.01 | O5: 33792.79 | P5: 33953.4 | Q5: 34192.7 | R5: 34431.35 | S5: 34601.24 | T5: 34744.76 | U5: 34886.88 | V5: 34994.56 | W5: 35085.88 | X5: 35152.13 | Y5: 35195.33 | Z5: 35205.66 | AA5: 35216.77 | AB5: 35273.27 | AC5: 35383.34 | AD5: 35513.12 | AE5: 35638.8 | AF5: 35772.38 | AG5: 35956.09 | AH5: 36175.06 | AI5: 36435.72 | AJ5: 36685.3 | AK5: 36916.48 | AL5: 37197 | AM5: 37558.84 | AN5: 37877.6 | AO5: 38141.88 | AP5: 38372.89 | AQ5: 38572.31 | AR5: 38878.28 | AS5: 39253.63 | AT5: 39477.15 | AU5: 39743.89 | AV5: 40075.52 | AW5: 40465.18 | AX5: 40864.96 | AY5: 41230.95 | AZ5: 41611.73 | BA5: 42058.89 | BB5: 42514.19 | BC5: 42920.37 | BD5: 43329.91 | BE5: 43931.74 | BF5: 44395.75 | BG5: 44787.54 | BH5: 45242.13 | BI5: 45815.64 | BJ5: 46194.32 | BK5: 46306.75 | BL5: 46369.88 | BM5: 46417.26 | BN5: 46461.01 | BO5: 46492.81 | BP5: 46511.65 | BQ5: 46527.01 | BR5: 46535.05 | BS5: 46540.29 | BT5: 46541.88 | BU5: 46558.4 | BV5: 46639.72 | BW5: 46756.44 | BX5: 46887.4 | BY5: 47054.41 | BZ5: 47364.89 | CA5: 47846.93 | CB5: 48201.31 | CC5: 48303.23 | CD5: 48358.84 | CE5: 48413.17 | CF5: 48469.81 | CG5: Office for National Statistics Population Estimates | CH5: False | CI5: NA | CJ5: NA | CK5: 2021 | CL5: 2 | CM5: NA | CN5: Calculated by Oxford Economics using ONS single-year population estimates. Allows for changing state pension age | CO5: NA | CP5: GBR | CQ5: POPW | CR5: FEB019C.db
A6: United Kingdom | B6: Nairu | C6: FEB019C | D6: % | E6: NA | F6: Level | G6: 4 | H6: 4 | I6: 4.5 | J6: 5.15 | K6: 5.625 | L6: 6.4 | M6: 7.2 | N6: 8 | O6: 8.8 | P6: 9.425 | Q6: 9.5 | R6: 9.5 | S6: 9.5 | T6: 9.5 | U6: 9.5 | V6: 9.5 | W6: 9.5 | X6: 9.5 | Y6: 9.5 | Z6: 9.5 | AA6: 9.425 | AB6: 9.049999 | AC6: 8.65 | AD6: 8 | AE6: 7.2 | AF6: 6.4 | AG6: 5.75 | AH6: 5.35 | AI6: 5.025 | AJ6: 5 | AK6: 5 | AL6: 5 | AM6: 5 | AN6: 5 | AO6: 5 | AP6: 5 | AQ6: 5 | AR6: 5.125 | AS6: 5.2875 | AT6: 5.3 | AU6: 5.3 | AV6: 5.2625 | AW6: 4.9875 | AX6: 4.775 | AY6: 4.575 | AZ6: 4.39375 | BA6: 4.2875 | BB6: 4.25 | BC6: 4.175 | BD6: 4.1 | BE6: 4.1 | BF6: 4.1 | BG6: 4.1 | BH6: 4.0375 | BI6: 3.9375 | BJ6: 3.8375 | BK6: 3.75625 | BL6: 3.75 | BM6: 3.75 | BN6: 3.75 | BO6: 3.75 | BP6: 3.75 | BQ6: 3.75 | BR6: 3.75 | BS6: 3.75 | BT6: 3.75 | BU6: 3.75 | BV6: 3.75 | BW6: 3.75 | BX6: 3.75 | BY6: 3.75 | BZ6: 3.75 | CA6: 3.75 | CB6: 3.75 | CC6: 3.75 | CD6: 3.75 | CE6: 3.75 | CF6: 3.75 | CG6: Oxford Economics estimate | CH6: False | CI6: NA | CJ6: NA | CK6: 2021 | CL6: 2 | CM6: NA | CN6: Oxford Economics estimate | CO6: The NAIRU | CP6: GBR | CQ6: NAIRU | CR6: FEB019C.db
A7: United Kingdom | B7: Potential output, LCU | C7: FEB019C | D7: Pound | E7: Millions | F7: Level | G7: 898803.2 | H7: 909717.9 | I7: 917020.3 | J7: 921384.1 | K7: 924484.8 | L7: 932047.9 | M7: 951947.9 | N7: 975762 | O7: 990112 | P7: 996004.9 | Q7: 1012416 | R7: 1047849 | S7: 1076968 | T7: 1104492 | U7: 1135284 | V7: 1175653 | W7: 1217964 | X7: 1250609 | Y7: 1267882 | Z7: 1285429 | AA7: 1306377 | AB7: 1340362 | AC7: 1374846 | AD7: 1411804 | AE7: 1451153 | AF7: 1482073 | AG7: 1523159 | AH7: 1561852 | AI7: 1611689 | AJ7: 1651285 | AK7: 1693448 | AL7: 1737570 | AM7: 1791043 | AN7: 1840881 | AO7: 1883737 | AP7: 1923485 | AQ7: 1930839 | AR7: 1951515 | AS7: 1968889 | AT7: 2003656 | AU7: 2037139 | AV7: 2069974 | AW7: 2101006 | AX7: 2136889 | AY7: 2171464 | AZ7: 2202562 | BA7: 2238861 | BB7: 2094635 | BC7: 2185763 | BD7: 2244500 | BE7: 2263783 | BF7: 2286365 | BG7: 2328245 | BH7: 2372045 | BI7: 2413245 | BJ7: 2453117 | BK7: 2492142 | BL7: 2529998 | BM7: 2568239 | BN7: 2606529 | BO7: 2644184 | BP7: 2681838 | BQ7: 2720205 | BR7: 2760292 | BS7: 2801571 | BT7: 2844332 | BU7: 2888392 | BV7: 2933352 | BW7: 2978445 | BX7: 3023788 | BY7: 3069663 | BZ7: 3116042 | CA7: 3162919 | CB7: 3210289 | CC7: 3258161 | CD7: 3306547 | CE7: 3355443 | CF7: 3404844 | CG7: Oxford Economics estimate | CH7: False | CI7: chained 2019 | CJ7: NA | CK7: 2021 | CL7: 2 | CM7: NA | CN7: Potential output | CO7: NA | CP7: GBR | CQ7: YHAT | CR7: FEB019C.db
A8: United Kingdom | B8: Average hours of work per week | C8: FEB019C | D8: Hours per week | E8: NA | F8: Level | G8: 0.001 | H8: 0.001 | I8: 0.001 | J8: 0.001 | K8: 0.001 | L8: 0.001 | M8: 0.001 | N8: 0.001 | O8: 0.001 | P8: 0.001 | Q8: 0.001 | R8: 0.001 | S8: 0.001 | T8: 33.52414 | U8: 33.52414 | V8: 33.6901 | W8: 33.77308 | X8: 33.60712 | Y8: 33.19222 | Z8: 33.07629 | AA8: 33 | AB8: 33.225 | AC8: 33.25 | AD8: 33.225 | AE8: 33.175 | AF8: 33.075 | AG8: 32.9 | AH8: 32.6 | AI8: 32.675 | AJ8: 32.325 | AK8: 32.15 | AL8: 32.075 | AM8: 32.175 | AN8: 32.05 | AO8: 32.075 | AP8: 31.975 | AQ8: 31.55 | AR8: 31.65 | AS8: 31.575 | AT8: 31.825 | AU8: 32.05 | AV8: 32.175 | AW8: 32.1 | AX8: 32.05 | AY8: 32.1 | AZ8: 32 | BA8: 32.075 | BB8: 28.95 | BC8: 30.975 | BD8: 31.8 | BE8: 31.575 | BF8: 31.65454 | BG8: 31.8 | BH8: 31.94546 | BI8: 31.99948 | BJ8: 31.99865 | BK8: 31.99781 | BL8: 31.99698 | BM8: 31.99615 | BN8: 31.99531 | BO8: 31.99357 | BP8: 31.99128 | BQ8: 31.98898 | BR8: 31.98669 | BS8: 31.9844 | BT8: 31.98211 | BU8: 31.97982 | BV8: 31.97753 | BW8: 31.97479 | BX8: 31.9718 | BY8: 31.9688 | BZ8: 31.9658 | CA8: 31.9628 | CB8: 31.95979 | CC8: 31.95679 | CD8: 31.95379 | CE8: 31.9508 | CF8: 31.94779 | CG8: ONS\Haver Analytics | CH8: False | CI8: NA | CJ8: NA | CK8: 2023 | CL8: 4 | CM8: NA | CN8: YBUVQ@UK | CO8: UK: LFS: Average Actual Weekly Hours Worked: All Workers (SA, Number) | CP8: GBR | CQ8: AVHR | CR8: FEB019C.db
A9: United Kingdom | B9: Employment at the NAIRU | C9: FEB019C | D9: NA | E9: Thousands | F9: Level | G9: 24874.8 | H9: 24938.64 | I9: 24932.05 | J9: 24850.21 | K9: 24800.74 | L9: 24703.73 | M9: 24709.44 | N9: 24765.53 | O9: 24659.65 | P9: 24297.71 | Q9: 24304.68 | R9: 24910.8 | S9: 25107.87 | T9: 25255.61 | U9: 25501.77 | V9: 25806.3 | W9: 26091.83 | X9: 26176.67 | Y9: 25966.49 | Z9: 25667.16 | AA9: 25571.12 | AB9: 25629.68 | AC9: 25810.1 | AD9: 26087.38 | AE9: 26460.54 | AF9: 26754.36 | AG9: 27233.62 | AH9: 27515.48 | AI9: 27733.68 | AJ9: 27999.35 | AK9: 28224.98 | AL9: 28456.06 | AM9: 28798.3 | AN9: 29268.07 | AO9: 29481.35 | AP9: 29844.01 | AQ9: 29980.81 | AR9: 30099.27 | AS9: 30283.13 | AT9: 30576.73 | AU9: 30835.98 | AV9: 31103.99 | AW9: 31459.18 | AX9: 31832.32 | AY9: 32051.37 | AZ9: 32379.71 | BA9: 32699 | BB9: 32670.62 | BC9: 32643.31 | BD9: 32844.79 | BE9: 33135.85 | BF9: 33172.24 | BG9: 33625.59 | BH9: 34081.88 | BI9: 34488.22 | BJ9: 34863.66 | BK9: 35192.36 | BL9: 35468.18 | BM9: 35729.58 | BN9: 35972.24 | BO9: 36172.36 | BP9: 36342.37 | BQ9: 36493.67 | BR9: 36646.18 | BS9: 36798.69 | BT9: 36951.2 | BU9: 37103.71 | BV9: 37256.23 | BW9: 37399.43 | BX9: 37537.04 | BY9: 37674.65 | BZ9: 37812.27 | CA9: 37949.88 | CB9: 38087.49 | CC9: 38225.1 | CD9: 38362.71 | CE9: 38500.33 | CF9: 38637.94 | CG9: Oxford Economics estimate | CH9: False | CI9: NA | CJ9: NA | CK9: 2021 | CL9: 2 | CM9: NA | CN9: Oxford Economics estimate | CO9: NA | CP9: GBR | CQ9: ESTAR | CR9: FEB019C.db
A10: United Kingdom | B10: Capital stock, real, LCU | C10: FEB019C | D10: Pound | E10: Millions | F10: Level | G10: 983736.3 | H10: 1010781 | I10: 1037121 | J10: 1061489 | K10: 1083744 | L10: 1111352 | M10: 1132762 | N10: 1149523 | O10: 1157411 | P10: 1167835 | Q10: 1180230 | R10: 1202767 | S10: 1226994 | T10: 1246573 | U10: 1274603 | V10: 1314888 | W10: 1362920 | X10: 1416727 | Y10: 1462646 | Z10: 1490253 | AA10: 1518284 | AB10: 1551666 | AC10: 1589698 | AD10: 1628714 | AE10: 1679000 | AF10: 1730000 | AG10: 1817000 | AH10: 1891000 | AI10: 1959000 | AJ10: 2015000 | AK10: 2062000 | AL10: 2113000 | AM10: 2168000 | AN10: 2230000 | AO10: 2305000 | AP10: 2365000 | AQ10: 2387000 | AR10: 2416000 | AS10: 2443000 | AT10: 2469000 | AU10: 2507000 | AV10: 2553000 | AW10: 2612000 | AX10: 2679000 | AY10: 2744000 | AZ10: 2797000 | BA10: 2850000 | BB10: 2869000 | BC10: 2894000 | BD10: 2939000 | BE10: 2992629 | BF10: 3033028 | BG10: 3069852 | BH10: 3109861 | BI10: 3151246 | BJ10: 3192697 | BK10: 3234931 | BL10: 3279805 | BM10: 3327676 | BN10: 3378419 | BO10: 3432026 | BP10: 3488402 | BQ10: 3547459 | BR10: 3609279 | BS10: 3673876 | BT10: 3741310 | BU10: 3811608 | BV10: 3883890 | BW10: 3957557 | BX10: 4032567 | BY10: 4108883 | BZ10: 4186484 | CA10: 4265376 | CB10: 4345567 | CC10: 4427064 | CD10: 4509879 | CE10: 4594021 | CF10: 4679501 | CG10: Office for National Statistics\Haver Analytics | CH10: False | CI10: chained 2019 | CJ10: NA | CK10: 2022 | CL10: 4 | CM10: NA | CN10: (MLR3A@UK-MLO9A@UK)*1000, interpolated | CO10: (UK: Net Capital Stock at CVM: Assets (Bil.GBP) - UK: Net Capital Stock at CVM: Dwellings excluding Land (Bil.GBP)) *1000, interpolated | CP10: GBR | CQ10: K | CR10: FEB019C.db
A11: United Kingdom | B11: Years of schooling in population | C11: FEB019C | D11: Years | E11: NA | F11: Level | G11: 286021.4 | H11: 288869 | I11: 291532.5 | J11: 293842.9 | K11: 295875.2 | L11: 297883.1 | M11: 300120.3 | N11: 306731.3 | O11: 309382.7 | P11: 311708.9 | Q11: 314668.8 | R11: 318382.6 | S11: 322872.1 | T11: 327826.4 | U11: 332272.4 | V11: 336945.5 | W11: 341767.8 | X11: 346213.4 | Y11: 350307.5 | Z11: 353919.6 | AA11: 357272.1 | AB11: 360583.8 | AC11: 363847.5 | AD11: 366199.2 | AE11: 368101.4 | AF11: 370531.5 | AG11: 375183.3 | AH11: 383089.9 | AI11: 395262.5 | AJ11: 410903.6 | AK11: 428210.7 | AL11: 445699.5 | AM11: 462180.4 | AN11: 476476.1 | AO11: 489499.3 | AP11: 500453.1 | AQ11: 509276.3 | AR11: 516794.4 | AS11: 523904.2 | AT11: 528051.7 | AU11: 532788 | AV11: 538611.7 | AW11: 545125.1 | AX11: 551423.6 | AY11: 556744.5 | AZ11: 562195.3 | BA11: 567581.8 | BB11: 573787.8 | BC11: 582107.6 | BD11: 591487 | BE11: 603564.2 | BF11: 613526.9 | BG11: 622273.4 | BH11: 629797.1 | BI11: 635882.6 | BJ11: 640583.9 | BK11: 644709 | BL11: 648620.4 | BM11: 652503.1 | BN11: 655958.8 | BO11: 659080.5 | BP11: 661921.4 | BQ11: 664541.9 | BR11: 666635.2 | BS11: 669091.8 | BT11: 671729.7 | BU11: 675201.2 | BV11: 678935.3 | BW11: 682886.4 | BX11: 686981 | BY11: 690738.3 | BZ11: 693698.9 | CA11: 696148.1 | CB11: 698527.1 | CC11: 700897.7 | CD11: 703152.1 | CE11: 705236.9 | CF11: 706899.9 | CG11: Barro R. & J.W. Lee\Office for National Statistics Mid-Year Population Estimates | CH11: False | CI11: NA | CJ11: NA | CK11: 2010 | CL11: 4 | CM11: NA | CN11: EDUCAVE * POP15_64 | CO11: NA | CP11: GBR | CQ11: EDUC | CR11: FEB019C.db
A12: United Kingdom | B12: Population, 15-64 | C12: FEB019C | D12: NA | E12: Thousands | F12: Level | G12: 35322.81 | H12: 35332.71 | I12: 35327.33 | J12: 35352.08 | K12: 35501.05 | L12: 35670.84 | M12: 35882.96 | N12: 36102.32 | O12: 36300.18 | P12: 36500.68 | Q12: 36776.19 | R12: 37029.13 | S12: 37116.96 | T12: 37205.48 | U12: 37265.83 | V12: 37299.2 | W12: 37327.73 | X12: 37358.56 | Y12: 37364.49 | Z12: 37339.07 | AA12: 37349.41 | AB12: 37433.7 | AC12: 37553 | AD12: 37673.28 | AE12: 37794.41 | AF12: 37944.26 | AG12: 38156.28 | AH12: 38407.35 | AI12: 38667.29 | AJ12: 38934.07 | AK12: 39208.64 | AL12: 39524.45 | AM12: 39942.1 | AN12: 40350.64 | AO12: 40723.55 | AP12: 41014.32 | AQ12: 41237.87 | AR12: 41479.08 | AS12: 41682.68 | AT12: 41657.2 | AU12: 41687.5 | AV12: 41810.11 | AW12: 41991.91 | AX12: 42161.43 | AY12: 42259.49 | AZ12: 42370.76 | BA12: 42480.22 | BB12: 42653.26 | BC12: 42984.3 | BD12: 43392.68 | BE12: 43996.9 | BF12: 44444.65 | BG12: 44803.5 | BH12: 45075.56 | BI12: 45248.6 | BJ12: 45328.88 | BK12: 45375.41 | BL12: 45414.74 | BM12: 45461.71 | BN12: 45492.61 | BO12: 45515.16 | BP12: 45533.71 | BQ12: 45552.58 | BR12: 45548.55 | BS12: 45577.19 | BT12: 45624.28 | BU12: 45732.02 | BV12: 45859.94 | BW12: 46004.29 | BX12: 46159.85 | BY12: 46294.54 | BZ12: 46378.6 | CA12: 46431.85 | CB12: 46483.73 | CC12: 46538.08 | CD12: 46587.35 | CE12: 46628.06 | CF12: 46643.86 | CG12: Office for National Statistics Mid-Year Population Estimates | CH12: False | CI12: NA | CJ12: NA | CK12: 2021 | CL12: 2 | CM12: NA | CN12: Population aged 15-64 aggregated from ONS mid-year population estimates | CO12: NA | CP12: GBR | CQ12: POP15_64 | CR12: FEB019C.db
A13: United Kingdom | B13: Total factor productivity trend | C13: FEB019C | D13: Number | E13: NA | F13: Level | G13: -1.989488 | H13: -1.993417 | I13: -1.997353 | J13: -2.001297 | K13: -2.005249 | L13: -2.003015 | M13: -1.990505 | N13: -1.978074 | O13: -1.965721 | P13: -1.953444 | Q13: -1.941244 | R13: -1.929121 | S13: -1.917073 | T13: -1.905234 | U13: -1.894 | V13: -1.882876 | W13: -1.871818 | X13: -1.860825 | Y13: -1.849896 | Z13: -1.839032 | AA13: -1.828231 | AB13: -1.817494 | AC13: -1.806819 | AD13: -1.796208 | AE13: -1.786856 | AF13: -1.782333 | AG13: -1.778219 | AH13: -1.774115 | AI13: -1.77002 | AJ13: -1.765935 | AK13: -1.761859 | AL13: -1.757793 | AM13: -1.753736 | AN13: -1.749689 | AO13: -1.747736 | AP13: -1.747867 | AQ13: -1.74876 | AR13: -1.748997 | AS13: -1.749272 | AT13: -1.749547 | AU13: -1.749822 | AV13: -1.750097 | AW13: -1.750372 | AX13: -1.750647 | AY13: -1.750923 | AZ13: -1.751199 | BA13: -1.751474 | BB13: -1.757496 | BC13: -1.763263 | BD13: -1.76374 | BE13: -1.764016 | BF13: -1.764119 | BG13: -1.763976 | BH13: -1.763193 | BI13: -1.7611 | BJ13: -1.75802 | BK13: -1.754507 | BL13: -1.750716 | BM13: -1.746868 | BN13: -1.742989 | BO13: -1.738871 | BP13: -1.734484 | BQ13: -1.729763 | BR13: -1.724708 | BS13: -1.71954 | BT13: -1.714174 | BU13: -1.708694 | BV13: -1.703233 | BW13: -1.697789 | BX13: -1.692363 | BY13: -1.686954 | BZ13: -1.681562 | CA13: -1.676188 | CB13: -1.67083 | CC13: -1.66549 | CD13: -1.660167 | CE13: -1.65486 | CF13: -1.649572 | CG13: Oxford Economics calculation | CH13: False | CI13: NA | CJ13: NA | CK13: 2021 | CL13: 2 | CM13: NA | CN13: Ln(Potential output, LCU) - 0.4 * Ln(Labour supply * Average hours of work per week) - 0.3 * Ln( Years of schooling in population / Population, total) - 0.3 * Ln(Capital stock, real, LCU(-1)) | CO13: NA | CP13: GBR | CQ13: TREND | CR13: FEB019C.db
... A18: United Kingdom | B18: GDP, nominal, LCU | C18: FEB019C | D18: Pound | E18: Millions | F18: Level | G18: 81793 | H18: 92673 | I18: 115093 | J18: 136999 | K18: 159786 | L18: 186158 | M18: 220981 | N18: 259970 | O18: 290180 | P18: 319558 | Q18: 351347 | R18: 377920 | S18: 414630 | T18: 446600 | U18: 496809 | V18: 555683 | W18: 614631 | X18: 670797 | Y18: 705884 | Z18: 730874 | AA18: 769855 | AB18: 810794 | AC18: 851845 | AD18: 909993 | AE18: 953405 | AF18: 998501 | AG18: 1043248 | AH18: 1100752 | AI18: 1146135 | AJ18: 1191439 | AK18: 1258334 | AL18: 1322637 | AM18: 1398749 | AN18: 1472038 | AO18: 1544637 | AP18: 1593600 | AQ18: 1548802 | AR18: 1608553 | AS18: 1662590 | AT18: 1713715 | AU18: 1781361 | AV18: 1862514 | AW18: 1916451 | AX18: 1991645 | AY18: 2082482 | AZ18: 2152304 | BA18: 2233921 | BB18: 2104288 | BC18: 2284079 | BD18: 2505981 | BE18: 2689974 | BF18: 2763627 | BG18: 2866512 | BH18: 2985598 | BI18: 3100489 | BJ18: 3216983 | BK18: 3334340 | BL18: 3458098 | BM18: 3587271 | BN18: 3720989 | BO18: 3857398 | BP18: 3997865 | BQ18: 4143577 | BR18: 4296403 | BS18: 4455828 | BT18: 4622663 | BU18: 4796871 | BV18: 4978016 | BW18: 5165017 | BX18: 5358253 | BY18: 5558505 | BZ18: 5765932 | CA18: 5980709 | CB18: 6203084 | CC18: 6433315 | CD18: 6671683 | CE18: 6918456 | CF18: 7173901 | CG18: Office for National Statistics\Haver Analytics | CH18: True | CI18: NA | CJ18: NA | CK18: 2023 | CL18: 4 | CM18: NA | CN18: YBHAQ@UK | CO18: U.K.: Gross Domestic Product (SA, Mil.Pounds) | CP18: GBR | CQ18: GDP! | CR18: FEB019C.db

Sheet ONS pop proj migration
A1: Figure 2: UK principal net international migration assumptions with illustrative figures to show potential levels of migration if they were 20% higher or 20% lower than the principal assumption
A2: Net international migration, persons, mid-2023 to mid-2030, UK
A4: Notes | B4: 1. Estimated total international migration for mid-2023 is provisional and will be updated when more complete data are available. 2. Estimated total international migration for mid-2023 does not match the release Long-term international migration, provisional: year ending June 2023 because of the use of data for Northern Ireland from the Northern Ireland Statistics and Research Agency (NISRA) 3. Source: National population projections and migration statistics from the Office for National Statistics; Northern Ireland Statistics and Research Agency (NISRA)
A5: Unit | B5: Persons, thousands
A7: Year | B7: Low net international migration variant assumptions | C7: Principal net international migration assumptions | D7: High net international migration assumptions
A8: Mid-2023 | B8: 670000 | C8: 670000 | D8: 670000
A9: Mid-2024 | B9: 586600 | C9: 599000 | D9: 611800
A10: Mid-2025 | B10: 503200 | C10: 528000 | D10: 553600
A11: Mid-2026 | B11: 419800 | C11: 457000 | D11: 495400
A12: Mid-2027 | B12: 336400 | C12: 386000 | D12: 437200
A13: Mid-2028 | B13: 253000 | C13: 315000 | D13: 379000
A14: Mid-2029 | B14: 253000 | C14: 315000 | D14: 379000
A15: Mid-2030 | B15: 253000 | C15: 315000 | D15: 379000

Sheet ONS pop proj 2020-based
A1: Sex | B1: Age | C1: 2020 | D1: 2021 | E1: 2022 | F1: 2023 | G1: 2024 | H1: 2025 | I1: 2026 | J1: 2027 | K1: 2028 | L1: 2029 | M1: 2030 | N1: 2031 | O1: 2032 | P1: 2033 | Q1: 2034 | R1: 2035 | S1: 2036 | T1: 2037 | U1: 2038 | V1: 2039 | W1: 2040 | X1: 2041 | Y1: 2042 | Z1: 2043 | AA1: 2044 | AB1: 2045 | AC1: 2046 | AD1: 2047 | AE1: 2048 | AF1: 2049 | AG1: 2050 | AH1: 2051 | AI1: 2052 | AJ1: 2053 | AK1: 2054 | AL1: 2055 | AM1: 2056 | AN1: 2057 | AO1: 2058 | AP1: 2059 | AQ1: 2060 | AR1: 2061 | AS1: 2062 | AT1: 2063 | AU1: 2064 | AV1: 2065 | AW1: 2066 | AX1: 2067 | AY1: 2068 | AZ1: 2069 | BA1: 2070 | BB1: 2071 | BC1: 2072 | BD1: 2073 | BE1: 2074 | BF1: 2075 | BG1: 2076 | BH1: 2077 | BI1: 2078 | BJ1: 2079 | BK1: 2080 | BL1: 2081 | BM1: 2082 | BN1: 2083 | BO1: 2084 | BP1: 2085 | BQ1: 2086 | BR1: 2087 | BS1: 2088 | BT1: 2089 | BU1: 2090 | BV1: 2091 | BW1: 2092 | BX1: 2093 | BY1: 2094 | BZ1: 2095 | CA1: 2096 | CB1: 2097 | CC1: 2098 | CD1: 2099 | CE1: 2100 | CF1: 2101 | CG1: 2102 | CH1: 2103 | CI1: 2104 | CJ1: 2105 | CK1: 2106 | CL1: 2107 | CM1: 2108 | CN1: 2109 | CO1: 2110 | CP1: 2111 | CQ1: 2112 | CR1: 2113 | CS1: 2114 | CT1: 2115 | CU1: 2116 | CV1: 2117 | CW1: 2118 | CX1: 2119 | CY1: 2120
A2: 1 | B2: 0 | C2: 360102 | D2: 343691 | E2: 340530 | F2: 339364 | G2: 341630 | H2: 342335 | I2: 341510 | J2: 340675 | K2: 339987 | L2: 339478 | M2: 339173 | N2: 339190 | O2: 339607 | P2: 340215 | Q2: 341088 | R2: 342393 | S2: 344681 | T2: 347971 | U2: 351497 | V2: 355059 | W2: 358548 | X2: 361596 | Y2: 364047 | Z2: 366100 | AA2: 367683 | AB2: 368219 | AC2: 367762 | AD2: 366775 | AE2: 365220 | AF2: 363091 | AG2: 360518 | AH2: 357724 | AI2: 354832 | AJ2: 351848 | AK2: 348850 | AL2: 346041 | AM2: 343535 | AN2: 341383 | AO2: 339575 | AP2: 338112 | AQ2: 337002 | AR2: 336223 | AS2: 335789 | AT2: 335723 | AU2: 335993 | AV2: 336559 | AW2: 337348 | AX2: 338292 | AY2: 339370 | AZ2: 340547 | BA2: 341771 | BB2: 342993 | BC2: 344160 | BD2: 345238 | BE2: 346179 | BF2: 346945 | BG2: 347502 | BH2: 347829 | BI2: 347923 | BJ2: 347769 | BK2: 347373 | BL2: 346748 | BM2: 345919 | BN2: 344924 | BO2: 343797 | BP2: 342578 | BQ2: 341314 | BR2: 340037 | BS2: 338799 | BT2: 337626 | BU2: 336562 | BV2: 335618 | BW2: 334823 | BX2: 334191 | BY2: 333718 | BZ2: 333416 | CA2: 333267 | CB2: 333269 | CC2: 333406 | CD2: 333656 | CE2: 333998 | CF2: 334413 | CG2: 334867 | CH2: 335349 | CI2: 335821 | CJ2: 336273 | CK2: 336678 | CL2: 337021 | CM2: 337283 | CN2: 337456 | CO2: 337533 | CP2: 337508 | CQ2: 337385 | CR2: 337158 | CS2: 336844 | CT2: 336451 | CU2: 335985 | CV2: 335471 | CW2: 334909 | CX2: 334335 | CY2: 333749
A3: 1 | B3: 1 | C3: 375332 | D3: 362549 | E3: 348404 | F3: 343726 | G3: 342398 | H3: 344494 | I3: 345035 | J3: 344043 | K3: 343213 | L3: 342529 | M3: 342025 | N3: 341724 | O3: 341744 | P3: 342163 | Q3: 342775 | R3: 343650 | S3: 344958 | T3: 347247 | U3: 350538 | V3: 354064 | W3: 357629 | X3: 361119 | Y3: 364166 | Z3: 366619 | AA3: 368674 | AB3: 370257 | AC3: 370795 | AD3: 370339 | AE3: 369358 | AF3: 367805 | AG3: 365678 | AH3: 363109 | AI3: 360316 | AJ3: 357431 | AK3: 354448 | AL3: 351452 | AM3: 348647 | AN3: 346142 | AO3: 343996 | AP3: 342191 | AQ3: 340729 | AR3: 339623 | AS3: 338844 | AT3: 338413 | AU3: 338347 | AV3: 338620 | AW3: 339188 | AX3: 339977 | AY3: 340922 | AZ3: 342001 | BA3: 343179 | BB3: 344405 | BC3: 345628 | BD3: 346796 | BE3: 347874 | BF3: 348815 | BG3: 349582 | BH3: 350141 | BI3: 350471 | BJ3: 350566 | BK3: 350413 | BL3: 350018 | BM3: 349395 | BN3: 348568 | BO3: 347574 | BP3: 346448 | BQ3: 345230 | BR3: 343969 | BS3: 342693 | BT3: 341458 | BU3: 340287 | BV3: 339225 | BW3: 338281 | BX3: 337487 | BY3: 336855 | BZ3: 336384 | CA3: 336084 | CB3: 335936 | CC3: 335940 | CD3: 336076 | CE3: 336328 | CF3: 336670 | CG3: 337085 | CH3: 337540 | CI3: 338024 | CJ3: 338497 | CK3: 338950 | CL3: 339356 | CM3: 339700 | CN3: 339963 | CO3: 340137 | CP3: 340214 | CQ3: 340190 | CR3: 340068 | CS3: 339843 | CT3: 339528 | CU3: 339139 | CV3: 338673 | CW3: 338161 | CX3: 337599 | CY3: 337025
A4: 1 | B4: 2 | C4: 389465 | D4: 378683 | E4: 368748 | F4: 352684 | G4: 347793 | H4: 346250 | I4: 348133 | J4: 348457 | K4: 347465 | L4: 346637 | M4: 345954 | N4: 345451 | O4: 345152 | P4: 345173 | Q4: 345592 | R4: 346205 | S4: 347080 | T4: 348388 | U4: 350679 | V4: 353972 | W4: 357497 | X4: 361061 | Y4: 364552 | Z4: 367600 | AA4: 370052 | AB4: 372108 | AC4: 373692 | AD4: 374231 | AE4: 373774 | AF4: 372795 | AG4: 371242 | AH4: 369117 | AI4: 366551 | AJ4: 363756 | AK4: 360872 | AL4: 357890 | AM4: 354896 | AN4: 352092 | AO4: 349588 | AP4: 347442 | AQ4: 345638 | AR4: 344176 | AS4: 343071 | AT4: 342292 | AU4: 341862 | AV4: 341797 | AW4: 342070 | AX4: 342638 | AY4: 343427 | AZ4: 344372 | BA4: 345452 | BB4: 346631 | BC4: 347857 | BD4: 349080 | BE4: 350250 | BF4: 351328 | BG4: 352268 | BH4: 353035 | BI4: 353596 | BJ4: 353926 | BK4: 354021 | BL4: 353869 | BM4: 353474 | BN4: 352851 | BO4: 352024 | BP4: 351031 | BQ4: 349907 | BR4: 348689 | BS4: 347428 | BT4: 346154 | BU4: 344919 | BV4: 343747 | BW4: 342686 | BX4: 341743 | BY4: 340951 | BZ4: 340319 | CA4: 339848 | CB4: 339547 | CC4: 339400 | CD4: 339404 | CE4: 339540 | CF4: 339792 | CG4: 340136 | CH4: 340551 | CI4: 341005 | CJ4: 341489 | CK4: 341963 | CL4: 342416 | CM4: 342822 | CN4: 343166 | CO4: 343428 | CP4: 343605 | CQ4: 343681 | CR4: 343658 | CS4: 343537 | CT4: 343313 | CU4: 342997 | CV4: 342609 | CW4: 342142 | CX4: 341631 | CY4: 341070
A5: 1 | B5: 3 | C5: 401864 | D5: 392485 | E5: 384286 | F5: 372616 | G5: 356360 | H5: 351274 | I5: 349539 | J5: 351227 | K5: 351553 | L5: 350562 | M5: 349735 | N5: 349052 | O5: 348549 | P5: 348249 | Q5: 348273 | R5: 348692 | S5: 349305 | T5: 350180 | U5: 351490 | V5: 353780 | W5: 357073 | X5: 360599 | Y5: 364163 | Z5: 367654 | AA5: 370702 | AB5: 373154 | AC5: 375209 | AD5: 376793 | AE5: 377334 | AF5: 376876 | AG5: 375898 | AH5: 374344 | AI5: 372219 | AJ5: 369655 | AK5: 366860 | AL5: 363976 | AM5: 360994 | AN5: 358000 | AO5: 355198 | AP5: 352694 | AQ5: 350547 | AR5: 348745 | AS5: 347283 | AT5: 346178 | AU5: 345399 | AV5: 344970 | AW5: 344905 | AX5: 345179 | AY5: 345747 | AZ5: 346536 | BA5: 347480 | BB5: 348560 | BC5: 349740 | BD5: 350967 | BE5: 352189 | BF5: 353360 | BG5: 354438 | BH5: 355378 | BI5: 356145 | BJ5: 356705 | BK5: 357035 | BL5: 357131 | BM5: 356980 | BN5: 356584 | BO5: 355961 | BP5: 355135 | BQ5: 354140 | BR5: 353018 | BS5: 351801 | BT5: 350540 | BU5: 349267 | BV5: 348032 | BW5: 346859 | BX5: 345799 | BY5: 344856 | BZ5: 344065 | CA5: 343431 | CB5: 342962 | CC5: 342660 | CD5: 342514 | CE5: 342518 | CF5: 342656 | CG5: 342908 | CH5: 343252 | CI5: 343667 | CJ5: 344121 | CK5: 344605 | CL5: 345079 | CM5: 345531 | CN5: 345937 | CO5: 346282 | CP5: 346543 | CQ5: 346722 | CR5: 346796 | CS5: 346773 | CT5: 346653 | CU5: 346430 | CV5: 346114 | CW5: 345726 | CX5: 345258 | CY5: 344747
A6: 1 | B6: 4 | C6: 414627 | D6: 404546 | E6: 397500 | F6: 387740 | G6: 375899 | H6: 359472 | I6: 354214 | J6: 352308 | K6: 353995 | L6: 354321 | M6: 353332 | N6: 352505 | O6: 351823 | P6: 351320 | Q6: 351020 | R6: 351045 | S6: 351465 | T6: 352077 | U6: 352952 | V6: 354263 | W6: 356553 | X6: 359847 | Y6: 363372 | Z6: 366935 | AA6: 370427 | AB6: 373475 | AC6: 375927 | AD6: 377982 | AE6: 379566 | AF6: 380107 | AG6: 379649 | AH6: 378672 | AI6: 377118 | AJ6: 374993 | AK6: 372429 | AL6: 369636 | AM6: 366753 | AN6: 363772 | AO6: 360776 | AP6: 357974 | AQ6: 355471 | AR6: 353326 | AS6: 351524 | AT6: 350062 | AU6: 348957 | AV6: 348177 | AW6: 347748 | AX6: 347683 | AY6: 347959 | AZ6: 348526 | BA6: 349315 | BB6: 350260 | BC6: 351339 | BD6: 352520 | BE6: 353747 | BF6: 354969 | BG6: 356141 | BH6: 357219 | BI6: 358158 | BJ6: 358926 | BK6: 359487 | BL6: 359817 | BM6: 359912 | BN6: 359763 | BO6: 359367 | BP6: 358743 | BQ6: 357918 | BR6: 356922 | BS6: 355802 | BT6: 354584 | BU6: 353323 | BV6: 352050 | BW6: 350815 | BX6: 349643 | BY6: 348583 | BZ6: 347639 | CA6: 346850 | CB6: 346214 | CC6: 345746 | CD6: 345444 | CE6: 345298 | CF6: 345301 | CG6: 345440 | CH6: 345692 | CI6: 346036 | CJ6: 346451 | CK6: 346905 | CL6: 347389 | CM6: 347865 | CN6: 348317 | CO6: 348721 | CP6: 349066 | CQ6: 349327 | CR6: 349508 | CS6: 349582 | CT6: 349559 | CU6: 349439 | CV6: 349216 | CW6: 348900 | CX6: 348513 | CY6: 348044
A7: 1 | B7: 5 | C7: 413937 | D7: 416893 | E7: 408892 | F7: 400471 | G7: 390564 | H7: 378575 | I7: 362003 | J7: 356598 | K7: 354693 | L7: 356380 | M7: 356706 | N7: 355717 | O7: 354891 | P7: 354210 | Q7: 353707 | R7: 353408 | S7: 353432 | T7: 353853 | U7: 354465 | V7: 355342 | W7: 356652 | X7: 358941 | Y7: 362235 | Z7: 365761 | AA7: 369323 | AB7: 372815 | AC7: 375864 | AD7: 378316 | AE7: 380371 | AF7: 381955 | AG7: 382497 | AH7: 382039 | AI7: 381062 | AJ7: 379509 | AK7: 377383 | AL7: 374818 | AM7: 372027 | AN7: 369145 | AO7: 366165 | AP7: 363169 | AQ7: 360367 | AR7: 357863 | AS7: 355718 | AT7: 353917 | AU7: 352455 | AV7: 351350 | AW7: 350572 | AX7: 350142 | AY7: 350075 | AZ7: 350353 | BA7: 350921 | BB7: 351709 | BC7: 352654 | BD7: 353734 | BE7: 354916 | BF7: 356143 | BG7: 357365 | BH7: 358536 | BI7: 359616 | BJ7: 360555 | BK7: 361322 | BL7: 361884 | BM7: 362214 | BN7: 362309 | BO7: 362160 | BP7: 361765 | BQ7: 361141 | BR7: 360316 | BS7: 359320 | BT7: 358201 | BU7: 356982 | BV7: 355722 | BW7: 354448 | BX7: 353213 | BY7: 352041 | BZ7: 350982 | CA7: 350037 | CB7: 349250 | CC7: 348614 | CD7: 348147 | CE7: 347844 | CF7: 347698 | CG7: 347701 | CH7: 347840 | CI7: 348092 | CJ7: 348436 | CK7: 348851 | CL7: 349306 | CM7: 349788 | CN7: 350264 | CO7: 350718 | CP7: 351122 | CQ7: 351467 | CR7: 351728 | CS7: 351908 | CT7: 351982 | CU7: 351959 | CV7: 351840 | CW7: 351616 | CX7: 351300 | CY7: 350914
A8: 1 | B8: 6 | C8: 416815 | D8: 415841 | E8: 420617 | F8: 411423 | G8: 402880 | H8: 392846 | I8: 380734 | J8: 364035 | K8: 358631 | L8: 356727 | M8: 358414 | N8: 358741 | O8: 357752 | P8: 356925 | Q8: 356246 | R8: 355743 | S8: 355445 | T8: 355469 | U8: 355890 | V8: 356501 | W8: 357379 | X8: 358690 | Y8: 360979 | Z8: 364273 | AA8: 367799 | AB8: 371361 | AC8: 374853 | AD8: 377902 | AE8: 380354 | AF8: 382408 | AG8: 383993 | AH8: 384535 | AI8: 384078 | AJ8: 383100 | AK8: 381548 | AL8: 379424 | AM8: 376858 | AN8: 374067 | AO8: 371185 | AP8: 368206 | AQ8: 365210 | AR8: 362408 | AS8: 359906 | AT8: 357760 | AU8: 355958 | AV8: 354497 | AW8: 353390 | AX8: 352614 | AY8: 352185 | AZ8: 352117 | BA8: 352396 | BB8: 352963 | BC8: 353752 | BD8: 354698 | BE8: 355778 | BF8: 356961 | BG8: 358188 | BH8: 359412 | BI8: 360582 | BJ8: 361662 | BK8: 362601 | BL8: 363368 | BM8: 363930 | BN8: 364260 | BO8: 364355 | BP8: 364206 | BQ8: 363811 | BR8: 363187 | BS8: 362362 | BT8: 361366 | BU8: 360249 | BV8: 359028 | BW8: 357770 | BX8: 356495 | BY8: 355259 | BZ8: 354088 | CA8: 353030 | CB8: 352084 | CC8: 351297 | CD8: 350660 | CE8: 350195 | CF8: 349892 | CG8: 349746 | CH8: 349749 | CI8: 349888 | CJ8: 350140 | CK8: 350484 | CL8: 350898 | CM8: 351355 | CN8: 351836 | CO8: 352311 | CP8: 352766 | CQ8: 353171 | CR8: 353515 | CS8: 353777 | CT8: 353957 | CU8: 354032 | CV8: 354007 | CW8: 353890 | CX8: 353665 | CY8: 353349
A9: 1 | B9: 7 | C9: 425759 | D9: 418508 | E9: 419150 | F9: 422867 | G9: 413563 | H9: 404907 | I9: 394763 | J9: 382539 | K9: 365842 | L9: 360438 | M9: 358534 | N9: 360222 | O9: 360551 | P9: 359562 | Q9: 358734 | R9: 358056 | S9: 357553 | T9: 357255 | U9: 357280 | V9: 357701 | W9: 358311 | X9: 359189 | Y9: 360500 | Z9: 362790 | AA9: 366084 | AB9: 369609 | AC9: 373173 | AD9: 376666 | AE9: 379714 | AF9: 382168 | AG9: 384220 | AH9: 385804 | AI9: 386346 | AJ9: 385891 | AK9: 384913 | AL9: 383361 | AM9: 381237 | AN9: 378672 | AO9: 375881 | AP9: 372999 | AQ9: 370021 | AR9: 367026 | AS9: 364223 | AT9: 361721 | AU9: 359576 | AV9: 357774 | AW9: 356314 | AX9: 355207 | AY9: 354432 | AZ9: 354003 | BA9: 353934 | BB9: 354214 | BC9: 354783 | BD9: 355572 | BE9: 356518 | BF9: 357597 | BG9: 358779 | BH9: 360007 | BI9: 361231 | BJ9: 362401 | BK9: 363481 | BL9: 364420 | BM9: 365187 | BN9: 365749 | BO9: 366079 | BP9: 366175 | BQ9: 366026 | BR9: 365631 | BS9: 365007 | BT9: 364182 | BU9: 363185 | BV9: 362069 | BW9: 360848 | BX9: 359589 | BY9: 358317 | BZ9: 357080 | CA9: 355910 | CB9: 354851 | CC9: 353905 | CD9: 353120 | CE9: 352481 | CF9: 352016 | CG9: 351713 | CH9: 351567 | CI9: 351572 | CJ9: 351711 | CK9: 351963 | CL9: 352306 | CM9: 352720 | CN9: 353178 | CO9: 353660 | CP9: 354135 | CQ9: 354588 | CR9: 354993 | CS9: 355337 | CT9: 355599 | CU9: 355778 | CV9: 355854 | CW9: 355828 | CX9: 355713 | CY9: 355488
A10: 1 | B10: 8 | C10: 438005 | D10: 427408 | E10: 421700 | F10: 421327 | G10: 424935 | H10: 415523 | I10: 406760 | J10: 396509 | K10: 384286 | L10: 367589 | M10: 362188 | N10: 360283 | O10: 361971 | P10: 362301 | Q10: 361311 | R10: 360484 | S10: 359807 | T10: 359304 | U10: 359006 | V10: 359032 | W10: 359455 | X10: 360065 | Y10: 360943 | Z10: 362252 | AA10: 364542 | AB10: 367837 | AC10: 371362 | AD10: 374924 | AE10: 378418 | AF10: 381465 | AG10: 383921 | AH10: 385974 | AI10: 387557 | AJ10: 388100 | AK10: 387645 | AL10: 386667 | AM10: 385116 | AN10: 382992 | AO10: 380427 | AP10: 377635 | AQ10: 374753 | AR10: 371775 | AS10: 368781 | AT10: 365978 | AU10: 363477 | AV10: 361331 | AW10: 359530 | AX10: 358071 | AY10: 356963 | AZ10: 356189 | BA10: 355761 | BB10: 355693 | BC10: 355972 | BD10: 356541 | BE10: 357330 | BF10: 358276 | BG10: 359357 | BH10: 360538 | BI10: 361767 | BJ10: 362991 | BK10: 364161 | BL10: 365241 | BM10: 366179 | BN10: 366946 | BO10: 367508 | BP10: 367838 | BQ10: 367934 | BR10: 367785 | BS10: 367391 | BT10: 366766 | BU10: 365942 | BV10: 364945 | BW10: 363830 | BX10: 362609 | BY10: 361349 | BZ10: 360078 | CA10: 358840 | CB10: 357671 | CC10: 356612 | CD10: 355665 | CE10: 354881 | CF10: 354242 | CG10: 353777 | CH10: 353475 | CI10: 353328 | CJ10: 353333 | CK10: 353472 | CL10: 353725 | CM10: 354068 | CN10: 354482 | CO10: 354939 | CP10: 355420 | CQ10: 355896 | CR10: 356350 | CS10: 356756 | CT10: 357099 | CU10: 357362 | CV10: 357541 | CW10: 357616 | CX10: 357590 | CY10: 357475
A11: 1 | B11: 9 | C11: 431442 | D11: 439703 | E11: 430636 | F11: 423911 | G11: 423429 | H11: 426925 | I11: 417404 | J11: 408530 | K11: 398280 | L11: 386059 | M11: 369362 | N11: 363962 | O11: 362057 | P11: 363744 | Q11: 364076 | R11: 363086 | S11: 362259 | T11: 361583 | U11: 361080 | V11: 360782 | W11: 360810 | X11: 361232 | Y11: 361843 | Z11: 362722 | AA11: 364030 | AB11: 366320 | AC11: 369614 | AD11: 373140 | AE11: 376703 | AF11: 380196 | AG11: 383243 | AH11: 385699 | AI11: 387751 | AJ11: 389335 | AK11: 389878 | AL11: 389424 | AM11: 388445 | AN11: 386894 | AO11: 384770 | AP11: 382207 | AQ11: 379416 | AR11: 376532 | AS11: 373553 | AT11: 370561 | AU11: 367757 | AV11: 365259 | AW11: 363113 | AX11: 361312 | AY11: 359853 | AZ11: 358746 | BA11: 357972 | BB11: 357545 | BC11: 357477 | BD11: 357756 | BE11: 358326 | BF11: 359115 | BG11: 360059 | BH11: 361140 | BI11: 362321 | BJ11: 363550 | BK11: 364774 | BL11: 365944 | BM11: 367025 | BN11: 367963 | BO11: 368730 | BP11: 369292 | BQ11: 369623 | BR11: 369719 | BS11: 369569 | BT11: 369176 | BU11: 368551 | BV11: 367727 | BW11: 366729 | BX11: 365615 | BY11: 364394 | BZ11: 363133 | CA11: 361864 | CB11: 360626 | CC11: 359457 | CD11: 358398 | CE11: 357451 | CF11: 356667 | CG11: 356028 | CH11: 355561 | CI11: 355259 | CJ11: 355113 | CK11: 355118 | CL11: 355257 | CM11: 355510 | CN11: 355854 | CO11: 356268 | CP11: 356725 | CQ11: 357206 | CR11: 357681 | CS11: 358136 | CT11: 358543 | CU11: 358884 | CV11: 359147 | CW11: 359328 | CX11: 359403 | CY11: 359376
