Workbook
Name _DLX1.INC: HAVERA!$A$2:$BN$7

Sheet Chart Data
A1: Budget policy decisions | I1: Fiscal rules | U1: Fiscal rules | AA1: Public sector net investment | AH1: OBR estimates of fiscal tightening | AM1: NICs impact
K2: Levels | P2: Diff | V2: Public sector net debt | W2: Public sector net debt (ex BoE) | X2: Public sector net financial liabilities | Y2: Public sector net worth | AN2: GDP | AR2: ER | AV2: ETILO | AZ2: UPILO | BD2: TP
B3: 2024-2025 | C3: 2025-2026 | D3: 2026-2027 | E3: 2027-2028 | F3: 2028-2029 | G3: 2029-2030 | K3: Public sector net debt | L3: Public sector net debt (ex BoE) | M3: Public sector net financial liabilities | N3: Public sector net worth (inverted) | P3: Public sector net debt | Q3: Public sector net debt (ex BoE) | R3: Public sector net financial liabilities | S3: Public sector net worth (inverted) | V3: Public sector net debt | W3: Public sector net debt (ex BoE) | X3: Public sector net financial liabilities | Y3: Public sector net worth (inverted) | AC3: Budget (Oct24) | AD3: Budget (Mar24) | AE3: UK average (2004-2023) | AF3: OECD average | AJ3: Budget (Oct24) | AK3: Budget (Mar24) | AN3: Baseline | AO3: Scenario | AP3: Diff | AR3: Baseline | AS3: Scenario | AT3: Diff | AV3: Baseline | AW3: Scenario | AX3: Diff | AZ3: Baseline | BA3: Scenario | BB3: Diff | BD3: Baseline | BE3: Scenario | BF3: Diff
A4: Tax | B4: ='HMT - Table 5.1'!F88 -> 1160 | C4: ='HMT - Table 5.1'!G88 -> 24005 | D4: ='HMT - Table 5.1'!H88 -> 34785 | E4: ='HMT - Table 5.1'!I88 -> 39065 | F4: ='HMT - Table 5.1'!J88 -> 39725 | G4: ='HMT - Table 5.1'!K88 -> 41170 | I4: 2000-01 | J4: =LEFT(I4,4) -> 2000 | K4: {=TRANSPOSE('C6.11'!D26:AG29)} -> 28.3 | L4: 28.4 | M4: 26.955398 | N4: 32.43637 | U4: 2029-2030 | V4: =-(P33/100)*$V$7 -> 6.6405827 | W4: =-(Q33/100)*$V$7 -> -5.7796597 | X4: =-(R33/100)*$V$7 -> 15.747235 | Y4: =-(S33/100)*$V$7 -> 16.945561 | AA4: ='Aggregates (% GDP) Oct24'!B57 -> 2000-01 | AB4: =LEFT(AA4,4) -> 2000 | AC4: ='Aggregates (% GDP) Oct24'!F57 -> 0.40470502 | AD4: ='Aggregates (% GDP) Mar24'!F57 -> 0.40470502 | AE4: =AVERAGE($AD$8:$AD$27) -> 2.145275 | AH4: ='Aggregates (% GDP) Oct24'!B57 -> 2000-01 | AI4: =LEFT(AH4,4) -> 2000 | AJ4: =-('Aggregates (% GDP) Oct24'!M57-'Aggregates (% GDP) Oct24'!M56) -> -0.014492648 | AM4: 2024 | AN4: =100*((DataCY!B51/DataCY!B50)-1) -> 0.98266797 | AO4: =100*((DataCY!H51/DataCY!H50)-1) -> 0.98266797 | AP4: =AO4-AN4 -> 0 | AR4: =100*((DataCY!D51/DataCY!D50)-1) -> 4.2451725 | AS4: =100*((DataCY!J51/DataCY!J50)-1) -> 4.2451725 | AT4: =AS4-AR4 -> 0 | AV4: =DataCY!C51 -> 33138.705 | AW4: =DataCY!I51 -> 33138.705 | AX4: =AW4-AV4 -> 0 | AZ4: =DataCY!E51 -> 4.2879467 | BA4: =DataCY!K51 -> 4.2879467 | BB4: =BA4-AZ4 -> 0 | BD4: =DataFY!G51 -> 152663.25 | BE4: =DataFY!M51 -> 152663.25 | BF4: =BE4-BD4 -> 0
A5: Current spending | B5: ='HMT - Table 5.1'!F87-'Chart Data'!B6 -> -27630 | C5: ='HMT - Table 5.1'!G87-'Chart Data'!C6 -> -48190 | D5: ='HMT - Table 5.1'!H87-'Chart Data'!D6 -> -50675 | E5: ='HMT - Table 5.1'!I87-'Chart Data'!E6 -> -51825 | F5: ='HMT - Table 5.1'!J87-'Chart Data'!F6 -> -52805 | G5: ='HMT - Table 5.1'!K87-'Chart Data'!G6 -> -51035 | I5: 2001-02 | J5: =LEFT(I5,4) -> 2001 | K5: 28.1 | L5: 28.2 | M5: 28.366806 | N5: 34.14847 | P5: =K5-K4 -> -0.2 | Q5: =L5-L4 -> -0.2 | R5: =M5-M4 -> 1.4114071 | S5: =N5-N4 -> 1.7120996 | AA5: ='Aggregates (% GDP) Oct24'!B58 -> 2001-02 | AB5: =LEFT(AA5,4) -> 2001 | AC5: ='Aggregates (% GDP) Oct24'!F58 -> 1.0969634 | AD5: ='Aggregates (% GDP) Mar24'!F58 -> 1.0969634 | AE5: =AVERAGE($AD$8:$AD$27) -> 2.145275 | AH5: ='Aggregates (% GDP) Oct24'!B58 -> 2001-02 | AI5: =LEFT(AH5,4) -> 2001 | AJ5: =-('Aggregates (% GDP) Oct24'!M58-'Aggregates (% GDP) Oct24'!M57) -> 1.9591308 | AM5: 2025 | AN5: =100*((DataCY!B52/DataCY!B51)-1) -> 1.5341097 | AO5: =100*((DataCY!H52/DataCY!H51)-1) -> 1.39618 | AP5: =AO5-AN5 -> -0.13792967 | AR5: =100*((DataCY!D52/DataCY!D51)-1) -> 3.5514545 | AS5: =100*((DataCY!J52/DataCY!J51)-1) -> 3.478492 | AT5: =AS5-AR5 -> -0.072962485 | AV5: =DataCY!C52 -> 33430.338 | AW5: =DataCY!I52 -> 33403.51 | AX5: =AW5-AV5 -> -26.8275 | AZ5: =DataCY!E52 -> 4.3347963 | BA5: =DataCY!K52 -> 4.4113922 | BB5: =BA5-AZ5 -> 0.076596 | BD5: =DataFY!G52 -> 159368.98 | BE5: =DataFY!M52 -> 182720.43 | BF5: =BE5-BD5 -> 23351.45
A6: Capital spending | B6: ='HMT - Table 5.1'!F5 -> 1765 | C6: ='HMT - Table 5.1'!G5 -> -15360 | D6: ='HMT - Table 5.1'!H5 -> -19440 | E6: ='HMT - Table 5.1'!I5 -> -23820 | F6: ='HMT - Table 5.1'!J5 -> -25695 | G6: ='HMT - Table 5.1'!K5 -> -23125 | I6: 2002-03 | J6: =LEFT(I6,4) -> 2002 | K6: 29.8 | L6: 29.9 | M6: 31.350052 | N6: 36.652789 | P6: =K6-K5 -> 1.7 | Q6: =L6-L5 -> 1.7 | R6: =M6-M5 -> 2.9832465 | S6: =N6-N5 -> 2.5043195 | U6: Change % of GDP | AA6: ='Aggregates (% GDP) Oct24'!B59 -> 2002-03 | AB6: =LEFT(AA6,4) -> 2002 | AC6: ='Aggregates (% GDP) Oct24'!F59 -> 1.4448275 | AD6: ='Aggregates (% GDP) Mar24'!F59 -> 1.4448275 | AE6: =AVERAGE($AD$8:$AD$27) -> 2.145275 | AH6: ='Aggregates (% GDP) Oct24'!B59 -> 2002-03 | AI6: =LEFT(AH6,4) -> 2002 | AJ6: =-('Aggregates (% GDP) Oct24'!M59-'Aggregates (% GDP) Oct24'!M58) -> 2.0383229 | AM6: 2026 | AN6: =100*((DataCY!B53/DataCY!B52)-1) -> 1.631252 | AO6: =100*((DataCY!H53/DataCY!H52)-1) -> 1.5073108 | AP6: =AO6-AN6 -> -0.12394115 | AR6: =100*((DataCY!D53/DataCY!D52)-1) -> 2.6851513 | AS6: =100*((DataCY!J53/DataCY!J52)-1) -> 2.5624237 | AT6: =AS6-AR6 -> -0.12272757 | AV6: =DataCY!C53 -> 33874.042 | AW6: =DataCY!I53 -> 33820.61 | AX6: =AW6-AV6 -> -53.4325 | AZ6: =DataCY!E53 -> 4.127162 | BA6: =DataCY!K53 -> 4.2783833 | BB6: =BA6-AZ6 -> 0.15122125 | BD6: =DataFY!G53 -> 166351.45 | BE6: =DataFY!M53 -> 189385.05 | BF6: =BE6-BD6 -> 23033.6
A7: Total | B7: =SUM(B4:B6) -> -24705 | C7: =SUM(C4:C6) -> -39545 | D7: =SUM(D4:D6) -> -35330 | E7: =SUM(E4:E6) -> -36580 | F7: =SUM(F4:F6) -> -38775 | G7: =SUM(G4:G6) -> -32990 | I7: 2003-04 | J7: =LEFT(I7,4) -> 2003 | K7: 30.9 | L7: 31 | M7: 31.244827 | N7: 37.45462 | P7: =K7-K6 -> 1.1 | Q7: =L7-L6 -> 1.1 | R7: =M7-M6 -> -0.10522481 | S7: =N7-N6 -> 0.80183026 | U7: GDP! | V7: 3459.596 | AA7: ='Aggregates (% GDP) Oct24'!B60 -> 2003-04 | AB7: =LEFT(AA7,4) -> 2003 | AC7: ='Aggregates (% GDP) Oct24'!F60 -> 1.6922036 | AD7: ='Aggregates (% GDP) Mar24'!F60 -> 1.6922036 | AE7: =AVERAGE($AD$8:$AD$27) -> 2.145275 | AH7: ='Aggregates (% GDP) Oct24'!B60 -> 2003-04 | AI7: =LEFT(AH7,4) -> 2003 | AJ7: =-('Aggregates (% GDP) Oct24'!M60-'Aggregates (% GDP) Oct24'!M59) -> 0.4553037 | AM7: 2027 | AN7: =100*((DataCY!B54/DataCY!B53)-1) -> 1.6566706 | AO7: =100*((DataCY!H54/DataCY!H53)-1) -> 1.6837409 | AP7: =AO7-AN7 -> 0.027070292 | AR7: =100*((DataCY!D54/DataCY!D53)-1) -> 2.5895984 | AS7: =100*((DataCY!J54/DataCY!J53)-1) -> 2.6013744 | AT7: =AS7-AR7 -> 0.011775959 | AV7: =DataCY!C54 -> 34275.132 | AW7: =DataCY!I54 -> 34229.768 | AX7: =AW7-AV7 -> -45.365 | AZ7: =DataCY!E54 -> 3.940423 | BA7: =DataCY!K54 -> 4.0675903 | BB7: =BA7-AZ7 -> 0.12716725 | BD7: =DataFY!G54 -> 173561.32 | BE7: =DataFY!M54 -> 197158.96 | BF7: =BE7-BD7 -> 23597.64
I8: 2004-05 | J8: =LEFT(I8,4) -> 2004 | K8: 33.5 | L8: 33.6 | M8: 33.412416 | N8: 37.390259 | P8: =K8-K7 -> 2.6 | Q8: =L8-L7 -> 2.6 | R8: =M8-M7 -> 2.1675887 | S8: =N8-N7 -> -0.064360255 | AA8: ='Aggregates (% GDP) Oct24'!B61 -> 2004-05 | AB8: =LEFT(AA8,4) -> 2004 | AC8: ='Aggregates (% GDP) Oct24'!F61 -> 2.0459664 | AD8: ='Aggregates (% GDP) Mar24'!F61 -> 2.0459664 | AE8: =AVERAGE($AD$8:$AD$27) -> 2.145275 | AH8: ='Aggregates (% GDP) Oct24'!B61 -> 2004-05 | AI8: =LEFT(AH8,4) -> 2004 | AJ8: =-('Aggregates (% GDP) Oct24'!M61-'Aggregates (% GDP) Oct24'!M60) -> 0.50237965 | AM8: 2028 | AN8: =100*((DataCY!B55/DataCY!B54)-1) -> 1.6473682 | AO8: =100*((DataCY!H55/DataCY!H54)-1) -> 1.6778525 | AP8: =AO8-AN8 -> 0.030484248 | AR8: =100*((DataCY!D55/DataCY!D54)-1) -> 2.591253 | AS8: =100*((DataCY!J55/DataCY!J54)-1) -> 2.6296951 | AT8: =AS8-AR8 -> 0.038442166 | AV8: =DataCY!C55 -> 34669.898 | AW8: =DataCY!I55 -> 34633.96 | AX8: =AW8-AV8 -> -35.9375 | AZ8: =DataCY!E55 -> 3.7972135 | BA8: =DataCY!K55 -> 3.8969493 | BB8: =BA8-AZ8 -> 0.09973575 | BD8: =DataFY!G55 -> 180390.25 | BE8: =DataFY!M55 -> 204855.91 | BF8: =BE8-BD8 -> 24465.66
A9: check | B9: ='HMT - Table 5.1'!F86 -> -24705 | C9: ='HMT - Table 5.1'!G86 -> -39550 | D9: ='HMT - Table 5.1'!H86 -> -35330 | E9: ='HMT - Table 5.1'!I86 -> -36585 | F9: ='HMT - Table 5.1'!J86 -> -38775 | G9: ='HMT - Table 5.1'!K86 -> -32990 | I9: 2005-06 | J9: =LEFT(I9,4) -> 2005 | K9: 34.3 | L9: 34.5 | M9: 32.378335 | N9: 34.942387 | P9: =K9-K8 -> 0.8 | Q9: =L9-L8 -> 0.9 | R9: =M9-M8 -> -1.0340813 | S9: =N9-N8 -> -2.4478726 | W9: Diff | X9: £bn | Y9: =X4-W4 -> 21.526895 | AA9: ='Aggregates (% GDP) Oct24'!B62 -> 2005-06 | AB9: =LEFT(AA9,4) -> 2005 | AC9: ='Aggregates (% GDP) Oct24'!F62 -> 1.8521352 | AD9: ='Aggregates (% GDP) Mar24'!F62 -> 1.8521352 | AE9: =AVERAGE($AD$8:$AD$27) -> 2.145275 | AH9: ='Aggregates (% GDP) Oct24'!B62 -> 2005-06 | AI9: =LEFT(AH9,4) -> 2005 | AJ9: =-('Aggregates (% GDP) Oct24'!M62-'Aggregates (% GDP) Oct24'!M61) -> -0.69717717 | AM9: 2029 | AN9: =100*((DataCY!B56/DataCY!B55)-1) -> 1.6121887 | AO9: =100*((DataCY!H56/DataCY!H55)-1) -> 1.6514389 | AP9: =AO9-AN9 -> 0.039250219 | AR9: =100*((DataCY!D56/DataCY!D55)-1) -> 2.649545 | AS9: =100*((DataCY!J56/DataCY!J55)-1) -> 2.6857202 | AT9: =AS9-AR9 -> 0.036175242 | AV9: =DataCY!C56 -> 35019.358 | AW9: =DataCY!I56 -> 34992.588 | AX9: =AW9-AV9 -> -26.77 | AZ9: =DataCY!E56 -> 3.749889 | BA9: =DataCY!K56 -> 3.8234867 | BB9: =BA9-AZ9 -> 0.07359775 | BD9: =DataFY!G56 -> 187169.91 | BE9: =DataFY!M56 -> 212530.68 | BF9: =BE9-BD9 -> 25360.77
I10: 2006-07 | J10: =LEFT(I10,4) -> 2006 | K10: 35.1 | L10: 35.3 | M10: 32.440742 | N10: 35.127873 | P10: =K10-K9 -> 0.8 | Q10: =L10-L9 -> 0.8 | R10: =M10-M9 -> 0.062407551 | S10: =N10-N9 -> 0.18548609 | X10: % of GDP | Y10: =R33-Q33 -> -0.62223726 | AA10: ='Aggregates (% GDP) Oct24'!B63 -> 2006-07 | AB10: =LEFT(AA10,4) -> 2006 | AC10: ='Aggregates (% GDP) Oct24'!F63 -> 1.8163774 | AD10: ='Aggregates (% GDP) Mar24'!F63 -> 1.8163774 | AE10: =AVERAGE($AD$8:$AD$27) -> 2.145275 | AH10: ='Aggregates (% GDP) Oct24'!B63 -> 2006-07 | AI10: =LEFT(AH10,4) -> 2006 | AJ10: =-('Aggregates (% GDP) Oct24'!M63-'Aggregates (% GDP) Oct24'!M62) -> -0.71890443 | AM10: 2030 | AN10: =100*((DataCY!B57/DataCY!B56)-1) -> 1.6097059 | AO10: =100*((DataCY!H57/DataCY!H56)-1) -> 1.6548179 | AP10: =AO10-AN10 -> 0.045112052 | AR10: =100*((DataCY!D57/DataCY!D56)-1) -> 2.7035181 | AS10: =100*((DataCY!J57/DataCY!J56)-1) -> 2.7420534 | AT10: =AS10-AR10 -> 0.038535354 | AV10: =DataCY!C57 -> 35334.71 | AW10: =DataCY!I57 -> 35317.572 | AX10: =AW10-AV10 -> -17.1375 | AZ10: =DataCY!E57 -> 3.7498765 | BA10: =DataCY!K57 -> 3.7965653 | BB10: =BA10-AZ10 -> 0.04668875
A11: GDP! | B11: 2814.6771 | C11: 2950.0172 | D11: 3059.3962 | E11: 3167.3346 | F11: 3279.0494 | G11: 3397.2814 | I11: 2007-08 | J11: =LEFT(I11,4) -> 2007 | K11: 35.6 | L11: 35.8 | M11: 34.196775 | N11: 37.427136 | P11: =K11-K10 -> 0.5 | Q11: =L11-L10 -> 0.5 | R11: =M11-M10 -> 1.7560329 | S11: =N11-N10 -> 2.2992633 | AA11: ='Aggregates (% GDP) Oct24'!B64 -> 2007-08 | AB11: =LEFT(AA11,4) -> 2007 | AC11: ='Aggregates (% GDP) Oct24'!F64 -> 1.7924771 | AD11: ='Aggregates (% GDP) Mar24'!F64 -> 1.7924771 | AE11: =AVERAGE($AD$8:$AD$27) -> 2.145275 | AH11: ='Aggregates (% GDP) Oct24'!B64 -> 2007-08 | AI11: =LEFT(AH11,4) -> 2007 | AJ11: =-('Aggregates (% GDP) Oct24'!M64-'Aggregates (% GDP) Oct24'!M63) -> 0.49578275
I12: 2008-09 | J12: =LEFT(I12,4) -> 2008 | K12: 50.6 | L12: 50.6 | M12: 47.544202 | N12: 46.938699 | P12: =K12-K11 -> 15 | Q12: =L12-L11 -> 14.8 | R12: =M12-M11 -> 13.347427 | S12: =N12-N11 -> 9.5115631 | AA12: ='Aggregates (% GDP) Oct24'!B65 -> 2008-09 | AB12: =LEFT(AA12,4) -> 2008 | AC12: ='Aggregates (% GDP) Oct24'!F65 -> 3.0053462 | AD12: ='Aggregates (% GDP) Mar24'!F65 -> 3.0053462 | AE12: =AVERAGE($AD$8:$AD$27) -> 2.145275 | AH12: ='Aggregates (% GDP) Oct24'!B65 -> 2008-09 | AI12: =LEFT(AH12,4) -> 2008 | AJ12: =-('Aggregates (% GDP) Oct24'!M65-'Aggregates (% GDP) Oct24'!M64) -> 3.6279951
A13: % of GDP | I13: 2009-10 | J13: =LEFT(I13,4) -> 2009 | K13: 64.7 | L13: 63.9 | M13: 54.597887 | N13: 54.07218 | P13: =K13-K12 -> 14.1 | Q13: =L13-L12 -> 13.3 | R13: =M13-M12 -> 7.0536849 | S13: =N13-N12 -> 7.1334808 | AA13: ='Aggregates (% GDP) Oct24'!B66 -> 2009-10 | AB13: =LEFT(AA13,4) -> 2009 | AC13: ='Aggregates (% GDP) Oct24'!F66 -> 3.0029004 | AD13: ='Aggregates (% GDP) Mar24'!F66 -> 3.0029004 | AE13: =AVERAGE($AD$8:$AD$27) -> 2.145275 | AH13: ='Aggregates (% GDP) Oct24'!B66 -> 2009-10 | AI13: =LEFT(AH13,4) -> 2009 | AJ13: =-('Aggregates (% GDP) Oct24'!M66-'Aggregates (% GDP) Oct24'!M65) -> 1.4319908
A14: Tax | B14: =100*((B4/1000)/B$11) -> 0.041212542 | C14: =100*((C4/1000)/C$11) -> 0.81372406 | D14: =100*((D4/1000)/D$11) -> 1.1369891 | E14: =100*((E4/1000)/E$11) -> 1.2333714 | F14: =100*((F4/1000)/F$11) -> 1.2114791 | G14: =100*((G4/1000)/G$11) -> 1.2118513 | I14: 2010-11 | J14: =LEFT(I14,4) -> 2010 | K14: 70.9 | L14: 70.6 | M14: 58.946492 | N14: 49.558414 | P14: =K14-K13 -> 6.2 | Q14: =L14-L13 -> 6.7 | R14: =M14-M13 -> 4.3486046 | S14: =N14-N13 -> -4.5137655 | AA14: ='Aggregates (% GDP) Oct24'!B67 -> 2010-11 | AB14: =LEFT(AA14,4) -> 2010 | AC14: ='Aggregates (% GDP) Oct24'!F67 -> 2.4446147 | AD14: ='Aggregates (% GDP) Mar24'!F67 -> 2.4446147 | AE14: =AVERAGE($AD$8:$AD$27) -> 2.145275 | AH14: ='Aggregates (% GDP) Oct24'!B67 -> 2010-11 | AI14: =LEFT(AH14,4) -> 2010 | AJ14: =-('Aggregates (% GDP) Oct24'!M67-'Aggregates (% GDP) Oct24'!M66) -> -2.2415985
A15: Current spending | B15: =100*((B5/1000)/B$11) -> -0.98164012 | C15: =100*((C5/1000)/C$11) -> -1.6335498 | D15: =100*((D5/1000)/D$11) -> -1.6563726 | E15: =100*((E5/1000)/E$11) -> -1.6362338 | F15: =100*((F5/1000)/F$11) -> -1.6103752 | G15: =100*((G5/1000)/G$11) -> -1.5022306 | I15: 2011-12 | J15: =LEFT(I15,4) -> 2011 | K15: 74.3 | L15: 74.6 | M15: 65.016918 | N15: 54.680429 | P15: =K15-K14 -> 3.4 | Q15: =L15-L14 -> 4 | R15: =M15-M14 -> 6.0704267 | S15: =N15-N14 -> 5.1220142 | AA15: ='Aggregates (% GDP) Oct24'!B68 -> 2011-12 | AB15: =LEFT(AA15,4) -> 2011 | AC15: ='Aggregates (% GDP) Oct24'!F68 -> 1.8421103 | AD15: ='Aggregates (% GDP) Mar24'!F68 -> 1.8421103 | AE15: =AVERAGE($AD$8:$AD$27) -> 2.145275 | AH15: ='Aggregates (% GDP) Oct24'!B68 -> 2011-12 | AI15: =LEFT(AH15,4) -> 2011 | AJ15: =-('Aggregates (% GDP) Oct24'!M68-'Aggregates (% GDP) Oct24'!M67) -> -1.4113887
A16: Capital spending | B16: =100*((B6/1000)/B$11) -> 0.062707015 | C16: =100*((C6/1000)/C$11) -> -0.52067492 | D16: =100*((D6/1000)/D$11) -> -0.6354195 | E16: =100*((E6/1000)/E$11) -> -0.7520519 | F16: =100*((F6/1000)/F$11) -> -0.78361125 | G16: =100*((G6/1000)/G$11) -> -0.68069133 | I16: 2012-13 | J16: =LEFT(I16,4) -> 2012 | K16: 77.5 | L16: 76.2 | M16: 69.72436 | N16: 58.751603 | P16: =K16-K15 -> 3.2 | Q16: =L16-L15 -> 1.6 | R16: =M16-M15 -> 4.7074411 | S16: =N16-N15 -> 4.0711743 | AA16: ='Aggregates (% GDP) Oct24'!B69 -> 2012-13 | AB16: =LEFT(AA16,4) -> 2012 | AC16: ='Aggregates (% GDP) Oct24'!F69 -> 1.8798625 | AD16: ='Aggregates (% GDP) Mar24'!F69 -> 1.8798625 | AE16: =AVERAGE($AD$8:$AD$27) -> 2.145275 | AH16: ='Aggregates (% GDP) Oct24'!B69 -> 2012-13 | AI16: =LEFT(AH16,4) -> 2012 | AJ16: =-('Aggregates (% GDP) Oct24'!M69-'Aggregates (% GDP) Oct24'!M68) -> 0.44780765
A17: Total | B17: =100*((B7/1000)/B$11) -> -0.87772057 | C17: =100*((C7/1000)/C$11) -> -1.3405006 | D17: =100*((D7/1000)/D$11) -> -1.154803 | E17: =100*((E7/1000)/E$11) -> -1.1549143 | F17: =100*((F7/1000)/F$11) -> -1.1825073 | G17: =100*((G7/1000)/G$11) -> -0.97107057 | I17: 2013-14 | J17: =LEFT(I17,4) -> 2013 | K17: 79.2 | L17: 77 | M17: 70.718374 | N17: 56.326968 | P17: =K17-K16 -> 1.7 | Q17: =L17-L16 -> 0.8 | R17: =M17-M16 -> 0.99401484 | S17: =N17-N16 -> -2.4246345 | AA17: ='Aggregates (% GDP) Oct24'!B70 -> 2013-14 | AB17: =LEFT(AA17,4) -> 2013 | AC17: ='Aggregates (% GDP) Oct24'!F70 -> 1.4526683 | AD17: ='Aggregates (% GDP) Mar24'!F70 -> 1.4526683 | AE17: =AVERAGE($AD$8:$AD$27) -> 2.145275 | AH17: ='Aggregates (% GDP) Oct24'!B70 -> 2013-14 | AI17: =LEFT(AH17,4) -> 2013 | AJ17: =-('Aggregates (% GDP) Oct24'!M70-'Aggregates (% GDP) Oct24'!M69) -> -0.91274837
I18: 2014-15 | J18: =LEFT(I18,4) -> 2014 | K18: 81.6 | L18: 79.2 | M18: 72.913428 | N18: 53.4578 | P18: =K18-K17 -> 2.4 | Q18: =L18-L17 -> 2.2 | R18: =M18-M17 -> 2.1950537 | S18: =N18-N17 -> -2.8691685 | AA18: ='Aggregates (% GDP) Oct24'!B71 -> 2014-15 | AB18: =LEFT(AA18,4) -> 2014 | AC18: ='Aggregates (% GDP) Oct24'!F71 -> 1.929131 | AD18: ='Aggregates (% GDP) Mar24'!F71 -> 1.929131 | AE18: =AVERAGE($AD$8:$AD$27) -> 2.145275 | AH18: ='Aggregates (% GDP) Oct24'!B71 -> 2014-15 | AI18: =LEFT(AH18,4) -> 2014 | AJ18: =-('Aggregates (% GDP) Oct24'!M71-'Aggregates (% GDP) Oct24'!M70) -> 0.36659488
I19: 2015-16 | J19: =LEFT(I19,4) -> 2015 | K19: 81.3 | L19: 78.9 | M19: 73.981933 | N19: 51.950634 | P19: =K19-K18 -> -0.3 | Q19: =L19-L18 -> -0.3 | R19: =M19-M18 -> 1.0685047 | S19: =N19-N18 -> -1.5071661 | AA19: ='Aggregates (% GDP) Oct24'!B72 -> 2015-16 | AB19: =LEFT(AA19,4) -> 2015 | AC19: ='Aggregates (% GDP) Oct24'!F72 -> 1.6691683 | AD19: ='Aggregates (% GDP) Mar24'!F72 -> 1.6691683 | AE19: =AVERAGE($AD$8:$AD$27) -> 2.145275 | AH19: ='Aggregates (% GDP) Oct24'!B72 -> 2015-16 | AI19: =LEFT(AH19,4) -> 2015 | AJ19: =-('Aggregates (% GDP) Oct24'!M72-'Aggregates (% GDP) Oct24'!M71) -> -0.50198668
I20: 2016-17 | J20: =LEFT(I20,4) -> 2016 | K20: 83.5 | L20: 77.4 | M20: 74.221682 | N20: 61.429268 | P20: =K20-K19 -> 2.2 | Q20: =L20-L19 -> -1.5 | R20: =M20-M19 -> 0.23974945 | S20: =N20-N19 -> 9.4786344 | AA20: ='Aggregates (% GDP) Oct24'!B73 -> 2016-17 | AB20: =LEFT(AA20,4) -> 2016 | AC20: ='Aggregates (% GDP) Oct24'!F73 -> 1.8101862 | AD20: ='Aggregates (% GDP) Mar24'!F73 -> 1.8101862 | AE20: =AVERAGE($AD$8:$AD$27) -> 2.145275 | AH20: ='Aggregates (% GDP) Oct24'!B73 -> 2016-17 | AI20: =LEFT(AH20,4) -> 2016 | AJ20: =-('Aggregates (% GDP) Oct24'!M73-'Aggregates (% GDP) Oct24'!M72) -> -1.4760005
I21: 2017-18 | J21: =LEFT(I21,4) -> 2017 | K21: 82.3 | L21: 73.7 | M21: 70.188464 | N21: 63.049303 | P21: =K21-K20 -> -1.2 | Q21: =L21-L20 -> -3.7 | R21: =M21-M20 -> -4.0332186 | S21: =N21-N20 -> 1.6200343 | AA21: ='Aggregates (% GDP) Oct24'!B74 -> 2017-18 | AB21: =LEFT(AA21,4) -> 2017 | AC21: ='Aggregates (% GDP) Oct24'!F74 -> 2.2089205 | AD21: ='Aggregates (% GDP) Mar24'!F74 -> 2.2089205 | AE21: =AVERAGE($AD$8:$AD$27) -> 2.145275 | AH21: ='Aggregates (% GDP) Oct24'!B74 -> 2017-18 | AI21: =LEFT(AH21,4) -> 2017 | AJ21: =-('Aggregates (% GDP) Oct24'!M74-'Aggregates (% GDP) Oct24'!M73) -> 0.080590287
I22: 2018-19 | J22: =LEFT(I22,4) -> 2018 | K22: 80.3 | L22: 72.3 | M22: 66.982374 | N22: 58.905421 | P22: =K22-K21 -> -2 | Q22: =L22-L21 -> -1.4 | R22: =M22-M21 -> -3.2060891 | S22: =N22-N21 -> -4.1438817 | AA22: ='Aggregates (% GDP) Oct24'!B75 -> 2018-19 | AB22: =LEFT(AA22,4) -> 2018 | AC22: ='Aggregates (% GDP) Oct24'!F75 -> 2.100128 | AD22: ='Aggregates (% GDP) Mar24'!F75 -> 2.100128 | AE22: =AVERAGE($AD$8:$AD$27) -> 2.145275 | AH22: ='Aggregates (% GDP) Oct24'!B75 -> 2018-19 | AI22: =LEFT(AH22,4) -> 2018 | AJ22: =-('Aggregates (% GDP) Oct24'!M75-'Aggregates (% GDP) Oct24'!M74) -> -0.22729184
I23: 2019-20 | J23: =LEFT(I23,4) -> 2019 | K23: 85.2 | L23: 77.1 | M23: 74.576335 | N23: 67.191349 | P23: =K23-K22 -> 4.9 | Q23: =L23-L22 -> 4.8 | R23: =M23-M22 -> 7.5939601 | S23: =N23-N22 -> 8.2859278 | AA23: ='Aggregates (% GDP) Oct24'!B76 -> 2019-20 | AB23: =LEFT(AA23,4) -> 2019 | AC23: ='Aggregates (% GDP) Oct24'!F76 -> 1.8937327 | AD23: ='Aggregates (% GDP) Mar24'!F76 -> 1.8960049 | AE23: =AVERAGE($AD$8:$AD$27) -> 2.145275 | AH23: ='Aggregates (% GDP) Oct24'!B76 -> 2019-20 | AI23: =LEFT(AH23,4) -> 2019 | AJ23: =-('Aggregates (% GDP) Oct24'!M76-'Aggregates (% GDP) Oct24'!M75) -> 1.0124527
I24: 2020-21 | J24: =LEFT(I24,4) -> 2020 | K24: 96.5 | L24: 86.5 | M24: 83.079863 | N24: 73.560623 | P24: =K24-K23 -> 11.3 | Q24: =L24-L23 -> 9.4 | R24: =M24-M23 -> 8.5035288 | S24: =N24-N23 -> 6.3692739 | AA24: ='Aggregates (% GDP) Oct24'!B77 -> 2020-21 | AB24: =LEFT(AA24,4) -> 2020 | AC24: ='Aggregates (% GDP) Oct24'!F77 -> 3.4413002 | AD24: ='Aggregates (% GDP) Mar24'!F77 -> 3.4519952 | AE24: =AVERAGE($AD$8:$AD$27) -> 2.145275 | AH24: ='Aggregates (% GDP) Oct24'!B77 -> 2020-21 | AI24: =LEFT(AH24,4) -> 2020 | AJ24: =-('Aggregates (% GDP) Oct24'!M77-'Aggregates (% GDP) Oct24'!M76) -> 12.342741
I25: 2021-22 | J25: =LEFT(I25,4) -> 2021 | K25: 96.6 | L25: 83.2 | M25: 80.629863 | N25: 67.135032 | P25: =K25-K24 -> 0.1 | Q25: =L25-L24 -> -3.3 | R25: =M25-M24 -> -2.4500005 | S25: =N25-N24 -> -6.4255903 | AA25: ='Aggregates (% GDP) Oct24'!B78 -> 2021-22 | AB25: =LEFT(AA25,4) -> 2021 | AC25: ='Aggregates (% GDP) Oct24'!F78 -> 2.2556225 | AD25: ='Aggregates (% GDP) Mar24'!F78 -> 2.3021101 | AE25: =AVERAGE($AD$8:$AD$27) -> 2.145275 | AH25: ='Aggregates (% GDP) Oct24'!B78 -> 2021-22 | AI25: =LEFT(AH25,4) -> 2021 | AJ25: =-('Aggregates (% GDP) Oct24'!M78-'Aggregates (% GDP) Oct24'!M77) -> -10.050778
I26: 2022-23 | J26: =LEFT(I26,4) -> 2022 | K26: 95.7 | L26: 84.8 | M26: 81.31136 | N26: 69.332774 | P26: =K26-K25 -> -0.9 | Q26: =L26-L25 -> 1.6 | R26: =M26-M25 -> 0.68149667 | S26: =N26-N25 -> 2.1977416 | AA26: ='Aggregates (% GDP) Oct24'!B79 -> 2022-23 | AB26: =LEFT(AA26,4) -> 2022 | AC26: ='Aggregates (% GDP) Oct24'!F79 -> 1.79943 | AD26: ='Aggregates (% GDP) Mar24'!F79 -> 1.7982158 | AE26: =AVERAGE($AD$8:$AD$27) -> 2.145275 | AH26: ='Aggregates (% GDP) Oct24'!B79 -> 2022-23 | AI26: =LEFT(AH26,4) -> 2022 | AJ26: =-('Aggregates (% GDP) Oct24'!M79-'Aggregates (% GDP) Oct24'!M78) -> -2.0594822
I27: 2023-24 | J27: =LEFT(I27,4) -> 2023 | K27: 97.810368 | L27: 88.853958 | M27: 82.794795 | N27: 69.878037 | P27: =K27-K26 -> 2.1103679 | Q27: =L27-L26 -> 4.0539585 | R27: =M27-M26 -> 1.4834357 | S27: =N27-N26 -> 0.54526299 | AA27: ='Aggregates (% GDP) Oct24'!B80 -> 2023-24 | AB27: =LEFT(AA27,4) -> 2023 | AC27: ='Aggregates (% GDP) Oct24'!F80 -> 2.5565458 | AD27: ='Aggregates (% GDP) Mar24'!F80 -> 2.6051807 | AE27: =AVERAGE($AD$8:$AD$27) -> 2.145275 | AH27: ='Aggregates (% GDP) Oct24'!B80 -> 2023-24 | AI27: =LEFT(AH27,4) -> 2023 | AJ27: =-('Aggregates (% GDP) Oct24'!M80-'Aggregates (% GDP) Oct24'!M79) -> -0.20463319
I28: 2024-25 | J28: =LEFT(I28,4) -> 2024 | K28: 98.395587 | L28: 91.752913 | M28: 83.54479 | N28: 69.572316 | P28: =K28-K27 -> 0.58521875 | Q28: =L28-L27 -> 2.8989543 | R28: =M28-M27 -> 0.74999443 | S28: =N28-N27 -> -0.30572066 | AA28: ='Aggregates (% GDP) Oct24'!B81 -> 2024-25 | AB28: =LEFT(AA28,4) -> 2024 | AC28: ='Aggregates (% GDP) Oct24'!F81 -> 2.5585174 | AD28: ='Aggregates (% GDP) Mar24'!F81 -> 2.3896524 | AE28: =AVERAGE($AD$8:$AD$27) -> 2.145275 | AH28: ='Aggregates (% GDP) Oct24'!B81 -> 2024-25 | AI28: =LEFT(AH28,4) -> 2024 | AJ28: =-('Aggregates (% GDP) Oct24'!M81-'Aggregates (% GDP) Oct24'!M80) -> -0.18733025 | AK28: =-('Aggregates (% GDP) Mar24'!N81-'Aggregates (% GDP) Mar24'!N80) -> -1.1415503
I29: 2025-26 | J29: =LEFT(I29,4) -> 2025 | K29: 96.921744 | L29: 93.140493 | M29: 83.791436 | N29: 69.261948 | P29: =K29-K28 -> -1.4738427 | Q29: =L29-L28 -> 1.3875805 | R29: =M29-M28 -> 0.24664648 | S29: =N29-N28 -> -0.31036835 | AA29: ='Aggregates (% GDP) Oct24'!B82 -> 2025-26 | AB29: =LEFT(AA29,4) -> 2025 | AC29: ='Aggregates (% GDP) Oct24'!F82 -> 2.6919811 | AD29: ='Aggregates (% GDP) Mar24'!F82 -> 2.1199635 | AE29: =AVERAGE($AD$8:$AD$27) -> 2.145275 | AH29: ='Aggregates (% GDP) Oct24'!B82 -> 2025-26 | AI29: =LEFT(AH29,4) -> 2025 | AJ29: =-('Aggregates (% GDP) Oct24'!M82-'Aggregates (% GDP) Oct24'!M81) -> -0.76306604 | AK29: =-('Aggregates (% GDP) Mar24'!N82-'Aggregates (% GDP) Mar24'!N81) -> -0.57313333
I30: 2026-27 | J30: =LEFT(I30,4) -> 2026 | K30: 96.966301 | L30: 94.384386 | M30: 84.227751 | N30: 69.189137 | P30: =K30-K29 -> 0.044556571 | Q30: =L30-L29 -> 1.2438926 | R30: =M30-M29 -> 0.43631488 | S30: =N30-N29 -> -0.072811329 | AA30: ='Aggregates (% GDP) Oct24'!B83 -> 2026-27 | AB30: =LEFT(AA30,4) -> 2026 | AC30: ='Aggregates (% GDP) Oct24'!F83 -> 2.7207402 | AD30: ='Aggregates (% GDP) Mar24'!F83 -> 1.9804928 | AE30: =AVERAGE($AD$8:$AD$27) -> 2.145275 | AH30: ='Aggregates (% GDP) Oct24'!B83 -> 2026-27 | AI30: =LEFT(AH30,4) -> 2026 | AJ30: =-('Aggregates (% GDP) Oct24'!M83-'Aggregates (% GDP) Oct24'!M82) -> -0.52998375 | AK30: =-('Aggregates (% GDP) Mar24'!N83-'Aggregates (% GDP) Mar24'!N82) -> -0.3785978
I31: 2027-28 | J31: =LEFT(I31,4) -> 2027 | K31: 97.245969 | L31: 95.054134 | M31: 84.100989 | N31: 68.709184 | P31: =K31-K30 -> 0.27966853 | Q31: =L31-L30 -> 0.66974783 | R31: =M31-M30 -> -0.12676194 | S31: =N31-N30 -> -0.47995311 | AA31: ='Aggregates (% GDP) Oct24'!B84 -> 2027-28 | AB31: =LEFT(AA31,4) -> 2027 | AC31: ='Aggregates (% GDP) Oct24'!F84 -> 2.6234059 | AD31: ='Aggregates (% GDP) Mar24'!F84 -> 1.8204393 | AE31: =AVERAGE($AD$8:$AD$27) -> 2.145275 | AH31: ='Aggregates (% GDP) Oct24'!B84 -> 2027-28 | AI31: =LEFT(AH31,4) -> 2027 | AJ31: =-('Aggregates (% GDP) Oct24'!M84-'Aggregates (% GDP) Oct24'!M83) -> -0.69853767 | AK31: =-('Aggregates (% GDP) Mar24'!N84-'Aggregates (% GDP) Mar24'!N83) -> -0.60360284
I32: 2028-29 | J32: =LEFT(I32,4) -> 2028 | K32: 97.339932 | L32: 95.607594 | M32: 83.872927 | N32: 68.377937 | P32: =K32-K31 -> 0.093962633 | Q32: =L32-L31 -> 0.55346059 | R32: =M32-M31 -> -0.22806211 | S32: =N32-N31 -> -0.33124701 | AA32: ='Aggregates (% GDP) Oct24'!B85 -> 2028-29 | AB32: =LEFT(AA32,4) -> 2028 | AC32: ='Aggregates (% GDP) Oct24'!F85 -> 2.4777518 | AD32: ='Aggregates (% GDP) Mar24'!F85 -> 1.6542068 | AE32: =AVERAGE($AD$8:$AD$27) -> 2.145275 | AH32: ='Aggregates (% GDP) Oct24'!B85 -> 2028-29 | AI32: =LEFT(AH32,4) -> 2028 | AJ32: =-('Aggregates (% GDP) Oct24'!M85-'Aggregates (% GDP) Oct24'!M84) -> -0.21076074 | AK32: =-('Aggregates (% GDP) Mar24'!N85-'Aggregates (% GDP) Mar24'!N84) -> -0.43227169
I33: 2029-30 | J33: =LEFT(I33,4) -> 2029 | K33: 97.147985 | L33: 95.774656 | M33: 83.417751 | N33: 67.888123 | P33: =K33-K32 -> -0.19194677 | Q33: =L33-L32 -> 0.1670617 | R33: =M33-M32 -> -0.45517556 | S33: =N33-N32 -> -0.48981329 | AA33: ='Aggregates (% GDP) Oct24'!B86 -> 2029-30 | AB33: =LEFT(AA33,4) -> 2029 | AC33: ='Aggregates (% GDP) Oct24'!F86 -> 2.3699287 | AE33: =AVERAGE($AD$8:$AD$27) -> 2.145275 | AH33: ='Aggregates (% GDP) Oct24'!B86 -> 2029-30 | AI33: =LEFT(AH33,4) -> 2029 | AJ33: =-('Aggregates (% GDP) Oct24'!M86-'Aggregates (% GDP) Oct24'!M85) -> -0.18679438
I36: 23-24 | K36: 97.6 | L36: 88.8 | M36: 82.9 | N36: 69.5
I37: 24-25 | K37: 98.8 | L37: 91.7 | M37: 83.6 | N37: 70.2
I38: 25-26 | K38: 96.4 | L38: 92.8 | M38: 83.2 | N38: 69.5
I39: 26-27 | K39: 95.5 | L39: 93.2 | M39: 82.1 | N39: 67.9
I40: 27-28 | K40: 95.1 | L40: 93.2 | M40: 80.6 | N40: 66
I41: 28-29 | K41: 94.3 | L41: 92.9 | M41: 78.7 | N41: 63.9

Sheet GMW
A1: Location | B1: Indicator | C1: Scenario | D1: Units | E1: Scale | F1: Measurement | G1: 1980 Q1 | H1: 1980 Q2 | I1: 1980 Q3 | J1: 1980 Q4 | K1: 1981 Q1 | L1: 1981 Q2 | M1: 1981 Q3 | N1: 1981 Q4 | O1: 1982 Q1 | P1: 1982 Q2 | Q1: 1982 Q3 | R1: 1982 Q4 | S1: 1983 Q1 | T1: 1983 Q2 | U1: 1983 Q3 | V1: 1983 Q4 | W1: 1984 Q1 | X1: 1984 Q2 | Y1: 1984 Q3 | Z1: 1984 Q4 | AA1: 1985 Q1 | AB1: 1985 Q2 | AC1: 1985 Q3 | AD1: 1985 Q4 | AE1: 1986 Q1 | AF1: 1986 Q2 | AG1: 1986 Q3 | AH1: 1986 Q4 | AI1: 1987 Q1 | AJ1: 1987 Q2 | AK1: 1987 Q3 | AL1: 1987 Q4 | AM1: 1988 Q1 | AN1: 1988 Q2 | AO1: 1988 Q3 | AP1: 1988 Q4 | AQ1: 1989 Q1 | AR1: 1989 Q2 | AS1: 1989 Q3 | AT1: 1989 Q4 | AU1: 1990 Q1 | AV1: 1990 Q2 | AW1: 1990 Q3 | AX1: 1990 Q4 | AY1: 1991 Q1 | AZ1: 1991 Q2 | BA1: 1991 Q3 | BB1: 1991 Q4 | BC1: 1992 Q1 | BD1: 1992 Q2 | BE1: 1992 Q3 | BF1: 1992 Q4 | BG1: 1993 Q1 | BH1: 1993 Q2 | BI1: 1993 Q3 | BJ1: 1993 Q4 | BK1: 1994 Q1 | BL1: 1994 Q2 | BM1: 1994 Q3 | BN1: 1994 Q4 | BO1: 1995 Q1 | BP1: 1995 Q2 | BQ1: 1995 Q3 | BR1: 1995 Q4 | BS1: 1996 Q1 | BT1: 1996 Q2 | BU1: 1996 Q3 | BV1: 1996 Q4 | BW1: 1997 Q1 | BX1: 1997 Q2 | BY1: 1997 Q3 | BZ1: 1997 Q4 | CA1: 1998 Q1 | CB1: 1998 Q2 | CC1: 1998 Q3 | CD1: 1998 Q4 | CE1: 1999 Q1 | CF1: 1999 Q2 | CG1: 1999 Q3 | CH1: 1999 Q4 | CI1: 2000 Q1 | CJ1: 2000 Q2 | CK1: 2000 Q3 | CL1: 2000 Q4 | CM1: 2001 Q1 | CN1: 2001 Q2 | CO1: 2001 Q3 | CP1: 2001 Q4 | CQ1: 2002 Q1 | CR1: 2002 Q2 | CS1: 2002 Q3 | CT1: 2002 Q4 | CU1: 2003 Q1 | CV1: 2003 Q2 | CW1: 2003 Q3 | CX1: 2003 Q4 | CY1: 2004 Q1 | CZ1: 2004 Q2 | DA1: 2004 Q3 | DB1: 2004 Q4 | DC1: 2005 Q1 | DD1: 2005 Q2 | DE1: 2005 Q3 | DF1: 2005 Q4 | DG1: 2006 Q1 | DH1: 2006 Q2 | DI1: 2006 Q3 | DJ1: 2006 Q4 | DK1: 2007 Q1 | DL1: 2007 Q2 | DM1: 2007 Q3 | DN1: 2007 Q4 | DO1: 2008 Q1 | DP1: 2008 Q2 | DQ1: 2008 Q3 | DR1: 2008 Q4 | DS1: 2009 Q1 | DT1: 2009 Q2 | DU1: 2009 Q3 | DV1: 2009 Q4 | DW1: 2010 Q1 | DX1: 2010 Q2 | DY1: 2010 Q3 | DZ1: 2010 Q4 | EA1: 2011 Q1 | EB1: 2011 Q2 | EC1: 2011 Q3 | ED1: 2011 Q4 | EE1: 2012 Q1 | EF1: 2012 Q2 | EG1: 2012 Q3 | EH1: 2012 Q4 | EI1: 2013 Q1 | EJ1: 2013 Q2 | EK1: 2013 Q3 | EL1: 2013 Q4 | EM1: 2014 Q1 | EN1: 2014 Q2 | EO1: 2014 Q3 | EP1: 2014 Q4 | EQ1: 2015 Q1 | ER1: 2015 Q2 | ES1: 2015 Q3 | ET1: 2015 Q4 | EU1: 2016 Q1 | EV1: 2016 Q2 | EW1: 2016 Q3 | EX1: 2016 Q4 | EY1: 2017 Q1 | EZ1: 2017 Q2 | FA1: 2017 Q3 | FB1: 2017 Q4 | FC1: 2018 Q1 | FD1: 2018 Q2 | FE1: 2018 Q3 | FF1: 2018 Q4 | FG1: 2019 Q1 | FH1: 2019 Q2 | FI1: 2019 Q3 | FJ1: 2019 Q4 | FK1: 2020 Q1 | FL1: 2020 Q2 | FM1: 2020 Q3 | FN1: 2020 Q4 | FO1: 2021 Q1 | FP1: 2021 Q2 | FQ1: 2021 Q3 | FR1: 2021 Q4 | FS1: 2022 Q1 | FT1: 2022 Q2 | FU1: 2022 Q3 | FV1: 2022 Q4 | FW1: 2023 Q1 | FX1: 2023 Q2 | FY1: 2023 Q3 | FZ1: 2023 Q4 | GA1: 2024 Q1 | GB1: 2024 Q2 | GC1: 2024 Q3 | GD1: 2024 Q4 | GE1: 2025 Q1 | GF1: 2025 Q2 | GG1: 2025 Q3 | GH1: 2025 Q4 | GI1: 2026 Q1 | GJ1: 2026 Q2 | GK1: 2026 Q3 | GL1: 2026 Q4 | GM1: 2027 Q1 | GN1: 2027 Q2 | GO1: 2027 Q3 | GP1: 2027 Q4 | GQ1: 2028 Q1 | GR1: 2028 Q2 | GS1: 2028 Q3 | GT1: 2028 Q4 | GU1: 2029 Q1 | GV1: 2029 Q2 | GW1: 2029 Q3 | GX1: 2029 Q4 | GY1: 2030 Q1 | GZ1: 2030 Q2 | HA1: 2030 Q3 | HB1: 2030 Q4 | HC1: Source | HD1: Seasonally adjusted | HE1: Base year price | HF1: Base year index | HG1: Historical end year | HH1: Historical end quarter | HI1: Date of last update | HJ1: Source details | HK1: Additional source details | HL1: Location code | HM1: Indicator code | HN1: Databank code
A2: United Kingdom | B2: Tax revenue, employer social security contributions, LCU | C2: Oct24_2 | D2: Pound | E2: Millions | F2: Level | G2: 2203.656 | H2: 2273.364 | I2: 2332.952 | J2: 2420.649 | K2: 2498.227 | L2: 2399.287 | M2: 2452.13 | N2: 2560.064 | O2: 2665.75 | P2: 2569.059 | Q2: 2582.55 | R2: 2688.236 | S2: 2872.623 | T2: 2925.466 | U2: 2987.303 | V2: 3060.384 | W2: 3088.492 | X2: 3128.967 | Y2: 3185.183 | Z2: 3267.258 | AA2: 3359.452 | AB2: 3403.3 | AC2: 3447.148 | AD2: 3557.331 | AE2: 3637.157 | AF2: 3792.313 | AG2: 3863.145 | AH2: 3930.603 | AI2: 4305 | AJ2: 4334 | AK2: 4487 | AL2: 4632 | AM2: 4640 | AN2: 4879 | AO2: 5040 | AP2: 5234 | AQ2: 5239 | AR2: 5247 | AS2: 5405 | AT2: 5609 | AU2: 5594 | AV2: 5782 | AW2: 5930 | AX2: 6012 | AY2: 5974 | AZ2: 6126 | BA2: 6125 | BB2: 6492 | BC2: 6453 | BD2: 6234 | BE2: 6198 | BF2: 6517 | BG2: 6477 | BH2: 6646 | BI2: 6727 | BJ2: 6997 | BK2: 6841 | BL2: 6602 | BM2: 6704 | BN2: 6891 | BO2: 6872 | BP2: 6901 | BQ2: 6999 | BR2: 7120 | BS2: 7100 | BT2: 7308 | BU2: 7377 | BV2: 7428 | BW2: 7219 | BX2: 7704 | BY2: 8050 | BZ2: 8065 | CA2: 7887 | CB2: 8048 | CC2: 8448 | CD2: 8468 | CE2: 8757 | CF2: 8818 | CG2: 9094 | CH2: 9184 | CI2: 9313 | CJ2: 9861 | CK2: 9826 | CL2: 10195 | CM2: 10811 | CN2: 9870 | CO2: 10189 | CP2: 10298 | CQ2: 10629 | CR2: 10379 | CS2: 10146 | CT2: 10703 | CU2: 10366 | CV2: 11989 | CW2: 12409 | CX2: 12408 | CY2: 12662 | CZ2: 12920 | DA2: 13279 | DB2: 13669 | DC2: 13668 | DD2: 14205 | DE2: 14681 | DF2: 14643 | DG2: 14713 | DH2: 14863 | DI2: 15292 | DJ2: 15652 | DK2: 15661 | DL2: 16295 | DM2: 16680 | DN2: 17084 | DO2: 17891 | DP2: 17172 | DQ2: 17328 | DR2: 17305 | DS2: 16825 | DT2: 17195 | DU2: 17157 | DV2: 17618 | DW2: 18831 | DX2: 17422 | DY2: 17548 | DZ2: 17762 | EA2: 18475 | EB2: 18242 | EC2: 18350 | ED2: 18382 | EE2: 18603 | EF2: 19029 | EG2: 19095 | EH2: 18982 | EI2: 18597 | EJ2: 19598 | EK2: 19195 | EL2: 19482 | EM2: 19571 | EN2: 19575 | EO2: 19825 | EP2: 19993 | EQ2: 20426 | ER2: 20839 | ES2: 20846 | ET2: 21129 | EU2: 20549 | EV2: 22462 | EW2: 22802 | EX2: 23011 | EY2: 23425 | EZ2: 23645 | FA2: 23594 | FB2: 23997 | FC2: 24296 | FD2: 24403 | FE2: 24535 | FF2: 24830 | FG2: 25806 | FH2: 26406 | FI2: 27085 | FJ2: 27639 | FK2: 27453 | FL2: 27064 | FM2: 27978 | FN2: 28812 | FO2: 28828 | FP2: 29940 | FQ2: 30764 | FR2: 31560 | FS2: 32437 | FT2: 35271 | FU2: 35446 | FV2: 34778 | FW2: 34923 | FX2: 35305 | FY2: 35835 | FZ2: 37193 | GA2: 38998 | GB2: 37308 | GC2: 38127.7 | GD2: 38385.24 | GE2: 38842.31 | GF2: 39239.57 | GG2: 39638.7 | GH2: 40042.66 | GI2: 40448.05 | GJ2: 40902.63 | GK2: 41359.82 | GL2: 41814.05 | GM2: 42274.95 | GN2: 42725.16 | GO2: 43178.24 | GP2: 43638.85 | GQ2: 44019.07 | GR2: 44443.03 | GS2: 44874.24 | GT2: 45316.12 | GU2: 45756.86 | GV2: 46168.63 | GW2: 46582.28 | GX2: 47000.28 | GY2: 47418.72 | GZ2: 47843.01 | HA2: 48273.44 | HB2: 48708.08 | HC2: Office for National Statistics\Haver Analytics | HD2: TRUE | HE2: NA | HF2: NA | HG2: 2024 | HH2: 2 | HI2: NA | HJ2: RNFSQ@UK | HK2: UK: IA: CG: Resources: Employers' Social Contributions (SA, Mil.GBP) | HL2: GBR | HM2: TP | HN2: Oct24_2.db
A3: United Kingdom | B3: GDP, real, LCU | C3: Oct24_2 | D3: Pound | E3: Millions | F3: Level | G3: 269776 | H3: 264448 | I3: 264139 | J3: 261297 | K3: 261131 | L3: 261739 | M3: 264602 | N3: 264902 | O3: 265408 | P3: 268196 | Q3: 268798 | R3: 270653 | S3: 275877 | T3: 277790 | U3: 280996 | V3: 283096 | W3: 285469 | X3: 282605 | Y3: 284676 | Z3: 289829 | AA3: 292612 | AB3: 298873 | AC3: 298814 | AD3: 298979 | AE3: 302117 | AF3: 304797 | AG3: 306708 | AH3: 312615 | AI3: 314804 | AJ3: 319478 | AK3: 327346 | AL3: 331075 | AM3: 336442 | AN3: 338186 | AO3: 342414 | AP3: 345162 | AQ3: 346836 | AR3: 348997 | AS3: 349572 | AT3: 349523 | AU3: 351299 | AV3: 353663 | AW3: 349780 | AX3: 348006 | AY3: 346292 | AZ3: 345892 | BA3: 345216 | BB3: 345643 | BC3: 345523 | BD3: 344987 | BE3: 346628 | BF3: 349299 | BG3: 351046 | BH3: 352612 | BI3: 355841 | BJ3: 358264 | BK3: 361793 | BL3: 365109 | BM3: 368798 | BN3: 370401 | BO3: 372307 | BP3: 373090 | BQ3: 377249 | BR3: 378442 | BS3: 380976 | BT3: 382146 | BU3: 385671 | BV3: 391053 | BW3: 397303 | BX3: 401790 | BY3: 405233 | BZ3: 411352 | CA3: 414377 | CB3: 416909 | CC3: 418294 | CD3: 421074 | CE3: 423875 | CF3: 425920 | CG3: 432860 | CH3: 439093 | CI3: 444540 | CJ3: 447825 | CK3: 450688 | CL3: 453447 | CM3: 457680 | CN3: 459620 | CO3: 462016 | CP3: 463404 | CQ3: 464698 | CR3: 466935 | CS3: 470277 | CT3: 473899 | CU3: 477357 | CV3: 481552 | CW3: 485973 | CX3: 490059 | CY3: 492014 | CZ3: 494824 | DA3: 496642 | DB3: 499020 | DC3: 502702 | DD3: 506906 | DE3: 511132 | DF3: 515935 | DG3: 518495 | DH3: 520318 | DI3: 521780 | DJ3: 524569 | DK3: 529398 | DL3: 533187 | DM3: 537052 | DN3: 540258 | DO3: 542804 | DP3: 539918 | DQ3: 531619 | DR3: 520230 | DS3: 509646 | DT3: 508009 | DU3: 508398 | DV3: 509889 | DW3: 514595 | DX3: 520128 | DY3: 523173 | DZ3: 523515 | EA3: 524955 | EB3: 525418 | EC3: 527034 | ED3: 527698 | EE3: 532300 | EF3: 531663 | EG3: 536720 | EH3: 536188 | EI3: 537974 | EJ3: 541586 | EK3: 546064 | EL3: 549709 | EM3: 554183 | EN3: 559331 | EO3: 563694 | EP3: 567619 | EQ3: 569150 | ER3: 572673 | ES3: 574836 | ET3: 578068 | EU3: 580110 | EV3: 583383 | EW3: 585856 | EX3: 589476 | EY3: 594423 | EZ3: 598176 | FA3: 601961 | FB3: 606396 | FC3: 606785 | FD3: 607775 | FE3: 609653 | FF3: 610481 | FG3: 614936 | FH3: 616853 | FI3: 621227 | FJ3: 621229 | FK3: 604719 | FL3: 481769 | FM3: 562648 | FN3: 570338 | FO3: 564411 | FP3: 605353 | FQ3: 615459 | FR3: 624592 | FS3: 629149 | FT3: 631258 | FU3: 631977 | FV3: 634044 | FW3: 634612 | FX3: 634624 | FY3: 633956 | FZ3: 631825 | GA3: 636222 | GB3: 639095 | GC3: 640741.9 | GD3: 643868.9 | GE3: 646136.9 | GF3: 648529.7 | GG3: 650983.9 | GH3: 653549.4 | GI3: 656294.3 | GJ3: 659051.3 | GK3: 661754 | GL3: 664499.8 | GM3: 667225.6 | GN3: 669961.6 | GO3: 672674.9 | GP3: 675499.9 | GQ3: 678268.4 | GR3: 681049.5 | GS3: 683773.6 | GT3: 686508.3 | GU3: 689254.8 | GV3: 692011.6 | GW3: 694780.4 | GX3: 697559.3 | GY3: 700349.6 | GZ3: 703151.1 | HA3: 705964.2 | HB3: 708788.1 | HC3: Office for National Statistics\Haver Analytics | HD3: TRUE | HE3: chained 2022 | HF3: NA | HG3: 2024 | HH3: 2 | HI3: NA | HJ3: ABMIQ@UK | HK3: U.K.: Real Gross Domestic Product (SA, Mil.Chn.2022.GBP) | HL3: GBR | HM3: GDP | HN3: Oct24_2.db
A4: United Kingdom | B4: Employment, aged 16 and over, ILO definition | C4: Oct24_2 | D4: Person | E4: Thousands | F4: Level | G4: 25250 | H4: 25190 | I4: 25050 | J4: 24855 | K4: 24661 | L4: 24495 | M4: 24355 | N4: 24209 | O4: 24120 | P4: 24027 | Q4: 23901 | R4: 23755 | S4: 23651 | T4: 23647 | U4: 23809 | V4: 23994 | W4: 24125 | X4: 24245 | Y4: 24335 | Z4: 24435 | AA4: 24515 | AB4: 24570 | AC4: 24625 | AD4: 24660 | AE4: 24670 | AF4: 24695 | AG4: 24770 | AH4: 24850 | AI4: 24925 | AJ4: 25110 | AK4: 25345 | AL4: 25575 | AM4: 25795 | AN4: 25970 | AO4: 26160 | AP4: 26355 | AQ4: 26590 | AR4: 26730 | AS4: 26795 | AT4: 26880 | AU4: 26900 | AV4: 26935 | AW4: 26900 | AX4: 26750 | AY4: 26530 | AZ4: 26275 | BA4: 26025 | BB4: 25820 | BC4: 25710 | BD4: 25605 | BE4: 25509 | BF4: 25336 | BG4: 25282 | BH4: 25293 | BI4: 25316 | BJ4: 25320 | BK4: 25408 | BL4: 25451 | BM4: 25559 | BN4: 25600 | BO4: 25670 | BP4: 25770 | BQ4: 25852 | BR4: 25982 | BS4: 25970 | BT4: 26009 | BU4: 26062 | BV4: 26198 | BW4: 26381 | BX4: 26514 | BY4: 26572 | BZ4: 26636 | CA4: 26677 | CB4: 26714 | CC4: 26834 | CD4: 26955 | CE4: 27036 | CF4: 27095 | CG4: 27218 | CH4: 27322 | CI4: 27362 | CJ4: 27468 | CK4: 27555 | CL4: 27549 | CM4: 27623 | CN4: 27707 | CO4: 27715 | CP4: 27803 | CQ4: 27797 | CR4: 27933 | CS4: 27935 | CT4: 28110 | CU4: 28099 | CV4: 28226 | CW4: 28256 | CX4: 28304 | CY4: 28459 | CZ4: 28470 | DA4: 28518 | DB4: 28673 | DC4: 28789 | DD4: 28802 | DE4: 28928 | DF4: 28880 | DG4: 29048 | DH4: 29106 | DI4: 29183 | DJ4: 29214 | DK4: 29194 | DL4: 29322 | DM4: 29420 | DN4: 29576 | DO4: 29684 | DP4: 29722 | DQ4: 29580 | DR4: 29528 | DS4: 29366 | DT4: 29087 | DU4: 29069 | DV4: 29102 | DW4: 29013 | DX4: 29192 | DY4: 29385 | DZ4: 29324 | EA4: 29441 | EB4: 29447 | EC4: 29283 | ED4: 29349 | EE4: 29464 | EF4: 29681 | EG4: 29778 | EH4: 29932 | EI4: 29869 | EJ4: 29974 | EK4: 30144 | EL4: 30330 | EM4: 30573 | EN4: 30747 | EO4: 30873 | EP4: 30981 | EQ4: 31188 | ER4: 31140 | ES4: 31361 | ET4: 31569 | EU4: 31603 | EV4: 31778 | EW4: 31843 | EX4: 31877 | EY4: 31978 | EZ4: 32098 | FA4: 32093 | FB4: 32179 | FC4: 32364 | FD4: 32403 | FE4: 32448 | FF4: 32618 | FG4: 32721 | FH4: 32839 | FI4: 32779 | FJ4: 32954 | FK4: 33000 | FL4: 32571 | FM4: 32354 | FN4: 32198 | FO4: 32221 | FP4: 32377 | FQ4: 32687 | FR4: 32686 | FS4: 32775 | FT4: 32958 | FU4: 32916 | FV4: 33067 | FW4: 33201 | FX4: 33163 | FY4: 33102 | FZ4: 33174 | GA4: 32997 | GB4: 33094 | GC4: 33306.91 | GD4: 33156.91 | GE4: 33260.84 | GF4: 33375.05 | GG4: 33484.89 | GH4: 33600.57 | GI4: 33714.82 | GJ4: 33826.11 | GK4: 33927.58 | GL4: 34027.66 | GM4: 34126.33 | GN4: 34225.34 | GO4: 34322.92 | GP4: 34425.94 | GQ4: 34525.75 | GR4: 34625.88 | GS4: 34718.88 | GT4: 34809.08 | GU4: 34896.14 | GV4: 34979.91 | GW4: 35060.37 | GX4: 35141.01 | GY4: 35218.32 | GZ4: 35295.8 | HA4: 35373.45 | HB4: 35451.27 | HC4: Office for National Statistics\Haver Analytics | HD4: TRUE | HE4: NA | HF4: NA | HG4: 2024 | HH4: 2 | HI4: NA | HJ4: MGRZQ@UK | HK4: UK: LFS: Employment: Aged 16 and Over (SA, Thous) | HL4: GBR | HM4: ETILO | HN4: Oct24_2.db
A5: United Kingdom | B5: Unemployment rate, ILO definition | C5: Oct24_2 | D5: % | E5: NA | F5: Level | G5: 5.8 | H5: 6.3 | I5: 7.1 | J5: 8 | K5: 8.9 | L5: 9.6 | M5: 9.9 | N5: 10.2 | O5: 10.4 | P5: 10.6 | Q5: 10.8 | R5: 11.1 | S5: 11.3 | T5: 11.4 | U5: 11.5 | V5: 11.7 | W5: 11.8 | X5: 11.9 | Y5: 11.7 | Z5: 11.6 | AA5: 11.5 | AB5: 11.4 | AC5: 11.3 | AD5: 11.3 | AE5: 11.3 | AF5: 11.3 | AG5: 11.4 | AH5: 11.3 | AI5: 11.1 | AJ5: 10.7 | AK5: 10.2 | AL5: 9.7 | AM5: 9.2 | AN5: 8.7 | AO5: 8.4 | AP5: 8 | AQ5: 7.6 | AR5: 7.2 | AS5: 7.1 | AT5: 7 | AU5: 6.9 | AV5: 6.9 | AW5: 7.1 | AX5: 7.5 | AY5: 8 | AZ5: 8.7 | BA5: 9.2 | BB5: 9.5 | BC5: 9.7 | BD5: 9.8 | BE5: 9.9 | BF5: 10.4 | BG5: 10.6 | BH5: 10.4 | BI5: 10.2 | BJ5: 10.3 | BK5: 9.9 | BL5: 9.7 | BM5: 9.4 | BN5: 9 | BO5: 8.9 | BP5: 8.7 | BQ5: 8.6 | BR5: 8.3 | BS5: 8.2 | BT5: 8.3 | BU5: 8.1 | BV5: 7.8 | BW5: 7.3 | BX5: 7.2 | BY5: 6.8 | BZ5: 6.5 | CA5: 6.4 | CB5: 6.3 | CC5: 6.2 | CD5: 6.1 | CE5: 6.2 | CF5: 6 | CG5: 5.9 | CH5: 5.8 | CI5: 5.8 | CJ5: 5.5 | CK5: 5.3 | CL5: 5.2 | CM5: 5.1 | CN5: 5 | CO5: 5.1 | CP5: 5.2 | CQ5: 5.2 | CR5: 5.2 | CS5: 5.3 | CT5: 5.1 | CU5: 5.2 | CV5: 4.9 | CW5: 5 | CX5: 4.9 | CY5: 4.8 | CZ5: 4.8 | DA5: 4.7 | DB5: 4.7 | DC5: 4.7 | DD5: 4.8 | DE5: 4.7 | DF5: 5.1 | DG5: 5.2 | DH5: 5.5 | DI5: 5.5 | DJ5: 5.5 | DK5: 5.5 | DL5: 5.4 | DM5: 5.3 | DN5: 5.2 | DO5: 5.2 | DP5: 5.4 | DQ5: 5.9 | DR5: 6.4 | DS5: 7.1 | DT5: 7.8 | DU5: 7.8 | DV5: 7.8 | DW5: 8 | DX5: 7.9 | DY5: 7.8 | DZ5: 7.9 | EA5: 7.8 | EB5: 7.9 | EC5: 8.3 | ED5: 8.4 | EE5: 8.2 | EF5: 8 | EG5: 7.9 | EH5: 7.8 | EI5: 7.9 | EJ5: 7.8 | EK5: 7.6 | EL5: 7.2 | EM5: 6.8 | EN5: 6.3 | EO5: 6 | EP5: 5.7 | EQ5: 5.6 | ER5: 5.6 | ES5: 5.4 | ET5: 5.1 | EU5: 5.1 | EV5: 5 | EW5: 4.9 | EX5: 4.8 | EY5: 4.6 | EZ5: 4.5 | FA5: 4.3 | FB5: 4.4 | FC5: 4.3 | FD5: 4.1 | FE5: 4.2 | FF5: 4.1 | FG5: 3.9 | FH5: 4 | FI5: 3.9 | FJ5: 3.9 | FK5: 4.1 | FL5: 4.2 | FM5: 5 | FN5: 5.3 | FO5: 5.1 | FP5: 4.8 | FQ5: 4.4 | FR5: 4.2 | FS5: 3.9 | FT5: 3.9 | FU5: 3.8 | FV5: 3.9 | FW5: 4 | FX5: 4.2 | FY5: 4.1 | FZ5: 3.8 | GA5: 4.3 | GB5: 4.2 | GC5: 4.243108 | GD5: 4.408679 | GE5: 4.380091 | GF5: 4.351475 | GG5: 4.322893 | GH5: 4.284726 | GI5: 4.2179 | GJ5: 4.151092 | GK5: 4.093759 | GL5: 4.045897 | GM5: 3.998046 | GN5: 3.959662 | GO5: 3.921238 | GP5: 3.882746 | GQ5: 3.844463 | GR5: 3.806106 | GS5: 3.778645 | GT5: 3.75964 | GU5: 3.749948 | GV5: 3.74987 | GW5: 3.749865 | GX5: 3.749873 | GY5: 3.749872 | GZ5: 3.749875 | HA5: 3.74988 | HB5: 3.749879 | HC5: Office for National Statistics\Haver Analytics | HD5: TRUE | HE5: NA | HF5: NA | HG5: 2024 | HH5: 2 | HI5: NA | HJ5: MGSXQ@UK | HK5: UK: LFS: Unemployment Rate: Aged 16 and Over (SA, %) | HL5: GBR | HM5: UPILO | HN5: Oct24_2.db
A6: United Kingdom | B6: Income, personal disposable, real, LCU | C6: Oct24_2 | D6: Pound | E6: Millions | F6: Level | G6: 157780 | H6: 158083 | I6: 160445 | J6: 158931 | K6: 160486 | L6: 158130 | M6: 157598 | N6: 158580 | O6: 157715 | P6: 160483 | Q6: 159367 | R6: 159886 | S6: 158854 | T6: 165111 | U6: 163522 | V6: 164202 | W6: 167088 | X6: 165111 | Y6: 169770 | Z6: 173527 | AA6: 175208 | AB6: 175613 | AC6: 175957 | AD6: 177164 | AE6: 179729 | AF6: 186661 | AG6: 183119 | AH6: 183388 | AI6: 180901 | AJ6: 185020 | AK6: 187551 | AL6: 188860 | AM6: 191709 | AN6: 194935 | AO6: 197179 | AP6: 198740 | AQ6: 201265 | AR6: 204179 | AS6: 209872 | AT6: 207949 | AU6: 213872 | AV6: 211391 | AW6: 213462 | AX6: 216821 | AY6: 218128 | AZ6: 214176 | BA6: 220568 | BB6: 220151 | BC6: 221591 | BD6: 223785 | BE6: 225633 | BF6: 225562 | BG6: 224008 | BH6: 230278 | BI6: 232470 | BJ6: 233411 | BK6: 232541 | BL6: 232173 | BM6: 236870 | BN6: 235558 | BO6: 239669 | BP6: 239943 | BQ6: 242123 | BR6: 243427 | BS6: 247598 | BT6: 247441 | BU6: 250067 | BV6: 245800 | BW6: 249558 | BX6: 251781 | BY6: 254358 | BZ6: 253468 | CA6: 253069 | CB6: 254576 | CC6: 253636 | CD6: 257028 | CE6: 254037 | CF6: 266557 | CG6: 267871 | CH6: 274118 | CI6: 274370 | CJ6: 277466 | CK6: 283106 | CL6: 287523 | CM6: 289476 | CN6: 288052 | CO6: 289545 | CP6: 295002 | CQ6: 295976 | CR6: 298538 | CS6: 297567 | CT6: 298904 | CU6: 301081 | CV6: 302934 | CW6: 304444 | CX6: 308695 | CY6: 309585 | CZ6: 312396 | DA6: 314574 | DB6: 315137 | DC6: 317057 | DD6: 320657 | DE6: 322465 | DF6: 322562 | DG6: 325138 | DH6: 323889 | DI6: 327580 | DJ6: 328682 | DK6: 339067 | DL6: 336009 | DM6: 340647 | DN6: 340314 | DO6: 335815 | DP6: 339732 | DQ6: 333684 | DR6: 340023 | DS6: 335761 | DT6: 344826 | DU6: 343613 | DV6: 346368 | DW6: 346769 | DX6: 347421 | DY6: 346091 | DZ6: 343460 | EA6: 334416 | EB6: 339976 | EC6: 339972 | ED6: 337625 | EE6: 344680 | EF6: 348062 | EG6: 346678 | EH6: 345765 | EI6: 342890 | EJ6: 350923 | EK6: 357263 | EL6: 360126 | EM6: 359009 | EN6: 359599 | EO6: 359708 | EP6: 364730 | EQ6: 372232 | ER6: 381179 | ES6: 388638 | ET6: 388470 | EU6: 386874 | EV6: 387633 | EW6: 384657 | EX6: 381981 | EY6: 382290 | EZ6: 390332 | FA6: 390954 | FB6: 391273 | FC6: 395975 | FD6: 394175 | FE6: 395431 | FF6: 400106 | FG6: 399632 | FH6: 405211 | FI6: 405428 | FJ6: 407970 | FK6: 402584 | FL6: 394596 | FM6: 406593 | FN6: 408367 | FO6: 411074 | FP6: 413832 | FQ6: 410138 | FR6: 402842 | FS6: 401738 | FT6: 398386 | FU6: 400405 | FV6: 408689 | FW6: 407362 | FX6: 412328 | FY6: 413001 | FZ6: 415159 | GA6: 420689 | GB6: 426221 | GC6: 427151.4 | GD6: 427205.6 | GE6: 429422.1 | GF6: 431072.3 | GG6: 432818.3 | GH6: 434694.7 | GI6: 436515.1 | GJ6: 437864.4 | GK6: 439188.4 | GL6: 440408.8 | GM6: 441787.5 | GN6: 443258.1 | GO6: 444859.4 | GP6: 446391.8 | GQ6: 448363 | GR6: 450539.2 | GS6: 452477.2 | GT6: 454341.6 | GU6: 456201.8 | GV6: 458220.1 | GW6: 459983.9 | GX6: 461695.3 | GY6: 463445.7 | GZ6: 465447 | HA6: 467184.9 | HB6: 468872.6 | HC6: Office for National Statistics\Haver Analytics | HD6: TRUE | HE6: chained 2022 | HF6: NA | HG6: 2024 | HH6: 2 | HI6: NA | HJ6: NRJRQ@UK | HK6: UK: HH & NPISH: Real Household Disposable Income (SA, Mil.Chn.2022.Pounds) | HL6: GBR | HM6: PEDY | HN6: Oct24_2.db
A7: United Kingdom | B7: Earnings, quarterly total, whole economy, Gross, LCU | C7: Oct24_2 | D7: Pound per Employee | E7: NA | F7: Level | G7: 1256.656 | H7: 1320.788 | I7: 1377.792 | J7: 1419.042 | K7: 1445.746 | L7: 1481.073 | M7: 1519.57 | N7: 1560.495 | O7: 1588.719 | P7: 1621.852 | Q7: 1645.302 | R7: 1677.714 | S7: 1735.998 | T7: 1757.346 | U7: 1777.221 | V7: 1805.329 | W7: 1833.021 | X7: 1859.965 | Y7: 1876.902 | Z7: 1935.882 | AA7: 1996.246 | AB7: 2015.939 | AC7: 2043.298 | AD7: 2093.281 | AE7: 2142.593 | AF7: 2185.823 | AG7: 2220.435 | AH7: 2251.233 | AI7: 2282.895 | AJ7: 2321.792 | AK7: 2369.95 | AL7: 2418.279 | AM7: 2470.636 | AN7: 2512.313 | AO7: 2569.618 | AP7: 2641.639 | AQ7: 2684.494 | AR7: 2756.293 | AS7: 2816.473 | AT7: 2895.669 | AU7: 2978.668 | AV7: 3042.386 | AW7: 3096.331 | AX7: 3142.508 | AY7: 3224.996 | AZ7: 3293.292 | BA7: 3373.081 | BB7: 3431.946 | BC7: 3467.976 | BD7: 3483.129 | BE7: 3486.288 | BF7: 3519.483 | BG7: 3533.243 | BH7: 3585.394 | BI7: 3630.535 | BJ7: 3662.197 | BK7: 3681.295 | BL7: 3682.575 | BM7: 3730.634 | BN7: 3764.534 | BO7: 3784.689 | BP7: 3813.237 | BQ7: 3825.77 | BR7: 3869.823 | BS7: 3882.18 | BT7: 3914.624 | BU7: 3968.22 | BV7: 3978.247 | BW7: 4081.993 | BX7: 4143.857 | BY7: 4207.873 | BZ7: 4225.691 | CA7: 4229.584 | CB7: 4273.278 | CC7: 4319.682 | CD7: 4319.271 | CE7: 4422.741 | CF7: 4529.62 | CG7: 4579.019 | CH7: 4624.274 | CI7: 4637.771 | CJ7: 4701.495 | CK7: 4802.455 | CL7: 4890.775 | CM7: 5001.369 | CN7: 5002.77 | CO7: 5029.651 | CP7: 5057.922 | CQ7: 5089.49 | CR7: 5073.909 | CS7: 5126.548 | CT7: 5142.66 | CU7: 5215.105 | CV7: 5274.743 | CW7: 5382.108 | CX7: 5458.233 | CY7: 5521.079 | CZ7: 5546.886 | DA7: 5624.504 | DB7: 5694.482 | DC7: 5778.829 | DD7: 5743.093 | DE7: 5808.466 | DF7: 5809.272 | DG7: 5993.517 | DH7: 6001.19 | DI7: 6067.312 | DJ7: 6166.277 | DK7: 6414.875 | DL7: 6339.471 | DM7: 6466.942 | DN7: 6476.04 | DO7: 6580.838 | DP7: 6498.069 | DQ7: 6496.127 | DR7: 6443.408 | DS7: 6371.857 | DT7: 6556.603 | DU7: 6566.035 | DV7: 6577.117 | DW7: 6601.875 | DX7: 6547.224 | DY7: 6603.561 | DZ7: 6617.42 | EA7: 6764.375 | EB7: 6692.795 | EC7: 6733.261 | ED7: 6724.496 | EE7: 6797.859 | EF7: 6797.991 | EG7: 6779.331 | EH7: 6805.55 | EI7: 6831.207 | EJ7: 7064.567 | EK7: 7073.654 | EL7: 7154.167 | EM7: 7221.816 | EN7: 7176 | EO7: 7114.859 | EP7: 7151.244 | EQ7: 7196.032 | ER7: 7235.93 | ES7: 7286.774 | ET7: 7292.882 | EU7: 7378.136 | EV7: 7418.134 | EW7: 7455.118 | EX7: 7453.085 | EY7: 7552.214 | EZ7: 7621.865 | FA7: 7682.057 | FB7: 7709.649 | FC7: 7783.628 | FD7: 7753.096 | FE7: 7876.518 | FF7: 7956.615 | FG7: 7998.079 | FH7: 8102.425 | FI7: 8093.845 | FJ7: 8076.643 | FK7: 8056.795 | FL7: 7842.464 | FM7: 8014.82 | FN7: 8241.492 | FO7: 8267.329 | FP7: 8500.161 | FQ7: 8499.45 | FR7: 8570.438 | FS7: 8762.161 | FT7: 8858.754 | FU7: 8972.382 | FV7: 9187.092 | FW7: 9460.302 | FX7: 9660.59 | FY7: 9771.033 | FZ7: 9774.984 | GA7: 9898.726 | GB7: 10025.21 | GC7: 10139.5 | GD7: 10244.95 | GE7: 10327.93 | GF7: 10399.2 | GG7: 10470.95 | GH7: 10541.84 | GI7: 10611.65 | GJ7: 10680.9 | GK7: 10750.04 | GL7: 10818.11 | GM7: 10887.61 | GN7: 10957.44 | GO7: 11027.81 | GP7: 11097.76 | GQ7: 11168.61 | GR7: 11240.3 | GS7: 11313.43 | GT7: 11387.67 | GU7: 11462.16 | GV7: 11537.54 | GW7: 11614.13 | GX7: 11691.39 | GY7: 11769.48 | GZ7: 11848.68 | HA7: 11928.99 | HB7: 12009.94 | HC7: Oxford Economics calculation using Office for National Statistics data | HD7: TRUE | HE7: NA | HF7: NA | HG7: 2024 | HH7: 2 | HI7: NA | HJ7: Oxford Economics calculation using Office for National Statistics data | HK7: NA | HL7: GBR | HM7: ER | HN7: Oct24_2.db
A8: United Kingdom | B8: Tax revenue, employer social security contributions, LCU | C8: NICS_Scen | D8: Pound | E8: Millions | F8: Level | G8: 2203.656 | H8: 2273.364 | I8: 2332.952 | J8: 2420.649 | K8: 2498.227 | L8: 2399.287 | M8: 2452.13 | N8: 2560.064 | O8: 2665.75 | P8: 2569.059 | Q8: 2582.55 | R8: 2688.236 | S8: 2872.623 | T8: 2925.466 | U8: 2987.303 | V8: 3060.384 | W8: 3088.492 | X8: 3128.967 | Y8: 3185.183 | Z8: 3267.258 | AA8: 3359.452 | AB8: 3403.3 | AC8: 3447.148 | AD8: 3557.331 | AE8: 3637.157 | AF8: 3792.313 | AG8: 3863.145 | AH8: 3930.603 | AI8: 4305 | AJ8: 4334 | AK8: 4487 | AL8: 4632 | AM8: 4640 | AN8: 4879 | AO8: 5040 | AP8: 5234 | AQ8: 5239 | AR8: 5247 | AS8: 5405 | AT8: 5609 | AU8: 5594 | AV8: 5782 | AW8: 5930 | AX8: 6012 | AY8: 5974 | AZ8: 6126 | BA8: 6125 | BB8: 6492 | BC8: 6453 | BD8: 6234 | BE8: 6198 | BF8: 6517 | BG8: 6477 | BH8: 6646 | BI8: 6727 | BJ8: 6997 | BK8: 6841 | BL8: 6602 | BM8: 6704 | BN8: 6891 | BO8: 6872 | BP8: 6901 | BQ8: 6999 | BR8: 7120 | BS8: 7100 | BT8: 7308 | BU8: 7377 | BV8: 7428 | BW8: 7219 | BX8: 7704 | BY8: 8050 | BZ8: 8065 | CA8: 7887 | CB8: 8048 | CC8: 8448 | CD8: 8468 | CE8: 8757 | CF8: 8818 | CG8: 9094 | CH8: 9184 | CI8: 9313 | CJ8: 9861 | CK8: 9826 | CL8: 10195 | CM8: 10811 | CN8: 9870 | CO8: 10189 | CP8: 10298 | CQ8: 10629 | CR8: 10379 | CS8: 10146 | CT8: 10703 | CU8: 10366 | CV8: 11989 | CW8: 12409 | CX8: 12408 | CY8: 12662 | CZ8: 12920 | DA8: 13279 | DB8: 13669 | DC8: 13668 | DD8: 14205 | DE8: 14681 | DF8: 14643 | DG8: 14713 | DH8: 14863 | DI8: 15292 | DJ8: 15652 | DK8: 15661 | DL8: 16295 | DM8: 16680 | DN8: 17084 | DO8: 17891 | DP8: 17172 | DQ8: 17328 | DR8: 17305 | DS8: 16825 | DT8: 17195 | DU8: 17157 | DV8: 17618 | DW8: 18831 | DX8: 17422 | DY8: 17548 | DZ8: 17762 | EA8: 18475 | EB8: 18242 | EC8: 18350 | ED8: 18382 | EE8: 18603 | EF8: 19029 | EG8: 19095 | EH8: 18982 | EI8: 18597 | EJ8: 19598 | EK8: 19195 | EL8: 19482 | EM8: 19571 | EN8: 19575 | EO8: 19825 | EP8: 19993 | EQ8: 20426 | ER8: 20839 | ES8: 20846 | ET8: 21129 | EU8: 20549 | EV8: 22462 | EW8: 22802 | EX8: 23011 | EY8: 23425 | EZ8: 23645 | FA8: 23594 | FB8: 23997 | FC8: 24296 | FD8: 24403 | FE8: 24535 | FF8: 24830 | FG8: 25806 | FH8: 26406 | FI8: 27085 | FJ8: 27639 | FK8: 27453 | FL8: 27064 | FM8: 27978 | FN8: 28812 | FO8: 28828 | FP8: 29940 | FQ8: 30764 | FR8: 31560 | FS8: 32437 | FT8: 35271 | FU8: 35446 | FV8: 34778 | FW8: 34923 | FX8: 35305 | FY8: 35835 | FZ8: 37193 | GA8: 38998 | GB8: 37308 | GC8: 38127.7 | GD8: 38385.24 | GE8: 38842.31 | GF8: 45125.97 | GG8: 45491.81 | GH8: 45860.71 | GI8: 46241.94 | GJ8: 46661.97 | GK8: 47114.59 | GL8: 47570.96 | GM8: 48037.53 | GN8: 48613.55 | GO8: 49073.86 | GP8: 49541.79 | GQ8: 49929.76 | GR8: 50549.02 | GS8: 50986.99 | GT8: 51435.8 | GU8: 51884.1 | GV8: 52496.83 | GW8: 52918.27 | GX8: 53344.36 | GY8: 53771.22 | GZ8: 54261.23 | HA8: 54758.03 | HB8: 55259.36 | HC8: Office for National Statistics\Haver Analytics | HD8: TRUE | HE8: NA | HF8: NA | HG8: 2024 | HH8: 2 | HI8: NA | HJ8: RNFSQ@UK | HK8: UK: IA: CG: Resources: Employers' Social Contributions (SA, Mil.GBP) | HL8: GBR | HM8: TP | HN8: NICS_Scen.db
A9: United Kingdom | B9: GDP, real, LCU | C9: NICS_Scen | D9: Pound | E9: Millions | F9: Level | G9: 269776 | H9: 264448 | I9: 264139 | J9: 261297 | K9: 261131 | L9: 261739 | M9: 264602 | N9: 264902 | O9: 265408 | P9: 268196 | Q9: 268798 | R9: 270653 | S9: 275877 | T9: 277790 | U9: 280996 | V9: 283096 | W9: 285469 | X9: 282605 | Y9: 284676 | Z9: 289829 | AA9: 292612 | AB9: 298873 | AC9: 298814 | AD9: 298979 | AE9: 302117 | AF9: 304797 | AG9: 306708 | AH9: 312615 | AI9: 314804 | AJ9: 319478 | AK9: 327346 | AL9: 331075 | AM9: 336442 | AN9: 338186 | AO9: 342414 | AP9: 345162 | AQ9: 346836 | AR9: 348997 | AS9: 349572 | AT9: 349523 | AU9: 351299 | AV9: 353663 | AW9: 349780 | AX9: 348006 | AY9: 346292 | AZ9: 345892 | BA9: 345216 | BB9: 345643 | BC9: 345523 | BD9: 344987 | BE9: 346628 | BF9: 349299 | BG9: 351046 | BH9: 352612 | BI9: 355841 | BJ9: 358264 | BK9: 361793 | BL9: 365109 | BM9: 368798 | BN9: 370401 | BO9: 372307 | BP9: 373090 | BQ9: 377249 | BR9: 378442 | BS9: 380976 | BT9: 382146 | BU9: 385671 | BV9: 391053 | BW9: 397303 | BX9: 401790 | BY9: 405233 | BZ9: 411352 | CA9: 414377 | CB9: 416909 | CC9: 418294 | CD9: 421074 | CE9: 423875 | CF9: 425920 | CG9: 432860 | CH9: 439093 | CI9: 444540 | CJ9: 447825 | CK9: 450688 | CL9: 453447 | CM9: 457680 | CN9: 459620 | CO9: 462016 | CP9: 463404 | CQ9: 464698 | CR9: 466935 | CS9: 470277 | CT9: 473899 | CU9: 477357 | CV9: 481552 | CW9: 485973 | CX9: 490059 | CY9: 492014 | CZ9: 494824 | DA9: 496642 | DB9: 499020 | DC9: 502702 | DD9: 506906 | DE9: 511132 | DF9: 515935 | DG9: 518495 | DH9: 520318 | DI9: 521780 | DJ9: 524569 | DK9: 529398 | DL9: 533187 | DM9: 537052 | DN9: 540258 | DO9: 542804 | DP9: 539918 | DQ9: 531619 | DR9: 520230 | DS9: 509646 | DT9: 508009 | DU9: 508398 | DV9: 509889 | DW9: 514595 | DX9: 520128 | DY9: 523173 | DZ9: 523515 | EA9: 524955 | EB9: 525418 | EC9: 527034 | ED9: 527698 | EE9: 532300 | EF9: 531663 | EG9: 536720 | EH9: 536188 | EI9: 537974 | EJ9: 541586 | EK9: 546064 | EL9: 549709 | EM9: 554183 | EN9: 559331 | EO9: 563694 | EP9: 567619 | EQ9: 569150 | ER9: 572673 | ES9: 574836 | ET9: 578068 | EU9: 580110 | EV9: 583383 | EW9: 585856 | EX9: 589476 | EY9: 594423 | EZ9: 598176 | FA9: 601961 | FB9: 606396 | FC9: 606785 | FD9: 607775 | FE9: 609653 | FF9: 610481 | FG9: 614936 | FH9: 616853 | FI9: 621227 | FJ9: 621229 | FK9: 604719 | FL9: 481769 | FM9: 562648 | FN9: 570338 | FO9: 564411 | FP9: 605353 | FQ9: 615459 | FR9: 624592 | FS9: 629149 | FT9: 631258 | FU9: 631977 | FV9: 634044 | FW9: 634612 | FX9: 634624 | FY9: 633956 | FZ9: 631825 | GA9: 636222 | GB9: 639095 | GC9: 640741.9 | GD9: 643868.9 | GE9: 646136.9 | GF9: 647772.1 | GG9: 649743.7 | GH9: 652016.3 | GI9: 654585 | GJ9: 657323.1 | GK9: 660047.9 | GL9: 662837.8 | GM9: 665613.3 | GN9: 668386.4 | GO9: 671143.1 | GP9: 674014.1 | GQ9: 676832.3 | GR9: 679646 | GS9: 682417.5 | GT9: 685213.4 | GU9: 688029.5 | GV9: 690845 | GW9: 693682.9 | GX9: 696538.8 | GY9: 699408.1 | GZ9: 702286.3 | HA9: 705169.4 | HB9: 708055.9 | HC9: Office for National Statistics\Haver Analytics | HD9: TRUE | HE9: chained 2022 | HF9: NA | HG9: 2024 | HH9: 2 | HI9: NA | HJ9: ABMIQ@UK | HK9: U.K.: Real Gross Domestic Product (SA, Mil.Chn.2022.GBP) | HL9: GBR | HM9: GDP | HN9: NICS_Scen.db
A10: United Kingdom | B10: Employment, aged 16 and over, ILO definition | C10: NICS_Scen | D10: Person | E10: Thousands | F10: Level | G10: 25250 | H10: 25190 | I10: 25050 | J10: 24855 | K10: 24661 | L10: 24495 | M10: 24355 | N10: 24209 | O10: 24120 | P10: 24027 | Q10: 23901 | R10: 23755 | S10: 23651 | T10: 23647 | U10: 23809 | V10: 23994 | W10: 24125 | X10: 24245 | Y10: 24335 | Z10: 24435 | AA10: 24515 | AB10: 24570 | AC10: 24625 | AD10: 24660 | AE10: 24670 | AF10: 24695 | AG10: 24770 | AH10: 24850 | AI10: 24925 | AJ10: 25110 | AK10: 25345 | AL10: 25575 | AM10: 25795 | AN10: 25970 | AO10: 26160 | AP10: 26355 | AQ10: 26590 | AR10: 26730 | AS10: 26795 | AT10: 26880 | AU10: 26900 | AV10: 26935 | AW10: 26900 | AX10: 26750 | AY10: 26530 | AZ10: 26275 | BA10: 26025 | BB10: 25820 | BC10: 25710 | BD10: 25605 | BE10: 25509 | BF10: 25336 | BG10: 25282 | BH10: 25293 | BI10: 25316 | BJ10: 25320 | BK10: 25408 | BL10: 25451 | BM10: 25559 | BN10: 25600 | BO10: 25670 | BP10: 25770 | BQ10: 25852 | BR10: 25982 | BS10: 25970 | BT10: 26009 | BU10: 26062 | BV10: 26198 | BW10: 26381 | BX10: 26514 | BY10: 26572 | BZ10: 26636 | CA10: 26677 | CB10: 26714 | CC10: 26834 | CD10: 26955 | CE10: 27036 | CF10: 27095 | CG10: 27218 | CH10: 27322 | CI10: 27362 | CJ10: 27468 | CK10: 27555 | CL10: 27549 | CM10: 27623 | CN10: 27707 | CO10: 27715 | CP10: 27803 | CQ10: 27797 | CR10: 27933 | CS10: 27935 | CT10: 28110 | CU10: 28099 | CV10: 28226 | CW10: 28256 | CX10: 28304 | CY10: 28459 | CZ10: 28470 | DA10: 28518 | DB10: 28673 | DC10: 28789 | DD10: 28802 | DE10: 28928 | DF10: 28880 | DG10: 29048 | DH10: 29106 | DI10: 29183 | DJ10: 29214 | DK10: 29194 | DL10: 29322 | DM10: 29420 | DN10: 29576 | DO10: 29684 | DP10: 29722 | DQ10: 29580 | DR10: 29528 | DS10: 29366 | DT10: 29087 | DU10: 29069 | DV10: 29102 | DW10: 29013 | DX10: 29192 | DY10: 29385 | DZ10: 29324 | EA10: 29441 | EB10: 29447 | EC10: 29283 | ED10: 29349 | EE10: 29464 | EF10: 29681 | EG10: 29778 | EH10: 29932 | EI10: 29869 | EJ10: 29974 | EK10: 30144 | EL10: 30330 | EM10: 30573 | EN10: 30747 | EO10: 30873 | EP10: 30981 | EQ10: 31188 | ER10: 31140 | ES10: 31361 | ET10: 31569 | EU10: 31603 | EV10: 31778 | EW10: 31843 | EX10: 31877 | EY10: 31978 | EZ10: 32098 | FA10: 32093 | FB10: 32179 | FC10: 32364 | FD10: 32403 | FE10: 32448 | FF10: 32618 | FG10: 32721 | FH10: 32839 | FI10: 32779 | FJ10: 32954 | FK10: 33000 | FL10: 32571 | FM10: 32354 | FN10: 32198 | FO10: 32221 | FP10: 32377 | FQ10: 32687 | FR10: 32686 | FS10: 32775 | FT10: 32958 | FU10: 32916 | FV10: 33067 | FW10: 33201 | FX10: 33163 | FY10: 33102 | FZ10: 33174 | GA10: 32997 | GB10: 33094 | GC10: 33306.91 | GD10: 33156.91 | GE10: 33260.84 | GF10: 33349.68 | GG10: 33449.47 | GH10: 33554.05 | GI10: 33662.36 | GJ10: 33771.11 | GK10: 33873.27 | GL10: 33975.7 | GM10: 34077.21 | GN10: 34178.63 | GO10: 34278.84 | GP10: 34384.39 | GQ10: 34486.76 | GR10: 34588.66 | GS10: 34683.95 | GT10: 34776.47 | GU10: 34866.05 | GV10: 34951.74 | GW10: 35034.71 | GX10: 35117.85 | GY10: 35197.73 | GZ10: 35277.58 | HA10: 35357.53 | HB10: 35437.45 | HC10: Office for National Statistics\Haver Analytics | HD10: TRUE | HE10: NA | HF10: NA | HG10: 2024 | HH10: 2 | HI10: NA | HJ10: MGRZQ@UK | HK10: UK: LFS: Employment: Aged 16 and Over (SA, Thous) | HL10: GBR | HM10: ETILO | HN10: NICS_Scen.db
A11: United Kingdom | B11: Unemployment rate, ILO definition | C11: NICS_Scen | D11: % | E11: NA | F11: Level | G11: 5.8 | H11: 6.3 | I11: 7.1 | J11: 8 | K11: 8.9 | L11: 9.6 | M11: 9.9 | N11: 10.2 | O11: 10.4 | P11: 10.6 | Q11: 10.8 | R11: 11.1 | S11: 11.3 | T11: 11.4 | U11: 11.5 | V11: 11.7 | W11: 11.8 | X11: 11.9 | Y11: 11.7 | Z11: 11.6 | AA11: 11.5 | AB11: 11.4 | AC11: 11.3 | AD11: 11.3 | AE11: 11.3 | AF11: 11.3 | AG11: 11.4 | AH11: 11.3 | AI11: 11.1 | AJ11: 10.7 | AK11: 10.2 | AL11: 9.7 | AM11: 9.2 | AN11: 8.7 | AO11: 8.4 | AP11: 8 | AQ11: 7.6 | AR11: 7.2 | AS11: 7.1 | AT11: 7 | AU11: 6.9 | AV11: 6.9 | AW11: 7.1 | AX11: 7.5 | AY11: 8 | AZ11: 8.7 | BA11: 9.2 | BB11: 9.5 | BC11: 9.7 | BD11: 9.8 | BE11: 9.9 | BF11: 10.4 | BG11: 10.6 | BH11: 10.4 | BI11: 10.2 | BJ11: 10.3 | BK11: 9.9 | BL11: 9.7 | BM11: 9.4 | BN11: 9 | BO11: 8.9 | BP11: 8.7 | BQ11: 8.6 | BR11: 8.3 | BS11: 8.2 | BT11: 8.3 | BU11: 8.1 | BV11: 7.8 | BW11: 7.3 | BX11: 7.2 | BY11: 6.8 | BZ11: 6.5 | CA11: 6.4 | CB11: 6.3 | CC11: 6.2 | CD11: 6.1 | CE11: 6.2 | CF11: 6 | CG11: 5.9 | CH11: 5.8 | CI11: 5.8 | CJ11: 5.5 | CK11: 5.3 | CL11: 5.2 | CM11: 5.1 | CN11: 5 | CO11: 5.1 | CP11: 5.2 | CQ11: 5.2 | CR11: 5.2 | CS11: 5.3 | CT11: 5.1 | CU11: 5.2 | CV11: 4.9 | CW11: 5 | CX11: 4.9 | CY11: 4.8 | CZ11: 4.8 | DA11: 4.7 | DB11: 4.7 | DC11: 4.7 | DD11: 4.8 | DE11: 4.7 | DF11: 5.1 | DG11: 5.2 | DH11: 5.5 | DI11: 5.5 | DJ11: 5.5 | DK11: 5.5 | DL11: 5.4 | DM11: 5.3 | DN11: 5.2 | DO11: 5.2 | DP11: 5.4 | DQ11: 5.9 | DR11: 6.4 | DS11: 7.1 | DT11: 7.8 | DU11: 7.8 | DV11: 7.8 | DW11: 8 | DX11: 7.9 | DY11: 7.8 | DZ11: 7.9 | EA11: 7.8 | EB11: 7.9 | EC11: 8.3 | ED11: 8.4 | EE11: 8.2 | EF11: 8 | EG11: 7.9 | EH11: 7.8 | EI11: 7.9 | EJ11: 7.8 | EK11: 7.6 | EL11: 7.2 | EM11: 6.8 | EN11: 6.3 | EO11: 6 | EP11: 5.7 | EQ11: 5.6 | ER11: 5.6 | ES11: 5.4 | ET11: 5.1 | EU11: 5.1 | EV11: 5 | EW11: 4.9 | EX11: 4.8 | EY11: 4.6 | EZ11: 4.5 | FA11: 4.3 | FB11: 4.4 | FC11: 4.3 | FD11: 4.1 | FE11: 4.2 | FF11: 4.1 | FG11: 3.9 | FH11: 4 | FI11: 3.9 | FJ11: 3.9 | FK11: 4.1 | FL11: 4.2 | FM11: 5 | FN11: 5.3 | FO11: 5.1 | FP11: 4.8 | FQ11: 4.4 | FR11: 4.2 | FS11: 3.9 | FT11: 3.9 | FU11: 3.8 | FV11: 3.9 | FW11: 4 | FX11: 4.2 | FY11: 4.1 | FZ11: 3.8 | GA11: 4.3 | GB11: 4.2 | GC11: 4.243108 | GD11: 4.408679 | GE11: 4.380091 | GF11: 4.424242 | GG11: 4.424083 | GH11: 4.417153 | GI11: 4.366939 | GJ11: 4.306917 | GK11: 4.247278 | GL11: 4.192399 | GM11: 4.13622 | GN11: 4.09075 | GO11: 4.044635 | GP11: 3.998756 | GQ11: 3.953046 | GR11: 3.909514 | GS11: 3.875439 | GT11: 3.849798 | GU11: 3.832931 | GV11: 3.827398 | GW11: 3.82032 | GX11: 3.813298 | GY11: 3.806122 | GZ11: 3.799546 | HA11: 3.793203 | HB11: 3.78739 | HC11: Office for National Statistics\Haver Analytics | HD11: TRUE | HE11: NA | HF11: NA | HG11: 2024 | HH11: 2 | HI11: NA | HJ11: MGSXQ@UK | HK11: UK: LFS: Unemployment Rate: Aged 16 and Over (SA, %) | HL11: GBR | HM11: UPILO | HN11: NICS_Scen.db
A12: United Kingdom | B12: Income, personal disposable, real, LCU | C12: NICS_Scen | D12: Pound | E12: Millions | F12: Level | G12: 157780 | H12: 158083 | I12: 160445 | J12: 158931 | K12: 160486 | L12: 158130 | M12: 157598 | N12: 158580 | O12: 157715 | P12: 160483 | Q12: 159367 | R12: 159886 | S12: 158854 | T12: 165111 | U12: 163522 | V12: 164202 | W12: 167088 | X12: 165111 | Y12: 169770 | Z12: 173527 | AA12: 175208 | AB12: 175613 | AC12: 175957 | AD12: 177164 | AE12: 179729 | AF12: 186661 | AG12: 183119 | AH12: 183388 | AI12: 180901 | AJ12: 185020 | AK12: 187551 | AL12: 188860 | AM12: 191709 | AN12: 194935 | AO12: 197179 | AP12: 198740 | AQ12: 201265 | AR12: 204179 | AS12: 209872 | AT12: 207949 | AU12: 213872 | AV12: 211391 | AW12: 213462 | AX12: 216821 | AY12: 218128 | AZ12: 214176 | BA12: 220568 | BB12: 220151 | BC12: 221591 | BD12: 223785 | BE12: 225633 | BF12: 225562 | BG12: 224008 | BH12: 230278 | BI12: 232470 | BJ12: 233411 | BK12: 232541 | BL12: 232173 | BM12: 236870 | BN12: 235558 | BO12: 239669 | BP12: 239943 | BQ12: 242123 | BR12: 243427 | BS12: 247598 | BT12: 247441 | BU12: 250067 | BV12: 245800 | BW12: 249558 | BX12: 251781 | BY12: 254358 | BZ12: 253468 | CA12: 253069 | CB12: 254576 | CC12: 253636 | CD12: 257028 | CE12: 254037 | CF12: 266557 | CG12: 267871 | CH12: 274118 | CI12: 274370 | CJ12: 277466 | CK12: 283106 | CL12: 287523 | CM12: 289476 | CN12: 288052 | CO12: 289545 | CP12: 295002 | CQ12: 295976 | CR12: 298538 | CS12: 297567 | CT12: 298904 | CU12: 301081 | CV12: 302934 | CW12: 304444 | CX12: 308695 | CY12: 309585 | CZ12: 312396 | DA12: 314574 | DB12: 315137 | DC12: 317057 | DD12: 320657 | DE12: 322465 | DF12: 322562 | DG12: 325138 | DH12: 323889 | DI12: 327580 | DJ12: 328682 | DK12: 339067 | DL12: 336009 | DM12: 340647 | DN12: 340314 | DO12: 335815 | DP12: 339732 | DQ12: 333684 | DR12: 340023 | DS12: 335761 | DT12: 344826 | DU12: 343613 | DV12: 346368 | DW12: 346769 | DX12: 347421 | DY12: 346091 | DZ12: 343460 | EA12: 334416 | EB12: 339976 | EC12: 339972 | ED12: 337625 | EE12: 344680 | EF12: 348062 | EG12: 346678 | EH12: 345765 | EI12: 342890 | EJ12: 350923 | EK12: 357263 | EL12: 360126 | EM12: 359009 | EN12: 359599 | EO12: 359708 | EP12: 364730 | EQ12: 372232 | ER12: 381179 | ES12: 388638 | ET12: 388470 | EU12: 386874 | EV12: 387633 | EW12: 384657 | EX12: 381981 | EY12: 382290 | EZ12: 390332 | FA12: 390954 | FB12: 391273 | FC12: 395975 | FD12: 394175 | FE12: 395431 | FF12: 400106 | FG12: 399632 | FH12: 405211 | FI12: 405428 | FJ12: 407970 | FK12: 402584 | FL12: 394596 | FM12: 406593 | FN12: 408367 | FO12: 411074 | FP12: 413832 | FQ12: 410138 | FR12: 402842 | FS12: 401738 | FT12: 398386 | FU12: 400405 | FV12: 408689 | FW12: 407362 | FX12: 412328 | FY12: 413001 | FZ12: 415159 | GA12: 420689 | GB12: 426221 | GC12: 427151.4 | GD12: 427205.6 | GE12: 429422 | GF12: 430118.1 | GG12: 431622 | GH12: 433221.2 | GI12: 434859.7 | GJ12: 436100.1 | GK12: 437349.4 | GL12: 438521.8 | GM12: 439874.5 | GN12: 441318.4 | GO12: 442919.5 | GP12: 444458.7 | GQ12: 446442 | GR12: 448606.1 | GS12: 450558.9 | GT12: 452442.6 | GU12: 454329.8 | GV12: 456356.1 | GW12: 458151.5 | GX12: 459896 | GY12: 461682.5 | GZ12: 463721.9 | HA12: 465491.3 | HB12: 467207.5 | HC12: Office for National Statistics\Haver Analytics | HD12: TRUE | HE12: chained 2022 | HF12: NA | HG12: 2024 | HH12: 2 | HI12: NA | HJ12: NRJRQ@UK | HK12: UK: HH & NPISH: Real Household Disposable Income (SA, Mil.Chn.2022.Pounds) | HL12: GBR | HM12: PEDY | HN12: NICS_Scen.db
A13: United Kingdom | B13: Earnings, quarterly total, whole economy, Gross, LCU | C13: NICS_Scen | D13: Pound per Employee | E13: NA | F13: Level | G13: 1256.656 | H13: 1320.788 | I13: 1377.792 | J13: 1419.042 | K13: 1445.746 | L13: 1481.073 | M13: 1519.57 | N13: 1560.495 | O13: 1588.719 | P13: 1621.852 | Q13: 1645.302 | R13: 1677.714 | S13: 1735.998 | T13: 1757.346 | U13: 1777.221 | V13: 1805.329 | W13: 1833.021 | X13: 1859.965 | Y13: 1876.902 | Z13: 1935.882 | AA13: 1996.246 | AB13: 2015.939 | AC13: 2043.298 | AD13: 2093.281 | AE13: 2142.593 | AF13: 2185.823 | AG13: 2220.435 | AH13: 2251.233 | AI13: 2282.895 | AJ13: 2321.792 | AK13: 2369.95 | AL13: 2418.279 | AM13: 2470.636 | AN13: 2512.313 | AO13: 2569.618 | AP13: 2641.639 | AQ13: 2684.494 | AR13: 2756.293 | AS13: 2816.473 | AT13: 2895.669 | AU13: 2978.668 | AV13: 3042.386 | AW13: 3096.331 | AX13: 3142.508 | AY13: 3224.996 | AZ13: 3293.292 | BA13: 3373.081 | BB13: 3431.946 | BC13: 3467.976 | BD13: 3483.129 | BE13: 3486.288 | BF13: 3519.483 | BG13: 3533.243 | BH13: 3585.394 | BI13: 3630.535 | BJ13: 3662.197 | BK13: 3681.295 | BL13: 3682.575 | BM13: 3730.634 | BN13: 3764.534 | BO13: 3784.689 | BP13: 3813.237 | BQ13: 3825.77 | BR13: 3869.823 | BS13: 3882.18 | BT13: 3914.624 | BU13: 3968.22 | BV13: 3978.247 | BW13: 4081.993 | BX13: 4143.857 | BY13: 4207.873 | BZ13: 4225.691 | CA13: 4229.584 | CB13: 4273.278 | CC13: 4319.682 | CD13: 4319.271 | CE13: 4422.741 | CF13: 4529.62 | CG13: 4579.019 | CH13: 4624.274 | CI13: 4637.771 | CJ13: 4701.495 | CK13: 4802.455 | CL13: 4890.775 | CM13: 5001.369 | CN13: 5002.77 | CO13: 5029.651 | CP13: 5057.922 | CQ13: 5089.49 | CR13: 5073.909 | CS13: 5126.548 | CT13: 5142.66 | CU13: 5215.105 | CV13: 5274.743 | CW13: 5382.108 | CX13: 5458.233 | CY13: 5521.079 | CZ13: 5546.886 | DA13: 5624.504 | DB13: 5694.482 | DC13: 5778.829 | DD13: 5743.093 | DE13: 5808.466 | DF13: 5809.272 | DG13: 5993.517 | DH13: 6001.19 | DI13: 6067.312 | DJ13: 6166.277 | DK13: 6414.875 | DL13: 6339.471 | DM13: 6466.942 | DN13: 6476.04 | DO13: 6580.838 | DP13: 6498.069 | DQ13: 6496.127 | DR13: 6443.408 | DS13: 6371.857 | DT13: 6556.603 | DU13: 6566.035 | DV13: 6577.117 | DW13: 6601.875 | DX13: 6547.224 | DY13: 6603.561 | DZ13: 6617.42 | EA13: 6764.375 | EB13: 6692.795 | EC13: 6733.261 | ED13: 6724.496 | EE13: 6797.859 | EF13: 6797.991 | EG13: 6779.331 | EH13: 6805.55 | EI13: 6831.207 | EJ13: 7064.567 | EK13: 7073.654 | EL13: 7154.167 | EM13: 7221.816 | EN13: 7176 | EO13: 7114.859 | EP13: 7151.244 | EQ13: 7196.032 | ER13: 7235.93 | ES13: 7286.774 | ET13: 7292.882 | EU13: 7378.136 | EV13: 7418.134 | EW13: 7455.118 | EX13: 7453.085 | EY13: 7552.214 | EZ13: 7621.865 | FA13: 7682.057 | FB13: 7709.649 | FC13: 7783.628 | FD13: 7753.096 | FE13: 7876.518 | FF13: 7956.615 | FG13: 7998.079 | FH13: 8102.425 | FI13: 8093.845 | FJ13: 8076.643 | FK13: 8056.795 | FL13: 7842.464 | FM13: 8014.82 | FN13: 8241.492 | FO13: 8267.329 | FP13: 8500.161 | FQ13: 8499.45 | FR13: 8570.438 | FS13: 8762.161 | FT13: 8858.754 | FU13: 8972.382 | FV13: 9187.092 | FW13: 9460.302 | FX13: 9660.59 | FY13: 9771.033 | FZ13: 9774.984 | GA13: 9898.726 | GB13: 10025.21 | GC13: 10139.5 | GD13: 10244.95 | GE13: 10327.93 | GF13: 10393.98 | GG13: 10461.16 | GH13: 10527.44 | GI13: 10593.65 | GJ13: 10660.51 | GK13: 10728.56 | GL13: 10796.59 | GM13: 10866.67 | GN13: 10937.3 | GO13: 11008.62 | GP13: 11079.57 | GQ13: 11151.42 | GR13: 11223.94 | GS13: 11297.95 | GT13: 11373.08 | GU13: 11448.53 | GV13: 11524.76 | GW13: 11602.32 | GX13: 11680.6 | GY13: 11759.76 | GZ13: 11840.03 | HA13: 11921.41 | HB13: 12003.38 | HC13: Oxford Economics calculation using Office for National Statistics data | HD13: TRUE | HE13: NA | HF13: NA | HG13: 2024 | HH13: 2 | HI13: NA | HJ13: Oxford Economics calculation using Office for National Statistics data | HK13: NA | HL13: GBR | HM13: ER | HN13: NICS_Scen.db

Sheet DataQ
E1: Oct24_2.db | F1: =$E$1 -> Oct24_2.db | G1: =$E$1 -> Oct24_2.db | H1: =$E$1 -> Oct24_2.db | I1: =$E$1 -> Oct24_2.db | J1: =$E$1 -> Oct24_2.db | K1: NICs_scen.db | L1: =$K$1 -> NICs_scen.db | M1: =$K$1 -> NICs_scen.db | N1: =$K$1 -> NICs_scen.db | O1: =$K$1 -> NICs_scen.db | P1: =$K$1 -> NICs_scen.db
E2: UK | F2: UK | G2: UK | H2: UK | I2: UK | J2: UK | K2: UK | L2: UK | M2: UK | N2: UK | O2: UK | P2: UK
E3: GDP | F3: ETILO | G3: ER | H3: UPILO | I3: PEDY | J3: TP | K3: GDP | L3: ETILO | M3: ER | N3: UPILO | O3: PEDY | P3: TP
E4: GBR | F4: GBR | G4: GBR | H4: GBR | I4: GBR | J4: GBR | K4: GBR | L4: GBR | M4: GBR | N4: GBR | O4: GBR | P4: GBR
E5: L | F5: L | G5: L | H5: L | I5: L | J5: L | K5: L | L5: L | M5: L | N5: L | O5: L | P5: L
B6: =B210+5 -> 2188 | C6: CY | D6: FY | E6: {=_xlfn.CONCAT(INDEX(GMW!$A$2:$HM$50,MATCH(1,(GMW!$HM$2:$HM$50=E$3)*(GMW!$HL$2:$HL$50=E$4),0),$B6-1973),"0",(INDEX(GMW!$A$2:$HM$50,MATCH(1,(GMW!$HM$2:$HM$50=E$3)*(GMW!$HL$2:$HL$50=E$4),0),$B6-1972)))} -> 202402 | F6: {=_xlfn.CONCAT(INDEX(GMW!$A$2:$HM$50,MATCH(1,(GMW!$HM$2:$HM$50=F$3)*(GMW!$HL$2:$HL$50=F$4),0),$B6-1973),"0",(INDEX(GMW!$A$2:$HM$50,MATCH(1,(GMW!$HM$2:$HM$50=F$3)*(GMW!$HL$2:$HL$50=F$4),0),$B6-1972)))} -> 202402 | G6: {=_xlfn.CONCAT(INDEX(GMW!$A$2:$HM$50,MATCH(1,(GMW!$HM$2:$HM$50=G$3)*(GMW!$HL$2:$HL$50=G$4),0),$B6-1973),"0",(INDEX(GMW!$A$2:$HM$50,MATCH(1,(GMW!$HM$2:$HM$50=G$3)*(GMW!$HL$2:$HL$50=G$4),0),$B6-1972)))} -> 202402 | H6: {=_xlfn.CONCAT(INDEX(GMW!$A$2:$HM$50,MATCH(1,(GMW!$HM$2:$HM$50=H$3)*(GMW!$HL$2:$HL$50=H$4),0),$B6-1973),"0",(INDEX(GMW!$A$2:$HM$50,MATCH(1,(GMW!$HM$2:$HM$50=H$3)*(GMW!$HL$2:$HL$50=H$4),0),$B6-1972)))} -> 202402 | I6: {=_xlfn.CONCAT(INDEX(GMW!$A$2:$HM$50,MATCH(1,(GMW!$HM$2:$HM$50=I$3)*(GMW!$HL$2:$HL$50=I$4),0),$B6-1973),"0",(INDEX(GMW!$A$2:$HM$50,MATCH(1,(GMW!$HM$2:$HM$50=I$3)*(GMW!$HL$2:$HL$50=I$4),0),$B6-1972)))} -> 202402 | J6: {=_xlfn.CONCAT(INDEX(GMW!$A$2:$HM$50,MATCH(1,(GMW!$HM$2:$HM$50=J$3)*(GMW!$HL$2:$HL$50=J$4),0),$B6-1973),"0",(INDEX(GMW!$A$2:$HM$50,MATCH(1,(GMW!$HM$2:$HM$50=J$3)*(GMW!$HL$2:$HL$50=J$4),0),$B6-1972)))} -> 202402 | K6: {=_xlfn.CONCAT(INDEX(GMW!$A$2:$HM$50,MATCH(1,(GMW!$HM$2:$HM$50=K$3)*(GMW!$HL$2:$HL$50=K$4),0),$B6-1973),"0",(INDEX(GMW!$A$2:$HM$50,MATCH(1,(GMW!$HM$2:$HM$50=K$3)*(GMW!$HL$2:$HL$50=K$4),0),$B6-1972)))} -> 202402 | L6: {=_xlfn.CONCAT(INDEX(GMW!$A$2:$HM$50,MATCH(1,(GMW!$HM$2:$HM$50=L$3)*(GMW!$HL$2:$HL$50=L$4),0),$B6-1973),"0",(INDEX(GMW!$A$2:$HM$50,MATCH(1,(GMW!$HM$2:$HM$50=L$3)*(GMW!$HL$2:$HL$50=L$4),0),$B6-1972)))} -> 202402 | ... P6: {=_xlfn.CONCAT(INDEX(GMW!$A$2:$HM$50,MATCH(1,(GMW!$HM$2:$HM$50=P$3)*(GMW!$HL$2:$HL$50=P$4),0),$B6-1973),"0",(INDEX(GMW!$A$2:$HM$50,MATCH(1,(GMW!$HM$2:$HM$50=P$3)*(GMW!$HL$2:$HL$50=P$4),0),$B6-1972)))} -> 202402
A7: 1980 | B7: 1980 | C7: 1980 | E7: {=INDEX(GMW!$A$2:$HN$50,MATCH(1,(GMW!$HM$2:$HM$50=E$3)*(GMW!$HN$2:$HN$50=E$1),0),$B7-1973)} -> 269776 | F7: {=INDEX(GMW!$A$2:$HN$50,MATCH(1,(GMW!$HM$2:$HM$50=F$3)*(GMW!$HN$2:$HN$50=F$1),0),$B7-1973)} -> 25250 | G7: {=INDEX(GMW!$A$2:$HN$50,MATCH(1,(GMW!$HM$2:$HM$50=G$3)*(GMW!$HN$2:$HN$50=G$1),0),$B7-1973)} -> 1256.656 | H7: {=INDEX(GMW!$A$2:$HN$50,MATCH(1,(GMW!$HM$2:$HM$50=H$3)*(GMW!$HN$2:$HN$50=H$1),0),$B7-1973)} -> 5.8 | I7: {=INDEX(GMW!$A$2:$HN$50,MATCH(1,(GMW!$HM$2:$HM$50=I$3)*(GMW!$HN$2:$HN$50=I$1),0),$B7-1973)} -> 157780 | J7: {=INDEX(GMW!$A$2:$HN$50,MATCH(1,(GMW!$HM$2:$HM$50=J$3)*(GMW!$HN$2:$HN$50=J$1),0),$B7-1973)} -> 2203.656 | K7: {=INDEX(GMW!$A$2:$HN$50,MATCH(1,(GMW!$HM$2:$HM$50=K$3)*(GMW!$HN$2:$HN$50=K$1),0),$B7-1973)} -> 269776 | L7: {=INDEX(GMW!$A$2:$HN$50,MATCH(1,(GMW!$HM$2:$HM$50=L$3)*(GMW!$HN$2:$HN$50=L$1),0),$B7-1973)} -> 25250 | ... P7: {=INDEX(GMW!$A$2:$HN$50,MATCH(1,(GMW!$HM$2:$HM$50=P$3)*(GMW!$HN$2:$HN$50=P$1),0),$B7-1973)} -> 2203.656
B8: =+B7+1 -> 1981 | C8: 1980 | D8: 1980 | E8: {=INDEX(GMW!$A$2:$HN$50,MATCH(1,(GMW!$HM$2:$HM$50=E$3)*(GMW!$HN$2:$HN$50=E$1),0),$B8-1973)} -> 264448 | F8: {=INDEX(GMW!$A$2:$HN$50,MATCH(1,(GMW!$HM$2:$HM$50=F$3)*(GMW!$HN$2:$HN$50=F$1),0),$B8-1973)} -> 25190 | G8: {=INDEX(GMW!$A$2:$HN$50,MATCH(1,(GMW!$HM$2:$HM$50=G$3)*(GMW!$HN$2:$HN$50=G$1),0),$B8-1973)} -> 1320.788 | H8: {=INDEX(GMW!$A$2:$HN$50,MATCH(1,(GMW!$HM$2:$HM$50=H$3)*(GMW!$HN$2:$HN$50=H$1),0),$B8-1973)} -> 6.3 | I8: {=INDEX(GMW!$A$2:$HN$50,MATCH(1,(GMW!$HM$2:$HM$50=I$3)*(GMW!$HN$2:$HN$50=I$1),0),$B8-1973)} -> 158083 | J8: {=INDEX(GMW!$A$2:$HN$50,MATCH(1,(GMW!$HM$2:$HM$50=J$3)*(GMW!$HN$2:$HN$50=J$1),0),$B8-1973)} -> 2273.364 | K8: {=INDEX(GMW!$A$2:$HN$50,MATCH(1,(GMW!$HM$2:$HM$50=K$3)*(GMW!$HN$2:$HN$50=K$1),0),$B8-1973)} -> 264448 | L8: {=INDEX(GMW!$A$2:$HN$50,MATCH(1,(GMW!$HM$2:$HM$50=L$3)*(GMW!$HN$2:$HN$50=L$1),0),$B8-1973)} -> 25190 | ... P8: {=INDEX(GMW!$A$2:$HN$50,MATCH(1,(GMW!$HM$2:$HM$50=P$3)*(GMW!$HN$2:$HN$50=P$1),0),$B8-1973)} -> 2273.364
B9: =+B8+1 -> 1982 | C9: 1980 | D9: 1980 | E9: {=INDEX(GMW!$A$2:$HN$50,MATCH(1,(GMW!$HM$2:$HM$50=E$3)*(GMW!$HN$2:$HN$50=E$1),0),$B9-1973)} -> 264139 | F9: {=INDEX(GMW!$A$2:$HN$50,MATCH(1,(GMW!$HM$2:$HM$50=F$3)*(GMW!$HN$2:$HN$50=F$1),0),$B9-1973)} -> 25050 | G9: {=INDEX(GMW!$A$2:$HN$50,MATCH(1,(GMW!$HM$2:$HM$50=G$3)*(GMW!$HN$2:$HN$50=G$1),0),$B9-1973)} -> 1377.792 | H9: {=INDEX(GMW!$A$2:$HN$50,MATCH(1,(GMW!$HM$2:$HM$50=H$3)*(GMW!$HN$2:$HN$50=H$1),0),$B9-1973)} -> 7.1 | I9: {=INDEX(GMW!$A$2:$HN$50,MATCH(1,(GMW!$HM$2:$HM$50=I$3)*(GMW!$HN$2:$HN$50=I$1),0),$B9-1973)} -> 160445 | J9: {=INDEX(GMW!$A$2:$HN$50,MATCH(1,(GMW!$HM$2:$HM$50=J$3)*(GMW!$HN$2:$HN$50=J$1),0),$B9-1973)} -> 2332.952 | K9: {=INDEX(GMW!$A$2:$HN$50,MATCH(1,(GMW!$HM$2:$HM$50=K$3)*(GMW!$HN$2:$HN$50=K$1),0),$B9-1973)} -> 264139 | L9: {=INDEX(GMW!$A$2:$HN$50,MATCH(1,(GMW!$HM$2:$HM$50=L$3)*(GMW!$HN$2:$HN$50=L$1),0),$B9-1973)} -> 25050 | ... P9: {=INDEX(GMW!$A$2:$HN$50,MATCH(1,(GMW!$HM$2:$HM$50=P$3)*(GMW!$HN$2:$HN$50=P$1),0),$B9-1973)} -> 2332.952
B10: =+B9+1 -> 1983 | C10: 1980 | D10: 1980 | E10: {=INDEX(GMW!$A$2:$HN$50,MATCH(1,(GMW!$HM$2:$HM$50=E$3)*(GMW!$HN$2:$HN$50=E$1),0),$B10-1973)} -> 261297 | F10: {=INDEX(GMW!$A$2:$HN$50,MATCH(1,(GMW!$HM$2:$HM$50=F$3)*(GMW!$HN$2:$HN$50=F$1),0),$B10-1973)} -> 24855 | G10: {=INDEX(GMW!$A$2:$HN$50,MATCH(1,(GMW!$HM$2:$HM$50=G$3)*(GMW!$HN$2:$HN$50=G$1),0),$B10-1973)} -> 1419.042 | H10: {=INDEX(GMW!$A$2:$HN$50,MATCH(1,(GMW!$HM$2:$HM$50=H$3)*(GMW!$HN$2:$HN$50=H$1),0),$B10-1973)} -> 8 | I10: {=INDEX(GMW!$A$2:$HN$50,MATCH(1,(GMW!$HM$2:$HM$50=I$3)*(GMW!$HN$2:$HN$50=I$1),0),$B10-1973)} -> 158931 | J10: {=INDEX(GMW!$A$2:$HN$50,MATCH(1,(GMW!$HM$2:$HM$50=J$3)*(GMW!$HN$2:$HN$50=J$1),0),$B10-1973)} -> 2420.649 | K10: {=INDEX(GMW!$A$2:$HN$50,MATCH(1,(GMW!$HM$2:$HM$50=K$3)*(GMW!$HN$2:$HN$50=K$1),0),$B10-1973)} -> 261297 | L10: {=INDEX(GMW!$A$2:$HN$50,MATCH(1,(GMW!$HM$2:$HM$50=L$3)*(GMW!$HN$2:$HN$50=L$1),0),$B10-1973)} -> 24855 | ... P10: {=INDEX(GMW!$A$2:$HN$50,MATCH(1,(GMW!$HM$2:$HM$50=P$3)*(GMW!$HN$2:$HN$50=P$1),0),$B10-1973)} -> 2420.649
A11: 1981 | B11: =+B10+1 -> 1984 | C11: =+C7+1 -> 1981 | D11: 1980 | E11: {=INDEX(GMW!$A$2:$HN$50,MATCH(1,(GMW!$HM$2:$HM$50=E$3)*(GMW!$HN$2:$HN$50=E$1),0),$B11-1973)} -> 261131 | F11: {=INDEX(GMW!$A$2:$HN$50,MATCH(1,(GMW!$HM$2:$HM$50=F$3)*(GMW!$HN$2:$HN$50=F$1),0),$B11-1973)} -> 24661 | G11: {=INDEX(GMW!$A$2:$HN$50,MATCH(1,(GMW!$HM$2:$HM$50=G$3)*(GMW!$HN$2:$HN$50=G$1),0),$B11-1973)} -> 1445.746 | H11: {=INDEX(GMW!$A$2:$HN$50,MATCH(1,(GMW!$HM$2:$HM$50=H$3)*(GMW!$HN$2:$HN$50=H$1),0),$B11-1973)} -> 8.9 | I11: {=INDEX(GMW!$A$2:$HN$50,MATCH(1,(GMW!$HM$2:$HM$50=I$3)*(GMW!$HN$2:$HN$50=I$1),0),$B11-1973)} -> 160486 | J11: {=INDEX(GMW!$A$2:$HN$50,MATCH(1,(GMW!$HM$2:$HM$50=J$3)*(GMW!$HN$2:$HN$50=J$1),0),$B11-1973)} -> 2498.227 | K11: {=INDEX(GMW!$A$2:$HN$50,MATCH(1,(GMW!$HM$2:$HM$50=K$3)*(GMW!$HN$2:$HN$50=K$1),0),$B11-1973)} -> 261131 | L11: {=INDEX(GMW!$A$2:$HN$50,MATCH(1,(GMW!$HM$2:$HM$50=L$3)*(GMW!$HN$2:$HN$50=L$1),0),$B11-1973)} -> 24661 | ... P11: {=INDEX(GMW!$A$2:$HN$50,MATCH(1,(GMW!$HM$2:$HM$50=P$3)*(GMW!$HN$2:$HN$50=P$1),0),$B11-1973)} -> 2498.227
B12: =+B11+1 -> 1985 | C12: =+C8+1 -> 1981 | D12: =+D8+1 -> 1981 | E12: {=INDEX(GMW!$A$2:$HN$50,MATCH(1,(GMW!$HM$2:$HM$50=E$3)*(GMW!$HN$2:$HN$50=E$1),0),$B12-1973)} -> 261739 | F12: {=INDEX(GMW!$A$2:$HN$50,MATCH(1,(GMW!$HM$2:$HM$50=F$3)*(GMW!$HN$2:$HN$50=F$1),0),$B12-1973)} -> 24495 | G12: {=INDEX(GMW!$A$2:$HN$50,MATCH(1,(GMW!$HM$2:$HM$50=G$3)*(GMW!$HN$2:$HN$50=G$1),0),$B12-1973)} -> 1481.073 | H12: {=INDEX(GMW!$A$2:$HN$50,MATCH(1,(GMW!$HM$2:$HM$50=H$3)*(GMW!$HN$2:$HN$50=H$1),0),$B12-1973)} -> 9.6 | I12: {=INDEX(GMW!$A$2:$HN$50,MATCH(1,(GMW!$HM$2:$HM$50=I$3)*(GMW!$HN$2:$HN$50=I$1),0),$B12-1973)} -> 158130 | J12: {=INDEX(GMW!$A$2:$HN$50,MATCH(1,(GMW!$HM$2:$HM$50=J$3)*(GMW!$HN$2:$HN$50=J$1),0),$B12-1973)} -> 2399.287 | K12: {=INDEX(GMW!$A$2:$HN$50,MATCH(1,(GMW!$HM$2:$HM$50=K$3)*(GMW!$HN$2:$HN$50=K$1),0),$B12-1973)} -> 261739 | L12: {=INDEX(GMW!$A$2:$HN$50,MATCH(1,(GMW!$HM$2:$HM$50=L$3)*(GMW!$HN$2:$HN$50=L$1),0),$B12-1973)} -> 24495 | ... P12: {=INDEX(GMW!$A$2:$HN$50,MATCH(1,(GMW!$HM$2:$HM$50=P$3)*(GMW!$HN$2:$HN$50=P$1),0),$B12-1973)} -> 2399.287
B13: =+B12+1 -> 1986 | C13: =+C9+1 -> 1981 | D13: =+D9+1 -> 1981 | E13: {=INDEX(GMW!$A$2:$HN$50,MATCH(1,(GMW!$HM$2:$HM$50=E$3)*(GMW!$HN$2:$HN$50=E$1),0),$B13-1973)} -> 264602 | F13: {=INDEX(GMW!$A$2:$HN$50,MATCH(1,(GMW!$HM$2:$HM$50=F$3)*(GMW!$HN$2:$HN$50=F$1),0),$B13-1973)} -> 24355 | G13: {=INDEX(GMW!$A$2:$HN$50,MATCH(1,(GMW!$HM$2:$HM$50=G$3)*(GMW!$HN$2:$HN$50=G$1),0),$B13-1973)} -> 1519.57 | H13: {=INDEX(GMW!$A$2:$HN$50,MATCH(1,(GMW!$HM$2:$HM$50=H$3)*(GMW!$HN$2:$HN$50=H$1),0),$B13-1973)} -> 9.9 | I13: {=INDEX(GMW!$A$2:$HN$50,MATCH(1,(GMW!$HM$2:$HM$50=I$3)*(GMW!$HN$2:$HN$50=I$1),0),$B13-1973)} -> 157598 | J13: {=INDEX(GMW!$A$2:$HN$50,MATCH(1,(GMW!$HM$2:$HM$50=J$3)*(GMW!$HN$2:$HN$50=J$1),0),$B13-1973)} -> 2452.13 | K13: {=INDEX(GMW!$A$2:$HN$50,MATCH(1,(GMW!$HM$2:$HM$50=K$3)*(GMW!$HN$2:$HN$50=K$1),0),$B13-1973)} -> 264602 | L13: {=INDEX(GMW!$A$2:$HN$50,MATCH(1,(GMW!$HM$2:$HM$50=L$3)*(GMW!$HN$2:$HN$50=L$1),0),$B13-1973)} -> 24355 | ... P13: {=INDEX(GMW!$A$2:$HN$50,MATCH(1,(GMW!$HM$2:$HM$50=P$3)*(GMW!$HN$2:$HN$50=P$1),0),$B13-1973)} -> 2452.13
B14: =+B13+1 -> 1987 | C14: =+C10+1 -> 1981 | D14: =+D10+1 -> 1981 | E14: {=INDEX(GMW!$A$2:$HN$50,MATCH(1,(GMW!$HM$2:$HM$50=E$3)*(GMW!$HN$2:$HN$50=E$1),0),$B14-1973)} -> 264902 | F14: {=INDEX(GMW!$A$2:$HN$50,MATCH(1,(GMW!$HM$2:$HM$50=F$3)*(GMW!$HN$2:$HN$50=F$1),0),$B14-1973)} -> 24209 | G14: {=INDEX(GMW!$A$2:$HN$50,MATCH(1,(GMW!$HM$2:$HM$50=G$3)*(GMW!$HN$2:$HN$50=G$1),0),$B14-1973)} -> 1560.495 | H14: {=INDEX(GMW!$A$2:$HN$50,MATCH(1,(GMW!$HM$2:$HM$50=H$3)*(GMW!$HN$2:$HN$50=H$1),0),$B14-1973)} -> 10.2 | I14: {=INDEX(GMW!$A$2:$HN$50,MATCH(1,(GMW!$HM$2:$HM$50=I$3)*(GMW!$HN$2:$HN$50=I$1),0),$B14-1973)} -> 158580 | J14: {=INDEX(GMW!$A$2:$HN$50,MATCH(1,(GMW!$HM$2:$HM$50=J$3)*(GMW!$HN$2:$HN$50=J$1),0),$B14-1973)} -> 2560.064 | K14: {=INDEX(GMW!$A$2:$HN$50,MATCH(1,(GMW!$HM$2:$HM$50=K$3)*(GMW!$HN$2:$HN$50=K$1),0),$B14-1973)} -> 264902 | L14: {=INDEX(GMW!$A$2:$HN$50,MATCH(1,(GMW!$HM$2:$HM$50=L$3)*(GMW!$HN$2:$HN$50=L$1),0),$B14-1973)} -> 24209 | ... P14: {=INDEX(GMW!$A$2:$HN$50,MATCH(1,(GMW!$HM$2:$HM$50=P$3)*(GMW!$HN$2:$HN$50=P$1),0),$B14-1973)} -> 2560.064
A15: 1982 | B15: =+B14+1 -> 1988 | C15: =+C11+1 -> 1982 | D15: =+D11+1 -> 1981 | E15: {=INDEX(GMW!$A$2:$HN$50,MATCH(1,(GMW!$HM$2:$HM$50=E$3)*(GMW!$HN$2:$HN$50=E$1),0),$B15-1973)} -> 265408 | F15: {=INDEX(GMW!$A$2:$HN$50,MATCH(1,(GMW!$HM$2:$HM$50=F$3)*(GMW!$HN$2:$HN$50=F$1),0),$B15-1973)} -> 24120 | G15: {=INDEX(GMW!$A$2:$HN$50,MATCH(1,(GMW!$HM$2:$HM$50=G$3)*(GMW!$HN$2:$HN$50=G$1),0),$B15-1973)} -> 1588.719 | H15: {=INDEX(GMW!$A$2:$HN$50,MATCH(1,(GMW!$HM$2:$HM$50=H$3)*(GMW!$HN$2:$HN$50=H$1),0),$B15-1973)} -> 10.4 | I15: {=INDEX(GMW!$A$2:$HN$50,MATCH(1,(GMW!$HM$2:$HM$50=I$3)*(GMW!$HN$2:$HN$50=I$1),0),$B15-1973)} -> 157715 | J15: {=INDEX(GMW!$A$2:$HN$50,MATCH(1,(GMW!$HM$2:$HM$50=J$3)*(GMW!$HN$2:$HN$50=J$1),0),$B15-1973)} -> 2665.75 | K15: {=INDEX(GMW!$A$2:$HN$50,MATCH(1,(GMW!$HM$2:$HM$50=K$3)*(GMW!$HN$2:$HN$50=K$1),0),$B15-1973)} -> 265408 | L15: {=INDEX(GMW!$A$2:$HN$50,MATCH(1,(GMW!$HM$2:$HM$50=L$3)*(GMW!$HN$2:$HN$50=L$1),0),$B15-1973)} -> 24120 | ... P15: {=INDEX(GMW!$A$2:$HN$50,MATCH(1,(GMW!$HM$2:$HM$50=P$3)*(GMW!$HN$2:$HN$50=P$1),0),$B15-1973)} -> 2665.75
B16: =+B15+1 -> 1989 | C16: =+C12+1 -> 1982 | D16: =+D12+1 -> 1982 | E16: {=INDEX(GMW!$A$2:$HN$50,MATCH(1,(GMW!$HM$2:$HM$50=E$3)*(GMW!$HN$2:$HN$50=E$1),0),$B16-1973)} -> 268196 | F16: {=INDEX(GMW!$A$2:$HN$50,MATCH(1,(GMW!$HM$2:$HM$50=F$3)*(GMW!$HN$2:$HN$50=F$1),0),$B16-1973)} -> 24027 | G16: {=INDEX(GMW!$A$2:$HN$50,MATCH(1,(GMW!$HM$2:$HM$50=G$3)*(GMW!$HN$2:$HN$50=G$1),0),$B16-1973)} -> 1621.852 | H16: {=INDEX(GMW!$A$2:$HN$50,MATCH(1,(GMW!$HM$2:$HM$50=H$3)*(GMW!$HN$2:$HN$50=H$1),0),$B16-1973)} -> 10.6 | I16: {=INDEX(GMW!$A$2:$HN$50,MATCH(1,(GMW!$HM$2:$HM$50=I$3)*(GMW!$HN$2:$HN$50=I$1),0),$B16-1973)} -> 160483 | J16: {=INDEX(GMW!$A$2:$HN$50,MATCH(1,(GMW!$HM$2:$HM$50=J$3)*(GMW!$HN$2:$HN$50=J$1),0),$B16-1973)} -> 2569.059 | K16: {=INDEX(GMW!$A$2:$HN$50,MATCH(1,(GMW!$HM$2:$HM$50=K$3)*(GMW!$HN$2:$HN$50=K$1),0),$B16-1973)} -> 268196 | L16: {=INDEX(GMW!$A$2:$HN$50,MATCH(1,(GMW!$HM$2:$HM$50=L$3)*(GMW!$HN$2:$HN$50=L$1),0),$B16-1973)} -> 24027 | ... P16: {=INDEX(GMW!$A$2:$HN$50,MATCH(1,(GMW!$HM$2:$HM$50=P$3)*(GMW!$HN$2:$HN$50=P$1),0),$B16-1973)} -> 2569.059
B17: =+B16+1 -> 1990 | C17: =+C13+1 -> 1982 | D17: =+D13+1 -> 1982 | E17: {=INDEX(GMW!$A$2:$HN$50,MATCH(1,(GMW!$HM$2:$HM$50=E$3)*(GMW!$HN$2:$HN$50=E$1),0),$B17-1973)} -> 268798 | F17: {=INDEX(GMW!$A$2:$HN$50,MATCH(1,(GMW!$HM$2:$HM$50=F$3)*(GMW!$HN$2:$HN$50=F$1),0),$B17-1973)} -> 23901 | G17: {=INDEX(GMW!$A$2:$HN$50,MATCH(1,(GMW!$HM$2:$HM$50=G$3)*(GMW!$HN$2:$HN$50=G$1),0),$B17-1973)} -> 1645.302 | H17: {=INDEX(GMW!$A$2:$HN$50,MATCH(1,(GMW!$HM$2:$HM$50=H$3)*(GMW!$HN$2:$HN$50=H$1),0),$B17-1973)} -> 10.8 | I17: {=INDEX(GMW!$A$2:$HN$50,MATCH(1,(GMW!$HM$2:$HM$50=I$3)*(GMW!$HN$2:$HN$50=I$1),0),$B17-1973)} -> 159367 | J17: {=INDEX(GMW!$A$2:$HN$50,MATCH(1,(GMW!$HM$2:$HM$50=J$3)*(GMW!$HN$2:$HN$50=J$1),0),$B17-1973)} -> 2582.55 | K17: {=INDEX(GMW!$A$2:$HN$50,MATCH(1,(GMW!$HM$2:$HM$50=K$3)*(GMW!$HN$2:$HN$50=K$1),0),$B17-1973)} -> 268798 | L17: {=INDEX(GMW!$A$2:$HN$50,MATCH(1,(GMW!$HM$2:$HM$50=L$3)*(GMW!$HN$2:$HN$50=L$1),0),$B17-1973)} -> 23901 | ... P17: {=INDEX(GMW!$A$2:$HN$50,MATCH(1,(GMW!$HM$2:$HM$50=P$3)*(GMW!$HN$2:$HN$50=P$1),0),$B17-1973)} -> 2582.55
B18: =+B17+1 -> 1991 | C18: =+C14+1 -> 1982 | D18: =+D14+1 -> 1982 | E18: {=INDEX(GMW!$A$2:$HN$50,MATCH(1,(GMW!$HM$2:$HM$50=E$3)*(GMW!$HN$2:$HN$50=E$1),0),$B18-1973)} -> 270653 | F18: {=INDEX(GMW!$A$2:$HN$50,MATCH(1,(GMW!$HM$2:$HM$50=F$3)*(GMW!$HN$2:$HN$50=F$1),0),$B18-1973)} -> 23755 | G18: {=INDEX(GMW!$A$2:$HN$50,MATCH(1,(GMW!$HM$2:$HM$50=G$3)*(GMW!$HN$2:$HN$50=G$1),0),$B18-1973)} -> 1677.714 | H18: {=INDEX(GMW!$A$2:$HN$50,MATCH(1,(GMW!$HM$2:$HM$50=H$3)*(GMW!$HN$2:$HN$50=H$1),0),$B18-1973)} -> 11.1 | I18: {=INDEX(GMW!$A$2:$HN$50,MATCH(1,(GMW!$HM$2:$HM$50=I$3)*(GMW!$HN$2:$HN$50=I$1),0),$B18-1973)} -> 159886 | J18: {=INDEX(GMW!$A$2:$HN$50,MATCH(1,(GMW!$HM$2:$HM$50=J$3)*(GMW!$HN$2:$HN$50=J$1),0),$B18-1973)} -> 2688.236 | K18: {=INDEX(GMW!$A$2:$HN$50,MATCH(1,(GMW!$HM$2:$HM$50=K$3)*(GMW!$HN$2:$HN$50=K$1),0),$B18-1973)} -> 270653 | L18: {=INDEX(GMW!$A$2:$HN$50,MATCH(1,(GMW!$HM$2:$HM$50=L$3)*(GMW!$HN$2:$HN$50=L$1),0),$B18-1973)} -> 23755 | ... P18: {=INDEX(GMW!$A$2:$HN$50,MATCH(1,(GMW!$HM$2:$HM$50=P$3)*(GMW!$HN$2:$HN$50=P$1),0),$B18-1973)} -> 2688.236
A19: 1983 | B19: =+B18+1 -> 1992 | C19: =+C15+1 -> 1983 | D19: =+D15+1 -> 1982 | E19: {=INDEX(GMW!$A$2:$HN$50,MATCH(1,(GMW!$HM$2:$HM$50=E$3)*(GMW!$HN$2:$HN$50=E$1),0),$B19-1973)} -> 275877 | F19: {=INDEX(GMW!$A$2:$HN$50,MATCH(1,(GMW!$HM$2:$HM$50=F$3)*(GMW!$HN$2:$HN$50=F$1),0),$B19-1973)} -> 23651 | G19: {=INDEX(GMW!$A$2:$HN$50,MATCH(1,(GMW!$HM$2:$HM$50=G$3)*(GMW!$HN$2:$HN$50=G$1),0),$B19-1973)} -> 1735.998 | H19: {=INDEX(GMW!$A$2:$HN$50,MATCH(1,(GMW!$HM$2:$HM$50=H$3)*(GMW!$HN$2:$HN$50=H$1),0),$B19-1973)} -> 11.3 | I19: {=INDEX(GMW!$A$2:$HN$50,MATCH(1,(GMW!$HM$2:$HM$50=I$3)*(GMW!$HN$2:$HN$50=I$1),0),$B19-1973)} -> 158854 | J19: {=INDEX(GMW!$A$2:$HN$50,MATCH(1,(GMW!$HM$2:$HM$50=J$3)*(GMW!$HN$2:$HN$50=J$1),0),$B19-1973)} -> 2872.623 | K19: {=INDEX(GMW!$A$2:$HN$50,MATCH(1,(GMW!$HM$2:$HM$50=K$3)*(GMW!$HN$2:$HN$50=K$1),0),$B19-1973)} -> 275877 | L19: {=INDEX(GMW!$A$2:$HN$50,MATCH(1,(GMW!$HM$2:$HM$50=L$3)*(GMW!$HN$2:$HN$50=L$1),0),$B19-1973)} -> 23651 | ... P19: {=INDEX(GMW!$A$2:$HN$50,MATCH(1,(GMW!$HM$2:$HM$50=P$3)*(GMW!$HN$2:$HN$50=P$1),0),$B19-1973)} -> 2872.623
B20: =+B19+1 -> 1993 | C20: =+C16+1 -> 1983 | D20: =+D16+1 -> 1983 | E20: {=INDEX(GMW!$A$2:$HN$50,MATCH(1,(GMW!$HM$2:$HM$50=E$3)*(GMW!$HN$2:$HN$50=E$1),0),$B20-1973)} -> 277790 | F20: {=INDEX(GMW!$A$2:$HN$50,MATCH(1,(GMW!$HM$2:$HM$50=F$3)*(GMW!$HN$2:$HN$50=F$1),0),$B20-1973)} -> 23647 | G20: {=INDEX(GMW!$A$2:$HN$50,MATCH(1,(GMW!$HM$2:$HM$50=G$3)*(GMW!$HN$2:$HN$50=G$1),0),$B20-1973)} -> 1757.346 | H20: {=INDEX(GMW!$A$2:$HN$50,MATCH(1,(GMW!$HM$2:$HM$50=H$3)*(GMW!$HN$2:$HN$50=H$1),0),$B20-1973)} -> 11.4 | I20: {=INDEX(GMW!$A$2:$HN$50,MATCH(1,(GMW!$HM$2:$HM$50=I$3)*(GMW!$HN$2:$HN$50=I$1),0),$B20-1973)} -> 165111 | J20: {=INDEX(GMW!$A$2:$HN$50,MATCH(1,(GMW!$HM$2:$HM$50=J$3)*(GMW!$HN$2:$HN$50=J$1),0),$B20-1973)} -> 2925.466 | K20: {=INDEX(GMW!$A$2:$HN$50,MATCH(1,(GMW!$HM$2:$HM$50=K$3)*(GMW!$HN$2:$HN$50=K$1),0),$B20-1973)} -> 277790 | L20: {=INDEX(GMW!$A$2:$HN$50,MATCH(1,(GMW!$HM$2:$HM$50=L$3)*(GMW!$HN$2:$HN$50=L$1),0),$B20-1973)} -> 23647 | ... P20: {=INDEX(GMW!$A$2:$HN$50,MATCH(1,(GMW!$HM$2:$HM$50=P$3)*(GMW!$HN$2:$HN$50=P$1),0),$B20-1973)} -> 2925.466
B21: =+B20+1 -> 1994 | C21: =+C17+1 -> 1983 | D21: =+D17+1 -> 1983 | E21: {=INDEX(GMW!$A$2:$HN$50,MATCH(1,(GMW!$HM$2:$HM$50=E$3)*(GMW!$HN$2:$HN$50=E$1),0),$B21-1973)} -> 280996 | F21: {=INDEX(GMW!$A$2:$HN$50,MATCH(1,(GMW!$HM$2:$HM$50=F$3)*(GMW!$HN$2:$HN$50=F$1),0),$B21-1973)} -> 23809 | G21: {=INDEX(GMW!$A$2:$HN$50,MATCH(1,(GMW!$HM$2:$HM$50=G$3)*(GMW!$HN$2:$HN$50=G$1),0),$B21-1973)} -> 1777.221 | H21: {=INDEX(GMW!$A$2:$HN$50,MATCH(1,(GMW!$HM$2:$HM$50=H$3)*(GMW!$HN$2:$HN$50=H$1),0),$B21-1973)} -> 11.5 | I21: {=INDEX(GMW!$A$2:$HN$50,MATCH(1,(GMW!$HM$2:$HM$50=I$3)*(GMW!$HN$2:$HN$50=I$1),0),$B21-1973)} -> 163522 | J21: {=INDEX(GMW!$A$2:$HN$50,MATCH(1,(GMW!$HM$2:$HM$50=J$3)*(GMW!$HN$2:$HN$50=J$1),0),$B21-1973)} -> 2987.303 | K21: {=INDEX(GMW!$A$2:$HN$50,MATCH(1,(GMW!$HM$2:$HM$50=K$3)*(GMW!$HN$2:$HN$50=K$1),0),$B21-1973)} -> 280996 | L21: {=INDEX(GMW!$A$2:$HN$50,MATCH(1,(GMW!$HM$2:$HM$50=L$3)*(GMW!$HN$2:$HN$50=L$1),0),$B21-1973)} -> 23809 | ... P21: {=INDEX(GMW!$A$2:$HN$50,MATCH(1,(GMW!$HM$2:$HM$50=P$3)*(GMW!$HN$2:$HN$50=P$1),0),$B21-1973)} -> 2987.303
B22: =+B21+1 -> 1995 | C22: =+C18+1 -> 1983 | D22: =+D18+1 -> 1983 | E22: {=INDEX(GMW!$A$2:$HN$50,MATCH(1,(GMW!$HM$2:$HM$50=E$3)*(GMW!$HN$2:$HN$50=E$1),0),$B22-1973)} -> 283096 | F22: {=INDEX(GMW!$A$2:$HN$50,MATCH(1,(GMW!$HM$2:$HM$50=F$3)*(GMW!$HN$2:$HN$50=F$1),0),$B22-1973)} -> 23994 | G22: {=INDEX(GMW!$A$2:$HN$50,MATCH(1,(GMW!$HM$2:$HM$50=G$3)*(GMW!$HN$2:$HN$50=G$1),0),$B22-1973)} -> 1805.329 | H22: {=INDEX(GMW!$A$2:$HN$50,MATCH(1,(GMW!$HM$2:$HM$50=H$3)*(GMW!$HN$2:$HN$50=H$1),0),$B22-1973)} -> 11.7 | I22: {=INDEX(GMW!$A$2:$HN$50,MATCH(1,(GMW!$HM$2:$HM$50=I$3)*(GMW!$HN$2:$HN$50=I$1),0),$B22-1973)} -> 164202 | J22: {=INDEX(GMW!$A$2:$HN$50,MATCH(1,(GMW!$HM$2:$HM$50=J$3)*(GMW!$HN$2:$HN$50=J$1),0),$B22-1973)} -> 3060.384 | K22: {=INDEX(GMW!$A$2:$HN$50,MATCH(1,(GMW!$HM$2:$HM$50=K$3)*(GMW!$HN$2:$HN$50=K$1),0),$B22-1973)} -> 283096 | L22: {=INDEX(GMW!$A$2:$HN$50,MATCH(1,(GMW!$HM$2:$HM$50=L$3)*(GMW!$HN$2:$HN$50=L$1),0),$B22-1973)} -> 23994 | ... P22: {=INDEX(GMW!$A$2:$HN$50,MATCH(1,(GMW!$HM$2:$HM$50=P$3)*(GMW!$HN$2:$HN$50=P$1),0),$B22-1973)} -> 3060.384
A23: 1984 | B23: =+B22+1 -> 1996 | C23: =+C19+1 -> 1984 | D23: =+D19+1 -> 1983 | E23: {=INDEX(GMW!$A$2:$HN$50,MATCH(1,(GMW!$HM$2:$HM$50=E$3)*(GMW!$HN$2:$HN$50=E$1),0),$B23-1973)} -> 285469 | F23: {=INDEX(GMW!$A$2:$HN$50,MATCH(1,(GMW!$HM$2:$HM$50=F$3)*(GMW!$HN$2:$HN$50=F$1),0),$B23-1973)} -> 24125 | G23: {=INDEX(GMW!$A$2:$HN$50,MATCH(1,(GMW!$HM$2:$HM$50=G$3)*(GMW!$HN$2:$HN$50=G$1),0),$B23-1973)} -> 1833.021 | H23: {=INDEX(GMW!$A$2:$HN$50,MATCH(1,(GMW!$HM$2:$HM$50=H$3)*(GMW!$HN$2:$HN$50=H$1),0),$B23-1973)} -> 11.8 | I23: {=INDEX(GMW!$A$2:$HN$50,MATCH(1,(GMW!$HM$2:$HM$50=I$3)*(GMW!$HN$2:$HN$50=I$1),0),$B23-1973)} -> 167088 | J23: {=INDEX(GMW!$A$2:$HN$50,MATCH(1,(GMW!$HM$2:$HM$50=J$3)*(GMW!$HN$2:$HN$50=J$1),0),$B23-1973)} -> 3088.492 | K23: {=INDEX(GMW!$A$2:$HN$50,MATCH(1,(GMW!$HM$2:$HM$50=K$3)*(GMW!$HN$2:$HN$50=K$1),0),$B23-1973)} -> 285469 | L23: {=INDEX(GMW!$A$2:$HN$50,MATCH(1,(GMW!$HM$2:$HM$50=L$3)*(GMW!$HN$2:$HN$50=L$1),0),$B23-1973)} -> 24125 | ... P23: {=INDEX(GMW!$A$2:$HN$50,MATCH(1,(GMW!$HM$2:$HM$50=P$3)*(GMW!$HN$2:$HN$50=P$1),0),$B23-1973)} -> 3088.492
B24: =+B23+1 -> 1997 | C24: =+C20+1 -> 1984 | D24: =+D20+1 -> 1984 | E24: {=INDEX(GMW!$A$2:$HN$50,MATCH(1,(GMW!$HM$2:$HM$50=E$3)*(GMW!$HN$2:$HN$50=E$1),0),$B24-1973)} -> 282605 | F24: {=INDEX(GMW!$A$2:$HN$50,MATCH(1,(GMW!$HM$2:$HM$50=F$3)*(GMW!$HN$2:$HN$50=F$1),0),$B24-1973)} -> 24245 | G24: {=INDEX(GMW!$A$2:$HN$50,MATCH(1,(GMW!$HM$2:$HM$50=G$3)*(GMW!$HN$2:$HN$50=G$1),0),$B24-1973)} -> 1859.965 | H24: {=INDEX(GMW!$A$2:$HN$50,MATCH(1,(GMW!$HM$2:$HM$50=H$3)*(GMW!$HN$2:$HN$50=H$1),0),$B24-1973)} -> 11.9 | I24: {=INDEX(GMW!$A$2:$HN$50,MATCH(1,(GMW!$HM$2:$HM$50=I$3)*(GMW!$HN$2:$HN$50=I$1),0),$B24-1973)} -> 165111 | J24: {=INDEX(GMW!$A$2:$HN$50,MATCH(1,(GMW!$HM$2:$HM$50=J$3)*(GMW!$HN$2:$HN$50=J$1),0),$B24-1973)} -> 3128.967 | K24: {=INDEX(GMW!$A$2:$HN$50,MATCH(1,(GMW!$HM$2:$HM$50=K$3)*(GMW!$HN$2:$HN$50=K$1),0),$B24-1973)} -> 282605 | L24: {=INDEX(GMW!$A$2:$HN$50,MATCH(1,(GMW!$HM$2:$HM$50=L$3)*(GMW!$HN$2:$HN$50=L$1),0),$B24-1973)} -> 24245 | ... P24: {=INDEX(GMW!$A$2:$HN$50,MATCH(1,(GMW!$HM$2:$HM$50=P$3)*(GMW!$HN$2:$HN$50=P$1),0),$B24-1973)} -> 3128.967
B25: =+B24+1 -> 1998 | C25: =+C21+1 -> 1984 | D25: =+D21+1 -> 1984 | E25: {=INDEX(GMW!$A$2:$HN$50,MATCH(1,(GMW!$HM$2:$HM$50=E$3)*(GMW!$HN$2:$HN$50=E$1),0),$B25-1973)} -> 284676 | F25: {=INDEX(GMW!$A$2:$HN$50,MATCH(1,(GMW!$HM$2:$HM$50=F$3)*(GMW!$HN$2:$HN$50=F$1),0),$B25-1973)} -> 24335 | G25: {=INDEX(GMW!$A$2:$HN$50,MATCH(1,(GMW!$HM$2:$HM$50=G$3)*(GMW!$HN$2:$HN$50=G$1),0),$B25-1973)} -> 1876.902 | H25: {=INDEX(GMW!$A$2:$HN$50,MATCH(1,(GMW!$HM$2:$HM$50=H$3)*(GMW!$HN$2:$HN$50=H$1),0),$B25-1973)} -> 11.7 | I25: {=INDEX(GMW!$A$2:$HN$50,MATCH(1,(GMW!$HM$2:$HM$50=I$3)*(GMW!$HN$2:$HN$50=I$1),0),$B25-1973)} -> 169770 | J25: {=INDEX(GMW!$A$2:$HN$50,MATCH(1,(GMW!$HM$2:$HM$50=J$3)*(GMW!$HN$2:$HN$50=J$1),0),$B25-1973)} -> 3185.183 | K25: {=INDEX(GMW!$A$2:$HN$50,MATCH(1,(GMW!$HM$2:$HM$50=K$3)*(GMW!$HN$2:$HN$50=K$1),0),$B25-1973)} -> 284676 | L25: {=INDEX(GMW!$A$2:$HN$50,MATCH(1,(GMW!$HM$2:$HM$50=L$3)*(GMW!$HN$2:$HN$50=L$1),0),$B25-1973)} -> 24335 | ... P25: {=INDEX(GMW!$A$2:$HN$50,MATCH(1,(GMW!$HM$2:$HM$50=P$3)*(GMW!$HN$2:$HN$50=P$1),0),$B25-1973)} -> 3185.183
B26: =+B25+1 -> 1999 | C26: =+C22+1 -> 1984 | D26: =+D22+1 -> 1984 | E26: {=INDEX(GMW!$A$2:$HN$50,MATCH(1,(GMW!$HM$2:$HM$50=E$3)*(GMW!$HN$2:$HN$50=E$1),0),$B26-1973)} -> 289829 | F26: {=INDEX(GMW!$A$2:$HN$50,MATCH(1,(GMW!$HM$2:$HM$50=F$3)*(GMW!$HN$2:$HN$50=F$1),0),$B26-1973)} -> 24435 | G26: {=INDEX(GMW!$A$2:$HN$50,MATCH(1,(GMW!$HM$2:$HM$50=G$3)*(GMW!$HN$2:$HN$50=G$1),0),$B26-1973)} -> 1935.882 | H26: {=INDEX(GMW!$A$2:$HN$50,MATCH(1,(GMW!$HM$2:$HM$50=H$3)*(GMW!$HN$2:$HN$50=H$1),0),$B26-1973)} -> 11.6 | I26: {=INDEX(GMW!$A$2:$HN$50,MATCH(1,(GMW!$HM$2:$HM$50=I$3)*(GMW!$HN$2:$HN$50=I$1),0),$B26-1973)} -> 173527 | J26: {=INDEX(GMW!$A$2:$HN$50,MATCH(1,(GMW!$HM$2:$HM$50=J$3)*(GMW!$HN$2:$HN$50=J$1),0),$B26-1973)} -> 3267.258 | K26: {=INDEX(GMW!$A$2:$HN$50,MATCH(1,(GMW!$HM$2:$HM$50=K$3)*(GMW!$HN$2:$HN$50=K$1),0),$B26-1973)} -> 289829 | L26: {=INDEX(GMW!$A$2:$HN$50,MATCH(1,(GMW!$HM$2:$HM$50=L$3)*(GMW!$HN$2:$HN$50=L$1),0),$B26-1973)} -> 24435 | ... P26: {=INDEX(GMW!$A$2:$HN$50,MATCH(1,(GMW!$HM$2:$HM$50=P$3)*(GMW!$HN$2:$HN$50=P$1),0),$B26-1973)} -> 3267.258
A27: 1985 | B27: =+B26+1 -> 2000 | C27: =+C23+1 -> 1985 | D27: =+D23+1 -> 1984 | E27: {=INDEX(GMW!$A$2:$HN$50,MATCH(1,(GMW!$HM$2:$HM$50=E$3)*(GMW!$HN$2:$HN$50=E$1),0),$B27-1973)} -> 292612 | F27: {=INDEX(GMW!$A$2:$HN$50,MATCH(1,(GMW!$HM$2:$HM$50=F$3)*(GMW!$HN$2:$HN$50=F$1),0),$B27-1973)} -> 24515 | G27: {=INDEX(GMW!$A$2:$HN$50,MATCH(1,(GMW!$HM$2:$HM$50=G$3)*(GMW!$HN$2:$HN$50=G$1),0),$B27-1973)} -> 1996.246 | H27: {=INDEX(GMW!$A$2:$HN$50,MATCH(1,(GMW!$HM$2:$HM$50=H$3)*(GMW!$HN$2:$HN$50=H$1),0),$B27-1973)} -> 11.5 | I27: {=INDEX(GMW!$A$2:$HN$50,MATCH(1,(GMW!$HM$2:$HM$50=I$3)*(GMW!$HN$2:$HN$50=I$1),0),$B27-1973)} -> 175208 | J27: {=INDEX(GMW!$A$2:$HN$50,MATCH(1,(GMW!$HM$2:$HM$50=J$3)*(GMW!$HN$2:$HN$50=J$1),0),$B27-1973)} -> 3359.452 | K27: {=INDEX(GMW!$A$2:$HN$50,MATCH(1,(GMW!$HM$2:$HM$50=K$3)*(GMW!$HN$2:$HN$50=K$1),0),$B27-1973)} -> 292612 | L27: {=INDEX(GMW!$A$2:$HN$50,MATCH(1,(GMW!$HM$2:$HM$50=L$3)*(GMW!$HN$2:$HN$50=L$1),0),$B27-1973)} -> 24515 | ... P27: {=INDEX(GMW!$A$2:$HN$50,MATCH(1,(GMW!$HM$2:$HM$50=P$3)*(GMW!$HN$2:$HN$50=P$1),0),$B27-1973)} -> 3359.452
B28: =+B27+1 -> 2001 | C28: =+C24+1 -> 1985 | D28: =+D24+1 -> 1985 | E28: {=INDEX(GMW!$A$2:$HN$50,MATCH(1,(GMW!$HM$2:$HM$50=E$3)*(GMW!$HN$2:$HN$50=E$1),0),$B28-1973)} -> 298873 | F28: {=INDEX(GMW!$A$2:$HN$50,MATCH(1,(GMW!$HM$2:$HM$50=F$3)*(GMW!$HN$2:$HN$50=F$1),0),$B28-1973)} -> 24570 | G28: {=INDEX(GMW!$A$2:$HN$50,MATCH(1,(GMW!$HM$2:$HM$50=G$3)*(GMW!$HN$2:$HN$50=G$1),0),$B28-1973)} -> 2015.939 | H28: {=INDEX(GMW!$A$2:$HN$50,MATCH(1,(GMW!$HM$2:$HM$50=H$3)*(GMW!$HN$2:$HN$50=H$1),0),$B28-1973)} -> 11.4 | I28: {=INDEX(GMW!$A$2:$HN$50,MATCH(1,(GMW!$HM$2:$HM$50=I$3)*(GMW!$HN$2:$HN$50=I$1),0),$B28-1973)} -> 175613 | J28: {=INDEX(GMW!$A$2:$HN$50,MATCH(1,(GMW!$HM$2:$HM$50=J$3)*(GMW!$HN$2:$HN$50=J$1),0),$B28-1973)} -> 3403.3 | K28: {=INDEX(GMW!$A$2:$HN$50,MATCH(1,(GMW!$HM$2:$HM$50=K$3)*(GMW!$HN$2:$HN$50=K$1),0),$B28-1973)} -> 298873 | L28: {=INDEX(GMW!$A$2:$HN$50,MATCH(1,(GMW!$HM$2:$HM$50=L$3)*(GMW!$HN$2:$HN$50=L$1),0),$B28-1973)} -> 24570 | ... P28: {=INDEX(GMW!$A$2:$HN$50,MATCH(1,(GMW!$HM$2:$HM$50=P$3)*(GMW!$HN$2:$HN$50=P$1),0),$B28-1973)} -> 3403.3
B29: =+B28+1 -> 2002 | C29: =+C25+1 -> 1985 | D29: =+D25+1 -> 1985 | E29: {=INDEX(GMW!$A$2:$HN$50,MATCH(1,(GMW!$HM$2:$HM$50=E$3)*(GMW!$HN$2:$HN$50=E$1),0),$B29-1973)} -> 298814 | F29: {=INDEX(GMW!$A$2:$HN$50,MATCH(1,(GMW!$HM$2:$HM$50=F$3)*(GMW!$HN$2:$HN$50=F$1),0),$B29-1973)} -> 24625 | G29: {=INDEX(GMW!$A$2:$HN$50,MATCH(1,(GMW!$HM$2:$HM$50=G$3)*(GMW!$HN$2:$HN$50=G$1),0),$B29-1973)} -> 2043.298 | H29: {=INDEX(GMW!$A$2:$HN$50,MATCH(1,(GMW!$HM$2:$HM$50=H$3)*(GMW!$HN$2:$HN$50=H$1),0),$B29-1973)} -> 11.3 | I29: {=INDEX(GMW!$A$2:$HN$50,MATCH(1,(GMW!$HM$2:$HM$50=I$3)*(GMW!$HN$2:$HN$50=I$1),0),$B29-1973)} -> 175957 | J29: {=INDEX(GMW!$A$2:$HN$50,MATCH(1,(GMW!$HM$2:$HM$50=J$3)*(GMW!$HN$2:$HN$50=J$1),0),$B29-1973)} -> 3447.148 | K29: {=INDEX(GMW!$A$2:$HN$50,MATCH(1,(GMW!$HM$2:$HM$50=K$3)*(GMW!$HN$2:$HN$50=K$1),0),$B29-1973)} -> 298814 | L29: {=INDEX(GMW!$A$2:$HN$50,MATCH(1,(GMW!$HM$2:$HM$50=L$3)*(GMW!$HN$2:$HN$50=L$1),0),$B29-1973)} -> 24625 | ... P29: {=INDEX(GMW!$A$2:$HN$50,MATCH(1,(GMW!$HM$2:$HM$50=P$3)*(GMW!$HN$2:$HN$50=P$1),0),$B29-1973)} -> 3447.148
B30: =+B29+1 -> 2003 | C30: =+C26+1 -> 1985 | D30: =+D26+1 -> 1985 | E30: {=INDEX(GMW!$A$2:$HN$50,MATCH(1,(GMW!$HM$2:$HM$50=E$3)*(GMW!$HN$2:$HN$50=E$1),0),$B30-1973)} -> 298979 | F30: {=INDEX(GMW!$A$2:$HN$50,MATCH(1,(GMW!$HM$2:$HM$50=F$3)*(GMW!$HN$2:$HN$50=F$1),0),$B30-1973)} -> 24660 | G30: {=INDEX(GMW!$A$2:$HN$50,MATCH(1,(GMW!$HM$2:$HM$50=G$3)*(GMW!$HN$2:$HN$50=G$1),0),$B30-1973)} -> 2093.281 | H30: {=INDEX(GMW!$A$2:$HN$50,MATCH(1,(GMW!$HM$2:$HM$50=H$3)*(GMW!$HN$2:$HN$50=H$1),0),$B30-1973)} -> 11.3 | I30: {=INDEX(GMW!$A$2:$HN$50,MATCH(1,(GMW!$HM$2:$HM$50=I$3)*(GMW!$HN$2:$HN$50=I$1),0),$B30-1973)} -> 177164 | J30: {=INDEX(GMW!$A$2:$HN$50,MATCH(1,(GMW!$HM$2:$HM$50=J$3)*(GMW!$HN$2:$HN$50=J$1),0),$B30-1973)} -> 3557.331 | K30: {=INDEX(GMW!$A$2:$HN$50,MATCH(1,(GMW!$HM$2:$HM$50=K$3)*(GMW!$HN$2:$HN$50=K$1),0),$B30-1973)} -> 298979 | L30: {=INDEX(GMW!$A$2:$HN$50,MATCH(1,(GMW!$HM$2:$HM$50=L$3)*(GMW!$HN$2:$HN$50=L$1),0),$B30-1973)} -> 24660 | ... P30: {=INDEX(GMW!$A$2:$HN$50,MATCH(1,(GMW!$HM$2:$HM$50=P$3)*(GMW!$HN$2:$HN$50=P$1),0),$B30-1973)} -> 3557.331
A31: 1986 | B31: =+B30+1 -> 2004 | C31: =+C27+1 -> 1986 | D31: =+D27+1 -> 1985 | E31: {=INDEX(GMW!$A$2:$HN$50,MATCH(1,(GMW!$HM$2:$HM$50=E$3)*(GMW!$HN$2:$HN$50=E$1),0),$B31-1973)} -> 302117 | F31: {=INDEX(GMW!$A$2:$HN$50,MATCH(1,(GMW!$HM$2:$HM$50=F$3)*(GMW!$HN$2:$HN$50=F$1),0),$B31-1973)} -> 24670 | G31: {=INDEX(GMW!$A$2:$HN$50,MATCH(1,(GMW!$HM$2:$HM$50=G$3)*(GMW!$HN$2:$HN$50=G$1),0),$B31-1973)} -> 2142.593 | H31: {=INDEX(GMW!$A$2:$HN$50,MATCH(1,(GMW!$HM$2:$HM$50=H$3)*(GMW!$HN$2:$HN$50=H$1),0),$B31-1973)} -> 11.3 | I31: {=INDEX(GMW!$A$2:$HN$50,MATCH(1,(GMW!$HM$2:$HM$50=I$3)*(GMW!$HN$2:$HN$50=I$1),0),$B31-1973)} -> 179729 | J31: {=INDEX(GMW!$A$2:$HN$50,MATCH(1,(GMW!$HM$2:$HM$50=J$3)*(GMW!$HN$2:$HN$50=J$1),0),$B31-1973)} -> 3637.157 | K31: {=INDEX(GMW!$A$2:$HN$50,MATCH(1,(GMW!$HM$2:$HM$50=K$3)*(GMW!$HN$2:$HN$50=K$1),0),$B31-1973)} -> 302117 | L31: {=INDEX(GMW!$A$2:$HN$50,MATCH(1,(GMW!$HM$2:$HM$50=L$3)*(GMW!$HN$2:$HN$50=L$1),0),$B31-1973)} -> 24670 | ... P31: {=INDEX(GMW!$A$2:$HN$50,MATCH(1,(GMW!$HM$2:$HM$50=P$3)*(GMW!$HN$2:$HN$50=P$1),0),$B31-1973)} -> 3637.157
B32: =+B31+1 -> 2005 | C32: =+C28+1 -> 1986 | D32: =+D28+1 -> 1986 | E32: {=INDEX(GMW!$A$2:$HN$50,MATCH(1,(GMW!$HM$2:$HM$50=E$3)*(GMW!$HN$2:$HN$50=E$1),0),$B32-1973)} -> 304797 | F32: {=INDEX(GMW!$A$2:$HN$50,MATCH(1,(GMW!$HM$2:$HM$50=F$3)*(GMW!$HN$2:$HN$50=F$1),0),$B32-1973)} -> 24695 | G32: {=INDEX(GMW!$A$2:$HN$50,MATCH(1,(GMW!$HM$2:$HM$50=G$3)*(GMW!$HN$2:$HN$50=G$1),0),$B32-1973)} -> 2185.823 | H32: {=INDEX(GMW!$A$2:$HN$50,MATCH(1,(GMW!$HM$2:$HM$50=H$3)*(GMW!$HN$2:$HN$50=H$1),0),$B32-1973)} -> 11.3 | I32: {=INDEX(GMW!$A$2:$HN$50,MATCH(1,(GMW!$HM$2:$HM$50=I$3)*(GMW!$HN$2:$HN$50=I$1),0),$B32-1973)} -> 186661 | J32: {=INDEX(GMW!$A$2:$HN$50,MATCH(1,(GMW!$HM$2:$HM$50=J$3)*(GMW!$HN$2:$HN$50=J$1),0),$B32-1973)} -> 3792.313 | K32: {=INDEX(GMW!$A$2:$HN$50,MATCH(1,(GMW!$HM$2:$HM$50=K$3)*(GMW!$HN$2:$HN$50=K$1),0),$B32-1973)} -> 304797 | L32: {=INDEX(GMW!$A$2:$HN$50,MATCH(1,(GMW!$HM$2:$HM$50=L$3)*(GMW!$HN$2:$HN$50=L$1),0),$B32-1973)} -> 24695 | ... P32: {=INDEX(GMW!$A$2:$HN$50,MATCH(1,(GMW!$HM$2:$HM$50=P$3)*(GMW!$HN$2:$HN$50=P$1),0),$B32-1973)} -> 3792.313
B33: =+B32+1 -> 2006 | C33: =+C29+1 -> 1986 | D33: =+D29+1 -> 1986 | E33: {=INDEX(GMW!$A$2:$HN$50,MATCH(1,(GMW!$HM$2:$HM$50=E$3)*(GMW!$HN$2:$HN$50=E$1),0),$B33-1973)} -> 306708 | F33: {=INDEX(GMW!$A$2:$HN$50,MATCH(1,(GMW!$HM$2:$HM$50=F$3)*(GMW!$HN$2:$HN$50=F$1),0),$B33-1973)} -> 24770 | G33: {=INDEX(GMW!$A$2:$HN$50,MATCH(1,(GMW!$HM$2:$HM$50=G$3)*(GMW!$HN$2:$HN$50=G$1),0),$B33-1973)} -> 2220.435 | H33: {=INDEX(GMW!$A$2:$HN$50,MATCH(1,(GMW!$HM$2:$HM$50=H$3)*(GMW!$HN$2:$HN$50=H$1),0),$B33-1973)} -> 11.4 | I33: {=INDEX(GMW!$A$2:$HN$50,MATCH(1,(GMW!$HM$2:$HM$50=I$3)*(GMW!$HN$2:$HN$50=I$1),0),$B33-1973)} -> 183119 | J33: {=INDEX(GMW!$A$2:$HN$50,MATCH(1,(GMW!$HM$2:$HM$50=J$3)*(GMW!$HN$2:$HN$50=J$1),0),$B33-1973)} -> 3863.145 | K33: {=INDEX(GMW!$A$2:$HN$50,MATCH(1,(GMW!$HM$2:$HM$50=K$3)*(GMW!$HN$2:$HN$50=K$1),0),$B33-1973)} -> 306708 | L33: {=INDEX(GMW!$A$2:$HN$50,MATCH(1,(GMW!$HM$2:$HM$50=L$3)*(GMW!$HN$2:$HN$50=L$1),0),$B33-1973)} -> 24770 | ... P33: {=INDEX(GMW!$A$2:$HN$50,MATCH(1,(GMW!$HM$2:$HM$50=P$3)*(GMW!$HN$2:$HN$50=P$1),0),$B33-1973)} -> 3863.145
B34: =+B33+1 -> 2007 | C34: =+C30+1 -> 1986 | D34: =+D30+1 -> 1986 | E34: {=INDEX(GMW!$A$2:$HN$50,MATCH(1,(GMW!$HM$2:$HM$50=E$3)*(GMW!$HN$2:$HN$50=E$1),0),$B34-1973)} -> 312615 | F34: {=INDEX(GMW!$A$2:$HN$50,MATCH(1,(GMW!$HM$2:$HM$50=F$3)*(GMW!$HN$2:$HN$50=F$1),0),$B34-1973)} -> 24850 | G34: {=INDEX(GMW!$A$2:$HN$50,MATCH(1,(GMW!$HM$2:$HM$50=G$3)*(GMW!$HN$2:$HN$50=G$1),0),$B34-1973)} -> 2251.233 | H34: {=INDEX(GMW!$A$2:$HN$50,MATCH(1,(GMW!$HM$2:$HM$50=H$3)*(GMW!$HN$2:$HN$50=H$1),0),$B34-1973)} -> 11.3 | I34: {=INDEX(GMW!$A$2:$HN$50,MATCH(1,(GMW!$HM$2:$HM$50=I$3)*(GMW!$HN$2:$HN$50=I$1),0),$B34-1973)} -> 183388 | J34: {=INDEX(GMW!$A$2:$HN$50,MATCH(1,(GMW!$HM$2:$HM$50=J$3)*(GMW!$HN$2:$HN$50=J$1),0),$B34-1973)} -> 3930.603 | K34: {=INDEX(GMW!$A$2:$HN$50,MATCH(1,(GMW!$HM$2:$HM$50=K$3)*(GMW!$HN$2:$HN$50=K$1),0),$B34-1973)} -> 312615 | L34: {=INDEX(GMW!$A$2:$HN$50,MATCH(1,(GMW!$HM$2:$HM$50=L$3)*(GMW!$HN$2:$HN$50=L$1),0),$B34-1973)} -> 24850 | ... P34: {=INDEX(GMW!$A$2:$HN$50,MATCH(1,(GMW!$HM$2:$HM$50=P$3)*(GMW!$HN$2:$HN$50=P$1),0),$B34-1973)} -> 3930.603
A35: 1987 | B35: =+B34+1 -> 2008 | C35: =+C31+1 -> 1987 | D35: =+D31+1 -> 1986 | E35: {=INDEX(GMW!$A$2:$HN$50,MATCH(1,(GMW!$HM$2:$HM$50=E$3)*(GMW!$HN$2:$HN$50=E$1),0),$B35-1973)} -> 314804 | F35: {=INDEX(GMW!$A$2:$HN$50,MATCH(1,(GMW!$HM$2:$HM$50=F$3)*(GMW!$HN$2:$HN$50=F$1),0),$B35-1973)} -> 24925 | G35: {=INDEX(GMW!$A$2:$HN$50,MATCH(1,(GMW!$HM$2:$HM$50=G$3)*(GMW!$HN$2:$HN$50=G$1),0),$B35-1973)} -> 2282.895 | H35: {=INDEX(GMW!$A$2:$HN$50,MATCH(1,(GMW!$HM$2:$HM$50=H$3)*(GMW!$HN$2:$HN$50=H$1),0),$B35-1973)} -> 11.1 | I35: {=INDEX(GMW!$A$2:$HN$50,MATCH(1,(GMW!$HM$2:$HM$50=I$3)*(GMW!$HN$2:$HN$50=I$1),0),$B35-1973)} -> 180901 | J35: {=INDEX(GMW!$A$2:$HN$50,MATCH(1,(GMW!$HM$2:$HM$50=J$3)*(GMW!$HN$2:$HN$50=J$1),0),$B35-1973)} -> 4305 | K35: {=INDEX(GMW!$A$2:$HN$50,MATCH(1,(GMW!$HM$2:$HM$50=K$3)*(GMW!$HN$2:$HN$50=K$1),0),$B35-1973)} -> 314804 | L35: {=INDEX(GMW!$A$2:$HN$50,MATCH(1,(GMW!$HM$2:$HM$50=L$3)*(GMW!$HN$2:$HN$50=L$1),0),$B35-1973)} -> 24925 | ... P35: {=INDEX(GMW!$A$2:$HN$50,MATCH(1,(GMW!$HM$2:$HM$50=P$3)*(GMW!$HN$2:$HN$50=P$1),0),$B35-1973)} -> 4305
B36: =+B35+1 -> 2009 | C36: =+C32+1 -> 1987 | D36: =+D32+1 -> 1987 | E36: {=INDEX(GMW!$A$2:$HN$50,MATCH(1,(GMW!$HM$2:$HM$50=E$3)*(GMW!$HN$2:$HN$50=E$1),0),$B36-1973)} -> 319478 | F36: {=INDEX(GMW!$A$2:$HN$50,MATCH(1,(GMW!$HM$2:$HM$50=F$3)*(GMW!$HN$2:$HN$50=F$1),0),$B36-1973)} -> 25110 | G36: {=INDEX(GMW!$A$2:$HN$50,MATCH(1,(GMW!$HM$2:$HM$50=G$3)*(GMW!$HN$2:$HN$50=G$1),0),$B36-1973)} -> 2321.792 | H36: {=INDEX(GMW!$A$2:$HN$50,MATCH(1,(GMW!$HM$2:$HM$50=H$3)*(GMW!$HN$2:$HN$50=H$1),0),$B36-1973)} -> 10.7 | I36: {=INDEX(GMW!$A$2:$HN$50,MATCH(1,(GMW!$HM$2:$HM$50=I$3)*(GMW!$HN$2:$HN$50=I$1),0),$B36-1973)} -> 185020 | J36: {=INDEX(GMW!$A$2:$HN$50,MATCH(1,(GMW!$HM$2:$HM$50=J$3)*(GMW!$HN$2:$HN$50=J$1),0),$B36-1973)} -> 4334 | K36: {=INDEX(GMW!$A$2:$HN$50,MATCH(1,(GMW!$HM$2:$HM$50=K$3)*(GMW!$HN$2:$HN$50=K$1),0),$B36-1973)} -> 319478 | L36: {=INDEX(GMW!$A$2:$HN$50,MATCH(1,(GMW!$HM$2:$HM$50=L$3)*(GMW!$HN$2:$HN$50=L$1),0),$B36-1973)} -> 25110 | ... P36: {=INDEX(GMW!$A$2:$HN$50,MATCH(1,(GMW!$HM$2:$HM$50=P$3)*(GMW!$HN$2:$HN$50=P$1),0),$B36-1973)} -> 4334
B37: =+B36+1 -> 2010 | C37: =+C33+1 -> 1987 | D37: =+D33+1 -> 1987 | E37: {=INDEX(GMW!$A$2:$HN$50,MATCH(1,(GMW!$HM$2:$HM$50=E$3)*(GMW!$HN$2:$HN$50=E$1),0),$B37-1973)} -> 327346 | F37: {=INDEX(GMW!$A$2:$HN$50,MATCH(1,(GMW!$HM$2:$HM$50=F$3)*(GMW!$HN$2:$HN$50=F$1),0),$B37-1973)} -> 25345 | G37: {=INDEX(GMW!$A$2:$HN$50,MATCH(1,(GMW!$HM$2:$HM$50=G$3)*(GMW!$HN$2:$HN$50=G$1),0),$B37-1973)} -> 2369.95 | H37: {=INDEX(GMW!$A$2:$HN$50,MATCH(1,(GMW!$HM$2:$HM$50=H$3)*(GMW!$HN$2:$HN$50=H$1),0),$B37-1973)} -> 10.2 | I37: {=INDEX(GMW!$A$2:$HN$50,MATCH(1,(GMW!$HM$2:$HM$50=I$3)*(GMW!$HN$2:$HN$50=I$1),0),$B37-1973)} -> 187551 | J37: {=INDEX(GMW!$A$2:$HN$50,MATCH(1,(GMW!$HM$2:$HM$50=J$3)*(GMW!$HN$2:$HN$50=J$1),0),$B37-1973)} -> 4487 | K37: {=INDEX(GMW!$A$2:$HN$50,MATCH(1,(GMW!$HM$2:$HM$50=K$3)*(GMW!$HN$2:$HN$50=K$1),0),$B37-1973)} -> 327346 | L37: {=INDEX(GMW!$A$2:$HN$50,MATCH(1,(GMW!$HM$2:$HM$50=L$3)*(GMW!$HN$2:$HN$50=L$1),0),$B37-1973)} -> 25345 | ... P37: {=INDEX(GMW!$A$2:$HN$50,MATCH(1,(GMW!$HM$2:$HM$50=P$3)*(GMW!$HN$2:$HN$50=P$1),0),$B37-1973)} -> 4487
B38: =+B37+1 -> 2011 | C38: =+C34+1 -> 1987 | D38: =+D34+1 -> 1987 | E38: {=INDEX(GMW!$A$2:$HN$50,MATCH(1,(GMW!$HM$2:$HM$50=E$3)*(GMW!$HN$2:$HN$50=E$1),0),$B38-1973)} -> 331075 | F38: {=INDEX(GMW!$A$2:$HN$50,MATCH(1,(GMW!$HM$2:$HM$50=F$3)*(GMW!$HN$2:$HN$50=F$1),0),$B38-1973)} -> 25575 | G38: {=INDEX(GMW!$A$2:$HN$50,MATCH(1,(GMW!$HM$2:$HM$50=G$3)*(GMW!$HN$2:$HN$50=G$1),0),$B38-1973)} -> 2418.279 | H38: {=INDEX(GMW!$A$2:$HN$50,MATCH(1,(GMW!$HM$2:$HM$50=H$3)*(GMW!$HN$2:$HN$50=H$1),0),$B38-1973)} -> 9.7 | I38: {=INDEX(GMW!$A$2:$HN$50,MATCH(1,(GMW!$HM$2:$HM$50=I$3)*(GMW!$HN$2:$HN$50=I$1),0),$B38-1973)} -> 188860 | J38: {=INDEX(GMW!$A$2:$HN$50,MATCH(1,(GMW!$HM$2:$HM$50=J$3)*(GMW!$HN$2:$HN$50=J$1),0),$B38-1973)} -> 4632 | K38: {=INDEX(GMW!$A$2:$HN$50,MATCH(1,(GMW!$HM$2:$HM$50=K$3)*(GMW!$HN$2:$HN$50=K$1),0),$B38-1973)} -> 331075 | L38: {=INDEX(GMW!$A$2:$HN$50,MATCH(1,(GMW!$HM$2:$HM$50=L$3)*(GMW!$HN$2:$HN$50=L$1),0),$B38-1973)} -> 25575 | ... P38: {=INDEX(GMW!$A$2:$HN$50,MATCH(1,(GMW!$HM$2:$HM$50=P$3)*(GMW!$HN$2:$HN$50=P$1),0),$B38-1973)} -> 4632
A39: 1988 | B39: =+B38+1 -> 2012 | C39: =+C35+1 -> 1988 | D39: =+D35+1 -> 1987 | E39: {=INDEX(GMW!$A$2:$HN$50,MATCH(1,(GMW!$HM$2:$HM$50=E$3)*(GMW!$HN$2:$HN$50=E$1),0),$B39-1973)} -> 336442 | F39: {=INDEX(GMW!$A$2:$HN$50,MATCH(1,(GMW!$HM$2:$HM$50=F$3)*(GMW!$HN$2:$HN$50=F$1),0),$B39-1973)} -> 25795 | G39: {=INDEX(GMW!$A$2:$HN$50,MATCH(1,(GMW!$HM$2:$HM$50=G$3)*(GMW!$HN$2:$HN$50=G$1),0),$B39-1973)} -> 2470.636 | H39: {=INDEX(GMW!$A$2:$HN$50,MATCH(1,(GMW!$HM$2:$HM$50=H$3)*(GMW!$HN$2:$HN$50=H$1),0),$B39-1973)} -> 9.2 | I39: {=INDEX(GMW!$A$2:$HN$50,MATCH(1,(GMW!$HM$2:$HM$50=I$3)*(GMW!$HN$2:$HN$50=I$1),0),$B39-1973)} -> 191709 | J39: {=INDEX(GMW!$A$2:$HN$50,MATCH(1,(GMW!$HM$2:$HM$50=J$3)*(GMW!$HN$2:$HN$50=J$1),0),$B39-1973)} -> 4640 | K39: {=INDEX(GMW!$A$2:$HN$50,MATCH(1,(GMW!$HM$2:$HM$50=K$3)*(GMW!$HN$2:$HN$50=K$1),0),$B39-1973)} -> 336442 | L39: {=INDEX(GMW!$A$2:$HN$50,MATCH(1,(GMW!$HM$2:$HM$50=L$3)*(GMW!$HN$2:$HN$50=L$1),0),$B39-1973)} -> 25795 | ... P39: {=INDEX(GMW!$A$2:$HN$50,MATCH(1,(GMW!$HM$2:$HM$50=P$3)*(GMW!$HN$2:$HN$50=P$1),0),$B39-1973)} -> 4640
B40: =+B39+1 -> 2013 | C40: =+C36+1 -> 1988 | D40: =+D36+1 -> 1988 | E40: {=INDEX(GMW!$A$2:$HN$50,MATCH(1,(GMW!$HM$2:$HM$50=E$3)*(GMW!$HN$2:$HN$50=E$1),0),$B40-1973)} -> 338186 | F40: {=INDEX(GMW!$A$2:$HN$50,MATCH(1,(GMW!$HM$2:$HM$50=F$3)*(GMW!$HN$2:$HN$50=F$1),0),$B40-1973)} -> 25970 | G40: {=INDEX(GMW!$A$2:$HN$50,MATCH(1,(GMW!$HM$2:$HM$50=G$3)*(GMW!$HN$2:$HN$50=G$1),0),$B40-1973)} -> 2512.313 | H40: {=INDEX(GMW!$A$2:$HN$50,MATCH(1,(GMW!$HM$2:$HM$50=H$3)*(GMW!$HN$2:$HN$50=H$1),0),$B40-1973)} -> 8.7 | I40: {=INDEX(GMW!$A$2:$HN$50,MATCH(1,(GMW!$HM$2:$HM$50=I$3)*(GMW!$HN$2:$HN$50=I$1),0),$B40-1973)} -> 194935 | J40: {=INDEX(GMW!$A$2:$HN$50,MATCH(1,(GMW!$HM$2:$HM$50=J$3)*(GMW!$HN$2:$HN$50=J$1),0),$B40-1973)} -> 4879 | K40: {=INDEX(GMW!$A$2:$HN$50,MATCH(1,(GMW!$HM$2:$HM$50=K$3)*(GMW!$HN$2:$HN$50=K$1),0),$B40-1973)} -> 338186 | L40: {=INDEX(GMW!$A$2:$HN$50,MATCH(1,(GMW!$HM$2:$HM$50=L$3)*(GMW!$HN$2:$HN$50=L$1),0),$B40-1973)} -> 25970 | ... P40: {=INDEX(GMW!$A$2:$HN$50,MATCH(1,(GMW!$HM$2:$HM$50=P$3)*(GMW!$HN$2:$HN$50=P$1),0),$B40-1973)} -> 4879
B41: =+B40+1 -> 2014 | C41: =+C37+1 -> 1988 | D41: =+D37+1 -> 1988 | E41: {=INDEX(GMW!$A$2:$HN$50,MATCH(1,(GMW!$HM$2:$HM$50=E$3)*(GMW!$HN$2:$HN$50=E$1),0),$B41-1973)} -> 342414 | F41: {=INDEX(GMW!$A$2:$HN$50,MATCH(1,(GMW!$HM$2:$HM$50=F$3)*(GMW!$HN$2:$HN$50=F$1),0),$B41-1973)} -> 26160 | G41: {=INDEX(GMW!$A$2:$HN$50,MATCH(1,(GMW!$HM$2:$HM$50=G$3)*(GMW!$HN$2:$HN$50=G$1),0),$B41-1973)} -> 2569.618 | H41: {=INDEX(GMW!$A$2:$HN$50,MATCH(1,(GMW!$HM$2:$HM$50=H$3)*(GMW!$HN$2:$HN$50=H$1),0),$B41-1973)} -> 8.4 | I41: {=INDEX(GMW!$A$2:$HN$50,MATCH(1,(GMW!$HM$2:$HM$50=I$3)*(GMW!$HN$2:$HN$50=I$1),0),$B41-1973)} -> 197179 | J41: {=INDEX(GMW!$A$2:$HN$50,MATCH(1,(GMW!$HM$2:$HM$50=J$3)*(GMW!$HN$2:$HN$50=J$1),0),$B41-1973)} -> 5040 | K41: {=INDEX(GMW!$A$2:$HN$50,MATCH(1,(GMW!$HM$2:$HM$50=K$3)*(GMW!$HN$2:$HN$50=K$1),0),$B41-1973)} -> 342414 | L41: {=INDEX(GMW!$A$2:$HN$50,MATCH(1,(GMW!$HM$2:$HM$50=L$3)*(GMW!$HN$2:$HN$50=L$1),0),$B41-1973)} -> 26160 | ... P41: {=INDEX(GMW!$A$2:$HN$50,MATCH(1,(GMW!$HM$2:$HM$50=P$3)*(GMW!$HN$2:$HN$50=P$1),0),$B41-1973)} -> 5040
B42: =+B41+1 -> 2015 | C42: =+C38+1 -> 1988 | D42: =+D38+1 -> 1988 | E42: {=INDEX(GMW!$A$2:$HN$50,MATCH(1,(GMW!$HM$2:$HM$50=E$3)*(GMW!$HN$2:$HN$50=E$1),0),$B42-1973)} -> 345162 | F42: {=INDEX(GMW!$A$2:$HN$50,MATCH(1,(GMW!$HM$2:$HM$50=F$3)*(GMW!$HN$2:$HN$50=F$1),0),$B42-1973)} -> 26355 | G42: {=INDEX(GMW!$A$2:$HN$50,MATCH(1,(GMW!$HM$2:$HM$50=G$3)*(GMW!$HN$2:$HN$50=G$1),0),$B42-1973)} -> 2641.639 | H42: {=INDEX(GMW!$A$2:$HN$50,MATCH(1,(GMW!$HM$2:$HM$50=H$3)*(GMW!$HN$2:$HN$50=H$1),0),$B42-1973)} -> 8 | I42: {=INDEX(GMW!$A$2:$HN$50,MATCH(1,(GMW!$HM$2:$HM$50=I$3)*(GMW!$HN$2:$HN$50=I$1),0),$B42-1973)} -> 198740 | J42: {=INDEX(GMW!$A$2:$HN$50,MATCH(1,(GMW!$HM$2:$HM$50=J$3)*(GMW!$HN$2:$HN$50=J$1),0),$B42-1973)} -> 5234 | K42: {=INDEX(GMW!$A$2:$HN$50,MATCH(1,(GMW!$HM$2:$HM$50=K$3)*(GMW!$HN$2:$HN$50=K$1),0),$B42-1973)} -> 345162 | L42: {=INDEX(GMW!$A$2:$HN$50,MATCH(1,(GMW!$HM$2:$HM$50=L$3)*(GMW!$HN$2:$HN$50=L$1),0),$B42-1973)} -> 26355 | ... P42: {=INDEX(GMW!$A$2:$HN$50,MATCH(1,(GMW!$HM$2:$HM$50=P$3)*(GMW!$HN$2:$HN$50=P$1),0),$B42-1973)} -> 5234
A43: 1989 | B43: =+B42+1 -> 2016 | C43: =+C39+1 -> 1989 | D43: =+D39+1 -> 1988 | E43: {=INDEX(GMW!$A$2:$HN$50,MATCH(1,(GMW!$HM$2:$HM$50=E$3)*(GMW!$HN$2:$HN$50=E$1),0),$B43-1973)} -> 346836 | F43: {=INDEX(GMW!$A$2:$HN$50,MATCH(1,(GMW!$HM$2:$HM$50=F$3)*(GMW!$HN$2:$HN$50=F$1),0),$B43-1973)} -> 26590 | G43: {=INDEX(GMW!$A$2:$HN$50,MATCH(1,(GMW!$HM$2:$HM$50=G$3)*(GMW!$HN$2:$HN$50=G$1),0),$B43-1973)} -> 2684.494 | H43: {=INDEX(GMW!$A$2:$HN$50,MATCH(1,(GMW!$HM$2:$HM$50=H$3)*(GMW!$HN$2:$HN$50=H$1),0),$B43-1973)} -> 7.6 | I43: {=INDEX(GMW!$A$2:$HN$50,MATCH(1,(GMW!$HM$2:$HM$50=I$3)*(GMW!$HN$2:$HN$50=I$1),0),$B43-1973)} -> 201265 | J43: {=INDEX(GMW!$A$2:$HN$50,MATCH(1,(GMW!$HM$2:$HM$50=J$3)*(GMW!$HN$2:$HN$50=J$1),0),$B43-1973)} -> 5239 | K43: {=INDEX(GMW!$A$2:$HN$50,MATCH(1,(GMW!$HM$2:$HM$50=K$3)*(GMW!$HN$2:$HN$50=K$1),0),$B43-1973)} -> 346836 | L43: {=INDEX(GMW!$A$2:$HN$50,MATCH(1,(GMW!$HM$2:$HM$50=L$3)*(GMW!$HN$2:$HN$50=L$1),0),$B43-1973)} -> 26590 | ... P43: {=INDEX(GMW!$A$2:$HN$50,MATCH(1,(GMW!$HM$2:$HM$50=P$3)*(GMW!$HN$2:$HN$50=P$1),0),$B43-1973)} -> 5239
B44: =+B43+1 -> 2017 | C44: =+C40+1 -> 1989 | D44: =+D40+1 -> 1989 | E44: {=INDEX(GMW!$A$2:$HN$50,MATCH(1,(GMW!$HM$2:$HM$50=E$3)*(GMW!$HN$2:$HN$50=E$1),0),$B44-1973)} -> 348997 | F44: {=INDEX(GMW!$A$2:$HN$50,MATCH(1,(GMW!$HM$2:$HM$50=F$3)*(GMW!$HN$2:$HN$50=F$1),0),$B44-1973)} -> 26730 | G44: {=INDEX(GMW!$A$2:$HN$50,MATCH(1,(GMW!$HM$2:$HM$50=G$3)*(GMW!$HN$2:$HN$50=G$1),0),$B44-1973)} -> 2756.293 | H44: {=INDEX(GMW!$A$2:$HN$50,MATCH(1,(GMW!$HM$2:$HM$50=H$3)*(GMW!$HN$2:$HN$50=H$1),0),$B44-1973)} -> 7.2 | I44: {=INDEX(GMW!$A$2:$HN$50,MATCH(1,(GMW!$HM$2:$HM$50=I$3)*(GMW!$HN$2:$HN$50=I$1),0),$B44-1973)} -> 204179 | J44: {=INDEX(GMW!$A$2:$HN$50,MATCH(1,(GMW!$HM$2:$HM$50=J$3)*(GMW!$HN$2:$HN$50=J$1),0),$B44-1973)} -> 5247 | K44: {=INDEX(GMW!$A$2:$HN$50,MATCH(1,(GMW!$HM$2:$HM$50=K$3)*(GMW!$HN$2:$HN$50=K$1),0),$B44-1973)} -> 348997 | L44: {=INDEX(GMW!$A$2:$HN$50,MATCH(1,(GMW!$HM$2:$HM$50=L$3)*(GMW!$HN$2:$HN$50=L$1),0),$B44-1973)} -> 26730 | ... P44: {=INDEX(GMW!$A$2:$HN$50,MATCH(1,(GMW!$HM$2:$HM$50=P$3)*(GMW!$HN$2:$HN$50=P$1),0),$B44-1973)} -> 5247
B45: =+B44+1 -> 2018 | C45: =+C41+1 -> 1989 | D45: =+D41+1 -> 1989 | E45: {=INDEX(GMW!$A$2:$HN$50,MATCH(1,(GMW!$HM$2:$HM$50=E$3)*(GMW!$HN$2:$HN$50=E$1),0),$B45-1973)} -> 349572 | F45: {=INDEX(GMW!$A$2:$HN$50,MATCH(1,(GMW!$HM$2:$HM$50=F$3)*(GMW!$HN$2:$HN$50=F$1),0),$B45-1973)} -> 26795 | G45: {=INDEX(GMW!$A$2:$HN$50,MATCH(1,(GMW!$HM$2:$HM$50=G$3)*(GMW!$HN$2:$HN$50=G$1),0),$B45-1973)} -> 2816.473 | H45: {=INDEX(GMW!$A$2:$HN$50,MATCH(1,(GMW!$HM$2:$HM$50=H$3)*(GMW!$HN$2:$HN$50=H$1),0),$B45-1973)} -> 7.1 | I45: {=INDEX(GMW!$A$2:$HN$50,MATCH(1,(GMW!$HM$2:$HM$50=I$3)*(GMW!$HN$2:$HN$50=I$1),0),$B45-1973)} -> 209872 | J45: {=INDEX(GMW!$A$2:$HN$50,MATCH(1,(GMW!$HM$2:$HM$50=J$3)*(GMW!$HN$2:$HN$50=J$1),0),$B45-1973)} -> 5405 | K45: {=INDEX(GMW!$A$2:$HN$50,MATCH(1,(GMW!$HM$2:$HM$50=K$3)*(GMW!$HN$2:$HN$50=K$1),0),$B45-1973)} -> 349572 | L45: {=INDEX(GMW!$A$2:$HN$50,MATCH(1,(GMW!$HM$2:$HM$50=L$3)*(GMW!$HN$2:$HN$50=L$1),0),$B45-1973)} -> 26795 | ... P45: {=INDEX(GMW!$A$2:$HN$50,MATCH(1,(GMW!$HM$2:$HM$50=P$3)*(GMW!$HN$2:$HN$50=P$1),0),$B45-1973)} -> 5405
B46: =+B45+1 -> 2019 | C46: =+C42+1 -> 1989 | D46: =+D42+1 -> 1989 | E46: {=INDEX(GMW!$A$2:$HN$50,MATCH(1,(GMW!$HM$2:$HM$50=E$3)*(GMW!$HN$2:$HN$50=E$1),0),$B46-1973)} -> 349523 | F46: {=INDEX(GMW!$A$2:$HN$50,MATCH(1,(GMW!$HM$2:$HM$50=F$3)*(GMW!$HN$2:$HN$50=F$1),0),$B46-1973)} -> 26880 | G46: {=INDEX(GMW!$A$2:$HN$50,MATCH(1,(GMW!$HM$2:$HM$50=G$3)*(GMW!$HN$2:$HN$50=G$1),0),$B46-1973)} -> 2895.669 | H46: {=INDEX(GMW!$A$2:$HN$50,MATCH(1,(GMW!$HM$2:$HM$50=H$3)*(GMW!$HN$2:$HN$50=H$1),0),$B46-1973)} -> 7 | I46: {=INDEX(GMW!$A$2:$HN$50,MATCH(1,(GMW!$HM$2:$HM$50=I$3)*(GMW!$HN$2:$HN$50=I$1),0),$B46-1973)} -> 207949 | J46: {=INDEX(GMW!$A$2:$HN$50,MATCH(1,(GMW!$HM$2:$HM$50=J$3)*(GMW!$HN$2:$HN$50=J$1),0),$B46-1973)} -> 5609 | K46: {=INDEX(GMW!$A$2:$HN$50,MATCH(1,(GMW!$HM$2:$HM$50=K$3)*(GMW!$HN$2:$HN$50=K$1),0),$B46-1973)} -> 349523 | L46: {=INDEX(GMW!$A$2:$HN$50,MATCH(1,(GMW!$HM$2:$HM$50=L$3)*(GMW!$HN$2:$HN$50=L$1),0),$B46-1973)} -> 26880 | ... P46: {=INDEX(GMW!$A$2:$HN$50,MATCH(1,(GMW!$HM$2:$HM$50=P$3)*(GMW!$HN$2:$HN$50=P$1),0),$B46-1973)} -> 5609
A47: 1990 | B47: =+B46+1 -> 2020 | C47: =+C43+1 -> 1990 | D47: =+D43+1 -> 1989 | E47: {=INDEX(GMW!$A$2:$HN$50,MATCH(1,(GMW!$HM$2:$HM$50=E$3)*(GMW!$HN$2:$HN$50=E$1),0),$B47-1973)} -> 351299 | F47: {=INDEX(GMW!$A$2:$HN$50,MATCH(1,(GMW!$HM$2:$HM$50=F$3)*(GMW!$HN$2:$HN$50=F$1),0),$B47-1973)} -> 26900 | G47: {=INDEX(GMW!$A$2:$HN$50,MATCH(1,(GMW!$HM$2:$HM$50=G$3)*(GMW!$HN$2:$HN$50=G$1),0),$B47-1973)} -> 2978.668 | H47: {=INDEX(GMW!$A$2:$HN$50,MATCH(1,(GMW!$HM$2:$HM$50=H$3)*(GMW!$HN$2:$HN$50=H$1),0),$B47-1973)} -> 6.9 | I47: {=INDEX(GMW!$A$2:$HN$50,MATCH(1,(GMW!$HM$2:$HM$50=I$3)*(GMW!$HN$2:$HN$50=I$1),0),$B47-1973)} -> 213872 | J47: {=INDEX(GMW!$A$2:$HN$50,MATCH(1,(GMW!$HM$2:$HM$50=J$3)*(GMW!$HN$2:$HN$50=J$1),0),$B47-1973)} -> 5594 | K47: {=INDEX(GMW!$A$2:$HN$50,MATCH(1,(GMW!$HM$2:$HM$50=K$3)*(GMW!$HN$2:$HN$50=K$1),0),$B47-1973)} -> 351299 | L47: {=INDEX(GMW!$A$2:$HN$50,MATCH(1,(GMW!$HM$2:$HM$50=L$3)*(GMW!$HN$2:$HN$50=L$1),0),$B47-1973)} -> 26900 | ... P47: {=INDEX(GMW!$A$2:$HN$50,MATCH(1,(GMW!$HM$2:$HM$50=P$3)*(GMW!$HN$2:$HN$50=P$1),0),$B47-1973)} -> 5594
B48: =+B47+1 -> 2021 | C48: =+C44+1 -> 1990 | D48: =+D44+1 -> 1990 | E48: {=INDEX(GMW!$A$2:$HN$50,MATCH(1,(GMW!$HM$2:$HM$50=E$3)*(GMW!$HN$2:$HN$50=E$1),0),$B48-1973)} -> 353663 | F48: {=INDEX(GMW!$A$2:$HN$50,MATCH(1,(GMW!$HM$2:$HM$50=F$3)*(GMW!$HN$2:$HN$50=F$1),0),$B48-1973)} -> 26935 | G48: {=INDEX(GMW!$A$2:$HN$50,MATCH(1,(GMW!$HM$2:$HM$50=G$3)*(GMW!$HN$2:$HN$50=G$1),0),$B48-1973)} -> 3042.386 | H48: {=INDEX(GMW!$A$2:$HN$50,MATCH(1,(GMW!$HM$2:$HM$50=H$3)*(GMW!$HN$2:$HN$50=H$1),0),$B48-1973)} -> 6.9 | I48: {=INDEX(GMW!$A$2:$HN$50,MATCH(1,(GMW!$HM$2:$HM$50=I$3)*(GMW!$HN$2:$HN$50=I$1),0),$B48-1973)} -> 211391 | J48: {=INDEX(GMW!$A$2:$HN$50,MATCH(1,(GMW!$HM$2:$HM$50=J$3)*(GMW!$HN$2:$HN$50=J$1),0),$B48-1973)} -> 5782 | K48: {=INDEX(GMW!$A$2:$HN$50,MATCH(1,(GMW!$HM$2:$HM$50=K$3)*(GMW!$HN$2:$HN$50=K$1),0),$B48-1973)} -> 353663 | L48: {=INDEX(GMW!$A$2:$HN$50,MATCH(1,(GMW!$HM$2:$HM$50=L$3)*(GMW!$HN$2:$HN$50=L$1),0),$B48-1973)} -> 26935 | ... P48: {=INDEX(GMW!$A$2:$HN$50,MATCH(1,(GMW!$HM$2:$HM$50=P$3)*(GMW!$HN$2:$HN$50=P$1),0),$B48-1973)} -> 5782
B49: =+B48+1 -> 2022 | C49: =+C45+1 -> 1990 | D49: =+D45+1 -> 1990 | E49: {=INDEX(GMW!$A$2:$HN$50,MATCH(1,(GMW!$HM$2:$HM$50=E$3)*(GMW!$HN$2:$HN$50=E$1),0),$B49-1973)} -> 349780 | F49: {=INDEX(GMW!$A$2:$HN$50,MATCH(1,(GMW!$HM$2:$HM$50=F$3)*(GMW!$HN$2:$HN$50=F$1),0),$B49-1973)} -> 26900 | G49: {=INDEX(GMW!$A$2:$HN$50,MATCH(1,(GMW!$HM$2:$HM$50=G$3)*(GMW!$HN$2:$HN$50=G$1),0),$B49-1973)} -> 3096.331 | H49: {=INDEX(GMW!$A$2:$HN$50,MATCH(1,(GMW!$HM$2:$HM$50=H$3)*(GMW!$HN$2:$HN$50=H$1),0),$B49-1973)} -> 7.1 | I49: {=INDEX(GMW!$A$2:$HN$50,MATCH(1,(GMW!$HM$2:$HM$50=I$3)*(GMW!$HN$2:$HN$50=I$1),0),$B49-1973)} -> 213462 | J49: {=INDEX(GMW!$A$2:$HN$50,MATCH(1,(GMW!$HM$2:$HM$50=J$3)*(GMW!$HN$2:$HN$50=J$1),0),$B49-1973)} -> 5930 | K49: {=INDEX(GMW!$A$2:$HN$50,MATCH(1,(GMW!$HM$2:$HM$50=K$3)*(GMW!$HN$2:$HN$50=K$1),0),$B49-1973)} -> 349780 | L49: {=INDEX(GMW!$A$2:$HN$50,MATCH(1,(GMW!$HM$2:$HM$50=L$3)*(GMW!$HN$2:$HN$50=L$1),0),$B49-1973)} -> 26900 | ... P49: {=INDEX(GMW!$A$2:$HN$50,MATCH(1,(GMW!$HM$2:$HM$50=P$3)*(GMW!$HN$2:$HN$50=P$1),0),$B49-1973)} -> 5930
B50: =+B49+1 -> 2023 | C50: =+C46+1 -> 1990 | D50: =+D46+1 -> 1990 | E50: {=INDEX(GMW!$A$2:$HN$50,MATCH(1,(GMW!$HM$2:$HM$50=E$3)*(GMW!$HN$2:$HN$50=E$1),0),$B50-1973)} -> 348006 | F50: {=INDEX(GMW!$A$2:$HN$50,MATCH(1,(GMW!$HM$2:$HM$50=F$3)*(GMW!$HN$2:$HN$50=F$1),0),$B50-1973)} -> 26750 | G50: {=INDEX(GMW!$A$2:$HN$50,MATCH(1,(GMW!$HM$2:$HM$50=G$3)*(GMW!$HN$2:$HN$50=G$1),0),$B50-1973)} -> 3142.508 | H50: {=INDEX(GMW!$A$2:$HN$50,MATCH(1,(GMW!$HM$2:$HM$50=H$3)*(GMW!$HN$2:$HN$50=H$1),0),$B50-1973)} -> 7.5 | I50: {=INDEX(GMW!$A$2:$HN$50,MATCH(1,(GMW!$HM$2:$HM$50=I$3)*(GMW!$HN$2:$HN$50=I$1),0),$B50-1973)} -> 216821 | J50: {=INDEX(GMW!$A$2:$HN$50,MATCH(1,(GMW!$HM$2:$HM$50=J$3)*(GMW!$HN$2:$HN$50=J$1),0),$B50-1973)} -> 6012 | K50: {=INDEX(GMW!$A$2:$HN$50,MATCH(1,(GMW!$HM$2:$HM$50=K$3)*(GMW!$HN$2:$HN$50=K$1),0),$B50-1973)} -> 348006 | L50: {=INDEX(GMW!$A$2:$HN$50,MATCH(1,(GMW!$HM$2:$HM$50=L$3)*(GMW!$HN$2:$HN$50=L$1),0),$B50-1973)} -> 26750 | ... P50: {=INDEX(GMW!$A$2:$HN$50,MATCH(1,(GMW!$HM$2:$HM$50=P$3)*(GMW!$HN$2:$HN$50=P$1),0),$B50-1973)} -> 6012
A51: 1991 | B51: =+B50+1 -> 2024 | C51: =+C47+1 -> 1991 | D51: =+D47+1 -> 1990 | E51: {=INDEX(GMW!$A$2:$HN$50,MATCH(1,(GMW!$HM$2:$HM$50=E$3)*(GMW!$HN$2:$HN$50=E$1),0),$B51-1973)} -> 346292 | F51: {=INDEX(GMW!$A$2:$HN$50,MATCH(1,(GMW!$HM$2:$HM$50=F$3)*(GMW!$HN$2:$HN$50=F$1),0),$B51-1973)} -> 26530 | G51: {=INDEX(GMW!$A$2:$HN$50,MATCH(1,(GMW!$HM$2:$HM$50=G$3)*(GMW!$HN$2:$HN$50=G$1),0),$B51-1973)} -> 3224.996 | H51: {=INDEX(GMW!$A$2:$HN$50,MATCH(1,(GMW!$HM$2:$HM$50=H$3)*(GMW!$HN$2:$HN$50=H$1),0),$B51-1973)} -> 8 | I51: {=INDEX(GMW!$A$2:$HN$50,MATCH(1,(GMW!$HM$2:$HM$50=I$3)*(GMW!$HN$2:$HN$50=I$1),0),$B51-1973)} -> 218128 | J51: {=INDEX(GMW!$A$2:$HN$50,MATCH(1,(GMW!$HM$2:$HM$50=J$3)*(GMW!$HN$2:$HN$50=J$1),0),$B51-1973)} -> 5974 | K51: {=INDEX(GMW!$A$2:$HN$50,MATCH(1,(GMW!$HM$2:$HM$50=K$3)*(GMW!$HN$2:$HN$50=K$1),0),$B51-1973)} -> 346292 | L51: {=INDEX(GMW!$A$2:$HN$50,MATCH(1,(GMW!$HM$2:$HM$50=L$3)*(GMW!$HN$2:$HN$50=L$1),0),$B51-1973)} -> 26530 | ... P51: {=INDEX(GMW!$A$2:$HN$50,MATCH(1,(GMW!$HM$2:$HM$50=P$3)*(GMW!$HN$2:$HN$50=P$1),0),$B51-1973)} -> 5974
B52: =+B51+1 -> 2025 | C52: =+C48+1 -> 1991 | D52: =+D48+1 -> 1991 | E52: {=INDEX(GMW!$A$2:$HN$50,MATCH(1,(GMW!$HM$2:$HM$50=E$3)*(GMW!$HN$2:$HN$50=E$1),0),$B52-1973)} -> 345892 | F52: {=INDEX(GMW!$A$2:$HN$50,MATCH(1,(GMW!$HM$2:$HM$50=F$3)*(GMW!$HN$2:$HN$50=F$1),0),$B52-1973)} -> 26275 | G52: {=INDEX(GMW!$A$2:$HN$50,MATCH(1,(GMW!$HM$2:$HM$50=G$3)*(GMW!$HN$2:$HN$50=G$1),0),$B52-1973)} -> 3293.292 | H52: {=INDEX(GMW!$A$2:$HN$50,MATCH(1,(GMW!$HM$2:$HM$50=H$3)*(GMW!$HN$2:$HN$50=H$1),0),$B52-1973)} -> 8.7 | I52: {=INDEX(GMW!$A$2:$HN$50,MATCH(1,(GMW!$HM$2:$HM$50=I$3)*(GMW!$HN$2:$HN$50=I$1),0),$B52-1973)} -> 214176 | J52: {=INDEX(GMW!$A$2:$HN$50,MATCH(1,(GMW!$HM$2:$HM$50=J$3)*(GMW!$HN$2:$HN$50=J$1),0),$B52-1973)} -> 6126 | K52: {=INDEX(GMW!$A$2:$HN$50,MATCH(1,(GMW!$HM$2:$HM$50=K$3)*(GMW!$HN$2:$HN$50=K$1),0),$B52-1973)} -> 345892 | L52: {=INDEX(GMW!$A$2:$HN$50,MATCH(1,(GMW!$HM$2:$HM$50=L$3)*(GMW!$HN$2:$HN$50=L$1),0),$B52-1973)} -> 26275 | ... P52: {=INDEX(GMW!$A$2:$HN$50,MATCH(1,(GMW!$HM$2:$HM$50=P$3)*(GMW!$HN$2:$HN$50=P$1),0),$B52-1973)} -> 6126
B53: =+B52+1 -> 2026 | C53: =+C49+1 -> 1991 | D53: =+D49+1 -> 1991 | E53: {=INDEX(GMW!$A$2:$HN$50,MATCH(1,(GMW!$HM$2:$HM$50=E$3)*(GMW!$HN$2:$HN$50=E$1),0),$B53-1973)} -> 345216 | F53: {=INDEX(GMW!$A$2:$HN$50,MATCH(1,(GMW!$HM$2:$HM$50=F$3)*(GMW!$HN$2:$HN$50=F$1),0),$B53-1973)} -> 26025 | G53: {=INDEX(GMW!$A$2:$HN$50,MATCH(1,(GMW!$HM$2:$HM$50=G$3)*(GMW!$HN$2:$HN$50=G$1),0),$B53-1973)} -> 3373.081 | H53: {=INDEX(GMW!$A$2:$HN$50,MATCH(1,(GMW!$HM$2:$HM$50=H$3)*(GMW!$HN$2:$HN$50=H$1),0),$B53-1973)} -> 9.2 | I53: {=INDEX(GMW!$A$2:$HN$50,MATCH(1,(GMW!$HM$2:$HM$50=I$3)*(GMW!$HN$2:$HN$50=I$1),0),$B53-1973)} -> 220568 | J53: {=INDEX(GMW!$A$2:$HN$50,MATCH(1,(GMW!$HM$2:$HM$50=J$3)*(GMW!$HN$2:$HN$50=J$1),0),$B53-1973)} -> 6125 | K53: {=INDEX(GMW!$A$2:$HN$50,MATCH(1,(GMW!$HM$2:$HM$50=K$3)*(GMW!$HN$2:$HN$50=K$1),0),$B53-1973)} -> 345216 | L53: {=INDEX(GMW!$A$2:$HN$50,MATCH(1,(GMW!$HM$2:$HM$50=L$3)*(GMW!$HN$2:$HN$50=L$1),0),$B53-1973)} -> 26025 | ... P53: {=INDEX(GMW!$A$2:$HN$50,MATCH(1,(GMW!$HM$2:$HM$50=P$3)*(GMW!$HN$2:$HN$50=P$1),0),$B53-1973)} -> 6125
B54: =+B53+1 -> 2027 | C54: =+C50+1 -> 1991 | D54: =+D50+1 -> 1991 | E54: {=INDEX(GMW!$A$2:$HN$50,MATCH(1,(GMW!$HM$2:$HM$50=E$3)*(GMW!$HN$2:$HN$50=E$1),0),$B54-1973)} -> 345643 | F54: {=INDEX(GMW!$A$2:$HN$50,MATCH(1,(GMW!$HM$2:$HM$50=F$3)*(GMW!$HN$2:$HN$50=F$1),0),$B54-1973)} -> 25820 | G54: {=INDEX(GMW!$A$2:$HN$50,MATCH(1,(GMW!$HM$2:$HM$50=G$3)*(GMW!$HN$2:$HN$50=G$1),0),$B54-1973)} -> 3431.946 | H54: {=INDEX(GMW!$A$2:$HN$50,MATCH(1,(GMW!$HM$2:$HM$50=H$3)*(GMW!$HN$2:$HN$50=H$1),0),$B54-1973)} -> 9.5 | I54: {=INDEX(GMW!$A$2:$HN$50,MATCH(1,(GMW!$HM$2:$HM$50=I$3)*(GMW!$HN$2:$HN$50=I$1),0),$B54-1973)} -> 220151 | J54: {=INDEX(GMW!$A$2:$HN$50,MATCH(1,(GMW!$HM$2:$HM$50=J$3)*(GMW!$HN$2:$HN$50=J$1),0),$B54-1973)} -> 6492 | K54: {=INDEX(GMW!$A$2:$HN$50,MATCH(1,(GMW!$HM$2:$HM$50=K$3)*(GMW!$HN$2:$HN$50=K$1),0),$B54-1973)} -> 345643 | L54: {=INDEX(GMW!$A$2:$HN$50,MATCH(1,(GMW!$HM$2:$HM$50=L$3)*(GMW!$HN$2:$HN$50=L$1),0),$B54-1973)} -> 25820 | ... P54: {=INDEX(GMW!$A$2:$HN$50,MATCH(1,(GMW!$HM$2:$HM$50=P$3)*(GMW!$HN$2:$HN$50=P$1),0),$B54-1973)} -> 6492
A55: 1992 | B55: =+B54+1 -> 2028 | C55: =+C51+1 -> 1992 | D55: =+D51+1 -> 1991 | E55: {=INDEX(GMW!$A$2:$HN$50,MATCH(1,(GMW!$HM$2:$HM$50=E$3)*(GMW!$HN$2:$HN$50=E$1),0),$B55-1973)} -> 345523 | F55: {=INDEX(GMW!$A$2:$HN$50,MATCH(1,(GMW!$HM$2:$HM$50=F$3)*(GMW!$HN$2:$HN$50=F$1),0),$B55-1973)} -> 25710 | G55: {=INDEX(GMW!$A$2:$HN$50,MATCH(1,(GMW!$HM$2:$HM$50=G$3)*(GMW!$HN$2:$HN$50=G$1),0),$B55-1973)} -> 3467.976 | H55: {=INDEX(GMW!$A$2:$HN$50,MATCH(1,(GMW!$HM$2:$HM$50=H$3)*(GMW!$HN$2:$HN$50=H$1),0),$B55-1973)} -> 9.7 | I55: {=INDEX(GMW!$A$2:$HN$50,MATCH(1,(GMW!$HM$2:$HM$50=I$3)*(GMW!$HN$2:$HN$50=I$1),0),$B55-1973)} -> 221591 | J55: {=INDEX(GMW!$A$2:$HN$50,MATCH(1,(GMW!$HM$2:$HM$50=J$3)*(GMW!$HN$2:$HN$50=J$1),0),$B55-1973)} -> 6453 | K55: {=INDEX(GMW!$A$2:$HN$50,MATCH(1,(GMW!$HM$2:$HM$50=K$3)*(GMW!$HN$2:$HN$50=K$1),0),$B55-1973)} -> 345523 | L55: {=INDEX(GMW!$A$2:$HN$50,MATCH(1,(GMW!$HM$2:$HM$50=L$3)*(GMW!$HN$2:$HN$50=L$1),0),$B55-1973)} -> 25710 | ... P55: {=INDEX(GMW!$A$2:$HN$50,MATCH(1,(GMW!$HM$2:$HM$50=P$3)*(GMW!$HN$2:$HN$50=P$1),0),$B55-1973)} -> 6453
B56: =+B55+1 -> 2029 | C56: =+C52+1 -> 1992 | D56: =+D52+1 -> 1992 | E56: {=INDEX(GMW!$A$2:$HN$50,MATCH(1,(GMW!$HM$2:$HM$50=E$3)*(GMW!$HN$2:$HN$50=E$1),0),$B56-1973)} -> 344987 | F56: {=INDEX(GMW!$A$2:$HN$50,MATCH(1,(GMW!$HM$2:$HM$50=F$3)*(GMW!$HN$2:$HN$50=F$1),0),$B56-1973)} -> 25605 | G56: {=INDEX(GMW!$A$2:$HN$50,MATCH(1,(GMW!$HM$2:$HM$50=G$3)*(GMW!$HN$2:$HN$50=G$1),0),$B56-1973)} -> 3483.129 | H56: {=INDEX(GMW!$A$2:$HN$50,MATCH(1,(GMW!$HM$2:$HM$50=H$3)*(GMW!$HN$2:$HN$50=H$1),0),$B56-1973)} -> 9.8 | I56: {=INDEX(GMW!$A$2:$HN$50,MATCH(1,(GMW!$HM$2:$HM$50=I$3)*(GMW!$HN$2:$HN$50=I$1),0),$B56-1973)} -> 223785 | J56: {=INDEX(GMW!$A$2:$HN$50,MATCH(1,(GMW!$HM$2:$HM$50=J$3)*(GMW!$HN$2:$HN$50=J$1),0),$B56-1973)} -> 6234 | K56: {=INDEX(GMW!$A$2:$HN$50,MATCH(1,(GMW!$HM$2:$HM$50=K$3)*(GMW!$HN$2:$HN$50=K$1),0),$B56-1973)} -> 344987 | L56: {=INDEX(GMW!$A$2:$HN$50,MATCH(1,(GMW!$HM$2:$HM$50=L$3)*(GMW!$HN$2:$HN$50=L$1),0),$B56-1973)} -> 25605 | ... P56: {=INDEX(GMW!$A$2:$HN$50,MATCH(1,(GMW!$HM$2:$HM$50=P$3)*(GMW!$HN$2:$HN$50=P$1),0),$B56-1973)} -> 6234
B57: =+B56+1 -> 2030 | C57: =+C53+1 -> 1992 | D57: =+D53+1 -> 1992 | E57: {=INDEX(GMW!$A$2:$HN$50,MATCH(1,(GMW!$HM$2:$HM$50=E$3)*(GMW!$HN$2:$HN$50=E$1),0),$B57-1973)} -> 346628 | F57: {=INDEX(GMW!$A$2:$HN$50,MATCH(1,(GMW!$HM$2:$HM$50=F$3)*(GMW!$HN$2:$HN$50=F$1),0),$B57-1973)} -> 25509 | G57: {=INDEX(GMW!$A$2:$HN$50,MATCH(1,(GMW!$HM$2:$HM$50=G$3)*(GMW!$HN$2:$HN$50=G$1),0),$B57-1973)} -> 3486.288 | H57: {=INDEX(GMW!$A$2:$HN$50,MATCH(1,(GMW!$HM$2:$HM$50=H$3)*(GMW!$HN$2:$HN$50=H$1),0),$B57-1973)} -> 9.9 | I57: {=INDEX(GMW!$A$2:$HN$50,MATCH(1,(GMW!$HM$2:$HM$50=I$3)*(GMW!$HN$2:$HN$50=I$1),0),$B57-1973)} -> 225633 | J57: {=INDEX(GMW!$A$2:$HN$50,MATCH(1,(GMW!$HM$2:$HM$50=J$3)*(GMW!$HN$2:$HN$50=J$1),0),$B57-1973)} -> 6198 | K57: {=INDEX(GMW!$A$2:$HN$50,MATCH(1,(GMW!$HM$2:$HM$50=K$3)*(GMW!$HN$2:$HN$50=K$1),0),$B57-1973)} -> 346628 | L57: {=INDEX(GMW!$A$2:$HN$50,MATCH(1,(GMW!$HM$2:$HM$50=L$3)*(GMW!$HN$2:$HN$50=L$1),0),$B57-1973)} -> 25509 | ... P57: {=INDEX(GMW!$A$2:$HN$50,MATCH(1,(GMW!$HM$2:$HM$50=P$3)*(GMW!$HN$2:$HN$50=P$1),0),$B57-1973)} -> 6198
B58: =+B57+1 -> 2031 | C58: =+C54+1 -> 1992 | D58: =+D54+1 -> 1992 | E58: {=INDEX(GMW!$A$2:$HN$50,MATCH(1,(GMW!$HM$2:$HM$50=E$3)*(GMW!$HN$2:$HN$50=E$1),0),$B58-1973)} -> 349299 | F58: {=INDEX(GMW!$A$2:$HN$50,MATCH(1,(GMW!$HM$2:$HM$50=F$3)*(GMW!$HN$2:$HN$50=F$1),0),$B58-1973)} -> 25336 | G58: {=INDEX(GMW!$A$2:$HN$50,MATCH(1,(GMW!$HM$2:$HM$50=G$3)*(GMW!$HN$2:$HN$50=G$1),0),$B58-1973)} -> 3519.483 | H58: {=INDEX(GMW!$A$2:$HN$50,MATCH(1,(GMW!$HM$2:$HM$50=H$3)*(GMW!$HN$2:$HN$50=H$1),0),$B58-1973)} -> 10.4 | I58: {=INDEX(GMW!$A$2:$HN$50,MATCH(1,(GMW!$HM$2:$HM$50=I$3)*(GMW!$HN$2:$HN$50=I$1),0),$B58-1973)} -> 225562 | J58: {=INDEX(GMW!$A$2:$HN$50,MATCH(1,(GMW!$HM$2:$HM$50=J$3)*(GMW!$HN$2:$HN$50=J$1),0),$B58-1973)} -> 6517 | K58: {=INDEX(GMW!$A$2:$HN$50,MATCH(1,(GMW!$HM$2:$HM$50=K$3)*(GMW!$HN$2:$HN$50=K$1),0),$B58-1973)} -> 349299 | L58: {=INDEX(GMW!$A$2:$HN$50,MATCH(1,(GMW!$HM$2:$HM$50=L$3)*(GMW!$HN$2:$HN$50=L$1),0),$B58-1973)} -> 25336 | ... P58: {=INDEX(GMW!$A$2:$HN$50,MATCH(1,(GMW!$HM$2:$HM$50=P$3)*(GMW!$HN$2:$HN$50=P$1),0),$B58-1973)} -> 6517
A59: 1993 | B59: =+B58+1 -> 2032 | C59: =+C55+1 -> 1993 | D59: =+D55+1 -> 1992 | E59: {=INDEX(GMW!$A$2:$HN$50,MATCH(1,(GMW!$HM$2:$HM$50=E$3)*(GMW!$HN$2:$HN$50=E$1),0),$B59-1973)} -> 351046 | F59: {=INDEX(GMW!$A$2:$HN$50,MATCH(1,(GMW!$HM$2:$HM$50=F$3)*(GMW!$HN$2:$HN$50=F$1),0),$B59-1973)} -> 25282 | G59: {=INDEX(GMW!$A$2:$HN$50,MATCH(1,(GMW!$HM$2:$HM$50=G$3)*(GMW!$HN$2:$HN$50=G$1),0),$B59-1973)} -> 3533.243 | H59: {=INDEX(GMW!$A$2:$HN$50,MATCH(1,(GMW!$HM$2:$HM$50=H$3)*(GMW!$HN$2:$HN$50=H$1),0),$B59-1973)} -> 10.6 | I59: {=INDEX(GMW!$A$2:$HN$50,MATCH(1,(GMW!$HM$2:$HM$50=I$3)*(GMW!$HN$2:$HN$50=I$1),0),$B59-1973)} -> 224008 | J59: {=INDEX(GMW!$A$2:$HN$50,MATCH(1,(GMW!$HM$2:$HM$50=J$3)*(GMW!$HN$2:$HN$50=J$1),0),$B59-1973)} -> 6477 | K59: {=INDEX(GMW!$A$2:$HN$50,MATCH(1,(GMW!$HM$2:$HM$50=K$3)*(GMW!$HN$2:$HN$50=K$1),0),$B59-1973)} -> 351046 | L59: {=INDEX(GMW!$A$2:$HN$50,MATCH(1,(GMW!$HM$2:$HM$50=L$3)*(GMW!$HN$2:$HN$50=L$1),0),$B59-1973)} -> 25282 | ... P59: {=INDEX(GMW!$A$2:$HN$50,MATCH(1,(GMW!$HM$2:$HM$50=P$3)*(GMW!$HN$2:$HN$50=P$1),0),$B59-1973)} -> 6477
B60: =+B59+1 -> 2033 | C60: =+C56+1 -> 1993 | D60: =+D56+1 -> 1993 | E60: {=INDEX(GMW!$A$2:$HN$50,MATCH(1,(GMW!$HM$2:$HM$50=E$3)*(GMW!$HN$2:$HN$50=E$1),0),$B60-1973)} -> 352612 | F60: {=INDEX(GMW!$A$2:$HN$50,MATCH(1,(GMW!$HM$2:$HM$50=F$3)*(GMW!$HN$2:$HN$50=F$1),0),$B60-1973)} -> 25293 | G60: {=INDEX(GMW!$A$2:$HN$50,MATCH(1,(GMW!$HM$2:$HM$50=G$3)*(GMW!$HN$2:$HN$50=G$1),0),$B60-1973)} -> 3585.394 | H60: {=INDEX(GMW!$A$2:$HN$50,MATCH(1,(GMW!$HM$2:$HM$50=H$3)*(GMW!$HN$2:$HN$50=H$1),0),$B60-1973)} -> 10.4 | I60: {=INDEX(GMW!$A$2:$HN$50,MATCH(1,(GMW!$HM$2:$HM$50=I$3)*(GMW!$HN$2:$HN$50=I$1),0),$B60-1973)} -> 230278 | J60: {=INDEX(GMW!$A$2:$HN$50,MATCH(1,(GMW!$HM$2:$HM$50=J$3)*(GMW!$HN$2:$HN$50=J$1),0),$B60-1973)} -> 6646 | K60: {=INDEX(GMW!$A$2:$HN$50,MATCH(1,(GMW!$HM$2:$HM$50=K$3)*(GMW!$HN$2:$HN$50=K$1),0),$B60-1973)} -> 352612 | L60: {=INDEX(GMW!$A$2:$HN$50,MATCH(1,(GMW!$HM$2:$HM$50=L$3)*(GMW!$HN$2:$HN$50=L$1),0),$B60-1973)} -> 25293 | ... P60: {=INDEX(GMW!$A$2:$HN$50,MATCH(1,(GMW!$HM$2:$HM$50=P$3)*(GMW!$HN$2:$HN$50=P$1),0),$B60-1973)} -> 6646
B61: =+B60+1 -> 2034 | C61: =+C57+1 -> 1993 | D61: =+D57+1 -> 1993 | E61: {=INDEX(GMW!$A$2:$HN$50,MATCH(1,(GMW!$HM$2:$HM$50=E$3)*(GMW!$HN$2:$HN$50=E$1),0),$B61-1973)} -> 355841 | F61: {=INDEX(GMW!$A$2:$HN$50,MATCH(1,(GMW!$HM$2:$HM$50=F$3)*(GMW!$HN$2:$HN$50=F$1),0),$B61-1973)} -> 25316 | G61: {=INDEX(GMW!$A$2:$HN$50,MATCH(1,(GMW!$HM$2:$HM$50=G$3)*(GMW!$HN$2:$HN$50=G$1),0),$B61-1973)} -> 3630.535 | H61: {=INDEX(GMW!$A$2:$HN$50,MATCH(1,(GMW!$HM$2:$HM$50=H$3)*(GMW!$HN$2:$HN$50=H$1),0),$B61-1973)} -> 10.2 | I61: {=INDEX(GMW!$A$2:$HN$50,MATCH(1,(GMW!$HM$2:$HM$50=I$3)*(GMW!$HN$2:$HN$50=I$1),0),$B61-1973)} -> 232470 | J61: {=INDEX(GMW!$A$2:$HN$50,MATCH(1,(GMW!$HM$2:$HM$50=J$3)*(GMW!$HN$2:$HN$50=J$1),0),$B61-1973)} -> 6727 | K61: {=INDEX(GMW!$A$2:$HN$50,MATCH(1,(GMW!$HM$2:$HM$50=K$3)*(GMW!$HN$2:$HN$50=K$1),0),$B61-1973)} -> 355841 | L61: {=INDEX(GMW!$A$2:$HN$50,MATCH(1,(GMW!$HM$2:$HM$50=L$3)*(GMW!$HN$2:$HN$50=L$1),0),$B61-1973)} -> 25316 | ... P61: {=INDEX(GMW!$A$2:$HN$50,MATCH(1,(GMW!$HM$2:$HM$50=P$3)*(GMW!$HN$2:$HN$50=P$1),0),$B61-1973)} -> 6727
B62: =+B61+1 -> 2035 | C62: =+C58+1 -> 1993 | D62: =+D58+1 -> 1993 | E62: {=INDEX(GMW!$A$2:$HN$50,MATCH(1,(GMW!$HM$2:$HM$50=E$3)*(GMW!$HN$2:$HN$50=E$1),0),$B62-1973)} -> 358264 | F62: {=INDEX(GMW!$A$2:$HN$50,MATCH(1,(GMW!$HM$2:$HM$50=F$3)*(GMW!$HN$2:$HN$50=F$1),0),$B62-1973)} -> 25320 | G62: {=INDEX(GMW!$A$2:$HN$50,MATCH(1,(GMW!$HM$2:$HM$50=G$3)*(GMW!$HN$2:$HN$50=G$1),0),$B62-1973)} -> 3662.197 | H62: {=INDEX(GMW!$A$2:$HN$50,MATCH(1,(GMW!$HM$2:$HM$50=H$3)*(GMW!$HN$2:$HN$50=H$1),0),$B62-1973)} -> 10.3 | I62: {=INDEX(GMW!$A$2:$HN$50,MATCH(1,(GMW!$HM$2:$HM$50=I$3)*(GMW!$HN$2:$HN$50=I$1),0),$B62-1973)} -> 233411 | J62: {=INDEX(GMW!$A$2:$HN$50,MATCH(1,(GMW!$HM$2:$HM$50=J$3)*(GMW!$HN$2:$HN$50=J$1),0),$B62-1973)} -> 6997 | K62: {=INDEX(GMW!$A$2:$HN$50,MATCH(1,(GMW!$HM$2:$HM$50=K$3)*(GMW!$HN$2:$HN$50=K$1),0),$B62-1973)} -> 358264 | L62: {=INDEX(GMW!$A$2:$HN$50,MATCH(1,(GMW!$HM$2:$HM$50=L$3)*(GMW!$HN$2:$HN$50=L$1),0),$B62-1973)} -> 25320 | ... P62: {=INDEX(GMW!$A$2:$HN$50,MATCH(1,(GMW!$HM$2:$HM$50=P$3)*(GMW!$HN$2:$HN$50=P$1),0),$B62-1973)} -> 6997
A63: 1994 | B63: =+B62+1 -> 2036 | C63: =+C59+1 -> 1994 | D63: =+D59+1 -> 1993 | E63: {=INDEX(GMW!$A$2:$HN$50,MATCH(1,(GMW!$HM$2:$HM$50=E$3)*(GMW!$HN$2:$HN$50=E$1),0),$B63-1973)} -> 361793 | F63: {=INDEX(GMW!$A$2:$HN$50,MATCH(1,(GMW!$HM$2:$HM$50=F$3)*(GMW!$HN$2:$HN$50=F$1),0),$B63-1973)} -> 25408 | G63: {=INDEX(GMW!$A$2:$HN$50,MATCH(1,(GMW!$HM$2:$HM$50=G$3)*(GMW!$HN$2:$HN$50=G$1),0),$B63-1973)} -> 3681.295 | H63: {=INDEX(GMW!$A$2:$HN$50,MATCH(1,(GMW!$HM$2:$HM$50=H$3)*(GMW!$HN$2:$HN$50=H$1),0),$B63-1973)} -> 9.9 | I63: {=INDEX(GMW!$A$2:$HN$50,MATCH(1,(GMW!$HM$2:$HM$50=I$3)*(GMW!$HN$2:$HN$50=I$1),0),$B63-1973)} -> 232541 | J63: {=INDEX(GMW!$A$2:$HN$50,MATCH(1,(GMW!$HM$2:$HM$50=J$3)*(GMW!$HN$2:$HN$50=J$1),0),$B63-1973)} -> 6841 | K63: {=INDEX(GMW!$A$2:$HN$50,MATCH(1,(GMW!$HM$2:$HM$50=K$3)*(GMW!$HN$2:$HN$50=K$1),0),$B63-1973)} -> 361793 | L63: {=INDEX(GMW!$A$2:$HN$50,MATCH(1,(GMW!$HM$2:$HM$50=L$3)*(GMW!$HN$2:$HN$50=L$1),0),$B63-1973)} -> 25408 | ... P63: {=INDEX(GMW!$A$2:$HN$50,MATCH(1,(GMW!$HM$2:$HM$50=P$3)*(GMW!$HN$2:$HN$50=P$1),0),$B63-1973)} -> 6841
B64: =+B63+1 -> 2037 | C64: =+C60+1 -> 1994 | D64: =+D60+1 -> 1994 | E64: {=INDEX(GMW!$A$2:$HN$50,MATCH(1,(GMW!$HM$2:$HM$50=E$3)*(GMW!$HN$2:$HN$50=E$1),0),$B64-1973)} -> 365109 | F64: {=INDEX(GMW!$A$2:$HN$50,MATCH(1,(GMW!$HM$2:$HM$50=F$3)*(GMW!$HN$2:$HN$50=F$1),0),$B64-1973)} -> 25451 | G64: {=INDEX(GMW!$A$2:$HN$50,MATCH(1,(GMW!$HM$2:$HM$50=G$3)*(GMW!$HN$2:$HN$50=G$1),0),$B64-1973)} -> 3682.575 | H64: {=INDEX(GMW!$A$2:$HN$50,MATCH(1,(GMW!$HM$2:$HM$50=H$3)*(GMW!$HN$2:$HN$50=H$1),0),$B64-1973)} -> 9.7 | I64: {=INDEX(GMW!$A$2:$HN$50,MATCH(1,(GMW!$HM$2:$HM$50=I$3)*(GMW!$HN$2:$HN$50=I$1),0),$B64-1973)} -> 232173 | J64: {=INDEX(GMW!$A$2:$HN$50,MATCH(1,(GMW!$HM$2:$HM$50=J$3)*(GMW!$HN$2:$HN$50=J$1),0),$B64-1973)} -> 6602 | K64: {=INDEX(GMW!$A$2:$HN$50,MATCH(1,(GMW!$HM$2:$HM$50=K$3)*(GMW!$HN$2:$HN$50=K$1),0),$B64-1973)} -> 365109 | L64: {=INDEX(GMW!$A$2:$HN$50,MATCH(1,(GMW!$HM$2:$HM$50=L$3)*(GMW!$HN$2:$HN$50=L$1),0),$B64-1973)} -> 25451 | ... P64: {=INDEX(GMW!$A$2:$HN$50,MATCH(1,(GMW!$HM$2:$HM$50=P$3)*(GMW!$HN$2:$HN$50=P$1),0),$B64-1973)} -> 6602
B65: =+B64+1 -> 2038 | C65: =+C61+1 -> 1994 | D65: =+D61+1 -> 1994 | E65: {=INDEX(GMW!$A$2:$HN$50,MATCH(1,(GMW!$HM$2:$HM$50=E$3)*(GMW!$HN$2:$HN$50=E$1),0),$B65-1973)} -> 368798 | F65: {=INDEX(GMW!$A$2:$HN$50,MATCH(1,(GMW!$HM$2:$HM$50=F$3)*(GMW!$HN$2:$HN$50=F$1),0),$B65-1973)} -> 25559 | G65: {=INDEX(GMW!$A$2:$HN$50,MATCH(1,(GMW!$HM$2:$HM$50=G$3)*(GMW!$HN$2:$HN$50=G$1),0),$B65-1973)} -> 3730.634 | H65: {=INDEX(GMW!$A$2:$HN$50,MATCH(1,(GMW!$HM$2:$HM$50=H$3)*(GMW!$HN$2:$HN$50=H$1),0),$B65-1973)} -> 9.4 | I65: {=INDEX(GMW!$A$2:$HN$50,MATCH(1,(GMW!$HM$2:$HM$50=I$3)*(GMW!$HN$2:$HN$50=I$1),0),$B65-1973)} -> 236870 | J65: {=INDEX(GMW!$A$2:$HN$50,MATCH(1,(GMW!$HM$2:$HM$50=J$3)*(GMW!$HN$2:$HN$50=J$1),0),$B65-1973)} -> 6704 | K65: {=INDEX(GMW!$A$2:$HN$50,MATCH(1,(GMW!$HM$2:$HM$50=K$3)*(GMW!$HN$2:$HN$50=K$1),0),$B65-1973)} -> 368798 | L65: {=INDEX(GMW!$A$2:$HN$50,MATCH(1,(GMW!$HM$2:$HM$50=L$3)*(GMW!$HN$2:$HN$50=L$1),0),$B65-1973)} -> 25559 | ... P65: {=INDEX(GMW!$A$2:$HN$50,MATCH(1,(GMW!$HM$2:$HM$50=P$3)*(GMW!$HN$2:$HN$50=P$1),0),$B65-1973)} -> 6704
B66: =+B65+1 -> 2039 | C66: =+C62+1 -> 1994 | D66: =+D62+1 -> 1994 | E66: {=INDEX(GMW!$A$2:$HN$50,MATCH(1,(GMW!$HM$2:$HM$50=E$3)*(GMW!$HN$2:$HN$50=E$1),0),$B66-1973)} -> 370401 | F66: {=INDEX(GMW!$A$2:$HN$50,MATCH(1,(GMW!$HM$2:$HM$50=F$3)*(GMW!$HN$2:$HN$50=F$1),0),$B66-1973)} -> 25600 | G66: {=INDEX(GMW!$A$2:$HN$50,MATCH(1,(GMW!$HM$2:$HM$50=G$3)*(GMW!$HN$2:$HN$50=G$1),0),$B66-1973)} -> 3764.534 | H66: {=INDEX(GMW!$A$2:$HN$50,MATCH(1,(GMW!$HM$2:$HM$50=H$3)*(GMW!$HN$2:$HN$50=H$1),0),$B66-1973)} -> 9 | I66: {=INDEX(GMW!$A$2:$HN$50,MATCH(1,(GMW!$HM$2:$HM$50=I$3)*(GMW!$HN$2:$HN$50=I$1),0),$B66-1973)} -> 235558 | J66: {=INDEX(GMW!$A$2:$HN$50,MATCH(1,(GMW!$HM$2:$HM$50=J$3)*(GMW!$HN$2:$HN$50=J$1),0),$B66-1973)} -> 6891 | K66: {=INDEX(GMW!$A$2:$HN$50,MATCH(1,(GMW!$HM$2:$HM$50=K$3)*(GMW!$HN$2:$HN$50=K$1),0),$B66-1973)} -> 370401 | L66: {=INDEX(GMW!$A$2:$HN$50,MATCH(1,(GMW!$HM$2:$HM$50=L$3)*(GMW!$HN$2:$HN$50=L$1),0),$B66-1973)} -> 25600 | ... P66: {=INDEX(GMW!$A$2:$HN$50,MATCH(1,(GMW!$HM$2:$HM$50=P$3)*(GMW!$HN$2:$HN$50=P$1),0),$B66-1973)} -> 6891
A67: 1995 | B67: =+B66+1 -> 2040 | C67: =+C63+1 -> 1995 | D67: =+D63+1 -> 1994 | E67: {=INDEX(GMW!$A$2:$HN$50,MATCH(1,(GMW!$HM$2:$HM$50=E$3)*(GMW!$HN$2:$HN$50=E$1),0),$B67-1973)} -> 372307 | F67: {=INDEX(GMW!$A$2:$HN$50,MATCH(1,(GMW!$HM$2:$HM$50=F$3)*(GMW!$HN$2:$HN$50=F$1),0),$B67-1973)} -> 25670 | G67: {=INDEX(GMW!$A$2:$HN$50,MATCH(1,(GMW!$HM$2:$HM$50=G$3)*(GMW!$HN$2:$HN$50=G$1),0),$B67-1973)} -> 3784.689 | H67: {=INDEX(GMW!$A$2:$HN$50,MATCH(1,(GMW!$HM$2:$HM$50=H$3)*(GMW!$HN$2:$HN$50=H$1),0),$B67-1973)} -> 8.9 | I67: {=INDEX(GMW!$A$2:$HN$50,MATCH(1,(GMW!$HM$2:$HM$50=I$3)*(GMW!$HN$2:$HN$50=I$1),0),$B67-1973)} -> 239669 | J67: {=INDEX(GMW!$A$2:$HN$50,MATCH(1,(GMW!$HM$2:$HM$50=J$3)*(GMW!$HN$2:$HN$50=J$1),0),$B67-1973)} -> 6872 | K67: {=INDEX(GMW!$A$2:$HN$50,MATCH(1,(GMW!$HM$2:$HM$50=K$3)*(GMW!$HN$2:$HN$50=K$1),0),$B67-1973)} -> 372307 | L67: {=INDEX(GMW!$A$2:$HN$50,MATCH(1,(GMW!$HM$2:$HM$50=L$3)*(GMW!$HN$2:$HN$50=L$1),0),$B67-1973)} -> 25670 | ... P67: {=INDEX(GMW!$A$2:$HN$50,MATCH(1,(GMW!$HM$2:$HM$50=P$3)*(GMW!$HN$2:$HN$50=P$1),0),$B67-1973)} -> 6872
B68: =+B67+1 -> 2041 | C68: =+C64+1 -> 1995 | D68: =+D64+1 -> 1995 | E68: {=INDEX(GMW!$A$2:$HN$50,MATCH(1,(GMW!$HM$2:$HM$50=E$3)*(GMW!$HN$2:$HN$50=E$1),0),$B68-1973)} -> 373090 | F68: {=INDEX(GMW!$A$2:$HN$50,MATCH(1,(GMW!$HM$2:$HM$50=F$3)*(GMW!$HN$2:$HN$50=F$1),0),$B68-1973)} -> 25770 | G68: {=INDEX(GMW!$A$2:$HN$50,MATCH(1,(GMW!$HM$2:$HM$50=G$3)*(GMW!$HN$2:$HN$50=G$1),0),$B68-1973)} -> 3813.237 | H68: {=INDEX(GMW!$A$2:$HN$50,MATCH(1,(GMW!$HM$2:$HM$50=H$3)*(GMW!$HN$2:$HN$50=H$1),0),$B68-1973)} -> 8.7 | I68: {=INDEX(GMW!$A$2:$HN$50,MATCH(1,(GMW!$HM$2:$HM$50=I$3)*(GMW!$HN$2:$HN$50=I$1),0),$B68-1973)} -> 239943 | J68: {=INDEX(GMW!$A$2:$HN$50,MATCH(1,(GMW!$HM$2:$HM$50=J$3)*(GMW!$HN$2:$HN$50=J$1),0),$B68-1973)} -> 6901 | K68: {=INDEX(GMW!$A$2:$HN$50,MATCH(1,(GMW!$HM$2:$HM$50=K$3)*(GMW!$HN$2:$HN$50=K$1),0),$B68-1973)} -> 373090 | L68: {=INDEX(GMW!$A$2:$HN$50,MATCH(1,(GMW!$HM$2:$HM$50=L$3)*(GMW!$HN$2:$HN$50=L$1),0),$B68-1973)} -> 25770 | ... P68: {=INDEX(GMW!$A$2:$HN$50,MATCH(1,(GMW!$HM$2:$HM$50=P$3)*(GMW!$HN$2:$HN$50=P$1),0),$B68-1973)} -> 6901
B69: =+B68+1 -> 2042 | C69: =+C65+1 -> 1995 | D69: =+D65+1 -> 1995 | E69: {=INDEX(GMW!$A$2:$HN$50,MATCH(1,(GMW!$HM$2:$HM$50=E$3)*(GMW!$HN$2:$HN$50=E$1),0),$B69-1973)} -> 377249 | F69: {=INDEX(GMW!$A$2:$HN$50,MATCH(1,(GMW!$HM$2:$HM$50=F$3)*(GMW!$HN$2:$HN$50=F$1),0),$B69-1973)} -> 25852 | G69: {=INDEX(GMW!$A$2:$HN$50,MATCH(1,(GMW!$HM$2:$HM$50=G$3)*(GMW!$HN$2:$HN$50=G$1),0),$B69-1973)} -> 3825.77 | H69: {=INDEX(GMW!$A$2:$HN$50,MATCH(1,(GMW!$HM$2:$HM$50=H$3)*(GMW!$HN$2:$HN$50=H$1),0),$B69-1973)} -> 8.6 | I69: {=INDEX(GMW!$A$2:$HN$50,MATCH(1,(GMW!$HM$2:$HM$50=I$3)*(GMW!$HN$2:$HN$50=I$1),0),$B69-1973)} -> 242123 | J69: {=INDEX(GMW!$A$2:$HN$50,MATCH(1,(GMW!$HM$2:$HM$50=J$3)*(GMW!$HN$2:$HN$50=J$1),0),$B69-1973)} -> 6999 | K69: {=INDEX(GMW!$A$2:$HN$50,MATCH(1,(GMW!$HM$2:$HM$50=K$3)*(GMW!$HN$2:$HN$50=K$1),0),$B69-1973)} -> 377249 | L69: {=INDEX(GMW!$A$2:$HN$50,MATCH(1,(GMW!$HM$2:$HM$50=L$3)*(GMW!$HN$2:$HN$50=L$1),0),$B69-1973)} -> 25852 | ... P69: {=INDEX(GMW!$A$2:$HN$50,MATCH(1,(GMW!$HM$2:$HM$50=P$3)*(GMW!$HN$2:$HN$50=P$1),0),$B69-1973)} -> 6999
B70: =+B69+1 -> 2043 | C70: =+C66+1 -> 1995 | D70: =+D66+1 -> 1995 | E70: {=INDEX(GMW!$A$2:$HN$50,MATCH(1,(GMW!$HM$2:$HM$50=E$3)*(GMW!$HN$2:$HN$50=E$1),0),$B70-1973)} -> 378442 | F70: {=INDEX(GMW!$A$2:$HN$50,MATCH(1,(GMW!$HM$2:$HM$50=F$3)*(GMW!$HN$2:$HN$50=F$1),0),$B70-1973)} -> 25982 | G70: {=INDEX(GMW!$A$2:$HN$50,MATCH(1,(GMW!$HM$2:$HM$50=G$3)*(GMW!$HN$2:$HN$50=G$1),0),$B70-1973)} -> 3869.823 | H70: {=INDEX(GMW!$A$2:$HN$50,MATCH(1,(GMW!$HM$2:$HM$50=H$3)*(GMW!$HN$2:$HN$50=H$1),0),$B70-1973)} -> 8.3 | I70: {=INDEX(GMW!$A$2:$HN$50,MATCH(1,(GMW!$HM$2:$HM$50=I$3)*(GMW!$HN$2:$HN$50=I$1),0),$B70-1973)} -> 243427 | J70: {=INDEX(GMW!$A$2:$HN$50,MATCH(1,(GMW!$HM$2:$HM$50=J$3)*(GMW!$HN$2:$HN$50=J$1),0),$B70-1973)} -> 7120 | K70: {=INDEX(GMW!$A$2:$HN$50,MATCH(1,(GMW!$HM$2:$HM$50=K$3)*(GMW!$HN$2:$HN$50=K$1),0),$B70-1973)} -> 378442 | L70: {=INDEX(GMW!$A$2:$HN$50,MATCH(1,(GMW!$HM$2:$HM$50=L$3)*(GMW!$HN$2:$HN$50=L$1),0),$B70-1973)} -> 25982 | ... P70: {=INDEX(GMW!$A$2:$HN$50,MATCH(1,(GMW!$HM$2:$HM$50=P$3)*(GMW!$HN$2:$HN$50=P$1),0),$B70-1973)} -> 7120
A71: 1996 | B71: =+B70+1 -> 2044 | C71: =+C67+1 -> 1996 | D71: =+D67+1 -> 1995 | E71: {=INDEX(GMW!$A$2:$HN$50,MATCH(1,(GMW!$HM$2:$HM$50=E$3)*(GMW!$HN$2:$HN$50=E$1),0),$B71-1973)} -> 380976 | F71: {=INDEX(GMW!$A$2:$HN$50,MATCH(1,(GMW!$HM$2:$HM$50=F$3)*(GMW!$HN$2:$HN$50=F$1),0),$B71-1973)} -> 25970 | G71: {=INDEX(GMW!$A$2:$HN$50,MATCH(1,(GMW!$HM$2:$HM$50=G$3)*(GMW!$HN$2:$HN$50=G$1),0),$B71-1973)} -> 3882.18 | H71: {=INDEX(GMW!$A$2:$HN$50,MATCH(1,(GMW!$HM$2:$HM$50=H$3)*(GMW!$HN$2:$HN$50=H$1),0),$B71-1973)} -> 8.2 | I71: {=INDEX(GMW!$A$2:$HN$50,MATCH(1,(GMW!$HM$2:$HM$50=I$3)*(GMW!$HN$2:$HN$50=I$1),0),$B71-1973)} -> 247598 | J71: {=INDEX(GMW!$A$2:$HN$50,MATCH(1,(GMW!$HM$2:$HM$50=J$3)*(GMW!$HN$2:$HN$50=J$1),0),$B71-1973)} -> 7100 | K71: {=INDEX(GMW!$A$2:$HN$50,MATCH(1,(GMW!$HM$2:$HM$50=K$3)*(GMW!$HN$2:$HN$50=K$1),0),$B71-1973)} -> 380976 | L71: {=INDEX(GMW!$A$2:$HN$50,MATCH(1,(GMW!$HM$2:$HM$50=L$3)*(GMW!$HN$2:$HN$50=L$1),0),$B71-1973)} -> 25970 | ... P71: {=INDEX(GMW!$A$2:$HN$50,MATCH(1,(GMW!$HM$2:$HM$50=P$3)*(GMW!$HN$2:$HN$50=P$1),0),$B71-1973)} -> 7100
B72: =+B71+1 -> 2045 | C72: =+C68+1 -> 1996 | D72: =+D68+1 -> 1996 | E72: {=INDEX(GMW!$A$2:$HN$50,MATCH(1,(GMW!$HM$2:$HM$50=E$3)*(GMW!$HN$2:$HN$50=E$1),0),$B72-1973)} -> 382146 | F72: {=INDEX(GMW!$A$2:$HN$50,MATCH(1,(GMW!$HM$2:$HM$50=F$3)*(GMW!$HN$2:$HN$50=F$1),0),$B72-1973)} -> 26009 | G72: {=INDEX(GMW!$A$2:$HN$50,MATCH(1,(GMW!$HM$2:$HM$50=G$3)*(GMW!$HN$2:$HN$50=G$1),0),$B72-1973)} -> 3914.624 | H72: {=INDEX(GMW!$A$2:$HN$50,MATCH(1,(GMW!$HM$2:$HM$50=H$3)*(GMW!$HN$2:$HN$50=H$1),0),$B72-1973)} -> 8.3 | I72: {=INDEX(GMW!$A$2:$HN$50,MATCH(1,(GMW!$HM$2:$HM$50=I$3)*(GMW!$HN$2:$HN$50=I$1),0),$B72-1973)} -> 247441 | J72: {=INDEX(GMW!$A$2:$HN$50,MATCH(1,(GMW!$HM$2:$HM$50=J$3)*(GMW!$HN$2:$HN$50=J$1),0),$B72-1973)} -> 7308 | K72: {=INDEX(GMW!$A$2:$HN$50,MATCH(1,(GMW!$HM$2:$HM$50=K$3)*(GMW!$HN$2:$HN$50=K$1),0),$B72-1973)} -> 382146 | L72: {=INDEX(GMW!$A$2:$HN$50,MATCH(1,(GMW!$HM$2:$HM$50=L$3)*(GMW!$HN$2:$HN$50=L$1),0),$B72-1973)} -> 26009 | ... P72: {=INDEX(GMW!$A$2:$HN$50,MATCH(1,(GMW!$HM$2:$HM$50=P$3)*(GMW!$HN$2:$HN$50=P$1),0),$B72-1973)} -> 7308
B73: =+B72+1 -> 2046 | C73: =+C69+1 -> 1996 | D73: =+D69+1 -> 1996 | E73: {=INDEX(GMW!$A$2:$HN$50,MATCH(1,(GMW!$HM$2:$HM$50=E$3)*(GMW!$HN$2:$HN$50=E$1),0),$B73-1973)} -> 385671 | F73: {=INDEX(GMW!$A$2:$HN$50,MATCH(1,(GMW!$HM$2:$HM$50=F$3)*(GMW!$HN$2:$HN$50=F$1),0),$B73-1973)} -> 26062 | G73: {=INDEX(GMW!$A$2:$HN$50,MATCH(1,(GMW!$HM$2:$HM$50=G$3)*(GMW!$HN$2:$HN$50=G$1),0),$B73-1973)} -> 3968.22 | H73: {=INDEX(GMW!$A$2:$HN$50,MATCH(1,(GMW!$HM$2:$HM$50=H$3)*(GMW!$HN$2:$HN$50=H$1),0),$B73-1973)} -> 8.1 | I73: {=INDEX(GMW!$A$2:$HN$50,MATCH(1,(GMW!$HM$2:$HM$50=I$3)*(GMW!$HN$2:$HN$50=I$1),0),$B73-1973)} -> 250067 | J73: {=INDEX(GMW!$A$2:$HN$50,MATCH(1,(GMW!$HM$2:$HM$50=J$3)*(GMW!$HN$2:$HN$50=J$1),0),$B73-1973)} -> 7377 | K73: {=INDEX(GMW!$A$2:$HN$50,MATCH(1,(GMW!$HM$2:$HM$50=K$3)*(GMW!$HN$2:$HN$50=K$1),0),$B73-1973)} -> 385671 | L73: {=INDEX(GMW!$A$2:$HN$50,MATCH(1,(GMW!$HM$2:$HM$50=L$3)*(GMW!$HN$2:$HN$50=L$1),0),$B73-1973)} -> 26062 | ... P73: {=INDEX(GMW!$A$2:$HN$50,MATCH(1,(GMW!$HM$2:$HM$50=P$3)*(GMW!$HN$2:$HN$50=P$1),0),$B73-1973)} -> 7377
B74: =+B73+1 -> 2047 | C74: =+C70+1 -> 1996 | D74: =+D70+1 -> 1996 | E74: {=INDEX(GMW!$A$2:$HN$50,MATCH(1,(GMW!$HM$2:$HM$50=E$3)*(GMW!$HN$2:$HN$50=E$1),0),$B74-1973)} -> 391053 | F74: {=INDEX(GMW!$A$2:$HN$50,MATCH(1,(GMW!$HM$2:$HM$50=F$3)*(GMW!$HN$2:$HN$50=F$1),0),$B74-1973)} -> 26198 | G74: {=INDEX(GMW!$A$2:$HN$50,MATCH(1,(GMW!$HM$2:$HM$50=G$3)*(GMW!$HN$2:$HN$50=G$1),0),$B74-1973)} -> 3978.247 | H74: {=INDEX(GMW!$A$2:$HN$50,MATCH(1,(GMW!$HM$2:$HM$50=H$3)*(GMW!$HN$2:$HN$50=H$1),0),$B74-1973)} -> 7.8 | I74: {=INDEX(GMW!$A$2:$HN$50,MATCH(1,(GMW!$HM$2:$HM$50=I$3)*(GMW!$HN$2:$HN$50=I$1),0),$B74-1973)} -> 245800 | J74: {=INDEX(GMW!$A$2:$HN$50,MATCH(1,(GMW!$HM$2:$HM$50=J$3)*(GMW!$HN$2:$HN$50=J$1),0),$B74-1973)} -> 7428 | K74: {=INDEX(GMW!$A$2:$HN$50,MATCH(1,(GMW!$HM$2:$HM$50=K$3)*(GMW!$HN$2:$HN$50=K$1),0),$B74-1973)} -> 391053 | L74: {=INDEX(GMW!$A$2:$HN$50,MATCH(1,(GMW!$HM$2:$HM$50=L$3)*(GMW!$HN$2:$HN$50=L$1),0),$B74-1973)} -> 26198 | ... P74: {=INDEX(GMW!$A$2:$HN$50,MATCH(1,(GMW!$HM$2:$HM$50=P$3)*(GMW!$HN$2:$HN$50=P$1),0),$B74-1973)} -> 7428
A75: 1997 | B75: =+B74+1 -> 2048 | C75: =+C71+1 -> 1997 | D75: =+D71+1 -> 1996 | E75: {=INDEX(GMW!$A$2:$HN$50,MATCH(1,(GMW!$HM$2:$HM$50=E$3)*(GMW!$HN$2:$HN$50=E$1),0),$B75-1973)} -> 397303 | F75: {=INDEX(GMW!$A$2:$HN$50,MATCH(1,(GMW!$HM$2:$HM$50=F$3)*(GMW!$HN$2:$HN$50=F$1),0),$B75-1973)} -> 26381 | G75: {=INDEX(GMW!$A$2:$HN$50,MATCH(1,(GMW!$HM$2:$HM$50=G$3)*(GMW!$HN$2:$HN$50=G$1),0),$B75-1973)} -> 4081.993 | H75: {=INDEX(GMW!$A$2:$HN$50,MATCH(1,(GMW!$HM$2:$HM$50=H$3)*(GMW!$HN$2:$HN$50=H$1),0),$B75-1973)} -> 7.3 | I75: {=INDEX(GMW!$A$2:$HN$50,MATCH(1,(GMW!$HM$2:$HM$50=I$3)*(GMW!$HN$2:$HN$50=I$1),0),$B75-1973)} -> 249558 | J75: {=INDEX(GMW!$A$2:$HN$50,MATCH(1,(GMW!$HM$2:$HM$50=J$3)*(GMW!$HN$2:$HN$50=J$1),0),$B75-1973)} -> 7219 | K75: {=INDEX(GMW!$A$2:$HN$50,MATCH(1,(GMW!$HM$2:$HM$50=K$3)*(GMW!$HN$2:$HN$50=K$1),0),$B75-1973)} -> 397303 | L75: {=INDEX(GMW!$A$2:$HN$50,MATCH(1,(GMW!$HM$2:$HM$50=L$3)*(GMW!$HN$2:$HN$50=L$1),0),$B75-1973)} -> 26381 | ... P75: {=INDEX(GMW!$A$2:$HN$50,MATCH(1,(GMW!$HM$2:$HM$50=P$3)*(GMW!$HN$2:$HN$50=P$1),0),$B75-1973)} -> 7219
B76: =+B75+1 -> 2049 | C76: =+C72+1 -> 1997 | D76: =+D72+1 -> 1997 | E76: {=INDEX(GMW!$A$2:$HN$50,MATCH(1,(GMW!$HM$2:$HM$50=E$3)*(GMW!$HN$2:$HN$50=E$1),0),$B76-1973)} -> 401790 | F76: {=INDEX(GMW!$A$2:$HN$50,MATCH(1,(GMW!$HM$2:$HM$50=F$3)*(GMW!$HN$2:$HN$50=F$1),0),$B76-1973)} -> 26514 | G76: {=INDEX(GMW!$A$2:$HN$50,MATCH(1,(GMW!$HM$2:$HM$50=G$3)*(GMW!$HN$2:$HN$50=G$1),0),$B76-1973)} -> 4143.857 | H76: {=INDEX(GMW!$A$2:$HN$50,MATCH(1,(GMW!$HM$2:$HM$50=H$3)*(GMW!$HN$2:$HN$50=H$1),0),$B76-1973)} -> 7.2 | I76: {=INDEX(GMW!$A$2:$HN$50,MATCH(1,(GMW!$HM$2:$HM$50=I$3)*(GMW!$HN$2:$HN$50=I$1),0),$B76-1973)} -> 251781 | J76: {=INDEX(GMW!$A$2:$HN$50,MATCH(1,(GMW!$HM$2:$HM$50=J$3)*(GMW!$HN$2:$HN$50=J$1),0),$B76-1973)} -> 7704 | K76: {=INDEX(GMW!$A$2:$HN$50,MATCH(1,(GMW!$HM$2:$HM$50=K$3)*(GMW!$HN$2:$HN$50=K$1),0),$B76-1973)} -> 401790 | L76: {=INDEX(GMW!$A$2:$HN$50,MATCH(1,(GMW!$HM$2:$HM$50=L$3)*(GMW!$HN$2:$HN$50=L$1),0),$B76-1973)} -> 26514 | ... P76: {=INDEX(GMW!$A$2:$HN$50,MATCH(1,(GMW!$HM$2:$HM$50=P$3)*(GMW!$HN$2:$HN$50=P$1),0),$B76-1973)} -> 7704
B77: =+B76+1 -> 2050 | C77: =+C73+1 -> 1997 | D77: =+D73+1 -> 1997 | E77: {=INDEX(GMW!$A$2:$HN$50,MATCH(1,(GMW!$HM$2:$HM$50=E$3)*(GMW!$HN$2:$HN$50=E$1),0),$B77-1973)} -> 405233 | F77: {=INDEX(GMW!$A$2:$HN$50,MATCH(1,(GMW!$HM$2:$HM$50=F$3)*(GMW!$HN$2:$HN$50=F$1),0),$B77-1973)} -> 26572 | G77: {=INDEX(GMW!$A$2:$HN$50,MATCH(1,(GMW!$HM$2:$HM$50=G$3)*(GMW!$HN$2:$HN$50=G$1),0),$B77-1973)} -> 4207.873 | H77: {=INDEX(GMW!$A$2:$HN$50,MATCH(1,(GMW!$HM$2:$HM$50=H$3)*(GMW!$HN$2:$HN$50=H$1),0),$B77-1973)} -> 6.8 | I77: {=INDEX(GMW!$A$2:$HN$50,MATCH(1,(GMW!$HM$2:$HM$50=I$3)*(GMW!$HN$2:$HN$50=I$1),0),$B77-1973)} -> 254358 | J77: {=INDEX(GMW!$A$2:$HN$50,MATCH(1,(GMW!$HM$2:$HM$50=J$3)*(GMW!$HN$2:$HN$50=J$1),0),$B77-1973)} -> 8050 | K77: {=INDEX(GMW!$A$2:$HN$50,MATCH(1,(GMW!$HM$2:$HM$50=K$3)*(GMW!$HN$2:$HN$50=K$1),0),$B77-1973)} -> 405233 | L77: {=INDEX(GMW!$A$2:$HN$50,MATCH(1,(GMW!$HM$2:$HM$50=L$3)*(GMW!$HN$2:$HN$50=L$1),0),$B77-1973)} -> 26572 | ... P77: {=INDEX(GMW!$A$2:$HN$50,MATCH(1,(GMW!$HM$2:$HM$50=P$3)*(GMW!$HN$2:$HN$50=P$1),0),$B77-1973)} -> 8050
B78: =+B77+1 -> 2051 | C78: =+C74+1 -> 1997 | D78: =+D74+1 -> 1997 | E78: {=INDEX(GMW!$A$2:$HN$50,MATCH(1,(GMW!$HM$2:$HM$50=E$3)*(GMW!$HN$2:$HN$50=E$1),0),$B78-1973)} -> 411352 | F78: {=INDEX(GMW!$A$2:$HN$50,MATCH(1,(GMW!$HM$2:$HM$50=F$3)*(GMW!$HN$2:$HN$50=F$1),0),$B78-1973)} -> 26636 | G78: {=INDEX(GMW!$A$2:$HN$50,MATCH(1,(GMW!$HM$2:$HM$50=G$3)*(GMW!$HN$2:$HN$50=G$1),0),$B78-1973)} -> 4225.691 | H78: {=INDEX(GMW!$A$2:$HN$50,MATCH(1,(GMW!$HM$2:$HM$50=H$3)*(GMW!$HN$2:$HN$50=H$1),0),$B78-1973)} -> 6.5 | I78: {=INDEX(GMW!$A$2:$HN$50,MATCH(1,(GMW!$HM$2:$HM$50=I$3)*(GMW!$HN$2:$HN$50=I$1),0),$B78-1973)} -> 253468 | J78: {=INDEX(GMW!$A$2:$HN$50,MATCH(1,(GMW!$HM$2:$HM$50=J$3)*(GMW!$HN$2:$HN$50=J$1),0),$B78-1973)} -> 8065 | K78: {=INDEX(GMW!$A$2:$HN$50,MATCH(1,(GMW!$HM$2:$HM$50=K$3)*(GMW!$HN$2:$HN$50=K$1),0),$B78-1973)} -> 411352 | L78: {=INDEX(GMW!$A$2:$HN$50,MATCH(1,(GMW!$HM$2:$HM$50=L$3)*(GMW!$HN$2:$HN$50=L$1),0),$B78-1973)} -> 26636 | ... P78: {=INDEX(GMW!$A$2:$HN$50,MATCH(1,(GMW!$HM$2:$HM$50=P$3)*(GMW!$HN$2:$HN$50=P$1),0),$B78-1973)} -> 8065
A79: 1998 | B79: =+B78+1 -> 2052 | C79: =+C75+1 -> 1998 | D79: =+D75+1 -> 1997 | E79: {=INDEX(GMW!$A$2:$HN$50,MATCH(1,(GMW!$HM$2:$HM$50=E$3)*(GMW!$HN$2:$HN$50=E$1),0),$B79-1973)} -> 414377 | F79: {=INDEX(GMW!$A$2:$HN$50,MATCH(1,(GMW!$HM$2:$HM$50=F$3)*(GMW!$HN$2:$HN$50=F$1),0),$B79-1973)} -> 26677 | G79: {=INDEX(GMW!$A$2:$HN$50,MATCH(1,(GMW!$HM$2:$HM$50=G$3)*(GMW!$HN$2:$HN$50=G$1),0),$B79-1973)} -> 4229.584 | H79: {=INDEX(GMW!$A$2:$HN$50,MATCH(1,(GMW!$HM$2:$HM$50=H$3)*(GMW!$HN$2:$HN$50=H$1),0),$B79-1973)} -> 6.4 | I79: {=INDEX(GMW!$A$2:$HN$50,MATCH(1,(GMW!$HM$2:$HM$50=I$3)*(GMW!$HN$2:$HN$50=I$1),0),$B79-1973)} -> 253069 | J79: {=INDEX(GMW!$A$2:$HN$50,MATCH(1,(GMW!$HM$2:$HM$50=J$3)*(GMW!$HN$2:$HN$50=J$1),0),$B79-1973)} -> 7887 | K79: {=INDEX(GMW!$A$2:$HN$50,MATCH(1,(GMW!$HM$2:$HM$50=K$3)*(GMW!$HN$2:$HN$50=K$1),0),$B79-1973)} -> 414377 | L79: {=INDEX(GMW!$A$2:$HN$50,MATCH(1,(GMW!$HM$2:$HM$50=L$3)*(GMW!$HN$2:$HN$50=L$1),0),$B79-1973)} -> 26677 | ... P79: {=INDEX(GMW!$A$2:$HN$50,MATCH(1,(GMW!$HM$2:$HM$50=P$3)*(GMW!$HN$2:$HN$50=P$1),0),$B79-1973)} -> 7887
B80: =+B79+1 -> 2053 | C80: =+C76+1 -> 1998 | D80: =+D76+1 -> 1998 | E80: {=INDEX(GMW!$A$2:$HN$50,MATCH(1,(GMW!$HM$2:$HM$50=E$3)*(GMW!$HN$2:$HN$50=E$1),0),$B80-1973)} -> 416909 | F80: {=INDEX(GMW!$A$2:$HN$50,MATCH(1,(GMW!$HM$2:$HM$50=F$3)*(GMW!$HN$2:$HN$50=F$1),0),$B80-1973)} -> 26714 | G80: {=INDEX(GMW!$A$2:$HN$50,MATCH(1,(GMW!$HM$2:$HM$50=G$3)*(GMW!$HN$2:$HN$50=G$1),0),$B80-1973)} -> 4273.278 | H80: {=INDEX(GMW!$A$2:$HN$50,MATCH(1,(GMW!$HM$2:$HM$50=H$3)*(GMW!$HN$2:$HN$50=H$1),0),$B80-1973)} -> 6.3 | I80: {=INDEX(GMW!$A$2:$HN$50,MATCH(1,(GMW!$HM$2:$HM$50=I$3)*(GMW!$HN$2:$HN$50=I$1),0),$B80-1973)} -> 254576 | J80: {=INDEX(GMW!$A$2:$HN$50,MATCH(1,(GMW!$HM$2:$HM$50=J$3)*(GMW!$HN$2:$HN$50=J$1),0),$B80-1973)} -> 8048 | K80: {=INDEX(GMW!$A$2:$HN$50,MATCH(1,(GMW!$HM$2:$HM$50=K$3)*(GMW!$HN$2:$HN$50=K$1),0),$B80-1973)} -> 416909 | L80: {=INDEX(GMW!$A$2:$HN$50,MATCH(1,(GMW!$HM$2:$HM$50=L$3)*(GMW!$HN$2:$HN$50=L$1),0),$B80-1973)} -> 26714 | ... P80: {=INDEX(GMW!$A$2:$HN$50,MATCH(1,(GMW!$HM$2:$HM$50=P$3)*(GMW!$HN$2:$HN$50=P$1),0),$B80-1973)} -> 8048
B81: =+B80+1 -> 2054 | C81: =+C77+1 -> 1998 | D81: =+D77+1 -> 1998 | E81: {=INDEX(GMW!$A$2:$HN$50,MATCH(1,(GMW!$HM$2:$HM$50=E$3)*(GMW!$HN$2:$HN$50=E$1),0),$B81-1973)} -> 418294 | F81: {=INDEX(GMW!$A$2:$HN$50,MATCH(1,(GMW!$HM$2:$HM$50=F$3)*(GMW!$HN$2:$HN$50=F$1),0),$B81-1973)} -> 26834 | G81: {=INDEX(GMW!$A$2:$HN$50,MATCH(1,(GMW!$HM$2:$HM$50=G$3)*(GMW!$HN$2:$HN$50=G$1),0),$B81-1973)} -> 4319.682 | H81: {=INDEX(GMW!$A$2:$HN$50,MATCH(1,(GMW!$HM$2:$HM$50=H$3)*(GMW!$HN$2:$HN$50=H$1),0),$B81-1973)} -> 6.2 | I81: {=INDEX(GMW!$A$2:$HN$50,MATCH(1,(GMW!$HM$2:$HM$50=I$3)*(GMW!$HN$2:$HN$50=I$1),0),$B81-1973)} -> 253636 | J81: {=INDEX(GMW!$A$2:$HN$50,MATCH(1,(GMW!$HM$2:$HM$50=J$3)*(GMW!$HN$2:$HN$50=J$1),0),$B81-1973)} -> 8448 | K81: {=INDEX(GMW!$A$2:$HN$50,MATCH(1,(GMW!$HM$2:$HM$50=K$3)*(GMW!$HN$2:$HN$50=K$1),0),$B81-1973)} -> 418294 | L81: {=INDEX(GMW!$A$2:$HN$50,MATCH(1,(GMW!$HM$2:$HM$50=L$3)*(GMW!$HN$2:$HN$50=L$1),0),$B81-1973)} -> 26834 | ... P81: {=INDEX(GMW!$A$2:$HN$50,MATCH(1,(GMW!$HM$2:$HM$50=P$3)*(GMW!$HN$2:$HN$50=P$1),0),$B81-1973)} -> 8448
B82: =+B81+1 -> 2055 | C82: =+C78+1 -> 1998 | D82: =+D78+1 -> 1998 | E82: {=INDEX(GMW!$A$2:$HN$50,MATCH(1,(GMW!$HM$2:$HM$50=E$3)*(GMW!$HN$2:$HN$50=E$1),0),$B82-1973)} -> 421074 | F82: {=INDEX(GMW!$A$2:$HN$50,MATCH(1,(GMW!$HM$2:$HM$50=F$3)*(GMW!$HN$2:$HN$50=F$1),0),$B82-1973)} -> 26955 | G82: {=INDEX(GMW!$A$2:$HN$50,MATCH(1,(GMW!$HM$2:$HM$50=G$3)*(GMW!$HN$2:$HN$50=G$1),0),$B82-1973)} -> 4319.271 | H82: {=INDEX(GMW!$A$2:$HN$50,MATCH(1,(GMW!$HM$2:$HM$50=H$3)*(GMW!$HN$2:$HN$50=H$1),0),$B82-1973)} -> 6.1 | I82: {=INDEX(GMW!$A$2:$HN$50,MATCH(1,(GMW!$HM$2:$HM$50=I$3)*(GMW!$HN$2:$HN$50=I$1),0),$B82-1973)} -> 257028 | J82: {=INDEX(GMW!$A$2:$HN$50,MATCH(1,(GMW!$HM$2:$HM$50=J$3)*(GMW!$HN$2:$HN$50=J$1),0),$B82-1973)} -> 8468 | K82: {=INDEX(GMW!$A$2:$HN$50,MATCH(1,(GMW!$HM$2:$HM$50=K$3)*(GMW!$HN$2:$HN$50=K$1),0),$B82-1973)} -> 421074 | L82: {=INDEX(GMW!$A$2:$HN$50,MATCH(1,(GMW!$HM$2:$HM$50=L$3)*(GMW!$HN$2:$HN$50=L$1),0),$B82-1973)} -> 26955 | ... P82: {=INDEX(GMW!$A$2:$HN$50,MATCH(1,(GMW!$HM$2:$HM$50=P$3)*(GMW!$HN$2:$HN$50=P$1),0),$B82-1973)} -> 8468
A83: 1999 | B83: =+B82+1 -> 2056 | C83: =+C79+1 -> 1999 | D83: =+D79+1 -> 1998 | E83: {=INDEX(GMW!$A$2:$HN$50,MATCH(1,(GMW!$HM$2:$HM$50=E$3)*(GMW!$HN$2:$HN$50=E$1),0),$B83-1973)} -> 423875 | F83: {=INDEX(GMW!$A$2:$HN$50,MATCH(1,(GMW!$HM$2:$HM$50=F$3)*(GMW!$HN$2:$HN$50=F$1),0),$B83-1973)} -> 27036 | G83: {=INDEX(GMW!$A$2:$HN$50,MATCH(1,(GMW!$HM$2:$HM$50=G$3)*(GMW!$HN$2:$HN$50=G$1),0),$B83-1973)} -> 4422.741 | H83: {=INDEX(GMW!$A$2:$HN$50,MATCH(1,(GMW!$HM$2:$HM$50=H$3)*(GMW!$HN$2:$HN$50=H$1),0),$B83-1973)} -> 6.2 | I83: {=INDEX(GMW!$A$2:$HN$50,MATCH(1,(GMW!$HM$2:$HM$50=I$3)*(GMW!$HN$2:$HN$50=I$1),0),$B83-1973)} -> 254037 | J83: {=INDEX(GMW!$A$2:$HN$50,MATCH(1,(GMW!$HM$2:$HM$50=J$3)*(GMW!$HN$2:$HN$50=J$1),0),$B83-1973)} -> 8757 | K83: {=INDEX(GMW!$A$2:$HN$50,MATCH(1,(GMW!$HM$2:$HM$50=K$3)*(GMW!$HN$2:$HN$50=K$1),0),$B83-1973)} -> 423875 | L83: {=INDEX(GMW!$A$2:$HN$50,MATCH(1,(GMW!$HM$2:$HM$50=L$3)*(GMW!$HN$2:$HN$50=L$1),0),$B83-1973)} -> 27036 | ... P83: {=INDEX(GMW!$A$2:$HN$50,MATCH(1,(GMW!$HM$2:$HM$50=P$3)*(GMW!$HN$2:$HN$50=P$1),0),$B83-1973)} -> 8757
B84: =+B83+1 -> 2057 | C84: =+C80+1 -> 1999 | D84: =+D80+1 -> 1999 | E84: {=INDEX(GMW!$A$2:$HN$50,MATCH(1,(GMW!$HM$2:$HM$50=E$3)*(GMW!$HN$2:$HN$50=E$1),0),$B84-1973)} -> 425920 | F84: {=INDEX(GMW!$A$2:$HN$50,MATCH(1,(GMW!$HM$2:$HM$50=F$3)*(GMW!$HN$2:$HN$50=F$1),0),$B84-1973)} -> 27095 | G84: {=INDEX(GMW!$A$2:$HN$50,MATCH(1,(GMW!$HM$2:$HM$50=G$3)*(GMW!$HN$2:$HN$50=G$1),0),$B84-1973)} -> 4529.62 | H84: {=INDEX(GMW!$A$2:$HN$50,MATCH(1,(GMW!$HM$2:$HM$50=H$3)*(GMW!$HN$2:$HN$50=H$1),0),$B84-1973)} -> 6 | I84: {=INDEX(GMW!$A$2:$HN$50,MATCH(1,(GMW!$HM$2:$HM$50=I$3)*(GMW!$HN$2:$HN$50=I$1),0),$B84-1973)} -> 266557 | J84: {=INDEX(GMW!$A$2:$HN$50,MATCH(1,(GMW!$HM$2:$HM$50=J$3)*(GMW!$HN$2:$HN$50=J$1),0),$B84-1973)} -> 8818 | K84: {=INDEX(GMW!$A$2:$HN$50,MATCH(1,(GMW!$HM$2:$HM$50=K$3)*(GMW!$HN$2:$HN$50=K$1),0),$B84-1973)} -> 425920 | L84: {=INDEX(GMW!$A$2:$HN$50,MATCH(1,(GMW!$HM$2:$HM$50=L$3)*(GMW!$HN$2:$HN$50=L$1),0),$B84-1973)} -> 27095 | ... P84: {=INDEX(GMW!$A$2:$HN$50,MATCH(1,(GMW!$HM$2:$HM$50=P$3)*(GMW!$HN$2:$HN$50=P$1),0),$B84-1973)} -> 8818
B85: =+B84+1 -> 2058 | C85: =+C81+1 -> 1999 | D85: =+D81+1 -> 1999 | E85: {=INDEX(GMW!$A$2:$HN$50,MATCH(1,(GMW!$HM$2:$HM$50=E$3)*(GMW!$HN$2:$HN$50=E$1),0),$B85-1973)} -> 432860 | F85: {=INDEX(GMW!$A$2:$HN$50,MATCH(1,(GMW!$HM$2:$HM$50=F$3)*(GMW!$HN$2:$HN$50=F$1),0),$B85-1973)} -> 27218 | G85: {=INDEX(GMW!$A$2:$HN$50,MATCH(1,(GMW!$HM$2:$HM$50=G$3)*(GMW!$HN$2:$HN$50=G$1),0),$B85-1973)} -> 4579.019 | H85: {=INDEX(GMW!$A$2:$HN$50,MATCH(1,(GMW!$HM$2:$HM$50=H$3)*(GMW!$HN$2:$HN$50=H$1),0),$B85-1973)} -> 5.9 | I85: {=INDEX(GMW!$A$2:$HN$50,MATCH(1,(GMW!$HM$2:$HM$50=I$3)*(GMW!$HN$2:$HN$50=I$1),0),$B85-1973)} -> 267871 | J85: {=INDEX(GMW!$A$2:$HN$50,MATCH(1,(GMW!$HM$2:$HM$50=J$3)*(GMW!$HN$2:$HN$50=J$1),0),$B85-1973)} -> 9094 | K85: {=INDEX(GMW!$A$2:$HN$50,MATCH(1,(GMW!$HM$2:$HM$50=K$3)*(GMW!$HN$2:$HN$50=K$1),0),$B85-1973)} -> 432860 | L85: {=INDEX(GMW!$A$2:$HN$50,MATCH(1,(GMW!$HM$2:$HM$50=L$3)*(GMW!$HN$2:$HN$50=L$1),0),$B85-1973)} -> 27218 | ... P85: {=INDEX(GMW!$A$2:$HN$50,MATCH(1,(GMW!$HM$2:$HM$50=P$3)*(GMW!$HN$2:$HN$50=P$1),0),$B85-1973)} -> 9094
B86: =+B85+1 -> 2059 | C86: =+C82+1 -> 1999 | D86: =+D82+1 -> 1999 | E86: {=INDEX(GMW!$A$2:$HN$50,MATCH(1,(GMW!$HM$2:$HM$50=E$3)*(GMW!$HN$2:$HN$50=E$1),0),$B86-1973)} -> 439093 | F86: {=INDEX(GMW!$A$2:$HN$50,MATCH(1,(GMW!$HM$2:$HM$50=F$3)*(GMW!$HN$2:$HN$50=F$1),0),$B86-1973)} -> 27322 | G86: {=INDEX(GMW!$A$2:$HN$50,MATCH(1,(GMW!$HM$2:$HM$50=G$3)*(GMW!$HN$2:$HN$50=G$1),0),$B86-1973)} -> 4624.274 | H86: {=INDEX(GMW!$A$2:$HN$50,MATCH(1,(GMW!$HM$2:$HM$50=H$3)*(GMW!$HN$2:$HN$50=H$1),0),$B86-1973)} -> 5.8 | I86: {=INDEX(GMW!$A$2:$HN$50,MATCH(1,(GMW!$HM$2:$HM$50=I$3)*(GMW!$HN$2:$HN$50=I$1),0),$B86-1973)} -> 274118 | J86: {=INDEX(GMW!$A$2:$HN$50,MATCH(1,(GMW!$HM$2:$HM$50=J$3)*(GMW!$HN$2:$HN$50=J$1),0),$B86-1973)} -> 9184 | K86: {=INDEX(GMW!$A$2:$HN$50,MATCH(1,(GMW!$HM$2:$HM$50=K$3)*(GMW!$HN$2:$HN$50=K$1),0),$B86-1973)} -> 439093 | L86: {=INDEX(GMW!$A$2:$HN$50,MATCH(1,(GMW!$HM$2:$HM$50=L$3)*(GMW!$HN$2:$HN$50=L$1),0),$B86-1973)} -> 27322 | ... P86: {=INDEX(GMW!$A$2:$HN$50,MATCH(1,(GMW!$HM$2:$HM$50=P$3)*(GMW!$HN$2:$HN$50=P$1),0),$B86-1973)} -> 9184
A87: 2000 | B87: =+B86+1 -> 2060 | C87: =+C83+1 -> 2000 | D87: =+D83+1 -> 1999 | E87: {=INDEX(GMW!$A$2:$HN$50,MATCH(1,(GMW!$HM$2:$HM$50=E$3)*(GMW!$HN$2:$HN$50=E$1),0),$B87-1973)} -> 444540 | F87: {=INDEX(GMW!$A$2:$HN$50,MATCH(1,(GMW!$HM$2:$HM$50=F$3)*(GMW!$HN$2:$HN$50=F$1),0),$B87-1973)} -> 27362 | G87: {=INDEX(GMW!$A$2:$HN$50,MATCH(1,(GMW!$HM$2:$HM$50=G$3)*(GMW!$HN$2:$HN$50=G$1),0),$B87-1973)} -> 4637.771 | H87: {=INDEX(GMW!$A$2:$HN$50,MATCH(1,(GMW!$HM$2:$HM$50=H$3)*(GMW!$HN$2:$HN$50=H$1),0),$B87-1973)} -> 5.8 | I87: {=INDEX(GMW!$A$2:$HN$50,MATCH(1,(GMW!$HM$2:$HM$50=I$3)*(GMW!$HN$2:$HN$50=I$1),0),$B87-1973)} -> 274370 | J87: {=INDEX(GMW!$A$2:$HN$50,MATCH(1,(GMW!$HM$2:$HM$50=J$3)*(GMW!$HN$2:$HN$50=J$1),0),$B87-1973)} -> 9313 | K87: {=INDEX(GMW!$A$2:$HN$50,MATCH(1,(GMW!$HM$2:$HM$50=K$3)*(GMW!$HN$2:$HN$50=K$1),0),$B87-1973)} -> 444540 | L87: {=INDEX(GMW!$A$2:$HN$50,MATCH(1,(GMW!$HM$2:$HM$50=L$3)*(GMW!$HN$2:$HN$50=L$1),0),$B87-1973)} -> 27362 | ... P87: {=INDEX(GMW!$A$2:$HN$50,MATCH(1,(GMW!$HM$2:$HM$50=P$3)*(GMW!$HN$2:$HN$50=P$1),0),$B87-1973)} -> 9313
B88: =+B87+1 -> 2061 | C88: =+C84+1 -> 2000 | D88: =+D84+1 -> 2000 | E88: {=INDEX(GMW!$A$2:$HN$50,MATCH(1,(GMW!$HM$2:$HM$50=E$3)*(GMW!$HN$2:$HN$50=E$1),0),$B88-1973)} -> 447825 | F88: {=INDEX(GMW!$A$2:$HN$50,MATCH(1,(GMW!$HM$2:$HM$50=F$3)*(GMW!$HN$2:$HN$50=F$1),0),$B88-1973)} -> 27468 | G88: {=INDEX(GMW!$A$2:$HN$50,MATCH(1,(GMW!$HM$2:$HM$50=G$3)*(GMW!$HN$2:$HN$50=G$1),0),$B88-1973)} -> 4701.495 | H88: {=INDEX(GMW!$A$2:$HN$50,MATCH(1,(GMW!$HM$2:$HM$50=H$3)*(GMW!$HN$2:$HN$50=H$1),0),$B88-1973)} -> 5.5 | I88: {=INDEX(GMW!$A$2:$HN$50,MATCH(1,(GMW!$HM$2:$HM$50=I$3)*(GMW!$HN$2:$HN$50=I$1),0),$B88-1973)} -> 277466 | J88: {=INDEX(GMW!$A$2:$HN$50,MATCH(1,(GMW!$HM$2:$HM$50=J$3)*(GMW!$HN$2:$HN$50=J$1),0),$B88-1973)} -> 9861 | K88: {=INDEX(GMW!$A$2:$HN$50,MATCH(1,(GMW!$HM$2:$HM$50=K$3)*(GMW!$HN$2:$HN$50=K$1),0),$B88-1973)} -> 447825 | L88: {=INDEX(GMW!$A$2:$HN$50,MATCH(1,(GMW!$HM$2:$HM$50=L$3)*(GMW!$HN$2:$HN$50=L$1),0),$B88-1973)} -> 27468 | ... P88: {=INDEX(GMW!$A$2:$HN$50,MATCH(1,(GMW!$HM$2:$HM$50=P$3)*(GMW!$HN$2:$HN$50=P$1),0),$B88-1973)} -> 9861
B89: =+B88+1 -> 2062 | C89: =+C85+1 -> 2000 | D89: =+D85+1 -> 2000 | E89: {=INDEX(GMW!$A$2:$HN$50,MATCH(1,(GMW!$HM$2:$HM$50=E$3)*(GMW!$HN$2:$HN$50=E$1),0),$B89-1973)} -> 450688 | F89: {=INDEX(GMW!$A$2:$HN$50,MATCH(1,(GMW!$HM$2:$HM$50=F$3)*(GMW!$HN$2:$HN$50=F$1),0),$B89-1973)} -> 27555 | G89: {=INDEX(GMW!$A$2:$HN$50,MATCH(1,(GMW!$HM$2:$HM$50=G$3)*(GMW!$HN$2:$HN$50=G$1),0),$B89-1973)} -> 4802.455 | H89: {=INDEX(GMW!$A$2:$HN$50,MATCH(1,(GMW!$HM$2:$HM$50=H$3)*(GMW!$HN$2:$HN$50=H$1),0),$B89-1973)} -> 5.3 | I89: {=INDEX(GMW!$A$2:$HN$50,MATCH(1,(GMW!$HM$2:$HM$50=I$3)*(GMW!$HN$2:$HN$50=I$1),0),$B89-1973)} -> 283106 | J89: {=INDEX(GMW!$A$2:$HN$50,MATCH(1,(GMW!$HM$2:$HM$50=J$3)*(GMW!$HN$2:$HN$50=J$1),0),$B89-1973)} -> 9826 | K89: {=INDEX(GMW!$A$2:$HN$50,MATCH(1,(GMW!$HM$2:$HM$50=K$3)*(GMW!$HN$2:$HN$50=K$1),0),$B89-1973)} -> 450688 | L89: {=INDEX(GMW!$A$2:$HN$50,MATCH(1,(GMW!$HM$2:$HM$50=L$3)*(GMW!$HN$2:$HN$50=L$1),0),$B89-1973)} -> 27555 | ... P89: {=INDEX(GMW!$A$2:$HN$50,MATCH(1,(GMW!$HM$2:$HM$50=P$3)*(GMW!$HN$2:$HN$50=P$1),0),$B89-1973)} -> 9826
B90: =+B89+1 -> 2063 | C90: =+C86+1 -> 2000 | D90: =+D86+1 -> 2000 | E90: {=INDEX(GMW!$A$2:$HN$50,MATCH(1,(GMW!$HM$2:$HM$50=E$3)*(GMW!$HN$2:$HN$50=E$1),0),$B90-1973)} -> 453447 | F90: {=INDEX(GMW!$A$2:$HN$50,MATCH(1,(GMW!$HM$2:$HM$50=F$3)*(GMW!$HN$2:$HN$50=F$1),0),$B90-1973)} -> 27549 | G90: {=INDEX(GMW!$A$2:$HN$50,MATCH(1,(GMW!$HM$2:$HM$50=G$3)*(GMW!$HN$2:$HN$50=G$1),0),$B90-1973)} -> 4890.775 | H90: {=INDEX(GMW!$A$2:$HN$50,MATCH(1,(GMW!$HM$2:$HM$50=H$3)*(GMW!$HN$2:$HN$50=H$1),0),$B90-1973)} -> 5.2 | I90: {=INDEX(GMW!$A$2:$HN$50,MATCH(1,(GMW!$HM$2:$HM$50=I$3)*(GMW!$HN$2:$HN$50=I$1),0),$B90-1973)} -> 287523 | J90: {=INDEX(GMW!$A$2:$HN$50,MATCH(1,(GMW!$HM$2:$HM$50=J$3)*(GMW!$HN$2:$HN$50=J$1),0),$B90-1973)} -> 10195 | K90: {=INDEX(GMW!$A$2:$HN$50,MATCH(1,(GMW!$HM$2:$HM$50=K$3)*(GMW!$HN$2:$HN$50=K$1),0),$B90-1973)} -> 453447 | L90: {=INDEX(GMW!$A$2:$HN$50,MATCH(1,(GMW!$HM$2:$HM$50=L$3)*(GMW!$HN$2:$HN$50=L$1),0),$B90-1973)} -> 27549 | ... P90: {=INDEX(GMW!$A$2:$HN$50,MATCH(1,(GMW!$HM$2:$HM$50=P$3)*(GMW!$HN$2:$HN$50=P$1),0),$B90-1973)} -> 10195
A91: 2001 | B91: =+B90+1 -> 2064 | C91: =+C87+1 -> 2001 | D91: =+D87+1 -> 2000 | E91: {=INDEX(GMW!$A$2:$HN$50,MATCH(1,(GMW!$HM$2:$HM$50=E$3)*(GMW!$HN$2:$HN$50=E$1),0),$B91-1973)} -> 457680 | F91: {=INDEX(GMW!$A$2:$HN$50,MATCH(1,(GMW!$HM$2:$HM$50=F$3)*(GMW!$HN$2:$HN$50=F$1),0),$B91-1973)} -> 27623 | G91: {=INDEX(GMW!$A$2:$HN$50,MATCH(1,(GMW!$HM$2:$HM$50=G$3)*(GMW!$HN$2:$HN$50=G$1),0),$B91-1973)} -> 5001.369 | H91: {=INDEX(GMW!$A$2:$HN$50,MATCH(1,(GMW!$HM$2:$HM$50=H$3)*(GMW!$HN$2:$HN$50=H$1),0),$B91-1973)} -> 5.1 | I91: {=INDEX(GMW!$A$2:$HN$50,MATCH(1,(GMW!$HM$2:$HM$50=I$3)*(GMW!$HN$2:$HN$50=I$1),0),$B91-1973)} -> 289476 | J91: {=INDEX(GMW!$A$2:$HN$50,MATCH(1,(GMW!$HM$2:$HM$50=J$3)*(GMW!$HN$2:$HN$50=J$1),0),$B91-1973)} -> 10811 | K91: {=INDEX(GMW!$A$2:$HN$50,MATCH(1,(GMW!$HM$2:$HM$50=K$3)*(GMW!$HN$2:$HN$50=K$1),0),$B91-1973)} -> 457680 | L91: {=INDEX(GMW!$A$2:$HN$50,MATCH(1,(GMW!$HM$2:$HM$50=L$3)*(GMW!$HN$2:$HN$50=L$1),0),$B91-1973)} -> 27623 | ... P91: {=INDEX(GMW!$A$2:$HN$50,MATCH(1,(GMW!$HM$2:$HM$50=P$3)*(GMW!$HN$2:$HN$50=P$1),0),$B91-1973)} -> 10811
B92: =+B91+1 -> 2065 | C92: =+C88+1 -> 2001 | D92: =+D88+1 -> 2001 | E92: {=INDEX(GMW!$A$2:$HN$50,MATCH(1,(GMW!$HM$2:$HM$50=E$3)*(GMW!$HN$2:$HN$50=E$1),0),$B92-1973)} -> 459620 | F92: {=INDEX(GMW!$A$2:$HN$50,MATCH(1,(GMW!$HM$2:$HM$50=F$3)*(GMW!$HN$2:$HN$50=F$1),0),$B92-1973)} -> 27707 | G92: {=INDEX(GMW!$A$2:$HN$50,MATCH(1,(GMW!$HM$2:$HM$50=G$3)*(GMW!$HN$2:$HN$50=G$1),0),$B92-1973)} -> 5002.77 | H92: {=INDEX(GMW!$A$2:$HN$50,MATCH(1,(GMW!$HM$2:$HM$50=H$3)*(GMW!$HN$2:$HN$50=H$1),0),$B92-1973)} -> 5 | I92: {=INDEX(GMW!$A$2:$HN$50,MATCH(1,(GMW!$HM$2:$HM$50=I$3)*(GMW!$HN$2:$HN$50=I$1),0),$B92-1973)} -> 288052 | J92: {=INDEX(GMW!$A$2:$HN$50,MATCH(1,(GMW!$HM$2:$HM$50=J$3)*(GMW!$HN$2:$HN$50=J$1),0),$B92-1973)} -> 9870 | K92: {=INDEX(GMW!$A$2:$HN$50,MATCH(1,(GMW!$HM$2:$HM$50=K$3)*(GMW!$HN$2:$HN$50=K$1),0),$B92-1973)} -> 459620 | L92: {=INDEX(GMW!$A$2:$HN$50,MATCH(1,(GMW!$HM$2:$HM$50=L$3)*(GMW!$HN$2:$HN$50=L$1),0),$B92-1973)} -> 27707 | ... P92: {=INDEX(GMW!$A$2:$HN$50,MATCH(1,(GMW!$HM$2:$HM$50=P$3)*(GMW!$HN$2:$HN$50=P$1),0),$B92-1973)} -> 9870
B93: =+B92+1 -> 2066 | C93: =+C89+1 -> 2001 | D93: =+D89+1 -> 2001 | E93: {=INDEX(GMW!$A$2:$HN$50,MATCH(1,(GMW!$HM$2:$HM$50=E$3)*(GMW!$HN$2:$HN$50=E$1),0),$B93-1973)} -> 462016 | F93: {=INDEX(GMW!$A$2:$HN$50,MATCH(1,(GMW!$HM$2:$HM$50=F$3)*(GMW!$HN$2:$HN$50=F$1),0),$B93-1973)} -> 27715 | G93: {=INDEX(GMW!$A$2:$HN$50,MATCH(1,(GMW!$HM$2:$HM$50=G$3)*(GMW!$HN$2:$HN$50=G$1),0),$B93-1973)} -> 5029.651 | H93: {=INDEX(GMW!$A$2:$HN$50,MATCH(1,(GMW!$HM$2:$HM$50=H$3)*(GMW!$HN$2:$HN$50=H$1),0),$B93-1973)} -> 5.1 | I93: {=INDEX(GMW!$A$2:$HN$50,MATCH(1,(GMW!$HM$2:$HM$50=I$3)*(GMW!$HN$2:$HN$50=I$1),0),$B93-1973)} -> 289545 | J93: {=INDEX(GMW!$A$2:$HN$50,MATCH(1,(GMW!$HM$2:$HM$50=J$3)*(GMW!$HN$2:$HN$50=J$1),0),$B93-1973)} -> 10189 | K93: {=INDEX(GMW!$A$2:$HN$50,MATCH(1,(GMW!$HM$2:$HM$50=K$3)*(GMW!$HN$2:$HN$50=K$1),0),$B93-1973)} -> 462016 | L93: {=INDEX(GMW!$A$2:$HN$50,MATCH(1,(GMW!$HM$2:$HM$50=L$3)*(GMW!$HN$2:$HN$50=L$1),0),$B93-1973)} -> 27715 | ... P93: {=INDEX(GMW!$A$2:$HN$50,MATCH(1,(GMW!$HM$2:$HM$50=P$3)*(GMW!$HN$2:$HN$50=P$1),0),$B93-1973)} -> 10189
B94: =+B93+1 -> 2067 | C94: =+C90+1 -> 2001 | D94: =+D90+1 -> 2001 | E94: {=INDEX(GMW!$A$2:$HN$50,MATCH(1,(GMW!$HM$2:$HM$50=E$3)*(GMW!$HN$2:$HN$50=E$1),0),$B94-1973)} -> 463404 | F94: {=INDEX(GMW!$A$2:$HN$50,MATCH(1,(GMW!$HM$2:$HM$50=F$3)*(GMW!$HN$2:$HN$50=F$1),0),$B94-1973)} -> 27803 | G94: {=INDEX(GMW!$A$2:$HN$50,MATCH(1,(GMW!$HM$2:$HM$50=G$3)*(GMW!$HN$2:$HN$50=G$1),0),$B94-1973)} -> 5057.922 | H94: {=INDEX(GMW!$A$2:$HN$50,MATCH(1,(GMW!$HM$2:$HM$50=H$3)*(GMW!$HN$2:$HN$50=H$1),0),$B94-1973)} -> 5.2 | I94: {=INDEX(GMW!$A$2:$HN$50,MATCH(1,(GMW!$HM$2:$HM$50=I$3)*(GMW!$HN$2:$HN$50=I$1),0),$B94-1973)} -> 295002 | J94: {=INDEX(GMW!$A$2:$HN$50,MATCH(1,(GMW!$HM$2:$HM$50=J$3)*(GMW!$HN$2:$HN$50=J$1),0),$B94-1973)} -> 10298 | K94: {=INDEX(GMW!$A$2:$HN$50,MATCH(1,(GMW!$HM$2:$HM$50=K$3)*(GMW!$HN$2:$HN$50=K$1),0),$B94-1973)} -> 463404 | L94: {=INDEX(GMW!$A$2:$HN$50,MATCH(1,(GMW!$HM$2:$HM$50=L$3)*(GMW!$HN$2:$HN$50=L$1),0),$B94-1973)} -> 27803 | ... P94: {=INDEX(GMW!$A$2:$HN$50,MATCH(1,(GMW!$HM$2:$HM$50=P$3)*(GMW!$HN$2:$HN$50=P$1),0),$B94-1973)} -> 10298
A95: 2002 | B95: =+B94+1 -> 2068 | C95: =+C91+1 -> 2002 | D95: =+D91+1 -> 2001 | E95: {=INDEX(GMW!$A$2:$HN$50,MATCH(1,(GMW!$HM$2:$HM$50=E$3)*(GMW!$HN$2:$HN$50=E$1),0),$B95-1973)} -> 464698 | F95: {=INDEX(GMW!$A$2:$HN$50,MATCH(1,(GMW!$HM$2:$HM$50=F$3)*(GMW!$HN$2:$HN$50=F$1),0),$B95-1973)} -> 27797 | G95: {=INDEX(GMW!$A$2:$HN$50,MATCH(1,(GMW!$HM$2:$HM$50=G$3)*(GMW!$HN$2:$HN$50=G$1),0),$B95-1973)} -> 5089.49 | H95: {=INDEX(GMW!$A$2:$HN$50,MATCH(1,(GMW!$HM$2:$HM$50=H$3)*(GMW!$HN$2:$HN$50=H$1),0),$B95-1973)} -> 5.2 | I95: {=INDEX(GMW!$A$2:$HN$50,MATCH(1,(GMW!$HM$2:$HM$50=I$3)*(GMW!$HN$2:$HN$50=I$1),0),$B95-1973)} -> 295976 | J95: {=INDEX(GMW!$A$2:$HN$50,MATCH(1,(GMW!$HM$2:$HM$50=J$3)*(GMW!$HN$2:$HN$50=J$1),0),$B95-1973)} -> 10629 | K95: {=INDEX(GMW!$A$2:$HN$50,MATCH(1,(GMW!$HM$2:$HM$50=K$3)*(GMW!$HN$2:$HN$50=K$1),0),$B95-1973)} -> 464698 | L95: {=INDEX(GMW!$A$2:$HN$50,MATCH(1,(GMW!$HM$2:$HM$50=L$3)*(GMW!$HN$2:$HN$50=L$1),0),$B95-1973)} -> 27797 | ... P95: {=INDEX(GMW!$A$2:$HN$50,MATCH(1,(GMW!$HM$2:$HM$50=P$3)*(GMW!$HN$2:$HN$50=P$1),0),$B95-1973)} -> 10629
B96: =+B95+1 -> 2069 | C96: =+C92+1 -> 2002 | D96: =+D92+1 -> 2002 | E96: {=INDEX(GMW!$A$2:$HN$50,MATCH(1,(GMW!$HM$2:$HM$50=E$3)*(GMW!$HN$2:$HN$50=E$1),0),$B96-1973)} -> 466935 | F96: {=INDEX(GMW!$A$2:$HN$50,MATCH(1,(GMW!$HM$2:$HM$50=F$3)*(GMW!$HN$2:$HN$50=F$1),0),$B96-1973)} -> 27933 | G96: {=INDEX(GMW!$A$2:$HN$50,MATCH(1,(GMW!$HM$2:$HM$50=G$3)*(GMW!$HN$2:$HN$50=G$1),0),$B96-1973)} -> 5073.909 | H96: {=INDEX(GMW!$A$2:$HN$50,MATCH(1,(GMW!$HM$2:$HM$50=H$3)*(GMW!$HN$2:$HN$50=H$1),0),$B96-1973)} -> 5.2 | I96: {=INDEX(GMW!$A$2:$HN$50,MATCH(1,(GMW!$HM$2:$HM$50=I$3)*(GMW!$HN$2:$HN$50=I$1),0),$B96-1973)} -> 298538 | J96: {=INDEX(GMW!$A$2:$HN$50,MATCH(1,(GMW!$HM$2:$HM$50=J$3)*(GMW!$HN$2:$HN$50=J$1),0),$B96-1973)} -> 10379 | K96: {=INDEX(GMW!$A$2:$HN$50,MATCH(1,(GMW!$HM$2:$HM$50=K$3)*(GMW!$HN$2:$HN$50=K$1),0),$B96-1973)} -> 466935 | L96: {=INDEX(GMW!$A$2:$HN$50,MATCH(1,(GMW!$HM$2:$HM$50=L$3)*(GMW!$HN$2:$HN$50=L$1),0),$B96-1973)} -> 27933 | ... P96: {=INDEX(GMW!$A$2:$HN$50,MATCH(1,(GMW!$HM$2:$HM$50=P$3)*(GMW!$HN$2:$HN$50=P$1),0),$B96-1973)} -> 10379
B97: =+B96+1 -> 2070 | C97: =+C93+1 -> 2002 | D97: =+D93+1 -> 2002 | E97: {=INDEX(GMW!$A$2:$HN$50,MATCH(1,(GMW!$HM$2:$HM$50=E$3)*(GMW!$HN$2:$HN$50=E$1),0),$B97-1973)} -> 470277 | F97: {=INDEX(GMW!$A$2:$HN$50,MATCH(1,(GMW!$HM$2:$HM$50=F$3)*(GMW!$HN$2:$HN$50=F$1),0),$B97-1973)} -> 27935 | G97: {=INDEX(GMW!$A$2:$HN$50,MATCH(1,(GMW!$HM$2:$HM$50=G$3)*(GMW!$HN$2:$HN$50=G$1),0),$B97-1973)} -> 5126.548 | H97: {=INDEX(GMW!$A$2:$HN$50,MATCH(1,(GMW!$HM$2:$HM$50=H$3)*(GMW!$HN$2:$HN$50=H$1),0),$B97-1973)} -> 5.3 | I97: {=INDEX(GMW!$A$2:$HN$50,MATCH(1,(GMW!$HM$2:$HM$50=I$3)*(GMW!$HN$2:$HN$50=I$1),0),$B97-1973)} -> 297567 | J97: {=INDEX(GMW!$A$2:$HN$50,MATCH(1,(GMW!$HM$2:$HM$50=J$3)*(GMW!$HN$2:$HN$50=J$1),0),$B97-1973)} -> 10146 | K97: {=INDEX(GMW!$A$2:$HN$50,MATCH(1,(GMW!$HM$2:$HM$50=K$3)*(GMW!$HN$2:$HN$50=K$1),0),$B97-1973)} -> 470277 | L97: {=INDEX(GMW!$A$2:$HN$50,MATCH(1,(GMW!$HM$2:$HM$50=L$3)*(GMW!$HN$2:$HN$50=L$1),0),$B97-1973)} -> 27935 | ... P97: {=INDEX(GMW!$A$2:$HN$50,MATCH(1,(GMW!$HM$2:$HM$50=P$3)*(GMW!$HN$2:$HN$50=P$1),0),$B97-1973)} -> 10146
B98: =+B97+1 -> 2071 | C98: =+C94+1 -> 2002 | D98: =+D94+1 -> 2002 | E98: {=INDEX(GMW!$A$2:$HN$50,MATCH(1,(GMW!$HM$2:$HM$50=E$3)*(GMW!$HN$2:$HN$50=E$1),0),$B98-1973)} -> 473899 | F98: {=INDEX(GMW!$A$2:$HN$50,MATCH(1,(GMW!$HM$2:$HM$50=F$3)*(GMW!$HN$2:$HN$50=F$1),0),$B98-1973)} -> 28110 | G98: {=INDEX(GMW!$A$2:$HN$50,MATCH(1,(GMW!$HM$2:$HM$50=G$3)*(GMW!$HN$2:$HN$50=G$1),0),$B98-1973)} -> 5142.66 | H98: {=INDEX(GMW!$A$2:$HN$50,MATCH(1,(GMW!$HM$2:$HM$50=H$3)*(GMW!$HN$2:$HN$50=H$1),0),$B98-1973)} -> 5.1 | I98: {=INDEX(GMW!$A$2:$HN$50,MATCH(1,(GMW!$HM$2:$HM$50=I$3)*(GMW!$HN$2:$HN$50=I$1),0),$B98-1973)} -> 298904 | J98: {=INDEX(GMW!$A$2:$HN$50,MATCH(1,(GMW!$HM$2:$HM$50=J$3)*(GMW!$HN$2:$HN$50=J$1),0),$B98-1973)} -> 10703 | K98: {=INDEX(GMW!$A$2:$HN$50,MATCH(1,(GMW!$HM$2:$HM$50=K$3)*(GMW!$HN$2:$HN$50=K$1),0),$B98-1973)} -> 473899 | L98: {=INDEX(GMW!$A$2:$HN$50,MATCH(1,(GMW!$HM$2:$HM$50=L$3)*(GMW!$HN$2:$HN$50=L$1),0),$B98-1973)} -> 28110 | ... P98: {=INDEX(GMW!$A$2:$HN$50,MATCH(1,(GMW!$HM$2:$HM$50=P$3)*(GMW!$HN$2:$HN$50=P$1),0),$B98-1973)} -> 10703
A99: 2003 | B99: =+B98+1 -> 2072 | C99: =+C95+1 -> 2003 | D99: =+D95+1 -> 2002 | E99: {=INDEX(GMW!$A$2:$HN$50,MATCH(1,(GMW!$HM$2:$HM$50=E$3)*(GMW!$HN$2:$HN$50=E$1),0),$B99-1973)} -> 477357 | F99: {=INDEX(GMW!$A$2:$HN$50,MATCH(1,(GMW!$HM$2:$HM$50=F$3)*(GMW!$HN$2:$HN$50=F$1),0),$B99-1973)} -> 28099 | G99: {=INDEX(GMW!$A$2:$HN$50,MATCH(1,(GMW!$HM$2:$HM$50=G$3)*(GMW!$HN$2:$HN$50=G$1),0),$B99-1973)} -> 5215.105 | H99: {=INDEX(GMW!$A$2:$HN$50,MATCH(1,(GMW!$HM$2:$HM$50=H$3)*(GMW!$HN$2:$HN$50=H$1),0),$B99-1973)} -> 5.2 | I99: {=INDEX(GMW!$A$2:$HN$50,MATCH(1,(GMW!$HM$2:$HM$50=I$3)*(GMW!$HN$2:$HN$50=I$1),0),$B99-1973)} -> 301081 | J99: {=INDEX(GMW!$A$2:$HN$50,MATCH(1,(GMW!$HM$2:$HM$50=J$3)*(GMW!$HN$2:$HN$50=J$1),0),$B99-1973)} -> 10366 | K99: {=INDEX(GMW!$A$2:$HN$50,MATCH(1,(GMW!$HM$2:$HM$50=K$3)*(GMW!$HN$2:$HN$50=K$1),0),$B99-1973)} -> 477357 | L99: {=INDEX(GMW!$A$2:$HN$50,MATCH(1,(GMW!$HM$2:$HM$50=L$3)*(GMW!$HN$2:$HN$50=L$1),0),$B99-1973)} -> 28099 | ... P99: {=INDEX(GMW!$A$2:$HN$50,MATCH(1,(GMW!$HM$2:$HM$50=P$3)*(GMW!$HN$2:$HN$50=P$1),0),$B99-1973)} -> 10366
B100: =+B99+1 -> 2073 | C100: =+C96+1 -> 2003 | D100: =+D96+1 -> 2003 | E100: {=INDEX(GMW!$A$2:$HN$50,MATCH(1,(GMW!$HM$2:$HM$50=E$3)*(GMW!$HN$2:$HN$50=E$1),0),$B100-1973)} -> 481552 | F100: {=INDEX(GMW!$A$2:$HN$50,MATCH(1,(GMW!$HM$2:$HM$50=F$3)*(GMW!$HN$2:$HN$50=F$1),0),$B100-1973)} -> 28226 | G100: {=INDEX(GMW!$A$2:$HN$50,MATCH(1,(GMW!$HM$2:$HM$50=G$3)*(GMW!$HN$2:$HN$50=G$1),0),$B100-1973)} -> 5274.743 | H100: {=INDEX(GMW!$A$2:$HN$50,MATCH(1,(GMW!$HM$2:$HM$50=H$3)*(GMW!$HN$2:$HN$50=H$1),0),$B100-1973)} -> 4.9 | I100: {=INDEX(GMW!$A$2:$HN$50,MATCH(1,(GMW!$HM$2:$HM$50=I$3)*(GMW!$HN$2:$HN$50=I$1),0),$B100-1973)} -> 302934 | J100: {=INDEX(GMW!$A$2:$HN$50,MATCH(1,(GMW!$HM$2:$HM$50=J$3)*(GMW!$HN$2:$HN$50=J$1),0),$B100-1973)} -> 11989 | K100: {=INDEX(GMW!$A$2:$HN$50,MATCH(1,(GMW!$HM$2:$HM$50=K$3)*(GMW!$HN$2:$HN$50=K$1),0),$B100-1973)} -> 481552 | L100: {=INDEX(GMW!$A$2:$HN$50,MATCH(1,(GMW!$HM$2:$HM$50=L$3)*(GMW!$HN$2:$HN$50=L$1),0),$B100-1973)} -> 28226 | ... P100: {=INDEX(GMW!$A$2:$HN$50,MATCH(1,(GMW!$HM$2:$HM$50=P$3)*(GMW!$HN$2:$HN$50=P$1),0),$B100-1973)} -> 11989
...

Sheet DataFY
B1: =DataQ!E1 -> Oct24_2.db | C1: =DataQ!F1 -> Oct24_2.db | D1: =DataQ!G1 -> Oct24_2.db | E1: =DataQ!H1 -> Oct24_2.db | F1: =DataQ!I1 -> Oct24_2.db | G1: =DataQ!J1 -> Oct24_2.db | H1: =DataQ!K1 -> NICs_scen.db | I1: =DataQ!L1 -> NICs_scen.db | ... M1: =DataQ!P1 -> NICs_scen.db
B2: =DataQ!E2 -> UK | C2: =DataQ!F2 -> UK | D2: =DataQ!G2 -> UK | E2: =DataQ!H2 -> UK | F2: =DataQ!I2 -> UK | G2: =DataQ!J2 -> UK | H2: =DataQ!K2 -> UK | I2: =DataQ!L2 -> UK | ... M2: =DataQ!P2 -> UK
B3: =DataQ!E3 -> GDP | C3: =DataQ!F3 -> ETILO | D3: =DataQ!G3 -> ER | E3: =DataQ!H3 -> UPILO | F3: =DataQ!I3 -> PEDY | G3: =DataQ!J3 -> TP | H3: =DataQ!K3 -> GDP | I3: =DataQ!L3 -> ETILO | ... M3: =DataQ!P3 -> TP
B4: =DataQ!E4 -> GBR | C4: =DataQ!F4 -> GBR | D4: =DataQ!G4 -> GBR | E4: =DataQ!H4 -> GBR | F4: =DataQ!I4 -> GBR | G4: =DataQ!J4 -> GBR | H4: =DataQ!K4 -> GBR | I4: =DataQ!L4 -> GBR | ... M4: =DataQ!P4 -> GBR
B5: =DataQ!E5 -> L | C5: =DataQ!F5 -> L | D5: =DataQ!G5 -> L | E5: =DataQ!H5 -> L | F5: =DataQ!I5 -> L | G5: =DataQ!J5 -> L | H5: =DataQ!K5 -> L | I5: =DataQ!L5 -> L | ... M5: =DataQ!P5 -> L
B6: =DataQ!E6 -> 202402 | C6: =DataQ!F6 -> 202402 | D6: =DataQ!G6 -> 202402 | E6: =DataQ!H6 -> 202402 | F6: =DataQ!I6 -> 202402 | G6: =DataQ!J6 -> 202402 | H6: =DataQ!K6 -> 202402 | I6: =DataQ!L6 -> 202402 | ... M6: =DataQ!P6 -> 202402
A7: 1980 | B7: =SUMIF(DataQ!$D:$D,DataFY!$A7,DataQ!E:E) -> 1051015 | C7: =AVERAGEIF(DataQ!$D:$D,DataFY!$A7,DataQ!F:F) -> 24939 | D7: =SUMIF(DataQ!$D:$D,DataFY!$A7,DataQ!G:G) -> 5563.368 | E7: =AVERAGEIF(DataQ!$D:$D,DataFY!$A7,DataQ!H:H) -> 7.575 | F7: =SUMIF(DataQ!$D:$D,DataFY!$A7,DataQ!I:I) -> 637945 | G7: =SUMIF(DataQ!$D:$D,DataFY!$A7,DataQ!J:J) -> 9525.192 | H7: =SUMIF(DataQ!$D:$D,DataFY!$A7,DataQ!K:K) -> 1051015 | I7: =AVERAGEIF(DataQ!$D:$D,DataFY!$A7,DataQ!L:L) -> 24939 | J7: =SUMIF(DataQ!$D:$D,DataFY!$A7,DataQ!M:M) -> 5563.368 | K7: =AVERAGEIF(DataQ!$D:$D,DataFY!$A7,DataQ!N:N) -> 7.575 | L7: =SUMIF(DataQ!$D:$D,DataFY!$A7,DataQ!O:O) -> 637945 | M7: =SUMIF(DataQ!$D:$D,DataFY!$A7,DataQ!P:P) -> 9525.192
A8: =+A7+1 -> 1981 | B8: =SUMIF(DataQ!$D:$D,DataFY!$A8,DataQ!E:E) -> 1056651 | C8: =AVERAGEIF(DataQ!$D:$D,DataFY!$A8,DataQ!F:F) -> 24294.75 | D8: =SUMIF(DataQ!$D:$D,DataFY!$A8,DataQ!G:G) -> 6149.857 | E8: =AVERAGEIF(DataQ!$D:$D,DataFY!$A8,DataQ!H:H) -> 10.025 | F8: =SUMIF(DataQ!$D:$D,DataFY!$A8,DataQ!I:I) -> 632023 | G8: =SUMIF(DataQ!$D:$D,DataFY!$A8,DataQ!J:J) -> 10077.231 | H8: =SUMIF(DataQ!$D:$D,DataFY!$A8,DataQ!K:K) -> 1056651 | I8: =AVERAGEIF(DataQ!$D:$D,DataFY!$A8,DataQ!L:L) -> 24294.75 | J8: =SUMIF(DataQ!$D:$D,DataFY!$A8,DataQ!M:M) -> 6149.857 | K8: =AVERAGEIF(DataQ!$D:$D,DataFY!$A8,DataQ!N:N) -> 10.025 | L8: =SUMIF(DataQ!$D:$D,DataFY!$A8,DataQ!O:O) -> 632023 | M8: =SUMIF(DataQ!$D:$D,DataFY!$A8,DataQ!P:P) -> 10077.231
A9: =+A8+1 -> 1982 | B9: =SUMIF(DataQ!$D:$D,DataFY!$A9,DataQ!E:E) -> 1083524 | C9: =AVERAGEIF(DataQ!$D:$D,DataFY!$A9,DataQ!F:F) -> 23833.5 | D9: =SUMIF(DataQ!$D:$D,DataFY!$A9,DataQ!G:G) -> 6680.866 | E9: =AVERAGEIF(DataQ!$D:$D,DataFY!$A9,DataQ!H:H) -> 10.95 | F9: =SUMIF(DataQ!$D:$D,DataFY!$A9,DataQ!I:I) -> 638590 | G9: =SUMIF(DataQ!$D:$D,DataFY!$A9,DataQ!J:J) -> 10712.468 | H9: =SUMIF(DataQ!$D:$D,DataFY!$A9,DataQ!K:K) -> 1083524 | I9: =AVERAGEIF(DataQ!$D:$D,DataFY!$A9,DataQ!L:L) -> 23833.5 | J9: =SUMIF(DataQ!$D:$D,DataFY!$A9,DataQ!M:M) -> 6680.866 | K9: =AVERAGEIF(DataQ!$D:$D,DataFY!$A9,DataQ!N:N) -> 10.95 | L9: =SUMIF(DataQ!$D:$D,DataFY!$A9,DataQ!O:O) -> 638590 | M9: =SUMIF(DataQ!$D:$D,DataFY!$A9,DataQ!P:P) -> 10712.468
A10: =+A9+1 -> 1983 | B10: =SUMIF(DataQ!$D:$D,DataFY!$A10,DataQ!E:E) -> 1127351 | C10: =AVERAGEIF(DataQ!$D:$D,DataFY!$A10,DataQ!F:F) -> 23893.75 | D10: =SUMIF(DataQ!$D:$D,DataFY!$A10,DataQ!G:G) -> 7172.917 | E10: =AVERAGEIF(DataQ!$D:$D,DataFY!$A10,DataQ!H:H) -> 11.6 | F10: =SUMIF(DataQ!$D:$D,DataFY!$A10,DataQ!I:I) -> 659923 | G10: =SUMIF(DataQ!$D:$D,DataFY!$A10,DataQ!J:J) -> 12061.645 | H10: =SUMIF(DataQ!$D:$D,DataFY!$A10,DataQ!K:K) -> 1127351 | I10: =AVERAGEIF(DataQ!$D:$D,DataFY!$A10,DataQ!L:L) -> 23893.75 | J10: =SUMIF(DataQ!$D:$D,DataFY!$A10,DataQ!M:M) -> 7172.917 | K10: =AVERAGEIF(DataQ!$D:$D,DataFY!$A10,DataQ!N:N) -> 11.6 | L10: =SUMIF(DataQ!$D:$D,DataFY!$A10,DataQ!O:O) -> 659923 | M10: =SUMIF(DataQ!$D:$D,DataFY!$A10,DataQ!P:P) -> 12061.645
A11: =+A10+1 -> 1984 | B11: =SUMIF(DataQ!$D:$D,DataFY!$A11,DataQ!E:E) -> 1149722 | C11: =AVERAGEIF(DataQ!$D:$D,DataFY!$A11,DataQ!F:F) -> 24382.5 | D11: =SUMIF(DataQ!$D:$D,DataFY!$A11,DataQ!G:G) -> 7668.995 | E11: =AVERAGEIF(DataQ!$D:$D,DataFY!$A11,DataQ!H:H) -> 11.675 | F11: =SUMIF(DataQ!$D:$D,DataFY!$A11,DataQ!I:I) -> 683616 | G11: =SUMIF(DataQ!$D:$D,DataFY!$A11,DataQ!J:J) -> 12940.86 | H11: =SUMIF(DataQ!$D:$D,DataFY!$A11,DataQ!K:K) -> 1149722 | I11: =AVERAGEIF(DataQ!$D:$D,DataFY!$A11,DataQ!L:L) -> 24382.5 | J11: =SUMIF(DataQ!$D:$D,DataFY!$A11,DataQ!M:M) -> 7668.995 | K11: =AVERAGEIF(DataQ!$D:$D,DataFY!$A11,DataQ!N:N) -> 11.675 | L11: =SUMIF(DataQ!$D:$D,DataFY!$A11,DataQ!O:O) -> 683616 | M11: =SUMIF(DataQ!$D:$D,DataFY!$A11,DataQ!P:P) -> 12940.86
A12: =+A11+1 -> 1985 | B12: =SUMIF(DataQ!$D:$D,DataFY!$A12,DataQ!E:E) -> 1198783 | C12: =AVERAGEIF(DataQ!$D:$D,DataFY!$A12,DataQ!F:F) -> 24631.25 | D12: =SUMIF(DataQ!$D:$D,DataFY!$A12,DataQ!G:G) -> 8295.111 | E12: =AVERAGEIF(DataQ!$D:$D,DataFY!$A12,DataQ!H:H) -> 11.325 | F12: =SUMIF(DataQ!$D:$D,DataFY!$A12,DataQ!I:I) -> 708463 | G12: =SUMIF(DataQ!$D:$D,DataFY!$A12,DataQ!J:J) -> 14044.936 | H12: =SUMIF(DataQ!$D:$D,DataFY!$A12,DataQ!K:K) -> 1198783 | I12: =AVERAGEIF(DataQ!$D:$D,DataFY!$A12,DataQ!L:L) -> 24631.25 | J12: =SUMIF(DataQ!$D:$D,DataFY!$A12,DataQ!M:M) -> 8295.111 | K12: =AVERAGEIF(DataQ!$D:$D,DataFY!$A12,DataQ!N:N) -> 11.325 | L12: =SUMIF(DataQ!$D:$D,DataFY!$A12,DataQ!O:O) -> 708463 | M12: =SUMIF(DataQ!$D:$D,DataFY!$A12,DataQ!P:P) -> 14044.936
A13: =+A12+1 -> 1986 | B13: =SUMIF(DataQ!$D:$D,DataFY!$A13,DataQ!E:E) -> 1238924 | C13: =AVERAGEIF(DataQ!$D:$D,DataFY!$A13,DataQ!F:F) -> 24810 | D13: =SUMIF(DataQ!$D:$D,DataFY!$A13,DataQ!G:G) -> 8940.386 | E13: =AVERAGEIF(DataQ!$D:$D,DataFY!$A13,DataQ!H:H) -> 11.275 | F13: =SUMIF(DataQ!$D:$D,DataFY!$A13,DataQ!I:I) -> 734069 | G13: =SUMIF(DataQ!$D:$D,DataFY!$A13,DataQ!J:J) -> 15891.061 | H13: =SUMIF(DataQ!$D:$D,DataFY!$A13,DataQ!K:K) -> 1238924 | I13: =AVERAGEIF(DataQ!$D:$D,DataFY!$A13,DataQ!L:L) -> 24810 | J13: =SUMIF(DataQ!$D:$D,DataFY!$A13,DataQ!M:M) -> 8940.386 | K13: =AVERAGEIF(DataQ!$D:$D,DataFY!$A13,DataQ!N:N) -> 11.275 | L13: =SUMIF(DataQ!$D:$D,DataFY!$A13,DataQ!O:O) -> 734069 | M13: =SUMIF(DataQ!$D:$D,DataFY!$A13,DataQ!P:P) -> 15891.061
A14: =+A13+1 -> 1987 | B14: =SUMIF(DataQ!$D:$D,DataFY!$A14,DataQ!E:E) -> 1314341 | C14: =AVERAGEIF(DataQ!$D:$D,DataFY!$A14,DataQ!F:F) -> 25456.25 | D14: =SUMIF(DataQ!$D:$D,DataFY!$A14,DataQ!G:G) -> 9580.657 | E14: =AVERAGEIF(DataQ!$D:$D,DataFY!$A14,DataQ!H:H) -> 9.95 | F14: =SUMIF(DataQ!$D:$D,DataFY!$A14,DataQ!I:I) -> 753140 | G14: =SUMIF(DataQ!$D:$D,DataFY!$A14,DataQ!J:J) -> 18093 | H14: =SUMIF(DataQ!$D:$D,DataFY!$A14,DataQ!K:K) -> 1314341 | I14: =AVERAGEIF(DataQ!$D:$D,DataFY!$A14,DataQ!L:L) -> 25456.25 | J14: =SUMIF(DataQ!$D:$D,DataFY!$A14,DataQ!M:M) -> 9580.657 | K14: =AVERAGEIF(DataQ!$D:$D,DataFY!$A14,DataQ!N:N) -> 9.95 | L14: =SUMIF(DataQ!$D:$D,DataFY!$A14,DataQ!O:O) -> 753140 | M14: =SUMIF(DataQ!$D:$D,DataFY!$A14,DataQ!P:P) -> 18093
A15: =+A14+1 -> 1988 | B15: =SUMIF(DataQ!$D:$D,DataFY!$A15,DataQ!E:E) -> 1372598 | C15: =AVERAGEIF(DataQ!$D:$D,DataFY!$A15,DataQ!F:F) -> 26268.75 | D15: =SUMIF(DataQ!$D:$D,DataFY!$A15,DataQ!G:G) -> 10408.064 | E15: =AVERAGEIF(DataQ!$D:$D,DataFY!$A15,DataQ!H:H) -> 8.175 | F15: =SUMIF(DataQ!$D:$D,DataFY!$A15,DataQ!I:I) -> 792119 | G15: =SUMIF(DataQ!$D:$D,DataFY!$A15,DataQ!J:J) -> 20392 | H15: =SUMIF(DataQ!$D:$D,DataFY!$A15,DataQ!K:K) -> 1372598 | I15: =AVERAGEIF(DataQ!$D:$D,DataFY!$A15,DataQ!L:L) -> 26268.75 | J15: =SUMIF(DataQ!$D:$D,DataFY!$A15,DataQ!M:M) -> 10408.064 | K15: =AVERAGEIF(DataQ!$D:$D,DataFY!$A15,DataQ!N:N) -> 8.175 | L15: =SUMIF(DataQ!$D:$D,DataFY!$A15,DataQ!O:O) -> 792119 | M15: =SUMIF(DataQ!$D:$D,DataFY!$A15,DataQ!P:P) -> 20392
A16: =+A15+1 -> 1989 | B16: =SUMIF(DataQ!$D:$D,DataFY!$A16,DataQ!E:E) -> 1399391 | C16: =AVERAGEIF(DataQ!$D:$D,DataFY!$A16,DataQ!F:F) -> 26826.25 | D16: =SUMIF(DataQ!$D:$D,DataFY!$A16,DataQ!G:G) -> 11447.103 | E16: =AVERAGEIF(DataQ!$D:$D,DataFY!$A16,DataQ!H:H) -> 7.05 | F16: =SUMIF(DataQ!$D:$D,DataFY!$A16,DataQ!I:I) -> 835872 | G16: =SUMIF(DataQ!$D:$D,DataFY!$A16,DataQ!J:J) -> 21855 | H16: =SUMIF(DataQ!$D:$D,DataFY!$A16,DataQ!K:K) -> 1399391 | I16: =AVERAGEIF(DataQ!$D:$D,DataFY!$A16,DataQ!L:L) -> 26826.25 | J16: =SUMIF(DataQ!$D:$D,DataFY!$A16,DataQ!M:M) -> 11447.103 | K16: =AVERAGEIF(DataQ!$D:$D,DataFY!$A16,DataQ!N:N) -> 7.05 | L16: =SUMIF(DataQ!$D:$D,DataFY!$A16,DataQ!O:O) -> 835872 | M16: =SUMIF(DataQ!$D:$D,DataFY!$A16,DataQ!P:P) -> 21855
A17: =+A16+1 -> 1990 | B17: =SUMIF(DataQ!$D:$D,DataFY!$A17,DataQ!E:E) -> 1397741 | C17: =AVERAGEIF(DataQ!$D:$D,DataFY!$A17,DataQ!F:F) -> 26778.75 | D17: =SUMIF(DataQ!$D:$D,DataFY!$A17,DataQ!G:G) -> 12506.221 | E17: =AVERAGEIF(DataQ!$D:$D,DataFY!$A17,DataQ!H:H) -> 7.375 | F17: =SUMIF(DataQ!$D:$D,DataFY!$A17,DataQ!I:I) -> 859802 | G17: =SUMIF(DataQ!$D:$D,DataFY!$A17,DataQ!J:J) -> 23698 | H17: =SUMIF(DataQ!$D:$D,DataFY!$A17,DataQ!K:K) -> 1397741 | I17: =AVERAGEIF(DataQ!$D:$D,DataFY!$A17,DataQ!L:L) -> 26778.75 | J17: =SUMIF(DataQ!$D:$D,DataFY!$A17,DataQ!M:M) -> 12506.221 | K17: =AVERAGEIF(DataQ!$D:$D,DataFY!$A17,DataQ!N:N) -> 7.375 | L17: =SUMIF(DataQ!$D:$D,DataFY!$A17,DataQ!O:O) -> 859802 | M17: =SUMIF(DataQ!$D:$D,DataFY!$A17,DataQ!P:P) -> 23698
A18: =+A17+1 -> 1991 | B18: =SUMIF(DataQ!$D:$D,DataFY!$A18,DataQ!E:E) -> 1382274 | C18: =AVERAGEIF(DataQ!$D:$D,DataFY!$A18,DataQ!F:F) -> 25957.5 | D18: =SUMIF(DataQ!$D:$D,DataFY!$A18,DataQ!G:G) -> 13566.295 | E18: =AVERAGEIF(DataQ!$D:$D,DataFY!$A18,DataQ!H:H) -> 9.275 | F18: =SUMIF(DataQ!$D:$D,DataFY!$A18,DataQ!I:I) -> 876486 | G18: =SUMIF(DataQ!$D:$D,DataFY!$A18,DataQ!J:J) -> 25196 | H18: =SUMIF(DataQ!$D:$D,DataFY!$A18,DataQ!K:K) -> 1382274 | I18: =AVERAGEIF(DataQ!$D:$D,DataFY!$A18,DataQ!L:L) -> 25957.5 | J18: =SUMIF(DataQ!$D:$D,DataFY!$A18,DataQ!M:M) -> 13566.295 | K18: =AVERAGEIF(DataQ!$D:$D,DataFY!$A18,DataQ!N:N) -> 9.275 | L18: =SUMIF(DataQ!$D:$D,DataFY!$A18,DataQ!O:O) -> 876486 | M18: =SUMIF(DataQ!$D:$D,DataFY!$A18,DataQ!P:P) -> 25196
A19: =+A18+1 -> 1992 | B19: =SUMIF(DataQ!$D:$D,DataFY!$A19,DataQ!E:E) -> 1391960 | C19: =AVERAGEIF(DataQ!$D:$D,DataFY!$A19,DataQ!F:F) -> 25433 | D19: =SUMIF(DataQ!$D:$D,DataFY!$A19,DataQ!G:G) -> 14022.143 | E19: =AVERAGEIF(DataQ!$D:$D,DataFY!$A19,DataQ!H:H) -> 10.175 | F19: =SUMIF(DataQ!$D:$D,DataFY!$A19,DataQ!I:I) -> 898988 | G19: =SUMIF(DataQ!$D:$D,DataFY!$A19,DataQ!J:J) -> 25426 | H19: =SUMIF(DataQ!$D:$D,DataFY!$A19,DataQ!K:K) -> 1391960 | I19: =AVERAGEIF(DataQ!$D:$D,DataFY!$A19,DataQ!L:L) -> 25433 | J19: =SUMIF(DataQ!$D:$D,DataFY!$A19,DataQ!M:M) -> 14022.143 | K19: =AVERAGEIF(DataQ!$D:$D,DataFY!$A19,DataQ!N:N) -> 10.175 | L19: =SUMIF(DataQ!$D:$D,DataFY!$A19,DataQ!O:O) -> 898988 | M19: =SUMIF(DataQ!$D:$D,DataFY!$A19,DataQ!P:P) -> 25426
... A57: =+A56+1 -> 2030 | B57: =SUMIF(DataQ!$D:$D,DataFY!$A57,DataQ!E:E) -> 2117903.4 | C57: =AVERAGEIF(DataQ!$D:$D,DataFY!$A57,DataQ!F:F) -> 35373.507 | D57: =SUMIF(DataQ!$D:$D,DataFY!$A57,DataQ!G:G) -> 35787.61 | E57: =AVERAGEIF(DataQ!$D:$D,DataFY!$A57,DataQ!H:H) -> 3.749878 | F57: =SUMIF(DataQ!$D:$D,DataFY!$A57,DataQ!I:I) -> 1401504.5 | G57: =SUMIF(DataQ!$D:$D,DataFY!$A57,DataQ!J:J) -> 144824.53 | H57: =SUMIF(DataQ!$D:$D,DataFY!$A57,DataQ!K:K) -> 2115511.6 | I57: =AVERAGEIF(DataQ!$D:$D,DataFY!$A57,DataQ!L:L) -> 35357.52 | J57: =SUMIF(DataQ!$D:$D,DataFY!$A57,DataQ!M:M) -> 35764.82 | K57: =AVERAGEIF(DataQ!$D:$D,DataFY!$A57,DataQ!N:N) -> 3.7933797 | L57: =SUMIF(DataQ!$D:$D,DataFY!$A57,DataQ!O:O) -> 1396420.7 | M57: =SUMIF(DataQ!$D:$D,DataFY!$A57,DataQ!P:P) -> 164278.62

Sheet DataCY
B1: =DataQ!E1 -> Oct24_2.db | C1: =DataQ!F1 -> Oct24_2.db | D1: =DataQ!G1 -> Oct24_2.db | E1: =DataQ!H1 -> Oct24_2.db | F1: =DataQ!I1 -> Oct24_2.db | G1: =DataQ!J1 -> Oct24_2.db | H1: =DataQ!K1 -> NICs_scen.db | I1: =DataQ!L1 -> NICs_scen.db | ... M1: =DataQ!P1 -> NICs_scen.db
B2: =DataQ!E2 -> UK | C2: =DataQ!F2 -> UK | D2: =DataQ!G2 -> UK | E2: =DataQ!H2 -> UK | F2: =DataQ!I2 -> UK | G2: =DataQ!J2 -> UK | H2: =DataQ!K2 -> UK | I2: =DataQ!L2 -> UK | ... M2: =DataQ!P2 -> UK
B3: =DataQ!E3 -> GDP | C3: =DataQ!F3 -> ETILO | D3: =DataQ!G3 -> ER | E3: =DataQ!H3 -> UPILO | F3: =DataQ!I3 -> PEDY | G3: =DataQ!J3 -> TP | H3: =DataQ!K3 -> GDP | I3: =DataQ!L3 -> ETILO | ... M3: =DataQ!P3 -> TP
B4: =DataQ!E4 -> GBR | C4: =DataQ!F4 -> GBR | D4: =DataQ!G4 -> GBR | E4: =DataQ!H4 -> GBR | F4: =DataQ!I4 -> GBR | G4: =DataQ!J4 -> GBR | H4: =DataQ!K4 -> GBR | I4: =DataQ!L4 -> GBR | ... M4: =DataQ!P4 -> GBR
B5: =DataQ!E5 -> L | C5: =DataQ!F5 -> L | D5: =DataQ!G5 -> L | E5: =DataQ!H5 -> L | F5: =DataQ!I5 -> L | G5: =DataQ!J5 -> L | H5: =DataQ!K5 -> L | I5: =DataQ!L5 -> L | ... M5: =DataQ!P5 -> L
B6: =DataQ!E6 -> 202402 | C6: =DataQ!F6 -> 202402 | D6: =DataQ!G6 -> 202402 | E6: =DataQ!H6 -> 202402 | F6: =DataQ!I6 -> 202402 | G6: =DataQ!J6 -> 202402 | H6: =DataQ!K6 -> 202402 | I6: =DataQ!L6 -> 202402 | ... M6: =DataQ!P6 -> 202402
A7: 1980 | B7: =SUMIF(DataQ!$C:$C,DataCY!$A7,DataQ!E:E) -> 1059660 | C7: =AVERAGEIF(DataQ!$C:$C,DataCY!$A7,DataQ!F:F) -> 25086.25 | D7: =SUMIF(DataQ!$C:$C,DataCY!$A7,DataQ!G:G) -> 5374.278 | E7: =AVERAGEIF(DataQ!$C:$C,DataCY!$A7,DataQ!H:H) -> 6.8 | F7: =SUMIF(DataQ!$C:$C,DataCY!$A7,DataQ!I:I) -> 635239 | G7: =SUMIF(DataQ!$C:$C,DataCY!$A7,DataQ!J:J) -> 9230.621 | H7: =SUMIF(DataQ!$C:$C,DataCY!$A7,DataQ!K:K) -> 1059660 | I7: =AVERAGEIF(DataQ!$C:$C,DataCY!$A7,DataQ!L:L) -> 25086.25 | J7: =SUMIF(DataQ!$C:$C,DataCY!$A7,DataQ!M:M) -> 5374.278 | K7: =AVERAGEIF(DataQ!$C:$C,DataCY!$A7,DataQ!N:N) -> 6.8 | L7: =SUMIF(DataQ!$C:$C,DataCY!$A7,DataQ!O:O) -> 635239 | M7: =SUMIF(DataQ!$C:$C,DataCY!$A7,DataQ!P:P) -> 9230.621
A8: =+A7+1 -> 1981 | B8: =SUMIF(DataQ!$C:$C,DataCY!$A8,DataQ!E:E) -> 1052374 | C8: =AVERAGEIF(DataQ!$C:$C,DataCY!$A8,DataQ!F:F) -> 24430 | D8: =SUMIF(DataQ!$C:$C,DataCY!$A8,DataQ!G:G) -> 6006.884 | E8: =AVERAGEIF(DataQ!$C:$C,DataCY!$A8,DataQ!H:H) -> 9.65 | F8: =SUMIF(DataQ!$C:$C,DataCY!$A8,DataQ!I:I) -> 634794 | G8: =SUMIF(DataQ!$C:$C,DataCY!$A8,DataQ!J:J) -> 9909.708 | H8: =SUMIF(DataQ!$C:$C,DataCY!$A8,DataQ!K:K) -> 1052374 | I8: =AVERAGEIF(DataQ!$C:$C,DataCY!$A8,DataQ!L:L) -> 24430 | J8: =SUMIF(DataQ!$C:$C,DataCY!$A8,DataQ!M:M) -> 6006.884 | K8: =AVERAGEIF(DataQ!$C:$C,DataCY!$A8,DataQ!N:N) -> 9.65 | L8: =SUMIF(DataQ!$C:$C,DataCY!$A8,DataQ!O:O) -> 634794 | M8: =SUMIF(DataQ!$C:$C,DataCY!$A8,DataQ!P:P) -> 9909.708
A9: =+A8+1 -> 1982 | B9: =SUMIF(DataQ!$C:$C,DataCY!$A9,DataQ!E:E) -> 1073055 | C9: =AVERAGEIF(DataQ!$C:$C,DataCY!$A9,DataQ!F:F) -> 23950.75 | D9: =SUMIF(DataQ!$C:$C,DataCY!$A9,DataQ!G:G) -> 6533.587 | E9: =AVERAGEIF(DataQ!$C:$C,DataCY!$A9,DataQ!H:H) -> 10.725 | F9: =SUMIF(DataQ!$C:$C,DataCY!$A9,DataQ!I:I) -> 637451 | G9: =SUMIF(DataQ!$C:$C,DataCY!$A9,DataQ!J:J) -> 10505.595 | H9: =SUMIF(DataQ!$C:$C,DataCY!$A9,DataQ!K:K) -> 1073055 | I9: =AVERAGEIF(DataQ!$C:$C,DataCY!$A9,DataQ!L:L) -> 23950.75 | J9: =SUMIF(DataQ!$C:$C,DataCY!$A9,DataQ!M:M) -> 6533.587 | K9: =AVERAGEIF(DataQ!$C:$C,DataCY!$A9,DataQ!N:N) -> 10.725 | L9: =SUMIF(DataQ!$C:$C,DataCY!$A9,DataQ!O:O) -> 637451 | M9: =SUMIF(DataQ!$C:$C,DataCY!$A9,DataQ!P:P) -> 10505.595
A10: =+A9+1 -> 1983 | B10: =SUMIF(DataQ!$C:$C,DataCY!$A10,DataQ!E:E) -> 1117759 | C10: =AVERAGEIF(DataQ!$C:$C,DataCY!$A10,DataQ!F:F) -> 23775.25 | D10: =SUMIF(DataQ!$C:$C,DataCY!$A10,DataQ!G:G) -> 7075.894 | E10: =AVERAGEIF(DataQ!$C:$C,DataCY!$A10,DataQ!H:H) -> 11.475 | F10: =SUMIF(DataQ!$C:$C,DataCY!$A10,DataQ!I:I) -> 651689 | G10: =SUMIF(DataQ!$C:$C,DataCY!$A10,DataQ!J:J) -> 11845.776 | H10: =SUMIF(DataQ!$C:$C,DataCY!$A10,DataQ!K:K) -> 1117759 | I10: =AVERAGEIF(DataQ!$C:$C,DataCY!$A10,DataQ!L:L) -> 23775.25 | J10: =SUMIF(DataQ!$C:$C,DataCY!$A10,DataQ!M:M) -> 7075.894 | K10: =AVERAGEIF(DataQ!$C:$C,DataCY!$A10,DataQ!N:N) -> 11.475 | L10: =SUMIF(DataQ!$C:$C,DataCY!$A10,DataQ!O:O) -> 651689 | M10: =SUMIF(DataQ!$C:$C,DataCY!$A10,DataQ!P:P) -> 11845.776
A11: =+A10+1 -> 1984 | B11: =SUMIF(DataQ!$C:$C,DataCY!$A11,DataQ!E:E) -> 1142579 | C11: =AVERAGEIF(DataQ!$C:$C,DataCY!$A11,DataQ!F:F) -> 24285 | D11: =SUMIF(DataQ!$C:$C,DataCY!$A11,DataQ!G:G) -> 7505.77 | E11: =AVERAGEIF(DataQ!$C:$C,DataCY!$A11,DataQ!H:H) -> 11.75 | F11: =SUMIF(DataQ!$C:$C,DataCY!$A11,DataQ!I:I) -> 675496 | G11: =SUMIF(DataQ!$C:$C,DataCY!$A11,DataQ!J:J) -> 12669.9 | H11: =SUMIF(DataQ!$C:$C,DataCY!$A11,DataQ!K:K) -> 1142579 | I11: =AVERAGEIF(DataQ!$C:$C,DataCY!$A11,DataQ!L:L) -> 24285 | J11: =SUMIF(DataQ!$C:$C,DataCY!$A11,DataQ!M:M) -> 7505.77 | K11: =AVERAGEIF(DataQ!$C:$C,DataCY!$A11,DataQ!N:N) -> 11.75 | L11: =SUMIF(DataQ!$C:$C,DataCY!$A11,DataQ!O:O) -> 675496 | M11: =SUMIF(DataQ!$C:$C,DataCY!$A11,DataQ!P:P) -> 12669.9
A12: =+A11+1 -> 1985 | B12: =SUMIF(DataQ!$C:$C,DataCY!$A12,DataQ!E:E) -> 1189278 | C12: =AVERAGEIF(DataQ!$C:$C,DataCY!$A12,DataQ!F:F) -> 24592.5 | D12: =SUMIF(DataQ!$C:$C,DataCY!$A12,DataQ!G:G) -> 8148.764 | E12: =AVERAGEIF(DataQ!$C:$C,DataCY!$A12,DataQ!H:H) -> 11.375 | F12: =SUMIF(DataQ!$C:$C,DataCY!$A12,DataQ!I:I) -> 703942 | G12: =SUMIF(DataQ!$C:$C,DataCY!$A12,DataQ!J:J) -> 13767.231 | H12: =SUMIF(DataQ!$C:$C,DataCY!$A12,DataQ!K:K) -> 1189278 | I12: =AVERAGEIF(DataQ!$C:$C,DataCY!$A12,DataQ!L:L) -> 24592.5 | J12: =SUMIF(DataQ!$C:$C,DataCY!$A12,DataQ!M:M) -> 8148.764 | K12: =AVERAGEIF(DataQ!$C:$C,DataCY!$A12,DataQ!N:N) -> 11.375 | L12: =SUMIF(DataQ!$C:$C,DataCY!$A12,DataQ!O:O) -> 703942 | M12: =SUMIF(DataQ!$C:$C,DataCY!$A12,DataQ!P:P) -> 13767.231
A13: =+A12+1 -> 1986 | B13: =SUMIF(DataQ!$C:$C,DataCY!$A13,DataQ!E:E) -> 1226237 | C13: =AVERAGEIF(DataQ!$C:$C,DataCY!$A13,DataQ!F:F) -> 24746.25 | D13: =SUMIF(DataQ!$C:$C,DataCY!$A13,DataQ!G:G) -> 8800.084 | E13: =AVERAGEIF(DataQ!$C:$C,DataCY!$A13,DataQ!H:H) -> 11.325 | F13: =SUMIF(DataQ!$C:$C,DataCY!$A13,DataQ!I:I) -> 732897 | G13: =SUMIF(DataQ!$C:$C,DataCY!$A13,DataQ!J:J) -> 15223.218 | H13: =SUMIF(DataQ!$C:$C,DataCY!$A13,DataQ!K:K) -> 1226237 | I13: =AVERAGEIF(DataQ!$C:$C,DataCY!$A13,DataQ!L:L) -> 24746.25 | J13: =SUMIF(DataQ!$C:$C,DataCY!$A13,DataQ!M:M) -> 8800.084 | K13: =AVERAGEIF(DataQ!$C:$C,DataCY!$A13,DataQ!N:N) -> 11.325 | L13: =SUMIF(DataQ!$C:$C,DataCY!$A13,DataQ!O:O) -> 732897 | M13: =SUMIF(DataQ!$C:$C,DataCY!$A13,DataQ!P:P) -> 15223.218
A14: =+A13+1 -> 1987 | B14: =SUMIF(DataQ!$C:$C,DataCY!$A14,DataQ!E:E) -> 1292703 | C14: =AVERAGEIF(DataQ!$C:$C,DataCY!$A14,DataQ!F:F) -> 25238.75 | D14: =SUMIF(DataQ!$C:$C,DataCY!$A14,DataQ!G:G) -> 9392.916 | E14: =AVERAGEIF(DataQ!$C:$C,DataCY!$A14,DataQ!H:H) -> 10.425 | F14: =SUMIF(DataQ!$C:$C,DataCY!$A14,DataQ!I:I) -> 742332 | G14: =SUMIF(DataQ!$C:$C,DataCY!$A14,DataQ!J:J) -> 17758 | H14: =SUMIF(DataQ!$C:$C,DataCY!$A14,DataQ!K:K) -> 1292703 | I14: =AVERAGEIF(DataQ!$C:$C,DataCY!$A14,DataQ!L:L) -> 25238.75 | J14: =SUMIF(DataQ!$C:$C,DataCY!$A14,DataQ!M:M) -> 9392.916 | K14: =AVERAGEIF(DataQ!$C:$C,DataCY!$A14,DataQ!N:N) -> 10.425 | L14: =SUMIF(DataQ!$C:$C,DataCY!$A14,DataQ!O:O) -> 742332 | M14: =SUMIF(DataQ!$C:$C,DataCY!$A14,DataQ!P:P) -> 17758
A15: =+A14+1 -> 1988 | B15: =SUMIF(DataQ!$C:$C,DataCY!$A15,DataQ!E:E) -> 1362204 | C15: =AVERAGEIF(DataQ!$C:$C,DataCY!$A15,DataQ!F:F) -> 26070 | D15: =SUMIF(DataQ!$C:$C,DataCY!$A15,DataQ!G:G) -> 10194.206 | E15: =AVERAGEIF(DataQ!$C:$C,DataCY!$A15,DataQ!H:H) -> 8.575 | F15: =SUMIF(DataQ!$C:$C,DataCY!$A15,DataQ!I:I) -> 782563 | G15: =SUMIF(DataQ!$C:$C,DataCY!$A15,DataQ!J:J) -> 19793 | H15: =SUMIF(DataQ!$C:$C,DataCY!$A15,DataQ!K:K) -> 1362204 | I15: =AVERAGEIF(DataQ!$C:$C,DataCY!$A15,DataQ!L:L) -> 26070 | J15: =SUMIF(DataQ!$C:$C,DataCY!$A15,DataQ!M:M) -> 10194.206 | K15: =AVERAGEIF(DataQ!$C:$C,DataCY!$A15,DataQ!N:N) -> 8.575 | L15: =SUMIF(DataQ!$C:$C,DataCY!$A15,DataQ!O:O) -> 782563 | M15: =SUMIF(DataQ!$C:$C,DataCY!$A15,DataQ!P:P) -> 19793
A16: =+A15+1 -> 1989 | B16: =SUMIF(DataQ!$C:$C,DataCY!$A16,DataQ!E:E) -> 1394928 | C16: =AVERAGEIF(DataQ!$C:$C,DataCY!$A16,DataQ!F:F) -> 26748.75 | D16: =SUMIF(DataQ!$C:$C,DataCY!$A16,DataQ!G:G) -> 11152.929 | E16: =AVERAGEIF(DataQ!$C:$C,DataCY!$A16,DataQ!H:H) -> 7.225 | F16: =SUMIF(DataQ!$C:$C,DataCY!$A16,DataQ!I:I) -> 823265 | G16: =SUMIF(DataQ!$C:$C,DataCY!$A16,DataQ!J:J) -> 21500 | H16: =SUMIF(DataQ!$C:$C,DataCY!$A16,DataQ!K:K) -> 1394928 | I16: =AVERAGEIF(DataQ!$C:$C,DataCY!$A16,DataQ!L:L) -> 26748.75 | J16: =SUMIF(DataQ!$C:$C,DataCY!$A16,DataQ!M:M) -> 11152.929 | K16: =AVERAGEIF(DataQ!$C:$C,DataCY!$A16,DataQ!N:N) -> 7.225 | L16: =SUMIF(DataQ!$C:$C,DataCY!$A16,DataQ!O:O) -> 823265 | M16: =SUMIF(DataQ!$C:$C,DataCY!$A16,DataQ!P:P) -> 21500
A17: =+A16+1 -> 1990 | B17: =SUMIF(DataQ!$C:$C,DataCY!$A17,DataQ!E:E) -> 1402748 | C17: =AVERAGEIF(DataQ!$C:$C,DataCY!$A17,DataQ!F:F) -> 26871.25 | D17: =SUMIF(DataQ!$C:$C,DataCY!$A17,DataQ!G:G) -> 12259.893 | E17: =AVERAGEIF(DataQ!$C:$C,DataCY!$A17,DataQ!H:H) -> 7.1 | F17: =SUMIF(DataQ!$C:$C,DataCY!$A17,DataQ!I:I) -> 855546 | G17: =SUMIF(DataQ!$C:$C,DataCY!$A17,DataQ!J:J) -> 23318 | H17: =SUMIF(DataQ!$C:$C,DataCY!$A17,DataQ!K:K) -> 1402748 | I17: =AVERAGEIF(DataQ!$C:$C,DataCY!$A17,DataQ!L:L) -> 26871.25 | J17: =SUMIF(DataQ!$C:$C,DataCY!$A17,DataQ!M:M) -> 12259.893 | K17: =AVERAGEIF(DataQ!$C:$C,DataCY!$A17,DataQ!N:N) -> 7.1 | L17: =SUMIF(DataQ!$C:$C,DataCY!$A17,DataQ!O:O) -> 855546 | M17: =SUMIF(DataQ!$C:$C,DataCY!$A17,DataQ!P:P) -> 23318
A18: =+A17+1 -> 1991 | B18: =SUMIF(DataQ!$C:$C,DataCY!$A18,DataQ!E:E) -> 1383043 | C18: =AVERAGEIF(DataQ!$C:$C,DataCY!$A18,DataQ!F:F) -> 26162.5 | D18: =SUMIF(DataQ!$C:$C,DataCY!$A18,DataQ!G:G) -> 13323.315 | E18: =AVERAGEIF(DataQ!$C:$C,DataCY!$A18,DataQ!H:H) -> 8.85 | F18: =SUMIF(DataQ!$C:$C,DataCY!$A18,DataQ!I:I) -> 873023 | G18: =SUMIF(DataQ!$C:$C,DataCY!$A18,DataQ!J:J) -> 24717 | H18: =SUMIF(DataQ!$C:$C,DataCY!$A18,DataQ!K:K) -> 1383043 | I18: =AVERAGEIF(DataQ!$C:$C,DataCY!$A18,DataQ!L:L) -> 26162.5 | J18: =SUMIF(DataQ!$C:$C,DataCY!$A18,DataQ!M:M) -> 13323.315 | K18: =AVERAGEIF(DataQ!$C:$C,DataCY!$A18,DataQ!N:N) -> 8.85 | L18: =SUMIF(DataQ!$C:$C,DataCY!$A18,DataQ!O:O) -> 873023 | M18: =SUMIF(DataQ!$C:$C,DataCY!$A18,DataQ!P:P) -> 24717
A19: =+A18+1 -> 1992 | B19: =SUMIF(DataQ!$C:$C,DataCY!$A19,DataQ!E:E) -> 1386437 | C19: =AVERAGEIF(DataQ!$C:$C,DataCY!$A19,DataQ!F:F) -> 25540 | D19: =SUMIF(DataQ!$C:$C,DataCY!$A19,DataQ!G:G) -> 13956.876 | E19: =AVERAGEIF(DataQ!$C:$C,DataCY!$A19,DataQ!H:H) -> 9.95 | F19: =SUMIF(DataQ!$C:$C,DataCY!$A19,DataQ!I:I) -> 896571 | G19: =SUMIF(DataQ!$C:$C,DataCY!$A19,DataQ!J:J) -> 25402 | H19: =SUMIF(DataQ!$C:$C,DataCY!$A19,DataQ!K:K) -> 1386437 | I19: =AVERAGEIF(DataQ!$C:$C,DataCY!$A19,DataQ!L:L) -> 25540 | J19: =SUMIF(DataQ!$C:$C,DataCY!$A19,DataQ!M:M) -> 13956.876 | K19: =AVERAGEIF(DataQ!$C:$C,DataCY!$A19,DataQ!N:N) -> 9.95 | L19: =SUMIF(DataQ!$C:$C,DataCY!$A19,DataQ!O:O) -> 896571 | M19: =SUMIF(DataQ!$C:$C,DataCY!$A19,DataQ!P:P) -> 25402
... A57: =+A56+1 -> 2030 | B57: =SUMIF(DataQ!$C:$C,DataCY!$A57,DataQ!E:E) -> 2818253 | C57: =AVERAGEIF(DataQ!$C:$C,DataCY!$A57,DataQ!F:F) -> 35334.71 | D57: =SUMIF(DataQ!$C:$C,DataCY!$A57,DataQ!G:G) -> 47557.09 | E57: =AVERAGEIF(DataQ!$C:$C,DataCY!$A57,DataQ!H:H) -> 3.7498765 | F57: =SUMIF(DataQ!$C:$C,DataCY!$A57,DataQ!I:I) -> 1864950.2 | G57: =SUMIF(DataQ!$C:$C,DataCY!$A57,DataQ!J:J) -> 192243.25 | H57: =SUMIF(DataQ!$C:$C,DataCY!$A57,DataQ!K:K) -> 2814919.7 | I57: =AVERAGEIF(DataQ!$C:$C,DataCY!$A57,DataQ!L:L) -> 35317.572 | J57: =SUMIF(DataQ!$C:$C,DataCY!$A57,DataQ!M:M) -> 47524.58 | K57: =AVERAGEIF(DataQ!$C:$C,DataCY!$A57,DataQ!N:N) -> 3.7965653 | L57: =SUMIF(DataQ!$C:$C,DataCY!$A57,DataQ!O:O) -> 1858103.2 | M57: =SUMIF(DataQ!$C:$C,DataCY!$A57,DataQ!P:P) -> 218049.84

Sheet HAVERA
B1: GI! | C1: GI! | D1: GI! | E1: GI! | F1: GI! | G1: GI! | H1: GI! | I1: GI! | J1: GI! | K1: GI! | L1: GI! | M1: GI! | N1: GI! | O1: GI! | P1: GI! | Q1: GI! | R1: GI! | S1: GI! | T1: GI! | U1: GI! | V1: GI! | W1: GI! | X1: GI! | Y1: GI! | Z1: GI! | AA1: GI! | AB1: GI! | AC1: GI! | AD1: GI! | AE1: GI! | AF1: GI! | AG1: GDP! | AH1: GDP! | AI1: GDP! | AJ1: GDP! | AK1: GDP! | AL1: GDP! | AM1: GDP! | AN1: GDP! | AO1: GDP! | AP1: GDP! | AQ1: GDP! | AR1: GDP! | AS1: GDP! | AT1: GDP! | AU1: GDP! | AV1: GDP! | AW1: GDP! | AX1: GDP! | AY1: GDP! | AZ1: GDP! | BA1: GDP! | BB1: GDP! | BC1: GDP! | BD1: GDP! | BE1: GDP! | BF1: GDP! | BG1: GDP! | BH1: GDP! | BI1: GDP! | BJ1: GDP! | BK1: GDP! | BM1: GI/GDP!
A2: 2000 !Y | B2: L112G201@OECDGOV | C2: L111G201@OECDGOV | D2: L158G201@OECDGOV | E2: L134G201@OECDGOV | F2: L132G201@OECDGOV | G2: L136G201@OECDGOV | H2: L193G101@OECDGOV | I2: L122G201@OECDGOV | J2: L124G201@OECDGOV | K2: L935G201@OECDGOV | L2: L128G201@OECDGOV | M2: L939G201@OECDGOV | N2: L172G201@OECDGOV | O2: L174G201@OECDGOV | P2: L944G201@OECDGOV | Q2: L176G101@OECDGOV | R2: L178G201@OECDGOV | S2: L436G201@OECDGOV | T2: L542G201@OECDGOV | U2: L941G201@OECDGOV | V2: L946G201@OECDGOV | W2: L137G201@OECDGOV | X2: L138G201@OECDGOV | Y2: L142G201@OECDGOV | Z2: L964G201@OECDGOV | AA2: L182G201@OECDGOV | AB2: L936G201@OECDGOV | AC2: L961G201@OECDGOV | AD2: L184G201@OECDGOV | AE2: L144G201@OECDGOV | AF2: L146G201@OECDGOV | AG2: L112T401@OECDGOV | AH2: L111T401@OECDGOV | AI2: L158T401@OECDGOV | AJ2: L134T401@OECDGOV | AK2: L132T401@OECDGOV | AL2: L136T401@OECDGOV | AM2: L193T401@OECDGOV | AN2: L122T401@OECDGOV | AO2: L124T401@OECDGOV | AP2: L935T401@OECDGOV | AQ2: L128T401@OECDGOV | AR2: L939T401@OECDGOV | AS2: L172T401@OECDGOV | AT2: L174T401@OECDGOV | AU2: L944T401@OECDGOV | AV2: L176T401@OECDGOV | AW2: L178T401@OECDGOV | AX2: L436T401@OECDGOV | AY2: L542T401@OECDGOV | AZ2: L941T401@OECDGOV | BA2: L946T401@OECDGOV | BB2: L137T401@OECDGOV | BC2: L138T401@OECDGOV | BD2: L142T401@OECDGOV | BE2: L964T401@OECDGOV | BF2: L182T401@OECDGOV | BG2: L936T401@OECDGOV | BH2: L961T401@OECDGOV | BI2: L184T401@OECDGOV | BJ2: L144T401@OECDGOV | BK2: L146T401@OECDGOV
