Workbook
Name _DLX1.INC: HAVERM!$I$1:$BB$6
Name _DLX2.INC: 'HAVER - UK Electricity'!$B$2:$DB$7
Name _DLX3.INC: 'HAVER - UK Gas'!$B$2:$DB$7
Name _DLX4.INC: HAVERM!$A$1:$F$6
Name _DLX5.INC: 'BoE feb MPR'!$O$1:$U$6
Name Annual_Data: '$template-default'!$A$1:$A$2
Name Annual_Data: GMW!$A$1:$A$2

Sheet Chart data
A1: Food price chart >>> | G1: m/m food seasonality chart >>> | S1: Gas futures prices chart >>> | Y1: =(Z299/Y298)-1 -> -0.16051506 | AE1: OE vs BoE inflation forecast chart >>>
A3: Date | B3: UK food price inflation (LHS) | C3: UK food producer input prices (adv 6 months, LHS) | D3: Global UN food price inflation (adv 6 months, RHS) | E3: Zero line | G3: Date | H3: 2024 | I3: 2023 | J3: 2022 | K3: 2010-2019 average | L3: 2010-2019 min | M3: 2010-2019 max | N3: 2010-2019 range | S3: Date | T3: Month | U3: Pence per therm | V3: Jul-2023 price cap | W3: Oct-2023 price cap | X3: Jan-2024 price cap | Y3: Apr-2024 price cap | Z3: Jul-2024 price cap | AB3: Average of observation window | AC3: Price cap period | AE3: Date | AF3: Oxford Economics - latest | AG3: Bank of England - February projections | AH3: modal fcast | AI3: 2% line | AK3: Date | AL3: Food | AM3: Petrol | AN3: Energy | AO3: Other goods | AP3: Services | AQ3: CPI | AR3: 2% line
A4: 40909 | B4: =HAVERM!K151 -> 3.4920635 | C4: =((HAVERM!M145/HAVERM!M133)-1)*100 -> 11.567568 | D4: =((HAVERM!R144/HAVERM!R132)-1)*100 -> 28.292691 | E4: 0 | G4: Jan | H4: =HAVERM!L295 -> -0.37009623 | I4: =HAVERM!L283 -> 0.55955236 | J4: =HAVERM!L271 -> 0.65359477 | K4: =AVERAGE(H20:Q20) -> -0.13281103 | L4: =MIN(H20:Q20) -> -0.68627451 | M4: =MAX(H20:Q20) -> 0.20429009 | N4: =M4-L4 -> 0.8905646 | S4: 44928 | T4: Jan | U4: =IF('HAVER - UK Gas'!H1574="",C1286,AVERAGE('HAVER - UK Gas'!H1574:Q1574)) -> 204.88 | AE4: 43831 | AF4: ='[1]CPI Forecast'!D294 -> 1.7692706 | AG4: =NA() -> #N/A | AH4: =NA() -> #N/A | AI4: 2 | AK4: 43466 | AL4: =[1]Contributions!C255 -> 0.25967276 | AM4: =[1]Contributions!D255 -> 0.022038567 | AN4: =[1]Contributions!E255 -> 0.049180328 | AO4: =[1]Contributions!H255 -> 0.3144532 | AP4: =[1]Contributions!I255 -> 1.2240339 | AQ4: =[1]Contributions!G255 -> 1.847949 | AR4: 2
A5: 40940 | B5: =HAVERM!K152 -> 3.6649215 | C5: =((HAVERM!M146/HAVERM!M134)-1)*100 -> 9.9465241 | D5: =((HAVERM!R145/HAVERM!R133)-1)*100 -> 26.222165 | E5: 0 | G5: Feb | H5: =HAVERM!L296 -> 0.22288262 | I5: =HAVERM!L284 -> 2.1462639 | J5: =HAVERM!L272 -> 1.0204082 | K5: =AVERAGE(H21:Q21) -> 0.59831851 | L5: =MIN(H21:Q21) -> -0.29615005 | M5: =MAX(H21:Q21) -> 1.2269939 | N5: =M5-L5 -> 1.5231439 | S5: 44929 | T5: Jan | U5: =IF('HAVER - UK Gas'!H1575="",C1287,AVERAGE('HAVER - UK Gas'!H1575:Q1575)) -> 183.035 | AE5: 43862 | AF5: ='[1]CPI Forecast'!D295 -> 1.7095297 | AG5: =NA() -> #N/A | AH5: =NA() -> #N/A | AI5: 2 | AK5: 43497 | AL5: =[1]Contributions!C256 -> 0.32713694 | AM5: =[1]Contributions!D256 -> 0.017187141 | AN5: =[1]Contributions!E256 -> 0.054936997 | AO5: =[1]Contributions!H256 -> 0.35977537 | AP5: =[1]Contributions!I256 -> 1.1728362 | AQ5: =[1]Contributions!G256 -> 1.8692837 | AR5: 2
A6: 40969 | B6: =HAVERM!K153 -> 4.5647558 | C6: =((HAVERM!M147/HAVERM!M135)-1)*100 -> 10.127932 | D6: =((HAVERM!R146/HAVERM!R134)-1)*100 -> 19.42735 | E6: 0 | G6: Mar | H6: =NA() -> #N/A | I6: =HAVERM!L285 -> 1.0894942 | J6: =HAVERM!L273 -> 0.091827365 | K6: =AVERAGE(H22:Q22) -> -0.25212978 | L6: =MIN(H22:Q22) -> -1.3612565 | M6: =MAX(H22:Q22) -> 0.40444894 | N6: =M6-L6 -> 1.7657055 | S6: 44930 | T6: Jan | U6: =IF('HAVER - UK Gas'!H1576="",C1288,AVERAGE('HAVER - UK Gas'!H1576:Q1576)) -> 202.814 | AE6: 43891 | AF6: ='[1]CPI Forecast'!D296 -> 1.5233075 | AG6: =NA() -> #N/A | AH6: =NA() -> #N/A | AI6: 2 | AK6: 43525 | AL6: =[1]Contributions!C257 -> 0.28591248 | AM6: =[1]Contributions!D257 -> 0.087241062 | AN6: =[1]Contributions!E257 -> 0.051600078 | AO6: =[1]Contributions!H257 -> 0.36155217 | AP6: =[1]Contributions!I257 -> 1.1708768 | AQ6: =[1]Contributions!G257 -> 1.9076009 | AR6: 2
A7: 41000 | B7: =HAVERM!K154 -> 4.3478261 | C7: =((HAVERM!M148/HAVERM!M136)-1)*100 -> 8.2809224 | D7: =((HAVERM!R147/HAVERM!R135)-1)*100 -> 12.801946 | E7: 0 | G7: Apr | H7: =NA() -> #N/A | I7: =HAVERM!L286 -> 1.3856813 | J7: =HAVERM!L274 -> 1.559633 | K7: =AVERAGE(H23:Q23) -> -0.02421449 | L7: =MIN(H23:Q23) -> -0.48123195 | M7: =MAX(H23:Q23) -> 0.68493151 | N7: =M7-L7 -> 1.1661635 | S7: 44931 | T7: Jan | U7: =IF('HAVER - UK Gas'!H1577="",C1289,AVERAGE('HAVER - UK Gas'!H1577:Q1577)) -> 197.436 | AE7: 43922 | AF7: ='[1]CPI Forecast'!D297 -> 0.76742263 | AG7: =NA() -> #N/A | AH7: =NA() -> #N/A | AI7: 2 | AK7: 43556 | AL7: =[1]Contributions!C258 -> 0.23115496 | AM7: =[1]Contributions!D258 -> 0.13025484 | AN7: =[1]Contributions!E258 -> 0.32590659 | AO7: =[1]Contributions!H258 -> 0.047641725 | AP7: =[1]Contributions!I258 -> 1.3872623 | AQ7: =[1]Contributions!G258 -> 2.117627 | AR7: 2
A8: 41030 | B8: =HAVERM!K155 -> 3.3507853 | C8: =((HAVERM!M149/HAVERM!M137)-1)*100 -> 8.125 | D8: =((HAVERM!R148/HAVERM!R136)-1)*100 -> 5.3369843 | E8: 0 | G8: May | H8: =NA() -> #N/A | I8: =HAVERM!L287 -> 0.91116173 | J8: =HAVERM!L275 -> 1.535682 | K8: =AVERAGE(H24:Q24) -> -0.01028101 | L8: =MIN(H24:Q24) -> -1.0638298 | M8: =MAX(H24:Q24) -> 1.2725345 | N8: =M8-L8 -> 2.3363643 | S8: 44932 | T8: Jan | U8: =IF('HAVER - UK Gas'!H1578="",C1290,AVERAGE('HAVER - UK Gas'!H1578:Q1578)) -> 205.748 | AE8: 43952 | AF8: ='[1]CPI Forecast'!D298 -> 0.47986067 | AG8: =NA() -> #N/A | AH8: =NA() -> #N/A | AI8: 2 | AK8: 43586 | AL8: =[1]Contributions!C259 -> 0.22997911 | AM8: =[1]Contributions!D259 -> 0.10253856 | AN8: =[1]Contributions!E259 -> 0.32437309 | AO8: =[1]Contributions!H259 -> 0.161432 | AP8: =[1]Contributions!I259 -> 1.203002 | AQ8: =[1]Contributions!G259 -> 2.020603 | AR8: 2
A9: 41061 | B9: =HAVERM!K156 -> 2.1761658 | C9: =((HAVERM!M150/HAVERM!M138)-1)*100 -> 6.4351379 | D9: =((HAVERM!R149/HAVERM!R137)-1)*100 -> 2.6213397 | E9: 0 | G9: Jun | H9: =NA() -> #N/A | I9: =HAVERM!L288 -> 0.37622272 | J9: =HAVERM!L276 -> 1.1565836 | K9: =AVERAGE(H25:Q25) -> -0.065925175 | L9: =MIN(H25:Q25) -> -0.49067713 | M9: =MAX(H25:Q25) -> 1.0471204 | N9: =M9-L9 -> 1.5377976 | S9: =+S4+7 -> 44935 | T9: Jan | U9: =IF('HAVER - UK Gas'!H1579="",C1291,AVERAGE('HAVER - UK Gas'!H1579:Q1579)) -> 196.433 | AE9: 43983 | AF9: ='[1]CPI Forecast'!D299 -> 0.60315196 | AG9: =NA() -> #N/A | AH9: =NA() -> #N/A | AI9: 2 | AK9: 43617 | AL9: =[1]Contributions!C260 -> 0.31087954 | AM9: =[1]Contributions!D260 -> 0.018591026 | AN9: =[1]Contributions!E260 -> 0.24701496 | AO9: =[1]Contributions!H260 -> 0.23588458 | AP9: =[1]Contributions!I260 -> 1.2020789 | AQ9: =[1]Contributions!G260 -> 2.0054626 | AR9: 2
A10: 41091 | B10: =HAVERM!K157 -> 2.1716649 | C10: =((HAVERM!M151/HAVERM!M139)-1)*100 -> 4.7331319 | D10: =((HAVERM!R150/HAVERM!R138)-1)*100 -> -4.2907793 | E10: 0 | G10: Jul | H10: =NA() -> #N/A | I10: =HAVERM!L289 -> 0.074962519 | J10: =HAVERM!L277 -> 2.2867194 | K10: =AVERAGE(H26:Q26) -> 0.069648957 | L10: =MIN(H26:Q26) -> -0.69860279 | M10: =MAX(H26:Q26) -> 0.99778271 | N10: =M10-L10 -> 1.6963855 | S10: =+S5+7 -> 44936 | T10: Jan | U10: =IF('HAVER - UK Gas'!H1580="",C1292,AVERAGE('HAVER - UK Gas'!H1580:Q1580)) -> 187.879 | AE10: 44013 | AF10: ='[1]CPI Forecast'!D300 -> 1.0403061 | AG10: =NA() -> #N/A | AH10: =NA() -> #N/A | AI10: 2 | AK10: 43647 | AL10: =[1]Contributions!C261 -> 0.29741971 | AM10: =[1]Contributions!D261 -> 0.0024687872 | AN10: =[1]Contributions!E261 -> 0.19884962 | AO10: =[1]Contributions!H261 -> 0.38893211 | AP10: =[1]Contributions!I261 -> 1.2007321 | AQ10: =[1]Contributions!G261 -> 2.0610954 | AR10: 2
A11: 41122 | B11: =HAVERM!K158 -> 2.1671827 | C11: =((HAVERM!M152/HAVERM!M140)-1)*100 -> 4.1874377 | D11: =((HAVERM!R151/HAVERM!R139)-1)*100 -> -6.8841632 | E11: 0 | G11: Aug | H11: =NA() -> #N/A | I11: =HAVERM!L290 -> 0.37453184 | J11: =HAVERM!L278 -> 1.4617369 | K11: =AVERAGE(H27:Q27) -> 0.20020714 | L11: =MIN(H27:Q27) -> -0.19569472 | M11: =MAX(H27:Q27) -> 0.58195926 | N11: =M11-L11 -> 0.77765398 | S11: =+S6+7 -> 44937 | T11: Jan | U11: =IF('HAVER - UK Gas'!H1581="",C1293,AVERAGE('HAVER - UK Gas'!H1581:Q1581)) -> 189.916 | AE11: 44044 | AF11: ='[1]CPI Forecast'!D301 -> 0.21960784 | AG11: =NA() -> #N/A | AH11: =NA() -> #N/A | AI11: 2 | AK11: 43678 | AL11: =[1]Contributions!C262 -> 0.30735609 | AM11: =[1]Contributions!D262 -> -0.0091266104 | AN11: =[1]Contributions!E262 -> 0.20035491 | AO11: =[1]Contributions!H262 -> 0.10015742 | AP11: =[1]Contributions!I262 -> 1.1017182 | AQ11: =[1]Contributions!G262 -> 1.7242674 | AR11: 2
A12: 41153 | B12: =HAVERM!K159 -> 1.9567456 | C12: =((HAVERM!M153/HAVERM!M141)-1)*100 -> 2.9498525 | D12: =((HAVERM!R152/HAVERM!R140)-1)*100 -> -6.978313 | E12: 0 | G12: Sep | H12: =NA() -> #N/A | I12: =HAVERM!L291 -> -0.14925373 | J12: =HAVERM!L279 -> 1.1016949 | K12: =AVERAGE(H28:Q28) -> 0.063265634 | L12: =MIN(H28:Q28) -> -0.19627085 | M12: =MAX(H28:Q28) -> 0.80482897 | N12: =M12-L12 -> 1.0010998 | S12: =+S7+7 -> 44938 | T12: Jan | U12: =IF('HAVER - UK Gas'!H1582="",C1294,AVERAGE('HAVER - UK Gas'!H1582:Q1582)) -> 183.519 | AE12: 44075 | AF12: ='[1]CPI Forecast'!D302 -> 0.53190018 | AG12: =NA() -> #N/A | AH12: =NA() -> #N/A | AI12: 2 | AK12: 43709 | AL12: =[1]Contributions!C263 -> 0.29412248 | AM12: =[1]Contributions!D263 -> -0.072719435 | AN12: =[1]Contributions!E263 -> 0.14559002 | AO12: =[1]Contributions!H263 -> 0.16419639 | AP12: =[1]Contributions!I263 -> 1.1905117 | AQ12: =[1]Contributions!G263 -> 1.7149555 | AR12: 2
A13: 41183 | B13: =HAVERM!K160 -> 3.4303534 | C13: =((HAVERM!M154/HAVERM!M142)-1)*100 -> 2.0368574 | D13: =((HAVERM!R153/HAVERM!R141)-1)*100 -> -4.3355408 | E13: 0 | G13: Oct | H13: =NA() -> #N/A | I13: =HAVERM!L292 -> 0.14947683 | J13: =HAVERM!L280 -> 2.0117351 | K13: =AVERAGE(H29:Q29) -> -0.1081351 | L13: =MIN(H29:Q29) -> -0.92687951 | M13: =MAX(H29:Q29) -> 0.50505051 | N13: =M13-L13 -> 1.43193 | S13: =+S8+7 -> 44939 | T13: Jan | U13: =IF('HAVER - UK Gas'!H1583="",C1295,AVERAGE('HAVER - UK Gas'!H1583:Q1583)) -> 160.836 | AE13: 44105 | AF13: ='[1]CPI Forecast'!D303 -> 0.69715046 | AG13: =NA() -> #N/A | AH13: =NA() -> #N/A | AI13: 2 | AK13: 43739 | AL13: =[1]Contributions!C264 -> 0.26808715 | AM13: =[1]Contributions!D264 -> -0.11127734 | AN13: =[1]Contributions!E264 -> -0.081176493 | AO13: =[1]Contributions!H264 -> 0.19533852 | AP13: =[1]Contributions!I264 -> 1.2339005 | AQ13: =[1]Contributions!G264 -> 1.4643744 | AR13: 2
A14: 41214 | B14: =HAVERM!K161 -> 3.9256198 | C14: =((HAVERM!M155/HAVERM!M143)-1)*100 -> 1.3500482 | D14: =((HAVERM!R154/HAVERM!R142)-1)*100 -> -6.4065877 | E14: 0 | G14: Nov | H14: =NA() -> #N/A | I14: =HAVERM!L293 -> 0.29850746 | J14: =HAVERM!L281 -> 1.1503698 | K14: =AVERAGE(H30:Q30) -> 0.50448327 | L14: =MIN(H30:Q30) -> -0.19627085 | M14: =MAX(H30:Q30) -> 1.5267176 | N14: =M14-L14 -> 1.7229884 | S14: =+S9+7 -> 44942 | T14: Jan | U14: =IF('HAVER - UK Gas'!H1584="",C1296,AVERAGE('HAVER - UK Gas'!H1584:Q1584)) -> 170.941 | AE14: 44136 | AF14: ='[1]CPI Forecast'!D304 -> 0.31506509 | AG14: =NA() -> #N/A | AH14: =NA() -> #N/A | AI14: 2 | AK14: 43770 | AL14: =[1]Contributions!C265 -> 0.27924808 | AM14: =[1]Contributions!D265 -> -0.096602573 | AN14: =[1]Contributions!E265 -> -0.074597789 | AO14: =[1]Contributions!H265 -> 0.16802979 | AP14: =[1]Contributions!I265 -> 1.1872287 | AQ14: =[1]Contributions!G265 -> 1.4742176 | AR14: 2
A15: 41244 | B15: =HAVERM!K162 -> 3.7716616 | C15: =((HAVERM!M156/HAVERM!M144)-1)*100 -> 2.3121387 | D15: =((HAVERM!R155/HAVERM!R143)-1)*100 -> -9.2371197 | E15: 0 | G15: Dec | H15: =NA() -> #N/A | I15: =HAVERM!L294 -> 0.52083333 | J15: =HAVERM!L282 -> 1.6246954 | K15: =AVERAGE(H31:Q31) -> 0.75041757 | L15: =MIN(H31:Q31) -> -0.2016129 | M15: =MAX(H31:Q31) -> 1.6111708 | N15: =M15-L15 -> 1.8127837 | S15: =+S10+7 -> 44943 | T15: Jan | U15: =IF('HAVER - UK Gas'!H1585="",C1297,AVERAGE('HAVER - UK Gas'!H1585:Q1585)) -> 173.819 | AE15: 44166 | AF15: ='[1]CPI Forecast'!D305 -> 0.58876645 | AG15: =NA() -> #N/A | AH15: =NA() -> #N/A | AI15: 2 | AK15: 43800 | AL15: =[1]Contributions!C266 -> 0.23858853 | AM15: =[1]Contributions!D266 -> 0.028714951 | AN15: =[1]Contributions!E266 -> -0.068093901 | AO15: =[1]Contributions!H266 -> 0.047240213 | AP15: =[1]Contributions!I266 -> 1.0078178 | AQ15: =[1]Contributions!G266 -> 1.3020712 | AR15: 2
A16: 41275 | B16: =HAVERM!K163 -> 4.192229 | C16: =((HAVERM!M157/HAVERM!M145)-1)*100 -> 2.3255814 | D16: =((HAVERM!R156/HAVERM!R144)-1)*100 -> -11.040591 | E16: 0 | S16: =+S11+7 -> 44944 | T16: Jan | U16: =IF('HAVER - UK Gas'!H1586="",C1298,AVERAGE('HAVER - UK Gas'!H1586:Q1586)) -> 172.696 | AE16: 44197 | AF16: ='[1]CPI Forecast'!D306 -> 0.70058043 | AG16: =NA() -> #N/A | AH16: =NA() -> #N/A | AI16: 2 | AK16: 43831 | AL16: =[1]Contributions!C267 -> 0.21172023 | AM16: =[1]Contributions!D267 -> 0.14220602 | AN16: =[1]Contributions!E267 -> 0.16311787 | AO16: =[1]Contributions!H267 -> 0.083346322 | AP16: =[1]Contributions!I267 -> 1.0983456 | AQ16: =[1]Contributions!G267 -> 1.7692706 | AR16: 2
A17: 41306 | B17: =HAVERM!K164 -> 3.6363636 | C17: =((HAVERM!M158/HAVERM!M146)-1)*100 -> 3.0155642 | D17: =((HAVERM!R157/HAVERM!R145)-1)*100 -> -5.0628427 | E17: 0 | S17: =+S12+7 -> 44945 | T17: Jan | U17: =IF('HAVER - UK Gas'!H1587="",C1299,AVERAGE('HAVER - UK Gas'!H1587:Q1587)) -> 187.973 | AE17: 44228 | AF17: ='[1]CPI Forecast'!D307 -> 0.41421589 | AG17: =NA() -> #N/A | AH17: =NA() -> #N/A | AI17: 2 | AK17: 43862 | AL17: =[1]Contributions!C268 -> 0.14481804 | AM17: =[1]Contributions!D268 -> 0.081385655 | AN17: =[1]Contributions!E268 -> 0.13454013 | AO17: =[1]Contributions!H268 -> -0.027200463 | AP17: =[1]Contributions!I268 -> 1.1904598 | AQ17: =[1]Contributions!G268 -> 1.7095297 | AR17: 2
A18: 41334 | B18: =HAVERM!K165 -> 3.7563452 | C18: =((HAVERM!M159/HAVERM!M147)-1)*100 -> 2.7105518 | D18: =((HAVERM!R158/HAVERM!R146)-1)*100 -> -6.5663908 | E18: 0 | S18: =+S13+7 -> 44946 | T18: Jan | U18: =IF('HAVER - UK Gas'!H1588="",C1300,AVERAGE('HAVER - UK Gas'!H1588:Q1588)) -> 186.824 | AE18: 44256 | AF18: ='[1]CPI Forecast'!D308 -> 0.71432517 | AG18: =NA() -> #N/A | AH18: =NA() -> #N/A | AI18: 2 | AK18: 43891 | AL18: =[1]Contributions!C269 -> 0.19696619 | AM18: =[1]Contributions!D269 -> -0.071410361 | AN18: =[1]Contributions!E269 -> 0.11918783 | AO18: =[1]Contributions!H269 -> -0.074988764 | AP18: =[1]Contributions!I269 -> 1.2334412 | AQ18: =[1]Contributions!G269 -> 1.5233075 | AR18: 2
A19: 41365 | B19: =HAVERM!K166 -> 4.5731707 | C19: =((HAVERM!M160/HAVERM!M148)-1)*100 -> 3.1945789 | D19: =((HAVERM!R159/HAVERM!R147)-1)*100 -> -5.9744777 | E19: 0 | H19: 2010 | I19: 2011 | J19: 2012 | K19: 2013 | L19: 2014 | M19: 2015 | N19: 2016 | O19: 2017 | P19: 2018 | Q19: 2019 | S19: =+S14+7 -> 44949 | T19: Jan | U19: =IF('HAVER - UK Gas'!H1589="",C1301,AVERAGE('HAVER - UK Gas'!H1589:Q1589)) -> 168.307 | AE19: 44287 | AF19: ='[1]CPI Forecast'!D309 -> 1.5259222 | AG19: =NA() -> #N/A | AH19: =NA() -> #N/A | AI19: 2 | AK19: 43922 | AL19: =[1]Contributions!C270 -> 0.23502657 | AM19: =[1]Contributions!D270 -> -0.37714641 | AN19: =[1]Contributions!E270 -> -0.23267241 | AO19: =[1]Contributions!H270 -> 0.04100588 | AP19: =[1]Contributions!I270 -> 0.96774728 | AQ19: =[1]Contributions!G270 -> 0.76742263 | AR19: 2
A20: 41395 | B20: =HAVERM!K167 -> 4.2553191 | C20: =((HAVERM!M161/HAVERM!M149)-1)*100 -> 3.7572254 | D20: =((HAVERM!R160/HAVERM!R148)-1)*100 -> -3.3087193 | E20: 0 | G20: January | H20: =HAVERM!L127 -> -0.22446689 | I20: =HAVERM!L139 -> -0.10570825 | J20: =HAVERM!L151 -> -0.3058104 | K20: =HAVERM!L163 -> 0.098231827 | L20: =HAVERM!L175 -> 0.096339114 | M20: =HAVERM!L187 -> -0.68627451 | N20: =HAVERM!L199 -> -0.4040404 | O20: =HAVERM!L211 -> 0.20429009 | P20: =HAVERM!L223 -> -0.098231827 | Q20: =HAVERM!L235 -> 0.097560976 | S20: =+S15+7 -> 44950 | T20: Jan | U20: =IF('HAVER - UK Gas'!H1590="",C1302,AVERAGE('HAVER - UK Gas'!H1590:Q1590)) -> 163.369 | AE20: 44317 | AF20: ='[1]CPI Forecast'!D310 -> 2.1149485 | AG20: =NA() -> #N/A | AH20: =NA() -> #N/A | AI20: 2 | AK20: 43952 | AL20: =[1]Contributions!C271 -> 0.28616843 | AM20: =[1]Contributions!D271 -> -0.52713414 | AN20: =[1]Contributions!E271 -> -0.23789164 | AO20: =[1]Contributions!H271 -> -0.11161792 | AP20: =[1]Contributions!I271 -> 0.96492333 | AQ20: =[1]Contributions!G271 -> 0.47986067 | AR20: 2
A21: 41426 | B21: =HAVERM!K168 -> 3.8539554 | C21: =((HAVERM!M162/HAVERM!M150)-1)*100 -> 4.2226488 | D21: =((HAVERM!R161/HAVERM!R149)-1)*100 -> -2.9503066 | E21: 0 | G21: February | H21: =HAVERM!L128 -> 1.1248594 | I21: =HAVERM!L140 -> 1.0582011 | J21: =HAVERM!L152 -> 1.2269939 | K21: =HAVERM!L164 -> 0.68694799 | L21: =HAVERM!L176 -> 0.57747834 | M21: =HAVERM!L188 -> -0.29615005 | N21: =HAVERM!L200 -> 0.20283976 | O21: =HAVERM!L212 -> 0.81549439 | P21: =HAVERM!L224 -> 0.19665683 | Q21: =HAVERM!L236 -> 0.38986355 | S21: =+S16+7 -> 44951 | T21: Jan | U21: =IF('HAVER - UK Gas'!H1591="",C1303,AVERAGE('HAVER - UK Gas'!H1591:Q1591)) -> 159.381 | AE21: 44348 | AF21: ='[1]CPI Forecast'!D311 -> 2.5141826 | AG21: =NA() -> #N/A | AH21: =NA() -> #N/A | AI21: 2 | AK21: 43983 | AL21: =[1]Contributions!C272 -> 0.19527087 | AM21: =[1]Contributions!D272 -> -0.51373872 | AN21: =[1]Contributions!E272 -> -0.22603286 | AO21: =[1]Contributions!H272 -> 0.21133783 | AP21: =[1]Contributions!I272 -> 0.87854939 | AQ21: =[1]Contributions!G272 -> 0.60315196 | AR21: 2
A22: 41456 | B22: =HAVERM!K169 -> 3.8461538 | C22: =((HAVERM!M163/HAVERM!M151)-1)*100 -> 4.6153846 | D22: =((HAVERM!R162/HAVERM!R150)-1)*100 -> 0.67431019 | E22: 0 | G22: March | H22: =HAVERM!L129 -> 0.22246941 | I22: =HAVERM!L141 -> -1.3612565 | J22: =HAVERM!L153 -> -0.50505051 | K22: =HAVERM!L165 -> -0.38986355 | L22: =HAVERM!L177 -> -0.57416268 | M22: =HAVERM!L189 -> -0.099009901 | N22: =HAVERM!L201 -> -0.70850202 | O22: =HAVERM!L213 -> 0.40444894 | P22: =HAVERM!L225 -> 0.39254171 | Q22: =HAVERM!L237 -> 0.097087379 | S22: =+S17+7 -> 44952 | T22: Jan | U22: =IF('HAVER - UK Gas'!H1592="",C1304,AVERAGE('HAVER - UK Gas'!H1592:Q1592)) -> 159.47 | AE22: 44378 | AF22: ='[1]CPI Forecast'!D312 -> 2.0399369 | AG22: =NA() -> #N/A | AH22: =NA() -> #N/A | AI22: 2 | AK22: 44013 | AL22: =[1]Contributions!C273 -> 0.18227004 | AM22: =[1]Contributions!D273 -> -0.37317568 | AN22: =[1]Contributions!E273 -> -0.2230972 | AO22: =[1]Contributions!H273 -> 0.37030064 | AP22: =[1]Contributions!I273 -> 1.01431 | AQ22: =[1]Contributions!G273 -> 1.0403061 | AR22: 2
A23: 41487 | B23: =HAVERM!K170 -> 4.1414141 | C23: =((HAVERM!M164/HAVERM!M152)-1)*100 -> 4.6889952 | D23: =((HAVERM!R163/HAVERM!R151)-1)*100 -> 1.8715633 | E23: 0 | G23: April | H23: =HAVERM!L130 -> 0.33296337 | I23: =HAVERM!L142 -> 0.10615711 | J23: =HAVERM!L154 -> -0.10152284 | K23: =HAVERM!L166 -> 0.68493151 | L23: =HAVERM!L178 -> -0.48123195 | M23: =HAVERM!L190 -> -0.39643211 | N23: =HAVERM!L202 -> -0.1019368 | O23: =HAVERM!L214 -> 0.20140987 | P23: =HAVERM!L226 -> -0.19550342 | Q23: =HAVERM!L238 -> -0.29097963 | S23: =+S18+7 -> 44953 | T23: Jan | U23: =IF('HAVER - UK Gas'!H1593="",C1305,AVERAGE('HAVER - UK Gas'!H1593:Q1593)) -> 160.034 | AE23: 44409 | AF23: ='[1]CPI Forecast'!D313 -> 3.1966707 | AG23: =NA() -> #N/A | AH23: =NA() -> #N/A | AI23: 2 | AK23: 44044 | AL23: =[1]Contributions!C274 -> 0.10372773 | AM23: =[1]Contributions!D274 -> -0.35277846 | AN23: =[1]Contributions!E274 -> -0.2280952 | AO23: =[1]Contributions!H274 -> 0.27483006 | AP23: =[1]Contributions!I274 -> 0.30999998 | AQ23: =[1]Contributions!G274 -> 0.21960784 | AR23: 2
A24: 41518 | B24: =HAVERM!K171 -> 4.2424242 | C24: =((HAVERM!M165/HAVERM!M153)-1)*100 -> 5.5396371 | D24: =((HAVERM!R164/HAVERM!R152)-1)*100 -> 0.38472031 | E24: 0 | G24: May | H24: =HAVERM!L131 -> -0.11061947 | I24: =HAVERM!L143 -> 1.2725345 | J24: =HAVERM!L155 -> 0.30487805 | K24: =HAVERM!L167 -> 0 | L24: =HAVERM!L179 -> -1.0638298 | M24: =HAVERM!L191 -> -0.099502488 | N24: =HAVERM!L203 -> -0.40816327 | O24: =HAVERM!L215 -> 0.10050251 | P24: =HAVERM!L227 -> -0.19588639 | Q24: =HAVERM!L239 -> 0.097276265 | S24: =+S19+7 -> 44956 | T24: Jan | U24: =IF('HAVER - UK Gas'!H1594="",C1306,AVERAGE('HAVER - UK Gas'!H1594:Q1594)) -> 167.975 | AE24: 44440 | AF24: ='[1]CPI Forecast'!D314 -> 3.080069 | AG24: =NA() -> #N/A | AH24: =NA() -> #N/A | AI24: 2 | AK24: 44075 | AL24: =[1]Contributions!C275 -> 0.065022832 | AM24: =[1]Contributions!D275 -> -0.32830787 | AN24: =[1]Contributions!E275 -> -0.22787652 | AO24: =[1]Contributions!H275 -> 0.24150721 | AP24: =[1]Contributions!I275 -> 0.70256487 | AQ24: =[1]Contributions!G275 -> 0.53190018 | AR24: 2
A25: 41548 | B25: =HAVERM!K172 -> 3.919598 | C25: =((HAVERM!M166/HAVERM!M154)-1)*100 -> 5.7034221 | D25: =((HAVERM!R165/HAVERM!R153)-1)*100 -> -0.13010683 | E25: 0 | G25: June | H25: =HAVERM!L132 -> -0.11074197 | I25: =HAVERM!L144 -> 1.0471204 | J25: =HAVERM!L156 -> -0.10131712 | K25: =HAVERM!L168 -> -0.48590865 | L25: =HAVERM!L180 -> 0.097751711 | M25: =HAVERM!L192 -> -0.19920319 | N25: =HAVERM!L204 -> -0.40983607 | O25: =HAVERM!L216 -> -0.20080321 | P25: =HAVERM!L228 -> -0.49067713 | Q25: =HAVERM!L240 -> 0.19436346 | S25: =+S20+7 -> 44957 | T25: Jan | U25: =IF('HAVER - UK Gas'!H1595="",C1307,AVERAGE('HAVER - UK Gas'!H1595:Q1595)) -> 173.496 | AE25: 44470 | AF25: ='[1]CPI Forecast'!D315 -> 4.2062117 | AG25: =NA() -> #N/A | AH25: =NA() -> #N/A | AI25: 2 | AK25: 44105 | AL25: =[1]Contributions!C276 -> 0.14295255 | AM25: =[1]Contributions!D276 -> -0.31544409 | AN25: =[1]Contributions!E276 -> -0.28976607 | AO25: =[1]Contributions!H276 -> 0.36791692 | AP25: =[1]Contributions!I276 -> 0.65975538 | AQ25: =[1]Contributions!G276 -> 0.69715046 | AR25: 2
A26: 41579 | B26: =HAVERM!K173 -> 2.7833002 | C26: =((HAVERM!M167/HAVERM!M155)-1)*100 -> 5.4234063 | D26: =((HAVERM!R166/HAVERM!R154)-1)*100 -> 0.62078635 | E26: 0 | G26: July | H26: =HAVERM!L133 -> 0.99778271 | I26: =HAVERM!L145 -> 0.20725389 | J26: =HAVERM!L157 -> 0.20283976 | K26: =HAVERM!L169 -> 0.1953125 | L26: =HAVERM!L181 -> -0.1953125 | M26: =HAVERM!L193 -> -0.69860279 | N26: =HAVERM!L205 -> -0.30864198 | O26: =HAVERM!L217 -> 0 | P26: =HAVERM!L229 -> 0.29585799 | Q26: =HAVERM!L241 -> 0 | S26: =+S21+7 -> 44958 | T26: Feb | U26: =IF('HAVER - UK Gas'!H1596="",C1308,AVERAGE('HAVER - UK Gas'!H1596:Q1596)) -> 169.514 | AE26: 44501 | AF26: ='[1]CPI Forecast'!D316 -> 5.1299005 | AG26: =NA() -> #N/A | AH26: =NA() -> #N/A | AI26: 2 | AK26: 44136 | AL26: =[1]Contributions!C277 -> 0.026160354 | AM26: =[1]Contributions!D277 -> -0.30405477 | AN26: =[1]Contributions!E277 -> -0.29207545 | AO26: =[1]Contributions!H277 -> 0.091255071 | AP26: =[1]Contributions!I277 -> 0.70152952 | AQ26: =[1]Contributions!G277 -> 0.31506509 | AR26: 2
A27: 41609 | B27: =HAVERM!K174 -> 1.9646365 | C27: =((HAVERM!M168/HAVERM!M156)-1)*100 -> 5.5555556 | D27: =((HAVERM!R167/HAVERM!R155)-1)*100 -> 4.1146348 | E27: 0 | G27: August | H27: =HAVERM!L134 -> 0.10976948 | I27: =HAVERM!L146 -> 0.20682523 | J27: =HAVERM!L158 -> 0.20242915 | K27: =HAVERM!L170 -> 0.48732943 | L27: =HAVERM!L182 -> -0.19569472 | M27: =HAVERM!L194 -> 0 | N27: =HAVERM!L206 -> 0.4127967 | O27: =HAVERM!L218 -> 0 | P27: =HAVERM!L230 -> 0.19665683 | Q27: =HAVERM!L242 -> 0.58195926 | S27: =+S22+7 -> 44959 | T27: Feb | U27: =IF('HAVER - UK Gas'!H1597="",C1309,AVERAGE('HAVER - UK Gas'!H1597:Q1597)) -> 172.12 | AE27: 44531 | AF27: ='[1]CPI Forecast'!D317 -> 5.3860457 | AG27: =NA() -> #N/A | AH27: =NA() -> #N/A | AI27: 2 | AK27: 44166 | AL27: =[1]Contributions!C278 -> 0.00036004292 | AM27: =[1]Contributions!D278 -> -0.25306379 | AN27: =[1]Contributions!E278 -> -0.28020169 | AO27: =[1]Contributions!H278 -> 0.31839669 | AP27: =[1]Contributions!I278 -> 0.70338654 | AQ27: =[1]Contributions!G278 -> 0.58876645 | AR27: 2
A28: 41640 | B28: =HAVERM!K175 -> 1.9627085 | C28: =((HAVERM!M169/HAVERM!M157)-1)*100 -> 4.9242424 | D28: =((HAVERM!R168/HAVERM!R156)-1)*100 -> 5.4549047 | E28: 0 | G28: September | H28: =HAVERM!L135 -> 0.10964912 | I28: =HAVERM!L147 -> 0.20639835 | J28: =HAVERM!L159 -> 0 | K28: =HAVERM!L171 -> 0.09699321 | L28: =HAVERM!L183 -> -0.19607843 | M28: =HAVERM!L195 -> 0 | N28: =HAVERM!L207 -> 0 | O28: =HAVERM!L219 -> 0.80482897 | P28: =HAVERM!L231 -> -0.19627085 | Q28: =HAVERM!L243 -> -0.19286403 | S28: =+S23+7 -> 44960 | T28: Feb | U28: =IF('HAVER - UK Gas'!H1598="",C1310,AVERAGE('HAVER - UK Gas'!H1598:Q1598)) -> 168.629 | AE28: 44562 | AF28: ='[1]CPI Forecast'!D318 -> 5.4555133 | AG28: =NA() -> #N/A | AH28: =NA() -> #N/A | AI28: 2 | AK28: 44197 | AL28: =[1]Contributions!C279 -> 0.051396648 | AM28: =[1]Contributions!D279 -> -0.25361184 | AN28: =[1]Contributions!E279 -> -0.26956522 | AO28: =[1]Contributions!H279 -> 0.70999565 | AP28: =[1]Contributions!I279 -> 0.83306379 | AQ28: =[1]Contributions!G279 -> 0.70058043 | AR28: 2
A29: 41671 | B29: =HAVERM!K176 -> 1.8518519 | C29: =((HAVERM!M170/HAVERM!M158)-1)*100 -> 2.9272899 | D29: =((HAVERM!R169/HAVERM!R157)-1)*100 -> -0.78903406 | E29: 0 | G29: October | H29: =HAVERM!L136 -> 0.4381161 | I29: =HAVERM!L148 -> -0.92687951 | J29: =HAVERM!L160 -> 0.50505051 | K29: =HAVERM!L172 -> 0.19379845 | L29: =HAVERM!L184 -> 0.098231827 | M29: =HAVERM!L196 -> -0.40201005 | N29: =HAVERM!L208 -> -0.51387461 | O29: =HAVERM!L220 -> 0.3992016 | P29: =HAVERM!L232 -> -0.19665683 | Q29: =HAVERM!L244 -> -0.6763285 | S29: =+S24+7 -> 44963 | T29: Feb | U29: =IF('HAVER - UK Gas'!H1599="",C1311,AVERAGE('HAVER - UK Gas'!H1599:Q1599)) -> 163.256 | AE29: 44593 | AF29: ='[1]CPI Forecast'!D319 -> 6.1766081 | AG29: =NA() -> #N/A | AH29: =NA() -> #N/A | AI29: 2 | AK29: 44228 | AL29: =[1]Contributions!C280 -> 0.053460793 | AM29: =[1]Contributions!D280 -> -0.1084029 | AN29: =[1]Contributions!E280 -> -0.25512712 | AO29: =[1]Contributions!H280 -> 0.34458477 | AP29: =[1]Contributions!I280 -> 0.7345853 | AQ29: =[1]Contributions!G280 -> 0.41421589 | AR29: 2
A30: 41699 | B30: =HAVERM!K177 -> 1.6634051 | C30: =((HAVERM!M171/HAVERM!M159)-1)*100 -> 2.3562677 | D30: =((HAVERM!R170/HAVERM!R158)-1)*100 -> -3.8084369 | E30: 0 | G30: November | H30: =HAVERM!L137 -> 1.5267176 | I30: =HAVERM!L149 -> 0.62370062 | J30: =HAVERM!L161 -> 1.1055276 | K30: =HAVERM!L173 -> 0 | L30: =HAVERM!L185 -> -0.19627085 | M30: =HAVERM!L197 -> 0.10090817 | N30: =HAVERM!L209 -> 0.41322314 | O30: =HAVERM!L221 -> 0.49701789 | P30: =HAVERM!L233 -> 0.098522167 | Q30: =HAVERM!L245 -> 0.87548638 | S30: =+S25+7 -> 44964 | T30: Feb | U30: =IF('HAVER - UK Gas'!H1600="",C1312,AVERAGE('HAVER - UK Gas'!H1600:Q1600)) -> 157.95 | AE30: 44621 | AF30: ='[1]CPI Forecast'!D320 -> 7.023124 | AG30: =NA() -> #N/A | AH30: =NA() -> #N/A | AI30: 2 | AK30: 44256 | AL30: =[1]Contributions!C281 -> -0.059171934 | AM30: =[1]Contributions!D281 -> 0.092082718 | AN30: =[1]Contributions!E281 -> -0.23697976 | AO30: =[1]Contributions!H281 -> 0.50026976 | AP30: =[1]Contributions!I281 -> 0.72382812 | AQ30: =[1]Contributions!G281 -> 0.71432517 | AR30: 2
A31: 41730 | B31: =HAVERM!K178 -> 0.48590865 | C31: =((HAVERM!M172/HAVERM!M160)-1)*100 -> 2.0637899 | D31: =((HAVERM!R171/HAVERM!R159)-1)*100 -> -5.5557963 | E31: 0 | G31: December | H31: =HAVERM!L138 -> 1.6111708 | I31: =HAVERM!L150 -> 1.3429752 | J31: =HAVERM!L162 -> 1.1928429 | K31: =HAVERM!L174 -> 0.3868472 | L31: =HAVERM!L186 -> 0.29498525 | M31: =HAVERM!L198 -> -0.2016129 | N31: =HAVERM!L210 -> 0.72016461 | O31: =HAVERM!L222 -> 0.69238378 | P31: =HAVERM!L234 -> 0.88582677 | Q31: =HAVERM!L246 -> 0.57859209 | S31: =+S26+7 -> 44965 | T31: Feb | U31: =IF('HAVER - UK Gas'!H1601="",C1313,AVERAGE('HAVER - UK Gas'!H1601:Q1601)) -> 154.895 | AE31: 44652 | AF31: ='[1]CPI Forecast'!D321 -> 9.0106617 | AG31: =NA() -> #N/A | AH31: =NA() -> #N/A | AI31: 2 | AK31: 44287 | AL31: =[1]Contributions!C282 -> 0.044450556 | AM31: =[1]Contributions!D282 -> 0.3543065 | AN31: =[1]Contributions!E282 -> 0.10426883 | AO31: =[1]Contributions!H282 -> 0.6426047 | AP31: =[1]Contributions!I282 -> 0.73108502 | AQ31: =[1]Contributions!G282 -> 1.5259222 | AR31: 2
A32: 41760 | B32: =HAVERM!K179 -> -0.58309038 | C32: =((HAVERM!M173/HAVERM!M161)-1)*100 -> 1.2070566 | D32: =((HAVERM!R172/HAVERM!R160)-1)*100 -> -4.2779272 | E32: 0 | S32: =+S27+7 -> 44966 | T32: Feb | U32: =IF('HAVER - UK Gas'!H1602="",C1314,AVERAGE('HAVER - UK Gas'!H1602:Q1602)) -> 155.348 | AE32: 44682 | AF32: ='[1]CPI Forecast'!D322 -> 9.0827013 | AG32: =NA() -> #N/A | AH32: =NA() -> #N/A | AI32: 2 | AK32: 44317 | AL32: =[1]Contributions!C283 -> -0.064550276 | AM32: =[1]Contributions!D283 -> 0.45743575 | AN32: =[1]Contributions!E283 -> 0.11052257 | AO32: =[1]Contributions!H283 -> 1.037649 | AP32: =[1]Contributions!I283 -> 0.84657298 | AQ32: =[1]Contributions!G283 -> 2.1149485 | AR32: 2
A33: 41791 | B33: =HAVERM!K180 -> 0 | C33: =((HAVERM!M174/HAVERM!M162)-1)*100 -> 0.18416206 | D33: =((HAVERM!R173/HAVERM!R161)-1)*100 -> -4.8133191 | E33: 0 | S33: =+S28+7 -> 44967 | T33: Feb | U33: =IF('HAVER - UK Gas'!H1603="",C1315,AVERAGE('HAVER - UK Gas'!H1603:Q1603)) -> 150.51 | AE33: 44713 | AF33: ='[1]CPI Forecast'!D323 -> 9.4121135 | AG33: =NA() -> #N/A | AH33: =NA() -> #N/A | AI33: 2 | AK33: 44348 | AL33: =[1]Contributions!C284 -> 0.044399386 | AM33: =[1]Contributions!D284 -> 0.51600178 | AN33: =[1]Contributions!E284 -> 0.10474233 | AO33: =[1]Contributions!H284 -> 1.210991 | AP33: =[1]Contributions!I284 -> 0.9556646 | AQ33: =[1]Contributions!G284 -> 2.5141826 | AR33: 2
A34: 41821 | B34: =HAVERM!K181 -> -0.38986355 | C34: =((HAVERM!M175/HAVERM!M163)-1)*100 -> -0.36764706 | D34: =((HAVERM!R174/HAVERM!R162)-1)*100 -> -6.5324871 | E34: 0 | S34: =+S29+7 -> 44970 | T34: Feb | U34: =IF('HAVER - UK Gas'!H1604="",C1316,AVERAGE('HAVER - UK Gas'!H1604:Q1604)) -> 150 | AE34: 44743 | AF34: ='[1]CPI Forecast'!D324 -> 10.100901 | AG34: =NA() -> #N/A | AH34: =NA() -> #N/A | AI34: 2 | AK34: 44378 | AL34: =[1]Contributions!C285 -> -0.0018952519 | AM34: =[1]Contributions!D285 -> 0.46543883 | AN34: =[1]Contributions!E285 -> 0.11079483 | AO34: =[1]Contributions!H285 -> 1.122908 | AP34: =[1]Contributions!I285 -> 0.67323793 | AQ34: =[1]Contributions!G285 -> 2.0399369 | AR34: 2
A35: 41852 | B35: =HAVERM!K182 -> -1.0669253 | C35: =((HAVERM!M176/HAVERM!M164)-1)*100 -> -1.3711152 | D35: =((HAVERM!R175/HAVERM!R163)-1)*100 -> -10.271322 | E35: 0 | S35: =+S30+7 -> 44971 | T35: Feb | U35: =IF('HAVER - UK Gas'!H1605="",C1317,AVERAGE('HAVER - UK Gas'!H1605:Q1605)) -> 153.979 | AE35: 44774 | AF35: ='[1]CPI Forecast'!D325 -> 9.8701878 | AG35: =NA() -> #N/A | AH35: =NA() -> #N/A | AI35: 2 | AK35: 44409 | AL35: =[1]Contributions!C286 -> 0.14415191 | AM35: =[1]Contributions!D286 -> 0.47085525 | AN35: =[1]Contributions!E286 -> 0.11096636 | AO35: =[1]Contributions!H286 -> 1.5349375 | AP35: =[1]Contributions!I286 -> 1.3507984 | AQ35: =[1]Contributions!G286 -> 3.1966707 | AR35: 2
A36: 41883 | B36: =HAVERM!K183 -> -1.3565891 | C36: =((HAVERM!M177/HAVERM!M165)-1)*100 -> -2.6244344 | D36: =((HAVERM!R176/HAVERM!R164)-1)*100 -> -10.208926 | E36: 0 | S36: =+S31+7 -> 44972 | T36: Feb | U36: =IF('HAVER - UK Gas'!H1606="",C1318,AVERAGE('HAVER - UK Gas'!H1606:Q1606)) -> 149.83 | AE36: 44805 | AF36: ='[1]CPI Forecast'!D326 -> 10.095628 | AG36: =NA() -> #N/A | AH36: =NA() -> #N/A | AI36: 2 | AK36: 44440 | AL36: =[1]Contributions!C287 -> 0.2077674 | AM36: =[1]Contributions!D287 -> 0.47137954 | AN36: =[1]Contributions!E287 -> 0.11703769 | AO36: =[1]Contributions!H287 -> 1.5235567 | AP36: =[1]Contributions!I287 -> 1.1269214 | AQ36: =[1]Contributions!G287 -> 3.080069 | AR36: 2
A37: 41913 | B37: =HAVERM!K184 -> -1.450677 | C37: =((HAVERM!M178/HAVERM!M166)-1)*100 -> -3.4172662 | D37: =((HAVERM!R177/HAVERM!R165)-1)*100 -> -7.488173 | E37: 0 | S37: =+S32+7 -> 44973 | T37: Feb | U37: =IF('HAVER - UK Gas'!H1607="",C1319,AVERAGE('HAVER - UK Gas'!H1607:Q1607)) -> 144.123 | AE37: 44835 | AF37: ='[1]CPI Forecast'!D327 -> 11.051566 | AG37: =NA() -> #N/A | AH37: =NA() -> #N/A | AI37: 2 | AK37: 44470 | AL37: =[1]Contributions!C288 -> 0.21156428 | AM37: =[1]Contributions!D288 -> 0.56867529 | AN37: =[1]Contributions!E288 -> 0.75184398 | AO37: =[1]Contributions!H288 -> 1.627456 | AP37: =[1]Contributions!I288 -> 1.4387625 | AQ37: =[1]Contributions!G288 -> 4.2062117 | AR37: 2
A38: 41944 | B38: =HAVERM!K185 -> -1.6441006 | C38: =((HAVERM!M179/HAVERM!M167)-1)*100 -> -2.7075812 | D38: =((HAVERM!R178/HAVERM!R166)-1)*100 -> -8.4643529 | E38: 0 | S38: =+S33+7 -> 44974 | T38: Feb | U38: =IF('HAVER - UK Gas'!H1608="",C1320,AVERAGE('HAVER - UK Gas'!H1608:Q1608)) -> 143.293 | AE38: 44866 | AF38: ='[1]CPI Forecast'!D328 -> 10.672013 | AG38: =NA() -> #N/A | AH38: =NA() -> #N/A | AI38: 2 | AK38: 44501 | AL38: =[1]Contributions!C289 -> 0.48658715 | AM38: =[1]Contributions!D289 -> 0.74681144 | AN38: =[1]Contributions!E289 -> 0.76246454 | AO38: =[1]Contributions!H289 -> 2.0371257 | AP38: =[1]Contributions!I289 -> 1.4792644 | AQ38: =[1]Contributions!G289 -> 5.1299005 | AR38: 2
A39: 41974 | B39: =HAVERM!K186 -> -1.734104 | C39: =((HAVERM!M180/HAVERM!M168)-1)*100 -> -5.6199822 | D39: =((HAVERM!R179/HAVERM!R167)-1)*100 -> -8.5345035 | E39: 0 | S39: =+S34+7 -> 44977 | T39: Feb | U39: =IF('HAVER - UK Gas'!H1609="",C1321,AVERAGE('HAVER - UK Gas'!H1609:Q1609)) -> 139.197 | V39: =AVERAGE($U$39:$U$71,$U$73:$U$102) -> 136.05151 | AB39: =AVERAGE($U$39:$U$71,$U$73:$U$102) -> 136.05151 | AC39: Q3 2023 | AE39: 44896 | AF39: ='[1]CPI Forecast'!D329 -> 10.528374 | AG39: =NA() -> #N/A | AH39: =NA() -> #N/A | AI39: 2 | AK39: 44531 | AL39: =[1]Contributions!C290 -> 0.61403406 | AM39: =[1]Contributions!D290 -> 0.7101353 | AN39: =[1]Contributions!E290 -> 0.74540163 | AO39: =[1]Contributions!H290 -> 2.2230712 | AP39: =[1]Contributions!I290 -> 1.4976266 | AQ39: =[1]Contributions!G290 -> 5.3860457 | AR39: 2
A40: 42005 | B40: =HAVERM!K187 -> -2.5024062 | C40: =((HAVERM!M181/HAVERM!M169)-1)*100 -> -5.7761733 | D40: =((HAVERM!R180/HAVERM!R168)-1)*100 -> -9.6586953 | E40: 0 | S40: =+S35+7 -> 44978 | T40: Feb | U40: =IF('HAVER - UK Gas'!H1610="",C1322,AVERAGE('HAVER - UK Gas'!H1610:Q1610)) -> 142.254 | V40: =AVERAGE($U$39:$U$71,$U$73:$U$102) -> 136.05151 | AB40: =AVERAGE($U$39:$U$71,$U$73:$U$102) -> 136.05151 | AE40: 44927 | AF40: ='[1]CPI Forecast'!D330 -> 10.051524 | AG40: =NA() -> #N/A | AH40: =NA() -> #N/A | AI40: 2 | AK40: 44562 | AL40: =[1]Contributions!C291 -> 0.63024119 | AM40: =[1]Contributions!D291 -> 0.61364929 | AN40: =[1]Contributions!E291 -> 0.75727003 | AO40: =[1]Contributions!H291 -> 1.991572 | AP40: =[1]Contributions!I291 -> 1.4120141 | AQ40: =[1]Contributions!G291 -> 5.4555133 | AR40: 2
A41: 42036 | B41: =HAVERM!K188 -> -3.3492823 | C41: =((HAVERM!M182/HAVERM!M170)-1)*100 -> -5.5963303 | D41: =((HAVERM!R181/HAVERM!R169)-1)*100 -> -12.242069 | E41: 0 | S41: =+S36+7 -> 44979 | T41: Feb | U41: =IF('HAVER - UK Gas'!H1611="",C1323,AVERAGE('HAVER - UK Gas'!H1611:Q1611)) -> 142.471 | V41: =AVERAGE($U$39:$U$71,$U$73:$U$102) -> 136.05151 | AB41: =AVERAGE($U$39:$U$71,$U$73:$U$102) -> 136.05151 | AE41: 44958 | AF41: ='[1]CPI Forecast'!D331 -> 10.416397 | AG41: =NA() -> #N/A | AH41: =NA() -> #N/A | AI41: 2 | AK41: 44593 | AL41: =[1]Contributions!C292 -> 0.74348786 | AM41: =[1]Contributions!D292 -> 0.61736985 | AN41: =[1]Contributions!E292 -> 0.76180494 | AO41: =[1]Contributions!H292 -> 2.5463428 | AP41: =[1]Contributions!I292 -> 1.4977042 | AQ41: =[1]Contributions!G292 -> 6.1766081 | AR41: 2
A42: 42064 | B42: =HAVERM!K189 -> -2.8873917 | C42: =((HAVERM!M183/HAVERM!M171)-1)*100 -> -6.1694291 | D42: =((HAVERM!R182/HAVERM!R170)-1)*100 -> -9.561053 | E42: 0 | S42: =+S37+7 -> 44980 | T42: Feb | U42: =IF('HAVER - UK Gas'!H1612="",C1324,AVERAGE('HAVER - UK Gas'!H1612:Q1612)) -> 144.786 | V42: =AVERAGE($U$39:$U$71,$U$73:$U$102) -> 136.05151 | AB42: =AVERAGE($U$39:$U$71,$U$73:$U$102) -> 136.05151 | AE42: 44986 | AF42: ='[1]CPI Forecast'!D332 -> 10.056877 | AG42: =NA() -> #N/A | AH42: =NA() -> #N/A | AI42: 2 | AK42: 44621 | AL42: =[1]Contributions!C293 -> 0.89250177 | AM42: =[1]Contributions!D293 -> 0.86609676 | AN42: =[1]Contributions!E293 -> 0.81106625 | AO42: =[1]Contributions!H293 -> 2.7196676 | AP42: =[1]Contributions!I293 -> 1.731011 | AQ42: =[1]Contributions!G293 -> 7.023124 | AR42: 2
A43: 42095 | B43: =HAVERM!K190 -> -2.8046422 | C43: =((HAVERM!M184/HAVERM!M172)-1)*100 -> -6.5257353 | D43: =((HAVERM!R183/HAVERM!R171)-1)*100 -> -8.6313003 | E43: 0 | S43: =+S38+7 -> 44981 | T43: Feb | U43: =IF('HAVER - UK Gas'!H1613="",C1325,AVERAGE('HAVER - UK Gas'!H1613:Q1613)) -> 137.015 | V43: =AVERAGE($U$39:$U$71,$U$73:$U$102) -> 136.05151 | AB43: =AVERAGE($U$39:$U$71,$U$73:$U$102) -> 136.05151 | AE43: 45017 | AF43: ='[1]CPI Forecast'!D333 -> 8.6582359 | AG43: =NA() -> #N/A | AH43: =NA() -> #N/A | AI43: 2 | AK43: 44652 | AL43: =[1]Contributions!C294 -> 0.97005533 | AM43: =[1]Contributions!D294 -> 0.89208333 | AN43: =[1]Contributions!E294 -> 2.3443764 | AO43: =[1]Contributions!H294 -> 2.6872988 | AP43: =[1]Contributions!I294 -> 2.0785004 | AQ43: =[1]Contributions!G294 -> 9.0106617 | AR43: 2
A44: 42125 | B44: =HAVERM!K191 -> -1.8572825 | C44: =((HAVERM!M185/HAVERM!M173)-1)*100 -> -6.6972477 | D44: =((HAVERM!R184/HAVERM!R172)-1)*100 -> -7.7664395 | E44: 0 | S44: =+S39+7 -> 44984 | T44: Feb | U44: =IF('HAVER - UK Gas'!H1614="",C1326,AVERAGE('HAVER - UK Gas'!H1614:Q1614)) -> 136.743 | V44: =AVERAGE($U$39:$U$71,$U$73:$U$102) -> 136.05151 | AB44: =AVERAGE($U$39:$U$71,$U$73:$U$102) -> 136.05151 | AE44: 45047 | AF44: ='[1]CPI Forecast'!D334 -> 8.680682 | AG44: =NA() -> #N/A | AH44: =NA() -> #N/A | AI44: 2 | AK44: 44682 | AL44: =[1]Contributions!C295 -> 1.2229849 | AM44: =[1]Contributions!D295 -> 0.9329656 | AN44: =[1]Contributions!E295 -> 2.3455187 | AO44: =[1]Contributions!H295 -> 2.4346094 | AP44: =[1]Contributions!I295 -> 2.1471304 | AQ44: =[1]Contributions!G295 -> 9.0827013 | AR44: 2
A45: 42156 | B45: =HAVERM!K192 -> -2.1484375 | C45: =((HAVERM!M186/HAVERM!M174)-1)*100 -> -5.7904412 | D45: =((HAVERM!R185/HAVERM!R173)-1)*100 -> -6.9785264 | E45: 0 | S45: =+S40+7 -> 44985 | T45: Feb | U45: =IF('HAVER - UK Gas'!H1615="",C1327,AVERAGE('HAVER - UK Gas'!H1615:Q1615)) -> 138.976 | V45: =AVERAGE($U$39:$U$71,$U$73:$U$102) -> 136.05151 | AB45: =AVERAGE($U$39:$U$71,$U$73:$U$102) -> 136.05151 | AE45: 45078 | AF45: ='[1]CPI Forecast'!D335 -> 7.9496843 | AG45: =NA() -> #N/A | AH45: =NA() -> #N/A | AI45: 2 | AK45: 44713 | AL45: =[1]Contributions!C296 -> 1.3264376 | AM45: =[1]Contributions!D296 -> 1.2191534 | AN45: =[1]Contributions!E296 -> 2.3455977 | AO45: =[1]Contributions!H296 -> 2.1794243 | AP45: =[1]Contributions!I296 -> 2.2950267 | AQ45: =[1]Contributions!G296 -> 9.4121135 | AR45: 2
A46: 42186 | B46: =HAVERM!K193 -> -2.6418787 | C46: =((HAVERM!M187/HAVERM!M175)-1)*100 -> -6.2730627 | D46: =((HAVERM!R186/HAVERM!R174)-1)*100 -> -7.518554 | E46: 0 | S46: =+S41+7 -> 44986 | T46: Mar | U46: =IF('HAVER - UK Gas'!H1616="",C1328,AVERAGE('HAVER - UK Gas'!H1616:Q1616)) -> 137.995 | V46: =AVERAGE($U$39:$U$71,$U$73:$U$102) -> 136.05151 | AB46: =AVERAGE($U$39:$U$71,$U$73:$U$102) -> 136.05151 | AE46: 45108 | AF46: ='[1]CPI Forecast'!D336 -> 6.8272142 | AG46: =NA() -> #N/A | AH46: =NA() -> #N/A | AI46: 2 | AK46: 44743 | AL46: =[1]Contributions!C297 -> 1.6748555 | AM46: =[1]Contributions!D297 -> 1.2819729 | AN46: =[1]Contributions!E297 -> 2.348535 | AO46: =[1]Contributions!H297 -> 2.220601 | AP46: =[1]Contributions!I297 -> 2.5301078 | AQ46: =[1]Contributions!G297 -> 10.100901 | AR46: 2
A47: 42217 | B47: =HAVERM!K194 -> -2.4509804 | C47: =((HAVERM!M188/HAVERM!M176)-1)*100 -> -5.931418 | D47: =((HAVERM!R187/HAVERM!R175)-1)*100 -> -8.1338188 | E47: 0 | S47: =+S42+7 -> 44987 | T47: Mar | U47: =IF('HAVER - UK Gas'!H1617="",C1329,AVERAGE('HAVER - UK Gas'!H1617:Q1617)) -> 132.74 | V47: =AVERAGE($U$39:$U$71,$U$73:$U$102) -> 136.05151 | AB47: =AVERAGE($U$39:$U$71,$U$73:$U$102) -> 136.05151 | AE47: 45139 | AF47: ='[1]CPI Forecast'!D337 -> 6.6570306 | AG47: =NA() -> #N/A | AH47: =NA() -> #N/A | AI47: 2 | AK47: 44774 | AL47: =[1]Contributions!C298 -> 1.7465608 | AM47: =[1]Contributions!D298 -> 0.94803139 | AN47: =[1]Contributions!E298 -> 2.3144145 | AO47: =[1]Contributions!H298 -> 2.1423186 | AP47: =[1]Contributions!I298 -> 2.6325435 | AQ47: =[1]Contributions!G298 -> 9.8701878 | AR47: 2
A48: 42248 | B48: =HAVERM!K195 -> -2.259332 | C48: =((HAVERM!M189/HAVERM!M177)-1)*100 -> -6.0408922 | D48: =((HAVERM!R188/HAVERM!R176)-1)*100 -> -10.192027 | E48: 0 | S48: =+S43+7 -> 44988 | T48: Mar | U48: =IF('HAVER - UK Gas'!H1618="",C1330,AVERAGE('HAVER - UK Gas'!H1618:Q1618)) -> 125.857 | V48: =AVERAGE($U$39:$U$71,$U$73:$U$102) -> 136.05151 | AB48: =AVERAGE($U$39:$U$71,$U$73:$U$102) -> 136.05151 | AE48: 45170 | AF48: ='[1]CPI Forecast'!D338 -> 6.6521767 | AG48: =NA() -> #N/A | AH48: =NA() -> #N/A | AI48: 2 | AK48: 44805 | AL48: =[1]Contributions!C299 -> 1.9079219 | AM48: =[1]Contributions!D299 -> 0.78477966 | AN48: =[1]Contributions!E299 -> 2.3249747 | AO48: =[1]Contributions!H299 -> 2.2615211 | AP48: =[1]Contributions!I299 -> 2.7012317 | AQ48: =[1]Contributions!G299 -> 10.095628 | AR48: 2
A49: 42278 | B49: =HAVERM!K196 -> -2.747792 | C49: =((HAVERM!M190/HAVERM!M178)-1)*100 -> -5.027933 | D49: =((HAVERM!R189/HAVERM!R177)-1)*100 -> -12.988435 | E49: 0 | S49: =+S44+7 -> 44991 | T49: Mar | U49: =IF('HAVER - UK Gas'!H1619="",C1331,AVERAGE('HAVER - UK Gas'!H1619:Q1619)) -> 128.087 | V49: =AVERAGE($U$39:$U$71,$U$73:$U$102) -> 136.05151 | AB49: =AVERAGE($U$39:$U$71,$U$73:$U$102) -> 136.05151 | AE49: 45200 | AF49: ='[1]CPI Forecast'!D339 -> 4.599878 | AG49: =NA() -> #N/A | AH49: =NA() -> #N/A | AI49: 2 | AK49: 44835 | AL49: =[1]Contributions!C300 -> 2.1135987 | AM49: =[1]Contributions!D300 -> 0.66630379 | AN49: =[1]Contributions!E300 -> 3.2486699 | AO49: =[1]Contributions!H300 -> 2.1449253 | AP49: =[1]Contributions!I300 -> 2.7549711 | AQ49: =[1]Contributions!G300 -> 11.051566 | AR49: 2
A50: 42309 | B50: =HAVERM!K197 -> -2.4582104 | C50: =((HAVERM!M191/HAVERM!M179)-1)*100 -> -6.0296846 | D50: =((HAVERM!R190/HAVERM!R178)-1)*100 -> -14.059448 | E50: 0 | S50: =+S45+7 -> 44992 | T50: Mar | U50: =IF('HAVER - UK Gas'!H1620="",C1332,AVERAGE('HAVER - UK Gas'!H1620:Q1620)) -> 127.054 | V50: =AVERAGE($U$39:$U$71,$U$73:$U$102) -> 136.05151 | AB50: =AVERAGE($U$39:$U$71,$U$73:$U$102) -> 136.05151 | AE50: 45231 | AF50: ='[1]CPI Forecast'!D340 -> 3.9409917 | AG50: =NA() -> #N/A | AH50: =NA() -> #N/A | AI50: 2 | AK50: 44866 | AL50: =[1]Contributions!C301 -> 2.0667528 | AM50: =[1]Contributions!D301 -> 0.5365614 | AN50: =[1]Contributions!E301 -> 3.2070765 | AO50: =[1]Contributions!H301 -> 2.0132669 | AP50: =[1]Contributions!I301 -> 2.7733783 | AQ50: =[1]Contributions!G301 -> 10.672013 | AR50: 2
A51: 42339 | B51: =HAVERM!K198 -> -2.9411765 | C51: =((HAVERM!M192/HAVERM!M180)-1)*100 -> -5.5765595 | D51: =((HAVERM!R191/HAVERM!R179)-1)*100 -> -14.307769 | E51: 0 | S51: =+S46+7 -> 44993 | T51: Mar | U51: =IF('HAVER - UK Gas'!H1621="",C1333,AVERAGE('HAVER - UK Gas'!H1621:Q1621)) -> 129.555 | V51: =AVERAGE($U$39:$U$71,$U$73:$U$102) -> 136.05151 | AB51: =AVERAGE($U$39:$U$71,$U$73:$U$102) -> 136.05151 | AE51: 45261 | AF51: ='[1]CPI Forecast'!D341 -> 3.9932685 | AG51: =NA() -> #N/A | AH51: =NA() -> #N/A | AI51: 2 | AK51: 44896 | AL51: =[1]Contributions!C302 -> 2.1065514 | AM51: =[1]Contributions!D302 -> 0.35582401 | AN51: =[1]Contributions!E302 -> 3.1797054 | AO51: =[1]Contributions!H302 -> 1.827357 | AP51: =[1]Contributions!I302 -> 2.9876384 | AQ51: =[1]Contributions!G302 -> 10.528374 | AR51: 2
A52: 42370 | B52: =HAVERM!K199 -> -2.6653504 | C52: =((HAVERM!M193/HAVERM!M181)-1)*100 -> -4.5977011 | D52: =((HAVERM!R192/HAVERM!R180)-1)*100 -> -13.9825 | E52: 0 | S52: =+S47+7 -> 44994 | T52: Mar | U52: =IF('HAVER - UK Gas'!H1622="",C1334,AVERAGE('HAVER - UK Gas'!H1622:Q1622)) -> 151.161 | V52: =AVERAGE($U$39:$U$71,$U$73:$U$102) -> 136.05151 | AB52: =AVERAGE($U$39:$U$71,$U$73:$U$102) -> 136.05151 | AE52: 45292 | AF52: ='[1]CPI Forecast'!D342 -> 3.9811146 | AG52: ='BoE feb MPR'!M55 -> 4.1 | AH52: =NA() -> #N/A | AI52: 2 | AK52: 44927 | AL52: =[1]Contributions!C303 -> 2.1520071 | AM52: =[1]Contributions!D303 -> 0.24010736 | AN52: =[1]Contributions!E303 -> 3.2205953 | AO52: =[1]Contributions!H303 -> 1.6568701 | AP52: =[1]Contributions!I303 -> 2.5734816 | AQ52: =[1]Contributions!G303 -> 10.051524 | AR52: 2
A53: 42401 | B53: =HAVERM!K200 -> -2.1782178 | C53: =((HAVERM!M194/HAVERM!M182)-1)*100 -> -4.1788144 | D53: =((HAVERM!R193/HAVERM!R181)-1)*100 -> -11.605048 | E53: 0 | S53: =+S48+7 -> 44995 | T53: Mar | U53: =IF('HAVER - UK Gas'!H1623="",C1335,AVERAGE('HAVER - UK Gas'!H1623:Q1623)) -> 143.818 | V53: =AVERAGE($U$39:$U$71,$U$73:$U$102) -> 136.05151 | AB53: =AVERAGE($U$39:$U$71,$U$73:$U$102) -> 136.05151 | AE53: 45323 | AF53: ='[1]CPI Forecast'!D343 -> 3.4114722 | AG53: ='BoE feb MPR'!M56 -> 3.5 | AH53: =NA() -> #N/A | AI53: 2 | AK53: 44958 | AL53: =[1]Contributions!C304 -> 2.3612304 | AM53: =[1]Contributions!D304 -> 0.14299417 | AN53: =[1]Contributions!E304 -> 3.1758564 | AO53: =[1]Contributions!H304 -> 1.576944 | AP53: =[1]Contributions!I304 -> 2.94457 | AQ53: =[1]Contributions!G304 -> 10.416397 | AR53: 2
A54: 42430 | B54: =HAVERM!K201 -> -2.7750248 | C54: =((HAVERM!M195/HAVERM!M183)-1)*100 -> -3.3366045 | D54: =((HAVERM!R194/HAVERM!R182)-1)*100 -> -14.324304 | E54: 0 | S54: =+S49+7 -> 44998 | T54: Mar | U54: =IF('HAVER - UK Gas'!H1624="",C1336,AVERAGE('HAVER - UK Gas'!H1624:Q1624)) -> 130.458 | V54: =AVERAGE($U$39:$U$71,$U$73:$U$102) -> 136.05151 | AB54: =AVERAGE($U$39:$U$71,$U$73:$U$102) -> 136.05151 | AE54: 45352 | AF54: ='[1]CPI Forecast'!D344 -> 2.9155194 | AG54: ='BoE feb MPR'!M57 -> 3.1 | AH54: =NA() -> #N/A | AI54: 2 | AK54: 44986 | AL54: =[1]Contributions!C305 -> 2.4411357 | AM54: =[1]Contributions!D305 -> -0.20459395 | AN54: =[1]Contributions!E305 -> 3.0813507 | AO54: =[1]Contributions!H305 -> 1.5759966 | AP54: =[1]Contributions!I305 -> 2.9850902 | AQ54: =[1]Contributions!G305 -> 10.056877 | AR54: 2
A55: 42461 | B55: =HAVERM!K202 -> -2.4875622 | C55: =((HAVERM!M196/HAVERM!M184)-1)*100 -> -3.1465093 | D55: =((HAVERM!R195/HAVERM!R183)-1)*100 -> -13.374511 | E55: 0 | S55: =+S50+7 -> 44999 | T55: Mar | U55: =IF('HAVER - UK Gas'!H1625="",C1337,AVERAGE('HAVER - UK Gas'!H1625:Q1625)) -> 126.638 | V55: =AVERAGE($U$39:$U$71,$U$73:$U$102) -> 136.05151 | AB55: =AVERAGE($U$39:$U$71,$U$73:$U$102) -> 136.05151 | AE55: 45383 | AF55: ='[1]CPI Forecast'!D345 -> 2.0297601 | AG55: ='BoE feb MPR'!M58 -> 2.1 | AH55: =NA() -> #N/A | AI55: 2 | AK55: 45017 | AL55: =[1]Contributions!C306 -> 2.5586967 | AM55: =[1]Contributions!D306 -> -0.30285561 | AN55: =[1]Contributions!E306 -> 1.2783364 | AO55: =[1]Contributions!H306 -> 1.8661178 | AP55: =[1]Contributions!I306 -> 3.1324463 | AQ55: =[1]Contributions!G306 -> 8.6582359 | AR55: 2
A56: 42491 | B56: =HAVERM!K203 -> -2.7888446 | C56: =((HAVERM!M197/HAVERM!M185)-1)*100 -> -3.2448378 | D56: =((HAVERM!R196/HAVERM!R184)-1)*100 -> -13.441064 | E56: 0 | S56: =+S51+7 -> 45000 | T56: Mar | U56: =IF('HAVER - UK Gas'!H1626="",C1338,AVERAGE('HAVER - UK Gas'!H1626:Q1626)) -> 131.245 | V56: =AVERAGE($U$39:$U$71,$U$73:$U$102) -> 136.05151 | AB56: =AVERAGE($U$39:$U$71,$U$73:$U$102) -> 136.05151 | AE56: 45413 | AF56: ='[1]CPI Forecast'!D346 -> 1.6038601 | AG56: ='BoE feb MPR'!M59 -> 1.9 | AH56: =NA() -> #N/A | AI56: 2 | AK56: 45047 | AL56: =[1]Contributions!C307 -> 2.4909984 | AM56: =[1]Contributions!D307 -> -0.45395927 | AN56: =[1]Contributions!E307 -> 1.2448054 | AO56: =[1]Contributions!H307 -> 1.9100659 | AP56: =[1]Contributions!I307 -> 3.3283139 | AQ56: =[1]Contributions!G307 -> 8.680682 | AR56: 2
A57: 42522 | B57: =HAVERM!K204 -> -2.994012 | C57: =((HAVERM!M198/HAVERM!M186)-1)*100 -> -3.5121951 | D57: =((HAVERM!R197/HAVERM!R185)-1)*100 -> -15.794444 | E57: 0 | S57: =+S52+7 -> 45001 | T57: Mar | U57: =IF('HAVER - UK Gas'!H1627="",C1339,AVERAGE('HAVER - UK Gas'!H1627:Q1627)) -> 127.982 | V57: =AVERAGE($U$39:$U$71,$U$73:$U$102) -> 136.05151 | AB57: =AVERAGE($U$39:$U$71,$U$73:$U$102) -> 136.05151 | AE57: 45444 | AF57: ='[1]CPI Forecast'!D347 -> 1.5718362 | AG57: ='BoE feb MPR'!M60 -> 1.9 | AH57: =NA() -> #N/A | AI57: 2 | AK57: 45078 | AL57: =[1]Contributions!C308 -> 2.370954 | AM57: =[1]Contributions!D308 -> -0.85127806 | AN57: =[1]Contributions!E308 -> 1.2190592 | AO57: =[1]Contributions!H308 -> 1.7108378 | AP57: =[1]Contributions!I308 -> 3.2932077 | AQ57: =[1]Contributions!G308 -> 7.9496843 | AR57: 2
A58: 42552 | B58: =HAVERM!K205 -> -2.6130653 | C58: =((HAVERM!M199/HAVERM!M187)-1)*100 -> -3.5433071 | D58: =((HAVERM!R198/HAVERM!R186)-1)*100 -> -13.010513 | E58: 0 | S58: =+S53+7 -> 45002 | T58: Mar | U58: =IF('HAVER - UK Gas'!H1628="",C1340,AVERAGE('HAVER - UK Gas'!H1628:Q1628)) -> 119.659 | V58: =AVERAGE($U$39:$U$71,$U$73:$U$102) -> 136.05151 | AB58: =AVERAGE($U$39:$U$71,$U$73:$U$102) -> 136.05151 | AE58: 45474 | AF58: ='[1]CPI Forecast'!D348 -> 1.7040227 | AG58: =NA() -> #N/A | AH58: =NA() -> #N/A | AI58: 2 | AK58: 45108 | AL58: =[1]Contributions!C309 -> 2.1319448 | AM58: =[1]Contributions!D309 -> -0.95530577 | AN58: =[1]Contributions!E309 -> 0.45415535 | AO58: =[1]Contributions!H309 -> 1.5060451 | AP58: =[1]Contributions!I309 -> 3.4625865 | AQ58: =[1]Contributions!G309 -> 6.8272142 | AR58: 2
A59: 42583 | B59: =HAVERM!K206 -> -2.2110553 | C59: =((HAVERM!M200/HAVERM!M188)-1)*100 -> -3.0541872 | D59: =((HAVERM!R199/HAVERM!R187)-1)*100 -> -10.556902 | E59: 0 | S59: =+S54+7 -> 45005 | T59: Mar | U59: =IF('HAVER - UK Gas'!H1629="",C1341,AVERAGE('HAVER - UK Gas'!H1629:Q1629)) -> 127.785 | V59: =AVERAGE($U$39:$U$71,$U$73:$U$102) -> 136.05151 | AB59: =AVERAGE($U$39:$U$71,$U$73:$U$102) -> 136.05151 | AE59: 45505 | AF59: ='[1]CPI Forecast'!D349 -> 1.7316836 | AG59: =NA() -> #N/A | AH59: ='BoE feb MPR'!P13 -> 2.2 | AI59: 2 | AK59: 45139 | AL59: =[1]Contributions!C310 -> 2.0321916 | AM59: =[1]Contributions!D310 -> -0.58232633 | AN59: =[1]Contributions!E310 -> 0.4836433 | AO59: =[1]Contributions!H310 -> 1.346194 | AP59: =[1]Contributions!I310 -> 3.1664388 | AQ59: =[1]Contributions!G310 -> 6.6570306 | AR59: 2
A60: 42614 | B60: =HAVERM!K207 -> -2.2110553 | C60: =((HAVERM!M201/HAVERM!M189)-1)*100 -> -3.066271 | D60: =((HAVERM!R200/HAVERM!R188)-1)*100 -> -6.3540742 | E60: 0 | S60: =+S55+7 -> 45006 | T60: Mar | U60: =IF('HAVER - UK Gas'!H1630="",C1342,AVERAGE('HAVER - UK Gas'!H1630:Q1630)) -> 122.972 | V60: =AVERAGE($U$39:$U$71,$U$73:$U$102) -> 136.05151 | AB60: =AVERAGE($U$39:$U$71,$U$73:$U$102) -> 136.05151 | AE60: 45536 | AF60: ='[1]CPI Forecast'!D350 -> 1.3629174 | AG60: =NA() -> #N/A | AH60: =NA() -> #N/A | AI60: 2 | AK60: 45170 | AL60: =[1]Contributions!C311 -> 1.89678 | AM60: =[1]Contributions!D311 -> -0.32772239 | AN60: =[1]Contributions!E311 -> 0.4661035 | AO60: =[1]Contributions!H311 -> 1.1996142 | AP60: =[1]Contributions!I311 -> 3.2350993 | AQ60: =[1]Contributions!G311 -> 6.6521767 | AR60: 2
A61: 42644 | B61: =HAVERM!K208 -> -2.320888 | C61: =((HAVERM!M202/HAVERM!M190)-1)*100 -> -3.9215686 | D61: =((HAVERM!R201/HAVERM!R189)-1)*100 -> -4.4039322 | E61: 0 | S61: =+S56+7 -> 45007 | T61: Mar | U61: =IF('HAVER - UK Gas'!H1631="",C1343,AVERAGE('HAVER - UK Gas'!H1631:Q1631)) -> 129.766 | V61: =AVERAGE($U$39:$U$71,$U$73:$U$102) -> 136.05151 | AB61: =AVERAGE($U$39:$U$71,$U$73:$U$102) -> 136.05151 | AE61: 45566 | AF61: ='[1]CPI Forecast'!D351 -> 1.559808 | AG61: =NA() -> #N/A | AH61: =NA() -> #N/A | AI61: 2 | AK61: 45200 | AL61: =[1]Contributions!C312 -> 1.6436973 | AM61: =[1]Contributions!D312 -> -0.25102589 | AN61: =[1]Contributions!E312 -> -1.0520086 | AO61: =[1]Contributions!H312 -> 1.056636 | AP61: =[1]Contributions!I312 -> 3.0549416 | AQ61: =[1]Contributions!G312 -> 4.599878 | AR61: 2
A62: 42675 | B62: =HAVERM!K209 -> -2.016129 | C62: =((HAVERM!M203/HAVERM!M191)-1)*100 -> -1.3820336 | D62: =((HAVERM!R202/HAVERM!R190)-1)*100 -> -0.22251186 | E62: 0 | S62: =+S57+7 -> 45008 | T62: Mar | U62: =IF('HAVER - UK Gas'!H1632="",C1344,AVERAGE('HAVER - UK Gas'!H1632:Q1632)) -> 126.225 | V62: =AVERAGE($U$39:$U$71,$U$73:$U$102) -> 136.05151 | AB62: =AVERAGE($U$39:$U$71,$U$73:$U$102) -> 136.05151 | AE62: 45597 | AF62: ='[1]CPI Forecast'!D352 -> 1.9150914 | AG62: =NA() -> #N/A | AH62: ='BoE feb MPR'!P14 -> 2.7 | AI62: 2 | AK62: 45231 | AL62: =[1]Contributions!C313 -> 1.5006795 | AM62: =[1]Contributions!D313 -> -0.35294412 | AN62: =[1]Contributions!E313 -> -1.043622 | AO62: =[1]Contributions!H313 -> 0.75839564 | AP62: =[1]Contributions!I313 -> 2.9000661 | AQ62: =[1]Contributions!G313 -> 3.9409917 | AR62: 2
A63: 42705 | B63: =HAVERM!K210 -> -1.1111111 | C63: =((HAVERM!M204/HAVERM!M192)-1)*100 -> 0.5005005 | D63: =((HAVERM!R203/HAVERM!R191)-1)*100 -> 2.751578 | E63: 0 | S63: =+S58+7 -> 45009 | T63: Mar | U63: =IF('HAVER - UK Gas'!H1633="",C1345,AVERAGE('HAVER - UK Gas'!H1633:Q1633)) -> 127.869 | V63: =AVERAGE($U$39:$U$71,$U$73:$U$102) -> 136.05151 | AB63: =AVERAGE($U$39:$U$71,$U$73:$U$102) -> 136.05151 | AE63: 45627 | AF63: ='[1]CPI Forecast'!D353 -> 1.901294 | AG63: =NA() -> #N/A | AH63: =NA() -> #N/A | AI63: 2 | AK63: 45261 | AL63: =[1]Contributions!C314 -> 1.4874908 | AM63: =[1]Contributions!D314 -> -0.34411789 | AN63: =[1]Contributions!E314 -> -1.0308184 | AO63: =[1]Contributions!H314 -> 0.61086738 | AP63: =[1]Contributions!I314 -> 3.0381605 | AQ63: =[1]Contributions!G314 -> 3.9932685 | AR63: 2
A64: 42736 | B64: =HAVERM!K211 -> -0.50709939 | C64: =((HAVERM!M205/HAVERM!M193)-1)*100 -> 1.4056225 | D64: =((HAVERM!R204/HAVERM!R192)-1)*100 -> 8.755313 | E64: 0 | S64: =+S59+7 -> 45012 | T64: Mar | U64: =IF('HAVER - UK Gas'!H1634="",C1346,AVERAGE('HAVER - UK Gas'!H1634:Q1634)) -> 129.182 | V64: =AVERAGE($U$39:$U$71,$U$73:$U$102) -> 136.05151 | AB64: =AVERAGE($U$39:$U$71,$U$73:$U$102) -> 136.05151 | AE64: 45658 | AF64: ='[1]CPI Forecast'!D354 -> 2.0604283 | AG64: =NA() -> #N/A | AH64: =NA() -> #N/A | AI64: 2 | AK64: 45292 | AL64: =[1]Contributions!C315 -> 1.3156028 | AM64: =[1]Contributions!D315 -> -0.29380783 | AN64: =[1]Contributions!E315 -> -0.88050955 | AO64: =[1]Contributions!H315 -> 0.57639331 | AP64: =[1]Contributions!I315 -> 3.0293215 | AQ64: =[1]Contributions!G315 -> 3.9811146 | AR64: 2
A65: 42767 | B65: =HAVERM!K212 -> 0.10121457 | C65: =((HAVERM!M206/HAVERM!M194)-1)*100 -> 3.0425963 | D65: =((HAVERM!R205/HAVERM!R193)-1)*100 -> 17.403239 | E65: 0 | S65: =+S60+7 -> 45013 | T65: Mar | U65: =IF('HAVER - UK Gas'!H1635="",C1347,AVERAGE('HAVER - UK Gas'!H1635:Q1635)) -> 129.078 | V65: =AVERAGE($U$39:$U$71,$U$73:$U$102) -> 136.05151 | AB65: =AVERAGE($U$39:$U$71,$U$73:$U$102) -> 136.05151 | AE65: 45689 | AF65: ='[1]CPI Forecast'!D355 -> 1.8319809 | AG65: =NA() -> #N/A | AH65: ='BoE feb MPR'!P15 -> 2.8 | AI65: 2 | AK65: 45323 | AL65: =[1]Contributions!C316 -> 1.0753215 | AM65: =[1]Contributions!D316 -> -0.18962054 | AN65: =[1]Contributions!E316 -> -0.87802559 | AO65: =[1]Contributions!H316 -> 0.38782074 | AP65: =[1]Contributions!I316 -> 2.8362795 | AQ65: =[1]Contributions!G316 -> 3.4114722 | AR65: 2
A66: 42795 | B66: =HAVERM!K213 -> 1.2232416 | C66: =((HAVERM!M207/HAVERM!M195)-1)*100 -> 3.7563452 | D66: =((HAVERM!R206/HAVERM!R194)-1)*100 -> 24.99237 | E66: 0 | S66: =+S61+7 -> 45014 | T66: Mar | U66: =IF('HAVER - UK Gas'!H1636="",C1348,AVERAGE('HAVER - UK Gas'!H1636:Q1636)) -> 134.123 | V66: =AVERAGE($U$39:$U$71,$U$73:$U$102) -> 136.05151 | AB66: =AVERAGE($U$39:$U$71,$U$73:$U$102) -> 136.05151 | AE66: 45717 | AF66: ='[1]CPI Forecast'!D356 -> 1.7733227 | AG66: =NA() -> #N/A | AH66: =NA() -> #N/A | AI66: 2 | AK66: 45352 | AL66: =[1]Contributions!C317 -> 0.88153525 | AM66: =[1]Contributions!D317 -> -0.093228123 | AN66: =[1]Contributions!E317 -> -0.86082301 | AO66: =[1]Contributions!H317 -> 0.19998488 | AP66: =[1]Contributions!I317 -> 2.5661336 | AQ66: =[1]Contributions!G317 -> 2.9155194 | AR66: 2
A67: 42826 | B67: =HAVERM!K214 -> 1.5306122 | C67: =((HAVERM!M208/HAVERM!M196)-1)*100 -> 5.3807107 | D67: =((HAVERM!R207/HAVERM!R195)-1)*100 -> 25.923179 | E67: 0 | S67: =+S62+7 -> 45015 | T67: Mar | U67: =IF('HAVER - UK Gas'!H1637="",C1349,AVERAGE('HAVER - UK Gas'!H1637:Q1637)) -> 146.271 | V67: =AVERAGE($U$39:$U$71,$U$73:$U$102) -> 136.05151 | AB67: =AVERAGE($U$39:$U$71,$U$73:$U$102) -> 136.05151 | AE67: 45748 | AF67: ='[1]CPI Forecast'!D357 -> 1.9096954 | AG67: =NA() -> #N/A | AH67: =NA() -> #N/A | AI67: 2 | AK67: 45383 | AL67: =[1]Contributions!C318 -> 0.60078925 | AM67: =[1]Contributions!D318 -> -0.044433995 | AN67: =[1]Contributions!E318 -> -1.2770267 | AO67: =[1]Contributions!H318 -> 0.087568599 | AP67: =[1]Contributions!I318 -> 2.4617764 | AQ67: =[1]Contributions!G318 -> 2.0297601 | AR67: 2
A68: 42856 | B68: =HAVERM!K215 -> 2.0491803 | C68: =((HAVERM!M209/HAVERM!M197)-1)*100 -> 6.402439 | D68: =((HAVERM!R208/HAVERM!R196)-1)*100 -> 31.981924 | E68: 0 | S68: =+S63+7 -> 45016 | T68: Mar | U68: =IF('HAVER - UK Gas'!H1638="",C1350,AVERAGE('HAVER - UK Gas'!H1638:Q1638)) -> 159.284 | V68: =AVERAGE($U$39:$U$71,$U$73:$U$102) -> 136.05151 | AB68: =AVERAGE($U$39:$U$71,$U$73:$U$102) -> 136.05151 | AE68: 45778 | AF68: ='[1]CPI Forecast'!D358 -> 1.9361585 | AG68: =NA() -> #N/A | AH68: ='BoE feb MPR'!P16 -> 2.7 | AI68: 2 | AK68: 45413 | AL68: =[1]Contributions!C319 -> 0.46378953 | AM68: =[1]Contributions!D319 -> 0.0048591644 | AN68: =[1]Contributions!E319 -> -1.2601637 | AO68: =[1]Contributions!H319 -> -0.031227093 | AP68: =[1]Contributions!I319 -> 2.2384287 | AQ68: =[1]Contributions!G319 -> 1.6038601 | AR68: 2
A69: 42887 | B69: =HAVERM!K216 -> 2.2633745 | C69: =((HAVERM!M210/HAVERM!M198)-1)*100 -> 6.471183 | D69: =((HAVERM!R209/HAVERM!R197)-1)*100 -> 33.478834 | E69: 0 | S69: =+S64+7 -> 45019 | T69: Apr | U69: =IF('HAVER - UK Gas'!H1639="",C1351,AVERAGE('HAVER - UK Gas'!H1639:Q1639)) -> 149.336 | V69: =AVERAGE($U$39:$U$71,$U$73:$U$102) -> 136.05151 | AB69: =AVERAGE($U$39:$U$71,$U$73:$U$102) -> 136.05151 | AE69: 45809 | AF69: ='[1]CPI Forecast'!D359 -> 1.9433044 | AG69: =NA() -> #N/A | AH69: =NA() -> #N/A | AI69: 2 | AK69: 45444 | AL69: =[1]Contributions!C320 -> 0.39425575 | AM69: =[1]Contributions!D320 -> 0.078194725 | AN69: =[1]Contributions!E320 -> -1.2567736 | AO69: =[1]Contributions!H320 -> 0.089678149 | AP69: =[1]Contributions!I320 -> 2.1298571 | AQ69: =[1]Contributions!G320 -> 1.5718362 | AR69: 2
A70: 42917 | B70: =HAVERM!K217 -> 2.5799794 | C70: =((HAVERM!M211/HAVERM!M199)-1)*100 -> 7.3469388 | D70: =((HAVERM!R210/HAVERM!R198)-1)*100 -> 30.59426 | E70: 0 | S70: =+S65+7 -> 45020 | T70: Apr | U70: =IF('HAVER - UK Gas'!H1640="",C1352,AVERAGE('HAVER - UK Gas'!H1640:Q1640)) -> 141.783 | V70: =AVERAGE($U$39:$U$71,$U$73:$U$102) -> 136.05151 | AB70: =AVERAGE($U$39:$U$71,$U$73:$U$102) -> 136.05151 | AE70: 45839 | AF70: ='[1]CPI Forecast'!D360 -> 2.3054746 | AG70: =NA() -> #N/A | AH70: =NA() -> #N/A | AI70: 2 | AK70: 45474 | AL70: =[1]Contributions!C321 -> 0.33432148 | AM70: =[1]Contributions!D321 -> 0.063960479 | AN70: =[1]Contributions!E321 -> -0.8689725 | AO70: =[1]Contributions!H321 -> 0.06903024 | AP70: =[1]Contributions!I321 -> 1.9650482 | AQ70: =[1]Contributions!G321 -> 1.7040227 | AR70: 2
A71: 42948 | B71: =HAVERM!K218 -> 2.1582734 | C71: =((HAVERM!M212/HAVERM!M200)-1)*100 -> 7.1138211 | D71: =((HAVERM!R211/HAVERM!R199)-1)*100 -> 34.676282 | E71: 0 | S71: =+S66+7 -> 45021 | T71: Apr | U71: =IF('HAVER - UK Gas'!H1641="",C1353,AVERAGE('HAVER - UK Gas'!H1641:Q1641)) -> 138.187 | V71: =AVERAGE($U$39:$U$71,$U$73:$U$102) -> 136.05151 | AB71: =AVERAGE($U$39:$U$71,$U$73:$U$102) -> 136.05151 | AE71: 45870 | AF71: ='[1]CPI Forecast'!D361 -> 2.3261068 | AG71: =NA() -> #N/A | AH71: ='BoE feb MPR'!P17 -> 2.7 | AI71: 2 | AK71: 45505 | AL71: =[1]Contributions!C322 -> 0.2603127 | AM71: =[1]Contributions!D322 -> -0.052736165 | AN71: =[1]Contributions!E322 -> -0.8782653 | AO71: =[1]Contributions!H322 -> 0.12403503 | AP71: =[1]Contributions!I322 -> 2.1425547 | AQ71: =[1]Contributions!G322 -> 1.7316836 | AR71: 2
A72: 42979 | B72: =HAVERM!K219 -> 2.9804728 | C72: =((HAVERM!M213/HAVERM!M201)-1)*100 -> 8.2653061 | D72: =((HAVERM!R212/HAVERM!R200)-1)*100 -> 30.568203 | E72: 0 | S72: =+S67+7 -> 45022 | T72: Apr | U72: =NA() -> #N/A | V72: =AVERAGE($U$39:$U$71,$U$73:$U$102) -> 136.05151 | AB72: =AVERAGE($U$39:$U$71,$U$73:$U$102) -> 136.05151 | AE72: 45901 | AF72: ='[1]CPI Forecast'!D362 -> 2.308454 | AG72: =NA() -> #N/A | AH72: =NA() -> #N/A | AI72: 2 | AK72: 45536 | AL72: =[1]Contributions!C323 -> 0.22352059 | AM72: =[1]Contributions!D323 -> -0.17049712 | AN72: =[1]Contributions!E323 -> -0.8799877 | AO72: =[1]Contributions!H323 -> 0.18287244 | AP72: =[1]Contributions!I323 -> 1.8883809 | AQ72: =[1]Contributions!G323 -> 1.3629174 | AR72: 2
A73: 43009 | B73: =HAVERM!K220 -> 3.9256198 | C73: =((HAVERM!M214/HAVERM!M202)-1)*100 -> 8.6734694 | D73: =((HAVERM!R213/HAVERM!R201)-1)*100 -> 27.503662 | E73: 0 | S73: =+S68+7 -> 45023 | T73: Apr | U73: =IF('HAVER - UK Gas'!H1643="",C1355,AVERAGE('HAVER - UK Gas'!H1643:Q1643)) -> 138.187 | V73: =AVERAGE($U$39:$U$71,$U$73:$U$102) -> 136.05151 | AB73: =AVERAGE($U$39:$U$71,$U$73:$U$102) -> 136.05151 | AE73: 45931 | AF73: ='[1]CPI Forecast'!D363 -> 2.3241947 | AG73: =NA() -> #N/A | AH73: =NA() -> #N/A | AI73: 2 | AK73: 45566 | AL73: =[1]Contributions!C324 -> 0.21060091 | AM73: =[1]Contributions!D324 -> -0.23295843 | AN73: =[1]Contributions!E324 -> -0.58664448 | AO73: =[1]Contributions!H324 -> 0.1627406 | AP73: =[1]Contributions!I324 -> 1.8607724 | AQ73: =[1]Contributions!G324 -> 1.559808 | AR73: 2
A74: 43040 | B74: =HAVERM!K221 -> 4.0123457 | C74: =((HAVERM!M215/HAVERM!M203)-1)*100 -> 8.1081081 | D74: =((HAVERM!R214/HAVERM!R202)-1)*100 -> 22.039457 | E74: 0 | S74: =+S69+7 -> 45026 | T74: Apr | U74: =IF('HAVER - UK Gas'!H1644="",C1356,AVERAGE('HAVER - UK Gas'!H1644:Q1644)) -> 142.831 | V74: =AVERAGE($U$39:$U$71,$U$73:$U$102) -> 136.05151 | AB74: =AVERAGE($U$39:$U$71,$U$73:$U$102) -> 136.05151 | AE74: 45962 | AF74: ='[1]CPI Forecast'!D364 -> 2.3407318 | AG74: =NA() -> #N/A | AH74: ='BoE feb MPR'!P18 -> 2.5 | AI74: 2 | AK74: 45597 | AL74: =[1]Contributions!C325 -> 0.21617074 | AM74: =[1]Contributions!D325 -> -0.17326057 | AN74: =[1]Contributions!E325 -> -0.58213677 | AO74: =[1]Contributions!H325 -> 0.37510977 | AP74: =[1]Contributions!I325 -> 1.92415 | AQ74: =[1]Contributions!G325 -> 1.9150914 | AR74: 2
A75: 43070 | B75: =HAVERM!K222 -> 3.9836568 | C75: =((HAVERM!M216/HAVERM!M204)-1)*100 -> 7.6693227 | D75: =((HAVERM!R215/HAVERM!R203)-1)*100 -> 21.113982 | E75: 0 | S75: =+S70+7 -> 45027 | T75: Apr | U75: =IF('HAVER - UK Gas'!H1645="",C1357,AVERAGE('HAVER - UK Gas'!H1645:Q1645)) -> 144.473 | V75: =AVERAGE($U$39:$U$71,$U$73:$U$102) -> 136.05151 | AB75: =AVERAGE($U$39:$U$71,$U$73:$U$102) -> 136.05151 | AE75: 45992 | AF75: ='[1]CPI Forecast'!D365 -> 2.3763204 | AG75: =NA() -> #N/A | AH75: =NA() -> #N/A | AI75: 2 | AK75: 45627 | AL75: =[1]Contributions!C326 -> 0.14148959 | AM75: =[1]Contributions!D326 -> -0.036577817 | AN75: =[1]Contributions!E326 -> -0.5758072 | AO75: =[1]Contributions!H326 -> 0.49808151 | AP75: =[1]Contributions!I326 -> 1.756196 | AQ75: =[1]Contributions!G326 -> 1.901294 | AR75: 2
A76: 43101 | B76: =HAVERM!K223 -> 3.6697248 | C76: =((HAVERM!M217/HAVERM!M205)-1)*100 -> 6.8316832 | D76: =((HAVERM!R216/HAVERM!R204)-1)*100 -> 15.857764 | E76: 0 | S76: =+S71+7 -> 45028 | T76: Apr | U76: =IF('HAVER - UK Gas'!H1646="",C1358,AVERAGE('HAVER - UK Gas'!H1646:Q1646)) -> 142.642 | V76: =AVERAGE($U$39:$U$71,$U$73:$U$102) -> 136.05151 | AB76: =AVERAGE($U$39:$U$71,$U$73:$U$102) -> 136.05151 | AE76: 46023 | AF76: ='[1]CPI Forecast'!D366 -> 2.3970724 | AG76: =NA() -> #N/A | AH76: =NA() -> #N/A | AI76: 2 | AK76: 45658 | AL76: =[1]Contributions!C327 -> 0.16560963 | AM76: =[1]Contributions!D327 -> 0.011831372 | AN76: =[1]Contributions!E327 -> -0.72101564 | AO76: =[1]Contributions!H327 -> 0.50333077 | AP76: =[1]Contributions!I327 -> 2.1167158 | AQ76: =[1]Contributions!G327 -> 2.0604283 | AR76: 2
A77: 43132 | B77: =HAVERM!K224 -> 3.033367 | C77: =((HAVERM!M218/HAVERM!M206)-1)*100 -> 6.3976378 | D77: =((HAVERM!R217/HAVERM!R205)-1)*100 -> 8.9560415 | E77: 0 | S77: =+S72+7 -> 45029 | T77: Apr | U77: =IF('HAVER - UK Gas'!H1647="",C1359,AVERAGE('HAVER - UK Gas'!H1647:Q1647)) -> 142.23 | V77: =AVERAGE($U$39:$U$71,$U$73:$U$102) -> 136.05151 | AB77: =AVERAGE($U$39:$U$71,$U$73:$U$102) -> 136.05151 | AE77: 46054 | AF77: ='[1]CPI Forecast'!D367 -> 2.3983852 | AG77: =NA() -> #N/A | AH77: ='BoE feb MPR'!P19 -> 2.3 | AI77: 2 | AK77: 45689 | AL77: =[1]Contributions!C328 -> 0.19258786 | AM77: =[1]Contributions!D328 -> -0.04809876 | AN77: =[1]Contributions!E328 -> -0.76280515 | AO77: =[1]Contributions!H328 -> 0.52688429 | AP77: =[1]Contributions!I328 -> 1.91928 | AQ77: =[1]Contributions!G328 -> 1.8319809 | AR77: 2
A78: 43160 | B78: =HAVERM!K225 -> 3.021148 | C78: =((HAVERM!M219/HAVERM!M207)-1)*100 -> 5.5772994 | D78: =((HAVERM!R218/HAVERM!R206)-1)*100 -> 4.0554908 | E78: 0 | S78: =+S73+7 -> 45030 | T78: Apr | U78: =IF('HAVER - UK Gas'!H1648="",C1360,AVERAGE('HAVER - UK Gas'!H1648:Q1648)) -> 141.458 | V78: =AVERAGE($U$39:$U$71,$U$73:$U$102) -> 136.05151 | AB78: =AVERAGE($U$39:$U$71,$U$73:$U$102) -> 136.05151 | AE78: 46082 | AF78: ='[1]CPI Forecast'!D368 -> 2.3840755 | AG78: =NA() -> #N/A | AH78: =NA() -> #N/A | AI78: 2 | AK78: 45717 | AL78: =[1]Contributions!C329 -> 0.18017431 | AM78: =[1]Contributions!D329 -> -0.1133425 | AN78: =[1]Contributions!E329 -> -0.76294401 | AO78: =[1]Contributions!H329 -> 0.53455075 | AP78: =[1]Contributions!I329 -> 1.941497 | AQ78: =[1]Contributions!G329 -> 1.7733227 | AR78: 2
A79: 43191 | B79: =HAVERM!K226 -> 2.6130653 | C79: =((HAVERM!M220/HAVERM!M208)-1)*100 -> 4.4315992 | D79: =((HAVERM!R219/HAVERM!R207)-1)*100 -> 2.5324013 | E79: 0 | S79: =+S74+7 -> 45033 | T79: Apr | U79: =IF('HAVER - UK Gas'!H1649="",C1361,AVERAGE('HAVER - UK Gas'!H1649:Q1649)) -> 143.176 | V79: =AVERAGE($U$39:$U$71,$U$73:$U$102) -> 136.05151 | AB79: =AVERAGE($U$39:$U$71,$U$73:$U$102) -> 136.05151 | AE79: 46113 | AF79: ='[1]CPI Forecast'!D369 -> 2.3650274 | AG79: =NA() -> #N/A | AH79: =NA() -> #N/A | AI79: 2 | AK79: 45748 | AL79: =[1]Contributions!C330 -> 0.18690903 | AM79: =[1]Contributions!D330 -> -0.12556339 | AN79: =[1]Contributions!E330 -> -0.27837861 | AO79: =[1]Contributions!H330 -> 0.41677735 | AP79: =[1]Contributions!I330 -> 1.6869565 | AQ79: =[1]Contributions!G330 -> 1.9096954 | AR79: 2
A80: 43221 | B80: =HAVERM!K227 -> 2.3092369 | C80: =((HAVERM!M221/HAVERM!M209)-1)*100 -> 4.3935053 | D80: =((HAVERM!R220/HAVERM!R208)-1)*100 -> -3.6528464 | E80: 0 | S80: =+S75+7 -> 45034 | T80: Apr | U80: =IF('HAVER - UK Gas'!H1650="",C1362,AVERAGE('HAVER - UK Gas'!H1650:Q1650)) -> 138.951 | V80: =AVERAGE($U$39:$U$71,$U$73:$U$102) -> 136.05151 | AB80: =AVERAGE($U$39:$U$71,$U$73:$U$102) -> 136.05151 | AE80: 46143 | AF80: ='[1]CPI Forecast'!D370 -> 2.3528568 | AG80: =NA() -> #N/A | AH80: ='BoE feb MPR'!P20 -> 2.2 | AI80: 2 | AK80: 45778 | AL80: =[1]Contributions!C331 -> 0.2022577 | AM80: =[1]Contributions!D331 -> -0.10805872 | AN80: =[1]Contributions!E331 -> -0.27794249 | AO80: =[1]Contributions!H331 -> 0.41159675 | AP80: =[1]Contributions!I331 -> 1.6851521 | AQ80: =[1]Contributions!G331 -> 1.9361585 | AR80: 2
A81: 43252 | B81: =HAVERM!K228 -> 2.0120724 | C81: =((HAVERM!M222/HAVERM!M210)-1)*100 -> 4.368471 | D81: =((HAVERM!R221/HAVERM!R209)-1)*100 -> -2.9211302 | E81: 0 | S81: =+S76+7 -> 45035 | T81: Apr | U81: =IF('HAVER - UK Gas'!H1651="",C1363,AVERAGE('HAVER - UK Gas'!H1651:Q1651)) -> 138.355 | V81: =AVERAGE($U$39:$U$71,$U$73:$U$102) -> 136.05151 | AB81: =AVERAGE($U$39:$U$71,$U$73:$U$102) -> 136.05151 | AE81: 46174 | AF81: ='[1]CPI Forecast'!D371 -> 2.3596478 | AG81: =NA() -> #N/A | AH81: =NA() -> #N/A | AI81: 2 | AK81: 45809 | AL81: =[1]Contributions!C332 -> 0.21222839 | AM81: =[1]Contributions!D332 -> -0.10854842 | AN81: =[1]Contributions!E332 -> -0.27733232 | AO81: =[1]Contributions!H332 -> 0.40565169 | AP81: =[1]Contributions!I332 -> 1.6857466 | AQ81: =[1]Contributions!G332 -> 1.9433044 | AR81: 2
A82: 43282 | B82: =HAVERM!K229 -> 2.3138833 | C82: =((HAVERM!M223/HAVERM!M211)-1)*100 -> 3.4220532 | D82: =((HAVERM!R222/HAVERM!R210)-1)*100 -> -6.2804732 | E82: 0 | S82: =+S77+7 -> 45036 | T82: Apr | U82: =IF('HAVER - UK Gas'!H1652="",C1364,AVERAGE('HAVER - UK Gas'!H1652:Q1652)) -> 137.925 | V82: =AVERAGE($U$39:$U$71,$U$73:$U$102) -> 136.05151 | AB82: =AVERAGE($U$39:$U$71,$U$73:$U$102) -> 136.05151 | AE82: 46204 | AF82: ='[1]CPI Forecast'!D372 -> 2.3600631 | AG82: =NA() -> #N/A | AH82: =NA() -> #N/A | AI82: 2 | AK82: 45839 | AL82: =[1]Contributions!C333 -> 0.21818411 | AM82: =[1]Contributions!D333 -> -0.095406781 | AN82: =[1]Contributions!E333 -> 0.03388317 | AO82: =[1]Contributions!H333 -> 0.40270316 | AP82: =[1]Contributions!I333 -> 1.6967441 | AQ82: =[1]Contributions!G333 -> 2.3054746 | AR82: 2
A83: 43313 | B83: =HAVERM!K230 -> 2.5150905 | C83: =((HAVERM!M224/HAVERM!M212)-1)*100 -> 3.2258065 | D83: =((HAVERM!R223/HAVERM!R211)-1)*100 -> -9.9053062 | E83: 0 | S83: =+S78+7 -> 45037 | T83: Apr | U83: =IF('HAVER - UK Gas'!H1653="",C1365,AVERAGE('HAVER - UK Gas'!H1653:Q1653)) -> 136.906 | V83: =AVERAGE($U$39:$U$71,$U$73:$U$102) -> 136.05151 | AB83: =AVERAGE($U$39:$U$71,$U$73:$U$102) -> 136.05151 | AE83: 46235 | AF83: ='[1]CPI Forecast'!D373 -> 2.3610628 | AG83: =NA() -> #N/A | AH83: ='BoE feb MPR'!P21 -> 2.1 | AI83: 2 | AK83: 45870 | AL83: =[1]Contributions!C334 -> 0.22863824 | AM83: =[1]Contributions!D334 -> -0.081638533 | AN83: =[1]Contributions!E334 -> 0.034108923 | AO83: =[1]Contributions!H334 -> 0.39486855 | AP83: =[1]Contributions!I334 -> 1.7005773 | AQ83: =[1]Contributions!G334 -> 2.3261068 | AR83: 2
A84: 43344 | B84: =HAVERM!K231 -> 1.497006 | C84: =((HAVERM!M225/HAVERM!M213)-1)*100 -> 3.204524 | D84: =((HAVERM!R224/HAVERM!R212)-1)*100 -> -10.719433 | E84: 0 | S84: =+S79+7 -> 45040 | T84: Apr | U84: =IF('HAVER - UK Gas'!H1654="",C1366,AVERAGE('HAVER - UK Gas'!H1654:Q1654)) -> 138.361 | V84: =AVERAGE($U$39:$U$71,$U$73:$U$102) -> 136.05151 | AB84: =AVERAGE($U$39:$U$71,$U$73:$U$102) -> 136.05151 | AE84: 46266 | AF84: ='[1]CPI Forecast'!D374 -> 2.2964309 | AG84: =NA() -> #N/A | AH84: =NA() -> #N/A | AI84: 2 | AK84: 45901 | AL84: =[1]Contributions!C335 -> 0.24035716 | AM84: =[1]Contributions!D335 -> -0.068126986 | AN84: =[1]Contributions!E335 -> 0.03433802 | AO84: =[1]Contributions!H335 -> 0.38798958 | AP84: =[1]Contributions!I335 -> 1.6700518 | AQ84: =[1]Contributions!G335 -> 2.308454 | AR84: 2
A85: 43374 | B85: =HAVERM!K232 -> 0.89463221 | C85: =((HAVERM!M226/HAVERM!M214)-1)*100 -> 2.629108 | D85: =((HAVERM!R225/HAVERM!R213)-1)*100 -> -7.8661056 | E85: 0 | S85: =+S80+7 -> 45041 | T85: Apr | U85: =IF('HAVER - UK Gas'!H1655="",C1367,AVERAGE('HAVER - UK Gas'!H1655:Q1655)) -> 137.731 | V85: =AVERAGE($U$39:$U$71,$U$73:$U$102) -> 136.05151 | AB85: =AVERAGE($U$39:$U$71,$U$73:$U$102) -> 136.05151 | AE85: 46296 | AF85: ='[1]CPI Forecast'!D375 -> 2.2836851 | AG85: =NA() -> #N/A | AH85: =NA() -> #N/A | AI85: 2 | AK85: 45931 | AL85: =[1]Contributions!C336 -> 0.2585572 | AM85: =[1]Contributions!D336 -> -0.056445086 | AN85: =[1]Contributions!E336 -> 0.02365567 | AO85: =[1]Contributions!H336 -> 0.38223665 | AP85: =[1]Contributions!I336 -> 1.6717919 | AQ85: =[1]Contributions!G336 -> 2.3241947 | AR85: 2
A86: 43405 | B86: =HAVERM!K233 -> 0.49455984 | C86: =((HAVERM!M227/HAVERM!M215)-1)*100 -> 1.5740741 | D86: =((HAVERM!R226/HAVERM!R214)-1)*100 -> -4.851322 | E86: 0 | S86: =+S81+7 -> 45042 | T86: Apr | U86: =IF('HAVER - UK Gas'!H1656="",C1368,AVERAGE('HAVER - UK Gas'!H1656:Q1656)) -> 141.82 | V86: =AVERAGE($U$39:$U$71,$U$73:$U$102) -> 136.05151 | AB86: =AVERAGE($U$39:$U$71,$U$73:$U$102) -> 136.05151 | AE86: 46327 | AF86: ='[1]CPI Forecast'!D376 -> 2.2658263 | AG86: =NA() -> #N/A | AH86: ='BoE feb MPR'!P22 -> 2 | AI86: 2 | AK86: 45962 | AL86: =[1]Contributions!C337 -> 0.27686329 | AM86: =[1]Contributions!D337 -> -0.044850049 | AN86: =[1]Contributions!E337 -> 0.023902991 | AO86: =[1]Contributions!H337 -> 0.37559369 | AP86: =[1]Contributions!I337 -> 1.6660275 | AQ86: =[1]Contributions!G337 -> 2.3407318 | AR86: 2
A87: 43435 | B87: =HAVERM!K234 -> 0.68762279 | C87: =((HAVERM!M228/HAVERM!M216)-1)*100 -> 1.2950971 | D87: =((HAVERM!R227/HAVERM!R215)-1)*100 -> -4.6740766 | E87: 0 | S87: =+S82+7 -> 45043 | T87: Apr | U87: =IF('HAVER - UK Gas'!H1657="",C1369,AVERAGE('HAVER - UK Gas'!H1657:Q1657)) -> 143.737 | V87: =AVERAGE($U$39:$U$71,$U$73:$U$102) -> 136.05151 | AB87: =AVERAGE($U$39:$U$71,$U$73:$U$102) -> 136.05151 | AE87: 46357 | AF87: ='[1]CPI Forecast'!D377 -> 2.2783479 | AG87: =NA() -> #N/A | AH87: =NA() -> #N/A | AI87: 2 | AK87: 45992 | AL87: =[1]Contributions!C338 -> 0.28612814 | AM87: =[1]Contributions!D338 -> -0.033181045 | AN87: =[1]Contributions!E338 -> 0.024086209 | AO87: =[1]Contributions!H338 -> 0.36882603 | AP87: =[1]Contributions!I338 -> 1.6836478 | AQ87: =[1]Contributions!G338 -> 2.3763204 | AR87: 2
A88: 43466 | B88: =HAVERM!K235 -> 0.88495575 | C88: =((HAVERM!M229/HAVERM!M217)-1)*100 -> 1.3901761 | D88: =((HAVERM!R228/HAVERM!R216)-1)*100 -> -4.5562159 | E88: 0 | S88: =+S83+7 -> 45044 | T88: Apr | U88: =IF('HAVER - UK Gas'!H1658="",C1370,AVERAGE('HAVER - UK Gas'!H1658:Q1658)) -> 143.737 | V88: =AVERAGE($U$39:$U$71,$U$73:$U$102) -> 136.05151 | AB88: =AVERAGE($U$39:$U$71,$U$73:$U$102) -> 136.05151 | AK88: 46023 | AL88: =[1]Contributions!C339 -> 0.29576322 | AM88: =[1]Contributions!D339 -> -0.026981197 | AN88: =[1]Contributions!E339 -> 0.037267441 | AO88: =[1]Contributions!H339 -> 0.37838827 | AP88: =[1]Contributions!I339 -> 1.6647224 | AQ88: =[1]Contributions!G339 -> 2.3970724 | AR88: 2
A89: 43497 | B89: =HAVERM!K236 -> 1.0794897 | C89: =((HAVERM!M230/HAVERM!M218)-1)*100 -> 2.0351526 | D89: =((HAVERM!R229/HAVERM!R217)-1)*100 -> -6.3463961 | E89: 0 | S89: =+S84+7 -> 45047 | T89: May | U89: =IF('HAVER - UK Gas'!H1659="",C1371,AVERAGE('HAVER - UK Gas'!H1659:Q1659)) -> 142.393 | V89: =AVERAGE($U$39:$U$71,$U$73:$U$102) -> 136.05151 | AB89: =AVERAGE($U$39:$U$71,$U$73:$U$102) -> 136.05151 | AK89: 46054 | AL89: =[1]Contributions!C340 -> 0.29606116 | AM89: =[1]Contributions!D340 -> -0.020464438 | AN89: =[1]Contributions!E340 -> 0.037446054 | AO89: =[1]Contributions!H340 -> 0.3762395 | AP89: =[1]Contributions!I340 -> 1.6628762 | AQ89: =[1]Contributions!G340 -> 2.3983852 | AR89: 2
A90: 43525 | B90: =HAVERM!K237 -> 0.78201369 | C90: =((HAVERM!M231/HAVERM!M219)-1)*100 -> 2.965709 | D90: =((HAVERM!R230/HAVERM!R218)-1)*100 -> -2.9984186 | E90: 0 | S90: =+S85+7 -> 45048 | T90: May | U90: =IF('HAVER - UK Gas'!H1660="",C1372,AVERAGE('HAVER - UK Gas'!H1660:Q1660)) -> 140.524 | V90: =AVERAGE($U$39:$U$71,$U$73:$U$102) -> 136.05151 | AB90: =AVERAGE($U$39:$U$71,$U$73:$U$102) -> 136.05151 | AK90: 46082 | AL90: =[1]Contributions!C341 -> 0.28448435 | AM90: =[1]Contributions!D341 -> -0.014013872 | AN90: =[1]Contributions!E341 -> 0.037512881 | AO90: =[1]Contributions!H341 -> 0.37487463 | AP90: =[1]Contributions!I341 -> 1.6566095 | AQ90: =[1]Contributions!G341 -> 2.3840755 | AR90: 2
A91: 43556 | B91: =HAVERM!K238 -> 0.68560235 | C91: =((HAVERM!M232/HAVERM!M220)-1)*100 -> 2.7675277 | D91: =((HAVERM!R231/HAVERM!R219)-1)*100 -> -3.810798 | E91: 0 | S91: =+S86+7 -> 45049 | T91: May | U91: =IF('HAVER - UK Gas'!H1661="",C1373,AVERAGE('HAVER - UK Gas'!H1661:Q1661)) -> 136.975 | V91: =AVERAGE($U$39:$U$71,$U$73:$U$102) -> 136.05151 | AB91: =AVERAGE($U$39:$U$71,$U$73:$U$102) -> 136.05151 | AK91: 46113 | AL91: =[1]Contributions!C342 -> 0.27772985 | AM91: =[1]Contributions!D342 -> -0.010919687 | AN91: =[1]Contributions!E342 -> 0.028196282 | AO91: =[1]Contributions!H342 -> 0.37805822 | AP91: =[1]Contributions!I342 -> 1.6456729 | AQ91: =[1]Contributions!G342 -> 2.3650274 | AR91: 2
A92: 43586 | B92: =HAVERM!K239 -> 0.98135427 | C92: =((HAVERM!M233/HAVERM!M221)-1)*100 -> 2.2872827 | D92: =((HAVERM!R232/HAVERM!R220)-1)*100 -> -4.3184575 | E92: 0 | S92: =+S87+7 -> 45050 | T92: May | U92: =IF('HAVER - UK Gas'!H1662="",C1374,AVERAGE('HAVER - UK Gas'!H1662:Q1662)) -> 138.062 | V92: =AVERAGE($U$39:$U$71,$U$73:$U$102) -> 136.05151 | AB92: =AVERAGE($U$39:$U$71,$U$73:$U$102) -> 136.05151 | AK92: 46143 | AL92: =[1]Contributions!C343 -> 0.27391218 | AM92: =[1]Contributions!D343 -> -0.0078687667 | AN92: =[1]Contributions!E343 -> 0.028266991 | AO92: =[1]Contributions!H343 -> 0.37689233 | AP92: =[1]Contributions!I343 -> 1.6361514 | AQ92: =[1]Contributions!G343 -> 2.3528568 | AR92: 2
A93: 43617 | B93: =HAVERM!K240 -> 1.6765286 | C93: =((HAVERM!M234/HAVERM!M222)-1)*100 -> 2.0928116 | D93: =((HAVERM!R233/HAVERM!R221)-1)*100 -> -4.4719342 | E93: 0 | S93: =+S88+7 -> 45051 | T93: May | U93: =IF('HAVER - UK Gas'!H1663="",C1375,AVERAGE('HAVER - UK Gas'!H1663:Q1663)) -> 138.062 | V93: =AVERAGE($U$39:$U$71,$U$73:$U$102) -> 136.05151 | AB93: =AVERAGE($U$39:$U$71,$U$73:$U$102) -> 136.05151 | AK93: 46174 | AL93: =[1]Contributions!C344 -> 0.27120159 | AM93: =[1]Contributions!D344 -> -0.0048426993 | AN93: =[1]Contributions!E344 -> 0.028261337 | AO93: =[1]Contributions!H344 -> 0.37775432 | AP93: =[1]Contributions!I344 -> 1.6403178 | AQ93: =[1]Contributions!G344 -> 2.3596478 | AR93: 2
A94: 43647 | B94: =HAVERM!K241 -> 1.3765978 | C94: =((HAVERM!M235/HAVERM!M223)-1)*100 -> 2.6654412 | D94: =((HAVERM!R234/HAVERM!R222)-1)*100 -> -0.46194407 | E94: 0 | S94: =+S89+7 -> 45054 | T94: May | U94: =IF('HAVER - UK Gas'!H1664="",C1376,AVERAGE('HAVER - UK Gas'!H1664:Q1664)) -> 139.229 | V94: =AVERAGE($U$39:$U$71,$U$73:$U$102) -> 136.05151 | AB94: =AVERAGE($U$39:$U$71,$U$73:$U$102) -> 136.05151 | AK94: 46204 | AL94: =[1]Contributions!C345 -> 0.26599061 | AM94: =[1]Contributions!D345 -> -0.0044411176 | AN94: =[1]Contributions!E345 -> 0.019035734 | AO94: =[1]Contributions!H345 -> 0.38311299 | AP94: =[1]Contributions!I345 -> 1.6444576 | AQ94: =[1]Contributions!G345 -> 2.3600631 | AR94: 2
A95: 43678 | B95: =HAVERM!K242 -> 1.7664377 | C95: =((HAVERM!M236/HAVERM!M224)-1)*100 -> 2.3897059 | D95: =((HAVERM!R235/HAVERM!R223)-1)*100 -> 1.84462 | E95: 0 | S95: =+S90+7 -> 45055 | T95: May | U95: =IF('HAVER - UK Gas'!H1665="",C1377,AVERAGE('HAVER - UK Gas'!H1665:Q1665)) -> 139.247 | V95: =AVERAGE($U$39:$U$71,$U$73:$U$102) -> 136.05151 | AB95: =AVERAGE($U$39:$U$71,$U$73:$U$102) -> 136.05151 | AK95: 46235 | AL95: =[1]Contributions!C346 -> 0.25888884 | AM95: =[1]Contributions!D346 -> -0.0040259542 | AN95: =[1]Contributions!E346 -> 0.018985715 | AO95: =[1]Contributions!H346 -> 0.37946304 | AP95: =[1]Contributions!I346 -> 1.6557899 | AQ95: =[1]Contributions!G346 -> 2.3610628 | AR95: 2
A96: 43709 | B96: =HAVERM!K243 -> 1.7699115 | C96: =((HAVERM!M237/HAVERM!M225)-1)*100 -> 1.5525114 | D96: =((HAVERM!R236/HAVERM!R224)-1)*100 -> 2.976075 | E96: 0 | S96: =+S91+7 -> 45056 | T96: May | U96: =IF('HAVER - UK Gas'!H1666="",C1378,AVERAGE('HAVER - UK Gas'!H1666:Q1666)) -> 139.722 | V96: =AVERAGE($U$39:$U$71,$U$73:$U$102) -> 136.05151 | AB96: =AVERAGE($U$39:$U$71,$U$73:$U$102) -> 136.05151 | AK96: 46266 | AL96: =[1]Contributions!C347 -> 0.25023881 | AM96: =[1]Contributions!D347 -> -0.0036230586 | AN96: =[1]Contributions!E347 -> 0.018935339 | AO96: =[1]Contributions!H347 -> 0.37917759 | AP96: =[1]Contributions!I347 -> 1.6064741 | AQ96: =[1]Contributions!G347 -> 2.2964309 | AR96: 2
A97: 43739 | B97: =HAVERM!K244 -> 1.2807882 | C97: =((HAVERM!M238/HAVERM!M226)-1)*100 -> 2.378774 | D97: =((HAVERM!R237/HAVERM!R225)-1)*100 -> -1.3734552 | E97: 0 | S97: =+S92+7 -> 45057 | T97: May | U97: =IF('HAVER - UK Gas'!H1667="",C1379,AVERAGE('HAVER - UK Gas'!H1667:Q1667)) -> 133.406 | V97: =AVERAGE($U$39:$U$71,$U$73:$U$102) -> 136.05151 | AB97: =AVERAGE($U$39:$U$71,$U$73:$U$102) -> 136.05151 | AK97: 46296 | AL97: =[1]Contributions!C348 -> 0.24236866 | AM97: =[1]Contributions!D348 -> -0.0042800848 | AN97: =[1]Contributions!E348 -> 0.0097134886 | AO97: =[1]Contributions!H348 -> 0.37967313 | AP97: =[1]Contributions!I348 -> 1.6102742 | AQ97: =[1]Contributions!G348 -> 2.2836851 | AR97: 2
A98: 43770 | B98: =HAVERM!K245 -> 2.0669291 | C98: =((HAVERM!M239/HAVERM!M227)-1)*100 -> 1.9143118 | D98: =((HAVERM!R238/HAVERM!R226)-1)*100 -> -0.53593422 | E98: 0 | S98: =+S93+7 -> 45058 | T98: May | U98: =IF('HAVER - UK Gas'!H1668="",C1380,AVERAGE('HAVER - UK Gas'!H1668:Q1668)) -> 124.711 | V98: =AVERAGE($U$39:$U$71,$U$73:$U$102) -> 136.05151 | AB98: =AVERAGE($U$39:$U$71,$U$73:$U$102) -> 136.05151 | AK98: 46327 | AL98: =[1]Contributions!C349 -> 0.23768175 | AM98: =[1]Contributions!D349 -> -0.0049373577 | AN98: =[1]Contributions!E349 -> 0.0096728645 | AO98: =[1]Contributions!H349 -> 0.37823658 | AP98: =[1]Contributions!I349 -> 1.6008635 | AQ98: =[1]Contributions!G349 -> 2.2658263 | AR98: 2
A99: 43800 | B99: =HAVERM!K246 -> 1.7560976 | C99: =((HAVERM!M240/HAVERM!M228)-1)*100 -> 1.9178082 | D99: =((HAVERM!R239/HAVERM!R227)-1)*100 -> 0.11919483 | E99: 0 | S99: =+S94+7 -> 45061 | T99: May | U99: =IF('HAVER - UK Gas'!H1669="",C1381,AVERAGE('HAVER - UK Gas'!H1669:Q1669)) -> 120.495 | V99: =AVERAGE($U$39:$U$71,$U$73:$U$102) -> 136.05151 | AB99: =AVERAGE($U$39:$U$71,$U$73:$U$102) -> 136.05151 | AK99: 46357 | AL99: =[1]Contributions!C350 -> 0.23359068 | AM99: =[1]Contributions!D350 -> -0.0055739479 | AN99: =[1]Contributions!E350 -> 0.0096037751 | AO99: =[1]Contributions!H350 -> 0.37537782 | AP99: =[1]Contributions!I350 -> 1.6183893 | AQ99: =[1]Contributions!G350 -> 2.2783479 | AR99: 2
A100: 43831 | B100: =HAVERM!K247 -> 1.4619883 | C100: =((HAVERM!M241/HAVERM!M229)-1)*100 -> 1.7367459 | D100: =((HAVERM!R240/HAVERM!R228)-1)*100 -> 3.0757245 | E100: 0 | S100: =+S95+7 -> 45062 | T100: May | U100: =IF('HAVER - UK Gas'!H1670="",C1382,AVERAGE('HAVER - UK Gas'!H1670:Q1670)) -> 124.964 | V100: =AVERAGE($U$39:$U$71,$U$73:$U$102) -> 136.05151 | AB100: =AVERAGE($U$39:$U$71,$U$73:$U$102) -> 136.05151
A101: 43862 | B101: =HAVERM!K248 -> 1.2621359 | C101: =((HAVERM!M242/HAVERM!M230)-1)*100 -> 0.090661831 | D101: =((HAVERM!R241/HAVERM!R229)-1)*100 -> 5.6121073 | E101: 0 | S101: =+S96+7 -> 45063 | T101: May | U101: =IF('HAVER - UK Gas'!H1671="",C1383,AVERAGE('HAVER - UK Gas'!H1671:Q1671)) -> 121.845 | V101: =AVERAGE($U$39:$U$71,$U$73:$U$102) -> 136.05151 | AB101: =AVERAGE($U$39:$U$71,$U$73:$U$102) -> 136.05151
...

Sheet HAVERM
A1: 201801 !M | B1: DOBY@UK | C1: DOBX@UK | D1: PEGDX@WBPRICES | E1: PEGEU@WBPRICES | F1: INTERP(X112USB@INTDAILY) | I1: 200001 !M | J1: D7BU@UK | M1: GHHV@UK | N1: GBA7@UK | O1: PUNFPI@CMDTY | P1: INTERP(X112USB@INTDAILY)
A2: .DESC | B2: UK: RPI: Fuel & Light: Gas (NSA, Jan-87=100) | C2: UK: RPI: Fuel & Light: Electricity (NSA, Jan-87=100) | D2: Natural Gas Index (NSA, 2010=100) | E2: Average Price: Natural Gas: Europe (US$/Mil.BTU) | F2: UK: Spot Exchange Rate: US Dollar (US$/GBP) | I2: .DESC | J2: UK: Consumer Price Index: Food & Non-Alcoholic Beverages (NSA, 2015=100) | K2: y/y calc | L2: m/m calc | M2: UK: PPI: Gross Sector Input: Food, Beverages & Tobacco (NSA, 2015=100) | N2: UK: PPI: Gross Sector Output: Food Products, Beverages & Tobacco (NSA, 2015=100) | O2: Food and Agriculture Organization of the UN: Food Price Index (2014-16=100) | P2: UK: Spot Exchange Rate: US Dollar (US$/GBP) | Q2: UN fx adjustment | R2: UN re-basing to 2015=100 | S2: BRC shop price inflation y/y
A3: .T1 | B3: Jan-1987 | C3: Jan-1987 | D3: Jan-1960 | E3: Jan-1960 | F3: Jan-1975 <- 02-Jan-1975 | I3: .T1 | J3: Jan-1988 | M3: Jan-1996 | N3: Jan-1996 | O3: Jan-1990 | P3: Jan-1975 <- 02-Jan-1975 | R3: =AVERAGE(Q187:Q198) -> 60.809735
A4: .TN | B4: Feb-2024 | C4: Feb-2024 | D4: Mar-2024 | E4: Mar-2024 | F4: Mar-2024 <- 05-Apr-2024 | I4: .TN | J4: Feb-2024 | M4: Feb-2024 | N4: Feb-2024 | O4: Mar-2024 | P4: Mar-2024 <- 05-Apr-2024
A5: .SOURCE | B5: ONS | C5: ONS | D5: WB | E5: WB | F5: BoE | I5: .LSOURCE | J5: Office for National Statistics | M5: Office for National Statistics | N5: Office for National Statistics | O5: Food and Agriculture Organization of the UN | P5: Bank of England
A6: .DTLM | B6: Mar-20-2024 07:15 | C6: Mar-20-2024 07:15 | D6: Apr-02-2024 21:20 | E6: Apr-02-2024 21:20 | F6: Apr-08-2024 09:31 | I6: .DTLM | J6: Mar-20-2024 07:15 | M6: Mar-20-2024 07:17 | N6: Mar-20-2024 07:17 | O6: Apr-05-2024 09:09 | P6: Apr-08-2024 09:31
A7: 201801 | B7: 353.2 | C7: 335.7 | D7: 84.82 | E7: 6.66 | F7: 1.3713621 | I7: 200001 | J7: 66 | M7: 64.8 | N7: 68.2 | O7: 52.6 | P7: 1.6069929 | Q7: =O7/P7 -> 32.731944 | R7: =(Q7/$R$3)*100 -> 53.826815
A8: 201802 | B8: 353.2 | C8: 335.7 | D8: 71.03 | E8: 6.72 | F8: 1.396075 | I8: 200002 | J8: 65.9 | L8: =((J8/J7)-1)*100 -> -0.15151515 | M8: 64.7 | N8: 68.2 | O8: 52.3 | P8: 1.5998143 | Q8: =O8/P8 -> 32.691295 | R8: =(Q8/$R$3)*100 -> 53.759969
A9: 201803 | B9: 353.2 | C9: 335.7 | D9: 71.46 | E9: 6.7 | F9: 1.3792563 | I9: 200003 | J9: 65.4 | L9: =((J9/J8)-1)*100 -> -0.75872534 | M9: 64.9 | N9: 68.5 | O9: 52.8 | P9: 1.5802217 | Q9: =O9/P9 -> 33.413032 | R9: =(Q9/$R$3)*100 -> 54.946847
A10: 201804 | B10: 354.5 | C10: 338.6 | D10: 73.52 | E10: 6.93 | F10: 1.3624375 | I10: 200004 | J10: 65.2 | L10: =((J10/J9)-1)*100 -> -0.3058104 | M10: 64.4 | N10: 69.1 | O10: 53.4 | P10: 1.5564403 | Q10: =O10/P10 -> 34.309059 | R10: =(Q10/$R$3)*100 -> 56.420339
A11: 201805 | B11: 354.7 | C11: 338.9 | D11: 76.51 | E11: 7.49 | F11: 1.3456187 | I11: 200005 | J11: 65.9 | L11: =((J11/J10)-1)*100 -> 1.0736196 | M11: 64.8 | N11: 69.4 | O11: 53.6 | P11: 1.5326588 | Q11: =O11/P11 -> 34.971907 | R11: =(Q11/$R$3)*100 -> 57.510376
A12: 201806 | B12: 363.9 | C12: 346.5 | D12: 78.34 | E12: 7.45 | F12: 1.3288 | I12: 200006 | J12: 66.1 | L12: =((J12/J11)-1)*100 -> 0.30349014 | M12: 66.3 | N12: 69.4 | O12: 53.8 | P12: 1.5088773 | Q12: =O12/P12 -> 35.65565 | R12: =(Q12/$R$3)*100 -> 58.634773
A13: 201807 | B13: 367.8 | C13: 352.7 | D13: 77.5 | E13: 7.6 | F13: 1.3168682 | I13: 200007 | J13: 66.6 | L13: =((J13/J12)-1)*100 -> 0.75642965 | M13: 66.6 | N13: 69.4 | O13: 54 | P13: 1.5087857 | Q13: =O13/P13 -> 35.790371 | R13: =(Q13/$R$3)*100 -> 58.856317
A14: 201808 | B14: 367.8 | C14: 352.7 | D14: 81.71 | E14: 8.08 | F14: 1.3115241 | I14: 200008 | J14: 66.1 | L14: =((J14/J13)-1)*100 -> -0.75075075 | M14: 66.7 | N14: 69.3 | O14: 53.2 | P14: 1.4721429 | Q14: =O14/P14 -> 36.137797 | R14: =(Q14/$R$3)*100 -> 59.427651
A15: 201809 | B15: 372.2 | C15: 359 | D15: 89.17 | E15: 9.52 | F15: 1.30618 | I15: 200009 | J15: 66.3 | L15: =((J15/J14)-1)*100 -> 0.30257186 | M15: 66.3 | N15: 69.3 | O15: 52.6 | P15: 1.4355 | Q15: =O15/P15 -> 36.642285 | R15: =(Q15/$R$3)*100 -> 60.257268
A16: 201810 | B16: 379.7 | C16: 366 | D16: 89.57 | E16: 8.79 | F16: 1.3011696 | I16: 200010 | J16: 66.3 | L16: =((J16/J15)-1)*100 -> 0 | M16: 66.2 | N16: 69.4 | O16: 53.4 | P16: 1.4511045 | Q16: =O16/P16 -> 36.799554 | R16: =(Q16/$R$3)*100 -> 60.515893
A17: 201811 | B17: 379.7 | C17: 366 | D17: 97.36 | E17: 8.27 | F17: 1.2900727 | I17: 200011 | J17: 66.7 | L17: =((J17/J16)-1)*100 -> 0.60331825 | M17: 66.5 | N17: 69.4 | O17: 53.8 | P17: 1.4255773 | Q17: =O17/P17 -> 37.739098 | R17: =(Q17/$R$3)*100 -> 62.060947
A18: 201812 | B18: 379.7 | C18: 366 | D18: 94.41 | E18: 7.98 | F18: 1.2939552 | I18: 200012 | J18: 66.8 | L18: =((J18/J17)-1)*100 -> 0.14992504 | M18: 66.7 | N18: 69.6 | O18: 54.4 | P18: 1.4346815 | Q18: =O18/P18 -> 37.917823 | R18: =(Q18/$R$3)*100 -> 62.354857
A19: 201901 | B19: 346.7 | C19: 348.2 | D19: 80.06 | E19: 7.26 | F19: 1.2978376 | I19: 200101 | J19: 67 | K19: =((J19/J7)-1)*100 -> 1.5151515 | L19: =((J19/J18)-1)*100 -> 0.2994012 | M19: 67 | N19: 69.7 | O19: 53.8 | P19: 1.4437858 | Q19: =O19/P19 -> 37.263146 | R19: =(Q19/$R$3)*100 -> 61.278258
A20: 201902 | B20: 347 | C20: 348.6 | D20: 69.55 | E20: 6.01 | F20: 1.30172 | I20: 200102 | J20: 67.1 | K20: =((J20/J8)-1)*100 -> 1.8209408 | L20: =((J20/J19)-1)*100 -> 0.14925373 | M20: 66.9 | N20: 69.8 | O20: 54.2 | P20: 1.45289 | Q20: =O20/P20 -> 37.304958 | R20: =(Q20/$R$3)*100 -> 61.347016
A21: 201903 | B21: 347 | C21: 348.6 | D21: 67.91 | E21: 5.18 | F21: 1.3165333 | I21: 200103 | J21: 67.9 | K21: =((J21/J9)-1)*100 -> 3.82263 | L21: =((J21/J20)-1)*100 -> 1.1922504 | M21: 67.4 | N21: 70.4 | O21: 55.1 | P21: 1.4453864 | Q21: =O21/P21 -> 38.121295 | R21: =(Q21/$R$3)*100 -> 62.689461
A22: 201904 | B22: 379.5 | C22: 386.4 | D22: 62.49 | E22: 4.92 | F22: 1.3003172 | I22: 200104 | J22: 68.1 | K22: =((J22/J10)-1)*100 -> 4.4478528 | L22: =((J22/J21)-1)*100 -> 0.29455081 | M22: 67.9 | N22: 70.5 | O22: 54.6 | P22: 1.4307211 | Q22: =O22/P22 -> 38.162575 | R22: =(Q22/$R$3)*100 -> 62.757345
A23: 201905 | B23: 379.5 | C23: 386.4 | D23: 59.42 | E23: 4.34 | F23: 1.2841011 | I23: 200105 | J23: 70 | K23: =((J23/J11)-1)*100 -> 6.2215478 | L23: =((J23/J22)-1)*100 -> 2.7900147 | M23: 68.7 | N23: 70.8 | O23: 55.4 | P23: 1.4160558 | Q23: =O23/P23 -> 39.122753 | R23: =(Q23/$R$3)*100 -> 64.336332
A24: 201906 | B24: 379.5 | C24: 386.4 | D24: 52.96 | E24: 3.59 | F24: 1.267885 | I24: 200106 | J24: 70.4 | K24: =((J24/J12)-1)*100 -> 6.505295 | L24: =((J24/J23)-1)*100 -> 0.57142857 | M24: 68.5 | N24: 70.6 | O24: 54.8 | P24: 1.4013905 | Q24: =O24/P24 -> 39.104019 | R24: =(Q24/$R$3)*100 -> 64.305525
A25: 201907 | B25: 379.5 | C25: 386.4 | D25: 52.73 | E25: 3.62 | F25: 1.2468913 | I25: 200107 | J25: 69 | K25: =((J25/J13)-1)*100 -> 3.6036036 | L25: =((J25/J24)-1)*100 -> -1.9886364 | M25: 68.8 | N25: 70.5 | O25: 56.5 | P25: 1.4138727 | Q25: =O25/P25 -> 39.961164 | R25: =(Q25/$R$3)*100 -> 65.715077
A26: 201908 | B26: 379.5 | C26: 386.4 | D26: 51.85 | E26: 3.68 | F26: 1.2411671 | I26: 200108 | J26: 68.8 | K26: =((J26/J14)-1)*100 -> 4.0847201 | L26: =((J26/J25)-1)*100 -> -0.28985507 | M26: 68.2 | N26: 70.5 | O26: 56.6 | P26: 1.4386614 | Q26: =O26/P26 -> 39.342128 | R26: =(Q26/$R$3)*100 -> 64.697089
A27: 201909 | B27: 379.5 | C27: 386.4 | D27: 58.19 | E27: 4.21 | F27: 1.2354429 | I27: 200109 | J27: 68.7 | K27: =((J27/J15)-1)*100 -> 3.6199095 | L27: =((J27/J26)-1)*100 -> -0.14534884 | M27: 67.7 | N27: 70.6 | O27: 55.4 | P27: 1.46345 | Q27: =O27/P27 -> 37.855752 | R27: =(Q27/$R$3)*100 -> 62.252782
A28: 201910 | B28: 345.7 | C28: 378.1 | D28: 59.12 | E28: 5.06 | F28: 1.2646913 | I28: 200110 | J28: 68.8 | K28: =((J28/J16)-1)*100 -> 3.7707391 | L28: =((J28/J27)-1)*100 -> 0.14556041 | M28: 67.4 | N28: 70.7 | O28: 54.2 | P28: 1.4517522 | Q28: =O28/P28 -> 37.334196 | R28: =(Q28/$R$3)*100 -> 61.395097
A29: 201911 | B29: 345.7 | C29: 378.1 | D29: 63.47 | E29: 5.15 | F29: 1.2882714 | I29: 200111 | J29: 68.7 | K29: =((J29/J17)-1)*100 -> 2.9985007 | L29: =((J29/J28)-1)*100 -> -0.14534884 | M29: 67.7 | N29: 70.7 | O29: 54.7 | P29: 1.4357818 | Q29: =O29/P29 -> 38.09771 | R29: =(Q29/$R$3)*100 -> 62.650677
A30: 201912 | B30: 345.7 | C30: 378.1 | D30: 56.01 | E30: 4.62 | F30: 1.2907593 | I30: 200112 | J30: 69.1 | K30: =((J30/J18)-1)*100 -> 3.4431138 | L30: =((J30/J29)-1)*100 -> 0.58224163 | M30: 68 | N30: 71.1 | O30: 54.3 | P30: 1.4315479 | Q30: =O30/P30 -> 37.93097 | R30: =(Q30/$R$3)*100 -> 62.376477
... A80: 202402 | B80: 636.6 | C80: 633.1 | D80: 68.88 | E80: 8.15 | F80: 1.2622333 | I80: 200602 | J80: 72.2 | K80: =((J80/J68)-1)*100 -> 0.97902098 | L80: =((J80/J79)-1)*100 -> 0.55710306 | M80: 72.6 | N80: 74.7 | O80: 70.4 | P80: 1.74703 | Q80: =O80/P80 -> 40.296961 | R80: =(Q80/$R$3)*100 -> 66.267286
A81: 202403 | D81: 68.05 | E81: 8.55 | F81: #N/A | I81: 200603 | J81: 71.8 | K81: =((J81/J69)-1)*100 -> -0.41608877 | L81: =((J81/J80)-1)*100 -> -0.55401662 | M81: 73.3 | N81: 74.9 | O81: 69.4 | P81: 1.7435261 | Q81: =O81/P81 -> 39.804394 | R81: =(Q81/$R$3)*100 -> 65.457273
I82: 200604 | J82: 71.7 | K82: =((J82/J70)-1)*100 -> 0.42016807 | L82: =((J82/J81)-1)*100 -> -0.13927577 | M82: 73 | N82: 75.3 | O82: 69.7 | P82: 1.776631 | Q82: =O82/P82 -> 39.231556 | R82: =(Q82/$R$3)*100 -> 64.515256
I83: 200605 | J83: 72.7 | K83: =((J83/J71)-1)*100 -> 1.1126565 | L83: =((J83/J82)-1)*100 -> 1.3947001 | M83: 73.4 | N83: 75.8 | O83: 71 | P83: 1.809736 | Q83: =O83/P83 -> 39.232242 | R83: =(Q83/$R$3)*100 -> 64.516384
I84: 200606 | J84: 73.2 | K84: =((J84/J72)-1)*100 -> 1.8080668 | L84: =((J84/J83)-1)*100 -> 0.68775791 | M84: 74.1 | N84: 76 | O84: 71.1 | P84: 1.8428409 | Q84: =O84/P84 -> 38.581735 | R84: =(Q84/$R$3)*100 -> 63.446643
I85: 200607 | J85: 73.3 | K85: =((J85/J73)-1)*100 -> 3.0942335 | L85: =((J85/J84)-1)*100 -> 0.13661202 | M85: 74.3 | N85: 76.1 | O85: 72.9 | P85: 1.8447429 | Q85: =O85/P85 -> 39.517703 | R85: =(Q85/$R$3)*100 -> 64.985816
I86: 200608 | J86: 73.7 | K86: =((J86/J74)-1)*100 -> 3.511236 | L86: =((J86/J85)-1)*100 -> 0.54570259 | M86: 74.8 | N86: 76.3 | O86: 72.9 | P86: 1.8647214 | Q86: =O86/P86 -> 39.094311 | R86: =(Q86/$R$3)*100 -> 64.28956
I87: 200609 | J87: 74.1 | K87: =((J87/J75)-1)*100 -> 3.9270687 | L87: =((J87/J86)-1)*100 -> 0.54274084 | M87: 74.8 | N87: 76.4 | O87: 73 | P87: 1.8847 | Q87: =O87/P87 -> 38.732955 | R87: =(Q87/$R$3)*100 -> 63.695319
I88: 200610 | J88: 74.5 | K88: =((J88/J76)-1)*100 -> 4.7819972 | L88: =((J88/J87)-1)*100 -> 0.53981107 | M88: 73.9 | N88: 76.4 | O88: 74.9 | P88: 1.8755227 | Q88: =O88/P88 -> 39.935533 | R88: =(Q88/$R$3)*100 -> 65.672927
I89: 200611 | J89: 75.2 | K89: =((J89/J77)-1)*100 -> 5.027933 | L89: =((J89/J88)-1)*100 -> 0.93959732 | M89: 74.9 | N89: 76.7 | O89: 77.5 | P89: 1.9118545 | Q89: =O89/P89 -> 40.536557 | R89: =(Q89/$R$3)*100 -> 66.661295
I90: 200612 | J90: 75.3 | K90: =((J90/J78)-1)*100 -> 4.5833333 | L90: =((J90/J89)-1)*100 -> 0.13297872 | M90: 75.5 | N90: 77 | O90: 78.6 | P90: 1.927253 | Q90: =O90/P90 -> 40.783436 | R90: =(Q90/$R$3)*100 -> 67.067281
I91: 200701 | J91: 74.6 | K91: =((J91/J79)-1)*100 -> 3.8997214 | L91: =((J91/J90)-1)*100 -> -0.92961487 | M91: 75 | N91: 77.1 | O91: 78.1 | P91: 1.9426515 | Q91: =O91/P91 -> 40.202784 | R91: =(Q91/$R$3)*100 -> 66.112415
I92: 200702 | J92: 75.4 | K92: =((J92/J80)-1)*100 -> 4.432133 | L92: =((J92/J91)-1)*100 -> 1.0723861 | M92: 75.1 | N92: 77.4 | O92: 79.6 | P92: 1.95805 | Q92: =O92/P92 -> 40.65269 | R92: =(Q92/$R$3)*100 -> 66.852273
I93: 200703 | J93: 75.8 | K93: =((J93/J81)-1)*100 -> 5.5710306 | L93: =((J93/J92)-1)*100 -> 0.53050398 | M93: 75.6 | N93: 77.9 | O93: 80.8 | P93: 1.9471409 | Q93: =O93/P93 -> 41.49674 | R93: =(Q93/$R$3)*100 -> 68.240291
... I103: 200801 | J103: 79.2 | K103: =((J103/J91)-1)*100 -> 6.1662198 | L103: =((J103/J102)-1)*100 -> -0.25188917 | M103: 85.8 | N103: 83.1 | O103: 120 | P103: 1.9992372 | Q103: =O103/P103 -> 60.022892 | R103: =(Q103/$R$3)*100 -> 98.706057
I104: 200802 | J104: 79.6 | K104: =((J104/J92)-1)*100 -> 5.5702918 | L104: =((J104/J103)-1)*100 -> 0.50505051 | M104: 86.3 | N104: 83.6 | O104: 128 | P104: 1.9638286 | Q104: =O104/P104 -> 65.178805 | R104: =(Q104/$R$3)*100 -> 107.18482 | S104: 0.004
I105: 200803 | J105: 79.9 | K105: =((J105/J93)-1)*100 -> 5.408971 | L105: =((J105/J104)-1)*100 -> 0.37688442 | M105: 87.5 | N105: 84.5 | O105: 132.1 | P105: 1.9727461 | Q105: =O105/P105 -> 66.962494 | R105: =(Q105/$R$3)*100 -> 110.11805 | S105: 0.011
I106: 200804 | J106: 80.9 | K106: =((J106/J94)-1)*100 -> 6.4473684 | L106: =((J106/J105)-1)*100 -> 1.2515645 | M106: 88.6 | N106: 85.4 | O106: 130.4 | P106: 1.9816636 | Q106: =O106/P106 -> 65.803297 | R106: =(Q106/$R$3)*100 -> 108.21178 | S106: 0.012
I107: 200805 | J107: 82.3 | K107: =((J107/J95)-1)*100 -> 7.8636959 | L107: =((J107/J106)-1)*100 -> 1.7305315 | M107: 90.4 | N107: 87 | O107: 130 | P107: 1.9737342 | Q107: =O107/P107 -> 65.864998 | R107: =(Q107/$R$3)*100 -> 108.31325 | S107: 0.018
I108: 200806 | J108: 84 | K108: =((J108/J96)-1)*100 -> 9.517601 | L108: =((J108/J107)-1)*100 -> 2.0656136 | M108: 93.9 | N108: 87.7 | O108: 132.5 | P108: 1.9658048 | Q108: =O108/P108 -> 67.402421 | R108: =(Q108/$R$3)*100 -> 110.8415 | S108: 0.025
I109: 200807 | J109: 84.7 | K109: =((J109/J97)-1)*100 -> 12.334218 | L109: =((J109/J108)-1)*100 -> 0.83333333 | M109: 91.7 | N109: 87.9 | O109: 130.1 | P109: 1.9879522 | Q109: =O109/P109 -> 65.44423 | R109: =(Q109/$R$3)*100 -> 107.6213 | S109: 0.032
I110: 200808 | J110: 85.8 | K110: =((J110/J98)-1)*100 -> 13.043478 | L110: =((J110/J109)-1)*100 -> 1.2987013 | M110: 91.1 | N110: 88.4 | O110: 121.1 | P110: 1.8932852 | Q110: =O110/P110 -> 63.962894 | R110: =(Q110/$R$3)*100 -> 105.18529 | S110: 0.038
I111: 200809 | J111: 85.5 | K111: =((J111/J99)-1)*100 -> 11.328125 | L111: =((J111/J110)-1)*100 -> -0.34965035 | M111: 91.7 | N111: 88.6 | O111: 112.8 | P111: 1.7986182 | Q111: =O111/P111 -> 62.714811 | R111: =(Q111/$R$3)*100 -> 103.13285 | S111: 0.036
I112: 200810 | J112: 85.9 | K112: =((J112/J100)-1)*100 -> 10.128205 | L112: =((J112/J111)-1)*100 -> 0.46783626 | M112: 91.4 | N112: 88.4 | O112: 97.6 | P112: 1.6899826 | Q112: =O112/P112 -> 57.752074 | R112: =(Q112/$R$3)*100 -> 94.971757 | S112: 0.03
I113: 200811 | J113: 87.1 | K113: =((J113/J101)-1)*100 -> 10.673443 | L113: =((J113/J112)-1)*100 -> 1.3969732 | M113: 91.2 | N113: 88.2 | O113: 89.5 | P113: 1.53378 | Q113: =O113/P113 -> 58.352567 | R113: =(Q113/$R$3)*100 -> 95.959252 | S113: 0.027
I114: 200812 | J114: 87.7 | K114: =((J114/J102)-1)*100 -> 10.453401 | L114: =((J114/J113)-1)*100 -> 0.68886338 | M114: 93.4 | N114: 89.2 | O114: 86 | P114: 1.50288 | Q114: =O114/P114 -> 57.223464 | R114: =(Q114/$R$3)*100 -> 94.102473 | S114: 0.005
I115: 200901 | J115: 87.3 | K115: =((J115/J103)-1)*100 -> 10.227273 | L115: =((J115/J114)-1)*100 -> -0.45610034 | M115: 93.6 | N115: 89.4 | O115: 86.4 | P115: 1.47198 | Q115: =O115/P115 -> 58.69645 | R115: =(Q115/$R$3)*100 -> 96.524758 | S115: 0.011
... I296: 202402 | J296: 134.9 | K296: =((J296/J284)-1)*100 -> 4.9805447 | L296: =((J296/J295)-1)*100 -> 0.22288262 | M296: 147.7 | N296: 134.3 | O296: 117 | P296: 1.2622333 | Q296: =O296/P296 -> 92.692846 | R296: =(Q296/$R$3)*100 -> 152.43093 | S296: 0.025
I297: 202403 | O297: 118.3 | P297: #N/A | Q297: =O297/P297 -> #N/A | R297: =(Q297/$R$3)*100 -> #N/A | S297: 0.013
P305: 1.2711

Sheet HAVER - UK Gas
D1: 1 | E1: 2 | F1: 3 | G1: 4 | H1: 5 | I1: 6 | J1: 7 | K1: 8 | L1: 9 | M1: 10 | N1: 11 | O1: 12 | P1: 13 | Q1: 14 | R1: 15 | S1: 16 | T1: 17 | U1: 18 | V1: 19 | W1: 20 | X1: 21 | Y1: 22 | Z1: 23 | AA1: 24 | AB1: 25 | AC1: 26 | AD1: 27 | AE1: 28 | AF1: 29 | AG1: 30 | AH1: 31 | AI1: 32 | AJ1: 33 | AK1: 34 | AL1: 35 | AM1: 36 | AN1: 37 | AO1: 38 | AP1: 39 | AQ1: 40 | AR1: 41 | AS1: 42 | AT1: 43 | AU1: 44 | AV1: 45 | AW1: 46 | AX1: 47 | AY1: 48
B2: 20170101 !D | C2: .excel_last | D2: IFNG01C@CMDTY | E2: IFNG02C@CMDTY | F2: IFNG03C@CMDTY | G2: IFNG04C@CMDTY | H2: IFNG05C@CMDTY | I2: IFNG06C@CMDTY | J2: IFNG07C@CMDTY | K2: IFNG08C@CMDTY | L2: IFNG09C@CMDTY | M2: IFNG10C@CMDTY | N2: IFNG11C@CMDTY | O2: IFNG12C@CMDTY | P2: IFNG13C@CMDTY | Q2: IFNG14C@CMDTY | R2: IFNG15C@CMDTY | S2: IFNG16C@CMDTY | T2: IFNG17C@CMDTY | U2: IFNG18C@CMDTY | V2: IFNG19C@CMDTY | W2: IFNG20C@CMDTY | X2: IFNG21C@CMDTY | Y2: IFNG22C@CMDTY | Z2: IFNG23C@CMDTY | AA2: IFNG24C@CMDTY | AB2: IFNG25C@CMDTY | AC2: IFNG26C@CMDTY | AD2: IFNG27C@CMDTY | AE2: IFNG28C@CMDTY | AF2: IFNG29C@CMDTY | AG2: IFNG30C@CMDTY | AH2: IFNG31C@CMDTY | AI2: IFNG32C@CMDTY | AJ2: IFNG33C@CMDTY | AK2: IFNG34C@CMDTY | AL2: IFNG35C@CMDTY | AM2: IFNG36C@CMDTY | AN2: IFNG37C@CMDTY | AO2: IFNG38C@CMDTY | AP2: IFNG39C@CMDTY | AQ2: IFNG40C@CMDTY | AR2: IFNG41C@CMDTY | AS2: IFNG42C@CMDTY | AT2: IFNG43C@CMDTY | AU2: IFNG44C@CMDTY | AV2: IFNG45C@CMDTY | AW2: IFNG46C@CMDTY | AX2: IFNG47C@CMDTY | AY2: IFNG48C@CMDTY
B3: .DESC | D3: ICE UK Natural Gas Futures: 1st Position: Settlement Price (Sterling/Therm) | E3: ICE UK Natural Gas Futures: 2nd Position: Settlement Price (Sterling/Therm) | F3: ICE UK Natural Gas Futures: 3rd Position: Settlement Price (Sterling/Therm) | G3: ICE UK Natural Gas Futures: 4th Position: Settlement Price (Sterling/Therm) | H3: ICE UK Natural Gas Futures: 5th Position: Settlement Price (Sterling/Therm) | I3: ICE UK Natural Gas Futures: 6th Position: Settlement Price (Sterling/Therm) | J3: ICE UK Natural Gas Futures: 7th Position: Settlement Price (Sterling/Therm) | K3: ICE UK Natural Gas Futures: 8th Position: Settlement Price (Sterling/Therm) | L3: ICE UK Natural Gas Futures: 9th Position: Settlement Price (Sterling/Therm) | M3: ICE UK Natural Gas Futures: 10th Position: Settlement Price (Sterling/Therm) | N3: ICE UK Natural Gas Futures: 11th Position: Settlement Price (Sterling/Therm) | O3: ICE UK Natural Gas Futures: 12th Position: Settlement Price (Sterling/Therm) | P3: ICE UK Natural Gas Futures: 13th Position: Settlement Price (Sterling/Therm) | Q3: ICE UK Natural Gas Futures: 14th Position: Settlement Price (Sterling/Therm) | R3: ICE UK Natural Gas Futures: 15th Position: Settlement Price (Sterling/Therm) | S3: ICE UK Natural Gas Futures: 16th Position: Settlement Price (Sterling/Therm) | T3: ICE UK Natural Gas Futures: 17th Position: Settlement Price (Sterling/Therm) | U3: ICE UK Natural Gas Futures: 18th Position: Settlement Price (Sterling/Therm) | V3: ICE UK Natural Gas Future: 19th Position: Settlement Price (Sterling/Therm) | W3: ICE UK Natural Gas Future: 20th Position: Settlement Price (Sterling/Therm) | X3: ICE UK Natural Gas Future: 21st Position: Settlement Price (Sterling/Therm) | Y3: ICE UK Natural Gas Future: 22nd Position: Settlement Price (Sterling/Therm) | Z3: ICE UK Natural Gas Future: 23rd Position: Settlement Price (Sterling/Therm) | AA3: ICE UK Natural Gas Future: 24th Position: Settlement Price (Sterling/Therm) | AB3: ICE UK Natural Gas Future: 25th Position: Settlement Price (Sterling/Therm) | AC3: ICE UK Natural Gas Future: 26th Position: Settlement Price (Sterling/Therm) | AD3: ICE UK Natural Gas Future: 27th Position: Settlement Price (Sterling/Therm) | AE3: ICE UK Natural Gas Future: 28th Position: Settlement Price (Sterling/Therm) | AF3: ICE UK Natural Gas Future: 29th Position: Settlement Price (Sterling/Therm) | AG3: ICE UK Natural Gas Future: 30th Position: Settlement Price (Sterling/Therm) | AH3: ICE UK Natural Gas Future: 31st Position: Settlement Price (Sterling/Therm) | AI3: ICE UK Natural Gas Future: 32nd Position: Settlement Price (Sterling/Therm) | AJ3: ICE UK Natural Gas Future: 33rd Position: Settlement Price (Sterling/Therm) | AK3: ICE UK Natural Gas Future: 34th Position: Settlement Price (Sterling/Therm) | AL3: ICE UK Natural Gas Future: 35th Position: Settlement Price (Sterling/Therm) | AM3: ICE UK Natural Gas Future: 36th Position: Settlement Price (Sterling/Therm) | AN3: ICE UK Natural Gas Future: 37th Position: Settlement Price (Sterling/Therm) | AO3: ICE UK Natural Gas Future: 38th Position: Settlement Price (Sterling/Therm) | AP3: ICE UK Natural Gas Future: 39th Position: Settlement Price (Sterling/Therm) | AQ3: ICE UK Natural Gas Future: 40th Position: Settlement Price (Sterling/Therm) | AR3: ICE UK Natural Gas Future: 41st Position: Settlement Price (Sterling/Therm) | AS3: ICE UK Natural Gas Future: 42nd Position: Settlement Price (Sterling/Therm) | AT3: ICE UK Natural Gas Future: 43rd Position: Settlement Price (Sterling/Therm) | AU3: ICE UK Natural Gas Future: 44th Position: Settlement Price (Sterling/Therm) | AV3: ICE UK Natural Gas Future: 45th Position: Settlement Price (Sterling/Therm) | AW3: ICE UK Natural Gas Future: 46th Position: Settlement Price (Sterling/Therm) | AX3: ICE UK Natural Gas Future: 47th Position: Settlement Price (Sterling/Therm) | AY3: ICE UK Natural Gas Future: 48th Position: Settlement Price (Sterling/Therm)
B4: .T1 | D4: 31-Jan-1997 | E4: 31-Jan-1997 | F4: 31-Jan-1997 | G4: 31-Jan-1997 | H4: 31-Jan-1997 | I4: 31-Jan-1997 | J4: 31-Jan-1997 | K4: 31-Jan-1997 | L4: 31-Jan-1997 | M4: 31-Jan-1997 | N4: 31-Jan-1997 | O4: 29-Jun-2004 | P4: 28-Feb-2007 | Q4: 11-Apr-2008 | R4: 11-Apr-2008 | S4: 11-Apr-2008 | T4: 11-Apr-2008 | U4: 30-May-2008 | V4: 16-Aug-2010 | W4: 16-Aug-2010 | X4: 16-Aug-2010 | Y4: 16-Aug-2010 | Z4: 16-Aug-2010 | AA4: 16-Aug-2010 | AB4: 16-Aug-2010 | AC4: 16-Aug-2010 | AD4: 16-Aug-2010 | AE4: 16-Aug-2010 | AF4: 16-Aug-2010 | AG4: 16-Aug-2010 | AH4: 16-Aug-2010 | AI4: 16-Aug-2010 | AJ4: 16-Aug-2010 | AK4: 16-Aug-2010 | AL4: 16-Aug-2010 | AM4: 16-Aug-2010 | AN4: 16-Aug-2010 | AO4: 16-Aug-2010 | AP4: 16-Aug-2010 | AQ4: 16-Aug-2010 | AR4: 16-Aug-2010 | AS4: 16-Aug-2010 | AT4: 16-Aug-2010 | AU4: 16-Aug-2010 | AV4: 16-Aug-2010 | AW4: 16-Aug-2010 | AX4: 16-Aug-2010 | AY4: 16-Aug-2010
B5: .TN | D5: 09-Apr-2024 | E5: 09-Apr-2024 | F5: 09-Apr-2024 | G5: 09-Apr-2024 | H5: 09-Apr-2024 | I5: 09-Apr-2024 | J5: 09-Apr-2024 | K5: 09-Apr-2024 | L5: 09-Apr-2024 | M5: 09-Apr-2024 | N5: 09-Apr-2024 | O5: 09-Apr-2024 | P5: 09-Apr-2024 | Q5: 09-Apr-2024 | R5: 09-Apr-2024 | S5: 09-Apr-2024 | T5: 09-Apr-2024 | U5: 09-Apr-2024 | V5: 09-Apr-2024 | W5: 09-Apr-2024 | X5: 09-Apr-2024 | Y5: 09-Apr-2024 | Z5: 09-Apr-2024 | AA5: 09-Apr-2024 | AB5: 09-Apr-2024 | AC5: 09-Apr-2024 | AD5: 09-Apr-2024 | AE5: 09-Apr-2024 | AF5: 09-Apr-2024 | AG5: 09-Apr-2024 | AH5: 09-Apr-2024 | AI5: 09-Apr-2024 | AJ5: 09-Apr-2024 | AK5: 09-Apr-2024 | AL5: 09-Apr-2024 | AM5: 09-Apr-2024 | AN5: 09-Apr-2024 | AO5: 09-Apr-2024 | AP5: 09-Apr-2024 | AQ5: 09-Apr-2024 | AR5: 09-Apr-2024 | AS5: 09-Apr-2024 | AT5: 09-Apr-2024 | AU5: 09-Apr-2024 | AV5: 09-Apr-2024 | AW5: 09-Apr-2024 | AX5: 09-Apr-2024 | AY5: 09-Apr-2024
B6: .LSOURCE | D6: IntercontinentalExchange | E6: IntercontinentalExchange | F6: IntercontinentalExchange | G6: IntercontinentalExchange | H6: IntercontinentalExchange | I6: IntercontinentalExchange | J6: IntercontinentalExchange | K6: IntercontinentalExchange | L6: IntercontinentalExchange | M6: IntercontinentalExchange | N6: IntercontinentalExchange | O6: IntercontinentalExchange | P6: IntercontinentalExchange | Q6: IntercontinentalExchange | R6: IntercontinentalExchange | S6: IntercontinentalExchange | T6: IntercontinentalExchange | U6: IntercontinentalExchange | V6: IntercontinentalExchange | W6: IntercontinentalExchange | X6: IntercontinentalExchange | Y6: IntercontinentalExchange | Z6: IntercontinentalExchange | AA6: IntercontinentalExchange | AB6: IntercontinentalExchange | AC6: IntercontinentalExchange | AD6: IntercontinentalExchange | AE6: IntercontinentalExchange | AF6: IntercontinentalExchange | AG6: IntercontinentalExchange | AH6: IntercontinentalExchange | AI6: IntercontinentalExchange | AJ6: IntercontinentalExchange | AK6: IntercontinentalExchange | AL6: IntercontinentalExchange | AM6: IntercontinentalExchange | AN6: IntercontinentalExchange | AO6: IntercontinentalExchange | AP6: IntercontinentalExchange | AQ6: IntercontinentalExchange | AR6: IntercontinentalExchange | AS6: IntercontinentalExchange | AT6: IntercontinentalExchange | AU6: IntercontinentalExchange | AV6: IntercontinentalExchange | AW6: IntercontinentalExchange | AX6: IntercontinentalExchange | AY6: IntercontinentalExchange
B7: .DTLM | D7: Apr-10-2024 03:12 | E7: Apr-10-2024 03:12 | F7: Apr-10-2024 03:12 | G7: Apr-10-2024 03:12 | H7: Apr-10-2024 03:12 | I7: Apr-10-2024 03:12 | J7: Apr-10-2024 03:12 | K7: Apr-10-2024 03:12 | L7: Apr-10-2024 03:12 | M7: Apr-10-2024 03:12 | N7: Apr-10-2024 03:12 | O7: Apr-10-2024 03:12 | P7: Apr-10-2024 03:12 | Q7: Apr-10-2024 03:12 | R7: Apr-10-2024 03:12 | S7: Apr-10-2024 03:12 | T7: Apr-10-2024 03:12 | U7: Apr-10-2024 03:12 | V7: Apr-10-2024 03:12 | W7: Apr-10-2024 03:12 | X7: Apr-10-2024 03:12 | Y7: Apr-10-2024 03:12 | Z7: Apr-10-2024 03:12 | AA7: Apr-10-2024 03:12 | AB7: Apr-10-2024 03:12 | AC7: Apr-10-2024 03:12 | AD7: Apr-10-2024 03:12 | AE7: Apr-10-2024 03:12 | AF7: Apr-10-2024 03:12 | AG7: Apr-10-2024 03:12 | AH7: Apr-10-2024 03:12 | AI7: Apr-10-2024 03:12 | AJ7: Apr-10-2024 03:12 | AK7: Apr-10-2024 03:12 | AL7: Apr-10-2024 03:12 | AM7: Apr-10-2024 03:12 | AN7: Apr-10-2024 03:12 | AO7: Apr-10-2024 03:12 | AP7: Apr-10-2024 03:12 | AQ7: Apr-10-2024 03:12 | AR7: Apr-10-2024 03:12 | AS7: Apr-10-2024 03:12 | AT7: Apr-10-2024 03:12 | AU7: Apr-10-2024 03:12 | AV7: Apr-10-2024 03:12 | AW7: Apr-10-2024 03:12 | AX7: Apr-10-2024 03:12 | AY7: Apr-10-2024 03:12
A8: 42737 | B8: 20170102 | C8: 42737 | D8: 53.63 | E8: 52.47 | F8: 50.06 | G8: 47.79 | H8: 45.84 | I8: 45.85 | J8: 45.98 | K8: 46.29 | L8: 48.14 | M8: 51.71 | N8: 53.29 | O8: 53.87 | P8: 54.08 | Q8: 52.93 | R8: 49.32 | S8: 45.74 | T8: 44.74 | U8: 45.08 | V8: 45.24 | W8: 45.07 | X8: 48.13 | Y8: 50.28 | Z8: 50.87 | AA8: 52.84 | AB8: 52.5 | AC8: 51.06 | AD8: 46.22 | AE8: 44.8 | AF8: 44.12 | AG8: 44.36 | AH8: 44.67 | AI8: 44.99 | AJ8: 48.74 | AK8: 49.4 | AL8: 50.74 | AM8: 51.88 | AN8: 49.84 | AO8: 48.9 | AP8: 45.61 | AQ8: 44.45 | AR8: 44.25 | AS8: 44.32 | AT8: 44.69 | AU8: 45.62 | AV8: 49.02 | AW8: 50.23 | AX8: 50.66 | AY8: 51.23
A9: =+A8+1 -> 42738 | B9: 20170103 | C9: 42738 | D9: 49.45 | E9: 48.66 | F9: 46.82 | G9: 44.95 | H9: 43.2 | I9: 43.27 | J9: 43.4 | K9: 43.59 | L9: 45.19 | M9: 48.69 | N9: 50.4 | O9: 51.11 | P9: 51.29 | Q9: 49.89 | R9: 46.11 | S9: 43.32 | T9: 42.07 | U9: 42.34 | V9: 42.5 | W9: 42.32 | X9: 45.43 | Y9: 47.58 | Z9: 48.13 | AA9: 50.1 | AB9: 49.76 | AC9: 48.6 | AD9: 43.99 | AE9: 42.57 | AF9: 41.89 | AG9: 42.13 | AH9: 42.44 | AI9: 42.76 | AJ9: 46.51 | AK9: 47.17 | AL9: 48.51 | AM9: 49.65 | AN9: 47.61 | AO9: 46.67 | AP9: 43.38 | AQ9: 42.22 | AR9: 42.02 | AS9: 42.09 | AT9: 42.46 | AU9: 43.39 | AV9: 46.79 | AW9: 48 | AX9: 48.43 | AY9: 49
A10: =+A9+1 -> 42739 | B10: 20170104 | C10: 42739 | D10: 50.68 | E10: 49.81 | F10: 47.81 | G10: 45.74 | H10: 43.97 | I10: 44.04 | J10: 44.17 | K10: 44.33 | L10: 45.93 | M10: 49.43 | N10: 51.14 | O10: 51.85 | P10: 52 | Q10: 50.6 | R10: 46.84 | S10: 44.05 | T10: 42.8 | U10: 43.1 | V10: 43.27 | W10: 43.1 | X10: 46.19 | Y10: 48.32 | Z10: 48.87 | AA10: 50.84 | AB10: 50.5 | AC10: 49.34 | AD10: 44.66 | AE10: 43.24 | AF10: 42.56 | AG10: 42.8 | AH10: 43.11 | AI10: 43.43 | AJ10: 47.18 | AK10: 47.84 | AL10: 49.18 | AM10: 50.32 | AN10: 48.28 | AO10: 47.34 | AP10: 44.05 | AQ10: 42.89 | AR10: 42.69 | AS10: 42.76 | AT10: 43.13 | AU10: 44.06 | AV10: 47.46 | AW10: 48.67 | AX10: 49.1 | AY10: 49.67
A11: =+A10+1 -> 42740 | B11: 20170105 | C11: 42740 | D11: 50.69 | E11: 49.81 | F11: 47.97 | G11: 45.77 | H11: 43.87 | I11: 43.88 | J11: 44.11 | K11: 44.38 | L11: 45.9 | M11: 49.3 | N11: 50.92 | O11: 51.63 | P11: 51.78 | Q11: 50.38 | R11: 46.66 | S11: 43.87 | T11: 42.61 | U11: 42.89 | V11: 43.05 | W11: 42.78 | X11: 45.77 | Y11: 47.87 | Z11: 48.48 | AA11: 50.52 | AB11: 50.22 | AC11: 49.06 | AD11: 44.36 | AE11: 42.94 | AF11: 42.26 | AG11: 42.5 | AH11: 42.81 | AI11: 43.13 | AJ11: 46.88 | AK11: 47.54 | AL11: 48.88 | AM11: 50.02 | AN11: 47.98 | AO11: 47.04 | AP11: 43.75 | AQ11: 42.59 | AR11: 42.39 | AS11: 42.46 | AT11: 42.83 | AU11: 43.76 | AV11: 47.16 | AW11: 48.37 | AX11: 48.8 | AY11: 49.37
A12: =+A11+1 -> 42741 | B12: 20170106 | C12: 42741 | D12: 49.77 | E12: 48.99 | F12: 47.1 | G12: 44.99 | H12: 43.06 | I12: 43.06 | J12: 43.27 | K12: 43.56 | L12: 45.08 | M12: 48.48 | N12: 50.12 | O12: 50.86 | P12: 51.01 | Q12: 49.61 | R12: 45.95 | S12: 43.15 | T12: 41.88 | U12: 42.17 | V12: 42.34 | W12: 42.08 | X12: 45.05 | Y12: 47.16 | Z12: 47.77 | AA12: 49.81 | AB12: 49.51 | AC12: 48.35 | AD12: 43.65 | AE12: 42.23 | AF12: 41.55 | AG12: 41.79 | AH12: 42.1 | AI12: 42.42 | AJ12: 46.17 | AK12: 46.83 | AL12: 48.17 | AM12: 49.31 | AN12: 47.27 | AO12: 46.33 | AP12: 43.04 | AQ12: 41.88 | AR12: 41.68 | AS12: 41.75 | AT12: 42.12 | AU12: 43.05 | AV12: 46.45 | AW12: 47.66 | AX12: 48.09 | AY12: 48.66
A13: =+A8+7 -> 42744 | B13: 20170109 | C13: 42744 | D13: 51.89 | E13: 50.99 | F13: 48.61 | G13: 46.17 | H13: 44.15 | I13: 44.18 | J13: 44.27 | K13: 44.55 | L13: 46.08 | M13: 49.53 | N13: 51.22 | O13: 51.96 | P13: 52.06 | Q13: 50.56 | R13: 47.05 | S13: 44.1 | T13: 42.73 | U13: 43.02 | V13: 43.19 | W13: 42.88 | X13: 45.95 | Y13: 48.06 | Z13: 48.67 | AA13: 50.71 | AB13: 50.41 | AC13: 49.25 | AD13: 44.55 | AE13: 43.13 | AF13: 42.45 | AG13: 42.69 | AH13: 43 | AI13: 43.32 | AJ13: 47.02 | AK13: 47.63 | AL13: 48.97 | AM13: 50.11 | AN13: 48.07 | AO13: 47.13 | AP13: 43.84 | AQ13: 42.68 | AR13: 42.48 | AS13: 42.55 | AT13: 42.92 | AU13: 43.85 | AV13: 47.25 | AW13: 48.46 | AX13: 48.89 | AY13: 49.46
A14: =+A9+7 -> 42745 | B14: 20170110 | C14: 42745 | D14: 54.53 | E14: 53.35 | F14: 50.24 | G14: 47.11 | H14: 45.01 | I14: 45.23 | J14: 45.27 | K14: 45.55 | L14: 47.09 | M14: 50.54 | N14: 52.23 | O14: 53.02 | P14: 53.12 | Q14: 51.62 | R14: 48.06 | S14: 45.05 | T14: 43.63 | U14: 43.92 | V14: 44.09 | W14: 43.78 | X14: 46.88 | Y14: 48.99 | Z14: 49.6 | AA14: 51.64 | AB14: 51.34 | AC14: 50.16 | AD14: 45.4 | AE14: 43.92 | AF14: 43.2 | AG14: 43.44 | AH14: 43.75 | AI14: 44.12 | AJ14: 47.89 | AK14: 48.57 | AL14: 49.93 | AM14: 51.07 | AN14: 49.03 | AO14: 48.09 | AP14: 44.73 | AQ14: 43.52 | AR14: 43.28 | AS14: 43.35 | AT14: 43.72 | AU14: 44.65 | AV14: 48.05 | AW14: 49.26 | AX14: 49.69 | AY14: 50.26
A15: =+A10+7 -> 42746 | B15: 20170111 | C15: 42746 | D15: 55.99 | E15: 54.89 | F15: 51.14 | G15: 47.91 | H15: 45.81 | I15: 46.02 | J15: 46.07 | K15: 46.37 | L15: 47.83 | M15: 51.2 | N15: 52.86 | O15: 53.65 | P15: 53.75 | Q15: 52.25 | R15: 48.69 | S15: 45.64 | T15: 44.18 | U15: 44.47 | V15: 44.64 | W15: 44.33 | X15: 47.48 | Y15: 49.59 | Z15: 50.2 | AA15: 52.24 | AB15: 51.94 | AC15: 50.71 | AD15: 45.9 | AE15: 44.42 | AF15: 43.7 | AG15: 43.94 | AH15: 44.25 | AI15: 44.62 | AJ15: 48.39 | AK15: 49.07 | AL15: 50.43 | AM15: 51.57 | AN15: 49.53 | AO15: 48.59 | AP15: 45.23 | AQ15: 44.02 | AR15: 43.78 | AS15: 43.85 | AT15: 44.22 | AU15: 45.15 | AV15: 48.55 | AW15: 49.76 | AX15: 50.19 | AY15: 50.76
A16: =+A11+7 -> 42747 | B16: 20170112 | C16: 42747 | D16: 55.93 | E16: 54.55 | F16: 50.88 | G16: 47.57 | H16: 45.47 | I16: 45.64 | J16: 45.78 | K16: 46.13 | L16: 47.64 | M16: 51.01 | N16: 52.67 | O16: 53.51 | P16: 53.61 | Q16: 52.16 | R16: 48.65 | S16: 45.6 | T16: 44.14 | U16: 44.43 | V16: 44.6 | W16: 44.29 | X16: 47.49 | Y16: 49.6 | Z16: 50.21 | AA16: 52.25 | AB16: 51.95 | AC16: 50.72 | AD16: 45.91 | AE16: 44.43 | AF16: 43.71 | AG16: 43.95 | AH16: 44.26 | AI16: 44.63 | AJ16: 48.4 | AK16: 49.08 | AL16: 50.44 | AM16: 51.58 | AN16: 49.54 | AO16: 48.6 | AP16: 45.24 | AQ16: 44.03 | AR16: 43.79 | AS16: 43.86 | AT16: 44.23 | AU16: 45.16 | AV16: 48.56 | AW16: 49.77 | AX16: 50.2 | AY16: 50.77
A17: =+A12+7 -> 42748 | B17: 20170113 | C17: 42748 | D17: 55.08 | E17: 53.58 | F17: 50.25 | G17: 46.96 | H17: 45 | I17: 45.17 | J17: 45.31 | K17: 45.66 | L17: 47.23 | M17: 50.6 | N17: 52.26 | O17: 53.1 | P17: 53.2 | Q17: 51.75 | R17: 48.24 | S17: 45.19 | T17: 43.73 | U17: 44.02 | V17: 44.19 | W17: 43.88 | X17: 47.11 | Y17: 49.22 | Z17: 49.83 | AA17: 51.87 | AB17: 51.57 | AC17: 50.34 | AD17: 45.53 | AE17: 44.05 | AF17: 43.33 | AG17: 43.57 | AH17: 43.88 | AI17: 44.25 | AJ17: 48.02 | AK17: 48.7 | AL17: 50.06 | AM17: 51.2 | AN17: 49.16 | AO17: 48.22 | AP17: 44.86 | AQ17: 43.65 | AR17: 43.41 | AS17: 43.48 | AT17: 43.85 | AU17: 44.78 | AV17: 48.18 | AW17: 49.39 | AX17: 49.82 | AY17: 50.39
A18: =+A13+7 -> 42751 | B18: 20170116 | C18: 42751 | D18: 52.34 | E18: 51.42 | F18: 48.97 | G18: 46.17 | H18: 44.37 | I18: 44.51 | J18: 44.59 | K18: 45.01 | L18: 46.66 | M18: 50.03 | N18: 51.69 | O18: 52.54 | P18: 52.64 | Q18: 51.19 | R18: 47.71 | S18: 44.69 | T18: 43.26 | U18: 43.55 | V18: 43.72 | W18: 43.41 | X18: 46.64 | Y18: 48.75 | Z18: 49.36 | AA18: 51.4 | AB18: 51.1 | AC18: 49.87 | AD18: 45.06 | AE18: 43.58 | AF18: 42.86 | AG18: 43.1 | AH18: 43.41 | AI18: 43.78 | AJ18: 47.51 | AK18: 48.19 | AL18: 49.55 | AM18: 50.69 | AN18: 48.65 | AO18: 47.71 | AP18: 44.35 | AQ18: 43.14 | AR18: 42.9 | AS18: 42.97 | AT18: 43.34 | AU18: 44.27 | AV18: 47.67 | AW18: 48.88 | AX18: 49.31 | AY18: 49.88
A19: =+A14+7 -> 42752 | B19: 20170117 | C19: 42752 | D19: 52.74 | E19: 51.84 | F19: 49.2 | G19: 46.32 | H19: 44.5 | I19: 44.65 | J19: 44.72 | K19: 45.14 | L19: 46.79 | M19: 50.16 | N19: 51.82 | O19: 52.67 | P19: 52.77 | Q19: 51.32 | R19: 47.8 | S19: 44.78 | T19: 43.35 | U19: 43.64 | V19: 43.81 | W19: 43.5 | X19: 46.73 | Y19: 48.84 | Z19: 49.45 | AA19: 51.5 | AB19: 51.2 | AC19: 49.97 | AD19: 45.16 | AE19: 43.68 | AF19: 42.96 | AG19: 43.2 | AH19: 43.51 | AI19: 43.88 | AJ19: 47.61 | AK19: 48.29 | AL19: 49.65 | AM19: 50.79 | AN19: 48.75 | AO19: 47.81 | AP19: 44.45 | AQ19: 43.24 | AR19: 43 | AS19: 43.07 | AT19: 43.44 | AU19: 44.37 | AV19: 47.77 | AW19: 48.98 | AX19: 49.41 | AY19: 49.98
A20: =+A15+7 -> 42753 | B20: 20170118 | C20: 42753 | D20: 53.22 | E20: 52.21 | F20: 49.61 | G20: 46.81 | H20: 44.91 | I20: 45.06 | J20: 45.19 | K20: 45.55 | L20: 47.08 | M20: 50.44 | N20: 52.13 | O20: 53.01 | P20: 53.11 | Q20: 51.66 | R20: 48.06 | S20: 44.86 | T20: 43.43 | U20: 43.72 | V20: 43.89 | W20: 43.58 | X20: 46.83 | Y20: 48.94 | Z20: 49.55 | AA20: 51.6 | AB20: 51.3 | AC20: 50.07 | AD20: 45.22 | AE20: 43.74 | AF20: 43.02 | AG20: 43.26 | AH20: 43.57 | AI20: 43.94 | AJ20: 47.67 | AK20: 48.35 | AL20: 49.71 | AM20: 50.85 | AN20: 48.81 | AO20: 47.87 | AP20: 44.51 | AQ20: 43.3 | AR20: 43.06 | AS20: 43.13 | AT20: 43.5 | AU20: 44.43 | AV20: 47.83 | AW20: 49.04 | AX20: 49.47 | AY20: 50.04
A21: =+A16+7 -> 42754 | B21: 20170119 | C21: 42754 | D21: 53.61 | E21: 52.52 | F21: 49.64 | G21: 46.67 | H21: 44.77 | I21: 44.86 | J21: 45 | K21: 45.36 | L21: 46.91 | M21: 50.27 | N21: 51.96 | O21: 52.84 | P21: 52.94 | Q21: 51.54 | R21: 47.99 | S21: 44.79 | T21: 43.36 | U21: 43.67 | V21: 43.84 | W21: 43.53 | X21: 46.78 | Y21: 48.89 | Z21: 49.5 | AA21: 51.57 | AB21: 51.27 | AC21: 50.04 | AD21: 45.19 | AE21: 43.71 | AF21: 42.99 | AG21: 43.23 | AH21: 43.54 | AI21: 43.91 | AJ21: 47.59 | AK21: 48.27 | AL21: 49.63 | AM21: 50.77 | AN21: 48.73 | AO21: 47.79 | AP21: 44.43 | AQ21: 43.22 | AR21: 42.98 | AS21: 43.05 | AT21: 43.42 | AU21: 44.35 | AV21: 47.75 | AW21: 48.96 | AX21: 49.39 | AY21: 49.96
A22: =+A17+7 -> 42755 | B22: 20170120 | C22: 42755 | D22: 55.56 | E22: 54.28 | F22: 50.83 | G22: 47.33 | H22: 45.39 | I22: 45.48 | J22: 45.62 | K22: 45.98 | L22: 47.57 | M22: 50.93 | N22: 52.62 | O22: 53.5 | P22: 53.6 | Q22: 52.11 | R22: 48.68 | S22: 45.37 | T22: 43.84 | U22: 44.15 | V22: 44.32 | W22: 44.01 | X22: 47.32 | Y22: 49.52 | Z22: 50.17 | AA22: 52.28 | AB22: 51.98 | AC22: 50.75 | AD22: 45.9 | AE22: 44.42 | AF22: 43.7 | AG22: 43.94 | AH22: 44.25 | AI22: 44.62 | AJ22: 48.3 | AK22: 48.98 | AL22: 50.34 | AM22: 51.48 | AN22: 49.44 | AO22: 48.5 | AP22: 45.14 | AQ22: 43.93 | AR22: 43.69 | AS22: 43.76 | AT22: 44.13 | AU22: 45.06 | AV22: 48.46 | AW22: 49.67 | AX22: 50.1 | AY22: 50.67
A23: =+A18+7 -> 42758 | B23: 20170123 | C23: 42758 | D23: 56.78 | E23: 55.54 | F23: 51.52 | G23: 47.72 | H23: 45.78 | I23: 45.87 | J23: 46.01 | K23: 46.37 | L23: 48.01 | M23: 51.34 | N23: 53.03 | O23: 53.91 | P23: 54.01 | Q23: 52.47 | R23: 48.94 | S23: 45.48 | T23: 43.9 | U23: 44.36 | V23: 44.58 | W23: 44.27 | X23: 47.53 | Y23: 49.68 | Z23: 50.28 | AA23: 52.39 | AB23: 52.09 | AC23: 50.81 | AD23: 45.91 | AE23: 44.43 | AF23: 43.71 | AG23: 43.95 | AH23: 44.26 | AI23: 44.63 | AJ23: 48.31 | AK23: 48.99 | AL23: 50.35 | AM23: 51.49 | AN23: 49.45 | AO23: 48.51 | AP23: 45.15 | AQ23: 43.94 | AR23: 43.7 | AS23: 43.77 | AT23: 44.14 | AU23: 45.07 | AV23: 48.47 | AW23: 49.68 | AX23: 50.11 | AY23: 50.68
A24: =+A19+7 -> 42759 | B24: 20170124 | C24: 42759 | D24: 55.44 | E24: 54.5 | F24: 50.7 | G24: 47 | H24: 45.12 | I24: 45.18 | J24: 45.34 | K24: 45.7 | L24: 47.34 | M24: 50.67 | N24: 52.36 | O24: 53.2 | P24: 53.3 | Q24: 51.76 | R24: 48.28 | S24: 44.87 | T24: 43.34 | U24: 43.8 | V24: 44.02 | W24: 43.71 | X24: 46.97 | Y24: 49.12 | Z24: 49.72 | AA24: 51.83 | AB24: 51.53 | AC24: 50.25 | AD24: 45.4 | AE24: 43.97 | AF24: 43.25 | AG24: 43.49 | AH24: 43.8 | AI24: 44.17 | AJ24: 47.85 | AK24: 48.53 | AL24: 49.89 | AM24: 51.03 | AN24: 48.99 | AO24: 48 | AP24: 44.54 | AQ24: 43.23 | AR24: 42.94 | AS24: 43.01 | AT24: 43.38 | AU24: 44.31 | AV24: 47.71 | AW24: 48.92 | AX24: 49.35 | AY24: 49.92
... A81: =+A76+7 -> 42838 | B81: 20170413 | C81: 42838 | D81: 38.51 | E81: 36.92 | F81: 38.02 | G81: 38.67 | H81: 39.12 | I81: 41.02 | J81: 45.23 | K81: 47.51 | L81: 48.75 | M81: 49.19 | N81: 47.29 | O81: 43.2 | P81: 40.24 | Q81: 38.81 | R81: 39.61 | S81: 39.76 | T81: 39.62 | U81: 43.08 | V81: 45.48 | W81: 46.47 | X81: 49.18 | Y81: 48.81 | Z81: 47.04 | AA81: 41.64 | AB81: 39.42 | AC81: 38.32 | AD81: 38.43 | AE81: 38.77 | AF81: 39.83 | AG81: 43.86 | AH81: 44.9 | AI81: 46.23 | AJ81: 47.9 | AK81: 45.98 | AL81: 44.75 | AM81: 40.64 | AN81: 39.11 | AO81: 38.81 | AP81: 38.86 | AQ81: 39.41 | AR81: 40.66 | AS81: 44.8 | AT81: 46.45 | AU81: 47.2 | AV81: 47.78 | AW81: 45.21 | AX81: 43.74 | AY81: 40.8
A82: =+A77+7 -> 42839 | B82: 20170414 | C82: 42839 | D82: #N/A | E82: #N/A | F82: #N/A | G82: #N/A | H82: #N/A | I82: #N/A | J82: #N/A | K82: #N/A | L82: #N/A | M82: #N/A | N82: #N/A | O82: #N/A | P82: #N/A | Q82: #N/A | R82: #N/A | S82: #N/A | T82: #N/A | U82: #N/A | V82: #N/A | W82: #N/A | X82: #N/A | Y82: #N/A | Z82: #N/A | AA82: #N/A | AB82: #N/A | AC82: #N/A | AD82: #N/A | AE82: #N/A | AF82: #N/A | AG82: #N/A | AH82: #N/A | AI82: #N/A | AJ82: #N/A | AK82: #N/A | AL82: #N/A | AM82: #N/A | AN82: #N/A | AO82: #N/A | AP82: #N/A | AQ82: #N/A | AR82: #N/A | AS82: #N/A | AT82: #N/A | AU82: #N/A | AV82: #N/A | AW82: #N/A | AX82: #N/A | AY82: #N/A
A83: =+A78+7 -> 42842 | B83: 20170417 | C83: 42842 | D83: 38.51 | E83: 36.92 | F83: 38.02 | G83: 38.67 | H83: 39.12 | I83: 41.02 | J83: 45.23 | K83: 47.51 | L83: 48.75 | M83: 49.19 | N83: 47.29 | O83: 43.2 | P83: 40.24 | Q83: 38.81 | R83: 39.61 | S83: 39.76 | T83: 39.62 | U83: 43.08 | V83: 45.48 | W83: 46.47 | X83: 49.18 | Y83: 48.81 | Z83: 47.04 | AA83: 41.64 | AB83: 39.42 | AC83: 38.32 | AD83: 38.43 | AE83: 38.77 | AF83: 39.83 | AG83: 43.86 | AH83: 44.9 | AI83: 46.23 | AJ83: 47.9 | AK83: 45.98 | AL83: 44.75 | AM83: 40.64 | AN83: 39.11 | AO83: 38.81 | AP83: 38.86 | AQ83: 39.41 | AR83: 40.66 | AS83: 44.8 | AT83: 46.45 | AU83: 47.2 | AV83: 47.78 | AW83: 45.21 | AX83: 43.74 | AY83: 40.8
A84: =+A79+7 -> 42843 | B84: 20170418 | C84: 42843 | D84: 39.46 | E84: 37.69 | F84: 38.81 | G84: 39.48 | H84: 39.89 | I84: 41.86 | J84: 46.06 | K84: 48.35 | L84: 49.62 | M84: 50.09 | N84: 48.1 | O84: 43.85 | P84: 40.83 | Q84: 39.4 | R84: 40.2 | S84: 40.35 | T84: 40.26 | U84: 43.7 | V84: 46.1 | W84: 47.09 | X84: 49.8 | Y84: 49.43 | Z84: 47.66 | AA84: 42.08 | AB84: 39.86 | AC84: 38.76 | AD84: 38.87 | AE84: 39.21 | AF84: 40.25 | AG84: 44.11 | AH84: 45.15 | AI84: 46.48 | AJ84: 48.15 | AK84: 46.23 | AL84: 45 | AM84: 40.92 | AN84: 39.39 | AO84: 39.09 | AP84: 39.14 | AQ84: 39.69 | AR84: 40.94 | AS84: 45.08 | AT84: 46.73 | AU84: 47.48 | AV84: 48.06 | AW84: 45.49 | AX84: 44.02 | AY84: 41.08
A85: =+A80+7 -> 42844 | B85: 20170419 | C85: 42844 | D85: 39.15 | E85: 37.37 | F85: 38.4 | G85: 39.09 | H85: 39.52 | I85: 41.27 | J85: 45.43 | K85: 47.8 | L85: 48.9 | M85: 49.25 | N85: 47.37 | O85: 43.27 | P85: 40.35 | Q85: 38.94 | R85: 39.76 | S85: 39.91 | T85: 39.82 | U85: 43.31 | V85: 45.71 | W85: 46.7 | X85: 49.41 | Y85: 49.04 | Z85: 47.27 | AA85: 41.9 | AB85: 39.68 | AC85: 38.58 | AD85: 38.69 | AE85: 39.03 | AF85: 40.07 | AG85: 43.93 | AH85: 44.97 | AI85: 46.3 | AJ85: 47.97 | AK85: 46.05 | AL85: 44.82 | AM85: 40.74 | AN85: 39.21 | AO85: 38.91 | AP85: 38.96 | AQ85: 39.51 | AR85: 40.76 | AS85: 44.9 | AT85: 46.55 | AU85: 47.3 | AV85: 47.88 | AW85: 45.31 | AX85: 43.84 | AY85: 40.9
A86: =+A81+7 -> 42845 | B86: 20170420 | C86: 42845 | D86: 39.03 | E86: 37.36 | F86: 38.3 | G86: 38.95 | H86: 39.38 | I86: 41.04 | J86: 45.19 | K86: 47.06 | L86: 48.22 | M86: 48.58 | N86: 46.73 | O86: 42.89 | P86: 40.01 | Q86: 38.6 | R86: 39.42 | S86: 39.57 | T86: 39.48 | U86: 42.92 | V86: 45.32 | W86: 46.31 | X86: 49.02 | Y86: 48.65 | Z86: 46.88 | AA86: 41.55 | AB86: 39.33 | AC86: 38.23 | AD86: 38.34 | AE86: 38.68 | AF86: 39.72 | AG86: 43.58 | AH86: 44.62 | AI86: 45.95 | AJ86: 47.62 | AK86: 45.7 | AL86: 44.47 | AM86: 40.39 | AN86: 38.86 | AO86: 38.56 | AP86: 38.61 | AQ86: 39.16 | AR86: 40.41 | AS86: 44.55 | AT86: 46.2 | AU86: 46.95 | AV86: 47.53 | AW86: 44.96 | AX86: 43.49 | AY86: 40.55
A87: =+A82+7 -> 42846 | B87: 20170421 | C87: 42846 | D87: 39.58 | E87: 37.84 | F87: 38.78 | G87: 39.43 | H87: 39.83 | I87: 41.43 | J87: 45.34 | K87: 47.25 | L87: 48.3 | M87: 48.86 | N87: 47.01 | O87: 43 | P87: 40.12 | Q87: 38.71 | R87: 39.53 | S87: 39.68 | T87: 39.62 | U87: 43.06 | V87: 45.46 | W87: 46.45 | X87: 49.16 | Y87: 48.79 | Z87: 47 | AA87: 41.58 | AB87: 39.33 | AC87: 38.23 | AD87: 38.34 | AE87: 38.84 | AF87: 39.98 | AG87: 43.86 | AH87: 44.9 | AI87: 46.23 | AJ87: 47.9 | AK87: 45.98 | AL87: 44.75 | AM87: 40.67 | AN87: 39.14 | AO87: 38.84 | AP87: 38.89 | AQ87: 39.44 | AR87: 40.69 | AS87: 44.83 | AT87: 46.48 | AU87: 47.23 | AV87: 47.81 | AW87: 45.24 | AX87: 43.77 | AY87: 40.83
A88: =+A83+7 -> 42849 | B88: 20170424 | C88: 42849 | D88: 39.77 | E88: 38.08 | F88: 38.8 | G88: 39.45 | H88: 39.85 | I88: 41.45 | J88: 45.37 | K88: 47.15 | L88: 48.38 | M88: 48.8 | N88: 46.93 | O88: 42.96 | P88: 40.08 | Q88: 38.67 | R88: 39.49 | S88: 39.64 | T88: 39.6 | U88: 43.05 | V88: 45.45 | W88: 46.44 | X88: 49.15 | Y88: 48.78 | Z88: 46.99 | AA88: 41.57 | AB88: 39.32 | AC88: 38.22 | AD88: 38.33 | AE88: 38.83 | AF88: 40 | AG88: 43.91 | AH88: 44.99 | AI88: 46.32 | AJ88: 47.99 | AK88: 46.07 | AL88: 44.84 | AM88: 40.76 | AN88: 39.23 | AO88: 38.93 | AP88: 38.98 | AQ88: 39.53 | AR88: 40.78 | AS88: 44.92 | AT88: 46.57 | AU88: 47.32 | AV88: 47.9 | AW88: 45.33 | AX88: 43.86 | AY88: 40.92
A89: =+A84+7 -> 42850 | B89: 20170425 | C89: 42850 | D89: 38.88 | E89: 37.18 | F89: 37.93 | G89: 38.58 | H89: 39.04 | I89: 40.65 | J89: 44.45 | K89: 46.45 | L89: 47.52 | M89: 47.91 | N89: 46.05 | O89: 42.16 | P89: 39.3 | Q89: 37.89 | R89: 38.7 | S89: 38.83 | T89: 38.8 | U89: 42.28 | V89: 44.68 | W89: 45.67 | X89: 48.39 | Y89: 47.96 | Z89: 45.97 | AA89: 40.88 | AB89: 38.45 | AC89: 37.31 | AD89: 37.42 | AE89: 37.93 | AF89: 39.17 | AG89: 43.13 | AH89: 44.25 | AI89: 45.58 | AJ89: 47.25 | AK89: 45.33 | AL89: 44.1 | AM89: 40.02 | AN89: 38.49 | AO89: 38.19 | AP89: 38.24 | AQ89: 38.79 | AR89: 39.99 | AS89: 44.07 | AT89: 45.72 | AU89: 46.47 | AV89: 47.05 | AW89: 44.48 | AX89: 42.96 | AY89: 39.99
A90: =+A85+7 -> 42851 | B90: 20170426 | C90: 42851 | D90: 39.4 | E90: 37.7 | F90: 38.42 | G90: 39.04 | H90: 39.45 | I90: 40.99 | J90: 44.77 | K90: 46.75 | L90: 47.82 | M90: 48.21 | N90: 46.29 | O90: 42.29 | P90: 39.49 | Q90: 38.08 | R90: 38.89 | S90: 39.02 | T90: 38.96 | U90: 42.39 | V90: 44.79 | W90: 45.78 | X90: 48.5 | Y90: 48.07 | Z90: 46.08 | AA90: 40.98 | AB90: 38.55 | AC90: 37.41 | AD90: 37.52 | AE90: 38.03 | AF90: 39.22 | AG90: 43.13 | AH90: 44.25 | AI90: 45.58 | AJ90: 47.25 | AK90: 45.33 | AL90: 44.1 | AM90: 40.02 | AN90: 38.49 | AO90: 38.19 | AP90: 38.24 | AQ90: 38.79 | AR90: 39.99 | AS90: 44.07 | AT90: 45.72 | AU90: 46.47 | AV90: 47.05 | AW90: 44.48 | AX90: 42.96 | AY90: 39.99
A91: =+A86+7 -> 42852 | B91: 20170427 | C91: 42852 | D91: 39.29 | E91: 37.54 | F91: 38.24 | G91: 38.84 | H91: 39.19 | I91: 40.76 | J91: 44.53 | K91: 46.43 | L91: 47.51 | M91: 47.92 | N91: 45.99 | O91: 41.94 | P91: 39.15 | Q91: 37.74 | R91: 38.55 | S91: 38.68 | T91: 38.58 | U91: 41.94 | V91: 44.34 | W91: 45.41 | X91: 48.21 | Y91: 47.78 | Z91: 45.79 | AA91: 40.68 | AB91: 38.25 | AC91: 37.11 | AD91: 37.22 | AE91: 37.73 | AF91: 38.92 | AG91: 42.83 | AH91: 43.95 | AI91: 45.28 | AJ91: 46.95 | AK91: 45.03 | AL91: 43.8 | AM91: 39.72 | AN91: 38.19 | AO91: 37.89 | AP91: 37.94 | AQ91: 38.49 | AR91: 39.69 | AS91: 43.77 | AT91: 45.42 | AU91: 46.17 | AV91: 46.75 | AW91: 44.18 | AX91: 42.66 | AY91: 39.69
A92: =+A87+7 -> 42853 | B92: 20170428 | C92: 42853 | D92: 38.16 | E92: 38.79 | F92: 39.35 | G92: 39.68 | H92: 41.13 | I92: 44.9 | J92: 46.8 | K92: 47.88 | L92: 48.27 | M92: 46.34 | N92: 42.29 | O92: 39.5 | P92: 38.09 | Q92: 38.9 | R92: 39.03 | S92: 38.8 | T92: 42.11 | U92: 44.51 | V92: 45.58 | W92: 48.38 | X92: 47.95 | Y92: 45.96 | Z92: 40.85 | AA92: 38.42 | AB92: 37.28 | AC92: 37.39 | AD92: 37.9 | AE92: 39.05 | AF92: 42.91 | AG92: 44.03 | AH92: 45.36 | AI92: 47.03 | AJ92: 45.11 | AK92: 43.88 | AL92: 39.77 | AM92: 38.19 | AN92: 37.87 | AO92: 37.88 | AP92: 38.39 | AQ92: 39.59 | AR92: 43.65 | AS92: 45.3 | AT92: 46.05 | AU92: 46.63 | AV92: 44.06 | AW92: 42.54 | AX92: 39.57 | AY92: 38.72
A93: =+A88+7 -> 42856 | B93: 20170501 | C93: 42856 | D93: 38.16 | E93: 38.79 | F93: 39.35 | G93: 39.68 | H93: 41.13 | I93: 44.9 | J93: 46.8 | K93: 47.88 | L93: 48.27 | M93: 46.34 | N93: 42.29 | O93: 39.5 | P93: 38.09 | Q93: 38.9 | R93: 39.03 | S93: 38.8 | T93: 42.11 | U93: 44.51 | V93: 45.58 | W93: 48.38 | X93: 47.95 | Y93: 45.96 | Z93: 40.85 | AA93: 38.42 | AB93: 37.28 | AC93: 37.39 | AD93: 37.9 | AE93: 39.05 | AF93: 42.91 | AG93: 44.03 | AH93: 45.36 | AI93: 47.03 | AJ93: 45.11 | AK93: 43.88 | AL93: 39.77 | AM93: 38.19 | AN93: 37.87 | AO93: 37.88 | AP93: 38.39 | AQ93: 39.59 | AR93: 43.65 | AS93: 45.3 | AT93: 46.05 | AU93: 46.63 | AV93: 44.06 | AW93: 42.54 | AX93: 39.57 | AY93: 38.72
A94: =+A89+7 -> 42857 | B94: 20170502 | C94: 42857 | D94: 39.4 | E94: 39.88 | F94: 40.26 | G94: 40.61 | H94: 42.03 | I94: 45.68 | J94: 47.6 | K94: 48.57 | L94: 48.96 | M94: 47.03 | N94: 42.87 | O94: 40.14 | P94: 38.73 | Q94: 39.54 | R94: 39.67 | S94: 39.44 | T94: 42.76 | U94: 45.16 | V94: 46.23 | W94: 49.03 | X94: 48.6 | Y94: 46.48 | Z94: 41.33 | AA94: 38.9 | AB94: 37.76 | AC94: 37.87 | AD94: 38.38 | AE94: 39.53 | AF94: 43.32 | AG94: 44.44 | AH94: 45.77 | AI94: 47.44 | AJ94: 45.52 | AK94: 44.29 | AL94: 40.18 | AM94: 38.6 | AN94: 38.28 | AO94: 38.29 | AP94: 38.8 | AQ94: 40 | AR94: 44.06 | AS94: 45.71 | AT94: 46.46 | AU94: 47.04 | AV94: 44.47 | AW94: 42.95 | AX94: 39.98 | AY94: 39.13
... A262: =+A257+7 -> 43091 | B262: 20171222 | C262: 43091 | D262: 56.85 | E262: 57.57 | F262: 54.08 | G262: 49.25 | H262: 45.81 | I262: 42.51 | J262: 42.99 | K262: 43.73 | L262: 44.43 | M262: 47.16 | N262: 51.35 | O262: 53.6 | P262: 55.75 | Q262: 56.28 | R262: 52.97 | S262: 47.44 | T262: 42.68 | U262: 39.84 | V262: 40.06 | W262: 40.55 | X262: 41.97 | Y262: 44.78 | Z262: 47.63 | AA262: 50.58 | AB262: 53.3 | AC262: 53 | AD262: 51.2 | AE262: 44.75 | AF262: 41.14 | AG262: 39.64 | AH262: 39.46 | AI262: 39.82 | AJ262: 41.91 | AK262: 47.06 | AL262: 49.36 | AM262: 50.37 | AN262: 51.25 | AO262: 48.93 | AP262: 46.93 | AQ262: 42.55 | AR262: 41.09 | AS262: 40.99 | AT262: 41.26 | AU262: 41.71 | AV262: 42.59 | AW262: 46.81 | AX262: 48.68 | AY262: 49.58
A263: =+A258+7 -> 43094 | B263: 20171225 | C263: 43094 | D263: #N/A | E263: #N/A | F263: #N/A | G263: #N/A | H263: #N/A | I263: #N/A | J263: #N/A | K263: #N/A | L263: #N/A | M263: #N/A | N263: #N/A | O263: #N/A | P263: #N/A | Q263: #N/A | R263: #N/A | S263: #N/A | T263: #N/A | U263: #N/A | V263: #N/A | W263: #N/A | X263: #N/A | Y263: #N/A | Z263: #N/A | AA263: #N/A | AB263: #N/A | AC263: #N/A | AD263: #N/A | AE263: #N/A | AF263: #N/A | AG263: #N/A | AH263: #N/A | AI263: #N/A | AJ263: #N/A | AK263: #N/A | AL263: #N/A | AM263: #N/A | AN263: #N/A | AO263: #N/A | AP263: #N/A | AQ263: #N/A | AR263: #N/A | AS263: #N/A | AT263: #N/A | AU263: #N/A | AV263: #N/A | AW263: #N/A | AX263: #N/A | AY263: #N/A
A264: =+A259+7 -> 43095 | B264: 20171226 | C264: 43095 | D264: 56.85 | E264: 57.57 | F264: 54.08 | G264: 49.25 | H264: 45.81 | I264: 42.51 | J264: 42.99 | K264: 43.73 | L264: 44.43 | M264: 47.16 | N264: 51.35 | O264: 53.6 | P264: 55.75 | Q264: 56.28 | R264: 52.97 | S264: 47.44 | T264: 42.68 | U264: 39.84 | V264: 40.06 | W264: 40.55 | X264: 41.97 | Y264: 44.78 | Z264: 47.63 | AA264: 50.58 | AB264: 53.3 | AC264: 53 | AD264: 51.2 | AE264: 44.75 | AF264: 41.14 | AG264: 39.64 | AH264: 39.46 | AI264: 39.82 | AJ264: 41.91 | AK264: 47.06 | AL264: 49.36 | AM264: 50.37 | AN264: 51.25 | AO264: 48.93 | AP264: 46.93 | AQ264: 42.55 | AR264: 41.09 | AS264: 40.99 | AT264: 41.26 | AU264: 41.71 | AV264: 42.59 | AW264: 46.81 | AX264: 48.68 | AY264: 49.58
A265: =+A260+7 -> 43096 | B265: 20171227 | C265: 43096 | D265: 54.97 | E265: 55.49 | F265: 52.66 | G265: 48.61 | H265: 45.35 | I265: 42.18 | J265: 42.79 | K265: 43.66 | L265: 44.48 | M265: 47.13 | N265: 51.3 | O265: 53.55 | P265: 55.7 | Q265: 56.23 | R265: 52.92 | S265: 47.34 | T265: 42.59 | U265: 39.76 | V265: 39.99 | W265: 40.49 | X265: 41.92 | Y265: 44.8 | Z265: 47.65 | AA265: 50.6 | AB265: 53.32 | AC265: 53.02 | AD265: 51.22 | AE265: 44.77 | AF265: 41.16 | AG265: 39.66 | AH265: 39.48 | AI265: 39.84 | AJ265: 41.93 | AK265: 47.08 | AL265: 49.38 | AM265: 50.39 | AN265: 51.27 | AO265: 48.95 | AP265: 46.95 | AQ265: 42.57 | AR265: 41.11 | AS265: 41.01 | AT265: 41.28 | AU265: 41.73 | AV265: 42.61 | AW265: 46.82 | AX265: 48.69 | AY265: 49.59
A266: =+A261+7 -> 43097 | B266: 20171228 | C266: 43097 | D266: 56.32 | E266: 56.74 | F266: 53.69 | G266: 49.57 | H266: 46.17 | I266: 42.87 | J266: 43.22 | K266: 44.08 | L266: 44.9 | M266: 47.55 | N266: 51.72 | O266: 53.97 | P266: 56.12 | Q266: 56.65 | R266: 53.34 | S266: 47.6 | T266: 42.85 | U266: 40.02 | V266: 40.25 | W266: 40.75 | X266: 42.18 | Y266: 45.2 | Z266: 48.05 | AA266: 51 | AB266: 53.72 | AC266: 53.42 | AD266: 51.62 | AE266: 44.93 | AF266: 41.32 | AG266: 39.82 | AH266: 39.64 | AI266: 40 | AJ266: 42.09 | AK266: 47.24 | AL266: 49.54 | AM266: 50.55 | AN266: 51.43 | AO266: 49.11 | AP266: 47.11 | AQ266: 42.73 | AR266: 41.27 | AS266: 41.17 | AT266: 41.44 | AU266: 41.89 | AV266: 42.77 | AW266: 46.94 | AX266: 48.81 | AY266: 49.71
A267: =+A262+7 -> 43098 | B267: 20171229 | C267: 43098 | D267: 56.43 | E267: 53.65 | F267: 49.5 | G267: 46.05 | H267: 42.76 | I267: 43.1 | J267: 43.97 | K267: 44.83 | L267: 47.44 | M267: 51.62 | N267: 53.87 | O267: 56.03 | P267: 56.59 | Q267: 53.33 | R267: 47.71 | S267: 42.98 | T267: 40.15 | U267: 40.37 | V267: 40.86 | W267: 42.26 | X267: 45.24 | Y267: 48.08 | Z267: 51.02 | AA267: 53.73 | AB267: 53.42 | AC267: 51.61 | AD267: 44.92 | AE267: 41.3 | AF267: 39.79 | AG267: 39.6 | AH267: 39.95 | AI267: 42.03 | AJ267: 47.19 | AK267: 49.49 | AL267: 50.5 | AM267: 51.38 | AN267: 49.04 | AO267: 47.04 | AP267: 42.66 | AQ267: 41.18 | AR267: 41.06 | AS267: 41.34 | AT267: 41.8 | AU267: 42.69 | AV267: 46.89 | AW267: 48.74 | AX267: 49.61 | AY267: 50.59
A268: =+A263+7 -> 43101 | B268: 20180101 | C268: 43101 | D268: #N/A | E268: #N/A | F268: #N/A | G268: #N/A | H268: #N/A | I268: #N/A | J268: #N/A | K268: #N/A | L268: #N/A | M268: #N/A | N268: #N/A | O268: #N/A | P268: #N/A | Q268: #N/A | R268: #N/A | S268: #N/A | T268: #N/A | U268: #N/A | V268: #N/A | W268: #N/A | X268: #N/A | Y268: #N/A | Z268: #N/A | AA268: #N/A | AB268: #N/A | AC268: #N/A | AD268: #N/A | AE268: #N/A | AF268: #N/A | AG268: #N/A | AH268: #N/A | AI268: #N/A | AJ268: #N/A | AK268: #N/A | AL268: #N/A | AM268: #N/A | AN268: #N/A | AO268: #N/A | AP268: #N/A | AQ268: #N/A | AR268: #N/A | AS268: #N/A | AT268: #N/A | AU268: #N/A | AV268: #N/A | AW268: #N/A | AX268: #N/A | AY268: #N/A
A269: =+A264+7 -> 43102 | B269: 20180102 | C269: 43102 | D269: 55.25 | E269: 52.85 | F269: 49.03 | G269: 46.03 | H269: 42.78 | I269: 43.16 | J269: 44.03 | K269: 44.89 | L269: 47.51 | M269: 51.7 | N269: 53.95 | O269: 56.11 | P269: 56.67 | Q269: 53.41 | R269: 47.89 | S269: 43.2 | T269: 40.41 | U269: 40.67 | V269: 41.2 | W269: 42.64 | X269: 45.59 | Y269: 48.38 | Z269: 51.27 | AA269: 53.97 | AB269: 53.66 | AC269: 51.85 | AD269: 45.2 | AE269: 41.58 | AF269: 40.07 | AG269: 39.88 | AH269: 40.23 | AI269: 42.31 | AJ269: 47.47 | AK269: 49.77 | AL269: 50.78 | AM269: 51.66 | AN269: 49.32 | AO269: 47.32 | AP269: 42.94 | AQ269: 41.46 | AR269: 41.34 | AS269: 41.62 | AT269: 42.08 | AU269: 42.97 | AV269: 47.2 | AW269: 49.08 | AX269: 49.95 | AY269: 50.93
A270: =+A265+7 -> 43103 | B270: 20180103 | C270: 43103 | D270: 54.69 | E270: 52.65 | F270: 48.95 | G270: 45.83 | H270: 42.93 | I270: 43.21 | J270: 44.03 | K270: 44.84 | L270: 47.26 | M270: 51.77 | N270: 54.02 | O270: 56.18 | P270: 56.74 | Q270: 53.54 | R270: 47.92 | S270: 43.32 | T270: 40.53 | U270: 40.79 | V270: 41.32 | W270: 42.76 | X270: 45.67 | Y270: 48.38 | Z270: 51.27 | AA270: 54.07 | AB270: 53.76 | AC270: 51.95 | AD270: 45.25 | AE270: 41.63 | AF270: 40.12 | AG270: 39.93 | AH270: 40.28 | AI270: 42.36 | AJ270: 47.52 | AK270: 49.82 | AL270: 50.83 | AM270: 51.71 | AN270: 49.37 | AO270: 47.32 | AP270: 42.79 | AQ270: 41.26 | AR270: 41.14 | AS270: 41.42 | AT270: 41.88 | AU270: 42.77 | AV270: 47.05 | AW270: 48.93 | AX270: 49.8 | AY270: 50.78
A271: =+A266+7 -> 43104 | B271: 20180104 | C271: 43104 | D271: 54.24 | E271: 52.28 | F271: 48.78 | G271: 45.88 | H271: 43.2 | I271: 43.55 | J271: 44.37 | K271: 45.17 | L271: 47.14 | M271: 52.14 | N271: 54.39 | O271: 56.25 | P271: 56.68 | Q271: 53.48 | R271: 47.96 | S271: 43.44 | T271: 40.73 | U271: 40.99 | V271: 41.52 | W271: 42.96 | X271: 45.79 | Y271: 48.46 | Z271: 51.35 | AA271: 54.15 | AB271: 53.84 | AC271: 52.03 | AD271: 45.33 | AE271: 41.71 | AF271: 40.2 | AG271: 40.01 | AH271: 40.36 | AI271: 42.44 | AJ271: 47.6 | AK271: 49.9 | AL271: 50.91 | AM271: 51.79 | AN271: 49.45 | AO271: 47.4 | AP271: 42.87 | AQ271: 41.34 | AR271: 41.22 | AS271: 41.5 | AT271: 41.96 | AU271: 42.85 | AV271: 47.13 | AW271: 49.01 | AX271: 49.88 | AY271: 50.86
A272: =+A267+7 -> 43105 | B272: 20180105 | C272: 43105 | D272: 52.91 | E272: 51.28 | F272: 48.13 | G272: 45.45 | H272: 42.74 | I272: 43.22 | J272: 44.04 | K272: 44.84 | L272: 46.8 | M272: 51.8 | N272: 54.05 | O272: 55.88 | P272: 56.31 | Q272: 53.11 | R272: 47.71 | S272: 43.26 | T272: 40.62 | U272: 40.89 | V272: 41.42 | W272: 42.86 | X272: 45.64 | Y272: 48.26 | Z272: 51.15 | AA272: 53.95 | AB272: 53.64 | AC272: 51.83 | AD272: 45.13 | AE272: 41.51 | AF272: 40 | AG272: 39.81 | AH272: 40.16 | AI272: 42.24 | AJ272: 47.45 | AK272: 49.75 | AL272: 50.76 | AM272: 51.64 | AN272: 49.3 | AO272: 47.25 | AP272: 42.67 | AQ272: 41.09 | AR272: 40.92 | AS272: 41.16 | AT272: 41.62 | AU272: 42.51 | AV272: 46.79 | AW272: 48.67 | AX272: 49.54 | AY272: 50.52
A273: =+A268+7 -> 43108 | B273: 20180108 | C273: 43108 | D273: 53.09 | E273: 51.55 | F273: 48.22 | G273: 45.42 | H273: 42.67 | I273: 43.18 | J273: 44 | K273: 44.81 | L273: 46.84 | M273: 51.84 | N273: 54.06 | O273: 55.87 | P273: 56.3 | Q273: 53.1 | R273: 47.68 | S273: 43.23 | T273: 40.59 | U273: 40.86 | V273: 41.39 | W273: 42.83 | X273: 45.61 | Y273: 48.23 | Z273: 51.12 | AA273: 53.92 | AB273: 53.61 | AC273: 51.8 | AD273: 45.1 | AE273: 41.48 | AF273: 39.97 | AG273: 39.78 | AH273: 40.13 | AI273: 42.21 | AJ273: 47.42 | AK273: 49.72 | AL273: 50.73 | AM273: 51.61 | AN273: 49.27 | AO273: 47.22 | AP273: 42.66 | AQ273: 41.08 | AR273: 40.91 | AS273: 41.15 | AT273: 41.61 | AU273: 42.5 | AV273: 46.78 | AW273: 48.66 | AX273: 49.53 | AY273: 50.51
A274: =+A269+7 -> 43109 | B274: 20180109 | C274: 43109 | D274: 54.42 | E274: 52.75 | F274: 48.8 | G274: 45.92 | H274: 43.12 | I274: 43.66 | J274: 44.48 | K274: 45.32 | L274: 47.38 | M274: 52.37 | N274: 54.58 | O274: 56.38 | P274: 56.8 | Q274: 53.56 | R274: 48.05 | S274: 43.6 | T274: 40.96 | U274: 41.23 | V274: 41.76 | W274: 43.18 | X274: 46.04 | Y274: 48.66 | Z274: 51.55 | AA274: 54.35 | AB274: 54.04 | AC274: 52.15 | AD274: 45.3 | AE274: 41.68 | AF274: 40.17 | AG274: 39.98 | AH274: 40.33 | AI274: 42.41 | AJ274: 47.62 | AK274: 49.92 | AL274: 50.93 | AM274: 51.81 | AN274: 49.47 | AO274: 47.42 | AP274: 42.86 | AQ274: 41.28 | AR274: 41.11 | AS274: 41.35 | AT274: 41.81 | AU274: 42.7 | AV274: 46.98 | AW274: 48.86 | AX274: 49.73 | AY274: 50.71
A275: =+A270+7 -> 43110 | B275: 20180110 | C275: 43110 | D275: 54.75 | E275: 53.18 | F275: 49.43 | G275: 46.62 | H275: 43.85 | I275: 44.36 | J275: 45.19 | K275: 46.11 | L275: 48.45 | M275: 53.54 | N275: 55.75 | O275: 57.55 | P275: 57.97 | Q275: 54.72 | R275: 49.05 | S275: 44.43 | T275: 41.79 | U275: 42.06 | V275: 42.43 | W275: 44.01 | X275: 47.07 | Y275: 49.72 | Z275: 52.72 | AA275: 55.52 | AB275: 55.21 | AC275: 52.99 | AD275: 45.81 | AE275: 42.07 | AF275: 40.56 | AG275: 40.37 | AH275: 40.72 | AI275: 42.8 | AJ275: 48.01 | AK275: 50.31 | AL275: 51.32 | AM275: 52.2 | AN275: 49.86 | AO275: 47.73 | AP275: 42.92 | AQ275: 41.34 | AR275: 41.17 | AS275: 41.41 | AT275: 41.87 | AU275: 42.74 | AV275: 47.02 | AW275: 48.9 | AX275: 49.77 | AY275: 50.75
A276: =+A271+7 -> 43111 | B276: 20180111 | C276: 43111 | D276: 54.38 | E276: 52.85 | F276: 49.07 | G276: 46.26 | H276: 43.51 | I276: 44.03 | J276: 44.88 | K276: 45.78 | L276: 48.15 | M276: 53.3 | N276: 55.51 | O276: 57.31 | P276: 57.72 | Q276: 54.45 | R276: 48.72 | S276: 44.1 | T276: 41.46 | U276: 41.73 | V276: 42.1 | W276: 43.72 | X276: 46.82 | Y276: 49.47 | Z276: 52.47 | AA276: 55.27 | AB276: 54.96 | AC276: 52.67 | AD276: 45.38 | AE276: 41.61 | AF276: 40.1 | AG276: 39.91 | AH276: 40.32 | AI276: 42.44 | AJ276: 47.75 | AK276: 50.05 | AL276: 51.06 | AM276: 51.94 | AN276: 49.6 | AO276: 47.43 | AP276: 42.59 | AQ276: 41.01 | AR276: 40.84 | AS276: 41.08 | AT276: 41.54 | AU276: 42.51 | AV276: 46.89 | AW276: 48.77 | AX276: 49.64 | AY276: 50.62
A277: =+A272+7 -> 43112 | B277: 20180112 | C277: 43112 | D277: 55.97 | E277: 54.07 | F277: 49.6 | G277: 46.25 | H277: 43.3 | I277: 43.93 | J277: 44.78 | K277: 45.68 | L277: 48.18 | M277: 53.33 | N277: 55.54 | O277: 57.37 | P277: 57.78 | Q277: 54.51 | R277: 48.52 | S277: 43.9 | T277: 41.26 | U277: 41.53 | V277: 41.9 | W277: 43.52 | X277: 46.62 | Y277: 49.27 | Z277: 52.27 | AA277: 55.07 | AB277: 54.76 | AC277: 52.47 | AD277: 45.18 | AE277: 41.41 | AF277: 39.9 | AG277: 39.71 | AH277: 40.12 | AI277: 42.24 | AJ277: 47.66 | AK277: 49.96 | AL277: 50.97 | AM277: 51.85 | AN277: 49.51 | AO277: 47.34 | AP277: 42.21 | AQ277: 40.39 | AR277: 40.22 | AS277: 40.46 | AT277: 40.92 | AU277: 41.89 | AV277: 46.61 | AW277: 48.81 | AX277: 49.68 | AY277: 50.66
A278: =+A273+7 -> 43115 | B278: 20180115 | C278: 43115 | D278: 53.84 | E278: 52.3 | F278: 48.48 | G278: 45.71 | H278: 43 | I278: 43.46 | J278: 44.31 | K278: 45.11 | L278: 47.69 | M278: 52.87 | N278: 55.08 | O278: 56.91 | P278: 57.32 | Q278: 54.17 | R278: 48.17 | S278: 43.52 | T278: 40.88 | U278: 41.15 | V278: 41.52 | W278: 43.14 | X278: 46.21 | Y278: 48.86 | Z278: 51.86 | AA278: 54.66 | AB278: 54.35 | AC278: 52.06 | AD278: 44.77 | AE278: 41 | AF278: 39.49 | AG278: 39.3 | AH278: 39.71 | AI278: 41.83 | AJ278: 47.25 | AK278: 49.55 | AL278: 50.56 | AM278: 51.44 | AN278: 49.1 | AO278: 46.93 | AP278: 41.8 | AQ278: 39.98 | AR278: 39.81 | AS278: 40.05 | AT278: 40.51 | AU278: 41.56 | AV278: 46.32 | AW278: 48.53 | AX278: 49.4 | AY278: 50.38
A279: =+A274+7 -> 43116 | B279: 20180116 | C279: 43116 | D279: 53 | E279: 51.8 | F279: 47.87 | G279: 44.97 | H279: 42.24 | I279: 42.81 | J279: 43.66 | K279: 44.46 | L279: 47 | M279: 52.18 | N279: 54.39 | O279: 56.22 | P279: 56.63 | Q279: 53.52 | R279: 47.61 | S279: 42.96 | T279: 40.32 | U279: 40.59 | V279: 40.96 | W279: 42.58 | X279: 45.59 | Y279: 48.24 | Z279: 51.24 | AA279: 54.04 | AB279: 53.73 | AC279: 51.44 | AD279: 44.15 | AE279: 40.38 | AF279: 38.87 | AG279: 38.68 | AH279: 39.09 | AI279: 41.21 | AJ279: 46.58 | AK279: 48.88 | AL279: 49.89 | AM279: 50.77 | AN279: 48.43 | AO279: 46.2 | AP279: 40.93 | AQ279: 38.98 | AR279: 38.7 | AS279: 38.94 | AT279: 39.4 | AU279: 40.45 | AV279: 45.21 | AW279: 47.42 | AX279: 48.29 | AY279: 49.27
A280: =+A275+7 -> 43117 | B280: 20180117 | C280: 43117 | D280: 51.01 | E280: 49.99 | F280: 46.84 | G280: 44.32 | H280: 41.68 | I280: 42.4 | J280: 43.19 | K280: 44.01 | L280: 46.51 | M280: 51.65 | N280: 53.86 | O280: 55.69 | P280: 56.1 | Q280: 52.99 | R280: 47.09 | S280: 42.46 | T280: 39.82 | U280: 40.09 | V280: 40.46 | W280: 42.08 | X280: 45.11 | Y280: 47.76 | Z280: 50.76 | AA280: 53.56 | AB280: 53.25 | AC280: 50.9 | AD280: 43.55 | AE280: 39.74 | AF280: 38.23 | AG280: 38.04 | AH280: 38.45 | AI280: 40.46 | AJ280: 45.72 | AK280: 47.89 | AL280: 48.9 | AM280: 49.78 | AN280: 47.44 | AO280: 45.21 | AP280: 39.94 | AQ280: 37.99 | AR280: 37.71 | AS280: 37.95 | AT280: 38.41 | AU280: 39.46 | AV280: 44.22 | AW280: 46.43 | AX280: 47.3 | AY280: 48.28
... A331: =+A326+7 -> 43188 | B331: 20180329 | C331: 43188 | D331: 47.36 | E331: 44.46 | F331: 44.95 | G331: 45.44 | H331: 45.97 | I331: 47.07 | J331: 52.08 | K331: 54.97 | L331: 56.79 | M331: 57.02 | N331: 53.37 | O331: 46.9 | P331: 41.17 | Q331: 38.04 | R331: 38.6 | S331: 39.28 | T331: 41.4 | U331: 43.88 | V331: 47.03 | W331: 49.98 | X331: 52.79 | Y331: 52.76 | Z331: 49.52 | AA331: 42.67 | AB331: 38.89 | AC331: 37.21 | AD331: 36.93 | AE331: 37.57 | AF331: 40.21 | AG331: 43.83 | AH331: 46.68 | AI331: 48.26 | AJ331: 49.16 | AK331: 49.25 | AL331: 46.49 | AM331: 40.36 | AN331: 38.2 | AO331: 37.69 | AP331: 37.9 | AQ331: 38.4 | AR331: 39.92 | AS331: 45 | AT331: 47.33 | AU331: 48.23 | AV331: 49.21 | AW331: 47.69 | AX331: 45.09 | AY331: 39.59
A332: =+A327+7 -> 43189 | B332: 20180330 | C332: 43189 | D332: #N/A | E332: #N/A | F332: #N/A | G332: #N/A | H332: #N/A | I332: #N/A | J332: #N/A | K332: #N/A | L332: #N/A | M332: #N/A | N332: #N/A | O332: #N/A | P332: #N/A | Q332: #N/A | R332: #N/A | S332: #N/A | T332: #N/A | U332: #N/A | V332: #N/A | W332: #N/A | X332: #N/A | Y332: #N/A | Z332: #N/A | AA332: #N/A | AB332: #N/A | AC332: #N/A | AD332: #N/A | AE332: #N/A | AF332: #N/A | AG332: #N/A | AH332: #N/A | AI332: #N/A | AJ332: #N/A | AK332: #N/A | AL332: #N/A | AM332: #N/A | AN332: #N/A | AO332: #N/A | AP332: #N/A | AQ332: #N/A | AR332: #N/A | AS332: #N/A | AT332: #N/A | AU332: #N/A | AV332: #N/A | AW332: #N/A | AX332: #N/A | AY332: #N/A
A333: =+A328+7 -> 43192 | B333: 20180402 | C333: 43192 | D333: 47.36 | E333: 44.46 | F333: 44.95 | G333: 45.44 | H333: 45.97 | I333: 47.07 | J333: 52.08 | K333: 54.97 | L333: 56.79 | M333: 57.02 | N333: 53.37 | O333: 46.9 | P333: 41.17 | Q333: 38.04 | R333: 38.6 | S333: 39.28 | T333: 41.4 | U333: 43.88 | V333: 47.03 | W333: 49.98 | X333: 52.79 | Y333: 52.76 | Z333: 49.52 | AA333: 42.67 | AB333: 38.89 | AC333: 37.21 | AD333: 36.93 | AE333: 37.57 | AF333: 40.21 | AG333: 43.83 | AH333: 46.68 | AI333: 48.26 | AJ333: 49.16 | AK333: 49.25 | AL333: 46.49 | AM333: 40.36 | AN333: 38.2 | AO333: 37.69 | AP333: 37.9 | AQ333: 38.4 | AR333: 39.92 | AS333: 45 | AT333: 47.33 | AU333: 48.23 | AV333: 49.21 | AW333: 47.69 | AX333: 45.09 | AY333: 39.59
A334: =+A329+7 -> 43193 | B334: 20180403 | C334: 43193 | D334: 46.92 | E334: 44.23 | F334: 44.72 | G334: 45.17 | H334: 45.7 | I334: 46.8 | J334: 51.8 | K334: 54.7 | L334: 56.53 | M334: 56.76 | N334: 53.11 | O334: 46.72 | P334: 40.99 | Q334: 37.86 | R334: 38.42 | S334: 39.1 | T334: 41.22 | U334: 43.7 | V334: 46.85 | W334: 49.8 | X334: 52.61 | Y334: 52.58 | Z334: 49.34 | AA334: 42.42 | AB334: 38.61 | AC334: 36.93 | AD334: 36.65 | AE334: 37.29 | AF334: 39.93 | AG334: 43.55 | AH334: 46.4 | AI334: 47.98 | AJ334: 48.88 | AK334: 48.97 | AL334: 46.21 | AM334: 40.08 | AN334: 37.92 | AO334: 37.41 | AP334: 37.62 | AQ334: 38.12 | AR334: 39.64 | AS334: 44.72 | AT334: 47.05 | AU334: 47.95 | AV334: 48.93 | AW334: 47.41 | AX334: 44.81 | AY334: 39.31
A335: =+A330+7 -> 43194 | B335: 20180404 | C335: 43194 | D335: 47.18 | E335: 44.22 | F335: 44.72 | G335: 45.36 | H335: 45.92 | I335: 46.85 | J335: 51.4 | K335: 54.75 | L335: 56.24 | M335: 56.56 | N335: 52.92 | O335: 46.46 | P335: 40.73 | Q335: 37.6 | R335: 38.16 | S335: 38.89 | T335: 41.08 | U335: 43.64 | V335: 46.79 | W335: 49.74 | X335: 52.55 | Y335: 52.52 | Z335: 49.28 | AA335: 42.36 | AB335: 38.55 | AC335: 36.87 | AD335: 36.59 | AE335: 37.23 | AF335: 39.87 | AG335: 43.49 | AH335: 46.34 | AI335: 47.92 | AJ335: 48.82 | AK335: 48.91 | AL335: 46.15 | AM335: 40.02 | AN335: 37.86 | AO335: 37.35 | AP335: 37.56 | AQ335: 38.06 | AR335: 39.58 | AS335: 44.66 | AT335: 46.99 | AU335: 47.89 | AV335: 48.87 | AW335: 47.35 | AX335: 44.75 | AY335: 39.25
A336: =+A331+7 -> 43195 | B336: 20180405 | C336: 43195 | D336: 46.97 | E336: 44.17 | F336: 44.73 | G336: 45.2 | H336: 45.76 | I336: 46.5 | J336: 51.6 | K336: 54.81 | L336: 56.29 | M336: 56.6 | N336: 52.96 | O336: 46.48 | P336: 40.75 | Q336: 37.62 | R336: 38.18 | S336: 38.91 | T336: 41.1 | U336: 43.58 | V336: 46.72 | W336: 49.67 | X336: 52.48 | Y336: 52.45 | Z336: 49.21 | AA336: 42.29 | AB336: 38.48 | AC336: 36.8 | AD336: 36.52 | AE336: 37.16 | AF336: 39.8 | AG336: 43.48 | AH336: 46.33 | AI336: 47.91 | AJ336: 48.81 | AK336: 48.9 | AL336: 46.14 | AM336: 40.01 | AN336: 37.85 | AO336: 37.34 | AP336: 37.55 | AQ336: 38.05 | AR336: 39.57 | AS336: 44.65 | AT336: 46.98 | AU336: 47.88 | AV336: 48.86 | AW336: 47.34 | AX336: 44.74 | AY336: 39.24
A337: =+A332+7 -> 43196 | B337: 20180406 | C337: 43196 | D337: 46.87 | E337: 44.14 | F337: 44.69 | G337: 45.09 | H337: 45.62 | I337: 46.46 | J337: 51.5 | K337: 54.71 | L337: 56.19 | M337: 56.5 | N337: 52.93 | O337: 46.52 | P337: 40.79 | Q337: 37.66 | R337: 38.22 | S337: 38.95 | T337: 41.14 | U337: 43.62 | V337: 46.76 | W337: 49.71 | X337: 52.52 | Y337: 52.49 | Z337: 49.21 | AA337: 42.23 | AB337: 38.42 | AC337: 36.74 | AD337: 36.46 | AE337: 37.1 | AF337: 39.7 | AG337: 43.31 | AH337: 46.16 | AI337: 47.74 | AJ337: 48.64 | AK337: 48.73 | AL337: 45.97 | AM337: 39.84 | AN337: 37.68 | AO337: 37.17 | AP337: 37.38 | AQ337: 37.88 | AR337: 39.47 | AS337: 44.67 | AT337: 47 | AU337: 47.9 | AV337: 48.88 | AW337: 47.36 | AX337: 44.76 | AY337: 39.26
A338: =+A333+7 -> 43199 | B338: 20180409 | C338: 43199 | D338: 48.14 | E338: 45.2 | F338: 45.65 | G338: 46.2 | H338: 46.76 | I338: 47.46 | J338: 52.2 | K338: 55.38 | L338: 56.92 | M338: 57.28 | N338: 53.55 | O338: 46.92 | P338: 41.1 | Q338: 37.97 | R338: 38.53 | S338: 39.26 | T338: 41.43 | U338: 43.85 | V338: 46.99 | W338: 49.96 | X338: 52.78 | Y338: 52.75 | Z338: 49.47 | AA338: 42.49 | AB338: 38.68 | AC338: 37 | AD338: 36.72 | AE338: 37.36 | AF338: 39.96 | AG338: 43.57 | AH338: 46.42 | AI338: 48 | AJ338: 48.9 | AK338: 48.99 | AL338: 46.23 | AM338: 40.1 | AN338: 37.94 | AO338: 37.43 | AP338: 37.64 | AQ338: 38.14 | AR338: 39.73 | AS338: 44.93 | AT338: 47.26 | AU338: 48.16 | AV338: 49.14 | AW338: 47.62 | AX338: 45.02 | AY338: 39.52
A339: =+A334+7 -> 43200 | B339: 20180410 | C339: 43200 | D339: 48.56 | E339: 45.69 | F339: 46.12 | G339: 46.62 | H339: 47.19 | I339: 47.91 | J339: 52.7 | K339: 55.91 | L339: 57.48 | M339: 57.84 | N339: 54.07 | O339: 47.33 | P339: 41.46 | Q339: 38.33 | R339: 38.89 | S339: 39.62 | T339: 41.74 | U339: 44.08 | V339: 47.22 | W339: 50.19 | X339: 53.01 | Y339: 52.98 | Z339: 49.7 | AA339: 42.84 | AB339: 39.03 | AC339: 37.35 | AD339: 37.07 | AE339: 37.71 | AF339: 40.31 | AG339: 43.92 | AH339: 46.77 | AI339: 48.35 | AJ339: 49.25 | AK339: 49.34 | AL339: 46.58 | AM339: 40.45 | AN339: 38.29 | AO339: 37.78 | AP339: 37.99 | AQ339: 38.49 | AR339: 40.08 | AS339: 45.28 | AT339: 47.61 | AU339: 48.51 | AV339: 49.49 | AW339: 47.97 | AX339: 45.37 | AY339: 39.87
A340: =+A335+7 -> 43201 | B340: 20180411 | C340: 43201 | D340: 49.95 | E340: 47.11 | F340: 47.48 | G340: 47.99 | H340: 48.53 | I340: 49.18 | J340: 53.94 | K340: 57.07 | L340: 58.73 | M340: 59.06 | N340: 55.14 | O340: 48.22 | P340: 42.32 | Q340: 39.19 | R340: 39.76 | S340: 40.5 | T340: 42.71 | U340: 45.13 | V340: 48.27 | W340: 51.24 | X340: 54.06 | Y340: 54.03 | Z340: 50.56 | AA340: 43.51 | AB340: 39.7 | AC340: 38.02 | AD340: 37.74 | AE340: 38.38 | AF340: 40.96 | AG340: 44.53 | AH340: 47.38 | AI340: 48.96 | AJ340: 49.86 | AK340: 49.95 | AL340: 47.19 | AM340: 41.06 | AN340: 38.9 | AO340: 38.39 | AP340: 38.6 | AQ340: 39.1 | AR340: 40.69 | AS340: 45.89 | AT340: 48.22 | AU340: 49.12 | AV340: 50.1 | AW340: 48.58 | AX340: 45.98 | AY340: 40.48
A341: =+A336+7 -> 43202 | B341: 20180412 | C341: 43202 | D341: 49.25 | E341: 46.64 | F341: 46.99 | G341: 47.58 | H341: 48.06 | I341: 48.72 | J341: 53.72 | K341: 56.85 | L341: 58.38 | M341: 58.71 | N341: 54.91 | O341: 47.87 | P341: 41.97 | Q341: 38.84 | R341: 39.41 | S341: 40.15 | T341: 42.36 | U341: 44.85 | V341: 47.99 | W341: 50.96 | X341: 53.78 | Y341: 53.75 | Z341: 50.35 | AA341: 43.5 | AB341: 39.74 | AC341: 38.06 | AD341: 37.78 | AE341: 38.42 | AF341: 41.08 | AG341: 44.73 | AH341: 47.63 | AI341: 49.21 | AJ341: 50.11 | AK341: 50.14 | AL341: 47.35 | AM341: 41.16 | AN341: 39 | AO341: 38.49 | AP341: 38.7 | AQ341: 39.2 | AR341: 40.79 | AS341: 45.99 | AT341: 48.32 | AU341: 49.22 | AV341: 50.2 | AW341: 48.68 | AX341: 46.08 | AY341: 40.58
A342: =+A337+7 -> 43203 | B342: 20180413 | C342: 43203 | D342: 50.35 | E342: 47.7 | F342: 47.97 | G342: 48.44 | H342: 48.88 | I342: 49.6 | J342: 54.66 | K342: 57.75 | L342: 59.4 | M342: 59.73 | N342: 55.83 | O342: 48.93 | P342: 42.62 | Q342: 39.26 | R342: 39.83 | S342: 40.61 | T342: 42.87 | U342: 45.41 | V342: 48.6 | W342: 51.57 | X342: 54.39 | Y342: 54.28 | Z342: 50.78 | AA342: 43.81 | AB342: 39.72 | AC342: 38.04 | AD342: 37.76 | AE342: 38.4 | AF342: 41.06 | AG342: 44.74 | AH342: 47.64 | AI342: 49.22 | AJ342: 50.12 | AK342: 50.15 | AL342: 47.36 | AM342: 41.17 | AN342: 39.01 | AO342: 38.5 | AP342: 38.71 | AQ342: 39.21 | AR342: 40.8 | AS342: 46 | AT342: 48.33 | AU342: 49.23 | AV342: 50.21 | AW342: 48.69 | AX342: 46.09 | AY342: 40.59
A343: =+A338+7 -> 43206 | B343: 20180416 | C343: 43206 | D343: 49.61 | E343: 47.62 | F343: 47.75 | G343: 48.15 | H343: 48.55 | I343: 49.21 | J343: 54.26 | K343: 57.35 | L343: 59 | M343: 59.33 | N343: 55.43 | O343: 48.76 | P343: 42.56 | Q343: 39.2 | R343: 39.77 | S343: 40.55 | T343: 42.81 | U343: 45.27 | V343: 48.46 | W343: 51.43 | X343: 54.25 | Y343: 54.14 | Z343: 50.64 | AA343: 43.54 | AB343: 39.45 | AC343: 37.77 | AD343: 37.49 | AE343: 38.13 | AF343: 40.79 | AG343: 44.47 | AH343: 47.37 | AI343: 48.95 | AJ343: 49.85 | AK343: 49.88 | AL343: 47.09 | AM343: 40.9 | AN343: 38.74 | AO343: 38.23 | AP343: 38.44 | AQ343: 38.94 | AR343: 40.53 | AS343: 45.73 | AT343: 48.06 | AU343: 48.96 | AV343: 49.94 | AW343: 48.42 | AX343: 45.75 | AY343: 40.25
A344: =+A339+7 -> 43207 | B344: 20180417 | C344: 43207 | D344: 48.67 | E344: 46.87 | F344: 46.87 | G344: 47.3 | H344: 47.66 | I344: 48.02 | J344: 53.24 | K344: 56.46 | L344: 57.89 | M344: 58.29 | N344: 54.6 | O344: 48.16 | P344: 42.13 | Q344: 38.77 | R344: 39.34 | S344: 40.12 | T344: 42.42 | U344: 44.8 | V344: 47.99 | W344: 50.96 | X344: 53.78 | Y344: 53.67 | Z344: 50.17 | AA344: 43.07 | AB344: 38.98 | AC344: 37.3 | AD344: 37.02 | AE344: 37.66 | AF344: 40.32 | AG344: 44 | AH344: 46.9 | AI344: 48.48 | AJ344: 49.38 | AK344: 49.41 | AL344: 46.62 | AM344: 40.43 | AN344: 38.27 | AO344: 37.76 | AP344: 37.97 | AQ344: 38.47 | AR344: 40.06 | AS344: 45.26 | AT344: 47.59 | AU344: 48.49 | AV344: 49.47 | AW344: 47.95 | AX344: 45.28 | AY344: 39.78
... A523: =+A518+7 -> 43458 | B523: 20181224 | C523: 43458 | D523: 67.34 | E523: 67.36 | F523: 65.35 | G523: 60.49 | H523: 57.4 | I523: 55.19 | J523: 54.97 | K523: 54.99 | L523: 57.48 | M523: 59.85 | N523: 63.32 | O523: 65.58 | P523: 67.7 | Q523: 67.43 | R523: 64.08 | S523: 56.28 | T523: 50.69 | U523: 48.23 | V523: 48.15 | W523: 48.84 | X523: 51.67 | Y523: 54.97 | Z523: 57.55 | AA523: 59.28 | AB523: 61.43 | AC523: 61.11 | AD523: 57.63 | AE523: 50.25 | AF523: 46.44 | AG523: 46.04 | AH523: 46.29 | AI523: 47.2 | AJ523: 49.63 | AK523: 54.05 | AL523: 56.48 | AM523: 57.55 | AN523: 58.19 | AO523: 56.57 | AP523: 53.35 | AQ523: 47.63 | AR523: 45.82 | AS523: 44.71 | AT523: 44.6 | AU523: 44.88 | AV523: 46.21 | AW523: 51.7 | AX523: 54.18 | AY523: 55.64
A524: =+A519+7 -> 43459 | B524: 20181225 | C524: 43459 | D524: #N/A | E524: #N/A | F524: #N/A | G524: #N/A | H524: #N/A | I524: #N/A | J524: #N/A | K524: #N/A | L524: #N/A | M524: #N/A | N524: #N/A | O524: #N/A | P524: #N/A | Q524: #N/A | R524: #N/A | S524: #N/A | T524: #N/A | U524: #N/A | V524: #N/A | W524: #N/A | X524: #N/A | Y524: #N/A | Z524: #N/A | AA524: #N/A | AB524: #N/A | AC524: #N/A | AD524: #N/A | AE524: #N/A | AF524: #N/A | AG524: #N/A | AH524: #N/A | AI524: #N/A | AJ524: #N/A | AK524: #N/A | AL524: #N/A | AM524: #N/A | AN524: #N/A | AO524: #N/A | AP524: #N/A | AQ524: #N/A | AR524: #N/A | AS524: #N/A | AT524: #N/A | AU524: #N/A | AV524: #N/A | AW524: #N/A | AX524: #N/A | AY524: #N/A
A525: =+A520+7 -> 43460 | B525: 20181226 | C525: 43460 | D525: 67.34 | E525: 67.36 | F525: 65.35 | G525: 60.49 | H525: 57.4 | I525: 55.19 | J525: 54.97 | K525: 54.99 | L525: 57.48 | M525: 59.85 | N525: 63.32 | O525: 65.58 | P525: 67.7 | Q525: 67.43 | R525: 64.08 | S525: 56.28 | T525: 50.69 | U525: 48.23 | V525: 48.15 | W525: 48.84 | X525: 51.67 | Y525: 54.97 | Z525: 57.55 | AA525: 59.28 | AB525: 61.43 | AC525: 61.11 | AD525: 57.63 | AE525: 50.25 | AF525: 46.44 | AG525: 46.04 | AH525: 46.29 | AI525: 47.2 | AJ525: 49.63 | AK525: 54.05 | AL525: 56.48 | AM525: 57.55 | AN525: 58.19 | AO525: 56.57 | AP525: 53.35 | AQ525: 47.63 | AR525: 45.82 | AS525: 44.71 | AT525: 44.6 | AU525: 44.88 | AV525: 46.21 | AW525: 51.7 | AX525: 54.18 | AY525: 55.64
A526: =+A521+7 -> 43461 | B526: 20181227 | C526: 43461 | D526: 64.36 | E526: 64.77 | F526: 63.09 | G526: 58.8 | H526: 56.04 | I526: 54.22 | J526: 53.94 | K526: 53.92 | L526: 56.42 | M526: 58.86 | N526: 62.4 | O526: 64.68 | P526: 66.82 | Q526: 66.57 | R526: 63.22 | S526: 55.5 | T526: 49.99 | U526: 47.61 | V526: 47.61 | W526: 48.38 | X526: 51.25 | Y526: 54.6 | Z526: 57.23 | AA526: 59.01 | AB526: 61.21 | AC526: 60.94 | AD526: 57.51 | AE526: 50.09 | AF526: 46.25 | AG526: 45.83 | AH526: 46.08 | AI526: 46.99 | AJ526: 49.42 | AK526: 53.69 | AL526: 55.99 | AM526: 56.94 | AN526: 57.47 | AO526: 55.8 | AP526: 52.58 | AQ526: 46.86 | AR526: 45.05 | AS526: 43.94 | AT526: 43.83 | AU526: 44.11 | AV526: 45.44 | AW526: 50.93 | AX526: 53.41 | AY526: 54.87
A527: =+A522+7 -> 43462 | B527: 20181228 | C527: 43462 | D527: 62.63 | E527: 63.29 | F527: 61.7 | G527: 57.96 | H527: 56.03 | I527: 53.68 | J527: 53.68 | K527: 53.24 | L527: 56.57 | M527: 58.96 | N527: 62.34 | O527: 64.46 | P527: 66.41 | Q527: 66 | R527: 62.65 | S527: 55.02 | T527: 49.6 | U527: 47.3 | V527: 47.37 | W527: 48.2 | X527: 51.07 | Y527: 54.33 | Z527: 56.88 | AA527: 58.6 | AB527: 60.8 | AC527: 60.53 | AD527: 57.1 | AE527: 49.54 | AF527: 45.64 | AG527: 45.17 | AH527: 45.42 | AI527: 46.33 | AJ527: 48.76 | AK527: 52.98 | AL527: 55.33 | AM527: 56.32 | AN527: 56.89 | AO527: 55.26 | AP527: 52.04 | AQ527: 46.41 | AR527: 44.6 | AS527: 43.49 | AT527: 43.38 | AU527: 43.66 | AV527: 44.99 | AW527: 50.48 | AX527: 52.96 | AY527: 54.42
A528: =+A523+7 -> 43465 | B528: 20181231 | C528: 43465 | D528: 61.07 | E528: 59.55 | F528: 55.9 | G528: 54.2 | H528: 52.11 | I528: 52 | J528: 51.27 | K528: 54.64 | L528: 57.05 | M528: 60.51 | N528: 62.63 | O528: 64.58 | P528: 64.21 | Q528: 61.06 | R528: 53.68 | S528: 48.36 | T528: 46.06 | U528: 46.13 | V528: 46.96 | W528: 49.93 | X528: 53.31 | Y528: 55.86 | Z528: 57.58 | AA528: 59.78 | AB528: 59.51 | AC528: 56.08 | AD528: 48.52 | AE528: 44.62 | AF528: 44.15 | AG528: 44.4 | AH528: 45.31 | AI528: 47.86 | AJ528: 52.2 | AK528: 54.55 | AL528: 55.54 | AM528: 56.11 | AN528: 54.48 | AO528: 51.26 | AP528: 45.56 | AQ528: 43.69 | AR528: 42.58 | AS528: 42.47 | AT528: 42.72 | AU528: 43.89 | AV528: 49.22 | AW528: 51.7 | AX528: 53.16 | AY528: 54.19
A529: =+A524+7 -> 43466 | B529: 20190101 | C529: 43466 | D529: #N/A | E529: #N/A | F529: #N/A | G529: #N/A | H529: #N/A | I529: #N/A | J529: #N/A | K529: #N/A | L529: #N/A | M529: #N/A | N529: #N/A | O529: #N/A | P529: #N/A | Q529: #N/A | R529: #N/A | S529: #N/A | T529: #N/A | U529: #N/A | V529: #N/A | W529: #N/A | X529: #N/A | Y529: #N/A | Z529: #N/A | AA529: #N/A | AB529: #N/A | AC529: #N/A | AD529: #N/A | AE529: #N/A | AF529: #N/A | AG529: #N/A | AH529: #N/A | AI529: #N/A | AJ529: #N/A | AK529: #N/A | AL529: #N/A | AM529: #N/A | AN529: #N/A | AO529: #N/A | AP529: #N/A | AQ529: #N/A | AR529: #N/A | AS529: #N/A | AT529: #N/A | AU529: #N/A | AV529: #N/A | AW529: #N/A | AX529: #N/A | AY529: #N/A
A530: =+A525+7 -> 43467 | B530: 20190102 | C530: 43467 | D530: 62.16 | E530: 60.65 | F530: 56.84 | G530: 54.47 | H530: 52.29 | I530: 52.28 | J530: 51.93 | K530: 55.22 | L530: 57.55 | M530: 61.01 | N530: 63.13 | O530: 65.08 | P530: 64.71 | Q530: 61.55 | R530: 54.2 | S530: 48.86 | T530: 46.56 | U530: 46.63 | V530: 47.46 | W530: 50.42 | X530: 53.67 | Y530: 56.22 | Z530: 57.94 | AA530: 60.14 | AB530: 59.74 | AC530: 56.24 | AD530: 48.73 | AE530: 44.83 | AF530: 44.36 | AG530: 44.61 | AH530: 45.52 | AI530: 48.07 | AJ530: 52.46 | AK530: 54.84 | AL530: 55.83 | AM530: 56.4 | AN530: 54.77 | AO530: 51.55 | AP530: 45.85 | AQ530: 43.98 | AR530: 42.87 | AS530: 42.76 | AT530: 43.01 | AU530: 44.18 | AV530: 49.51 | AW530: 51.99 | AX530: 53.45 | AY530: 54.48
A531: =+A526+7 -> 43468 | B531: 20190103 | C531: 43468 | D531: 61.81 | E531: 60.25 | F531: 56.44 | G531: 53.83 | H531: 51.94 | I531: 51.7 | J531: 51.81 | K531: 54.58 | L531: 56.88 | M531: 60.39 | N531: 62.67 | O531: 64.77 | P531: 64.53 | Q531: 61.42 | R531: 54.02 | S531: 48.62 | T531: 46.32 | U531: 46.39 | V531: 47.22 | W531: 50.17 | X531: 53.56 | Y531: 56.18 | Z531: 57.86 | AA531: 60.04 | AB531: 59.56 | AC531: 55.94 | AD531: 48.37 | AE531: 44.45 | AF531: 44.09 | AG531: 44.52 | AH531: 45.52 | AI531: 48.19 | AJ531: 52.5 | AK531: 54.92 | AL531: 55.91 | AM531: 56.48 | AN531: 54.85 | AO531: 51.63 | AP531: 45.93 | AQ531: 44.06 | AR531: 42.95 | AS531: 42.84 | AT531: 43.09 | AU531: 44.26 | AV531: 49.59 | AW531: 52.07 | AX531: 53.53 | AY531: 54.56
A532: =+A527+7 -> 43469 | B532: 20190104 | C532: 43469 | D532: 63.55 | E532: 61.73 | F532: 57.67 | G532: 55.08 | H532: 52.97 | I532: 52.97 | J532: 53.24 | K532: 55.36 | L532: 57.91 | M532: 61.46 | N532: 63.76 | O532: 65.86 | P532: 65.62 | Q532: 62.51 | R532: 54.97 | S532: 49.51 | T532: 47.21 | U532: 47.28 | V532: 48.11 | W532: 51.06 | X532: 54.49 | Y532: 57.16 | Z532: 58.84 | AA532: 61.02 | AB532: 60.54 | AC532: 56.92 | AD532: 49.37 | AE532: 45.49 | AF532: 45.14 | AG532: 45.57 | AH532: 46.57 | AI532: 49.24 | AJ532: 53.53 | AK532: 55.95 | AL532: 56.94 | AM532: 57.51 | AN532: 55.88 | AO532: 52.66 | AP532: 46.88 | AQ532: 45.01 | AR532: 43.9 | AS532: 43.79 | AT532: 44.04 | AU532: 45.21 | AV532: 50.54 | AW532: 53.02 | AX532: 54.48 | AY532: 55.51
A533: =+A528+7 -> 43472 | B533: 20190107 | C533: 43472 | D533: 59.26 | E533: 58.04 | F533: 54.92 | G533: 52.97 | H533: 50.91 | I533: 50.9 | J533: 51.28 | K533: 53.45 | L533: 56.03 | M533: 59.74 | N533: 62.21 | O533: 64.31 | P533: 64.07 | Q533: 60.96 | R533: 53.64 | S533: 48.34 | T533: 46.2 | U533: 46.41 | V533: 47.36 | W533: 50.43 | X533: 53.77 | Y533: 56.35 | Z533: 57.94 | AA533: 60.14 | AB533: 59.7 | AC533: 56.13 | AD533: 48.62 | AE533: 44.79 | AF533: 44.49 | AG533: 44.97 | AH533: 46.02 | AI533: 48.69 | AJ533: 52.95 | AK533: 55.35 | AL533: 56.32 | AM533: 56.87 | AN533: 55.22 | AO533: 52 | AP533: 46.19 | AQ533: 44.28 | AR533: 43.13 | AS533: 43.02 | AT533: 43.27 | AU533: 44.44 | AV533: 49.77 | AW533: 52.25 | AX533: 53.71 | AY533: 54.74
A534: =+A529+7 -> 43473 | B534: 20190108 | C534: 43473 | D534: 60.73 | E534: 59.39 | F534: 56.03 | G534: 53.96 | H534: 52.1 | I534: 52.18 | J534: 52.27 | K534: 54.35 | L534: 56.94 | M534: 60.66 | N534: 63.14 | O534: 65.15 | P534: 64.89 | Q534: 61.79 | R534: 54.44 | S534: 49.11 | T534: 46.94 | U534: 47.21 | V534: 48.17 | W534: 51.24 | X534: 54.52 | Y534: 57.04 | Z534: 58.62 | AA534: 60.81 | AB534: 60.36 | AC534: 56.78 | AD534: 49.28 | AE534: 45.46 | AF534: 45.17 | AG534: 45.66 | AH534: 46.72 | AI534: 49.39 | AJ534: 53.65 | AK534: 56.05 | AL534: 57.02 | AM534: 57.57 | AN534: 55.92 | AO534: 52.7 | AP534: 46.89 | AQ534: 44.98 | AR534: 43.83 | AS534: 43.72 | AT534: 43.97 | AU534: 45.14 | AV534: 50.47 | AW534: 52.95 | AX534: 54.41 | AY534: 55.44
A535: =+A530+7 -> 43474 | B535: 20190109 | C535: 43474 | D535: 60.03 | E535: 58.46 | F535: 55.06 | G535: 52.84 | H535: 50.97 | I535: 51.06 | J535: 51.23 | K535: 53.32 | L535: 56.23 | M535: 60.15 | N535: 62.71 | O535: 64.68 | P535: 64.39 | Q535: 61.29 | R535: 53.9 | S535: 48.63 | T535: 46.5 | U535: 46.78 | V535: 47.75 | W535: 50.83 | X535: 54.23 | Y535: 56.82 | Z535: 58.4 | AA535: 60.59 | AB535: 60.14 | AC535: 56.56 | AD535: 49.19 | AE535: 45.48 | AF535: 45.29 | AG535: 45.78 | AH535: 46.84 | AI535: 49.51 | AJ535: 53.77 | AK535: 56.17 | AL535: 57.14 | AM535: 57.69 | AN535: 56.04 | AO535: 52.82 | AP535: 47.01 | AQ535: 45.1 | AR535: 43.95 | AS535: 43.84 | AT535: 44.09 | AU535: 45.26 | AV535: 50.59 | AW535: 53.07 | AX535: 54.53 | AY535: 55.56
A536: =+A531+7 -> 43475 | B536: 20190110 | C536: 43475 | D536: 59.87 | E536: 58.44 | F536: 55.06 | G536: 52.87 | H536: 51 | I536: 51.16 | J536: 51.36 | K536: 53.45 | L536: 56.37 | M536: 60.29 | N536: 62.85 | O536: 64.82 | P536: 64.58 | Q536: 61.48 | R536: 54.18 | S536: 48.97 | T536: 46.89 | U536: 47.1 | V536: 48.01 | W536: 51.09 | X536: 54.6 | Y536: 57.3 | Z536: 58.89 | AA536: 61.08 | AB536: 60.63 | AC536: 57.05 | AD536: 49.68 | AE536: 45.97 | AF536: 45.78 | AG536: 46.27 | AH536: 47.33 | AI536: 50 | AJ536: 54.26 | AK536: 56.66 | AL536: 57.63 | AM536: 58.18 | AN536: 56.53 | AO536: 53.31 | AP536: 47.5 | AQ536: 45.59 | AR536: 44.44 | AS536: 44.33 | AT536: 44.58 | AU536: 45.75 | AV536: 51.08 | AW536: 53.56 | AX536: 55.02 | AY536: 56.05
A537: =+A532+7 -> 43476 | B537: 20190111 | C537: 43476 | D537: 61.39 | E537: 59.51 | F537: 55.98 | G537: 53.51 | H537: 51.51 | I537: 51.68 | J537: 51.89 | K537: 53.88 | L537: 57.15 | M537: 61.1 | N537: 62.97 | O537: 65.3 | P537: 65.06 | Q537: 61.96 | R537: 54.56 | S537: 49.23 | T537: 47.1 | U537: 47.31 | V537: 48.22 | W537: 51.3 | X537: 54.81 | Y537: 57.51 | Z537: 59.1 | AA537: 61.29 | AB537: 60.84 | AC537: 57.26 | AD537: 49.89 | AE537: 46.18 | AF537: 45.99 | AG537: 46.48 | AH537: 47.54 | AI537: 50.2 | AJ537: 54.45 | AK537: 56.84 | AL537: 57.8 | AM537: 58.34 | AN537: 56.68 | AO537: 53.45 | AP537: 47.64 | AQ537: 45.73 | AR537: 44.58 | AS537: 44.47 | AT537: 44.72 | AU537: 45.89 | AV537: 51.22 | AW537: 53.7 | AX537: 55.16 | AY537: 56.19
A538: =+A533+7 -> 43479 | B538: 20190114 | C538: 43479 | D538: 59.3 | E538: 57.46 | F538: 54.06 | G538: 52.05 | H538: 50.13 | I538: 50.32 | J538: 50.54 | K538: 52.7 | L538: 56 | M538: 59.89 | N538: 61.76 | O538: 64.09 | P538: 63.85 | Q538: 60.84 | R538: 53.73 | S538: 48.52 | T538: 46.39 | U538: 46.6 | V538: 47.51 | W538: 50.59 | X538: 54.05 | Y538: 56.75 | Z538: 58.34 | AA538: 60.53 | AB538: 60.05 | AC538: 56.45 | AD538: 49.08 | AE538: 45.37 | AF538: 45.18 | AG538: 45.67 | AH538: 46.73 | AI538: 49.39 | AJ538: 53.64 | AK538: 56.03 | AL538: 56.99 | AM538: 57.53 | AN538: 55.87 | AO538: 52.64 | AP538: 46.83 | AQ538: 44.92 | AR538: 43.77 | AS538: 43.66 | AT538: 43.91 | AU538: 45.08 | AV538: 50.41 | AW538: 52.89 | AX538: 54.35 | AY538: 55.38
A539: =+A534+7 -> 43480 | B539: 20190115 | C539: 43480 | D539: 60.61 | E539: 58.72 | F539: 55.3 | G539: 53.29 | H539: 51.09 | I539: 51.28 | J539: 51.69 | K539: 53.8 | L539: 56.65 | M539: 60.86 | N539: 62.73 | O539: 65.01 | P539: 64.77 | Q539: 61.72 | R539: 54.49 | S539: 49.27 | T539: 47.14 | U539: 47.35 | V539: 48.26 | W539: 51.3 | X539: 54.75 | Y539: 57.45 | Z539: 59.04 | AA539: 61.23 | AB539: 60.75 | AC539: 57.09 | AD539: 49.76 | AE539: 46.08 | AF539: 45.89 | AG539: 46.38 | AH539: 47.44 | AI539: 50.1 | AJ539: 54.35 | AK539: 56.74 | AL539: 57.7 | AM539: 58.24 | AN539: 56.58 | AO539: 53.35 | AP539: 47.5 | AQ539: 45.59 | AR539: 44.44 | AS539: 44.33 | AT539: 44.61 | AU539: 45.88 | AV539: 51.31 | AW539: 53.87 | AX539: 55.33 | AY539: 56.36
A540: =+A535+7 -> 43481 | B540: 20190116 | C540: 43481 | D540: 60.15 | E540: 58.3 | F540: 55.09 | G540: 53.19 | H540: 51.1 | I540: 51.11 | J540: 51.59 | K540: 53.75 | L540: 56.72 | M540: 60.98 | N540: 62.88 | O540: 65 | P540: 64.76 | Q540: 61.71 | R540: 54.56 | S540: 49.4 | T540: 47.27 | U540: 47.48 | V540: 48.39 | W540: 51.43 | X540: 54.93 | Y540: 57.63 | Z540: 59.22 | AA540: 61.41 | AB540: 60.94 | AC540: 57.22 | AD540: 49.89 | AE540: 46.21 | AF540: 46.02 | AG540: 46.51 | AH540: 47.57 | AI540: 50.23 | AJ540: 54.48 | AK540: 56.87 | AL540: 57.83 | AM540: 58.37 | AN540: 56.71 | AO540: 53.48 | AP540: 47.63 | AQ540: 45.72 | AR540: 44.57 | AS540: 44.46 | AT540: 44.74 | AU540: 46.01 | AV540: 51.34 | AW540: 53.9 | AX540: 55.36 | AY540: 56.39
A541: =+A536+7 -> 43482 | B541: 20190117 | C541: 43482 | D541: 62.97 | E541: 60.73 | F541: 57.58 | G541: 55.54 | H541: 53.52 | I541: 53.63 | J541: 54.11 | K541: 56.15 | L541: 58.99 | M541: 63.13 | N541: 64.89 | O541: 66.86 | P541: 66.64 | Q541: 63.57 | R541: 56.24 | S541: 50.99 | T541: 48.74 | U541: 48.86 | V541: 49.77 | W541: 52.81 | X541: 56.2 | Y541: 58.9 | Z541: 60.49 | AA541: 62.68 | AB541: 62.12 | AC541: 58.36 | AD541: 51.05 | AE541: 47.38 | AF541: 46.94 | AG541: 47.07 | AH541: 48.04 | AI541: 50.82 | AJ541: 55.19 | AK541: 57.65 | AL541: 58.61 | AM541: 59.15 | AN541: 57.49 | AO541: 54.26 | AP541: 48.41 | AQ541: 46.5 | AR541: 45.35 | AS541: 45.24 | AT541: 45.52 | AU541: 46.79 | AV541: 52.12 | AW541: 54.68 | AX541: 56.14 | AY541: 57.17
... A606: =+A601+7 -> 43573 | B606: 20190418 | C606: 43573 | D606: 34.41 | E606: 33.75 | F606: 34.75 | G606: 37.35 | H606: 40.66 | I606: 45.81 | J606: 56.02 | K606: 60.01 | L606: 60.61 | M606: 60.65 | N606: 57.66 | O606: 50.85 | P606: 46.96 | Q606: 43.66 | R606: 44.36 | S606: 45.27 | T606: 48.65 | U606: 51.81 | V606: 54.57 | W606: 56.53 | X606: 59.42 | Y606: 59.25 | Z606: 55.51 | AA606: 48.02 | AB606: 44.55 | AC606: 44.23 | AD606: 44.56 | AE606: 45.45 | AF606: 48.33 | AG606: 52.46 | AH606: 56.08 | AI606: 57.01 | AJ606: 57.7 | AK606: 56.15 | AL606: 52.94 | AM606: 47.17 | AN606: 45.26 | AO606: 43.99 | AP606: 44.04 | AQ606: 44.49 | AR606: 46 | AS606: 51.47 | AT606: 54.41 | AU606: 55.98 | AV606: 57.15 | AW606: 56.27 | AX606: 53.36 | AY606: 46.76
A607: =+A602+7 -> 43574 | B607: 20190419 | C607: 43574 | D607: #N/A | E607: #N/A | F607: #N/A | G607: #N/A | H607: #N/A | I607: #N/A | J607: #N/A | K607: #N/A | L607: #N/A | M607: #N/A | N607: #N/A | O607: #N/A | P607: #N/A | Q607: #N/A | R607: #N/A | S607: #N/A | T607: #N/A | U607: #N/A | V607: #N/A | W607: #N/A | X607: #N/A | Y607: #N/A | Z607: #N/A | AA607: #N/A | AB607: #N/A | AC607: #N/A | AD607: #N/A | AE607: #N/A | AF607: #N/A | AG607: #N/A | AH607: #N/A | AI607: #N/A | AJ607: #N/A | AK607: #N/A | AL607: #N/A | AM607: #N/A | AN607: #N/A | AO607: #N/A | AP607: #N/A | AQ607: #N/A | AR607: #N/A | AS607: #N/A | AT607: #N/A | AU607: #N/A | AV607: #N/A | AW607: #N/A | AX607: #N/A | AY607: #N/A
A608: =+A603+7 -> 43577 | B608: 20190422 | C608: 43577 | D608: 34.41 | E608: 33.75 | F608: 34.75 | G608: 37.35 | H608: 40.66 | I608: 45.81 | J608: 56.02 | K608: 60.01 | L608: 60.61 | M608: 60.65 | N608: 57.66 | O608: 50.85 | P608: 46.96 | Q608: 43.66 | R608: 44.36 | S608: 45.27 | T608: 48.65 | U608: 51.81 | V608: 54.57 | W608: 56.53 | X608: 59.42 | Y608: 59.25 | Z608: 55.51 | AA608: 48.02 | AB608: 44.55 | AC608: 44.23 | AD608: 44.56 | AE608: 45.45 | AF608: 48.33 | AG608: 52.46 | AH608: 56.08 | AI608: 57.01 | AJ608: 57.7 | AK608: 56.15 | AL608: 52.94 | AM608: 47.17 | AN608: 45.26 | AO608: 43.99 | AP608: 44.04 | AQ608: 44.49 | AR608: 46 | AS608: 51.47 | AT608: 54.41 | AU608: 55.98 | AV608: 57.15 | AW608: 56.27 | AX608: 53.36 | AY608: 46.76
A609: =+A604+7 -> 43578 | B609: 20190423 | C609: 43578 | D609: 34.34 | E609: 33.7 | F609: 34.59 | G609: 36.74 | H609: 40.27 | I609: 45.67 | J609: 56.37 | K609: 60.71 | L609: 61.35 | M609: 61.4 | N609: 58.42 | O609: 51.56 | P609: 47.7 | Q609: 44.43 | R609: 45.18 | S609: 46.11 | T609: 49.52 | U609: 52.76 | V609: 55.57 | W609: 57.58 | X609: 60.45 | Y609: 60.26 | Z609: 56.5 | AA609: 48.96 | AB609: 45.45 | AC609: 45.09 | AD609: 45.41 | AE609: 46.31 | AF609: 49.2 | AG609: 53.33 | AH609: 56.95 | AI609: 57.88 | AJ609: 58.57 | AK609: 57.02 | AL609: 53.81 | AM609: 48.04 | AN609: 46.13 | AO609: 44.86 | AP609: 44.91 | AQ609: 45.36 | AR609: 46.87 | AS609: 52.34 | AT609: 55.28 | AU609: 56.85 | AV609: 58.02 | AW609: 57.14 | AX609: 54.23 | AY609: 47.63
A610: =+A605+7 -> 43579 | B610: 20190424 | C610: 43579 | D610: 33.87 | E610: 33.29 | F610: 34.17 | G610: 36.36 | H610: 39.89 | I610: 45.12 | J610: 56.44 | K610: 60.64 | L610: 61.12 | M610: 61.09 | N610: 58.02 | O610: 51.22 | P610: 47.43 | Q610: 44.23 | R610: 45.05 | S610: 46.03 | T610: 49.49 | U610: 52.7 | V610: 55.51 | W610: 57.52 | X610: 60.39 | Y610: 60.2 | Z610: 56.44 | AA610: 48.9 | AB610: 45.39 | AC610: 45.03 | AD610: 45.35 | AE610: 46.25 | AF610: 49.14 | AG610: 53.27 | AH610: 56.89 | AI610: 57.82 | AJ610: 58.51 | AK610: 56.96 | AL610: 53.75 | AM610: 47.96 | AN610: 46.03 | AO610: 44.74 | AP610: 44.79 | AQ610: 45.24 | AR610: 46.75 | AS610: 52.25 | AT610: 55.22 | AU610: 56.81 | AV610: 57.98 | AW610: 57.1 | AX610: 54.19 | AY610: 47.59
A611: =+A606+7 -> 43580 | B611: 20190425 | C611: 43580 | D611: 34.36 | E611: 33.89 | F611: 34.74 | G611: 36.96 | H611: 40.4 | I611: 45.42 | J611: 56.64 | K611: 61.15 | L611: 61.44 | M611: 61.52 | N611: 58.48 | O611: 51.65 | P611: 47.8 | Q611: 44.63 | R611: 45.51 | S611: 46.54 | T611: 50.03 | U611: 53.22 | V611: 55.99 | W611: 57.96 | X611: 60.81 | Y611: 60.56 | Z611: 56.7 | AA611: 49.08 | AB611: 45.5 | AC611: 45.1 | AD611: 45.39 | AE611: 46.26 | AF611: 49.15 | AG611: 53.27 | AH611: 56.87 | AI611: 57.8 | AJ611: 58.49 | AK611: 56.94 | AL611: 53.71 | AM611: 47.92 | AN611: 45.99 | AO611: 44.7 | AP611: 44.75 | AQ611: 45.2 | AR611: 46.71 | AS611: 52.18 | AT611: 55.15 | AU611: 56.74 | AV611: 57.91 | AW611: 57.03 | AX611: 54.12 | AY611: 47.52
A612: =+A607+7 -> 43581 | B612: 20190426 | C612: 43581 | D612: 33.9 | E612: 33.58 | F612: 34.51 | G612: 36.53 | H612: 39.73 | I612: 44.93 | J612: 56.23 | K612: 60.77 | L612: 61.06 | M612: 61.16 | N612: 58.09 | O612: 51.17 | P612: 47.3 | Q612: 44.11 | R612: 44.97 | S612: 45.98 | T612: 49.45 | U612: 52.73 | V612: 55.52 | W612: 57.51 | X612: 60.36 | Y612: 60.11 | Z612: 56.25 | AA612: 48.45 | AB612: 44.76 | AC612: 44.25 | AD612: 44.46 | AE612: 45.26 | AF612: 48.08 | AG612: 52.35 | AH612: 56.08 | AI612: 57.11 | AJ612: 57.89 | AK612: 56.41 | AL612: 53.24 | AM612: 47.45 | AN612: 45.52 | AO612: 44.23 | AP612: 44.28 | AQ612: 44.73 | AR612: 46.24 | AS612: 51.71 | AT612: 54.68 | AU612: 56.27 | AV612: 57.44 | AW612: 56.56 | AX612: 53.65 | AY612: 47.05
A613: =+A608+7 -> 43584 | B613: 20190429 | C613: 43584 | D613: 34.07 | E613: 33.62 | F613: 34.52 | G613: 36.66 | H613: 39.96 | I613: 44.67 | J613: 56.06 | K613: 60.14 | L613: 60.64 | M613: 60.94 | N613: 57.95 | O613: 50.99 | P613: 47.06 | Q613: 43.83 | R613: 44.67 | S613: 45.68 | T613: 49.15 | U613: 52.43 | V613: 55.22 | W613: 57.21 | X613: 60.06 | Y613: 59.81 | Z613: 55.95 | AA613: 48.15 | AB613: 44.46 | AC613: 43.95 | AD613: 44.16 | AE613: 44.96 | AF613: 47.78 | AG613: 52.05 | AH613: 55.78 | AI613: 56.81 | AJ613: 57.59 | AK613: 56.11 | AL613: 52.94 | AM613: 47.15 | AN613: 45.22 | AO613: 43.93 | AP613: 43.98 | AQ613: 44.43 | AR613: 45.94 | AS613: 51.41 | AT613: 54.38 | AU613: 55.97 | AV613: 57.14 | AW613: 56.26 | AX613: 53.35 | AY613: 46.75
A614: =+A609+7 -> 43585 | B614: 20190430 | C614: 43585 | D614: 33.66 | E614: 34.46 | F614: 36.41 | G614: 39.5 | H614: 43.75 | I614: 54.9 | J614: 58.75 | K614: 59.13 | L614: 59.27 | M614: 56.15 | N614: 50.34 | O614: 45.4 | P614: 42.2 | Q614: 43.13 | R614: 44.25 | S614: 47.78 | T614: 51.2 | U614: 54.07 | V614: 56.09 | W614: 58.95 | X614: 58.75 | Y614: 54.92 | Z614: 47.15 | AA614: 43.51 | AB614: 43.08 | AC614: 43.37 | AD614: 44.23 | AE614: 47.1 | AF614: 51.39 | AG614: 55.12 | AH614: 56.15 | AI614: 56.86 | AJ614: 55.32 | AK614: 52.08 | AL614: 46.15 | AM614: 44.1 | AN614: 42.69 | AO614: 42.63 | AP614: 42.98 | AQ614: 44.42 | AR614: 49.96 | AS614: 53.01 | AT614: 54.6 | AU614: 55.77 | AV614: 54.89 | AW614: 51.98 | AX614: 45.38 | AY614: 43.58
A615: =+A610+7 -> 43586 | B615: 20190501 | C615: 43586 | D615: 32.59 | E615: 33.49 | F615: 35.42 | G615: 38.48 | H615: 42.7 | I615: 53.7 | J615: 57.41 | K615: 57.75 | L615: 57.89 | M615: 54.7 | N615: 48.94 | O615: 44.24 | P615: 42.23 | Q615: 42.37 | R615: 43.09 | S615: 46.25 | T615: 49.86 | U615: 52.96 | V615: 55.2 | W615: 58.12 | X615: 57.92 | Y615: 54.09 | Z615: 46.29 | AA615: 42.57 | AB615: 42.07 | AC615: 42.34 | AD615: 43.2 | AE615: 46.07 | AF615: 50.33 | AG615: 54.1 | AH615: 55.2 | AI615: 55.94 | AJ615: 54.4 | AK615: 51.16 | AL615: 45.23 | AM615: 43.18 | AN615: 41.77 | AO615: 41.71 | AP615: 42.06 | AQ615: 43.5 | AR615: 49.04 | AS615: 52.09 | AT615: 53.68 | AU615: 54.85 | AV615: 53.97 | AW615: 51.06 | AX615: 44.46 | AY615: 42.66
...

Sheet BoE feb MPR
A1: Section 2: Current economic conditions | O1: 20231 !Q | P1: UNPD@UK
O2: .DESC | P2: UK: BoE CPI Projections Based on Expected Interest Rate: Mode (Y/Y % Chg)
A3: 2.18 - Contributions to CPI inflation | O3: .T1 | P3: Q1-2024
O4: .TN | P4: Q1-2027
B5: Contributions | H5: Inflation rates | O5: .LSOURCE | P5: Bank of England
A6: Date | B6: Services | C6: Food | D6: Electricity and gas | E6: Fuels and lubricants | F6: Other goods | H6: Services | I6: Food | J6: Electricity and gas | K6: Fuels and lubricants | L6: Other goods | M6: CPI | O6: .DTLM | P6: Feb-01-2024 12:05
A7: 43831 | B7: 1.1 | C7: 0.1 | D7: 0.2 | E7: 0.1 | F7: 0.2 | H7: 2.3 | I7: 1.4 | J7: 4.9 | K7: 4.7 | L7: 0.6 | M7: 1.8 | O7: 20231 | P7: #N/A
A8: 43862 | B8: 1.2 | C8: 0.1 | D8: 0.1 | E8: 0.1 | F8: 0.2 | H8: 2.5 | I8: 1.2 | J8: 4.4 | K8: 2.8 | L8: 0.5 | M8: 1.7 | O8: 20232 | P8: #N/A
A9: 43891 | B9: 1.2 | C9: 0.1 | D9: 0.1 | E9: -0.1 | F9: 0.1 | H9: 2.5 | I9: 1.3 | J9: 3.9 | K9: -2.4 | L9: 0.4 | M9: 1.5 | O9: 20233 | P9: #N/A
A10: 43922 | B10: 1 | C10: 0.1 | D10: -0.2 | E10: -0.4 | F10: 0.3 | H10: 2 | I10: 1.3 | J10: -6.8 | K10: -12.2 | L10: 0.7 | M10: 0.8 | O10: 20234 | P10: #N/A
A11: 43952 | B11: 0.9 | C11: 0.2 | D11: -0.2 | E11: -0.5 | F11: 0.1 | H11: 1.9 | I11: 1.8 | J11: -7 | K11: -16.7 | L11: 0.4 | M11: 0.5 | O11: 20241 | P11: 3.6
A12: 43983 | B12: 0.9 | C12: 0.1 | D12: -0.2 | E12: -0.5 | F12: 0.4 | H12: 1.8 | I12: 1.1 | J12: -6.6 | K12: -16.4 | L12: 1 | M12: 0.6 | O12: 20242 | P12: 2
A13: 44013 | B13: 1 | C13: 0.1 | D13: -0.2 | E13: -0.4 | F13: 0.5 | H13: 2.1 | I13: 0.8 | J13: -6.6 | K13: -12 | L13: 1.5 | M13: 1 | O13: 20243 | P13: 2.2
A14: 44044 | B14: 0.3 | C14: 0 | D14: -0.2 | E14: -0.4 | F14: 0.5 | H14: 0.6 | I14: 0.4 | J14: -6.7 | K14: -11.4 | L14: 1.3 | M14: 0.2 | O14: 20244 | P14: 2.7 | T14: 1129.34 | V14: 1141.19
A15: 44075 | B15: 0.7 | C15: 0 | D15: -0.2 | E15: -0.3 | F15: 0.4 | H15: 1.4 | I15: -0.1 | J15: -6.8 | K15: -10.6 | L15: 1.1 | M15: 0.5 | O15: 20251 | P15: 2.8 | T15: 673.72 | V15: 665.81
A16: 44105 | B16: 0.7 | C16: 0.1 | D16: -0.3 | E16: -0.3 | F16: 0.6 | H16: 1.4 | I16: 0.6 | J16: -8.8 | K16: -10.2 | L16: 1.6 | M16: 0.7 | O16: 20252 | P16: 2.7
A17: 44136 | B17: 0.7 | C17: -0.1 | D17: -0.3 | E17: -0.3 | F17: 0.3 | H17: 1.4 | I17: -0.6 | J17: -8.8 | K17: -10 | L17: 0.8 | M17: 0.3 | O17: 20253 | P17: 2.7 | T17: =(T15/T14)*100 -> 59.656082 | V17: =(V15/V14)*100 -> 58.343484
A18: 44166 | B18: 0.7 | C18: -0.1 | D18: -0.3 | E18: -0.3 | F18: 0.5 | H18: 1.5 | I18: -1.4 | J18: -8.5 | K18: -8.3 | L18: 1.5 | M18: 0.6 | O18: 20254 | P18: 2.5
A19: 44197 | B19: 0.8 | C19: -0.1 | D19: -0.3 | E19: -0.3 | F19: 0.4 | H19: 1.7 | I19: -0.7 | J19: -8.4 | K19: -8.2 | L19: 1.4 | M19: 0.7 | O19: 20261 | P19: 2.3
A20: 44228 | B20: 0.7 | C20: 0 | D20: -0.3 | E20: -0.1 | F20: 0.1 | H20: 1.5 | I20: -0.6 | J20: -7.9 | K20: -3.5 | L20: 0.5 | M20: 0.4 | O20: 20262 | P20: 2.2
A21: 44256 | B21: 0.7 | C21: -0.1 | D21: -0.2 | E21: 0.1 | F21: 0.3 | H21: 1.5 | I21: -1.4 | J21: -7.3 | K21: 3.5 | L21: 0.9 | M21: 0.7 | O21: 20263 | P21: 2.1
A22: 44287 | B22: 0.7 | C22: 0 | D22: 0.1 | E22: 0.4 | F22: 0.4 | H22: 1.6 | I22: -0.4 | J22: 2.4 | K22: 13.6 | L22: 1.2 | M22: 1.5 | O22: 20264 | P22: 2
A23: 44317 | B23: 0.9 | C23: -0.1 | D23: 0.1 | E23: 0.5 | F23: 0.8 | H23: 1.9 | I23: -1.3 | J23: 2.6 | K23: 17.9 | L23: 2.2 | M23: 2.1 | O23: 20271 | P23: 1.9
A24: 44348 | B24: 0.9 | C24: 0 | D24: 0.1 | E24: 0.5 | F24: 1 | H24: 2.1 | I24: -0.6 | J24: 2.5 | K24: 20.3 | L24: 2.7 | M24: 2.5
A25: 44378 | B25: 0.7 | C25: -0.1 | D25: 0.1 | E25: 0.5 | F25: 0.8 | H25: 1.6 | I25: -0.6 | J25: 2.6 | K25: 17.7 | L25: 2.3 | M25: 2
A26: 44409 | B26: 1.4 | C26: 0.1 | D26: 0.1 | E26: 0.5 | F26: 1.2 | H26: 3 | I26: 0.3 | J26: 2.6 | K26: 17.7 | L26: 3.2 | M26: 3.2
A27: 44440 | B27: 1.1 | C27: 0.1 | D27: 0.1 | E27: 0.5 | F27: 1.3 | H27: 2.6 | I27: 0.8 | J27: 2.8 | K27: 17.8 | L27: 3.3 | M27: 3.1
A28: 44470 | B28: 1.4 | C28: 0.2 | D28: 0.8 | E28: 0.6 | F28: 1.3 | H28: 3.2 | I28: 1.2 | J28: 22.9 | K28: 21.5 | L28: 3.4 | M28: 4.2
A29: 44501 | B29: 1.5 | C29: 0.3 | D29: 0.8 | E29: 0.7 | F29: 1.9 | H29: 3.3 | I29: 2.5 | J29: 23.2 | K29: 28.5 | L29: 4.8 | M29: 5.1
A30: 44531 | B30: 1.5 | C30: 0.5 | D30: 0.7 | E30: 0.7 | F30: 2 | H30: 3.4 | I30: 4.2 | J30: 22.7 | K30: 26.8 | L30: 5 | M30: 5.4
A31: 44562 | B31: 1.4 | C31: 0.5 | D31: 0.8 | E31: 0.6 | F31: 2.2 | H31: 3.2 | I31: 4.3 | J31: 22.9 | K31: 23.6 | L31: 5.5 | M31: 5.5
A32: 44593 | B32: 1.5 | C32: 0.6 | D32: 0.8 | E32: 0.6 | F32: 2.7 | H32: 3.5 | I32: 5.1 | J32: 23.1 | K32: 22.3 | L32: 6.9 | M32: 6.2
A33: 44621 | B33: 1.8 | C33: 0.7 | D33: 0.8 | E33: 0.9 | F33: 2.9 | H33: 4 | I33: 5.9 | J33: 24.8 | K33: 30.7 | L33: 7.5 | M33: 7
A34: 44652 | B34: 2.1 | C34: 0.8 | D34: 2.3 | E34: 0.9 | F34: 2.9 | H34: 4.7 | I34: 6.7 | J34: 69.6 | K34: 31.4 | L34: 7.6 | M34: 9
A35: 44682 | B35: 2.1 | C35: 1 | D35: 2.3 | E35: 0.9 | F35: 2.7 | H35: 4.9 | I35: 8.6 | J35: 69.9 | K35: 32.8 | L35: 6.9 | M35: 9.1
... A54: 45261 | B54: 3 | C54: 0.9 | D54: -1 | E54: -0.3 | F54: 1.4 | H54: 6.4 | I54: 8 | J54: -21.5 | K54: -10.8 | L54: 4.3 | M54: 4
A55: Jan 2024 (Bank staff projections) | B55: 3.1 | C55: 0.8 | D55: -0.9 | E55: -0.3 | F55: 1.4 | H55: 6.6 | I55: 7 | J55: -17.8 | K55: -9.2 | L55: 4.1 | M55: 4.1
A56: Feb 2024 (Bank staff projections) | B56: 2.9 | C56: 0.6 | D56: -0.8 | E56: -0.2 | F56: 1.1 | H56: 6.1 | I56: 5 | J56: -17.7 | K56: -7 | L56: 3.3 | M56: 3.5
A57: Mar 2024 (Bank staff projections) | B57: 2.7 | C57: 0.4 | D57: -0.8 | E57: -0.1 | F57: 1 | H57: 5.8 | I57: 3.3 | J57: -17.6 | K57: -4.2 | L57: 2.9 | M57: 3.1
A58: Apr 2024 (Bank staff projections) | B58: 2.5 | C58: 0.2 | D58: -1.3 | E58: 0.1 | F58: 0.6 | H58: 5.3 | I58: 1.9 | J58: -27.3 | K58: 3.3 | L58: 1.7 | M58: 2.1
A59: May 2024 (Bank staff projections) | B59: 2.3 | C59: 0.1 | D59: -1.3 | E59: 0.2 | F59: 0.5 | H59: 4.9 | I59: 1 | J59: -27.2 | K59: 6.5 | L59: 1.5 | M59: 1.9
A60: Jun 2024 (Bank staff projections) | B60: 2.3 | C60: 0.1 | D60: -1.3 | E60: 0.3 | F60: 0.5 | H60: 4.9 | I60: 0.7 | J60: -27.1 | K60: 9.8 | L60: 1.5 | M60: 1.9
A61: 2024 Q3 (Bank staff projections) | B61: n.a. | C61: n.a. | D61: n.a. | E61: n.a. | F61: n.a. | H61: n.a. | I61: n.a. | J61: n.a. | K61: n.a. | L61: n.a. | M61: 2.2
A62: 2024 Q4 (Bank staff projections) | B62: n.a. | C62: n.a. | D62: n.a. | E62: n.a. | F62: n.a. | H62: n.a. | I62: n.a. | J62: n.a. | K62: n.a. | L62: n.a. | M62: 2.7

Sheet Charts >>>

Sheet Energy stuff >>>

Sheet EPC history
B1: Ofgem energy price cap | R1: https://www.ofgem.gov.uk/energy-price-cap
C2: Cap levels | F2: % change | I2: Default tariff cap | L2: % change | O2: RPI % change
C3: Default tariff | D3: Pre-payment meter | F3: Default tariff | G3: Pre-payment meter | I3: Gas | J3: Electricity | L3: Gas | M3: Electricity | O3: Gas | P3: Electricity
A4: 2019 TDCV | B4: 43466 | C4: =1254-117 -> 1137 | D4: =1242-106 -> 1136
B5: 43556 | C5: 1254 | D5: 1242 | F5: =100*((C5/C4)-1) -> 10.290237 | G5: =100*((D5/D4)-1) -> 9.3309859 | O5: =100*((HAVERM!B22/HAVERM!B21)-1) -> 9.3659942 | P5: =100*((HAVERM!C22/HAVERM!C21)-1) -> 10.843373 | R5: https://www.ofgem.gov.uk/publications-and-updates/higher-wholesale-costs-push-default-and-pre-payment-price-caps-april
B6: 43739 | C6: 1179 | D6: 1217 | F6: =100*((C6/C5)-1) -> -5.9808612 | G6: =100*((D6/D5)-1) -> -2.0128824 | O6: =100*((HAVERM!B28/HAVERM!B27)-1) -> -8.9064559 | P6: =100*((HAVERM!C28/HAVERM!C27)-1) -> -2.1480331 | R6: https://www.ofgem.gov.uk/publications-and-updates/energy-caps-fall-winter-due-lower-wholesale-costs
B7: 43922 | C7: 1162 | D7: 1200 | F7: =100*((C7/C6)-1) -> -1.4418999 | G7: =100*((D7/D6)-1) -> -1.3968776 | O7: =100*((HAVERM!B34/HAVERM!B33)-1) -> -3.6158519 | P7: =100*((HAVERM!C34/HAVERM!C33)-1) -> 0.18513621 | R7: https://www.ofgem.gov.uk/publications-and-updates/savings-energy-bills-millions-price-caps-fall
C8: 1126 | D8: 1164 | I8: 545.78 | J8: 645.47
B9: 44105 | C9: 1042 | D9: 1070 | F9: =100*((C9/C8)-1) -> -7.4600355 | G9: =100*((D9/D8)-1) -> -8.0756014 | I9: 445.37 | J9: 583.16 | O9: =100*((HAVERM!B40/HAVERM!B39)-1) -> -12.57503 | P9: =100*((HAVERM!C40/HAVERM!C39)-1) -> -3.1976744 | R9: https://www.ofgem.gov.uk/publications-and-updates/savings-energy-bills-winter-price-cap-falls
B10: 44287 | C10: 1138 | D10: 1156 | F10: =100*((C10/C9)-1) -> 9.2130518 | G10: =100*((D10/D9)-1) -> 8.0373832 | I10: 487.81 | J10: 639.16 | O10: =100*((HAVERM!B46/HAVERM!B45)-1) -> 9.5090972 | P10: =100*((HAVERM!C46/HAVERM!C45)-1) -> 9.1182091 | R10: https://www.ofgem.gov.uk/publications-and-updates/energy-price-cap-increase-april-consumers-should-switch-save-money | S10: https://www.ofgem.gov.uk/publications/default-tariff-cap-level-1-april-2021-30-september-2021
B11: 44470 | C11: 1277 | D11: 1309 | F11: =100*((C11/C10)-1) -> 12.214411 | G11: =100*((D11/D10)-1) -> 13.235294 | I11: 569.35 | J11: 694.31 | L11: =100*((I11/I10)-1) -> 16.715524 | M11: =100*((J11/J10)-1) -> 8.6285124 | O11: =100*((HAVERM!B52/HAVERM!B51)-1) -> 17.586207 | P11: =100*((HAVERM!C52/HAVERM!C51)-1) -> 8.6956522 | R11: https://www.ofgem.gov.uk/publications/record-gas-prices-drive-price-cap-ps139-customers-encouraged-contact-supplier-support-and-switch-better-deal-if-possible
B12: 44652 | C12: 1971 | D12: 2017 | F12: =100*((C12/C11)-1) -> 54.346124 | G12: =100*((D12/D11)-1) -> 54.087089 | I12: 953.74 | J12: 986.6 | L12: =100*((I12/I11)-1) -> 67.513832 | M12: =100*((J12/J11)-1) -> 42.09791 | O12: =100*((HAVERM!B58/HAVERM!B57)-1) -> 68.808318 | P12: =100*((HAVERM!C58/HAVERM!C57)-1) -> 40.531257 | R12: https://www.ofgem.gov.uk/publications/price-cap-increase-ps693-april
B13: 44835 | C13: 3549 | D13: 3608 | F13: =100*((C13/C12)-1) -> 80.060883 | G13: =100*((D13/D12)-1) -> 78.879524 | I13: 1806.1 | J13: 1699.08 | L13: =100*((I13/I12)-1) -> 89.370269 | M13: =100*((J13/J12)-1) -> 72.21569 | O13: =100*((HAVERM!B64/HAVERM!B63)-1) -> 37.539482 | P13: =100*((HAVERM!C64/HAVERM!C63)-1) -> 16.918086 | R13: https://www.ofgem.gov.uk/publications/ofgem-updates-price-cap-level-and-tightens-rules-suppliers
B14: 44927 | C14: 4279 | D14: 4358 | F14: =100*((C14/C13)-1) -> 20.569174 | G14: =100*((D14/D13)-1) -> 20.78714 | I14: 2193.62 | J14: 2167.46 | L14: =100*((I14/I13)-1) -> 21.456176 | M14: =100*((J14/J13)-1) -> 27.566683 | O14: =100*((HAVERM!B67/HAVERM!B66)-1) -> 0.32150649 | P14: =100*((HAVERM!C67/HAVERM!C66)-1) -> 1.1815402 | R14: https://www.ofgem.gov.uk/publications/latest-energy-price-cap-announced-ofgem
B15: 45017 | C15: 3280 | D15: 3325 | F15: =100*((C15/C14)-1) -> -23.346576 | G15: =100*((D15/D14)-1) -> -23.703534 | I15: 1542.46 | J15: 1670.42 | L15: =100*((I15/I14)-1) -> -29.684266 | M15: =100*((J15/J14)-1) -> -22.931911 | O15: =100*((HAVERM!B70/HAVERM!B67)-1) -> -1.0186563 | P15: =100*((HAVERM!C70/HAVERM!C67)-1) -> -1.1127902 | R15: https://www.ofgem.gov.uk/publications/ofgem-announces-latest-quarterly-price-cap-update
B16: 45108 | C16: 2074 | D16: 2077 | F16: =100*((C16/C15)-1) -> -36.768293 | G16: =100*((D16/D15)-1) -> -37.533835 | I16: 959.65 | J16: 1053.62 | L16: =100*((I16/I15)-1) -> -37.784448 | M16: =100*((J16/J15)-1) -> -36.924845 | O16: =100*((HAVERM!B73/HAVERM!B70)-1) -> -25.763182 | P16: =100*((HAVERM!C73/HAVERM!C70)-1) -> -8.6135038 | R16: https://www.ofgem.gov.uk/publications/customers-pay-less-energy-bills-summer
B17: 45200 | C17: 1923 | D17: 1949 | F17: =100*((C17/C16)-1) -> -7.2806172 | G17: =100*((D17/D16)-1) -> -6.1627347 | I17: 891.17 | J17: 973.2 | L17: =100*((I17/I16)-1) -> -7.135935 | M17: =100*((J17/J16)-1) -> -7.6327329 | O17: =100*((HAVERM!B76/HAVERM!B73)-1) -> -7.258567 | P17: =100*((HAVERM!C76/HAVERM!C73)-1) -> -7.479477 | R17: https://www.ofgem.gov.uk/publications/energy-prices-fall-again-winter
A19: 2023 TDCV | B19: 45200 | C19: 1834 | D19: 1861 | I19: 891.17 | J19: 973.2
B20: 45292 | C20: 1928 | D20: 1960 | F20: =100*((C20/C19)-1) -> 5.1254089 | G20: =100*((D20/D19)-1) -> 5.3197206 | I20: 951.06 | J20: 1011.52 | L20: =100*((I20/I19)-1) -> 6.7203788 | M20: =100*((J20/J19)-1) -> 3.9375257 | O20: =100*((HAVERM!B79/HAVERM!B76)-1) -> 6.9197178 | P20: =100*((HAVERM!C79/HAVERM!C76)-1) -> 4.0256326 | R20: https://www.ofgem.gov.uk/publications/increased-wholesale-energy-costs-lead-rise-price-cap
B21: 45383 | C21: 1690 | D21: =C21 -> 1690 | F21: =100*((C21/C20)-1) -> -12.344398 | G21: =100*((D21/D20)-1) -> -13.77551 | I21: 809.82 | J21: 901.17 | L21: =100*((I21/I20)-1) -> -14.850798 | M21: =100*((J21/J20)-1) -> -10.909325 | R21: https://www.ofgem.gov.uk/publications/welcome-fall-price-cap-high-debt-levels-remain

Sheet EPC calculation
C1: Level | V1: % change q/q | AK1: Calcs for inflation model - EPG | AN1: Actual prices charged | AQ1: % change for inflation model | AT1: Calcs for RPI spreadsheet - EPG stays at £3,000 until April 2024 | AW1: Actual prices charged | AY1: % change for RPI spreadsheet | BB1: Calcs for RPI spreadsheet - EPG stays at 2500 | BE1: Actual prices charged | BG1: % change for RPI spreadsheet | BJ1: Data for EPC/EPG chart
C2: Wholesale | D2: Gas | E2: Electricity | F2: Adjustment | G2: Networks | H2: Supplier operating costs | I2: Policy | J2: EBIT allowance | K2: Headroom | L2: Direct Debit uplift | M2: CfD | N2: Levelisation allowance | O2: VAT | P2: Energy Price Cap | Q2: EPC (2019 TDCV) | R2: Old forecast | T2: Energy price guarantee | V2: Wholesale | W2: Gas | X2: Electricity | Y2: Adjustment | Z2: Networks | AA2: Operating | AB2: Policy | AC2: Smart | AD2: Headroom | AE2: Direct Debit uplift | AF2: CfD | AG2: VAT | AH2: Energy Price Cap | AI2: Prices charged | AK2: Non-wholesale cost | AL2: Gas | AM2: Electricity | AN2: Gas | AO2: Electricity | AQ2: Gas | AR2: Electricity | AU2: Energy price guarantee | AV2: Gas | AW2: Electricity | AY2: Gas | AZ2: Electricity | BC2: Energy price guarantee | BD2: Gas | BE2: Electricity | BG2: Gas | BH2: Electricity | BJ2: Energy price cap | BK2: Energy price guarantee
A3: ='EPC history'!B4 -> 43466 | P3: =P4*Q3/Q4 -> 1084.8383 | Q3: 1137 | R3: ='[2]EPC calculation'!P3 -> 1084.8383 | T3: =P3 -> 1084.8383 | AU3: =T3 -> 1084.8383 | BC3: =T3 -> 1084.8383 | BJ3: =P3 -> 1084.8383
A4: ='EPC history'!B5 -> 43556 | P4: =P5*Q4/Q5 -> 1196.4708 | Q4: 1254 | R4: ='[2]EPC calculation'!P4 -> 1196.4708 | T4: =P4 -> 1196.4708 | AH4: =100*((P4/P3)-1) -> 10.290237 | AI4: =100*((T4/T3)-1) -> 10.290237 | AU4: =T4 -> 1196.4708 | BC4: =T4 -> 1196.4708 | BJ4: =P4 -> 1196.4708
A5: ='EPC history'!B6 -> 43739 | P5: =P6*Q5/Q6 -> 1124.9115 | Q5: 1179 | R5: ='[2]EPC calculation'!P5 -> 1124.9115 | T5: =P5 -> 1124.9115 | AH5: =100*((P5/P4)-1) -> -5.9808612 | AI5: =100*((T5/T4)-1) -> -5.9808612 | AU5: =T5 -> 1124.9115 | BC5: =T5 -> 1124.9115 | BJ5: =P5 -> 1124.9115
A6: ='EPC history'!B7 -> 43922 | P6: =P7*Q6/Q7 -> 1108.6914 | Q6: 1162 | R6: ='[2]EPC calculation'!P6 -> 1108.6914 | T6: =P6 -> 1108.6914 | AH6: =100*((P6/P5)-1) -> -1.4418999 | AI6: =100*((T6/T5)-1) -> -1.4418999 | AU6: =T6 -> 1108.6914 | BC6: =T6 -> 1108.6914 | BJ6: =P6 -> 1108.6914
A7: 44105 | C7: 307 | D7: =$C7*('EPC history'!I9/('EPC history'!$I9+'EPC history'!$J9)) -> 132.93593 | E7: =$C7*('EPC history'!J9/('EPC history'!$I9+'EPC history'!$J9)) -> 174.06407 | F7: 15 | G7: 265 | H7: 162 | I7: 194 | J7: 28 | K7: 10 | L7: 11 | M7: 0 | N7: 0 | O7: =SUM(D7:N7)*0.05 -> 49.6 | P7: =P8*Q7/Q8 -> 993.81496 | Q7: 1041.6 | R7: ='[2]EPC calculation'!P7 -> 993.81496 | T7: =P7 -> 993.81496 | AH7: =100*((P7/P6)-1) -> -10.361446 | AI7: =100*((T7/T6)-1) -> -10.361446 | AK7: =T7-C7 -> 686.81496 | AL7: =D7+($AK7*(D7/$C7)) -> 430.33783 | AM7: =E7+($AK7*(E7/$C7)) -> 563.47713 | AN7: =$T7*(AL7/($AL7+$AM7)) -> 430.33783 | AO7: =$T7*(AM7/($AL7+$AM7)) -> 563.47713 | AQ7: =100*((AN7/AN2)-1) -> #VALUE! | AR7: =100*((AO7/AO2)-1) -> #VALUE! | AU7: =T7 -> 993.81496 | AV7: =$T7*(AL7/($AL7+$AM7)) -> 430.33783 | AW7: =$T7*(AM7/($AL7+$AM7)) -> 563.47713 | AY7: =100*((AV7/AV2)-1) -> #VALUE! | AZ7: =100*((AW7/AW2)-1) -> #VALUE! | BC7: =T7 -> 993.81496 | BD7: =$BC7*(AL7/($AL7+$AM7)) -> 430.33783 | BE7: =$BC7*(AM7/($AL7+$AM7)) -> 563.47713 | BG7: =100*((BD7/BD2)-1) -> #VALUE! | BH7: =100*((BE7/BE2)-1) -> #VALUE! | BJ7: =P7 -> 993.81496
A8: 44287 | C8: 373 | D8: =$C8*('EPC history'!I10/('EPC history'!$I10+'EPC history'!$J10)) -> 161.45339 | E8: =$C8*('EPC history'!J10/('EPC history'!$I10+'EPC history'!$J10)) -> 211.54661 | F8: 23 | G8: 268 | H8: 172 | I8: 197 | J8: 27 | K8: 12 | L8: 12 | M8: 0 | N8: 0 | O8: =SUM(D8:N8)*0.05 -> 54.2 | P8: =P9*Q8/Q9 -> 1085.9833 | Q8: 1138.2 | R8: ='[2]EPC calculation'!P8 -> 1085.9833 | T8: =P8 -> 1085.9833 | V8: =100*((C8/C7)-1) -> 21.498371 | W8: =100*((D8/D7)-1) -> 21.452037 | X8: =100*((E8/E7)-1) -> 21.533758 | Y8: =100*((F8/F7)-1) -> 53.333333 | Z8: =100*((G8/G7)-1) -> 1.1320755 | AA8: =100*((H8/H7)-1) -> 6.1728395 | AB8: =100*((I8/I7)-1) -> 1.5463918 | AC8: =100*((J8/J7)-1) -> -3.5714286 | ... AF8: =100*((M8/M7)-1) -> #DIV/0! | AG8: =100*((O8/O7)-1) -> 9.2741935 | AH8: =100*((P8/P7)-1) -> 9.2741935 | AI8: =100*((T8/T7)-1) -> 9.2741935 | AK8: =P8-C8 -> 712.98329 | AL8: =D8+($AK8*(D8/$C8)) -> 470.06886 | AM8: =E8+($AK8*(E8/$C8)) -> 615.91442 | AN8: =$T8*(AL8/($AL8+$AM8)) -> 470.06886 | AO8: =$T8*(AM8/($AL8+$AM8)) -> 615.91442 | AQ8: =100*((AN8/AN7)-1) -> 9.2325212 | AR8: =100*((AO8/AO7)-1) -> 9.3060195 | AU8: =T8 -> 1085.9833 | AV8: =$T8*(AL8/($AL8+$AM8)) -> 470.06886 | AW8: =$T8*(AM8/($AL8+$AM8)) -> 615.91442 | AY8: =100*((AV8/AV7)-1) -> 9.2325212 | AZ8: =100*((AW8/AW7)-1) -> 9.3060195 | BC8: =T8 -> 1085.9833 | BD8: =$BC8*(AL8/($AL8+$AM8)) -> 470.06886 | BE8: =$BC8*(AM8/($AL8+$AM8)) -> 615.91442 | BG8: =100*((BD8/BD7)-1) -> 9.2325212 | BH8: =100*((BE8/BE7)-1) -> 9.3060195 | BJ8: =P8 -> 1085.9833
A9: 44470 | B9: Winter 2021/2022 | C9: 528 | D9: =$C9*('EPC history'!I11/('EPC history'!$I11+'EPC history'!$J11)) -> 237.89374 | E9: =$C9*('EPC history'!J11/('EPC history'!$I11+'EPC history'!$J11)) -> 290.10626 | F9: 9 | G9: 268 | H9: 203 | I9: 159 | J9: 24 | K9: 14 | L9: 12 | M9: 0 | N9: 0 | O9: =SUM(D9:N9)*0.05 -> 60.85 | P9: =P10*Q9/Q10 -> 1219.2266 | Q9: 1277.85 | R9: ='[2]EPC calculation'!P9 -> 1219.2266 | T9: =P9 -> 1219.2266 | V9: =100*((C9/C8)-1) -> 41.55496 | W9: =100*((D9/D8)-1) -> 47.345146 | X9: =100*((E9/E8)-1) -> 37.135862 | Y9: =100*((F9/F8)-1) -> -60.869565 | Z9: =100*((G9/G8)-1) -> 0 | AA9: =100*((H9/H8)-1) -> 18.023256 | AB9: =100*((I9/I8)-1) -> -19.28934 | AC9: =100*((J9/J8)-1) -> -11.111111 | ... AF9: =100*((M9/M8)-1) -> #DIV/0! | AG9: =100*((O9/O8)-1) -> 12.269373 | AH9: =100*((P9/P8)-1) -> 12.269373 | AI9: =100*((T9/T8)-1) -> 12.269373 | AK9: =P9-C9 -> 691.22662 | AL9: =D9+($AK9*(D9/$C9)) -> 549.33026 | AM9: =E9+($AK9*(E9/$C9)) -> 669.89636 | AN9: =$T9*(AL9/($AL9+$AM9)) -> 549.33026 | AO9: =$T9*(AM9/($AL9+$AM9)) -> 669.89636 | AQ9: =100*((AN9/AN8)-1) -> 16.861657 | AR9: =100*((AO9/AO8)-1) -> 8.7645194 | AU9: =T9 -> 1219.2266 | AV9: =$T9*(AL9/($AL9+$AM9)) -> 549.33026 | AW9: =$T9*(AM9/($AL9+$AM9)) -> 669.89636 | AY9: =100*((AV9/AV8)-1) -> 16.861657 | AZ9: =100*((AW9/AW8)-1) -> 8.7645194 | BC9: =T9 -> 1219.2266 | BD9: =$BC9*(AL9/($AL9+$AM9)) -> 549.33026 | BE9: =$BC9*(AM9/($AL9+$AM9)) -> 669.89636 | BG9: =100*((BD9/BD8)-1) -> 16.861657 | BH9: =100*((BE9/BE8)-1) -> 8.7645194 | BJ9: =P9 -> 1219.2266
A10: 44652 | B10: Summer 2022 | C10: 1077 | D10: =$C10*('EPC history'!I12/('EPC history'!$I12+'EPC history'!$J12)) -> 529.38041 | E10: =$C10*('EPC history'!J12/('EPC history'!$I12+'EPC history'!$J12)) -> 547.61959 | F10: 0 | G10: 371 | H10: 220 | I10: 153 | J10: 18 | K10: 22 | L10: 16 | M10: 0 | N10: 0 | O10: =SUM(D10:N10)*0.05 -> 93.85 | P10: =P11*Q10/Q11 -> 1880.4342 | Q10: 1970.85 | R10: ='[2]EPC calculation'!P10 -> 1880.4342 | T10: =P10 -> 1880.4342 | V10: =100*((C10/C9)-1) -> 103.97727 | W10: =100*((D10/D9)-1) -> 122.5281 | X10: =100*((E10/E9)-1) -> 88.765174 | Y10: =100*((F10/F9)-1) -> -100 | Z10: =100*((G10/G9)-1) -> 38.432836 | AA10: =100*((H10/H9)-1) -> 8.3743842 | AB10: =100*((I10/I9)-1) -> -3.7735849 | AC10: =100*((J10/J9)-1) -> -25 | ... AF10: =100*((M10/M9)-1) -> #DIV/0! | AG10: =100*((O10/O9)-1) -> 54.231717 | AH10: =100*((P10/P9)-1) -> 54.231717 | AI10: =100*((T10/T9)-1) -> 54.231717 | AK10: =P10-C10 -> 803.43416 | AL10: =D10+($AK10*(D10/$C10)) -> 924.29434 | AM10: =E10+($AK10*(E10/$C10)) -> 956.13982 | AN10: =$T10*(AL10/($AL10+$AM10)) -> 924.29434 | AO10: =$T10*(AM10/($AL10+$AM10)) -> 956.13982 | AQ10: =100*((AN10/AN9)-1) -> 68.258405 | AR10: =100*((AO10/AO9)-1) -> 42.729514 | AU10: =T10 -> 1880.4342 | AV10: =$T10*(AL10/($AL10+$AM10)) -> 924.29434 | AW10: =$T10*(AM10/($AL10+$AM10)) -> 956.13982 | AY10: =100*((AV10/AV9)-1) -> 68.258405 | AZ10: =100*((AW10/AW9)-1) -> 42.729514 | BC10: =T10 -> 1880.4342 | BD10: =$BC10*(AL10/($AL10+$AM10)) -> 924.29434 | BE10: =$BC10*(AM10/($AL10+$AM10)) -> 956.13982 | BG10: =100*((BD10/BD9)-1) -> 68.258405 | BH10: =100*((BE10/BE9)-1) -> 42.729514 | BJ10: =P10 -> 1880.4342
A11: 44835 | B11: Q4 2022 | C11: 2491 | D11: =$C11*('EPC history'!I13/('EPC history'!$I13+'EPC history'!$J13)) -> 1283.5276 | E11: =$C11*('EPC history'!J13/('EPC history'!$I13+'EPC history'!$J13)) -> 1207.4724 | F11: 46 | G11: =311+61 -> 372 | H11: 258 | I11: 152 | J11: 19 | K11: 43 | L11: =22 -> 22 | M11: -23 | N11: 0 | O11: =SUM(D11:N11)*0.05 -> 169 | P11: =P12*Q11/Q12 -> 3386.1841 | Q11: 3549 | R11: ='[2]EPC calculation'!P11 -> 3386.1841 | T11: =IF(P11>2500,2500,P11) -> 2500 | V11: =100*((C11/C10)-1) -> 131.29062 | W11: =100*((D11/D10)-1) -> 142.45845 | X11: =100*((E11/E10)-1) -> 120.49475 | Y11: =100*((F11/F10)-1) -> #DIV/0! | Z11: =100*((G11/G10)-1) -> 0.26954178 | AA11: =100*((H11/H10)-1) -> 17.272727 | AB11: =100*((I11/I10)-1) -> -0.65359477 | AC11: =100*((J11/J10)-1) -> 5.5555556 | ... AF11: =100*((M11/M10)-1) -> #DIV/0! | AG11: =100*((O11/O10)-1) -> 80.074587 | AH11: =100*((P11/P10)-1) -> 80.074587 | AI11: =100*((T11/T10)-1) -> 32.948021 | AK11: =P11-C11 -> 895.18405 | AL11: =D11+($AK11*(D11/$C11)) -> 1744.7854 | AM11: =E11+($AK11*(E11/$C11)) -> 1641.3986 | AN11: =$T11*(AL11/($AL11+$AM11)) -> 1288.1649 | AO11: =$T11*(AM11/($AL11+$AM11)) -> 1211.8351 | AQ11: =100*((AN11/AN10)-1) -> 39.367395 | AR11: =100*((AO11/AO10)-1) -> 26.742452 | AU11: =T11 -> 2500 | AV11: =$T11*(AL11/($AL11+$AM11)) -> 1288.1649 | AW11: =$T11*(AM11/($AL11+$AM11)) -> 1211.8351 | AY11: =100*((AV11/AV10)-1) -> 39.367395 | AZ11: =100*((AW11/AW10)-1) -> 26.742452 | BC11: =T11 -> 2500 | BD11: =$BC11*(AL11/($AL11+$AM11)) -> 1288.1649 | BE11: =$BC11*(AM11/($AL11+$AM11)) -> 1211.8351 | BG11: =100*((BD11/BD10)-1) -> 39.367395 | BH11: =100*((BE11/BE10)-1) -> 26.742452 | BJ11: =P11 -> 3386.1841 | BK11: 2500
A12: 44927 | B12: Q1 2023 | C12: 3177 | D12: =$C12*('EPC history'!I14/('EPC history'!$I14+'EPC history'!$J14)) -> 1598.0286 | E12: =$C12*('EPC history'!J14/('EPC history'!$I14+'EPC history'!$J14)) -> 1578.9714 | F12: 0 | G12: =311+61 -> 372 | H12: 271 | I12: 152 | J12: 19 | K12: 53 | L12: 25 | M12: 6 | N12: 0 | O12: =SUM(D12:N12)*0.05 -> 203.75 | P12: =P13*Q12/Q13 -> 4082.4556 | Q12: 4278.75 | R12: ='[2]EPC calculation'!P12 -> 4082.4556 | T12: =IF(P12>2500,2500,P12) -> 2500 | V12: =100*((C12/C11)-1) -> 27.539141 | W12: =100*((D12/D11)-1) -> 24.50287 | X12: =100*((E12/E11)-1) -> 30.766657 | Y12: =100*((F12/F11)-1) -> -100 | Z12: =100*((G12/G11)-1) -> 0 | AA12: =100*((H12/H11)-1) -> 5.0387597 | AB12: =100*((I12/I11)-1) -> 0 | AC12: =100*((J12/J11)-1) -> 0 | ... AF12: =100*((M12/M11)-1) -> -126.08696 | AG12: =100*((O12/O11)-1) -> 20.56213 | AH12: =100*((P12/P11)-1) -> 20.56213 | AI12: =100*((T12/T11)-1) -> 0 | AK12: =P12-C12 -> 905.45563 | AL12: =D12+($AK12*(D12/$C12)) -> 2053.4721 | AM12: =E12+($AK12*(E12/$C12)) -> 2028.9835 | AN12: =$T12*(AL12/($AL12+$AM12)) -> 1257.4981 | AO12: =$T12*(AM12/($AL12+$AM12)) -> 1242.5019 | AQ12: =100*((AN12/AN11)-1) -> -2.380658 | AR12: =100*((AO12/AO11)-1) -> 2.5306086 | AU12: =T12 -> 2500 | AV12: =$T12*(AL12/($AL12+$AM12)) -> 1257.4981 | AW12: =$T12*(AM12/($AL12+$AM12)) -> 1242.5019 | AY12: =100*((AV12/AV11)-1) -> -2.380658 | AZ12: =100*((AW12/AW11)-1) -> 2.5306086 | BC12: =T12 -> 2500 | BD12: =$BC12*(AL12/($AL12+$AM12)) -> 1257.4981 | BE12: =$BC12*(AM12/($AL12+$AM12)) -> 1242.5019 | BG12: =100*((BD12/BD11)-1) -> -2.380658 | BH12: =100*((BE12/BE11)-1) -> 2.5306086 | BJ12: =P12 -> 4082.4556 | BK12: 2500
