Workbook
Name Data: [1]sheet0!$C$2
Name IQ_CH: 110000
Name IQ_CQ: 5000
Name IQ_CY: 10000
Name IQ_DAILY: 500000
Name IQ_FH: 100000
Name IQ_FQ: 500
Name IQ_FY: 1000
Name IQ_LTM: 2000
Name IQ_MONTH: 15000
Name IQ_NTM: 6000
Name IQ_WEEK: 50000
Name IQ_YTD: 3000

Sheet >> CHARTS

Sheet >> DATA

Sheet Chart Data
A1: AE debt dynamics (2024-2028) | Z1: Manifestos | AI1: Real government spending | CO1: PSCEX (% of GDP) | CU1: PSNIX (% of GDP) | DA1: Government revenues (% of GDP) | DG1: GDP (2023-2024=100) | DL1: Labour likely | EA1: Labour likely - net debt calculation
AA2: % of GDP | AD2: £mn (2028-2029) | AI2: Real PSCE in RDEL per head (2023-2024=100) | AN2: Real PSGI in RDEL per head (2023-2024=100) | AS2: Real PSCE in RDEL per head (2023-2024 prices) | AW2: Real PSGI in RDEL per head (2023-2024 prices) | BA2: PSCE in RDEL per head | BE2: PSGI in RDEL per head | BI2: PSCE in RDEL | BM2: PSCE spending pledges | BP2: PSGI in RDEL | BT2: PSNI spending pledges | BW2: GDP deflator (2023-2024 = 100) | CA2: GDP deflator (raw) | CE2: Population | CJ2: Real £ | CK2: Real £ | CL2: Index | CM2: Index | DM2: GDP | DQ2: PSCEX | DV2: PSNIX
B3: =X3 -> UK (OBR) | C3: =DataA!BK2&" (OE)" -> UK (OE) | D3: =DataA!BL2 -> US | E3: =DataA!BM2 -> Japan | F3: =DataA!BN2 -> Canada | G3: =DataA!BO2 -> Australia | H3: =DataA!BP2 -> Denmark | I3: =DataA!BQ2 -> Sweden | J3: =DataA!BR2 -> Switzerland | K3: =DataA!BS2 -> S Korea | ... V3: =DataA!CD2 -> Portugal | X3: UK (OBR) | AA3: Conservative | AB3: Labour | AD3: Conservative | AE3: Labour | AI3: Budget 2024 | AJ3: Conservative | AK3: Labour manifesto | AL3: 100 LINE | AN3: Budget 2024 | AO3: Conservative | AP3: Labour manifesto | AQ3: 100 LINE | AS3: Budget 2024 | AT3: Conservative | AU3: Labour | AW3: Budget 2024 | AX3: Conservative | AY3: Labour | BA3: Budget 2024 | BB3: Conservative | BC3: Labour | BE3: Budget 2024 | BF3: Conservative | BG3: Labour | BI3: Budget 2024 | BJ3: Conservative | BK3: Labour | BM3: Conservative | BN3: Labour | BP3: Budget 2024 | BQ3: Conservative | BR3: Labour | BT3: Conservative | BU3: Labour | BW3: Budget 2024 | BX3: Conservative | BY3: Labour | CA3: Budget 2024 | CB3: Conservative | CC3: Labour | CE3: Budget 2024 | CF3: Conservative | CG3: Labour | CJ3: PSCE | CK3: PSGI | CL3: PSCE | CM3: PSGI | CQ3: Budget 2024 | CR3: Conservative | CS3: Labour | CW3: Budget 2024 | CX3: Conservative | CY3: Labour | DC3: Budget 2024 | DD3: Conservative | DE3: Labour | DH3: Budget 2024 | DI3: Conservative | DJ3: Labour | DM3: Budget 2024 | DN3: Labour manifesto | DO3: Labour extra spending | DR3: Budget 2024 | DS3: Labour manifesto | DT3: Labour extra spending | DW3: Budget 2024 | DX3: Labour manifesto | DY3: Labour extra spending | EB3: GNDBTX | EC3: BoE | ED3: GNDBTX exc BoE | EE3: GDP! | EF3: % of GDP | EG3: Y/Y change (%) | EH3: Y/Y change (£bn) | EI3: APF losses | EJ3: y/y ex APF
A4: Expected effective interest rates on government debt (r) | B4: =X4 -> 4.0670842 | C4: =AVERAGE(DataA!BK58:BK62) -> 3.9726327 | D4: =AVERAGE(DataA!BL58:BL62) -> 3.4292239 | E4: =AVERAGE(DataA!BM58:BM62) -> 0.75030083 | F4: =AVERAGE(DataA!BN58:BN62) -> 3.3279579 | G4: =AVERAGE(DataA!BO58:BO62) -> 2.7255229 | H4: =AVERAGE(DataA!BP58:BP62) -> 2.8058555 | I4: =AVERAGE(DataA!BQ58:BQ62) -> 1.5458391 | J4: =AVERAGE(DataA!BR58:BR62) -> 1.1900635 | ... V4: =AVERAGE(DataA!CD58:CD62) -> 2.3325724 | X4: =AVERAGE(DataOBR!F58:F62) -> 4.0670842 | Z4: NICs | AA4: =100*(AD4/$AA$12) -> 0.363744 | AB4: =100*(AE4/$AA$12) -> 0 | AD4: ='[2]Top level assumptions'!$F$5 -> 11667 | AE4: 0 | AG4: ="20"&LEFT(AH4,2) -> 2007 | AH4: =RIGHT(CI4,5) -> 07-08 | AI4: =CL4 -> 100.43541 | AL4: 100 | AN4: =CM4 -> 83.985641 | AQ4: 100 | CI4: {=TRANSPOSE(OBR_MAR24_ST4.3!E4:Z4)} -> 2007-08 | CJ4: {=TRANSPOSE(OBR_MAR24_ST4.3!E11:Z11)} -> 6193.1143 | CK4: {=TRANSPOSE(OBR_MAR24_ST4.3!E17:Z17)} -> 1170.3834 | CL4: =100*(CJ4/CJ$20) -> 100.43541 | CM4: =100*(CK4/CK$20) -> 83.985641 | CO4: ="20"&LEFT(CP4,2) -> 2007 | CP4: =RIGHT(CI4,5) -> 07-08 | CQ4: =100*(DataScen!CG34/DataScen!CL34) -> 36.148169 | CR4: =100*(DataScen!CY34/DataScen!DD34) -> 36.148169 | CS4: =100*(DataScen!DQ34/DataScen!DV34) -> 36.148169 | CU4: ="20"&LEFT(CV4,2) -> 2007 | CV4: =RIGHT(CI4,5) -> 07-08 | CW4: =100*(DataScen!CH34/DataScen!CL34) -> 1.7932627 | CX4: =100*(DataScen!CZ34/DataScen!DD34) -> 1.7932627 | CY4: =100*(DataScen!DR34/DataScen!DV34) -> 1.7932627 | DA4: ="20"&LEFT(DB4,2) -> 2007 | DB4: =RIGHT(CI4,5) -> 07-08 | DC4: =100*(DataScen!CJ34/DataScen!CL34) -> 37.334264 | DD4: =100*(DataScen!DB34/DataScen!DD34) -> 37.334264 | DE4: =100*(DataScen!DT34/DataScen!DV34) -> 37.334264 | DG4: 2022- 2023 | DH4: =100*(DataScen!CD49/DataScen!$CD$50) -> 99.916458 | DI4: =100*(DataScen!CV49/DataScen!$CV$50) -> 99.916458 | DJ4: =100*(DataScen!DN49/DataScen!$DN$50) -> 99.916458 | DL4: 22-23 | DM4: =100*(DataScen!CD49/DataScen!$CD$50) -> 99.916458 | DN4: =100*(DataScen!DN49/DataScen!$DN$50) -> 99.916458 | DO4: =100*(DataScen!EF49/DataScen!$EF$50) -> 99.916458 | DQ4: 22-23 | DR4: =100*(DataScen!CG49/DataScen!CL49) -> 41.129001 | DS4: =100*(DataScen!DQ49/DataScen!DV49) -> 41.129001 | DT4: =100*(DataScen!EI49/DataScen!EN49) -> 41.129001 | DV4: 22-23 | DW4: =100*(DataScen!CH49/DataScen!CL49) -> 1.797143 | DX4: =100*(DataScen!DR49/DataScen!DV49) -> 1.797143 | DY4: =100*(DataScen!EJ49/DataScen!EN49) -> 1.797143 | EA4: 2022- 2023 | EB4: =DataScen!EM49 -> 2539700 | EC4: 322300 | ED4: =+EB4-EC4 -> 2217400 | EE4: =DataScen!EN49 -> 2555445 | EF4: =100*(ED4/EE4) -> 86.77158
A5: Expected annual average nominal GDP growth (g) | B5: =X5 -> 3.3581279 | C5: =100*((DataA!AP62/DataA!AP57)^(1/5)-1) -> 3.7171817 | D5: =100*((DataA!AQ62/DataA!AQ57)^(1/5)-1) -> 4.1837418 | E5: =100*((DataA!AR62/DataA!AR57)^(1/5)-1) -> 1.8517227 | F5: =100*((DataA!AS62/DataA!AS57)^(1/5)-1) -> 4.3318505 | G5: =100*((DataA!AT62/DataA!AT57)^(1/5)-1) -> 4.8381108 | H5: =100*((DataA!AU62/DataA!AU57)^(1/5)-1) -> 4.1112533 | I5: =100*((DataA!AV62/DataA!AV57)^(1/5)-1) -> 3.9943263 | J5: =100*((DataA!AW62/DataA!AW57)^(1/5)-1) -> 2.6377391 | ... V5: =100*((DataA!BI62/DataA!BI57)^(1/5)-1) -> 3.4715938 | X5: =100*((DataOBR!D62/DataOBR!D57)^(1/5)-1) -> 3.3581279 | Z5: Reducing tax avoidance | AA5: =100*(AD5/$AA$12) -> -0.15588583 | AB5: =100*(AE5/$AA$12) -> -0.16305658 | AD5: ='[2]Top level assumptions'!$F$11 -> -5000 | AE5: =-'[3]Top level assumptions'!$F$8 -> -5230 | AG5: ="20"&LEFT(AH5,2) -> 2008 | AH5: =RIGHT(CI5,5) -> 08-09 | AI5: =CL5 -> 100.66341 | AL5: 100 | AN5: =CM5 -> 86.761543 | AQ5: 100 | CI5: 2008-09 | CJ5: 6207.1735 | CK5: 1209.067 | CL5: =100*(CJ5/CJ$20) -> 100.66341 | CM5: =100*(CK5/CK$20) -> 86.761543 | CO5: ="20"&LEFT(CP5,2) -> 2008 | CP5: =RIGHT(CI5,5) -> 08-09 | CQ5: =100*(DataScen!CG35/DataScen!CL35) -> 37.933751 | CR5: =100*(DataScen!CY35/DataScen!DD35) -> 37.933751 | CS5: =100*(DataScen!DQ35/DataScen!DV35) -> 37.933751 | CU5: ="20"&LEFT(CV5,2) -> 2008 | CV5: =RIGHT(CI5,5) -> 08-09 | CW5: =100*(DataScen!CH35/DataScen!CL35) -> 3.0057032 | CX5: =100*(DataScen!CZ35/DataScen!DD35) -> 3.0057032 | CY5: =100*(DataScen!DR35/DataScen!DV35) -> 3.0057032 | DA5: ="20"&LEFT(DB5,2) -> 2008 | DB5: =RIGHT(CI5,5) -> 08-09 | DC5: =100*(DataScen!CJ35/DataScen!CL35) -> 36.020864 | DD5: =100*(DataScen!DB35/DataScen!DD35) -> 36.020864 | DE5: =100*(DataScen!DT35/DataScen!DV35) -> 36.020864 | DG5: 2023- 2024 | DH5: =100*(DataScen!CD50/DataScen!$CD$50) -> 100 | DI5: =100*(DataScen!CV50/DataScen!$CV$50) -> 100 | DJ5: =100*(DataScen!DN50/DataScen!$DN$50) -> 100 | DL5: 23-24 | DM5: =100*(DataScen!CD50/DataScen!$CD$50) -> 100 | DN5: =100*(DataScen!DN50/DataScen!$DN$50) -> 100 | DO5: =100*(DataScen!EF50/DataScen!$EF$50) -> 100 | DQ5: 23-24 | DR5: =100*(DataScen!CG50/DataScen!CL50) -> 39.823317 | DS5: =100*(DataScen!DQ50/DataScen!DV50) -> 39.823317 | DT5: =100*(DataScen!EI50/DataScen!EN50) -> 39.823317 | DV5: 23-24 | DW5: =100*(DataScen!CH50/DataScen!CL50) -> 2.5808861 | DX5: =100*(DataScen!DR50/DataScen!DV50) -> 2.5808861 | DY5: =100*(DataScen!EJ50/DataScen!EN50) -> 2.5808861 | EA5: 2023- 2024 | EB5: =DataScen!EM50 -> 2694300 | EC5: 278070.92 | ED5: =+EB5-EC5 -> 2416229.1 | EE5: =DataScen!EN50 -> 2714804 | EF5: =100*(ED5/EE5) -> 89.001971 | EG5: =EF5-EF4 -> 2.2303915 | EH5: =(EG5/100)*EE5 -> 60550.758 | EJ5: =EH5-EI5 -> 60550.758
Z6: Other taxation | AA6: =100*(AD6/$AA$12) -> 0.12265097 | AB6: =100*(AE6/$AA$12) -> -0.10335231 | AD6: ='[2]Top level assumptions'!$F$9+'[2]Top level assumptions'!$F$10 -> 3934 | AE6: =-'[3]Top level assumptions'!$F$5-'[3]Top level assumptions'!$F$6+-'[3]Top level assumptions'!$F$7 -> -3315 | AG6: ="20"&LEFT(AH6,2) -> 2009 | AH6: =RIGHT(CI6,5) -> 09-10 | AI6: =CL6 -> 104.95422 | AL6: 100 | AN6: =CM6 -> 96.7349 | AQ6: 100 | CI6: 2009-10 | CJ6: 6471.7565 | CK6: 1348.0509 | CL6: =100*(CJ6/CJ$20) -> 104.95422 | CM6: =100*(CK6/CK$20) -> 96.7349 | CO6: ="20"&LEFT(CP6,2) -> 2009 | CP6: =RIGHT(CI6,5) -> 09-10 | CQ6: =100*(DataScen!CG36/DataScen!CL36) -> 40.740006 | CR6: =100*(DataScen!CY36/DataScen!DD36) -> 40.740006 | CS6: =100*(DataScen!DQ36/DataScen!DV36) -> 40.740006 | CU6: ="20"&LEFT(CV6,2) -> 2009 | CV6: =RIGHT(CI6,5) -> 09-10 | CW6: =100*(DataScen!CH36/DataScen!CL36) -> 3.000688 | CX6: =100*(DataScen!CZ36/DataScen!DD36) -> 3.000688 | CY6: =100*(DataScen!DR36/DataScen!DV36) -> 3.000688 | DA6: ="20"&LEFT(DB6,2) -> 2009 | DB6: =RIGHT(CI6,5) -> 09-10 | DC6: =100*(DataScen!CJ36/DataScen!CL36) -> 36.093805 | DD6: =100*(DataScen!DB36/DataScen!DD36) -> 36.093805 | DE6: =100*(DataScen!DT36/DataScen!DV36) -> 36.093805 | DG6: 2024- 2025 | DH6: =100*(DataScen!CD51/DataScen!$CD$50) -> 101.26127 | DI6: =100*(DataScen!CV51/DataScen!$CV$50) -> 101.26117 | DJ6: =100*(DataScen!DN51/DataScen!$DN$50) -> 101.26117 | DL6: 24-25 | DM6: =100*(DataScen!CD51/DataScen!$CD$50) -> 101.26127 | DN6: =100*(DataScen!DN51/DataScen!$DN$50) -> 101.26117 | DO6: =100*(DataScen!EF51/DataScen!$EF$50) -> 101.26117 | DQ6: 24-25 | DR6: =100*(DataScen!CG51/DataScen!CL51) -> 39.455399 | DS6: =100*(DataScen!DQ51/DataScen!DV51) -> 39.455681 | DT6: =100*(DataScen!EI51/DataScen!EN51) -> 39.455681 | DV6: 24-25 | DW6: =100*(DataScen!CH51/DataScen!CL51) -> 2.3916702 | DX6: =100*(DataScen!DR51/DataScen!DV51) -> 2.3916733 | DY6: =100*(DataScen!EJ51/DataScen!EN51) -> 2.3916733 | EA6: 2024- 2025 | EB6: =DataScen!EM51 -> 2804618 | EC6: 234782.39 | ED6: =+EB6-EC6 -> 2569835.6 | EE6: =DataScen!EN51 -> 2783071.2 | EF6: =100*(ED6/EE6) -> 92.33812 | EG6: =EF6-EF5 -> 3.3361482 | EH6: =(EG6/100)*EE6 -> 92847.381 | EI6: {=-TRANSPOSE(OBR_MAR24_ST6.6!O10:S10)*1000} -> 19049.878 | EJ6: =EH6-EI6 -> 73797.503
Z7: Welfare spending | AA7: =100*(AD7/$AA$12) -> -0.34294883 | AB7: =100*(AE7/$AA$12) -> 0 | AD7: ='[2]Top level assumptions'!$F$17 -> -11000 | AE7: 0 | AG7: ="20"&LEFT(AH7,2) -> 2010 | AH7: =RIGHT(CI7,5) -> 10-11 | AI7: =CL7 -> 104.32871 | AL7: 100 | AN7: =CM7 -> 80.784526 | AQ7: 100 | CI7: 2010-11 | CJ7: 6433.1857 | CK7: 1125.7742 | CL7: =100*(CJ7/CJ$20) -> 104.32871 | CM7: =100*(CK7/CK$20) -> 80.784526 | CO7: ="20"&LEFT(CP7,2) -> 2010 | CP7: =RIGHT(CI7,5) -> 10-11 | CQ7: =100*(DataScen!CG37/DataScen!CL37) -> 40.719727 | CR7: =100*(DataScen!CY37/DataScen!DD37) -> 40.719727 | CS7: =100*(DataScen!DQ37/DataScen!DV37) -> 40.719727 | CU7: ="20"&LEFT(CV7,2) -> 2010 | CV7: =RIGHT(CI7,5) -> 10-11 | CW7: =100*(DataScen!CH37/DataScen!CL37) -> 2.4455927 | CX7: =100*(DataScen!CZ37/DataScen!DD37) -> 2.4455927 | CY7: =100*(DataScen!DR37/DataScen!DV37) -> 2.4455927 | DA7: ="20"&LEFT(DB7,2) -> 2010 | DB7: =RIGHT(CI7,5) -> 10-11 | DC7: =100*(DataScen!CJ37/DataScen!CL37) -> 37.025281 | DD7: =100*(DataScen!DB37/DataScen!DD37) -> 37.025281 | DE7: =100*(DataScen!DT37/DataScen!DV37) -> 37.025281 | DG7: 2025- 2026 | DH7: =100*(DataScen!CD52/DataScen!$CD$50) -> 103.09176 | DI7: =100*(DataScen!CV52/DataScen!$CV$50) -> 103.16699 | DJ7: =100*(DataScen!DN52/DataScen!$DN$50) -> 103.31837 | DL7: 25-26 | DM7: =100*(DataScen!CD52/DataScen!$CD$50) -> 103.09176 | DN7: =100*(DataScen!DN52/DataScen!$DN$50) -> 103.31837 | DO7: =100*(DataScen!EF52/DataScen!$EF$50) -> 103.68554 | DQ7: 25-26 | DR7: =100*(DataScen!CG52/DataScen!CL52) -> 39.315972 | DS7: =100*(DataScen!DQ52/DataScen!DV52) -> 39.25918 | DT7: =100*(DataScen!EI52/DataScen!EN52) -> 39.242652 | DV7: 25-26 | DW7: =100*(DataScen!CH52/DataScen!CL52) -> 2.1220676 | DX7: =100*(DataScen!DR52/DataScen!DV52) -> 2.2813384 | DY7: =100*(DataScen!EJ52/DataScen!EN52) -> 2.3503227 | EA7: 2025- 2026 | EB7: =DataScen!EM52 -> 2846965 | EC7: 139577.23 | ED7: =+EB7-EC7 -> 2707387.8 | EE7: =DataScen!EN52 -> 2893863 | EF7: =100*(ED7/EE7) -> 93.556183 | EG7: =EF7-EF6 -> 1.2180637 | EH7: =(EG7/100)*EE7 -> 35249.094 | EI7: 9152.3991 | EJ7: =EH7-EI7 -> 26096.695
Z8: Other current spending | AA8: =100*(AD8/$AA$12) -> -0.012003209 | AB8: =100*(AE8/$AA$12) -> 0.1507416 | AD8: ='[2]Top level assumptions'!$F$19 -> -385 | AE8: ='[3]Top level assumptions'!$F$14+'[3]Top level assumptions'!$F$15 -> 4835 | AG8: ="20"&LEFT(AH8,2) -> 2011 | AH8: =RIGHT(CI8,5) -> 11-12 | AI8: =CL8 -> 100.33174 | AL8: 100 | AN8: =CM8 -> 68.060388 | AQ8: 100 | CI8: 2011-12 | CJ8: 6186.7218 | CK8: 948.45675 | CL8: =100*(CJ8/CJ$20) -> 100.33174 | CM8: =100*(CK8/CK$20) -> 68.060388 | CO8: ="20"&LEFT(CP8,2) -> 2011 | CP8: =RIGHT(CI8,5) -> 11-12 | CQ8: =100*(DataScen!CG38/DataScen!CL38) -> 40.14769 | CR8: =100*(DataScen!CY38/DataScen!DD38) -> 40.14769 | CS8: =100*(DataScen!DQ38/DataScen!DV38) -> 40.14769 | CU8: ="20"&LEFT(CV8,2) -> 2011 | CV8: =RIGHT(CI8,5) -> 11-12 | CW8: =100*(DataScen!CH38/DataScen!CL38) -> 1.8428614 | CX8: =100*(DataScen!CZ38/DataScen!DD38) -> 1.8428614 | CY8: =100*(DataScen!DR38/DataScen!DV38) -> 1.8428614 | DA8: ="20"&LEFT(DB8,2) -> 2011 | DB8: =RIGHT(CI8,5) -> 11-12 | DC8: =100*(DataScen!CJ38/DataScen!CL38) -> 37.340559 | DD8: =100*(DataScen!DB38/DataScen!DD38) -> 37.340559 | DE8: =100*(DataScen!DT38/DataScen!DV38) -> 37.340559 | DG8: 2026- 2027 | DH8: =100*(DataScen!CD53/DataScen!$CD$50) -> 105.08799 | DI8: =100*(DataScen!CV53/DataScen!$CV$50) -> 105.08974 | DJ8: =100*(DataScen!DN53/DataScen!$DN$50) -> 105.27839 | DL8: 26-27 | DM8: =100*(DataScen!CD53/DataScen!$CD$50) -> 105.08799 | DN8: =100*(DataScen!DN53/DataScen!$DN$50) -> 105.27839 | DO8: =100*(DataScen!EF53/DataScen!$EF$50) -> 105.81967 | DQ8: 26-27 | DR8: =100*(DataScen!CG53/DataScen!CL53) -> 39.196978 | DS8: =100*(DataScen!DQ53/DataScen!DV53) -> 39.181183 | DT8: =100*(DataScen!EI53/DataScen!EN53) -> 39.18609 | DV8: 26-27 | DW8: =100*(DataScen!CH53/DataScen!CL53) -> 1.9838395 | DX8: =100*(DataScen!DR53/DataScen!DV53) -> 2.1387945 | DY8: =100*(DataScen!EJ53/DataScen!EN53) -> 2.2579542 | EA8: 2026- 2027 | EB8: =DataScen!EM53 -> 2946197 | EC8: 104897.13 | ED8: =+EB8-EC8 -> 2841299.9 | EE8: =DataScen!EN53 -> 3011923.4 | EF8: =100*(ED8/EE8) -> 94.335064 | EG8: =EF8-EF7 -> 0.77888063 | EH8: =(EG8/100)*EE8 -> 23459.288 | EI8: 15970.596 | EJ8: =EH8-EI8 -> 7488.6917
Z9: Capital spending | AA9: =100*(AD9/$AA$12) -> 0 | AB9: =100*(AE9/$AA$12) -> 0.14653268 | AD9: 0 | AE9: ='[3]Top level assumptions'!$F$19 -> 4700 | AG9: ="20"&LEFT(AH9,2) -> 2012 | AH9: =RIGHT(CI9,5) -> 12-13 | AI9: =CL9 -> 96.544117 | AL9: 100 | AN9: =CM9 -> 64.3172 | AQ9: 100 | CI9: 2012-13 | CJ9: 5953.1669 | CK9: 896.29347 | CL9: =100*(CJ9/CJ$20) -> 96.544117 | CM9: =100*(CK9/CK$20) -> 64.3172 | CO9: ="20"&LEFT(CP9,2) -> 2012 | CP9: =RIGHT(CI9,5) -> 12-13 | CQ9: =100*(DataScen!CG39/DataScen!CL39) -> 39.560156 | CR9: =100*(DataScen!CY39/DataScen!DD39) -> 39.560156 | CS9: =100*(DataScen!DQ39/DataScen!DV39) -> 39.560156 | CU9: ="20"&LEFT(CV9,2) -> 2012 | CV9: =RIGHT(CI9,5) -> 12-13 | CW9: =100*(DataScen!CH39/DataScen!CL39) -> 1.8779305 | CX9: =100*(DataScen!CZ39/DataScen!DD39) -> 1.8779305 | CY9: =100*(DataScen!DR39/DataScen!DV39) -> 1.8779305 | DA9: ="20"&LEFT(DB9,2) -> 2012 | DB9: =RIGHT(CI9,5) -> 12-13 | DC9: =100*(DataScen!CJ39/DataScen!CL39) -> 36.818357 | DD9: =100*(DataScen!DB39/DataScen!DD39) -> 36.818357 | DE9: =100*(DataScen!DT39/DataScen!DV39) -> 36.818357 | DG9: 2027- 2028 | DH9: =100*(DataScen!CD54/DataScen!$CD$50) -> 106.95727 | DI9: =100*(DataScen!CV54/DataScen!$CV$50) -> 106.97349 | DJ9: =100*(DataScen!DN54/DataScen!$DN$50) -> 107.12585 | DL9: 27-28 | DM9: =100*(DataScen!CD54/DataScen!$CD$50) -> 106.95727 | DN9: =100*(DataScen!DN54/DataScen!$DN$50) -> 107.12585 | DO9: =100*(DataScen!EF54/DataScen!$EF$50) -> 107.57942 | DQ9: 27-28 | DR9: =100*(DataScen!CG54/DataScen!CL54) -> 38.85815 | DS9: =100*(DataScen!DQ54/DataScen!DV54) -> 38.900601 | DT9: =100*(DataScen!EI54/DataScen!EN54) -> 39.003616 | DV9: 27-28 | DW9: =100*(DataScen!CH54/DataScen!CL54) -> 1.8228113 | DX9: =100*(DataScen!DR54/DataScen!DV54) -> 1.9730193 | DY9: =100*(DataScen!EJ54/DataScen!EN54) -> 2.1039041 | EA9: 2027- 2028 | EB9: =DataScen!EM54 -> 3057814 | EC9: 93282.767 | ED9: =+EB9-EC9 -> 2964531.2 | EE9: =DataScen!EN54 -> 3124122.9 | EF9: =100*(ED9/EE9) -> 94.891633 | EG9: =EF9-EF8 -> 0.55656891 | EH9: =(EG9/100)*EE9 -> 17387.897 | EI9: 17644.314 | EJ9: =EH9-EI9 -> -256.41716
Z10: Total | AA10: =SUM(AA4:AA9) -> -0.024442899 | AB10: =SUM(AB4:AB9) -> 0.030865395 | AD10: =SUM(AD4:AD9) -> -784 | AE10: =SUM(AE4:AE9) -> 990 | AG10: ="20"&LEFT(AH10,2) -> 2013 | AH10: =RIGHT(CI10,5) -> 13-14 | AI10: =CL10 -> 95.557909 | AL10: 100 | AN10: =CM10 -> 67.741493 | AQ10: 100 | CI10: 2013-14 | CJ10: 5892.3547 | CK10: 944.01278 | CL10: =100*(CJ10/CJ$20) -> 95.557909 | CM10: =100*(CK10/CK$20) -> 67.741493 | CO10: ="20"&LEFT(CP10,2) -> 2013 | CP10: =RIGHT(CI10,5) -> 13-14 | CQ10: =100*(DataScen!CG40/DataScen!CL40) -> 38.579764 | CR10: =100*(DataScen!CY40/DataScen!DD40) -> 38.579764 | CS10: =100*(DataScen!DQ40/DataScen!DV40) -> 38.579764 | CU10: ="20"&LEFT(CV10,2) -> 2013 | CV10: =RIGHT(CI10,5) -> 13-14 | CW10: =100*(DataScen!CH40/DataScen!CL40) -> 1.4547675 | CX10: =100*(DataScen!CZ40/DataScen!DD40) -> 1.4547675 | CY10: =100*(DataScen!DR40/DataScen!DV40) -> 1.4547675 | DA10: ="20"&LEFT(DB10,2) -> 2013 | DB10: =RIGHT(CI10,5) -> 13-14 | DC10: =100*(DataScen!CJ40/DataScen!CL40) -> 36.800222 | DD10: =100*(DataScen!DB40/DataScen!DD40) -> 36.800222 | DE10: =100*(DataScen!DT40/DataScen!DV40) -> 36.800222 | DG10: 2028- 2029 | DH10: =100*(DataScen!CD55/DataScen!$CD$50) -> 108.77442 | DI10: =100*(DataScen!CV55/DataScen!$CV$50) -> 108.81754 | DJ10: =100*(DataScen!DN55/DataScen!$DN$50) -> 108.96377 | DL10: 28-29 | DM10: =100*(DataScen!CD55/DataScen!$CD$50) -> 108.77442 | DN10: =100*(DataScen!DN55/DataScen!$DN$50) -> 108.96377 | DO10: =100*(DataScen!EF55/DataScen!$EF$50) -> 109.4142 | DQ10: 28-29 | DR10: =100*(DataScen!CG55/DataScen!CL55) -> 38.693797 | DS10: =100*(DataScen!DQ55/DataScen!DV55) -> 38.76017 | DT10: =100*(DataScen!EI55/DataScen!EN55) -> 38.950111 | DV10: 28-29 | DW10: =100*(DataScen!CH55/DataScen!CL55) -> 1.6559616 | DX10: =100*(DataScen!DR55/DataScen!DV55) -> 1.800856 | DY10: =100*(DataScen!EJ55/DataScen!EN55) -> 1.9490527 | EA10: 2028- 2029 | EB10: =DataScen!EM55 -> 3163102 | EC10: 79450.758 | ED10: =+EB10-EC10 -> 3083651.2 | EE10: =DataScen!EN55 -> 3243345.3 | EF10: =100*(ED10/EE10) -> 95.076255 | EG10: =EF10-EF9 -> 0.18462196 | EH10: =(EG10/100)*EE10 -> 5987.9278 | EI10: 20408.856 | EJ10: =EH10-EI10 -> -14420.929
AG11: ="20"&LEFT(AH11,2) -> 2014 | AH11: =RIGHT(CI11,5) -> 14-15 | AI11: =CL11 -> 94.289963 | AL11: 100 | AN11: =CM11 -> 72.034572 | AQ11: 100 | CI11: 2014-15 | CJ11: 5814.1698 | CK11: 1003.839 | CL11: =100*(CJ11/CJ$20) -> 94.289963 | CM11: =100*(CK11/CK$20) -> 72.034572 | CO11: ="20"&LEFT(CP11,2) -> 2014 | CP11: =RIGHT(CI11,5) -> 14-15 | CQ11: =100*(DataScen!CG41/DataScen!CL41) -> 37.539989 | CR11: =100*(DataScen!CY41/DataScen!DD41) -> 37.539989 | CS11: =100*(DataScen!DQ41/DataScen!DV41) -> 37.539989 | CU11: ="20"&LEFT(CV11,2) -> 2014 | CV11: =RIGHT(CI11,5) -> 14-15 | CW11: =100*(DataScen!CH41/DataScen!CL41) -> 1.9251727 | CX11: =100*(DataScen!CZ41/DataScen!DD41) -> 1.9251727 | CY11: =100*(DataScen!DR41/DataScen!DV41) -> 1.9251727 | DA11: ="20"&LEFT(DB11,2) -> 2014 | DB11: =RIGHT(CI11,5) -> 14-15 | DC11: =100*(DataScen!CJ41/DataScen!CL41) -> 36.695827 | DD11: =100*(DataScen!DB41/DataScen!DD41) -> 36.695827 | DE11: =100*(DataScen!DT41/DataScen!DV41) -> 36.695827
Z12: GDP! | AA12: =[4]TA.3!$I$10*1000 -> 3207475.6 | AG12: ="20"&LEFT(AH12,2) -> 2015 | AH12: =RIGHT(CI12,5) -> 15-16 | AI12: =CL12 -> 92.40396 | AL12: 100 | AN12: =CM12 -> 68.29393 | AQ12: 100 | CI12: 2015-16 | CJ12: 5697.8739 | CK12: 951.71127 | CL12: =100*(CJ12/CJ$20) -> 92.40396 | CM12: =100*(CK12/CK$20) -> 68.29393 | CO12: ="20"&LEFT(CP12,2) -> 2015 | CP12: =RIGHT(CI12,5) -> 15-16 | CQ12: =100*(DataScen!CG42/DataScen!CL42) -> 37.084294 | CR12: =100*(DataScen!CY42/DataScen!DD42) -> 37.084294 | CS12: =100*(DataScen!DQ42/DataScen!DV42) -> 37.084294 | CU12: ="20"&LEFT(CV12,2) -> 2015 | CV12: =RIGHT(CI12,5) -> 15-16 | CW12: =100*(DataScen!CH42/DataScen!CL42) -> 1.669736 | CX12: =100*(DataScen!CZ42/DataScen!DD42) -> 1.669736 | CY12: =100*(DataScen!DR42/DataScen!DV42) -> 1.669736 | DA12: ="20"&LEFT(DB12,2) -> 2015 | DB12: =RIGHT(CI12,5) -> 15-16 | DC12: =100*(DataScen!CJ42/DataScen!CL42) -> 36.984731 | DD12: =100*(DataScen!DB42/DataScen!DD42) -> 36.984731 | DE12: =100*(DataScen!DT42/DataScen!DV42) -> 36.984731
AG13: ="20"&LEFT(AH13,2) -> 2016 | AH13: =RIGHT(CI13,5) -> 16-17 | AI13: =CL13 -> 90.751464 | AL13: 100 | AN13: =CM13 -> 67.698326 | AQ13: 100 | CI13: 2016-17 | CJ13: 5595.9765 | CK13: 943.41122 | CL13: =100*(CJ13/CJ$20) -> 90.751464 | CM13: =100*(CK13/CK$20) -> 67.698326 | CO13: ="20"&LEFT(CP13,2) -> 2016 | CP13: =RIGHT(CI13,5) -> 16-17 | CQ13: =100*(DataScen!CG43/DataScen!CL43) -> 36.103244 | CR13: =100*(DataScen!CY43/DataScen!DD43) -> 36.103244 | CS13: =100*(DataScen!DQ43/DataScen!DV43) -> 36.103244 | CU13: ="20"&LEFT(CV13,2) -> 2016 | CV13: =RIGHT(CI13,5) -> 16-17 | CW13: =100*(DataScen!CH43/DataScen!CL43) -> 1.8081783 | CX13: =100*(DataScen!CZ43/DataScen!DD43) -> 1.8081783 | CY13: =100*(DataScen!DR43/DataScen!DV43) -> 1.8081783 | DA13: ="20"&LEFT(DB13,2) -> 2016 | DB13: =RIGHT(CI13,5) -> 16-17 | DC13: =100*(DataScen!CJ43/DataScen!CL43) -> 37.484306 | DD13: =100*(DataScen!DB43/DataScen!DD43) -> 37.484306 | DE13: =100*(DataScen!DT43/DataScen!DV43) -> 37.484306
AG14: ="20"&LEFT(AH14,2) -> 2017 | AH14: =RIGHT(CI14,5) -> 17-18 | AI14: =CL14 -> 89.829709 | AL14: 100 | AN14: =CM14 -> 70.926661 | AQ14: 100 | CI14: 2017-18 | CJ14: 5539.1387 | CK14: 988.39974 | CL14: =100*(CJ14/CJ$20) -> 89.829709 | CM14: =100*(CK14/CK$20) -> 70.926661 | CO14: ="20"&LEFT(CP14,2) -> 2017 | CP14: =RIGHT(CI14,5) -> 17-18 | CQ14: =100*(DataScen!CG44/DataScen!CL44) -> 35.467482 | CR14: =100*(DataScen!CY44/DataScen!DD44) -> 35.467482 | CS14: =100*(DataScen!DQ44/DataScen!DV44) -> 35.467482 | CU14: ="20"&LEFT(CV14,2) -> 2017 | CV14: =RIGHT(CI14,5) -> 17-18 | CW14: =100*(DataScen!CH44/DataScen!CL44) -> 2.2078538 | CX14: =100*(DataScen!CZ44/DataScen!DD44) -> 2.2078538 | CY14: =100*(DataScen!DR44/DataScen!DV44) -> 2.2078538 | DA14: ="20"&LEFT(DB14,2) -> 2017 | DB14: =RIGHT(CI14,5) -> 17-18 | DC14: =100*(DataScen!CJ44/DataScen!CL44) -> 37.174722 | DD14: =100*(DataScen!DB44/DataScen!DD44) -> 37.174722 | DE14: =100*(DataScen!DT44/DataScen!DV44) -> 37.174722
AG15: ="20"&LEFT(AH15,2) -> 2018 | AH15: =RIGHT(CI15,5) -> 18-19 | AI15: =CL15 -> 89.519645 | AL15: 100 | AN15: =CM15 -> 73.803986 | AQ15: 100 | CI15: 2018-19 | CJ15: 5520.0193 | CK15: 1028.4968 | CL15: =100*(CJ15/CJ$20) -> 89.519645 | CM15: =100*(CK15/CK$20) -> 73.803986 | CO15: ="20"&LEFT(CP15,2) -> 2018 | CP15: =RIGHT(CI15,5) -> 18-19 | CQ15: =100*(DataScen!CG45/DataScen!CL45) -> 35.087439 | CR15: =100*(DataScen!CY45/DataScen!DD45) -> 35.087439 | CS15: =100*(DataScen!DQ45/DataScen!DV45) -> 35.087439 | CU15: ="20"&LEFT(CV15,2) -> 2018 | CV15: =RIGHT(CI15,5) -> 18-19 | CW15: =100*(DataScen!CH45/DataScen!CL45) -> 2.1032679 | CX15: =100*(DataScen!CZ45/DataScen!DD45) -> 2.1032679 | CY15: =100*(DataScen!DR45/DataScen!DV45) -> 2.1032679 | DA15: ="20"&LEFT(DB15,2) -> 2018 | DB15: =RIGHT(CI15,5) -> 18-19 | DC15: =100*(DataScen!CJ45/DataScen!CL45) -> 37.46761 | DD15: =100*(DataScen!DB45/DataScen!DD45) -> 37.46761 | DE15: =100*(DataScen!DT45/DataScen!DV45) -> 37.46761
AG16: ="20"&LEFT(AH16,2) -> 2019 | AH16: =RIGHT(CI16,5) -> 19-20 | AI16: =CL16 -> 93.503228 | AL16: 100 | AN16: =CM16 -> 75.285142 | AQ16: 100 | BW16: =100*(CA16/CA$20) -> 84.011728 | BX16: =100*(CB16/CB$20) -> 84.011728 | BY16: =100*(CC16/CC$20) -> 84.011728 | CA16: =OBR_MAR24_1.2!X122 -> 100.73409 | CB16: =$CA16 -> 100.73409 | CC16: =$CA16 -> 100.73409 | CE16: {=TRANSPOSE(OBR_MAR24_ST4.3!Q34:Z34)} -> 66903.5 | CF16: =$CE16 -> 66903.5 | CG16: =$CE16 -> 66903.5 | CI16: 2019-20 | CJ16: 5765.6577 | CK16: 1049.1374 | CL16: =100*(CJ16/CJ$20) -> 93.503228 | CM16: =100*(CK16/CK$20) -> 75.285142 | CO16: ="20"&LEFT(CP16,2) -> 2019 | CP16: =RIGHT(CI16,5) -> 19-20 | CQ16: =100*(DataScen!CG46/DataScen!CL46) -> 35.404422 | CR16: =100*(DataScen!CY46/DataScen!DD46) -> 35.404422 | CS16: =100*(DataScen!DQ46/DataScen!DV46) -> 35.404422 | CU16: ="20"&LEFT(CV16,2) -> 2019 | CV16: =RIGHT(CI16,5) -> 19-20 | CW16: =100*(DataScen!CH46/DataScen!CL46) -> 1.8992228 | CX16: =100*(DataScen!CZ46/DataScen!DD46) -> 1.8992228 | CY16: =100*(DataScen!DR46/DataScen!DV46) -> 1.8992228 | DA16: ="20"&LEFT(DB16,2) -> 2019 | DB16: =RIGHT(CI16,5) -> 19-20 | DC16: =100*(DataScen!CJ46/DataScen!CL46) -> 36.946346 | DD16: =100*(DataScen!DB46/DataScen!DD46) -> 36.946346 | DE16: =100*(DataScen!DT46/DataScen!DV46) -> 36.946346
AG17: ="20"&LEFT(AH17,2) -> 2020 | AH17: =RIGHT(CI17,5) -> 20-21 | AI17: =CL17 -> 112.15508 | AL17: 100 | AN17: =CM17 -> 91.228347 | AQ17: 100 | BW17: =100*(CA17/CA$20) -> 88.488253 | BX17: =100*(CB17/CB$20) -> 88.488253 | BY17: =100*(CC17/CC$20) -> 88.488253 | CA17: =OBR_MAR24_1.2!X123 -> 106.10166 | CB17: =$CA17 -> 106.10166 | CC17: =$CA17 -> 106.10166 | CE17: 67060.5 | CF17: =$CE17 -> 67060.5 | CG17: =$CE17 -> 67060.5 | CI17: 2020-21 | CJ17: 6915.7804 | CK17: 1271.3142 | CL17: =100*(CJ17/CJ$20) -> 112.15508 | CM17: =100*(CK17/CK$20) -> 91.228347 | CO17: ="20"&LEFT(CP17,2) -> 2020 | CP17: =RIGHT(CI17,5) -> 20-21 | CQ17: =100*(DataScen!CG47/DataScen!CL47) -> 47.055132 | CR17: =100*(DataScen!CY47/DataScen!DD47) -> 47.055132 | CS17: =100*(DataScen!DQ47/DataScen!DV47) -> 47.055132 | CU17: ="20"&LEFT(CV17,2) -> 2020 | CV17: =RIGHT(CI17,5) -> 20-21 | CW17: =100*(DataScen!CH47/DataScen!CL47) -> 3.4502793 | CX17: =100*(DataScen!CZ47/DataScen!DD47) -> 3.4502793 | CY17: =100*(DataScen!DR47/DataScen!DV47) -> 3.4502793 | DA17: ="20"&LEFT(DB17,2) -> 2020 | DB17: =RIGHT(CI17,5) -> 20-21 | DC17: =100*(DataScen!CJ47/DataScen!CL47) -> 37.988017 | DD17: =100*(DataScen!DB47/DataScen!DD47) -> 37.988017 | DE17: =100*(DataScen!DT47/DataScen!DV47) -> 37.988017
AG18: ="20"&LEFT(AH18,2) -> 2021 | AH18: =RIGHT(CI18,5) -> 21-22 | AI18: =CL18 -> 110.01328 | AL18: 100 | AN18: =CM18 -> 93.606097 | AQ18: 100 | BW18: =100*(CA18/CA$20) -> 87.880815 | BX18: =100*(CB18/CB$20) -> 87.880815 | BY18: =100*(CC18/CC$20) -> 87.880815 | CA18: =OBR_MAR24_1.2!X124 -> 105.37331 | CB18: =$CA18 -> 105.37331 | CC18: =$CA18 -> 105.37331 | CE18: 67313.25 | CF18: =$CE18 -> 67313.25 | CG18: =$CE18 -> 67313.25 | CI18: 2021-22 | CJ18: 6783.7111 | CK18: 1304.4494 | CL18: =100*(CJ18/CJ$20) -> 110.01328 | CM18: =100*(CK18/CK$20) -> 93.606097 | CO18: ="20"&LEFT(CP18,2) -> 2021 | CP18: =RIGHT(CI18,5) -> 21-22 | CQ18: =100*(DataScen!CG48/DataScen!CL48) -> 39.822995 | CR18: =100*(DataScen!CY48/DataScen!DD48) -> 39.822995 | CS18: =100*(DataScen!DQ48/DataScen!DV48) -> 39.822995 | CU18: ="20"&LEFT(CV18,2) -> 2021 | CV18: =RIGHT(CI18,5) -> 21-22 | CW18: =100*(DataScen!CH48/DataScen!CL48) -> 2.309637 | CX18: =100*(DataScen!CZ48/DataScen!DD48) -> 2.309637 | CY18: =100*(DataScen!DR48/DataScen!DV48) -> 2.309637 | DA18: ="20"&LEFT(DB18,2) -> 2021 | DB18: =RIGHT(CI18,5) -> 21-22 | DC18: =100*(DataScen!CJ48/DataScen!CL48) -> 39.116614 | DD18: =100*(DataScen!DB48/DataScen!DD48) -> 39.116614 | DE18: =100*(DataScen!DT48/DataScen!DV48) -> 39.116614
AG19: ="20"&LEFT(AH19,2) -> 2022 | AH19: =RIGHT(CI19,5) -> 22-23 | AI19: =100*(AS19/AS$20) -> 103.6084 | AL19: 100 | AN19: =100*(AW19/AW$20) -> 101.02944 | AQ19: 100 | AS19: =100*(BA19/BW19) -> 6.3887696 | AW19: =100*(BE19/BW19) -> 1.4078975 | BA19: =BI19/(CE19/1000) -> 5.9957062 | BE19: =BP19/(CE19/1000) -> 1.3212779 | BI19: {=TRANSPOSE(OBR_MAR24_TA.7!C8:I8)} -> 407.4577 | BJ19: =$BI19+BM19 -> 407.4577 | BK19: =$BI19+BN19 -> 407.4577 | BP19: {=TRANSPOSE(OBR_MAR24_TA.7!C32:I32)} -> 89.791733 | BW19: =100*(CA19/CA$20) -> 93.847589 | BX19: =100*(CB19/CB$20) -> 93.847589 | BY19: =100*(CC19/CC$20) -> 93.847589 | CA19: =OBR_MAR24_1.2!X125 -> 112.52776 | CB19: =$CA19 -> 112.52776 | CC19: =$CA19 -> 112.52776 | CE19: 67958.25 | CF19: =$CE19 -> 67958.25 | CG19: =$CE19 -> 67958.25 | CI19: 2022-23 | CJ19: 6388.0887 | CK19: 1407.7475 | CL19: =100*(CJ19/CJ$20) -> 103.59736 | CM19: =100*(CK19/CK$20) -> 101.01867 | CO19: ="20"&LEFT(CP19,2) -> 2022 | CP19: =RIGHT(CI19,5) -> 22-23 | CQ19: =100*(DataScen!CG49/DataScen!CL49) -> 41.129001 | CR19: =100*(DataScen!CY49/DataScen!DD49) -> 41.129001 | CS19: =100*(DataScen!DQ49/DataScen!DV49) -> 41.129001 | CU19: ="20"&LEFT(CV19,2) -> 2022 | CV19: =RIGHT(CI19,5) -> 22-23 | CW19: =100*(DataScen!CH49/DataScen!CL49) -> 1.797143 | CX19: =100*(DataScen!CZ49/DataScen!DD49) -> 1.797143 | CY19: =100*(DataScen!DR49/DataScen!DV49) -> 1.797143 | DA19: ="20"&LEFT(DB19,2) -> 2022 | DB19: =RIGHT(CI19,5) -> 22-23 | DC19: =100*(DataScen!CJ49/DataScen!CL49) -> 40.286682 | DD19: =100*(DataScen!DB49/DataScen!DD49) -> 40.286682 | DE19: =100*(DataScen!DT49/DataScen!DV49) -> 40.286682
AG20: ="20"&LEFT(AH20,2) -> 2023 | AH20: =RIGHT(CI20,5) -> 23-24 | AI20: =100*(AS20/AS$20) -> 100 | AJ20: =100*(AT20/AT$20) -> 100 | AK20: =100*(AU20/AU$20) -> 100 | AL20: 100 | AN20: =100*(AW20/AW$20) -> 100 | AO20: =100*(AX20/AX$20) -> 100 | AP20: =100*(AY20/AY$20) -> 100 | AQ20: 100 | AS20: =100*(BA20/BW20) -> 6.1662659 | AT20: =100*(BB20/BX20) -> 6.1662659 | AU20: =100*(BC20/BY20) -> 6.1662659 | AW20: =100*(BE20/BW20) -> 1.3935518 | AX20: =100*(BF20/BX20) -> 1.3935518 | AY20: =100*(BG20/BY20) -> 1.3935518 | BA20: =BI20/(CE20/1000) -> 6.1662659 | BB20: =BJ20/(CF20/1000) -> 6.1662659 | BC20: =BK20/(CG20/1000) -> 6.1662659 | BE20: =BP20/(CE20/1000) -> 1.3935518 | BF20: =BQ20/(CF20/1000) -> 1.3935518 | BG20: =BR20/(CG20/1000) -> 1.3935518 | BI20: 422.94449 | BJ20: =$BI20+BM20 -> 422.94449 | BK20: =$BI20+BN20 -> 422.94449 | BM20: {=TRANSPOSE('[2]Top level assumptions'!$B$19:$G$19)/1000} -> 0 | BN20: {=TRANSPOSE('[3]Top level assumptions'!$B$17:$G$17)/1000} -> 0 | BP20: 95.583786 | BQ20: =$BP20+BT20 -> 95.583786 | BR20: =$BP20+BU20 -> 95.583786 | BT20: 0 | BU20: {=TRANSPOSE('[3]Top level assumptions'!$B$19:$G$19)/1000} -> 0 | BW20: =100*(CA20/CA$20) -> 100 | BX20: =100*(CB20/CB$20) -> 100 | BY20: =100*(CC20/CC$20) -> 100 | CA20: =OBR_MAR24_1.2!X126 -> 119.9048 | CB20: =$CA20 -> 119.9048 | CC20: =$CA20 -> 119.9048 | CE20: 68590.05 | CF20: =$CE20 -> 68590.05 | CG20: =$CE20 -> 68590.05 | CI20: 2023-24 | CJ20: 6166.2659 | CK20: 1393.5518 | CL20: =100*(CJ20/CJ$20) -> 100 | CM20: =100*(CK20/CK$20) -> 100 | CO20: ="20"&LEFT(CP20,2) -> 2023 | CP20: =RIGHT(CI20,5) -> 23-24 | CQ20: =100*(DataScen!CG50/DataScen!CL50) -> 39.823317 | CR20: =100*(DataScen!CY50/DataScen!DD50) -> 39.823317 | CS20: =100*(DataScen!DQ50/DataScen!DV50) -> 39.823317 | CU20: ="20"&LEFT(CV20,2) -> 2023 | CV20: =RIGHT(CI20,5) -> 23-24 | CW20: =100*(DataScen!CH50/DataScen!CL50) -> 2.5808861 | CX20: =100*(DataScen!CZ50/DataScen!DD50) -> 2.5808861 | CY20: =100*(DataScen!DR50/DataScen!DV50) -> 2.5808861 | DA20: ="20"&LEFT(DB20,2) -> 2023 | DB20: =RIGHT(CI20,5) -> 23-24 | DC20: =100*(DataScen!CJ50/DataScen!CL50) -> 40.332967 | DD20: =100*(DataScen!DB50/DataScen!DD50) -> 40.332967 | DE20: =100*(DataScen!DT50/DataScen!DV50) -> 40.332967
AG21: ="20"&LEFT(AH21,2) -> 2024 | AH21: =RIGHT(CI21,5) -> 24-25 | AI21: =100*(AS21/AS$20) -> 100.11566 | AJ21: =100*(AT21/AT$20) -> 100.30812 | AK21: =100*(AU21/AU$20) -> 100.39697 | AL21: 100 | AN21: =100*(AW21/AW$20) -> 102.15208 | AO21: =100*(AX21/AX$20) -> 102.15208 | AP21: =100*(AY21/AY$20) -> 106.99195 | AQ21: 100 | AS21: =100*(BA21/BW21) -> 6.173398 | AT21: =100*(BB21/BX21) -> 6.1852657 | AU21: =100*(BC21/BY21) -> 6.1907439 | AW21: =100*(BE21/BW21) -> 1.4235422 | AX21: =100*(BF21/BX21) -> 1.4235422 | AY21: =100*(BG21/BY21) -> 1.4909882 | BA21: =BI21/(CE21/1000) -> 6.2223006 | BB21: =BJ21/(CF21/1000) -> 6.2342623 | BC21: =BK21/(CG21/1000) -> 6.2397839 | BE21: =BP21/(CE21/1000) -> 1.4348188 | BF21: =BQ21/(CF21/1000) -> 1.4348188 | BG21: =BR21/(CG21/1000) -> 1.5027991 | BI21: 430.19538 | BJ21: =$BI21+BM21 -> 431.02238 | BK21: =$BI21+BN21 -> 431.40413 | BM21: 0.827 | BN21: 1.20875 | BP21: 99.20003 | BQ21: =$BP21+BT21 -> 99.20003 | BR21: =$BP21+BU21 -> 103.90003 | BT21: 0 | BU21: 4.7 | BW21: =100*(CA21/CA$20) -> 100.79215 | BX21: =100*(CB21/CB$20) -> 100.79215 | BY21: =100*(CC21/CC$20) -> 100.79215 | CA21: =OBR_MAR24_1.2!X127 -> 120.85462 | CB21: =$CA21 -> 120.85462 | CC21: =$CA21 -> 120.85462 | CE21: 69137.672 | CF21: =$CE21 -> 69137.672 | CG21: =$CE21 -> 69137.672 | CI21: 2024-25 | CJ21: 6172.6818 | CK21: 1423.377 | CL21: =100*(CJ21/CJ$20) -> 100.10405 | CM21: =100*(CK21/CK$20) -> 102.14023 | CO21: ="20"&LEFT(CP21,2) -> 2024 | CP21: =RIGHT(CI21,5) -> 24-25 | CQ21: =100*(DataScen!CG51/DataScen!CL51) -> 39.455399 | CR21: =100*(DataScen!CY51/DataScen!DD51) -> 39.455696 | CS21: =100*(DataScen!DQ51/DataScen!DV51) -> 39.455681 | CU21: ="20"&LEFT(CV21,2) -> 2024 | CV21: =RIGHT(CI21,5) -> 24-25 | CW21: =100*(DataScen!CH51/DataScen!CL51) -> 2.3916702 | CX21: =100*(DataScen!CZ51/DataScen!DD51) -> 2.3916729 | CY21: =100*(DataScen!DR51/DataScen!DV51) -> 2.3916733 | DA21: ="20"&LEFT(DB21,2) -> 2024 | DB21: =RIGHT(CI21,5) -> 24-25 | DC21: =100*(DataScen!CJ51/DataScen!CL51) -> 40.918356 | DD21: =100*(DataScen!DB51/DataScen!DD51) -> 40.918382 | DE21: =100*(DataScen!DT51/DataScen!DV51) -> 40.918378
AG22: ="20"&LEFT(AH22,2) -> 2025 | AH22: =RIGHT(CI22,5) -> 25-26 | AI22: =100*(AS22/AS$20) -> 100.47952 | AJ22: =100*(AT22/AT$20) -> 100.62452 | AK22: =100*(AU22/AU$20) -> 101.03154 | AL22: 100 | AN22: =100*(AW22/AW$20) -> 99.081719 | AO22: =100*(AX22/AX$20) -> 99.081719 | AP22: =100*(AY22/AY$20) -> 103.83055 | AQ22: 100 | AS22: =100*(BA22/BW22) -> 6.1958343 | AT22: =100*(BB22/BX22) -> 6.2047753 | AU22: =100*(BC22/BY22) -> 6.2298734 | AW22: =100*(BE22/BW22) -> 1.380755 | AX22: =100*(BF22/BX22) -> 1.380755 | AY22: =100*(BG22/BY22) -> 1.4469325 | BA22: =BI22/(CE22/1000) -> 6.3291723 | BB22: =BJ22/(CF22/1000) -> 6.3383057 | BC22: =BK22/(CG22/1000) -> 6.363944 | BE22: =BP22/(CE22/1000) -> 1.4104697 | BF22: =BQ22/(CF22/1000) -> 1.4104697 | BG22: =BR22/(CG22/1000) -> 1.4780713 | BI22: 440.03535 | BJ22: =$BI22+BM22 -> 440.67035 | BK22: =$BI22+BN22 -> 442.45285 | BM22: 0.635 | BN22: 2.4175 | BP22: 98.062828 | BQ22: =$BP22+BT22 -> 98.062828 | BR22: =$BP22+BU22 -> 102.76283 | BT22: 0 | BU22: 4.7 | BW22: =100*(CA22/CA$20) -> 102.15206 | BX22: =100*(CB22/CB$20) -> 102.15206 | BY22: =100*(CC22/CC$20) -> 102.15206 | CA22: =OBR_MAR24_1.2!X128 -> 122.48522 | CB22: =$CA22 -> 122.48522 | CC22: =$CA22 -> 122.48522 | CE22: 69524.944 | CF22: =$CE22 -> 69524.944 | CG22: =$CE22 -> 69524.944 | CI22: 2025-26 | CJ22: 6195.1797 | CK22: 1380.6092 | CL22: =100*(CJ22/CJ$20) -> 100.4689 | CM22: =100*(CK22/CK$20) -> 99.07125 | CO22: ="20"&LEFT(CP22,2) -> 2025 | CP22: =RIGHT(CI22,5) -> 25-26 | CQ22: =100*(DataScen!CG52/DataScen!CL52) -> 39.315972 | CR22: =100*(DataScen!CY52/DataScen!DD52) -> 39.190745 | CS22: =100*(DataScen!DQ52/DataScen!DV52) -> 39.25918 | CU22: ="20"&LEFT(CV22,2) -> 2025 | CV22: =RIGHT(CI22,5) -> 25-26 | CW22: =100*(DataScen!CH52/DataScen!CL52) -> 2.1220676 | CX22: =100*(DataScen!CZ52/DataScen!DD52) -> 2.1212355 | CY22: =100*(DataScen!DR52/DataScen!DV52) -> 2.2813384 | DA22: ="20"&LEFT(DB22,2) -> 2025 | DB22: =RIGHT(CI22,5) -> 25-26 | DC22: =100*(DataScen!CJ52/DataScen!CL52) -> 40.84992 | DD22: =100*(DataScen!DB52/DataScen!DD52) -> 40.659409 | DE22: =100*(DataScen!DT52/DataScen!DV52) -> 40.901883
AG23: ="20"&LEFT(AH23,2) -> 2026 | AH23: =RIGHT(CI23,5) -> 26-27 | AI23: =100*(AS23/AS$20) -> 100.99373 | AJ23: =100*(AT23/AT$20) -> 100.87828 | AK23: =100*(AU23/AU$20) -> 101.80347 | AL23: 100 | AN23: =100*(AW23/AW$20) -> 97.174292 | AO23: =100*(AX23/AX$20) -> 97.174292 | AP23: =100*(AY23/AY$20) -> 101.8182 | AQ23: 100 | AS23: =100*(BA23/BW23) -> 6.2275418 | AT23: =100*(BB23/BX23) -> 6.2204231 | AU23: =100*(BC23/BY23) -> 6.2774723 | AW23: =100*(BE23/BW23) -> 1.3541741 | AX23: =100*(BF23/BX23) -> 1.3541741 | AY23: =100*(BG23/BY23) -> 1.4188893 | BA23: =BI23/(CE23/1000) -> 6.472483 | BB23: =BJ23/(CF23/1000) -> 6.4650843 | BC23: =BK23/(CG23/1000) -> 6.5243774 | BE23: =BP23/(CE23/1000) -> 1.4074363 | BF23: =BQ23/(CF23/1000) -> 1.4074363 | BG23: =BR23/(CG23/1000) -> 1.4746969 | BI23: 452.28089 | BJ23: =$BI23+BM23 -> 451.76389 | BK23: =$BI23+BN23 -> 455.90714 | BM23: -0.517 | BN23: 3.62625 | BP23: 98.348124 | BQ23: =$BP23+BT23 -> 98.348124 | BR23: =$BP23+BU23 -> 103.04812 | BT23: 0 | BU23: 4.7 | BW23: =100*(CA23/CA$20) -> 103.93319 | BX23: =100*(CB23/CB$20) -> 103.93319 | BY23: =100*(CC23/CC$20) -> 103.93319 | CA23: =OBR_MAR24_1.2!X129 -> 124.62088 | CB23: =$CA23 -> 124.62088 | CC23: =$CA23 -> 124.62088 | CE23: 69877.494 | CF23: =$CE23 -> 69877.494 | CG23: =$CE23 -> 69877.494 | CI23: 2026-27 | CJ23: 6226.8892 | CK23: 1354.0321 | CL23: =100*(CJ23/CJ$20) -> 100.98314 | CM23: =100*(CK23/CK$20) -> 97.164108 | CO23: ="20"&LEFT(CP23,2) -> 2026 | CP23: =RIGHT(CI23,5) -> 26-27 | CQ23: =100*(DataScen!CG53/DataScen!CL53) -> 39.196978 | CR23: =100*(DataScen!CY53/DataScen!DD53) -> 39.049251 | CS23: =100*(DataScen!DQ53/DataScen!DV53) -> 39.181183 | CU23: ="20"&LEFT(CV23,2) -> 2026 | CV23: =RIGHT(CI23,5) -> 26-27 | CW23: =100*(DataScen!CH53/DataScen!CL53) -> 1.9838395 | CX23: =100*(DataScen!CZ53/DataScen!DD53) -> 1.9865244 | CY23: =100*(DataScen!DR53/DataScen!DV53) -> 2.1387945 | DA23: ="20"&LEFT(DB23,2) -> 2026 | DB23: =RIGHT(CI23,5) -> 26-27 | DC23: =100*(DataScen!CJ53/DataScen!CL53) -> 40.961169 | DD23: =100*(DataScen!DB53/DataScen!DD53) -> 40.713521 | DE23: =100*(DataScen!DT53/DataScen!DV53) -> 41.097252
AG24: ="20"&LEFT(AH24,2) -> 2027 | AH24: =RIGHT(CI24,5) -> 27-28 | AI24: =100*(AS24/AS$20) -> 101.5171 | AJ24: =100*(AT24/AT$20) -> 101.43315 | AK24: =100*(AU24/AU$20) -> 102.57139 | AL24: 100 | AN24: =100*(AW24/AW$20) -> 94.884158 | AO24: =100*(AX24/AX$20) -> 94.884158 | AP24: =100*(AY24/AY$20) -> 99.419005 | AQ24: 100 | AS24: =100*(BA24/BW24) -> 6.2598142 | AT24: =100*(BB24/BX24) -> 6.2546376 | AU24: =100*(BC24/BY24) -> 6.3248248 | AW24: =100*(BE24/BW24) -> 1.3222599 | AX24: =100*(BF24/BX24) -> 1.3222599 | AY24: =100*(BG24/BY24) -> 1.3854553 | BA24: =BI24/(CE24/1000) -> 6.6278684 | BB24: =BJ24/(CF24/1000) -> 6.6223874 | BC24: =BK24/(CG24/1000) -> 6.6967014 | BE24: =BP24/(CE24/1000) -> 1.4000039 | BF24: =BQ24/(CF24/1000) -> 1.4000039 | BG24: =BR24/(CG24/1000) -> 1.466915 | BI24: 465.55777 | BJ24: =$BI24+BM24 -> 465.17277 | BK24: =$BI24+BN24 -> 470.39277 | BM24: -0.385 | BN24: 4.835 | BP24: 98.339717 | BQ24: =$BP24+BT24 -> 98.339717 | BR24: =$BP24+BU24 -> 103.03972 | BT24: 0 | BU24: 4.7 | BW24: =100*(CA24/CA$20) -> 105.87963 | BX24: =100*(CB24/CB$20) -> 105.87963 | BY24: =100*(CC24/CC$20) -> 105.87963 | CA24: =OBR_MAR24_1.2!X130 -> 126.95476 | CB24: =$CA24 -> 126.95476 | CC24: =$CA24 -> 126.95476 | CE24: 70242.459 | CF24: =$CE24 -> 70242.459 | CG24: =$CE24 -> 70242.459 | CI24: 2027-28 | CJ24: 6259.1505 | CK24: 1322.1197 | CL24: =100*(CJ24/CJ$20) -> 101.50633 | CM24: =100*(CK24/CK$20) -> 94.874097 | CO24: ="20"&LEFT(CP24,2) -> 2027 | CP24: =RIGHT(CI24,5) -> 27-28 | CQ24: =100*(DataScen!CG54/DataScen!CL54) -> 38.85815 | CR24: =100*(DataScen!CY54/DataScen!DD54) -> 38.580237 | CS24: =100*(DataScen!DQ54/DataScen!DV54) -> 38.900601 | CU24: ="20"&LEFT(CV24,2) -> 2027 | CV24: =RIGHT(CI24,5) -> 27-28 | CW24: =100*(DataScen!CH54/DataScen!CL54) -> 1.8228113 | CX24: =100*(DataScen!CZ54/DataScen!DD54) -> 1.8246417 | CY24: =100*(DataScen!DR54/DataScen!DV54) -> 1.9730193 | DA24: ="20"&LEFT(DB24,2) -> 2027 | DB24: =RIGHT(CI24,5) -> 27-28 | DC24: =100*(DataScen!CJ54/DataScen!CL54) -> 41.142867 | DD24: =100*(DataScen!DB54/DataScen!DD54) -> 40.738068 | DE24: =100*(DataScen!DT54/DataScen!DV54) -> 41.319094
AG25: ="20"&LEFT(AH25,2) -> 2028 | AH25: =RIGHT(CI25,5) -> 28-29 | AI25: =100*(AS25/AS$20) -> 101.97236 | AJ25: =100*(AT25/AT$20) -> 102.07983 | AK25: =100*(AU25/AU$20) -> 103.34431 | AL25: 100 | AN25: =100*(AW25/AW$20) -> 91.679851 | AO25: =100*(AX25/AX$20) -> 91.679851 | AP25: =100*(AY25/AY$20) -> 96.105734 | AQ25: 100 | AS25: =100*(BA25/BW25) -> 6.2878867 | AT25: =100*(BB25/BX25) -> 6.2945137 | AU25: =100*(BC25/BY25) -> 6.3724847 | AW25: =100*(BE25/BW25) -> 1.2776062 | AX25: =100*(BF25/BX25) -> 1.2776062 | AY25: =100*(BG25/BY25) -> 1.3392832 | BA25: =BI25/(CE25/1000) -> 6.7862634 | BB25: =BJ25/(CF25/1000) -> 6.7934156 | BC25: =BK25/(CG25/1000) -> 6.8775666 | BE25: =BP25/(CE25/1000) -> 1.378869 | BF25: =BQ25/(CF25/1000) -> 1.378869 | BG25: =BR25/(CG25/1000) -> 1.4454345 | BI25: 479.15889 | BJ25: =$BI25+BM25 -> 479.66389 | BK25: =$BI25+BN25 -> 485.60556 | BM25: 0.505 | BN25: 6.4466667 | BP25: 97.358047 | BQ25: =$BP25+BT25 -> 97.358047 | BR25: =$BP25+BU25 -> 102.05805 | BT25: 0 | BU25: 4.7 | BW25: =100*(CA25/CA$20) -> 107.92598 | BX25: =100*(CB25/CB$20) -> 107.92598 | BY25: =100*(CC25/CC$20) -> 107.92598 | CA25: =OBR_MAR24_1.2!X131 -> 129.40843 | CB25: =$CA25 -> 129.40843 | CC25: =$CA25 -> 129.40843 | CE25: 70607.176 | CF25: =$CE25 -> 70607.176 | CG25: =$CE25 -> 70607.176 | CI25: 2028-29 | CJ25: 6287.2179 | CK25: 1277.4703 | CL25: =100*(CJ25/CJ$20) -> 101.96151 | CM25: =100*(CK25/CK$20) -> 91.6701 | CO25: ="20"&LEFT(CP25,2) -> 2028 | CP25: =RIGHT(CI25,5) -> 28-29 | CQ25: =100*(DataScen!CG55/DataScen!CL55) -> 38.693797 | CR25: =100*(DataScen!CY55/DataScen!DD55) -> 38.404761 | CS25: =100*(DataScen!DQ55/DataScen!DV55) -> 38.76017 | CU25: ="20"&LEFT(CV25,2) -> 2028 | CV25: =RIGHT(CI25,5) -> 28-29 | CW25: =100*(DataScen!CH55/DataScen!CL55) -> 1.6559616 | CX25: =100*(DataScen!CZ55/DataScen!DD55) -> 1.6580935 | CY25: =100*(DataScen!DR55/DataScen!DV55) -> 1.800856 | DA25: ="20"&LEFT(DB25,2) -> 2028 | DB25: =RIGHT(CI25,5) -> 28-29 | DC25: =100*(DataScen!CJ55/DataScen!CL55) -> 41.239421 | DD25: =100*(DataScen!DB55/DataScen!DD55) -> 40.835838 | DE25: =100*(DataScen!DT55/DataScen!DV55) -> 41.451861
AI30: =AI19-EU19 -> 103.6084
AI31: =AI20-EU20 -> 100
AI32: =AI21-EU21 -> 100.11566
AI33: =AI22-EU22 -> 100.47952
AI34: =AI23-EU23 -> 100.99373
AI35: =AI24-EU24 -> 101.5171
AI36: =AI25-EU25 -> 101.97236

Sheet DataA
B1: =GMWA!$CR$2 -> JUN011A.db | C1: =$B$1 -> JUN011A.db | D1: =$B$1 -> JUN011A.db | E1: =$B$1 -> JUN011A.db | F1: =$B$1 -> JUN011A.db | G1: =$B$1 -> JUN011A.db | H1: =$B$1 -> JUN011A.db | I1: =$B$1 -> JUN011A.db | J1: =$B$1 -> JUN011A.db | ... BI1: =$B$1 -> JUN011A.db
B2: UK | C2: US | D2: Japan | E2: Canada | F2: Australia | G2: Denmark | H2: Sweden | I2: Switzerland | J2: S Korea | K2: Germany | L2: France | M2: Italy | N2: Spain | O2: Netherlands | P2: Belgium | Q2: Austria | R2: Finland | S2: Ireland | T2: Greece | U2: Portugal | V2: UK | W2: US | X2: Japan | Y2: Canada | Z2: Australia | AA2: Denmark | AB2: Sweden | AC2: Switzerland | AD2: S Korea | AE2: Germany | AF2: France | AG2: Italy | AH2: Spain | AI2: Netherlands | AJ2: Belgium | AK2: Austria | AL2: Finland | AM2: Ireland | AN2: Greece | AO2: Portugal | AP2: UK | AQ2: US | AR2: Japan | AS2: Canada | AT2: Australia | AU2: Denmark | AV2: Sweden | AW2: Switzerland | AX2: S Korea | AY2: Germany | AZ2: France | BA2: Italy | BB2: Spain | BC2: Netherlands | BD2: Belgium | BE2: Austria | BF2: Finland | BG2: Ireland | BH2: Greece | BI2: Portugal | BK2: =B2 -> UK | BL2: =C2 -> US | BM2: =D2 -> Japan | BN2: =E2 -> Canada | BO2: =F2 -> Australia | BP2: =G2 -> Denmark | BQ2: =H2 -> Sweden | BR2: =I2 -> Switzerland | ... CD2: =U2 -> Portugal
B3: GDIP | C3: GDIP | D3: GDIP | E3: GDIP | F3: GDIP | G3: GDIP | H3: GDIP | I3: GDIP | J3: GDIP | K3: GDIP | L3: GDIP | M3: GDIP | N3: GDIP | O3: GDIP | P3: GDIP | Q3: GDIP | R3: GDIP | S3: GDIP | T3: GDIP | U3: GDIP | V3: GGDBT | W3: GGDBT | X3: GGDBT | Y3: GGDBT | Z3: GGDBT | AA3: GGDBT | AB3: GGDBT | AC3: GGDBT | AD3: GGDBT | AE3: GGDBT | AF3: GGDBT | AG3: GGDBT | AH3: GGDBT | AI3: GGDBT | AJ3: GGDBT | AK3: GGDBT | AL3: GGDBT | AM3: GGDBT | AN3: GGDBT | AO3: GGDBT | AP3: GDP! | AQ3: GDP! | AR3: GDP! | AS3: GDP! | AT3: GDP! | AU3: GDP! | AV3: GDP! | AW3: GDP! | AX3: GDP! | AY3: GDP! | AZ3: GDP! | BA3: GDP! | BB3: GDP! | BC3: GDP! | BD3: GDP! | BE3: GDP! | BF3: GDP! | BG3: GDP! | BH3: GDP! | BI3: GDP! | BK3: GDIP/GGDBT | BL3: GDIP/GGDBT | BM3: GDIP/GGDBT | BN3: GDIP/GGDBT | BO3: GDIP/GGDBT | BP3: GDIP/GGDBT | BQ3: GDIP/GGDBT | BR3: GDIP/GGDBT | BS3: GDIP/GGDBT | BT3: GDIP/GGDBT | BU3: GDIP/GGDBT | BV3: GDIP/GGDBT | BW3: GDIP/GGDBT | BX3: GDIP/GGDBT | BY3: GDIP/GGDBT | BZ3: GDIP/GGDBT | CA3: GDIP/GGDBT | CB3: GDIP/GGDBT | CC3: GDIP/GGDBT | CD3: GDIP/GGDBT
B4: GBR | C4: USA | D4: JPN | E4: CAN | F4: AUS | G4: DNK | H4: SWE | I4: CHE | J4: KOR | K4: DEU | L4: FRA | M4: ITA | N4: ESP | O4: NLD | P4: BEL | Q4: AUT | R4: FIN | S4: IRL | T4: GRC | U4: PRT | V4: GBR | W4: USA | X4: JPN | Y4: CAN | Z4: AUS | AA4: DNK | AB4: SWE | AC4: CHE | AD4: KOR | AE4: DEU | AF4: FRA | AG4: ITA | AH4: ESP | AI4: NLD | AJ4: BEL | AK4: AUT | AL4: FIN | AM4: IRL | AN4: GRC | AO4: PRT | AP4: GBR | AQ4: USA | AR4: JPN | AS4: CAN | AT4: AUS | AU4: DNK | AV4: SWE | AW4: CHE | AX4: KOR | AY4: DEU | AZ4: FRA | BA4: ITA | BB4: ESP | BC4: NLD | BD4: BEL | BE4: AUT | BF4: FIN | BG4: IRL | BH4: GRC | BI4: PRT | BK4: =B4 -> GBR | BL4: =C4 -> USA | BM4: =D4 -> JPN | BN4: =E4 -> CAN | BO4: =F4 -> AUS | BP4: =G4 -> DNK | BQ4: =H4 -> SWE | BR4: =I4 -> CHE | ... CD4: =U4 -> PRT
B5: L | C5: L | D5: L | E5: L | F5: L | G5: L | H5: L | I5: L | J5: L | K5: L | L5: L | M5: L | N5: L | O5: L | P5: L | Q5: L | R5: L | S5: L | T5: L | U5: L | V5: L | W5: L | X5: L | Y5: L | Z5: L | AA5: L | AB5: L | AC5: L | AD5: L | AE5: L | AF5: L | AG5: L | AH5: L | AI5: L | AJ5: L | AK5: L | AL5: L | AM5: L | AN5: L | AO5: L | AP5: L | AQ5: L | AR5: L | AS5: L | AT5: L | AU5: L | AV5: L | AW5: L | AX5: L | AY5: L | AZ5: L | BA5: L | BB5: L | BC5: L | BD5: L | BE5: L | BF5: L | BG5: L | BH5: L | BI5: L
A6: =A84+5 -> 2055 | B6: {=_xlfn.CONCAT(INDEX(GMWA!$A$2:$CR$600,MATCH(1,(GMWA!$CQ$2:$CQ$600=B$3)*(GMWA!$CP$2:$CP$600=B$4)*(GMWA!$CR$2:$CR$600=B$1),0),$A6-1966),"0",(INDEX(GMWA!$A$2:$LR$600,MATCH(1,(GMWA!$CQ$2:$CQ$600=B$3)*(GMWA!$CP$2:$CP$600=B$4)*(GMWA!$CR$2:$CR$600=B$1),0),$A6-1965)))} -> 202401 | C6: {=_xlfn.CONCAT(INDEX(GMWA!$A$2:$CR$600,MATCH(1,(GMWA!$CQ$2:$CQ$600=C$3)*(GMWA!$CP$2:$CP$600=C$4)*(GMWA!$CR$2:$CR$600=C$1),0),$A6-1966),"0",(INDEX(GMWA!$A$2:$LR$600,MATCH(1,(GMWA!$CQ$2:$CQ$600=C$3)*(GMWA!$CP$2:$CP$600=C$4)*(GMWA!$CR$2:$CR$600=C$1),0),$A6-1965)))} -> 202401 | D6: {=_xlfn.CONCAT(INDEX(GMWA!$A$2:$CR$600,MATCH(1,(GMWA!$CQ$2:$CQ$600=D$3)*(GMWA!$CP$2:$CP$600=D$4)*(GMWA!$CR$2:$CR$600=D$1),0),$A6-1966),"0",(INDEX(GMWA!$A$2:$LR$600,MATCH(1,(GMWA!$CQ$2:$CQ$600=D$3)*(GMWA!$CP$2:$CP$600=D$4)*(GMWA!$CR$2:$CR$600=D$1),0),$A6-1965)))} -> 202301 | E6: {=_xlfn.CONCAT(INDEX(GMWA!$A$2:$CR$600,MATCH(1,(GMWA!$CQ$2:$CQ$600=E$3)*(GMWA!$CP$2:$CP$600=E$4)*(GMWA!$CR$2:$CR$600=E$1),0),$A6-1966),"0",(INDEX(GMWA!$A$2:$LR$600,MATCH(1,(GMWA!$CQ$2:$CQ$600=E$3)*(GMWA!$CP$2:$CP$600=E$4)*(GMWA!$CR$2:$CR$600=E$1),0),$A6-1965)))} -> 202401 | F6: {=_xlfn.CONCAT(INDEX(GMWA!$A$2:$CR$600,MATCH(1,(GMWA!$CQ$2:$CQ$600=F$3)*(GMWA!$CP$2:$CP$600=F$4)*(GMWA!$CR$2:$CR$600=F$1),0),$A6-1966),"0",(INDEX(GMWA!$A$2:$LR$600,MATCH(1,(GMWA!$CQ$2:$CQ$600=F$3)*(GMWA!$CP$2:$CP$600=F$4)*(GMWA!$CR$2:$CR$600=F$1),0),$A6-1965)))} -> 202401 | G6: {=_xlfn.CONCAT(INDEX(GMWA!$A$2:$CR$600,MATCH(1,(GMWA!$CQ$2:$CQ$600=G$3)*(GMWA!$CP$2:$CP$600=G$4)*(GMWA!$CR$2:$CR$600=G$1),0),$A6-1966),"0",(INDEX(GMWA!$A$2:$LR$600,MATCH(1,(GMWA!$CQ$2:$CQ$600=G$3)*(GMWA!$CP$2:$CP$600=G$4)*(GMWA!$CR$2:$CR$600=G$1),0),$A6-1965)))} -> 202304 | H6: {=_xlfn.CONCAT(INDEX(GMWA!$A$2:$CR$600,MATCH(1,(GMWA!$CQ$2:$CQ$600=H$3)*(GMWA!$CP$2:$CP$600=H$4)*(GMWA!$CR$2:$CR$600=H$1),0),$A6-1966),"0",(INDEX(GMWA!$A$2:$LR$600,MATCH(1,(GMWA!$CQ$2:$CQ$600=H$3)*(GMWA!$CP$2:$CP$600=H$4)*(GMWA!$CR$2:$CR$600=H$1),0),$A6-1965)))} -> 202304 | I6: {=_xlfn.CONCAT(INDEX(GMWA!$A$2:$CR$600,MATCH(1,(GMWA!$CQ$2:$CQ$600=I$3)*(GMWA!$CP$2:$CP$600=I$4)*(GMWA!$CR$2:$CR$600=I$1),0),$A6-1966),"0",(INDEX(GMWA!$A$2:$LR$600,MATCH(1,(GMWA!$CQ$2:$CQ$600=I$3)*(GMWA!$CP$2:$CP$600=I$4)*(GMWA!$CR$2:$CR$600=I$1),0),$A6-1965)))} -> 202004 | ... BI6: {=_xlfn.CONCAT(INDEX(GMWA!$A$2:$CR$600,MATCH(1,(GMWA!$CQ$2:$CQ$600=BI$3)*(GMWA!$CP$2:$CP$600=BI$4)*(GMWA!$CR$2:$CR$600=BI$1),0),$A6-1966),"0",(INDEX(GMWA!$A$2:$LR$600,MATCH(1,(GMWA!$CQ$2:$CQ$600=BI$3)*(GMWA!$CP$2:$CP$600=BI$4)*(GMWA!$CR$2:$CR$600=BI$1),0),$A6-1965)))} -> 202401
A7: 1973 | B7: {=INDEX(GMWA!$A$2:$CR$600,MATCH(1,(GMWA!$CQ$2:$CQ$600=B$3)*(GMWA!$CP$2:$CP$600=B$4)*(GMWA!$CR$2:$CR$600=B$1),0),$A7-1966)} -> 3087 | C7: {=INDEX(GMWA!$A$2:$CR$600,MATCH(1,(GMWA!$CQ$2:$CQ$600=C$3)*(GMWA!$CP$2:$CP$600=C$4)*(GMWA!$CR$2:$CR$600=C$1),0),$A7-1966)} -> 61.95 | D7: {=INDEX(GMWA!$A$2:$CR$600,MATCH(1,(GMWA!$CQ$2:$CQ$600=D$3)*(GMWA!$CP$2:$CP$600=D$4)*(GMWA!$CR$2:$CR$600=D$1),0),$A7-1966)} -> 922.9716 | E7: {=INDEX(GMWA!$A$2:$CR$600,MATCH(1,(GMWA!$CQ$2:$CQ$600=E$3)*(GMWA!$CP$2:$CP$600=E$4)*(GMWA!$CR$2:$CR$600=E$1),0),$A7-1966)} -> 4910 | F7: {=INDEX(GMWA!$A$2:$CR$600,MATCH(1,(GMWA!$CQ$2:$CQ$600=F$3)*(GMWA!$CP$2:$CP$600=F$4)*(GMWA!$CR$2:$CR$600=F$1),0),$A7-1966)} -> 738.1701 | G7: {=INDEX(GMWA!$A$2:$CR$600,MATCH(1,(GMWA!$CQ$2:$CQ$600=G$3)*(GMWA!$CP$2:$CP$600=G$4)*(GMWA!$CR$2:$CR$600=G$1),0),$A7-1966)} -> 2.120414 | H7: {=INDEX(GMWA!$A$2:$CR$600,MATCH(1,(GMWA!$CQ$2:$CQ$600=H$3)*(GMWA!$CP$2:$CP$600=H$4)*(GMWA!$CR$2:$CR$600=H$1),0),$A7-1966)} -> 3553.037 | I7: {=INDEX(GMWA!$A$2:$CR$600,MATCH(1,(GMWA!$CQ$2:$CQ$600=I$3)*(GMWA!$CP$2:$CP$600=I$4)*(GMWA!$CR$2:$CR$600=I$1),0),$A7-1966)} -> 1.915308 | ... BI7: {=INDEX(GMWA!$A$2:$CR$600,MATCH(1,(GMWA!$CQ$2:$CQ$600=BI$3)*(GMWA!$CP$2:$CP$600=BI$4)*(GMWA!$CR$2:$CR$600=BI$1),0),$A7-1966)} -> 23.33717 | BK7: =100*(B7/V7) -> 8.5822878 | BL7: =100*(C7/W7) -> 5.4078119 | BM7: =100*(D7/X7) -> 5.1939876 | BN7: =100*(E7/Y7) -> 7.5628052 | BO7: =100*(F7/Z7) -> 73817010 | BP7: =100*(G7/AA7) -> 1.269709 | BQ7: =100*(H7/AB7) -> 5.1925969 | BR7: =100*(I7/AC7) -> 1.8912737 | ... CD7: =100*(U7/AO7) -> 1.3545299
A8: =+A7+1 -> 1974 | B8: {=INDEX(GMWA!$A$2:$CR$600,MATCH(1,(GMWA!$CQ$2:$CQ$600=B$3)*(GMWA!$CP$2:$CP$600=B$4)*(GMWA!$CR$2:$CR$600=B$1),0),$A8-1966)} -> 4131 | C8: {=INDEX(GMWA!$A$2:$CR$600,MATCH(1,(GMWA!$CQ$2:$CQ$600=C$3)*(GMWA!$CP$2:$CP$600=C$4)*(GMWA!$CR$2:$CR$600=C$1),0),$A8-1966)} -> 69.55 | D8: {=INDEX(GMWA!$A$2:$CR$600,MATCH(1,(GMWA!$CQ$2:$CQ$600=D$3)*(GMWA!$CP$2:$CP$600=D$4)*(GMWA!$CR$2:$CR$600=D$1),0),$A8-1966)} -> 1196.62 | E8: {=INDEX(GMWA!$A$2:$CR$600,MATCH(1,(GMWA!$CQ$2:$CQ$600=E$3)*(GMWA!$CP$2:$CP$600=E$4)*(GMWA!$CR$2:$CR$600=E$1),0),$A8-1966)} -> 5488 | F8: {=INDEX(GMWA!$A$2:$CR$600,MATCH(1,(GMWA!$CQ$2:$CQ$600=F$3)*(GMWA!$CP$2:$CP$600=F$4)*(GMWA!$CR$2:$CR$600=F$1),0),$A8-1966)} -> 807 | G8: {=INDEX(GMWA!$A$2:$CR$600,MATCH(1,(GMWA!$CQ$2:$CQ$600=G$3)*(GMWA!$CP$2:$CP$600=G$4)*(GMWA!$CR$2:$CR$600=G$1),0),$A8-1966)} -> 2.308616 | H8: {=INDEX(GMWA!$A$2:$CR$600,MATCH(1,(GMWA!$CQ$2:$CQ$600=H$3)*(GMWA!$CP$2:$CP$600=H$4)*(GMWA!$CR$2:$CR$600=H$1),0),$A8-1966)} -> 4397.595 | I8: {=INDEX(GMWA!$A$2:$CR$600,MATCH(1,(GMWA!$CQ$2:$CQ$600=I$3)*(GMWA!$CP$2:$CP$600=I$4)*(GMWA!$CR$2:$CR$600=I$1),0),$A8-1966)} -> 2.263996 | ... BI8: {=INDEX(GMWA!$A$2:$CR$600,MATCH(1,(GMWA!$CQ$2:$CQ$600=BI$3)*(GMWA!$CP$2:$CP$600=BI$4)*(GMWA!$CR$2:$CR$600=BI$1),0),$A8-1966)} -> 23.33717 | BK8: =100*(B8/V8) -> 8.4599839 | BL8: =100*(C8/W8) -> 5.617306 | BM8: =100*(D8/X8) -> 7.2509241 | BN8: =100*(E8/Y8) -> 7.4126101 | BO8: =100*(F8/Z8) -> 80700000 | BP8: =100*(G8/AA8) -> 1.3824048 | BQ8: =100*(H8/AB8) -> 5.6173231 | BR8: =100*(I8/AC8) -> 2.1942007 | ... CD8: =100*(U8/AO8) -> 1.1515709
A9: =+A8+1 -> 1975 | B9: {=INDEX(GMWA!$A$2:$CR$600,MATCH(1,(GMWA!$CQ$2:$CQ$600=B$3)*(GMWA!$CP$2:$CP$600=B$4)*(GMWA!$CR$2:$CR$600=B$1),0),$A9-1966)} -> 4939 | C9: {=INDEX(GMWA!$A$2:$CR$600,MATCH(1,(GMWA!$CQ$2:$CQ$600=C$3)*(GMWA!$CP$2:$CP$600=C$4)*(GMWA!$CR$2:$CR$600=C$1),0),$A9-1966)} -> 77.425 | D9: {=INDEX(GMWA!$A$2:$CR$600,MATCH(1,(GMWA!$CQ$2:$CQ$600=D$3)*(GMWA!$CP$2:$CP$600=D$4)*(GMWA!$CR$2:$CR$600=D$1),0),$A9-1966)} -> 1681.87 | E9: {=INDEX(GMWA!$A$2:$CR$600,MATCH(1,(GMWA!$CQ$2:$CQ$600=E$3)*(GMWA!$CP$2:$CP$600=E$4)*(GMWA!$CR$2:$CR$600=E$1),0),$A9-1966)} -> 6639 | F9: {=INDEX(GMWA!$A$2:$CR$600,MATCH(1,(GMWA!$CQ$2:$CQ$600=F$3)*(GMWA!$CP$2:$CP$600=F$4)*(GMWA!$CR$2:$CR$600=F$1),0),$A9-1966)} -> 916 | G9: {=INDEX(GMWA!$A$2:$CR$600,MATCH(1,(GMWA!$CQ$2:$CQ$600=G$3)*(GMWA!$CP$2:$CP$600=G$4)*(GMWA!$CR$2:$CR$600=G$1),0),$A9-1966)} -> 2.534459 | H9: {=INDEX(GMWA!$A$2:$CR$600,MATCH(1,(GMWA!$CQ$2:$CQ$600=H$3)*(GMWA!$CP$2:$CP$600=H$4)*(GMWA!$CR$2:$CR$600=H$1),0),$A9-1966)} -> 5346.4 | I9: {=INDEX(GMWA!$A$2:$CR$600,MATCH(1,(GMWA!$CQ$2:$CQ$600=I$3)*(GMWA!$CP$2:$CP$600=I$4)*(GMWA!$CR$2:$CR$600=I$1),0),$A9-1966)} -> 2.686347 | ... BI9: {=INDEX(GMWA!$A$2:$CR$600,MATCH(1,(GMWA!$CQ$2:$CQ$600=BI$3)*(GMWA!$CP$2:$CP$600=BI$4)*(GMWA!$CR$2:$CR$600=BI$1),0),$A9-1966)} -> 23.33717 | BK9: =100*(B9/V9) -> 7.883983 | BL9: =100*(C9/W9) -> 5.53676 | BM9: =100*(D9/X9) -> 5.7659502 | BN9: =100*(E9/Y9) -> 8.0669267 | BO9: =100*(F9/Z9) -> 91600000 | BP9: =100*(G9/AA9) -> 1.5176401 | BQ9: =100*(H9/AB9) -> 5.9833203 | BR9: =100*(I9/AC9) -> 2.5110529 | ... CD9: =100*(U9/AO9) -> 0.71420664
A10: =+A9+1 -> 1976 | B10: {=INDEX(GMWA!$A$2:$CR$600,MATCH(1,(GMWA!$CQ$2:$CQ$600=B$3)*(GMWA!$CP$2:$CP$600=B$4)*(GMWA!$CR$2:$CR$600=B$1),0),$A10-1966)} -> 6380 | C10: {=INDEX(GMWA!$A$2:$CR$600,MATCH(1,(GMWA!$CQ$2:$CQ$600=C$3)*(GMWA!$CP$2:$CP$600=C$4)*(GMWA!$CR$2:$CR$600=C$1),0),$A10-1966)} -> 86.725 | D10: {=INDEX(GMWA!$A$2:$CR$600,MATCH(1,(GMWA!$CQ$2:$CQ$600=D$3)*(GMWA!$CP$2:$CP$600=D$4)*(GMWA!$CR$2:$CR$600=D$1),0),$A10-1966)} -> 2416.859 | E10: {=INDEX(GMWA!$A$2:$CR$600,MATCH(1,(GMWA!$CQ$2:$CQ$600=E$3)*(GMWA!$CP$2:$CP$600=E$4)*(GMWA!$CR$2:$CR$600=E$1),0),$A10-1966)} -> 8242 | F10: {=INDEX(GMWA!$A$2:$CR$600,MATCH(1,(GMWA!$CQ$2:$CQ$600=F$3)*(GMWA!$CP$2:$CP$600=F$4)*(GMWA!$CR$2:$CR$600=F$1),0),$A10-1966)} -> 1191 | G10: {=INDEX(GMWA!$A$2:$CR$600,MATCH(1,(GMWA!$CQ$2:$CQ$600=G$3)*(GMWA!$CP$2:$CP$600=G$4)*(GMWA!$CR$2:$CR$600=G$1),0),$A10-1966)} -> 3.290406 | H10: {=INDEX(GMWA!$A$2:$CR$600,MATCH(1,(GMWA!$CQ$2:$CQ$600=H$3)*(GMWA!$CP$2:$CP$600=H$4)*(GMWA!$CR$2:$CR$600=H$1),0),$A10-1966)} -> 5906.224 | I10: {=INDEX(GMWA!$A$2:$CR$600,MATCH(1,(GMWA!$CQ$2:$CQ$600=I$3)*(GMWA!$CP$2:$CP$600=I$4)*(GMWA!$CR$2:$CR$600=I$1),0),$A10-1966)} -> 2.877871 | ... BI10: {=INDEX(GMWA!$A$2:$CR$600,MATCH(1,(GMWA!$CQ$2:$CQ$600=BI$3)*(GMWA!$CP$2:$CP$600=BI$4)*(GMWA!$CR$2:$CR$600=BI$1),0),$A10-1966)} -> 23.33717 | BK10: =100*(B10/V10) -> 8.6917724 | BL10: =100*(C10/W10) -> 5.7520703 | BM10: =100*(D10/X10) -> 5.4923621 | BN10: =100*(E10/Y10) -> 9.0138565 | BO10: =100*(F10/Z10) -> 119100000 | BP10: =100*(G10/AA10) -> 1.970303 | BQ10: =100*(H10/AB10) -> 6.2641779 | BR10: =100*(I10/AC10) -> 2.6295615 | ... CD10: =100*(U10/AO10) -> 0.47137638
A11: =+A10+1 -> 1977 | B11: {=INDEX(GMWA!$A$2:$CR$600,MATCH(1,(GMWA!$CQ$2:$CQ$600=B$3)*(GMWA!$CP$2:$CP$600=B$4)*(GMWA!$CR$2:$CR$600=B$1),0),$A11-1966)} -> 7333 | C11: {=INDEX(GMWA!$A$2:$CR$600,MATCH(1,(GMWA!$CQ$2:$CQ$600=C$3)*(GMWA!$CP$2:$CP$600=C$4)*(GMWA!$CR$2:$CR$600=C$1),0),$A11-1966)} -> 95.75 | D11: {=INDEX(GMWA!$A$2:$CR$600,MATCH(1,(GMWA!$CQ$2:$CQ$600=D$3)*(GMWA!$CP$2:$CP$600=D$4)*(GMWA!$CR$2:$CR$600=D$1),0),$A11-1966)} -> 3374.968 | E11: {=INDEX(GMWA!$A$2:$CR$600,MATCH(1,(GMWA!$CQ$2:$CQ$600=E$3)*(GMWA!$CP$2:$CP$600=E$4)*(GMWA!$CR$2:$CR$600=E$1),0),$A11-1966)} -> 9432 | F11: {=INDEX(GMWA!$A$2:$CR$600,MATCH(1,(GMWA!$CQ$2:$CQ$600=F$3)*(GMWA!$CP$2:$CP$600=F$4)*(GMWA!$CR$2:$CR$600=F$1),0),$A11-1966)} -> 1532 | G11: {=INDEX(GMWA!$A$2:$CR$600,MATCH(1,(GMWA!$CQ$2:$CQ$600=G$3)*(GMWA!$CP$2:$CP$600=G$4)*(GMWA!$CR$2:$CR$600=G$1),0),$A11-1966)} -> 4.972726 | H11: {=INDEX(GMWA!$A$2:$CR$600,MATCH(1,(GMWA!$CQ$2:$CQ$600=H$3)*(GMWA!$CP$2:$CP$600=H$4)*(GMWA!$CR$2:$CR$600=H$1),0),$A11-1966)} -> 7658.689 | I11: {=INDEX(GMWA!$A$2:$CR$600,MATCH(1,(GMWA!$CQ$2:$CQ$600=I$3)*(GMWA!$CP$2:$CP$600=I$4)*(GMWA!$CR$2:$CR$600=I$1),0),$A11-1966)} -> 3.113591 | ... BI11: {=INDEX(GMWA!$A$2:$CR$600,MATCH(1,(GMWA!$CQ$2:$CQ$600=BI$3)*(GMWA!$CP$2:$CP$600=BI$4)*(GMWA!$CR$2:$CR$600=BI$1),0),$A11-1966)} -> 23.33717 | BK11: =100*(B11/V11) -> 8.7542007 | BL11: =100*(C11/W11) -> 5.8924092 | BM11: =100*(D11/X11) -> 5.7381801 | BN11: =100*(E11/Y11) -> 9.0254918 | BO11: =100*(F11/Z11) -> 153200000 | BP11: =100*(G11/AA11) -> 2.9776802 | BQ11: =100*(H11/AB11) -> 6.8816601 | BR11: =100*(I11/AC11) -> 2.8045341 | ... CD11: =100*(U11/AO11) -> 0.33766216
A12: =+A11+1 -> 1978 | B12: {=INDEX(GMWA!$A$2:$CR$600,MATCH(1,(GMWA!$CQ$2:$CQ$600=B$3)*(GMWA!$CP$2:$CP$600=B$4)*(GMWA!$CR$2:$CR$600=B$1),0),$A12-1966)} -> 8160 | C12: {=INDEX(GMWA!$A$2:$CR$600,MATCH(1,(GMWA!$CQ$2:$CQ$600=C$3)*(GMWA!$CP$2:$CP$600=C$4)*(GMWA!$CR$2:$CR$600=C$1),0),$A12-1966)} -> 112.45 | D12: {=INDEX(GMWA!$A$2:$CR$600,MATCH(1,(GMWA!$CQ$2:$CQ$600=D$3)*(GMWA!$CP$2:$CP$600=D$4)*(GMWA!$CR$2:$CR$600=D$1),0),$A12-1966)} -> 4369.668 | E12: {=INDEX(GMWA!$A$2:$CR$600,MATCH(1,(GMWA!$CQ$2:$CQ$600=E$3)*(GMWA!$CP$2:$CP$600=E$4)*(GMWA!$CR$2:$CR$600=E$1),0),$A12-1966)} -> 11741 | F12: {=INDEX(GMWA!$A$2:$CR$600,MATCH(1,(GMWA!$CQ$2:$CQ$600=F$3)*(GMWA!$CP$2:$CP$600=F$4)*(GMWA!$CR$2:$CR$600=F$1),0),$A12-1966)} -> 1796 | G12: {=INDEX(GMWA!$A$2:$CR$600,MATCH(1,(GMWA!$CQ$2:$CQ$600=G$3)*(GMWA!$CP$2:$CP$600=G$4)*(GMWA!$CR$2:$CR$600=G$1),0),$A12-1966)} -> 6.626816 | H12: {=INDEX(GMWA!$A$2:$CR$600,MATCH(1,(GMWA!$CQ$2:$CQ$600=H$3)*(GMWA!$CP$2:$CP$600=H$4)*(GMWA!$CR$2:$CR$600=H$1),0),$A12-1966)} -> 9006.922 | I12: {=INDEX(GMWA!$A$2:$CR$600,MATCH(1,(GMWA!$CQ$2:$CQ$600=I$3)*(GMWA!$CP$2:$CP$600=I$4)*(GMWA!$CR$2:$CR$600=I$1),0),$A12-1966)} -> 3.064492 | ... BI12: {=INDEX(GMWA!$A$2:$CR$600,MATCH(1,(GMWA!$CQ$2:$CQ$600=BI$3)*(GMWA!$CP$2:$CP$600=BI$4)*(GMWA!$CR$2:$CR$600=BI$1),0),$A12-1966)} -> 23.33717 | BK12: =100*(B12/V12) -> 8.6681716 | BL12: =100*(C12/W12) -> 6.3736507 | BM12: =100*(D12/X12) -> 5.3282786 | BN12: =100*(E12/Y12) -> 9.5232302 | BO12: =100*(F12/Z12) -> 179600000 | BP12: =100*(G12/AA12) -> 3.9681533 | BQ12: =100*(H12/AB12) -> 6.285795 | BR12: =100*(I12/AC12) -> 2.7169626 | ... CD12: =100*(U12/AO12) -> 0.2391964
A13: =+A12+1 -> 1979 | B13: {=INDEX(GMWA!$A$2:$CR$600,MATCH(1,(GMWA!$CQ$2:$CQ$600=B$3)*(GMWA!$CP$2:$CP$600=B$4)*(GMWA!$CR$2:$CR$600=B$1),0),$A13-1966)} -> 9791 | C13: {=INDEX(GMWA!$A$2:$CR$600,MATCH(1,(GMWA!$CQ$2:$CQ$600=C$3)*(GMWA!$CP$2:$CP$600=C$4)*(GMWA!$CR$2:$CR$600=C$1),0),$A13-1966)} -> 128.475 | D13: {=INDEX(GMWA!$A$2:$CR$600,MATCH(1,(GMWA!$CQ$2:$CQ$600=D$3)*(GMWA!$CP$2:$CP$600=D$4)*(GMWA!$CR$2:$CR$600=D$1),0),$A13-1966)} -> 5571.224 | E13: {=INDEX(GMWA!$A$2:$CR$600,MATCH(1,(GMWA!$CQ$2:$CQ$600=E$3)*(GMWA!$CP$2:$CP$600=E$4)*(GMWA!$CR$2:$CR$600=E$1),0),$A13-1966)} -> 14057 | F13: {=INDEX(GMWA!$A$2:$CR$600,MATCH(1,(GMWA!$CQ$2:$CQ$600=F$3)*(GMWA!$CP$2:$CP$600=F$4)*(GMWA!$CR$2:$CR$600=F$1),0),$A13-1966)} -> 2136 | G13: {=INDEX(GMWA!$A$2:$CR$600,MATCH(1,(GMWA!$CQ$2:$CQ$600=G$3)*(GMWA!$CP$2:$CP$600=G$4)*(GMWA!$CR$2:$CR$600=G$1),0),$A13-1966)} -> 11.80134 | H13: {=INDEX(GMWA!$A$2:$CR$600,MATCH(1,(GMWA!$CQ$2:$CQ$600=H$3)*(GMWA!$CP$2:$CP$600=H$4)*(GMWA!$CR$2:$CR$600=H$1),0),$A13-1966)} -> 11487.63 | I13: {=INDEX(GMWA!$A$2:$CR$600,MATCH(1,(GMWA!$CQ$2:$CQ$600=I$3)*(GMWA!$CP$2:$CP$600=I$4)*(GMWA!$CR$2:$CR$600=I$1),0),$A13-1966)} -> 2.971176 | ... BI13: {=INDEX(GMWA!$A$2:$CR$600,MATCH(1,(GMWA!$CQ$2:$CQ$600=BI$3)*(GMWA!$CP$2:$CP$600=BI$4)*(GMWA!$CR$2:$CR$600=BI$1),0),$A13-1966)} -> 23.33717 | BK13: =100*(B13/V13) -> 9.3419333 | BL13: =100*(C13/W13) -> 6.7311974 | BM13: =100*(D13/X13) -> 5.6404892 | BN13: =100*(E13/Y13) -> 10.594664 | BO13: =100*(F13/Z13) -> 213600000 | BP13: =100*(G13/AA13) -> 7.0666707 | BQ13: =100*(H13/AB13) -> 6.2418083 | BR13: =100*(I13/AC13) -> 2.534986 | ... CD13: =100*(U13/AO13) -> 0.27793412
A14: =+A13+1 -> 1980 | B14: {=INDEX(GMWA!$A$2:$CR$600,MATCH(1,(GMWA!$CQ$2:$CQ$600=B$3)*(GMWA!$CP$2:$CP$600=B$4)*(GMWA!$CR$2:$CR$600=B$1),0),$A14-1966)} -> 11972 | C14: {=INDEX(GMWA!$A$2:$CR$600,MATCH(1,(GMWA!$CQ$2:$CQ$600=C$3)*(GMWA!$CP$2:$CP$600=C$4)*(GMWA!$CR$2:$CR$600=C$1),0),$A14-1966)} -> 148.775 | D14: {=INDEX(GMWA!$A$2:$CR$600,MATCH(1,(GMWA!$CQ$2:$CQ$600=D$3)*(GMWA!$CP$2:$CP$600=D$4)*(GMWA!$CR$2:$CR$600=D$1),0),$A14-1966)} -> 7259.869 | E14: {=INDEX(GMWA!$A$2:$CR$600,MATCH(1,(GMWA!$CQ$2:$CQ$600=E$3)*(GMWA!$CP$2:$CP$600=E$4)*(GMWA!$CR$2:$CR$600=E$1),0),$A14-1966)} -> 17033 | F14: {=INDEX(GMWA!$A$2:$CR$600,MATCH(1,(GMWA!$CQ$2:$CQ$600=F$3)*(GMWA!$CP$2:$CP$600=F$4)*(GMWA!$CR$2:$CR$600=F$1),0),$A14-1966)} -> 2396 | G14: {=INDEX(GMWA!$A$2:$CR$600,MATCH(1,(GMWA!$CQ$2:$CQ$600=G$3)*(GMWA!$CP$2:$CP$600=G$4)*(GMWA!$CR$2:$CR$600=G$1),0),$A14-1966)} -> 14.26993 | H14: {=INDEX(GMWA!$A$2:$CR$600,MATCH(1,(GMWA!$CQ$2:$CQ$600=H$3)*(GMWA!$CP$2:$CP$600=H$4)*(GMWA!$CR$2:$CR$600=H$1),0),$A14-1966)} -> 16780.39 | I14: {=INDEX(GMWA!$A$2:$CR$600,MATCH(1,(GMWA!$CQ$2:$CQ$600=I$3)*(GMWA!$CP$2:$CP$600=I$4)*(GMWA!$CR$2:$CR$600=I$1),0),$A14-1966)} -> 3.154236 | ... BI14: {=INDEX(GMWA!$A$2:$CR$600,MATCH(1,(GMWA!$CQ$2:$CQ$600=BI$3)*(GMWA!$CP$2:$CP$600=BI$4)*(GMWA!$CR$2:$CR$600=BI$1),0),$A14-1966)} -> 23.33717 | BK14: =100*(B14/V14) -> 9.8501497 | BL14: =100*(C14/W14) -> 7.2611566 | BM14: =100*(D14/X14) -> 6.1974945 | BN14: =100*(E14/Y14) -> 11.32566 | BO14: =100*(F14/Z14) -> 239600000 | BP14: =100*(G14/AA14) -> 8.0359564 | BQ14: =100*(H14/AB14) -> 6.4221104 | BR14: =100*(I14/AC14) -> 2.6313609 | ... CD14: =100*(U14/AO14) -> 0.15037526
A15: =+A14+1 -> 1981 | B15: {=INDEX(GMWA!$A$2:$CR$600,MATCH(1,(GMWA!$CQ$2:$CQ$600=B$3)*(GMWA!$CP$2:$CP$600=B$4)*(GMWA!$CR$2:$CR$600=B$1),0),$A15-1966)} -> 14207 | C15: {=INDEX(GMWA!$A$2:$CR$600,MATCH(1,(GMWA!$CQ$2:$CQ$600=C$3)*(GMWA!$CP$2:$CP$600=C$4)*(GMWA!$CR$2:$CR$600=C$1),0),$A15-1966)} -> 180.075 | D15: {=INDEX(GMWA!$A$2:$CR$600,MATCH(1,(GMWA!$CQ$2:$CQ$600=D$3)*(GMWA!$CP$2:$CP$600=D$4)*(GMWA!$CR$2:$CR$600=D$1),0),$A15-1966)} -> 8747.427 | E15: {=INDEX(GMWA!$A$2:$CR$600,MATCH(1,(GMWA!$CQ$2:$CQ$600=E$3)*(GMWA!$CP$2:$CP$600=E$4)*(GMWA!$CR$2:$CR$600=E$1),0),$A15-1966)} -> 22530 | F15: {=INDEX(GMWA!$A$2:$CR$600,MATCH(1,(GMWA!$CQ$2:$CQ$600=F$3)*(GMWA!$CP$2:$CP$600=F$4)*(GMWA!$CR$2:$CR$600=F$1),0),$A15-1966)} -> 2661 | G15: {=INDEX(GMWA!$A$2:$CR$600,MATCH(1,(GMWA!$CQ$2:$CQ$600=G$3)*(GMWA!$CP$2:$CP$600=G$4)*(GMWA!$CR$2:$CR$600=G$1),0),$A15-1966)} -> 20.8591 | H15: {=INDEX(GMWA!$A$2:$CR$600,MATCH(1,(GMWA!$CQ$2:$CQ$600=H$3)*(GMWA!$CP$2:$CP$600=H$4)*(GMWA!$CR$2:$CR$600=H$1),0),$A15-1966)} -> 24984.48 | I15: {=INDEX(GMWA!$A$2:$CR$600,MATCH(1,(GMWA!$CQ$2:$CQ$600=I$3)*(GMWA!$CP$2:$CP$600=I$4)*(GMWA!$CR$2:$CR$600=I$1),0),$A15-1966)} -> 3.402169 | ... BI15: {=INDEX(GMWA!$A$2:$CR$600,MATCH(1,(GMWA!$CQ$2:$CQ$600=BI$3)*(GMWA!$CP$2:$CP$600=BI$4)*(GMWA!$CR$2:$CR$600=BI$1),0),$A15-1966)} -> 23.33717 | BK15: =100*(B15/V15) -> 10.779906 | BL15: =100*(C15/W15) -> 8.0297351 | BM15: =100*(D15/X15) -> 6.1947545 | BN15: =100*(E15/Y15) -> 12.703478 | BO15: =100*(F15/Z15) -> 266100000 | BP15: =100*(G15/AA15) -> 8.7574836 | BQ15: =100*(H15/AB15) -> 7.4161822 | BR15: =100*(I15/AC15) -> 2.8492899 | ... CD15: =100*(U15/AO15) -> 0.099924332
A16: =+A15+1 -> 1982 | B16: {=INDEX(GMWA!$A$2:$CR$600,MATCH(1,(GMWA!$CQ$2:$CQ$600=B$3)*(GMWA!$CP$2:$CP$600=B$4)*(GMWA!$CR$2:$CR$600=B$1),0),$A16-1966)} -> 15540 | C16: {=INDEX(GMWA!$A$2:$CR$600,MATCH(1,(GMWA!$CQ$2:$CQ$600=C$3)*(GMWA!$CP$2:$CP$600=C$4)*(GMWA!$CR$2:$CR$600=C$1),0),$A16-1966)} -> 206.175 | D16: {=INDEX(GMWA!$A$2:$CR$600,MATCH(1,(GMWA!$CQ$2:$CQ$600=D$3)*(GMWA!$CP$2:$CP$600=D$4)*(GMWA!$CR$2:$CR$600=D$1),0),$A16-1966)} -> 10090.23 | E16: {=INDEX(GMWA!$A$2:$CR$600,MATCH(1,(GMWA!$CQ$2:$CQ$600=E$3)*(GMWA!$CP$2:$CP$600=E$4)*(GMWA!$CR$2:$CR$600=E$1),0),$A16-1966)} -> 27419 | F16: {=INDEX(GMWA!$A$2:$CR$600,MATCH(1,(GMWA!$CQ$2:$CQ$600=F$3)*(GMWA!$CP$2:$CP$600=F$4)*(GMWA!$CR$2:$CR$600=F$1),0),$A16-1966)} -> 3141 | G16: {=INDEX(GMWA!$A$2:$CR$600,MATCH(1,(GMWA!$CQ$2:$CQ$600=G$3)*(GMWA!$CP$2:$CP$600=G$4)*(GMWA!$CR$2:$CR$600=G$1),0),$A16-1966)} -> 27.02273 | H16: {=INDEX(GMWA!$A$2:$CR$600,MATCH(1,(GMWA!$CQ$2:$CQ$600=H$3)*(GMWA!$CP$2:$CP$600=H$4)*(GMWA!$CR$2:$CR$600=H$1),0),$A16-1966)} -> 36744.3 | I16: {=INDEX(GMWA!$A$2:$CR$600,MATCH(1,(GMWA!$CQ$2:$CQ$600=I$3)*(GMWA!$CP$2:$CP$600=I$4)*(GMWA!$CR$2:$CR$600=I$1),0),$A16-1966)} -> 3.559402 | ... BI16: {=INDEX(GMWA!$A$2:$CR$600,MATCH(1,(GMWA!$CQ$2:$CQ$600=BI$3)*(GMWA!$CP$2:$CP$600=BI$4)*(GMWA!$CR$2:$CR$600=BI$1),0),$A16-1966)} -> 23.33717 | BK16: =100*(B16/V16) -> 11.054298 | BL16: =100*(C16/W16) -> 8.1881566 | BM16: =100*(D16/X16) -> 6.1194076 | BN16: =100*(E16/Y16) -> 13.073351 | BO16: =100*(F16/Z16) -> 314100000 | BP16: =100*(G16/AA16) -> 8.1714717 | BQ16: =100*(H16/AB16) -> 8.4203707 | BR16: =100*(I16/AC16) -> 3.0338252 | ... CD16: =100*(U16/AO16) -> 0.075589546
A17: =+A16+1 -> 1983 | B17: {=INDEX(GMWA!$A$2:$CR$600,MATCH(1,(GMWA!$CQ$2:$CQ$600=B$3)*(GMWA!$CP$2:$CP$600=B$4)*(GMWA!$CR$2:$CR$600=B$1),0),$A17-1966)} -> 15996 | C17: {=INDEX(GMWA!$A$2:$CR$600,MATCH(1,(GMWA!$CQ$2:$CQ$600=C$3)*(GMWA!$CP$2:$CP$600=C$4)*(GMWA!$CR$2:$CR$600=C$1),0),$A17-1966)} -> 227.975 | D17: {=INDEX(GMWA!$A$2:$CR$600,MATCH(1,(GMWA!$CQ$2:$CQ$600=D$3)*(GMWA!$CP$2:$CP$600=D$4)*(GMWA!$CR$2:$CR$600=D$1),0),$A17-1966)} -> 11534.9 | E17: {=INDEX(GMWA!$A$2:$CR$600,MATCH(1,(GMWA!$CQ$2:$CQ$600=E$3)*(GMWA!$CP$2:$CP$600=E$4)*(GMWA!$CR$2:$CR$600=E$1),0),$A17-1966)} -> 29858 | F17: {=INDEX(GMWA!$A$2:$CR$600,MATCH(1,(GMWA!$CQ$2:$CQ$600=F$3)*(GMWA!$CP$2:$CP$600=F$4)*(GMWA!$CR$2:$CR$600=F$1),0),$A17-1966)} -> 3764 | G17: {=INDEX(GMWA!$A$2:$CR$600,MATCH(1,(GMWA!$CQ$2:$CQ$600=G$3)*(GMWA!$CP$2:$CP$600=G$4)*(GMWA!$CR$2:$CR$600=G$1),0),$A17-1966)} -> 40.02752 | H17: {=INDEX(GMWA!$A$2:$CR$600,MATCH(1,(GMWA!$CQ$2:$CQ$600=H$3)*(GMWA!$CP$2:$CP$600=H$4)*(GMWA!$CR$2:$CR$600=H$1),0),$A17-1966)} -> 43218.67 | I17: {=INDEX(GMWA!$A$2:$CR$600,MATCH(1,(GMWA!$CQ$2:$CQ$600=I$3)*(GMWA!$CP$2:$CP$600=I$4)*(GMWA!$CR$2:$CR$600=I$1),0),$A17-1966)} -> 3.657443 | ... BI17: {=INDEX(GMWA!$A$2:$CR$600,MATCH(1,(GMWA!$CQ$2:$CQ$600=BI$3)*(GMWA!$CP$2:$CP$600=BI$4)*(GMWA!$CR$2:$CR$600=BI$1),0),$A17-1966)} -> 23.33717 | BK17: =100*(B17/V17) -> 10.51792 | BL17: =100*(C17/W17) -> 8.1487452 | BM17: =100*(D17/X17) -> 6.0859908 | BN17: =100*(E17/Y17) -> 11.854622 | BO17: =100*(F17/Z17) -> 376400000 | BP17: =100*(G17/AA17) -> 9.4344673 | BQ17: =100*(H17/AB17) -> 8.3170278 | BR17: =100*(I17/AC17) -> 3.1183198 | ... CD17: =100*(U17/AO17) -> 0.054465
A18: =+A17+1 -> 1984 | B18: {=INDEX(GMWA!$A$2:$CR$600,MATCH(1,(GMWA!$CQ$2:$CQ$600=B$3)*(GMWA!$CP$2:$CP$600=B$4)*(GMWA!$CR$2:$CR$600=B$1),0),$A18-1966)} -> 17461 | C18: {=INDEX(GMWA!$A$2:$CR$600,MATCH(1,(GMWA!$CQ$2:$CQ$600=C$3)*(GMWA!$CP$2:$CP$600=C$4)*(GMWA!$CR$2:$CR$600=C$1),0),$A18-1966)} -> 260.05 | D18: {=INDEX(GMWA!$A$2:$CR$600,MATCH(1,(GMWA!$CQ$2:$CQ$600=D$3)*(GMWA!$CP$2:$CP$600=D$4)*(GMWA!$CR$2:$CR$600=D$1),0),$A18-1966)} -> 12792.81 | E18: {=INDEX(GMWA!$A$2:$CR$600,MATCH(1,(GMWA!$CQ$2:$CQ$600=E$3)*(GMWA!$CP$2:$CP$600=E$4)*(GMWA!$CR$2:$CR$600=E$1),0),$A18-1966)} -> 35147 | F18: {=INDEX(GMWA!$A$2:$CR$600,MATCH(1,(GMWA!$CQ$2:$CQ$600=F$3)*(GMWA!$CP$2:$CP$600=F$4)*(GMWA!$CR$2:$CR$600=F$1),0),$A18-1966)} -> 4951 | G18: {=INDEX(GMWA!$A$2:$CR$600,MATCH(1,(GMWA!$CQ$2:$CQ$600=G$3)*(GMWA!$CP$2:$CP$600=G$4)*(GMWA!$CR$2:$CR$600=G$1),0),$A18-1966)} -> 52.45829 | H18: {=INDEX(GMWA!$A$2:$CR$600,MATCH(1,(GMWA!$CQ$2:$CQ$600=H$3)*(GMWA!$CP$2:$CP$600=H$4)*(GMWA!$CR$2:$CR$600=H$1),0),$A18-1966)} -> 51442.58 | I18: {=INDEX(GMWA!$A$2:$CR$600,MATCH(1,(GMWA!$CQ$2:$CQ$600=I$3)*(GMWA!$CP$2:$CP$600=I$4)*(GMWA!$CR$2:$CR$600=I$1),0),$A18-1966)} -> 3.631457 | ... BI18: {=INDEX(GMWA!$A$2:$CR$600,MATCH(1,(GMWA!$CQ$2:$CQ$600=BI$3)*(GMWA!$CP$2:$CP$600=BI$4)*(GMWA!$CR$2:$CR$600=BI$1),0),$A18-1966)} -> 23.33717 | BK18: =100*(B18/V18) -> 10.66982 | BL18: =100*(C18/W18) -> 8.3536325 | BM18: =100*(D18/X18) -> 6.1521937 | BN18: =100*(E18/Y18) -> 12.091678 | BO18: =100*(F18/Z18) -> 495100000 | BP18: =100*(G18/AA18) -> 11.012043 | BQ18: =100*(H18/AB18) -> 8.6642995 | BR18: =100*(I18/AC18) -> 3.1088846 | ... CD18: =100*(U18/AO18) -> 0.039992361
A19: =+A18+1 -> 1985 | B19: {=INDEX(GMWA!$A$2:$CR$600,MATCH(1,(GMWA!$CQ$2:$CQ$600=B$3)*(GMWA!$CP$2:$CP$600=B$4)*(GMWA!$CR$2:$CR$600=B$1),0),$A19-1966)} -> 19036 | C19: {=INDEX(GMWA!$A$2:$CR$600,MATCH(1,(GMWA!$CQ$2:$CQ$600=C$3)*(GMWA!$CP$2:$CP$600=C$4)*(GMWA!$CR$2:$CR$600=C$1),0),$A19-1966)} -> 285.75 | D19: {=INDEX(GMWA!$A$2:$CR$600,MATCH(1,(GMWA!$CQ$2:$CQ$600=D$3)*(GMWA!$CP$2:$CP$600=D$4)*(GMWA!$CR$2:$CR$600=D$1),0),$A19-1966)} -> 13766.58 | E19: {=INDEX(GMWA!$A$2:$CR$600,MATCH(1,(GMWA!$CQ$2:$CQ$600=E$3)*(GMWA!$CP$2:$CP$600=E$4)*(GMWA!$CR$2:$CR$600=E$1),0),$A19-1966)} -> 40585 | F19: {=INDEX(GMWA!$A$2:$CR$600,MATCH(1,(GMWA!$CQ$2:$CQ$600=F$3)*(GMWA!$CP$2:$CP$600=F$4)*(GMWA!$CR$2:$CR$600=F$1),0),$A19-1966)} -> 6665 | G19: {=INDEX(GMWA!$A$2:$CR$600,MATCH(1,(GMWA!$CQ$2:$CQ$600=G$3)*(GMWA!$CP$2:$CP$600=G$4)*(GMWA!$CR$2:$CR$600=G$1),0),$A19-1966)} -> 58.77248 | H19: {=INDEX(GMWA!$A$2:$CR$600,MATCH(1,(GMWA!$CQ$2:$CQ$600=H$3)*(GMWA!$CP$2:$CP$600=H$4)*(GMWA!$CR$2:$CR$600=H$1),0),$A19-1966)} -> 62413.66 | I19: {=INDEX(GMWA!$A$2:$CR$600,MATCH(1,(GMWA!$CQ$2:$CQ$600=I$3)*(GMWA!$CP$2:$CP$600=I$4)*(GMWA!$CR$2:$CR$600=I$1),0),$A19-1966)} -> 3.735457 | ... BI19: {=INDEX(GMWA!$A$2:$CR$600,MATCH(1,(GMWA!$CQ$2:$CQ$600=BI$3)*(GMWA!$CP$2:$CP$600=BI$4)*(GMWA!$CR$2:$CR$600=BI$1),0),$A19-1966)} -> 23.33717 | BK19: =100*(B19/V19) -> 10.810823 | BL19: =100*(C19/W19) -> 8.1672936 | BM19: =100*(D19/X19) -> 5.9562838 | BN19: =100*(E19/Y19) -> 11.919692 | BO19: =100*(F19/Z19) -> 666500000 | BP19: =100*(G19/AA19) -> 11.735039 | BQ19: =100*(H19/AB19) -> 9.7183358 | BR19: =100*(I19/AC19) -> 3.260981 | ... CD19: =100*(U19/AO19) -> 0.030260414
... A84: =+A83+1 -> 2050 | B84: {=INDEX(GMWA!$A$2:$CR$600,MATCH(1,(GMWA!$CQ$2:$CQ$600=B$3)*(GMWA!$CP$2:$CP$600=B$4)*(GMWA!$CR$2:$CR$600=B$1),0),$A84-1966)} -> 212062.4 | C84: {=INDEX(GMWA!$A$2:$CR$600,MATCH(1,(GMWA!$CQ$2:$CQ$600=C$3)*(GMWA!$CP$2:$CP$600=C$4)*(GMWA!$CR$2:$CR$600=C$1),0),$A84-1966)} -> 4043.098 | D84: {=INDEX(GMWA!$A$2:$CR$600,MATCH(1,(GMWA!$CQ$2:$CQ$600=D$3)*(GMWA!$CP$2:$CP$600=D$4)*(GMWA!$CR$2:$CR$600=D$1),0),$A84-1966)} -> 22421.49 | E84: {=INDEX(GMWA!$A$2:$CR$600,MATCH(1,(GMWA!$CQ$2:$CQ$600=E$3)*(GMWA!$CP$2:$CP$600=E$4)*(GMWA!$CR$2:$CR$600=E$1),0),$A84-1966)} -> 109089.5 | F84: {=INDEX(GMWA!$A$2:$CR$600,MATCH(1,(GMWA!$CQ$2:$CQ$600=F$3)*(GMWA!$CP$2:$CP$600=F$4)*(GMWA!$CR$2:$CR$600=F$1),0),$A84-1966)} -> 119241.3 | G84: {=INDEX(GMWA!$A$2:$CR$600,MATCH(1,(GMWA!$CQ$2:$CQ$600=G$3)*(GMWA!$CP$2:$CP$600=G$4)*(GMWA!$CR$2:$CR$600=G$1),0),$A84-1966)} -> 73.18843 | H84: {=INDEX(GMWA!$A$2:$CR$600,MATCH(1,(GMWA!$CQ$2:$CQ$600=H$3)*(GMWA!$CP$2:$CP$600=H$4)*(GMWA!$CR$2:$CR$600=H$1),0),$A84-1966)} -> 55505.98 | I84: {=INDEX(GMWA!$A$2:$CR$600,MATCH(1,(GMWA!$CQ$2:$CQ$600=I$3)*(GMWA!$CP$2:$CP$600=I$4)*(GMWA!$CR$2:$CR$600=I$1),0),$A84-1966)} -> 4.672529 | ... BI84: {=INDEX(GMWA!$A$2:$CR$600,MATCH(1,(GMWA!$CQ$2:$CQ$600=BI$3)*(GMWA!$CP$2:$CP$600=BI$4)*(GMWA!$CR$2:$CR$600=BI$1),0),$A84-1966)} -> 555.4814 | BK84: =100*(B84/V84) -> 3.2512621 | BL84: =100*(C84/W84) -> 2.9702672 | BM84: =100*(D84/X84) -> 1.4174301 | BN84: =100*(E84/Y84) -> 3.829302 | BO84: =100*(F84/Z84) -> 3.1613806 | BP84: =100*(G84/AA84) -> 7.7163712 | BQ84: =100*(H84/AB84) -> 1.6033752 | BR84: =100*(I84/AC84) -> 0.95973631 | ... CD84: =100*(U84/AO84) -> 2.2457696

Sheet DataScen
C1: OBR_Baseline.db | D1: =$C$1 -> OBR_Baseline.db | E1: =$C$1 -> OBR_Baseline.db | F1: =$C$1 -> OBR_Baseline.db | G1: =$C$1 -> OBR_Baseline.db | H1: =$C$1 -> OBR_Baseline.db | I1: =$C$1 -> OBR_Baseline.db | J1: =$C$1 -> OBR_Baseline.db | K1: =$C$1 -> OBR_Baseline.db | ... T1: =$C$1 -> OBR_Baseline.db | U1: Conservatives.db | V1: =$U$1 -> Conservatives.db | W1: =$U$1 -> Conservatives.db | X1: =$U$1 -> Conservatives.db | Y1: =$U$1 -> Conservatives.db | Z1: =$U$1 -> Conservatives.db | AA1: =$U$1 -> Conservatives.db | AB1: =$U$1 -> Conservatives.db | AC1: =$U$1 -> Conservatives.db | ... AL1: =$U$1 -> Conservatives.db | AM1: Labour.db | AN1: =$AM$1 -> Labour.db | AO1: =$AM$1 -> Labour.db | AP1: =$AM$1 -> Labour.db | AQ1: =$AM$1 -> Labour.db | AR1: =$AM$1 -> Labour.db | AS1: =$AM$1 -> Labour.db | AT1: =$AM$1 -> Labour.db | AU1: =$AM$1 -> Labour.db | ... BD1: =$AM$1 -> Labour.db | BE1: Labour_likely.db | BF1: =$BE$1 -> Labour_likely.db | BG1: =$BE$1 -> Labour_likely.db | BH1: =$BE$1 -> Labour_likely.db | BI1: =$BE$1 -> Labour_likely.db | BJ1: =$BE$1 -> Labour_likely.db | BK1: =$BE$1 -> Labour_likely.db | BL1: =$BE$1 -> Labour_likely.db | BM1: =$BE$1 -> Labour_likely.db | ... BV1: =$BE$1 -> Labour_likely.db | BY1: Lookup | BZ1: Lookup | CB1: Financial years
C2: UK | D2: UK | E2: UK | F2: UK | G2: UK | H2: UK | I2: UK | J2: UK | K2: UK | L2: UK | M2: UK | N2: UK | O2: UK | P2: UK | Q2: UK | R2: UK | S2: UK | T2: UK | U2: UK | V2: UK | W2: UK | X2: UK | Y2: UK | Z2: UK | AA2: UK | AB2: UK | AC2: UK | AD2: UK | AE2: UK | AF2: UK | AG2: UK | AH2: UK | AI2: UK | AJ2: UK | AK2: UK | AL2: UK | AM2: UK | AN2: UK | AO2: UK | AP2: UK | AQ2: UK | AR2: UK | AS2: UK | AT2: UK | AU2: UK | AV2: UK | AW2: UK | AX2: UK | AY2: UK | AZ2: UK | BA2: UK | BB2: UK | BC2: UK | BD2: UK | BE2: UK | BF2: UK | BG2: UK | BH2: UK | BI2: UK | BJ2: UK | BK2: UK | BL2: UK | BM2: UK | BN2: UK | BO2: UK | BP2: UK | BQ2: UK | BR2: UK | BS2: UK | BT2: UK | BU2: UK | BV2: UK | BY2: FY sum | BZ2: FY end | CD2: =C1 -> OBR_Baseline.db | CE2: =D1 -> OBR_Baseline.db | CF2: =E1 -> OBR_Baseline.db | CG2: =F1 -> OBR_Baseline.db | CH2: =G1 -> OBR_Baseline.db | CI2: =H1 -> OBR_Baseline.db | CJ2: =I1 -> OBR_Baseline.db | CK2: =J1 -> OBR_Baseline.db | ... EW2: =BV1 -> Labour_likely.db
C3: GDP | D3: PSNBX | E3: PSCBX | F3: PSCEX | G3: PSNIX | H3: DEPX | I3: GREVX | J3: GNDBTX | K3: GDP! | L3: YHAT | M3: PGDP | N3: CPI | O3: RCBEOP | P3: GVAMAN | Q3: IP | R3: GVACON | S3: UPILO | T3: CUMOD | U3: GDP | V3: PSNBX | W3: PSCBX | X3: PSCEX | Y3: PSNIX | Z3: DEPX | AA3: GREVX | AB3: GNDBTX | AC3: GDP! | AD3: YHAT | AE3: PGDP | AF3: CPI | AG3: RCBEOP | AH3: GVAMAN | AI3: IP | AJ3: GVACON | AK3: UPILO | AL3: CUMOD | AM3: GDP | AN3: PSNBX | AO3: PSCBX | AP3: PSCEX | AQ3: PSNIX | AR3: DEPX | AS3: GREVX | AT3: GNDBTX | AU3: GDP! | AV3: YHAT | AW3: PGDP | AX3: CPI | AY3: RCBEOP | AZ3: GVAMAN | BA3: IP | BB3: GVACON | BC3: UPILO | BD3: CUMOD | BE3: GDP | BF3: PSNBX | BG3: PSCBX | BH3: PSCEX | BI3: PSNIX | BJ3: DEPX | BK3: GREVX | BL3: GNDBTX | BM3: GDP! | BN3: YHAT | BO3: PGDP | BP3: CPI | BQ3: RCBEOP | BR3: GVAMAN | BS3: IP | BT3: GVACON | BU3: UPILO | BV3: CUMOD | CD3: =C3 -> GDP | CE3: =D3 -> PSNBX | CF3: =E3 -> PSCBX | CG3: =F3 -> PSCEX | CH3: =G3 -> PSNIX | CI3: =H3 -> DEPX | CJ3: =I3 -> GREVX | CK3: =J3 -> GNDBTX | ... EW3: =BV3 -> CUMOD
C4: GBR | D4: GBR | E4: GBR | F4: GBR | G4: GBR | H4: GBR | I4: GBR | J4: GBR | K4: GBR | L4: GBR | M4: GBR | N4: GBR | O4: GBR | P4: GBR | Q4: GBR | R4: GBR | S4: GBR | T4: GBR | U4: GBR | V4: GBR | W4: GBR | X4: GBR | Y4: GBR | Z4: GBR | AA4: GBR | AB4: GBR | AC4: GBR | AD4: GBR | AE4: GBR | AF4: GBR | AG4: GBR | AH4: GBR | AI4: GBR | AJ4: GBR | AK4: GBR | AL4: GBR | AM4: GBR | AN4: GBR | AO4: GBR | AP4: GBR | AQ4: GBR | AR4: GBR | AS4: GBR | AT4: GBR | AU4: GBR | AV4: GBR | AW4: GBR | AX4: GBR | AY4: GBR | AZ4: GBR | BA4: GBR | BB4: GBR | BC4: GBR | BD4: GBR | BE4: GBR | BF4: GBR | BG4: GBR | BH4: GBR | BI4: GBR | BJ4: GBR | BK4: GBR | BL4: GBR | BM4: GBR | BN4: GBR | BO4: GBR | BP4: GBR | BQ4: GBR | BR4: GBR | BS4: GBR | BT4: GBR | BU4: GBR | BV4: GBR
C5: L | D5: L | E5: L | F5: L | G5: L | H5: L | I5: L | J5: L | K5: L | L5: L | M5: L | N5: L | O5: L | P5: L | Q5: L | R5: L | S5: L | T5: L | U5: L | V5: L | W5: L | X5: L | Y5: L | Z5: L | AA5: L | AB5: L | AC5: L | AD5: L | AE5: L | AF5: L | AG5: L | AH5: L | AI5: L | AJ5: L | AK5: L | AL5: L | AM5: L | AN5: L | AO5: L | AP5: L | AQ5: L | AR5: L | AS5: L | AT5: L | AU5: L | AV5: L | AW5: L | AX5: L | AY5: L | AZ5: L | BA5: L | BB5: L | BC5: L | BD5: L | BE5: L | BF5: L | BG5: L | BH5: L | BI5: L | BJ5: L | BK5: L | BL5: L | BM5: L | BN5: L | BO5: L | BP5: L | BQ5: L | BR5: L | BS5: L | BT5: L | BU5: L | BV5: L
B6: =B206+5 -> 2184 | C6: {=_xlfn.CONCAT(INDEX(GMWSCEN!$A$2:$HJ$150,MATCH(1,(GMWSCEN!$HI$2:$HI$150=C$3)*(GMWSCEN!$HJ$2:$HJ$150=C$1),0),$B6-1973),"0",(INDEX(GMWSCEN!$A$2:$HJ$150,MATCH(1,(GMWSCEN!$HI$2:$HI$150=C$3)*(GMWSCEN!$HJ$2:$HJ$150=C$1),0),$B6-1972)))} -> 202401 | D6: {=_xlfn.CONCAT(INDEX([5]GMW!$A$2:$HJ$150,MATCH(1,([5]GMW!$HI$2:$HI$150=D$3)*([5]GMW!$HJ$2:$HJ$150=D$1),0),$B6-1973),"0",(INDEX([5]GMW!$A$2:$HJ$150,MATCH(1,([5]GMW!$HI$2:$HI$150=D$3)*([5]GMW!$HJ$2:$HJ$150=D$1),0),$B6-1972)))} -> 202401 | E6: {=_xlfn.CONCAT(INDEX([5]GMW!$A$2:$HJ$150,MATCH(1,([5]GMW!$HI$2:$HI$150=E$3)*([5]GMW!$HJ$2:$HJ$150=E$1),0),$B6-1973),"0",(INDEX([5]GMW!$A$2:$HJ$150,MATCH(1,([5]GMW!$HI$2:$HI$150=E$3)*([5]GMW!$HJ$2:$HJ$150=E$1),0),$B6-1972)))} -> 202401 | F6: {=_xlfn.CONCAT(INDEX([5]GMW!$A$2:$HJ$150,MATCH(1,([5]GMW!$HI$2:$HI$150=F$3)*([5]GMW!$HJ$2:$HJ$150=F$1),0),$B6-1973),"0",(INDEX([5]GMW!$A$2:$HJ$150,MATCH(1,([5]GMW!$HI$2:$HI$150=F$3)*([5]GMW!$HJ$2:$HJ$150=F$1),0),$B6-1972)))} -> 202401 | G6: {=_xlfn.CONCAT(INDEX([5]GMW!$A$2:$HJ$150,MATCH(1,([5]GMW!$HI$2:$HI$150=G$3)*([5]GMW!$HJ$2:$HJ$150=G$1),0),$B6-1973),"0",(INDEX([5]GMW!$A$2:$HJ$150,MATCH(1,([5]GMW!$HI$2:$HI$150=G$3)*([5]GMW!$HJ$2:$HJ$150=G$1),0),$B6-1972)))} -> 202401 | H6: {=_xlfn.CONCAT(INDEX([5]GMW!$A$2:$HJ$150,MATCH(1,([5]GMW!$HI$2:$HI$150=H$3)*([5]GMW!$HJ$2:$HJ$150=H$1),0),$B6-1973),"0",(INDEX([5]GMW!$A$2:$HJ$150,MATCH(1,([5]GMW!$HI$2:$HI$150=H$3)*([5]GMW!$HJ$2:$HJ$150=H$1),0),$B6-1972)))} -> 202401 | I6: {=_xlfn.CONCAT(INDEX([5]GMW!$A$2:$HJ$150,MATCH(1,([5]GMW!$HI$2:$HI$150=I$3)*([5]GMW!$HJ$2:$HJ$150=I$1),0),$B6-1973),"0",(INDEX([5]GMW!$A$2:$HJ$150,MATCH(1,([5]GMW!$HI$2:$HI$150=I$3)*([5]GMW!$HJ$2:$HJ$150=I$1),0),$B6-1972)))} -> 202401 | J6: {=_xlfn.CONCAT(INDEX([5]GMW!$A$2:$HJ$150,MATCH(1,([5]GMW!$HI$2:$HI$150=J$3)*([5]GMW!$HJ$2:$HJ$150=J$1),0),$B6-1973),"0",(INDEX([5]GMW!$A$2:$HJ$150,MATCH(1,([5]GMW!$HI$2:$HI$150=J$3)*([5]GMW!$HJ$2:$HJ$150=J$1),0),$B6-1972)))} -> 202401 | K6: {=_xlfn.CONCAT(INDEX([5]GMW!$A$2:$HJ$150,MATCH(1,([5]GMW!$HI$2:$HI$150=K$3)*([5]GMW!$HJ$2:$HJ$150=K$1),0),$B6-1973),"0",(INDEX([5]GMW!$A$2:$HJ$150,MATCH(1,([5]GMW!$HI$2:$HI$150=K$3)*([5]GMW!$HJ$2:$HJ$150=K$1),0),$B6-1972)))} -> 202401 | ... BV6: {=_xlfn.CONCAT(INDEX([5]GMW!$A$2:$HJ$150,MATCH(1,([5]GMW!$HI$2:$HI$150=BV$3)*([5]GMW!$HJ$2:$HJ$150=BV$1),0),$B6-1973),"0",(INDEX([5]GMW!$A$2:$HJ$150,MATCH(1,([5]GMW!$HI$2:$HI$150=BV$3)*([5]GMW!$HJ$2:$HJ$150=BV$1),0),$B6-1972)))} -> NA0NA
A7: 1980 | B7: 1980 | C7: {=INDEX(GMWSCEN!$A$2:$HJ$150,MATCH(1,(GMWSCEN!$HI$2:$HI$150=C$3)*(GMWSCEN!$HJ$2:$HJ$150=C$1),0),$B7-1973)} -> 243513 | D7: {=INDEX(GMWSCEN!$A$2:$HJ$150,MATCH(1,(GMWSCEN!$HI$2:$HI$150=D$3)*(GMWSCEN!$HJ$2:$HJ$150=D$1),0),$B7-1973)} -> 1674 | E7: {=INDEX(GMWSCEN!$A$2:$HJ$150,MATCH(1,(GMWSCEN!$HI$2:$HI$150=E$3)*(GMWSCEN!$HJ$2:$HJ$150=E$1),0),$B7-1973)} -> 302 | F7: {=INDEX(GMWSCEN!$A$2:$HJ$150,MATCH(1,(GMWSCEN!$HI$2:$HI$150=F$3)*(GMWSCEN!$HJ$2:$HJ$150=F$1),0),$B7-1973)} -> 22229 | G7: {=INDEX(GMWSCEN!$A$2:$HJ$150,MATCH(1,(GMWSCEN!$HI$2:$HI$150=G$3)*(GMWSCEN!$HJ$2:$HJ$150=G$1),0),$B7-1973)} -> 1976 | H7: {=INDEX(GMWSCEN!$A$2:$HJ$150,MATCH(1,(GMWSCEN!$HI$2:$HI$150=H$3)*(GMWSCEN!$HJ$2:$HJ$150=H$1),0),$B7-1973)} -> 2656 | I7: {=INDEX(GMWSCEN!$A$2:$HJ$150,MATCH(1,(GMWSCEN!$HI$2:$HI$150=I$3)*(GMWSCEN!$HJ$2:$HJ$150=I$1),0),$B7-1973)} -> 25187 | J7: {=INDEX(GMWSCEN!$A$2:$HJ$150,MATCH(1,(GMWSCEN!$HI$2:$HI$150=J$3)*(GMWSCEN!$HJ$2:$HJ$150=J$1),0),$B7-1973)} -> 75983.41 | ... BV7: {=INDEX(GMWSCEN!$A$2:$HJ$150,MATCH(1,(GMWSCEN!$HI$2:$HI$150=BV$3)*(GMWSCEN!$HJ$2:$HJ$150=BV$1),0),$B7-1973)} -> 0.5753517 | BY7: 1979 | CB7: 1980 | CC7: 198001 | CD7: =SUMIF($BY$7:$BY$206,$CB7,C$7:C$206) -> 948732 | CE7: =SUMIF($BY$7:$BY$206,$CB7,D$7:D$206) -> 11537 | CF7: =SUMIF($BY$7:$BY$206,$CB7,E$7:E$206) -> -5519 | CG7: =SUMIF($BY$7:$BY$206,$CB7,F$7:F$206) -> 96636 | CH7: =SUMIF($BY$7:$BY$206,$CB7,G$7:G$206) -> 6018 | CI7: =SUMIF($BY$7:$BY$206,$CB7,H$7:H$206) -> 11867 | CJ7: =SUMIF($BY$7:$BY$206,$CB7,I$7:I$206) -> 102984 | CK7: =SUMIF($BZ$7:$BZ$206,$CC7,J$7:J$206) -> 88342.79 | CL7: =SUMIF($BY$7:$BY$206,$CB7,K$7:K$206) -> 267802 | CM7: =SUMIF($BY$7:$BY$206,$CB7,L$7:L$206) -> 980411.5 | CN7: =AVERAGEIF($BY$7:$BY$206,$CB7,M$7:M$206) -> 28.233728 | CO7: =AVERAGEIF($BY$7:$BY$206,$CB7,N$7:N$206) -> 33.283678 | CP7: =AVERAGEIF($BY$7:$BY$206,$CB7,O$7:O$206) -> 14.75 | CQ7: =SUMIF($BY$7:$BY$206,$CB7,P$7:P$206) -> 96475.3 | CR7: =AVERAGEIF($BY$7:$BY$206,$CB7,Q$7:Q$206) -> 59.55 | CS7: =SUMIF($BY$7:$BY$206,$CB7,R$7:R$206) -> 0.004 | CT7: =AVERAGEIF($BY$7:$BY$206,$CB7,S$7:S$206) -> 7.575 | CU7: =SUMIF($BZ$7:$BZ$206,$CC7,T$7:T$206) -> -4.582787 | CV7: =SUMIF($BY$7:$BY$206,$CB7,U$7:U$206) -> 948732 | CW7: =SUMIF($BY$7:$BY$206,$CB7,V$7:V$206) -> 11537 | CX7: =SUMIF($BY$7:$BY$206,$CB7,W$7:W$206) -> -5519 | CY7: =SUMIF($BY$7:$BY$206,$CB7,X$7:X$206) -> 96636 | CZ7: =SUMIF($BY$7:$BY$206,$CB7,Y$7:Y$206) -> 6018 | DA7: =SUMIF($BY$7:$BY$206,$CB7,Z$7:Z$206) -> 11867 | DB7: =SUMIF($BY$7:$BY$206,$CB7,AA$7:AA$206) -> 102984 | DC7: =SUMIF($BZ$7:$BZ$206,$CC7,AB$7:AB$206) -> 88342.79 | DD7: =SUMIF($BY$7:$BY$206,$CB7,AC$7:AC$206) -> 267802 | DE7: =SUMIF($BY$7:$BY$206,$CB7,AD$7:AD$206) -> 980411.5 | DF7: =AVERAGEIF($BY$7:$BY$206,$CB7,AE$7:AE$206) -> 28.233728 | DG7: =AVERAGEIF($BY$7:$BY$206,$CB7,AF$7:AF$206) -> 33.283678 | DH7: =AVERAGEIF($BY$7:$BY$206,$CB7,AG$7:AG$206) -> 14.75 | DI7: =SUMIF($BY$7:$BY$206,$CB7,AH$7:AH$206) -> 96475.3 | DJ7: =AVERAGEIF($BY$7:$BY$206,$CB7,AI$7:AI$206) -> 59.55 | DK7: =SUMIF($BY$7:$BY$206,$CB7,AJ$7:AJ$206) -> 0.004 | DL7: =AVERAGEIF($BY$7:$BY$206,$CB7,AK$7:AK$206) -> 7.575 | DM7: =SUMIF($BZ$7:$BZ$206,$CC7,AL$7:AL$206) -> -4.582787 | DN7: =SUMIF($BY$7:$BY$206,$CB7,AM$7:AM$206) -> 948732 | DO7: =SUMIF($BY$7:$BY$206,$CB7,AN$7:AN$206) -> 11537 | DP7: =SUMIF($BY$7:$BY$206,$CB7,AO$7:AO$206) -> -5519 | DQ7: =SUMIF($BY$7:$BY$206,$CB7,AP$7:AP$206) -> 96636 | DR7: =SUMIF($BY$7:$BY$206,$CB7,AQ$7:AQ$206) -> 6018 | DS7: =SUMIF($BY$7:$BY$206,$CB7,AR$7:AR$206) -> 11867 | DT7: =SUMIF($BY$7:$BY$206,$CB7,AS$7:AS$206) -> 102984 | DU7: =SUMIF($BZ$7:$BZ$206,$CC7,AT$7:AT$206) -> 88342.79 | DV7: =SUMIF($BY$7:$BY$206,$CB7,AU$7:AU$206) -> 267802 | DW7: =SUMIF($BY$7:$BY$206,$CB7,AV$7:AV$206) -> 980411.5 | DX7: =AVERAGEIF($BY$7:$BY$206,$CB7,AW$7:AW$206) -> 28.233728 | DY7: =AVERAGEIF($BY$7:$BY$206,$CB7,AX$7:AX$206) -> 33.283678 | DZ7: =AVERAGEIF($BY$7:$BY$206,$CB7,AY$7:AY$206) -> 14.75 | EA7: =SUMIF($BY$7:$BY$206,$CB7,AZ$7:AZ$206) -> 96475.3 | EB7: =AVERAGEIF($BY$7:$BY$206,$CB7,BA$7:BA$206) -> 59.55 | EC7: =SUMIF($BY$7:$BY$206,$CB7,BB$7:BB$206) -> 0.004 | ED7: =AVERAGEIF($BY$7:$BY$206,$CB7,BC$7:BC$206) -> 7.575 | EE7: =SUMIF($BZ$7:$BZ$206,$CC7,BD$7:BD$206) -> -4.582787 | EF7: =SUMIF($BY$7:$BY$206,$CB7,BE$7:BE$206) -> 948732 | EG7: =SUMIF($BY$7:$BY$206,$CB7,BF$7:BF$206) -> 11537 | EH7: =SUMIF($BY$7:$BY$206,$CB7,BG$7:BG$206) -> -5519 | EI7: =SUMIF($BY$7:$BY$206,$CB7,BH$7:BH$206) -> 96636 | EJ7: =SUMIF($BY$7:$BY$206,$CB7,BI$7:BI$206) -> 6018 | EK7: =SUMIF($BY$7:$BY$206,$CB7,BJ$7:BJ$206) -> 11867 | EL7: =SUMIF($BY$7:$BY$206,$CB7,BK$7:BK$206) -> 102984 | EM7: =SUMIF($BZ$7:$BZ$206,$CC7,BL$7:BL$206) -> 88342.79 | EN7: =SUMIF($BY$7:$BY$206,$CB7,BM$7:BM$206) -> 267802 | EO7: =SUMIF($BY$7:$BY$206,$CB7,BN$7:BN$206) -> 980411.5 | EP7: =AVERAGEIF($BY$7:$BY$206,$CB7,BO$7:BO$206) -> 28.233728 | EQ7: =AVERAGEIF($BY$7:$BY$206,$CB7,BP$7:BP$206) -> 33.283678 | ER7: =AVERAGEIF($BY$7:$BY$206,$CB7,BQ$7:BQ$206) -> 14.75 | ES7: =SUMIF($BY$7:$BY$206,$CB7,BR$7:BR$206) -> 96475.3 | ET7: =AVERAGEIF($BY$7:$BY$206,$CB7,BS$7:BS$206) -> 59.55 | EU7: =SUMIF($BY$7:$BY$206,$CB7,BT$7:BT$206) -> 0.004 | EV7: =AVERAGEIF($BY$7:$BY$206,$CB7,BU$7:BU$206) -> 7.575 | EW7: =SUMIF($BZ$7:$BZ$206,$CC7,BV$7:BV$206) -> -4.582787
B8: =+B7+1 -> 1981 | C8: {=INDEX(GMWSCEN!$A$2:$HJ$150,MATCH(1,(GMWSCEN!$HI$2:$HI$150=C$3)*(GMWSCEN!$HJ$2:$HJ$150=C$1),0),$B8-1973)} -> 238722 | D8: {=INDEX(GMWSCEN!$A$2:$HJ$150,MATCH(1,(GMWSCEN!$HI$2:$HI$150=D$3)*(GMWSCEN!$HJ$2:$HJ$150=D$1),0),$B8-1973)} -> 3351 | E8: {=INDEX(GMWSCEN!$A$2:$HJ$150,MATCH(1,(GMWSCEN!$HI$2:$HI$150=E$3)*(GMWSCEN!$HJ$2:$HJ$150=E$1),0),$B8-1973)} -> -2364 | F8: {=INDEX(GMWSCEN!$A$2:$HJ$150,MATCH(1,(GMWSCEN!$HI$2:$HI$150=F$3)*(GMWSCEN!$HJ$2:$HJ$150=F$1),0),$B8-1973)} -> 22146 | G8: {=INDEX(GMWSCEN!$A$2:$HJ$150,MATCH(1,(GMWSCEN!$HI$2:$HI$150=G$3)*(GMWSCEN!$HJ$2:$HJ$150=G$1),0),$B8-1973)} -> 987 | H8: {=INDEX(GMWSCEN!$A$2:$HJ$150,MATCH(1,(GMWSCEN!$HI$2:$HI$150=H$3)*(GMWSCEN!$HJ$2:$HJ$150=H$1),0),$B8-1973)} -> 2802 | I8: {=INDEX(GMWSCEN!$A$2:$HJ$150,MATCH(1,(GMWSCEN!$HI$2:$HI$150=I$3)*(GMWSCEN!$HJ$2:$HJ$150=I$1),0),$B8-1973)} -> 22584 | J8: {=INDEX(GMWSCEN!$A$2:$HJ$150,MATCH(1,(GMWSCEN!$HI$2:$HI$150=J$3)*(GMWSCEN!$HJ$2:$HJ$150=J$1),0),$B8-1973)} -> 78965.55 | ... BV8: {=INDEX(GMWSCEN!$A$2:$HJ$150,MATCH(1,(GMWSCEN!$HI$2:$HI$150=BV$3)*(GMWSCEN!$HJ$2:$HJ$150=BV$1),0),$B8-1973)} -> -1.929665 | BY8: 1980 | CB8: =+CB7+1 -> 1981 | CC8: =+CC7+100 -> 198101 | CD8: =SUMIF($BY$7:$BY$206,$CB8,C$7:C$206) -> 953827 | CE8: =SUMIF($BY$7:$BY$206,$CB8,D$7:D$206) -> 5999.0001 | CF8: =SUMIF($BY$7:$BY$206,$CB8,E$7:E$206) -> -1631 | CG8: =SUMIF($BY$7:$BY$206,$CB8,F$7:F$206) -> 110587 | CH8: =SUMIF($BY$7:$BY$206,$CB8,G$7:G$206) -> 4368 | CI8: =SUMIF($BY$7:$BY$206,$CB8,H$7:H$206) -> 12966 | CJ8: =SUMIF($BY$7:$BY$206,$CB8,I$7:I$206) -> 121922 | CK8: =SUMIF($BZ$7:$BZ$206,$CC8,J$7:J$206) -> 96841.12 | CL8: =SUMIF($BY$7:$BY$206,$CB8,K$7:K$206) -> 297709 | CM8: =SUMIF($BY$7:$BY$206,$CB8,L$7:L$206) -> 991671.3 | CN8: =AVERAGEIF($BY$7:$BY$206,$CB8,M$7:M$206) -> 31.208325 | CO8: =AVERAGEIF($BY$7:$BY$206,$CB8,N$7:N$206) -> 37.031108 | CP8: =AVERAGEIF($BY$7:$BY$206,$CB8,O$7:O$206) -> 13.40625 | CQ8: =SUMIF($BY$7:$BY$206,$CB8,P$7:P$206) -> 94121.05 | CR8: =AVERAGEIF($BY$7:$BY$206,$CB8,Q$7:Q$206) -> 59.475 | CS8: =SUMIF($BY$7:$BY$206,$CB8,R$7:R$206) -> 0.004 | CT8: =AVERAGEIF($BY$7:$BY$206,$CB8,S$7:S$206) -> 10.025 | CU8: =SUMIF($BZ$7:$BZ$206,$CC8,T$7:T$206) -> -3.585911 | CV8: =SUMIF($BY$7:$BY$206,$CB8,U$7:U$206) -> 953827 | CW8: =SUMIF($BY$7:$BY$206,$CB8,V$7:V$206) -> 5999.0001 | CX8: =SUMIF($BY$7:$BY$206,$CB8,W$7:W$206) -> -1631 | CY8: =SUMIF($BY$7:$BY$206,$CB8,X$7:X$206) -> 110587 | CZ8: =SUMIF($BY$7:$BY$206,$CB8,Y$7:Y$206) -> 4368 | DA8: =SUMIF($BY$7:$BY$206,$CB8,Z$7:Z$206) -> 12966 | DB8: =SUMIF($BY$7:$BY$206,$CB8,AA$7:AA$206) -> 121922 | DC8: =SUMIF($BZ$7:$BZ$206,$CC8,AB$7:AB$206) -> 96841.12 | DD8: =SUMIF($BY$7:$BY$206,$CB8,AC$7:AC$206) -> 297709 | DE8: =SUMIF($BY$7:$BY$206,$CB8,AD$7:AD$206) -> 991671.3 | DF8: =AVERAGEIF($BY$7:$BY$206,$CB8,AE$7:AE$206) -> 31.208325 | DG8: =AVERAGEIF($BY$7:$BY$206,$CB8,AF$7:AF$206) -> 37.031108 | DH8: =AVERAGEIF($BY$7:$BY$206,$CB8,AG$7:AG$206) -> 13.40625 | DI8: =SUMIF($BY$7:$BY$206,$CB8,AH$7:AH$206) -> 94121.05 | DJ8: =AVERAGEIF($BY$7:$BY$206,$CB8,AI$7:AI$206) -> 59.475 | DK8: =SUMIF($BY$7:$BY$206,$CB8,AJ$7:AJ$206) -> 0.004 | DL8: =AVERAGEIF($BY$7:$BY$206,$CB8,AK$7:AK$206) -> 10.025 | DM8: =SUMIF($BZ$7:$BZ$206,$CC8,AL$7:AL$206) -> -3.585911 | DN8: =SUMIF($BY$7:$BY$206,$CB8,AM$7:AM$206) -> 953827 | DO8: =SUMIF($BY$7:$BY$206,$CB8,AN$7:AN$206) -> 5999.0001 | DP8: =SUMIF($BY$7:$BY$206,$CB8,AO$7:AO$206) -> -1631 | DQ8: =SUMIF($BY$7:$BY$206,$CB8,AP$7:AP$206) -> 110587 | DR8: =SUMIF($BY$7:$BY$206,$CB8,AQ$7:AQ$206) -> 4368 | DS8: =SUMIF($BY$7:$BY$206,$CB8,AR$7:AR$206) -> 12966 | DT8: =SUMIF($BY$7:$BY$206,$CB8,AS$7:AS$206) -> 121922 | DU8: =SUMIF($BZ$7:$BZ$206,$CC8,AT$7:AT$206) -> 96841.12 | DV8: =SUMIF($BY$7:$BY$206,$CB8,AU$7:AU$206) -> 297709 | DW8: =SUMIF($BY$7:$BY$206,$CB8,AV$7:AV$206) -> 991671.3 | DX8: =AVERAGEIF($BY$7:$BY$206,$CB8,AW$7:AW$206) -> 31.208325 | DY8: =AVERAGEIF($BY$7:$BY$206,$CB8,AX$7:AX$206) -> 37.031108 | DZ8: =AVERAGEIF($BY$7:$BY$206,$CB8,AY$7:AY$206) -> 13.40625 | EA8: =SUMIF($BY$7:$BY$206,$CB8,AZ$7:AZ$206) -> 94121.05 | EB8: =AVERAGEIF($BY$7:$BY$206,$CB8,BA$7:BA$206) -> 59.475 | EC8: =SUMIF($BY$7:$BY$206,$CB8,BB$7:BB$206) -> 0.004 | ED8: =AVERAGEIF($BY$7:$BY$206,$CB8,BC$7:BC$206) -> 10.025 | EE8: =SUMIF($BZ$7:$BZ$206,$CC8,BD$7:BD$206) -> -3.585911 | EF8: =SUMIF($BY$7:$BY$206,$CB8,BE$7:BE$206) -> 953827 | EG8: =SUMIF($BY$7:$BY$206,$CB8,BF$7:BF$206) -> 5999.0001 | EH8: =SUMIF($BY$7:$BY$206,$CB8,BG$7:BG$206) -> -1631 | EI8: =SUMIF($BY$7:$BY$206,$CB8,BH$7:BH$206) -> 110587 | EJ8: =SUMIF($BY$7:$BY$206,$CB8,BI$7:BI$206) -> 4368 | EK8: =SUMIF($BY$7:$BY$206,$CB8,BJ$7:BJ$206) -> 12966 | EL8: =SUMIF($BY$7:$BY$206,$CB8,BK$7:BK$206) -> 121922 | EM8: =SUMIF($BZ$7:$BZ$206,$CC8,BL$7:BL$206) -> 96841.12 | EN8: =SUMIF($BY$7:$BY$206,$CB8,BM$7:BM$206) -> 297709 | EO8: =SUMIF($BY$7:$BY$206,$CB8,BN$7:BN$206) -> 991671.3 | EP8: =AVERAGEIF($BY$7:$BY$206,$CB8,BO$7:BO$206) -> 31.208325 | EQ8: =AVERAGEIF($BY$7:$BY$206,$CB8,BP$7:BP$206) -> 37.031108 | ER8: =AVERAGEIF($BY$7:$BY$206,$CB8,BQ$7:BQ$206) -> 13.40625 | ES8: =SUMIF($BY$7:$BY$206,$CB8,BR$7:BR$206) -> 94121.05 | ET8: =AVERAGEIF($BY$7:$BY$206,$CB8,BS$7:BS$206) -> 59.475 | EU8: =SUMIF($BY$7:$BY$206,$CB8,BT$7:BT$206) -> 0.004 | EV8: =AVERAGEIF($BY$7:$BY$206,$CB8,BU$7:BU$206) -> 10.025 | EW8: =SUMIF($BZ$7:$BZ$206,$CC8,BV$7:BV$206) -> -3.585911
B9: =+B8+1 -> 1982 | C9: {=INDEX(GMWSCEN!$A$2:$HJ$150,MATCH(1,(GMWSCEN!$HI$2:$HI$150=C$3)*(GMWSCEN!$HJ$2:$HJ$150=C$1),0),$B9-1973)} -> 238432 | D9: {=INDEX(GMWSCEN!$A$2:$HJ$150,MATCH(1,(GMWSCEN!$HI$2:$HI$150=D$3)*(GMWSCEN!$HJ$2:$HJ$150=D$1),0),$B9-1973)} -> 3213 | E9: {=INDEX(GMWSCEN!$A$2:$HJ$150,MATCH(1,(GMWSCEN!$HI$2:$HI$150=E$3)*(GMWSCEN!$HJ$2:$HJ$150=E$1),0),$B9-1973)} -> -1527 | F9: {=INDEX(GMWSCEN!$A$2:$HJ$150,MATCH(1,(GMWSCEN!$HI$2:$HI$150=F$3)*(GMWSCEN!$HJ$2:$HJ$150=F$1),0),$B9-1973)} -> 23935 | G9: {=INDEX(GMWSCEN!$A$2:$HJ$150,MATCH(1,(GMWSCEN!$HI$2:$HI$150=G$3)*(GMWSCEN!$HJ$2:$HJ$150=G$1),0),$B9-1973)} -> 1686 | H9: {=INDEX(GMWSCEN!$A$2:$HJ$150,MATCH(1,(GMWSCEN!$HI$2:$HI$150=H$3)*(GMWSCEN!$HJ$2:$HJ$150=H$1),0),$B9-1973)} -> 2939 | I9: {=INDEX(GMWSCEN!$A$2:$HJ$150,MATCH(1,(GMWSCEN!$HI$2:$HI$150=I$3)*(GMWSCEN!$HJ$2:$HJ$150=I$1),0),$B9-1973)} -> 25347 | J9: {=INDEX(GMWSCEN!$A$2:$HJ$150,MATCH(1,(GMWSCEN!$HI$2:$HI$150=J$3)*(GMWSCEN!$HJ$2:$HJ$150=J$1),0),$B9-1973)} -> 81955.84 | ... BV9: {=INDEX(GMWSCEN!$A$2:$HJ$150,MATCH(1,(GMWSCEN!$HI$2:$HI$150=BV$3)*(GMWSCEN!$HJ$2:$HJ$150=BV$1),0),$B9-1973)} -> -2.527905 | BY9: 1980 | CB9: =+CB8+1 -> 1982 | CC9: =+CC8+100 -> 198201 | CD9: =SUMIF($BY$7:$BY$206,$CB9,C$7:C$206) -> 978083 | CE9: =SUMIF($BY$7:$BY$206,$CB9,D$7:D$206) -> 8542 | CF9: =SUMIF($BY$7:$BY$206,$CB9,E$7:E$206) -> -2205 | CG9: =SUMIF($BY$7:$BY$206,$CB9,F$7:F$206) -> 121436 | CH9: =SUMIF($BY$7:$BY$206,$CB9,G$7:G$206) -> 6337 | CI9: =SUMIF($BY$7:$BY$206,$CB9,H$7:H$206) -> 13648 | CJ9: =SUMIF($BY$7:$BY$206,$CB9,I$7:I$206) -> 132879 | CK9: =SUMIF($BZ$7:$BZ$206,$CC9,J$7:J$206) -> 107892.9 | CL9: =SUMIF($BY$7:$BY$206,$CB9,K$7:K$206) -> 327817 | CM9: =SUMIF($BY$7:$BY$206,$CB9,L$7:L$206) -> 997947.1 | CN9: =AVERAGEIF($BY$7:$BY$206,$CB9,M$7:M$206) -> 33.509248 | CO9: =AVERAGEIF($BY$7:$BY$206,$CB9,N$7:N$206) -> 39.66408 | CP9: =AVERAGEIF($BY$7:$BY$206,$CB9,O$7:O$206) -> 10.828125 | CQ9: =SUMIF($BY$7:$BY$206,$CB9,P$7:P$206) -> 93679.63 | CR9: =AVERAGEIF($BY$7:$BY$206,$CB9,Q$7:Q$206) -> 60.725 | CS9: =SUMIF($BY$7:$BY$206,$CB9,R$7:R$206) -> 0.004 | CT9: =AVERAGEIF($BY$7:$BY$206,$CB9,S$7:S$206) -> 10.95 | CU9: =SUMIF($BZ$7:$BZ$206,$CC9,T$7:T$206) -> -0.4946709 | CV9: =SUMIF($BY$7:$BY$206,$CB9,U$7:U$206) -> 978083 | CW9: =SUMIF($BY$7:$BY$206,$CB9,V$7:V$206) -> 8542 | CX9: =SUMIF($BY$7:$BY$206,$CB9,W$7:W$206) -> -2205 | CY9: =SUMIF($BY$7:$BY$206,$CB9,X$7:X$206) -> 121436 | CZ9: =SUMIF($BY$7:$BY$206,$CB9,Y$7:Y$206) -> 6337 | DA9: =SUMIF($BY$7:$BY$206,$CB9,Z$7:Z$206) -> 13648 | DB9: =SUMIF($BY$7:$BY$206,$CB9,AA$7:AA$206) -> 132879 | DC9: =SUMIF($BZ$7:$BZ$206,$CC9,AB$7:AB$206) -> 107892.9 | DD9: =SUMIF($BY$7:$BY$206,$CB9,AC$7:AC$206) -> 327817 | DE9: =SUMIF($BY$7:$BY$206,$CB9,AD$7:AD$206) -> 997947.1 | DF9: =AVERAGEIF($BY$7:$BY$206,$CB9,AE$7:AE$206) -> 33.509248 | DG9: =AVERAGEIF($BY$7:$BY$206,$CB9,AF$7:AF$206) -> 39.66408 | DH9: =AVERAGEIF($BY$7:$BY$206,$CB9,AG$7:AG$206) -> 10.828125 | DI9: =SUMIF($BY$7:$BY$206,$CB9,AH$7:AH$206) -> 93679.63 | DJ9: =AVERAGEIF($BY$7:$BY$206,$CB9,AI$7:AI$206) -> 60.725 | DK9: =SUMIF($BY$7:$BY$206,$CB9,AJ$7:AJ$206) -> 0.004 | DL9: =AVERAGEIF($BY$7:$BY$206,$CB9,AK$7:AK$206) -> 10.95 | DM9: =SUMIF($BZ$7:$BZ$206,$CC9,AL$7:AL$206) -> -0.4946709 | DN9: =SUMIF($BY$7:$BY$206,$CB9,AM$7:AM$206) -> 978083 | DO9: =SUMIF($BY$7:$BY$206,$CB9,AN$7:AN$206) -> 8542 | DP9: =SUMIF($BY$7:$BY$206,$CB9,AO$7:AO$206) -> -2205 | DQ9: =SUMIF($BY$7:$BY$206,$CB9,AP$7:AP$206) -> 121436 | DR9: =SUMIF($BY$7:$BY$206,$CB9,AQ$7:AQ$206) -> 6337 | DS9: =SUMIF($BY$7:$BY$206,$CB9,AR$7:AR$206) -> 13648 | DT9: =SUMIF($BY$7:$BY$206,$CB9,AS$7:AS$206) -> 132879 | DU9: =SUMIF($BZ$7:$BZ$206,$CC9,AT$7:AT$206) -> 107892.9 | DV9: =SUMIF($BY$7:$BY$206,$CB9,AU$7:AU$206) -> 327817 | DW9: =SUMIF($BY$7:$BY$206,$CB9,AV$7:AV$206) -> 997947.1 | DX9: =AVERAGEIF($BY$7:$BY$206,$CB9,AW$7:AW$206) -> 33.509248 | DY9: =AVERAGEIF($BY$7:$BY$206,$CB9,AX$7:AX$206) -> 39.66408 | DZ9: =AVERAGEIF($BY$7:$BY$206,$CB9,AY$7:AY$206) -> 10.828125 | EA9: =SUMIF($BY$7:$BY$206,$CB9,AZ$7:AZ$206) -> 93679.63 | EB9: =AVERAGEIF($BY$7:$BY$206,$CB9,BA$7:BA$206) -> 60.725 | EC9: =SUMIF($BY$7:$BY$206,$CB9,BB$7:BB$206) -> 0.004 | ED9: =AVERAGEIF($BY$7:$BY$206,$CB9,BC$7:BC$206) -> 10.95 | EE9: =SUMIF($BZ$7:$BZ$206,$CC9,BD$7:BD$206) -> -0.4946709 | EF9: =SUMIF($BY$7:$BY$206,$CB9,BE$7:BE$206) -> 978083 | EG9: =SUMIF($BY$7:$BY$206,$CB9,BF$7:BF$206) -> 8542 | EH9: =SUMIF($BY$7:$BY$206,$CB9,BG$7:BG$206) -> -2205 | EI9: =SUMIF($BY$7:$BY$206,$CB9,BH$7:BH$206) -> 121436 | EJ9: =SUMIF($BY$7:$BY$206,$CB9,BI$7:BI$206) -> 6337 | EK9: =SUMIF($BY$7:$BY$206,$CB9,BJ$7:BJ$206) -> 13648 | EL9: =SUMIF($BY$7:$BY$206,$CB9,BK$7:BK$206) -> 132879 | EM9: =SUMIF($BZ$7:$BZ$206,$CC9,BL$7:BL$206) -> 107892.9 | EN9: =SUMIF($BY$7:$BY$206,$CB9,BM$7:BM$206) -> 327817 | EO9: =SUMIF($BY$7:$BY$206,$CB9,BN$7:BN$206) -> 997947.1 | EP9: =AVERAGEIF($BY$7:$BY$206,$CB9,BO$7:BO$206) -> 33.509248 | EQ9: =AVERAGEIF($BY$7:$BY$206,$CB9,BP$7:BP$206) -> 39.66408 | ER9: =AVERAGEIF($BY$7:$BY$206,$CB9,BQ$7:BQ$206) -> 10.828125 | ES9: =SUMIF($BY$7:$BY$206,$CB9,BR$7:BR$206) -> 93679.63 | ET9: =AVERAGEIF($BY$7:$BY$206,$CB9,BS$7:BS$206) -> 60.725 | EU9: =SUMIF($BY$7:$BY$206,$CB9,BT$7:BT$206) -> 0.004 | EV9: =AVERAGEIF($BY$7:$BY$206,$CB9,BU$7:BU$206) -> 10.95 | EW9: =SUMIF($BZ$7:$BZ$206,$CC9,BV$7:BV$206) -> -0.4946709
B10: =+B9+1 -> 1983 | C10: {=INDEX(GMWSCEN!$A$2:$HJ$150,MATCH(1,(GMWSCEN!$HI$2:$HI$150=C$3)*(GMWSCEN!$HJ$2:$HJ$150=C$1),0),$B10-1973)} -> 235866 | D10: {=INDEX(GMWSCEN!$A$2:$HJ$150,MATCH(1,(GMWSCEN!$HI$2:$HI$150=D$3)*(GMWSCEN!$HJ$2:$HJ$150=D$1),0),$B10-1973)} -> 1803 | E10: {=INDEX(GMWSCEN!$A$2:$HJ$150,MATCH(1,(GMWSCEN!$HI$2:$HI$150=E$3)*(GMWSCEN!$HJ$2:$HJ$150=E$1),0),$B10-1973)} -> -296 | F10: {=INDEX(GMWSCEN!$A$2:$HJ$150,MATCH(1,(GMWSCEN!$HI$2:$HI$150=F$3)*(GMWSCEN!$HJ$2:$HJ$150=F$1),0),$B10-1973)} -> 24175 | G10: {=INDEX(GMWSCEN!$A$2:$HJ$150,MATCH(1,(GMWSCEN!$HI$2:$HI$150=G$3)*(GMWSCEN!$HJ$2:$HJ$150=G$1),0),$B10-1973)} -> 1507 | H10: {=INDEX(GMWSCEN!$A$2:$HJ$150,MATCH(1,(GMWSCEN!$HI$2:$HI$150=H$3)*(GMWSCEN!$HJ$2:$HJ$150=H$1),0),$B10-1973)} -> 3037 | I10: {=INDEX(GMWSCEN!$A$2:$HJ$150,MATCH(1,(GMWSCEN!$HI$2:$HI$150=I$3)*(GMWSCEN!$HJ$2:$HJ$150=I$1),0),$B10-1973)} -> 26916 | J10: {=INDEX(GMWSCEN!$A$2:$HJ$150,MATCH(1,(GMWSCEN!$HI$2:$HI$150=J$3)*(GMWSCEN!$HJ$2:$HJ$150=J$1),0),$B10-1973)} -> 84954.26 | ... BV10: {=INDEX(GMWSCEN!$A$2:$HJ$150,MATCH(1,(GMWSCEN!$HI$2:$HI$150=BV$3)*(GMWSCEN!$HJ$2:$HJ$150=BV$1),0),$B10-1973)} -> -4.09956 | BY10: 1980 | CB10: =+CB9+1 -> 1983 | CC10: =+CC9+100 -> 198301 | CD10: =SUMIF($BY$7:$BY$206,$CB10,C$7:C$206) -> 1017632 | CE10: =SUMIF($BY$7:$BY$206,$CB10,D$7:D$206) -> 11802 | CF10: =SUMIF($BY$7:$BY$206,$CB10,E$7:E$206) -> -3972 | CG10: =SUMIF($BY$7:$BY$206,$CB10,F$7:F$206) -> 131027 | CH10: =SUMIF($BY$7:$BY$206,$CB10,G$7:G$206) -> 7830 | CI10: =SUMIF($BY$7:$BY$206,$CB10,H$7:H$206) -> 14306 | CJ10: =SUMIF($BY$7:$BY$206,$CB10,I$7:I$206) -> 141361 | CK10: =SUMIF($BZ$7:$BZ$206,$CC10,J$7:J$206) -> 97493.3 | CL10: =SUMIF($BY$7:$BY$206,$CB10,K$7:K$206) -> 357283 | CM10: =SUMIF($BY$7:$BY$206,$CB10,L$7:L$206) -> 1021080 | CN10: =AVERAGEIF($BY$7:$BY$206,$CB10,M$7:M$206) -> 35.104712 | CO10: =AVERAGEIF($BY$7:$BY$206,$CB10,N$7:N$206) -> 41.443295 | CP10: =AVERAGEIF($BY$7:$BY$206,$CB10,O$7:O$206) -> 9.1875 | CQ10: =SUMIF($BY$7:$BY$206,$CB10,P$7:P$206) -> 96720.55 | CR10: =AVERAGEIF($BY$7:$BY$206,$CB10,Q$7:Q$206) -> 63.15 | CS10: =SUMIF($BY$7:$BY$206,$CB10,R$7:R$206) -> 0.004 | CT10: =AVERAGEIF($BY$7:$BY$206,$CB10,S$7:S$206) -> 11.6 | CU10: =SUMIF($BZ$7:$BZ$206,$CC10,T$7:T$206) -> -0.4833221 | CV10: =SUMIF($BY$7:$BY$206,$CB10,U$7:U$206) -> 1017632 | CW10: =SUMIF($BY$7:$BY$206,$CB10,V$7:V$206) -> 11802 | CX10: =SUMIF($BY$7:$BY$206,$CB10,W$7:W$206) -> -3972 | CY10: =SUMIF($BY$7:$BY$206,$CB10,X$7:X$206) -> 131027 | CZ10: =SUMIF($BY$7:$BY$206,$CB10,Y$7:Y$206) -> 7830 | DA10: =SUMIF($BY$7:$BY$206,$CB10,Z$7:Z$206) -> 14306 | DB10: =SUMIF($BY$7:$BY$206,$CB10,AA$7:AA$206) -> 141361 | DC10: =SUMIF($BZ$7:$BZ$206,$CC10,AB$7:AB$206) -> 97493.3 | DD10: =SUMIF($BY$7:$BY$206,$CB10,AC$7:AC$206) -> 357283 | DE10: =SUMIF($BY$7:$BY$206,$CB10,AD$7:AD$206) -> 1021080 | DF10: =AVERAGEIF($BY$7:$BY$206,$CB10,AE$7:AE$206) -> 35.104712 | DG10: =AVERAGEIF($BY$7:$BY$206,$CB10,AF$7:AF$206) -> 41.443295 | DH10: =AVERAGEIF($BY$7:$BY$206,$CB10,AG$7:AG$206) -> 9.1875 | DI10: =SUMIF($BY$7:$BY$206,$CB10,AH$7:AH$206) -> 96720.55 | DJ10: =AVERAGEIF($BY$7:$BY$206,$CB10,AI$7:AI$206) -> 63.15 | DK10: =SUMIF($BY$7:$BY$206,$CB10,AJ$7:AJ$206) -> 0.004 | DL10: =AVERAGEIF($BY$7:$BY$206,$CB10,AK$7:AK$206) -> 11.6 | DM10: =SUMIF($BZ$7:$BZ$206,$CC10,AL$7:AL$206) -> -0.4833221 | DN10: =SUMIF($BY$7:$BY$206,$CB10,AM$7:AM$206) -> 1017632 | DO10: =SUMIF($BY$7:$BY$206,$CB10,AN$7:AN$206) -> 11802 | DP10: =SUMIF($BY$7:$BY$206,$CB10,AO$7:AO$206) -> -3972 | DQ10: =SUMIF($BY$7:$BY$206,$CB10,AP$7:AP$206) -> 131027 | DR10: =SUMIF($BY$7:$BY$206,$CB10,AQ$7:AQ$206) -> 7830 | DS10: =SUMIF($BY$7:$BY$206,$CB10,AR$7:AR$206) -> 14306 | DT10: =SUMIF($BY$7:$BY$206,$CB10,AS$7:AS$206) -> 141361 | DU10: =SUMIF($BZ$7:$BZ$206,$CC10,AT$7:AT$206) -> 97493.3 | DV10: =SUMIF($BY$7:$BY$206,$CB10,AU$7:AU$206) -> 357283 | DW10: =SUMIF($BY$7:$BY$206,$CB10,AV$7:AV$206) -> 1021080 | DX10: =AVERAGEIF($BY$7:$BY$206,$CB10,AW$7:AW$206) -> 35.104712 | DY10: =AVERAGEIF($BY$7:$BY$206,$CB10,AX$7:AX$206) -> 41.443295 | DZ10: =AVERAGEIF($BY$7:$BY$206,$CB10,AY$7:AY$206) -> 9.1875 | EA10: =SUMIF($BY$7:$BY$206,$CB10,AZ$7:AZ$206) -> 96720.55 | EB10: =AVERAGEIF($BY$7:$BY$206,$CB10,BA$7:BA$206) -> 63.15 | EC10: =SUMIF($BY$7:$BY$206,$CB10,BB$7:BB$206) -> 0.004 | ED10: =AVERAGEIF($BY$7:$BY$206,$CB10,BC$7:BC$206) -> 11.6 | EE10: =SUMIF($BZ$7:$BZ$206,$CC10,BD$7:BD$206) -> -0.4833221 | EF10: =SUMIF($BY$7:$BY$206,$CB10,BE$7:BE$206) -> 1017632 | EG10: =SUMIF($BY$7:$BY$206,$CB10,BF$7:BF$206) -> 11802 | EH10: =SUMIF($BY$7:$BY$206,$CB10,BG$7:BG$206) -> -3972 | EI10: =SUMIF($BY$7:$BY$206,$CB10,BH$7:BH$206) -> 131027 | EJ10: =SUMIF($BY$7:$BY$206,$CB10,BI$7:BI$206) -> 7830 | EK10: =SUMIF($BY$7:$BY$206,$CB10,BJ$7:BJ$206) -> 14306 | EL10: =SUMIF($BY$7:$BY$206,$CB10,BK$7:BK$206) -> 141361 | EM10: =SUMIF($BZ$7:$BZ$206,$CC10,BL$7:BL$206) -> 97493.3 | EN10: =SUMIF($BY$7:$BY$206,$CB10,BM$7:BM$206) -> 357283 | EO10: =SUMIF($BY$7:$BY$206,$CB10,BN$7:BN$206) -> 1021080 | EP10: =AVERAGEIF($BY$7:$BY$206,$CB10,BO$7:BO$206) -> 35.104712 | EQ10: =AVERAGEIF($BY$7:$BY$206,$CB10,BP$7:BP$206) -> 41.443295 | ER10: =AVERAGEIF($BY$7:$BY$206,$CB10,BQ$7:BQ$206) -> 9.1875 | ES10: =SUMIF($BY$7:$BY$206,$CB10,BR$7:BR$206) -> 96720.55 | ET10: =AVERAGEIF($BY$7:$BY$206,$CB10,BS$7:BS$206) -> 63.15 | EU10: =SUMIF($BY$7:$BY$206,$CB10,BT$7:BT$206) -> 0.004 | EV10: =AVERAGEIF($BY$7:$BY$206,$CB10,BU$7:BU$206) -> 11.6 | EW10: =SUMIF($BZ$7:$BZ$206,$CC10,BV$7:BV$206) -> -0.4833221
A11: 1981 | B11: =+B10+1 -> 1984 | C11: {=INDEX(GMWSCEN!$A$2:$HJ$150,MATCH(1,(GMWSCEN!$HI$2:$HI$150=C$3)*(GMWSCEN!$HJ$2:$HJ$150=C$1),0),$B11-1973)} -> 235712 | D11: {=INDEX(GMWSCEN!$A$2:$HJ$150,MATCH(1,(GMWSCEN!$HI$2:$HI$150=D$3)*(GMWSCEN!$HJ$2:$HJ$150=D$1),0),$B11-1973)} -> 3170 | E11: {=INDEX(GMWSCEN!$A$2:$HJ$150,MATCH(1,(GMWSCEN!$HI$2:$HI$150=E$3)*(GMWSCEN!$HJ$2:$HJ$150=E$1),0),$B11-1973)} -> -1332 | F11: {=INDEX(GMWSCEN!$A$2:$HJ$150,MATCH(1,(GMWSCEN!$HI$2:$HI$150=F$3)*(GMWSCEN!$HJ$2:$HJ$150=F$1),0),$B11-1973)} -> 26380 | G11: {=INDEX(GMWSCEN!$A$2:$HJ$150,MATCH(1,(GMWSCEN!$HI$2:$HI$150=G$3)*(GMWSCEN!$HJ$2:$HJ$150=G$1),0),$B11-1973)} -> 1838 | H11: {=INDEX(GMWSCEN!$A$2:$HJ$150,MATCH(1,(GMWSCEN!$HI$2:$HI$150=H$3)*(GMWSCEN!$HJ$2:$HJ$150=H$1),0),$B11-1973)} -> 3089 | I11: {=INDEX(GMWSCEN!$A$2:$HJ$150,MATCH(1,(GMWSCEN!$HI$2:$HI$150=I$3)*(GMWSCEN!$HJ$2:$HJ$150=I$1),0),$B11-1973)} -> 28137 | J11: {=INDEX(GMWSCEN!$A$2:$HJ$150,MATCH(1,(GMWSCEN!$HI$2:$HI$150=J$3)*(GMWSCEN!$HJ$2:$HJ$150=J$1),0),$B11-1973)} -> 88342.79 | ... BV11: {=INDEX(GMWSCEN!$A$2:$HJ$150,MATCH(1,(GMWSCEN!$HI$2:$HI$150=BV$3)*(GMWSCEN!$HJ$2:$HJ$150=BV$1),0),$B11-1973)} -> -4.582787 | BY11: 1980 | BZ11: =BY11&"01" -> 198001 | CB11: =+CB10+1 -> 1984 | CC11: =+CC10+100 -> 198401 | CD11: =SUMIF($BY$7:$BY$206,$CB11,C$7:C$206) -> 1037829 | CE11: =SUMIF($BY$7:$BY$206,$CB11,D$7:D$206) -> 12535 | CF11: =SUMIF($BY$7:$BY$206,$CB11,E$7:E$206) -> -5067 | CG11: =SUMIF($BY$7:$BY$206,$CB11,F$7:F$206) -> 141819 | CH11: =SUMIF($BY$7:$BY$206,$CB11,G$7:G$206) -> 7468 | CI11: =SUMIF($BY$7:$BY$206,$CB11,H$7:H$206) -> 14613 | CJ11: =SUMIF($BY$7:$BY$206,$CB11,I$7:I$206) -> 151365 | CK11: =SUMIF($BZ$7:$BZ$206,$CC11,J$7:J$206) -> 100950.3 | CL11: =SUMIF($BY$7:$BY$206,$CB11,K$7:K$206) -> 385669 | CM11: =SUMIF($BY$7:$BY$206,$CB11,L$7:L$206) -> 1055566.9 | CN11: =AVERAGEIF($BY$7:$BY$206,$CB11,M$7:M$206) -> 37.15556 | CO11: =AVERAGEIF($BY$7:$BY$206,$CB11,N$7:N$206) -> 43.26813 | CP11: =AVERAGEIF($BY$7:$BY$206,$CB11,O$7:O$206) -> 10.4375 | CQ11: =SUMIF($BY$7:$BY$206,$CB11,P$7:P$206) -> 100055.73 | CR11: =AVERAGEIF($BY$7:$BY$206,$CB11,Q$7:Q$206) -> 62.575 | CS11: =SUMIF($BY$7:$BY$206,$CB11,R$7:R$206) -> 0.004 | CT11: =AVERAGEIF($BY$7:$BY$206,$CB11,S$7:S$206) -> 11.675 | CU11: =SUMIF($BZ$7:$BZ$206,$CC11,T$7:T$206) -> -0.9504318 | CV11: =SUMIF($BY$7:$BY$206,$CB11,U$7:U$206) -> 1037829 | CW11: =SUMIF($BY$7:$BY$206,$CB11,V$7:V$206) -> 12535 | CX11: =SUMIF($BY$7:$BY$206,$CB11,W$7:W$206) -> -5067 | CY11: =SUMIF($BY$7:$BY$206,$CB11,X$7:X$206) -> 141819 | CZ11: =SUMIF($BY$7:$BY$206,$CB11,Y$7:Y$206) -> 7468 | DA11: =SUMIF($BY$7:$BY$206,$CB11,Z$7:Z$206) -> 14613 | DB11: =SUMIF($BY$7:$BY$206,$CB11,AA$7:AA$206) -> 151365 | DC11: =SUMIF($BZ$7:$BZ$206,$CC11,AB$7:AB$206) -> 100950.3 | DD11: =SUMIF($BY$7:$BY$206,$CB11,AC$7:AC$206) -> 385669 | DE11: =SUMIF($BY$7:$BY$206,$CB11,AD$7:AD$206) -> 1055566.9 | DF11: =AVERAGEIF($BY$7:$BY$206,$CB11,AE$7:AE$206) -> 37.15556 | DG11: =AVERAGEIF($BY$7:$BY$206,$CB11,AF$7:AF$206) -> 43.26813 | DH11: =AVERAGEIF($BY$7:$BY$206,$CB11,AG$7:AG$206) -> 10.4375 | DI11: =SUMIF($BY$7:$BY$206,$CB11,AH$7:AH$206) -> 100055.73 | DJ11: =AVERAGEIF($BY$7:$BY$206,$CB11,AI$7:AI$206) -> 62.575 | DK11: =SUMIF($BY$7:$BY$206,$CB11,AJ$7:AJ$206) -> 0.004 | DL11: =AVERAGEIF($BY$7:$BY$206,$CB11,AK$7:AK$206) -> 11.675 | DM11: =SUMIF($BZ$7:$BZ$206,$CC11,AL$7:AL$206) -> -0.9504318 | DN11: =SUMIF($BY$7:$BY$206,$CB11,AM$7:AM$206) -> 1037829 | DO11: =SUMIF($BY$7:$BY$206,$CB11,AN$7:AN$206) -> 12535 | DP11: =SUMIF($BY$7:$BY$206,$CB11,AO$7:AO$206) -> -5067 | DQ11: =SUMIF($BY$7:$BY$206,$CB11,AP$7:AP$206) -> 141819 | DR11: =SUMIF($BY$7:$BY$206,$CB11,AQ$7:AQ$206) -> 7468 | DS11: =SUMIF($BY$7:$BY$206,$CB11,AR$7:AR$206) -> 14613 | DT11: =SUMIF($BY$7:$BY$206,$CB11,AS$7:AS$206) -> 151365 | DU11: =SUMIF($BZ$7:$BZ$206,$CC11,AT$7:AT$206) -> 100950.3 | DV11: =SUMIF($BY$7:$BY$206,$CB11,AU$7:AU$206) -> 385669 | DW11: =SUMIF($BY$7:$BY$206,$CB11,AV$7:AV$206) -> 1055566.9 | DX11: =AVERAGEIF($BY$7:$BY$206,$CB11,AW$7:AW$206) -> 37.15556 | DY11: =AVERAGEIF($BY$7:$BY$206,$CB11,AX$7:AX$206) -> 43.26813 | DZ11: =AVERAGEIF($BY$7:$BY$206,$CB11,AY$7:AY$206) -> 10.4375 | EA11: =SUMIF($BY$7:$BY$206,$CB11,AZ$7:AZ$206) -> 100055.73 | EB11: =AVERAGEIF($BY$7:$BY$206,$CB11,BA$7:BA$206) -> 62.575 | EC11: =SUMIF($BY$7:$BY$206,$CB11,BB$7:BB$206) -> 0.004 | ED11: =AVERAGEIF($BY$7:$BY$206,$CB11,BC$7:BC$206) -> 11.675 | EE11: =SUMIF($BZ$7:$BZ$206,$CC11,BD$7:BD$206) -> -0.9504318 | EF11: =SUMIF($BY$7:$BY$206,$CB11,BE$7:BE$206) -> 1037829 | EG11: =SUMIF($BY$7:$BY$206,$CB11,BF$7:BF$206) -> 12535 | EH11: =SUMIF($BY$7:$BY$206,$CB11,BG$7:BG$206) -> -5067 | EI11: =SUMIF($BY$7:$BY$206,$CB11,BH$7:BH$206) -> 141819 | EJ11: =SUMIF($BY$7:$BY$206,$CB11,BI$7:BI$206) -> 7468 | EK11: =SUMIF($BY$7:$BY$206,$CB11,BJ$7:BJ$206) -> 14613 | EL11: =SUMIF($BY$7:$BY$206,$CB11,BK$7:BK$206) -> 151365 | EM11: =SUMIF($BZ$7:$BZ$206,$CC11,BL$7:BL$206) -> 100950.3 | EN11: =SUMIF($BY$7:$BY$206,$CB11,BM$7:BM$206) -> 385669 | EO11: =SUMIF($BY$7:$BY$206,$CB11,BN$7:BN$206) -> 1055566.9 | EP11: =AVERAGEIF($BY$7:$BY$206,$CB11,BO$7:BO$206) -> 37.15556 | EQ11: =AVERAGEIF($BY$7:$BY$206,$CB11,BP$7:BP$206) -> 43.26813 | ER11: =AVERAGEIF($BY$7:$BY$206,$CB11,BQ$7:BQ$206) -> 10.4375 | ES11: =SUMIF($BY$7:$BY$206,$CB11,BR$7:BR$206) -> 100055.73 | ET11: =AVERAGEIF($BY$7:$BY$206,$CB11,BS$7:BS$206) -> 62.575 | EU11: =SUMIF($BY$7:$BY$206,$CB11,BT$7:BT$206) -> 0.004 | EV11: =AVERAGEIF($BY$7:$BY$206,$CB11,BU$7:BU$206) -> 11.675 | EW11: =SUMIF($BZ$7:$BZ$206,$CC11,BV$7:BV$206) -> -0.9504318
B12: =+B11+1 -> 1985 | C12: {=INDEX(GMWSCEN!$A$2:$HJ$150,MATCH(1,(GMWSCEN!$HI$2:$HI$150=C$3)*(GMWSCEN!$HJ$2:$HJ$150=C$1),0),$B12-1973)} -> 236272 | D12: {=INDEX(GMWSCEN!$A$2:$HJ$150,MATCH(1,(GMWSCEN!$HI$2:$HI$150=D$3)*(GMWSCEN!$HJ$2:$HJ$150=D$1),0),$B12-1973)} -> 3679 | E12: {=INDEX(GMWSCEN!$A$2:$HJ$150,MATCH(1,(GMWSCEN!$HI$2:$HI$150=E$3)*(GMWSCEN!$HJ$2:$HJ$150=E$1),0),$B12-1973)} -> -2964 | F12: {=INDEX(GMWSCEN!$A$2:$HJ$150,MATCH(1,(GMWSCEN!$HI$2:$HI$150=F$3)*(GMWSCEN!$HJ$2:$HJ$150=F$1),0),$B12-1973)} -> 26203 | G12: {=INDEX(GMWSCEN!$A$2:$HJ$150,MATCH(1,(GMWSCEN!$HI$2:$HI$150=G$3)*(GMWSCEN!$HJ$2:$HJ$150=G$1),0),$B12-1973)} -> 715 | H12: {=INDEX(GMWSCEN!$A$2:$HJ$150,MATCH(1,(GMWSCEN!$HI$2:$HI$150=H$3)*(GMWSCEN!$HJ$2:$HJ$150=H$1),0),$B12-1973)} -> 3163 | I12: {=INDEX(GMWSCEN!$A$2:$HJ$150,MATCH(1,(GMWSCEN!$HI$2:$HI$150=I$3)*(GMWSCEN!$HJ$2:$HJ$150=I$1),0),$B12-1973)} -> 26402 | J12: {=INDEX(GMWSCEN!$A$2:$HJ$150,MATCH(1,(GMWSCEN!$HI$2:$HI$150=J$3)*(GMWSCEN!$HJ$2:$HJ$150=J$1),0),$B12-1973)} -> 91718.73 | ... BV12: {=INDEX(GMWSCEN!$A$2:$HJ$150,MATCH(1,(GMWSCEN!$HI$2:$HI$150=BV$3)*(GMWSCEN!$HJ$2:$HJ$150=BV$1),0),$B12-1973)} -> -4.6422 | BY12: =+BY8+1 -> 1981 | CB12: =+CB11+1 -> 1985 | CC12: =+CC11+100 -> 198501 | CD12: =SUMIF($BY$7:$BY$206,$CB12,C$7:C$206) -> 1082140 | CE12: =SUMIF($BY$7:$BY$206,$CB12,D$7:D$206) -> 9034 | CF12: =SUMIF($BY$7:$BY$206,$CB12,E$7:E$206) -> -2703 | CG12: =SUMIF($BY$7:$BY$206,$CB12,F$7:F$206) -> 150561 | CH12: =SUMIF($BY$7:$BY$206,$CB12,G$7:G$206) -> 6331 | CI12: =SUMIF($BY$7:$BY$206,$CB12,H$7:H$206) -> 14387 | CJ12: =SUMIF($BY$7:$BY$206,$CB12,I$7:I$206) -> 162245 | CK12: =SUMIF($BZ$7:$BZ$206,$CC12,J$7:J$206) -> 111237.2 | CL12: =SUMIF($BY$7:$BY$206,$CB12,K$7:K$206) -> 423971 | CM12: =SUMIF($BY$7:$BY$206,$CB12,L$7:L$206) -> 1083936 | CN12: =AVERAGEIF($BY$7:$BY$206,$CB12,M$7:M$206) -> 39.176993 | CO12: =AVERAGEIF($BY$7:$BY$206,$CB12,N$7:N$206) -> 45.31455 | CP12: =AVERAGEIF($BY$7:$BY$206,$CB12,O$7:O$206) -> 11.625 | CQ12: =SUMIF($BY$7:$BY$206,$CB12,P$7:P$206) -> 102017.61 | CR12: =AVERAGEIF($BY$7:$BY$206,$CB12,Q$7:Q$206) -> 66.375 | CS12: =SUMIF($BY$7:$BY$206,$CB12,R$7:R$206) -> 0.004 | CT12: =AVERAGEIF($BY$7:$BY$206,$CB12,S$7:S$206) -> 11.325 | CU12: =SUMIF($BZ$7:$BZ$206,$CC12,T$7:T$206) -> -0.3285408 | CV12: =SUMIF($BY$7:$BY$206,$CB12,U$7:U$206) -> 1082140 | CW12: =SUMIF($BY$7:$BY$206,$CB12,V$7:V$206) -> 9034 | CX12: =SUMIF($BY$7:$BY$206,$CB12,W$7:W$206) -> -2703 | CY12: =SUMIF($BY$7:$BY$206,$CB12,X$7:X$206) -> 150561 | CZ12: =SUMIF($BY$7:$BY$206,$CB12,Y$7:Y$206) -> 6331 | DA12: =SUMIF($BY$7:$BY$206,$CB12,Z$7:Z$206) -> 14387 | DB12: =SUMIF($BY$7:$BY$206,$CB12,AA$7:AA$206) -> 162245 | DC12: =SUMIF($BZ$7:$BZ$206,$CC12,AB$7:AB$206) -> 111237.2 | DD12: =SUMIF($BY$7:$BY$206,$CB12,AC$7:AC$206) -> 423971 | DE12: =SUMIF($BY$7:$BY$206,$CB12,AD$7:AD$206) -> 1083936 | DF12: =AVERAGEIF($BY$7:$BY$206,$CB12,AE$7:AE$206) -> 39.176993 | DG12: =AVERAGEIF($BY$7:$BY$206,$CB12,AF$7:AF$206) -> 45.31455 | DH12: =AVERAGEIF($BY$7:$BY$206,$CB12,AG$7:AG$206) -> 11.625 | DI12: =SUMIF($BY$7:$BY$206,$CB12,AH$7:AH$206) -> 102017.61 | DJ12: =AVERAGEIF($BY$7:$BY$206,$CB12,AI$7:AI$206) -> 66.375 | DK12: =SUMIF($BY$7:$BY$206,$CB12,AJ$7:AJ$206) -> 0.004 | DL12: =AVERAGEIF($BY$7:$BY$206,$CB12,AK$7:AK$206) -> 11.325 | DM12: =SUMIF($BZ$7:$BZ$206,$CC12,AL$7:AL$206) -> -0.3285408 | DN12: =SUMIF($BY$7:$BY$206,$CB12,AM$7:AM$206) -> 1082140 | DO12: =SUMIF($BY$7:$BY$206,$CB12,AN$7:AN$206) -> 9034 | DP12: =SUMIF($BY$7:$BY$206,$CB12,AO$7:AO$206) -> -2703 | DQ12: =SUMIF($BY$7:$BY$206,$CB12,AP$7:AP$206) -> 150561 | DR12: =SUMIF($BY$7:$BY$206,$CB12,AQ$7:AQ$206) -> 6331 | DS12: =SUMIF($BY$7:$BY$206,$CB12,AR$7:AR$206) -> 14387 | DT12: =SUMIF($BY$7:$BY$206,$CB12,AS$7:AS$206) -> 162245 | DU12: =SUMIF($BZ$7:$BZ$206,$CC12,AT$7:AT$206) -> 111237.2 | DV12: =SUMIF($BY$7:$BY$206,$CB12,AU$7:AU$206) -> 423971 | DW12: =SUMIF($BY$7:$BY$206,$CB12,AV$7:AV$206) -> 1083936 | DX12: =AVERAGEIF($BY$7:$BY$206,$CB12,AW$7:AW$206) -> 39.176993 | DY12: =AVERAGEIF($BY$7:$BY$206,$CB12,AX$7:AX$206) -> 45.31455 | DZ12: =AVERAGEIF($BY$7:$BY$206,$CB12,AY$7:AY$206) -> 11.625 | EA12: =SUMIF($BY$7:$BY$206,$CB12,AZ$7:AZ$206) -> 102017.61 | EB12: =AVERAGEIF($BY$7:$BY$206,$CB12,BA$7:BA$206) -> 66.375 | EC12: =SUMIF($BY$7:$BY$206,$CB12,BB$7:BB$206) -> 0.004 | ED12: =AVERAGEIF($BY$7:$BY$206,$CB12,BC$7:BC$206) -> 11.325 | EE12: =SUMIF($BZ$7:$BZ$206,$CC12,BD$7:BD$206) -> -0.3285408 | EF12: =SUMIF($BY$7:$BY$206,$CB12,BE$7:BE$206) -> 1082140 | EG12: =SUMIF($BY$7:$BY$206,$CB12,BF$7:BF$206) -> 9034 | EH12: =SUMIF($BY$7:$BY$206,$CB12,BG$7:BG$206) -> -2703 | EI12: =SUMIF($BY$7:$BY$206,$CB12,BH$7:BH$206) -> 150561 | EJ12: =SUMIF($BY$7:$BY$206,$CB12,BI$7:BI$206) -> 6331 | EK12: =SUMIF($BY$7:$BY$206,$CB12,BJ$7:BJ$206) -> 14387 | EL12: =SUMIF($BY$7:$BY$206,$CB12,BK$7:BK$206) -> 162245 | EM12: =SUMIF($BZ$7:$BZ$206,$CC12,BL$7:BL$206) -> 111237.2 | EN12: =SUMIF($BY$7:$BY$206,$CB12,BM$7:BM$206) -> 423971 | EO12: =SUMIF($BY$7:$BY$206,$CB12,BN$7:BN$206) -> 1083936 | EP12: =AVERAGEIF($BY$7:$BY$206,$CB12,BO$7:BO$206) -> 39.176993 | EQ12: =AVERAGEIF($BY$7:$BY$206,$CB12,BP$7:BP$206) -> 45.31455 | ER12: =AVERAGEIF($BY$7:$BY$206,$CB12,BQ$7:BQ$206) -> 11.625 | ES12: =SUMIF($BY$7:$BY$206,$CB12,BR$7:BR$206) -> 102017.61 | ET12: =AVERAGEIF($BY$7:$BY$206,$CB12,BS$7:BS$206) -> 66.375 | EU12: =SUMIF($BY$7:$BY$206,$CB12,BT$7:BT$206) -> 0.004 | EV12: =AVERAGEIF($BY$7:$BY$206,$CB12,BU$7:BU$206) -> 11.325 | EW12: =SUMIF($BZ$7:$BZ$206,$CC12,BV$7:BV$206) -> -0.3285408
B13: =+B12+1 -> 1986 | C13: {=INDEX(GMWSCEN!$A$2:$HJ$150,MATCH(1,(GMWSCEN!$HI$2:$HI$150=C$3)*(GMWSCEN!$HJ$2:$HJ$150=C$1),0),$B13-1973)} -> 238846 | D13: {=INDEX(GMWSCEN!$A$2:$HJ$150,MATCH(1,(GMWSCEN!$HI$2:$HI$150=D$3)*(GMWSCEN!$HJ$2:$HJ$150=D$1),0),$B13-1973)} -> 2967 | E13: {=INDEX(GMWSCEN!$A$2:$HJ$150,MATCH(1,(GMWSCEN!$HI$2:$HI$150=E$3)*(GMWSCEN!$HJ$2:$HJ$150=E$1),0),$B13-1973)} -> -1973 | F13: {=INDEX(GMWSCEN!$A$2:$HJ$150,MATCH(1,(GMWSCEN!$HI$2:$HI$150=F$3)*(GMWSCEN!$HJ$2:$HJ$150=F$1),0),$B13-1973)} -> 27949 | G13: {=INDEX(GMWSCEN!$A$2:$HJ$150,MATCH(1,(GMWSCEN!$HI$2:$HI$150=G$3)*(GMWSCEN!$HJ$2:$HJ$150=G$1),0),$B13-1973)} -> 994 | H13: {=INDEX(GMWSCEN!$A$2:$HJ$150,MATCH(1,(GMWSCEN!$HI$2:$HI$150=H$3)*(GMWSCEN!$HJ$2:$HJ$150=H$1),0),$B13-1973)} -> 3223 | I13: {=INDEX(GMWSCEN!$A$2:$HJ$150,MATCH(1,(GMWSCEN!$HI$2:$HI$150=I$3)*(GMWSCEN!$HJ$2:$HJ$150=I$1),0),$B13-1973)} -> 29199 | J13: {=INDEX(GMWSCEN!$A$2:$HJ$150,MATCH(1,(GMWSCEN!$HI$2:$HI$150=J$3)*(GMWSCEN!$HJ$2:$HJ$150=J$1),0),$B13-1973)} -> 94133.53 | ... BV13: {=INDEX(GMWSCEN!$A$2:$HJ$150,MATCH(1,(GMWSCEN!$HI$2:$HI$150=BV$3)*(GMWSCEN!$HJ$2:$HJ$150=BV$1),0),$B13-1973)} -> -3.693104 | BY13: =+BY9+1 -> 1981 | CB13: =+CB12+1 -> 1986 | CC13: =+CC12+100 -> 198601 | CD13: =SUMIF($BY$7:$BY$206,$CB13,C$7:C$206) -> 1118364 | CE13: =SUMIF($BY$7:$BY$206,$CB13,D$7:D$206) -> 8482 | CF13: =SUMIF($BY$7:$BY$206,$CB13,E$7:E$206) -> -4493 | CG13: =SUMIF($BY$7:$BY$206,$CB13,F$7:F$206) -> 158890 | CH13: =SUMIF($BY$7:$BY$206,$CB13,G$7:G$206) -> 4247 | CI13: =SUMIF($BY$7:$BY$206,$CB13,H$7:H$206) -> 15860 | CJ13: =SUMIF($BY$7:$BY$206,$CB13,I$7:I$206) -> 170257 | CK13: =SUMIF($BZ$7:$BZ$206,$CC13,J$7:J$206) -> 118539.7 | CL13: =SUMIF($BY$7:$BY$206,$CB13,K$7:K$206) -> 455983 | CM13: =SUMIF($BY$7:$BY$206,$CB13,L$7:L$206) -> 1111237.2 | CN13: =AVERAGEIF($BY$7:$BY$206,$CB13,M$7:M$206) -> 40.764628 | CO13: =AVERAGEIF($BY$7:$BY$206,$CB13,N$7:N$206) -> 46.761385 | CP13: =AVERAGEIF($BY$7:$BY$206,$CB13,O$7:O$206) -> 10.125 | CQ13: =SUMIF($BY$7:$BY$206,$CB13,P$7:P$206) -> 104175.67 | CR13: =AVERAGEIF($BY$7:$BY$206,$CB13,Q$7:Q$206) -> 68.175 | CS13: =SUMIF($BY$7:$BY$206,$CB13,R$7:R$206) -> 0.004 | CT13: =AVERAGEIF($BY$7:$BY$206,$CB13,S$7:S$206) -> 11.275 | CU13: =SUMIF($BZ$7:$BZ$206,$CC13,T$7:T$206) -> 1.349545 | CV13: =SUMIF($BY$7:$BY$206,$CB13,U$7:U$206) -> 1118364 | CW13: =SUMIF($BY$7:$BY$206,$CB13,V$7:V$206) -> 8482 | CX13: =SUMIF($BY$7:$BY$206,$CB13,W$7:W$206) -> -4493 | CY13: =SUMIF($BY$7:$BY$206,$CB13,X$7:X$206) -> 158890 | CZ13: =SUMIF($BY$7:$BY$206,$CB13,Y$7:Y$206) -> 4247 | DA13: =SUMIF($BY$7:$BY$206,$CB13,Z$7:Z$206) -> 15860 | DB13: =SUMIF($BY$7:$BY$206,$CB13,AA$7:AA$206) -> 170257 | DC13: =SUMIF($BZ$7:$BZ$206,$CC13,AB$7:AB$206) -> 118539.7 | DD13: =SUMIF($BY$7:$BY$206,$CB13,AC$7:AC$206) -> 455983 | DE13: =SUMIF($BY$7:$BY$206,$CB13,AD$7:AD$206) -> 1111237.2 | DF13: =AVERAGEIF($BY$7:$BY$206,$CB13,AE$7:AE$206) -> 40.764628 | DG13: =AVERAGEIF($BY$7:$BY$206,$CB13,AF$7:AF$206) -> 46.761385 | DH13: =AVERAGEIF($BY$7:$BY$206,$CB13,AG$7:AG$206) -> 10.125 | DI13: =SUMIF($BY$7:$BY$206,$CB13,AH$7:AH$206) -> 104175.67 | DJ13: =AVERAGEIF($BY$7:$BY$206,$CB13,AI$7:AI$206) -> 68.175 | DK13: =SUMIF($BY$7:$BY$206,$CB13,AJ$7:AJ$206) -> 0.004 | DL13: =AVERAGEIF($BY$7:$BY$206,$CB13,AK$7:AK$206) -> 11.275 | DM13: =SUMIF($BZ$7:$BZ$206,$CC13,AL$7:AL$206) -> 1.349545 | DN13: =SUMIF($BY$7:$BY$206,$CB13,AM$7:AM$206) -> 1118364 | DO13: =SUMIF($BY$7:$BY$206,$CB13,AN$7:AN$206) -> 8482 | DP13: =SUMIF($BY$7:$BY$206,$CB13,AO$7:AO$206) -> -4493 | DQ13: =SUMIF($BY$7:$BY$206,$CB13,AP$7:AP$206) -> 158890 | DR13: =SUMIF($BY$7:$BY$206,$CB13,AQ$7:AQ$206) -> 4247 | DS13: =SUMIF($BY$7:$BY$206,$CB13,AR$7:AR$206) -> 15860 | DT13: =SUMIF($BY$7:$BY$206,$CB13,AS$7:AS$206) -> 170257 | DU13: =SUMIF($BZ$7:$BZ$206,$CC13,AT$7:AT$206) -> 118539.7 | DV13: =SUMIF($BY$7:$BY$206,$CB13,AU$7:AU$206) -> 455983 | DW13: =SUMIF($BY$7:$BY$206,$CB13,AV$7:AV$206) -> 1111237.2 | DX13: =AVERAGEIF($BY$7:$BY$206,$CB13,AW$7:AW$206) -> 40.764628 | DY13: =AVERAGEIF($BY$7:$BY$206,$CB13,AX$7:AX$206) -> 46.761385 | DZ13: =AVERAGEIF($BY$7:$BY$206,$CB13,AY$7:AY$206) -> 10.125 | EA13: =SUMIF($BY$7:$BY$206,$CB13,AZ$7:AZ$206) -> 104175.67 | EB13: =AVERAGEIF($BY$7:$BY$206,$CB13,BA$7:BA$206) -> 68.175 | EC13: =SUMIF($BY$7:$BY$206,$CB13,BB$7:BB$206) -> 0.004 | ED13: =AVERAGEIF($BY$7:$BY$206,$CB13,BC$7:BC$206) -> 11.275 | EE13: =SUMIF($BZ$7:$BZ$206,$CC13,BD$7:BD$206) -> 1.349545 | EF13: =SUMIF($BY$7:$BY$206,$CB13,BE$7:BE$206) -> 1118364 | EG13: =SUMIF($BY$7:$BY$206,$CB13,BF$7:BF$206) -> 8482 | EH13: =SUMIF($BY$7:$BY$206,$CB13,BG$7:BG$206) -> -4493 | EI13: =SUMIF($BY$7:$BY$206,$CB13,BH$7:BH$206) -> 158890 | EJ13: =SUMIF($BY$7:$BY$206,$CB13,BI$7:BI$206) -> 4247 | EK13: =SUMIF($BY$7:$BY$206,$CB13,BJ$7:BJ$206) -> 15860 | EL13: =SUMIF($BY$7:$BY$206,$CB13,BK$7:BK$206) -> 170257 | EM13: =SUMIF($BZ$7:$BZ$206,$CC13,BL$7:BL$206) -> 118539.7 | EN13: =SUMIF($BY$7:$BY$206,$CB13,BM$7:BM$206) -> 455983 | EO13: =SUMIF($BY$7:$BY$206,$CB13,BN$7:BN$206) -> 1111237.2 | EP13: =AVERAGEIF($BY$7:$BY$206,$CB13,BO$7:BO$206) -> 40.764628 | EQ13: =AVERAGEIF($BY$7:$BY$206,$CB13,BP$7:BP$206) -> 46.761385 | ER13: =AVERAGEIF($BY$7:$BY$206,$CB13,BQ$7:BQ$206) -> 10.125 | ES13: =SUMIF($BY$7:$BY$206,$CB13,BR$7:BR$206) -> 104175.67 | ET13: =AVERAGEIF($BY$7:$BY$206,$CB13,BS$7:BS$206) -> 68.175 | EU13: =SUMIF($BY$7:$BY$206,$CB13,BT$7:BT$206) -> 0.004 | EV13: =AVERAGEIF($BY$7:$BY$206,$CB13,BU$7:BU$206) -> 11.275 | EW13: =SUMIF($BZ$7:$BZ$206,$CC13,BV$7:BV$206) -> 1.349545
B14: =+B13+1 -> 1987 | C14: {=INDEX(GMWSCEN!$A$2:$HJ$150,MATCH(1,(GMWSCEN!$HI$2:$HI$150=C$3)*(GMWSCEN!$HJ$2:$HJ$150=C$1),0),$B14-1973)} -> 239131 | D14: {=INDEX(GMWSCEN!$A$2:$HJ$150,MATCH(1,(GMWSCEN!$HI$2:$HI$150=D$3)*(GMWSCEN!$HJ$2:$HJ$150=D$1),0),$B14-1973)} -> -990.9999 | E14: {=INDEX(GMWSCEN!$A$2:$HJ$150,MATCH(1,(GMWSCEN!$HI$2:$HI$150=E$3)*(GMWSCEN!$HJ$2:$HJ$150=E$1),0),$B14-1973)} -> 1855 | F14: {=INDEX(GMWSCEN!$A$2:$HJ$150,MATCH(1,(GMWSCEN!$HI$2:$HI$150=F$3)*(GMWSCEN!$HJ$2:$HJ$150=F$1),0),$B14-1973)} -> 26934 | G14: {=INDEX(GMWSCEN!$A$2:$HJ$150,MATCH(1,(GMWSCEN!$HI$2:$HI$150=G$3)*(GMWSCEN!$HJ$2:$HJ$150=G$1),0),$B14-1973)} -> 864 | H14: {=INDEX(GMWSCEN!$A$2:$HJ$150,MATCH(1,(GMWSCEN!$HI$2:$HI$150=H$3)*(GMWSCEN!$HJ$2:$HJ$150=H$1),0),$B14-1973)} -> 3274 | I14: {=INDEX(GMWSCEN!$A$2:$HJ$150,MATCH(1,(GMWSCEN!$HI$2:$HI$150=I$3)*(GMWSCEN!$HJ$2:$HJ$150=I$1),0),$B14-1973)} -> 32063 | J14: {=INDEX(GMWSCEN!$A$2:$HJ$150,MATCH(1,(GMWSCEN!$HI$2:$HI$150=J$3)*(GMWSCEN!$HJ$2:$HJ$150=J$1),0),$B14-1973)} -> 95587.21 | ... BV14: {=INDEX(GMWSCEN!$A$2:$HJ$150,MATCH(1,(GMWSCEN!$HI$2:$HI$150=BV$3)*(GMWSCEN!$HJ$2:$HJ$150=BV$1),0),$B14-1973)} -> -3.648186 | BY14: =+BY10+1 -> 1981 | CB14: =+CB13+1 -> 1987 | CC14: =+CC13+100 -> 198701 | CD14: =SUMIF($BY$7:$BY$206,$CB14,C$7:C$206) -> 1186431 | CE14: =SUMIF($BY$7:$BY$206,$CB14,D$7:D$206) -> 5074 | CF14: =SUMIF($BY$7:$BY$206,$CB14,E$7:E$206) -> -3577 | CG14: =SUMIF($BY$7:$BY$206,$CB14,F$7:F$206) -> 170159 | CH14: =SUMIF($BY$7:$BY$206,$CB14,G$7:G$206) -> 1497 | CI14: =SUMIF($BY$7:$BY$206,$CB14,H$7:H$206) -> 18486 | CJ14: =SUMIF($BY$7:$BY$206,$CB14,I$7:I$206) -> 185068 | CK14: =SUMIF($BZ$7:$BZ$206,$CC14,J$7:J$206) -> 111566.4 | CL14: =SUMIF($BY$7:$BY$206,$CB14,K$7:K$206) -> 511956 | CM14: =SUMIF($BY$7:$BY$206,$CB14,L$7:L$206) -> 1144975.6 | CN14: =AVERAGEIF($BY$7:$BY$206,$CB14,M$7:M$206) -> 43.13937 | CO14: =AVERAGEIF($BY$7:$BY$206,$CB14,N$7:N$206) -> 48.182147 | CP14: =AVERAGEIF($BY$7:$BY$206,$CB14,O$7:O$206) -> 8.875 | CQ14: =SUMIF($BY$7:$BY$206,$CB14,P$7:P$206) -> 110257.49 | CR14: =AVERAGEIF($BY$7:$BY$206,$CB14,Q$7:Q$206) -> 71.125 | CS14: =SUMIF($BY$7:$BY$206,$CB14,R$7:R$206) -> 0.004 | CT14: =AVERAGEIF($BY$7:$BY$206,$CB14,S$7:S$206) -> 9.95 | CU14: =SUMIF($BZ$7:$BZ$206,$CC14,T$7:T$206) -> 4.596519 | CV14: =SUMIF($BY$7:$BY$206,$CB14,U$7:U$206) -> 1186431 | CW14: =SUMIF($BY$7:$BY$206,$CB14,V$7:V$206) -> 5074 | CX14: =SUMIF($BY$7:$BY$206,$CB14,W$7:W$206) -> -3577 | CY14: =SUMIF($BY$7:$BY$206,$CB14,X$7:X$206) -> 170159 | CZ14: =SUMIF($BY$7:$BY$206,$CB14,Y$7:Y$206) -> 1497 | DA14: =SUMIF($BY$7:$BY$206,$CB14,Z$7:Z$206) -> 18486 | DB14: =SUMIF($BY$7:$BY$206,$CB14,AA$7:AA$206) -> 185068 | DC14: =SUMIF($BZ$7:$BZ$206,$CC14,AB$7:AB$206) -> 111566.4 | DD14: =SUMIF($BY$7:$BY$206,$CB14,AC$7:AC$206) -> 511956 | DE14: =SUMIF($BY$7:$BY$206,$CB14,AD$7:AD$206) -> 1144975.6 | DF14: =AVERAGEIF($BY$7:$BY$206,$CB14,AE$7:AE$206) -> 43.13937 | DG14: =AVERAGEIF($BY$7:$BY$206,$CB14,AF$7:AF$206) -> 48.182147 | DH14: =AVERAGEIF($BY$7:$BY$206,$CB14,AG$7:AG$206) -> 8.875 | DI14: =SUMIF($BY$7:$BY$206,$CB14,AH$7:AH$206) -> 110257.49 | DJ14: =AVERAGEIF($BY$7:$BY$206,$CB14,AI$7:AI$206) -> 71.125 | DK14: =SUMIF($BY$7:$BY$206,$CB14,AJ$7:AJ$206) -> 0.004 | DL14: =AVERAGEIF($BY$7:$BY$206,$CB14,AK$7:AK$206) -> 9.95 | DM14: =SUMIF($BZ$7:$BZ$206,$CC14,AL$7:AL$206) -> 4.596519 | DN14: =SUMIF($BY$7:$BY$206,$CB14,AM$7:AM$206) -> 1186431 | DO14: =SUMIF($BY$7:$BY$206,$CB14,AN$7:AN$206) -> 5074 | DP14: =SUMIF($BY$7:$BY$206,$CB14,AO$7:AO$206) -> -3577 | DQ14: =SUMIF($BY$7:$BY$206,$CB14,AP$7:AP$206) -> 170159 | DR14: =SUMIF($BY$7:$BY$206,$CB14,AQ$7:AQ$206) -> 1497 | DS14: =SUMIF($BY$7:$BY$206,$CB14,AR$7:AR$206) -> 18486 | DT14: =SUMIF($BY$7:$BY$206,$CB14,AS$7:AS$206) -> 185068 | DU14: =SUMIF($BZ$7:$BZ$206,$CC14,AT$7:AT$206) -> 111566.4 | DV14: =SUMIF($BY$7:$BY$206,$CB14,AU$7:AU$206) -> 511956 | DW14: =SUMIF($BY$7:$BY$206,$CB14,AV$7:AV$206) -> 1144975.6 | DX14: =AVERAGEIF($BY$7:$BY$206,$CB14,AW$7:AW$206) -> 43.13937 | DY14: =AVERAGEIF($BY$7:$BY$206,$CB14,AX$7:AX$206) -> 48.182147 | DZ14: =AVERAGEIF($BY$7:$BY$206,$CB14,AY$7:AY$206) -> 8.875 | EA14: =SUMIF($BY$7:$BY$206,$CB14,AZ$7:AZ$206) -> 110257.49 | EB14: =AVERAGEIF($BY$7:$BY$206,$CB14,BA$7:BA$206) -> 71.125 | EC14: =SUMIF($BY$7:$BY$206,$CB14,BB$7:BB$206) -> 0.004 | ED14: =AVERAGEIF($BY$7:$BY$206,$CB14,BC$7:BC$206) -> 9.95 | EE14: =SUMIF($BZ$7:$BZ$206,$CC14,BD$7:BD$206) -> 4.596519 | EF14: =SUMIF($BY$7:$BY$206,$CB14,BE$7:BE$206) -> 1186431 | EG14: =SUMIF($BY$7:$BY$206,$CB14,BF$7:BF$206) -> 5074 | EH14: =SUMIF($BY$7:$BY$206,$CB14,BG$7:BG$206) -> -3577 | EI14: =SUMIF($BY$7:$BY$206,$CB14,BH$7:BH$206) -> 170159 | EJ14: =SUMIF($BY$7:$BY$206,$CB14,BI$7:BI$206) -> 1497 | EK14: =SUMIF($BY$7:$BY$206,$CB14,BJ$7:BJ$206) -> 18486 | EL14: =SUMIF($BY$7:$BY$206,$CB14,BK$7:BK$206) -> 185068 | EM14: =SUMIF($BZ$7:$BZ$206,$CC14,BL$7:BL$206) -> 111566.4 | EN14: =SUMIF($BY$7:$BY$206,$CB14,BM$7:BM$206) -> 511956 | EO14: =SUMIF($BY$7:$BY$206,$CB14,BN$7:BN$206) -> 1144975.6 | EP14: =AVERAGEIF($BY$7:$BY$206,$CB14,BO$7:BO$206) -> 43.13937 | EQ14: =AVERAGEIF($BY$7:$BY$206,$CB14,BP$7:BP$206) -> 48.182147 | ER14: =AVERAGEIF($BY$7:$BY$206,$CB14,BQ$7:BQ$206) -> 8.875 | ES14: =SUMIF($BY$7:$BY$206,$CB14,BR$7:BR$206) -> 110257.49 | ET14: =AVERAGEIF($BY$7:$BY$206,$CB14,BS$7:BS$206) -> 71.125 | EU14: =SUMIF($BY$7:$BY$206,$CB14,BT$7:BT$206) -> 0.004 | EV14: =AVERAGEIF($BY$7:$BY$206,$CB14,BU$7:BU$206) -> 9.95 | EW14: =SUMIF($BZ$7:$BZ$206,$CC14,BV$7:BV$206) -> 4.596519
A15: 1982 | B15: =+B14+1 -> 1988 | C15: {=INDEX(GMWSCEN!$A$2:$HJ$150,MATCH(1,(GMWSCEN!$HI$2:$HI$150=C$3)*(GMWSCEN!$HJ$2:$HJ$150=C$1),0),$B15-1973)} -> 239578 | D15: {=INDEX(GMWSCEN!$A$2:$HJ$150,MATCH(1,(GMWSCEN!$HI$2:$HI$150=D$3)*(GMWSCEN!$HJ$2:$HJ$150=D$1),0),$B15-1973)} -> 344 | E15: {=INDEX(GMWSCEN!$A$2:$HJ$150,MATCH(1,(GMWSCEN!$HI$2:$HI$150=E$3)*(GMWSCEN!$HJ$2:$HJ$150=E$1),0),$B15-1973)} -> 1451 | F15: {=INDEX(GMWSCEN!$A$2:$HJ$150,MATCH(1,(GMWSCEN!$HI$2:$HI$150=F$3)*(GMWSCEN!$HJ$2:$HJ$150=F$1),0),$B15-1973)} -> 29501 | G15: {=INDEX(GMWSCEN!$A$2:$HJ$150,MATCH(1,(GMWSCEN!$HI$2:$HI$150=G$3)*(GMWSCEN!$HJ$2:$HJ$150=G$1),0),$B15-1973)} -> 1795 | H15: {=INDEX(GMWSCEN!$A$2:$HJ$150,MATCH(1,(GMWSCEN!$HI$2:$HI$150=H$3)*(GMWSCEN!$HJ$2:$HJ$150=H$1),0),$B15-1973)} -> 3306 | I15: {=INDEX(GMWSCEN!$A$2:$HJ$150,MATCH(1,(GMWSCEN!$HI$2:$HI$150=I$3)*(GMWSCEN!$HJ$2:$HJ$150=I$1),0),$B15-1973)} -> 34258 | J15: {=INDEX(GMWSCEN!$A$2:$HJ$150,MATCH(1,(GMWSCEN!$HI$2:$HI$150=J$3)*(GMWSCEN!$HJ$2:$HJ$150=J$1),0),$B15-1973)} -> 96841.12 | ... BV15: {=INDEX(GMWSCEN!$A$2:$HJ$150,MATCH(1,(GMWSCEN!$HI$2:$HI$150=BV$3)*(GMWSCEN!$HJ$2:$HJ$150=BV$1),0),$B15-1973)} -> -3.585911 | BY15: =+BY11+1 -> 1981 | BZ15: =BY15&"01" -> 198101 | CB15: =+CB14+1 -> 1988 | CC15: =+CC14+100 -> 198801 | CD15: =SUMIF($BY$7:$BY$206,$CB15,C$7:C$206) -> 1239035 | CE15: =SUMIF($BY$7:$BY$206,$CB15,D$7:D$206) -> -5530 | CF15: =SUMIF($BY$7:$BY$206,$CB15,E$7:E$206) -> 5845 | CG15: =SUMIF($BY$7:$BY$206,$CB15,F$7:F$206) -> 177051 | CH15: =SUMIF($BY$7:$BY$206,$CB15,G$7:G$206) -> 315 | CI15: =SUMIF($BY$7:$BY$206,$CB15,H$7:H$206) -> 19789 | CJ15: =SUMIF($BY$7:$BY$206,$CB15,I$7:I$206) -> 202685 | CK15: =SUMIF($BZ$7:$BZ$206,$CC15,J$7:J$206) -> 97603.77 | CL15: =SUMIF($BY$7:$BY$206,$CB15,K$7:K$206) -> 571023 | CM15: =SUMIF($BY$7:$BY$206,$CB15,L$7:L$206) -> 1186568.7 | CN15: =AVERAGEIF($BY$7:$BY$206,$CB15,M$7:M$206) -> 46.07665 | CO15: =AVERAGEIF($BY$7:$BY$206,$CB15,N$7:N$206) -> 50.216667 | CP15: =AVERAGEIF($BY$7:$BY$206,$CB15,O$7:O$206) -> 11.625 | CQ15: =SUMIF($BY$7:$BY$206,$CB15,P$7:P$206) -> 117908.82 | CR15: =AVERAGEIF($BY$7:$BY$206,$CB15,Q$7:Q$206) -> 74.275 | CS15: =SUMIF($BY$7:$BY$206,$CB15,R$7:R$206) -> 0.004 | CT15: =AVERAGEIF($BY$7:$BY$206,$CB15,S$7:S$206) -> 8.175 | CU15: =SUMIF($BZ$7:$BZ$206,$CC15,T$7:T$206) -> 3.945732 | CV15: =SUMIF($BY$7:$BY$206,$CB15,U$7:U$206) -> 1239035 | CW15: =SUMIF($BY$7:$BY$206,$CB15,V$7:V$206) -> -5530 | CX15: =SUMIF($BY$7:$BY$206,$CB15,W$7:W$206) -> 5845 | CY15: =SUMIF($BY$7:$BY$206,$CB15,X$7:X$206) -> 177051 | CZ15: =SUMIF($BY$7:$BY$206,$CB15,Y$7:Y$206) -> 315 | DA15: =SUMIF($BY$7:$BY$206,$CB15,Z$7:Z$206) -> 19789 | DB15: =SUMIF($BY$7:$BY$206,$CB15,AA$7:AA$206) -> 202685 | DC15: =SUMIF($BZ$7:$BZ$206,$CC15,AB$7:AB$206) -> 97603.77 | DD15: =SUMIF($BY$7:$BY$206,$CB15,AC$7:AC$206) -> 571023 | DE15: =SUMIF($BY$7:$BY$206,$CB15,AD$7:AD$206) -> 1186568.7 | DF15: =AVERAGEIF($BY$7:$BY$206,$CB15,AE$7:AE$206) -> 46.07665 | DG15: =AVERAGEIF($BY$7:$BY$206,$CB15,AF$7:AF$206) -> 50.216667 | DH15: =AVERAGEIF($BY$7:$BY$206,$CB15,AG$7:AG$206) -> 11.625 | DI15: =SUMIF($BY$7:$BY$206,$CB15,AH$7:AH$206) -> 117908.82 | DJ15: =AVERAGEIF($BY$7:$BY$206,$CB15,AI$7:AI$206) -> 74.275 | DK15: =SUMIF($BY$7:$BY$206,$CB15,AJ$7:AJ$206) -> 0.004 | DL15: =AVERAGEIF($BY$7:$BY$206,$CB15,AK$7:AK$206) -> 8.175 | DM15: =SUMIF($BZ$7:$BZ$206,$CC15,AL$7:AL$206) -> 3.945732 | DN15: =SUMIF($BY$7:$BY$206,$CB15,AM$7:AM$206) -> 1239035 | DO15: =SUMIF($BY$7:$BY$206,$CB15,AN$7:AN$206) -> -5530 | DP15: =SUMIF($BY$7:$BY$206,$CB15,AO$7:AO$206) -> 5845 | DQ15: =SUMIF($BY$7:$BY$206,$CB15,AP$7:AP$206) -> 177051 | DR15: =SUMIF($BY$7:$BY$206,$CB15,AQ$7:AQ$206) -> 315 | DS15: =SUMIF($BY$7:$BY$206,$CB15,AR$7:AR$206) -> 19789 | DT15: =SUMIF($BY$7:$BY$206,$CB15,AS$7:AS$206) -> 202685 | DU15: =SUMIF($BZ$7:$BZ$206,$CC15,AT$7:AT$206) -> 97603.77 | DV15: =SUMIF($BY$7:$BY$206,$CB15,AU$7:AU$206) -> 571023 | DW15: =SUMIF($BY$7:$BY$206,$CB15,AV$7:AV$206) -> 1186568.7 | DX15: =AVERAGEIF($BY$7:$BY$206,$CB15,AW$7:AW$206) -> 46.07665 | DY15: =AVERAGEIF($BY$7:$BY$206,$CB15,AX$7:AX$206) -> 50.216667 | DZ15: =AVERAGEIF($BY$7:$BY$206,$CB15,AY$7:AY$206) -> 11.625 | EA15: =SUMIF($BY$7:$BY$206,$CB15,AZ$7:AZ$206) -> 117908.82 | EB15: =AVERAGEIF($BY$7:$BY$206,$CB15,BA$7:BA$206) -> 74.275 | EC15: =SUMIF($BY$7:$BY$206,$CB15,BB$7:BB$206) -> 0.004 | ED15: =AVERAGEIF($BY$7:$BY$206,$CB15,BC$7:BC$206) -> 8.175 | EE15: =SUMIF($BZ$7:$BZ$206,$CC15,BD$7:BD$206) -> 3.945732 | EF15: =SUMIF($BY$7:$BY$206,$CB15,BE$7:BE$206) -> 1239035 | EG15: =SUMIF($BY$7:$BY$206,$CB15,BF$7:BF$206) -> -5530 | EH15: =SUMIF($BY$7:$BY$206,$CB15,BG$7:BG$206) -> 5845 | EI15: =SUMIF($BY$7:$BY$206,$CB15,BH$7:BH$206) -> 177051 | EJ15: =SUMIF($BY$7:$BY$206,$CB15,BI$7:BI$206) -> 315 | EK15: =SUMIF($BY$7:$BY$206,$CB15,BJ$7:BJ$206) -> 19789 | EL15: =SUMIF($BY$7:$BY$206,$CB15,BK$7:BK$206) -> 202685 | EM15: =SUMIF($BZ$7:$BZ$206,$CC15,BL$7:BL$206) -> 97603.77 | EN15: =SUMIF($BY$7:$BY$206,$CB15,BM$7:BM$206) -> 571023 | EO15: =SUMIF($BY$7:$BY$206,$CB15,BN$7:BN$206) -> 1186568.7 | EP15: =AVERAGEIF($BY$7:$BY$206,$CB15,BO$7:BO$206) -> 46.07665 | EQ15: =AVERAGEIF($BY$7:$BY$206,$CB15,BP$7:BP$206) -> 50.216667 | ER15: =AVERAGEIF($BY$7:$BY$206,$CB15,BQ$7:BQ$206) -> 11.625 | ES15: =SUMIF($BY$7:$BY$206,$CB15,BR$7:BR$206) -> 117908.82 | ET15: =AVERAGEIF($BY$7:$BY$206,$CB15,BS$7:BS$206) -> 74.275 | EU15: =SUMIF($BY$7:$BY$206,$CB15,BT$7:BT$206) -> 0.004 | EV15: =AVERAGEIF($BY$7:$BY$206,$CB15,BU$7:BU$206) -> 8.175 | EW15: =SUMIF($BZ$7:$BZ$206,$CC15,BV$7:BV$206) -> 3.945732
B16: =+B15+1 -> 1989 | C16: {=INDEX(GMWSCEN!$A$2:$HJ$150,MATCH(1,(GMWSCEN!$HI$2:$HI$150=C$3)*(GMWSCEN!$HJ$2:$HJ$150=C$1),0),$B16-1973)} -> 242095 | D16: {=INDEX(GMWSCEN!$A$2:$HJ$150,MATCH(1,(GMWSCEN!$HI$2:$HI$150=D$3)*(GMWSCEN!$HJ$2:$HJ$150=D$1),0),$B16-1973)} -> 2938 | E16: {=INDEX(GMWSCEN!$A$2:$HJ$150,MATCH(1,(GMWSCEN!$HI$2:$HI$150=E$3)*(GMWSCEN!$HJ$2:$HJ$150=E$1),0),$B16-1973)} -> -2280 | F16: {=INDEX(GMWSCEN!$A$2:$HJ$150,MATCH(1,(GMWSCEN!$HI$2:$HI$150=F$3)*(GMWSCEN!$HJ$2:$HJ$150=F$1),0),$B16-1973)} -> 28856 | G16: {=INDEX(GMWSCEN!$A$2:$HJ$150,MATCH(1,(GMWSCEN!$HI$2:$HI$150=G$3)*(GMWSCEN!$HJ$2:$HJ$150=G$1),0),$B16-1973)} -> 658 | H16: {=INDEX(GMWSCEN!$A$2:$HJ$150,MATCH(1,(GMWSCEN!$HI$2:$HI$150=H$3)*(GMWSCEN!$HJ$2:$HJ$150=H$1),0),$B16-1973)} -> 3350 | I16: {=INDEX(GMWSCEN!$A$2:$HJ$150,MATCH(1,(GMWSCEN!$HI$2:$HI$150=I$3)*(GMWSCEN!$HJ$2:$HJ$150=I$1),0),$B16-1973)} -> 29926 | J16: {=INDEX(GMWSCEN!$A$2:$HJ$150,MATCH(1,(GMWSCEN!$HI$2:$HI$150=J$3)*(GMWSCEN!$HJ$2:$HJ$150=J$1),0),$B16-1973)} -> 98489.59 | ... BV16: {=INDEX(GMWSCEN!$A$2:$HJ$150,MATCH(1,(GMWSCEN!$HI$2:$HI$150=BV$3)*(GMWSCEN!$HJ$2:$HJ$150=BV$1),0),$B16-1973)} -> -2.735233 | BY16: =+BY12+1 -> 1982 | CB16: =+CB15+1 -> 1989 | CC16: =+CC15+100 -> 198901 | CD16: =SUMIF($BY$7:$BY$206,$CB16,C$7:C$206) -> 1263225 | CE16: =SUMIF($BY$7:$BY$206,$CB16,D$7:D$206) -> 124 | CF16: =SUMIF($BY$7:$BY$206,$CB16,E$7:E$206) -> 4785 | CG16: =SUMIF($BY$7:$BY$206,$CB16,F$7:F$206) -> 192223 | CH16: =SUMIF($BY$7:$BY$206,$CB16,G$7:G$206) -> 4909 | CI16: =SUMIF($BY$7:$BY$206,$CB16,H$7:H$206) -> 21622 | CJ16: =SUMIF($BY$7:$BY$206,$CB16,I$7:I$206) -> 218630 | CK16: =SUMIF($BZ$7:$BZ$206,$CC16,J$7:J$206) -> 97206.61 | CL16: =SUMIF($BY$7:$BY$206,$CB16,K$7:K$206) -> 629064 | CM16: =SUMIF($BY$7:$BY$206,$CB16,L$7:L$206) -> 1226805.8 | CN16: =AVERAGEIF($BY$7:$BY$206,$CB16,M$7:M$206) -> 49.795542 | CO16: =AVERAGEIF($BY$7:$BY$206,$CB16,N$7:N$206) -> 52.950002 | CP16: =AVERAGEIF($BY$7:$BY$206,$CB16,O$7:O$206) -> 14.3125 | CQ16: =SUMIF($BY$7:$BY$206,$CB16,P$7:P$206) -> 120949.72 | CR16: =AVERAGEIF($BY$7:$BY$206,$CB16,Q$7:Q$206) -> 75.175 | CS16: =SUMIF($BY$7:$BY$206,$CB16,R$7:R$206) -> 34046.003 | CT16: =AVERAGEIF($BY$7:$BY$206,$CB16,S$7:S$206) -> 7.05 | CU16: =SUMIF($BZ$7:$BZ$206,$CC16,T$7:T$206) -> 2.330494 | CV16: =SUMIF($BY$7:$BY$206,$CB16,U$7:U$206) -> 1263225 | CW16: =SUMIF($BY$7:$BY$206,$CB16,V$7:V$206) -> 124 | CX16: =SUMIF($BY$7:$BY$206,$CB16,W$7:W$206) -> 4785 | CY16: =SUMIF($BY$7:$BY$206,$CB16,X$7:X$206) -> 192223 | CZ16: =SUMIF($BY$7:$BY$206,$CB16,Y$7:Y$206) -> 4909 | DA16: =SUMIF($BY$7:$BY$206,$CB16,Z$7:Z$206) -> 21622 | DB16: =SUMIF($BY$7:$BY$206,$CB16,AA$7:AA$206) -> 218630 | DC16: =SUMIF($BZ$7:$BZ$206,$CC16,AB$7:AB$206) -> 97206.61 | DD16: =SUMIF($BY$7:$BY$206,$CB16,AC$7:AC$206) -> 629064 | DE16: =SUMIF($BY$7:$BY$206,$CB16,AD$7:AD$206) -> 1226805.8 | DF16: =AVERAGEIF($BY$7:$BY$206,$CB16,AE$7:AE$206) -> 49.795542 | DG16: =AVERAGEIF($BY$7:$BY$206,$CB16,AF$7:AF$206) -> 52.950002 | DH16: =AVERAGEIF($BY$7:$BY$206,$CB16,AG$7:AG$206) -> 14.3125 | DI16: =SUMIF($BY$7:$BY$206,$CB16,AH$7:AH$206) -> 120949.72 | DJ16: =AVERAGEIF($BY$7:$BY$206,$CB16,AI$7:AI$206) -> 75.175 | DK16: =SUMIF($BY$7:$BY$206,$CB16,AJ$7:AJ$206) -> 34046.003 | DL16: =AVERAGEIF($BY$7:$BY$206,$CB16,AK$7:AK$206) -> 7.05 | DM16: =SUMIF($BZ$7:$BZ$206,$CC16,AL$7:AL$206) -> 2.330494 | DN16: =SUMIF($BY$7:$BY$206,$CB16,AM$7:AM$206) -> 1263225 | DO16: =SUMIF($BY$7:$BY$206,$CB16,AN$7:AN$206) -> 124 | DP16: =SUMIF($BY$7:$BY$206,$CB16,AO$7:AO$206) -> 4785 | DQ16: =SUMIF($BY$7:$BY$206,$CB16,AP$7:AP$206) -> 192223 | DR16: =SUMIF($BY$7:$BY$206,$CB16,AQ$7:AQ$206) -> 4909 | DS16: =SUMIF($BY$7:$BY$206,$CB16,AR$7:AR$206) -> 21622 | DT16: =SUMIF($BY$7:$BY$206,$CB16,AS$7:AS$206) -> 218630 | DU16: =SUMIF($BZ$7:$BZ$206,$CC16,AT$7:AT$206) -> 97206.61 | DV16: =SUMIF($BY$7:$BY$206,$CB16,AU$7:AU$206) -> 629064 | DW16: =SUMIF($BY$7:$BY$206,$CB16,AV$7:AV$206) -> 1226805.8 | DX16: =AVERAGEIF($BY$7:$BY$206,$CB16,AW$7:AW$206) -> 49.795542 | DY16: =AVERAGEIF($BY$7:$BY$206,$CB16,AX$7:AX$206) -> 52.950002 | DZ16: =AVERAGEIF($BY$7:$BY$206,$CB16,AY$7:AY$206) -> 14.3125 | EA16: =SUMIF($BY$7:$BY$206,$CB16,AZ$7:AZ$206) -> 120949.72 | EB16: =AVERAGEIF($BY$7:$BY$206,$CB16,BA$7:BA$206) -> 75.175 | EC16: =SUMIF($BY$7:$BY$206,$CB16,BB$7:BB$206) -> 34046.003 | ED16: =AVERAGEIF($BY$7:$BY$206,$CB16,BC$7:BC$206) -> 7.05 | EE16: =SUMIF($BZ$7:$BZ$206,$CC16,BD$7:BD$206) -> 2.330494 | EF16: =SUMIF($BY$7:$BY$206,$CB16,BE$7:BE$206) -> 1263225 | EG16: =SUMIF($BY$7:$BY$206,$CB16,BF$7:BF$206) -> 124 | EH16: =SUMIF($BY$7:$BY$206,$CB16,BG$7:BG$206) -> 4785 | EI16: =SUMIF($BY$7:$BY$206,$CB16,BH$7:BH$206) -> 192223 | EJ16: =SUMIF($BY$7:$BY$206,$CB16,BI$7:BI$206) -> 4909 | EK16: =SUMIF($BY$7:$BY$206,$CB16,BJ$7:BJ$206) -> 21622 | EL16: =SUMIF($BY$7:$BY$206,$CB16,BK$7:BK$206) -> 218630 | EM16: =SUMIF($BZ$7:$BZ$206,$CC16,BL$7:BL$206) -> 97206.61 | EN16: =SUMIF($BY$7:$BY$206,$CB16,BM$7:BM$206) -> 629064 | EO16: =SUMIF($BY$7:$BY$206,$CB16,BN$7:BN$206) -> 1226805.8 | EP16: =AVERAGEIF($BY$7:$BY$206,$CB16,BO$7:BO$206) -> 49.795542 | EQ16: =AVERAGEIF($BY$7:$BY$206,$CB16,BP$7:BP$206) -> 52.950002 | ER16: =AVERAGEIF($BY$7:$BY$206,$CB16,BQ$7:BQ$206) -> 14.3125 | ES16: =SUMIF($BY$7:$BY$206,$CB16,BR$7:BR$206) -> 120949.72 | ET16: =AVERAGEIF($BY$7:$BY$206,$CB16,BS$7:BS$206) -> 75.175 | EU16: =SUMIF($BY$7:$BY$206,$CB16,BT$7:BT$206) -> 34046.003 | EV16: =AVERAGEIF($BY$7:$BY$206,$CB16,BU$7:BU$206) -> 7.05 | EW16: =SUMIF($BZ$7:$BZ$206,$CC16,BV$7:BV$206) -> 2.330494
B17: =+B16+1 -> 1990 | C17: {=INDEX(GMWSCEN!$A$2:$HJ$150,MATCH(1,(GMWSCEN!$HI$2:$HI$150=C$3)*(GMWSCEN!$HJ$2:$HJ$150=C$1),0),$B17-1973)} -> 242639 | D17: {=INDEX(GMWSCEN!$A$2:$HJ$150,MATCH(1,(GMWSCEN!$HI$2:$HI$150=D$3)*(GMWSCEN!$HJ$2:$HJ$150=D$1),0),$B17-1973)} -> 2421 | E17: {=INDEX(GMWSCEN!$A$2:$HJ$150,MATCH(1,(GMWSCEN!$HI$2:$HI$150=E$3)*(GMWSCEN!$HJ$2:$HJ$150=E$1),0),$B17-1973)} -> -1135 | F17: {=INDEX(GMWSCEN!$A$2:$HJ$150,MATCH(1,(GMWSCEN!$HI$2:$HI$150=F$3)*(GMWSCEN!$HJ$2:$HJ$150=F$1),0),$B17-1973)} -> 30155 | G17: {=INDEX(GMWSCEN!$A$2:$HJ$150,MATCH(1,(GMWSCEN!$HI$2:$HI$150=G$3)*(GMWSCEN!$HJ$2:$HJ$150=G$1),0),$B17-1973)} -> 1286 | H17: {=INDEX(GMWSCEN!$A$2:$HJ$150,MATCH(1,(GMWSCEN!$HI$2:$HI$150=H$3)*(GMWSCEN!$HJ$2:$HJ$150=H$1),0),$B17-1973)} -> 3397 | I17: {=INDEX(GMWSCEN!$A$2:$HJ$150,MATCH(1,(GMWSCEN!$HI$2:$HI$150=I$3)*(GMWSCEN!$HJ$2:$HJ$150=I$1),0),$B17-1973)} -> 32417 | J17: {=INDEX(GMWSCEN!$A$2:$HJ$150,MATCH(1,(GMWSCEN!$HI$2:$HI$150=J$3)*(GMWSCEN!$HJ$2:$HJ$150=J$1),0),$B17-1973)} -> 100607.5 | ... BV17: {=INDEX(GMWSCEN!$A$2:$HJ$150,MATCH(1,(GMWSCEN!$HI$2:$HI$150=BV$3)*(GMWSCEN!$HJ$2:$HJ$150=BV$1),0),$B17-1973)} -> -2.66428 | BY17: =+BY13+1 -> 1982 | CB17: =+CB16+1 -> 1990 | CC17: =+CC16+100 -> 199001 | CD17: =SUMIF($BY$7:$BY$206,$CB17,C$7:C$206) -> 1261727 | CE17: =SUMIF($BY$7:$BY$206,$CB17,D$7:D$206) -> 7315 | CF17: =SUMIF($BY$7:$BY$206,$CB17,E$7:E$206) -> -641 | CG17: =SUMIF($BY$7:$BY$206,$CB17,F$7:F$206) -> 209589 | CH17: =SUMIF($BY$7:$BY$206,$CB17,G$7:G$206) -> 6674 | CI17: =SUMIF($BY$7:$BY$206,$CB17,H$7:H$206) -> 21429 | CJ17: =SUMIF($BY$7:$BY$206,$CB17,I$7:I$206) -> 230377 | CK17: =SUMIF($BZ$7:$BZ$206,$CC17,J$7:J$206) -> 100297.1 | CL17: =SUMIF($BY$7:$BY$206,$CB17,K$7:K$206) -> 680933 | CM17: =SUMIF($BY$7:$BY$206,$CB17,L$7:L$206) -> 1256318.7 | CN17: =AVERAGEIF($BY$7:$BY$206,$CB17,M$7:M$206) -> 53.977305 | CO17: =AVERAGEIF($BY$7:$BY$206,$CB17,N$7:N$206) -> 56.783335 | CP17: =AVERAGEIF($BY$7:$BY$206,$CB17,O$7:O$206) -> 14 | CQ17: =SUMIF($BY$7:$BY$206,$CB17,P$7:P$206) -> 119574 | CR17: =AVERAGEIF($BY$7:$BY$206,$CB17,Q$7:Q$206) -> 74.5 | CS17: =SUMIF($BY$7:$BY$206,$CB17,R$7:R$206) -> 130557 | CT17: =AVERAGEIF($BY$7:$BY$206,$CB17,S$7:S$206) -> 7.375 | CU17: =SUMIF($BZ$7:$BZ$206,$CC17,T$7:T$206) -> -0.9316444 | CV17: =SUMIF($BY$7:$BY$206,$CB17,U$7:U$206) -> 1261727 | CW17: =SUMIF($BY$7:$BY$206,$CB17,V$7:V$206) -> 7315 | CX17: =SUMIF($BY$7:$BY$206,$CB17,W$7:W$206) -> -641 | CY17: =SUMIF($BY$7:$BY$206,$CB17,X$7:X$206) -> 209589 | CZ17: =SUMIF($BY$7:$BY$206,$CB17,Y$7:Y$206) -> 6674 | DA17: =SUMIF($BY$7:$BY$206,$CB17,Z$7:Z$206) -> 21429 | DB17: =SUMIF($BY$7:$BY$206,$CB17,AA$7:AA$206) -> 230377 | DC17: =SUMIF($BZ$7:$BZ$206,$CC17,AB$7:AB$206) -> 100297.1 | DD17: =SUMIF($BY$7:$BY$206,$CB17,AC$7:AC$206) -> 680933 | DE17: =SUMIF($BY$7:$BY$206,$CB17,AD$7:AD$206) -> 1256318.7 | DF17: =AVERAGEIF($BY$7:$BY$206,$CB17,AE$7:AE$206) -> 53.977305 | DG17: =AVERAGEIF($BY$7:$BY$206,$CB17,AF$7:AF$206) -> 56.783335 | DH17: =AVERAGEIF($BY$7:$BY$206,$CB17,AG$7:AG$206) -> 14 | DI17: =SUMIF($BY$7:$BY$206,$CB17,AH$7:AH$206) -> 119574 | DJ17: =AVERAGEIF($BY$7:$BY$206,$CB17,AI$7:AI$206) -> 74.5 | DK17: =SUMIF($BY$7:$BY$206,$CB17,AJ$7:AJ$206) -> 130557 | DL17: =AVERAGEIF($BY$7:$BY$206,$CB17,AK$7:AK$206) -> 7.375 | DM17: =SUMIF($BZ$7:$BZ$206,$CC17,AL$7:AL$206) -> -0.9316444 | DN17: =SUMIF($BY$7:$BY$206,$CB17,AM$7:AM$206) -> 1261727 | DO17: =SUMIF($BY$7:$BY$206,$CB17,AN$7:AN$206) -> 7315 | DP17: =SUMIF($BY$7:$BY$206,$CB17,AO$7:AO$206) -> -641 | DQ17: =SUMIF($BY$7:$BY$206,$CB17,AP$7:AP$206) -> 209589 | DR17: =SUMIF($BY$7:$BY$206,$CB17,AQ$7:AQ$206) -> 6674 | DS17: =SUMIF($BY$7:$BY$206,$CB17,AR$7:AR$206) -> 21429 | DT17: =SUMIF($BY$7:$BY$206,$CB17,AS$7:AS$206) -> 230377 | DU17: =SUMIF($BZ$7:$BZ$206,$CC17,AT$7:AT$206) -> 100297.1 | DV17: =SUMIF($BY$7:$BY$206,$CB17,AU$7:AU$206) -> 680933 | DW17: =SUMIF($BY$7:$BY$206,$CB17,AV$7:AV$206) -> 1256318.7 | DX17: =AVERAGEIF($BY$7:$BY$206,$CB17,AW$7:AW$206) -> 53.977305 | DY17: =AVERAGEIF($BY$7:$BY$206,$CB17,AX$7:AX$206) -> 56.783335 | DZ17: =AVERAGEIF($BY$7:$BY$206,$CB17,AY$7:AY$206) -> 14 | EA17: =SUMIF($BY$7:$BY$206,$CB17,AZ$7:AZ$206) -> 119574 | EB17: =AVERAGEIF($BY$7:$BY$206,$CB17,BA$7:BA$206) -> 74.5 | EC17: =SUMIF($BY$7:$BY$206,$CB17,BB$7:BB$206) -> 130557 | ED17: =AVERAGEIF($BY$7:$BY$206,$CB17,BC$7:BC$206) -> 7.375 | EE17: =SUMIF($BZ$7:$BZ$206,$CC17,BD$7:BD$206) -> -0.9316444 | EF17: =SUMIF($BY$7:$BY$206,$CB17,BE$7:BE$206) -> 1261727 | EG17: =SUMIF($BY$7:$BY$206,$CB17,BF$7:BF$206) -> 7315 | EH17: =SUMIF($BY$7:$BY$206,$CB17,BG$7:BG$206) -> -641 | EI17: =SUMIF($BY$7:$BY$206,$CB17,BH$7:BH$206) -> 209589 | EJ17: =SUMIF($BY$7:$BY$206,$CB17,BI$7:BI$206) -> 6674 | EK17: =SUMIF($BY$7:$BY$206,$CB17,BJ$7:BJ$206) -> 21429 | EL17: =SUMIF($BY$7:$BY$206,$CB17,BK$7:BK$206) -> 230377 | EM17: =SUMIF($BZ$7:$BZ$206,$CC17,BL$7:BL$206) -> 100297.1 | EN17: =SUMIF($BY$7:$BY$206,$CB17,BM$7:BM$206) -> 680933 | EO17: =SUMIF($BY$7:$BY$206,$CB17,BN$7:BN$206) -> 1256318.7 | EP17: =AVERAGEIF($BY$7:$BY$206,$CB17,BO$7:BO$206) -> 53.977305 | EQ17: =AVERAGEIF($BY$7:$BY$206,$CB17,BP$7:BP$206) -> 56.783335 | ER17: =AVERAGEIF($BY$7:$BY$206,$CB17,BQ$7:BQ$206) -> 14 | ES17: =SUMIF($BY$7:$BY$206,$CB17,BR$7:BR$206) -> 119574 | ET17: =AVERAGEIF($BY$7:$BY$206,$CB17,BS$7:BS$206) -> 74.5 | EU17: =SUMIF($BY$7:$BY$206,$CB17,BT$7:BT$206) -> 130557 | EV17: =AVERAGEIF($BY$7:$BY$206,$CB17,BU$7:BU$206) -> 7.375 | EW17: =SUMIF($BZ$7:$BZ$206,$CC17,BV$7:BV$206) -> -0.9316444
B18: =+B17+1 -> 1991 | C18: {=INDEX(GMWSCEN!$A$2:$HJ$150,MATCH(1,(GMWSCEN!$HI$2:$HI$150=C$3)*(GMWSCEN!$HJ$2:$HJ$150=C$1),0),$B18-1973)} -> 244317 | D18: {=INDEX(GMWSCEN!$A$2:$HJ$150,MATCH(1,(GMWSCEN!$HI$2:$HI$150=D$3)*(GMWSCEN!$HJ$2:$HJ$150=D$1),0),$B18-1973)} -> 1656 | E18: {=INDEX(GMWSCEN!$A$2:$HJ$150,MATCH(1,(GMWSCEN!$HI$2:$HI$150=E$3)*(GMWSCEN!$HJ$2:$HJ$150=E$1),0),$B18-1973)} -> -255 | F18: {=INDEX(GMWSCEN!$A$2:$HJ$150,MATCH(1,(GMWSCEN!$HI$2:$HI$150=F$3)*(GMWSCEN!$HJ$2:$HJ$150=F$1),0),$B18-1973)} -> 30212 | G18: {=INDEX(GMWSCEN!$A$2:$HJ$150,MATCH(1,(GMWSCEN!$HI$2:$HI$150=G$3)*(GMWSCEN!$HJ$2:$HJ$150=G$1),0),$B18-1973)} -> 1401 | H18: {=INDEX(GMWSCEN!$A$2:$HJ$150,MATCH(1,(GMWSCEN!$HI$2:$HI$150=H$3)*(GMWSCEN!$HJ$2:$HJ$150=H$1),0),$B18-1973)} -> 3447 | I18: {=INDEX(GMWSCEN!$A$2:$HJ$150,MATCH(1,(GMWSCEN!$HI$2:$HI$150=I$3)*(GMWSCEN!$HJ$2:$HJ$150=I$1),0),$B18-1973)} -> 33404 | J18: {=INDEX(GMWSCEN!$A$2:$HJ$150,MATCH(1,(GMWSCEN!$HI$2:$HI$150=J$3)*(GMWSCEN!$HJ$2:$HJ$150=J$1),0),$B18-1973)} -> 103194.7 | ... BV18: {=INDEX(GMWSCEN!$A$2:$HJ$150,MATCH(1,(GMWSCEN!$HI$2:$HI$150=BV$3)*(GMWSCEN!$HJ$2:$HJ$150=BV$1),0),$B18-1973)} -> -2.171993 | BY18: =+BY14+1 -> 1982 | CB18: =+CB17+1 -> 1991 | CC18: =+CC17+100 -> 199101 | CD18: =SUMIF($BY$7:$BY$206,$CB18,C$7:C$206) -> 1247769 | CE18: =SUMIF($BY$7:$BY$206,$CB18,D$7:D$206) -> 23764 | CF18: =SUMIF($BY$7:$BY$206,$CB18,E$7:E$206) -> -14698 | CG18: =SUMIF($BY$7:$BY$206,$CB18,F$7:F$206) -> 233675 | CH18: =SUMIF($BY$7:$BY$206,$CB18,G$7:G$206) -> 9066 | CI18: =SUMIF($BY$7:$BY$206,$CB18,H$7:H$206) -> 20656 | CJ18: =SUMIF($BY$7:$BY$206,$CB18,I$7:I$206) -> 239633 | CK18: =SUMIF($BZ$7:$BZ$206,$CC18,J$7:J$206) -> 131212.8 | CL18: =SUMIF($BY$7:$BY$206,$CB18,K$7:K$206) -> 714130 | CM18: =SUMIF($BY$7:$BY$206,$CB18,L$7:L$206) -> 1272868.8 | CN18: =AVERAGEIF($BY$7:$BY$206,$CB18,M$7:M$206) -> 57.232687 | CO18: =AVERAGEIF($BY$7:$BY$206,$CB18,N$7:N$206) -> 61.066667 | CP18: =AVERAGEIF($BY$7:$BY$206,$CB18,O$7:O$206) -> 10.625 | CQ18: =SUMIF($BY$7:$BY$206,$CB18,P$7:P$206) -> 114068 | CR18: =AVERAGEIF($BY$7:$BY$206,$CB18,Q$7:Q$206) -> 72.25 | CS18: =SUMIF($BY$7:$BY$206,$CB18,R$7:R$206) -> 122315 | CT18: =AVERAGEIF($BY$7:$BY$206,$CB18,S$7:S$206) -> 9.275 | CU18: =SUMIF($BZ$7:$BZ$206,$CC18,T$7:T$206) -> -2.7215 | CV18: =SUMIF($BY$7:$BY$206,$CB18,U$7:U$206) -> 1247769 | CW18: =SUMIF($BY$7:$BY$206,$CB18,V$7:V$206) -> 23764 | CX18: =SUMIF($BY$7:$BY$206,$CB18,W$7:W$206) -> -14698 | CY18: =SUMIF($BY$7:$BY$206,$CB18,X$7:X$206) -> 233675 | CZ18: =SUMIF($BY$7:$BY$206,$CB18,Y$7:Y$206) -> 9066 | DA18: =SUMIF($BY$7:$BY$206,$CB18,Z$7:Z$206) -> 20656 | DB18: =SUMIF($BY$7:$BY$206,$CB18,AA$7:AA$206) -> 239633 | DC18: =SUMIF($BZ$7:$BZ$206,$CC18,AB$7:AB$206) -> 131212.8 | DD18: =SUMIF($BY$7:$BY$206,$CB18,AC$7:AC$206) -> 714130 | DE18: =SUMIF($BY$7:$BY$206,$CB18,AD$7:AD$206) -> 1272868.8 | DF18: =AVERAGEIF($BY$7:$BY$206,$CB18,AE$7:AE$206) -> 57.232687 | DG18: =AVERAGEIF($BY$7:$BY$206,$CB18,AF$7:AF$206) -> 61.066667 | DH18: =AVERAGEIF($BY$7:$BY$206,$CB18,AG$7:AG$206) -> 10.625 | DI18: =SUMIF($BY$7:$BY$206,$CB18,AH$7:AH$206) -> 114068 | DJ18: =AVERAGEIF($BY$7:$BY$206,$CB18,AI$7:AI$206) -> 72.25 | DK18: =SUMIF($BY$7:$BY$206,$CB18,AJ$7:AJ$206) -> 122315 | DL18: =AVERAGEIF($BY$7:$BY$206,$CB18,AK$7:AK$206) -> 9.275 | DM18: =SUMIF($BZ$7:$BZ$206,$CC18,AL$7:AL$206) -> -2.7215 | DN18: =SUMIF($BY$7:$BY$206,$CB18,AM$7:AM$206) -> 1247769 | DO18: =SUMIF($BY$7:$BY$206,$CB18,AN$7:AN$206) -> 23764 | DP18: =SUMIF($BY$7:$BY$206,$CB18,AO$7:AO$206) -> -14698 | DQ18: =SUMIF($BY$7:$BY$206,$CB18,AP$7:AP$206) -> 233675 | DR18: =SUMIF($BY$7:$BY$206,$CB18,AQ$7:AQ$206) -> 9066 | DS18: =SUMIF($BY$7:$BY$206,$CB18,AR$7:AR$206) -> 20656 | DT18: =SUMIF($BY$7:$BY$206,$CB18,AS$7:AS$206) -> 239633 | DU18: =SUMIF($BZ$7:$BZ$206,$CC18,AT$7:AT$206) -> 131212.8 | DV18: =SUMIF($BY$7:$BY$206,$CB18,AU$7:AU$206) -> 714130 | DW18: =SUMIF($BY$7:$BY$206,$CB18,AV$7:AV$206) -> 1272868.8 | DX18: =AVERAGEIF($BY$7:$BY$206,$CB18,AW$7:AW$206) -> 57.232687 | DY18: =AVERAGEIF($BY$7:$BY$206,$CB18,AX$7:AX$206) -> 61.066667 | DZ18: =AVERAGEIF($BY$7:$BY$206,$CB18,AY$7:AY$206) -> 10.625 | EA18: =SUMIF($BY$7:$BY$206,$CB18,AZ$7:AZ$206) -> 114068 | EB18: =AVERAGEIF($BY$7:$BY$206,$CB18,BA$7:BA$206) -> 72.25 | EC18: =SUMIF($BY$7:$BY$206,$CB18,BB$7:BB$206) -> 122315 | ED18: =AVERAGEIF($BY$7:$BY$206,$CB18,BC$7:BC$206) -> 9.275 | EE18: =SUMIF($BZ$7:$BZ$206,$CC18,BD$7:BD$206) -> -2.7215 | EF18: =SUMIF($BY$7:$BY$206,$CB18,BE$7:BE$206) -> 1247769 | EG18: =SUMIF($BY$7:$BY$206,$CB18,BF$7:BF$206) -> 23764 | EH18: =SUMIF($BY$7:$BY$206,$CB18,BG$7:BG$206) -> -14698 | EI18: =SUMIF($BY$7:$BY$206,$CB18,BH$7:BH$206) -> 233675 | EJ18: =SUMIF($BY$7:$BY$206,$CB18,BI$7:BI$206) -> 9066 | EK18: =SUMIF($BY$7:$BY$206,$CB18,BJ$7:BJ$206) -> 20656 | EL18: =SUMIF($BY$7:$BY$206,$CB18,BK$7:BK$206) -> 239633 | EM18: =SUMIF($BZ$7:$BZ$206,$CC18,BL$7:BL$206) -> 131212.8 | EN18: =SUMIF($BY$7:$BY$206,$CB18,BM$7:BM$206) -> 714130 | EO18: =SUMIF($BY$7:$BY$206,$CB18,BN$7:BN$206) -> 1272868.8 | EP18: =AVERAGEIF($BY$7:$BY$206,$CB18,BO$7:BO$206) -> 57.232687 | EQ18: =AVERAGEIF($BY$7:$BY$206,$CB18,BP$7:BP$206) -> 61.066667 | ER18: =AVERAGEIF($BY$7:$BY$206,$CB18,BQ$7:BQ$206) -> 10.625 | ES18: =SUMIF($BY$7:$BY$206,$CB18,BR$7:BR$206) -> 114068 | ET18: =AVERAGEIF($BY$7:$BY$206,$CB18,BS$7:BS$206) -> 72.25 | EU18: =SUMIF($BY$7:$BY$206,$CB18,BT$7:BT$206) -> 122315 | EV18: =AVERAGEIF($BY$7:$BY$206,$CB18,BU$7:BU$206) -> 9.275 | EW18: =SUMIF($BZ$7:$BZ$206,$CC18,BV$7:BV$206) -> -2.7215
A19: 1983 | B19: =+B18+1 -> 1992 | C19: {=INDEX(GMWSCEN!$A$2:$HJ$150,MATCH(1,(GMWSCEN!$HI$2:$HI$150=C$3)*(GMWSCEN!$HJ$2:$HJ$150=C$1),0),$B19-1973)} -> 249032 | D19: {=INDEX(GMWSCEN!$A$2:$HJ$150,MATCH(1,(GMWSCEN!$HI$2:$HI$150=D$3)*(GMWSCEN!$HJ$2:$HJ$150=D$1),0),$B19-1973)} -> 1527 | E19: {=INDEX(GMWSCEN!$A$2:$HJ$150,MATCH(1,(GMWSCEN!$HI$2:$HI$150=E$3)*(GMWSCEN!$HJ$2:$HJ$150=E$1),0),$B19-1973)} -> 1465 | F19: {=INDEX(GMWSCEN!$A$2:$HJ$150,MATCH(1,(GMWSCEN!$HI$2:$HI$150=F$3)*(GMWSCEN!$HJ$2:$HJ$150=F$1),0),$B19-1973)} -> 32213 | G19: {=INDEX(GMWSCEN!$A$2:$HJ$150,MATCH(1,(GMWSCEN!$HI$2:$HI$150=G$3)*(GMWSCEN!$HJ$2:$HJ$150=G$1),0),$B19-1973)} -> 2992 | H19: {=INDEX(GMWSCEN!$A$2:$HJ$150,MATCH(1,(GMWSCEN!$HI$2:$HI$150=H$3)*(GMWSCEN!$HJ$2:$HJ$150=H$1),0),$B19-1973)} -> 3454 | I19: {=INDEX(GMWSCEN!$A$2:$HJ$150,MATCH(1,(GMWSCEN!$HI$2:$HI$150=I$3)*(GMWSCEN!$HJ$2:$HJ$150=I$1),0),$B19-1973)} -> 37132 | J19: {=INDEX(GMWSCEN!$A$2:$HJ$150,MATCH(1,(GMWSCEN!$HI$2:$HI$150=J$3)*(GMWSCEN!$HJ$2:$HJ$150=J$1),0),$B19-1973)} -> 107892.9 | ... BV19: {=INDEX(GMWSCEN!$A$2:$HJ$150,MATCH(1,(GMWSCEN!$HI$2:$HI$150=BV$3)*(GMWSCEN!$HJ$2:$HJ$150=BV$1),0),$B19-1973)} -> -0.4946709 | BY19: =+BY15+1 -> 1982 | BZ19: =BY19&"01" -> 198201 | CB19: =+CB18+1 -> 1992 | CC19: =+CC18+100 -> 199201 | CD19: =SUMIF($BY$7:$BY$206,$CB19,C$7:C$206) -> 1256503 | CE19: =SUMIF($BY$7:$BY$206,$CB19,D$7:D$206) -> 46552 | CF19: =SUMIF($BY$7:$BY$206,$CB19,E$7:E$206) -> -38528 | CG19: =SUMIF($BY$7:$BY$206,$CB19,F$7:F$206) -> 254584 | CH19: =SUMIF($BY$7:$BY$206,$CB19,G$7:G$206) -> 7819 | CI19: =SUMIF($BY$7:$BY$206,$CB19,H$7:H$206) -> 20849 | CJ19: =SUMIF($BY$7:$BY$206,$CB19,I$7:I$206) -> 236905 | CK19: =SUMIF($BZ$7:$BZ$206,$CC19,J$7:J$206) -> 201900 | CL19: =SUMIF($BY$7:$BY$206,$CB19,K$7:K$206) -> 739015 | CM19: =SUMIF($BY$7:$BY$206,$CB19,L$7:L$206) -> 1289319.2 | CN19: =AVERAGEIF($BY$7:$BY$206,$CB19,M$7:M$206) -> 58.8118 | CO19: =AVERAGEIF($BY$7:$BY$206,$CB19,N$7:N$206) -> 62.975 | CP19: =AVERAGEIF($BY$7:$BY$206,$CB19,O$7:O$206) -> 7.875 | CQ19: =SUMIF($BY$7:$BY$206,$CB19,P$7:P$206) -> 115041 | CR19: =AVERAGEIF($BY$7:$BY$206,$CB19,Q$7:Q$206) -> 72.95 | CS19: =SUMIF($BY$7:$BY$206,$CB19,R$7:R$206) -> 116618 | CT19: =AVERAGEIF($BY$7:$BY$206,$CB19,S$7:S$206) -> 10.175 | CU19: =SUMIF($BZ$7:$BZ$206,$CC19,T$7:T$206) -> -2.344513 | CV19: =SUMIF($BY$7:$BY$206,$CB19,U$7:U$206) -> 1256503 | CW19: =SUMIF($BY$7:$BY$206,$CB19,V$7:V$206) -> 46552 | CX19: =SUMIF($BY$7:$BY$206,$CB19,W$7:W$206) -> -38528 | CY19: =SUMIF($BY$7:$BY$206,$CB19,X$7:X$206) -> 254584 | CZ19: =SUMIF($BY$7:$BY$206,$CB19,Y$7:Y$206) -> 7819 | DA19: =SUMIF($BY$7:$BY$206,$CB19,Z$7:Z$206) -> 20849 | DB19: =SUMIF($BY$7:$BY$206,$CB19,AA$7:AA$206) -> 236905 | DC19: =SUMIF($BZ$7:$BZ$206,$CC19,AB$7:AB$206) -> 201900 | DD19: =SUMIF($BY$7:$BY$206,$CB19,AC$7:AC$206) -> 739015 | DE19: =SUMIF($BY$7:$BY$206,$CB19,AD$7:AD$206) -> 1289319.2 | DF19: =AVERAGEIF($BY$7:$BY$206,$CB19,AE$7:AE$206) -> 58.8118 | DG19: =AVERAGEIF($BY$7:$BY$206,$CB19,AF$7:AF$206) -> 62.975 | DH19: =AVERAGEIF($BY$7:$BY$206,$CB19,AG$7:AG$206) -> 7.875 | DI19: =SUMIF($BY$7:$BY$206,$CB19,AH$7:AH$206) -> 115041 | DJ19: =AVERAGEIF($BY$7:$BY$206,$CB19,AI$7:AI$206) -> 72.95 | DK19: =SUMIF($BY$7:$BY$206,$CB19,AJ$7:AJ$206) -> 116618 | DL19: =AVERAGEIF($BY$7:$BY$206,$CB19,AK$7:AK$206) -> 10.175 | DM19: =SUMIF($BZ$7:$BZ$206,$CC19,AL$7:AL$206) -> -2.344513 | DN19: =SUMIF($BY$7:$BY$206,$CB19,AM$7:AM$206) -> 1256503 | DO19: =SUMIF($BY$7:$BY$206,$CB19,AN$7:AN$206) -> 46552 | DP19: =SUMIF($BY$7:$BY$206,$CB19,AO$7:AO$206) -> -38528 | DQ19: =SUMIF($BY$7:$BY$206,$CB19,AP$7:AP$206) -> 254584 | DR19: =SUMIF($BY$7:$BY$206,$CB19,AQ$7:AQ$206) -> 7819 | DS19: =SUMIF($BY$7:$BY$206,$CB19,AR$7:AR$206) -> 20849 | DT19: =SUMIF($BY$7:$BY$206,$CB19,AS$7:AS$206) -> 236905 | DU19: =SUMIF($BZ$7:$BZ$206,$CC19,AT$7:AT$206) -> 201900 | DV19: =SUMIF($BY$7:$BY$206,$CB19,AU$7:AU$206) -> 739015 | DW19: =SUMIF($BY$7:$BY$206,$CB19,AV$7:AV$206) -> 1289319.2 | DX19: =AVERAGEIF($BY$7:$BY$206,$CB19,AW$7:AW$206) -> 58.8118 | DY19: =AVERAGEIF($BY$7:$BY$206,$CB19,AX$7:AX$206) -> 62.975 | DZ19: =AVERAGEIF($BY$7:$BY$206,$CB19,AY$7:AY$206) -> 7.875 | EA19: =SUMIF($BY$7:$BY$206,$CB19,AZ$7:AZ$206) -> 115041 | EB19: =AVERAGEIF($BY$7:$BY$206,$CB19,BA$7:BA$206) -> 72.95 | EC19: =SUMIF($BY$7:$BY$206,$CB19,BB$7:BB$206) -> 116618 | ED19: =AVERAGEIF($BY$7:$BY$206,$CB19,BC$7:BC$206) -> 10.175 | EE19: =SUMIF($BZ$7:$BZ$206,$CC19,BD$7:BD$206) -> -2.344513 | EF19: =SUMIF($BY$7:$BY$206,$CB19,BE$7:BE$206) -> 1256503 | EG19: =SUMIF($BY$7:$BY$206,$CB19,BF$7:BF$206) -> 46552 | EH19: =SUMIF($BY$7:$BY$206,$CB19,BG$7:BG$206) -> -38528 | EI19: =SUMIF($BY$7:$BY$206,$CB19,BH$7:BH$206) -> 254584 | EJ19: =SUMIF($BY$7:$BY$206,$CB19,BI$7:BI$206) -> 7819 | EK19: =SUMIF($BY$7:$BY$206,$CB19,BJ$7:BJ$206) -> 20849 | EL19: =SUMIF($BY$7:$BY$206,$CB19,BK$7:BK$206) -> 236905 | EM19: =SUMIF($BZ$7:$BZ$206,$CC19,BL$7:BL$206) -> 201900 | EN19: =SUMIF($BY$7:$BY$206,$CB19,BM$7:BM$206) -> 739015 | EO19: =SUMIF($BY$7:$BY$206,$CB19,BN$7:BN$206) -> 1289319.2 | EP19: =AVERAGEIF($BY$7:$BY$206,$CB19,BO$7:BO$206) -> 58.8118 | EQ19: =AVERAGEIF($BY$7:$BY$206,$CB19,BP$7:BP$206) -> 62.975 | ER19: =AVERAGEIF($BY$7:$BY$206,$CB19,BQ$7:BQ$206) -> 7.875 | ES19: =SUMIF($BY$7:$BY$206,$CB19,BR$7:BR$206) -> 115041 | ET19: =AVERAGEIF($BY$7:$BY$206,$CB19,BS$7:BS$206) -> 72.95 | EU19: =SUMIF($BY$7:$BY$206,$CB19,BT$7:BT$206) -> 116618 | EV19: =AVERAGEIF($BY$7:$BY$206,$CB19,BU$7:BU$206) -> 10.175 | EW19: =SUMIF($BZ$7:$BZ$206,$CC19,BV$7:BV$206) -> -2.344513
B20: =+B19+1 -> 1993 | C20: {=INDEX(GMWSCEN!$A$2:$HJ$150,MATCH(1,(GMWSCEN!$HI$2:$HI$150=C$3)*(GMWSCEN!$HJ$2:$HJ$150=C$1),0),$B20-1973)} -> 250761 | D20: {=INDEX(GMWSCEN!$A$2:$HJ$150,MATCH(1,(GMWSCEN!$HI$2:$HI$150=D$3)*(GMWSCEN!$HJ$2:$HJ$150=D$1),0),$B20-1973)} -> 4050 | E20: {=INDEX(GMWSCEN!$A$2:$HJ$150,MATCH(1,(GMWSCEN!$HI$2:$HI$150=E$3)*(GMWSCEN!$HJ$2:$HJ$150=E$1),0),$B20-1973)} -> -2799 | F20: {=INDEX(GMWSCEN!$A$2:$HJ$150,MATCH(1,(GMWSCEN!$HI$2:$HI$150=F$3)*(GMWSCEN!$HJ$2:$HJ$150=F$1),0),$B20-1973)} -> 31312 | G20: {=INDEX(GMWSCEN!$A$2:$HJ$150,MATCH(1,(GMWSCEN!$HI$2:$HI$150=G$3)*(GMWSCEN!$HJ$2:$HJ$150=G$1),0),$B20-1973)} -> 1251 | H20: {=INDEX(GMWSCEN!$A$2:$HJ$150,MATCH(1,(GMWSCEN!$HI$2:$HI$150=H$3)*(GMWSCEN!$HJ$2:$HJ$150=H$1),0),$B20-1973)} -> 3494 | I20: {=INDEX(GMWSCEN!$A$2:$HJ$150,MATCH(1,(GMWSCEN!$HI$2:$HI$150=I$3)*(GMWSCEN!$HJ$2:$HJ$150=I$1),0),$B20-1973)} -> 32007 | J20: {=INDEX(GMWSCEN!$A$2:$HJ$150,MATCH(1,(GMWSCEN!$HI$2:$HI$150=J$3)*(GMWSCEN!$HJ$2:$HJ$150=J$1),0),$B20-1973)} -> 112350.4 | ... BV20: {=INDEX(GMWSCEN!$A$2:$HJ$150,MATCH(1,(GMWSCEN!$HI$2:$HI$150=BV$3)*(GMWSCEN!$HJ$2:$HJ$150=BV$1),0),$B20-1973)} -> -0.3248215 | BY20: =+BY16+1 -> 1983 | CB20: =+CB19+1 -> 1993 | CC20: =+CC19+100 -> 199301 | CD20: =SUMIF($BY$7:$BY$206,$CB20,C$7:C$206) -> 1289505 | CE20: =SUMIF($BY$7:$BY$206,$CB20,D$7:D$206) -> 51556 | CF20: =SUMIF($BY$7:$BY$206,$CB20,E$7:E$206) -> -45188.999 | CG20: =SUMIF($BY$7:$BY$206,$CB20,F$7:F$206) -> 268660 | CH20: =SUMIF($BY$7:$BY$206,$CB20,G$7:G$206) -> 6153 | CI20: =SUMIF($BY$7:$BY$206,$CB20,H$7:H$206) -> 21237 | CJ20: =SUMIF($BY$7:$BY$206,$CB20,I$7:I$206) -> 244708 | CK20: =SUMIF($BZ$7:$BZ$206,$CC20,J$7:J$206) -> 249800 | CL20: =SUMIF($BY$7:$BY$206,$CB20,K$7:K$206) -> 780073 | CM20: =SUMIF($BY$7:$BY$206,$CB20,L$7:L$206) -> 1313607.1 | CN20: =AVERAGEIF($BY$7:$BY$206,$CB20,M$7:M$206) -> 60.488498 | CO20: =AVERAGEIF($BY$7:$BY$206,$CB20,N$7:N$206) -> 64.591665 | CP20: =AVERAGEIF($BY$7:$BY$206,$CB20,O$7:O$206) -> 5.5625 | CQ20: =SUMIF($BY$7:$BY$206,$CB20,P$7:P$206) -> 116936 | CR20: =AVERAGEIF($BY$7:$BY$206,$CB20,Q$7:Q$206) -> 75.025 | CS20: =SUMIF($BY$7:$BY$206,$CB20,R$7:R$206) -> 112917 | CT20: =AVERAGEIF($BY$7:$BY$206,$CB20,S$7:S$206) -> 10.2 | CU20: =SUMIF($BZ$7:$BZ$206,$CC20,T$7:T$206) -> -1.53265 | CV20: =SUMIF($BY$7:$BY$206,$CB20,U$7:U$206) -> 1289505 | CW20: =SUMIF($BY$7:$BY$206,$CB20,V$7:V$206) -> 51556 | CX20: =SUMIF($BY$7:$BY$206,$CB20,W$7:W$206) -> -45188.999 | CY20: =SUMIF($BY$7:$BY$206,$CB20,X$7:X$206) -> 268660 | CZ20: =SUMIF($BY$7:$BY$206,$CB20,Y$7:Y$206) -> 6153 | DA20: =SUMIF($BY$7:$BY$206,$CB20,Z$7:Z$206) -> 21237 | DB20: =SUMIF($BY$7:$BY$206,$CB20,AA$7:AA$206) -> 244708 | DC20: =SUMIF($BZ$7:$BZ$206,$CC20,AB$7:AB$206) -> 249800 | DD20: =SUMIF($BY$7:$BY$206,$CB20,AC$7:AC$206) -> 780073 | DE20: =SUMIF($BY$7:$BY$206,$CB20,AD$7:AD$206) -> 1313607.1 | DF20: =AVERAGEIF($BY$7:$BY$206,$CB20,AE$7:AE$206) -> 60.488498 | DG20: =AVERAGEIF($BY$7:$BY$206,$CB20,AF$7:AF$206) -> 64.591665 | DH20: =AVERAGEIF($BY$7:$BY$206,$CB20,AG$7:AG$206) -> 5.5625 | DI20: =SUMIF($BY$7:$BY$206,$CB20,AH$7:AH$206) -> 116936 | DJ20: =AVERAGEIF($BY$7:$BY$206,$CB20,AI$7:AI$206) -> 75.025 | DK20: =SUMIF($BY$7:$BY$206,$CB20,AJ$7:AJ$206) -> 112917 | DL20: =AVERAGEIF($BY$7:$BY$206,$CB20,AK$7:AK$206) -> 10.2 | DM20: =SUMIF($BZ$7:$BZ$206,$CC20,AL$7:AL$206) -> -1.53265 | DN20: =SUMIF($BY$7:$BY$206,$CB20,AM$7:AM$206) -> 1289505 | DO20: =SUMIF($BY$7:$BY$206,$CB20,AN$7:AN$206) -> 51556 | DP20: =SUMIF($BY$7:$BY$206,$CB20,AO$7:AO$206) -> -45188.999 | DQ20: =SUMIF($BY$7:$BY$206,$CB20,AP$7:AP$206) -> 268660 | DR20: =SUMIF($BY$7:$BY$206,$CB20,AQ$7:AQ$206) -> 6153 | DS20: =SUMIF($BY$7:$BY$206,$CB20,AR$7:AR$206) -> 21237 | DT20: =SUMIF($BY$7:$BY$206,$CB20,AS$7:AS$206) -> 244708 | DU20: =SUMIF($BZ$7:$BZ$206,$CC20,AT$7:AT$206) -> 249800 | DV20: =SUMIF($BY$7:$BY$206,$CB20,AU$7:AU$206) -> 780073 | DW20: =SUMIF($BY$7:$BY$206,$CB20,AV$7:AV$206) -> 1313607.1 | DX20: =AVERAGEIF($BY$7:$BY$206,$CB20,AW$7:AW$206) -> 60.488498 | DY20: =AVERAGEIF($BY$7:$BY$206,$CB20,AX$7:AX$206) -> 64.591665 | DZ20: =AVERAGEIF($BY$7:$BY$206,$CB20,AY$7:AY$206) -> 5.5625 | EA20: =SUMIF($BY$7:$BY$206,$CB20,AZ$7:AZ$206) -> 116936 | EB20: =AVERAGEIF($BY$7:$BY$206,$CB20,BA$7:BA$206) -> 75.025 | EC20: =SUMIF($BY$7:$BY$206,$CB20,BB$7:BB$206) -> 112917 | ED20: =AVERAGEIF($BY$7:$BY$206,$CB20,BC$7:BC$206) -> 10.2 | EE20: =SUMIF($BZ$7:$BZ$206,$CC20,BD$7:BD$206) -> -1.53265 | EF20: =SUMIF($BY$7:$BY$206,$CB20,BE$7:BE$206) -> 1289505 | EG20: =SUMIF($BY$7:$BY$206,$CB20,BF$7:BF$206) -> 51556 | EH20: =SUMIF($BY$7:$BY$206,$CB20,BG$7:BG$206) -> -45188.999 | EI20: =SUMIF($BY$7:$BY$206,$CB20,BH$7:BH$206) -> 268660 | EJ20: =SUMIF($BY$7:$BY$206,$CB20,BI$7:BI$206) -> 6153 | EK20: =SUMIF($BY$7:$BY$206,$CB20,BJ$7:BJ$206) -> 21237 | EL20: =SUMIF($BY$7:$BY$206,$CB20,BK$7:BK$206) -> 244708 | EM20: =SUMIF($BZ$7:$BZ$206,$CC20,BL$7:BL$206) -> 249800 | EN20: =SUMIF($BY$7:$BY$206,$CB20,BM$7:BM$206) -> 780073 | EO20: =SUMIF($BY$7:$BY$206,$CB20,BN$7:BN$206) -> 1313607.1 | EP20: =AVERAGEIF($BY$7:$BY$206,$CB20,BO$7:BO$206) -> 60.488498 | EQ20: =AVERAGEIF($BY$7:$BY$206,$CB20,BP$7:BP$206) -> 64.591665 | ER20: =AVERAGEIF($BY$7:$BY$206,$CB20,BQ$7:BQ$206) -> 5.5625 | ES20: =SUMIF($BY$7:$BY$206,$CB20,BR$7:BR$206) -> 116936 | ET20: =AVERAGEIF($BY$7:$BY$206,$CB20,BS$7:BS$206) -> 75.025 | EU20: =SUMIF($BY$7:$BY$206,$CB20,BT$7:BT$206) -> 112917 | EV20: =AVERAGEIF($BY$7:$BY$206,$CB20,BU$7:BU$206) -> 10.2 | EW20: =SUMIF($BZ$7:$BZ$206,$CC20,BV$7:BV$206) -> -1.53265
B21: =+B20+1 -> 1994 | C21: {=INDEX(GMWSCEN!$A$2:$HJ$150,MATCH(1,(GMWSCEN!$HI$2:$HI$150=C$3)*(GMWSCEN!$HJ$2:$HJ$150=C$1),0),$B21-1973)} -> 253655 | D21: {=INDEX(GMWSCEN!$A$2:$HJ$150,MATCH(1,(GMWSCEN!$HI$2:$HI$150=D$3)*(GMWSCEN!$HJ$2:$HJ$150=D$1),0),$B21-1973)} -> 4112 | E21: {=INDEX(GMWSCEN!$A$2:$HJ$150,MATCH(1,(GMWSCEN!$HI$2:$HI$150=E$3)*(GMWSCEN!$HJ$2:$HJ$150=E$1),0),$B21-1973)} -> -2262 | F21: {=INDEX(GMWSCEN!$A$2:$HJ$150,MATCH(1,(GMWSCEN!$HI$2:$HI$150=F$3)*(GMWSCEN!$HJ$2:$HJ$150=F$1),0),$B21-1973)} -> 32277 | G21: {=INDEX(GMWSCEN!$A$2:$HJ$150,MATCH(1,(GMWSCEN!$HI$2:$HI$150=G$3)*(GMWSCEN!$HJ$2:$HJ$150=G$1),0),$B21-1973)} -> 1850 | H21: {=INDEX(GMWSCEN!$A$2:$HJ$150,MATCH(1,(GMWSCEN!$HI$2:$HI$150=H$3)*(GMWSCEN!$HJ$2:$HJ$150=H$1),0),$B21-1973)} -> 3549 | I21: {=INDEX(GMWSCEN!$A$2:$HJ$150,MATCH(1,(GMWSCEN!$HI$2:$HI$150=I$3)*(GMWSCEN!$HJ$2:$HJ$150=I$1),0),$B21-1973)} -> 33564 | J21: {=INDEX(GMWSCEN!$A$2:$HJ$150,MATCH(1,(GMWSCEN!$HI$2:$HI$150=J$3)*(GMWSCEN!$HJ$2:$HJ$150=J$1),0),$B21-1973)} -> 111617.2 | ... BV21: {=INDEX(GMWSCEN!$A$2:$HJ$150,MATCH(1,(GMWSCEN!$HI$2:$HI$150=BV$3)*(GMWSCEN!$HJ$2:$HJ$150=BV$1),0),$B21-1973)} -> -0.1347542 | BY21: =+BY17+1 -> 1983 | CB21: =+CB20+1 -> 1994 | CC21: =+CC20+100 -> 199401 | CD21: =SUMIF($BY$7:$BY$206,$CB21,C$7:C$206) -> 1332948 | CE21: =SUMIF($BY$7:$BY$206,$CB21,D$7:D$206) -> 43804 | CF21: =SUMIF($BY$7:$BY$206,$CB21,E$7:E$206) -> -37204 | CG21: =SUMIF($BY$7:$BY$206,$CB21,F$7:F$206) -> 280356 | CH21: =SUMIF($BY$7:$BY$206,$CB21,G$7:G$206) -> 6720 | CI21: =SUMIF($BY$7:$BY$206,$CB21,H$7:H$206) -> 21401 | CJ21: =SUMIF($BY$7:$BY$206,$CB21,I$7:I$206) -> 264553 | CK21: =SUMIF($BZ$7:$BZ$206,$CC21,J$7:J$206) -> 290000 | CL21: =SUMIF($BY$7:$BY$206,$CB21,K$7:K$206) -> 819654 | CM21: =SUMIF($BY$7:$BY$206,$CB21,L$7:L$206) -> 1349067.1 | CN21: =AVERAGEIF($BY$7:$BY$206,$CB21,M$7:M$206) -> 61.48845 | CO21: =AVERAGEIF($BY$7:$BY$206,$CB21,N$7:N$206) -> 65.866668 | CP21: =AVERAGEIF($BY$7:$BY$206,$CB21,O$7:O$206) -> 5.875 | CQ21: =SUMIF($BY$7:$BY$206,$CB21,P$7:P$206) -> 122631 | CR21: =AVERAGEIF($BY$7:$BY$206,$CB21,Q$7:Q$206) -> 78.875 | CS21: =SUMIF($BY$7:$BY$206,$CB21,R$7:R$206) -> 110827 | CT21: =AVERAGEIF($BY$7:$BY$206,$CB21,S$7:S$206) -> 9.25 | CU21: =SUMIF($BZ$7:$BZ$206,$CC21,T$7:T$206) -> -1.254845 | CV21: =SUMIF($BY$7:$BY$206,$CB21,U$7:U$206) -> 1332948 | CW21: =SUMIF($BY$7:$BY$206,$CB21,V$7:V$206) -> 43804 | CX21: =SUMIF($BY$7:$BY$206,$CB21,W$7:W$206) -> -37204 | CY21: =SUMIF($BY$7:$BY$206,$CB21,X$7:X$206) -> 280356 | CZ21: =SUMIF($BY$7:$BY$206,$CB21,Y$7:Y$206) -> 6720 | DA21: =SUMIF($BY$7:$BY$206,$CB21,Z$7:Z$206) -> 21401 | DB21: =SUMIF($BY$7:$BY$206,$CB21,AA$7:AA$206) -> 264553 | DC21: =SUMIF($BZ$7:$BZ$206,$CC21,AB$7:AB$206) -> 290000 | DD21: =SUMIF($BY$7:$BY$206,$CB21,AC$7:AC$206) -> 819654 | DE21: =SUMIF($BY$7:$BY$206,$CB21,AD$7:AD$206) -> 1349067.1 | DF21: =AVERAGEIF($BY$7:$BY$206,$CB21,AE$7:AE$206) -> 61.48845 | DG21: =AVERAGEIF($BY$7:$BY$206,$CB21,AF$7:AF$206) -> 65.866668 | DH21: =AVERAGEIF($BY$7:$BY$206,$CB21,AG$7:AG$206) -> 5.875 | DI21: =SUMIF($BY$7:$BY$206,$CB21,AH$7:AH$206) -> 122631 | DJ21: =AVERAGEIF($BY$7:$BY$206,$CB21,AI$7:AI$206) -> 78.875 | DK21: =SUMIF($BY$7:$BY$206,$CB21,AJ$7:AJ$206) -> 110827 | DL21: =AVERAGEIF($BY$7:$BY$206,$CB21,AK$7:AK$206) -> 9.25 | DM21: =SUMIF($BZ$7:$BZ$206,$CC21,AL$7:AL$206) -> -1.254845 | DN21: =SUMIF($BY$7:$BY$206,$CB21,AM$7:AM$206) -> 1332948 | DO21: =SUMIF($BY$7:$BY$206,$CB21,AN$7:AN$206) -> 43804 | DP21: =SUMIF($BY$7:$BY$206,$CB21,AO$7:AO$206) -> -37204 | DQ21: =SUMIF($BY$7:$BY$206,$CB21,AP$7:AP$206) -> 280356 | DR21: =SUMIF($BY$7:$BY$206,$CB21,AQ$7:AQ$206) -> 6720 | DS21: =SUMIF($BY$7:$BY$206,$CB21,AR$7:AR$206) -> 21401 | DT21: =SUMIF($BY$7:$BY$206,$CB21,AS$7:AS$206) -> 264553 | DU21: =SUMIF($BZ$7:$BZ$206,$CC21,AT$7:AT$206) -> 290000 | DV21: =SUMIF($BY$7:$BY$206,$CB21,AU$7:AU$206) -> 819654 | DW21: =SUMIF($BY$7:$BY$206,$CB21,AV$7:AV$206) -> 1349067.1 | DX21: =AVERAGEIF($BY$7:$BY$206,$CB21,AW$7:AW$206) -> 61.48845 | DY21: =AVERAGEIF($BY$7:$BY$206,$CB21,AX$7:AX$206) -> 65.866668 | DZ21: =AVERAGEIF($BY$7:$BY$206,$CB21,AY$7:AY$206) -> 5.875 | EA21: =SUMIF($BY$7:$BY$206,$CB21,AZ$7:AZ$206) -> 122631 | EB21: =AVERAGEIF($BY$7:$BY$206,$CB21,BA$7:BA$206) -> 78.875 | EC21: =SUMIF($BY$7:$BY$206,$CB21,BB$7:BB$206) -> 110827 | ED21: =AVERAGEIF($BY$7:$BY$206,$CB21,BC$7:BC$206) -> 9.25 | EE21: =SUMIF($BZ$7:$BZ$206,$CC21,BD$7:BD$206) -> -1.254845 | EF21: =SUMIF($BY$7:$BY$206,$CB21,BE$7:BE$206) -> 1332948 | EG21: =SUMIF($BY$7:$BY$206,$CB21,BF$7:BF$206) -> 43804 | EH21: =SUMIF($BY$7:$BY$206,$CB21,BG$7:BG$206) -> -37204 | EI21: =SUMIF($BY$7:$BY$206,$CB21,BH$7:BH$206) -> 280356 | EJ21: =SUMIF($BY$7:$BY$206,$CB21,BI$7:BI$206) -> 6720 | EK21: =SUMIF($BY$7:$BY$206,$CB21,BJ$7:BJ$206) -> 21401 | EL21: =SUMIF($BY$7:$BY$206,$CB21,BK$7:BK$206) -> 264553 | EM21: =SUMIF($BZ$7:$BZ$206,$CC21,BL$7:BL$206) -> 290000 | EN21: =SUMIF($BY$7:$BY$206,$CB21,BM$7:BM$206) -> 819654 | EO21: =SUMIF($BY$7:$BY$206,$CB21,BN$7:BN$206) -> 1349067.1 | EP21: =AVERAGEIF($BY$7:$BY$206,$CB21,BO$7:BO$206) -> 61.48845 | EQ21: =AVERAGEIF($BY$7:$BY$206,$CB21,BP$7:BP$206) -> 65.866668 | ER21: =AVERAGEIF($BY$7:$BY$206,$CB21,BQ$7:BQ$206) -> 5.875 | ES21: =SUMIF($BY$7:$BY$206,$CB21,BR$7:BR$206) -> 122631 | ET21: =AVERAGEIF($BY$7:$BY$206,$CB21,BS$7:BS$206) -> 78.875 | EU21: =SUMIF($BY$7:$BY$206,$CB21,BT$7:BT$206) -> 110827 | EV21: =AVERAGEIF($BY$7:$BY$206,$CB21,BU$7:BU$206) -> 9.25 | EW21: =SUMIF($BZ$7:$BZ$206,$CC21,BV$7:BV$206) -> -1.254845
B22: =+B21+1 -> 1995 | C22: {=INDEX(GMWSCEN!$A$2:$HJ$150,MATCH(1,(GMWSCEN!$HI$2:$HI$150=C$3)*(GMWSCEN!$HJ$2:$HJ$150=C$1),0),$B22-1973)} -> 255533 | D22: {=INDEX(GMWSCEN!$A$2:$HJ$150,MATCH(1,(GMWSCEN!$HI$2:$HI$150=D$3)*(GMWSCEN!$HJ$2:$HJ$150=D$1),0),$B22-1973)} -> 893 | E22: {=INDEX(GMWSCEN!$A$2:$HJ$150,MATCH(1,(GMWSCEN!$HI$2:$HI$150=E$3)*(GMWSCEN!$HJ$2:$HJ$150=E$1),0),$B22-1973)} -> 1020 | F22: {=INDEX(GMWSCEN!$A$2:$HJ$150,MATCH(1,(GMWSCEN!$HI$2:$HI$150=F$3)*(GMWSCEN!$HJ$2:$HJ$150=F$1),0),$B22-1973)} -> 32618 | G22: {=INDEX(GMWSCEN!$A$2:$HJ$150,MATCH(1,(GMWSCEN!$HI$2:$HI$150=G$3)*(GMWSCEN!$HJ$2:$HJ$150=G$1),0),$B22-1973)} -> 1913 | H22: {=INDEX(GMWSCEN!$A$2:$HJ$150,MATCH(1,(GMWSCEN!$HI$2:$HI$150=H$3)*(GMWSCEN!$HJ$2:$HJ$150=H$1),0),$B22-1973)} -> 3619 | I22: {=INDEX(GMWSCEN!$A$2:$HJ$150,MATCH(1,(GMWSCEN!$HI$2:$HI$150=I$3)*(GMWSCEN!$HJ$2:$HJ$150=I$1),0),$B22-1973)} -> 37257 | J22: {=INDEX(GMWSCEN!$A$2:$HJ$150,MATCH(1,(GMWSCEN!$HI$2:$HI$150=J$3)*(GMWSCEN!$HJ$2:$HJ$150=J$1),0),$B22-1973)} -> 105693.5 | ... BV22: {=INDEX(GMWSCEN!$A$2:$HJ$150,MATCH(1,(GMWSCEN!$HI$2:$HI$150=BV$3)*(GMWSCEN!$HJ$2:$HJ$150=BV$1),0),$B22-1973)} -> -0.4068375 | BY22: =+BY18+1 -> 1983 | CB22: =+CB21+1 -> 1995 | CC22: =+CC21+100 -> 199501 | CD22: =SUMIF($BY$7:$BY$206,$CB22,C$7:C$206) -> 1362792 | CE22: =SUMIF($BY$7:$BY$206,$CB22,D$7:D$206) -> 35310 | CF22: =SUMIF($BY$7:$BY$206,$CB22,E$7:E$206) -> -28924.999 | CG22: =SUMIF($BY$7:$BY$206,$CB22,F$7:F$206) -> 294289 | CH22: =SUMIF($BY$7:$BY$206,$CB22,G$7:G$206) -> 6610 | CI22: =SUMIF($BY$7:$BY$206,$CB22,H$7:H$206) -> 21936 | CJ22: =SUMIF($BY$7:$BY$206,$CB22,I$7:I$206) -> 287300 | CK22: =SUMIF($BZ$7:$BZ$206,$CC22,J$7:J$206) -> 322100 | CL22: =SUMIF($BY$7:$BY$206,$CB22,K$7:K$206) -> 864621 | CM22: =SUMIF($BY$7:$BY$206,$CB22,L$7:L$206) -> 1383443.7 | CN22: =AVERAGEIF($BY$7:$BY$206,$CB22,M$7:M$206) -> 63.439863 | CO22: =AVERAGEIF($BY$7:$BY$206,$CB22,N$7:N$206) -> 67.625 | CP22: =AVERAGEIF($BY$7:$BY$206,$CB22,O$7:O$206) -> 6.390625 | CQ22: =SUMIF($BY$7:$BY$206,$CB22,P$7:P$206) -> 124109 | CR22: =AVERAGEIF($BY$7:$BY$206,$CB22,Q$7:Q$206) -> 80.1 | CS22: =SUMIF($BY$7:$BY$206,$CB22,R$7:R$206) -> 111588 | CT22: =AVERAGEIF($BY$7:$BY$206,$CB22,S$7:S$206) -> 8.45 | CU22: =SUMIF($BZ$7:$BZ$206,$CC22,T$7:T$206) -> -1.464558 | CV22: =SUMIF($BY$7:$BY$206,$CB22,U$7:U$206) -> 1362792 | CW22: =SUMIF($BY$7:$BY$206,$CB22,V$7:V$206) -> 35310 | CX22: =SUMIF($BY$7:$BY$206,$CB22,W$7:W$206) -> -28924.999 | CY22: =SUMIF($BY$7:$BY$206,$CB22,X$7:X$206) -> 294289 | CZ22: =SUMIF($BY$7:$BY$206,$CB22,Y$7:Y$206) -> 6610 | DA22: =SUMIF($BY$7:$BY$206,$CB22,Z$7:Z$206) -> 21936 | DB22: =SUMIF($BY$7:$BY$206,$CB22,AA$7:AA$206) -> 287300 | DC22: =SUMIF($BZ$7:$BZ$206,$CC22,AB$7:AB$206) -> 322100 | DD22: =SUMIF($BY$7:$BY$206,$CB22,AC$7:AC$206) -> 864621 | DE22: =SUMIF($BY$7:$BY$206,$CB22,AD$7:AD$206) -> 1383443.7 | DF22: =AVERAGEIF($BY$7:$BY$206,$CB22,AE$7:AE$206) -> 63.439863 | DG22: =AVERAGEIF($BY$7:$BY$206,$CB22,AF$7:AF$206) -> 67.625 | DH22: =AVERAGEIF($BY$7:$BY$206,$CB22,AG$7:AG$206) -> 6.390625 | DI22: =SUMIF($BY$7:$BY$206,$CB22,AH$7:AH$206) -> 124109 | DJ22: =AVERAGEIF($BY$7:$BY$206,$CB22,AI$7:AI$206) -> 80.1 | DK22: =SUMIF($BY$7:$BY$206,$CB22,AJ$7:AJ$206) -> 111588 | DL22: =AVERAGEIF($BY$7:$BY$206,$CB22,AK$7:AK$206) -> 8.45 | DM22: =SUMIF($BZ$7:$BZ$206,$CC22,AL$7:AL$206) -> -1.464558 | DN22: =SUMIF($BY$7:$BY$206,$CB22,AM$7:AM$206) -> 1362792 | DO22: =SUMIF($BY$7:$BY$206,$CB22,AN$7:AN$206) -> 35310 | DP22: =SUMIF($BY$7:$BY$206,$CB22,AO$7:AO$206) -> -28924.999 | DQ22: =SUMIF($BY$7:$BY$206,$CB22,AP$7:AP$206) -> 294289 | DR22: =SUMIF($BY$7:$BY$206,$CB22,AQ$7:AQ$206) -> 6610 | DS22: =SUMIF($BY$7:$BY$206,$CB22,AR$7:AR$206) -> 21936 | DT22: =SUMIF($BY$7:$BY$206,$CB22,AS$7:AS$206) -> 287300 | DU22: =SUMIF($BZ$7:$BZ$206,$CC22,AT$7:AT$206) -> 322100 | DV22: =SUMIF($BY$7:$BY$206,$CB22,AU$7:AU$206) -> 864621 | DW22: =SUMIF($BY$7:$BY$206,$CB22,AV$7:AV$206) -> 1383443.7 | DX22: =AVERAGEIF($BY$7:$BY$206,$CB22,AW$7:AW$206) -> 63.439863 | DY22: =AVERAGEIF($BY$7:$BY$206,$CB22,AX$7:AX$206) -> 67.625 | DZ22: =AVERAGEIF($BY$7:$BY$206,$CB22,AY$7:AY$206) -> 6.390625 | EA22: =SUMIF($BY$7:$BY$206,$CB22,AZ$7:AZ$206) -> 124109 | EB22: =AVERAGEIF($BY$7:$BY$206,$CB22,BA$7:BA$206) -> 80.1 | EC22: =SUMIF($BY$7:$BY$206,$CB22,BB$7:BB$206) -> 111588 | ED22: =AVERAGEIF($BY$7:$BY$206,$CB22,BC$7:BC$206) -> 8.45 | EE22: =SUMIF($BZ$7:$BZ$206,$CC22,BD$7:BD$206) -> -1.464558 | EF22: =SUMIF($BY$7:$BY$206,$CB22,BE$7:BE$206) -> 1362792 | EG22: =SUMIF($BY$7:$BY$206,$CB22,BF$7:BF$206) -> 35310 | EH22: =SUMIF($BY$7:$BY$206,$CB22,BG$7:BG$206) -> -28924.999 | EI22: =SUMIF($BY$7:$BY$206,$CB22,BH$7:BH$206) -> 294289 | EJ22: =SUMIF($BY$7:$BY$206,$CB22,BI$7:BI$206) -> 6610 | EK22: =SUMIF($BY$7:$BY$206,$CB22,BJ$7:BJ$206) -> 21936 | EL22: =SUMIF($BY$7:$BY$206,$CB22,BK$7:BK$206) -> 287300 | EM22: =SUMIF($BZ$7:$BZ$206,$CC22,BL$7:BL$206) -> 322100 | EN22: =SUMIF($BY$7:$BY$206,$CB22,BM$7:BM$206) -> 864621 | EO22: =SUMIF($BY$7:$BY$206,$CB22,BN$7:BN$206) -> 1383443.7 | EP22: =AVERAGEIF($BY$7:$BY$206,$CB22,BO$7:BO$206) -> 63.439863 | EQ22: =AVERAGEIF($BY$7:$BY$206,$CB22,BP$7:BP$206) -> 67.625 | ER22: =AVERAGEIF($BY$7:$BY$206,$CB22,BQ$7:BQ$206) -> 6.390625 | ES22: =SUMIF($BY$7:$BY$206,$CB22,BR$7:BR$206) -> 124109 | ET22: =AVERAGEIF($BY$7:$BY$206,$CB22,BS$7:BS$206) -> 80.1 | EU22: =SUMIF($BY$7:$BY$206,$CB22,BT$7:BT$206) -> 111588 | EV22: =AVERAGEIF($BY$7:$BY$206,$CB22,BU$7:BU$206) -> 8.45 | EW22: =SUMIF($BZ$7:$BZ$206,$CC22,BV$7:BV$206) -> -1.464558
A23: 1984 | B23: =+B22+1 -> 1996 | C23: {=INDEX(GMWSCEN!$A$2:$HJ$150,MATCH(1,(GMWSCEN!$HI$2:$HI$150=C$3)*(GMWSCEN!$HJ$2:$HJ$150=C$1),0),$B23-1973)} -> 257683 | D23: {=INDEX(GMWSCEN!$A$2:$HJ$150,MATCH(1,(GMWSCEN!$HI$2:$HI$150=D$3)*(GMWSCEN!$HJ$2:$HJ$150=D$1),0),$B23-1973)} -> 2747 | E23: {=INDEX(GMWSCEN!$A$2:$HJ$150,MATCH(1,(GMWSCEN!$HI$2:$HI$150=E$3)*(GMWSCEN!$HJ$2:$HJ$150=E$1),0),$B23-1973)} -> 69 | F23: {=INDEX(GMWSCEN!$A$2:$HJ$150,MATCH(1,(GMWSCEN!$HI$2:$HI$150=F$3)*(GMWSCEN!$HJ$2:$HJ$150=F$1),0),$B23-1973)} -> 34820 | G23: {=INDEX(GMWSCEN!$A$2:$HJ$150,MATCH(1,(GMWSCEN!$HI$2:$HI$150=G$3)*(GMWSCEN!$HJ$2:$HJ$150=G$1),0),$B23-1973)} -> 2816 | H23: {=INDEX(GMWSCEN!$A$2:$HJ$150,MATCH(1,(GMWSCEN!$HI$2:$HI$150=H$3)*(GMWSCEN!$HJ$2:$HJ$150=H$1),0),$B23-1973)} -> 3644 | I23: {=INDEX(GMWSCEN!$A$2:$HJ$150,MATCH(1,(GMWSCEN!$HI$2:$HI$150=I$3)*(GMWSCEN!$HJ$2:$HJ$150=I$1),0),$B23-1973)} -> 38533 | J23: {=INDEX(GMWSCEN!$A$2:$HJ$150,MATCH(1,(GMWSCEN!$HI$2:$HI$150=J$3)*(GMWSCEN!$HJ$2:$HJ$150=J$1),0),$B23-1973)} -> 97493.3 | ... BV23: {=INDEX(GMWSCEN!$A$2:$HJ$150,MATCH(1,(GMWSCEN!$HI$2:$HI$150=BV$3)*(GMWSCEN!$HJ$2:$HJ$150=BV$1),0),$B23-1973)} -> -0.4833221 | BY23: =+BY19+1 -> 1983 | BZ23: =BY23&"01" -> 198301 | CB23: =+CB22+1 -> 1996 | CC23: =+CC22+100 -> 199601 | CD23: =SUMIF($BY$7:$BY$206,$CB23,C$7:C$206) -> 1404762 | CE23: =SUMIF($BY$7:$BY$206,$CB23,D$7:D$206) -> 27976 | CF23: =SUMIF($BY$7:$BY$206,$CB23,E$7:E$206) -> -25625 | CG23: =SUMIF($BY$7:$BY$206,$CB23,F$7:F$206) -> 303467 | CH23: =SUMIF($BY$7:$BY$206,$CB23,G$7:G$206) -> 3299 | CI23: =SUMIF($BY$7:$BY$206,$CB23,H$7:H$206) -> 21669 | CJ23: =SUMIF($BY$7:$BY$206,$CB23,I$7:I$206) -> 299511 | CK23: =SUMIF($BZ$7:$BZ$206,$CC23,J$7:J$206) -> 347000 | CL23: =SUMIF($BY$7:$BY$206,$CB23,K$7:K$206) -> 921289 | CM23: =SUMIF($BY$7:$BY$206,$CB23,L$7:L$206) -> 1422150.3 | CN23: =AVERAGEIF($BY$7:$BY$206,$CB23,M$7:M$206) -> 65.587415 | CO23: =AVERAGEIF($BY$7:$BY$206,$CB23,N$7:N$206) -> 69.133335 | CP23: =AVERAGEIF($BY$7:$BY$206,$CB23,O$7:O$206) -> 5.8125 | CQ23: =SUMIF($BY$7:$BY$206,$CB23,P$7:P$206) -> 125033 | CR23: =AVERAGEIF($BY$7:$BY$206,$CB23,Q$7:Q$206) -> 80.95 | CS23: =SUMIF($BY$7:$BY$206,$CB23,R$7:R$206) -> 113358 | CT23: =AVERAGEIF($BY$7:$BY$206,$CB23,S$7:S$206) -> 7.875 | CU23: =SUMIF($BZ$7:$BZ$206,$CC23,T$7:T$206) -> -0.1859665 | CV23: =SUMIF($BY$7:$BY$206,$CB23,U$7:U$206) -> 1404762 | CW23: =SUMIF($BY$7:$BY$206,$CB23,V$7:V$206) -> 27976 | CX23: =SUMIF($BY$7:$BY$206,$CB23,W$7:W$206) -> -25625 | CY23: =SUMIF($BY$7:$BY$206,$CB23,X$7:X$206) -> 303467 | CZ23: =SUMIF($BY$7:$BY$206,$CB23,Y$7:Y$206) -> 3299 | DA23: =SUMIF($BY$7:$BY$206,$CB23,Z$7:Z$206) -> 21669 | DB23: =SUMIF($BY$7:$BY$206,$CB23,AA$7:AA$206) -> 299511 | DC23: =SUMIF($BZ$7:$BZ$206,$CC23,AB$7:AB$206) -> 347000 | DD23: =SUMIF($BY$7:$BY$206,$CB23,AC$7:AC$206) -> 921289 | DE23: =SUMIF($BY$7:$BY$206,$CB23,AD$7:AD$206) -> 1422150.3 | DF23: =AVERAGEIF($BY$7:$BY$206,$CB23,AE$7:AE$206) -> 65.587415 | DG23: =AVERAGEIF($BY$7:$BY$206,$CB23,AF$7:AF$206) -> 69.133335 | DH23: =AVERAGEIF($BY$7:$BY$206,$CB23,AG$7:AG$206) -> 5.8125 | DI23: =SUMIF($BY$7:$BY$206,$CB23,AH$7:AH$206) -> 125033 | DJ23: =AVERAGEIF($BY$7:$BY$206,$CB23,AI$7:AI$206) -> 80.95 | DK23: =SUMIF($BY$7:$BY$206,$CB23,AJ$7:AJ$206) -> 113358 | DL23: =AVERAGEIF($BY$7:$BY$206,$CB23,AK$7:AK$206) -> 7.875 | DM23: =SUMIF($BZ$7:$BZ$206,$CC23,AL$7:AL$206) -> -0.1859665 | DN23: =SUMIF($BY$7:$BY$206,$CB23,AM$7:AM$206) -> 1404762 | DO23: =SUMIF($BY$7:$BY$206,$CB23,AN$7:AN$206) -> 27976 | DP23: =SUMIF($BY$7:$BY$206,$CB23,AO$7:AO$206) -> -25625 | DQ23: =SUMIF($BY$7:$BY$206,$CB23,AP$7:AP$206) -> 303467 | DR23: =SUMIF($BY$7:$BY$206,$CB23,AQ$7:AQ$206) -> 3299 | DS23: =SUMIF($BY$7:$BY$206,$CB23,AR$7:AR$206) -> 21669 | DT23: =SUMIF($BY$7:$BY$206,$CB23,AS$7:AS$206) -> 299511 | DU23: =SUMIF($BZ$7:$BZ$206,$CC23,AT$7:AT$206) -> 347000 | DV23: =SUMIF($BY$7:$BY$206,$CB23,AU$7:AU$206) -> 921289 | DW23: =SUMIF($BY$7:$BY$206,$CB23,AV$7:AV$206) -> 1422150.3 | DX23: =AVERAGEIF($BY$7:$BY$206,$CB23,AW$7:AW$206) -> 65.587415 | DY23: =AVERAGEIF($BY$7:$BY$206,$CB23,AX$7:AX$206) -> 69.133335 | DZ23: =AVERAGEIF($BY$7:$BY$206,$CB23,AY$7:AY$206) -> 5.8125 | EA23: =SUMIF($BY$7:$BY$206,$CB23,AZ$7:AZ$206) -> 125033 | EB23: =AVERAGEIF($BY$7:$BY$206,$CB23,BA$7:BA$206) -> 80.95 | EC23: =SUMIF($BY$7:$BY$206,$CB23,BB$7:BB$206) -> 113358 | ED23: =AVERAGEIF($BY$7:$BY$206,$CB23,BC$7:BC$206) -> 7.875 | EE23: =SUMIF($BZ$7:$BZ$206,$CC23,BD$7:BD$206) -> -0.1859665 | EF23: =SUMIF($BY$7:$BY$206,$CB23,BE$7:BE$206) -> 1404762 | EG23: =SUMIF($BY$7:$BY$206,$CB23,BF$7:BF$206) -> 27976 | EH23: =SUMIF($BY$7:$BY$206,$CB23,BG$7:BG$206) -> -25625 | EI23: =SUMIF($BY$7:$BY$206,$CB23,BH$7:BH$206) -> 303467 | EJ23: =SUMIF($BY$7:$BY$206,$CB23,BI$7:BI$206) -> 3299 | EK23: =SUMIF($BY$7:$BY$206,$CB23,BJ$7:BJ$206) -> 21669 | EL23: =SUMIF($BY$7:$BY$206,$CB23,BK$7:BK$206) -> 299511 | EM23: =SUMIF($BZ$7:$BZ$206,$CC23,BL$7:BL$206) -> 347000 | EN23: =SUMIF($BY$7:$BY$206,$CB23,BM$7:BM$206) -> 921289 | EO23: =SUMIF($BY$7:$BY$206,$CB23,BN$7:BN$206) -> 1422150.3 | EP23: =AVERAGEIF($BY$7:$BY$206,$CB23,BO$7:BO$206) -> 65.587415 | EQ23: =AVERAGEIF($BY$7:$BY$206,$CB23,BP$7:BP$206) -> 69.133335 | ER23: =AVERAGEIF($BY$7:$BY$206,$CB23,BQ$7:BQ$206) -> 5.8125 | ES23: =SUMIF($BY$7:$BY$206,$CB23,BR$7:BR$206) -> 125033 | ET23: =AVERAGEIF($BY$7:$BY$206,$CB23,BS$7:BS$206) -> 80.95 | EU23: =SUMIF($BY$7:$BY$206,$CB23,BT$7:BT$206) -> 113358 | EV23: =AVERAGEIF($BY$7:$BY$206,$CB23,BU$7:BU$206) -> 7.875 | EW23: =SUMIF($BZ$7:$BZ$206,$CC23,BV$7:BV$206) -> -0.1859665
B24: =+B23+1 -> 1997 | C24: {=INDEX(GMWSCEN!$A$2:$HJ$150,MATCH(1,(GMWSCEN!$HI$2:$HI$150=C$3)*(GMWSCEN!$HJ$2:$HJ$150=C$1),0),$B24-1973)} -> 255100 | D24: {=INDEX(GMWSCEN!$A$2:$HJ$150,MATCH(1,(GMWSCEN!$HI$2:$HI$150=D$3)*(GMWSCEN!$HJ$2:$HJ$150=D$1),0),$B24-1973)} -> 4927 | E24: {=INDEX(GMWSCEN!$A$2:$HJ$150,MATCH(1,(GMWSCEN!$HI$2:$HI$150=E$3)*(GMWSCEN!$HJ$2:$HJ$150=E$1),0),$B24-1973)} -> -4056 | F24: {=INDEX(GMWSCEN!$A$2:$HJ$150,MATCH(1,(GMWSCEN!$HI$2:$HI$150=F$3)*(GMWSCEN!$HJ$2:$HJ$150=F$1),0),$B24-1973)} -> 33897 | G24: {=INDEX(GMWSCEN!$A$2:$HJ$150,MATCH(1,(GMWSCEN!$HI$2:$HI$150=G$3)*(GMWSCEN!$HJ$2:$HJ$150=G$1),0),$B24-1973)} -> 871 | H24: {=INDEX(GMWSCEN!$A$2:$HJ$150,MATCH(1,(GMWSCEN!$HI$2:$HI$150=H$3)*(GMWSCEN!$HJ$2:$HJ$150=H$1),0),$B24-1973)} -> 3709 | I24: {=INDEX(GMWSCEN!$A$2:$HJ$150,MATCH(1,(GMWSCEN!$HI$2:$HI$150=I$3)*(GMWSCEN!$HJ$2:$HJ$150=I$1),0),$B24-1973)} -> 33550 | J24: {=INDEX(GMWSCEN!$A$2:$HJ$150,MATCH(1,(GMWSCEN!$HI$2:$HI$150=J$3)*(GMWSCEN!$HJ$2:$HJ$150=J$1),0),$B24-1973)} -> 91452.49 | ... BV24: {=INDEX(GMWSCEN!$A$2:$HJ$150,MATCH(1,(GMWSCEN!$HI$2:$HI$150=BV$3)*(GMWSCEN!$HJ$2:$HJ$150=BV$1),0),$B24-1973)} -> -2.319431 | BY24: =+BY20+1 -> 1984 | CB24: =+CB23+1 -> 1997 | CC24: =+CC23+100 -> 199701 | CD24: =SUMIF($BY$7:$BY$206,$CB24,C$7:C$206) -> 1473893 | CE24: =SUMIF($BY$7:$BY$206,$CB24,D$7:D$206) -> 10505 | CF24: =SUMIF($BY$7:$BY$206,$CB24,E$7:E$206) -> -5700 | CG24: =SUMIF($BY$7:$BY$206,$CB24,F$7:F$206) -> 317368 | CH24: =SUMIF($BY$7:$BY$206,$CB24,G$7:G$206) -> 4805 | CI24: =SUMIF($BY$7:$BY$206,$CB24,H$7:H$206) -> 22347 | CJ24: =SUMIF($BY$7:$BY$206,$CB24,I$7:I$206) -> 334015 | CK24: =SUMIF($BZ$7:$BZ$206,$CC24,J$7:J$206) -> 360400 | CL24: =SUMIF($BY$7:$BY$206,$CB24,K$7:K$206) -> 966520 | CM24: =SUMIF($BY$7:$BY$206,$CB24,L$7:L$206) -> 1459562.7 | CN24: =AVERAGEIF($BY$7:$BY$206,$CB24,M$7:M$206) -> 65.576262 | CO24: =AVERAGEIF($BY$7:$BY$206,$CB24,N$7:N$206) -> 70.35 | CP24: =AVERAGEIF($BY$7:$BY$206,$CB24,O$7:O$206) -> 7 | CQ24: =SUMIF($BY$7:$BY$206,$CB24,P$7:P$206) -> 132013 | CR24: =AVERAGEIF($BY$7:$BY$206,$CB24,Q$7:Q$206) -> 84.5 | CS24: =SUMIF($BY$7:$BY$206,$CB24,R$7:R$206) -> 117858 | CT24: =AVERAGEIF($BY$7:$BY$206,$CB24,S$7:S$206) -> 6.725 | CU24: =SUMIF($BZ$7:$BZ$206,$CC24,T$7:T$206) -> 1.711941 | CV24: =SUMIF($BY$7:$BY$206,$CB24,U$7:U$206) -> 1473893 | CW24: =SUMIF($BY$7:$BY$206,$CB24,V$7:V$206) -> 10505 | CX24: =SUMIF($BY$7:$BY$206,$CB24,W$7:W$206) -> -5700 | CY24: =SUMIF($BY$7:$BY$206,$CB24,X$7:X$206) -> 317368 | CZ24: =SUMIF($BY$7:$BY$206,$CB24,Y$7:Y$206) -> 4805 | DA24: =SUMIF($BY$7:$BY$206,$CB24,Z$7:Z$206) -> 22347 | DB24: =SUMIF($BY$7:$BY$206,$CB24,AA$7:AA$206) -> 334015 | DC24: =SUMIF($BZ$7:$BZ$206,$CC24,AB$7:AB$206) -> 360400 | DD24: =SUMIF($BY$7:$BY$206,$CB24,AC$7:AC$206) -> 966520 | DE24: =SUMIF($BY$7:$BY$206,$CB24,AD$7:AD$206) -> 1459562.7 | DF24: =AVERAGEIF($BY$7:$BY$206,$CB24,AE$7:AE$206) -> 65.576262 | DG24: =AVERAGEIF($BY$7:$BY$206,$CB24,AF$7:AF$206) -> 70.35 | DH24: =AVERAGEIF($BY$7:$BY$206,$CB24,AG$7:AG$206) -> 7 | DI24: =SUMIF($BY$7:$BY$206,$CB24,AH$7:AH$206) -> 132013 | DJ24: =AVERAGEIF($BY$7:$BY$206,$CB24,AI$7:AI$206) -> 84.5 | DK24: =SUMIF($BY$7:$BY$206,$CB24,AJ$7:AJ$206) -> 117858 | DL24: =AVERAGEIF($BY$7:$BY$206,$CB24,AK$7:AK$206) -> 6.725 | DM24: =SUMIF($BZ$7:$BZ$206,$CC24,AL$7:AL$206) -> 1.711941 | DN24: =SUMIF($BY$7:$BY$206,$CB24,AM$7:AM$206) -> 1473893 | DO24: =SUMIF($BY$7:$BY$206,$CB24,AN$7:AN$206) -> 10505 | DP24: =SUMIF($BY$7:$BY$206,$CB24,AO$7:AO$206) -> -5700 | DQ24: =SUMIF($BY$7:$BY$206,$CB24,AP$7:AP$206) -> 317368 | DR24: =SUMIF($BY$7:$BY$206,$CB24,AQ$7:AQ$206) -> 4805 | DS24: =SUMIF($BY$7:$BY$206,$CB24,AR$7:AR$206) -> 22347 | DT24: =SUMIF($BY$7:$BY$206,$CB24,AS$7:AS$206) -> 334015 | DU24: =SUMIF($BZ$7:$BZ$206,$CC24,AT$7:AT$206) -> 360400 | DV24: =SUMIF($BY$7:$BY$206,$CB24,AU$7:AU$206) -> 966520 | DW24: =SUMIF($BY$7:$BY$206,$CB24,AV$7:AV$206) -> 1459562.7 | DX24: =AVERAGEIF($BY$7:$BY$206,$CB24,AW$7:AW$206) -> 65.576262 | DY24: =AVERAGEIF($BY$7:$BY$206,$CB24,AX$7:AX$206) -> 70.35 | DZ24: =AVERAGEIF($BY$7:$BY$206,$CB24,AY$7:AY$206) -> 7 | EA24: =SUMIF($BY$7:$BY$206,$CB24,AZ$7:AZ$206) -> 132013 | EB24: =AVERAGEIF($BY$7:$BY$206,$CB24,BA$7:BA$206) -> 84.5 | EC24: =SUMIF($BY$7:$BY$206,$CB24,BB$7:BB$206) -> 117858 | ED24: =AVERAGEIF($BY$7:$BY$206,$CB24,BC$7:BC$206) -> 6.725 | EE24: =SUMIF($BZ$7:$BZ$206,$CC24,BD$7:BD$206) -> 1.711941 | EF24: =SUMIF($BY$7:$BY$206,$CB24,BE$7:BE$206) -> 1473893 | EG24: =SUMIF($BY$7:$BY$206,$CB24,BF$7:BF$206) -> 10505 | EH24: =SUMIF($BY$7:$BY$206,$CB24,BG$7:BG$206) -> -5700 | EI24: =SUMIF($BY$7:$BY$206,$CB24,BH$7:BH$206) -> 317368 | EJ24: =SUMIF($BY$7:$BY$206,$CB24,BI$7:BI$206) -> 4805 | EK24: =SUMIF($BY$7:$BY$206,$CB24,BJ$7:BJ$206) -> 22347 | EL24: =SUMIF($BY$7:$BY$206,$CB24,BK$7:BK$206) -> 334015 | EM24: =SUMIF($BZ$7:$BZ$206,$CC24,BL$7:BL$206) -> 360400 | EN24: =SUMIF($BY$7:$BY$206,$CB24,BM$7:BM$206) -> 966520 | EO24: =SUMIF($BY$7:$BY$206,$CB24,BN$7:BN$206) -> 1459562.7 | EP24: =AVERAGEIF($BY$7:$BY$206,$CB24,BO$7:BO$206) -> 65.576262 | EQ24: =AVERAGEIF($BY$7:$BY$206,$CB24,BP$7:BP$206) -> 70.35 | ER24: =AVERAGEIF($BY$7:$BY$206,$CB24,BQ$7:BQ$206) -> 7 | ES24: =SUMIF($BY$7:$BY$206,$CB24,BR$7:BR$206) -> 132013 | ET24: =AVERAGEIF($BY$7:$BY$206,$CB24,BS$7:BS$206) -> 84.5 | EU24: =SUMIF($BY$7:$BY$206,$CB24,BT$7:BT$206) -> 117858 | EV24: =AVERAGEIF($BY$7:$BY$206,$CB24,BU$7:BU$206) -> 6.725 | EW24: =SUMIF($BZ$7:$BZ$206,$CC24,BV$7:BV$206) -> 1.711941
B25: =+B24+1 -> 1998 | C25: {=INDEX(GMWSCEN!$A$2:$HJ$150,MATCH(1,(GMWSCEN!$HI$2:$HI$150=C$3)*(GMWSCEN!$HJ$2:$HJ$150=C$1),0),$B25-1973)} -> 256975 | D25: {=INDEX(GMWSCEN!$A$2:$HJ$150,MATCH(1,(GMWSCEN!$HI$2:$HI$150=D$3)*(GMWSCEN!$HJ$2:$HJ$150=D$1),0),$B25-1973)} -> 2934 | E25: {=INDEX(GMWSCEN!$A$2:$HJ$150,MATCH(1,(GMWSCEN!$HI$2:$HI$150=E$3)*(GMWSCEN!$HJ$2:$HJ$150=E$1),0),$B25-1973)} -> -1335 | F25: {=INDEX(GMWSCEN!$A$2:$HJ$150,MATCH(1,(GMWSCEN!$HI$2:$HI$150=F$3)*(GMWSCEN!$HJ$2:$HJ$150=F$1),0),$B25-1973)} -> 34360 | G25: {=INDEX(GMWSCEN!$A$2:$HJ$150,MATCH(1,(GMWSCEN!$HI$2:$HI$150=G$3)*(GMWSCEN!$HJ$2:$HJ$150=G$1),0),$B25-1973)} -> 1599 | H25: {=INDEX(GMWSCEN!$A$2:$HJ$150,MATCH(1,(GMWSCEN!$HI$2:$HI$150=H$3)*(GMWSCEN!$HJ$2:$HJ$150=H$1),0),$B25-1973)} -> 3776 | I25: {=INDEX(GMWSCEN!$A$2:$HJ$150,MATCH(1,(GMWSCEN!$HI$2:$HI$150=I$3)*(GMWSCEN!$HJ$2:$HJ$150=I$1),0),$B25-1973)} -> 36801 | J25: {=INDEX(GMWSCEN!$A$2:$HJ$150,MATCH(1,(GMWSCEN!$HI$2:$HI$150=J$3)*(GMWSCEN!$HJ$2:$HJ$150=J$1),0),$B25-1973)} -> 90897.73 | ... BV25: {=INDEX(GMWSCEN!$A$2:$HJ$150,MATCH(1,(GMWSCEN!$HI$2:$HI$150=BV$3)*(GMWSCEN!$HJ$2:$HJ$150=BV$1),0),$B25-1973)} -> -2.290058 | BY25: =+BY21+1 -> 1984 | CB25: =+CB24+1 -> 1998 | CC25: =+CC24+100 -> 199801 | CD25: =SUMIF($BY$7:$BY$206,$CB25,C$7:C$206) -> 1517015 | CE25: =SUMIF($BY$7:$BY$206,$CB25,D$7:D$206) -> 274 | CF25: =SUMIF($BY$7:$BY$206,$CB25,E$7:E$206) -> 4899 | CG25: =SUMIF($BY$7:$BY$206,$CB25,F$7:F$206) -> 327095 | CH25: =SUMIF($BY$7:$BY$206,$CB25,G$7:G$206) -> 5173 | CI25: =SUMIF($BY$7:$BY$206,$CB25,H$7:H$206) -> 23011 | CJ25: =SUMIF($BY$7:$BY$206,$CB25,I$7:I$206) -> 355005 | CK25: =SUMIF($BZ$7:$BZ$206,$CC25,J$7:J$206) -> 363100 | CL25: =SUMIF($BY$7:$BY$206,$CB25,K$7:K$206) -> 1008430 | CM25: =SUMIF($BY$7:$BY$206,$CB25,L$7:L$206) -> 1490682.5 | CN25: =AVERAGEIF($BY$7:$BY$206,$CB25,M$7:M$206) -> 66.472503 | CO25: =AVERAGEIF($BY$7:$BY$206,$CB25,N$7:N$206) -> 71.433333 | CP25: =AVERAGEIF($BY$7:$BY$206,$CB25,O$7:O$206) -> 6.6875 | CQ25: =SUMIF($BY$7:$BY$206,$CB25,P$7:P$206) -> 137869 | CR25: =AVERAGEIF($BY$7:$BY$206,$CB25,Q$7:Q$206) -> 87.575 | CS25: =SUMIF($BY$7:$BY$206,$CB25,R$7:R$206) -> 121862 | CT25: =AVERAGEIF($BY$7:$BY$206,$CB25,S$7:S$206) -> 6.2 | CU25: =SUMIF($BZ$7:$BZ$206,$CC25,T$7:T$206) -> 1.710224 | CV25: =SUMIF($BY$7:$BY$206,$CB25,U$7:U$206) -> 1517015 | CW25: =SUMIF($BY$7:$BY$206,$CB25,V$7:V$206) -> 274 | CX25: =SUMIF($BY$7:$BY$206,$CB25,W$7:W$206) -> 4899 | CY25: =SUMIF($BY$7:$BY$206,$CB25,X$7:X$206) -> 327095 | CZ25: =SUMIF($BY$7:$BY$206,$CB25,Y$7:Y$206) -> 5173 | DA25: =SUMIF($BY$7:$BY$206,$CB25,Z$7:Z$206) -> 23011 | DB25: =SUMIF($BY$7:$BY$206,$CB25,AA$7:AA$206) -> 355005 | DC25: =SUMIF($BZ$7:$BZ$206,$CC25,AB$7:AB$206) -> 363100 | DD25: =SUMIF($BY$7:$BY$206,$CB25,AC$7:AC$206) -> 1008430 | DE25: =SUMIF($BY$7:$BY$206,$CB25,AD$7:AD$206) -> 1490682.5 | DF25: =AVERAGEIF($BY$7:$BY$206,$CB25,AE$7:AE$206) -> 66.472503 | DG25: =AVERAGEIF($BY$7:$BY$206,$CB25,AF$7:AF$206) -> 71.433333 | DH25: =AVERAGEIF($BY$7:$BY$206,$CB25,AG$7:AG$206) -> 6.6875 | DI25: =SUMIF($BY$7:$BY$206,$CB25,AH$7:AH$206) -> 137869 | DJ25: =AVERAGEIF($BY$7:$BY$206,$CB25,AI$7:AI$206) -> 87.575 | DK25: =SUMIF($BY$7:$BY$206,$CB25,AJ$7:AJ$206) -> 121862 | DL25: =AVERAGEIF($BY$7:$BY$206,$CB25,AK$7:AK$206) -> 6.2 | DM25: =SUMIF($BZ$7:$BZ$206,$CC25,AL$7:AL$206) -> 1.710224 | DN25: =SUMIF($BY$7:$BY$206,$CB25,AM$7:AM$206) -> 1517015 | DO25: =SUMIF($BY$7:$BY$206,$CB25,AN$7:AN$206) -> 274 | DP25: =SUMIF($BY$7:$BY$206,$CB25,AO$7:AO$206) -> 4899 | DQ25: =SUMIF($BY$7:$BY$206,$CB25,AP$7:AP$206) -> 327095 | DR25: =SUMIF($BY$7:$BY$206,$CB25,AQ$7:AQ$206) -> 5173 | DS25: =SUMIF($BY$7:$BY$206,$CB25,AR$7:AR$206) -> 23011 | DT25: =SUMIF($BY$7:$BY$206,$CB25,AS$7:AS$206) -> 355005 | DU25: =SUMIF($BZ$7:$BZ$206,$CC25,AT$7:AT$206) -> 363100 | DV25: =SUMIF($BY$7:$BY$206,$CB25,AU$7:AU$206) -> 1008430 | DW25: =SUMIF($BY$7:$BY$206,$CB25,AV$7:AV$206) -> 1490682.5 | DX25: =AVERAGEIF($BY$7:$BY$206,$CB25,AW$7:AW$206) -> 66.472503 | DY25: =AVERAGEIF($BY$7:$BY$206,$CB25,AX$7:AX$206) -> 71.433333 | DZ25: =AVERAGEIF($BY$7:$BY$206,$CB25,AY$7:AY$206) -> 6.6875 | EA25: =SUMIF($BY$7:$BY$206,$CB25,AZ$7:AZ$206) -> 137869 | EB25: =AVERAGEIF($BY$7:$BY$206,$CB25,BA$7:BA$206) -> 87.575 | EC25: =SUMIF($BY$7:$BY$206,$CB25,BB$7:BB$206) -> 121862 | ED25: =AVERAGEIF($BY$7:$BY$206,$CB25,BC$7:BC$206) -> 6.2 | EE25: =SUMIF($BZ$7:$BZ$206,$CC25,BD$7:BD$206) -> 1.710224 | EF25: =SUMIF($BY$7:$BY$206,$CB25,BE$7:BE$206) -> 1517015 | EG25: =SUMIF($BY$7:$BY$206,$CB25,BF$7:BF$206) -> 274 | EH25: =SUMIF($BY$7:$BY$206,$CB25,BG$7:BG$206) -> 4899 | EI25: =SUMIF($BY$7:$BY$206,$CB25,BH$7:BH$206) -> 327095 | EJ25: =SUMIF($BY$7:$BY$206,$CB25,BI$7:BI$206) -> 5173 | EK25: =SUMIF($BY$7:$BY$206,$CB25,BJ$7:BJ$206) -> 23011 | EL25: =SUMIF($BY$7:$BY$206,$CB25,BK$7:BK$206) -> 355005 | EM25: =SUMIF($BZ$7:$BZ$206,$CC25,BL$7:BL$206) -> 363100 | EN25: =SUMIF($BY$7:$BY$206,$CB25,BM$7:BM$206) -> 1008430 | EO25: =SUMIF($BY$7:$BY$206,$CB25,BN$7:BN$206) -> 1490682.5 | EP25: =AVERAGEIF($BY$7:$BY$206,$CB25,BO$7:BO$206) -> 66.472503 | EQ25: =AVERAGEIF($BY$7:$BY$206,$CB25,BP$7:BP$206) -> 71.433333 | ER25: =AVERAGEIF($BY$7:$BY$206,$CB25,BQ$7:BQ$206) -> 6.6875 | ES25: =SUMIF($BY$7:$BY$206,$CB25,BR$7:BR$206) -> 137869 | ET25: =AVERAGEIF($BY$7:$BY$206,$CB25,BS$7:BS$206) -> 87.575 | EU25: =SUMIF($BY$7:$BY$206,$CB25,BT$7:BT$206) -> 121862 | EV25: =AVERAGEIF($BY$7:$BY$206,$CB25,BU$7:BU$206) -> 6.2 | EW25: =SUMIF($BZ$7:$BZ$206,$CC25,BV$7:BV$206) -> 1.710224
B26: =+B25+1 -> 1999 | C26: {=INDEX(GMWSCEN!$A$2:$HJ$150,MATCH(1,(GMWSCEN!$HI$2:$HI$150=C$3)*(GMWSCEN!$HJ$2:$HJ$150=C$1),0),$B26-1973)} -> 261627 | D26: {=INDEX(GMWSCEN!$A$2:$HJ$150,MATCH(1,(GMWSCEN!$HI$2:$HI$150=D$3)*(GMWSCEN!$HJ$2:$HJ$150=D$1),0),$B26-1973)} -> 1815 | E26: {=INDEX(GMWSCEN!$A$2:$HJ$150,MATCH(1,(GMWSCEN!$HI$2:$HI$150=E$3)*(GMWSCEN!$HJ$2:$HJ$150=E$1),0),$B26-1973)} -> 174 | F26: {=INDEX(GMWSCEN!$A$2:$HJ$150,MATCH(1,(GMWSCEN!$HI$2:$HI$150=F$3)*(GMWSCEN!$HJ$2:$HJ$150=F$1),0),$B26-1973)} -> 35416 | G26: {=INDEX(GMWSCEN!$A$2:$HJ$150,MATCH(1,(GMWSCEN!$HI$2:$HI$150=G$3)*(GMWSCEN!$HJ$2:$HJ$150=G$1),0),$B26-1973)} -> 1989 | H26: {=INDEX(GMWSCEN!$A$2:$HJ$150,MATCH(1,(GMWSCEN!$HI$2:$HI$150=H$3)*(GMWSCEN!$HJ$2:$HJ$150=H$1),0),$B26-1973)} -> 3688 | I26: {=INDEX(GMWSCEN!$A$2:$HJ$150,MATCH(1,(GMWSCEN!$HI$2:$HI$150=I$3)*(GMWSCEN!$HJ$2:$HJ$150=I$1),0),$B26-1973)} -> 39278 | J26: {=INDEX(GMWSCEN!$A$2:$HJ$150,MATCH(1,(GMWSCEN!$HI$2:$HI$150=J$3)*(GMWSCEN!$HJ$2:$HJ$150=J$1),0),$B26-1973)} -> 95829.01 | ... BV26: {=INDEX(GMWSCEN!$A$2:$HJ$150,MATCH(1,(GMWSCEN!$HI$2:$HI$150=BV$3)*(GMWSCEN!$HJ$2:$HJ$150=BV$1),0),$B26-1973)} -> -1.244831 | BY26: =+BY22+1 -> 1984 | CB26: =+CB25+1 -> 1999 | CC26: =+CC25+100 -> 199901 | CD26: =SUMIF($BY$7:$BY$206,$CB26,C$7:C$206) -> 1572962 | CE26: =SUMIF($BY$7:$BY$206,$CB26,D$7:D$206) -> -11040 | CF26: =SUMIF($BY$7:$BY$206,$CB26,E$7:E$206) -> 15952 | CG26: =SUMIF($BY$7:$BY$206,$CB26,F$7:F$206) -> 338782 | CH26: =SUMIF($BY$7:$BY$206,$CB26,G$7:G$206) -> 4912 | CI26: =SUMIF($BY$7:$BY$206,$CB26,H$7:H$206) -> 24191 | CJ26: =SUMIF($BY$7:$BY$206,$CB26,I$7:I$206) -> 378925 | CK26: =SUMIF($BZ$7:$BZ$206,$CC26,J$7:J$206) -> 353300 | CL26: =SUMIF($BY$7:$BY$206,$CB26,K$7:K$206) -> 1059608 | CM26: =SUMIF($BY$7:$BY$206,$CB26,L$7:L$206) -> 1531755.8 | CN26: =AVERAGEIF($BY$7:$BY$206,$CB26,M$7:M$206) -> 67.35935 | CO26: =AVERAGEIF($BY$7:$BY$206,$CB26,N$7:N$206) -> 72.249998 | CP26: =AVERAGEIF($BY$7:$BY$206,$CB26,O$7:O$206) -> 5.4375 | CQ26: =SUMIF($BY$7:$BY$206,$CB26,P$7:P$206) -> 144940 | CR26: =AVERAGEIF($BY$7:$BY$206,$CB26,Q$7:Q$206) -> 91.7 | CS26: =SUMIF($BY$7:$BY$206,$CB26,R$7:R$206) -> 128826 | CT26: =AVERAGEIF($BY$7:$BY$206,$CB26,S$7:S$206) -> 5.875 | CU26: =SUMIF($BZ$7:$BZ$206,$CC26,T$7:T$206) -> 4.159451 | CV26: =SUMIF($BY$7:$BY$206,$CB26,U$7:U$206) -> 1572962 | CW26: =SUMIF($BY$7:$BY$206,$CB26,V$7:V$206) -> -11040 | CX26: =SUMIF($BY$7:$BY$206,$CB26,W$7:W$206) -> 15952 | CY26: =SUMIF($BY$7:$BY$206,$CB26,X$7:X$206) -> 338782 | CZ26: =SUMIF($BY$7:$BY$206,$CB26,Y$7:Y$206) -> 4912 | DA26: =SUMIF($BY$7:$BY$206,$CB26,Z$7:Z$206) -> 24191 | DB26: =SUMIF($BY$7:$BY$206,$CB26,AA$7:AA$206) -> 378925 | DC26: =SUMIF($BZ$7:$BZ$206,$CC26,AB$7:AB$206) -> 353300 | DD26: =SUMIF($BY$7:$BY$206,$CB26,AC$7:AC$206) -> 1059608 | DE26: =SUMIF($BY$7:$BY$206,$CB26,AD$7:AD$206) -> 1531755.8 | DF26: =AVERAGEIF($BY$7:$BY$206,$CB26,AE$7:AE$206) -> 67.35935 | DG26: =AVERAGEIF($BY$7:$BY$206,$CB26,AF$7:AF$206) -> 72.249998 | DH26: =AVERAGEIF($BY$7:$BY$206,$CB26,AG$7:AG$206) -> 5.4375 | DI26: =SUMIF($BY$7:$BY$206,$CB26,AH$7:AH$206) -> 144940 | DJ26: =AVERAGEIF($BY$7:$BY$206,$CB26,AI$7:AI$206) -> 91.7 | DK26: =SUMIF($BY$7:$BY$206,$CB26,AJ$7:AJ$206) -> 128826 | DL26: =AVERAGEIF($BY$7:$BY$206,$CB26,AK$7:AK$206) -> 5.875 | DM26: =SUMIF($BZ$7:$BZ$206,$CC26,AL$7:AL$206) -> 4.159451 | DN26: =SUMIF($BY$7:$BY$206,$CB26,AM$7:AM$206) -> 1572962 | DO26: =SUMIF($BY$7:$BY$206,$CB26,AN$7:AN$206) -> -11040 | DP26: =SUMIF($BY$7:$BY$206,$CB26,AO$7:AO$206) -> 15952 | DQ26: =SUMIF($BY$7:$BY$206,$CB26,AP$7:AP$206) -> 338782 | DR26: =SUMIF($BY$7:$BY$206,$CB26,AQ$7:AQ$206) -> 4912 | DS26: =SUMIF($BY$7:$BY$206,$CB26,AR$7:AR$206) -> 24191 | DT26: =SUMIF($BY$7:$BY$206,$CB26,AS$7:AS$206) -> 378925 | DU26: =SUMIF($BZ$7:$BZ$206,$CC26,AT$7:AT$206) -> 353300 | DV26: =SUMIF($BY$7:$BY$206,$CB26,AU$7:AU$206) -> 1059608 | DW26: =SUMIF($BY$7:$BY$206,$CB26,AV$7:AV$206) -> 1531755.8 | DX26: =AVERAGEIF($BY$7:$BY$206,$CB26,AW$7:AW$206) -> 67.35935 | DY26: =AVERAGEIF($BY$7:$BY$206,$CB26,AX$7:AX$206) -> 72.249998 | DZ26: =AVERAGEIF($BY$7:$BY$206,$CB26,AY$7:AY$206) -> 5.4375 | EA26: =SUMIF($BY$7:$BY$206,$CB26,AZ$7:AZ$206) -> 144940 | EB26: =AVERAGEIF($BY$7:$BY$206,$CB26,BA$7:BA$206) -> 91.7 | EC26: =SUMIF($BY$7:$BY$206,$CB26,BB$7:BB$206) -> 128826 | ED26: =AVERAGEIF($BY$7:$BY$206,$CB26,BC$7:BC$206) -> 5.875 | EE26: =SUMIF($BZ$7:$BZ$206,$CC26,BD$7:BD$206) -> 4.159451 | EF26: =SUMIF($BY$7:$BY$206,$CB26,BE$7:BE$206) -> 1572962 | EG26: =SUMIF($BY$7:$BY$206,$CB26,BF$7:BF$206) -> -11040 | EH26: =SUMIF($BY$7:$BY$206,$CB26,BG$7:BG$206) -> 15952 | EI26: =SUMIF($BY$7:$BY$206,$CB26,BH$7:BH$206) -> 338782 | EJ26: =SUMIF($BY$7:$BY$206,$CB26,BI$7:BI$206) -> 4912 | EK26: =SUMIF($BY$7:$BY$206,$CB26,BJ$7:BJ$206) -> 24191 | EL26: =SUMIF($BY$7:$BY$206,$CB26,BK$7:BK$206) -> 378925 | EM26: =SUMIF($BZ$7:$BZ$206,$CC26,BL$7:BL$206) -> 353300 | EN26: =SUMIF($BY$7:$BY$206,$CB26,BM$7:BM$206) -> 1059608 | EO26: =SUMIF($BY$7:$BY$206,$CB26,BN$7:BN$206) -> 1531755.8 | EP26: =AVERAGEIF($BY$7:$BY$206,$CB26,BO$7:BO$206) -> 67.35935 | EQ26: =AVERAGEIF($BY$7:$BY$206,$CB26,BP$7:BP$206) -> 72.249998 | ER26: =AVERAGEIF($BY$7:$BY$206,$CB26,BQ$7:BQ$206) -> 5.4375 | ES26: =SUMIF($BY$7:$BY$206,$CB26,BR$7:BR$206) -> 144940 | ET26: =AVERAGEIF($BY$7:$BY$206,$CB26,BS$7:BS$206) -> 91.7 | EU26: =SUMIF($BY$7:$BY$206,$CB26,BT$7:BT$206) -> 128826 | EV26: =AVERAGEIF($BY$7:$BY$206,$CB26,BU$7:BU$206) -> 5.875 | EW26: =SUMIF($BZ$7:$BZ$206,$CC26,BV$7:BV$206) -> 4.159451
A27: 1985 | B27: =+B26+1 -> 2000 | C27: {=INDEX(GMWSCEN!$A$2:$HJ$150,MATCH(1,(GMWSCEN!$HI$2:$HI$150=C$3)*(GMWSCEN!$HJ$2:$HJ$150=C$1),0),$B27-1973)} -> 264127 | D27: {=INDEX(GMWSCEN!$A$2:$HJ$150,MATCH(1,(GMWSCEN!$HI$2:$HI$150=D$3)*(GMWSCEN!$HJ$2:$HJ$150=D$1),0),$B27-1973)} -> 2859 | E27: {=INDEX(GMWSCEN!$A$2:$HJ$150,MATCH(1,(GMWSCEN!$HI$2:$HI$150=E$3)*(GMWSCEN!$HJ$2:$HJ$150=E$1),0),$B27-1973)} -> 150 | F27: {=INDEX(GMWSCEN!$A$2:$HJ$150,MATCH(1,(GMWSCEN!$HI$2:$HI$150=F$3)*(GMWSCEN!$HJ$2:$HJ$150=F$1),0),$B27-1973)} -> 38146 | G27: {=INDEX(GMWSCEN!$A$2:$HJ$150,MATCH(1,(GMWSCEN!$HI$2:$HI$150=G$3)*(GMWSCEN!$HJ$2:$HJ$150=G$1),0),$B27-1973)} -> 3009 | H27: {=INDEX(GMWSCEN!$A$2:$HJ$150,MATCH(1,(GMWSCEN!$HI$2:$HI$150=H$3)*(GMWSCEN!$HJ$2:$HJ$150=H$1),0),$B27-1973)} -> 3440 | I27: {=INDEX(GMWSCEN!$A$2:$HJ$150,MATCH(1,(GMWSCEN!$HI$2:$HI$150=I$3)*(GMWSCEN!$HJ$2:$HJ$150=I$1),0),$B27-1973)} -> 41736 | J27: {=INDEX(GMWSCEN!$A$2:$HJ$150,MATCH(1,(GMWSCEN!$HI$2:$HI$150=J$3)*(GMWSCEN!$HJ$2:$HJ$150=J$1),0),$B27-1973)} -> 100950.3 | ... BV27: {=INDEX(GMWSCEN!$A$2:$HJ$150,MATCH(1,(GMWSCEN!$HI$2:$HI$150=BV$3)*(GMWSCEN!$HJ$2:$HJ$150=BV$1),0),$B27-1973)} -> -0.9504318 | BY27: =+BY23+1 -> 1984 | BZ27: =BY27&"01" -> 198401 | CB27: =+CB26+1 -> 2000 | CC27: =+CC26+100 -> 200001 | CD27: =SUMIF($BY$7:$BY$206,$CB27,C$7:C$206) -> 1633456 | CE27: =SUMIF($BY$7:$BY$206,$CB27,D$7:D$206) -> -16049 | CF27: =SUMIF($BY$7:$BY$206,$CB27,E$7:E$206) -> 20560 | CG27: =SUMIF($BY$7:$BY$206,$CB27,F$7:F$206) -> 361247 | CH27: =SUMIF($BY$7:$BY$206,$CB27,G$7:G$206) -> 4511 | CI27: =SUMIF($BY$7:$BY$206,$CB27,H$7:H$206) -> 25186 | CJ27: =SUMIF($BY$7:$BY$206,$CB27,I$7:I$206) -> 406993 | CK27: =SUMIF($BZ$7:$BZ$206,$CC27,J$7:J$206) -> 322000 | CL27: =SUMIF($BY$7:$BY$206,$CB27,K$7:K$206) -> 1111547 | CM27: =SUMIF($BY$7:$BY$206,$CB27,L$7:L$206) -> 1575334.5 | CN27: =AVERAGEIF($BY$7:$BY$206,$CB27,M$7:M$206) -> 68.046707 | CO27: =AVERAGEIF($BY$7:$BY$206,$CB27,N$7:N$206) -> 72.85 | CP27: =AVERAGEIF($BY$7:$BY$206,$CB27,O$7:O$206) -> 5.9375 | CQ27: =SUMIF($BY$7:$BY$206,$CB27,P$7:P$206) -> 151906 | CR27: =AVERAGEIF($BY$7:$BY$206,$CB27,Q$7:Q$206) -> 94.075 | CS27: =SUMIF($BY$7:$BY$206,$CB27,R$7:R$206) -> 125945 | CT27: =AVERAGEIF($BY$7:$BY$206,$CB27,S$7:S$206) -> 5.275 | CU27: =SUMIF($BZ$7:$BZ$206,$CC27,T$7:T$206) -> 3.617859 | CV27: =SUMIF($BY$7:$BY$206,$CB27,U$7:U$206) -> 1633456 | CW27: =SUMIF($BY$7:$BY$206,$CB27,V$7:V$206) -> -16049 | CX27: =SUMIF($BY$7:$BY$206,$CB27,W$7:W$206) -> 20560 | CY27: =SUMIF($BY$7:$BY$206,$CB27,X$7:X$206) -> 361247 | CZ27: =SUMIF($BY$7:$BY$206,$CB27,Y$7:Y$206) -> 4511 | DA27: =SUMIF($BY$7:$BY$206,$CB27,Z$7:Z$206) -> 25186 | DB27: =SUMIF($BY$7:$BY$206,$CB27,AA$7:AA$206) -> 406993 | DC27: =SUMIF($BZ$7:$BZ$206,$CC27,AB$7:AB$206) -> 322000 | DD27: =SUMIF($BY$7:$BY$206,$CB27,AC$7:AC$206) -> 1111547 | DE27: =SUMIF($BY$7:$BY$206,$CB27,AD$7:AD$206) -> 1575334.5 | DF27: =AVERAGEIF($BY$7:$BY$206,$CB27,AE$7:AE$206) -> 68.046707 | DG27: =AVERAGEIF($BY$7:$BY$206,$CB27,AF$7:AF$206) -> 72.85 | DH27: =AVERAGEIF($BY$7:$BY$206,$CB27,AG$7:AG$206) -> 5.9375 | DI27: =SUMIF($BY$7:$BY$206,$CB27,AH$7:AH$206) -> 151906 | DJ27: =AVERAGEIF($BY$7:$BY$206,$CB27,AI$7:AI$206) -> 94.075 | DK27: =SUMIF($BY$7:$BY$206,$CB27,AJ$7:AJ$206) -> 125945 | DL27: =AVERAGEIF($BY$7:$BY$206,$CB27,AK$7:AK$206) -> 5.275 | DM27: =SUMIF($BZ$7:$BZ$206,$CC27,AL$7:AL$206) -> 3.617859 | DN27: =SUMIF($BY$7:$BY$206,$CB27,AM$7:AM$206) -> 1633456 | DO27: =SUMIF($BY$7:$BY$206,$CB27,AN$7:AN$206) -> -16049 | DP27: =SUMIF($BY$7:$BY$206,$CB27,AO$7:AO$206) -> 20560 | DQ27: =SUMIF($BY$7:$BY$206,$CB27,AP$7:AP$206) -> 361247 | DR27: =SUMIF($BY$7:$BY$206,$CB27,AQ$7:AQ$206) -> 4511 | DS27: =SUMIF($BY$7:$BY$206,$CB27,AR$7:AR$206) -> 25186 | DT27: =SUMIF($BY$7:$BY$206,$CB27,AS$7:AS$206) -> 406993 | DU27: =SUMIF($BZ$7:$BZ$206,$CC27,AT$7:AT$206) -> 322000 | DV27: =SUMIF($BY$7:$BY$206,$CB27,AU$7:AU$206) -> 1111547 | DW27: =SUMIF($BY$7:$BY$206,$CB27,AV$7:AV$206) -> 1575334.5 | DX27: =AVERAGEIF($BY$7:$BY$206,$CB27,AW$7:AW$206) -> 68.046707 | DY27: =AVERAGEIF($BY$7:$BY$206,$CB27,AX$7:AX$206) -> 72.85 | DZ27: =AVERAGEIF($BY$7:$BY$206,$CB27,AY$7:AY$206) -> 5.9375 | EA27: =SUMIF($BY$7:$BY$206,$CB27,AZ$7:AZ$206) -> 151906 | EB27: =AVERAGEIF($BY$7:$BY$206,$CB27,BA$7:BA$206) -> 94.075 | EC27: =SUMIF($BY$7:$BY$206,$CB27,BB$7:BB$206) -> 125945 | ED27: =AVERAGEIF($BY$7:$BY$206,$CB27,BC$7:BC$206) -> 5.275 | EE27: =SUMIF($BZ$7:$BZ$206,$CC27,BD$7:BD$206) -> 3.617859 | EF27: =SUMIF($BY$7:$BY$206,$CB27,BE$7:BE$206) -> 1633456 | EG27: =SUMIF($BY$7:$BY$206,$CB27,BF$7:BF$206) -> -16049 | EH27: =SUMIF($BY$7:$BY$206,$CB27,BG$7:BG$206) -> 20560 | EI27: =SUMIF($BY$7:$BY$206,$CB27,BH$7:BH$206) -> 361247 | EJ27: =SUMIF($BY$7:$BY$206,$CB27,BI$7:BI$206) -> 4511 | EK27: =SUMIF($BY$7:$BY$206,$CB27,BJ$7:BJ$206) -> 25186 | EL27: =SUMIF($BY$7:$BY$206,$CB27,BK$7:BK$206) -> 406993 | EM27: =SUMIF($BZ$7:$BZ$206,$CC27,BL$7:BL$206) -> 322000 | EN27: =SUMIF($BY$7:$BY$206,$CB27,BM$7:BM$206) -> 1111547 | EO27: =SUMIF($BY$7:$BY$206,$CB27,BN$7:BN$206) -> 1575334.5 | EP27: =AVERAGEIF($BY$7:$BY$206,$CB27,BO$7:BO$206) -> 68.046707 | EQ27: =AVERAGEIF($BY$7:$BY$206,$CB27,BP$7:BP$206) -> 72.85 | ER27: =AVERAGEIF($BY$7:$BY$206,$CB27,BQ$7:BQ$206) -> 5.9375 | ES27: =SUMIF($BY$7:$BY$206,$CB27,BR$7:BR$206) -> 151906 | ET27: =AVERAGEIF($BY$7:$BY$206,$CB27,BS$7:BS$206) -> 94.075 | EU27: =SUMIF($BY$7:$BY$206,$CB27,BT$7:BT$206) -> 125945 | EV27: =AVERAGEIF($BY$7:$BY$206,$CB27,BU$7:BU$206) -> 5.275 | EW27: =SUMIF($BZ$7:$BZ$206,$CC27,BV$7:BV$206) -> 3.617859
B28: =+B27+1 -> 2001 | C28: {=INDEX(GMWSCEN!$A$2:$HJ$150,MATCH(1,(GMWSCEN!$HI$2:$HI$150=C$3)*(GMWSCEN!$HJ$2:$HJ$150=C$1),0),$B28-1973)} -> 269787 | D28: {=INDEX(GMWSCEN!$A$2:$HJ$150,MATCH(1,(GMWSCEN!$HI$2:$HI$150=D$3)*(GMWSCEN!$HJ$2:$HJ$150=D$1),0),$B28-1973)} -> 4910 | E28: {=INDEX(GMWSCEN!$A$2:$HJ$150,MATCH(1,(GMWSCEN!$HI$2:$HI$150=E$3)*(GMWSCEN!$HJ$2:$HJ$150=E$1),0),$B28-1973)} -> -4184 | F28: {=INDEX(GMWSCEN!$A$2:$HJ$150,MATCH(1,(GMWSCEN!$HI$2:$HI$150=F$3)*(GMWSCEN!$HJ$2:$HJ$150=F$1),0),$B28-1973)} -> 36578 | G28: {=INDEX(GMWSCEN!$A$2:$HJ$150,MATCH(1,(GMWSCEN!$HI$2:$HI$150=G$3)*(GMWSCEN!$HJ$2:$HJ$150=G$1),0),$B28-1973)} -> 726 | H28: {=INDEX(GMWSCEN!$A$2:$HJ$150,MATCH(1,(GMWSCEN!$HI$2:$HI$150=H$3)*(GMWSCEN!$HJ$2:$HJ$150=H$1),0),$B28-1973)} -> 3502 | I28: {=INDEX(GMWSCEN!$A$2:$HJ$150,MATCH(1,(GMWSCEN!$HI$2:$HI$150=I$3)*(GMWSCEN!$HJ$2:$HJ$150=I$1),0),$B28-1973)} -> 35896 | J28: {=INDEX(GMWSCEN!$A$2:$HJ$150,MATCH(1,(GMWSCEN!$HI$2:$HI$150=J$3)*(GMWSCEN!$HJ$2:$HJ$150=J$1),0),$B28-1973)} -> 103842.1 | ... BV28: {=INDEX(GMWSCEN!$A$2:$HJ$150,MATCH(1,(GMWSCEN!$HI$2:$HI$150=BV$3)*(GMWSCEN!$HJ$2:$HJ$150=BV$1),0),$B28-1973)} -> 0.5440712 | BY28: =+BY24+1 -> 1985 | CB28: =+CB27+1 -> 2001 | CC28: =+CC27+100 -> 200101 | CD28: =SUMIF($BY$7:$BY$206,$CB28,C$7:C$206) -> 1669942 | CE28: =SUMIF($BY$7:$BY$206,$CB28,D$7:D$206) -> 5959 | CF28: =SUMIF($BY$7:$BY$206,$CB28,E$7:E$206) -> 6682 | CG28: =SUMIF($BY$7:$BY$206,$CB28,F$7:F$206) -> 379869 | CH28: =SUMIF($BY$7:$BY$206,$CB28,G$7:G$206) -> 12641 | CI28: =SUMIF($BY$7:$BY$206,$CB28,H$7:H$206) -> 26330 | CJ28: =SUMIF($BY$7:$BY$206,$CB28,I$7:I$206) -> 412881 | CK28: =SUMIF($BZ$7:$BZ$206,$CC28,J$7:J$206) -> 330600 | CL28: =SUMIF($BY$7:$BY$206,$CB28,K$7:K$206) -> 1155639 | CM28: =SUMIF($BY$7:$BY$206,$CB28,L$7:L$206) -> 1622453.5 | CN28: =AVERAGEIF($BY$7:$BY$206,$CB28,M$7:M$206) -> 69.20171 | CO28: =AVERAGEIF($BY$7:$BY$206,$CB28,N$7:N$206) -> 73.86667 | CP28: =AVERAGEIF($BY$7:$BY$206,$CB28,O$7:O$206) -> 4.5 | CQ28: =SUMIF($BY$7:$BY$206,$CB28,P$7:P$206) -> 156492 | CR28: =AVERAGEIF($BY$7:$BY$206,$CB28,Q$7:Q$206) -> 97.3 | CS28: =SUMIF($BY$7:$BY$206,$CB28,R$7:R$206) -> 127350 | CT28: =AVERAGEIF($BY$7:$BY$206,$CB28,S$7:S$206) -> 5.125 | CU28: =SUMIF($BZ$7:$BZ$206,$CC28,T$7:T$206) -> 2.508163 | CV28: =SUMIF($BY$7:$BY$206,$CB28,U$7:U$206) -> 1669942 | CW28: =SUMIF($BY$7:$BY$206,$CB28,V$7:V$206) -> 5959 | CX28: =SUMIF($BY$7:$BY$206,$CB28,W$7:W$206) -> 6682 | CY28: =SUMIF($BY$7:$BY$206,$CB28,X$7:X$206) -> 379869 | CZ28: =SUMIF($BY$7:$BY$206,$CB28,Y$7:Y$206) -> 12641 | DA28: =SUMIF($BY$7:$BY$206,$CB28,Z$7:Z$206) -> 26330 | DB28: =SUMIF($BY$7:$BY$206,$CB28,AA$7:AA$206) -> 412881 | DC28: =SUMIF($BZ$7:$BZ$206,$CC28,AB$7:AB$206) -> 330600 | DD28: =SUMIF($BY$7:$BY$206,$CB28,AC$7:AC$206) -> 1155639 | DE28: =SUMIF($BY$7:$BY$206,$CB28,AD$7:AD$206) -> 1622453.5 | DF28: =AVERAGEIF($BY$7:$BY$206,$CB28,AE$7:AE$206) -> 69.20171 | DG28: =AVERAGEIF($BY$7:$BY$206,$CB28,AF$7:AF$206) -> 73.86667 | DH28: =AVERAGEIF($BY$7:$BY$206,$CB28,AG$7:AG$206) -> 4.5 | DI28: =SUMIF($BY$7:$BY$206,$CB28,AH$7:AH$206) -> 156492 | DJ28: =AVERAGEIF($BY$7:$BY$206,$CB28,AI$7:AI$206) -> 97.3 | DK28: =SUMIF($BY$7:$BY$206,$CB28,AJ$7:AJ$206) -> 127350 | DL28: =AVERAGEIF($BY$7:$BY$206,$CB28,AK$7:AK$206) -> 5.125 | DM28: =SUMIF($BZ$7:$BZ$206,$CC28,AL$7:AL$206) -> 2.508163 | DN28: =SUMIF($BY$7:$BY$206,$CB28,AM$7:AM$206) -> 1669942 | DO28: =SUMIF($BY$7:$BY$206,$CB28,AN$7:AN$206) -> 5959 | DP28: =SUMIF($BY$7:$BY$206,$CB28,AO$7:AO$206) -> 6682 | DQ28: =SUMIF($BY$7:$BY$206,$CB28,AP$7:AP$206) -> 379869 | DR28: =SUMIF($BY$7:$BY$206,$CB28,AQ$7:AQ$206) -> 12641 | DS28: =SUMIF($BY$7:$BY$206,$CB28,AR$7:AR$206) -> 26330 | DT28: =SUMIF($BY$7:$BY$206,$CB28,AS$7:AS$206) -> 412881 | DU28: =SUMIF($BZ$7:$BZ$206,$CC28,AT$7:AT$206) -> 330600 | DV28: =SUMIF($BY$7:$BY$206,$CB28,AU$7:AU$206) -> 1155639 | DW28: =SUMIF($BY$7:$BY$206,$CB28,AV$7:AV$206) -> 1622453.5 | DX28: =AVERAGEIF($BY$7:$BY$206,$CB28,AW$7:AW$206) -> 69.20171 | DY28: =AVERAGEIF($BY$7:$BY$206,$CB28,AX$7:AX$206) -> 73.86667 | DZ28: =AVERAGEIF($BY$7:$BY$206,$CB28,AY$7:AY$206) -> 4.5 | EA28: =SUMIF($BY$7:$BY$206,$CB28,AZ$7:AZ$206) -> 156492 | EB28: =AVERAGEIF($BY$7:$BY$206,$CB28,BA$7:BA$206) -> 97.3 | EC28: =SUMIF($BY$7:$BY$206,$CB28,BB$7:BB$206) -> 127350 | ED28: =AVERAGEIF($BY$7:$BY$206,$CB28,BC$7:BC$206) -> 5.125 | EE28: =SUMIF($BZ$7:$BZ$206,$CC28,BD$7:BD$206) -> 2.508163 | EF28: =SUMIF($BY$7:$BY$206,$CB28,BE$7:BE$206) -> 1669942 | EG28: =SUMIF($BY$7:$BY$206,$CB28,BF$7:BF$206) -> 5959 | EH28: =SUMIF($BY$7:$BY$206,$CB28,BG$7:BG$206) -> 6682 | EI28: =SUMIF($BY$7:$BY$206,$CB28,BH$7:BH$206) -> 379869 | EJ28: =SUMIF($BY$7:$BY$206,$CB28,BI$7:BI$206) -> 12641 | EK28: =SUMIF($BY$7:$BY$206,$CB28,BJ$7:BJ$206) -> 26330 | EL28: =SUMIF($BY$7:$BY$206,$CB28,BK$7:BK$206) -> 412881 | EM28: =SUMIF($BZ$7:$BZ$206,$CC28,BL$7:BL$206) -> 330600 | EN28: =SUMIF($BY$7:$BY$206,$CB28,BM$7:BM$206) -> 1155639 | EO28: =SUMIF($BY$7:$BY$206,$CB28,BN$7:BN$206) -> 1622453.5 | EP28: =AVERAGEIF($BY$7:$BY$206,$CB28,BO$7:BO$206) -> 69.20171 | EQ28: =AVERAGEIF($BY$7:$BY$206,$CB28,BP$7:BP$206) -> 73.86667 | ER28: =AVERAGEIF($BY$7:$BY$206,$CB28,BQ$7:BQ$206) -> 4.5 | ES28: =SUMIF($BY$7:$BY$206,$CB28,BR$7:BR$206) -> 156492 | ET28: =AVERAGEIF($BY$7:$BY$206,$CB28,BS$7:BS$206) -> 97.3 | EU28: =SUMIF($BY$7:$BY$206,$CB28,BT$7:BT$206) -> 127350 | EV28: =AVERAGEIF($BY$7:$BY$206,$CB28,BU$7:BU$206) -> 5.125 | EW28: =SUMIF($BZ$7:$BZ$206,$CC28,BV$7:BV$206) -> 2.508163
