Workbook
Name _1_: #REF!
Name _2ecm: #REF!
Name _3ecw: #REF!
Name _bot1: #REF!
Name _bot2: #REF!
Name _bot3: #REF!
Name _bot4: #REF!
Name _bot5: #REF!
Name _bot6: #REF!
Name _DLX1.INC: HAVERM!$A$1:$G$6
Name _DLX2.INC: HAVERD!$B$1:$G$6
Name _I2: '[6]XR data'!#REF!
Name _top1: #REF!
Name _top2: #REF!
Name _top3: #REF!
Name _top4: #REF!
Name _top5: #REF!
Name _top6: #REF!
Name a: SERIES1s:SERIES1e
Name AllNSAData: '[7]Labour market flows NSA'!#REF!
Name AllSAData: '[8]Labour market flows SA'!#REF!
Name AME: OFFSET([9]AME!$H$15,0,0,MAX([9]AME!$B$15:$B100),1)
Name Ann: #REF!
Name Ann_chg: #REF!
Name Apr_50: [10]Sheet1!$B$5:$F$5
Name Apr_51: [10]Sheet1!$B$17:$F$17
Name Apr_52: [10]Sheet1!$B$29:$F$29
Name Apr_53: [10]Sheet1!$B$41:$F$41
Name Apr_54: [10]Sheet1!$B$53:$F$53
Name Apr_55: [10]Sheet1!$B$65:$F$65
Name Apr_56: [10]Sheet1!$B$77:$F$77
Name Apr_57: [10]Sheet1!$B$89:$F$89
Name Apr_58: [10]Sheet1!$B$101:$F$101
Name Apr_59: [10]Sheet1!$B$113:$F$113
Name Apr_60: [10]Sheet1!$B$125:$F$125
Name Apr_61: [10]Sheet1!$B$137:$F$137
Name Apr_62: [10]Sheet1!$B$149:$F$149
Name Apr_63: [10]Sheet1!$B$161:$F$161
Name Apr_64: [10]Sheet1!$B$173:$F$173
Name Apr_65: [10]Sheet1!$B$185:$F$185
Name Apr_66: [10]Sheet1!$B$197:$F$197
Name Apr_67: [10]Sheet1!$B$209:$F$209
Name Apr_68: [10]Sheet1!$B$221:$F$221
Name Apr_69: [10]Sheet1!$B$233:$F$233
Name Apr_70: [10]Sheet1!$B$245:$F$245
Name Apr_71: [10]Sheet1!$B$257:$F$257
Name Apr_72: [10]Sheet1!$B$269:$F$269
Name Apr_73: [10]Sheet1!$B$281:$F$281
Name Apr_74: [10]Sheet1!$B$293:$F$293
Name Apr_75: [10]Sheet1!$B$305:$F$305
Name Apr_76: [10]Sheet1!$B$317:$F$317
Name Apr_77: [10]Sheet1!$B$329:$F$329
Name Apr_78: [10]Sheet1!$B$341:$F$341
Name Apr_79: [10]Sheet1!$B$353:$F$353
Name Apr_80: [10]Sheet1!$B$365:$F$365
Name Apr_81: [10]Sheet1!$B$377:$F$377
Name Apr_82: [10]Sheet1!$B$389:$F$389
Name Apr_83: [10]Sheet1!$B$401:$F$401
Name Apr_84: [10]Sheet1!$B$413:$F$413
Name Apr_85: [10]Sheet1!$B$425:$F$425

Sheet Chart Data
A1: Services inflation | E1: Private sector pay growth
B2: Outturn | C2: BoE forecast | F2: Outturn | G2: BoE forecast
A3: 44562 | B3: =100*((HAVERM!C151/HAVERM!C139)-1) -> 3.2685512 | E3: 44562 | F3: =HAVERM!D151 -> 4.2
A4: 44593 | B4: =100*((HAVERM!C152/HAVERM!C140)-1) -> 3.4391534 | E4: 44593 | F4: =HAVERM!D152 -> 4.6
A5: 44621 | B5: =100*((HAVERM!C153/HAVERM!C141)-1) -> 3.9612676 | E5: 44621 | F5: =HAVERM!D153 -> 4.9
A6: 44652 | B6: =100*((HAVERM!C154/HAVERM!C142)-1) -> 4.7244094 | E6: 44652 | F6: =HAVERM!D154 -> 4.8
A7: 44682 | B7: =100*((HAVERM!C155/HAVERM!C143)-1) -> 4.886562 | E7: 44682 | F7: =HAVERM!D155 -> 5.1
A8: 44713 | B8: =100*((HAVERM!C156/HAVERM!C144)-1) -> 5.2173913 | E8: 44713 | F8: =HAVERM!D156 -> 5.4
A9: 44743 | B9: =100*((HAVERM!C157/HAVERM!C145)-1) -> 5.7241977 | E9: 44743 | F9: =HAVERM!D157 -> 6
A10: 44774 | B10: =100*((HAVERM!C158/HAVERM!C146)-1) -> 5.9585492 | E10: 44774 | F10: =HAVERM!D158 -> 6.2
A11: 44805 | B11: =100*((HAVERM!C159/HAVERM!C147)-1) -> 6.1312608 | E11: 44805 | F11: =HAVERM!D159 -> 6.6
A12: 44835 | B12: =100*((HAVERM!C160/HAVERM!C148)-1) -> 6.2660944 | E12: 44835 | F12: =HAVERM!D160 -> 6.9
A13: 44866 | B13: =100*((HAVERM!C161/HAVERM!C149)-1) -> 6.3464837 | E13: 44866 | F13: =HAVERM!D161 -> 7.3
A14: 44896 | B14: =100*((HAVERM!C162/HAVERM!C150)-1) -> 6.8376068 | E14: 44896 | F14: =HAVERM!D162 -> 7.3
... A26: 45261 | B26: =100*((HAVERM!C174/HAVERM!C162)-1) -> 6.4 | E26: 45261 | F26: =HAVERM!D174 -> 6.2
A27: 45292 | B27: =100*((HAVERM!C175/HAVERM!C163)-1) -> 6.542811 | C27: ='Chart 2.18'!H55 -> 6.6 | E27: 45292
A28: 45323 | C28: ='Chart 2.18'!H56 -> 6.1 | E28: 45323
A29: 45352 | C29: ='Chart 2.18'!H57 -> 5.8 | E29: 45352 | G29: ='Chart 2.16'!B31 -> 5.7
A30: 45383 | C30: ='Chart 2.18'!H58 -> 5.3 | E30: 45383
A31: 45413 | C31: ='Chart 2.18'!H59 -> 4.9 | E31: 45413
A32: 45444 | C32: ='Chart 2.18'!H60 -> 4.9 | E32: 45444 | G32: ='Chart 2.16'!B32 -> 4.7

Sheet Chart 2.16
A1: Section 2: Current economic conditions
A3: Chart 2.16 - Measures of annual private sector wage growth
A5: Date | B5: ONS private sector regular pay | C5: KPMG/REC (advanced 12 months) | D5: HMRC RTI | E5: Indeed | F5: DMP | G5: Agents' pay survey
A6: 44592 | B6: 3.8 | C6: No permission | D6: 6.5 | E6: 4.2 | F6: n.a. | G6: n.a.
A7: 44620 | B7: 4.1 | D7: 6.5 | E7: 4.7 | F7: n.a. | G7: n.a.
A8: 44651 | B8: 4.3 | D8: 6.7 | E8: 5.6 | F8: n.a. | G8: n.a.
A9: 44681 | B9: 4.8 | D9: 6.6 | E9: 6.3 | F9: n.a. | G9: n.a.
A10: 44712 | B10: 5.1 | D10: 6.8 | E10: 6.2 | F10: 5.5 | G10: n.a.
A11: 44742 | B11: 5.4 | D11: 6.9 | E11: 6.2 | F11: 5.6 | G11: n.a.
A12: 44773 | B12: 6 | D12: 7.1 | E12: 5.9 | F12: 5.5 | G12: n.a.
A13: 44804 | B13: 6.2 | D13: 7.1 | E13: 6.1 | F13: 5.8 | G13: n.a.
A14: 44834 | B14: 6.6 | D14: 7.1 | E14: 6.2 | F14: 6.1 | G14: n.a.
A15: 44865 | B15: 6.9 | D15: 7 | E15: 6 | F15: 6.3 | G15: n.a.
A16: 44895 | B16: 7.3 | D16: 6.9 | E16: 5.8 | F16: 6.2 | G16: n.a.
A17: 44926 | B17: 7.3 | D17: 6.9 | E17: 5.9 | F17: 6.3 | G17: n.a.
A18: 44957 | B18: 7.1 | D18: 7.2 | E18: 6.3 | F18: 6.3 | G18: n.a.
A19: 44985 | B19: 7 | D19: 7.4 | E19: 6.5 | F19: 6.5 | G19: n.a.
A20: 45016 | B20: 7.1 | D20: 7.4 | E20: 7 | F20: 6.5 | G20: n.a.
A21: 45046 | B21: 7.7 | D21: 7.3 | E21: 7.5 | F21: 6.6 | G21: n.a.
... A28: 45260 | B28: 6.5 | D28: 6.5 | E28: 6.5 | F28: 7 | G28: n.a.
A29: 45291 | B29: n.a. | D29: 6.3 | E29: 6.5 | F29: 6.9 | G29: n.a.
A30: 45322 | B30: n.a. | D30: n.a. | E30: n.a. | F30: 6.8 | G30: n.a.
A31: 2024 Q1 (Bank staff projection) | B31: 5.7 | D31: n.a. | E31: n.a. | F31: n.a. | G31: n.a.
A32: 2024 Q2 (Bank staff projection) | B32: 4.7 | D32: n.a. | E32: n.a. | F32: n.a. | G32: n.a.
A33: 2024 Q3 (Bank staff projection) | B33: 4.4 | D33: n.a. | E33: n.a. | F33: n.a. | G33: n.a.
A34: 2024 Q4 (Bank staff projection) | B34: 4.8 | D34: n.a. | E34: n.a. | F34: 5.2 | G34: 5.4

Sheet Chart 2.18
A1: Section 2: Current economic conditions
A3: 2.18 - Contributions to CPI inflation
B5: Contributions | H5: Inflation rates
A6: Date | B6: Services | C6: Food | D6: Electricity and gas | E6: Fuels and lubricants | F6: Other goods | H6: Services | I6: Food | J6: Electricity and gas | K6: Fuels and lubricants | L6: Other goods | M6: CPI
A7: 43831 | B7: 1.1 | C7: 0.1 | D7: 0.2 | E7: 0.1 | F7: 0.2 | H7: 2.3 | I7: 1.4 | J7: 4.9 | K7: 4.7 | L7: 0.6 | M7: 1.8
A8: 43862 | B8: 1.2 | C8: 0.1 | D8: 0.1 | E8: 0.1 | F8: 0.2 | H8: 2.5 | I8: 1.2 | J8: 4.4 | K8: 2.8 | L8: 0.5 | M8: 1.7
A9: 43891 | B9: 1.2 | C9: 0.1 | D9: 0.1 | E9: -0.1 | F9: 0.1 | H9: 2.5 | I9: 1.3 | J9: 3.9 | K9: -2.4 | L9: 0.4 | M9: 1.5
A10: 43922 | B10: 1 | C10: 0.1 | D10: -0.2 | E10: -0.4 | F10: 0.3 | H10: 2 | I10: 1.3 | J10: -6.8 | K10: -12.2 | L10: 0.7 | M10: 0.8
A11: 43952 | B11: 0.9 | C11: 0.2 | D11: -0.2 | E11: -0.5 | F11: 0.1 | H11: 1.9 | I11: 1.8 | J11: -7 | K11: -16.7 | L11: 0.4 | M11: 0.5
A12: 43983 | B12: 0.9 | C12: 0.1 | D12: -0.2 | E12: -0.5 | F12: 0.4 | H12: 1.8 | I12: 1.1 | J12: -6.6 | K12: -16.4 | L12: 1 | M12: 0.6
A13: 44013 | B13: 1 | C13: 0.1 | D13: -0.2 | E13: -0.4 | F13: 0.5 | H13: 2.1 | I13: 0.8 | J13: -6.6 | K13: -12 | L13: 1.5 | M13: 1
A14: 44044 | B14: 0.3 | C14: 0 | D14: -0.2 | E14: -0.4 | F14: 0.5 | H14: 0.6 | I14: 0.4 | J14: -6.7 | K14: -11.4 | L14: 1.3 | M14: 0.2
A15: 44075 | B15: 0.7 | C15: 0 | D15: -0.2 | E15: -0.3 | F15: 0.4 | H15: 1.4 | I15: -0.1 | J15: -6.8 | K15: -10.6 | L15: 1.1 | M15: 0.5
A16: 44105 | B16: 0.7 | C16: 0.1 | D16: -0.3 | E16: -0.3 | F16: 0.6 | H16: 1.4 | I16: 0.6 | J16: -8.8 | K16: -10.2 | L16: 1.6 | M16: 0.7
A17: 44136 | B17: 0.7 | C17: -0.1 | D17: -0.3 | E17: -0.3 | F17: 0.3 | H17: 1.4 | I17: -0.6 | J17: -8.8 | K17: -10 | L17: 0.8 | M17: 0.3
A18: 44166 | B18: 0.7 | C18: -0.1 | D18: -0.3 | E18: -0.3 | F18: 0.5 | H18: 1.5 | I18: -1.4 | J18: -8.5 | K18: -8.3 | L18: 1.5 | M18: 0.6
... A54: 45261 | B54: 3 | C54: 0.9 | D54: -1 | E54: -0.3 | F54: 1.4 | H54: 6.4 | I54: 8 | J54: -21.5 | K54: -10.8 | L54: 4.3 | M54: 4
A55: Jan 2024 (Bank staff projections) | B55: 3.1 | C55: 0.8 | D55: -0.9 | E55: -0.3 | F55: 1.4 | H55: 6.6 | I55: 7 | J55: -17.8 | K55: -9.2 | L55: 4.1 | M55: 4.1
A56: Feb 2024 (Bank staff projections) | B56: 2.9 | C56: 0.6 | D56: -0.8 | E56: -0.2 | F56: 1.1 | H56: 6.1 | I56: 5 | J56: -17.7 | K56: -7 | L56: 3.3 | M56: 3.5
A57: Mar 2024 (Bank staff projections) | B57: 2.7 | C57: 0.4 | D57: -0.8 | E57: -0.1 | F57: 1 | H57: 5.8 | I57: 3.3 | J57: -17.6 | K57: -4.2 | L57: 2.9 | M57: 3.1
A58: Apr 2024 (Bank staff projections) | B58: 2.5 | C58: 0.2 | D58: -1.3 | E58: 0.1 | F58: 0.6 | H58: 5.3 | I58: 1.9 | J58: -27.3 | K58: 3.3 | L58: 1.7 | M58: 2.1
A59: May 2024 (Bank staff projections) | B59: 2.3 | C59: 0.1 | D59: -1.3 | E59: 0.2 | F59: 0.5 | H59: 4.9 | I59: 1 | J59: -27.2 | K59: 6.5 | L59: 1.5 | M59: 1.9
A60: Jun 2024 (Bank staff projections) | B60: 2.3 | C60: 0.1 | D60: -1.3 | E60: 0.3 | F60: 0.5 | H60: 4.9 | I60: 0.7 | J60: -27.1 | K60: 9.8 | L60: 1.5 | M60: 1.9
A61: 2024 Q3 (Bank staff projections) | B61: n.a. | C61: n.a. | D61: n.a. | E61: n.a. | F61: n.a. | H61: n.a. | I61: n.a. | J61: n.a. | K61: n.a. | L61: n.a. | M61: 2.2
A62: 2024 Q4 (Bank staff projections) | B62: n.a. | C62: n.a. | D62: n.a. | E62: n.a. | F62: n.a. | H62: n.a. | I62: n.a. | J62: n.a. | K62: n.a. | L62: n.a. | M62: 2.7

Sheet HAVERM
A1: 201001 !M | B1: D7BT@UK | C1: D7F5@UK | D1: KAJ4@UK
A2: .DESC | B2: UK: Consumer Price Index: All Items (NSA, 2015=100) | C2: UK: Consumer Price Index: All Services (NSA, 2015=100) | D2: Great Britain: AWE, Regular Pay: Private Sector [3Mo Mvg Avg vs Yr Ago] (SA, %)
A3: .T1 | B3: Jan-1988 | C3: Jan-1988 | D3: Mar-2001
A4: .TN | B4: Jan-2024 | C4: Jan-2024 | D4: Jan-2024
A5: .LSOURCE | B5: Office for National Statistics | C5: Office for National Statistics | D5: Office for National Statistics
A6: .DTLM | B6: Feb-14-2024 07:06 | C6: Feb-14-2024 07:06 | D6: Mar-12-2024 07:13
A7: 201001 | B7: 87.8 | C7: 83.9 | D7: 0.5
A8: 201002 | B8: 88.2 | C8: 84.1 | D8: 0.7
A9: 201003 | B9: 88.7 | C9: 84.4 | D9: 1
A10: 201004 | B10: 89.2 | C10: 84.9 | D10: 0.9
A11: 201005 | B11: 89.4 | C11: 85.2 | D11: 0.8
A12: 201006 | B12: 89.5 | C12: 85.7 | D12: 0.6
A13: 201007 | B13: 89.3 | C13: 86.1 | D13: 1
A14: 201008 | B14: 89.8 | C14: 86.7 | D14: 1.6
A15: 201009 | B15: 89.8 | C15: 85.9 | D15: 2
A16: 201010 | B16: 90 | C16: 86.3 | D16: 2
A17: 201011 | B17: 90.3 | C17: 86.1 | D17: 2
A18: 201012 | B18: 91.2 | C18: 87.2 | D18: 1.9
... A175: 202401 | B175: 131.5 | C175: 131.9 | D175: 6.1

Sheet HAVERD
B1: 20220101 !D | C1: T112G2@INTDAILY | D1: T112GA@INTDAILY
B2: .DESC | C2: UK: 2-Yr Government Bond Yield (%) | D2: UK: 10-Yr Government Bond Yield (%)
B3: .T1 | C3: 26-Jan-1994 | D3: 26-Jan-1994
B4: .TN | C4: 12-Mar-2024 | D4: 12-Mar-2024
B5: .LSOURCE | C5: London Stock Exchange Group | D5: London Stock Exchange Group
B6: .DTLM | C6: Mar-12-2024 19:53 | D6: Mar-12-2024 19:53
A7: 44564 | B7: 20220103 | C7: 0.68 | D7: 0.97
A8: 44565 | B8: 20220104 | C8: 0.77 | D8: 1.08
A9: 44566 | B9: 20220105 | C9: 0.76 | D9: 1.09
A10: 44567 | B10: 20220106 | C10: 0.8 | D10: 1.14
A11: 44568 | B11: 20220107 | C11: 0.82 | D11: 1.18
A12: =+A7+7 -> 44571 | B12: 20220110 | C12: 0.84 | D12: 1.19
A13: =+A8+7 -> 44572 | B13: 20220111 | C13: 0.84 | D13: 1.17
A14: =+A9+7 -> 44573 | B14: 20220112 | C14: 0.79 | D14: 1.13
A15: =+A10+7 -> 44574 | B15: 20220113 | C15: 0.76 | D15: 1.11
A16: =+A11+7 -> 44575 | B16: 20220114 | C16: 0.79 | D16: 1.16
A17: =+A12+7 -> 44578 | B17: 20220117 | C17: 0.84 | D17: 1.19
A18: =+A13+7 -> 44579 | B18: 20220118 | C18: 0.87 | D18: 1.22
A19: =+A14+7 -> 44580 | B19: 20220119 | C19: 0.9 | D19: 1.26
A20: =+A15+7 -> 44581 | B20: 20220120 | C20: 0.89 | D20: 1.22
A21: =+A16+7 -> 44582 | B21: 20220121 | C21: 0.87 | D21: 1.17
A22: =+A17+7 -> 44585 | B22: 20220124 | C22: 0.87 | D22: 1.13
A23: =+A18+7 -> 44586 | B23: 20220125 | C23: 0.9 | D23: 1.17
... A80: =+A75+7 -> 44665 | B80: 20220414 | C80: 1.56 | D80: 1.89
A81: =+A76+7 -> 44666 | B81: 20220415 | C81: #N/A | D81: 1.9
A82: =+A77+7 -> 44669 | B82: 20220418 | C82: #N/A | D82: 1.88
A83: =+A78+7 -> 44670 | B83: 20220419 | C83: 1.59 | D83: 1.99
A84: =+A79+7 -> 44671 | B84: 20220420 | C84: 1.57 | D84: 1.93
A85: =+A80+7 -> 44672 | B85: 20220421 | C85: 1.76 | D85: 2.03
A86: =+A81+7 -> 44673 | B86: 20220422 | C86: 1.72 | D86: 1.97
A87: =+A82+7 -> 44676 | B87: 20220425 | C87: 1.57 | D87: 1.85
A88: =+A83+7 -> 44677 | B88: 20220426 | C88: 1.5 | D88: 1.82
A89: =+A84+7 -> 44678 | B89: 20220427 | C89: 1.49 | D89: 1.81
A90: =+A85+7 -> 44679 | B90: 20220428 | C90: 1.55 | D90: 1.87
A91: =+A86+7 -> 44680 | B91: 20220429 | C91: 1.6 | D91: 1.91
A92: =+A87+7 -> 44683 | B92: 20220502 | C92: 1.58 | D92: 1.9
A93: =+A88+7 -> 44684 | B93: 20220503 | C93: 1.65 | D93: 1.95
A94: =+A89+7 -> 44685 | B94: 20220504 | C94: 1.64 | D94: 1.97
... A262: =+A257+7 -> 44921 | B262: 20221226 | C262: 3.65 | D262: 3.64
A263: =+A258+7 -> 44922 | B263: 20221227 | C263: #N/A | D263: 3.64
A264: =+A259+7 -> 44923 | B264: 20221228 | C264: 3.58 | D264: 3.65
A265: =+A260+7 -> 44924 | B265: 20221229 | C265: 3.62 | D265: 3.66
A266: =+A261+7 -> 44925 | B266: 20221230 | C266: 3.71 | D266: 3.67
A267: =+A262+7 -> 44928 | B267: 20230102 | C267: #N/A | D267: 3.67
A268: =+A263+7 -> 44929 | B268: 20230103 | C268: 3.57 | D268: 3.65
A269: =+A264+7 -> 44930 | B269: 20230104 | C269: 3.44 | D269: 3.5
A270: =+A265+7 -> 44931 | B270: 20230105 | C270: 3.5 | D270: 3.55
A271: =+A266+7 -> 44932 | B271: 20230106 | C271: 3.41 | D271: 3.47
A272: =+A267+7 -> 44935 | B272: 20230109 | C272: 3.44 | D272: 3.53
A273: =+A268+7 -> 44936 | B273: 20230110 | C273: 3.46 | D273: 3.56
A274: =+A269+7 -> 44937 | B274: 20230111 | C274: 3.52 | D274: 3.41
A275: =+A270+7 -> 44938 | B275: 20230112 | C275: 3.41 | D275: 3.32
A276: =+A271+7 -> 44939 | B276: 20230113 | C276: 3.48 | D276: 3.37
A277: =+A272+7 -> 44942 | B277: 20230116 | C277: 3.5 | D277: 3.39
A278: =+A273+7 -> 44943 | B278: 20230117 | C278: 3.46 | D278: 3.33
A279: =+A274+7 -> 44944 | B279: 20230118 | C279: 3.48 | D279: 3.31
... A335: =+A330+7 -> 45022 | B335: 20230406 | C335: 3.33 | D335: 3.41
A336: =+A331+7 -> 45023 | B336: 20230407 | C336: #N/A | D336: #N/A
A337: =+A332+7 -> 45026 | B337: 20230410 | C337: 3.36 | D337: #N/A
A338: =+A333+7 -> 45027 | B338: 20230411 | C338: 3.48 | D338: 3.54
A339: =+A334+7 -> 45028 | B339: 20230412 | C339: 3.52 | D339: 3.57
A340: =+A335+7 -> 45029 | B340: 20230413 | C340: 3.5 | D340: 3.56
A341: =+A336+7 -> 45030 | B341: 20230414 | C341: 3.6 | D341: 3.65
A342: =+A337+7 -> 45033 | B342: 20230417 | C342: 3.62 | D342: 3.7
A343: =+A338+7 -> 45034 | B343: 20230418 | C343: 3.69 | D343: 3.75
A344: =+A339+7 -> 45035 | B344: 20230419 | C344: 3.82 | D344: 3.85
A345: =+A340+7 -> 45036 | B345: 20230420 | C345: 3.71 | D345: 3.75
A346: =+A341+7 -> 45037 | B346: 20230421 | C346: 3.74 | D346: 3.75
A347: =+A342+7 -> 45040 | B347: 20230424 | C347: 3.81 | D347: 3.78
A348: =+A343+7 -> 45041 | B348: 20230425 | C348: 3.73 | D348: 3.69
A349: =+A344+7 -> 45042 | B349: 20230426 | C349: 3.77 | D349: 3.74
... A351: =+A346+7 -> 45044 | B351: 20230428 | C351: 3.78 | D351: 3.72
A352: =+A347+7 -> 45047 | B352: 20230501 | C352: 3.78 | D352: #N/A
A353: =+A348+7 -> 45048 | B353: 20230502 | C353: 3.73 | D353: 3.66
A354: =+A349+7 -> 45049 | B354: 20230503 | C354: 3.76 | D354: 3.69
A355: =+A350+7 -> 45050 | B355: 20230504 | C355: 3.68 | D355: 3.66
A356: =+A351+7 -> 45051 | B356: 20230505 | C356: 3.77 | D356: 3.77
A357: =+A352+7 -> 45054 | B357: 20230508 | C357: 3.78 | D357: #N/A
A358: =+A353+7 -> 45055 | B358: 20230509 | C358: 3.87 | D358: 3.86
A359: =+A354+7 -> 45056 | B359: 20230510 | C359: 3.83 | D359: 3.8
A360: =+A355+7 -> 45057 | B360: 20230511 | C360: 3.73 | D360: 3.71
A361: =+A356+7 -> 45058 | B361: 20230512 | C361: 3.8 | D361: 3.78
A362: =+A357+7 -> 45061 | B362: 20230515 | C362: 3.83 | D362: 3.82
A363: =+A358+7 -> 45062 | B363: 20230516 | C363: 3.8 | D363: 3.8
A364: =+A359+7 -> 45063 | B364: 20230517 | C364: 3.87 | D364: 3.84
A365: =+A360+7 -> 45064 | B365: 20230518 | C365: 3.97 | D365: 3.97
A366: =+A361+7 -> 45065 | B366: 20230519 | C366: 3.96 | D366: 4.01
A367: =+A362+7 -> 45068 | B367: 20230522 | C367: 4.04 | D367: 4.05
A368: =+A363+7 -> 45069 | B368: 20230523 | C368: 4.13 | D368: 4.16
A369: =+A364+7 -> 45070 | B369: 20230524 | C369: 4.38 | D369: 4.22
... A371: =+A366+7 -> 45072 | B371: 20230526 | C371: 4.48 | D371: 4.33
A372: =+A367+7 -> 45075 | B372: 20230529 | C372: 4.51 | D372: #N/A
A373: =+A368+7 -> 45076 | B373: 20230530 | C373: 4.44 | D373: 4.24
A374: =+A369+7 -> 45077 | B374: 20230531 | C374: 4.32 | D374: 4.18
A375: =+A370+7 -> 45078 | B375: 20230601 | C375: 4.29 | D375: 4.13
A376: =+A371+7 -> 45079 | B376: 20230602 | C376: 4.36 | D376: 4.15
A377: =+A372+7 -> 45082 | B377: 20230605 | C377: 4.46 | D377: 4.22
A378: =+A373+7 -> 45083 | B378: 20230606 | C378: 4.46 | D378: 4.19
A379: =+A374+7 -> 45084 | B379: 20230607 | C379: 4.58 | D379: 4.26
A380: =+A375+7 -> 45085 | B380: 20230608 | C380: 4.51 | D380: 4.25
...
