Workbook
Name _DLX1.INC: HAVERQ!$B$1:$K$6
Name _DLX2.INC: HAVERM!$A$1:$H$6
Name Data: [1]sheet0!$C$2

Sheet >> CHARTS

Sheet >> DATA

Sheet Chart Data
A1: GDP forecasts vs consensus | S1: GDP - OE vs consensus | Y1: C cont to GDP | AG1: Real wages | AN1: CONTRIBUTIONS TO CPI INFLATION >> | BK1: Quoted mortgage rates | CA1: Change in interest rates
AN2: Unchained indices | AS2: Rescaled indices | AX2: Price-updated item weights | BC2: Contributions to CPI inflation | BQ2: Margins | BW2: Diff vs expiring deal
B3: =DataA!C1 -> JAN011B.db | C3: =DataA!D1 -> JAN024B.db | D3: =DataA!E1 -> FEB006C.db | E3: =DataA!F1 -> FEB019C.db | F3: =DataA!G1 -> MAR011D.db | G3: =DataA!H1 -> MAR020B.db | H3: =DataA!I1 -> APR009C.db | I3: =DataA!J1 -> APR023B.db | ... P3: =DataA!Q1 -> AUG008C.db | Q3: =DataA!B1 -> SEP002A.db | T3: OE (Sep24) | U3: Consensus (Aug24)* | W3: Consensus | Z3: C | AA3: IF | AB3: GC | AC3: NX | AD3: Oth | AE3: GDP | AH3: Average weekly earnings | AI3: CPI inflation | AJ3: Real wages | AK3: ZERO LINE | AN3: Food | AO3: Petrol | AP3: Energy | AQ3: CPI | AS3: Food | AT3: Petrol | AU3: Energy | AV3: CPI | AX3: Food | AY3: Petrol | AZ3: Energy | BA3: CPI | BC3: Food | BD3: Petrol | BE3: Energy | BF3: Other | BG3: CPI | BH3: CPI check | BI3: 2% TARGET | BL3: 2 year fix, 75% LTV | BM3: 5 year fix, 75% LTV | BN3: 2yr | BO3: 5yr | BQ3: 2 year fix, 75% LTV | BR3: 5 year fix, 75% LTV | BT3: 2 year swap | BU3: 5 year swap | BW3: 2 year fix, 75% LTV | BX3: 5 year fix, 75% LTV | BY3: ZERO LINE | CB3: Non-financial corporations | CC3: Secured household | CD3: ZERO LINE
B4: 45302 | C4: 45315 | D4: 45328 | E4: 45341 | F4: 45362 | G4: 45371 | H4: 45391 | I4: 45405 | J4: 45419 | K4: 45399 | L4: 45393 | M4: 45400 | N4: 45483 | O4: 45497 | P4: 45512 | Q4: 45519 | S4: Q1 2023 | T4: =100*((DataQ!D207/DataQ!D206)-1) -> 0.17481348 | U4: =T4 -> 0.17481348 | W4: =DataQ!D207 -> 569027 | Y4: 45200 | Z4: =DataQ!AA210 -> 336957 | AA4: =DataQ!AB210 -> 107170 | AB4: =DataQ!AC210 -> 117343 | AC4: =DataQ!AD210-DataQ!AE210 -> -7718 | AD4: =AE4-Z4-AA4-AB4-AC4 -> 12874 | AE4: =DataQ!D210 -> 566626 | AG4: 40179 | AH4: =100*((DataQ!U155/DataQ!U151)-1) -> 4.9881235 | AI4: =100*((DataQ!V155/DataQ!V151)-1) -> 3.2774094 | AJ4: =AH4-AI4 -> 1.7107141 | AK4: 0 | AM4: 40179 | AN4: =DataQ!W155/DataQ!W154*100 -> 101.95374 | AO4: =DataQ!X155/DataQ!X154*100 -> 104.81632 | AP4: =DataQ!Y155/DataQ!Y154*100 -> 99.747155 | AQ4: =DataQ!V155/DataQ!V154*100 -> 100.76132 | AS4: =DataQ!W154/DataQ!W151*100 -> 100.72289 | AT4: =DataQ!X154/DataQ!X151*100 -> 118.27868 | AU4: =DataQ!Y154/DataQ!Y151*100 -> 94.882043 | AV4: =DataQ!V154/DataQ!V151*100 -> 102.49708 | AX4: =HAVERQ!C47*AN4/$AQ4 -> 149.75146 | AY4: =HAVERQ!D47*AO4/$AQ4 -> 42.64999 | AZ4: =HAVERQ!E47*AP4/$AQ4 -> 46.526946 | BA4: =1000*AQ4/$AQ4 -> 1000 | BC4: =$AV4/100*(AN4-100)*HAVERQ!C47/1000+(AS4-100)*AX4/$BA4 -> 0.40462859 | BD4: =$AV4/100*(AO4-100)*HAVERQ!D47/1000+(AT4-100)*AY4/$BA4 -> 0.98198555 | BE4: =$AV4/100*(AP4-100)*HAVERQ!E47/1000+(AU4-100)*AZ4/$BA4 -> -0.25030333 | BF4: =BG4-BE4-BD4-BC4 -> 2.1410986 | BG4: =$AV4/100*(AQ4-100)*1000/1000+(AV4-100)*BA4/$BA4 -> 3.2774094 | BH4: =100*((DataQ!V155/DataQ!V151)-1) -> 3.2774094 | BI4: 2 | BK4: 41640 | BL4: =HAVERM!B295 -> 2.37 | BM4: =HAVERM!C295 -> 3.34 | BQ4: =BL4-BT4 -> #N/A | BR4: =BM4-BU4 -> #N/A | BT4: =HAVERM!D295 -> #N/A | BU4: =HAVERM!E295 -> #N/A | BY4: 0 | CA4: 44531 | CB4: =HAVERM!G390-HAVERM!G$389 -> 0.05 | CC4: =HAVERM!H390-HAVERM!H$389 -> -0.01 | CD4: 0
A5: OE | B5: =100*((DataA!C58/DataA!C57)-1) -> 0.55733861 | C5: =100*((DataA!D58/DataA!D57)-1) -> 0.607622 | D5: =100*((DataA!E58/DataA!E57)-1) -> 0.607622 | E5: =100*((DataA!F58/DataA!F57)-1) -> 0.38200567 | F5: =100*((DataA!G58/DataA!G57)-1) -> 0.52154526 | G5: =100*((DataA!H58/DataA!H57)-1) -> 0.52442558 | H5: =100*((DataA!I58/DataA!I57)-1) -> 0.54016363 | I5: =100*((DataA!J58/DataA!J57)-1) -> 0.61547842 | ... P5: =100*((DataA!Q58/DataA!Q57)-1) -> 1.0829668 | Q5: =100*((DataA!B58/DataA!B57)-1) -> 1.1412126 | S5: Q2 2023 | T5: =100*((DataQ!D208/DataQ!D207)-1) -> 0.0086111907 | U5: =T5 -> 0.0086111907 | W5: =DataQ!D208 -> 569076 | Y5: 45292 | Z5: =DataQ!AA211 -> 338388 | AA5: =DataQ!AB211 -> 108142 | AB5: =DataQ!AC211 -> 117324 | AC5: =DataQ!AD211-DataQ!AE211 -> -4531 | AD5: =AE5-Z5-AA5-AB5-AC5 -> 11371 | AE5: =DataQ!D211 -> 570694 | AG5: 40269 | AH5: =100*((DataQ!U156/DataQ!U152)-1) -> 0.99009132 | AI5: =100*((DataQ!V156/DataQ!V152)-1) -> 3.4735622 | AJ5: =AH5-AI5 -> -2.4834709 | AK5: 0 | AM5: 40269 | AN5: =DataQ!W156/DataQ!W154*100 -> 103.11005 | AO5: =DataQ!X156/DataQ!X154*100 -> 111.29595 | AP5: =DataQ!Y156/DataQ!Y154*100 -> 97.724399 | AQ5: =DataQ!V156/DataQ!V154*100 -> 102.05558 | AS5: =DataQ!W154/DataQ!W152*100 -> 100.03988 | AT5: =DataQ!X154/DataQ!X152*100 -> 108.86458 | AU5: =DataQ!Y154/DataQ!Y152*100 -> 99.789735 | AV5: =DataQ!V154/DataQ!V152*100 -> 101.38942 | AX5: =HAVERQ!C48*AN5/$AQ5 -> 149.52918 | AY5: =HAVERQ!D48*AO5/$AQ5 -> 44.712243 | AZ5: =HAVERQ!E48*AP5/$AQ5 -> 45.005348 | BA5: =1000*AQ5/$AQ5 -> 1000 | BC5: =$AV5/100*(AN5-100)*HAVERQ!C48/1000+(AS5-100)*AX5/$BA5 -> 0.47264629 | BD5: =$AV5/100*(AO5-100)*HAVERQ!D48/1000+(AT5-100)*AY5/$BA5 -> 0.86592373 | BE5: =$AV5/100*(AP5-100)*HAVERQ!E48/1000+(AU5-100)*AZ5/$BA5 -> -0.1179023 | BF5: =BG5-BE5-BD5-BC5 -> 2.2528945 | BG5: =$AV5/100*(AQ5-100)*1000/1000+(AV5-100)*BA5/$BA5 -> 3.4735622 | BH5: =100*((DataQ!V156/DataQ!V152)-1) -> 3.4735622 | BI5: 2 | BK5: 41671 | BL5: =HAVERM!B296 -> 2.38 | BM5: =HAVERM!C296 -> 3.45 | BQ5: =BL5-BT5 -> #N/A | BR5: =BM5-BU5 -> #N/A | BT5: =HAVERM!D296 -> #N/A | BU5: =HAVERM!E296 -> #N/A | BY5: 0 | CA5: 44562 | CB5: =HAVERM!G391-HAVERM!G$389 -> 0.11 | CC5: =HAVERM!H391-HAVERM!H$389 -> -0.01 | CD5: 0
A6: Consensus | B6: 0.4 | C6: =B6 -> 0.4 | D6: 0.4 | E6: =D6 -> 0.4 | F6: 0.4 | G6: =F6 -> 0.4 | H6: 0.4 | I6: =H6 -> 0.4 | J6: 0.6 | K6: =J6 -> 0.6 | L6: 0.8 | M6: =L6 -> 0.8 | N6: 0.9 | O6: =N6 -> 0.9 | P6: =O6 -> 0.9 | Q6: =P6 -> 0.9 | S6: Q3 2023 | T6: =100*((DataQ!D209/DataQ!D208)-1) -> -0.11931622 | U6: =T6 -> -0.11931622 | W6: =DataQ!D209 -> 568397 | Y6: 45383 | Z6: =DataQ!AA212 -> 339057 | AA6: =DataQ!AB212 -> 108571 | AB6: =DataQ!AC212 -> 119020 | AC6: =DataQ!AD212-DataQ!AE212 -> -17105 | AD6: =AE6-Z6-AA6-AB6-AC6 -> 24413 | AE6: =DataQ!D212 -> 573956 | AG6: 40360 | AH6: =100*((DataQ!U157/DataQ!U153)-1) -> 1.5220776 | AI6: =100*((DataQ!V157/DataQ!V153)-1) -> 3.1058283 | AJ6: =AH6-AI6 -> -1.5837507 | AK6: 0 | AM6: 40360 | AN6: =DataQ!W157/DataQ!W154*100 -> 103.82775 | AO6: =DataQ!X157/DataQ!X154*100 -> 108.24667 | AP6: =DataQ!Y157/DataQ!Y154*100 -> 97.471555 | AQ6: =DataQ!V157/DataQ!V154*100 -> 102.3601 | AS6: =DataQ!W154/DataQ!W153*100 -> 100.56135 | AT6: =DataQ!X154/DataQ!X153*100 -> 103.1451 | AU6: =DataQ!Y154/DataQ!Y153*100 -> 100.33826 | AV6: =DataQ!V154/DataQ!V153*100 -> 100.72854 | AX6: =HAVERQ!C49*AN6/$AQ6 -> 150.12204 | AY6: =HAVERQ!D49*AO6/$AQ6 -> 43.357848 | AZ6: =HAVERQ!E49*AP6/$AQ6 -> 44.75536 | BA6: =1000*AQ6/$AQ6 -> 1000 | BC6: =$AV6/100*(AN6-100)*HAVERQ!C49/1000+(AS6-100)*AX6/$BA6 -> 0.65490558 | BD6: =$AV6/100*(AO6-100)*HAVERQ!D49/1000+(AT6-100)*AY6/$BA6 -> 0.47694166 | BE6: =$AV6/100*(AP6-100)*HAVERQ!E49/1000+(AU6-100)*AZ6/$BA6 -> -0.10456383 | BF6: =BG6-BE6-BD6-BC6 -> 2.0785449 | BG6: =$AV6/100*(AQ6-100)*1000/1000+(AV6-100)*BA6/$BA6 -> 3.1058283 | BH6: =100*((DataQ!V157/DataQ!V153)-1) -> 3.1058283 | BI6: 2 | BK6: 41699 | BL6: =HAVERM!B297 -> 2.37 | BM6: =HAVERM!C297 -> 3.48 | BQ6: =BL6-BT6 -> #N/A | BR6: =BM6-BU6 -> #N/A | BT6: =HAVERM!D297 -> #N/A | BU6: =HAVERM!E297 -> #N/A | BY6: 0 | CA6: 44593 | CB6: =HAVERM!G392-HAVERM!G$389 -> 0.25 | CC6: =HAVERM!H392-HAVERM!H$389 -> 0 | CD6: 0
S7: Q4 2023 | T7: =100*((DataQ!D210/DataQ!D209)-1) -> -0.311578 | U7: =T7 -> -0.311578 | W7: =DataQ!D210 -> 566626 | AG7: 40452 | AH7: =100*((DataQ!U158/DataQ!U154)-1) -> 1.8953676 | AI7: =100*((DataQ!V158/DataQ!V154)-1) -> 3.3498248 | AJ7: =AH7-AI7 -> -1.4544572 | AK7: 0 | AM7: 40452 | AN7: =DataQ!W158/DataQ!W154*100 -> 105.58214 | AO7: =DataQ!X158/DataQ!X154*100 -> 111.46913 | AP7: =DataQ!Y158/DataQ!Y154*100 -> 99.030771 | AQ7: =DataQ!V158/DataQ!V154*100 -> 103.34982 | AS7: =DataQ!W154/DataQ!W154*100 -> 100 | AT7: =DataQ!X154/DataQ!X154*100 -> 100 | AU7: =DataQ!Y154/DataQ!Y154*100 -> 100 | AV7: =DataQ!V154/DataQ!V154*100 -> 100 | AX7: =HAVERQ!C50*AN7/$AQ7 -> 151.19674 | AY7: =HAVERQ!D50*AO7/$AQ7 -> 44.221015 | AZ7: =HAVERQ!E50*AP7/$AQ7 -> 45.035841 | BA7: =1000*AQ7/$AQ7 -> 1000 | BC7: =$AV7/100*(AN7-100)*HAVERQ!C50/1000+(AS7-100)*AX7/$BA7 -> 0.82615689 | BD7: =$AV7/100*(AO7-100)*HAVERQ!D50/1000+(AT7-100)*AY7/$BA7 -> 0.4702342 | BE7: =$AV7/100*(AP7-100)*HAVERQ!E50/1000+(AU7-100)*AZ7/$BA7 -> -0.045553755 | BF7: =BG7-BE7-BD7-BC7 -> 2.0989874 | BG7: =$AV7/100*(AQ7-100)*1000/1000+(AV7-100)*BA7/$BA7 -> 3.3498248 | BH7: =100*((DataQ!V158/DataQ!V154)-1) -> 3.3498248 | BI7: 2 | BK7: 41730 | BL7: =HAVERM!B298 -> 2.54 | BM7: =HAVERM!C298 -> 3.69 | BQ7: =BL7-BT7 -> #N/A | BR7: =BM7-BU7 -> #N/A | BT7: =HAVERM!D298 -> #N/A | BU7: =HAVERM!E298 -> #N/A | BY7: 0 | CA7: 44621 | CB7: =HAVERM!G393-HAVERM!G$389 -> 0.35 | CC7: =HAVERM!H393-HAVERM!H$389 -> 0.03 | CD7: 0
S8: Q1 2024 | T8: =100*((DataQ!D211/DataQ!D210)-1) -> 0.71793388 | U8: =T8 -> 0.71793388 | W8: =DataQ!D211 -> 570694 | Y8: Cont | Z8: =100*((Z6-Z4)/$AE4) -> 0.37061483 | AA8: =100*((AA6-AA4)/$AE4) -> 0.24725304 | AB8: =100*((AB6-AB4)/$AE4) -> 0.29596242 | AC8: =100*((AC6-AC4)/$AE4) -> -1.6566483 | AD8: =100*((AD6-AD4)/$AE4) -> 2.0364403 | AE8: =SUM(Z8:AD8) -> 1.2936222 | AG8: 40544 | AH8: =100*((DataQ!U159/DataQ!U155)-1) -> 2.8657692 | AI8: =100*((DataQ!V159/DataQ!V155)-1) -> 4.0801022 | AJ8: =AH8-AI8 -> -1.2143329 | AK8: 0 | AM8: 40544 | AN8: =DataQ!W159/DataQ!W158*100 -> 102.15256 | AO8: =DataQ!X159/DataQ!X158*100 -> 108.82813 | AP8: =DataQ!Y159/DataQ!Y158*100 -> 104.2553 | AQ8: =DataQ!V159/DataQ!V158*100 -> 101.4733 | AS8: =DataQ!W158/DataQ!W155*100 -> 103.55887 | AT8: =DataQ!X158/DataQ!X155*100 -> 106.34711 | AU8: =DataQ!Y158/DataQ!Y155*100 -> 99.2818 | AV8: =DataQ!V158/DataQ!V155*100 -> 102.56895 | AX8: =HAVERQ!C51*AN8/$AQ8 -> 161.07102 | AY8: =HAVERQ!D51*AO8/$AQ8 -> 46.116659 | AZ8: =HAVERQ!E51*AP8/$AQ8 -> 45.206307 | BA8: =1000*AQ8/$AQ8 -> 1000 | BC8: =$AV8/100*(AN8-100)*HAVERQ!C51/1000+(AS8-100)*AX8/$BA8 -> 0.92648694 | BD8: =$AV8/100*(AO8-100)*HAVERQ!D51/1000+(AT8-100)*AY8/$BA8 -> 0.68206926 | BE8: =$AV8/100*(AP8-100)*HAVERQ!E51/1000+(AU8-100)*AZ8/$BA8 -> 0.15957603 | BF8: =BG8-BE8-BD8-BC8 -> 2.3119699 | BG8: =$AV8/100*(AQ8-100)*1000/1000+(AV8-100)*BA8/$BA8 -> 4.0801022 | BH8: =100*((DataQ!V159/DataQ!V155)-1) -> 4.0801022 | BI8: 2 | BK8: 41760 | BL8: =HAVERM!B299 -> 2.56 | BM8: =HAVERM!C299 -> 3.72 | BQ8: =BL8-BT8 -> #N/A | BR8: =BM8-BU8 -> #N/A | BT8: =HAVERM!D299 -> #N/A | BU8: =HAVERM!E299 -> #N/A | BY8: 0 | CA8: 44652 | CB8: =HAVERM!G394-HAVERM!G$389 -> 0.45 | CC8: =HAVERM!H394-HAVERM!H$389 -> 0.03 | CD8: 0
S9: Q2 2024 | T9: =100*((DataQ!D212/DataQ!D211)-1) -> 0.57158477 | U9: =T9 -> 0.57158477 | W9: =DataQ!D212 -> 573956 | Y9: Growth | AE9: =100*((AE6/AE4)-1) -> 1.2936222 | AG9: 40634 | AH9: =100*((DataQ!U160/DataQ!U156)-1) -> 2.564095 | AI9: =100*((DataQ!V160/DataQ!V156)-1) -> 4.4013389 | AJ9: =AH9-AI9 -> -1.8372439 | AK9: 0 | AM9: 40634 | AN9: =DataQ!W160/DataQ!W158*100 -> 104.19184 | AO9: =DataQ!X160/DataQ!X158*100 -> 113.64632 | AP9: =DataQ!Y160/DataQ!Y158*100 -> 105.06382 | AQ9: =DataQ!V160/DataQ!V158*100 -> 103.09392 | AS9: =DataQ!W158/DataQ!W156*100 -> 102.39753 | AT9: =DataQ!X158/DataQ!X156*100 -> 100.1556 | AU9: =DataQ!Y158/DataQ!Y156*100 -> 101.33679 | AV9: =DataQ!V158/DataQ!V156*100 -> 101.26818 | AX9: =HAVERQ!C52*AN9/$AQ9 -> 161.70395 | AY9: =HAVERQ!D52*AO9/$AQ9 -> 47.401357 | AZ9: =HAVERQ!E52*AP9/$AQ9 -> 44.840743 | BA9: =1000*AQ9/$AQ9 -> 1000 | BC9: =$AV9/100*(AN9-100)*HAVERQ!C52/1000+(AS9-100)*AX9/$BA9 -> 1.0668904 | BD9: =$AV9/100*(AO9-100)*HAVERQ!D52/1000+(AT9-100)*AY9/$BA9 -> 0.6016092 | BE9: =$AV9/100*(AP9-100)*HAVERQ!E52/1000+(AU9-100)*AZ9/$BA9 -> 0.28557646 | BF9: =BG9-BE9-BD9-BC9 -> 2.4472629 | BG9: =$AV9/100*(AQ9-100)*1000/1000+(AV9-100)*BA9/$BA9 -> 4.4013389 | BH9: =100*((DataQ!V160/DataQ!V156)-1) -> 4.4013389 | BI9: 2 | BK9: 41791 | BL9: =HAVERM!B300 -> 2.6 | BM9: =HAVERM!C300 -> 3.69 | BQ9: =BL9-BT9 -> #N/A | BR9: =BM9-BU9 -> #N/A | BT9: =HAVERM!D300 -> #N/A | BU9: =HAVERM!E300 -> #N/A | BY9: 0 | CA9: 44682 | CB9: =HAVERM!G395-HAVERM!G$389 -> 0.65 | CC9: =HAVERM!H395-HAVERM!H$389 -> 0.06 | CD9: 0
S10: Q3 2024 | T10: =100*((DataQ!D213/DataQ!D212)-1) -> 0.36912237 | U10: =T10 -> 0.36912237 | W10: =W9*(1+U10/100) -> 576074.6 | AE10: =Z8/AE9 -> 0.28649386 | AG10: 40725 | AH10: =100*((DataQ!U161/DataQ!U157)-1) -> 2.2488754 | AI10: =100*((DataQ!V161/DataQ!V157)-1) -> 4.6857681 | AJ10: =AH10-AI10 -> -2.4368927 | AK10: 0 | AM10: 40725 | AN10: =DataQ!W161/DataQ!W158*100 -> 105.43807 | AO10: =DataQ!X161/DataQ!X158*100 -> 113.2733 | AP10: =DataQ!Y161/DataQ!Y158*100 -> 109.14893 | AQ10: =DataQ!V161/DataQ!V158*100 -> 103.68325 | AS10: =DataQ!W158/DataQ!W157*100 -> 101.68971 | AT10: =DataQ!X158/DataQ!X157*100 -> 102.97695 | AU10: =DataQ!Y158/DataQ!Y157*100 -> 101.59966 | AV10: =DataQ!V158/DataQ!V157*100 -> 100.96691 | AX10: =HAVERQ!C53*AN10/$AQ10 -> 162.70797 | AY10: =HAVERQ!D53*AO10/$AQ10 -> 46.977232 | AZ10: =HAVERQ!E53*AP10/$AQ10 -> 46.319467 | BA10: =1000*AQ10/$AQ10 -> 1000 | BC10: =$AV10/100*(AN10-100)*HAVERQ!C53/1000+(AS10-100)*AX10/$BA10 -> 1.1534332 | BD10: =$AV10/100*(AO10-100)*HAVERQ!D53/1000+(AT10-100)*AY10/$BA10 -> 0.71611967 | BE10: =$AV10/100*(AP10-100)*HAVERQ!E53/1000+(AU10-100)*AZ10/$BA10 -> 0.48054062 | BF10: =BG10-BE10-BD10-BC10 -> 2.3356747 | BG10: =$AV10/100*(AQ10-100)*1000/1000+(AV10-100)*BA10/$BA10 -> 4.6857681 | BH10: =100*((DataQ!V161/DataQ!V157)-1) -> 4.6857681 | BI10: 2 | BK10: 41821 | BL10: =HAVERM!B301 -> 2.54 | BM10: =HAVERM!C301 -> 3.78 | BQ10: =BL10-BT10 -> #N/A | BR10: =BM10-BU10 -> #N/A | BT10: =HAVERM!D301 -> #N/A | BU10: =HAVERM!E301 -> #N/A | BY10: 0 | CA10: 44713 | CB10: =HAVERM!G396-HAVERM!G$389 -> 0.78 | CC10: =HAVERM!H396-HAVERM!H$389 -> 0.1 | CD10: 0
S11: Q4 2024 | T11: =100*((DataQ!D214/DataQ!D213)-1) -> 0.39369901 | U11: =T11 -> 0.39369901 | W11: =W10*(1+U11/100) -> 578342.6 | AG11: 40817 | AH11: =100*((DataQ!U162/DataQ!U158)-1) -> 1.9345313 | AI11: =100*((DataQ!V162/DataQ!V158)-1) -> 4.6777127 | AJ11: =AH11-AI11 -> -2.7431815 | AK11: 0 | AM11: 40817 | AN11: =DataQ!W162/DataQ!W158*100 -> 105.58912 | AO11: =DataQ!X162/DataQ!X158*100 -> 112.58937 | AP11: =DataQ!Y162/DataQ!Y158*100 -> 118.97871 | AQ11: =DataQ!V162/DataQ!V158*100 -> 104.67771 | AS11: =DataQ!W158/DataQ!W158*100 -> 100 | AT11: =DataQ!X158/DataQ!X158*100 -> 100 | AU11: =DataQ!Y158/DataQ!Y158*100 -> 100 | AV11: =DataQ!V158/DataQ!V158*100 -> 100 | AX11: =HAVERQ!C54*AN11/$AQ11 -> 161.39309 | AY11: =HAVERQ!D54*AO11/$AQ11 -> 46.249989 | AZ11: =HAVERQ!E54*AP11/$AQ11 -> 50.011251 | BA11: =1000*AQ11/$AQ11 -> 1000 | BC11: =$AV11/100*(AN11-100)*HAVERQ!C54/1000+(AS11-100)*AX11/$BA11 -> 0.89425918 | BD11: =$AV11/100*(AO11-100)*HAVERQ!D54/1000+(AT11-100)*AY11/$BA11 -> 0.54134303 | BE11: =$AV11/100*(AP11-100)*HAVERQ!E54/1000+(AU11-100)*AZ11/$BA11 -> 0.83506338 | BF11: =BG11-BE11-BD11-BC11 -> 2.4070471 | BG11: =$AV11/100*(AQ11-100)*1000/1000+(AV11-100)*BA11/$BA11 -> 4.6777127 | BH11: =100*((DataQ!V162/DataQ!V158)-1) -> 4.6777127 | BI11: 2 | BK11: 41852 | BL11: =HAVERM!B302 -> 2.54 | BM11: =HAVERM!C302 -> 3.76 | BQ11: =BL11-BT11 -> 1.5588 | BR11: =BM11-BU11 -> 2.15 | BT11: =HAVERM!D302 -> 0.9812 | BU11: =HAVERM!E302 -> 1.61 | BY11: 0 | CA11: 44743 | CB11: =HAVERM!G397-HAVERM!G$389 -> 0.86 | CC11: =HAVERM!H397-HAVERM!H$389 -> 0.11 | CD11: 0
S12: Q1 2025 | T12: =100*((DataQ!D215/DataQ!D214)-1) -> 0.41191847 | U12: 0.3 | W12: =W11*(1+U12/100) -> 580077.63 | AG12: 40909 | AH12: =100*((DataQ!U163/DataQ!U159)-1) -> 0.51318911 | AI12: =100*((DataQ!V163/DataQ!V159)-1) -> 3.4845624 | AJ12: =AH12-AI12 -> -2.9713732 | AK12: 0 | AM12: 40909 | AN12: =DataQ!W163/DataQ!W162*100 -> 101.46638 | AO12: =DataQ!X163/DataQ!X162*100 -> 101.60138 | AP12: =DataQ!Y163/DataQ!Y162*100 -> 99.606588 | AQ12: =DataQ!V163/DataQ!V162*100 -> 100.31668 | AS12: =DataQ!W162/DataQ!W159*100 -> 103.36415 | AT12: =DataQ!X162/DataQ!X159*100 -> 103.45613 | AU12: =DataQ!Y162/DataQ!Y159*100 -> 114.12246 | AV12: =DataQ!V162/DataQ!V159*100 -> 103.15788 | AX12: =HAVERQ!C55*AN12/$AQ12 -> 155.76496 | AY12: =HAVERQ!D55*AO12/$AQ12 -> 46.589098 | AZ12: =HAVERQ!E55*AP12/$AQ12 -> 55.603605 | BA12: =1000*AQ12/$AQ12 -> 1000 | BC12: =$AV12/100*(AN12-100)*HAVERQ!C55/1000+(AS12-100)*AX12/$BA12 -> 0.75697078 | BD12: =$AV12/100*(AO12-100)*HAVERQ!D55/1000+(AT12-100)*AY12/$BA12 -> 0.23700756 | BE12: =$AV12/100*(AP12-100)*HAVERQ!E55/1000+(AU12-100)*AZ12/$BA12 -> 0.7625328 | BF12: =BG12-BE12-BD12-BC12 -> 1.7280512 | BG12: =$AV12/100*(AQ12-100)*1000/1000+(AV12-100)*BA12/$BA12 -> 3.4845624 | BH12: =100*((DataQ!V163/DataQ!V159)-1) -> 3.4845624 | BI12: 2 | BK12: 41883 | BL12: =HAVERM!B303 -> 2.46 | BM12: =HAVERM!C303 -> 3.61 | BQ12: =BL12-BT12 -> 1.4812727 | BR12: =BM12-BU12 -> 1.9375955 | BT12: =HAVERM!D303 -> 0.97872727 | BU12: =HAVERM!E303 -> 1.6724045 | BY12: 0 | CA12: 44774 | CB12: =HAVERM!G398-HAVERM!G$389 -> 1.17 | CC12: =HAVERM!H398-HAVERM!H$389 -> 0.16 | CD12: 0
S13: Q2 2025 | T13: =100*((DataQ!D216/DataQ!D215)-1) -> 0.4400879 | U13: 0.3 | W13: =W12*(1+U13/100) -> 581817.86 | AG13: 41000 | AH13: =100*((DataQ!U164/DataQ!U160)-1) -> 1.6176619 | AI13: =100*((DataQ!V164/DataQ!V160)-1) -> 2.6795284 | AJ13: =AH13-AI13 -> -1.0618665 | AK13: 0 | AM13: 41000 | AN13: =DataQ!W164/DataQ!W162*100 -> 102.43205 | AO13: =DataQ!X164/DataQ!X162*100 -> 102.45723 | AP13: =DataQ!Y164/DataQ!Y162*100 -> 98.140204 | AQ13: =DataQ!V164/DataQ!V162*100 -> 101.12597 | AS13: =DataQ!W162/DataQ!W160*100 -> 101.34106 | AT13: =DataQ!X162/DataQ!X160*100 -> 99.069967 | AU13: =DataQ!Y162/DataQ!Y160*100 -> 113.24423 | AV13: =DataQ!V162/DataQ!V160*100 -> 101.53626 | AX13: =HAVERQ!C56*AN13/$AQ13 -> 155.98897 | AY13: =HAVERQ!D56*AO13/$AQ13 -> 46.605563 | AZ13: =HAVERQ!E56*AP13/$AQ13 -> 54.346587 | BA13: =1000*AQ13/$AQ13 -> 1000 | BC13: =$AV13/100*(AN13-100)*HAVERQ!C56/1000+(AS13-100)*AX13/$BA13 -> 0.5894803 | BD13: =$AV13/100*(AO13-100)*HAVERQ!D56/1000+(AT13-100)*AY13/$BA13 -> 0.071424561 | BE13: =$AV13/100*(AP13-100)*HAVERQ!E56/1000+(AU13-100)*AZ13/$BA13 -> 0.61403004 | BF13: =BG13-BE13-BD13-BC13 -> 1.4045935 | BG13: =$AV13/100*(AQ13-100)*1000/1000+(AV13-100)*BA13/$BA13 -> 2.6795284 | BH13: =100*((DataQ!V164/DataQ!V160)-1) -> 2.6795284 | BI13: 2 | BK13: 41913 | BL13: =HAVERM!B304 -> 2.21 | BM13: =HAVERM!C304 -> 3.27 | BQ13: =BL13-BT13 -> 1.3656522 | BR13: =BM13-BU13 -> 1.8341696 | BT13: =HAVERM!D304 -> 0.84434783 | BU13: =HAVERM!E304 -> 1.4358304 | BY13: 0 | CA13: 44805 | CB13: =HAVERM!G399-HAVERM!G$389 -> 1.38 | CC13: =HAVERM!H399-HAVERM!H$389 -> 0.23 | CD13: 0
S14: Q3 2025 | T14: =100*((DataQ!D217/DataQ!D216)-1) -> 0.43003316 | U14: 0.3 | W14: =W13*(1+U14/100) -> 583563.31 | AG14: 41091 | AH14: =100*((DataQ!U165/DataQ!U161)-1) -> 1.8328371 | AI14: =100*((DataQ!V165/DataQ!V161)-1) -> 2.3801029 | AJ14: =AH14-AI14 -> -0.54726574 | AK14: 0 | AM14: 41091 | AN14: =DataQ!W165/DataQ!W162*100 -> 102.93276 | AO14: =DataQ!X165/DataQ!X162*100 -> 100.85594 | AP14: =DataQ!Y165/DataQ!Y162*100 -> 98.140204 | AQ14: =DataQ!V165/DataQ!V162*100 -> 101.40747 | AS14: =DataQ!W162/DataQ!W161*100 -> 100.14326 | AT14: =DataQ!X162/DataQ!X161*100 -> 99.396213 | AU14: =DataQ!Y162/DataQ!Y161*100 -> 109.00585 | AV14: =DataQ!V162/DataQ!V161*100 -> 100.95914 | AX14: =HAVERQ!C57*AN14/$AQ14 -> 156.31635 | AY14: =HAVERQ!D57*AO14/$AQ14 -> 45.749817 | AZ14: =HAVERQ!E57*AP14/$AQ14 -> 54.195727 | BA14: =1000*AQ14/$AQ14 -> 1000 | BC14: =$AV14/100*(AN14-100)*HAVERQ!C57/1000+(AS14-100)*AX14/$BA14 -> 0.47837088 | BD14: =$AV14/100*(AO14-100)*HAVERQ!D57/1000+(AT14-100)*AY14/$BA14 -> 0.012127566 | BE14: =$AV14/100*(AP14-100)*HAVERQ!E57/1000+(AU14-100)*AZ14/$BA14 -> 0.38293097 | BF14: =BG14-BE14-BD14-BC14 -> 1.5066734 | BG14: =$AV14/100*(AQ14-100)*1000/1000+(AV14-100)*BA14/$BA14 -> 2.3801029 | BH14: =100*((DataQ!V165/DataQ!V161)-1) -> 2.3801029 | BI14: 2 | BK14: 41944 | BL14: =HAVERM!B305 -> 2.17 | BM14: =HAVERM!C305 -> 3.21 | BQ14: =BL14-BT14 -> 1.4026833 | BR14: =BM14-BU14 -> 1.8787167 | BT14: =HAVERM!D305 -> 0.76731667 | BU14: =HAVERM!E305 -> 1.3312833 | BY14: 0 | CA14: 44835 | CB14: =HAVERM!G400-HAVERM!G$389 -> 1.63 | CC14: =HAVERM!H400-HAVERM!H$389 -> 0.27 | CD14: 0
S15: Q4 2025 | T15: =100*((DataQ!D218/DataQ!D217)-1) -> 0.4449043 | U15: 0.3 | W15: =W14*(1+U15/100) -> 585314 | AG15: 41183 | AH15: =100*((DataQ!U166/DataQ!U162)-1) -> 1.1678758 | AI15: =100*((DataQ!V166/DataQ!V162)-1) -> 2.6741802 | AJ15: =AH15-AI15 -> -1.5063044 | AK15: 0 | AM15: 41183 | AN15: =DataQ!W166/DataQ!W162*100 -> 104.32761 | AO15: =DataQ!X166/DataQ!X162*100 -> 101.04917 | AP15: =DataQ!Y166/DataQ!Y162*100 -> 101.03719 | AQ15: =DataQ!V166/DataQ!V162*100 -> 102.67418 | AS15: =DataQ!W162/DataQ!W162*100 -> 100 | AT15: =DataQ!X162/DataQ!X162*100 -> 100 | AU15: =DataQ!Y162/DataQ!Y162*100 -> 100 | AV15: =DataQ!V162/DataQ!V162*100 -> 100 | AX15: =HAVERQ!C58*AN15/$AQ15 -> 156.47996 | AY15: =HAVERQ!D58*AO15/$AQ15 -> 45.271965 | AZ15: =HAVERQ!E58*AP15/$AQ15 -> 55.107161 | BA15: =1000*AQ15/$AQ15 -> 1000 | BC15: =$AV15/100*(AN15-100)*HAVERQ!C58/1000+(AS15-100)*AX15/$BA15 -> 0.66645152 | BD15: =$AV15/100*(AO15-100)*HAVERQ!D58/1000+(AT15-100)*AY15/$BA15 -> 0.048261913 | BE15: =$AV15/100*(AP15-100)*HAVERQ!E58/1000+(AU15-100)*AZ15/$BA15 -> 0.058082575 | BF15: =BG15-BE15-BD15-BC15 -> 1.9013842 | BG15: =$AV15/100*(AQ15-100)*1000/1000+(AV15-100)*BA15/$BA15 -> 2.6741802 | BH15: =100*((DataQ!V166/DataQ!V162)-1) -> 2.6741802 | BI15: 2 | BK15: 41974 | BL15: =HAVERM!B306 -> 2.08 | BM15: =HAVERM!C306 -> 3.21 | BQ15: =BL15-BT15 -> 1.3790636 | BR15: =BM15-BU15 -> 2.0094227 | BT15: =HAVERM!D306 -> 0.70093636 | BU15: =HAVERM!E306 -> 1.2005773 | BY15: 0 | CA15: 44866 | CB15: =HAVERM!G401-HAVERM!G$389 -> 2.12 | CC15: =HAVERM!H401-HAVERM!H$389 -> 0.37 | CD15: 0
AG16: 41275 | AH16: =100*((DataQ!U167/DataQ!U163)-1) -> 0.51056893 | AI16: =100*((DataQ!V167/DataQ!V163)-1) -> 2.7709541 | AJ16: =AH16-AI16 -> -2.2603852 | AK16: 0 | AM16: 41275 | AN16: =DataQ!W167/DataQ!W166*100 -> 101.98834 | AO16: =DataQ!X167/DataQ!X166*100 -> 100.57377 | AP16: =DataQ!Y167/DataQ!Y166*100 -> 104.63717 | AQ16: =DataQ!V167/DataQ!V166*100 -> 100.41123 | AS16: =DataQ!W166/DataQ!W163*100 -> 102.81987 | AT16: =DataQ!X166/DataQ!X163*100 -> 99.456495 | AU16: =DataQ!Y166/DataQ!Y163*100 -> 101.43625 | AV16: =DataQ!V166/DataQ!V163*100 -> 102.35006 | AX16: =HAVERQ!C59*AN16/$AQ16 -> 152.35598 | AY16: =HAVERQ!D59*AO16/$AQ16 -> 40.06475 | AZ16: =HAVERQ!E59*AP16/$AQ16 -> 50.020145 | BA16: =1000*AQ16/$AQ16 -> 1000 | BC16: =$AV16/100*(AN16-100)*HAVERQ!C59/1000+(AS16-100)*AX16/$BA16 -> 0.73488471 | BD16: =$AV16/100*(AO16-100)*HAVERQ!D59/1000+(AT16-100)*AY16/$BA16 -> 0.0017147743 | BE16: =$AV16/100*(AP16-100)*HAVERQ!E59/1000+(AU16-100)*AZ16/$BA16 -> 0.29965661 | BF16: =BG16-BE16-BD16-BC16 -> 1.734698 | BG16: =$AV16/100*(AQ16-100)*1000/1000+(AV16-100)*BA16/$BA16 -> 2.7709541 | BH16: =100*((DataQ!V167/DataQ!V163)-1) -> 2.7709541 | BI16: 2 | BK16: 42005 | BL16: =HAVERM!B307 -> 2.01 | BM16: =HAVERM!C307 -> 3.09 | BQ16: =BL16-BT16 -> 1.4174286 | BR16: =BM16-BU16 -> 2.1329952 | BT16: =HAVERM!D307 -> 0.59257143 | BU16: =HAVERM!E307 -> 0.95700476 | BY16: 0 | CA16: 44896 | CB16: =HAVERM!G402-HAVERM!G$389 -> 2.44 | CC16: =HAVERM!H402-HAVERM!H$389 -> 0.49 | CD16: 0
S17: 2023 | W17: =SUM(W4:W7) -> 2273126 | AG17: 41365 | AH17: =100*((DataQ!U168/DataQ!U164)-1) -> 2.0983935 | AI17: =100*((DataQ!V168/DataQ!V164)-1) -> 2.6791962 | AJ17: =AH17-AI17 -> -0.58080276 | AK17: 0 | AM17: 41365 | AN17: =DataQ!W168/DataQ!W166*100 -> 102.91399 | AO17: =DataQ!X168/DataQ!X166*100 -> 99.398934 | AP17: =DataQ!Y168/DataQ!Y166*100 -> 104.60178 | AQ17: =DataQ!V168/DataQ!V166*100 -> 101.13091 | AS17: =DataQ!W166/DataQ!W164*100 -> 101.85055 | AT17: =DataQ!X166/DataQ!X164*100 -> 98.625707 | AU17: =DataQ!Y166/DataQ!Y164*100 -> 102.95188 | AV17: =DataQ!V166/DataQ!V164*100 -> 101.53097 | AX17: =HAVERQ!C60*AN17/$AQ17 -> 152.64471 | AY17: =HAVERQ!D60*AO17/$AQ17 -> 39.314956 | AZ17: =HAVERQ!E60*AP17/$AQ17 -> 49.647385 | BA17: =1000*AQ17/$AQ17 -> 1000 | BC17: =$AV17/100*(AN17-100)*HAVERQ!C60/1000+(AS17-100)*AX17/$BA17 -> 0.72626734 | BD17: =$AV17/100*(AO17-100)*HAVERQ!D60/1000+(AT17-100)*AY17/$BA17 -> -0.078440964 | BE17: =$AV17/100*(AP17-100)*HAVERQ!E60/1000+(AU17-100)*AZ17/$BA17 -> 0.37082032 | BF17: =BG17-BE17-BD17-BC17 -> 1.6605495 | BG17: =$AV17/100*(AQ17-100)*1000/1000+(AV17-100)*BA17/$BA17 -> 2.6791962 | BH17: =100*((DataQ!V168/DataQ!V164)-1) -> 2.6791962 | BI17: 2 | BK17: 42036 | BL17: =HAVERM!B308 -> 1.96 | BM17: =HAVERM!C308 -> 3.05 | BQ17: =BL17-BT17 -> 1.280755 | BR17: =BM17-BU17 -> 1.92882 | BT17: =HAVERM!D308 -> 0.679245 | BU17: =HAVERM!E308 -> 1.12118 | BY17: 0 | CA17: 44927 | CB17: =HAVERM!G403-HAVERM!G$389 -> 2.6 | CC17: =HAVERM!H403-HAVERM!H$389 -> 0.53 | CD17: 0
S18: 2024 | T18: =100*((DataA!B58/DataA!B57)-1) -> 1.1412126 | U18: =100*((W18/W17)-1) -> 1.1412126 | W18: =SUM(W8:W11) -> 2299067.2 | AG18: 41456 | AH18: =100*((DataQ!U169/DataQ!U165)-1) -> 0.64794816 | AI18: =100*((DataQ!V169/DataQ!V165)-1) -> 2.7411484 | AJ18: =AH18-AI18 -> -2.0932002 | AK18: 0 | AM18: 41456 | AN18: =DataQ!W169/DataQ!W166*100 -> 103.32537 | AO18: =DataQ!X169/DataQ!X166*100 -> 100.43713 | AP18: =DataQ!Y169/DataQ!Y166*100 -> 104.84956 | AQ18: =DataQ!V169/DataQ!V166*100 -> 101.47361 | AS18: =DataQ!W166/DataQ!W165*100 -> 101.35511 | AT18: =DataQ!X166/DataQ!X165*100 -> 100.1916 | AU18: =DataQ!Y166/DataQ!Y165*100 -> 102.95188 | AV18: =DataQ!V166/DataQ!V165*100 -> 101.24913 | AX18: =HAVERQ!C61*AN18/$AQ18 -> 152.73731 | AY18: =HAVERQ!D61*AO18/$AQ18 -> 39.59143 | AZ18: =HAVERQ!E61*AP18/$AQ18 -> 49.596925 | BA18: =1000*AQ18/$AQ18 -> 1000 | BC18: =$AV18/100*(AN18-100)*HAVERQ!C61/1000+(AS18-100)*AX18/$BA18 -> 0.71201207 | BD18: =$AV18/100*(AO18-100)*HAVERQ!D61/1000+(AT18-100)*AY18/$BA18 -> 0.025289215 | BE18: =$AV18/100*(AP18-100)*HAVERQ!E61/1000+(AU18-100)*AZ18/$BA18 -> 0.38209103 | BF18: =BG18-BE18-BD18-BC18 -> 1.6217561 | BG18: =$AV18/100*(AQ18-100)*1000/1000+(AV18-100)*BA18/$BA18 -> 2.7411484 | BH18: =100*((DataQ!V169/DataQ!V165)-1) -> 2.7411484 | BI18: 2 | BK18: 42064 | BL18: =HAVERM!B309 -> 1.99 | BM18: =HAVERM!C309 -> 2.98 | BQ18: =BL18-BT18 -> 1.3028524 | BR18: =BM18-BU18 -> 1.8285952 | BT18: =HAVERM!D309 -> 0.68714762 | BU18: =HAVERM!E309 -> 1.1514048 | BY18: 0 | CA18: 44958 | CB18: =HAVERM!G404-HAVERM!G$389 -> 2.95 | CC18: =HAVERM!H404-HAVERM!H$389 -> 0.63 | CD18: 0
S19: 2025 | T19: =100*((DataA!B59/DataA!B58)-1) -> 1.7016597 | U19: =100*((W19/W18)-1) -> 1.379064 | W19: =SUM(W12:W15) -> 2330772.8 | AG19: 41548 | AH19: =100*((DataQ!U170/DataQ!U166)-1) -> 1.0101082 | AI19: =100*((DataQ!V170/DataQ!V166)-1) -> 2.0904694 | AJ19: =AH19-AI19 -> -1.0803612 | AK19: 0 | AM19: 41548 | AN19: =DataQ!W170/DataQ!W166*100 -> 103.73675 | AO19: =DataQ!X170/DataQ!X166*100 -> 96.967213 | AP19: =DataQ!Y170/DataQ!Y166*100 -> 106.97342 | AQ19: =DataQ!V170/DataQ!V166*100 -> 102.09047 | AS19: =DataQ!W166/DataQ!W166*100 -> 100 | AT19: =DataQ!X166/DataQ!X166*100 -> 100 | AU19: =DataQ!Y166/DataQ!Y166*100 -> 100 | AV19: =DataQ!V166/DataQ!V166*100 -> 100 | AX19: =HAVERQ!C62*AN19/$AQ19 -> 152.41886 | AY19: =HAVERQ!D62*AO19/$AQ19 -> 37.99266 | AZ19: =HAVERQ!E62*AP19/$AQ19 -> 50.295824 | BA19: =1000*AQ19/$AQ19 -> 1000 | BC19: =$AV19/100*(AN19-100)*HAVERQ!C62/1000+(AS19-100)*AX19/$BA19 -> 0.56051305 | BD19: =$AV19/100*(AO19-100)*HAVERQ!D62/1000+(AT19-100)*AY19/$BA19 -> -0.12131148 | BE19: =$AV19/100*(AP19-100)*HAVERQ!E62/1000+(AU19-100)*AZ19/$BA19 -> 0.33472433 | BF19: =BG19-BE19-BD19-BC19 -> 1.3165435 | BG19: =$AV19/100*(AQ19-100)*1000/1000+(AV19-100)*BA19/$BA19 -> 2.0904694 | BH19: =100*((DataQ!V170/DataQ!V166)-1) -> 2.0904694 | BI19: 2 | BK19: 42095 | BL19: =HAVERM!B310 -> 1.95 | BM19: =HAVERM!C310 -> 2.92 | BQ19: =BL19-BT19 -> 1.3036476 | BR19: =BM19-BU19 -> 1.8594333 | BT19: =HAVERM!D310 -> 0.64635238 | BU19: =HAVERM!E310 -> 1.0605667 | BY19: 0 | CA19: 44986 | CB19: =HAVERM!G405-HAVERM!G$389 -> 3.09 | CC19: =HAVERM!H405-HAVERM!H$389 -> 0.73 | CD19: 0
AG20: 41640 | AH20: =100*((DataQ!U171/DataQ!U167)-1) -> 1.7416547 | AI20: =100*((DataQ!V171/DataQ!V167)-1) -> 1.774751 | AJ20: =AH20-AI20 -> -0.033096276 | AK20: 0 | AM20: 41640 | AN20: =DataQ!W171/DataQ!W170*100 -> 100.89227 | AO20: =DataQ!X171/DataQ!X170*100 -> 98.98563 | AP20: =DataQ!Y171/DataQ!Y170*100 -> 103.44146 | AQ20: =DataQ!V171/DataQ!V170*100 -> 100.1007 | AS20: =DataQ!W170/DataQ!W167*100 -> 101.71433 | AT20: =DataQ!X170/DataQ!X167*100 -> 96.414018 | AU20: =DataQ!Y170/DataQ!Y167*100 -> 102.23272 | AV20: =DataQ!V170/DataQ!V167*100 -> 101.67236 | AX20: =HAVERQ!C63*AN20/$AQ20 -> 158.2415 | AY20: =HAVERQ!D63*AO20/$AQ20 -> 34.610116 | AZ20: =HAVERQ!E63*AP20/$AQ20 -> 46.501829 | BA20: =1000*AQ20/$AQ20 -> 1000 | BC20: =$AV20/100*(AN20-100)*HAVERQ!C63/1000+(AS20-100)*AX20/$BA20 -> 0.41370617 | BD20: =$AV20/100*(AO20-100)*HAVERQ!D63/1000+(AT20-100)*AY20/$BA20 -> -0.16020795 | BE20: =$AV20/100*(AP20-100)*HAVERQ!E63/1000+(AU20-100)*AZ20/$BA20 -> 0.26128119 | BF20: =BG20-BE20-BD20-BC20 -> 1.2599716 | BG20: =$AV20/100*(AQ20-100)*1000/1000+(AV20-100)*BA20/$BA20 -> 1.774751 | BH20: =100*((DataQ!V171/DataQ!V167)-1) -> 1.774751 | BI20: 2 | BK20: 42125 | BL20: =HAVERM!B311 -> 1.9 | BM20: =HAVERM!C311 -> 2.86 | BQ20: =BL20-BT20 -> 1.1638524 | BR20: =BM20-BU20 -> 1.5970476 | BT20: =HAVERM!D311 -> 0.73614762 | BU20: =HAVERM!E311 -> 1.2629524 | BY20: 0 | CA20: 45017 | CB20: =HAVERM!G406-HAVERM!G$389 -> 3.21 | CC20: =HAVERM!H406-HAVERM!H$389 -> 0.74 | CD20: 0
U21: HMT survey - https://assets.publishing.service.gov.uk/media/66c4ce002e8f04b086cdf4f7/Forecasts_for_the_UK_economy_August_2024.pdf | AG21: 41730 | AH21: =100*((DataQ!U172/DataQ!U168)-1) -> -0.21261518 | AI21: =100*((DataQ!V172/DataQ!V168)-1) -> 1.7621111 | AJ21: =AH21-AI21 -> -1.9747263 | AK21: 0 | AM21: 41730 | AN21: =DataQ!W172/DataQ!W170*100 -> 100.39656 | AO21: =DataQ!X172/DataQ!X170*100 -> 98.901099 | AP21: =DataQ!Y172/DataQ!Y170*100 -> 102.61423 | AQ21: =DataQ!V172/DataQ!V170*100 -> 100.80564 | AS21: =DataQ!W170/DataQ!W168*100 -> 100.79947 | AT21: =DataQ!X170/DataQ!X168*100 -> 97.553574 | AU21: =DataQ!Y170/DataQ!Y168*100 -> 102.26731 | AV21: =DataQ!V170/DataQ!V168*100 -> 100.94883 | AX21: =HAVERQ!C64*AN21/$AQ21 -> 156.36288 | AY21: =HAVERQ!D64*AO21/$AQ21 -> 34.338738 | AZ21: =HAVERQ!E64*AP21/$AQ21 -> 45.807361 | BA21: =1000*AQ21/$AQ21 -> 1000 | BC21: =$AV21/100*(AN21-100)*HAVERQ!C64/1000+(AS21-100)*AX21/$BA21 -> 0.18785806 | BD21: =$AV21/100*(AO21-100)*HAVERQ!D64/1000+(AT21-100)*AY21/$BA21 -> -0.12283365 | BE21: =$AV21/100*(AP21-100)*HAVERQ!E64/1000+(AU21-100)*AZ21/$BA21 -> 0.22261602 | BF21: =BG21-BE21-BD21-BC21 -> 1.4744707 | BG21: =$AV21/100*(AQ21-100)*1000/1000+(AV21-100)*BA21/$BA21 -> 1.7621111 | BH21: =100*((DataQ!V172/DataQ!V168)-1) -> 1.7621111 | BI21: 2 | BK21: 42156 | BL21: =HAVERM!B312 -> 1.83 | BM21: =HAVERM!C312 -> 2.82 | BQ21: =BL21-BT21 -> 1.0497955 | BR21: =BM21-BU21 -> 1.4679636 | BT21: =HAVERM!D312 -> 0.78020455 | BU21: =HAVERM!E312 -> 1.3520364 | BY21: 0 | CA21: 45047 | CB21: =HAVERM!G407-HAVERM!G$389 -> 3.34 | CC21: =HAVERM!H407-HAVERM!H$389 -> 0.81 | CD21: 0
S22: 2024 | U22: 1.1 | AG22: 41821 | AH22: =100*((DataQ!U173/DataQ!U169)-1) -> 0.8583691 | AI22: =100*((DataQ!V173/DataQ!V169)-1) -> 1.4521783 | AJ22: =AH22-AI22 -> -0.59380922 | AK22: 0 | AM22: 41821 | AN22: =DataQ!W173/DataQ!W170*100 -> 100.13215 | AO22: =DataQ!X173/DataQ!X170*100 -> 98.506593 | AP22: =DataQ!Y173/DataQ!Y170*100 -> 102.51496 | AQ22: =DataQ!V173/DataQ!V170*100 -> 100.83917 | AS22: =DataQ!W170/DataQ!W169*100 -> 100.39814 | AT22: =DataQ!X170/DataQ!X169*100 -> 96.545184 | AU22: =DataQ!Y170/DataQ!Y169*100 -> 102.02563 | AV22: =DataQ!V170/DataQ!V169*100 -> 100.6079 | AX22: =HAVERQ!C65*AN22/$AQ22 -> 155.89922 | AY22: =HAVERQ!D65*AO22/$AQ22 -> 34.190391 | AZ22: =HAVERQ!E65*AP22/$AQ22 -> 45.747827 | BA22: =1000*AQ22/$AQ22 -> 1000 | BC22: =$AV22/100*(AN22-100)*HAVERQ!C65/1000+(AS22-100)*AX22/$BA22 -> 0.08294441 | BD22: =$AV22/100*(AO22-100)*HAVERQ!D65/1000+(AT22-100)*AY22/$BA22 -> -0.17070848 | BE22: =$AV22/100*(AP22-100)*HAVERQ!E65/1000+(AU22-100)*AZ22/$BA22 -> 0.20652916 | BF22: =BG22-BE22-BD22-BC22 -> 1.3334132 | BG22: =$AV22/100*(AQ22-100)*1000/1000+(AV22-100)*BA22/$BA22 -> 1.4521783 | BH22: =100*((DataQ!V173/DataQ!V169)-1) -> 1.4521783 | BI22: 2 | BK22: 42186 | BL22: =HAVERM!B313 -> 1.87 | BM22: =HAVERM!C313 -> 2.83 | BQ22: =BL22-BT22 -> 1.0242609 | BR22: =BM22-BU22 -> 1.422013 | BT22: =HAVERM!D313 -> 0.84573913 | BU22: =HAVERM!E313 -> 1.407987 | BY22: 0 | CA22: 45078 | CB22: =HAVERM!G408-HAVERM!G$389 -> 3.62 | CC22: =HAVERM!H408-HAVERM!H$389 -> 0.91 | CD22: 0
S23: 2025 | U23: 1.4 | AG23: 41913 | AH23: =100*((DataQ!U174/DataQ!U170)-1) -> 1.9999927 | AI23: =100*((DataQ!V174/DataQ!V170)-1) -> 0.90634441 | AJ23: =AH23-AI23 -> 1.0936483 | AK23: 0 | AM23: 41913 | AN23: =DataQ!W174/DataQ!W170*100 -> 100.19828 | AO23: =DataQ!X174/DataQ!X170*100 -> 92.927557 | AP23: =DataQ!Y174/DataQ!Y170*100 -> 102.18398 | AQ23: =DataQ!V174/DataQ!V170*100 -> 100.90634 | AS23: =DataQ!W170/DataQ!W170*100 -> 100 | AT23: =DataQ!X170/DataQ!X170*100 -> 100 | AU23: =DataQ!Y170/DataQ!Y170*100 -> 100 | AV23: =DataQ!V170/DataQ!V170*100 -> 100 | AX23: =HAVERQ!C66*AN23/$AQ23 -> 155.89833 | AY23: =HAVERQ!D66*AO23/$AQ23 -> 32.232507 | AZ23: =HAVERQ!E66*AP23/$AQ23 -> 45.569774 | BA23: =1000*AQ23/$AQ23 -> 1000 | BC23: =$AV23/100*(AN23-100)*HAVERQ!C66/1000+(AS23-100)*AX23/$BA23 -> 0.031130195 | BD23: =$AV23/100*(AO23-100)*HAVERQ!D66/1000+(AT23-100)*AY23/$BA23 -> -0.2475355 | BE23: =$AV23/100*(AP23-100)*HAVERQ!E66/1000+(AU23-100)*AZ23/$BA23 -> 0.098279318 | BF23: =BG23-BE23-BD23-BC23 -> 1.0244704 | BG23: =$AV23/100*(AQ23-100)*1000/1000+(AV23-100)*BA23/$BA23 -> 0.90634441 | BH23: =100*((DataQ!V174/DataQ!V170)-1) -> 0.90634441 | BI23: 2 | BK23: 42217 | BL23: =HAVERM!B314 -> 1.95 | BM23: =HAVERM!C314 -> 2.92 | BQ23: =BL23-BT23 -> 1.1439048 | BR23: =BM23-BU23 -> 1.5978381 | BT23: =HAVERM!D314 -> 0.80609524 | BU23: =HAVERM!E314 -> 1.3221619 | BY23: 0 | CA23: 45108 | CB23: =HAVERM!G409-HAVERM!G$389 -> 3.81 | CC23: =HAVERM!H409-HAVERM!H$389 -> 0.96 | CD23: 0
AG24: 42005 | AH24: =100*((DataQ!U175/DataQ!U171)-1) -> 2.2824609 | AI24: =100*((DataQ!V175/DataQ!V171)-1) -> 0.10060362 | AJ24: =AH24-AI24 -> 2.1818573 | AK24: 0 | AM24: 42005 | AN24: =DataQ!W175/DataQ!W174*100 -> 99.571174 | AO24: =DataQ!X175/DataQ!X174*100 -> 89.99396 | AP24: =DataQ!Y175/DataQ!Y174*100 -> 98.639896 | AQ24: =DataQ!V175/DataQ!V174*100 -> 99.301397 | AS24: =DataQ!W174/DataQ!W171*100 -> 99.312152 | AT24: =DataQ!X174/DataQ!X171*100 -> 93.879846 | AU24: =DataQ!Y174/DataQ!Y171*100 -> 98.784357 | AV24: =DataQ!V174/DataQ!V171*100 -> 100.80483 | AX24: =HAVERQ!C67*AN24/$AQ24 -> 153.41566 | AY24: =HAVERQ!D67*AO24/$AQ24 -> 30.813208 | AZ24: =HAVERQ!E67*AP24/$AQ24 -> 41.720215 | BA24: =1000*AQ24/$AQ24 -> 1000 | BC24: =$AV24/100*(AN24-100)*HAVERQ!C67/1000+(AS24-100)*AX24/$BA24 -> -0.17166501 | BD24: =$AV24/100*(AO24-100)*HAVERQ!D67/1000+(AT24-100)*AY24/$BA24 -> -0.531525 | BE24: =$AV24/100*(AP24-100)*HAVERQ!E67/1000+(AU24-100)*AZ24/$BA24 -> -0.10830101 | BF24: =BG24-BE24-BD24-BC24 -> 0.91209465 | BG24: =$AV24/100*(AQ24-100)*1000/1000+(AV24-100)*BA24/$BA24 -> 0.10060362 | BH24: =100*((DataQ!V175/DataQ!V171)-1) -> 0.10060362 | BI24: 2 | BK24: 42248 | BL24: =HAVERM!B315 -> 1.91 | BM24: =HAVERM!C315 -> 2.84 | BQ24: =BL24-BT24 -> 1.1834227 | BR24: =BM24-BU24 -> 1.6508136 | BT24: =HAVERM!D315 -> 0.72657727 | BU24: =HAVERM!E315 -> 1.1891864 | BY24: 0 | CA24: 45139 | CB24: =HAVERM!G410-HAVERM!G$389 -> 4.01 | CC24: =HAVERM!H410-HAVERM!H$389 -> 1.05 | CD24: 0
S25: H1 2024 | T25: =AVERAGE(T8:T9) -> 0.64475932 | U25: =AVERAGE(U8:U9) -> 0.64475932 | AG25: 42095 | AH25: =100*((DataQ!U176/DataQ!U172)-1) -> 2.5568184 | AI25: =100*((DataQ!V176/DataQ!V172)-1) -> -0.033266733 | AJ25: =AH25-AI25 -> 2.5900851 | AK25: 0 | AM25: 42095 | AN25: =DataQ!W176/DataQ!W174*100 -> 99.274341 | AO25: =DataQ!X176/DataQ!X174*100 -> 94.451181 | AP25: =DataQ!Y176/DataQ!Y174*100 -> 97.40939 | AQ25: =DataQ!V176/DataQ!V174*100 -> 99.866966 | AS25: =DataQ!W174/DataQ!W172*100 -> 99.802502 | AT25: =DataQ!X174/DataQ!X172*100 -> 93.960085 | AU25: =DataQ!Y174/DataQ!Y172*100 -> 99.580716 | AV25: =DataQ!V174/DataQ!V172*100 -> 100.0999 | AX25: =HAVERQ!C68*AN25/$AQ25 -> 152.09208 | AY25: =HAVERQ!D68*AO25/$AQ25 -> 32.15618 | AZ25: =HAVERQ!E68*AP25/$AQ25 -> 40.966443 | BA25: =1000*AQ25/$AQ25 -> 1000 | BC25: =$AV25/100*(AN25-100)*HAVERQ!C68/1000+(AS25-100)*AX25/$BA25 -> -0.14117473 | BD25: =$AV25/100*(AO25-100)*HAVERQ!D68/1000+(AT25-100)*AY25/$BA25 -> -0.3830689 | BE25: =$AV25/100*(AP25-100)*HAVERQ!E68/1000+(AU25-100)*AZ25/$BA25 -> -0.12609087 | BF25: =BG25-BE25-BD25-BC25 -> 0.61706777 | BG25: =$AV25/100*(AQ25-100)*1000/1000+(AV25-100)*BA25/$BA25 -> -0.033266733 | BH25: =100*((DataQ!V176/DataQ!V172)-1) -> -0.033266733 | BI25: 2 | BK25: 42278 | BL25: =HAVERM!B316 -> 1.87 | BM25: =HAVERM!C316 -> 2.78 | BQ25: =BL25-BT25 -> 1.2124818 | BR25: =BM25-BU25 -> 1.6863545 | BT25: =HAVERM!D316 -> 0.65751818 | BU25: =HAVERM!E316 -> 1.0936455 | BY25: 0 | CA25: 45170 | CB25: =HAVERM!G411-HAVERM!G$389 -> 4.11 | CC25: =HAVERM!H411-HAVERM!H$389 -> 1.14 | CD25: 0
S26: H2 2024 & 2025 | T26: =AVERAGE(T10:T15) -> 0.41496087 | U26: =AVERAGE(U10:U15) -> 0.3271369 | AG26: 42186 | AH26: =100*((DataQ!U177/DataQ!U173)-1) -> 2.9078085 | AI26: =100*((DataQ!V177/DataQ!V173)-1) -> 0.033355537 | AJ26: =AH26-AI26 -> 2.874453 | AK26: 0 | AM26: 42186 | AN26: =DataQ!W177/DataQ!W174*100 -> 98.680703 | AO26: =DataQ!X177/DataQ!X174*100 -> 92.207457 | AP26: =DataQ!Y177/DataQ!Y174*100 -> 96.664539 | AQ26: =DataQ!V177/DataQ!V174*100 -> 99.966766 | AS26: =DataQ!W174/DataQ!W173*100 -> 100.06604 | AT26: =DataQ!X174/DataQ!X173*100 -> 94.336383 | AU26: =DataQ!Y174/DataQ!Y173*100 -> 99.677147 | AV26: =DataQ!V174/DataQ!V173*100 -> 100.06661 | AX26: =HAVERQ!C69*AN26/$AQ26 -> 151.03167 | AY26: =HAVERQ!D69*AO26/$AQ26 -> 31.360958 | AZ26: =HAVERQ!E69*AP26/$AQ26 -> 40.612603 | BA26: =1000*AQ26/$AQ26 -> 1000 | BC26: =$AV26/100*(AN26-100)*HAVERQ!C69/1000+(AS26-100)*AX26/$BA26 -> -0.19201283 | BD26: =$AV26/100*(AO26-100)*HAVERQ!D69/1000+(AT26-100)*AY26/$BA26 -> -0.44273941 | BE26: =$AV26/100*(AP26-100)*HAVERQ!E69/1000+(AU26-100)*AZ26/$BA26 -> -0.15329459 | BF26: =BG26-BE26-BD26-BC26 -> 0.82140238 | BG26: =$AV26/100*(AQ26-100)*1000/1000+(AV26-100)*BA26/$BA26 -> 0.033355537 | BH26: =100*((DataQ!V177/DataQ!V173)-1) -> 0.033355537 | BI26: 2 | BK26: 42309 | BL26: =HAVERM!B317 -> 1.92 | BM26: =HAVERM!C317 -> 2.77 | BQ26: =BL26-BT26 -> 1.1974619 | BR26: =BM26-BU26 -> 1.5989381 | BT26: =HAVERM!D317 -> 0.7225381 | BU26: =HAVERM!E317 -> 1.1710619 | BY26: 0 | CA26: 45200 | CB26: =HAVERM!G412-HAVERM!G$389 -> 4.08 | CC26: =HAVERM!H412-HAVERM!H$389 -> 1.2 | CD26: 0
AG27: 42278 | AH27: =100*((DataQ!U178/DataQ!U174)-1) -> 1.8907563 | AI27: =100*((DataQ!V178/DataQ!V174)-1) -> 0.099800399 | AJ27: =AH27-AI27 -> 1.7909559 | AK27: 0 | AM27: 42278 | AN27: =DataQ!W178/DataQ!W174*100 -> 98.251946 | AO27: =DataQ!X178/DataQ!X174*100 -> 87.204396 | AP27: =DataQ!Y178/DataQ!Y174*100 -> 95.887337 | AQ27: =DataQ!V178/DataQ!V174*100 -> 100.0998 | AS27: =DataQ!W174/DataQ!W174*100 -> 100 | AT27: =DataQ!X174/DataQ!X174*100 -> 100 | AU27: =DataQ!Y174/DataQ!Y174*100 -> 100 | AV27: =DataQ!V174/DataQ!V174*100 -> 100 | AX27: =HAVERQ!C70*AN27/$AQ27 -> 150.1756 | AY27: =HAVERQ!D70*AO27/$AQ27 -> 29.619934 | AZ27: =HAVERQ!E70*AP27/$AQ27 -> 40.232529 | BA27: =1000*AQ27/$AQ27 -> 1000 | BC27: =$AV27/100*(AN27-100)*HAVERQ!C70/1000+(AS27-100)*AX27/$BA27 -> -0.26745219 | BD27: =$AV27/100*(AO27-100)*HAVERQ!D70/1000+(AT27-100)*AY27/$BA27 -> -0.43505054 | BE27: =$AV27/100*(AP27-100)*HAVERQ!E70/1000+(AU27-100)*AZ27/$BA27 -> -0.17273186 | BF27: =BG27-BE27-BD27-BC27 -> 0.97503499 | BG27: =$AV27/100*(AQ27-100)*1000/1000+(AV27-100)*BA27/$BA27 -> 0.099800399 | BH27: =100*((DataQ!V178/DataQ!V174)-1) -> 0.099800399 | BI27: 2 | BK27: 42339 | BL27: =HAVERM!B318 -> 1.9 | BM27: =HAVERM!C318 -> 2.75 | BQ27: =BL27-BT27 -> 1.1574739 | BR27: =BM27-BU27 -> 1.5918435 | BT27: =HAVERM!D318 -> 0.74252609 | BU27: =HAVERM!E318 -> 1.1581565 | BY27: 0 | CA27: 45231 | CB27: =HAVERM!G413-HAVERM!G$389 -> 4.1 | CC27: =HAVERM!H413-HAVERM!H$389 -> 1.26 | CD27: 0
AG28: 42370 | AH28: =100*((DataQ!U179/DataQ!U175)-1) -> 2.1617782 | AI28: =100*((DataQ!V179/DataQ!V175)-1) -> 0.33501508 | AJ28: =AH28-AI28 -> 1.8267632 | AK28: 0 | AM28: 42370 | AN28: =DataQ!W179/DataQ!W178*100 -> 99.832155 | AO28: =DataQ!X179/DataQ!X178*100 -> 94.993046 | AP28: =DataQ!Y179/DataQ!Y178*100 -> 98.986829 | AQ28: =DataQ!V179/DataQ!V178*100 -> 99.534736 | AS28: =DataQ!W178/DataQ!W175*100 -> 98.675091 | AT28: =DataQ!X178/DataQ!X175*100 -> 96.900276 | AU28: =DataQ!Y178/DataQ!Y175*100 -> 97.209487 | AV28: =DataQ!V178/DataQ!V175*100 -> 100.80402 | AX28: =HAVERQ!C71*AN28/$AQ28 -> 145.43327 | AY28: =HAVERQ!D71*AO28/$AQ28 -> 30.539866 | AZ28: =HAVERQ!E71*AP28/$AQ28 -> 34.807336 | BA28: =1000*AQ28/$AQ28 -> 1000 | BC28: =$AV28/100*(AN28-100)*HAVERQ!C71/1000+(AS28-100)*AX28/$BA28 -> -0.2172191 | BD28: =$AV28/100*(AO28-100)*HAVERQ!D71/1000+(AT28-100)*AY28/$BA28 -> -0.2561759 | BE28: =$AV28/100*(AP28-100)*HAVERQ!E71/1000+(AU28-100)*AZ28/$BA28 -> -0.13287643 | BF28: =BG28-BE28-BD28-BC28 -> 0.9412865 | BG28: =$AV28/100*(AQ28-100)*1000/1000+(AV28-100)*BA28/$BA28 -> 0.33501508 | BH28: =100*((DataQ!V179/DataQ!V175)-1) -> 0.33501508 | BI28: 2 | BK28: 42370 | BL28: =HAVERM!B319 -> 1.93 | BM28: =HAVERM!C319 -> 2.68 | BQ28: =BL28-BT28 -> 1.3224 | BR28: =BM28-BU28 -> 1.6969905 | BT28: =HAVERM!D319 -> 0.6076 | BU28: =HAVERM!E319 -> 0.98300952 | BW28: =BL28-BL4 -> -0.44 | BY28: 0 | CA28: 45261 | CB28: =HAVERM!G414-HAVERM!G$389 -> 4.12 | CC28: =HAVERM!H414-HAVERM!H$389 -> 1.35 | CD28: 0
AG29: 42461 | AH29: =100*((DataQ!U180/DataQ!U176)-1) -> 2.5623409 | AI29: =100*((DataQ!V180/DataQ!V176)-1) -> 0.33307784 | AJ29: =AH29-AI29 -> 2.2292631 | AK29: 0 | AM29: 42461 | AN29: =DataQ!W180/DataQ!W178*100 -> 99.32863 | AO29: =DataQ!X180/DataQ!X178*100 -> 101.18219 | AP29: =DataQ!Y180/DataQ!Y178*100 -> 97.737254 | AQ29: =DataQ!V180/DataQ!V178*100 -> 100.0997 | AS29: =DataQ!W178/DataQ!W176*100 -> 98.970133 | AT29: =DataQ!X178/DataQ!X176*100 -> 92.327481 | AU29: =DataQ!Y178/DataQ!Y176*100 -> 98.437467 | AV29: =DataQ!V178/DataQ!V176*100 -> 100.23314 | AX29: =HAVERQ!C72*AN29/$AQ29 -> 143.88306 | AY29: =HAVERQ!D72*AO29/$AQ29 -> 32.346053 | AZ29: =HAVERQ!E72*AP29/$AQ29 -> 34.173967 | BA29: =1000*AQ29/$AQ29 -> 1000 | BC29: =$AV29/100*(AN29-100)*HAVERQ!C72/1000+(AS29-100)*AX29/$BA29 -> -0.24575603 | BD29: =$AV29/100*(AO29-100)*HAVERQ!D72/1000+(AT29-100)*AY29/$BA29 -> -0.21025731 | BE29: =$AV29/100*(AP29-100)*HAVERQ!E72/1000+(AU29-100)*AZ29/$BA29 -> -0.13277868 | BF29: =BG29-BE29-BD29-BC29 -> 0.92186986 | BG29: =$AV29/100*(AQ29-100)*1000/1000+(AV29-100)*BA29/$BA29 -> 0.33307784 | BH29: =100*((DataQ!V180/DataQ!V176)-1) -> 0.33307784 | BI29: 2 | BK29: 42401 | BL29: =HAVERM!B320 -> 1.95 | BM29: =HAVERM!C320 -> 2.73 | BQ29: =BL29-BT29 -> 1.5433238 | BR29: =BM29-BU29 -> 2.1155333 | BT29: =HAVERM!D320 -> 0.40667619 | BU29: =HAVERM!E320 -> 0.61446667 | BW29: =BL29-BL5 -> -0.43 | BY29: 0 | CA29: 45292 | CB29: =HAVERM!G415-HAVERM!G$389 -> 4.14 | CC29: =HAVERM!H415-HAVERM!H$389 -> 1.4 | CD29: 0
AG30: 42552 | AH30: =100*((DataQ!U181/DataQ!U177)-1) -> 2.3432045 | AI30: =100*((DataQ!V181/DataQ!V177)-1) -> 0.69883504 | AJ30: =AH30-AI30 -> 1.6443695 | AK30: 0 | AM30: 42552 | AN30: =DataQ!W181/DataQ!W178*100 -> 99.227925 | AO30: =DataQ!X181/DataQ!X178*100 -> 103.75522 | AP30: =DataQ!Y181/DataQ!Y178*100 -> 97.973658 | AQ30: =DataQ!V181/DataQ!V178*100 -> 100.565 | AS30: =DataQ!W178/DataQ!W177*100 -> 99.565511 | AT30: =DataQ!X178/DataQ!X177*100 -> 94.574125 | AU30: =DataQ!Y178/DataQ!Y177*100 -> 99.19598 | AV30: =DataQ!V178/DataQ!V177*100 -> 100.13308 | AX30: =HAVERQ!C73*AN30/$AQ30 -> 143.07213 | AY30: =HAVERQ!D73*AO30/$AQ30 -> 33.015132 | AZ30: =HAVERQ!E73*AP30/$AQ30 -> 34.098124 | BA30: =1000*AQ30/$AQ30 -> 1000 | BC30: =$AV30/100*(AN30-100)*HAVERQ!C73/1000+(AS30-100)*AX30/$BA30 -> -0.174263 | BD30: =$AV30/100*(AO30-100)*HAVERQ!D73/1000+(AT30-100)*AY30/$BA30 -> -0.058809154 | BE30: =$AV30/100*(AP30-100)*HAVERQ!E73/1000+(AU30-100)*AZ30/$BA30 -> -0.098431945 | BF30: =BG30-BE30-BD30-BC30 -> 1.0303391 | BG30: =$AV30/100*(AQ30-100)*1000/1000+(AV30-100)*BA30/$BA30 -> 0.69883504 | BH30: =100*((DataQ!V181/DataQ!V177)-1) -> 0.69883504 | BI30: 2 | BK30: 42430 | BL30: =HAVERM!B321 -> 1.9 | BM30: =HAVERM!C321 -> 2.7 | BQ30: =BL30-BT30 -> 1.4501435 | BR30: =BM30-BU30 -> 2.0500696 | BT30: =HAVERM!D321 -> 0.44985652 | BU30: =HAVERM!E321 -> 0.64993043 | BW30: =BL30-BL6 -> -0.47 | BY30: 0 | CA30: 45323 | CB30: =HAVERM!G416-HAVERM!G$389 -> 4.15 | CC30: =HAVERM!H416-HAVERM!H$389 -> 1.47 | CD30: 0
AG31: 42644 | AH31: =100*((DataQ!U182/DataQ!U178)-1) -> 2.4742268 | AI31: =100*((DataQ!V182/DataQ!V178)-1) -> 1.1964108 | AJ31: =AH31-AI31 -> 1.277816 | AK31: 0 | AM31: 42644 | AN31: =DataQ!W182/DataQ!W178*100 -> 99.295065 | AO31: =DataQ!X182/DataQ!X178*100 -> 107.37131 | AP31: =DataQ!Y182/DataQ!Y178*100 -> 98.615339 | AQ31: =DataQ!V182/DataQ!V178*100 -> 101.19641 | AS31: =DataQ!W178/DataQ!W178*100 -> 100 | AT31: =DataQ!X178/DataQ!X178*100 -> 100 | AU31: =DataQ!Y178/DataQ!Y178*100 -> 100 | AV31: =DataQ!V178/DataQ!V178*100 -> 100 | AX31: =HAVERQ!C74*AN31/$AQ31 -> 142.27564 | AY31: =HAVERQ!D74*AO31/$AQ31 -> 33.952607 | AZ31: =HAVERQ!E74*AP31/$AQ31 -> 34.107305 | BA31: =1000*AQ31/$AQ31 -> 1000 | BC31: =$AV31/100*(AN31-100)*HAVERQ!C74/1000+(AS31-100)*AX31/$BA31 -> -0.10221551 | BD31: =$AV31/100*(AO31-100)*HAVERQ!D74/1000+(AT31-100)*AY31/$BA31 -> 0.23588194 | BE31: =$AV31/100*(AP31-100)*HAVERQ!E74/1000+(AU31-100)*AZ31/$BA31 -> -0.048463121 | BF31: =BG31-BE31-BD31-BC31 -> 1.1112075 | BG31: =$AV31/100*(AQ31-100)*1000/1000+(AV31-100)*BA31/$BA31 -> 1.1964108 | BH31: =100*((DataQ!V182/DataQ!V178)-1) -> 1.1964108 | BI31: 2 | BK31: 42461 | BL31: =HAVERM!B322 -> 1.84 | BM31: =HAVERM!C322 -> 2.71 | BQ31: =BL31-BT31 -> 1.3879619 | BR31: =BM31-BU31 -> 2.0608476 | BT31: =HAVERM!D322 -> 0.4520381 | BU31: =HAVERM!E322 -> 0.64915238 | BW31: =BL31-BL7 -> -0.7 | BY31: 0 | CA31: 45352 | CB31: =HAVERM!G417-HAVERM!G$389 -> 4.18 | CC31: =HAVERM!H417-HAVERM!H$389 -> 1.49 | CD31: 0
AG32: 42736 | AH32: =100*((DataQ!U183/DataQ!U179)-1) -> 2.1843073 | AI32: =100*((DataQ!V183/DataQ!V179)-1) -> 2.170277 | AJ32: =AH32-AI32 -> 0.014030333 | AK32: 0 | AM32: 42736 | AN32: =DataQ!W183/DataQ!W182*100 -> 101.72414 | AO32: =DataQ!X183/DataQ!X182*100 -> 104.17746 | AP32: =DataQ!Y183/DataQ!Y182*100 -> 100.27397 | AQ32: =DataQ!V183/DataQ!V182*100 -> 100.49261 | AS32: =DataQ!W182/DataQ!W179*100 -> 99.462007 | AT32: =DataQ!X182/DataQ!X179*100 -> 113.03071 | AU32: =DataQ!Y182/DataQ!Y179*100 -> 99.624708 | AV32: =DataQ!V182/DataQ!V179*100 -> 101.66944 | AX32: =HAVERQ!C75*AN32/$AQ32 -> 146.77696 | AY32: =HAVERQ!D75*AO32/$AQ32 -> 33.864484 | AZ32: =HAVERQ!E75*AP32/$AQ32 -> 33.593417 | BA32: =1000*AQ32/$AQ32 -> 1000 | BC32: =$AV32/100*(AN32-100)*HAVERQ!C75/1000+(AS32-100)*AX32/$BA32 -> 0.17520868 | BD32: =$AV32/100*(AO32-100)*HAVERQ!D75/1000+(AT32-100)*AY32/$BA32 -> 0.5800201 | BE32: =$AV32/100*(AP32-100)*HAVERQ!E75/1000+(AU32-100)*AZ32/$BA32 -> -0.0032298366 | BF32: =BG32-BE32-BD32-BC32 -> 1.418278 | BG32: =$AV32/100*(AQ32-100)*1000/1000+(AV32-100)*BA32/$BA32 -> 2.170277 | BH32: =100*((DataQ!V183/DataQ!V179)-1) -> 2.170277 | BI32: 2 | BK32: 42491 | BL32: =HAVERM!B323 -> 1.91 | BM32: =HAVERM!C323 -> 2.64 | BQ32: =BL32-BT32 -> 1.4411136 | BR32: =BM32-BU32 -> 1.9507182 | BT32: =HAVERM!D323 -> 0.46888636 | BU32: =HAVERM!E323 -> 0.68928182 | BW32: =BL32-BL8 -> -0.65 | BY32: 0 | CA32: 45383 | CB32: =HAVERM!G418-HAVERM!G$389 -> 4.17 | CC32: =HAVERM!H418-HAVERM!H$389 -> 1.56 | CD32: 0
AG33: 42826 | AH33: =100*((DataQ!U184/DataQ!U180)-1) -> 2.1606886 | AI33: =100*((DataQ!V184/DataQ!V180)-1) -> 2.7556773 | AJ33: =AH33-AI33 -> -0.59498871 | AK33: 0 | AM33: 42826 | AN33: =DataQ!W184/DataQ!W182*100 -> 102.83976 | AO33: =DataQ!X184/DataQ!X182*100 -> 101.4249 | AP33: =DataQ!Y184/DataQ!Y182*100 -> 102.87667 | AQ33: =DataQ!V184/DataQ!V182*100 -> 101.64207 | AS33: =DataQ!W182/DataQ!W180*100 -> 99.966208 | AT33: =DataQ!X182/DataQ!X180*100 -> 106.1168 | AU33: =DataQ!Y182/DataQ!Y180*100 -> 100.89841 | AV33: =DataQ!V182/DataQ!V180*100 -> 101.09562 | AX33: =HAVERQ!C76*AN33/$AQ33 -> 147.72037 | AY33: =HAVERQ!D76*AO33/$AQ33 -> 32.929493 | AZ33: =HAVERQ!E76*AP33/$AQ33 -> 34.412983 | BA33: =1000*AQ33/$AQ33 -> 1000 | BC33: =$AV33/100*(AN33-100)*HAVERQ!C76/1000+(AS33-100)*AX33/$BA33 -> 0.4141552 | BD33: =$AV33/100*(AO33-100)*HAVERQ!D76/1000+(AT33-100)*AY33/$BA33 -> 0.24896025 | BE33: =$AV33/100*(AP33-100)*HAVERQ!E76/1000+(AU33-100)*AZ33/$BA33 -> 0.12979551 | BF33: =BG33-BE33-BD33-BC33 -> 1.9627663 | BG33: =$AV33/100*(AQ33-100)*1000/1000+(AV33-100)*BA33/$BA33 -> 2.7556773 | BH33: =100*((DataQ!V184/DataQ!V180)-1) -> 2.7556773 | BI33: 2 | BK33: 42522 | BL33: =HAVERM!B324 -> 1.75 | BM33: =HAVERM!C324 -> 2.54 | BQ33: =BL33-BT33 -> 1.3929045 | BR33: =BM33-BU33 -> 2.0278727 | BT33: =HAVERM!D324 -> 0.35709545 | BU33: =HAVERM!E324 -> 0.51212727 | BW33: =BL33-BL9 -> -0.85 | BY33: 0 | CA33: 45413 | CB33: =HAVERM!G419-HAVERM!G$389 -> 4.18 | CC33: =HAVERM!H419-HAVERM!H$389 -> 1.6 | CD33: 0
AG34: 42917 | AH34: =100*((DataQ!U185/DataQ!U181)-1) -> 2.3569091 | AI34: =100*((DataQ!V185/DataQ!V181)-1) -> 2.8089548 | AJ34: =AH34-AI34 -> -0.4520457 | AK34: 0 | AM34: 42917 | AN34: =DataQ!W185/DataQ!W182*100 -> 103.11024 | AO34: =DataQ!X185/DataQ!X182*100 -> 100.9068 | AP34: =DataQ!Y185/DataQ!Y182*100 -> 104.48629 | AQ34: =DataQ!V185/DataQ!V182*100 -> 102.16749 | AS34: =DataQ!W182/DataQ!W181*100 -> 100.06766 | AT34: =DataQ!X182/DataQ!X181*100 -> 103.48522 | AU34: =DataQ!Y182/DataQ!Y181*100 -> 100.65495 | AV34: =DataQ!V182/DataQ!V181*100 -> 100.62786 | AX34: =HAVERQ!C77*AN34/$AQ34 -> 147.34722 | AY34: =HAVERQ!D77*AO34/$AQ34 -> 32.592799 | AZ34: =HAVERQ!E77*AP34/$AQ34 -> 34.771668 | BA34: =1000*AQ34/$AQ34 -> 1000 | BC34: =$AV34/100*(AN34-100)*HAVERQ!C77/1000+(AS34-100)*AX34/$BA34 -> 0.46691648 | BD34: =$AV34/100*(AO34-100)*HAVERQ!D77/1000+(AT34-100)*AY34/$BA34 -> 0.14370531 | BE34: =$AV34/100*(AP34-100)*HAVERQ!E77/1000+(AU34-100)*AZ34/$BA34 -> 0.17626553 | BF34: =BG34-BE34-BD34-BC34 -> 2.0220675 | BG34: =$AV34/100*(AQ34-100)*1000/1000+(AV34-100)*BA34/$BA34 -> 2.8089548 | BH34: =100*((DataQ!V185/DataQ!V181)-1) -> 2.8089548 | BI34: 2 | BK34: 42552 | BL34: =HAVERM!B325 -> 1.72 | BM34: =HAVERM!C325 -> 2.51 | BQ34: =BL34-BT34 -> 1.5872619 | BR34: =BM34-BU34 -> 2.2893238 | BT34: =HAVERM!D325 -> 0.1327381 | BU34: =HAVERM!E325 -> 0.22067619 | BW34: =BL34-BL10 -> -0.82 | BY34: 0 | CA34: 45444 | CB34: =HAVERM!G420-HAVERM!G$389 -> 4.22 | CC34: =HAVERM!H420-HAVERM!H$389 -> 1.64 | CD34: 0
AG35: 43009 | AH35: =100*((DataQ!U186/DataQ!U182)-1) -> 2.6827565 | AI35: =100*((DataQ!V186/DataQ!V182)-1) -> 3.0213793 | AJ35: =AH35-AI35 -> -0.33862277 | AK35: 0 | AM35: 43009 | AN35: =DataQ!W186/DataQ!W182*100 -> 104.22586 | AO35: =DataQ!X186/DataQ!X182*100 -> 103.85366 | AP35: =DataQ!Y186/DataQ!Y182*100 -> 106.19866 | AQ35: =DataQ!V186/DataQ!V182*100 -> 103.02138 | AS35: =DataQ!W182/DataQ!W182*100 -> 100 | AT35: =DataQ!X182/DataQ!X182*100 -> 100 | AU35: =DataQ!Y182/DataQ!Y182*100 -> 100 | AV35: =DataQ!V182/DataQ!V182*100 -> 100 | AX35: =HAVERQ!C78*AN35/$AQ35 -> 147.70697 | AY35: =HAVERQ!D78*AO35/$AQ35 -> 33.266598 | AZ35: =HAVERQ!E78*AP35/$AQ35 -> 35.048592 | BA35: =1000*AQ35/$AQ35 -> 1000 | BC35: =$AV35/100*(AN35-100)*HAVERQ!C78/1000+(AS35-100)*AX35/$BA35 -> 0.61697586 | BD35: =$AV35/100*(AO35-100)*HAVERQ!D78/1000+(AT35-100)*AY35/$BA35 -> 0.1271708 | BE35: =$AV35/100*(AP35-100)*HAVERQ!E78/1000+(AU35-100)*AZ35/$BA35 -> 0.21075434 | BF35: =BG35-BE35-BD35-BC35 -> 2.0664783 | BG35: =$AV35/100*(AQ35-100)*1000/1000+(AV35-100)*BA35/$BA35 -> 3.0213793 | BH35: =100*((DataQ!V186/DataQ!V182)-1) -> 3.0213793 | BI35: 2 | BK35: 42583 | BL35: =HAVERM!B326 -> 1.69 | BM35: =HAVERM!C326 -> 2.39 | BQ35: =BL35-BT35 -> 1.5824 | BR35: =BM35-BU35 -> 2.2147217 | BT35: =HAVERM!D326 -> 0.1076 | BU35: =HAVERM!E326 -> 0.17527826 | BW35: =BL35-BL11 -> -0.85 | BY35: 0 | CA35: 45474 | CB35: =HAVERM!G421-HAVERM!G$389 -> 4.18 | CC35: =HAVERM!H421-HAVERM!H$389 -> 1.68 | CD35: 0
AG36: 43101 | AH36: =100*((DataQ!U187/DataQ!U183)-1) -> 2.6052104 | AI36: =100*((DataQ!V187/DataQ!V183)-1) -> 2.712451 | AJ36: =AH36-AI36 -> -0.10724056 | AK36: 0 | AM36: 43101 | AN36: =DataQ!W187/DataQ!W186*100 -> 101.2325 | AO36: =DataQ!X187/DataQ!X186*100 -> 101.37203 | AP36: =DataQ!Y187/DataQ!Y186*100 -> 100.35466 | AQ36: =DataQ!V187/DataQ!V186*100 -> 100.19127 | AS36: =DataQ!W186/DataQ!W183*100 -> 102.45932 | AT36: =DataQ!X186/DataQ!X183*100 -> 99.689182 | AU36: =DataQ!Y186/DataQ!Y183*100 -> 105.9085 | AV36: =DataQ!V186/DataQ!V183*100 -> 102.51637 | AX36: =HAVERQ!C79*AN36/$AQ36 -> 144.14933 | AY36: =HAVERQ!D79*AO36/$AQ36 -> 31.028077 | AZ36: =HAVERQ!E79*AP36/$AQ36 -> 34.055448 | BA36: =1000*AQ36/$AQ36 -> 1000 | BC36: =$AV36/100*(AN36-100)*HAVERQ!C79/1000+(AS36-100)*AX36/$BA36 -> 0.53477105 | BD36: =$AV36/100*(AO36-100)*HAVERQ!D79/1000+(AT36-100)*AY36/$BA36 -> 0.03349029 | BE36: =$AV36/100*(AP36-100)*HAVERQ!E79/1000+(AU36-100)*AZ36/$BA36 -> 0.21357862 | BF36: =BG36-BE36-BD36-BC36 -> 1.930611 | BG36: =$AV36/100*(AQ36-100)*1000/1000+(AV36-100)*BA36/$BA36 -> 2.712451 | BH36: =100*((DataQ!V187/DataQ!V183)-1) -> 2.712451 | BI36: 2 | BK36: 42614 | BL36: =HAVERM!B327 -> 1.59 | BM36: =HAVERM!C327 -> 2.34 | BQ36: =BL36-BT36 -> 1.4666318 | BR36: =BM36-BU36 -> 2.1336091 | BT36: =HAVERM!D327 -> 0.12336818 | BU36: =HAVERM!E327 -> 0.20639091 | BW36: =BL36-BL12 -> -0.87 | BY36: 0
AG37: 43191 | AH37: =100*((DataQ!U188/DataQ!U184)-1) -> 2.445486 | AI37: =100*((DataQ!V188/DataQ!V184)-1) -> 2.4232625 | AJ37: =AH37-AI37 -> 0.022223406 | AK37: 0 | AM37: 43191 | AN37: =DataQ!W188/DataQ!W186*100 -> 101.42712 | AO37: =DataQ!X188/DataQ!X186*100 -> 105.0203 | AP37: =DataQ!Y188/DataQ!Y186*100 -> 101.90255 | AQ37: =DataQ!V188/DataQ!V186*100 -> 101.05196 | AS37: =DataQ!W186/DataQ!W184*100 -> 101.34783 | AT37: =DataQ!X186/DataQ!X184*100 -> 102.39464 | AU37: =DataQ!Y186/DataQ!Y184*100 -> 103.2291 | AV37: =DataQ!V186/DataQ!V184*100 -> 101.35703 | AX37: =HAVERQ!C80*AN37/$AQ37 -> 143.53089 | AY37: =HAVERQ!D80*AO37/$AQ37 -> 32.217379 | AZ37: =HAVERQ!E80*AP37/$AQ37 -> 34.286189 | BA37: =1000*AQ37/$AQ37 -> 1000 | BC37: =$AV37/100*(AN37-100)*HAVERQ!C80/1000+(AS37-100)*AX37/$BA37 -> 0.40030226 | BD37: =$AV37/100*(AO37-100)*HAVERQ!D80/1000+(AT37-100)*AY37/$BA37 -> 0.23489011 | BE37: =$AV37/100*(AP37-100)*HAVERQ!E80/1000+(AU37-100)*AZ37/$BA37 -> 0.17627779 | BF37: =BG37-BE37-BD37-BC37 -> 1.6117924 | BG37: =$AV37/100*(AQ37-100)*1000/1000+(AV37-100)*BA37/$BA37 -> 2.4232625 | BH37: =100*((DataQ!V188/DataQ!V184)-1) -> 2.4232625 | BI37: 2 | BK37: 42644 | BL37: =HAVERM!B328 -> 1.52 | BM37: =HAVERM!C328 -> 2.27 | BQ37: =BL37-BT37 -> 1.3240381 | BR37: =BM37-BU37 -> 1.9146571 | BT37: =HAVERM!D328 -> 0.1959619 | BU37: =HAVERM!E328 -> 0.35534286 | BW37: =BL37-BL13 -> -0.69 | BY37: 0
AG38: 43282 | AH38: =100*((DataQ!U189/DataQ!U185)-1) -> 3.0920919 | AI38: =100*((DataQ!V189/DataQ!V185)-1) -> 2.5072324 | AJ38: =AH38-AI38 -> 0.5848595 | AK38: 0 | AM38: 43282 | AN38: =DataQ!W189/DataQ!W186*100 -> 101.52442 | AO38: =DataQ!X189/DataQ!X186*100 -> 108.45023 | AP38: =DataQ!Y189/DataQ!Y186*100 -> 105.32086 | AQ38: =DataQ!V189/DataQ!V186*100 -> 101.6576 | AS38: =DataQ!W186/DataQ!W185*100 -> 101.08197 | AT38: =DataQ!X186/DataQ!X185*100 -> 102.92038 | AU38: =DataQ!Y186/DataQ!Y185*100 -> 101.63884 | AV38: =DataQ!V186/DataQ!V185*100 -> 100.83578 | AX38: =HAVERQ!C81*AN38/$AQ38 -> 142.81266 | AY38: =HAVERQ!D81*AO38/$AQ38 -> 33.071381 | AZ38: =HAVERQ!E81*AP38/$AQ38 -> 35.2252 | BA38: =1000*AQ38/$AQ38 -> 1000 | BC38: =$AV38/100*(AN38-100)*HAVERQ!C81/1000+(AS38-100)*AX38/$BA38 -> 0.37433309 | BD38: =$AV38/100*(AO38-100)*HAVERQ!D81/1000+(AT38-100)*AY38/$BA38 -> 0.36072755 | BE38: =$AV38/100*(AP38-100)*HAVERQ!E81/1000+(AU38-100)*AZ38/$BA38 -> 0.24014978 | BF38: =BG38-BE38-BD38-BC38 -> 1.532022 | BG38: =$AV38/100*(AQ38-100)*1000/1000+(AV38-100)*BA38/$BA38 -> 2.5072324 | BH38: =100*((DataQ!V189/DataQ!V185)-1) -> 2.5072324 | BI38: 2 | BK38: 42675 | BL38: =HAVERM!B329 -> 1.43 | BM38: =HAVERM!C329 -> 2.25 | BQ38: =BL38-BT38 -> 1.1526455 | BR38: =BM38-BU38 -> 1.6863136 | BT38: =HAVERM!D329 -> 0.27735455 | BU38: =HAVERM!E329 -> 0.56368636 | BW38: =BL38-BL14 -> -0.74 | BY38: 0
AG39: 43374 | AH39: =100*((DataQ!U190/DataQ!U186)-1) -> 3.4617964 | AI39: =100*((DataQ!V190/DataQ!V186)-1) -> 2.2632444 | AJ39: =AH39-AI39 -> 1.198552 | AK39: 0 | AM39: 43374 | AN39: =DataQ!W190/DataQ!W186*100 -> 101.81635 | AO39: =DataQ!X190/DataQ!X186*100 -> 108.01375 | AP39: =DataQ!Y190/DataQ!Y186*100 -> 108.5456 | AQ39: =DataQ!V190/DataQ!V186*100 -> 102.26324 | AS39: =DataQ!W186/DataQ!W186*100 -> 100 | AT39: =DataQ!X186/DataQ!X186*100 -> 100 | AU39: =DataQ!Y186/DataQ!Y186*100 -> 100 | AV39: =DataQ!V186/DataQ!V186*100 -> 100 | AX39: =HAVERQ!C82*AN39/$AQ39 -> 142.37508 | AY39: =HAVERQ!D82*AO39/$AQ39 -> 32.743204 | AZ39: =HAVERQ!E82*AP39/$AQ39 -> 36.088726 | BA39: =1000*AQ39/$AQ39 -> 1000 | BC39: =$AV39/100*(AN39-100)*HAVERQ!C82/1000+(AS39-100)*AX39/$BA39 -> 0.25973764 | BD39: =$AV39/100*(AO39-100)*HAVERQ!D82/1000+(AT39-100)*AY39/$BA39 -> 0.24842629 | BE39: =$AV39/100*(AP39-100)*HAVERQ!E82/1000+(AU39-100)*AZ39/$BA39 -> 0.29055024 | BF39: =BG39-BE39-BD39-BC39 -> 1.4645302 | BG39: =$AV39/100*(AQ39-100)*1000/1000+(AV39-100)*BA39/$BA39 -> 2.2632444 | BH39: =100*((DataQ!V190/DataQ!V186)-1) -> 2.2632444 | BI39: 2 | BK39: 42705 | BL39: =HAVERM!B330 -> 1.45 | BM39: =HAVERM!C330 -> 2.26 | BQ39: =BL39-BT39 -> 1.1509364 | BR39: =BM39-BU39 -> 1.6513864 | BT39: =HAVERM!D330 -> 0.29906364 | BU39: =HAVERM!E330 -> 0.60861364 | BW39: =BL39-BL15 -> -0.63 | BY39: 0
AG40: 43466 | AH40: =100*((DataQ!U191/DataQ!U187)-1) -> 3.2552148 | AI40: =100*((DataQ!V191/DataQ!V187)-1) -> 1.8453383 | AJ40: =AH40-AI40 -> 1.4098766 | AK40: 0 | AM40: 43466 | AN40: =DataQ!W191/DataQ!W190*100 -> 101.4655 | AO40: =DataQ!X191/DataQ!X190*100 -> 95.150117 | AP40: =DataQ!Y191/DataQ!Y190*100 -> 93.879947 | AQ40: =DataQ!V191/DataQ!V190*100 -> 99.781827 | AS40: =DataQ!W190/DataQ!W187*100 -> 100.57674 | AT40: =DataQ!X190/DataQ!X187*100 -> 106.55183 | AU40: =DataQ!Y190/DataQ!Y187*100 -> 108.16199 | AV40: =DataQ!V190/DataQ!V187*100 -> 102.06802 | AX40: =HAVERQ!C83*AN40/$AQ40 -> 142.3623 | AY40: =HAVERQ!D83*AO40/$AQ40 -> 28.607449 | AZ40: =HAVERQ!E83*AP40/$AQ40 -> 29.793652 | BA40: =1000*AQ40/$AQ40 -> 1000 | BC40: =$AV40/100*(AN40-100)*HAVERQ!C83/1000+(AS40-100)*AX40/$BA40 -> 0.29151863 | BD40: =$AV40/100*(AO40-100)*HAVERQ!D83/1000+(AT40-100)*AY40/$BA40 -> 0.038925695 | BE40: =$AV40/100*(AP40-100)*HAVERQ!E83/1000+(AU40-100)*AZ40/$BA40 -> 0.045365883 | BF40: =BG40-BE40-BD40-BC40 -> 1.4695281 | BG40: =$AV40/100*(AQ40-100)*1000/1000+(AV40-100)*BA40/$BA40 -> 1.8453383 | BH40: =100*((DataQ!V191/DataQ!V187)-1) -> 1.8453383 | BI40: 2 | BK40: 42736 | BL40: =HAVERM!B331 -> 1.45 | BM40: =HAVERM!C331 -> 2.22 | BQ40: =BL40-BT40 -> 1.1252182 | BR40: =BM40-BU40 -> 1.61045 | BT40: =HAVERM!D331 -> 0.32478182 | BU40: =HAVERM!E331 -> 0.60955 | BW40: =BL40-BL16 -> -0.56 | BY40: 0
AG41: 43556 | AH41: =100*((DataQ!U192/DataQ!U188)-1) -> 3.9354772 | AI41: =100*((DataQ!V192/DataQ!V188)-1) -> 2.0188953 | AJ41: =AH41-AI41 -> 1.9165819 | AK41: 0 | AM41: 43556 | AN41: =DataQ!W192/DataQ!W190*100 -> 101.43358 | AO41: =DataQ!X192/DataQ!X190*100 -> 99.913395 | AP41: =DataQ!Y192/DataQ!Y190*100 -> 102.88173 | AQ41: =DataQ!V192/DataQ!V190*100 -> 100.81051 | AS41: =DataQ!W190/DataQ!W188*100 -> 100.38375 | AT41: =DataQ!X190/DataQ!X188*100 -> 102.85036 | AU41: =DataQ!Y190/DataQ!Y188*100 -> 106.51902 | AV41: =DataQ!V190/DataQ!V188*100 -> 101.19867 | AX41: =HAVERQ!C84*AN41/$AQ41 -> 140.86529 | AY41: =HAVERQ!D84*AO41/$AQ41 -> 29.733031 | AZ41: =HAVERQ!E84*AP41/$AQ41 -> 31.636917 | BA41: =1000*AQ41/$AQ41 -> 1000 | BC41: =$AV41/100*(AN41-100)*HAVERQ!C84/1000+(AS41-100)*AX41/$BA41 -> 0.25716437 | BD41: =$AV41/100*(AO41-100)*HAVERQ!D84/1000+(AT41-100)*AY41/$BA41 -> 0.082120411 | BE41: =$AV41/100*(AP41-100)*HAVERQ!E84/1000+(AU41-100)*AZ41/$BA41 -> 0.29664615 | BF41: =BG41-BE41-BD41-BC41 -> 1.3829643 | BG41: =$AV41/100*(AQ41-100)*1000/1000+(AV41-100)*BA41/$BA41 -> 2.0188953 | BH41: =100*((DataQ!V192/DataQ!V188)-1) -> 2.0188953 | BI41: 2 | BK41: 42767 | BL41: =HAVERM!B332 -> 1.42 | BM41: =HAVERM!C332 -> 2.2 | BQ41: =BL41-BT41 -> 1.12247 | BR41: =BM41-BU41 -> 1.648535 | BT41: =HAVERM!D332 -> 0.29753 | BU41: =HAVERM!E332 -> 0.551465 | BW41: =BL41-BL17 -> -0.54 | BY41: 0
AG42: 43647 | AH42: =100*((DataQ!U193/DataQ!U189)-1) -> 3.8289728 | AI42: =100*((DataQ!V193/DataQ!V189)-1) -> 1.8501411 | AJ42: =AH42-AI42 -> 1.9788317 | AK42: 0 | AM42: 43647 | AN42: =DataQ!W193/DataQ!W190*100 -> 101.84779 | AO42: =DataQ!X193/DataQ!X190*100 -> 99.682419 | AP42: =DataQ!Y193/DataQ!Y190*100 -> 102.82237 | AQ42: =DataQ!V193/DataQ!V190*100 -> 101.24695 | AS42: =DataQ!W190/DataQ!W189*100 -> 100.28754 | AT42: =DataQ!X190/DataQ!X189*100 -> 99.597527 | AU42: =DataQ!Y190/DataQ!Y189*100 -> 103.06182 | AV42: =DataQ!V190/DataQ!V189*100 -> 100.59577 | AX42: =HAVERQ!C85*AN42/$AQ42 -> 140.83082 | AY42: =HAVERQ!D85*AO42/$AQ42 -> 29.536423 | AZ42: =HAVERQ!E85*AP42/$AQ42 -> 31.482367 | BA42: =1000*AQ42/$AQ42 -> 1000 | BC42: =$AV42/100*(AN42-100)*HAVERQ!C85/1000+(AS42-100)*AX42/$BA42 -> 0.3007258 | BD42: =$AV42/100*(AO42-100)*HAVERQ!D85/1000+(AT42-100)*AY42/$BA42 -> -0.02147179 | BE42: =$AV42/100*(AP42-100)*HAVERQ!E85/1000+(AU42-100)*AZ42/$BA42 -> 0.18440802 | BF42: =BG42-BE42-BD42-BC42 -> 1.3864791 | BG42: =$AV42/100*(AQ42-100)*1000/1000+(AV42-100)*BA42/$BA42 -> 1.8501411 | BH42: =100*((DataQ!V193/DataQ!V189)-1) -> 1.8501411 | BI42: 2 | BK42: 42795 | BL42: =HAVERM!B333 -> 1.37 | BM42: =HAVERM!C333 -> 2.15 | BQ42: =BL42-BT42 -> 1.0473304 | BR42: =BM42-BU42 -> 1.591987 | BT42: =HAVERM!D333 -> 0.32266957 | BU42: =HAVERM!E333 -> 0.55801304 | BW42: =BL42-BL18 -> -0.62 | BY42: 0
AG43: 43739 | AH43: =100*((DataQ!U194/DataQ!U190)-1) -> 2.7146402 | AI43: =100*((DataQ!V194/DataQ!V190)-1) -> 1.4027436 | AJ43: =AH43-AI43 -> 1.3118966 | AK43: 0 | AM43: 43739 | AN43: =DataQ!W194/DataQ!W190*100 -> 101.87961 | AO43: =DataQ!X194/DataQ!X190*100 -> 98.210133 | AP43: =DataQ!Y194/DataQ!Y190*100 -> 98.306595 | AQ43: =DataQ!V194/DataQ!V190*100 -> 101.40274 | AS43: =DataQ!W190/DataQ!W190*100 -> 100 | AT43: =DataQ!X190/DataQ!X190*100 -> 100 | AU43: =DataQ!Y190/DataQ!Y190*100 -> 100 | AV43: =DataQ!V190/DataQ!V190*100 -> 100 | AX43: =HAVERQ!C86*AN43/$AQ43 -> 140.65838 | AY43: =HAVERQ!D86*AO43/$AQ43 -> 29.055466 | AZ43: =HAVERQ!E86*AP43/$AQ43 -> 30.053471 | BA43: =1000*AQ43/$AQ43 -> 1000 | BC43: =$AV43/100*(AN43-100)*HAVERQ!C86/1000+(AS43-100)*AX43/$BA43 -> 0.26314567 | BD43: =$AV43/100*(AO43-100)*HAVERQ!D86/1000+(AT43-100)*AY43/$BA43 -> -0.053696001 | BE43: =$AV43/100*(AP43-100)*HAVERQ!E86/1000+(AU43-100)*AZ43/$BA43 -> -0.052495544 | BF43: =BG43-BE43-BD43-BC43 -> 1.2457895 | BG43: =$AV43/100*(AQ43-100)*1000/1000+(AV43-100)*BA43/$BA43 -> 1.4027436 | BH43: =100*((DataQ!V194/DataQ!V190)-1) -> 1.4027436 | BI43: 2 | BK43: 42826 | BL43: =HAVERM!B334 -> 1.35 | BM43: =HAVERM!C334 -> 2.09 | BQ43: =BL43-BT43 -> 1.07341 | BR43: =BM43-BU43 -> 1.624545 | BT43: =HAVERM!D334 -> 0.27659 | BU43: =HAVERM!E334 -> 0.465455 | BW43: =BL43-BL19 -> -0.6 | BY43: 0
AG44: 43831 | AH44: =100*((DataQ!U195/DataQ!U191)-1) -> 2.2067968 | AI44: =100*((DataQ!V195/DataQ!V191)-1) -> 1.6557638 | AJ44: =AH44-AI44 -> 0.55103301 | AK44: 0 | AM44: 43831 | AN44: =DataQ!W195/DataQ!W194*100 -> 100.90685 | AO44: =DataQ!X195/DataQ!X194*100 -> 98.530247 | AP44: =DataQ!Y195/DataQ!Y194*100 -> 99.697824 | AQ44: =DataQ!V195/DataQ!V194*100 -> 100.0308 | AS44: =DataQ!W194/DataQ!W191*100 -> 100.40813 | AT44: =DataQ!X194/DataQ!X191*100 -> 103.21599 | AU44: =DataQ!Y194/DataQ!Y191*100 -> 104.71522 | AV44: =DataQ!V194/DataQ!V191*100 -> 101.62446 | AX44: =HAVERQ!C87*AN44/$AQ44 -> 139.88108 | AY44: =HAVERQ!D87*AO44/$AQ44 -> 30.534971 | AZ44: =HAVERQ!E87*AP44/$AQ44 -> 32.557927 | BA44: =1000*AQ44/$AQ44 -> 1000 | BC44: =$AV44/100*(AN44-100)*HAVERQ!C87/1000+(AS44-100)*AX44/$BA44 -> 0.18488225 | BD44: =$AV44/100*(AO44-100)*HAVERQ!D87/1000+(AT44-100)*AY44/$BA44 -> 0.051897615 | BE44: =$AV44/100*(AP44-100)*HAVERQ!E87/1000+(AU44-100)*AZ44/$BA44 -> 0.14348646 | BF44: =BG44-BE44-BD44-BC44 -> 1.2754975 | BG44: =$AV44/100*(AQ44-100)*1000/1000+(AV44-100)*BA44/$BA44 -> 1.6557638 | BH44: =100*((DataQ!V195/DataQ!V191)-1) -> 1.6557638 | BI44: 2 | BK44: 42856 | BL44: =HAVERM!B335 -> 1.49 | BM44: =HAVERM!C335 -> 2.03 | BQ44: =BL44-BT44 -> 1.1840478 | BR44: =BM44-BU44 -> 1.5019739 | BT44: =HAVERM!D335 -> 0.30595217 | BU44: =HAVERM!E335 -> 0.52802609 | BW44: =BL44-BL20 -> -0.41 | BY44: 0
AG45: 43922 | AH45: =100*((DataQ!U196/DataQ!U192)-1) -> -1.1173184 | AI45: =100*((DataQ!V196/DataQ!V192)-1) -> 0.68024119 | AJ45: =AH45-AI45 -> -1.7975596 | AK45: 0 | AM45: 43922 | AN45: =DataQ!W196/DataQ!W194*100 -> 101.28208 | AO45: =DataQ!X196/DataQ!X194*100 -> 86.33157 | AP45: =DataQ!Y196/DataQ!Y194*100 -> 97.491659 | AQ45: =DataQ!V196/DataQ!V194*100 -> 100.09222 | AS45: =DataQ!W194/DataQ!W192*100 -> 100.43973 | AT45: =DataQ!X194/DataQ!X192*100 -> 98.295262 | AU45: =DataQ!Y194/DataQ!Y192*100 -> 95.553016 | AV45: =DataQ!V194/DataQ!V192*100 -> 100.58748 | AX45: =HAVERQ!C88*AN45/$AQ45 -> 140.65238 | AY45: =HAVERQ!D88*AO45/$AQ45 -> 26.738128 | AZ45: =HAVERQ!E88*AP45/$AQ45 -> 32.142605 | BA45: =1000*AQ45/$AQ45 -> 1000 | BC45: =$AV45/100*(AN45-100)*HAVERQ!C88/1000+(AS45-100)*AX45/$BA45 -> 0.24110549 | BD45: =$AV45/100*(AO45-100)*HAVERQ!D88/1000+(AT45-100)*AY45/$BA45 -> -0.47179211 | BE45: =$AV45/100*(AP45-100)*HAVERQ!E88/1000+(AU45-100)*AZ45/$BA45 -> -0.22619917 | BF45: =BG45-BE45-BD45-BC45 -> 1.137127 | BG45: =$AV45/100*(AQ45-100)*1000/1000+(AV45-100)*BA45/$BA45 -> 0.68024119 | BH45: =100*((DataQ!V196/DataQ!V192)-1) -> 0.68024119 | BI45: 2 | BK45: 42887 | BL45: =HAVERM!B336 -> 1.48 | BM45: =HAVERM!C336 -> 1.99 | BQ45: =BL45-BT45 -> 1.1347682 | BR45: =BM45-BU45 -> 1.4356773 | BT45: =HAVERM!D336 -> 0.34523182 | BU45: =HAVERM!E336 -> 0.55432273 | BW45: =BL45-BL21 -> -0.35 | BY45: 0
AG46: 44013 | AH46: =100*((DataQ!U197/DataQ!U193)-1) -> 1.4751077 | AI46: =100*((DataQ!V197/DataQ!V193)-1) -> 0.61570178 | AJ46: =AH46-AI46 -> 0.85940587 | AK46: 0 | AM46: 44013 | AN46: =DataQ!W197/DataQ!W194*100 -> 100.81304 | AO46: =DataQ!X197/DataQ!X194*100 -> 90.005908 | AP46: =DataQ!Y197/DataQ!Y194*100 -> 97.582321 | AQ46: =DataQ!V197/DataQ!V194*100 -> 100.46111 | AS46: =DataQ!W194/DataQ!W193*100 -> 100.03125 | AT46: =DataQ!X194/DataQ!X193*100 -> 98.523023 | AU46: =DataQ!Y194/DataQ!Y193*100 -> 95.608178 | AV46: =DataQ!V194/DataQ!V193*100 -> 100.15388 | AX46: =HAVERQ!C89*AN46/$AQ46 -> 139.48693 | AY46: =HAVERQ!D89*AO46/$AQ46 -> 27.773763 | AZ46: =HAVERQ!E89*AP46/$AQ46 -> 32.054359 | BA46: =1000*AQ46/$AQ46 -> 1000 | BC46: =$AV46/100*(AN46-100)*HAVERQ!C89/1000+(AS46-100)*AX46/$BA46 -> 0.11754507 | BD46: =$AV46/100*(AO46-100)*HAVERQ!D89/1000+(AT46-100)*AY46/$BA46 -> -0.35131478 | BE46: =$AV46/100*(AP46-100)*HAVERQ!E89/1000+(AU46-100)*AZ46/$BA46 -> -0.22068322 | BF46: =BG46-BE46-BD46-BC46 -> 1.0701547 | BG46: =$AV46/100*(AQ46-100)*1000/1000+(AV46-100)*BA46/$BA46 -> 0.61570178 | BH46: =100*((DataQ!V197/DataQ!V193)-1) -> 0.61570178 | BI46: 2 | BK46: 42917 | BL46: =HAVERM!B337 -> 1.41 | BM46: =HAVERM!C337 -> 1.97 | BQ46: =BL46-BT46 -> 0.97240952 | BR46: =BM46-BU46 -> 1.2782571 | BT46: =HAVERM!D337 -> 0.43759048 | BU46: =HAVERM!E337 -> 0.69174286 | BW46: =BL46-BL22 -> -0.46 | BY46: 0
AG47: 44105 | AH47: =100*((DataQ!U198/DataQ!U194)-1) -> 4.5482547 | AI47: =100*((DataQ!V198/DataQ!V194)-1) -> 0.5841379 | AJ47: =AH47-AI47 -> 3.9641168 | AK47: 0 | AM47: 44105 | AN47: =DataQ!W198/DataQ!W194*100 -> 100.40647 | AO47: =DataQ!X198/DataQ!X194*100 -> 90.47619 | AP47: =DataQ!Y198/DataQ!Y194*100 -> 91.266274 | AQ47: =DataQ!V198/DataQ!V194*100 -> 100.58414 | AS47: =DataQ!W194/DataQ!W194*100 -> 100 | AT47: =DataQ!X194/DataQ!X194*100 -> 100 | AU47: =DataQ!Y194/DataQ!Y194*100 -> 100 | AV47: =DataQ!V194/DataQ!V194*100 -> 100 | AX47: =HAVERQ!C90*AN47/$AQ47 -> 138.75448 | AY47: =HAVERQ!D90*AO47/$AQ47 -> 27.884734 | AZ47: =HAVERQ!E90*AP47/$AQ47 -> 29.942962 | BA47: =1000*AQ47/$AQ47 -> 1000 | BC47: =$AV47/100*(AN47-100)*HAVERQ!C90/1000+(AS47-100)*AX47/$BA47 -> 0.056499719 | BD47: =$AV47/100*(AO47-100)*HAVERQ!D90/1000+(AT47-100)*AY47/$BA47 -> -0.2952381 | BE47: =$AV47/100*(AP47-100)*HAVERQ!E90/1000+(AU47-100)*AZ47/$BA47 -> -0.28821296 | BF47: =BG47-BE47-BD47-BC47 -> 1.1110892 | BG47: =$AV47/100*(AQ47-100)*1000/1000+(AV47-100)*BA47/$BA47 -> 0.5841379 | BH47: =100*((DataQ!V198/DataQ!V194)-1) -> 0.5841379 | BI47: 2 | BK47: 42948 | BL47: =HAVERM!B338 -> 1.43 | BM47: =HAVERM!C338 -> 1.96 | BQ47: =BL47-BT47 -> 1.0583739 | BR47: =BM47-BU47 -> 1.3781739 | BT47: =HAVERM!D338 -> 0.37162609 | BU47: =HAVERM!E338 -> 0.58182609 | BW47: =BL47-BL23 -> -0.52 | BY47: 0
AG48: 44197 | AH48: =100*((DataQ!U199/DataQ!U195)-1) -> 4.1949478 | AI48: =100*((DataQ!V199/DataQ!V195)-1) -> 0.64535936 | AJ48: =AH48-AI48 -> 3.5495885 | AK48: 0 | AM48: 44197 | AN48: =DataQ!W199/DataQ!W198*100 -> 100.62289 | AO48: =DataQ!X199/DataQ!X198*100 -> 105.78294 | AP48: =DataQ!Y199/DataQ!Y198*100 -> 100.66219 | AQ48: =DataQ!V199/DataQ!V198*100 -> 100.09169 | AS48: =DataQ!W198/DataQ!W195*100 -> 99.504122 | AT48: =DataQ!X198/DataQ!X195*100 -> 91.825803 | AU48: =DataQ!Y198/DataQ!Y195*100 -> 91.542894 | AV48: =DataQ!V198/DataQ!V195*100 -> 100.55317 | AX48: =HAVERQ!C91*AN48/$AQ48 -> 159.50874 | AY48: =HAVERQ!D91*AO48/$AQ48 -> 28.182945 | AZ48: =HAVERQ!E91*AP48/$AQ48 -> 33.188092 | BA48: =1000*AQ48/$AQ48 -> 1000 | BC48: =$AV48/100*(AN48-100)*HAVERQ!C91/1000+(AS48-100)*AX48/$BA48 -> 0.020281692 | BD48: =$AV48/100*(AO48-100)*HAVERQ!D91/1000+(AT48-100)*AY48/$BA48 -> -0.07530807 | BE48: =$AV48/100*(AP48-100)*HAVERQ!E91/1000+(AU48-100)*AZ48/$BA48 -> -0.25870221 | BF48: =BG48-BE48-BD48-BC48 -> 0.95908795 | BG48: =$AV48/100*(AQ48-100)*1000/1000+(AV48-100)*BA48/$BA48 -> 0.64535936 | BH48: =100*((DataQ!V199/DataQ!V195)-1) -> 0.64535936 | BI48: 2 | BK48: 42979 | BL48: =HAVERM!B339 -> 1.4 | BM48: =HAVERM!C339 -> 1.9 | BQ48: =BL48-BT48 -> 0.86071429 | BR48: =BM48-BU48 -> 1.1466619 | BT48: =HAVERM!D339 -> 0.53928571 | BU48: =HAVERM!E339 -> 0.7533381 | BW48: =BL48-BL24 -> -0.51 | BY48: 0
AG49: 44287 | AH49: =100*((DataQ!U200/DataQ!U196)-1) -> 8.8512241 | AI49: =100*((DataQ!V200/DataQ!V196)-1) -> 2.0270276 | AJ49: =AH49-AI49 -> 6.8241965 | AK49: 0 | AM49: 44287 | AN49: =DataQ!W200/DataQ!W198*100 -> 100.90318 | AO49: =DataQ!X200/DataQ!X198*100 -> 111.85838 | AP49: =DataQ!Y200/DataQ!Y198*100 -> 109.47016 | AQ49: =DataQ!V200/DataQ!V198*100 -> 101.52806 | AS49: =DataQ!W198/DataQ!W196*100 -> 99.135474 | AT49: =DataQ!X198/DataQ!X196*100 -> 104.80082 | AU49: =DataQ!Y198/DataQ!Y196*100 -> 93.614443 | AV49: =DataQ!V198/DataQ!V196*100 -> 100.49146 | AX49: =HAVERQ!C92*AN49/$AQ49 -> 158.0214 | AY49: =HAVERQ!D92*AO49/$AQ49 -> 29.747209 | AZ49: =HAVERQ!E92*AP49/$AQ49 -> 35.581449 | BA49: =1000*AQ49/$AQ49 -> 1000 | BC49: =$AV49/100*(AN49-100)*HAVERQ!C92/1000+(AS49-100)*AX49/$BA49 -> 0.0076973084 | BD49: =$AV49/100*(AO49-100)*HAVERQ!D92/1000+(AT49-100)*AY49/$BA49 -> 0.46456077 | BE49: =$AV49/100*(AP49-100)*HAVERQ!E92/1000+(AU49-100)*AZ49/$BA49 -> 0.086843888 | BF49: =BG49-BE49-BD49-BC49 -> 1.4679257 | BG49: =$AV49/100*(AQ49-100)*1000/1000+(AV49-100)*BA49/$BA49 -> 2.0270276 | BH49: =100*((DataQ!V200/DataQ!V196)-1) -> 2.0270276 | BI49: 2 | BK49: 43009 | BL49: =HAVERM!B340 -> 1.55 | BM49: =HAVERM!C340 -> 2.04 | BQ49: =BL49-BT49 -> 0.87478182 | BR49: =BM49-BU49 -> 1.1439545 | BT49: =HAVERM!D340 -> 0.67521818 | BU49: =HAVERM!E340 -> 0.89604545 | BW49: =BL49-BL25 -> -0.32 | BY49: 0
AG50: 44378 | AH50: =100*((DataQ!U201/DataQ!U197)-1) -> 6.0569477 | AI50: =100*((DataQ!V201/DataQ!V197)-1) -> 2.7539788 | AJ50: =AH50-AI50 -> 3.3029689 | AK50: 0 | AM50: 44378 | AN50: =DataQ!W201/DataQ!W198*100 -> 101.18346 | AO50: =DataQ!X201/DataQ!X198*100 -> 117.18645 | AP50: =DataQ!Y201/DataQ!Y198*100 -> 109.76818 | AQ50: =DataQ!V201/DataQ!V198*100 -> 102.6283 | AS50: =DataQ!W198/DataQ!W197*100 -> 99.596712 | AT50: =DataQ!X198/DataQ!X197*100 -> 100.5225 | AU50: =DataQ!Y198/DataQ!Y197*100 -> 93.527468 | AV50: =DataQ!V198/DataQ!V197*100 -> 100.12246 | AX50: =HAVERQ!C93*AN50/$AQ50 -> 156.76154 | AY50: =HAVERQ!D93*AO50/$AQ50 -> 30.830036 | AZ50: =HAVERQ!E93*AP50/$AQ50 -> 35.295818 | BA50: =1000*AQ50/$AQ50 -> 1000 | BC50: =$AV50/100*(AN50-100)*HAVERQ!C93/1000+(AS50-100)*AX50/$BA50 -> 0.12518112 | BD50: =$AV50/100*(AO50-100)*HAVERQ!D93/1000+(AT50-100)*AY50/$BA50 -> 0.48071121 | BE50: =$AV50/100*(AP50-100)*HAVERQ!E93/1000+(AU50-100)*AZ50/$BA50 -> 0.094291226 | BF50: =BG50-BE50-BD50-BC50 -> 2.0537953 | BG50: =$AV50/100*(AQ50-100)*1000/1000+(AV50-100)*BA50/$BA50 -> 2.7539788 | BH50: =100*((DataQ!V201/DataQ!V197)-1) -> 2.7539788 | BI50: 2 | BK50: 43040 | BL50: =HAVERM!B341 -> 1.61 | BM50: =HAVERM!C341 -> 2.04 | BQ50: =BL50-BT50 -> 0.93155238 | BR50: =BM50-BU50 -> 1.1523905 | BT50: =HAVERM!D341 -> 0.67844762 | BU50: =HAVERM!E341 -> 0.88760952 | BW50: =BL50-BL26 -> -0.31 | BY50: 0
AG51: 44470 | AH51: =100*((DataQ!U202/DataQ!U198)-1) -> 4.5267549 | AI51: =100*((DataQ!V202/DataQ!V198)-1) -> 4.8899435 | AJ51: =AH51-AI51 -> -0.36318864 | AK51: 0 | AM51: 44470 | AN51: =DataQ!W202/DataQ!W198*100 -> 102.86518 | AO51: =DataQ!X202/DataQ!X198*100 -> 125.60107 | AP51: =DataQ!Y202/DataQ!Y198*100 -> 122.98009 | AQ51: =DataQ!V202/DataQ!V198*100 -> 104.88994 | AS51: =DataQ!W198/DataQ!W198*100 -> 100 | AT51: =DataQ!X198/DataQ!X198*100 -> 100 | AU51: =DataQ!Y198/DataQ!Y198*100 -> 100 | AV51: =DataQ!V198/DataQ!V198*100 -> 100 | AX51: =HAVERQ!C94*AN51/$AQ51 -> 155.93072 | AY51: =HAVERQ!D94*AO51/$AQ51 -> 32.331307 | AZ51: =HAVERQ!E94*AP51/$AQ51 -> 38.691441 | BA51: =1000*AQ51/$AQ51 -> 1000 | BC51: =$AV51/100*(AN51-100)*HAVERQ!C94/1000+(AS51-100)*AX51/$BA51 -> 0.45556411 | BD51: =$AV51/100*(AO51-100)*HAVERQ!D94/1000+(AT51-100)*AY51/$BA51 -> 0.69122895 | BE51: =$AV51/100*(AP51-100)*HAVERQ!E94/1000+(AU51-100)*AZ51/$BA51 -> 0.75834303 | BF51: =BG51-BE51-BD51-BC51 -> 2.9848074 | BG51: =$AV51/100*(AQ51-100)*1000/1000+(AV51-100)*BA51/$BA51 -> 4.8899435 | BH51: =100*((DataQ!V202/DataQ!V198)-1) -> 4.8899435 | BI51: 2 | BK51: 43070 | BL51: =HAVERM!B342 -> 1.57 | BM51: =HAVERM!C342 -> 2.07 | BQ51: =BL51-BT51 -> 0.88347143 | BR51: =BM51-BU51 -> 1.1779048 | BT51: =HAVERM!D342 -> 0.68652857 | BU51: =HAVERM!E342 -> 0.89209524 | BW51: =BL51-BL27 -> -0.33 | BY51: 0
AG52: 44562 | AH52: =100*((DataQ!U203/DataQ!U199)-1) -> 6.9863766 | AI52: =100*((DataQ!V203/DataQ!V199)-1) -> 6.1984103 | AJ52: =AH52-AI52 -> 0.78796623 | AK52: 0 | AM52: 44562 | AN52: =DataQ!W203/DataQ!W202*100 -> 102.45232 | AO52: =DataQ!X203/DataQ!X202*100 -> 105.79405 | AP52: =DataQ!Y203/DataQ!Y202*100 -> 101.15775 | AQ52: =DataQ!V203/DataQ!V202*100 -> 101.3403 | AS52: =DataQ!W202/DataQ!W199*100 -> 102.22841 | AT52: =DataQ!X202/DataQ!X199*100 -> 118.73471 | AU52: =DataQ!Y202/DataQ!Y199*100 -> 122.17109 | AV52: =DataQ!V202/DataQ!V199*100 -> 104.79386 | AX52: =HAVERQ!C95*AN52/$AQ52 -> 166.81056 | AY52: =HAVERQ!D95*AO52/$AQ52 -> 32.362403 | AZ52: =HAVERQ!E95*AP52/$AQ52 -> 35.935154 | BA52: =1000*AQ52/$AQ52 -> 1000 | BC52: =$AV52/100*(AN52-100)*HAVERQ!C95/1000+(AS52-100)*AX52/$BA52 -> 0.79575236 | BD52: =$AV52/100*(AO52-100)*HAVERQ!D95/1000+(AT52-100)*AY52/$BA52 -> 0.79452631 | BE52: =$AV52/100*(AP52-100)*HAVERQ!E95/1000+(AU52-100)*AZ52/$BA52 -> 0.84039883 | BF52: =BG52-BE52-BD52-BC52 -> 3.7677328 | BG52: =$AV52/100*(AQ52-100)*1000/1000+(AV52-100)*BA52/$BA52 -> 6.1984103 | BH52: =100*((DataQ!V203/DataQ!V199)-1) -> 6.1984103 | BI52: 2 | BK52: 43101 | BL52: =HAVERM!B343 -> 1.54 | BM52: =HAVERM!C343 -> 1.98 | BQ52: =BL52-BT52 -> 0.79875455 | BR52: =BM52-BU52 -> 0.99838636 | BT52: =HAVERM!D343 -> 0.74124545 | BU52: =HAVERM!E343 -> 0.98161364 | BW52: =BL52-BL28 -> -0.39 | BY52: 0
AG53: 44652 | AH53: =100*((DataQ!U204/DataQ!U200)-1) -> 5.1326471 | AI53: =100*((DataQ!V204/DataQ!V200)-1) -> 9.1511767 | AJ53: =AH53-AI53 -> -4.0185297 | AK53: 0 | AM53: 44652 | AN53: =DataQ!W204/DataQ!W202*100 -> 105.23769 | AO53: =DataQ!X204/DataQ!X202*100 -> 120.74492 | AP53: =DataQ!Y204/DataQ!Y202*100 -> 151.26551 | AQ53: =DataQ!V204/DataQ!V202*100 -> 105.65271 | AS53: =DataQ!W202/DataQ!W200*100 -> 101.94444 | AT53: =DataQ!X202/DataQ!X200*100 -> 112.28579 | AU53: =DataQ!Y202/DataQ!Y200*100 -> 112.3412 | AV53: =DataQ!V202/DataQ!V200*100 -> 103.31129 | AX53: =HAVERQ!C96*AN53/$AQ53 -> 165.34793 | AY53: =HAVERQ!D96*AO53/$AQ53 -> 35.428269 | AZ53: =HAVERQ!E96*AP53/$AQ53 -> 51.54206 | BA53: =1000*AQ53/$AQ53 -> 1000 | BC53: =$AV53/100*(AN53-100)*HAVERQ!C96/1000+(AS53-100)*AX53/$BA53 -> 1.2197571 | BD53: =$AV53/100*(AO53-100)*HAVERQ!D96/1000+(AT53-100)*AY53/$BA53 -> 1.0996517 | BE53: =$AV53/100*(AP53-100)*HAVERQ!E96/1000+(AU53-100)*AZ53/$BA53 -> 2.5427609 | BF53: =BG53-BE53-BD53-BC53 -> 4.289007 | BG53: =$AV53/100*(AQ53-100)*1000/1000+(AV53-100)*BA53/$BA53 -> 9.1511767 | BH53: =100*((DataQ!V204/DataQ!V200)-1) -> 9.1511767 | BI53: 2 | BK53: 43132 | BL53: =HAVERM!B344 -> 1.49 | BM53: =HAVERM!C344 -> 1.99 | BQ53: =BL53-BT53 -> 0.62635 | BR53: =BM53-BU53 -> 0.81268 | BT53: =HAVERM!D344 -> 0.86365 | BU53: =HAVERM!E344 -> 1.17732 | BW53: =BL53-BL29 -> -0.46 | BY53: 0
AG54: 44743 | AH54: =100*((DataQ!U205/DataQ!U201)-1) -> 5.8823469 | AI54: =100*((DataQ!V205/DataQ!V201)-1) -> 10.005959 | AJ54: =AH54-AI54 -> -4.123612 | AK54: 0 | AM54: 44743 | AN54: =DataQ!W205/DataQ!W202*100 -> 109.17348 | AO54: =DataQ!X205/DataQ!X202*100 -> 125.06466 | AP54: =DataQ!Y205/DataQ!Y202*100 -> 151.77706 | AQ54: =DataQ!V205/DataQ!V202*100 -> 107.634 | AS54: =DataQ!W202/DataQ!W201*100 -> 101.66205 | AT54: =DataQ!X202/DataQ!X201*100 -> 107.18054 | AU54: =DataQ!Y202/DataQ!Y201*100 -> 112.0362 | AV54: =DataQ!V202/DataQ!V201*100 -> 102.20372 | AX54: =HAVERQ!C97*AN54/$AQ54 -> 168.37428 | AY54: =HAVERQ!D97*AO54/$AQ54 -> 36.020257 | AZ54: =HAVERQ!E97*AP54/$AQ54 -> 50.764386 | BA54: =1000*AQ54/$AQ54 -> 1000 | BC54: =$AV54/100*(AN54-100)*HAVERQ!C97/1000+(AS54-100)*AX54/$BA54 -> 1.8362021 | BD54: =$AV54/100*(AO54-100)*HAVERQ!D97/1000+(AT54-100)*AY54/$BA54 -> 1.0527724 | BE54: =$AV54/100*(AP54-100)*HAVERQ!E97/1000+(AU54-100)*AZ54/$BA54 -> 2.5160612 | BF54: =BG54-BE54-BD54-BC54 -> 4.6009232 | BG54: =$AV54/100*(AQ54-100)*1000/1000+(AV54-100)*BA54/$BA54 -> 10.005959 | BH54: =100*((DataQ!V205/DataQ!V201)-1) -> 10.005959 | BI54: 2 | BK54: 43160 | BL54: =HAVERM!B345 -> 1.53 | BM54: =HAVERM!C345 -> 2.02 | BQ54: =BL54-BT54 -> 0.63301818 | BR54: =BM54-BU54 -> 0.89234545 | BT54: =HAVERM!D345 -> 0.89698182 | BU54: =HAVERM!E345 -> 1.1276545 | BW54: =BL54-BL30 -> -0.37 | BY54: 0
AG55: 44835 | AH55: =100*((DataQ!U206/DataQ!U202)-1) -> 6.355444 | AI55: =100*((DataQ!V206/DataQ!V202)-1) -> 10.751748 | AJ55: =AH55-AI55 -> -4.3963043 | AK55: 0 | AM55: 44835 | AN55: =DataQ!W206/DataQ!W202*100 -> 112.89737 | AO55: =DataQ!X206/DataQ!X202*100 -> 116.83911 | AP55: =DataQ!Y206/DataQ!Y202*100 -> 189.14919 | AQ55: =DataQ!V206/DataQ!V202*100 -> 110.75175 | AS55: =DataQ!W202/DataQ!W202*100 -> 100 | AT55: =DataQ!X202/DataQ!X202*100 -> 100 | AU55: =DataQ!Y202/DataQ!Y202*100 -> 100 | AV55: =DataQ!V202/DataQ!V202*100 -> 100 | AX55: =HAVERQ!C98*AN55/$AQ55 -> 169.21595 | AY55: =HAVERQ!D98*AO55/$AQ55 -> 32.703884 | AZ55: =HAVERQ!E98*AP55/$AQ55 -> 61.483191 | BA55: =1000*AQ55/$AQ55 -> 1000 | BC55: =$AV55/100*(AN55-100)*HAVERQ!C98/1000+(AS55-100)*AX55/$BA55 -> 2.1409628 | BD55: =$AV55/100*(AO55-100)*HAVERQ!D98/1000+(AT55-100)*AY55/$BA55 -> 0.52201228 | BE55: =$AV55/100*(AP55-100)*HAVERQ!E98/1000+(AU55-100)*AZ55/$BA55 -> 3.2093709 | BF55: =BG55-BE55-BD55-BC55 -> 4.8794023 | BG55: =$AV55/100*(AQ55-100)*1000/1000+(AV55-100)*BA55/$BA55 -> 10.751748 | BH55: =100*((DataQ!V206/DataQ!V202)-1) -> 10.751748 | BI55: 2 | BK55: 43191 | BL55: =HAVERM!B346 -> 1.72 | BM55: =HAVERM!C346 -> 2.01 | BQ55: =BL55-BT55 -> 0.8357 | BR55: =BM55-BU55 -> 0.90777143 | BT55: =HAVERM!D346 -> 0.8843 | BU55: =HAVERM!E346 -> 1.1022286 | BW55: =BL55-BL31 -> -0.12 | BY55: 0
AG56: 44927 | AH56: =100*((DataQ!U207/DataQ!U203)-1) -> 6.3087995 | AI56: =100*((DataQ!V207/DataQ!V203)-1) -> 10.178266 | AJ56: =AH56-AI56 -> -3.8694668 | AK56: 0 | AM56: 44927 | AN56: =DataQ!W207/DataQ!W206*100 -> 103.62027 | AO56: =DataQ!X207/DataQ!X206*100 -> 92.207175 | AP56: =DataQ!Y207/DataQ!Y206*100 -> 100.45549 | AQ56: =DataQ!V207/DataQ!V206*100 -> 100.81555 | AS56: =DataQ!W206/DataQ!W203*100 -> 110.19504 | AT56: =DataQ!X206/DataQ!X203*100 -> 110.44015 | AU56: =DataQ!Y206/DataQ!Y203*100 -> 186.98437 | AV56: =DataQ!V206/DataQ!V203*100 -> 109.28698 | AX56: =HAVERQ!C99*AN56/$AQ56 -> 164.79386 | AY56: =HAVERQ!D99*AO56/$AQ56 -> 28.657863 | AZ56: =HAVERQ!E99*AP56/$AQ56 -> 48.492854 | BA56: =1000*AQ56/$AQ56 -> 1000 | BC56: =$AV56/100*(AN56-100)*HAVERQ!C99/1000+(AS56-100)*AX56/$BA56 -> 2.3144361 | BD56: =$AV56/100*(AO56-100)*HAVERQ!D99/1000+(AT56-100)*AY56/$BA56 -> 0.032340671 | BE56: 3.17 | BF56: =BG56-BE56-BD56-BC56 -> 4.6614895 | BG56: =$AV56/100*(AQ56-100)*1000/1000+(AV56-100)*BA56/$BA56 -> 10.178266 | BH56: =100*((DataQ!V207/DataQ!V203)-1) -> 10.178266 | BI56: 2 | BK56: 43221 | BL56: =HAVERM!B347 -> 1.74 | BM56: =HAVERM!C347 -> 2.06 | BQ56: =BL56-BT56 -> 0.95797826 | BR56: =BM56-BU56 -> 1.0067348 | BT56: =HAVERM!D347 -> 0.78202174 | BU56: =HAVERM!E347 -> 1.0532652 | BW56: =BL56-BL32 -> -0.17 | BY56: 0
AG57: 45017 | AH57: =100*((DataQ!U208/DataQ!U204)-1) -> 8.283044 | AI57: =100*((DataQ!V208/DataQ!V204)-1) -> 8.439049 | AJ57: =AH57-AI57 -> -0.15600499 | AK57: 0 | AM57: 45017 | AN57: =DataQ!W208/DataQ!W206*100 -> 107.66959 | AO57: =DataQ!X208/DataQ!X206*100 -> 87.668787 | AP57: =DataQ!Y208/DataQ!Y206*100 -> 98.98931 | AQ57: =DataQ!V208/DataQ!V206*100 -> 103.44649 | AS57: =DataQ!W206/DataQ!W204*100 -> 107.27845 | AT57: =DataQ!X206/DataQ!X204*100 -> 96.765231 | AU57: =DataQ!Y206/DataQ!Y204*100 -> 125.0445 | AV57: =DataQ!V206/DataQ!V204*100 -> 104.82623 | AX57: =HAVERQ!C100*AN57/$AQ57 -> 167.57267 | AY57: =HAVERQ!D100*AO57/$AQ57 -> 26.271867 | AZ57: =HAVERQ!E100*AP57/$AQ57 -> 46.888747 | BA57: =1000*AQ57/$AQ57 -> 1000 | BC57: =$AV57/100*(AN57-100)*HAVERQ!C100/1000+(AS57-100)*AX57/$BA57 -> 2.5140677 | BD57: =$AV57/100*(AO57-100)*HAVERQ!D100/1000+(AT57-100)*AY57/$BA57 -> -0.4857001 | BE57: =$AV57/100*(AP57-100)*HAVERQ!E100/1000+(AU57-100)*AZ57/$BA57 -> 1.122391 | BF57: =BG57-BE57-BD57-BC57 -> 5.2882903 | BG57: =$AV57/100*(AQ57-100)*1000/1000+(AV57-100)*BA57/$BA57 -> 8.439049 | BH57: =100*((DataQ!V208/DataQ!V204)-1) -> 8.439049 | BI57: 2 | BK57: 43252 | BL57: =HAVERM!B348 -> 1.74 | BM57: =HAVERM!C348 -> 2.03 | BQ57: =BL57-BT57 -> 0.94799524 | BR57: =BM57-BU57 -> 0.99781905 | BT57: =HAVERM!D348 -> 0.79200476 | BU57: =HAVERM!E348 -> 1.032181 | BW57: =BL57-BL33 -> -0.01 | BY57: 0
AG58: 45108 | AH58: =100*((DataQ!U209/DataQ!U205)-1) -> 7.9827346 | AI58: =100*((DataQ!V209/DataQ!V205)-1) -> 6.7136185 | AJ58: =AH58-AI58 -> 1.2691161 | AK58: 0 | AM58: 45108 | AN58: =DataQ!W209/DataQ!W206*100 -> 108.84956 | AO58: =DataQ!X209/DataQ!X206*100 -> 88.554308 | AP58: =DataQ!Y209/DataQ!Y206*100 -> 84.213511 | AQ58: =DataQ!V209/DataQ!V206*100 -> 103.70955 | AS58: =DataQ!W206/DataQ!W205*100 -> 103.41098 | AT58: =DataQ!X206/DataQ!X205*100 -> 93.422959 | AU58: =DataQ!Y206/DataQ!Y205*100 -> 124.62304 | AV58: =DataQ!V206/DataQ!V205*100 -> 102.89662 | AX58: =HAVERQ!C101*AN58/$AQ58 -> 168.97941 | AY58: =HAVERQ!D101*AO58/$AQ58 -> 26.469921 | AZ58: =HAVERQ!E101*AP58/$AQ58 -> 39.788641 | BA58: =1000*AQ58/$AQ58 -> 1000 | BC58: =$AV58/100*(AN58-100)*HAVERQ!C101/1000+(AS58-100)*AX58/$BA58 -> 2.0424348 | BD58: =$AV58/100*(AO58-100)*HAVERQ!D101/1000+(AT58-100)*AY58/$BA58 -> -0.53918786 | BE58: =$AV58/100*(AP58-100)*HAVERQ!E101/1000+(AU58-100)*AZ58/$BA58 -> 0.18377308 | BF58: =BG58-BE58-BD58-BC58 -> 5.0265985 | BG58: =$AV58/100*(AQ58-100)*1000/1000+(AV58-100)*BA58/$BA58 -> 6.7136185 | BH58: =100*((DataQ!V209/DataQ!V205)-1) -> 6.7136185 | BI58: 2 | BK58: 43282 | BL58: =HAVERM!B349 -> 1.75 | BM58: =HAVERM!C349 -> 2.04 | BQ58: =BL58-BT58 -> 0.91528636 | BR58: =BM58-BU58 -> 1.0096955 | BT58: =HAVERM!D349 -> 0.83471364 | BU58: =HAVERM!E349 -> 1.0303045 | BW58: =BL58-BL34 -> 0.03 | BY58: 0
AG59: 45200 | AH59: =100*((DataQ!U210/DataQ!U206)-1) -> 5.7641568 | AI59: =100*((DataQ!V210/DataQ!V206)-1) -> 4.1568272 | AJ59: =AH59-AI59 -> 1.6073297 | AK59: 0 | AM59: 45200 | AN59: =DataQ!W210/DataQ!W206*100 -> 109.68085 | AO59: =DataQ!X210/DataQ!X206*100 -> 90.325417 | AP59: =DataQ!Y210/DataQ!Y206*100 -> 78.419903 | AQ59: =DataQ!V210/DataQ!V206*100 -> 104.15683 | AS59: =DataQ!W206/DataQ!W206*100 -> 100 | AT59: =DataQ!X206/DataQ!X206*100 -> 100 | AU59: =DataQ!Y206/DataQ!Y206*100 -> 100 | AV59: =DataQ!V206/DataQ!V206*100 -> 100 | AX59: =HAVERQ!C102*AN59/$AQ59 -> 169.53874 | AY59: =HAVERQ!D102*AO59/$AQ59 -> 26.883384 | AZ59: =HAVERQ!E102*AP59/$AQ59 -> 36.892207 | BA59: =1000*AQ59/$AQ59 -> 1000 | BC59: =$AV59/100*(AN59-100)*HAVERQ!C102/1000+(AS59-100)*AX59/$BA59 -> 1.5586173 | BD59: =$AV59/100*(AO59-100)*HAVERQ!D102/1000+(AT59-100)*AY59/$BA59 -> -0.29991207 | BE59: =$AV59/100*(AP59-100)*HAVERQ!E102/1000+(AU59-100)*AZ59/$BA59 -> -1.0574247 | BF59: =BG59-BE59-BD59-BC59 -> 3.9555467 | BG59: =$AV59/100*(AQ59-100)*1000/1000+(AV59-100)*BA59/$BA59 -> 4.1568272 | BH59: =100*((DataQ!V210/DataQ!V206)-1) -> 4.1568272 | BI59: 2 | BK59: 43313 | BL59: =HAVERM!B350 -> 1.75 | BM59: =HAVERM!C350 -> 2.03 | BQ59: =BL59-BT59 -> 0.88283478 | BR59: =BM59-BU59 -> 0.9683913 | BT59: =HAVERM!D350 -> 0.86716522 | BU59: =HAVERM!E350 -> 1.0616087 | BW59: =BL59-BL35 -> 0.06 | BY59: 0
AG60: 45292 | AH60: =100*((DataQ!U211/DataQ!U207)-1) -> 5.9344095 | AI60: =100*((DataQ!V211/DataQ!V207)-1) -> 3.5491137 | AJ60: =AH60-AI60 -> 2.3852958 | AK60: 0 | AM60: 45292 | AN60: =DataQ!W211/DataQ!W210*100 -> 101.05139 | AO60: =DataQ!X211/DataQ!X210*100 -> 95.490221 | AP60: =DataQ!Y211/DataQ!Y210*100 -> 104.77403 | AQ60: =DataQ!V211/DataQ!V210*100 -> 100.22733 | AS60: =DataQ!W210/DataQ!W207*100 -> 105.84884 | AT60: =DataQ!X210/DataQ!X207*100 -> 97.959207 | AU60: =DataQ!Y210/DataQ!Y207*100 -> 78.06433 | AV60: =DataQ!V210/DataQ!V207*100 -> 103.31425 | AX60: =HAVERQ!C103*AN60/$AQ60 -> 153.1105 | AY60: =HAVERQ!D103*AO60/$AQ60 -> 29.546831 | AZ60: =HAVERQ!E103*AP60/$AQ60 -> 41.99798 | BA60: =1000*AQ60/$AQ60 -> 1000 | BC60: =$AV60/100*(AN60-100)*HAVERQ!C103/1000+(AS60-100)*AX60/$BA60 -> 1.0604765 | BD60: =$AV60/100*(AO60-100)*HAVERQ!D103/1000+(AT60-100)*AY60/$BA60 -> -0.20479425 | BE60: =$AV60/100*(AP60-100)*HAVERQ!E103/1000+(AU60-100)*AZ60/$BA60 -> -0.72309844 | BF60: =BG60-BE60-BD60-BC60 -> 3.4165298 | BG60: =$AV60/100*(AQ60-100)*1000/1000+(AV60-100)*BA60/$BA60 -> 3.5491137 | BH60: =100*((DataQ!V211/DataQ!V207)-1) -> 3.5491137 | BI60: 2 | BK60: 43344 | BL60: =HAVERM!B351 -> 1.71 | BM60: =HAVERM!C351 -> 2.01 | BQ60: =BL60-BT60 -> 0.790295 | BR60: =BM60-BU60 -> 0.85918 | BT60: =HAVERM!D351 -> 0.919705 | BU60: =HAVERM!E351 -> 1.15082 | BW60: =BL60-BL36 -> 0.12 | BY60: 0
AG61: 45383 | AH61: =100*((DataQ!U212/DataQ!U208)-1) -> 4.5592705 | AI61: =100*((DataQ!V212/DataQ!V208)-1) -> 2.1108336 | AJ61: =AH61-AI61 -> 2.4484369 | AK61: 0 | AM61: 45383 | AN61: =DataQ!W212/DataQ!W210*100 -> 101.58927 | AO61: =DataQ!X212/DataQ!X210*100 -> 98.529412 | AP61: =DataQ!Y212/DataQ!Y210*100 -> 91.976782 | AQ61: =DataQ!V212/DataQ!V210*100 -> 101.41445 | AS61: =DataQ!W210/DataQ!W208*100 -> 101.868 | AT61: =DataQ!X210/DataQ!X208*100 -> 103.0303 | AU61: =DataQ!Y210/DataQ!Y208*100 -> 79.220578 | AV61: =DataQ!V210/DataQ!V208*100 -> 100.68667 | AX61: =HAVERQ!C104*AN61/$AQ61 -> 152.55813 | AY61: =HAVERQ!D104*AO61/$AQ61 -> 29.984719 | AZ61: =HAVERQ!E104*AP61/$AQ61 -> 37.082948 | BA61: =1000*AQ61/$AQ61 -> 1000 | BC61: =$AV61/100*(AN61-100)*HAVERQ!C104/1000+(AS61-100)*AX61/$BA61 -> 0.52867826 | BD61: =$AV61/100*(AO61-100)*HAVERQ!D104/1000+(AT61-100)*AY61/$BA61 -> 0.045164804 | BE61: =$AV61/100*(AP61-100)*HAVERQ!E104/1000+(AU61-100)*AZ61/$BA61 -> -1.1008682 | BF61: =BG61-BE61-BD61-BC61 -> 2.6378588 | BG61: =$AV61/100*(AQ61-100)*1000/1000+(AV61-100)*BA61/$BA61 -> 2.1108336 | BH61: =100*((DataQ!V212/DataQ!V208)-1) -> 2.1108336 | BI61: 2 | BK61: 43374 | BL61: =HAVERM!B352 -> 1.8 | BM61: =HAVERM!C352 -> 2.06 | BQ61: =BL61-BT61 -> 0.85045217 | BR61: =BM61-BU61 -> 0.86357826 | BT61: =HAVERM!D352 -> 0.94954783 | BU61: =HAVERM!E352 -> 1.1964217 | BW61: =BL61-BL37 -> 0.28 | BY61: 0
AG62: 45474 | AH62: =100*((DataQ!U213/DataQ!U209)-1) -> 4.1318484 | AI62: =100*((DataQ!V213/DataQ!V209)-1) -> 2.0927702 | AJ62: =AH62-AI62 -> 2.0390782 | AK62: 0 | AM62: 45474 | AN62: =DataQ!W213/DataQ!W210*100 -> 101.74653 | AO62: =DataQ!X213/DataQ!X210*100 -> 94.946618 | AP62: =DataQ!Y213/DataQ!Y210*100 -> 85.559918 | AQ62: =DataQ!V213/DataQ!V210*100 -> 101.65436 | AS62: =DataQ!W210/DataQ!W209*100 -> 100.76371 | AT62: =DataQ!X210/DataQ!X209*100 -> 102.00003 | AU62: =DataQ!Y210/DataQ!Y209*100 -> 93.120335 | AV62: =DataQ!V210/DataQ!V209*100 -> 100.43128 | AX62: =HAVERQ!C105*AN62/$AQ62 -> 152.43369 | AY62: =HAVERQ!D105*AO62/$AQ62 -> 28.826202 | AZ62: =HAVERQ!E105*AP62/$AQ62 -> 34.414402 | BA62: =1000*AQ62/$AQ62 -> 1000 | BC62: =$AV62/100*(AN62-100)*HAVERQ!C105/1000+(AS62-100)*AX62/$BA62 -> 0.38355094 | BD62: =$AV62/100*(AO62-100)*HAVERQ!D105/1000+(AT62-100)*AY62/$BA62 -> -0.098980512 | BE62: =$AV62/100*(AP62-100)*HAVERQ!E105/1000+(AU62-100)*AZ62/$BA62 -> -0.82973204 | BF62: =BG62-BE62-BD62-BC62 -> 2.6379318 | BG62: =$AV62/100*(AQ62-100)*1000/1000+(AV62-100)*BA62/$BA62 -> 2.0927702 | BH62: =100*((DataQ!V213/DataQ!V209)-1) -> 2.0927702 | BI62: 2 | BK62: 43405 | BL62: =HAVERM!B353 -> 1.75 | BM62: =HAVERM!C353 -> 2.02 | BQ62: =BL62-BT62 -> 0.83523182 | BR62: =BM62-BU62 -> 0.89829545 | BT62: =HAVERM!D353 -> 0.91476818 | BU62: =HAVERM!E353 -> 1.1217045 | BW62: =BL62-BL38 -> 0.32 | BY62: 0
AG63: 45566 | AH63: =100*((DataQ!U214/DataQ!U210)-1) -> 5.3200497 | AI63: =100*((DataQ!V214/DataQ!V210)-1) -> 2.5582969 | AJ63: =AH63-AI63 -> 2.7617528 | AK63: 0 | AM63: 45566 | AN63: =DataQ!W214/DataQ!W210*100 -> 102.09083 | AO63: =DataQ!X214/DataQ!X210*100 -> 94.298824 | AP63: =DataQ!Y214/DataQ!Y210*100 -> 93.141059 | AQ63: =DataQ!V214/DataQ!V210*100 -> 102.5583 | AS63: =DataQ!W210/DataQ!W210*100 -> 100 | AT63: =DataQ!X210/DataQ!X210*100 -> 100 | AU63: =DataQ!Y210/DataQ!Y210*100 -> 100 | AV63: =DataQ!V210/DataQ!V210*100 -> 100 | AX63: =HAVERQ!C106*AN63/$AQ63 -> 151.60143 | AY63: =HAVERQ!D106*AO63/$AQ63 -> 28.37719 | AZ63: =HAVERQ!E106*AP63/$AQ63 -> 37.13353 | BA63: =1000*AQ63/$AQ63 -> 1000 | BC63: =$AV63/100*(AN63-100)*HAVERQ!C106/1000+(AS63-100)*AX63/$BA63 -> 0.31842448 | BD63: =$AV63/100*(AO63-100)*HAVERQ!D106/1000+(AT63-100)*AY63/$BA63 -> -0.1759537 | BE63: =$AV63/100*(AP63-100)*HAVERQ!E106/1000+(AU63-100)*AZ63/$BA63 -> -0.28044839 | BF63: =BG63-BE63-BD63-BC63 -> 2.6962745 | BG63: =$AV63/100*(AQ63-100)*1000/1000+(AV63-100)*BA63/$BA63 -> 2.5582969 | BH63: =100*((DataQ!V214/DataQ!V210)-1) -> 2.5582969 | BI63: 2 | BK63: 43435 | BL63: =HAVERM!B354 -> 1.73 | BM63: =HAVERM!C354 -> 2.01 | BQ63: =BL63-BT63 -> 0.8571 | BR63: =BM63-BU63 -> 0.98364286 | BT63: =HAVERM!D354 -> 0.8729 | BU63: =HAVERM!E354 -> 1.0263571 | BW63: =BL63-BL39 -> 0.28 | BY63: 0
AG64: 45658 | AH64: =100*((DataQ!U215/DataQ!U211)-1) -> 4.3469634 | AI64: =100*((DataQ!V215/DataQ!V211)-1) -> 2.7192785 | AJ64: =AH64-AI64 -> 1.6276848 | AK64: 0 | AM64: 45658 | AN64: =DataQ!W215/DataQ!W214*100 -> 100.91203 | AO64: =DataQ!X215/DataQ!X214*100 -> 99.826116 | AP64: =DataQ!Y215/DataQ!Y214*100 -> 104.36108 | AQ64: =DataQ!V215/DataQ!V214*100 -> 100.38465 | AS64: =DataQ!W214/DataQ!W211*100 -> 101.02862 | AT64: =DataQ!X214/DataQ!X211*100 -> 98.752336 | AU64: =DataQ!Y214/DataQ!Y211*100 -> 88.897089 | AV64: =DataQ!V214/DataQ!V211*100 -> 102.32568 | AX64: =HAVERQ!C107*AN64/$AQ64 -> 153.0957 | AY64: =HAVERQ!D107*AO64/$AQ64 -> 30.690981 | AZ64: =HAVERQ!E107*AP64/$AQ64 -> 42.507651 | BA64: =1000*AQ64/$AQ64 -> 1000 | BC64: =$AV64/100*(AN64-100)*HAVERQ!C107/1000+(AS64-100)*AX64/$BA64 -> 0.29960646 | BD64: =$AV64/100*(AO64-100)*HAVERQ!D107/1000+(AT64-100)*AY64/$BA64 -> -0.043783369 | BE64: =$AV64/100*(AP64-100)*HAVERQ!E107/1000+(AU64-100)*AZ64/$BA64 -> -0.28949585 | BF64: =BG64-BE64-BD64-BC64 -> 2.7529513 | BG64: =$AV64/100*(AQ64-100)*1000/1000+(AV64-100)*BA64/$BA64 -> 2.7192785 | BH64: =100*((DataQ!V215/DataQ!V211)-1) -> 2.7192785 | BI64: 2 | BK64: 43466 | BL64: =HAVERM!B355 -> 1.72 | BM64: =HAVERM!C355 -> 2.05 | BQ64: =BL64-BT64 -> 0.85026087 | BR64: =BM64-BU64 -> 1.0260217 | BT64: =HAVERM!D355 -> 0.86973913 | BU64: =HAVERM!E355 -> 1.0239783 | BW64: =BL64-BL40 -> 0.27 | BX64: =BM64-BM4 -> -1.29 | BY64: 0
AG65: 45748 | AH65: =100*((DataQ!U216/DataQ!U212)-1) -> 3.5907849 | AI65: =100*((DataQ!V216/DataQ!V212)-1) -> 2.4867503 | AJ65: =AH65-AI65 -> 1.1040346 | AK65: 0 | AM65: 45748 | AN65: =DataQ!W216/DataQ!W214*100 -> 101.28384 | AO65: =DataQ!X216/DataQ!X214*100 -> 99.281149 | AP65: =DataQ!Y216/DataQ!Y214*100 -> 103.90966 | AQ65: =DataQ!V216/DataQ!V214*100 -> 101.3437 | AS65: =DataQ!W214/DataQ!W212*100 -> 100.49372 | AT65: =DataQ!X214/DataQ!X212*100 -> 95.706269 | AU65: =DataQ!Y214/DataQ!Y212*100 -> 101.26584 | AV65: =DataQ!V214/DataQ!V212*100 -> 101.1279 | AX65: =HAVERQ!C108*AN65/$AQ65 -> 152.20565 | AY65: =HAVERQ!D108*AO65/$AQ65 -> 30.234581 | AZ65: =HAVERQ!E108*AP65/$AQ65 -> 41.923258 | BA65: =1000*AQ65/$AQ65 -> 1000 | BC65: =$AV65/100*(AN65-100)*HAVERQ!C108/1000+(AS65-100)*AX65/$BA65 -> 0.27287551 | BD65: =$AV65/100*(AO65-100)*HAVERQ!D108/1000+(AT65-100)*AY65/$BA65 -> -0.15225507 | BE65: =$AV65/100*(AP65-100)*HAVERQ!E108/1000+(AU65-100)*AZ65/$BA65 -> 0.21472915 | BF65: =BG65-BE65-BD65-BC65 -> 2.1514007 | BG65: =$AV65/100*(AQ65-100)*1000/1000+(AV65-100)*BA65/$BA65 -> 2.4867503 | BH65: =100*((DataQ!V216/DataQ!V212)-1) -> 2.4867503 | BI65: 2 | BK65: 43497 | BL65: =HAVERM!B356 -> 1.7 | BM65: =HAVERM!C356 -> 2.05 | BQ65: =BL65-BT65 -> 0.873395 | BR65: =BM65-BU65 -> 1.07894 | BT65: =HAVERM!D356 -> 0.826605 | BU65: =HAVERM!E356 -> 0.97106 | BW65: =BL65-BL41 -> 0.28 | BX65: =BM65-BM5 -> -1.4 | BY65: 0
AG66: 45839 | AH66: =100*((DataQ!U217/DataQ!U213)-1) -> 3.268857 | AI66: =100*((DataQ!V217/DataQ!V213)-1) -> 2.7588541 | AJ66: =AH66-AI66 -> 0.51000295 | AK66: 0 | AM66: 45839 | AN66: =DataQ!W217/DataQ!W214*100 -> 101.31603 | AO66: =DataQ!X217/DataQ!X214*100 -> 98.824528 | AP66: =DataQ!Y217/DataQ!Y214*100 -> 103.47508 | AQ66: =DataQ!V217/DataQ!V214*100 -> 101.85315 | AS66: =DataQ!W214/DataQ!W213*100 -> 100.33839 | AT66: =DataQ!X214/DataQ!X213*100 -> 99.317728 | AU66: =DataQ!Y214/DataQ!Y213*100 -> 108.86062 | AV66: =DataQ!V214/DataQ!V213*100 -> 100.88923 | AX66: =HAVERQ!C109*AN66/$AQ66 -> 151.49248 | AY66: =HAVERQ!D109*AO66/$AQ66 -> 29.944993 | AZ66: =HAVERQ!E109*AP66/$AQ66 -> 41.539109 | BA66: =1000*AQ66/$AQ66 -> 1000 | BC66: =$AV66/100*(AN66-100)*HAVERQ!C109/1000+(AS66-100)*AX66/$BA66 -> 0.25347177 | BD66: =$AV66/100*(AO66-100)*HAVERQ!D109/1000+(AT66-100)*AY66/$BA66 -> -0.057031452 | BE66: =$AV66/100*(AP66-100)*HAVERQ!E109/1000+(AU66-100)*AZ66/$BA66 -> 0.51141475 | BF66: =BG66-BE66-BD66-BC66 -> 2.050999 | BG66: =$AV66/100*(AQ66-100)*1000/1000+(AV66-100)*BA66/$BA66 -> 2.7588541 | BH66: =100*((DataQ!V217/DataQ!V213)-1) -> 2.7588541 | BI66: 2 | BK66: 43525 | BL66: =HAVERM!B357 -> 1.7 | BM66: =HAVERM!C357 -> 2.03 | BQ66: =BL66-BT66 -> 0.90167619 | BR66: =BM66-BU66 -> 1.0868 | BT66: =HAVERM!D357 -> 0.79832381 | BU66: =HAVERM!E357 -> 0.9432 | BW66: =BL66-BL42 -> 0.33 | BX66: =BM66-BM6 -> -1.45 | BY66: 0
AG67: 45931 | AH67: =100*((DataQ!U218/DataQ!U214)-1) -> 2.9158976 | AI67: =100*((DataQ!V218/DataQ!V214)-1) -> 2.4929291 | AJ67: =AH67-AI67 -> 0.42296858 | AK67: 0 | AM67: 45931 | AN67: =DataQ!W218/DataQ!W214*100 -> 102.03544 | AO67: =DataQ!X218/DataQ!X214*100 -> 98.574931 | AP67: =DataQ!Y218/DataQ!Y214*100 -> 103.0592 | AQ67: =DataQ!V218/DataQ!V214*100 -> 102.49293 | AS67: =DataQ!W214/DataQ!W214*100 -> 100 | AT67: =DataQ!X214/DataQ!X214*100 -> 100 | AU67: =DataQ!Y214/DataQ!Y214*100 -> 100 | AV67: =DataQ!V214/DataQ!V214*100 -> 100 | AX67: =HAVERQ!C110*AN67/$AQ67 -> 151.61581 | AY67: =HAVERQ!D110*AO67/$AQ67 -> 29.682911 | AZ67: =HAVERQ!E110*AP67/$AQ67 -> 41.113906 | BA67: =1000*AQ67/$AQ67 -> 1000 | BC67: =$AV67/100*(AN67-100)*HAVERQ!C110/1000+(AS67-100)*AX67/$BA67 -> 0.30998826 | BD67: =$AV67/100*(AO67-100)*HAVERQ!D110/1000+(AT67-100)*AY67/$BA67 -> -0.043981484 | BE67: =$AV67/100*(AP67-100)*HAVERQ!E110/1000+(AU67-100)*AZ67/$BA67 -> 0.1250847 | BF67: =BG67-BE67-BD67-BC67 -> 2.1018376 | BG67: =$AV67/100*(AQ67-100)*1000/1000+(AV67-100)*BA67/$BA67 -> 2.4929291 | BH67: =100*((DataQ!V218/DataQ!V214)-1) -> 2.4929291 | BI67: 2 | BK67: 43556 | BL67: =HAVERM!B358 -> 1.66 | BM67: =HAVERM!C358 -> 2 | BQ67: =BL67-BT67 -> 0.86787273 | BR67: =BM67-BU67 -> 1.0611364 | BT67: =HAVERM!D358 -> 0.79212727 | BU67: =HAVERM!E358 -> 0.93886364 | BW67: =BL67-BL43 -> 0.31 | BX67: =BM67-BM7 -> -1.69 | BY67: 0
BK68: 43586 | BL68: =HAVERM!B359 -> 1.65 | BM68: =HAVERM!C359 -> 1.99 | BQ68: =BL68-BT68 -> 0.88321304 | BR68: =BM68-BU68 -> 1.1189522 | BT68: =HAVERM!D359 -> 0.76678696 | BU68: =HAVERM!E359 -> 0.87104783 | BW68: =BL68-BL44 -> 0.16 | BX68: =BM68-BM8 -> -1.73 | BY68: 0
BK69: 43617 | BL69: =HAVERM!B360 -> 1.64 | BM69: =HAVERM!C360 -> 1.97 | BQ69: =BL69-BT69 -> 0.998995 | BR69: =BM69-BU69 -> 1.290385 | BT69: =HAVERM!D360 -> 0.641005 | BU69: =HAVERM!E360 -> 0.679615 | BW69: =BL69-BL45 -> 0.16 | BX69: =BM69-BM9 -> -1.72 | BY69: 0
BK70: 43647 | BL70: =HAVERM!B361 -> 1.61 | BM70: =HAVERM!C361 -> 1.93 | BQ70: =BL70-BT70 -> 1.074087 | BR70: =BM70-BU70 -> 1.3573087 | BT70: =HAVERM!D361 -> 0.53591304 | BU70: =HAVERM!E361 -> 0.5726913 | BW70: =BL70-BL46 -> 0.2 | BX70: =BM70-BM10 -> -1.85 | BY70: 0
BK71: 43678 | BL71: =HAVERM!B362 -> 1.59 | BM71: =HAVERM!C362 -> 1.89 | BO71: 100 | BQ71: =BL71-BT71 -> 1.1301773 | BR71: =BM71-BU71 -> 1.4921818 | BT71: =HAVERM!D362 -> 0.45982273 | BU71: =HAVERM!E362 -> 0.39781818 | BW71: =BL71-BL47 -> 0.16 | BX71: =BM71-BM11 -> -1.87 | BY71: 0
BK72: 43709 | BL72: =HAVERM!B363 -> 1.55 | BM72: =HAVERM!C363 -> 1.79 | BO72: 100 | BQ72: =BL72-BT72 -> 1.0178952 | BR72: =BM72-BU72 -> 1.3218286 | BT72: =HAVERM!D363 -> 0.53210476 | BU72: =HAVERM!E363 -> 0.46817143 | BW72: =BL72-BL48 -> 0.15 | BX72: =BM72-BM12 -> -1.82 | BY72: 0
BK73: 43739 | BL73: =HAVERM!B364 -> 1.47 | BM73: =HAVERM!C364 -> 1.71 | BO73: 100 | BQ73: =BL73-BT73 -> 0.9451087 | BR73: =BM73-BU73 -> 1.2177696 | BT73: =HAVERM!D364 -> 0.5248913 | BU73: =HAVERM!E364 -> 0.49223043 | BW73: =BL73-BL49 -> -0.08 | BX73: =BM73-BM13 -> -1.56 | BY73: 0
BK74: 43770 | BL74: =HAVERM!B365 -> 1.41 | BM74: =HAVERM!C365 -> 1.67 | BO74: 100 | BQ74: =BL74-BT74 -> 0.82919524 | BR74: =BM74-BU74 -> 1.0745143 | BT74: =HAVERM!D365 -> 0.58080476 | BU74: =HAVERM!E365 -> 0.59548571 | BW74: =BL74-BL50 -> -0.2 | BX74: =BM74-BM14 -> -1.54 | BY74: 0
BK75: 43800 | BL75: =HAVERM!B366 -> 1.42 | BM75: =HAVERM!C366 -> 1.67 | BO75: 100 | BQ75: =BL75-BT75 -> 0.81618182 | BR75: =BM75-BU75 -> 1.0191955 | BT75: =HAVERM!D366 -> 0.60381818 | BU75: =HAVERM!E366 -> 0.65080455 | BW75: =BL75-BL51 -> -0.15 | BX75: =BM75-BM15 -> -1.54 | BY75: 0
BK76: 43831 | BL76: =HAVERM!B367 -> 1.41 | BM76: =HAVERM!C367 -> 1.68 | BO76: 100 | BQ76: =BL76-BT76 -> 0.908 | BR76: =BM76-BU76 -> 1.1408261 | BT76: =HAVERM!D367 -> 0.502 | BU76: =HAVERM!E367 -> 0.53917391 | BW76: =BL76-BL52 -> -0.13 | BX76: =BM76-BM16 -> -1.41 | BY76: 0
BK77: 43862 | BL77: =HAVERM!B368 -> 1.4 | BM77: =HAVERM!C368 -> 1.67 | BO77: 100 | BQ77: =BL77-BT77 -> 0.89046 | BR77: =BM77-BU77 -> 1.17575 | BT77: =HAVERM!D368 -> 0.50954 | BU77: =HAVERM!E368 -> 0.49425 | BW77: =BL77-BL53 -> -0.09 | BX77: =BM77-BM17 -> -1.38 | BY77: 0
BK78: 43891 | BL78: =HAVERM!B369 -> 1.4 | BM78: =HAVERM!C369 -> 1.66 | BO78: 100 | BQ78: =BL78-BT78 -> 1.2043318 | BR78: =BM78-BU78 -> 1.3765318 | BT78: =HAVERM!D369 -> 0.19566818 | BU78: =HAVERM!E369 -> 0.28346818 | BW78: =BL78-BL54 -> -0.13 | BX78: =BM78-BM18 -> -1.32 | BY78: 0
BK79: 43922 | BL79: =HAVERM!B370 -> 1.38 | BM79: =HAVERM!C370 -> 1.67 | BO79: 100 | BQ79: =BL79-BT79 -> 1.2634182 | BR79: =BM79-BU79 -> 1.4713273 | BT79: =HAVERM!D370 -> 0.11658182 | BU79: =HAVERM!E370 -> 0.19867273 | BW79: =BL79-BL55 -> -0.34 | BX79: =BM79-BM19 -> -1.25 | BY79: 0
BK80: 43952 | BL80: =HAVERM!B371 -> 1.42 | BM80: =HAVERM!C371 -> 1.7 | BO80: 100 | BQ80: =BL80-BT80 -> 1.3964 | BR80: =BM80-BU80 -> 1.6153 | BT80: =HAVERM!D371 -> 0.0236 | BU80: =HAVERM!E371 -> 0.0847 | BW80: =BL80-BL56 -> -0.32 | BX80: =BM80-BM20 -> -1.16 | BY80: 0
BK81: 43983 | BL81: =HAVERM!B372 -> 1.41 | BM81: =HAVERM!C372 -> 1.69 | BO81: 100 | BQ81: =BL81-BT81 -> 1.4068773 | BR81: =BM81-BU81 -> 1.6384455 | BT81: =HAVERM!D372 -> 0.0031227273 | BU81: =HAVERM!E372 -> 0.051554545 | BW81: =BL81-BL57 -> -0.33 | BX81: =BM81-BM21 -> -1.13 | BY81: 0
BK82: 44013 | BL82: =HAVERM!B373 -> 1.45 | BM82: =HAVERM!C373 -> 1.7 | BO82: 100 | BQ82: =BL82-BT82 -> 1.4926739 | BR82: =BM82-BU82 -> 1.7278957 | BT82: =HAVERM!D373 -> -0.042673913 | BU82: =HAVERM!E373 -> -0.027895652 | BW82: =BL82-BL58 -> -0.3 | BX82: =BM82-BM22 -> -1.13 | BY82: 0
... BK87: 44166 | BL87: =HAVERM!B378 -> 1.86 | BM87: =HAVERM!C378 -> 2 | BO87: 100 | BQ87: =BL87-BT87 -> 1.888087 | BR87: =BM87-BU87 -> 1.9713739 | BT87: =HAVERM!D378 -> -0.028086957 | BU87: =HAVERM!E378 -> 0.028626087 | BW87: =BL87-BL63 -> 0.13 | BX87: =BM87-BM27 -> -0.75 | BY87: 0
BK88: 44197 | BL88: =HAVERM!B379 -> 1.75 | BM88: =HAVERM!C379 -> 1.92 | BQ88: =BL88-BT88 -> 1.8021952 | BR88: =BM88-BU88 -> 1.8915286 | BT88: =HAVERM!D379 -> -0.052195238 | BU88: =HAVERM!E379 -> 0.028471429 | BW88: =BL88-BL64 -> 0.03 | BX88: =BM88-BM28 -> -0.76 | BY88: 0
BK89: 44228 | BL89: =HAVERM!B380 -> 1.61 | BM89: =HAVERM!C380 -> 1.8 | BQ89: =BL89-BT89 -> 1.57728 | BR89: =BM89-BU89 -> 1.579405 | BT89: =HAVERM!D380 -> 0.03272 | BU89: =HAVERM!E380 -> 0.220595 | BW89: =BL89-BL65 -> -0.09 | BX89: =BM89-BM29 -> -0.93 | BY89: 0
BK90: 44256 | BL90: =HAVERM!B381 -> 1.56 | BM90: =HAVERM!C381 -> 1.74 | BQ90: =BL90-BT90 -> 1.4588913 | BR90: =BM90-BU90 -> 1.3311 | BT90: =HAVERM!D381 -> 0.1011087 | BU90: =HAVERM!E381 -> 0.4089 | BW90: =BL90-BL66 -> -0.14 | BX90: =BM90-BM30 -> -0.96 | BY90: 0
BK91: 44287 | BL91: =HAVERM!B382 -> 1.49 | BM91: =HAVERM!C382 -> 1.71 | BQ91: =BL91-BT91 -> 1.3774682 | BR91: =BM91-BU91 -> 1.2763364 | BT91: =HAVERM!D382 -> 0.11253182 | BU91: =HAVERM!E382 -> 0.43366364 | BW91: =BL91-BL67 -> -0.17 | BX91: =BM91-BM31 -> -1 | BY91: 0
BK92: 44317 | BL92: =HAVERM!B383 -> 1.47 | BM92: =HAVERM!C383 -> 1.68 | BQ92: =BL92-BT92 -> 1.3356 | BR92: =BM92-BU92 -> 1.2163 | BT92: =HAVERM!D383 -> 0.1344 | BU92: =HAVERM!E383 -> 0.4637 | BW92: =BL92-BL68 -> -0.18 | BX92: =BM92-BM32 -> -0.96 | BY92: 0
BK93: 44348 | BL93: =HAVERM!B384 -> 1.39 | BM93: =HAVERM!C384 -> 1.6 | BQ93: =BL93-BT93 -> 1.2148727 | BR93: =BM93-BU93 -> 1.1281045 | BT93: =HAVERM!D384 -> 0.17512727 | BU93: =HAVERM!E384 -> 0.47189545 | BW93: =BL93-BL69 -> -0.25 | BX93: =BM93-BM33 -> -0.94 | BY93: 0
BK94: 44378 | BL94: =HAVERM!B385 -> 1.29 | BM94: =HAVERM!C385 -> 1.45 | BQ94: =BL94-BT94 -> 1.0817273 | BR94: =BM94-BU94 -> 1.0199273 | BT94: =HAVERM!D385 -> 0.20827273 | BU94: =HAVERM!E385 -> 0.43007273 | BW94: =BL94-BL70 -> -0.32 | BX94: =BM94-BM34 -> -1.06 | BY94: 0
BK95: 44409 | BL95: =HAVERM!B386 -> 1.23 | BM95: =HAVERM!C386 -> 1.39 | BQ95: =BL95-BT95 -> 0.96960455 | BR95: =BM95-BU95 -> 0.95339545 | BT95: =HAVERM!D386 -> 0.26039545 | BU95: =HAVERM!E386 -> 0.43660455 | BW95: =BL95-BL71 -> -0.36 | BX95: =BM95-BM35 -> -1 | BY95: 0
BK96: 44440 | BL96: =HAVERM!B387 -> 1.2 | BM96: =HAVERM!C387 -> 1.28 | BQ96: =BL96-BT96 -> 0.84570455 | BR96: =BM96-BU96 -> 0.7078 | BT96: =HAVERM!D387 -> 0.35429545 | BU96: =HAVERM!E387 -> 0.5722 | BW96: =BL96-BL72 -> -0.35 | BX96: =BM96-BM36 -> -1.06 | BY96: 0
BK97: 44470 | BL97: =HAVERM!B388 -> 1.29 | BM97: =HAVERM!C388 -> 1.3 | BQ97: =BL97-BT97 -> 0.51142857 | BR97: =BM97-BU97 -> 0.39312857 | BT97: =HAVERM!D388 -> 0.77857143 | BU97: =HAVERM!E388 -> 0.90687143 | BW97: =BL97-BL73 -> -0.18 | BX97: =BM97-BM37 -> -0.97 | BY97: 0
BK98: 44501 | BL98: =HAVERM!B389 -> 1.53 | BM98: =HAVERM!C389 -> 1.52 | BQ98: =BL98-BT98 -> 0.63360909 | BR98: =BM98-BU98 -> 0.53602727 | BT98: =HAVERM!D389 -> 0.89639091 | BU98: =HAVERM!E389 -> 0.98397273 | BW98: =BL98-BL74 -> 0.12 | BX98: =BM98-BM38 -> -0.73 | BY98: 0
BK99: 44531 | BL99: =HAVERM!B390 -> 1.57 | BM99: =HAVERM!C390 -> 1.59 | BQ99: =BL99-BT99 -> 0.67037826 | BR99: =BM99-BU99 -> 0.65821739 | BT99: =HAVERM!D390 -> 0.89962174 | BU99: =HAVERM!E390 -> 0.93178261 | BW99: =BL99-BL75 -> 0.15 | BX99: =BM99-BM39 -> -0.67 | BY99: 0
... BK106: 44743 | BL106: =HAVERM!B397 -> 3.48 | BM106: =HAVERM!C397 -> 3.43 | BQ106: =BL106-BT106 -> 0.83590476 | BR106: =BM106-BU106 -> 1.0384238 | BT106: =HAVERM!D397 -> 2.6440952 | BU106: =HAVERM!E397 -> 2.3915762 | BW106: =BL106-BL82 -> 2.03 | BX106: =BM106-BM46 -> 1.46 | BY106: 0
BK107: 44774 | BL107: =HAVERM!B398 -> 3.6 | BM107: =HAVERM!C398 -> 3.61 | BN107: 100 | BQ107: =BL107-BT107 -> 0.40231304 | BR107: =BM107-BU107 -> 0.8439087 | BT107: =HAVERM!D398 -> 3.197687 | BU107: =HAVERM!E398 -> 2.7660913 | BW107: =BL107-BL83 -> 2 | BX107: =BM107-BM47 -> 1.65 | BY107: 0
BK108: 44805 | BL108: =HAVERM!B399 -> 4.17 | BM108: =HAVERM!C399 -> 3.97 | BN108: 100 | BQ108: =BL108-BT108 -> -0.29443636 | BR108: =BM108-BU108 -> -0.045904545 | BT108: =HAVERM!D399 -> 4.4644364 | BU108: =HAVERM!E399 -> 4.0159045 | BW108: =BL108-BL84 -> 2.42 | BX108: =BM108-BM48 -> 2.07 | BY108: 0
BK109: 44835 | BL109: =HAVERM!B400 -> 5.99 | BM109: =HAVERM!C400 -> 5.61 | BN109: 100 | BQ109: =BL109-BT109 -> 1.0282 | BR109: =BM109-BU109 -> 0.88082857 | BT109: =HAVERM!D400 -> 4.9618 | BU109: =HAVERM!E400 -> 4.7291714 | BW109: =BL109-BL85 -> 4.05 | BX109: =BM109-BM49 -> 3.57 | BY109: 0
BK110: 44866 | BL110: =HAVERM!B401 -> 5.98 | BM110: =HAVERM!C401 -> 5.5 | BN110: 100 | BQ110: =BL110-BT110 -> 1.6356273 | BR110: =BM110-BU110 -> 1.5627591 | BT110: =HAVERM!D401 -> 4.3443727 | BU110: =HAVERM!E401 -> 3.9372409 | BW110: =BL110-BL86 -> 4.06 | BX110: =BM110-BM50 -> 3.46 | BY110: 0
...

Sheet DataA
B1: =DataQ!D1 -> SEP002A.db | C1: =DataQ!E1 -> JAN011B.db | D1: =DataQ!F1 -> JAN024B.db | E1: =DataQ!G1 -> FEB006C.db | F1: =DataQ!H1 -> FEB019C.db | G1: =DataQ!I1 -> MAR011D.db | H1: =DataQ!J1 -> MAR020B.db | I1: =DataQ!K1 -> APR009C.db | ... AE1: =DataQ!AG1 -> SEP002A.db
B2: =DataQ!D2 -> UK | C2: =DataQ!E2 -> UK | D2: =DataQ!F2 -> UK | E2: =DataQ!G2 -> UK | F2: =DataQ!H2 -> UK | G2: =DataQ!I2 -> UK | H2: =DataQ!J2 -> UK | I2: =DataQ!K2 -> UK | ... AE2: =DataQ!AG2 -> UK
B3: =DataQ!D3 -> GDP | C3: =DataQ!E3 -> GDP | D3: =DataQ!F3 -> GDP | E3: =DataQ!G3 -> GDP | F3: =DataQ!H3 -> GDP | G3: =DataQ!I3 -> GDP | H3: =DataQ!J3 -> GDP | I3: =DataQ!K3 -> GDP | ... AE3: =DataQ!AG3 -> RSWAP5YR_RFR
B4: =DataQ!D4 -> GBR | C4: =DataQ!E4 -> GBR | D4: =DataQ!F4 -> GBR | E4: =DataQ!G4 -> GBR | F4: =DataQ!H4 -> GBR | G4: =DataQ!I4 -> GBR | H4: =DataQ!J4 -> GBR | I4: =DataQ!K4 -> GBR | ... AE4: =DataQ!AG4 -> GBR
B5: =DataQ!D5 -> L | C5: =DataQ!E5 -> L | D5: =DataQ!F5 -> L | E5: =DataQ!G5 -> L | F5: =DataQ!H5 -> L | G5: =DataQ!I5 -> L | H5: =DataQ!J5 -> L | I5: =DataQ!K5 -> L | ... AE5: =DataQ!AG5 -> L
B6: =DataQ!D6 -> 202402 | C6: =DataQ!E6 -> 202303 | D6: =DataQ!F6 -> 202303 | E6: =DataQ!G6 -> 202303 | F6: =DataQ!H6 -> 202304 | G6: =DataQ!I6 -> 202304 | H6: =DataQ!J6 -> 202304 | I6: =DataQ!K6 -> 202304 | ... AE6: =DataQ!AG6 -> 202402
A7: 1973 | B7: =SUMIF(DataQ!$B:$B,DataA!$A7,DataQ!D:D) -> 891381 | C7: =SUMIF(DataQ!$B:$B,DataA!$A7,DataQ!E:E) -> 891381 | D7: =SUMIF(DataQ!$B:$B,DataA!$A7,DataQ!F:F) -> 891381 | E7: =SUMIF(DataQ!$B:$B,DataA!$A7,DataQ!G:G) -> 891381 | F7: =SUMIF(DataQ!$B:$B,DataA!$A7,DataQ!H:H) -> 891381 | G7: =SUMIF(DataQ!$B:$B,DataA!$A7,DataQ!I:I) -> 891381 | H7: =SUMIF(DataQ!$B:$B,DataA!$A7,DataQ!J:J) -> 891381 | I7: =SUMIF(DataQ!$B:$B,DataA!$A7,DataQ!K:K) -> 891381 | J7: =SUMIF(DataQ!$B:$B,DataA!$A7,DataQ!L:L) -> 891381 | K7: =SUMIF(DataQ!$B:$B,DataA!$A7,DataQ!M:M) -> 891381 | L7: =SUMIF(DataQ!$B:$B,DataA!$A7,DataQ!N:N) -> 891381 | M7: =SUMIF(DataQ!$B:$B,DataA!$A7,DataQ!O:O) -> 891381 | N7: =SUMIF(DataQ!$B:$B,DataA!$A7,DataQ!P:P) -> 891381 | O7: =SUMIF(DataQ!$B:$B,DataA!$A7,DataQ!Q:Q) -> 891381 | P7: =SUMIF(DataQ!$B:$B,DataA!$A7,DataQ!R:R) -> 891381 | Q7: =SUMIF(DataQ!$B:$B,DataA!$A7,DataQ!S:S) -> 891381 | R7: =SUMIF(DataQ!$B:$B,DataA!$A7,DataQ!T:T) -> 891381 | S7: =AVERAGEIF(DataQ!$B:$B,DataA!$A7,DataQ!U:U) -> 15.940815 | T7: =AVERAGEIF(DataQ!$B:$B,DataA!$A7,DataQ!V:V) -> 12.428425 | U7: =AVERAGEIF(DataQ!$B:$B,DataA!$A7,DataQ!W:W) -> 0.001 | V7: =AVERAGEIF(DataQ!$B:$B,DataA!$A7,DataQ!X:X) -> 0.001 | W7: =AVERAGEIF(DataQ!$B:$B,DataA!$A7,DataQ!Y:Y) -> 0.001 | X7: =AVERAGEIF(DataQ!$B:$B,DataA!$A7,DataQ!Z:Z) -> 0.001 | Y7: =SUMIF(DataQ!$B:$B,DataA!$A7,DataQ!AA:AA) -> 461905 | Z7: =SUMIF(DataQ!$B:$B,DataA!$A7,DataQ!AB:AB) -> 178241 | AA7: =SUMIF(DataQ!$B:$B,DataA!$A7,DataQ!AC:AC) -> 204050 | AB7: =SUMIF(DataQ!$B:$B,DataA!$A7,DataQ!AD:AD) -> 126702 | AC7: =SUMIF(DataQ!$B:$B,DataA!$A7,DataQ!AE:AE) -> 117567 | AD7: =AVERAGEIF(DataQ!$B:$B,DataA!$A7,DataQ!AF:AF) -> 0.001 | AE7: =AVERAGEIF(DataQ!$B:$B,DataA!$A7,DataQ!AG:AG) -> 0.001
A8: =+A7+1 -> 1974 | B8: =SUMIF(DataQ!$B:$B,DataA!$A8,DataQ!D:D) -> 869155 | C8: =SUMIF(DataQ!$B:$B,DataA!$A8,DataQ!E:E) -> 869155 | D8: =SUMIF(DataQ!$B:$B,DataA!$A8,DataQ!F:F) -> 869155 | E8: =SUMIF(DataQ!$B:$B,DataA!$A8,DataQ!G:G) -> 869155 | F8: =SUMIF(DataQ!$B:$B,DataA!$A8,DataQ!H:H) -> 869155 | G8: =SUMIF(DataQ!$B:$B,DataA!$A8,DataQ!I:I) -> 869155 | H8: =SUMIF(DataQ!$B:$B,DataA!$A8,DataQ!J:J) -> 869155 | I8: =SUMIF(DataQ!$B:$B,DataA!$A8,DataQ!K:K) -> 869155 | J8: =SUMIF(DataQ!$B:$B,DataA!$A8,DataQ!L:L) -> 869155 | K8: =SUMIF(DataQ!$B:$B,DataA!$A8,DataQ!M:M) -> 869155 | L8: =SUMIF(DataQ!$B:$B,DataA!$A8,DataQ!N:N) -> 869155 | M8: =SUMIF(DataQ!$B:$B,DataA!$A8,DataQ!O:O) -> 869155 | N8: =SUMIF(DataQ!$B:$B,DataA!$A8,DataQ!P:P) -> 869155 | O8: =SUMIF(DataQ!$B:$B,DataA!$A8,DataQ!Q:Q) -> 869155 | P8: =SUMIF(DataQ!$B:$B,DataA!$A8,DataQ!R:R) -> 869155 | Q8: =SUMIF(DataQ!$B:$B,DataA!$A8,DataQ!S:S) -> 869155 | R8: =SUMIF(DataQ!$B:$B,DataA!$A8,DataQ!T:T) -> 869155 | S8: =AVERAGEIF(DataQ!$B:$B,DataA!$A8,DataQ!U:U) -> 19.300352 | T8: =AVERAGEIF(DataQ!$B:$B,DataA!$A8,DataQ!V:V) -> 14.383608 | U8: =AVERAGEIF(DataQ!$B:$B,DataA!$A8,DataQ!W:W) -> 0.001 | V8: =AVERAGEIF(DataQ!$B:$B,DataA!$A8,DataQ!X:X) -> 0.001 | W8: =AVERAGEIF(DataQ!$B:$B,DataA!$A8,DataQ!Y:Y) -> 0.001 | X8: =AVERAGEIF(DataQ!$B:$B,DataA!$A8,DataQ!Z:Z) -> 0.001 | Y8: =SUMIF(DataQ!$B:$B,DataA!$A8,DataQ!AA:AA) -> 456007 | Z8: =SUMIF(DataQ!$B:$B,DataA!$A8,DataQ!AB:AB) -> 164938 | AA8: =SUMIF(DataQ!$B:$B,DataA!$A8,DataQ!AC:AC) -> 207503 | AB8: =SUMIF(DataQ!$B:$B,DataA!$A8,DataQ!AD:AD) -> 135895 | AC8: =SUMIF(DataQ!$B:$B,DataA!$A8,DataQ!AE:AE) -> 118687 | AD8: =AVERAGEIF(DataQ!$B:$B,DataA!$A8,DataQ!AF:AF) -> 0.001 | AE8: =AVERAGEIF(DataQ!$B:$B,DataA!$A8,DataQ!AG:AG) -> 0.001
A9: =+A8+1 -> 1975 | B9: =SUMIF(DataQ!$B:$B,DataA!$A9,DataQ!D:D) -> 856049 | C9: =SUMIF(DataQ!$B:$B,DataA!$A9,DataQ!E:E) -> 856049 | D9: =SUMIF(DataQ!$B:$B,DataA!$A9,DataQ!F:F) -> 856049 | E9: =SUMIF(DataQ!$B:$B,DataA!$A9,DataQ!G:G) -> 856049 | F9: =SUMIF(DataQ!$B:$B,DataA!$A9,DataQ!H:H) -> 856049 | G9: =SUMIF(DataQ!$B:$B,DataA!$A9,DataQ!I:I) -> 856049 | H9: =SUMIF(DataQ!$B:$B,DataA!$A9,DataQ!J:J) -> 856049 | I9: =SUMIF(DataQ!$B:$B,DataA!$A9,DataQ!K:K) -> 856049 | J9: =SUMIF(DataQ!$B:$B,DataA!$A9,DataQ!L:L) -> 856049 | K9: =SUMIF(DataQ!$B:$B,DataA!$A9,DataQ!M:M) -> 856049 | L9: =SUMIF(DataQ!$B:$B,DataA!$A9,DataQ!N:N) -> 856049 | M9: =SUMIF(DataQ!$B:$B,DataA!$A9,DataQ!O:O) -> 856049 | N9: =SUMIF(DataQ!$B:$B,DataA!$A9,DataQ!P:P) -> 856049 | O9: =SUMIF(DataQ!$B:$B,DataA!$A9,DataQ!Q:Q) -> 856049 | P9: =SUMIF(DataQ!$B:$B,DataA!$A9,DataQ!R:R) -> 856049 | Q9: =SUMIF(DataQ!$B:$B,DataA!$A9,DataQ!S:S) -> 856049 | R9: =SUMIF(DataQ!$B:$B,DataA!$A9,DataQ!T:T) -> 856049 | S9: =AVERAGEIF(DataQ!$B:$B,DataA!$A9,DataQ!U:U) -> 25.941457 | T9: =AVERAGEIF(DataQ!$B:$B,DataA!$A9,DataQ!V:V) -> 17.648755 | U9: =AVERAGEIF(DataQ!$B:$B,DataA!$A9,DataQ!W:W) -> 0.001 | V9: =AVERAGEIF(DataQ!$B:$B,DataA!$A9,DataQ!X:X) -> 0.001 | W9: =AVERAGEIF(DataQ!$B:$B,DataA!$A9,DataQ!Y:Y) -> 0.001 | X9: =AVERAGEIF(DataQ!$B:$B,DataA!$A9,DataQ!Z:Z) -> 0.001 | Y9: =SUMIF(DataQ!$B:$B,DataA!$A9,DataQ!AA:AA) -> 455397 | Z9: =SUMIF(DataQ!$B:$B,DataA!$A9,DataQ!AB:AB) -> 155077 | AA9: =SUMIF(DataQ!$B:$B,DataA!$A9,DataQ!AC:AC) -> 219574 | AB9: =SUMIF(DataQ!$B:$B,DataA!$A9,DataQ!AD:AD) -> 131880 | AC9: =SUMIF(DataQ!$B:$B,DataA!$A9,DataQ!AE:AE) -> 110825 | AD9: =AVERAGEIF(DataQ!$B:$B,DataA!$A9,DataQ!AF:AF) -> 0.001 | AE9: =AVERAGEIF(DataQ!$B:$B,DataA!$A9,DataQ!AG:AG) -> 0.001
A10: =+A9+1 -> 1976 | B10: =SUMIF(DataQ!$B:$B,DataA!$A10,DataQ!D:D) -> 881878 | C10: =SUMIF(DataQ!$B:$B,DataA!$A10,DataQ!E:E) -> 881878 | D10: =SUMIF(DataQ!$B:$B,DataA!$A10,DataQ!F:F) -> 881878 | E10: =SUMIF(DataQ!$B:$B,DataA!$A10,DataQ!G:G) -> 881878 | F10: =SUMIF(DataQ!$B:$B,DataA!$A10,DataQ!H:H) -> 881878 | G10: =SUMIF(DataQ!$B:$B,DataA!$A10,DataQ!I:I) -> 881878 | H10: =SUMIF(DataQ!$B:$B,DataA!$A10,DataQ!J:J) -> 881878 | I10: =SUMIF(DataQ!$B:$B,DataA!$A10,DataQ!K:K) -> 881878 | J10: =SUMIF(DataQ!$B:$B,DataA!$A10,DataQ!L:L) -> 881878 | K10: =SUMIF(DataQ!$B:$B,DataA!$A10,DataQ!M:M) -> 881878 | L10: =SUMIF(DataQ!$B:$B,DataA!$A10,DataQ!N:N) -> 881878 | M10: =SUMIF(DataQ!$B:$B,DataA!$A10,DataQ!O:O) -> 881878 | N10: =SUMIF(DataQ!$B:$B,DataA!$A10,DataQ!P:P) -> 881878 | O10: =SUMIF(DataQ!$B:$B,DataA!$A10,DataQ!Q:Q) -> 881878 | P10: =SUMIF(DataQ!$B:$B,DataA!$A10,DataQ!R:R) -> 881878 | Q10: =SUMIF(DataQ!$B:$B,DataA!$A10,DataQ!S:S) -> 881878 | R10: =SUMIF(DataQ!$B:$B,DataA!$A10,DataQ!T:T) -> 881878 | S10: =AVERAGEIF(DataQ!$B:$B,DataA!$A10,DataQ!U:U) -> 31.409385 | T10: =AVERAGEIF(DataQ!$B:$B,DataA!$A10,DataQ!V:V) -> 20.412077 | U10: =AVERAGEIF(DataQ!$B:$B,DataA!$A10,DataQ!W:W) -> 0.001 | V10: =AVERAGEIF(DataQ!$B:$B,DataA!$A10,DataQ!X:X) -> 0.001 | W10: =AVERAGEIF(DataQ!$B:$B,DataA!$A10,DataQ!Y:Y) -> 0.001 | X10: =AVERAGEIF(DataQ!$B:$B,DataA!$A10,DataQ!Z:Z) -> 0.001 | Y10: =SUMIF(DataQ!$B:$B,DataA!$A10,DataQ!AA:AA) -> 457926 | Z10: =SUMIF(DataQ!$B:$B,DataA!$A10,DataQ!AB:AB) -> 156130 | AA10: =SUMIF(DataQ!$B:$B,DataA!$A10,DataQ!AC:AC) -> 222968 | AB10: =SUMIF(DataQ!$B:$B,DataA!$A10,DataQ!AD:AD) -> 143534 | AC10: =SUMIF(DataQ!$B:$B,DataA!$A10,DataQ!AE:AE) -> 116253 | AD10: =AVERAGEIF(DataQ!$B:$B,DataA!$A10,DataQ!AF:AF) -> 0.001 | AE10: =AVERAGEIF(DataQ!$B:$B,DataA!$A10,DataQ!AG:AG) -> 0.001
A11: =+A10+1 -> 1977 | B11: =SUMIF(DataQ!$B:$B,DataA!$A11,DataQ!D:D) -> 903587 | C11: =SUMIF(DataQ!$B:$B,DataA!$A11,DataQ!E:E) -> 903587 | D11: =SUMIF(DataQ!$B:$B,DataA!$A11,DataQ!F:F) -> 903587 | E11: =SUMIF(DataQ!$B:$B,DataA!$A11,DataQ!G:G) -> 903587 | F11: =SUMIF(DataQ!$B:$B,DataA!$A11,DataQ!H:H) -> 903587 | G11: =SUMIF(DataQ!$B:$B,DataA!$A11,DataQ!I:I) -> 903587 | H11: =SUMIF(DataQ!$B:$B,DataA!$A11,DataQ!J:J) -> 903587 | I11: =SUMIF(DataQ!$B:$B,DataA!$A11,DataQ!K:K) -> 903587 | J11: =SUMIF(DataQ!$B:$B,DataA!$A11,DataQ!L:L) -> 903587 | K11: =SUMIF(DataQ!$B:$B,DataA!$A11,DataQ!M:M) -> 903587 | L11: =SUMIF(DataQ!$B:$B,DataA!$A11,DataQ!N:N) -> 903587 | M11: =SUMIF(DataQ!$B:$B,DataA!$A11,DataQ!O:O) -> 903587 | N11: =SUMIF(DataQ!$B:$B,DataA!$A11,DataQ!P:P) -> 903587 | O11: =SUMIF(DataQ!$B:$B,DataA!$A11,DataQ!Q:Q) -> 903587 | P11: =SUMIF(DataQ!$B:$B,DataA!$A11,DataQ!R:R) -> 903587 | Q11: =SUMIF(DataQ!$B:$B,DataA!$A11,DataQ!S:S) -> 903587 | R11: =SUMIF(DataQ!$B:$B,DataA!$A11,DataQ!T:T) -> 903587 | S11: =AVERAGEIF(DataQ!$B:$B,DataA!$A11,DataQ!U:U) -> 35.091777 | T11: =AVERAGEIF(DataQ!$B:$B,DataA!$A11,DataQ!V:V) -> 23.462157 | U11: =AVERAGEIF(DataQ!$B:$B,DataA!$A11,DataQ!W:W) -> 0.001 | V11: =AVERAGEIF(DataQ!$B:$B,DataA!$A11,DataQ!X:X) -> 0.001 | W11: =AVERAGEIF(DataQ!$B:$B,DataA!$A11,DataQ!Y:Y) -> 0.001 | X11: =AVERAGEIF(DataQ!$B:$B,DataA!$A11,DataQ!Z:Z) -> 0.001 | Y11: =SUMIF(DataQ!$B:$B,DataA!$A11,DataQ!AA:AA) -> 456906 | Z11: =SUMIF(DataQ!$B:$B,DataA!$A11,DataQ!AB:AB) -> 158549 | AA11: =SUMIF(DataQ!$B:$B,DataA!$A11,DataQ!AC:AC) -> 220135 | AB11: =SUMIF(DataQ!$B:$B,DataA!$A11,DataQ!AD:AD) -> 153003 | AC11: =SUMIF(DataQ!$B:$B,DataA!$A11,DataQ!AE:AE) -> 118265 | AD11: =AVERAGEIF(DataQ!$B:$B,DataA!$A11,DataQ!AF:AF) -> 0.001 | AE11: =AVERAGEIF(DataQ!$B:$B,DataA!$A11,DataQ!AG:AG) -> 0.001
A12: =+A11+1 -> 1978 | B12: =SUMIF(DataQ!$B:$B,DataA!$A12,DataQ!D:D) -> 941461 | C12: =SUMIF(DataQ!$B:$B,DataA!$A12,DataQ!E:E) -> 941461 | D12: =SUMIF(DataQ!$B:$B,DataA!$A12,DataQ!F:F) -> 941461 | E12: =SUMIF(DataQ!$B:$B,DataA!$A12,DataQ!G:G) -> 941461 | F12: =SUMIF(DataQ!$B:$B,DataA!$A12,DataQ!H:H) -> 941461 | G12: =SUMIF(DataQ!$B:$B,DataA!$A12,DataQ!I:I) -> 941461 | H12: =SUMIF(DataQ!$B:$B,DataA!$A12,DataQ!J:J) -> 941461 | I12: =SUMIF(DataQ!$B:$B,DataA!$A12,DataQ!K:K) -> 941461 | J12: =SUMIF(DataQ!$B:$B,DataA!$A12,DataQ!L:L) -> 941461 | K12: =SUMIF(DataQ!$B:$B,DataA!$A12,DataQ!M:M) -> 941461 | L12: =SUMIF(DataQ!$B:$B,DataA!$A12,DataQ!N:N) -> 941461 | M12: =SUMIF(DataQ!$B:$B,DataA!$A12,DataQ!O:O) -> 941461 | N12: =SUMIF(DataQ!$B:$B,DataA!$A12,DataQ!P:P) -> 941461 | O12: =SUMIF(DataQ!$B:$B,DataA!$A12,DataQ!Q:Q) -> 941461 | P12: =SUMIF(DataQ!$B:$B,DataA!$A12,DataQ!R:R) -> 941461 | Q12: =SUMIF(DataQ!$B:$B,DataA!$A12,DataQ!S:S) -> 941461 | R12: =SUMIF(DataQ!$B:$B,DataA!$A12,DataQ!T:T) -> 941461 | S12: =AVERAGEIF(DataQ!$B:$B,DataA!$A12,DataQ!U:U) -> 40.728302 | T12: =AVERAGEIF(DataQ!$B:$B,DataA!$A12,DataQ!V:V) -> 25.215303 | U12: =AVERAGEIF(DataQ!$B:$B,DataA!$A12,DataQ!W:W) -> 0.001 | V12: =AVERAGEIF(DataQ!$B:$B,DataA!$A12,DataQ!X:X) -> 0.001 | W12: =AVERAGEIF(DataQ!$B:$B,DataA!$A12,DataQ!Y:Y) -> 0.001 | X12: =AVERAGEIF(DataQ!$B:$B,DataA!$A12,DataQ!Z:Z) -> 0.001 | Y12: =SUMIF(DataQ!$B:$B,DataA!$A12,DataQ!AA:AA) -> 481558 | Z12: =SUMIF(DataQ!$B:$B,DataA!$A12,DataQ!AB:AB) -> 170231 | AA12: =SUMIF(DataQ!$B:$B,DataA!$A12,DataQ!AC:AC) -> 223839 | AB12: =SUMIF(DataQ!$B:$B,DataA!$A12,DataQ!AD:AD) -> 155528 | AC12: =SUMIF(DataQ!$B:$B,DataA!$A12,DataQ!AE:AE) -> 122400 | AD12: =AVERAGEIF(DataQ!$B:$B,DataA!$A12,DataQ!AF:AF) -> 0.001 | AE12: =AVERAGEIF(DataQ!$B:$B,DataA!$A12,DataQ!AG:AG) -> 0.001
A13: =+A12+1 -> 1979 | B13: =SUMIF(DataQ!$B:$B,DataA!$A13,DataQ!D:D) -> 976566 | C13: =SUMIF(DataQ!$B:$B,DataA!$A13,DataQ!E:E) -> 976566 | D13: =SUMIF(DataQ!$B:$B,DataA!$A13,DataQ!F:F) -> 976566 | E13: =SUMIF(DataQ!$B:$B,DataA!$A13,DataQ!G:G) -> 976566 | F13: =SUMIF(DataQ!$B:$B,DataA!$A13,DataQ!H:H) -> 976566 | G13: =SUMIF(DataQ!$B:$B,DataA!$A13,DataQ!I:I) -> 976566 | H13: =SUMIF(DataQ!$B:$B,DataA!$A13,DataQ!J:J) -> 976566 | I13: =SUMIF(DataQ!$B:$B,DataA!$A13,DataQ!K:K) -> 976566 | J13: =SUMIF(DataQ!$B:$B,DataA!$A13,DataQ!L:L) -> 976566 | K13: =SUMIF(DataQ!$B:$B,DataA!$A13,DataQ!M:M) -> 976566 | L13: =SUMIF(DataQ!$B:$B,DataA!$A13,DataQ!N:N) -> 976566 | M13: =SUMIF(DataQ!$B:$B,DataA!$A13,DataQ!O:O) -> 976566 | N13: =SUMIF(DataQ!$B:$B,DataA!$A13,DataQ!P:P) -> 976566 | O13: =SUMIF(DataQ!$B:$B,DataA!$A13,DataQ!Q:Q) -> 976566 | P13: =SUMIF(DataQ!$B:$B,DataA!$A13,DataQ!R:R) -> 976566 | Q13: =SUMIF(DataQ!$B:$B,DataA!$A13,DataQ!S:S) -> 976566 | R13: =SUMIF(DataQ!$B:$B,DataA!$A13,DataQ!T:T) -> 976566 | S13: =AVERAGEIF(DataQ!$B:$B,DataA!$A13,DataQ!U:U) -> 48.39366 | T13: =AVERAGEIF(DataQ!$B:$B,DataA!$A13,DataQ!V:V) -> 28.082898 | U13: =AVERAGEIF(DataQ!$B:$B,DataA!$A13,DataQ!W:W) -> 0.001 | V13: =AVERAGEIF(DataQ!$B:$B,DataA!$A13,DataQ!X:X) -> 0.001 | W13: =AVERAGEIF(DataQ!$B:$B,DataA!$A13,DataQ!Y:Y) -> 0.001 | X13: =AVERAGEIF(DataQ!$B:$B,DataA!$A13,DataQ!Z:Z) -> 0.001 | Y13: =SUMIF(DataQ!$B:$B,DataA!$A13,DataQ!AA:AA) -> 504380 | Z13: =SUMIF(DataQ!$B:$B,DataA!$A13,DataQ!AB:AB) -> 184880 | AA13: =SUMIF(DataQ!$B:$B,DataA!$A13,DataQ!AC:AC) -> 227267 | AB13: =SUMIF(DataQ!$B:$B,DataA!$A13,DataQ!AD:AD) -> 161066 | AC13: =SUMIF(DataQ!$B:$B,DataA!$A13,DataQ!AE:AE) -> 133788 | AD13: =AVERAGEIF(DataQ!$B:$B,DataA!$A13,DataQ!AF:AF) -> 0.001 | AE13: =AVERAGEIF(DataQ!$B:$B,DataA!$A13,DataQ!AG:AG) -> 0.001
A14: =+A13+1 -> 1980 | B14: =SUMIF(DataQ!$B:$B,DataA!$A14,DataQ!D:D) -> 956533 | C14: =SUMIF(DataQ!$B:$B,DataA!$A14,DataQ!E:E) -> 956533 | D14: =SUMIF(DataQ!$B:$B,DataA!$A14,DataQ!F:F) -> 956533 | E14: =SUMIF(DataQ!$B:$B,DataA!$A14,DataQ!G:G) -> 956533 | F14: =SUMIF(DataQ!$B:$B,DataA!$A14,DataQ!H:H) -> 956533 | G14: =SUMIF(DataQ!$B:$B,DataA!$A14,DataQ!I:I) -> 956533 | H14: =SUMIF(DataQ!$B:$B,DataA!$A14,DataQ!J:J) -> 956533 | I14: =SUMIF(DataQ!$B:$B,DataA!$A14,DataQ!K:K) -> 956533 | J14: =SUMIF(DataQ!$B:$B,DataA!$A14,DataQ!L:L) -> 956533 | K14: =SUMIF(DataQ!$B:$B,DataA!$A14,DataQ!M:M) -> 956533 | L14: =SUMIF(DataQ!$B:$B,DataA!$A14,DataQ!N:N) -> 956533 | M14: =SUMIF(DataQ!$B:$B,DataA!$A14,DataQ!O:O) -> 956533 | N14: =SUMIF(DataQ!$B:$B,DataA!$A14,DataQ!P:P) -> 956533 | O14: =SUMIF(DataQ!$B:$B,DataA!$A14,DataQ!Q:Q) -> 956533 | P14: =SUMIF(DataQ!$B:$B,DataA!$A14,DataQ!R:R) -> 956533 | Q14: =SUMIF(DataQ!$B:$B,DataA!$A14,DataQ!S:S) -> 956533 | R14: =SUMIF(DataQ!$B:$B,DataA!$A14,DataQ!T:T) -> 956533 | S14: =AVERAGEIF(DataQ!$B:$B,DataA!$A14,DataQ!U:U) -> 61.12267 | T14: =AVERAGEIF(DataQ!$B:$B,DataA!$A14,DataQ!V:V) -> 32.338673 | U14: =AVERAGEIF(DataQ!$B:$B,DataA!$A14,DataQ!W:W) -> 0.001 | V14: =AVERAGEIF(DataQ!$B:$B,DataA!$A14,DataQ!X:X) -> 0.001 | W14: =AVERAGEIF(DataQ!$B:$B,DataA!$A14,DataQ!Y:Y) -> 0.001 | X14: =AVERAGEIF(DataQ!$B:$B,DataA!$A14,DataQ!Z:Z) -> 0.001 | Y14: =SUMIF(DataQ!$B:$B,DataA!$A14,DataQ!AA:AA) -> 504992 | Z14: =SUMIF(DataQ!$B:$B,DataA!$A14,DataQ!AB:AB) -> 172984 | AA14: =SUMIF(DataQ!$B:$B,DataA!$A14,DataQ!AC:AC) -> 229881 | AB14: =SUMIF(DataQ!$B:$B,DataA!$A14,DataQ!AD:AD) -> 160235 | AC14: =SUMIF(DataQ!$B:$B,DataA!$A14,DataQ!AE:AE) -> 129029 | AD14: =AVERAGEIF(DataQ!$B:$B,DataA!$A14,DataQ!AF:AF) -> 0.001 | AE14: =AVERAGEIF(DataQ!$B:$B,DataA!$A14,DataQ!AG:AG) -> 0.001
A15: =+A14+1 -> 1981 | B15: =SUMIF(DataQ!$B:$B,DataA!$A15,DataQ!D:D) -> 949961 | C15: =SUMIF(DataQ!$B:$B,DataA!$A15,DataQ!E:E) -> 949961 | D15: =SUMIF(DataQ!$B:$B,DataA!$A15,DataQ!F:F) -> 949961 | E15: =SUMIF(DataQ!$B:$B,DataA!$A15,DataQ!G:G) -> 949961 | F15: =SUMIF(DataQ!$B:$B,DataA!$A15,DataQ!H:H) -> 949961 | G15: =SUMIF(DataQ!$B:$B,DataA!$A15,DataQ!I:I) -> 949961 | H15: =SUMIF(DataQ!$B:$B,DataA!$A15,DataQ!J:J) -> 949961 | I15: =SUMIF(DataQ!$B:$B,DataA!$A15,DataQ!K:K) -> 949961 | J15: =SUMIF(DataQ!$B:$B,DataA!$A15,DataQ!L:L) -> 949961 | K15: =SUMIF(DataQ!$B:$B,DataA!$A15,DataQ!M:M) -> 949961 | L15: =SUMIF(DataQ!$B:$B,DataA!$A15,DataQ!N:N) -> 949961 | M15: =SUMIF(DataQ!$B:$B,DataA!$A15,DataQ!O:O) -> 949961 | N15: =SUMIF(DataQ!$B:$B,DataA!$A15,DataQ!P:P) -> 949961 | O15: =SUMIF(DataQ!$B:$B,DataA!$A15,DataQ!Q:Q) -> 949961 | P15: =SUMIF(DataQ!$B:$B,DataA!$A15,DataQ!R:R) -> 949961 | Q15: =SUMIF(DataQ!$B:$B,DataA!$A15,DataQ!S:S) -> 949961 | R15: =SUMIF(DataQ!$B:$B,DataA!$A15,DataQ!T:T) -> 949961 | S15: =AVERAGEIF(DataQ!$B:$B,DataA!$A15,DataQ!U:U) -> 71.618053 | T15: =AVERAGEIF(DataQ!$B:$B,DataA!$A15,DataQ!V:V) -> 36.157795 | U15: =AVERAGEIF(DataQ!$B:$B,DataA!$A15,DataQ!W:W) -> 0.001 | V15: =AVERAGEIF(DataQ!$B:$B,DataA!$A15,DataQ!X:X) -> 0.001 | W15: =AVERAGEIF(DataQ!$B:$B,DataA!$A15,DataQ!Y:Y) -> 0.001 | X15: =AVERAGEIF(DataQ!$B:$B,DataA!$A15,DataQ!Z:Z) -> 0.001 | Y15: =SUMIF(DataQ!$B:$B,DataA!$A15,DataQ!AA:AA) -> 506426 | Z15: =SUMIF(DataQ!$B:$B,DataA!$A15,DataQ!AB:AB) -> 161511 | AA15: =SUMIF(DataQ!$B:$B,DataA!$A15,DataQ!AC:AC) -> 229663 | AB15: =SUMIF(DataQ!$B:$B,DataA!$A15,DataQ!AD:AD) -> 159266 | AC15: =SUMIF(DataQ!$B:$B,DataA!$A15,DataQ!AE:AE) -> 125351 | AD15: =AVERAGEIF(DataQ!$B:$B,DataA!$A15,DataQ!AF:AF) -> 0.001 | AE15: =AVERAGEIF(DataQ!$B:$B,DataA!$A15,DataQ!AG:AG) -> 0.001
A16: =+A15+1 -> 1982 | B16: =SUMIF(DataQ!$B:$B,DataA!$A16,DataQ!D:D) -> 968629 | C16: =SUMIF(DataQ!$B:$B,DataA!$A16,DataQ!E:E) -> 968629 | D16: =SUMIF(DataQ!$B:$B,DataA!$A16,DataQ!F:F) -> 968629 | E16: =SUMIF(DataQ!$B:$B,DataA!$A16,DataQ!G:G) -> 968629 | F16: =SUMIF(DataQ!$B:$B,DataA!$A16,DataQ!H:H) -> 968629 | G16: =SUMIF(DataQ!$B:$B,DataA!$A16,DataQ!I:I) -> 968629 | H16: =SUMIF(DataQ!$B:$B,DataA!$A16,DataQ!J:J) -> 968629 | I16: =SUMIF(DataQ!$B:$B,DataA!$A16,DataQ!K:K) -> 968629 | J16: =SUMIF(DataQ!$B:$B,DataA!$A16,DataQ!L:L) -> 968629 | K16: =SUMIF(DataQ!$B:$B,DataA!$A16,DataQ!M:M) -> 968629 | L16: =SUMIF(DataQ!$B:$B,DataA!$A16,DataQ!N:N) -> 968629 | M16: =SUMIF(DataQ!$B:$B,DataA!$A16,DataQ!O:O) -> 968629 | N16: =SUMIF(DataQ!$B:$B,DataA!$A16,DataQ!P:P) -> 968629 | O16: =SUMIF(DataQ!$B:$B,DataA!$A16,DataQ!Q:Q) -> 968629 | P16: =SUMIF(DataQ!$B:$B,DataA!$A16,DataQ!R:R) -> 968629 | Q16: =SUMIF(DataQ!$B:$B,DataA!$A16,DataQ!S:S) -> 968629 | R16: =SUMIF(DataQ!$B:$B,DataA!$A16,DataQ!T:T) -> 968629 | S16: =AVERAGEIF(DataQ!$B:$B,DataA!$A16,DataQ!U:U) -> 80.275882 | T16: =AVERAGEIF(DataQ!$B:$B,DataA!$A16,DataQ!V:V) -> 39.09056 | U16: =AVERAGEIF(DataQ!$B:$B,DataA!$A16,DataQ!W:W) -> 0.001 | V16: =AVERAGEIF(DataQ!$B:$B,DataA!$A16,DataQ!X:X) -> 0.001 | W16: =AVERAGEIF(DataQ!$B:$B,DataA!$A16,DataQ!Y:Y) -> 0.001 | X16: =AVERAGEIF(DataQ!$B:$B,DataA!$A16,DataQ!Z:Z) -> 0.001 | Y16: =SUMIF(DataQ!$B:$B,DataA!$A16,DataQ!AA:AA) -> 512285 | Z16: =SUMIF(DataQ!$B:$B,DataA!$A16,DataQ!AB:AB) -> 169791 | AA16: =SUMIF(DataQ!$B:$B,DataA!$A16,DataQ!AC:AC) -> 231086 | AB16: =SUMIF(DataQ!$B:$B,DataA!$A16,DataQ!AD:AD) -> 160647 | AC16: =SUMIF(DataQ!$B:$B,DataA!$A16,DataQ!AE:AE) -> 131032 | AD16: =AVERAGEIF(DataQ!$B:$B,DataA!$A16,DataQ!AF:AF) -> 0.001 | AE16: =AVERAGEIF(DataQ!$B:$B,DataA!$A16,DataQ!AG:AG) -> 0.001
A17: =+A16+1 -> 1983 | B17: =SUMIF(DataQ!$B:$B,DataA!$A17,DataQ!D:D) -> 1008981 | C17: =SUMIF(DataQ!$B:$B,DataA!$A17,DataQ!E:E) -> 1008981 | D17: =SUMIF(DataQ!$B:$B,DataA!$A17,DataQ!F:F) -> 1008981 | E17: =SUMIF(DataQ!$B:$B,DataA!$A17,DataQ!G:G) -> 1008981 | F17: =SUMIF(DataQ!$B:$B,DataA!$A17,DataQ!H:H) -> 1008981 | G17: =SUMIF(DataQ!$B:$B,DataA!$A17,DataQ!I:I) -> 1008981 | H17: =SUMIF(DataQ!$B:$B,DataA!$A17,DataQ!J:J) -> 1008981 | I17: =SUMIF(DataQ!$B:$B,DataA!$A17,DataQ!K:K) -> 1008981 | J17: =SUMIF(DataQ!$B:$B,DataA!$A17,DataQ!L:L) -> 1008981 | K17: =SUMIF(DataQ!$B:$B,DataA!$A17,DataQ!M:M) -> 1008981 | L17: =SUMIF(DataQ!$B:$B,DataA!$A17,DataQ!N:N) -> 1008981 | M17: =SUMIF(DataQ!$B:$B,DataA!$A17,DataQ!O:O) -> 1008981 | N17: =SUMIF(DataQ!$B:$B,DataA!$A17,DataQ!P:P) -> 1008981 | O17: =SUMIF(DataQ!$B:$B,DataA!$A17,DataQ!Q:Q) -> 1008981 | P17: =SUMIF(DataQ!$B:$B,DataA!$A17,DataQ!R:R) -> 1008981 | Q17: =SUMIF(DataQ!$B:$B,DataA!$A17,DataQ!S:S) -> 1008981 | R17: =SUMIF(DataQ!$B:$B,DataA!$A17,DataQ!T:T) -> 1008981 | S17: =AVERAGEIF(DataQ!$B:$B,DataA!$A17,DataQ!U:U) -> 88.73282 | T17: =AVERAGEIF(DataQ!$B:$B,DataA!$A17,DataQ!V:V) -> 41.019672 | U17: =AVERAGEIF(DataQ!$B:$B,DataA!$A17,DataQ!W:W) -> 0.001 | V17: =AVERAGEIF(DataQ!$B:$B,DataA!$A17,DataQ!X:X) -> 0.001 | W17: =AVERAGEIF(DataQ!$B:$B,DataA!$A17,DataQ!Y:Y) -> 0.001 | X17: =AVERAGEIF(DataQ!$B:$B,DataA!$A17,DataQ!Z:Z) -> 0.001 | Y17: =SUMIF(DataQ!$B:$B,DataA!$A17,DataQ!AA:AA) -> 534478 | Z17: =SUMIF(DataQ!$B:$B,DataA!$A17,DataQ!AB:AB) -> 182084 | AA17: =SUMIF(DataQ!$B:$B,DataA!$A17,DataQ!AC:AC) -> 234700 | AB17: =SUMIF(DataQ!$B:$B,DataA!$A17,DataQ!AD:AD) -> 163491 | AC17: =SUMIF(DataQ!$B:$B,DataA!$A17,DataQ!AE:AE) -> 139113 | AD17: =AVERAGEIF(DataQ!$B:$B,DataA!$A17,DataQ!AF:AF) -> 0.001 | AE17: =AVERAGEIF(DataQ!$B:$B,DataA!$A17,DataQ!AG:AG) -> 0.001
A18: =+A17+1 -> 1984 | B18: =SUMIF(DataQ!$B:$B,DataA!$A18,DataQ!D:D) -> 1031385 | C18: =SUMIF(DataQ!$B:$B,DataA!$A18,DataQ!E:E) -> 1031385 | D18: =SUMIF(DataQ!$B:$B,DataA!$A18,DataQ!F:F) -> 1031385 | E18: =SUMIF(DataQ!$B:$B,DataA!$A18,DataQ!G:G) -> 1031385 | F18: =SUMIF(DataQ!$B:$B,DataA!$A18,DataQ!H:H) -> 1031385 | G18: =SUMIF(DataQ!$B:$B,DataA!$A18,DataQ!I:I) -> 1031385 | H18: =SUMIF(DataQ!$B:$B,DataA!$A18,DataQ!J:J) -> 1031385 | I18: =SUMIF(DataQ!$B:$B,DataA!$A18,DataQ!K:K) -> 1031385 | J18: =SUMIF(DataQ!$B:$B,DataA!$A18,DataQ!L:L) -> 1031385 | K18: =SUMIF(DataQ!$B:$B,DataA!$A18,DataQ!M:M) -> 1031385 | L18: =SUMIF(DataQ!$B:$B,DataA!$A18,DataQ!N:N) -> 1031385 | M18: =SUMIF(DataQ!$B:$B,DataA!$A18,DataQ!O:O) -> 1031385 | N18: =SUMIF(DataQ!$B:$B,DataA!$A18,DataQ!P:P) -> 1031385 | O18: =SUMIF(DataQ!$B:$B,DataA!$A18,DataQ!Q:Q) -> 1031385 | P18: =SUMIF(DataQ!$B:$B,DataA!$A18,DataQ!R:R) -> 1031385 | Q18: =SUMIF(DataQ!$B:$B,DataA!$A18,DataQ!S:S) -> 1031385 | R18: =SUMIF(DataQ!$B:$B,DataA!$A18,DataQ!T:T) -> 1031385 | S18: =AVERAGEIF(DataQ!$B:$B,DataA!$A18,DataQ!U:U) -> 95.596452 | T18: =AVERAGEIF(DataQ!$B:$B,DataA!$A18,DataQ!V:V) -> 42.766303 | U18: =AVERAGEIF(DataQ!$B:$B,DataA!$A18,DataQ!W:W) -> 0.001 | V18: =AVERAGEIF(DataQ!$B:$B,DataA!$A18,DataQ!X:X) -> 0.001 | W18: =AVERAGEIF(DataQ!$B:$B,DataA!$A18,DataQ!Y:Y) -> 0.001 | X18: =AVERAGEIF(DataQ!$B:$B,DataA!$A18,DataQ!Z:Z) -> 0.001 | Y18: =SUMIF(DataQ!$B:$B,DataA!$A18,DataQ!AA:AA) -> 547479 | Z18: =SUMIF(DataQ!$B:$B,DataA!$A18,DataQ!AB:AB) -> 193798 | AA18: =SUMIF(DataQ!$B:$B,DataA!$A18,DataQ!AC:AC) -> 237498 | AB18: =SUMIF(DataQ!$B:$B,DataA!$A18,DataQ!AD:AD) -> 174015 | AC18: =SUMIF(DataQ!$B:$B,DataA!$A18,DataQ!AE:AE) -> 152269 | AD18: =AVERAGEIF(DataQ!$B:$B,DataA!$A18,DataQ!AF:AF) -> 0.001 | AE18: =AVERAGEIF(DataQ!$B:$B,DataA!$A18,DataQ!AG:AG) -> 0.001
A19: =+A18+1 -> 1985 | B19: =SUMIF(DataQ!$B:$B,DataA!$A19,DataQ!D:D) -> 1073547 | C19: =SUMIF(DataQ!$B:$B,DataA!$A19,DataQ!E:E) -> 1073547 | D19: =SUMIF(DataQ!$B:$B,DataA!$A19,DataQ!F:F) -> 1073547 | E19: =SUMIF(DataQ!$B:$B,DataA!$A19,DataQ!G:G) -> 1073547 | F19: =SUMIF(DataQ!$B:$B,DataA!$A19,DataQ!H:H) -> 1073547 | G19: =SUMIF(DataQ!$B:$B,DataA!$A19,DataQ!I:I) -> 1073547 | H19: =SUMIF(DataQ!$B:$B,DataA!$A19,DataQ!J:J) -> 1073547 | I19: =SUMIF(DataQ!$B:$B,DataA!$A19,DataQ!K:K) -> 1073547 | J19: =SUMIF(DataQ!$B:$B,DataA!$A19,DataQ!L:L) -> 1073547 | K19: =SUMIF(DataQ!$B:$B,DataA!$A19,DataQ!M:M) -> 1073547 | L19: =SUMIF(DataQ!$B:$B,DataA!$A19,DataQ!N:N) -> 1073547 | M19: =SUMIF(DataQ!$B:$B,DataA!$A19,DataQ!O:O) -> 1073547 | N19: =SUMIF(DataQ!$B:$B,DataA!$A19,DataQ!P:P) -> 1073547 | O19: =SUMIF(DataQ!$B:$B,DataA!$A19,DataQ!Q:Q) -> 1073547 | P19: =SUMIF(DataQ!$B:$B,DataA!$A19,DataQ!R:R) -> 1073547 | Q19: =SUMIF(DataQ!$B:$B,DataA!$A19,DataQ!S:S) -> 1073547 | R19: =SUMIF(DataQ!$B:$B,DataA!$A19,DataQ!T:T) -> 1073547 | S19: =AVERAGEIF(DataQ!$B:$B,DataA!$A19,DataQ!U:U) -> 105.4799 | T19: =AVERAGEIF(DataQ!$B:$B,DataA!$A19,DataQ!V:V) -> 44.871375 | U19: =AVERAGEIF(DataQ!$B:$B,DataA!$A19,DataQ!W:W) -> 0.001 | V19: =AVERAGEIF(DataQ!$B:$B,DataA!$A19,DataQ!X:X) -> 0.001 | W19: =AVERAGEIF(DataQ!$B:$B,DataA!$A19,DataQ!Y:Y) -> 0.001 | X19: =AVERAGEIF(DataQ!$B:$B,DataA!$A19,DataQ!Z:Z) -> 0.001 | Y19: =SUMIF(DataQ!$B:$B,DataA!$A19,DataQ!AA:AA) -> 575061 | Z19: =SUMIF(DataQ!$B:$B,DataA!$A19,DataQ!AB:AB) -> 197673 | AA19: =SUMIF(DataQ!$B:$B,DataA!$A19,DataQ!AC:AC) -> 236788 | AB19: =SUMIF(DataQ!$B:$B,DataA!$A19,DataQ!AD:AD) -> 183853 | AC19: =SUMIF(DataQ!$B:$B,DataA!$A19,DataQ!AE:AE) -> 155835 | AD19: =AVERAGEIF(DataQ!$B:$B,DataA!$A19,DataQ!AF:AF) -> 0.001 | AE19: =AVERAGEIF(DataQ!$B:$B,DataA!$A19,DataQ!AG:AG) -> 0.001
... A84: =+A83+1 -> 2050 | B84: =SUMIF(DataQ!$B:$B,DataA!$A84,DataQ!D:D) -> 3438103.8 | C84: =SUMIF(DataQ!$B:$B,DataA!$A84,DataQ!E:E) -> 3379077.3 | D84: =SUMIF(DataQ!$B:$B,DataA!$A84,DataQ!F:F) -> 3380308.9 | E84: =SUMIF(DataQ!$B:$B,DataA!$A84,DataQ!G:G) -> 3380308.9 | F84: =SUMIF(DataQ!$B:$B,DataA!$A84,DataQ!H:H) -> 3404845.5 | G84: =SUMIF(DataQ!$B:$B,DataA!$A84,DataQ!I:I) -> 3405918.5 | H84: =SUMIF(DataQ!$B:$B,DataA!$A84,DataQ!J:J) -> 3405766.6 | I84: =SUMIF(DataQ!$B:$B,DataA!$A84,DataQ!K:K) -> 3405650.9 | J84: =SUMIF(DataQ!$B:$B,DataA!$A84,DataQ!L:L) -> 3405849.4 | K84: =SUMIF(DataQ!$B:$B,DataA!$A84,DataQ!M:M) -> 3405849.4 | L84: =SUMIF(DataQ!$B:$B,DataA!$A84,DataQ!N:N) -> 3426952.3 | M84: =SUMIF(DataQ!$B:$B,DataA!$A84,DataQ!O:O) -> 3435087 | N84: =SUMIF(DataQ!$B:$B,DataA!$A84,DataQ!P:P) -> 3436128.2 | O84: =SUMIF(DataQ!$B:$B,DataA!$A84,DataQ!Q:Q) -> 3447474.4 | P84: =SUMIF(DataQ!$B:$B,DataA!$A84,DataQ!R:R) -> 3455524.5 | Q84: =SUMIF(DataQ!$B:$B,DataA!$A84,DataQ!S:S) -> 3443064.7 | R84: =SUMIF(DataQ!$B:$B,DataA!$A84,DataQ!T:T) -> 3444283.1 | S84: =AVERAGEIF(DataQ!$B:$B,DataA!$A84,DataQ!U:U) -> 1517.2275 | T84: =AVERAGEIF(DataQ!$B:$B,DataA!$A84,DataQ!V:V) -> 226.29695 | U84: =AVERAGEIF(DataQ!$B:$B,DataA!$A84,DataQ!W:W) -> 205.09245 | V84: =AVERAGEIF(DataQ!$B:$B,DataA!$A84,DataQ!X:X) -> 128.10697 | W84: =AVERAGEIF(DataQ!$B:$B,DataA!$A84,DataQ!Y:Y) -> 342.5681 | X84: =AVERAGEIF(DataQ!$B:$B,DataA!$A84,DataQ!Z:Z) -> 229.13137 | Y84: =SUMIF(DataQ!$B:$B,DataA!$A84,DataQ!AA:AA) -> 2045524.2 | Z84: =SUMIF(DataQ!$B:$B,DataA!$A84,DataQ!AB:AB) -> 726076.3 | AA84: =SUMIF(DataQ!$B:$B,DataA!$A84,DataQ!AC:AC) -> 717216.8 | AB84: =SUMIF(DataQ!$B:$B,DataA!$A84,DataQ!AD:AD) -> 1149804.9 | AC84: =SUMIF(DataQ!$B:$B,DataA!$A84,DataQ!AE:AE) -> 1297457.1 | AD84: =AVERAGEIF(DataQ!$B:$B,DataA!$A84,DataQ!AF:AF) -> 2.106464 | AE84: =AVERAGEIF(DataQ!$B:$B,DataA!$A84,DataQ!AG:AG) -> 2.433474

Sheet DataQ
D1: SEP002A.db | E1: JAN011B.db | F1: JAN024B.db | G1: FEB006C.db | H1: FEB019C.db | I1: MAR011D.db | J1: MAR020B.db | K1: APR009C.db | L1: APR023B.db | M1: MAY007C.db | N1: MAY017C.db | O1: JUN011A.db | P1: JUN018H.db | Q1: JUL010A.db | R1: JUL024D.db | S1: AUG008C.db | T1: AUG019C.db | U1: SEP002A.db | V1: SEP002A.db | W1: SEP002A.db | X1: SEP002A.db | Y1: SEP002A.db | Z1: SEP002A.db | AA1: SEP002A.db | AB1: SEP002A.db | AC1: SEP002A.db | AD1: SEP002A.db | AE1: SEP002A.db | AF1: SEP002A.db | AG1: SEP002A.db
D2: UK | E2: UK | F2: UK | G2: UK | H2: UK | I2: UK | J2: UK | K2: UK | L2: UK | M2: UK | N2: UK | O2: UK | P2: UK | Q2: UK | R2: UK | S2: UK | T2: UK | U2: UK | V2: UK | W2: UK | X2: UK | Y2: UK | Z2: UK | AA2: UK | AB2: UK | AC2: UK | AD2: UK | AE2: UK | AF2: UK | AG2: UK
D3: GDP | E3: GDP | F3: GDP | G3: GDP | H3: GDP | I3: GDP | J3: GDP | K3: GDP | L3: GDP | M3: GDP | N3: GDP | O3: GDP | P3: GDP | Q3: GDP | R3: GDP | S3: GDP | T3: GDP | U3: WAGEWKLY | V3: CPI | W3: CPIFD | X3: CPIFU | Y3: CPIEN | Z3: CPICORE | AA3: C | AB3: IF | AC3: GC | AD3: X | AE3: M | AF3: RSWAP2YR_RFR | AG3: RSWAP5YR_RFR
D4: GBR | E4: GBR | F4: GBR | G4: GBR | H4: GBR | I4: GBR | J4: GBR | K4: GBR | L4: GBR | M4: GBR | N4: GBR | O4: GBR | P4: GBR | Q4: GBR | R4: GBR | S4: GBR | T4: GBR | U4: GBR | V4: GBR | W4: GBR | X4: GBR | Y4: GBR | Z4: GBR | AA4: GBR | AB4: GBR | AC4: GBR | AD4: GBR | AE4: GBR | AF4: GBR | AG4: GBR
D5: L | E5: L | F5: L | G5: L | H5: L | I5: L | J5: L | K5: L | L5: L | M5: L | N5: L | O5: L | P5: L | Q5: L | R5: L | S5: L | T5: L | U5: L | V5: L | W5: L | X5: L | Y5: L | Z5: L | AA5: L | AB5: L | AC5: L | AD5: L | AE5: L | AF5: L | AG5: L
C6: =C318+5 -> 2289 | D6: {=_xlfn.CONCAT(INDEX(GMW!$A$2:$LR$60,MATCH(1,(GMW!$LQ$2:$LQ$60=D$3)*(GMW!$LP$2:$LP$60=D$4)*(GMW!$LR$2:$LR$60=D$1),0),$C6-1966),"0",(INDEX(GMW!$A$2:$LR$60,MATCH(1,(GMW!$LQ$2:$LQ$60=D$3)*(GMW!$LP$2:$LP$60=D$4)*(GMW!$LR$2:$LR$60=D$1),0),$C6-1965)))} -> 202402 | E6: {=_xlfn.CONCAT(INDEX(GMW!$A$2:$LR$60,MATCH(1,(GMW!$LQ$2:$LQ$60=E$3)*(GMW!$LP$2:$LP$60=E$4)*(GMW!$LR$2:$LR$60=E$1),0),$C6-1966),"0",(INDEX(GMW!$A$2:$LR$60,MATCH(1,(GMW!$LQ$2:$LQ$60=E$3)*(GMW!$LP$2:$LP$60=E$4)*(GMW!$LR$2:$LR$60=E$1),0),$C6-1965)))} -> 202303 | F6: {=_xlfn.CONCAT(INDEX(GMW!$A$2:$LR$60,MATCH(1,(GMW!$LQ$2:$LQ$60=F$3)*(GMW!$LP$2:$LP$60=F$4)*(GMW!$LR$2:$LR$60=F$1),0),$C6-1966),"0",(INDEX(GMW!$A$2:$LR$60,MATCH(1,(GMW!$LQ$2:$LQ$60=F$3)*(GMW!$LP$2:$LP$60=F$4)*(GMW!$LR$2:$LR$60=F$1),0),$C6-1965)))} -> 202303 | G6: {=_xlfn.CONCAT(INDEX(GMW!$A$2:$LR$60,MATCH(1,(GMW!$LQ$2:$LQ$60=G$3)*(GMW!$LP$2:$LP$60=G$4)*(GMW!$LR$2:$LR$60=G$1),0),$C6-1966),"0",(INDEX(GMW!$A$2:$LR$60,MATCH(1,(GMW!$LQ$2:$LQ$60=G$3)*(GMW!$LP$2:$LP$60=G$4)*(GMW!$LR$2:$LR$60=G$1),0),$C6-1965)))} -> 202303 | H6: {=_xlfn.CONCAT(INDEX(GMW!$A$2:$LR$60,MATCH(1,(GMW!$LQ$2:$LQ$60=H$3)*(GMW!$LP$2:$LP$60=H$4)*(GMW!$LR$2:$LR$60=H$1),0),$C6-1966),"0",(INDEX(GMW!$A$2:$LR$60,MATCH(1,(GMW!$LQ$2:$LQ$60=H$3)*(GMW!$LP$2:$LP$60=H$4)*(GMW!$LR$2:$LR$60=H$1),0),$C6-1965)))} -> 202304 | I6: {=_xlfn.CONCAT(INDEX(GMW!$A$2:$LR$60,MATCH(1,(GMW!$LQ$2:$LQ$60=I$3)*(GMW!$LP$2:$LP$60=I$4)*(GMW!$LR$2:$LR$60=I$1),0),$C6-1966),"0",(INDEX(GMW!$A$2:$LR$60,MATCH(1,(GMW!$LQ$2:$LQ$60=I$3)*(GMW!$LP$2:$LP$60=I$4)*(GMW!$LR$2:$LR$60=I$1),0),$C6-1965)))} -> 202304 | J6: {=_xlfn.CONCAT(INDEX(GMW!$A$2:$LR$60,MATCH(1,(GMW!$LQ$2:$LQ$60=J$3)*(GMW!$LP$2:$LP$60=J$4)*(GMW!$LR$2:$LR$60=J$1),0),$C6-1966),"0",(INDEX(GMW!$A$2:$LR$60,MATCH(1,(GMW!$LQ$2:$LQ$60=J$3)*(GMW!$LP$2:$LP$60=J$4)*(GMW!$LR$2:$LR$60=J$1),0),$C6-1965)))} -> 202304 | K6: {=_xlfn.CONCAT(INDEX(GMW!$A$2:$LR$60,MATCH(1,(GMW!$LQ$2:$LQ$60=K$3)*(GMW!$LP$2:$LP$60=K$4)*(GMW!$LR$2:$LR$60=K$1),0),$C6-1966),"0",(INDEX(GMW!$A$2:$LR$60,MATCH(1,(GMW!$LQ$2:$LQ$60=K$3)*(GMW!$LP$2:$LP$60=K$4)*(GMW!$LR$2:$LR$60=K$1),0),$C6-1965)))} -> 202304 | ... AG6: {=_xlfn.CONCAT(INDEX(GMW!$A$2:$LR$60,MATCH(1,(GMW!$LQ$2:$LQ$60=AG$3)*(GMW!$LP$2:$LP$60=AG$4)*(GMW!$LR$2:$LR$60=AG$1),0),$C6-1966),"0",(INDEX(GMW!$A$2:$LR$60,MATCH(1,(GMW!$LQ$2:$LQ$60=AG$3)*(GMW!$LP$2:$LP$60=AG$4)*(GMW!$LR$2:$LR$60=AG$1),0),$C6-1965)))} -> 202402
A7: 1973 | B7: 1973 | C7: 1973 | D7: {=INDEX(GMW!$A$2:$LR$60,MATCH(1,(GMW!$LQ$2:$LQ$60=D$3)*(GMW!$LP$2:$LP$60=D$4)*(GMW!$LR$2:$LR$60=D$1),0),$C7-1966)} -> 223780 | E7: {=INDEX(GMW!$A$2:$LR$60,MATCH(1,(GMW!$LQ$2:$LQ$60=E$3)*(GMW!$LP$2:$LP$60=E$4)*(GMW!$LR$2:$LR$60=E$1),0),$C7-1966)} -> 223780 | F7: {=INDEX(GMW!$A$2:$LR$60,MATCH(1,(GMW!$LQ$2:$LQ$60=F$3)*(GMW!$LP$2:$LP$60=F$4)*(GMW!$LR$2:$LR$60=F$1),0),$C7-1966)} -> 223780 | G7: {=INDEX(GMW!$A$2:$LR$60,MATCH(1,(GMW!$LQ$2:$LQ$60=G$3)*(GMW!$LP$2:$LP$60=G$4)*(GMW!$LR$2:$LR$60=G$1),0),$C7-1966)} -> 223780 | H7: {=INDEX(GMW!$A$2:$LR$60,MATCH(1,(GMW!$LQ$2:$LQ$60=H$3)*(GMW!$LP$2:$LP$60=H$4)*(GMW!$LR$2:$LR$60=H$1),0),$C7-1966)} -> 223780 | I7: {=INDEX(GMW!$A$2:$LR$60,MATCH(1,(GMW!$LQ$2:$LQ$60=I$3)*(GMW!$LP$2:$LP$60=I$4)*(GMW!$LR$2:$LR$60=I$1),0),$C7-1966)} -> 223780 | J7: {=INDEX(GMW!$A$2:$LR$60,MATCH(1,(GMW!$LQ$2:$LQ$60=J$3)*(GMW!$LP$2:$LP$60=J$4)*(GMW!$LR$2:$LR$60=J$1),0),$C7-1966)} -> 223780 | K7: {=INDEX(GMW!$A$2:$LR$60,MATCH(1,(GMW!$LQ$2:$LQ$60=K$3)*(GMW!$LP$2:$LP$60=K$4)*(GMW!$LR$2:$LR$60=K$1),0),$C7-1966)} -> 223780 | ... AG7: {=INDEX(GMW!$A$2:$LR$60,MATCH(1,(GMW!$LQ$2:$LQ$60=AG$3)*(GMW!$LP$2:$LP$60=AG$4)*(GMW!$LR$2:$LR$60=AG$1),0),$C7-1966)} -> 0.001
B8: =B7 -> 1973 | C8: =+C7+1 -> 1974 | D8: {=INDEX(GMW!$A$2:$LR$60,MATCH(1,(GMW!$LQ$2:$LQ$60=D$3)*(GMW!$LP$2:$LP$60=D$4)*(GMW!$LR$2:$LR$60=D$1),0),$C8-1966)} -> 224213 | E8: {=INDEX(GMW!$A$2:$LR$60,MATCH(1,(GMW!$LQ$2:$LQ$60=E$3)*(GMW!$LP$2:$LP$60=E$4)*(GMW!$LR$2:$LR$60=E$1),0),$C8-1966)} -> 224213 | F8: {=INDEX(GMW!$A$2:$LR$60,MATCH(1,(GMW!$LQ$2:$LQ$60=F$3)*(GMW!$LP$2:$LP$60=F$4)*(GMW!$LR$2:$LR$60=F$1),0),$C8-1966)} -> 224213 | G8: {=INDEX(GMW!$A$2:$LR$60,MATCH(1,(GMW!$LQ$2:$LQ$60=G$3)*(GMW!$LP$2:$LP$60=G$4)*(GMW!$LR$2:$LR$60=G$1),0),$C8-1966)} -> 224213 | H8: {=INDEX(GMW!$A$2:$LR$60,MATCH(1,(GMW!$LQ$2:$LQ$60=H$3)*(GMW!$LP$2:$LP$60=H$4)*(GMW!$LR$2:$LR$60=H$1),0),$C8-1966)} -> 224213 | I8: {=INDEX(GMW!$A$2:$LR$60,MATCH(1,(GMW!$LQ$2:$LQ$60=I$3)*(GMW!$LP$2:$LP$60=I$4)*(GMW!$LR$2:$LR$60=I$1),0),$C8-1966)} -> 224213 | J8: {=INDEX(GMW!$A$2:$LR$60,MATCH(1,(GMW!$LQ$2:$LQ$60=J$3)*(GMW!$LP$2:$LP$60=J$4)*(GMW!$LR$2:$LR$60=J$1),0),$C8-1966)} -> 224213 | K8: {=INDEX(GMW!$A$2:$LR$60,MATCH(1,(GMW!$LQ$2:$LQ$60=K$3)*(GMW!$LP$2:$LP$60=K$4)*(GMW!$LR$2:$LR$60=K$1),0),$C8-1966)} -> 224213 | ... AG8: {=INDEX(GMW!$A$2:$LR$60,MATCH(1,(GMW!$LQ$2:$LQ$60=AG$3)*(GMW!$LP$2:$LP$60=AG$4)*(GMW!$LR$2:$LR$60=AG$1),0),$C8-1966)} -> 0.001
B9: =B8 -> 1973 | C9: =+C8+1 -> 1975 | D9: {=INDEX(GMW!$A$2:$LR$60,MATCH(1,(GMW!$LQ$2:$LQ$60=D$3)*(GMW!$LP$2:$LP$60=D$4)*(GMW!$LR$2:$LR$60=D$1),0),$C9-1966)} -> 222122 | E9: {=INDEX(GMW!$A$2:$LR$60,MATCH(1,(GMW!$LQ$2:$LQ$60=E$3)*(GMW!$LP$2:$LP$60=E$4)*(GMW!$LR$2:$LR$60=E$1),0),$C9-1966)} -> 222122 | F9: {=INDEX(GMW!$A$2:$LR$60,MATCH(1,(GMW!$LQ$2:$LQ$60=F$3)*(GMW!$LP$2:$LP$60=F$4)*(GMW!$LR$2:$LR$60=F$1),0),$C9-1966)} -> 222122 | G9: {=INDEX(GMW!$A$2:$LR$60,MATCH(1,(GMW!$LQ$2:$LQ$60=G$3)*(GMW!$LP$2:$LP$60=G$4)*(GMW!$LR$2:$LR$60=G$1),0),$C9-1966)} -> 222122 | H9: {=INDEX(GMW!$A$2:$LR$60,MATCH(1,(GMW!$LQ$2:$LQ$60=H$3)*(GMW!$LP$2:$LP$60=H$4)*(GMW!$LR$2:$LR$60=H$1),0),$C9-1966)} -> 222122 | I9: {=INDEX(GMW!$A$2:$LR$60,MATCH(1,(GMW!$LQ$2:$LQ$60=I$3)*(GMW!$LP$2:$LP$60=I$4)*(GMW!$LR$2:$LR$60=I$1),0),$C9-1966)} -> 222122 | J9: {=INDEX(GMW!$A$2:$LR$60,MATCH(1,(GMW!$LQ$2:$LQ$60=J$3)*(GMW!$LP$2:$LP$60=J$4)*(GMW!$LR$2:$LR$60=J$1),0),$C9-1966)} -> 222122 | K9: {=INDEX(GMW!$A$2:$LR$60,MATCH(1,(GMW!$LQ$2:$LQ$60=K$3)*(GMW!$LP$2:$LP$60=K$4)*(GMW!$LR$2:$LR$60=K$1),0),$C9-1966)} -> 222122 | ... AG9: {=INDEX(GMW!$A$2:$LR$60,MATCH(1,(GMW!$LQ$2:$LQ$60=AG$3)*(GMW!$LP$2:$LP$60=AG$4)*(GMW!$LR$2:$LR$60=AG$1),0),$C9-1966)} -> 0.001
B10: =B9 -> 1973 | C10: =+C9+1 -> 1976 | D10: {=INDEX(GMW!$A$2:$LR$60,MATCH(1,(GMW!$LQ$2:$LQ$60=D$3)*(GMW!$LP$2:$LP$60=D$4)*(GMW!$LR$2:$LR$60=D$1),0),$C10-1966)} -> 221266 | E10: {=INDEX(GMW!$A$2:$LR$60,MATCH(1,(GMW!$LQ$2:$LQ$60=E$3)*(GMW!$LP$2:$LP$60=E$4)*(GMW!$LR$2:$LR$60=E$1),0),$C10-1966)} -> 221266 | F10: {=INDEX(GMW!$A$2:$LR$60,MATCH(1,(GMW!$LQ$2:$LQ$60=F$3)*(GMW!$LP$2:$LP$60=F$4)*(GMW!$LR$2:$LR$60=F$1),0),$C10-1966)} -> 221266 | G10: {=INDEX(GMW!$A$2:$LR$60,MATCH(1,(GMW!$LQ$2:$LQ$60=G$3)*(GMW!$LP$2:$LP$60=G$4)*(GMW!$LR$2:$LR$60=G$1),0),$C10-1966)} -> 221266 | H10: {=INDEX(GMW!$A$2:$LR$60,MATCH(1,(GMW!$LQ$2:$LQ$60=H$3)*(GMW!$LP$2:$LP$60=H$4)*(GMW!$LR$2:$LR$60=H$1),0),$C10-1966)} -> 221266 | I10: {=INDEX(GMW!$A$2:$LR$60,MATCH(1,(GMW!$LQ$2:$LQ$60=I$3)*(GMW!$LP$2:$LP$60=I$4)*(GMW!$LR$2:$LR$60=I$1),0),$C10-1966)} -> 221266 | J10: {=INDEX(GMW!$A$2:$LR$60,MATCH(1,(GMW!$LQ$2:$LQ$60=J$3)*(GMW!$LP$2:$LP$60=J$4)*(GMW!$LR$2:$LR$60=J$1),0),$C10-1966)} -> 221266 | K10: {=INDEX(GMW!$A$2:$LR$60,MATCH(1,(GMW!$LQ$2:$LQ$60=K$3)*(GMW!$LP$2:$LP$60=K$4)*(GMW!$LR$2:$LR$60=K$1),0),$C10-1966)} -> 221266 | ... AG10: {=INDEX(GMW!$A$2:$LR$60,MATCH(1,(GMW!$LQ$2:$LQ$60=AG$3)*(GMW!$LP$2:$LP$60=AG$4)*(GMW!$LR$2:$LR$60=AG$1),0),$C10-1966)} -> 0.001
A11: 1974 | B11: =B7+1 -> 1974 | C11: =+C10+1 -> 1977 | D11: {=INDEX(GMW!$A$2:$LR$60,MATCH(1,(GMW!$LQ$2:$LQ$60=D$3)*(GMW!$LP$2:$LP$60=D$4)*(GMW!$LR$2:$LR$60=D$1),0),$C11-1966)} -> 215122 | E11: {=INDEX(GMW!$A$2:$LR$60,MATCH(1,(GMW!$LQ$2:$LQ$60=E$3)*(GMW!$LP$2:$LP$60=E$4)*(GMW!$LR$2:$LR$60=E$1),0),$C11-1966)} -> 215122 | F11: {=INDEX(GMW!$A$2:$LR$60,MATCH(1,(GMW!$LQ$2:$LQ$60=F$3)*(GMW!$LP$2:$LP$60=F$4)*(GMW!$LR$2:$LR$60=F$1),0),$C11-1966)} -> 215122 | G11: {=INDEX(GMW!$A$2:$LR$60,MATCH(1,(GMW!$LQ$2:$LQ$60=G$3)*(GMW!$LP$2:$LP$60=G$4)*(GMW!$LR$2:$LR$60=G$1),0),$C11-1966)} -> 215122 | H11: {=INDEX(GMW!$A$2:$LR$60,MATCH(1,(GMW!$LQ$2:$LQ$60=H$3)*(GMW!$LP$2:$LP$60=H$4)*(GMW!$LR$2:$LR$60=H$1),0),$C11-1966)} -> 215122 | I11: {=INDEX(GMW!$A$2:$LR$60,MATCH(1,(GMW!$LQ$2:$LQ$60=I$3)*(GMW!$LP$2:$LP$60=I$4)*(GMW!$LR$2:$LR$60=I$1),0),$C11-1966)} -> 215122 | J11: {=INDEX(GMW!$A$2:$LR$60,MATCH(1,(GMW!$LQ$2:$LQ$60=J$3)*(GMW!$LP$2:$LP$60=J$4)*(GMW!$LR$2:$LR$60=J$1),0),$C11-1966)} -> 215122 | K11: {=INDEX(GMW!$A$2:$LR$60,MATCH(1,(GMW!$LQ$2:$LQ$60=K$3)*(GMW!$LP$2:$LP$60=K$4)*(GMW!$LR$2:$LR$60=K$1),0),$C11-1966)} -> 215122 | ... AG11: {=INDEX(GMW!$A$2:$LR$60,MATCH(1,(GMW!$LQ$2:$LQ$60=AG$3)*(GMW!$LP$2:$LP$60=AG$4)*(GMW!$LR$2:$LR$60=AG$1),0),$C11-1966)} -> 0.001
B12: =B8+1 -> 1974 | C12: =+C11+1 -> 1978 | D12: {=INDEX(GMW!$A$2:$LR$60,MATCH(1,(GMW!$LQ$2:$LQ$60=D$3)*(GMW!$LP$2:$LP$60=D$4)*(GMW!$LR$2:$LR$60=D$1),0),$C12-1966)} -> 218215 | E12: {=INDEX(GMW!$A$2:$LR$60,MATCH(1,(GMW!$LQ$2:$LQ$60=E$3)*(GMW!$LP$2:$LP$60=E$4)*(GMW!$LR$2:$LR$60=E$1),0),$C12-1966)} -> 218215 | F12: {=INDEX(GMW!$A$2:$LR$60,MATCH(1,(GMW!$LQ$2:$LQ$60=F$3)*(GMW!$LP$2:$LP$60=F$4)*(GMW!$LR$2:$LR$60=F$1),0),$C12-1966)} -> 218215 | G12: {=INDEX(GMW!$A$2:$LR$60,MATCH(1,(GMW!$LQ$2:$LQ$60=G$3)*(GMW!$LP$2:$LP$60=G$4)*(GMW!$LR$2:$LR$60=G$1),0),$C12-1966)} -> 218215 | H12: {=INDEX(GMW!$A$2:$LR$60,MATCH(1,(GMW!$LQ$2:$LQ$60=H$3)*(GMW!$LP$2:$LP$60=H$4)*(GMW!$LR$2:$LR$60=H$1),0),$C12-1966)} -> 218215 | I12: {=INDEX(GMW!$A$2:$LR$60,MATCH(1,(GMW!$LQ$2:$LQ$60=I$3)*(GMW!$LP$2:$LP$60=I$4)*(GMW!$LR$2:$LR$60=I$1),0),$C12-1966)} -> 218215 | J12: {=INDEX(GMW!$A$2:$LR$60,MATCH(1,(GMW!$LQ$2:$LQ$60=J$3)*(GMW!$LP$2:$LP$60=J$4)*(GMW!$LR$2:$LR$60=J$1),0),$C12-1966)} -> 218215 | K12: {=INDEX(GMW!$A$2:$LR$60,MATCH(1,(GMW!$LQ$2:$LQ$60=K$3)*(GMW!$LP$2:$LP$60=K$4)*(GMW!$LR$2:$LR$60=K$1),0),$C12-1966)} -> 218215 | ... AG12: {=INDEX(GMW!$A$2:$LR$60,MATCH(1,(GMW!$LQ$2:$LQ$60=AG$3)*(GMW!$LP$2:$LP$60=AG$4)*(GMW!$LR$2:$LR$60=AG$1),0),$C12-1966)} -> 0.001
B13: =B9+1 -> 1974 | C13: =+C12+1 -> 1979 | D13: {=INDEX(GMW!$A$2:$LR$60,MATCH(1,(GMW!$LQ$2:$LQ$60=D$3)*(GMW!$LP$2:$LP$60=D$4)*(GMW!$LR$2:$LR$60=D$1),0),$C13-1966)} -> 219517 | E13: {=INDEX(GMW!$A$2:$LR$60,MATCH(1,(GMW!$LQ$2:$LQ$60=E$3)*(GMW!$LP$2:$LP$60=E$4)*(GMW!$LR$2:$LR$60=E$1),0),$C13-1966)} -> 219517 | F13: {=INDEX(GMW!$A$2:$LR$60,MATCH(1,(GMW!$LQ$2:$LQ$60=F$3)*(GMW!$LP$2:$LP$60=F$4)*(GMW!$LR$2:$LR$60=F$1),0),$C13-1966)} -> 219517 | G13: {=INDEX(GMW!$A$2:$LR$60,MATCH(1,(GMW!$LQ$2:$LQ$60=G$3)*(GMW!$LP$2:$LP$60=G$4)*(GMW!$LR$2:$LR$60=G$1),0),$C13-1966)} -> 219517 | H13: {=INDEX(GMW!$A$2:$LR$60,MATCH(1,(GMW!$LQ$2:$LQ$60=H$3)*(GMW!$LP$2:$LP$60=H$4)*(GMW!$LR$2:$LR$60=H$1),0),$C13-1966)} -> 219517 | I13: {=INDEX(GMW!$A$2:$LR$60,MATCH(1,(GMW!$LQ$2:$LQ$60=I$3)*(GMW!$LP$2:$LP$60=I$4)*(GMW!$LR$2:$LR$60=I$1),0),$C13-1966)} -> 219517 | J13: {=INDEX(GMW!$A$2:$LR$60,MATCH(1,(GMW!$LQ$2:$LQ$60=J$3)*(GMW!$LP$2:$LP$60=J$4)*(GMW!$LR$2:$LR$60=J$1),0),$C13-1966)} -> 219517 | K13: {=INDEX(GMW!$A$2:$LR$60,MATCH(1,(GMW!$LQ$2:$LQ$60=K$3)*(GMW!$LP$2:$LP$60=K$4)*(GMW!$LR$2:$LR$60=K$1),0),$C13-1966)} -> 219517 | ... AG13: {=INDEX(GMW!$A$2:$LR$60,MATCH(1,(GMW!$LQ$2:$LQ$60=AG$3)*(GMW!$LP$2:$LP$60=AG$4)*(GMW!$LR$2:$LR$60=AG$1),0),$C13-1966)} -> 0.001
B14: =B10+1 -> 1974 | C14: =+C13+1 -> 1980 | D14: {=INDEX(GMW!$A$2:$LR$60,MATCH(1,(GMW!$LQ$2:$LQ$60=D$3)*(GMW!$LP$2:$LP$60=D$4)*(GMW!$LR$2:$LR$60=D$1),0),$C14-1966)} -> 216301 | E14: {=INDEX(GMW!$A$2:$LR$60,MATCH(1,(GMW!$LQ$2:$LQ$60=E$3)*(GMW!$LP$2:$LP$60=E$4)*(GMW!$LR$2:$LR$60=E$1),0),$C14-1966)} -> 216301 | F14: {=INDEX(GMW!$A$2:$LR$60,MATCH(1,(GMW!$LQ$2:$LQ$60=F$3)*(GMW!$LP$2:$LP$60=F$4)*(GMW!$LR$2:$LR$60=F$1),0),$C14-1966)} -> 216301 | G14: {=INDEX(GMW!$A$2:$LR$60,MATCH(1,(GMW!$LQ$2:$LQ$60=G$3)*(GMW!$LP$2:$LP$60=G$4)*(GMW!$LR$2:$LR$60=G$1),0),$C14-1966)} -> 216301 | H14: {=INDEX(GMW!$A$2:$LR$60,MATCH(1,(GMW!$LQ$2:$LQ$60=H$3)*(GMW!$LP$2:$LP$60=H$4)*(GMW!$LR$2:$LR$60=H$1),0),$C14-1966)} -> 216301 | I14: {=INDEX(GMW!$A$2:$LR$60,MATCH(1,(GMW!$LQ$2:$LQ$60=I$3)*(GMW!$LP$2:$LP$60=I$4)*(GMW!$LR$2:$LR$60=I$1),0),$C14-1966)} -> 216301 | J14: {=INDEX(GMW!$A$2:$LR$60,MATCH(1,(GMW!$LQ$2:$LQ$60=J$3)*(GMW!$LP$2:$LP$60=J$4)*(GMW!$LR$2:$LR$60=J$1),0),$C14-1966)} -> 216301 | K14: {=INDEX(GMW!$A$2:$LR$60,MATCH(1,(GMW!$LQ$2:$LQ$60=K$3)*(GMW!$LP$2:$LP$60=K$4)*(GMW!$LR$2:$LR$60=K$1),0),$C14-1966)} -> 216301 | ... AG14: {=INDEX(GMW!$A$2:$LR$60,MATCH(1,(GMW!$LQ$2:$LQ$60=AG$3)*(GMW!$LP$2:$LP$60=AG$4)*(GMW!$LR$2:$LR$60=AG$1),0),$C14-1966)} -> 0.001
A15: 1975 | B15: =B11+1 -> 1975 | C15: =+C14+1 -> 1981 | D15: {=INDEX(GMW!$A$2:$LR$60,MATCH(1,(GMW!$LQ$2:$LQ$60=D$3)*(GMW!$LP$2:$LP$60=D$4)*(GMW!$LR$2:$LR$60=D$1),0),$C15-1966)} -> 216390 | E15: {=INDEX(GMW!$A$2:$LR$60,MATCH(1,(GMW!$LQ$2:$LQ$60=E$3)*(GMW!$LP$2:$LP$60=E$4)*(GMW!$LR$2:$LR$60=E$1),0),$C15-1966)} -> 216390 | F15: {=INDEX(GMW!$A$2:$LR$60,MATCH(1,(GMW!$LQ$2:$LQ$60=F$3)*(GMW!$LP$2:$LP$60=F$4)*(GMW!$LR$2:$LR$60=F$1),0),$C15-1966)} -> 216390 | G15: {=INDEX(GMW!$A$2:$LR$60,MATCH(1,(GMW!$LQ$2:$LQ$60=G$3)*(GMW!$LP$2:$LP$60=G$4)*(GMW!$LR$2:$LR$60=G$1),0),$C15-1966)} -> 216390 | H15: {=INDEX(GMW!$A$2:$LR$60,MATCH(1,(GMW!$LQ$2:$LQ$60=H$3)*(GMW!$LP$2:$LP$60=H$4)*(GMW!$LR$2:$LR$60=H$1),0),$C15-1966)} -> 216390 | I15: {=INDEX(GMW!$A$2:$LR$60,MATCH(1,(GMW!$LQ$2:$LQ$60=I$3)*(GMW!$LP$2:$LP$60=I$4)*(GMW!$LR$2:$LR$60=I$1),0),$C15-1966)} -> 216390 | J15: {=INDEX(GMW!$A$2:$LR$60,MATCH(1,(GMW!$LQ$2:$LQ$60=J$3)*(GMW!$LP$2:$LP$60=J$4)*(GMW!$LR$2:$LR$60=J$1),0),$C15-1966)} -> 216390 | K15: {=INDEX(GMW!$A$2:$LR$60,MATCH(1,(GMW!$LQ$2:$LQ$60=K$3)*(GMW!$LP$2:$LP$60=K$4)*(GMW!$LR$2:$LR$60=K$1),0),$C15-1966)} -> 216390 | ... AG15: {=INDEX(GMW!$A$2:$LR$60,MATCH(1,(GMW!$LQ$2:$LQ$60=AG$3)*(GMW!$LP$2:$LP$60=AG$4)*(GMW!$LR$2:$LR$60=AG$1),0),$C15-1966)} -> 0.001
B16: =B12+1 -> 1975 | C16: =+C15+1 -> 1982 | D16: {=INDEX(GMW!$A$2:$LR$60,MATCH(1,(GMW!$LQ$2:$LQ$60=D$3)*(GMW!$LP$2:$LP$60=D$4)*(GMW!$LR$2:$LR$60=D$1),0),$C16-1966)} -> 212882 | E16: {=INDEX(GMW!$A$2:$LR$60,MATCH(1,(GMW!$LQ$2:$LQ$60=E$3)*(GMW!$LP$2:$LP$60=E$4)*(GMW!$LR$2:$LR$60=E$1),0),$C16-1966)} -> 212882 | F16: {=INDEX(GMW!$A$2:$LR$60,MATCH(1,(GMW!$LQ$2:$LQ$60=F$3)*(GMW!$LP$2:$LP$60=F$4)*(GMW!$LR$2:$LR$60=F$1),0),$C16-1966)} -> 212882 | G16: {=INDEX(GMW!$A$2:$LR$60,MATCH(1,(GMW!$LQ$2:$LQ$60=G$3)*(GMW!$LP$2:$LP$60=G$4)*(GMW!$LR$2:$LR$60=G$1),0),$C16-1966)} -> 212882 | H16: {=INDEX(GMW!$A$2:$LR$60,MATCH(1,(GMW!$LQ$2:$LQ$60=H$3)*(GMW!$LP$2:$LP$60=H$4)*(GMW!$LR$2:$LR$60=H$1),0),$C16-1966)} -> 212882 | I16: {=INDEX(GMW!$A$2:$LR$60,MATCH(1,(GMW!$LQ$2:$LQ$60=I$3)*(GMW!$LP$2:$LP$60=I$4)*(GMW!$LR$2:$LR$60=I$1),0),$C16-1966)} -> 212882 | J16: {=INDEX(GMW!$A$2:$LR$60,MATCH(1,(GMW!$LQ$2:$LQ$60=J$3)*(GMW!$LP$2:$LP$60=J$4)*(GMW!$LR$2:$LR$60=J$1),0),$C16-1966)} -> 212882 | K16: {=INDEX(GMW!$A$2:$LR$60,MATCH(1,(GMW!$LQ$2:$LQ$60=K$3)*(GMW!$LP$2:$LP$60=K$4)*(GMW!$LR$2:$LR$60=K$1),0),$C16-1966)} -> 212882 | ... AG16: {=INDEX(GMW!$A$2:$LR$60,MATCH(1,(GMW!$LQ$2:$LQ$60=AG$3)*(GMW!$LP$2:$LP$60=AG$4)*(GMW!$LR$2:$LR$60=AG$1),0),$C16-1966)} -> 0.001
B17: =B13+1 -> 1975 | C17: =+C16+1 -> 1983 | D17: {=INDEX(GMW!$A$2:$LR$60,MATCH(1,(GMW!$LQ$2:$LQ$60=D$3)*(GMW!$LP$2:$LP$60=D$4)*(GMW!$LR$2:$LR$60=D$1),0),$C17-1966)} -> 212192 | E17: {=INDEX(GMW!$A$2:$LR$60,MATCH(1,(GMW!$LQ$2:$LQ$60=E$3)*(GMW!$LP$2:$LP$60=E$4)*(GMW!$LR$2:$LR$60=E$1),0),$C17-1966)} -> 212192 | F17: {=INDEX(GMW!$A$2:$LR$60,MATCH(1,(GMW!$LQ$2:$LQ$60=F$3)*(GMW!$LP$2:$LP$60=F$4)*(GMW!$LR$2:$LR$60=F$1),0),$C17-1966)} -> 212192 | G17: {=INDEX(GMW!$A$2:$LR$60,MATCH(1,(GMW!$LQ$2:$LQ$60=G$3)*(GMW!$LP$2:$LP$60=G$4)*(GMW!$LR$2:$LR$60=G$1),0),$C17-1966)} -> 212192 | H17: {=INDEX(GMW!$A$2:$LR$60,MATCH(1,(GMW!$LQ$2:$LQ$60=H$3)*(GMW!$LP$2:$LP$60=H$4)*(GMW!$LR$2:$LR$60=H$1),0),$C17-1966)} -> 212192 | I17: {=INDEX(GMW!$A$2:$LR$60,MATCH(1,(GMW!$LQ$2:$LQ$60=I$3)*(GMW!$LP$2:$LP$60=I$4)*(GMW!$LR$2:$LR$60=I$1),0),$C17-1966)} -> 212192 | J17: {=INDEX(GMW!$A$2:$LR$60,MATCH(1,(GMW!$LQ$2:$LQ$60=J$3)*(GMW!$LP$2:$LP$60=J$4)*(GMW!$LR$2:$LR$60=J$1),0),$C17-1966)} -> 212192 | K17: {=INDEX(GMW!$A$2:$LR$60,MATCH(1,(GMW!$LQ$2:$LQ$60=K$3)*(GMW!$LP$2:$LP$60=K$4)*(GMW!$LR$2:$LR$60=K$1),0),$C17-1966)} -> 212192 | ... AG17: {=INDEX(GMW!$A$2:$LR$60,MATCH(1,(GMW!$LQ$2:$LQ$60=AG$3)*(GMW!$LP$2:$LP$60=AG$4)*(GMW!$LR$2:$LR$60=AG$1),0),$C17-1966)} -> 0.001
B18: =B14+1 -> 1975 | C18: =+C17+1 -> 1984 | D18: {=INDEX(GMW!$A$2:$LR$60,MATCH(1,(GMW!$LQ$2:$LQ$60=D$3)*(GMW!$LP$2:$LP$60=D$4)*(GMW!$LR$2:$LR$60=D$1),0),$C18-1966)} -> 214585 | E18: {=INDEX(GMW!$A$2:$LR$60,MATCH(1,(GMW!$LQ$2:$LQ$60=E$3)*(GMW!$LP$2:$LP$60=E$4)*(GMW!$LR$2:$LR$60=E$1),0),$C18-1966)} -> 214585 | F18: {=INDEX(GMW!$A$2:$LR$60,MATCH(1,(GMW!$LQ$2:$LQ$60=F$3)*(GMW!$LP$2:$LP$60=F$4)*(GMW!$LR$2:$LR$60=F$1),0),$C18-1966)} -> 214585 | G18: {=INDEX(GMW!$A$2:$LR$60,MATCH(1,(GMW!$LQ$2:$LQ$60=G$3)*(GMW!$LP$2:$LP$60=G$4)*(GMW!$LR$2:$LR$60=G$1),0),$C18-1966)} -> 214585 | H18: {=INDEX(GMW!$A$2:$LR$60,MATCH(1,(GMW!$LQ$2:$LQ$60=H$3)*(GMW!$LP$2:$LP$60=H$4)*(GMW!$LR$2:$LR$60=H$1),0),$C18-1966)} -> 214585 | I18: {=INDEX(GMW!$A$2:$LR$60,MATCH(1,(GMW!$LQ$2:$LQ$60=I$3)*(GMW!$LP$2:$LP$60=I$4)*(GMW!$LR$2:$LR$60=I$1),0),$C18-1966)} -> 214585 | J18: {=INDEX(GMW!$A$2:$LR$60,MATCH(1,(GMW!$LQ$2:$LQ$60=J$3)*(GMW!$LP$2:$LP$60=J$4)*(GMW!$LR$2:$LR$60=J$1),0),$C18-1966)} -> 214585 | K18: {=INDEX(GMW!$A$2:$LR$60,MATCH(1,(GMW!$LQ$2:$LQ$60=K$3)*(GMW!$LP$2:$LP$60=K$4)*(GMW!$LR$2:$LR$60=K$1),0),$C18-1966)} -> 214585 | ... AG18: {=INDEX(GMW!$A$2:$LR$60,MATCH(1,(GMW!$LQ$2:$LQ$60=AG$3)*(GMW!$LP$2:$LP$60=AG$4)*(GMW!$LR$2:$LR$60=AG$1),0),$C18-1966)} -> 0.001
A19: 1976 | B19: =B15+1 -> 1976 | C19: =+C18+1 -> 1985 | D19: {=INDEX(GMW!$A$2:$LR$60,MATCH(1,(GMW!$LQ$2:$LQ$60=D$3)*(GMW!$LP$2:$LP$60=D$4)*(GMW!$LR$2:$LR$60=D$1),0),$C19-1966)} -> 218180 | E19: {=INDEX(GMW!$A$2:$LR$60,MATCH(1,(GMW!$LQ$2:$LQ$60=E$3)*(GMW!$LP$2:$LP$60=E$4)*(GMW!$LR$2:$LR$60=E$1),0),$C19-1966)} -> 218180 | F19: {=INDEX(GMW!$A$2:$LR$60,MATCH(1,(GMW!$LQ$2:$LQ$60=F$3)*(GMW!$LP$2:$LP$60=F$4)*(GMW!$LR$2:$LR$60=F$1),0),$C19-1966)} -> 218180 | G19: {=INDEX(GMW!$A$2:$LR$60,MATCH(1,(GMW!$LQ$2:$LQ$60=G$3)*(GMW!$LP$2:$LP$60=G$4)*(GMW!$LR$2:$LR$60=G$1),0),$C19-1966)} -> 218180 | H19: {=INDEX(GMW!$A$2:$LR$60,MATCH(1,(GMW!$LQ$2:$LQ$60=H$3)*(GMW!$LP$2:$LP$60=H$4)*(GMW!$LR$2:$LR$60=H$1),0),$C19-1966)} -> 218180 | I19: {=INDEX(GMW!$A$2:$LR$60,MATCH(1,(GMW!$LQ$2:$LQ$60=I$3)*(GMW!$LP$2:$LP$60=I$4)*(GMW!$LR$2:$LR$60=I$1),0),$C19-1966)} -> 218180 | J19: {=INDEX(GMW!$A$2:$LR$60,MATCH(1,(GMW!$LQ$2:$LQ$60=J$3)*(GMW!$LP$2:$LP$60=J$4)*(GMW!$LR$2:$LR$60=J$1),0),$C19-1966)} -> 218180 | K19: {=INDEX(GMW!$A$2:$LR$60,MATCH(1,(GMW!$LQ$2:$LQ$60=K$3)*(GMW!$LP$2:$LP$60=K$4)*(GMW!$LR$2:$LR$60=K$1),0),$C19-1966)} -> 218180 | ... AG19: {=INDEX(GMW!$A$2:$LR$60,MATCH(1,(GMW!$LQ$2:$LQ$60=AG$3)*(GMW!$LP$2:$LP$60=AG$4)*(GMW!$LR$2:$LR$60=AG$1),0),$C19-1966)} -> 0.001
B20: =B16+1 -> 1976 | C20: =+C19+1 -> 1986 | D20: {=INDEX(GMW!$A$2:$LR$60,MATCH(1,(GMW!$LQ$2:$LQ$60=D$3)*(GMW!$LP$2:$LP$60=D$4)*(GMW!$LR$2:$LR$60=D$1),0),$C20-1966)} -> 217883 | E20: {=INDEX(GMW!$A$2:$LR$60,MATCH(1,(GMW!$LQ$2:$LQ$60=E$3)*(GMW!$LP$2:$LP$60=E$4)*(GMW!$LR$2:$LR$60=E$1),0),$C20-1966)} -> 217883 | F20: {=INDEX(GMW!$A$2:$LR$60,MATCH(1,(GMW!$LQ$2:$LQ$60=F$3)*(GMW!$LP$2:$LP$60=F$4)*(GMW!$LR$2:$LR$60=F$1),0),$C20-1966)} -> 217883 | G20: {=INDEX(GMW!$A$2:$LR$60,MATCH(1,(GMW!$LQ$2:$LQ$60=G$3)*(GMW!$LP$2:$LP$60=G$4)*(GMW!$LR$2:$LR$60=G$1),0),$C20-1966)} -> 217883 | H20: {=INDEX(GMW!$A$2:$LR$60,MATCH(1,(GMW!$LQ$2:$LQ$60=H$3)*(GMW!$LP$2:$LP$60=H$4)*(GMW!$LR$2:$LR$60=H$1),0),$C20-1966)} -> 217883 | I20: {=INDEX(GMW!$A$2:$LR$60,MATCH(1,(GMW!$LQ$2:$LQ$60=I$3)*(GMW!$LP$2:$LP$60=I$4)*(GMW!$LR$2:$LR$60=I$1),0),$C20-1966)} -> 217883 | J20: {=INDEX(GMW!$A$2:$LR$60,MATCH(1,(GMW!$LQ$2:$LQ$60=J$3)*(GMW!$LP$2:$LP$60=J$4)*(GMW!$LR$2:$LR$60=J$1),0),$C20-1966)} -> 217883 | K20: {=INDEX(GMW!$A$2:$LR$60,MATCH(1,(GMW!$LQ$2:$LQ$60=K$3)*(GMW!$LP$2:$LP$60=K$4)*(GMW!$LR$2:$LR$60=K$1),0),$C20-1966)} -> 217883 | ... AG20: {=INDEX(GMW!$A$2:$LR$60,MATCH(1,(GMW!$LQ$2:$LQ$60=AG$3)*(GMW!$LP$2:$LP$60=AG$4)*(GMW!$LR$2:$LR$60=AG$1),0),$C20-1966)} -> 0.001
B21: =B17+1 -> 1976 | C21: =+C20+1 -> 1987 | D21: {=INDEX(GMW!$A$2:$LR$60,MATCH(1,(GMW!$LQ$2:$LQ$60=D$3)*(GMW!$LP$2:$LP$60=D$4)*(GMW!$LR$2:$LR$60=D$1),0),$C21-1966)} -> 220587 | E21: {=INDEX(GMW!$A$2:$LR$60,MATCH(1,(GMW!$LQ$2:$LQ$60=E$3)*(GMW!$LP$2:$LP$60=E$4)*(GMW!$LR$2:$LR$60=E$1),0),$C21-1966)} -> 220587 | F21: {=INDEX(GMW!$A$2:$LR$60,MATCH(1,(GMW!$LQ$2:$LQ$60=F$3)*(GMW!$LP$2:$LP$60=F$4)*(GMW!$LR$2:$LR$60=F$1),0),$C21-1966)} -> 220587 | G21: {=INDEX(GMW!$A$2:$LR$60,MATCH(1,(GMW!$LQ$2:$LQ$60=G$3)*(GMW!$LP$2:$LP$60=G$4)*(GMW!$LR$2:$LR$60=G$1),0),$C21-1966)} -> 220587 | H21: {=INDEX(GMW!$A$2:$LR$60,MATCH(1,(GMW!$LQ$2:$LQ$60=H$3)*(GMW!$LP$2:$LP$60=H$4)*(GMW!$LR$2:$LR$60=H$1),0),$C21-1966)} -> 220587 | I21: {=INDEX(GMW!$A$2:$LR$60,MATCH(1,(GMW!$LQ$2:$LQ$60=I$3)*(GMW!$LP$2:$LP$60=I$4)*(GMW!$LR$2:$LR$60=I$1),0),$C21-1966)} -> 220587 | J21: {=INDEX(GMW!$A$2:$LR$60,MATCH(1,(GMW!$LQ$2:$LQ$60=J$3)*(GMW!$LP$2:$LP$60=J$4)*(GMW!$LR$2:$LR$60=J$1),0),$C21-1966)} -> 220587 | K21: {=INDEX(GMW!$A$2:$LR$60,MATCH(1,(GMW!$LQ$2:$LQ$60=K$3)*(GMW!$LP$2:$LP$60=K$4)*(GMW!$LR$2:$LR$60=K$1),0),$C21-1966)} -> 220587 | ... AG21: {=INDEX(GMW!$A$2:$LR$60,MATCH(1,(GMW!$LQ$2:$LQ$60=AG$3)*(GMW!$LP$2:$LP$60=AG$4)*(GMW!$LR$2:$LR$60=AG$1),0),$C21-1966)} -> 0.001
B22: =B18+1 -> 1976 | C22: =+C21+1 -> 1988 | D22: {=INDEX(GMW!$A$2:$LR$60,MATCH(1,(GMW!$LQ$2:$LQ$60=D$3)*(GMW!$LP$2:$LP$60=D$4)*(GMW!$LR$2:$LR$60=D$1),0),$C22-1966)} -> 225228 | E22: {=INDEX(GMW!$A$2:$LR$60,MATCH(1,(GMW!$LQ$2:$LQ$60=E$3)*(GMW!$LP$2:$LP$60=E$4)*(GMW!$LR$2:$LR$60=E$1),0),$C22-1966)} -> 225228 | F22: {=INDEX(GMW!$A$2:$LR$60,MATCH(1,(GMW!$LQ$2:$LQ$60=F$3)*(GMW!$LP$2:$LP$60=F$4)*(GMW!$LR$2:$LR$60=F$1),0),$C22-1966)} -> 225228 | G22: {=INDEX(GMW!$A$2:$LR$60,MATCH(1,(GMW!$LQ$2:$LQ$60=G$3)*(GMW!$LP$2:$LP$60=G$4)*(GMW!$LR$2:$LR$60=G$1),0),$C22-1966)} -> 225228 | H22: {=INDEX(GMW!$A$2:$LR$60,MATCH(1,(GMW!$LQ$2:$LQ$60=H$3)*(GMW!$LP$2:$LP$60=H$4)*(GMW!$LR$2:$LR$60=H$1),0),$C22-1966)} -> 225228 | I22: {=INDEX(GMW!$A$2:$LR$60,MATCH(1,(GMW!$LQ$2:$LQ$60=I$3)*(GMW!$LP$2:$LP$60=I$4)*(GMW!$LR$2:$LR$60=I$1),0),$C22-1966)} -> 225228 | J22: {=INDEX(GMW!$A$2:$LR$60,MATCH(1,(GMW!$LQ$2:$LQ$60=J$3)*(GMW!$LP$2:$LP$60=J$4)*(GMW!$LR$2:$LR$60=J$1),0),$C22-1966)} -> 225228 | K22: {=INDEX(GMW!$A$2:$LR$60,MATCH(1,(GMW!$LQ$2:$LQ$60=K$3)*(GMW!$LP$2:$LP$60=K$4)*(GMW!$LR$2:$LR$60=K$1),0),$C22-1966)} -> 225228 | ... AG22: {=INDEX(GMW!$A$2:$LR$60,MATCH(1,(GMW!$LQ$2:$LQ$60=AG$3)*(GMW!$LP$2:$LP$60=AG$4)*(GMW!$LR$2:$LR$60=AG$1),0),$C22-1966)} -> 0.001
A23: 1977 | B23: =B19+1 -> 1977 | C23: =+C22+1 -> 1989 | D23: {=INDEX(GMW!$A$2:$LR$60,MATCH(1,(GMW!$LQ$2:$LQ$60=D$3)*(GMW!$LP$2:$LP$60=D$4)*(GMW!$LR$2:$LR$60=D$1),0),$C23-1966)} -> 225362 | E23: {=INDEX(GMW!$A$2:$LR$60,MATCH(1,(GMW!$LQ$2:$LQ$60=E$3)*(GMW!$LP$2:$LP$60=E$4)*(GMW!$LR$2:$LR$60=E$1),0),$C23-1966)} -> 225362 | F23: {=INDEX(GMW!$A$2:$LR$60,MATCH(1,(GMW!$LQ$2:$LQ$60=F$3)*(GMW!$LP$2:$LP$60=F$4)*(GMW!$LR$2:$LR$60=F$1),0),$C23-1966)} -> 225362 | G23: {=INDEX(GMW!$A$2:$LR$60,MATCH(1,(GMW!$LQ$2:$LQ$60=G$3)*(GMW!$LP$2:$LP$60=G$4)*(GMW!$LR$2:$LR$60=G$1),0),$C23-1966)} -> 225362 | H23: {=INDEX(GMW!$A$2:$LR$60,MATCH(1,(GMW!$LQ$2:$LQ$60=H$3)*(GMW!$LP$2:$LP$60=H$4)*(GMW!$LR$2:$LR$60=H$1),0),$C23-1966)} -> 225362 | I23: {=INDEX(GMW!$A$2:$LR$60,MATCH(1,(GMW!$LQ$2:$LQ$60=I$3)*(GMW!$LP$2:$LP$60=I$4)*(GMW!$LR$2:$LR$60=I$1),0),$C23-1966)} -> 225362 | J23: {=INDEX(GMW!$A$2:$LR$60,MATCH(1,(GMW!$LQ$2:$LQ$60=J$3)*(GMW!$LP$2:$LP$60=J$4)*(GMW!$LR$2:$LR$60=J$1),0),$C23-1966)} -> 225362 | K23: {=INDEX(GMW!$A$2:$LR$60,MATCH(1,(GMW!$LQ$2:$LQ$60=K$3)*(GMW!$LP$2:$LP$60=K$4)*(GMW!$LR$2:$LR$60=K$1),0),$C23-1966)} -> 225362 | ... AG23: {=INDEX(GMW!$A$2:$LR$60,MATCH(1,(GMW!$LQ$2:$LQ$60=AG$3)*(GMW!$LP$2:$LP$60=AG$4)*(GMW!$LR$2:$LR$60=AG$1),0),$C23-1966)} -> 0.001
B24: =B20+1 -> 1977 | C24: =+C23+1 -> 1990 | D24: {=INDEX(GMW!$A$2:$LR$60,MATCH(1,(GMW!$LQ$2:$LQ$60=D$3)*(GMW!$LP$2:$LP$60=D$4)*(GMW!$LR$2:$LR$60=D$1),0),$C24-1966)} -> 223815 | E24: {=INDEX(GMW!$A$2:$LR$60,MATCH(1,(GMW!$LQ$2:$LQ$60=E$3)*(GMW!$LP$2:$LP$60=E$4)*(GMW!$LR$2:$LR$60=E$1),0),$C24-1966)} -> 223815 | F24: {=INDEX(GMW!$A$2:$LR$60,MATCH(1,(GMW!$LQ$2:$LQ$60=F$3)*(GMW!$LP$2:$LP$60=F$4)*(GMW!$LR$2:$LR$60=F$1),0),$C24-1966)} -> 223815 | G24: {=INDEX(GMW!$A$2:$LR$60,MATCH(1,(GMW!$LQ$2:$LQ$60=G$3)*(GMW!$LP$2:$LP$60=G$4)*(GMW!$LR$2:$LR$60=G$1),0),$C24-1966)} -> 223815 | H24: {=INDEX(GMW!$A$2:$LR$60,MATCH(1,(GMW!$LQ$2:$LQ$60=H$3)*(GMW!$LP$2:$LP$60=H$4)*(GMW!$LR$2:$LR$60=H$1),0),$C24-1966)} -> 223815 | I24: {=INDEX(GMW!$A$2:$LR$60,MATCH(1,(GMW!$LQ$2:$LQ$60=I$3)*(GMW!$LP$2:$LP$60=I$4)*(GMW!$LR$2:$LR$60=I$1),0),$C24-1966)} -> 223815 | J24: {=INDEX(GMW!$A$2:$LR$60,MATCH(1,(GMW!$LQ$2:$LQ$60=J$3)*(GMW!$LP$2:$LP$60=J$4)*(GMW!$LR$2:$LR$60=J$1),0),$C24-1966)} -> 223815 | K24: {=INDEX(GMW!$A$2:$LR$60,MATCH(1,(GMW!$LQ$2:$LQ$60=K$3)*(GMW!$LP$2:$LP$60=K$4)*(GMW!$LR$2:$LR$60=K$1),0),$C24-1966)} -> 223815 | ... AG24: {=INDEX(GMW!$A$2:$LR$60,MATCH(1,(GMW!$LQ$2:$LQ$60=AG$3)*(GMW!$LP$2:$LP$60=AG$4)*(GMW!$LR$2:$LR$60=AG$1),0),$C24-1966)} -> 0.001
B25: =B21+1 -> 1977 | C25: =+C24+1 -> 1991 | D25: {=INDEX(GMW!$A$2:$LR$60,MATCH(1,(GMW!$LQ$2:$LQ$60=D$3)*(GMW!$LP$2:$LP$60=D$4)*(GMW!$LR$2:$LR$60=D$1),0),$C25-1966)} -> 225295 | E25: {=INDEX(GMW!$A$2:$LR$60,MATCH(1,(GMW!$LQ$2:$LQ$60=E$3)*(GMW!$LP$2:$LP$60=E$4)*(GMW!$LR$2:$LR$60=E$1),0),$C25-1966)} -> 225295 | F25: {=INDEX(GMW!$A$2:$LR$60,MATCH(1,(GMW!$LQ$2:$LQ$60=F$3)*(GMW!$LP$2:$LP$60=F$4)*(GMW!$LR$2:$LR$60=F$1),0),$C25-1966)} -> 225295 | G25: {=INDEX(GMW!$A$2:$LR$60,MATCH(1,(GMW!$LQ$2:$LQ$60=G$3)*(GMW!$LP$2:$LP$60=G$4)*(GMW!$LR$2:$LR$60=G$1),0),$C25-1966)} -> 225295 | H25: {=INDEX(GMW!$A$2:$LR$60,MATCH(1,(GMW!$LQ$2:$LQ$60=H$3)*(GMW!$LP$2:$LP$60=H$4)*(GMW!$LR$2:$LR$60=H$1),0),$C25-1966)} -> 225295 | I25: {=INDEX(GMW!$A$2:$LR$60,MATCH(1,(GMW!$LQ$2:$LQ$60=I$3)*(GMW!$LP$2:$LP$60=I$4)*(GMW!$LR$2:$LR$60=I$1),0),$C25-1966)} -> 225295 | J25: {=INDEX(GMW!$A$2:$LR$60,MATCH(1,(GMW!$LQ$2:$LQ$60=J$3)*(GMW!$LP$2:$LP$60=J$4)*(GMW!$LR$2:$LR$60=J$1),0),$C25-1966)} -> 225295 | K25: {=INDEX(GMW!$A$2:$LR$60,MATCH(1,(GMW!$LQ$2:$LQ$60=K$3)*(GMW!$LP$2:$LP$60=K$4)*(GMW!$LR$2:$LR$60=K$1),0),$C25-1966)} -> 225295 | ... AG25: {=INDEX(GMW!$A$2:$LR$60,MATCH(1,(GMW!$LQ$2:$LQ$60=AG$3)*(GMW!$LP$2:$LP$60=AG$4)*(GMW!$LR$2:$LR$60=AG$1),0),$C25-1966)} -> 0.001
B26: =B22+1 -> 1977 | C26: =+C25+1 -> 1992 | D26: {=INDEX(GMW!$A$2:$LR$60,MATCH(1,(GMW!$LQ$2:$LQ$60=D$3)*(GMW!$LP$2:$LP$60=D$4)*(GMW!$LR$2:$LR$60=D$1),0),$C26-1966)} -> 229115 | E26: {=INDEX(GMW!$A$2:$LR$60,MATCH(1,(GMW!$LQ$2:$LQ$60=E$3)*(GMW!$LP$2:$LP$60=E$4)*(GMW!$LR$2:$LR$60=E$1),0),$C26-1966)} -> 229115 | F26: {=INDEX(GMW!$A$2:$LR$60,MATCH(1,(GMW!$LQ$2:$LQ$60=F$3)*(GMW!$LP$2:$LP$60=F$4)*(GMW!$LR$2:$LR$60=F$1),0),$C26-1966)} -> 229115 | G26: {=INDEX(GMW!$A$2:$LR$60,MATCH(1,(GMW!$LQ$2:$LQ$60=G$3)*(GMW!$LP$2:$LP$60=G$4)*(GMW!$LR$2:$LR$60=G$1),0),$C26-1966)} -> 229115 | H26: {=INDEX(GMW!$A$2:$LR$60,MATCH(1,(GMW!$LQ$2:$LQ$60=H$3)*(GMW!$LP$2:$LP$60=H$4)*(GMW!$LR$2:$LR$60=H$1),0),$C26-1966)} -> 229115 | I26: {=INDEX(GMW!$A$2:$LR$60,MATCH(1,(GMW!$LQ$2:$LQ$60=I$3)*(GMW!$LP$2:$LP$60=I$4)*(GMW!$LR$2:$LR$60=I$1),0),$C26-1966)} -> 229115 | J26: {=INDEX(GMW!$A$2:$LR$60,MATCH(1,(GMW!$LQ$2:$LQ$60=J$3)*(GMW!$LP$2:$LP$60=J$4)*(GMW!$LR$2:$LR$60=J$1),0),$C26-1966)} -> 229115 | K26: {=INDEX(GMW!$A$2:$LR$60,MATCH(1,(GMW!$LQ$2:$LQ$60=K$3)*(GMW!$LP$2:$LP$60=K$4)*(GMW!$LR$2:$LR$60=K$1),0),$C26-1966)} -> 229115 | ... AG26: {=INDEX(GMW!$A$2:$LR$60,MATCH(1,(GMW!$LQ$2:$LQ$60=AG$3)*(GMW!$LP$2:$LP$60=AG$4)*(GMW!$LR$2:$LR$60=AG$1),0),$C26-1966)} -> 0.001
A27: 1978 | B27: =B23+1 -> 1978 | C27: =+C26+1 -> 1993 | D27: {=INDEX(GMW!$A$2:$LR$60,MATCH(1,(GMW!$LQ$2:$LQ$60=D$3)*(GMW!$LP$2:$LP$60=D$4)*(GMW!$LR$2:$LR$60=D$1),0),$C27-1966)} -> 231258 | E27: {=INDEX(GMW!$A$2:$LR$60,MATCH(1,(GMW!$LQ$2:$LQ$60=E$3)*(GMW!$LP$2:$LP$60=E$4)*(GMW!$LR$2:$LR$60=E$1),0),$C27-1966)} -> 231258 | F27: {=INDEX(GMW!$A$2:$LR$60,MATCH(1,(GMW!$LQ$2:$LQ$60=F$3)*(GMW!$LP$2:$LP$60=F$4)*(GMW!$LR$2:$LR$60=F$1),0),$C27-1966)} -> 231258 | G27: {=INDEX(GMW!$A$2:$LR$60,MATCH(1,(GMW!$LQ$2:$LQ$60=G$3)*(GMW!$LP$2:$LP$60=G$4)*(GMW!$LR$2:$LR$60=G$1),0),$C27-1966)} -> 231258 | H27: {=INDEX(GMW!$A$2:$LR$60,MATCH(1,(GMW!$LQ$2:$LQ$60=H$3)*(GMW!$LP$2:$LP$60=H$4)*(GMW!$LR$2:$LR$60=H$1),0),$C27-1966)} -> 231258 | I27: {=INDEX(GMW!$A$2:$LR$60,MATCH(1,(GMW!$LQ$2:$LQ$60=I$3)*(GMW!$LP$2:$LP$60=I$4)*(GMW!$LR$2:$LR$60=I$1),0),$C27-1966)} -> 231258 | J27: {=INDEX(GMW!$A$2:$LR$60,MATCH(1,(GMW!$LQ$2:$LQ$60=J$3)*(GMW!$LP$2:$LP$60=J$4)*(GMW!$LR$2:$LR$60=J$1),0),$C27-1966)} -> 231258 | K27: {=INDEX(GMW!$A$2:$LR$60,MATCH(1,(GMW!$LQ$2:$LQ$60=K$3)*(GMW!$LP$2:$LP$60=K$4)*(GMW!$LR$2:$LR$60=K$1),0),$C27-1966)} -> 231258 | ... AG27: {=INDEX(GMW!$A$2:$LR$60,MATCH(1,(GMW!$LQ$2:$LQ$60=AG$3)*(GMW!$LP$2:$LP$60=AG$4)*(GMW!$LR$2:$LR$60=AG$1),0),$C27-1966)} -> 0.001
B28: =B24+1 -> 1978 | C28: =+C27+1 -> 1994 | D28: {=INDEX(GMW!$A$2:$LR$60,MATCH(1,(GMW!$LQ$2:$LQ$60=D$3)*(GMW!$LP$2:$LP$60=D$4)*(GMW!$LR$2:$LR$60=D$1),0),$C28-1966)} -> 233910 | E28: {=INDEX(GMW!$A$2:$LR$60,MATCH(1,(GMW!$LQ$2:$LQ$60=E$3)*(GMW!$LP$2:$LP$60=E$4)*(GMW!$LR$2:$LR$60=E$1),0),$C28-1966)} -> 233910 | F28: {=INDEX(GMW!$A$2:$LR$60,MATCH(1,(GMW!$LQ$2:$LQ$60=F$3)*(GMW!$LP$2:$LP$60=F$4)*(GMW!$LR$2:$LR$60=F$1),0),$C28-1966)} -> 233910 | G28: {=INDEX(GMW!$A$2:$LR$60,MATCH(1,(GMW!$LQ$2:$LQ$60=G$3)*(GMW!$LP$2:$LP$60=G$4)*(GMW!$LR$2:$LR$60=G$1),0),$C28-1966)} -> 233910 | H28: {=INDEX(GMW!$A$2:$LR$60,MATCH(1,(GMW!$LQ$2:$LQ$60=H$3)*(GMW!$LP$2:$LP$60=H$4)*(GMW!$LR$2:$LR$60=H$1),0),$C28-1966)} -> 233910 | I28: {=INDEX(GMW!$A$2:$LR$60,MATCH(1,(GMW!$LQ$2:$LQ$60=I$3)*(GMW!$LP$2:$LP$60=I$4)*(GMW!$LR$2:$LR$60=I$1),0),$C28-1966)} -> 233910 | J28: {=INDEX(GMW!$A$2:$LR$60,MATCH(1,(GMW!$LQ$2:$LQ$60=J$3)*(GMW!$LP$2:$LP$60=J$4)*(GMW!$LR$2:$LR$60=J$1),0),$C28-1966)} -> 233910 | K28: {=INDEX(GMW!$A$2:$LR$60,MATCH(1,(GMW!$LQ$2:$LQ$60=K$3)*(GMW!$LP$2:$LP$60=K$4)*(GMW!$LR$2:$LR$60=K$1),0),$C28-1966)} -> 233910 | ... AG28: {=INDEX(GMW!$A$2:$LR$60,MATCH(1,(GMW!$LQ$2:$LQ$60=AG$3)*(GMW!$LP$2:$LP$60=AG$4)*(GMW!$LR$2:$LR$60=AG$1),0),$C28-1966)} -> 0.001
B29: =B25+1 -> 1978 | C29: =+C28+1 -> 1995 | D29: {=INDEX(GMW!$A$2:$LR$60,MATCH(1,(GMW!$LQ$2:$LQ$60=D$3)*(GMW!$LP$2:$LP$60=D$4)*(GMW!$LR$2:$LR$60=D$1),0),$C29-1966)} -> 237107 | E29: {=INDEX(GMW!$A$2:$LR$60,MATCH(1,(GMW!$LQ$2:$LQ$60=E$3)*(GMW!$LP$2:$LP$60=E$4)*(GMW!$LR$2:$LR$60=E$1),0),$C29-1966)} -> 237107 | F29: {=INDEX(GMW!$A$2:$LR$60,MATCH(1,(GMW!$LQ$2:$LQ$60=F$3)*(GMW!$LP$2:$LP$60=F$4)*(GMW!$LR$2:$LR$60=F$1),0),$C29-1966)} -> 237107 | G29: {=INDEX(GMW!$A$2:$LR$60,MATCH(1,(GMW!$LQ$2:$LQ$60=G$3)*(GMW!$LP$2:$LP$60=G$4)*(GMW!$LR$2:$LR$60=G$1),0),$C29-1966)} -> 237107 | H29: {=INDEX(GMW!$A$2:$LR$60,MATCH(1,(GMW!$LQ$2:$LQ$60=H$3)*(GMW!$LP$2:$LP$60=H$4)*(GMW!$LR$2:$LR$60=H$1),0),$C29-1966)} -> 237107 | I29: {=INDEX(GMW!$A$2:$LR$60,MATCH(1,(GMW!$LQ$2:$LQ$60=I$3)*(GMW!$LP$2:$LP$60=I$4)*(GMW!$LR$2:$LR$60=I$1),0),$C29-1966)} -> 237107 | J29: {=INDEX(GMW!$A$2:$LR$60,MATCH(1,(GMW!$LQ$2:$LQ$60=J$3)*(GMW!$LP$2:$LP$60=J$4)*(GMW!$LR$2:$LR$60=J$1),0),$C29-1966)} -> 237107 | K29: {=INDEX(GMW!$A$2:$LR$60,MATCH(1,(GMW!$LQ$2:$LQ$60=K$3)*(GMW!$LP$2:$LP$60=K$4)*(GMW!$LR$2:$LR$60=K$1),0),$C29-1966)} -> 237107 | ... AG29: {=INDEX(GMW!$A$2:$LR$60,MATCH(1,(GMW!$LQ$2:$LQ$60=AG$3)*(GMW!$LP$2:$LP$60=AG$4)*(GMW!$LR$2:$LR$60=AG$1),0),$C29-1966)} -> 0.001
B30: =B26+1 -> 1978 | C30: =+C29+1 -> 1996 | D30: {=INDEX(GMW!$A$2:$LR$60,MATCH(1,(GMW!$LQ$2:$LQ$60=D$3)*(GMW!$LP$2:$LP$60=D$4)*(GMW!$LR$2:$LR$60=D$1),0),$C30-1966)} -> 239186 | E30: {=INDEX(GMW!$A$2:$LR$60,MATCH(1,(GMW!$LQ$2:$LQ$60=E$3)*(GMW!$LP$2:$LP$60=E$4)*(GMW!$LR$2:$LR$60=E$1),0),$C30-1966)} -> 239186 | F30: {=INDEX(GMW!$A$2:$LR$60,MATCH(1,(GMW!$LQ$2:$LQ$60=F$3)*(GMW!$LP$2:$LP$60=F$4)*(GMW!$LR$2:$LR$60=F$1),0),$C30-1966)} -> 239186 | G30: {=INDEX(GMW!$A$2:$LR$60,MATCH(1,(GMW!$LQ$2:$LQ$60=G$3)*(GMW!$LP$2:$LP$60=G$4)*(GMW!$LR$2:$LR$60=G$1),0),$C30-1966)} -> 239186 | H30: {=INDEX(GMW!$A$2:$LR$60,MATCH(1,(GMW!$LQ$2:$LQ$60=H$3)*(GMW!$LP$2:$LP$60=H$4)*(GMW!$LR$2:$LR$60=H$1),0),$C30-1966)} -> 239186 | I30: {=INDEX(GMW!$A$2:$LR$60,MATCH(1,(GMW!$LQ$2:$LQ$60=I$3)*(GMW!$LP$2:$LP$60=I$4)*(GMW!$LR$2:$LR$60=I$1),0),$C30-1966)} -> 239186 | J30: {=INDEX(GMW!$A$2:$LR$60,MATCH(1,(GMW!$LQ$2:$LQ$60=J$3)*(GMW!$LP$2:$LP$60=J$4)*(GMW!$LR$2:$LR$60=J$1),0),$C30-1966)} -> 239186 | K30: {=INDEX(GMW!$A$2:$LR$60,MATCH(1,(GMW!$LQ$2:$LQ$60=K$3)*(GMW!$LP$2:$LP$60=K$4)*(GMW!$LR$2:$LR$60=K$1),0),$C30-1966)} -> 239186 | ... AG30: {=INDEX(GMW!$A$2:$LR$60,MATCH(1,(GMW!$LQ$2:$LQ$60=AG$3)*(GMW!$LP$2:$LP$60=AG$4)*(GMW!$LR$2:$LR$60=AG$1),0),$C30-1966)} -> 0.001
A31: 1979 | B31: =B27+1 -> 1979 | C31: =+C30+1 -> 1997 | D31: {=INDEX(GMW!$A$2:$LR$60,MATCH(1,(GMW!$LQ$2:$LQ$60=D$3)*(GMW!$LP$2:$LP$60=D$4)*(GMW!$LR$2:$LR$60=D$1),0),$C31-1966)} -> 238472 | E31: {=INDEX(GMW!$A$2:$LR$60,MATCH(1,(GMW!$LQ$2:$LQ$60=E$3)*(GMW!$LP$2:$LP$60=E$4)*(GMW!$LR$2:$LR$60=E$1),0),$C31-1966)} -> 238472 | F31: {=INDEX(GMW!$A$2:$LR$60,MATCH(1,(GMW!$LQ$2:$LQ$60=F$3)*(GMW!$LP$2:$LP$60=F$4)*(GMW!$LR$2:$LR$60=F$1),0),$C31-1966)} -> 238472 | G31: {=INDEX(GMW!$A$2:$LR$60,MATCH(1,(GMW!$LQ$2:$LQ$60=G$3)*(GMW!$LP$2:$LP$60=G$4)*(GMW!$LR$2:$LR$60=G$1),0),$C31-1966)} -> 238472 | H31: {=INDEX(GMW!$A$2:$LR$60,MATCH(1,(GMW!$LQ$2:$LQ$60=H$3)*(GMW!$LP$2:$LP$60=H$4)*(GMW!$LR$2:$LR$60=H$1),0),$C31-1966)} -> 238472 | I31: {=INDEX(GMW!$A$2:$LR$60,MATCH(1,(GMW!$LQ$2:$LQ$60=I$3)*(GMW!$LP$2:$LP$60=I$4)*(GMW!$LR$2:$LR$60=I$1),0),$C31-1966)} -> 238472 | J31: {=INDEX(GMW!$A$2:$LR$60,MATCH(1,(GMW!$LQ$2:$LQ$60=J$3)*(GMW!$LP$2:$LP$60=J$4)*(GMW!$LR$2:$LR$60=J$1),0),$C31-1966)} -> 238472 | K31: {=INDEX(GMW!$A$2:$LR$60,MATCH(1,(GMW!$LQ$2:$LQ$60=K$3)*(GMW!$LP$2:$LP$60=K$4)*(GMW!$LR$2:$LR$60=K$1),0),$C31-1966)} -> 238472 | ... AG31: {=INDEX(GMW!$A$2:$LR$60,MATCH(1,(GMW!$LQ$2:$LQ$60=AG$3)*(GMW!$LP$2:$LP$60=AG$4)*(GMW!$LR$2:$LR$60=AG$1),0),$C31-1966)} -> 0.001
B32: =B28+1 -> 1979 | C32: =+C31+1 -> 1998 | D32: {=INDEX(GMW!$A$2:$LR$60,MATCH(1,(GMW!$LQ$2:$LQ$60=D$3)*(GMW!$LP$2:$LP$60=D$4)*(GMW!$LR$2:$LR$60=D$1),0),$C32-1966)} -> 248867 | E32: {=INDEX(GMW!$A$2:$LR$60,MATCH(1,(GMW!$LQ$2:$LQ$60=E$3)*(GMW!$LP$2:$LP$60=E$4)*(GMW!$LR$2:$LR$60=E$1),0),$C32-1966)} -> 248867 | F32: {=INDEX(GMW!$A$2:$LR$60,MATCH(1,(GMW!$LQ$2:$LQ$60=F$3)*(GMW!$LP$2:$LP$60=F$4)*(GMW!$LR$2:$LR$60=F$1),0),$C32-1966)} -> 248867 | G32: {=INDEX(GMW!$A$2:$LR$60,MATCH(1,(GMW!$LQ$2:$LQ$60=G$3)*(GMW!$LP$2:$LP$60=G$4)*(GMW!$LR$2:$LR$60=G$1),0),$C32-1966)} -> 248867 | H32: {=INDEX(GMW!$A$2:$LR$60,MATCH(1,(GMW!$LQ$2:$LQ$60=H$3)*(GMW!$LP$2:$LP$60=H$4)*(GMW!$LR$2:$LR$60=H$1),0),$C32-1966)} -> 248867 | I32: {=INDEX(GMW!$A$2:$LR$60,MATCH(1,(GMW!$LQ$2:$LQ$60=I$3)*(GMW!$LP$2:$LP$60=I$4)*(GMW!$LR$2:$LR$60=I$1),0),$C32-1966)} -> 248867 | J32: {=INDEX(GMW!$A$2:$LR$60,MATCH(1,(GMW!$LQ$2:$LQ$60=J$3)*(GMW!$LP$2:$LP$60=J$4)*(GMW!$LR$2:$LR$60=J$1),0),$C32-1966)} -> 248867 | K32: {=INDEX(GMW!$A$2:$LR$60,MATCH(1,(GMW!$LQ$2:$LQ$60=K$3)*(GMW!$LP$2:$LP$60=K$4)*(GMW!$LR$2:$LR$60=K$1),0),$C32-1966)} -> 248867 | ... AG32: {=INDEX(GMW!$A$2:$LR$60,MATCH(1,(GMW!$LQ$2:$LQ$60=AG$3)*(GMW!$LP$2:$LP$60=AG$4)*(GMW!$LR$2:$LR$60=AG$1),0),$C32-1966)} -> 0.001
B33: =B29+1 -> 1979 | C33: =+C32+1 -> 1999 | D33: {=INDEX(GMW!$A$2:$LR$60,MATCH(1,(GMW!$LQ$2:$LQ$60=D$3)*(GMW!$LP$2:$LP$60=D$4)*(GMW!$LR$2:$LR$60=D$1),0),$C33-1966)} -> 243369 | E33: {=INDEX(GMW!$A$2:$LR$60,MATCH(1,(GMW!$LQ$2:$LQ$60=E$3)*(GMW!$LP$2:$LP$60=E$4)*(GMW!$LR$2:$LR$60=E$1),0),$C33-1966)} -> 243369 | F33: {=INDEX(GMW!$A$2:$LR$60,MATCH(1,(GMW!$LQ$2:$LQ$60=F$3)*(GMW!$LP$2:$LP$60=F$4)*(GMW!$LR$2:$LR$60=F$1),0),$C33-1966)} -> 243369 | G33: {=INDEX(GMW!$A$2:$LR$60,MATCH(1,(GMW!$LQ$2:$LQ$60=G$3)*(GMW!$LP$2:$LP$60=G$4)*(GMW!$LR$2:$LR$60=G$1),0),$C33-1966)} -> 243369 | H33: {=INDEX(GMW!$A$2:$LR$60,MATCH(1,(GMW!$LQ$2:$LQ$60=H$3)*(GMW!$LP$2:$LP$60=H$4)*(GMW!$LR$2:$LR$60=H$1),0),$C33-1966)} -> 243369 | I33: {=INDEX(GMW!$A$2:$LR$60,MATCH(1,(GMW!$LQ$2:$LQ$60=I$3)*(GMW!$LP$2:$LP$60=I$4)*(GMW!$LR$2:$LR$60=I$1),0),$C33-1966)} -> 243369 | J33: {=INDEX(GMW!$A$2:$LR$60,MATCH(1,(GMW!$LQ$2:$LQ$60=J$3)*(GMW!$LP$2:$LP$60=J$4)*(GMW!$LR$2:$LR$60=J$1),0),$C33-1966)} -> 243369 | K33: {=INDEX(GMW!$A$2:$LR$60,MATCH(1,(GMW!$LQ$2:$LQ$60=K$3)*(GMW!$LP$2:$LP$60=K$4)*(GMW!$LR$2:$LR$60=K$1),0),$C33-1966)} -> 243369 | ... AG33: {=INDEX(GMW!$A$2:$LR$60,MATCH(1,(GMW!$LQ$2:$LQ$60=AG$3)*(GMW!$LP$2:$LP$60=AG$4)*(GMW!$LR$2:$LR$60=AG$1),0),$C33-1966)} -> 0.001
B34: =B30+1 -> 1979 | C34: =+C33+1 -> 2000 | D34: {=INDEX(GMW!$A$2:$LR$60,MATCH(1,(GMW!$LQ$2:$LQ$60=D$3)*(GMW!$LP$2:$LP$60=D$4)*(GMW!$LR$2:$LR$60=D$1),0),$C34-1966)} -> 245858 | E34: {=INDEX(GMW!$A$2:$LR$60,MATCH(1,(GMW!$LQ$2:$LQ$60=E$3)*(GMW!$LP$2:$LP$60=E$4)*(GMW!$LR$2:$LR$60=E$1),0),$C34-1966)} -> 245858 | F34: {=INDEX(GMW!$A$2:$LR$60,MATCH(1,(GMW!$LQ$2:$LQ$60=F$3)*(GMW!$LP$2:$LP$60=F$4)*(GMW!$LR$2:$LR$60=F$1),0),$C34-1966)} -> 245858 | G34: {=INDEX(GMW!$A$2:$LR$60,MATCH(1,(GMW!$LQ$2:$LQ$60=G$3)*(GMW!$LP$2:$LP$60=G$4)*(GMW!$LR$2:$LR$60=G$1),0),$C34-1966)} -> 245858 | H34: {=INDEX(GMW!$A$2:$LR$60,MATCH(1,(GMW!$LQ$2:$LQ$60=H$3)*(GMW!$LP$2:$LP$60=H$4)*(GMW!$LR$2:$LR$60=H$1),0),$C34-1966)} -> 245858 | I34: {=INDEX(GMW!$A$2:$LR$60,MATCH(1,(GMW!$LQ$2:$LQ$60=I$3)*(GMW!$LP$2:$LP$60=I$4)*(GMW!$LR$2:$LR$60=I$1),0),$C34-1966)} -> 245858 | J34: {=INDEX(GMW!$A$2:$LR$60,MATCH(1,(GMW!$LQ$2:$LQ$60=J$3)*(GMW!$LP$2:$LP$60=J$4)*(GMW!$LR$2:$LR$60=J$1),0),$C34-1966)} -> 245858 | K34: {=INDEX(GMW!$A$2:$LR$60,MATCH(1,(GMW!$LQ$2:$LQ$60=K$3)*(GMW!$LP$2:$LP$60=K$4)*(GMW!$LR$2:$LR$60=K$1),0),$C34-1966)} -> 245858 | ... AG34: {=INDEX(GMW!$A$2:$LR$60,MATCH(1,(GMW!$LQ$2:$LQ$60=AG$3)*(GMW!$LP$2:$LP$60=AG$4)*(GMW!$LR$2:$LR$60=AG$1),0),$C34-1966)} -> 0.001
A35: 1980 | B35: =B31+1 -> 1980 | C35: =+C34+1 -> 2001 | D35: {=INDEX(GMW!$A$2:$LR$60,MATCH(1,(GMW!$LQ$2:$LQ$60=D$3)*(GMW!$LP$2:$LP$60=D$4)*(GMW!$LR$2:$LR$60=D$1),0),$C35-1966)} -> 243513 | E35: {=INDEX(GMW!$A$2:$LR$60,MATCH(1,(GMW!$LQ$2:$LQ$60=E$3)*(GMW!$LP$2:$LP$60=E$4)*(GMW!$LR$2:$LR$60=E$1),0),$C35-1966)} -> 243513 | F35: {=INDEX(GMW!$A$2:$LR$60,MATCH(1,(GMW!$LQ$2:$LQ$60=F$3)*(GMW!$LP$2:$LP$60=F$4)*(GMW!$LR$2:$LR$60=F$1),0),$C35-1966)} -> 243513 | G35: {=INDEX(GMW!$A$2:$LR$60,MATCH(1,(GMW!$LQ$2:$LQ$60=G$3)*(GMW!$LP$2:$LP$60=G$4)*(GMW!$LR$2:$LR$60=G$1),0),$C35-1966)} -> 243513 | H35: {=INDEX(GMW!$A$2:$LR$60,MATCH(1,(GMW!$LQ$2:$LQ$60=H$3)*(GMW!$LP$2:$LP$60=H$4)*(GMW!$LR$2:$LR$60=H$1),0),$C35-1966)} -> 243513 | I35: {=INDEX(GMW!$A$2:$LR$60,MATCH(1,(GMW!$LQ$2:$LQ$60=I$3)*(GMW!$LP$2:$LP$60=I$4)*(GMW!$LR$2:$LR$60=I$1),0),$C35-1966)} -> 243513 | J35: {=INDEX(GMW!$A$2:$LR$60,MATCH(1,(GMW!$LQ$2:$LQ$60=J$3)*(GMW!$LP$2:$LP$60=J$4)*(GMW!$LR$2:$LR$60=J$1),0),$C35-1966)} -> 243513 | K35: {=INDEX(GMW!$A$2:$LR$60,MATCH(1,(GMW!$LQ$2:$LQ$60=K$3)*(GMW!$LP$2:$LP$60=K$4)*(GMW!$LR$2:$LR$60=K$1),0),$C35-1966)} -> 243513 | ... AG35: {=INDEX(GMW!$A$2:$LR$60,MATCH(1,(GMW!$LQ$2:$LQ$60=AG$3)*(GMW!$LP$2:$LP$60=AG$4)*(GMW!$LR$2:$LR$60=AG$1),0),$C35-1966)} -> 0.001
B36: =B32+1 -> 1980 | C36: =+C35+1 -> 2002 | D36: {=INDEX(GMW!$A$2:$LR$60,MATCH(1,(GMW!$LQ$2:$LQ$60=D$3)*(GMW!$LP$2:$LP$60=D$4)*(GMW!$LR$2:$LR$60=D$1),0),$C36-1966)} -> 238722 | E36: {=INDEX(GMW!$A$2:$LR$60,MATCH(1,(GMW!$LQ$2:$LQ$60=E$3)*(GMW!$LP$2:$LP$60=E$4)*(GMW!$LR$2:$LR$60=E$1),0),$C36-1966)} -> 238722 | F36: {=INDEX(GMW!$A$2:$LR$60,MATCH(1,(GMW!$LQ$2:$LQ$60=F$3)*(GMW!$LP$2:$LP$60=F$4)*(GMW!$LR$2:$LR$60=F$1),0),$C36-1966)} -> 238722 | G36: {=INDEX(GMW!$A$2:$LR$60,MATCH(1,(GMW!$LQ$2:$LQ$60=G$3)*(GMW!$LP$2:$LP$60=G$4)*(GMW!$LR$2:$LR$60=G$1),0),$C36-1966)} -> 238722 | H36: {=INDEX(GMW!$A$2:$LR$60,MATCH(1,(GMW!$LQ$2:$LQ$60=H$3)*(GMW!$LP$2:$LP$60=H$4)*(GMW!$LR$2:$LR$60=H$1),0),$C36-1966)} -> 238722 | I36: {=INDEX(GMW!$A$2:$LR$60,MATCH(1,(GMW!$LQ$2:$LQ$60=I$3)*(GMW!$LP$2:$LP$60=I$4)*(GMW!$LR$2:$LR$60=I$1),0),$C36-1966)} -> 238722 | J36: {=INDEX(GMW!$A$2:$LR$60,MATCH(1,(GMW!$LQ$2:$LQ$60=J$3)*(GMW!$LP$2:$LP$60=J$4)*(GMW!$LR$2:$LR$60=J$1),0),$C36-1966)} -> 238722 | K36: {=INDEX(GMW!$A$2:$LR$60,MATCH(1,(GMW!$LQ$2:$LQ$60=K$3)*(GMW!$LP$2:$LP$60=K$4)*(GMW!$LR$2:$LR$60=K$1),0),$C36-1966)} -> 238722 | ... AG36: {=INDEX(GMW!$A$2:$LR$60,MATCH(1,(GMW!$LQ$2:$LQ$60=AG$3)*(GMW!$LP$2:$LP$60=AG$4)*(GMW!$LR$2:$LR$60=AG$1),0),$C36-1966)} -> 0.001
B37: =B33+1 -> 1980 | C37: =+C36+1 -> 2003 | D37: {=INDEX(GMW!$A$2:$LR$60,MATCH(1,(GMW!$LQ$2:$LQ$60=D$3)*(GMW!$LP$2:$LP$60=D$4)*(GMW!$LR$2:$LR$60=D$1),0),$C37-1966)} -> 238432 | E37: {=INDEX(GMW!$A$2:$LR$60,MATCH(1,(GMW!$LQ$2:$LQ$60=E$3)*(GMW!$LP$2:$LP$60=E$4)*(GMW!$LR$2:$LR$60=E$1),0),$C37-1966)} -> 238432 | F37: {=INDEX(GMW!$A$2:$LR$60,MATCH(1,(GMW!$LQ$2:$LQ$60=F$3)*(GMW!$LP$2:$LP$60=F$4)*(GMW!$LR$2:$LR$60=F$1),0),$C37-1966)} -> 238432 | G37: {=INDEX(GMW!$A$2:$LR$60,MATCH(1,(GMW!$LQ$2:$LQ$60=G$3)*(GMW!$LP$2:$LP$60=G$4)*(GMW!$LR$2:$LR$60=G$1),0),$C37-1966)} -> 238432 | H37: {=INDEX(GMW!$A$2:$LR$60,MATCH(1,(GMW!$LQ$2:$LQ$60=H$3)*(GMW!$LP$2:$LP$60=H$4)*(GMW!$LR$2:$LR$60=H$1),0),$C37-1966)} -> 238432 | I37: {=INDEX(GMW!$A$2:$LR$60,MATCH(1,(GMW!$LQ$2:$LQ$60=I$3)*(GMW!$LP$2:$LP$60=I$4)*(GMW!$LR$2:$LR$60=I$1),0),$C37-1966)} -> 238432 | J37: {=INDEX(GMW!$A$2:$LR$60,MATCH(1,(GMW!$LQ$2:$LQ$60=J$3)*(GMW!$LP$2:$LP$60=J$4)*(GMW!$LR$2:$LR$60=J$1),0),$C37-1966)} -> 238432 | K37: {=INDEX(GMW!$A$2:$LR$60,MATCH(1,(GMW!$LQ$2:$LQ$60=K$3)*(GMW!$LP$2:$LP$60=K$4)*(GMW!$LR$2:$LR$60=K$1),0),$C37-1966)} -> 238432 | ... AG37: {=INDEX(GMW!$A$2:$LR$60,MATCH(1,(GMW!$LQ$2:$LQ$60=AG$3)*(GMW!$LP$2:$LP$60=AG$4)*(GMW!$LR$2:$LR$60=AG$1),0),$C37-1966)} -> 0.001
B38: =B34+1 -> 1980 | C38: =+C37+1 -> 2004 | D38: {=INDEX(GMW!$A$2:$LR$60,MATCH(1,(GMW!$LQ$2:$LQ$60=D$3)*(GMW!$LP$2:$LP$60=D$4)*(GMW!$LR$2:$LR$60=D$1),0),$C38-1966)} -> 235866 | E38: {=INDEX(GMW!$A$2:$LR$60,MATCH(1,(GMW!$LQ$2:$LQ$60=E$3)*(GMW!$LP$2:$LP$60=E$4)*(GMW!$LR$2:$LR$60=E$1),0),$C38-1966)} -> 235866 | F38: {=INDEX(GMW!$A$2:$LR$60,MATCH(1,(GMW!$LQ$2:$LQ$60=F$3)*(GMW!$LP$2:$LP$60=F$4)*(GMW!$LR$2:$LR$60=F$1),0),$C38-1966)} -> 235866 | G38: {=INDEX(GMW!$A$2:$LR$60,MATCH(1,(GMW!$LQ$2:$LQ$60=G$3)*(GMW!$LP$2:$LP$60=G$4)*(GMW!$LR$2:$LR$60=G$1),0),$C38-1966)} -> 235866 | H38: {=INDEX(GMW!$A$2:$LR$60,MATCH(1,(GMW!$LQ$2:$LQ$60=H$3)*(GMW!$LP$2:$LP$60=H$4)*(GMW!$LR$2:$LR$60=H$1),0),$C38-1966)} -> 235866 | I38: {=INDEX(GMW!$A$2:$LR$60,MATCH(1,(GMW!$LQ$2:$LQ$60=I$3)*(GMW!$LP$2:$LP$60=I$4)*(GMW!$LR$2:$LR$60=I$1),0),$C38-1966)} -> 235866 | J38: {=INDEX(GMW!$A$2:$LR$60,MATCH(1,(GMW!$LQ$2:$LQ$60=J$3)*(GMW!$LP$2:$LP$60=J$4)*(GMW!$LR$2:$LR$60=J$1),0),$C38-1966)} -> 235866 | K38: {=INDEX(GMW!$A$2:$LR$60,MATCH(1,(GMW!$LQ$2:$LQ$60=K$3)*(GMW!$LP$2:$LP$60=K$4)*(GMW!$LR$2:$LR$60=K$1),0),$C38-1966)} -> 235866 | ... AG38: {=INDEX(GMW!$A$2:$LR$60,MATCH(1,(GMW!$LQ$2:$LQ$60=AG$3)*(GMW!$LP$2:$LP$60=AG$4)*(GMW!$LR$2:$LR$60=AG$1),0),$C38-1966)} -> 0.001
A39: 1981 | B39: =B35+1 -> 1981 | C39: =+C38+1 -> 2005 | D39: {=INDEX(GMW!$A$2:$LR$60,MATCH(1,(GMW!$LQ$2:$LQ$60=D$3)*(GMW!$LP$2:$LP$60=D$4)*(GMW!$LR$2:$LR$60=D$1),0),$C39-1966)} -> 235712 | E39: {=INDEX(GMW!$A$2:$LR$60,MATCH(1,(GMW!$LQ$2:$LQ$60=E$3)*(GMW!$LP$2:$LP$60=E$4)*(GMW!$LR$2:$LR$60=E$1),0),$C39-1966)} -> 235712 | F39: {=INDEX(GMW!$A$2:$LR$60,MATCH(1,(GMW!$LQ$2:$LQ$60=F$3)*(GMW!$LP$2:$LP$60=F$4)*(GMW!$LR$2:$LR$60=F$1),0),$C39-1966)} -> 235712 | G39: {=INDEX(GMW!$A$2:$LR$60,MATCH(1,(GMW!$LQ$2:$LQ$60=G$3)*(GMW!$LP$2:$LP$60=G$4)*(GMW!$LR$2:$LR$60=G$1),0),$C39-1966)} -> 235712 | H39: {=INDEX(GMW!$A$2:$LR$60,MATCH(1,(GMW!$LQ$2:$LQ$60=H$3)*(GMW!$LP$2:$LP$60=H$4)*(GMW!$LR$2:$LR$60=H$1),0),$C39-1966)} -> 235712 | I39: {=INDEX(GMW!$A$2:$LR$60,MATCH(1,(GMW!$LQ$2:$LQ$60=I$3)*(GMW!$LP$2:$LP$60=I$4)*(GMW!$LR$2:$LR$60=I$1),0),$C39-1966)} -> 235712 | J39: {=INDEX(GMW!$A$2:$LR$60,MATCH(1,(GMW!$LQ$2:$LQ$60=J$3)*(GMW!$LP$2:$LP$60=J$4)*(GMW!$LR$2:$LR$60=J$1),0),$C39-1966)} -> 235712 | K39: {=INDEX(GMW!$A$2:$LR$60,MATCH(1,(GMW!$LQ$2:$LQ$60=K$3)*(GMW!$LP$2:$LP$60=K$4)*(GMW!$LR$2:$LR$60=K$1),0),$C39-1966)} -> 235712 | ... AG39: {=INDEX(GMW!$A$2:$LR$60,MATCH(1,(GMW!$LQ$2:$LQ$60=AG$3)*(GMW!$LP$2:$LP$60=AG$4)*(GMW!$LR$2:$LR$60=AG$1),0),$C39-1966)} -> 0.001
B40: =B36+1 -> 1981 | C40: =+C39+1 -> 2006 | D40: {=INDEX(GMW!$A$2:$LR$60,MATCH(1,(GMW!$LQ$2:$LQ$60=D$3)*(GMW!$LP$2:$LP$60=D$4)*(GMW!$LR$2:$LR$60=D$1),0),$C40-1966)} -> 236272 | E40: {=INDEX(GMW!$A$2:$LR$60,MATCH(1,(GMW!$LQ$2:$LQ$60=E$3)*(GMW!$LP$2:$LP$60=E$4)*(GMW!$LR$2:$LR$60=E$1),0),$C40-1966)} -> 236272 | F40: {=INDEX(GMW!$A$2:$LR$60,MATCH(1,(GMW!$LQ$2:$LQ$60=F$3)*(GMW!$LP$2:$LP$60=F$4)*(GMW!$LR$2:$LR$60=F$1),0),$C40-1966)} -> 236272 | G40: {=INDEX(GMW!$A$2:$LR$60,MATCH(1,(GMW!$LQ$2:$LQ$60=G$3)*(GMW!$LP$2:$LP$60=G$4)*(GMW!$LR$2:$LR$60=G$1),0),$C40-1966)} -> 236272 | H40: {=INDEX(GMW!$A$2:$LR$60,MATCH(1,(GMW!$LQ$2:$LQ$60=H$3)*(GMW!$LP$2:$LP$60=H$4)*(GMW!$LR$2:$LR$60=H$1),0),$C40-1966)} -> 236272 | I40: {=INDEX(GMW!$A$2:$LR$60,MATCH(1,(GMW!$LQ$2:$LQ$60=I$3)*(GMW!$LP$2:$LP$60=I$4)*(GMW!$LR$2:$LR$60=I$1),0),$C40-1966)} -> 236272 | J40: {=INDEX(GMW!$A$2:$LR$60,MATCH(1,(GMW!$LQ$2:$LQ$60=J$3)*(GMW!$LP$2:$LP$60=J$4)*(GMW!$LR$2:$LR$60=J$1),0),$C40-1966)} -> 236272 | K40: {=INDEX(GMW!$A$2:$LR$60,MATCH(1,(GMW!$LQ$2:$LQ$60=K$3)*(GMW!$LP$2:$LP$60=K$4)*(GMW!$LR$2:$LR$60=K$1),0),$C40-1966)} -> 236272 | ... AG40: {=INDEX(GMW!$A$2:$LR$60,MATCH(1,(GMW!$LQ$2:$LQ$60=AG$3)*(GMW!$LP$2:$LP$60=AG$4)*(GMW!$LR$2:$LR$60=AG$1),0),$C40-1966)} -> 0.001
B41: =B37+1 -> 1981 | C41: =+C40+1 -> 2007 | D41: {=INDEX(GMW!$A$2:$LR$60,MATCH(1,(GMW!$LQ$2:$LQ$60=D$3)*(GMW!$LP$2:$LP$60=D$4)*(GMW!$LR$2:$LR$60=D$1),0),$C41-1966)} -> 238846 | E41: {=INDEX(GMW!$A$2:$LR$60,MATCH(1,(GMW!$LQ$2:$LQ$60=E$3)*(GMW!$LP$2:$LP$60=E$4)*(GMW!$LR$2:$LR$60=E$1),0),$C41-1966)} -> 238846 | F41: {=INDEX(GMW!$A$2:$LR$60,MATCH(1,(GMW!$LQ$2:$LQ$60=F$3)*(GMW!$LP$2:$LP$60=F$4)*(GMW!$LR$2:$LR$60=F$1),0),$C41-1966)} -> 238846 | G41: {=INDEX(GMW!$A$2:$LR$60,MATCH(1,(GMW!$LQ$2:$LQ$60=G$3)*(GMW!$LP$2:$LP$60=G$4)*(GMW!$LR$2:$LR$60=G$1),0),$C41-1966)} -> 238846 | H41: {=INDEX(GMW!$A$2:$LR$60,MATCH(1,(GMW!$LQ$2:$LQ$60=H$3)*(GMW!$LP$2:$LP$60=H$4)*(GMW!$LR$2:$LR$60=H$1),0),$C41-1966)} -> 238846 | I41: {=INDEX(GMW!$A$2:$LR$60,MATCH(1,(GMW!$LQ$2:$LQ$60=I$3)*(GMW!$LP$2:$LP$60=I$4)*(GMW!$LR$2:$LR$60=I$1),0),$C41-1966)} -> 238846 | J41: {=INDEX(GMW!$A$2:$LR$60,MATCH(1,(GMW!$LQ$2:$LQ$60=J$3)*(GMW!$LP$2:$LP$60=J$4)*(GMW!$LR$2:$LR$60=J$1),0),$C41-1966)} -> 238846 | K41: {=INDEX(GMW!$A$2:$LR$60,MATCH(1,(GMW!$LQ$2:$LQ$60=K$3)*(GMW!$LP$2:$LP$60=K$4)*(GMW!$LR$2:$LR$60=K$1),0),$C41-1966)} -> 238846 | ... AG41: {=INDEX(GMW!$A$2:$LR$60,MATCH(1,(GMW!$LQ$2:$LQ$60=AG$3)*(GMW!$LP$2:$LP$60=AG$4)*(GMW!$LR$2:$LR$60=AG$1),0),$C41-1966)} -> 0.001
B42: =B38+1 -> 1981 | C42: =+C41+1 -> 2008 | D42: {=INDEX(GMW!$A$2:$LR$60,MATCH(1,(GMW!$LQ$2:$LQ$60=D$3)*(GMW!$LP$2:$LP$60=D$4)*(GMW!$LR$2:$LR$60=D$1),0),$C42-1966)} -> 239131 | E42: {=INDEX(GMW!$A$2:$LR$60,MATCH(1,(GMW!$LQ$2:$LQ$60=E$3)*(GMW!$LP$2:$LP$60=E$4)*(GMW!$LR$2:$LR$60=E$1),0),$C42-1966)} -> 239131 | F42: {=INDEX(GMW!$A$2:$LR$60,MATCH(1,(GMW!$LQ$2:$LQ$60=F$3)*(GMW!$LP$2:$LP$60=F$4)*(GMW!$LR$2:$LR$60=F$1),0),$C42-1966)} -> 239131 | G42: {=INDEX(GMW!$A$2:$LR$60,MATCH(1,(GMW!$LQ$2:$LQ$60=G$3)*(GMW!$LP$2:$LP$60=G$4)*(GMW!$LR$2:$LR$60=G$1),0),$C42-1966)} -> 239131 | H42: {=INDEX(GMW!$A$2:$LR$60,MATCH(1,(GMW!$LQ$2:$LQ$60=H$3)*(GMW!$LP$2:$LP$60=H$4)*(GMW!$LR$2:$LR$60=H$1),0),$C42-1966)} -> 239131 | I42: {=INDEX(GMW!$A$2:$LR$60,MATCH(1,(GMW!$LQ$2:$LQ$60=I$3)*(GMW!$LP$2:$LP$60=I$4)*(GMW!$LR$2:$LR$60=I$1),0),$C42-1966)} -> 239131 | J42: {=INDEX(GMW!$A$2:$LR$60,MATCH(1,(GMW!$LQ$2:$LQ$60=J$3)*(GMW!$LP$2:$LP$60=J$4)*(GMW!$LR$2:$LR$60=J$1),0),$C42-1966)} -> 239131 | K42: {=INDEX(GMW!$A$2:$LR$60,MATCH(1,(GMW!$LQ$2:$LQ$60=K$3)*(GMW!$LP$2:$LP$60=K$4)*(GMW!$LR$2:$LR$60=K$1),0),$C42-1966)} -> 239131 | ... AG42: {=INDEX(GMW!$A$2:$LR$60,MATCH(1,(GMW!$LQ$2:$LQ$60=AG$3)*(GMW!$LP$2:$LP$60=AG$4)*(GMW!$LR$2:$LR$60=AG$1),0),$C42-1966)} -> 0.001
A43: 1982 | B43: =B39+1 -> 1982 | C43: =+C42+1 -> 2009 | D43: {=INDEX(GMW!$A$2:$LR$60,MATCH(1,(GMW!$LQ$2:$LQ$60=D$3)*(GMW!$LP$2:$LP$60=D$4)*(GMW!$LR$2:$LR$60=D$1),0),$C43-1966)} -> 239578 | E43: {=INDEX(GMW!$A$2:$LR$60,MATCH(1,(GMW!$LQ$2:$LQ$60=E$3)*(GMW!$LP$2:$LP$60=E$4)*(GMW!$LR$2:$LR$60=E$1),0),$C43-1966)} -> 239578 | F43: {=INDEX(GMW!$A$2:$LR$60,MATCH(1,(GMW!$LQ$2:$LQ$60=F$3)*(GMW!$LP$2:$LP$60=F$4)*(GMW!$LR$2:$LR$60=F$1),0),$C43-1966)} -> 239578 | G43: {=INDEX(GMW!$A$2:$LR$60,MATCH(1,(GMW!$LQ$2:$LQ$60=G$3)*(GMW!$LP$2:$LP$60=G$4)*(GMW!$LR$2:$LR$60=G$1),0),$C43-1966)} -> 239578 | H43: {=INDEX(GMW!$A$2:$LR$60,MATCH(1,(GMW!$LQ$2:$LQ$60=H$3)*(GMW!$LP$2:$LP$60=H$4)*(GMW!$LR$2:$LR$60=H$1),0),$C43-1966)} -> 239578 | I43: {=INDEX(GMW!$A$2:$LR$60,MATCH(1,(GMW!$LQ$2:$LQ$60=I$3)*(GMW!$LP$2:$LP$60=I$4)*(GMW!$LR$2:$LR$60=I$1),0),$C43-1966)} -> 239578 | J43: {=INDEX(GMW!$A$2:$LR$60,MATCH(1,(GMW!$LQ$2:$LQ$60=J$3)*(GMW!$LP$2:$LP$60=J$4)*(GMW!$LR$2:$LR$60=J$1),0),$C43-1966)} -> 239578 | K43: {=INDEX(GMW!$A$2:$LR$60,MATCH(1,(GMW!$LQ$2:$LQ$60=K$3)*(GMW!$LP$2:$LP$60=K$4)*(GMW!$LR$2:$LR$60=K$1),0),$C43-1966)} -> 239578 | ... AG43: {=INDEX(GMW!$A$2:$LR$60,MATCH(1,(GMW!$LQ$2:$LQ$60=AG$3)*(GMW!$LP$2:$LP$60=AG$4)*(GMW!$LR$2:$LR$60=AG$1),0),$C43-1966)} -> 0.001
B44: =B40+1 -> 1982 | C44: =+C43+1 -> 2010 | D44: {=INDEX(GMW!$A$2:$LR$60,MATCH(1,(GMW!$LQ$2:$LQ$60=D$3)*(GMW!$LP$2:$LP$60=D$4)*(GMW!$LR$2:$LR$60=D$1),0),$C44-1966)} -> 242095 | E44: {=INDEX(GMW!$A$2:$LR$60,MATCH(1,(GMW!$LQ$2:$LQ$60=E$3)*(GMW!$LP$2:$LP$60=E$4)*(GMW!$LR$2:$LR$60=E$1),0),$C44-1966)} -> 242095 | F44: {=INDEX(GMW!$A$2:$LR$60,MATCH(1,(GMW!$LQ$2:$LQ$60=F$3)*(GMW!$LP$2:$LP$60=F$4)*(GMW!$LR$2:$LR$60=F$1),0),$C44-1966)} -> 242095 | G44: {=INDEX(GMW!$A$2:$LR$60,MATCH(1,(GMW!$LQ$2:$LQ$60=G$3)*(GMW!$LP$2:$LP$60=G$4)*(GMW!$LR$2:$LR$60=G$1),0),$C44-1966)} -> 242095 | H44: {=INDEX(GMW!$A$2:$LR$60,MATCH(1,(GMW!$LQ$2:$LQ$60=H$3)*(GMW!$LP$2:$LP$60=H$4)*(GMW!$LR$2:$LR$60=H$1),0),$C44-1966)} -> 242095 | I44: {=INDEX(GMW!$A$2:$LR$60,MATCH(1,(GMW!$LQ$2:$LQ$60=I$3)*(GMW!$LP$2:$LP$60=I$4)*(GMW!$LR$2:$LR$60=I$1),0),$C44-1966)} -> 242095 | J44: {=INDEX(GMW!$A$2:$LR$60,MATCH(1,(GMW!$LQ$2:$LQ$60=J$3)*(GMW!$LP$2:$LP$60=J$4)*(GMW!$LR$2:$LR$60=J$1),0),$C44-1966)} -> 242095 | K44: {=INDEX(GMW!$A$2:$LR$60,MATCH(1,(GMW!$LQ$2:$LQ$60=K$3)*(GMW!$LP$2:$LP$60=K$4)*(GMW!$LR$2:$LR$60=K$1),0),$C44-1966)} -> 242095 | ... AG44: {=INDEX(GMW!$A$2:$LR$60,MATCH(1,(GMW!$LQ$2:$LQ$60=AG$3)*(GMW!$LP$2:$LP$60=AG$4)*(GMW!$LR$2:$LR$60=AG$1),0),$C44-1966)} -> 0.001
B45: =B41+1 -> 1982 | C45: =+C44+1 -> 2011 | D45: {=INDEX(GMW!$A$2:$LR$60,MATCH(1,(GMW!$LQ$2:$LQ$60=D$3)*(GMW!$LP$2:$LP$60=D$4)*(GMW!$LR$2:$LR$60=D$1),0),$C45-1966)} -> 242639 | E45: {=INDEX(GMW!$A$2:$LR$60,MATCH(1,(GMW!$LQ$2:$LQ$60=E$3)*(GMW!$LP$2:$LP$60=E$4)*(GMW!$LR$2:$LR$60=E$1),0),$C45-1966)} -> 242639 | F45: {=INDEX(GMW!$A$2:$LR$60,MATCH(1,(GMW!$LQ$2:$LQ$60=F$3)*(GMW!$LP$2:$LP$60=F$4)*(GMW!$LR$2:$LR$60=F$1),0),$C45-1966)} -> 242639 | G45: {=INDEX(GMW!$A$2:$LR$60,MATCH(1,(GMW!$LQ$2:$LQ$60=G$3)*(GMW!$LP$2:$LP$60=G$4)*(GMW!$LR$2:$LR$60=G$1),0),$C45-1966)} -> 242639 | H45: {=INDEX(GMW!$A$2:$LR$60,MATCH(1,(GMW!$LQ$2:$LQ$60=H$3)*(GMW!$LP$2:$LP$60=H$4)*(GMW!$LR$2:$LR$60=H$1),0),$C45-1966)} -> 242639 | I45: {=INDEX(GMW!$A$2:$LR$60,MATCH(1,(GMW!$LQ$2:$LQ$60=I$3)*(GMW!$LP$2:$LP$60=I$4)*(GMW!$LR$2:$LR$60=I$1),0),$C45-1966)} -> 242639 | J45: {=INDEX(GMW!$A$2:$LR$60,MATCH(1,(GMW!$LQ$2:$LQ$60=J$3)*(GMW!$LP$2:$LP$60=J$4)*(GMW!$LR$2:$LR$60=J$1),0),$C45-1966)} -> 242639 | K45: {=INDEX(GMW!$A$2:$LR$60,MATCH(1,(GMW!$LQ$2:$LQ$60=K$3)*(GMW!$LP$2:$LP$60=K$4)*(GMW!$LR$2:$LR$60=K$1),0),$C45-1966)} -> 242639 | ... AG45: {=INDEX(GMW!$A$2:$LR$60,MATCH(1,(GMW!$LQ$2:$LQ$60=AG$3)*(GMW!$LP$2:$LP$60=AG$4)*(GMW!$LR$2:$LR$60=AG$1),0),$C45-1966)} -> 0.001
B46: =B42+1 -> 1982 | C46: =+C45+1 -> 2012 | D46: {=INDEX(GMW!$A$2:$LR$60,MATCH(1,(GMW!$LQ$2:$LQ$60=D$3)*(GMW!$LP$2:$LP$60=D$4)*(GMW!$LR$2:$LR$60=D$1),0),$C46-1966)} -> 244317 | E46: {=INDEX(GMW!$A$2:$LR$60,MATCH(1,(GMW!$LQ$2:$LQ$60=E$3)*(GMW!$LP$2:$LP$60=E$4)*(GMW!$LR$2:$LR$60=E$1),0),$C46-1966)} -> 244317 | F46: {=INDEX(GMW!$A$2:$LR$60,MATCH(1,(GMW!$LQ$2:$LQ$60=F$3)*(GMW!$LP$2:$LP$60=F$4)*(GMW!$LR$2:$LR$60=F$1),0),$C46-1966)} -> 244317 | G46: {=INDEX(GMW!$A$2:$LR$60,MATCH(1,(GMW!$LQ$2:$LQ$60=G$3)*(GMW!$LP$2:$LP$60=G$4)*(GMW!$LR$2:$LR$60=G$1),0),$C46-1966)} -> 244317 | H46: {=INDEX(GMW!$A$2:$LR$60,MATCH(1,(GMW!$LQ$2:$LQ$60=H$3)*(GMW!$LP$2:$LP$60=H$4)*(GMW!$LR$2:$LR$60=H$1),0),$C46-1966)} -> 244317 | I46: {=INDEX(GMW!$A$2:$LR$60,MATCH(1,(GMW!$LQ$2:$LQ$60=I$3)*(GMW!$LP$2:$LP$60=I$4)*(GMW!$LR$2:$LR$60=I$1),0),$C46-1966)} -> 244317 | J46: {=INDEX(GMW!$A$2:$LR$60,MATCH(1,(GMW!$LQ$2:$LQ$60=J$3)*(GMW!$LP$2:$LP$60=J$4)*(GMW!$LR$2:$LR$60=J$1),0),$C46-1966)} -> 244317 | K46: {=INDEX(GMW!$A$2:$LR$60,MATCH(1,(GMW!$LQ$2:$LQ$60=K$3)*(GMW!$LP$2:$LP$60=K$4)*(GMW!$LR$2:$LR$60=K$1),0),$C46-1966)} -> 244317 | ... AG46: {=INDEX(GMW!$A$2:$LR$60,MATCH(1,(GMW!$LQ$2:$LQ$60=AG$3)*(GMW!$LP$2:$LP$60=AG$4)*(GMW!$LR$2:$LR$60=AG$1),0),$C46-1966)} -> 0.001
A47: 1983 | B47: =B43+1 -> 1983 | C47: =+C46+1 -> 2013 | D47: {=INDEX(GMW!$A$2:$LR$60,MATCH(1,(GMW!$LQ$2:$LQ$60=D$3)*(GMW!$LP$2:$LP$60=D$4)*(GMW!$LR$2:$LR$60=D$1),0),$C47-1966)} -> 249032 | E47: {=INDEX(GMW!$A$2:$LR$60,MATCH(1,(GMW!$LQ$2:$LQ$60=E$3)*(GMW!$LP$2:$LP$60=E$4)*(GMW!$LR$2:$LR$60=E$1),0),$C47-1966)} -> 249032 | F47: {=INDEX(GMW!$A$2:$LR$60,MATCH(1,(GMW!$LQ$2:$LQ$60=F$3)*(GMW!$LP$2:$LP$60=F$4)*(GMW!$LR$2:$LR$60=F$1),0),$C47-1966)} -> 249032 | G47: {=INDEX(GMW!$A$2:$LR$60,MATCH(1,(GMW!$LQ$2:$LQ$60=G$3)*(GMW!$LP$2:$LP$60=G$4)*(GMW!$LR$2:$LR$60=G$1),0),$C47-1966)} -> 249032 | H47: {=INDEX(GMW!$A$2:$LR$60,MATCH(1,(GMW!$LQ$2:$LQ$60=H$3)*(GMW!$LP$2:$LP$60=H$4)*(GMW!$LR$2:$LR$60=H$1),0),$C47-1966)} -> 249032 | I47: {=INDEX(GMW!$A$2:$LR$60,MATCH(1,(GMW!$LQ$2:$LQ$60=I$3)*(GMW!$LP$2:$LP$60=I$4)*(GMW!$LR$2:$LR$60=I$1),0),$C47-1966)} -> 249032 | J47: {=INDEX(GMW!$A$2:$LR$60,MATCH(1,(GMW!$LQ$2:$LQ$60=J$3)*(GMW!$LP$2:$LP$60=J$4)*(GMW!$LR$2:$LR$60=J$1),0),$C47-1966)} -> 249032 | K47: {=INDEX(GMW!$A$2:$LR$60,MATCH(1,(GMW!$LQ$2:$LQ$60=K$3)*(GMW!$LP$2:$LP$60=K$4)*(GMW!$LR$2:$LR$60=K$1),0),$C47-1966)} -> 249032 | ... AG47: {=INDEX(GMW!$A$2:$LR$60,MATCH(1,(GMW!$LQ$2:$LQ$60=AG$3)*(GMW!$LP$2:$LP$60=AG$4)*(GMW!$LR$2:$LR$60=AG$1),0),$C47-1966)} -> 0.001
B48: =B44+1 -> 1983 | C48: =+C47+1 -> 2014 | D48: {=INDEX(GMW!$A$2:$LR$60,MATCH(1,(GMW!$LQ$2:$LQ$60=D$3)*(GMW!$LP$2:$LP$60=D$4)*(GMW!$LR$2:$LR$60=D$1),0),$C48-1966)} -> 250761 | E48: {=INDEX(GMW!$A$2:$LR$60,MATCH(1,(GMW!$LQ$2:$LQ$60=E$3)*(GMW!$LP$2:$LP$60=E$4)*(GMW!$LR$2:$LR$60=E$1),0),$C48-1966)} -> 250761 | F48: {=INDEX(GMW!$A$2:$LR$60,MATCH(1,(GMW!$LQ$2:$LQ$60=F$3)*(GMW!$LP$2:$LP$60=F$4)*(GMW!$LR$2:$LR$60=F$1),0),$C48-1966)} -> 250761 | G48: {=INDEX(GMW!$A$2:$LR$60,MATCH(1,(GMW!$LQ$2:$LQ$60=G$3)*(GMW!$LP$2:$LP$60=G$4)*(GMW!$LR$2:$LR$60=G$1),0),$C48-1966)} -> 250761 | H48: {=INDEX(GMW!$A$2:$LR$60,MATCH(1,(GMW!$LQ$2:$LQ$60=H$3)*(GMW!$LP$2:$LP$60=H$4)*(GMW!$LR$2:$LR$60=H$1),0),$C48-1966)} -> 250761 | I48: {=INDEX(GMW!$A$2:$LR$60,MATCH(1,(GMW!$LQ$2:$LQ$60=I$3)*(GMW!$LP$2:$LP$60=I$4)*(GMW!$LR$2:$LR$60=I$1),0),$C48-1966)} -> 250761 | J48: {=INDEX(GMW!$A$2:$LR$60,MATCH(1,(GMW!$LQ$2:$LQ$60=J$3)*(GMW!$LP$2:$LP$60=J$4)*(GMW!$LR$2:$LR$60=J$1),0),$C48-1966)} -> 250761 | K48: {=INDEX(GMW!$A$2:$LR$60,MATCH(1,(GMW!$LQ$2:$LQ$60=K$3)*(GMW!$LP$2:$LP$60=K$4)*(GMW!$LR$2:$LR$60=K$1),0),$C48-1966)} -> 250761 | ... AG48: {=INDEX(GMW!$A$2:$LR$60,MATCH(1,(GMW!$LQ$2:$LQ$60=AG$3)*(GMW!$LP$2:$LP$60=AG$4)*(GMW!$LR$2:$LR$60=AG$1),0),$C48-1966)} -> 0.001
B49: =B45+1 -> 1983 | C49: =+C48+1 -> 2015 | D49: {=INDEX(GMW!$A$2:$LR$60,MATCH(1,(GMW!$LQ$2:$LQ$60=D$3)*(GMW!$LP$2:$LP$60=D$4)*(GMW!$LR$2:$LR$60=D$1),0),$C49-1966)} -> 253655 | E49: {=INDEX(GMW!$A$2:$LR$60,MATCH(1,(GMW!$LQ$2:$LQ$60=E$3)*(GMW!$LP$2:$LP$60=E$4)*(GMW!$LR$2:$LR$60=E$1),0),$C49-1966)} -> 253655 | F49: {=INDEX(GMW!$A$2:$LR$60,MATCH(1,(GMW!$LQ$2:$LQ$60=F$3)*(GMW!$LP$2:$LP$60=F$4)*(GMW!$LR$2:$LR$60=F$1),0),$C49-1966)} -> 253655 | G49: {=INDEX(GMW!$A$2:$LR$60,MATCH(1,(GMW!$LQ$2:$LQ$60=G$3)*(GMW!$LP$2:$LP$60=G$4)*(GMW!$LR$2:$LR$60=G$1),0),$C49-1966)} -> 253655 | H49: {=INDEX(GMW!$A$2:$LR$60,MATCH(1,(GMW!$LQ$2:$LQ$60=H$3)*(GMW!$LP$2:$LP$60=H$4)*(GMW!$LR$2:$LR$60=H$1),0),$C49-1966)} -> 253655 | I49: {=INDEX(GMW!$A$2:$LR$60,MATCH(1,(GMW!$LQ$2:$LQ$60=I$3)*(GMW!$LP$2:$LP$60=I$4)*(GMW!$LR$2:$LR$60=I$1),0),$C49-1966)} -> 253655 | J49: {=INDEX(GMW!$A$2:$LR$60,MATCH(1,(GMW!$LQ$2:$LQ$60=J$3)*(GMW!$LP$2:$LP$60=J$4)*(GMW!$LR$2:$LR$60=J$1),0),$C49-1966)} -> 253655 | K49: {=INDEX(GMW!$A$2:$LR$60,MATCH(1,(GMW!$LQ$2:$LQ$60=K$3)*(GMW!$LP$2:$LP$60=K$4)*(GMW!$LR$2:$LR$60=K$1),0),$C49-1966)} -> 253655 | ... AG49: {=INDEX(GMW!$A$2:$LR$60,MATCH(1,(GMW!$LQ$2:$LQ$60=AG$3)*(GMW!$LP$2:$LP$60=AG$4)*(GMW!$LR$2:$LR$60=AG$1),0),$C49-1966)} -> 0.001
B50: =B46+1 -> 1983 | C50: =+C49+1 -> 2016 | D50: {=INDEX(GMW!$A$2:$LR$60,MATCH(1,(GMW!$LQ$2:$LQ$60=D$3)*(GMW!$LP$2:$LP$60=D$4)*(GMW!$LR$2:$LR$60=D$1),0),$C50-1966)} -> 255533 | E50: {=INDEX(GMW!$A$2:$LR$60,MATCH(1,(GMW!$LQ$2:$LQ$60=E$3)*(GMW!$LP$2:$LP$60=E$4)*(GMW!$LR$2:$LR$60=E$1),0),$C50-1966)} -> 255533 | F50: {=INDEX(GMW!$A$2:$LR$60,MATCH(1,(GMW!$LQ$2:$LQ$60=F$3)*(GMW!$LP$2:$LP$60=F$4)*(GMW!$LR$2:$LR$60=F$1),0),$C50-1966)} -> 255533 | G50: {=INDEX(GMW!$A$2:$LR$60,MATCH(1,(GMW!$LQ$2:$LQ$60=G$3)*(GMW!$LP$2:$LP$60=G$4)*(GMW!$LR$2:$LR$60=G$1),0),$C50-1966)} -> 255533 | H50: {=INDEX(GMW!$A$2:$LR$60,MATCH(1,(GMW!$LQ$2:$LQ$60=H$3)*(GMW!$LP$2:$LP$60=H$4)*(GMW!$LR$2:$LR$60=H$1),0),$C50-1966)} -> 255533 | I50: {=INDEX(GMW!$A$2:$LR$60,MATCH(1,(GMW!$LQ$2:$LQ$60=I$3)*(GMW!$LP$2:$LP$60=I$4)*(GMW!$LR$2:$LR$60=I$1),0),$C50-1966)} -> 255533 | J50: {=INDEX(GMW!$A$2:$LR$60,MATCH(1,(GMW!$LQ$2:$LQ$60=J$3)*(GMW!$LP$2:$LP$60=J$4)*(GMW!$LR$2:$LR$60=J$1),0),$C50-1966)} -> 255533 | K50: {=INDEX(GMW!$A$2:$LR$60,MATCH(1,(GMW!$LQ$2:$LQ$60=K$3)*(GMW!$LP$2:$LP$60=K$4)*(GMW!$LR$2:$LR$60=K$1),0),$C50-1966)} -> 255533 | ... AG50: {=INDEX(GMW!$A$2:$LR$60,MATCH(1,(GMW!$LQ$2:$LQ$60=AG$3)*(GMW!$LP$2:$LP$60=AG$4)*(GMW!$LR$2:$LR$60=AG$1),0),$C50-1966)} -> 0.001
A51: 1984 | B51: =B47+1 -> 1984 | C51: =+C50+1 -> 2017 | D51: {=INDEX(GMW!$A$2:$LR$60,MATCH(1,(GMW!$LQ$2:$LQ$60=D$3)*(GMW!$LP$2:$LP$60=D$4)*(GMW!$LR$2:$LR$60=D$1),0),$C51-1966)} -> 257683 | E51: {=INDEX(GMW!$A$2:$LR$60,MATCH(1,(GMW!$LQ$2:$LQ$60=E$3)*(GMW!$LP$2:$LP$60=E$4)*(GMW!$LR$2:$LR$60=E$1),0),$C51-1966)} -> 257683 | F51: {=INDEX(GMW!$A$2:$LR$60,MATCH(1,(GMW!$LQ$2:$LQ$60=F$3)*(GMW!$LP$2:$LP$60=F$4)*(GMW!$LR$2:$LR$60=F$1),0),$C51-1966)} -> 257683 | G51: {=INDEX(GMW!$A$2:$LR$60,MATCH(1,(GMW!$LQ$2:$LQ$60=G$3)*(GMW!$LP$2:$LP$60=G$4)*(GMW!$LR$2:$LR$60=G$1),0),$C51-1966)} -> 257683 | H51: {=INDEX(GMW!$A$2:$LR$60,MATCH(1,(GMW!$LQ$2:$LQ$60=H$3)*(GMW!$LP$2:$LP$60=H$4)*(GMW!$LR$2:$LR$60=H$1),0),$C51-1966)} -> 257683 | I51: {=INDEX(GMW!$A$2:$LR$60,MATCH(1,(GMW!$LQ$2:$LQ$60=I$3)*(GMW!$LP$2:$LP$60=I$4)*(GMW!$LR$2:$LR$60=I$1),0),$C51-1966)} -> 257683 | J51: {=INDEX(GMW!$A$2:$LR$60,MATCH(1,(GMW!$LQ$2:$LQ$60=J$3)*(GMW!$LP$2:$LP$60=J$4)*(GMW!$LR$2:$LR$60=J$1),0),$C51-1966)} -> 257683 | K51: {=INDEX(GMW!$A$2:$LR$60,MATCH(1,(GMW!$LQ$2:$LQ$60=K$3)*(GMW!$LP$2:$LP$60=K$4)*(GMW!$LR$2:$LR$60=K$1),0),$C51-1966)} -> 257683 | ... AG51: {=INDEX(GMW!$A$2:$LR$60,MATCH(1,(GMW!$LQ$2:$LQ$60=AG$3)*(GMW!$LP$2:$LP$60=AG$4)*(GMW!$LR$2:$LR$60=AG$1),0),$C51-1966)} -> 0.001
B52: =B48+1 -> 1984 | C52: =+C51+1 -> 2018 | D52: {=INDEX(GMW!$A$2:$LR$60,MATCH(1,(GMW!$LQ$2:$LQ$60=D$3)*(GMW!$LP$2:$LP$60=D$4)*(GMW!$LR$2:$LR$60=D$1),0),$C52-1966)} -> 255100 | E52: {=INDEX(GMW!$A$2:$LR$60,MATCH(1,(GMW!$LQ$2:$LQ$60=E$3)*(GMW!$LP$2:$LP$60=E$4)*(GMW!$LR$2:$LR$60=E$1),0),$C52-1966)} -> 255100 | F52: {=INDEX(GMW!$A$2:$LR$60,MATCH(1,(GMW!$LQ$2:$LQ$60=F$3)*(GMW!$LP$2:$LP$60=F$4)*(GMW!$LR$2:$LR$60=F$1),0),$C52-1966)} -> 255100 | G52: {=INDEX(GMW!$A$2:$LR$60,MATCH(1,(GMW!$LQ$2:$LQ$60=G$3)*(GMW!$LP$2:$LP$60=G$4)*(GMW!$LR$2:$LR$60=G$1),0),$C52-1966)} -> 255100 | H52: {=INDEX(GMW!$A$2:$LR$60,MATCH(1,(GMW!$LQ$2:$LQ$60=H$3)*(GMW!$LP$2:$LP$60=H$4)*(GMW!$LR$2:$LR$60=H$1),0),$C52-1966)} -> 255100 | I52: {=INDEX(GMW!$A$2:$LR$60,MATCH(1,(GMW!$LQ$2:$LQ$60=I$3)*(GMW!$LP$2:$LP$60=I$4)*(GMW!$LR$2:$LR$60=I$1),0),$C52-1966)} -> 255100 | J52: {=INDEX(GMW!$A$2:$LR$60,MATCH(1,(GMW!$LQ$2:$LQ$60=J$3)*(GMW!$LP$2:$LP$60=J$4)*(GMW!$LR$2:$LR$60=J$1),0),$C52-1966)} -> 255100 | K52: {=INDEX(GMW!$A$2:$LR$60,MATCH(1,(GMW!$LQ$2:$LQ$60=K$3)*(GMW!$LP$2:$LP$60=K$4)*(GMW!$LR$2:$LR$60=K$1),0),$C52-1966)} -> 255100 | ... AG52: {=INDEX(GMW!$A$2:$LR$60,MATCH(1,(GMW!$LQ$2:$LQ$60=AG$3)*(GMW!$LP$2:$LP$60=AG$4)*(GMW!$LR$2:$LR$60=AG$1),0),$C52-1966)} -> 0.001
B53: =B49+1 -> 1984 | C53: =+C52+1 -> 2019 | D53: {=INDEX(GMW!$A$2:$LR$60,MATCH(1,(GMW!$LQ$2:$LQ$60=D$3)*(GMW!$LP$2:$LP$60=D$4)*(GMW!$LR$2:$LR$60=D$1),0),$C53-1966)} -> 256975 | E53: {=INDEX(GMW!$A$2:$LR$60,MATCH(1,(GMW!$LQ$2:$LQ$60=E$3)*(GMW!$LP$2:$LP$60=E$4)*(GMW!$LR$2:$LR$60=E$1),0),$C53-1966)} -> 256975 | F53: {=INDEX(GMW!$A$2:$LR$60,MATCH(1,(GMW!$LQ$2:$LQ$60=F$3)*(GMW!$LP$2:$LP$60=F$4)*(GMW!$LR$2:$LR$60=F$1),0),$C53-1966)} -> 256975 | G53: {=INDEX(GMW!$A$2:$LR$60,MATCH(1,(GMW!$LQ$2:$LQ$60=G$3)*(GMW!$LP$2:$LP$60=G$4)*(GMW!$LR$2:$LR$60=G$1),0),$C53-1966)} -> 256975 | H53: {=INDEX(GMW!$A$2:$LR$60,MATCH(1,(GMW!$LQ$2:$LQ$60=H$3)*(GMW!$LP$2:$LP$60=H$4)*(GMW!$LR$2:$LR$60=H$1),0),$C53-1966)} -> 256975 | I53: {=INDEX(GMW!$A$2:$LR$60,MATCH(1,(GMW!$LQ$2:$LQ$60=I$3)*(GMW!$LP$2:$LP$60=I$4)*(GMW!$LR$2:$LR$60=I$1),0),$C53-1966)} -> 256975 | J53: {=INDEX(GMW!$A$2:$LR$60,MATCH(1,(GMW!$LQ$2:$LQ$60=J$3)*(GMW!$LP$2:$LP$60=J$4)*(GMW!$LR$2:$LR$60=J$1),0),$C53-1966)} -> 256975 | K53: {=INDEX(GMW!$A$2:$LR$60,MATCH(1,(GMW!$LQ$2:$LQ$60=K$3)*(GMW!$LP$2:$LP$60=K$4)*(GMW!$LR$2:$LR$60=K$1),0),$C53-1966)} -> 256975 | ... AG53: {=INDEX(GMW!$A$2:$LR$60,MATCH(1,(GMW!$LQ$2:$LQ$60=AG$3)*(GMW!$LP$2:$LP$60=AG$4)*(GMW!$LR$2:$LR$60=AG$1),0),$C53-1966)} -> 0.001
B54: =B50+1 -> 1984 | C54: =+C53+1 -> 2020 | D54: {=INDEX(GMW!$A$2:$LR$60,MATCH(1,(GMW!$LQ$2:$LQ$60=D$3)*(GMW!$LP$2:$LP$60=D$4)*(GMW!$LR$2:$LR$60=D$1),0),$C54-1966)} -> 261627 | E54: {=INDEX(GMW!$A$2:$LR$60,MATCH(1,(GMW!$LQ$2:$LQ$60=E$3)*(GMW!$LP$2:$LP$60=E$4)*(GMW!$LR$2:$LR$60=E$1),0),$C54-1966)} -> 261627 | F54: {=INDEX(GMW!$A$2:$LR$60,MATCH(1,(GMW!$LQ$2:$LQ$60=F$3)*(GMW!$LP$2:$LP$60=F$4)*(GMW!$LR$2:$LR$60=F$1),0),$C54-1966)} -> 261627 | G54: {=INDEX(GMW!$A$2:$LR$60,MATCH(1,(GMW!$LQ$2:$LQ$60=G$3)*(GMW!$LP$2:$LP$60=G$4)*(GMW!$LR$2:$LR$60=G$1),0),$C54-1966)} -> 261627 | H54: {=INDEX(GMW!$A$2:$LR$60,MATCH(1,(GMW!$LQ$2:$LQ$60=H$3)*(GMW!$LP$2:$LP$60=H$4)*(GMW!$LR$2:$LR$60=H$1),0),$C54-1966)} -> 261627 | I54: {=INDEX(GMW!$A$2:$LR$60,MATCH(1,(GMW!$LQ$2:$LQ$60=I$3)*(GMW!$LP$2:$LP$60=I$4)*(GMW!$LR$2:$LR$60=I$1),0),$C54-1966)} -> 261627 | J54: {=INDEX(GMW!$A$2:$LR$60,MATCH(1,(GMW!$LQ$2:$LQ$60=J$3)*(GMW!$LP$2:$LP$60=J$4)*(GMW!$LR$2:$LR$60=J$1),0),$C54-1966)} -> 261627 | K54: {=INDEX(GMW!$A$2:$LR$60,MATCH(1,(GMW!$LQ$2:$LQ$60=K$3)*(GMW!$LP$2:$LP$60=K$4)*(GMW!$LR$2:$LR$60=K$1),0),$C54-1966)} -> 261627 | ... AG54: {=INDEX(GMW!$A$2:$LR$60,MATCH(1,(GMW!$LQ$2:$LQ$60=AG$3)*(GMW!$LP$2:$LP$60=AG$4)*(GMW!$LR$2:$LR$60=AG$1),0),$C54-1966)} -> 0.001
A55: 1985 | B55: =B51+1 -> 1985 | C55: =+C54+1 -> 2021 | D55: {=INDEX(GMW!$A$2:$LR$60,MATCH(1,(GMW!$LQ$2:$LQ$60=D$3)*(GMW!$LP$2:$LP$60=D$4)*(GMW!$LR$2:$LR$60=D$1),0),$C55-1966)} -> 264127 | E55: {=INDEX(GMW!$A$2:$LR$60,MATCH(1,(GMW!$LQ$2:$LQ$60=E$3)*(GMW!$LP$2:$LP$60=E$4)*(GMW!$LR$2:$LR$60=E$1),0),$C55-1966)} -> 264127 | F55: {=INDEX(GMW!$A$2:$LR$60,MATCH(1,(GMW!$LQ$2:$LQ$60=F$3)*(GMW!$LP$2:$LP$60=F$4)*(GMW!$LR$2:$LR$60=F$1),0),$C55-1966)} -> 264127 | G55: {=INDEX(GMW!$A$2:$LR$60,MATCH(1,(GMW!$LQ$2:$LQ$60=G$3)*(GMW!$LP$2:$LP$60=G$4)*(GMW!$LR$2:$LR$60=G$1),0),$C55-1966)} -> 264127 | H55: {=INDEX(GMW!$A$2:$LR$60,MATCH(1,(GMW!$LQ$2:$LQ$60=H$3)*(GMW!$LP$2:$LP$60=H$4)*(GMW!$LR$2:$LR$60=H$1),0),$C55-1966)} -> 264127 | I55: {=INDEX(GMW!$A$2:$LR$60,MATCH(1,(GMW!$LQ$2:$LQ$60=I$3)*(GMW!$LP$2:$LP$60=I$4)*(GMW!$LR$2:$LR$60=I$1),0),$C55-1966)} -> 264127 | J55: {=INDEX(GMW!$A$2:$LR$60,MATCH(1,(GMW!$LQ$2:$LQ$60=J$3)*(GMW!$LP$2:$LP$60=J$4)*(GMW!$LR$2:$LR$60=J$1),0),$C55-1966)} -> 264127 | K55: {=INDEX(GMW!$A$2:$LR$60,MATCH(1,(GMW!$LQ$2:$LQ$60=K$3)*(GMW!$LP$2:$LP$60=K$4)*(GMW!$LR$2:$LR$60=K$1),0),$C55-1966)} -> 264127 | ... AG55: {=INDEX(GMW!$A$2:$LR$60,MATCH(1,(GMW!$LQ$2:$LQ$60=AG$3)*(GMW!$LP$2:$LP$60=AG$4)*(GMW!$LR$2:$LR$60=AG$1),0),$C55-1966)} -> 0.001
B56: =B52+1 -> 1985 | C56: =+C55+1 -> 2022 | D56: {=INDEX(GMW!$A$2:$LR$60,MATCH(1,(GMW!$LQ$2:$LQ$60=D$3)*(GMW!$LP$2:$LP$60=D$4)*(GMW!$LR$2:$LR$60=D$1),0),$C56-1966)} -> 269787 | E56: {=INDEX(GMW!$A$2:$LR$60,MATCH(1,(GMW!$LQ$2:$LQ$60=E$3)*(GMW!$LP$2:$LP$60=E$4)*(GMW!$LR$2:$LR$60=E$1),0),$C56-1966)} -> 269787 | F56: {=INDEX(GMW!$A$2:$LR$60,MATCH(1,(GMW!$LQ$2:$LQ$60=F$3)*(GMW!$LP$2:$LP$60=F$4)*(GMW!$LR$2:$LR$60=F$1),0),$C56-1966)} -> 269787 | G56: {=INDEX(GMW!$A$2:$LR$60,MATCH(1,(GMW!$LQ$2:$LQ$60=G$3)*(GMW!$LP$2:$LP$60=G$4)*(GMW!$LR$2:$LR$60=G$1),0),$C56-1966)} -> 269787 | H56: {=INDEX(GMW!$A$2:$LR$60,MATCH(1,(GMW!$LQ$2:$LQ$60=H$3)*(GMW!$LP$2:$LP$60=H$4)*(GMW!$LR$2:$LR$60=H$1),0),$C56-1966)} -> 269787 | I56: {=INDEX(GMW!$A$2:$LR$60,MATCH(1,(GMW!$LQ$2:$LQ$60=I$3)*(GMW!$LP$2:$LP$60=I$4)*(GMW!$LR$2:$LR$60=I$1),0),$C56-1966)} -> 269787 | J56: {=INDEX(GMW!$A$2:$LR$60,MATCH(1,(GMW!$LQ$2:$LQ$60=J$3)*(GMW!$LP$2:$LP$60=J$4)*(GMW!$LR$2:$LR$60=J$1),0),$C56-1966)} -> 269787 | K56: {=INDEX(GMW!$A$2:$LR$60,MATCH(1,(GMW!$LQ$2:$LQ$60=K$3)*(GMW!$LP$2:$LP$60=K$4)*(GMW!$LR$2:$LR$60=K$1),0),$C56-1966)} -> 269787 | ... AG56: {=INDEX(GMW!$A$2:$LR$60,MATCH(1,(GMW!$LQ$2:$LQ$60=AG$3)*(GMW!$LP$2:$LP$60=AG$4)*(GMW!$LR$2:$LR$60=AG$1),0),$C56-1966)} -> 0.001
