Workbook
Name _DLX1.INC: HAVERM!$A$1:$AG$6
Name _DLX2.INC: HAVERD!$G$2:$BW$7
Name _DLX3.INC: HAVERQ!$A$1:$G$6
Name Data: [15]sheet0!$C$2

Sheet Chart Data
A1: Services inflation | E1: Private sector pay growth | I1: Inflation forecasts | P1: BoE DMP | V1: BoE DMP | AB1: APF run down
B2: Outturn | C2: BoE forecast | F2: Outturn | G2: BoE forecast | J2: CPI inflation | K2: BoE market expectations (Aug) | L2: OE (Aug) | M2: HMT consensus (Jul) | N2: 2% LINE | Q2: Prices - past year | R2: Prices - next year | S2: Wages - past year | T2: Wages - next year | W2: Prices - past year | X2: Prices - next year | Y2: Wages - past year | Z2: Wages - next year | AC2: Redemptions | AD2: Gilt sales | AE2: Gilt sales implied by BoE MaPS | AF2: Total run down
A3: 44562 | B3: =100*((HAVERM!C151/HAVERM!C139)-1) -> 3.2685512 | E3: 44562 | F3: =HAVERM!D151 -> 4.2 | I3: 44927 | J3: =100*((HAVERQ!E39/HAVERQ!E35)-1) -> 10.178263 | N3: 2 | P3: 43466 | Q3: =HAVERM!E115 -> 2.79 | R3: =HAVERM!F115 -> 2.532 | S3: =HAVERM!G115 -> #N/A | T3: =HAVERM!H115 -> #N/A | V3: 43466 | W3: =HAVERM!I115 -> 2.528 | X3: =HAVERM!J115 -> 2.465 | Y3: =HAVERM!K115 -> #N/A | Z3: =HAVERM!L115 -> #N/A | AB3: 2022/ 2023 | AC3: 37 | AD3: =80-AC3 -> 43 | AF3: =SUM(AC3:AD3) -> 80 | AH3: =SUM('APF gilt sales'!H3:H592)/1000 -> 41.994
A4: 44593 | B4: =100*((HAVERM!C152/HAVERM!C140)-1) -> 3.4391534 | E4: 44593 | F4: =HAVERM!D152 -> 4.6 | I4: 45017 | J4: =100*((HAVERQ!E40/HAVERQ!E36)-1) -> 8.4390513 | N4: 2 | P4: 43497 | Q4: =HAVERM!E116 -> 2.23 | R4: =HAVERM!F116 -> 2.561 | S4: =HAVERM!G116 -> #N/A | T4: =HAVERM!H116 -> #N/A | V4: 43497 | W4: =HAVERM!I116 -> 2.412 | X4: =HAVERM!J116 -> 2.423 | Y4: =HAVERM!K116 -> #N/A | Z4: =HAVERM!L116 -> #N/A | AB4: 2023/ 2024 | AC4: 50 | AD4: =100-AC4 -> 50 | AF4: =SUM(AC4:AD4) -> 100 | AH4: =SUM('APF gilt sales'!H593:H1125)/1000 -> 40.9895
A5: 44621 | B5: =100*((HAVERM!C153/HAVERM!C141)-1) -> 3.9612676 | E5: 44621 | F5: =HAVERM!D153 -> 4.9 | I5: 45108 | J5: =100*((HAVERQ!E41/HAVERQ!E37)-1) -> 6.7135896 | N5: 2 | P5: 43525 | Q5: =HAVERM!E117 -> 2.39 | R5: =HAVERM!F117 -> 2.068 | S5: =HAVERM!G117 -> #N/A | T5: =HAVERM!H117 -> #N/A | V5: 43525 | W5: =HAVERM!I117 -> 2.47 | X5: =HAVERM!J117 -> 2.387 | Y5: =HAVERM!K117 -> #N/A | Z5: =HAVERM!L117 -> #N/A | AB5: 2024/ 2025 | AC5: ='Maturity Profile of APF (Table)'!H4 -> 87.187539 | AE5: =100-AC5 -> 12.812461 | AF5: =SUM(AC5:AE5) -> 100
A6: 44652 | B6: =100*((HAVERM!C154/HAVERM!C142)-1) -> 4.7244094 | E6: 44652 | F6: =HAVERM!D154 -> 4.8 | I6: 45200 | J6: =100*((HAVERQ!E42/HAVERQ!E38)-1) -> 4.1568008 | N6: 2 | P6: 43556 | Q6: =HAVERM!E118 -> 2.88 | R6: =HAVERM!F118 -> 2.715 | S6: =HAVERM!G118 -> #N/A | T6: =HAVERM!H118 -> #N/A | V6: 43556 | W6: =HAVERM!I118 -> 2.499 | X6: =HAVERM!J118 -> 2.448 | Y6: =HAVERM!K118 -> #N/A | Z6: =HAVERM!L118 -> #N/A | AB6: 2025/ 2026 | AC6: ='Maturity Profile of APF (Table)'!H5 -> 49.127841 | AE6: =75-AC6 -> 25.872159 | AF6: =SUM(AC6:AE6) -> 75
A7: 44682 | B7: =100*((HAVERM!C155/HAVERM!C143)-1) -> 4.886562 | E7: 44682 | F7: =HAVERM!D155 -> 5.1 | I7: 45292 | J7: =100*((HAVERQ!E43/HAVERQ!E39)-1) -> 3.5490605 | L7: =100*((GMW!B211/GMW!B207)-1) -> 3.5491137 | N7: 2 | P7: 43586 | Q7: =HAVERM!E119 -> 1.82 | R7: =HAVERM!F119 -> 2.332 | S7: =HAVERM!G119 -> #N/A | T7: =HAVERM!H119 -> #N/A | V7: 43586 | W7: =HAVERM!I119 -> 2.362 | X7: =HAVERM!J119 -> 2.372 | Y7: =HAVERM!K119 -> #N/A | Z7: =HAVERM!L119 -> #N/A | AB7: 2026/ 2027 | AC7: ='Maturity Profile of APF (Table)'!H6 -> 30.505274 | AE7: =50-AC7 -> 19.494726 | AF7: =SUM(AC7:AE7) -> 50
A8: 44713 | B8: =100*((HAVERM!C156/HAVERM!C144)-1) -> 5.2173913 | E8: 44713 | F8: =HAVERM!D156 -> 5.4 | I8: 45383 | J8: =100*((HAVERQ!E44/HAVERQ!E40)-1) -> 2.110885 | L8: =100*((GMW!B212/GMW!B208)-1) -> 2.1108336 | N8: 2 | P8: 43617 | Q8: =HAVERM!E120 -> 2.69 | R8: =HAVERM!F120 -> 2.154 | S8: =HAVERM!G120 -> #N/A | T8: =HAVERM!H120 -> #N/A | V8: 43617 | W8: =HAVERM!I120 -> 2.462 | X8: =HAVERM!J120 -> 2.4 | Y8: =HAVERM!K120 -> #N/A | Z8: =HAVERM!L120 -> #N/A | AB8: 2027/ 2028 | AC8: ='Maturity Profile of APF (Table)'!H7 -> 29.223226 | AE8: =31-AC8 -> 1.7767736 | AF8: =SUM(AC8:AE8) -> 31
A9: 44743 | B9: =100*((HAVERM!C157/HAVERM!C145)-1) -> 5.7241977 | E9: 44743 | F9: =HAVERM!D157 -> 6 | I9: 45474 | K9: =HAVERQ!B45 -> 2.3 | L9: =100*((GMW!B213/GMW!B209)-1) -> 2.1209285 | N9: 2 | P9: 43647 | Q9: =HAVERM!E121 -> 2.26 | R9: =HAVERM!F121 -> 2.098 | S9: =HAVERM!G121 -> #N/A | T9: =HAVERM!H121 -> #N/A | V9: 43647 | W9: =HAVERM!I121 -> 2.256 | X9: =HAVERM!J121 -> 2.195 | Y9: =HAVERM!K121 -> #N/A | Z9: =HAVERM!L121 -> #N/A
A10: 44774 | B10: =100*((HAVERM!C158/HAVERM!C146)-1) -> 5.9585492 | E10: 44774 | F10: =HAVERM!D158 -> 6.2 | I10: 45566 | K10: =HAVERQ!B46 -> 2.7 | L10: =100*((GMW!B214/GMW!B210)-1) -> 2.5595093 | M10: 2.4 | N10: 2 | P10: 43678 | Q10: =HAVERM!E122 -> 1.94 | R10: =HAVERM!F122 -> 2.289 | S10: =HAVERM!G122 -> #N/A | T10: =HAVERM!H122 -> #N/A | V10: 43678 | W10: =HAVERM!I122 -> 2.296 | X10: =HAVERM!J122 -> 2.18 | Y10: =HAVERM!K122 -> #N/A | Z10: =HAVERM!L122 -> #N/A
A11: 44805 | B11: =100*((HAVERM!C159/HAVERM!C147)-1) -> 6.1312608 | E11: 44805 | F11: =HAVERM!D159 -> 6.6 | I11: 45658 | K11: =HAVERQ!B47 -> 2.7 | L11: =100*((GMW!B215/GMW!B211)-1) -> 2.5444802 | N11: 2 | P11: 43709 | Q11: =HAVERM!E123 -> 2.27 | R11: =HAVERM!F123 -> 2.355 | S11: =HAVERM!G123 -> #N/A | T11: =HAVERM!H123 -> #N/A | V11: 43709 | W11: =HAVERM!I123 -> 2.156 | X11: =HAVERM!J123 -> 2.247 | Y11: =HAVERM!K123 -> #N/A | Z11: =HAVERM!L123 -> #N/A
A12: 44835 | B12: =100*((HAVERM!C160/HAVERM!C148)-1) -> 6.2660944 | E12: 44835 | F12: =HAVERM!D160 -> 6.9 | I12: 45748 | K12: =HAVERQ!B48 -> 2.6 | L12: =100*((GMW!B216/GMW!B212)-1) -> 2.3549445 | N12: 2 | P12: 43739 | Q12: =HAVERM!E124 -> 1.99 | R12: =HAVERM!F124 -> 2.216 | S12: =HAVERM!G124 -> #N/A | T12: =HAVERM!H124 -> #N/A | V12: 43739 | W12: =HAVERM!I124 -> 2.067 | X12: =HAVERM!J124 -> 2.287 | Y12: =HAVERM!K124 -> #N/A | Z12: =HAVERM!L124 -> #N/A
A13: 44866 | B13: =100*((HAVERM!C161/HAVERM!C149)-1) -> 6.3464837 | E13: 44866 | F13: =HAVERM!D161 -> 7.3 | I13: 45839 | K13: =HAVERQ!B49 -> 2.4 | L13: =100*((GMW!B217/GMW!B213)-1) -> 2.6438497 | N13: 2 | P13: 43770 | Q13: =HAVERM!E125 -> 1.89 | R13: =HAVERM!F125 -> 2.181 | S13: =HAVERM!G125 -> #N/A | T13: =HAVERM!H125 -> #N/A | V13: 43770 | W13: =HAVERM!I125 -> 2.051 | X13: =HAVERM!J125 -> 2.251 | Y13: =HAVERM!K125 -> #N/A | Z13: =HAVERM!L125 -> #N/A
A14: 44896 | B14: =100*((HAVERM!C162/HAVERM!C150)-1) -> 6.8376068 | E14: 44896 | F14: =HAVERM!D162 -> 7.3 | I14: 45931 | K14: =HAVERQ!B50 -> 2.2 | L14: =100*((GMW!B218/GMW!B214)-1) -> 2.4348994 | M14: 2.1 | N14: 2 | P14: 43800 | Q14: =HAVERM!E126 -> 1.99 | R14: =HAVERM!F126 -> 2.371 | S14: =HAVERM!G126 -> #N/A | T14: =HAVERM!H126 -> #N/A | V14: 43800 | W14: =HAVERM!I126 -> 1.958 | X14: =HAVERM!J126 -> 2.256 | Y14: =HAVERM!K126 -> #N/A | Z14: =HAVERM!L126 -> #N/A
A15: 44927 | B15: =100*((HAVERM!C163/HAVERM!C151)-1) -> 5.9024808 | E15: 44927 | F15: =HAVERM!D163 -> 7.1 | I15: 46023 | K15: =HAVERQ!B51 -> 2 | L15: =100*((GMW!B219/GMW!B215)-1) -> 2.3920573 | N15: 2 | P15: 43831 | Q15: =HAVERM!E127 -> 2.07 | R15: =HAVERM!F127 -> 2.121 | S15: =HAVERM!G127 -> #N/A | T15: =HAVERM!H127 -> #N/A | V15: 43831 | W15: =HAVERM!I127 -> 1.982 | X15: =HAVERM!J127 -> 2.224 | Y15: =HAVERM!K127 -> #N/A | Z15: =HAVERM!L127 -> #N/A
A16: 44958 | B16: =100*((HAVERM!C164/HAVERM!C152)-1) -> 6.6496164 | E16: 44958 | F16: =HAVERM!D164 -> 7.1 | I16: 46113 | K16: =HAVERQ!B52 -> 1.7 | L16: =100*((GMW!B220/GMW!B216)-1) -> 2.3063109 | N16: 2 | P16: 43862 | Q16: =HAVERM!E128 -> 1.79 | R16: =HAVERM!F128 -> 2.126 | S16: =HAVERM!G128 -> #N/A | T16: =HAVERM!H128 -> #N/A | V16: 43862 | W16: =HAVERM!I128 -> 1.949 | X16: =HAVERM!J128 -> 2.206 | Y16: =HAVERM!K128 -> #N/A | Z16: =HAVERM!L128 -> #N/A
A17: 44986 | B17: =100*((HAVERM!C165/HAVERM!C153)-1) -> 6.6892464 | E17: 44986 | F17: =HAVERM!D165 -> 7.2 | I17: 46204 | K17: =HAVERQ!B53 -> 1.7 | L17: =100*((GMW!B221/GMW!B217)-1) -> 2.2260202 | N17: 2 | P17: 43891 | Q17: =HAVERM!E129 -> 1.82 | R17: =HAVERM!F129 -> 1.615 | S17: =HAVERM!G129 -> #N/A | T17: =HAVERM!H129 -> #N/A | V17: 43891 | W17: =HAVERM!I129 -> 1.893 | X17: =HAVERM!J129 -> 1.954 | Y17: =HAVERM!K129 -> #N/A | Z17: =HAVERM!L129 -> #N/A
A18: 45017 | B18: =100*((HAVERM!C166/HAVERM!C154)-1) -> 6.9340017 | E18: 45017 | F18: =HAVERM!D166 -> 7.7 | I18: 46296 | K18: =HAVERQ!B54 -> 1.6 | L18: =100*((GMW!B222/GMW!B218)-1) -> 2.0986743 | N18: 2 | P18: 43922 | Q18: =HAVERM!E130 -> 1.86 | R18: =HAVERM!F130 -> 1.207 | S18: =HAVERM!G130 -> #N/A | T18: =HAVERM!H130 -> #N/A | V18: 43922 | W18: =HAVERM!I130 -> 1.824 | X18: =HAVERM!J130 -> 1.649 | Y18: =HAVERM!K130 -> #N/A | Z18: =HAVERM!L130 -> #N/A
A19: 45047 | B19: =100*((HAVERM!C167/HAVERM!C155)-1) -> 7.3211314 | E19: 45047 | F19: =HAVERM!D167 -> 7.9 | I19: 46388 | K19: =HAVERQ!B55 -> 1.5 | L19: =100*((GMW!B223/GMW!B219)-1) -> 2.1633594 | N19: 2 | P19: 43952 | Q19: =HAVERM!E131 -> 1.76 | R19: =HAVERM!F131 -> 1.387 | S19: =HAVERM!G131 -> #N/A | T19: =HAVERM!H131 -> #N/A | V19: 43952 | W19: =HAVERM!I131 -> 1.813 | X19: =HAVERM!J131 -> 1.403 | Y19: =HAVERM!K131 -> #N/A | Z19: =HAVERM!L131 -> #N/A
A20: 45078 | B20: =100*((HAVERM!C168/HAVERM!C156)-1) -> 7.1900826 | E20: 45078 | F20: =HAVERM!D168 -> 8.1 | I20: 46478 | K20: =HAVERQ!B56 -> 1.5 | L20: =100*((GMW!B224/GMW!B220)-1) -> 2.1882445 | N20: 2 | P20: 43983 | Q20: =HAVERM!E132 -> 1.19 | R20: =HAVERM!F132 -> 1.45 | S20: =HAVERM!G132 -> #N/A | T20: =HAVERM!H132 -> #N/A | V20: 43983 | W20: =HAVERM!I132 -> 1.6 | X20: =HAVERM!J132 -> 1.348 | Y20: =HAVERM!K132 -> #N/A | Z20: =HAVERM!L132 -> #N/A
A21: 45108 | B21: =100*((HAVERM!C169/HAVERM!C157)-1) -> 7.4651354 | E21: 45108 | F21: =HAVERM!D169 -> 8.1 | I21: 46569 | K21: =HAVERQ!B57 -> 1.5 | L21: =100*((GMW!B225/GMW!B221)-1) -> 2.2367092 | N21: 2 | P21: 44013 | Q21: =HAVERM!E133 -> 1.34 | R21: =HAVERM!F133 -> 1.663 | S21: =HAVERM!G133 -> #N/A | T21: =HAVERM!H133 -> #N/A | V21: 44013 | W21: =HAVERM!I133 -> 1.427 | X21: =HAVERM!J133 -> 1.5 | Y21: =HAVERM!K133 -> #N/A | Z21: =HAVERM!L133 -> #N/A
A22: 45139 | B22: =100*((HAVERM!C170/HAVERM!C158)-1) -> 6.7644662 | E22: 45139 | F22: =HAVERM!D170 -> 8.1 | I22: 46661 | L22: =100*((GMW!B226/GMW!B222)-1) -> 2.2573022 | N22: 2 | P22: 44044 | Q22: =HAVERM!E134 -> 1.08 | R22: =HAVERM!F134 -> 2.181 | S22: =HAVERM!G134 -> #N/A | T22: =HAVERM!H134 -> #N/A | V22: 44044 | W22: =HAVERM!I134 -> 1.2 | X22: =HAVERM!J134 -> 1.764 | Y22: =HAVERM!K134 -> #N/A | Z22: =HAVERM!L134 -> #N/A
A23: 45170 | B23: =100*((HAVERM!C171/HAVERM!C159)-1) -> 6.916192 | E23: 45170 | F23: =HAVERM!D171 -> 7.9 | P23: 44075 | Q23: =HAVERM!E135 -> 1.44 | R23: =HAVERM!F135 -> 1.887 | S23: =HAVERM!G135 -> #N/A | T23: =HAVERM!H135 -> #N/A | V23: 44075 | W23: =HAVERM!I135 -> 1.286 | X23: =HAVERM!J135 -> 1.91 | Y23: =HAVERM!K135 -> #N/A | Z23: =HAVERM!L135 -> #N/A
A24: 45200 | B24: =100*((HAVERM!C172/HAVERM!C160)-1) -> 6.542811 | E24: 45200 | F24: =HAVERM!D172 -> 7.2 | P24: 44105 | Q24: =HAVERM!E136 -> 2.21 | R24: =HAVERM!F136 -> 2.364 | S24: =HAVERM!G136 -> #N/A | T24: =HAVERM!H136 -> #N/A | V24: 44105 | W24: =HAVERM!I136 -> 1.576 | X24: =HAVERM!J136 -> 2.144 | Y24: =HAVERM!K136 -> #N/A | Z24: =HAVERM!L136 -> #N/A
A25: 45231 | B25: =100*((HAVERM!C173/HAVERM!C161)-1) -> 6.2096774 | E25: 45231 | F25: =HAVERM!D173 -> 6.6 | P25: 44136 | Q25: =HAVERM!E137 -> 1.69 | R25: =HAVERM!F137 -> 2.092 | S25: =HAVERM!G137 -> #N/A | T25: =HAVERM!H137 -> #N/A | V25: 44136 | W25: =HAVERM!I137 -> 1.78 | X25: =HAVERM!J137 -> 2.115 | Y25: =HAVERM!K137 -> #N/A | Z25: =HAVERM!L137 -> #N/A
A26: 45261 | B26: =100*((HAVERM!C174/HAVERM!C162)-1) -> 6.4 | E26: 45261 | F26: =HAVERM!D174 -> 6.2 | P26: 44166 | Q26: =HAVERM!E138 -> 0.85 | R26: =HAVERM!F138 -> 2.696 | S26: =HAVERM!G138 -> #N/A | T26: =HAVERM!H138 -> #N/A | V26: 44166 | W26: =HAVERM!I138 -> 1.582 | X26: =HAVERM!J138 -> 2.384 | Y26: =HAVERM!K138 -> #N/A | Z26: =HAVERM!L138 -> #N/A
A27: 45292 | B27: =100*((HAVERM!C175/HAVERM!C163)-1) -> 6.542811 | E27: 45292 | F27: =HAVERM!D175 -> 6.1 | P27: 44197 | Q27: =HAVERM!E139 -> 1.83 | R27: =HAVERM!F139 -> 2.509 | S27: =HAVERM!G139 -> #N/A | T27: =HAVERM!H139 -> #N/A | V27: 44197 | W27: =HAVERM!I139 -> 1.456 | X27: =HAVERM!J139 -> 2.433 | Y27: =HAVERM!K139 -> #N/A | Z27: =HAVERM!L139 -> #N/A
A28: 45323 | B28: =100*((HAVERM!C176/HAVERM!C164)-1) -> 6.0751399 | E28: 45323 | F28: =HAVERM!D176 -> 6 | P28: 44228 | Q28: =HAVERM!E140 -> 2.07 | R28: =HAVERM!F140 -> 2.719 | S28: =HAVERM!G140 -> #N/A | T28: =HAVERM!H140 -> #N/A | V28: 44228 | W28: =HAVERM!I140 -> 1.585 | X28: =HAVERM!J140 -> 2.642 | Y28: =HAVERM!K140 -> #N/A | Z28: =HAVERM!L140 -> #N/A
A29: 45352 | B29: =100*((HAVERM!C177/HAVERM!C165)-1) -> 5.952381 | E29: 45352 | F29: =HAVERM!D177 -> 5.9 | P29: 44256 | Q29: =HAVERM!E141 -> 1.65 | R29: =HAVERM!F141 -> 2.978 | S29: =HAVERM!G141 -> #N/A | T29: =HAVERM!H141 -> #N/A | V29: 44256 | W29: =HAVERM!I141 -> 1.852 | X29: =HAVERM!J141 -> 2.735 | Y29: =HAVERM!K141 -> #N/A | Z29: =HAVERM!L141 -> #N/A
A30: 45383 | B30: =100*((HAVERM!C178/HAVERM!C166)-1) -> 5.859375 | E30: 45383 | F30: =HAVERM!D178 -> 5.9 | P30: 44287 | Q30: =HAVERM!E142 -> 2.78 | R30: =HAVERM!F142 -> 3.137 | S30: =HAVERM!G142 -> #N/A | T30: =HAVERM!H142 -> #N/A | V30: 44287 | W30: =HAVERM!I142 -> 2.168 | X30: =HAVERM!J142 -> 2.945 | Y30: =HAVERM!K142 -> #N/A | Z30: =HAVERM!L142 -> #N/A
A31: 45413 | B31: =100*((HAVERM!C179/HAVERM!C167)-1) -> 5.7364341 | E31: 45413 | F31: =HAVERM!D179 -> 5.6 | P31: 44317 | Q31: =HAVERM!E143 -> 2.84 | R31: =HAVERM!F143 -> 3.449 | S31: =HAVERM!G143 -> #N/A | T31: =HAVERM!H143 -> #N/A | V31: 44317 | W31: =HAVERM!I143 -> 2.425 | X31: =HAVERM!J143 -> 3.188 | Y31: =HAVERM!K143 -> #N/A | Z31: =HAVERM!L143 -> #N/A
A32: 45444 | B32: =100*((HAVERM!C180/HAVERM!C168)-1) -> 5.7054742 | E32: 45444 | F32: =HAVERM!D180 -> 5.2 | G32: ='MPR Chart 2.21'!B32 -> 5.141 | P32: 44348 | Q32: =HAVERM!E144 -> 3.13 | R32: =HAVERM!F144 -> 3.255 | S32: =HAVERM!G144 -> #N/A | T32: =HAVERM!H144 -> #N/A | V32: 44348 | W32: =HAVERM!I144 -> 2.917 | X32: =HAVERM!J144 -> 3.28 | Y32: =HAVERM!K144 -> #N/A | Z32: =HAVERM!L144 -> #N/A
A33: 45474 | B33: =100*((HAVERM!C181/HAVERM!C169)-1) -> 5.1908397 | C33: ='MPR Chart 2.16'!L49 -> 5.563 | E33: 45474 | P33: 44378 | Q33: =HAVERM!E145 -> 3.76 | R33: =HAVERM!F145 -> 2.922 | S33: =HAVERM!G145 -> #N/A | T33: =HAVERM!H145 -> #N/A | V33: 44378 | W33: =HAVERM!I145 -> 3.244 | X33: =HAVERM!J145 -> 3.209 | Y33: =HAVERM!K145 -> #N/A | Z33: =HAVERM!L145 -> #N/A
A34: 45505 | C34: ='MPR Chart 2.16'!L50 -> 5.84 | E34: 45505 | P34: 44409 | Q34: =HAVERM!E146 -> 3.45 | R34: =HAVERM!F146 -> 3.223 | S34: =HAVERM!G146 -> #N/A | T34: =HAVERM!H146 -> #N/A | V34: 44409 | W34: =HAVERM!I146 -> 3.446 | X34: =HAVERM!J146 -> 3.133 | Y34: =HAVERM!K146 -> #N/A | Z34: =HAVERM!L146 -> #N/A
A35: 45536 | C35: ='MPR Chart 2.16'!L51 -> 5.52 | E35: 45536 | G35: ='MPR Chart 2.21'!B33 -> 4.83 | P35: 44440 | Q35: =HAVERM!E147 -> 4.54 | R35: =HAVERM!F147 -> 4.106 | S35: =HAVERM!G147 -> #N/A | T35: =HAVERM!H147 -> #N/A | V35: 44440 | W35: =HAVERM!I147 -> 3.916 | X35: =HAVERM!J147 -> 3.417 | Y35: =HAVERM!K147 -> #N/A | Z35: =HAVERM!L147 -> #N/A
A36: 45566 | C36: ='MPR Chart 2.16'!L52 -> 5.502 | E36: 45566 | P36: 44470 | Q36: =HAVERM!E148 -> 5.42 | R36: =HAVERM!F148 -> 4.707 | S36: =HAVERM!G148 -> #N/A | T36: =HAVERM!H148 -> #N/A | V36: 44470 | W36: =HAVERM!I148 -> 4.469 | X36: =HAVERM!J148 -> 4.012 | Y36: =HAVERM!K148 -> #N/A | Z36: =HAVERM!L148 -> #N/A
A37: 45597 | C37: ='MPR Chart 2.16'!L53 -> 5.395 | E37: 45597 | P37: 44501 | Q37: =HAVERM!E149 -> 4.82 | R37: =HAVERM!F149 -> 4.444 | S37: =HAVERM!G149 -> #N/A | T37: =HAVERM!H149 -> #N/A | V37: 44501 | W37: =HAVERM!I149 -> 4.925 | X37: =HAVERM!J149 -> 4.419 | Y37: =HAVERM!K149 -> #N/A | Z37: =HAVERM!L149 -> #N/A
A38: 45627 | C38: ='MPR Chart 2.16'!L54 -> 5.286 | E38: 45627 | P38: 44531 | Q38: =HAVERM!E150 -> 5.48 | R38: =HAVERM!F150 -> 5.099 | S38: =HAVERM!G150 -> #N/A | T38: =HAVERM!H150 -> #N/A | V38: 44531 | W38: =HAVERM!I150 -> 5.24 | X38: =HAVERM!J150 -> 4.75 | Y38: =HAVERM!K150 -> #N/A | Z38: =HAVERM!L150 -> #N/A
P39: 44562 | Q39: =HAVERM!E151 -> 5.41 | R39: =HAVERM!F151 -> 4.527 | S39: =HAVERM!G151 -> #N/A | T39: =HAVERM!H151 -> #N/A | V39: 44562 | W39: =HAVERM!I151 -> 5.235 | X39: =HAVERM!J151 -> 4.69 | Y39: =HAVERM!K151 -> #N/A | Z39: =HAVERM!L151 -> #N/A
P40: 44593 | Q40: =HAVERM!E152 -> 5.26 | R40: =HAVERM!F152 -> 4.892 | S40: =HAVERM!G152 -> #N/A | T40: =HAVERM!H152 -> #N/A | V40: 44593 | W40: =HAVERM!I152 -> 5.383 | X40: =HAVERM!J152 -> 4.839 | Y40: =HAVERM!K152 -> #N/A | Z40: =HAVERM!L152 -> #N/A
P41: 44621 | Q41: =HAVERM!E153 -> 6.84 | R41: =HAVERM!F153 -> 5.87 | S41: =HAVERM!G153 -> #N/A | T41: =HAVERM!H153 -> #N/A | V41: 44621 | W41: =HAVERM!I153 -> 5.834 | X41: =HAVERM!J153 -> 5.096 | Y41: =HAVERM!K153 -> #N/A | Z41: =HAVERM!L153 -> #N/A
P42: 44652 | Q42: =HAVERM!E154 -> 6.5 | R42: =HAVERM!F154 -> 5.998 | S42: =HAVERM!G154 -> #N/A | T42: =HAVERM!H154 -> #N/A | V42: 44652 | W42: =HAVERM!I154 -> 6.2 | X42: =HAVERM!J154 -> 5.587 | Y42: =HAVERM!K154 -> #N/A | Z42: =HAVERM!L154 -> #N/A
P43: 44682 | Q43: =HAVERM!E155 -> 7.28 | R43: =HAVERM!F155 -> 5.883 | S43: =HAVERM!G155 -> 5.5 | T43: =HAVERM!H155 -> 4.8 | V43: 44682 | W43: =HAVERM!I155 -> 6.874 | X43: =HAVERM!J155 -> 5.917 | Y43: =HAVERM!K155 -> 5.451 | Z43: =HAVERM!L155 -> 4.774
P44: 44713 | Q44: =HAVERM!E156 -> 7.44 | R44: =HAVERM!F156 -> 6.292 | S44: =HAVERM!G156 -> 5.7 | T44: =HAVERM!H156 -> 5.1 | V44: 44713 | W44: =HAVERM!I156 -> 7.076 | X44: =HAVERM!J156 -> 6.058 | Y44: =HAVERM!K156 -> 5.566 | Z44: =HAVERM!L156 -> 4.933
P45: 44743 | Q45: =HAVERM!E157 -> 7.96 | R45: =HAVERM!F157 -> 6.668 | S45: =HAVERM!G157 -> 5.5 | T45: =HAVERM!H157 -> 5.2 | V45: 44743 | W45: =HAVERM!I157 -> 7.56 | X45: =HAVERM!J157 -> 6.281 | Y45: =HAVERM!K157 -> 5.53 | Z45: =HAVERM!L157 -> 5.013
P46: 44774 | Q46: =HAVERM!E158 -> 7.63 | R46: =HAVERM!F158 -> 6.434 | S46: =HAVERM!G158 -> 6.4 | T46: =HAVERM!H158 -> 5.5 | V46: 44774 | W46: =HAVERM!I158 -> 7.676 | X46: =HAVERM!J158 -> 6.465 | Y46: =HAVERM!K158 -> 5.835 | Z46: =HAVERM!L158 -> 5.245
P47: 44805 | Q47: =HAVERM!E159 -> 7.41 | R47: =HAVERM!F159 -> 6.638 | S47: =HAVERM!G159 -> 6.5 | T47: =HAVERM!H159 -> 5.9 | V47: 44805 | W47: =HAVERM!I159 -> 7.665 | X47: =HAVERM!J159 -> 6.58 | Y47: =HAVERM!K159 -> 6.1 | Z47: =HAVERM!L159 -> 5.503
P48: 44835 | Q48: =HAVERM!E160 -> 7.76 | R48: =HAVERM!F160 -> 6.221 | S48: =HAVERM!G160 -> 6.1 | T48: =HAVERM!H160 -> 5.8 | V48: 44835 | W48: =HAVERM!I160 -> 7.599 | X48: =HAVERM!J160 -> 6.431 | Y48: =HAVERM!K160 -> 6.301 | Z48: =HAVERM!L160 -> 5.725
P49: 44866 | Q49: =HAVERM!E161 -> 7.2 | R49: =HAVERM!F161 -> 5.747 | S49: =HAVERM!G161 -> 6.1 | T49: =HAVERM!H161 -> 5.8 | V49: 44866 | W49: =HAVERM!I161 -> 7.456 | X49: =HAVERM!J161 -> 6.202 | Y49: =HAVERM!K161 -> 6.214 | Z49: =HAVERM!L161 -> 5.828
P50: 44896 | Q50: =HAVERM!E162 -> 8.54 | R50: =HAVERM!F162 -> 5.783 | S50: =HAVERM!G162 -> 6.6 | T50: =HAVERM!H162 -> 6.3 | V50: 44896 | W50: =HAVERM!I162 -> 7.832 | X50: =HAVERM!J162 -> 5.917 | Y50: =HAVERM!K162 -> 6.258 | Z50: =HAVERM!L162 -> 5.974
... P70: 45505 | Q70: =HAVERM!E182 -> 3.87 | R70: =HAVERM!F182 -> 3.366 | S70: =HAVERM!G182 -> 5.7 | T70: =HAVERM!H182 -> 4.1 | V70: 45505 | W70: =HAVERM!I182 -> 4.02 | X70: =HAVERM!J182 -> 3.551 | Y70: =HAVERM!K182 -> 5.771 | Z70: =HAVERM!L182 -> 4.068
P71: 45536 | V71: 45536
P72: 45566 | V72: 45566
P73: 45597 | V73: 45597
P74: 45627 | V74: 45627

Sheet Market expectations
A1: August MPR | C1: 15 working days to 22 July 2024 | BA1: November MPR | BC1: 15 working days to 28 October 2024
A2: Column # | B2: 9 | C2: =+B2+1 -> 10 | D2: =+C2+1 -> 11 | E2: =+D2+1 -> 12 | F2: =+E2+1 -> 13 | G2: =+F2+1 -> 14 | H2: =+G2+1 -> 15 | I2: =+H2+1 -> 16 | J2: =+I2+1 -> 17 | ... AX2: =+AW2+1 -> 57 | BA2: Column # | BB2: 9 | BC2: =+BB2+1 -> 10 | BD2: =+BC2+1 -> 11 | BE2: =+BD2+1 -> 12 | BF2: =+BE2+1 -> 13 | BG2: =+BF2+1 -> 14 | BH2: =+BG2+1 -> 15 | BI2: =+BH2+1 -> 16 | BJ2: =+BI2+1 -> 17 | ... CW2: =+CV2+1 -> 56
A3: Months | B3: =HAVERD!I$1 -> Overnight | C3: =HAVERD!J$1 -> 1 | D3: =HAVERD!K$1 -> 2 | E3: =HAVERD!L$1 -> 3 | F3: =HAVERD!M$1 -> 4 | G3: =HAVERD!N$1 -> 5 | H3: =HAVERD!O$1 -> 6 | I3: =HAVERD!P$1 -> 7 | ... AX3: =HAVERD!BE$1 -> 48 | BA3: Months | BB3: =HAVERD!J$1 -> 1 | BC3: =HAVERD!K$1 -> 2 | BD3: =HAVERD!L$1 -> 3 | BE3: =HAVERD!M$1 -> 4 | BF3: =HAVERD!N$1 -> 5 | BG3: =HAVERD!O$1 -> 6 | BH3: =HAVERD!P$1 -> 7 | BI3: =HAVERD!Q$1 -> 8 | ... CW3: =HAVERD!BE$1 -> 48
A4: Days | C4: 30.416667 | D4: =+C4+30.4166667 -> 60.833333 | E4: =+D4+30.4166667 -> 91.25 | F4: =+E4+30.4166667 -> 121.66667 | G4: =+F4+30.4166667 -> 152.08333 | H4: =+G4+30.4166667 -> 182.5 | I4: =+H4+30.4166667 -> 212.91667 | J4: =+I4+30.4166667 -> 243.33333 | K4: =+J4+30.4166667 -> 273.75 | ... AX4: =+AW4+30.4166667 -> 1460 | BA4: Days | BC4: 30.416667 | BD4: =+BC4+30.4166667 -> 60.833333 | BE4: =+BD4+30.4166667 -> 91.25 | BF4: =+BE4+30.4166667 -> 121.66667 | BG4: =+BF4+30.4166667 -> 152.08333 | BH4: =+BG4+30.4166667 -> 182.5 | BI4: =+BH4+30.4166667 -> 212.91667 | BJ4: =+BI4+30.4166667 -> 243.33333 | BK4: =+BJ4+30.4166667 -> 273.75 | ... CW4: =+CV4+30.4166667 -> 1429.5833
A5: Dates | BA5: Dates
A6: =A11-7 -> 45475 | B6: =A6 -> 45475 | C6: =$B6+C$4 -> 45505.417 | D6: =$B6+D$4 -> 45535.833 | E6: =$B6+E$4 -> 45566.25 | F6: =$B6+F$4 -> 45596.667 | G6: =$B6+G$4 -> 45627.083 | H6: =$B6+H$4 -> 45657.5 | I6: =$B6+I$4 -> 45687.917 | J6: =$B6+J$4 -> 45718.333 | ... AX6: =$B6+AX$4 -> 46935 | BA6: =BA11-7 -> 45573 | BB6: =BA6 -> 45573 | BC6: =$BA6+BC$4 -> 45603.417 | BD6: =$BA6+BD$4 -> 45633.833 | BE6: =$BA6+BE$4 -> 45664.25 | BF6: =$BA6+BF$4 -> 45694.667 | BG6: =$BA6+BG$4 -> 45725.083 | BH6: =$BA6+BH$4 -> 45755.5 | BI6: =$BA6+BI$4 -> 45785.917 | BJ6: =$BA6+BJ$4 -> 45816.333 | ... CW6: =$BA6+CW$4 -> 47002.583
A7: =A12-7 -> 45476 | B7: =A7 -> 45476 | C7: =$B7+C$4 -> 45506.417 | D7: =$B7+D$4 -> 45536.833 | E7: =$B7+E$4 -> 45567.25 | F7: =$B7+F$4 -> 45597.667 | G7: =$B7+G$4 -> 45628.083 | H7: =$B7+H$4 -> 45658.5 | I7: =$B7+I$4 -> 45688.917 | J7: =$B7+J$4 -> 45719.333 | ... AX7: =$B7+AX$4 -> 46936 | BA7: =BA12-7 -> 45574 | BB7: =BA7 -> 45574 | BC7: =$BA7+BC$4 -> 45604.417 | BD7: =$BA7+BD$4 -> 45634.833 | BE7: =$BA7+BE$4 -> 45665.25 | BF7: =$BA7+BF$4 -> 45695.667 | BG7: =$BA7+BG$4 -> 45726.083 | BH7: =$BA7+BH$4 -> 45756.5 | BI7: =$BA7+BI$4 -> 45786.917 | BJ7: =$BA7+BJ$4 -> 45817.333 | ... CW7: =$BA7+CW$4 -> 47003.583
A8: =A13-7 -> 45477 | B8: =A8 -> 45477 | C8: =$B8+C$4 -> 45507.417 | D8: =$B8+D$4 -> 45537.833 | E8: =$B8+E$4 -> 45568.25 | F8: =$B8+F$4 -> 45598.667 | G8: =$B8+G$4 -> 45629.083 | H8: =$B8+H$4 -> 45659.5 | I8: =$B8+I$4 -> 45689.917 | J8: =$B8+J$4 -> 45720.333 | ... AX8: =$B8+AX$4 -> 46937 | BA8: =BA13-7 -> 45575 | BB8: =BA8 -> 45575 | BC8: =$BA8+BC$4 -> 45605.417 | BD8: =$BA8+BD$4 -> 45635.833 | BE8: =$BA8+BE$4 -> 45666.25 | BF8: =$BA8+BF$4 -> 45696.667 | BG8: =$BA8+BG$4 -> 45727.083 | BH8: =$BA8+BH$4 -> 45757.5 | BI8: =$BA8+BI$4 -> 45787.917 | BJ8: =$BA8+BJ$4 -> 45818.333 | ... CW8: =$BA8+CW$4 -> 47004.583
A9: =A14-7 -> 45478 | B9: =A9 -> 45478 | C9: =$B9+C$4 -> 45508.417 | D9: =$B9+D$4 -> 45538.833 | E9: =$B9+E$4 -> 45569.25 | F9: =$B9+F$4 -> 45599.667 | G9: =$B9+G$4 -> 45630.083 | H9: =$B9+H$4 -> 45660.5 | I9: =$B9+I$4 -> 45690.917 | J9: =$B9+J$4 -> 45721.333 | ... AX9: =$B9+AX$4 -> 46938 | BA9: =BA14-7 -> 45576 | BB9: =BA9 -> 45576 | BC9: =$BA9+BC$4 -> 45606.417 | BD9: =$BA9+BD$4 -> 45636.833 | BE9: =$BA9+BE$4 -> 45667.25 | BF9: =$BA9+BF$4 -> 45697.667 | BG9: =$BA9+BG$4 -> 45728.083 | BH9: =$BA9+BH$4 -> 45758.5 | BI9: =$BA9+BI$4 -> 45788.917 | BJ9: =$BA9+BJ$4 -> 45819.333 | ... CW9: =$BA9+CW$4 -> 47005.583
A10: =A15-7 -> 45481 | B10: =A10 -> 45481 | C10: =$B10+C$4 -> 45511.417 | D10: =$B10+D$4 -> 45541.833 | E10: =$B10+E$4 -> 45572.25 | F10: =$B10+F$4 -> 45602.667 | G10: =$B10+G$4 -> 45633.083 | H10: =$B10+H$4 -> 45663.5 | I10: =$B10+I$4 -> 45693.917 | J10: =$B10+J$4 -> 45724.333 | ... AX10: =$B10+AX$4 -> 46941 | BA10: =BA15-7 -> 45579 | BB10: =BA10 -> 45579 | BC10: =$BA10+BC$4 -> 45609.417 | BD10: =$BA10+BD$4 -> 45639.833 | BE10: =$BA10+BE$4 -> 45670.25 | BF10: =$BA10+BF$4 -> 45700.667 | BG10: =$BA10+BG$4 -> 45731.083 | BH10: =$BA10+BH$4 -> 45761.5 | BI10: =$BA10+BI$4 -> 45791.917 | BJ10: =$BA10+BJ$4 -> 45822.333 | ... CW10: =$BA10+CW$4 -> 47008.583
A11: =A16-7 -> 45482 | B11: =A11 -> 45482 | C11: =$B11+C$4 -> 45512.417 | D11: =$B11+D$4 -> 45542.833 | E11: =$B11+E$4 -> 45573.25 | F11: =$B11+F$4 -> 45603.667 | G11: =$B11+G$4 -> 45634.083 | H11: =$B11+H$4 -> 45664.5 | I11: =$B11+I$4 -> 45694.917 | J11: =$B11+J$4 -> 45725.333 | ... AX11: =$B11+AX$4 -> 46942 | BA11: =BA16-7 -> 45580 | BB11: =BA11 -> 45580 | BC11: =$BA11+BC$4 -> 45610.417 | BD11: =$BA11+BD$4 -> 45640.833 | BE11: =$BA11+BE$4 -> 45671.25 | BF11: =$BA11+BF$4 -> 45701.667 | BG11: =$BA11+BG$4 -> 45732.083 | BH11: =$BA11+BH$4 -> 45762.5 | BI11: =$BA11+BI$4 -> 45792.917 | BJ11: =$BA11+BJ$4 -> 45823.333 | ... CW11: =$BA11+CW$4 -> 47009.583
A12: =A17-7 -> 45483 | B12: =A12 -> 45483 | C12: =$B12+C$4 -> 45513.417 | D12: =$B12+D$4 -> 45543.833 | E12: =$B12+E$4 -> 45574.25 | F12: =$B12+F$4 -> 45604.667 | G12: =$B12+G$4 -> 45635.083 | H12: =$B12+H$4 -> 45665.5 | I12: =$B12+I$4 -> 45695.917 | J12: =$B12+J$4 -> 45726.333 | ... AX12: =$B12+AX$4 -> 46943 | BA12: =BA17-7 -> 45581 | BB12: =BA12 -> 45581 | BC12: =$BA12+BC$4 -> 45611.417 | BD12: =$BA12+BD$4 -> 45641.833 | BE12: =$BA12+BE$4 -> 45672.25 | BF12: =$BA12+BF$4 -> 45702.667 | BG12: =$BA12+BG$4 -> 45733.083 | BH12: =$BA12+BH$4 -> 45763.5 | BI12: =$BA12+BI$4 -> 45793.917 | BJ12: =$BA12+BJ$4 -> 45824.333 | ... CW12: =$BA12+CW$4 -> 47010.583
A13: =A18-7 -> 45484 | B13: =A13 -> 45484 | C13: =$B13+C$4 -> 45514.417 | D13: =$B13+D$4 -> 45544.833 | E13: =$B13+E$4 -> 45575.25 | F13: =$B13+F$4 -> 45605.667 | G13: =$B13+G$4 -> 45636.083 | H13: =$B13+H$4 -> 45666.5 | I13: =$B13+I$4 -> 45696.917 | J13: =$B13+J$4 -> 45727.333 | ... AX13: =$B13+AX$4 -> 46944 | BA13: =BA18-7 -> 45582 | BB13: =BA13 -> 45582 | BC13: =$BA13+BC$4 -> 45612.417 | BD13: =$BA13+BD$4 -> 45642.833 | BE13: =$BA13+BE$4 -> 45673.25 | BF13: =$BA13+BF$4 -> 45703.667 | BG13: =$BA13+BG$4 -> 45734.083 | BH13: =$BA13+BH$4 -> 45764.5 | BI13: =$BA13+BI$4 -> 45794.917 | BJ13: =$BA13+BJ$4 -> 45825.333 | ... CW13: =$BA13+CW$4 -> 47011.583
A14: =A19-7 -> 45485 | B14: =A14 -> 45485 | C14: =$B14+C$4 -> 45515.417 | D14: =$B14+D$4 -> 45545.833 | E14: =$B14+E$4 -> 45576.25 | F14: =$B14+F$4 -> 45606.667 | G14: =$B14+G$4 -> 45637.083 | H14: =$B14+H$4 -> 45667.5 | I14: =$B14+I$4 -> 45697.917 | J14: =$B14+J$4 -> 45728.333 | ... AX14: =$B14+AX$4 -> 46945 | BA14: =BA19-7 -> 45583 | BB14: =BA14 -> 45583 | BC14: =$BA14+BC$4 -> 45613.417 | BD14: =$BA14+BD$4 -> 45643.833 | BE14: =$BA14+BE$4 -> 45674.25 | BF14: =$BA14+BF$4 -> 45704.667 | BG14: =$BA14+BG$4 -> 45735.083 | BH14: =$BA14+BH$4 -> 45765.5 | BI14: =$BA14+BI$4 -> 45795.917 | BJ14: =$BA14+BJ$4 -> 45826.333 | ... CW14: =$BA14+CW$4 -> 47012.583
A15: =A20-7 -> 45488 | B15: =A15 -> 45488 | C15: =$B15+C$4 -> 45518.417 | D15: =$B15+D$4 -> 45548.833 | E15: =$B15+E$4 -> 45579.25 | F15: =$B15+F$4 -> 45609.667 | G15: =$B15+G$4 -> 45640.083 | H15: =$B15+H$4 -> 45670.5 | I15: =$B15+I$4 -> 45700.917 | J15: =$B15+J$4 -> 45731.333 | ... AX15: =$B15+AX$4 -> 46948 | BA15: =BA20-7 -> 45586 | BB15: =BA15 -> 45586 | BC15: =$BA15+BC$4 -> 45616.417 | BD15: =$BA15+BD$4 -> 45646.833 | BE15: =$BA15+BE$4 -> 45677.25 | BF15: =$BA15+BF$4 -> 45707.667 | BG15: =$BA15+BG$4 -> 45738.083 | BH15: =$BA15+BH$4 -> 45768.5 | BI15: =$BA15+BI$4 -> 45798.917 | BJ15: =$BA15+BJ$4 -> 45829.333 | ... CW15: =$BA15+CW$4 -> 47015.583
A16: =+A17-1 -> 45489 | B16: =A16 -> 45489 | C16: =$B16+C$4 -> 45519.417 | D16: =$B16+D$4 -> 45549.833 | E16: =$B16+E$4 -> 45580.25 | F16: =$B16+F$4 -> 45610.667 | G16: =$B16+G$4 -> 45641.083 | H16: =$B16+H$4 -> 45671.5 | I16: =$B16+I$4 -> 45701.917 | J16: =$B16+J$4 -> 45732.333 | ... AX16: =$B16+AX$4 -> 46949 | BA16: =+BA17-1 -> 45587 | BB16: =BA16 -> 45587 | BC16: =$BA16+BC$4 -> 45617.417 | BD16: =$BA16+BD$4 -> 45647.833 | BE16: =$BA16+BE$4 -> 45678.25 | BF16: =$BA16+BF$4 -> 45708.667 | BG16: =$BA16+BG$4 -> 45739.083 | BH16: =$BA16+BH$4 -> 45769.5 | BI16: =$BA16+BI$4 -> 45799.917 | BJ16: =$BA16+BJ$4 -> 45830.333 | ... CW16: =$BA16+CW$4 -> 47016.583
A17: =+A18-1 -> 45490 | B17: =A17 -> 45490 | C17: =$B17+C$4 -> 45520.417 | D17: =$B17+D$4 -> 45550.833 | E17: =$B17+E$4 -> 45581.25 | F17: =$B17+F$4 -> 45611.667 | G17: =$B17+G$4 -> 45642.083 | H17: =$B17+H$4 -> 45672.5 | I17: =$B17+I$4 -> 45702.917 | J17: =$B17+J$4 -> 45733.333 | ... AX17: =$B17+AX$4 -> 46950 | BA17: =+BA18-1 -> 45588 | BB17: =BA17 -> 45588 | BC17: =$BA17+BC$4 -> 45618.417 | BD17: =$BA17+BD$4 -> 45648.833 | BE17: =$BA17+BE$4 -> 45679.25 | BF17: =$BA17+BF$4 -> 45709.667 | BG17: =$BA17+BG$4 -> 45740.083 | BH17: =$BA17+BH$4 -> 45770.5 | BI17: =$BA17+BI$4 -> 45800.917 | BJ17: =$BA17+BJ$4 -> 45831.333 | ... CW17: =$BA17+CW$4 -> 47017.583
A18: =+A19-1 -> 45491 | B18: =A18 -> 45491 | C18: =$B18+C$4 -> 45521.417 | D18: =$B18+D$4 -> 45551.833 | E18: =$B18+E$4 -> 45582.25 | F18: =$B18+F$4 -> 45612.667 | G18: =$B18+G$4 -> 45643.083 | H18: =$B18+H$4 -> 45673.5 | I18: =$B18+I$4 -> 45703.917 | J18: =$B18+J$4 -> 45734.333 | ... AX18: =$B18+AX$4 -> 46951 | BA18: =+BA19-1 -> 45589 | BB18: =BA18 -> 45589 | BC18: =$BA18+BC$4 -> 45619.417 | BD18: =$BA18+BD$4 -> 45649.833 | BE18: =$BA18+BE$4 -> 45680.25 | BF18: =$BA18+BF$4 -> 45710.667 | BG18: =$BA18+BG$4 -> 45741.083 | BH18: =$BA18+BH$4 -> 45771.5 | BI18: =$BA18+BI$4 -> 45801.917 | BJ18: =$BA18+BJ$4 -> 45832.333 | ... CW18: =$BA18+CW$4 -> 47018.583
A19: 45492 | B19: =A19 -> 45492 | C19: =$B19+C$4 -> 45522.417 | D19: =$B19+D$4 -> 45552.833 | E19: =$B19+E$4 -> 45583.25 | F19: =$B19+F$4 -> 45613.667 | G19: =$B19+G$4 -> 45644.083 | H19: =$B19+H$4 -> 45674.5 | I19: =$B19+I$4 -> 45704.917 | J19: =$B19+J$4 -> 45735.333 | ... AX19: =$B19+AX$4 -> 46952 | BA19: 45590 | BB19: =BA19 -> 45590 | BC19: =$BA19+BC$4 -> 45620.417 | BD19: =$BA19+BD$4 -> 45650.833 | BE19: =$BA19+BE$4 -> 45681.25 | BF19: =$BA19+BF$4 -> 45711.667 | BG19: =$BA19+BG$4 -> 45742.083 | BH19: =$BA19+BH$4 -> 45772.5 | BI19: =$BA19+BI$4 -> 45802.917 | BJ19: =$BA19+BJ$4 -> 45833.333 | ... CW19: =$BA19+CW$4 -> 47019.583
A20: 45495 | B20: =A20 -> 45495 | C20: =$B20+C$4 -> 45525.417 | D20: =$B20+D$4 -> 45555.833 | E20: =$B20+E$4 -> 45586.25 | F20: =$B20+F$4 -> 45616.667 | G20: =$B20+G$4 -> 45647.083 | H20: =$B20+H$4 -> 45677.5 | I20: =$B20+I$4 -> 45707.917 | J20: =$B20+J$4 -> 45738.333 | ... AX20: =$B20+AX$4 -> 46955 | BA20: 45593 | BB20: =BA20 -> 45593 | BC20: =$BA20+BC$4 -> 45623.417 | BD20: =$BA20+BD$4 -> 45653.833 | BE20: =$BA20+BE$4 -> 45684.25 | BF20: =$BA20+BF$4 -> 45714.667 | BG20: =$BA20+BG$4 -> 45745.083 | BH20: =$BA20+BH$4 -> 45775.5 | BI20: =$BA20+BI$4 -> 45805.917 | BJ20: =$BA20+BJ$4 -> 45836.333 | ... CW20: =$BA20+CW$4 -> 47022.583
A22: Market expectations | BA22: Market expectations
A23: =A6 -> 45475 | B23: =VLOOKUP($A23,HAVERD!$A:$BS,B$2,FALSE) -> 5.2 | C23: =VLOOKUP($A23,HAVERD!$A:$BS,C$2,FALSE) -> 5.136252 | D23: =VLOOKUP($A23,HAVERD!$A:$BS,D$2,FALSE) -> 5.0458777 | E23: =VLOOKUP($A23,HAVERD!$A:$BS,E$2,FALSE) -> 4.9812657 | F23: =VLOOKUP($A23,HAVERD!$A:$BS,F$2,FALSE) -> 4.9207792 | G23: =VLOOKUP($A23,HAVERD!$A:$BS,G$2,FALSE) -> 4.8541057 | H23: =VLOOKUP($A23,HAVERD!$A:$BS,H$2,FALSE) -> 4.7827699 | I23: =VLOOKUP($A23,HAVERD!$A:$BS,I$2,FALSE) -> 4.7105142 | ... AX23: =VLOOKUP($A23,HAVERD!$A:$BS,AX$2,FALSE) -> 3.5194949 | BA23: =BA6 -> 45573 | BB23: =VLOOKUP($BA23,HAVERD!$A:$BS,BB$2,FALSE) -> #N/A | BC23: =VLOOKUP($BA23,HAVERD!$A:$BS,BC$2,FALSE) -> #N/A | BD23: =VLOOKUP($BA23,HAVERD!$A:$BS,BD$2,FALSE) -> #N/A | BE23: =VLOOKUP($BA23,HAVERD!$A:$BS,BE$2,FALSE) -> #N/A | BF23: =VLOOKUP($BA23,HAVERD!$A:$BS,BF$2,FALSE) -> #N/A | BG23: =VLOOKUP($BA23,HAVERD!$A:$BS,BG$2,FALSE) -> #N/A | BH23: =VLOOKUP($BA23,HAVERD!$A:$BS,BH$2,FALSE) -> #N/A | BI23: =VLOOKUP($BA23,HAVERD!$A:$BS,BI$2,FALSE) -> #N/A | ... CW23: =VLOOKUP($BA23,HAVERD!$A:$BS,CW$2,FALSE) -> #N/A
A24: =A7 -> 45476 | B24: =VLOOKUP($A24,HAVERD!$A:$BS,B$2,FALSE) -> 5.2 | C24: =VLOOKUP($A24,HAVERD!$A:$BS,C$2,FALSE) -> 5.1234718 | D24: =VLOOKUP($A24,HAVERD!$A:$BS,D$2,FALSE) -> 5.0360844 | E24: =VLOOKUP($A24,HAVERD!$A:$BS,E$2,FALSE) -> 4.9704607 | F24: =VLOOKUP($A24,HAVERD!$A:$BS,F$2,FALSE) -> 4.9070404 | G24: =VLOOKUP($A24,HAVERD!$A:$BS,G$2,FALSE) -> 4.8371358 | H24: =VLOOKUP($A24,HAVERD!$A:$BS,H$2,FALSE) -> 4.7628149 | I24: =VLOOKUP($A24,HAVERD!$A:$BS,I$2,FALSE) -> 4.687981 | ... AX24: =VLOOKUP($A24,HAVERD!$A:$BS,AX$2,FALSE) -> 3.4500435 | BA24: =BA7 -> 45574 | BB24: =VLOOKUP($BA24,HAVERD!$A:$BS,BB$2,FALSE) -> #N/A | BC24: =VLOOKUP($BA24,HAVERD!$A:$BS,BC$2,FALSE) -> #N/A | BD24: =VLOOKUP($BA24,HAVERD!$A:$BS,BD$2,FALSE) -> #N/A | BE24: =VLOOKUP($BA24,HAVERD!$A:$BS,BE$2,FALSE) -> #N/A | BF24: =VLOOKUP($BA24,HAVERD!$A:$BS,BF$2,FALSE) -> #N/A | BG24: =VLOOKUP($BA24,HAVERD!$A:$BS,BG$2,FALSE) -> #N/A | BH24: =VLOOKUP($BA24,HAVERD!$A:$BS,BH$2,FALSE) -> #N/A | BI24: =VLOOKUP($BA24,HAVERD!$A:$BS,BI$2,FALSE) -> #N/A | ... CW24: =VLOOKUP($BA24,HAVERD!$A:$BS,CW$2,FALSE) -> #N/A
A25: =A8 -> 45477 | B25: =VLOOKUP($A25,HAVERD!$A:$BS,B$2,FALSE) -> 5.2 | C25: =VLOOKUP($A25,HAVERD!$A:$BS,C$2,FALSE) -> 5.1204583 | D25: =VLOOKUP($A25,HAVERD!$A:$BS,D$2,FALSE) -> 5.0323288 | E25: =VLOOKUP($A25,HAVERD!$A:$BS,E$2,FALSE) -> 4.9651069 | F25: =VLOOKUP($A25,HAVERD!$A:$BS,F$2,FALSE) -> 4.8999988 | G25: =VLOOKUP($A25,HAVERD!$A:$BS,G$2,FALSE) -> 4.8292264 | H25: =VLOOKUP($A25,HAVERD!$A:$BS,H$2,FALSE) -> 4.7546948 | I25: =VLOOKUP($A25,HAVERD!$A:$BS,I$2,FALSE) -> 4.6797389 | ... AX25: =VLOOKUP($A25,HAVERD!$A:$BS,AX$2,FALSE) -> 3.499697 | BA25: =BA8 -> 45575 | BB25: =VLOOKUP($BA25,HAVERD!$A:$BS,BB$2,FALSE) -> #N/A | BC25: =VLOOKUP($BA25,HAVERD!$A:$BS,BC$2,FALSE) -> #N/A | BD25: =VLOOKUP($BA25,HAVERD!$A:$BS,BD$2,FALSE) -> #N/A | BE25: =VLOOKUP($BA25,HAVERD!$A:$BS,BE$2,FALSE) -> #N/A | BF25: =VLOOKUP($BA25,HAVERD!$A:$BS,BF$2,FALSE) -> #N/A | BG25: =VLOOKUP($BA25,HAVERD!$A:$BS,BG$2,FALSE) -> #N/A | BH25: =VLOOKUP($BA25,HAVERD!$A:$BS,BH$2,FALSE) -> #N/A | BI25: =VLOOKUP($BA25,HAVERD!$A:$BS,BI$2,FALSE) -> #N/A | ... CW25: =VLOOKUP($BA25,HAVERD!$A:$BS,CW$2,FALSE) -> #N/A
A26: =A9 -> 45478 | B26: =VLOOKUP($A26,HAVERD!$A:$BS,B$2,FALSE) -> 5.2 | C26: =VLOOKUP($A26,HAVERD!$A:$BS,C$2,FALSE) -> 5.1110264 | D26: =VLOOKUP($A26,HAVERD!$A:$BS,D$2,FALSE) -> 5.0182524 | E26: =VLOOKUP($A26,HAVERD!$A:$BS,E$2,FALSE) -> 4.9469981 | F26: =VLOOKUP($A26,HAVERD!$A:$BS,F$2,FALSE) -> 4.8774441 | G26: =VLOOKUP($A26,HAVERD!$A:$BS,G$2,FALSE) -> 4.8016677 | H26: =VLOOKUP($A26,HAVERD!$A:$BS,H$2,FALSE) -> 4.7220228 | I26: =VLOOKUP($A26,HAVERD!$A:$BS,I$2,FALSE) -> 4.6420148 | ... AX26: =VLOOKUP($A26,HAVERD!$A:$BS,AX$2,FALSE) -> 3.4525486 | BA26: =BA9 -> 45576 | BB26: =VLOOKUP($BA26,HAVERD!$A:$BS,BB$2,FALSE) -> #N/A | BC26: =VLOOKUP($BA26,HAVERD!$A:$BS,BC$2,FALSE) -> #N/A | BD26: =VLOOKUP($BA26,HAVERD!$A:$BS,BD$2,FALSE) -> #N/A | BE26: =VLOOKUP($BA26,HAVERD!$A:$BS,BE$2,FALSE) -> #N/A | BF26: =VLOOKUP($BA26,HAVERD!$A:$BS,BF$2,FALSE) -> #N/A | BG26: =VLOOKUP($BA26,HAVERD!$A:$BS,BG$2,FALSE) -> #N/A | BH26: =VLOOKUP($BA26,HAVERD!$A:$BS,BH$2,FALSE) -> #N/A | BI26: =VLOOKUP($BA26,HAVERD!$A:$BS,BI$2,FALSE) -> #N/A | ... CW26: =VLOOKUP($BA26,HAVERD!$A:$BS,CW$2,FALSE) -> #N/A
A27: =A10 -> 45481 | B27: =VLOOKUP($A27,HAVERD!$A:$BS,B$2,FALSE) -> 5.2 | C27: =VLOOKUP($A27,HAVERD!$A:$BS,C$2,FALSE) -> 5.1003777 | D27: =VLOOKUP($A27,HAVERD!$A:$BS,D$2,FALSE) -> 5.0193512 | E27: =VLOOKUP($A27,HAVERD!$A:$BS,E$2,FALSE) -> 4.9524209 | F27: =VLOOKUP($A27,HAVERD!$A:$BS,F$2,FALSE) -> 4.8817792 | G27: =VLOOKUP($A27,HAVERD!$A:$BS,G$2,FALSE) -> 4.8028356 | H27: =VLOOKUP($A27,HAVERD!$A:$BS,H$2,FALSE) -> 4.7200436 | I27: =VLOOKUP($A27,HAVERD!$A:$BS,I$2,FALSE) -> 4.6378883 | ... AX27: =VLOOKUP($A27,HAVERD!$A:$BS,AX$2,FALSE) -> 3.4001976 | BA27: =BA10 -> 45579 | BB27: =VLOOKUP($BA27,HAVERD!$A:$BS,BB$2,FALSE) -> #N/A | BC27: =VLOOKUP($BA27,HAVERD!$A:$BS,BC$2,FALSE) -> #N/A | BD27: =VLOOKUP($BA27,HAVERD!$A:$BS,BD$2,FALSE) -> #N/A | BE27: =VLOOKUP($BA27,HAVERD!$A:$BS,BE$2,FALSE) -> #N/A | BF27: =VLOOKUP($BA27,HAVERD!$A:$BS,BF$2,FALSE) -> #N/A | BG27: =VLOOKUP($BA27,HAVERD!$A:$BS,BG$2,FALSE) -> #N/A | BH27: =VLOOKUP($BA27,HAVERD!$A:$BS,BH$2,FALSE) -> #N/A | BI27: =VLOOKUP($BA27,HAVERD!$A:$BS,BI$2,FALSE) -> #N/A | ... CW27: =VLOOKUP($BA27,HAVERD!$A:$BS,CW$2,FALSE) -> #N/A
A28: =A11 -> 45482 | B28: =VLOOKUP($A28,HAVERD!$A:$BS,B$2,FALSE) -> 5.2 | C28: =VLOOKUP($A28,HAVERD!$A:$BS,C$2,FALSE) -> 5.096547 | D28: =VLOOKUP($A28,HAVERD!$A:$BS,D$2,FALSE) -> 5.0182862 | E28: =VLOOKUP($A28,HAVERD!$A:$BS,E$2,FALSE) -> 4.9517053 | F28: =VLOOKUP($A28,HAVERD!$A:$BS,F$2,FALSE) -> 4.8809924 | G28: =VLOOKUP($A28,HAVERD!$A:$BS,G$2,FALSE) -> 4.8026843 | H28: =VLOOKUP($A28,HAVERD!$A:$BS,H$2,FALSE) -> 4.7214162 | I28: =VLOOKUP($A28,HAVERD!$A:$BS,I$2,FALSE) -> 4.641473 | ... AX28: =VLOOKUP($A28,HAVERD!$A:$BS,AX$2,FALSE) -> 3.4410117 | BA28: =BA11 -> 45580 | BB28: =VLOOKUP($BA28,HAVERD!$A:$BS,BB$2,FALSE) -> #N/A | BC28: =VLOOKUP($BA28,HAVERD!$A:$BS,BC$2,FALSE) -> #N/A | BD28: =VLOOKUP($BA28,HAVERD!$A:$BS,BD$2,FALSE) -> #N/A | BE28: =VLOOKUP($BA28,HAVERD!$A:$BS,BE$2,FALSE) -> #N/A | BF28: =VLOOKUP($BA28,HAVERD!$A:$BS,BF$2,FALSE) -> #N/A | BG28: =VLOOKUP($BA28,HAVERD!$A:$BS,BG$2,FALSE) -> #N/A | BH28: =VLOOKUP($BA28,HAVERD!$A:$BS,BH$2,FALSE) -> #N/A | BI28: =VLOOKUP($BA28,HAVERD!$A:$BS,BI$2,FALSE) -> #N/A | ... CW28: =VLOOKUP($BA28,HAVERD!$A:$BS,CW$2,FALSE) -> #N/A
A29: =A12 -> 45483 | B29: =VLOOKUP($A29,HAVERD!$A:$BS,B$2,FALSE) -> 5.2 | C29: =VLOOKUP($A29,HAVERD!$A:$BS,C$2,FALSE) -> 5.1042224 | D29: =VLOOKUP($A29,HAVERD!$A:$BS,D$2,FALSE) -> 5.0320985 | E29: =VLOOKUP($A29,HAVERD!$A:$BS,E$2,FALSE) -> 4.9630142 | F29: =VLOOKUP($A29,HAVERD!$A:$BS,F$2,FALSE) -> 4.8865742 | G29: =VLOOKUP($A29,HAVERD!$A:$BS,G$2,FALSE) -> 4.8036903 | H29: =VLOOKUP($A29,HAVERD!$A:$BS,H$2,FALSE) -> 4.7199091 | I29: =VLOOKUP($A29,HAVERD!$A:$BS,I$2,FALSE) -> 4.6387821 | ... AX29: =VLOOKUP($A29,HAVERD!$A:$BS,AX$2,FALSE) -> 3.4171134 | BA29: =BA12 -> 45581 | BB29: =VLOOKUP($BA29,HAVERD!$A:$BS,BB$2,FALSE) -> #N/A | BC29: =VLOOKUP($BA29,HAVERD!$A:$BS,BC$2,FALSE) -> #N/A | BD29: =VLOOKUP($BA29,HAVERD!$A:$BS,BD$2,FALSE) -> #N/A | BE29: =VLOOKUP($BA29,HAVERD!$A:$BS,BE$2,FALSE) -> #N/A | BF29: =VLOOKUP($BA29,HAVERD!$A:$BS,BF$2,FALSE) -> #N/A | BG29: =VLOOKUP($BA29,HAVERD!$A:$BS,BG$2,FALSE) -> #N/A | BH29: =VLOOKUP($BA29,HAVERD!$A:$BS,BH$2,FALSE) -> #N/A | BI29: =VLOOKUP($BA29,HAVERD!$A:$BS,BI$2,FALSE) -> #N/A | ... CW29: =VLOOKUP($BA29,HAVERD!$A:$BS,CW$2,FALSE) -> #N/A
A30: =A13 -> 45484 | B30: =VLOOKUP($A30,HAVERD!$A:$BS,B$2,FALSE) -> 5.2 | C30: =VLOOKUP($A30,HAVERD!$A:$BS,C$2,FALSE) -> 5.0945082 | D30: =VLOOKUP($A30,HAVERD!$A:$BS,D$2,FALSE) -> 5.0217773 | E30: =VLOOKUP($A30,HAVERD!$A:$BS,E$2,FALSE) -> 4.9511235 | F30: =VLOOKUP($A30,HAVERD!$A:$BS,F$2,FALSE) -> 4.8706331 | G30: =VLOOKUP($A30,HAVERD!$A:$BS,G$2,FALSE) -> 4.7813489 | H30: =VLOOKUP($A30,HAVERD!$A:$BS,H$2,FALSE) -> 4.6895095 | I30: =VLOOKUP($A30,HAVERD!$A:$BS,I$2,FALSE) -> 4.5990318 | ... AX30: =VLOOKUP($A30,HAVERD!$A:$BS,AX$2,FALSE) -> 3.3787976 | BA30: =BA13 -> 45582 | BB30: =VLOOKUP($BA30,HAVERD!$A:$BS,BB$2,FALSE) -> #N/A | BC30: =VLOOKUP($BA30,HAVERD!$A:$BS,BC$2,FALSE) -> #N/A | BD30: =VLOOKUP($BA30,HAVERD!$A:$BS,BD$2,FALSE) -> #N/A | BE30: =VLOOKUP($BA30,HAVERD!$A:$BS,BE$2,FALSE) -> #N/A | BF30: =VLOOKUP($BA30,HAVERD!$A:$BS,BF$2,FALSE) -> #N/A | BG30: =VLOOKUP($BA30,HAVERD!$A:$BS,BG$2,FALSE) -> #N/A | BH30: =VLOOKUP($BA30,HAVERD!$A:$BS,BH$2,FALSE) -> #N/A | BI30: =VLOOKUP($BA30,HAVERD!$A:$BS,BI$2,FALSE) -> #N/A | ... CW30: =VLOOKUP($BA30,HAVERD!$A:$BS,CW$2,FALSE) -> #N/A
A31: =A14 -> 45485 | B31: =VLOOKUP($A31,HAVERD!$A:$BS,B$2,FALSE) -> 5.2 | C31: =VLOOKUP($A31,HAVERD!$A:$BS,C$2,FALSE) -> 5.1031083 | D31: =VLOOKUP($A31,HAVERD!$A:$BS,D$2,FALSE) -> 5.0352073 | E31: =VLOOKUP($A31,HAVERD!$A:$BS,E$2,FALSE) -> 4.9632403 | F31: =VLOOKUP($A31,HAVERD!$A:$BS,F$2,FALSE) -> 4.8806377 | G31: =VLOOKUP($A31,HAVERD!$A:$BS,G$2,FALSE) -> 4.7906448 | H31: =VLOOKUP($A31,HAVERD!$A:$BS,H$2,FALSE) -> 4.6995387 | I31: =VLOOKUP($A31,HAVERD!$A:$BS,I$2,FALSE) -> 4.6110254 | ... AX31: =VLOOKUP($A31,HAVERD!$A:$BS,AX$2,FALSE) -> 3.4355071 | BA31: =BA14 -> 45583 | BB31: =VLOOKUP($BA31,HAVERD!$A:$BS,BB$2,FALSE) -> #N/A | BC31: =VLOOKUP($BA31,HAVERD!$A:$BS,BC$2,FALSE) -> #N/A | BD31: =VLOOKUP($BA31,HAVERD!$A:$BS,BD$2,FALSE) -> #N/A | BE31: =VLOOKUP($BA31,HAVERD!$A:$BS,BE$2,FALSE) -> #N/A | BF31: =VLOOKUP($BA31,HAVERD!$A:$BS,BF$2,FALSE) -> #N/A | BG31: =VLOOKUP($BA31,HAVERD!$A:$BS,BG$2,FALSE) -> #N/A | BH31: =VLOOKUP($BA31,HAVERD!$A:$BS,BH$2,FALSE) -> #N/A | BI31: =VLOOKUP($BA31,HAVERD!$A:$BS,BI$2,FALSE) -> #N/A | ... CW31: =VLOOKUP($BA31,HAVERD!$A:$BS,CW$2,FALSE) -> #N/A
A32: =A15 -> 45488 | B32: =VLOOKUP($A32,HAVERD!$A:$BS,B$2,FALSE) -> 5.2 | C32: =VLOOKUP($A32,HAVERD!$A:$BS,C$2,FALSE) -> 5.0946079 | D32: =VLOOKUP($A32,HAVERD!$A:$BS,D$2,FALSE) -> 5.0373513 | E32: =VLOOKUP($A32,HAVERD!$A:$BS,E$2,FALSE) -> 4.9645256 | F32: =VLOOKUP($A32,HAVERD!$A:$BS,F$2,FALSE) -> 4.8771415 | G32: =VLOOKUP($A32,HAVERD!$A:$BS,G$2,FALSE) -> 4.7822119 | H32: =VLOOKUP($A32,HAVERD!$A:$BS,H$2,FALSE) -> 4.6868572 | I32: =VLOOKUP($A32,HAVERD!$A:$BS,I$2,FALSE) -> 4.5953285 | ... AX32: =VLOOKUP($A32,HAVERD!$A:$BS,AX$2,FALSE) -> 3.3980712 | BA32: =BA15 -> 45586 | BB32: =VLOOKUP($BA32,HAVERD!$A:$BS,BB$2,FALSE) -> #N/A | BC32: =VLOOKUP($BA32,HAVERD!$A:$BS,BC$2,FALSE) -> #N/A | BD32: =VLOOKUP($BA32,HAVERD!$A:$BS,BD$2,FALSE) -> #N/A | BE32: =VLOOKUP($BA32,HAVERD!$A:$BS,BE$2,FALSE) -> #N/A | BF32: =VLOOKUP($BA32,HAVERD!$A:$BS,BF$2,FALSE) -> #N/A | BG32: =VLOOKUP($BA32,HAVERD!$A:$BS,BG$2,FALSE) -> #N/A | BH32: =VLOOKUP($BA32,HAVERD!$A:$BS,BH$2,FALSE) -> #N/A | BI32: =VLOOKUP($BA32,HAVERD!$A:$BS,BI$2,FALSE) -> #N/A | ... CW32: =VLOOKUP($BA32,HAVERD!$A:$BS,CW$2,FALSE) -> #N/A
A33: =A16 -> 45489 | B33: =VLOOKUP($A33,HAVERD!$A:$BS,B$2,FALSE) -> 5.2 | C33: =VLOOKUP($A33,HAVERD!$A:$BS,C$2,FALSE) -> 5.0913668 | D33: =VLOOKUP($A33,HAVERD!$A:$BS,D$2,FALSE) -> 5.0388587 | E33: =VLOOKUP($A33,HAVERD!$A:$BS,E$2,FALSE) -> 4.9656485 | F33: =VLOOKUP($A33,HAVERD!$A:$BS,F$2,FALSE) -> 4.8757257 | G33: =VLOOKUP($A33,HAVERD!$A:$BS,G$2,FALSE) -> 4.7770689 | H33: =VLOOKUP($A33,HAVERD!$A:$BS,H$2,FALSE) -> 4.6770052 | I33: =VLOOKUP($A33,HAVERD!$A:$BS,I$2,FALSE) -> 4.5801525 | ... AX33: =VLOOKUP($A33,HAVERD!$A:$BS,AX$2,FALSE) -> 3.3356155 | BA33: =BA16 -> 45587 | BB33: =VLOOKUP($BA33,HAVERD!$A:$BS,BB$2,FALSE) -> #N/A | BC33: =VLOOKUP($BA33,HAVERD!$A:$BS,BC$2,FALSE) -> #N/A | BD33: =VLOOKUP($BA33,HAVERD!$A:$BS,BD$2,FALSE) -> #N/A | BE33: =VLOOKUP($BA33,HAVERD!$A:$BS,BE$2,FALSE) -> #N/A | BF33: =VLOOKUP($BA33,HAVERD!$A:$BS,BF$2,FALSE) -> #N/A | BG33: =VLOOKUP($BA33,HAVERD!$A:$BS,BG$2,FALSE) -> #N/A | BH33: =VLOOKUP($BA33,HAVERD!$A:$BS,BH$2,FALSE) -> #N/A | BI33: =VLOOKUP($BA33,HAVERD!$A:$BS,BI$2,FALSE) -> #N/A | ... CW33: =VLOOKUP($BA33,HAVERD!$A:$BS,CW$2,FALSE) -> #N/A
A34: =A17 -> 45490 | B34: =VLOOKUP($A34,HAVERD!$A:$BS,B$2,FALSE) -> 5.2 | C34: =VLOOKUP($A34,HAVERD!$A:$BS,C$2,FALSE) -> 5.114171 | D34: =VLOOKUP($A34,HAVERD!$A:$BS,D$2,FALSE) -> 5.0628366 | E34: =VLOOKUP($A34,HAVERD!$A:$BS,E$2,FALSE) -> 4.9891878 | F34: =VLOOKUP($A34,HAVERD!$A:$BS,F$2,FALSE) -> 4.9001319 | G34: =VLOOKUP($A34,HAVERD!$A:$BS,G$2,FALSE) -> 4.8037042 | H34: =VLOOKUP($A34,HAVERD!$A:$BS,H$2,FALSE) -> 4.7062092 | I34: =VLOOKUP($A34,HAVERD!$A:$BS,I$2,FALSE) -> 4.6115039 | ... AX34: =VLOOKUP($A34,HAVERD!$A:$BS,AX$2,FALSE) -> 3.3739323 | BA34: =BA17 -> 45588 | BB34: =VLOOKUP($BA34,HAVERD!$A:$BS,BB$2,FALSE) -> #N/A | BC34: =VLOOKUP($BA34,HAVERD!$A:$BS,BC$2,FALSE) -> #N/A | BD34: =VLOOKUP($BA34,HAVERD!$A:$BS,BD$2,FALSE) -> #N/A | BE34: =VLOOKUP($BA34,HAVERD!$A:$BS,BE$2,FALSE) -> #N/A | BF34: =VLOOKUP($BA34,HAVERD!$A:$BS,BF$2,FALSE) -> #N/A | BG34: =VLOOKUP($BA34,HAVERD!$A:$BS,BG$2,FALSE) -> #N/A | BH34: =VLOOKUP($BA34,HAVERD!$A:$BS,BH$2,FALSE) -> #N/A | BI34: =VLOOKUP($BA34,HAVERD!$A:$BS,BI$2,FALSE) -> #N/A | ... CW34: =VLOOKUP($BA34,HAVERD!$A:$BS,CW$2,FALSE) -> #N/A
... A37: =A20 -> 45495 | B37: =VLOOKUP($A37,HAVERD!$A:$BS,B$2,FALSE) -> 5.2 | C37: =VLOOKUP($A37,HAVERD!$A:$BS,C$2,FALSE) -> 5.0981736 | D37: =VLOOKUP($A37,HAVERD!$A:$BS,D$2,FALSE) -> 5.0525574 | E37: =VLOOKUP($A37,HAVERD!$A:$BS,E$2,FALSE) -> 4.9866557 | F37: =VLOOKUP($A37,HAVERD!$A:$BS,F$2,FALSE) -> 4.9069106 | G37: =VLOOKUP($A37,HAVERD!$A:$BS,G$2,FALSE) -> 4.8212351 | H37: =VLOOKUP($A37,HAVERD!$A:$BS,H$2,FALSE) -> 4.7344874 | I37: =VLOOKUP($A37,HAVERD!$A:$BS,I$2,FALSE) -> 4.6498897 | ... AX37: =VLOOKUP($A37,HAVERD!$A:$BS,AX$2,FALSE) -> 3.4707482 | BA37: =BA20 -> 45593 | BB37: =VLOOKUP($BA37,HAVERD!$A:$BS,BB$2,FALSE) -> #N/A | BC37: =VLOOKUP($BA37,HAVERD!$A:$BS,BC$2,FALSE) -> #N/A | BD37: =VLOOKUP($BA37,HAVERD!$A:$BS,BD$2,FALSE) -> #N/A | BE37: =VLOOKUP($BA37,HAVERD!$A:$BS,BE$2,FALSE) -> #N/A | BF37: =VLOOKUP($BA37,HAVERD!$A:$BS,BF$2,FALSE) -> #N/A | BG37: =VLOOKUP($BA37,HAVERD!$A:$BS,BG$2,FALSE) -> #N/A | BH37: =VLOOKUP($BA37,HAVERD!$A:$BS,BH$2,FALSE) -> #N/A | BI37: =VLOOKUP($BA37,HAVERD!$A:$BS,BI$2,FALSE) -> #N/A | ... CW37: =VLOOKUP($BA37,HAVERD!$A:$BS,CW$2,FALSE) -> #N/A
A39: Average | BA39: Average
A40: Month | B40: =MONTH(B20) -> 7 | C40: =MONTH(C20) -> 8 | D40: =MONTH(D20) -> 9 | E40: =MONTH(E20) -> 10 | F40: =MONTH(F20) -> 11 | G40: =MONTH(G20) -> 12 | H40: =MONTH(H20) -> 1 | I40: =MONTH(I20) -> 2 | ... AX40: =MONTH(AX20) -> 7 | BA40: Month | BB40: =MONTH(BB20) -> 10 | BC40: =MONTH(BC20) -> 11 | BD40: =MONTH(BD20) -> 12 | BE40: =MONTH(BE20) -> 1 | BF40: =MONTH(BF20) -> 2 | BG40: =MONTH(BG20) -> 3 | BH40: =MONTH(BH20) -> 4 | BI40: =MONTH(BI20) -> 5 | ... CW40: =MONTH(CW20) -> 9
A41: Year | B41: =YEAR(B20) -> 2024 | C41: =YEAR(C20) -> 2024 | D41: =YEAR(D20) -> 2024 | E41: =YEAR(E20) -> 2024 | F41: =YEAR(F20) -> 2024 | G41: =YEAR(G20) -> 2024 | H41: =YEAR(H20) -> 2025 | I41: =YEAR(I20) -> 2025 | ... AX41: =YEAR(AX20) -> 2028 | BA41: Year | BB41: =YEAR(BB20) -> 2024 | BC41: =YEAR(BC20) -> 2024 | BD41: =YEAR(BD20) -> 2024 | BE41: =YEAR(BE20) -> 2025 | BF41: =YEAR(BF20) -> 2025 | BG41: =YEAR(BG20) -> 2025 | BH41: =YEAR(BH20) -> 2025 | BI41: =YEAR(BI20) -> 2025 | ... CW41: =YEAR(CW20) -> 2028
A42: YYYYMM | B42: =B41*100+B40 -> 202407 | C42: =C41*100+C40 -> 202408 | D42: =D41*100+D40 -> 202409 | E42: =E41*100+E40 -> 202410 | F42: =F41*100+F40 -> 202411 | G42: =G41*100+G40 -> 202412 | H42: =H41*100+H40 -> 202501 | I42: =I41*100+I40 -> 202502 | ... AX42: =AX41*100+AX40 -> 202807 | BA42: YYYYMM | BB42: =BB41*100+BB40 -> 202410 | BC42: =BC41*100+BC40 -> 202411 | BD42: =BD41*100+BD40 -> 202412 | BE42: =BE41*100+BE40 -> 202501 | BF42: =BF41*100+BF40 -> 202502 | BG42: =BG41*100+BG40 -> 202503 | BH42: =BH41*100+BH40 -> 202504 | BI42: =BI41*100+BI40 -> 202505 | ... CW42: =CW41*100+CW40 -> 202809
A43: Quarter | B43: =IF(B40<4,1,IF(B40<7,2,IF(B40<10,3,4))) -> 3 | C43: =IF(C40<4,1,IF(C40<7,2,IF(C40<10,3,4))) -> 3 | D43: =IF(D40<4,1,IF(D40<7,2,IF(D40<10,3,4))) -> 3 | E43: =IF(E40<4,1,IF(E40<7,2,IF(E40<10,3,4))) -> 4 | F43: =IF(F40<4,1,IF(F40<7,2,IF(F40<10,3,4))) -> 4 | G43: =IF(G40<4,1,IF(G40<7,2,IF(G40<10,3,4))) -> 4 | H43: =IF(H40<4,1,IF(H40<7,2,IF(H40<10,3,4))) -> 1 | I43: =IF(I40<4,1,IF(I40<7,2,IF(I40<10,3,4))) -> 1 | ... AX43: =IF(AX40<4,1,IF(AX40<7,2,IF(AX40<10,3,4))) -> 3 | BA43: Quarter | BB43: =IF(BB40<4,1,IF(BB40<7,2,IF(BB40<10,3,4))) -> 4 | BC43: =IF(BC40<4,1,IF(BC40<7,2,IF(BC40<10,3,4))) -> 4 | BD43: =IF(BD40<4,1,IF(BD40<7,2,IF(BD40<10,3,4))) -> 4 | BE43: =IF(BE40<4,1,IF(BE40<7,2,IF(BE40<10,3,4))) -> 1 | BF43: =IF(BF40<4,1,IF(BF40<7,2,IF(BF40<10,3,4))) -> 1 | BG43: =IF(BG40<4,1,IF(BG40<7,2,IF(BG40<10,3,4))) -> 1 | BH43: =IF(BH40<4,1,IF(BH40<7,2,IF(BH40<10,3,4))) -> 2 | BI43: =IF(BI40<4,1,IF(BI40<7,2,IF(BI40<10,3,4))) -> 2 | ... CW43: =IF(CW40<4,1,IF(CW40<7,2,IF(CW40<10,3,4))) -> 3
A44: YYYYQQ | B44: =B41*100+B43 -> 202403 | C44: =C41*100+C43 -> 202403 | D44: =D41*100+D43 -> 202403 | E44: =E41*100+E43 -> 202404 | F44: =F41*100+F43 -> 202404 | G44: =G41*100+G43 -> 202404 | H44: =H41*100+H43 -> 202501 | I44: =I41*100+I43 -> 202501 | ... AX44: =AX41*100+AX43 -> 202803 | BA44: YYYYQQ | BB44: =BB41*100+BB43 -> 202404 | BC44: =BC41*100+BC43 -> 202404 | BD44: =BD41*100+BD43 -> 202404 | BE44: =BE41*100+BE43 -> 202501 | BF44: =BF41*100+BF43 -> 202501 | BG44: =BG41*100+BG43 -> 202501 | BH44: =BH41*100+BH43 -> 202502 | BI44: =BI41*100+BI43 -> 202502 | ... CW44: =CW41*100+CW43 -> 202803
A45: Average | B45: =AVERAGE(B23:B37) -> 5.2 | C45: =AVERAGE(C23:C37) -> 5.1041256 | D45: =AVERAGE(D23:D37) -> 5.0355198 | E45: =AVERAGE(E23:E37) -> 4.966103 | F45: =AVERAGE(F23:F37) -> 4.8887192 | G45: =AVERAGE(G23:G37) -> 4.8042128 | H45: =AVERAGE(H23:H37) -> 4.7174629 | I45: =AVERAGE(I23:I37) -> 4.6322333 | ... AX45: =AVERAGE(AX23:AX37) -> 3.4276605 | BA45: Average | BB45: =AVERAGE(BB23:BB37) -> #N/A | BC45: =AVERAGE(BC23:BC37) -> #N/A | BD45: =AVERAGE(BD23:BD37) -> #N/A | BE45: =AVERAGE(BE23:BE37) -> #N/A | BF45: =AVERAGE(BF23:BF37) -> #N/A | BG45: =AVERAGE(BG23:BG37) -> #N/A | BH45: =AVERAGE(BH23:BH37) -> #N/A | BI45: =AVERAGE(BI23:BI37) -> #N/A | ... CW45: =AVERAGE(CW23:CW37) -> #N/A
A47: Quarterly series | BA47: Quarterly series
B48: =B44 -> 202403 | C48: =IF(RIGHT(B48)="4",B48+97,B48+1) -> 202404 | D48: =IF(RIGHT(C48)="4",C48+97,C48+1) -> 202501 | E48: =IF(RIGHT(D48)="4",D48+97,D48+1) -> 202502 | F48: =IF(RIGHT(E48)="4",E48+97,E48+1) -> 202503 | G48: =IF(RIGHT(F48)="4",F48+97,F48+1) -> 202504 | H48: =IF(RIGHT(G48)="4",G48+97,G48+1) -> 202601 | I48: =IF(RIGHT(H48)="4",H48+97,H48+1) -> 202602 | J48: =IF(RIGHT(I48)="4",I48+97,I48+1) -> 202603 | ... R48: =IF(RIGHT(Q48)="4",Q48+97,Q48+1) -> 202803 | BB48: =BB44 -> 202404 | BC48: =IF(RIGHT(BB48)="4",BB48+97,BB48+1) -> 202501 | BD48: =IF(RIGHT(BC48)="4",BC48+97,BC48+1) -> 202502 | BE48: =IF(RIGHT(BD48)="4",BD48+97,BD48+1) -> 202503 | BF48: =IF(RIGHT(BE48)="4",BE48+97,BE48+1) -> 202504 | BG48: =IF(RIGHT(BF48)="4",BF48+97,BF48+1) -> 202601 | BH48: =IF(RIGHT(BG48)="4",BG48+97,BG48+1) -> 202602 | BI48: =IF(RIGHT(BH48)="4",BH48+97,BH48+1) -> 202603 | BJ48: =IF(RIGHT(BI48)="4",BI48+97,BI48+1) -> 202604 | ... BQ48: =IF(RIGHT(BP48)="4",BP48+97,BP48+1) -> 202803
A49: =A1 -> August MPR | B49: =AVERAGEIF($B$44:$AX$44,B48,$B$45:$AX$45) -> 5.1132151 | C49: =AVERAGEIF($B$44:$AX$44,C48,$B$45:$AX$45) -> 4.886345 | D49: =AVERAGEIF($B$44:$AX$44,D48,$B$45:$AX$45) -> 4.6336645 | E49: =AVERAGEIF($B$44:$AX$44,E48,$B$45:$AX$45) -> 4.4108281 | F49: =AVERAGEIF($B$44:$AX$44,F48,$B$45:$AX$45) -> 4.2411694 | G49: =AVERAGEIF($B$44:$AX$44,G48,$B$45:$AX$45) -> 4.1022737 | H49: =AVERAGEIF($B$44:$AX$44,H48,$B$45:$AX$45) -> 3.9779006 | I49: =AVERAGEIF($B$44:$AX$44,I48,$B$45:$AX$45) -> 3.8620146 | ... R49: =AVERAGEIF($B$44:$AX$44,R48,$B$45:$AX$45) -> 3.4276605 | BA49: =BA1 -> November MPR | BB49: =AVERAGEIF($BB$44:$CW$44,BB48,$BB$45:$CW$45) -> #N/A | BC49: =AVERAGEIF($BB$44:$CW$44,BC48,$BB$45:$CW$45) -> #N/A | BD49: =AVERAGEIF($BB$44:$CW$44,BD48,$BB$45:$CW$45) -> #N/A | BE49: =AVERAGEIF($BB$44:$CW$44,BE48,$BB$45:$CW$45) -> #N/A | BF49: =AVERAGEIF($BB$44:$CW$44,BF48,$BB$45:$CW$45) -> #N/A | BG49: =AVERAGEIF($BB$44:$CW$44,BG48,$BB$45:$CW$45) -> #N/A | BH49: =AVERAGEIF($BB$44:$CW$44,BH48,$BB$45:$CW$45) -> #N/A | BI49: =AVERAGEIF($BB$44:$CW$44,BI48,$BB$45:$CW$45) -> #N/A | ... BQ49: =AVERAGEIF($BB$44:$CW$44,BQ48,$BB$45:$CW$45) -> #N/A
BA51: Comparison - monthly
BB52: 44927 | BC52: 44958 | BD52: 44986 | BE52: 45017 | BF52: 45047 | BG52: 45078 | BH52: 45108 | BI52: 45139 | BJ52: 45170 | BK52: 45200 | BL52: 45231 | BM52: 45261 | BN52: 45292 | BO52: 45323 | BP52: 45352 | BQ52: 45383 | BR52: 45413 | BS52: 45444 | BT52: 45474 | BU52: 45505 | BV52: 45536 | BW52: 45566 | BX52: 45597 | BY52: 45627 | BZ52: 45658 | CA52: 45689 | CB52: 45717 | CC52: 45748 | CD52: 45778 | CE52: 45809 | CF52: 45839 | CG52: 45870 | CH52: 45901 | CI52: 45931 | CJ52: 45962 | CK52: 45992 | CL52: 46023 | CM52: 46054 | CN52: 46082 | CO52: 46113 | CP52: 46143 | CQ52: 46174 | CR52: 46204 | CS52: 46235 | CT52: 46266 | CU52: 46296 | CV52: 46327 | CW52: 46357 | CX52: 46388 | CY52: 46419 | CZ52: 46447 | DA52: 46478 | DB52: 46508 | DC52: 46539 | DD52: 46569 | DE52: 46600 | DF52: 46631 | DG52: 46661 | DH52: 46692 | DI52: 46722
BB53: =MONTH(BB52) -> 1 | BC53: =MONTH(BC52) -> 2 | BD53: =MONTH(BD52) -> 3 | BE53: =MONTH(BE52) -> 4 | BF53: =MONTH(BF52) -> 5 | BG53: =MONTH(BG52) -> 6 | BH53: =MONTH(BH52) -> 7 | BI53: =MONTH(BI52) -> 8 | ... DI53: =MONTH(DI52) -> 12
BB54: 202301 | BC54: =IF(BC53=1,BB54+89,BB54+1) -> 202302 | BD54: =IF(BD53=1,BC54+89,BC54+1) -> 202303 | BE54: =IF(BE53=1,BD54+89,BD54+1) -> 202304 | BF54: =IF(BF53=1,BE54+89,BE54+1) -> 202305 | BG54: =IF(BG53=1,BF54+89,BF54+1) -> 202306 | BH54: =IF(BH53=1,BG54+89,BG54+1) -> 202307 | BI54: =IF(BI53=1,BH54+89,BH54+1) -> 202308 | BJ54: =IF(BJ53=1,BI54+89,BI54+1) -> 202309 | ... DI54: =IF(DI53=1,DH54+89,DH54+1) -> 202712
BA55: Bank Rate | BB55: =AVERAGEIF(HAVERD!$D:$D,'Market expectations'!BB54,HAVERD!$H:$H) -> 3.5 | BC55: =AVERAGEIF(HAVERD!$D:$D,'Market expectations'!BC54,HAVERD!$H:$H) -> 3.975 | BD55: =AVERAGEIF(HAVERD!$D:$D,'Market expectations'!BD54,HAVERD!$H:$H) -> 4.076087 | BE55: =AVERAGEIF(HAVERD!$D:$D,'Market expectations'!BE54,HAVERD!$H:$H) -> 4.25 | BF55: =AVERAGEIF(HAVERD!$D:$D,'Market expectations'!BF54,HAVERD!$H:$H) -> 4.4130435 | BG55: =AVERAGEIF(HAVERD!$D:$D,'Market expectations'!BG54,HAVERD!$H:$H) -> 4.6590909 | BH55: =AVERAGEIF(HAVERD!$D:$D,'Market expectations'!BH54,HAVERD!$H:$H) -> 5 | BI55: =AVERAGEIF(HAVERD!$D:$D,'Market expectations'!BI54,HAVERD!$H:$H) -> 5.2282609 | ... BQ55: =AVERAGEIF(HAVERD!$D:$D,'Market expectations'!BQ54,HAVERD!$H:$H) -> 5.25
BA56: =A49 -> August MPR | BB56: =HLOOKUP(BB$54,$B$42:$AX$45,4,FALSE) -> #N/A | BC56: =HLOOKUP(BC$54,$B$42:$AX$45,4,FALSE) -> #N/A | BD56: =HLOOKUP(BD$54,$B$42:$AX$45,4,FALSE) -> #N/A | BE56: =HLOOKUP(BE$54,$B$42:$AX$45,4,FALSE) -> #N/A | BF56: =HLOOKUP(BF$54,$B$42:$AX$45,4,FALSE) -> #N/A | BG56: =HLOOKUP(BG$54,$B$42:$AX$45,4,FALSE) -> #N/A | BH56: =HLOOKUP(BH$54,$B$42:$AX$45,4,FALSE) -> #N/A | BI56: =HLOOKUP(BI$54,$B$42:$AX$45,4,FALSE) -> #N/A | ... DI56: =HLOOKUP(DI$54,$B$42:$AX$45,4,FALSE) -> 3.4611795
BA57: =BA49 -> November MPR | BB57: =HLOOKUP(BB$54,$BB$42:$CW$45,4,FALSE) -> #N/A | BC57: =HLOOKUP(BC$54,$BB$42:$CW$45,4,FALSE) -> #N/A | BD57: =HLOOKUP(BD$54,$BB$42:$CW$45,4,FALSE) -> #N/A | BE57: =HLOOKUP(BE$54,$BB$42:$CW$45,4,FALSE) -> #N/A | BF57: =HLOOKUP(BF$54,$BB$42:$CW$45,4,FALSE) -> #N/A | BG57: =HLOOKUP(BG$54,$BB$42:$CW$45,4,FALSE) -> #N/A | BH57: =HLOOKUP(BH$54,$BB$42:$CW$45,4,FALSE) -> #N/A | BI57: =HLOOKUP(BI$54,$BB$42:$CW$45,4,FALSE) -> #N/A | ... DI57: =HLOOKUP(DI$54,$BB$42:$CW$45,4,FALSE) -> #N/A
BA58: Difference | BQ58: =BQ57-BQ56 -> #N/A | BR58: =BR57-BR56 -> #N/A | BS58: =BS57-BS56 -> #N/A | BT58: =BT57-BT56 -> #N/A | BU58: =BU57-BU56 -> #N/A | BV58: =BV57-BV56 -> #N/A | BW58: =BW57-BW56 -> #N/A | BX58: =BX57-BX56 -> #N/A | ... DI58: =DI57-DI56 -> #N/A
BA59: Next 3 years | CZ59: =AVERAGE(BQ58:CZ58) -> #N/A
BA61: Comparison - quarterly
BB62: 44927 | BC62: 45017 | BD62: 45108 | BE62: 45200 | BF62: 45292 | BG62: 45383 | BH62: 45474 | BI62: 45566 | BJ62: 45658 | BK62: 45748 | BL62: 45839 | BM62: 45931 | BN62: 46023 | BO62: 46113 | BP62: 46204 | BQ62: 46296 | BR62: 46388 | BS62: 46478 | BT62: 46569 | BU62: 46661
BB63: 202301 | BC63: =IF(RIGHT(BB63)="4",BB63+97,BB63+1) -> 202302 | BD63: =IF(RIGHT(BC63)="4",BC63+97,BC63+1) -> 202303 | BE63: =IF(RIGHT(BD63)="4",BD63+97,BD63+1) -> 202304 | BF63: =IF(RIGHT(BE63)="4",BE63+97,BE63+1) -> 202401 | BG63: =IF(RIGHT(BF63)="4",BF63+97,BF63+1) -> 202402 | BH63: =IF(RIGHT(BG63)="4",BG63+97,BG63+1) -> 202403 | BI63: =IF(RIGHT(BH63)="4",BH63+97,BH63+1) -> 202404 | BJ63: =IF(RIGHT(BI63)="4",BI63+97,BI63+1) -> 202501 | ... BU63: =IF(RIGHT(BT63)="4",BT63+97,BT63+1) -> 202704
BA64: Bank Rate | BB64: =AVERAGEIF(HAVERD!$F:$F,'Market expectations'!BB63,HAVERD!$H:$H) -> 3.85 | BC64: =AVERAGEIF(HAVERD!$F:$F,'Market expectations'!BC63,HAVERD!$H:$H) -> 4.4461538 | BD64: =AVERAGEIF(HAVERD!$F:$F,'Market expectations'!BD63,HAVERD!$H:$H) -> 5.1615385 | BE64: =AVERAGEIF(HAVERD!$F:$F,'Market expectations'!BE63,HAVERD!$H:$H) -> 5.25 | BF64: =AVERAGEIF(HAVERD!$F:$F,'Market expectations'!BF63,HAVERD!$H:$H) -> 5.25 | BG64: =AVERAGEIF(HAVERD!$F:$F,'Market expectations'!BG63,HAVERD!$H:$H) -> 5.25
BA65: =A49 -> August MPR | BB65: =HLOOKUP(BB$63,$B$48:$R$49,2,FALSE) -> #N/A | BC65: =HLOOKUP(BC$63,$B$48:$R$49,2,FALSE) -> #N/A | BD65: =HLOOKUP(BD$63,$B$48:$R$49,2,FALSE) -> #N/A | BE65: =HLOOKUP(BE$63,$B$48:$R$49,2,FALSE) -> #N/A | BF65: =BF64 -> 5.25 | BG65: =HLOOKUP(BG$63,$B$48:$R$49,2,FALSE) -> #N/A | BH65: =HLOOKUP(BH$63,$B$48:$R$49,2,FALSE) -> 5.1132151 | BI65: =HLOOKUP(BI$63,$B$48:$R$49,2,FALSE) -> 4.886345 | BJ65: =HLOOKUP(BJ$63,$B$48:$R$49,2,FALSE) -> 4.6336645 | BK65: =HLOOKUP(BK$63,$B$48:$R$49,2,FALSE) -> 4.4108281 | BL65: =HLOOKUP(BL$63,$B$48:$R$49,2,FALSE) -> 4.2411694 | BM65: =HLOOKUP(BM$63,$B$48:$R$49,2,FALSE) -> 4.1022737 | BN65: =HLOOKUP(BN$63,$B$48:$R$49,2,FALSE) -> 3.9779006 | ... BU65: =HLOOKUP(BU$63,$B$48:$R$49,2,FALSE) -> 3.4700284
BA66: =BA49 -> November MPR | BB66: =HLOOKUP(BB$63,$BB$48:$BR$49,2,FALSE) -> #N/A | BC66: =HLOOKUP(BC$63,$BB$48:$BR$49,2,FALSE) -> #N/A | BD66: =HLOOKUP(BD$63,$BB$48:$BR$49,2,FALSE) -> #N/A | BE66: =HLOOKUP(BE$63,$BB$48:$BR$49,2,FALSE) -> #N/A | BF66: =HLOOKUP(BF$63,$BB$48:$BR$49,2,FALSE) -> #N/A | BG66: =BG64 -> 5.25 | BH66: =HLOOKUP(BH$63,$BB$48:$BR$49,2,FALSE) -> #N/A | BI66: =HLOOKUP(BI$63,$BB$48:$BR$49,2,FALSE) -> #N/A | BJ66: =HLOOKUP(BJ$63,$BB$48:$BR$49,2,FALSE) -> #N/A | BK66: =HLOOKUP(BK$63,$BB$48:$BR$49,2,FALSE) -> #N/A | BL66: =HLOOKUP(BL$63,$BB$48:$BR$49,2,FALSE) -> #N/A | BM66: =HLOOKUP(BM$63,$BB$48:$BR$49,2,FALSE) -> #N/A | BN66: =HLOOKUP(BN$63,$BB$48:$BR$49,2,FALSE) -> #N/A | BO66: =HLOOKUP(BO$63,$BB$48:$BR$49,2,FALSE) -> #N/A | ... BU66: =HLOOKUP(BU$63,$BB$48:$BR$49,2,FALSE) -> #N/A
BA67: Difference | BH67: =BH66-BH65 -> #N/A | BI67: =BI66-BI65 -> #N/A | BJ67: =BJ66-BJ65 -> #N/A | BK67: =BK66-BK65 -> #N/A | BL67: =BL66-BL65 -> #N/A | BM67: =BM66-BM65 -> #N/A | BN67: =BN66-BN65 -> #N/A | BO67: =BO66-BO65 -> #N/A | ... BU67: =BU66-BU65 -> #N/A
BA68: Next 3 years | BS68: =AVERAGE(BH67:BS67) -> #N/A

Sheet MPR Chart 2.16
A1: Section 2: Current economic conditions
A3: Chart 2.16 - Contributions to CPI inflation
B5: Contributions | H5: Inflation rates
A6: Date | B6: Food | C6: Electricity and gas | D6: Fuels and lubricants | E6: Other goods | F6: Services | H6: Food | I6: Electricity and gas | J6: Fuels and lubricants | K6: Other goods | L6: Services | M6: Total CPI
A7: 44227 | B7: -0.1 | C7: -0.3 | D7: -0.3 | E7: 0.4 | F7: 0.8 | H7: -0.7 | I7: -8.4 | J7: -8.2 | K7: 1.4 | L7: 1.7 | M7: 0.7
A8: 44255 | B8: 0 | C8: -0.3 | D8: -0.1 | E8: 0.1 | F8: 0.7 | H8: -0.6 | I8: -7.9 | J8: -3.5 | K8: 0.5 | L8: 1.5 | M8: 0.4
A9: 44286 | B9: -0.1 | C9: -0.2 | D9: 0.1 | E9: 0.3 | F9: 0.7 | H9: -1.4 | I9: -7.3 | J9: 3.5 | K9: 0.9 | L9: 1.5 | M9: 0.7
A10: 44316 | B10: 0 | C10: 0.1 | D10: 0.4 | E10: 0.4 | F10: 0.7 | H10: -0.4 | I10: 2.4 | J10: 13.6 | K10: 1.2 | L10: 1.6 | M10: 1.5
A11: 44347 | B11: -0.1 | C11: 0.1 | D11: 0.5 | E11: 0.8 | F11: 0.9 | H11: -1.3 | I11: 2.6 | J11: 17.9 | K11: 2.2 | L11: 1.9 | M11: 2.1
A12: 44377 | B12: 0 | C12: 0.1 | D12: 0.5 | E12: 1 | F12: 0.9 | H12: -0.6 | I12: 2.5 | J12: 20.3 | K12: 2.7 | L12: 2.1 | M12: 2.5
A13: 44408 | B13: -0.1 | C13: 0.1 | D13: 0.5 | E13: 0.8 | F13: 0.7 | H13: -0.6 | I13: 2.6 | J13: 17.7 | K13: 2.3 | L13: 1.6 | M13: 2
A14: 44439 | B14: 0.1 | C14: 0.1 | D14: 0.5 | E14: 1.2 | F14: 1.4 | H14: 0.3 | I14: 2.6 | J14: 17.7 | K14: 3.2 | L14: 3 | M14: 3.2
A15: 44469 | B15: 0.1 | C15: 0.1 | D15: 0.5 | E15: 1.3 | F15: 1.1 | H15: 0.8 | I15: 2.8 | J15: 17.8 | K15: 3.3 | L15: 2.6 | M15: 3.1
A16: 44500 | B16: 0.2 | C16: 0.8 | D16: 0.6 | E16: 1.3 | F16: 1.4 | H16: 1.2 | I16: 22.9 | J16: 21.5 | K16: 3.4 | L16: 3.2 | M16: 4.2
A17: 44530 | B17: 0.3 | C17: 0.8 | D17: 0.7 | E17: 1.9 | F17: 1.5 | H17: 2.5 | I17: 23.2 | J17: 28.5 | K17: 4.8 | L17: 3.3 | M17: 5.1
A18: 44561 | B18: 0.5 | C18: 0.7 | D18: 0.7 | E18: 2 | F18: 1.5 | H18: 4.2 | I18: 22.7 | J18: 26.8 | K18: 5 | L18: 3.4 | M18: 5.4
... A48: 45444 | B48: 0.2 | C48: -1.3 | D48: 0.1 | E48: 0.3 | F48: 2.7 | H48: 1.5 | I48: -27.2 | J48: 2.6 | K48: 0.8 | L48: 5.7 | M48: 2
A49: July 2024 (Bank staff projections) | B49: 0.159 | C49: -0.828 | D49: 0.054 | E49: 0.281 | F49: 2.7 | H49: 1.31 | I49: -20.122 | J49: 1.894 | K49: 0.831 | L49: 5.563 | M49: 2.366
A50: August 2024 (Bank staff projections) | B50: 0.156 | C50: -0.838 | D50: -0.024 | E50: 0.245 | F50: 2.827 | H50: 1.313 | I50: -20.372 | J50: -1.018 | K50: 0.735 | L50: 5.84 | M50: 2.367
A51: September 2024 (Bank staff projections) | B51: 0.142 | C51: -0.84 | D51: -0.086 | E51: 0.21 | F51: 2.67 | H51: 1.191 | I51: -20.502 | J51: -3.285 | K51: 0.647 | L51: 5.52 | M51: 2.097
A52: October 2024 (Bank staff projections) | B52: 0.112 | C52: -0.329 | D52: -0.109 | E52: 0.249 | F52: 2.675 | H52: 0.928 | I52: -8.466 | J52: -4.125 | K52: 0.768 | L52: 5.502 | M52: 2.6
A53: November 2024 (Bank staff projections) | B53: 0.091 | C53: -0.324 | D53: -0.025 | E53: 0.396 | F53: 2.625 | H53: 0.764 | I53: -8.329 | J53: -1.368 | K53: 1.207 | L53: 5.395 | M53: 2.763
A54: December 2024 (Bank staff projections) | B54: 0.081 | C54: -0.32 | D54: 0.132 | E54: 0.31 | F54: 2.596 | H54: 0.719 | I54: -8.249 | J54: 4.225 | K54: 0.953 | L54: 5.286 | M54: 2.8
A56: 2025 Q1 (Bank staff projection) | B56: n.a. | C56: n.a. | D56: n.a. | E56: n.a. | F56: n.a. | H56: n.a. | I56: n.a. | J56: n.a. | K56: n.a. | L56: n.a. | M56: 2.67

Sheet MPR Chart 2.21
A1: Section 2: Current economic conditions
A3: Chart 2.21 - Measures of annual pay growth
B5: Quarterly frequency | F5: Monthly frequency
A6: Date | B6: AWE private sector regular pay | C6: Indicator-based model | E6: Date | F6: AWE private sector regular pay | G6: KPMG/REC survey (advanced 12 months) | H6: HMRC RTI private sector median | I6: Indeed Wage Tracker
A7: 2018 Q1 | B7: 3 | C7: 2.9 | E7: 43131 | F7: 2.7 | G7: No permissions | H7: 3.1 | I7: n.a.
A8: 2018 Q2 | B8: 2.8 | C8: 3 | E8: 43159 | F8: 2.9 | H8: 3.2 | I8: n.a.
A9: 2018 Q3 | B9: 3.3 | C9: 3.2 | E9: 43190 | F9: 3 | H9: 3.2 | I9: n.a.
A10: 2018 Q4 | B10: 3.5 | C10: 3.4 | E10: 43220 | F10: 3 | H10: 3 | I10: n.a.
A11: 2019 Q1 | B11: 3.6 | C11: 3.4 | E11: 43251 | F11: 2.9 | H11: 3.2 | I11: n.a.
A12: 2019 Q2 | B12: 3.9 | C12: 3.5 | E12: 43281 | F12: 2.8 | H12: 3.4 | I12: n.a.
A13: 2019 Q3 | B13: 3.7 | C13: 3.4 | E13: 43312 | F13: 3 | H13: 3.7 | I13: n.a.
A14: 2019 Q4 | B14: 3.2 | C14: 3.2 | E14: 43343 | F14: 3.2 | H14: 3.9 | I14: n.a.
A15: 2020 Q1 | B15: 2.5 | C15: 3 | E15: 43373 | F15: 3.3 | H15: 3.8 | I15: n.a.
A16: 2020 Q2 | B16: -1.2 | C16: 2.2 | E16: 43404 | F16: 3.4 | H16: 3.8 | I16: n.a.
A17: 2020 Q3 | B17: 1.4 | C17: 1.4 | E17: 43434 | F17: 3.4 | H17: 3.7 | I17: n.a.
A18: 2020 Q4 | B18: 4 | C18: 1.3 | E18: 43465 | F18: 3.5 | H18: 3.7 | I18: n.a.
A19: 2021 Q1 | B19: 4.3 | C19: 1.1 | E19: 43496 | F19: 3.6 | H19: 3.7 | I19: n.a.
... A31: 2024 Q1 | B31: 5.9 | C31: 5.6 | E31: 43861 | F31: 3 | H31: 3.3 | I31: n.a.
A32: 2024 Q2 (Bank Staff Projection) | B32: 5.141 | C32: n.a. | E32: 43890 | F32: 2.9 | H32: 3.7 | I32: n.a.
A33: 2024 Q3 (Bank Staff Projection) | B33: 4.83 | C33: n.a. | E33: 43921 | F33: 2.5 | H33: 3.2 | I33: n.a.
E34: 43951 | F34: 1.3 | H34: 1.2 | I34: 5.5
E35: 43982 | F35: -0.1 | H35: -1 | I35: 4.6
E36: 44012 | F36: -1.2 | H36: -1.8 | I36: 3.8
E37: 44043 | F37: -0.8 | H37: -0.6 | I37: 3.5
E38: 44074 | F38: 0.1 | H38: 1.2 | I38: 3.2
E39: 44104 | F39: 1.4 | H39: 2.7 | I39: 3.2
E40: 44135 | F40: 2.5 | H40: 3.7 | I40: 3.2
E41: 44165 | F41: 3.3 | H41: 4.3 | I41: 3.2
E42: 44196 | F42: 4 | H42: 4.5 | I42: 3.4
E43: 44227 | F43: 4.1 | H43: 4.3 | I43: 3.6
E44: 44255 | F44: 4.2 | H44: 4 | I44: 3.3
E45: 44286 | F45: 4.3 | H45: 4.5 | I45: 2.8
... E83: 45443 | F83: 5.6 | H83: 6.3 | I83: 6.9
E84: 45473 | F84: n.a. | H84: 6.2 | I84: 6.8

Sheet HAVERM
A1: 201001 !M | B1: D7BT@UK | C1: D7F5@UK | D1: KAJ4@UK | E1: UNVDPR1@UK | F1: UNVDPE1@UK | G1: UNVDWR@UK | H1: UNVDWE@UK | I1: UNVDPR3@UK | J1: UNVDPE3@UK | K1: UNVDWR3@UK | L1: UNVDWE3@UK
A2: .DESC | B2: UK: Consumer Price Index: All Items (NSA, 2015=100) | C2: UK: Consumer Price Index: All Services (NSA, 2015=100) | D2: Great Britain: AWE, Regular Pay: Private Sector [3Mo Mvg Avg vs Yr Ago] (SA, %) | E2: UK: BoE DMP: Realized Price Growth Over the Past Year: Single Month (%) | F2: UK: BoE DMP: Expected Price Growth Over the Next Year: Single Month (%) | G2: UK: BoE DMP: Realized Wage Growth Over the Past Year: Single Month (%) | H2: UK: BoE DMP: Expected Wage Growth Over the Next Year: Single Month (%) | I2: UK: BoE DMP: Realized Price Growth Over the Past Year: 3 Month Average (%) | J2: UK: BoE DMP: Expected Price Growth Over the Next Year: 3 Month Average (%) | K2: UK: BoE DMP: Realized Wage Growth Over the Past Year: 3 Month Average (%) | L2: UK: BoE DMP: Expected Wage Growth Over the Past Year: 3 Month Average (%)
A3: .T1 | B3: Jan-1988 | C3: Jan-1988 | D3: Mar-2001 | E3: Jan-2017 | F3: Jan-2017 | G3: Aug-2017 | H3: Aug-2017 | I3: Jan-2017 | J3: Jan-2017 | K3: Aug-2017 | L3: Aug-2017
A4: .TN | B4: Jul-2024 | C4: Jul-2024 | D4: Jun-2024 | E4: Aug-2024 | F4: Aug-2024 | G4: Aug-2024 | H4: Aug-2024 | I4: Aug-2024 | J4: Aug-2024 | K4: Aug-2024 | L4: Aug-2024
A5: .LSOURCE | B5: Office for National Statistics | C5: Office for National Statistics | D5: Office for National Statistics | E5: Bank of England | F5: Bank of England | G5: Bank of England | H5: Bank of England | I5: Bank of England | J5: Bank of England | K5: Bank of England | L5: Bank of England
A6: .DTLM | B6: Aug-14-2024 07:02 | C6: Aug-14-2024 07:02 | D6: Aug-13-2024 07:03 | E6: Sep-05-2024 09:34 | F6: Sep-05-2024 09:34 | G6: Sep-05-2024 09:34 | H6: Sep-05-2024 09:34 | I6: Sep-05-2024 09:34 | J6: Sep-05-2024 09:34 | K6: Sep-05-2024 09:34 | L6: Sep-05-2024 09:34
A7: 201001 | B7: 87.8 | C7: 83.9 | D7: 0.5 | E7: #N/A | F7: #N/A | G7: #N/A | H7: #N/A | I7: #N/A | J7: #N/A | K7: #N/A | L7: #N/A
A8: 201002 | B8: 88.2 | C8: 84.1 | D8: 0.7 | E8: #N/A | F8: #N/A | G8: #N/A | H8: #N/A | I8: #N/A | J8: #N/A | K8: #N/A | L8: #N/A
A9: 201003 | B9: 88.7 | C9: 84.4 | D9: 1 | E9: #N/A | F9: #N/A | G9: #N/A | H9: #N/A | I9: #N/A | J9: #N/A | K9: #N/A | L9: #N/A
A10: 201004 | B10: 89.2 | C10: 84.9 | D10: 0.9 | E10: #N/A | F10: #N/A | G10: #N/A | H10: #N/A | I10: #N/A | J10: #N/A | K10: #N/A | L10: #N/A
A11: 201005 | B11: 89.4 | C11: 85.2 | D11: 0.8 | E11: #N/A | F11: #N/A | G11: #N/A | H11: #N/A | I11: #N/A | J11: #N/A | K11: #N/A | L11: #N/A
A12: 201006 | B12: 89.5 | C12: 85.7 | D12: 0.6 | E12: #N/A | F12: #N/A | G12: #N/A | H12: #N/A | I12: #N/A | J12: #N/A | K12: #N/A | L12: #N/A
A13: 201007 | B13: 89.3 | C13: 86.1 | D13: 1 | E13: #N/A | F13: #N/A | G13: #N/A | H13: #N/A | I13: #N/A | J13: #N/A | K13: #N/A | L13: #N/A
A14: 201008 | B14: 89.8 | C14: 86.7 | D14: 1.6 | E14: #N/A | F14: #N/A | G14: #N/A | H14: #N/A | I14: #N/A | J14: #N/A | K14: #N/A | L14: #N/A
A15: 201009 | B15: 89.8 | C15: 85.9 | D15: 2 | E15: #N/A | F15: #N/A | G15: #N/A | H15: #N/A | I15: #N/A | J15: #N/A | K15: #N/A | L15: #N/A
A16: 201010 | B16: 90 | C16: 86.3 | D16: 2 | E16: #N/A | F16: #N/A | G16: #N/A | H16: #N/A | I16: #N/A | J16: #N/A | K16: #N/A | L16: #N/A
A17: 201011 | B17: 90.3 | C17: 86.1 | D17: 2 | E17: #N/A | F17: #N/A | G17: #N/A | H17: #N/A | I17: #N/A | J17: #N/A | K17: #N/A | L17: #N/A
A18: 201012 | B18: 91.2 | C18: 87.2 | D18: 1.9 | E18: #N/A | F18: #N/A | G18: #N/A | H18: #N/A | I18: #N/A | J18: #N/A | K18: #N/A | L18: #N/A
... A90: 201612 | B90: 101.9 | C90: 104 | D90: 2.8 | E90: #N/A | F90: #N/A | G90: #N/A | H90: #N/A | I90: #N/A | J90: #N/A | K90: #N/A | L90: #N/A
A91: 201701 | B91: 101.4 | C91: 103.3 | D91: 2.6 | E91: 3.495 | F91: 3.346 | G91: #N/A | H91: #N/A | I91: 2.649 | J91: 2.963 | K91: #N/A | L91: #N/A
A92: 201702 | B92: 102.1 | C92: 103.9 | D92: 2.2 | E92: 2.069 | F92: 2.748 | G92: #N/A | H92: #N/A | I92: 2.649 | J92: 2.841 | K92: #N/A | L92: #N/A
A93: 201703 | B93: 102.5 | C93: 103.8 | D93: 2.1 | E93: 2.008 | F93: 2.282 | G93: #N/A | H93: #N/A | I93: 2.524 | J93: 2.792 | K93: #N/A | L93: #N/A
A94: 201704 | B94: 102.9 | C94: 105 | D94: 2 | E94: 4.144 | F94: 3.279 | G94: #N/A | H94: #N/A | I94: 2.74 | J94: 2.77 | K94: #N/A | L94: #N/A
A95: 201705 | B95: 103.3 | C95: 105.1 | D95: 2.2 | E95: 2.456 | F95: 2.447 | G95: #N/A | H95: #N/A | I95: 2.869 | J95: 2.669 | K95: #N/A | L95: #N/A
A96: 201706 | B96: 103.3 | C96: 105.5 | D96: 2.2 | E96: 2.66 | F96: 2.074 | G96: #N/A | H96: #N/A | I96: 3.087 | J96: 2.6 | K96: #N/A | L96: #N/A
A97: 201707 | B97: 103.2 | C97: 106 | D97: 2.3 | E97: 3.673 | F97: 2.828 | G97: #N/A | H97: #N/A | I97: 2.93 | J97: 2.45 | K97: #N/A | L97: #N/A
A98: 201708 | B98: 103.8 | C98: 106.5 | D98: 2.3 | E98: 3.074 | F98: 2.461 | G98: 2.6 | H98: 2.4 | I98: 3.135 | J98: 2.455 | K98: 2.635 | L98: 2.43
A99: 201709 | B99: 104.1 | C99: 106.1 | D99: 2.4 | E99: 2.525 | F99: 2.394 | G99: 2.5 | H99: 2.3 | I99: 3.09 | J99: 2.561 | K99: 2.548 | L99: 2.345
A100: 201710 | B100: 104.2 | C100: 105.9 | D100: 2.4 | E100: 2.853 | F100: 2.581 | G100: 2.7 | H100: 2.6 | I100: 2.817 | J100: 2.479 | K100: 2.613 | L100: 2.419
A101: 201711 | B101: 104.6 | C101: 105.9 | D101: 2.4 | E101: 2.867 | F101: 2.421 | G101: #N/A | H101: #N/A | I101: 2.748 | J101: 2.465 | K101: #N/A | L101: #N/A
A102: 201712 | B102: 104.9 | C102: 106.6 | D102: 2.6 | E102: 2.939 | F102: 2.442 | G102: #N/A | H102: #N/A | I102: 2.886 | J102: 2.481 | K102: #N/A | L102: #N/A
A103: 201801 | B103: 104.4 | C103: 106.1 | D103: 2.7 | E103: 3.01 | F103: 2.463 | G103: #N/A | H103: #N/A | I103: 2.939 | J103: 2.442 | K103: #N/A | L103: #N/A
A104: 201802 | B104: 104.9 | C104: 106.4 | D104: 2.9 | E104: 2.95 | F104: 2.408 | G104: #N/A | H104: #N/A | I104: 2.966 | J104: 2.438 | K104: #N/A | L104: #N/A
A105: 201803 | B105: 105 | C105: 106.5 | D105: 3 | E105: 2.56 | F105: 2.135 | G105: #N/A | H105: #N/A | I105: 2.838 | J105: 2.335 | K105: #N/A | L105: #N/A
A106: 201804 | B106: 105.4 | C106: 107.2 | D106: 3 | E106: 3.25 | F106: 2.444 | G106: #N/A | H106: #N/A | I106: 2.919 | J106: 2.329 | K106: #N/A | L106: #N/A
A107: 201805 | B107: 105.8 | C107: 107.6 | D107: 2.9 | E107: 2.47 | F107: 1.977 | G107: #N/A | H107: #N/A | I107: 2.76 | J107: 2.186 | K107: #N/A | L107: #N/A
A108: 201806 | B108: 105.8 | C108: 107.9 | D108: 2.8 | E108: 2.79 | F108: 2.317 | G108: #N/A | H108: #N/A | I108: 2.835 | J108: 2.246 | K108: #N/A | L108: #N/A
A109: 201807 | B109: 105.8 | C109: 108.5 | D109: 3 | E109: 2.79 | F109: 2.424 | G109: #N/A | H109: #N/A | I109: 2.68 | J109: 2.239 | K109: #N/A | L109: #N/A
A110: 201808 | B110: 106.5 | C110: 109.2 | D110: 3.2 | E110: 2.28 | F110: 2.254 | G110: #N/A | H110: #N/A | I110: 2.616 | J110: 2.332 | K110: #N/A | L110: #N/A
A111: 201809 | B111: 106.6 | C111: 108.6 | D111: 3.3 | E111: 2.41 | F111: 2.002 | G111: #N/A | H111: #N/A | I111: 2.491 | J111: 2.226 | K111: #N/A | L111: #N/A
A112: 201810 | B112: 106.7 | C112: 108.5 | D112: 3.4 | E112: 2.56 | F112: 2.591 | G112: #N/A | H112: #N/A | I112: 2.417 | J112: 2.282 | K112: #N/A | L112: #N/A
... A154: 202204 | B154: 120 | C154: 119.7 | D154: 4.8 | E154: 6.5 | F154: 5.998 | G154: #N/A | H154: #N/A | I154: 6.2 | J154: 5.587 | K154: #N/A | L154: #N/A
A155: 202205 | B155: 120.8 | C155: 120.2 | D155: 5.1 | E155: 7.28 | F155: 5.883 | G155: 5.5 | H155: 4.8 | I155: 6.874 | J155: 5.917 | K155: 5.451 | L155: 4.774
A156: 202206 | B156: 121.8 | C156: 121 | D156: 5.4 | E156: 7.44 | F156: 6.292 | G156: 5.7 | H156: 5.1 | I156: 7.076 | J156: 6.058 | K156: 5.566 | L156: 4.933
A157: 202207 | B157: 122.5 | C157: 121.9 | D157: 6 | E157: 7.96 | F157: 6.668 | G157: 5.5 | H157: 5.2 | I157: 7.56 | J157: 6.281 | K157: 5.53 | L157: 5.013
A158: 202208 | B158: 123.1 | C158: 122.7 | D158: 6.2 | E158: 7.63 | F158: 6.434 | G158: 6.4 | H158: 5.5 | I158: 7.676 | J158: 6.465 | K158: 5.835 | L158: 5.245
A159: 202209 | B159: 123.8 | C159: 122.9 | D159: 6.6 | E159: 7.41 | F159: 6.638 | G159: 6.5 | H159: 5.9 | I159: 7.665 | J159: 6.58 | K159: 6.1 | L159: 5.503
A160: 202210 | B160: 126.2 | C160: 123.8 | D160: 6.9 | E160: 7.76 | F160: 6.221 | G160: 6.1 | H160: 5.8 | I160: 7.599 | J160: 6.431 | K160: 6.301 | L160: 5.725
A161: 202211 | B161: 126.7 | C161: 124 | D161: 7.3 | E161: 7.2 | F161: 5.747 | G161: 6.1 | H161: 5.8 | I161: 7.456 | J161: 6.202 | K161: 6.214 | L161: 5.828
A162: 202212 | B162: 127.2 | C162: 125 | D162: 7.3 | E162: 8.54 | F162: 5.783 | G162: 6.6 | H162: 6.3 | I162: 7.832 | J162: 5.917 | K162: 6.258 | L162: 5.974
A163: 202301 | B163: 126.4 | C163: 123.8 | D163: 7.1 | E163: 7.85 | F163: 5.8 | G163: 6.3 | H163: 5.7 | I163: 7.864 | J163: 5.777 | K163: 6.337 | L163: 5.933
A164: 202302 | B164: 127.9 | C164: 125.1 | D164: 7.1 | E164: 7.78 | F164: 5.388 | G164: 6.6 | H164: 5.8 | I164: 8.059 | J164: 5.657 | K164: 6.51 | L164: 5.923
A165: 202303 | B165: 128.9 | C165: 126 | D165: 7.2 | E165: 7.81 | F165: 5.311 | G165: 6.5 | H165: 5.6 | I165: 7.815 | J165: 5.499 | K165: 6.464 | L165: 5.678
A166: 202304 | B166: 130.4 | C166: 128 | D166: 7.7 | E166: 7.44 | F166: 5.956 | G166: 6.6 | H166: 5.4 | I166: 7.677 | J166: 5.552 | K166: 6.557 | L166: 5.565
... A180: 202406 | B180: 134.1 | C180: 137.1 | D180: 5.2 | E180: 3.84 | F180: 3.576 | G180: 5.9 | H180: 4 | I180: 4.587 | J180: 3.875 | K180: 5.979 | L180: 4.239
A181: 202407 | B181: 133.8 | C181: 137.8 | E181: 4.35 | F181: 3.711 | G181: 5.7 | H181: 4.1 | I181: 4.26 | J181: 3.703 | K181: 5.882 | L181: 4.064
A182: 202408 | E182: 3.87 | F182: 3.366 | G182: 5.7 | H182: 4.1 | I182: 4.02 | J182: 3.551 | K182: 5.771 | L182: 4.068

Sheet HAVERD
A1: Date | B1: Month | C1: Year | D1: YYYYMM | E1: Quarter | F1: YYYYQQ | H1: Bank Rate | I1: Overnight | J1: 1 | K1: 2 | L1: 3 | M1: 4 | N1: 5 | O1: 6 | P1: 7 | Q1: 8 | R1: 9 | S1: 10 | T1: 11 | U1: 12 | V1: 13 | W1: 14 | X1: 15 | Y1: 16 | Z1: 17 | AA1: 18 | AB1: 19 | AC1: 20 | AD1: 21 | AE1: 22 | AF1: 23 | AG1: 24 | AH1: 25 | AI1: 26 | AJ1: 27 | AK1: 28 | AL1: 29 | AM1: 30 | AN1: 31 | AO1: 32 | AP1: 33 | AQ1: 34 | AR1: 35 | AS1: 36 | AT1: 37 | AU1: 38 | AV1: 39 | AW1: 40 | AX1: 41 | AY1: 42 | AZ1: 43 | BA1: 44 | BB1: 45 | BC1: 46 | BD1: 47 | BE1: 48 | BF1: 49 | BG1: 50 | BH1: 51 | BI1: 52 | BJ1: 53 | BK1: 54 | BL1: 55 | BM1: 56 | BN1: 57 | BO1: 58 | BP1: 59 | BQ1: 60 | BR1: 5.5yrs | BS1: 6yrs
G2: 20220101 !D | H2: R112RD@INTDAILY | I2: R112LOS@INTDAILY | J2: R11201F@INTDAILY | K2: R11202F@INTDAILY | L2: R11203F@INTDAILY | M2: R11204F@INTDAILY | N2: R11205F@INTDAILY | O2: R11206F@INTDAILY | P2: R11207F@INTDAILY | Q2: R11208F@INTDAILY | R2: R11209F@INTDAILY | S2: R11210F@INTDAILY | T2: R11211F@INTDAILY | U2: R11212F@INTDAILY | V2: R11213F@INTDAILY | W2: R11214F@INTDAILY | X2: R11215F@INTDAILY | Y2: R11216F@INTDAILY | Z2: R11217F@INTDAILY | AA2: R11218F@INTDAILY | AB2: R11219F@INTDAILY | AC2: R11220F@INTDAILY | AD2: R11221F@INTDAILY | AE2: R11222F@INTDAILY | AF2: R11223F@INTDAILY | AG2: R11224F@INTDAILY | AH2: R11225F@INTDAILY | AI2: R11226F@INTDAILY | AJ2: R11227F@INTDAILY | AK2: R11228F@INTDAILY | AL2: R11229F@INTDAILY | AM2: R11230F@INTDAILY | AN2: R11231F@INTDAILY | AO2: R11232F@INTDAILY | AP2: R11233F@INTDAILY | AQ2: R11234F@INTDAILY | AR2: R11235F@INTDAILY | AS2: R11236F@INTDAILY | AT2: R11237F@INTDAILY | AU2: R11238F@INTDAILY | AV2: R11239F@INTDAILY | AW2: R11240F@INTDAILY | AX2: R11241F@INTDAILY | AY2: R11242F@INTDAILY | AZ2: R11243F@INTDAILY | BA2: R11244F@INTDAILY | BB2: R11245F@INTDAILY | BC2: R11246F@INTDAILY | BD2: R11247F@INTDAILY | BE2: R11248F@INTDAILY | BF2: R11249F@INTDAILY | BG2: R11250F@INTDAILY | BH2: R11251F@INTDAILY | BI2: R11252F@INTDAILY | BJ2: R11253F@INTDAILY | BK2: R11254F@INTDAILY | BL2: R11255F@INTDAILY | BM2: R11256F@INTDAILY | BN2: R11257F@INTDAILY | BO2: R11258F@INTDAILY | BP2: R11259F@INTDAILY | BQ2: R11260F@INTDAILY | BR2: R112I5B@INTDAILY | BS2: R112I6A@INTDAILY | BU2: T112G2@INTDAILY | BV2: T112GA@INTDAILY | BW2: X112EN@INTDAILY
G3: .DESC | H3: United Kingdom: Official Bank Rate (%) | I3: UK:Lending Rate: Sterling Overnight Interbank Average [SONIA] (% pa) | J3: UK: Overnight Index Swap: Forward Yields, 1-Month (% p.a.) | K3: UK: Overnight Index Swap: Forward Yields, 2-Month (% p.a.) | L3: UK: Overnight Index Swap: Forward Yields, 3-Month (% p.a.) | M3: UK: Overnight Index Swap: Forward Yields, 4-Month (% p.a.) | N3: UK: Overnight Index Swap: Forward Yields, 5-Month (% p.a.) | O3: UK: Overnight Index Swap: Forward Yields, 6-Month (% p.a.) | P3: UK: Overnight Index Swap: Forward Yields, 7-Month (% p.a.) | Q3: UK: Overnight Index Swap: Forward Yields, 8-Month (% p.a.) | R3: UK: Overnight Index Swap: Forward Yields, 9-Month (% p.a.) | S3: UK: Overnight Index Swap: Forward Yields, 10-Month (% p.a.) | T3: UK: Overnight Index Swap: Forward Yields, 11-Month (% p.a.) | U3: UK: Overnight Index Swap: Forward Yields, 12-Month (% p.a.) | V3: UK: Overnight Index Swap: Forward Yields, 13-Month (% p.a.) | W3: UK: Overnight Index Swap: Forward Yields, 14-Month (% p.a.) | X3: UK: Overnight Index Swap: Forward Yields, 15-Month (% p.a.) | Y3: UK: Overnight Index Swap: Forward Yields, 16-Month (% p.a.) | Z3: UK: Overnight Index Swap: Forward Yields, 17-Month (% p.a.) | AA3: UK: Overnight Index Swap: Forward Yields, 18-Month (% p.a.) | AB3: UK: Overnight Index Swap: Forward Yields, 19-Month (% p.a.) | AC3: UK: Overnight Index Swap: Forward Yields, 20-Month (% p.a.) | AD3: UK: Overnight Index Swap: Forward Yields, 21-Month (% p.a.) | AE3: UK: Overnight Index Swap: Forward Yields, 22-Month (% p.a.) | AF3: UK: Overnight Index Swap: Forward Yields, 23-Month (% p.a.) | AG3: UK: Overnight Index Swap: Forward Yields, 24-Month (% p.a.) | AH3: UK: Overnight Index Swap: Forward Yields, 25-Month (% p.a.) | AI3: UK: Overnight Index Swap: Forward Yields, 26-Month (% p.a.) | AJ3: UK: Overnight Index Swap: Forward Yields, 27-Month (% p.a.) | AK3: UK: Overnight Index Swap: Forward Yields, 28-Month (% p.a.) | AL3: UK: Overnight Index Swap: Forward Yields, 29-Month (% p.a.) | AM3: UK: Overnight Index Swap: Forward Yields, 30-Month (% p.a.) | AN3: UK: Overnight Index Swap: Forward Yields, 31-Month (% p.a.) | AO3: UK: Overnight Index Swap: Forward Yields, 32-Month (% p.a.) | AP3: UK: Overnight Index Swap: Forward Yields, 33-Month (% p.a.) | AQ3: UK: Overnight Index Swap: Forward Yields, 34-Month (% p.a.) | AR3: UK: Overnight Index Swap: Forward Yields, 35-Month (% p.a.) | AS3: UK: Overnight Index Swap: Forward Yields, 36-Month (% p.a.) | AT3: UK: Overnight Index Swap: Forward Yields, 37-Month (% p.a.) | AU3: UK: Overnight Index Swap: Forward Yields, 38-Month (% p.a.) | AV3: UK: Overnight Index Swap: Forward Yields, 39-Month (% p.a.) | AW3: UK: Overnight Index Swap: Forward Yields, 40-Month (% p.a.) | AX3: UK: Overnight Index Swap: Forward Yields, 41-Month (% p.a.) | AY3: UK: Overnight Index Swap: Forward Yields, 42-Month (% p.a.) | AZ3: UK: Overnight Index Swap: Forward Yields, 43-Month (% p.a.) | BA3: UK: Overnight Index Swap: Forward Yields, 44-Month (% p.a.) | BB3: UK: Overnight Index Swap: Forward Yields, 45-Month (% p.a.) | BC3: UK: Overnight Index Swap: Forward Yields, 46-Month (% p.a.) | BD3: UK: Overnight Index Swap: Forward Yields, 47-Month (% p.a.) | BE3: UK: Overnight Index Swap: Forward Yields, 48-Month (% p.a.) | BF3: UK: Overnight Index Swap: Forward Yields, 49-Month (% p.a.) | BG3: UK: Overnight Index Swap: Forward Yields, 50-Month (% p.a.) | BH3: UK: Overnight Index Swap: Forward Yields, 51-Month (% p.a.) | BI3: UK: Overnight Index Swap: Forward Yields, 52-Month (% p.a.) | BJ3: UK: Overnight Index Swap: Forward Yields, 53-Month (% p.a.) | BK3: UK: Overnight Index Swap: Forward Yields, 54-Month (% p.a.) | BL3: UK: Overnight Index Swap: Forward Yields, 55-Month (% p.a.) | BM3: UK: Overnight Index Swap: Forward Yields, 56-Month (% p.a.) | BN3: UK: Overnight Index Swap: Forward Yields, 57-Month (% p.a.) | BO3: UK: Overnight Index Swap: Forward Yields, 58-Month (% p.a.) | BP3: UK: Overnight Index Swap: Forward Yields, 59-Month (% p.a.) | BQ3: UK: Overnight Index Swap: Forward Yields, 60-Month (% p.a.) | BR3: UK: Overnight Index Swap: Forward Yields, 5.5-Year (% p.a.) | BS3: UK: Overnight Index Swap: Forward Yields, 6-Year (% p.a.) | BU3: UK: 2-Yr Government Bond Yield (%) | BV3: UK: 10-Yr Government Bond Yield (%) | BW3: UK: Effective Exchange Rate Index: Narrow (Jan-05=100)
G4: .T1 | H4: 01-Jan-1953 | I4: 02-Jan-1997 | J4: 02-Jan-2009 | K4: 02-Jan-2009 | L4: 02-Jan-2009 | M4: 02-Jan-2009 | N4: 02-Jan-2009 | O4: 02-Jan-2009 | P4: 02-Jan-2009 | Q4: 02-Jan-2009 | R4: 02-Jan-2009 | S4: 02-Jan-2009 | T4: 02-Jan-2009 | U4: 02-Jan-2009 | V4: 02-Jan-2009 | W4: 02-Jan-2009 | X4: 02-Jan-2009 | Y4: 02-Jan-2009 | Z4: 02-Jan-2009 | AA4: 02-Jan-2009 | AB4: 02-Jan-2009 | AC4: 02-Jan-2009 | AD4: 02-Jan-2009 | AE4: 02-Jan-2009 | AF4: 02-Jan-2009 | AG4: 02-Jan-2009 | AH4: 02-Jan-2009 | AI4: 02-Jan-2009 | AJ4: 02-Jan-2009 | AK4: 02-Jan-2009 | AL4: 02-Jan-2009 | AM4: 02-Jan-2009 | AN4: 02-Jan-2009 | AO4: 02-Jan-2009 | AP4: 02-Jan-2009 | AQ4: 02-Jan-2009 | AR4: 02-Jan-2009 | AS4: 02-Jan-2009 | AT4: 02-Jan-2009 | AU4: 02-Jan-2009 | AV4: 02-Jan-2009 | AW4: 02-Jan-2009 | AX4: 02-Jan-2009 | AY4: 02-Jan-2009 | AZ4: 02-Jan-2009 | BA4: 02-Jan-2009 | BB4: 02-Jan-2009 | BC4: 02-Jan-2009 | BD4: 02-Jan-2009 | BE4: 02-Jan-2009 | BF4: 02-Jan-2009 | BG4: 02-Jan-2009 | BH4: 02-Jan-2009 | BI4: 02-Jan-2009 | BJ4: 02-Jan-2009 | BK4: 02-Jan-2009 | BL4: 02-Jan-2009 | BM4: 02-Jan-2009 | BN4: 02-Jan-2009 | BO4: 02-Jan-2009 | BP4: 02-Jan-2009 | BQ4: 02-Jan-2009 | BR4: 01-Dec-2021 | BS4: 01-Dec-2021 | BU4: 26-Jan-1994 | BV4: 26-Jan-1994 | BW4: 02-Jan-1990
G5: .TN | H5: 06-Sep-2024 | I5: 05-Sep-2024 | J5: 05-Sep-2024 | K5: 05-Sep-2024 | L5: 05-Sep-2024 | M5: 05-Sep-2024 | N5: 05-Sep-2024 | O5: 05-Sep-2024 | P5: 05-Sep-2024 | Q5: 05-Sep-2024 | R5: 05-Sep-2024 | S5: 05-Sep-2024 | T5: 05-Sep-2024 | U5: 05-Sep-2024 | V5: 05-Sep-2024 | W5: 05-Sep-2024 | X5: 05-Sep-2024 | Y5: 05-Sep-2024 | Z5: 05-Sep-2024 | AA5: 05-Sep-2024 | AB5: 05-Sep-2024 | AC5: 05-Sep-2024 | AD5: 05-Sep-2024 | AE5: 05-Sep-2024 | AF5: 05-Sep-2024 | AG5: 05-Sep-2024 | AH5: 05-Sep-2024 | AI5: 05-Sep-2024 | AJ5: 05-Sep-2024 | AK5: 05-Sep-2024 | AL5: 05-Sep-2024 | AM5: 05-Sep-2024 | AN5: 05-Sep-2024 | AO5: 05-Sep-2024 | AP5: 05-Sep-2024 | AQ5: 05-Sep-2024 | AR5: 05-Sep-2024 | AS5: 05-Sep-2024 | AT5: 05-Sep-2024 | AU5: 05-Sep-2024 | AV5: 05-Sep-2024 | AW5: 05-Sep-2024 | AX5: 05-Sep-2024 | AY5: 05-Sep-2024 | AZ5: 05-Sep-2024 | BA5: 05-Sep-2024 | BB5: 05-Sep-2024 | BC5: 05-Sep-2024 | BD5: 05-Sep-2024 | BE5: 05-Sep-2024 | BF5: 05-Sep-2024 | BG5: 05-Sep-2024 | BH5: 05-Sep-2024 | BI5: 05-Sep-2024 | BJ5: 05-Sep-2024 | BK5: 05-Sep-2024 | BL5: 05-Sep-2024 | BM5: 05-Sep-2024 | BN5: 05-Sep-2024 | BO5: 05-Sep-2024 | BP5: 05-Sep-2024 | BQ5: 05-Sep-2024 | BR5: 05-Sep-2024 | BS5: 05-Sep-2024 | BU5: 06-Sep-2024 | BV5: 06-Sep-2024 | BW5: 06-Sep-2024
G6: .LSOURCE | H6: Bank of England | I6: Bank of England | J6: Bank of England | K6: Bank of England | L6: Bank of England | M6: Bank of England | N6: Bank of England | O6: Bank of England | P6: Bank of England | Q6: Bank of England | R6: Bank of England | S6: Bank of England | T6: Bank of England | U6: Bank of England | V6: Bank of England | W6: Bank of England | X6: Bank of England | Y6: Bank of England | Z6: Bank of England | AA6: Bank of England | AB6: Bank of England | AC6: Bank of England | AD6: Bank of England | AE6: Bank of England | AF6: Bank of England | AG6: Bank of England | AH6: Bank of England | AI6: Bank of England | AJ6: Bank of England | AK6: Bank of England | AL6: Bank of England | AM6: Bank of England | AN6: Bank of England | AO6: Bank of England | AP6: Bank of England | AQ6: Bank of England | AR6: Bank of England | AS6: Bank of England | AT6: Bank of England | AU6: Bank of England | AV6: Bank of England | AW6: Bank of England | AX6: Bank of England | AY6: Bank of England | AZ6: Bank of England | BA6: Bank of England | BB6: Bank of England | BC6: Bank of England | BD6: Bank of England | BE6: Bank of England | BF6: Bank of England | BG6: Bank of England | BH6: Bank of England | BI6: Bank of England | BJ6: Bank of England | BK6: Bank of England | BL6: Bank of England | BM6: Bank of England | BN6: Bank of England | BO6: Bank of England | BP6: Bank of England | BQ6: Bank of England | BR6: Bank of England | BS6: Bank of England | BU6: London Stock Exchange Group | BV6: London Stock Exchange Group | BW6: Bank of England
G7: .DTLM | H7: Sep-06-2024 13:57 | I7: Sep-09-2024 09:30 | J7: Sep-06-2024 11:11 | K7: Sep-06-2024 11:11 | L7: Sep-06-2024 11:11 | M7: Sep-06-2024 11:11 | N7: Sep-06-2024 11:11 | O7: Sep-06-2024 11:11 | P7: Sep-06-2024 11:11 | Q7: Sep-06-2024 11:11 | R7: Sep-06-2024 11:11 | S7: Sep-06-2024 11:11 | T7: Sep-06-2024 11:11 | U7: Sep-06-2024 11:11 | V7: Sep-06-2024 11:11 | W7: Sep-06-2024 11:11 | X7: Sep-06-2024 11:11 | Y7: Sep-06-2024 11:11 | Z7: Sep-06-2024 11:11 | AA7: Sep-06-2024 11:11 | AB7: Sep-06-2024 11:11 | AC7: Sep-06-2024 11:11 | AD7: Sep-06-2024 11:11 | AE7: Sep-06-2024 11:11 | AF7: Sep-06-2024 11:11 | AG7: Sep-06-2024 11:11 | AH7: Sep-06-2024 11:11 | AI7: Sep-06-2024 11:11 | AJ7: Sep-06-2024 11:11 | AK7: Sep-06-2024 11:11 | AL7: Sep-06-2024 11:11 | AM7: Sep-06-2024 11:11 | AN7: Sep-06-2024 11:11 | AO7: Sep-06-2024 11:11 | AP7: Sep-06-2024 11:11 | AQ7: Sep-06-2024 11:11 | AR7: Sep-06-2024 11:11 | AS7: Sep-06-2024 11:11 | AT7: Sep-06-2024 11:11 | AU7: Sep-06-2024 11:11 | AV7: Sep-06-2024 11:11 | AW7: Sep-06-2024 11:11 | AX7: Sep-06-2024 11:11 | AY7: Sep-06-2024 11:11 | AZ7: Sep-06-2024 11:11 | BA7: Sep-06-2024 11:11 | BB7: Sep-06-2024 11:11 | BC7: Sep-06-2024 11:11 | BD7: Sep-06-2024 11:11 | BE7: Sep-06-2024 11:11 | BF7: Sep-06-2024 11:11 | BG7: Sep-06-2024 11:11 | BH7: Sep-06-2024 11:11 | BI7: Sep-06-2024 11:11 | BJ7: Sep-06-2024 11:11 | BK7: Sep-06-2024 11:11 | BL7: Sep-06-2024 11:11 | BM7: Sep-06-2024 11:11 | BN7: Sep-06-2024 11:11 | BO7: Sep-06-2024 11:11 | BP7: Sep-06-2024 11:11 | BQ7: Sep-06-2024 11:11 | BR7: Sep-06-2024 11:11 | BS7: Sep-06-2024 11:11 | BU7: Sep-06-2024 21:03 | BV7: Sep-06-2024 21:03 | BW7: Sep-09-2024 09:30
A8: 44564 | B8: =MONTH(A8) -> 1 | C8: =YEAR(A8) -> 2022 | D8: =C8*100+B8 -> 202201 | E8: =IF(B8<4,1,IF(B8<7,2,IF(B8<10,3,4))) -> 1 | F8: =C8*100+E8 -> 202201 | G8: 20220103 | H8: 0.25 | I8: #N/A | J8: #N/A | K8: #N/A | L8: #N/A | M8: #N/A | N8: #N/A | O8: #N/A | P8: #N/A | Q8: #N/A | R8: #N/A | S8: #N/A | T8: #N/A | U8: #N/A | V8: #N/A | W8: #N/A | X8: #N/A | Y8: #N/A | Z8: #N/A | AA8: #N/A | AB8: #N/A | AC8: #N/A | AD8: #N/A | AE8: #N/A | AF8: #N/A | AG8: #N/A | AH8: #N/A | AI8: #N/A | AJ8: #N/A | AK8: #N/A | AL8: #N/A | AM8: #N/A | AN8: #N/A | AO8: #N/A | AP8: #N/A | AQ8: #N/A | AR8: #N/A | AS8: #N/A | AT8: #N/A | AU8: #N/A | AV8: #N/A | AW8: #N/A | AX8: #N/A | AY8: #N/A | AZ8: #N/A | BA8: #N/A | BB8: #N/A | BC8: #N/A | BD8: #N/A | BE8: #N/A | BF8: #N/A | BG8: #N/A | BH8: #N/A | BI8: #N/A | BJ8: #N/A | BK8: #N/A | BL8: #N/A | BM8: #N/A | BN8: #N/A | BO8: #N/A | BP8: #N/A | BQ8: #N/A | BR8: #N/A | BS8: #N/A | BU8: 0.68 | BV8: 0.97 | BW8: #N/A
A9: 44565 | B9: =MONTH(A9) -> 1 | C9: =YEAR(A9) -> 2022 | D9: =C9*100+B9 -> 202201 | E9: =IF(B9<4,1,IF(B9<7,2,IF(B9<10,3,4))) -> 1 | F9: =C9*100+E9 -> 202201 | G9: 20220104 | H9: 0.25 | I9: 0.1947 | J9: 0.2791187 | K9: 0.4284083 | L9: 0.5445391 | M9: 0.6472082 | N9: 0.7432518 | O9: 0.8319514 | P9: 0.9125866 | Q9: 0.9841672 | R9: 1.0459395 | S9: 1.0986445 | T9: 1.1431408 | U9: 1.1805307 | V9: 1.2124128 | W9: 1.2394521 | X9: 1.2620316 | Y9: 1.2805346 | Z9: 1.295344 | AA9: 1.3068431 | AB9: 1.315385 | AC9: 1.3212194 | AD9: 1.3245738 | AE9: 1.3256757 | AF9: 1.3247525 | AG9: 1.3220317 | AH9: 1.3177258 | AI9: 1.3119874 | AJ9: 1.3049541 | AK9: 1.2967636 | AL9: 1.2875535 | AM9: 1.2774616 | AN9: 1.2666254 | AO9: 1.2551827 | AP9: 1.243271 | AQ9: 1.2310281 | AR9: 1.2185915 | AS9: 1.206099 | AT9: 1.1936743 | AU9: 1.1813664 | AV9: 1.1691993 | AW9: 1.157197 | AX9: 1.1453834 | AY9: 1.1337824 | AZ9: 1.122418 | BA9: 1.1113142 | BB9: 1.1004949 | BC9: 1.089984 | BD9: 1.0798055 | BE9: 1.0699833 | BF9: 1.060538 | BG9: 1.0514731 | BH9: 1.0427873 | BI9: 1.0344791 | BJ9: 1.0265469 | BK9: 1.0189894 | BL9: 1.0118051 | BM9: 1.0049925 | BN9: 0.9985501 | BO9: 0.9924765 | BP9: 0.9867702 | BQ9: 0.9814298 | BR9: 0.9567349 | BS9: 0.943305 | BU9: 0.77 | BV9: 1.08 | BW9: 82.7359
A10: 44566 | B10: =MONTH(A10) -> 1 | C10: =YEAR(A10) -> 2022 | D10: =C10*100+B10 -> 202201 | E10: =IF(B10<4,1,IF(B10<7,2,IF(B10<10,3,4))) -> 1 | F10: =C10*100+E10 -> 202201 | G10: 20220105 | H10: 0.25 | I10: 0.1948 | J10: 0.2877935 | K10: 0.4230475 | L10: 0.5370288 | M10: 0.6435925 | N10: 0.7449776 | O10: 0.838019 | P10: 0.9216542 | Q10: 0.9952707 | R10: 1.0587198 | S10: 1.1129231 | T10: 1.1591448 | U10: 1.1982755 | V10: 1.2318165 | W10: 1.2603874 | X10: 1.2843212 | Y10: 1.3039511 | Z10: 1.3196102 | AA10: 1.3316315 | AB10: 1.3403383 | AC10: 1.3460196 | AD10: 1.3489575 | AE10: 1.3494335 | AF10: 1.3477296 | AG10: 1.3441275 | AH10: 1.3388866 | AI10: 1.3321754 | AJ10: 1.3241403 | AK10: 1.3149274 | AL10: 1.3046828 | AM10: 1.2935527 | AN10: 1.2816834 | AO10: 1.269221 | AP10: 1.2563116 | AQ10: 1.2431014 | AR10: 1.2297367 | AS10: 1.2163635 | AT10: 1.2031114 | AU10: 1.1900286 | AV10: 1.1771387 | AW10: 1.1644651 | AX10: 1.1520314 | AY10: 1.139861 | AZ10: 1.1279775 | BA10: 1.1164044 | BB10: 1.1051652 | BC10: 1.0942833 | BD10: 1.0837824 | BE10: 1.073686 | BF10: 1.0640132 | BG10: 1.0547647 | BH10: 1.0459358 | BI10: 1.0375221 | BJ10: 1.0295189 | BK10: 1.0219216 | BL10: 1.0147257 | BM10: 1.0079265 | BN10: 1.0015195 | BO10: 0.9955001 | BP10: 0.9898637 | BQ10: 0.9846058 | BR10: 0.9605211 | BS10: 0.947527 | BU10: 0.76 | BV10: 1.09 | BW10: 82.7017
A11: 44567 | B11: =MONTH(A11) -> 1 | C11: =YEAR(A11) -> 2022 | D11: =C11*100+B11 -> 202201 | E11: =IF(B11<4,1,IF(B11<7,2,IF(B11<10,3,4))) -> 1 | F11: =C11*100+E11 -> 202201 | G11: 20220106 | H11: 0.25 | I11: 0.1947 | J11: 0.294144 | K11: 0.4323879 | L11: 0.549438 | M11: 0.6611223 | N11: 0.7694016 | O11: 0.8695319 | P11: 0.9589803 | Q11: 1.0364108 | R11: 1.1020323 | S11: 1.1573209 | T11: 1.2039229 | U11: 1.2431974 | V11: 1.2768497 | W11: 1.3055114 | X11: 1.3294981 | Y11: 1.3491254 | Z11: 1.3647088 | AA11: 1.3765642 | AB11: 1.3850088 | AC11: 1.3903667 | AD11: 1.392963 | AE11: 1.3931229 | AF11: 1.3911717 | AG11: 1.3874346 | AH11: 1.3822112 | AI11: 1.375676 | AJ11: 1.3679653 | AK11: 1.3592157 | AL11: 1.3495635 | AM11: 1.3391451 | AN11: 1.328097 | AO11: 1.3165555 | AP11: 1.3046571 | AQ11: 1.2925382 | AR11: 1.2803352 | AS11: 1.2681845 | AT11: 1.2562039 | AU11: 1.2444291 | AV11: 1.2328733 | AW11: 1.2215495 | AX11: 1.2104707 | AY11: 1.19965 | AZ11: 1.1891005 | BA11: 1.1788352 | BB11: 1.1688672 | BC11: 1.1592096 | BD11: 1.1498754 | BE11: 1.1408777 | BF11: 1.1322272 | BG11: 1.1239243 | BH11: 1.1159664 | BI11: 1.108351 | BJ11: 1.1010755 | BK11: 1.0941375 | BL11: 1.0875344 | BM11: 1.0812636 | BN11: 1.0753228 | BO11: 1.0697092 | BP11: 1.0644204 | BQ11: 1.0594539 | BR11: 1.0360997 | BS11: 1.0226118 | BU11: 0.8 | BV11: 1.14 | BW11: 82.6995
A12: 44568 | B12: =MONTH(A12) -> 1 | C12: =YEAR(A12) -> 2022 | D12: =C12*100+B12 -> 202201 | E12: =IF(B12<4,1,IF(B12<7,2,IF(B12<10,3,4))) -> 1 | F12: =C12*100+E12 -> 202201 | G12: 20220107 | H12: 0.25 | I12: 0.195 | J12: 0.299367 | K12: 0.4352152 | L12: 0.5506315 | M12: 0.6600259 | N12: 0.7651957 | O12: 0.862934 | P12: 0.9518709 | Q12: 1.030635 | R12: 1.0986118 | S12: 1.1564615 | T12: 1.2051818 | U12: 1.2459918 | V12: 1.2805155 | W12: 1.3095279 | X12: 1.3335035 | Y12: 1.3529163 | Z12: 1.3682406 | AA12: 1.3799507 | AB12: 1.388485 | AC12: 1.3941595 | AD12: 1.3972636 | AE12: 1.3980865 | AF12: 1.3969177 | AG12: 1.3940465 | AH12: 1.389738 | AI12: 1.3841499 | AJ12: 1.3774102 | AK12: 1.3696471 | AL12: 1.3609885 | AM12: 1.3515626 | AN12: 1.3414974 | AO12: 1.330921 | AP12: 1.3199615 | AQ12: 1.308747 | AR12: 1.2974055 | AS12: 1.2860651 | AT12: 1.2748371 | AU12: 1.2637586 | AV12: 1.2528464 | AW12: 1.2421173 | AX12: 1.2315879 | AY12: 1.2212749 | AZ12: 1.2111952 | BA12: 1.2013654 | BB12: 1.1918023 | BC12: 1.1825225 | BD12: 1.1735429 | BE12: 1.1648801 | BF12: 1.156548 | BG12: 1.1485479 | BH12: 1.1408774 | BI12: 1.1335344 | BJ12: 1.1265165 | BK12: 1.1198215 | BL12: 1.1134472 | BM12: 1.1073913 | BN12: 1.1016514 | BO12: 1.0962255 | BP12: 1.0911112 | BQ12: 1.0863062 | BR12: 1.0636822 | BS12: 1.0506291 | BU12: 0.82 | BV12: 1.18 | BW12: 82.7637
A13: =+A8+7 -> 44571 | B13: =MONTH(A13) -> 1 | C13: =YEAR(A13) -> 2022 | D13: =C13*100+B13 -> 202201 | E13: =IF(B13<4,1,IF(B13<7,2,IF(B13<10,3,4))) -> 1 | F13: =C13*100+E13 -> 202201 | G13: 20220110 | H13: 0.25 | I13: 0.1948 | J13: 0.3233739 | K13: 0.4492843 | L13: 0.5595041 | M13: 0.6674331 | N13: 0.7737431 | O13: 0.8738596 | P13: 0.9649919 | Q13: 1.0455164 | R13: 1.1145573 | S13: 1.1728955 | T13: 1.2213302 | U13: 1.2611431 | V13: 1.2946625 | W13: 1.3228045 | X13: 1.34603 | Y13: 1.3647996 | Z13: 1.3795741 | AA13: 1.3908142 | AB13: 1.398948 | AC13: 1.4042908 | AD13: 1.4071335 | AE13: 1.4077671 | AF13: 1.4064827 | AG13: 1.4035711 | AH13: 1.3992955 | AI13: 1.3938068 | AJ13: 1.3872284 | AK13: 1.3796834 | AL13: 1.371295 | AM13: 1.3621864 | AN13: 1.3524807 | AO13: 1.3423012 | AP13: 1.331771 | AQ13: 1.3210133 | AR13: 1.3101512 | AS13: 1.2993081 | AT13: 1.2885905 | AU13: 1.2780322 | AV13: 1.267647 | AW13: 1.2574486 | AX13: 1.2474507 | AY13: 1.237667 | AZ13: 1.2281112 | BA13: 1.2187971 | BB13: 1.2097383 | BC13: 1.2009486 | BD13: 1.1924416 | BE13: 1.1842312 | BF13: 1.1763291 | BG13: 1.1687377 | BH13: 1.1614562 | BI13: 1.1544835 | BJ13: 1.1478187 | BK13: 1.1414609 | BL13: 1.1354091 | BM13: 1.1296625 | BN13: 1.1242201 | BO13: 1.119081 | BP13: 1.1142442 | BQ13: 1.1097088 | BR13: 1.0885565 | BS13: 1.0766866 | BU13: 0.84 | BV13: 1.19 | BW13: 82.7903
A14: =+A9+7 -> 44572 | B14: =MONTH(A14) -> 1 | C14: =YEAR(A14) -> 2022 | D14: =C14*100+B14 -> 202201 | E14: =IF(B14<4,1,IF(B14<7,2,IF(B14<10,3,4))) -> 1 | F14: =C14*100+E14 -> 202201 | G14: 20220111 | H14: 0.25 | I14: 0.1952 | J14: 0.3342072 | K14: 0.4580591 | L14: 0.5662436 | M14: 0.6727476 | N14: 0.7785918 | O14: 0.8790316 | P14: 0.9703171 | Q14: 1.0506056 | R14: 1.1193507 | S14: 1.1775816 | T14: 1.2262998 | U14: 1.2666799 | V14: 1.3001884 | W14: 1.3276384 | X14: 1.3496509 | Y14: 1.3668469 | Z14: 1.3798474 | AA14: 1.3892736 | AB14: 1.3956845 | AC14: 1.399425 | AD14: 1.4007942 | AE14: 1.4000909 | AF14: 1.397614 | AG14: 1.3936624 | AH14: 1.3885031 | AI14: 1.3822749 | AJ14: 1.3750845 | AK14: 1.3670387 | AL14: 1.3582444 | AM14: 1.3488084 | AN14: 1.3388374 | AO14: 1.3284383 | AP14: 1.3177178 | AQ14: 1.3067828 | AR14: 1.2957401 | AS14: 1.2846964 | AT14: 1.2737474 | AU14: 1.2629286 | AV14: 1.2522551 | AW14: 1.2417422 | AX14: 1.2314051 | AY14: 1.2212591 | AZ14: 1.2113194 | BA14: 1.2016012 | BB14: 1.1921198 | BC14: 1.1828905 | BD14: 1.1739284 | BE14: 1.1652487 | BF14: 1.1568647 | BG14: 1.148779 | BH14: 1.1409912 | BI14: 1.1335009 | BJ14: 1.1263078 | BK14: 1.1194114 | BL14: 1.1128112 | BM14: 1.106507 | BN14: 1.1004982 | BO14: 1.0947845 | BP14: 1.0893655 | BQ14: 1.0842408 | BR14: 1.0594709 | BS14: 1.044113 | BU14: 0.84 | BV14: 1.17 | BW14: 82.9655
A15: =+A10+7 -> 44573 | B15: =MONTH(A15) -> 1 | C15: =YEAR(A15) -> 2022 | D15: =C15*100+B15 -> 202201 | E15: =IF(B15<4,1,IF(B15<7,2,IF(B15<10,3,4))) -> 1 | F15: =C15*100+E15 -> 202201 | G15: 20220112 | H15: 0.25 | I15: 0.1958 | J15: 0.3438824 | K15: 0.4613511 | L15: 0.5666589 | M15: 0.6719027 | N15: 0.7761783 | O15: 0.873638 | P15: 0.9603971 | Q15: 1.0349568 | R15: 1.0973904 | S15: 1.1488798 | T15: 1.1910577 | U15: 1.2252432 | V15: 1.253462 | W15: 1.2765734 | X15: 1.2950677 | Y15: 1.3094355 | Z15: 1.3201675 | AA15: 1.3277541 | AB15: 1.3326424 | AC15: 1.3351294 | AD15: 1.3354798 | AE15: 1.333958 | AF15: 1.3308289 | AG15: 1.3263569 | AH15: 1.3207797 | AI15: 1.3142275 | AJ15: 1.3068032 | AK15: 1.2986099 | AL15: 1.2897508 | AM15: 1.280329 | AN15: 1.2704474 | AO15: 1.2602093 | AP15: 1.2497177 | AQ15: 1.2390756 | AR15: 1.2283863 | AS15: 1.2177527 | AT15: 1.2072655 | AU15: 1.1969543 | AV15: 1.1868302 | AW15: 1.1769044 | AX15: 1.1671879 | AY15: 1.1576918 | AZ15: 1.1484273 | BA15: 1.1394056 | BB15: 1.1306376 | BC15: 1.1221344 | BD15: 1.1139074 | BE15: 1.1059674 | BF15: 1.0983236 | BG15: 1.0909761 | BH15: 1.0839224 | BI15: 1.0771601 | BJ15: 1.0706868 | BK15: 1.0645001 | BL15: 1.0585976 | BM15: 1.0529769 | BN15: 1.0476354 | BO15: 1.0425709 | BP15: 1.0377809 | BQ15: 1.033263 | BR15: 1.011594 | BS15: 0.9982642 | BU15: 0.79 | BV15: 1.13 | BW15: 83.0292
A16: =+A11+7 -> 44574 | B16: =MONTH(A16) -> 1 | C16: =YEAR(A16) -> 2022 | D16: =C16*100+B16 -> 202201 | E16: =IF(B16<4,1,IF(B16<7,2,IF(B16<10,3,4))) -> 1 | F16: =C16*100+E16 -> 202201 | G16: 20220113 | H16: 0.25 | I16: 0.1959 | J16: 0.3486056 | K16: 0.4580109 | L16: 0.557275 | M16: 0.6585685 | N16: 0.7606032 | O16: 0.8566349 | P16: 0.9420787 | Q16: 1.0151672 | R16: 1.0761158 | S16: 1.1262448 | T16: 1.1671739 | U16: 1.2003912 | V16: 1.2278107 | W16: 1.2502337 | X16: 1.2681317 | Y16: 1.2819765 | Z16: 1.2922397 | AA16: 1.2993931 | AB16: 1.303871 | AC16: 1.3059785 | AD16: 1.3059933 | AE16: 1.3041928 | AF16: 1.3008544 | AG16: 1.2962556 | AH16: 1.2906494 | AI16: 1.2841688 | AJ16: 1.2769104 | AK16: 1.2689711 | AL16: 1.2604473 | AM16: 1.2514357 | AN16: 1.2420331 | AO16: 1.232336 | AP16: 1.2224411 | AQ16: 1.212445 | AR16: 1.2024444 | AS16: 1.192536 | AT16: 1.1828026 | AU16: 1.1732666 | AV16: 1.1639336 | AW16: 1.1548091 | AX16: 1.1458988 | AY16: 1.1372082 | AZ16: 1.1287429 | BA16: 1.1205084 | BB16: 1.1125105 | BC16: 1.1047546 | BD16: 1.0972463 | BE16: 1.0899913 | BF16: 1.0829938 | BG16: 1.0762524 | BH16: 1.0697642 | BI16: 1.063526 | BJ16: 1.057535 | BK16: 1.0517881 | BL16: 1.0462824 | BM16: 1.0410148 | BN16: 1.0359823 | BO16: 1.0311821 | BP16: 1.026611 | BQ16: 1.022266 | BR16: 1.0007577 | BS16: 0.9865096 | BU16: 0.76 | BV16: 1.11 | BW16: 83.1356
A17: =+A12+7 -> 44575 | B17: =MONTH(A17) -> 1 | C17: =YEAR(A17) -> 2022 | D17: =C17*100+B17 -> 202201 | E17: =IF(B17<4,1,IF(B17<7,2,IF(B17<10,3,4))) -> 1 | F17: =C17*100+E17 -> 202201 | G17: 20220114 | H17: 0.25 | I17: 0.1959 | J17: 0.3626426 | K17: 0.4689781 | L17: 0.5695873 | M17: 0.6729465 | N17: 0.7768524 | O17: 0.8747632 | P17: 0.9622623 | Q17: 1.0375233 | R17: 1.1006587 | S17: 1.1530048 | T17: 1.1960602 | U17: 1.2313642 | V17: 1.2606326 | W17: 1.2846771 | X17: 1.3040059 | Y17: 1.319127 | Z17: 1.3305484 | AA17: 1.3387783 | AB17: 1.3442797 | AC17: 1.3473607 | AD17: 1.3482956 | AE17: 1.347359 | AF17: 1.3448254 | AG17: 1.3409693 | AH17: 1.3360392 | AI17: 1.3301692 | AJ17: 1.3234618 | AK17: 1.3160195 | AL17: 1.3079446 | AM17: 1.2993397 | AN17: 1.2903072 | AO17: 1.2809497 | AP17: 1.2713695 | AQ17: 1.2616692 | AR17: 1.2519511 | AS17: 1.2423179 | AT17: 1.2328574 | AU17: 1.2235937 | AV17: 1.2145332 | AW17: 1.2056823 | AX17: 1.1970474 | AY17: 1.1886349 | AZ17: 1.1804511 | BA17: 1.1725026 | BB17: 1.1647957 | BC17: 1.1573368 | BD17: 1.1501322 | BE17: 1.1431885 | BF17: 1.1365105 | BG17: 1.1300967 | BH17: 1.1239441 | BI17: 1.1180493 | BJ17: 1.1124092 | BK17: 1.1070205 | BL17: 1.1018801 | BM17: 1.0969846 | BN17: 1.092331 | BO17: 1.087916 | BP17: 1.0837363 | BQ17: 1.0797888 | BR17: 1.0607315 | BS17: 1.0488111 | BU17: 0.79 | BV17: 1.16 | BW17: 82.9327
A18: =+A13+7 -> 44578 | B18: =MONTH(A18) -> 1 | C18: =YEAR(A18) -> 2022 | D18: =C18*100+B18 -> 202201 | E18: =IF(B18<4,1,IF(B18<7,2,IF(B18<10,3,4))) -> 1 | F18: =C18*100+E18 -> 202201 | G18: 20220117 | H18: 0.25 | I18: 0.196 | J18: 0.3899075 | K18: 0.4769121 | L18: 0.5779532 | M18: 0.6882092 | N18: 0.7976721 | O18: 0.8984824 | P18: 0.9868723 | Q18: 1.0621298 | R18: 1.1250355 | S18: 1.1778111 | T18: 1.2221904 | U18: 1.2596575 | V18: 1.2914684 | W18: 1.3181761 | X18: 1.3401611 | Y18: 1.3578041 | Z18: 1.3714858 | AA18: 1.3815867 | AB18: 1.3884772 | AC18: 1.3924918 | AD18: 1.3939571 | AE18: 1.3932 | AF18: 1.3905472 | AG18: 1.3863255 | AH18: 1.3808275 | AI18: 1.3742095 | AJ18: 1.3665936 | AK18: 1.3581018 | AL18: 1.3488562 | AM18: 1.3389791 | AN18: 1.3285924 | AO18: 1.3178182 | AP18: 1.3067788 | AQ18: 1.2955961 | AR18: 1.2843924 | AS18: 1.2732896 | AT18: 1.2623932 | AU18: 1.2517347 | AV18: 1.2413254 | AW18: 1.2311764 | AX18: 1.2212989 | AY18: 1.2117041 | AZ18: 1.2024032 | BA18: 1.1934074 | BB18: 1.1847279 | BC18: 1.1763758 | BD18: 1.1683624 | BE18: 1.1606989 | BF18: 1.1533944 | BG18: 1.146447 | BH18: 1.139851 | BI18: 1.1336008 | BJ18: 1.1276907 | BK18: 1.1221152 | BL18: 1.1168685 | BM18: 1.1119451 | BN18: 1.1073392 | BO18: 1.1030453 | BP18: 1.0990576 | BQ18: 1.0953707 | BR18: 1.079044 | BS18: 1.0708763 | BU18: 0.84 | BV18: 1.19 | BW18: 82.8507
A19: =+A14+7 -> 44579 | B19: =MONTH(A19) -> 1 | C19: =YEAR(A19) -> 2022 | D19: =C19*100+B19 -> 202201 | E19: =IF(B19<4,1,IF(B19<7,2,IF(B19<10,3,4))) -> 1 | F19: =C19*100+E19 -> 202201 | G19: 20220118 | H19: 0.25 | I19: 0.1959 | J19: 0.3981459 | K19: 0.4807325 | L19: 0.58498 | M19: 0.7009283 | N19: 0.8160644 | O19: 0.9219551 | P19: 1.0141382 | Q19: 1.092129 | R19: 1.157068 | S19: 1.2112449 | T19: 1.2564449 | U19: 1.2941611 | V19: 1.3258299 | W19: 1.3521082 | X19: 1.373445 | Y19: 1.3902898 | Z19: 1.4030918 | AA19: 1.4123002 | AB19: 1.4183468 | AC19: 1.4216022 | AD19: 1.422424 | AE19: 1.4211698 | AF19: 1.4181973 | AG19: 1.413864 | AH19: 1.4084854 | AI19: 1.4022082 | AJ19: 1.395137 | AK19: 1.3873763 | AL19: 1.3790308 | AM19: 1.370205 | AN19: 1.3610035 | AO19: 1.3515308 | AP19: 1.3418916 | AQ19: 1.3321904 | AR19: 1.3225318 | AS19: 1.3130203 | AT19: 1.303748 | AU19: 1.2947389 | AV19: 1.2859943 | AW19: 1.2775156 | AX19: 1.269304 | AY19: 1.2613609 | AZ19: 1.2536875 | BA19: 1.2462852 | BB19: 1.2391553 | BC19: 1.2322991 | BD19: 1.2257179 | BE19: 1.219413 | BF19: 1.2133848 | BG19: 1.2076298 | BH19: 1.2021429 | BI19: 1.1969195 | BJ19: 1.1919545 | BK19: 1.187243 | BL19: 1.1827803 | BM19: 1.1785613 | BN19: 1.1745812 | BO19: 1.1708352 | BP19: 1.1673182 | BQ19: 1.1640255 | BR19: 1.1486324 | BS19: 1.1396425 | BU19: 0.87 | BV19: 1.22 | BW19: 82.7193
A20: =+A15+7 -> 44580 | B20: =MONTH(A20) -> 1 | C20: =YEAR(A20) -> 2022 | D20: =C20*100+B20 -> 202201 | E20: =IF(B20<4,1,IF(B20<7,2,IF(B20<10,3,4))) -> 1 | F20: =C20*100+E20 -> 202201 | G20: 20220119 | H20: 0.25 | I20: 0.1964 | J20: 0.4290017 | K20: 0.5100013 | L20: 0.6165126 | M20: 0.737476 | N20: 0.8585316 | O20: 0.9694682 | P20: 1.0650571 | Q20: 1.1445178 | R20: 1.2093518 | S20: 1.2620145 | T20: 1.3050801 | U20: 1.3403781 | V20: 1.3700989 | W20: 1.3949778 | X20: 1.4153205 | Y20: 1.4314327 | Z20: 1.4436201 | AA20: 1.4521884 | AB20: 1.4574541 | AC20: 1.4597722 | AD20: 1.4595055 | AE20: 1.4570169 | AF20: 1.4526695 | AG20: 1.4468261 | AH20: 1.4398097 | AI20: 1.4317823 | AJ20: 1.4228664 | AK20: 1.4131838 | AL20: 1.402857 | AM20: 1.3920079 | AN20: 1.3807588 | AO20: 1.3692318 | AP20: 1.3575491 | AQ20: 1.3458328 | AR20: 1.3342051 | AS20: 1.3227882 | AT20: 1.3116874 | AU20: 1.3009266 | AV20: 1.2905047 | AW20: 1.2804207 | AX20: 1.2706735 | AY20: 1.2612622 | AZ20: 1.2521857 | BA20: 1.2434429 | BB20: 1.2350329 | BC20: 1.2269545 | BD20: 1.2192067 | BE20: 1.2117886 | BF20: 1.2046981 | BG20: 1.1979289 | BH20: 1.1914737 | BI20: 1.1853251 | BJ20: 1.1794757 | BK20: 1.1739181 | BL20: 1.1686448 | BM20: 1.1636486 | BN20: 1.1589219 | BO20: 1.1544575 | BP20: 1.1502479 | BQ20: 1.1462856 | BR20: 1.1273046 | BS20: 1.1154342 | BU20: 0.9 | BV20: 1.26 | BW20: 82.8369
A21: =+A16+7 -> 44581 | B21: =MONTH(A21) -> 1 | C21: =YEAR(A21) -> 2022 | D21: =C21*100+B21 -> 202201 | E21: =IF(B21<4,1,IF(B21<7,2,IF(B21<10,3,4))) -> 1 | F21: =C21*100+E21 -> 202201 | G21: 20220120 | H21: 0.25 | I21: 0.1966 | J21: 0.4338542 | K21: 0.5064212 | L21: 0.6106891 | M21: 0.7318173 | N21: 0.8532363 | O21: 0.9638598 | P21: 1.0589021 | Q21: 1.1379868 | R21: 1.2032494 | S21: 1.257273 | T21: 1.3021498 | U21: 1.3392934 | V21: 1.3700383 | W21: 1.3950419 | X21: 1.4147749 | Y21: 1.429708 | Z21: 1.440312 | AA21: 1.4470577 | AB21: 1.4504028 | AC21: 1.45076 | AD21: 1.4485323 | AE21: 1.4441229 | AF21: 1.4379348 | AG21: 1.4303711 | AH21: 1.4217948 | AI21: 1.4123736 | AJ21: 1.4022159 | AK21: 1.3914301 | AL21: 1.3801244 | AM21: 1.3684074 | AN21: 1.3563872 | AO21: 1.3441723 | AP21: 1.331871 | AQ21: 1.3195916 | AR21: 1.3074425 | AS21: 1.2955321 | AT21: 1.283952 | AU21: 1.2727201 | AV21: 1.2618339 | AW21: 1.2512912 | AX21: 1.2410893 | AY21: 1.231226 | AZ21: 1.2216987 | BA21: 1.2125051 | BB21: 1.2036428 | BC21: 1.1951092 | BD21: 1.186902 | BE21: 1.1790187 | BF21: 1.1714563 | BG21: 1.1642089 | BH21: 1.1572698 | BI21: 1.1506323 | BJ21: 1.1442896 | BK21: 1.1382352 | BL21: 1.1324623 | BM21: 1.1269643 | BN21: 1.1217344 | BO21: 1.1167659 | BP21: 1.1120522 | BQ21: 1.1075866 | BR21: 1.0856712 | BS21: 1.0712633 | BU21: 0.89 | BV21: 1.22 | BW21: 83.0444
A22: =+A17+7 -> 44582 | B22: =MONTH(A22) -> 1 | C22: =YEAR(A22) -> 2022 | D22: =C22*100+B22 -> 202201 | E22: =IF(B22<4,1,IF(B22<7,2,IF(B22<10,3,4))) -> 1 | F22: =C22*100+E22 -> 202201 | G22: 20220121 | H22: 0.25 | I22: 0.1967 | J22: 0.4239742 | K22: 0.4988124 | L22: 0.6043799 | M22: 0.7236346 | N22: 0.8402447 | O22: 0.9448683 | P22: 1.0337686 | Q22: 1.1072492 | R22: 1.1678137 | S22: 1.2182093 | T22: 1.2603784 | U22: 1.2956652 | V22: 1.3250783 | W22: 1.3491366 | X22: 1.3682205 | Y22: 1.3827104 | Z22: 1.3929866 | AA22: 1.3994293 | AB22: 1.4024272 | AC22: 1.4023971 | AD22: 1.3997618 | AE22: 1.3949443 | AF22: 1.3883675 | AG22: 1.3804544 | AH22: 1.3715801 | AI22: 1.3619092 | AJ22: 1.351548 | AK22: 1.340603 | AL22: 1.3291806 | AM22: 1.3173871 | AN22: 1.3053291 | AO22: 1.2931129 | AP22: 1.2808449 | AQ22: 1.2686315 | AR22: 1.2565791 | AS22: 1.2447942 | AT22: 1.2333656 | AU22: 1.2223047 | AV22: 1.2116015 | AW22: 1.2012461 | AX22: 1.1912285 | AY22: 1.1815388 | AZ22: 1.172167 | BA22: 1.1631032 | BB22: 1.1543373 | BC22: 1.1458594 | BD22: 1.1376596 | BE22: 1.1297279 | BF22: 1.1220553 | BG22: 1.114637 | BH22: 1.1074694 | BI22: 1.1005488 | BJ22: 1.0938716 | BK22: 1.0874343 | BL22: 1.0812331 | BM22: 1.0752645 | BN22: 1.0695248 | BO22: 1.0640104 | BP22: 1.0587176 | BQ22: 1.053643 | BR22: 1.02764 | BS22: 1.0089915 | BU22: 0.87 | BV22: 1.17 | BW22: 82.4712
A23: =+A18+7 -> 44585 | B23: =MONTH(A23) -> 1 | C23: =YEAR(A23) -> 2022 | D23: =C23*100+B23 -> 202201 | E23: =IF(B23<4,1,IF(B23<7,2,IF(B23<10,3,4))) -> 1 | F23: =C23*100+E23 -> 202201 | G23: 20220124 | H23: 0.25 | I23: 0.1955 | J23: 0.4273185 | K23: 0.5138679 | L23: 0.6243277 | M23: 0.7429747 | N23: 0.8547213 | O23: 0.952448 | P23: 1.0344217 | Q23: 1.1020548 | R23: 1.157899 | S23: 1.2048633 | T23: 1.2446842 | U23: 1.2787125 | V23: 1.3078157 | W23: 1.3323761 | X23: 1.3526896 | Y23: 1.3690517 | Z23: 1.3817581 | AA23: 1.3911046 | AB23: 1.3973802 | AC23: 1.4008508 | AD23: 1.4017776 | AE23: 1.4004215 | AF23: 1.3970436 | AG23: 1.3919049 | AH23: 1.3852462 | AI23: 1.3772272 | AJ23: 1.3679871 | AK23: 1.3576654 | AL23: 1.3464013 | AM23: 1.3343342 | AN23: 1.3216035 | AO23: 1.3083486 | AP23: 1.2947086 | AQ23: 1.2808231 | AR23: 1.2668313 | AS23: 1.2528725 | AT23: 1.2390684 | AU23: 1.2254615 | AV23: 1.2120728 | AW23: 1.1989232 | AX23: 1.1860336 | AY23: 1.1734249 | AZ23: 1.1611182 | BA23: 1.1491342 | BB23: 1.137494 | BC23: 1.1262184 | BD23: 1.1153283 | BE23: 1.1048448 | BF23: 1.0947851 | BG23: 1.0851476 | BH23: 1.0759242 | BI23: 1.0671066 | BJ23: 1.0586868 | BK23: 1.0506567 | BL23: 1.0430082 | BM23: 1.035733 | BN23: 1.0288231 | BO23: 1.0222704 | BP23: 1.0160668 | BQ23: 1.010204 | BR23: 0.9816964 | BS23: 0.9631982 | BU23: 0.87 | BV23: 1.13 | BW23: 82.1482
A24: =+A19+7 -> 44586 | B24: =MONTH(A24) -> 1 | C24: =YEAR(A24) -> 2022 | D24: =C24*100+B24 -> 202201 | E24: =IF(B24<4,1,IF(B24<7,2,IF(B24<10,3,4))) -> 1 | F24: =C24*100+E24 -> 202201 | G24: 20220125 | H24: 0.25 | I24: 0.1954 | J24: 0.4319917 | K24: 0.5230304 | L24: 0.6368681 | M24: 0.7589784 | N24: 0.8741631 | O24: 0.9753824 | P24: 1.060564 | Q24: 1.1315509 | R24: 1.1910872 | S24: 1.2418626 | T24: 1.2853995 | U24: 1.3227382 | V24: 1.3543684 | W24: 1.3806312 | X24: 1.4018726 | Y24: 1.4184388 | Z24: 1.4306758 | AA24: 1.4389297 | AB24: 1.4435575 | AC24: 1.4449547 | AD24: 1.4435249 | AE24: 1.4396717 | AF24: 1.4337986 | AG24: 1.4263093 | AH24: 1.4175616 | AI24: 1.4077302 | AJ24: 1.3969442 | AK24: 1.3853324 | AL24: 1.3730238 | AM24: 1.3601473 | AN24: 1.3468321 | AO24: 1.3332069 | AP24: 1.3194007 | AQ24: 1.3055426 | AR24: 1.2917615 | AS24: 1.2781863 | AT24: 1.2649308 | AU24: 1.2520269 | AV24: 1.2394791 | AW24: 1.2272919 | AX24: 1.2154697 | AY24: 1.2040171 | AZ24: 1.1929384 | BA24: 1.1822382 | BB24: 1.1719209 | BC24: 1.161991 | BD24: 1.152453 | BE24: 1.1433113 | BF24: 1.1345684 | BG24: 1.1262176 | BH24: 1.1182489 | BI24: 1.1106527 | BJ24: 1.1034193 | BK24: 1.0965388 | BL24: 1.0900016 | BM24: 1.0837978 | BN24: 1.0779178 | BO24: 1.0723517 | BP24: 1.0670899 | BQ24: 1.0621225 | BR24: 1.0379676 | BS24: 1.0220258 | BU24: 0.9 | BV24: 1.17 | BW24: 82.3875
... A81: =+A76+7 -> 44665 | B81: =MONTH(A81) -> 4 | C81: =YEAR(A81) -> 2022 | D81: =C81*100+B81 -> 202204 | E81: =IF(B81<4,1,IF(B81<7,2,IF(B81<10,3,4))) -> 2 | F81: =C81*100+E81 -> 202202 | G81: 20220414 | H81: 0.75 | I81: 0.6908 | J81: 0.9167665 | K81: 1.1146715 | L81: 1.2905475 | M81: 1.4552974 | N81: 1.6152791 | O81: 1.7693233 | P81: 1.9156515 | Q81: 2.0539289 | R81: 2.1830728 | S81: 2.3008167 | T81: 2.4051419 | U81: 2.4931749 | V81: 2.5619705 | W81: 2.6122293 | X81: 2.6456084 | Y81: 2.6637649 | Z81: 2.6683558 | AA81: 2.6610382 | AB81: 2.6435053 | AC81: 2.6176346 | AD81: 2.5853629 | AE81: 2.5486267 | AF81: 2.5093628 | AG81: 2.4695079 | AH81: 2.4307371 | AI81: 2.3934507 | AJ81: 2.3576612 | AK81: 2.3233809 | AL81: 2.2906223 | AM81: 2.2593976 | AN81: 2.2297193 | AO81: 2.2015998 | AP81: 2.1750513 | AQ81: 2.1500863 | AR81: 2.1267171 | AS81: 2.1049562 | AT81: 2.0847957 | AU81: 2.0661392 | AV81: 2.0488658 | AW81: 2.0328545 | AX81: 2.0179845 | AY81: 2.0041347 | AZ81: 1.9911843 | BA81: 1.9790123 | BB81: 1.9674979 | BC81: 1.9565199 | BD81: 1.9459576 | BE81: 1.93569 | BF81: 1.925615 | BG81: 1.9157135 | BH81: 1.9059893 | BI81: 1.8964463 | BJ81: 1.8870884 | BK81: 1.8779195 | BL81: 1.8689433 | BM81: 1.8601637 | BN81: 1.8515846 | BO81: 1.8432098 | BP81: 1.8350432 | BQ81: 1.8270886 | BR81: 1.7841489 | BS81: 1.750537 | BU81: 1.56 | BV81: 1.89 | BW81: 81.9688
A82: =+A77+7 -> 44666 | B82: =MONTH(A82) -> 4 | C82: =YEAR(A82) -> 2022 | D82: =C82*100+B82 -> 202204 | E82: =IF(B82<4,1,IF(B82<7,2,IF(B82<10,3,4))) -> 2 | F82: =C82*100+E82 -> 202202 | G82: 20220415 | H82: 0.75 | I82: #N/A | J82: #N/A | K82: #N/A | L82: #N/A | M82: #N/A | N82: #N/A | O82: #N/A | P82: #N/A | Q82: #N/A | R82: #N/A | S82: #N/A | T82: #N/A | U82: #N/A | V82: #N/A | W82: #N/A | X82: #N/A | Y82: #N/A | Z82: #N/A | AA82: #N/A | AB82: #N/A | AC82: #N/A | AD82: #N/A | AE82: #N/A | AF82: #N/A | AG82: #N/A | AH82: #N/A | AI82: #N/A | AJ82: #N/A | AK82: #N/A | AL82: #N/A | AM82: #N/A | AN82: #N/A | AO82: #N/A | AP82: #N/A | AQ82: #N/A | AR82: #N/A | AS82: #N/A | AT82: #N/A | AU82: #N/A | AV82: #N/A | AW82: #N/A | AX82: #N/A | AY82: #N/A | AZ82: #N/A | BA82: #N/A | BB82: #N/A | BC82: #N/A | BD82: #N/A | BE82: #N/A | BF82: #N/A | BG82: #N/A | BH82: #N/A | BI82: #N/A | BJ82: #N/A | BK82: #N/A | BL82: #N/A | BM82: #N/A | BN82: #N/A | BO82: #N/A | BP82: #N/A | BQ82: #N/A | BR82: #N/A | BS82: #N/A | BU82: #N/A | BV82: 1.9 | BW82: #N/A
A83: =+A78+7 -> 44669 | B83: =MONTH(A83) -> 4 | C83: =YEAR(A83) -> 2022 | D83: =C83*100+B83 -> 202204 | E83: =IF(B83<4,1,IF(B83<7,2,IF(B83<10,3,4))) -> 2 | F83: =C83*100+E83 -> 202202 | G83: 20220418 | H83: 0.75 | I83: #N/A | J83: #N/A | K83: #N/A | L83: #N/A | M83: #N/A | N83: #N/A | O83: #N/A | P83: #N/A | Q83: #N/A | R83: #N/A | S83: #N/A | T83: #N/A | U83: #N/A | V83: #N/A | W83: #N/A | X83: #N/A | Y83: #N/A | Z83: #N/A | AA83: #N/A | AB83: #N/A | AC83: #N/A | AD83: #N/A | AE83: #N/A | AF83: #N/A | AG83: #N/A | AH83: #N/A | AI83: #N/A | AJ83: #N/A | AK83: #N/A | AL83: #N/A | AM83: #N/A | AN83: #N/A | AO83: #N/A | AP83: #N/A | AQ83: #N/A | AR83: #N/A | AS83: #N/A | AT83: #N/A | AU83: #N/A | AV83: #N/A | AW83: #N/A | AX83: #N/A | AY83: #N/A | AZ83: #N/A | BA83: #N/A | BB83: #N/A | BC83: #N/A | BD83: #N/A | BE83: #N/A | BF83: #N/A | BG83: #N/A | BH83: #N/A | BI83: #N/A | BJ83: #N/A | BK83: #N/A | BL83: #N/A | BM83: #N/A | BN83: #N/A | BO83: #N/A | BP83: #N/A | BQ83: #N/A | BR83: #N/A | BS83: #N/A | BU83: #N/A | BV83: 1.88 | BW83: #N/A
A84: =+A79+7 -> 44670 | B84: =MONTH(A84) -> 4 | C84: =YEAR(A84) -> 2022 | D84: =C84*100+B84 -> 202204 | E84: =IF(B84<4,1,IF(B84<7,2,IF(B84<10,3,4))) -> 2 | F84: =C84*100+E84 -> 202202 | G84: 20220419 | H84: 0.75 | I84: 0.6902 | J84: 0.9775071 | K84: 1.1316388 | L84: 1.3046769 | M84: 1.4810365 | N84: 1.651714 | O84: 1.8129344 | P84: 1.9636415 | Q84: 2.1043235 | R84: 2.2342542 | S84: 2.3518714 | T84: 2.4555707 | U84: 2.5429295 | V84: 2.6117962 | W84: 2.6630566 | X84: 2.6983709 | Y84: 2.7193992 | Z84: 2.7278017 | AA84: 2.7252386 | AB84: 2.7133529 | AC84: 2.6937156 | AD84: 2.6678788 | AE84: 2.6373946 | AF84: 2.603815 | AG84: 2.5686922 | AH84: 2.5333625 | AI84: 2.4982096 | AJ84: 2.4633545 | AK84: 2.428918 | AL84: 2.3950212 | AM84: 2.3617849 | AN84: 2.3293301 | AO84: 2.2977777 | AP84: 2.2672487 | AQ84: 2.2378639 | AR84: 2.2097444 | AS84: 2.1830111 | AT84: 2.1577641 | AU84: 2.1339808 | AV84: 2.1115929 | AW84: 2.090532 | AX84: 2.0707299 | AY84: 2.0521183 | AZ84: 2.0346289 | BA84: 2.0181934 | BB84: 2.0027435 | BC84: 1.9882109 | BD84: 1.9745272 | BE84: 1.9616243 | BF84: 1.9494397 | BG84: 1.9379402 | BH84: 1.9271012 | BI84: 1.9168982 | BJ84: 1.9073067 | BK84: 1.8983023 | BL84: 1.8898603 | BM84: 1.8819565 | BN84: 1.8745661 | BO84: 1.8676648 | BP84: 1.861228 | BQ84: 1.8552313 | BR84: 1.8275228 | BS84: 1.811927 | BU84: 1.59 | BV84: 1.99 | BW84: 81.7085
A85: =+A80+7 -> 44671 | B85: =MONTH(A85) -> 4 | C85: =YEAR(A85) -> 2022 | D85: =C85*100+B85 -> 202204 | E85: =IF(B85<4,1,IF(B85<7,2,IF(B85<10,3,4))) -> 2 | F85: =C85*100+E85 -> 202202 | G85: 20220420 | H85: 0.75 | I85: 0.6904 | J85: 0.9845496 | K85: 1.1343656 | L85: 1.3075093 | M85: 1.4849827 | N85: 1.6561272 | O85: 1.8171075 | P85: 1.9671053 | Q85: 2.1068745 | R85: 2.23606 | S85: 2.3533256 | T85: 2.456814 | U85: 2.5440207 | V85: 2.6123756 | W85: 2.6626557 | X85: 2.6965249 | Y85: 2.7156474 | Z85: 2.721687 | AA85: 2.7163078 | AB85: 2.701181 | AC85: 2.6780074 | AD85: 2.6484958 | AE85: 2.614355 | AF85: 2.5772939 | AG85: 2.5390211 | AH85: 2.5010468 | AI85: 2.4638104 | AJ85: 2.4273925 | AK85: 2.3918735 | AL85: 2.3573338 | AM85: 2.3238538 | AN85: 2.2915138 | AO85: 2.2603943 | AP85: 2.2305755 | AQ85: 2.202138 | AR85: 2.175162 | AS85: 2.1497279 | AT85: 2.1258946 | AU85: 2.1036052 | AV85: 2.0827639 | AW85: 2.0632749 | AX85: 2.0450425 | AY85: 2.0279708 | AZ85: 2.0119641 | BA85: 1.9969266 | BB85: 1.9827625 | BC85: 1.969376 | BD85: 1.9566713 | BE85: 1.9445526 | BF85: 1.9329367 | BG85: 1.9217947 | BH85: 1.9111132 | BI85: 1.9008786 | BJ85: 1.8910774 | BK85: 1.881696 | BL85: 1.8727209 | BM85: 1.8641385 | BN85: 1.8559353 | BO85: 1.8480978 | BP85: 1.8406124 | BQ85: 1.8334655 | BR85: 1.7972761 | BS85: 1.7719278 | BU85: 1.57 | BV85: 1.93 | BW85: 81.759
A86: =+A81+7 -> 44672 | B86: =MONTH(A86) -> 4 | C86: =YEAR(A86) -> 2022 | D86: =C86*100+B86 -> 202204 | E86: =IF(B86<4,1,IF(B86<7,2,IF(B86<10,3,4))) -> 2 | F86: =C86*100+E86 -> 202202 | G86: 20220421 | H86: 0.75 | I86: 0.6904 | J86: 1.0799067 | K86: 1.2566874 | L86: 1.4660016 | M86: 1.6751555 | N86: 1.8665144 | O86: 2.0366881 | P86: 2.1876125 | Q86: 2.3234747 | R86: 2.4469362 | S86: 2.5580726 | T86: 2.656084 | U86: 2.7386436 | V86: 2.8029236 | W86: 2.8494464 | X86: 2.8796323 | Y86: 2.8949019 | Z86: 2.8966757 | AA86: 2.886374 | AB86: 2.8654863 | AC86: 2.8358551 | AD86: 2.7994355 | AE86: 2.7581827 | AF86: 2.714052 | AG86: 2.6689987 | AH86: 2.62472 | AI86: 2.5816549 | AJ86: 2.5398601 | AK86: 2.4993917 | AL86: 2.4603062 | AM86: 2.4226599 | AN86: 2.3865092 | AO86: 2.3519104 | AP86: 2.3189198 | AQ86: 2.2875938 | AR86: 2.2579887 | AS86: 2.2301609 | AT86: 2.2041438 | AU86: 2.1798582 | AV86: 2.1571911 | AW86: 2.1360294 | AX86: 2.1162599 | AY86: 2.0977694 | AZ86: 2.0804448 | BA86: 2.064173 | BB86: 2.0488408 | BC86: 2.0343351 | BD86: 2.0205427 | BE86: 2.0073504 | BF86: 1.9946607 | BG86: 1.9824444 | BH86: 1.9706912 | BI86: 1.9593908 | BJ86: 1.9485329 | BK86: 1.9381073 | BL86: 1.9281036 | BM86: 1.9185117 | BN86: 1.9093212 | BO86: 1.9005218 | BP86: 1.8921033 | BQ86: 1.8840554 | BR86: 1.8431446 | BS86: 1.8140145 | BU86: 1.76 | BV86: 2.03 | BW86: 81.8366
A87: =+A82+7 -> 44673 | B87: =MONTH(A87) -> 4 | C87: =YEAR(A87) -> 2022 | D87: =C87*100+B87 -> 202204 | E87: =IF(B87<4,1,IF(B87<7,2,IF(B87<10,3,4))) -> 2 | F87: =C87*100+E87 -> 202202 | G87: 20220422 | H87: 0.75 | I87: 0.6905 | J87: 1.0291901 | K87: 1.2060208 | L87: 1.4117846 | M87: 1.6158124 | N87: 1.8019129 | O87: 1.966447 | P87: 2.1115901 | Q87: 2.2410031 | R87: 2.3575211 | S87: 2.461625 | T87: 2.5528131 | U87: 2.6294464 | V87: 2.6896667 | W87: 2.7340648 | X87: 2.7640102 | Y87: 2.7808722 | Z87: 2.7860201 | AA87: 2.7808235 | AB87: 2.7666674 | AC87: 2.7450093 | AD87: 2.7173279 | AE87: 2.6851019 | AF87: 2.6498098 | AG87: 2.6129303 | AH87: 2.575739 | AI87: 2.5386156 | AJ87: 2.5016924 | AK87: 2.4651017 | AL87: 2.428976 | AM87: 2.3934475 | AN87: 2.3586487 | AO87: 2.3247119 | AP87: 2.2917694 | AQ87: 2.2599537 | AR87: 2.229397 | AS87: 2.2002318 | AT87: 2.1725601 | AU87: 2.1463503 | AV87: 2.1215338 | AW87: 2.0980421 | AX87: 2.0758066 | AY87: 2.0547589 | AZ87: 2.0348304 | BA87: 2.0159524 | BB87: 1.9980566 | BC87: 1.9810744 | BD87: 1.9649371 | BE87: 1.9495763 | BF87: 1.9349306 | BG87: 1.92097 | BH87: 1.9076732 | BI87: 1.8950189 | BJ87: 1.8829857 | BK87: 1.8715525 | BL87: 1.8606979 | BM87: 1.8504005 | BN87: 1.8406392 | BO87: 1.8313926 | BP87: 1.8226394 | BQ87: 1.8143584 | BR87: 1.7737373 | BS87: 1.7468299 | BU87: 1.72 | BV87: 1.97 | BW87: 81.0328
A88: =+A83+7 -> 44676 | B88: =MONTH(A88) -> 4 | C88: =YEAR(A88) -> 2022 | D88: =C88*100+B88 -> 202204 | E88: =IF(B88<4,1,IF(B88<7,2,IF(B88<10,3,4))) -> 2 | F88: =C88*100+E88 -> 202202 | G88: 20220425 | H88: 0.75 | I88: 0.6899 | J88: 1.0121962 | K88: 1.1924333 | L88: 1.3919608 | M88: 1.5866905 | N88: 1.7602931 | O88: 1.9096153 | P88: 2.0371826 | Q88: 2.1480398 | R88: 2.2459927 | S88: 2.3331871 | T88: 2.4096384 | U88: 2.4741088 | V88: 2.5245104 | W88: 2.5612145 | X88: 2.5853082 | Y88: 2.5978783 | Z88: 2.6000119 | AA88: 2.5927958 | AB88: 2.5773725 | AC88: 2.5551171 | AD88: 2.527466 | AE88: 2.4958553 | AF88: 2.4617216 | AG88: 2.426501 | AH88: 2.3914259 | AI88: 2.3568272 | AJ88: 2.3227876 | AK88: 2.2893895 | AL88: 2.2567155 | AM88: 2.2248479 | AN88: 2.1938695 | AO88: 2.1638626 | AP88: 2.1349097 | AQ88: 2.1070935 | AR88: 2.0804963 | AS88: 2.0552007 | AT88: 2.0312664 | AU88: 2.0086525 | AV88: 1.9872903 | AW88: 1.9671111 | AX88: 1.9480463 | AY88: 1.9300271 | AZ88: 1.9129849 | BA88: 1.8968511 | BB88: 1.8815568 | BC88: 1.8670335 | BD88: 1.8532125 | BE88: 1.8400251 | BF88: 1.8274096 | BG88: 1.8153423 | BH88: 1.8038118 | BI88: 1.7928072 | BJ88: 1.7823173 | BK88: 1.7723309 | BL88: 1.7628368 | BM88: 1.753824 | BN88: 1.7452813 | BO88: 1.7371975 | BP88: 1.7295616 | BQ88: 1.7223623 | BR88: 1.6876872 | BS88: 1.6657694 | BU88: 1.57 | BV88: 1.85 | BW88: 80.6489
A89: =+A84+7 -> 44677 | B89: =MONTH(A89) -> 4 | C89: =YEAR(A89) -> 2022 | D89: =C89*100+B89 -> 202204 | E89: =IF(B89<4,1,IF(B89<7,2,IF(B89<10,3,4))) -> 2 | F89: =C89*100+E89 -> 202202 | G89: 20220426 | H89: 0.75 | I89: 0.6903 | J89: 1.0100269 | K89: 1.1912066 | L89: 1.3896115 | M89: 1.5835589 | N89: 1.7570452 | O89: 1.9059299 | P89: 2.0313715 | Q89: 2.1381799 | R89: 2.2305612 | S89: 2.3113792 | T89: 2.3815053 | U89: 2.4399736 | V89: 2.4850688 | W89: 2.5172121 | X89: 2.5374217 | Y89: 2.5467157 | Z89: 2.5461122 | AA89: 2.5366294 | AB89: 2.5193443 | AC89: 2.4955812 | AD89: 2.4667294 | AE89: 2.434178 | AF89: 2.3993165 | AG89: 2.3635339 | AH89: 2.328022 | AI89: 2.2931005 | AJ89: 2.2588483 | AK89: 2.2253446 | AL89: 2.1926683 | AM89: 2.1608984 | AN89: 2.130114 | AO89: 2.1003942 | AP89: 2.0718178 | AQ89: 2.044464 | AR89: 2.0184119 | AS89: 1.9937403 | AT89: 1.9705089 | AU89: 1.9486725 | AV89: 1.9281509 | AW89: 1.9088637 | AX89: 1.8907306 | AY89: 1.8736713 | AZ89: 1.8576055 | BA89: 1.8424528 | BB89: 1.828133 | BC89: 1.8145658 | BD89: 1.8016708 | BE89: 1.7893677 | BF89: 1.7775853 | BG89: 1.7662969 | BH89: 1.7554894 | BI89: 1.7451494 | BJ89: 1.7352637 | BK89: 1.7258192 | BL89: 1.7168027 | BM89: 1.7082009 | BN89: 1.7000007 | BO89: 1.6921888 | BP89: 1.684752 | BQ89: 1.6776771 | BR89: 1.6423184 | BS89: 1.6180549 | BU89: 1.5 | BV89: 1.82 | BW89: 80.2724
A90: =+A85+7 -> 44678 | B90: =MONTH(A90) -> 4 | C90: =YEAR(A90) -> 2022 | D90: =C90*100+B90 -> 202204 | E90: =IF(B90<4,1,IF(B90<7,2,IF(B90<10,3,4))) -> 2 | F90: =C90*100+E90 -> 202202 | G90: 20220427 | H90: 0.75 | I90: 0.6902 | J90: 1.0096871 | K90: 1.1844644 | L90: 1.3757817 | M90: 1.5639892 | N90: 1.7330932 | O90: 1.879242 | P90: 2.0033579 | Q90: 2.1099116 | R90: 2.2031471 | S90: 2.2856509 | T90: 2.3578567 | U90: 2.4184971 | V90: 2.4652861 | W90: 2.4985559 | X90: 2.5193828 | Y90: 2.5288431 | Z90: 2.5280131 | AA90: 2.5179692 | AB90: 2.4998497 | AC90: 2.475054 | AD90: 2.4450501 | AE90: 2.4113058 | AF90: 2.3752892 | AG90: 2.3384683 | AH90: 2.3021387 | AI90: 2.2666699 | AJ90: 2.2321204 | AK90: 2.1985485 | AL90: 2.1660127 | AM90: 2.1345712 | AN90: 2.1042825 | AO90: 2.075205 | AP90: 2.0473969 | AQ90: 2.0209167 | AR90: 1.9958227 | AS90: 1.9721733 | AT90: 1.950007 | AU90: 1.929266 | AV90: 1.9098628 | AW90: 1.89171 | AX90: 1.8747205 | AY90: 1.8588067 | AZ90: 1.8438814 | BA90: 1.8298573 | BB90: 1.8166469 | BC90: 1.8041629 | BD90: 1.792318 | BE90: 1.7810248 | BF90: 1.7702073 | BG90: 1.7598398 | BH90: 1.7499102 | BI90: 1.7404066 | BJ90: 1.7313169 | BK90: 1.7226292 | BL90: 1.7143315 | BM90: 1.7064118 | BN90: 1.6988581 | BO90: 1.6916585 | BP90: 1.684801 | BQ90: 1.6782735 | BR90: 1.6455956 | BS90: 1.6231554 | BU90: 1.49 | BV90: 1.81 | BW90: 80.1227
A91: =+A86+7 -> 44679 | B91: =MONTH(A91) -> 4 | C91: =YEAR(A91) -> 2022 | D91: =C91*100+B91 -> 202204 | E91: =IF(B91<4,1,IF(B91<7,2,IF(B91<10,3,4))) -> 2 | F91: =C91*100+E91 -> 202202 | G91: 20220428 | H91: 0.75 | I91: 0.6896 | J91: 1.0152349 | K91: 1.2104818 | L91: 1.413487 | M91: 1.6075696 | N91: 1.7792106 | O91: 1.926193 | P91: 2.0500399 | Q91: 2.155115 | R91: 2.2459651 | S91: 2.3249745 | T91: 2.3931703 | U91: 2.4497252 | V91: 2.4931881 | W91: 2.5240014 | X91: 2.5431217 | Y91: 2.5515053 | Z91: 2.5501088 | AA91: 2.5398884 | AB91: 2.5218637 | AC91: 2.4973767 | AD91: 2.4678723 | AE91: 2.4347956 | AF91: 2.3995917 | AG91: 2.3637057 | AH91: 2.3283945 | AI91: 2.2939974 | AJ91: 2.2605747 | AK91: 2.2281867 | AL91: 2.1968936 | AM91: 2.1667555 | AN91: 2.1378327 | AO91: 2.1101853 | AP91: 2.0838737 | AQ91: 2.0589579 | AR91: 2.0354983 | AS91: 2.013555 | AT91: 1.993164 | AU91: 1.9742551 | AV91: 1.9567286 | AW91: 1.9404845 | AX91: 1.9254233 | AY91: 1.9114452 | AZ91: 1.8984504 | BA91: 1.8863392 | BB91: 1.8750119 | BC91: 1.8643687 | BD91: 1.8543099 | BE91: 1.8447357 | BF91: 1.8355598 | BG91: 1.8267549 | BH91: 1.8183102 | BI91: 1.8102147 | BJ91: 1.8024576 | BK91: 1.7950277 | BL91: 1.7879144 | BM91: 1.7811065 | BN91: 1.7745933 | BO91: 1.7683638 | BP91: 1.762407 | BQ91: 1.7567121 | BR91: 1.727765 | BS91: 1.7075245 | BU91: 1.55 | BV91: 1.87 | BW91: 79.8409
A92: =+A87+7 -> 44680 | B92: =MONTH(A92) -> 4 | C92: =YEAR(A92) -> 2022 | D92: =C92*100+B92 -> 202204 | E92: =IF(B92<4,1,IF(B92<7,2,IF(B92<10,3,4))) -> 2 | F92: =C92*100+E92 -> 202202 | G92: 20220429 | H92: 0.75 | I92: 0.6907 | J92: 1.0331931 | K92: 1.2361322 | L92: 1.4466988 | M92: 1.6472819 | N92: 1.8235784 | O92: 1.9742979 | P92: 2.1018594 | Q92: 2.2096186 | R92: 2.3023909 | S92: 2.3831586 | T92: 2.4530633 | U92: 2.5114679 | V92: 2.556008 | W92: 2.5868861 | X92: 2.6053255 | Y92: 2.61255 | Z92: 2.6097836 | AA92: 2.59825 | AB92: 2.5791978 | AC92: 2.5539905 | AD92: 2.5240243 | AE92: 2.4906958 | AF92: 2.4554014 | AG92: 2.4195378 | AH92: 2.3842971 | AI92: 2.3499708 | AJ92: 2.3166016 | AK92: 2.2842322 | AL92: 2.2529053 | AM92: 2.2226636 | AN92: 2.1935499 | AO92: 2.1656068 | AP92: 2.1388772 | AQ92: 2.1134036 | AR92: 2.0892289 | AS92: 2.0663957 | AT92: 2.0449289 | AU92: 2.024774 | AV92: 2.0058548 | AW92: 1.9880951 | AX92: 1.9714186 | AY92: 1.9557491 | AZ92: 1.9410104 | BA92: 1.9271263 | BB92: 1.9140204 | BC92: 1.9016166 | BD92: 1.8898386 | BE92: 1.8786102 | BF92: 1.867865 | BG92: 1.8575797 | BH92: 1.8477428 | BI92: 1.8383431 | BJ92: 1.8293693 | BK92: 1.8208098 | BL92: 1.8126535 | BM92: 1.804889 | BN92: 1.7975048 | BO92: 1.7904896 | BP92: 1.7838321 | BQ92: 1.777521 | BR92: 1.7464885 | BS92: 1.7262609 | BU92: 1.6 | BV92: 1.91 | BW92: 80.3655
A93: =+A88+7 -> 44683 | B93: =MONTH(A93) -> 5 | C93: =YEAR(A93) -> 2022 | D93: =C93*100+B93 -> 202205 | E93: =IF(B93<4,1,IF(B93<7,2,IF(B93<10,3,4))) -> 2 | F93: =C93*100+E93 -> 202202 | G93: 20220502 | H93: 0.75 | I93: #N/A | J93: #N/A | K93: #N/A | L93: #N/A | M93: #N/A | N93: #N/A | O93: #N/A | P93: #N/A | Q93: #N/A | R93: #N/A | S93: #N/A | T93: #N/A | U93: #N/A | V93: #N/A | W93: #N/A | X93: #N/A | Y93: #N/A | Z93: #N/A | AA93: #N/A | AB93: #N/A | AC93: #N/A | AD93: #N/A | AE93: #N/A | AF93: #N/A | AG93: #N/A | AH93: #N/A | AI93: #N/A | AJ93: #N/A | AK93: #N/A | AL93: #N/A | AM93: #N/A | AN93: #N/A | AO93: #N/A | AP93: #N/A | AQ93: #N/A | AR93: #N/A | AS93: #N/A | AT93: #N/A | AU93: #N/A | AV93: #N/A | AW93: #N/A | AX93: #N/A | AY93: #N/A | AZ93: #N/A | BA93: #N/A | BB93: #N/A | BC93: #N/A | BD93: #N/A | BE93: #N/A | BF93: #N/A | BG93: #N/A | BH93: #N/A | BI93: #N/A | BJ93: #N/A | BK93: #N/A | BL93: #N/A | BM93: #N/A | BN93: #N/A | BO93: #N/A | BP93: #N/A | BQ93: #N/A | BR93: #N/A | BS93: #N/A | BU93: 1.58 | BV93: 1.9 | BW93: #N/A
A94: =+A89+7 -> 44684 | B94: =MONTH(A94) -> 5 | C94: =YEAR(A94) -> 2022 | D94: =C94*100+B94 -> 202205 | E94: =IF(B94<4,1,IF(B94<7,2,IF(B94<10,3,4))) -> 2 | F94: =C94*100+E94 -> 202202 | G94: 20220503 | H94: 0.75 | I94: 0.6906 | J94: 1.0550917 | K94: 1.2727673 | L94: 1.492292 | M94: 1.7002609 | N94: 1.8813465 | O94: 2.0347202 | P94: 2.1633004 | Q94: 2.2716196 | R94: 2.3642204 | S94: 2.4442308 | T94: 2.5126146 | U94: 2.5691439 | V94: 2.6126706 | W94: 2.64362 | X94: 2.6628973 | Y94: 2.6714076 | Z94: 2.670056 | AA94: 2.6597477 | AB94: 2.6414628 | AC94: 2.6165285 | AD94: 2.5863731 | AE94: 2.5524245 | AF94: 2.5161108 | AG94: 2.4788602 | AH94: 2.4418994 | AI94: 2.4055664 | AJ94: 2.3699542 | AK94: 2.3351555 | AL94: 2.3012632 | AM94: 2.2683703 | AN94: 2.2365694 | AO94: 2.2059536 | AP94: 2.1766156 | AQ94: 2.1486482 | AR94: 2.1221445 | AS94: 2.0971971 | AT94: 2.0738787 | AU94: 2.0521417 | AV94: 2.0318937 | AW94: 2.0130426 | AX94: 1.9954962 | AY94: 1.9791621 | AZ94: 1.9639481 | BA94: 1.9497621 | BB94: 1.9365117 | BC94: 1.9241047 | BD94: 1.9124488 | BE94: 1.9014519 | BF94: 1.8910306 | BG94: 1.881149 | BH94: 1.8717874 | BI94: 1.8629262 | BJ94: 1.8545454 | BK94: 1.8466255 | BL94: 1.8391466 | BM94: 1.8320889 | BN94: 1.8254328 | BO94: 1.8191585 | BP94: 1.8132462 | BQ94: 1.8076762 | BR94: 1.7807422 | BS94: 1.7636313 | BU94: 1.65 | BV94: 1.95 | BW94: 80.1822
A95: =+A90+7 -> 44685 | B95: =MONTH(A95) -> 5 | C95: =YEAR(A95) -> 2022 | D95: =C95*100+B95 -> 202205 | E95: =IF(B95<4,1,IF(B95<7,2,IF(B95<10,3,4))) -> 2 | F95: =C95*100+E95 -> 202202 | G95: 20220504 | H95: 0.75 | I95: 0.691 | J95: 1.0461372 | K95: 1.2635624 | L95: 1.48565 | M95: 1.7013775 | N95: 1.8926485 | O95: 2.0551845 | P95: 2.1905345 | Q95: 2.3031934 | R95: 2.3986276 | S95: 2.4802206 | T95: 2.5498267 | U95: 2.6071067 | V95: 2.6509575 | W95: 2.68185 | X95: 2.7006909 | Y95: 2.7083868 | Z95: 2.7058445 | AA95: 2.6939706 | AB95: 2.6737424 | AC95: 2.6465386 | AD95: 2.6138785 | AE95: 2.5772817 | AF95: 2.538268 | AG95: 2.4983569 | AH95: 2.4589106 | AI95: 2.4203525 | AJ95: 2.3827603 | AK95: 2.3462106 | AL95: 2.3107804 | AM95: 2.2765467 | AN95: 2.2435861 | AO95: 2.2119757 | AP95: 2.1817923 | AQ95: 2.1531127 | AR95: 2.1260139 | AS95: 2.1005727 | AT95: 2.0768443 | AU95: 2.054767 | AV95: 2.03424 | AW95: 2.0151623 | AX95: 1.9974332 | AY95: 1.9809516 | AZ95: 1.9656168 | BA95: 1.9513279 | BB95: 1.937984 | BC95: 1.9254841 | BD95: 1.9137275 | BE95: 1.9026132 | BF95: 1.8920515 | BG95: 1.8820076 | BH95: 1.872463 | BI95: 1.8633994 | BJ95: 1.8547984 | BK95: 1.8466417 | BL95: 1.838911 | BM95: 1.831588 | BN95: 1.8246542 | BO95: 1.8180913 | BP95: 1.811881 | BQ95: 1.806005 | BR95: 1.7771 | BS95: 1.7577858 | BU95: 1.64 | BV95: 1.97 | BW95: 80.0705
A96: =+A91+7 -> 44686 | B96: =MONTH(A96) -> 5 | C96: =YEAR(A96) -> 2022 | D96: =C96*100+B96 -> 202205 | E96: =IF(B96<4,1,IF(B96<7,2,IF(B96<10,3,4))) -> 2 | F96: =C96*100+E96 -> 202202 | G96: 20220505 | H96: 1 | I96: 0.9382 | J96: 0.9936849 | K96: 1.1896014 | L96: 1.3852564 | M96: 1.5764026 | N96: 1.7506132 | O96: 1.903282 | P96: 2.0347503 | Q96: 2.1463309 | R96: 2.2414149 | S96: 2.322425 | T96: 2.3908163 | U96: 2.4468897 | V96: 2.4908973 | W96: 2.5235195 | X96: 2.5455335 | Y96: 2.5577164 | Z96: 2.5608455 | AA96: 2.5556979 | AB96: 2.5431177 | AC96: 2.5242904 | AD96: 2.5005109 | AE96: 2.473074 | AF96: 2.4432746 | AG96: 2.4124075 | AH96: 2.3816207 | AI96: 2.3512706 | AJ96: 2.3214484 | AK96: 2.2922452 | AL96: 2.2637518 | AM96: 2.2360593 | AN96: 2.2092587 | AO96: 2.183441 | AP96: 2.1586972 | AQ96: 2.1351182 | AR96: 2.1127951 | AS96: 2.0918188 | AT96: 2.0722564 | AU96: 2.0540575 | AV96: 2.0371362 | AW96: 2.0214066 | AX96: 2.0067829 | AY96: 1.993179 | AZ96: 1.980509 | BA96: 1.9686871 | BB96: 1.9576273 | BC96: 1.9472436 | BD96: 1.9374502 | BE96: 1.9281612 | BF96: 1.9193017 | BG96: 1.9108467 | BH96: 1.9027845 | BI96: 1.8951035 | BJ96: 1.8877922 | BK96: 1.8808389 | BL96: 1.8742321 | BM96: 1.8679603 | BN96: 1.8620118 | BO96: 1.856375 | BP96: 1.8510384 | BQ96: 1.8459904 | BR96: 1.8213771 | BS96: 1.805828 | BU96: 1.55 | BV96: 1.97 | BW96: 79.3935
A97: =+A92+7 -> 44687 | B97: =MONTH(A97) -> 5 | C97: =YEAR(A97) -> 2022 | D97: =C97*100+B97 -> 202205 | E97: =IF(B97<4,1,IF(B97<7,2,IF(B97<10,3,4))) -> 2 | F97: =C97*100+E97 -> 202202 | G97: 20220506 | H97: 1 | I97: 0.9409 | J97: 1.0026312 | K97: 1.2003506 | L97: 1.3914514 | M97: 1.5747577 | N97: 1.7433145 | O97: 1.8951852 | P97: 2.0302865 | Q97: 2.1484731 | R97: 2.2507317 | S97: 2.3381535 | T97: 2.4111817 | U97: 2.4701341 | V97: 2.5151619 | W97: 2.5472524 | X97: 2.5676796 | Y97: 2.5777173 | Z97: 2.5786396 | AA97: 2.5717203 | AB97: 2.5582163 | AC97: 2.5393058 | AD97: 2.516144 | AE97: 2.4898862 | AF97: 2.4616876 | AG97: 2.4327034 | AH97: 2.4039411 | AI97: 2.3756872 | AJ97: 2.3480091 | AK97: 2.320974 | AL97: 2.2946492 | AM97: 2.2691019 | AN97: 2.2443994 | AO97: 2.2206089 | AP97: 2.1977977 | AQ97: 2.176033 | AR97: 2.1553822 | AS97: 2.1359124 | AT97: 2.1176706 | AU97: 2.1006143 | AV97: 2.0846763 | AW97: 2.0697893 | AX97: 2.0558861 | AY97: 2.0428995 | AZ97: 2.0307622 | BA97: 2.019407 | BB97: 2.0087666 | BC97: 1.998774 | BD97: 1.9893617 | BE97: 1.9804625 | BF97: 1.9720176 | BG97: 1.9640045 | BH97: 1.9564107 | BI97: 1.949224 | BJ97: 1.9424319 | BK97: 1.9360222 | BL97: 1.9299823 | BM97: 1.9243 | BN97: 1.9189629 | BO97: 1.9139587 | BP97: 1.9092749 | BQ97: 1.9048991 | BR97: 1.8846315 | BS97: 1.8736094 | BU97: 1.51 | BV97: 2.01 | BW97: 79.2176
A98: =+A93+7 -> 44690 | B98: =MONTH(A98) -> 5 | C98: =YEAR(A98) -> 2022 | D98: =C98*100+B98 -> 202205 | E98: =IF(B98<4,1,IF(B98<7,2,IF(B98<10,3,4))) -> 2 | F98: =C98*100+E98 -> 202202 | G98: 20220509 | H98: 1 | I98: 0.9403 | J98: 1.0085881 | K98: 1.2047798 | L98: 1.387806 | M98: 1.5591343 | N98: 1.7151414 | O98: 1.8560551 | P98: 1.9828427 | Q98: 2.0954584 | R98: 2.1938333 | S98: 2.2781844 | T98: 2.348416 | U98: 2.4047989 | V98: 2.4473863 | W98: 2.477218 | X98: 2.4956349 | Y98: 2.5039778 | Z98: 2.5035874 | AA98: 2.4958047 | AB98: 2.4819355 | AC98: 2.4631245 | AD98: 2.4404692 | AE98: 2.4150675 | AF98: 2.3880168 | AG98: 2.360415 | AH98: 2.3332014 | AI98: 2.3066165 | AJ98: 2.2807081 | AK98: 2.2555237 | AL98: 2.2311112 | AM98: 2.2075181 | AN98: 2.1847922 | AO98: 2.1629813 | AP98: 2.1421329 | AQ98: 2.1222947 | AR98: 2.1035146 | AS98: 2.0858401 | AT98: 2.0693024 | AU98: 2.0538596 | AV98: 2.0394497 | AW98: 2.0260106 | AX98: 2.0134802 | AY98: 2.0017965 | AZ98: 1.9908975 | BA98: 1.980721 | BB98: 1.9712051 | BC98: 1.9622876 | BD98: 1.9539066 | BE98: 1.9459999 | BF98: 1.9385118 | BG98: 1.9314199 | BH98: 1.9247134 | BI98: 1.9183812 | BJ98: 1.9124122 | BK98: 1.9067956 | BL98: 1.9015204 | BM98: 1.8965755 | BN98: 1.8919499 | BO98: 1.8876327 | BP98: 1.8836129 | BQ98: 1.8798795 | BR98: 1.863048 | BS98: 1.854802 | BU98: 1.39 | BV98: 1.96 | BW98: 79.3021
A99: =+A94+7 -> 44691 | B99: =MONTH(A99) -> 5 | C99: =YEAR(A99) -> 2022 | D99: =C99*100+B99 -> 202205 | E99: =IF(B99<4,1,IF(B99<7,2,IF(B99<10,3,4))) -> 2 | F99: =C99*100+E99 -> 202202 | G99: 20220510 | H99: 1 | I99: 0.9397 | J99: 1.0152454 | K99: 1.2135983 | L99: 1.3892208 | M99: 1.5476343 | N99: 1.6899201 | O99: 1.8193459 | P99: 1.9378319 | Q99: 2.045016 | R99: 2.1396328 | S99: 2.2210502 | T99: 2.2888117 | U99: 2.3429893 | V99: 2.3838795 | W99: 2.4125524 | X99: 2.4302815 | Y99: 2.4383405 | Z99: 2.4380028 | AA99: 2.430542 | AB99: 2.417199 | AC99: 2.399064 | AD99: 2.3771834 | AE99: 2.3526038 | AF99: 2.3263714 | AG99: 2.2995328 | AH99: 2.2729844 | AI99: 2.2469608 | AJ99: 2.2215139 | AK99: 2.1966956 | AL99: 2.1725579 | AM99: 2.1491527 | AN99: 2.1265318 | AO99: 2.1047473 | AP99: 2.083851 | AQ99: 2.0638948 | AR99: 2.0449307 | AS99: 2.0270106 | AT99: 2.0101725 | AU99: 1.9943798 | AV99: 1.9795707 | AW99: 1.9656834 | AX99: 1.9526561 | AY99: 1.9404272 | AZ99: 1.9289347 | BA99: 1.918117 | BB99: 1.9079123 | BC99: 1.8982589 | BD99: 1.8890948 | BE99: 1.8803585 | BF99: 1.8719954 | BG99: 1.8639866 | BH99: 1.8563239 | BI99: 1.8489994 | BJ99: 1.8420048 | BK99: 1.835332 | BL99: 1.828973 | BM99: 1.8229197 | BN99: 1.8171639 | BO99: 1.8116975 | BP99: 1.8065125 | BQ99: 1.8016007 | BR99: 1.7775956 | BS99: 1.7624888 | BU99: 1.33 | BV99: 1.85 | BW99: 79.292
A100: =+A95+7 -> 44692 | B100: =MONTH(A100) -> 5 | C100: =YEAR(A100) -> 2022 | D100: =C100*100+B100 -> 202205 | E100: =IF(B100<4,1,IF(B100<7,2,IF(B100<10,3,4))) -> 2 | F100: =C100*100+E100 -> 202202 | G100: 20220511 | H100: 1 | I100: 0.9405 | J100: 1.0169683 | K100: 1.221967 | L100: 1.3979857 | M100: 1.5538227 | N100: 1.6927052 | O100: 1.8180545 | P100: 1.9321206 | Q100: 2.0351108 | R100: 2.1264041 | S100: 2.2048625 | T100: 2.2701879 | U100: 2.3216327 | V100: 2.3591232 | W100: 2.3838167 | X100: 2.39713 | Y100: 2.4004798 | Z100: 2.3952827 | AA100: 2.3829554 | AB100: 2.3648822 | AC100: 2.3422649 | AD100: 2.3162407 | AE100: 2.2879467 | AF100: 2.2585203 | AG100: 2.2290986 | AH100: 2.2006777 | AI100: 2.1734937 | AJ100: 2.1475281 | AK100: 2.122762 | AL100: 2.0991766 | AM100: 2.0767531 | AN100: 2.0554726 | AO100: 2.0353164 | AP100: 2.0162656 | AQ100: 1.9983014 | AR100: 1.981405 | AS100: 1.9655576 | AT100: 1.9507333 | AU100: 1.936872 | AV100: 1.9239031 | AW100: 1.9117562 | AX100: 1.9003605 | AY100: 1.8896456 | AZ100: 1.8795409 | BA100: 1.8699758 | BB100: 1.8608797 | BC100: 1.8521822 | BD100: 1.8438126 | BE100: 1.8357004 | BF100: 1.8277862 | BG100: 1.8200599 | BH100: 1.8125251 | BI100: 1.8051854 | BJ100: 1.7980442 | BK100: 1.7911053 | BL100: 1.7843722 | BM100: 1.7778483 | BN100: 1.7715374 | BO100: 1.7654429 | BP100: 1.7595684 | BQ100: 1.7539174 | BR100: 1.7248909 | BS100: 1.7047171 | BU100: 1.29 | BV100: 1.8 | BW100: 79.4351
A101: =+A96+7 -> 44693 | B101: =MONTH(A101) -> 5 | C101: =YEAR(A101) -> 2022 | D101: =C101*100+B101 -> 202205 | E101: =IF(B101<4,1,IF(B101<7,2,IF(B101<10,3,4))) -> 2 | F101: =C101*100+E101 -> 202202 | G101: 20220512 | H101: 1 | I101: 0.9401 | J101: 1.0198281 | K101: 1.2224412 | L101: 1.3978531 | M101: 1.5545008 | N101: 1.6940499 | O101: 1.8179917 | P101: 1.9279018 | Q101: 2.0233285 | R101: 2.1042022 | S101: 2.1706067 | T101: 2.2231257 | U101: 2.2621347 | V101: 2.2886248 | W101: 2.3038709 | X101: 2.3091678 | Y101: 2.3058107 | Z101: 2.2950946 | AA101: 2.2783147 | AB101: 2.2567312 | AC101: 2.2314263 | AD101: 2.2034254 | AE101: 2.1737539 | AF101: 2.1434369 | AG101: 2.1134999 | AH101: 2.084823 | AI101: 2.0575792 | AJ101: 2.0317263 | AK101: 2.007222 | AL101: 1.9840239 | AM101: 1.9620899 | AN101: 1.9413776 | AO101: 1.9218447 | AP101: 1.903449 | AQ101: 1.8861481 | AR101: 1.8698998 | AS101: 1.8546618 | AT101: 1.8403876 | AU101: 1.8270123 | AV101: 1.8144658 | AW101: 1.8026779 | AX101: 1.7915787 | AY101: 1.781098 | AZ101: 1.7711659 | BA101: 1.7617121 | BB101: 1.7526667 | BC101: 1.7439596 | BD101: 1.7355206 | BE101: 1.7272798 | BF101: 1.7191789 | BG101: 1.7112122 | BH101: 1.7033882 | BI101: 1.6957157 | BJ101: 1.6882034 | BK101: 1.6808598 | BL101: 1.6736936 | BM101: 1.6667136 | BN101: 1.6599284 | BO101: 1.6533466 | BP101: 1.6469769 | BQ101: 1.640828 | BR101: 1.6088853 | BS101: 1.5860396 | BU101: 1.18 | BV101: 1.68 | BW101: 79.3222
A102: =+A97+7 -> 44694 | B102: =MONTH(A102) -> 5 | C102: =YEAR(A102) -> 2022 | D102: =C102*100+B102 -> 202205 | E102: =IF(B102<4,1,IF(B102<7,2,IF(B102<10,3,4))) -> 2 | F102: =C102*100+E102 -> 202202 | G102: 20220513 | H102: 1 | I102: 0.9398 | J102: 1.028724 | K102: 1.241012 | L102: 1.4220109 | M102: 1.5818553 | N102: 1.7230545 | O102: 1.8468493 | P102: 1.9552028 | Q102: 2.0491014 | R102: 2.1293428 | S102: 2.1966081 | T102: 2.2511223 | U102: 2.2931324 | V102: 2.3228541 | W102: 2.3412971 | X102: 2.3497341 | Y102: 2.3494375 | Z102: 2.3416801 | AA102: 2.3277344 | AB102: 2.3088333 | AC102: 2.2860257 | AD102: 2.2603067 | AE102: 2.2326718 | AF102: 2.2041164 | AG102: 2.1756357 | AH102: 2.1480732 | AI102: 2.1216015 | AJ102: 2.0962084 | AK102: 2.0718813 | AL102: 2.048608 | AM102: 2.0263761 | AN102: 2.0051732 | AO102: 1.9849869 | AP102: 1.9658048 | AQ102: 1.9476146 | AR102: 1.9304038 | AS102: 1.9141602 | AT102: 1.8988638 | AU102: 1.8844618 | AV102: 1.8708919 | AW102: 1.8580921 | AX102: 1.8460003 | AY102: 1.8345545 | AZ102: 1.8236925 | BA102: 1.8133523 | BB102: 1.8034717 | BC102: 1.7939887 | BD102: 1.7848412 | BE102: 1.7759671 | BF102: 1.7673143 | BG102: 1.7588747 | BH102: 1.7506523 | BI102: 1.7426514 | BJ102: 1.7348758 | BK102: 1.7273297 | BL102: 1.7200172 | BM102: 1.7129423 | BN102: 1.706109 | BO102: 1.6995216 | BP102: 1.693184 | BQ102: 1.6871003 | BR102: 1.6561261 | BS102: 1.6351234 | BU102: 1.25 | BV102: 1.75 | BW102: 79.3534
A103: =+A98+7 -> 44697 | B103: =MONTH(A103) -> 5 | C103: =YEAR(A103) -> 2022 | D103: =C103*100+B103 -> 202205 | E103: =IF(B103<4,1,IF(B103<7,2,IF(B103<10,3,4))) -> 2 | F103: =C103*100+E103 -> 202202 | G103: 20220516 | H103: 1 | I103: 0.9398 | J103: 1.0409659 | K103: 1.2728966 | L103: 1.4636584 | M103: 1.6256021 | N103: 1.764916 | O103: 1.8848671 | P103: 1.9886256 | Q103: 2.0783834 | R103: 2.1554143 | S103: 2.2205088 | T103: 2.2737385 | U103: 2.3150966 | V103: 2.3444137 | W103: 2.3625539 | X103: 2.3706779 | Y103: 2.3699463 | Z103: 2.3615197 | AA103: 2.3465588 | AB103: 2.3262138 | AC103: 2.3015877 | AD103: 2.2737694 | AE103: 2.2438479 | AF103: 2.2129123 | AG103: 2.1820515 | AH103: 2.1521893 | AI103: 2.1235184 | AJ103: 2.0960303 | AK103: 2.0697165 | AL103: 2.0445682 | AM103: 2.0205771 | AN103: 1.9977344 | AO103: 1.9760315 | AP103: 1.95546 | AQ103: 1.9360111 | AR103: 1.9176763 | AS103: 1.900447 | AT103: 1.8843056 | AU103: 1.8691942 | AV103: 1.8550439 | AW103: 1.841786 | AX103: 1.8293515 | AY103: 1.8176716 | AZ103: 1.8066774 | BA103: 1.7963002 | BB103: 1.7864709 | BC103: 1.7771207 | BD103: 1.7681809 | BE103: 1.7595824 | BF103: 1.751265 | BG103: 1.7432134 | BH103: 1.7354278 | BI103: 1.7279083 | BJ103: 1.720655 | BK103: 1.713668 | BL103: 1.7069475 | BM103: 1.7004934 | BN103: 1.694306 | BO103: 1.6883854 | BP103: 1.6827316 | BQ103: 1.6773448 | BR103: 1.6506014 | BS103: 1.6332819 | BU103: 1.23 | BV103: 1.74 | BW103: 79.545
A104: =+A99+7 -> 44698 | B104: =MONTH(A104) -> 5 | C104: =YEAR(A104) -> 2022 | D104: =C104*100+B104 -> 202205 | E104: =IF(B104<4,1,IF(B104<7,2,IF(B104<10,3,4))) -> 2 | F104: =C104*100+E104 -> 202202 | G104: 20220517 | H104: 1 | I104: 0.9398 | J104: 1.0761297 | K104: 1.3508632 | L104: 1.577636 | M104: 1.7673482 | N104: 1.9258314 | O104: 2.0591482 | P104: 2.1725515 | Q104: 2.2703562 | R104: 2.3550705 | S104: 2.4280118 | T104: 2.4891958 | U104: 2.5381977 | V104: 2.5743899 | W104: 2.5984591 | X104: 2.6114591 | Y104: 2.6144436 | Z104: 2.6084666 | AA104: 2.5945818 | AB104: 2.5738806 | AC104: 2.5476291 | AD104: 2.5171439 | AE104: 2.4837419 | AF104: 2.4487396 | AG104: 2.4134537 | AH104: 2.3790063 | AI104: 2.3456601 | AJ104: 2.313441 | AK104: 2.2823746 | AL104: 2.2524868 | AM104: 2.2238033 | AN104: 2.1963497 | AO104: 2.170152 | AP104: 2.1452357 | AQ104: 2.1216267 | AR104: 2.0993507 | AS104: 2.0784335 | AT104: 2.058887 | AU104: 2.0406488 | AV104: 2.0236318 | AW104: 2.0077486 | AX104: 1.992912 | AY104: 1.9790347 | AZ104: 1.9660294 | BA104: 1.9538089 | BB104: 1.9422859 | BC104: 1.9313732 | BD104: 1.9209834 | BE104: 1.9110294 | BF104: 1.9014348 | BG104: 1.8921777 | BH104: 1.8832521 | BI104: 1.8746525 | BJ104: 1.8663731 | BK104: 1.8584082 | BL104: 1.8507521 | BM104: 1.843399 | BN104: 1.8363432 | BO104: 1.8295791 | BP104: 1.8231008 | BQ104: 1.8169027 | BR104: 1.7854341 | BS104: 1.7635586 | BU104: 1.45 | BV104: 1.9 | BW104: 80.3371
A105: =+A100+7 -> 44699 | B105: =MONTH(A105) -> 5 | C105: =YEAR(A105) -> 2022 | D105: =C105*100+B105 -> 202205 | E105: =IF(B105<4,1,IF(B105<7,2,IF(B105<10,3,4))) -> 2 | F105: =C105*100+E105 -> 202202 | G105: 20220518 | H105: 1 | I105: 0.9394 | J105: 1.0919087 | K105: 1.3417437 | L105: 1.5508324 | M105: 1.7287612 | N105: 1.8799987 | O105: 2.0088996 | P105: 2.1193366 | Q105: 2.2144764 | R105: 2.2965767 | S105: 2.3665601 | T105: 2.4250503 | U105: 2.4714581 | V105: 2.5052063 | W105: 2.5270468 | X105: 2.5380581 | Y105: 2.5393184 | Z105: 2.531906 | AA105: 2.5168992 | AB105: 2.4954045 | AC105: 2.4686874 | AD105: 2.4380698 | AE105: 2.4048732 | AF105: 2.3704196 | AG105: 2.3360306 | AH105: 2.3028638 | AI105: 2.2711919 | AJ105: 2.2409913 | AK105: 2.212238 | AL105: 2.184908 | AM105: 2.1589775 | AN105: 2.1344226 | AO105: 2.1112191 | AP105: 2.0893434 | AQ105: 2.0687713 | AR105: 2.049479 | AS105: 2.0314425 | AT105: 2.0146289 | AU105: 1.9989618 | AV105: 1.9843512 | AW105: 1.9707075 | AX105: 1.9579407 | AY105: 1.945961 | AZ105: 1.9346787 | BA105: 1.9240038 | BB105: 1.9138467 | BC105: 1.9041175 | BD105: 1.8947263 | BE105: 1.8855834 | BF105: 1.8766136 | BG105: 1.8678069 | BH105: 1.8591708 | BI105: 1.8507133 | BJ105: 1.842442 | BK105: 1.8343647 | BL105: 1.8264891 | BM105: 1.8188231 | BN105: 1.8113744 | BO105: 1.8041507 | BP105: 1.7971598 | BQ105: 1.7904094 | BR105: 1.7552439 | BS105: 1.7297882 | BU105: 1.46 | BV105: 1.87 | BW105: 80.049
... A115: =+A110+7 -> 44713 | B115: =MONTH(A115) -> 6 | C115: =YEAR(A115) -> 2022 | D115: =C115*100+B115 -> 202206 | E115: =IF(B115<4,1,IF(B115<7,2,IF(B115<10,3,4))) -> 2 | F115: =C115*100+E115 -> 202202 | G115: 20220601 | H115: 1 | I115: 0.9389 | J115: 1.2318121 | K115: 1.4023849 | L115: 1.6083482 | M115: 1.8152552 | N115: 2.0083227 | O115: 2.1831957 | P115: 2.3362595 | Q115: 2.4669137 | R115: 2.5749327 | S115: 2.661803 | T115: 2.7294434 | U115: 2.7793831 | V115: 2.8143222 | W115: 2.8361762 | X115: 2.8465521 | Y115: 2.847057 | Z115: 2.839298 | AA115: 2.8248822 | AB115: 2.8053098 | AC115: 2.7816317 | AD115: 2.7547806 | AE115: 2.7256895 | AF115: 2.6952912 | AG115: 2.6645185 | AH115: 2.634195 | AI115: 2.6045553 | AJ115: 2.5756364 | AK115: 2.5474756 | AL115: 2.5201097 | AM115: 2.4935758 | AN115: 2.467911 | AO115: 2.4431523 | AP115: 2.4193367 | AQ115: 2.3965012 | AR115: 2.374683 | AS115: 2.3539189 | AT115: 2.334233 | AU115: 2.3155851 | AV115: 2.297916 | AW115: 2.281166 | AX115: 2.2652758 | AY115: 2.2501858 | AZ115: 2.2358366 | BA115: 2.2221687 | BB115: 2.2091227 | BC115: 2.1966391 | BD115: 2.1846585 | BE115: 2.1731213 | BF115: 2.1619762 | BG115: 2.1512082 | BH115: 2.1408119 | BI115: 2.1307821 | BJ115: 2.1211135 | BK115: 2.1118009 | BL115: 2.1028392 | BM115: 2.0942229 | BN115: 2.085947 | BO115: 2.0780061 | BP115: 2.070395 | BQ115: 2.0631085 | BR115: 2.0260619 | BS115: 2.0002895 | BU115: 1.67 | BV115: 2.16 | BW115: 79.8125
A116: =+A111+7 -> 44714 | B116: =MONTH(A116) -> 6 | C116: =YEAR(A116) -> 2022 | D116: =C116*100+B116 -> 202206 | E116: =IF(B116<4,1,IF(B116<7,2,IF(B116<10,3,4))) -> 2 | F116: =C116*100+E116 -> 202202 | G116: 20220602 | H116: 1 | I116: #N/A | J116: #N/A | K116: #N/A | L116: #N/A | M116: #N/A | N116: #N/A | O116: #N/A | P116: #N/A | Q116: #N/A | R116: #N/A | S116: #N/A | T116: #N/A | U116: #N/A | V116: #N/A | W116: #N/A | X116: #N/A | Y116: #N/A | Z116: #N/A | AA116: #N/A | AB116: #N/A | AC116: #N/A | AD116: #N/A | AE116: #N/A | AF116: #N/A | AG116: #N/A | AH116: #N/A | AI116: #N/A | AJ116: #N/A | AK116: #N/A | AL116: #N/A | AM116: #N/A | AN116: #N/A | AO116: #N/A | AP116: #N/A | AQ116: #N/A | AR116: #N/A | AS116: #N/A | AT116: #N/A | AU116: #N/A | AV116: #N/A | AW116: #N/A | AX116: #N/A | AY116: #N/A | AZ116: #N/A | BA116: #N/A | BB116: #N/A | BC116: #N/A | BD116: #N/A | BE116: #N/A | BF116: #N/A | BG116: #N/A | BH116: #N/A | BI116: #N/A | BJ116: #N/A | BK116: #N/A | BL116: #N/A | BM116: #N/A | BN116: #N/A | BO116: #N/A | BP116: #N/A | BQ116: #N/A | BR116: #N/A | BS116: #N/A | BU116: 1.65 | BV116: 2.15 | BW116: #N/A
A117: =+A112+7 -> 44715 | B117: =MONTH(A117) -> 6 | C117: =YEAR(A117) -> 2022 | D117: =C117*100+B117 -> 202206 | E117: =IF(B117<4,1,IF(B117<7,2,IF(B117<10,3,4))) -> 2 | F117: =C117*100+E117 -> 202202 | G117: 20220603 | H117: 1 | I117: #N/A | J117: #N/A | K117: #N/A | L117: #N/A | M117: #N/A | N117: #N/A | O117: #N/A | P117: #N/A | Q117: #N/A | R117: #N/A | S117: #N/A | T117: #N/A | U117: #N/A | V117: #N/A | W117: #N/A | X117: #N/A | Y117: #N/A | Z117: #N/A | AA117: #N/A | AB117: #N/A | AC117: #N/A | AD117: #N/A | AE117: #N/A | AF117: #N/A | AG117: #N/A | AH117: #N/A | AI117: #N/A | AJ117: #N/A | AK117: #N/A | AL117: #N/A | AM117: #N/A | AN117: #N/A | AO117: #N/A | AP117: #N/A | AQ117: #N/A | AR117: #N/A | AS117: #N/A | AT117: #N/A | AU117: #N/A | AV117: #N/A | AW117: #N/A | AX117: #N/A | AY117: #N/A | AZ117: #N/A | BA117: #N/A | BB117: #N/A | BC117: #N/A | BD117: #N/A | BE117: #N/A | BF117: #N/A | BG117: #N/A | BH117: #N/A | BI117: #N/A | BJ117: #N/A | BK117: #N/A | BL117: #N/A | BM117: #N/A | BN117: #N/A | BO117: #N/A | BP117: #N/A | BQ117: #N/A | BR117: #N/A | BS117: #N/A | BU117: 1.65 | BV117: 2.15 | BW117: #N/A
A118: =+A113+7 -> 44718 | B118: =MONTH(A118) -> 6 | C118: =YEAR(A118) -> 2022 | D118: =C118*100+B118 -> 202206 | E118: =IF(B118<4,1,IF(B118<7,2,IF(B118<10,3,4))) -> 2 | F118: =C118*100+E118 -> 202202 | G118: 20220606 | H118: 1 | I118: 0.9394 | J118: 1.2446245 | K118: 1.4281523 | L118: 1.6485151 | M118: 1.8703102 | N118: 2.0765179 | O118: 2.2617213 | P118: 2.4220046 | Q118: 2.5566389 | R118: 2.666385 | S118: 2.7539468 | T118: 2.8215855 | U118: 2.8719771 | V118: 2.9081295 | W118: 2.9318884 | X118: 2.9447719 | Y118: 2.9482983 | Z118: 2.9439858 | AA118: 2.9333525 | AB118: 2.9177985 | AC118: 2.8982277 | AD118: 2.8754136 | AE118: 2.8501296 | AF118: 2.8231494 | AG118: 2.7952463 | AH118: 2.7670895 | AI118: 2.7388878 | AJ118: 2.7107225 | AK118: 2.6826752 | AL118: 2.6548274 | AM118: 2.6272607 | AN118: 2.6000565 | AO118: 2.5732964 | AP118: 2.5470619 | AQ118: 2.5214346 | AR118: 2.4964959 | AS118: 2.4723273 | AT118: 2.4489959 | AU118: 2.4265042 | AV118: 2.4048369 | AW118: 2.3839788 | AX118: 2.3639148 | AY118: 2.3446297 | AZ118: 2.3261082 | BA118: 2.3083352 | BB118: 2.2912953 | BC118: 2.2749735 | BD118: 2.2593546 | BE118: 2.2444232 | BF118: 2.2301647 | BG118: 2.2165665 | BH118: 2.2036167 | BI118: 2.1913036 | BJ118: 2.1796154 | BK118: 2.1685403 | BL118: 2.1580664 | BM118: 2.148182 | BN118: 2.1388753 | BO118: 2.1301344 | BP118: 2.1219475 | BQ118: 2.114303 | BR118: 2.0790269 | BS118: 2.0594696 | BU118: 1.77 | BV118: 2.26 | BW118: 79.9795
A119: =+A114+7 -> 44719 | B119: =MONTH(A119) -> 6 | C119: =YEAR(A119) -> 2022 | D119: =C119*100+B119 -> 202206 | E119: =IF(B119<4,1,IF(B119<7,2,IF(B119<10,3,4))) -> 2 | F119: =C119*100+E119 -> 202202 | G119: 20220607 | H119: 1 | I119: 0.9403 | J119: 1.237853 | K119: 1.4272938 | L119: 1.652123 | M119: 1.8770456 | N119: 2.0854476 | O119: 2.2718384 | P119: 2.4318409 | Q119: 2.5651138 | R119: 2.6726431 | S119: 2.7574233 | T119: 2.8223871 | U119: 2.8698384 | V119: 2.9029607 | W119: 2.923705 | X119: 2.9336093 | Y119: 2.9342116 | Z119: 2.9270498 | AA119: 2.9136619 | AB119: 2.8954657 | AC119: 2.8733744 | AD119: 2.848169 | AE119: 2.82063 | AF119: 2.7915383 | AG119: 2.7616747 | AH119: 2.7317152 | AI119: 2.7018748 | AJ119: 2.6722408 | AK119: 2.6429005 | AL119: 2.6139415 | AM119: 2.5854511 | AN119: 2.5575168 | AO119: 2.5302258 | AP119: 2.5036658 | AQ119: 2.477924 | AR119: 2.4530879 | AS119: 2.4292449 | AT119: 2.4064665 | AU119: 2.384739 | AV119: 2.3640201 | AW119: 2.3442673 | AX119: 2.3254383 | AY119: 2.3074907 | AZ119: 2.2903821 | BA119: 2.2740702 | BB119: 2.2585125 | BC119: 2.2436666 | BD119: 2.2294903 | BE119: 2.215941 | BF119: 2.2029802 | BG119: 2.1905867 | BH119: 2.1787452 | BI119: 2.1674401 | BJ119: 2.1566559 | BK119: 2.146377 | BL119: 2.136588 | BM119: 2.1272733 | BN119: 2.1184175 | BO119: 2.1100049 | BP119: 2.1020201 | BQ119: 2.0944475 | BR119: 2.0570814 | BS119: 2.0323508 | BU119: 1.75 | BV119: 2.22 | BW119: 80.2673
A120: =+A115+7 -> 44720 | B120: =MONTH(A120) -> 6 | C120: =YEAR(A120) -> 2022 | D120: =C120*100+B120 -> 202206 | E120: =IF(B120<4,1,IF(B120<7,2,IF(B120<10,3,4))) -> 2 | F120: =C120*100+E120 -> 202202 | G120: 20220608 | H120: 1 | I120: 0.9402 | J120: 1.2573688 | K120: 1.4597938 | L120: 1.6951206 | M120: 1.9265737 | N120: 2.1371815 | O120: 2.3235348 | P120: 2.4828744 | Q120: 2.6155492 | R120: 2.7230636 | S120: 2.8082433 | T120: 2.8741218 | U120: 2.9224387 | V120: 2.956263 | W120: 2.9775334 | X120: 2.9877646 | Y120: 2.9884711 | Z120: 2.9811676 | AA120: 2.9673684 | AB120: 2.948484 | AC120: 2.9254863 | AD120: 2.8992319 | AE120: 2.8705778 | AF120: 2.8403807 | AG120: 2.8094975 | AH120: 2.7786886 | AI120: 2.7481966 | AJ120: 2.71809 | AK120: 2.6884374 | AL120: 2.6593074 | AM120: 2.6307685 | AN120: 2.6028893 | AO120: 2.5757383 | AP120: 2.5493841 | AQ120: 2.5238952 | AR120: 2.4993402 | AS120: 2.4757875 | AT120: 2.4532901 | AU120: 2.4318236 | AV120: 2.4113405 | AW120: 2.391793 | AX120: 2.3731336 | AY120: 2.3553145 | AZ120: 2.3382882 | BA120: 2.3220069 | BB120: 2.3064231 | BC120: 2.2914891 | BD120: 2.2771572 | BE120: 2.2633798 | BF120: 2.2501151 | BG120: 2.2373467 | BH120: 2.2250653 | BI120: 2.2132617 | BJ120: 2.2019266 | BK120: 2.1910508 | BL120: 2.1806249 | BM120: 2.1706397 | BN120: 2.1610859 | BO120: 2.1519543 | BP120: 2.1432355 | BQ120: 2.1349203 | BR120: 2.0931347 | BS120: 2.0644449 | BU120: 1.78 | BV120: 2.25 | BW120: 80.0635
A121: =+A116+7 -> 44721 | B121: =MONTH(A121) -> 6 | C121: =YEAR(A121) -> 2022 | D121: =C121*100+B121 -> 202206 | E121: =IF(B121<4,1,IF(B121<7,2,IF(B121<10,3,4))) -> 2 | F121: =C121*100+E121 -> 202202 | G121: 20220609 | H121: 1 | I121: 0.9407 | J121: 1.2865069 | K121: 1.5171319 | L121: 1.778179 | M121: 2.030638 | N121: 2.2567558 | O121: 2.4538069 | P121: 2.6201131 | Q121: 2.7573069 | R121: 2.8677539 | S121: 2.9546192 | T121: 3.0207709 | U121: 3.0682557 | V121: 3.1002242 | W121: 3.1188293 | X121: 3.1258673 | Y121: 3.1231341 | Z121: 3.112426 | AA121: 3.0955388 | AB121: 3.0741367 | AC121: 3.0492066 | AD121: 3.0215194 | AE121: 2.9918457 | AF121: 2.9609563 | AG121: 2.9296219 | AH121: 2.8985146 | AI121: 2.8678258 | AJ121: 2.8376003 | AK121: 2.8078832 | AL121: 2.7787194 | AM121: 2.750154 | AN121: 2.7222319 | AO121: 2.694998 | AP121: 2.6684974 | AQ121: 2.642775 | AR121: 2.6178758 | AS121: 2.5938448 | AT121: 2.5707151 | AU121: 2.5484679 | AV121: 2.5270703 | AW121: 2.5064889 | AX121: 2.4866907 | AY121: 2.4676426 | AZ121: 2.4493114 | BA121: 2.431664 | BB121: 2.4146673 | BC121: 2.3982881 | BD121: 2.3824933 | BE121: 2.3672498 | BF121: 2.3525284 | BG121: 2.3383179 | BH121: 2.3246118 | BI121: 2.3114038 | BJ121: 2.2986873 | BK121: 2.286456 | BL121: 2.2747034 | BM121: 2.2634231 | BN121: 2.2526088 | BO121: 2.2422539 | BP121: 2.2323521 | BQ121: 2.2228969 | BR121: 2.1751978 | BS121: 2.1420328 | BU121: 1.86 | BV121: 2.34 | BW121: 80.3866
A122: =+A117+7 -> 44722 | B122: =MONTH(A122) -> 6 | C122: =YEAR(A122) -> 2022 | D122: =C122*100+B122 -> 202206 | E122: =IF(B122<4,1,IF(B122<7,2,IF(B122<10,3,4))) -> 2 | F122: =C122*100+E122 -> 202202 | G122: 20220610 | H122: 1 | I122: 0.9402 | J122: 1.3282644 | K122: 1.5717858 | L122: 1.8508546 | M122: 2.1234839 | N122: 2.371242 | O122: 2.5904503 | P122: 2.7780717 | Q122: 2.9320502 | R122: 3.0534656 | S122: 3.1460868 | T122: 3.2138481 | U122: 3.2608467 | V122: 3.2925587 | W122: 3.3117199 | X122: 3.3200793 | Y122: 3.3193857 | Z122: 3.3113879 | AA122: 3.2978346 | AB122: 3.2802927 | AC122: 3.2594856 | AD122: 3.2358919 | AE122: 3.2099906 | AF122: 3.1822604 | AG122: 3.1531801 | AH122: 3.1231765 | AI122: 3.0924472 | AJ122: 3.0611267 | AK122: 3.0293492 | AL122: 2.9972492 | AM122: 2.9649609 | AN122: 2.9326187 | AO122: 2.900357 | AP122: 2.8683102 | AQ122: 2.8366126 | AR122: 2.8053985 | AS122: 2.7748024 | AT122: 2.7449404 | AU122: 2.7158495 | AV122: 2.6875442 | AW122: 2.6600393 | AX122: 2.6333496 | AY122: 2.6074899 | AZ122: 2.5824748 | BA122: 2.5583191 | BB122: 2.5350376 | BC122: 2.512645 | BD122: 2.491156 | BE122: 2.4705854 | BF122: 2.4509427 | BG122: 2.4322148 | BH122: 2.4143819 | BI122: 2.3974245 | BJ122: 2.381323 | BK122: 2.3660578 | BL122: 2.3516094 | BM122: 2.3379581 | BN122: 2.3250844 | BO122: 2.3129686 | BP122: 2.3015912 | BQ122: 2.2909327 | BR122: 2.2408487 | BS122: 2.2109146 | BU122: 2.05 | BV122: 2.43 | BW122: 79.6178
A123: =+A118+7 -> 44725 | B123: =MONTH(A123) -> 6 | C123: =YEAR(A123) -> 2022 | D123: =C123*100+B123 -> 202206 | E123: =IF(B123<4,1,IF(B123<7,2,IF(B123<10,3,4))) -> 2 | F123: =C123*100+E123 -> 202202 | G123: 20220613 | H123: 1 | I123: 0.9396 | J123: 1.3121659 | K123: 1.5672049 | L123: 1.852908 | M123: 2.1401494 | N123: 2.4083384 | O123: 2.6501363 | P123: 2.8597323 | Q123: 3.0352853 | R123: 3.1778844 | S123: 3.2911251 | T123: 3.3777399 | U123: 3.4411892 | V123: 3.4857149 | W123: 3.5138948 | X123: 3.527816 | Y123: 3.5295656 | Z123: 3.5212305 | AA123: 3.5048978 | AB123: 3.4824703 | AC123: 3.4550764 | AD123: 3.423641 | AE123: 3.3890892 | AF123: 3.352346 | AG123: 3.3143364 | AH123: 3.2758649 | AI123: 3.2372038 | AJ123: 3.1984787 | AK123: 3.1598149 | AL123: 3.1213381 | AM123: 3.0831737 | AN123: 3.0454471 | AO123: 3.008284 | AP123: 2.9718099 | AQ123: 2.9361501 | AR123: 2.9014302 | AS123: 2.8677758 | AT123: 2.8352902 | AU123: 2.8039797 | AV123: 2.7738235 | AW123: 2.7448011 | AX123: 2.7168916 | AY123: 2.6900746 | AZ123: 2.6643292 | BA123: 2.6396348 | BB123: 2.6159708 | BC123: 2.5933164 | BD123: 2.571651 | BE123: 2.5509539 | BF123: 2.5312043 | BG123: 2.51238 | BH123: 2.4944586 | BI123: 2.4774175 | BJ123: 2.4612343 | BK123: 2.4458865 | BL123: 2.4313515 | BM123: 2.417607 | BN123: 2.4046304 | BO123: 2.3923992 | BP123: 2.380891 | BQ123: 2.3700832 | BR123: 2.3186527 | BS123: 2.2865635 | BU123: 2.13 | BV123: 2.52 | BW123: 78.8471
A124: =+A119+7 -> 44726 | B124: =MONTH(A124) -> 6 | C124: =YEAR(A124) -> 2022 | D124: =C124*100+B124 -> 202206 | E124: =IF(B124<4,1,IF(B124<7,2,IF(B124<10,3,4))) -> 2 | F124: =C124*100+E124 -> 202202 | G124: 20220614 | H124: 1 | I124: 0.9398 | J124: 1.3239705 | K124: 1.6076612 | L124: 1.9149638 | M124: 2.211123 | N124: 2.4764295 | O124: 2.7077749 | P124: 2.9037991 | Q124: 3.0665644 | R124: 3.1985098 | S124: 3.3033862 | T124: 3.3834368 | U124: 3.4412306 | V124: 3.4799984 | W124: 3.5021927 | X124: 3.5100233 | Y124: 3.5057002 | Z124: 3.4914332 | AA124: 3.4694323 | AB124: 3.44172 | AC124: 3.4095311 | AD124: 3.3738937 | AE124: 3.3358359 | AF124: 3.2963855 | AG124: 3.2565708 | AH124: 3.2172731 | AI124: 3.1787272 | AJ124: 3.1409891 | AK124: 3.1041151 | AL124: 3.0681614 | AM124: 3.033184 | AN124: 2.9992393 | AO124: 2.9663833 | AP124: 2.9346723 | AQ124: 2.9041624 | AR124: 2.8749098 | AS124: 2.8469706 | AT124: 2.8203875 | AU124: 2.7951303 | AV124: 2.771144 | AW124: 2.748374 | AX124: 2.7267655 | AY124: 2.7062637 | AZ124: 2.6868139 | BA124: 2.6683612 | BB124: 2.6508509 | BC124: 2.6342282 | BD124: 2.6184383 | BE124: 2.6034266 | BF124: 2.5891429 | BG124: 2.5755607 | BH124: 2.5626608 | BI124: 2.5504236 | BJ124: 2.5388299 | BK124: 2.5278601 | BL124: 2.5174948 | BM124: 2.5077148 | BN124: 2.4985006 | BO124: 2.4898328 | BP124: 2.481692 | BQ124: 2.4740588 | BR124: 2.4379798 | BS124: 2.4161748 | BU124: 2.11 | BV124: 2.59 | BW124: 78.0834
A125: =+A120+7 -> 44727 | B125: =MONTH(A125) -> 6 | C125: =YEAR(A125) -> 2022 | D125: =C125*100+B125 -> 202206 | E125: =IF(B125<4,1,IF(B125<7,2,IF(B125<10,3,4))) -> 2 | F125: =C125*100+E125 -> 202202 | G125: 20220615 | H125: 1 | I125: 0.9399 | J125: 1.3479689 | K125: 1.6309812 | L125: 1.9344149 | M125: 2.225544 | N125: 2.4825164 | O125: 2.7015928 | P125: 2.8805894 | Q125: 3.0214481 | R125: 3.1281521 | S125: 3.2060993 | T125: 3.2600011 | U125: 3.2933694 | V125: 3.3109991 | W125: 3.3154614 | X125: 3.3086247 | Y125: 3.2923575 | Z125: 3.2685284 | AA125: 3.2390057 | AB125: 3.2055094 | AC125: 3.1691348 | AD125: 3.1308131 | AE125: 3.0914755 | AF125: 3.0520532 | AG125: 3.0134777 | AH125: 2.9765599 | AI125: 2.9414647 | AJ125: 2.90814 | AK125: 2.8765335 | AL125: 2.8465931 | AM125: 2.8182665 | AN125: 2.7915016 | AO125: 2.7662461 | AP125: 2.7424479 | AQ125: 2.7200547 | AR125: 2.6990143 | AS125: 2.6792745 | AT125: 2.6607794 | AU125: 2.6434549 | AV125: 2.6272214 | AW125: 2.6119993 | AX125: 2.597709 | AY125: 2.5842709 | AZ125: 2.5716053 | BA125: 2.5596327 | BB125: 2.5482735 | BC125: 2.537448 | BD125: 2.5270767 | BE125: 2.5170799 | BF125: 2.5073903 | BG125: 2.4979941 | BH125: 2.4888928 | BI125: 2.4800873 | BJ125: 2.4715791 | BK125: 2.4633694 | BL125: 2.4554593 | BM125: 2.4478501 | BN125: 2.440543 | BO125: 2.4335393 | BP125: 2.4268402 | BQ125: 2.420447 | BR125: 2.3884157 | BS125: 2.3667162 | BU125: 1.97 | BV125: 2.49 | BW125: 78.485
A126: =+A121+7 -> 44728 | B126: =MONTH(A126) -> 6 | C126: =YEAR(A126) -> 2022 | D126: =C126*100+B126 -> 202206 | E126: =IF(B126<4,1,IF(B126<7,2,IF(B126<10,3,4))) -> 2 | F126: =C126*100+E126 -> 202202 | G126: 20220616 | H126: 1.25 | I126: 1.1884 | J126: 1.2624813 | K126: 1.6231444 | L126: 1.9960359 | M126: 2.3409706 | N126: 2.6312107 | O126: 2.8640677 | P126: 3.0421763 | Q126: 3.1738762 | R126: 3.2680809 | S126: 3.3332329 | T126: 3.3750184 | U126: 3.3975509 | V126: 3.4051867 | W126: 3.4003309 | X126: 3.384833 | Y126: 3.360543 | Z126: 3.3293105 | AA126: 3.2929853 | AB126: 3.2532962 | AC126: 3.2113533 | AD126: 3.1680688 | AE126: 3.124355 | AF126: 3.081124 | AG126: 3.0392881 | AH126: 2.9996217 | AI126: 2.9622287 | AJ126: 2.9270087 | AK126: 2.8938612 | AL126: 2.8626858 | AM126: 2.8333822 | AN126: 2.8058498 | AO126: 2.7799882 | AP126: 2.7556971 | AQ126: 2.7328761 | AR126: 2.7114245 | AS126: 2.6912422 | AT126: 2.6722316 | AU126: 2.6543084 | AV126: 2.6373919 | AW126: 2.6214014 | AX126: 2.6062563 | AY126: 2.5918758 | AZ126: 2.5781794 | BA126: 2.5650862 | BB126: 2.5525157 | BC126: 2.540387 | BD126: 2.5286197 | BE126: 2.5171328 | BF126: 2.5058594 | BG126: 2.4947919 | BH126: 2.4839394 | BI126: 2.4733108 | BJ126: 2.4629151 | BK126: 2.4527614 | BL126: 2.4428588 | BM126: 2.433216 | BN126: 2.4238423 | BO126: 2.4147466 | BP126: 2.405938 | BQ126: 2.3974253 | BR126: 2.3528595 | BS126: 2.3199422 | BU126: 2.12 | BV126: 2.52 | BW126: 79.43
A127: =+A122+7 -> 44729 | B127: =MONTH(A127) -> 6 | C127: =YEAR(A127) -> 2022 | D127: =C127*100+B127 -> 202206 | E127: =IF(B127<4,1,IF(B127<7,2,IF(B127<10,3,4))) -> 2 | F127: =C127*100+E127 -> 202202 | G127: 20220617 | H127: 1.25 | I127: 1.1895 | J127: 1.2642406 | K127: 1.6181306 | L127: 1.9898765 | M127: 2.3412406 | N127: 2.6434905 | O127: 2.8890925 | P127: 3.0809167 | Q127: 3.2260415 | R127: 3.3330515 | S127: 3.4096041 | T127: 3.460367 | U127: 3.4895619 | V127: 3.5019548 | W127: 3.5002672 | X127: 3.486525 | Y127: 3.4627536 | Z127: 3.4309787 | AA127: 3.3932258 | AB127: 3.3513692 | AC127: 3.3065813 | AD127: 3.259831 | AE127: 3.2120873 | AF127: 3.1643192 | AG127: 3.1174956 | AH127: 3.0724331 | AI127: 3.0292761 | AJ127: 2.9879831 | AK127: 2.9485127 | AL127: 2.9108238 | AM127: 2.8748749 | AN127: 2.8406247 | AO127: 2.8080318 | AP127: 2.7770551 | AQ127: 2.747653 | AR127: 2.7197843 | AS127: 2.6934077 | AT127: 2.6684755 | AU127: 2.6449123 | AV127: 2.6226351 | AW127: 2.6015608 | AX127: 2.5816063 | AY127: 2.5626885 | AZ127: 2.5447244 | BA127: 2.5276309 | BB127: 2.511325 | BC127: 2.4957236 | BD127: 2.4807435 | BE127: 2.4663019 | BF127: 2.4523273 | BG127: 2.4388014 | BH127: 2.4257198 | BI127: 2.4130786 | BJ127: 2.4008735 | BK127: 2.3891005 | BL127: 2.3777554 | BM127: 2.3668341 | BN127: 2.3563325 | BO127: 2.3462464 | BP127: 2.3365718 | BQ127: 2.3273045 | BR127: 2.2801088 | BS127: 2.2470582 | BU127: 2.21 | BV127: 2.49 | BW127: 78.9941
A128: =+A123+7 -> 44732 | B128: =MONTH(A128) -> 6 | C128: =YEAR(A128) -> 2022 | D128: =C128*100+B128 -> 202206 | E128: =IF(B128<4,1,IF(B128<7,2,IF(B128<10,3,4))) -> 2 | F128: =C128*100+E128 -> 202202 | G128: 20220620 | H128: 1.25 | I128: 1.1896 | J128: 1.2869813 | K128: 1.6538645 | L128: 2.0259624 | M128: 2.3770059 | N128: 2.683333 | O128: 2.9369203 | P128: 3.13693 | Q128: 3.2892386 | R128: 3.4015725 | S128: 3.4823175 | T128: 3.5369036 | U128: 3.5700365 | V128: 3.5862937 | W128: 3.5882377 | X128: 3.5778975 | Y128: 3.5573023 | Z128: 3.5284812 | AA128: 3.4934634 | AB128: 3.4541094 | AC128: 3.4115718 | AD128: 3.366817 | AE128: 3.3208113 | AF128: 3.2745213 | AG128: 3.2289134 | AH128: 3.1848052 | AI128: 3.1423577 | AJ128: 3.1015509 | AK128: 3.0623645 | AL128: 3.0247783 | AM128: 2.9887721 | AN128: 2.9543259 | AO128: 2.9214194 | AP128: 2.8900324 | AQ128: 2.8601447 | AR128: 2.8317363 | AS128: 2.8047868 | AT128: 2.7792687 | AU128: 2.7551216 | AV128: 2.7322758 | AW128: 2.7106619 | AX128: 2.6902103 | AY128: 2.6708514 | AZ128: 2.6525158 | BA128: 2.6351339 | BB128: 2.6186361 | BC128: 2.602953 | BD128: 2.588015 | BE128: 2.5737525 | BF128: 2.5601032 | BG128: 2.5470436 | BH128: 2.5345631 | BI128: 2.5226512 | BJ128: 2.5112975 | BK128: 2.5004912 | BL128: 2.4902221 | BM128: 2.4804794 | BN128: 2.4712527 | BO128: 2.4625315 | BP128: 2.4543052 | BQ128: 2.4465633 | BR128: 2.4096683 | BS128: 2.3873961 | BU128: 2.29 | BV128: 2.61 | BW128: 79.0981
A129: =+A124+7 -> 44733 | B129: =MONTH(A129) -> 6 | C129: =YEAR(A129) -> 2022 | D129: =C129*100+B129 -> 202206 | E129: =IF(B129<4,1,IF(B129<7,2,IF(B129<10,3,4))) -> 2 | F129: =C129*100+E129 -> 202202 | G129: 20220621 | H129: 1.25 | I129: 1.1892 | J129: 1.295895 | K129: 1.6719695 | L129: 2.0445503 | M129: 2.3873397 | N129: 2.6808982 | O129: 2.9214775 | P129: 3.1106589 | Q129: 3.2554348 | R129: 3.3625317 | S129: 3.4394904 | T129: 3.4913089 | U129: 3.522543 | V129: 3.5381665 | W129: 3.5406946 | X129: 3.5319573 | Y129: 3.5137841 | Z129: 3.4880049 | AA129: 3.4564494 | AB129: 3.4207993 | AC129: 3.3821144 | AD129: 3.3412911 | AE129: 3.2992258 | AF129: 3.2568149 | AG129: 3.2149548 | AH129: 3.1744069 | AI129: 3.1353373 | AJ129: 3.0977474 | AK129: 3.0616388 | AL129: 3.0270131 | AM129: 2.9938717 | AN129: 2.9622164 | AO129: 2.9320485 | AP129: 2.9033698 | AQ129: 2.8761816 | AR129: 2.8504857 | AS129: 2.8262835 | AT129: 2.8035665 | AU129: 2.7822718 | AV129: 2.7623182 | AW129: 2.7436246 | AX129: 2.7261098 | AY129: 2.7096925 | AZ129: 2.6942918 | BA129: 2.6798263 | BB129: 2.6662149 | BC129: 2.6533765 | BD129: 2.6412298 | BE129: 2.6296938 | BF129: 2.6186963 | BG129: 2.6082101 | BH129: 2.5982215 | BI129: 2.5887167 | BJ129: 2.579682 | BK129: 2.5711038 | BL129: 2.5629681 | BM129: 2.5552615 | BN129: 2.54797 | BO129: 2.5410801 | BP129: 2.5345779 | BQ129: 2.5284498 | BR129: 2.4990177 | BS129: 2.4811096 | BU129: 2.32 | BV129: 2.65 | BW129: 79.1835
... A177: =+A172+7 -> 44799 | B177: =MONTH(A177) -> 8 | C177: =YEAR(A177) -> 2022 | D177: =C177*100+B177 -> 202208 | E177: =IF(B177<4,1,IF(B177<7,2,IF(B177<10,3,4))) -> 3 | F177: =C177*100+E177 -> 202203 | G177: 20220826 | H177: 1.75 | I177: 1.6904 | J177: 2.1307672 | K177: 2.525546 | L177: 2.9003487 | M177: 3.237083 | N177: 3.5252007 | O177: 3.7621403 | P177: 3.9470967 | Q177: 4.0808912 | R177: 4.169629 | S177: 4.221027 | T177: 4.24229 | U177: 4.240061 | V177: 4.2207766 | W177: 4.1878332 | X177: 4.1435665 | Y177: 4.0903114 | Z177: 4.0304027 | AA177: 3.9661754 | AB177: 3.8997288 | AC177: 3.8320695 | AD177: 3.7638874 | AE177: 3.6958726 | AF177: 3.6287149 | AG177: 3.5631044 | AH177: 3.4996366 | AI177: 3.438447 | AJ177: 3.3795311 | AK177: 3.3228843 | AL177: 3.2685021 | AM177: 3.2163799 | AN177: 3.1665133 | AO177: 3.1188977 | AP177: 3.0735286 | AQ177: 3.0304013 | AR177: 2.9895114 | AS177: 2.9508544 | AT177: 2.9144106 | AU177: 2.8800943 | AV177: 2.8478014 | AW177: 2.8174276 | AX177: 2.788869 | AY177: 2.7620213 | AZ177: 2.7367805 | BA177: 2.7130425 | BB177: 2.6907032 | BC177: 2.6696583 | BD177: 2.6498039 | BE177: 2.6310357 | BF177: 2.613259 | BG177: 2.59642 | BH177: 2.5804762 | BI177: 2.5653851 | BJ177: 2.5511041 | BK177: 2.5375909 | BL177: 2.5248029 | BM177: 2.5126977 | BN177: 2.5012327 | BO177: 2.4903654 | BP177: 2.4800535 | BQ177: 2.4702544 | BR177: 2.4210576 | BS177: 2.3869467 | BU177: 2.82 | BV177: 2.62 | BW177: 78.4444
A178: =+A173+7 -> 44802 | B178: =MONTH(A178) -> 8 | C178: =YEAR(A178) -> 2022 | D178: =C178*100+B178 -> 202208 | E178: =IF(B178<4,1,IF(B178<7,2,IF(B178<10,3,4))) -> 3 | F178: =C178*100+E178 -> 202203 | G178: 20220829 | H178: 1.75 | I178: #N/A | J178: #N/A | K178: #N/A | L178: #N/A | M178: #N/A | N178: #N/A | O178: #N/A | P178: #N/A | Q178: #N/A | R178: #N/A | S178: #N/A | T178: #N/A | U178: #N/A | V178: #N/A | W178: #N/A | X178: #N/A | Y178: #N/A | Z178: #N/A | AA178: #N/A | AB178: #N/A | AC178: #N/A | AD178: #N/A | AE178: #N/A | AF178: #N/A | AG178: #N/A | AH178: #N/A | AI178: #N/A | AJ178: #N/A | AK178: #N/A | AL178: #N/A | AM178: #N/A | AN178: #N/A | AO178: #N/A | AP178: #N/A | AQ178: #N/A | AR178: #N/A | AS178: #N/A | AT178: #N/A | AU178: #N/A | AV178: #N/A | AW178: #N/A | AX178: #N/A | AY178: #N/A | AZ178: #N/A | BA178: #N/A | BB178: #N/A | BC178: #N/A | BD178: #N/A | BE178: #N/A | BF178: #N/A | BG178: #N/A | BH178: #N/A | BI178: #N/A | BJ178: #N/A | BK178: #N/A | BL178: #N/A | BM178: #N/A | BN178: #N/A | BO178: #N/A | BP178: #N/A | BQ178: #N/A | BR178: #N/A | BS178: #N/A | BU178: 2.8 | BV178: 2.63 | BW178: #N/A
A179: =+A174+7 -> 44803 | B179: =MONTH(A179) -> 8 | C179: =YEAR(A179) -> 2022 | D179: =C179*100+B179 -> 202208 | E179: =IF(B179<4,1,IF(B179<7,2,IF(B179<10,3,4))) -> 3 | F179: =C179*100+E179 -> 202203 | G179: 20220830 | H179: 1.75 | I179: 1.6905 | J179: 2.2512643 | K179: 2.5980412 | L179: 2.980015 | M179: 3.3284794 | N179: 3.6194098 | O179: 3.8532869 | P179: 4.0340543 | Q179: 4.1677619 | R179: 4.2596277 | S179: 4.3165662 | T179: 4.344258 | U179: 4.3480278 | V179: 4.3328335 | W179: 4.3017681 | X179: 4.2574529 | Y179: 4.2025093 | Z179: 4.1395588 | AA179: 4.0712226 | AB179: 3.9998839 | AC179: 3.9268198 | AD179: 3.8529872 | AE179: 3.7793429 | AF179: 3.7068436 | AG179: 3.6364461 | AH179: 3.568952 | AI179: 3.5044773 | AJ179: 3.442949 | AK179: 3.3842942 | AL179: 3.3284397 | AM179: 3.2753126 | AN179: 3.2248398 | AO179: 3.1769483 | AP179: 3.1315651 | AQ179: 3.0886172 | AR179: 3.0480314 | AS179: 3.0097349 | AT179: 2.9736504 | AU179: 2.9396782 | AV179: 2.9077111 | AW179: 2.8776418 | AX179: 2.8493631 | AY179: 2.8227678 | AZ179: 2.7977487 | BA179: 2.7741984 | BB179: 2.7520098 | BC179: 2.7310756 | BD179: 2.7112887 | BE179: 2.6925416 | BF179: 2.6747363 | BG179: 2.6578233 | BH179: 2.6417692 | BI179: 2.6265408 | BJ179: 2.612105 | BK179: 2.5984285 | BL179: 2.5854782 | BM179: 2.5732207 | BN179: 2.5616228 | BO179: 2.5506514 | BP179: 2.5402732 | BQ179: 2.5304551 | BR179: 2.4821844 | BS179: 2.4502333 | BU179: 2.92 | BV179: 2.7 | BW179: 77.624
A180: =+A175+7 -> 44804 | B180: =MONTH(A180) -> 8 | C180: =YEAR(A180) -> 2022 | D180: =C180*100+B180 -> 202208 | E180: =IF(B180<4,1,IF(B180<7,2,IF(B180<10,3,4))) -> 3 | F180: =C180*100+E180 -> 202203 | G180: 20220831 | H180: 1.75 | I180: 1.6896 | J180: 2.2805599 | K180: 2.6090552 | L180: 2.9922317 | M180: 3.3568264 | N180: 3.6636737 | O180: 3.9057465 | P180: 4.0866936 | Q180: 4.2180203 | R180: 4.3074351 | S180: 4.3627472 | T180: 4.3899566 | U180: 4.3945469 | V180: 4.3810059 | W180: 4.3520811 | X180: 4.310123 | Y180: 4.2574821 | Z180: 4.196509 | AA180: 4.1295541 | AB180: 4.0587495 | AC180: 3.9853949 | AD180: 3.9105921 | AE180: 3.8354428 | AF180: 3.7610487 | AG180: 3.6885117 | AH180: 3.6187918 | AI180: 3.5520874 | AJ180: 3.488341 | AK180: 3.4274951 | AL180: 3.3694923 | AM180: 3.314275 | AN180: 3.2617856 | AO180: 3.2119668 | AP180: 3.1647608 | AQ180: 3.1201104 | AR180: 3.0779578 | AS180: 3.0382457 | AT180: 3.000909 | AU180: 2.9658466 | AV180: 2.9329462 | AW180: 2.9020955 | AX180: 2.8731823 | AY180: 2.8460944 | AZ180: 2.8207194 | BA180: 2.7969452 | BB180: 2.7746594 | BC180: 2.7537499 | BD180: 2.7341044 | BE180: 2.7156106 | BF180: 2.6981665 | BG180: 2.6817192 | BH180: 2.6662312 | BI180: 2.6516649 | BJ180: 2.6379825 | BK180: 2.6251465 | BL180: 2.6131191 | BM180: 2.6018627 | BN180: 2.5913398 | BO180: 2.5815125 | BP180: 2.5723433 | BQ180: 2.5637946 | BR180: 2.5240966 | BS180: 2.5013353 | BU180: 3.01 | BV180: 2.79 | BW180: 77.3914
A181: =+A176+7 -> 44805 | B181: =MONTH(A181) -> 9 | C181: =YEAR(A181) -> 2022 | D181: =C181*100+B181 -> 202209 | E181: =IF(B181<4,1,IF(B181<7,2,IF(B181<10,3,4))) -> 3 | F181: =C181*100+E181 -> 202203 | G181: 20220901 | H181: 1.75 | I181: 1.6902 | J181: 2.3391016 | K181: 2.6767396 | L181: 3.0791268 | M181: 3.4496455 | N181: 3.7512841 | O181: 3.9857749 | P181: 4.1588015 | Q181: 4.2814334 | R181: 4.3637235 | S181: 4.4140176 | T181: 4.43877 | U181: 4.4424074 | V181: 4.4287878 | W181: 4.400448 | X181: 4.3595791 | Y181: 4.3083723 | Z181: 4.2490186 | AA181: 4.1837092 | AB181: 4.1144363 | AC181: 4.0424362 | AD181: 3.9687648 | AE181: 3.8944781 | AF181: 3.8206322 | AG181: 3.7482831 | AH181: 3.6783457 | AI181: 3.6110463 | AJ181: 3.5464019 | AK181: 3.4844296 | AL181: 3.4251463 | AM181: 3.3685688 | AN181: 3.3147143 | AO181: 3.2635995 | AP181: 3.2152415 | AQ181: 3.1696572 | AR181: 3.1268636 | AS181: 3.0868775 | AT181: 3.0496934 | AU181: 3.0152059 | AV181: 2.9832819 | AW181: 2.9537885 | AX181: 2.9265927 | AY181: 2.9015616 | AZ181: 2.8785622 | BA181: 2.8574616 | BB181: 2.8381268 | BC181: 2.8204248 | BD181: 2.8042227 | BE181: 2.7893875 | BF181: 2.7757964 | BG181: 2.7633712 | BH181: 2.7520462 | BI181: 2.7417556 | BJ181: 2.7324336 | BK181: 2.7240144 | BL181: 2.7164323 | BM181: 2.7096214 | BN181: 2.7035159 | BO181: 2.6980501 | BP181: 2.6931582 | BQ181: 2.6887743 | BR181: 2.6708329 | BS181: 2.6629498 | BU181: 3.08 | BV181: 2.89 | BW181: 77.2087
A182: =+A177+7 -> 44806 | B182: =MONTH(A182) -> 9 | C182: =YEAR(A182) -> 2022 | D182: =C182*100+B182 -> 202209 | E182: =IF(B182<4,1,IF(B182<7,2,IF(B182<10,3,4))) -> 3 | F182: =C182*100+E182 -> 202203 | G182: 20220902 | H182: 1.75 | I182: 1.6911 | J182: 2.3453346 | K182: 2.677399 | L182: 3.0677292 | M182: 3.4250971 | N182: 3.7176341 | O182: 3.9460644 | P182: 4.114477 | Q182: 4.2330502 | R182: 4.3122607 | S182: 4.3599093 | T182: 4.3819469 | U182: 4.3827804 | V182: 4.3658764 | W182: 4.3338798 | X182: 4.2892222 | Y182: 4.2343351 | Z182: 4.1716499 | AA182: 4.1035981 | AB182: 4.0324035 | AC182: 3.9593267 | AD182: 3.8853491 | AE182: 3.811452 | AF182: 3.7386169 | AG182: 3.6678251 | AH182: 3.5999057 | AI182: 3.5350153 | AJ182: 3.473125 | AK182: 3.4142059 | AL182: 3.3582289 | AM182: 3.3051652 | AN182: 3.2549858 | AO182: 3.2076618 | AP182: 3.1631643 | AQ182: 3.1214642 | AR182: 3.0825327 | AS182: 3.0463409 | AT182: 3.0128399 | AU182: 2.9818928 | AV182: 2.9533387 | AW182: 2.9270166 | AX182: 2.9027654 | AY182: 2.8804241 | AZ182: 2.8598317 | BA182: 2.840827 | BB182: 2.8232492 | BC182: 2.8069371 | BD182: 2.7917298 | BE182: 2.7774661 | BF182: 2.7640062 | BG182: 2.751303 | BH182: 2.739335 | BI182: 2.7280808 | BJ182: 2.7175191 | BK182: 2.7076284 | BL182: 2.6983873 | BM182: 2.6897744 | BN182: 2.6817683 | BO182: 2.6743476 | BP182: 2.6674908 | BQ182: 2.6611766 | BR182: 2.634042 | BS182: 2.6244182 | BU182: 3.15 | BV182: 2.9 | BW182: 77.2203
A183: =+A178+7 -> 44809 | B183: =MONTH(A183) -> 9 | C183: =YEAR(A183) -> 2022 | D183: =C183*100+B183 -> 202209 | E183: =IF(B183<4,1,IF(B183<7,2,IF(B183<10,3,4))) -> 3 | F183: =C183*100+E183 -> 202203 | G183: 20220905 | H183: 1.75 | I183: 1.6907 | J183: 2.4305786 | K183: 2.7879031 | L183: 3.1884029 | M183: 3.5509108 | N183: 3.8448909 | O183: 4.0719369 | P183: 4.2386465 | Q183: 4.355838 | R183: 4.4337045 | S183: 4.4803313 | T183: 4.5019762 | U183: 4.5037636 | V183: 4.489877 | W183: 4.462708 | X183: 4.4242256 | Y183: 4.3763984 | Z183: 4.3211954 | AA183: 4.2605854 | AB183: 4.1963526 | AC183: 4.1295788 | AD183: 4.0611786 | AE183: 3.9920667 | AF183: 3.9231574 | AG183: 3.8553655 | AH183: 3.7894711 | AI183: 3.7256606 | AJ183: 3.663957 | AK183: 3.604383 | AL183: 3.5469614 | AM183: 3.4917151 | AN183: 3.4386667 | AO183: 3.3878391 | AP183: 3.3392552 | AQ183: 3.2929376 | AR183: 3.2489093 | AS183: 3.207193 | AT183: 3.1677926 | AU183: 3.1306291 | AV183: 3.0956002 | AW183: 3.0626039 | AX183: 3.0315382 | AY183: 3.0023008 | AZ183: 2.9747897 | BA183: 2.9489028 | BB183: 2.9245379 | BC183: 2.9015931 | BD183: 2.8799661 | BE183: 2.8595549 | BF183: 2.840265 | BG183: 2.8220436 | BH183: 2.8048516 | BI183: 2.78865 | BJ183: 2.7733998 | BK183: 2.7590619 | BL183: 2.7455975 | BM183: 2.7329674 | BN183: 2.7211326 | BO183: 2.7100542 | BP183: 2.6996931 | BQ183: 2.6900103 | BR183: 2.6447231 | BS183: 2.6186222 | BU183: 3.21 | BV183: 2.94 | BW183: 77.2013
A184: =+A179+7 -> 44810 | B184: =MONTH(A184) -> 9 | C184: =YEAR(A184) -> 2022 | D184: =C184*100+B184 -> 202209 | E184: =IF(B184<4,1,IF(B184<7,2,IF(B184<10,3,4))) -> 3 | F184: =C184*100+E184 -> 202203 | G184: 20220906 | H184: 1.75 | I184: 1.6913 | J184: 2.3854853 | K184: 2.7590265 | L184: 3.1727631 | M184: 3.5446676 | N184: 3.8451339 | O184: 4.0753424 | P184: 4.2408882 | Q184: 4.354635 | R184: 4.4276676 | S184: 4.4702257 | T184: 4.4889624 | U184: 4.489154 | V184: 4.4749801 | W184: 4.4487179 | X184: 4.4122066 | Y184: 4.3672851 | Z184: 4.3157926 | AA184: 4.259568 | AB184: 4.2002749 | AC184: 4.1389076 | AD184: 4.0763015 | AE184: 4.0132919 | AF184: 3.9507141 | AG184: 3.8894033 | AH184: 3.8300688 | AI184: 3.7728635 | AJ184: 3.7177866 | AK184: 3.6648375 | AL184: 3.6140155 | AM184: 3.5653199 | AN184: 3.5187501 | AO184: 3.4743052 | AP184: 3.4319847 | AQ184: 3.3917879 | AR184: 3.353714 | AS184: 3.3177624 | AT184: 3.2839202 | AU184: 3.2521086 | AV184: 3.2222267 | AW184: 3.1941736 | AX184: 3.1678485 | AY184: 3.1431504 | AZ184: 3.1199785 | BA184: 3.098232 | BB184: 3.0778099 | BC184: 3.0586113 | BD184: 3.0405354 | BE184: 3.0234813 | BF184: 3.0073571 | BG184: 2.9921154 | BH184: 2.9777221 | BI184: 2.964143 | BJ184: 2.9513441 | BK184: 2.9392913 | BL184: 2.9279505 | BM184: 2.9172877 | BN184: 2.9072688 | BO184: 2.8978597 | BP184: 2.8890262 | BQ184: 2.8807344 | BR184: 2.841275 | BS184: 2.8177351 | BU184: 3.2 | BV184: 3.09 | BW184: 77.4673
A185: =+A180+7 -> 44811 | B185: =MONTH(A185) -> 9 | C185: =YEAR(A185) -> 2022 | D185: =C185*100+B185 -> 202209 | E185: =IF(B185<4,1,IF(B185<7,2,IF(B185<10,3,4))) -> 3 | F185: =C185*100+E185 -> 202203 | G185: 20220907 | H185: 1.75 | I185: 1.6907 | J185: 2.3453788 | K185: 2.7298868 | L185: 3.1398975 | M185: 3.4925526 | N185: 3.764464 | O185: 3.9670671 | P185: 4.1110432 | Q185: 4.2097703 | R185: 4.273647 | S185: 4.3109105 | T185: 4.3270431 | U185: 4.3262486 | V185: 4.3115845 | W185: 4.2850857 | X185: 4.2485809 | Y185: 4.2038989 | Z185: 4.1528683 | AA185: 4.0973179 | AB185: 4.0389152 | AC185: 3.9787132 | AD185: 3.9176192 | AE185: 3.8565399 | AF185: 3.7963827 | AG185: 3.7380543 | AH185: 3.6823397 | AI185: 3.6293653 | AJ185: 3.5790367 | AK185: 3.5312596 | AL185: 3.4859395 | AM185: 3.4429819 | AN185: 3.4022925 | AO185: 3.3637768 | AP185: 3.3273403 | AQ185: 3.2928887 | AR185: 3.2603274 | AS185: 3.2295621 | AT185: 3.2004985 | AU185: 3.1730439 | AV185: 3.1471057 | AW185: 3.1225915 | AX185: 3.0994089 | AY185: 3.0774653 | AZ185: 3.0566685 | BA185: 3.0369258 | BB185: 3.0181448 | BC185: 3.0002331 | BD185: 2.9830983 | BE185: 2.9666478 | BF185: 2.950802 | BG185: 2.9355375 | BH185: 2.9208464 | BI185: 2.9067211 | BJ185: 2.8931535 | BK185: 2.8801359 | BL185: 2.8676605 | BM185: 2.8557194 | BN185: 2.8443049 | BO185: 2.833409 | BP185: 2.8230239 | BQ185: 2.8131419 | BR185: 2.7641677 | BS185: 2.7325002 | BU185: 3.01 | BV185: 3.01 | BW185: 76.9564
A186: =+A181+7 -> 44812 | B186: =MONTH(A186) -> 9 | C186: =YEAR(A186) -> 2022 | D186: =C186*100+B186 -> 202209 | E186: =IF(B186<4,1,IF(B186<7,2,IF(B186<10,3,4))) -> 3 | F186: =C186*100+E186 -> 202203 | G186: 20220908 | H186: 1.75 | I186: 1.6903 | J186: 2.3710041 | K186: 2.7639244 | L186: 3.1681797 | M186: 3.5130376 | N186: 3.7796313 | O186: 3.9781982 | P186: 4.1191586 | Q186: 4.2154057 | R186: 4.2781238 | S186: 4.3151864 | T186: 4.332694 | U186: 4.334378 | V186: 4.3229134 | W186: 4.3001965 | X186: 4.267947 | Y186: 4.2278847 | Z186: 4.1817294 | AA186: 4.1312006 | AB186: 4.0778666 | AC186: 4.0227186 | AD186: 3.9666106 | AE186: 3.9103966 | AF186: 3.8549305 | AG186: 3.8010661 | AH186: 3.7495319 | AI186: 3.7004436 | AJ186: 3.6537305 | AK186: 3.609322 | AL186: 3.5671475 | AM186: 3.5271363 | AN186: 3.4892177 | AO186: 3.4533211 | AP186: 3.4193758 | AQ186: 3.3873112 | AR186: 3.3570566 | AS186: 3.3285414 | AT186: 3.3016921 | AU186: 3.276423 | AV186: 3.2526451 | AW186: 3.2302693 | AX186: 3.2092065 | AY186: 3.1893677 | AZ186: 3.1706638 | BA186: 3.1530057 | BB186: 3.1363043 | BC186: 3.1204706 | BD186: 3.1054156 | BE186: 3.09105 | BF186: 3.0772965 | BG186: 3.0641284 | BH186: 3.0515332 | BI186: 3.0394984 | BJ186: 3.0280114 | BK186: 3.0170596 | BL186: 3.0066307 | BM186: 2.9967119 | BN186: 2.9872909 | BO186: 2.978355 | BP186: 2.9698917 | BQ186: 2.9618885 | BR186: 2.9231061 | BS186: 2.8994071 | BU186: 3.07 | BV186: 3.16 | BW186: 77.0236
A187: =+A182+7 -> 44813 | B187: =MONTH(A187) -> 9 | C187: =YEAR(A187) -> 2022 | D187: =C187*100+B187 -> 202209 | E187: =IF(B187<4,1,IF(B187<7,2,IF(B187<10,3,4))) -> 3 | F187: =C187*100+E187 -> 202203 | G187: 20220909 | H187: 1.75 | I187: 1.6919 | J187: 2.4108963 | K187: 2.7875587 | L187: 3.190057 | M187: 3.538078 | N187: 3.806347 | O187: 4.0022023 | P187: 4.1369298 | Q187: 4.2249551 | R187: 4.2786858 | S187: 4.3067739 | T187: 4.3153832 | U187: 4.3085544 | V187: 4.2894183 | W187: 4.260011 | X187: 4.2220553 | Y187: 4.177274 | Z187: 4.1273896 | AA187: 4.0741249 | AB187: 4.0190517 | AC187: 3.9630418 | AD187: 3.9067642 | AE187: 3.8508877 | AF187: 3.7960815 | AG187: 3.7430144 | AH187: 3.692244 | AI187: 3.6438371 | AJ187: 3.5977244 | AK187: 3.5538372 | AL187: 3.5121063 | AM187: 3.4724629 | AN187: 3.4348379 | AO187: 3.3991624 | AP187: 3.3653673 | AQ187: 3.3333837 | AR187: 3.3031427 | AS187: 3.2745752 | AT187: 3.2476103 | AU187: 3.2221686 | AV187: 3.1981683 | AW187: 3.1755275 | AX187: 3.1541646 | AY187: 3.1339977 | AZ187: 3.1149451 | BA187: 3.0969248 | BB187: 3.0798553 | BC187: 3.0636545 | BD187: 3.0482409 | BE187: 3.0335325 | BF187: 3.0194578 | BG187: 3.0059906 | BH187: 2.993117 | BI187: 2.9808233 | BJ187: 2.9690957 | BK187: 2.9579203 | BL187: 2.9472835 | BM187: 2.9371713 | BN187: 2.9275701 | BO187: 2.9184659 | BP187: 2.9098451 | BQ187: 2.9016938 | BR187: 2.8622532 | BS187: 2.8385413 | BU187: 3.06 | BV187: 3.1 | BW187: 77.1689
A188: =+A183+7 -> 44816 | B188: =MONTH(A188) -> 9 | C188: =YEAR(A188) -> 2022 | D188: =C188*100+B188 -> 202209 | E188: =IF(B188<4,1,IF(B188<7,2,IF(B188<10,3,4))) -> 3 | F188: =C188*100+E188 -> 202203 | G188: 20220912 | H188: 1.75 | I188: 1.6911 | J188: 2.4241439 | K188: 2.8139017 | L188: 3.2123365 | M188: 3.5563314 | N188: 3.8200604 | O188: 4.0103346 | P188: 4.1389467 | Q188: 4.220883 | R188: 4.269015 | S188: 4.292493 | T188: 4.2977946 | U188: 4.2896214 | V188: 4.2714891 | W188: 4.2450676 | X188: 4.2115989 | Y188: 4.1723252 | Z188: 4.1284888 | AA188: 4.0813318 | AB188: 4.0319766 | AC188: 3.9810894 | AD188: 3.9292278 | AE188: 3.8769495 | AF188: 3.8248121 | AG188: 3.7733733 | AH188: 3.7231118 | AI188: 3.6741581 | AJ188: 3.6265466 | AK188: 3.5803117 | AL188: 3.5354878 | AM188: 3.4921093 | AN188: 3.4502106 | AO188: 3.409826 | AP188: 3.3709899 | AQ188: 3.3337368 | AR188: 3.298101 | AS188: 3.264117 | AT188: 3.2318046 | AU188: 3.2011201 | AV188: 3.1720022 | AW188: 3.1443895 | AX188: 3.1182206 | AY188: 3.0934342 | AZ188: 3.0699689 | BA188: 3.0477634 | BB188: 3.0267564 | BC188: 3.0068863 | BD188: 2.988092 | BE188: 2.9703121 | BF188: 2.953489 | BG188: 2.937586 | BH188: 2.9225735 | BI188: 2.9084217 | BJ188: 2.8951008 | BK188: 2.8825812 | BL188: 2.8708332 | BM188: 2.8598269 | BN188: 2.8495326 | BO188: 2.8399207 | BP188: 2.8309614 | BQ188: 2.822625 | BR188: 2.784566 | BS188: 2.7647735 | BU188: 3.03 | BV188: 3.07 | BW188: 77.5887
A189: =+A184+7 -> 44817 | B189: =MONTH(A189) -> 9 | C189: =YEAR(A189) -> 2022 | D189: =C189*100+B189 -> 202209 | E189: =IF(B189<4,1,IF(B189<7,2,IF(B189<10,3,4))) -> 3 | F189: =C189*100+E189 -> 202203 | G189: 20220913 | H189: 1.75 | I189: 1.6911 | J189: 2.452919 | K189: 2.8758087 | L189: 3.3074061 | M189: 3.6785596 | N189: 3.9601805 | O189: 4.1606145 | P189: 4.2938443 | Q189: 4.3781465 | R189: 4.4272715 | S189: 4.4521305 | T189: 4.4593205 | U189: 4.4533227 | V189: 4.4370052 | W189: 4.4118905 | X189: 4.3792396 | Y189: 4.3403135 | Z189: 4.296373 | AA189: 4.2486792 | AB189: 4.1983817 | AC189: 4.1462078 | AD189: 4.0927835 | AE189: 4.0387354 | AF189: 3.9846897 | AG189: 3.9312727 | AH189: 3.8790224 | AI189: 3.8280862 | AJ189: 3.7785041 | AK189: 3.7303159 | AL189: 3.6835614 | AM189: 3.6382805 | AN189: 3.594513 | AO189: 3.5522987 | AP189: 3.5116775 | AQ189: 3.4726893 | AR189: 3.4353738 | AS189: 3.399771 | AT189: 3.3659072 | AU189: 3.3337366 | AV189: 3.3031893 | AW189: 3.2741952 | AX189: 3.2466843 | AY189: 3.2205865 | AZ189: 3.1958319 | BA189: 3.1723503 | BB189: 3.1500719 | BC189: 3.1289264 | BD189: 3.108844 | BE189: 3.0897546 | BF189: 3.0715938 | BG189: 3.054325 | BH189: 3.0379199 | BI189: 3.0223503 | BJ189: 3.007588 | BK189: 2.9936047 | BL189: 2.9803722 | BM189: 2.9678622 | BN189: 2.9560465 | BO189: 2.9448968 | BP189: 2.934385 | BQ189: 2.9244828 | BR189: 2.8769015 | BS189: 2.8478621 | BU189: 3.19 | BV189: 3.17 | BW189: 77.0696
A190: =+A185+7 -> 44818 | B190: =MONTH(A190) -> 9 | C190: =YEAR(A190) -> 2022 | D190: =C190*100+B190 -> 202209 | E190: =IF(B190<4,1,IF(B190<7,2,IF(B190<10,3,4))) -> 3 | F190: =C190*100+E190 -> 202203 | G190: 20220914 | H190: 1.75 | I190: 1.6914 | J190: 2.4626598 | K190: 2.8876393 | L190: 3.3135793 | M190: 3.6777275 | N190: 3.9525927 | O190: 4.1495668 | P190: 4.2818655 | Q190: 4.3662257 | R190: 4.4159667 | S190: 4.4411484 | T190: 4.4481216 | U190: 4.4411437 | V190: 4.4228691 | W190: 4.3949409 | X190: 4.3588195 | Y190: 4.3159653 | Z190: 4.2678386 | AA190: 4.2158997 | AB190: 4.1614831 | AC190: 4.105444 | AD190: 4.0485238 | AE190: 3.9914636 | AF190: 3.9350047 | AG190: 3.8798884 | AH190: 3.8267588 | AI190: 3.7757374 | AJ190: 3.7267703 | AK190: 3.6798036 | AL190: 3.6347834 | AM190: 3.5916557 | AN190: 3.5503665 | AO190: 3.5108619 | AP190: 3.4730881 | AQ190: 3.4369909 | AR190: 3.4025165 | AS190: 3.369611 | AT190: 3.3382185 | AU190: 3.3082743 | AV190: 3.2797106 | AW190: 3.2524601 | AX190: 3.2264551 | AY190: 3.201628 | AZ190: 3.1779113 | BA190: 3.1552375 | BB190: 3.1335389 | BC190: 3.1127479 | BD190: 3.0927971 | BE190: 3.0736188 | BF190: 3.0551542 | BG190: 3.0373828 | BH190: 3.0202947 | BI190: 3.00388 | BJ190: 2.9881289 | BK190: 2.9730315 | BL190: 2.958578 | BM190: 2.9447583 | BN190: 2.9315627 | BO190: 2.9189813 | BP190: 2.9070042 | BQ190: 2.8956216 | BR190: 2.8393182 | BS190: 2.8023066 | BU190: 3.16 | BV190: 3.14 | BW190: 77.4137
... A192: =+A187+7 -> 44820 | B192: =MONTH(A192) -> 9 | C192: =YEAR(A192) -> 2022 | D192: =C192*100+B192 -> 202209 | E192: =IF(B192<4,1,IF(B192<7,2,IF(B192<10,3,4))) -> 3 | F192: =C192*100+E192 -> 202203 | G192: 20220916 | H192: 1.75 | I192: 1.6906 | J192: 2.4153754 | K192: 2.8617572 | L192: 3.2999782 | M192: 3.6750913 | N192: 3.964459 | O192: 4.1779542 | P192: 4.328078 | Q192: 4.4289629 | R192: 4.4929733 | S192: 4.5290158 | T192: 4.543762 | U192: 4.5418024 | V192: 4.5261793 | W192: 4.4989614 | X192: 4.461995 | Y192: 4.4171264 | Z192: 4.3662018 | AA192: 4.3110674 | AB192: 4.2534068 | AC192: 4.1941487 | AD192: 4.134003 | AE192: 4.0736797 | AF192: 4.0138888 | AG192: 3.9553403 | AH192: 3.8986339 | AI192: 3.8438832 | AJ192: 3.7910674 | AK192: 3.7401658 | AL192: 3.6911577 | AM192: 3.6440222 | AN192: 3.5987388 | AO192: 3.5552867 | AP192: 3.5136451 | AQ192: 3.4737933 | AR192: 3.4357106 | AS192: 3.3993762 | AT192: 3.3647617 | AU192: 3.3318042 | AV192: 3.3004314 | AW192: 3.2705709 | AX192: 3.2421504 | AY192: 3.2150975 | AZ192: 3.1893399 | BA192: 3.1648053 | BB192: 3.1414213 | BC192: 3.1191157 | BD192: 3.0978159 | BE192: 3.0774499 | BF192: 3.0579523 | BG192: 3.0392903 | BH192: 3.0214397 | BI192: 3.0043763 | BJ192: 2.988076 | BK192: 2.9725145 | BL192: 2.9576678 | BM192: 2.9435116 | BN192: 2.9300218 | BO192: 2.9171743 | BP192: 2.9049448 | BQ192: 2.8933092 | BR192: 2.8351503 | BS192: 2.7955316 | BU192: 3.2 | BV192: 3.14 | BW192: 76.439
A193: =+A188+7 -> 44823 | B193: =MONTH(A193) -> 9 | C193: =YEAR(A193) -> 2022 | D193: =C193*100+B193 -> 202209 | E193: =IF(B193<4,1,IF(B193<7,2,IF(B193<10,3,4))) -> 3 | F193: =C193*100+E193 -> 202203 | G193: 20220919 | H193: 1.75 | I193: #N/A | J193: #N/A | K193: #N/A | L193: #N/A | M193: #N/A | N193: #N/A | O193: #N/A | P193: #N/A | Q193: #N/A | R193: #N/A | S193: #N/A | T193: #N/A | U193: #N/A | V193: #N/A | W193: #N/A | X193: #N/A | Y193: #N/A | Z193: #N/A | AA193: #N/A | AB193: #N/A | AC193: #N/A | AD193: #N/A | AE193: #N/A | AF193: #N/A | AG193: #N/A | AH193: #N/A | AI193: #N/A | AJ193: #N/A | AK193: #N/A | AL193: #N/A | AM193: #N/A | AN193: #N/A | AO193: #N/A | AP193: #N/A | AQ193: #N/A | AR193: #N/A | AS193: #N/A | AT193: #N/A | AU193: #N/A | AV193: #N/A | AW193: #N/A | AX193: #N/A | AY193: #N/A | AZ193: #N/A | BA193: #N/A | BB193: #N/A | BC193: #N/A | BD193: #N/A | BE193: #N/A | BF193: #N/A | BG193: #N/A | BH193: #N/A | BI193: #N/A | BJ193: #N/A | BK193: #N/A | BL193: #N/A | BM193: #N/A | BN193: #N/A | BO193: #N/A | BP193: #N/A | BQ193: #N/A | BR193: #N/A | BS193: #N/A | BU193: 3.11 | BV193: 3.16 | BW193: #N/A
A194: =+A189+7 -> 44824 | B194: =MONTH(A194) -> 9 | C194: =YEAR(A194) -> 2022 | D194: =C194*100+B194 -> 202209 | E194: =IF(B194<4,1,IF(B194<7,2,IF(B194<10,3,4))) -> 3 | F194: =C194*100+E194 -> 202203 | G194: 20220920 | H194: 1.75 | I194: 1.691 | J194: 2.4845554 | K194: 2.9832903 | L194: 3.4486857 | M194: 3.8418095 | N194: 4.1487732 | O194: 4.3787939 | P194: 4.5421284 | Q194: 4.6528761 | R194: 4.7231529 | S194: 4.7642504 | T194: 4.7835693 | U194: 4.7863708 | V194: 4.7758887 | W194: 4.7539709 | X194: 4.722223 | Y194: 4.6822506 | Z194: 4.6356591 | AA194: 4.5840543 | AB194: 4.5289046 | AC194: 4.4711569 | AD194: 4.4116338 | AE194: 4.351158 | AF194: 4.2905521 | AG194: 4.2306388 | AH194: 4.1721189 | AI194: 4.1151559 | AJ194: 4.059765 | AK194: 4.0059612 | AL194: 3.9537596 | AM194: 3.9031754 | AN194: 3.8542238 | AO194: 3.8069197 | AP194: 3.7612783 | AQ194: 3.7173148 | AR194: 3.6750442 | AS194: 3.6344818 | AT194: 3.5956322 | AU194: 3.558445 | AV194: 3.522851 | AW194: 3.4887809 | AX194: 3.4561657 | AY194: 3.4249361 | AZ194: 3.3950229 | BA194: 3.3663571 | BB194: 3.3388694 | BC194: 3.3124906 | BD194: 3.2871516 | BE194: 3.2627832 | BF194: 3.2393239 | BG194: 3.2167494 | BH194: 3.1950469 | BI194: 3.1742035 | BJ194: 3.1542064 | BK194: 3.1350427 | BL194: 3.1166996 | BM194: 3.0991641 | BN194: 3.0824234 | BO194: 3.0664646 | BP194: 3.051275 | BQ194: 3.0368416 | BR194: 2.9653849 | BS194: 2.9178116 | BU194: 3.29 | BV194: 3.29 | BW194: 76.5018
A195: =+A190+7 -> 44825 | B195: =MONTH(A195) -> 9 | C195: =YEAR(A195) -> 2022 | D195: =C195*100+B195 -> 202209 | E195: =IF(B195<4,1,IF(B195<7,2,IF(B195<10,3,4))) -> 3 | F195: =C195*100+E195 -> 202203 | G195: 20220921 | H195: 1.75 | I195: 1.6903 | J195: 2.5123928 | K195: 3.0032396 | L195: 3.4590484 | M195: 3.8513215 | N195: 4.1649374 | O195: 4.4073423 | P195: 4.5862323 | Q195: 4.7137694 | R195: 4.8013672 | S195: 4.8590453 | T195: 4.893641 | U195: 4.9099017 | V195: 4.910482 | W195: 4.8972677 | X195: 4.8720582 | Y195: 4.8366528 | Z195: 4.792851 | AA195: 4.7424523 | AB195: 4.6871229 | AC195: 4.6280223 | AD195: 4.5661895 | AE195: 4.5026633 | AF195: 4.4384827 | AG195: 4.3746867 | AH195: 4.3121899 | AI195: 4.2512385 | AJ195: 4.1918546 | AK195: 4.13406 | AL195: 4.0778766 | AM195: 4.0233262 | AN195: 3.9704308 | AO195: 3.9192122 | AP195: 3.8696922 | AQ195: 3.8218928 | AR195: 3.7758358 | AS195: 3.7315431 | AT195: 3.6890236 | AU195: 3.6482241 | AV195: 3.6090719 | AW195: 3.5714947 | AX195: 3.5354199 | AY195: 3.500775 | AZ195: 3.4674877 | BA195: 3.4354854 | BB195: 3.4046956 | BC195: 3.3750459 | BD195: 3.3464638 | BE195: 3.3188768 | BF195: 3.2922209 | BG195: 3.2664696 | BH195: 3.2416067 | BI195: 3.2176158 | BJ195: 3.1944808 | BK195: 3.1721855 | BL195: 3.1507136 | BM195: 3.1300489 | BN195: 3.1101751 | BO195: 3.0910761 | BP195: 3.0727356 | BQ195: 3.0551373 | BR195: 2.9645709 | BS195: 2.898724 | BU195: 3.46 | BV195: 3.31 | BW195: 76.4813
A196: =+A191+7 -> 44826 | B196: =MONTH(A196) -> 9 | C196: =YEAR(A196) -> 2022 | D196: =C196*100+B196 -> 202209 | E196: =IF(B196<4,1,IF(B196<7,2,IF(B196<10,3,4))) -> 3 | F196: =C196*100+E196 -> 202203 | G196: 20220922 | H196: 2.25 | I196: 2.1876 | J196: 2.3383378 | K196: 2.8574992 | L196: 3.3440895 | M196: 3.773375 | N196: 4.125186 | O196: 4.398563 | P196: 4.597924 | Q196: 4.7376679 | R196: 4.8352859 | S196: 4.9032601 | T196: 4.9497955 | U196: 4.9789781 | V196: 4.9929353 | W196: 4.9932474 | X196: 4.9814157 | Y196: 4.9589417 | Z196: 4.9273267 | AA196: 4.8880721 | AB196: 4.842612 | AC196: 4.7921239 | AD196: 4.7377239 | AE196: 4.6805287 | AF196: 4.6216544 | AG196: 4.5622175 | AH196: 4.5031963 | AI196: 4.4448962 | AJ196: 4.3874178 | AK196: 4.3308616 | AL196: 4.2753284 | AM196: 4.2209187 | AN196: 4.167733 | AO196: 4.115872 | AP196: 4.0654363 | AQ196: 4.0165264 | AR196: 3.9692429 | AS196: 3.9236865 | AT196: 3.8799318 | AU196: 3.8379398 | AV196: 3.7976397 | AW196: 3.7589608 | AX196: 3.7218326 | AY196: 3.6861842 | AZ196: 3.6519452 | BA196: 3.6190447 | BB196: 3.5874122 | BC196: 3.556977 | BD196: 3.5276683 | BE196: 3.4994156 | BF196: 3.4721556 | BG196: 3.4458574 | BH196: 3.4204992 | BI196: 3.3960592 | BJ196: 3.3725155 | BK196: 3.3498463 | BL196: 3.3280298 | BM196: 3.307044 | BN196: 3.2868673 | BO196: 3.2674777 | BP196: 3.2488535 | BQ196: 3.2309727 | BR196: 3.1385595 | BS196: 3.0703303 | BU196: 3.59 | BV196: 3.5 | BW196: 76.3668
A197: =+A192+7 -> 44827 | B197: =MONTH(A197) -> 9 | C197: =YEAR(A197) -> 2022 | D197: =C197*100+B197 -> 202209 | E197: =IF(B197<4,1,IF(B197<7,2,IF(B197<10,3,4))) -> 3 | F197: =C197*100+E197 -> 202203 | G197: 20220923 | H197: 2.25 | I197: 2.1884 | J197: 2.6932767 | K197: 3.3747378 | L197: 3.9864644 | M197: 4.4918003 | N197: 4.8725669 | O197: 5.1377185 | P197: 5.3056273 | Q197: 5.4058465 | R197: 5.4664312 | S197: 5.506507 | T197: 5.5369024 | U197: 5.5600971 | V197: 5.5730539 | W197: 5.5750173 | X197: 5.5662688 | Y197: 5.5470902 | Z197: 5.517763 | AA197: 5.4785691 | AB197: 5.4299692 | AC197: 5.3732544 | AD197: 5.3099564 | AE197: 5.2416071 | AF197: 5.1697382 | AG197: 5.0958816 | AH197: 5.0213864 | AI197: 4.9467964 | AJ197: 4.8724331 | AK197: 4.7986179 | AL197: 4.7256722 | AM197: 4.6539174 | AN197: 4.583675 | AO197: 4.5152664 | AP197: 4.4490131 | AQ197: 4.3852364 | AR197: 4.3242579 | AS197: 4.2663989 | AT197: 4.2119005 | AU197: 4.1606487 | AV197: 4.1124316 | AW197: 4.0670374 | AX197: 4.0242542 | AY197: 3.98387 | AZ197: 3.945673 | BA197: 3.9094513 | BB197: 3.874993 | BC197: 3.8420863 | BD197: 3.8105191 | BE197: 3.7800797 | BF197: 3.7505812 | BG197: 3.7219479 | BH197: 3.6941343 | BI197: 3.6670954 | BJ197: 3.6407859 | BK197: 3.6151604 | BL197: 3.5901737 | BM197: 3.5657806 | BN197: 3.5419357 | BO197: 3.518594 | BP197: 3.49571 | BQ197: 3.4732386 | BR197: 3.3471974 | BS197: 3.2407313 | BU197: 3.91 | BV197: 3.81 | BW197: 74.4051
A198: =+A193+7 -> 44830 | B198: =MONTH(A198) -> 9 | C198: =YEAR(A198) -> 2022 | D198: =C198*100+B198 -> 202209 | E198: =IF(B198<4,1,IF(B198<7,2,IF(B198<10,3,4))) -> 3 | F198: =C198*100+E198 -> 202203 | G198: 20220926 | H198: 2.25 | I198: 2.189 | J198: 2.8262419 | K198: 3.7180041 | L198: 4.4254044 | M198: 4.9538191 | N198: 5.3389484 | O198: 5.6112839 | P198: 5.7950331 | Q198: 5.916904 | R198: 6.0000732 | S198: 6.0594093 | T198: 6.1027482 | U198: 6.1334689 | V198: 6.1523266 | W198: 6.1596949 | X198: 6.1560132 | Y198: 6.1417207 | Z198: 6.1172569 | AA198: 6.0830609 | AB198: 6.0397003 | AC198: 5.9882308 | AD198: 5.9298242 | AE198: 5.8656523 | AF198: 5.7968869 | AG198: 5.7246999 | AH198: 5.6501468 | AI198: 5.5737704 | AJ198: 5.4959719 | AK198: 5.4171524 | AL198: 5.3377132 | AM198: 5.2580554 | AN198: 5.1785802 | AO198: 5.0996889 | AP198: 5.0217825 | AQ198: 4.9452623 | AR198: 4.8705295 | AS198: 4.7979852 | AT198: 4.7279638 | AU198: 4.6605044 | AV198: 4.5955649 | AW198: 4.5331029 | AX198: 4.4730762 | AY198: 4.4154426 | AZ198: 4.3601598 | BA198: 4.3071854 | BB198: 4.2564774 | BC198: 4.2079934 | BD198: 4.1616911 | BE198: 4.1175284 | BF198: 4.0754604 | BG198: 4.0354283 | BH198: 3.997369 | BI198: 3.9612191 | BJ198: 3.9269153 | BK198: 3.8943943 | BL198: 3.8635927 | BM198: 3.8344473 | BN198: 3.8068948 | BO198: 3.7808718 | BP198: 3.756315 | BQ198: 3.7331612 | BR198: 3.620835 | BS198: 3.5472372 | BU198: 4.49 | BV198: 4.24 | BW198: 73.9918
A199: =+A194+7 -> 44831 | B199: =MONTH(A199) -> 9 | C199: =YEAR(A199) -> 2022 | D199: =C199*100+B199 -> 202209 | E199: =IF(B199<4,1,IF(B199<7,2,IF(B199<10,3,4))) -> 3 | F199: =C199*100+E199 -> 202203 | G199: 20220927 | H199: 2.25 | I199: 2.189 | J199: 2.8611434 | K199: 3.8979428 | L199: 4.6988387 | M199: 5.2739187 | N199: 5.6717313 | O199: 5.9390587 | P199: 6.1094321 | Q199: 6.2155377 | R199: 6.2817077 | S199: 6.3257992 | T199: 6.356979 | U199: 6.3790063 | V199: 6.3904192 | W199: 6.3909165 | X199: 6.3808693 | Y199: 6.3606485 | Z199: 6.3306253 | AA199: 6.2911707 | AB199: 6.242861 | AC199: 6.1870538 | AD199: 6.1252927 | AE199: 6.0591214 | AF199: 5.9900835 | AG199: 5.9197226 | AH199: 5.8493683 | AI199: 5.7794062 | AJ199: 5.7099611 | AK199: 5.6411579 | AL199: 5.5731215 | AM199: 5.5059769 | AN199: 5.4398488 | AO199: 5.3748623 | AP199: 5.3111421 | AQ199: 5.2488133 | AR199: 5.1880006 | AS199: 5.128829 | AT199: 5.0713993 | AU199: 5.0156831 | AV199: 4.9616084 | AW199: 4.9091032 | AX199: 4.8580957 | AY199: 4.8085139 | AZ199: 4.7602858 | BA199: 4.7133395 | BB199: 4.6676031 | BC199: 4.6230045 | BD199: 4.579472 | BE199: 4.5369335 | BF199: 4.4953291 | BG199: 4.4546569 | BH199: 4.4149328 | BI199: 4.3761728 | BJ199: 4.3383928 | BK199: 4.3016088 | BL199: 4.2658366 | BM199: 4.2310921 | BN199: 4.1973913 | BO199: 4.1647501 | BP199: 4.1331844 | BQ199: 4.1027101 | BR199: 3.9430763 | BS199: 3.823108 | BU199: 4.72 | BV199: 4.48 | BW199: 74.0226
A200: =+A195+7 -> 44832 | B200: =MONTH(A200) -> 9 | C200: =YEAR(A200) -> 2022 | D200: =C200*100+B200 -> 202209 | E200: =IF(B200<4,1,IF(B200<7,2,IF(B200<10,3,4))) -> 3 | F200: =C200*100+E200 -> 202203 | G200: 20220928 | H200: 2.25 | I200: 2.1891 | J200: 2.9106783 | K200: 3.8366736 | L200: 4.5175888 | M200: 5.0021632 | N200: 5.3415798 | O200: 5.5720949 | P200: 5.71454 | Q200: 5.7936422 | R200: 5.83103 | S200: 5.8445221 | T200: 5.8448631 | U200: 5.83763 | V200: 5.8248705 | W200: 5.8069022 | X200: 5.7837767 | Y200: 5.7555453 | Z200: 5.7222595 | AA200: 5.6839708 | AB200: 5.6408385 | AC200: 5.5934334 | AD200: 5.542424 | AE200: 5.488479 | AF200: 5.4322668 | AG200: 5.374456 | AH200: 5.3156568 | AI200: 5.2561643 | AJ200: 5.196168 | AK200: 5.1358576 | AL200: 5.0754224 | AM200: 5.0150522 | AN200: 4.9549362 | AO200: 4.8952642 | AP200: 4.8362256 | AQ200: 4.7780099 | AR200: 4.7208066 | AS200: 4.6648053 | AT200: 4.6101667 | AU200: 4.556911 | AV200: 4.5050156 | AW200: 4.454458 | AX200: 4.4052158 | AY200: 4.3572662 | AZ200: 4.3105869 | BA200: 4.2651553 | BB200: 4.2209488 | BC200: 4.1779449 | BD200: 4.1361211 | BE200: 4.0954548 | BF200: 4.0559256 | BG200: 4.0175225 | BH200: 3.980237 | BI200: 3.9440606 | BJ200: 3.9089849 | BK200: 3.8750014 | BL200: 3.8421016 | BM200: 3.810277 | BN200: 3.7795192 | BO200: 3.7498197 | BP200: 3.7211701 | BQ200: 3.6935619 | BR200: 3.5492045 | BS200: 3.4395812 | BU200: 4.29 | BV200: 4.01 | BW200: 73.9156
A201: =+A196+7 -> 44833 | B201: =MONTH(A201) -> 9 | C201: =YEAR(A201) -> 2022 | D201: =C201*100+B201 -> 202209 | E201: =IF(B201<4,1,IF(B201<7,2,IF(B201<10,3,4))) -> 3 | F201: =C201*100+E201 -> 202203 | G201: 20220929 | H201: 2.25 | I201: 2.189 | J201: 2.7583712 | K201: 3.7659011 | L201: 4.4821839 | M201: 4.9719204 | N201: 5.3064059 | O201: 5.5336301 | P201: 5.6826183 | Q201: 5.7764894 | R201: 5.8311378 | S201: 5.85989 | T201: 5.8730844 | U201: 5.8765906 | V201: 5.8734352 | W201: 5.8641509 | X201: 5.8487247 | Y201: 5.8271437 | Z201: 5.799395 | AA201: 5.7654658 | AB201: 5.7254541 | AC201: 5.6800884 | AD201: 5.6303184 | AE201: 5.5770941 | AF201: 5.5213656 | AG201: 5.4640828 | AH201: 5.4060941 | AI201: 5.3477515 | AJ201: 5.2892561 | AK201: 5.230809 | AL201: 5.1726112 | AM201: 5.1148639 | AN201: 5.0577682 | AO201: 5.001525 | AP201: 4.9463355 | AQ201: 4.8924008 | AR201: 4.839922 | AS201: 4.7891001 | AT201: 4.7400961 | AU201: 4.6928938 | AV201: 4.6474284 | AW201: 4.6036347 | AX201: 4.5614478 | AY201: 4.5208028 | AZ201: 4.4816345 | BA201: 4.4438781 | BB201: 4.4074686 | BC201: 4.3723409 | BD201: 4.3384301 | BE201: 4.3056712 | BF201: 4.2740053 | BG201: 4.243401 | BH201: 4.213834 | BI201: 4.1852805 | BJ201: 4.1577164 | BK201: 4.1311176 | BL201: 4.10546 | BM201: 4.0807197 | BN201: 4.0568725 | BO201: 4.0338945 | BP201: 4.0117616 | BQ201: 3.9904496 | BR201: 3.8789285 | BS201: 3.793667 | BU201: 4.35 | BV201: 4.21 | BW201: 75.3309
A202: =+A197+7 -> 44834 | B202: =MONTH(A202) -> 9 | C202: =YEAR(A202) -> 2022 | D202: =C202*100+B202 -> 202209 | E202: =IF(B202<4,1,IF(B202<7,2,IF(B202<10,3,4))) -> 3 | F202: =C202*100+E202 -> 202203 | G202: 20220930 | H202: 2.25 | I202: 2.1901 | J202: 2.6910518 | K202: 3.6736921 | L202: 4.4164265 | M202: 4.9471792 | N202: 5.3043648 | O202: 5.5308589 | P202: 5.6671618 | Q202: 5.7434154 | R202: 5.7832101 | S202: 5.8042088 | T202: 5.8168847 | U202: 5.8254408 | V202: 5.8283277 | W202: 5.8249651 | X202: 5.8154892 | Y202: 5.8000361 | Z202: 5.778742 | AA202: 5.7517431 | AB202: 5.7192664 | AC202: 5.6820039 | AD202: 5.6407962 | AE202: 5.5964841 | AF202: 5.549908 | AG202: 5.5019088 | AH202: 5.4532179 | AI202: 5.4040847 | AJ202: 5.3546258 | AK202: 5.3049577 | AL202: 5.255197 | AM202: 5.20546 | AN202: 5.1558634 | AO202: 5.1065235 | AP202: 5.0575571 | AQ202: 5.0090804 | AR202: 4.9612101 | AS202: 4.9140627 | AT202: 4.8677359 | AU202: 4.8222444 | AV202: 4.7775801 | AW202: 4.7337349 | AX202: 4.6907006 | AY202: 4.6484692 | AZ202: 4.6070325 | BA202: 4.5663823 | BB202: 4.5265106 | BC202: 4.4874092 | BD202: 4.44907 | BE202: 4.4114848 | BF202: 4.3746487 | BG202: 4.3385705 | BH202: 4.3032627 | BI202: 4.268738 | BJ202: 4.2350089 | BK202: 4.2020881 | BL202: 4.1699882 | BM202: 4.1387217 | BN202: 4.1083013 | BO202: 4.0787397 | BP202: 4.0500492 | BQ202: 4.0222427 | BR202: 3.8740984 | BS202: 3.7574768 | BU202: 4.29 | BV202: 4.08 | BW202: 75.9815
A203: =+A198+7 -> 44837 | B203: =MONTH(A203) -> 10 | C203: =YEAR(A203) -> 2022 | D203: =C203*100+B203 -> 202210 | E203: =IF(B203<4,1,IF(B203<7,2,IF(B203<10,3,4))) -> 4 | F203: =C203*100+E203 -> 202204 | G203: 20221003 | H203: 2.25 | I203: 2.188 | J203: 2.6720747 | K203: 3.573402 | L203: 4.2401582 | M203: 4.7143722 | N203: 5.0524634 | O203: 5.2820546 | P203: 5.4255134 | Q203: 5.5061795 | R203: 5.5451088 | S203: 5.560346 | T203: 5.5629842 | U203: 5.5590138 | V203: 5.5504295 | W203: 5.5375973 | X203: 5.5206954 | Y203: 5.4999021 | Z203: 5.4753957 | AA203: 5.4473545 | AB203: 5.4160037 | AC203: 5.3817666 | AD203: 5.3451182 | AE203: 5.3065336 | AF203: 5.266488 | AG203: 5.2254564 | AH203: 5.1838526 | AI203: 5.1418198 | AJ203: 5.0994269 | AK203: 5.0567423 | AL203: 5.0138347 | AM203: 4.9707727 | AN203: 4.927625 | AO203: 4.8844602 | AP203: 4.8413469 | AQ203: 4.7983538 | AR203: 4.7555494 | AS203: 4.7130026 | AT203: 4.670777 | AU203: 4.6289159 | AV203: 4.5874566 | AW203: 4.5464365 | AX203: 4.5058929 | AY203: 4.4658632 | AZ203: 4.4263847 | BA203: 4.3874949 | BB203: 4.349231 | BC203: 4.3116304 | BD203: 4.2747305 | BE203: 4.2385686 | BF203: 4.2031798 | BG203: 4.1685869 | BH203: 4.1348086 | BI203: 4.1018633 | BJ203: 4.0697699 | BK203: 4.0385468 | BL203: 4.0082128 | BM203: 3.9787865 | BN203: 3.9502865 | BO203: 3.9227314 | BP203: 3.89614 | BQ203: 3.8705307 | BR203: 3.7372836 | BS203: 3.6363554 | BU203: 4.02 | BV203: 3.96 | BW203: 76.6575
