Workbook
Name _DLX1.INC: HAVERQ!$A$3:$BJ$8
Name _DLX2.INC: HAVERM!$A$2:$BL$7
Name Annual_Data: GMWA!$A$1:$A$2
Name Annual_Data: GMWQ!$A$1:$A$2
Name Data: [1]sheet0!$C$2

Sheet >> CHARTS

Sheet >> DATA

Sheet Chart Data
A1: Business investment & corporate gearing rate | F1: Business investment & corporate gearing rate (4qma) | N1: Business investment & ICT (Q1 2021=100) | T1: Business investment by industry (Diff vs Q1 2021, £bn) | AA1: Business investment by industry (cont to rise since Q1 2021) | AH1: Business investment by industry (cont to change since Q4 2019) | AO1: Business investment by industry (cont to change since 2016) | AV1: Interest rates | BA1: Interest rates - change since Bank Rate started to rise | BI1: Business investment by industry (Q4 2019=100) | BQ1: Business investment by industry (Diff vs Q4 2019, £bn) | BY1: Business investment by industry (cont to change since Q4 2019) | CG1: Business investment by industry (£bn) | CN1: Business investment by sector - services (Diff vs Q4 2019, £bn) | CW1: Business investment by sector - services (Diff vs Q4 2019, £bn) | DI1: Investment by asset (Q4 2019=100) | DR1: Business investment by asset (Diff vs Q4 2019, £bn) | DZ1: Surveys vs business investment | EL1: Standard deviations | EQ1: Whole economy weighted averages | EV1: Weights | EW1: Manufacturing | EX1: Services | EY1: Retail | EZ1: B&P | FA1: Consumer | FC1: Corporate debt - SMEs vs large (Feb20=100) | FI1: Services - business investment shortfall vs change in debt | FV1: Corporate deposits vs pre-pandemic trend | GC1: Business investment forecasts | GJ1: Business investment historical revisions | GO1: Business investment historical revisions | GT1: IPNR - UK vs G7 | HA1: Business investment history | HJ1: IPNR - UK vs G7 | HQ1: Business investment forecast | HZ1: Capital stock per hour worked | IH1: CBI surveys - constraints on investment | IQ1: Business investment & expected loan growth | IW1: Financing: | IX1: https://twitter.com/Gilesyb/status/1519332233206714375?s=20&t=cwRE5RP0CO_DabR5P63a5w
N2: https://www.gov.uk/guidance/super-deduction | EQ2: LT av | ER2: =AVERAGE(ER7:ER102) -> 8.20371 | ES2: =AVERAGE(ES7:ES102) -> -6.2358118 | ET2: =AVERAGE(ET7:ET102) -> 0.82260665 | EW2: =SUM(HAVERQ!I125:I128)/SUM(HAVERQ!B125:B128) -> 0.15573293 | EX2: =1-EW2 -> 0.84426707 | EY2: =SUM(HAVERQ!L125:L128)/SUM(HAVERQ!B125:B128) -> 0.089018552 | EZ2: =1-EW2-EY2-FA2 -> 0.73088214 | FA2: =SUM(HAVERQ!O125:O128)/SUM(HAVERQ!B125:B128) -> 0.024366377 | FI2: Q2 2024 vs Q4 2019 | GC2: Q4 2019 = 100 | GJ2: 2022 = 100 | GO2: Q4 2019= 100 | IH2: Z scores | IW2: Debt and investmet: | IX2: https://bankunderground.co.uk/2022/05/25/debt-and-investment-what-can-we-learn-from-smes-investment-behaviour-during-and-after-the-global-financial-crisis/
EQ3: STDEV | ER3: =STDEV(ER7:ER102) -> 11.720889 | ES3: =STDEV(ES7:ES102) -> 14.071805 | ET3: =STDEV(ET7:ET102) -> 1.570543 | IX3: https://bankunderground.co.uk/2021/09/28/weighed-down-by-debt-revisiting-the-link-between-corporate-debt-overhang-and-investment/
B4: Business investment (LHS) | C4: Corporate debt servicing costs (RHS) | D4: ZERO LINE | G4: Business investment (LHS) | H4: Corporate debt servicing costs (RHS) | I4: ZERO LINE | K4: CGEAR forecast | L4: Actual CGEAR | O4: Total business investment | P4: ICT equipment and other machinery | Q4: Super deduction | R4: 100 LINE | U4: Transport equipment | V4: ICT equipment and other machinery | W4: Other buildings & structures | X4: Intellectual property products | Y4: Total | AB4: Transport equipment | AC4: ICT equipment and other machinery | AD4: Other buildings & structures | AE4: Intellectual property products | AF4: Total | AI4: Transport equipment | AJ4: ICT equipment and other machinery | AK4: Other buildings & structures | AL4: Intellectual property products | AM4: Total | AP4: Transport equipment | AQ4: ICT equipment & oth. machinery | AR4: Other buildings & structures | AS4: Intellectual property products | AT4: Total | AW4: Bank Rate | AX4: Non-financial corporations | AY4: Secured household | BB4: Non-financial corporations | BC4: Secured household | BD4: Hiking cycle | BE4: Cutting cycle | BF4: ZERO LINE | BJ4: Total | BK4: Manufacturing | BL4: Other production | BM4: Construction | BN4: Services | BO4: 100 LINE | BR4: Manufacturing | BS4: Other production | BT4: Construction | BU4: Services | BV4: Other | BW4: Total | BZ4: Manufacturing | CA4: Other production | CB4: Construction | CC4: Services | CD4: Other | CE4: Total | CH4: Manufacturing | CI4: Other production | CJ4: Construction | CK4: Services | CL4: Other | CO4: Distribution | CP4: Hotels & restaurants | CQ4: Financial interm. | CR4: Transport | CS4: Real estate | CT4: Other | CU4: Total services | CX4: Distribution | CY4: Hotels & restaurants | CZ4: Financial interm. | DA4: Transport | DB4: Information & comms | DC4: Real estate | DD4: Education | DE4: Health | DF4: Other services | DG4: Total services | DJ4: Total | DK4: Transport equipment | DL4: ICT and other machinery | DM4: Dwellings | DN4: Other buildings | DO4: Intellectual property | DP4: 100 LINE | DS4: Transport equipment | DT4: ICT and other machinery | DU4: Dwellings | DV4: Other buildings | DW4: Intellectual property | DX4: Total | EA4: Min | EB4: Range of surveys* (LHS) | EC4: Business investment (RHS) | ED4: ZERO LINE | EF4: Max | EG4: Average | EJ4: Business investment exc nuclear fuels | EM4: BCC | EN4: CBI | EO4: BoE agents | ER4: BCC | ES4: CBI | ET4: BoE agents | FD4: All firms | FE4: SMEs | FF4: Large | FG4: 100 LINE | FJ4: Manufacturing | FK4: Utilities | FL4: Construction | FM4: Distribution | FN4: Hotels & restaurants | FO4: Transport & comms | FP4: Real estate | FQ4: Education | FR4: Health | FS4: Other services | FT4: Total services | FW4: Actual | FX4: Assuming 2016-2019 trend had continued | FY4: Monthly change | FZ4: Av monthly change | GA4: Difference | GD4: January 2020 | GE4: June 2021 | GF4: September 2024 | GG4: Super deduction | GH4: 100 LINE | GK4: September 2024 | GL4: October 2024 | GM4: 100 LINE | GP4: September 2024 | GQ4: October 2024 | GR4: 100 LINE | GU4: UK | GV4: G7 bottom | GW4: Range of G7 exc. UK | GX4: 100 LINE | GY4: G7 top | HB4: UK | HC4: US | HD4: Japan | HE4: Germany | HF4: France | HG4: Italy | HH4: Canada | HK4: UK | HL4: G7 bottom | HM4: Range of G7 exc. UK | HN4: 100 LINE | HO4: G7 top | HR4: UK | HS4: US | HT4: Japan | HU4: Germany | HV4: France | HW4: Italy | HX4: Canada | IA4: Actual | IB4: Pre-2008 trend | IC4: Difference | IF4: Hours worked | II4: Inadequate net return | IJ4: Internal finance shortage | IK4: Unable to raise finance | IL4: Cost of finance | IM4: Demand uncertainty | IN4: Labour Shortage | IO4: Other | IR4: Expected change in loan demand due to investment (LHS) | IS4: Business investment (RHS) | IT4: ZERO LINE
A5: 1990 | B5: =100*((DataQ!C75/DataQ!C71)-1) -> 1.672029 | C5: =K5 -> 18.593076 | D5: 0 | F5: 1990 | I5: 0 | K5: =L5 -> 18.593076 | L5: =100*(HAVERQ!AF9/HAVERQ!AI9) -> 18.593076 | N5: 2018 | O5: =100*('ONS CVM_SA_(Quarterly)'!B89/'ONS CVM_SA_(Quarterly)'!B$101) -> 113.95928 | P5: =100*('ONS CVM_SA_(Quarterly)'!D89/'ONS CVM_SA_(Quarterly)'!D$101) -> 115.73484 | R5: 100 | T5: 2021 | U5: ='ONS CVM_SA_(Quarterly)'!C101-'ONS CVM_SA_(Quarterly)'!C$101 -> 0 | V5: ='ONS CVM_SA_(Quarterly)'!D101-'ONS CVM_SA_(Quarterly)'!D$101 -> 0 | W5: ='ONS CVM_SA_(Quarterly)'!E101-'ONS CVM_SA_(Quarterly)'!E$101 -> 0 | X5: ='ONS CVM_SA_(Quarterly)'!F101-'ONS CVM_SA_(Quarterly)'!F$101 -> 0 | Y5: ='ONS CVM_SA_(Quarterly)'!B101-'ONS CVM_SA_(Quarterly)'!B$101 -> 0 | AA5: 2021 | AB5: =100*(U5/'ONS CVM_SA_(Quarterly)'!$B$101) -> 0 | AC5: =100*(V5/'ONS CVM_SA_(Quarterly)'!$B$101) -> 0 | AD5: =100*(W5/'ONS CVM_SA_(Quarterly)'!$B$101) -> 0 | AE5: =100*(X5/'ONS CVM_SA_(Quarterly)'!$B$101) -> 0 | AF5: =100*(('ONS CVM_SA_(Quarterly)'!B101/'ONS CVM_SA_(Quarterly)'!B$101)-1) -> 0 | AH5: 2019 | AI5: =100*(('ONS CVM_SA_(Quarterly)'!C93-'ONS CVM_SA_(Quarterly)'!C$96)/'ONS CVM_SA_(Quarterly)'!$B$96) -> 1.3469045 | AJ5: =100*(('ONS CVM_SA_(Quarterly)'!D93-'ONS CVM_SA_(Quarterly)'!D$96)/'ONS CVM_SA_(Quarterly)'!$B$96) -> 0.58231442 | AK5: =100*(('ONS CVM_SA_(Quarterly)'!E93-'ONS CVM_SA_(Quarterly)'!E$96)/'ONS CVM_SA_(Quarterly)'!$B$96) -> 0.41778237 | AL5: =100*(('ONS CVM_SA_(Quarterly)'!F93-'ONS CVM_SA_(Quarterly)'!F$96)/'ONS CVM_SA_(Quarterly)'!$B$96) -> -1.3194825 | AM5: =100*(('ONS CVM_SA_(Quarterly)'!B93-'ONS CVM_SA_(Quarterly)'!B$96)/'ONS CVM_SA_(Quarterly)'!$B$96) -> -1.279156 | AO5: 2016 | AP5: =100*(('ONS CVM_SA_(Quarterly)'!C81-AVERAGE('ONS CVM_SA_(Quarterly)'!C$81:C$84))/AVERAGE('ONS CVM_SA_(Quarterly)'!$B$81:$B$84)) -> 1.2876667 | AQ5: =100*(('ONS CVM_SA_(Quarterly)'!D81-AVERAGE('ONS CVM_SA_(Quarterly)'!D$81:D$84))/AVERAGE('ONS CVM_SA_(Quarterly)'!$B$81:$B$84)) -> 0.1616674 | AR5: =100*(('ONS CVM_SA_(Quarterly)'!E81-AVERAGE('ONS CVM_SA_(Quarterly)'!E$81:E$84))/AVERAGE('ONS CVM_SA_(Quarterly)'!$B$81:$B$84)) -> -0.32455035 | AS5: =100*(('ONS CVM_SA_(Quarterly)'!F81-AVERAGE('ONS CVM_SA_(Quarterly)'!F$81:F$84))/AVERAGE('ONS CVM_SA_(Quarterly)'!$B$81:$B$84)) -> -0.33143843 | AT5: =100*(('ONS CVM_SA_(Quarterly)'!B81-AVERAGE('ONS CVM_SA_(Quarterly)'!B$81:B$84))/AVERAGE('ONS CVM_SA_(Quarterly)'!$B$81:$B$84)) -> -0.027147158 | AV5: 43466 | AW5: =HAVERM!D236 -> 0.75 | AX5: =HAVERM!B236 -> 3.35 | AY5: =HAVERM!C236 -> 2.48 | BA5: 44531 | BB5: =AX40-AX$39 -> 0.05 | BC5: =AY40-AY$39 -> -0.01 | BD5: 1000 | BF5: 0 | BI5: 2018 | BJ5: =100*(HAVERQ!B121/HAVERQ!B$128) -> 98.948285 | BK5: =100*(HAVERQ!I121/HAVERQ!I$128) -> 104.1024 | BL5: =100*(HAVERQ!J121/HAVERQ!J$128) -> 87.403786 | BM5: =100*(HAVERQ!K121/HAVERQ!K$128) -> 59.678417 | BN5: =100*((HAVERQ!L121+HAVERQ!M121)/(HAVERQ!L$128+HAVERQ!M$128)) -> 95.582593 | BO5: 100 | BQ5: 2018 | BR5: =HAVERQ!I121-HAVERQ!I$128 -> 383 | BS5: =HAVERQ!J121-HAVERQ!J$128 -> -1211 | BT5: =HAVERQ!K121-HAVERQ!K$128 -> -1304 | BU5: =(HAVERQ!L121+HAVERQ!M121)-(HAVERQ!L$128+HAVERQ!M$128) -> -1750 | BV5: =HAVERQ!N121-HAVERQ!N$128 -> 45 | BW5: =HAVERQ!B121-HAVERQ!B$128 -> -652 | BY5: 2019 | BZ5: =100*((HAVERQ!I125-HAVERQ!I$128)/HAVERQ!$B$128) -> 1.0549408 | CA5: =100*((HAVERQ!J125-HAVERQ!J$128)/HAVERQ!$B$128) -> -2.0469723 | CB5: =100*((HAVERQ!K125-HAVERQ!K$128)/HAVERQ!$B$128) -> -0.44520437 | CC5: =100*(((HAVERQ!L125+HAVERQ!M125)-(HAVERQ!L$128+HAVERQ!M$128))/HAVERQ!$B$128) -> -0.20969771 | CD5: =CE5-BZ5-CA5-CB5-CC5 -> 0.36777753 | CE5: =100*((HAVERQ!B125-HAVERQ!B$128)/HAVERQ!B$128) -> -1.279156 | CG5: 2018 | CH5: =HAVERQ!I121 -> 9719 | CI5: =HAVERQ!J121 -> 8403 | CJ5: =HAVERQ!K121 -> 1930 | CK5: =HAVERQ!L121+HAVERQ!M121 -> 37866 | CL5: =HAVERQ!N121 -> 1403 | CN5: 2018 | CO5: =CX5 -> -251 | CP5: =CY5 -> 94 | CQ5: =CZ5 -> 80 | CR5: =DA5 -> -442 | CS5: =DC5 -> 1041 | CT5: =+DB5+DD5+DE5+DF5 -> -437 | CU5: =DG5 -> -1750 | CW5: 2018 | CX5: =HAVERQ!L121-HAVERQ!L$128 -> -251 | CY5: =HAVERQ!O121-HAVERQ!O$128 -> 94 | CZ5: =HAVERQ!P121-HAVERQ!P$128 -> 80 | DA5: =HAVERQ!Q121-HAVERQ!Q$128 -> -442 | DB5: =HAVERQ!R121-HAVERQ!R$128 -> -155 | DC5: =HAVERQ!S121-HAVERQ!S$128 -> 1041 | DD5: =HAVERQ!T121-HAVERQ!T$128 -> 127 | DE5: =HAVERQ!U121-HAVERQ!U$128 -> 147 | DF5: =HAVERQ!V121-HAVERQ!V$128 -> -556 | DG5: =(HAVERQ!L121+HAVERQ!M121)-(HAVERQ!L$128+HAVERQ!M$128) -> -1750 | DI5: 2018 | DJ5: =100*(HAVERQ!C121/HAVERQ!C$128) -> 99.463919 | DK5: =100*(HAVERQ!D121/HAVERQ!D$128) -> 120.35968 | DL5: =100*(HAVERQ!E121/HAVERQ!E$128) -> 103.4275 | DM5: =100*(HAVERQ!F121/HAVERQ!F$128) -> 97.293779 | DN5: =100*(HAVERQ!G121/HAVERQ!G$128) -> 99.390359 | DO5: =100*(HAVERQ!H121/HAVERQ!H$128) -> 94.274795 | DP5: 100 | DR5: 2018 | DS5: =HAVERQ!D121-HAVERQ!D$128 -> 917 | DT5: =HAVERQ!E121-HAVERQ!E$128 -> 569 | DU5: =HAVERQ!F121-HAVERQ!F$128 -> -686 | DV5: =HAVERQ!G121-HAVERQ!G$128 -> -226 | DW5: =HAVERQ!H121-HAVERQ!H$128 -> -1513 | DX5: =HAVERQ!C121-HAVERQ!C$128 -> -588 | DZ5: 2000 | EA5: =MIN(EM5:EO5) -> 0.51551789 | EB5: =+EF5-EA5 -> 0.44336509 | EC5: =100*((EJ9/EJ5)-1) -> 6.0508083 | ED5: 0 | EF5: =MAX(EM5:EO5) -> 0.95888298 | EG5: =AVERAGE(EM5:EO5) -> 0.80805841 | EI5: 1999 | EJ5: ='IPNR ex BNFL'!I13 -> 41135 | EM5: =(ER5-ER$2)/ER$3 -> 0.95888298 | EN5: =(ES5-ES$2)/ES$3 -> 0.94977435 | EO5: =(ET5-ET$2)/ET$3 -> 0.51551789 | ER5: =(HAVERQ!W47*$EW$2)+(HAVERQ!X47*$EX$2)/($EW$2+$EX$2) -> 19.442671 | ES5: =(HAVERQ!AB47*$EW$2)+(HAVERQ!AC47*$EY$2)+(HAVERQ!AD47*$EZ$2)+(HAVERQ!AE47*$FA$2)/($EW$2+$EY$2+$EZ$2+$FA$2) -> 7.1292275 | ET5: =(HAVERQ!Y47*$EW$2)+(HAVERQ!Z47*$EX$2)/($EW$2+$EX$2) -> 1.6322497 | FC5: 43466 | FD5: =100*((HAVERM!E236+HAVERM!F236)/(HAVERM!E$249+HAVERM!F$249)) -> 98.455793 | FE5: =100*(HAVERM!E236/HAVERM!E$249) -> 98.994791 | FF5: =100*(HAVERM!F236/HAVERM!F$249) -> 98.160042 | FG5: 100 | FI5: Investment | FJ5: =100*((HAVERQ!I146/HAVERQ!I$128)-1) -> 12.992716 | FK5: =100*((HAVERQ!J146/HAVERQ!J$128)-1) -> 8.0403578 | FL5: =100*((HAVERQ!K146/HAVERQ!K$128)-1) -> -28.911565 | FM5: =100*((HAVERQ!L146/HAVERQ!L$128)-1) -> -44.648919 | FN5: =100*((HAVERQ!O146/HAVERQ!O$128)-1) -> 9.3023256 | FO5: =100*(((HAVERQ!Q146+HAVERQ!R146)/(HAVERQ!Q$128+HAVERQ!R$128))-1) -> 24.249763 | FP5: =100*((HAVERQ!S146/HAVERQ!S$128)-1) -> 14.619818 | FQ5: =100*((HAVERQ!T146/HAVERQ!T$128)-1) -> -6.302202 | FR5: =100*((HAVERQ!U146/HAVERQ!U$128)-1) -> -47.300564 | FS5: =100*((HAVERQ!V146/HAVERQ!V$128)-1) -> -6.9942452 | FT5: =100*(((HAVERQ!L146+HAVERQ!M146)/(HAVERQ!L$128+HAVERQ!M$128))-1) -> -4.8010905 | FV5: 42339 | FW5: =HAVERM!G199 -> 343353 | GC5: 2010 | GD5: =100*(DataQ!W155/DataQ!W$194) -> 73.538662 | GE5: =100*(DataQ!X155/DataQ!X$194) -> 70.761518 | GF5: =100*(DataQ!C155/DataQ!C$194) -> 66.908088 | GH5: 100 | GJ5: 2005 | GK5: =100*(DataQ!Z135/AVERAGE(DataQ!$Z$203:$Z$206)) -> 67.924859 | GL5: =100*(DataQ!C135/AVERAGE(DataQ!$C$203:$C$206)) -> 70.279484 | GM5: 100 | GO5: 2005 | GP5: =100*(DataQ!Z135/DataQ!$Z$194) -> 67.671443 | GQ5: =100*(DataQ!C135/DataQ!$C$194) -> 67.840436 | GR5: 100 | GT5: 2018 | GU5: =HB5 -> 98.948285 | GV5: =MIN(HC5:HH5) -> 93.70119 | GW5: =+GY5-GV5 -> 11.699942 | GX5: 100 | GY5: =MAX(HC5:HH5) -> 105.40113 | HA5: 2018 | HB5: =100*(DataQ!C187/DataQ!C$194) -> 98.948285 | HC5: =100*(DataQ!Q187/DataQ!Q$194) -> 94.445006 | HD5: =100*(DataQ!R187/DataQ!R$194) -> 105.40113 | HE5: =100*(DataQ!S187/DataQ!S$194) -> 96.262109 | HF5: =100*(DataQ!T187/DataQ!T$194) -> 93.70119 | HG5: =100*(DataQ!U187/DataQ!U$194) -> 98.836204 | HH5: =100*(DataQ!V187/DataQ!V$194) -> 97.446653 | HJ5: 2018 | HK5: =HR5 -> 98.948285 | HL5: =MIN(HS5:HX5) -> 93.70119 | HM5: =+HO5-HL5 -> 11.699942 | HN5: 100 | HO5: =MAX(HS5:HX5) -> 105.40113 | HQ5: 2018 | HR5: =100*(DataQ!C187/DataQ!C$194) -> 98.948285 | HS5: =100*(DataQ!Q187/DataQ!Q$194) -> 94.445006 | HT5: =100*(DataQ!R187/DataQ!R$194) -> 105.40113 | HU5: =100*(DataQ!S187/DataQ!S$194) -> 96.262109 | HV5: =100*(DataQ!T187/DataQ!T$194) -> 93.70119 | HW5: =100*(DataQ!U187/DataQ!U$194) -> 98.836204 | HX5: =100*(DataQ!V187/DataQ!V$194) -> 97.446653 | HZ5: 1990 | IA5: =DataA!J24/'Chart Data'!IF5 -> 1.7494582 | IB5: =IA5 -> 1.7494582 | IC5: =100*((IA5/IB5)-1) -> 0 | ID5: =100*((IA22/IA5)^(1/17)-1) -> 2.6565709 | IF5: =DataA!K24*DataA!L24 -> 903065.32 | IH5: Manufacturing | II5: =(HAVERQ!AJ147-HAVERQ!AJ1)/HAVERQ!AJ2 -> -0.64986461 | IJ5: =(HAVERQ!AK147-HAVERQ!AK1)/HAVERQ!AK2 -> -0.15549091 | IK5: =(HAVERQ!AL147-HAVERQ!AL1)/HAVERQ!AL2 -> -0.1555263 | IL5: =(HAVERQ!AM147-HAVERQ!AM1)/HAVERQ!AM2 -> 0.98209825 | IM5: =(HAVERQ!AN147-HAVERQ!AN1)/HAVERQ!AN2 -> -0.97139905 | IN5: =(HAVERQ!AO147-HAVERQ!AO1)/HAVERQ!AO2 -> 0.91449689 | IO5: =(HAVERQ!AP147-HAVERQ!AP1)/HAVERQ!AP2 -> 1.8777181 | IQ5: 2007 | IR5: =HAVERQ!AH76 -> #N/A | IS5: =100*(('IPNR ex BNFL'!I45/'IPNR ex BNFL'!I41)-1) -> 8.6831897 | IT5: 0
B6: =100*((DataQ!C76/DataQ!C72)-1) -> 1.9545723 | C6: =K6 -> 20.025766 | D6: 0 | I6: 0 | K6: =L6 -> 20.025766 | L6: =100*(HAVERQ!AF10/HAVERQ!AI10) -> 20.025766 | O6: =100*('ONS CVM_SA_(Quarterly)'!B90/'ONS CVM_SA_(Quarterly)'!B$101) -> 111.56833 | P6: =100*('ONS CVM_SA_(Quarterly)'!D90/'ONS CVM_SA_(Quarterly)'!D$101) -> 113.69953 | R6: 100 | U6: ='ONS CVM_SA_(Quarterly)'!C102-'ONS CVM_SA_(Quarterly)'!C$101 -> -52 | V6: ='ONS CVM_SA_(Quarterly)'!D102-'ONS CVM_SA_(Quarterly)'!D$101 -> 101 | W6: ='ONS CVM_SA_(Quarterly)'!E102-'ONS CVM_SA_(Quarterly)'!E$101 -> 1967 | X6: ='ONS CVM_SA_(Quarterly)'!F102-'ONS CVM_SA_(Quarterly)'!F$101 -> 2097 | Y6: ='ONS CVM_SA_(Quarterly)'!B102-'ONS CVM_SA_(Quarterly)'!B$101 -> 4159 | AB6: =100*(U6/'ONS CVM_SA_(Quarterly)'!$B$101) -> -0.096603998 | AC6: =100*(V6/'ONS CVM_SA_(Quarterly)'!$B$101) -> 0.18763469 | AD6: =100*(W6/'ONS CVM_SA_(Quarterly)'!$B$101) -> 3.654232 | AE6: =100*(X6/'ONS CVM_SA_(Quarterly)'!$B$101) -> 3.895742 | AF6: =100*(('ONS CVM_SA_(Quarterly)'!B102/'ONS CVM_SA_(Quarterly)'!B$101)-1) -> 7.7264621 | AI6: =100*(('ONS CVM_SA_(Quarterly)'!C94-'ONS CVM_SA_(Quarterly)'!C$96)/'ONS CVM_SA_(Quarterly)'!$B$96) -> 2.1598864 | AJ6: =100*(('ONS CVM_SA_(Quarterly)'!D94-'ONS CVM_SA_(Quarterly)'!D$96)/'ONS CVM_SA_(Quarterly)'!$B$96) -> 0.91460464 | AK6: =100*(('ONS CVM_SA_(Quarterly)'!E94-'ONS CVM_SA_(Quarterly)'!E$96)/'ONS CVM_SA_(Quarterly)'!$B$96) -> 0.18872794 | AL6: =100*(('ONS CVM_SA_(Quarterly)'!F94-'ONS CVM_SA_(Quarterly)'!F$96)/'ONS CVM_SA_(Quarterly)'!$B$96) -> -1.0839759 | AM6: =100*(('ONS CVM_SA_(Quarterly)'!B94-'ONS CVM_SA_(Quarterly)'!B$96)/'ONS CVM_SA_(Quarterly)'!$B$96) -> 0.30164209 | AP6: =100*(('ONS CVM_SA_(Quarterly)'!C82-AVERAGE('ONS CVM_SA_(Quarterly)'!C$81:C$84))/AVERAGE('ONS CVM_SA_(Quarterly)'!$B$81:$B$84)) -> 0.34278352 | AQ6: =100*(('ONS CVM_SA_(Quarterly)'!D82-AVERAGE('ONS CVM_SA_(Quarterly)'!D$81:D$84))/AVERAGE('ONS CVM_SA_(Quarterly)'!$B$81:$B$84)) -> 0.1487016 | AR6: =100*(('ONS CVM_SA_(Quarterly)'!E82-AVERAGE('ONS CVM_SA_(Quarterly)'!E$81:E$84))/AVERAGE('ONS CVM_SA_(Quarterly)'!$B$81:$B$84)) -> 0.44205297 | AS6: =100*(('ONS CVM_SA_(Quarterly)'!F82-AVERAGE('ONS CVM_SA_(Quarterly)'!F$81:F$84))/AVERAGE('ONS CVM_SA_(Quarterly)'!$B$81:$B$84)) -> -0.062397945 | AT6: =100*(('ONS CVM_SA_(Quarterly)'!B82-AVERAGE('ONS CVM_SA_(Quarterly)'!B$81:B$84))/AVERAGE('ONS CVM_SA_(Quarterly)'!$B$81:$B$84)) -> -0.32698144 | AV6: 43497 | AW6: =HAVERM!D237 -> 0.75 | AX6: =HAVERM!B237 -> 3.34 | AY6: =HAVERM!C237 -> 2.46 | BA6: 44562 | BB6: =AX41-AX$39 -> 0.11 | BC6: =AY41-AY$39 -> -0.01 | BD6: 1000 | BF6: 0 | BJ6: =100*(HAVERQ!B122/HAVERQ!B$128) -> 96.872278 | BK6: =100*(HAVERQ!I122/HAVERQ!I$128) -> 102.28149 | BL6: =100*(HAVERQ!J122/HAVERQ!J$128) -> 91.231537 | BM6: =100*(HAVERQ!K122/HAVERQ!K$128) -> 63.234385 | BN6: =100*((HAVERQ!L122+HAVERQ!M122)/(HAVERQ!L$128+HAVERQ!M$128)) -> 94.908623 | BO6: 100 | BR6: =HAVERQ!I122-HAVERQ!I$128 -> 213 | BS6: =HAVERQ!J122-HAVERQ!J$128 -> -843 | BT6: =HAVERQ!K122-HAVERQ!K$128 -> -1189 | BU6: =(HAVERQ!L122+HAVERQ!M122)-(HAVERQ!L$128+HAVERQ!M$128) -> -2017 | BV6: =HAVERQ!N122-HAVERQ!N$128 -> -100 | BW6: =HAVERQ!B122-HAVERQ!B$128 -> -1939 | BZ6: =100*((HAVERQ!I126-HAVERQ!I$128)/HAVERQ!$B$128) -> 0.59683195 | CA6: =100*((HAVERQ!J126-HAVERQ!J$128)/HAVERQ!$B$128) -> -2.6196083 | CB6: =100*((HAVERQ!K126-HAVERQ!K$128)/HAVERQ!$B$128) -> -0.10484886 | CC6: =100*(((HAVERQ!L126+HAVERQ!M126)-(HAVERQ!L$128+HAVERQ!M$128))/HAVERQ!$B$128) -> -0.2855115 | CD6: =CE6-BZ6-CA6-CB6-CC6 -> 2.7147788 | CE6: =100*((HAVERQ!B126-HAVERQ!B$128)/HAVERQ!B$128) -> 0.30164209 | CH6: =HAVERQ!I122 -> 9549 | CI6: =HAVERQ!J122 -> 8771 | CJ6: =HAVERQ!K122 -> 2045 | CK6: =HAVERQ!L122+HAVERQ!M122 -> 37599 | CL6: =HAVERQ!N122 -> 1258 | CO6: =CX6 -> -89 | CP6: =CY6 -> 45 | CQ6: =CZ6 -> 75 | CR6: =DA6 -> -1635 | CS6: =DC6 -> 1220 | CT6: =+DB6+DD6+DE6+DF6 -> -558 | CU6: =DG6 -> -2017 | CX6: =HAVERQ!L122-HAVERQ!L$128 -> -89 | CY6: =HAVERQ!O122-HAVERQ!O$128 -> 45 | CZ6: =HAVERQ!P122-HAVERQ!P$128 -> 75 | DA6: =HAVERQ!Q122-HAVERQ!Q$128 -> -1635 | DB6: =HAVERQ!R122-HAVERQ!R$128 -> -202 | DC6: =HAVERQ!S122-HAVERQ!S$128 -> 1220 | DD6: =HAVERQ!T122-HAVERQ!T$128 -> 95 | DE6: =HAVERQ!U122-HAVERQ!U$128 -> -110 | DF6: =HAVERQ!V122-HAVERQ!V$128 -> -341 | DG6: =(HAVERQ!L122+HAVERQ!M122)-(HAVERQ!L$128+HAVERQ!M$128) -> -2017 | DJ6: =100*(HAVERQ!C122/HAVERQ!C$128) -> 98.307882 | DK6: =100*(HAVERQ!D122/HAVERQ!D$128) -> 72.868561 | DL6: =100*(HAVERQ!E122/HAVERQ!E$128) -> 104.36118 | DM6: =100*(HAVERQ!F122/HAVERQ!F$128) -> 100.79688 | DN6: =100*(HAVERQ!G122/HAVERQ!G$128) -> 98.594589 | DO6: =100*(HAVERQ!H122/HAVERQ!H$128) -> 97.010633 | DP6: 100 | DS6: =HAVERQ!D122-HAVERQ!D$128 -> -1222 | DT6: =HAVERQ!E122-HAVERQ!E$128 -> 724 | DU6: =HAVERQ!F122-HAVERQ!F$128 -> 202 | DV6: =HAVERQ!G122-HAVERQ!G$128 -> -521 | DW6: =HAVERQ!H122-HAVERQ!H$128 -> -790 | DX6: =HAVERQ!C122-HAVERQ!C$128 -> -1856 | EA6: =MIN(EM6:EO6) -> 0.67591527 | EB6: =+EF6-EA6 -> 0.61095198 | EC6: =100*((EJ10/EJ6)-1) -> 12.08986 | ED6: 0 | EF6: =MAX(EM6:EO6) -> 1.2868673 | EG6: =AVERAGE(EM6:EO6) -> 0.98404781 | EJ6: ='IPNR ex BNFL'!I14 -> 41175 | EM6: =(ER6-ER$2)/ER$3 -> 1.2868673 | EN6: =(ES6-ES$2)/ES$3 -> 0.98936091 | EO6: =(ET6-ET$2)/ET$3 -> 0.67591527 | ER6: =(HAVERQ!W48*$EW$2)+(HAVERQ!X48*$EX$2)/($EW$2+$EX$2) -> 23.286938 | ES6: =(HAVERQ!AB48*$EW$2)+(HAVERQ!AC48*$EY$2)+(HAVERQ!AD48*$EZ$2)+(HAVERQ!AE48*$FA$2)/($EW$2+$EY$2+$EZ$2+$FA$2) -> 7.6862819 | ET6: =(HAVERQ!Y48*$EW$2)+(HAVERQ!Z48*$EX$2)/($EW$2+$EX$2) -> 1.8841606 | FC6: 43497 | FD6: =100*((HAVERM!E237+HAVERM!F237)/(HAVERM!E$249+HAVERM!F$249)) -> 99.010632 | FE6: =100*(HAVERM!E237/HAVERM!E$249) -> 98.8816 | FF6: =100*(HAVERM!F237/HAVERM!F$249) -> 99.081432 | FG6: 100 | FI6: Loans (exc overdrafts) | FJ6: =100*((HAVERM!AR301/HAVERM!AR$247)-1) -> -10.687935 | FK6: =100*((HAVERM!AS301/HAVERM!AS$247)-1) -> 74.410266 | FL6: =100*((HAVERM!AT301/HAVERM!AT$247)-1) -> 5.3551277 | FM6: =100*((HAVERM!AU301/HAVERM!AU$247)-1) -> -1.0601875 | FN6: =100*((HAVERM!AV301/HAVERM!AV$247)-1) -> 0.13226484 | FO6: =100*((HAVERM!AW301/HAVERM!AW$247)-1) -> 32.185076 | FP6: =100*((HAVERM!AX301/HAVERM!AX$247)-1) -> 17.050048 | FQ6: =100*((HAVERM!AY301/HAVERM!AY$247)-1) -> -22.896942 | ... FT6: =100*((HAVERM!BB301/HAVERM!BB$247)-1) -> 9.889607 | FV6: 42370 | FW6: =HAVERM!G200 -> 347433 | FY6: =FW6-FW5 -> 4080 | GD6: =100*(DataQ!W156/DataQ!W$194) -> 72.325013 | GE6: =100*(DataQ!X156/DataQ!X$194) -> 69.9162 | GF6: =100*(DataQ!C156/DataQ!C$194) -> 65.906378 | GH6: 100 | GK6: =100*(DataQ!Z136/AVERAGE(DataQ!$Z$203:$Z$206)) -> 69.771414 | GL6: =100*(DataQ!C136/AVERAGE(DataQ!$C$203:$C$206)) -> 72.212057 | GM6: 100 | GP6: =100*(DataQ!Z136/DataQ!$Z$194) -> 69.51111 | GQ6: =100*(DataQ!C136/DataQ!$C$194) -> 69.705939 | GR6: 100 | GU6: =HB6 -> 96.872278 | GV6: =MIN(HC6:HH6) -> 94.856789 | GW6: =+GY6-GV6 -> 12.0845 | GX6: 100 | GY6: =MAX(HC6:HH6) -> 106.94129 | HB6: =100*(DataQ!C188/DataQ!C$194) -> 96.872278 | HC6: =100*(DataQ!Q188/DataQ!Q$194) -> 95.515604 | HD6: =100*(DataQ!R188/DataQ!R$194) -> 106.94129 | HE6: =100*(DataQ!S188/DataQ!S$194) -> 97.989399 | HF6: =100*(DataQ!T188/DataQ!T$194) -> 94.856789 | HG6: =100*(DataQ!U188/DataQ!U$194) -> 100.81953 | HH6: =100*(DataQ!V188/DataQ!V$194) -> 98.996503 | HK6: =HR6 -> 96.872278 | HL6: =MIN(HS6:HX6) -> 94.856789 | HM6: =+HO6-HL6 -> 12.0845 | HN6: 100 | HO6: =MAX(HS6:HX6) -> 106.94129 | HR6: =100*(DataQ!C188/DataQ!C$194) -> 96.872278 | HS6: =100*(DataQ!Q188/DataQ!Q$194) -> 95.515604 | HT6: =100*(DataQ!R188/DataQ!R$194) -> 106.94129 | HU6: =100*(DataQ!S188/DataQ!S$194) -> 97.989399 | HV6: =100*(DataQ!T188/DataQ!T$194) -> 94.856789 | HW6: =100*(DataQ!U188/DataQ!U$194) -> 100.81953 | HX6: =100*(DataQ!V188/DataQ!V$194) -> 98.996503 | HZ6: 1991 | IA6: =DataA!J25/'Chart Data'!IF6 -> 1.8782797 | IB6: =IB5*(1+$ID$5/100) -> 1.7959338 | IC6: =100*((IA6/IB6)-1) -> 4.5851298 | IF6: =DataA!K25*DataA!L25 -> 868391.46 | IH6: Business & professional services | II6: =(HAVERQ!AQ147-HAVERQ!AQ1)/HAVERQ!AQ2 -> 0.4099103 | IJ6: =(HAVERQ!AR147-HAVERQ!AR1)/HAVERQ!AR2 -> 0.74386752 | IK6: =(HAVERQ!AS147-HAVERQ!AS1)/HAVERQ!AS2 -> -0.048963609 | IL6: =(HAVERQ!AT147-HAVERQ!AT1)/HAVERQ!AT2 -> 2.0208248 | IM6: =(HAVERQ!AU147-HAVERQ!AU1)/HAVERQ!AU2 -> -1.5628406 | IN6: =(HAVERQ!AV147-HAVERQ!AV1)/HAVERQ!AV2 -> 0.48966085 | IO6: =(HAVERQ!AW147-HAVERQ!AW1)/HAVERQ!AW2 -> 2.6192848 | IR6: =HAVERQ!AH77 -> #N/A | IS6: =100*(('IPNR ex BNFL'!I46/'IPNR ex BNFL'!I42)-1) -> 14.678179 | IT6: 0
B7: =100*((DataQ!C77/DataQ!C73)-1) -> -2.5390103 | C7: =K7 -> 20.106924 | D7: 0 | I7: 0 | K7: =L7 -> 20.106924 | L7: =100*(HAVERQ!AF11/HAVERQ!AI11) -> 20.106924 | O7: =100*('ONS CVM_SA_(Quarterly)'!B91/'ONS CVM_SA_(Quarterly)'!B$101) -> 111.67979 | P7: =100*('ONS CVM_SA_(Quarterly)'!D91/'ONS CVM_SA_(Quarterly)'!D$101) -> 112.56335 | R7: 100 | U7: ='ONS CVM_SA_(Quarterly)'!C103-'ONS CVM_SA_(Quarterly)'!C$101 -> 762 | V7: ='ONS CVM_SA_(Quarterly)'!D103-'ONS CVM_SA_(Quarterly)'!D$101 -> 640 | W7: ='ONS CVM_SA_(Quarterly)'!E103-'ONS CVM_SA_(Quarterly)'!E$101 -> 1149 | X7: ='ONS CVM_SA_(Quarterly)'!F103-'ONS CVM_SA_(Quarterly)'!F$101 -> 553 | Y7: ='ONS CVM_SA_(Quarterly)'!B103-'ONS CVM_SA_(Quarterly)'!B$101 -> 3170 | AB7: =100*(U7/'ONS CVM_SA_(Quarterly)'!$B$101) -> 1.4156201 | AC7: =100*(V7/'ONS CVM_SA_(Quarterly)'!$B$101) -> 1.1889723 | AD7: =100*(W7/'ONS CVM_SA_(Quarterly)'!$B$101) -> 2.1345768 | AE7: =100*(X7/'ONS CVM_SA_(Quarterly)'!$B$101) -> 1.0273464 | AF7: =100*(('ONS CVM_SA_(Quarterly)'!B103/'ONS CVM_SA_(Quarterly)'!B$101)-1) -> 5.8891283 | AI7: =100*(('ONS CVM_SA_(Quarterly)'!C95-'ONS CVM_SA_(Quarterly)'!C$96)/'ONS CVM_SA_(Quarterly)'!$B$96) -> 1.2049553 | AJ7: =100*(('ONS CVM_SA_(Quarterly)'!D95-'ONS CVM_SA_(Quarterly)'!D$96)/'ONS CVM_SA_(Quarterly)'!$B$96) -> 0.037100365 | AK7: =100*(('ONS CVM_SA_(Quarterly)'!E95-'ONS CVM_SA_(Quarterly)'!E$96)/'ONS CVM_SA_(Quarterly)'!$B$96) -> -0.81782108 | AL7: =100*(('ONS CVM_SA_(Quarterly)'!F95-'ONS CVM_SA_(Quarterly)'!F$96)/'ONS CVM_SA_(Quarterly)'!$B$96) -> -0.36132529 | AM7: =100*(('ONS CVM_SA_(Quarterly)'!B95-'ONS CVM_SA_(Quarterly)'!B$96)/'ONS CVM_SA_(Quarterly)'!$B$96) -> -0.10000968 | AP7: =100*(('ONS CVM_SA_(Quarterly)'!C83-AVERAGE('ONS CVM_SA_(Quarterly)'!C$81:C$84))/AVERAGE('ONS CVM_SA_(Quarterly)'!$B$81:$B$84)) -> 1.3249434 | AQ7: =100*(('ONS CVM_SA_(Quarterly)'!D83-AVERAGE('ONS CVM_SA_(Quarterly)'!D$81:D$84))/AVERAGE('ONS CVM_SA_(Quarterly)'!$B$81:$B$84)) -> 0.28646329 | AR7: =100*(('ONS CVM_SA_(Quarterly)'!E83-AVERAGE('ONS CVM_SA_(Quarterly)'!E$81:E$84))/AVERAGE('ONS CVM_SA_(Quarterly)'!$B$81:$B$84)) -> 0.25404878 | AS7: =100*(('ONS CVM_SA_(Quarterly)'!F83-AVERAGE('ONS CVM_SA_(Quarterly)'!F$81:F$84))/AVERAGE('ONS CVM_SA_(Quarterly)'!$B$81:$B$84)) -> 0.1726073 | AT7: =100*(('ONS CVM_SA_(Quarterly)'!B83-AVERAGE('ONS CVM_SA_(Quarterly)'!B$81:B$84))/AVERAGE('ONS CVM_SA_(Quarterly)'!$B$81:$B$84)) -> 2.0652099 | AV7: 43525 | AW7: =HAVERM!D238 -> 0.75 | AX7: =HAVERM!B238 -> 3.34 | AY7: =HAVERM!C238 -> 2.45 | BA7: 44593 | BB7: =AX42-AX$39 -> 0.25 | BC7: =AY42-AY$39 -> 0 | BD7: 1000 | BF7: 0 | BJ7: =100*(HAVERQ!B123/HAVERQ!B$128) -> 96.969062 | BK7: =100*(HAVERQ!I123/HAVERQ!I$128) -> 105.40917 | BL7: =100*(HAVERQ!J123/HAVERQ!J$128) -> 85.105055 | BM7: =100*(HAVERQ!K123/HAVERQ!K$128) -> 70.34632 | BN7: =100*((HAVERQ!L123+HAVERQ!M123)/(HAVERQ!L$128+HAVERQ!M$128)) -> 104.3644 | BO7: 100 | BR7: =HAVERQ!I123-HAVERQ!I$128 -> 505 | BS7: =HAVERQ!J123-HAVERQ!J$128 -> -1432 | BT7: =HAVERQ!K123-HAVERQ!K$128 -> -959 | BU7: =(HAVERQ!L123+HAVERQ!M123)-(HAVERQ!L$128+HAVERQ!M$128) -> 1729 | BV7: =HAVERQ!N123-HAVERQ!N$128 -> -111 | BW7: =HAVERQ!B123-HAVERQ!B$128 -> -1879 | BZ7: =100*((HAVERQ!I127-HAVERQ!I$128)/HAVERQ!$B$128) -> 0.23550666 | CA7: =100*((HAVERQ!J127-HAVERQ!J$128)/HAVERQ!$B$128) -> -2.7373617 | CB7: =100*((HAVERQ!K127-HAVERQ!K$128)/HAVERQ!$B$128) -> -0.31615963 | CC7: =100*(((HAVERQ!L127+HAVERQ!M127)-(HAVERQ!L$128+HAVERQ!M$128))/HAVERQ!$B$128) -> 0.67587186 | CD7: =CE7-BZ7-CA7-CB7-CC7 -> 2.0421331 | CE7: =100*((HAVERQ!B127-HAVERQ!B$128)/HAVERQ!B$128) -> -0.10000968 | CH7: =HAVERQ!I123 -> 9841 | CI7: =HAVERQ!J123 -> 8182 | CJ7: =HAVERQ!K123 -> 2275 | CK7: =HAVERQ!L123+HAVERQ!M123 -> 41345 | CL7: =HAVERQ!N123 -> 1247 | CO7: =CX7 -> -139 | CP7: =CY7 -> 73 | CQ7: =CZ7 -> -309 | CR7: =DA7 -> 800 | CS7: =DC7 -> 519 | CT7: =+DB7+DD7+DE7+DF7 -> 9 | CU7: =DG7 -> 1729 | CX7: =HAVERQ!L123-HAVERQ!L$128 -> -139 | CY7: =HAVERQ!O123-HAVERQ!O$128 -> 73 | CZ7: =HAVERQ!P123-HAVERQ!P$128 -> -309 | DA7: =HAVERQ!Q123-HAVERQ!Q$128 -> 800 | DB7: =HAVERQ!R123-HAVERQ!R$128 -> 122 | DC7: =HAVERQ!S123-HAVERQ!S$128 -> 519 | DD7: =HAVERQ!T123-HAVERQ!T$128 -> 26 | DE7: =HAVERQ!U123-HAVERQ!U$128 -> -40 | DF7: =HAVERQ!V123-HAVERQ!V$128 -> -99 | DG7: =(HAVERQ!L123+HAVERQ!M123)-(HAVERQ!L$128+HAVERQ!M$128) -> 1729 | DJ7: =100*(HAVERQ!C123/HAVERQ!C$128) -> 98.287824 | DK7: =100*(HAVERQ!D123/HAVERQ!D$128) -> 125.97691 | DL7: =100*(HAVERQ!E123/HAVERQ!E$128) -> 99.873502 | DM7: =100*(HAVERQ!F123/HAVERQ!F$128) -> 98.982208 | DN7: =100*(HAVERQ!G123/HAVERQ!G$128) -> 98.397669 | DO7: =100*(HAVERQ!H123/HAVERQ!H$128) -> 90.509706 | DP7: 100 | DS7: =HAVERQ!D123-HAVERQ!D$128 -> 1170 | DT7: =HAVERQ!E123-HAVERQ!E$128 -> -21 | DU7: =HAVERQ!F123-HAVERQ!F$128 -> -258 | DV7: =HAVERQ!G123-HAVERQ!G$128 -> -594 | DW7: =HAVERQ!H123-HAVERQ!H$128 -> -2508 | DX7: =HAVERQ!C123-HAVERQ!C$128 -> -1878 | EA7: =MIN(EM7:EO7) -> -0.1043378 | EB7: =+EF7-EA7 -> 0.94152221 | EC7: =100*((EJ11/EJ7)-1) -> 1.6332696 | ED7: 0 | EF7: =MAX(EM7:EO7) -> 0.83718441 | EG7: =AVERAGE(EM7:EO7) -> 0.48302103 | EJ7: ='IPNR ex BNFL'!I15 -> 42369 | EL7: 2000 | EM7: =(ER7-ER$2)/ER$3 -> 0.71621648 | EN7: =(ES7-ES$2)/ES$3 -> -0.1043378 | EO7: =(ET7-ET$2)/ET$3 -> 0.83718441 | EQ7: 2000 | ER7: =(HAVERQ!W49*$EW$2)+(HAVERQ!X49*$EX$2)/($EW$2+$EX$2) -> 16.598404 | ES7: =(HAVERQ!AB49*$EW$2)+(HAVERQ!AC49*$EY$2)+(HAVERQ!AD49*$EZ$2)+(HAVERQ!AE49*$FA$2)/($EW$2+$EY$2+$EZ$2+$FA$2) -> -7.704033 | ET7: =(HAVERQ!Y49*$EW$2)+(HAVERQ!Z49*$EX$2)/($EW$2+$EX$2) -> 2.1374408 | FC7: 43525 | FD7: =100*((HAVERM!E238+HAVERM!F238)/(HAVERM!E$249+HAVERM!F$249)) -> 98.884853 | FE7: =100*(HAVERM!E238/HAVERM!E$249) -> 99.062319 | FF7: =100*(HAVERM!F238/HAVERM!F$249) -> 98.787477 | FG7: 100 | FV7: 42401 | FW7: =HAVERM!G201 -> 347792 | FY7: =FW7-FW6 -> 359 | GD7: =100*(DataQ!W157/DataQ!W$194) -> 74.929721 | GE7: =100*(DataQ!X157/DataQ!X$194) -> 72.560105 | GF7: =100*(DataQ!C157/DataQ!C$194) -> 68.872794 | GH7: 100 | GK7: =100*(DataQ!Z137/AVERAGE(DataQ!$Z$203:$Z$206)) -> 71.61797 | GL7: =100*(DataQ!C137/AVERAGE(DataQ!$C$203:$C$206)) -> 74.14463 | GM7: 100 | GP7: =100*(DataQ!Z137/DataQ!$Z$194) -> 71.350776 | GQ7: =100*(DataQ!C137/DataQ!$C$194) -> 71.571442 | GR7: 100 | GU7: =HB7 -> 96.969062 | GV7: =MIN(HC7:HH7) -> 95.909498 | GW7: =+GY7-GV7 -> 7.9581683 | GX7: 100 | GY7: =MAX(HC7:HH7) -> 103.86767 | HB7: =100*(DataQ!C189/DataQ!C$194) -> 96.969062 | HC7: =100*(DataQ!Q189/DataQ!Q$194) -> 96.104771 | HD7: =100*(DataQ!R189/DataQ!R$194) -> 103.86767 | HE7: =100*(DataQ!S189/DataQ!S$194) -> 98.711387 | HF7: =100*(DataQ!T189/DataQ!T$194) -> 95.909498 | HG7: =100*(DataQ!U189/DataQ!U$194) -> 99.390287 | HH7: =100*(DataQ!V189/DataQ!V$194) -> 96.997835 | HK7: =HR7 -> 96.969062 | HL7: =MIN(HS7:HX7) -> 95.909498 | HM7: =+HO7-HL7 -> 7.9581683 | HN7: 100 | HO7: =MAX(HS7:HX7) -> 103.86767 | HR7: =100*(DataQ!C189/DataQ!C$194) -> 96.969062 | HS7: =100*(DataQ!Q189/DataQ!Q$194) -> 96.104771 | HT7: =100*(DataQ!R189/DataQ!R$194) -> 103.86767 | HU7: =100*(DataQ!S189/DataQ!S$194) -> 98.711387 | HV7: =100*(DataQ!T189/DataQ!T$194) -> 95.909498 | HW7: =100*(DataQ!U189/DataQ!U$194) -> 99.390287 | HX7: =100*(DataQ!V189/DataQ!V$194) -> 96.997835 | HZ7: 1992 | IA7: =DataA!J26/'Chart Data'!IF7 -> 1.967248 | IB7: =IB6*(1+$ID$5/100) -> 1.843644 | IC7: =100*((IA7/IB7)-1) -> 6.7043282 | IF7: =DataA!K26*DataA!L26 -> 844768.45 | IH7: Consumer services | II7: =(HAVERQ!AX147-HAVERQ!AX1)/HAVERQ!AX2 -> 0.27759281 | IJ7: =(HAVERQ!AY147-HAVERQ!AY1)/HAVERQ!AY2 -> 1.8605197 | IK7: =(HAVERQ!AZ147-HAVERQ!AZ1)/HAVERQ!AZ2 -> 0.81079388 | IL7: =(HAVERQ!BA147-HAVERQ!BA1)/HAVERQ!BA2 -> 2.5848416 | IM7: =(HAVERQ!BB147-HAVERQ!BB1)/HAVERQ!BB2 -> -0.15880748 | IN7: =(HAVERQ!BC147-HAVERQ!BC1)/HAVERQ!BC2 -> 0.98110399 | IO7: =(HAVERQ!BD147-HAVERQ!BD1)/HAVERQ!BD2 -> 0.16358536 | IR7: =HAVERQ!AH78 -> -4.2 | IS7: =100*(('IPNR ex BNFL'!I47/'IPNR ex BNFL'!I43)-1) -> 1.7949732 | IT7: 0
B8: =100*((DataQ!C78/DataQ!C74)-1) -> -1.2784077 | C8: =K8 -> 18.468171 | D8: 0 | I8: 0 | K8: =L8 -> 18.468171 | L8: =100*(HAVERQ!AF12/HAVERQ!AI12) -> 18.468171 | O8: =100*('ONS CVM_SA_(Quarterly)'!B92/'ONS CVM_SA_(Quarterly)'!B$101) -> 112.46192 | P8: =100*('ONS CVM_SA_(Quarterly)'!D92/'ONS CVM_SA_(Quarterly)'!D$101) -> 107.88785 | R8: 100 | U8: ='ONS CVM_SA_(Quarterly)'!C104-'ONS CVM_SA_(Quarterly)'!C$101 -> 1538 | V8: ='ONS CVM_SA_(Quarterly)'!D104-'ONS CVM_SA_(Quarterly)'!D$101 -> 93 | W8: ='ONS CVM_SA_(Quarterly)'!E104-'ONS CVM_SA_(Quarterly)'!E$101 -> 927 | X8: ='ONS CVM_SA_(Quarterly)'!F104-'ONS CVM_SA_(Quarterly)'!F$101 -> 630 | Y8: ='ONS CVM_SA_(Quarterly)'!B104-'ONS CVM_SA_(Quarterly)'!B$101 -> 3350 | AB8: =100*(U8/'ONS CVM_SA_(Quarterly)'!$B$101) -> 2.857249 | AC8: =100*(V8/'ONS CVM_SA_(Quarterly)'!$B$101) -> 0.17277253 | AD8: =100*(W8/'ONS CVM_SA_(Quarterly)'!$B$101) -> 1.722152 | AE8: =100*(X8/'ONS CVM_SA_(Quarterly)'!$B$101) -> 1.1703946 | AF8: =100*(('ONS CVM_SA_(Quarterly)'!B104/'ONS CVM_SA_(Quarterly)'!B$101)-1) -> 6.2235268 | AI8: =100*(('ONS CVM_SA_(Quarterly)'!C96-'ONS CVM_SA_(Quarterly)'!C$96)/'ONS CVM_SA_(Quarterly)'!$B$96) -> 0 | AJ8: =100*(('ONS CVM_SA_(Quarterly)'!D96-'ONS CVM_SA_(Quarterly)'!D$96)/'ONS CVM_SA_(Quarterly)'!$B$96) -> 0 | AK8: =100*(('ONS CVM_SA_(Quarterly)'!E96-'ONS CVM_SA_(Quarterly)'!E$96)/'ONS CVM_SA_(Quarterly)'!$B$96) -> 0 | AL8: =100*(('ONS CVM_SA_(Quarterly)'!F96-'ONS CVM_SA_(Quarterly)'!F$96)/'ONS CVM_SA_(Quarterly)'!$B$96) -> 0 | AM8: =100*(('ONS CVM_SA_(Quarterly)'!B96-'ONS CVM_SA_(Quarterly)'!B$96)/'ONS CVM_SA_(Quarterly)'!$B$96) -> 0 | AP8: =100*(('ONS CVM_SA_(Quarterly)'!C84-AVERAGE('ONS CVM_SA_(Quarterly)'!C$81:C$84))/AVERAGE('ONS CVM_SA_(Quarterly)'!$B$81:$B$84)) -> -2.9553936 | AQ8: =100*(('ONS CVM_SA_(Quarterly)'!D84-AVERAGE('ONS CVM_SA_(Quarterly)'!D$81:D$84))/AVERAGE('ONS CVM_SA_(Quarterly)'!$B$81:$B$84)) -> -0.59683229 | AR8: =100*(('ONS CVM_SA_(Quarterly)'!E84-AVERAGE('ONS CVM_SA_(Quarterly)'!E$81:E$84))/AVERAGE('ONS CVM_SA_(Quarterly)'!$B$81:$B$84)) -> -0.3715514 | AS8: =100*(('ONS CVM_SA_(Quarterly)'!F84-AVERAGE('ONS CVM_SA_(Quarterly)'!F$81:F$84))/AVERAGE('ONS CVM_SA_(Quarterly)'!$B$81:$B$84)) -> 0.22122908 | AT8: =100*(('ONS CVM_SA_(Quarterly)'!B84-AVERAGE('ONS CVM_SA_(Quarterly)'!B$81:B$84))/AVERAGE('ONS CVM_SA_(Quarterly)'!$B$81:$B$84)) -> -1.7110813 | AV8: 43556 | AW8: =HAVERM!D239 -> 0.75 | AX8: =HAVERM!B239 -> 3.34 | AY8: =HAVERM!C239 -> 2.45 | BA8: 44621 | BB8: =AX43-AX$39 -> 0.35 | BC8: =AY43-AY$39 -> 0.03 | BD8: 1000 | BF8: 0 | BJ8: =100*(HAVERQ!B124/HAVERQ!B$128) -> 97.648159 | BK8: =100*(HAVERQ!I124/HAVERQ!I$128) -> 105.09854 | BL8: =100*(HAVERQ!J124/HAVERQ!J$128) -> 90.815477 | BM8: =100*(HAVERQ!K124/HAVERQ!K$128) -> 75.819419 | BN8: =100*((HAVERQ!L124+HAVERQ!M124)/(HAVERQ!L$128+HAVERQ!M$128)) -> 102.98364 | BO8: 100 | BR8: =HAVERQ!I124-HAVERQ!I$128 -> 476 | BS8: =HAVERQ!J124-HAVERQ!J$128 -> -883 | BT8: =HAVERQ!K124-HAVERQ!K$128 -> -782 | BU8: =(HAVERQ!L124+HAVERQ!M124)-(HAVERQ!L$128+HAVERQ!M$128) -> 1182 | BV8: =HAVERQ!N124-HAVERQ!N$128 -> -123 | BW8: =HAVERQ!B124-HAVERQ!B$128 -> -1458 | BZ8: =100*((HAVERQ!I128-HAVERQ!I$128)/HAVERQ!$B$128) -> 0 | CA8: =100*((HAVERQ!J128-HAVERQ!J$128)/HAVERQ!$B$128) -> 0 | CB8: =100*((HAVERQ!K128-HAVERQ!K$128)/HAVERQ!$B$128) -> 0 | CC8: =100*(((HAVERQ!L128+HAVERQ!M128)-(HAVERQ!L$128+HAVERQ!M$128))/HAVERQ!$B$128) -> 0 | CD8: =CE8-BZ8-CA8-CB8-CC8 -> 0 | CE8: =100*((HAVERQ!B128-HAVERQ!B$128)/HAVERQ!B$128) -> 0 | CH8: =HAVERQ!I124 -> 9812 | CI8: =HAVERQ!J124 -> 8731 | CJ8: =HAVERQ!K124 -> 2452 | CK8: =HAVERQ!L124+HAVERQ!M124 -> 40798 | CL8: =HAVERQ!N124 -> 1235 | CO8: =CX8 -> -626 | CP8: =CY8 -> 265 | CQ8: =CZ8 -> 67 | CR8: =DA8 -> 2021 | CS8: =DC8 -> 311 | CT8: =+DB8+DD8+DE8+DF8 -> -43 | CU8: =DG8 -> 1182 | CX8: =HAVERQ!L124-HAVERQ!L$128 -> -626 | CY8: =HAVERQ!O124-HAVERQ!O$128 -> 265 | CZ8: =HAVERQ!P124-HAVERQ!P$128 -> 67 | DA8: =HAVERQ!Q124-HAVERQ!Q$128 -> 2021 | DB8: =HAVERQ!R124-HAVERQ!R$128 -> 178 | DC8: =HAVERQ!S124-HAVERQ!S$128 -> 311 | DD8: =HAVERQ!T124-HAVERQ!T$128 -> 112 | DE8: =HAVERQ!U124-HAVERQ!U$128 -> 27 | DF8: =HAVERQ!V124-HAVERQ!V$128 -> -360 | DG8: =(HAVERQ!L124+HAVERQ!M124)-(HAVERQ!L$128+HAVERQ!M$128) -> 1182 | DJ8: =100*(HAVERQ!C124/HAVERQ!C$128) -> 98.155627 | DK8: =100*(HAVERQ!D124/HAVERQ!D$128) -> 130.17318 | DL8: =100*(HAVERQ!E124/HAVERQ!E$128) -> 97.078489 | DM8: =100*(HAVERQ!F124/HAVERQ!F$128) -> 98.982208 | DN8: =100*(HAVERQ!G124/HAVERQ!G$128) -> 98.888619 | DO8: =100*(HAVERQ!H124/HAVERQ!H$128) -> 90.237257 | DP8: 100 | DS8: =HAVERQ!D124-HAVERQ!D$128 -> 1359 | DT8: =HAVERQ!E124-HAVERQ!E$128 -> -485 | DU8: =HAVERQ!F124-HAVERQ!F$128 -> -258 | DV8: =HAVERQ!G124-HAVERQ!G$128 -> -412 | DW8: =HAVERQ!H124-HAVERQ!H$128 -> -2580 | DX8: =HAVERQ!C124-HAVERQ!C$128 -> -2023 | EA8: =MIN(EM8:EO8) -> 0.11963873 | EB8: =+EF8-EA8 -> 0.86228838 | EC8: =100*((EJ12/EJ8)-1) -> 6.3559423 | ED8: 0 | EF8: =MAX(EM8:EO8) -> 0.98192711 | EG8: =AVERAGE(EM8:EO8) -> 0.6912452 | EJ8: ='IPNR ex BNFL'!I16 -> 41945 | EM8: =(ER8-ER$2)/ER$3 -> 0.97216977 | EN8: =(ES8-ES$2)/ES$3 -> 0.11963873 | EO8: =(ET8-ET$2)/ET$3 -> 0.98192711 | ER8: =(HAVERQ!W50*$EW$2)+(HAVERQ!X50*$EX$2)/($EW$2+$EX$2) -> 19.598404 | ES8: =(HAVERQ!AB50*$EW$2)+(HAVERQ!AC50*$EY$2)+(HAVERQ!AD50*$EZ$2)+(HAVERQ!AE50*$FA$2)/($EW$2+$EY$2+$EZ$2+$FA$2) -> -4.5522789 | ET8: =(HAVERQ!Y50*$EW$2)+(HAVERQ!Z50*$EX$2)/($EW$2+$EX$2) -> 2.3647654 | FC8: 43556 | FD8: =100*((HAVERM!E239+HAVERM!F239)/(HAVERM!E$249+HAVERM!F$249)) -> 98.09304 | FE8: =100*(HAVERM!E239/HAVERM!E$249) -> 98.668082 | FF8: =100*(HAVERM!F239/HAVERM!F$249) -> 97.777511 | FG8: 100 | FV8: 42430 | FW8: =HAVERM!G202 -> 349767 | FY8: =FW8-FW7 -> 1975 | GD8: =100*(DataQ!W158/DataQ!W$194) -> 79.266198 | GE8: =100*(DataQ!X158/DataQ!X$194) -> 77.549676 | GF8: =100*(DataQ!C158/DataQ!C$194) -> 73.418395 | GH8: 100 | GK8: =100*(DataQ!Z138/AVERAGE(DataQ!$Z$203:$Z$206)) -> 71.236045 | GL8: =100*(DataQ!C138/AVERAGE(DataQ!$C$203:$C$206)) -> 73.773656 | GM8: 100 | GP8: =100*(DataQ!Z138/DataQ!$Z$194) -> 70.970276 | GQ8: =100*(DataQ!C138/DataQ!$C$194) -> 71.213343 | GR8: 100 | GU8: =HB8 -> 97.648159 | GV8: =MIN(HC8:HH8) -> 96.743943 | GW8: =+GY8-GV8 -> 9.3122804 | GX8: 100 | GY8: =MAX(HC8:HH8) -> 106.05622 | HB8: =100*(DataQ!C190/DataQ!C$194) -> 97.648159 | HC8: =100*(DataQ!Q190/DataQ!Q$194) -> 96.97337 | HD8: =100*(DataQ!R190/DataQ!R$194) -> 106.05622 | HE8: =100*(DataQ!S190/DataQ!S$194) -> 99.826357 | HF8: =100*(DataQ!T190/DataQ!T$194) -> 96.743943 | HG8: =100*(DataQ!U190/DataQ!U$194) -> 98.91243 | HH8: =100*(DataQ!V190/DataQ!V$194) -> 97.285285 | HK8: =HR8 -> 97.648159 | HL8: =MIN(HS8:HX8) -> 96.743943 | HM8: =+HO8-HL8 -> 9.3122804 | HN8: 100 | HO8: =MAX(HS8:HX8) -> 106.05622 | HR8: =100*(DataQ!C190/DataQ!C$194) -> 97.648159 | HS8: =100*(DataQ!Q190/DataQ!Q$194) -> 96.97337 | HT8: =100*(DataQ!R190/DataQ!R$194) -> 106.05622 | HU8: =100*(DataQ!S190/DataQ!S$194) -> 99.826357 | HV8: =100*(DataQ!T190/DataQ!T$194) -> 96.743943 | HW8: =100*(DataQ!U190/DataQ!U$194) -> 98.91243 | HX8: =100*(DataQ!V190/DataQ!V$194) -> 97.285285 | HZ8: 1993 | IA8: =DataA!J27/'Chart Data'!IF8 -> 2.0277195 | IB8: =IB7*(1+$ID$5/100) -> 1.8926217 | IC8: =100*((IA8/IB8)-1) -> 7.1381273 | IF8: =DataA!K27*DataA!L27 -> 834990.75 | IR8: =HAVERQ!AH79 -> -27.5 | IS8: =100*(('IPNR ex BNFL'!I48/'IPNR ex BNFL'!I44)-1) -> 10.124899 | IT8: 0
A9: 1991 | B9: =100*((DataQ!C79/DataQ!C75)-1) -> -3.4497683 | C9: =K9 -> 21.139532 | D9: 0 | F9: 1991 | G9: =100*((AVERAGE(DataQ!C76:C79)/AVERAGE(DataQ!C72:C75))-1) -> -1.3371628 | H9: =AVERAGE(K6:K9) -> 19.935098 | I9: 0 | K9: =L9 -> 21.139532 | L9: =100*(HAVERQ!AF13/HAVERQ!AI13) -> 21.139532 | N9: 2019 | O9: =100*('ONS CVM_SA_(Quarterly)'!B93/'ONS CVM_SA_(Quarterly)'!B$101) -> 113.69733 | P9: =100*('ONS CVM_SA_(Quarterly)'!D93/'ONS CVM_SA_(Quarterly)'!D$101) -> 107.45463 | R9: 100 | T9: 2022 | U9: ='ONS CVM_SA_(Quarterly)'!C105-'ONS CVM_SA_(Quarterly)'!C$101 -> 916 | V9: ='ONS CVM_SA_(Quarterly)'!D105-'ONS CVM_SA_(Quarterly)'!D$101 -> 1387 | W9: ='ONS CVM_SA_(Quarterly)'!E105-'ONS CVM_SA_(Quarterly)'!E$101 -> 2002 | X9: ='ONS CVM_SA_(Quarterly)'!F105-'ONS CVM_SA_(Quarterly)'!F$101 -> 524 | Y9: ='ONS CVM_SA_(Quarterly)'!B105-'ONS CVM_SA_(Quarterly)'!B$101 -> 5074 | AA9: 2022 | AB9: =100*(U9/'ONS CVM_SA_(Quarterly)'!$B$101) -> 1.7017166 | AC9: =100*(V9/'ONS CVM_SA_(Quarterly)'!$B$101) -> 2.5767259 | AD9: =100*(W9/'ONS CVM_SA_(Quarterly)'!$B$101) -> 3.7192539 | AE9: =100*(X9/'ONS CVM_SA_(Quarterly)'!$B$101) -> 0.97347106 | AF9: =100*(('ONS CVM_SA_(Quarterly)'!B105/'ONS CVM_SA_(Quarterly)'!B$101)-1) -> 9.4263209 | AH9: 2020 | AI9: =100*(('ONS CVM_SA_(Quarterly)'!C97-'ONS CVM_SA_(Quarterly)'!C$96)/'ONS CVM_SA_(Quarterly)'!$B$96) -> 0.67587186 | AJ9: =100*(('ONS CVM_SA_(Quarterly)'!D97-'ONS CVM_SA_(Quarterly)'!D$96)/'ONS CVM_SA_(Quarterly)'!$B$96) -> -0.014517534 | AK9: =100*(('ONS CVM_SA_(Quarterly)'!E97-'ONS CVM_SA_(Quarterly)'!E$96)/'ONS CVM_SA_(Quarterly)'!$B$96) -> -2.2679614 | AL9: =100*(('ONS CVM_SA_(Quarterly)'!F97-'ONS CVM_SA_(Quarterly)'!F$96)/'ONS CVM_SA_(Quarterly)'!$B$96) -> 0.35648611 | AM9: =100*(('ONS CVM_SA_(Quarterly)'!B97-'ONS CVM_SA_(Quarterly)'!B$96)/'ONS CVM_SA_(Quarterly)'!$B$96) -> -2.2502178 | AO9: 2017 | AP9: =100*(('ONS CVM_SA_(Quarterly)'!C85-AVERAGE('ONS CVM_SA_(Quarterly)'!C$81:C$84))/AVERAGE('ONS CVM_SA_(Quarterly)'!$B$81:$B$84)) -> -1.1790781 | AQ9: =100*(('ONS CVM_SA_(Quarterly)'!D85-AVERAGE('ONS CVM_SA_(Quarterly)'!D$81:D$84))/AVERAGE('ONS CVM_SA_(Quarterly)'!$B$81:$B$84)) -> 0.27187676 | AR9: =100*(('ONS CVM_SA_(Quarterly)'!E85-AVERAGE('ONS CVM_SA_(Quarterly)'!E$81:E$84))/AVERAGE('ONS CVM_SA_(Quarterly)'!$B$81:$B$84)) -> -0.21758244 | AS9: =100*(('ONS CVM_SA_(Quarterly)'!F85-AVERAGE('ONS CVM_SA_(Quarterly)'!F$81:F$84))/AVERAGE('ONS CVM_SA_(Quarterly)'!$B$81:$B$84)) -> 0.209884 | AT9: =100*(('ONS CVM_SA_(Quarterly)'!B85-AVERAGE('ONS CVM_SA_(Quarterly)'!B$81:B$84))/AVERAGE('ONS CVM_SA_(Quarterly)'!$B$81:$B$84)) -> 0.54983124 | AV9: 43586 | AW9: =HAVERM!D240 -> 0.75 | AX9: =HAVERM!B240 -> 3.32 | AY9: =HAVERM!C240 -> 2.43 | BA9: 44652 | BB9: =AX44-AX$39 -> 0.45 | BC9: =AY44-AY$39 -> 0.03 | BD9: 1000 | BF9: 0 | BI9: 2019 | BJ9: =100*(HAVERQ!B125/HAVERQ!B$128) -> 98.720844 | BK9: =100*(HAVERQ!I125/HAVERQ!I$128) -> 107.00514 | BL9: =100*(HAVERQ!J125/HAVERQ!J$128) -> 86.800499 | BM9: =100*(HAVERQ!K125/HAVERQ!K$128) -> 91.465677 | BN9: =100*((HAVERQ!L125+HAVERQ!M125)/(HAVERQ!L$128+HAVERQ!M$128)) -> 99.67185 | BO9: 100 | BQ9: 2019 | BR9: =HAVERQ!I125-HAVERQ!I$128 -> 654 | BS9: =HAVERQ!J125-HAVERQ!J$128 -> -1269 | BT9: =HAVERQ!K125-HAVERQ!K$128 -> -276 | BU9: =(HAVERQ!L125+HAVERQ!M125)-(HAVERQ!L$128+HAVERQ!M$128) -> -130 | BV9: =HAVERQ!N125-HAVERQ!N$128 -> -104 | BW9: =HAVERQ!B125-HAVERQ!B$128 -> -793 | BY9: 2020 | BZ9: =100*((HAVERQ!I129-HAVERQ!I$128)/HAVERQ!$B$128) -> -0.040326483 | CA9: =100*((HAVERQ!J129-HAVERQ!J$128)/HAVERQ!$B$128) -> -2.8228538 | CB9: =100*((HAVERQ!K129-HAVERQ!K$128)/HAVERQ!$B$128) -> -0.34035552 | CC9: =100*(((HAVERQ!L129+HAVERQ!M129)-(HAVERQ!L$128+HAVERQ!M$128))/HAVERQ!$B$128) -> -4.9101526 | CD9: =CE9-BZ9-CA9-CB9-CC9 -> 5.8634707 | CE9: =100*((HAVERQ!B129-HAVERQ!B$128)/HAVERQ!B$128) -> -2.2502178 | CG9: 2019 | CH9: =HAVERQ!I125 -> 9990 | CI9: =HAVERQ!J125 -> 8345 | CJ9: =HAVERQ!K125 -> 2958 | CK9: =HAVERQ!L125+HAVERQ!M125 -> 39486 | CL9: =HAVERQ!N125 -> 1254 | CN9: 2019 | CO9: =CX9 -> -297 | CP9: =CY9 -> 65 | CQ9: =CZ9 -> 138 | CR9: =DA9 -> 867 | CS9: =DC9 -> 100 | CT9: =+DB9+DD9+DE9+DF9 -> -403 | CU9: =DG9 -> -130 | CW9: 2019 | CX9: =HAVERQ!L125-HAVERQ!L$128 -> -297 | CY9: =HAVERQ!O125-HAVERQ!O$128 -> 65 | CZ9: =HAVERQ!P125-HAVERQ!P$128 -> 138 | DA9: =HAVERQ!Q125-HAVERQ!Q$128 -> 867 | DB9: =HAVERQ!R125-HAVERQ!R$128 -> -23 | DC9: =HAVERQ!S125-HAVERQ!S$128 -> 100 | DD9: =HAVERQ!T125-HAVERQ!T$128 -> 167 | DE9: =HAVERQ!U125-HAVERQ!U$128 -> -107 | DF9: =HAVERQ!V125-HAVERQ!V$128 -> -440 | DG9: =(HAVERQ!L125+HAVERQ!M125)-(HAVERQ!L$128+HAVERQ!M$128) -> -130 | DI9: 2019 | DJ9: =100*(HAVERQ!C125/HAVERQ!C$128) -> 101.15148 | DK9: =100*(HAVERQ!D125/HAVERQ!D$128) -> 118.51687 | DL9: =100*(HAVERQ!E125/HAVERQ!E$128) -> 99.506054 | DM9: =100*(HAVERQ!F125/HAVERQ!F$128) -> 101.5543 | DN9: =100*(HAVERQ!G125/HAVERQ!G$128) -> 103.73338 | DO9: =100*(HAVERQ!H125/HAVERQ!H$128) -> 94.569947 | DP9: 100 | DR9: 2019 | DS9: =HAVERQ!D125-HAVERQ!D$128 -> 834 | DT9: =HAVERQ!E125-HAVERQ!E$128 -> -82 | DU9: =HAVERQ!F125-HAVERQ!F$128 -> 394 | DV9: =HAVERQ!G125-HAVERQ!G$128 -> 1384 | DW9: =HAVERQ!H125-HAVERQ!H$128 -> -1435 | DX9: =HAVERQ!C125-HAVERQ!C$128 -> 1263 | DZ9: 2001 | EA9: =MIN(EM9:EO9) -> 0.55360156 | EB9: =+EF9-EA9 -> 0.47171535 | EC9: =100*((EJ13/EJ9)-1) -> 1.6481753 | ED9: 0 | EF9: =MAX(EM9:EO9) -> 1.0253169 | EG9: =AVERAGE(EM9:EO9) -> 0.79922117 | EI9: 2000 | EJ9: ='IPNR ex BNFL'!I17 -> 43624 | EM9: =(ER9-ER$2)/ER$3 -> 1.0253169 | EN9: =(ES9-ES$2)/ES$3 -> 0.55360156 | EO9: =(ET9-ET$2)/ET$3 -> 0.81874503 | ER9: =(HAVERQ!W51*$EW$2)+(HAVERQ!X51*$EX$2)/($EW$2+$EX$2) -> 20.221335 | ES9: =(HAVERQ!AB51*$EW$2)+(HAVERQ!AC51*$EY$2)+(HAVERQ!AD51*$EZ$2)+(HAVERQ!AE51*$FA$2)/($EW$2+$EY$2+$EZ$2+$FA$2) -> 1.5543614 | ET9: =(HAVERQ!Y51*$EW$2)+(HAVERQ!Z51*$EX$2)/($EW$2+$EX$2) -> 2.1084809 | FC9: 43586 | FD9: =100*((HAVERM!E240+HAVERM!F240)/(HAVERM!E$249+HAVERM!F$249)) -> 99.160108 | FE9: =100*(HAVERM!E240/HAVERM!E$249) -> 99.295132 | FF9: =100*(HAVERM!F240/HAVERM!F$249) -> 99.08602 | FG9: 100 | FV9: 42461 | FW9: =HAVERM!G203 -> 345227 | FY9: =FW9-FW8 -> -4540 | GC9: 2011 | GD9: =100*(DataQ!W159/DataQ!W$194) -> 72.139538 | GE9: =100*(DataQ!X159/DataQ!X$194) -> 70.642588 | GF9: =100*(DataQ!C159/DataQ!C$194) -> 68.280801 | GH9: 100 | GJ9: 2006 | GK9: =100*(DataQ!Z139/AVERAGE(DataQ!$Z$203:$Z$206)) -> 74.848566 | GL9: =100*(DataQ!C139/AVERAGE(DataQ!$C$203:$C$206)) -> 77.536868 | GM9: 100 | GO9: 2006 | GP9: =100*(DataQ!Z139/DataQ!$Z$194) -> 74.569319 | GQ9: =100*(DataQ!C139/DataQ!$C$194) -> 74.845953 | GR9: 100 | GT9: 2019 | GU9: =HB9 -> 98.720844 | GV9: =MIN(HC9:HH9) -> 97.150651 | GW9: =+GY9-GV9 -> 8.9744031 | GX9: 100 | GY9: =MAX(HC9:HH9) -> 106.12505 | HA9: 2019 | HB9: =100*(DataQ!C191/DataQ!C$194) -> 98.720844 | HC9: =100*(DataQ!Q191/DataQ!Q$194) -> 97.626502 | HD9: =100*(DataQ!R191/DataQ!R$194) -> 106.12505 | HE9: =100*(DataQ!S191/DataQ!S$194) -> 101.27947 | HF9: =100*(DataQ!T191/DataQ!T$194) -> 97.150651 | HG9: =100*(DataQ!U191/DataQ!U$194) -> 99.355527 | HH9: =100*(DataQ!V191/DataQ!V$194) -> 101.984 | HJ9: 2019 | HK9: =HR9 -> 98.720844 | HL9: =MIN(HS9:HX9) -> 97.150651 | HM9: =+HO9-HL9 -> 8.9744031 | HN9: 100 | HO9: =MAX(HS9:HX9) -> 106.12505 | HQ9: 2019 | HR9: =100*(DataQ!C191/DataQ!C$194) -> 98.720844 | HS9: =100*(DataQ!Q191/DataQ!Q$194) -> 97.626502 | HT9: =100*(DataQ!R191/DataQ!R$194) -> 106.12505 | HU9: =100*(DataQ!S191/DataQ!S$194) -> 101.27947 | HV9: =100*(DataQ!T191/DataQ!T$194) -> 97.150651 | HW9: =100*(DataQ!U191/DataQ!U$194) -> 99.355527 | HX9: =100*(DataQ!V191/DataQ!V$194) -> 101.984 | HZ9: 1994 | IA9: =DataA!J28/'Chart Data'!IF9 -> 2.0419879 | IB9: =IB8*(1+$ID$5/100) -> 1.9429006 | IC9: =100*((IA9/IB9)-1) -> 5.0999682 | IF9: =DataA!K28*DataA!L28 -> 847387.01 | IQ9: 2008 | IR9: =HAVERQ!AH80 -> -8.3 | IS9: =100*(('IPNR ex BNFL'!I49/'IPNR ex BNFL'!I45)-1) -> -2.5877967 | IT9: 0
B10: =100*((DataQ!C80/DataQ!C76)-1) -> -9.0430141 | C10: =K10 -> 21.655655 | D10: 0 | G10: =100*((AVERAGE(DataQ!C77:C80)/AVERAGE(DataQ!C73:C76))-1) -> -4.0916 | H10: =AVERAGE(K7:K10) -> 20.34257 | I10: 0 | K10: =L10 -> 21.655655 | L10: =100*(HAVERQ!AF14/HAVERQ!AI14) -> 21.655655 | O10: =100*('ONS CVM_SA_(Quarterly)'!B94/'ONS CVM_SA_(Quarterly)'!B$101) -> 115.51795 | P10: =100*('ONS CVM_SA_(Quarterly)'!D94/'ONS CVM_SA_(Quarterly)'!D$101) -> 109.13847 | R10: 100 | U10: ='ONS CVM_SA_(Quarterly)'!C106-'ONS CVM_SA_(Quarterly)'!C$101 -> 3063 | V10: ='ONS CVM_SA_(Quarterly)'!D106-'ONS CVM_SA_(Quarterly)'!D$101 -> 1819 | W10: ='ONS CVM_SA_(Quarterly)'!E106-'ONS CVM_SA_(Quarterly)'!E$101 -> 1388 | X10: ='ONS CVM_SA_(Quarterly)'!F106-'ONS CVM_SA_(Quarterly)'!F$101 -> -8 | Y10: ='ONS CVM_SA_(Quarterly)'!B106-'ONS CVM_SA_(Quarterly)'!B$101 -> 6504 | AB10: =100*(U10/'ONS CVM_SA_(Quarterly)'!$B$101) -> 5.690347 | AC10: =100*(V10/'ONS CVM_SA_(Quarterly)'!$B$101) -> 3.3792822 | AD10: =100*(W10/'ONS CVM_SA_(Quarterly)'!$B$101) -> 2.5785836 | AE10: =100*(X10/'ONS CVM_SA_(Quarterly)'!$B$101) -> -0.014862154 | AF10: =100*(('ONS CVM_SA_(Quarterly)'!B106/'ONS CVM_SA_(Quarterly)'!B$101)-1) -> 12.082931 | AI10: =100*(('ONS CVM_SA_(Quarterly)'!C98-'ONS CVM_SA_(Quarterly)'!C$96)/'ONS CVM_SA_(Quarterly)'!$B$96) -> -3.9342517 | AJ10: =100*(('ONS CVM_SA_(Quarterly)'!D98-'ONS CVM_SA_(Quarterly)'!D$96)/'ONS CVM_SA_(Quarterly)'!$B$96) -> -5.5763461 | AK10: =100*(('ONS CVM_SA_(Quarterly)'!E98-'ONS CVM_SA_(Quarterly)'!E$96)/'ONS CVM_SA_(Quarterly)'!$B$96) -> -7.1571442 | AL10: =100*(('ONS CVM_SA_(Quarterly)'!F98-'ONS CVM_SA_(Quarterly)'!F$96)/'ONS CVM_SA_(Quarterly)'!$B$96) -> -2.9051199 | AM10: =100*(('ONS CVM_SA_(Quarterly)'!B98-'ONS CVM_SA_(Quarterly)'!B$96)/'ONS CVM_SA_(Quarterly)'!$B$96) -> -21.039133 | AP10: =100*(('ONS CVM_SA_(Quarterly)'!C86-AVERAGE('ONS CVM_SA_(Quarterly)'!C$81:C$84))/AVERAGE('ONS CVM_SA_(Quarterly)'!$B$81:$B$84)) -> 0.46433795 | AQ10: =100*(('ONS CVM_SA_(Quarterly)'!D86-AVERAGE('ONS CVM_SA_(Quarterly)'!D$81:D$84))/AVERAGE('ONS CVM_SA_(Quarterly)'!$B$81:$B$84)) -> 0.31563636 | AR10: =100*(('ONS CVM_SA_(Quarterly)'!E86-AVERAGE('ONS CVM_SA_(Quarterly)'!E$81:E$84))/AVERAGE('ONS CVM_SA_(Quarterly)'!$B$81:$B$84)) -> -1.7264782 | AS10: =100*(('ONS CVM_SA_(Quarterly)'!F86-AVERAGE('ONS CVM_SA_(Quarterly)'!F$81:F$84))/AVERAGE('ONS CVM_SA_(Quarterly)'!$B$81:$B$84)) -> 0.7495857 | AT10: =100*(('ONS CVM_SA_(Quarterly)'!B86-AVERAGE('ONS CVM_SA_(Quarterly)'!B$81:B$84))/AVERAGE('ONS CVM_SA_(Quarterly)'!$B$81:$B$84)) -> 0.047406231 | AV10: 43617 | AW10: =HAVERM!D241 -> 0.75 | AX10: =HAVERM!B241 -> 3.31 | AY10: =HAVERM!C241 -> 2.43 | BA10: 44682 | BB10: =AX45-AX$39 -> 0.65 | BC10: =AY45-AY$39 -> 0.06 | BD10: 1000 | BF10: 0 | BJ10: =100*(HAVERQ!B126/HAVERQ!B$128) -> 100.30164 | BK10: =100*(HAVERQ!I126/HAVERQ!I$128) -> 103.96315 | BL10: =100*(HAVERQ!J126/HAVERQ!J$128) -> 83.107968 | BM10: =100*(HAVERQ!K126/HAVERQ!K$128) -> 97.990105 | BN10: =100*((HAVERQ!L126+HAVERQ!M126)/(HAVERQ!L$128+HAVERQ!M$128)) -> 99.553211 | BO10: 100 | BR10: =HAVERQ!I126-HAVERQ!I$128 -> 370 | BS10: =HAVERQ!J126-HAVERQ!J$128 -> -1624 | BT10: =HAVERQ!K126-HAVERQ!K$128 -> -65 | BU10: =(HAVERQ!L126+HAVERQ!M126)-(HAVERQ!L$128+HAVERQ!M$128) -> -177 | BV10: =HAVERQ!N126-HAVERQ!N$128 -> -6 | BW10: =HAVERQ!B126-HAVERQ!B$128 -> 187 | BZ10: =100*((HAVERQ!I130-HAVERQ!I$128)/HAVERQ!$B$128) -> -1.7066168 | CA10: =100*((HAVERQ!J130-HAVERQ!J$128)/HAVERQ!$B$128) -> -4.6165758 | CB10: =100*((HAVERQ!K130-HAVERQ!K$128)/HAVERQ!$B$128) -> -1.8405007 | CC10: =100*(((HAVERQ!L130+HAVERQ!M130)-(HAVERQ!L$128+HAVERQ!M$128))/HAVERQ!$B$128) -> -5.3521309 | CD10: =CE10-BZ10-CA10-CB10-CC10 -> -7.5233087 | CE10: =100*((HAVERQ!B130-HAVERQ!B$128)/HAVERQ!B$128) -> -21.039133 | CH10: =HAVERQ!I126 -> 9706 | CI10: =HAVERQ!J126 -> 7990 | CJ10: =HAVERQ!K126 -> 3169 | CK10: =HAVERQ!L126+HAVERQ!M126 -> 39439 | CL10: =HAVERQ!N126 -> 1352 | CO10: =CX10 -> -258 | CP10: =CY10 -> -104 | CQ10: =CZ10 -> 52 | CR10: =DA10 -> 2139 | CS10: =DC10 -> 95 | CT10: =+DB10+DD10+DE10+DF10 -> -31 | CU10: =DG10 -> -177 | CX10: =HAVERQ!L126-HAVERQ!L$128 -> -258 | CY10: =HAVERQ!O126-HAVERQ!O$128 -> -104 | CZ10: =HAVERQ!P126-HAVERQ!P$128 -> 52 | DA10: =HAVERQ!Q126-HAVERQ!Q$128 -> 2139 | DB10: =HAVERQ!R126-HAVERQ!R$128 -> 246 | DC10: =HAVERQ!S126-HAVERQ!S$128 -> 95 | DD10: =HAVERQ!T126-HAVERQ!T$128 -> 127 | DE10: =HAVERQ!U126-HAVERQ!U$128 -> 14 | DF10: =HAVERQ!V126-HAVERQ!V$128 -> -418 | DG10: =(HAVERQ!L126+HAVERQ!M126)-(HAVERQ!L$128+HAVERQ!M$128) -> -177 | DJ10: =100*(HAVERQ!C126/HAVERQ!C$128) -> 100.32912 | DK10: =100*(HAVERQ!D126/HAVERQ!D$128) -> 129.66252 | DL10: =100*(HAVERQ!E126/HAVERQ!E$128) -> 99.108487 | DM10: =100*(HAVERQ!F126/HAVERQ!F$128) -> 102.0632 | DN10: =100*(HAVERQ!G126/HAVERQ!G$128) -> 100.31022 | DO10: =100*(HAVERQ!H126/HAVERQ!H$128) -> 94.191547 | DP10: 100 | DS10: =HAVERQ!D126-HAVERQ!D$128 -> 1336 | DT10: =HAVERQ!E126-HAVERQ!E$128 -> -148 | DU10: =HAVERQ!F126-HAVERQ!F$128 -> 523 | DV10: =HAVERQ!G126-HAVERQ!G$128 -> 115 | DW10: =HAVERQ!H126-HAVERQ!H$128 -> -1535 | DX10: =HAVERQ!C126-HAVERQ!C$128 -> 361 | EA10: =MIN(EM10:EO10) -> 0.52228064 | EB10: =+EF10-EA10 -> 0.65269528 | EC10: =100*((EJ14/EJ10)-1) -> -3.0572227 | ED10: 0 | EF10: =MAX(EM10:EO10) -> 1.1749759 | EG10: =AVERAGE(EM10:EO10) -> 0.82625722 | EJ10: ='IPNR ex BNFL'!I18 -> 46153 | EM10: =(ER10-ER$2)/ER$3 -> 1.1749759 | EN10: =(ES10-ES$2)/ES$3 -> 0.52228064 | EO10: =(ET10-ET$2)/ET$3 -> 0.78151509 | ER10: =(HAVERQ!W52*$EW$2)+(HAVERQ!X52*$EX$2)/($EW$2+$EX$2) -> 21.975472 | ES10: =(HAVERQ!AB52*$EW$2)+(HAVERQ!AC52*$EY$2)+(HAVERQ!AD52*$EZ$2)+(HAVERQ!AE52*$FA$2)/($EW$2+$EY$2+$EZ$2+$FA$2) -> 1.1136195 | ET10: =(HAVERQ!Y52*$EW$2)+(HAVERQ!Z52*$EX$2)/($EW$2+$EX$2) -> 2.0500097 | FC10: 43617 | FD10: =100*((HAVERM!E241+HAVERM!F241)/(HAVERM!E$249+HAVERM!F$249)) -> 99.441515 | FE10: =100*(HAVERM!E241/HAVERM!E$249) -> 100.05531 | FF10: =100*(HAVERM!F241/HAVERM!F$249) -> 99.104723 | FG10: 100 | FV10: 42491 | FW10: =HAVERM!G204 -> 346739 | FY10: =FW10-FW9 -> 1512 | GD10: =100*(DataQ!W160/DataQ!W$194) -> 73.802761 | GE10: =100*(DataQ!X160/DataQ!X$194) -> 72.464961 | GF10: =100*(DataQ!C160/DataQ!C$194) -> 72.1715 | GH10: 100 | GK10: =100*(DataQ!Z140/AVERAGE(DataQ!$Z$203:$Z$206)) -> 71.957848 | GL10: =100*(DataQ!C140/AVERAGE(DataQ!$C$203:$C$206)) -> 74.512261 | GM10: 100 | GP10: =100*(DataQ!Z140/DataQ!$Z$194) -> 71.689386 | GQ10: =100*(DataQ!C140/DataQ!$C$194) -> 71.926315 | GR10: 100 | GU10: =HB10 -> 100.30164 | GV10: =MIN(HC10:HH10) -> 98.655933 | GW10: =+GY10-GV10 -> 6.8336367 | GX10: 100 | GY10: =MAX(HC10:HH10) -> 105.48957 | HB10: =100*(DataQ!C192/DataQ!C$194) -> 100.30164 | HC10: =100*(DataQ!Q192/DataQ!Q$194) -> 99.484901 | HD10: =100*(DataQ!R192/DataQ!R$194) -> 105.48957 | HE10: =100*(DataQ!S192/DataQ!S$194) -> 100.7951 | HF10: =100*(DataQ!T192/DataQ!T$194) -> 98.655933 | HG10: =100*(DataQ!U192/DataQ!U$194) -> 101.05983 | HH10: =100*(DataQ!V192/DataQ!V$194) -> 99.711361 | HK10: =HR10 -> 100.30164 | HL10: =MIN(HS10:HX10) -> 98.655933 | HM10: =+HO10-HL10 -> 6.8336367 | HN10: 100 | HO10: =MAX(HS10:HX10) -> 105.48957 | HR10: =100*(DataQ!C192/DataQ!C$194) -> 100.30164 | HS10: =100*(DataQ!Q192/DataQ!Q$194) -> 99.484901 | HT10: =100*(DataQ!R192/DataQ!R$194) -> 105.48957 | HU10: =100*(DataQ!S192/DataQ!S$194) -> 100.7951 | HV10: =100*(DataQ!T192/DataQ!T$194) -> 98.655933 | HW10: =100*(DataQ!U192/DataQ!U$194) -> 101.05983 | HX10: =100*(DataQ!V192/DataQ!V$194) -> 99.711361 | HZ10: 1995 | IA10: =DataA!J29/'Chart Data'!IF10 -> 2.0650402 | IB10: =IB9*(1+$ID$5/100) -> 1.9945151 | IC10: =100*((IA10/IB10)-1) -> 3.5359532 | IF10: =DataA!K29*DataA!L29 -> 858465.12 | IR10: =HAVERQ!AH81 -> -10.6 | IS10: =100*(('IPNR ex BNFL'!I50/'IPNR ex BNFL'!I46)-1) -> -0.28356312 | IT10: 0
B11: =100*((DataQ!C81/DataQ!C77)-1) -> -11.494886 | C11: =K11 -> 21.631379 | D11: 0 | G11: =100*((AVERAGE(DataQ!C78:C81)/AVERAGE(DataQ!C74:C77))-1) -> -6.3280374 | H11: =AVERAGE(K8:K11) -> 20.723684 | I11: 0 | K11: =L11 -> 21.631379 | L11: =100*(HAVERQ!AF15/HAVERQ!AI15) -> 21.631379 | O11: =100*('ONS CVM_SA_(Quarterly)'!B95/'ONS CVM_SA_(Quarterly)'!B$101) -> 115.05536 | P11: =100*('ONS CVM_SA_(Quarterly)'!D95/'ONS CVM_SA_(Quarterly)'!D$101) -> 104.69184 | R11: 100 | U11: ='ONS CVM_SA_(Quarterly)'!C107-'ONS CVM_SA_(Quarterly)'!C$101 -> 2946 | V11: ='ONS CVM_SA_(Quarterly)'!D107-'ONS CVM_SA_(Quarterly)'!D$101 -> 2106 | W11: ='ONS CVM_SA_(Quarterly)'!E107-'ONS CVM_SA_(Quarterly)'!E$101 -> 1416 | X11: ='ONS CVM_SA_(Quarterly)'!F107-'ONS CVM_SA_(Quarterly)'!F$101 -> 349 | Y11: ='ONS CVM_SA_(Quarterly)'!B107-'ONS CVM_SA_(Quarterly)'!B$101 -> 7059 | AB11: =100*(U11/'ONS CVM_SA_(Quarterly)'!$B$101) -> 5.472988 | AC11: =100*(V11/'ONS CVM_SA_(Quarterly)'!$B$101) -> 3.9124619 | AD11: =100*(W11/'ONS CVM_SA_(Quarterly)'!$B$101) -> 2.6306012 | AE11: =100*(X11/'ONS CVM_SA_(Quarterly)'!$B$101) -> 0.64836145 | AF11: =100*(('ONS CVM_SA_(Quarterly)'!B107/'ONS CVM_SA_(Quarterly)'!B$101)-1) -> 13.113993 | AI11: =100*(('ONS CVM_SA_(Quarterly)'!C99-'ONS CVM_SA_(Quarterly)'!C$96)/'ONS CVM_SA_(Quarterly)'!$B$96) -> 1.279156 | AJ11: =100*(('ONS CVM_SA_(Quarterly)'!D99-'ONS CVM_SA_(Quarterly)'!D$96)/'ONS CVM_SA_(Quarterly)'!$B$96) -> -3.5438913 | AK11: =100*(('ONS CVM_SA_(Quarterly)'!E99-'ONS CVM_SA_(Quarterly)'!E$96)/'ONS CVM_SA_(Quarterly)'!$B$96) -> -6.5280511 | AL11: =100*(('ONS CVM_SA_(Quarterly)'!F99-'ONS CVM_SA_(Quarterly)'!F$96)/'ONS CVM_SA_(Quarterly)'!$B$96) -> -2.4163629 | AM11: =100*(('ONS CVM_SA_(Quarterly)'!B99-'ONS CVM_SA_(Quarterly)'!B$96)/'ONS CVM_SA_(Quarterly)'!$B$96) -> -11.749524 | AP11: =100*(('ONS CVM_SA_(Quarterly)'!C87-AVERAGE('ONS CVM_SA_(Quarterly)'!C$81:C$84))/AVERAGE('ONS CVM_SA_(Quarterly)'!$B$81:$B$84)) -> -0.50161465 | AQ11: =100*(('ONS CVM_SA_(Quarterly)'!D87-AVERAGE('ONS CVM_SA_(Quarterly)'!D$81:D$84))/AVERAGE('ONS CVM_SA_(Quarterly)'!$B$81:$B$84)) -> 0.29618765 | AR11: =100*(('ONS CVM_SA_(Quarterly)'!E87-AVERAGE('ONS CVM_SA_(Quarterly)'!E$81:E$84))/AVERAGE('ONS CVM_SA_(Quarterly)'!$B$81:$B$84)) -> -2.0781757 | AS11: =100*(('ONS CVM_SA_(Quarterly)'!F87-AVERAGE('ONS CVM_SA_(Quarterly)'!F$81:F$84))/AVERAGE('ONS CVM_SA_(Quarterly)'!$B$81:$B$84)) -> 1.5178098 | AT11: =100*(('ONS CVM_SA_(Quarterly)'!B87-AVERAGE('ONS CVM_SA_(Quarterly)'!B$81:B$84))/AVERAGE('ONS CVM_SA_(Quarterly)'!$B$81:$B$84)) -> -1.6527352 | AV11: 43647 | AW11: =HAVERM!D242 -> 0.75 | AX11: =HAVERM!B242 -> 3.3 | AY11: =HAVERM!C242 -> 2.42 | BA11: 44713 | BB11: =AX46-AX$39 -> 0.78 | BC11: =AY46-AY$39 -> 0.1 | BD11: 1000 | BF11: 0 | BJ11: =100*(HAVERQ!B127/HAVERQ!B$128) -> 99.89999 | BK11: =100*(HAVERQ!I127/HAVERQ!I$128) -> 101.56384 | BL11: =100*(HAVERQ!J127/HAVERQ!J$128) -> 82.348658 | BM11: =100*(HAVERQ!K127/HAVERQ!K$128) -> 93.939394 | BN11: =100*((HAVERQ!L127+HAVERQ!M127)/(HAVERQ!L$128+HAVERQ!M$128)) -> 101.05765 | BO11: 100 | BR11: =HAVERQ!I127-HAVERQ!I$128 -> 146 | BS11: =HAVERQ!J127-HAVERQ!J$128 -> -1697 | BT11: =HAVERQ!K127-HAVERQ!K$128 -> -196 | BU11: =(HAVERQ!L127+HAVERQ!M127)-(HAVERQ!L$128+HAVERQ!M$128) -> 419 | BV11: =HAVERQ!N127-HAVERQ!N$128 -> -20 | BW11: =HAVERQ!B127-HAVERQ!B$128 -> -62 | BZ11: =100*((HAVERQ!I131-HAVERQ!I$128)/HAVERQ!$B$128) -> -0.92750911 | CA11: =100*((HAVERQ!J131-HAVERQ!J$128)/HAVERQ!$B$128) -> -4.377843 | CB11: =100*((HAVERQ!K131-HAVERQ!K$128)/HAVERQ!$B$128) -> -1.1291415 | CC11: =100*(((HAVERQ!L131+HAVERQ!M131)-(HAVERQ!L$128+HAVERQ!M$128))/HAVERQ!$B$128) -> -8.2169242 | CD11: =CE11-BZ11-CA11-CB11-CC11 -> 2.9018937 | CE11: =100*((HAVERQ!B131-HAVERQ!B$128)/HAVERQ!B$128) -> -11.749524 | CH11: =HAVERQ!I127 -> 9482 | CI11: =HAVERQ!J127 -> 7917 | CJ11: =HAVERQ!K127 -> 3038 | CK11: =HAVERQ!L127+HAVERQ!M127 -> 40035 | CL11: =HAVERQ!N127 -> 1338 | CO11: =CX11 -> 182 | CP11: =CY11 -> -127 | CQ11: =CZ11 -> -18 | CR11: =DA11 -> 230 | CS11: =DC11 -> 427 | CT11: =+DB11+DD11+DE11+DF11 -> -103 | CU11: =DG11 -> 419 | CX11: =HAVERQ!L127-HAVERQ!L$128 -> 182 | CY11: =HAVERQ!O127-HAVERQ!O$128 -> -127 | CZ11: =HAVERQ!P127-HAVERQ!P$128 -> -18 | DA11: =HAVERQ!Q127-HAVERQ!Q$128 -> 230 | DB11: =HAVERQ!R127-HAVERQ!R$128 -> 309 | DC11: =HAVERQ!S127-HAVERQ!S$128 -> 427 | DD11: =HAVERQ!T127-HAVERQ!T$128 -> 91 | DE11: =HAVERQ!U127-HAVERQ!U$128 -> -52 | DF11: =HAVERQ!V127-HAVERQ!V$128 -> -451 | DG11: =(HAVERQ!L127+HAVERQ!M127)-(HAVERQ!L$128+HAVERQ!M$128) -> 419 | DJ11: =100*(HAVERQ!C127/HAVERQ!C$128) -> 101.14601 | DK11: =100*(HAVERQ!D127/HAVERQ!D$128) -> 116.62966 | DL11: =100*(HAVERQ!E127/HAVERQ!E$128) -> 98.909704 | DM11: =100*(HAVERQ!F127/HAVERQ!F$128) -> 104.8207 | DN11: =100*(HAVERQ!G127/HAVERQ!G$128) -> 99.107119 | DO11: =100*(HAVERQ!H127/HAVERQ!H$128) -> 98.618837 | DP11: 100 | DS11: =HAVERQ!D127-HAVERQ!D$128 -> 749 | DT11: =HAVERQ!E127-HAVERQ!E$128 -> -181 | DU11: =HAVERQ!F127-HAVERQ!F$128 -> 1222 | DV11: =HAVERQ!G127-HAVERQ!G$128 -> -331 | DW11: =HAVERQ!H127-HAVERQ!H$128 -> -365 | DX11: =HAVERQ!C127-HAVERQ!C$128 -> 1257 | EA11: =MIN(EM11:EO11) -> -0.69878276 | EB11: =+EF11-EA11 -> 1.6045186 | EC11: =100*((EJ15/EJ11)-1) -> 3.9037644 | ED11: 0 | EF11: =MAX(EM11:EO11) -> 0.90573584 | EG11: =AVERAGE(EM11:EO11) -> 0.30136415 | EJ11: ='IPNR ex BNFL'!I19 -> 43061 | EL11: 2001 | EM11: =(ER11-ER$2)/ER$3 -> 0.90573584 | EN11: =(ES11-ES$2)/ES$3 -> -0.69878276 | EO11: =(ET11-ET$2)/ET$3 -> 0.69713935 | EQ11: 2001 | ER11: =(HAVERQ!W53*$EW$2)+(HAVERQ!X53*$EX$2)/($EW$2+$EX$2) -> 18.819739 | ES11: =(HAVERQ!AB53*$EW$2)+(HAVERQ!AC53*$EY$2)+(HAVERQ!AD53*$EZ$2)+(HAVERQ!AE53*$FA$2)/($EW$2+$EY$2+$EZ$2+$FA$2) -> -16.068946 | ET11: =(HAVERQ!Y53*$EW$2)+(HAVERQ!Z53*$EX$2)/($EW$2+$EX$2) -> 1.917494 | FC11: 43647 | FD11: =100*((HAVERM!E242+HAVERM!F242)/(HAVERM!E$249+HAVERM!F$249)) -> 98.930881 | FE11: =100*(HAVERM!E242/HAVERM!E$249) -> 99.586469 | FF11: =100*(HAVERM!F242/HAVERM!F$249) -> 98.571156 | FG11: 100 | FV11: 42522 | FW11: =HAVERM!G205 -> 350230 | FY11: =FW11-FW10 -> 3491 | GD11: =100*(DataQ!W161/DataQ!W$194) -> 76.125226 | GE11: =100*(DataQ!X161/DataQ!X$194) -> 74.706334 | GF11: =100*(DataQ!C161/DataQ!C$194) -> 74.552376 | GH11: 100 | GK11: =100*(DataQ!Z141/AVERAGE(DataQ!$Z$203:$Z$206)) -> 77.469483 | GL11: =100*(DataQ!C141/AVERAGE(DataQ!$C$203:$C$206)) -> 80.248987 | GM11: 100 | GP11: =100*(DataQ!Z141/DataQ!$Z$194) -> 77.180458 | GQ11: =100*(DataQ!C141/DataQ!$C$194) -> 77.463948 | GR11: 100 | GU11: =HB11 -> 99.89999 | GV11: =MIN(HC11:HH11) -> 99.556107 | GW11: =+GY11-GV11 -> 8.1859149 | GX11: 100 | GY11: =MAX(HC11:HH11) -> 107.74202 | HB11: =100*(DataQ!C193/DataQ!C$194) -> 99.89999 | HC11: =100*(DataQ!Q193/DataQ!Q$194) -> 100.4444 | HD11: =100*(DataQ!R193/DataQ!R$194) -> 107.74202 | HE11: =100*(DataQ!S193/DataQ!S$194) -> 100.36556 | HF11: =100*(DataQ!T193/DataQ!T$194) -> 99.556107 | HG11: =100*(DataQ!U193/DataQ!U$194) -> 101.00098 | HH11: =100*(DataQ!V193/DataQ!V$194) -> 101.73342 | HK11: =HR11 -> 99.89999 | HL11: =MIN(HS11:HX11) -> 99.556107 | HM11: =+HO11-HL11 -> 8.1859149 | HN11: 100 | HO11: =MAX(HS11:HX11) -> 107.74202 | HR11: =100*(DataQ!C193/DataQ!C$194) -> 99.89999 | HS11: =100*(DataQ!Q193/DataQ!Q$194) -> 100.4444 | HT11: =100*(DataQ!R193/DataQ!R$194) -> 107.74202 | HU11: =100*(DataQ!S193/DataQ!S$194) -> 100.36556 | HV11: =100*(DataQ!T193/DataQ!T$194) -> 99.556107 | HW11: =100*(DataQ!U193/DataQ!U$194) -> 101.00098 | HX11: =100*(DataQ!V193/DataQ!V$194) -> 101.73342 | HZ11: 1996 | IA11: =DataA!J30/'Chart Data'!IF11 -> 2.0977145 | IB11: =IB10*(1+$ID$5/100) -> 2.0475008 | IC11: =100*((IA11/IB11)-1) -> 2.4524366 | IF11: =DataA!K30*DataA!L30 -> 865835.19 | IR11: =HAVERQ!AH82 -> -15.1 | IS11: =100*(('IPNR ex BNFL'!I51/'IPNR ex BNFL'!I47)-1) -> 0.34161808 | IT11: 0
B12: =100*((DataQ!C82/DataQ!C78)-1) -> -8.0417943 | C12: =K12 -> 20.342783 | D12: 0 | G12: =100*((AVERAGE(DataQ!C79:C82)/AVERAGE(DataQ!C75:C78))-1) -> -8.0092753 | H12: =AVERAGE(K9:K12) -> 21.192337 | I12: 0 | K12: =L12 -> 20.342783 | L12: =100*(HAVERQ!AF16/HAVERQ!AI16) -> 20.342783 | O12: =100*('ONS CVM_SA_(Quarterly)'!B96/'ONS CVM_SA_(Quarterly)'!B$101) -> 115.17054 | P12: =100*('ONS CVM_SA_(Quarterly)'!D96/'ONS CVM_SA_(Quarterly)'!D$101) -> 104.50384 | R12: 100 | U12: ='ONS CVM_SA_(Quarterly)'!C108-'ONS CVM_SA_(Quarterly)'!C$101 -> 3545 | V12: ='ONS CVM_SA_(Quarterly)'!D108-'ONS CVM_SA_(Quarterly)'!D$101 -> 1005 | W12: ='ONS CVM_SA_(Quarterly)'!E108-'ONS CVM_SA_(Quarterly)'!E$101 -> 484 | X12: ='ONS CVM_SA_(Quarterly)'!F108-'ONS CVM_SA_(Quarterly)'!F$101 -> 144 | Y12: ='ONS CVM_SA_(Quarterly)'!B108-'ONS CVM_SA_(Quarterly)'!B$101 -> 5420 | AB12: =100*(U12/'ONS CVM_SA_(Quarterly)'!$B$101) -> 6.5857918 | AC12: =100*(V12/'ONS CVM_SA_(Quarterly)'!$B$101) -> 1.867058 | AD12: =100*(W12/'ONS CVM_SA_(Quarterly)'!$B$101) -> 0.89916029 | AE12: =100*(X12/'ONS CVM_SA_(Quarterly)'!$B$101) -> 0.26751876 | AF12: =100*(('ONS CVM_SA_(Quarterly)'!B108/'ONS CVM_SA_(Quarterly)'!B$101)-1) -> 10.069109 | AI12: =100*(('ONS CVM_SA_(Quarterly)'!C100-'ONS CVM_SA_(Quarterly)'!C$96)/'ONS CVM_SA_(Quarterly)'!$B$96) -> 2.9809336 | AJ12: =100*(('ONS CVM_SA_(Quarterly)'!D100-'ONS CVM_SA_(Quarterly)'!D$96)/'ONS CVM_SA_(Quarterly)'!$B$96) -> -1.3791657 | AK12: =100*(('ONS CVM_SA_(Quarterly)'!E100-'ONS CVM_SA_(Quarterly)'!E$96)/'ONS CVM_SA_(Quarterly)'!$B$96) -> -5.8602445 | AL12: =100*(('ONS CVM_SA_(Quarterly)'!F100-'ONS CVM_SA_(Quarterly)'!F$96)/'ONS CVM_SA_(Quarterly)'!$B$96) -> -2.1324644 | AM12: =100*(('ONS CVM_SA_(Quarterly)'!B100-'ONS CVM_SA_(Quarterly)'!B$96)/'ONS CVM_SA_(Quarterly)'!$B$96) -> -6.8054973 | AP12: =100*(('ONS CVM_SA_(Quarterly)'!C88-AVERAGE('ONS CVM_SA_(Quarterly)'!C$81:C$84))/AVERAGE('ONS CVM_SA_(Quarterly)'!$B$81:$B$84)) -> 0.45137215 | AQ12: =100*(('ONS CVM_SA_(Quarterly)'!D88-AVERAGE('ONS CVM_SA_(Quarterly)'!D$81:D$84))/AVERAGE('ONS CVM_SA_(Quarterly)'!$B$81:$B$84)) -> 0.34480942 | AR12: =100*(('ONS CVM_SA_(Quarterly)'!E88-AVERAGE('ONS CVM_SA_(Quarterly)'!E$81:E$84))/AVERAGE('ONS CVM_SA_(Quarterly)'!$B$81:$B$84)) -> -2.0781757 | AS12: =100*(('ONS CVM_SA_(Quarterly)'!F88-AVERAGE('ONS CVM_SA_(Quarterly)'!F$81:F$84))/AVERAGE('ONS CVM_SA_(Quarterly)'!$B$81:$B$84)) -> 2.1839281 | AT12: =100*(('ONS CVM_SA_(Quarterly)'!B88-AVERAGE('ONS CVM_SA_(Quarterly)'!B$81:B$84))/AVERAGE('ONS CVM_SA_(Quarterly)'!$B$81:$B$84)) -> 0.019853892 | AV12: 43678 | AW12: =HAVERM!D243 -> 0.75 | AX12: =HAVERM!B243 -> 3.27 | AY12: =HAVERM!C243 -> 2.42 | BA12: 44743 | BB12: =AX47-AX$39 -> 0.86 | BC12: =AY47-AY$39 -> 0.11 | BD12: 1000 | BF12: 0 | BJ12: =100*(HAVERQ!B128/HAVERQ!B$128) -> 100 | BK12: =100*(HAVERQ!I128/HAVERQ!I$128) -> 100 | BL12: =100*(HAVERQ!J128/HAVERQ!J$128) -> 100 | BM12: =100*(HAVERQ!K128/HAVERQ!K$128) -> 100 | BN12: =100*((HAVERQ!L128+HAVERQ!M128)/(HAVERQ!L$128+HAVERQ!M$128)) -> 100 | BO12: 100 | BR12: =HAVERQ!I128-HAVERQ!I$128 -> 0 | BS12: =HAVERQ!J128-HAVERQ!J$128 -> 0 | BT12: =HAVERQ!K128-HAVERQ!K$128 -> 0 | BU12: =(HAVERQ!L128+HAVERQ!M128)-(HAVERQ!L$128+HAVERQ!M$128) -> 0 | BV12: =HAVERQ!N128-HAVERQ!N$128 -> 0 | BW12: =HAVERQ!B128-HAVERQ!B$128 -> 0 | BZ12: =100*((HAVERQ!I132-HAVERQ!I$128)/HAVERQ!$B$128) -> -0.52263122 | CA12: =100*((HAVERQ!J132-HAVERQ!J$128)/HAVERQ!$B$128) -> -4.785947 | CB12: =100*((HAVERQ!K132-HAVERQ!K$128)/HAVERQ!$B$128) -> -1.3485176 | CC12: =100*(((HAVERQ!L132+HAVERQ!M132)-(HAVERQ!L$128+HAVERQ!M$128))/HAVERQ!$B$128) -> -6.5199858 | CD12: =CE12-BZ12-CA12-CB12-CC12 -> 6.3715843 | CE12: =100*((HAVERQ!B132-HAVERQ!B$128)/HAVERQ!B$128) -> -6.8054973 | CH12: =HAVERQ!I128 -> 9336 | CI12: =HAVERQ!J128 -> 9614 | CJ12: =HAVERQ!K128 -> 3234 | CK12: =HAVERQ!L128+HAVERQ!M128 -> 39616 | CL12: =HAVERQ!N128 -> 1358 | CO12: =CX12 -> 0 | CP12: =CY12 -> 0 | CQ12: =CZ12 -> 0 | CR12: =DA12 -> 0 | CS12: =DC12 -> 0 | CT12: =+DB12+DD12+DE12+DF12 -> 0 | CU12: =DG12 -> 0 | CX12: =HAVERQ!L128-HAVERQ!L$128 -> 0 | CY12: =HAVERQ!O128-HAVERQ!O$128 -> 0 | CZ12: =HAVERQ!P128-HAVERQ!P$128 -> 0 | DA12: =HAVERQ!Q128-HAVERQ!Q$128 -> 0 | DB12: =HAVERQ!R128-HAVERQ!R$128 -> 0 | DC12: =HAVERQ!S128-HAVERQ!S$128 -> 0 | DD12: =HAVERQ!T128-HAVERQ!T$128 -> 0 | DE12: =HAVERQ!U128-HAVERQ!U$128 -> 0 | DF12: =HAVERQ!V128-HAVERQ!V$128 -> 0 | DG12: =(HAVERQ!L128+HAVERQ!M128)-(HAVERQ!L$128+HAVERQ!M$128) -> 0 | DJ12: =100*(HAVERQ!C128/HAVERQ!C$128) -> 100 | DK12: =100*(HAVERQ!D128/HAVERQ!D$128) -> 100 | DL12: =100*(HAVERQ!E128/HAVERQ!E$128) -> 100 | DM12: =100*(HAVERQ!F128/HAVERQ!F$128) -> 100 | DN12: =100*(HAVERQ!G128/HAVERQ!G$128) -> 100 | DO12: =100*(HAVERQ!H128/HAVERQ!H$128) -> 100 | DP12: 100 | DS12: =HAVERQ!D128-HAVERQ!D$128 -> 0 | DT12: =HAVERQ!E128-HAVERQ!E$128 -> 0 | DU12: =HAVERQ!F128-HAVERQ!F$128 -> 0 | DV12: =HAVERQ!G128-HAVERQ!G$128 -> 0 | DW12: =HAVERQ!H128-HAVERQ!H$128 -> 0 | DX12: =HAVERQ!C128-HAVERQ!C$128 -> 0 | EA12: =MIN(EM12:EO12) -> 0.24340866 | EB12: =+EF12-EA12 -> 0.33434292 | EC12: =100*((EJ16/EJ12)-1) -> -3.9183161 | ED12: 0 | EF12: =MAX(EM12:EO12) -> 0.57775157 | EG12: =AVERAGE(EM12:EO12) -> 0.38426418 | EJ12: ='IPNR ex BNFL'!I20 -> 44611 | EM12: =(ER12-ER$2)/ER$3 -> 0.57775157 | EN12: =(ES12-ES$2)/ES$3 -> 0.24340866 | EO12: =(ET12-ET$2)/ET$3 -> 0.33163232 | ER12: =(HAVERQ!W54*$EW$2)+(HAVERQ!X54*$EX$2)/($EW$2+$EX$2) -> 14.975472 | ES12: =(HAVERQ!AB54*$EW$2)+(HAVERQ!AC54*$EY$2)+(HAVERQ!AD54*$EZ$2)+(HAVERQ!AE54*$FA$2)/($EW$2+$EY$2+$EZ$2+$FA$2) -> -2.8106127 | ET12: =(HAVERQ!Y54*$EW$2)+(HAVERQ!Z54*$EX$2)/($EW$2+$EX$2) -> 1.3434495 | FC12: 43678 | FD12: =100*((HAVERM!E243+HAVERM!F243)/(HAVERM!E$249+HAVERM!F$249)) -> 99.537672 | FE12: =100*(HAVERM!E243/HAVERM!E$249) -> 99.743392 | FF12: =100*(HAVERM!F243/HAVERM!F$249) -> 99.424793 | FG12: 100 | FV12: 42552 | FW12: =HAVERM!G206 -> 352760 | FY12: =FW12-FW11 -> 2530 | GD12: =100*(DataQ!W162/DataQ!W$194) -> 79.008146 | GE12: =100*(DataQ!X162/DataQ!X$194) -> 77.483807 | GF12: =100*(DataQ!C162/DataQ!C$194) -> 76.41546 | GH12: 100 | GK12: =100*(DataQ!Z142/AVERAGE(DataQ!$Z$203:$Z$206)) -> 77.595624 | GL12: =100*(DataQ!C142/AVERAGE(DataQ!$C$203:$C$206)) -> 80.409408 | GM12: 100 | GP12: =100*(DataQ!Z142/DataQ!$Z$194) -> 77.306128 | GQ12: =100*(DataQ!C142/DataQ!$C$194) -> 77.618802 | GR12: 100 | GU12: =HB12 -> 100 | GV12: =MIN(HC12:HH12) -> 100 | GW12: =+GY12-GV12 -> 0 | GX12: 100 | GY12: =MAX(HC12:HH12) -> 100 | HB12: =100*(DataQ!C194/DataQ!C$194) -> 100 | HC12: =100*(DataQ!Q194/DataQ!Q$194) -> 100 | HD12: =100*(DataQ!R194/DataQ!R$194) -> 100 | HE12: =100*(DataQ!S194/DataQ!S$194) -> 100 | HF12: =100*(DataQ!T194/DataQ!T$194) -> 100 | HG12: =100*(DataQ!U194/DataQ!U$194) -> 100 | HH12: =100*(DataQ!V194/DataQ!V$194) -> 100 | HK12: =HR12 -> 100 | HL12: =MIN(HS12:HX12) -> 100 | HM12: =+HO12-HL12 -> 0 | HN12: 100 | HO12: =MAX(HS12:HX12) -> 100 | HR12: =100*(DataQ!C194/DataQ!C$194) -> 100 | HS12: =100*(DataQ!Q194/DataQ!Q$194) -> 100 | HT12: =100*(DataQ!R194/DataQ!R$194) -> 100 | HU12: =100*(DataQ!S194/DataQ!S$194) -> 100 | HV12: =100*(DataQ!T194/DataQ!T$194) -> 100 | HW12: =100*(DataQ!U194/DataQ!U$194) -> 100 | HX12: =100*(DataQ!V194/DataQ!V$194) -> 100 | HZ12: 1997 | IA12: =DataA!J31/'Chart Data'!IF12 -> 2.1276915 | IB12: =IB11*(1+$ID$5/100) -> 2.1018941 | IC12: =100*((IA12/IB12)-1) -> 1.2273415 | IF12: =DataA!K31*DataA!L31 -> 879991.76 | IR12: =HAVERQ!AH83 -> -51.7 | IS12: =100*(('IPNR ex BNFL'!I52/'IPNR ex BNFL'!I48)-1) -> -10.581042 | IT12: 0
A13: 1992 | B13: =100*((DataQ!C83/DataQ!C79)-1) -> -5.7367988 | C13: =K13 -> 27.600521 | D13: 0 | F13: 1992 | G13: =100*((AVERAGE(DataQ!C80:C83)/AVERAGE(DataQ!C76:C79))-1) -> -8.6059455 | H13: =AVERAGE(K10:K13) -> 22.807585 | I13: 0 | K13: =L13 -> 27.600521 | L13: =100*(HAVERQ!AF17/HAVERQ!AI17) -> 27.600521 | N13: 2020 | O13: =100*('ONS CVM_SA_(Quarterly)'!B97/'ONS CVM_SA_(Quarterly)'!B$101) -> 112.57896 | P13: =100*('ONS CVM_SA_(Quarterly)'!D97/'ONS CVM_SA_(Quarterly)'!D$101) -> 104.43028 | R13: 100 | T13: 2023 | U13: ='ONS CVM_SA_(Quarterly)'!C109-'ONS CVM_SA_(Quarterly)'!C$101 -> 4252 | V13: ='ONS CVM_SA_(Quarterly)'!D109-'ONS CVM_SA_(Quarterly)'!D$101 -> 1931 | W13: ='ONS CVM_SA_(Quarterly)'!E109-'ONS CVM_SA_(Quarterly)'!E$101 -> 1689 | X13: ='ONS CVM_SA_(Quarterly)'!F109-'ONS CVM_SA_(Quarterly)'!F$101 -> 540 | Y13: ='ONS CVM_SA_(Quarterly)'!B109-'ONS CVM_SA_(Quarterly)'!B$101 -> 8654 | AA13: 2023 | AB13: =100*(U13/'ONS CVM_SA_(Quarterly)'!$B$101) -> 7.8992346 | AC13: =100*(V13/'ONS CVM_SA_(Quarterly)'!$B$101) -> 3.5873523 | AD13: =100*(W13/'ONS CVM_SA_(Quarterly)'!$B$101) -> 3.1377722 | AE13: =100*(X13/'ONS CVM_SA_(Quarterly)'!$B$101) -> 1.0031954 | AF13: =100*(('ONS CVM_SA_(Quarterly)'!B109/'ONS CVM_SA_(Quarterly)'!B$101)-1) -> 16.077135 | AH13: 2021 | AI13: =100*(('ONS CVM_SA_(Quarterly)'!C101-'ONS CVM_SA_(Quarterly)'!C$96)/'ONS CVM_SA_(Quarterly)'!$B$96) -> -1.658225 | AJ13: =100*(('ONS CVM_SA_(Quarterly)'!D101-'ONS CVM_SA_(Quarterly)'!D$96)/'ONS CVM_SA_(Quarterly)'!$B$96) -> -0.88879569 | AK13: =100*(('ONS CVM_SA_(Quarterly)'!E101-'ONS CVM_SA_(Quarterly)'!E$96)/'ONS CVM_SA_(Quarterly)'!$B$96) -> -7.7959157 | AL13: =100*(('ONS CVM_SA_(Quarterly)'!F101-'ONS CVM_SA_(Quarterly)'!F$96)/'ONS CVM_SA_(Quarterly)'!$B$96) -> -2.0921379 | AM13: =100*(('ONS CVM_SA_(Quarterly)'!B101-'ONS CVM_SA_(Quarterly)'!B$96)/'ONS CVM_SA_(Quarterly)'!$B$96) -> -13.172242 | AO13: 2018 | AP13: =100*(('ONS CVM_SA_(Quarterly)'!C89-AVERAGE('ONS CVM_SA_(Quarterly)'!C$81:C$84))/AVERAGE('ONS CVM_SA_(Quarterly)'!$B$81:$B$84)) -> -2.6717666 | AQ13: =100*(('ONS CVM_SA_(Quarterly)'!D89-AVERAGE('ONS CVM_SA_(Quarterly)'!D$81:D$84))/AVERAGE('ONS CVM_SA_(Quarterly)'!$B$81:$B$84)) -> 0.92827073 | AR13: =100*(('ONS CVM_SA_(Quarterly)'!E89-AVERAGE('ONS CVM_SA_(Quarterly)'!E$81:E$84))/AVERAGE('ONS CVM_SA_(Quarterly)'!$B$81:$B$84)) -> -1.1235682 | AS13: =100*(('ONS CVM_SA_(Quarterly)'!F89-AVERAGE('ONS CVM_SA_(Quarterly)'!F$81:F$84))/AVERAGE('ONS CVM_SA_(Quarterly)'!$B$81:$B$84)) -> 2.0737187 | AT13: =100*(('ONS CVM_SA_(Quarterly)'!B89-AVERAGE('ONS CVM_SA_(Quarterly)'!B$81:B$84))/AVERAGE('ONS CVM_SA_(Quarterly)'!$B$81:$B$84)) -> -0.5814354 | AV13: 43709 | AW13: =HAVERM!D244 -> 0.75 | AX13: =HAVERM!B244 -> 3.27 | AY13: =HAVERM!C244 -> 2.4 | BA13: 44774 | BB13: =AX48-AX$39 -> 1.17 | BC13: =AY48-AY$39 -> 0.16 | BD13: 1000 | BF13: 0 | BI13: 2020 | BJ13: =100*(HAVERQ!B129/HAVERQ!B$128) -> 97.749782 | BK13: =100*(HAVERQ!I129/HAVERQ!I$128) -> 99.732219 | BL13: =100*(HAVERQ!J129/HAVERQ!J$128) -> 81.797379 | BM13: =100*(HAVERQ!K129/HAVERQ!K$128) -> 93.475572 | BN13: =100*((HAVERQ!L129+HAVERQ!M129)/(HAVERQ!L$128+HAVERQ!M$128)) -> 92.316236 | BO13: 100 | BQ13: 2020 | BR13: =HAVERQ!I129-HAVERQ!I$128 -> -25 | BS13: =HAVERQ!J129-HAVERQ!J$128 -> -1750 | BT13: =HAVERQ!K129-HAVERQ!K$128 -> -211 | BU13: =(HAVERQ!L129+HAVERQ!M129)-(HAVERQ!L$128+HAVERQ!M$128) -> -3044 | BV13: =HAVERQ!N129-HAVERQ!N$128 -> 37 | BW13: =HAVERQ!B129-HAVERQ!B$128 -> -1395 | BY13: 2021 | BZ13: =100*((HAVERQ!I133-HAVERQ!I$128)/HAVERQ!$B$128) -> -0.49359615 | CA13: =100*((HAVERQ!J133-HAVERQ!J$128)/HAVERQ!$B$128) -> -3.0002904 | CB13: =100*((HAVERQ!K133-HAVERQ!K$128)/HAVERQ!$B$128) -> -0.9162177 | CC13: =100*(((HAVERQ!L133+HAVERQ!M133)-(HAVERQ!L$128+HAVERQ!M$128))/HAVERQ!$B$128) -> -7.7781721 | CD13: =CE13-BZ13-CA13-CB13-CC13 -> -0.98396619 | CE13: =100*((HAVERQ!B133-HAVERQ!B$128)/HAVERQ!B$128) -> -13.172242 | CG13: 2020 | CH13: =HAVERQ!I129 -> 9311 | CI13: =HAVERQ!J129 -> 7864 | CJ13: =HAVERQ!K129 -> 3023 | CK13: =HAVERQ!L129+HAVERQ!M129 -> 36572 | CL13: =HAVERQ!N129 -> 1395 | CN13: 2020 | CO13: =CX13 -> -87 | CP13: =CY13 -> 244 | CQ13: =CZ13 -> -284 | CR13: =DA13 -> -343 | CS13: =DC13 -> 370 | CT13: =+DB13+DD13+DE13+DF13 -> -481 | CU13: =DG13 -> -3044 | CW13: 2020 | CX13: =HAVERQ!L129-HAVERQ!L$128 -> -87 | CY13: =HAVERQ!O129-HAVERQ!O$128 -> 244 | CZ13: =HAVERQ!P129-HAVERQ!P$128 -> -284 | DA13: =HAVERQ!Q129-HAVERQ!Q$128 -> -343 | DB13: =HAVERQ!R129-HAVERQ!R$128 -> -86 | DC13: =HAVERQ!S129-HAVERQ!S$128 -> 370 | DD13: =HAVERQ!T129-HAVERQ!T$128 -> -189 | DE13: =HAVERQ!U129-HAVERQ!U$128 -> 17 | DF13: =HAVERQ!V129-HAVERQ!V$128 -> -223 | DG13: =(HAVERQ!L129+HAVERQ!M129)-(HAVERQ!L$128+HAVERQ!M$128) -> -3044 | DI13: 2020 | DJ13: =100*(HAVERQ!C129/HAVERQ!C$128) -> 96.838219 | DK13: =100*(HAVERQ!D129/HAVERQ!D$128) -> 109.16963 | DL13: =100*(HAVERQ!E129/HAVERQ!E$128) -> 95.777363 | DM13: =100*(HAVERQ!F129/HAVERQ!F$128) -> 96.982129 | DN13: =100*(HAVERQ!G129/HAVERQ!G$128) -> 93.60956 | DO13: =100*(HAVERQ!H129/HAVERQ!H$128) -> 99.784311 | DP13: 100 | DR13: 2020 | DS13: =HAVERQ!D129-HAVERQ!D$128 -> 413 | DT13: =HAVERQ!E129-HAVERQ!E$128 -> -701 | DU13: =HAVERQ!F129-HAVERQ!F$128 -> -765 | DV13: =HAVERQ!G129-HAVERQ!G$128 -> -2369 | DW13: =HAVERQ!H129-HAVERQ!H$128 -> -57 | DX13: =HAVERQ!C129-HAVERQ!C$128 -> -3468 | DZ13: 2002 | EA13: =MIN(EM13:EO13) -> -1.112446 | EB13: =+EF13-EA13 -> 1.2048646 | EC13: =100*((EJ17/EJ13)-1) -> -5.0785919 | ED13: 0 | EF13: =MAX(EM13:EO13) -> 0.092418564 | EG13: =AVERAGE(EM13:EO13) -> -0.35304012 | EI13: 2001 | EJ13: ='IPNR ex BNFL'!I21 -> 44343 | EM13: =(ER13-ER$2)/ER$3 -> 0.092418564 | EN13: =(ES13-ES$2)/ES$3 -> -1.112446 | EO13: =(ET13-ET$2)/ET$3 -> -0.039092939 | ER13: =(HAVERQ!W55*$EW$2)+(HAVERQ!X55*$EX$2)/($EW$2+$EX$2) -> 9.2869377 | ES13: =(HAVERQ!AB55*$EW$2)+(HAVERQ!AC55*$EY$2)+(HAVERQ!AD55*$EZ$2)+(HAVERQ!AE55*$FA$2)/($EW$2+$EY$2+$EZ$2+$FA$2) -> -21.889935 | ET13: =(HAVERQ!Y55*$EW$2)+(HAVERQ!Z55*$EX$2)/($EW$2+$EX$2) -> 0.7612095 | FC13: 43709 | FD13: =100*((HAVERM!E244+HAVERM!F244)/(HAVERM!E$249+HAVERM!F$249)) -> 99.75938 | FE13: =100*(HAVERM!E244/HAVERM!E$249) -> 99.527301 | FF13: =100*(HAVERM!F244/HAVERM!F$249) -> 99.886723 | FG13: 100 | FV13: 42583 | FW13: =HAVERM!G207 -> 355987 | FY13: =FW13-FW12 -> 3227 | GC13: 2012 | GD13: =100*(DataQ!W163/DataQ!W$194) -> 80.264132 | GE13: =100*(DataQ!X163/DataQ!X$194) -> 78.609068 | GF13: =100*(DataQ!C163/DataQ!C$194) -> 79.244766 | GH13: 100 | GJ13: 2007 | GK13: =100*(DataQ!Z143/AVERAGE(DataQ!$Z$203:$Z$206)) -> 81.325525 | GL13: =100*(DataQ!C143/AVERAGE(DataQ!$C$203:$C$206)) -> 84.269541 | GM13: 100 | GO13: 2007 | GP13: =100*(DataQ!Z143/DataQ!$Z$194) -> 81.022114 | GQ13: =100*(DataQ!C143/DataQ!$C$194) -> 81.344969 | GR13: 100 | GT13: 2020 | GU13: =HB13 -> 97.749782 | GV13: =MIN(HC13:HH13) -> 90.759916 | GW13: =+GY13-GV13 -> 13.660056 | GX13: 100 | GY13: =MAX(HC13:HH13) -> 104.41997 | HA13: 2020 | HB13: =100*(DataQ!C195/DataQ!C$194) -> 97.749782 | HC13: =100*(DataQ!Q195/DataQ!Q$194) -> 98.101202 | HD13: =100*(DataQ!R195/DataQ!R$194) -> 104.41997 | HE13: =100*(DataQ!S195/DataQ!S$194) -> 92.789252 | HF13: =100*(DataQ!T195/DataQ!T$194) -> 92.755102 | HG13: =100*(DataQ!U195/DataQ!U$194) -> 90.759916 | HH13: =100*(DataQ!V195/DataQ!V$194) -> 99.506379 | HJ13: 2020 | HK13: =HR13 -> 97.749782 | HL13: =MIN(HS13:HX13) -> 90.759916 | HM13: =+HO13-HL13 -> 13.660056 | HN13: 100 | HO13: =MAX(HS13:HX13) -> 104.41997 | HQ13: 2020 | HR13: =100*(DataQ!C195/DataQ!C$194) -> 97.749782 | HS13: =100*(DataQ!Q195/DataQ!Q$194) -> 98.101202 | HT13: =100*(DataQ!R195/DataQ!R$194) -> 104.41997 | HU13: =100*(DataQ!S195/DataQ!S$194) -> 92.789252 | HV13: =100*(DataQ!T195/DataQ!T$194) -> 92.755102 | HW13: =100*(DataQ!U195/DataQ!U$194) -> 90.759916 | HX13: =100*(DataQ!V195/DataQ!V$194) -> 99.506379 | HZ13: 1998 | IA13: =DataA!J32/'Chart Data'!IF13 -> 2.2021899 | IB13: =IB12*(1+$ID$5/100) -> 2.1577324 | IC13: =100*((IA13/IB13)-1) -> 2.060382 | IF13: =DataA!K32*DataA!L32 -> 886244.63 | IQ13: 2009 | IR13: =HAVERQ!AH84 -> -47.5 | IS13: =100*(('IPNR ex BNFL'!I53/'IPNR ex BNFL'!I49)-1) -> -12.224167 | IT13: 0
B14: =100*((DataQ!C84/DataQ!C80)-1) -> -3.7348199 | C14: =K14 -> 18.392294 | D14: 0 | G14: =100*((AVERAGE(DataQ!C81:C84)/AVERAGE(DataQ!C77:C80))-1) -> -7.3274428 | H14: =AVERAGE(K11:K14) -> 21.991744 | I14: 0 | K14: =L14 -> 18.392294 | L14: =100*(HAVERQ!AF18/HAVERQ!AI18) -> 18.392294 | O14: =100*('ONS CVM_SA_(Quarterly)'!B98/'ONS CVM_SA_(Quarterly)'!B$101) -> 90.93966 | P14: =100*('ONS CVM_SA_(Quarterly)'!D98/'ONS CVM_SA_(Quarterly)'!D$101) -> 76.246526 | R14: 100 | U14: ='ONS CVM_SA_(Quarterly)'!C110-'ONS CVM_SA_(Quarterly)'!C$101 -> 4977 | V14: ='ONS CVM_SA_(Quarterly)'!D110-'ONS CVM_SA_(Quarterly)'!D$101 -> 1807 | W14: ='ONS CVM_SA_(Quarterly)'!E110-'ONS CVM_SA_(Quarterly)'!E$101 -> 449 | X14: ='ONS CVM_SA_(Quarterly)'!F110-'ONS CVM_SA_(Quarterly)'!F$101 -> 849 | Y14: ='ONS CVM_SA_(Quarterly)'!B110-'ONS CVM_SA_(Quarterly)'!B$101 -> 8324 | AB14: =100*(U14/'ONS CVM_SA_(Quarterly)'!$B$101) -> 9.2461173 | AC14: =100*(V14/'ONS CVM_SA_(Quarterly)'!$B$101) -> 3.3569889 | AD14: =100*(W14/'ONS CVM_SA_(Quarterly)'!$B$101) -> 0.83413837 | AE14: =100*(X14/'ONS CVM_SA_(Quarterly)'!$B$101) -> 1.577246 | AF14: =100*(('ONS CVM_SA_(Quarterly)'!B110/'ONS CVM_SA_(Quarterly)'!B$101)-1) -> 15.464071 | AI14: =100*(('ONS CVM_SA_(Quarterly)'!C102-'ONS CVM_SA_(Quarterly)'!C$96)/'ONS CVM_SA_(Quarterly)'!$B$96) -> -1.7421041 | AJ14: =100*(('ONS CVM_SA_(Quarterly)'!D102-'ONS CVM_SA_(Quarterly)'!D$96)/'ONS CVM_SA_(Quarterly)'!$B$96) -> -0.7258767 | AK14: =100*(('ONS CVM_SA_(Quarterly)'!E102-'ONS CVM_SA_(Quarterly)'!E$96)/'ONS CVM_SA_(Quarterly)'!$B$96) -> -4.623028 | AL14: =100*(('ONS CVM_SA_(Quarterly)'!F102-'ONS CVM_SA_(Quarterly)'!F$96)/'ONS CVM_SA_(Quarterly)'!$B$96) -> 1.2904475 | AM14: =100*(('ONS CVM_SA_(Quarterly)'!B102-'ONS CVM_SA_(Quarterly)'!B$96)/'ONS CVM_SA_(Quarterly)'!$B$96) -> -6.4635287 | AP14: =100*(('ONS CVM_SA_(Quarterly)'!C90-AVERAGE('ONS CVM_SA_(Quarterly)'!C$81:C$84))/AVERAGE('ONS CVM_SA_(Quarterly)'!$B$81:$B$84)) -> -6.1401199 | AQ14: =100*(('ONS CVM_SA_(Quarterly)'!D90-AVERAGE('ONS CVM_SA_(Quarterly)'!D$81:D$84))/AVERAGE('ONS CVM_SA_(Quarterly)'!$B$81:$B$84)) -> 0.52470999 | AR14: =100*(('ONS CVM_SA_(Quarterly)'!E90-AVERAGE('ONS CVM_SA_(Quarterly)'!E$81:E$84))/AVERAGE('ONS CVM_SA_(Quarterly)'!$B$81:$B$84)) -> -0.58548721 | AS14: =100*(('ONS CVM_SA_(Quarterly)'!F90-AVERAGE('ONS CVM_SA_(Quarterly)'!F$81:F$84))/AVERAGE('ONS CVM_SA_(Quarterly)'!$B$81:$B$84)) -> 2.3930017 | AT14: =100*(('ONS CVM_SA_(Quarterly)'!B90-AVERAGE('ONS CVM_SA_(Quarterly)'!B$81:B$84))/AVERAGE('ONS CVM_SA_(Quarterly)'!$B$81:$B$84)) -> -2.6673096 | AV14: 43739 | AW14: =HAVERM!D245 -> 0.75 | AX14: =HAVERM!B245 -> 3.26 | AY14: =HAVERM!C245 -> 2.39 | BA14: 44805 | BB14: =AX49-AX$39 -> 1.38 | BC14: =AY49-AY$39 -> 0.23 | BD14: 1000 | BF14: 0 | BJ14: =100*(HAVERQ!B130/HAVERQ!B$128) -> 78.960867 | BK14: =100*(HAVERQ!I130/HAVERQ!I$128) -> 88.667524 | BL14: =100*(HAVERQ!J130/HAVERQ!J$128) -> 70.230913 | BM14: =100*(HAVERQ!K130/HAVERQ!K$128) -> 64.718615 | BN14: =100*((HAVERQ!L130+HAVERQ!M130)/(HAVERQ!L$128+HAVERQ!M$128)) -> 91.624596 | BO14: 100 | BR14: =HAVERQ!I130-HAVERQ!I$128 -> -1058 | BS14: =HAVERQ!J130-HAVERQ!J$128 -> -2862 | BT14: =HAVERQ!K130-HAVERQ!K$128 -> -1141 | BU14: =(HAVERQ!L130+HAVERQ!M130)-(HAVERQ!L$128+HAVERQ!M$128) -> -3318 | BV14: =HAVERQ!N130-HAVERQ!N$128 -> -172 | BW14: =HAVERQ!B130-HAVERQ!B$128 -> -13043 | BZ14: =100*((HAVERQ!I134-HAVERQ!I$128)/HAVERQ!$B$128) -> 0.079039907 | CA14: =100*((HAVERQ!J134-HAVERQ!J$128)/HAVERQ!$B$128) -> -2.5195987 | CB14: =100*((HAVERQ!K134-HAVERQ!K$128)/HAVERQ!$B$128) -> -1.3501307 | CC14: =100*(((HAVERQ!L134+HAVERQ!M134)-(HAVERQ!L$128+HAVERQ!M$128))/HAVERQ!$B$128) -> -7.4345904 | CD14: =CE14-BZ14-CA14-CB14-CC14 -> 4.7617511 | CE14: =100*((HAVERQ!B134-HAVERQ!B$128)/HAVERQ!B$128) -> -6.4635287 | CH14: =HAVERQ!I130 -> 8278 | CI14: =HAVERQ!J130 -> 6752 | CJ14: =HAVERQ!K130 -> 2093 | CK14: =HAVERQ!L130+HAVERQ!M130 -> 36298 | CL14: =HAVERQ!N130 -> 1186 | CO14: =CX14 -> -1446 | CP14: =CY14 -> -754 | CQ14: =CZ14 -> -291 | CR14: =DA14 -> -1008 | CS14: =DC14 -> -2522 | CT14: =+DB14+DD14+DE14+DF14 -> -1411 | CU14: =DG14 -> -3318 | CX14: =HAVERQ!L130-HAVERQ!L$128 -> -1446 | CY14: =HAVERQ!O130-HAVERQ!O$128 -> -754 | CZ14: =HAVERQ!P130-HAVERQ!P$128 -> -291 | DA14: =HAVERQ!Q130-HAVERQ!Q$128 -> -1008 | DB14: =HAVERQ!R130-HAVERQ!R$128 -> -91 | DC14: =HAVERQ!S130-HAVERQ!S$128 -> -2522 | DD14: =HAVERQ!T130-HAVERQ!T$128 -> -269 | DE14: =HAVERQ!U130-HAVERQ!U$128 -> -124 | DF14: =HAVERQ!V130-HAVERQ!V$128 -> -927 | DG14: =(HAVERQ!L130+HAVERQ!M130)-(HAVERQ!L$128+HAVERQ!M$128) -> -3318 | DJ14: =100*(HAVERQ!C130/HAVERQ!C$128) -> 78.622419 | DK14: =100*(HAVERQ!D130/HAVERQ!D$128) -> 45.337478 | DL14: =100*(HAVERQ!E130/HAVERQ!E$128) -> 82.627553 | DM14: =100*(HAVERQ!F130/HAVERQ!F$128) -> 56.092943 | DN14: =100*(HAVERQ!G130/HAVERQ!G$128) -> 86.593294 | DO14: =100*(HAVERQ!H130/HAVERQ!H$128) -> 92.662807 | DP14: 100 | DS14: =HAVERQ!D130-HAVERQ!D$128 -> -2462 | DT14: =HAVERQ!E130-HAVERQ!E$128 -> -2884 | DU14: =HAVERQ!F130-HAVERQ!F$128 -> -11130 | DV14: =HAVERQ!G130-HAVERQ!G$128 -> -4970 | DW14: =HAVERQ!H130-HAVERQ!H$128 -> -1939 | DX14: =HAVERQ!C130-HAVERQ!C$128 -> -23448 | EA14: =MIN(EM14:EO14) -> -1.2544627 | EB14: =+EF14-EA14 -> 1.0643544 | EC14: =100*((EJ18/EJ14)-1) -> -6.8660319 | ED14: 0 | EF14: =MAX(EM14:EO14) -> -0.1901083 | EG14: =AVERAGE(EM14:EO14) -> -0.66875435 | EJ14: ='IPNR ex BNFL'!I22 -> 44742 | EM14: =(ER14-ER$2)/ER$3 -> -0.1901083 | EN14: =(ES14-ES$2)/ES$3 -> -1.2544627 | EO14: =(ET14-ET$2)/ET$3 -> -0.56169206 | ER14: =(HAVERQ!W56*$EW$2)+(HAVERQ!X56*$EX$2)/($EW$2+$EX$2) -> 5.9754719 | ES14: =(HAVERQ!AB56*$EW$2)+(HAVERQ!AC56*$EY$2)+(HAVERQ!AD56*$EZ$2)+(HAVERQ!AE56*$FA$2)/($EW$2+$EY$2+$EZ$2+$FA$2) -> -23.888366 | ET14: =(HAVERQ!Y56*$EW$2)+(HAVERQ!Z56*$EX$2)/($EW$2+$EX$2) -> -0.059554887 | FC14: 43739 | FD14: =100*((HAVERM!E245+HAVERM!F245)/(HAVERM!E$249+HAVERM!F$249)) -> 99.863968 | FE14: =100*(HAVERM!E245/HAVERM!E$249) -> 99.468133 | FF14: =100*(HAVERM!F245/HAVERM!F$249) -> 100.08116 | FG14: 100 | FV14: 42614 | FW14: =HAVERM!G208 -> 358565 | FY14: =FW14-FW13 -> 2578 | GD14: =100*(DataQ!W164/DataQ!W$194) -> 77.369115 | GE14: =100*(DataQ!X164/DataQ!X$194) -> 75.873678 | GF14: =100*(DataQ!C164/DataQ!C$194) -> 75.836371 | GH14: 100 | GK14: =100*(DataQ!Z144/AVERAGE(DataQ!$Z$203:$Z$206)) -> 82.464293 | GL14: =100*(DataQ!C144/AVERAGE(DataQ!$C$203:$C$206)) -> 85.449304 | GM14: 100 | GP14: =100*(DataQ!Z144/DataQ!$Z$194) -> 82.156633 | GQ14: =100*(DataQ!C144/DataQ!$C$194) -> 82.483789 | GR14: 100 | GU14: =HB14 -> 78.960867 | GV14: =MIN(HC14:HH14) -> 76.366352 | GW14: =+GY14-GV14 -> 20.702577 | GX14: 100 | GY14: =MAX(HC14:HH14) -> 97.068929 | HB14: =100*(DataQ!C196/DataQ!C$194) -> 78.960867 | HC14: =100*(DataQ!Q196/DataQ!Q$194) -> 90.21311 | HD14: =100*(DataQ!R196/DataQ!R$194) -> 97.068929 | HE14: =100*(DataQ!S196/DataQ!S$194) -> 82.562603 | HF14: =100*(DataQ!T196/DataQ!T$194) -> 82.29881 | HG14: =100*(DataQ!U196/DataQ!U$194) -> 76.366352 | HH14: =100*(DataQ!V196/DataQ!V$194) -> 82.788302 | HK14: =HR14 -> 78.960867 | HL14: =MIN(HS14:HX14) -> 76.366352 | HM14: =+HO14-HL14 -> 20.702577 | HN14: 100 | HO14: =MAX(HS14:HX14) -> 97.068929 | HR14: =100*(DataQ!C196/DataQ!C$194) -> 78.960867 | HS14: =100*(DataQ!Q196/DataQ!Q$194) -> 90.21311 | HT14: =100*(DataQ!R196/DataQ!R$194) -> 97.068929 | HU14: =100*(DataQ!S196/DataQ!S$194) -> 82.562603 | HV14: =100*(DataQ!T196/DataQ!T$194) -> 82.29881 | HW14: =100*(DataQ!U196/DataQ!U$194) -> 76.366352 | HX14: =100*(DataQ!V196/DataQ!V$194) -> 82.788302 | HZ14: 1999 | IA14: =DataA!J33/'Chart Data'!IF14 -> 2.2674166 | IB14: =IB13*(1+$ID$5/100) -> 2.2150541 | IC14: =100*((IA14/IB14)-1) -> 2.3639386 | IF14: =DataA!K33*DataA!L33 -> 893818.97 | IR14: =HAVERQ!AH85 -> -28.4 | IS14: =100*(('IPNR ex BNFL'!I54/'IPNR ex BNFL'!I50)-1) -> -19.833301 | IT14: 0
B15: =100*((DataQ!C85/DataQ!C81)-1) -> 0.73436832 | C15: =K15 -> 14.791891 | D15: 0 | G15: =100*((AVERAGE(DataQ!C82:C85)/AVERAGE(DataQ!C78:C81))-1) -> -4.327874 | H15: =AVERAGE(K12:K15) -> 20.281872 | I15: 0 | K15: =L15 -> 14.791891 | L15: =100*(HAVERQ!AF19/HAVERQ!AI19) -> 14.791891 | O15: =100*('ONS CVM_SA_(Quarterly)'!B99/'ONS CVM_SA_(Quarterly)'!B$101) -> 101.63855 | P15: =100*('ONS CVM_SA_(Quarterly)'!D99/'ONS CVM_SA_(Quarterly)'!D$101) -> 86.545692 | R15: 100 | U15: ='ONS CVM_SA_(Quarterly)'!C111-'ONS CVM_SA_(Quarterly)'!C$101 -> 4418 | V15: ='ONS CVM_SA_(Quarterly)'!D111-'ONS CVM_SA_(Quarterly)'!D$101 -> 1438 | W15: ='ONS CVM_SA_(Quarterly)'!E111-'ONS CVM_SA_(Quarterly)'!E$101 -> -52 | X15: ='ONS CVM_SA_(Quarterly)'!F111-'ONS CVM_SA_(Quarterly)'!F$101 -> 422 | Y15: ='ONS CVM_SA_(Quarterly)'!B111-'ONS CVM_SA_(Quarterly)'!B$101 -> 6468 | AB15: =100*(U15/'ONS CVM_SA_(Quarterly)'!$B$101) -> 8.2076243 | AC15: =100*(V15/'ONS CVM_SA_(Quarterly)'!$B$101) -> 2.6714721 | AD15: =100*(W15/'ONS CVM_SA_(Quarterly)'!$B$101) -> -0.096603998 | AE15: =100*(X15/'ONS CVM_SA_(Quarterly)'!$B$101) -> 0.7839786 | AF15: =100*(('ONS CVM_SA_(Quarterly)'!B111/'ONS CVM_SA_(Quarterly)'!B$101)-1) -> 12.016051 | AI15: =100*(('ONS CVM_SA_(Quarterly)'!C103-'ONS CVM_SA_(Quarterly)'!C$96)/'ONS CVM_SA_(Quarterly)'!$B$96) -> -0.42907378 | AJ15: =100*(('ONS CVM_SA_(Quarterly)'!D103-'ONS CVM_SA_(Quarterly)'!D$96)/'ONS CVM_SA_(Quarterly)'!$B$96) -> 0.14356228 | AK15: =100*(('ONS CVM_SA_(Quarterly)'!E103-'ONS CVM_SA_(Quarterly)'!E$96)/'ONS CVM_SA_(Quarterly)'!$B$96) -> -5.9425106 | AL15: =100*(('ONS CVM_SA_(Quarterly)'!F103-'ONS CVM_SA_(Quarterly)'!F$96)/'ONS CVM_SA_(Quarterly)'!$B$96) -> -1.2001161 | AM15: =100*(('ONS CVM_SA_(Quarterly)'!B103-'ONS CVM_SA_(Quarterly)'!B$96)/'ONS CVM_SA_(Quarterly)'!$B$96) -> -8.0588444 | AP15: =100*(('ONS CVM_SA_(Quarterly)'!C91-AVERAGE('ONS CVM_SA_(Quarterly)'!C$81:C$84))/AVERAGE('ONS CVM_SA_(Quarterly)'!$B$81:$B$84)) -> -2.2649644 | AQ15: =100*(('ONS CVM_SA_(Quarterly)'!D91-AVERAGE('ONS CVM_SA_(Quarterly)'!D$81:D$84))/AVERAGE('ONS CVM_SA_(Quarterly)'!$B$81:$B$84)) -> 0.2994291 | AR15: =100*(('ONS CVM_SA_(Quarterly)'!E91-AVERAGE('ONS CVM_SA_(Quarterly)'!E$81:E$84))/AVERAGE('ONS CVM_SA_(Quarterly)'!$B$81:$B$84)) -> -0.616281 | AS15: =100*(('ONS CVM_SA_(Quarterly)'!F91-AVERAGE('ONS CVM_SA_(Quarterly)'!F$81:F$84))/AVERAGE('ONS CVM_SA_(Quarterly)'!$B$81:$B$84)) -> 1.6896067 | AT15: =100*(('ONS CVM_SA_(Quarterly)'!B91-AVERAGE('ONS CVM_SA_(Quarterly)'!B$81:B$84))/AVERAGE('ONS CVM_SA_(Quarterly)'!$B$81:$B$84)) -> -2.570066 | AV15: 43770 | AW15: =HAVERM!D246 -> 0.75 | AX15: =HAVERM!B246 -> 3.24 | AY15: =HAVERM!C246 -> 2.4 | BA15: 44835 | BB15: =AX50-AX$39 -> 1.63 | BC15: =AY50-AY$39 -> 0.27 | BD15: 1000 | BF15: 0 | BJ15: =100*(HAVERQ!B131/HAVERQ!B$128) -> 88.250476 | BK15: =100*(HAVERQ!I131/HAVERQ!I$128) -> 93.841045 | BL15: =100*(HAVERQ!J131/HAVERQ!J$128) -> 71.770335 | BM15: =100*(HAVERQ!K131/HAVERQ!K$128) -> 78.354978 | BN15: =100*((HAVERQ!L131+HAVERQ!M131)/(HAVERQ!L$128+HAVERQ!M$128)) -> 87.141559 | BO15: 100 | BR15: =HAVERQ!I131-HAVERQ!I$128 -> -575 | BS15: =HAVERQ!J131-HAVERQ!J$128 -> -2714 | BT15: =HAVERQ!K131-HAVERQ!K$128 -> -700 | BU15: =(HAVERQ!L131+HAVERQ!M131)-(HAVERQ!L$128+HAVERQ!M$128) -> -5094 | BV15: =HAVERQ!N131-HAVERQ!N$128 -> -105 | BW15: =HAVERQ!B131-HAVERQ!B$128 -> -7284 | BZ15: =100*((HAVERQ!I135-HAVERQ!I$128)/HAVERQ!$B$128) -> 0.380682 | CA15: =100*((HAVERQ!J135-HAVERQ!J$128)/HAVERQ!$B$128) -> -2.774462 | CB15: =100*((HAVERQ!K135-HAVERQ!K$128)/HAVERQ!$B$128) -> -1.0404233 | CC15: =100*(((HAVERQ!L135+HAVERQ!M135)-(HAVERQ!L$128+HAVERQ!M$128))/HAVERQ!$B$128) -> -6.0102591 | CD15: =CE15-BZ15-CA15-CB15-CC15 -> 1.385618 | CE15: =100*((HAVERQ!B135-HAVERQ!B$128)/HAVERQ!B$128) -> -8.0588444 | CH15: =HAVERQ!I131 -> 8761 | CI15: =HAVERQ!J131 -> 6900 | CJ15: =HAVERQ!K131 -> 2534 | CK15: =HAVERQ!L131+HAVERQ!M131 -> 34522 | CL15: =HAVERQ!N131 -> 1253 | CO15: =CX15 -> -1143 | CP15: =CY15 -> -543 | CQ15: =CZ15 -> -485 | CR15: =DA15 -> -15 | CS15: =DC15 -> -732 | CT15: =+DB15+DD15+DE15+DF15 -> -1399 | CU15: =DG15 -> -5094 | CX15: =HAVERQ!L131-HAVERQ!L$128 -> -1143 | CY15: =HAVERQ!O131-HAVERQ!O$128 -> -543 | CZ15: =HAVERQ!P131-HAVERQ!P$128 -> -485 | DA15: =HAVERQ!Q131-HAVERQ!Q$128 -> -15 | DB15: =HAVERQ!R131-HAVERQ!R$128 -> -52 | DC15: =HAVERQ!S131-HAVERQ!S$128 -> -732 | DD15: =HAVERQ!T131-HAVERQ!T$128 -> -367 | DE15: =HAVERQ!U131-HAVERQ!U$128 -> -236 | DF15: =HAVERQ!V131-HAVERQ!V$128 -> -744 | DG15: =(HAVERQ!L131+HAVERQ!M131)-(HAVERQ!L$128+HAVERQ!M$128) -> -5094 | DJ15: =100*(HAVERQ!C131/HAVERQ!C$128) -> 91.239458 | DK15: =100*(HAVERQ!D131/HAVERQ!D$128) -> 117.29574 | DL15: =100*(HAVERQ!E131/HAVERQ!E$128) -> 89.01271 | DM15: =100*(HAVERQ!F131/HAVERQ!F$128) -> 90.654464 | DN15: =100*(HAVERQ!G131/HAVERQ!G$128) -> 87.008713 | DO15: =100*(HAVERQ!H131/HAVERQ!H$128) -> 93.737465 | DP15: 100 | DS15: =HAVERQ!D131-HAVERQ!D$128 -> 779 | DT15: =HAVERQ!E131-HAVERQ!E$128 -> -1824 | DU15: =HAVERQ!F131-HAVERQ!F$128 -> -2369 | DV15: =HAVERQ!G131-HAVERQ!G$128 -> -4816 | DW15: =HAVERQ!H131-HAVERQ!H$128 -> -1655 | DX15: =HAVERQ!C131-HAVERQ!C$128 -> -9609 | EA15: =MIN(EM15:EO15) -> -1.0540851 | EB15: =+EF15-EA15 -> 1.3947672 | EC15: =100*((EJ19/EJ15)-1) -> -1.7433284 | ED15: 0 | EF15: =MAX(EM15:EO15) -> 0.34068212 | EG15: =AVERAGE(EM15:EO15) -> -0.36309884 | EJ15: ='IPNR ex BNFL'!I23 -> 44742 | EL15: 2002 | EM15: =(ER15-ER$2)/ER$3 -> 0.34068212 | EN15: =(ES15-ES$2)/ES$3 -> -1.0540851 | EO15: =(ET15-ET$2)/ET$3 -> -0.37589355 | EQ15: 2002 | ER15: =(HAVERQ!W57*$EW$2)+(HAVERQ!X57*$EX$2)/($EW$2+$EX$2) -> 12.196807 | ES15: =(HAVERQ!AB57*$EW$2)+(HAVERQ!AC57*$EY$2)+(HAVERQ!AD57*$EZ$2)+(HAVERQ!AE57*$FA$2)/($EW$2+$EY$2+$EZ$2+$FA$2) -> -21.068692 | ET15: =(HAVERQ!Y57*$EW$2)+(HAVERQ!Z57*$EX$2)/($EW$2+$EX$2) -> 0.23224966 | FC15: 43770 | FD15: =100*((HAVERM!E246+HAVERM!F246)/(HAVERM!E$249+HAVERM!F$249)) -> 100.82827 | FE15: =100*(HAVERM!E246/HAVERM!E$249) -> 100.59618 | FF15: =100*(HAVERM!F246/HAVERM!F$249) -> 100.95562 | FG15: 100 | FV15: 42644 | FW15: =HAVERM!G209 -> 359546 | FY15: =FW15-FW14 -> 981 | GD15: =100*(DataQ!W165/DataQ!W$194) -> 78.546476 | GE15: =100*(DataQ!X165/DataQ!X$194) -> 76.856223 | GF15: =100*(DataQ!C165/DataQ!C$194) -> 76.21544 | GH15: 100 | GK15: =100*(DataQ!Z145/AVERAGE(DataQ!$Z$203:$Z$206)) -> 78.827245 | GL15: =100*(DataQ!C145/AVERAGE(DataQ!$C$203:$C$206)) -> 81.689435 | GM15: 100 | GP15: =100*(DataQ!Z145/DataQ!$Z$194) -> 78.533154 | GQ15: =100*(DataQ!C145/DataQ!$C$194) -> 78.854405 | GR15: 100 | GU15: =HB15 -> 88.250476 | GV15: =MIN(HC15:HH15) -> 88.73197 | GW15: =+GY15-GV15 -> 8.4496915 | GX15: 100 | GY15: =MAX(HC15:HH15) -> 97.181662 | HB15: =100*(DataQ!C197/DataQ!C$194) -> 88.250476 | HC15: =100*(DataQ!Q197/DataQ!Q$194) -> 94.158839 | HD15: =100*(DataQ!R197/DataQ!R$194) -> 97.099377 | HE15: =100*(DataQ!S197/DataQ!S$194) -> 91.208189 | HF15: =100*(DataQ!T197/DataQ!T$194) -> 97.181662 | HG15: =100*(DataQ!U197/DataQ!U$194) -> 96.36863 | HH15: =100*(DataQ!V197/DataQ!V$194) -> 88.73197 | HK15: =HR15 -> 88.250476 | HL15: =MIN(HS15:HX15) -> 88.73197 | HM15: =+HO15-HL15 -> 8.4496915 | HN15: 100 | HO15: =MAX(HS15:HX15) -> 97.181662 | HR15: =100*(DataQ!C197/DataQ!C$194) -> 88.250476 | HS15: =100*(DataQ!Q197/DataQ!Q$194) -> 94.158839 | HT15: =100*(DataQ!R197/DataQ!R$194) -> 97.099377 | HU15: =100*(DataQ!S197/DataQ!S$194) -> 91.208189 | HV15: =100*(DataQ!T197/DataQ!T$194) -> 97.181662 | HW15: =100*(DataQ!U197/DataQ!U$194) -> 96.36863 | HX15: =100*(DataQ!V197/DataQ!V$194) -> 88.73197 | HZ15: 2000 | IA15: =DataA!J34/'Chart Data'!IF15 -> 2.3578096 | IB15: =IB14*(1+$ID$5/100) -> 2.2738986 | IC15: =100*((IA15/IB15)-1) -> 3.6901808 | IF15: =DataA!K34*DataA!L34 -> 895962.1 | IR15: =HAVERQ!AH86 -> -24.2 | IS15: =100*(('IPNR ex BNFL'!I55/'IPNR ex BNFL'!I51)-1) -> -18.498736 | IT15: 0
B16: =100*((DataQ!C86/DataQ!C82)-1) -> -6.1297894 | C16: =K16 -> 13.787557 | D16: 0 | G16: =100*((AVERAGE(DataQ!C83:C86)/AVERAGE(DataQ!C79:C82))-1) -> -3.7773734 | H16: =AVERAGE(K13:K16) -> 18.643066 | I16: 0 | K16: =L16 -> 13.787557 | L16: =100*(HAVERQ!AF20/HAVERQ!AI20) -> 13.787557 | O16: =100*('ONS CVM_SA_(Quarterly)'!B100/'ONS CVM_SA_(Quarterly)'!B$101) -> 107.33261 | P16: =100*('ONS CVM_SA_(Quarterly)'!D100/'ONS CVM_SA_(Quarterly)'!D$101) -> 97.515122 | R16: 100 | U16: ='ONS CVM_SA_(Quarterly)'!C112-'ONS CVM_SA_(Quarterly)'!C$101 -> 4681 | V16: ='ONS CVM_SA_(Quarterly)'!D112-'ONS CVM_SA_(Quarterly)'!D$101 -> 1253 | W16: ='ONS CVM_SA_(Quarterly)'!E112-'ONS CVM_SA_(Quarterly)'!E$101 -> 842 | X16: ='ONS CVM_SA_(Quarterly)'!F112-'ONS CVM_SA_(Quarterly)'!F$101 -> 175 | Y16: ='ONS CVM_SA_(Quarterly)'!B112-'ONS CVM_SA_(Quarterly)'!B$101 -> 7193 | AB16: =100*(U16/'ONS CVM_SA_(Quarterly)'!$B$101) -> 8.6962176 | AC16: =100*(V16/'ONS CVM_SA_(Quarterly)'!$B$101) -> 2.3277848 | AD16: =100*(W16/'ONS CVM_SA_(Quarterly)'!$B$101) -> 1.5642417 | AE16: =100*(X16/'ONS CVM_SA_(Quarterly)'!$B$101) -> 0.32510961 | AF16: =100*(('ONS CVM_SA_(Quarterly)'!B112/'ONS CVM_SA_(Quarterly)'!B$101)-1) -> 13.362934 | AI16: =100*(('ONS CVM_SA_(Quarterly)'!C104-'ONS CVM_SA_(Quarterly)'!C$96)/'ONS CVM_SA_(Quarterly)'!$B$96) -> 0.82266026 | AJ16: =100*(('ONS CVM_SA_(Quarterly)'!D104-'ONS CVM_SA_(Quarterly)'!D$96)/'ONS CVM_SA_(Quarterly)'!$B$96) -> -0.73878117 | AK16: =100*(('ONS CVM_SA_(Quarterly)'!E104-'ONS CVM_SA_(Quarterly)'!E$96)/'ONS CVM_SA_(Quarterly)'!$B$96) -> -6.3006097 | AL16: =100*(('ONS CVM_SA_(Quarterly)'!F104-'ONS CVM_SA_(Quarterly)'!F$96)/'ONS CVM_SA_(Quarterly)'!$B$96) -> -1.0759106 | AM16: =100*(('ONS CVM_SA_(Quarterly)'!B104-'ONS CVM_SA_(Quarterly)'!B$96)/'ONS CVM_SA_(Quarterly)'!$B$96) -> -7.7684937 | AP16: =100*(('ONS CVM_SA_(Quarterly)'!C92-AVERAGE('ONS CVM_SA_(Quarterly)'!C$81:C$84))/AVERAGE('ONS CVM_SA_(Quarterly)'!$B$81:$B$84)) -> -1.9521643 | AQ16: =100*(('ONS CVM_SA_(Quarterly)'!D92-AVERAGE('ONS CVM_SA_(Quarterly)'!D$81:D$84))/AVERAGE('ONS CVM_SA_(Quarterly)'!$B$81:$B$84)) -> -0.62762608 | AR16: =100*(('ONS CVM_SA_(Quarterly)'!E92-AVERAGE('ONS CVM_SA_(Quarterly)'!E$81:E$84))/AVERAGE('ONS CVM_SA_(Quarterly)'!$B$81:$B$84)) -> 0.75161161 | AS16: =100*(('ONS CVM_SA_(Quarterly)'!F92-AVERAGE('ONS CVM_SA_(Quarterly)'!F$81:F$84))/AVERAGE('ONS CVM_SA_(Quarterly)'!$B$81:$B$84)) -> 1.6069497 | AT16: =100*(('ONS CVM_SA_(Quarterly)'!B92-AVERAGE('ONS CVM_SA_(Quarterly)'!B$81:B$84))/AVERAGE('ONS CVM_SA_(Quarterly)'!$B$81:$B$84)) -> -1.8877404 | AV16: 43800 | AW16: =HAVERM!D247 -> 0.75 | AX16: =HAVERM!B247 -> 3.28 | AY16: =HAVERM!C247 -> 2.37 | BA16: 44866 | BB16: =AX51-AX$39 -> 2.12 | BC16: =AY51-AY$39 -> 0.37 | BD16: 1000 | BF16: 0 | BJ16: =100*(HAVERQ!B132/HAVERQ!B$128) -> 93.194503 | BK16: =100*(HAVERQ!I132/HAVERQ!I$128) -> 96.529563 | BL16: =100*(HAVERQ!J132/HAVERQ!J$128) -> 69.138756 | BM16: =100*(HAVERQ!K132/HAVERQ!K$128) -> 74.14966 | BN16: =100*((HAVERQ!L132+HAVERQ!M132)/(HAVERQ!L$128+HAVERQ!M$128)) -> 89.797052 | BO16: 100 | BR16: =HAVERQ!I132-HAVERQ!I$128 -> -324 | BS16: =HAVERQ!J132-HAVERQ!J$128 -> -2967 | BT16: =HAVERQ!K132-HAVERQ!K$128 -> -836 | BU16: =(HAVERQ!L132+HAVERQ!M132)-(HAVERQ!L$128+HAVERQ!M$128) -> -4042 | BV16: =HAVERQ!N132-HAVERQ!N$128 -> -67 | BW16: =HAVERQ!B132-HAVERQ!B$128 -> -4219 | BZ16: =100*((HAVERQ!I136-HAVERQ!I$128)/HAVERQ!$B$128) -> 0.65328903 | CA16: =100*((HAVERQ!J136-HAVERQ!J$128)/HAVERQ!$B$128) -> -2.6470304 | CB16: =100*((HAVERQ!K136-HAVERQ!K$128)/HAVERQ!$B$128) -> -1.5791851 | CC16: =100*(((HAVERQ!L136+HAVERQ!M136)-(HAVERQ!L$128+HAVERQ!M$128))/HAVERQ!$B$128) -> -6.0973643 | CD16: =CE16-BZ16-CA16-CB16-CC16 -> 1.9017969 | CE16: =100*((HAVERQ!B136-HAVERQ!B$128)/HAVERQ!B$128) -> -7.7684937 | CH16: =HAVERQ!I132 -> 9012 | CI16: =HAVERQ!J132 -> 6647 | CJ16: =HAVERQ!K132 -> 2398 | CK16: =HAVERQ!L132+HAVERQ!M132 -> 35574 | CL16: =HAVERQ!N132 -> 1291 | CO16: =CX16 -> -480 | CP16: =CY16 -> -580 | CQ16: =CZ16 -> -196 | CR16: =DA16 -> 2091 | CS16: =DC16 -> -222 | CT16: =+DB16+DD16+DE16+DF16 -> -902 | CU16: =DG16 -> -4042 | CX16: =HAVERQ!L132-HAVERQ!L$128 -> -480 | CY16: =HAVERQ!O132-HAVERQ!O$128 -> -580 | CZ16: =HAVERQ!P132-HAVERQ!P$128 -> -196 | DA16: =HAVERQ!Q132-HAVERQ!Q$128 -> 2091 | DB16: =HAVERQ!R132-HAVERQ!R$128 -> 433 | DC16: =HAVERQ!S132-HAVERQ!S$128 -> -222 | DD16: =HAVERQ!T132-HAVERQ!T$128 -> -414 | DE16: =HAVERQ!U132-HAVERQ!U$128 -> -186 | DF16: =HAVERQ!V132-HAVERQ!V$128 -> -735 | DG16: =(HAVERQ!L132+HAVERQ!M132)-(HAVERQ!L$128+HAVERQ!M$128) -> -4042 | DJ16: =100*(HAVERQ!C132/HAVERQ!C$128) -> 96.957651 | DK16: =100*(HAVERQ!D132/HAVERQ!D$128) -> 140.96359 | DL16: =100*(HAVERQ!E132/HAVERQ!E$128) -> 97.451961 | DM16: =100*(HAVERQ!F132/HAVERQ!F$128) -> 96.457454 | DN16: =100*(HAVERQ!G132/HAVERQ!G$128) -> 92.576407 | DO16: =100*(HAVERQ!H132/HAVERQ!H$128) -> 94.498051 | DP16: 100 | DS16: =HAVERQ!D132-HAVERQ!D$128 -> 1845 | DT16: =HAVERQ!E132-HAVERQ!E$128 -> -423 | DU16: =HAVERQ!F132-HAVERQ!F$128 -> -898 | DV16: =HAVERQ!G132-HAVERQ!G$128 -> -2752 | DW16: =HAVERQ!H132-HAVERQ!H$128 -> -1454 | DX16: =HAVERQ!C132-HAVERQ!C$128 -> -3337 | EA16: =MIN(EM16:EO16) -> -0.7994043 | EB16: =+EF16-EA16 -> 1.3449852 | EC16: =100*((EJ20/EJ16)-1) -> 6.6654224 | ED16: 0 | EF16: =MAX(EM16:EO16) -> 0.54558095 | EG16: =AVERAGE(EM16:EO16) -> -0.09624641 | EJ16: ='IPNR ex BNFL'!I24 -> 42863 | EM16: =(ER16-ER$2)/ER$3 -> 0.54558095 | EN16: =(ES16-ES$2)/ES$3 -> -0.7994043 | EO16: =(ET16-ET$2)/ET$3 -> -0.034915886 | ER16: =(HAVERQ!W58*$EW$2)+(HAVERQ!X58*$EX$2)/($EW$2+$EX$2) -> 14.598404 | ES16: =(HAVERQ!AB58*$EW$2)+(HAVERQ!AC58*$EY$2)+(HAVERQ!AD58*$EZ$2)+(HAVERQ!AE58*$FA$2)/($EW$2+$EY$2+$EZ$2+$FA$2) -> -17.484873 | ET16: =(HAVERQ!Y58*$EW$2)+(HAVERQ!Z58*$EX$2)/($EW$2+$EX$2) -> 0.76776974 | FC16: 43800 | FD16: =100*((HAVERM!E247+HAVERM!F247)/(HAVERM!E$249+HAVERM!F$249)) -> 100.93992 | FE16: =100*(HAVERM!E247/HAVERM!E$249) -> 100.4637 | FF16: =100*(HAVERM!F247/HAVERM!F$249) -> 101.20123 | FG16: 100 | FV16: 42675 | FW16: =HAVERM!G210 -> 359015 | FY16: =FW16-FW15 -> -531 | GD16: =100*(DataQ!W166/DataQ!W$194) -> 85.322347 | GE16: =100*(DataQ!X166/DataQ!X$194) -> 83.41384 | GF16: =100*(DataQ!C166/DataQ!C$194) -> 80.635223 | GH16: 100 | GK16: =100*(DataQ!Z146/AVERAGE(DataQ!$Z$203:$Z$206)) -> 85.442608 | GL16: =100*(DataQ!C146/AVERAGE(DataQ!$C$203:$C$206)) -> 88.550779 | GM16: 100 | GP16: =100*(DataQ!Z146/DataQ!$Z$194) -> 85.123837 | GQ16: =100*(DataQ!C146/DataQ!$C$194) -> 85.477627 | GR16: 100 | GU16: =HB16 -> 93.194503 | GV16: =MIN(HC16:HH16) -> 91.349547 | GW16: =+GY16-GV16 -> 9.0571364 | GX16: 100 | GY16: =MAX(HC16:HH16) -> 100.40668 | HB16: =100*(DataQ!C198/DataQ!C$194) -> 93.194503 | HC16: =100*(DataQ!Q198/DataQ!Q$194) -> 96.677103 | HD16: =100*(DataQ!R198/DataQ!R$194) -> 98.868123 | HE16: =100*(DataQ!S198/DataQ!S$194) -> 93.940779 | HF16: =100*(DataQ!T198/DataQ!T$194) -> 100.40668 | HG16: =100*(DataQ!U198/DataQ!U$194) -> 95.572845 | HH16: =100*(DataQ!V198/DataQ!V$194) -> 91.349547 | HK16: =HR16 -> 93.194503 | HL16: =MIN(HS16:HX16) -> 91.349547 | HM16: =+HO16-HL16 -> 9.0571364 | HN16: 100 | HO16: =MAX(HS16:HX16) -> 100.40668 | HR16: =100*(DataQ!C198/DataQ!C$194) -> 93.194503 | HS16: =100*(DataQ!Q198/DataQ!Q$194) -> 96.677103 | HT16: =100*(DataQ!R198/DataQ!R$194) -> 98.868123 | HU16: =100*(DataQ!S198/DataQ!S$194) -> 93.940779 | HV16: =100*(DataQ!T198/DataQ!T$194) -> 100.40668 | HW16: =100*(DataQ!U198/DataQ!U$194) -> 95.572845 | HX16: =100*(DataQ!V198/DataQ!V$194) -> 91.349547 | HZ16: 2001 | IA16: =DataA!J35/'Chart Data'!IF16 -> 2.415808 | IB16: =IB15*(1+$ID$5/100) -> 2.3343063 | IC16: =100*((IA16/IB16)-1) -> 3.4914726 | IF16: =DataA!K35*DataA!L35 -> 905489.6 | IR16: =HAVERQ!AH87 -> -6.6 | IS16: =100*(('IPNR ex BNFL'!I56/'IPNR ex BNFL'!I52)-1) -> -16.389499 | IT16: 0
A17: 1993 | B17: =100*((DataQ!C87/DataQ!C83)-1) -> -4.3201741 | C17: =K17 -> 12.715625 | D17: 0 | F17: 1993 | G17: =100*((AVERAGE(DataQ!C84:C87)/AVERAGE(DataQ!C80:C83))-1) -> -3.391577 | H17: =AVERAGE(K14:K17) -> 14.921842 | I17: 0 | K17: =L17 -> 12.715625 | L17: =100*(HAVERQ!AF21/HAVERQ!AI21) -> 12.715625 | N17: 2021 | O17: =100*('ONS CVM_SA_(Quarterly)'!B101/'ONS CVM_SA_(Quarterly)'!B$101) -> 100 | P17: =100*('ONS CVM_SA_(Quarterly)'!D101/'ONS CVM_SA_(Quarterly)'!D$101) -> 100 | R17: 100 | T17: 2024 | U17: ='ONS CVM_SA_(Quarterly)'!C113-'ONS CVM_SA_(Quarterly)'!C$101 -> 4542 | V17: ='ONS CVM_SA_(Quarterly)'!D113-'ONS CVM_SA_(Quarterly)'!D$101 -> 1909 | W17: ='ONS CVM_SA_(Quarterly)'!E113-'ONS CVM_SA_(Quarterly)'!E$101 -> 902 | X17: ='ONS CVM_SA_(Quarterly)'!F113-'ONS CVM_SA_(Quarterly)'!F$101 -> -53 | Y17: ='ONS CVM_SA_(Quarterly)'!B113-'ONS CVM_SA_(Quarterly)'!B$101 -> 7542 | AA17: 2024 | AB17: =100*(U17/'ONS CVM_SA_(Quarterly)'!$B$101) -> 8.4379877 | AC17: =100*(V17/'ONS CVM_SA_(Quarterly)'!$B$101) -> 3.5464814 | AD17: =100*(W17/'ONS CVM_SA_(Quarterly)'!$B$101) -> 1.6757078 | AE17: =100*(X17/'ONS CVM_SA_(Quarterly)'!$B$101) -> -0.098461767 | AF17: =100*(('ONS CVM_SA_(Quarterly)'!B113/'ONS CVM_SA_(Quarterly)'!B$101)-1) -> 14.011295 | AH17: 2022 | AI17: =100*(('ONS CVM_SA_(Quarterly)'!C105-'ONS CVM_SA_(Quarterly)'!C$96)/'ONS CVM_SA_(Quarterly)'!$B$96) -> -0.18066264 | AJ17: =100*(('ONS CVM_SA_(Quarterly)'!D105-'ONS CVM_SA_(Quarterly)'!D$96)/'ONS CVM_SA_(Quarterly)'!$B$96) -> 1.3485176 | AK17: =100*(('ONS CVM_SA_(Quarterly)'!E105-'ONS CVM_SA_(Quarterly)'!E$96)/'ONS CVM_SA_(Quarterly)'!$B$96) -> -4.566571 | AL17: =100*(('ONS CVM_SA_(Quarterly)'!F105-'ONS CVM_SA_(Quarterly)'!F$96)/'ONS CVM_SA_(Quarterly)'!$B$96) -> -1.2468949 | AM17: =100*(('ONS CVM_SA_(Quarterly)'!B105-'ONS CVM_SA_(Quarterly)'!B$96)/'ONS CVM_SA_(Quarterly)'!$B$96) -> -4.9875794 | AO17: 2019 | AP17: =100*(('ONS CVM_SA_(Quarterly)'!C93-AVERAGE('ONS CVM_SA_(Quarterly)'!C$81:C$84))/AVERAGE('ONS CVM_SA_(Quarterly)'!$B$81:$B$84)) -> -2.811149 | AQ17: =100*(('ONS CVM_SA_(Quarterly)'!D93-AVERAGE('ONS CVM_SA_(Quarterly)'!D$81:D$84))/AVERAGE('ONS CVM_SA_(Quarterly)'!$B$81:$B$84)) -> -0.71352455 | AR17: =100*(('ONS CVM_SA_(Quarterly)'!E93-AVERAGE('ONS CVM_SA_(Quarterly)'!E$81:E$84))/AVERAGE('ONS CVM_SA_(Quarterly)'!$B$81:$B$84)) -> 1.8634295 | AS17: =100*(('ONS CVM_SA_(Quarterly)'!F93-AVERAGE('ONS CVM_SA_(Quarterly)'!F$81:F$84))/AVERAGE('ONS CVM_SA_(Quarterly)'!$B$81:$B$84)) -> 2.6344899 | AT17: =100*(('ONS CVM_SA_(Quarterly)'!B93-AVERAGE('ONS CVM_SA_(Quarterly)'!B$81:B$84))/AVERAGE('ONS CVM_SA_(Quarterly)'!$B$81:$B$84)) -> -0.80995774 | AV17: 43831 | AW17: =HAVERM!D248 -> 0.75 | AX17: =HAVERM!B248 -> 3.29 | AY17: =HAVERM!C248 -> 2.37 | BA17: 44896 | BB17: =AX52-AX$39 -> 2.44 | BC17: =AY52-AY$39 -> 0.49 | BD17: 1000 | BF17: 0 | BI17: 2021 | BJ17: =100*(HAVERQ!B133/HAVERQ!B$128) -> 86.827758 | BK17: =100*(HAVERQ!I133/HAVERQ!I$128) -> 96.722365 | BL17: =100*(HAVERQ!J133/HAVERQ!J$128) -> 80.653214 | BM17: =100*(HAVERQ!K133/HAVERQ!K$128) -> 82.436611 | BN17: =100*((HAVERQ!L133+HAVERQ!M133)/(HAVERQ!L$128+HAVERQ!M$128)) -> 87.82815 | BO17: 100 | BQ17: 2021 | BR17: =HAVERQ!I133-HAVERQ!I$128 -> -306 | BS17: =HAVERQ!J133-HAVERQ!J$128 -> -1860 | BT17: =HAVERQ!K133-HAVERQ!K$128 -> -568 | BU17: =(HAVERQ!L133+HAVERQ!M133)-(HAVERQ!L$128+HAVERQ!M$128) -> -4822 | BV17: =HAVERQ!N133-HAVERQ!N$128 -> -55 | BW17: =HAVERQ!B133-HAVERQ!B$128 -> -8166 | BY17: 2022 | BZ17: =100*((HAVERQ!I137-HAVERQ!I$128)/HAVERQ!$B$128) -> 0.6226409 | CA17: =100*((HAVERQ!J137-HAVERQ!J$128)/HAVERQ!$B$128) -> -4.7504597 | CB17: =100*((HAVERQ!K137-HAVERQ!K$128)/HAVERQ!$B$128) -> -1.0194535 | CC17: =100*(((HAVERQ!L137+HAVERQ!M137)-(HAVERQ!L$128+HAVERQ!M$128))/HAVERQ!$B$128) -> -1.575959 | CD17: =CE17-BZ17-CA17-CB17-CC17 -> 1.7372649 | CE17: =100*((HAVERQ!B137-HAVERQ!B$128)/HAVERQ!B$128) -> -4.9859664 | CG17: 2021 | CH17: =HAVERQ!I133 -> 9030 | CI17: =HAVERQ!J133 -> 7754 | CJ17: =HAVERQ!K133 -> 2666 | CK17: =HAVERQ!L133+HAVERQ!M133 -> 34794 | CL17: =HAVERQ!N133 -> 1303 | CN17: 2021 | CO17: =CX17 -> -135 | CP17: =CY17 -> -849 | CQ17: =CZ17 -> -1564 | CR17: =DA17 -> -2254 | CS17: =DC17 -> -982 | CT17: =+DB17+DD17+DE17+DF17 -> -1219 | CU17: =DG17 -> -4822 | CW17: 2021 | CX17: =HAVERQ!L133-HAVERQ!L$128 -> -135 | CY17: =HAVERQ!O133-HAVERQ!O$128 -> -849 | CZ17: =HAVERQ!P133-HAVERQ!P$128 -> -1564 | DA17: =HAVERQ!Q133-HAVERQ!Q$128 -> -2254 | DB17: =HAVERQ!R133-HAVERQ!R$128 -> 108 | DC17: =HAVERQ!S133-HAVERQ!S$128 -> -982 | DD17: =HAVERQ!T133-HAVERQ!T$128 -> -328 | DE17: =HAVERQ!U133-HAVERQ!U$128 -> -193 | DF17: =HAVERQ!V133-HAVERQ!V$128 -> -806 | DG17: =(HAVERQ!L133+HAVERQ!M133)-(HAVERQ!L$128+HAVERQ!M$128) -> -4822 | DI17: 2021 | DJ17: =100*(HAVERQ!C133/HAVERQ!C$128) -> 94.354743 | DK17: =100*(HAVERQ!D133/HAVERQ!D$128) -> 77.131439 | DL17: =100*(HAVERQ!E133/HAVERQ!E$128) -> 96.054455 | DM17: =100*(HAVERQ!F133/HAVERQ!F$128) -> 103.01393 | DN17: =100*(HAVERQ!G133/HAVERQ!G$128) -> 90.798738 | DO17: =100*(HAVERQ!H133/HAVERQ!H$128) -> 92.916336 | DP17: 100 | DR17: 2021 | DS17: =HAVERQ!D133-HAVERQ!D$128 -> -1030 | DT17: =HAVERQ!E133-HAVERQ!E$128 -> -655 | DU17: =HAVERQ!F133-HAVERQ!F$128 -> 764 | DV17: =HAVERQ!G133-HAVERQ!G$128 -> -3411 | DW17: =HAVERQ!H133-HAVERQ!H$128 -> -1872 | DX17: =HAVERQ!C133-HAVERQ!C$128 -> -6192 | DZ17: 2003 | EA17: =MIN(EM17:EO17) -> -1.365324 | EB17: =+EF17-EA17 -> 1.7346723 | EC17: =100*((EJ21/EJ17)-1) -> 8.5101328 | ED17: 0 | EF17: =MAX(EM17:EO17) -> 0.36934837 | EG17: =AVERAGE(EM17:EO17) -> -0.36044752 | EI17: 2002 | EJ17: ='IPNR ex BNFL'!I25 -> 42091 | EM17: =(ER17-ER$2)/ER$3 -> 0.36934837 | EN17: =(ES17-ES$2)/ES$3 -> -1.365324 | EO17: =(ET17-ET$2)/ET$3 -> -0.085366978 | ER17: =(HAVERQ!W59*$EW$2)+(HAVERQ!X59*$EX$2)/($EW$2+$EX$2) -> 12.532801 | ES17: =(HAVERQ!AB59*$EW$2)+(HAVERQ!AC59*$EY$2)+(HAVERQ!AD59*$EZ$2)+(HAVERQ!AE59*$FA$2)/($EW$2+$EY$2+$EZ$2+$FA$2) -> -25.448384 | ET17: =(HAVERQ!Y59*$EW$2)+(HAVERQ!Z59*$EX$2)/($EW$2+$EX$2) -> 0.68853414 | FC17: 43831 | FD17: =100*((HAVERM!E248+HAVERM!F248)/(HAVERM!E$249+HAVERM!F$249)) -> 99.743658 | FE17: =100*(HAVERM!E248/HAVERM!E$249) -> 100.03859 | FF17: =100*(HAVERM!F248/HAVERM!F$249) -> 99.581828 | FG17: 100 | FV17: 42705 | FW17: =HAVERM!G211 -> 362472 | FY17: =FW17-FW16 -> 3457 | GC17: 2013 | GD17: =100*(DataQ!W167/DataQ!W$194) -> 80.548392 | GE17: =100*(DataQ!X167/DataQ!X$194) -> 79.348264 | GF17: =100*(DataQ!C167/DataQ!C$194) -> 78.296287 | GH17: 100 | GJ17: 2008 | GK17: =100*(DataQ!Z147/AVERAGE(DataQ!$Z$203:$Z$206)) -> 79.203914 | GL17: =100*(DataQ!C147/AVERAGE(DataQ!$C$203:$C$206)) -> 82.088816 | GM17: 100 | GO17: 2008 | GP17: =100*(DataQ!Z147/DataQ!$Z$194) -> 78.908418 | GQ17: =100*(DataQ!C147/DataQ!$C$194) -> 79.239926 | GR17: 100 | GT17: 2021 | GU17: =HB17 -> 86.827758 | GV17: =MIN(HC17:HH17) -> 92.798392 | GW17: =+GY17-GV17 -> 8.6609885 | GX17: 100 | GY17: =MAX(HC17:HH17) -> 101.45938 | HA17: 2021 | HB17: =100*(DataQ!C199/DataQ!C$194) -> 86.827758 | HC17: =100*(DataQ!Q199/DataQ!Q$194) -> 98.909201 | HD17: =100*(DataQ!R199/DataQ!R$194) -> 100.33765 | HE17: =100*(DataQ!S199/DataQ!S$194) -> 92.798392 | HF17: =100*(DataQ!T199/DataQ!T$194) -> 101.45938 | HG17: =100*(DataQ!U199/DataQ!U$194) -> 97.388412 | HH17: =100*(DataQ!V199/DataQ!V$194) -> 93.762142 | HJ17: 2021 | HK17: =HR17 -> 86.827758 | HL17: =MIN(HS17:HX17) -> 92.798392 | HM17: =+HO17-HL17 -> 8.6609885 | HN17: 100 | HO17: =MAX(HS17:HX17) -> 101.45938 | HQ17: 2021 | HR17: =100*(DataQ!C199/DataQ!C$194) -> 86.827758 | HS17: =100*(DataQ!Q199/DataQ!Q$194) -> 98.909201 | HT17: =100*(DataQ!R199/DataQ!R$194) -> 100.33765 | HU17: =100*(DataQ!S199/DataQ!S$194) -> 92.798392 | HV17: =100*(DataQ!T199/DataQ!T$194) -> 101.45938 | HW17: =100*(DataQ!U199/DataQ!U$194) -> 97.388412 | HX17: =100*(DataQ!V199/DataQ!V$194) -> 93.762142 | HZ17: 2002 | IA17: =DataA!J36/'Chart Data'!IF17 -> 2.4890828 | IB17: =IB16*(1+$ID$5/100) -> 2.3963188 | IC17: =100*((IA17/IB17)-1) -> 3.8711042 | IF17: =DataA!K36*DataA!L36 -> 903281.72 | IQ17: 2010 | IR17: =HAVERQ!AH88 -> -5.2 | IS17: =100*(('IPNR ex BNFL'!I57/'IPNR ex BNFL'!I53)-1) -> -3.8034277 | IT17: 0
B18: =100*((DataQ!C88/DataQ!C84)-1) -> -5.6060054 | C18: =K18 -> 12.803698 | D18: 0 | G18: =100*((AVERAGE(DataQ!C85:C88)/AVERAGE(DataQ!C81:C84))-1) -> -3.8526262 | H18: =AVERAGE(K15:K18) -> 13.524693 | I18: 0 | K18: =L18 -> 12.803698 | L18: =100*(HAVERQ!AF22/HAVERQ!AI22) -> 12.803698 | O18: =100*('ONS CVM_SA_(Quarterly)'!B102/'ONS CVM_SA_(Quarterly)'!B$101) -> 107.72646 | P18: =100*('ONS CVM_SA_(Quarterly)'!D102/'ONS CVM_SA_(Quarterly)'!D$101) -> 100.82557 | Q18: 1000 | R18: 100 | U18: ='ONS CVM_SA_(Quarterly)'!C114-'ONS CVM_SA_(Quarterly)'!C$101 -> 5229 | V18: ='ONS CVM_SA_(Quarterly)'!D114-'ONS CVM_SA_(Quarterly)'!D$101 -> 983 | W18: ='ONS CVM_SA_(Quarterly)'!E114-'ONS CVM_SA_(Quarterly)'!E$101 -> 1598 | X18: ='ONS CVM_SA_(Quarterly)'!F114-'ONS CVM_SA_(Quarterly)'!F$101 -> 370 | Y18: ='ONS CVM_SA_(Quarterly)'!B114-'ONS CVM_SA_(Quarterly)'!B$101 -> 8422 | AB18: =100*(U18/'ONS CVM_SA_(Quarterly)'!$B$101) -> 9.7142751 | AC18: =100*(V18/'ONS CVM_SA_(Quarterly)'!$B$101) -> 1.8261871 | AD18: =100*(W18/'ONS CVM_SA_(Quarterly)'!$B$101) -> 2.9687152 | AE18: =100*(X18/'ONS CVM_SA_(Quarterly)'!$B$101) -> 0.6873746 | AF18: =100*(('ONS CVM_SA_(Quarterly)'!B114/'ONS CVM_SA_(Quarterly)'!B$101)-1) -> 15.646132 | AI18: =100*(('ONS CVM_SA_(Quarterly)'!C106-'ONS CVM_SA_(Quarterly)'!C$96)/'ONS CVM_SA_(Quarterly)'!$B$96) -> 3.2825757 | AJ18: =100*(('ONS CVM_SA_(Quarterly)'!D106-'ONS CVM_SA_(Quarterly)'!D$96)/'ONS CVM_SA_(Quarterly)'!$B$96) -> 2.0453592 | AK18: =100*(('ONS CVM_SA_(Quarterly)'!E106-'ONS CVM_SA_(Quarterly)'!E$96)/'ONS CVM_SA_(Quarterly)'!$B$96) -> -5.5569894 | AL18: =100*(('ONS CVM_SA_(Quarterly)'!F106-'ONS CVM_SA_(Quarterly)'!F$96)/'ONS CVM_SA_(Quarterly)'!$B$96) -> -2.1050424 | AM18: =100*(('ONS CVM_SA_(Quarterly)'!B106-'ONS CVM_SA_(Quarterly)'!B$96)/'ONS CVM_SA_(Quarterly)'!$B$96) -> -2.6809046 | AP18: =100*(('ONS CVM_SA_(Quarterly)'!C94-AVERAGE('ONS CVM_SA_(Quarterly)'!C$81:C$84))/AVERAGE('ONS CVM_SA_(Quarterly)'!$B$81:$B$84)) -> -1.9943031 | AQ18: =100*(('ONS CVM_SA_(Quarterly)'!D94-AVERAGE('ONS CVM_SA_(Quarterly)'!D$81:D$84))/AVERAGE('ONS CVM_SA_(Quarterly)'!$B$81:$B$84)) -> -0.37965503 | AR18: =100*(('ONS CVM_SA_(Quarterly)'!E94-AVERAGE('ONS CVM_SA_(Quarterly)'!E$81:E$84))/AVERAGE('ONS CVM_SA_(Quarterly)'!$B$81:$B$84)) -> 1.6332865 | AS18: =100*(('ONS CVM_SA_(Quarterly)'!F94-AVERAGE('ONS CVM_SA_(Quarterly)'!F$81:F$84))/AVERAGE('ONS CVM_SA_(Quarterly)'!$B$81:$B$84)) -> 2.8711158 | AT18: =100*(('ONS CVM_SA_(Quarterly)'!B94-AVERAGE('ONS CVM_SA_(Quarterly)'!B$81:B$84))/AVERAGE('ONS CVM_SA_(Quarterly)'!$B$81:$B$84)) -> 0.77835359 | AV18: 43862 | AW18: =HAVERM!D249 -> 0.75 | AX18: =HAVERM!B249 -> 3.3 | AY18: =HAVERM!C249 -> 2.37 | BA18: 44927 | BB18: =AX53-AX$39 -> 2.6 | BC18: =AY53-AY$39 -> 0.53 | BD18: 1000 | BF18: 0 | BJ18: =100*(HAVERQ!B134/HAVERQ!B$128) -> 93.536471 | BK18: =100*(HAVERQ!I134/HAVERQ!I$128) -> 100.52485 | BL18: =100*(HAVERQ!J134/HAVERQ!J$128) -> 83.75286 | BM18: =100*(HAVERQ!K134/HAVERQ!K$128) -> 74.118738 | BN18: =100*((HAVERQ!L134+HAVERQ!M134)/(HAVERQ!L$128+HAVERQ!M$128)) -> 88.365812 | BO18: 100 | BR18: =HAVERQ!I134-HAVERQ!I$128 -> 49 | BS18: =HAVERQ!J134-HAVERQ!J$128 -> -1562 | BT18: =HAVERQ!K134-HAVERQ!K$128 -> -837 | BU18: =(HAVERQ!L134+HAVERQ!M134)-(HAVERQ!L$128+HAVERQ!M$128) -> -4609 | BV18: =HAVERQ!N134-HAVERQ!N$128 -> -57 | BW18: =HAVERQ!B134-HAVERQ!B$128 -> -4007 | BZ18: =100*((HAVERQ!I138-HAVERQ!I$128)/HAVERQ!$B$128) -> 1.5082105 | CA18: =100*((HAVERQ!J138-HAVERQ!J$128)/HAVERQ!$B$128) -> -3.0825564 | CB18: =100*((HAVERQ!K138-HAVERQ!K$128)/HAVERQ!$B$128) -> -1.1646288 | CC18: =100*(((HAVERQ!L138+HAVERQ!M138)-(HAVERQ!L$128+HAVERQ!M$128))/HAVERQ!$B$128) -> -1.7614608 | CD18: =CE18-BZ18-CA18-CB18-CC18 -> 1.8195309 | CE18: =100*((HAVERQ!B138-HAVERQ!B$128)/HAVERQ!B$128) -> -2.6809046 | CH18: =HAVERQ!I134 -> 9385 | CI18: =HAVERQ!J134 -> 8052 | CJ18: =HAVERQ!K134 -> 2397 | CK18: =HAVERQ!L134+HAVERQ!M134 -> 35007 | CL18: =HAVERQ!N134 -> 1301 | CO18: =CX18 -> 334 | CP18: =CY18 -> -538 | CQ18: =CZ18 -> -1446 | CR18: =DA18 -> -811 | CS18: =DC18 -> -493 | CT18: =+DB18+DD18+DE18+DF18 -> -560 | CU18: =DG18 -> -4609 | CX18: =HAVERQ!L134-HAVERQ!L$128 -> 334 | CY18: =HAVERQ!O134-HAVERQ!O$128 -> -538 | CZ18: =HAVERQ!P134-HAVERQ!P$128 -> -1446 | DA18: =HAVERQ!Q134-HAVERQ!Q$128 -> -811 | DB18: =HAVERQ!R134-HAVERQ!R$128 -> 557 | DC18: =HAVERQ!S134-HAVERQ!S$128 -> -493 | DD18: =HAVERQ!T134-HAVERQ!T$128 -> -270 | DE18: =HAVERQ!U134-HAVERQ!U$128 -> -136 | DF18: =HAVERQ!V134-HAVERQ!V$128 -> -711 | DG18: =(HAVERQ!L134+HAVERQ!M134)-(HAVERQ!L$128+HAVERQ!M$128) -> -4609 | DJ18: =100*(HAVERQ!C134/HAVERQ!C$128) -> 99.010804 | DK18: =100*(HAVERQ!D134/HAVERQ!D$128) -> 76.198934 | DL18: =100*(HAVERQ!E134/HAVERQ!E$128) -> 102.75887 | DM18: =100*(HAVERQ!F134/HAVERQ!F$128) -> 101.45962 | DN18: =100*(HAVERQ!G134/HAVERQ!G$128) -> 95.211891 | DO18: =100*(HAVERQ!H134/HAVERQ!H$128) -> 103.2883 | DP18: 100 | DS18: =HAVERQ!D134-HAVERQ!D$128 -> -1072 | DT18: =HAVERQ!E134-HAVERQ!E$128 -> 458 | DU18: =HAVERQ!F134-HAVERQ!F$128 -> 370 | DV18: =HAVERQ!G134-HAVERQ!G$128 -> -1775 | DW18: =HAVERQ!H134-HAVERQ!H$128 -> 869 | DX18: =HAVERQ!C134-HAVERQ!C$128 -> -1085 | EA18: =MIN(EM18:EO18) -> -0.4253075 | EB18: =+EF18-EA18 -> 0.76808231 | EC18: =100*((EJ22/EJ18)-1) -> -0.80393569 | ED18: 0 | EF18: =MAX(EM18:EO18) -> 0.3427748 | EG18: =AVERAGE(EM18:EO18) -> -0.09731296 | EJ18: ='IPNR ex BNFL'!I26 -> 41670 | EM18: =(ER18-ER$2)/ER$3 -> 0.3427748 | EN18: =(ES18-ES$2)/ES$3 -> -0.4253075 | EO18: =(ET18-ET$2)/ET$3 -> -0.20940618 | ER18: =(HAVERQ!W60*$EW$2)+(HAVERQ!X60*$EX$2)/($EW$2+$EX$2) -> 12.221335 | ES18: =(HAVERQ!AB60*$EW$2)+(HAVERQ!AC60*$EY$2)+(HAVERQ!AD60*$EZ$2)+(HAVERQ!AE60*$FA$2)/($EW$2+$EY$2+$EZ$2+$FA$2) -> -12.220656 | ET18: =(HAVERQ!Y60*$EW$2)+(HAVERQ!Z60*$EX$2)/($EW$2+$EX$2) -> 0.49372523 | FC18: 43862 | FD18: =100*((HAVERM!E249+HAVERM!F249)/(HAVERM!E$249+HAVERM!F$249)) -> 100 | FE18: =100*(HAVERM!E249/HAVERM!E$249) -> 100 | FF18: =100*(HAVERM!F249/HAVERM!F$249) -> 100 | FG18: 100 | FV18: 42736 | FW18: =HAVERM!G212 -> 364162 | FY18: =FW18-FW17 -> 1690 | GD18: =100*(DataQ!W168/DataQ!W$194) -> 82.705542 | GE18: =100*(DataQ!X168/DataQ!X$194) -> 81.600615 | GF18: =100*(DataQ!C168/DataQ!C$194) -> 79.862567 | GH18: 100 | GK18: =100*(DataQ!Z148/AVERAGE(DataQ!$Z$203:$Z$206)) -> 82.21026 | GL18: =100*(DataQ!C148/AVERAGE(DataQ!$C$203:$C$206)) -> 85.207002 | GM18: 100 | GP18: =100*(DataQ!Z148/DataQ!$Z$194) -> 81.903548 | GQ18: =100*(DataQ!C148/DataQ!$C$194) -> 82.249895 | GR18: 100 | GU18: =HB18 -> 93.536471 | GV18: =MIN(HC18:HH18) -> 94.754158 | GW18: =+GY18-GV18 -> 8.3803612 | GX18: 100 | GY18: =MAX(HC18:HH18) -> 103.13452 | HB18: =100*(DataQ!C200/DataQ!C$194) -> 93.536471 | HC18: =100*(DataQ!Q200/DataQ!Q$194) -> 101.04703 | HD18: =100*(DataQ!R200/DataQ!R$194) -> 102.43509 | HE18: =100*(DataQ!S200/DataQ!S$194) -> 94.754158 | HF18: =100*(DataQ!T200/DataQ!T$194) -> 103.13452 | HG18: =100*(DataQ!U200/DataQ!U$194) -> 98.330493 | HH18: =100*(DataQ!V200/DataQ!V$194) -> 99.235582 | HK18: =HR18 -> 93.536471 | HL18: =MIN(HS18:HX18) -> 94.754158 | HM18: =+HO18-HL18 -> 8.3803612 | HN18: 100 | HO18: =MAX(HS18:HX18) -> 103.13452 | HR18: =100*(DataQ!C200/DataQ!C$194) -> 93.536471 | HS18: =100*(DataQ!Q200/DataQ!Q$194) -> 101.04703 | HT18: =100*(DataQ!R200/DataQ!R$194) -> 102.43509 | HU18: =100*(DataQ!S200/DataQ!S$194) -> 94.754158 | HV18: =100*(DataQ!T200/DataQ!T$194) -> 103.13452 | HW18: =100*(DataQ!U200/DataQ!U$194) -> 98.330493 | HX18: =100*(DataQ!V200/DataQ!V$194) -> 99.235582 | HZ18: 2003 | IA18: =DataA!J37/'Chart Data'!IF18 -> 2.5367095 | IB18: =IB17*(1+$ID$5/100) -> 2.4599787 | IC18: =100*((IA18/IB18)-1) -> 3.1191651 | IF18: =DataA!K37*DataA!L37 -> 907313.19 | IR18: =HAVERQ!AH89 -> -0.7 | IS18: =100*(('IPNR ex BNFL'!I58/'IPNR ex BNFL'!I54)-1) -> -0.046480906 | IT18: 0
B19: =100*((DataQ!C89/DataQ!C85)-1) -> -5.3681002 | C19: =K19 -> 12.961493 | D19: 0 | G19: =100*((AVERAGE(DataQ!C86:C89)/AVERAGE(DataQ!C82:C85))-1) -> -5.353561 | H19: =AVERAGE(K16:K19) -> 13.067093 | I19: 0 | K19: =L19 -> 12.961493 | L19: =100*(HAVERQ!AF23/HAVERQ!AI23) -> 12.961493 | O19: =100*('ONS CVM_SA_(Quarterly)'!B103/'ONS CVM_SA_(Quarterly)'!B$101) -> 105.88913 | P19: =100*('ONS CVM_SA_(Quarterly)'!D103/'ONS CVM_SA_(Quarterly)'!D$101) -> 105.23132 | Q19: 1000 | R19: 100 | AI19: =100*(('ONS CVM_SA_(Quarterly)'!C107-'ONS CVM_SA_(Quarterly)'!C$96)/'ONS CVM_SA_(Quarterly)'!$B$96) -> 3.0938478 | AJ19: =100*(('ONS CVM_SA_(Quarterly)'!D107-'ONS CVM_SA_(Quarterly)'!D$96)/'ONS CVM_SA_(Quarterly)'!$B$96) -> 2.5083073 | AK19: =100*(('ONS CVM_SA_(Quarterly)'!E107-'ONS CVM_SA_(Quarterly)'!E$96)/'ONS CVM_SA_(Quarterly)'!$B$96) -> -5.5118237 | AL19: =100*(('ONS CVM_SA_(Quarterly)'!F107-'ONS CVM_SA_(Quarterly)'!F$96)/'ONS CVM_SA_(Quarterly)'!$B$96) -> -1.5291802 | AM19: =100*(('ONS CVM_SA_(Quarterly)'!B107-'ONS CVM_SA_(Quarterly)'!B$96)/'ONS CVM_SA_(Quarterly)'!$B$96) -> -1.7856567 | AP19: =100*(('ONS CVM_SA_(Quarterly)'!C95-AVERAGE('ONS CVM_SA_(Quarterly)'!C$81:C$84))/AVERAGE('ONS CVM_SA_(Quarterly)'!$B$81:$B$84)) -> -2.9537728 | AQ19: =100*(('ONS CVM_SA_(Quarterly)'!D95-AVERAGE('ONS CVM_SA_(Quarterly)'!D$81:D$84))/AVERAGE('ONS CVM_SA_(Quarterly)'!$B$81:$B$84)) -> -1.2613299 | AR19: =100*(('ONS CVM_SA_(Quarterly)'!E95-AVERAGE('ONS CVM_SA_(Quarterly)'!E$81:E$84))/AVERAGE('ONS CVM_SA_(Quarterly)'!$B$81:$B$84)) -> 0.62195354 | AS19: =100*(('ONS CVM_SA_(Quarterly)'!F95-AVERAGE('ONS CVM_SA_(Quarterly)'!F$81:F$84))/AVERAGE('ONS CVM_SA_(Quarterly)'!$B$81:$B$84)) -> 3.597201 | AT19: =100*(('ONS CVM_SA_(Quarterly)'!B95-AVERAGE('ONS CVM_SA_(Quarterly)'!B$81:B$84))/AVERAGE('ONS CVM_SA_(Quarterly)'!$B$81:$B$84)) -> 0.37479285 | AV19: 43891 | AW19: =HAVERM!D250 -> 0.34772727 | AX19: =HAVERM!B250 -> 3.21 | AY19: =HAVERM!C250 -> 2.33 | BA19: 44958 | BB19: =AX54-AX$39 -> 2.95 | BC19: =AY54-AY$39 -> 0.63 | BD19: 1000 | BF19: 0 | BJ19: =100*(HAVERQ!B135/HAVERQ!B$128) -> 91.941156 | BK19: =100*(HAVERQ!I135/HAVERQ!I$128) -> 102.52785 | BL19: =100*(HAVERQ!J135/HAVERQ!J$128) -> 82.109424 | BM19: =100*(HAVERQ!K135/HAVERQ!K$128) -> 80.055659 | BN19: =100*((HAVERQ!L135+HAVERQ!M135)/(HAVERQ!L$128+HAVERQ!M$128)) -> 90.594709 | BO19: 100 | BR19: =HAVERQ!I135-HAVERQ!I$128 -> 236 | BS19: =HAVERQ!J135-HAVERQ!J$128 -> -1720 | BT19: =HAVERQ!K135-HAVERQ!K$128 -> -645 | BU19: =(HAVERQ!L135+HAVERQ!M135)-(HAVERQ!L$128+HAVERQ!M$128) -> -3726 | BV19: =HAVERQ!N135-HAVERQ!N$128 -> -41 | BW19: =HAVERQ!B135-HAVERQ!B$128 -> -4996 | BZ19: =100*((HAVERQ!I139-HAVERQ!I$128)/HAVERQ!$B$128) -> 1.2823822 | CA19: =100*((HAVERQ!J139-HAVERQ!J$128)/HAVERQ!$B$128) -> -2.0695551 | CB19: =100*((HAVERQ!K139-HAVERQ!K$128)/HAVERQ!$B$128) -> -0.57586218 | CC19: =100*(((HAVERQ!L139+HAVERQ!M139)-(HAVERQ!L$128+HAVERQ!M$128))/HAVERQ!$B$128) -> -2.2776398 | CD19: =CE19-BZ19-CA19-CB19-CC19 -> 1.8550182 | CE19: =100*((HAVERQ!B139-HAVERQ!B$128)/HAVERQ!B$128) -> -1.7856567 | CH19: =HAVERQ!I135 -> 9572 | CI19: =HAVERQ!J135 -> 7894 | CJ19: =HAVERQ!K135 -> 2589 | CK19: =HAVERQ!L135+HAVERQ!M135 -> 35890 | CL19: =HAVERQ!N135 -> 1317 | CO19: =CX19 -> 601 | CP19: =CY19 -> -569 | CQ19: =CZ19 -> -1237 | CR19: =DA19 -> -585 | CS19: =DC19 -> -323 | CT19: =+DB19+DD19+DE19+DF19 -> -473 | CU19: =DG19 -> -3726 | CX19: =HAVERQ!L135-HAVERQ!L$128 -> 601 | CY19: =HAVERQ!O135-HAVERQ!O$128 -> -569 | CZ19: =HAVERQ!P135-HAVERQ!P$128 -> -1237 | DA19: =HAVERQ!Q135-HAVERQ!Q$128 -> -585 | DB19: =HAVERQ!R135-HAVERQ!R$128 -> 467 | DC19: =HAVERQ!S135-HAVERQ!S$128 -> -323 | DD19: =HAVERQ!T135-HAVERQ!T$128 -> -256 | DE19: =HAVERQ!U135-HAVERQ!U$128 -> -164 | DF19: =HAVERQ!V135-HAVERQ!V$128 -> -520 | DG19: =(HAVERQ!L135+HAVERQ!M135)-(HAVERQ!L$128+HAVERQ!M$128) -> -3726 | DJ19: =100*(HAVERQ!C135/HAVERQ!C$128) -> 98.629712 | DK19: =100*(HAVERQ!D135/HAVERQ!D$128) -> 93.983126 | DL19: =100*(HAVERQ!E135/HAVERQ!E$128) -> 106.73453 | DM19: =100*(HAVERQ!F135/HAVERQ!F$128) -> 101.79494 | DN19: =100*(HAVERQ!G135/HAVERQ!G$128) -> 93.749831 | DO19: =100*(HAVERQ!H135/HAVERQ!H$128) -> 97.763651 | DP19: 100 | DS19: =HAVERQ!D135-HAVERQ!D$128 -> -271 | DT19: =HAVERQ!E135-HAVERQ!E$128 -> 1118 | DU19: =HAVERQ!F135-HAVERQ!F$128 -> 455 | DV19: =HAVERQ!G135-HAVERQ!G$128 -> -2317 | DW19: =HAVERQ!H135-HAVERQ!H$128 -> -591 | DX19: =HAVERQ!C135-HAVERQ!C$128 -> -1503 | EA19: =MIN(EM19:EO19) -> -0.45725569 | EB19: =+EF19-EA19 -> 0.076143915 | EC19: =100*((EJ23/EJ19)-1) -> -3.6258587 | ED19: 0 | EF19: =MAX(EM19:EO19) -> -0.38111177 | EG19: =AVERAGE(EM19:EO19) -> -0.41109186 | EJ19: ='IPNR ex BNFL'!I27 -> 43962 | EL19: 2003 | EM19: =(ER19-ER$2)/ER$3 -> -0.45725569 | EN19: =(ES19-ES$2)/ES$3 -> -0.39490811 | EO19: =(ET19-ET$2)/ET$3 -> -0.38111177 | EQ19: 2003 | ER19: =(HAVERQ!W61*$EW$2)+(HAVERQ!X61*$EX$2)/($EW$2+$EX$2) -> 2.8442671 | ES19: =(HAVERQ!AB61*$EW$2)+(HAVERQ!AC61*$EY$2)+(HAVERQ!AD61*$EZ$2)+(HAVERQ!AE61*$FA$2)/($EW$2+$EY$2+$EZ$2+$FA$2) -> -11.792882 | ET19: =(HAVERQ!Y61*$EW$2)+(HAVERQ!Z61*$EX$2)/($EW$2+$EX$2) -> 0.22405422 | FC19: 43891 | FD19: =100*((HAVERM!E250+HAVERM!F250)/(HAVERM!E$249+HAVERM!F$249)) -> 107.71466 | FE19: =100*(HAVERM!E250/HAVERM!E$249) -> 101.4271 | FF19: =100*(HAVERM!F250/HAVERM!F$249) -> 111.16467 | FG19: 100 | FV19: 42767 | FW19: =HAVERM!G213 -> 366516 | FY19: =FW19-FW18 -> 2354 | GD19: =100*(DataQ!W169/DataQ!W$194) -> 84.461503 | GE19: =100*(DataQ!X169/DataQ!X$194) -> 83.2327 | GF19: =100*(DataQ!C169/DataQ!C$194) -> 82.657999 | GH19: 100 | GK19: =100*(DataQ!Z149/AVERAGE(DataQ!$Z$203:$Z$206)) -> 79.097045 | GL19: =100*(DataQ!C149/AVERAGE(DataQ!$C$203:$C$206)) -> 81.968501 | GM19: 100 | GP19: =100*(DataQ!Z149/DataQ!$Z$194) -> 78.801948 | GQ19: =100*(DataQ!C149/DataQ!$C$194) -> 79.123786 | GR19: 100 | GU19: =HB19 -> 91.941156 | GV19: =MIN(HC19:HH19) -> 91.957595 | GW19: =+GY19-GV19 -> 10.558214 | GX19: 100 | GY19: =MAX(HC19:HH19) -> 102.51581 | HB19: =100*(DataQ!C201/DataQ!C$194) -> 91.941156 | HC19: =100*(DataQ!Q201/DataQ!Q$194) -> 100.60263 | HD19: =100*(DataQ!R201/DataQ!R$194) -> 100.98803 | HE19: =100*(DataQ!S201/DataQ!S$194) -> 91.957595 | HF19: =100*(DataQ!T201/DataQ!T$194) -> 102.51581 | HG19: =100*(DataQ!U201/DataQ!U$194) -> 100.32298 | HH19: =100*(DataQ!V201/DataQ!V$194) -> 99.816429 | HK19: =HR19 -> 91.941156 | HL19: =MIN(HS19:HX19) -> 91.957595 | HM19: =+HO19-HL19 -> 10.558214 | HN19: 100 | HO19: =MAX(HS19:HX19) -> 102.51581 | HR19: =100*(DataQ!C201/DataQ!C$194) -> 91.941156 | HS19: =100*(DataQ!Q201/DataQ!Q$194) -> 100.60263 | HT19: =100*(DataQ!R201/DataQ!R$194) -> 100.98803 | HU19: =100*(DataQ!S201/DataQ!S$194) -> 91.957595 | HV19: =100*(DataQ!T201/DataQ!T$194) -> 102.51581 | HW19: =100*(DataQ!U201/DataQ!U$194) -> 100.32298 | HX19: =100*(DataQ!V201/DataQ!V$194) -> 99.816429 | HZ19: 2004 | IA19: =DataA!J38/'Chart Data'!IF19 -> 2.5780621 | IB19: =IB18*(1+$ID$5/100) -> 2.5253298 | IC19: =100*((IA19/IB19)-1) -> 2.0881359 | IF19: =DataA!K38*DataA!L38 -> 915099.75 | IR19: =HAVERQ!AH90 -> 0.7 | IS19: =100*(('IPNR ex BNFL'!I59/'IPNR ex BNFL'!I55)-1) -> 6.8012407 | IT19: 0
B20: =100*((DataQ!C90/DataQ!C86)-1) -> 0.98959788 | C20: =K20 -> 12.12648 | D20: 0 | G20: =100*((AVERAGE(DataQ!C87:C90)/AVERAGE(DataQ!C83:C86))-1) -> -3.6320611 | H20: =AVERAGE(K17:K20) -> 12.651824 | I20: 0 | K20: =L20 -> 12.12648 | L20: =100*(HAVERQ!AF24/HAVERQ!AI24) -> 12.12648 | O20: =100*('ONS CVM_SA_(Quarterly)'!B104/'ONS CVM_SA_(Quarterly)'!B$101) -> 106.22353 | P20: =100*('ONS CVM_SA_(Quarterly)'!D104/'ONS CVM_SA_(Quarterly)'!D$101) -> 100.76018 | Q20: 1000 | R20: 100 | AI20: =100*(('ONS CVM_SA_(Quarterly)'!C108-'ONS CVM_SA_(Quarterly)'!C$96)/'ONS CVM_SA_(Quarterly)'!$B$96) -> 4.0600703 | AJ20: =100*(('ONS CVM_SA_(Quarterly)'!D108-'ONS CVM_SA_(Quarterly)'!D$96)/'ONS CVM_SA_(Quarterly)'!$B$96) -> 0.73232894 | AK20: =100*(('ONS CVM_SA_(Quarterly)'!E108-'ONS CVM_SA_(Quarterly)'!E$96)/'ONS CVM_SA_(Quarterly)'!$B$96) -> -7.015195 | AL20: =100*(('ONS CVM_SA_(Quarterly)'!F108-'ONS CVM_SA_(Quarterly)'!F$96)/'ONS CVM_SA_(Quarterly)'!$B$96) -> -1.8598574 | AM20: =100*(('ONS CVM_SA_(Quarterly)'!B108-'ONS CVM_SA_(Quarterly)'!B$96)/'ONS CVM_SA_(Quarterly)'!$B$96) -> -4.4294609 | AP20: =100*(('ONS CVM_SA_(Quarterly)'!C96-AVERAGE('ONS CVM_SA_(Quarterly)'!C$81:C$84))/AVERAGE('ONS CVM_SA_(Quarterly)'!$B$81:$B$84)) -> -4.1644551 | AQ20: =100*(('ONS CVM_SA_(Quarterly)'!D96-AVERAGE('ONS CVM_SA_(Quarterly)'!D$81:D$84))/AVERAGE('ONS CVM_SA_(Quarterly)'!$B$81:$B$84)) -> -1.2986066 | AR20: =100*(('ONS CVM_SA_(Quarterly)'!E96-AVERAGE('ONS CVM_SA_(Quarterly)'!E$81:E$84))/AVERAGE('ONS CVM_SA_(Quarterly)'!$B$81:$B$84)) -> 1.4436615 | AS20: =100*(('ONS CVM_SA_(Quarterly)'!F96-AVERAGE('ONS CVM_SA_(Quarterly)'!F$81:F$84))/AVERAGE('ONS CVM_SA_(Quarterly)'!$B$81:$B$84)) -> 3.9602436 | AT20: =100*(('ONS CVM_SA_(Quarterly)'!B96-AVERAGE('ONS CVM_SA_(Quarterly)'!B$81:B$84))/AVERAGE('ONS CVM_SA_(Quarterly)'!$B$81:$B$84)) -> 0.47527785 | AV20: 43922 | AW20: =HAVERM!D251 -> 0.1 | AX20: =HAVERM!B251 -> 2.98 | AY20: =HAVERM!C251 -> 2.21 | BA20: 44986 | BB20: =AX55-AX$39 -> 3.09 | BC20: =AY55-AY$39 -> 0.73 | BD20: 1000 | BF20: 0 | BJ20: =100*(HAVERQ!B136/HAVERQ!B$128) -> 92.231506 | BK20: =100*(HAVERQ!I136/HAVERQ!I$128) -> 104.33805 | BL20: =100*(HAVERQ!J136/HAVERQ!J$128) -> 82.931142 | BM20: =100*(HAVERQ!K136/HAVERQ!K$128) -> 69.727891 | BN20: =100*((HAVERQ!L136+HAVERQ!M136)/(HAVERQ!L$128+HAVERQ!M$128)) -> 90.458401 | BO20: 100 | BR20: =HAVERQ!I136-HAVERQ!I$128 -> 405 | BS20: =HAVERQ!J136-HAVERQ!J$128 -> -1641 | BT20: =HAVERQ!K136-HAVERQ!K$128 -> -979 | BU20: =(HAVERQ!L136+HAVERQ!M136)-(HAVERQ!L$128+HAVERQ!M$128) -> -3780 | BV20: =HAVERQ!N136-HAVERQ!N$128 -> -78 | BW20: =HAVERQ!B136-HAVERQ!B$128 -> -4816 | BZ20: =100*((HAVERQ!I140-HAVERQ!I$128)/HAVERQ!$B$128) -> 1.2597993 | CA20: =100*((HAVERQ!J140-HAVERQ!J$128)/HAVERQ!$B$128) -> -2.0872988 | CB20: =100*((HAVERQ!K140-HAVERQ!K$128)/HAVERQ!$B$128) -> -0.55166629 | CC20: =100*(((HAVERQ!L140+HAVERQ!M140)-(HAVERQ!L$128+HAVERQ!M$128))/HAVERQ!$B$128) -> -4.9311224 | CD20: =CE20-BZ20-CA20-CB20-CC20 -> 1.8808272 | CE20: =100*((HAVERQ!B140-HAVERQ!B$128)/HAVERQ!B$128) -> -4.4294609 | CH20: =HAVERQ!I136 -> 9741 | CI20: =HAVERQ!J136 -> 7973 | CJ20: =HAVERQ!K136 -> 2255 | CK20: =HAVERQ!L136+HAVERQ!M136 -> 35836 | CL20: =HAVERQ!N136 -> 1280 | CO20: =CX20 -> 551 | CP20: =CY20 -> -314 | CQ20: =CZ20 -> -1364 | CR20: =DA20 -> 980 | CS20: =DC20 -> -587 | CT20: =+DB20+DD20+DE20+DF20 -> -172 | CU20: =DG20 -> -3780 | CX20: =HAVERQ!L136-HAVERQ!L$128 -> 551 | CY20: =HAVERQ!O136-HAVERQ!O$128 -> -314 | CZ20: =HAVERQ!P136-HAVERQ!P$128 -> -1364 | DA20: =HAVERQ!Q136-HAVERQ!Q$128 -> 980 | DB20: =HAVERQ!R136-HAVERQ!R$128 -> 946 | DC20: =HAVERQ!S136-HAVERQ!S$128 -> -587 | DD20: =HAVERQ!T136-HAVERQ!T$128 -> -225 | DE20: =HAVERQ!U136-HAVERQ!U$128 -> -184 | DF20: =HAVERQ!V136-HAVERQ!V$128 -> -709 | DG20: =(HAVERQ!L136+HAVERQ!M136)-(HAVERQ!L$128+HAVERQ!M$128) -> -3780 | DJ20: =100*(HAVERQ!C136/HAVERQ!C$128) -> 99.234171 | DK20: =100*(HAVERQ!D136/HAVERQ!D$128) -> 111.34547 | DL20: =100*(HAVERQ!E136/HAVERQ!E$128) -> 103.36727 | DM20: =100*(HAVERQ!F136/HAVERQ!F$128) -> 102.57209 | DN20: =100*(HAVERQ!G136/HAVERQ!G$128) -> 94.033072 | DO20: =100*(HAVERQ!H136/HAVERQ!H$128) -> 97.971771 | DP20: 100 | DS20: =HAVERQ!D136-HAVERQ!D$128 -> 511 | DT20: =HAVERQ!E136-HAVERQ!E$128 -> 559 | DU20: =HAVERQ!F136-HAVERQ!F$128 -> 652 | DV20: =HAVERQ!G136-HAVERQ!G$128 -> -2212 | DW20: =HAVERQ!H136-HAVERQ!H$128 -> -536 | DX20: =HAVERQ!C136-HAVERQ!C$128 -> -840 | EA20: =MIN(EM20:EO20) -> -1.0449715 | EB20: =+EF20-EA20 -> 1.0464752 | EC20: =100*((EJ24/EJ20)-1) -> -7.8871391 | ED20: 0 | EF20: =MAX(EM20:EO20) -> 0.0015037502 | EG20: =AVERAGE(EM20:EO20) -> -0.5014192 | EJ20: ='IPNR ex BNFL'!I28 -> 45720 | EM20: =(ER20-ER$2)/ER$3 -> 0.0015037502 | EN20: =(ES20-ES$2)/ES$3 -> -1.0449715 | EO20: =(ET20-ET$2)/ET$3 -> -0.46078988 | ER20: =(HAVERQ!W62*$EW$2)+(HAVERQ!X62*$EX$2)/($EW$2+$EX$2) -> 8.2213353 | ES20: =(HAVERQ!AB62*$EW$2)+(HAVERQ!AC62*$EY$2)+(HAVERQ!AD62*$EZ$2)+(HAVERQ!AE62*$FA$2)/($EW$2+$EY$2+$EZ$2+$FA$2) -> -20.940447 | ET20: =(HAVERQ!Y62*$EW$2)+(HAVERQ!Z62*$EX$2)/($EW$2+$EX$2) -> 0.098916331 | FC20: 43922 | FD20: =100*((HAVERM!E251+HAVERM!F251)/(HAVERM!E$249+HAVERM!F$249)) -> 110.9931 | FE20: =100*(HAVERM!E251/HAVERM!E$249) -> 102.26252 | FF20: =100*(HAVERM!F251/HAVERM!F$249) -> 115.78362 | FG20: 100 | FV20: 42795 | FW20: =HAVERM!G214 -> 372600 | FY20: =FW20-FW19 -> 6084 | GD20: =100*(DataQ!W170/DataQ!W$194) -> 84.310301 | GE20: =100*(DataQ!X170/DataQ!X$194) -> 83.307718 | GF20: =100*(DataQ!C170/DataQ!C$194) -> 82.327322 | GH20: 100 | GK20: =100*(DataQ!Z150/AVERAGE(DataQ!$Z$203:$Z$206)) -> 76.414809 | GL20: =100*(DataQ!C150/AVERAGE(DataQ!$C$203:$C$206)) -> 79.181184 | GM20: 100 | GP20: =100*(DataQ!Z150/DataQ!$Z$194) -> 76.129719 | GQ20: =100*(DataQ!C150/DataQ!$C$194) -> 76.433203 | GR20: 100 | GU20: =HB20 -> 92.231506 | GV20: =MIN(HC20:HH20) -> 92.71614 | GW20: =+GY20-GV20 -> 9.7210222 | GX20: 100 | GY20: =MAX(HC20:HH20) -> 102.43716 | HB20: =100*(DataQ!C202/DataQ!C$194) -> 92.231506 | HC20: =100*(DataQ!Q202/DataQ!Q$194) -> 101.44767 | HD20: =100*(DataQ!R202/DataQ!R$194) -> 101.29607 | HE20: =100*(DataQ!S202/DataQ!S$194) -> 92.71614 | HF20: =100*(DataQ!T202/DataQ!T$194) -> 101.94419 | HG20: =100*(DataQ!U202/DataQ!U$194) -> 102.43716 | HH20: =100*(DataQ!V202/DataQ!V$194) -> 102.40467 | HK20: =HR20 -> 92.231506 | HL20: =MIN(HS20:HX20) -> 92.71614 | HM20: =+HO20-HL20 -> 9.7210222 | HN20: 100 | HO20: =MAX(HS20:HX20) -> 102.43716 | HR20: =100*(DataQ!C202/DataQ!C$194) -> 92.231506 | HS20: =100*(DataQ!Q202/DataQ!Q$194) -> 101.44767 | HT20: =100*(DataQ!R202/DataQ!R$194) -> 101.29607 | HU20: =100*(DataQ!S202/DataQ!S$194) -> 92.71614 | HV20: =100*(DataQ!T202/DataQ!T$194) -> 101.94419 | HW20: =100*(DataQ!U202/DataQ!U$194) -> 102.43716 | HX20: =100*(DataQ!V202/DataQ!V$194) -> 102.40467 | HZ20: 2005 | IA20: =DataA!J39/'Chart Data'!IF20 -> 2.6071244 | IB20: =IB19*(1+$ID$5/100) -> 2.592417 | IC20: =100*((IA20/IB20)-1) -> 0.56732501 | IF20: =DataA!K39*DataA!L39 -> 928240.71 | IR20: =HAVERQ!AH91 -> 2.3 | IS20: =100*(('IPNR ex BNFL'!I60/'IPNR ex BNFL'!I56)-1) -> 14.884648 | IT20: 0
A21: 1994 | B21: =100*((DataQ!C91/DataQ!C87)-1) -> 0.5105591 | C21: =K21 -> 11.065532 | D21: 0 | F21: 1994 | G21: =100*((AVERAGE(DataQ!C88:C91)/AVERAGE(DataQ!C84:C87))-1) -> -2.4225625 | H21: =AVERAGE(K18:K21) -> 12.239301 | I21: 0 | K21: =L21 -> 11.065532 | L21: =100*(HAVERQ!AF25/HAVERQ!AI25) -> 11.065532 | N21: 2022 | O21: =100*('ONS CVM_SA_(Quarterly)'!B105/'ONS CVM_SA_(Quarterly)'!B$101) -> 109.42632 | P21: =100*('ONS CVM_SA_(Quarterly)'!D105/'ONS CVM_SA_(Quarterly)'!D$101) -> 111.33726 | Q21: 1000 | R21: 100 | AH21: 2023 | AI21: =100*(('ONS CVM_SA_(Quarterly)'!C109-'ONS CVM_SA_(Quarterly)'!C$96)/'ONS CVM_SA_(Quarterly)'!$B$96) -> 5.2005033 | AJ21: =100*(('ONS CVM_SA_(Quarterly)'!D109-'ONS CVM_SA_(Quarterly)'!D$96)/'ONS CVM_SA_(Quarterly)'!$B$96) -> 2.2260219 | AK21: =100*(('ONS CVM_SA_(Quarterly)'!E109-'ONS CVM_SA_(Quarterly)'!E$96)/'ONS CVM_SA_(Quarterly)'!$B$96) -> -5.0714585 | AL21: =100*(('ONS CVM_SA_(Quarterly)'!F109-'ONS CVM_SA_(Quarterly)'!F$96)/'ONS CVM_SA_(Quarterly)'!$B$96) -> -1.2210859 | AM21: =100*(('ONS CVM_SA_(Quarterly)'!B109-'ONS CVM_SA_(Quarterly)'!B$96)/'ONS CVM_SA_(Quarterly)'!$B$96) -> 0.78717295 | AO21: 2020 | AP21: =100*(('ONS CVM_SA_(Quarterly)'!C97-AVERAGE('ONS CVM_SA_(Quarterly)'!C$81:C$84))/AVERAGE('ONS CVM_SA_(Quarterly)'!$B$81:$B$84)) -> -3.4853709 | AQ21: =100*(('ONS CVM_SA_(Quarterly)'!D97-AVERAGE('ONS CVM_SA_(Quarterly)'!D$81:D$84))/AVERAGE('ONS CVM_SA_(Quarterly)'!$B$81:$B$84)) -> -1.3131931 | AR21: =100*(('ONS CVM_SA_(Quarterly)'!E97-AVERAGE('ONS CVM_SA_(Quarterly)'!E$81:E$84))/AVERAGE('ONS CVM_SA_(Quarterly)'!$B$81:$B$84)) -> -0.83507899 | AS21: =100*(('ONS CVM_SA_(Quarterly)'!F97-AVERAGE('ONS CVM_SA_(Quarterly)'!F$81:F$84))/AVERAGE('ONS CVM_SA_(Quarterly)'!$B$81:$B$84)) -> 4.318424 | AT21: =100*(('ONS CVM_SA_(Quarterly)'!B97-AVERAGE('ONS CVM_SA_(Quarterly)'!B$81:B$84))/AVERAGE('ONS CVM_SA_(Quarterly)'!$B$81:$B$84)) -> -1.7856347 | AV21: 43952 | AW21: =HAVERM!D252 -> 0.1 | AX21: =HAVERM!B252 -> 2.86 | AY21: =HAVERM!C252 -> 2.17 | BA21: 45017 | BB21: =AX56-AX$39 -> 3.21 | BC21: =AY56-AY$39 -> 0.74 | BD21: 1000 | BF21: 0 | BI21: 2022 | BJ21: =100*(HAVERQ!B137/HAVERQ!B$128) -> 95.014034 | BK21: =100*(HAVERQ!I137/HAVERQ!I$128) -> 104.13453 | BL21: =100*(HAVERQ!J137/HAVERQ!J$128) -> 69.367589 | BM21: =100*(HAVERQ!K137/HAVERQ!K$128) -> 80.457638 | BN21: =100*((HAVERQ!L137+HAVERQ!M137)/(HAVERQ!L$128+HAVERQ!M$128)) -> 97.533825 | BO21: 100 | BQ21: 2022 | BR21: =HAVERQ!I137-HAVERQ!I$128 -> 386 | BS21: =HAVERQ!J137-HAVERQ!J$128 -> -2945 | BT21: =HAVERQ!K137-HAVERQ!K$128 -> -632 | BU21: =(HAVERQ!L137+HAVERQ!M137)-(HAVERQ!L$128+HAVERQ!M$128) -> -977 | BV21: =HAVERQ!N137-HAVERQ!N$128 -> -88 | BW21: =HAVERQ!B137-HAVERQ!B$128 -> -3091 | BY21: 2023 | BZ21: =100*((HAVERQ!I141-HAVERQ!I$128)/HAVERQ!$B$128) -> 1.6791948 | CA21: =100*((HAVERQ!J141-HAVERQ!J$128)/HAVERQ!$B$128) -> -1.6130593 | CB21: =100*((HAVERQ!K141-HAVERQ!K$128)/HAVERQ!$B$128) -> -0.69038939 | CC21: =100*(((HAVERQ!L141+HAVERQ!M141)-(HAVERQ!L$128+HAVERQ!M$128))/HAVERQ!$B$128) -> -0.38713424 | CD21: =CE21-BZ21-CA21-CB21-CC21 -> 1.7985612 | CE21: =100*((HAVERQ!B141-HAVERQ!B$128)/HAVERQ!B$128) -> 0.78717295 | CG21: 2022 | CH21: =HAVERQ!I137 -> 9722 | CI21: =HAVERQ!J137 -> 6669 | CJ21: =HAVERQ!K137 -> 2602 | CK21: =HAVERQ!L137+HAVERQ!M137 -> 38639 | CL21: =HAVERQ!N137 -> 1270 | CN21: 2022 | CO21: =CX21 -> -814 | CP21: =CY21 -> -218 | CQ21: =CZ21 -> -1329 | CR21: =DA21 -> -83 | CS21: =DC21 -> 1954 | CT21: =+DB21+DD21+DE21+DF21 -> 199 | CU21: =DG21 -> -977 | CW21: 2022 | CX21: =HAVERQ!L137-HAVERQ!L$128 -> -814 | CY21: =HAVERQ!O137-HAVERQ!O$128 -> -218 | CZ21: =HAVERQ!P137-HAVERQ!P$128 -> -1329 | DA21: =HAVERQ!Q137-HAVERQ!Q$128 -> -83 | DB21: =HAVERQ!R137-HAVERQ!R$128 -> 1450 | DC21: =HAVERQ!S137-HAVERQ!S$128 -> 1954 | DD21: =HAVERQ!T137-HAVERQ!T$128 -> -216 | DE21: =HAVERQ!U137-HAVERQ!U$128 -> -231 | DF21: =HAVERQ!V137-HAVERQ!V$128 -> -804 | DG21: =(HAVERQ!L137+HAVERQ!M137)-(HAVERQ!L$128+HAVERQ!M$128) -> -977 | DI21: 2022 | DJ21: =100*(HAVERQ!C137/HAVERQ!C$128) -> 103.05967 | DK21: =100*(HAVERQ!D137/HAVERQ!D$128) -> 97.779751 | DL21: =100*(HAVERQ!E137/HAVERQ!E$128) -> 110.54153 | DM21: =100*(HAVERQ!F137/HAVERQ!F$128) -> 107.49931 | DN21: =100*(HAVERQ!G137/HAVERQ!G$128) -> 100.30482 | DO21: =100*(HAVERQ!H137/HAVERQ!H$128) -> 97.820411 | DP21: 100 | DR21: 2022 | DS21: =HAVERQ!D137-HAVERQ!D$128 -> -100 | DT21: =HAVERQ!E137-HAVERQ!E$128 -> 1750 | DU21: =HAVERQ!F137-HAVERQ!F$128 -> 1901 | DV21: =HAVERQ!G137-HAVERQ!G$128 -> 113 | DW21: =HAVERQ!H137-HAVERQ!H$128 -> -576 | DX21: =HAVERQ!C137-HAVERQ!C$128 -> 3356 | DZ21: 2004 | EA21: =MIN(EM21:EO21) -> -0.18842778 | EB21: =+EF21-EA21 -> 0.47805544 | EC21: =100*((EJ25/EJ21)-1) -> -7.0566856 | ED21: 0 | EF21: =MAX(EM21:EO21) -> 0.28962766 | EG21: =AVERAGE(EM21:EO21) -> -0.017512327 | EI21: 2003 | EJ21: ='IPNR ex BNFL'!I29 -> 45673 | EM21: =(ER21-ER$2)/ER$3 -> 0.28962766 | EN21: =(ES21-ES$2)/ES$3 -> -0.18842778 | EO21: =(ET21-ET$2)/ET$3 -> -0.15373686 | ER21: =(HAVERQ!W63*$EW$2)+(HAVERQ!X63*$EX$2)/($EW$2+$EX$2) -> 11.598404 | ES21: =(HAVERQ!AB63*$EW$2)+(HAVERQ!AC63*$EY$2)+(HAVERQ!AD63*$EZ$2)+(HAVERQ!AE63*$FA$2)/($EW$2+$EY$2+$EZ$2+$FA$2) -> -8.8873308 | ET21: =(HAVERQ!Y63*$EW$2)+(HAVERQ!Z63*$EX$2)/($EW$2+$EX$2) -> 0.58115629 | FC21: 43952 | FD21: =100*((HAVERM!E252+HAVERM!F252)/(HAVERM!E$249+HAVERM!F$249)) -> 113.54628 | FE21: =100*(HAVERM!E252/HAVERM!E$249) -> 115.31931 | FF21: =100*(HAVERM!F252/HAVERM!F$249) -> 112.5734 | FG21: 100 | FV21: 42826 | FW21: =HAVERM!G215 -> 376274 | FY21: =FW21-FW20 -> 3674 | GC21: 2014 | GD21: =100*(DataQ!W171/DataQ!W$194) -> 85.630799 | GE21: =100*(DataQ!X171/DataQ!X$194) -> 84.637904 | GF21: =100*(DataQ!C171/DataQ!C$194) -> 83.974256 | GH21: 100 | GJ21: 2009 | GK21: =100*(DataQ!Z151/AVERAGE(DataQ!$Z$203:$Z$206)) -> 69.547165 | GL21: =100*(DataQ!C151/AVERAGE(DataQ!$C$203:$C$206)) -> 72.054142 | GM21: 100 | GO21: 2009 | GP21: =100*(DataQ!Z151/DataQ!$Z$194) -> 69.287697 | GQ21: =100*(DataQ!C151/DataQ!$C$194) -> 69.553505 | GR21: 100 | GT21: 2022 | GU21: =HB21 -> 95.014034 | GV21: =MIN(HC21:HH21) -> 94.818132 | GW21: =+GY21-GV21 -> 11.757665 | GX21: 100 | GY21: =MAX(HC21:HH21) -> 106.5758 | HA21: 2022 | HB21: =100*(DataQ!C203/DataQ!C$194) -> 95.014034 | HC21: =100*(DataQ!Q203/DataQ!Q$194) -> 104.7268 | HD21: =100*(DataQ!R203/DataQ!R$194) -> 101.66919 | HE21: =100*(DataQ!S203/DataQ!S$194) -> 94.818132 | HF21: =100*(DataQ!T203/DataQ!T$194) -> 102.32733 | HG21: =100*(DataQ!U203/DataQ!U$194) -> 106.5758 | HH21: =100*(DataQ!V203/DataQ!V$194) -> 102.02325 | HJ21: 2022 | HK21: =HR21 -> 95.014034 | HL21: =MIN(HS21:HX21) -> 94.818132 | HM21: =+HO21-HL21 -> 11.757665 | HN21: 100 | HO21: =MAX(HS21:HX21) -> 106.5758 | HQ21: 2022 | HR21: =100*(DataQ!C203/DataQ!C$194) -> 95.014034 | HS21: =100*(DataQ!Q203/DataQ!Q$194) -> 104.7268 | HT21: =100*(DataQ!R203/DataQ!R$194) -> 101.66919 | HU21: =100*(DataQ!S203/DataQ!S$194) -> 94.818132 | HV21: =100*(DataQ!T203/DataQ!T$194) -> 102.32733 | HW21: =100*(DataQ!U203/DataQ!U$194) -> 106.5758 | HX21: =100*(DataQ!V203/DataQ!V$194) -> 102.02325 | HZ21: 2006 | IA21: =DataA!J40/'Chart Data'!IF21 -> 2.6658953 | IB21: =IB20*(1+$ID$5/100) -> 2.6612864 | IC21: =100*((IA21/IB21)-1) -> 0.17318369 | IF21: =DataA!K40*DataA!L40 -> 933864.89 | IQ21: 2011 | IR21: =HAVERQ!AH92 -> -0.8 | IS21: =100*(('IPNR ex BNFL'!I61/'IPNR ex BNFL'!I57)-1) -> 2.0516406 | IT21: 0
B22: =100*((DataQ!C92/DataQ!C88)-1) -> 3.6258138 | C22: =K22 -> 11.063109 | D22: 0 | G22: =100*((AVERAGE(DataQ!C89:C92)/AVERAGE(DataQ!C85:C88))-1) -> -0.12730869 | H22: =AVERAGE(K19:K22) -> 11.804154 | I22: 0 | K22: =L22 -> 11.063109 | L22: =100*(HAVERQ!AF26/HAVERQ!AI26) -> 11.063109 | O22: =100*('ONS CVM_SA_(Quarterly)'!B106/'ONS CVM_SA_(Quarterly)'!B$101) -> 112.08293 | P22: =100*('ONS CVM_SA_(Quarterly)'!D106/'ONS CVM_SA_(Quarterly)'!D$101) -> 114.8684 | Q22: 1000 | R22: 100 | AI22: =100*(('ONS CVM_SA_(Quarterly)'!C110-'ONS CVM_SA_(Quarterly)'!C$96)/'ONS CVM_SA_(Quarterly)'!$B$96) -> 6.3699713 | AJ22: =100*(('ONS CVM_SA_(Quarterly)'!D110-'ONS CVM_SA_(Quarterly)'!D$96)/'ONS CVM_SA_(Quarterly)'!$B$96) -> 2.0260025 | AK22: =100*(('ONS CVM_SA_(Quarterly)'!E110-'ONS CVM_SA_(Quarterly)'!E$96)/'ONS CVM_SA_(Quarterly)'!$B$96) -> -7.0716521 | AL22: =100*(('ONS CVM_SA_(Quarterly)'!F110-'ONS CVM_SA_(Quarterly)'!F$96)/'ONS CVM_SA_(Quarterly)'!$B$96) -> -0.72265058 | AM22: =100*(('ONS CVM_SA_(Quarterly)'!B110-'ONS CVM_SA_(Quarterly)'!B$96)/'ONS CVM_SA_(Quarterly)'!$B$96) -> 0.25486337 | AP22: =100*(('ONS CVM_SA_(Quarterly)'!C98-AVERAGE('ONS CVM_SA_(Quarterly)'!C$81:C$84))/AVERAGE('ONS CVM_SA_(Quarterly)'!$B$81:$B$84)) -> -8.1174054 | AQ22: =100*(('ONS CVM_SA_(Quarterly)'!D98-AVERAGE('ONS CVM_SA_(Quarterly)'!D$81:D$84))/AVERAGE('ONS CVM_SA_(Quarterly)'!$B$81:$B$84)) -> -6.9014558 | AR22: =100*(('ONS CVM_SA_(Quarterly)'!E98-AVERAGE('ONS CVM_SA_(Quarterly)'!E$81:E$84))/AVERAGE('ONS CVM_SA_(Quarterly)'!$B$81:$B$84)) -> -5.747499 | AS22: =100*(('ONS CVM_SA_(Quarterly)'!F98-AVERAGE('ONS CVM_SA_(Quarterly)'!F$81:F$84))/AVERAGE('ONS CVM_SA_(Quarterly)'!$B$81:$B$84)) -> 1.0413164 | AT22: =100*(('ONS CVM_SA_(Quarterly)'!B98-AVERAGE('ONS CVM_SA_(Quarterly)'!B$81:B$84))/AVERAGE('ONS CVM_SA_(Quarterly)'!$B$81:$B$84)) -> -20.663849 | AV22: 43983 | AW22: =HAVERM!D253 -> 0.1 | AX22: =HAVERM!B253 -> 2.79 | AY22: =HAVERM!C253 -> 2.17 | BA22: 45047 | BB22: =AX57-AX$39 -> 3.34 | BC22: =AY57-AY$39 -> 0.81 | BD22: 1000 | BF22: 0 | BJ22: =100*(HAVERQ!B138/HAVERQ!B$128) -> 97.319095 | BK22: =100*(HAVERQ!I138/HAVERQ!I$128) -> 110.015 | BL22: =100*(HAVERQ!J138/HAVERQ!J$128) -> 80.122738 | BM22: =100*(HAVERQ!K138/HAVERQ!K$128) -> 77.674706 | BN22: =100*((HAVERQ!L138+HAVERQ!M138)/(HAVERQ!L$128+HAVERQ!M$128)) -> 97.243538 | BO22: 100 | BR22: =HAVERQ!I138-HAVERQ!I$128 -> 935 | BS22: =HAVERQ!J138-HAVERQ!J$128 -> -1911 | BT22: =HAVERQ!K138-HAVERQ!K$128 -> -722 | BU22: =(HAVERQ!L138+HAVERQ!M138)-(HAVERQ!L$128+HAVERQ!M$128) -> -1092 | BV22: =HAVERQ!N138-HAVERQ!N$128 -> -36 | BW22: =HAVERQ!B138-HAVERQ!B$128 -> -1662 | BZ22: =100*((HAVERQ!I142-HAVERQ!I$128)/HAVERQ!$B$128) -> 2.1163338 | CA22: =100*((HAVERQ!J142-HAVERQ!J$128)/HAVERQ!$B$128) -> -2.2760267 | CB22: =100*((HAVERQ!K142-HAVERQ!K$128)/HAVERQ!$B$128) -> -1.3630351 | CC22: =100*(((HAVERQ!L142+HAVERQ!M142)-(HAVERQ!L$128+HAVERQ!M$128))/HAVERQ!$B$128) -> -0.059683195 | CD22: =CE22-BZ22-CA22-CB22-CC22 -> 1.8372746 | CE22: =100*((HAVERQ!B142-HAVERQ!B$128)/HAVERQ!B$128) -> 0.25486337 | CH22: =HAVERQ!I138 -> 10271 | CI22: =HAVERQ!J138 -> 7703 | CJ22: =HAVERQ!K138 -> 2512 | CK22: =HAVERQ!L138+HAVERQ!M138 -> 38524 | CL22: =HAVERQ!N138 -> 1322 | CO22: =CX22 -> -26 | CP22: =CY22 -> -100 | CQ22: =CZ22 -> -1165 | CR22: =DA22 -> 164 | CS22: =DC22 -> 1029 | CT22: =+DB22+DD22+DE22+DF22 -> -308 | CU22: =DG22 -> -1092 | CX22: =HAVERQ!L138-HAVERQ!L$128 -> -26 | CY22: =HAVERQ!O138-HAVERQ!O$128 -> -100 | CZ22: =HAVERQ!P138-HAVERQ!P$128 -> -1165 | DA22: =HAVERQ!Q138-HAVERQ!Q$128 -> 164 | DB22: =HAVERQ!R138-HAVERQ!R$128 -> 555 | DC22: =HAVERQ!S138-HAVERQ!S$128 -> 1029 | DD22: =HAVERQ!T138-HAVERQ!T$128 -> -20 | DE22: =HAVERQ!U138-HAVERQ!U$128 -> -183 | DF22: =HAVERQ!V138-HAVERQ!V$128 -> -660 | DG22: =(HAVERQ!L138+HAVERQ!M138)-(HAVERQ!L$128+HAVERQ!M$128) -> -1092 | DJ22: =100*(HAVERQ!C138/HAVERQ!C$128) -> 103.00588 | DK22: =100*(HAVERQ!D138/HAVERQ!D$128) -> 145.33748 | DL22: =100*(HAVERQ!E138/HAVERQ!E$128) -> 110.38492 | DM22: =100*(HAVERQ!F138/HAVERQ!F$128) -> 106.57225 | DN22: =100*(HAVERQ!G138/HAVERQ!G$128) -> 96.247741 | DO22: =100*(HAVERQ!H138/HAVERQ!H$128) -> 96.174367 | DP22: 100 | DS22: =HAVERQ!D138-HAVERQ!D$128 -> 2042 | DT22: =HAVERQ!E138-HAVERQ!E$128 -> 1724 | DU22: =HAVERQ!F138-HAVERQ!F$128 -> 1666 | DV22: =HAVERQ!G138-HAVERQ!G$128 -> -1391 | DW22: =HAVERQ!H138-HAVERQ!H$128 -> -1011 | DX22: =HAVERQ!C138-HAVERQ!C$128 -> 3297 | EA22: =MIN(EM22:EO22) -> -0.43568546 | EB22: =+EF22-EA22 -> 1.271483 | EC22: =100*((EJ26/EJ22)-1) -> -5.5159066 | ED22: 0 | EF22: =MAX(EM22:EO22) -> 0.83579755 | EG22: =AVERAGE(EM22:EO22) -> 0.2045984 | EJ22: ='IPNR ex BNFL'!I30 -> 41335 | EM22: =(ER22-ER$2)/ER$3 -> 0.83579755 | EN22: =(ES22-ES$2)/ES$3 -> -0.43568546 | EO22: =(ET22-ET$2)/ET$3 -> 0.21368311 | ER22: =(HAVERQ!W64*$EW$2)+(HAVERQ!X64*$EX$2)/($EW$2+$EX$2) -> 18 | ES22: =(HAVERQ!AB64*$EW$2)+(HAVERQ!AC64*$EY$2)+(HAVERQ!AD64*$EZ$2)+(HAVERQ!AE64*$FA$2)/($EW$2+$EY$2+$EZ$2+$FA$2) -> -12.366693 | ET22: =(HAVERQ!Y64*$EW$2)+(HAVERQ!Z64*$EX$2)/($EW$2+$EX$2) -> 1.1582052 | FC22: 43983 | FD22: =100*((HAVERM!E253+HAVERM!F253)/(HAVERM!E$249+HAVERM!F$249)) -> 112.34523 | FE22: =100*(HAVERM!E253/HAVERM!E$249) -> 122.10496 | FF22: =100*(HAVERM!F253/HAVERM!F$249) -> 106.99001 | FG22: 100 | FV22: 42856 | FW22: =HAVERM!G216 -> 379101 | FY22: =FW22-FW21 -> 2827 | GD22: =100*(DataQ!W172/DataQ!W$194) -> 88.775803 | GE22: =100*(DataQ!X172/DataQ!X$194) -> 87.713617 | GF22: =100*(DataQ!C172/DataQ!C$194) -> 84.225893 | GH22: 100 | GK22: =100*(DataQ!Z152/AVERAGE(DataQ!$Z$203:$Z$206)) -> 65.897853 | GL22: =100*(DataQ!C152/AVERAGE(DataQ!$C$203:$C$206)) -> 68.307641 | GM22: 100 | GP22: =100*(DataQ!Z152/DataQ!$Z$194) -> 65.651999 | GQ22: =100*(DataQ!C152/DataQ!$C$194) -> 65.937026 | GR22: 100 | GU22: =HB22 -> 97.319095 | GV22: =MIN(HC22:HH22) -> 96.636812 | GW22: =+GY22-GV22 -> 12.846705 | GX22: 100 | GY22: =MAX(HC22:HH22) -> 109.48352 | HB22: =100*(DataQ!C204/DataQ!C$194) -> 97.319095 | HC22: =100*(DataQ!Q204/DataQ!Q$194) -> 106.58519 | HD22: =100*(DataQ!R204/DataQ!R$194) -> 103.97839 | HE22: =100*(DataQ!S204/DataQ!S$194) -> 96.636812 | HF22: =100*(DataQ!T204/DataQ!T$194) -> 102.37942 | HG22: =100*(DataQ!U204/DataQ!U$194) -> 109.48352 | HH22: =100*(DataQ!V204/DataQ!V$194) -> 104.01835 | HK22: =HR22 -> 97.319095 | HL22: =MIN(HS22:HX22) -> 96.636812 | HM22: =+HO22-HL22 -> 12.846705 | HN22: 100 | HO22: =MAX(HS22:HX22) -> 109.48352 | HR22: =100*(DataQ!C204/DataQ!C$194) -> 97.319095 | HS22: =100*(DataQ!Q204/DataQ!Q$194) -> 106.58519 | HT22: =100*(DataQ!R204/DataQ!R$194) -> 103.97839 | HU22: =100*(DataQ!S204/DataQ!S$194) -> 96.636812 | HV22: =100*(DataQ!T204/DataQ!T$194) -> 102.37942 | HW22: =100*(DataQ!U204/DataQ!U$194) -> 109.48352 | HX22: =100*(DataQ!V204/DataQ!V$194) -> 104.01835 | HZ22: 2007 | IA22: =DataA!J41/'Chart Data'!IF22 -> 2.7319853 | IB22: =IB21*(1+$ID$5/100) -> 2.7319853 | IC22: =100*((IA22/IB22)-1) -> 1.5543122e-13 | IF22: =DataA!K41*DataA!L41 -> 942299.35 | IR22: =HAVERQ!AH93 -> -0.9 | IS22: =100*(('IPNR ex BNFL'!I62/'IPNR ex BNFL'!I58)-1) -> 9.5060943 | IT22: 0
B23: =100*((DataQ!C93/DataQ!C89)-1) -> 7.1242004 | C23: =K23 -> 11.47864 | D23: 0 | G23: =100*((AVERAGE(DataQ!C90:C93)/AVERAGE(DataQ!C86:C89))-1) -> 3.0352062 | H23: =AVERAGE(K20:K23) -> 11.43344 | I23: 0 | K23: =L23 -> 11.47864 | L23: =100*(HAVERQ!AF27/HAVERQ!AI27) -> 11.47864 | O23: =100*('ONS CVM_SA_(Quarterly)'!B107/'ONS CVM_SA_(Quarterly)'!B$101) -> 113.11399 | P23: =100*('ONS CVM_SA_(Quarterly)'!D107/'ONS CVM_SA_(Quarterly)'!D$101) -> 117.21432 | Q23: 1000 | R23: 100 | AI23: =100*(('ONS CVM_SA_(Quarterly)'!C111-'ONS CVM_SA_(Quarterly)'!C$96)/'ONS CVM_SA_(Quarterly)'!$B$96) -> 5.4682711 | AJ23: =100*(('ONS CVM_SA_(Quarterly)'!D111-'ONS CVM_SA_(Quarterly)'!D$96)/'ONS CVM_SA_(Quarterly)'!$B$96) -> 1.4307836 | AK23: =100*(('ONS CVM_SA_(Quarterly)'!E111-'ONS CVM_SA_(Quarterly)'!E$96)/'ONS CVM_SA_(Quarterly)'!$B$96) -> -7.8797948 | AL23: =100*(('ONS CVM_SA_(Quarterly)'!F111-'ONS CVM_SA_(Quarterly)'!F$96)/'ONS CVM_SA_(Quarterly)'!$B$96) -> -1.4114269 | AM23: =100*(('ONS CVM_SA_(Quarterly)'!B111-'ONS CVM_SA_(Quarterly)'!B$96)/'ONS CVM_SA_(Quarterly)'!$B$96) -> -2.7389747 | AP23: =100*(('ONS CVM_SA_(Quarterly)'!C99-AVERAGE('ONS CVM_SA_(Quarterly)'!C$81:C$84))/AVERAGE('ONS CVM_SA_(Quarterly)'!$B$81:$B$84)) -> -2.8792195 | AQ23: =100*(('ONS CVM_SA_(Quarterly)'!D99-AVERAGE('ONS CVM_SA_(Quarterly)'!D$81:D$84))/AVERAGE('ONS CVM_SA_(Quarterly)'!$B$81:$B$84)) -> -4.8593413 | AR23: =100*(('ONS CVM_SA_(Quarterly)'!E99-AVERAGE('ONS CVM_SA_(Quarterly)'!E$81:E$84))/AVERAGE('ONS CVM_SA_(Quarterly)'!$B$81:$B$84)) -> -5.1154159 | AS23: =100*(('ONS CVM_SA_(Quarterly)'!F99-AVERAGE('ONS CVM_SA_(Quarterly)'!F$81:F$84))/AVERAGE('ONS CVM_SA_(Quarterly)'!$B$81:$B$84)) -> 1.5323963 | AT23: =100*(('ONS CVM_SA_(Quarterly)'!B99-AVERAGE('ONS CVM_SA_(Quarterly)'!B$81:B$84))/AVERAGE('ONS CVM_SA_(Quarterly)'!$B$81:$B$84)) -> -11.330089 | AV23: 44013 | AW23: =HAVERM!D254 -> 0.1 | AX23: =HAVERM!B254 -> 2.66 | AY23: =HAVERM!C254 -> 2.16 | BA23: 45078 | BB23: =AX58-AX$39 -> 3.62 | BC23: =AY58-AY$39 -> 0.91 | BD23: 1000 | BF23: 0 | BJ23: =100*(HAVERQ!B139/HAVERQ!B$128) -> 98.214343 | BK23: =100*(HAVERQ!I139/HAVERQ!I$128) -> 108.51542 | BL23: =100*(HAVERQ!J139/HAVERQ!J$128) -> 86.654878 | BM23: =100*(HAVERQ!K139/HAVERQ!K$128) -> 88.961039 | BN23: =100*((HAVERQ!L139+HAVERQ!M139)/(HAVERQ!L$128+HAVERQ!M$128)) -> 96.435784 | BO23: 100 | BR23: =HAVERQ!I139-HAVERQ!I$128 -> 795 | BS23: =HAVERQ!J139-HAVERQ!J$128 -> -1283 | BT23: =HAVERQ!K139-HAVERQ!K$128 -> -357 | BU23: =(HAVERQ!L139+HAVERQ!M139)-(HAVERQ!L$128+HAVERQ!M$128) -> -1412 | BV23: =HAVERQ!N139-HAVERQ!N$128 -> -14 | BW23: =HAVERQ!B139-HAVERQ!B$128 -> -1107 | BZ23: =100*((HAVERQ!I143-HAVERQ!I$128)/HAVERQ!$B$128) -> 1.7743653 | CA23: =100*((HAVERQ!J143-HAVERQ!J$128)/HAVERQ!$B$128) -> -2.4099106 | CB23: =100*((HAVERQ!K143-HAVERQ!K$128)/HAVERQ!$B$128) -> -1.8808272 | CC23: =100*(((HAVERQ!L143+HAVERQ!M143)-(HAVERQ!L$128+HAVERQ!M$128))/HAVERQ!$B$128) -> -2.0614898 | CD23: =CE23-BZ23-CA23-CB23-CC23 -> 1.8388876 | CE23: =100*((HAVERQ!B143-HAVERQ!B$128)/HAVERQ!B$128) -> -2.7389747 | CH23: =HAVERQ!I139 -> 10131 | CI23: =HAVERQ!J139 -> 8331 | CJ23: =HAVERQ!K139 -> 2877 | CK23: =HAVERQ!L139+HAVERQ!M139 -> 38204 | CL23: =HAVERQ!N139 -> 1344 | CO23: =CX23 -> -597 | CP23: =CY23 -> -187 | CQ23: =CZ23 -> -1235 | CR23: =DA23 -> 308 | CS23: =DC23 -> 1472 | CT23: =+DB23+DD23+DE23+DF23 -> -487 | CU23: =DG23 -> -1412 | CX23: =HAVERQ!L139-HAVERQ!L$128 -> -597 | CY23: =HAVERQ!O139-HAVERQ!O$128 -> -187 | CZ23: =HAVERQ!P139-HAVERQ!P$128 -> -1235 | DA23: =HAVERQ!Q139-HAVERQ!Q$128 -> 308 | DB23: =HAVERQ!R139-HAVERQ!R$128 -> 531 | DC23: =HAVERQ!S139-HAVERQ!S$128 -> 1472 | DD23: =HAVERQ!T139-HAVERQ!T$128 -> -80 | DE23: =HAVERQ!U139-HAVERQ!U$128 -> -265 | DF23: =HAVERQ!V139-HAVERQ!V$128 -> -673 | DG23: =(HAVERQ!L139+HAVERQ!M139)-(HAVERQ!L$128+HAVERQ!M$128) -> -1412 | DJ23: =100*(HAVERQ!C139/HAVERQ!C$128) -> 103.27848 | DK23: =100*(HAVERQ!D139/HAVERQ!D$128) -> 142.51776 | DL23: =100*(HAVERQ!E139/HAVERQ!E$128) -> 112.63779 | DM23: =100*(HAVERQ!F139/HAVERQ!F$128) -> 107.37307 | DN23: =100*(HAVERQ!G139/HAVERQ!G$128) -> 94.451188 | DO23: =100*(HAVERQ!H139/HAVERQ!H$128) -> 98.123132 | DP23: 100 | DS23: =HAVERQ!D139-HAVERQ!D$128 -> 1915 | DT23: =HAVERQ!E139-HAVERQ!E$128 -> 2098 | DU23: =HAVERQ!F139-HAVERQ!F$128 -> 1869 | DV23: =HAVERQ!G139-HAVERQ!G$128 -> -2057 | DW23: =HAVERQ!H139-HAVERQ!H$128 -> -496 | DX23: =HAVERQ!C139-HAVERQ!C$128 -> 3596 | EA23: =MIN(EM23:EO23) -> 0.37237331 | EB23: =+EF23-EA23 -> 0.35712996 | EC23: =100*((EJ27/EJ23)-1) -> -2.3815144 | ED23: 0 | EF23: =MAX(EM23:EO23) -> 0.72950326 | EG23: =AVERAGE(EM23:EO23) -> 0.52718563 | EJ23: ='IPNR ex BNFL'!I31 -> 42368 | EL23: 2004 | EM23: =(ER23-ER$2)/ER$3 -> 0.72950326 | EN23: =(ES23-ES$2)/ES$3 -> 0.37237331 | EO23: =(ET23-ET$2)/ET$3 -> 0.47968031 | EQ23: 2004 | ER23: =(HAVERQ!W65*$EW$2)+(HAVERQ!X65*$EX$2)/($EW$2+$EX$2) -> 16.754137 | ES23: =(HAVERQ!AB65*$EW$2)+(HAVERQ!AC65*$EY$2)+(HAVERQ!AD65*$EZ$2)+(HAVERQ!AE65*$FA$2)/($EW$2+$EY$2+$EZ$2+$FA$2) -> -0.99584728 | ET23: =(HAVERQ!Y65*$EW$2)+(HAVERQ!Z65*$EX$2)/($EW$2+$EX$2) -> 1.5759652 | FC23: 44013 | FD23: =100*((HAVERM!E254+HAVERM!F254)/(HAVERM!E$249+HAVERM!F$249)) -> 111.57779 | FE23: =100*(HAVERM!E254/HAVERM!E$249) -> 125.37719 | FF23: =100*(HAVERM!F254/HAVERM!F$249) -> 104.00598 | FG23: 100 | FV23: 42887 | FW23: =HAVERM!G217 -> 384147 | FY23: =FW23-FW22 -> 5046 | GD23: =100*(DataQ!W173/DataQ!W$194) -> 88.489527 | GE23: =100*(DataQ!X173/DataQ!X$194) -> 87.45746 | GF23: =100*(DataQ!C173/DataQ!C$194) -> 84.816273 | GH23: 100 | GK23: =100*(DataQ!Z153/AVERAGE(DataQ!$Z$203:$Z$206)) -> 64.473517 | GL23: =100*(DataQ!C153/AVERAGE(DataQ!$C$203:$C$206)) -> 66.805364 | GM23: 100 | GP23: =100*(DataQ!Z153/DataQ!$Z$194) -> 64.232978 | GQ23: =100*(DataQ!C153/DataQ!$C$194) -> 64.486886 | GR23: 100 | GU23: =HB23 -> 98.214343 | GV23: =MIN(HC23:HH23) -> 96.86529 | GW23: =+GY23-GV23 -> 13.732255 | GX23: 100 | GY23: =MAX(HC23:HH23) -> 110.59754 | HB23: =100*(DataQ!C205/DataQ!C$194) -> 98.214343 | HC23: =100*(DataQ!Q205/DataQ!Q$194) -> 108.57826 | HD23: =100*(DataQ!R205/DataQ!R$194) -> 106.18618 | HE23: =100*(DataQ!S205/DataQ!S$194) -> 96.86529 | HF23: =100*(DataQ!T205/DataQ!T$194) -> 105.04896 | HG23: =100*(DataQ!U205/DataQ!U$194) -> 110.59754 | HH23: =100*(DataQ!V205/DataQ!V$194) -> 103.96205 | HK23: =HR23 -> 98.214343 | HL23: =MIN(HS23:HX23) -> 96.86529 | HM23: =+HO23-HL23 -> 13.732255 | HN23: 100 | HO23: =MAX(HS23:HX23) -> 110.59754 | HR23: =100*(DataQ!C205/DataQ!C$194) -> 98.214343 | HS23: =100*(DataQ!Q205/DataQ!Q$194) -> 108.57826 | HT23: =100*(DataQ!R205/DataQ!R$194) -> 106.18618 | HU23: =100*(DataQ!S205/DataQ!S$194) -> 96.86529 | HV23: =100*(DataQ!T205/DataQ!T$194) -> 105.04896 | HW23: =100*(DataQ!U205/DataQ!U$194) -> 110.59754 | HX23: =100*(DataQ!V205/DataQ!V$194) -> 103.96205 | HZ23: 2008 | IA23: =DataA!J42/'Chart Data'!IF23 -> 2.7896222 | IB23: =IB22*(1+$ID$5/100) -> 2.8045625 | IC23: =100*((IA23/IB23)-1) -> -0.53271161 | IF23: =DataA!K42*DataA!L42 -> 947371.29 | IR23: =HAVERQ!AH94 -> -7.4 | IS23: =100*(('IPNR ex BNFL'!I63/'IPNR ex BNFL'!I59)-1) -> 8.246481 | IT23: 0
B24: =100*((DataQ!C94/DataQ!C90)-1) -> 8.3822036 | C24: =K24 -> 11.418332 | D24: 0 | G24: =100*((AVERAGE(DataQ!C91:C94)/AVERAGE(DataQ!C87:C90))-1) -> 4.8902138 | H24: =AVERAGE(K21:K24) -> 11.256403 | I24: 0 | K24: =L24 -> 11.418332 | L24: =100*(HAVERQ!AF28/HAVERQ!AI28) -> 11.418332 | O24: =100*('ONS CVM_SA_(Quarterly)'!B108/'ONS CVM_SA_(Quarterly)'!B$101) -> 110.06911 | P24: =100*('ONS CVM_SA_(Quarterly)'!D108/'ONS CVM_SA_(Quarterly)'!D$101) -> 108.21481 | Q24: 1000 | R24: 100 | AI24: =100*(('ONS CVM_SA_(Quarterly)'!C112-'ONS CVM_SA_(Quarterly)'!C$96)/'ONS CVM_SA_(Quarterly)'!$B$96) -> 5.8925057 | AJ24: =100*(('ONS CVM_SA_(Quarterly)'!D112-'ONS CVM_SA_(Quarterly)'!D$96)/'ONS CVM_SA_(Quarterly)'!$B$96) -> 1.1323676 | AK24: =100*(('ONS CVM_SA_(Quarterly)'!E112-'ONS CVM_SA_(Quarterly)'!E$96)/'ONS CVM_SA_(Quarterly)'!$B$96) -> -6.4377198 | AL24: =100*(('ONS CVM_SA_(Quarterly)'!F112-'ONS CVM_SA_(Quarterly)'!F$96)/'ONS CVM_SA_(Quarterly)'!$B$96) -> -1.8098526 | AM24: =100*(('ONS CVM_SA_(Quarterly)'!B112-'ONS CVM_SA_(Quarterly)'!B$96)/'ONS CVM_SA_(Quarterly)'!$B$96) -> -1.5695067 | AP24: =100*(('ONS CVM_SA_(Quarterly)'!C100-AVERAGE('ONS CVM_SA_(Quarterly)'!C$81:C$84))/AVERAGE('ONS CVM_SA_(Quarterly)'!$B$81:$B$84)) -> -1.1693537 | AQ24: =100*(('ONS CVM_SA_(Quarterly)'!D100-AVERAGE('ONS CVM_SA_(Quarterly)'!D$81:D$84))/AVERAGE('ONS CVM_SA_(Quarterly)'!$B$81:$B$84)) -> -2.6843272 | AR24: =100*(('ONS CVM_SA_(Quarterly)'!E100-AVERAGE('ONS CVM_SA_(Quarterly)'!E$81:E$84))/AVERAGE('ONS CVM_SA_(Quarterly)'!$B$81:$B$84)) -> -4.4444354 | AS24: =100*(('ONS CVM_SA_(Quarterly)'!F100-AVERAGE('ONS CVM_SA_(Quarterly)'!F$81:F$84))/AVERAGE('ONS CVM_SA_(Quarterly)'!$B$81:$B$84)) -> 1.817644 | AT24: =100*(('ONS CVM_SA_(Quarterly)'!B100-AVERAGE('ONS CVM_SA_(Quarterly)'!B$81:B$84))/AVERAGE('ONS CVM_SA_(Quarterly)'!$B$81:$B$84)) -> -6.3625645 | AV24: 44044 | AW24: =HAVERM!D255 -> 0.1 | AX24: =HAVERM!B255 -> 2.53 | AY24: =HAVERM!C255 -> 2.14 | BA24: 45108 | BB24: =AX59-AX$39 -> 3.81 | BC24: =AY59-AY$39 -> 0.96 | BD24: 1000 | BF24: 0 | BJ24: =100*(HAVERQ!B140/HAVERQ!B$128) -> 95.570539 | BK24: =100*(HAVERQ!I140/HAVERQ!I$128) -> 108.36547 | BL24: =100*(HAVERQ!J140/HAVERQ!J$128) -> 86.540462 | BM24: =100*(HAVERQ!K140/HAVERQ!K$128) -> 89.424861 | BN24: =100*((HAVERQ!L140+HAVERQ!M140)/(HAVERQ!L$128+HAVERQ!M$128)) -> 92.283421 | BO24: 100 | BR24: =HAVERQ!I140-HAVERQ!I$128 -> 781 | BS24: =HAVERQ!J140-HAVERQ!J$128 -> -1294 | BT24: =HAVERQ!K140-HAVERQ!K$128 -> -342 | BU24: =(HAVERQ!L140+HAVERQ!M140)-(HAVERQ!L$128+HAVERQ!M$128) -> -3057 | BV24: =HAVERQ!N140-HAVERQ!N$128 -> 2 | BW24: =HAVERQ!B140-HAVERQ!B$128 -> -2746 | BZ24: =100*((HAVERQ!I144-HAVERQ!I$128)/HAVERQ!$B$128) -> 1.6840339 | CA24: =100*((HAVERQ!J144-HAVERQ!J$128)/HAVERQ!$B$128) -> -1.3017389 | CB24: =100*((HAVERQ!K144-HAVERQ!K$128)/HAVERQ!$B$128) -> -1.7663 | CC24: =100*(((HAVERQ!L144+HAVERQ!M144)-(HAVERQ!L$128+HAVERQ!M$128))/HAVERQ!$B$128) -> -1.9824499 | CD24: =CE24-BZ24-CA24-CB24-CC24 -> 1.7969481 | CE24: =100*((HAVERQ!B144-HAVERQ!B$128)/HAVERQ!B$128) -> -1.5695067 | CH24: =HAVERQ!I140 -> 10117 | CI24: =HAVERQ!J140 -> 8320 | CJ24: =HAVERQ!K140 -> 2892 | CK24: =HAVERQ!L140+HAVERQ!M140 -> 36559 | CL24: =HAVERQ!N140 -> 1360 | CO24: =CX24 -> 35 | CP24: =CY24 -> -194 | CQ24: =CZ24 -> -1171 | CR24: =DA24 -> 2491 | CS24: =DC24 -> -1942 | CT24: =+DB24+DD24+DE24+DF24 -> -1590 | CU24: =DG24 -> -3057 | CX24: =HAVERQ!L140-HAVERQ!L$128 -> 35 | CY24: =HAVERQ!O140-HAVERQ!O$128 -> -194 | CZ24: =HAVERQ!P140-HAVERQ!P$128 -> -1171 | DA24: =HAVERQ!Q140-HAVERQ!Q$128 -> 2491 | DB24: =HAVERQ!R140-HAVERQ!R$128 -> 49 | DC24: =HAVERQ!S140-HAVERQ!S$128 -> -1942 | DD24: =HAVERQ!T140-HAVERQ!T$128 -> -835 | DE24: =HAVERQ!U140-HAVERQ!U$128 -> -285 | DF24: =HAVERQ!V140-HAVERQ!V$128 -> -519 | DG24: =(HAVERQ!L140+HAVERQ!M140)-(HAVERQ!L$128+HAVERQ!M$128) -> -3057 | DJ24: =100*(HAVERQ!C140/HAVERQ!C$128) -> 101.9164 | DK24: =100*(HAVERQ!D140/HAVERQ!D$128) -> 155.90586 | DL24: =100*(HAVERQ!E140/HAVERQ!E$128) -> 106.74658 | DM24: =100*(HAVERQ!F140/HAVERQ!F$128) -> 106.2606 | DN24: =100*(HAVERQ!G140/HAVERQ!G$128) -> 91.637668 | DO24: =100*(HAVERQ!H140/HAVERQ!H$128) -> 98.902637 | DP24: 100 | DS24: =HAVERQ!D140-HAVERQ!D$128 -> 2518 | DT24: =HAVERQ!E140-HAVERQ!E$128 -> 1120 | DU24: =HAVERQ!F140-HAVERQ!F$128 -> 1587 | DV24: =HAVERQ!G140-HAVERQ!G$128 -> -3100 | DW24: =HAVERQ!H140-HAVERQ!H$128 -> -290 | DX24: =HAVERQ!C140-HAVERQ!C$128 -> 2102 | EA24: =MIN(EM24:EO24) -> 0.71175286 | EB24: =+EF24-EA24 -> 0.36777693 | EC24: =100*((EJ28/EJ24)-1) -> 0.36804863 | ED24: 0 | EF24: =MAX(EM24:EO24) -> 1.0795298 | EG24: =AVERAGE(EM24:EO24) -> 0.90786402 | EJ24: ='IPNR ex BNFL'!I32 -> 42114 | EM24: =(ER24-ER$2)/ER$3 -> 0.93230941 | EN24: =(ES24-ES$2)/ES$3 -> 1.0795298 | EO24: =(ET24-ET$2)/ET$3 -> 0.71175286 | ER24: =(HAVERQ!W66*$EW$2)+(HAVERQ!X66*$EX$2)/($EW$2+$EX$2) -> 19.131205 | ES24: =(HAVERQ!AB66*$EW$2)+(HAVERQ!AC66*$EY$2)+(HAVERQ!AD66*$EZ$2)+(HAVERQ!AE66*$FA$2)/($EW$2+$EY$2+$EZ$2+$FA$2) -> 8.9551207 | ET24: =(HAVERQ!Y66*$EW$2)+(HAVERQ!Z66*$EX$2)/($EW$2+$EX$2) -> 1.9404451 | FC24: 44044 | FD24: =100*((HAVERM!E255+HAVERM!F255)/(HAVERM!E$249+HAVERM!F$249)) -> 112.20054 | FE24: =100*(HAVERM!E255/HAVERM!E$249) -> 127.06926 | FF24: =100*(HAVERM!F255/HAVERM!F$249) -> 104.04198 | FG24: 100 | FV24: 42917 | FW24: =HAVERM!G218 -> 379497 | FY24: =FW24-FW23 -> -4650 | GD24: =100*(DataQ!W174/DataQ!W$194) -> 90.428946 | GE24: =100*(DataQ!X174/DataQ!X$194) -> 89.579903 | GF24: =100*(DataQ!C174/DataQ!C$194) -> 87.869794 | GH24: 100 | GK24: =100*(DataQ!Z154/AVERAGE(DataQ!$Z$203:$Z$206)) -> 63.914645 | GL24: =100*(DataQ!C154/AVERAGE(DataQ!$C$203:$C$206)) -> 66.203785 | GM24: 100 | GP24: =100*(DataQ!Z154/DataQ!$Z$194) -> 63.676191 | GQ24: =100*(DataQ!C154/DataQ!$C$194) -> 63.906184 | GR24: 100 | GU24: =HB24 -> 95.570539 | GV24: =MIN(HC24:HH24) -> 96.86529 | GW24: =+GY24-GV24 -> 13.504126 | GX24: 100 | GY24: =MAX(HC24:HH24) -> 110.36942 | HB24: =100*(DataQ!C206/DataQ!C$194) -> 95.570539 | HC24: =100*(DataQ!Q206/DataQ!Q$194) -> 110.08989 | HD24: =100*(DataQ!R206/DataQ!R$194) -> 104.91895 | HE24: =100*(DataQ!S206/DataQ!S$194) -> 96.86529 | HF24: =100*(DataQ!T206/DataQ!T$194) -> 105.66646 | HG24: =100*(DataQ!U206/DataQ!U$194) -> 110.36942 | HH24: =100*(DataQ!V206/DataQ!V$194) -> 102.1533 | HK24: =HR24 -> 95.570539 | HL24: =MIN(HS24:HX24) -> 96.86529 | HM24: =+HO24-HL24 -> 13.504126 | HN24: 100 | HO24: =MAX(HS24:HX24) -> 110.36942 | HR24: =100*(DataQ!C206/DataQ!C$194) -> 95.570539 | HS24: =100*(DataQ!Q206/DataQ!Q$194) -> 110.08989 | HT24: =100*(DataQ!R206/DataQ!R$194) -> 104.91895 | HU24: =100*(DataQ!S206/DataQ!S$194) -> 96.86529 | HV24: =100*(DataQ!T206/DataQ!T$194) -> 105.66646 | HW24: =100*(DataQ!U206/DataQ!U$194) -> 110.36942 | HX24: =100*(DataQ!V206/DataQ!V$194) -> 102.1533 | HZ24: 2009 | IA24: =DataA!J43/'Chart Data'!IF24 -> 2.9013706 | IB24: =IB23*(1+$ID$5/100) -> 2.8790676 | IC24: =100*((IA24/IB24)-1) -> 0.77465907 | IF24: =DataA!K43*DataA!L43 -> 919871.8 | IR24: =HAVERQ!AH95 -> -12.2 | IS24: =100*(('IPNR ex BNFL'!I64/'IPNR ex BNFL'!I60)-1) -> 4.0821707 | IT24: 0
A25: 1995 | B25: =100*((DataQ!C95/DataQ!C91)-1) -> 4.2475269 | C25: =K25 -> 12.317573 | D25: 0 | F25: 1995 | G25: =100*((AVERAGE(DataQ!C92:C95)/AVERAGE(DataQ!C88:C91))-1) -> 5.842125 | H25: =AVERAGE(K22:K25) -> 11.569414 | I25: 0 | K25: =L25 -> 12.317573 | L25: =100*(HAVERQ!AF29/HAVERQ!AI29) -> 12.317573 | N25: 2023 | O25: =100*('ONS CVM_SA_(Quarterly)'!B109/'ONS CVM_SA_(Quarterly)'!B$101) -> 116.07713 | P25: =100*('ONS CVM_SA_(Quarterly)'!D109/'ONS CVM_SA_(Quarterly)'!D$101) -> 115.78388 | Q25: 1000 | R25: 100 | AH25: 2024 | AI25: =100*(('ONS CVM_SA_(Quarterly)'!C113-'ONS CVM_SA_(Quarterly)'!C$96)/'ONS CVM_SA_(Quarterly)'!$B$96) -> 5.6682905 | AJ25: =100*(('ONS CVM_SA_(Quarterly)'!D113-'ONS CVM_SA_(Quarterly)'!D$96)/'ONS CVM_SA_(Quarterly)'!$B$96) -> 2.1905346 | AK25: =100*(('ONS CVM_SA_(Quarterly)'!E113-'ONS CVM_SA_(Quarterly)'!E$96)/'ONS CVM_SA_(Quarterly)'!$B$96) -> -6.3409362 | AL25: =100*(('ONS CVM_SA_(Quarterly)'!F113-'ONS CVM_SA_(Quarterly)'!F$96)/'ONS CVM_SA_(Quarterly)'!$B$96) -> -2.1776301 | AM25: =100*(('ONS CVM_SA_(Quarterly)'!B113-'ONS CVM_SA_(Quarterly)'!B$96)/'ONS CVM_SA_(Quarterly)'!$B$96) -> -1.006549 | AO25: 2021 | AP25: =100*(('ONS CVM_SA_(Quarterly)'!C101-AVERAGE('ONS CVM_SA_(Quarterly)'!C$81:C$84))/AVERAGE('ONS CVM_SA_(Quarterly)'!$B$81:$B$84)) -> -5.8305612 | AQ25: =100*(('ONS CVM_SA_(Quarterly)'!D101-AVERAGE('ONS CVM_SA_(Quarterly)'!D$81:D$84))/AVERAGE('ONS CVM_SA_(Quarterly)'!$B$81:$B$84)) -> -2.1916265 | AR25: =100*(('ONS CVM_SA_(Quarterly)'!E101-AVERAGE('ONS CVM_SA_(Quarterly)'!E$81:E$84))/AVERAGE('ONS CVM_SA_(Quarterly)'!$B$81:$B$84)) -> -6.3893065 | AS25: =100*(('ONS CVM_SA_(Quarterly)'!F101-AVERAGE('ONS CVM_SA_(Quarterly)'!F$81:F$84))/AVERAGE('ONS CVM_SA_(Quarterly)'!$B$81:$B$84)) -> 1.8581622 | AT25: =100*(('ONS CVM_SA_(Quarterly)'!B101-AVERAGE('ONS CVM_SA_(Quarterly)'!B$81:B$84))/AVERAGE('ONS CVM_SA_(Quarterly)'!$B$81:$B$84)) -> -12.759569 | AV25: 44075 | AW25: =HAVERM!D256 -> 0.1 | AX25: =HAVERM!B256 -> 2.52 | AY25: =HAVERM!C256 -> 2.13 | BA25: 45139 | BB25: =AX60-AX$39 -> 4.01 | BC25: =AY60-AY$39 -> 1.05 | BD25: 1000 | BF25: 0 | BI25: 2023 | BJ25: =100*(HAVERQ!B141/HAVERQ!B$128) -> 100.78717 | BK25: =100*(HAVERQ!I141/HAVERQ!I$128) -> 111.15039 | BL25: =100*(HAVERQ!J141/HAVERQ!J$128) -> 89.598502 | BM25: =100*(HAVERQ!K141/HAVERQ!K$128) -> 86.765615 | BN25: =100*((HAVERQ!L141+HAVERQ!M141)/(HAVERQ!L$128+HAVERQ!M$128)) -> 99.394184 | BO25: 100 | BQ25: 2023 | BR25: =HAVERQ!I141-HAVERQ!I$128 -> 1041 | BS25: =HAVERQ!J141-HAVERQ!J$128 -> -1000 | BT25: =HAVERQ!K141-HAVERQ!K$128 -> -428 | BU25: =(HAVERQ!L141+HAVERQ!M141)-(HAVERQ!L$128+HAVERQ!M$128) -> -240 | BV25: =HAVERQ!N141-HAVERQ!N$128 -> -49 | BW25: =HAVERQ!B141-HAVERQ!B$128 -> 488 | BY25: 2024 | BZ25: =100*((HAVERQ!I145-HAVERQ!I$128)/HAVERQ!$B$128) -> 1.8469529 | CA25: =100*((HAVERQ!J145-HAVERQ!J$128)/HAVERQ!$B$128) -> -1.3081911 | CB25: =100*((HAVERQ!K145-HAVERQ!K$128)/HAVERQ!$B$128) -> -1.7082298 | CC25: =100*(((HAVERQ!L145+HAVERQ!M145)-(HAVERQ!L$128+HAVERQ!M$128))/HAVERQ!$B$128) -> -1.6356422 | CD25: =CE25-BZ25-CA25-CB25-CC25 -> 1.7985612 | CE25: =100*((HAVERQ!B145-HAVERQ!B$128)/HAVERQ!B$128) -> -1.006549 | CG25: 2023 | CH25: =HAVERQ!I141 -> 10377 | CI25: =HAVERQ!J141 -> 8614 | CJ25: =HAVERQ!K141 -> 2806 | CK25: =HAVERQ!L141+HAVERQ!M141 -> 39376 | CL25: =HAVERQ!N141 -> 1309 | CN25: 2023 | CO25: =CX25 -> -1413 | CP25: =CY25 -> -142 | CQ25: =CZ25 -> -1146 | CR25: =DA25 -> 1357 | CS25: =DC25 -> 2084 | CT25: =+DB25+DD25+DE25+DF25 -> -294 | CU25: =DG25 -> -240 | CW25: 2023 | CX25: =HAVERQ!L141-HAVERQ!L$128 -> -1413 | CY25: =HAVERQ!O141-HAVERQ!O$128 -> -142 | CZ25: =HAVERQ!P141-HAVERQ!P$128 -> -1146 | DA25: =HAVERQ!Q141-HAVERQ!Q$128 -> 1357 | DB25: =HAVERQ!R141-HAVERQ!R$128 -> 496 | DC25: =HAVERQ!S141-HAVERQ!S$128 -> 2084 | DD25: =HAVERQ!T141-HAVERQ!T$128 -> -132 | DE25: =HAVERQ!U141-HAVERQ!U$128 -> -261 | DF25: =HAVERQ!V141-HAVERQ!V$128 -> -397 | DG25: =(HAVERQ!L141+HAVERQ!M141)-(HAVERQ!L$128+HAVERQ!M$128) -> -240 | DI25: 2023 | DJ25: =100*(HAVERQ!C141/HAVERQ!C$128) -> 104.69071 | DK25: =100*(HAVERQ!D141/HAVERQ!D$128) -> 171.00355 | DL25: =100*(HAVERQ!E141/HAVERQ!E$128) -> 116.72188 | DM25: =100*(HAVERQ!F141/HAVERQ!F$128) -> 104.48933 | DN25: =100*(HAVERQ!G141/HAVERQ!G$128) -> 94.024979 | DO25: =100*(HAVERQ!H141/HAVERQ!H$128) -> 99.928104 | DP25: 100 | DR25: 2023 | DS25: =HAVERQ!D141-HAVERQ!D$128 -> 3198 | DT25: =HAVERQ!E141-HAVERQ!E$128 -> 2776 | DU25: =HAVERQ!F141-HAVERQ!F$128 -> 1138 | DV25: =HAVERQ!G141-HAVERQ!G$128 -> -2215 | DW25: =HAVERQ!H141-HAVERQ!H$128 -> -19 | DX25: =HAVERQ!C141-HAVERQ!C$128 -> 5145 | DZ25: 2005 | EA25: =MIN(EM25:EO25) -> 0.76376657 | EB25: =+EF25-EA25 -> 0.22111465 | EC25: =100*((EJ29/EJ25)-1) -> -0.92579505 | ED25: 0 | EF25: =MAX(EM25:EO25) -> 0.98488122 | EG25: =AVERAGE(EM25:EO25) -> 0.90008821 | EI25: 2004 | EJ25: ='IPNR ex BNFL'!I33 -> 42450 | EM25: =(ER25-ER$2)/ER$3 -> 0.76376657 | EN25: =(ES25-ES$2)/ES$3 -> 0.95161684 | EO25: =(ET25-ET$2)/ET$3 -> 0.98488122 | ER25: =(HAVERQ!W67*$EW$2)+(HAVERQ!X67*$EX$2)/($EW$2+$EX$2) -> 17.155733 | ES25: =(HAVERQ!AB67*$EW$2)+(HAVERQ!AC67*$EY$2)+(HAVERQ!AD67*$EZ$2)+(HAVERQ!AE67*$FA$2)/($EW$2+$EY$2+$EZ$2+$FA$2) -> 7.1551547 | ET25: =(HAVERQ!Y67*$EW$2)+(HAVERQ!Z67*$EX$2)/($EW$2+$EX$2) -> 2.369405 | FC25: 44075 | FD25: =100*((HAVERM!E256+HAVERM!F256)/(HAVERM!E$249+HAVERM!F$249)) -> 111.60309 | FE25: =100*(HAVERM!E256/HAVERM!E$249) -> 128.86552 | FF25: =100*(HAVERM!F256/HAVERM!F$249) -> 102.13109 | FG25: 100 | FV25: 42948 | FW25: =HAVERM!G219 -> 384008 | FY25: =FW25-FW24 -> 4511 | GC25: 2015 | GD25: =100*(DataQ!W175/DataQ!W$194) -> 94.049733 | GE25: =100*(DataQ!X175/DataQ!X$194) -> 93.016065 | GF25: =100*(DataQ!C175/DataQ!C$194) -> 93.492919 | GH25: 100 | GJ25: 2010 | GK25: =100*(DataQ!Z155/AVERAGE(DataQ!$Z$203:$Z$206)) -> 66.931503 | GL25: =100*(DataQ!C155/AVERAGE(DataQ!$C$203:$C$206)) -> 69.313615 | GM25: 100 | GO25: 2010 | GP25: =100*(DataQ!Z155/DataQ!$Z$194) -> 66.681794 | GQ25: =100*(DataQ!C155/DataQ!$C$194) -> 66.908088 | GR25: 100 | GT25: 2023 | GU25: =HB25 -> 100.78717 | GV25: =MIN(HC25:HH25) -> 97.340523 | GW25: =+GY25-GV25 -> 14.190299 | GX25: 100 | GY25: =MAX(HC25:HH25) -> 111.53082 | HA25: 2023 | HB25: =100*(DataQ!C207/DataQ!C$194) -> 100.78717 | HC25: =100*(DataQ!Q207/DataQ!Q$194) -> 111.53082 | HD25: =100*(DataQ!R207/DataQ!R$194) -> 107.36018 | HE25: =100*(DataQ!S207/DataQ!S$194) -> 97.340523 | HF25: =100*(DataQ!T207/DataQ!T$194) -> 105.76193 | HG25: =100*(DataQ!U207/DataQ!U$194) -> 110.92911 | HH25: =100*(DataQ!V207/DataQ!V$194) -> 102.97877 | HJ25: 2023 | HK25: =HR25 -> 100.78717 | HL25: =MIN(HS25:HX25) -> 97.340523 | HM25: =+HO25-HL25 -> 14.190299 | HN25: 100 | HO25: =MAX(HS25:HX25) -> 111.53082 | HQ25: 2023 | HR25: =100*(DataQ!C207/DataQ!C$194) -> 100.78717 | HS25: =100*(DataQ!Q207/DataQ!Q$194) -> 111.53082 | HT25: =100*(DataQ!R207/DataQ!R$194) -> 107.36018 | HU25: =100*(DataQ!S207/DataQ!S$194) -> 97.340523 | HV25: =100*(DataQ!T207/DataQ!T$194) -> 105.76193 | HW25: =100*(DataQ!U207/DataQ!U$194) -> 110.92911 | HX25: =100*(DataQ!V207/DataQ!V$194) -> 102.97877 | HZ25: 2010 | IA25: =DataA!J44/'Chart Data'!IF25 -> 2.9202697 | IB25: =IB24*(1+$ID$5/100) -> 2.9555521 | IC25: =100*((IA25/IB25)-1) -> -1.1937677 | IF25: =DataA!K44*DataA!L44 -> 925082.02 | IQ25: 2012 | IR25: =HAVERQ!AH96 -> -3.2 | IS25: =100*(('IPNR ex BNFL'!I65/'IPNR ex BNFL'!I61)-1) -> 16.05717 | IT25: 0
B26: =100*((DataQ!C96/DataQ!C92)-1) -> 8.4430174 | C26: =K26 -> 13.64473 | D26: 0 | G26: =100*((AVERAGE(DataQ!C93:C96)/AVERAGE(DataQ!C89:C92))-1) -> 7.040264 | H26: =AVERAGE(K23:K26) -> 12.214819 | I26: 0 | K26: =L26 -> 13.64473 | L26: =100*(HAVERQ!AF30/HAVERQ!AI30) -> 13.64473 | O26: =100*('ONS CVM_SA_(Quarterly)'!B110/'ONS CVM_SA_(Quarterly)'!B$101) -> 115.46407 | P26: =100*('ONS CVM_SA_(Quarterly)'!D110/'ONS CVM_SA_(Quarterly)'!D$101) -> 114.77031 | R26: 100 | AI26: =100*(('ONS CVM_SA_(Quarterly)'!C114-'ONS CVM_SA_(Quarterly)'!C$96)/'ONS CVM_SA_(Quarterly)'!$B$96) -> 6.7764622 | AJ26: =100*(('ONS CVM_SA_(Quarterly)'!D114-'ONS CVM_SA_(Quarterly)'!D$96)/'ONS CVM_SA_(Quarterly)'!$B$96) -> 0.69684163 | AK26: =100*(('ONS CVM_SA_(Quarterly)'!E114-'ONS CVM_SA_(Quarterly)'!E$96)/'ONS CVM_SA_(Quarterly)'!$B$96) -> -5.2182469 | AL26: =100*(('ONS CVM_SA_(Quarterly)'!F114-'ONS CVM_SA_(Quarterly)'!F$96)/'ONS CVM_SA_(Quarterly)'!$B$96) -> -1.495306 | AM26: =100*(('ONS CVM_SA_(Quarterly)'!B114-'ONS CVM_SA_(Quarterly)'!B$96)/'ONS CVM_SA_(Quarterly)'!$B$96) -> 0.41294319 | AP26: =100*(('ONS CVM_SA_(Quarterly)'!C102-AVERAGE('ONS CVM_SA_(Quarterly)'!C$81:C$84))/AVERAGE('ONS CVM_SA_(Quarterly)'!$B$81:$B$84)) -> -5.914839 | AQ26: =100*(('ONS CVM_SA_(Quarterly)'!D102-AVERAGE('ONS CVM_SA_(Quarterly)'!D$81:D$84))/AVERAGE('ONS CVM_SA_(Quarterly)'!$B$81:$B$84)) -> -2.0279332 | AR26: =100*(('ONS CVM_SA_(Quarterly)'!E102-AVERAGE('ONS CVM_SA_(Quarterly)'!E$81:E$84))/AVERAGE('ONS CVM_SA_(Quarterly)'!$B$81:$B$84)) -> -3.2013387 | AS26: =100*(('ONS CVM_SA_(Quarterly)'!F102-AVERAGE('ONS CVM_SA_(Quarterly)'!F$81:F$84))/AVERAGE('ONS CVM_SA_(Quarterly)'!$B$81:$B$84)) -> 5.2568243 | AT26: =100*(('ONS CVM_SA_(Quarterly)'!B102-AVERAGE('ONS CVM_SA_(Quarterly)'!B$81:B$84))/AVERAGE('ONS CVM_SA_(Quarterly)'!$B$81:$B$84)) -> -6.0189706 | AV26: 44105 | AW26: =HAVERM!D257 -> 0.1 | AX26: =HAVERM!B257 -> 2.46 | AY26: =HAVERM!C257 -> 2.12 | BA26: 45170 | BB26: =AX61-AX$39 -> 4.11 | BC26: =AY61-AY$39 -> 1.14 | BF26: 0 | BJ26: =100*(HAVERQ!B142/HAVERQ!B$128) -> 100.25486 | BK26: =100*(HAVERQ!I142/HAVERQ!I$128) -> 114.05313 | BL26: =100*(HAVERQ!J142/HAVERQ!J$128) -> 85.323487 | BM26: =100*(HAVERQ!K142/HAVERQ!K$128) -> 73.871367 | BN26: =100*((HAVERQ!L142+HAVERQ!M142)/(HAVERQ!L$128+HAVERQ!M$128)) -> 99.906603 | BO26: 100 | BR26: =HAVERQ!I142-HAVERQ!I$128 -> 1312 | BS26: =HAVERQ!J142-HAVERQ!J$128 -> -1411 | BT26: =HAVERQ!K142-HAVERQ!K$128 -> -845 | BU26: =(HAVERQ!L142+HAVERQ!M142)-(HAVERQ!L$128+HAVERQ!M$128) -> -37 | BV26: =HAVERQ!N142-HAVERQ!N$128 -> -25 | BW26: =HAVERQ!B142-HAVERQ!B$128 -> 158 | BZ26: =100*((HAVERQ!I146-HAVERQ!I$128)/HAVERQ!$B$128) -> 1.956641 | CA26: =100*((HAVERQ!J146-HAVERQ!J$128)/HAVERQ!$B$128) -> 1.2468949 | CB26: =100*((HAVERQ!K146-HAVERQ!K$128)/HAVERQ!$B$128) -> -1.5082105 | CC26: =100*(((HAVERQ!L146+HAVERQ!M146)-(HAVERQ!L$128+HAVERQ!M$128))/HAVERQ!$B$128) -> -3.0680388 | CD26: =CE26-BZ26-CA26-CB26-CC26 -> 1.7856567 | CE26: =100*((HAVERQ!B146-HAVERQ!B$128)/HAVERQ!B$128) -> 0.41294319 | CH26: =HAVERQ!I142 -> 10648 | CI26: =HAVERQ!J142 -> 8203 | CJ26: =HAVERQ!K142 -> 2389 | CK26: =HAVERQ!L142+HAVERQ!M142 -> 39579 | CL26: =HAVERQ!N142 -> 1333 | CO26: =CX26 -> -1977 | CP26: =CY26 -> -30 | CQ26: =CZ26 -> -1185 | CR26: =DA26 -> 2993 | CS26: =DC26 -> 1075 | CT26: =+DB26+DD26+DE26+DF26 -> -227 | CU26: =DG26 -> -37 | CX26: =HAVERQ!L142-HAVERQ!L$128 -> -1977 | CY26: =HAVERQ!O142-HAVERQ!O$128 -> -30 | CZ26: =HAVERQ!P142-HAVERQ!P$128 -> -1185 | DA26: =HAVERQ!Q142-HAVERQ!Q$128 -> 2993 | DB26: =HAVERQ!R142-HAVERQ!R$128 -> 543 | DC26: =HAVERQ!S142-HAVERQ!S$128 -> 1075 | DD26: =HAVERQ!T142-HAVERQ!T$128 -> -467 | DE26: =HAVERQ!U142-HAVERQ!U$128 -> -267 | DF26: =HAVERQ!V142-HAVERQ!V$128 -> -36 | DG26: =(HAVERQ!L142+HAVERQ!M142)-(HAVERQ!L$128+HAVERQ!M$128) -> -37 | DJ26: =100*(HAVERQ!C142/HAVERQ!C$128) -> 103.0305 | DK26: =100*(HAVERQ!D142/HAVERQ!D$128) -> 187.36679 | DL26: =100*(HAVERQ!E142/HAVERQ!E$128) -> 113.75218 | DM26: =100*(HAVERQ!F142/HAVERQ!F$128) -> 100.67458 | DN26: =100*(HAVERQ!G142/HAVERQ!G$128) -> 91.084675 | DO26: =100*(HAVERQ!H142/HAVERQ!H$128) -> 99.894048 | DP26: 100 | DS26: =HAVERQ!D142-HAVERQ!D$128 -> 3935 | DT26: =HAVERQ!E142-HAVERQ!E$128 -> 2283 | DU26: =HAVERQ!F142-HAVERQ!F$128 -> 171 | DV26: =HAVERQ!G142-HAVERQ!G$128 -> -3305 | DW26: =HAVERQ!H142-HAVERQ!H$128 -> -28 | DX26: =HAVERQ!C142-HAVERQ!C$128 -> 3324 | EA26: =MIN(EM26:EO26) -> 0.59313104 | EB26: =+EF26-EA26 -> 0.49622814 | EC26: =100*((EJ30/EJ26)-1) -> 23.182691 | ED26: 0 | EF26: =MAX(EM26:EO26) -> 1.0893592 | EG26: =AVERAGE(EM26:EO26) -> 0.88315089 | EJ26: ='IPNR ex BNFL'!I34 -> 39055 | EM26: =(ER26-ER$2)/ER$3 -> 0.59313104 | EN26: =(ES26-ES$2)/ES$3 -> 1.0893592 | EO26: =(ET26-ET$2)/ET$3 -> 0.96696243 | ER26: =(HAVERQ!W68*$EW$2)+(HAVERQ!X68*$EX$2)/($EW$2+$EX$2) -> 15.155733 | ES26: =(HAVERQ!AB68*$EW$2)+(HAVERQ!AC68*$EY$2)+(HAVERQ!AD68*$EZ$2)+(HAVERQ!AE68*$FA$2)/($EW$2+$EY$2+$EZ$2+$FA$2) -> 9.0934381 | ET26: =(HAVERQ!Y68*$EW$2)+(HAVERQ!Z68*$EX$2)/($EW$2+$EX$2) -> 2.3412627 | FC26: 44105 | FD26: =100*((HAVERM!E257+HAVERM!F257)/(HAVERM!E$249+HAVERM!F$249)) -> 110.41639 | FE26: =100*(HAVERM!E257/HAVERM!E$249) -> 130.04566 | FF26: =100*(HAVERM!F257/HAVERM!F$249) -> 99.6457 | FG26: 100 | FV26: 42979 | FW26: =HAVERM!G220 -> 389067 | FY26: =FW26-FW25 -> 5059 | GD26: =100*(DataQ!W176/DataQ!W$194) -> 94.456971 | GE26: =100*(DataQ!X176/DataQ!X$194) -> 92.979471 | GF26: =100*(DataQ!C176/DataQ!C$194) -> 90.968481 | GH26: 100 | GK26: =100*(DataQ!Z156/AVERAGE(DataQ!$Z$203:$Z$206)) -> 65.925884 | GL26: =100*(DataQ!C156/AVERAGE(DataQ!$C$203:$C$206)) -> 68.275891 | GM26: 100 | GP26: =100*(DataQ!Z156/DataQ!$Z$194) -> 65.679926 | GQ26: =100*(DataQ!C156/DataQ!$C$194) -> 65.906378 | GR26: 100 | GU26: =HB26 -> 100.25486 | GV26: =MIN(HC26:HH26) -> 97.313105 | GW26: =+GY26-GV26 -> 16.870647 | GX26: 100 | GY26: =MAX(HC26:HH26) -> 114.18375 | HB26: =100*(DataQ!C208/DataQ!C$194) -> 100.25486 | HC26: =100*(DataQ!Q208/DataQ!Q$194) -> 114.18375 | HD26: =100*(DataQ!R208/DataQ!R$194) -> 105.16862 | HE26: =100*(DataQ!S208/DataQ!S$194) -> 97.313105 | HF26: =100*(DataQ!T208/DataQ!T$194) -> 106.56415 | HG26: =100*(DataQ!U208/DataQ!U$194) -> 109.7074 | HH26: =100*(DataQ!V208/DataQ!V$194) -> 105.66653 | HK26: =HR26 -> 100.25486 | HL26: =MIN(HS26:HX26) -> 97.313105 | HM26: =+HO26-HL26 -> 16.870647 | HN26: 100 | HO26: =MAX(HS26:HX26) -> 114.18375 | HR26: =100*(DataQ!C208/DataQ!C$194) -> 100.25486 | HS26: =100*(DataQ!Q208/DataQ!Q$194) -> 114.18375 | HT26: =100*(DataQ!R208/DataQ!R$194) -> 105.16862 | HU26: =100*(DataQ!S208/DataQ!S$194) -> 97.313105 | HV26: =100*(DataQ!T208/DataQ!T$194) -> 106.56415 | HW26: =100*(DataQ!U208/DataQ!U$194) -> 109.7074 | HX26: =100*(DataQ!V208/DataQ!V$194) -> 105.66653 | HZ26: 2011 | IA26: =DataA!J45/'Chart Data'!IF26 -> 2.9449111 | IB26: =IB25*(1+$ID$5/100) -> 3.0340685 | IC26: =100*((IA26/IB26)-1) -> -2.9385409 | IF26: =DataA!K45*DataA!L45 -> 927673.5 | IR26: =HAVERQ!AH97 -> -1.6 | IS26: =100*(('IPNR ex BNFL'!I66/'IPNR ex BNFL'!I62)-1) -> 5.0780028 | IT26: 0
B27: =100*((DataQ!C97/DataQ!C93)-1) -> 9.984538 | C27: =K27 -> 12.814855 | D27: 0 | G27: =100*((AVERAGE(DataQ!C94:C97)/AVERAGE(DataQ!C90:C93))-1) -> 7.7770509 | H27: =AVERAGE(K24:K27) -> 12.548872 | I27: 0 | K27: =L27 -> 12.814855 | L27: =100*(HAVERQ!AF31/HAVERQ!AI31) -> 12.814855 | O27: =100*('ONS CVM_SA_(Quarterly)'!B111/'ONS CVM_SA_(Quarterly)'!B$101) -> 112.01605 | P27: =100*('ONS CVM_SA_(Quarterly)'!D111/'ONS CVM_SA_(Quarterly)'!D$101) -> 111.75413 | R27: 100 | AP27: =100*(('ONS CVM_SA_(Quarterly)'!C103-AVERAGE('ONS CVM_SA_(Quarterly)'!C$81:C$84))/AVERAGE('ONS CVM_SA_(Quarterly)'!$B$81:$B$84)) -> -4.5955681 | AQ27: =100*(('ONS CVM_SA_(Quarterly)'!D103-AVERAGE('ONS CVM_SA_(Quarterly)'!D$81:D$84))/AVERAGE('ONS CVM_SA_(Quarterly)'!$B$81:$B$84)) -> -1.154362 | AR27: =100*(('ONS CVM_SA_(Quarterly)'!E103-AVERAGE('ONS CVM_SA_(Quarterly)'!E$81:E$84))/AVERAGE('ONS CVM_SA_(Quarterly)'!$B$81:$B$84)) -> -4.5270925 | AS27: =100*(('ONS CVM_SA_(Quarterly)'!F103-AVERAGE('ONS CVM_SA_(Quarterly)'!F$81:F$84))/AVERAGE('ONS CVM_SA_(Quarterly)'!$B$81:$B$84)) -> 2.7544236 | AT27: =100*(('ONS CVM_SA_(Quarterly)'!B103-AVERAGE('ONS CVM_SA_(Quarterly)'!B$81:B$84))/AVERAGE('ONS CVM_SA_(Quarterly)'!$B$81:$B$84)) -> -7.6218685 | AV27: 44136 | AW27: =HAVERM!D258 -> 0.1 | AX27: =HAVERM!B258 -> 2.45 | AY27: =HAVERM!C258 -> 2.12 | BA27: 45200 | BB27: =AX62-AX$39 -> 4.08 | BC27: =AY62-AY$39 -> 1.2 | BF27: 0 | BJ27: =100*(HAVERQ!B143/HAVERQ!B$128) -> 97.261025 | BK27: =100*(HAVERQ!I143/HAVERQ!I$128) -> 111.78235 | BL27: =100*(HAVERQ!J143/HAVERQ!J$128) -> 84.460162 | BM27: =100*(HAVERQ!K143/HAVERQ!K$128) -> 63.945578 | BN27: =100*((HAVERQ!L143+HAVERQ!M143)/(HAVERQ!L$128+HAVERQ!M$128)) -> 96.774031 | BO27: 100 | BR27: =HAVERQ!I143-HAVERQ!I$128 -> 1100 | BS27: =HAVERQ!J143-HAVERQ!J$128 -> -1494 | BT27: =HAVERQ!K143-HAVERQ!K$128 -> -1166 | BU27: =(HAVERQ!L143+HAVERQ!M143)-(HAVERQ!L$128+HAVERQ!M$128) -> -1278 | BV27: =HAVERQ!N143-HAVERQ!N$128 -> -24 | BW27: =HAVERQ!B143-HAVERQ!B$128 -> -1698 | CH27: =HAVERQ!I143 -> 10436 | CI27: =HAVERQ!J143 -> 8120 | CJ27: =HAVERQ!K143 -> 2068 | CK27: =HAVERQ!L143+HAVERQ!M143 -> 38338 | CL27: =HAVERQ!N143 -> 1334 | CO27: =CX27 -> -2332 | CP27: =CY27 -> 102 | CQ27: =CZ27 -> -1092 | CR27: =DA27 -> -12 | CS27: =DC27 -> 2619 | CT27: =+DB27+DD27+DE27+DF27 -> 123 | CU27: =DG27 -> -1278 | CX27: =HAVERQ!L143-HAVERQ!L$128 -> -2332 | CY27: =HAVERQ!O143-HAVERQ!O$128 -> 102 | CZ27: =HAVERQ!P143-HAVERQ!P$128 -> -1092 | DA27: =HAVERQ!Q143-HAVERQ!Q$128 -> -12 | DB27: =HAVERQ!R143-HAVERQ!R$128 -> 769 | DC27: =HAVERQ!S143-HAVERQ!S$128 -> 2619 | DD27: =HAVERQ!T143-HAVERQ!T$128 -> -109 | DE27: =HAVERQ!U143-HAVERQ!U$128 -> -513 | DF27: =HAVERQ!V143-HAVERQ!V$128 -> -24 | DG27: =(HAVERQ!L143+HAVERQ!M143)-(HAVERQ!L$128+HAVERQ!M$128) -> -1278 | DJ27: =100*(HAVERQ!C143/HAVERQ!C$128) -> 101.28915 | DK27: =100*(HAVERQ!D143/HAVERQ!D$128) -> 175.08881 | DL27: =100*(HAVERQ!E143/HAVERQ!E$128) -> 111.84266 | DM27: =100*(HAVERQ!F143/HAVERQ!F$128) -> 98.859916 | DN27: =100*(HAVERQ!G143/HAVERQ!G$128) -> 89.382536 | DO27: =100*(HAVERQ!H143/HAVERQ!H$128) -> 100.09082 | DP27: 100 | DS27: =HAVERQ!D143-HAVERQ!D$128 -> 3382 | DT27: =HAVERQ!E143-HAVERQ!E$128 -> 1966 | DU27: =HAVERQ!F143-HAVERQ!F$128 -> -289 | DV27: =HAVERQ!G143-HAVERQ!G$128 -> -3936 | DW27: =HAVERQ!H143-HAVERQ!H$128 -> 24 | DX27: =HAVERQ!C143-HAVERQ!C$128 -> 1414 | EA27: =MIN(EM27:EO27) -> 0.22528642 | EB27: =+EF27-EA27 -> 0.61102623 | EC27: =100*((EJ31/EJ27)-1) -> 7.2801567 | ED27: 0 | EF27: =MAX(EM27:EO27) -> 0.83631265 | EG27: =AVERAGE(EM27:EO27) -> 0.61629548 | EJ27: ='IPNR ex BNFL'!I35 -> 41359 | EL27: 2005 | EM27: =(ER27-ER$2)/ER$3 -> 0.22528642 | EN27: =(ES27-ES$2)/ES$3 -> 0.78728738 | EO27: =(ET27-ET$2)/ET$3 -> 0.83631265 | EQ27: 2005 | ER27: =(HAVERQ!W69*$EW$2)+(HAVERQ!X69*$EX$2)/($EW$2+$EX$2) -> 10.844267 | ES27: =(HAVERQ!AB69*$EW$2)+(HAVERQ!AC69*$EY$2)+(HAVERQ!AD69*$EZ$2)+(HAVERQ!AE69*$FA$2)/($EW$2+$EY$2+$EZ$2+$FA$2) -> 4.8427427 | ET27: =(HAVERQ!Y69*$EW$2)+(HAVERQ!Z69*$EX$2)/($EW$2+$EX$2) -> 2.1360716 | FC27: 44136 | FD27: =100*((HAVERM!E258+HAVERM!F258)/(HAVERM!E$249+HAVERM!F$249)) -> 110.54923 | FE27: =100*(HAVERM!E258/HAVERM!E$249) -> 131.10618 | FF27: =100*(HAVERM!F258/HAVERM!F$249) -> 99.269522 | FG27: 100 | FV27: 43009 | FW27: =HAVERM!G221 -> 390045 | FY27: =FW27-FW26 -> 978 | GD27: =100*(DataQ!W177/DataQ!W$194) -> 94.00538 | GE27: =100*(DataQ!X177/DataQ!X$194) -> 92.536685 | GF27: =100*(DataQ!C177/DataQ!C$194) -> 91.150757 | GH27: 100 | GK27: =100*(DataQ!Z157/AVERAGE(DataQ!$Z$203:$Z$206)) -> 68.874416 | GL27: =100*(DataQ!C157/AVERAGE(DataQ!$C$203:$C$206)) -> 71.348958 | GM27: 100 | GP27: =100*(DataQ!Z157/DataQ!$Z$194) -> 68.617458 | GQ27: =100*(DataQ!C157/DataQ!$C$194) -> 68.872794 | GR27: 100 | GU27: =HB27 -> 97.261025 | GV27: =MIN(HC27:HH27) -> 97.002376 | GW27: =+GY27-GV27 -> 17.494476 | GX27: 100 | GY27: =MAX(HC27:HH27) -> 114.49685 | HB27: =100*(DataQ!C209/DataQ!C$194) -> 97.261025 | HC27: =100*(DataQ!Q209/DataQ!Q$194) -> 114.49685 | HD27: =100*(DataQ!R209/DataQ!R$194) -> 105 | HE27: =100*(DataQ!S209/DataQ!S$194) -> 97.002376 | HF27: =100*(DataQ!T209/DataQ!T$194) -> 107.17297 | HG27: =100*(DataQ!U209/DataQ!U$194) -> 108.44422 | HH27: =100*(DataQ!V209/DataQ!V$194) -> 101.75562 | HK27: =HR27 -> 97.261025 | HL27: =MIN(HS27:HX27) -> 97.002376 | HM27: =+HO27-HL27 -> 17.494476 | HN27: 100 | HO27: =MAX(HS27:HX27) -> 114.49685 | HR27: =100*(DataQ!C209/DataQ!C$194) -> 97.261025 | HS27: =100*(DataQ!Q209/DataQ!Q$194) -> 114.49685 | HT27: =100*(DataQ!R209/DataQ!R$194) -> 105 | HU27: =100*(DataQ!S209/DataQ!S$194) -> 97.002376 | HV27: =100*(DataQ!T209/DataQ!T$194) -> 107.17297 | HW27: =100*(DataQ!U209/DataQ!U$194) -> 108.44422 | HX27: =100*(DataQ!V209/DataQ!V$194) -> 101.75562 | HZ27: 2012 | IA27: =DataA!J46/'Chart Data'!IF27 -> 2.9245831 | IB27: =IB26*(1+$ID$5/100) -> 3.1146706 | IC27: =100*((IA27/IB27)-1) -> -6.1029751 | IF27: =DataA!K46*DataA!L46 -> 945640.09 | IR27: =HAVERQ!AH98 -> -1.3 | IS27: =100*(('IPNR ex BNFL'!I67/'IPNR ex BNFL'!I63)-1) -> 2.2307326 | IT27: 0
B28: =100*((DataQ!C98/DataQ!C94)-1) -> 8.2464925 | C28: =K28 -> 13.047839 | D28: 0 | G28: =100*((AVERAGE(DataQ!C95:C98)/AVERAGE(DataQ!C91:C94))-1) -> 7.7539358 | H28: =AVERAGE(K25:K28) -> 12.956249 | I28: 0 | K28: =L28 -> 13.047839 | L28: =100*(HAVERQ!AF32/HAVERQ!AI32) -> 13.047839 | O28: =100*('ONS CVM_SA_(Quarterly)'!B112/'ONS CVM_SA_(Quarterly)'!B$101) -> 113.36293 | P28: =100*('ONS CVM_SA_(Quarterly)'!D112/'ONS CVM_SA_(Quarterly)'!D$101) -> 110.24195 | R28: 100 | AP28: =100*(('ONS CVM_SA_(Quarterly)'!C104-AVERAGE('ONS CVM_SA_(Quarterly)'!C$81:C$84))/AVERAGE('ONS CVM_SA_(Quarterly)'!$B$81:$B$84)) -> -3.3378849 | AQ28: =100*(('ONS CVM_SA_(Quarterly)'!D104-AVERAGE('ONS CVM_SA_(Quarterly)'!D$81:D$84))/AVERAGE('ONS CVM_SA_(Quarterly)'!$B$81:$B$84)) -> -2.040899 | AR28: =100*(('ONS CVM_SA_(Quarterly)'!E104-AVERAGE('ONS CVM_SA_(Quarterly)'!E$81:E$84))/AVERAGE('ONS CVM_SA_(Quarterly)'!$B$81:$B$84)) -> -4.8868936 | AS28: =100*(('ONS CVM_SA_(Quarterly)'!F104-AVERAGE('ONS CVM_SA_(Quarterly)'!F$81:F$84))/AVERAGE('ONS CVM_SA_(Quarterly)'!$B$81:$B$84)) -> 2.8792195 | AT28: =100*(('ONS CVM_SA_(Quarterly)'!B104-AVERAGE('ONS CVM_SA_(Quarterly)'!B$81:B$84))/AVERAGE('ONS CVM_SA_(Quarterly)'!$B$81:$B$84)) -> -7.3301378 | AV28: 44166 | AW28: =HAVERM!D259 -> 0.1 | AX28: =HAVERM!B259 -> 2.45 | AY28: =HAVERM!C259 -> 2.12 | BA28: 45231 | BB28: =AX63-AX$39 -> 4.1 | BC28: =AY63-AY$39 -> 1.26 | BF28: 0 | BJ28: =100*(HAVERQ!B144/HAVERQ!B$128) -> 98.430493 | BK28: =100*(HAVERQ!I144/HAVERQ!I$128) -> 111.18252 | BL28: =100*(HAVERQ!J144/HAVERQ!J$128) -> 91.605991 | BM28: =100*(HAVERQ!K144/HAVERQ!K$128) -> 66.141002 | BN28: =100*((HAVERQ!L144+HAVERQ!M144)/(HAVERQ!L$128+HAVERQ!M$128)) -> 96.897718 | BO28: 100 | BR28: =HAVERQ!I144-HAVERQ!I$128 -> 1044 | BS28: =HAVERQ!J144-HAVERQ!J$128 -> -807 | BT28: =HAVERQ!K144-HAVERQ!K$128 -> -1095 | BU28: =(HAVERQ!L144+HAVERQ!M144)-(HAVERQ!L$128+HAVERQ!M$128) -> -1229 | BV28: =HAVERQ!N144-HAVERQ!N$128 -> -50 | BW28: =HAVERQ!B144-HAVERQ!B$128 -> -973 | CH28: =HAVERQ!I144 -> 10380 | CI28: =HAVERQ!J144 -> 8807 | CJ28: =HAVERQ!K144 -> 2139 | CK28: =HAVERQ!L144+HAVERQ!M144 -> 38387 | CL28: =HAVERQ!N144 -> 1308 | CO28: =CX28 -> -2649 | CP28: =CY28 -> -127 | CQ28: =CZ28 -> -1506 | CR28: =DA28 -> 1191 | CS28: =DC28 -> 2888 | CT28: =+DB28+DD28+DE28+DF28 -> -340 | CU28: =DG28 -> -1229 | CX28: =HAVERQ!L144-HAVERQ!L$128 -> -2649 | CY28: =HAVERQ!O144-HAVERQ!O$128 -> -127 | CZ28: =HAVERQ!P144-HAVERQ!P$128 -> -1506 | DA28: =HAVERQ!Q144-HAVERQ!Q$128 -> 1191 | DB28: =HAVERQ!R144-HAVERQ!R$128 -> 274 | DC28: =HAVERQ!S144-HAVERQ!S$128 -> 2888 | DD28: =HAVERQ!T144-HAVERQ!T$128 -> -317 | DE28: =HAVERQ!U144-HAVERQ!U$128 -> -401 | DF28: =HAVERQ!V144-HAVERQ!V$128 -> 104 | DG28: =(HAVERQ!L144+HAVERQ!M144)-(HAVERQ!L$128+HAVERQ!M$128) -> -1229 | DJ28: =100*(HAVERQ!C144/HAVERQ!C$128) -> 101.96563 | DK28: =100*(HAVERQ!D144/HAVERQ!D$128) -> 180.72824 | DL28: =100*(HAVERQ!E144/HAVERQ!E$128) -> 114.24613 | DM28: =100*(HAVERQ!F144/HAVERQ!F$128) -> 97.865794 | DN28: =100*(HAVERQ!G144/HAVERQ!G$128) -> 90.998355 | DO28: =100*(HAVERQ!H144/HAVERQ!H$128) -> 99.114542 | DP28: 100 | DS28: =HAVERQ!D144-HAVERQ!D$128 -> 3636 | DT28: =HAVERQ!E144-HAVERQ!E$128 -> 2365 | DU28: =HAVERQ!F144-HAVERQ!F$128 -> -541 | DV28: =HAVERQ!G144-HAVERQ!G$128 -> -3337 | DW28: =HAVERQ!H144-HAVERQ!H$128 -> -234 | DX28: =HAVERQ!C144-HAVERQ!C$128 -> 2156 | EA28: =MIN(EM28:EO28) -> -1.2643556 | EB28: =+EF28-EA28 -> 2.1119764 | EC28: =100*((EJ32/EJ28)-1) -> 4.4453382 | ED28: 0 | EF28: =MAX(EM28:EO28) -> 0.84762086 | EG28: =AVERAGE(EM28:EO28) -> -0.14027601 | EJ28: ='IPNR ex BNFL'!I36 -> 42269 | EM28: =(ER28-ER$2)/ER$3 -> -0.0040933004 | EN28: =(ES28-ES$2)/ES$3 -> -1.2643556 | EO28: =(ET28-ET$2)/ET$3 -> 0.84762086 | ER28: =(HAVERQ!W70*$EW$2)+(HAVERQ!X70*$EX$2)/($EW$2+$EX$2) -> 8.1557329 | ES28: =(HAVERQ!AB70*$EW$2)+(HAVERQ!AC70*$EY$2)+(HAVERQ!AD70*$EZ$2)+(HAVERQ!AE70*$FA$2)/($EW$2+$EY$2+$EZ$2+$FA$2) -> -24.027577 | ET28: =(HAVERQ!Y70*$EW$2)+(HAVERQ!Z70*$EX$2)/($EW$2+$EX$2) -> 2.1538317 | FC28: 44166 | FD28: =100*((HAVERM!E259+HAVERM!F259)/(HAVERM!E$249+HAVERM!F$249)) -> 111.13073 | FE28: =100*(HAVERM!E259/HAVERM!E$249) -> 131.79497 | FF28: =100*(HAVERM!F259/HAVERM!F$249) -> 99.792149 | FG28: 100 | FV28: 43040 | FW28: =HAVERM!G222 -> 393924 | FY28: =FW28-FW27 -> 3879 | GD28: =100*(DataQ!W178/DataQ!W$194) -> 96.315749 | GE28: =100*(DataQ!X178/DataQ!X$194) -> 97.842793 | GF28: =100*(DataQ!C178/DataQ!C$194) -> 97.167468 | GH28: 100 | GK28: =100*(DataQ!Z158/AVERAGE(DataQ!$Z$203:$Z$206)) -> 73.431238 | GL28: =100*(DataQ!C158/AVERAGE(DataQ!$C$203:$C$206)) -> 76.057986 | GM28: 100 | GP28: =100*(DataQ!Z158/DataQ!$Z$194) -> 73.157279 | GQ28: =100*(DataQ!C158/DataQ!$C$194) -> 73.418395 | GR28: 100 | GU28: =HB28 -> 98.430493 | GV28: =MIN(HC28:HH28) -> 95.658929 | GW28: =+GY28-GV28 -> 19.915256 | GX28: 100 | GY28: =MAX(HC28:HH28) -> 115.57418 | HB28: =100*(DataQ!C210/DataQ!C$194) -> 98.430493 | HC28: =100*(DataQ!Q210/DataQ!Q$194) -> 115.57418 | HD28: =100*(DataQ!R210/DataQ!R$194) -> 107.19719 | HE28: =100*(DataQ!S210/DataQ!S$194) -> 95.658929 | HF28: =100*(DataQ!T210/DataQ!T$194) -> 106.16119 | HG28: =100*(DataQ!U210/DataQ!U$194) -> 107.85091 | HH28: =100*(DataQ!V210/DataQ!V$194) -> 99.011569 | HK28: =HR28 -> 98.430493 | HL28: =MIN(HS28:HX28) -> 95.658929 | HM28: =+HO28-HL28 -> 19.915256 | HN28: 100 | HO28: =MAX(HS28:HX28) -> 115.57418 | HR28: =100*(DataQ!C210/DataQ!C$194) -> 98.430493 | HS28: =100*(DataQ!Q210/DataQ!Q$194) -> 115.57418 | HT28: =100*(DataQ!R210/DataQ!R$194) -> 107.19719 | HU28: =100*(DataQ!S210/DataQ!S$194) -> 95.658929 | HV28: =100*(DataQ!T210/DataQ!T$194) -> 106.16119 | HW28: =100*(DataQ!U210/DataQ!U$194) -> 107.85091 | HX28: =100*(DataQ!V210/DataQ!V$194) -> 99.011569 | HZ28: 2013 | IA28: =DataA!J47/'Chart Data'!IF28 -> 2.9082166 | IB28: =IB27*(1+$ID$5/100) -> 3.1974141 | IC28: =100*((IA28/IB28)-1) -> -9.0447306 | IF28: =DataA!K47*DataA!L47 -> 964039.96 | IR28: =HAVERQ!AH99 -> -6.5 | IS28: =100*(('IPNR ex BNFL'!I68/'IPNR ex BNFL'!I64)-1) -> 5.5221329 | IT28: 0
A29: 1996 | B29: =100*((DataQ!C99/DataQ!C95)-1) -> 13.673446 | C29: =K29 -> 11.515138 | D29: 0 | F29: 1996 | G29: =100*((AVERAGE(DataQ!C96:C99)/AVERAGE(DataQ!C92:C95))-1) -> 10.096914 | H29: =AVERAGE(K26:K29) -> 12.75564 | I29: 0 | K29: =L29 -> 11.515138 | L29: =100*(HAVERQ!AF33/HAVERQ!AI33) -> 11.515138 | N29: 2024 | O29: =100*('ONS CVM_SA_(Quarterly)'!B113/'ONS CVM_SA_(Quarterly)'!B$101) -> 114.0113 | P29: =100*('ONS CVM_SA_(Quarterly)'!D113/'ONS CVM_SA_(Quarterly)'!D$101) -> 115.60405 | R29: 100 | AO29: 2022 | AP29: =100*(('ONS CVM_SA_(Quarterly)'!C105-AVERAGE('ONS CVM_SA_(Quarterly)'!C$81:C$84))/AVERAGE('ONS CVM_SA_(Quarterly)'!$B$81:$B$84)) -> -4.3459763 | AQ29: =100*(('ONS CVM_SA_(Quarterly)'!D105-AVERAGE('ONS CVM_SA_(Quarterly)'!D$81:D$84))/AVERAGE('ONS CVM_SA_(Quarterly)'!$B$81:$B$84)) -> 0.056320223 | AR29: =100*(('ONS CVM_SA_(Quarterly)'!E105-AVERAGE('ONS CVM_SA_(Quarterly)'!E$81:E$84))/AVERAGE('ONS CVM_SA_(Quarterly)'!$B$81:$B$84)) -> -3.1446133 | AS29: =100*(('ONS CVM_SA_(Quarterly)'!F105-AVERAGE('ONS CVM_SA_(Quarterly)'!F$81:F$84))/AVERAGE('ONS CVM_SA_(Quarterly)'!$B$81:$B$84)) -> 2.7074225 | AT29: =100*(('ONS CVM_SA_(Quarterly)'!B105-AVERAGE('ONS CVM_SA_(Quarterly)'!B$81:B$84))/AVERAGE('ONS CVM_SA_(Quarterly)'!$B$81:$B$84)) -> -4.5360065 | AV29: 44197 | AW29: =HAVERM!D260 -> 0.1 | AX29: =HAVERM!B260 -> 2.41 | AY29: =HAVERM!C260 -> 2.09 | BA29: 45261 | BB29: =AX64-AX$39 -> 4.12 | BC29: =AY64-AY$39 -> 1.35 | BF29: 0 | BI29: 2024 | BJ29: =100*(HAVERQ!B145/HAVERQ!B$128) -> 98.993451 | BK29: =100*(HAVERQ!I145/HAVERQ!I$128) -> 112.26435 | BL29: =100*(HAVERQ!J145/HAVERQ!J$128) -> 91.564385 | BM29: =100*(HAVERQ!K145/HAVERQ!K$128) -> 67.254174 | BN29: =100*((HAVERQ!L145+HAVERQ!M145)/(HAVERQ!L$128+HAVERQ!M$128)) -> 97.440428 | BO29: 100 | BQ29: 2024 | BR29: =HAVERQ!I145-HAVERQ!I$128 -> 1145 | BS29: =HAVERQ!J145-HAVERQ!J$128 -> -811 | BT29: =HAVERQ!K145-HAVERQ!K$128 -> -1059 | BU29: =(HAVERQ!L145+HAVERQ!M145)-(HAVERQ!L$128+HAVERQ!M$128) -> -1014 | BV29: =HAVERQ!N145-HAVERQ!N$128 -> -49 | BW29: =HAVERQ!B145-HAVERQ!B$128 -> -624 | CG29: 2024 | CH29: =HAVERQ!I145 -> 10481 | CI29: =HAVERQ!J145 -> 8803 | CJ29: =HAVERQ!K145 -> 2175 | CK29: =HAVERQ!L145+HAVERQ!M145 -> 38602 | CL29: =HAVERQ!N145 -> 1309 | CN29: 2024 | CO29: =CX29 -> -2447 | CP29: =CY29 -> 132 | CQ29: =CZ29 -> -1116 | CR29: =DA29 -> -264 | CS29: =DC29 -> 2685 | CT29: =+DB29+DD29+DE29+DF29 -> 682 | CU29: =DG29 -> -1014 | CW29: 2024 | CX29: =HAVERQ!L145-HAVERQ!L$128 -> -2447 | CY29: =HAVERQ!O145-HAVERQ!O$128 -> 132 | CZ29: =HAVERQ!P145-HAVERQ!P$128 -> -1116 | DA29: =HAVERQ!Q145-HAVERQ!Q$128 -> -264 | DB29: =HAVERQ!R145-HAVERQ!R$128 -> 909 | DC29: =HAVERQ!S145-HAVERQ!S$128 -> 2685 | DD29: =HAVERQ!T145-HAVERQ!T$128 -> 247 | DE29: =HAVERQ!U145-HAVERQ!U$128 -> -558 | DF29: =HAVERQ!V145-HAVERQ!V$128 -> 84 | DG29: =(HAVERQ!L145+HAVERQ!M145)-(HAVERQ!L$128+HAVERQ!M$128) -> -1014 | DI29: 2024 | DJ29: =100*(HAVERQ!C145/HAVERQ!C$128) -> 103.18549 | DK29: =100*(HAVERQ!D145/HAVERQ!D$128) -> 177.46448 | DL29: =100*(HAVERQ!E145/HAVERQ!E$128) -> 117.4869 | DM29: =100*(HAVERQ!F145/HAVERQ!F$128) -> 102.89163 | DN29: =100*(HAVERQ!G145/HAVERQ!G$128) -> 91.53786 | DO29: =100*(HAVERQ!H145/HAVERQ!H$128) -> 97.120369 | DP29: 100 | DR29: 2024 | DS29: =HAVERQ!D145-HAVERQ!D$128 -> 3489 | DT29: =HAVERQ!E145-HAVERQ!E$128 -> 2903 | DU29: =HAVERQ!F145-HAVERQ!F$128 -> 733 | DV29: =HAVERQ!G145-HAVERQ!G$128 -> -3137 | DW29: =HAVERQ!H145-HAVERQ!H$128 -> -761 | DX29: =HAVERQ!C145-HAVERQ!C$128 -> 3494 | DZ29: 2006 | EA29: =MIN(EM29:EO29) -> -0.94643812 | EB29: =+EF29-EA29 -> 1.4167232 | EC29: =100*((EJ33/EJ29)-1) -> 10.326462 | ED29: 0 | EF29: =MAX(EM29:EO29) -> 0.47028503 | EG29: =AVERAGE(EM29:EO29) -> -0.20810278 | EI29: 2005 | EJ29: ='IPNR ex BNFL'!I37 -> 42057 | EM29: =(ER29-ER$2)/ER$3 -> -0.14815526 | EN29: =(ES29-ES$2)/ES$3 -> -0.94643812 | EO29: =(ET29-ET$2)/ET$3 -> 0.47028503 | ER29: =(HAVERQ!W71*$EW$2)+(HAVERQ!X71*$EX$2)/($EW$2+$EX$2) -> 6.4671988 | ES29: =(HAVERQ!AB71*$EW$2)+(HAVERQ!AC71*$EY$2)+(HAVERQ!AD71*$EZ$2)+(HAVERQ!AE71*$FA$2)/($EW$2+$EY$2+$EZ$2+$FA$2) -> -19.553904 | ET29: =(HAVERQ!Y71*$EW$2)+(HAVERQ!Z71*$EX$2)/($EW$2+$EX$2) -> 1.5612095 | FC29: 44197 | FD29: =100*((HAVERM!E260+HAVERM!F260)/(HAVERM!E$249+HAVERM!F$249)) -> 110.51323 | FE29: =100*(HAVERM!E260/HAVERM!E$249) -> 132.17056 | FF29: =100*(HAVERM!F260/HAVERM!F$249) -> 98.629736 | FG29: 100 | FV29: 43070 | FW29: =HAVERM!G223 -> 392951 | FY29: =FW29-FW28 -> -973 | GC29: 2016 | GD29: =100*(DataQ!W179/DataQ!W$194) -> 97.722936 | GE29: =100*(DataQ!X179/DataQ!X$194) -> 98.409997 | GF29: =100*(DataQ!C179/DataQ!C$194) -> 99.499952 | GH29: 100 | GJ29: 2011 | GK29: =100*(DataQ!Z159/AVERAGE(DataQ!$Z$203:$Z$206)) -> 68.326055 | GL29: =100*(DataQ!C159/AVERAGE(DataQ!$C$203:$C$206)) -> 70.735681 | GM29: 100 | GO29: 2011 | GP29: =100*(DataQ!Z159/DataQ!$Z$194) -> 68.071143 | GQ29: =100*(DataQ!C159/DataQ!$C$194) -> 68.280801 | GR29: 100 | GT29: 2024 | GU29: =HB29 -> 98.993451 | GV29: =MIN(HC29:HH29) -> 95.110583 | GW29: =+GY29-GV29 -> 21.7463 | GX29: 100 | GY29: =MAX(HC29:HH29) -> 116.85688 | HA29: 2024 | HB29: =100*(DataQ!C211/DataQ!C$194) -> 98.993451 | HC29: =100*(DataQ!Q211/DataQ!Q$194) -> 116.85688 | HD29: =100*(DataQ!R211/DataQ!R$194) -> 106.68709 | HE29: =100*(DataQ!S211/DataQ!S$194) -> 95.110583 | HF29: =100*(DataQ!T211/DataQ!T$194) -> 105.84376 | HG29: =100*(DataQ!U211/DataQ!U$194) -> 110.43295 | HH29: =100*(DataQ!V211/DataQ!V$194) -> 99.857266 | HJ29: 2024 | HK29: =HR29 -> 98.993451 | HL29: =MIN(HS29:HX29) -> 95.110583 | HM29: =+HO29-HL29 -> 21.7463 | HN29: 100 | HO29: =MAX(HS29:HX29) -> 116.85688 | HQ29: 2024 | HR29: =100*(DataQ!C211/DataQ!C$194) -> 98.993451 | HS29: =100*(DataQ!Q211/DataQ!Q$194) -> 116.85688 | HT29: =100*(DataQ!R211/DataQ!R$194) -> 106.68709 | HU29: =100*(DataQ!S211/DataQ!S$194) -> 95.110583 | HV29: =100*(DataQ!T211/DataQ!T$194) -> 105.84376 | HW29: =100*(DataQ!U211/DataQ!U$194) -> 110.43295 | HX29: =100*(DataQ!V211/DataQ!V$194) -> 99.857266 | HZ29: 2014 | IA29: =DataA!J48/'Chart Data'!IF29 -> 2.882371 | IB29: =IB28*(1+$ID$5/100) -> 3.2823556 | IC29: =100*((IA29/IB29)-1) -> -12.185903 | IF29: =DataA!K48*DataA!L48 -> 990780.86 | IQ29: 2013 | IR29: =HAVERQ!AH100 -> -0.9 | IS29: =100*(('IPNR ex BNFL'!I69/'IPNR ex BNFL'!I65)-1) -> -1.1968978 | IT29: 0
B30: =100*((DataQ!C100/DataQ!C96)-1) -> 13.002552 | C30: =K30 -> 11.161098 | D30: 0 | G30: =100*((AVERAGE(DataQ!C97:C100)/AVERAGE(DataQ!C93:C96))-1) -> 11.231647 | H30: =AVERAGE(K27:K30) -> 12.134732 | I30: 0 | K30: =L30 -> 11.161098 | L30: =100*(HAVERQ!AF34/HAVERQ!AI34) -> 11.161098 | O30: =100*('ONS CVM_SA_(Quarterly)'!B114/'ONS CVM_SA_(Quarterly)'!B$101) -> 115.64613 | P30: =100*('ONS CVM_SA_(Quarterly)'!D114/'ONS CVM_SA_(Quarterly)'!D$101) -> 108.03498 | R30: 100 | AP30: =100*(('ONS CVM_SA_(Quarterly)'!C106-AVERAGE('ONS CVM_SA_(Quarterly)'!C$81:C$84))/AVERAGE('ONS CVM_SA_(Quarterly)'!$B$81:$B$84)) -> -0.86627796 | AQ30: =100*(('ONS CVM_SA_(Quarterly)'!D106-AVERAGE('ONS CVM_SA_(Quarterly)'!D$81:D$84))/AVERAGE('ONS CVM_SA_(Quarterly)'!$B$81:$B$84)) -> 0.75647379 | AR30: =100*(('ONS CVM_SA_(Quarterly)'!E106-AVERAGE('ONS CVM_SA_(Quarterly)'!E$81:E$84))/AVERAGE('ONS CVM_SA_(Quarterly)'!$B$81:$B$84)) -> -4.139739 | AS30: =100*(('ONS CVM_SA_(Quarterly)'!F106-AVERAGE('ONS CVM_SA_(Quarterly)'!F$81:F$84))/AVERAGE('ONS CVM_SA_(Quarterly)'!$B$81:$B$84)) -> 1.8451964 | AT30: =100*(('ONS CVM_SA_(Quarterly)'!B106-AVERAGE('ONS CVM_SA_(Quarterly)'!B$81:B$84))/AVERAGE('ONS CVM_SA_(Quarterly)'!$B$81:$B$84)) -> -2.2183685 | AV30: 44228 | AW30: =HAVERM!D261 -> 0.1 | AX30: =HAVERM!B261 -> 2.43 | AY30: =HAVERM!C261 -> 2.09 | BA30: 45292 | BB30: =AX65-AX$39 -> 4.14 | BC30: =AY65-AY$39 -> 1.4 | BF30: 0 | BJ30: =100*(HAVERQ!B146/HAVERQ!B$128) -> 100.41294 | BK30: =100*(HAVERQ!I146/HAVERQ!I$128) -> 112.99272 | BL30: =100*(HAVERQ!J146/HAVERQ!J$128) -> 108.04036 | BM30: =100*(HAVERQ!K146/HAVERQ!K$128) -> 71.088435 | BN30: =100*((HAVERQ!L146+HAVERQ!M146)/(HAVERQ!L$128+HAVERQ!M$128)) -> 95.19891 | BO30: 100 | BR30: =HAVERQ!I146-HAVERQ!I$128 -> 1213 | BS30: =HAVERQ!J146-HAVERQ!J$128 -> 773 | BT30: =HAVERQ!K146-HAVERQ!K$128 -> -935 | BU30: =(HAVERQ!L146+HAVERQ!M146)-(HAVERQ!L$128+HAVERQ!M$128) -> -1902 | BV30: =HAVERQ!N146-HAVERQ!N$128 -> -57 | BW30: =HAVERQ!B146-HAVERQ!B$128 -> 256 | CH30: =HAVERQ!I146 -> 10549 | CI30: =HAVERQ!J146 -> 10387 | CJ30: =HAVERQ!K146 -> 2299 | CK30: =HAVERQ!L146+HAVERQ!M146 -> 37714 | CL30: =HAVERQ!N146 -> 1301 | CO30: =CX30 -> -2499 | CP30: =CY30 -> 144 | CQ30: =CZ30 -> -1406 | CR30: =DA30 -> 2393 | CS30: =DC30 -> 1319 | CT30: =+DB30+DD30+DE30+DF30 -> -1167 | CU30: =DG30 -> -1902 | CX30: =HAVERQ!L146-HAVERQ!L$128 -> -2499 | CY30: =HAVERQ!O146-HAVERQ!O$128 -> 144 | CZ30: =HAVERQ!P146-HAVERQ!P$128 -> -1406 | DA30: =HAVERQ!Q146-HAVERQ!Q$128 -> 2393 | DB30: =HAVERQ!R146-HAVERQ!R$128 -> -90 | DC30: =HAVERQ!S146-HAVERQ!S$128 -> 1319 | DD30: =HAVERQ!T146-HAVERQ!T$128 -> -332 | DE30: =HAVERQ!U146-HAVERQ!U$128 -> -587 | DF30: =HAVERQ!V146-HAVERQ!V$128 -> -158 | DG30: =(HAVERQ!L146+HAVERQ!M146)-(HAVERQ!L$128+HAVERQ!M$128) -> -1902 | DJ30: =100*(HAVERQ!C146/HAVERQ!C$128) -> 103.78174 | DK30: =100*(HAVERQ!D146/HAVERQ!D$128) -> 192.98401 | DL30: =100*(HAVERQ!E146/HAVERQ!E$128) -> 110.55358 | DM30: =100*(HAVERQ!F146/HAVERQ!F$128) -> 99.846148 | DN30: =100*(HAVERQ!G146/HAVERQ!G$128) -> 94.564484 | DO30: =100*(HAVERQ!H146/HAVERQ!H$128) -> 99.98108 | DP30: 100 | DS30: =HAVERQ!D146-HAVERQ!D$128 -> 4188 | DT30: =HAVERQ!E146-HAVERQ!E$128 -> 1752 | DU30: =HAVERQ!F146-HAVERQ!F$128 -> -39 | DV30: =HAVERQ!G146-HAVERQ!G$128 -> -2015 | DW30: =HAVERQ!H146-HAVERQ!H$128 -> -5 | DX30: =HAVERQ!C146-HAVERQ!C$128 -> 4148 | EA30: =MIN(EM30:EO30) -> -1.3084076 | EB30: =+EF30-EA30 -> 1.5499253 | EC30: =100*((EJ34/EJ30)-1) -> -7.3146397 | ED30: 0 | EF30: =MAX(EM30:EO30) -> 0.24151777 | EG30: =AVERAGE(EM30:EO30) -> -0.3614233 | EJ30: ='IPNR ex BNFL'!I38 -> 48109 | EM30: =(ER30-ER$2)/ER$3 -> -0.017380086 | EN30: =(ES30-ES$2)/ES$3 -> -1.3084076 | EO30: =(ET30-ET$2)/ET$3 -> 0.24151777 | ER30: =(HAVERQ!W72*$EW$2)+(HAVERQ!X72*$EX$2)/($EW$2+$EX$2) -> 8 | ES30: =(HAVERQ!AB72*$EW$2)+(HAVERQ!AC72*$EY$2)+(HAVERQ!AD72*$EZ$2)+(HAVERQ!AE72*$FA$2)/($EW$2+$EY$2+$EZ$2+$FA$2) -> -24.647468 | ET30: =(HAVERQ!Y72*$EW$2)+(HAVERQ!Z72*$EX$2)/($EW$2+$EX$2) -> 1.2019207 | FC30: 44228 | FD30: =100*((HAVERM!E261+HAVERM!F261)/(HAVERM!E$249+HAVERM!F$249)) -> 110.92862 | FE30: =100*(HAVERM!E261/HAVERM!E$249) -> 132.72108 | FF30: =100*(HAVERM!F261/HAVERM!F$249) -> 98.970978 | FG30: 100 | FV30: 43101 | FW30: =HAVERM!G224 -> 394807 | FY30: =FW30-FW29 -> 1856 | GD30: =100*(DataQ!W180/DataQ!W$194) -> 98.692646 | GE30: =100*(DataQ!X180/DataQ!X$194) -> 99.707249 | GF30: =100*(DataQ!C180/DataQ!C$194) -> 99.201536 | GH30: 100 | GK30: =100*(DataQ!Z160/AVERAGE(DataQ!$Z$203:$Z$206)) -> 72.213633 | GL30: =100*(DataQ!C160/AVERAGE(DataQ!$C$203:$C$206)) -> 74.766261 | GM30: 100 | GP30: =100*(DataQ!Z160/DataQ!$Z$194) -> 71.944217 | GQ30: =100*(DataQ!C160/DataQ!$C$194) -> 72.1715 | GR30: 100 | GU30: =HB30 -> 100.41294 | GV30: =MIN(HC30:HH30) -> 92.478523 | GW30: =+GY30-GV30 -> 25.492726 | GX30: 100 | GY30: =MAX(HC30:HH30) -> 117.97125 | HB30: =100*(DataQ!C212/DataQ!C$194) -> 100.41294 | HC30: =100*(DataQ!Q212/DataQ!Q$194) -> 117.97125 | HD30: =100*(DataQ!R212/DataQ!R$194) -> 107.51435 | HE30: =100*(DataQ!S212/DataQ!S$194) -> 92.478523 | HF30: =100*(DataQ!T212/DataQ!T$194) -> 105.42097 | HG30: =100*(DataQ!U212/DataQ!U$194) -> 110.61275 | HH30: =100*(DataQ!V212/DataQ!V$194) -> 102.02404 | HK30: =HR30 -> 100.41294 | HL30: =MIN(HS30:HX30) -> 92.478523 | HM30: =+HO30-HL30 -> 25.492726 | HN30: 100 | HO30: =MAX(HS30:HX30) -> 117.97125 | HR30: =100*(DataQ!C212/DataQ!C$194) -> 100.41294 | HS30: =100*(DataQ!Q212/DataQ!Q$194) -> 117.97125 | HT30: =100*(DataQ!R212/DataQ!R$194) -> 107.51435 | HU30: =100*(DataQ!S212/DataQ!S$194) -> 92.478523 | HV30: =100*(DataQ!T212/DataQ!T$194) -> 105.42097 | HW30: =100*(DataQ!U212/DataQ!U$194) -> 110.61275 | HX30: =100*(DataQ!V212/DataQ!V$194) -> 102.02404 | HZ30: 2015 | IA30: =DataA!J49/'Chart Data'!IF30 -> 2.9069819 | IB30: =IB29*(1+$ID$5/100) -> 3.3695537 | IC30: =100*((IA30/IB30)-1) -> -13.727985 | IF30: =DataA!K49*DataA!L49 -> 1005195.5 | IR30: =HAVERQ!AH101 -> 3.9 | IS30: =100*(('IPNR ex BNFL'!I70/'IPNR ex BNFL'!I66)-1) -> 5.3090569 | IT30: 0
