Workbook
Name Data: [1]sheet0!$C$2

Sheet Chart Data
A1: Annualised growth in 2025 | J1: Budget deficit in 2025 | S1: Gross government debt in 2025
B2: UK | C2: US | D2: Japan | E2: Germany | F2: France | G2: Italy | H2: Canada | K2: =RANK(K4,$K$4:$Q$4) -> 5 | L2: =RANK(L4,$K$4:$Q$4) -> 7 | M2: =RANK(M4,$K$4:$Q$4) -> 3 | N2: =RANK(N4,$K$4:$Q$4) -> 2 | O2: =RANK(O4,$K$4:$Q$4) -> 6 | P2: =RANK(P4,$K$4:$Q$4) -> 4 | Q2: =RANK(Q4,$K$4:$Q$4) -> 1 | T2: =RANK(T4,$T$4:$Z$4) -> 6 | U2: =RANK(U4,$T$4:$Z$4) -> 3 | V2: =RANK(V4,$T$4:$Z$4) -> 1 | W2: =RANK(W4,$T$4:$Z$4) -> 7 | X2: =RANK(X4,$T$4:$Z$4) -> 4 | Y2: =RANK(Y4,$T$4:$Z$4) -> 2 | Z2: =RANK(Z4,$T$4:$Z$4) -> 5
A3: H1 2025 | B3: =100*((B7/B6)^2-1) -> 1.925908 | C3: =100*((C7/C6)^2-1) -> 1.1703616 | D3: =100*((D7/D6)^2-1) -> 1.1324058 | E3: =100*((E7/E6)^2-1) -> 0.51810504 | F3: =100*((F7/F6)^2-1) -> 0.50566345 | G3: =100*((G7/G6)^2-1) -> 0.74627187 | H3: =100*((H7/H6)^2-1) -> 1.12204 | K3: UK | L3: US | M3: Japan | N3: Germany | O3: France | P3: Italy | Q3: Canada | T3: UK | U3: US | V3: Japan | W3: Germany | X3: France | Y3: Italy | Z3: Canada
A4: H2 2025 | B4: =100*((B8/B7)^2-1) -> 0.64216098 | C4: =100*((C8/C7)^2-1) -> 2.3462452 | D4: =100*((D8/D7)^2-1) -> -0.020202818 | E4: =100*((E8/E7)^2-1) -> -0.092323007 | F4: =100*((F8/F7)^2-1) -> 0.51507841 | G4: =100*((G8/G7)^2-1) -> 0.3049117 | H4: =100*((H8/H7)^2-1) -> -0.24697282 | J4: 2025 | K4: =100*(DataA!I60/DataA!W60) -> -4.5090271 | L4: =100*(DataA!J60/DataA!X60) -> -7.0961317 | M4: =100*(DataA!K60/DataA!Y60) -> -2.9490875 | N4: =100*(DataA!L60/DataA!Z60) -> -2.0656985 | O4: =100*(DataA!M60/DataA!AA60) -> -5.3818188 | P4: =100*(DataA!N60/DataA!AB60) -> -3.0009128 | Q4: =100*(DataA!O60/DataA!AC60) -> -1.5627124 | S4: 2025 | T4: =100*(DataA!P60/DataA!W60) -> 102.50331 | U4: =100*(DataA!Q60/DataA!X60) -> 139.37292 | V4: =100*(DataA!R60/DataA!Y60) -> 217.09153 | W4: =100*(DataA!S60/DataA!Z60) -> 58.229624 | X4: =100*(DataA!T60/DataA!AA60) -> 127.49831 | Y4: =100*(DataA!U60/DataA!AB60) -> 150.0575 | Z4: =100*(DataA!V60/DataA!AC60) -> 107.07335
A6: H2 2024 | B6: =SUM(DataQ!G213:G214) -> 1283962 | C6: =SUM(DataQ!H213:H214) -> 11735.65 | D6: =SUM(DataQ!I213:I214) -> 279556.3 | E6: =SUM(DataQ!J213:J214) -> 1801.19 | F6: =SUM(DataQ!K213:K214) -> 1309.636 | G6: =SUM(DataQ!L213:L214) -> 966.861 | H6: =SUM(DataQ!M213:M214) -> 1218310.6
A7: H1 2025 | B7: =SUM(DataQ!G215:G216) -> 1296267 | C7: =SUM(DataQ!H215:H216) -> 11804.125 | D7: =SUM(DataQ!I215:I216) -> 281134.7 | E7: =SUM(DataQ!J215:J216) -> 1805.85 | F7: =SUM(DataQ!K215:K216) -> 1312.943 | G7: =SUM(DataQ!L215:L216) -> 970.462 | H7: =SUM(DataQ!M215:M216) -> 1225126.5
A8: H2 2025 | B8: =SUM(DataQ!G217:G218) -> 1300422.4 | C8: =SUM(DataQ!H217:H218) -> 11941.799 | D8: =SUM(DataQ!I217:I218) -> 281106.3 | E8: =SUM(DataQ!J217:J218) -> 1805.0162 | F8: =SUM(DataQ!K217:K218) -> 1316.32 | G8: =SUM(DataQ!L217:L218) -> 971.9404 | H8: =SUM(DataQ!M217:M218) -> 1223612.7

Sheet DataA
B1: CY total | P1: CY end | W1: CY total
B2: =DataQ!G1 -> SEP008W.db | C2: =DataQ!H1 -> SEP008W.db | D2: =DataQ!I1 -> SEP008W.db | E2: =DataQ!J1 -> SEP008W.db | F2: =DataQ!K1 -> SEP008W.db | G2: =DataQ!L1 -> SEP008W.db | H2: =DataQ!M1 -> SEP008W.db | I2: =DataQ!N1 -> SEP008W.db | ... AC2: =DataQ!AH1 -> SEP008W.db
B3: =DataQ!G2 -> UK | C3: =DataQ!H2 -> US | D3: =DataQ!I2 -> Japan | E3: =DataQ!J2 -> Germany | F3: =DataQ!K2 -> France | G3: =DataQ!L2 -> Italy | H3: =DataQ!M2 -> Canada | I3: =DataQ!N2 -> UK | ... AC3: =DataQ!AH2 -> Canada
B4: =DataQ!G3 -> GDP | C4: =DataQ!H3 -> GDP | D4: =DataQ!I3 -> GDP | E4: =DataQ!J3 -> GDP | F4: =DataQ!K3 -> GDP | G4: =DataQ!L3 -> GDP | H4: =DataQ!M3 -> GDP | I4: =DataQ!N3 -> GB | ... AC4: =DataQ!AH3 -> GDP!
B5: =DataQ!G4 -> GBR | C5: =DataQ!H4 -> USA | D5: =DataQ!I4 -> JPN | E5: =DataQ!J4 -> DEU | F5: =DataQ!K4 -> FRA | G5: =DataQ!L4 -> ITA | H5: =DataQ!M4 -> CAN | I5: =DataQ!N4 -> GBR | ... AC5: =DataQ!AH4 -> CAN
B6: =DataQ!G5 -> L | C6: =DataQ!H5 -> L | D6: =DataQ!I5 -> L | E6: =DataQ!J5 -> L | F6: =DataQ!K5 -> L | G6: =DataQ!L5 -> L | H6: =DataQ!M5 -> L | I6: =DataQ!N5 -> L | ... AC6: =DataQ!AH5 -> L
B7: =DataQ!G6 -> 202502 | C7: =DataQ!H6 -> 202502 | D7: =DataQ!I6 -> 202502 | E7: =DataQ!J6 -> 202502 | F7: =DataQ!K6 -> 202502 | G7: =DataQ!L6 -> 202502 | H7: =DataQ!M6 -> 202502 | I7: =DataQ!N6 -> 202502 | ... AC7: =DataQ!AH6 -> 202502
A8: 1973 | B8: =SUMIF(DataQ!$B:$B,DataA!$A8,DataQ!G:G) -> 987527 | C8: =SUMIF(DataQ!$B:$B,DataA!$A8,DataQ!H:H) -> 6106.35 | D8: =SUMIF(DataQ!$B:$B,DataA!$A8,DataQ!I:I) -> 211380.51 | E8: =SUMIF(DataQ!$B:$B,DataA!$A8,DataQ!J:J) -> 1556.14 | F8: =SUMIF(DataQ!$B:$B,DataA!$A8,DataQ!K:K) -> 999.15 | G8: =SUMIF(DataQ!$B:$B,DataA!$A8,DataQ!L:L) -> 932.5699 | H8: =SUMIF(DataQ!$B:$B,DataA!$A8,DataQ!M:M) -> 707164.6 | I8: =SUMIF(DataQ!$B:$B,DataA!$A8,DataQ!N:N) -> -2740 | J8: =SUMIF(DataQ!$B:$B,DataA!$A8,DataQ!O:O) -> -44.59125 | K8: =SUMIF(DataQ!$B:$B,DataA!$A8,DataQ!P:P) -> -2130.75 | L8: =SUMIF(DataQ!$B:$B,DataA!$A8,DataQ!Q:Q) -> -23.045528 | M8: =SUMIF(DataQ!$B:$B,DataA!$A8,DataQ!R:R) -> 0.8040001 | N8: =SUMIF(DataQ!$B:$B,DataA!$A8,DataQ!S:S) -> -3.2833435 | O8: =SUMIF(DataQ!$B:$B,DataA!$A8,DataQ!T:T) -> 1605 | P8: =SUMIF(DataQ!$E:$E,DataA!$A8,DataQ!U:U) -> 35969.43 | Q8: =SUMIF(DataQ!$E:$E,DataA!$A8,DataQ!V:V) -> 1158.847 | R8: =SUMIF(DataQ!$E:$E,DataA!$A8,DataQ!W:W) -> 17803 | S8: =SUMIF(DataQ!$E:$E,DataA!$A8,DataQ!X:X) -> 89.06523 | T8: =SUMIF(DataQ!$E:$E,DataA!$A8,DataQ!Y:Y) -> 56.7663 | U8: =SUMIF(DataQ!$E:$E,DataA!$A8,DataQ!Z:Z) -> 36.414 | V8: =SUMIF(DataQ!$E:$E,DataA!$A8,DataQ!AA:AA) -> 64923 | W8: =SUMIF(DataQ!$B:$B,DataA!$A8,DataQ!AB:AB) -> 81793 | X8: =SUMIF(DataQ!$B:$B,DataA!$A8,DataQ!AC:AC) -> 1425.375 | Y8: =SUMIF(DataQ!$B:$B,DataA!$A8,DataQ!AD:AD) -> 115345.45 | Z8: =SUMIF(DataQ!$B:$B,DataA!$A8,DataQ!AE:AE) -> 553.1868 | AA8: =SUMIF(DataQ!$B:$B,DataA!$A8,DataQ!AF:AF) -> 177.825 | AB8: =SUMIF(DataQ!$B:$B,DataA!$A8,DataQ!AG:AG) -> 53.293 | AC8: =SUMIF(DataQ!$B:$B,DataA!$A8,DataQ!AH:AH) -> 132966
A9: 1974 | B9: =SUMIF(DataQ!$B:$B,DataA!$A9,DataQ!G:G) -> 962880 | C9: =SUMIF(DataQ!$B:$B,DataA!$A9,DataQ!H:H) -> 6073.4 | D9: =SUMIF(DataQ!$B:$B,DataA!$A9,DataQ!I:I) -> 209230.97 | E9: =SUMIF(DataQ!$B:$B,DataA!$A9,DataQ!J:J) -> 1571.34 | F9: =SUMIF(DataQ!$B:$B,DataA!$A9,DataQ!K:K) -> 1043.039 | G9: =SUMIF(DataQ!$B:$B,DataA!$A9,DataQ!L:L) -> 981.7783 | H9: =SUMIF(DataQ!$B:$B,DataA!$A9,DataQ!M:M) -> 730909.6 | I9: =SUMIF(DataQ!$B:$B,DataA!$A9,DataQ!N:N) -> -4310 | J9: =SUMIF(DataQ!$B:$B,DataA!$A9,DataQ!O:O) -> -59.765 | K9: =SUMIF(DataQ!$B:$B,DataA!$A9,DataQ!P:P) -> -2482.25 | L9: =SUMIF(DataQ!$B:$B,DataA!$A9,DataQ!Q:Q) -> -36.381582 | M9: =SUMIF(DataQ!$B:$B,DataA!$A9,DataQ!R:R) -> 0.4830001 | N9: =SUMIF(DataQ!$B:$B,DataA!$A9,DataQ!S:S) -> -4.0740696 | O9: =SUMIF(DataQ!$B:$B,DataA!$A9,DataQ!T:T) -> 3052 | P9: =SUMIF(DataQ!$E:$E,DataA!$A9,DataQ!U:U) -> 48829.88 | Q9: =SUMIF(DataQ!$E:$E,DataA!$A9,DataQ!V:V) -> 1251.709 | R9: =SUMIF(DataQ!$E:$E,DataA!$A9,DataQ!W:W) -> 16534 | S9: =SUMIF(DataQ!$E:$E,DataA!$A9,DataQ!X:X) -> 106.168 | T9: =SUMIF(DataQ!$E:$E,DataA!$A9,DataQ!Y:Y) -> 61.89546 | U9: =SUMIF(DataQ!$E:$E,DataA!$A9,DataQ!Z:Z) -> 45.795 | V9: =SUMIF(DataQ!$E:$E,DataA!$A9,DataQ!AA:AA) -> 74036 | W9: =SUMIF(DataQ!$B:$B,DataA!$A9,DataQ!AB:AB) -> 92673 | X9: =SUMIF(DataQ!$B:$B,DataA!$A9,DataQ!AC:AC) -> 1545.25 | Y9: =SUMIF(DataQ!$B:$B,DataA!$A9,DataQ!AD:AD) -> 137675.47 | Z9: =SUMIF(DataQ!$B:$B,DataA!$A9,DataQ!AE:AE) -> 599.3288 | AA9: =SUMIF(DataQ!$B:$B,DataA!$A9,DataQ!AF:AF) -> 207.305 | AB9: =SUMIF(DataQ!$B:$B,DataA!$A9,DataQ!AG:AG) -> 67.409 | AC9: =SUMIF(DataQ!$B:$B,DataA!$A9,DataQ!AH:AH) -> 158176
A10: 1975 | B10: =SUMIF(DataQ!$B:$B,DataA!$A10,DataQ!G:G) -> 948361 | C10: =SUMIF(DataQ!$B:$B,DataA!$A10,DataQ!H:H) -> 6060.85 | D10: =SUMIF(DataQ!$B:$B,DataA!$A10,DataQ!I:I) -> 215781.13 | E10: =SUMIF(DataQ!$B:$B,DataA!$A10,DataQ!J:J) -> 1557.62 | F10: =SUMIF(DataQ!$B:$B,DataA!$A10,DataQ!K:K) -> 1033.444 | G10: =SUMIF(DataQ!$B:$B,DataA!$A10,DataQ!L:L) -> 961.6561 | H10: =SUMIF(DataQ!$B:$B,DataA!$A10,DataQ!M:M) -> 742205.1 | I10: =SUMIF(DataQ!$B:$B,DataA!$A10,DataQ!N:N) -> -7211 | J10: =SUMIF(DataQ!$B:$B,DataA!$A10,DataQ!O:O) -> -128.606 | K10: =SUMIF(DataQ!$B:$B,DataA!$A10,DataQ!P:P) -> -7342 | L10: =SUMIF(DataQ!$B:$B,DataA!$A10,DataQ!Q:Q) -> -62.44885 | M10: =SUMIF(DataQ!$B:$B,DataA!$A10,DataQ!R:R) -> -4.3009993 | N10: =SUMIF(DataQ!$B:$B,DataA!$A10,DataQ!S:S) -> -7.734278 | O10: =SUMIF(DataQ!$B:$B,DataA!$A10,DataQ!T:T) -> -4505 | P10: =SUMIF(DataQ!$E:$E,DataA!$A10,DataQ!U:U) -> 62646 | Q10: =SUMIF(DataQ!$E:$E,DataA!$A10,DataQ!V:V) -> 1412.028 | R10: =SUMIF(DataQ!$E:$E,DataA!$A10,DataQ!W:W) -> 29223 | S10: =SUMIF(DataQ!$E:$E,DataA!$A10,DataQ!X:X) -> 136.7461 | T10: =SUMIF(DataQ!$E:$E,DataA!$A10,DataQ!Y:Y) -> 70.28793 | U10: =SUMIF(DataQ!$E:$E,DataA!$A10,DataQ!Z:Z) -> 61.44 | V10: =SUMIF(DataQ!$E:$E,DataA!$A10,DataQ!AA:AA) -> 82299 | W10: =SUMIF(DataQ!$B:$B,DataA!$A10,DataQ!AB:AB) -> 115093 | X10: =SUMIF(DataQ!$B:$B,DataA!$A10,DataQ!AC:AC) -> 1684.9 | Y10: =SUMIF(DataQ!$B:$B,DataA!$A10,DataQ!AD:AD) -> 152524.06 | Z10: =SUMIF(DataQ!$B:$B,DataA!$A10,DataQ!AE:AE) -> 627.6409 | AA10: =SUMIF(DataQ!$B:$B,DataA!$A10,DataQ!AF:AF) -> 233.583 | AB10: =SUMIF(DataQ!$B:$B,DataA!$A10,DataQ!AG:AG) -> 76.902 | AC10: =SUMIF(DataQ!$B:$B,DataA!$A10,DataQ!AH:AH) -> 177928
A11: 1976 | B11: =SUMIF(DataQ!$B:$B,DataA!$A11,DataQ!G:G) -> 976967 | C11: =SUMIF(DataQ!$B:$B,DataA!$A11,DataQ!H:H) -> 6387.425 | D11: =SUMIF(DataQ!$B:$B,DataA!$A11,DataQ!I:I) -> 224484.6 | E11: =SUMIF(DataQ!$B:$B,DataA!$A11,DataQ!J:J) -> 1626.82 | F11: =SUMIF(DataQ!$B:$B,DataA!$A11,DataQ!K:K) -> 1078.312 | G11: =SUMIF(DataQ!$B:$B,DataA!$A11,DataQ!L:L) -> 1024.4384 | H11: =SUMIF(DataQ!$B:$B,DataA!$A11,DataQ!M:M) -> 785915.6 | I11: =SUMIF(DataQ!$B:$B,DataA!$A11,DataQ!N:N) -> -7961 | J11: =SUMIF(DataQ!$B:$B,DataA!$A11,DataQ!O:O) -> -104.50225 | K11: =SUMIF(DataQ!$B:$B,DataA!$A11,DataQ!P:P) -> -9301 | L11: =SUMIF(DataQ!$B:$B,DataA!$A11,DataQ!Q:Q) -> -53.17428 | M11: =SUMIF(DataQ!$B:$B,DataA!$A11,DataQ!R:R) -> -1.5120001 | N11: =SUMIF(DataQ!$B:$B,DataA!$A11,DataQ!S:S) -> -7.402609 | O11: =SUMIF(DataQ!$B:$B,DataA!$A11,DataQ!T:T) -> -4501 | P11: =SUMIF(DataQ!$E:$E,DataA!$A11,DataQ!U:U) -> 73402.75 | Q11: =SUMIF(DataQ!$E:$E,DataA!$A11,DataQ!V:V) -> 1521.477 | R11: =SUMIF(DataQ!$E:$E,DataA!$A11,DataQ!W:W) -> 44086 | S11: =SUMIF(DataQ!$E:$E,DataA!$A11,DataQ!X:X) -> 155.0151 | T11: =SUMIF(DataQ!$E:$E,DataA!$A11,DataQ!Y:Y) -> 77.04875 | U11: =SUMIF(DataQ!$E:$E,DataA!$A11,DataQ!Z:Z) -> 76.946 | V11: =SUMIF(DataQ!$E:$E,DataA!$A11,DataQ!AA:AA) -> 91437 | W11: =SUMIF(DataQ!$B:$B,DataA!$A11,DataQ!AB:AB) -> 136999 | X11: =SUMIF(DataQ!$B:$B,DataA!$A11,DataQ!AC:AC) -> 1873.425 | Y11: =SUMIF(DataQ!$B:$B,DataA!$A11,DataQ!AD:AD) -> 171384.16 | Z11: =SUMIF(DataQ!$B:$B,DataA!$A11,DataQ!AE:AE) -> 677.2367 | AA11: =SUMIF(DataQ!$B:$B,DataA!$A11,DataQ!AF:AF) -> 269.714 | AB11: =SUMIF(DataQ!$B:$B,DataA!$A11,DataQ!AG:AG) -> 96.562 | AC11: =SUMIF(DataQ!$B:$B,DataA!$A11,DataQ!AH:AH) -> 205986
A12: 1977 | B12: =SUMIF(DataQ!$B:$B,DataA!$A12,DataQ!G:G) -> 1001004 | C12: =SUMIF(DataQ!$B:$B,DataA!$A12,DataQ!H:H) -> 6682.825 | D12: =SUMIF(DataQ!$B:$B,DataA!$A12,DataQ!I:I) -> 234520.75 | E12: =SUMIF(DataQ!$B:$B,DataA!$A12,DataQ!J:J) -> 1683.93 | F12: =SUMIF(DataQ!$B:$B,DataA!$A12,DataQ!K:K) -> 1116.289 | G12: =SUMIF(DataQ!$B:$B,DataA!$A12,DataQ!L:L) -> 1048.6038 | H12: =SUMIF(DataQ!$B:$B,DataA!$A12,DataQ!M:M) -> 813696.4 | I12: =SUMIF(DataQ!$B:$B,DataA!$A12,DataQ!N:N) -> -5836 | J12: =SUMIF(DataQ!$B:$B,DataA!$A12,DataQ!O:O) -> -88.151 | K12: =SUMIF(DataQ!$B:$B,DataA!$A12,DataQ!P:P) -> -10191.75 | L12: =SUMIF(DataQ!$B:$B,DataA!$A12,DataQ!Q:Q) -> -44.70044 | M12: =SUMIF(DataQ!$B:$B,DataA!$A12,DataQ!R:R) -> -1.9469999 | N12: =SUMIF(DataQ!$B:$B,DataA!$A12,DataQ!S:S) -> -7.911603 | O12: =SUMIF(DataQ!$B:$B,DataA!$A12,DataQ!T:T) -> -7329 | P12: =SUMIF(DataQ!$E:$E,DataA!$A12,DataQ!U:U) -> 83765.5 | Q12: =SUMIF(DataQ!$E:$E,DataA!$A12,DataQ!V:V) -> 1639.112 | R12: =SUMIF(DataQ!$E:$E,DataA!$A12,DataQ!W:W) -> 58926 | S12: =SUMIF(DataQ!$E:$E,DataA!$A12,DataQ!X:X) -> 172.103 | T12: =SUMIF(DataQ!$E:$E,DataA!$A12,DataQ!Y:Y) -> 85.55736 | U12: =SUMIF(DataQ!$E:$E,DataA!$A12,DataQ!Z:Z) -> 97.55 | V12: =SUMIF(DataQ!$E:$E,DataA!$A12,DataQ!AA:AA) -> 104504 | W12: =SUMIF(DataQ!$B:$B,DataA!$A12,DataQ!AB:AB) -> 159786 | X12: =SUMIF(DataQ!$B:$B,DataA!$A12,DataQ!AC:AC) -> 2081.825 | Y12: =SUMIF(DataQ!$B:$B,DataA!$A12,DataQ!AD:AD) -> 191055.77 | Z12: =SUMIF(DataQ!$B:$B,DataA!$A12,DataQ!AE:AE) -> 722.7076 | AA12: =SUMIF(DataQ!$B:$B,DataA!$A12,DataQ!AF:AF) -> 303.907 | AB12: =SUMIF(DataQ!$B:$B,DataA!$A12,DataQ!AG:AG) -> 117.316 | AC12: =SUMIF(DataQ!$B:$B,DataA!$A12,DataQ!AH:AH) -> 227601
A13: 1978 | B13: =SUMIF(DataQ!$B:$B,DataA!$A13,DataQ!G:G) -> 1042953 | C13: =SUMIF(DataQ!$B:$B,DataA!$A13,DataQ!H:H) -> 7052.725 | D13: =SUMIF(DataQ!$B:$B,DataA!$A13,DataQ!I:I) -> 247036.86 | E13: =SUMIF(DataQ!$B:$B,DataA!$A13,DataQ!J:J) -> 1736.22 | F13: =SUMIF(DataQ!$B:$B,DataA!$A13,DataQ!K:K) -> 1160.514 | G13: =SUMIF(DataQ!$B:$B,DataA!$A13,DataQ!L:L) -> 1086.8867 | H13: =SUMIF(DataQ!$B:$B,DataA!$A13,DataQ!M:M) -> 844095.8 | I13: =SUMIF(DataQ!$B:$B,DataA!$A13,DataQ!N:N) -> -8334 | J13: =SUMIF(DataQ!$B:$B,DataA!$A13,DataQ!O:O) -> -81.16925 | K13: =SUMIF(DataQ!$B:$B,DataA!$A13,DataQ!P:P) -> -13458 | L13: =SUMIF(DataQ!$B:$B,DataA!$A13,DataQ!Q:Q) -> -52.05288 | M13: =SUMIF(DataQ!$B:$B,DataA!$A13,DataQ!R:R) -> -6.702 | N13: =SUMIF(DataQ!$B:$B,DataA!$A13,DataQ!S:S) -> -11.376781 | O13: =SUMIF(DataQ!$B:$B,DataA!$A13,DataQ!T:T) -> -10455 | P13: =SUMIF(DataQ!$E:$E,DataA!$A13,DataQ!U:U) -> 94137.5 | Q13: =SUMIF(DataQ!$E:$E,DataA!$A13,DataQ!V:V) -> 1778.414 | R13: =SUMIF(DataQ!$E:$E,DataA!$A13,DataQ!W:W) -> 82162 | S13: =SUMIF(DataQ!$E:$E,DataA!$A13,DataQ!X:X) -> 193.9361 | T13: =SUMIF(DataQ!$E:$E,DataA!$A13,DataQ!Y:Y) -> 100.8063 | U13: =SUMIF(DataQ!$E:$E,DataA!$A13,DataQ!Z:Z) -> 121.674 | V13: =SUMIF(DataQ!$E:$E,DataA!$A13,DataQ!AA:AA) -> 123288 | W13: =SUMIF(DataQ!$B:$B,DataA!$A13,DataQ!AB:AB) -> 186158 | X13: =SUMIF(DataQ!$B:$B,DataA!$A13,DataQ!AC:AC) -> 2351.6 | Y13: =SUMIF(DataQ!$B:$B,DataA!$A13,DataQ!AD:AD) -> 210468.72 | Z13: =SUMIF(DataQ!$B:$B,DataA!$A13,DataQ!AE:AE) -> 771.5664 | AA13: =SUMIF(DataQ!$B:$B,DataA!$A13,DataQ!AF:AF) -> 345.187 | AB13: =SUMIF(DataQ!$B:$B,DataA!$A13,DataQ!AG:AG) -> 138.022 | AC13: =SUMIF(DataQ!$B:$B,DataA!$A13,DataQ!AH:AH) -> 252075
A14: 1979 | B14: =SUMIF(DataQ!$B:$B,DataA!$A14,DataQ!G:G) -> 1081838 | C14: =SUMIF(DataQ!$B:$B,DataA!$A14,DataQ!H:H) -> 7276 | D14: =SUMIF(DataQ!$B:$B,DataA!$A14,DataQ!I:I) -> 261577.77 | E14: =SUMIF(DataQ!$B:$B,DataA!$A14,DataQ!J:J) -> 1810.62 | F14: =SUMIF(DataQ!$B:$B,DataA!$A14,DataQ!K:K) -> 1203.514 | G14: =SUMIF(DataQ!$B:$B,DataA!$A14,DataQ!L:L) -> 1147.0066 | H14: =SUMIF(DataQ!$B:$B,DataA!$A14,DataQ!M:M) -> 875540.1 | I14: =SUMIF(DataQ!$B:$B,DataA!$A14,DataQ!N:N) -> -9364 | J14: =SUMIF(DataQ!$B:$B,DataA!$A14,DataQ!O:O) -> -78.56225 | K14: =SUMIF(DataQ!$B:$B,DataA!$A14,DataQ!P:P) -> -12426.5 | L14: =SUMIF(DataQ!$B:$B,DataA!$A14,DataQ!Q:Q) -> -58.44036 | M14: =SUMIF(DataQ!$B:$B,DataA!$A14,DataQ!R:R) -> -1.934 | N14: =SUMIF(DataQ!$B:$B,DataA!$A14,DataQ!S:S) -> -13.51795 | O14: =SUMIF(DataQ!$B:$B,DataA!$A14,DataQ!T:T) -> -8532 | P14: =SUMIF(DataQ!$E:$E,DataA!$A14,DataQ!U:U) -> 104807 | Q14: =SUMIF(DataQ!$E:$E,DataA!$A14,DataQ!V:V) -> 1922.42 | R14: =SUMIF(DataQ!$E:$E,DataA!$A14,DataQ!W:W) -> 98956 | S14: =SUMIF(DataQ!$E:$E,DataA!$A14,DataQ!X:X) -> 217.6445 | T14: =SUMIF(DataQ!$E:$E,DataA!$A14,DataQ!Y:Y) -> 115.7283 | U14: =SUMIF(DataQ!$E:$E,DataA!$A14,DataQ!Z:Z) -> 146.611 | V14: =SUMIF(DataQ!$E:$E,DataA!$A14,DataQ!AA:AA) -> 132680 | W14: =SUMIF(DataQ!$B:$B,DataA!$A14,DataQ!AB:AB) -> 220981 | X14: =SUMIF(DataQ!$B:$B,DataA!$A14,DataQ!AC:AC) -> 2627.325 | Y14: =SUMIF(DataQ!$B:$B,DataA!$A14,DataQ!AD:AD) -> 227860.58 | Z14: =SUMIF(DataQ!$B:$B,DataA!$A14,DataQ!AE:AE) -> 839.0251 | AA14: =SUMIF(DataQ!$B:$B,DataA!$A14,DataQ!AF:AF) -> 394.491 | AB14: =SUMIF(DataQ!$B:$B,DataA!$A14,DataQ!AG:AG) -> 168.884 | AC14: =SUMIF(DataQ!$B:$B,DataA!$A14,DataQ!AH:AH) -> 287608
A15: 1980 | B15: =SUMIF(DataQ!$B:$B,DataA!$A15,DataQ!G:G) -> 1059660 | C15: =SUMIF(DataQ!$B:$B,DataA!$A15,DataQ!H:H) -> 7257.325 | D15: =SUMIF(DataQ!$B:$B,DataA!$A15,DataQ!I:I) -> 272992.43 | E15: =SUMIF(DataQ!$B:$B,DataA!$A15,DataQ!J:J) -> 1833.95 | F15: =SUMIF(DataQ!$B:$B,DataA!$A15,DataQ!K:K) -> 1223.307 | G15: =SUMIF(DataQ!$B:$B,DataA!$A15,DataQ!L:L) -> 1186.9547 | H15: =SUMIF(DataQ!$B:$B,DataA!$A15,DataQ!M:M) -> 894602.4 | I15: =SUMIF(DataQ!$B:$B,DataA!$A15,DataQ!N:N) -> -10041 | J15: =SUMIF(DataQ!$B:$B,DataA!$A15,DataQ!O:O) -> -128.273 | K15: =SUMIF(DataQ!$B:$B,DataA!$A15,DataQ!P:P) -> -11822.5 | L15: =SUMIF(DataQ!$B:$B,DataA!$A15,DataQ!Q:Q) -> -62.0868 | M15: =SUMIF(DataQ!$B:$B,DataA!$A15,DataQ!R:R) -> -1.928 | N15: =SUMIF(DataQ!$B:$B,DataA!$A15,DataQ!S:S) -> -14.305154 | O15: =SUMIF(DataQ!$B:$B,DataA!$A15,DataQ!T:T) -> -11149 | P15: =SUMIF(DataQ!$E:$E,DataA!$A15,DataQ!U:U) -> 121541.3 | Q15: =SUMIF(DataQ!$E:$E,DataA!$A15,DataQ!V:V) -> 2062.851 | R15: =SUMIF(DataQ!$E:$E,DataA!$A15,DataQ!W:W) -> 117360 | S15: =SUMIF(DataQ!$E:$E,DataA!$A15,DataQ!X:X) -> 248.8942 | T15: =SUMIF(DataQ!$E:$E,DataA!$A15,DataQ!Y:Y) -> 129.1328 | U15: =SUMIF(DataQ!$E:$E,DataA!$A15,DataQ!Z:Z) -> 178.644 | V15: =SUMIF(DataQ!$E:$E,DataA!$A15,DataQ!AA:AA) -> 150393 | W15: =SUMIF(DataQ!$B:$B,DataA!$A15,DataQ!AB:AB) -> 259970 | X15: =SUMIF(DataQ!$B:$B,DataA!$A15,DataQ!AC:AC) -> 2857.325 | Y15: =SUMIF(DataQ!$B:$B,DataA!$A15,DataQ!AD:AD) -> 255596.35 | Z15: =SUMIF(DataQ!$B:$B,DataA!$A15,DataQ!AE:AE) -> 896.4522 | AA15: =SUMIF(DataQ!$B:$B,DataA!$A15,DataQ!AF:AF) -> 447.345 | AB15: =SUMIF(DataQ!$B:$B,DataA!$A15,DataQ!AG:AG) -> 217.501 | AC15: =SUMIF(DataQ!$B:$B,DataA!$A15,DataQ!AH:AH) -> 322782
A16: 1981 | B16: =SUMIF(DataQ!$B:$B,DataA!$A16,DataQ!G:G) -> 1052374 | C16: =SUMIF(DataQ!$B:$B,DataA!$A16,DataQ!H:H) -> 7441.475 | D16: =SUMIF(DataQ!$B:$B,DataA!$A16,DataQ!I:I) -> 284947.89 | E16: =SUMIF(DataQ!$B:$B,DataA!$A16,DataQ!J:J) -> 1845.86 | F16: =SUMIF(DataQ!$B:$B,DataA!$A16,DataQ!K:K) -> 1237.82 | G16: =SUMIF(DataQ!$B:$B,DataA!$A16,DataQ!L:L) -> 1197.887 | H16: =SUMIF(DataQ!$B:$B,DataA!$A16,DataQ!M:M) -> 925153.7 | I16: =SUMIF(DataQ!$B:$B,DataA!$A16,DataQ!N:N) -> -8825 | J16: =SUMIF(DataQ!$B:$B,DataA!$A16,DataQ!O:O) -> -130.469 | K16: =SUMIF(DataQ!$B:$B,DataA!$A16,DataQ!P:P) -> -10937.75 | L16: =SUMIF(DataQ!$B:$B,DataA!$A16,DataQ!Q:Q) -> -75.16716 | M16: =SUMIF(DataQ!$B:$B,DataA!$A16,DataQ!R:R) -> -12.242 | N16: =SUMIF(DataQ!$B:$B,DataA!$A16,DataQ!S:S) -> -27.037463 | O16: =SUMIF(DataQ!$B:$B,DataA!$A16,DataQ!T:T) -> -7830 | P16: =SUMIF(DataQ!$E:$E,DataA!$A16,DataQ!U:U) -> 131791.5 | Q16: =SUMIF(DataQ!$E:$E,DataA!$A16,DataQ!V:V) -> 2256.733 | R16: =SUMIF(DataQ!$E:$E,DataA!$A16,DataQ!W:W) -> 141470 | S16: =SUMIF(DataQ!$E:$E,DataA!$A16,DataQ!X:X) -> 287.4771 | T16: =SUMIF(DataQ!$E:$E,DataA!$A16,DataQ!Y:Y) -> 141.5108 | U16: =SUMIF(DataQ!$E:$E,DataA!$A16,DataQ!Z:Z) -> 224.365 | V16: =SUMIF(DataQ!$E:$E,DataA!$A16,DataQ!AA:AA) -> 177353 | W16: =SUMIF(DataQ!$B:$B,DataA!$A16,DataQ!AB:AB) -> 290180 | X16: =SUMIF(DataQ!$B:$B,DataA!$A16,DataQ!AC:AC) -> 3207.025 | Y16: =SUMIF(DataQ!$B:$B,DataA!$A16,DataQ!AD:AD) -> 274362.5 | Z16: =SUMIF(DataQ!$B:$B,DataA!$A16,DataQ!AE:AE) -> 939.7564 | AA16: =SUMIF(DataQ!$B:$B,DataA!$A16,DataQ!AF:AF) -> 504.566 | AB16: =SUMIF(DataQ!$B:$B,DataA!$A16,DataQ!AG:AG) -> 260.06 | AC16: =SUMIF(DataQ!$B:$B,DataA!$A16,DataQ!AH:AH) -> 368358
A17: 1982 | B17: =SUMIF(DataQ!$B:$B,DataA!$A17,DataQ!G:G) -> 1073055 | C17: =SUMIF(DataQ!$B:$B,DataA!$A17,DataQ!H:H) -> 7307.3 | D17: =SUMIF(DataQ!$B:$B,DataA!$A17,DataQ!I:I) -> 294351.01 | E17: =SUMIF(DataQ!$B:$B,DataA!$A17,DataQ!J:J) -> 1836.61 | F17: =SUMIF(DataQ!$B:$B,DataA!$A17,DataQ!K:K) -> 1267.574 | G17: =SUMIF(DataQ!$B:$B,DataA!$A17,DataQ!L:L) -> 1201.783 | H17: =SUMIF(DataQ!$B:$B,DataA!$A17,DataQ!M:M) -> 895861.9 | I17: =SUMIF(DataQ!$B:$B,DataA!$A17,DataQ!N:N) -> -7359 | J17: =SUMIF(DataQ!$B:$B,DataA!$A17,DataQ!O:O) -> -220.126 | K17: =SUMIF(DataQ!$B:$B,DataA!$A17,DataQ!P:P) -> -11134.25 | L17: =SUMIF(DataQ!$B:$B,DataA!$A17,DataQ!Q:Q) -> -74.95508 | M17: =SUMIF(DataQ!$B:$B,DataA!$A17,DataQ!R:R) -> -16.498 | N17: =SUMIF(DataQ!$B:$B,DataA!$A17,DataQ!S:S) -> -29.281416 | O17: =SUMIF(DataQ!$B:$B,DataA!$A17,DataQ!T:T) -> -23407 | P17: =SUMIF(DataQ!$E:$E,DataA!$A17,DataQ!U:U) -> 140578.8 | Q17: =SUMIF(DataQ!$E:$E,DataA!$A17,DataQ!V:V) -> 2532.298 | R17: =SUMIF(DataQ!$E:$E,DataA!$A17,DataQ!W:W) -> 165196 | S17: =SUMIF(DataQ!$E:$E,DataA!$A17,DataQ!X:X) -> 320.4308 | T17: =SUMIF(DataQ!$E:$E,DataA!$A17,DataQ!Y:Y) -> 184.3563 | U17: =SUMIF(DataQ!$E:$E,DataA!$A17,DataQ!Z:Z) -> 275.674 | V17: =SUMIF(DataQ!$E:$E,DataA!$A17,DataQ!AA:AA) -> 209732 | W17: =SUMIF(DataQ!$B:$B,DataA!$A17,DataQ!AB:AB) -> 319558 | X17: =SUMIF(DataQ!$B:$B,DataA!$A17,DataQ!AC:AC) -> 3343.8 | Y17: =SUMIF(DataQ!$B:$B,DataA!$A17,DataQ!AD:AD) -> 288540.02 | Z17: =SUMIF(DataQ!$B:$B,DataA!$A17,DataQ!AE:AE) -> 977.803 | AA17: =SUMIF(DataQ!$B:$B,DataA!$A17,DataQ!AF:AF) -> 578.925 | AB17: =SUMIF(DataQ!$B:$B,DataA!$A17,DataQ!AG:AG) -> 306.689 | AC17: =SUMIF(DataQ!$B:$B,DataA!$A17,DataQ!AH:AH) -> 388181
A18: 1983 | B18: =SUMIF(DataQ!$B:$B,DataA!$A18,DataQ!G:G) -> 1117759 | C18: =SUMIF(DataQ!$B:$B,DataA!$A18,DataQ!H:H) -> 7642.275 | D18: =SUMIF(DataQ!$B:$B,DataA!$A18,DataQ!I:I) -> 304984.68 | E18: =SUMIF(DataQ!$B:$B,DataA!$A18,DataQ!J:J) -> 1863.58 | F18: =SUMIF(DataQ!$B:$B,DataA!$A18,DataQ!K:K) -> 1283.577 | G18: =SUMIF(DataQ!$B:$B,DataA!$A18,DataQ!L:L) -> 1218.202 | H18: =SUMIF(DataQ!$B:$B,DataA!$A18,DataQ!M:M) -> 918816.2 | I18: =SUMIF(DataQ!$B:$B,DataA!$A18,DataQ!N:N) -> -10582 | J18: =SUMIF(DataQ!$B:$B,DataA!$A18,DataQ!O:O) -> -265.23725 | K18: =SUMIF(DataQ!$B:$B,DataA!$A18,DataQ!P:P) -> -11809.25 | L18: =SUMIF(DataQ!$B:$B,DataA!$A18,DataQ!Q:Q) -> -71.17676 | M18: =SUMIF(DataQ!$B:$B,DataA!$A18,DataQ!R:R) -> -16.481 | N18: =SUMIF(DataQ!$B:$B,DataA!$A18,DataQ!S:S) -> -34.423509 | O18: =SUMIF(DataQ!$B:$B,DataA!$A18,DataQ!T:T) -> -30637 | P18: =SUMIF(DataQ!$E:$E,DataA!$A18,DataQ!U:U) -> 152083.3 | Q18: =SUMIF(DataQ!$E:$E,DataA!$A18,DataQ!V:V) -> 2812.196 | R18: =SUMIF(DataQ!$E:$E,DataA!$A18,DataQ!W:W) -> 189884 | S18: =SUMIF(DataQ!$E:$E,DataA!$A18,DataQ!X:X) -> 347.2786 | T18: =SUMIF(DataQ!$E:$E,DataA!$A18,DataQ!Y:Y) -> 210.6735 | U18: =SUMIF(DataQ!$E:$E,DataA!$A18,DataQ!Z:Z) -> 269.128 | V18: =SUMIF(DataQ!$E:$E,DataA!$A18,DataQ!AA:AA) -> 251868 | W18: =SUMIF(DataQ!$B:$B,DataA!$A18,DataQ!AB:AB) -> 351347 | X18: =SUMIF(DataQ!$B:$B,DataA!$A18,DataQ!AC:AC) -> 3634.025 | Y18: =SUMIF(DataQ!$B:$B,DataA!$A18,DataQ!AD:AD) -> 301733.15 | Z18: =SUMIF(DataQ!$B:$B,DataA!$A18,DataQ!AE:AE) -> 1020.0841 | AA18: =SUMIF(DataQ!$B:$B,DataA!$A18,DataQ!AF:AF) -> 642.54 | AB18: =SUMIF(DataQ!$B:$B,DataA!$A18,DataQ!AG:AG) -> 357.802 | AC18: =SUMIF(DataQ!$B:$B,DataA!$A18,DataQ!AH:AH) -> 421316
A19: 1984 | B19: =SUMIF(DataQ!$B:$B,DataA!$A19,DataQ!G:G) -> 1142579 | C19: =SUMIF(DataQ!$B:$B,DataA!$A19,DataQ!H:H) -> 8195.3 | D19: =SUMIF(DataQ!$B:$B,DataA!$A19,DataQ!I:I) -> 318480.11 | E19: =SUMIF(DataQ!$B:$B,DataA!$A19,DataQ!J:J) -> 1917.61 | F19: =SUMIF(DataQ!$B:$B,DataA!$A19,DataQ!K:K) -> 1305.053 | G19: =SUMIF(DataQ!$B:$B,DataA!$A19,DataQ!L:L) -> 1257.309 | H19: =SUMIF(DataQ!$B:$B,DataA!$A19,DataQ!M:M) -> 973013.1 | I19: =SUMIF(DataQ!$B:$B,DataA!$A19,DataQ!N:N) -> -12423 | J19: =SUMIF(DataQ!$B:$B,DataA!$A19,DataQ!O:O) -> -249.608 | K19: =SUMIF(DataQ!$B:$B,DataA!$A19,DataQ!P:P) -> -8204.75 | L19: =SUMIF(DataQ!$B:$B,DataA!$A19,DataQ!Q:Q) -> -66.7484 | M19: =SUMIF(DataQ!$B:$B,DataA!$A19,DataQ!R:R) -> -19.303 | N19: =SUMIF(DataQ!$B:$B,DataA!$A19,DataQ!S:S) -> -44.8364 | O19: =SUMIF(DataQ!$B:$B,DataA!$A19,DataQ!T:T) -> -33224.999 | P19: =SUMIF(DataQ!$E:$E,DataA!$A19,DataQ!U:U) -> 163648.5 | Q19: =SUMIF(DataQ!$E:$E,DataA!$A19,DataQ!V:V) -> 3127.651 | R19: =SUMIF(DataQ!$E:$E,DataA!$A19,DataQ!W:W) -> 208326 | S19: =SUMIF(DataQ!$E:$E,DataA!$A19,DataQ!X:X) -> 369.349 | T19: =SUMIF(DataQ!$E:$E,DataA!$A19,DataQ!Y:Y) -> 240.8142 | U19: =SUMIF(DataQ!$E:$E,DataA!$A19,DataQ!Z:Z) -> 318.727 | V19: =SUMIF(DataQ!$E:$E,DataA!$A19,DataQ!AA:AA) -> 290671 | W19: =SUMIF(DataQ!$B:$B,DataA!$A19,DataQ!AB:AB) -> 377920 | X19: =SUMIF(DataQ!$B:$B,DataA!$A19,DataQ!AC:AC) -> 4037.65 | Y19: =SUMIF(DataQ!$B:$B,DataA!$A19,DataQ!AD:AD) -> 319635.48 | Z19: =SUMIF(DataQ!$B:$B,DataA!$A19,DataQ!AE:AE) -> 1070.7138 | AA19: =SUMIF(DataQ!$B:$B,DataA!$A19,DataQ!AF:AF) -> 699.5 | AB19: =SUMIF(DataQ!$B:$B,DataA!$A19,DataQ!AG:AG) -> 409.026 | AC19: =SUMIF(DataQ!$B:$B,DataA!$A19,DataQ!AH:AH) -> 461986
... A95: 2060 | B95: =SUMIF(DataQ!$B:$B,DataA!$A95,DataQ!G:G) -> 4282693 | C95: =SUMIF(DataQ!$B:$B,DataA!$A95,DataQ!H:H) -> 43611.64 | D95: =SUMIF(DataQ!$B:$B,DataA!$A95,DataQ!I:I) -> 575869.8 | E95: =SUMIF(DataQ!$B:$B,DataA!$A95,DataQ!J:J) -> 4940.229 | F95: =SUMIF(DataQ!$B:$B,DataA!$A95,DataQ!K:K) -> 3240.5261 | G95: =SUMIF(DataQ!$B:$B,DataA!$A95,DataQ!L:L) -> 2172.8906 | H95: =SUMIF(DataQ!$B:$B,DataA!$A95,DataQ!M:M) -> 4690331 | I95: =SUMIF(DataQ!$B:$B,DataA!$A95,DataQ!N:N) -> -422235.08 | J95: =SUMIF(DataQ!$B:$B,DataA!$A95,DataQ!O:O) -> -4085.043 | K95: =SUMIF(DataQ!$B:$B,DataA!$A95,DataQ!P:P) -> -9856.876 | L95: =SUMIF(DataQ!$B:$B,DataA!$A95,DataQ!Q:Q) -> -175.23095 | M95: =SUMIF(DataQ!$B:$B,DataA!$A95,DataQ!R:R) -> -244.19832 | N95: =SUMIF(DataQ!$B:$B,DataA!$A95,DataQ!S:S) -> -87.62374 | O95: =SUMIF(DataQ!$B:$B,DataA!$A95,DataQ!T:T) -> -287749.88 | P95: =SUMIF(DataQ!$E:$E,DataA!$A95,DataQ!U:U) -> 11324100 | Q95: =SUMIF(DataQ!$E:$E,DataA!$A95,DataQ!V:V) -> 181081 | R95: =SUMIF(DataQ!$E:$E,DataA!$A95,DataQ!W:W) -> 1741352 | S95: =SUMIF(DataQ!$E:$E,DataA!$A95,DataQ!X:X) -> 7253.72 | T95: =SUMIF(DataQ!$E:$E,DataA!$A95,DataQ!Y:Y) -> 9996.658 | U95: =SUMIF(DataQ!$E:$E,DataA!$A95,DataQ!Z:Z) -> 5756.39 | V95: =SUMIF(DataQ!$E:$E,DataA!$A95,DataQ!AA:AA) -> 9232492 | W95: =SUMIF(DataQ!$B:$B,DataA!$A95,DataQ!AB:AB) -> 10420241 | X95: =SUMIF(DataQ!$B:$B,DataA!$A95,DataQ!AC:AC) -> 107862.69 | Y95: =SUMIF(DataQ!$B:$B,DataA!$A95,DataQ!AD:AD) -> 1059071.7 | Z95: =SUMIF(DataQ!$B:$B,DataA!$A95,DataQ!AE:AE) -> 12560.15 | AA95: =SUMIF(DataQ!$B:$B,DataA!$A95,DataQ!AF:AF) -> 7400.093 | AB95: =SUMIF(DataQ!$B:$B,DataA!$A95,DataQ!AG:AG) -> 4938.557 | AC95: =SUMIF(DataQ!$B:$B,DataA!$A95,DataQ!AH:AH) -> 11878789

Sheet DataQ
G1: =GMW!NF2 -> SEP008W.db | H1: =$G$1 -> SEP008W.db | I1: =$G$1 -> SEP008W.db | J1: =$G$1 -> SEP008W.db | K1: =$G$1 -> SEP008W.db | L1: =$G$1 -> SEP008W.db | M1: =$G$1 -> SEP008W.db | N1: =$G$1 -> SEP008W.db | O1: =$G$1 -> SEP008W.db | ... AH1: =$G$1 -> SEP008W.db
G2: UK | H2: US | I2: Japan | J2: Germany | K2: France | L2: Italy | M2: Canada | N2: UK | O2: US | P2: Japan | Q2: Germany | R2: France | S2: Italy | T2: Canada | U2: UK | V2: US | W2: Japan | X2: Germany | Y2: France | Z2: Italy | AA2: Canada | AB2: UK | AC2: US | AD2: Japan | AE2: Germany | AF2: France | AG2: Italy | AH2: Canada
G3: GDP | H3: GDP | I3: GDP | J3: GDP | K3: GDP | L3: GDP | M3: GDP | N3: GB | O3: GB | P3: GB | Q3: GB | R3: GB | S3: GB | T3: GB | U3: GGDBT | V3: GGDBT | W3: GGDBT | X3: GGDBT | Y3: GGDBT | Z3: GGDBT | AA3: GGDBT | AB3: GDP! | AC3: GDP! | AD3: GDP! | AE3: GDP! | AF3: GDP! | AG3: GDP! | AH3: GDP!
G4: GBR | H4: USA | I4: JPN | J4: DEU | K4: FRA | L4: ITA | M4: CAN | N4: GBR | O4: USA | P4: JPN | Q4: DEU | R4: FRA | S4: ITA | T4: CAN | U4: GBR | V4: USA | W4: JPN | X4: DEU | Y4: FRA | Z4: ITA | AA4: CAN | AB4: GBR | AC4: USA | AD4: JPN | AE4: DEU | AF4: FRA | AG4: ITA | AH4: CAN
G5: L | H5: L | I5: L | J5: L | K5: L | L5: L | M5: L | N5: L | O5: L | P5: L | Q5: L | R5: L | S5: L | T5: L | U5: L | V5: L | W5: L | X5: L | Y5: L | Z5: L | AA5: L | AB5: L | AC5: L | AD5: L | AE5: L | AF5: L | AG5: L | AH5: L
B6: CYs | C6: FYs | D6: FY end | E6: CY end | F6: =F358+5 -> 2329 | G6: {=_xlfn.CONCAT(INDEX(GMW!$A$2:$NE$60,MATCH(1,(GMW!$NE$2:$NE$60=G$3)*(GMW!$ND$2:$ND$60=G$4)*(GMW!$NF$2:$NF$60=G$1),0),$F6-1966),"0",(INDEX(GMW!$A$2:$NE$60,MATCH(1,(GMW!$NE$2:$NE$60=G$3)*(GMW!$ND$2:$ND$60=G$4)*(GMW!$NF$2:$NF$60=G$1),0),$F6-1965)))} -> 202502 | H6: {=_xlfn.CONCAT(INDEX(GMW!$A$2:$NE$60,MATCH(1,(GMW!$NE$2:$NE$60=H$3)*(GMW!$ND$2:$ND$60=H$4)*(GMW!$NF$2:$NF$60=H$1),0),$F6-1966),"0",(INDEX(GMW!$A$2:$NE$60,MATCH(1,(GMW!$NE$2:$NE$60=H$3)*(GMW!$ND$2:$ND$60=H$4)*(GMW!$NF$2:$NF$60=H$1),0),$F6-1965)))} -> 202502 | I6: {=_xlfn.CONCAT(INDEX(GMW!$A$2:$NE$60,MATCH(1,(GMW!$NE$2:$NE$60=I$3)*(GMW!$ND$2:$ND$60=I$4)*(GMW!$NF$2:$NF$60=I$1),0),$F6-1966),"0",(INDEX(GMW!$A$2:$NE$60,MATCH(1,(GMW!$NE$2:$NE$60=I$3)*(GMW!$ND$2:$ND$60=I$4)*(GMW!$NF$2:$NF$60=I$1),0),$F6-1965)))} -> 202502 | J6: {=_xlfn.CONCAT(INDEX(GMW!$A$2:$NE$60,MATCH(1,(GMW!$NE$2:$NE$60=J$3)*(GMW!$ND$2:$ND$60=J$4)*(GMW!$NF$2:$NF$60=J$1),0),$F6-1966),"0",(INDEX(GMW!$A$2:$NE$60,MATCH(1,(GMW!$NE$2:$NE$60=J$3)*(GMW!$ND$2:$ND$60=J$4)*(GMW!$NF$2:$NF$60=J$1),0),$F6-1965)))} -> 202502 | K6: {=_xlfn.CONCAT(INDEX(GMW!$A$2:$NE$60,MATCH(1,(GMW!$NE$2:$NE$60=K$3)*(GMW!$ND$2:$ND$60=K$4)*(GMW!$NF$2:$NF$60=K$1),0),$F6-1966),"0",(INDEX(GMW!$A$2:$NE$60,MATCH(1,(GMW!$NE$2:$NE$60=K$3)*(GMW!$ND$2:$ND$60=K$4)*(GMW!$NF$2:$NF$60=K$1),0),$F6-1965)))} -> 202502 | L6: {=_xlfn.CONCAT(INDEX(GMW!$A$2:$NE$60,MATCH(1,(GMW!$NE$2:$NE$60=L$3)*(GMW!$ND$2:$ND$60=L$4)*(GMW!$NF$2:$NF$60=L$1),0),$F6-1966),"0",(INDEX(GMW!$A$2:$NE$60,MATCH(1,(GMW!$NE$2:$NE$60=L$3)*(GMW!$ND$2:$ND$60=L$4)*(GMW!$NF$2:$NF$60=L$1),0),$F6-1965)))} -> 202502 | M6: {=_xlfn.CONCAT(INDEX(GMW!$A$2:$NE$60,MATCH(1,(GMW!$NE$2:$NE$60=M$3)*(GMW!$ND$2:$ND$60=M$4)*(GMW!$NF$2:$NF$60=M$1),0),$F6-1966),"0",(INDEX(GMW!$A$2:$NE$60,MATCH(1,(GMW!$NE$2:$NE$60=M$3)*(GMW!$ND$2:$ND$60=M$4)*(GMW!$NF$2:$NF$60=M$1),0),$F6-1965)))} -> 202502 | N6: {=_xlfn.CONCAT(INDEX(GMW!$A$2:$NE$60,MATCH(1,(GMW!$NE$2:$NE$60=N$3)*(GMW!$ND$2:$ND$60=N$4)*(GMW!$NF$2:$NF$60=N$1),0),$F6-1966),"0",(INDEX(GMW!$A$2:$NE$60,MATCH(1,(GMW!$NE$2:$NE$60=N$3)*(GMW!$ND$2:$ND$60=N$4)*(GMW!$NF$2:$NF$60=N$1),0),$F6-1965)))} -> 202502 | ... AH6: {=_xlfn.CONCAT(INDEX(GMW!$A$2:$NE$60,MATCH(1,(GMW!$NE$2:$NE$60=AH$3)*(GMW!$ND$2:$ND$60=AH$4)*(GMW!$NF$2:$NF$60=AH$1),0),$F6-1966),"0",(INDEX(GMW!$A$2:$NE$60,MATCH(1,(GMW!$NE$2:$NE$60=AH$3)*(GMW!$ND$2:$ND$60=AH$4)*(GMW!$NF$2:$NF$60=AH$1),0),$F6-1965)))} -> 202502
A7: 1973 | B7: 1973 | F7: 1973 | G7: {=INDEX(GMW!$A$2:$NF$60,MATCH(1,(GMW!$NE$2:$NE$60=G$3)*(GMW!$ND$2:$ND$60=G$4)*(GMW!$NF$2:$NF$60=G$1),0),$F7-1966)} -> 247921 | H7: {=INDEX(GMW!$A$2:$NF$60,MATCH(1,(GMW!$NE$2:$NE$60=H$3)*(GMW!$ND$2:$ND$60=H$4)*(GMW!$NF$2:$NF$60=H$1),0),$F7-1966)} -> 1514.625 | I7: {=INDEX(GMW!$A$2:$NF$60,MATCH(1,(GMW!$NE$2:$NE$60=I$3)*(GMW!$ND$2:$ND$60=I$4)*(GMW!$NF$2:$NF$60=I$1),0),$F7-1966)} -> 52242.65 | J7: {=INDEX(GMW!$A$2:$NF$60,MATCH(1,(GMW!$NE$2:$NE$60=J$3)*(GMW!$ND$2:$ND$60=J$4)*(GMW!$NF$2:$NF$60=J$1),0),$F7-1966)} -> 386.07 | K7: {=INDEX(GMW!$A$2:$NF$60,MATCH(1,(GMW!$NE$2:$NE$60=K$3)*(GMW!$ND$2:$ND$60=K$4)*(GMW!$NF$2:$NF$60=K$1),0),$F7-1966)} -> 244.379 | L7: {=INDEX(GMW!$A$2:$NF$60,MATCH(1,(GMW!$NE$2:$NE$60=L$3)*(GMW!$ND$2:$ND$60=L$4)*(GMW!$NF$2:$NF$60=L$1),0),$F7-1966)} -> 223.0287 | M7: {=INDEX(GMW!$A$2:$NF$60,MATCH(1,(GMW!$NE$2:$NE$60=M$3)*(GMW!$ND$2:$ND$60=M$4)*(GMW!$NF$2:$NF$60=M$1),0),$F7-1966)} -> 174319.5 | N7: {=INDEX(GMW!$A$2:$NF$60,MATCH(1,(GMW!$NE$2:$NE$60=N$3)*(GMW!$ND$2:$ND$60=N$4)*(GMW!$NF$2:$NF$60=N$1),0),$F7-1966)} -> -145 | ... AH7: {=INDEX(GMW!$A$2:$NF$60,MATCH(1,(GMW!$NE$2:$NE$60=AH$3)*(GMW!$ND$2:$ND$60=AH$4)*(GMW!$NF$2:$NF$60=AH$1),0),$F7-1966)} -> 31189
B8: 1973 | C8: 1973 | F8: =+F7+1 -> 1974 | G8: {=INDEX(GMW!$A$2:$NF$60,MATCH(1,(GMW!$NE$2:$NE$60=G$3)*(GMW!$ND$2:$ND$60=G$4)*(GMW!$NF$2:$NF$60=G$1),0),$F8-1966)} -> 248384 | H8: {=INDEX(GMW!$A$2:$NF$60,MATCH(1,(GMW!$NE$2:$NE$60=H$3)*(GMW!$ND$2:$ND$60=H$4)*(GMW!$NF$2:$NF$60=H$1),0),$F8-1966)} -> 1531.125 | I8: {=INDEX(GMW!$A$2:$NF$60,MATCH(1,(GMW!$NE$2:$NE$60=I$3)*(GMW!$ND$2:$ND$60=I$4)*(GMW!$NF$2:$NF$60=I$1),0),$F8-1966)} -> 52722.43 | J8: {=INDEX(GMW!$A$2:$NF$60,MATCH(1,(GMW!$NE$2:$NE$60=J$3)*(GMW!$ND$2:$ND$60=J$4)*(GMW!$NF$2:$NF$60=J$1),0),$F8-1966)} -> 388.81 | K8: {=INDEX(GMW!$A$2:$NF$60,MATCH(1,(GMW!$NE$2:$NE$60=K$3)*(GMW!$ND$2:$ND$60=K$4)*(GMW!$NF$2:$NF$60=K$1),0),$F8-1966)} -> 247.949 | L8: {=INDEX(GMW!$A$2:$NF$60,MATCH(1,(GMW!$NE$2:$NE$60=L$3)*(GMW!$ND$2:$ND$60=L$4)*(GMW!$NF$2:$NF$60=L$1),0),$F8-1966)} -> 229.7104 | M8: {=INDEX(GMW!$A$2:$NF$60,MATCH(1,(GMW!$NE$2:$NE$60=M$3)*(GMW!$ND$2:$ND$60=M$4)*(GMW!$NF$2:$NF$60=M$1),0),$F8-1966)} -> 175982.5 | N8: {=INDEX(GMW!$A$2:$NF$60,MATCH(1,(GMW!$NE$2:$NE$60=N$3)*(GMW!$ND$2:$ND$60=N$4)*(GMW!$NF$2:$NF$60=N$1),0),$F8-1966)} -> -1195 | ... AH8: {=INDEX(GMW!$A$2:$NF$60,MATCH(1,(GMW!$NE$2:$NE$60=AH$3)*(GMW!$ND$2:$ND$60=AH$4)*(GMW!$NF$2:$NF$60=AH$1),0),$F8-1966)} -> 32510
B9: 1973 | C9: 1973 | F9: =+F8+1 -> 1975 | G9: {=INDEX(GMW!$A$2:$NF$60,MATCH(1,(GMW!$NE$2:$NE$60=G$3)*(GMW!$ND$2:$ND$60=G$4)*(GMW!$NF$2:$NF$60=G$1),0),$F9-1966)} -> 246082 | H9: {=INDEX(GMW!$A$2:$NF$60,MATCH(1,(GMW!$NE$2:$NE$60=H$3)*(GMW!$ND$2:$ND$60=H$4)*(GMW!$NF$2:$NF$60=H$1),0),$F9-1966)} -> 1523.075 | I9: {=INDEX(GMW!$A$2:$NF$60,MATCH(1,(GMW!$NE$2:$NE$60=I$3)*(GMW!$ND$2:$ND$60=I$4)*(GMW!$NF$2:$NF$60=I$1),0),$F9-1966)} -> 52875.77 | J9: {=INDEX(GMW!$A$2:$NF$60,MATCH(1,(GMW!$NE$2:$NE$60=J$3)*(GMW!$ND$2:$ND$60=J$4)*(GMW!$NF$2:$NF$60=J$1),0),$F9-1966)} -> 390.14 | K9: {=INDEX(GMW!$A$2:$NF$60,MATCH(1,(GMW!$NE$2:$NE$60=K$3)*(GMW!$ND$2:$ND$60=K$4)*(GMW!$NF$2:$NF$60=K$1),0),$F9-1966)} -> 251.887 | L9: {=INDEX(GMW!$A$2:$NF$60,MATCH(1,(GMW!$NE$2:$NE$60=L$3)*(GMW!$ND$2:$ND$60=L$4)*(GMW!$NF$2:$NF$60=L$1),0),$F9-1966)} -> 237.0208 | M9: {=INDEX(GMW!$A$2:$NF$60,MATCH(1,(GMW!$NE$2:$NE$60=M$3)*(GMW!$ND$2:$ND$60=M$4)*(GMW!$NF$2:$NF$60=M$1),0),$F9-1966)} -> 176800.8 | N9: {=INDEX(GMW!$A$2:$NF$60,MATCH(1,(GMW!$NE$2:$NE$60=N$3)*(GMW!$ND$2:$ND$60=N$4)*(GMW!$NF$2:$NF$60=N$1),0),$F9-1966)} -> -676 | ... AH9: {=INDEX(GMW!$A$2:$NF$60,MATCH(1,(GMW!$NE$2:$NE$60=AH$3)*(GMW!$ND$2:$ND$60=AH$4)*(GMW!$NF$2:$NF$60=AH$1),0),$F9-1966)} -> 33631
B10: 1973 | C10: 1973 | E10: 1973 | F10: =+F9+1 -> 1976 | G10: {=INDEX(GMW!$A$2:$NF$60,MATCH(1,(GMW!$NE$2:$NE$60=G$3)*(GMW!$ND$2:$ND$60=G$4)*(GMW!$NF$2:$NF$60=G$1),0),$F10-1966)} -> 245140 | H10: {=INDEX(GMW!$A$2:$NF$60,MATCH(1,(GMW!$NE$2:$NE$60=H$3)*(GMW!$ND$2:$ND$60=H$4)*(GMW!$NF$2:$NF$60=H$1),0),$F10-1966)} -> 1537.525 | I10: {=INDEX(GMW!$A$2:$NF$60,MATCH(1,(GMW!$NE$2:$NE$60=I$3)*(GMW!$ND$2:$ND$60=I$4)*(GMW!$NF$2:$NF$60=I$1),0),$F10-1966)} -> 53539.66 | J10: {=INDEX(GMW!$A$2:$NF$60,MATCH(1,(GMW!$NE$2:$NE$60=J$3)*(GMW!$ND$2:$ND$60=J$4)*(GMW!$NF$2:$NF$60=J$1),0),$F10-1966)} -> 391.12 | K10: {=INDEX(GMW!$A$2:$NF$60,MATCH(1,(GMW!$NE$2:$NE$60=K$3)*(GMW!$ND$2:$ND$60=K$4)*(GMW!$NF$2:$NF$60=K$1),0),$F10-1966)} -> 254.935 | L10: {=INDEX(GMW!$A$2:$NF$60,MATCH(1,(GMW!$NE$2:$NE$60=L$3)*(GMW!$ND$2:$ND$60=L$4)*(GMW!$NF$2:$NF$60=L$1),0),$F10-1966)} -> 242.81 | M10: {=INDEX(GMW!$A$2:$NF$60,MATCH(1,(GMW!$NE$2:$NE$60=M$3)*(GMW!$ND$2:$ND$60=M$4)*(GMW!$NF$2:$NF$60=M$1),0),$F10-1966)} -> 180061.8 | N10: {=INDEX(GMW!$A$2:$NF$60,MATCH(1,(GMW!$NE$2:$NE$60=N$3)*(GMW!$ND$2:$ND$60=N$4)*(GMW!$NF$2:$NF$60=N$1),0),$F10-1966)} -> -724 | ... AH10: {=INDEX(GMW!$A$2:$NF$60,MATCH(1,(GMW!$NE$2:$NE$60=AH$3)*(GMW!$ND$2:$ND$60=AH$4)*(GMW!$NF$2:$NF$60=AH$1),0),$F10-1966)} -> 35636
A11: 1974 | B11: =+B7+1 -> 1974 | C11: 1973 | D11: 1973 | F11: =+F10+1 -> 1977 | G11: {=INDEX(GMW!$A$2:$NF$60,MATCH(1,(GMW!$NE$2:$NE$60=G$3)*(GMW!$ND$2:$ND$60=G$4)*(GMW!$NF$2:$NF$60=G$1),0),$F11-1966)} -> 238319 | H11: {=INDEX(GMW!$A$2:$NF$60,MATCH(1,(GMW!$NE$2:$NE$60=H$3)*(GMW!$ND$2:$ND$60=H$4)*(GMW!$NF$2:$NF$60=H$1),0),$F11-1966)} -> 1524.325 | I11: {=INDEX(GMW!$A$2:$NF$60,MATCH(1,(GMW!$NE$2:$NE$60=I$3)*(GMW!$ND$2:$ND$60=I$4)*(GMW!$NF$2:$NF$60=I$1),0),$F11-1966)} -> 51759.14 | J11: {=INDEX(GMW!$A$2:$NF$60,MATCH(1,(GMW!$NE$2:$NE$60=J$3)*(GMW!$ND$2:$ND$60=J$4)*(GMW!$NF$2:$NF$60=J$1),0),$F11-1966)} -> 394.27 | K11: {=INDEX(GMW!$A$2:$NF$60,MATCH(1,(GMW!$NE$2:$NE$60=K$3)*(GMW!$ND$2:$ND$60=K$4)*(GMW!$NF$2:$NF$60=K$1),0),$F11-1966)} -> 259.118 | L11: {=INDEX(GMW!$A$2:$NF$60,MATCH(1,(GMW!$NE$2:$NE$60=L$3)*(GMW!$ND$2:$ND$60=L$4)*(GMW!$NF$2:$NF$60=L$1),0),$F11-1966)} -> 244.7785 | M11: {=INDEX(GMW!$A$2:$NF$60,MATCH(1,(GMW!$NE$2:$NE$60=M$3)*(GMW!$ND$2:$ND$60=M$4)*(GMW!$NF$2:$NF$60=M$1),0),$F11-1966)} -> 181552 | N11: {=INDEX(GMW!$A$2:$NF$60,MATCH(1,(GMW!$NE$2:$NE$60=N$3)*(GMW!$ND$2:$ND$60=N$4)*(GMW!$NF$2:$NF$60=N$1),0),$F11-1966)} -> -788 | ... AH11: {=INDEX(GMW!$A$2:$NF$60,MATCH(1,(GMW!$NE$2:$NE$60=AH$3)*(GMW!$ND$2:$ND$60=AH$4)*(GMW!$NF$2:$NF$60=AH$1),0),$F11-1966)} -> 37325
B12: =+B8+1 -> 1974 | C12: =+C8+1 -> 1974 | F12: =+F11+1 -> 1978 | G12: {=INDEX(GMW!$A$2:$NF$60,MATCH(1,(GMW!$NE$2:$NE$60=G$3)*(GMW!$ND$2:$ND$60=G$4)*(GMW!$NF$2:$NF$60=G$1),0),$F12-1966)} -> 241752 | H12: {=INDEX(GMW!$A$2:$NF$60,MATCH(1,(GMW!$NE$2:$NE$60=H$3)*(GMW!$ND$2:$ND$60=H$4)*(GMW!$NF$2:$NF$60=H$1),0),$F12-1966)} -> 1527.95 | I12: {=INDEX(GMW!$A$2:$NF$60,MATCH(1,(GMW!$NE$2:$NE$60=I$3)*(GMW!$ND$2:$ND$60=I$4)*(GMW!$NF$2:$NF$60=I$1),0),$F12-1966)} -> 52134.51 | J12: {=INDEX(GMW!$A$2:$NF$60,MATCH(1,(GMW!$NE$2:$NE$60=J$3)*(GMW!$ND$2:$ND$60=J$4)*(GMW!$NF$2:$NF$60=J$1),0),$F12-1966)} -> 393.93 | K12: {=INDEX(GMW!$A$2:$NF$60,MATCH(1,(GMW!$NE$2:$NE$60=K$3)*(GMW!$ND$2:$ND$60=K$4)*(GMW!$NF$2:$NF$60=K$1),0),$F12-1966)} -> 260.946 | L12: {=INDEX(GMW!$A$2:$NF$60,MATCH(1,(GMW!$NE$2:$NE$60=L$3)*(GMW!$ND$2:$ND$60=L$4)*(GMW!$NF$2:$NF$60=L$1),0),$F12-1966)} -> 247.1172 | M12: {=INDEX(GMW!$A$2:$NF$60,MATCH(1,(GMW!$NE$2:$NE$60=M$3)*(GMW!$ND$2:$ND$60=M$4)*(GMW!$NF$2:$NF$60=M$1),0),$F12-1966)} -> 183414.3 | N12: {=INDEX(GMW!$A$2:$NF$60,MATCH(1,(GMW!$NE$2:$NE$60=N$3)*(GMW!$ND$2:$ND$60=N$4)*(GMW!$NF$2:$NF$60=N$1),0),$F12-1966)} -> -631 | ... AH12: {=INDEX(GMW!$A$2:$NF$60,MATCH(1,(GMW!$NE$2:$NE$60=AH$3)*(GMW!$ND$2:$ND$60=AH$4)*(GMW!$NF$2:$NF$60=AH$1),0),$F12-1966)} -> 38990
B13: =+B9+1 -> 1974 | C13: =+C9+1 -> 1974 | F13: =+F12+1 -> 1979 | G13: {=INDEX(GMW!$A$2:$NF$60,MATCH(1,(GMW!$NE$2:$NE$60=G$3)*(GMW!$ND$2:$ND$60=G$4)*(GMW!$NF$2:$NF$60=G$1),0),$F13-1966)} -> 243197 | H13: {=INDEX(GMW!$A$2:$NF$60,MATCH(1,(GMW!$NE$2:$NE$60=H$3)*(GMW!$ND$2:$ND$60=H$4)*(GMW!$NF$2:$NF$60=H$1),0),$F13-1966)} -> 1513.5 | I13: {=INDEX(GMW!$A$2:$NF$60,MATCH(1,(GMW!$NE$2:$NE$60=I$3)*(GMW!$ND$2:$ND$60=I$4)*(GMW!$NF$2:$NF$60=I$1),0),$F13-1966)} -> 52810.48 | J13: {=INDEX(GMW!$A$2:$NF$60,MATCH(1,(GMW!$NE$2:$NE$60=J$3)*(GMW!$ND$2:$ND$60=J$4)*(GMW!$NF$2:$NF$60=J$1),0),$F13-1966)} -> 394.09 | K13: {=INDEX(GMW!$A$2:$NF$60,MATCH(1,(GMW!$NE$2:$NE$60=K$3)*(GMW!$ND$2:$ND$60=K$4)*(GMW!$NF$2:$NF$60=K$1),0),$F13-1966)} -> 263.841 | L13: {=INDEX(GMW!$A$2:$NF$60,MATCH(1,(GMW!$NE$2:$NE$60=L$3)*(GMW!$ND$2:$ND$60=L$4)*(GMW!$NF$2:$NF$60=L$1),0),$F13-1966)} -> 247.5283 | M13: {=INDEX(GMW!$A$2:$NF$60,MATCH(1,(GMW!$NE$2:$NE$60=M$3)*(GMW!$ND$2:$ND$60=M$4)*(GMW!$NF$2:$NF$60=M$1),0),$F13-1966)} -> 183449.5 | N13: {=INDEX(GMW!$A$2:$NF$60,MATCH(1,(GMW!$NE$2:$NE$60=N$3)*(GMW!$ND$2:$ND$60=N$4)*(GMW!$NF$2:$NF$60=N$1),0),$F13-1966)} -> -1345 | ... AH13: {=INDEX(GMW!$A$2:$NF$60,MATCH(1,(GMW!$NE$2:$NE$60=AH$3)*(GMW!$ND$2:$ND$60=AH$4)*(GMW!$NF$2:$NF$60=AH$1),0),$F13-1966)} -> 40561
B14: =+B10+1 -> 1974 | C14: =+C10+1 -> 1974 | E14: =+E10+1 -> 1974 | F14: =+F13+1 -> 1980 | G14: {=INDEX(GMW!$A$2:$NF$60,MATCH(1,(GMW!$NE$2:$NE$60=G$3)*(GMW!$ND$2:$ND$60=G$4)*(GMW!$NF$2:$NF$60=G$1),0),$F14-1966)} -> 239612 | H14: {=INDEX(GMW!$A$2:$NF$60,MATCH(1,(GMW!$NE$2:$NE$60=H$3)*(GMW!$ND$2:$ND$60=H$4)*(GMW!$NF$2:$NF$60=H$1),0),$F14-1966)} -> 1507.625 | I14: {=INDEX(GMW!$A$2:$NF$60,MATCH(1,(GMW!$NE$2:$NE$60=I$3)*(GMW!$ND$2:$ND$60=I$4)*(GMW!$NF$2:$NF$60=I$1),0),$F14-1966)} -> 52526.84 | J14: {=INDEX(GMW!$A$2:$NF$60,MATCH(1,(GMW!$NE$2:$NE$60=J$3)*(GMW!$ND$2:$ND$60=J$4)*(GMW!$NF$2:$NF$60=J$1),0),$F14-1966)} -> 389.05 | K14: {=INDEX(GMW!$A$2:$NF$60,MATCH(1,(GMW!$NE$2:$NE$60=K$3)*(GMW!$ND$2:$ND$60=K$4)*(GMW!$NF$2:$NF$60=K$1),0),$F14-1966)} -> 259.134 | L14: {=INDEX(GMW!$A$2:$NF$60,MATCH(1,(GMW!$NE$2:$NE$60=L$3)*(GMW!$ND$2:$ND$60=L$4)*(GMW!$NF$2:$NF$60=L$1),0),$F14-1966)} -> 242.3543 | M14: {=INDEX(GMW!$A$2:$NF$60,MATCH(1,(GMW!$NE$2:$NE$60=M$3)*(GMW!$ND$2:$ND$60=M$4)*(GMW!$NF$2:$NF$60=M$1),0),$F14-1966)} -> 182493.8 | N14: {=INDEX(GMW!$A$2:$NF$60,MATCH(1,(GMW!$NE$2:$NE$60=N$3)*(GMW!$ND$2:$ND$60=N$4)*(GMW!$NF$2:$NF$60=N$1),0),$F14-1966)} -> -1546 | ... AH14: {=INDEX(GMW!$A$2:$NF$60,MATCH(1,(GMW!$NE$2:$NE$60=AH$3)*(GMW!$ND$2:$ND$60=AH$4)*(GMW!$NF$2:$NF$60=AH$1),0),$F14-1966)} -> 41300
A15: 1975 | B15: =+B11+1 -> 1975 | C15: =+C11+1 -> 1974 | D15: =+D11+1 -> 1974 | F15: =+F14+1 -> 1981 | G15: {=INDEX(GMW!$A$2:$NF$60,MATCH(1,(GMW!$NE$2:$NE$60=G$3)*(GMW!$ND$2:$ND$60=G$4)*(GMW!$NF$2:$NF$60=G$1),0),$F15-1966)} -> 239702 | H15: {=INDEX(GMW!$A$2:$NF$60,MATCH(1,(GMW!$NE$2:$NE$60=H$3)*(GMW!$ND$2:$ND$60=H$4)*(GMW!$NF$2:$NF$60=H$1),0),$F15-1966)} -> 1489.25 | I15: {=INDEX(GMW!$A$2:$NF$60,MATCH(1,(GMW!$NE$2:$NE$60=I$3)*(GMW!$ND$2:$ND$60=I$4)*(GMW!$NF$2:$NF$60=I$1),0),$F15-1966)} -> 52595.21 | J15: {=INDEX(GMW!$A$2:$NF$60,MATCH(1,(GMW!$NE$2:$NE$60=J$3)*(GMW!$ND$2:$ND$60=J$4)*(GMW!$NF$2:$NF$60=J$1),0),$F15-1966)} -> 386.82 | K15: {=INDEX(GMW!$A$2:$NF$60,MATCH(1,(GMW!$NE$2:$NE$60=K$3)*(GMW!$ND$2:$ND$60=K$4)*(GMW!$NF$2:$NF$60=K$1),0),$F15-1966)} -> 257.134 | L15: {=INDEX(GMW!$A$2:$NF$60,MATCH(1,(GMW!$NE$2:$NE$60=L$3)*(GMW!$ND$2:$ND$60=L$4)*(GMW!$NF$2:$NF$60=L$1),0),$F15-1966)} -> 238.1379 | M15: {=INDEX(GMW!$A$2:$NF$60,MATCH(1,(GMW!$NE$2:$NE$60=M$3)*(GMW!$ND$2:$ND$60=M$4)*(GMW!$NF$2:$NF$60=M$1),0),$F15-1966)} -> 181499.5 | N15: {=INDEX(GMW!$A$2:$NF$60,MATCH(1,(GMW!$NE$2:$NE$60=N$3)*(GMW!$ND$2:$ND$60=N$4)*(GMW!$NF$2:$NF$60=N$1),0),$F15-1966)} -> -2070 | ... AH15: {=INDEX(GMW!$A$2:$NF$60,MATCH(1,(GMW!$NE$2:$NE$60=AH$3)*(GMW!$ND$2:$ND$60=AH$4)*(GMW!$NF$2:$NF$60=AH$1),0),$F15-1966)} -> 41861
B16: =+B12+1 -> 1975 | C16: =+C12+1 -> 1975 | F16: =+F15+1 -> 1982 | G16: {=INDEX(GMW!$A$2:$NF$60,MATCH(1,(GMW!$NE$2:$NE$60=G$3)*(GMW!$ND$2:$ND$60=G$4)*(GMW!$NF$2:$NF$60=G$1),0),$F16-1966)} -> 235807 | H16: {=INDEX(GMW!$A$2:$NF$60,MATCH(1,(GMW!$NE$2:$NE$60=H$3)*(GMW!$ND$2:$ND$60=H$4)*(GMW!$NF$2:$NF$60=H$1),0),$F16-1966)} -> 1499.9 | I16: {=INDEX(GMW!$A$2:$NF$60,MATCH(1,(GMW!$NE$2:$NE$60=I$3)*(GMW!$ND$2:$ND$60=I$4)*(GMW!$NF$2:$NF$60=I$1),0),$F16-1966)} -> 53789.34 | J16: {=INDEX(GMW!$A$2:$NF$60,MATCH(1,(GMW!$NE$2:$NE$60=J$3)*(GMW!$ND$2:$ND$60=J$4)*(GMW!$NF$2:$NF$60=J$1),0),$F16-1966)} -> 384.92 | K16: {=INDEX(GMW!$A$2:$NF$60,MATCH(1,(GMW!$NE$2:$NE$60=K$3)*(GMW!$ND$2:$ND$60=K$4)*(GMW!$NF$2:$NF$60=K$1),0),$F16-1966)} -> 257.051 | L16: {=INDEX(GMW!$A$2:$NF$60,MATCH(1,(GMW!$NE$2:$NE$60=L$3)*(GMW!$ND$2:$ND$60=L$4)*(GMW!$NF$2:$NF$60=L$1),0),$F16-1966)} -> 238.0164 | M16: {=INDEX(GMW!$A$2:$NF$60,MATCH(1,(GMW!$NE$2:$NE$60=M$3)*(GMW!$ND$2:$ND$60=M$4)*(GMW!$NF$2:$NF$60=M$1),0),$F16-1966)} -> 183828 | N16: {=INDEX(GMW!$A$2:$NF$60,MATCH(1,(GMW!$NE$2:$NE$60=N$3)*(GMW!$ND$2:$ND$60=N$4)*(GMW!$NF$2:$NF$60=N$1),0),$F16-1966)} -> -1658 | ... AH16: {=INDEX(GMW!$A$2:$NF$60,MATCH(1,(GMW!$NE$2:$NE$60=AH$3)*(GMW!$ND$2:$ND$60=AH$4)*(GMW!$NF$2:$NF$60=AH$1),0),$F16-1966)} -> 43406
B17: =+B13+1 -> 1975 | C17: =+C13+1 -> 1975 | F17: =+F16+1 -> 1983 | G17: {=INDEX(GMW!$A$2:$NF$60,MATCH(1,(GMW!$NE$2:$NE$60=G$3)*(GMW!$ND$2:$ND$60=G$4)*(GMW!$NF$2:$NF$60=G$1),0),$F17-1966)} -> 235105 | H17: {=INDEX(GMW!$A$2:$NF$60,MATCH(1,(GMW!$NE$2:$NE$60=H$3)*(GMW!$ND$2:$ND$60=H$4)*(GMW!$NF$2:$NF$60=H$1),0),$F17-1966)} -> 1525.575 | I17: {=INDEX(GMW!$A$2:$NF$60,MATCH(1,(GMW!$NE$2:$NE$60=I$3)*(GMW!$ND$2:$ND$60=I$4)*(GMW!$NF$2:$NF$60=I$1),0),$F17-1966)} -> 54409.61 | J17: {=INDEX(GMW!$A$2:$NF$60,MATCH(1,(GMW!$NE$2:$NE$60=J$3)*(GMW!$ND$2:$ND$60=J$4)*(GMW!$NF$2:$NF$60=J$1),0),$F17-1966)} -> 389.05 | K17: {=INDEX(GMW!$A$2:$NF$60,MATCH(1,(GMW!$NE$2:$NE$60=K$3)*(GMW!$ND$2:$ND$60=K$4)*(GMW!$NF$2:$NF$60=K$1),0),$F17-1966)} -> 256.883 | L17: {=INDEX(GMW!$A$2:$NF$60,MATCH(1,(GMW!$NE$2:$NE$60=L$3)*(GMW!$ND$2:$ND$60=L$4)*(GMW!$NF$2:$NF$60=L$1),0),$F17-1966)} -> 241.3983 | M17: {=INDEX(GMW!$A$2:$NF$60,MATCH(1,(GMW!$NE$2:$NE$60=M$3)*(GMW!$ND$2:$ND$60=M$4)*(GMW!$NF$2:$NF$60=M$1),0),$F17-1966)} -> 187354.8 | N17: {=INDEX(GMW!$A$2:$NF$60,MATCH(1,(GMW!$NE$2:$NE$60=N$3)*(GMW!$ND$2:$ND$60=N$4)*(GMW!$NF$2:$NF$60=N$1),0),$F17-1966)} -> -1874 | ... AH17: {=INDEX(GMW!$A$2:$NF$60,MATCH(1,(GMW!$NE$2:$NE$60=AH$3)*(GMW!$ND$2:$ND$60=AH$4)*(GMW!$NF$2:$NF$60=AH$1),0),$F17-1966)} -> 45554
B18: =+B14+1 -> 1975 | C18: =+C14+1 -> 1975 | E18: =+E14+1 -> 1975 | F18: =+F17+1 -> 1984 | G18: {=INDEX(GMW!$A$2:$NF$60,MATCH(1,(GMW!$NE$2:$NE$60=G$3)*(GMW!$ND$2:$ND$60=G$4)*(GMW!$NF$2:$NF$60=G$1),0),$F18-1966)} -> 237747 | H18: {=INDEX(GMW!$A$2:$NF$60,MATCH(1,(GMW!$NE$2:$NE$60=H$3)*(GMW!$ND$2:$ND$60=H$4)*(GMW!$NF$2:$NF$60=H$1),0),$F18-1966)} -> 1546.125 | I18: {=INDEX(GMW!$A$2:$NF$60,MATCH(1,(GMW!$NE$2:$NE$60=I$3)*(GMW!$ND$2:$ND$60=I$4)*(GMW!$NF$2:$NF$60=I$1),0),$F18-1966)} -> 54986.97 | J18: {=INDEX(GMW!$A$2:$NF$60,MATCH(1,(GMW!$NE$2:$NE$60=J$3)*(GMW!$ND$2:$ND$60=J$4)*(GMW!$NF$2:$NF$60=J$1),0),$F18-1966)} -> 396.83 | K18: {=INDEX(GMW!$A$2:$NF$60,MATCH(1,(GMW!$NE$2:$NE$60=K$3)*(GMW!$ND$2:$ND$60=K$4)*(GMW!$NF$2:$NF$60=K$1),0),$F18-1966)} -> 262.376 | L18: {=INDEX(GMW!$A$2:$NF$60,MATCH(1,(GMW!$NE$2:$NE$60=L$3)*(GMW!$ND$2:$ND$60=L$4)*(GMW!$NF$2:$NF$60=L$1),0),$F18-1966)} -> 244.1035 | M18: {=INDEX(GMW!$A$2:$NF$60,MATCH(1,(GMW!$NE$2:$NE$60=M$3)*(GMW!$ND$2:$ND$60=M$4)*(GMW!$NF$2:$NF$60=M$1),0),$F18-1966)} -> 189522.8 | N18: {=INDEX(GMW!$A$2:$NF$60,MATCH(1,(GMW!$NE$2:$NE$60=N$3)*(GMW!$ND$2:$ND$60=N$4)*(GMW!$NF$2:$NF$60=N$1),0),$F18-1966)} -> -1609 | ... AH18: {=INDEX(GMW!$A$2:$NF$60,MATCH(1,(GMW!$NE$2:$NE$60=AH$3)*(GMW!$ND$2:$ND$60=AH$4)*(GMW!$NF$2:$NF$60=AH$1),0),$F18-1966)} -> 47107
A19: 1976 | B19: =+B15+1 -> 1976 | C19: =+C15+1 -> 1975 | D19: =+D15+1 -> 1975 | F19: =+F18+1 -> 1985 | G19: {=INDEX(GMW!$A$2:$NF$60,MATCH(1,(GMW!$NE$2:$NE$60=G$3)*(GMW!$ND$2:$ND$60=G$4)*(GMW!$NF$2:$NF$60=G$1),0),$F19-1966)} -> 241709 | H19: {=INDEX(GMW!$A$2:$NF$60,MATCH(1,(GMW!$NE$2:$NE$60=H$3)*(GMW!$ND$2:$ND$60=H$4)*(GMW!$NF$2:$NF$60=H$1),0),$F19-1966)} -> 1580.9 | I19: {=INDEX(GMW!$A$2:$NF$60,MATCH(1,(GMW!$NE$2:$NE$60=I$3)*(GMW!$ND$2:$ND$60=I$4)*(GMW!$NF$2:$NF$60=I$1),0),$F19-1966)} -> 55458.37 | J19: {=INDEX(GMW!$A$2:$NF$60,MATCH(1,(GMW!$NE$2:$NE$60=J$3)*(GMW!$ND$2:$ND$60=J$4)*(GMW!$NF$2:$NF$60=J$1),0),$F19-1966)} -> 400.23 | K19: {=INDEX(GMW!$A$2:$NF$60,MATCH(1,(GMW!$NE$2:$NE$60=K$3)*(GMW!$ND$2:$ND$60=K$4)*(GMW!$NF$2:$NF$60=K$1),0),$F19-1966)} -> 264.851 | L19: {=INDEX(GMW!$A$2:$NF$60,MATCH(1,(GMW!$NE$2:$NE$60=L$3)*(GMW!$ND$2:$ND$60=L$4)*(GMW!$NF$2:$NF$60=L$1),0),$F19-1966)} -> 248.4038 | M19: {=INDEX(GMW!$A$2:$NF$60,MATCH(1,(GMW!$NE$2:$NE$60=M$3)*(GMW!$ND$2:$ND$60=M$4)*(GMW!$NF$2:$NF$60=M$1),0),$F19-1966)} -> 192825.5 | N19: {=INDEX(GMW!$A$2:$NF$60,MATCH(1,(GMW!$NE$2:$NE$60=N$3)*(GMW!$ND$2:$ND$60=N$4)*(GMW!$NF$2:$NF$60=N$1),0),$F19-1966)} -> -2510 | ... AH19: {=INDEX(GMW!$A$2:$NF$60,MATCH(1,(GMW!$NE$2:$NE$60=AH$3)*(GMW!$ND$2:$ND$60=AH$4)*(GMW!$NF$2:$NF$60=AH$1),0),$F19-1966)} -> 49062
B20: =+B16+1 -> 1976 | C20: =+C16+1 -> 1976 | F20: =+F19+1 -> 1986 | G20: {=INDEX(GMW!$A$2:$NF$60,MATCH(1,(GMW!$NE$2:$NE$60=G$3)*(GMW!$ND$2:$ND$60=G$4)*(GMW!$NF$2:$NF$60=G$1),0),$F20-1966)} -> 241380 | H20: {=INDEX(GMW!$A$2:$NF$60,MATCH(1,(GMW!$NE$2:$NE$60=H$3)*(GMW!$ND$2:$ND$60=H$4)*(GMW!$NF$2:$NF$60=H$1),0),$F20-1966)} -> 1592.5 | I20: {=INDEX(GMW!$A$2:$NF$60,MATCH(1,(GMW!$NE$2:$NE$60=I$3)*(GMW!$ND$2:$ND$60=I$4)*(GMW!$NF$2:$NF$60=I$1),0),$F20-1966)} -> 55787.51 | J20: {=INDEX(GMW!$A$2:$NF$60,MATCH(1,(GMW!$NE$2:$NE$60=J$3)*(GMW!$ND$2:$ND$60=J$4)*(GMW!$NF$2:$NF$60=J$1),0),$F20-1966)} -> 406.27 | K20: {=INDEX(GMW!$A$2:$NF$60,MATCH(1,(GMW!$NE$2:$NE$60=K$3)*(GMW!$ND$2:$ND$60=K$4)*(GMW!$NF$2:$NF$60=K$1),0),$F20-1966)} -> 268.472 | L20: {=INDEX(GMW!$A$2:$NF$60,MATCH(1,(GMW!$NE$2:$NE$60=L$3)*(GMW!$ND$2:$ND$60=L$4)*(GMW!$NF$2:$NF$60=L$1),0),$F20-1966)} -> 252.8942 | M20: {=INDEX(GMW!$A$2:$NF$60,MATCH(1,(GMW!$NE$2:$NE$60=M$3)*(GMW!$ND$2:$ND$60=M$4)*(GMW!$NF$2:$NF$60=M$1),0),$F20-1966)} -> 196983.8 | N20: {=INDEX(GMW!$A$2:$NF$60,MATCH(1,(GMW!$NE$2:$NE$60=N$3)*(GMW!$ND$2:$ND$60=N$4)*(GMW!$NF$2:$NF$60=N$1),0),$F20-1966)} -> -1926 | ... AH20: {=INDEX(GMW!$A$2:$NF$60,MATCH(1,(GMW!$NE$2:$NE$60=AH$3)*(GMW!$ND$2:$ND$60=AH$4)*(GMW!$NF$2:$NF$60=AH$1),0),$F20-1966)} -> 51563
B21: =+B17+1 -> 1976 | C21: =+C17+1 -> 1976 | F21: =+F20+1 -> 1987 | G21: {=INDEX(GMW!$A$2:$NF$60,MATCH(1,(GMW!$NE$2:$NE$60=G$3)*(GMW!$ND$2:$ND$60=G$4)*(GMW!$NF$2:$NF$60=G$1),0),$F21-1966)} -> 244367 | H21: {=INDEX(GMW!$A$2:$NF$60,MATCH(1,(GMW!$NE$2:$NE$60=H$3)*(GMW!$ND$2:$ND$60=H$4)*(GMW!$NF$2:$NF$60=H$1),0),$F21-1966)} -> 1601.225 | I21: {=INDEX(GMW!$A$2:$NF$60,MATCH(1,(GMW!$NE$2:$NE$60=I$3)*(GMW!$ND$2:$ND$60=I$4)*(GMW!$NF$2:$NF$60=I$1),0),$F21-1966)} -> 56585.37 | J21: {=INDEX(GMW!$A$2:$NF$60,MATCH(1,(GMW!$NE$2:$NE$60=J$3)*(GMW!$ND$2:$ND$60=J$4)*(GMW!$NF$2:$NF$60=J$1),0),$F21-1966)} -> 406.44 | K21: {=INDEX(GMW!$A$2:$NF$60,MATCH(1,(GMW!$NE$2:$NE$60=K$3)*(GMW!$ND$2:$ND$60=K$4)*(GMW!$NF$2:$NF$60=K$1),0),$F21-1966)} -> 271.536 | L21: {=INDEX(GMW!$A$2:$NF$60,MATCH(1,(GMW!$NE$2:$NE$60=L$3)*(GMW!$ND$2:$ND$60=L$4)*(GMW!$NF$2:$NF$60=L$1),0),$F21-1966)} -> 259.3207 | M21: {=INDEX(GMW!$A$2:$NF$60,MATCH(1,(GMW!$NE$2:$NE$60=M$3)*(GMW!$ND$2:$ND$60=M$4)*(GMW!$NF$2:$NF$60=M$1),0),$F21-1966)} -> 197893.3 | N21: {=INDEX(GMW!$A$2:$NF$60,MATCH(1,(GMW!$NE$2:$NE$60=N$3)*(GMW!$ND$2:$ND$60=N$4)*(GMW!$NF$2:$NF$60=N$1),0),$F21-1966)} -> -2444 | ... AH21: {=INDEX(GMW!$A$2:$NF$60,MATCH(1,(GMW!$NE$2:$NE$60=AH$3)*(GMW!$ND$2:$ND$60=AH$4)*(GMW!$NF$2:$NF$60=AH$1),0),$F21-1966)} -> 52112
B22: =+B18+1 -> 1976 | C22: =+C18+1 -> 1976 | E22: =+E18+1 -> 1976 | F22: =+F21+1 -> 1988 | G22: {=INDEX(GMW!$A$2:$NF$60,MATCH(1,(GMW!$NE$2:$NE$60=G$3)*(GMW!$ND$2:$ND$60=G$4)*(GMW!$NF$2:$NF$60=G$1),0),$F22-1966)} -> 249511 | H22: {=INDEX(GMW!$A$2:$NF$60,MATCH(1,(GMW!$NE$2:$NE$60=H$3)*(GMW!$ND$2:$ND$60=H$4)*(GMW!$NF$2:$NF$60=H$1),0),$F22-1966)} -> 1612.8 | I22: {=INDEX(GMW!$A$2:$NF$60,MATCH(1,(GMW!$NE$2:$NE$60=I$3)*(GMW!$ND$2:$ND$60=I$4)*(GMW!$NF$2:$NF$60=I$1),0),$F22-1966)} -> 56653.35 | J22: {=INDEX(GMW!$A$2:$NF$60,MATCH(1,(GMW!$NE$2:$NE$60=J$3)*(GMW!$ND$2:$ND$60=J$4)*(GMW!$NF$2:$NF$60=J$1),0),$F22-1966)} -> 413.88 | K22: {=INDEX(GMW!$A$2:$NF$60,MATCH(1,(GMW!$NE$2:$NE$60=K$3)*(GMW!$ND$2:$ND$60=K$4)*(GMW!$NF$2:$NF$60=K$1),0),$F22-1966)} -> 273.453 | L22: {=INDEX(GMW!$A$2:$NF$60,MATCH(1,(GMW!$NE$2:$NE$60=L$3)*(GMW!$ND$2:$ND$60=L$4)*(GMW!$NF$2:$NF$60=L$1),0),$F22-1966)} -> 263.8197 | M22: {=INDEX(GMW!$A$2:$NF$60,MATCH(1,(GMW!$NE$2:$NE$60=M$3)*(GMW!$ND$2:$ND$60=M$4)*(GMW!$NF$2:$NF$60=M$1),0),$F22-1966)} -> 198213 | N22: {=INDEX(GMW!$A$2:$NF$60,MATCH(1,(GMW!$NE$2:$NE$60=N$3)*(GMW!$ND$2:$ND$60=N$4)*(GMW!$NF$2:$NF$60=N$1),0),$F22-1966)} -> -1081 | ... AH22: {=INDEX(GMW!$A$2:$NF$60,MATCH(1,(GMW!$NE$2:$NE$60=AH$3)*(GMW!$ND$2:$ND$60=AH$4)*(GMW!$NF$2:$NF$60=AH$1),0),$F22-1966)} -> 53249
A23: 1977 | B23: =+B19+1 -> 1977 | C23: =+C19+1 -> 1976 | D23: =+D19+1 -> 1976 | F23: =+F22+1 -> 1989 | G23: {=INDEX(GMW!$A$2:$NF$60,MATCH(1,(GMW!$NE$2:$NE$60=G$3)*(GMW!$ND$2:$ND$60=G$4)*(GMW!$NF$2:$NF$60=G$1),0),$F23-1966)} -> 249671 | H23: {=INDEX(GMW!$A$2:$NF$60,MATCH(1,(GMW!$NE$2:$NE$60=H$3)*(GMW!$ND$2:$ND$60=H$4)*(GMW!$NF$2:$NF$60=H$1),0),$F23-1966)} -> 1631.925 | I23: {=INDEX(GMW!$A$2:$NF$60,MATCH(1,(GMW!$NE$2:$NE$60=I$3)*(GMW!$ND$2:$ND$60=I$4)*(GMW!$NF$2:$NF$60=I$1),0),$F23-1966)} -> 57921.84 | J23: {=INDEX(GMW!$A$2:$NF$60,MATCH(1,(GMW!$NE$2:$NE$60=J$3)*(GMW!$ND$2:$ND$60=J$4)*(GMW!$NF$2:$NF$60=J$1),0),$F23-1966)} -> 417.53 | K23: {=INDEX(GMW!$A$2:$NF$60,MATCH(1,(GMW!$NE$2:$NE$60=K$3)*(GMW!$ND$2:$ND$60=K$4)*(GMW!$NF$2:$NF$60=K$1),0),$F23-1966)} -> 276.547 | L23: {=INDEX(GMW!$A$2:$NF$60,MATCH(1,(GMW!$NE$2:$NE$60=L$3)*(GMW!$ND$2:$ND$60=L$4)*(GMW!$NF$2:$NF$60=L$1),0),$F23-1966)} -> 263.9241 | M23: {=INDEX(GMW!$A$2:$NF$60,MATCH(1,(GMW!$NE$2:$NE$60=M$3)*(GMW!$ND$2:$ND$60=M$4)*(GMW!$NF$2:$NF$60=M$1),0),$F23-1966)} -> 201253.3 | N23: {=INDEX(GMW!$A$2:$NF$60,MATCH(1,(GMW!$NE$2:$NE$60=N$3)*(GMW!$ND$2:$ND$60=N$4)*(GMW!$NF$2:$NF$60=N$1),0),$F23-1966)} -> -1553 | ... AH23: {=INDEX(GMW!$A$2:$NF$60,MATCH(1,(GMW!$NE$2:$NE$60=AH$3)*(GMW!$ND$2:$ND$60=AH$4)*(GMW!$NF$2:$NF$60=AH$1),0),$F23-1966)} -> 54978
B24: =+B20+1 -> 1977 | C24: =+C20+1 -> 1977 | F24: =+F23+1 -> 1990 | G24: {=INDEX(GMW!$A$2:$NF$60,MATCH(1,(GMW!$NE$2:$NE$60=G$3)*(GMW!$ND$2:$ND$60=G$4)*(GMW!$NF$2:$NF$60=G$1),0),$F24-1966)} -> 247936 | H24: {=INDEX(GMW!$A$2:$NF$60,MATCH(1,(GMW!$NE$2:$NE$60=H$3)*(GMW!$ND$2:$ND$60=H$4)*(GMW!$NF$2:$NF$60=H$1),0),$F24-1966)} -> 1663.625 | I24: {=INDEX(GMW!$A$2:$NF$60,MATCH(1,(GMW!$NE$2:$NE$60=I$3)*(GMW!$ND$2:$ND$60=I$4)*(GMW!$NF$2:$NF$60=I$1),0),$F24-1966)} -> 58330.15 | J24: {=INDEX(GMW!$A$2:$NF$60,MATCH(1,(GMW!$NE$2:$NE$60=J$3)*(GMW!$ND$2:$ND$60=J$4)*(GMW!$NF$2:$NF$60=J$1),0),$F24-1966)} -> 419.84 | K24: {=INDEX(GMW!$A$2:$NF$60,MATCH(1,(GMW!$NE$2:$NE$60=K$3)*(GMW!$ND$2:$ND$60=K$4)*(GMW!$NF$2:$NF$60=K$1),0),$F24-1966)} -> 277.655 | L24: {=INDEX(GMW!$A$2:$NF$60,MATCH(1,(GMW!$NE$2:$NE$60=L$3)*(GMW!$ND$2:$ND$60=L$4)*(GMW!$NF$2:$NF$60=L$1),0),$F24-1966)} -> 262.4543 | M24: {=INDEX(GMW!$A$2:$NF$60,MATCH(1,(GMW!$NE$2:$NE$60=M$3)*(GMW!$ND$2:$ND$60=M$4)*(GMW!$NF$2:$NF$60=M$1),0),$F24-1966)} -> 202280.3 | N24: {=INDEX(GMW!$A$2:$NF$60,MATCH(1,(GMW!$NE$2:$NE$60=N$3)*(GMW!$ND$2:$ND$60=N$4)*(GMW!$NF$2:$NF$60=N$1),0),$F24-1966)} -> -1256 | ... AH24: {=INDEX(GMW!$A$2:$NF$60,MATCH(1,(GMW!$NE$2:$NE$60=AH$3)*(GMW!$ND$2:$ND$60=AH$4)*(GMW!$NF$2:$NF$60=AH$1),0),$F24-1966)} -> 56202
B25: =+B21+1 -> 1977 | C25: =+C21+1 -> 1977 | F25: =+F24+1 -> 1991 | G25: {=INDEX(GMW!$A$2:$NF$60,MATCH(1,(GMW!$NE$2:$NE$60=G$3)*(GMW!$ND$2:$ND$60=G$4)*(GMW!$NF$2:$NF$60=G$1),0),$F25-1966)} -> 249578 | H25: {=INDEX(GMW!$A$2:$NF$60,MATCH(1,(GMW!$NE$2:$NE$60=H$3)*(GMW!$ND$2:$ND$60=H$4)*(GMW!$NF$2:$NF$60=H$1),0),$F25-1966)} -> 1693.625 | I25: {=INDEX(GMW!$A$2:$NF$60,MATCH(1,(GMW!$NE$2:$NE$60=I$3)*(GMW!$ND$2:$ND$60=I$4)*(GMW!$NF$2:$NF$60=I$1),0),$F25-1966)} -> 58729.51 | J25: {=INDEX(GMW!$A$2:$NF$60,MATCH(1,(GMW!$NE$2:$NE$60=J$3)*(GMW!$ND$2:$ND$60=J$4)*(GMW!$NF$2:$NF$60=J$1),0),$F25-1966)} -> 419.68 | K25: {=INDEX(GMW!$A$2:$NF$60,MATCH(1,(GMW!$NE$2:$NE$60=K$3)*(GMW!$ND$2:$ND$60=K$4)*(GMW!$NF$2:$NF$60=K$1),0),$F25-1966)} -> 279.927 | L25: {=INDEX(GMW!$A$2:$NF$60,MATCH(1,(GMW!$NE$2:$NE$60=L$3)*(GMW!$ND$2:$ND$60=L$4)*(GMW!$NF$2:$NF$60=L$1),0),$F25-1966)} -> 259.9991 | M25: {=INDEX(GMW!$A$2:$NF$60,MATCH(1,(GMW!$NE$2:$NE$60=M$3)*(GMW!$ND$2:$ND$60=M$4)*(GMW!$NF$2:$NF$60=M$1),0),$F25-1966)} -> 203469.3 | N25: {=INDEX(GMW!$A$2:$NF$60,MATCH(1,(GMW!$NE$2:$NE$60=N$3)*(GMW!$ND$2:$ND$60=N$4)*(GMW!$NF$2:$NF$60=N$1),0),$F25-1966)} -> -1656 | ... AH25: {=INDEX(GMW!$A$2:$NF$60,MATCH(1,(GMW!$NE$2:$NE$60=AH$3)*(GMW!$ND$2:$ND$60=AH$4)*(GMW!$NF$2:$NF$60=AH$1),0),$F25-1966)} -> 57431
B26: =+B22+1 -> 1977 | C26: =+C22+1 -> 1977 | E26: =+E22+1 -> 1977 | F26: =+F25+1 -> 1992 | G26: {=INDEX(GMW!$A$2:$NF$60,MATCH(1,(GMW!$NE$2:$NE$60=G$3)*(GMW!$ND$2:$ND$60=G$4)*(GMW!$NF$2:$NF$60=G$1),0),$F26-1966)} -> 253819 | H26: {=INDEX(GMW!$A$2:$NF$60,MATCH(1,(GMW!$NE$2:$NE$60=H$3)*(GMW!$ND$2:$ND$60=H$4)*(GMW!$NF$2:$NF$60=H$1),0),$F26-1966)} -> 1693.65 | I26: {=INDEX(GMW!$A$2:$NF$60,MATCH(1,(GMW!$NE$2:$NE$60=I$3)*(GMW!$ND$2:$ND$60=I$4)*(GMW!$NF$2:$NF$60=I$1),0),$F26-1966)} -> 59539.25 | J26: {=INDEX(GMW!$A$2:$NF$60,MATCH(1,(GMW!$NE$2:$NE$60=J$3)*(GMW!$ND$2:$ND$60=J$4)*(GMW!$NF$2:$NF$60=J$1),0),$F26-1966)} -> 426.88 | K26: {=INDEX(GMW!$A$2:$NF$60,MATCH(1,(GMW!$NE$2:$NE$60=K$3)*(GMW!$ND$2:$ND$60=K$4)*(GMW!$NF$2:$NF$60=K$1),0),$F26-1966)} -> 282.16 | L26: {=INDEX(GMW!$A$2:$NF$60,MATCH(1,(GMW!$NE$2:$NE$60=L$3)*(GMW!$ND$2:$ND$60=L$4)*(GMW!$NF$2:$NF$60=L$1),0),$F26-1966)} -> 262.2263 | M26: {=INDEX(GMW!$A$2:$NF$60,MATCH(1,(GMW!$NE$2:$NE$60=M$3)*(GMW!$ND$2:$ND$60=M$4)*(GMW!$NF$2:$NF$60=M$1),0),$F26-1966)} -> 206693.5 | N26: {=INDEX(GMW!$A$2:$NF$60,MATCH(1,(GMW!$NE$2:$NE$60=N$3)*(GMW!$ND$2:$ND$60=N$4)*(GMW!$NF$2:$NF$60=N$1),0),$F26-1966)} -> -1371 | ... AH26: {=INDEX(GMW!$A$2:$NF$60,MATCH(1,(GMW!$NE$2:$NE$60=AH$3)*(GMW!$ND$2:$ND$60=AH$4)*(GMW!$NF$2:$NF$60=AH$1),0),$F26-1966)} -> 58990
A27: 1978 | B27: =+B23+1 -> 1978 | C27: =+C23+1 -> 1977 | D27: =+D23+1 -> 1977 | F27: =+F26+1 -> 1993 | G27: {=INDEX(GMW!$A$2:$NF$60,MATCH(1,(GMW!$NE$2:$NE$60=G$3)*(GMW!$ND$2:$ND$60=G$4)*(GMW!$NF$2:$NF$60=G$1),0),$F27-1966)} -> 256193 | H27: {=INDEX(GMW!$A$2:$NF$60,MATCH(1,(GMW!$NE$2:$NE$60=H$3)*(GMW!$ND$2:$ND$60=H$4)*(GMW!$NF$2:$NF$60=H$1),0),$F27-1966)} -> 1699.075 | I27: {=INDEX(GMW!$A$2:$NF$60,MATCH(1,(GMW!$NE$2:$NE$60=I$3)*(GMW!$ND$2:$ND$60=I$4)*(GMW!$NF$2:$NF$60=I$1),0),$F27-1966)} -> 60686.21 | J27: {=INDEX(GMW!$A$2:$NF$60,MATCH(1,(GMW!$NE$2:$NE$60=J$3)*(GMW!$ND$2:$ND$60=J$4)*(GMW!$NF$2:$NF$60=J$1),0),$F27-1966)} -> 428.69 | K27: {=INDEX(GMW!$A$2:$NF$60,MATCH(1,(GMW!$NE$2:$NE$60=K$3)*(GMW!$ND$2:$ND$60=K$4)*(GMW!$NF$2:$NF$60=K$1),0),$F27-1966)} -> 286.062 | L27: {=INDEX(GMW!$A$2:$NF$60,MATCH(1,(GMW!$NE$2:$NE$60=L$3)*(GMW!$ND$2:$ND$60=L$4)*(GMW!$NF$2:$NF$60=L$1),0),$F27-1966)} -> 266.513 | M27: {=INDEX(GMW!$A$2:$NF$60,MATCH(1,(GMW!$NE$2:$NE$60=M$3)*(GMW!$ND$2:$ND$60=M$4)*(GMW!$NF$2:$NF$60=M$1),0),$F27-1966)} -> 208478.5 | N27: {=INDEX(GMW!$A$2:$NF$60,MATCH(1,(GMW!$NE$2:$NE$60=N$3)*(GMW!$ND$2:$ND$60=N$4)*(GMW!$NF$2:$NF$60=N$1),0),$F27-1966)} -> -2141 | ... AH27: {=INDEX(GMW!$A$2:$NF$60,MATCH(1,(GMW!$NE$2:$NE$60=AH$3)*(GMW!$ND$2:$ND$60=AH$4)*(GMW!$NF$2:$NF$60=AH$1),0),$F27-1966)} -> 60330
B28: =+B24+1 -> 1978 | C28: =+C24+1 -> 1978 | F28: =+F27+1 -> 1994 | G28: {=INDEX(GMW!$A$2:$NF$60,MATCH(1,(GMW!$NE$2:$NE$60=G$3)*(GMW!$ND$2:$ND$60=G$4)*(GMW!$NF$2:$NF$60=G$1),0),$F28-1966)} -> 259127 | H28: {=INDEX(GMW!$A$2:$NF$60,MATCH(1,(GMW!$NE$2:$NE$60=H$3)*(GMW!$ND$2:$ND$60=H$4)*(GMW!$NF$2:$NF$60=H$1),0),$F28-1966)} -> 1764.725 | I28: {=INDEX(GMW!$A$2:$NF$60,MATCH(1,(GMW!$NE$2:$NE$60=I$3)*(GMW!$ND$2:$ND$60=I$4)*(GMW!$NF$2:$NF$60=I$1),0),$F28-1966)} -> 61280.64 | J28: {=INDEX(GMW!$A$2:$NF$60,MATCH(1,(GMW!$NE$2:$NE$60=J$3)*(GMW!$ND$2:$ND$60=J$4)*(GMW!$NF$2:$NF$60=J$1),0),$F28-1966)} -> 430.44 | K28: {=INDEX(GMW!$A$2:$NF$60,MATCH(1,(GMW!$NE$2:$NE$60=K$3)*(GMW!$ND$2:$ND$60=K$4)*(GMW!$NF$2:$NF$60=K$1),0),$F28-1966)} -> 289.179 | L28: {=INDEX(GMW!$A$2:$NF$60,MATCH(1,(GMW!$NE$2:$NE$60=L$3)*(GMW!$ND$2:$ND$60=L$4)*(GMW!$NF$2:$NF$60=L$1),0),$F28-1966)} -> 271.1233 | M28: {=INDEX(GMW!$A$2:$NF$60,MATCH(1,(GMW!$NE$2:$NE$60=M$3)*(GMW!$ND$2:$ND$60=M$4)*(GMW!$NF$2:$NF$60=M$1),0),$F28-1966)} -> 209897.5 | N28: {=INDEX(GMW!$A$2:$NF$60,MATCH(1,(GMW!$NE$2:$NE$60=N$3)*(GMW!$ND$2:$ND$60=N$4)*(GMW!$NF$2:$NF$60=N$1),0),$F28-1966)} -> -1905 | ... AH28: {=INDEX(GMW!$A$2:$NF$60,MATCH(1,(GMW!$NE$2:$NE$60=AH$3)*(GMW!$ND$2:$ND$60=AH$4)*(GMW!$NF$2:$NF$60=AH$1),0),$F28-1966)} -> 62171
B29: =+B25+1 -> 1978 | C29: =+C25+1 -> 1978 | F29: =+F28+1 -> 1995 | G29: {=INDEX(GMW!$A$2:$NF$60,MATCH(1,(GMW!$NE$2:$NE$60=G$3)*(GMW!$ND$2:$ND$60=G$4)*(GMW!$NF$2:$NF$60=G$1),0),$F29-1966)} -> 262661 | H29: {=INDEX(GMW!$A$2:$NF$60,MATCH(1,(GMW!$NE$2:$NE$60=H$3)*(GMW!$ND$2:$ND$60=H$4)*(GMW!$NF$2:$NF$60=H$1),0),$F29-1966)} -> 1782.475 | I29: {=INDEX(GMW!$A$2:$NF$60,MATCH(1,(GMW!$NE$2:$NE$60=I$3)*(GMW!$ND$2:$ND$60=I$4)*(GMW!$NF$2:$NF$60=I$1),0),$F29-1966)} -> 62081.49 | J29: {=INDEX(GMW!$A$2:$NF$60,MATCH(1,(GMW!$NE$2:$NE$60=J$3)*(GMW!$ND$2:$ND$60=J$4)*(GMW!$NF$2:$NF$60=J$1),0),$F29-1966)} -> 435.98 | K29: {=INDEX(GMW!$A$2:$NF$60,MATCH(1,(GMW!$NE$2:$NE$60=K$3)*(GMW!$ND$2:$ND$60=K$4)*(GMW!$NF$2:$NF$60=K$1),0),$F29-1966)} -> 290.979 | L29: {=INDEX(GMW!$A$2:$NF$60,MATCH(1,(GMW!$NE$2:$NE$60=L$3)*(GMW!$ND$2:$ND$60=L$4)*(GMW!$NF$2:$NF$60=L$1),0),$F29-1966)} -> 272.5487 | M29: {=INDEX(GMW!$A$2:$NF$60,MATCH(1,(GMW!$NE$2:$NE$60=M$3)*(GMW!$ND$2:$ND$60=M$4)*(GMW!$NF$2:$NF$60=M$1),0),$F29-1966)} -> 211855.5 | N29: {=INDEX(GMW!$A$2:$NF$60,MATCH(1,(GMW!$NE$2:$NE$60=N$3)*(GMW!$ND$2:$ND$60=N$4)*(GMW!$NF$2:$NF$60=N$1),0),$F29-1966)} -> -2710 | ... AH29: {=INDEX(GMW!$A$2:$NF$60,MATCH(1,(GMW!$NE$2:$NE$60=AH$3)*(GMW!$ND$2:$ND$60=AH$4)*(GMW!$NF$2:$NF$60=AH$1),0),$F29-1966)} -> 63801
B30: =+B26+1 -> 1978 | C30: =+C26+1 -> 1978 | E30: =+E26+1 -> 1978 | F30: =+F29+1 -> 1996 | G30: {=INDEX(GMW!$A$2:$NF$60,MATCH(1,(GMW!$NE$2:$NE$60=G$3)*(GMW!$ND$2:$ND$60=G$4)*(GMW!$NF$2:$NF$60=G$1),0),$F30-1966)} -> 264972 | H30: {=INDEX(GMW!$A$2:$NF$60,MATCH(1,(GMW!$NE$2:$NE$60=H$3)*(GMW!$ND$2:$ND$60=H$4)*(GMW!$NF$2:$NF$60=H$1),0),$F30-1966)} -> 1806.45 | I30: {=INDEX(GMW!$A$2:$NF$60,MATCH(1,(GMW!$NE$2:$NE$60=I$3)*(GMW!$ND$2:$ND$60=I$4)*(GMW!$NF$2:$NF$60=I$1),0),$F30-1966)} -> 62988.52 | J30: {=INDEX(GMW!$A$2:$NF$60,MATCH(1,(GMW!$NE$2:$NE$60=J$3)*(GMW!$ND$2:$ND$60=J$4)*(GMW!$NF$2:$NF$60=J$1),0),$F30-1966)} -> 441.11 | K30: {=INDEX(GMW!$A$2:$NF$60,MATCH(1,(GMW!$NE$2:$NE$60=K$3)*(GMW!$ND$2:$ND$60=K$4)*(GMW!$NF$2:$NF$60=K$1),0),$F30-1966)} -> 294.294 | L30: {=INDEX(GMW!$A$2:$NF$60,MATCH(1,(GMW!$NE$2:$NE$60=L$3)*(GMW!$ND$2:$ND$60=L$4)*(GMW!$NF$2:$NF$60=L$1),0),$F30-1966)} -> 276.7017 | M30: {=INDEX(GMW!$A$2:$NF$60,MATCH(1,(GMW!$NE$2:$NE$60=M$3)*(GMW!$ND$2:$ND$60=M$4)*(GMW!$NF$2:$NF$60=M$1),0),$F30-1966)} -> 213864.3 | N30: {=INDEX(GMW!$A$2:$NF$60,MATCH(1,(GMW!$NE$2:$NE$60=N$3)*(GMW!$ND$2:$ND$60=N$4)*(GMW!$NF$2:$NF$60=N$1),0),$F30-1966)} -> -1578 | ... AH30: {=INDEX(GMW!$A$2:$NF$60,MATCH(1,(GMW!$NE$2:$NE$60=AH$3)*(GMW!$ND$2:$ND$60=AH$4)*(GMW!$NF$2:$NF$60=AH$1),0),$F30-1966)} -> 65773
A31: 1979 | B31: =+B27+1 -> 1979 | C31: =+C27+1 -> 1978 | D31: =+D27+1 -> 1978 | F31: =+F30+1 -> 1997 | G31: {=INDEX(GMW!$A$2:$NF$60,MATCH(1,(GMW!$NE$2:$NE$60=G$3)*(GMW!$ND$2:$ND$60=G$4)*(GMW!$NF$2:$NF$60=G$1),0),$F31-1966)} -> 264185 | H31: {=INDEX(GMW!$A$2:$NF$60,MATCH(1,(GMW!$NE$2:$NE$60=H$3)*(GMW!$ND$2:$ND$60=H$4)*(GMW!$NF$2:$NF$60=H$1),0),$F31-1966)} -> 1809.675 | I31: {=INDEX(GMW!$A$2:$NF$60,MATCH(1,(GMW!$NE$2:$NE$60=I$3)*(GMW!$ND$2:$ND$60=I$4)*(GMW!$NF$2:$NF$60=I$1),0),$F31-1966)} -> 64175.77 | J31: {=INDEX(GMW!$A$2:$NF$60,MATCH(1,(GMW!$NE$2:$NE$60=J$3)*(GMW!$ND$2:$ND$60=J$4)*(GMW!$NF$2:$NF$60=J$1),0),$F31-1966)} -> 441.69 | K31: {=INDEX(GMW!$A$2:$NF$60,MATCH(1,(GMW!$NE$2:$NE$60=K$3)*(GMW!$ND$2:$ND$60=K$4)*(GMW!$NF$2:$NF$60=K$1),0),$F31-1966)} -> 297.552 | L31: {=INDEX(GMW!$A$2:$NF$60,MATCH(1,(GMW!$NE$2:$NE$60=L$3)*(GMW!$ND$2:$ND$60=L$4)*(GMW!$NF$2:$NF$60=L$1),0),$F31-1966)} -> 281.0739 | M31: {=INDEX(GMW!$A$2:$NF$60,MATCH(1,(GMW!$NE$2:$NE$60=M$3)*(GMW!$ND$2:$ND$60=M$4)*(GMW!$NF$2:$NF$60=M$1),0),$F31-1966)} -> 215570.5 | N31: {=INDEX(GMW!$A$2:$NF$60,MATCH(1,(GMW!$NE$2:$NE$60=N$3)*(GMW!$ND$2:$ND$60=N$4)*(GMW!$NF$2:$NF$60=N$1),0),$F31-1966)} -> -2492 | ... AH31: {=INDEX(GMW!$A$2:$NF$60,MATCH(1,(GMW!$NE$2:$NE$60=AH$3)*(GMW!$ND$2:$ND$60=AH$4)*(GMW!$NF$2:$NF$60=AH$1),0),$F31-1966)} -> 67850
B32: =+B28+1 -> 1979 | C32: =+C28+1 -> 1979 | F32: =+F31+1 -> 1998 | G32: {=INDEX(GMW!$A$2:$NF$60,MATCH(1,(GMW!$NE$2:$NE$60=G$3)*(GMW!$ND$2:$ND$60=G$4)*(GMW!$NF$2:$NF$60=G$1),0),$F32-1966)} -> 275695 | H32: {=INDEX(GMW!$A$2:$NF$60,MATCH(1,(GMW!$NE$2:$NE$60=H$3)*(GMW!$ND$2:$ND$60=H$4)*(GMW!$NF$2:$NF$60=H$1),0),$F32-1966)} -> 1811.625 | I32: {=INDEX(GMW!$A$2:$NF$60,MATCH(1,(GMW!$NE$2:$NE$60=I$3)*(GMW!$ND$2:$ND$60=I$4)*(GMW!$NF$2:$NF$60=I$1),0),$F32-1966)} -> 65372.08 | J32: {=INDEX(GMW!$A$2:$NF$60,MATCH(1,(GMW!$NE$2:$NE$60=J$3)*(GMW!$ND$2:$ND$60=J$4)*(GMW!$NF$2:$NF$60=J$1),0),$F32-1966)} -> 455.35 | K32: {=INDEX(GMW!$A$2:$NF$60,MATCH(1,(GMW!$NE$2:$NE$60=K$3)*(GMW!$ND$2:$ND$60=K$4)*(GMW!$NF$2:$NF$60=K$1),0),$F32-1966)} -> 299.071 | L32: {=INDEX(GMW!$A$2:$NF$60,MATCH(1,(GMW!$NE$2:$NE$60=L$3)*(GMW!$ND$2:$ND$60=L$4)*(GMW!$NF$2:$NF$60=L$1),0),$F32-1966)} -> 283.1178 | M32: {=INDEX(GMW!$A$2:$NF$60,MATCH(1,(GMW!$NE$2:$NE$60=M$3)*(GMW!$ND$2:$ND$60=M$4)*(GMW!$NF$2:$NF$60=M$1),0),$F32-1966)} -> 218430.3 | N32: {=INDEX(GMW!$A$2:$NF$60,MATCH(1,(GMW!$NE$2:$NE$60=N$3)*(GMW!$ND$2:$ND$60=N$4)*(GMW!$NF$2:$NF$60=N$1),0),$F32-1966)} -> -2137 | ... AH32: {=INDEX(GMW!$A$2:$NF$60,MATCH(1,(GMW!$NE$2:$NE$60=AH$3)*(GMW!$ND$2:$ND$60=AH$4)*(GMW!$NF$2:$NF$60=AH$1),0),$F32-1966)} -> 71043
B33: =+B29+1 -> 1979 | C33: =+C29+1 -> 1979 | F33: =+F32+1 -> 1999 | G33: {=INDEX(GMW!$A$2:$NF$60,MATCH(1,(GMW!$NE$2:$NE$60=G$3)*(GMW!$ND$2:$ND$60=G$4)*(GMW!$NF$2:$NF$60=G$1),0),$F33-1966)} -> 269599 | H33: {=INDEX(GMW!$A$2:$NF$60,MATCH(1,(GMW!$NE$2:$NE$60=H$3)*(GMW!$ND$2:$ND$60=H$4)*(GMW!$NF$2:$NF$60=H$1),0),$F33-1966)} -> 1825.075 | I33: {=INDEX(GMW!$A$2:$NF$60,MATCH(1,(GMW!$NE$2:$NE$60=I$3)*(GMW!$ND$2:$ND$60=I$4)*(GMW!$NF$2:$NF$60=I$1),0),$F33-1966)} -> 65872.72 | J33: {=INDEX(GMW!$A$2:$NF$60,MATCH(1,(GMW!$NE$2:$NE$60=J$3)*(GMW!$ND$2:$ND$60=J$4)*(GMW!$NF$2:$NF$60=J$1),0),$F33-1966)} -> 455.43 | K33: {=INDEX(GMW!$A$2:$NF$60,MATCH(1,(GMW!$NE$2:$NE$60=K$3)*(GMW!$ND$2:$ND$60=K$4)*(GMW!$NF$2:$NF$60=K$1),0),$F33-1966)} -> 302.92 | L33: {=INDEX(GMW!$A$2:$NF$60,MATCH(1,(GMW!$NE$2:$NE$60=L$3)*(GMW!$ND$2:$ND$60=L$4)*(GMW!$NF$2:$NF$60=L$1),0),$F33-1966)} -> 288.0178 | M33: {=INDEX(GMW!$A$2:$NF$60,MATCH(1,(GMW!$NE$2:$NE$60=M$3)*(GMW!$ND$2:$ND$60=M$4)*(GMW!$NF$2:$NF$60=M$1),0),$F33-1966)} -> 220031.5 | N33: {=INDEX(GMW!$A$2:$NF$60,MATCH(1,(GMW!$NE$2:$NE$60=N$3)*(GMW!$ND$2:$ND$60=N$4)*(GMW!$NF$2:$NF$60=N$1),0),$F33-1966)} -> -2934 | ... AH33: {=INDEX(GMW!$A$2:$NF$60,MATCH(1,(GMW!$NE$2:$NE$60=AH$3)*(GMW!$ND$2:$ND$60=AH$4)*(GMW!$NF$2:$NF$60=AH$1),0),$F33-1966)} -> 73230
B34: =+B30+1 -> 1979 | C34: =+C30+1 -> 1979 | E34: =+E30+1 -> 1979 | F34: =+F33+1 -> 2000 | G34: {=INDEX(GMW!$A$2:$NF$60,MATCH(1,(GMW!$NE$2:$NE$60=G$3)*(GMW!$ND$2:$ND$60=G$4)*(GMW!$NF$2:$NF$60=G$1),0),$F34-1966)} -> 272359 | H34: {=INDEX(GMW!$A$2:$NF$60,MATCH(1,(GMW!$NE$2:$NE$60=H$3)*(GMW!$ND$2:$ND$60=H$4)*(GMW!$NF$2:$NF$60=H$1),0),$F34-1966)} -> 1829.625 | I34: {=INDEX(GMW!$A$2:$NF$60,MATCH(1,(GMW!$NE$2:$NE$60=I$3)*(GMW!$ND$2:$ND$60=I$4)*(GMW!$NF$2:$NF$60=I$1),0),$F34-1966)} -> 66157.2 | J34: {=INDEX(GMW!$A$2:$NF$60,MATCH(1,(GMW!$NE$2:$NE$60=J$3)*(GMW!$ND$2:$ND$60=J$4)*(GMW!$NF$2:$NF$60=J$1),0),$F34-1966)} -> 458.15 | K34: {=INDEX(GMW!$A$2:$NF$60,MATCH(1,(GMW!$NE$2:$NE$60=K$3)*(GMW!$ND$2:$ND$60=K$4)*(GMW!$NF$2:$NF$60=K$1),0),$F34-1966)} -> 303.971 | L34: {=INDEX(GMW!$A$2:$NF$60,MATCH(1,(GMW!$NE$2:$NE$60=L$3)*(GMW!$ND$2:$ND$60=L$4)*(GMW!$NF$2:$NF$60=L$1),0),$F34-1966)} -> 294.7971 | M34: {=INDEX(GMW!$A$2:$NF$60,MATCH(1,(GMW!$NE$2:$NE$60=M$3)*(GMW!$ND$2:$ND$60=M$4)*(GMW!$NF$2:$NF$60=M$1),0),$F34-1966)} -> 221507.8 | N34: {=INDEX(GMW!$A$2:$NF$60,MATCH(1,(GMW!$NE$2:$NE$60=N$3)*(GMW!$ND$2:$ND$60=N$4)*(GMW!$NF$2:$NF$60=N$1),0),$F34-1966)} -> -1801 | ... AH34: {=INDEX(GMW!$A$2:$NF$60,MATCH(1,(GMW!$NE$2:$NE$60=AH$3)*(GMW!$ND$2:$ND$60=AH$4)*(GMW!$NF$2:$NF$60=AH$1),0),$F34-1966)} -> 75485
A35: 1980 | B35: =+B31+1 -> 1980 | C35: =+C31+1 -> 1979 | D35: =+D31+1 -> 1979 | F35: =+F34+1 -> 2001 | G35: {=INDEX(GMW!$A$2:$NF$60,MATCH(1,(GMW!$NE$2:$NE$60=G$3)*(GMW!$ND$2:$ND$60=G$4)*(GMW!$NF$2:$NF$60=G$1),0),$F35-1966)} -> 269776 | H35: {=INDEX(GMW!$A$2:$NF$60,MATCH(1,(GMW!$NE$2:$NE$60=H$3)*(GMW!$ND$2:$ND$60=H$4)*(GMW!$NF$2:$NF$60=H$1),0),$F35-1966)} -> 1835.4 | I35: {=INDEX(GMW!$A$2:$NF$60,MATCH(1,(GMW!$NE$2:$NE$60=I$3)*(GMW!$ND$2:$ND$60=I$4)*(GMW!$NF$2:$NF$60=I$1),0),$F35-1966)} -> 67431.65 | J35: {=INDEX(GMW!$A$2:$NF$60,MATCH(1,(GMW!$NE$2:$NE$60=J$3)*(GMW!$ND$2:$ND$60=J$4)*(GMW!$NF$2:$NF$60=J$1),0),$F35-1966)} -> 461.8 | K35: {=INDEX(GMW!$A$2:$NF$60,MATCH(1,(GMW!$NE$2:$NE$60=K$3)*(GMW!$ND$2:$ND$60=K$4)*(GMW!$NF$2:$NF$60=K$1),0),$F35-1966)} -> 307.574 | L35: {=INDEX(GMW!$A$2:$NF$60,MATCH(1,(GMW!$NE$2:$NE$60=L$3)*(GMW!$ND$2:$ND$60=L$4)*(GMW!$NF$2:$NF$60=L$1),0),$F35-1966)} -> 294.2694 | M35: {=INDEX(GMW!$A$2:$NF$60,MATCH(1,(GMW!$NE$2:$NE$60=M$3)*(GMW!$ND$2:$ND$60=M$4)*(GMW!$NF$2:$NF$60=M$1),0),$F35-1966)} -> 223045.8 | N35: {=INDEX(GMW!$A$2:$NF$60,MATCH(1,(GMW!$NE$2:$NE$60=N$3)*(GMW!$ND$2:$ND$60=N$4)*(GMW!$NF$2:$NF$60=N$1),0),$F35-1966)} -> -1674 | ... AH35: {=INDEX(GMW!$A$2:$NF$60,MATCH(1,(GMW!$NE$2:$NE$60=AH$3)*(GMW!$ND$2:$ND$60=AH$4)*(GMW!$NF$2:$NF$60=AH$1),0),$F35-1966)} -> 77446
B36: =+B32+1 -> 1980 | C36: =+C32+1 -> 1980 | F36: =+F35+1 -> 2002 | G36: {=INDEX(GMW!$A$2:$NF$60,MATCH(1,(GMW!$NE$2:$NE$60=G$3)*(GMW!$ND$2:$ND$60=G$4)*(GMW!$NF$2:$NF$60=G$1),0),$F36-1966)} -> 264448 | H36: {=INDEX(GMW!$A$2:$NF$60,MATCH(1,(GMW!$NE$2:$NE$60=H$3)*(GMW!$ND$2:$ND$60=H$4)*(GMW!$NF$2:$NF$60=H$1),0),$F36-1966)} -> 1797.575 | I36: {=INDEX(GMW!$A$2:$NF$60,MATCH(1,(GMW!$NE$2:$NE$60=I$3)*(GMW!$ND$2:$ND$60=I$4)*(GMW!$NF$2:$NF$60=I$1),0),$F36-1966)} -> 67125.25 | J36: {=INDEX(GMW!$A$2:$NF$60,MATCH(1,(GMW!$NE$2:$NE$60=J$3)*(GMW!$ND$2:$ND$60=J$4)*(GMW!$NF$2:$NF$60=J$1),0),$F36-1966)} -> 458.81 | K36: {=INDEX(GMW!$A$2:$NF$60,MATCH(1,(GMW!$NE$2:$NE$60=K$3)*(GMW!$ND$2:$ND$60=K$4)*(GMW!$NF$2:$NF$60=K$1),0),$F36-1966)} -> 305.096 | L36: {=INDEX(GMW!$A$2:$NF$60,MATCH(1,(GMW!$NE$2:$NE$60=L$3)*(GMW!$ND$2:$ND$60=L$4)*(GMW!$NF$2:$NF$60=L$1),0),$F36-1966)} -> 296.5532 | M36: {=INDEX(GMW!$A$2:$NF$60,MATCH(1,(GMW!$NE$2:$NE$60=M$3)*(GMW!$ND$2:$ND$60=M$4)*(GMW!$NF$2:$NF$60=M$1),0),$F36-1966)} -> 222948.3 | N36: {=INDEX(GMW!$A$2:$NF$60,MATCH(1,(GMW!$NE$2:$NE$60=N$3)*(GMW!$ND$2:$ND$60=N$4)*(GMW!$NF$2:$NF$60=N$1),0),$F36-1966)} -> -3351 | ... AH36: {=INDEX(GMW!$A$2:$NF$60,MATCH(1,(GMW!$NE$2:$NE$60=AH$3)*(GMW!$ND$2:$ND$60=AH$4)*(GMW!$NF$2:$NF$60=AH$1),0),$F36-1966)} -> 79307
B37: =+B33+1 -> 1980 | C37: =+C33+1 -> 1980 | F37: =+F36+1 -> 2003 | G37: {=INDEX(GMW!$A$2:$NF$60,MATCH(1,(GMW!$NE$2:$NE$60=G$3)*(GMW!$ND$2:$ND$60=G$4)*(GMW!$NF$2:$NF$60=G$1),0),$F37-1966)} -> 264139 | H37: {=INDEX(GMW!$A$2:$NF$60,MATCH(1,(GMW!$NE$2:$NE$60=H$3)*(GMW!$ND$2:$ND$60=H$4)*(GMW!$NF$2:$NF$60=H$1),0),$F37-1966)} -> 1795.425 | I37: {=INDEX(GMW!$A$2:$NF$60,MATCH(1,(GMW!$NE$2:$NE$60=I$3)*(GMW!$ND$2:$ND$60=I$4)*(GMW!$NF$2:$NF$60=I$1),0),$F37-1966)} -> 68540.48 | J37: {=INDEX(GMW!$A$2:$NF$60,MATCH(1,(GMW!$NE$2:$NE$60=J$3)*(GMW!$ND$2:$ND$60=J$4)*(GMW!$NF$2:$NF$60=J$1),0),$F37-1966)} -> 457 | K37: {=INDEX(GMW!$A$2:$NF$60,MATCH(1,(GMW!$NE$2:$NE$60=K$3)*(GMW!$ND$2:$ND$60=K$4)*(GMW!$NF$2:$NF$60=K$1),0),$F37-1966)} -> 305.557 | L37: {=INDEX(GMW!$A$2:$NF$60,MATCH(1,(GMW!$NE$2:$NE$60=L$3)*(GMW!$ND$2:$ND$60=L$4)*(GMW!$NF$2:$NF$60=L$1),0),$F37-1966)} -> 296.8017 | M37: {=INDEX(GMW!$A$2:$NF$60,MATCH(1,(GMW!$NE$2:$NE$60=M$3)*(GMW!$ND$2:$ND$60=M$4)*(GMW!$NF$2:$NF$60=M$1),0),$F37-1966)} -> 222763 | N37: {=INDEX(GMW!$A$2:$NF$60,MATCH(1,(GMW!$NE$2:$NE$60=N$3)*(GMW!$ND$2:$ND$60=N$4)*(GMW!$NF$2:$NF$60=N$1),0),$F37-1966)} -> -3213 | ... AH37: {=INDEX(GMW!$A$2:$NF$60,MATCH(1,(GMW!$NE$2:$NE$60=AH$3)*(GMW!$ND$2:$ND$60=AH$4)*(GMW!$NF$2:$NF$60=AH$1),0),$F37-1966)} -> 81191
B38: =+B34+1 -> 1980 | C38: =+C34+1 -> 1980 | E38: =+E34+1 -> 1980 | F38: =+F37+1 -> 2004 | G38: {=INDEX(GMW!$A$2:$NF$60,MATCH(1,(GMW!$NE$2:$NE$60=G$3)*(GMW!$ND$2:$ND$60=G$4)*(GMW!$NF$2:$NF$60=G$1),0),$F38-1966)} -> 261297 | H38: {=INDEX(GMW!$A$2:$NF$60,MATCH(1,(GMW!$NE$2:$NE$60=H$3)*(GMW!$ND$2:$ND$60=H$4)*(GMW!$NF$2:$NF$60=H$1),0),$F38-1966)} -> 1828.925 | I38: {=INDEX(GMW!$A$2:$NF$60,MATCH(1,(GMW!$NE$2:$NE$60=I$3)*(GMW!$ND$2:$ND$60=I$4)*(GMW!$NF$2:$NF$60=I$1),0),$F38-1966)} -> 69895.05 | J38: {=INDEX(GMW!$A$2:$NF$60,MATCH(1,(GMW!$NE$2:$NE$60=J$3)*(GMW!$ND$2:$ND$60=J$4)*(GMW!$NF$2:$NF$60=J$1),0),$F38-1966)} -> 456.34 | K38: {=INDEX(GMW!$A$2:$NF$60,MATCH(1,(GMW!$NE$2:$NE$60=K$3)*(GMW!$ND$2:$ND$60=K$4)*(GMW!$NF$2:$NF$60=K$1),0),$F38-1966)} -> 305.08 | L38: {=INDEX(GMW!$A$2:$NF$60,MATCH(1,(GMW!$NE$2:$NE$60=L$3)*(GMW!$ND$2:$ND$60=L$4)*(GMW!$NF$2:$NF$60=L$1),0),$F38-1966)} -> 299.3304 | M38: {=INDEX(GMW!$A$2:$NF$60,MATCH(1,(GMW!$NE$2:$NE$60=M$3)*(GMW!$ND$2:$ND$60=M$4)*(GMW!$NF$2:$NF$60=M$1),0),$F38-1966)} -> 225845.3 | N38: {=INDEX(GMW!$A$2:$NF$60,MATCH(1,(GMW!$NE$2:$NE$60=N$3)*(GMW!$ND$2:$ND$60=N$4)*(GMW!$NF$2:$NF$60=N$1),0),$F38-1966)} -> -1803 | ... AH38: {=INDEX(GMW!$A$2:$NF$60,MATCH(1,(GMW!$NE$2:$NE$60=AH$3)*(GMW!$ND$2:$ND$60=AH$4)*(GMW!$NF$2:$NF$60=AH$1),0),$F38-1966)} -> 84838
A39: 1981 | B39: =+B35+1 -> 1981 | C39: =+C35+1 -> 1980 | D39: =+D35+1 -> 1980 | F39: =+F38+1 -> 2005 | G39: {=INDEX(GMW!$A$2:$NF$60,MATCH(1,(GMW!$NE$2:$NE$60=G$3)*(GMW!$ND$2:$ND$60=G$4)*(GMW!$NF$2:$NF$60=G$1),0),$F39-1966)} -> 261131 | H39: {=INDEX(GMW!$A$2:$NF$60,MATCH(1,(GMW!$NE$2:$NE$60=H$3)*(GMW!$ND$2:$ND$60=H$4)*(GMW!$NF$2:$NF$60=H$1),0),$F39-1966)} -> 1864.75 | I39: {=INDEX(GMW!$A$2:$NF$60,MATCH(1,(GMW!$NE$2:$NE$60=I$3)*(GMW!$ND$2:$ND$60=I$4)*(GMW!$NF$2:$NF$60=I$1),0),$F39-1966)} -> 70493.48 | J39: {=INDEX(GMW!$A$2:$NF$60,MATCH(1,(GMW!$NE$2:$NE$60=J$3)*(GMW!$ND$2:$ND$60=J$4)*(GMW!$NF$2:$NF$60=J$1),0),$F39-1966)} -> 461.88 | K39: {=INDEX(GMW!$A$2:$NF$60,MATCH(1,(GMW!$NE$2:$NE$60=K$3)*(GMW!$ND$2:$ND$60=K$4)*(GMW!$NF$2:$NF$60=K$1),0),$F39-1966)} -> 306.214 | L39: {=INDEX(GMW!$A$2:$NF$60,MATCH(1,(GMW!$NE$2:$NE$60=L$3)*(GMW!$ND$2:$ND$60=L$4)*(GMW!$NF$2:$NF$60=L$1),0),$F39-1966)} -> 298.359 | M39: {=INDEX(GMW!$A$2:$NF$60,MATCH(1,(GMW!$NE$2:$NE$60=M$3)*(GMW!$ND$2:$ND$60=M$4)*(GMW!$NF$2:$NF$60=M$1),0),$F39-1966)} -> 230710.8 | N39: {=INDEX(GMW!$A$2:$NF$60,MATCH(1,(GMW!$NE$2:$NE$60=N$3)*(GMW!$ND$2:$ND$60=N$4)*(GMW!$NF$2:$NF$60=N$1),0),$F39-1966)} -> -3170 | ... AH39: {=INDEX(GMW!$A$2:$NF$60,MATCH(1,(GMW!$NE$2:$NE$60=AH$3)*(GMW!$ND$2:$ND$60=AH$4)*(GMW!$NF$2:$NF$60=AH$1),0),$F39-1966)} -> 88998
B40: =+B36+1 -> 1981 | C40: =+C36+1 -> 1981 | F40: =+F39+1 -> 2006 | G40: {=INDEX(GMW!$A$2:$NF$60,MATCH(1,(GMW!$NE$2:$NE$60=G$3)*(GMW!$ND$2:$ND$60=G$4)*(GMW!$NF$2:$NF$60=G$1),0),$F40-1966)} -> 261739 | H40: {=INDEX(GMW!$A$2:$NF$60,MATCH(1,(GMW!$NE$2:$NE$60=H$3)*(GMW!$ND$2:$ND$60=H$4)*(GMW!$NF$2:$NF$60=H$1),0),$F40-1966)} -> 1850.925 | I40: {=INDEX(GMW!$A$2:$NF$60,MATCH(1,(GMW!$NE$2:$NE$60=I$3)*(GMW!$ND$2:$ND$60=I$4)*(GMW!$NF$2:$NF$60=I$1),0),$F40-1966)} -> 71146.73 | J40: {=INDEX(GMW!$A$2:$NF$60,MATCH(1,(GMW!$NE$2:$NE$60=J$3)*(GMW!$ND$2:$ND$60=J$4)*(GMW!$NF$2:$NF$60=J$1),0),$F40-1966)} -> 460.64 | K40: {=INDEX(GMW!$A$2:$NF$60,MATCH(1,(GMW!$NE$2:$NE$60=K$3)*(GMW!$ND$2:$ND$60=K$4)*(GMW!$NF$2:$NF$60=K$1),0),$F40-1966)} -> 308.53 | L40: {=INDEX(GMW!$A$2:$NF$60,MATCH(1,(GMW!$NE$2:$NE$60=L$3)*(GMW!$ND$2:$ND$60=L$4)*(GMW!$NF$2:$NF$60=L$1),0),$F40-1966)} -> 298.941 | M40: {=INDEX(GMW!$A$2:$NF$60,MATCH(1,(GMW!$NE$2:$NE$60=M$3)*(GMW!$ND$2:$ND$60=M$4)*(GMW!$NF$2:$NF$60=M$1),0),$F40-1966)} -> 233233.3 | N40: {=INDEX(GMW!$A$2:$NF$60,MATCH(1,(GMW!$NE$2:$NE$60=N$3)*(GMW!$ND$2:$ND$60=N$4)*(GMW!$NF$2:$NF$60=N$1),0),$F40-1966)} -> -3679 | ... AH40: {=INDEX(GMW!$A$2:$NF$60,MATCH(1,(GMW!$NE$2:$NE$60=AH$3)*(GMW!$ND$2:$ND$60=AH$4)*(GMW!$NF$2:$NF$60=AH$1),0),$F40-1966)} -> 91998
B41: =+B37+1 -> 1981 | C41: =+C37+1 -> 1981 | F41: =+F40+1 -> 2007 | G41: {=INDEX(GMW!$A$2:$NF$60,MATCH(1,(GMW!$NE$2:$NE$60=G$3)*(GMW!$ND$2:$ND$60=G$4)*(GMW!$NF$2:$NF$60=G$1),0),$F41-1966)} -> 264602 | H41: {=INDEX(GMW!$A$2:$NF$60,MATCH(1,(GMW!$NE$2:$NE$60=H$3)*(GMW!$ND$2:$ND$60=H$4)*(GMW!$NF$2:$NF$60=H$1),0),$F41-1966)} -> 1873.1 | I41: {=INDEX(GMW!$A$2:$NF$60,MATCH(1,(GMW!$NE$2:$NE$60=I$3)*(GMW!$ND$2:$ND$60=I$4)*(GMW!$NF$2:$NF$60=I$1),0),$F41-1966)} -> 71480.1 | J41: {=INDEX(GMW!$A$2:$NF$60,MATCH(1,(GMW!$NE$2:$NE$60=J$3)*(GMW!$ND$2:$ND$60=J$4)*(GMW!$NF$2:$NF$60=J$1),0),$F41-1966)} -> 461.88 | K41: {=INDEX(GMW!$A$2:$NF$60,MATCH(1,(GMW!$NE$2:$NE$60=K$3)*(GMW!$ND$2:$ND$60=K$4)*(GMW!$NF$2:$NF$60=K$1),0),$F41-1966)} -> 310.602 | L41: {=INDEX(GMW!$A$2:$NF$60,MATCH(1,(GMW!$NE$2:$NE$60=L$3)*(GMW!$ND$2:$ND$60=L$4)*(GMW!$NF$2:$NF$60=L$1),0),$F41-1966)} -> 299.08 | M41: {=INDEX(GMW!$A$2:$NF$60,MATCH(1,(GMW!$NE$2:$NE$60=M$3)*(GMW!$ND$2:$ND$60=M$4)*(GMW!$NF$2:$NF$60=M$1),0),$F41-1966)} -> 231136.3 | N41: {=INDEX(GMW!$A$2:$NF$60,MATCH(1,(GMW!$NE$2:$NE$60=N$3)*(GMW!$ND$2:$ND$60=N$4)*(GMW!$NF$2:$NF$60=N$1),0),$F41-1966)} -> -2967 | ... AH41: {=INDEX(GMW!$A$2:$NF$60,MATCH(1,(GMW!$NE$2:$NE$60=AH$3)*(GMW!$ND$2:$ND$60=AH$4)*(GMW!$NF$2:$NF$60=AH$1),0),$F41-1966)} -> 93205
B42: =+B38+1 -> 1981 | C42: =+C38+1 -> 1981 | E42: =+E38+1 -> 1981 | F42: =+F41+1 -> 2008 | G42: {=INDEX(GMW!$A$2:$NF$60,MATCH(1,(GMW!$NE$2:$NE$60=G$3)*(GMW!$ND$2:$ND$60=G$4)*(GMW!$NF$2:$NF$60=G$1),0),$F42-1966)} -> 264902 | H42: {=INDEX(GMW!$A$2:$NF$60,MATCH(1,(GMW!$NE$2:$NE$60=H$3)*(GMW!$ND$2:$ND$60=H$4)*(GMW!$NF$2:$NF$60=H$1),0),$F42-1966)} -> 1852.7 | I42: {=INDEX(GMW!$A$2:$NF$60,MATCH(1,(GMW!$NE$2:$NE$60=I$3)*(GMW!$ND$2:$ND$60=I$4)*(GMW!$NF$2:$NF$60=I$1),0),$F42-1966)} -> 71827.58 | J42: {=INDEX(GMW!$A$2:$NF$60,MATCH(1,(GMW!$NE$2:$NE$60=J$3)*(GMW!$ND$2:$ND$60=J$4)*(GMW!$NF$2:$NF$60=J$1),0),$F42-1966)} -> 461.46 | K42: {=INDEX(GMW!$A$2:$NF$60,MATCH(1,(GMW!$NE$2:$NE$60=K$3)*(GMW!$ND$2:$ND$60=K$4)*(GMW!$NF$2:$NF$60=K$1),0),$F42-1966)} -> 312.474 | L42: {=INDEX(GMW!$A$2:$NF$60,MATCH(1,(GMW!$NE$2:$NE$60=L$3)*(GMW!$ND$2:$ND$60=L$4)*(GMW!$NF$2:$NF$60=L$1),0),$F42-1966)} -> 301.507 | M42: {=INDEX(GMW!$A$2:$NF$60,MATCH(1,(GMW!$NE$2:$NE$60=M$3)*(GMW!$ND$2:$ND$60=M$4)*(GMW!$NF$2:$NF$60=M$1),0),$F42-1966)} -> 230073.3 | N42: {=INDEX(GMW!$A$2:$NF$60,MATCH(1,(GMW!$NE$2:$NE$60=N$3)*(GMW!$ND$2:$ND$60=N$4)*(GMW!$NF$2:$NF$60=N$1),0),$F42-1966)} -> 991 | ... AH42: {=INDEX(GMW!$A$2:$NF$60,MATCH(1,(GMW!$NE$2:$NE$60=AH$3)*(GMW!$ND$2:$ND$60=AH$4)*(GMW!$NF$2:$NF$60=AH$1),0),$F42-1966)} -> 94157
A43: 1982 | B43: =+B39+1 -> 1982 | C43: =+C39+1 -> 1981 | D43: =+D39+1 -> 1981 | F43: =+F42+1 -> 2009 | G43: {=INDEX(GMW!$A$2:$NF$60,MATCH(1,(GMW!$NE$2:$NE$60=G$3)*(GMW!$ND$2:$ND$60=G$4)*(GMW!$NF$2:$NF$60=G$1),0),$F43-1966)} -> 265408 | H43: {=INDEX(GMW!$A$2:$NF$60,MATCH(1,(GMW!$NE$2:$NE$60=H$3)*(GMW!$ND$2:$ND$60=H$4)*(GMW!$NF$2:$NF$60=H$1),0),$F43-1966)} -> 1823.9 | I43: {=INDEX(GMW!$A$2:$NF$60,MATCH(1,(GMW!$NE$2:$NE$60=I$3)*(GMW!$ND$2:$ND$60=I$4)*(GMW!$NF$2:$NF$60=I$1),0),$F43-1966)} -> 72823.85 | J43: {=INDEX(GMW!$A$2:$NF$60,MATCH(1,(GMW!$NE$2:$NE$60=J$3)*(GMW!$ND$2:$ND$60=J$4)*(GMW!$NF$2:$NF$60=J$1),0),$F43-1966)} -> 463.29 | K43: {=INDEX(GMW!$A$2:$NF$60,MATCH(1,(GMW!$NE$2:$NE$60=K$3)*(GMW!$ND$2:$ND$60=K$4)*(GMW!$NF$2:$NF$60=K$1),0),$F43-1966)} -> 314.838 | L43: {=INDEX(GMW!$A$2:$NF$60,MATCH(1,(GMW!$NE$2:$NE$60=L$3)*(GMW!$ND$2:$ND$60=L$4)*(GMW!$NF$2:$NF$60=L$1),0),$F43-1966)} -> 301.387 | M43: {=INDEX(GMW!$A$2:$NF$60,MATCH(1,(GMW!$NE$2:$NE$60=M$3)*(GMW!$ND$2:$ND$60=M$4)*(GMW!$NF$2:$NF$60=M$1),0),$F43-1966)} -> 227440.3 | N43: {=INDEX(GMW!$A$2:$NF$60,MATCH(1,(GMW!$NE$2:$NE$60=N$3)*(GMW!$ND$2:$ND$60=N$4)*(GMW!$NF$2:$NF$60=N$1),0),$F43-1966)} -> -344 | ... AH43: {=INDEX(GMW!$A$2:$NF$60,MATCH(1,(GMW!$NE$2:$NE$60=AH$3)*(GMW!$ND$2:$ND$60=AH$4)*(GMW!$NF$2:$NF$60=AH$1),0),$F43-1966)} -> 95751
B44: =+B40+1 -> 1982 | C44: =+C40+1 -> 1982 | F44: =+F43+1 -> 2010 | G44: {=INDEX(GMW!$A$2:$NF$60,MATCH(1,(GMW!$NE$2:$NE$60=G$3)*(GMW!$ND$2:$ND$60=G$4)*(GMW!$NF$2:$NF$60=G$1),0),$F44-1966)} -> 268196 | H44: {=INDEX(GMW!$A$2:$NF$60,MATCH(1,(GMW!$NE$2:$NE$60=H$3)*(GMW!$ND$2:$ND$60=H$4)*(GMW!$NF$2:$NF$60=H$1),0),$F44-1966)} -> 1832.225 | I44: {=INDEX(GMW!$A$2:$NF$60,MATCH(1,(GMW!$NE$2:$NE$60=I$3)*(GMW!$ND$2:$ND$60=I$4)*(GMW!$NF$2:$NF$60=I$1),0),$F44-1966)} -> 73296.85 | J44: {=INDEX(GMW!$A$2:$NF$60,MATCH(1,(GMW!$NE$2:$NE$60=J$3)*(GMW!$ND$2:$ND$60=J$4)*(GMW!$NF$2:$NF$60=J$1),0),$F44-1966)} -> 460.39 | K44: {=INDEX(GMW!$A$2:$NF$60,MATCH(1,(GMW!$NE$2:$NE$60=K$3)*(GMW!$ND$2:$ND$60=K$4)*(GMW!$NF$2:$NF$60=K$1),0),$F44-1966)} -> 317.069 | L44: {=INDEX(GMW!$A$2:$NF$60,MATCH(1,(GMW!$NE$2:$NE$60=L$3)*(GMW!$ND$2:$ND$60=L$4)*(GMW!$NF$2:$NF$60=L$1),0),$F44-1966)} -> 300.531 | M44: {=INDEX(GMW!$A$2:$NF$60,MATCH(1,(GMW!$NE$2:$NE$60=M$3)*(GMW!$ND$2:$ND$60=M$4)*(GMW!$NF$2:$NF$60=M$1),0),$F44-1966)} -> 224821.8 | N44: {=INDEX(GMW!$A$2:$NF$60,MATCH(1,(GMW!$NE$2:$NE$60=N$3)*(GMW!$ND$2:$ND$60=N$4)*(GMW!$NF$2:$NF$60=N$1),0),$F44-1966)} -> -2938 | ... AH44: {=INDEX(GMW!$A$2:$NF$60,MATCH(1,(GMW!$NE$2:$NE$60=AH$3)*(GMW!$ND$2:$ND$60=AH$4)*(GMW!$NF$2:$NF$60=AH$1),0),$F44-1966)} -> 96629
B45: =+B41+1 -> 1982 | C45: =+C41+1 -> 1982 | F45: =+F44+1 -> 2011 | G45: {=INDEX(GMW!$A$2:$NF$60,MATCH(1,(GMW!$NE$2:$NE$60=G$3)*(GMW!$ND$2:$ND$60=G$4)*(GMW!$NF$2:$NF$60=G$1),0),$F45-1966)} -> 268798 | H45: {=INDEX(GMW!$A$2:$NF$60,MATCH(1,(GMW!$NE$2:$NE$60=H$3)*(GMW!$ND$2:$ND$60=H$4)*(GMW!$NF$2:$NF$60=H$1),0),$F45-1966)} -> 1825.225 | I45: {=INDEX(GMW!$A$2:$NF$60,MATCH(1,(GMW!$NE$2:$NE$60=I$3)*(GMW!$ND$2:$ND$60=I$4)*(GMW!$NF$2:$NF$60=I$1),0),$F45-1966)} -> 73595.08 | J45: {=INDEX(GMW!$A$2:$NF$60,MATCH(1,(GMW!$NE$2:$NE$60=J$3)*(GMW!$ND$2:$ND$60=J$4)*(GMW!$NF$2:$NF$60=J$1),0),$F45-1966)} -> 455.93 | K45: {=INDEX(GMW!$A$2:$NF$60,MATCH(1,(GMW!$NE$2:$NE$60=K$3)*(GMW!$ND$2:$ND$60=K$4)*(GMW!$NF$2:$NF$60=K$1),0),$F45-1966)} -> 316.885 | L45: {=INDEX(GMW!$A$2:$NF$60,MATCH(1,(GMW!$NE$2:$NE$60=L$3)*(GMW!$ND$2:$ND$60=L$4)*(GMW!$NF$2:$NF$60=L$1),0),$F45-1966)} -> 300.37 | M45: {=INDEX(GMW!$A$2:$NF$60,MATCH(1,(GMW!$NE$2:$NE$60=M$3)*(GMW!$ND$2:$ND$60=M$4)*(GMW!$NF$2:$NF$60=M$1),0),$F45-1966)} -> 222828 | N45: {=INDEX(GMW!$A$2:$NF$60,MATCH(1,(GMW!$NE$2:$NE$60=N$3)*(GMW!$ND$2:$ND$60=N$4)*(GMW!$NF$2:$NF$60=N$1),0),$F45-1966)} -> -2421 | ... AH45: {=INDEX(GMW!$A$2:$NF$60,MATCH(1,(GMW!$NE$2:$NE$60=AH$3)*(GMW!$ND$2:$ND$60=AH$4)*(GMW!$NF$2:$NF$60=AH$1),0),$F45-1966)} -> 97390
B46: =+B42+1 -> 1982 | C46: =+C42+1 -> 1982 | E46: =+E42+1 -> 1982 | F46: =+F45+1 -> 2012 | G46: {=INDEX(GMW!$A$2:$NF$60,MATCH(1,(GMW!$NE$2:$NE$60=G$3)*(GMW!$ND$2:$ND$60=G$4)*(GMW!$NF$2:$NF$60=G$1),0),$F46-1966)} -> 270653 | H46: {=INDEX(GMW!$A$2:$NF$60,MATCH(1,(GMW!$NE$2:$NE$60=H$3)*(GMW!$ND$2:$ND$60=H$4)*(GMW!$NF$2:$NF$60=H$1),0),$F46-1966)} -> 1825.95 | I46: {=INDEX(GMW!$A$2:$NF$60,MATCH(1,(GMW!$NE$2:$NE$60=I$3)*(GMW!$ND$2:$ND$60=I$4)*(GMW!$NF$2:$NF$60=I$1),0),$F46-1966)} -> 74635.23 | J46: {=INDEX(GMW!$A$2:$NF$60,MATCH(1,(GMW!$NE$2:$NE$60=J$3)*(GMW!$ND$2:$ND$60=J$4)*(GMW!$NF$2:$NF$60=J$1),0),$F46-1966)} -> 457 | K46: {=INDEX(GMW!$A$2:$NF$60,MATCH(1,(GMW!$NE$2:$NE$60=K$3)*(GMW!$ND$2:$ND$60=K$4)*(GMW!$NF$2:$NF$60=K$1),0),$F46-1966)} -> 318.782 | L46: {=INDEX(GMW!$A$2:$NF$60,MATCH(1,(GMW!$NE$2:$NE$60=L$3)*(GMW!$ND$2:$ND$60=L$4)*(GMW!$NF$2:$NF$60=L$1),0),$F46-1966)} -> 299.495 | M46: {=INDEX(GMW!$A$2:$NF$60,MATCH(1,(GMW!$NE$2:$NE$60=M$3)*(GMW!$ND$2:$ND$60=M$4)*(GMW!$NF$2:$NF$60=M$1),0),$F46-1966)} -> 220771.8 | N46: {=INDEX(GMW!$A$2:$NF$60,MATCH(1,(GMW!$NE$2:$NE$60=N$3)*(GMW!$ND$2:$ND$60=N$4)*(GMW!$NF$2:$NF$60=N$1),0),$F46-1966)} -> -1656 | ... AH46: {=INDEX(GMW!$A$2:$NF$60,MATCH(1,(GMW!$NE$2:$NE$60=AH$3)*(GMW!$ND$2:$ND$60=AH$4)*(GMW!$NF$2:$NF$60=AH$1),0),$F46-1966)} -> 98411
A47: 1983 | B47: =+B43+1 -> 1983 | C47: =+C43+1 -> 1982 | D47: =+D43+1 -> 1982 | F47: =+F46+1 -> 2013 | G47: {=INDEX(GMW!$A$2:$NF$60,MATCH(1,(GMW!$NE$2:$NE$60=G$3)*(GMW!$ND$2:$ND$60=G$4)*(GMW!$NF$2:$NF$60=G$1),0),$F47-1966)} -> 275877 | H47: {=INDEX(GMW!$A$2:$NF$60,MATCH(1,(GMW!$NE$2:$NE$60=H$3)*(GMW!$ND$2:$ND$60=H$4)*(GMW!$NF$2:$NF$60=H$1),0),$F47-1966)} -> 1850.025 | I47: {=INDEX(GMW!$A$2:$NF$60,MATCH(1,(GMW!$NE$2:$NE$60=I$3)*(GMW!$ND$2:$ND$60=I$4)*(GMW!$NF$2:$NF$60=I$1),0),$F47-1966)} -> 75168.8 | J47: {=INDEX(GMW!$A$2:$NF$60,MATCH(1,(GMW!$NE$2:$NE$60=J$3)*(GMW!$ND$2:$ND$60=J$4)*(GMW!$NF$2:$NF$60=J$1),0),$F47-1966)} -> 461.22 | K47: {=INDEX(GMW!$A$2:$NF$60,MATCH(1,(GMW!$NE$2:$NE$60=K$3)*(GMW!$ND$2:$ND$60=K$4)*(GMW!$NF$2:$NF$60=K$1),0),$F47-1966)} -> 320.007 | L47: {=INDEX(GMW!$A$2:$NF$60,MATCH(1,(GMW!$NE$2:$NE$60=L$3)*(GMW!$ND$2:$ND$60=L$4)*(GMW!$NF$2:$NF$60=L$1),0),$F47-1966)} -> 300.334 | M47: {=INDEX(GMW!$A$2:$NF$60,MATCH(1,(GMW!$NE$2:$NE$60=M$3)*(GMW!$ND$2:$ND$60=M$4)*(GMW!$NF$2:$NF$60=M$1),0),$F47-1966)} -> 224379.8 | N47: {=INDEX(GMW!$A$2:$NF$60,MATCH(1,(GMW!$NE$2:$NE$60=N$3)*(GMW!$ND$2:$ND$60=N$4)*(GMW!$NF$2:$NF$60=N$1),0),$F47-1966)} -> -1527 | ... AH47: {=INDEX(GMW!$A$2:$NF$60,MATCH(1,(GMW!$NE$2:$NE$60=AH$3)*(GMW!$ND$2:$ND$60=AH$4)*(GMW!$NF$2:$NF$60=AH$1),0),$F47-1966)} -> 100809
B48: =+B44+1 -> 1983 | C48: =+C44+1 -> 1983 | F48: =+F47+1 -> 2014 | G48: {=INDEX(GMW!$A$2:$NF$60,MATCH(1,(GMW!$NE$2:$NE$60=G$3)*(GMW!$ND$2:$ND$60=G$4)*(GMW!$NF$2:$NF$60=G$1),0),$F48-1966)} -> 277790 | H48: {=INDEX(GMW!$A$2:$NF$60,MATCH(1,(GMW!$NE$2:$NE$60=H$3)*(GMW!$ND$2:$ND$60=H$4)*(GMW!$NF$2:$NF$60=H$1),0),$F48-1966)} -> 1892.125 | I48: {=INDEX(GMW!$A$2:$NF$60,MATCH(1,(GMW!$NE$2:$NE$60=I$3)*(GMW!$ND$2:$ND$60=I$4)*(GMW!$NF$2:$NF$60=I$1),0),$F48-1966)} -> 75743.88 | J48: {=INDEX(GMW!$A$2:$NF$60,MATCH(1,(GMW!$NE$2:$NE$60=J$3)*(GMW!$ND$2:$ND$60=J$4)*(GMW!$NF$2:$NF$60=J$1),0),$F48-1966)} -> 466.02 | K48: {=INDEX(GMW!$A$2:$NF$60,MATCH(1,(GMW!$NE$2:$NE$60=K$3)*(GMW!$ND$2:$ND$60=K$4)*(GMW!$NF$2:$NF$60=K$1),0),$F48-1966)} -> 320.182 | L48: {=INDEX(GMW!$A$2:$NF$60,MATCH(1,(GMW!$NE$2:$NE$60=L$3)*(GMW!$ND$2:$ND$60=L$4)*(GMW!$NF$2:$NF$60=L$1),0),$F48-1966)} -> 299.975 | M48: {=INDEX(GMW!$A$2:$NF$60,MATCH(1,(GMW!$NE$2:$NE$60=M$3)*(GMW!$ND$2:$ND$60=M$4)*(GMW!$NF$2:$NF$60=M$1),0),$F48-1966)} -> 228806.3 | N48: {=INDEX(GMW!$A$2:$NF$60,MATCH(1,(GMW!$NE$2:$NE$60=N$3)*(GMW!$ND$2:$ND$60=N$4)*(GMW!$NF$2:$NF$60=N$1),0),$F48-1966)} -> -4050 | ... AH48: {=INDEX(GMW!$A$2:$NF$60,MATCH(1,(GMW!$NE$2:$NE$60=AH$3)*(GMW!$ND$2:$ND$60=AH$4)*(GMW!$NF$2:$NF$60=AH$1),0),$F48-1966)} -> 103951
B49: =+B45+1 -> 1983 | C49: =+C45+1 -> 1983 | F49: =+F48+1 -> 2015 | G49: {=INDEX(GMW!$A$2:$NF$60,MATCH(1,(GMW!$NE$2:$NE$60=G$3)*(GMW!$ND$2:$ND$60=G$4)*(GMW!$NF$2:$NF$60=G$1),0),$F49-1966)} -> 280996 | H49: {=INDEX(GMW!$A$2:$NF$60,MATCH(1,(GMW!$NE$2:$NE$60=H$3)*(GMW!$ND$2:$ND$60=H$4)*(GMW!$NF$2:$NF$60=H$1),0),$F49-1966)} -> 1929.925 | I49: {=INDEX(GMW!$A$2:$NF$60,MATCH(1,(GMW!$NE$2:$NE$60=I$3)*(GMW!$ND$2:$ND$60=I$4)*(GMW!$NF$2:$NF$60=I$1),0),$F49-1966)} -> 76764.23 | J49: {=INDEX(GMW!$A$2:$NF$60,MATCH(1,(GMW!$NE$2:$NE$60=J$3)*(GMW!$ND$2:$ND$60=J$4)*(GMW!$NF$2:$NF$60=J$1),0),$F49-1966)} -> 464.95 | K49: {=INDEX(GMW!$A$2:$NF$60,MATCH(1,(GMW!$NE$2:$NE$60=K$3)*(GMW!$ND$2:$ND$60=K$4)*(GMW!$NF$2:$NF$60=K$1),0),$F49-1966)} -> 320.696 | L49: {=INDEX(GMW!$A$2:$NF$60,MATCH(1,(GMW!$NE$2:$NE$60=L$3)*(GMW!$ND$2:$ND$60=L$4)*(GMW!$NF$2:$NF$60=L$1),0),$F49-1966)} -> 305.559 | M49: {=INDEX(GMW!$A$2:$NF$60,MATCH(1,(GMW!$NE$2:$NE$60=M$3)*(GMW!$ND$2:$ND$60=M$4)*(GMW!$NF$2:$NF$60=M$1),0),$F49-1966)} -> 231376.8 | N49: {=INDEX(GMW!$A$2:$NF$60,MATCH(1,(GMW!$NE$2:$NE$60=N$3)*(GMW!$ND$2:$ND$60=N$4)*(GMW!$NF$2:$NF$60=N$1),0),$F49-1966)} -> -4112 | ... AH49: {=INDEX(GMW!$A$2:$NF$60,MATCH(1,(GMW!$NE$2:$NE$60=AH$3)*(GMW!$ND$2:$ND$60=AH$4)*(GMW!$NF$2:$NF$60=AH$1),0),$F49-1966)} -> 107240
B50: =+B46+1 -> 1983 | C50: =+C46+1 -> 1983 | E50: =+E46+1 -> 1983 | F50: =+F49+1 -> 2016 | G50: {=INDEX(GMW!$A$2:$NF$60,MATCH(1,(GMW!$NE$2:$NE$60=G$3)*(GMW!$ND$2:$ND$60=G$4)*(GMW!$NF$2:$NF$60=G$1),0),$F50-1966)} -> 283096 | H50: {=INDEX(GMW!$A$2:$NF$60,MATCH(1,(GMW!$NE$2:$NE$60=H$3)*(GMW!$ND$2:$ND$60=H$4)*(GMW!$NF$2:$NF$60=H$1),0),$F50-1966)} -> 1970.2 | I50: {=INDEX(GMW!$A$2:$NF$60,MATCH(1,(GMW!$NE$2:$NE$60=I$3)*(GMW!$ND$2:$ND$60=I$4)*(GMW!$NF$2:$NF$60=I$1),0),$F50-1966)} -> 77307.77 | J50: {=INDEX(GMW!$A$2:$NF$60,MATCH(1,(GMW!$NE$2:$NE$60=J$3)*(GMW!$ND$2:$ND$60=J$4)*(GMW!$NF$2:$NF$60=J$1),0),$F50-1966)} -> 471.39 | K50: {=INDEX(GMW!$A$2:$NF$60,MATCH(1,(GMW!$NE$2:$NE$60=K$3)*(GMW!$ND$2:$ND$60=K$4)*(GMW!$NF$2:$NF$60=K$1),0),$F50-1966)} -> 322.692 | L50: {=INDEX(GMW!$A$2:$NF$60,MATCH(1,(GMW!$NE$2:$NE$60=L$3)*(GMW!$ND$2:$ND$60=L$4)*(GMW!$NF$2:$NF$60=L$1),0),$F50-1966)} -> 312.334 | M50: {=INDEX(GMW!$A$2:$NF$60,MATCH(1,(GMW!$NE$2:$NE$60=M$3)*(GMW!$ND$2:$ND$60=M$4)*(GMW!$NF$2:$NF$60=M$1),0),$F50-1966)} -> 234253.3 | N50: {=INDEX(GMW!$A$2:$NF$60,MATCH(1,(GMW!$NE$2:$NE$60=N$3)*(GMW!$ND$2:$ND$60=N$4)*(GMW!$NF$2:$NF$60=N$1),0),$F50-1966)} -> -893 | ... AH50: {=INDEX(GMW!$A$2:$NF$60,MATCH(1,(GMW!$NE$2:$NE$60=AH$3)*(GMW!$ND$2:$ND$60=AH$4)*(GMW!$NF$2:$NF$60=AH$1),0),$F50-1966)} -> 109316
A51: 1984 | B51: =+B47+1 -> 1984 | C51: =+C47+1 -> 1983 | D51: =+D47+1 -> 1983 | F51: =+F50+1 -> 2017 | G51: {=INDEX(GMW!$A$2:$NF$60,MATCH(1,(GMW!$NE$2:$NE$60=G$3)*(GMW!$ND$2:$ND$60=G$4)*(GMW!$NF$2:$NF$60=G$1),0),$F51-1966)} -> 285469 | H51: {=INDEX(GMW!$A$2:$NF$60,MATCH(1,(GMW!$NE$2:$NE$60=H$3)*(GMW!$ND$2:$ND$60=H$4)*(GMW!$NF$2:$NF$60=H$1),0),$F51-1966)} -> 2008.7 | I51: {=INDEX(GMW!$A$2:$NF$60,MATCH(1,(GMW!$NE$2:$NE$60=I$3)*(GMW!$ND$2:$ND$60=I$4)*(GMW!$NF$2:$NF$60=I$1),0),$F51-1966)} -> 78032.58 | J51: {=INDEX(GMW!$A$2:$NF$60,MATCH(1,(GMW!$NE$2:$NE$60=J$3)*(GMW!$ND$2:$ND$60=J$4)*(GMW!$NF$2:$NF$60=J$1),0),$F51-1966)} -> 477.6 | K51: {=INDEX(GMW!$A$2:$NF$60,MATCH(1,(GMW!$NE$2:$NE$60=K$3)*(GMW!$ND$2:$ND$60=K$4)*(GMW!$NF$2:$NF$60=K$1),0),$F51-1966)} -> 324.129 | L51: {=INDEX(GMW!$A$2:$NF$60,MATCH(1,(GMW!$NE$2:$NE$60=L$3)*(GMW!$ND$2:$ND$60=L$4)*(GMW!$NF$2:$NF$60=L$1),0),$F51-1966)} -> 311.719 | M51: {=INDEX(GMW!$A$2:$NF$60,MATCH(1,(GMW!$NE$2:$NE$60=M$3)*(GMW!$ND$2:$ND$60=M$4)*(GMW!$NF$2:$NF$60=M$1),0),$F51-1966)} -> 238310.5 | N51: {=INDEX(GMW!$A$2:$NF$60,MATCH(1,(GMW!$NE$2:$NE$60=N$3)*(GMW!$ND$2:$ND$60=N$4)*(GMW!$NF$2:$NF$60=N$1),0),$F51-1966)} -> -2747 | ... AH51: {=INDEX(GMW!$A$2:$NF$60,MATCH(1,(GMW!$NE$2:$NE$60=AH$3)*(GMW!$ND$2:$ND$60=AH$4)*(GMW!$NF$2:$NF$60=AH$1),0),$F51-1966)} -> 111960
B52: =+B48+1 -> 1984 | C52: =+C48+1 -> 1984 | F52: =+F51+1 -> 2018 | G52: {=INDEX(GMW!$A$2:$NF$60,MATCH(1,(GMW!$NE$2:$NE$60=G$3)*(GMW!$ND$2:$ND$60=G$4)*(GMW!$NF$2:$NF$60=G$1),0),$F52-1966)} -> 282605 | H52: {=INDEX(GMW!$A$2:$NF$60,MATCH(1,(GMW!$NE$2:$NE$60=H$3)*(GMW!$ND$2:$ND$60=H$4)*(GMW!$NF$2:$NF$60=H$1),0),$F52-1966)} -> 2043.425 | I52: {=INDEX(GMW!$A$2:$NF$60,MATCH(1,(GMW!$NE$2:$NE$60=I$3)*(GMW!$ND$2:$ND$60=I$4)*(GMW!$NF$2:$NF$60=I$1),0),$F52-1966)} -> 79658.95 | J52: {=INDEX(GMW!$A$2:$NF$60,MATCH(1,(GMW!$NE$2:$NE$60=J$3)*(GMW!$ND$2:$ND$60=J$4)*(GMW!$NF$2:$NF$60=J$1),0),$F52-1966)} -> 470.16 | K52: {=INDEX(GMW!$A$2:$NF$60,MATCH(1,(GMW!$NE$2:$NE$60=K$3)*(GMW!$ND$2:$ND$60=K$4)*(GMW!$NF$2:$NF$60=K$1),0),$F52-1966)} -> 325.672 | L52: {=INDEX(GMW!$A$2:$NF$60,MATCH(1,(GMW!$NE$2:$NE$60=L$3)*(GMW!$ND$2:$ND$60=L$4)*(GMW!$NF$2:$NF$60=L$1),0),$F52-1966)} -> 312.725 | M52: {=INDEX(GMW!$A$2:$NF$60,MATCH(1,(GMW!$NE$2:$NE$60=M$3)*(GMW!$ND$2:$ND$60=M$4)*(GMW!$NF$2:$NF$60=M$1),0),$F52-1966)} -> 242935.3 | N52: {=INDEX(GMW!$A$2:$NF$60,MATCH(1,(GMW!$NE$2:$NE$60=N$3)*(GMW!$ND$2:$ND$60=N$4)*(GMW!$NF$2:$NF$60=N$1),0),$F52-1966)} -> -4927 | ... AH52: {=INDEX(GMW!$A$2:$NF$60,MATCH(1,(GMW!$NE$2:$NE$60=AH$3)*(GMW!$ND$2:$ND$60=AH$4)*(GMW!$NF$2:$NF$60=AH$1),0),$F52-1966)} -> 114888
B53: =+B49+1 -> 1984 | C53: =+C49+1 -> 1984 | F53: =+F52+1 -> 2019 | G53: {=INDEX(GMW!$A$2:$NF$60,MATCH(1,(GMW!$NE$2:$NE$60=G$3)*(GMW!$ND$2:$ND$60=G$4)*(GMW!$NF$2:$NF$60=G$1),0),$F53-1966)} -> 284676 | H53: {=INDEX(GMW!$A$2:$NF$60,MATCH(1,(GMW!$NE$2:$NE$60=H$3)*(GMW!$ND$2:$ND$60=H$4)*(GMW!$NF$2:$NF$60=H$1),0),$F53-1966)} -> 2063.125 | I53: {=INDEX(GMW!$A$2:$NF$60,MATCH(1,(GMW!$NE$2:$NE$60=I$3)*(GMW!$ND$2:$ND$60=I$4)*(GMW!$NF$2:$NF$60=I$1),0),$F53-1966)} -> 80246.33 | J53: {=INDEX(GMW!$A$2:$NF$60,MATCH(1,(GMW!$NE$2:$NE$60=J$3)*(GMW!$ND$2:$ND$60=J$4)*(GMW!$NF$2:$NF$60=J$1),0),$F53-1966)} -> 482.9 | K53: {=INDEX(GMW!$A$2:$NF$60,MATCH(1,(GMW!$NE$2:$NE$60=K$3)*(GMW!$ND$2:$ND$60=K$4)*(GMW!$NF$2:$NF$60=K$1),0),$F53-1966)} -> 327.777 | L53: {=INDEX(GMW!$A$2:$NF$60,MATCH(1,(GMW!$NE$2:$NE$60=L$3)*(GMW!$ND$2:$ND$60=L$4)*(GMW!$NF$2:$NF$60=L$1),0),$F53-1966)} -> 316.407 | M53: {=INDEX(GMW!$A$2:$NF$60,MATCH(1,(GMW!$NE$2:$NE$60=M$3)*(GMW!$ND$2:$ND$60=M$4)*(GMW!$NF$2:$NF$60=M$1),0),$F53-1966)} -> 243979.8 | N53: {=INDEX(GMW!$A$2:$NF$60,MATCH(1,(GMW!$NE$2:$NE$60=N$3)*(GMW!$ND$2:$ND$60=N$4)*(GMW!$NF$2:$NF$60=N$1),0),$F53-1966)} -> -2934 | ... AH53: {=INDEX(GMW!$A$2:$NF$60,MATCH(1,(GMW!$NE$2:$NE$60=AH$3)*(GMW!$ND$2:$ND$60=AH$4)*(GMW!$NF$2:$NF$60=AH$1),0),$F53-1966)} -> 116295
B54: =+B50+1 -> 1984 | C54: =+C50+1 -> 1984 | E54: =+E50+1 -> 1984 | F54: =+F53+1 -> 2020 | G54: {=INDEX(GMW!$A$2:$NF$60,MATCH(1,(GMW!$NE$2:$NE$60=G$3)*(GMW!$ND$2:$ND$60=G$4)*(GMW!$NF$2:$NF$60=G$1),0),$F54-1966)} -> 289829 | H54: {=INDEX(GMW!$A$2:$NF$60,MATCH(1,(GMW!$NE$2:$NE$60=H$3)*(GMW!$ND$2:$ND$60=H$4)*(GMW!$NF$2:$NF$60=H$1),0),$F54-1966)} -> 2080.05 | I54: {=INDEX(GMW!$A$2:$NF$60,MATCH(1,(GMW!$NE$2:$NE$60=I$3)*(GMW!$ND$2:$ND$60=I$4)*(GMW!$NF$2:$NF$60=I$1),0),$F54-1966)} -> 80542.25 | J54: {=INDEX(GMW!$A$2:$NF$60,MATCH(1,(GMW!$NE$2:$NE$60=J$3)*(GMW!$ND$2:$ND$60=J$4)*(GMW!$NF$2:$NF$60=J$1),0),$F54-1966)} -> 486.95 | K54: {=INDEX(GMW!$A$2:$NF$60,MATCH(1,(GMW!$NE$2:$NE$60=K$3)*(GMW!$ND$2:$ND$60=K$4)*(GMW!$NF$2:$NF$60=K$1),0),$F54-1966)} -> 327.475 | L54: {=INDEX(GMW!$A$2:$NF$60,MATCH(1,(GMW!$NE$2:$NE$60=L$3)*(GMW!$ND$2:$ND$60=L$4)*(GMW!$NF$2:$NF$60=L$1),0),$F54-1966)} -> 316.458 | M54: {=INDEX(GMW!$A$2:$NF$60,MATCH(1,(GMW!$NE$2:$NE$60=M$3)*(GMW!$ND$2:$ND$60=M$4)*(GMW!$NF$2:$NF$60=M$1),0),$F54-1966)} -> 247787.5 | N54: {=INDEX(GMW!$A$2:$NF$60,MATCH(1,(GMW!$NE$2:$NE$60=N$3)*(GMW!$ND$2:$ND$60=N$4)*(GMW!$NF$2:$NF$60=N$1),0),$F54-1966)} -> -1815 | ... AH54: {=INDEX(GMW!$A$2:$NF$60,MATCH(1,(GMW!$NE$2:$NE$60=AH$3)*(GMW!$ND$2:$ND$60=AH$4)*(GMW!$NF$2:$NF$60=AH$1),0),$F54-1966)} -> 118843
A55: 1985 | B55: =+B51+1 -> 1985 | C55: =+C51+1 -> 1984 | D55: =+D51+1 -> 1984 | F55: =+F54+1 -> 2021 | G55: {=INDEX(GMW!$A$2:$NF$60,MATCH(1,(GMW!$NE$2:$NE$60=G$3)*(GMW!$ND$2:$ND$60=G$4)*(GMW!$NF$2:$NF$60=G$1),0),$F55-1966)} -> 292612 | H55: {=INDEX(GMW!$A$2:$NF$60,MATCH(1,(GMW!$NE$2:$NE$60=H$3)*(GMW!$ND$2:$ND$60=H$4)*(GMW!$NF$2:$NF$60=H$1),0),$F55-1966)} -> 2100.2 | I55: {=INDEX(GMW!$A$2:$NF$60,MATCH(1,(GMW!$NE$2:$NE$60=I$3)*(GMW!$ND$2:$ND$60=I$4)*(GMW!$NF$2:$NF$60=I$1),0),$F55-1966)} -> 81627.42 | J55: {=INDEX(GMW!$A$2:$NF$60,MATCH(1,(GMW!$NE$2:$NE$60=J$3)*(GMW!$ND$2:$ND$60=J$4)*(GMW!$NF$2:$NF$60=J$1),0),$F55-1966)} -> 484.39 | K55: {=INDEX(GMW!$A$2:$NF$60,MATCH(1,(GMW!$NE$2:$NE$60=K$3)*(GMW!$ND$2:$ND$60=K$4)*(GMW!$NF$2:$NF$60=K$1),0),$F55-1966)} -> 328.296 | L55: {=INDEX(GMW!$A$2:$NF$60,MATCH(1,(GMW!$NE$2:$NE$60=L$3)*(GMW!$ND$2:$ND$60=L$4)*(GMW!$NF$2:$NF$60=L$1),0),$F55-1966)} -> 318.265 | M55: {=INDEX(GMW!$A$2:$NF$60,MATCH(1,(GMW!$NE$2:$NE$60=M$3)*(GMW!$ND$2:$ND$60=M$4)*(GMW!$NF$2:$NF$60=M$1),0),$F55-1966)} -> 251594.5 | N55: {=INDEX(GMW!$A$2:$NF$60,MATCH(1,(GMW!$NE$2:$NE$60=N$3)*(GMW!$ND$2:$ND$60=N$4)*(GMW!$NF$2:$NF$60=N$1),0),$F55-1966)} -> -2859 | ... AH55: {=INDEX(GMW!$A$2:$NF$60,MATCH(1,(GMW!$NE$2:$NE$60=AH$3)*(GMW!$ND$2:$ND$60=AH$4)*(GMW!$NF$2:$NF$60=AH$1),0),$F55-1966)} -> 121524
B56: =+B52+1 -> 1985 | C56: =+C52+1 -> 1985 | F56: =+F55+1 -> 2022 | G56: {=INDEX(GMW!$A$2:$NF$60,MATCH(1,(GMW!$NE$2:$NE$60=G$3)*(GMW!$ND$2:$ND$60=G$4)*(GMW!$NF$2:$NF$60=G$1),0),$F56-1966)} -> 298873 | H56: {=INDEX(GMW!$A$2:$NF$60,MATCH(1,(GMW!$NE$2:$NE$60=H$3)*(GMW!$ND$2:$ND$60=H$4)*(GMW!$NF$2:$NF$60=H$1),0),$F56-1966)} -> 2118.7 | I56: {=INDEX(GMW!$A$2:$NF$60,MATCH(1,(GMW!$NE$2:$NE$60=I$3)*(GMW!$ND$2:$ND$60=I$4)*(GMW!$NF$2:$NF$60=I$1),0),$F56-1966)} -> 83146.85 | J56: {=INDEX(GMW!$A$2:$NF$60,MATCH(1,(GMW!$NE$2:$NE$60=J$3)*(GMW!$ND$2:$ND$60=J$4)*(GMW!$NF$2:$NF$60=J$1),0),$F56-1966)} -> 489.11 | K56: {=INDEX(GMW!$A$2:$NF$60,MATCH(1,(GMW!$NE$2:$NE$60=K$3)*(GMW!$ND$2:$ND$60=K$4)*(GMW!$NF$2:$NF$60=K$1),0),$F56-1966)} -> 331.027 | L56: {=INDEX(GMW!$A$2:$NF$60,MATCH(1,(GMW!$NE$2:$NE$60=L$3)*(GMW!$ND$2:$ND$60=L$4)*(GMW!$NF$2:$NF$60=L$1),0),$F56-1966)} -> 322.471 | M56: {=INDEX(GMW!$A$2:$NF$60,MATCH(1,(GMW!$NE$2:$NE$60=M$3)*(GMW!$ND$2:$ND$60=M$4)*(GMW!$NF$2:$NF$60=M$1),0),$F56-1966)} -> 252403.8 | N56: {=INDEX(GMW!$A$2:$NF$60,MATCH(1,(GMW!$NE$2:$NE$60=N$3)*(GMW!$ND$2:$ND$60=N$4)*(GMW!$NF$2:$NF$60=N$1),0),$F56-1966)} -> -4910 | ... AH56: {=INDEX(GMW!$A$2:$NF$60,MATCH(1,(GMW!$NE$2:$NE$60=AH$3)*(GMW!$ND$2:$ND$60=AH$4)*(GMW!$NF$2:$NF$60=AH$1),0),$F56-1966)} -> 123838
B57: =+B53+1 -> 1985 | C57: =+C53+1 -> 1985 | F57: =+F56+1 -> 2023 | G57: {=INDEX(GMW!$A$2:$NF$60,MATCH(1,(GMW!$NE$2:$NE$60=G$3)*(GMW!$ND$2:$ND$60=G$4)*(GMW!$NF$2:$NF$60=G$1),0),$F57-1966)} -> 298814 | H57: {=INDEX(GMW!$A$2:$NF$60,MATCH(1,(GMW!$NE$2:$NE$60=H$3)*(GMW!$ND$2:$ND$60=H$4)*(GMW!$NF$2:$NF$60=H$1),0),$F57-1966)} -> 2151.05 | I57: {=INDEX(GMW!$A$2:$NF$60,MATCH(1,(GMW!$NE$2:$NE$60=I$3)*(GMW!$ND$2:$ND$60=I$4)*(GMW!$NF$2:$NF$60=I$1),0),$F57-1966)} -> 84384.77 | J57: {=INDEX(GMW!$A$2:$NF$60,MATCH(1,(GMW!$NE$2:$NE$60=J$3)*(GMW!$ND$2:$ND$60=J$4)*(GMW!$NF$2:$NF$60=J$1),0),$F57-1966)} -> 495.57 | K57: {=INDEX(GMW!$A$2:$NF$60,MATCH(1,(GMW!$NE$2:$NE$60=K$3)*(GMW!$ND$2:$ND$60=K$4)*(GMW!$NF$2:$NF$60=K$1),0),$F57-1966)} -> 332.921 | L57: {=INDEX(GMW!$A$2:$NF$60,MATCH(1,(GMW!$NE$2:$NE$60=L$3)*(GMW!$ND$2:$ND$60=L$4)*(GMW!$NF$2:$NF$60=L$1),0),$F57-1966)} -> 325.052 | M57: {=INDEX(GMW!$A$2:$NF$60,MATCH(1,(GMW!$NE$2:$NE$60=M$3)*(GMW!$ND$2:$ND$60=M$4)*(GMW!$NF$2:$NF$60=M$1),0),$F57-1966)} -> 255608 | N57: {=INDEX(GMW!$A$2:$NF$60,MATCH(1,(GMW!$NE$2:$NE$60=N$3)*(GMW!$ND$2:$ND$60=N$4)*(GMW!$NF$2:$NF$60=N$1),0),$F57-1966)} -> -1575 | ... AH57: {=INDEX(GMW!$A$2:$NF$60,MATCH(1,(GMW!$NE$2:$NE$60=AH$3)*(GMW!$ND$2:$ND$60=AH$4)*(GMW!$NF$2:$NF$60=AH$1),0),$F57-1966)} -> 125968
B58: =+B54+1 -> 1985 | C58: =+C54+1 -> 1985 | E58: =+E54+1 -> 1985 | F58: =+F57+1 -> 2024 | G58: {=INDEX(GMW!$A$2:$NF$60,MATCH(1,(GMW!$NE$2:$NE$60=G$3)*(GMW!$ND$2:$ND$60=G$4)*(GMW!$NF$2:$NF$60=G$1),0),$F58-1966)} -> 298979 | H58: {=INDEX(GMW!$A$2:$NF$60,MATCH(1,(GMW!$NE$2:$NE$60=H$3)*(GMW!$ND$2:$ND$60=H$4)*(GMW!$NF$2:$NF$60=H$1),0),$F58-1966)} -> 2167.05 | I58: {=INDEX(GMW!$A$2:$NF$60,MATCH(1,(GMW!$NE$2:$NE$60=I$3)*(GMW!$ND$2:$ND$60=I$4)*(GMW!$NF$2:$NF$60=I$1),0),$F58-1966)} -> 85720.3 | J58: {=INDEX(GMW!$A$2:$NF$60,MATCH(1,(GMW!$NE$2:$NE$60=J$3)*(GMW!$ND$2:$ND$60=J$4)*(GMW!$NF$2:$NF$60=J$1),0),$F58-1966)} -> 498.46 | K58: {=INDEX(GMW!$A$2:$NF$60,MATCH(1,(GMW!$NE$2:$NE$60=K$3)*(GMW!$ND$2:$ND$60=K$4)*(GMW!$NF$2:$NF$60=K$1),0),$F58-1966)} -> 334.602 | L58: {=INDEX(GMW!$A$2:$NF$60,MATCH(1,(GMW!$NE$2:$NE$60=L$3)*(GMW!$ND$2:$ND$60=L$4)*(GMW!$NF$2:$NF$60=L$1),0),$F58-1966)} -> 327.22 | M58: {=INDEX(GMW!$A$2:$NF$60,MATCH(1,(GMW!$NE$2:$NE$60=M$3)*(GMW!$ND$2:$ND$60=M$4)*(GMW!$NF$2:$NF$60=M$1),0),$F58-1966)} -> 259505 | N58: {=INDEX(GMW!$A$2:$NF$60,MATCH(1,(GMW!$NE$2:$NE$60=N$3)*(GMW!$ND$2:$ND$60=N$4)*(GMW!$NF$2:$NF$60=N$1),0),$F58-1966)} -> -1219 | ... AH58: {=INDEX(GMW!$A$2:$NF$60,MATCH(1,(GMW!$NE$2:$NE$60=AH$3)*(GMW!$ND$2:$ND$60=AH$4)*(GMW!$NF$2:$NF$60=AH$1),0),$F58-1966)} -> 128697
A59: 1986 | B59: =+B55+1 -> 1986 | C59: =+C55+1 -> 1985 | D59: =+D55+1 -> 1985 | F59: =+F58+1 -> 2025 | G59: {=INDEX(GMW!$A$2:$NF$60,MATCH(1,(GMW!$NE$2:$NE$60=G$3)*(GMW!$ND$2:$ND$60=G$4)*(GMW!$NF$2:$NF$60=G$1),0),$F59-1966)} -> 302117 | H59: {=INDEX(GMW!$A$2:$NF$60,MATCH(1,(GMW!$NE$2:$NE$60=H$3)*(GMW!$ND$2:$ND$60=H$4)*(GMW!$NF$2:$NF$60=H$1),0),$F59-1966)} -> 2187.275 | I59: {=INDEX(GMW!$A$2:$NF$60,MATCH(1,(GMW!$NE$2:$NE$60=I$3)*(GMW!$ND$2:$ND$60=I$4)*(GMW!$NF$2:$NF$60=I$1),0),$F59-1966)} -> 85758.42 | J59: {=INDEX(GMW!$A$2:$NF$60,MATCH(1,(GMW!$NE$2:$NE$60=J$3)*(GMW!$ND$2:$ND$60=J$4)*(GMW!$NF$2:$NF$60=J$1),0),$F59-1966)} -> 495.73 | K59: {=INDEX(GMW!$A$2:$NF$60,MATCH(1,(GMW!$NE$2:$NE$60=K$3)*(GMW!$ND$2:$ND$60=K$4)*(GMW!$NF$2:$NF$60=K$1),0),$F59-1966)} -> 335.636 | L59: {=INDEX(GMW!$A$2:$NF$60,MATCH(1,(GMW!$NE$2:$NE$60=L$3)*(GMW!$ND$2:$ND$60=L$4)*(GMW!$NF$2:$NF$60=L$1),0),$F59-1966)} -> 329.26 | M59: {=INDEX(GMW!$A$2:$NF$60,MATCH(1,(GMW!$NE$2:$NE$60=M$3)*(GMW!$ND$2:$ND$60=M$4)*(GMW!$NF$2:$NF$60=M$1),0),$F59-1966)} -> 259373.5 | N59: {=INDEX(GMW!$A$2:$NF$60,MATCH(1,(GMW!$NE$2:$NE$60=N$3)*(GMW!$ND$2:$ND$60=N$4)*(GMW!$NF$2:$NF$60=N$1),0),$F59-1966)} -> -1330 | ... AH59: {=INDEX(GMW!$A$2:$NF$60,MATCH(1,(GMW!$NE$2:$NE$60=AH$3)*(GMW!$ND$2:$ND$60=AH$4)*(GMW!$NF$2:$NF$60=AH$1),0),$F59-1966)} -> 129653
B60: =+B56+1 -> 1986 | C60: =+C56+1 -> 1986 | F60: =+F59+1 -> 2026 | G60: {=INDEX(GMW!$A$2:$NF$60,MATCH(1,(GMW!$NE$2:$NE$60=G$3)*(GMW!$ND$2:$ND$60=G$4)*(GMW!$NF$2:$NF$60=G$1),0),$F60-1966)} -> 304797 | H60: {=INDEX(GMW!$A$2:$NF$60,MATCH(1,(GMW!$NE$2:$NE$60=H$3)*(GMW!$ND$2:$ND$60=H$4)*(GMW!$NF$2:$NF$60=H$1),0),$F60-1966)} -> 2197.125 | I60: {=INDEX(GMW!$A$2:$NF$60,MATCH(1,(GMW!$NE$2:$NE$60=I$3)*(GMW!$ND$2:$ND$60=I$4)*(GMW!$NF$2:$NF$60=I$1),0),$F60-1966)} -> 86018.4 | J60: {=INDEX(GMW!$A$2:$NF$60,MATCH(1,(GMW!$NE$2:$NE$60=J$3)*(GMW!$ND$2:$ND$60=J$4)*(GMW!$NF$2:$NF$60=J$1),0),$F60-1966)} -> 501.44 | K60: {=INDEX(GMW!$A$2:$NF$60,MATCH(1,(GMW!$NE$2:$NE$60=K$3)*(GMW!$ND$2:$ND$60=K$4)*(GMW!$NF$2:$NF$60=K$1),0),$F60-1966)} -> 339.318 | L60: {=INDEX(GMW!$A$2:$NF$60,MATCH(1,(GMW!$NE$2:$NE$60=L$3)*(GMW!$ND$2:$ND$60=L$4)*(GMW!$NF$2:$NF$60=L$1),0),$F60-1966)} -> 331.389 | M60: {=INDEX(GMW!$A$2:$NF$60,MATCH(1,(GMW!$NE$2:$NE$60=M$3)*(GMW!$ND$2:$ND$60=M$4)*(GMW!$NF$2:$NF$60=M$1),0),$F60-1966)} -> 260864.3 | N60: {=INDEX(GMW!$A$2:$NF$60,MATCH(1,(GMW!$NE$2:$NE$60=N$3)*(GMW!$ND$2:$ND$60=N$4)*(GMW!$NF$2:$NF$60=N$1),0),$F60-1966)} -> -3479 | ... AH60: {=INDEX(GMW!$A$2:$NF$60,MATCH(1,(GMW!$NE$2:$NE$60=AH$3)*(GMW!$ND$2:$ND$60=AH$4)*(GMW!$NF$2:$NF$60=AH$1),0),$F60-1966)} -> 130961
B61: =+B57+1 -> 1986 | C61: =+C57+1 -> 1986 | F61: =+F60+1 -> 2027 | G61: {=INDEX(GMW!$A$2:$NF$60,MATCH(1,(GMW!$NE$2:$NE$60=G$3)*(GMW!$ND$2:$ND$60=G$4)*(GMW!$NF$2:$NF$60=G$1),0),$F61-1966)} -> 306708 | H61: {=INDEX(GMW!$A$2:$NF$60,MATCH(1,(GMW!$NE$2:$NE$60=H$3)*(GMW!$ND$2:$ND$60=H$4)*(GMW!$NF$2:$NF$60=H$1),0),$F61-1966)} -> 2218.15 | I61: {=INDEX(GMW!$A$2:$NF$60,MATCH(1,(GMW!$NE$2:$NE$60=I$3)*(GMW!$ND$2:$ND$60=I$4)*(GMW!$NF$2:$NF$60=I$1),0),$F61-1966)} -> 86623.83 | J61: {=INDEX(GMW!$A$2:$NF$60,MATCH(1,(GMW!$NE$2:$NE$60=J$3)*(GMW!$ND$2:$ND$60=J$4)*(GMW!$NF$2:$NF$60=J$1),0),$F61-1966)} -> 505.16 | K61: {=INDEX(GMW!$A$2:$NF$60,MATCH(1,(GMW!$NE$2:$NE$60=K$3)*(GMW!$ND$2:$ND$60=K$4)*(GMW!$NF$2:$NF$60=K$1),0),$F61-1966)} -> 341.16 | L61: {=INDEX(GMW!$A$2:$NF$60,MATCH(1,(GMW!$NE$2:$NE$60=L$3)*(GMW!$ND$2:$ND$60=L$4)*(GMW!$NF$2:$NF$60=L$1),0),$F61-1966)} -> 334.698 | M61: {=INDEX(GMW!$A$2:$NF$60,MATCH(1,(GMW!$NE$2:$NE$60=M$3)*(GMW!$ND$2:$ND$60=M$4)*(GMW!$NF$2:$NF$60=M$1),0),$F61-1966)} -> 261192.3 | N61: {=INDEX(GMW!$A$2:$NF$60,MATCH(1,(GMW!$NE$2:$NE$60=N$3)*(GMW!$ND$2:$ND$60=N$4)*(GMW!$NF$2:$NF$60=N$1),0),$F61-1966)} -> -3898 | ... AH61: {=INDEX(GMW!$A$2:$NF$60,MATCH(1,(GMW!$NE$2:$NE$60=AH$3)*(GMW!$ND$2:$ND$60=AH$4)*(GMW!$NF$2:$NF$60=AH$1),0),$F61-1966)} -> 132555
B62: =+B58+1 -> 1986 | C62: =+C58+1 -> 1986 | E62: =+E58+1 -> 1986 | F62: =+F61+1 -> 2028 | G62: {=INDEX(GMW!$A$2:$NF$60,MATCH(1,(GMW!$NE$2:$NE$60=G$3)*(GMW!$ND$2:$ND$60=G$4)*(GMW!$NF$2:$NF$60=G$1),0),$F62-1966)} -> 312615 | H62: {=INDEX(GMW!$A$2:$NF$60,MATCH(1,(GMW!$NE$2:$NE$60=H$3)*(GMW!$ND$2:$ND$60=H$4)*(GMW!$NF$2:$NF$60=H$1),0),$F62-1966)} -> 2230.05 | I62: {=INDEX(GMW!$A$2:$NF$60,MATCH(1,(GMW!$NE$2:$NE$60=I$3)*(GMW!$ND$2:$ND$60=I$4)*(GMW!$NF$2:$NF$60=I$1),0),$F62-1966)} -> 87631.63 | J62: {=INDEX(GMW!$A$2:$NF$60,MATCH(1,(GMW!$NE$2:$NE$60=J$3)*(GMW!$ND$2:$ND$60=J$4)*(GMW!$NF$2:$NF$60=J$1),0),$F62-1966)} -> 510.13 | K62: {=INDEX(GMW!$A$2:$NF$60,MATCH(1,(GMW!$NE$2:$NE$60=K$3)*(GMW!$ND$2:$ND$60=K$4)*(GMW!$NF$2:$NF$60=K$1),0),$F62-1966)} -> 341.586 | L62: {=INDEX(GMW!$A$2:$NF$60,MATCH(1,(GMW!$NE$2:$NE$60=L$3)*(GMW!$ND$2:$ND$60=L$4)*(GMW!$NF$2:$NF$60=L$1),0),$F62-1966)} -> 336.071 | M62: {=INDEX(GMW!$A$2:$NF$60,MATCH(1,(GMW!$NE$2:$NE$60=M$3)*(GMW!$ND$2:$ND$60=M$4)*(GMW!$NF$2:$NF$60=M$1),0),$F62-1966)} -> 259301.5 | N62: {=INDEX(GMW!$A$2:$NF$60,MATCH(1,(GMW!$NE$2:$NE$60=N$3)*(GMW!$ND$2:$ND$60=N$4)*(GMW!$NF$2:$NF$60=N$1),0),$F62-1966)} -> -250 | ... AH62: {=INDEX(GMW!$A$2:$NF$60,MATCH(1,(GMW!$NE$2:$NE$60=AH$3)*(GMW!$ND$2:$ND$60=AH$4)*(GMW!$NF$2:$NF$60=AH$1),0),$F62-1966)} -> 133461
A63: 1987 | B63: =+B59+1 -> 1987 | C63: =+C59+1 -> 1986 | D63: =+D59+1 -> 1986 | F63: =+F62+1 -> 2029 | G63: {=INDEX(GMW!$A$2:$NF$60,MATCH(1,(GMW!$NE$2:$NE$60=G$3)*(GMW!$ND$2:$ND$60=G$4)*(GMW!$NF$2:$NF$60=G$1),0),$F63-1966)} -> 314804 | H63: {=INDEX(GMW!$A$2:$NF$60,MATCH(1,(GMW!$NE$2:$NE$60=H$3)*(GMW!$ND$2:$ND$60=H$4)*(GMW!$NF$2:$NF$60=H$1),0),$F63-1966)} -> 2246.6 | I63: {=INDEX(GMW!$A$2:$NF$60,MATCH(1,(GMW!$NE$2:$NE$60=I$3)*(GMW!$ND$2:$ND$60=I$4)*(GMW!$NF$2:$NF$60=I$1),0),$F63-1966)} -> 87931.4 | J63: {=INDEX(GMW!$A$2:$NF$60,MATCH(1,(GMW!$NE$2:$NE$60=J$3)*(GMW!$ND$2:$ND$60=J$4)*(GMW!$NF$2:$NF$60=J$1),0),$F63-1966)} -> 497.3 | K63: {=INDEX(GMW!$A$2:$NF$60,MATCH(1,(GMW!$NE$2:$NE$60=K$3)*(GMW!$ND$2:$ND$60=K$4)*(GMW!$NF$2:$NF$60=K$1),0),$F63-1966)} -> 341.867 | L63: {=INDEX(GMW!$A$2:$NF$60,MATCH(1,(GMW!$NE$2:$NE$60=L$3)*(GMW!$ND$2:$ND$60=L$4)*(GMW!$NF$2:$NF$60=L$1),0),$F63-1966)} -> 337.449 | M63: {=INDEX(GMW!$A$2:$NF$60,MATCH(1,(GMW!$NE$2:$NE$60=M$3)*(GMW!$ND$2:$ND$60=M$4)*(GMW!$NF$2:$NF$60=M$1),0),$F63-1966)} -> 265295 | N63: {=INDEX(GMW!$A$2:$NF$60,MATCH(1,(GMW!$NE$2:$NE$60=N$3)*(GMW!$ND$2:$ND$60=N$4)*(GMW!$NF$2:$NF$60=N$1),0),$F63-1966)} -> -855 | ... AH63: {=INDEX(GMW!$A$2:$NF$60,MATCH(1,(GMW!$NE$2:$NE$60=AH$3)*(GMW!$ND$2:$ND$60=AH$4)*(GMW!$NF$2:$NF$60=AH$1),0),$F63-1966)} -> 138121
B64: =+B60+1 -> 1987 | C64: =+C60+1 -> 1987 | F64: =+F63+1 -> 2030 | G64: {=INDEX(GMW!$A$2:$NF$60,MATCH(1,(GMW!$NE$2:$NE$60=G$3)*(GMW!$ND$2:$ND$60=G$4)*(GMW!$NF$2:$NF$60=G$1),0),$F64-1966)} -> 319478 | H64: {=INDEX(GMW!$A$2:$NF$60,MATCH(1,(GMW!$NE$2:$NE$60=H$3)*(GMW!$ND$2:$ND$60=H$4)*(GMW!$NF$2:$NF$60=H$1),0),$F64-1966)} -> 2270.825 | I64: {=INDEX(GMW!$A$2:$NF$60,MATCH(1,(GMW!$NE$2:$NE$60=I$3)*(GMW!$ND$2:$ND$60=I$4)*(GMW!$NF$2:$NF$60=I$1),0),$F64-1966)} -> 89458.15 | J64: {=INDEX(GMW!$A$2:$NF$60,MATCH(1,(GMW!$NE$2:$NE$60=J$3)*(GMW!$ND$2:$ND$60=J$4)*(GMW!$NF$2:$NF$60=J$1),0),$F64-1966)} -> 508.47 | K64: {=INDEX(GMW!$A$2:$NF$60,MATCH(1,(GMW!$NE$2:$NE$60=K$3)*(GMW!$ND$2:$ND$60=K$4)*(GMW!$NF$2:$NF$60=K$1),0),$F64-1966)} -> 346.957 | L64: {=INDEX(GMW!$A$2:$NF$60,MATCH(1,(GMW!$NE$2:$NE$60=L$3)*(GMW!$ND$2:$ND$60=L$4)*(GMW!$NF$2:$NF$60=L$1),0),$F64-1966)} -> 342.558 | M64: {=INDEX(GMW!$A$2:$NF$60,MATCH(1,(GMW!$NE$2:$NE$60=M$3)*(GMW!$ND$2:$ND$60=M$4)*(GMW!$NF$2:$NF$60=M$1),0),$F64-1966)} -> 268693.5 | N64: {=INDEX(GMW!$A$2:$NF$60,MATCH(1,(GMW!$NE$2:$NE$60=N$3)*(GMW!$ND$2:$ND$60=N$4)*(GMW!$NF$2:$NF$60=N$1),0),$F64-1966)} -> -4353 | ... AH64: {=INDEX(GMW!$A$2:$NF$60,MATCH(1,(GMW!$NE$2:$NE$60=AH$3)*(GMW!$ND$2:$ND$60=AH$4)*(GMW!$NF$2:$NF$60=AH$1),0),$F64-1966)} -> 141855
B65: =+B61+1 -> 1987 | C65: =+C61+1 -> 1987 | F65: =+F64+1 -> 2031 | G65: {=INDEX(GMW!$A$2:$NF$60,MATCH(1,(GMW!$NE$2:$NE$60=G$3)*(GMW!$ND$2:$ND$60=G$4)*(GMW!$NF$2:$NF$60=G$1),0),$F65-1966)} -> 327346 | H65: {=INDEX(GMW!$A$2:$NF$60,MATCH(1,(GMW!$NE$2:$NE$60=H$3)*(GMW!$ND$2:$ND$60=H$4)*(GMW!$NF$2:$NF$60=H$1),0),$F65-1966)} -> 2290.5 | I65: {=INDEX(GMW!$A$2:$NF$60,MATCH(1,(GMW!$NE$2:$NE$60=I$3)*(GMW!$ND$2:$ND$60=I$4)*(GMW!$NF$2:$NF$60=I$1),0),$F65-1966)} -> 91089.55 | J65: {=INDEX(GMW!$A$2:$NF$60,MATCH(1,(GMW!$NE$2:$NE$60=J$3)*(GMW!$ND$2:$ND$60=J$4)*(GMW!$NF$2:$NF$60=J$1),0),$F65-1966)} -> 512.03 | K65: {=INDEX(GMW!$A$2:$NF$60,MATCH(1,(GMW!$NE$2:$NE$60=K$3)*(GMW!$ND$2:$ND$60=K$4)*(GMW!$NF$2:$NF$60=K$1),0),$F65-1966)} -> 349.29 | L65: {=INDEX(GMW!$A$2:$NF$60,MATCH(1,(GMW!$NE$2:$NE$60=L$3)*(GMW!$ND$2:$ND$60=L$4)*(GMW!$NF$2:$NF$60=L$1),0),$F65-1966)} -> 343.547 | M65: {=INDEX(GMW!$A$2:$NF$60,MATCH(1,(GMW!$NE$2:$NE$60=M$3)*(GMW!$ND$2:$ND$60=M$4)*(GMW!$NF$2:$NF$60=M$1),0),$F65-1966)} -> 272798.8 | N65: {=INDEX(GMW!$A$2:$NF$60,MATCH(1,(GMW!$NE$2:$NE$60=N$3)*(GMW!$ND$2:$ND$60=N$4)*(GMW!$NF$2:$NF$60=N$1),0),$F65-1966)} -> -1823 | ... AH65: {=INDEX(GMW!$A$2:$NF$60,MATCH(1,(GMW!$NE$2:$NE$60=AH$3)*(GMW!$ND$2:$ND$60=AH$4)*(GMW!$NF$2:$NF$60=AH$1),0),$F65-1966)} -> 145420
B66: =+B62+1 -> 1987 | C66: =+C62+1 -> 1987 | E66: =+E62+1 -> 1987 | F66: =+F65+1 -> 2032 | G66: {=INDEX(GMW!$A$2:$NF$60,MATCH(1,(GMW!$NE$2:$NE$60=G$3)*(GMW!$ND$2:$ND$60=G$4)*(GMW!$NF$2:$NF$60=G$1),0),$F66-1966)} -> 331075 | H66: {=INDEX(GMW!$A$2:$NF$60,MATCH(1,(GMW!$NE$2:$NE$60=H$3)*(GMW!$ND$2:$ND$60=H$4)*(GMW!$NF$2:$NF$60=H$1),0),$F66-1966)} -> 2329.825 | I66: {=INDEX(GMW!$A$2:$NF$60,MATCH(1,(GMW!$NE$2:$NE$60=I$3)*(GMW!$ND$2:$ND$60=I$4)*(GMW!$NF$2:$NF$60=I$1),0),$F66-1966)} -> 93422.8 | J66: {=INDEX(GMW!$A$2:$NF$60,MATCH(1,(GMW!$NE$2:$NE$60=J$3)*(GMW!$ND$2:$ND$60=J$4)*(GMW!$NF$2:$NF$60=J$1),0),$F66-1966)} -> 520.15 | K66: {=INDEX(GMW!$A$2:$NF$60,MATCH(1,(GMW!$NE$2:$NE$60=K$3)*(GMW!$ND$2:$ND$60=K$4)*(GMW!$NF$2:$NF$60=K$1),0),$F66-1966)} -> 354.442 | L66: {=INDEX(GMW!$A$2:$NF$60,MATCH(1,(GMW!$NE$2:$NE$60=L$3)*(GMW!$ND$2:$ND$60=L$4)*(GMW!$NF$2:$NF$60=L$1),0),$F66-1966)} -> 347.243 | M66: {=INDEX(GMW!$A$2:$NF$60,MATCH(1,(GMW!$NE$2:$NE$60=M$3)*(GMW!$ND$2:$ND$60=M$4)*(GMW!$NF$2:$NF$60=M$1),0),$F66-1966)} -> 276323 | N66: {=INDEX(GMW!$A$2:$NF$60,MATCH(1,(GMW!$NE$2:$NE$60=N$3)*(GMW!$ND$2:$ND$60=N$4)*(GMW!$NF$2:$NF$60=N$1),0),$F66-1966)} -> 101 | ... AH66: {=INDEX(GMW!$A$2:$NF$60,MATCH(1,(GMW!$NE$2:$NE$60=AH$3)*(GMW!$ND$2:$ND$60=AH$4)*(GMW!$NF$2:$NF$60=AH$1),0),$F66-1966)} -> 148940
A67: 1988 | B67: =+B63+1 -> 1988 | C67: =+C63+1 -> 1987 | D67: =+D63+1 -> 1987 | F67: =+F66+1 -> 2033 | G67: {=INDEX(GMW!$A$2:$NF$60,MATCH(1,(GMW!$NE$2:$NE$60=G$3)*(GMW!$ND$2:$ND$60=G$4)*(GMW!$NF$2:$NF$60=G$1),0),$F67-1966)} -> 336442 | H67: {=INDEX(GMW!$A$2:$NF$60,MATCH(1,(GMW!$NE$2:$NE$60=H$3)*(GMW!$ND$2:$ND$60=H$4)*(GMW!$NF$2:$NF$60=H$1),0),$F67-1966)} -> 2341.875 | I67: {=INDEX(GMW!$A$2:$NF$60,MATCH(1,(GMW!$NE$2:$NE$60=I$3)*(GMW!$ND$2:$ND$60=I$4)*(GMW!$NF$2:$NF$60=I$1),0),$F67-1966)} -> 94866.7 | J67: {=INDEX(GMW!$A$2:$NF$60,MATCH(1,(GMW!$NE$2:$NE$60=J$3)*(GMW!$ND$2:$ND$60=J$4)*(GMW!$NF$2:$NF$60=J$1),0),$F67-1966)} -> 515.6 | K67: {=INDEX(GMW!$A$2:$NF$60,MATCH(1,(GMW!$NE$2:$NE$60=K$3)*(GMW!$ND$2:$ND$60=K$4)*(GMW!$NF$2:$NF$60=K$1),0),$F67-1966)} -> 358.993 | L67: {=INDEX(GMW!$A$2:$NF$60,MATCH(1,(GMW!$NE$2:$NE$60=L$3)*(GMW!$ND$2:$ND$60=L$4)*(GMW!$NF$2:$NF$60=L$1),0),$F67-1966)} -> 352.354 | M67: {=INDEX(GMW!$A$2:$NF$60,MATCH(1,(GMW!$NE$2:$NE$60=M$3)*(GMW!$ND$2:$ND$60=M$4)*(GMW!$NF$2:$NF$60=M$1),0),$F67-1966)} -> 280349 | N67: {=INDEX(GMW!$A$2:$NF$60,MATCH(1,(GMW!$NE$2:$NE$60=N$3)*(GMW!$ND$2:$ND$60=N$4)*(GMW!$NF$2:$NF$60=N$1),0),$F67-1966)} -> 1001 | ... AH67: {=INDEX(GMW!$A$2:$NF$60,MATCH(1,(GMW!$NE$2:$NE$60=AH$3)*(GMW!$ND$2:$ND$60=AH$4)*(GMW!$NF$2:$NF$60=AH$1),0),$F67-1966)} -> 152737
B68: =+B64+1 -> 1988 | C68: =+C64+1 -> 1988 | F68: =+F67+1 -> 2034 | G68: {=INDEX(GMW!$A$2:$NF$60,MATCH(1,(GMW!$NE$2:$NE$60=G$3)*(GMW!$ND$2:$ND$60=G$4)*(GMW!$NF$2:$NF$60=G$1),0),$F68-1966)} -> 338186 | H68: {=INDEX(GMW!$A$2:$NF$60,MATCH(1,(GMW!$NE$2:$NE$60=H$3)*(GMW!$ND$2:$ND$60=H$4)*(GMW!$NF$2:$NF$60=H$1),0),$F68-1966)} -> 2372.65 | I68: {=INDEX(GMW!$A$2:$NF$60,MATCH(1,(GMW!$NE$2:$NE$60=I$3)*(GMW!$ND$2:$ND$60=I$4)*(GMW!$NF$2:$NF$60=I$1),0),$F68-1966)} -> 95559.08 | J68: {=INDEX(GMW!$A$2:$NF$60,MATCH(1,(GMW!$NE$2:$NE$60=J$3)*(GMW!$ND$2:$ND$60=J$4)*(GMW!$NF$2:$NF$60=J$1),0),$F68-1966)} -> 524.95 | K68: {=INDEX(GMW!$A$2:$NF$60,MATCH(1,(GMW!$NE$2:$NE$60=K$3)*(GMW!$ND$2:$ND$60=K$4)*(GMW!$NF$2:$NF$60=K$1),0),$F68-1966)} -> 362.135 | L68: {=INDEX(GMW!$A$2:$NF$60,MATCH(1,(GMW!$NE$2:$NE$60=L$3)*(GMW!$ND$2:$ND$60=L$4)*(GMW!$NF$2:$NF$60=L$1),0),$F68-1966)} -> 354.592 | M68: {=INDEX(GMW!$A$2:$NF$60,MATCH(1,(GMW!$NE$2:$NE$60=M$3)*(GMW!$ND$2:$ND$60=M$4)*(GMW!$NF$2:$NF$60=M$1),0),$F68-1966)} -> 282836.8 | N68: {=INDEX(GMW!$A$2:$NF$60,MATCH(1,(GMW!$NE$2:$NE$60=N$3)*(GMW!$ND$2:$ND$60=N$4)*(GMW!$NF$2:$NF$60=N$1),0),$F68-1966)} -> -1693 | ... AH68: {=INDEX(GMW!$A$2:$NF$60,MATCH(1,(GMW!$NE$2:$NE$60=AH$3)*(GMW!$ND$2:$ND$60=AH$4)*(GMW!$NF$2:$NF$60=AH$1),0),$F68-1966)} -> 155292
B69: =+B65+1 -> 1988 | C69: =+C65+1 -> 1988 | F69: =+F68+1 -> 2035 | G69: {=INDEX(GMW!$A$2:$NF$60,MATCH(1,(GMW!$NE$2:$NE$60=G$3)*(GMW!$ND$2:$ND$60=G$4)*(GMW!$NF$2:$NF$60=G$1),0),$F69-1966)} -> 342414 | H69: {=INDEX(GMW!$A$2:$NF$60,MATCH(1,(GMW!$NE$2:$NE$60=H$3)*(GMW!$ND$2:$ND$60=H$4)*(GMW!$NF$2:$NF$60=H$1),0),$F69-1966)} -> 2386.55 | I69: {=INDEX(GMW!$A$2:$NF$60,MATCH(1,(GMW!$NE$2:$NE$60=I$3)*(GMW!$ND$2:$ND$60=I$4)*(GMW!$NF$2:$NF$60=I$1),0),$F69-1966)} -> 97321.1 | J69: {=INDEX(GMW!$A$2:$NF$60,MATCH(1,(GMW!$NE$2:$NE$60=J$3)*(GMW!$ND$2:$ND$60=J$4)*(GMW!$NF$2:$NF$60=J$1),0),$F69-1966)} -> 530.74 | K69: {=INDEX(GMW!$A$2:$NF$60,MATCH(1,(GMW!$NE$2:$NE$60=K$3)*(GMW!$ND$2:$ND$60=K$4)*(GMW!$NF$2:$NF$60=K$1),0),$F69-1966)} -> 366.718 | L69: {=INDEX(GMW!$A$2:$NF$60,MATCH(1,(GMW!$NE$2:$NE$60=L$3)*(GMW!$ND$2:$ND$60=L$4)*(GMW!$NF$2:$NF$60=L$1),0),$F69-1966)} -> 359.252 | M69: {=INDEX(GMW!$A$2:$NF$60,MATCH(1,(GMW!$NE$2:$NE$60=M$3)*(GMW!$ND$2:$ND$60=M$4)*(GMW!$NF$2:$NF$60=M$1),0),$F69-1966)} -> 282878.8 | N69: {=INDEX(GMW!$A$2:$NF$60,MATCH(1,(GMW!$NE$2:$NE$60=N$3)*(GMW!$ND$2:$ND$60=N$4)*(GMW!$NF$2:$NF$60=N$1),0),$F69-1966)} -> 1095 | ... AH69: {=INDEX(GMW!$A$2:$NF$60,MATCH(1,(GMW!$NE$2:$NE$60=AH$3)*(GMW!$ND$2:$ND$60=AH$4)*(GMW!$NF$2:$NF$60=AH$1),0),$F69-1966)} -> 157848
B70: =+B66+1 -> 1988 | C70: =+C66+1 -> 1988 | E70: =+E66+1 -> 1988 | F70: =+F69+1 -> 2036 | G70: {=INDEX(GMW!$A$2:$NF$60,MATCH(1,(GMW!$NE$2:$NE$60=G$3)*(GMW!$ND$2:$ND$60=G$4)*(GMW!$NF$2:$NF$60=G$1),0),$F70-1966)} -> 345162 | H70: {=INDEX(GMW!$A$2:$NF$60,MATCH(1,(GMW!$NE$2:$NE$60=H$3)*(GMW!$ND$2:$ND$60=H$4)*(GMW!$NF$2:$NF$60=H$1),0),$F70-1966)} -> 2418.35 | I70: {=INDEX(GMW!$A$2:$NF$60,MATCH(1,(GMW!$NE$2:$NE$60=I$3)*(GMW!$ND$2:$ND$60=I$4)*(GMW!$NF$2:$NF$60=I$1),0),$F70-1966)} -> 98386.73 | J70: {=INDEX(GMW!$A$2:$NF$60,MATCH(1,(GMW!$NE$2:$NE$60=J$3)*(GMW!$ND$2:$ND$60=J$4)*(GMW!$NF$2:$NF$60=J$1),0),$F70-1966)} -> 537.11 | K70: {=INDEX(GMW!$A$2:$NF$60,MATCH(1,(GMW!$NE$2:$NE$60=K$3)*(GMW!$ND$2:$ND$60=K$4)*(GMW!$NF$2:$NF$60=K$1),0),$F70-1966)} -> 369.743 | L70: {=INDEX(GMW!$A$2:$NF$60,MATCH(1,(GMW!$NE$2:$NE$60=L$3)*(GMW!$ND$2:$ND$60=L$4)*(GMW!$NF$2:$NF$60=L$1),0),$F70-1966)} -> 363.541 | M70: {=INDEX(GMW!$A$2:$NF$60,MATCH(1,(GMW!$NE$2:$NE$60=M$3)*(GMW!$ND$2:$ND$60=M$4)*(GMW!$NF$2:$NF$60=M$1),0),$F70-1966)} -> 284820 | N70: {=INDEX(GMW!$A$2:$NF$60,MATCH(1,(GMW!$NE$2:$NE$60=N$3)*(GMW!$ND$2:$ND$60=N$4)*(GMW!$NF$2:$NF$60=N$1),0),$F70-1966)} -> 2730 | ... AH70: {=INDEX(GMW!$A$2:$NF$60,MATCH(1,(GMW!$NE$2:$NE$60=AH$3)*(GMW!$ND$2:$ND$60=AH$4)*(GMW!$NF$2:$NF$60=AH$1),0),$F70-1966)} -> 161017
A71: 1989 | B71: =+B67+1 -> 1989 | C71: =+C67+1 -> 1988 | D71: =+D67+1 -> 1988 | F71: =+F70+1 -> 2037 | G71: {=INDEX(GMW!$A$2:$NF$60,MATCH(1,(GMW!$NE$2:$NE$60=G$3)*(GMW!$ND$2:$ND$60=G$4)*(GMW!$NF$2:$NF$60=G$1),0),$F71-1966)} -> 346836 | H71: {=INDEX(GMW!$A$2:$NF$60,MATCH(1,(GMW!$NE$2:$NE$60=H$3)*(GMW!$ND$2:$ND$60=H$4)*(GMW!$NF$2:$NF$60=H$1),0),$F71-1966)} -> 2442.925 | I71: {=INDEX(GMW!$A$2:$NF$60,MATCH(1,(GMW!$NE$2:$NE$60=I$3)*(GMW!$ND$2:$ND$60=I$4)*(GMW!$NF$2:$NF$60=I$1),0),$F71-1966)} -> 100718.5 | J71: {=INDEX(GMW!$A$2:$NF$60,MATCH(1,(GMW!$NE$2:$NE$60=J$3)*(GMW!$ND$2:$ND$60=J$4)*(GMW!$NF$2:$NF$60=J$1),0),$F71-1966)} -> 542.57 | K71: {=INDEX(GMW!$A$2:$NF$60,MATCH(1,(GMW!$NE$2:$NE$60=K$3)*(GMW!$ND$2:$ND$60=K$4)*(GMW!$NF$2:$NF$60=K$1),0),$F71-1966)} -> 374.552 | L71: {=INDEX(GMW!$A$2:$NF$60,MATCH(1,(GMW!$NE$2:$NE$60=L$3)*(GMW!$ND$2:$ND$60=L$4)*(GMW!$NF$2:$NF$60=L$1),0),$F71-1966)} -> 365.798 | M71: {=INDEX(GMW!$A$2:$NF$60,MATCH(1,(GMW!$NE$2:$NE$60=M$3)*(GMW!$ND$2:$ND$60=M$4)*(GMW!$NF$2:$NF$60=M$1),0),$F71-1966)} -> 288111 | N71: {=INDEX(GMW!$A$2:$NF$60,MATCH(1,(GMW!$NE$2:$NE$60=N$3)*(GMW!$ND$2:$ND$60=N$4)*(GMW!$NF$2:$NF$60=N$1),0),$F71-1966)} -> 3398 | ... AH71: {=INDEX(GMW!$A$2:$NF$60,MATCH(1,(GMW!$NE$2:$NE$60=AH$3)*(GMW!$ND$2:$ND$60=AH$4)*(GMW!$NF$2:$NF$60=AH$1),0),$F71-1966)} -> 164040
B72: =+B68+1 -> 1989 | C72: =+C68+1 -> 1989 | F72: =+F71+1 -> 2038 | G72: {=INDEX(GMW!$A$2:$NF$60,MATCH(1,(GMW!$NE$2:$NE$60=G$3)*(GMW!$ND$2:$ND$60=G$4)*(GMW!$NF$2:$NF$60=G$1),0),$F72-1966)} -> 348997 | H72: {=INDEX(GMW!$A$2:$NF$60,MATCH(1,(GMW!$NE$2:$NE$60=H$3)*(GMW!$ND$2:$ND$60=H$4)*(GMW!$NF$2:$NF$60=H$1),0),$F72-1966)} -> 2461.575 | I72: {=INDEX(GMW!$A$2:$NF$60,MATCH(1,(GMW!$NE$2:$NE$60=I$3)*(GMW!$ND$2:$ND$60=I$4)*(GMW!$NF$2:$NF$60=I$1),0),$F72-1966)} -> 99521.33 | J72: {=INDEX(GMW!$A$2:$NF$60,MATCH(1,(GMW!$NE$2:$NE$60=J$3)*(GMW!$ND$2:$ND$60=J$4)*(GMW!$NF$2:$NF$60=J$1),0),$F72-1966)} -> 544.81 | K72: {=INDEX(GMW!$A$2:$NF$60,MATCH(1,(GMW!$NE$2:$NE$60=K$3)*(GMW!$ND$2:$ND$60=K$4)*(GMW!$NF$2:$NF$60=K$1),0),$F72-1966)} -> 378.731 | L72: {=INDEX(GMW!$A$2:$NF$60,MATCH(1,(GMW!$NE$2:$NE$60=L$3)*(GMW!$ND$2:$ND$60=L$4)*(GMW!$NF$2:$NF$60=L$1),0),$F72-1966)} -> 367.382 | M72: {=INDEX(GMW!$A$2:$NF$60,MATCH(1,(GMW!$NE$2:$NE$60=M$3)*(GMW!$ND$2:$ND$60=M$4)*(GMW!$NF$2:$NF$60=M$1),0),$F72-1966)} -> 289231.8 | N72: {=INDEX(GMW!$A$2:$NF$60,MATCH(1,(GMW!$NE$2:$NE$60=N$3)*(GMW!$ND$2:$ND$60=N$4)*(GMW!$NF$2:$NF$60=N$1),0),$F72-1966)} -> -2035 | ... AH72: {=INDEX(GMW!$A$2:$NF$60,MATCH(1,(GMW!$NE$2:$NE$60=AH$3)*(GMW!$ND$2:$ND$60=AH$4)*(GMW!$NF$2:$NF$60=AH$1),0),$F72-1966)} -> 167448
B73: =+B69+1 -> 1989 | C73: =+C69+1 -> 1989 | F73: =+F72+1 -> 2039 | G73: {=INDEX(GMW!$A$2:$NF$60,MATCH(1,(GMW!$NE$2:$NE$60=G$3)*(GMW!$ND$2:$ND$60=G$4)*(GMW!$NF$2:$NF$60=G$1),0),$F73-1966)} -> 349572 | H73: {=INDEX(GMW!$A$2:$NF$60,MATCH(1,(GMW!$NE$2:$NE$60=H$3)*(GMW!$ND$2:$ND$60=H$4)*(GMW!$NF$2:$NF$60=H$1),0),$F73-1966)} -> 2479.8 | I73: {=INDEX(GMW!$A$2:$NF$60,MATCH(1,(GMW!$NE$2:$NE$60=I$3)*(GMW!$ND$2:$ND$60=I$4)*(GMW!$NF$2:$NF$60=I$1),0),$F73-1966)} -> 101067.9 | J73: {=INDEX(GMW!$A$2:$NF$60,MATCH(1,(GMW!$NE$2:$NE$60=J$3)*(GMW!$ND$2:$ND$60=J$4)*(GMW!$NF$2:$NF$60=J$1),0),$F73-1966)} -> 549.78 | K73: {=INDEX(GMW!$A$2:$NF$60,MATCH(1,(GMW!$NE$2:$NE$60=K$3)*(GMW!$ND$2:$ND$60=K$4)*(GMW!$NF$2:$NF$60=K$1),0),$F73-1966)} -> 382.998 | L73: {=INDEX(GMW!$A$2:$NF$60,MATCH(1,(GMW!$NE$2:$NE$60=L$3)*(GMW!$ND$2:$ND$60=L$4)*(GMW!$NF$2:$NF$60=L$1),0),$F73-1966)} -> 371.212 | M73: {=INDEX(GMW!$A$2:$NF$60,MATCH(1,(GMW!$NE$2:$NE$60=M$3)*(GMW!$ND$2:$ND$60=M$4)*(GMW!$NF$2:$NF$60=M$1),0),$F73-1966)} -> 290276 | N73: {=INDEX(GMW!$A$2:$NF$60,MATCH(1,(GMW!$NE$2:$NE$60=N$3)*(GMW!$ND$2:$ND$60=N$4)*(GMW!$NF$2:$NF$60=N$1),0),$F73-1966)} -> -784 | ... AH73: {=INDEX(GMW!$A$2:$NF$60,MATCH(1,(GMW!$NE$2:$NE$60=AH$3)*(GMW!$ND$2:$ND$60=AH$4)*(GMW!$NF$2:$NF$60=AH$1),0),$F73-1966)} -> 169783
B74: =+B70+1 -> 1989 | C74: =+C70+1 -> 1989 | E74: =+E70+1 -> 1989 | F74: =+F73+1 -> 2040 | G74: {=INDEX(GMW!$A$2:$NF$60,MATCH(1,(GMW!$NE$2:$NE$60=G$3)*(GMW!$ND$2:$ND$60=G$4)*(GMW!$NF$2:$NF$60=G$1),0),$F74-1966)} -> 349523 | H74: {=INDEX(GMW!$A$2:$NF$60,MATCH(1,(GMW!$NE$2:$NE$60=H$3)*(GMW!$ND$2:$ND$60=H$4)*(GMW!$NF$2:$NF$60=H$1),0),$F74-1966)} -> 2484.7 | I74: {=INDEX(GMW!$A$2:$NF$60,MATCH(1,(GMW!$NE$2:$NE$60=I$3)*(GMW!$ND$2:$ND$60=I$4)*(GMW!$NF$2:$NF$60=I$1),0),$F74-1966)} -> 103823.8 | J74: {=INDEX(GMW!$A$2:$NF$60,MATCH(1,(GMW!$NE$2:$NE$60=J$3)*(GMW!$ND$2:$ND$60=J$4)*(GMW!$NF$2:$NF$60=J$1),0),$F74-1966)} -> 556.15 | K74: {=INDEX(GMW!$A$2:$NF$60,MATCH(1,(GMW!$NE$2:$NE$60=K$3)*(GMW!$ND$2:$ND$60=K$4)*(GMW!$NF$2:$NF$60=K$1),0),$F74-1966)} -> 388.135 | L74: {=INDEX(GMW!$A$2:$NF$60,MATCH(1,(GMW!$NE$2:$NE$60=L$3)*(GMW!$ND$2:$ND$60=L$4)*(GMW!$NF$2:$NF$60=L$1),0),$F74-1966)} -> 375.032 | M74: {=INDEX(GMW!$A$2:$NF$60,MATCH(1,(GMW!$NE$2:$NE$60=M$3)*(GMW!$ND$2:$ND$60=M$4)*(GMW!$NF$2:$NF$60=M$1),0),$F74-1966)} -> 289698.3 | N74: {=INDEX(GMW!$A$2:$NF$60,MATCH(1,(GMW!$NE$2:$NE$60=N$3)*(GMW!$ND$2:$ND$60=N$4)*(GMW!$NF$2:$NF$60=N$1),0),$F74-1966)} -> 2538 | ... AH74: {=INDEX(GMW!$A$2:$NF$60,MATCH(1,(GMW!$NE$2:$NE$60=AH$3)*(GMW!$ND$2:$ND$60=AH$4)*(GMW!$NF$2:$NF$60=AH$1),0),$F74-1966)} -> 170308
A75: 1990 | B75: =+B71+1 -> 1990 | C75: =+C71+1 -> 1989 | D75: =+D71+1 -> 1989 | F75: =+F74+1 -> 2041 | G75: {=INDEX(GMW!$A$2:$NF$60,MATCH(1,(GMW!$NE$2:$NE$60=G$3)*(GMW!$ND$2:$ND$60=G$4)*(GMW!$NF$2:$NF$60=G$1),0),$F75-1966)} -> 351299 | H75: {=INDEX(GMW!$A$2:$NF$60,MATCH(1,(GMW!$NE$2:$NE$60=H$3)*(GMW!$ND$2:$ND$60=H$4)*(GMW!$NF$2:$NF$60=H$1),0),$F75-1966)} -> 2511.85 | I75: {=INDEX(GMW!$A$2:$NF$60,MATCH(1,(GMW!$NE$2:$NE$60=I$3)*(GMW!$ND$2:$ND$60=I$4)*(GMW!$NF$2:$NF$60=I$1),0),$F75-1966)} -> 103264 | J75: {=INDEX(GMW!$A$2:$NF$60,MATCH(1,(GMW!$NE$2:$NE$60=J$3)*(GMW!$ND$2:$ND$60=J$4)*(GMW!$NF$2:$NF$60=J$1),0),$F75-1966)} -> 567.64 | K75: {=INDEX(GMW!$A$2:$NF$60,MATCH(1,(GMW!$NE$2:$NE$60=K$3)*(GMW!$ND$2:$ND$60=K$4)*(GMW!$NF$2:$NF$60=K$1),0),$F75-1966)} -> 388.956 | L75: {=INDEX(GMW!$A$2:$NF$60,MATCH(1,(GMW!$NE$2:$NE$60=L$3)*(GMW!$ND$2:$ND$60=L$4)*(GMW!$NF$2:$NF$60=L$1),0),$F75-1966)} -> 376.526 | M75: {=INDEX(GMW!$A$2:$NF$60,MATCH(1,(GMW!$NE$2:$NE$60=M$3)*(GMW!$ND$2:$ND$60=M$4)*(GMW!$NF$2:$NF$60=M$1),0),$F75-1966)} -> 292484.3 | N75: {=INDEX(GMW!$A$2:$NF$60,MATCH(1,(GMW!$NE$2:$NE$60=N$3)*(GMW!$ND$2:$ND$60=N$4)*(GMW!$NF$2:$NF$60=N$1),0),$F75-1966)} -> 157 | ... AH75: {=INDEX(GMW!$A$2:$NF$60,MATCH(1,(GMW!$NE$2:$NE$60=AH$3)*(GMW!$ND$2:$ND$60=AH$4)*(GMW!$NF$2:$NF$60=AH$1),0),$F75-1966)} -> 172982
B76: =+B72+1 -> 1990 | C76: =+C72+1 -> 1990 | F76: =+F75+1 -> 2042 | G76: {=INDEX(GMW!$A$2:$NF$60,MATCH(1,(GMW!$NE$2:$NE$60=G$3)*(GMW!$ND$2:$ND$60=G$4)*(GMW!$NF$2:$NF$60=G$1),0),$F76-1966)} -> 353663 | H76: {=INDEX(GMW!$A$2:$NF$60,MATCH(1,(GMW!$NE$2:$NE$60=H$3)*(GMW!$ND$2:$ND$60=H$4)*(GMW!$NF$2:$NF$60=H$1),0),$F76-1966)} -> 2520.975 | I76: {=INDEX(GMW!$A$2:$NF$60,MATCH(1,(GMW!$NE$2:$NE$60=I$3)*(GMW!$ND$2:$ND$60=I$4)*(GMW!$NF$2:$NF$60=I$1),0),$F76-1966)} -> 105791 | J76: {=INDEX(GMW!$A$2:$NF$60,MATCH(1,(GMW!$NE$2:$NE$60=J$3)*(GMW!$ND$2:$ND$60=J$4)*(GMW!$NF$2:$NF$60=J$1),0),$F76-1966)} -> 570.55 | K76: {=INDEX(GMW!$A$2:$NF$60,MATCH(1,(GMW!$NE$2:$NE$60=K$3)*(GMW!$ND$2:$ND$60=K$4)*(GMW!$NF$2:$NF$60=K$1),0),$F76-1966)} -> 391.046 | L76: {=INDEX(GMW!$A$2:$NF$60,MATCH(1,(GMW!$NE$2:$NE$60=L$3)*(GMW!$ND$2:$ND$60=L$4)*(GMW!$NF$2:$NF$60=L$1),0),$F76-1966)} -> 377.674 | M76: {=INDEX(GMW!$A$2:$NF$60,MATCH(1,(GMW!$NE$2:$NE$60=M$3)*(GMW!$ND$2:$ND$60=M$4)*(GMW!$NF$2:$NF$60=M$1),0),$F76-1966)} -> 291310.8 | N76: {=INDEX(GMW!$A$2:$NF$60,MATCH(1,(GMW!$NE$2:$NE$60=N$3)*(GMW!$ND$2:$ND$60=N$4)*(GMW!$NF$2:$NF$60=N$1),0),$F76-1966)} -> -3212 | ... AH76: {=INDEX(GMW!$A$2:$NF$60,MATCH(1,(GMW!$NE$2:$NE$60=AH$3)*(GMW!$ND$2:$ND$60=AH$4)*(GMW!$NF$2:$NF$60=AH$1),0),$F76-1966)} -> 173906
B77: =+B73+1 -> 1990 | C77: =+C73+1 -> 1990 | F77: =+F76+1 -> 2043 | G77: {=INDEX(GMW!$A$2:$NF$60,MATCH(1,(GMW!$NE$2:$NE$60=G$3)*(GMW!$ND$2:$ND$60=G$4)*(GMW!$NF$2:$NF$60=G$1),0),$F77-1966)} -> 349780 | H77: {=INDEX(GMW!$A$2:$NF$60,MATCH(1,(GMW!$NE$2:$NE$60=H$3)*(GMW!$ND$2:$ND$60=H$4)*(GMW!$NF$2:$NF$60=H$1),0),$F77-1966)} -> 2522.65 | I77: {=INDEX(GMW!$A$2:$NF$60,MATCH(1,(GMW!$NE$2:$NE$60=I$3)*(GMW!$ND$2:$ND$60=I$4)*(GMW!$NF$2:$NF$60=I$1),0),$F77-1966)} -> 107937.8 | J77: {=INDEX(GMW!$A$2:$NF$60,MATCH(1,(GMW!$NE$2:$NE$60=J$3)*(GMW!$ND$2:$ND$60=J$4)*(GMW!$NF$2:$NF$60=J$1),0),$F77-1966)} -> 582.54 | K77: {=INDEX(GMW!$A$2:$NF$60,MATCH(1,(GMW!$NE$2:$NE$60=K$3)*(GMW!$ND$2:$ND$60=K$4)*(GMW!$NF$2:$NF$60=K$1),0),$F77-1966)} -> 393.587 | L77: {=INDEX(GMW!$A$2:$NF$60,MATCH(1,(GMW!$NE$2:$NE$60=L$3)*(GMW!$ND$2:$ND$60=L$4)*(GMW!$NF$2:$NF$60=L$1),0),$F77-1966)} -> 378.281 | M77: {=INDEX(GMW!$A$2:$NF$60,MATCH(1,(GMW!$NE$2:$NE$60=M$3)*(GMW!$ND$2:$ND$60=M$4)*(GMW!$NF$2:$NF$60=M$1),0),$F77-1966)} -> 289223 | N77: {=INDEX(GMW!$A$2:$NF$60,MATCH(1,(GMW!$NE$2:$NE$60=N$3)*(GMW!$ND$2:$ND$60=N$4)*(GMW!$NF$2:$NF$60=N$1),0),$F77-1966)} -> -1084 | ... AH77: {=INDEX(GMW!$A$2:$NF$60,MATCH(1,(GMW!$NE$2:$NE$60=AH$3)*(GMW!$ND$2:$ND$60=AH$4)*(GMW!$NF$2:$NF$60=AH$1),0),$F77-1966)} -> 174421
B78: =+B74+1 -> 1990 | C78: =+C74+1 -> 1990 | E78: =+E74+1 -> 1990 | F78: =+F77+1 -> 2044 | G78: {=INDEX(GMW!$A$2:$NF$60,MATCH(1,(GMW!$NE$2:$NE$60=G$3)*(GMW!$ND$2:$ND$60=G$4)*(GMW!$NF$2:$NF$60=G$1),0),$F78-1966)} -> 348006 | H78: {=INDEX(GMW!$A$2:$NF$60,MATCH(1,(GMW!$NE$2:$NE$60=H$3)*(GMW!$ND$2:$ND$60=H$4)*(GMW!$NF$2:$NF$60=H$1),0),$F78-1966)} -> 2499.675 | I78: {=INDEX(GMW!$A$2:$NF$60,MATCH(1,(GMW!$NE$2:$NE$60=I$3)*(GMW!$ND$2:$ND$60=I$4)*(GMW!$NF$2:$NF$60=I$1),0),$F78-1966)} -> 107869 | J78: {=INDEX(GMW!$A$2:$NF$60,MATCH(1,(GMW!$NE$2:$NE$60=J$3)*(GMW!$ND$2:$ND$60=J$4)*(GMW!$NF$2:$NF$60=J$1),0),$F78-1966)} -> 592.8 | K78: {=INDEX(GMW!$A$2:$NF$60,MATCH(1,(GMW!$NE$2:$NE$60=K$3)*(GMW!$ND$2:$ND$60=K$4)*(GMW!$NF$2:$NF$60=K$1),0),$F78-1966)} -> 393.398 | L78: {=INDEX(GMW!$A$2:$NF$60,MATCH(1,(GMW!$NE$2:$NE$60=L$3)*(GMW!$ND$2:$ND$60=L$4)*(GMW!$NF$2:$NF$60=L$1),0),$F78-1966)} -> 375.822 | M78: {=INDEX(GMW!$A$2:$NF$60,MATCH(1,(GMW!$NE$2:$NE$60=M$3)*(GMW!$ND$2:$ND$60=M$4)*(GMW!$NF$2:$NF$60=M$1),0),$F78-1966)} -> 286647.8 | N78: {=INDEX(GMW!$A$2:$NF$60,MATCH(1,(GMW!$NE$2:$NE$60=N$3)*(GMW!$ND$2:$ND$60=N$4)*(GMW!$NF$2:$NF$60=N$1),0),$F78-1966)} -> -1129 | ... AH78: {=INDEX(GMW!$A$2:$NF$60,MATCH(1,(GMW!$NE$2:$NE$60=AH$3)*(GMW!$ND$2:$ND$60=AH$4)*(GMW!$NF$2:$NF$60=AH$1),0),$F78-1966)} -> 174192
A79: 1991 | B79: =+B75+1 -> 1991 | C79: =+C75+1 -> 1990 | D79: =+D75+1 -> 1990 | F79: =+F78+1 -> 2045 | G79: {=INDEX(GMW!$A$2:$NF$60,MATCH(1,(GMW!$NE$2:$NE$60=G$3)*(GMW!$ND$2:$ND$60=G$4)*(GMW!$NF$2:$NF$60=G$1),0),$F79-1966)} -> 346292 | H79: {=INDEX(GMW!$A$2:$NF$60,MATCH(1,(GMW!$NE$2:$NE$60=H$3)*(GMW!$ND$2:$ND$60=H$4)*(GMW!$NF$2:$NF$60=H$1),0),$F79-1966)} -> 2487.975 | I79: {=INDEX(GMW!$A$2:$NF$60,MATCH(1,(GMW!$NE$2:$NE$60=I$3)*(GMW!$ND$2:$ND$60=I$4)*(GMW!$NF$2:$NF$60=I$1),0),$F79-1966)} -> 109030.2 | J79: {=INDEX(GMW!$A$2:$NF$60,MATCH(1,(GMW!$NE$2:$NE$60=J$3)*(GMW!$ND$2:$ND$60=J$4)*(GMW!$NF$2:$NF$60=J$1),0),$F79-1966)} -> 610.84 | K79: {=INDEX(GMW!$A$2:$NF$60,MATCH(1,(GMW!$NE$2:$NE$60=K$3)*(GMW!$ND$2:$ND$60=K$4)*(GMW!$NF$2:$NF$60=K$1),0),$F79-1966)} -> 394.433 | L79: {=INDEX(GMW!$A$2:$NF$60,MATCH(1,(GMW!$NE$2:$NE$60=L$3)*(GMW!$ND$2:$ND$60=L$4)*(GMW!$NF$2:$NF$60=L$1),0),$F79-1966)} -> 379.581 | M79: {=INDEX(GMW!$A$2:$NF$60,MATCH(1,(GMW!$NE$2:$NE$60=M$3)*(GMW!$ND$2:$ND$60=M$4)*(GMW!$NF$2:$NF$60=M$1),0),$F79-1966)} -> 282524 | N79: {=INDEX(GMW!$A$2:$NF$60,MATCH(1,(GMW!$NE$2:$NE$60=N$3)*(GMW!$ND$2:$ND$60=N$4)*(GMW!$NF$2:$NF$60=N$1),0),$F79-1966)} -> -1890 | ... AH79: {=INDEX(GMW!$A$2:$NF$60,MATCH(1,(GMW!$NE$2:$NE$60=AH$3)*(GMW!$ND$2:$ND$60=AH$4)*(GMW!$NF$2:$NF$60=AH$1),0),$F79-1966)} -> 173502
B80: =+B76+1 -> 1991 | C80: =+C76+1 -> 1991 | F80: =+F79+1 -> 2046 | G80: {=INDEX(GMW!$A$2:$NF$60,MATCH(1,(GMW!$NE$2:$NE$60=G$3)*(GMW!$ND$2:$ND$60=G$4)*(GMW!$NF$2:$NF$60=G$1),0),$F80-1966)} -> 345892 | H80: {=INDEX(GMW!$A$2:$NF$60,MATCH(1,(GMW!$NE$2:$NE$60=H$3)*(GMW!$ND$2:$ND$60=H$4)*(GMW!$NF$2:$NF$60=H$1),0),$F80-1966)} -> 2507.375 | I80: {=INDEX(GMW!$A$2:$NF$60,MATCH(1,(GMW!$NE$2:$NE$60=I$3)*(GMW!$ND$2:$ND$60=I$4)*(GMW!$NF$2:$NF$60=I$1),0),$F80-1966)} -> 109977.8 | J80: {=INDEX(GMW!$A$2:$NF$60,MATCH(1,(GMW!$NE$2:$NE$60=J$3)*(GMW!$ND$2:$ND$60=J$4)*(GMW!$NF$2:$NF$60=J$1),0),$F80-1966)} -> 607.91 | K80: {=INDEX(GMW!$A$2:$NF$60,MATCH(1,(GMW!$NE$2:$NE$60=K$3)*(GMW!$ND$2:$ND$60=K$4)*(GMW!$NF$2:$NF$60=K$1),0),$F80-1966)} -> 395.89 | L80: {=INDEX(GMW!$A$2:$NF$60,MATCH(1,(GMW!$NE$2:$NE$60=L$3)*(GMW!$ND$2:$ND$60=L$4)*(GMW!$NF$2:$NF$60=L$1),0),$F80-1966)} -> 377.503 | M80: {=INDEX(GMW!$A$2:$NF$60,MATCH(1,(GMW!$NE$2:$NE$60=M$3)*(GMW!$ND$2:$ND$60=M$4)*(GMW!$NF$2:$NF$60=M$1),0),$F80-1966)} -> 283880 | N80: {=INDEX(GMW!$A$2:$NF$60,MATCH(1,(GMW!$NE$2:$NE$60=N$3)*(GMW!$ND$2:$ND$60=N$4)*(GMW!$NF$2:$NF$60=N$1),0),$F80-1966)} -> -7462 | ... AH80: {=INDEX(GMW!$A$2:$NF$60,MATCH(1,(GMW!$NE$2:$NE$60=AH$3)*(GMW!$ND$2:$ND$60=AH$4)*(GMW!$NF$2:$NF$60=AH$1),0),$F80-1966)} -> 175393
B81: =+B77+1 -> 1991 | C81: =+C77+1 -> 1991 | F81: =+F80+1 -> 2047 | G81: {=INDEX(GMW!$A$2:$NF$60,MATCH(1,(GMW!$NE$2:$NE$60=G$3)*(GMW!$ND$2:$ND$60=G$4)*(GMW!$NF$2:$NF$60=G$1),0),$F81-1966)} -> 345216 | H81: {=INDEX(GMW!$A$2:$NF$60,MATCH(1,(GMW!$NE$2:$NE$60=H$3)*(GMW!$ND$2:$ND$60=H$4)*(GMW!$NF$2:$NF$60=H$1),0),$F81-1966)} -> 2520.05 | I81: {=INDEX(GMW!$A$2:$NF$60,MATCH(1,(GMW!$NE$2:$NE$60=I$3)*(GMW!$ND$2:$ND$60=I$4)*(GMW!$NF$2:$NF$60=I$1),0),$F81-1966)} -> 109973 | J81: {=INDEX(GMW!$A$2:$NF$60,MATCH(1,(GMW!$NE$2:$NE$60=J$3)*(GMW!$ND$2:$ND$60=J$4)*(GMW!$NF$2:$NF$60=J$1),0),$F81-1966)} -> 606.96 | K81: {=INDEX(GMW!$A$2:$NF$60,MATCH(1,(GMW!$NE$2:$NE$60=K$3)*(GMW!$ND$2:$ND$60=K$4)*(GMW!$NF$2:$NF$60=K$1),0),$F81-1966)} -> 397.495 | L81: {=INDEX(GMW!$A$2:$NF$60,MATCH(1,(GMW!$NE$2:$NE$60=L$3)*(GMW!$ND$2:$ND$60=L$4)*(GMW!$NF$2:$NF$60=L$1),0),$F81-1966)} -> 377.639 | M81: {=INDEX(GMW!$A$2:$NF$60,MATCH(1,(GMW!$NE$2:$NE$60=M$3)*(GMW!$ND$2:$ND$60=M$4)*(GMW!$NF$2:$NF$60=M$1),0),$F81-1966)} -> 284256.5 | N81: {=INDEX(GMW!$A$2:$NF$60,MATCH(1,(GMW!$NE$2:$NE$60=N$3)*(GMW!$ND$2:$ND$60=N$4)*(GMW!$NF$2:$NF$60=N$1),0),$F81-1966)} -> -5732 | ... AH81: {=INDEX(GMW!$A$2:$NF$60,MATCH(1,(GMW!$NE$2:$NE$60=AH$3)*(GMW!$ND$2:$ND$60=AH$4)*(GMW!$NF$2:$NF$60=AH$1),0),$F81-1966)} -> 176199
B82: =+B78+1 -> 1991 | C82: =+C78+1 -> 1991 | E82: =+E78+1 -> 1991 | F82: =+F81+1 -> 2048 | G82: {=INDEX(GMW!$A$2:$NF$60,MATCH(1,(GMW!$NE$2:$NE$60=G$3)*(GMW!$ND$2:$ND$60=G$4)*(GMW!$NF$2:$NF$60=G$1),0),$F82-1966)} -> 345643 | H82: {=INDEX(GMW!$A$2:$NF$60,MATCH(1,(GMW!$NE$2:$NE$60=H$3)*(GMW!$ND$2:$ND$60=H$4)*(GMW!$NF$2:$NF$60=H$1),0),$F82-1966)} -> 2528.825 | I82: {=INDEX(GMW!$A$2:$NF$60,MATCH(1,(GMW!$NE$2:$NE$60=I$3)*(GMW!$ND$2:$ND$60=I$4)*(GMW!$NF$2:$NF$60=I$1),0),$F82-1966)} -> 110813.9 | J82: {=INDEX(GMW!$A$2:$NF$60,MATCH(1,(GMW!$NE$2:$NE$60=J$3)*(GMW!$ND$2:$ND$60=J$4)*(GMW!$NF$2:$NF$60=J$1),0),$F82-1966)} -> 615.67 | K82: {=INDEX(GMW!$A$2:$NF$60,MATCH(1,(GMW!$NE$2:$NE$60=K$3)*(GMW!$ND$2:$ND$60=K$4)*(GMW!$NF$2:$NF$60=K$1),0),$F82-1966)} -> 399.413 | L82: {=INDEX(GMW!$A$2:$NF$60,MATCH(1,(GMW!$NE$2:$NE$60=L$3)*(GMW!$ND$2:$ND$60=L$4)*(GMW!$NF$2:$NF$60=L$1),0),$F82-1966)} -> 382.071 | M82: {=INDEX(GMW!$A$2:$NF$60,MATCH(1,(GMW!$NE$2:$NE$60=M$3)*(GMW!$ND$2:$ND$60=M$4)*(GMW!$NF$2:$NF$60=M$1),0),$F82-1966)} -> 284756 | N82: {=INDEX(GMW!$A$2:$NF$60,MATCH(1,(GMW!$NE$2:$NE$60=N$3)*(GMW!$ND$2:$ND$60=N$4)*(GMW!$NF$2:$NF$60=N$1),0),$F82-1966)} -> -4106 | ... AH82: {=INDEX(GMW!$A$2:$NF$60,MATCH(1,(GMW!$NE$2:$NE$60=AH$3)*(GMW!$ND$2:$ND$60=AH$4)*(GMW!$NF$2:$NF$60=AH$1),0),$F82-1966)} -> 176679
A83: 1992 | B83: =+B79+1 -> 1992 | C83: =+C79+1 -> 1991 | D83: =+D79+1 -> 1991 | F83: =+F82+1 -> 2049 | G83: {=INDEX(GMW!$A$2:$NF$60,MATCH(1,(GMW!$NE$2:$NE$60=G$3)*(GMW!$ND$2:$ND$60=G$4)*(GMW!$NF$2:$NF$60=G$1),0),$F83-1966)} -> 345523 | H83: {=INDEX(GMW!$A$2:$NF$60,MATCH(1,(GMW!$NE$2:$NE$60=H$3)*(GMW!$ND$2:$ND$60=H$4)*(GMW!$NF$2:$NF$60=H$1),0),$F83-1966)} -> 2559.1 | I83: {=INDEX(GMW!$A$2:$NF$60,MATCH(1,(GMW!$NE$2:$NE$60=I$3)*(GMW!$ND$2:$ND$60=I$4)*(GMW!$NF$2:$NF$60=I$1),0),$F83-1966)} -> 110645.6 | J83: {=INDEX(GMW!$A$2:$NF$60,MATCH(1,(GMW!$NE$2:$NE$60=J$3)*(GMW!$ND$2:$ND$60=J$4)*(GMW!$NF$2:$NF$60=J$1),0),$F83-1966)} -> 624.15 | K83: {=INDEX(GMW!$A$2:$NF$60,MATCH(1,(GMW!$NE$2:$NE$60=K$3)*(GMW!$ND$2:$ND$60=K$4)*(GMW!$NF$2:$NF$60=K$1),0),$F83-1966)} -> 402.27 | L83: {=INDEX(GMW!$A$2:$NF$60,MATCH(1,(GMW!$NE$2:$NE$60=L$3)*(GMW!$ND$2:$ND$60=L$4)*(GMW!$NF$2:$NF$60=L$1),0),$F83-1966)} -> 383.1 | M83: {=INDEX(GMW!$A$2:$NF$60,MATCH(1,(GMW!$NE$2:$NE$60=M$3)*(GMW!$ND$2:$ND$60=M$4)*(GMW!$NF$2:$NF$60=M$1),0),$F83-1966)} -> 284957 | N83: {=INDEX(GMW!$A$2:$NF$60,MATCH(1,(GMW!$NE$2:$NE$60=N$3)*(GMW!$ND$2:$ND$60=N$4)*(GMW!$NF$2:$NF$60=N$1),0),$F83-1966)} -> -6464 | ... AH83: {=INDEX(GMW!$A$2:$NF$60,MATCH(1,(GMW!$NE$2:$NE$60=AH$3)*(GMW!$ND$2:$ND$60=AH$4)*(GMW!$NF$2:$NF$60=AH$1),0),$F83-1966)} -> 177502
B84: =+B80+1 -> 1992 | C84: =+C80+1 -> 1992 | F84: =+F83+1 -> 2050 | G84: {=INDEX(GMW!$A$2:$NF$60,MATCH(1,(GMW!$NE$2:$NE$60=G$3)*(GMW!$ND$2:$ND$60=G$4)*(GMW!$NF$2:$NF$60=G$1),0),$F84-1966)} -> 344987 | H84: {=INDEX(GMW!$A$2:$NF$60,MATCH(1,(GMW!$NE$2:$NE$60=H$3)*(GMW!$ND$2:$ND$60=H$4)*(GMW!$NF$2:$NF$60=H$1),0),$F84-1966)} -> 2586.85 | I84: {=INDEX(GMW!$A$2:$NF$60,MATCH(1,(GMW!$NE$2:$NE$60=I$3)*(GMW!$ND$2:$ND$60=I$4)*(GMW!$NF$2:$NF$60=I$1),0),$F84-1966)} -> 110982.4 | J84: {=INDEX(GMW!$A$2:$NF$60,MATCH(1,(GMW!$NE$2:$NE$60=J$3)*(GMW!$ND$2:$ND$60=J$4)*(GMW!$NF$2:$NF$60=J$1),0),$F84-1966)} -> 620.27 | K84: {=INDEX(GMW!$A$2:$NF$60,MATCH(1,(GMW!$NE$2:$NE$60=K$3)*(GMW!$ND$2:$ND$60=K$4)*(GMW!$NF$2:$NF$60=K$1),0),$F84-1966)} -> 402.721 | L84: {=INDEX(GMW!$A$2:$NF$60,MATCH(1,(GMW!$NE$2:$NE$60=L$3)*(GMW!$ND$2:$ND$60=L$4)*(GMW!$NF$2:$NF$60=L$1),0),$F84-1966)} -> 382.879 | M84: {=INDEX(GMW!$A$2:$NF$60,MATCH(1,(GMW!$NE$2:$NE$60=M$3)*(GMW!$ND$2:$ND$60=M$4)*(GMW!$NF$2:$NF$60=M$1),0),$F84-1966)} -> 285281.8 | N84: {=INDEX(GMW!$A$2:$NF$60,MATCH(1,(GMW!$NE$2:$NE$60=N$3)*(GMW!$ND$2:$ND$60=N$4)*(GMW!$NF$2:$NF$60=N$1),0),$F84-1966)} -> -13625 | ... AH84: {=INDEX(GMW!$A$2:$NF$60,MATCH(1,(GMW!$NE$2:$NE$60=AH$3)*(GMW!$ND$2:$ND$60=AH$4)*(GMW!$NF$2:$NF$60=AH$1),0),$F84-1966)} -> 178686
B85: =+B81+1 -> 1992 | C85: =+C81+1 -> 1992 | F85: =+F84+1 -> 2051 | G85: {=INDEX(GMW!$A$2:$NF$60,MATCH(1,(GMW!$NE$2:$NE$60=G$3)*(GMW!$ND$2:$ND$60=G$4)*(GMW!$NF$2:$NF$60=G$1),0),$F85-1966)} -> 346628 | H85: {=INDEX(GMW!$A$2:$NF$60,MATCH(1,(GMW!$NE$2:$NE$60=H$3)*(GMW!$ND$2:$ND$60=H$4)*(GMW!$NF$2:$NF$60=H$1),0),$F85-1966)} -> 2612.425 | I85: {=INDEX(GMW!$A$2:$NF$60,MATCH(1,(GMW!$NE$2:$NE$60=I$3)*(GMW!$ND$2:$ND$60=I$4)*(GMW!$NF$2:$NF$60=I$1),0),$F85-1966)} -> 111402.7 | J85: {=INDEX(GMW!$A$2:$NF$60,MATCH(1,(GMW!$NE$2:$NE$60=J$3)*(GMW!$ND$2:$ND$60=J$4)*(GMW!$NF$2:$NF$60=J$1),0),$F85-1966)} -> 618.8 | K85: {=INDEX(GMW!$A$2:$NF$60,MATCH(1,(GMW!$NE$2:$NE$60=K$3)*(GMW!$ND$2:$ND$60=K$4)*(GMW!$NF$2:$NF$60=K$1),0),$F85-1966)} -> 402.258 | L85: {=INDEX(GMW!$A$2:$NF$60,MATCH(1,(GMW!$NE$2:$NE$60=L$3)*(GMW!$ND$2:$ND$60=L$4)*(GMW!$NF$2:$NF$60=L$1),0),$F85-1966)} -> 382.028 | M85: {=INDEX(GMW!$A$2:$NF$60,MATCH(1,(GMW!$NE$2:$NE$60=M$3)*(GMW!$ND$2:$ND$60=M$4)*(GMW!$NF$2:$NF$60=M$1),0),$F85-1966)} -> 286827 | N85: {=INDEX(GMW!$A$2:$NF$60,MATCH(1,(GMW!$NE$2:$NE$60=N$3)*(GMW!$ND$2:$ND$60=N$4)*(GMW!$NF$2:$NF$60=N$1),0),$F85-1966)} -> -10937 | ... AH85: {=INDEX(GMW!$A$2:$NF$60,MATCH(1,(GMW!$NE$2:$NE$60=AH$3)*(GMW!$ND$2:$ND$60=AH$4)*(GMW!$NF$2:$NF$60=AH$1),0),$F85-1966)} -> 180415
B86: =+B82+1 -> 1992 | C86: =+C82+1 -> 1992 | E86: =+E82+1 -> 1992 | F86: =+F85+1 -> 2052 | G86: {=INDEX(GMW!$A$2:$NF$60,MATCH(1,(GMW!$NE$2:$NE$60=G$3)*(GMW!$ND$2:$ND$60=G$4)*(GMW!$NF$2:$NF$60=G$1),0),$F86-1966)} -> 349299 | H86: {=INDEX(GMW!$A$2:$NF$60,MATCH(1,(GMW!$NE$2:$NE$60=H$3)*(GMW!$ND$2:$ND$60=H$4)*(GMW!$NF$2:$NF$60=H$1),0),$F86-1966)} -> 2639.65 | I86: {=INDEX(GMW!$A$2:$NF$60,MATCH(1,(GMW!$NE$2:$NE$60=I$3)*(GMW!$ND$2:$ND$60=I$4)*(GMW!$NF$2:$NF$60=I$1),0),$F86-1966)} -> 110721.5 | J86: {=INDEX(GMW!$A$2:$NF$60,MATCH(1,(GMW!$NE$2:$NE$60=J$3)*(GMW!$ND$2:$ND$60=J$4)*(GMW!$NF$2:$NF$60=J$1),0),$F86-1966)} -> 617.08 | K86: {=INDEX(GMW!$A$2:$NF$60,MATCH(1,(GMW!$NE$2:$NE$60=K$3)*(GMW!$ND$2:$ND$60=K$4)*(GMW!$NF$2:$NF$60=K$1),0),$F86-1966)} -> 402.334 | L86: {=INDEX(GMW!$A$2:$NF$60,MATCH(1,(GMW!$NE$2:$NE$60=L$3)*(GMW!$ND$2:$ND$60=L$4)*(GMW!$NF$2:$NF$60=L$1),0),$F86-1966)} -> 379.396 | M86: {=INDEX(GMW!$A$2:$NF$60,MATCH(1,(GMW!$NE$2:$NE$60=M$3)*(GMW!$ND$2:$ND$60=M$4)*(GMW!$NF$2:$NF$60=M$1),0),$F86-1966)} -> 288461.3 | N86: {=INDEX(GMW!$A$2:$NF$60,MATCH(1,(GMW!$NE$2:$NE$60=N$3)*(GMW!$ND$2:$ND$60=N$4)*(GMW!$NF$2:$NF$60=N$1),0),$F86-1966)} -> -9142 | ... AH86: {=INDEX(GMW!$A$2:$NF$60,MATCH(1,(GMW!$NE$2:$NE$60=AH$3)*(GMW!$ND$2:$ND$60=AH$4)*(GMW!$NF$2:$NF$60=AH$1),0),$F86-1966)} -> 181833
A87: 1993 | B87: =+B83+1 -> 1993 | C87: =+C83+1 -> 1992 | D87: =+D83+1 -> 1992 | F87: =+F86+1 -> 2053 | G87: {=INDEX(GMW!$A$2:$NF$60,MATCH(1,(GMW!$NE$2:$NE$60=G$3)*(GMW!$ND$2:$ND$60=G$4)*(GMW!$NF$2:$NF$60=G$1),0),$F87-1966)} -> 351046 | H87: {=INDEX(GMW!$A$2:$NF$60,MATCH(1,(GMW!$NE$2:$NE$60=H$3)*(GMW!$ND$2:$ND$60=H$4)*(GMW!$NF$2:$NF$60=H$1),0),$F87-1966)} -> 2644.075 | I87: {=INDEX(GMW!$A$2:$NF$60,MATCH(1,(GMW!$NE$2:$NE$60=I$3)*(GMW!$ND$2:$ND$60=I$4)*(GMW!$NF$2:$NF$60=I$1),0),$F87-1966)} -> 111282 | J87: {=INDEX(GMW!$A$2:$NF$60,MATCH(1,(GMW!$NE$2:$NE$60=J$3)*(GMW!$ND$2:$ND$60=J$4)*(GMW!$NF$2:$NF$60=J$1),0),$F87-1966)} -> 612.18 | K87: {=INDEX(GMW!$A$2:$NF$60,MATCH(1,(GMW!$NE$2:$NE$60=K$3)*(GMW!$ND$2:$ND$60=K$4)*(GMW!$NF$2:$NF$60=K$1),0),$F87-1966)} -> 400.161 | L87: {=INDEX(GMW!$A$2:$NF$60,MATCH(1,(GMW!$NE$2:$NE$60=L$3)*(GMW!$ND$2:$ND$60=L$4)*(GMW!$NF$2:$NF$60=L$1),0),$F87-1966)} -> 378.865 | M87: {=INDEX(GMW!$A$2:$NF$60,MATCH(1,(GMW!$NE$2:$NE$60=M$3)*(GMW!$ND$2:$ND$60=M$4)*(GMW!$NF$2:$NF$60=M$1),0),$F87-1966)} -> 290292.8 | N87: {=INDEX(GMW!$A$2:$NF$60,MATCH(1,(GMW!$NE$2:$NE$60=N$3)*(GMW!$ND$2:$ND$60=N$4)*(GMW!$NF$2:$NF$60=N$1),0),$F87-1966)} -> -12848 | ... AH87: {=INDEX(GMW!$A$2:$NF$60,MATCH(1,(GMW!$NE$2:$NE$60=AH$3)*(GMW!$ND$2:$ND$60=AH$4)*(GMW!$NF$2:$NF$60=AH$1),0),$F87-1966)} -> 183488
B88: =+B84+1 -> 1993 | C88: =+C84+1 -> 1993 | F88: =+F87+1 -> 2054 | G88: {=INDEX(GMW!$A$2:$NF$60,MATCH(1,(GMW!$NE$2:$NE$60=G$3)*(GMW!$ND$2:$ND$60=G$4)*(GMW!$NF$2:$NF$60=G$1),0),$F88-1966)} -> 352612 | H88: {=INDEX(GMW!$A$2:$NF$60,MATCH(1,(GMW!$NE$2:$NE$60=H$3)*(GMW!$ND$2:$ND$60=H$4)*(GMW!$NF$2:$NF$60=H$1),0),$F88-1966)} -> 2659.45 | I88: {=INDEX(GMW!$A$2:$NF$60,MATCH(1,(GMW!$NE$2:$NE$60=I$3)*(GMW!$ND$2:$ND$60=I$4)*(GMW!$NF$2:$NF$60=I$1),0),$F88-1966)} -> 110343.9 | J88: {=INDEX(GMW!$A$2:$NF$60,MATCH(1,(GMW!$NE$2:$NE$60=J$3)*(GMW!$ND$2:$ND$60=J$4)*(GMW!$NF$2:$NF$60=J$1),0),$F88-1966)} -> 612.27 | K88: {=INDEX(GMW!$A$2:$NF$60,MATCH(1,(GMW!$NE$2:$NE$60=K$3)*(GMW!$ND$2:$ND$60=K$4)*(GMW!$NF$2:$NF$60=K$1),0),$F88-1966)} -> 400.18 | L88: {=INDEX(GMW!$A$2:$NF$60,MATCH(1,(GMW!$NE$2:$NE$60=L$3)*(GMW!$ND$2:$ND$60=L$4)*(GMW!$NF$2:$NF$60=L$1),0),$F88-1966)} -> 377.952 | M88: {=INDEX(GMW!$A$2:$NF$60,MATCH(1,(GMW!$NE$2:$NE$60=M$3)*(GMW!$ND$2:$ND$60=M$4)*(GMW!$NF$2:$NF$60=M$1),0),$F88-1966)} -> 292937 | N88: {=INDEX(GMW!$A$2:$NF$60,MATCH(1,(GMW!$NE$2:$NE$60=N$3)*(GMW!$ND$2:$ND$60=N$4)*(GMW!$NF$2:$NF$60=N$1),0),$F88-1966)} -> -15714 | ... AH88: {=INDEX(GMW!$A$2:$NF$60,MATCH(1,(GMW!$NE$2:$NE$60=AH$3)*(GMW!$ND$2:$ND$60=AH$4)*(GMW!$NF$2:$NF$60=AH$1),0),$F88-1966)} -> 186340
B89: =+B85+1 -> 1993 | C89: =+C85+1 -> 1993 | F89: =+F88+1 -> 2055 | G89: {=INDEX(GMW!$A$2:$NF$60,MATCH(1,(GMW!$NE$2:$NE$60=G$3)*(GMW!$ND$2:$ND$60=G$4)*(GMW!$NF$2:$NF$60=G$1),0),$F89-1966)} -> 355841 | H89: {=INDEX(GMW!$A$2:$NF$60,MATCH(1,(GMW!$NE$2:$NE$60=H$3)*(GMW!$ND$2:$ND$60=H$4)*(GMW!$NF$2:$NF$60=H$1),0),$F89-1966)} -> 2672.15 | I89: {=INDEX(GMW!$A$2:$NF$60,MATCH(1,(GMW!$NE$2:$NE$60=I$3)*(GMW!$ND$2:$ND$60=I$4)*(GMW!$NF$2:$NF$60=I$1),0),$F89-1966)} -> 109839 | J89: {=INDEX(GMW!$A$2:$NF$60,MATCH(1,(GMW!$NE$2:$NE$60=J$3)*(GMW!$ND$2:$ND$60=J$4)*(GMW!$NF$2:$NF$60=J$1),0),$F89-1966)} -> 615.89 | K89: {=INDEX(GMW!$A$2:$NF$60,MATCH(1,(GMW!$NE$2:$NE$60=K$3)*(GMW!$ND$2:$ND$60=K$4)*(GMW!$NF$2:$NF$60=K$1),0),$F89-1966)} -> 400.67 | L89: {=INDEX(GMW!$A$2:$NF$60,MATCH(1,(GMW!$NE$2:$NE$60=L$3)*(GMW!$ND$2:$ND$60=L$4)*(GMW!$NF$2:$NF$60=L$1),0),$F89-1966)} -> 377.356 | M89: {=INDEX(GMW!$A$2:$NF$60,MATCH(1,(GMW!$NE$2:$NE$60=M$3)*(GMW!$ND$2:$ND$60=M$4)*(GMW!$NF$2:$NF$60=M$1),0),$F89-1966)} -> 295738.5 | N89: {=INDEX(GMW!$A$2:$NF$60,MATCH(1,(GMW!$NE$2:$NE$60=N$3)*(GMW!$ND$2:$ND$60=N$4)*(GMW!$NF$2:$NF$60=N$1),0),$F89-1966)} -> -12329 | ... AH89: {=INDEX(GMW!$A$2:$NF$60,MATCH(1,(GMW!$NE$2:$NE$60=AH$3)*(GMW!$ND$2:$ND$60=AH$4)*(GMW!$NF$2:$NF$60=AH$1),0),$F89-1966)} -> 187517
B90: =+B86+1 -> 1993 | C90: =+C86+1 -> 1993 | E90: =+E86+1 -> 1993 | F90: =+F89+1 -> 2056 | G90: {=INDEX(GMW!$A$2:$NF$60,MATCH(1,(GMW!$NE$2:$NE$60=G$3)*(GMW!$ND$2:$ND$60=G$4)*(GMW!$NF$2:$NF$60=G$1),0),$F90-1966)} -> 358264 | H90: {=INDEX(GMW!$A$2:$NF$60,MATCH(1,(GMW!$NE$2:$NE$60=H$3)*(GMW!$ND$2:$ND$60=H$4)*(GMW!$NF$2:$NF$60=H$1),0),$F90-1966)} -> 2708.5 | I90: {=INDEX(GMW!$A$2:$NF$60,MATCH(1,(GMW!$NE$2:$NE$60=I$3)*(GMW!$ND$2:$ND$60=I$4)*(GMW!$NF$2:$NF$60=I$1),0),$F90-1966)} -> 110263.7 | J90: {=INDEX(GMW!$A$2:$NF$60,MATCH(1,(GMW!$NE$2:$NE$60=J$3)*(GMW!$ND$2:$ND$60=J$4)*(GMW!$NF$2:$NF$60=J$1),0),$F90-1966)} -> 615.37 | K90: {=INDEX(GMW!$A$2:$NF$60,MATCH(1,(GMW!$NE$2:$NE$60=K$3)*(GMW!$ND$2:$ND$60=K$4)*(GMW!$NF$2:$NF$60=K$1),0),$F90-1966)} -> 401.724 | L90: {=INDEX(GMW!$A$2:$NF$60,MATCH(1,(GMW!$NE$2:$NE$60=L$3)*(GMW!$ND$2:$ND$60=L$4)*(GMW!$NF$2:$NF$60=L$1),0),$F90-1966)} -> 380.122 | M90: {=INDEX(GMW!$A$2:$NF$60,MATCH(1,(GMW!$NE$2:$NE$60=M$3)*(GMW!$ND$2:$ND$60=M$4)*(GMW!$NF$2:$NF$60=M$1),0),$F90-1966)} -> 297003.5 | N90: {=INDEX(GMW!$A$2:$NF$60,MATCH(1,(GMW!$NE$2:$NE$60=N$3)*(GMW!$ND$2:$ND$60=N$4)*(GMW!$NF$2:$NF$60=N$1),0),$F90-1966)} -> -10500 | ... AH90: {=INDEX(GMW!$A$2:$NF$60,MATCH(1,(GMW!$NE$2:$NE$60=AH$3)*(GMW!$ND$2:$ND$60=AH$4)*(GMW!$NF$2:$NF$60=AH$1),0),$F90-1966)} -> 189692
A91: 1994 | B91: =+B87+1 -> 1994 | C91: =+C87+1 -> 1993 | D91: =+D87+1 -> 1993 | F91: =+F90+1 -> 2057 | G91: {=INDEX(GMW!$A$2:$NF$60,MATCH(1,(GMW!$NE$2:$NE$60=G$3)*(GMW!$ND$2:$ND$60=G$4)*(GMW!$NF$2:$NF$60=G$1),0),$F91-1966)} -> 361793 | H91: {=INDEX(GMW!$A$2:$NF$60,MATCH(1,(GMW!$NE$2:$NE$60=H$3)*(GMW!$ND$2:$ND$60=H$4)*(GMW!$NF$2:$NF$60=H$1),0),$F91-1966)} -> 2734.775 | I91: {=INDEX(GMW!$A$2:$NF$60,MATCH(1,(GMW!$NE$2:$NE$60=I$3)*(GMW!$ND$2:$ND$60=I$4)*(GMW!$NF$2:$NF$60=I$1),0),$F91-1966)} -> 111555.8 | J91: {=INDEX(GMW!$A$2:$NF$60,MATCH(1,(GMW!$NE$2:$NE$60=J$3)*(GMW!$ND$2:$ND$60=J$4)*(GMW!$NF$2:$NF$60=J$1),0),$F91-1966)} -> 624.06 | K91: {=INDEX(GMW!$A$2:$NF$60,MATCH(1,(GMW!$NE$2:$NE$60=K$3)*(GMW!$ND$2:$ND$60=K$4)*(GMW!$NF$2:$NF$60=K$1),0),$F91-1966)} -> 404.451 | L91: {=INDEX(GMW!$A$2:$NF$60,MATCH(1,(GMW!$NE$2:$NE$60=L$3)*(GMW!$ND$2:$ND$60=L$4)*(GMW!$NF$2:$NF$60=L$1),0),$F91-1966)} -> 383.018 | M91: {=INDEX(GMW!$A$2:$NF$60,MATCH(1,(GMW!$NE$2:$NE$60=M$3)*(GMW!$ND$2:$ND$60=M$4)*(GMW!$NF$2:$NF$60=M$1),0),$F91-1966)} -> 301382.8 | N91: {=INDEX(GMW!$A$2:$NF$60,MATCH(1,(GMW!$NE$2:$NE$60=N$3)*(GMW!$ND$2:$ND$60=N$4)*(GMW!$NF$2:$NF$60=N$1),0),$F91-1966)} -> -13013 | ... AH91: {=INDEX(GMW!$A$2:$NF$60,MATCH(1,(GMW!$NE$2:$NE$60=AH$3)*(GMW!$ND$2:$ND$60=AH$4)*(GMW!$NF$2:$NF$60=AH$1),0),$F91-1966)} -> 193164
B92: =+B88+1 -> 1994 | C92: =+C88+1 -> 1994 | F92: =+F91+1 -> 2058 | G92: {=INDEX(GMW!$A$2:$NF$60,MATCH(1,(GMW!$NE$2:$NE$60=G$3)*(GMW!$ND$2:$ND$60=G$4)*(GMW!$NF$2:$NF$60=G$1),0),$F92-1966)} -> 365109 | H92: {=INDEX(GMW!$A$2:$NF$60,MATCH(1,(GMW!$NE$2:$NE$60=H$3)*(GMW!$ND$2:$ND$60=H$4)*(GMW!$NF$2:$NF$60=H$1),0),$F92-1966)} -> 2771.85 | I92: {=INDEX(GMW!$A$2:$NF$60,MATCH(1,(GMW!$NE$2:$NE$60=I$3)*(GMW!$ND$2:$ND$60=I$4)*(GMW!$NF$2:$NF$60=I$1),0),$F92-1966)} -> 110953.6 | J92: {=INDEX(GMW!$A$2:$NF$60,MATCH(1,(GMW!$NE$2:$NE$60=J$3)*(GMW!$ND$2:$ND$60=J$4)*(GMW!$NF$2:$NF$60=J$1),0),$F92-1966)} -> 627.51 | K92: {=INDEX(GMW!$A$2:$NF$60,MATCH(1,(GMW!$NE$2:$NE$60=K$3)*(GMW!$ND$2:$ND$60=K$4)*(GMW!$NF$2:$NF$60=K$1),0),$F92-1966)} -> 408.509 | L92: {=INDEX(GMW!$A$2:$NF$60,MATCH(1,(GMW!$NE$2:$NE$60=L$3)*(GMW!$ND$2:$ND$60=L$4)*(GMW!$NF$2:$NF$60=L$1),0),$F92-1966)} -> 385.79 | M92: {=INDEX(GMW!$A$2:$NF$60,MATCH(1,(GMW!$NE$2:$NE$60=M$3)*(GMW!$ND$2:$ND$60=M$4)*(GMW!$NF$2:$NF$60=M$1),0),$F92-1966)} -> 305782.5 | N92: {=INDEX(GMW!$A$2:$NF$60,MATCH(1,(GMW!$NE$2:$NE$60=N$3)*(GMW!$ND$2:$ND$60=N$4)*(GMW!$NF$2:$NF$60=N$1),0),$F92-1966)} -> -14620 | ... AH92: {=INDEX(GMW!$A$2:$NF$60,MATCH(1,(GMW!$NE$2:$NE$60=AH$3)*(GMW!$ND$2:$ND$60=AH$4)*(GMW!$NF$2:$NF$60=AH$1),0),$F92-1966)} -> 195915
B93: =+B89+1 -> 1994 | C93: =+C89+1 -> 1994 | F93: =+F92+1 -> 2059 | G93: {=INDEX(GMW!$A$2:$NF$60,MATCH(1,(GMW!$NE$2:$NE$60=G$3)*(GMW!$ND$2:$ND$60=G$4)*(GMW!$NF$2:$NF$60=G$1),0),$F93-1966)} -> 368798 | H93: {=INDEX(GMW!$A$2:$NF$60,MATCH(1,(GMW!$NE$2:$NE$60=H$3)*(GMW!$ND$2:$ND$60=H$4)*(GMW!$NF$2:$NF$60=H$1),0),$F93-1966)} -> 2788.05 | I93: {=INDEX(GMW!$A$2:$NF$60,MATCH(1,(GMW!$NE$2:$NE$60=I$3)*(GMW!$ND$2:$ND$60=I$4)*(GMW!$NF$2:$NF$60=I$1),0),$F93-1966)} -> 112226.3 | J93: {=INDEX(GMW!$A$2:$NF$60,MATCH(1,(GMW!$NE$2:$NE$60=J$3)*(GMW!$ND$2:$ND$60=J$4)*(GMW!$NF$2:$NF$60=J$1),0),$F93-1966)} -> 631.22 | K93: {=INDEX(GMW!$A$2:$NF$60,MATCH(1,(GMW!$NE$2:$NE$60=K$3)*(GMW!$ND$2:$ND$60=K$4)*(GMW!$NF$2:$NF$60=K$1),0),$F93-1966)} -> 412.199 | L93: {=INDEX(GMW!$A$2:$NF$60,MATCH(1,(GMW!$NE$2:$NE$60=L$3)*(GMW!$ND$2:$ND$60=L$4)*(GMW!$NF$2:$NF$60=L$1),0),$F93-1966)} -> 388.197 | M93: {=INDEX(GMW!$A$2:$NF$60,MATCH(1,(GMW!$NE$2:$NE$60=M$3)*(GMW!$ND$2:$ND$60=M$4)*(GMW!$NF$2:$NF$60=M$1),0),$F93-1966)} -> 309702.8 | N93: {=INDEX(GMW!$A$2:$NF$60,MATCH(1,(GMW!$NE$2:$NE$60=N$3)*(GMW!$ND$2:$ND$60=N$4)*(GMW!$NF$2:$NF$60=N$1),0),$F93-1966)} -> -10958 | ... AH93: {=INDEX(GMW!$A$2:$NF$60,MATCH(1,(GMW!$NE$2:$NE$60=AH$3)*(GMW!$ND$2:$ND$60=AH$4)*(GMW!$NF$2:$NF$60=AH$1),0),$F93-1966)} -> 200196
B94: =+B90+1 -> 1994 | C94: =+C90+1 -> 1994 | E94: =+E90+1 -> 1994 | F94: =+F93+1 -> 2060 | G94: {=INDEX(GMW!$A$2:$NF$60,MATCH(1,(GMW!$NE$2:$NE$60=G$3)*(GMW!$ND$2:$ND$60=G$4)*(GMW!$NF$2:$NF$60=G$1),0),$F94-1966)} -> 370401 | H94: {=INDEX(GMW!$A$2:$NF$60,MATCH(1,(GMW!$NE$2:$NE$60=H$3)*(GMW!$ND$2:$ND$60=H$4)*(GMW!$NF$2:$NF$60=H$1),0),$F94-1966)} -> 2819.975 | I94: {=INDEX(GMW!$A$2:$NF$60,MATCH(1,(GMW!$NE$2:$NE$60=I$3)*(GMW!$ND$2:$ND$60=I$4)*(GMW!$NF$2:$NF$60=I$1),0),$F94-1966)} -> 111797.5 | J94: {=INDEX(GMW!$A$2:$NF$60,MATCH(1,(GMW!$NE$2:$NE$60=J$3)*(GMW!$ND$2:$ND$60=J$4)*(GMW!$NF$2:$NF$60=J$1),0),$F94-1966)} -> 638.21 | K94: {=INDEX(GMW!$A$2:$NF$60,MATCH(1,(GMW!$NE$2:$NE$60=K$3)*(GMW!$ND$2:$ND$60=K$4)*(GMW!$NF$2:$NF$60=K$1),0),$F94-1966)} -> 416.085 | L94: {=INDEX(GMW!$A$2:$NF$60,MATCH(1,(GMW!$NE$2:$NE$60=L$3)*(GMW!$ND$2:$ND$60=L$4)*(GMW!$NF$2:$NF$60=L$1),0),$F94-1966)} -> 391.841 | M94: {=INDEX(GMW!$A$2:$NF$60,MATCH(1,(GMW!$NE$2:$NE$60=M$3)*(GMW!$ND$2:$ND$60=M$4)*(GMW!$NF$2:$NF$60=M$1),0),$F94-1966)} -> 311952.5 | N94: {=INDEX(GMW!$A$2:$NF$60,MATCH(1,(GMW!$NE$2:$NE$60=N$3)*(GMW!$ND$2:$ND$60=N$4)*(GMW!$NF$2:$NF$60=N$1),0),$F94-1966)} -> -7891 | ... AH94: {=INDEX(GMW!$A$2:$NF$60,MATCH(1,(GMW!$NE$2:$NE$60=AH$3)*(GMW!$ND$2:$ND$60=AH$4)*(GMW!$NF$2:$NF$60=AH$1),0),$F94-1966)} -> 202697
A95: 1995 | B95: =+B91+1 -> 1995 | C95: =+C91+1 -> 1994 | D95: =+D91+1 -> 1994 | F95: =+F94+1 -> 2061 | G95: {=INDEX(GMW!$A$2:$NF$60,MATCH(1,(GMW!$NE$2:$NE$60=G$3)*(GMW!$ND$2:$ND$60=G$4)*(GMW!$NF$2:$NF$60=G$1),0),$F95-1966)} -> 372307 | H95: {=INDEX(GMW!$A$2:$NF$60,MATCH(1,(GMW!$NE$2:$NE$60=H$3)*(GMW!$ND$2:$ND$60=H$4)*(GMW!$NF$2:$NF$60=H$1),0),$F95-1966)} -> 2830 | I95: {=INDEX(GMW!$A$2:$NF$60,MATCH(1,(GMW!$NE$2:$NE$60=I$3)*(GMW!$ND$2:$ND$60=I$4)*(GMW!$NF$2:$NF$60=I$1),0),$F95-1966)} -> 113005 | J95: {=INDEX(GMW!$A$2:$NF$60,MATCH(1,(GMW!$NE$2:$NE$60=J$3)*(GMW!$ND$2:$ND$60=J$4)*(GMW!$NF$2:$NF$60=J$1),0),$F95-1966)} -> 635.69 | K95: {=INDEX(GMW!$A$2:$NF$60,MATCH(1,(GMW!$NE$2:$NE$60=K$3)*(GMW!$ND$2:$ND$60=K$4)*(GMW!$NF$2:$NF$60=K$1),0),$F95-1966)} -> 418.051 | L95: {=INDEX(GMW!$A$2:$NF$60,MATCH(1,(GMW!$NE$2:$NE$60=L$3)*(GMW!$ND$2:$ND$60=L$4)*(GMW!$NF$2:$NF$60=L$1),0),$F95-1966)} -> 396.76 | M95: {=INDEX(GMW!$A$2:$NF$60,MATCH(1,(GMW!$NE$2:$NE$60=M$3)*(GMW!$ND$2:$ND$60=M$4)*(GMW!$NF$2:$NF$60=M$1),0),$F95-1966)} -> 314818.8 | N95: {=INDEX(GMW!$A$2:$NF$60,MATCH(1,(GMW!$NE$2:$NE$60=N$3)*(GMW!$ND$2:$ND$60=N$4)*(GMW!$NF$2:$NF$60=N$1),0),$F95-1966)} -> -10335 | ... AH95: {=INDEX(GMW!$A$2:$NF$60,MATCH(1,(GMW!$NE$2:$NE$60=AH$3)*(GMW!$ND$2:$ND$60=AH$4)*(GMW!$NF$2:$NF$60=AH$1),0),$F95-1966)} -> 205993
B96: =+B92+1 -> 1995 | C96: =+C92+1 -> 1995 | F96: =+F95+1 -> 2062 | G96: {=INDEX(GMW!$A$2:$NF$60,MATCH(1,(GMW!$NE$2:$NE$60=G$3)*(GMW!$ND$2:$ND$60=G$4)*(GMW!$NF$2:$NF$60=G$1),0),$F96-1966)} -> 373090 | H96: {=INDEX(GMW!$A$2:$NF$60,MATCH(1,(GMW!$NE$2:$NE$60=H$3)*(GMW!$ND$2:$ND$60=H$4)*(GMW!$NF$2:$NF$60=H$1),0),$F96-1966)} -> 2838.425 | I96: {=INDEX(GMW!$A$2:$NF$60,MATCH(1,(GMW!$NE$2:$NE$60=I$3)*(GMW!$ND$2:$ND$60=I$4)*(GMW!$NF$2:$NF$60=I$1),0),$F96-1966)} -> 114086.1 | J96: {=INDEX(GMW!$A$2:$NF$60,MATCH(1,(GMW!$NE$2:$NE$60=J$3)*(GMW!$ND$2:$ND$60=J$4)*(GMW!$NF$2:$NF$60=J$1),0),$F96-1966)} -> 640.78 | K96: {=INDEX(GMW!$A$2:$NF$60,MATCH(1,(GMW!$NE$2:$NE$60=K$3)*(GMW!$ND$2:$ND$60=K$4)*(GMW!$NF$2:$NF$60=K$1),0),$F96-1966)} -> 420.792 | L96: {=INDEX(GMW!$A$2:$NF$60,MATCH(1,(GMW!$NE$2:$NE$60=L$3)*(GMW!$ND$2:$ND$60=L$4)*(GMW!$NF$2:$NF$60=L$1),0),$F96-1966)} -> 397.038 | M96: {=INDEX(GMW!$A$2:$NF$60,MATCH(1,(GMW!$NE$2:$NE$60=M$3)*(GMW!$ND$2:$ND$60=M$4)*(GMW!$NF$2:$NF$60=M$1),0),$F96-1966)} -> 314952.5 | N96: {=INDEX(GMW!$A$2:$NF$60,MATCH(1,(GMW!$NE$2:$NE$60=N$3)*(GMW!$ND$2:$ND$60=N$4)*(GMW!$NF$2:$NF$60=N$1),0),$F96-1966)} -> -12054 | ... AH96: {=INDEX(GMW!$A$2:$NF$60,MATCH(1,(GMW!$NE$2:$NE$60=AH$3)*(GMW!$ND$2:$ND$60=AH$4)*(GMW!$NF$2:$NF$60=AH$1),0),$F96-1966)} -> 207214
B97: =+B93+1 -> 1995 | C97: =+C93+1 -> 1995 | F97: =+F96+1 -> 2063 | G97: {=INDEX(GMW!$A$2:$NF$60,MATCH(1,(GMW!$NE$2:$NE$60=G$3)*(GMW!$ND$2:$ND$60=G$4)*(GMW!$NF$2:$NF$60=G$1),0),$F97-1966)} -> 377249 | H97: {=INDEX(GMW!$A$2:$NF$60,MATCH(1,(GMW!$NE$2:$NE$60=H$3)*(GMW!$ND$2:$ND$60=H$4)*(GMW!$NF$2:$NF$60=H$1),0),$F97-1966)} -> 2862.575 | I97: {=INDEX(GMW!$A$2:$NF$60,MATCH(1,(GMW!$NE$2:$NE$60=I$3)*(GMW!$ND$2:$ND$60=I$4)*(GMW!$NF$2:$NF$60=I$1),0),$F97-1966)} -> 115422 | J97: {=INDEX(GMW!$A$2:$NF$60,MATCH(1,(GMW!$NE$2:$NE$60=J$3)*(GMW!$ND$2:$ND$60=J$4)*(GMW!$NF$2:$NF$60=J$1),0),$F97-1966)} -> 642.07 | K97: {=INDEX(GMW!$A$2:$NF$60,MATCH(1,(GMW!$NE$2:$NE$60=K$3)*(GMW!$ND$2:$ND$60=K$4)*(GMW!$NF$2:$NF$60=K$1),0),$F97-1966)} -> 421.449 | L97: {=INDEX(GMW!$A$2:$NF$60,MATCH(1,(GMW!$NE$2:$NE$60=L$3)*(GMW!$ND$2:$ND$60=L$4)*(GMW!$NF$2:$NF$60=L$1),0),$F97-1966)} -> 398.804 | M97: {=INDEX(GMW!$A$2:$NF$60,MATCH(1,(GMW!$NE$2:$NE$60=M$3)*(GMW!$ND$2:$ND$60=M$4)*(GMW!$NF$2:$NF$60=M$1),0),$F97-1966)} -> 315368.8 | N97: {=INDEX(GMW!$A$2:$NF$60,MATCH(1,(GMW!$NE$2:$NE$60=N$3)*(GMW!$ND$2:$ND$60=N$4)*(GMW!$NF$2:$NF$60=N$1),0),$F97-1966)} -> -10371 | ... AH97: {=INDEX(GMW!$A$2:$NF$60,MATCH(1,(GMW!$NE$2:$NE$60=AH$3)*(GMW!$ND$2:$ND$60=AH$4)*(GMW!$NF$2:$NF$60=AH$1),0),$F97-1966)} -> 208244
B98: =+B94+1 -> 1995 | C98: =+C94+1 -> 1995 | E98: =+E94+1 -> 1995 | F98: =+F97+1 -> 2064 | G98: {=INDEX(GMW!$A$2:$NF$60,MATCH(1,(GMW!$NE$2:$NE$60=G$3)*(GMW!$ND$2:$ND$60=G$4)*(GMW!$NF$2:$NF$60=G$1),0),$F98-1966)} -> 378442 | H98: {=INDEX(GMW!$A$2:$NF$60,MATCH(1,(GMW!$NE$2:$NE$60=H$3)*(GMW!$ND$2:$ND$60=H$4)*(GMW!$NF$2:$NF$60=H$1),0),$F98-1966)} -> 2882.025 | I98: {=INDEX(GMW!$A$2:$NF$60,MATCH(1,(GMW!$NE$2:$NE$60=I$3)*(GMW!$ND$2:$ND$60=I$4)*(GMW!$NF$2:$NF$60=I$1),0),$F98-1966)} -> 115718.8 | J98: {=INDEX(GMW!$A$2:$NF$60,MATCH(1,(GMW!$NE$2:$NE$60=J$3)*(GMW!$ND$2:$ND$60=J$4)*(GMW!$NF$2:$NF$60=J$1),0),$F98-1966)} -> 642.33 | K98: {=INDEX(GMW!$A$2:$NF$60,MATCH(1,(GMW!$NE$2:$NE$60=K$3)*(GMW!$ND$2:$ND$60=K$4)*(GMW!$NF$2:$NF$60=K$1),0),$F98-1966)} -> 421.283 | L98: {=INDEX(GMW!$A$2:$NF$60,MATCH(1,(GMW!$NE$2:$NE$60=L$3)*(GMW!$ND$2:$ND$60=L$4)*(GMW!$NF$2:$NF$60=L$1),0),$F98-1966)} -> 402.107 | M98: {=INDEX(GMW!$A$2:$NF$60,MATCH(1,(GMW!$NE$2:$NE$60=M$3)*(GMW!$ND$2:$ND$60=M$4)*(GMW!$NF$2:$NF$60=M$1),0),$F98-1966)} -> 316641.5 | N98: {=INDEX(GMW!$A$2:$NF$60,MATCH(1,(GMW!$NE$2:$NE$60=N$3)*(GMW!$ND$2:$ND$60=N$4)*(GMW!$NF$2:$NF$60=N$1),0),$F98-1966)} -> -6400 | ... AH98: {=INDEX(GMW!$A$2:$NF$60,MATCH(1,(GMW!$NE$2:$NE$60=AH$3)*(GMW!$ND$2:$ND$60=AH$4)*(GMW!$NF$2:$NF$60=AH$1),0),$F98-1966)} -> 210170
A99: 1996 | B99: =+B95+1 -> 1996 | C99: =+C95+1 -> 1995 | D99: =+D95+1 -> 1995 | F99: =+F98+1 -> 2065 | G99: {=INDEX(GMW!$A$2:$NF$60,MATCH(1,(GMW!$NE$2:$NE$60=G$3)*(GMW!$ND$2:$ND$60=G$4)*(GMW!$NF$2:$NF$60=G$1),0),$F99-1966)} -> 380976 | H99: {=INDEX(GMW!$A$2:$NF$60,MATCH(1,(GMW!$NE$2:$NE$60=H$3)*(GMW!$ND$2:$ND$60=H$4)*(GMW!$NF$2:$NF$60=H$1),0),$F99-1966)} -> 2903.6 | I99: {=INDEX(GMW!$A$2:$NF$60,MATCH(1,(GMW!$NE$2:$NE$60=I$3)*(GMW!$ND$2:$ND$60=I$4)*(GMW!$NF$2:$NF$60=I$1),0),$F99-1966)} -> 116661.9 | J99: {=INDEX(GMW!$A$2:$NF$60,MATCH(1,(GMW!$NE$2:$NE$60=J$3)*(GMW!$ND$2:$ND$60=J$4)*(GMW!$NF$2:$NF$60=J$1),0),$F99-1966)} -> 637.76 | K99: {=INDEX(GMW!$A$2:$NF$60,MATCH(1,(GMW!$NE$2:$NE$60=K$3)*(GMW!$ND$2:$ND$60=K$4)*(GMW!$NF$2:$NF$60=K$1),0),$F99-1966)} -> 424.211 | L99: {=INDEX(GMW!$A$2:$NF$60,MATCH(1,(GMW!$NE$2:$NE$60=L$3)*(GMW!$ND$2:$ND$60=L$4)*(GMW!$NF$2:$NF$60=L$1),0),$F99-1966)} -> 402.945 | M99: {=INDEX(GMW!$A$2:$NF$60,MATCH(1,(GMW!$NE$2:$NE$60=M$3)*(GMW!$ND$2:$ND$60=M$4)*(GMW!$NF$2:$NF$60=M$1),0),$F99-1966)} -> 317101 | N99: {=INDEX(GMW!$A$2:$NF$60,MATCH(1,(GMW!$NE$2:$NE$60=N$3)*(GMW!$ND$2:$ND$60=N$4)*(GMW!$NF$2:$NF$60=N$1),0),$F99-1966)} -> -6485 | ... AH99: {=INDEX(GMW!$A$2:$NF$60,MATCH(1,(GMW!$NE$2:$NE$60=AH$3)*(GMW!$ND$2:$ND$60=AH$4)*(GMW!$NF$2:$NF$60=AH$1),0),$F99-1966)} -> 211052
B100: =+B96+1 -> 1996 | C100: =+C96+1 -> 1996 | F100: =+F99+1 -> 2066 | G100: {=INDEX(GMW!$A$2:$NF$60,MATCH(1,(GMW!$NE$2:$NE$60=G$3)*(GMW!$ND$2:$ND$60=G$4)*(GMW!$NF$2:$NF$60=G$1),0),$F100-1966)} -> 382146 | H100: {=INDEX(GMW!$A$2:$NF$60,MATCH(1,(GMW!$NE$2:$NE$60=H$3)*(GMW!$ND$2:$ND$60=H$4)*(GMW!$NF$2:$NF$60=H$1),0),$F100-1966)} -> 2952.025 | I100: {=INDEX(GMW!$A$2:$NF$60,MATCH(1,(GMW!$NE$2:$NE$60=I$3)*(GMW!$ND$2:$ND$60=I$4)*(GMW!$NF$2:$NF$60=I$1),0),$F100-1966)} -> 118139.6 | J100: {=INDEX(GMW!$A$2:$NF$60,MATCH(1,(GMW!$NE$2:$NE$60=J$3)*(GMW!$ND$2:$ND$60=J$4)*(GMW!$NF$2:$NF$60=J$1),0),$F100-1966)} -> 646.47 | K100: {=INDEX(GMW!$A$2:$NF$60,MATCH(1,(GMW!$NE$2:$NE$60=K$3)*(GMW!$ND$2:$ND$60=K$4)*(GMW!$NF$2:$NF$60=K$1),0),$F100-1966)} -> 425.029 | L100: {=INDEX(GMW!$A$2:$NF$60,MATCH(1,(GMW!$NE$2:$NE$60=L$3)*(GMW!$ND$2:$ND$60=L$4)*(GMW!$NF$2:$NF$60=L$1),0),$F100-1966)} -> 403.618 | M100: {=INDEX(GMW!$A$2:$NF$60,MATCH(1,(GMW!$NE$2:$NE$60=M$3)*(GMW!$ND$2:$ND$60=M$4)*(GMW!$NF$2:$NF$60=M$1),0),$F100-1966)} -> 319358.5 | N100: {=INDEX(GMW!$A$2:$NF$60,MATCH(1,(GMW!$NE$2:$NE$60=N$3)*(GMW!$ND$2:$ND$60=N$4)*(GMW!$NF$2:$NF$60=N$1),0),$F100-1966)} -> -13912 | ... AH100: {=INDEX(GMW!$A$2:$NF$60,MATCH(1,(GMW!$NE$2:$NE$60=AH$3)*(GMW!$ND$2:$ND$60=AH$4)*(GMW!$NF$2:$NF$60=AH$1),0),$F100-1966)} -> 213226
...

Sheet GMW
A1: Location | B1: Indicator | C1: Scenario | D1: Units | E1: Scale | F1: Measurement | G1: 1973 Q1 | H1: 1973 Q2 | I1: 1973 Q3 | J1: 1973 Q4 | K1: 1974 Q1 | L1: 1974 Q2 | M1: 1974 Q3 | N1: 1974 Q4 | O1: 1975 Q1 | P1: 1975 Q2 | Q1: 1975 Q3 | R1: 1975 Q4 | S1: 1976 Q1 | T1: 1976 Q2 | U1: 1976 Q3 | V1: 1976 Q4 | W1: 1977 Q1 | X1: 1977 Q2 | Y1: 1977 Q3 | Z1: 1977 Q4 | AA1: 1978 Q1 | AB1: 1978 Q2 | AC1: 1978 Q3 | AD1: 1978 Q4 | AE1: 1979 Q1 | AF1: 1979 Q2 | AG1: 1979 Q3 | AH1: 1979 Q4 | AI1: 1980 Q1 | AJ1: 1980 Q2 | AK1: 1980 Q3 | AL1: 1980 Q4 | AM1: 1981 Q1 | AN1: 1981 Q2 | AO1: 1981 Q3 | AP1: 1981 Q4 | AQ1: 1982 Q1 | AR1: 1982 Q2 | AS1: 1982 Q3 | AT1: 1982 Q4 | AU1: 1983 Q1 | AV1: 1983 Q2 | AW1: 1983 Q3 | AX1: 1983 Q4 | AY1: 1984 Q1 | AZ1: 1984 Q2 | BA1: 1984 Q3 | BB1: 1984 Q4 | BC1: 1985 Q1 | BD1: 1985 Q2 | BE1: 1985 Q3 | BF1: 1985 Q4 | BG1: 1986 Q1 | BH1: 1986 Q2 | BI1: 1986 Q3 | BJ1: 1986 Q4 | BK1: 1987 Q1 | BL1: 1987 Q2 | BM1: 1987 Q3 | BN1: 1987 Q4 | BO1: 1988 Q1 | BP1: 1988 Q2 | BQ1: 1988 Q3 | BR1: 1988 Q4 | BS1: 1989 Q1 | BT1: 1989 Q2 | BU1: 1989 Q3 | BV1: 1989 Q4 | BW1: 1990 Q1 | BX1: 1990 Q2 | BY1: 1990 Q3 | BZ1: 1990 Q4 | CA1: 1991 Q1 | CB1: 1991 Q2 | CC1: 1991 Q3 | CD1: 1991 Q4 | CE1: 1992 Q1 | CF1: 1992 Q2 | CG1: 1992 Q3 | CH1: 1992 Q4 | CI1: 1993 Q1 | CJ1: 1993 Q2 | CK1: 1993 Q3 | CL1: 1993 Q4 | CM1: 1994 Q1 | CN1: 1994 Q2 | CO1: 1994 Q3 | CP1: 1994 Q4 | CQ1: 1995 Q1 | CR1: 1995 Q2 | CS1: 1995 Q3 | CT1: 1995 Q4 | CU1: 1996 Q1 | CV1: 1996 Q2 | CW1: 1996 Q3 | CX1: 1996 Q4 | CY1: 1997 Q1 | CZ1: 1997 Q2 | DA1: 1997 Q3 | DB1: 1997 Q4 | DC1: 1998 Q1 | DD1: 1998 Q2 | DE1: 1998 Q3 | DF1: 1998 Q4 | DG1: 1999 Q1 | DH1: 1999 Q2 | DI1: 1999 Q3 | DJ1: 1999 Q4 | DK1: 2000 Q1 | DL1: 2000 Q2 | DM1: 2000 Q3 | DN1: 2000 Q4 | DO1: 2001 Q1 | DP1: 2001 Q2 | DQ1: 2001 Q3 | DR1: 2001 Q4 | DS1: 2002 Q1 | DT1: 2002 Q2 | DU1: 2002 Q3 | DV1: 2002 Q4 | DW1: 2003 Q1 | DX1: 2003 Q2 | DY1: 2003 Q3 | DZ1: 2003 Q4 | EA1: 2004 Q1 | EB1: 2004 Q2 | EC1: 2004 Q3 | ED1: 2004 Q4 | EE1: 2005 Q1 | EF1: 2005 Q2 | EG1: 2005 Q3 | EH1: 2005 Q4 | EI1: 2006 Q1 | EJ1: 2006 Q2 | EK1: 2006 Q3 | EL1: 2006 Q4 | EM1: 2007 Q1 | EN1: 2007 Q2 | EO1: 2007 Q3 | EP1: 2007 Q4 | EQ1: 2008 Q1 | ER1: 2008 Q2 | ES1: 2008 Q3 | ET1: 2008 Q4 | EU1: 2009 Q1 | EV1: 2009 Q2 | EW1: 2009 Q3 | EX1: 2009 Q4 | EY1: 2010 Q1 | EZ1: 2010 Q2 | FA1: 2010 Q3 | FB1: 2010 Q4 | FC1: 2011 Q1 | FD1: 2011 Q2 | FE1: 2011 Q3 | FF1: 2011 Q4 | FG1: 2012 Q1 | FH1: 2012 Q2 | FI1: 2012 Q3 | FJ1: 2012 Q4 | FK1: 2013 Q1 | FL1: 2013 Q2 | FM1: 2013 Q3 | FN1: 2013 Q4 | FO1: 2014 Q1 | FP1: 2014 Q2 | FQ1: 2014 Q3 | FR1: 2014 Q4 | FS1: 2015 Q1 | FT1: 2015 Q2 | FU1: 2015 Q3 | FV1: 2015 Q4 | FW1: 2016 Q1 | FX1: 2016 Q2 | FY1: 2016 Q3 | FZ1: 2016 Q4 | GA1: 2017 Q1 | GB1: 2017 Q2 | GC1: 2017 Q3 | GD1: 2017 Q4 | GE1: 2018 Q1 | GF1: 2018 Q2 | GG1: 2018 Q3 | GH1: 2018 Q4 | GI1: 2019 Q1 | GJ1: 2019 Q2 | GK1: 2019 Q3 | GL1: 2019 Q4 | GM1: 2020 Q1 | GN1: 2020 Q2 | GO1: 2020 Q3 | GP1: 2020 Q4 | GQ1: 2021 Q1 | GR1: 2021 Q2 | GS1: 2021 Q3 | GT1: 2021 Q4 | GU1: 2022 Q1 | GV1: 2022 Q2 | GW1: 2022 Q3 | GX1: 2022 Q4 | GY1: 2023 Q1 | GZ1: 2023 Q2 | HA1: 2023 Q3 | HB1: 2023 Q4 | HC1: 2024 Q1 | HD1: 2024 Q2 | HE1: 2024 Q3 | HF1: 2024 Q4 | HG1: 2025 Q1 | HH1: 2025 Q2 | HI1: 2025 Q3 | HJ1: 2025 Q4 | HK1: 2026 Q1 | HL1: 2026 Q2 | HM1: 2026 Q3 | HN1: 2026 Q4 | HO1: 2027 Q1 | HP1: 2027 Q2 | HQ1: 2027 Q3 | HR1: 2027 Q4 | HS1: 2028 Q1 | HT1: 2028 Q2 | HU1: 2028 Q3 | HV1: 2028 Q4 | HW1: 2029 Q1 | HX1: 2029 Q2 | HY1: 2029 Q3 | HZ1: 2029 Q4 | IA1: 2030 Q1 | IB1: 2030 Q2 | IC1: 2030 Q3 | ID1: 2030 Q4 | IE1: 2031 Q1 | IF1: 2031 Q2 | IG1: 2031 Q3 | IH1: 2031 Q4 | II1: 2032 Q1 | IJ1: 2032 Q2 | IK1: 2032 Q3 | IL1: 2032 Q4 | IM1: 2033 Q1 | IN1: 2033 Q2 | IO1: 2033 Q3 | IP1: 2033 Q4 | IQ1: 2034 Q1 | IR1: 2034 Q2 | IS1: 2034 Q3 | IT1: 2034 Q4 | IU1: 2035 Q1 | IV1: 2035 Q2 | IW1: 2035 Q3 | IX1: 2035 Q4 | IY1: 2036 Q1 | IZ1: 2036 Q2 | JA1: 2036 Q3 | JB1: 2036 Q4 | JC1: 2037 Q1 | JD1: 2037 Q2 | JE1: 2037 Q3 | JF1: 2037 Q4 | JG1: 2038 Q1 | JH1: 2038 Q2 | JI1: 2038 Q3 | JJ1: 2038 Q4 | JK1: 2039 Q1 | JL1: 2039 Q2 | JM1: 2039 Q3 | JN1: 2039 Q4 | JO1: 2040 Q1 | JP1: 2040 Q2 | JQ1: 2040 Q3 | JR1: 2040 Q4 | JS1: 2041 Q1 | JT1: 2041 Q2 | JU1: 2041 Q3 | JV1: 2041 Q4 | JW1: 2042 Q1 | JX1: 2042 Q2 | JY1: 2042 Q3 | JZ1: 2042 Q4 | KA1: 2043 Q1 | KB1: 2043 Q2 | KC1: 2043 Q3 | KD1: 2043 Q4 | KE1: 2044 Q1 | KF1: 2044 Q2 | KG1: 2044 Q3 | KH1: 2044 Q4 | KI1: 2045 Q1 | KJ1: 2045 Q2 | KK1: 2045 Q3 | KL1: 2045 Q4 | KM1: 2046 Q1 | KN1: 2046 Q2 | KO1: 2046 Q3 | KP1: 2046 Q4 | KQ1: 2047 Q1 | KR1: 2047 Q2 | KS1: 2047 Q3 | KT1: 2047 Q4 | KU1: 2048 Q1 | KV1: 2048 Q2 | KW1: 2048 Q3 | KX1: 2048 Q4 | KY1: 2049 Q1 | KZ1: 2049 Q2 | LA1: 2049 Q3 | LB1: 2049 Q4 | LC1: 2050 Q1 | LD1: 2050 Q2 | LE1: 2050 Q3 | LF1: 2050 Q4 | LG1: 2051 Q1 | LH1: 2051 Q2 | LI1: 2051 Q3 | LJ1: 2051 Q4 | LK1: 2052 Q1 | LL1: 2052 Q2 | LM1: 2052 Q3 | LN1: 2052 Q4 | LO1: 2053 Q1 | LP1: 2053 Q2 | LQ1: 2053 Q3 | LR1: 2053 Q4 | LS1: 2054 Q1 | LT1: 2054 Q2 | LU1: 2054 Q3 | LV1: 2054 Q4 | LW1: 2055 Q1 | LX1: 2055 Q2 | LY1: 2055 Q3 | LZ1: 2055 Q4 | MA1: 2056 Q1 | MB1: 2056 Q2 | MC1: 2056 Q3 | MD1: 2056 Q4 | ME1: 2057 Q1 | MF1: 2057 Q2 | MG1: 2057 Q3 | MH1: 2057 Q4 | MI1: 2058 Q1 | MJ1: 2058 Q2 | MK1: 2058 Q3 | ML1: 2058 Q4 | MM1: 2059 Q1 | MN1: 2059 Q2 | MO1: 2059 Q3 | MP1: 2059 Q4 | MQ1: 2060 Q1 | MR1: 2060 Q2 | MS1: 2060 Q3 | MT1: 2060 Q4 | MU1: Source | MV1: Seasonally adjusted | MW1: Base year price | MX1: Base year index | MY1: Historical end year | MZ1: Historical end quarter | NA1: Date of last update | NB1: Source details | NC1: Additional source details | ND1: Location code | NE1: Indicator code | NF1: Databank code
A2: United Kingdom | B2: GDP, real, LCU | C2: SEP008W | D2: Pound | E2: Millions | F2: Level | G2: 247921 | H2: 248384 | I2: 246082 | J2: 245140 | K2: 238319 | L2: 241752 | M2: 243197 | N2: 239612 | O2: 239702 | P2: 235807 | Q2: 235105 | R2: 237747 | S2: 241709 | T2: 241380 | U2: 244367 | V2: 249511 | W2: 249671 | X2: 247936 | Y2: 249578 | Z2: 253819 | AA2: 256193 | AB2: 259127 | AC2: 262661 | AD2: 264972 | AE2: 264185 | AF2: 275695 | AG2: 269599 | AH2: 272359 | AI2: 269776 | AJ2: 264448 | AK2: 264139 | AL2: 261297 | AM2: 261131 | AN2: 261739 | AO2: 264602 | AP2: 264902 | AQ2: 265408 | AR2: 268196 | AS2: 268798 | AT2: 270653 | AU2: 275877 | AV2: 277790 | AW2: 280996 | AX2: 283096 | AY2: 285469 | AZ2: 282605 | BA2: 284676 | BB2: 289829 | BC2: 292612 | BD2: 298873 | BE2: 298814 | BF2: 298979 | BG2: 302117 | BH2: 304797 | BI2: 306708 | BJ2: 312615 | BK2: 314804 | BL2: 319478 | BM2: 327346 | BN2: 331075 | BO2: 336442 | BP2: 338186 | BQ2: 342414 | BR2: 345162 | BS2: 346836 | BT2: 348997 | BU2: 349572 | BV2: 349523 | BW2: 351299 | BX2: 353663 | BY2: 349780 | BZ2: 348006 | CA2: 346292 | CB2: 345892 | CC2: 345216 | CD2: 345643 | CE2: 345523 | CF2: 344987 | CG2: 346628 | CH2: 349299 | CI2: 351046 | CJ2: 352612 | CK2: 355841 | CL2: 358264 | CM2: 361793 | CN2: 365109 | CO2: 368798 | CP2: 370401 | CQ2: 372307 | CR2: 373090 | CS2: 377249 | CT2: 378442 | CU2: 380976 | CV2: 382146 | CW2: 385671 | CX2: 391053 | CY2: 397303 | CZ2: 401790 | DA2: 405233 | DB2: 411352 | DC2: 414377 | DD2: 416909 | DE2: 418294 | DF2: 421074 | DG2: 423875 | DH2: 425920 | DI2: 432860 | DJ2: 439093 | DK2: 444540 | DL2: 447825 | DM2: 450688 | DN2: 453447 | DO2: 457680 | DP2: 459620 | DQ2: 462016 | DR2: 463404 | DS2: 464698 | DT2: 466935 | DU2: 470277 | DV2: 473899 | DW2: 477357 | DX2: 481552 | DY2: 485973 | DZ2: 490059 | EA2: 492014 | EB2: 494824 | EC2: 496642 | ED2: 499020 | EE2: 502702 | EF2: 506906 | EG2: 511132 | EH2: 515935 | EI2: 518495 | EJ2: 520318 | EK2: 521780 | EL2: 524569 | EM2: 529398 | EN2: 533187 | EO2: 537052 | EP2: 540258 | EQ2: 542804 | ER2: 539918 | ES2: 531619 | ET2: 520230 | EU2: 509646 | EV2: 508009 | EW2: 508398 | EX2: 509889 | EY2: 514595 | EZ2: 520128 | FA2: 523173 | FB2: 523515 | FC2: 524955 | FD2: 525418 | FE2: 527034 | FF2: 527698 | FG2: 532300 | FH2: 531663 | FI2: 536720 | FJ2: 536188 | FK2: 537974 | FL2: 541586 | FM2: 546064 | FN2: 549709 | FO2: 554183 | FP2: 559331 | FQ2: 563694 | FR2: 567619 | FS2: 569150 | FT2: 572673 | FU2: 574836 | FV2: 578068 | FW2: 580110 | FX2: 583383 | FY2: 585856 | FZ2: 589476 | GA2: 594423 | GB2: 598176 | GC2: 601961 | GD2: 606396 | GE2: 606785 | GF2: 607775 | GG2: 609653 | GH2: 610481 | GI2: 614936 | GJ2: 616853 | GK2: 621227 | GL2: 621229 | GM2: 604719 | GN2: 481769 | GO2: 562648 | GP2: 570338 | GQ2: 564411 | GR2: 605353 | GS2: 615459 | GT2: 624592 | GU2: 629149 | GV2: 631258 | GW2: 631977 | GX2: 634044 | GY2: 634428 | GZ2: 634694 | HA2: 634327 | HB2: 633011 | HC2: 638746 | HD2: 641670 | HE2: 641675 | HF2: 642287 | HG2: 647018 | HH2: 649249 | HI2: 649495.6 | HJ2: 650926.8 | HK2: 652456.9 | HL2: 653991 | HM2: 655625.9 | HN2: 657559.6 | HO2: 659696.7 | HP2: 662121.6 | HQ2: 664902.4 | HR2: 667827.8 | HS2: 670766.3 | HT2: 673650.4 | HU2: 676648.1 | HV2: 679557.8 | HW2: 682344 | HX2: 685039.2 | HY2: 687779.4 | HZ2: 690530.6 | IA2: 693223.7 | IB2: 695927.3 | IC2: 698641.4 | ID2: 701401 | IE2: 704206.6 | IF2: 707023.4 | IG2: 709780.8 | IH2: 712548.9 | II2: 715327.9 | IJ2: 718081.9 | IK2: 720882.4 | IL2: 723729.9 | IM2: 726536.1 | IN2: 729279 | IO2: 732034.8 | IP2: 734734.6 | IQ2: 737531.2 | IR2: 740293.6 | IS2: 743059.1 | IT2: 745779 | IU2: 748598.8 | IV2: 751430.9 | IW2: 754274.7 | IX2: 757130.4 | IY2: 760063.8 | IZ2: 763012.3 | JA2: 765976.1 | JB2: 768955.1 | JC2: 771949.1 | JD2: 774958 | JE2: 777982.3 | JF2: 781021.9 | JG2: 784076.8 | JH2: 787146.6 | JI2: 790232.4 | JJ2: 793334.1 | JK2: 796451.6 | JL2: 799584.6 | JM2: 802733.8 | JN2: 805899.1 | JO2: 809080.5 | JP2: 812276.5 | JQ2: 815487.6 | JR2: 818713.6 | JS2: 822031 | JT2: 825364.4 | JU2: 828724.3 | JV2: 832100.3 | JW2: 835492.6 | JX2: 838901.1 | JY2: 842256.2 | JZ2: 845626.2 | KA2: 849011.3 | KB2: 852411.2 | KC2: 855736.1 | KD2: 859074.1 | KE2: 862425.1 | KF2: 865789.1 | KG2: 869008.4 | KH2: 872238.2 | KI2: 875478.5 | KJ2: 878729.1 | KK2: 881916.9 | KL2: 885113.8 | KM2: 888320.1 | KN2: 891535.6 | KO2: 894759.7 | KP2: 897993.3 | KQ2: 901236.2 | KR2: 904488.6 | KS2: 907697.1 | KT2: 910914.5 | KU2: 914140.7 | KV2: 917375.6 | KW2: 920596.6 | KX2: 923826.1 | KY2: 927063.9 | KZ2: 930310.1 | LA2: 933491.5 | LB2: 936680.1 | LC2: 939875.5 | LD2: 943076.8 | LE2: 946260.4 | LF2: 949449.4 | LG2: 952644.9 | LH2: 955846.6 | LI2: 959017.3 | LJ2: 962193.6 | LK2: 965375.7 | LL2: 968563.6 | LM2: 971680.8 | LN2: 974802 | LO2: 977927.8 | LP2: 981057.6 | LQ2: 984191 | LR2: 987328.8 | LS2: 990471.1 | LT2: 993618 | LU2: 996736.1 | LV2: 999857.9 | LW2: 1002984 | LX2: 1006113 | LY2: 1009215 | LZ2: 1012320 | MA2: 1015429 | MB2: 1018541 | MC2: 1021655 | MD2: 1024772 | ME2: 1027894 | MF2: 1031019 | MG2: 1034173 | MH2: 1037330 | MI2: 1040492 | MJ2: 1043659 | MK2: 1046809 | ML2: 1049963 | MM2: 1053121 | MN2: 1056283 | MO2: 1059472 | MP2: 1062666 | MQ2: 1065864 | MR2: 1069067 | MS2: 1072275 | MT2: 1075487 | MU2: Office for National Statistics\Haver Analytics | MV2: TRUE | MW2: chained 2022 | MX2: NA | MY2: 2025 | MZ2: 2 | NA2: NA | NB2: ABMIQ@UK | NC2: U.K.: Real Gross Domestic Product (SA, Mil.Chn.2022.GBP) | ND2: GBR | NE2: GDP | NF2: SEP008W.db
A3: United States | B3: GDP, real, LCU | C3: SEP008W | D3: US$ | E3: Billions | F3: Level | G3: 1514.625 | H3: 1531.125 | I3: 1523.075 | J3: 1537.525 | K3: 1524.325 | L3: 1527.95 | M3: 1513.5 | N3: 1507.625 | O3: 1489.25 | P3: 1499.9 | Q3: 1525.575 | R3: 1546.125 | S3: 1580.9 | T3: 1592.5 | U3: 1601.225 | V3: 1612.8 | W3: 1631.925 | X3: 1663.625 | Y3: 1693.625 | Z3: 1693.65 | AA3: 1699.075 | AB3: 1764.725 | AC3: 1782.475 | AD3: 1806.45 | AE3: 1809.675 | AF3: 1811.625 | AG3: 1825.075 | AH3: 1829.625 | AI3: 1835.4 | AJ3: 1797.575 | AK3: 1795.425 | AL3: 1828.925 | AM3: 1864.75 | AN3: 1850.925 | AO3: 1873.1 | AP3: 1852.7 | AQ3: 1823.9 | AR3: 1832.225 | AS3: 1825.225 | AT3: 1825.95 | AU3: 1850.025 | AV3: 1892.125 | AW3: 1929.925 | AX3: 1970.2 | AY3: 2008.7 | AZ3: 2043.425 | BA3: 2063.125 | BB3: 2080.05 | BC3: 2100.2 | BD3: 2118.7 | BE3: 2151.05 | BF3: 2167.05 | BG3: 2187.275 | BH3: 2197.125 | BI3: 2218.15 | BJ3: 2230.05 | BK3: 2246.6 | BL3: 2270.825 | BM3: 2290.5 | BN3: 2329.825 | BO3: 2341.875 | BP3: 2372.65 | BQ3: 2386.55 | BR3: 2418.35 | BS3: 2442.925 | BT3: 2461.575 | BU3: 2479.8 | BV3: 2484.7 | BW3: 2511.85 | BX3: 2520.975 | BY3: 2522.65 | BZ3: 2499.675 | CA3: 2487.975 | CB3: 2507.375 | CC3: 2520.05 | CD3: 2528.825 | CE3: 2559.1 | CF3: 2586.85 | CG3: 2612.425 | CH3: 2639.65 | CI3: 2644.075 | CJ3: 2659.45 | CK3: 2672.15 | CL3: 2708.5 | CM3: 2734.775 | CN3: 2771.85 | CO3: 2788.05 | CP3: 2819.975 | CQ3: 2830 | CR3: 2838.425 | CS3: 2862.575 | CT3: 2882.025 | CU3: 2903.6 | CV3: 2952.025 | CW3: 2978.525 | CX3: 3009.45 | CY3: 3028.875 | CZ3: 3079.3 | DA3: 3117.75 | DB3: 3144.375 | DC3: 3175.925 | DD3: 3205.325 | DE3: 3245.7 | DF3: 3297.925 | DG3: 3328.9 | DH3: 3356.675 | DI3: 3401.2 | DJ3: 3457 | DK3: 3469.525 | DL3: 3532.725 | DM3: 3536.325 | DN3: 3557.45 | DO3: 3545.775 | DP3: 3567.925 | DQ3: 3553.625 | DR3: 3563.4 | DS3: 3593.2 | DT3: 3615.2 | DU3: 3629.9 | DV3: 3634.4 | DW3: 3653.525 | DX3: 3685.9 | DY3: 3747.2 | DZ3: 3790.7 | EA3: 3812.175 | EB3: 3841.725 | EC3: 3878.15 | ED3: 3917.725 | EE3: 3961.175 | EF3: 3980.7 | EG3: 4011.9 | EH3: 4034.175 | EI3: 4088.45 | EJ3: 4099.05 | EK3: 4105.175 | EL3: 4140.475 | EM3: 4152.925 | EN3: 4178.325 | EO3: 4202.4 | EP3: 4228.8 | EQ3: 4210.75 | ER3: 4235.825 | ES3: 4213.575 | ET3: 4121.35 | EU3: 4074.575 | EV3: 4067.275 | EW3: 4081.575 | EX3: 4125.7 | EY3: 4145.675 | EZ3: 4185.8 | FA3: 4218.075 | FB3: 4240.225 | FC3: 4230.15 | FD3: 4258.775 | FE3: 4257.825 | FF3: 4305.65 | FG3: 4341.75 | FH3: 4361.125 | FI3: 4367.425 | FJ3: 4372.475 | FK3: 4415.6 | FL3: 4427.425 | FM3: 4465.125 | FN3: 4504.025 | FO3: 4488.5 | FP3: 4546.475 | FQ3: 4601.725 | FR3: 4625 | FS3: 4666.65 | FT3: 4695.55 | FU3: 4714.35 | FV3: 4723.05 | FW3: 4750.425 | FX3: 4765.675 | FY3: 4799.475 | FZ3: 4826.1 | GA3: 4849.575 | GB3: 4876.725 | GC3: 4915.2 | GD3: 4970.6 | GE3: 5011.025 | GF3: 5037.625 | GG3: 5069.05 | GH3: 5076.225 | GI3: 5107.9 | GJ3: 5150.575 | GK3: 5210.825 | GL3: 5246.35 | GM3: 5173.3 | GN3: 4764.15 | GO3: 5137.2 | GP3: 5192.925 | GQ3: 5264.6 | GR3: 5347.25 | GS3: 5392.85 | GT3: 5490.1 | GU3: 5475.975 | GV3: 5479.8 | GW3: 5516.7 | GX3: 5562.375 | GY3: 5600.85 | GZ3: 5634.85 | HA3: 5695.225 | HB3: 5740.15 | HC3: 5763.375 | HD3: 5805.975 | HE3: 5850.075 | HF3: 5885.575 | HG3: 5878.175 | HH3: 5925.95 | HI3: 5960.899 | HJ3: 5980.9 | HK3: 6006.469 | HL3: 6037.903 | HM3: 6072.807 | HN3: 6110.222 | HO3: 6148.098 | HP3: 6185.644 | HQ3: 6222.729 | HR3: 6259.227 | HS3: 6295.312 | HT3: 6331 | HU3: 6366.284 | HV3: 6401.181 | HW3: 6435.654 | HX3: 6469.723 | HY3: 6503.323 | HZ3: 6536.444 | IA3: 6569.078 | IB3: 6601.313 | IC3: 6633.142 | ID3: 6664.535 | IE3: 6695.686 | IF3: 6726.804 | IG3: 6757.833 | IH3: 6788.818 | II3: 6819.79 | IJ3: 6850.769 | IK3: 6881.737 | IL3: 6912.755 | IM3: 6943.899 | IN3: 6975.17 | IO3: 7006.569 | IP3: 7038.096 | IQ3: 7069.752 | IR3: 7101.537 | IS3: 7133.452 | IT3: 7165.496 | IU3: 7197.671 | IV3: 7229.977 | IW3: 7262.414 | IX3: 7294.983 | IY3: 7327.663 | IZ3: 7360.546 | JA3: 7393.339 | JB3: 7426.289 | JC3: 7459.111 | JD3: 7492.011 | JE3: 7525.263 | JF3: 7558.164 | JG3: 7591.247 | JH3: 7624.247 | JI3: 7657.523 | JJ3: 7690.787 | JK3: 7724.164 | JL3: 7757.704 | JM3: 7790.869 | JN3: 7824.518 | JO3: 7858.102 | JP3: 7891.695 | JQ3: 7925.356 | JR3: 7959.177 | JS3: 7992.982 | JT3: 8026.912 | JU3: 8060.972 | JV3: 8095.077 | JW3: 8129.236 | JX3: 8163.513 | JY3: 8197.81 | JZ3: 8232.188 | KA3: 8266.805 | KB3: 8301.581 | KC3: 8336.274 | KD3: 8371.271 | KE3: 8406.265 | KF3: 8441.307 | KG3: 8476.375 | KH3: 8511.699 | KI3: 8546.866 | KJ3: 8582.217 | KK3: 8617.521 | KL3: 8653.007 | KM3: 8688.629 | KN3: 8724.187 | KO3: 8759.862 | KP3: 8795.721 | KQ3: 8831.57 | KR3: 8867.463 | KS3: 8903.477 | KT3: 8939.488 | KU3: 8975.586 | KV3: 9011.988 | KW3: 9048.095 | KX3: 9084.718 | KY3: 9121.205 | KZ3: 9157.445 | LA3: 9194.076 | LB3: 9230.601 | LC3: 9267.576 | LD3: 9304.396 | LE3: 9341.087 | LF3: 9378.168 | LG3: 9415.25 | LH3: 9452.497 | LI3: 9489.891 | LJ3: 9527.306 | LK3: 9565.014 | LL3: 9602.733 | LM3: 9640.641 | LN3: 9678.649 | LO3: 9716.763 | LP3: 9754.988 | LQ3: 9793.43 | LR3: 9831.984 | LS3: 9870.654 | LT3: 9909.362 | LU3: 9948.271 | LV3: 9987.312 | LW3: 10026.48 | LX3: 10065.79 | LY3: 10105.29 | LZ3: 10144.75 | MA3: 10184.55 | MB3: 10224.29 | MC3: 10264.3 | MD3: 10304.48 | ME3: 10344.63 | MF3: 10385.06 | MG3: 10425.63 | MH3: 10466.31 | MI3: 10507.24 | MJ3: 10548.2 | MK3: 10589.38 | ML3: 10630.68 | MM3: 10672.17 | MN3: 10713.71 | MO3: 10755.45 | MP3: 10797.4 | MQ3: 10839.46 | MR3: 10881.68 | MS3: 10924.04 | MT3: 10966.46 | MU3: Bureau of Economic Analysis\Haver Analytics | MV3: TRUE | MW3: chained 2017 | MX3: NA | MY3: 2025 | MZ3: 2 | NA3: NA | NB3: GDPH@USNA / 4 | NC3: Real Gross Domestic Product (SAAR, Bil.Chn.2017$) / 4 | ND3: USA | NE3: GDP | NF3: SEP008W.db
A4: Japan | B4: GDP, real, LCU | C4: SEP008W | D4: Yen | E4: Billions | F4: Level | G4: 52242.65 | H4: 52722.43 | I4: 52875.77 | J4: 53539.66 | K4: 51759.14 | L4: 52134.51 | M4: 52810.48 | N4: 52526.84 | O4: 52595.21 | P4: 53789.34 | Q4: 54409.61 | R4: 54986.97 | S4: 55458.37 | T4: 55787.51 | U4: 56585.37 | V4: 56653.35 | W4: 57921.84 | X4: 58330.15 | Y4: 58729.51 | Z4: 59539.25 | AA4: 60686.21 | AB4: 61280.64 | AC4: 62081.49 | AD4: 62988.52 | AE4: 64175.77 | AF4: 65372.08 | AG4: 65872.72 | AH4: 66157.2 | AI4: 67431.65 | AJ4: 67125.25 | AK4: 68540.48 | AL4: 69895.05 | AM4: 70493.48 | AN4: 71146.73 | AO4: 71480.1 | AP4: 71827.58 | AQ4: 72823.85 | AR4: 73296.85 | AS4: 73595.08 | AT4: 74635.23 | AU4: 75168.8 | AV4: 75743.88 | AW4: 76764.23 | AX4: 77307.77 | AY4: 78032.58 | AZ4: 79658.95 | BA4: 80246.33 | BB4: 80542.25 | BC4: 81627.42 | BD4: 83146.85 | BE4: 84384.77 | BF4: 85720.3 | BG4: 85758.42 | BH4: 86018.4 | BI4: 86623.83 | BJ4: 87631.63 | BK4: 87931.4 | BL4: 89458.15 | BM4: 91089.55 | BN4: 93422.8 | BO4: 94866.7 | BP4: 95559.08 | BQ4: 97321.1 | BR4: 98386.73 | BS4: 100718.5 | BT4: 99521.33 | BU4: 101067.9 | BV4: 103823.8 | BW4: 103264 | BX4: 105791 | BY4: 107937.8 | BZ4: 107869 | CA4: 109030.2 | CB4: 109977.8 | CC4: 109973 | CD4: 110813.9 | CE4: 110645.6 | CF4: 110982.4 | CG4: 111402.7 | CH4: 110721.5 | CI4: 111282 | CJ4: 110343.9 | CK4: 109839 | CL4: 110263.7 | CM4: 111555.8 | CN4: 110953.6 | CO4: 112226.3 | CP4: 111797.5 | CQ4: 113005 | CR4: 114086.1 | CS4: 115422 | CT4: 115718.8 | CU4: 116661.9 | CV4: 118139.6 | CW4: 118288.7 | CX4: 119618.3 | CY4: 119889.1 | CZ4: 119023.4 | DA4: 119250.4 | DB4: 119301.8 | DC4: 117820.5 | DD4: 117331.6 | DE4: 117535.2 | DF4: 118481.3 | DG4: 116835.3 | DH4: 117298.9 | DI4: 117919.2 | DJ4: 117957 | DK4: 119997.6 | DL4: 120531 | DM4: 120565.3 | DN4: 121729.4 | DO4: 122635.2 | DP4: 121711.9 | DQ4: 120400 | DR4: 119972.3 | DS4: 120184.6 | DT4: 121142.8 | DU4: 121545.5 | DV4: 121874.9 | DW4: 121950.3 | DX4: 122774 | DY4: 123157.5 | DZ4: 124497 | EA4: 125445.5 | EB4: 125411.1 | EC4: 126195.2 | ED4: 125960.1 | EE4: 126598.6 | EF4: 127572.6 | EG4: 128875.7 | EH4: 129108.6 | EI4: 129311.9 | EJ4: 129494.1 | EK4: 129248 | EL4: 130994.4 | EM4: 131865.7 | EN4: 131898.3 | EO4: 131197.3 | EP4: 131753.5 | EQ4: 132283.2 | ER4: 131458.2 | ES4: 129842.8 | ET4: 126600.7 | EU4: 120530.5 | EV4: 122898.3 | EW4: 122855 | EX4: 124335.5 | EY4: 125665.3 | EZ4: 127188.3 | FA4: 129488.8 | FB4: 128402.8 | FC4: 127080.9 | FD4: 125989.6 | FE4: 129025.6 | FF4: 128830.9 | FG4: 130701.9 | FH4: 129468.2 | FI4: 128944.8 | FJ4: 128854.3 | FK4: 130664.3 | FL4: 131845.8 | FM4: 133082.1 | FN4: 132920.2 | FO4: 134019.7 | FP4: 131619.5 | FQ4: 131706 | FR4: 132301.8 | FS4: 134366.4 | FT4: 134579.5 | FU4: 134696.8 | FV4: 134452.7 | FW4: 135492.6 | FX4: 135265.7 | FY4: 135545.8 | FZ4: 135724.3 | GA4: 136780.7 | GB4: 137324.1 | GC4: 138516.8 | GD4: 138606.1 | GE4: 138694.6 | GF4: 139239 | GG4: 138545.5 | GH4: 138219.1 | GI4: 138528.5 | GJ4: 139158.5 | GK4: 139424.4 | GL4: 135393 | GM4: 136078.3 | GN4: 125772.4 | GO4: 132570.5 | GP4: 134848 | GQ4: 135160.3 | GR4: 136139 | GS4: 135556.7 | GT4: 137095.1 | GU4: 136415.3 | GV4: 137862.3 | GW4: 137188.8 | GX4: 137553.4 | GY4: 139288 | GZ4: 139845.8 | HA4: 138394.4 | HB4: 138327.2 | HC4: 137944.8 | HD4: 138965.4 | HE4: 139362.8 | HF4: 140193.5 | HG4: 140387.7 | HH4: 140747 | HI4: 140529.4 | HJ4: 140576.9 | HK4: 140776.5 | HL4: 141111 | HM4: 141371.1 | HN4: 141568.4 | HO4: 141727.7 | HP4: 141860.8 | HQ4: 141976.2 | HR4: 142083.8 | HS4: 142172.5 | HT4: 142247.3 | HU4: 142315.3 | HV4: 142371.4 | HW4: 142425.6 | HX4: 142477.7 | HY4: 142525.7 | HZ4: 142565.8 | IA4: 142600.3 | IB4: 142633.3 | IC4: 142653.4 | ID4: 142668.5 | IE4: 142673.4 | IF4: 142676.7 | IG4: 142668.1 | IH4: 142650.5 | II4: 142628 | IJ4: 142605 | IK4: 142579.3 | IL4: 142550.5 | IM4: 142510.1 | IN4: 142472.7 | IO4: 142445.1 | IP4: 142402 | IQ4: 142363 | IR4: 142327.2 | IS4: 142275.3 | IT4: 142206.9 | IU4: 142142.8 | IV4: 142083.6 | IW4: 142011.8 | IX4: 141926.6 | IY4: 141840.5 | IZ4: 141758.2 | JA4: 141672.6 | JB4: 141585 | JC4: 141496.8 | JD4: 141407.7 | JE4: 141316.3 | JF4: 141222.1 | JG4: 141128.3 | JH4: 141033.4 | JI4: 140934.9 | JJ4: 140832.2 | JK4: 140727.5 | JL4: 140622.1 | JM4: 140520.6 | JN4: 140423.3 | JO4: 140327.6 | JP4: 140231 | JQ4: 140139.1 | JR4: 140051.6 | JS4: 139965.7 | JT4: 139880 | JU4: 139798.3 | JV4: 139719.8 | JW4: 139643.9 | JX4: 139568.8 | JY4: 139498.4 | JZ4: 139432.5 | KA4: 139369.1 | KB4: 139306.6 | KC4: 139247.3 | KD4: 139191.5 | KE4: 139139.9 | KF4: 139093.5 | KG4: 139054 | KH4: 139021.4 | KI4: 138994.4 | KJ4: 138971.4 | KK4: 138954.3 | KL4: 138943.2 | KM4: 138937 | KN4: 138934.9 | KO4: 138937.8 | KP4: 138944.9 | KQ4: 138953.2 | KR4: 138962.2 | KS4: 138976.6 | KT4: 138995.6 | KU4: 139013.5 | KV4: 139030.6 | KW4: 139050.4 | KX4: 139073.6 | KY4: 139093.3 | KZ4: 139112.9 | LA4: 139140.2 | LB4: 139177.5 | LC4: 139215.6 | LD4: 139252.7 | LE4: 139299.3 | LF4: 139355.4 | LG4: 139411.9 | LH4: 139468.2 | LI4: 139533.6 | LJ4: 139607.3 | LK4: 139679 | LL4: 139749.6 | LM4: 139833 | LN4: 139930.3 | LO4: 140027.8 | LP4: 140122.3 | LQ4: 140223.8 | LR4: 140332.9 | LS4: 140443.6 | LT4: 140553.3 | LU4: 140667.4 | LV4: 140786.1 | LW4: 140905.9 | LX4: 141026.3 | LY4: 141152.4 | LZ4: 141283 | MA4: 141415.6 | MB4: 141548.2 | MC4: 141684.5 | MD4: 141823.8 | ME4: 141961.9 | MF4: 142097.8 | MG4: 142240.7 | MH4: 142389.9 | MI4: 142537.5 | MJ4: 142683 | MK4: 142832.6 | ML4: 142986.8 | MM4: 143139.3 | MN4: 143288.3 | MO4: 143438.8 | MP4: 143591.6 | MQ4: 143741.5 | MR4: 143889.3 | MS4: 144041.5 | MT4: 144197.5 | MU4: Cabinet Office of Japan\Haver Analytics | MV4: TRUE | MW4: 2015 | MX4: NA | MY4: 2025 | MZ4: 2 | NA4: NA | NB4: REDPC2@JAPAN/4 | NC4: Japan: Gross Domestic Product (SAAR, Bil.Chn.2015.Yen) | ND4: JPN | NE4: GDP | NF4: SEP008W.db
A5: Germany | B5: GDP, real, LCU | C5: SEP008W | D5: Euro | E5: Billions | F5: Level | G5: 386.07 | H5: 388.81 | I5: 390.14 | J5: 391.12 | K5: 394.27 | L5: 393.93 | M5: 394.09 | N5: 389.05 | O5: 386.82 | P5: 384.92 | Q5: 389.05 | R5: 396.83 | S5: 400.23 | T5: 406.27 | U5: 406.44 | V5: 413.88 | W5: 417.53 | X5: 419.84 | Y5: 419.68 | Z5: 426.88 | AA5: 428.69 | AB5: 430.44 | AC5: 435.98 | AD5: 441.11 | AE5: 441.69 | AF5: 455.35 | AG5: 455.43 | AH5: 458.15 | AI5: 461.8 | AJ5: 458.81 | AK5: 457 | AL5: 456.34 | AM5: 461.88 | AN5: 460.64 | AO5: 461.88 | AP5: 461.46 | AQ5: 463.29 | AR5: 460.39 | AS5: 455.93 | AT5: 457 | AU5: 461.22 | AV5: 466.02 | AW5: 464.95 | AX5: 471.39 | AY5: 477.6 | AZ5: 470.16 | BA5: 482.9 | BB5: 486.95 | BC5: 484.39 | BD5: 489.11 | BE5: 495.57 | BF5: 498.46 | BG5: 495.73 | BH5: 501.44 | BI5: 505.16 | BJ5: 510.13 | BK5: 497.3 | BL5: 508.47 | BM5: 512.03 | BN5: 520.15 | BO5: 515.6 | BP5: 524.95 | BQ5: 530.74 | BR5: 537.11 | BS5: 542.57 | BT5: 544.81 | BU5: 549.78 | BV5: 556.15 | BW5: 567.64 | BX5: 570.55 | BY5: 582.54 | BZ5: 592.8 | CA5: 610.84 | CB5: 607.91 | CC5: 606.96 | CD5: 615.67 | CE5: 624.15 | CF5: 620.27 | CG5: 618.8 | CH5: 617.08 | CI5: 612.18 | CJ5: 612.27 | CK5: 615.89 | CL5: 615.37 | CM5: 624.06 | CN5: 627.51 | CO5: 631.22 | CP5: 638.21 | CQ5: 635.69 | CR5: 640.78 | CS5: 642.07 | CT5: 642.33 | CU5: 637.76 | CV5: 646.47 | CW5: 648.97 | CX5: 654.93 | CY5: 651.58 | CZ5: 658.83 | DA5: 661.42 | DB5: 666.33 | DC5: 672.7 | DD5: 669.59 | DE5: 672.87 | DF5: 672.7 | DG5: 680.5 | DH5: 679.64 | DI5: 688.96 | DJ5: 692.24 | DK5: 702.91 | DL5: 708.52 | DM5: 709.04 | DN5: 706.02 | DO5: 721.01 | DP5: 719.2 | DQ5: 719.2 | DR5: 716.95 | DS5: 713.61 | DT5: 716.37 | DU5: 721.29 | DV5: 719.3 | DW5: 709.53 | DX5: 710.57 | DY5: 717.04 | DZ5: 717.9 | EA5: 716.8 | EB5: 721.03 | EC5: 718.7 | ED5: 718.44 | EE5: 719.58 | EF5: 723.9 | EG5: 729.59 | EH5: 732.35 | EI5: 740.52 | EJ5: 753.21 | EK5: 758.9 | EL5: 770.03 | EM5: 771.04 | EN5: 776.13 | EO5: 780.1 | EP5: 785.88 | EQ5: 790.5 | ER5: 787.65 | ES5: 783.34 | ET5: 771.17 | EU5: 735.03 | EV5: 736.84 | EW5: 741.41 | EX5: 747.1 | EY5: 752.54 | EZ5: 768.84 | FA5: 776.26 | FB5: 781.35 | FC5: 795.48 | FD5: 797.63 | FE5: 801.95 | FF5: 801.86 | FG5: 803.57 | FH5: 804.43 | FI5: 806.07 | FJ5: 803.65 | FK5: 799.21 | FL5: 808.53 | FM5: 812.67 | FN5: 813.87 | FO5: 822.37 | FP5: 822.2 | FQ5: 826.77 | FR5: 833.07 | FS5: 831.26 | FT5: 835.57 | FU5: 840.06 | FV5: 844.37 | FW5: 851.79 | FX5: 853.69 | FY5: 856.71 | FZ5: 860.67 | GA5: 871.85 | GB5: 878.06 | GC5: 885.05 | GD5: 894.02 | GE5: 889.08 | GF5: 896.07 | GG5: 890.2 | GH5: 894.17 | GI5: 900.03 | GJ5: 900.55 | GK5: 904 | GL5: 900.98 | GM5: 882.69 | GN5: 804.36 | GO5: 874.15 | GP5: 882.61 | GQ5: 877.17 | GR5: 897.79 | GS5: 898.57 | GT5: 903.4 | GU5: 909.52 | GV5: 910.9 | GW5: 913.58 | GX5: 910.39 | GY5: 906.09 | GZ5: 905.4 | HA5: 905.4 | HB5: 902.9 | HC5: 901.93 | HD5: 899.6 | HE5: 899.78 | HF5: 901.41 | HG5: 904.18 | HH5: 901.67 | HI5: 902.0363 | HJ5: 902.9799 | HK5: 904.6468 | HL5: 907.7305 | HM5: 911.3778 | HN5: 915.7637 | HO5: 920.6661 | HP5: 926.0956 | HQ5: 931.8219 | HR5: 937.5429 | HS5: 943.1637 | HT5: 948.4047 | HU5: 953.0765 | HV5: 957.2838 | HW5: 961.1807 | HX5: 964.8649 | HY5: 968.4431 | HZ5: 971.7866 | IA5: 974.868 | IB5: 977.7058 | IC5: 980.3386 | ID5: 982.7238 | IE5: 984.8571 | IF5: 986.8453 | IG5: 988.6469 | IH5: 990.2596 | II5: 991.7475 | IJ5: 993.1532 | IK5: 994.4139 | IL5: 995.5951 | IM5: 996.7846 | IN5: 997.9819 | IO5: 999.1866 | IP5: 1000.344 | IQ5: 1001.509 | IR5: 1002.679 | IS5: 1003.801 | IT5: 1004.928 | IU5: 1006.126 | IV5: 1007.533 | IW5: 1009.191 | IX5: 1011.057 | IY5: 1013.008 | IZ5: 1014.957 | JA5: 1016.906 | JB5: 1018.852 | JC5: 1020.899 | JD5: 1022.947 | JE5: 1024.995 | JF5: 1027.045 | JG5: 1029.071 | JH5: 1031.1 | JI5: 1033.13 | JJ5: 1035.162 | JK5: 1037.48 | JL5: 1039.752 | JM5: 1042.028 | JN5: 1044.236 | JO5: 1046.705 | JP5: 1049.181 | JQ5: 1051.665 | JR5: 1054.156 | JS5: 1056.69 | JT5: 1059.232 | JU5: 1061.781 | JV5: 1064.339 | JW5: 1066.961 | JX5: 1069.593 | JY5: 1072.232 | JZ5: 1074.88 | KA5: 1077.454 | KB5: 1080.035 | KC5: 1082.624 | KD5: 1085.221 | KE5: 1087.746 | KF5: 1090.279 | KG5: 1092.82 | KH5: 1095.367 | KI5: 1097.867 | KJ5: 1100.373 | KK5: 1102.885 | KL5: 1105.404 | KM5: 1107.863 | KN5: 1110.328 | KO5: 1112.8 | KP5: 1115.279 | KQ5: 1117.579 | KR5: 1119.884 | KS5: 1122.194 | KT5: 1124.476 | KU5: 1126.762 | KV5: 1129.053 | KW5: 1131.351 | KX5: 1133.655 | KY5: 1135.903 | KZ5: 1138.157 | LA5: 1140.416 | LB5: 1142.68 | LC5: 1144.987 | LD5: 1147.3 | LE5: 1149.619 | LF5: 1151.943 | LG5: 1154.253 | LH5: 1156.567 | LI5: 1158.884 | LJ5: 1161.125 | LK5: 1163.326 | LL5: 1165.529 | LM5: 1167.735 | LN5: 1169.944 | LO5: 1172.027 | LP5: 1174.112 | LQ5: 1176.197 | LR5: 1178.282 | LS5: 1180.292 | LT5: 1182.302 | LU5: 1184.313 | LV5: 1186.322 | LW5: 1188.242 | LX5: 1190.16 | LY5: 1192.077 | LZ5: 1193.993 | MA5: 1196.005 | MB5: 1198.018 | MC5: 1200.032 | MD5: 1202.048 | ME5: 1204.013 | MF5: 1205.98 | MG5: 1207.949 | MH5: 1209.92 | MI5: 1212.218 | MJ5: 1214.521 | MK5: 1216.83 | ML5: 1219.143 | MM5: 1221.553 | MN5: 1223.969 | MO5: 1226.39 | MP5: 1228.818 | MQ5: 1231.307 | MR5: 1233.803 | MS5: 1236.305 | MT5: 1238.814 | MU5: Federal Statistics Office\Haver Analytics | MV5: TRUE | MW5: chained 2020 | MX5: NA | MY5: 2025 | MZ5: 2 | NA5: NA | NB5: DESNGDPC@GERMANY | NC5: Germany: Gross Domestic Product (SWDA, Bil.Chained.2020.Euros) | ND5: DEU | NE5: GDP | NF5: SEP008W.db
A6: France | B6: GDP, real, LCU | C6: SEP008W | D6: Euro | E6: Billions | F6: Level | G6: 244.379 | H6: 247.949 | I6: 251.887 | J6: 254.935 | K6: 259.118 | L6: 260.946 | M6: 263.841 | N6: 259.134 | O6: 257.134 | P6: 257.051 | Q6: 256.883 | R6: 262.376 | S6: 264.851 | T6: 268.472 | U6: 271.536 | V6: 273.453 | W6: 276.547 | X6: 277.655 | Y6: 279.927 | Z6: 282.16 | AA6: 286.062 | AB6: 289.179 | AC6: 290.979 | AD6: 294.294 | AE6: 297.552 | AF6: 299.071 | AG6: 302.92 | AH6: 303.971 | AI6: 307.574 | AJ6: 305.096 | AK6: 305.557 | AL6: 305.08 | AM6: 306.214 | AN6: 308.53 | AO6: 310.602 | AP6: 312.474 | AQ6: 314.838 | AR6: 317.069 | AS6: 316.885 | AT6: 318.782 | AU6: 320.007 | AV6: 320.182 | AW6: 320.696 | AX6: 322.692 | AY6: 324.129 | AZ6: 325.672 | BA6: 327.777 | BB6: 327.475 | BC6: 328.296 | BD6: 331.027 | BE6: 332.921 | BF6: 334.602 | BG6: 335.636 | BH6: 339.318 | BI6: 341.16 | BJ6: 341.586 | BK6: 341.867 | BL6: 346.957 | BM6: 349.29 | BN6: 354.442 | BO6: 358.993 | BP6: 362.135 | BQ6: 366.718 | BR6: 369.743 | BS6: 374.552 | BT6: 378.731 | BU6: 382.998 | BV6: 388.135 | BW6: 388.956 | BX6: 391.046 | BY6: 393.587 | BZ6: 393.398 | CA6: 394.433 | CB6: 395.89 | CC6: 397.495 | CD6: 399.413 | CE6: 402.27 | CF6: 402.721 | CG6: 402.258 | CH6: 402.334 | CI6: 400.161 | CJ6: 400.18 | CK6: 400.67 | CL6: 401.724 | CM6: 404.451 | CN6: 408.509 | CO6: 412.199 | CP6: 416.085 | CQ6: 418.051 | CR6: 420.792 | CS6: 421.449 | CT6: 421.283 | CU6: 424.211 | CV6: 425.029 | CW6: 426.67 | CX6: 428.311 | CY6: 430.14 | CZ6: 434.654 | DA6: 438.976 | DB6: 443.314 | DC6: 447.564 | DD6: 450.769 | DE6: 453.1 | DF6: 456.206 | DG6: 459.345 | DH6: 462.324 | DI6: 469.134 | DJ6: 475.778 | DK6: 480.381 | DL6: 485.751 | DM6: 489.487 | DN6: 492.463 | DO6: 495.037 | DP6: 495.157 | DQ6: 497.976 | DR6: 495.812 | DS6: 498.673 | DT6: 501.004 | DU6: 503.071 | DV6: 503.507 | DW6: 505.071 | DX6: 502.817 | DY6: 508.236 | DZ6: 510.008 | EA6: 515.562 | EB6: 517.822 | EC6: 519.632 | ED6: 524.256 | EE6: 525.852 | EF6: 527.018 | EG6: 530.978 | EH6: 534.65 | EI6: 539.351 | EJ6: 545.831 | EK6: 546.204 | EL6: 549.188 | EM6: 554.926 | EN6: 558.574 | EO6: 560.333 | EP6: 560.925 | EQ6: 565.776 | ER6: 561.562 | ES6: 560.195 | ET6: 553.087 | EU6: 542.56 | EV6: 543.517 | EW6: 544.741 | EX6: 548.618 | EY6: 550.3 | EZ6: 552.871 | FA6: 556.492 | FB6: 559.837 | FC6: 567.201 | FD6: 567.286 | FE6: 569.07 | FF6: 571.074 | FG6: 570.803 | FH6: 568.561 | FI6: 570.275 | FJ6: 570.214 | FK6: 571.282 | FL6: 576.301 | FM6: 574.93 | FN6: 578.438 | FO6: 578.458 | FP6: 579.909 | FQ6: 583.604 | FR6: 582.011 | FS6: 585.375 | FT6: 585.786 | FU6: 587.286 | FV6: 588.718 | FW6: 590.553 | FX6: 589.52 | FY6: 590.302 | FZ6: 594.035 | GA6: 598.014 | GB6: 602.59 | GC6: 606.887 | GD6: 610.543 | GE6: 610.307 | GF6: 611.92 | GG6: 614.846 | GH6: 619.487 | GI6: 625.191 | GJ6: 628.634 | GK6: 628.582 | GL6: 625.508 | GM6: 593.757 | GN6: 521.351 | GO6: 601.406 | GP6: 600.715 | GQ6: 603.162 | GR6: 610.51 | GS6: 628.722 | GT6: 632.259 | GU6: 631.696 | GV6: 634.423 | GW6: 637.7 | GX6: 640.147 | GY6: 640.545 | GZ6: 646.222 | HA6: 647.783 | HB6: 650.61 | HC6: 651.405 | HD6: 652.617 | HE6: 655.015 | HF6: 654.621 | HG6: 655.373 | HH6: 657.57 | HI6: 657.8 | HJ6: 658.52 | HK6: 659.6 | HL6: 660.71 | HM6: 662.22 | HN6: 664.17 | HO6: 666.37 | HP6: 668.74 | HQ6: 671.38 | HR6: 673.84 | HS6: 676.43 | HT6: 679.06 | HU6: 681.85 | HV6: 684.64 | HW6: 687.36 | HX6: 690.06 | HY6: 692.75 | HZ6: 695.31 | IA6: 697.82 | IB6: 700.05 | IC6: 702.29 | ID6: 704.44 | IE6: 706.66 | IF6: 708.68 | IG6: 710.44 | IH6: 711.77 | II6: 713.32 | IJ6: 714.71 | IK6: 716.1 | IL6: 717.46 | IM6: 718.57 | IN6: 719.83 | IO6: 721.01 | IP6: 722.39 | IQ6: 723.77 | IR6: 725.22 | IS6: 726.64 | IT6: 727.83 | IU6: 729.3 | IV6: 730.69 | IW6: 731.9 | IX6: 733.038 | IY6: 734.3823 | IZ6: 735.6849 | JA6: 737.0613 | JB6: 738.2462 | JC6: 739.5468 | JD6: 740.7153 | JE6: 742.0748 | JF6: 743.259 | JG6: 744.3857 | JH6: 745.2888 | JI6: 746.2032 | JJ6: 747.0458 | JK6: 748.0897 | JL6: 749.0757 | JM6: 750.167 | JN6: 751.2386 | JO6: 752.1554 | JP6: 753.1324 | JQ6: 753.9583 | JR6: 754.9525 | JS6: 755.863 | JT6: 756.8497 | JU6: 757.7531 | JV6: 758.7794 | JW6: 759.8123 | JX6: 760.9152 | JY6: 761.8667 | JZ6: 763.0565 | KA6: 764.01 | KB6: 765.1212 | KC6: 766.2203 | KD6: 767.2972 | KE6: 768.2823 | KF6: 769.1647 | KG6: 770.1605 | KH6: 771.2364 | KI6: 772.0459 | KJ6: 773.0117 | KK6: 773.9572 | KL6: 774.8 | KM6: 775.7426 | KN6: 776.595 | KO6: 777.3335 | KP6: 778.2012 | KQ6: 778.902 | KR6: 779.5984 | KS6: 780.2461 | KT6: 780.8224 | KU6: 781.5941 | KV6: 782.2543 | KW6: 782.7665 | KX6: 783.4472 | KY6: 784.1266 | KZ6: 784.798 | LA6: 785.4583 | LB6: 785.9971 | LC6: 786.7712 | LD6: 787.5934 | LE6: 788.3079 | LF6: 788.9588 | LG6: 789.6753 | LH6: 790.3989 | LI6: 791.1016 | LJ6: 791.695 | LK6: 792.379 | LL6: 793.0197 | LM6: 793.6216 | LN6: 794.1515 | LO6: 794.7668 | LP6: 795.3889 | LQ6: 795.9703 | LR6: 796.5511 | LS6: 797.0638 | LT6: 797.7346 | LU6: 798.2769 | LV6: 798.8634 | LW6: 799.3601 | LX6: 799.9229 | LY6: 800.4748 | LZ6: 800.9381 | MA6: 801.491 | MB6: 802.054 | MC6: 802.5939 | MD6: 803.0579 | ME6: 803.55 | MF6: 804.0494 | MG6: 804.4695 | MH6: 804.9568 | MI6: 805.5199 | MJ6: 805.9442 | MK6: 806.4751 | ML6: 806.8876 | MM6: 807.4219 | MN6: 807.8232 | MO6: 808.3388 | MP6: 808.8334 | MQ6: 809.301 | MR6: 809.8839 | MS6: 810.4373 | MT6: 810.9039 | MU6: Institut National de la Statistique et des Etudes Economiques\Haver Analytics | MV6: TRUE | MW6: chained 2020 | MX6: NA | MY6: 2025 | MZ6: 2 | NA6: NA | NB6: FRSNGDPC@FRANCE/1000 | NC6: France: Gross Domestic Product (SA/WDA, Mil.Chn.2020.Euros)/1000 | ND6: FRA | NE6: GDP | NF6: SEP008W.db
A7: Italy | B7: GDP, real, LCU | C7: SEP008W | D7: Euro | E7: Billions | F7: Level | G7: 223.0287 | H7: 229.7104 | I7: 237.0208 | J7: 242.81 | K7: 244.7785 | L7: 247.1172 | M7: 247.5283 | N7: 242.3543 | O7: 238.1379 | P7: 238.0164 | Q7: 241.3983 | R7: 244.1035 | S7: 248.4038 | T7: 252.8942 | U7: 259.3207 | V7: 263.8197 | W7: 263.9241 | X7: 262.4543 | Y7: 259.9991 | Z7: 262.2263 | AA7: 266.513 | AB7: 271.1233 | AC7: 272.5487 | AD7: 276.7017 | AE7: 281.0739 | AF7: 283.1178 | AG7: 288.0178 | AH7: 294.7971 | AI7: 294.2694 | AJ7: 296.5532 | AK7: 296.8017 | AL7: 299.3304 | AM7: 298.359 | AN7: 298.941 | AO7: 299.08 | AP7: 301.507 | AQ7: 301.387 | AR7: 300.531 | AS7: 300.37 | AT7: 299.495 | AU7: 300.334 | AV7: 299.975 | AW7: 305.559 | AX7: 312.334 | AY7: 311.719 | AZ7: 312.725 | BA7: 316.407 | BB7: 316.458 | BC7: 318.265 | BD7: 322.471 | BE7: 325.052 | BF7: 327.22 | BG7: 329.26 | BH7: 331.389 | BI7: 334.698 | BJ7: 336.071 | BK7: 337.449 | BL7: 342.558 | BM7: 343.547 | BN7: 347.243 | BO7: 352.354 | BP7: 354.592 | BQ7: 359.252 | BR7: 363.541 | BS7: 365.798 | BT7: 367.382 | BU7: 371.212 | BV7: 375.032 | BW7: 376.526 | BX7: 377.674 | BY7: 378.281 | BZ7: 375.822 | CA7: 379.581 | CB7: 377.503 | CC7: 377.639 | CD7: 382.071 | CE7: 383.1 | CF7: 382.879 | CG7: 382.028 | CH7: 379.396 | CI7: 378.865 | CJ7: 377.952 | CK7: 377.356 | CL7: 380.122 | CM7: 383.018 | CN7: 385.79 | CO7: 388.197 | CP7: 391.841 | CQ7: 396.76 | CR7: 397.038 | CS7: 398.804 | CT7: 402.107 | CU7: 402.945 | CV7: 403.618 | CW7: 404.416 | CX7: 403.024 | CY7: 404.187 | CZ7: 410.584 | DA7: 412.505 | DB7: 418.613 | DC7: 416.498 | DD7: 419 | DE7: 419.321 | DF7: 418.008 | DG7: 420.023 | DH7: 421.657 | DI7: 426.043 | DJ7: 432.351 | DK7: 437.661 | DL7: 440.545 | DM7: 444.529 | DN7: 448.836 | DO7: 452.368 | DP7: 452.065 | DQ7: 450.324 | DR7: 449.673 | DS7: 450.235 | DT7: 451.48 | DU7: 452.267 | DV7: 454.882 | DW7: 452.98 | DX7: 452.182 | DY7: 451.075 | DZ7: 455.314 | EA7: 457.215 | EB7: 458.387 | EC7: 458.712 | ED7: 459.891 | EE7: 459.057 | EF7: 463.016 | EG7: 465.476 | EH7: 467.647 | EI7: 468.87 | EJ7: 470.604 | EK7: 472.086 | EL7: 478.756 | EM7: 477.757 | EN7: 479.139 | EO7: 479.299 | EP7: 478.289 | EQ7: 483.194 | ER7: 478.677 | ES7: 471.556 | ET7: 460.734 | EU7: 449.464 | EV7: 446.835 | EW7: 447.954 | EX7: 449.072 | EY7: 451.187 | EZ7: 454.075 | FA7: 455.303 | FB7: 459.282 | FC7: 461.593 | FD7: 460.723 | FE7: 458.746 | FF7: 454.35 | FG7: 449.162 | FH7: 445.757 | FI7: 442.682 | FJ7: 439.553 | FK7: 435.578 | FL7: 435.555 | FM7: 436.971 | FN7: 436.608 | FO7: 436.416 | FP7: 436.627 | FQ7: 436.722 | FR7: 436.269 | FS7: 437.801 | FT7: 439.526 | FU7: 439.695 | FV7: 442.027 | FW7: 442.808 | FX7: 444.022 | FY7: 447.174 | FZ7: 448.867 | GA7: 450.875 | GB7: 452.625 | GC7: 453.397 | GD7: 456.102 | GE7: 455.296 | GF7: 456.236 | GG7: 456.218 | GH7: 457.576 | GI7: 458.562 | GJ7: 459.828 | GK7: 458.126 | GL7: 456.423 | GM7: 429.875 | GN7: 376.881 | GO7: 431.182 | GP7: 430.917 | GQ7: 438.548 | GR7: 449.303 | GS7: 460.468 | GT7: 467.533 | GU7: 470.949 | GV7: 477.841 | GW7: 479.065 | GX7: 478.331 | GY7: 480.508 | GZ7: 479.729 | HA7: 480.336 | HB7: 481.133 | HC7: 481.897 | HD7: 482.933 | HE7: 482.951 | HF7: 483.91 | HG7: 485.416 | HH7: 485.046 | HI7: 485.6545 | HJ7: 486.2859 | HK7: 487.0153 | HL7: 487.7215 | HM7: 488.6579 | HN7: 489.5764 | HO7: 490.4948 | HP7: 491.4132 | HQ7: 492.3316 | HR7: 493.2501 | HS7: 494.2372 | HT7: 495.226 | HU7: 496.1987 | HV7: 497.1046 | HW7: 497.9619 | HX7: 498.7935 | HY7: 499.6448 | HZ7: 500.3661 | IA7: 501.0874 | IB7: 501.7727 | IC7: 502.4564 | ID7: 503.1397 | IE7: 503.649 | IF7: 504.1346 | IG7: 504.6175 | IH7: 505.0973 | II7: 505.5107 | IJ7: 505.9149 | IK7: 506.3171 | IL7: 506.7327 | IM7: 507.1345 | IN7: 507.5345 | IO7: 507.9331 | IP7: 508.2708 | IQ7: 508.5952 | IR7: 508.9185 | IS7: 509.2438 | IT7: 509.5685 | IU7: 509.8835 | IV7: 510.233 | IW7: 510.5598 | IX7: 510.8859 | IY7: 511.1859 | IZ7: 511.4803 | JA7: 511.7735 | JB7: 512.0653 | JC7: 512.3428 | JD7: 512.618 | JE7: 512.8932 | JF7: 513.1641 | JG7: 513.421 | JH7: 513.6747 | JI7: 513.9258 | JJ7: 514.1743 | JK7: 514.3877 | JL7: 514.5984 | JM7: 514.806 | JN7: 515.0089 | JO7: 515.2296 | JP7: 515.4458 | JQ7: 515.6595 | JR7: 515.8658 | JS7: 516.0659 | JT7: 516.2628 | JU7: 516.4546 | JV7: 516.6412 | JW7: 516.8396 | JX7: 517.0337 | JY7: 517.2256 | JZ7: 517.4109 | KA7: 517.6251 | KB7: 517.8355 | KC7: 517.9747 | KD7: 518.1105 | KE7: 518.2624 | KF7: 518.4105 | KG7: 518.5545 | KH7: 518.6974 | KI7: 518.9105 | KJ7: 519.0959 | KK7: 519.2783 | KL7: 519.4584 | KM7: 519.7029 | KN7: 519.947 | KO7: 520.1873 | KP7: 520.4241 | KQ7: 520.7195 | KR7: 521.0126 | KS7: 521.3046 | KT7: 521.5927 | KU7: 521.8915 | KV7: 522.1891 | KW7: 522.4851 | KX7: 522.7788 | KY7: 523.1382 | KZ7: 523.4955 | LA7: 523.8518 | LB7: 524.2064 | LC7: 524.6005 | LD7: 524.9929 | LE7: 525.3853 | LF7: 525.7759 | LG7: 526.1898 | LH7: 526.6029 | LI7: 527.0159 | LJ7: 527.4275 | LK7: 527.8618 | LL7: 528.295 | LM7: 528.7274 | LN7: 529.1606 | LO7: 529.6319 | LP7: 530.1033 | LQ7: 530.5745 | LR7: 531.0442 | LS7: 531.5294 | LT7: 532.012 | LU7: 532.4969 | LV7: 532.9799 | LW7: 533.4833 | LX7: 533.9865 | LY7: 534.4902 | LZ7: 534.9921 | MA7: 535.5266 | MB7: 536.0617 | MC7: 536.5966 | MD7: 537.1315 | ME7: 537.6577 | MF7: 538.1846 | MG7: 538.71 | MH7: 539.2361 | MI7: 539.7142 | MJ7: 540.1925 | MK7: 540.6722 | ML7: 541.1506 | MM7: 541.4798 | MN7: 541.8076 | MO7: 542.1349 | MP7: 542.4622 | MQ7: 542.7671 | MR7: 543.0703 | MS7: 543.3746 | MT7: 543.6786 | MU7: Statistical Office of the European Communities\Haver Analytics | MV7: TRUE | MW7: chained 2020 | MX7: NA | MY7: 2025 | MZ7: 2 | NA7: NA | NB7: ITSNGDPC@ITALY/1000 | NC7: Italy: Gross Domestic Product (SWDA, Mil.Ch.20.EUR) /1000 | ND7: ITA | NE7: GDP | NF7: SEP008W.db
A8: Canada | B8: GDP, real, LCU | C8: SEP008W | D8: C$ | E8: Millions | F8: Level | G8: 174319.5 | H8: 175982.5 | I8: 176800.8 | J8: 180061.8 | K8: 181552 | L8: 183414.3 | M8: 183449.5 | N8: 182493.8 | O8: 181499.5 | P8: 183828 | Q8: 187354.8 | R8: 189522.8 | S8: 192825.5 | T8: 196983.8 | U8: 197893.3 | V8: 198213 | W8: 201253.3 | X8: 202280.3 | Y8: 203469.3 | Z8: 206693.5 | AA8: 208478.5 | AB8: 209897.5 | AC8: 211855.5 | AD8: 213864.3 | AE8: 215570.5 | AF8: 218430.3 | AG8: 220031.5 | AH8: 221507.8 | AI8: 223045.8 | AJ8: 222948.3 | AK8: 222763 | AL8: 225845.3 | AM8: 230710.8 | AN8: 233233.3 | AO8: 231136.3 | AP8: 230073.3 | AQ8: 227440.3 | AR8: 224821.8 | AS8: 222828 | AT8: 220771.8 | AU8: 224379.8 | AV8: 228806.3 | AW8: 231376.8 | AX8: 234253.3 | AY8: 238310.5 | AZ8: 242935.3 | BA8: 243979.8 | BB8: 247787.5 | BC8: 251594.5 | BD8: 252403.8 | BE8: 255608 | BF8: 259505 | BG8: 259373.5 | BH8: 260864.3 | BI8: 261192.3 | BJ8: 259301.5 | BK8: 265295 | BL8: 268693.5 | BM8: 272798.8 | BN8: 276323 | BO8: 280349 | BP8: 282836.8 | BQ8: 282878.8 | BR8: 284820 | BS8: 288111 | BT8: 289231.8 | BU8: 290276 | BV8: 289698.3 | BW8: 292484.3 | BX8: 291310.8 | BY8: 289223 | BZ8: 286647.8 | CA8: 282524 | CB8: 283880 | CC8: 284256.5 | CD8: 284756 | CE8: 284957 | CF8: 285281.8 | CG8: 286827 | CH8: 288461.3 | CI8: 290292.8 | CJ8: 292937 | CK8: 295738.5 | CL8: 297003.5 | CM8: 301382.8 | CN8: 305782.5 | CO8: 309702.8 | CP8: 311952.5 | CQ8: 314818.8 | CR8: 314952.5 | CS8: 315368.8 | CT8: 316641.5 | CU8: 317101 | CV8: 319358.5 | CW8: 322040.8 | CX8: 324592.3 | CY8: 328941.5 | CZ8: 332643.3 | DA8: 336586.8 | DB8: 339839.5 | DC8: 344638 | DD8: 344820.5 | DE8: 347962.5 | DF8: 352677.3 | DG8: 359045 | DH8: 362006.3 | DI8: 367680.5 | DJ8: 372831.5 | DK8: 378669 | DL8: 383125.8 | DM8: 387053 | DN8: 387818.5 | DO8: 390001.5 | DP8: 391228 | DQ8: 390953 | DR8: 393297.8 | DS8: 399048.5 | DT8: 401406.3 | DU8: 404877.3 | DV8: 407101 | DW8: 409366 | DX8: 408772.3 | DY8: 410300.5 | DZ8: 413121 | EA8: 416125 | EB8: 421055.5 | EC8: 426033.8 | ED8: 429108.5 | EE8: 430611.3 | EF8: 433723.5 | EG8: 438979.8 | EH8: 443339.5 | EI8: 446939 | EJ8: 447162.5 | EK8: 448421.3 | EL8: 450207 | EM8: 453080.3 | EN8: 457455.8 | EO8: 459169.8 | EP8: 459773.3 | EQ8: 460118.3 | ER8: 461794.8 | ES8: 465589.5 | ET8: 460187.3 | EU8: 449802.8 | EV8: 444950.8 | EW8: 446940.8 | EX8: 452133.8 | EY8: 457611.5 | EZ8: 460007.8 | FA8: 463228 | FB8: 468424.5 | FC8: 471992 | FD8: 472848.8 | FE8: 479318.5 | FF8: 483127.8 | FG8: 483432.8 | FH8: 485004.3 | FI8: 485668 | FJ8: 486667.5 | FK8: 491023.8 | FL8: 493851.5 | FM8: 497912.5 | FN8: 503123.5 | FO8: 503973.8 | FP8: 508567.8 | FQ8: 513442.8 | FR8: 516991.5 | FS8: 514113 | FT8: 512709.5 | FU8: 514545.5 | FV8: 514886.5 | FW8: 517933 | FX8: 515353 | FY8: 520701.3 | FZ8: 523622.5 | GA8: 530210.8 | GB8: 535791.5 | GC8: 535959.8 | GD8: 538679 | GE8: 544941.3 | GF8: 549192 | GG8: 551962.3 | GH8: 553262.5 | GI8: 554594 | GJ8: 560665.5 | GK8: 562233.3 | GL8: 563838.5 | GM8: 552844 | GN8: 492031.5 | GO8: 536725.3 | GP8: 546807 | GQ8: 556122.3 | GR8: 555470.5 | GS8: 566660.5 | GT8: 576806 | GU8: 581725.3 | GV8: 587179.3 | GW8: 590733.3 | GX8: 589886.8 | GY8: 595588.8 | GZ8: 596820 | HA8: 595994.8 | HB8: 597039.3 | HC8: 600215.5 | HD8: 604005.5 | HE8: 607606.3 | HF8: 610704.3 | HG8: 613784.5 | HH8: 611342 | HI8: 611435.3 | HJ8: 612177.4 | HK8: 613289.5 | HL8: 615261.9 | HM8: 618522.8 | HN8: 623312.1 | HO8: 626933.8 | HP8: 631274 | HQ8: 635299 | HR8: 639106.4 | HS8: 642511.8 | HT8: 645171.7 | HU8: 647990.2 | HV8: 650834.7 | HW8: 653450.1 | HX8: 656353.3 | HY8: 659325.7 | HZ8: 662456 | IA8: 665776.4 | IB8: 669240.2 | IC8: 672740.6 | ID8: 676308.9 | IE8: 679760.9 | IF8: 683140.6 | IG8: 686558.6 | IH8: 689969.4 | II8: 693350.1 | IJ8: 696735.3 | IK8: 700125.6 | IL8: 703499.1 | IM8: 706922 | IN8: 710353.1 | IO8: 713808.1 | IP8: 717296.1 | IQ8: 720852 | IR8: 724415 | IS8: 727992.8 | IT8: 731572.6 | IU8: 734993.9 | IV8: 738402.5 | IW8: 741856.4 | IX8: 745373.8 | IY8: 749054.8 | IZ8: 752763.6 | JA8: 756496.7 | JB8: 760257.2 | JC8: 764053.3 | JD8: 767846.1 | JE8: 771600.4 | JF8: 775320.9 | JG8: 779032.1 | JH8: 782783.1 | JI8: 786560.3 | JJ8: 790365.3 | JK8: 794153.3 | JL8: 797952.2 | JM8: 801844 | JN8: 805831.4 | JO8: 809819.8 | JP8: 813788.3 | JQ8: 817823.1 | JR8: 821928.9 | JS8: 826049.1 | JT8: 830164.9 | JU8: 834298.6 | JV8: 838446.8 | JW8: 842624.8 | JX8: 846818.6 | JY8: 850994.8 | JZ8: 855160.1 | KA8: 859343.2 | KB8: 863551.8 | KC8: 867772.9 | KD8: 871995.6 | KE8: 876239.5 | KF8: 880463.9 | KG8: 884663.5 | KH8: 888899.2 | KI8: 893105.2 | KJ8: 897313.7 | KK8: 901551.4 | KL8: 905810.6 | KM8: 910096.7 | KN8: 914391.4 | KO8: 918696.6 | KP8: 923011.5 | KQ8: 927347 | KR8: 931683.1 | KS8: 936015.4 | KT8: 940334.8 | KU8: 944667.7 | KV8: 949001.9 | KW8: 953325.8 | KX8: 957644.3 | KY8: 961979 | KZ8: 966348.3 | LA8: 970732.6 | LB8: 975126.9 | LC8: 979531.8 | LD8: 983950.4 | LE8: 988377.7 | LF8: 992814.8 | LG8: 997261.9 | LH8: 1001709 | LI8: 1006165 | LJ8: 1010618 | LK8: 1015086 | LL8: 1019568 | LM8: 1024061 | LN8: 1028561 | LO8: 1033081 | LP8: 1037603 | LQ8: 1042132 | LR8: 1046669 | LS8: 1051204 | LT8: 1055739 | LU8: 1060298 | LV8: 1064881 | LW8: 1069446 | LX8: 1074028 | LY8: 1078636 | LZ8: 1083273 | MA8: 1087856 | MB8: 1092519 | MC8: 1097225 | MD8: 1101974 | ME8: 1106822 | MF8: 1111607 | MG8: 1116394 | MH8: 1121202 | MI8: 1125975 | MJ8: 1130787 | MK8: 1135640 | ML8: 1140522 | MM8: 1145442 | MN8: 1150330 | MO8: 1155245 | MP8: 1160198 | MQ8: 1165149 | MR8: 1170096 | MS8: 1175054 | MT8: 1180032 | MU8: Statistics Canada\Haver Analytics | MV8: TRUE | MW8: chained 2017 | MX8: NA | MY8: 2025 | MZ8: 2 | NA8: NA | NB8: V6E05752@CANADA/4 | NC8: Canada: Gross Domestic Product at Market Prices (SAAR, Mil.Chn.2017.C$)/4 | ND8: CAN | NE8: GDP | NF8: SEP008W.db
