Workbook
Name Data: [1]sheet0!$C$2

Sheet CHARTS>>

Sheet DATA>>

Sheet Chart Data
A1: AE debt dynamics (2025-2029) | W1: Budget deficit in 2025 | AF1: Gross government debt in 2025 | AO1: Budget deficit & debt | AX1: Term premium | BD1: Scenario - conts to GDP change | BM1: Financial market assumptions | BN1: $/£ | BR1: RLG | BU1: CPI inflation
B2: =DataA!BK2 -> UK | C2: =DataA!BL2 -> US | D2: =DataA!BM2 -> Japan | E2: =DataA!BN2 -> Canada | F2: =DataA!BO2 -> Australia | G2: =DataA!BP2 -> Denmark | H2: =DataA!BQ2 -> Sweden | I2: =DataA!BR2 -> Switzerland | ... U2: =DataA!CD2 -> Portugal | X2: =RANK(X4,$X$4:$AD$4) -> 5 | Y2: =RANK(Y4,$X$4:$AD$4) -> 7 | Z2: =RANK(Z4,$X$4:$AD$4) -> 3 | AA2: =RANK(AA4,$X$4:$AD$4) -> 2 | AB2: =RANK(AB4,$X$4:$AD$4) -> 6 | AC2: =RANK(AC4,$X$4:$AD$4) -> 4 | AD2: =RANK(AD4,$X$4:$AD$4) -> 1 | AG2: =RANK(AG4,$AG$4:$AM$4) -> 6 | AH2: =RANK(AH4,$AG$4:$AM$4) -> 3 | AI2: =RANK(AI4,$AG$4:$AM$4) -> 1 | AJ2: =RANK(AJ4,$AG$4:$AM$4) -> 7 | AK2: =RANK(AK4,$AG$4:$AM$4) -> 4 | AL2: =RANK(AL4,$AG$4:$AM$4) -> 2 | AM2: =RANK(AM4,$AG$4:$AM$4) -> 5 | AO2: 2025 | AP2: =X3&", "&$AO2 -> UK, 2025 | AQ2: =Y3&", "&$AO2 -> US, 2025 | AR2: =Z3&", "&$AO2 -> Japan, 2025 | AS2: =AA3&", "&$AO2 -> Germany, 2025 | AT2: =AB3&", "&$AO2 -> France, 2025 | AU2: =AC3&", "&$AO2 -> Italy, 2025 | AV2: =AD3&", "&$AO2 -> Canada, 2025 | AY2: UK | AZ2: US | BA2: Germany | BB2: Japan | BF2: Consumer spending | BG2: Fixed investment | BH2: Government consumption | BI2: Net exports | BJ2: Other | BK2: GDP | BN2: Baseline | BO2: Scenario | BR2: Baseline | BS2: Scenario | BV2: Baseline | BW2: Scenario
A3: Expected effective interest rates on government debt (r) | B3: =AVERAGE(DataA!BK59:BK63) -> 4.0541862 | C3: =AVERAGE(DataA!BL59:BL63) -> 3.4859128 | D3: =AVERAGE(DataA!BM59:BM63) -> 1.0367112 | E3: =AVERAGE(DataA!BN59:BN63) -> 3.262102 | F3: =AVERAGE(DataA!BO59:BO63) -> 2.226878 | G3: =AVERAGE(DataA!BP59:BP63) -> 1.9487714 | H3: =AVERAGE(DataA!BQ59:BQ63) -> 1.5550773 | I3: =AVERAGE(DataA!BR59:BR63) -> 1.2049825 | ... U3: =AVERAGE(DataA!CD59:CD63) -> 2.322023 | X3: UK | Y3: US | Z3: Japan | AA3: Germany | AB3: France | AC3: Italy | AD3: Canada | AG3: UK | AH3: US | AI3: Japan | AJ3: Germany | AK3: France | AL3: Italy | AM3: Canada | AP3: =X3 -> UK | AQ3: =Y3 -> US | AR3: =Z3 -> Japan | AS3: =AA3 -> Germany | AT3: =AB3 -> France | AU3: =AC3 -> Italy | AV3: =AD3 -> Canada | AX3: 43831 | AY3: =DataQ!AI195 -> -1.415394 | AZ3: =DataQ!AJ195 -> -1.280833 | BA3: =DataQ!AK195 -> -1.552948 | BB3: =DataQ!AL195 -> -0.3934202 | BD3: 45931 | BE3: Q4 25 | BF3: =100*((DataScen!X218-DataScen!H218)/DataScen!$G218) -> -0.048749908 | BG3: =100*((DataScen!Y218-DataScen!I218)/DataScen!$G218) -> -0.0090382217 | BH3: =100*((DataScen!Z218-DataScen!J218)/DataScen!$G218) -> 0 | BI3: =100*(((DataScen!AA218-DataScen!AB218)-(DataScen!K218-DataScen!L218))/DataScen!$G218) -> 0.053028941 | BJ3: =BK3-BF3-BG3-BH3-BI3 -> -1.4122221e-05 | BK3: =100*((DataScen!W218/DataScen!G218)-1) -> -0.0047733108 | BM3: 45292 | BN3: =DataScen!R211 -> 1.267967 | BO3: =DataScen!AH211 -> 1.267967 | BQ3: 45292 | BR3: =DataScen!O211 -> 3.972031 | BS3: =DataScen!AE211 -> 3.972031 | BU3: 45292 | BV3: =100*((DataScen!M211/DataScen!M207)-1) -> 3.5491137 | BW3: =100*((DataScen!AC211/DataScen!AC207)-1) -> 3.5491137
A4: Expected annual average nominal GDP growth (g) | B4: =100*((DataA!AP63/DataA!AP58)^(1/5)-1) -> 3.9672499 | C4: =100*((DataA!AQ63/DataA!AQ58)^(1/5)-1) -> 4.3583029 | D4: =100*((DataA!AR63/DataA!AR58)^(1/5)-1) -> 1.7591278 | E4: =100*((DataA!AS63/DataA!AS58)^(1/5)-1) -> 3.6123652 | F4: =100*((DataA!AT63/DataA!AT58)^(1/5)-1) -> 4.3438259 | G4: =100*((DataA!AU63/DataA!AU58)^(1/5)-1) -> 3.8570117 | H4: =100*((DataA!AV63/DataA!AV58)^(1/5)-1) -> 3.778961 | I4: =100*((DataA!AW63/DataA!AW58)^(1/5)-1) -> 2.0447691 | ... U4: =100*((DataA!BI63/DataA!BI58)^(1/5)-1) -> 3.4305293 | W4: 2025 | X4: =100*('Data Q to A'!I60/'Data Q to A'!W60) -> -4.6502172 | Y4: =100*('Data Q to A'!J60/'Data Q to A'!X60) -> -7.4168274 | Z4: =100*('Data Q to A'!K60/'Data Q to A'!Y60) -> -2.9476509 | AA4: =100*('Data Q to A'!L60/'Data Q to A'!Z60) -> -2.07748 | AB4: =100*('Data Q to A'!M60/'Data Q to A'!AA60) -> -5.4069183 | AC4: =100*('Data Q to A'!N60/'Data Q to A'!AB60) -> -2.9942321 | AD4: =100*('Data Q to A'!O60/'Data Q to A'!AC60) -> -1.5593717 | AF4: 2025 | AG4: =100*('Data Q to A'!P60/'Data Q to A'!W60) -> 101.22663 | AH4: =100*('Data Q to A'!Q60/'Data Q to A'!X60) -> 139.4818 | AI4: =100*('Data Q to A'!R60/'Data Q to A'!Y60) -> 216.98578 | AJ4: =100*('Data Q to A'!S60/'Data Q to A'!Z60) -> 58.235605 | AK4: =100*('Data Q to A'!T60/'Data Q to A'!AA60) -> 127.41761 | AL4: =100*('Data Q to A'!U60/'Data Q to A'!AB60) -> 149.72344 | AM4: =100*('Data Q to A'!V60/'Data Q to A'!AC60) -> 107.05075 | AO4: Budget deficit | AP4: =X4 -> -4.6502172 | AQ4: =Y4 -> -7.4168274 | AR4: =Z4 -> -2.9476509 | AS4: =AA4 -> -2.07748 | AT4: =AB4 -> -5.4069183 | AU4: =AC4 -> -2.9942321 | AV4: =AD4 -> -1.5593717 | AX4: 43922 | AY4: =DataQ!AI196 -> -0.4839782 | AZ4: =DataQ!AJ196 -> -1.337862 | BA4: =DataQ!AK196 -> -1.164785 | BB4: =DataQ!AL196 -> -0.3085212 | BD4: 46023 | BE4: Q1 26 | BF4: =100*((DataScen!X219-DataScen!H219)/DataScen!$G219) -> -0.14160034 | BG4: =100*((DataScen!Y219-DataScen!I219)/DataScen!$G219) -> -0.0059452136 | BH4: =100*((DataScen!Z219-DataScen!J219)/DataScen!$G219) -> 0 | BI4: =100*(((DataScen!AA219-DataScen!AB219)-(DataScen!K219-DataScen!L219))/DataScen!$G219) -> 0.25815188 | BJ4: =BK4-BF4-BG4-BH4-BI4 -> -0.00074667374 | BK4: =100*((DataScen!W219/DataScen!G219)-1) -> 0.10985966 | BM4: 45383 | BN4: =DataScen!R212 -> 1.261867 | BO4: =DataScen!AH212 -> 1.261867 | BQ4: 45383 | BR4: =DataScen!O212 -> 4.183968 | BS4: =DataScen!AE212 -> 4.183968 | BU4: 45383 | BV4: =100*((DataScen!M212/DataScen!M208)-1) -> 2.1108336 | BW4: =100*((DataScen!AC212/DataScen!AC208)-1) -> 2.1108336
AO5: Government debt | AP5: =AG4 -> 101.22663 | AQ5: =AH4 -> 139.4818 | AR5: =AI4 -> 216.98578 | AS5: =AJ4 -> 58.235605 | AT5: =AK4 -> 127.41761 | AU5: =AL4 -> 149.72344 | AV5: =AM4 -> 107.05075 | AX5: 44013 | AY5: =DataQ!AI197 -> 0.2473059 | AZ5: =DataQ!AJ197 -> -1.26913 | BA5: =DataQ!AK197 -> -1.138384 | BB5: =DataQ!AL197 -> -0.1991098 | BD5: 46113 | BE5: Q2 26 | BF5: =100*((DataScen!X220-DataScen!H220)/DataScen!$G220) -> -0.36596958 | BG5: =100*((DataScen!Y220-DataScen!I220)/DataScen!$G220) -> -0.061772652 | BH5: =100*((DataScen!Z220-DataScen!J220)/DataScen!$G220) -> -0.1381065 | BI5: =100*(((DataScen!AA220-DataScen!AB220)-(DataScen!K220-DataScen!L220))/DataScen!$G220) -> 0.40580205 | BJ5: =BK5-BF5-BG5-BH5-BI5 -> 0.016613259 | BK5: =100*((DataScen!W220/DataScen!G220)-1) -> -0.14343343 | BM5: 45474 | BN5: =DataScen!R213 -> 1.300467 | BO5: =DataScen!AH213 -> 1.300467 | BQ5: 45474 | BR5: =DataScen!O213 -> 3.986061 | BS5: =DataScen!AE213 -> 3.986061 | BU5: 45474 | BV5: =100*((DataScen!M213/DataScen!M209)-1) -> 2.0547945 | BW5: =100*((DataScen!AC213/DataScen!AC209)-1) -> 2.0547945
A6: AE debt dynamics (2026-2030) | X6: 1 | Y6: 2 | Z6: 3 | AA6: 4 | AB6: 5 | AC6: 6 | AD6: 7 | AG6: 1 | AH6: 2 | AI6: 3 | AJ6: 4 | AK6: 5 | AL6: 6 | AM6: 7 | AX6: 44105 | AY6: =DataQ!AI198 -> 0.7989324 | AZ6: =DataQ!AJ198 -> -0.9776321 | BA6: =DataQ!AK198 -> -1.120849 | BB6: =DataQ!AL198 -> -0.07849678 | BD6: 46204 | BE6: Q3 26 | BF6: =100*((DataScen!X221-DataScen!H221)/DataScen!$G221) -> -0.50096645 | BG6: =100*((DataScen!Y221-DataScen!I221)/DataScen!$G221) -> -0.10430667 | BH6: =100*((DataScen!Z221-DataScen!J221)/DataScen!$G221) -> -0.13843066 | BI6: =100*(((DataScen!AA221-DataScen!AB221)-(DataScen!K221-DataScen!L221))/DataScen!$G221) -> 0.54494629 | BJ6: =BK6-BF6-BG6-BH6-BI6 -> -0.024688717 | BK6: =100*((DataScen!W221/DataScen!G221)-1) -> -0.22344621 | BM6: 45566 | BN6: =DataScen!R214 -> 1.2814 | BO6: =DataScen!AH214 -> 1.2814 | BQ6: 45566 | BR6: =DataScen!O214 -> 4.34127 | BS6: =DataScen!AE214 -> 4.34127 | BU6: 45566 | BV6: =100*((DataScen!M214/DataScen!M210)-1) -> 2.4753214 | BW6: =100*((DataScen!AC214/DataScen!AC210)-1) -> 2.4753214
B7: =DataA!BK2 -> UK | C7: =DataA!BL2 -> US | D7: =DataA!BM2 -> Japan | E7: =DataA!BN2 -> Canada | F7: =DataA!BO2 -> Australia | G7: =DataA!BP2 -> Denmark | H7: =DataA!BQ2 -> Sweden | I7: =DataA!BR2 -> Switzerland | ... U7: =DataA!CD2 -> Portugal | X7: =HLOOKUP(X$6,$X$2:$AD$4,2,FALSE) -> Canada | Y7: =HLOOKUP(Y$6,$X$2:$AD$4,2,FALSE) -> Germany | Z7: =HLOOKUP(Z$6,$X$2:$AD$4,2,FALSE) -> Japan | AA7: =HLOOKUP(AA$6,$X$2:$AD$4,2,FALSE) -> Italy | AB7: =HLOOKUP(AB$6,$X$2:$AD$4,2,FALSE) -> UK | AC7: =HLOOKUP(AC$6,$X$2:$AD$4,2,FALSE) -> France | AD7: =HLOOKUP(AD$6,$X$2:$AD$4,2,FALSE) -> US | AG7: =HLOOKUP(AG$6,$AF$2:$AM$4,2,FALSE) -> Japan | AH7: =HLOOKUP(AH$6,$AF$2:$AM$4,2,FALSE) -> Italy | AI7: =HLOOKUP(AI$6,$AF$2:$AM$4,2,FALSE) -> US | AJ7: =HLOOKUP(AJ$6,$AF$2:$AM$4,2,FALSE) -> France | AK7: =HLOOKUP(AK$6,$AF$2:$AM$4,2,FALSE) -> Canada | AL7: =HLOOKUP(AL$6,$AF$2:$AM$4,2,FALSE) -> UK | AM7: =HLOOKUP(AM$6,$AF$2:$AM$4,2,FALSE) -> Germany | AO7: 2030 | AP7: =X13&", "&$AO7 -> UK, 2030 | AQ7: =Y13&", "&$AO7 -> US, 2030 | AR7: =Z13&", "&$AO7 -> Japan, 2030 | AS7: =AA13&", "&$AO7 -> Germany, 2030 | AT7: =AB13&", "&$AO7 -> France, 2030 | AU7: =AC13&", "&$AO7 -> Italy, 2030 | AV7: =AD13&", "&$AO7 -> Canada, 2030 | AX7: 44197 | AY7: =DataQ!AI199 -> 1.557647 | AZ7: =DataQ!AJ199 -> -0.5086092 | BA7: =DataQ!AK199 -> -0.8559847 | BB7: =DataQ!AL199 -> 0.01564632 | BD7: 46296 | BE7: Q4 26 | BF7: =100*((DataScen!X222-DataScen!H222)/DataScen!$G222) -> -0.58576697 | BG7: =100*((DataScen!Y222-DataScen!I222)/DataScen!$G222) -> -0.13811948 | BH7: =100*((DataScen!Z222-DataScen!J222)/DataScen!$G222) -> -0.13888844 | BI7: =100*(((DataScen!AA222-DataScen!AB222)-(DataScen!K222-DataScen!L222))/DataScen!$G222) -> 0.65652541 | BJ7: =BK7-BF7-BG7-BH7-BI7 -> -0.03184899 | BK7: =100*((DataScen!W222/DataScen!G222)-1) -> -0.23809847 | BM7: 45658 | BN7: =DataScen!R215 -> 1.260133 | BO7: =DataScen!AH215 -> 1.260133 | BQ7: 45658 | BR7: =DataScen!O215 -> 4.627143 | BS7: =DataScen!AE215 -> 4.627143 | BU7: 45658 | BV7: =100*((DataScen!M215/DataScen!M211)-1) -> 2.7973783 | BW7: =100*((DataScen!AC215/DataScen!AC211)-1) -> 2.7973783
A8: Expected effective interest rates on government debt (r) | B8: =AVERAGE(DataA!BK60:BK64) -> 3.9219808 | C8: =AVERAGE(DataA!BL60:BL64) -> 3.5225755 | D8: =AVERAGE(DataA!BM60:BM64) -> 1.2385339 | E8: =AVERAGE(DataA!BN60:BN64) -> 3.2698792 | F8: =AVERAGE(DataA!BO60:BO64) -> 2.3844976 | G8: =AVERAGE(DataA!BP60:BP64) -> 1.9092147 | H8: =AVERAGE(DataA!BQ60:BQ64) -> 1.6031096 | I8: =AVERAGE(DataA!BR60:BR64) -> 1.2243915 | ... U8: =AVERAGE(DataA!CD60:CD64) -> 2.3960688 | W8: =W4 -> 2025 | X8: =HLOOKUP(X$6,$X$2:$AD$4,3,FALSE) -> -1.5593717 | Y8: =HLOOKUP(Y$6,$X$2:$AD$4,3,FALSE) -> -2.07748 | Z8: =HLOOKUP(Z$6,$X$2:$AD$4,3,FALSE) -> -2.9476509 | AA8: =HLOOKUP(AA$6,$X$2:$AD$4,3,FALSE) -> -2.9942321 | AB8: =HLOOKUP(AB$6,$X$2:$AD$4,3,FALSE) -> -4.6502172 | AC8: =HLOOKUP(AC$6,$X$2:$AD$4,3,FALSE) -> -5.4069183 | AD8: =HLOOKUP(AD$6,$X$2:$AD$4,3,FALSE) -> -7.4168274 | AF8: =AF4 -> 2025 | AG8: =HLOOKUP(AG$6,$AF$2:$AM$4,3,FALSE) -> 216.98578 | AH8: =HLOOKUP(AH$6,$AF$2:$AM$4,3,FALSE) -> 149.72344 | AI8: =HLOOKUP(AI$6,$AF$2:$AM$4,3,FALSE) -> 139.4818 | AJ8: =HLOOKUP(AJ$6,$AF$2:$AM$4,3,FALSE) -> 127.41761 | AK8: =HLOOKUP(AK$6,$AF$2:$AM$4,3,FALSE) -> 107.05075 | AL8: =HLOOKUP(AL$6,$AF$2:$AM$4,3,FALSE) -> 101.22663 | AM8: =HLOOKUP(AM$6,$AF$2:$AM$4,3,FALSE) -> 58.235605 | AP8: =X13 -> UK | AQ8: =Y13 -> US | AR8: =Z13 -> Japan | AS8: =AA13 -> Germany | AT8: =AB13 -> France | AU8: =AC13 -> Italy | AV8: =AD13 -> Canada | AX8: 44287 | AY8: =DataQ!AI200 -> 1.208585 | AZ8: =DataQ!AJ200 -> -0.3946431 | BA8: =DataQ!AK200 -> -1.171975 | BB8: =DataQ!AL200 -> 0.08187032 | BD8: 46388 | BE8: Q1 27 | BF8: =100*((DataScen!X223-DataScen!H223)/DataScen!$G223) -> -0.67656064 | BG8: =100*((DataScen!Y223-DataScen!I223)/DataScen!$G223) -> -0.16016065 | BH8: =100*((DataScen!Z223-DataScen!J223)/DataScen!$G223) -> -0.13942103 | BI8: =100*(((DataScen!AA223-DataScen!AB223)-(DataScen!K223-DataScen!L223))/DataScen!$G223) -> 0.67702059 | BJ8: =BK8-BF8-BG8-BH8-BI8 -> -0.027875843 | BK8: =100*((DataScen!W223/DataScen!G223)-1) -> -0.32699757 | BM8: 45748 | BN8: =DataScen!R216 -> 1.335467 | BO8: =DataScen!AH216 -> 1.335467 | BQ8: 45748 | BR8: =DataScen!O216 -> 4.584677 | BS8: =DataScen!AE216 -> 4.584677 | BU8: 45748 | BV8: =100*((DataScen!M216/DataScen!M212)-1) -> 3.4869498 | BW8: =100*((DataScen!AC216/DataScen!AC212)-1) -> 3.4869498
A9: Expected annual average nominal GDP growth (g) | B9: =100*((DataA!AP64/DataA!AP59)^(1/5)-1) -> 3.702996 | C9: =100*((DataA!AQ64/DataA!AQ59)^(1/5)-1) -> 4.2135937 | D9: =100*((DataA!AR64/DataA!AR59)^(1/5)-1) -> 1.2375372 | E9: =100*((DataA!AS64/DataA!AS59)^(1/5)-1) -> 3.7440525 | F9: =100*((DataA!AT64/DataA!AT59)^(1/5)-1) -> 4.6409095 | G9: =100*((DataA!AU64/DataA!AU59)^(1/5)-1) -> 4.2067184 | H9: =100*((DataA!AV64/DataA!AV59)^(1/5)-1) -> 4.0481623 | I9: =100*((DataA!AW64/DataA!AW59)^(1/5)-1) -> 2.344035 | ... U9: =100*((DataA!BI64/DataA!BI59)^(1/5)-1) -> 3.0486017 | AO9: Budget deficit | AP9: =X14 -> -2.6955346 | AQ9: =Y14 -> -7.656273 | AR9: =Z14 -> -2.903139 | AS9: =AA14 -> -3.2496949 | AT9: =AB14 -> -4.4268838 | AU9: =AC14 -> -2.6555728 | AV9: =AD14 -> -2.8483556 | AX9: 44378 | AY9: =DataQ!AI201 -> 0.603907 | AZ9: =DataQ!AJ201 -> -0.8853215 | BA9: =DataQ!AK201 -> -1.291921 | BB9: =DataQ!AL201 -> 0.03307072 | BD9: 46478 | BE9: Q2 27 | BF9: =100*((DataScen!X224-DataScen!H224)/DataScen!$G224) -> -0.77637834 | BG9: =100*((DataScen!Y224-DataScen!I224)/DataScen!$G224) -> -0.18448691 | BH9: =100*((DataScen!Z224-DataScen!J224)/DataScen!$G224) -> -0.13588947 | BI9: =100*(((DataScen!AA224-DataScen!AB224)-(DataScen!K224-DataScen!L224))/DataScen!$G224) -> 0.69457243 | BJ9: =BK9-BF9-BG9-BH9-BI9 -> -0.036180711 | BK9: =100*((DataScen!W224/DataScen!G224)-1) -> -0.438363 | BM9: 45839 | BN9: =DataScen!R217 -> 1.348233 | BO9: =DataScen!AH217 -> 1.348233 | BQ9: 45839 | BR9: =DataScen!O217 -> 4.641692 | BS9: =DataScen!AE217 -> 4.641692 | BU9: 45839 | BV9: =100*((DataScen!M217/DataScen!M213)-1) -> 3.856525 | BW9: =100*((DataScen!AC217/DataScen!AC213)-1) -> 3.856525
AO10: Government debt | AP10: =AG14 -> 98.067934 | AQ10: =AH14 -> 149.4809 | AR10: =AI14 -> 219.82424 | AS10: =AJ14 -> 61.798331 | AT10: =AK14 -> 132.60008 | AU10: =AL14 -> 149.90342 | AV10: =AM14 -> 104.55796 | AX10: 44470 | AY10: =DataQ!AI202 -> 0.4656473 | AZ10: =DataQ!AJ202 -> -0.9625124 | BA10: =DataQ!AK202 -> -1.156949 | BB10: =DataQ!AL202 -> 0.03946926 | BD10: 46569 | BE10: Q3 27 | BF10: =100*((DataScen!X225-DataScen!H225)/DataScen!$G225) -> -0.86970041 | BG10: =100*((DataScen!Y225-DataScen!I225)/DataScen!$G225) -> -0.21376666 | BH10: =100*((DataScen!Z225-DataScen!J225)/DataScen!$G225) -> -0.13625463 | BI10: =100*(((DataScen!AA225-DataScen!AB225)-(DataScen!K225-DataScen!L225))/DataScen!$G225) -> 0.71867368 | BJ10: =BK10-BF10-BG10-BH10-BI10 -> -0.046460187 | BK10: =100*((DataScen!W225/DataScen!G225)-1) -> -0.5475082 | BM10: 45931 | BN10: =DataScen!R218 -> 1.344331 | BO10: =DataScen!AH218 -> 1.296493 | BQ10: 45931 | BR10: =DataScen!O218 -> 4.699989 | BS10: =DataScen!AE218 -> 4.799991 | BU10: 45931 | BV10: =100*((DataScen!M218/DataScen!M214)-1) -> 3.7064835 | BW10: =100*((DataScen!AC218/DataScen!AC214)-1) -> 4.0897471
W11: Budget deficit in 2030 | AF11: Gross government debt in 2030 | AX11: 44562 | AY11: =DataQ!AI203 -> 0.02904415 | AZ11: =DataQ!AJ203 -> -1.047033 | BA11: =DataQ!AK203 -> -1.003417 | BB11: =DataQ!AL203 -> 0.06193143 | BD11: 46661 | BE11: Q4 27 | BF11: =100*((DataScen!X226-DataScen!H226)/DataScen!$G226) -> -0.95574645 | BG11: =100*((DataScen!Y226-DataScen!I226)/DataScen!$G226) -> -0.23989025 | BH11: =100*((DataScen!Z226-DataScen!J226)/DataScen!$G226) -> -0.13656668 | BI11: =100*(((DataScen!AA226-DataScen!AB226)-(DataScen!K226-DataScen!L226))/DataScen!$G226) -> 0.74816288 | BJ11: =BK11-BF11-BG11-BH11-BI11 -> -0.054656969 | BK11: =100*((DataScen!W226/DataScen!G226)-1) -> -0.63869746 | BM11: 46023 | BN11: =DataScen!R219 -> 1.342767 | BO11: =DataScen!AH219 -> 1.200001 | BQ11: 46023 | BR11: =DataScen!O219 -> 4.67632 | BS11: =DataScen!AE219 -> 4.885736 | BU11: 46023 | BV11: =100*((DataScen!M219/DataScen!M215)-1) -> 3.3849465 | BW11: =100*((DataScen!AC219/DataScen!AC215)-1) -> 4.3103201
X12: =RANK(X14,$X$14:$AD$14) -> 2 | Y12: =RANK(Y14,$X$14:$AD$14) -> 7 | Z12: =RANK(Z14,$X$14:$AD$14) -> 4 | AA12: =RANK(AA14,$X$14:$AD$14) -> 5 | AB12: =RANK(AB14,$X$14:$AD$14) -> 6 | AC12: =RANK(AC14,$X$14:$AD$14) -> 1 | AD12: =RANK(AD14,$X$14:$AD$14) -> 3 | AG12: =RANK(AG14,$AG$14:$AM$14) -> 6 | AH12: =RANK(AH14,$AG$14:$AM$14) -> 3 | AI12: =RANK(AI14,$AG$14:$AM$14) -> 1 | AJ12: =RANK(AJ14,$AG$14:$AM$14) -> 7 | AK12: =RANK(AK14,$AG$14:$AM$14) -> 4 | AL12: =RANK(AL14,$AG$14:$AM$14) -> 2 | AM12: =RANK(AM14,$AG$14:$AM$14) -> 5 | AO12: 2026 | AP12: =X19&", "&$AO12 -> UK, 2026 | AQ12: =Y19&", "&$AO12 -> US, 2026 | AR12: =Z19&", "&$AO12 -> Japan, 2026 | AS12: =AA19&", "&$AO12 -> Germany, 2026 | AT12: =AB19&", "&$AO12 -> France, 2026 | AU12: =AC19&", "&$AO12 -> Italy, 2026 | AV12: =AD19&", "&$AO12 -> Canada, 2026 | AX12: 44652 | AY12: =DataQ!AI204 -> -1.077437 | AZ12: =DataQ!AJ204 -> -0.956619 | BA12: =DataQ!AK204 -> -0.8716033 | BB12: =DataQ!AL204 -> -0.07522872 | BD12: 46753 | BE12: Q1 28 | BF12: =100*((DataScen!X227-DataScen!H227)/DataScen!$G227) -> -1.0238964 | BG12: =100*((DataScen!Y227-DataScen!I227)/DataScen!$G227) -> -0.25701954 | BH12: =100*((DataScen!Z227-DataScen!J227)/DataScen!$G227) -> -0.1369281 | BI12: =100*(((DataScen!AA227-DataScen!AB227)-(DataScen!K227-DataScen!L227))/DataScen!$G227) -> 0.78435792 | BJ12: =BK12-BF12-BG12-BH12-BI12 -> -0.058887171 | BK12: =100*((DataScen!W227/DataScen!G227)-1) -> -0.69237328 | BM12: 46113 | BN12: =DataScen!R220 -> 1.341715 | BO12: =DataScen!AH220 -> 1.2 | BQ12: 46113 | BR12: =DataScen!O220 -> 4.596054 | BS12: =DataScen!AE220 -> 4.895629 | BU12: 46113 | BV12: =100*((DataScen!M220/DataScen!M216)-1) -> 2.5638267 | BW12: =100*((DataScen!AC220/DataScen!AC216)-1) -> 3.6692419
X13: UK | Y13: US | Z13: Japan | AA13: Germany | AB13: France | AC13: Italy | AD13: Canada | AG13: UK | AH13: US | AI13: Japan | AJ13: Germany | AK13: France | AL13: Italy | AM13: Canada | AP13: =X18 -> 5 | AQ13: =Y18 -> 7 | AR13: =Z18 -> 3 | AS13: =AA18 -> 1 | AT13: =AB18 -> 6 | AU13: =AC18 -> 2 | AV13: =AD18 -> 4 | AX13: 44743 | AY13: =DataQ!AI205 -> -2.220368 | AZ13: =DataQ!AJ205 -> -2.037583 | BA13: =DataQ!AK205 -> -1.227004 | BB13: =DataQ!AL205 -> -0.3186778 | BD13: 46844 | BE13: Q2 28 | BF13: =100*((DataScen!X228-DataScen!H228)/DataScen!$G228) -> -1.0631036 | BG13: =100*((DataScen!Y228-DataScen!I228)/DataScen!$G228) -> -0.26073834 | BH13: =100*((DataScen!Z228-DataScen!J228)/DataScen!$G228) -> -0.13272413 | BI13: =100*(((DataScen!AA228-DataScen!AB228)-(DataScen!K228-DataScen!L228))/DataScen!$G228) -> 0.81345065 | BJ13: =BK13-BF13-BG13-BH13-BI13 -> -0.056819361 | BK13: =100*((DataScen!W228/DataScen!G228)-1) -> -0.6999348 | BM13: 46204 | BN13: =DataScen!R221 -> 1.340664 | BO13: =DataScen!AH221 -> 1.200001 | BQ13: 46204 | BR13: =DataScen!O221 -> 4.470532 | BS13: =DataScen!AE221 -> 4.810573 | BU13: 46204 | BV13: =100*((DataScen!M221/DataScen!M217)-1) -> 2.633631 | BW13: =100*((DataScen!AC221/DataScen!AC217)-1) -> 3.8613041
W14: 2030 | X14: =100*('Data Q to A'!I65/'Data Q to A'!W65) -> -2.6955346 | Y14: =100*('Data Q to A'!J65/'Data Q to A'!X65) -> -7.656273 | Z14: =100*('Data Q to A'!K65/'Data Q to A'!Y65) -> -2.903139 | AA14: =100*('Data Q to A'!L65/'Data Q to A'!Z65) -> -3.2496949 | AB14: =100*('Data Q to A'!M65/'Data Q to A'!AA65) -> -4.4268838 | AC14: =100*('Data Q to A'!N65/'Data Q to A'!AB65) -> -2.6555728 | AD14: =100*('Data Q to A'!O65/'Data Q to A'!AC65) -> -2.8483556 | AF14: 2030 | AG14: =100*('Data Q to A'!P65/'Data Q to A'!W65) -> 98.067934 | AH14: =100*('Data Q to A'!Q65/'Data Q to A'!X65) -> 149.4809 | AI14: =100*('Data Q to A'!R65/'Data Q to A'!Y65) -> 219.82424 | AJ14: =100*('Data Q to A'!S65/'Data Q to A'!Z65) -> 61.798331 | AK14: =100*('Data Q to A'!T65/'Data Q to A'!AA65) -> 132.60008 | AL14: =100*('Data Q to A'!U65/'Data Q to A'!AB65) -> 149.90342 | AM14: =100*('Data Q to A'!V65/'Data Q to A'!AC65) -> 104.55796 | AO14: Budget deficit | AP14: =X20 -> -3.7166276 | AQ14: =Y20 -> -8.1781006 | AR14: =Z20 -> -3.5055345 | AS14: =AA20 -> -2.5893717 | AT14: =AB20 -> -5.6696548 | AU14: =AC20 -> -2.8028244 | AV14: =AD20 -> -3.5934936 | AX14: 44835 | AY14: =DataQ!AI206 -> -2.703098 | AZ14: =DataQ!AJ206 -> -2.388281 | BA14: =DataQ!AK206 -> -1.518819 | BB14: =DataQ!AL206 -> -0.5677544 | BD14: 46935 | BE14: Q3 28 | BF14: =100*((DataScen!X229-DataScen!H229)/DataScen!$G229) -> -1.085522 | BG14: =100*((DataScen!Y229-DataScen!I229)/DataScen!$G229) -> -0.25307282 | BH14: =100*((DataScen!Z229-DataScen!J229)/DataScen!$G229) -> -0.13301953 | BI14: =100*(((DataScen!AA229-DataScen!AB229)-(DataScen!K229-DataScen!L229))/DataScen!$G229) -> 0.83515391 | BJ14: =BK14-BF14-BG14-BH14-BI14 -> -0.048630213 | BK14: =100*((DataScen!W229/DataScen!G229)-1) -> -0.68509069 | BM14: 46296 | BN14: =DataScen!R222 -> 1.339612 | BO14: =DataScen!AH222 -> 1.2 | BQ14: 46296 | BR14: =DataScen!O222 -> 4.327124 | BS14: =DataScen!AE222 -> 4.693847 | BU14: 46296 | BV14: =100*((DataScen!M222/DataScen!M218)-1) -> 2.5655689 | BW14: =100*((DataScen!AC222/DataScen!AC218)-1) -> 3.5251201
AO15: Government debt | AP15: =AG20 -> 101.65539 | AQ15: =AH20 -> 141.75638 | AR15: =AI20 -> 217.02748 | AS15: =AJ20 -> 59.008035 | AT15: =AK20 -> 130.10576 | AU15: =AL20 -> 152.02351 | AV15: =AM20 -> 108.15788 | AX15: 44927 | AY15: =DataQ!AI207 -> -4.149235 | AZ15: =DataQ!AJ207 -> -3.100953 | BA15: =DataQ!AK207 -> -2.404197 | BB15: =DataQ!AL207 -> -0.6169774 | BD15: 47027 | BE15: Q4 28 | BF15: =100*((DataScen!X230-DataScen!H230)/DataScen!$G230) -> -1.0909165 | BG15: =100*((DataScen!Y230-DataScen!I230)/DataScen!$G230) -> -0.23630434 | BH15: =100*((DataScen!Z230-DataScen!J230)/DataScen!$G230) -> -0.13334326 | BI15: =100*(((DataScen!AA230-DataScen!AB230)-(DataScen!K230-DataScen!L230))/DataScen!$G230) -> 0.84854923 | BJ15: =BK15-BF15-BG15-BH15-BI15 -> -0.038921669 | BK15: =100*((DataScen!W230/DataScen!G230)-1) -> -0.6509365 | BM15: 46388 | BN15: =DataScen!R223 -> 1.338561 | BO15: =DataScen!AH223 -> 1.215806 | BQ15: 46388 | BR15: =DataScen!O223 -> 4.182954 | BS15: =DataScen!AE223 -> 4.59452 | BU15: 46388 | BV15: =100*((DataScen!M223/DataScen!M219)-1) -> 2.6026346 | BW15: =100*((DataScen!AC223/DataScen!AC219)-1) -> 3.0687322
AX16: 45017 | AY16: =DataQ!AI208 -> -3.705824 | AZ16: =DataQ!AJ208 -> -3.350867 | BA16: =DataQ!AK208 -> -2.505757 | BB16: =DataQ!AL208 -> -0.8306971 | BM16: 46478 | BN16: =DataScen!R224 -> 1.337874 | BO16: =DataScen!AH224 -> 1.229295 | BQ16: 46478 | BR16: =DataScen!O224 -> 4.048969 | BS16: =DataScen!AE224 -> 4.497655 | BU16: 46478 | BV16: =100*((DataScen!M224/DataScen!M220)-1) -> 2.5581675 | BW16: =100*((DataScen!AC224/DataScen!AC220)-1) -> 2.8930527
W17: Budget deficit in 2026 | AF17: Gross government debt in 2026 | AX17: 45108 | AY17: =DataQ!AI209 -> -3.457875 | AZ17: =DataQ!AJ209 -> -2.826797 | BA17: =DataQ!AK209 -> -2.697079 | BB17: =DataQ!AL209 -> -0.7969345 | BM17: 46569 | BN17: =DataScen!R225 -> 1.337551 | BO17: =DataScen!AH225 -> 1.24054 | BQ17: 46569 | BR17: =DataScen!O225 -> 3.9281 | BS17: =DataScen!AE225 -> 4.401708 | BU17: 46569 | BV17: =100*((DataScen!M225/DataScen!M221)-1) -> 2.4956712 | BW17: =100*((DataScen!AC225/DataScen!AC221)-1) -> 2.7723605
X18: =RANK(X20,$X$20:$AD$20) -> 5 | Y18: =RANK(Y20,$X$20:$AD$20) -> 7 | Z18: =RANK(Z20,$X$20:$AD$20) -> 3 | AA18: =RANK(AA20,$X$20:$AD$20) -> 1 | AB18: =RANK(AB20,$X$20:$AD$20) -> 6 | AC18: =RANK(AC20,$X$20:$AD$20) -> 2 | AD18: =RANK(AD20,$X$20:$AD$20) -> 4 | AG18: =RANK(AG20,$AG$20:$AM$20) -> 6 | AH18: =RANK(AH20,$AG$20:$AM$20) -> 3 | AI18: =RANK(AI20,$AG$20:$AM$20) -> 1 | AJ18: =RANK(AJ20,$AG$20:$AM$20) -> 7 | AK18: =RANK(AK20,$AG$20:$AM$20) -> 4 | AL18: =RANK(AL20,$AG$20:$AM$20) -> 2 | AM18: =RANK(AM20,$AG$20:$AM$20) -> 5 | AX18: 45200 | AY18: =DataQ!AI210 -> -3.401873 | AZ18: =DataQ!AJ210 -> -2.325372 | BA18: =DataQ!AK210 -> -2.819133 | BB18: =DataQ!AL210 -> -0.6955835 | BM18: 46661 | BN18: =DataScen!R226 -> 1.337228 | BO18: =DataScen!AH226 -> 1.249791 | BQ18: 46661 | BR18: =DataScen!O226 -> 3.829388 | BS18: =DataScen!AE226 -> 4.318294 | BU18: 46661 | BV18: =100*((DataScen!M226/DataScen!M222)-1) -> 2.387868 | BW18: =100*((DataScen!AC226/DataScen!AC222)-1) -> 2.5961719
X19: UK | Y19: US | Z19: Japan | AA19: Germany | AB19: France | AC19: Italy | AD19: Canada | AG19: UK | AH19: US | AI19: Japan | AJ19: Germany | AK19: France | AL19: Italy | AM19: Canada | AX19: 45292 | AY19: =DataQ!AI211 -> -3.181256 | AZ19: =DataQ!AJ211 -> -2.302343 | BA19: =DataQ!AK211 -> -2.815394 | BB19: =DataQ!AL211 -> -0.8791806
W20: 2026 | X20: =100*('Data Q to A'!I61/'Data Q to A'!W61) -> -3.7166276 | Y20: =100*('Data Q to A'!J61/'Data Q to A'!X61) -> -8.1781006 | Z20: =100*('Data Q to A'!K61/'Data Q to A'!Y61) -> -3.5055345 | AA20: =100*('Data Q to A'!L61/'Data Q to A'!Z61) -> -2.5893717 | AB20: =100*('Data Q to A'!M61/'Data Q to A'!AA61) -> -5.6696548 | AC20: =100*('Data Q to A'!N61/'Data Q to A'!AB61) -> -2.8028244 | AD20: =100*('Data Q to A'!O61/'Data Q to A'!AC61) -> -3.5934936 | AF20: 2030 | AG20: =100*('Data Q to A'!P61/'Data Q to A'!W61) -> 101.65539 | AH20: =100*('Data Q to A'!Q61/'Data Q to A'!X61) -> 141.75638 | AI20: =100*('Data Q to A'!R61/'Data Q to A'!Y61) -> 217.02748 | AJ20: =100*('Data Q to A'!S61/'Data Q to A'!Z61) -> 59.008035 | AK20: =100*('Data Q to A'!T61/'Data Q to A'!AA61) -> 130.10576 | AL20: =100*('Data Q to A'!U61/'Data Q to A'!AB61) -> 152.02351 | AM20: =100*('Data Q to A'!V61/'Data Q to A'!AC61) -> 108.15788 | AX20: 45383 | AY20: =DataQ!AI212 -> -2.509396 | AZ20: =DataQ!AJ212 -> -1.723849 | BA20: =DataQ!AK212 -> -2.279839 | BB20: =DataQ!AL212 -> -0.7389167
AX21: 45474 | AY21: =DataQ!AI213 -> -2.278532 | AZ21: =DataQ!AJ213 -> -1.775833 | BA21: =DataQ!AK213 -> -1.942126 | BB21: =DataQ!AL213 -> -0.7493371
AX22: 45566 | AY22: =DataQ!AI214 -> -1.373426 | AZ22: =DataQ!AJ214 -> -0.872263 | BA22: =DataQ!AK214 -> -1.38094 | BB22: =DataQ!AL214 -> -0.6486924
AX23: 45658 | AY23: =DataQ!AI215 -> -0.5658989 | AZ23: =DataQ!AJ215 -> -0.4111123 | BA23: =DataQ!AK215 -> -0.5560845 | BB23: =DataQ!AL215 -> -0.449419
AX24: 45748 | AY24: =DataQ!AI216 -> -0.2743466 | AZ24: =DataQ!AJ216 -> -0.4273167 | BA24: =DataQ!AK216 -> -0.1488339 | BB24: =DataQ!AL216 -> -0.4773142
AX25: 45839 | AY25: =DataQ!AI217 -> 0.02999306 | AZ25: =DataQ!AJ217 -> -0.447391 | BA25: =DataQ!AK217 -> 0.2001213 | BB25: =DataQ!AL217 -> -0.3751646

Sheet DataA
B1: =GMWA!$DB$2 -> OCT004A.db | C1: =$B$1 -> OCT004A.db | D1: =$B$1 -> OCT004A.db | E1: =$B$1 -> OCT004A.db | F1: =$B$1 -> OCT004A.db | G1: =$B$1 -> OCT004A.db | H1: =$B$1 -> OCT004A.db | I1: =$B$1 -> OCT004A.db | J1: =$B$1 -> OCT004A.db | ... BI1: =$B$1 -> OCT004A.db | CF1: FYs | CN1: CYs
B2: UK | C2: US | D2: Japan | E2: Canada | F2: Australia | G2: Denmark | H2: Sweden | I2: Switzerland | J2: S Korea | K2: Germany | L2: France | M2: Italy | N2: Spain | O2: Netherlands | P2: Belgium | Q2: Austria | R2: Finland | S2: Ireland | T2: Greece | U2: Portugal | V2: UK | W2: US | X2: Japan | Y2: Canada | Z2: Australia | AA2: Denmark | AB2: Sweden | AC2: Switzerland | AD2: S Korea | AE2: Germany | AF2: France | AG2: Italy | AH2: Spain | AI2: Netherlands | AJ2: Belgium | AK2: Austria | AL2: Finland | AM2: Ireland | AN2: Greece | AO2: Portugal | AP2: UK | AQ2: US | AR2: Japan | AS2: Canada | AT2: Australia | AU2: Denmark | AV2: Sweden | AW2: Switzerland | AX2: S Korea | AY2: Germany | AZ2: France | BA2: Italy | BB2: Spain | BC2: Netherlands | BD2: Belgium | BE2: Austria | BF2: Finland | BG2: Ireland | BH2: Greece | BI2: Portugal | BK2: =B2 -> UK | BL2: =C2 -> US | BM2: =D2 -> Japan | BN2: =E2 -> Canada | BO2: =F2 -> Australia | BP2: =G2 -> Denmark | BQ2: =H2 -> Sweden | BR2: =I2 -> Switzerland | ... CD2: =U2 -> Portugal
B3: GDIP | C3: GDIP | D3: GDIP | E3: GDIP | F3: GDIP | G3: GDIP | H3: GDIP | I3: GDIP | J3: GDIP | K3: GDIP | L3: GDIP | M3: GDIP | N3: GDIP | O3: GDIP | P3: GDIP | Q3: GDIP | R3: GDIP | S3: GDIP | T3: GDIP | U3: GDIP | V3: GGDBT | W3: GGDBT | X3: GGDBT | Y3: GGDBT | Z3: GGDBT | AA3: GGDBT | AB3: GGDBT | AC3: GGDBT | AD3: GGDBT | AE3: GGDBT | AF3: GGDBT | AG3: GGDBT | AH3: GGDBT | AI3: GGDBT | AJ3: GGDBT | AK3: GGDBT | AL3: GGDBT | AM3: GGDBT | AN3: GGDBT | AO3: GGDBT | AP3: GDP! | AQ3: GDP! | AR3: GDP! | AS3: GDP! | AT3: GDP! | AU3: GDP! | AV3: GDP! | AW3: GDP! | AX3: GDP! | AY3: GDP! | AZ3: GDP! | BA3: GDP! | BB3: GDP! | BC3: GDP! | BD3: GDP! | BE3: GDP! | BF3: GDP! | BG3: GDP! | BH3: GDP! | BI3: GDP! | BK3: GDIP/GGDBT | BL3: GDIP/GGDBT | BM3: GDIP/GGDBT | BN3: GDIP/GGDBT | BO3: GDIP/GGDBT | BP3: GDIP/GGDBT | BQ3: GDIP/GGDBT | BR3: GDIP/GGDBT | BS3: GDIP/GGDBT | BT3: GDIP/GGDBT | BU3: GDIP/GGDBT | BV3: GDIP/GGDBT | BW3: GDIP/GGDBT | BX3: GDIP/GGDBT | BY3: GDIP/GGDBT | BZ3: GDIP/GGDBT | CA3: GDIP/GGDBT | CB3: GDIP/GGDBT | CC3: GDIP/GGDBT | CD3: GDIP/GGDBT | CF3: =DataQ!H3 -> GDP | CG3: =DataQ!I3 -> GDP | CH3: =DataQ!J3 -> GDP | CI3: =DataQ!K3 -> GDP | CJ3: =DataQ!L3 -> GDP | CK3: =DataQ!M3 -> GDP | CL3: =DataQ!N3 -> GB | CN3: =DataQ!O3 -> GB | CO3: =DataQ!P3 -> GB | CP3: =DataQ!Q3 -> GB
B4: GBR | C4: USA | D4: JPN | E4: CAN | F4: AUS | G4: DNK | H4: SWE | I4: CHE | J4: KOR | K4: DEU | L4: FRA | M4: ITA | N4: ESP | O4: NLD | P4: BEL | Q4: AUT | R4: FIN | S4: IRL | T4: GRC | U4: PRT | V4: GBR | W4: USA | X4: JPN | Y4: CAN | Z4: AUS | AA4: DNK | AB4: SWE | AC4: CHE | AD4: KOR | AE4: DEU | AF4: FRA | AG4: ITA | AH4: ESP | AI4: NLD | AJ4: BEL | AK4: AUT | AL4: FIN | AM4: IRL | AN4: GRC | AO4: PRT | AP4: GBR | AQ4: USA | AR4: JPN | AS4: CAN | AT4: AUS | AU4: DNK | AV4: SWE | AW4: CHE | AX4: KOR | AY4: DEU | AZ4: FRA | BA4: ITA | BB4: ESP | BC4: NLD | BD4: BEL | BE4: AUT | BF4: FIN | BG4: IRL | BH4: GRC | BI4: PRT | BK4: =B4 -> GBR | BL4: =C4 -> USA | BM4: =D4 -> JPN | BN4: =E4 -> CAN | BO4: =F4 -> AUS | BP4: =G4 -> DNK | BQ4: =H4 -> SWE | BR4: =I4 -> CHE | ... CD4: =U4 -> PRT
B5: L | C5: L | D5: L | E5: L | F5: L | G5: L | H5: L | I5: L | J5: L | K5: L | L5: L | M5: L | N5: L | O5: L | P5: L | Q5: L | R5: L | S5: L | T5: L | U5: L | V5: L | W5: L | X5: L | Y5: L | Z5: L | AA5: L | AB5: L | AC5: L | AD5: L | AE5: L | AF5: L | AG5: L | AH5: L | AI5: L | AJ5: L | AK5: L | AL5: L | AM5: L | AN5: L | AO5: L | AP5: L | AQ5: L | AR5: L | AS5: L | AT5: L | AU5: L | AV5: L | AW5: L | AX5: L | AY5: L | AZ5: L | BA5: L | BB5: L | BC5: L | BD5: L | BE5: L | BF5: L | BG5: L | BH5: L | BI5: L
A6: =A94+5 -> 2065 | B6: {=_xlfn.CONCAT(INDEX(GMWA!$A$2:$DB$600,MATCH(1,(GMWA!$DA$2:$DA$600=B$3)*(GMWA!$CZ$2:$CZ$600=B$4)*(GMWA!$DB$2:$DB$600=B$1),0),$A6-1966),"0",(INDEX(GMWA!$A$2:$DB$600,MATCH(1,(GMWA!$DA$2:$DA$600=B$3)*(GMWA!$CZ$2:$CZ$600=B$4)*(GMWA!$DB$2:$DB$600=B$1),0),$A6-1965)))} -> 202502 | C6: {=_xlfn.CONCAT(INDEX(GMWA!$A$2:$DB$600,MATCH(1,(GMWA!$DA$2:$DA$600=C$3)*(GMWA!$CZ$2:$CZ$600=C$4)*(GMWA!$DB$2:$DB$600=C$1),0),$A6-1966),"0",(INDEX(GMWA!$A$2:$DB$600,MATCH(1,(GMWA!$DA$2:$DA$600=C$3)*(GMWA!$CZ$2:$CZ$600=C$4)*(GMWA!$DB$2:$DB$600=C$1),0),$A6-1965)))} -> 202502 | D6: {=_xlfn.CONCAT(INDEX(GMWA!$A$2:$DB$600,MATCH(1,(GMWA!$DA$2:$DA$600=D$3)*(GMWA!$CZ$2:$CZ$600=D$4)*(GMWA!$DB$2:$DB$600=D$1),0),$A6-1966),"0",(INDEX(GMWA!$A$2:$DB$600,MATCH(1,(GMWA!$DA$2:$DA$600=D$3)*(GMWA!$CZ$2:$CZ$600=D$4)*(GMWA!$DB$2:$DB$600=D$1),0),$A6-1965)))} -> 202402 | E6: {=_xlfn.CONCAT(INDEX(GMWA!$A$2:$DB$600,MATCH(1,(GMWA!$DA$2:$DA$600=E$3)*(GMWA!$CZ$2:$CZ$600=E$4)*(GMWA!$DB$2:$DB$600=E$1),0),$A6-1966),"0",(INDEX(GMWA!$A$2:$DB$600,MATCH(1,(GMWA!$DA$2:$DA$600=E$3)*(GMWA!$CZ$2:$CZ$600=E$4)*(GMWA!$DB$2:$DB$600=E$1),0),$A6-1965)))} -> 202502 | F6: {=_xlfn.CONCAT(INDEX(GMWA!$A$2:$DB$600,MATCH(1,(GMWA!$DA$2:$DA$600=F$3)*(GMWA!$CZ$2:$CZ$600=F$4)*(GMWA!$DB$2:$DB$600=F$1),0),$A6-1966),"0",(INDEX(GMWA!$A$2:$DB$600,MATCH(1,(GMWA!$DA$2:$DA$600=F$3)*(GMWA!$CZ$2:$CZ$600=F$4)*(GMWA!$DB$2:$DB$600=F$1),0),$A6-1965)))} -> 202502 | G6: {=_xlfn.CONCAT(INDEX(GMWA!$A$2:$DB$600,MATCH(1,(GMWA!$DA$2:$DA$600=G$3)*(GMWA!$CZ$2:$CZ$600=G$4)*(GMWA!$DB$2:$DB$600=G$1),0),$A6-1966),"0",(INDEX(GMWA!$A$2:$DB$600,MATCH(1,(GMWA!$DA$2:$DA$600=G$3)*(GMWA!$CZ$2:$CZ$600=G$4)*(GMWA!$DB$2:$DB$600=G$1),0),$A6-1965)))} -> 202501 | H6: {=_xlfn.CONCAT(INDEX(GMWA!$A$2:$DB$600,MATCH(1,(GMWA!$DA$2:$DA$600=H$3)*(GMWA!$CZ$2:$CZ$600=H$4)*(GMWA!$DB$2:$DB$600=H$1),0),$A6-1966),"0",(INDEX(GMWA!$A$2:$DB$600,MATCH(1,(GMWA!$DA$2:$DA$600=H$3)*(GMWA!$CZ$2:$CZ$600=H$4)*(GMWA!$DB$2:$DB$600=H$1),0),$A6-1965)))} -> 202501 | I6: {=_xlfn.CONCAT(INDEX(GMWA!$A$2:$DB$600,MATCH(1,(GMWA!$DA$2:$DA$600=I$3)*(GMWA!$CZ$2:$CZ$600=I$4)*(GMWA!$DB$2:$DB$600=I$1),0),$A6-1966),"0",(INDEX(GMWA!$A$2:$DB$600,MATCH(1,(GMWA!$DA$2:$DA$600=I$3)*(GMWA!$CZ$2:$CZ$600=I$4)*(GMWA!$DB$2:$DB$600=I$1),0),$A6-1965)))} -> 202004 | ... BI6: {=_xlfn.CONCAT(INDEX(GMWA!$A$2:$DB$600,MATCH(1,(GMWA!$DA$2:$DA$600=BI$3)*(GMWA!$CZ$2:$CZ$600=BI$4)*(GMWA!$DB$2:$DB$600=BI$1),0),$A6-1966),"0",(INDEX(GMWA!$A$2:$DB$600,MATCH(1,(GMWA!$DA$2:$DA$600=BI$3)*(GMWA!$CZ$2:$CZ$600=BI$4)*(GMWA!$DB$2:$DB$600=BI$1),0),$A6-1965)))} -> 202502 | CF6: =DataQ!H6 -> 202502 | CG6: =DataQ!I6 -> 202502 | CH6: =DataQ!J6 -> 202502 | CI6: =DataQ!K6 -> 202502 | CJ6: =DataQ!L6 -> 202502 | CK6: =DataQ!M6 -> 202502 | CL6: =DataQ!N6 -> 202502 | CN6: =DataQ!O6 -> 202502 | CO6: =DataQ!P6 -> 202402 | CP6: =DataQ!Q6 -> 202502
A7: 1973 | B7: {=INDEX(GMWA!$A$2:$DB$600,MATCH(1,(GMWA!$DA$2:$DA$600=B$3)*(GMWA!$CZ$2:$CZ$600=B$4)*(GMWA!$DB$2:$DB$600=B$1),0),$A7-1966)} -> 3087 | C7: {=INDEX(GMWA!$A$2:$DB$600,MATCH(1,(GMWA!$DA$2:$DA$600=C$3)*(GMWA!$CZ$2:$CZ$600=C$4)*(GMWA!$DB$2:$DB$600=C$1),0),$A7-1966)} -> 61.95 | D7: {=INDEX(GMWA!$A$2:$DB$600,MATCH(1,(GMWA!$DA$2:$DA$600=D$3)*(GMWA!$CZ$2:$CZ$600=D$4)*(GMWA!$DB$2:$DB$600=D$1),0),$A7-1966)} -> 922.9716 | E7: {=INDEX(GMWA!$A$2:$DB$600,MATCH(1,(GMWA!$DA$2:$DA$600=E$3)*(GMWA!$CZ$2:$CZ$600=E$4)*(GMWA!$DB$2:$DB$600=E$1),0),$A7-1966)} -> 4910 | F7: {=INDEX(GMWA!$A$2:$DB$600,MATCH(1,(GMWA!$DA$2:$DA$600=F$3)*(GMWA!$CZ$2:$CZ$600=F$4)*(GMWA!$DB$2:$DB$600=F$1),0),$A7-1966)} -> 738.1701 | G7: {=INDEX(GMWA!$A$2:$DB$600,MATCH(1,(GMWA!$DA$2:$DA$600=G$3)*(GMWA!$CZ$2:$CZ$600=G$4)*(GMWA!$DB$2:$DB$600=G$1),0),$A7-1966)} -> 1.986917 | H7: {=INDEX(GMWA!$A$2:$DB$600,MATCH(1,(GMWA!$DA$2:$DA$600=H$3)*(GMWA!$CZ$2:$CZ$600=H$4)*(GMWA!$DB$2:$DB$600=H$1),0),$A7-1966)} -> 3553.037 | I7: {=INDEX(GMWA!$A$2:$DB$600,MATCH(1,(GMWA!$DA$2:$DA$600=I$3)*(GMWA!$CZ$2:$CZ$600=I$4)*(GMWA!$DB$2:$DB$600=I$1),0),$A7-1966)} -> 1.915308 | ... BI7: {=INDEX(GMWA!$A$2:$DB$600,MATCH(1,(GMWA!$DA$2:$DA$600=BI$3)*(GMWA!$CZ$2:$CZ$600=BI$4)*(GMWA!$DB$2:$DB$600=BI$1),0),$A7-1966)} -> 23.33603 | BK7: =100*(B7/V7) -> 8.5822878 | BL7: =100*(C7/W7) -> 5.3458308 | BM7: =100*(D7/X7) -> 5.1843599 | BN7: =100*(E7/Y7) -> 7.5628052 | BO7: =100*(F7/Z7) -> 73817010 | BP7: =100*(G7/AA7) -> 1.1897707 | BQ7: =100*(H7/AB7) -> 5.1876507 | BR7: =100*(I7/AC7) -> 1.8912737 | ... CD7: =100*(U7/AO7) -> 1.139807 | CF7: =SUMIF(DataQ!$C:$C,DataA!$A7,DataQ!H:H) -> 6116.05 | CG7: =SUMIF(DataQ!$C:$C,DataA!$A7,DataQ!I:I) -> 210897 | CH7: =SUMIF(DataQ!$C:$C,DataA!$A7,DataQ!J:J) -> 1564.34 | CI7: =SUMIF(DataQ!$C:$C,DataA!$A7,DataQ!K:K) -> 1013.889 | CJ7: =SUMIF(DataQ!$C:$C,DataA!$A7,DataQ!L:L) -> 954.3197 | CK7: =AVERAGEIF(DataQ!$C:$C,DataA!$A7,DataQ!M:M) -> 178599.27 | CL7: =SUMIF(DataQ!$C:$C,DataA!$A7,DataQ!N:N) -> -3383 | CN7: =SUMIF(DataQ!$B:$B,DataA!$A7,DataQ!O:O) -> -44.59125 | CO7: =SUMIF(DataQ!$B:$B,DataA!$A7,DataQ!P:P) -> -2130.75 | CP7: =SUMIF(DataQ!$B:$B,DataA!$A7,DataQ!Q:Q) -> -23.045528
A8: =+A7+1 -> 1974 | B8: {=INDEX(GMWA!$A$2:$DB$600,MATCH(1,(GMWA!$DA$2:$DA$600=B$3)*(GMWA!$CZ$2:$CZ$600=B$4)*(GMWA!$DB$2:$DB$600=B$1),0),$A8-1966)} -> 4131 | C8: {=INDEX(GMWA!$A$2:$DB$600,MATCH(1,(GMWA!$DA$2:$DA$600=C$3)*(GMWA!$CZ$2:$CZ$600=C$4)*(GMWA!$DB$2:$DB$600=C$1),0),$A8-1966)} -> 69.55 | D8: {=INDEX(GMWA!$A$2:$DB$600,MATCH(1,(GMWA!$DA$2:$DA$600=D$3)*(GMWA!$CZ$2:$CZ$600=D$4)*(GMWA!$DB$2:$DB$600=D$1),0),$A8-1966)} -> 1196.62 | E8: {=INDEX(GMWA!$A$2:$DB$600,MATCH(1,(GMWA!$DA$2:$DA$600=E$3)*(GMWA!$CZ$2:$CZ$600=E$4)*(GMWA!$DB$2:$DB$600=E$1),0),$A8-1966)} -> 5488 | F8: {=INDEX(GMWA!$A$2:$DB$600,MATCH(1,(GMWA!$DA$2:$DA$600=F$3)*(GMWA!$CZ$2:$CZ$600=F$4)*(GMWA!$DB$2:$DB$600=F$1),0),$A8-1966)} -> 807 | G8: {=INDEX(GMWA!$A$2:$DB$600,MATCH(1,(GMWA!$DA$2:$DA$600=G$3)*(GMWA!$CZ$2:$CZ$600=G$4)*(GMWA!$DB$2:$DB$600=G$1),0),$A8-1966)} -> 2.163271 | H8: {=INDEX(GMWA!$A$2:$DB$600,MATCH(1,(GMWA!$DA$2:$DA$600=H$3)*(GMWA!$CZ$2:$CZ$600=H$4)*(GMWA!$DB$2:$DB$600=H$1),0),$A8-1966)} -> 4397.595 | I8: {=INDEX(GMWA!$A$2:$DB$600,MATCH(1,(GMWA!$DA$2:$DA$600=I$3)*(GMWA!$CZ$2:$CZ$600=I$4)*(GMWA!$DB$2:$DB$600=I$1),0),$A8-1966)} -> 2.263996 | ... BI8: {=INDEX(GMWA!$A$2:$DB$600,MATCH(1,(GMWA!$DA$2:$DA$600=BI$3)*(GMWA!$CZ$2:$CZ$600=BI$4)*(GMWA!$DB$2:$DB$600=BI$1),0),$A8-1966)} -> 23.33603 | BK8: =100*(B8/V8) -> 8.4599839 | BL8: =100*(C8/W8) -> 5.5564033 | BM8: =100*(D8/X8) -> 7.2373291 | BN8: =100*(E8/Y8) -> 7.4126101 | BO8: =100*(F8/Z8) -> 80700000 | BP8: =100*(G8/AA8) -> 1.2953719 | BQ8: =100*(H8/AB8) -> 5.6119733 | BR8: =100*(I8/AC8) -> 2.1942007 | ... CD8: =100*(U8/AO8) -> 0.96902159 | CF8: =SUMIF(DataQ!$C:$C,DataA!$A8,DataQ!H:H) -> 6038.325 | CG8: =SUMIF(DataQ!$C:$C,DataA!$A8,DataQ!I:I) -> 210067.04 | CH8: =SUMIF(DataQ!$C:$C,DataA!$A8,DataQ!J:J) -> 1563.89 | CI8: =SUMIF(DataQ!$C:$C,DataA!$A8,DataQ!K:K) -> 1041.055 | CJ8: =SUMIF(DataQ!$C:$C,DataA!$A8,DataQ!L:L) -> 975.1377 | CK8: =AVERAGEIF(DataQ!$C:$C,DataA!$A8,DataQ!M:M) -> 182714.27 | CL8: =SUMIF(DataQ!$C:$C,DataA!$A8,DataQ!N:N) -> -5592 | CN8: =SUMIF(DataQ!$B:$B,DataA!$A8,DataQ!O:O) -> -59.765 | CO8: =SUMIF(DataQ!$B:$B,DataA!$A8,DataQ!P:P) -> -2482.25 | CP8: =SUMIF(DataQ!$B:$B,DataA!$A8,DataQ!Q:Q) -> -36.381582
A9: =+A8+1 -> 1975 | B9: {=INDEX(GMWA!$A$2:$DB$600,MATCH(1,(GMWA!$DA$2:$DA$600=B$3)*(GMWA!$CZ$2:$CZ$600=B$4)*(GMWA!$DB$2:$DB$600=B$1),0),$A9-1966)} -> 4939 | C9: {=INDEX(GMWA!$A$2:$DB$600,MATCH(1,(GMWA!$DA$2:$DA$600=C$3)*(GMWA!$CZ$2:$CZ$600=C$4)*(GMWA!$DB$2:$DB$600=C$1),0),$A9-1966)} -> 77.425 | D9: {=INDEX(GMWA!$A$2:$DB$600,MATCH(1,(GMWA!$DA$2:$DA$600=D$3)*(GMWA!$CZ$2:$CZ$600=D$4)*(GMWA!$DB$2:$DB$600=D$1),0),$A9-1966)} -> 1681.87 | E9: {=INDEX(GMWA!$A$2:$DB$600,MATCH(1,(GMWA!$DA$2:$DA$600=E$3)*(GMWA!$CZ$2:$CZ$600=E$4)*(GMWA!$DB$2:$DB$600=E$1),0),$A9-1966)} -> 6639 | F9: {=INDEX(GMWA!$A$2:$DB$600,MATCH(1,(GMWA!$DA$2:$DA$600=F$3)*(GMWA!$CZ$2:$CZ$600=F$4)*(GMWA!$DB$2:$DB$600=F$1),0),$A9-1966)} -> 916 | G9: {=INDEX(GMWA!$A$2:$DB$600,MATCH(1,(GMWA!$DA$2:$DA$600=G$3)*(GMWA!$CZ$2:$CZ$600=G$4)*(GMWA!$DB$2:$DB$600=G$1),0),$A9-1966)} -> 2.374895 | H9: {=INDEX(GMWA!$A$2:$DB$600,MATCH(1,(GMWA!$DA$2:$DA$600=H$3)*(GMWA!$CZ$2:$CZ$600=H$4)*(GMWA!$DB$2:$DB$600=H$1),0),$A9-1966)} -> 5346.4 | I9: {=INDEX(GMWA!$A$2:$DB$600,MATCH(1,(GMWA!$DA$2:$DA$600=I$3)*(GMWA!$CZ$2:$CZ$600=I$4)*(GMWA!$DB$2:$DB$600=I$1),0),$A9-1966)} -> 2.686347 | ... BI9: {=INDEX(GMWA!$A$2:$DB$600,MATCH(1,(GMWA!$DA$2:$DA$600=BI$3)*(GMWA!$CZ$2:$CZ$600=BI$4)*(GMWA!$DB$2:$DB$600=BI$1),0),$A9-1966)} -> 23.33603 | BK9: =100*(B9/V9) -> 7.883983 | BL9: =100*(C9/W9) -> 5.4832482 | BM9: =100*(D9/X9) -> 5.7552955 | BN9: =100*(E9/Y9) -> 8.0669267 | BO9: =100*(F9/Z9) -> 91600000 | BP9: =100*(G9/AA9) -> 1.4220928 | BQ9: =100*(H9/AB9) -> 5.9776213 | BR9: =100*(I9/AC9) -> 2.5110529 | ... CD9: =100*(U9/AO9) -> 0.60098917 | CF9: =SUMIF(DataQ!$C:$C,DataA!$A9,DataQ!H:H) -> 6152.5 | CG9: =SUMIF(DataQ!$C:$C,DataA!$A9,DataQ!I:I) -> 218644.29 | CH9: =SUMIF(DataQ!$C:$C,DataA!$A9,DataQ!J:J) -> 1571.03 | CI9: =SUMIF(DataQ!$C:$C,DataA!$A9,DataQ!K:K) -> 1041.161 | CJ9: =SUMIF(DataQ!$C:$C,DataA!$A9,DataQ!L:L) -> 971.922 | CK9: =AVERAGEIF(DataQ!$C:$C,DataA!$A9,DataQ!M:M) -> 188382.77 | CL9: =SUMIF(DataQ!$C:$C,DataA!$A9,DataQ!N:N) -> -7651 | CN9: =SUMIF(DataQ!$B:$B,DataA!$A9,DataQ!O:O) -> -128.606 | CO9: =SUMIF(DataQ!$B:$B,DataA!$A9,DataQ!P:P) -> -7342 | CP9: =SUMIF(DataQ!$B:$B,DataA!$A9,DataQ!Q:Q) -> -62.44885
A10: =+A9+1 -> 1976 | B10: {=INDEX(GMWA!$A$2:$DB$600,MATCH(1,(GMWA!$DA$2:$DA$600=B$3)*(GMWA!$CZ$2:$CZ$600=B$4)*(GMWA!$DB$2:$DB$600=B$1),0),$A10-1966)} -> 6380 | C10: {=INDEX(GMWA!$A$2:$DB$600,MATCH(1,(GMWA!$DA$2:$DA$600=C$3)*(GMWA!$CZ$2:$CZ$600=C$4)*(GMWA!$DB$2:$DB$600=C$1),0),$A10-1966)} -> 86.725 | D10: {=INDEX(GMWA!$A$2:$DB$600,MATCH(1,(GMWA!$DA$2:$DA$600=D$3)*(GMWA!$CZ$2:$CZ$600=D$4)*(GMWA!$DB$2:$DB$600=D$1),0),$A10-1966)} -> 2416.859 | E10: {=INDEX(GMWA!$A$2:$DB$600,MATCH(1,(GMWA!$DA$2:$DA$600=E$3)*(GMWA!$CZ$2:$CZ$600=E$4)*(GMWA!$DB$2:$DB$600=E$1),0),$A10-1966)} -> 8242 | F10: {=INDEX(GMWA!$A$2:$DB$600,MATCH(1,(GMWA!$DA$2:$DA$600=F$3)*(GMWA!$CZ$2:$CZ$600=F$4)*(GMWA!$DB$2:$DB$600=F$1),0),$A10-1966)} -> 1191 | G10: {=INDEX(GMWA!$A$2:$DB$600,MATCH(1,(GMWA!$DA$2:$DA$600=G$3)*(GMWA!$CZ$2:$CZ$600=G$4)*(GMWA!$DB$2:$DB$600=G$1),0),$A10-1966)} -> 3.083249 | H10: {=INDEX(GMWA!$A$2:$DB$600,MATCH(1,(GMWA!$DA$2:$DA$600=H$3)*(GMWA!$CZ$2:$CZ$600=H$4)*(GMWA!$DB$2:$DB$600=H$1),0),$A10-1966)} -> 5906.224 | I10: {=INDEX(GMWA!$A$2:$DB$600,MATCH(1,(GMWA!$DA$2:$DA$600=I$3)*(GMWA!$CZ$2:$CZ$600=I$4)*(GMWA!$DB$2:$DB$600=I$1),0),$A10-1966)} -> 2.877871 | ... BI10: {=INDEX(GMWA!$A$2:$DB$600,MATCH(1,(GMWA!$DA$2:$DA$600=BI$3)*(GMWA!$CZ$2:$CZ$600=BI$4)*(GMWA!$DB$2:$DB$600=BI$1),0),$A10-1966)} -> 23.33603 | BK10: =100*(B10/V10) -> 8.6917724 | BL10: =100*(C10/W10) -> 5.7000533 | BM10: =100*(D10/X10) -> 5.4821463 | BN10: =100*(E10/Y10) -> 9.0138565 | BO10: =100*(F10/Z10) -> 119100000 | BP10: =100*(G10/AA10) -> 1.8462569 | BQ10: =100*(H10/AB10) -> 6.2582121 | BR10: =100*(I10/AC10) -> 2.6295615 | ... CD10: =100*(U10/AO10) -> 0.39665304 | CF10: =SUMIF(DataQ!$C:$C,DataA!$A10,DataQ!H:H) -> 6438.45 | CG10: =SUMIF(DataQ!$C:$C,DataA!$A10,DataQ!I:I) -> 226948.07 | CH10: =SUMIF(DataQ!$C:$C,DataA!$A10,DataQ!J:J) -> 1644.12 | CI10: =SUMIF(DataQ!$C:$C,DataA!$A10,DataQ!K:K) -> 1090.008 | CJ10: =SUMIF(DataQ!$C:$C,DataA!$A10,DataQ!L:L) -> 1039.9587 | CK10: =AVERAGEIF(DataQ!$C:$C,DataA!$A10,DataQ!M:M) -> 198585.85 | CL10: =SUMIF(DataQ!$C:$C,DataA!$A10,DataQ!N:N) -> -7004 | CN10: =SUMIF(DataQ!$B:$B,DataA!$A10,DataQ!O:O) -> -104.50225 | CO10: =SUMIF(DataQ!$B:$B,DataA!$A10,DataQ!P:P) -> -9301 | CP10: =SUMIF(DataQ!$B:$B,DataA!$A10,DataQ!Q:Q) -> -53.17428
A11: =+A10+1 -> 1977 | B11: {=INDEX(GMWA!$A$2:$DB$600,MATCH(1,(GMWA!$DA$2:$DA$600=B$3)*(GMWA!$CZ$2:$CZ$600=B$4)*(GMWA!$DB$2:$DB$600=B$1),0),$A11-1966)} -> 7333 | C11: {=INDEX(GMWA!$A$2:$DB$600,MATCH(1,(GMWA!$DA$2:$DA$600=C$3)*(GMWA!$CZ$2:$CZ$600=C$4)*(GMWA!$DB$2:$DB$600=C$1),0),$A11-1966)} -> 95.75 | D11: {=INDEX(GMWA!$A$2:$DB$600,MATCH(1,(GMWA!$DA$2:$DA$600=D$3)*(GMWA!$CZ$2:$CZ$600=D$4)*(GMWA!$DB$2:$DB$600=D$1),0),$A11-1966)} -> 3374.968 | E11: {=INDEX(GMWA!$A$2:$DB$600,MATCH(1,(GMWA!$DA$2:$DA$600=E$3)*(GMWA!$CZ$2:$CZ$600=E$4)*(GMWA!$DB$2:$DB$600=E$1),0),$A11-1966)} -> 9432 | F11: {=INDEX(GMWA!$A$2:$DB$600,MATCH(1,(GMWA!$DA$2:$DA$600=F$3)*(GMWA!$CZ$2:$CZ$600=F$4)*(GMWA!$DB$2:$DB$600=F$1),0),$A11-1966)} -> 1532 | G11: {=INDEX(GMWA!$A$2:$DB$600,MATCH(1,(GMWA!$DA$2:$DA$600=G$3)*(GMWA!$CZ$2:$CZ$600=G$4)*(GMWA!$DB$2:$DB$600=G$1),0),$A11-1966)} -> 4.659654 | H11: {=INDEX(GMWA!$A$2:$DB$600,MATCH(1,(GMWA!$DA$2:$DA$600=H$3)*(GMWA!$CZ$2:$CZ$600=H$4)*(GMWA!$DB$2:$DB$600=H$1),0),$A11-1966)} -> 7658.689 | I11: {=INDEX(GMWA!$A$2:$DB$600,MATCH(1,(GMWA!$DA$2:$DA$600=I$3)*(GMWA!$CZ$2:$CZ$600=I$4)*(GMWA!$DB$2:$DB$600=I$1),0),$A11-1966)} -> 3.113591 | ... BI11: {=INDEX(GMWA!$A$2:$DB$600,MATCH(1,(GMWA!$DA$2:$DA$600=BI$3)*(GMWA!$CZ$2:$CZ$600=BI$4)*(GMWA!$DB$2:$DB$600=BI$1),0),$A11-1966)} -> 23.33603 | BK11: =100*(B11/V11) -> 8.7542007 | BL11: =100*(C11/W11) -> 5.8415776 | BM11: =100*(D11/X11) -> 5.7274684 | BN11: =100*(E11/Y11) -> 9.0254918 | BO11: =100*(F11/Z11) -> 153200000 | BP11: =100*(G11/AA11) -> 2.790212 | BQ11: =100*(H11/AB11) -> 6.8751057 | BR11: =100*(I11/AC11) -> 2.8045341 | ... CD11: =100*(U11/AO11) -> 0.28413531 | CF11: =SUMIF(DataQ!$C:$C,DataA!$A11,DataQ!H:H) -> 6749.975 | CG11: =SUMIF(DataQ!$C:$C,DataA!$A11,DataQ!I:I) -> 237285.12 | CH11: =SUMIF(DataQ!$C:$C,DataA!$A11,DataQ!J:J) -> 1695.09 | CI11: =SUMIF(DataQ!$C:$C,DataA!$A11,DataQ!K:K) -> 1125.804 | CJ11: =SUMIF(DataQ!$C:$C,DataA!$A11,DataQ!L:L) -> 1051.1927 | CK11: =AVERAGEIF(DataQ!$C:$C,DataA!$A11,DataQ!M:M) -> 205230.4 | CL11: =SUMIF(DataQ!$C:$C,DataA!$A11,DataQ!N:N) -> -6424 | CN11: =SUMIF(DataQ!$B:$B,DataA!$A11,DataQ!O:O) -> -88.151 | CO11: =SUMIF(DataQ!$B:$B,DataA!$A11,DataQ!P:P) -> -10191.75 | CP11: =SUMIF(DataQ!$B:$B,DataA!$A11,DataQ!Q:Q) -> -44.70044
A12: =+A11+1 -> 1978 | B12: {=INDEX(GMWA!$A$2:$DB$600,MATCH(1,(GMWA!$DA$2:$DA$600=B$3)*(GMWA!$CZ$2:$CZ$600=B$4)*(GMWA!$DB$2:$DB$600=B$1),0),$A12-1966)} -> 8160 | C12: {=INDEX(GMWA!$A$2:$DB$600,MATCH(1,(GMWA!$DA$2:$DA$600=C$3)*(GMWA!$CZ$2:$CZ$600=C$4)*(GMWA!$DB$2:$DB$600=C$1),0),$A12-1966)} -> 112.45 | D12: {=INDEX(GMWA!$A$2:$DB$600,MATCH(1,(GMWA!$DA$2:$DA$600=D$3)*(GMWA!$CZ$2:$CZ$600=D$4)*(GMWA!$DB$2:$DB$600=D$1),0),$A12-1966)} -> 4369.668 | E12: {=INDEX(GMWA!$A$2:$DB$600,MATCH(1,(GMWA!$DA$2:$DA$600=E$3)*(GMWA!$CZ$2:$CZ$600=E$4)*(GMWA!$DB$2:$DB$600=E$1),0),$A12-1966)} -> 11741 | F12: {=INDEX(GMWA!$A$2:$DB$600,MATCH(1,(GMWA!$DA$2:$DA$600=F$3)*(GMWA!$CZ$2:$CZ$600=F$4)*(GMWA!$DB$2:$DB$600=F$1),0),$A12-1966)} -> 1796 | G12: {=INDEX(GMWA!$A$2:$DB$600,MATCH(1,(GMWA!$DA$2:$DA$600=G$3)*(GMWA!$CZ$2:$CZ$600=G$4)*(GMWA!$DB$2:$DB$600=G$1),0),$A12-1966)} -> 6.209607 | H12: {=INDEX(GMWA!$A$2:$DB$600,MATCH(1,(GMWA!$DA$2:$DA$600=H$3)*(GMWA!$CZ$2:$CZ$600=H$4)*(GMWA!$DB$2:$DB$600=H$1),0),$A12-1966)} -> 9006.922 | I12: {=INDEX(GMWA!$A$2:$DB$600,MATCH(1,(GMWA!$DA$2:$DA$600=I$3)*(GMWA!$CZ$2:$CZ$600=I$4)*(GMWA!$DB$2:$DB$600=I$1),0),$A12-1966)} -> 3.064492 | ... BI12: {=INDEX(GMWA!$A$2:$DB$600,MATCH(1,(GMWA!$DA$2:$DA$600=BI$3)*(GMWA!$CZ$2:$CZ$600=BI$4)*(GMWA!$DB$2:$DB$600=BI$1),0),$A12-1966)} -> 23.33603 | BK12: =100*(B12/V12) -> 8.6681716 | BL12: =100*(C12/W12) -> 6.3230496 | BM12: =100*(D12/X12) -> 5.3183564 | BN12: =100*(E12/Y12) -> 9.5232302 | BO12: =100*(F12/Z12) -> 179600000 | BP12: =100*(G12/AA12) -> 3.7183275 | BQ12: =100*(H12/AB12) -> 6.2798084 | BR12: =100*(I12/AC12) -> 2.7169626 | ... CD12: =100*(U12/AO12) -> 0.20127852 | CF12: =SUMIF(DataQ!$C:$C,DataA!$A12,DataQ!H:H) -> 7163.325 | CG12: =SUMIF(DataQ!$C:$C,DataA!$A12,DataQ!I:I) -> 250526.42 | CH12: =SUMIF(DataQ!$C:$C,DataA!$A12,DataQ!J:J) -> 1749.22 | CI12: =SUMIF(DataQ!$C:$C,DataA!$A12,DataQ!K:K) -> 1172.004 | CJ12: =SUMIF(DataQ!$C:$C,DataA!$A12,DataQ!L:L) -> 1101.4476 | CK12: =AVERAGEIF(DataQ!$C:$C,DataA!$A12,DataQ!M:M) -> 212796.95 | CL12: =SUMIF(DataQ!$C:$C,DataA!$A12,DataQ!N:N) -> -8685 | CN12: =SUMIF(DataQ!$B:$B,DataA!$A12,DataQ!O:O) -> -81.16925 | CO12: =SUMIF(DataQ!$B:$B,DataA!$A12,DataQ!P:P) -> -13458 | CP12: =SUMIF(DataQ!$B:$B,DataA!$A12,DataQ!Q:Q) -> -52.05288
A13: =+A12+1 -> 1979 | B13: {=INDEX(GMWA!$A$2:$DB$600,MATCH(1,(GMWA!$DA$2:$DA$600=B$3)*(GMWA!$CZ$2:$CZ$600=B$4)*(GMWA!$DB$2:$DB$600=B$1),0),$A13-1966)} -> 9791 | C13: {=INDEX(GMWA!$A$2:$DB$600,MATCH(1,(GMWA!$DA$2:$DA$600=C$3)*(GMWA!$CZ$2:$CZ$600=C$4)*(GMWA!$DB$2:$DB$600=C$1),0),$A13-1966)} -> 128.475 | D13: {=INDEX(GMWA!$A$2:$DB$600,MATCH(1,(GMWA!$DA$2:$DA$600=D$3)*(GMWA!$CZ$2:$CZ$600=D$4)*(GMWA!$DB$2:$DB$600=D$1),0),$A13-1966)} -> 5571.224 | E13: {=INDEX(GMWA!$A$2:$DB$600,MATCH(1,(GMWA!$DA$2:$DA$600=E$3)*(GMWA!$CZ$2:$CZ$600=E$4)*(GMWA!$DB$2:$DB$600=E$1),0),$A13-1966)} -> 14057 | F13: {=INDEX(GMWA!$A$2:$DB$600,MATCH(1,(GMWA!$DA$2:$DA$600=F$3)*(GMWA!$CZ$2:$CZ$600=F$4)*(GMWA!$DB$2:$DB$600=F$1),0),$A13-1966)} -> 2136 | G13: {=INDEX(GMWA!$A$2:$DB$600,MATCH(1,(GMWA!$DA$2:$DA$600=G$3)*(GMWA!$CZ$2:$CZ$600=G$4)*(GMWA!$DB$2:$DB$600=G$1),0),$A13-1966)} -> 11.05835 | H13: {=INDEX(GMWA!$A$2:$DB$600,MATCH(1,(GMWA!$DA$2:$DA$600=H$3)*(GMWA!$CZ$2:$CZ$600=H$4)*(GMWA!$DB$2:$DB$600=H$1),0),$A13-1966)} -> 11487.63 | I13: {=INDEX(GMWA!$A$2:$DB$600,MATCH(1,(GMWA!$DA$2:$DA$600=I$3)*(GMWA!$CZ$2:$CZ$600=I$4)*(GMWA!$DB$2:$DB$600=I$1),0),$A13-1966)} -> 2.971176 | ... BI13: {=INDEX(GMWA!$A$2:$DB$600,MATCH(1,(GMWA!$DA$2:$DA$600=BI$3)*(GMWA!$CZ$2:$CZ$600=BI$4)*(GMWA!$DB$2:$DB$600=BI$1),0),$A13-1966)} -> 23.33603 | BK13: =100*(B13/V13) -> 9.3419333 | BL13: =100*(C13/W13) -> 6.6829829 | BM13: =100*(D13/X13) -> 5.6300012 | BN13: =100*(E13/Y13) -> 10.594664 | BO13: =100*(F13/Z13) -> 213600000 | BP13: =100*(G13/AA13) -> 6.6217665 | BQ13: =100*(H13/AB13) -> 6.2358653 | BR13: =100*(I13/AC13) -> 2.534986 | ... CD13: =100*(U13/AO13) -> 0.23387546 | CF13: =SUMIF(DataQ!$C:$C,DataA!$A13,DataQ!H:H) -> 7301.725 | CG13: =SUMIF(DataQ!$C:$C,DataA!$A13,DataQ!I:I) -> 264833.65 | CH13: =SUMIF(DataQ!$C:$C,DataA!$A13,DataQ!J:J) -> 1830.73 | CI13: =SUMIF(DataQ!$C:$C,DataA!$A13,DataQ!K:K) -> 1213.536 | CJ13: =SUMIF(DataQ!$C:$C,DataA!$A13,DataQ!L:L) -> 1160.2021 | CK13: =AVERAGEIF(DataQ!$C:$C,DataA!$A13,DataQ!M:M) -> 220753.85 | CL13: =SUMIF(DataQ!$C:$C,DataA!$A13,DataQ!N:N) -> -8546 | CN13: =SUMIF(DataQ!$B:$B,DataA!$A13,DataQ!O:O) -> -78.56225 | CO13: =SUMIF(DataQ!$B:$B,DataA!$A13,DataQ!P:P) -> -12426.5 | CP13: =SUMIF(DataQ!$B:$B,DataA!$A13,DataQ!Q:Q) -> -58.44036
A14: =+A13+1 -> 1980 | B14: {=INDEX(GMWA!$A$2:$DB$600,MATCH(1,(GMWA!$DA$2:$DA$600=B$3)*(GMWA!$CZ$2:$CZ$600=B$4)*(GMWA!$DB$2:$DB$600=B$1),0),$A14-1966)} -> 11972 | C14: {=INDEX(GMWA!$A$2:$DB$600,MATCH(1,(GMWA!$DA$2:$DA$600=C$3)*(GMWA!$CZ$2:$CZ$600=C$4)*(GMWA!$DB$2:$DB$600=C$1),0),$A14-1966)} -> 148.775 | D14: {=INDEX(GMWA!$A$2:$DB$600,MATCH(1,(GMWA!$DA$2:$DA$600=D$3)*(GMWA!$CZ$2:$CZ$600=D$4)*(GMWA!$DB$2:$DB$600=D$1),0),$A14-1966)} -> 7259.869 | E14: {=INDEX(GMWA!$A$2:$DB$600,MATCH(1,(GMWA!$DA$2:$DA$600=E$3)*(GMWA!$CZ$2:$CZ$600=E$4)*(GMWA!$DB$2:$DB$600=E$1),0),$A14-1966)} -> 17033 | F14: {=INDEX(GMWA!$A$2:$DB$600,MATCH(1,(GMWA!$DA$2:$DA$600=F$3)*(GMWA!$CZ$2:$CZ$600=F$4)*(GMWA!$DB$2:$DB$600=F$1),0),$A14-1966)} -> 2396 | G14: {=INDEX(GMWA!$A$2:$DB$600,MATCH(1,(GMWA!$DA$2:$DA$600=G$3)*(GMWA!$CZ$2:$CZ$600=G$4)*(GMWA!$DB$2:$DB$600=G$1),0),$A14-1966)} -> 13.37152 | H14: {=INDEX(GMWA!$A$2:$DB$600,MATCH(1,(GMWA!$DA$2:$DA$600=H$3)*(GMWA!$CZ$2:$CZ$600=H$4)*(GMWA!$DB$2:$DB$600=H$1),0),$A14-1966)} -> 16780.39 | I14: {=INDEX(GMWA!$A$2:$DB$600,MATCH(1,(GMWA!$DA$2:$DA$600=I$3)*(GMWA!$CZ$2:$CZ$600=I$4)*(GMWA!$DB$2:$DB$600=I$1),0),$A14-1966)} -> 3.154236 | ... BI14: {=INDEX(GMWA!$A$2:$DB$600,MATCH(1,(GMWA!$DA$2:$DA$600=BI$3)*(GMWA!$CZ$2:$CZ$600=BI$4)*(GMWA!$DB$2:$DB$600=BI$1),0),$A14-1966)} -> 23.33603 | BK14: =100*(B14/V14) -> 9.8501497 | BL14: =100*(C14/W14) -> 7.212106 | BM14: =100*(D14/X14) -> 6.1859824 | BN14: =100*(E14/Y14) -> 11.32566 | BO14: =100*(F14/Z14) -> 239600000 | BP14: =100*(G14/AA14) -> 7.5300266 | BQ14: =100*(H14/AB14) -> 6.4159937 | BR14: =100*(I14/AC14) -> 2.6313609 | ... CD14: =100*(U14/AO14) -> 0.12653751 | CF14: =SUMIF(DataQ!$C:$C,DataA!$A14,DataQ!H:H) -> 7286.675 | CG14: =SUMIF(DataQ!$C:$C,DataA!$A14,DataQ!I:I) -> 276054.26 | CH14: =SUMIF(DataQ!$C:$C,DataA!$A14,DataQ!J:J) -> 1834.03 | CI14: =SUMIF(DataQ!$C:$C,DataA!$A14,DataQ!K:K) -> 1221.947 | CJ14: =SUMIF(DataQ!$C:$C,DataA!$A14,DataQ!L:L) -> 1191.0443 | CK14: =AVERAGEIF(DataQ!$C:$C,DataA!$A14,DataQ!M:M) -> 225566.85 | CL14: =SUMIF(DataQ!$C:$C,DataA!$A14,DataQ!N:N) -> -11537 | CN14: =SUMIF(DataQ!$B:$B,DataA!$A14,DataQ!O:O) -> -128.273 | CO14: =SUMIF(DataQ!$B:$B,DataA!$A14,DataQ!P:P) -> -11822.5 | CP14: =SUMIF(DataQ!$B:$B,DataA!$A14,DataQ!Q:Q) -> -62.0868
A15: =+A14+1 -> 1981 | B15: {=INDEX(GMWA!$A$2:$DB$600,MATCH(1,(GMWA!$DA$2:$DA$600=B$3)*(GMWA!$CZ$2:$CZ$600=B$4)*(GMWA!$DB$2:$DB$600=B$1),0),$A15-1966)} -> 14207 | C15: {=INDEX(GMWA!$A$2:$DB$600,MATCH(1,(GMWA!$DA$2:$DA$600=C$3)*(GMWA!$CZ$2:$CZ$600=C$4)*(GMWA!$DB$2:$DB$600=C$1),0),$A15-1966)} -> 180.075 | D15: {=INDEX(GMWA!$A$2:$DB$600,MATCH(1,(GMWA!$DA$2:$DA$600=D$3)*(GMWA!$CZ$2:$CZ$600=D$4)*(GMWA!$DB$2:$DB$600=D$1),0),$A15-1966)} -> 8747.427 | E15: {=INDEX(GMWA!$A$2:$DB$600,MATCH(1,(GMWA!$DA$2:$DA$600=E$3)*(GMWA!$CZ$2:$CZ$600=E$4)*(GMWA!$DB$2:$DB$600=E$1),0),$A15-1966)} -> 22530 | F15: {=INDEX(GMWA!$A$2:$DB$600,MATCH(1,(GMWA!$DA$2:$DA$600=F$3)*(GMWA!$CZ$2:$CZ$600=F$4)*(GMWA!$DB$2:$DB$600=F$1),0),$A15-1966)} -> 2661 | G15: {=INDEX(GMWA!$A$2:$DB$600,MATCH(1,(GMWA!$DA$2:$DA$600=G$3)*(GMWA!$CZ$2:$CZ$600=G$4)*(GMWA!$DB$2:$DB$600=G$1),0),$A15-1966)} -> 19.54586 | H15: {=INDEX(GMWA!$A$2:$DB$600,MATCH(1,(GMWA!$DA$2:$DA$600=H$3)*(GMWA!$CZ$2:$CZ$600=H$4)*(GMWA!$DB$2:$DB$600=H$1),0),$A15-1966)} -> 24984.48 | I15: {=INDEX(GMWA!$A$2:$DB$600,MATCH(1,(GMWA!$DA$2:$DA$600=I$3)*(GMWA!$CZ$2:$CZ$600=I$4)*(GMWA!$DB$2:$DB$600=I$1),0),$A15-1966)} -> 3.402169 | ... BI15: {=INDEX(GMWA!$A$2:$DB$600,MATCH(1,(GMWA!$DA$2:$DA$600=BI$3)*(GMWA!$CZ$2:$CZ$600=BI$4)*(GMWA!$DB$2:$DB$600=BI$1),0),$A15-1966)} -> 23.33603 | BK15: =100*(B15/V15) -> 10.779906 | BL15: =100*(C15/W15) -> 7.9794553 | BM15: =100*(D15/X15) -> 6.1832381 | BN15: =100*(E15/Y15) -> 12.703478 | BO15: =100*(F15/Z15) -> 266100000 | BP15: =100*(G15/AA15) -> 8.206133 | BQ15: =100*(H15/AB15) -> 7.4091182 | BR15: =100*(I15/AC15) -> 2.8492899 | ... CD15: =100*(U15/AO15) -> 0.084084135 | CF15: =SUMIF(DataQ!$C:$C,DataA!$A15,DataQ!H:H) -> 7400.625 | CG15: =SUMIF(DataQ!$C:$C,DataA!$A15,DataQ!I:I) -> 287278.26 | CH15: =SUMIF(DataQ!$C:$C,DataA!$A15,DataQ!J:J) -> 1847.27 | CI15: =SUMIF(DataQ!$C:$C,DataA!$A15,DataQ!K:K) -> 1246.444 | CJ15: =SUMIF(DataQ!$C:$C,DataA!$A15,DataQ!L:L) -> 1200.915 | CK15: =AVERAGEIF(DataQ!$C:$C,DataA!$A15,DataQ!M:M) -> 230470.8 | CL15: =SUMIF(DataQ!$C:$C,DataA!$A15,DataQ!N:N) -> -5999 | CN15: =SUMIF(DataQ!$B:$B,DataA!$A15,DataQ!O:O) -> -130.469 | CO15: =SUMIF(DataQ!$B:$B,DataA!$A15,DataQ!P:P) -> -10937.75 | CP15: =SUMIF(DataQ!$B:$B,DataA!$A15,DataQ!Q:Q) -> -75.16716
A16: =+A15+1 -> 1982 | B16: {=INDEX(GMWA!$A$2:$DB$600,MATCH(1,(GMWA!$DA$2:$DA$600=B$3)*(GMWA!$CZ$2:$CZ$600=B$4)*(GMWA!$DB$2:$DB$600=B$1),0),$A16-1966)} -> 15540 | C16: {=INDEX(GMWA!$A$2:$DB$600,MATCH(1,(GMWA!$DA$2:$DA$600=C$3)*(GMWA!$CZ$2:$CZ$600=C$4)*(GMWA!$DB$2:$DB$600=C$1),0),$A16-1966)} -> 206.175 | D16: {=INDEX(GMWA!$A$2:$DB$600,MATCH(1,(GMWA!$DA$2:$DA$600=D$3)*(GMWA!$CZ$2:$CZ$600=D$4)*(GMWA!$DB$2:$DB$600=D$1),0),$A16-1966)} -> 10090.23 | E16: {=INDEX(GMWA!$A$2:$DB$600,MATCH(1,(GMWA!$DA$2:$DA$600=E$3)*(GMWA!$CZ$2:$CZ$600=E$4)*(GMWA!$DB$2:$DB$600=E$1),0),$A16-1966)} -> 27419 | F16: {=INDEX(GMWA!$A$2:$DB$600,MATCH(1,(GMWA!$DA$2:$DA$600=F$3)*(GMWA!$CZ$2:$CZ$600=F$4)*(GMWA!$DB$2:$DB$600=F$1),0),$A16-1966)} -> 3141 | G16: {=INDEX(GMWA!$A$2:$DB$600,MATCH(1,(GMWA!$DA$2:$DA$600=G$3)*(GMWA!$CZ$2:$CZ$600=G$4)*(GMWA!$DB$2:$DB$600=G$1),0),$A16-1966)} -> 25.32144 | H16: {=INDEX(GMWA!$A$2:$DB$600,MATCH(1,(GMWA!$DA$2:$DA$600=H$3)*(GMWA!$CZ$2:$CZ$600=H$4)*(GMWA!$DB$2:$DB$600=H$1),0),$A16-1966)} -> 36744.3 | I16: {=INDEX(GMWA!$A$2:$DB$600,MATCH(1,(GMWA!$DA$2:$DA$600=I$3)*(GMWA!$CZ$2:$CZ$600=I$4)*(GMWA!$DB$2:$DB$600=I$1),0),$A16-1966)} -> 3.559402 | ... BI16: {=INDEX(GMWA!$A$2:$DB$600,MATCH(1,(GMWA!$DA$2:$DA$600=BI$3)*(GMWA!$CZ$2:$CZ$600=BI$4)*(GMWA!$DB$2:$DB$600=BI$1),0),$A16-1966)} -> 23.33603 | BK16: =100*(B16/V16) -> 11.054298 | BL16: =100*(C16/W16) -> 8.1418143 | BM16: =100*(D16/X16) -> 6.1080353 | BN16: =100*(E16/Y16) -> 13.073351 | BO16: =100*(F16/Z16) -> 314100000 | BP16: =100*(G16/AA16) -> 7.6570143 | BQ16: =100*(H16/AB16) -> 8.4123511 | BR16: =100*(I16/AC16) -> 3.0338252 | ... CD16: =100*(U16/AO16) -> 0.06360694 | CF16: =SUMIF(DataQ!$C:$C,DataA!$A16,DataQ!H:H) -> 7333.425 | CG16: =SUMIF(DataQ!$C:$C,DataA!$A16,DataQ!I:I) -> 296695.96 | CH16: =SUMIF(DataQ!$C:$C,DataA!$A16,DataQ!J:J) -> 1834.54 | CI16: =SUMIF(DataQ!$C:$C,DataA!$A16,DataQ!K:K) -> 1272.743 | CJ16: =SUMIF(DataQ!$C:$C,DataA!$A16,DataQ!L:L) -> 1200.73 | CK16: =AVERAGEIF(DataQ!$C:$C,DataA!$A16,DataQ!M:M) -> 223200.35 | CL16: =SUMIF(DataQ!$C:$C,DataA!$A16,DataQ!N:N) -> -8542 | CN16: =SUMIF(DataQ!$B:$B,DataA!$A16,DataQ!O:O) -> -220.126 | CO16: =SUMIF(DataQ!$B:$B,DataA!$A16,DataQ!P:P) -> -11134.25 | CP16: =SUMIF(DataQ!$B:$B,DataA!$A16,DataQ!Q:Q) -> -74.95508
A17: =+A16+1 -> 1983 | B17: {=INDEX(GMWA!$A$2:$DB$600,MATCH(1,(GMWA!$DA$2:$DA$600=B$3)*(GMWA!$CZ$2:$CZ$600=B$4)*(GMWA!$DB$2:$DB$600=B$1),0),$A17-1966)} -> 15996 | C17: {=INDEX(GMWA!$A$2:$DB$600,MATCH(1,(GMWA!$DA$2:$DA$600=C$3)*(GMWA!$CZ$2:$CZ$600=C$4)*(GMWA!$DB$2:$DB$600=C$1),0),$A17-1966)} -> 227.975 | D17: {=INDEX(GMWA!$A$2:$DB$600,MATCH(1,(GMWA!$DA$2:$DA$600=D$3)*(GMWA!$CZ$2:$CZ$600=D$4)*(GMWA!$DB$2:$DB$600=D$1),0),$A17-1966)} -> 11534.9 | E17: {=INDEX(GMWA!$A$2:$DB$600,MATCH(1,(GMWA!$DA$2:$DA$600=E$3)*(GMWA!$CZ$2:$CZ$600=E$4)*(GMWA!$DB$2:$DB$600=E$1),0),$A17-1966)} -> 29858 | F17: {=INDEX(GMWA!$A$2:$DB$600,MATCH(1,(GMWA!$DA$2:$DA$600=F$3)*(GMWA!$CZ$2:$CZ$600=F$4)*(GMWA!$DB$2:$DB$600=F$1),0),$A17-1966)} -> 3764 | G17: {=INDEX(GMWA!$A$2:$DB$600,MATCH(1,(GMWA!$DA$2:$DA$600=G$3)*(GMWA!$CZ$2:$CZ$600=G$4)*(GMWA!$DB$2:$DB$600=G$1),0),$A17-1966)} -> 37.50747 | H17: {=INDEX(GMWA!$A$2:$DB$600,MATCH(1,(GMWA!$DA$2:$DA$600=H$3)*(GMWA!$CZ$2:$CZ$600=H$4)*(GMWA!$DB$2:$DB$600=H$1),0),$A17-1966)} -> 43218.67 | I17: {=INDEX(GMWA!$A$2:$DB$600,MATCH(1,(GMWA!$DA$2:$DA$600=I$3)*(GMWA!$CZ$2:$CZ$600=I$4)*(GMWA!$DB$2:$DB$600=I$1),0),$A17-1966)} -> 3.657443 | ... BI17: {=INDEX(GMWA!$A$2:$DB$600,MATCH(1,(GMWA!$DA$2:$DA$600=BI$3)*(GMWA!$CZ$2:$CZ$600=BI$4)*(GMWA!$DB$2:$DB$600=BI$1),0),$A17-1966)} -> 23.33603 | BK17: =100*(B17/V17) -> 10.51792 | BL17: =100*(C17/W17) -> 8.106654 | BM17: =100*(D17/X17) -> 6.0747088 | BN17: =100*(E17/Y17) -> 11.854622 | BO17: =100*(F17/Z17) -> 376400000 | BP17: =100*(G17/AA17) -> 8.8404927 | BQ17: =100*(H17/AB17) -> 8.3091047 | BR17: =100*(I17/AC17) -> 3.1183198 | ... CD17: =100*(U17/AO17) -> 0.0458311 | CF17: =SUMIF(DataQ!$C:$C,DataA!$A17,DataQ!H:H) -> 7800.95 | CG17: =SUMIF(DataQ!$C:$C,DataA!$A17,DataQ!I:I) -> 307848.46 | CH17: =SUMIF(DataQ!$C:$C,DataA!$A17,DataQ!J:J) -> 1879.96 | CI17: =SUMIF(DataQ!$C:$C,DataA!$A17,DataQ!K:K) -> 1287.699 | CJ17: =SUMIF(DataQ!$C:$C,DataA!$A17,DataQ!L:L) -> 1229.587 | CK17: =AVERAGEIF(DataQ!$C:$C,DataA!$A17,DataQ!M:M) -> 233186.72 | CL17: =SUMIF(DataQ!$C:$C,DataA!$A17,DataQ!N:N) -> -11802 | CN17: =SUMIF(DataQ!$B:$B,DataA!$A17,DataQ!O:O) -> -265.23725 | CO17: =SUMIF(DataQ!$B:$B,DataA!$A17,DataQ!P:P) -> -11809.25 | CP17: =SUMIF(DataQ!$B:$B,DataA!$A17,DataQ!Q:Q) -> -71.17676
A18: =+A17+1 -> 1984 | B18: {=INDEX(GMWA!$A$2:$DB$600,MATCH(1,(GMWA!$DA$2:$DA$600=B$3)*(GMWA!$CZ$2:$CZ$600=B$4)*(GMWA!$DB$2:$DB$600=B$1),0),$A18-1966)} -> 17461 | C18: {=INDEX(GMWA!$A$2:$DB$600,MATCH(1,(GMWA!$DA$2:$DA$600=C$3)*(GMWA!$CZ$2:$CZ$600=C$4)*(GMWA!$DB$2:$DB$600=C$1),0),$A18-1966)} -> 260.05 | D18: {=INDEX(GMWA!$A$2:$DB$600,MATCH(1,(GMWA!$DA$2:$DA$600=D$3)*(GMWA!$CZ$2:$CZ$600=D$4)*(GMWA!$DB$2:$DB$600=D$1),0),$A18-1966)} -> 12792.81 | E18: {=INDEX(GMWA!$A$2:$DB$600,MATCH(1,(GMWA!$DA$2:$DA$600=E$3)*(GMWA!$CZ$2:$CZ$600=E$4)*(GMWA!$DB$2:$DB$600=E$1),0),$A18-1966)} -> 35147 | F18: {=INDEX(GMWA!$A$2:$DB$600,MATCH(1,(GMWA!$DA$2:$DA$600=F$3)*(GMWA!$CZ$2:$CZ$600=F$4)*(GMWA!$DB$2:$DB$600=F$1),0),$A18-1966)} -> 4951 | G18: {=INDEX(GMWA!$A$2:$DB$600,MATCH(1,(GMWA!$DA$2:$DA$600=G$3)*(GMWA!$CZ$2:$CZ$600=G$4)*(GMWA!$DB$2:$DB$600=G$1),0),$A18-1966)} -> 49.15562 | H18: {=INDEX(GMWA!$A$2:$DB$600,MATCH(1,(GMWA!$DA$2:$DA$600=H$3)*(GMWA!$CZ$2:$CZ$600=H$4)*(GMWA!$DB$2:$DB$600=H$1),0),$A18-1966)} -> 51442.58 | I18: {=INDEX(GMWA!$A$2:$DB$600,MATCH(1,(GMWA!$DA$2:$DA$600=I$3)*(GMWA!$CZ$2:$CZ$600=I$4)*(GMWA!$DB$2:$DB$600=I$1),0),$A18-1966)} -> 3.631457 | ... BI18: {=INDEX(GMWA!$A$2:$DB$600,MATCH(1,(GMWA!$DA$2:$DA$600=BI$3)*(GMWA!$CZ$2:$CZ$600=BI$4)*(GMWA!$DB$2:$DB$600=BI$1),0),$A18-1966)} -> 23.33603 | BK18: =100*(B18/V18) -> 10.66982 | BL18: =100*(C18/W18) -> 8.2256117 | BM18: =100*(D18/X18) -> 6.140765 | BN18: =100*(E18/Y18) -> 12.091678 | BO18: =100*(F18/Z18) -> 495100000 | BP18: =100*(G18/AA18) -> 10.318747 | BQ18: =100*(H18/AB18) -> 8.6560477 | BR18: =100*(I18/AC18) -> 3.1088846 | ... CD18: =100*(U18/AO18) -> 0.033652669 | CF18: =SUMIF(DataQ!$C:$C,DataA!$A18,DataQ!H:H) -> 8286.8 | CG18: =SUMIF(DataQ!$C:$C,DataA!$A18,DataQ!I:I) -> 322074.95 | CH18: =SUMIF(DataQ!$C:$C,DataA!$A18,DataQ!J:J) -> 1924.4 | CI18: =SUMIF(DataQ!$C:$C,DataA!$A18,DataQ!K:K) -> 1309.22 | CJ18: =SUMIF(DataQ!$C:$C,DataA!$A18,DataQ!L:L) -> 1263.855 | CK18: =AVERAGEIF(DataQ!$C:$C,DataA!$A18,DataQ!M:M) -> 246574.27 | CL18: =SUMIF(DataQ!$C:$C,DataA!$A18,DataQ!N:N) -> -12535 | CN18: =SUMIF(DataQ!$B:$B,DataA!$A18,DataQ!O:O) -> -249.608 | CO18: =SUMIF(DataQ!$B:$B,DataA!$A18,DataQ!P:P) -> -8204.75 | CP18: =SUMIF(DataQ!$B:$B,DataA!$A18,DataQ!Q:Q) -> -66.7484
A19: =+A18+1 -> 1985 | B19: {=INDEX(GMWA!$A$2:$DB$600,MATCH(1,(GMWA!$DA$2:$DA$600=B$3)*(GMWA!$CZ$2:$CZ$600=B$4)*(GMWA!$DB$2:$DB$600=B$1),0),$A19-1966)} -> 19036 | C19: {=INDEX(GMWA!$A$2:$DB$600,MATCH(1,(GMWA!$DA$2:$DA$600=C$3)*(GMWA!$CZ$2:$CZ$600=C$4)*(GMWA!$DB$2:$DB$600=C$1),0),$A19-1966)} -> 285.75 | D19: {=INDEX(GMWA!$A$2:$DB$600,MATCH(1,(GMWA!$DA$2:$DA$600=D$3)*(GMWA!$CZ$2:$CZ$600=D$4)*(GMWA!$DB$2:$DB$600=D$1),0),$A19-1966)} -> 13766.58 | E19: {=INDEX(GMWA!$A$2:$DB$600,MATCH(1,(GMWA!$DA$2:$DA$600=E$3)*(GMWA!$CZ$2:$CZ$600=E$4)*(GMWA!$DB$2:$DB$600=E$1),0),$A19-1966)} -> 40585 | F19: {=INDEX(GMWA!$A$2:$DB$600,MATCH(1,(GMWA!$DA$2:$DA$600=F$3)*(GMWA!$CZ$2:$CZ$600=F$4)*(GMWA!$DB$2:$DB$600=F$1),0),$A19-1966)} -> 6665 | G19: {=INDEX(GMWA!$A$2:$DB$600,MATCH(1,(GMWA!$DA$2:$DA$600=G$3)*(GMWA!$CZ$2:$CZ$600=G$4)*(GMWA!$DB$2:$DB$600=G$1),0),$A19-1966)} -> 55.07229 | H19: {=INDEX(GMWA!$A$2:$DB$600,MATCH(1,(GMWA!$DA$2:$DA$600=H$3)*(GMWA!$CZ$2:$CZ$600=H$4)*(GMWA!$DB$2:$DB$600=H$1),0),$A19-1966)} -> 62413.66 | I19: {=INDEX(GMWA!$A$2:$DB$600,MATCH(1,(GMWA!$DA$2:$DA$600=I$3)*(GMWA!$CZ$2:$CZ$600=I$4)*(GMWA!$DB$2:$DB$600=I$1),0),$A19-1966)} -> 3.735457 | ... BI19: {=INDEX(GMWA!$A$2:$DB$600,MATCH(1,(GMWA!$DA$2:$DA$600=BI$3)*(GMWA!$CZ$2:$CZ$600=BI$4)*(GMWA!$DB$2:$DB$600=BI$1),0),$A19-1966)} -> 23.33603 | BK19: =100*(B19/V19) -> 10.810823 | BL19: =100*(C19/W19) -> 8.0367403 | BM19: =100*(D19/X19) -> 5.945223 | BN19: =100*(E19/Y19) -> 11.919692 | BO19: =100*(F19/Z19) -> 666500000 | BP19: =100*(G19/AA19) -> 10.996226 | BQ19: =100*(H19/AB19) -> 9.7090807 | BR19: =100*(I19/AC19) -> 3.260981 | ... CD19: =100*(U19/AO19) -> 0.025463467 | CF19: =SUMIF(DataQ!$C:$C,DataA!$A19,DataQ!H:H) -> 8624.075 | CG19: =SUMIF(DataQ!$C:$C,DataA!$A19,DataQ!I:I) -> 339010.34 | CH19: =SUMIF(DataQ!$C:$C,DataA!$A19,DataQ!J:J) -> 1978.87 | CI19: =SUMIF(DataQ!$C:$C,DataA!$A19,DataQ!K:K) -> 1334.186 | CJ19: =SUMIF(DataQ!$C:$C,DataA!$A19,DataQ!L:L) -> 1304.003 | CK19: =AVERAGEIF(DataQ!$C:$C,DataA!$A19,DataQ!M:M) -> 256722.58 | CL19: =SUMIF(DataQ!$C:$C,DataA!$A19,DataQ!N:N) -> -9034 | CN19: =SUMIF(DataQ!$B:$B,DataA!$A19,DataQ!O:O) -> -270.54324 | CO19: =SUMIF(DataQ!$B:$B,DataA!$A19,DataQ!P:P) -> -4308.75 | CP19: =SUMIF(DataQ!$B:$B,DataA!$A19,DataQ!Q:Q) -> -82.98528
... A94: =+A93+1 -> 2060 | B94: {=INDEX(GMWA!$A$2:$DB$600,MATCH(1,(GMWA!$DA$2:$DA$600=B$3)*(GMWA!$CZ$2:$CZ$600=B$4)*(GMWA!$DB$2:$DB$600=B$1),0),$A94-1966)} -> 371800.6 | C94: {=INDEX(GMWA!$A$2:$DB$600,MATCH(1,(GMWA!$DA$2:$DA$600=C$3)*(GMWA!$CZ$2:$CZ$600=C$4)*(GMWA!$DB$2:$DB$600=C$1),0),$A94-1966)} -> 6563.423 | D94: {=INDEX(GMWA!$A$2:$DB$600,MATCH(1,(GMWA!$DA$2:$DA$600=D$3)*(GMWA!$CZ$2:$CZ$600=D$4)*(GMWA!$DB$2:$DB$600=D$1),0),$A94-1966)} -> 32202.59 | E94: {=INDEX(GMWA!$A$2:$DB$600,MATCH(1,(GMWA!$DA$2:$DA$600=E$3)*(GMWA!$CZ$2:$CZ$600=E$4)*(GMWA!$DB$2:$DB$600=E$1),0),$A94-1966)} -> 321538.3 | F94: {=INDEX(GMWA!$A$2:$DB$600,MATCH(1,(GMWA!$DA$2:$DA$600=F$3)*(GMWA!$CZ$2:$CZ$600=F$4)*(GMWA!$DB$2:$DB$600=F$1),0),$A94-1966)} -> 192740.7 | G94: {=INDEX(GMWA!$A$2:$DB$600,MATCH(1,(GMWA!$DA$2:$DA$600=G$3)*(GMWA!$CZ$2:$CZ$600=G$4)*(GMWA!$DB$2:$DB$600=G$1),0),$A94-1966)} -> 25.90304 | H94: {=INDEX(GMWA!$A$2:$DB$600,MATCH(1,(GMWA!$DA$2:$DA$600=H$3)*(GMWA!$CZ$2:$CZ$600=H$4)*(GMWA!$DB$2:$DB$600=H$1),0),$A94-1966)} -> 112505.4 | I94: {=INDEX(GMWA!$A$2:$DB$600,MATCH(1,(GMWA!$DA$2:$DA$600=I$3)*(GMWA!$CZ$2:$CZ$600=I$4)*(GMWA!$DB$2:$DB$600=I$1),0),$A94-1966)} -> 5.549664 | ... BI94: {=INDEX(GMWA!$A$2:$DB$600,MATCH(1,(GMWA!$DA$2:$DA$600=BI$3)*(GMWA!$CZ$2:$CZ$600=BI$4)*(GMWA!$DB$2:$DB$600=BI$1),0),$A94-1966)} -> 814.1521 | BK94: =100*(B94/V94) -> 3.2077521 | BL94: =100*(C94/W94) -> 3.5996862 | BM94: =100*(D94/X94) -> 1.8484714 | BN94: =100*(E94/Y94) -> 3.4744464 | BO94: =100*(F94/Z94) -> 3.3726109 | BP94: =100*(G94/AA94) -> 1.1698077 | BQ94: =100*(H94/AB94) -> 1.8800603 | BR94: =100*(I94/AC94) -> 0.72570041 | ... CD94: =100*(U94/AO94) -> 2.9385924 | CF94: =SUMIF(DataQ!$C:$C,DataA!$A94,DataQ!H:H) -> 32910.97 | CG94: =SUMIF(DataQ!$C:$C,DataA!$A94,DataQ!I:I) -> 432128.3 | CH94: =SUMIF(DataQ!$C:$C,DataA!$A94,DataQ!J:J) -> 3713.436 | CI94: =SUMIF(DataQ!$C:$C,DataA!$A94,DataQ!K:K) -> 2431.2251 | CJ94: =SUMIF(DataQ!$C:$C,DataA!$A94,DataQ!L:L) -> 1633.8914 | CK94: =AVERAGEIF(DataQ!$C:$C,DataA!$A94,DataQ!M:M) -> 1174933.3 | CL94: =SUMIF(DataQ!$C:$C,DataA!$A94,DataQ!N:N) -> -425026.33 | CN94: =SUMIF(DataQ!$B:$B,DataA!$A94,DataQ!O:O) -> -4188.266 | CO94: =SUMIF(DataQ!$B:$B,DataA!$A94,DataQ!P:P) -> -9878.532 | CP94: =SUMIF(DataQ!$B:$B,DataA!$A94,DataQ!Q:Q) -> -182.69702

Sheet Data Q to A
B1: CY total | P1: CY end | W1: CY total
B2: =DataQ!G1 -> OCT004A.db | C2: =DataQ!H1 -> OCT004A.db | D2: =DataQ!I1 -> OCT004A.db | E2: =DataQ!J1 -> OCT004A.db | F2: =DataQ!K1 -> OCT004A.db | G2: =DataQ!L1 -> OCT004A.db | H2: =DataQ!M1 -> OCT004A.db | I2: =DataQ!N1 -> OCT004A.db | ... AC2: =DataQ!AH1 -> OCT004A.db
B3: =DataQ!G2 -> UK | C3: =DataQ!H2 -> US | D3: =DataQ!I2 -> Japan | E3: =DataQ!J2 -> Germany | F3: =DataQ!K2 -> France | G3: =DataQ!L2 -> Italy | H3: =DataQ!M2 -> Canada | I3: =DataQ!N2 -> UK | ... AC3: =DataQ!AH2 -> Canada
B4: =DataQ!G3 -> GDP | C4: =DataQ!H3 -> GDP | D4: =DataQ!I3 -> GDP | E4: =DataQ!J3 -> GDP | F4: =DataQ!K3 -> GDP | G4: =DataQ!L3 -> GDP | H4: =DataQ!M3 -> GDP | I4: =DataQ!N3 -> GB | ... AC4: =DataQ!AH3 -> GDP!
B5: =DataQ!G4 -> GBR | C5: =DataQ!H4 -> USA | D5: =DataQ!I4 -> JPN | E5: =DataQ!J4 -> DEU | F5: =DataQ!K4 -> FRA | G5: =DataQ!L4 -> ITA | H5: =DataQ!M4 -> CAN | I5: =DataQ!N4 -> GBR | ... AC5: =DataQ!AH4 -> CAN
B6: =DataQ!G5 -> L | C6: =DataQ!H5 -> L | D6: =DataQ!I5 -> L | E6: =DataQ!J5 -> L | F6: =DataQ!K5 -> L | G6: =DataQ!L5 -> L | H6: =DataQ!M5 -> L | I6: =DataQ!N5 -> L | ... AC6: =DataQ!AH5 -> L
B7: =DataQ!G6 -> 202502 | C7: =DataQ!H6 -> 202502 | D7: =DataQ!I6 -> 202502 | E7: =DataQ!J6 -> 202502 | F7: =DataQ!K6 -> 202502 | G7: =DataQ!L6 -> 202502 | H7: =DataQ!M6 -> 202502 | I7: =DataQ!N6 -> 202502 | ... AC7: =DataQ!AH6 -> 202502
A8: 1973 | B8: =SUMIF(DataQ!$B:$B,'Data Q to A'!$A8,DataQ!G:G) -> 1063550 | C8: =SUMIF(DataQ!$B:$B,'Data Q to A'!$A8,DataQ!H:H) -> 6106.35 | D8: =SUMIF(DataQ!$B:$B,'Data Q to A'!$A8,DataQ!I:I) -> 211380.51 | E8: =SUMIF(DataQ!$B:$B,'Data Q to A'!$A8,DataQ!J:J) -> 1556.14 | F8: =SUMIF(DataQ!$B:$B,'Data Q to A'!$A8,DataQ!K:K) -> 999.15 | G8: =SUMIF(DataQ!$B:$B,'Data Q to A'!$A8,DataQ!L:L) -> 932.5699 | H8: =SUMIF(DataQ!$B:$B,'Data Q to A'!$A8,DataQ!M:M) -> 707164.6 | I8: =SUMIF(DataQ!$B:$B,'Data Q to A'!$A8,DataQ!N:N) -> -2740 | J8: =SUMIF(DataQ!$B:$B,'Data Q to A'!$A8,DataQ!O:O) -> -44.59125 | K8: =SUMIF(DataQ!$B:$B,'Data Q to A'!$A8,DataQ!P:P) -> -2130.75 | L8: =SUMIF(DataQ!$B:$B,'Data Q to A'!$A8,DataQ!Q:Q) -> -23.045528 | M8: =SUMIF(DataQ!$B:$B,'Data Q to A'!$A8,DataQ!R:R) -> 0.8040001 | N8: =SUMIF(DataQ!$B:$B,'Data Q to A'!$A8,DataQ!S:S) -> -3.2833435 | O8: =SUMIF(DataQ!$B:$B,'Data Q to A'!$A8,DataQ!T:T) -> 1605 | P8: =SUMIF(DataQ!$E:$E,'Data Q to A'!$A8,DataQ!U:U) -> 35969.43 | Q8: =SUMIF(DataQ!$E:$E,'Data Q to A'!$A8,DataQ!V:V) -> 1158.847 | R8: =SUMIF(DataQ!$E:$E,'Data Q to A'!$A8,DataQ!W:W) -> 17803 | S8: =SUMIF(DataQ!$E:$E,'Data Q to A'!$A8,DataQ!X:X) -> 89.06523 | T8: =SUMIF(DataQ!$E:$E,'Data Q to A'!$A8,DataQ!Y:Y) -> 56.7663 | U8: =SUMIF(DataQ!$E:$E,'Data Q to A'!$A8,DataQ!Z:Z) -> 36.414 | V8: =SUMIF(DataQ!$E:$E,'Data Q to A'!$A8,DataQ!AA:AA) -> 64923 | W8: =SUMIF(DataQ!$B:$B,'Data Q to A'!$A8,DataQ!AB:AB) -> 81809 | X8: =SUMIF(DataQ!$B:$B,'Data Q to A'!$A8,DataQ!AC:AC) -> 1425.375 | Y8: =SUMIF(DataQ!$B:$B,'Data Q to A'!$A8,DataQ!AD:AD) -> 115345.45 | Z8: =SUMIF(DataQ!$B:$B,'Data Q to A'!$A8,DataQ!AE:AE) -> 553.1868 | AA8: =SUMIF(DataQ!$B:$B,'Data Q to A'!$A8,DataQ!AF:AF) -> 177.825 | AB8: =SUMIF(DataQ!$B:$B,'Data Q to A'!$A8,DataQ!AG:AG) -> 53.293 | AC8: =SUMIF(DataQ!$B:$B,'Data Q to A'!$A8,DataQ!AH:AH) -> 132966
A9: 1974 | B9: =SUMIF(DataQ!$B:$B,'Data Q to A'!$A9,DataQ!G:G) -> 1036973 | C9: =SUMIF(DataQ!$B:$B,'Data Q to A'!$A9,DataQ!H:H) -> 6073.4 | D9: =SUMIF(DataQ!$B:$B,'Data Q to A'!$A9,DataQ!I:I) -> 209230.97 | E9: =SUMIF(DataQ!$B:$B,'Data Q to A'!$A9,DataQ!J:J) -> 1571.34 | F9: =SUMIF(DataQ!$B:$B,'Data Q to A'!$A9,DataQ!K:K) -> 1043.039 | G9: =SUMIF(DataQ!$B:$B,'Data Q to A'!$A9,DataQ!L:L) -> 981.7783 | H9: =SUMIF(DataQ!$B:$B,'Data Q to A'!$A9,DataQ!M:M) -> 730909.6 | I9: =SUMIF(DataQ!$B:$B,'Data Q to A'!$A9,DataQ!N:N) -> -4310 | J9: =SUMIF(DataQ!$B:$B,'Data Q to A'!$A9,DataQ!O:O) -> -59.765 | K9: =SUMIF(DataQ!$B:$B,'Data Q to A'!$A9,DataQ!P:P) -> -2482.25 | L9: =SUMIF(DataQ!$B:$B,'Data Q to A'!$A9,DataQ!Q:Q) -> -36.381582 | M9: =SUMIF(DataQ!$B:$B,'Data Q to A'!$A9,DataQ!R:R) -> 0.4830001 | N9: =SUMIF(DataQ!$B:$B,'Data Q to A'!$A9,DataQ!S:S) -> -4.0740696 | O9: =SUMIF(DataQ!$B:$B,'Data Q to A'!$A9,DataQ!T:T) -> 3052 | P9: =SUMIF(DataQ!$E:$E,'Data Q to A'!$A9,DataQ!U:U) -> 48829.88 | Q9: =SUMIF(DataQ!$E:$E,'Data Q to A'!$A9,DataQ!V:V) -> 1251.709 | R9: =SUMIF(DataQ!$E:$E,'Data Q to A'!$A9,DataQ!W:W) -> 16534 | S9: =SUMIF(DataQ!$E:$E,'Data Q to A'!$A9,DataQ!X:X) -> 106.168 | T9: =SUMIF(DataQ!$E:$E,'Data Q to A'!$A9,DataQ!Y:Y) -> 61.89546 | U9: =SUMIF(DataQ!$E:$E,'Data Q to A'!$A9,DataQ!Z:Z) -> 45.795 | V9: =SUMIF(DataQ!$E:$E,'Data Q to A'!$A9,DataQ!AA:AA) -> 74036 | W9: =SUMIF(DataQ!$B:$B,'Data Q to A'!$A9,DataQ!AB:AB) -> 92686 | X9: =SUMIF(DataQ!$B:$B,'Data Q to A'!$A9,DataQ!AC:AC) -> 1545.25 | Y9: =SUMIF(DataQ!$B:$B,'Data Q to A'!$A9,DataQ!AD:AD) -> 137675.47 | Z9: =SUMIF(DataQ!$B:$B,'Data Q to A'!$A9,DataQ!AE:AE) -> 599.3288 | AA9: =SUMIF(DataQ!$B:$B,'Data Q to A'!$A9,DataQ!AF:AF) -> 207.305 | AB9: =SUMIF(DataQ!$B:$B,'Data Q to A'!$A9,DataQ!AG:AG) -> 67.409 | AC9: =SUMIF(DataQ!$B:$B,'Data Q to A'!$A9,DataQ!AH:AH) -> 158176
A10: 1975 | B10: =SUMIF(DataQ!$B:$B,'Data Q to A'!$A10,DataQ!G:G) -> 1021204 | C10: =SUMIF(DataQ!$B:$B,'Data Q to A'!$A10,DataQ!H:H) -> 6060.85 | D10: =SUMIF(DataQ!$B:$B,'Data Q to A'!$A10,DataQ!I:I) -> 215781.13 | E10: =SUMIF(DataQ!$B:$B,'Data Q to A'!$A10,DataQ!J:J) -> 1557.62 | F10: =SUMIF(DataQ!$B:$B,'Data Q to A'!$A10,DataQ!K:K) -> 1033.444 | G10: =SUMIF(DataQ!$B:$B,'Data Q to A'!$A10,DataQ!L:L) -> 961.6561 | H10: =SUMIF(DataQ!$B:$B,'Data Q to A'!$A10,DataQ!M:M) -> 742205.1 | I10: =SUMIF(DataQ!$B:$B,'Data Q to A'!$A10,DataQ!N:N) -> -7211 | J10: =SUMIF(DataQ!$B:$B,'Data Q to A'!$A10,DataQ!O:O) -> -128.606 | K10: =SUMIF(DataQ!$B:$B,'Data Q to A'!$A10,DataQ!P:P) -> -7342 | L10: =SUMIF(DataQ!$B:$B,'Data Q to A'!$A10,DataQ!Q:Q) -> -62.44885 | M10: =SUMIF(DataQ!$B:$B,'Data Q to A'!$A10,DataQ!R:R) -> -4.3009993 | N10: =SUMIF(DataQ!$B:$B,'Data Q to A'!$A10,DataQ!S:S) -> -7.734278 | O10: =SUMIF(DataQ!$B:$B,'Data Q to A'!$A10,DataQ!T:T) -> -4505 | P10: =SUMIF(DataQ!$E:$E,'Data Q to A'!$A10,DataQ!U:U) -> 62646 | Q10: =SUMIF(DataQ!$E:$E,'Data Q to A'!$A10,DataQ!V:V) -> 1412.028 | R10: =SUMIF(DataQ!$E:$E,'Data Q to A'!$A10,DataQ!W:W) -> 29223 | S10: =SUMIF(DataQ!$E:$E,'Data Q to A'!$A10,DataQ!X:X) -> 136.7461 | T10: =SUMIF(DataQ!$E:$E,'Data Q to A'!$A10,DataQ!Y:Y) -> 70.28793 | U10: =SUMIF(DataQ!$E:$E,'Data Q to A'!$A10,DataQ!Z:Z) -> 61.44 | V10: =SUMIF(DataQ!$E:$E,'Data Q to A'!$A10,DataQ!AA:AA) -> 82299 | W10: =SUMIF(DataQ!$B:$B,'Data Q to A'!$A10,DataQ!AB:AB) -> 115095 | X10: =SUMIF(DataQ!$B:$B,'Data Q to A'!$A10,DataQ!AC:AC) -> 1684.9 | Y10: =SUMIF(DataQ!$B:$B,'Data Q to A'!$A10,DataQ!AD:AD) -> 152524.06 | Z10: =SUMIF(DataQ!$B:$B,'Data Q to A'!$A10,DataQ!AE:AE) -> 627.6409 | AA10: =SUMIF(DataQ!$B:$B,'Data Q to A'!$A10,DataQ!AF:AF) -> 233.583 | AB10: =SUMIF(DataQ!$B:$B,'Data Q to A'!$A10,DataQ!AG:AG) -> 76.902 | AC10: =SUMIF(DataQ!$B:$B,'Data Q to A'!$A10,DataQ!AH:AH) -> 177928
A11: 1976 | B11: =SUMIF(DataQ!$B:$B,'Data Q to A'!$A11,DataQ!G:G) -> 1051973 | C11: =SUMIF(DataQ!$B:$B,'Data Q to A'!$A11,DataQ!H:H) -> 6387.425 | D11: =SUMIF(DataQ!$B:$B,'Data Q to A'!$A11,DataQ!I:I) -> 224484.6 | E11: =SUMIF(DataQ!$B:$B,'Data Q to A'!$A11,DataQ!J:J) -> 1626.82 | F11: =SUMIF(DataQ!$B:$B,'Data Q to A'!$A11,DataQ!K:K) -> 1078.312 | G11: =SUMIF(DataQ!$B:$B,'Data Q to A'!$A11,DataQ!L:L) -> 1024.4384 | H11: =SUMIF(DataQ!$B:$B,'Data Q to A'!$A11,DataQ!M:M) -> 785915.6 | I11: =SUMIF(DataQ!$B:$B,'Data Q to A'!$A11,DataQ!N:N) -> -7961 | J11: =SUMIF(DataQ!$B:$B,'Data Q to A'!$A11,DataQ!O:O) -> -104.50225 | K11: =SUMIF(DataQ!$B:$B,'Data Q to A'!$A11,DataQ!P:P) -> -9301 | L11: =SUMIF(DataQ!$B:$B,'Data Q to A'!$A11,DataQ!Q:Q) -> -53.17428 | M11: =SUMIF(DataQ!$B:$B,'Data Q to A'!$A11,DataQ!R:R) -> -1.5120001 | N11: =SUMIF(DataQ!$B:$B,'Data Q to A'!$A11,DataQ!S:S) -> -7.402609 | O11: =SUMIF(DataQ!$B:$B,'Data Q to A'!$A11,DataQ!T:T) -> -4501 | P11: =SUMIF(DataQ!$E:$E,'Data Q to A'!$A11,DataQ!U:U) -> 73402.75 | Q11: =SUMIF(DataQ!$E:$E,'Data Q to A'!$A11,DataQ!V:V) -> 1521.477 | R11: =SUMIF(DataQ!$E:$E,'Data Q to A'!$A11,DataQ!W:W) -> 44086 | S11: =SUMIF(DataQ!$E:$E,'Data Q to A'!$A11,DataQ!X:X) -> 155.0151 | T11: =SUMIF(DataQ!$E:$E,'Data Q to A'!$A11,DataQ!Y:Y) -> 77.04875 | U11: =SUMIF(DataQ!$E:$E,'Data Q to A'!$A11,DataQ!Z:Z) -> 76.946 | V11: =SUMIF(DataQ!$E:$E,'Data Q to A'!$A11,DataQ!AA:AA) -> 91437 | W11: =SUMIF(DataQ!$B:$B,'Data Q to A'!$A11,DataQ!AB:AB) -> 136995 | X11: =SUMIF(DataQ!$B:$B,'Data Q to A'!$A11,DataQ!AC:AC) -> 1873.425 | Y11: =SUMIF(DataQ!$B:$B,'Data Q to A'!$A11,DataQ!AD:AD) -> 171384.16 | Z11: =SUMIF(DataQ!$B:$B,'Data Q to A'!$A11,DataQ!AE:AE) -> 677.2367 | AA11: =SUMIF(DataQ!$B:$B,'Data Q to A'!$A11,DataQ!AF:AF) -> 269.714 | AB11: =SUMIF(DataQ!$B:$B,'Data Q to A'!$A11,DataQ!AG:AG) -> 96.562 | AC11: =SUMIF(DataQ!$B:$B,'Data Q to A'!$A11,DataQ!AH:AH) -> 205986
A12: 1977 | B12: =SUMIF(DataQ!$B:$B,'Data Q to A'!$A12,DataQ!G:G) -> 1077816 | C12: =SUMIF(DataQ!$B:$B,'Data Q to A'!$A12,DataQ!H:H) -> 6682.825 | D12: =SUMIF(DataQ!$B:$B,'Data Q to A'!$A12,DataQ!I:I) -> 234520.75 | E12: =SUMIF(DataQ!$B:$B,'Data Q to A'!$A12,DataQ!J:J) -> 1683.93 | F12: =SUMIF(DataQ!$B:$B,'Data Q to A'!$A12,DataQ!K:K) -> 1116.289 | G12: =SUMIF(DataQ!$B:$B,'Data Q to A'!$A12,DataQ!L:L) -> 1048.6038 | H12: =SUMIF(DataQ!$B:$B,'Data Q to A'!$A12,DataQ!M:M) -> 813696.4 | I12: =SUMIF(DataQ!$B:$B,'Data Q to A'!$A12,DataQ!N:N) -> -5836 | J12: =SUMIF(DataQ!$B:$B,'Data Q to A'!$A12,DataQ!O:O) -> -88.151 | K12: =SUMIF(DataQ!$B:$B,'Data Q to A'!$A12,DataQ!P:P) -> -10191.75 | L12: =SUMIF(DataQ!$B:$B,'Data Q to A'!$A12,DataQ!Q:Q) -> -44.70044 | M12: =SUMIF(DataQ!$B:$B,'Data Q to A'!$A12,DataQ!R:R) -> -1.9469999 | N12: =SUMIF(DataQ!$B:$B,'Data Q to A'!$A12,DataQ!S:S) -> -7.911603 | O12: =SUMIF(DataQ!$B:$B,'Data Q to A'!$A12,DataQ!T:T) -> -7329 | P12: =SUMIF(DataQ!$E:$E,'Data Q to A'!$A12,DataQ!U:U) -> 83765.5 | Q12: =SUMIF(DataQ!$E:$E,'Data Q to A'!$A12,DataQ!V:V) -> 1639.112 | R12: =SUMIF(DataQ!$E:$E,'Data Q to A'!$A12,DataQ!W:W) -> 58926 | S12: =SUMIF(DataQ!$E:$E,'Data Q to A'!$A12,DataQ!X:X) -> 172.103 | T12: =SUMIF(DataQ!$E:$E,'Data Q to A'!$A12,DataQ!Y:Y) -> 85.55736 | U12: =SUMIF(DataQ!$E:$E,'Data Q to A'!$A12,DataQ!Z:Z) -> 97.55 | V12: =SUMIF(DataQ!$E:$E,'Data Q to A'!$A12,DataQ!AA:AA) -> 104504 | W12: =SUMIF(DataQ!$B:$B,'Data Q to A'!$A12,DataQ!AB:AB) -> 159775 | X12: =SUMIF(DataQ!$B:$B,'Data Q to A'!$A12,DataQ!AC:AC) -> 2081.825 | Y12: =SUMIF(DataQ!$B:$B,'Data Q to A'!$A12,DataQ!AD:AD) -> 191055.77 | Z12: =SUMIF(DataQ!$B:$B,'Data Q to A'!$A12,DataQ!AE:AE) -> 722.7076 | AA12: =SUMIF(DataQ!$B:$B,'Data Q to A'!$A12,DataQ!AF:AF) -> 303.907 | AB12: =SUMIF(DataQ!$B:$B,'Data Q to A'!$A12,DataQ!AG:AG) -> 117.316 | AC12: =SUMIF(DataQ!$B:$B,'Data Q to A'!$A12,DataQ!AH:AH) -> 227601
A13: 1978 | B13: =SUMIF(DataQ!$B:$B,'Data Q to A'!$A13,DataQ!G:G) -> 1122953 | C13: =SUMIF(DataQ!$B:$B,'Data Q to A'!$A13,DataQ!H:H) -> 7052.725 | D13: =SUMIF(DataQ!$B:$B,'Data Q to A'!$A13,DataQ!I:I) -> 247036.86 | E13: =SUMIF(DataQ!$B:$B,'Data Q to A'!$A13,DataQ!J:J) -> 1736.22 | F13: =SUMIF(DataQ!$B:$B,'Data Q to A'!$A13,DataQ!K:K) -> 1160.514 | G13: =SUMIF(DataQ!$B:$B,'Data Q to A'!$A13,DataQ!L:L) -> 1086.8867 | H13: =SUMIF(DataQ!$B:$B,'Data Q to A'!$A13,DataQ!M:M) -> 844095.8 | I13: =SUMIF(DataQ!$B:$B,'Data Q to A'!$A13,DataQ!N:N) -> -8334 | J13: =SUMIF(DataQ!$B:$B,'Data Q to A'!$A13,DataQ!O:O) -> -81.16925 | K13: =SUMIF(DataQ!$B:$B,'Data Q to A'!$A13,DataQ!P:P) -> -13458 | L13: =SUMIF(DataQ!$B:$B,'Data Q to A'!$A13,DataQ!Q:Q) -> -52.05288 | M13: =SUMIF(DataQ!$B:$B,'Data Q to A'!$A13,DataQ!R:R) -> -6.702 | N13: =SUMIF(DataQ!$B:$B,'Data Q to A'!$A13,DataQ!S:S) -> -11.376781 | O13: =SUMIF(DataQ!$B:$B,'Data Q to A'!$A13,DataQ!T:T) -> -10455 | P13: =SUMIF(DataQ!$E:$E,'Data Q to A'!$A13,DataQ!U:U) -> 94137.5 | Q13: =SUMIF(DataQ!$E:$E,'Data Q to A'!$A13,DataQ!V:V) -> 1778.414 | R13: =SUMIF(DataQ!$E:$E,'Data Q to A'!$A13,DataQ!W:W) -> 82162 | S13: =SUMIF(DataQ!$E:$E,'Data Q to A'!$A13,DataQ!X:X) -> 193.9361 | T13: =SUMIF(DataQ!$E:$E,'Data Q to A'!$A13,DataQ!Y:Y) -> 100.8063 | U13: =SUMIF(DataQ!$E:$E,'Data Q to A'!$A13,DataQ!Z:Z) -> 121.674 | V13: =SUMIF(DataQ!$E:$E,'Data Q to A'!$A13,DataQ!AA:AA) -> 123288 | W13: =SUMIF(DataQ!$B:$B,'Data Q to A'!$A13,DataQ!AB:AB) -> 186141 | X13: =SUMIF(DataQ!$B:$B,'Data Q to A'!$A13,DataQ!AC:AC) -> 2351.6 | Y13: =SUMIF(DataQ!$B:$B,'Data Q to A'!$A13,DataQ!AD:AD) -> 210468.72 | Z13: =SUMIF(DataQ!$B:$B,'Data Q to A'!$A13,DataQ!AE:AE) -> 771.5664 | AA13: =SUMIF(DataQ!$B:$B,'Data Q to A'!$A13,DataQ!AF:AF) -> 345.187 | AB13: =SUMIF(DataQ!$B:$B,'Data Q to A'!$A13,DataQ!AG:AG) -> 138.022 | AC13: =SUMIF(DataQ!$B:$B,'Data Q to A'!$A13,DataQ!AH:AH) -> 252075
A14: 1979 | B14: =SUMIF(DataQ!$B:$B,'Data Q to A'!$A14,DataQ!G:G) -> 1164860 | C14: =SUMIF(DataQ!$B:$B,'Data Q to A'!$A14,DataQ!H:H) -> 7276 | D14: =SUMIF(DataQ!$B:$B,'Data Q to A'!$A14,DataQ!I:I) -> 261577.77 | E14: =SUMIF(DataQ!$B:$B,'Data Q to A'!$A14,DataQ!J:J) -> 1810.62 | F14: =SUMIF(DataQ!$B:$B,'Data Q to A'!$A14,DataQ!K:K) -> 1203.514 | G14: =SUMIF(DataQ!$B:$B,'Data Q to A'!$A14,DataQ!L:L) -> 1147.0066 | H14: =SUMIF(DataQ!$B:$B,'Data Q to A'!$A14,DataQ!M:M) -> 875540.1 | I14: =SUMIF(DataQ!$B:$B,'Data Q to A'!$A14,DataQ!N:N) -> -9364 | J14: =SUMIF(DataQ!$B:$B,'Data Q to A'!$A14,DataQ!O:O) -> -78.56225 | K14: =SUMIF(DataQ!$B:$B,'Data Q to A'!$A14,DataQ!P:P) -> -12426.5 | L14: =SUMIF(DataQ!$B:$B,'Data Q to A'!$A14,DataQ!Q:Q) -> -58.44036 | M14: =SUMIF(DataQ!$B:$B,'Data Q to A'!$A14,DataQ!R:R) -> -1.934 | N14: =SUMIF(DataQ!$B:$B,'Data Q to A'!$A14,DataQ!S:S) -> -13.51795 | O14: =SUMIF(DataQ!$B:$B,'Data Q to A'!$A14,DataQ!T:T) -> -8532 | P14: =SUMIF(DataQ!$E:$E,'Data Q to A'!$A14,DataQ!U:U) -> 104807 | Q14: =SUMIF(DataQ!$E:$E,'Data Q to A'!$A14,DataQ!V:V) -> 1922.42 | R14: =SUMIF(DataQ!$E:$E,'Data Q to A'!$A14,DataQ!W:W) -> 98956 | S14: =SUMIF(DataQ!$E:$E,'Data Q to A'!$A14,DataQ!X:X) -> 217.6445 | T14: =SUMIF(DataQ!$E:$E,'Data Q to A'!$A14,DataQ!Y:Y) -> 115.7283 | U14: =SUMIF(DataQ!$E:$E,'Data Q to A'!$A14,DataQ!Z:Z) -> 146.611 | V14: =SUMIF(DataQ!$E:$E,'Data Q to A'!$A14,DataQ!AA:AA) -> 132680 | W14: =SUMIF(DataQ!$B:$B,'Data Q to A'!$A14,DataQ!AB:AB) -> 220966 | X14: =SUMIF(DataQ!$B:$B,'Data Q to A'!$A14,DataQ!AC:AC) -> 2627.325 | Y14: =SUMIF(DataQ!$B:$B,'Data Q to A'!$A14,DataQ!AD:AD) -> 227860.58 | Z14: =SUMIF(DataQ!$B:$B,'Data Q to A'!$A14,DataQ!AE:AE) -> 839.0251 | AA14: =SUMIF(DataQ!$B:$B,'Data Q to A'!$A14,DataQ!AF:AF) -> 394.491 | AB14: =SUMIF(DataQ!$B:$B,'Data Q to A'!$A14,DataQ!AG:AG) -> 168.884 | AC14: =SUMIF(DataQ!$B:$B,'Data Q to A'!$A14,DataQ!AH:AH) -> 287608
A15: 1980 | B15: =SUMIF(DataQ!$B:$B,'Data Q to A'!$A15,DataQ!G:G) -> 1140989 | C15: =SUMIF(DataQ!$B:$B,'Data Q to A'!$A15,DataQ!H:H) -> 7257.325 | D15: =SUMIF(DataQ!$B:$B,'Data Q to A'!$A15,DataQ!I:I) -> 272992.43 | E15: =SUMIF(DataQ!$B:$B,'Data Q to A'!$A15,DataQ!J:J) -> 1833.95 | F15: =SUMIF(DataQ!$B:$B,'Data Q to A'!$A15,DataQ!K:K) -> 1223.307 | G15: =SUMIF(DataQ!$B:$B,'Data Q to A'!$A15,DataQ!L:L) -> 1186.9547 | H15: =SUMIF(DataQ!$B:$B,'Data Q to A'!$A15,DataQ!M:M) -> 894602.4 | I15: =SUMIF(DataQ!$B:$B,'Data Q to A'!$A15,DataQ!N:N) -> -10041 | J15: =SUMIF(DataQ!$B:$B,'Data Q to A'!$A15,DataQ!O:O) -> -128.273 | K15: =SUMIF(DataQ!$B:$B,'Data Q to A'!$A15,DataQ!P:P) -> -11822.5 | L15: =SUMIF(DataQ!$B:$B,'Data Q to A'!$A15,DataQ!Q:Q) -> -62.0868 | M15: =SUMIF(DataQ!$B:$B,'Data Q to A'!$A15,DataQ!R:R) -> -1.928 | N15: =SUMIF(DataQ!$B:$B,'Data Q to A'!$A15,DataQ!S:S) -> -14.305154 | O15: =SUMIF(DataQ!$B:$B,'Data Q to A'!$A15,DataQ!T:T) -> -11149 | P15: =SUMIF(DataQ!$E:$E,'Data Q to A'!$A15,DataQ!U:U) -> 121541.3 | Q15: =SUMIF(DataQ!$E:$E,'Data Q to A'!$A15,DataQ!V:V) -> 2062.851 | R15: =SUMIF(DataQ!$E:$E,'Data Q to A'!$A15,DataQ!W:W) -> 117360 | S15: =SUMIF(DataQ!$E:$E,'Data Q to A'!$A15,DataQ!X:X) -> 248.8942 | T15: =SUMIF(DataQ!$E:$E,'Data Q to A'!$A15,DataQ!Y:Y) -> 129.1328 | U15: =SUMIF(DataQ!$E:$E,'Data Q to A'!$A15,DataQ!Z:Z) -> 178.644 | V15: =SUMIF(DataQ!$E:$E,'Data Q to A'!$A15,DataQ!AA:AA) -> 150393 | W15: =SUMIF(DataQ!$B:$B,'Data Q to A'!$A15,DataQ!AB:AB) -> 259956 | X15: =SUMIF(DataQ!$B:$B,'Data Q to A'!$A15,DataQ!AC:AC) -> 2857.325 | Y15: =SUMIF(DataQ!$B:$B,'Data Q to A'!$A15,DataQ!AD:AD) -> 255596.35 | Z15: =SUMIF(DataQ!$B:$B,'Data Q to A'!$A15,DataQ!AE:AE) -> 896.4522 | AA15: =SUMIF(DataQ!$B:$B,'Data Q to A'!$A15,DataQ!AF:AF) -> 447.345 | AB15: =SUMIF(DataQ!$B:$B,'Data Q to A'!$A15,DataQ!AG:AG) -> 217.501 | AC15: =SUMIF(DataQ!$B:$B,'Data Q to A'!$A15,DataQ!AH:AH) -> 322782
A16: 1981 | B16: =SUMIF(DataQ!$B:$B,'Data Q to A'!$A16,DataQ!G:G) -> 1134663 | C16: =SUMIF(DataQ!$B:$B,'Data Q to A'!$A16,DataQ!H:H) -> 7441.475 | D16: =SUMIF(DataQ!$B:$B,'Data Q to A'!$A16,DataQ!I:I) -> 284947.89 | E16: =SUMIF(DataQ!$B:$B,'Data Q to A'!$A16,DataQ!J:J) -> 1845.86 | F16: =SUMIF(DataQ!$B:$B,'Data Q to A'!$A16,DataQ!K:K) -> 1237.82 | G16: =SUMIF(DataQ!$B:$B,'Data Q to A'!$A16,DataQ!L:L) -> 1197.887 | H16: =SUMIF(DataQ!$B:$B,'Data Q to A'!$A16,DataQ!M:M) -> 925153.7 | I16: =SUMIF(DataQ!$B:$B,'Data Q to A'!$A16,DataQ!N:N) -> -8825 | J16: =SUMIF(DataQ!$B:$B,'Data Q to A'!$A16,DataQ!O:O) -> -130.469 | K16: =SUMIF(DataQ!$B:$B,'Data Q to A'!$A16,DataQ!P:P) -> -10937.75 | L16: =SUMIF(DataQ!$B:$B,'Data Q to A'!$A16,DataQ!Q:Q) -> -75.16716 | M16: =SUMIF(DataQ!$B:$B,'Data Q to A'!$A16,DataQ!R:R) -> -12.242 | N16: =SUMIF(DataQ!$B:$B,'Data Q to A'!$A16,DataQ!S:S) -> -27.037463 | O16: =SUMIF(DataQ!$B:$B,'Data Q to A'!$A16,DataQ!T:T) -> -7830 | P16: =SUMIF(DataQ!$E:$E,'Data Q to A'!$A16,DataQ!U:U) -> 131791.5 | Q16: =SUMIF(DataQ!$E:$E,'Data Q to A'!$A16,DataQ!V:V) -> 2256.733 | R16: =SUMIF(DataQ!$E:$E,'Data Q to A'!$A16,DataQ!W:W) -> 141470 | S16: =SUMIF(DataQ!$E:$E,'Data Q to A'!$A16,DataQ!X:X) -> 287.4771 | T16: =SUMIF(DataQ!$E:$E,'Data Q to A'!$A16,DataQ!Y:Y) -> 141.5108 | U16: =SUMIF(DataQ!$E:$E,'Data Q to A'!$A16,DataQ!Z:Z) -> 224.365 | V16: =SUMIF(DataQ!$E:$E,'Data Q to A'!$A16,DataQ!AA:AA) -> 177353 | W16: =SUMIF(DataQ!$B:$B,'Data Q to A'!$A16,DataQ!AB:AB) -> 290550 | X16: =SUMIF(DataQ!$B:$B,'Data Q to A'!$A16,DataQ!AC:AC) -> 3207.025 | Y16: =SUMIF(DataQ!$B:$B,'Data Q to A'!$A16,DataQ!AD:AD) -> 274362.5 | Z16: =SUMIF(DataQ!$B:$B,'Data Q to A'!$A16,DataQ!AE:AE) -> 939.7564 | AA16: =SUMIF(DataQ!$B:$B,'Data Q to A'!$A16,DataQ!AF:AF) -> 504.566 | AB16: =SUMIF(DataQ!$B:$B,'Data Q to A'!$A16,DataQ!AG:AG) -> 260.06 | AC16: =SUMIF(DataQ!$B:$B,'Data Q to A'!$A16,DataQ!AH:AH) -> 368358
A17: 1982 | B17: =SUMIF(DataQ!$B:$B,'Data Q to A'!$A17,DataQ!G:G) -> 1157191 | C17: =SUMIF(DataQ!$B:$B,'Data Q to A'!$A17,DataQ!H:H) -> 7307.3 | D17: =SUMIF(DataQ!$B:$B,'Data Q to A'!$A17,DataQ!I:I) -> 294351.01 | E17: =SUMIF(DataQ!$B:$B,'Data Q to A'!$A17,DataQ!J:J) -> 1836.61 | F17: =SUMIF(DataQ!$B:$B,'Data Q to A'!$A17,DataQ!K:K) -> 1267.574 | G17: =SUMIF(DataQ!$B:$B,'Data Q to A'!$A17,DataQ!L:L) -> 1201.783 | H17: =SUMIF(DataQ!$B:$B,'Data Q to A'!$A17,DataQ!M:M) -> 895861.9 | I17: =SUMIF(DataQ!$B:$B,'Data Q to A'!$A17,DataQ!N:N) -> -7359 | J17: =SUMIF(DataQ!$B:$B,'Data Q to A'!$A17,DataQ!O:O) -> -220.126 | K17: =SUMIF(DataQ!$B:$B,'Data Q to A'!$A17,DataQ!P:P) -> -11134.25 | L17: =SUMIF(DataQ!$B:$B,'Data Q to A'!$A17,DataQ!Q:Q) -> -74.95508 | M17: =SUMIF(DataQ!$B:$B,'Data Q to A'!$A17,DataQ!R:R) -> -16.498 | N17: =SUMIF(DataQ!$B:$B,'Data Q to A'!$A17,DataQ!S:S) -> -29.281416 | O17: =SUMIF(DataQ!$B:$B,'Data Q to A'!$A17,DataQ!T:T) -> -23407 | P17: =SUMIF(DataQ!$E:$E,'Data Q to A'!$A17,DataQ!U:U) -> 140578.8 | Q17: =SUMIF(DataQ!$E:$E,'Data Q to A'!$A17,DataQ!V:V) -> 2532.298 | R17: =SUMIF(DataQ!$E:$E,'Data Q to A'!$A17,DataQ!W:W) -> 165196 | S17: =SUMIF(DataQ!$E:$E,'Data Q to A'!$A17,DataQ!X:X) -> 320.4308 | T17: =SUMIF(DataQ!$E:$E,'Data Q to A'!$A17,DataQ!Y:Y) -> 184.3563 | U17: =SUMIF(DataQ!$E:$E,'Data Q to A'!$A17,DataQ!Z:Z) -> 275.674 | V17: =SUMIF(DataQ!$E:$E,'Data Q to A'!$A17,DataQ!AA:AA) -> 209732 | W17: =SUMIF(DataQ!$B:$B,'Data Q to A'!$A17,DataQ!AB:AB) -> 320013 | X17: =SUMIF(DataQ!$B:$B,'Data Q to A'!$A17,DataQ!AC:AC) -> 3343.8 | Y17: =SUMIF(DataQ!$B:$B,'Data Q to A'!$A17,DataQ!AD:AD) -> 288540.02 | Z17: =SUMIF(DataQ!$B:$B,'Data Q to A'!$A17,DataQ!AE:AE) -> 977.803 | AA17: =SUMIF(DataQ!$B:$B,'Data Q to A'!$A17,DataQ!AF:AF) -> 578.925 | AB17: =SUMIF(DataQ!$B:$B,'Data Q to A'!$A17,DataQ!AG:AG) -> 306.689 | AC17: =SUMIF(DataQ!$B:$B,'Data Q to A'!$A17,DataQ!AH:AH) -> 388181
A18: 1983 | B18: =SUMIF(DataQ!$B:$B,'Data Q to A'!$A18,DataQ!G:G) -> 1205632 | C18: =SUMIF(DataQ!$B:$B,'Data Q to A'!$A18,DataQ!H:H) -> 7642.275 | D18: =SUMIF(DataQ!$B:$B,'Data Q to A'!$A18,DataQ!I:I) -> 304984.68 | E18: =SUMIF(DataQ!$B:$B,'Data Q to A'!$A18,DataQ!J:J) -> 1863.58 | F18: =SUMIF(DataQ!$B:$B,'Data Q to A'!$A18,DataQ!K:K) -> 1283.577 | G18: =SUMIF(DataQ!$B:$B,'Data Q to A'!$A18,DataQ!L:L) -> 1218.202 | H18: =SUMIF(DataQ!$B:$B,'Data Q to A'!$A18,DataQ!M:M) -> 918816.2 | I18: =SUMIF(DataQ!$B:$B,'Data Q to A'!$A18,DataQ!N:N) -> -10582 | J18: =SUMIF(DataQ!$B:$B,'Data Q to A'!$A18,DataQ!O:O) -> -265.23725 | K18: =SUMIF(DataQ!$B:$B,'Data Q to A'!$A18,DataQ!P:P) -> -11809.25 | L18: =SUMIF(DataQ!$B:$B,'Data Q to A'!$A18,DataQ!Q:Q) -> -71.17676 | M18: =SUMIF(DataQ!$B:$B,'Data Q to A'!$A18,DataQ!R:R) -> -16.481 | N18: =SUMIF(DataQ!$B:$B,'Data Q to A'!$A18,DataQ!S:S) -> -34.423509 | O18: =SUMIF(DataQ!$B:$B,'Data Q to A'!$A18,DataQ!T:T) -> -30637 | P18: =SUMIF(DataQ!$E:$E,'Data Q to A'!$A18,DataQ!U:U) -> 152083.3 | Q18: =SUMIF(DataQ!$E:$E,'Data Q to A'!$A18,DataQ!V:V) -> 2812.196 | R18: =SUMIF(DataQ!$E:$E,'Data Q to A'!$A18,DataQ!W:W) -> 189884 | S18: =SUMIF(DataQ!$E:$E,'Data Q to A'!$A18,DataQ!X:X) -> 347.2786 | T18: =SUMIF(DataQ!$E:$E,'Data Q to A'!$A18,DataQ!Y:Y) -> 210.6735 | U18: =SUMIF(DataQ!$E:$E,'Data Q to A'!$A18,DataQ!Z:Z) -> 269.128 | V18: =SUMIF(DataQ!$E:$E,'Data Q to A'!$A18,DataQ!AA:AA) -> 251868 | W18: =SUMIF(DataQ!$B:$B,'Data Q to A'!$A18,DataQ!AB:AB) -> 351900 | X18: =SUMIF(DataQ!$B:$B,'Data Q to A'!$A18,DataQ!AC:AC) -> 3634.025 | Y18: =SUMIF(DataQ!$B:$B,'Data Q to A'!$A18,DataQ!AD:AD) -> 301733.15 | Z18: =SUMIF(DataQ!$B:$B,'Data Q to A'!$A18,DataQ!AE:AE) -> 1020.0841 | AA18: =SUMIF(DataQ!$B:$B,'Data Q to A'!$A18,DataQ!AF:AF) -> 642.54 | AB18: =SUMIF(DataQ!$B:$B,'Data Q to A'!$A18,DataQ!AG:AG) -> 357.802 | AC18: =SUMIF(DataQ!$B:$B,'Data Q to A'!$A18,DataQ!AH:AH) -> 421316
A19: 1984 | B19: =SUMIF(DataQ!$B:$B,'Data Q to A'!$A19,DataQ!G:G) -> 1232675 | C19: =SUMIF(DataQ!$B:$B,'Data Q to A'!$A19,DataQ!H:H) -> 8195.3 | D19: =SUMIF(DataQ!$B:$B,'Data Q to A'!$A19,DataQ!I:I) -> 318480.11 | E19: =SUMIF(DataQ!$B:$B,'Data Q to A'!$A19,DataQ!J:J) -> 1917.61 | F19: =SUMIF(DataQ!$B:$B,'Data Q to A'!$A19,DataQ!K:K) -> 1305.053 | G19: =SUMIF(DataQ!$B:$B,'Data Q to A'!$A19,DataQ!L:L) -> 1257.309 | H19: =SUMIF(DataQ!$B:$B,'Data Q to A'!$A19,DataQ!M:M) -> 973013.1 | I19: =SUMIF(DataQ!$B:$B,'Data Q to A'!$A19,DataQ!N:N) -> -12423 | J19: =SUMIF(DataQ!$B:$B,'Data Q to A'!$A19,DataQ!O:O) -> -249.608 | K19: =SUMIF(DataQ!$B:$B,'Data Q to A'!$A19,DataQ!P:P) -> -8204.75 | L19: =SUMIF(DataQ!$B:$B,'Data Q to A'!$A19,DataQ!Q:Q) -> -66.7484 | M19: =SUMIF(DataQ!$B:$B,'Data Q to A'!$A19,DataQ!R:R) -> -19.303 | N19: =SUMIF(DataQ!$B:$B,'Data Q to A'!$A19,DataQ!S:S) -> -44.8364 | O19: =SUMIF(DataQ!$B:$B,'Data Q to A'!$A19,DataQ!T:T) -> -33224.999 | P19: =SUMIF(DataQ!$E:$E,'Data Q to A'!$A19,DataQ!U:U) -> 163648.5 | Q19: =SUMIF(DataQ!$E:$E,'Data Q to A'!$A19,DataQ!V:V) -> 3161.467 | R19: =SUMIF(DataQ!$E:$E,'Data Q to A'!$A19,DataQ!W:W) -> 208326 | S19: =SUMIF(DataQ!$E:$E,'Data Q to A'!$A19,DataQ!X:X) -> 369.349 | T19: =SUMIF(DataQ!$E:$E,'Data Q to A'!$A19,DataQ!Y:Y) -> 240.8142 | U19: =SUMIF(DataQ!$E:$E,'Data Q to A'!$A19,DataQ!Z:Z) -> 318.727 | V19: =SUMIF(DataQ!$E:$E,'Data Q to A'!$A19,DataQ!AA:AA) -> 290671 | W19: =SUMIF(DataQ!$B:$B,'Data Q to A'!$A19,DataQ!AB:AB) -> 378608 | X19: =SUMIF(DataQ!$B:$B,'Data Q to A'!$A19,DataQ!AC:AC) -> 4037.65 | Y19: =SUMIF(DataQ!$B:$B,'Data Q to A'!$A19,DataQ!AD:AD) -> 319635.48 | Z19: =SUMIF(DataQ!$B:$B,'Data Q to A'!$A19,DataQ!AE:AE) -> 1070.7138 | AA19: =SUMIF(DataQ!$B:$B,'Data Q to A'!$A19,DataQ!AF:AF) -> 699.5 | AB19: =SUMIF(DataQ!$B:$B,'Data Q to A'!$A19,DataQ!AG:AG) -> 409.026 | AC19: =SUMIF(DataQ!$B:$B,'Data Q to A'!$A19,DataQ!AH:AH) -> 461986
... A95: 2060 | B95: =SUMIF(DataQ!$B:$B,'Data Q to A'!$A95,DataQ!G:G) -> 4637065 | C95: =SUMIF(DataQ!$B:$B,'Data Q to A'!$A95,DataQ!H:H) -> 43795.78 | D95: =SUMIF(DataQ!$B:$B,'Data Q to A'!$A95,DataQ!I:I) -> 575869.8 | E95: =SUMIF(DataQ!$B:$B,'Data Q to A'!$A95,DataQ!J:J) -> 4946.232 | F95: =SUMIF(DataQ!$B:$B,'Data Q to A'!$A95,DataQ!K:K) -> 3240.5261 | G95: =SUMIF(DataQ!$B:$B,'Data Q to A'!$A95,DataQ!L:L) -> 2177.9131 | H95: =SUMIF(DataQ!$B:$B,'Data Q to A'!$A95,DataQ!M:M) -> 4689823 | I95: =SUMIF(DataQ!$B:$B,'Data Q to A'!$A95,DataQ!N:N) -> -434469.33 | J95: =SUMIF(DataQ!$B:$B,'Data Q to A'!$A95,DataQ!O:O) -> -4188.266 | K95: =SUMIF(DataQ!$B:$B,'Data Q to A'!$A95,DataQ!P:P) -> -9878.532 | L95: =SUMIF(DataQ!$B:$B,'Data Q to A'!$A95,DataQ!Q:Q) -> -182.69702 | M95: =SUMIF(DataQ!$B:$B,'Data Q to A'!$A95,DataQ!R:R) -> -255.30535 | N95: =SUMIF(DataQ!$B:$B,'Data Q to A'!$A95,DataQ!S:S) -> -87.70124 | O95: =SUMIF(DataQ!$B:$B,'Data Q to A'!$A95,DataQ!T:T) -> -289162.51 | P95: =SUMIF(DataQ!$E:$E,'Data Q to A'!$A95,DataQ!U:U) -> 11590690 | Q95: =SUMIF(DataQ!$E:$E,'Data Q to A'!$A95,DataQ!V:V) -> 182333.2 | R95: =SUMIF(DataQ!$E:$E,'Data Q to A'!$A95,DataQ!W:W) -> 1742120 | S95: =SUMIF(DataQ!$E:$E,'Data Q to A'!$A95,DataQ!X:X) -> 7376.668 | T95: =SUMIF(DataQ!$E:$E,'Data Q to A'!$A95,DataQ!Y:Y) -> 10292.69 | U95: =SUMIF(DataQ!$E:$E,'Data Q to A'!$A95,DataQ!Z:Z) -> 5757.584 | V95: =SUMIF(DataQ!$E:$E,'Data Q to A'!$A95,DataQ!AA:AA) -> 9254375 | W95: =SUMIF(DataQ!$B:$B,'Data Q to A'!$A95,DataQ!AB:AB) -> 10547161 | X95: =SUMIF(DataQ!$B:$B,'Data Q to A'!$A95,DataQ!AC:AC) -> 108570.98 | Y95: =SUMIF(DataQ!$B:$B,'Data Q to A'!$A95,DataQ!AD:AD) -> 1059071.7 | Z95: =SUMIF(DataQ!$B:$B,'Data Q to A'!$A95,DataQ!AE:AE) -> 12542.691 | AA95: =SUMIF(DataQ!$B:$B,'Data Q to A'!$A95,DataQ!AF:AF) -> 7372.173 | AB95: =SUMIF(DataQ!$B:$B,'Data Q to A'!$A95,DataQ!AG:AG) -> 4946.305 | AC95: =SUMIF(DataQ!$B:$B,'Data Q to A'!$A95,DataQ!AH:AH) -> 11874134

Sheet DataQ
G1: =GMWQ!NF2 -> OCT004A.db | H1: =$G$1 -> OCT004A.db | I1: =$G$1 -> OCT004A.db | J1: =$G$1 -> OCT004A.db | K1: =$G$1 -> OCT004A.db | L1: =$G$1 -> OCT004A.db | M1: =$G$1 -> OCT004A.db | N1: =$G$1 -> OCT004A.db | O1: =$G$1 -> OCT004A.db | ... AL1: =$G$1 -> OCT004A.db
G2: UK | H2: US | I2: Japan | J2: Germany | K2: France | L2: Italy | M2: Canada | N2: UK | O2: US | P2: Japan | Q2: Germany | R2: France | S2: Italy | T2: Canada | U2: UK | V2: US | W2: Japan | X2: Germany | Y2: France | Z2: Italy | AA2: Canada | AB2: UK | AC2: US | AD2: Japan | AE2: Germany | AF2: France | AG2: Italy | AH2: Canada | AI2: UK | AJ2: US | AK2: Germany | AL2: Japan
G3: GDP | H3: GDP | I3: GDP | J3: GDP | K3: GDP | L3: GDP | M3: GDP | N3: GB | O3: GB | P3: GB | Q3: GB | R3: GB | S3: GB | T3: GB | U3: GGDBT | V3: GGDBT | W3: GGDBT | X3: GGDBT | Y3: GGDBT | Z3: GGDBT | AA3: GGDBT | AB3: GDP! | AC3: GDP! | AD3: GDP! | AE3: GDP! | AF3: GDP! | AG3: GDP! | AH3: GDP! | AI3: RLG_TERM_PREM | AJ3: RLG_TERM_PREM | AK3: RLG_TERM_PREM | AL3: RLG_TERM_PREM
G4: GBR | H4: USA | I4: JPN | J4: DEU | K4: FRA | L4: ITA | M4: CAN | N4: GBR | O4: USA | P4: JPN | Q4: DEU | R4: FRA | S4: ITA | T4: CAN | U4: GBR | V4: USA | W4: JPN | X4: DEU | Y4: FRA | Z4: ITA | AA4: CAN | AB4: GBR | AC4: USA | AD4: JPN | AE4: DEU | AF4: FRA | AG4: ITA | AH4: CAN | AI4: GBR | AJ4: USA | AK4: DEU | AL4: JPN
G5: L | H5: L | I5: L | J5: L | K5: L | L5: L | M5: L | N5: L | O5: L | P5: L | Q5: L | R5: L | S5: L | T5: L | U5: L | V5: L | W5: L | X5: L | Y5: L | Z5: L | AA5: L | AB5: L | AC5: L | AD5: L | AE5: L | AF5: L | AG5: L | AH5: L | AI5: L | AJ5: L | AK5: L | AL5: L
B6: CYs | C6: FYs | D6: FY end | E6: CY end | F6: =F358+5 -> 2329 | G6: {=_xlfn.CONCAT(INDEX(GMWQ!$A$2:$NE$60,MATCH(1,(GMWQ!$NE$2:$NE$60=G$3)*(GMWQ!$ND$2:$ND$60=G$4)*(GMWQ!$NF$2:$NF$60=G$1),0),$F6-1966),"0",(INDEX(GMWQ!$A$2:$NE$60,MATCH(1,(GMWQ!$NE$2:$NE$60=G$3)*(GMWQ!$ND$2:$ND$60=G$4)*(GMWQ!$NF$2:$NF$60=G$1),0),$F6-1965)))} -> 202502 | H6: {=_xlfn.CONCAT(INDEX(GMWQ!$A$2:$NE$60,MATCH(1,(GMWQ!$NE$2:$NE$60=H$3)*(GMWQ!$ND$2:$ND$60=H$4)*(GMWQ!$NF$2:$NF$60=H$1),0),$F6-1966),"0",(INDEX(GMWQ!$A$2:$NE$60,MATCH(1,(GMWQ!$NE$2:$NE$60=H$3)*(GMWQ!$ND$2:$ND$60=H$4)*(GMWQ!$NF$2:$NF$60=H$1),0),$F6-1965)))} -> 202502 | I6: {=_xlfn.CONCAT(INDEX(GMWQ!$A$2:$NE$60,MATCH(1,(GMWQ!$NE$2:$NE$60=I$3)*(GMWQ!$ND$2:$ND$60=I$4)*(GMWQ!$NF$2:$NF$60=I$1),0),$F6-1966),"0",(INDEX(GMWQ!$A$2:$NE$60,MATCH(1,(GMWQ!$NE$2:$NE$60=I$3)*(GMWQ!$ND$2:$ND$60=I$4)*(GMWQ!$NF$2:$NF$60=I$1),0),$F6-1965)))} -> 202502 | J6: {=_xlfn.CONCAT(INDEX(GMWQ!$A$2:$NE$60,MATCH(1,(GMWQ!$NE$2:$NE$60=J$3)*(GMWQ!$ND$2:$ND$60=J$4)*(GMWQ!$NF$2:$NF$60=J$1),0),$F6-1966),"0",(INDEX(GMWQ!$A$2:$NE$60,MATCH(1,(GMWQ!$NE$2:$NE$60=J$3)*(GMWQ!$ND$2:$ND$60=J$4)*(GMWQ!$NF$2:$NF$60=J$1),0),$F6-1965)))} -> 202502 | K6: {=_xlfn.CONCAT(INDEX(GMWQ!$A$2:$NE$60,MATCH(1,(GMWQ!$NE$2:$NE$60=K$3)*(GMWQ!$ND$2:$ND$60=K$4)*(GMWQ!$NF$2:$NF$60=K$1),0),$F6-1966),"0",(INDEX(GMWQ!$A$2:$NE$60,MATCH(1,(GMWQ!$NE$2:$NE$60=K$3)*(GMWQ!$ND$2:$ND$60=K$4)*(GMWQ!$NF$2:$NF$60=K$1),0),$F6-1965)))} -> 202502 | L6: {=_xlfn.CONCAT(INDEX(GMWQ!$A$2:$NE$60,MATCH(1,(GMWQ!$NE$2:$NE$60=L$3)*(GMWQ!$ND$2:$ND$60=L$4)*(GMWQ!$NF$2:$NF$60=L$1),0),$F6-1966),"0",(INDEX(GMWQ!$A$2:$NE$60,MATCH(1,(GMWQ!$NE$2:$NE$60=L$3)*(GMWQ!$ND$2:$ND$60=L$4)*(GMWQ!$NF$2:$NF$60=L$1),0),$F6-1965)))} -> 202502 | M6: {=_xlfn.CONCAT(INDEX(GMWQ!$A$2:$NE$60,MATCH(1,(GMWQ!$NE$2:$NE$60=M$3)*(GMWQ!$ND$2:$ND$60=M$4)*(GMWQ!$NF$2:$NF$60=M$1),0),$F6-1966),"0",(INDEX(GMWQ!$A$2:$NE$60,MATCH(1,(GMWQ!$NE$2:$NE$60=M$3)*(GMWQ!$ND$2:$ND$60=M$4)*(GMWQ!$NF$2:$NF$60=M$1),0),$F6-1965)))} -> 202502 | N6: {=_xlfn.CONCAT(INDEX(GMWQ!$A$2:$NE$60,MATCH(1,(GMWQ!$NE$2:$NE$60=N$3)*(GMWQ!$ND$2:$ND$60=N$4)*(GMWQ!$NF$2:$NF$60=N$1),0),$F6-1966),"0",(INDEX(GMWQ!$A$2:$NE$60,MATCH(1,(GMWQ!$NE$2:$NE$60=N$3)*(GMWQ!$ND$2:$ND$60=N$4)*(GMWQ!$NF$2:$NF$60=N$1),0),$F6-1965)))} -> 202502 | ... AL6: {=_xlfn.CONCAT(INDEX(GMWQ!$A$2:$NE$60,MATCH(1,(GMWQ!$NE$2:$NE$60=AL$3)*(GMWQ!$ND$2:$ND$60=AL$4)*(GMWQ!$NF$2:$NF$60=AL$1),0),$F6-1966),"0",(INDEX(GMWQ!$A$2:$NE$60,MATCH(1,(GMWQ!$NE$2:$NE$60=AL$3)*(GMWQ!$ND$2:$ND$60=AL$4)*(GMWQ!$NF$2:$NF$60=AL$1),0),$F6-1965)))} -> NA0NA
A7: 1973 | B7: 1973 | F7: 1973 | G7: {=INDEX(GMWQ!$A$2:$NF$60,MATCH(1,(GMWQ!$NE$2:$NE$60=G$3)*(GMWQ!$ND$2:$ND$60=G$4)*(GMWQ!$NF$2:$NF$60=G$1),0),$F7-1966)} -> 267015 | H7: {=INDEX(GMWQ!$A$2:$NF$60,MATCH(1,(GMWQ!$NE$2:$NE$60=H$3)*(GMWQ!$ND$2:$ND$60=H$4)*(GMWQ!$NF$2:$NF$60=H$1),0),$F7-1966)} -> 1514.625 | I7: {=INDEX(GMWQ!$A$2:$NF$60,MATCH(1,(GMWQ!$NE$2:$NE$60=I$3)*(GMWQ!$ND$2:$ND$60=I$4)*(GMWQ!$NF$2:$NF$60=I$1),0),$F7-1966)} -> 52242.65 | J7: {=INDEX(GMWQ!$A$2:$NF$60,MATCH(1,(GMWQ!$NE$2:$NE$60=J$3)*(GMWQ!$ND$2:$ND$60=J$4)*(GMWQ!$NF$2:$NF$60=J$1),0),$F7-1966)} -> 386.07 | K7: {=INDEX(GMWQ!$A$2:$NF$60,MATCH(1,(GMWQ!$NE$2:$NE$60=K$3)*(GMWQ!$ND$2:$ND$60=K$4)*(GMWQ!$NF$2:$NF$60=K$1),0),$F7-1966)} -> 244.379 | L7: {=INDEX(GMWQ!$A$2:$NF$60,MATCH(1,(GMWQ!$NE$2:$NE$60=L$3)*(GMWQ!$ND$2:$ND$60=L$4)*(GMWQ!$NF$2:$NF$60=L$1),0),$F7-1966)} -> 223.0287 | M7: {=INDEX(GMWQ!$A$2:$NF$60,MATCH(1,(GMWQ!$NE$2:$NE$60=M$3)*(GMWQ!$ND$2:$ND$60=M$4)*(GMWQ!$NF$2:$NF$60=M$1),0),$F7-1966)} -> 174319.5 | N7: {=INDEX(GMWQ!$A$2:$NF$60,MATCH(1,(GMWQ!$NE$2:$NE$60=N$3)*(GMWQ!$ND$2:$ND$60=N$4)*(GMWQ!$NF$2:$NF$60=N$1),0),$F7-1966)} -> -145 | ... AL7: {=INDEX(GMWQ!$A$2:$NF$60,MATCH(1,(GMWQ!$NE$2:$NE$60=AL$3)*(GMWQ!$ND$2:$ND$60=AL$4)*(GMWQ!$NF$2:$NF$60=AL$1),0),$F7-1966)} -> 0
B8: 1973 | C8: 1973 | F8: =+F7+1 -> 1974 | G8: {=INDEX(GMWQ!$A$2:$NF$60,MATCH(1,(GMWQ!$NE$2:$NE$60=G$3)*(GMWQ!$ND$2:$ND$60=G$4)*(GMWQ!$NF$2:$NF$60=G$1),0),$F8-1966)} -> 267521 | H8: {=INDEX(GMWQ!$A$2:$NF$60,MATCH(1,(GMWQ!$NE$2:$NE$60=H$3)*(GMWQ!$ND$2:$ND$60=H$4)*(GMWQ!$NF$2:$NF$60=H$1),0),$F8-1966)} -> 1531.125 | I8: {=INDEX(GMWQ!$A$2:$NF$60,MATCH(1,(GMWQ!$NE$2:$NE$60=I$3)*(GMWQ!$ND$2:$ND$60=I$4)*(GMWQ!$NF$2:$NF$60=I$1),0),$F8-1966)} -> 52722.43 | J8: {=INDEX(GMWQ!$A$2:$NF$60,MATCH(1,(GMWQ!$NE$2:$NE$60=J$3)*(GMWQ!$ND$2:$ND$60=J$4)*(GMWQ!$NF$2:$NF$60=J$1),0),$F8-1966)} -> 388.81 | K8: {=INDEX(GMWQ!$A$2:$NF$60,MATCH(1,(GMWQ!$NE$2:$NE$60=K$3)*(GMWQ!$ND$2:$ND$60=K$4)*(GMWQ!$NF$2:$NF$60=K$1),0),$F8-1966)} -> 247.949 | L8: {=INDEX(GMWQ!$A$2:$NF$60,MATCH(1,(GMWQ!$NE$2:$NE$60=L$3)*(GMWQ!$ND$2:$ND$60=L$4)*(GMWQ!$NF$2:$NF$60=L$1),0),$F8-1966)} -> 229.7104 | M8: {=INDEX(GMWQ!$A$2:$NF$60,MATCH(1,(GMWQ!$NE$2:$NE$60=M$3)*(GMWQ!$ND$2:$ND$60=M$4)*(GMWQ!$NF$2:$NF$60=M$1),0),$F8-1966)} -> 175982.5 | N8: {=INDEX(GMWQ!$A$2:$NF$60,MATCH(1,(GMWQ!$NE$2:$NE$60=N$3)*(GMWQ!$ND$2:$ND$60=N$4)*(GMWQ!$NF$2:$NF$60=N$1),0),$F8-1966)} -> -1195 | ... AL8: {=INDEX(GMWQ!$A$2:$NF$60,MATCH(1,(GMWQ!$NE$2:$NE$60=AL$3)*(GMWQ!$ND$2:$ND$60=AL$4)*(GMWQ!$NF$2:$NF$60=AL$1),0),$F8-1966)} -> 0
B9: 1973 | C9: 1973 | F9: =+F8+1 -> 1975 | G9: {=INDEX(GMWQ!$A$2:$NF$60,MATCH(1,(GMWQ!$NE$2:$NE$60=G$3)*(GMWQ!$ND$2:$ND$60=G$4)*(GMWQ!$NF$2:$NF$60=G$1),0),$F9-1966)} -> 265025 | H9: {=INDEX(GMWQ!$A$2:$NF$60,MATCH(1,(GMWQ!$NE$2:$NE$60=H$3)*(GMWQ!$ND$2:$ND$60=H$4)*(GMWQ!$NF$2:$NF$60=H$1),0),$F9-1966)} -> 1523.075 | I9: {=INDEX(GMWQ!$A$2:$NF$60,MATCH(1,(GMWQ!$NE$2:$NE$60=I$3)*(GMWQ!$ND$2:$ND$60=I$4)*(GMWQ!$NF$2:$NF$60=I$1),0),$F9-1966)} -> 52875.77 | J9: {=INDEX(GMWQ!$A$2:$NF$60,MATCH(1,(GMWQ!$NE$2:$NE$60=J$3)*(GMWQ!$ND$2:$ND$60=J$4)*(GMWQ!$NF$2:$NF$60=J$1),0),$F9-1966)} -> 390.14 | K9: {=INDEX(GMWQ!$A$2:$NF$60,MATCH(1,(GMWQ!$NE$2:$NE$60=K$3)*(GMWQ!$ND$2:$ND$60=K$4)*(GMWQ!$NF$2:$NF$60=K$1),0),$F9-1966)} -> 251.887 | L9: {=INDEX(GMWQ!$A$2:$NF$60,MATCH(1,(GMWQ!$NE$2:$NE$60=L$3)*(GMWQ!$ND$2:$ND$60=L$4)*(GMWQ!$NF$2:$NF$60=L$1),0),$F9-1966)} -> 237.0208 | M9: {=INDEX(GMWQ!$A$2:$NF$60,MATCH(1,(GMWQ!$NE$2:$NE$60=M$3)*(GMWQ!$ND$2:$ND$60=M$4)*(GMWQ!$NF$2:$NF$60=M$1),0),$F9-1966)} -> 176800.8 | N9: {=INDEX(GMWQ!$A$2:$NF$60,MATCH(1,(GMWQ!$NE$2:$NE$60=N$3)*(GMWQ!$ND$2:$ND$60=N$4)*(GMWQ!$NF$2:$NF$60=N$1),0),$F9-1966)} -> -676 | ... AL9: {=INDEX(GMWQ!$A$2:$NF$60,MATCH(1,(GMWQ!$NE$2:$NE$60=AL$3)*(GMWQ!$ND$2:$ND$60=AL$4)*(GMWQ!$NF$2:$NF$60=AL$1),0),$F9-1966)} -> 0
B10: 1973 | C10: 1973 | E10: 1973 | F10: =+F9+1 -> 1976 | G10: {=INDEX(GMWQ!$A$2:$NF$60,MATCH(1,(GMWQ!$NE$2:$NE$60=G$3)*(GMWQ!$ND$2:$ND$60=G$4)*(GMWQ!$NF$2:$NF$60=G$1),0),$F10-1966)} -> 263989 | H10: {=INDEX(GMWQ!$A$2:$NF$60,MATCH(1,(GMWQ!$NE$2:$NE$60=H$3)*(GMWQ!$ND$2:$ND$60=H$4)*(GMWQ!$NF$2:$NF$60=H$1),0),$F10-1966)} -> 1537.525 | I10: {=INDEX(GMWQ!$A$2:$NF$60,MATCH(1,(GMWQ!$NE$2:$NE$60=I$3)*(GMWQ!$ND$2:$ND$60=I$4)*(GMWQ!$NF$2:$NF$60=I$1),0),$F10-1966)} -> 53539.66 | J10: {=INDEX(GMWQ!$A$2:$NF$60,MATCH(1,(GMWQ!$NE$2:$NE$60=J$3)*(GMWQ!$ND$2:$ND$60=J$4)*(GMWQ!$NF$2:$NF$60=J$1),0),$F10-1966)} -> 391.12 | K10: {=INDEX(GMWQ!$A$2:$NF$60,MATCH(1,(GMWQ!$NE$2:$NE$60=K$3)*(GMWQ!$ND$2:$ND$60=K$4)*(GMWQ!$NF$2:$NF$60=K$1),0),$F10-1966)} -> 254.935 | L10: {=INDEX(GMWQ!$A$2:$NF$60,MATCH(1,(GMWQ!$NE$2:$NE$60=L$3)*(GMWQ!$ND$2:$ND$60=L$4)*(GMWQ!$NF$2:$NF$60=L$1),0),$F10-1966)} -> 242.81 | M10: {=INDEX(GMWQ!$A$2:$NF$60,MATCH(1,(GMWQ!$NE$2:$NE$60=M$3)*(GMWQ!$ND$2:$ND$60=M$4)*(GMWQ!$NF$2:$NF$60=M$1),0),$F10-1966)} -> 180061.8 | N10: {=INDEX(GMWQ!$A$2:$NF$60,MATCH(1,(GMWQ!$NE$2:$NE$60=N$3)*(GMWQ!$ND$2:$ND$60=N$4)*(GMWQ!$NF$2:$NF$60=N$1),0),$F10-1966)} -> -724 | ... AL10: {=INDEX(GMWQ!$A$2:$NF$60,MATCH(1,(GMWQ!$NE$2:$NE$60=AL$3)*(GMWQ!$ND$2:$ND$60=AL$4)*(GMWQ!$NF$2:$NF$60=AL$1),0),$F10-1966)} -> 0
A11: 1974 | B11: =+B7+1 -> 1974 | C11: 1973 | D11: 1973 | F11: =+F10+1 -> 1977 | G11: {=INDEX(GMWQ!$A$2:$NF$60,MATCH(1,(GMWQ!$NE$2:$NE$60=G$3)*(GMWQ!$ND$2:$ND$60=G$4)*(GMWQ!$NF$2:$NF$60=G$1),0),$F11-1966)} -> 256670 | H11: {=INDEX(GMWQ!$A$2:$NF$60,MATCH(1,(GMWQ!$NE$2:$NE$60=H$3)*(GMWQ!$ND$2:$ND$60=H$4)*(GMWQ!$NF$2:$NF$60=H$1),0),$F11-1966)} -> 1524.325 | I11: {=INDEX(GMWQ!$A$2:$NF$60,MATCH(1,(GMWQ!$NE$2:$NE$60=I$3)*(GMWQ!$ND$2:$ND$60=I$4)*(GMWQ!$NF$2:$NF$60=I$1),0),$F11-1966)} -> 51759.14 | J11: {=INDEX(GMWQ!$A$2:$NF$60,MATCH(1,(GMWQ!$NE$2:$NE$60=J$3)*(GMWQ!$ND$2:$ND$60=J$4)*(GMWQ!$NF$2:$NF$60=J$1),0),$F11-1966)} -> 394.27 | K11: {=INDEX(GMWQ!$A$2:$NF$60,MATCH(1,(GMWQ!$NE$2:$NE$60=K$3)*(GMWQ!$ND$2:$ND$60=K$4)*(GMWQ!$NF$2:$NF$60=K$1),0),$F11-1966)} -> 259.118 | L11: {=INDEX(GMWQ!$A$2:$NF$60,MATCH(1,(GMWQ!$NE$2:$NE$60=L$3)*(GMWQ!$ND$2:$ND$60=L$4)*(GMWQ!$NF$2:$NF$60=L$1),0),$F11-1966)} -> 244.7785 | M11: {=INDEX(GMWQ!$A$2:$NF$60,MATCH(1,(GMWQ!$NE$2:$NE$60=M$3)*(GMWQ!$ND$2:$ND$60=M$4)*(GMWQ!$NF$2:$NF$60=M$1),0),$F11-1966)} -> 181552 | N11: {=INDEX(GMWQ!$A$2:$NF$60,MATCH(1,(GMWQ!$NE$2:$NE$60=N$3)*(GMWQ!$ND$2:$ND$60=N$4)*(GMWQ!$NF$2:$NF$60=N$1),0),$F11-1966)} -> -788 | ... AL11: {=INDEX(GMWQ!$A$2:$NF$60,MATCH(1,(GMWQ!$NE$2:$NE$60=AL$3)*(GMWQ!$ND$2:$ND$60=AL$4)*(GMWQ!$NF$2:$NF$60=AL$1),0),$F11-1966)} -> 0
B12: =+B8+1 -> 1974 | C12: =+C8+1 -> 1974 | F12: =+F11+1 -> 1978 | G12: {=INDEX(GMWQ!$A$2:$NF$60,MATCH(1,(GMWQ!$NE$2:$NE$60=G$3)*(GMWQ!$ND$2:$ND$60=G$4)*(GMWQ!$NF$2:$NF$60=G$1),0),$F12-1966)} -> 260347 | H12: {=INDEX(GMWQ!$A$2:$NF$60,MATCH(1,(GMWQ!$NE$2:$NE$60=H$3)*(GMWQ!$ND$2:$ND$60=H$4)*(GMWQ!$NF$2:$NF$60=H$1),0),$F12-1966)} -> 1527.95 | I12: {=INDEX(GMWQ!$A$2:$NF$60,MATCH(1,(GMWQ!$NE$2:$NE$60=I$3)*(GMWQ!$ND$2:$ND$60=I$4)*(GMWQ!$NF$2:$NF$60=I$1),0),$F12-1966)} -> 52134.51 | J12: {=INDEX(GMWQ!$A$2:$NF$60,MATCH(1,(GMWQ!$NE$2:$NE$60=J$3)*(GMWQ!$ND$2:$ND$60=J$4)*(GMWQ!$NF$2:$NF$60=J$1),0),$F12-1966)} -> 393.93 | K12: {=INDEX(GMWQ!$A$2:$NF$60,MATCH(1,(GMWQ!$NE$2:$NE$60=K$3)*(GMWQ!$ND$2:$ND$60=K$4)*(GMWQ!$NF$2:$NF$60=K$1),0),$F12-1966)} -> 260.946 | L12: {=INDEX(GMWQ!$A$2:$NF$60,MATCH(1,(GMWQ!$NE$2:$NE$60=L$3)*(GMWQ!$ND$2:$ND$60=L$4)*(GMWQ!$NF$2:$NF$60=L$1),0),$F12-1966)} -> 247.1172 | M12: {=INDEX(GMWQ!$A$2:$NF$60,MATCH(1,(GMWQ!$NE$2:$NE$60=M$3)*(GMWQ!$ND$2:$ND$60=M$4)*(GMWQ!$NF$2:$NF$60=M$1),0),$F12-1966)} -> 183414.3 | N12: {=INDEX(GMWQ!$A$2:$NF$60,MATCH(1,(GMWQ!$NE$2:$NE$60=N$3)*(GMWQ!$ND$2:$ND$60=N$4)*(GMWQ!$NF$2:$NF$60=N$1),0),$F12-1966)} -> -631 | ... AL12: {=INDEX(GMWQ!$A$2:$NF$60,MATCH(1,(GMWQ!$NE$2:$NE$60=AL$3)*(GMWQ!$ND$2:$ND$60=AL$4)*(GMWQ!$NF$2:$NF$60=AL$1),0),$F12-1966)} -> 0
B13: =+B9+1 -> 1974 | C13: =+C9+1 -> 1974 | F13: =+F12+1 -> 1979 | G13: {=INDEX(GMWQ!$A$2:$NF$60,MATCH(1,(GMWQ!$NE$2:$NE$60=G$3)*(GMWQ!$ND$2:$ND$60=G$4)*(GMWQ!$NF$2:$NF$60=G$1),0),$F13-1966)} -> 261890 | H13: {=INDEX(GMWQ!$A$2:$NF$60,MATCH(1,(GMWQ!$NE$2:$NE$60=H$3)*(GMWQ!$ND$2:$ND$60=H$4)*(GMWQ!$NF$2:$NF$60=H$1),0),$F13-1966)} -> 1513.5 | I13: {=INDEX(GMWQ!$A$2:$NF$60,MATCH(1,(GMWQ!$NE$2:$NE$60=I$3)*(GMWQ!$ND$2:$ND$60=I$4)*(GMWQ!$NF$2:$NF$60=I$1),0),$F13-1966)} -> 52810.48 | J13: {=INDEX(GMWQ!$A$2:$NF$60,MATCH(1,(GMWQ!$NE$2:$NE$60=J$3)*(GMWQ!$ND$2:$ND$60=J$4)*(GMWQ!$NF$2:$NF$60=J$1),0),$F13-1966)} -> 394.09 | K13: {=INDEX(GMWQ!$A$2:$NF$60,MATCH(1,(GMWQ!$NE$2:$NE$60=K$3)*(GMWQ!$ND$2:$ND$60=K$4)*(GMWQ!$NF$2:$NF$60=K$1),0),$F13-1966)} -> 263.841 | L13: {=INDEX(GMWQ!$A$2:$NF$60,MATCH(1,(GMWQ!$NE$2:$NE$60=L$3)*(GMWQ!$ND$2:$ND$60=L$4)*(GMWQ!$NF$2:$NF$60=L$1),0),$F13-1966)} -> 247.5283 | M13: {=INDEX(GMWQ!$A$2:$NF$60,MATCH(1,(GMWQ!$NE$2:$NE$60=M$3)*(GMWQ!$ND$2:$ND$60=M$4)*(GMWQ!$NF$2:$NF$60=M$1),0),$F13-1966)} -> 183449.5 | N13: {=INDEX(GMWQ!$A$2:$NF$60,MATCH(1,(GMWQ!$NE$2:$NE$60=N$3)*(GMWQ!$ND$2:$ND$60=N$4)*(GMWQ!$NF$2:$NF$60=N$1),0),$F13-1966)} -> -1345 | ... AL13: {=INDEX(GMWQ!$A$2:$NF$60,MATCH(1,(GMWQ!$NE$2:$NE$60=AL$3)*(GMWQ!$ND$2:$ND$60=AL$4)*(GMWQ!$NF$2:$NF$60=AL$1),0),$F13-1966)} -> 0
B14: =+B10+1 -> 1974 | C14: =+C10+1 -> 1974 | E14: =+E10+1 -> 1974 | F14: =+F13+1 -> 1980 | G14: {=INDEX(GMWQ!$A$2:$NF$60,MATCH(1,(GMWQ!$NE$2:$NE$60=G$3)*(GMWQ!$ND$2:$ND$60=G$4)*(GMWQ!$NF$2:$NF$60=G$1),0),$F14-1966)} -> 258066 | H14: {=INDEX(GMWQ!$A$2:$NF$60,MATCH(1,(GMWQ!$NE$2:$NE$60=H$3)*(GMWQ!$ND$2:$ND$60=H$4)*(GMWQ!$NF$2:$NF$60=H$1),0),$F14-1966)} -> 1507.625 | I14: {=INDEX(GMWQ!$A$2:$NF$60,MATCH(1,(GMWQ!$NE$2:$NE$60=I$3)*(GMWQ!$ND$2:$ND$60=I$4)*(GMWQ!$NF$2:$NF$60=I$1),0),$F14-1966)} -> 52526.84 | J14: {=INDEX(GMWQ!$A$2:$NF$60,MATCH(1,(GMWQ!$NE$2:$NE$60=J$3)*(GMWQ!$ND$2:$ND$60=J$4)*(GMWQ!$NF$2:$NF$60=J$1),0),$F14-1966)} -> 389.05 | K14: {=INDEX(GMWQ!$A$2:$NF$60,MATCH(1,(GMWQ!$NE$2:$NE$60=K$3)*(GMWQ!$ND$2:$ND$60=K$4)*(GMWQ!$NF$2:$NF$60=K$1),0),$F14-1966)} -> 259.134 | L14: {=INDEX(GMWQ!$A$2:$NF$60,MATCH(1,(GMWQ!$NE$2:$NE$60=L$3)*(GMWQ!$ND$2:$ND$60=L$4)*(GMWQ!$NF$2:$NF$60=L$1),0),$F14-1966)} -> 242.3543 | M14: {=INDEX(GMWQ!$A$2:$NF$60,MATCH(1,(GMWQ!$NE$2:$NE$60=M$3)*(GMWQ!$ND$2:$ND$60=M$4)*(GMWQ!$NF$2:$NF$60=M$1),0),$F14-1966)} -> 182493.8 | N14: {=INDEX(GMWQ!$A$2:$NF$60,MATCH(1,(GMWQ!$NE$2:$NE$60=N$3)*(GMWQ!$ND$2:$ND$60=N$4)*(GMWQ!$NF$2:$NF$60=N$1),0),$F14-1966)} -> -1546 | ... AL14: {=INDEX(GMWQ!$A$2:$NF$60,MATCH(1,(GMWQ!$NE$2:$NE$60=AL$3)*(GMWQ!$ND$2:$ND$60=AL$4)*(GMWQ!$NF$2:$NF$60=AL$1),0),$F14-1966)} -> 0
A15: 1975 | B15: =+B11+1 -> 1975 | C15: =+C11+1 -> 1974 | D15: =+D11+1 -> 1974 | F15: =+F14+1 -> 1981 | G15: {=INDEX(GMWQ!$A$2:$NF$60,MATCH(1,(GMWQ!$NE$2:$NE$60=G$3)*(GMWQ!$ND$2:$ND$60=G$4)*(GMWQ!$NF$2:$NF$60=G$1),0),$F15-1966)} -> 258116 | H15: {=INDEX(GMWQ!$A$2:$NF$60,MATCH(1,(GMWQ!$NE$2:$NE$60=H$3)*(GMWQ!$ND$2:$ND$60=H$4)*(GMWQ!$NF$2:$NF$60=H$1),0),$F15-1966)} -> 1489.25 | I15: {=INDEX(GMWQ!$A$2:$NF$60,MATCH(1,(GMWQ!$NE$2:$NE$60=I$3)*(GMWQ!$ND$2:$ND$60=I$4)*(GMWQ!$NF$2:$NF$60=I$1),0),$F15-1966)} -> 52595.21 | J15: {=INDEX(GMWQ!$A$2:$NF$60,MATCH(1,(GMWQ!$NE$2:$NE$60=J$3)*(GMWQ!$ND$2:$ND$60=J$4)*(GMWQ!$NF$2:$NF$60=J$1),0),$F15-1966)} -> 386.82 | K15: {=INDEX(GMWQ!$A$2:$NF$60,MATCH(1,(GMWQ!$NE$2:$NE$60=K$3)*(GMWQ!$ND$2:$ND$60=K$4)*(GMWQ!$NF$2:$NF$60=K$1),0),$F15-1966)} -> 257.134 | L15: {=INDEX(GMWQ!$A$2:$NF$60,MATCH(1,(GMWQ!$NE$2:$NE$60=L$3)*(GMWQ!$ND$2:$ND$60=L$4)*(GMWQ!$NF$2:$NF$60=L$1),0),$F15-1966)} -> 238.1379 | M15: {=INDEX(GMWQ!$A$2:$NF$60,MATCH(1,(GMWQ!$NE$2:$NE$60=M$3)*(GMWQ!$ND$2:$ND$60=M$4)*(GMWQ!$NF$2:$NF$60=M$1),0),$F15-1966)} -> 181499.5 | N15: {=INDEX(GMWQ!$A$2:$NF$60,MATCH(1,(GMWQ!$NE$2:$NE$60=N$3)*(GMWQ!$ND$2:$ND$60=N$4)*(GMWQ!$NF$2:$NF$60=N$1),0),$F15-1966)} -> -2070 | ... AL15: {=INDEX(GMWQ!$A$2:$NF$60,MATCH(1,(GMWQ!$NE$2:$NE$60=AL$3)*(GMWQ!$ND$2:$ND$60=AL$4)*(GMWQ!$NF$2:$NF$60=AL$1),0),$F15-1966)} -> 0
B16: =+B12+1 -> 1975 | C16: =+C12+1 -> 1975 | F16: =+F15+1 -> 1982 | G16: {=INDEX(GMWQ!$A$2:$NF$60,MATCH(1,(GMWQ!$NE$2:$NE$60=G$3)*(GMWQ!$ND$2:$ND$60=G$4)*(GMWQ!$NF$2:$NF$60=G$1),0),$F16-1966)} -> 253935 | H16: {=INDEX(GMWQ!$A$2:$NF$60,MATCH(1,(GMWQ!$NE$2:$NE$60=H$3)*(GMWQ!$ND$2:$ND$60=H$4)*(GMWQ!$NF$2:$NF$60=H$1),0),$F16-1966)} -> 1499.9 | I16: {=INDEX(GMWQ!$A$2:$NF$60,MATCH(1,(GMWQ!$NE$2:$NE$60=I$3)*(GMWQ!$ND$2:$ND$60=I$4)*(GMWQ!$NF$2:$NF$60=I$1),0),$F16-1966)} -> 53789.34 | J16: {=INDEX(GMWQ!$A$2:$NF$60,MATCH(1,(GMWQ!$NE$2:$NE$60=J$3)*(GMWQ!$ND$2:$ND$60=J$4)*(GMWQ!$NF$2:$NF$60=J$1),0),$F16-1966)} -> 384.92 | K16: {=INDEX(GMWQ!$A$2:$NF$60,MATCH(1,(GMWQ!$NE$2:$NE$60=K$3)*(GMWQ!$ND$2:$ND$60=K$4)*(GMWQ!$NF$2:$NF$60=K$1),0),$F16-1966)} -> 257.051 | L16: {=INDEX(GMWQ!$A$2:$NF$60,MATCH(1,(GMWQ!$NE$2:$NE$60=L$3)*(GMWQ!$ND$2:$ND$60=L$4)*(GMWQ!$NF$2:$NF$60=L$1),0),$F16-1966)} -> 238.0164 | M16: {=INDEX(GMWQ!$A$2:$NF$60,MATCH(1,(GMWQ!$NE$2:$NE$60=M$3)*(GMWQ!$ND$2:$ND$60=M$4)*(GMWQ!$NF$2:$NF$60=M$1),0),$F16-1966)} -> 183828 | N16: {=INDEX(GMWQ!$A$2:$NF$60,MATCH(1,(GMWQ!$NE$2:$NE$60=N$3)*(GMWQ!$ND$2:$ND$60=N$4)*(GMWQ!$NF$2:$NF$60=N$1),0),$F16-1966)} -> -1658 | ... AL16: {=INDEX(GMWQ!$A$2:$NF$60,MATCH(1,(GMWQ!$NE$2:$NE$60=AL$3)*(GMWQ!$ND$2:$ND$60=AL$4)*(GMWQ!$NF$2:$NF$60=AL$1),0),$F16-1966)} -> 0
B17: =+B13+1 -> 1975 | C17: =+C13+1 -> 1975 | F17: =+F16+1 -> 1983 | G17: {=INDEX(GMWQ!$A$2:$NF$60,MATCH(1,(GMWQ!$NE$2:$NE$60=G$3)*(GMWQ!$ND$2:$ND$60=G$4)*(GMWQ!$NF$2:$NF$60=G$1),0),$F17-1966)} -> 253168 | H17: {=INDEX(GMWQ!$A$2:$NF$60,MATCH(1,(GMWQ!$NE$2:$NE$60=H$3)*(GMWQ!$ND$2:$ND$60=H$4)*(GMWQ!$NF$2:$NF$60=H$1),0),$F17-1966)} -> 1525.575 | I17: {=INDEX(GMWQ!$A$2:$NF$60,MATCH(1,(GMWQ!$NE$2:$NE$60=I$3)*(GMWQ!$ND$2:$ND$60=I$4)*(GMWQ!$NF$2:$NF$60=I$1),0),$F17-1966)} -> 54409.61 | J17: {=INDEX(GMWQ!$A$2:$NF$60,MATCH(1,(GMWQ!$NE$2:$NE$60=J$3)*(GMWQ!$ND$2:$ND$60=J$4)*(GMWQ!$NF$2:$NF$60=J$1),0),$F17-1966)} -> 389.05 | K17: {=INDEX(GMWQ!$A$2:$NF$60,MATCH(1,(GMWQ!$NE$2:$NE$60=K$3)*(GMWQ!$ND$2:$ND$60=K$4)*(GMWQ!$NF$2:$NF$60=K$1),0),$F17-1966)} -> 256.883 | L17: {=INDEX(GMWQ!$A$2:$NF$60,MATCH(1,(GMWQ!$NE$2:$NE$60=L$3)*(GMWQ!$ND$2:$ND$60=L$4)*(GMWQ!$NF$2:$NF$60=L$1),0),$F17-1966)} -> 241.3983 | M17: {=INDEX(GMWQ!$A$2:$NF$60,MATCH(1,(GMWQ!$NE$2:$NE$60=M$3)*(GMWQ!$ND$2:$ND$60=M$4)*(GMWQ!$NF$2:$NF$60=M$1),0),$F17-1966)} -> 187354.8 | N17: {=INDEX(GMWQ!$A$2:$NF$60,MATCH(1,(GMWQ!$NE$2:$NE$60=N$3)*(GMWQ!$ND$2:$ND$60=N$4)*(GMWQ!$NF$2:$NF$60=N$1),0),$F17-1966)} -> -1874 | ... AL17: {=INDEX(GMWQ!$A$2:$NF$60,MATCH(1,(GMWQ!$NE$2:$NE$60=AL$3)*(GMWQ!$ND$2:$ND$60=AL$4)*(GMWQ!$NF$2:$NF$60=AL$1),0),$F17-1966)} -> 0
B18: =+B14+1 -> 1975 | C18: =+C14+1 -> 1975 | E18: =+E14+1 -> 1975 | F18: =+F17+1 -> 1984 | G18: {=INDEX(GMWQ!$A$2:$NF$60,MATCH(1,(GMWQ!$NE$2:$NE$60=G$3)*(GMWQ!$ND$2:$ND$60=G$4)*(GMWQ!$NF$2:$NF$60=G$1),0),$F18-1966)} -> 255985 | H18: {=INDEX(GMWQ!$A$2:$NF$60,MATCH(1,(GMWQ!$NE$2:$NE$60=H$3)*(GMWQ!$ND$2:$ND$60=H$4)*(GMWQ!$NF$2:$NF$60=H$1),0),$F18-1966)} -> 1546.125 | I18: {=INDEX(GMWQ!$A$2:$NF$60,MATCH(1,(GMWQ!$NE$2:$NE$60=I$3)*(GMWQ!$ND$2:$ND$60=I$4)*(GMWQ!$NF$2:$NF$60=I$1),0),$F18-1966)} -> 54986.97 | J18: {=INDEX(GMWQ!$A$2:$NF$60,MATCH(1,(GMWQ!$NE$2:$NE$60=J$3)*(GMWQ!$ND$2:$ND$60=J$4)*(GMWQ!$NF$2:$NF$60=J$1),0),$F18-1966)} -> 396.83 | K18: {=INDEX(GMWQ!$A$2:$NF$60,MATCH(1,(GMWQ!$NE$2:$NE$60=K$3)*(GMWQ!$ND$2:$ND$60=K$4)*(GMWQ!$NF$2:$NF$60=K$1),0),$F18-1966)} -> 262.376 | L18: {=INDEX(GMWQ!$A$2:$NF$60,MATCH(1,(GMWQ!$NE$2:$NE$60=L$3)*(GMWQ!$ND$2:$ND$60=L$4)*(GMWQ!$NF$2:$NF$60=L$1),0),$F18-1966)} -> 244.1035 | M18: {=INDEX(GMWQ!$A$2:$NF$60,MATCH(1,(GMWQ!$NE$2:$NE$60=M$3)*(GMWQ!$ND$2:$ND$60=M$4)*(GMWQ!$NF$2:$NF$60=M$1),0),$F18-1966)} -> 189522.8 | N18: {=INDEX(GMWQ!$A$2:$NF$60,MATCH(1,(GMWQ!$NE$2:$NE$60=N$3)*(GMWQ!$ND$2:$ND$60=N$4)*(GMWQ!$NF$2:$NF$60=N$1),0),$F18-1966)} -> -1609 | ... AL18: {=INDEX(GMWQ!$A$2:$NF$60,MATCH(1,(GMWQ!$NE$2:$NE$60=AL$3)*(GMWQ!$ND$2:$ND$60=AL$4)*(GMWQ!$NF$2:$NF$60=AL$1),0),$F18-1966)} -> 0
A19: 1976 | B19: =+B15+1 -> 1976 | C19: =+C15+1 -> 1975 | D19: =+D15+1 -> 1975 | F19: =+F18+1 -> 1985 | G19: {=INDEX(GMWQ!$A$2:$NF$60,MATCH(1,(GMWQ!$NE$2:$NE$60=G$3)*(GMWQ!$ND$2:$ND$60=G$4)*(GMWQ!$NF$2:$NF$60=G$1),0),$F19-1966)} -> 260268 | H19: {=INDEX(GMWQ!$A$2:$NF$60,MATCH(1,(GMWQ!$NE$2:$NE$60=H$3)*(GMWQ!$ND$2:$ND$60=H$4)*(GMWQ!$NF$2:$NF$60=H$1),0),$F19-1966)} -> 1580.9 | I19: {=INDEX(GMWQ!$A$2:$NF$60,MATCH(1,(GMWQ!$NE$2:$NE$60=I$3)*(GMWQ!$ND$2:$ND$60=I$4)*(GMWQ!$NF$2:$NF$60=I$1),0),$F19-1966)} -> 55458.37 | J19: {=INDEX(GMWQ!$A$2:$NF$60,MATCH(1,(GMWQ!$NE$2:$NE$60=J$3)*(GMWQ!$ND$2:$ND$60=J$4)*(GMWQ!$NF$2:$NF$60=J$1),0),$F19-1966)} -> 400.23 | K19: {=INDEX(GMWQ!$A$2:$NF$60,MATCH(1,(GMWQ!$NE$2:$NE$60=K$3)*(GMWQ!$ND$2:$ND$60=K$4)*(GMWQ!$NF$2:$NF$60=K$1),0),$F19-1966)} -> 264.851 | L19: {=INDEX(GMWQ!$A$2:$NF$60,MATCH(1,(GMWQ!$NE$2:$NE$60=L$3)*(GMWQ!$ND$2:$ND$60=L$4)*(GMWQ!$NF$2:$NF$60=L$1),0),$F19-1966)} -> 248.4038 | M19: {=INDEX(GMWQ!$A$2:$NF$60,MATCH(1,(GMWQ!$NE$2:$NE$60=M$3)*(GMWQ!$ND$2:$ND$60=M$4)*(GMWQ!$NF$2:$NF$60=M$1),0),$F19-1966)} -> 192825.5 | N19: {=INDEX(GMWQ!$A$2:$NF$60,MATCH(1,(GMWQ!$NE$2:$NE$60=N$3)*(GMWQ!$ND$2:$ND$60=N$4)*(GMWQ!$NF$2:$NF$60=N$1),0),$F19-1966)} -> -2510 | ... AL19: {=INDEX(GMWQ!$A$2:$NF$60,MATCH(1,(GMWQ!$NE$2:$NE$60=AL$3)*(GMWQ!$ND$2:$ND$60=AL$4)*(GMWQ!$NF$2:$NF$60=AL$1),0),$F19-1966)} -> 0
B20: =+B16+1 -> 1976 | C20: =+C16+1 -> 1976 | F20: =+F19+1 -> 1986 | G20: {=INDEX(GMWQ!$A$2:$NF$60,MATCH(1,(GMWQ!$NE$2:$NE$60=G$3)*(GMWQ!$ND$2:$ND$60=G$4)*(GMWQ!$NF$2:$NF$60=G$1),0),$F20-1966)} -> 259911 | H20: {=INDEX(GMWQ!$A$2:$NF$60,MATCH(1,(GMWQ!$NE$2:$NE$60=H$3)*(GMWQ!$ND$2:$ND$60=H$4)*(GMWQ!$NF$2:$NF$60=H$1),0),$F20-1966)} -> 1592.5 | I20: {=INDEX(GMWQ!$A$2:$NF$60,MATCH(1,(GMWQ!$NE$2:$NE$60=I$3)*(GMWQ!$ND$2:$ND$60=I$4)*(GMWQ!$NF$2:$NF$60=I$1),0),$F20-1966)} -> 55787.51 | J20: {=INDEX(GMWQ!$A$2:$NF$60,MATCH(1,(GMWQ!$NE$2:$NE$60=J$3)*(GMWQ!$ND$2:$ND$60=J$4)*(GMWQ!$NF$2:$NF$60=J$1),0),$F20-1966)} -> 406.27 | K20: {=INDEX(GMWQ!$A$2:$NF$60,MATCH(1,(GMWQ!$NE$2:$NE$60=K$3)*(GMWQ!$ND$2:$ND$60=K$4)*(GMWQ!$NF$2:$NF$60=K$1),0),$F20-1966)} -> 268.472 | L20: {=INDEX(GMWQ!$A$2:$NF$60,MATCH(1,(GMWQ!$NE$2:$NE$60=L$3)*(GMWQ!$ND$2:$ND$60=L$4)*(GMWQ!$NF$2:$NF$60=L$1),0),$F20-1966)} -> 252.8942 | M20: {=INDEX(GMWQ!$A$2:$NF$60,MATCH(1,(GMWQ!$NE$2:$NE$60=M$3)*(GMWQ!$ND$2:$ND$60=M$4)*(GMWQ!$NF$2:$NF$60=M$1),0),$F20-1966)} -> 196983.8 | N20: {=INDEX(GMWQ!$A$2:$NF$60,MATCH(1,(GMWQ!$NE$2:$NE$60=N$3)*(GMWQ!$ND$2:$ND$60=N$4)*(GMWQ!$NF$2:$NF$60=N$1),0),$F20-1966)} -> -1926 | ... AL20: {=INDEX(GMWQ!$A$2:$NF$60,MATCH(1,(GMWQ!$NE$2:$NE$60=AL$3)*(GMWQ!$ND$2:$ND$60=AL$4)*(GMWQ!$NF$2:$NF$60=AL$1),0),$F20-1966)} -> 0
B21: =+B17+1 -> 1976 | C21: =+C17+1 -> 1976 | F21: =+F20+1 -> 1987 | G21: {=INDEX(GMWQ!$A$2:$NF$60,MATCH(1,(GMWQ!$NE$2:$NE$60=G$3)*(GMWQ!$ND$2:$ND$60=G$4)*(GMWQ!$NF$2:$NF$60=G$1),0),$F21-1966)} -> 263132 | H21: {=INDEX(GMWQ!$A$2:$NF$60,MATCH(1,(GMWQ!$NE$2:$NE$60=H$3)*(GMWQ!$ND$2:$ND$60=H$4)*(GMWQ!$NF$2:$NF$60=H$1),0),$F21-1966)} -> 1601.225 | I21: {=INDEX(GMWQ!$A$2:$NF$60,MATCH(1,(GMWQ!$NE$2:$NE$60=I$3)*(GMWQ!$ND$2:$ND$60=I$4)*(GMWQ!$NF$2:$NF$60=I$1),0),$F21-1966)} -> 56585.37 | J21: {=INDEX(GMWQ!$A$2:$NF$60,MATCH(1,(GMWQ!$NE$2:$NE$60=J$3)*(GMWQ!$ND$2:$ND$60=J$4)*(GMWQ!$NF$2:$NF$60=J$1),0),$F21-1966)} -> 406.44 | K21: {=INDEX(GMWQ!$A$2:$NF$60,MATCH(1,(GMWQ!$NE$2:$NE$60=K$3)*(GMWQ!$ND$2:$ND$60=K$4)*(GMWQ!$NF$2:$NF$60=K$1),0),$F21-1966)} -> 271.536 | L21: {=INDEX(GMWQ!$A$2:$NF$60,MATCH(1,(GMWQ!$NE$2:$NE$60=L$3)*(GMWQ!$ND$2:$ND$60=L$4)*(GMWQ!$NF$2:$NF$60=L$1),0),$F21-1966)} -> 259.3207 | M21: {=INDEX(GMWQ!$A$2:$NF$60,MATCH(1,(GMWQ!$NE$2:$NE$60=M$3)*(GMWQ!$ND$2:$ND$60=M$4)*(GMWQ!$NF$2:$NF$60=M$1),0),$F21-1966)} -> 197893.3 | N21: {=INDEX(GMWQ!$A$2:$NF$60,MATCH(1,(GMWQ!$NE$2:$NE$60=N$3)*(GMWQ!$ND$2:$ND$60=N$4)*(GMWQ!$NF$2:$NF$60=N$1),0),$F21-1966)} -> -2444 | ... AL21: {=INDEX(GMWQ!$A$2:$NF$60,MATCH(1,(GMWQ!$NE$2:$NE$60=AL$3)*(GMWQ!$ND$2:$ND$60=AL$4)*(GMWQ!$NF$2:$NF$60=AL$1),0),$F21-1966)} -> 0
B22: =+B18+1 -> 1976 | C22: =+C18+1 -> 1976 | E22: =+E18+1 -> 1976 | F22: =+F21+1 -> 1988 | G22: {=INDEX(GMWQ!$A$2:$NF$60,MATCH(1,(GMWQ!$NE$2:$NE$60=G$3)*(GMWQ!$ND$2:$ND$60=G$4)*(GMWQ!$NF$2:$NF$60=G$1),0),$F22-1966)} -> 268662 | H22: {=INDEX(GMWQ!$A$2:$NF$60,MATCH(1,(GMWQ!$NE$2:$NE$60=H$3)*(GMWQ!$ND$2:$ND$60=H$4)*(GMWQ!$NF$2:$NF$60=H$1),0),$F22-1966)} -> 1612.8 | I22: {=INDEX(GMWQ!$A$2:$NF$60,MATCH(1,(GMWQ!$NE$2:$NE$60=I$3)*(GMWQ!$ND$2:$ND$60=I$4)*(GMWQ!$NF$2:$NF$60=I$1),0),$F22-1966)} -> 56653.35 | J22: {=INDEX(GMWQ!$A$2:$NF$60,MATCH(1,(GMWQ!$NE$2:$NE$60=J$3)*(GMWQ!$ND$2:$ND$60=J$4)*(GMWQ!$NF$2:$NF$60=J$1),0),$F22-1966)} -> 413.88 | K22: {=INDEX(GMWQ!$A$2:$NF$60,MATCH(1,(GMWQ!$NE$2:$NE$60=K$3)*(GMWQ!$ND$2:$ND$60=K$4)*(GMWQ!$NF$2:$NF$60=K$1),0),$F22-1966)} -> 273.453 | L22: {=INDEX(GMWQ!$A$2:$NF$60,MATCH(1,(GMWQ!$NE$2:$NE$60=L$3)*(GMWQ!$ND$2:$ND$60=L$4)*(GMWQ!$NF$2:$NF$60=L$1),0),$F22-1966)} -> 263.8197 | M22: {=INDEX(GMWQ!$A$2:$NF$60,MATCH(1,(GMWQ!$NE$2:$NE$60=M$3)*(GMWQ!$ND$2:$ND$60=M$4)*(GMWQ!$NF$2:$NF$60=M$1),0),$F22-1966)} -> 198213 | N22: {=INDEX(GMWQ!$A$2:$NF$60,MATCH(1,(GMWQ!$NE$2:$NE$60=N$3)*(GMWQ!$ND$2:$ND$60=N$4)*(GMWQ!$NF$2:$NF$60=N$1),0),$F22-1966)} -> -1081 | ... AL22: {=INDEX(GMWQ!$A$2:$NF$60,MATCH(1,(GMWQ!$NE$2:$NE$60=AL$3)*(GMWQ!$ND$2:$ND$60=AL$4)*(GMWQ!$NF$2:$NF$60=AL$1),0),$F22-1966)} -> 0
A23: 1977 | B23: =+B19+1 -> 1977 | C23: =+C19+1 -> 1976 | D23: =+D19+1 -> 1976 | F23: =+F22+1 -> 1989 | G23: {=INDEX(GMWQ!$A$2:$NF$60,MATCH(1,(GMWQ!$NE$2:$NE$60=G$3)*(GMWQ!$ND$2:$ND$60=G$4)*(GMWQ!$NF$2:$NF$60=G$1),0),$F23-1966)} -> 268833 | H23: {=INDEX(GMWQ!$A$2:$NF$60,MATCH(1,(GMWQ!$NE$2:$NE$60=H$3)*(GMWQ!$ND$2:$ND$60=H$4)*(GMWQ!$NF$2:$NF$60=H$1),0),$F23-1966)} -> 1631.925 | I23: {=INDEX(GMWQ!$A$2:$NF$60,MATCH(1,(GMWQ!$NE$2:$NE$60=I$3)*(GMWQ!$ND$2:$ND$60=I$4)*(GMWQ!$NF$2:$NF$60=I$1),0),$F23-1966)} -> 57921.84 | J23: {=INDEX(GMWQ!$A$2:$NF$60,MATCH(1,(GMWQ!$NE$2:$NE$60=J$3)*(GMWQ!$ND$2:$ND$60=J$4)*(GMWQ!$NF$2:$NF$60=J$1),0),$F23-1966)} -> 417.53 | K23: {=INDEX(GMWQ!$A$2:$NF$60,MATCH(1,(GMWQ!$NE$2:$NE$60=K$3)*(GMWQ!$ND$2:$ND$60=K$4)*(GMWQ!$NF$2:$NF$60=K$1),0),$F23-1966)} -> 276.547 | L23: {=INDEX(GMWQ!$A$2:$NF$60,MATCH(1,(GMWQ!$NE$2:$NE$60=L$3)*(GMWQ!$ND$2:$ND$60=L$4)*(GMWQ!$NF$2:$NF$60=L$1),0),$F23-1966)} -> 263.9241 | M23: {=INDEX(GMWQ!$A$2:$NF$60,MATCH(1,(GMWQ!$NE$2:$NE$60=M$3)*(GMWQ!$ND$2:$ND$60=M$4)*(GMWQ!$NF$2:$NF$60=M$1),0),$F23-1966)} -> 201253.3 | N23: {=INDEX(GMWQ!$A$2:$NF$60,MATCH(1,(GMWQ!$NE$2:$NE$60=N$3)*(GMWQ!$ND$2:$ND$60=N$4)*(GMWQ!$NF$2:$NF$60=N$1),0),$F23-1966)} -> -1553 | ... AL23: {=INDEX(GMWQ!$A$2:$NF$60,MATCH(1,(GMWQ!$NE$2:$NE$60=AL$3)*(GMWQ!$ND$2:$ND$60=AL$4)*(GMWQ!$NF$2:$NF$60=AL$1),0),$F23-1966)} -> 0
B24: =+B20+1 -> 1977 | C24: =+C20+1 -> 1977 | F24: =+F23+1 -> 1990 | G24: {=INDEX(GMWQ!$A$2:$NF$60,MATCH(1,(GMWQ!$NE$2:$NE$60=G$3)*(GMWQ!$ND$2:$ND$60=G$4)*(GMWQ!$NF$2:$NF$60=G$1),0),$F24-1966)} -> 266987 | H24: {=INDEX(GMWQ!$A$2:$NF$60,MATCH(1,(GMWQ!$NE$2:$NE$60=H$3)*(GMWQ!$ND$2:$ND$60=H$4)*(GMWQ!$NF$2:$NF$60=H$1),0),$F24-1966)} -> 1663.625 | I24: {=INDEX(GMWQ!$A$2:$NF$60,MATCH(1,(GMWQ!$NE$2:$NE$60=I$3)*(GMWQ!$ND$2:$ND$60=I$4)*(GMWQ!$NF$2:$NF$60=I$1),0),$F24-1966)} -> 58330.15 | J24: {=INDEX(GMWQ!$A$2:$NF$60,MATCH(1,(GMWQ!$NE$2:$NE$60=J$3)*(GMWQ!$ND$2:$ND$60=J$4)*(GMWQ!$NF$2:$NF$60=J$1),0),$F24-1966)} -> 419.84 | K24: {=INDEX(GMWQ!$A$2:$NF$60,MATCH(1,(GMWQ!$NE$2:$NE$60=K$3)*(GMWQ!$ND$2:$ND$60=K$4)*(GMWQ!$NF$2:$NF$60=K$1),0),$F24-1966)} -> 277.655 | L24: {=INDEX(GMWQ!$A$2:$NF$60,MATCH(1,(GMWQ!$NE$2:$NE$60=L$3)*(GMWQ!$ND$2:$ND$60=L$4)*(GMWQ!$NF$2:$NF$60=L$1),0),$F24-1966)} -> 262.4543 | M24: {=INDEX(GMWQ!$A$2:$NF$60,MATCH(1,(GMWQ!$NE$2:$NE$60=M$3)*(GMWQ!$ND$2:$ND$60=M$4)*(GMWQ!$NF$2:$NF$60=M$1),0),$F24-1966)} -> 202280.3 | N24: {=INDEX(GMWQ!$A$2:$NF$60,MATCH(1,(GMWQ!$NE$2:$NE$60=N$3)*(GMWQ!$ND$2:$ND$60=N$4)*(GMWQ!$NF$2:$NF$60=N$1),0),$F24-1966)} -> -1256 | ... AL24: {=INDEX(GMWQ!$A$2:$NF$60,MATCH(1,(GMWQ!$NE$2:$NE$60=AL$3)*(GMWQ!$ND$2:$ND$60=AL$4)*(GMWQ!$NF$2:$NF$60=AL$1),0),$F24-1966)} -> 0
B25: =+B21+1 -> 1977 | C25: =+C21+1 -> 1977 | F25: =+F24+1 -> 1991 | G25: {=INDEX(GMWQ!$A$2:$NF$60,MATCH(1,(GMWQ!$NE$2:$NE$60=G$3)*(GMWQ!$ND$2:$ND$60=G$4)*(GMWQ!$NF$2:$NF$60=G$1),0),$F25-1966)} -> 268717 | H25: {=INDEX(GMWQ!$A$2:$NF$60,MATCH(1,(GMWQ!$NE$2:$NE$60=H$3)*(GMWQ!$ND$2:$ND$60=H$4)*(GMWQ!$NF$2:$NF$60=H$1),0),$F25-1966)} -> 1693.625 | I25: {=INDEX(GMWQ!$A$2:$NF$60,MATCH(1,(GMWQ!$NE$2:$NE$60=I$3)*(GMWQ!$ND$2:$ND$60=I$4)*(GMWQ!$NF$2:$NF$60=I$1),0),$F25-1966)} -> 58729.51 | J25: {=INDEX(GMWQ!$A$2:$NF$60,MATCH(1,(GMWQ!$NE$2:$NE$60=J$3)*(GMWQ!$ND$2:$ND$60=J$4)*(GMWQ!$NF$2:$NF$60=J$1),0),$F25-1966)} -> 419.68 | K25: {=INDEX(GMWQ!$A$2:$NF$60,MATCH(1,(GMWQ!$NE$2:$NE$60=K$3)*(GMWQ!$ND$2:$ND$60=K$4)*(GMWQ!$NF$2:$NF$60=K$1),0),$F25-1966)} -> 279.927 | L25: {=INDEX(GMWQ!$A$2:$NF$60,MATCH(1,(GMWQ!$NE$2:$NE$60=L$3)*(GMWQ!$ND$2:$ND$60=L$4)*(GMWQ!$NF$2:$NF$60=L$1),0),$F25-1966)} -> 259.9991 | M25: {=INDEX(GMWQ!$A$2:$NF$60,MATCH(1,(GMWQ!$NE$2:$NE$60=M$3)*(GMWQ!$ND$2:$ND$60=M$4)*(GMWQ!$NF$2:$NF$60=M$1),0),$F25-1966)} -> 203469.3 | N25: {=INDEX(GMWQ!$A$2:$NF$60,MATCH(1,(GMWQ!$NE$2:$NE$60=N$3)*(GMWQ!$ND$2:$ND$60=N$4)*(GMWQ!$NF$2:$NF$60=N$1),0),$F25-1966)} -> -1656 | ... AL25: {=INDEX(GMWQ!$A$2:$NF$60,MATCH(1,(GMWQ!$NE$2:$NE$60=AL$3)*(GMWQ!$ND$2:$ND$60=AL$4)*(GMWQ!$NF$2:$NF$60=AL$1),0),$F25-1966)} -> 0
B26: =+B22+1 -> 1977 | C26: =+C22+1 -> 1977 | E26: =+E22+1 -> 1977 | F26: =+F25+1 -> 1992 | G26: {=INDEX(GMWQ!$A$2:$NF$60,MATCH(1,(GMWQ!$NE$2:$NE$60=G$3)*(GMWQ!$ND$2:$ND$60=G$4)*(GMWQ!$NF$2:$NF$60=G$1),0),$F26-1966)} -> 273279 | H26: {=INDEX(GMWQ!$A$2:$NF$60,MATCH(1,(GMWQ!$NE$2:$NE$60=H$3)*(GMWQ!$ND$2:$ND$60=H$4)*(GMWQ!$NF$2:$NF$60=H$1),0),$F26-1966)} -> 1693.65 | I26: {=INDEX(GMWQ!$A$2:$NF$60,MATCH(1,(GMWQ!$NE$2:$NE$60=I$3)*(GMWQ!$ND$2:$ND$60=I$4)*(GMWQ!$NF$2:$NF$60=I$1),0),$F26-1966)} -> 59539.25 | J26: {=INDEX(GMWQ!$A$2:$NF$60,MATCH(1,(GMWQ!$NE$2:$NE$60=J$3)*(GMWQ!$ND$2:$ND$60=J$4)*(GMWQ!$NF$2:$NF$60=J$1),0),$F26-1966)} -> 426.88 | K26: {=INDEX(GMWQ!$A$2:$NF$60,MATCH(1,(GMWQ!$NE$2:$NE$60=K$3)*(GMWQ!$ND$2:$ND$60=K$4)*(GMWQ!$NF$2:$NF$60=K$1),0),$F26-1966)} -> 282.16 | L26: {=INDEX(GMWQ!$A$2:$NF$60,MATCH(1,(GMWQ!$NE$2:$NE$60=L$3)*(GMWQ!$ND$2:$ND$60=L$4)*(GMWQ!$NF$2:$NF$60=L$1),0),$F26-1966)} -> 262.2263 | M26: {=INDEX(GMWQ!$A$2:$NF$60,MATCH(1,(GMWQ!$NE$2:$NE$60=M$3)*(GMWQ!$ND$2:$ND$60=M$4)*(GMWQ!$NF$2:$NF$60=M$1),0),$F26-1966)} -> 206693.5 | N26: {=INDEX(GMWQ!$A$2:$NF$60,MATCH(1,(GMWQ!$NE$2:$NE$60=N$3)*(GMWQ!$ND$2:$ND$60=N$4)*(GMWQ!$NF$2:$NF$60=N$1),0),$F26-1966)} -> -1371 | ... AL26: {=INDEX(GMWQ!$A$2:$NF$60,MATCH(1,(GMWQ!$NE$2:$NE$60=AL$3)*(GMWQ!$ND$2:$ND$60=AL$4)*(GMWQ!$NF$2:$NF$60=AL$1),0),$F26-1966)} -> 0
A27: 1978 | B27: =+B23+1 -> 1978 | C27: =+C23+1 -> 1977 | D27: =+D23+1 -> 1977 | F27: =+F26+1 -> 1993 | G27: {=INDEX(GMWQ!$A$2:$NF$60,MATCH(1,(GMWQ!$NE$2:$NE$60=G$3)*(GMWQ!$ND$2:$ND$60=G$4)*(GMWQ!$NF$2:$NF$60=G$1),0),$F27-1966)} -> 275841 | H27: {=INDEX(GMWQ!$A$2:$NF$60,MATCH(1,(GMWQ!$NE$2:$NE$60=H$3)*(GMWQ!$ND$2:$ND$60=H$4)*(GMWQ!$NF$2:$NF$60=H$1),0),$F27-1966)} -> 1699.075 | I27: {=INDEX(GMWQ!$A$2:$NF$60,MATCH(1,(GMWQ!$NE$2:$NE$60=I$3)*(GMWQ!$ND$2:$ND$60=I$4)*(GMWQ!$NF$2:$NF$60=I$1),0),$F27-1966)} -> 60686.21 | J27: {=INDEX(GMWQ!$A$2:$NF$60,MATCH(1,(GMWQ!$NE$2:$NE$60=J$3)*(GMWQ!$ND$2:$ND$60=J$4)*(GMWQ!$NF$2:$NF$60=J$1),0),$F27-1966)} -> 428.69 | K27: {=INDEX(GMWQ!$A$2:$NF$60,MATCH(1,(GMWQ!$NE$2:$NE$60=K$3)*(GMWQ!$ND$2:$ND$60=K$4)*(GMWQ!$NF$2:$NF$60=K$1),0),$F27-1966)} -> 286.062 | L27: {=INDEX(GMWQ!$A$2:$NF$60,MATCH(1,(GMWQ!$NE$2:$NE$60=L$3)*(GMWQ!$ND$2:$ND$60=L$4)*(GMWQ!$NF$2:$NF$60=L$1),0),$F27-1966)} -> 266.513 | M27: {=INDEX(GMWQ!$A$2:$NF$60,MATCH(1,(GMWQ!$NE$2:$NE$60=M$3)*(GMWQ!$ND$2:$ND$60=M$4)*(GMWQ!$NF$2:$NF$60=M$1),0),$F27-1966)} -> 208478.5 | N27: {=INDEX(GMWQ!$A$2:$NF$60,MATCH(1,(GMWQ!$NE$2:$NE$60=N$3)*(GMWQ!$ND$2:$ND$60=N$4)*(GMWQ!$NF$2:$NF$60=N$1),0),$F27-1966)} -> -2141 | ... AL27: {=INDEX(GMWQ!$A$2:$NF$60,MATCH(1,(GMWQ!$NE$2:$NE$60=AL$3)*(GMWQ!$ND$2:$ND$60=AL$4)*(GMWQ!$NF$2:$NF$60=AL$1),0),$F27-1966)} -> 0
B28: =+B24+1 -> 1978 | C28: =+C24+1 -> 1978 | F28: =+F27+1 -> 1994 | G28: {=INDEX(GMWQ!$A$2:$NF$60,MATCH(1,(GMWQ!$NE$2:$NE$60=G$3)*(GMWQ!$ND$2:$ND$60=G$4)*(GMWQ!$NF$2:$NF$60=G$1),0),$F28-1966)} -> 279001 | H28: {=INDEX(GMWQ!$A$2:$NF$60,MATCH(1,(GMWQ!$NE$2:$NE$60=H$3)*(GMWQ!$ND$2:$ND$60=H$4)*(GMWQ!$NF$2:$NF$60=H$1),0),$F28-1966)} -> 1764.725 | I28: {=INDEX(GMWQ!$A$2:$NF$60,MATCH(1,(GMWQ!$NE$2:$NE$60=I$3)*(GMWQ!$ND$2:$ND$60=I$4)*(GMWQ!$NF$2:$NF$60=I$1),0),$F28-1966)} -> 61280.64 | J28: {=INDEX(GMWQ!$A$2:$NF$60,MATCH(1,(GMWQ!$NE$2:$NE$60=J$3)*(GMWQ!$ND$2:$ND$60=J$4)*(GMWQ!$NF$2:$NF$60=J$1),0),$F28-1966)} -> 430.44 | K28: {=INDEX(GMWQ!$A$2:$NF$60,MATCH(1,(GMWQ!$NE$2:$NE$60=K$3)*(GMWQ!$ND$2:$ND$60=K$4)*(GMWQ!$NF$2:$NF$60=K$1),0),$F28-1966)} -> 289.179 | L28: {=INDEX(GMWQ!$A$2:$NF$60,MATCH(1,(GMWQ!$NE$2:$NE$60=L$3)*(GMWQ!$ND$2:$ND$60=L$4)*(GMWQ!$NF$2:$NF$60=L$1),0),$F28-1966)} -> 271.1233 | M28: {=INDEX(GMWQ!$A$2:$NF$60,MATCH(1,(GMWQ!$NE$2:$NE$60=M$3)*(GMWQ!$ND$2:$ND$60=M$4)*(GMWQ!$NF$2:$NF$60=M$1),0),$F28-1966)} -> 209897.5 | N28: {=INDEX(GMWQ!$A$2:$NF$60,MATCH(1,(GMWQ!$NE$2:$NE$60=N$3)*(GMWQ!$ND$2:$ND$60=N$4)*(GMWQ!$NF$2:$NF$60=N$1),0),$F28-1966)} -> -1905 | ... AL28: {=INDEX(GMWQ!$A$2:$NF$60,MATCH(1,(GMWQ!$NE$2:$NE$60=AL$3)*(GMWQ!$ND$2:$ND$60=AL$4)*(GMWQ!$NF$2:$NF$60=AL$1),0),$F28-1966)} -> 0
B29: =+B25+1 -> 1978 | C29: =+C25+1 -> 1978 | F29: =+F28+1 -> 1995 | G29: {=INDEX(GMWQ!$A$2:$NF$60,MATCH(1,(GMWQ!$NE$2:$NE$60=G$3)*(GMWQ!$ND$2:$ND$60=G$4)*(GMWQ!$NF$2:$NF$60=G$1),0),$F29-1966)} -> 282797 | H29: {=INDEX(GMWQ!$A$2:$NF$60,MATCH(1,(GMWQ!$NE$2:$NE$60=H$3)*(GMWQ!$ND$2:$ND$60=H$4)*(GMWQ!$NF$2:$NF$60=H$1),0),$F29-1966)} -> 1782.475 | I29: {=INDEX(GMWQ!$A$2:$NF$60,MATCH(1,(GMWQ!$NE$2:$NE$60=I$3)*(GMWQ!$ND$2:$ND$60=I$4)*(GMWQ!$NF$2:$NF$60=I$1),0),$F29-1966)} -> 62081.49 | J29: {=INDEX(GMWQ!$A$2:$NF$60,MATCH(1,(GMWQ!$NE$2:$NE$60=J$3)*(GMWQ!$ND$2:$ND$60=J$4)*(GMWQ!$NF$2:$NF$60=J$1),0),$F29-1966)} -> 435.98 | K29: {=INDEX(GMWQ!$A$2:$NF$60,MATCH(1,(GMWQ!$NE$2:$NE$60=K$3)*(GMWQ!$ND$2:$ND$60=K$4)*(GMWQ!$NF$2:$NF$60=K$1),0),$F29-1966)} -> 290.979 | L29: {=INDEX(GMWQ!$A$2:$NF$60,MATCH(1,(GMWQ!$NE$2:$NE$60=L$3)*(GMWQ!$ND$2:$ND$60=L$4)*(GMWQ!$NF$2:$NF$60=L$1),0),$F29-1966)} -> 272.5487 | M29: {=INDEX(GMWQ!$A$2:$NF$60,MATCH(1,(GMWQ!$NE$2:$NE$60=M$3)*(GMWQ!$ND$2:$ND$60=M$4)*(GMWQ!$NF$2:$NF$60=M$1),0),$F29-1966)} -> 211855.5 | N29: {=INDEX(GMWQ!$A$2:$NF$60,MATCH(1,(GMWQ!$NE$2:$NE$60=N$3)*(GMWQ!$ND$2:$ND$60=N$4)*(GMWQ!$NF$2:$NF$60=N$1),0),$F29-1966)} -> -2710 | ... AL29: {=INDEX(GMWQ!$A$2:$NF$60,MATCH(1,(GMWQ!$NE$2:$NE$60=AL$3)*(GMWQ!$ND$2:$ND$60=AL$4)*(GMWQ!$NF$2:$NF$60=AL$1),0),$F29-1966)} -> 0
B30: =+B26+1 -> 1978 | C30: =+C26+1 -> 1978 | E30: =+E26+1 -> 1978 | F30: =+F29+1 -> 1996 | G30: {=INDEX(GMWQ!$A$2:$NF$60,MATCH(1,(GMWQ!$NE$2:$NE$60=G$3)*(GMWQ!$ND$2:$ND$60=G$4)*(GMWQ!$NF$2:$NF$60=G$1),0),$F30-1966)} -> 285314 | H30: {=INDEX(GMWQ!$A$2:$NF$60,MATCH(1,(GMWQ!$NE$2:$NE$60=H$3)*(GMWQ!$ND$2:$ND$60=H$4)*(GMWQ!$NF$2:$NF$60=H$1),0),$F30-1966)} -> 1806.45 | I30: {=INDEX(GMWQ!$A$2:$NF$60,MATCH(1,(GMWQ!$NE$2:$NE$60=I$3)*(GMWQ!$ND$2:$ND$60=I$4)*(GMWQ!$NF$2:$NF$60=I$1),0),$F30-1966)} -> 62988.52 | J30: {=INDEX(GMWQ!$A$2:$NF$60,MATCH(1,(GMWQ!$NE$2:$NE$60=J$3)*(GMWQ!$ND$2:$ND$60=J$4)*(GMWQ!$NF$2:$NF$60=J$1),0),$F30-1966)} -> 441.11 | K30: {=INDEX(GMWQ!$A$2:$NF$60,MATCH(1,(GMWQ!$NE$2:$NE$60=K$3)*(GMWQ!$ND$2:$ND$60=K$4)*(GMWQ!$NF$2:$NF$60=K$1),0),$F30-1966)} -> 294.294 | L30: {=INDEX(GMWQ!$A$2:$NF$60,MATCH(1,(GMWQ!$NE$2:$NE$60=L$3)*(GMWQ!$ND$2:$ND$60=L$4)*(GMWQ!$NF$2:$NF$60=L$1),0),$F30-1966)} -> 276.7017 | M30: {=INDEX(GMWQ!$A$2:$NF$60,MATCH(1,(GMWQ!$NE$2:$NE$60=M$3)*(GMWQ!$ND$2:$ND$60=M$4)*(GMWQ!$NF$2:$NF$60=M$1),0),$F30-1966)} -> 213864.3 | N30: {=INDEX(GMWQ!$A$2:$NF$60,MATCH(1,(GMWQ!$NE$2:$NE$60=N$3)*(GMWQ!$ND$2:$ND$60=N$4)*(GMWQ!$NF$2:$NF$60=N$1),0),$F30-1966)} -> -1578 | ... AL30: {=INDEX(GMWQ!$A$2:$NF$60,MATCH(1,(GMWQ!$NE$2:$NE$60=AL$3)*(GMWQ!$ND$2:$ND$60=AL$4)*(GMWQ!$NF$2:$NF$60=AL$1),0),$F30-1966)} -> 0
A31: 1979 | B31: =+B27+1 -> 1979 | C31: =+C27+1 -> 1978 | D31: =+D27+1 -> 1978 | F31: =+F30+1 -> 1997 | G31: {=INDEX(GMWQ!$A$2:$NF$60,MATCH(1,(GMWQ!$NE$2:$NE$60=G$3)*(GMWQ!$ND$2:$ND$60=G$4)*(GMWQ!$NF$2:$NF$60=G$1),0),$F31-1966)} -> 284457 | H31: {=INDEX(GMWQ!$A$2:$NF$60,MATCH(1,(GMWQ!$NE$2:$NE$60=H$3)*(GMWQ!$ND$2:$ND$60=H$4)*(GMWQ!$NF$2:$NF$60=H$1),0),$F31-1966)} -> 1809.675 | I31: {=INDEX(GMWQ!$A$2:$NF$60,MATCH(1,(GMWQ!$NE$2:$NE$60=I$3)*(GMWQ!$ND$2:$ND$60=I$4)*(GMWQ!$NF$2:$NF$60=I$1),0),$F31-1966)} -> 64175.77 | J31: {=INDEX(GMWQ!$A$2:$NF$60,MATCH(1,(GMWQ!$NE$2:$NE$60=J$3)*(GMWQ!$ND$2:$ND$60=J$4)*(GMWQ!$NF$2:$NF$60=J$1),0),$F31-1966)} -> 441.69 | K31: {=INDEX(GMWQ!$A$2:$NF$60,MATCH(1,(GMWQ!$NE$2:$NE$60=K$3)*(GMWQ!$ND$2:$ND$60=K$4)*(GMWQ!$NF$2:$NF$60=K$1),0),$F31-1966)} -> 297.552 | L31: {=INDEX(GMWQ!$A$2:$NF$60,MATCH(1,(GMWQ!$NE$2:$NE$60=L$3)*(GMWQ!$ND$2:$ND$60=L$4)*(GMWQ!$NF$2:$NF$60=L$1),0),$F31-1966)} -> 281.0739 | M31: {=INDEX(GMWQ!$A$2:$NF$60,MATCH(1,(GMWQ!$NE$2:$NE$60=M$3)*(GMWQ!$ND$2:$ND$60=M$4)*(GMWQ!$NF$2:$NF$60=M$1),0),$F31-1966)} -> 215570.5 | N31: {=INDEX(GMWQ!$A$2:$NF$60,MATCH(1,(GMWQ!$NE$2:$NE$60=N$3)*(GMWQ!$ND$2:$ND$60=N$4)*(GMWQ!$NF$2:$NF$60=N$1),0),$F31-1966)} -> -2492 | ... AL31: {=INDEX(GMWQ!$A$2:$NF$60,MATCH(1,(GMWQ!$NE$2:$NE$60=AL$3)*(GMWQ!$ND$2:$ND$60=AL$4)*(GMWQ!$NF$2:$NF$60=AL$1),0),$F31-1966)} -> 0
B32: =+B28+1 -> 1979 | C32: =+C28+1 -> 1979 | F32: =+F31+1 -> 1998 | G32: {=INDEX(GMWQ!$A$2:$NF$60,MATCH(1,(GMWQ!$NE$2:$NE$60=G$3)*(GMWQ!$ND$2:$ND$60=G$4)*(GMWQ!$NF$2:$NF$60=G$1),0),$F32-1966)} -> 296841 | H32: {=INDEX(GMWQ!$A$2:$NF$60,MATCH(1,(GMWQ!$NE$2:$NE$60=H$3)*(GMWQ!$ND$2:$ND$60=H$4)*(GMWQ!$NF$2:$NF$60=H$1),0),$F32-1966)} -> 1811.625 | I32: {=INDEX(GMWQ!$A$2:$NF$60,MATCH(1,(GMWQ!$NE$2:$NE$60=I$3)*(GMWQ!$ND$2:$ND$60=I$4)*(GMWQ!$NF$2:$NF$60=I$1),0),$F32-1966)} -> 65372.08 | J32: {=INDEX(GMWQ!$A$2:$NF$60,MATCH(1,(GMWQ!$NE$2:$NE$60=J$3)*(GMWQ!$ND$2:$ND$60=J$4)*(GMWQ!$NF$2:$NF$60=J$1),0),$F32-1966)} -> 455.35 | K32: {=INDEX(GMWQ!$A$2:$NF$60,MATCH(1,(GMWQ!$NE$2:$NE$60=K$3)*(GMWQ!$ND$2:$ND$60=K$4)*(GMWQ!$NF$2:$NF$60=K$1),0),$F32-1966)} -> 299.071 | L32: {=INDEX(GMWQ!$A$2:$NF$60,MATCH(1,(GMWQ!$NE$2:$NE$60=L$3)*(GMWQ!$ND$2:$ND$60=L$4)*(GMWQ!$NF$2:$NF$60=L$1),0),$F32-1966)} -> 283.1178 | M32: {=INDEX(GMWQ!$A$2:$NF$60,MATCH(1,(GMWQ!$NE$2:$NE$60=M$3)*(GMWQ!$ND$2:$ND$60=M$4)*(GMWQ!$NF$2:$NF$60=M$1),0),$F32-1966)} -> 218430.3 | N32: {=INDEX(GMWQ!$A$2:$NF$60,MATCH(1,(GMWQ!$NE$2:$NE$60=N$3)*(GMWQ!$ND$2:$ND$60=N$4)*(GMWQ!$NF$2:$NF$60=N$1),0),$F32-1966)} -> -2137 | ... AL32: {=INDEX(GMWQ!$A$2:$NF$60,MATCH(1,(GMWQ!$NE$2:$NE$60=AL$3)*(GMWQ!$ND$2:$ND$60=AL$4)*(GMWQ!$NF$2:$NF$60=AL$1),0),$F32-1966)} -> 0
B33: =+B29+1 -> 1979 | C33: =+C29+1 -> 1979 | F33: =+F32+1 -> 1999 | G33: {=INDEX(GMWQ!$A$2:$NF$60,MATCH(1,(GMWQ!$NE$2:$NE$60=G$3)*(GMWQ!$ND$2:$ND$60=G$4)*(GMWQ!$NF$2:$NF$60=G$1),0),$F33-1966)} -> 290297 | H33: {=INDEX(GMWQ!$A$2:$NF$60,MATCH(1,(GMWQ!$NE$2:$NE$60=H$3)*(GMWQ!$ND$2:$ND$60=H$4)*(GMWQ!$NF$2:$NF$60=H$1),0),$F33-1966)} -> 1825.075 | I33: {=INDEX(GMWQ!$A$2:$NF$60,MATCH(1,(GMWQ!$NE$2:$NE$60=I$3)*(GMWQ!$ND$2:$ND$60=I$4)*(GMWQ!$NF$2:$NF$60=I$1),0),$F33-1966)} -> 65872.72 | J33: {=INDEX(GMWQ!$A$2:$NF$60,MATCH(1,(GMWQ!$NE$2:$NE$60=J$3)*(GMWQ!$ND$2:$ND$60=J$4)*(GMWQ!$NF$2:$NF$60=J$1),0),$F33-1966)} -> 455.43 | K33: {=INDEX(GMWQ!$A$2:$NF$60,MATCH(1,(GMWQ!$NE$2:$NE$60=K$3)*(GMWQ!$ND$2:$ND$60=K$4)*(GMWQ!$NF$2:$NF$60=K$1),0),$F33-1966)} -> 302.92 | L33: {=INDEX(GMWQ!$A$2:$NF$60,MATCH(1,(GMWQ!$NE$2:$NE$60=L$3)*(GMWQ!$ND$2:$ND$60=L$4)*(GMWQ!$NF$2:$NF$60=L$1),0),$F33-1966)} -> 288.0178 | M33: {=INDEX(GMWQ!$A$2:$NF$60,MATCH(1,(GMWQ!$NE$2:$NE$60=M$3)*(GMWQ!$ND$2:$ND$60=M$4)*(GMWQ!$NF$2:$NF$60=M$1),0),$F33-1966)} -> 220031.5 | N33: {=INDEX(GMWQ!$A$2:$NF$60,MATCH(1,(GMWQ!$NE$2:$NE$60=N$3)*(GMWQ!$ND$2:$ND$60=N$4)*(GMWQ!$NF$2:$NF$60=N$1),0),$F33-1966)} -> -2934 | ... AL33: {=INDEX(GMWQ!$A$2:$NF$60,MATCH(1,(GMWQ!$NE$2:$NE$60=AL$3)*(GMWQ!$ND$2:$ND$60=AL$4)*(GMWQ!$NF$2:$NF$60=AL$1),0),$F33-1966)} -> 0
B34: =+B30+1 -> 1979 | C34: =+C30+1 -> 1979 | E34: =+E30+1 -> 1979 | F34: =+F33+1 -> 2000 | G34: {=INDEX(GMWQ!$A$2:$NF$60,MATCH(1,(GMWQ!$NE$2:$NE$60=G$3)*(GMWQ!$ND$2:$ND$60=G$4)*(GMWQ!$NF$2:$NF$60=G$1),0),$F34-1966)} -> 293265 | H34: {=INDEX(GMWQ!$A$2:$NF$60,MATCH(1,(GMWQ!$NE$2:$NE$60=H$3)*(GMWQ!$ND$2:$ND$60=H$4)*(GMWQ!$NF$2:$NF$60=H$1),0),$F34-1966)} -> 1829.625 | I34: {=INDEX(GMWQ!$A$2:$NF$60,MATCH(1,(GMWQ!$NE$2:$NE$60=I$3)*(GMWQ!$ND$2:$ND$60=I$4)*(GMWQ!$NF$2:$NF$60=I$1),0),$F34-1966)} -> 66157.2 | J34: {=INDEX(GMWQ!$A$2:$NF$60,MATCH(1,(GMWQ!$NE$2:$NE$60=J$3)*(GMWQ!$ND$2:$ND$60=J$4)*(GMWQ!$NF$2:$NF$60=J$1),0),$F34-1966)} -> 458.15 | K34: {=INDEX(GMWQ!$A$2:$NF$60,MATCH(1,(GMWQ!$NE$2:$NE$60=K$3)*(GMWQ!$ND$2:$ND$60=K$4)*(GMWQ!$NF$2:$NF$60=K$1),0),$F34-1966)} -> 303.971 | L34: {=INDEX(GMWQ!$A$2:$NF$60,MATCH(1,(GMWQ!$NE$2:$NE$60=L$3)*(GMWQ!$ND$2:$ND$60=L$4)*(GMWQ!$NF$2:$NF$60=L$1),0),$F34-1966)} -> 294.7971 | M34: {=INDEX(GMWQ!$A$2:$NF$60,MATCH(1,(GMWQ!$NE$2:$NE$60=M$3)*(GMWQ!$ND$2:$ND$60=M$4)*(GMWQ!$NF$2:$NF$60=M$1),0),$F34-1966)} -> 221507.8 | N34: {=INDEX(GMWQ!$A$2:$NF$60,MATCH(1,(GMWQ!$NE$2:$NE$60=N$3)*(GMWQ!$ND$2:$ND$60=N$4)*(GMWQ!$NF$2:$NF$60=N$1),0),$F34-1966)} -> -1801 | ... AL34: {=INDEX(GMWQ!$A$2:$NF$60,MATCH(1,(GMWQ!$NE$2:$NE$60=AL$3)*(GMWQ!$ND$2:$ND$60=AL$4)*(GMWQ!$NF$2:$NF$60=AL$1),0),$F34-1966)} -> 0
A35: 1980 | B35: =+B31+1 -> 1980 | C35: =+C31+1 -> 1979 | D35: =+D31+1 -> 1979 | F35: =+F34+1 -> 2001 | G35: {=INDEX(GMWQ!$A$2:$NF$60,MATCH(1,(GMWQ!$NE$2:$NE$60=G$3)*(GMWQ!$ND$2:$ND$60=G$4)*(GMWQ!$NF$2:$NF$60=G$1),0),$F35-1966)} -> 290378 | H35: {=INDEX(GMWQ!$A$2:$NF$60,MATCH(1,(GMWQ!$NE$2:$NE$60=H$3)*(GMWQ!$ND$2:$ND$60=H$4)*(GMWQ!$NF$2:$NF$60=H$1),0),$F35-1966)} -> 1835.4 | I35: {=INDEX(GMWQ!$A$2:$NF$60,MATCH(1,(GMWQ!$NE$2:$NE$60=I$3)*(GMWQ!$ND$2:$ND$60=I$4)*(GMWQ!$NF$2:$NF$60=I$1),0),$F35-1966)} -> 67431.65 | J35: {=INDEX(GMWQ!$A$2:$NF$60,MATCH(1,(GMWQ!$NE$2:$NE$60=J$3)*(GMWQ!$ND$2:$ND$60=J$4)*(GMWQ!$NF$2:$NF$60=J$1),0),$F35-1966)} -> 461.8 | K35: {=INDEX(GMWQ!$A$2:$NF$60,MATCH(1,(GMWQ!$NE$2:$NE$60=K$3)*(GMWQ!$ND$2:$ND$60=K$4)*(GMWQ!$NF$2:$NF$60=K$1),0),$F35-1966)} -> 307.574 | L35: {=INDEX(GMWQ!$A$2:$NF$60,MATCH(1,(GMWQ!$NE$2:$NE$60=L$3)*(GMWQ!$ND$2:$ND$60=L$4)*(GMWQ!$NF$2:$NF$60=L$1),0),$F35-1966)} -> 294.2694 | M35: {=INDEX(GMWQ!$A$2:$NF$60,MATCH(1,(GMWQ!$NE$2:$NE$60=M$3)*(GMWQ!$ND$2:$ND$60=M$4)*(GMWQ!$NF$2:$NF$60=M$1),0),$F35-1966)} -> 223045.8 | N35: {=INDEX(GMWQ!$A$2:$NF$60,MATCH(1,(GMWQ!$NE$2:$NE$60=N$3)*(GMWQ!$ND$2:$ND$60=N$4)*(GMWQ!$NF$2:$NF$60=N$1),0),$F35-1966)} -> -1674 | ... AL35: {=INDEX(GMWQ!$A$2:$NF$60,MATCH(1,(GMWQ!$NE$2:$NE$60=AL$3)*(GMWQ!$ND$2:$ND$60=AL$4)*(GMWQ!$NF$2:$NF$60=AL$1),0),$F35-1966)} -> -809.2665
B36: =+B32+1 -> 1980 | C36: =+C32+1 -> 1980 | F36: =+F35+1 -> 2002 | G36: {=INDEX(GMWQ!$A$2:$NF$60,MATCH(1,(GMWQ!$NE$2:$NE$60=G$3)*(GMWQ!$ND$2:$ND$60=G$4)*(GMWQ!$NF$2:$NF$60=G$1),0),$F36-1966)} -> 284713 | H36: {=INDEX(GMWQ!$A$2:$NF$60,MATCH(1,(GMWQ!$NE$2:$NE$60=H$3)*(GMWQ!$ND$2:$ND$60=H$4)*(GMWQ!$NF$2:$NF$60=H$1),0),$F36-1966)} -> 1797.575 | I36: {=INDEX(GMWQ!$A$2:$NF$60,MATCH(1,(GMWQ!$NE$2:$NE$60=I$3)*(GMWQ!$ND$2:$ND$60=I$4)*(GMWQ!$NF$2:$NF$60=I$1),0),$F36-1966)} -> 67125.25 | J36: {=INDEX(GMWQ!$A$2:$NF$60,MATCH(1,(GMWQ!$NE$2:$NE$60=J$3)*(GMWQ!$ND$2:$ND$60=J$4)*(GMWQ!$NF$2:$NF$60=J$1),0),$F36-1966)} -> 458.81 | K36: {=INDEX(GMWQ!$A$2:$NF$60,MATCH(1,(GMWQ!$NE$2:$NE$60=K$3)*(GMWQ!$ND$2:$ND$60=K$4)*(GMWQ!$NF$2:$NF$60=K$1),0),$F36-1966)} -> 305.096 | L36: {=INDEX(GMWQ!$A$2:$NF$60,MATCH(1,(GMWQ!$NE$2:$NE$60=L$3)*(GMWQ!$ND$2:$ND$60=L$4)*(GMWQ!$NF$2:$NF$60=L$1),0),$F36-1966)} -> 296.5532 | M36: {=INDEX(GMWQ!$A$2:$NF$60,MATCH(1,(GMWQ!$NE$2:$NE$60=M$3)*(GMWQ!$ND$2:$ND$60=M$4)*(GMWQ!$NF$2:$NF$60=M$1),0),$F36-1966)} -> 222948.3 | N36: {=INDEX(GMWQ!$A$2:$NF$60,MATCH(1,(GMWQ!$NE$2:$NE$60=N$3)*(GMWQ!$ND$2:$ND$60=N$4)*(GMWQ!$NF$2:$NF$60=N$1),0),$F36-1966)} -> -3351 | ... AL36: {=INDEX(GMWQ!$A$2:$NF$60,MATCH(1,(GMWQ!$NE$2:$NE$60=AL$3)*(GMWQ!$ND$2:$ND$60=AL$4)*(GMWQ!$NF$2:$NF$60=AL$1),0),$F36-1966)} -> -845.0994
B37: =+B33+1 -> 1980 | C37: =+C33+1 -> 1980 | F37: =+F36+1 -> 2003 | G37: {=INDEX(GMWQ!$A$2:$NF$60,MATCH(1,(GMWQ!$NE$2:$NE$60=G$3)*(GMWQ!$ND$2:$ND$60=G$4)*(GMWQ!$NF$2:$NF$60=G$1),0),$F37-1966)} -> 284402 | H37: {=INDEX(GMWQ!$A$2:$NF$60,MATCH(1,(GMWQ!$NE$2:$NE$60=H$3)*(GMWQ!$ND$2:$ND$60=H$4)*(GMWQ!$NF$2:$NF$60=H$1),0),$F37-1966)} -> 1795.425 | I37: {=INDEX(GMWQ!$A$2:$NF$60,MATCH(1,(GMWQ!$NE$2:$NE$60=I$3)*(GMWQ!$ND$2:$ND$60=I$4)*(GMWQ!$NF$2:$NF$60=I$1),0),$F37-1966)} -> 68540.48 | J37: {=INDEX(GMWQ!$A$2:$NF$60,MATCH(1,(GMWQ!$NE$2:$NE$60=J$3)*(GMWQ!$ND$2:$ND$60=J$4)*(GMWQ!$NF$2:$NF$60=J$1),0),$F37-1966)} -> 457 | K37: {=INDEX(GMWQ!$A$2:$NF$60,MATCH(1,(GMWQ!$NE$2:$NE$60=K$3)*(GMWQ!$ND$2:$ND$60=K$4)*(GMWQ!$NF$2:$NF$60=K$1),0),$F37-1966)} -> 305.557 | L37: {=INDEX(GMWQ!$A$2:$NF$60,MATCH(1,(GMWQ!$NE$2:$NE$60=L$3)*(GMWQ!$ND$2:$ND$60=L$4)*(GMWQ!$NF$2:$NF$60=L$1),0),$F37-1966)} -> 296.8017 | M37: {=INDEX(GMWQ!$A$2:$NF$60,MATCH(1,(GMWQ!$NE$2:$NE$60=M$3)*(GMWQ!$ND$2:$ND$60=M$4)*(GMWQ!$NF$2:$NF$60=M$1),0),$F37-1966)} -> 222763 | N37: {=INDEX(GMWQ!$A$2:$NF$60,MATCH(1,(GMWQ!$NE$2:$NE$60=N$3)*(GMWQ!$ND$2:$ND$60=N$4)*(GMWQ!$NF$2:$NF$60=N$1),0),$F37-1966)} -> -3213 | ... AL37: {=INDEX(GMWQ!$A$2:$NF$60,MATCH(1,(GMWQ!$NE$2:$NE$60=AL$3)*(GMWQ!$ND$2:$ND$60=AL$4)*(GMWQ!$NF$2:$NF$60=AL$1),0),$F37-1966)} -> -865.8214
B38: =+B34+1 -> 1980 | C38: =+C34+1 -> 1980 | E38: =+E34+1 -> 1980 | F38: =+F37+1 -> 2004 | G38: {=INDEX(GMWQ!$A$2:$NF$60,MATCH(1,(GMWQ!$NE$2:$NE$60=G$3)*(GMWQ!$ND$2:$ND$60=G$4)*(GMWQ!$NF$2:$NF$60=G$1),0),$F38-1966)} -> 281496 | H38: {=INDEX(GMWQ!$A$2:$NF$60,MATCH(1,(GMWQ!$NE$2:$NE$60=H$3)*(GMWQ!$ND$2:$ND$60=H$4)*(GMWQ!$NF$2:$NF$60=H$1),0),$F38-1966)} -> 1828.925 | I38: {=INDEX(GMWQ!$A$2:$NF$60,MATCH(1,(GMWQ!$NE$2:$NE$60=I$3)*(GMWQ!$ND$2:$ND$60=I$4)*(GMWQ!$NF$2:$NF$60=I$1),0),$F38-1966)} -> 69895.05 | J38: {=INDEX(GMWQ!$A$2:$NF$60,MATCH(1,(GMWQ!$NE$2:$NE$60=J$3)*(GMWQ!$ND$2:$ND$60=J$4)*(GMWQ!$NF$2:$NF$60=J$1),0),$F38-1966)} -> 456.34 | K38: {=INDEX(GMWQ!$A$2:$NF$60,MATCH(1,(GMWQ!$NE$2:$NE$60=K$3)*(GMWQ!$ND$2:$ND$60=K$4)*(GMWQ!$NF$2:$NF$60=K$1),0),$F38-1966)} -> 305.08 | L38: {=INDEX(GMWQ!$A$2:$NF$60,MATCH(1,(GMWQ!$NE$2:$NE$60=L$3)*(GMWQ!$ND$2:$ND$60=L$4)*(GMWQ!$NF$2:$NF$60=L$1),0),$F38-1966)} -> 299.3304 | M38: {=INDEX(GMWQ!$A$2:$NF$60,MATCH(1,(GMWQ!$NE$2:$NE$60=M$3)*(GMWQ!$ND$2:$ND$60=M$4)*(GMWQ!$NF$2:$NF$60=M$1),0),$F38-1966)} -> 225845.3 | N38: {=INDEX(GMWQ!$A$2:$NF$60,MATCH(1,(GMWQ!$NE$2:$NE$60=N$3)*(GMWQ!$ND$2:$ND$60=N$4)*(GMWQ!$NF$2:$NF$60=N$1),0),$F38-1966)} -> -1803 | ... AL38: {=INDEX(GMWQ!$A$2:$NF$60,MATCH(1,(GMWQ!$NE$2:$NE$60=AL$3)*(GMWQ!$ND$2:$ND$60=AL$4)*(GMWQ!$NF$2:$NF$60=AL$1),0),$F38-1966)} -> -880.4047
A39: 1981 | B39: =+B35+1 -> 1981 | C39: =+C35+1 -> 1980 | D39: =+D35+1 -> 1980 | F39: =+F38+1 -> 2005 | G39: {=INDEX(GMWQ!$A$2:$NF$60,MATCH(1,(GMWQ!$NE$2:$NE$60=G$3)*(GMWQ!$ND$2:$ND$60=G$4)*(GMWQ!$NF$2:$NF$60=G$1),0),$F39-1966)} -> 281257 | H39: {=INDEX(GMWQ!$A$2:$NF$60,MATCH(1,(GMWQ!$NE$2:$NE$60=H$3)*(GMWQ!$ND$2:$ND$60=H$4)*(GMWQ!$NF$2:$NF$60=H$1),0),$F39-1966)} -> 1864.75 | I39: {=INDEX(GMWQ!$A$2:$NF$60,MATCH(1,(GMWQ!$NE$2:$NE$60=I$3)*(GMWQ!$ND$2:$ND$60=I$4)*(GMWQ!$NF$2:$NF$60=I$1),0),$F39-1966)} -> 70493.48 | J39: {=INDEX(GMWQ!$A$2:$NF$60,MATCH(1,(GMWQ!$NE$2:$NE$60=J$3)*(GMWQ!$ND$2:$ND$60=J$4)*(GMWQ!$NF$2:$NF$60=J$1),0),$F39-1966)} -> 461.88 | K39: {=INDEX(GMWQ!$A$2:$NF$60,MATCH(1,(GMWQ!$NE$2:$NE$60=K$3)*(GMWQ!$ND$2:$ND$60=K$4)*(GMWQ!$NF$2:$NF$60=K$1),0),$F39-1966)} -> 306.214 | L39: {=INDEX(GMWQ!$A$2:$NF$60,MATCH(1,(GMWQ!$NE$2:$NE$60=L$3)*(GMWQ!$ND$2:$ND$60=L$4)*(GMWQ!$NF$2:$NF$60=L$1),0),$F39-1966)} -> 298.359 | M39: {=INDEX(GMWQ!$A$2:$NF$60,MATCH(1,(GMWQ!$NE$2:$NE$60=M$3)*(GMWQ!$ND$2:$ND$60=M$4)*(GMWQ!$NF$2:$NF$60=M$1),0),$F39-1966)} -> 230710.8 | N39: {=INDEX(GMWQ!$A$2:$NF$60,MATCH(1,(GMWQ!$NE$2:$NE$60=N$3)*(GMWQ!$ND$2:$ND$60=N$4)*(GMWQ!$NF$2:$NF$60=N$1),0),$F39-1966)} -> -3170 | ... AL39: {=INDEX(GMWQ!$A$2:$NF$60,MATCH(1,(GMWQ!$NE$2:$NE$60=AL$3)*(GMWQ!$ND$2:$ND$60=AL$4)*(GMWQ!$NF$2:$NF$60=AL$1),0),$F39-1966)} -> -87.59197
B40: =+B36+1 -> 1981 | C40: =+C36+1 -> 1981 | F40: =+F39+1 -> 2006 | G40: {=INDEX(GMWQ!$A$2:$NF$60,MATCH(1,(GMWQ!$NE$2:$NE$60=G$3)*(GMWQ!$ND$2:$ND$60=G$4)*(GMWQ!$NF$2:$NF$60=G$1),0),$F40-1966)} -> 282155 | H40: {=INDEX(GMWQ!$A$2:$NF$60,MATCH(1,(GMWQ!$NE$2:$NE$60=H$3)*(GMWQ!$ND$2:$ND$60=H$4)*(GMWQ!$NF$2:$NF$60=H$1),0),$F40-1966)} -> 1850.925 | I40: {=INDEX(GMWQ!$A$2:$NF$60,MATCH(1,(GMWQ!$NE$2:$NE$60=I$3)*(GMWQ!$ND$2:$ND$60=I$4)*(GMWQ!$NF$2:$NF$60=I$1),0),$F40-1966)} -> 71146.73 | J40: {=INDEX(GMWQ!$A$2:$NF$60,MATCH(1,(GMWQ!$NE$2:$NE$60=J$3)*(GMWQ!$ND$2:$ND$60=J$4)*(GMWQ!$NF$2:$NF$60=J$1),0),$F40-1966)} -> 460.64 | K40: {=INDEX(GMWQ!$A$2:$NF$60,MATCH(1,(GMWQ!$NE$2:$NE$60=K$3)*(GMWQ!$ND$2:$ND$60=K$4)*(GMWQ!$NF$2:$NF$60=K$1),0),$F40-1966)} -> 308.53 | L40: {=INDEX(GMWQ!$A$2:$NF$60,MATCH(1,(GMWQ!$NE$2:$NE$60=L$3)*(GMWQ!$ND$2:$ND$60=L$4)*(GMWQ!$NF$2:$NF$60=L$1),0),$F40-1966)} -> 298.941 | M40: {=INDEX(GMWQ!$A$2:$NF$60,MATCH(1,(GMWQ!$NE$2:$NE$60=M$3)*(GMWQ!$ND$2:$ND$60=M$4)*(GMWQ!$NF$2:$NF$60=M$1),0),$F40-1966)} -> 233233.3 | N40: {=INDEX(GMWQ!$A$2:$NF$60,MATCH(1,(GMWQ!$NE$2:$NE$60=N$3)*(GMWQ!$ND$2:$ND$60=N$4)*(GMWQ!$NF$2:$NF$60=N$1),0),$F40-1966)} -> -3679 | ... AL40: {=INDEX(GMWQ!$A$2:$NF$60,MATCH(1,(GMWQ!$NE$2:$NE$60=AL$3)*(GMWQ!$ND$2:$ND$60=AL$4)*(GMWQ!$NF$2:$NF$60=AL$1),0),$F40-1966)} -> -61.88543
B41: =+B37+1 -> 1981 | C41: =+C37+1 -> 1981 | F41: =+F40+1 -> 2007 | G41: {=INDEX(GMWQ!$A$2:$NF$60,MATCH(1,(GMWQ!$NE$2:$NE$60=G$3)*(GMWQ!$ND$2:$ND$60=G$4)*(GMWQ!$NF$2:$NF$60=G$1),0),$F41-1966)} -> 285437 | H41: {=INDEX(GMWQ!$A$2:$NF$60,MATCH(1,(GMWQ!$NE$2:$NE$60=H$3)*(GMWQ!$ND$2:$ND$60=H$4)*(GMWQ!$NF$2:$NF$60=H$1),0),$F41-1966)} -> 1873.1 | I41: {=INDEX(GMWQ!$A$2:$NF$60,MATCH(1,(GMWQ!$NE$2:$NE$60=I$3)*(GMWQ!$ND$2:$ND$60=I$4)*(GMWQ!$NF$2:$NF$60=I$1),0),$F41-1966)} -> 71480.1 | J41: {=INDEX(GMWQ!$A$2:$NF$60,MATCH(1,(GMWQ!$NE$2:$NE$60=J$3)*(GMWQ!$ND$2:$ND$60=J$4)*(GMWQ!$NF$2:$NF$60=J$1),0),$F41-1966)} -> 461.88 | K41: {=INDEX(GMWQ!$A$2:$NF$60,MATCH(1,(GMWQ!$NE$2:$NE$60=K$3)*(GMWQ!$ND$2:$ND$60=K$4)*(GMWQ!$NF$2:$NF$60=K$1),0),$F41-1966)} -> 310.602 | L41: {=INDEX(GMWQ!$A$2:$NF$60,MATCH(1,(GMWQ!$NE$2:$NE$60=L$3)*(GMWQ!$ND$2:$ND$60=L$4)*(GMWQ!$NF$2:$NF$60=L$1),0),$F41-1966)} -> 299.08 | M41: {=INDEX(GMWQ!$A$2:$NF$60,MATCH(1,(GMWQ!$NE$2:$NE$60=M$3)*(GMWQ!$ND$2:$ND$60=M$4)*(GMWQ!$NF$2:$NF$60=M$1),0),$F41-1966)} -> 231136.3 | N41: {=INDEX(GMWQ!$A$2:$NF$60,MATCH(1,(GMWQ!$NE$2:$NE$60=N$3)*(GMWQ!$ND$2:$ND$60=N$4)*(GMWQ!$NF$2:$NF$60=N$1),0),$F41-1966)} -> -2967 | ... AL41: {=INDEX(GMWQ!$A$2:$NF$60,MATCH(1,(GMWQ!$NE$2:$NE$60=AL$3)*(GMWQ!$ND$2:$ND$60=AL$4)*(GMWQ!$NF$2:$NF$60=AL$1),0),$F41-1966)} -> -49.27825
B42: =+B38+1 -> 1981 | C42: =+C38+1 -> 1981 | E42: =+E38+1 -> 1981 | F42: =+F41+1 -> 2008 | G42: {=INDEX(GMWQ!$A$2:$NF$60,MATCH(1,(GMWQ!$NE$2:$NE$60=G$3)*(GMWQ!$ND$2:$ND$60=G$4)*(GMWQ!$NF$2:$NF$60=G$1),0),$F42-1966)} -> 285814 | H42: {=INDEX(GMWQ!$A$2:$NF$60,MATCH(1,(GMWQ!$NE$2:$NE$60=H$3)*(GMWQ!$ND$2:$ND$60=H$4)*(GMWQ!$NF$2:$NF$60=H$1),0),$F42-1966)} -> 1852.7 | I42: {=INDEX(GMWQ!$A$2:$NF$60,MATCH(1,(GMWQ!$NE$2:$NE$60=I$3)*(GMWQ!$ND$2:$ND$60=I$4)*(GMWQ!$NF$2:$NF$60=I$1),0),$F42-1966)} -> 71827.58 | J42: {=INDEX(GMWQ!$A$2:$NF$60,MATCH(1,(GMWQ!$NE$2:$NE$60=J$3)*(GMWQ!$ND$2:$ND$60=J$4)*(GMWQ!$NF$2:$NF$60=J$1),0),$F42-1966)} -> 461.46 | K42: {=INDEX(GMWQ!$A$2:$NF$60,MATCH(1,(GMWQ!$NE$2:$NE$60=K$3)*(GMWQ!$ND$2:$ND$60=K$4)*(GMWQ!$NF$2:$NF$60=K$1),0),$F42-1966)} -> 312.474 | L42: {=INDEX(GMWQ!$A$2:$NF$60,MATCH(1,(GMWQ!$NE$2:$NE$60=L$3)*(GMWQ!$ND$2:$ND$60=L$4)*(GMWQ!$NF$2:$NF$60=L$1),0),$F42-1966)} -> 301.507 | M42: {=INDEX(GMWQ!$A$2:$NF$60,MATCH(1,(GMWQ!$NE$2:$NE$60=M$3)*(GMWQ!$ND$2:$ND$60=M$4)*(GMWQ!$NF$2:$NF$60=M$1),0),$F42-1966)} -> 230073.3 | N42: {=INDEX(GMWQ!$A$2:$NF$60,MATCH(1,(GMWQ!$NE$2:$NE$60=N$3)*(GMWQ!$ND$2:$ND$60=N$4)*(GMWQ!$NF$2:$NF$60=N$1),0),$F42-1966)} -> 991 | ... AL42: {=INDEX(GMWQ!$A$2:$NF$60,MATCH(1,(GMWQ!$NE$2:$NE$60=AL$3)*(GMWQ!$ND$2:$ND$60=AL$4)*(GMWQ!$NF$2:$NF$60=AL$1),0),$F42-1966)} -> -41.42122
A43: 1982 | B43: =+B39+1 -> 1982 | C43: =+C39+1 -> 1981 | D43: =+D39+1 -> 1981 | F43: =+F42+1 -> 2009 | G43: {=INDEX(GMWQ!$A$2:$NF$60,MATCH(1,(GMWQ!$NE$2:$NE$60=G$3)*(GMWQ!$ND$2:$ND$60=G$4)*(GMWQ!$NF$2:$NF$60=G$1),0),$F43-1966)} -> 286275 | H43: {=INDEX(GMWQ!$A$2:$NF$60,MATCH(1,(GMWQ!$NE$2:$NE$60=H$3)*(GMWQ!$ND$2:$ND$60=H$4)*(GMWQ!$NF$2:$NF$60=H$1),0),$F43-1966)} -> 1823.9 | I43: {=INDEX(GMWQ!$A$2:$NF$60,MATCH(1,(GMWQ!$NE$2:$NE$60=I$3)*(GMWQ!$ND$2:$ND$60=I$4)*(GMWQ!$NF$2:$NF$60=I$1),0),$F43-1966)} -> 72823.85 | J43: {=INDEX(GMWQ!$A$2:$NF$60,MATCH(1,(GMWQ!$NE$2:$NE$60=J$3)*(GMWQ!$ND$2:$ND$60=J$4)*(GMWQ!$NF$2:$NF$60=J$1),0),$F43-1966)} -> 463.29 | K43: {=INDEX(GMWQ!$A$2:$NF$60,MATCH(1,(GMWQ!$NE$2:$NE$60=K$3)*(GMWQ!$ND$2:$ND$60=K$4)*(GMWQ!$NF$2:$NF$60=K$1),0),$F43-1966)} -> 314.838 | L43: {=INDEX(GMWQ!$A$2:$NF$60,MATCH(1,(GMWQ!$NE$2:$NE$60=L$3)*(GMWQ!$ND$2:$ND$60=L$4)*(GMWQ!$NF$2:$NF$60=L$1),0),$F43-1966)} -> 301.387 | M43: {=INDEX(GMWQ!$A$2:$NF$60,MATCH(1,(GMWQ!$NE$2:$NE$60=M$3)*(GMWQ!$ND$2:$ND$60=M$4)*(GMWQ!$NF$2:$NF$60=M$1),0),$F43-1966)} -> 227440.3 | N43: {=INDEX(GMWQ!$A$2:$NF$60,MATCH(1,(GMWQ!$NE$2:$NE$60=N$3)*(GMWQ!$ND$2:$ND$60=N$4)*(GMWQ!$NF$2:$NF$60=N$1),0),$F43-1966)} -> -344 | ... AL43: {=INDEX(GMWQ!$A$2:$NF$60,MATCH(1,(GMWQ!$NE$2:$NE$60=AL$3)*(GMWQ!$ND$2:$ND$60=AL$4)*(GMWQ!$NF$2:$NF$60=AL$1),0),$F43-1966)} -> -30.05238
B44: =+B40+1 -> 1982 | C44: =+C40+1 -> 1982 | F44: =+F43+1 -> 2010 | G44: {=INDEX(GMWQ!$A$2:$NF$60,MATCH(1,(GMWQ!$NE$2:$NE$60=G$3)*(GMWQ!$ND$2:$ND$60=G$4)*(GMWQ!$NF$2:$NF$60=G$1),0),$F44-1966)} -> 289232 | H44: {=INDEX(GMWQ!$A$2:$NF$60,MATCH(1,(GMWQ!$NE$2:$NE$60=H$3)*(GMWQ!$ND$2:$ND$60=H$4)*(GMWQ!$NF$2:$NF$60=H$1),0),$F44-1966)} -> 1832.225 | I44: {=INDEX(GMWQ!$A$2:$NF$60,MATCH(1,(GMWQ!$NE$2:$NE$60=I$3)*(GMWQ!$ND$2:$ND$60=I$4)*(GMWQ!$NF$2:$NF$60=I$1),0),$F44-1966)} -> 73296.85 | J44: {=INDEX(GMWQ!$A$2:$NF$60,MATCH(1,(GMWQ!$NE$2:$NE$60=J$3)*(GMWQ!$ND$2:$ND$60=J$4)*(GMWQ!$NF$2:$NF$60=J$1),0),$F44-1966)} -> 460.39 | K44: {=INDEX(GMWQ!$A$2:$NF$60,MATCH(1,(GMWQ!$NE$2:$NE$60=K$3)*(GMWQ!$ND$2:$ND$60=K$4)*(GMWQ!$NF$2:$NF$60=K$1),0),$F44-1966)} -> 317.069 | L44: {=INDEX(GMWQ!$A$2:$NF$60,MATCH(1,(GMWQ!$NE$2:$NE$60=L$3)*(GMWQ!$ND$2:$ND$60=L$4)*(GMWQ!$NF$2:$NF$60=L$1),0),$F44-1966)} -> 300.531 | M44: {=INDEX(GMWQ!$A$2:$NF$60,MATCH(1,(GMWQ!$NE$2:$NE$60=M$3)*(GMWQ!$ND$2:$ND$60=M$4)*(GMWQ!$NF$2:$NF$60=M$1),0),$F44-1966)} -> 224821.8 | N44: {=INDEX(GMWQ!$A$2:$NF$60,MATCH(1,(GMWQ!$NE$2:$NE$60=N$3)*(GMWQ!$ND$2:$ND$60=N$4)*(GMWQ!$NF$2:$NF$60=N$1),0),$F44-1966)} -> -2938 | ... AL44: {=INDEX(GMWQ!$A$2:$NF$60,MATCH(1,(GMWQ!$NE$2:$NE$60=AL$3)*(GMWQ!$ND$2:$ND$60=AL$4)*(GMWQ!$NF$2:$NF$60=AL$1),0),$F44-1966)} -> -20.7383
B45: =+B41+1 -> 1982 | C45: =+C41+1 -> 1982 | F45: =+F44+1 -> 2011 | G45: {=INDEX(GMWQ!$A$2:$NF$60,MATCH(1,(GMWQ!$NE$2:$NE$60=G$3)*(GMWQ!$ND$2:$ND$60=G$4)*(GMWQ!$NF$2:$NF$60=G$1),0),$F45-1966)} -> 289852 | H45: {=INDEX(GMWQ!$A$2:$NF$60,MATCH(1,(GMWQ!$NE$2:$NE$60=H$3)*(GMWQ!$ND$2:$ND$60=H$4)*(GMWQ!$NF$2:$NF$60=H$1),0),$F45-1966)} -> 1825.225 | I45: {=INDEX(GMWQ!$A$2:$NF$60,MATCH(1,(GMWQ!$NE$2:$NE$60=I$3)*(GMWQ!$ND$2:$ND$60=I$4)*(GMWQ!$NF$2:$NF$60=I$1),0),$F45-1966)} -> 73595.08 | J45: {=INDEX(GMWQ!$A$2:$NF$60,MATCH(1,(GMWQ!$NE$2:$NE$60=J$3)*(GMWQ!$ND$2:$ND$60=J$4)*(GMWQ!$NF$2:$NF$60=J$1),0),$F45-1966)} -> 455.93 | K45: {=INDEX(GMWQ!$A$2:$NF$60,MATCH(1,(GMWQ!$NE$2:$NE$60=K$3)*(GMWQ!$ND$2:$ND$60=K$4)*(GMWQ!$NF$2:$NF$60=K$1),0),$F45-1966)} -> 316.885 | L45: {=INDEX(GMWQ!$A$2:$NF$60,MATCH(1,(GMWQ!$NE$2:$NE$60=L$3)*(GMWQ!$ND$2:$ND$60=L$4)*(GMWQ!$NF$2:$NF$60=L$1),0),$F45-1966)} -> 300.37 | M45: {=INDEX(GMWQ!$A$2:$NF$60,MATCH(1,(GMWQ!$NE$2:$NE$60=M$3)*(GMWQ!$ND$2:$ND$60=M$4)*(GMWQ!$NF$2:$NF$60=M$1),0),$F45-1966)} -> 222828 | N45: {=INDEX(GMWQ!$A$2:$NF$60,MATCH(1,(GMWQ!$NE$2:$NE$60=N$3)*(GMWQ!$ND$2:$ND$60=N$4)*(GMWQ!$NF$2:$NF$60=N$1),0),$F45-1966)} -> -2421 | ... AL45: {=INDEX(GMWQ!$A$2:$NF$60,MATCH(1,(GMWQ!$NE$2:$NE$60=AL$3)*(GMWQ!$ND$2:$ND$60=AL$4)*(GMWQ!$NF$2:$NF$60=AL$1),0),$F45-1966)} -> -12.85332
B46: =+B42+1 -> 1982 | C46: =+C42+1 -> 1982 | E46: =+E42+1 -> 1982 | F46: =+F45+1 -> 2012 | G46: {=INDEX(GMWQ!$A$2:$NF$60,MATCH(1,(GMWQ!$NE$2:$NE$60=G$3)*(GMWQ!$ND$2:$ND$60=G$4)*(GMWQ!$NF$2:$NF$60=G$1),0),$F46-1966)} -> 291832 | H46: {=INDEX(GMWQ!$A$2:$NF$60,MATCH(1,(GMWQ!$NE$2:$NE$60=H$3)*(GMWQ!$ND$2:$ND$60=H$4)*(GMWQ!$NF$2:$NF$60=H$1),0),$F46-1966)} -> 1825.95 | I46: {=INDEX(GMWQ!$A$2:$NF$60,MATCH(1,(GMWQ!$NE$2:$NE$60=I$3)*(GMWQ!$ND$2:$ND$60=I$4)*(GMWQ!$NF$2:$NF$60=I$1),0),$F46-1966)} -> 74635.23 | J46: {=INDEX(GMWQ!$A$2:$NF$60,MATCH(1,(GMWQ!$NE$2:$NE$60=J$3)*(GMWQ!$ND$2:$ND$60=J$4)*(GMWQ!$NF$2:$NF$60=J$1),0),$F46-1966)} -> 457 | K46: {=INDEX(GMWQ!$A$2:$NF$60,MATCH(1,(GMWQ!$NE$2:$NE$60=K$3)*(GMWQ!$ND$2:$ND$60=K$4)*(GMWQ!$NF$2:$NF$60=K$1),0),$F46-1966)} -> 318.782 | L46: {=INDEX(GMWQ!$A$2:$NF$60,MATCH(1,(GMWQ!$NE$2:$NE$60=L$3)*(GMWQ!$ND$2:$ND$60=L$4)*(GMWQ!$NF$2:$NF$60=L$1),0),$F46-1966)} -> 299.495 | M46: {=INDEX(GMWQ!$A$2:$NF$60,MATCH(1,(GMWQ!$NE$2:$NE$60=M$3)*(GMWQ!$ND$2:$ND$60=M$4)*(GMWQ!$NF$2:$NF$60=M$1),0),$F46-1966)} -> 220771.8 | N46: {=INDEX(GMWQ!$A$2:$NF$60,MATCH(1,(GMWQ!$NE$2:$NE$60=N$3)*(GMWQ!$ND$2:$ND$60=N$4)*(GMWQ!$NF$2:$NF$60=N$1),0),$F46-1966)} -> -1656 | ... AL46: {=INDEX(GMWQ!$A$2:$NF$60,MATCH(1,(GMWQ!$NE$2:$NE$60=AL$3)*(GMWQ!$ND$2:$ND$60=AL$4)*(GMWQ!$NF$2:$NF$60=AL$1),0),$F46-1966)} -> -6.010588
A47: 1983 | B47: =+B43+1 -> 1983 | C47: =+C43+1 -> 1982 | D47: =+D43+1 -> 1982 | F47: =+F46+1 -> 2013 | G47: {=INDEX(GMWQ!$A$2:$NF$60,MATCH(1,(GMWQ!$NE$2:$NE$60=G$3)*(GMWQ!$ND$2:$ND$60=G$4)*(GMWQ!$NF$2:$NF$60=G$1),0),$F47-1966)} -> 297563 | H47: {=INDEX(GMWQ!$A$2:$NF$60,MATCH(1,(GMWQ!$NE$2:$NE$60=H$3)*(GMWQ!$ND$2:$ND$60=H$4)*(GMWQ!$NF$2:$NF$60=H$1),0),$F47-1966)} -> 1850.025 | I47: {=INDEX(GMWQ!$A$2:$NF$60,MATCH(1,(GMWQ!$NE$2:$NE$60=I$3)*(GMWQ!$ND$2:$ND$60=I$4)*(GMWQ!$NF$2:$NF$60=I$1),0),$F47-1966)} -> 75168.8 | J47: {=INDEX(GMWQ!$A$2:$NF$60,MATCH(1,(GMWQ!$NE$2:$NE$60=J$3)*(GMWQ!$ND$2:$ND$60=J$4)*(GMWQ!$NF$2:$NF$60=J$1),0),$F47-1966)} -> 461.22 | K47: {=INDEX(GMWQ!$A$2:$NF$60,MATCH(1,(GMWQ!$NE$2:$NE$60=K$3)*(GMWQ!$ND$2:$ND$60=K$4)*(GMWQ!$NF$2:$NF$60=K$1),0),$F47-1966)} -> 320.007 | L47: {=INDEX(GMWQ!$A$2:$NF$60,MATCH(1,(GMWQ!$NE$2:$NE$60=L$3)*(GMWQ!$ND$2:$ND$60=L$4)*(GMWQ!$NF$2:$NF$60=L$1),0),$F47-1966)} -> 300.334 | M47: {=INDEX(GMWQ!$A$2:$NF$60,MATCH(1,(GMWQ!$NE$2:$NE$60=M$3)*(GMWQ!$ND$2:$ND$60=M$4)*(GMWQ!$NF$2:$NF$60=M$1),0),$F47-1966)} -> 224379.8 | N47: {=INDEX(GMWQ!$A$2:$NF$60,MATCH(1,(GMWQ!$NE$2:$NE$60=N$3)*(GMWQ!$ND$2:$ND$60=N$4)*(GMWQ!$NF$2:$NF$60=N$1),0),$F47-1966)} -> -1527 | ... AL47: {=INDEX(GMWQ!$A$2:$NF$60,MATCH(1,(GMWQ!$NE$2:$NE$60=AL$3)*(GMWQ!$ND$2:$ND$60=AL$4)*(GMWQ!$NF$2:$NF$60=AL$1),0),$F47-1966)} -> -5.73373
B48: =+B44+1 -> 1983 | C48: =+C44+1 -> 1983 | F48: =+F47+1 -> 2014 | G48: {=INDEX(GMWQ!$A$2:$NF$60,MATCH(1,(GMWQ!$NE$2:$NE$60=G$3)*(GMWQ!$ND$2:$ND$60=G$4)*(GMWQ!$NF$2:$NF$60=G$1),0),$F48-1966)} -> 299623 | H48: {=INDEX(GMWQ!$A$2:$NF$60,MATCH(1,(GMWQ!$NE$2:$NE$60=H$3)*(GMWQ!$ND$2:$ND$60=H$4)*(GMWQ!$NF$2:$NF$60=H$1),0),$F48-1966)} -> 1892.125 | I48: {=INDEX(GMWQ!$A$2:$NF$60,MATCH(1,(GMWQ!$NE$2:$NE$60=I$3)*(GMWQ!$ND$2:$ND$60=I$4)*(GMWQ!$NF$2:$NF$60=I$1),0),$F48-1966)} -> 75743.88 | J48: {=INDEX(GMWQ!$A$2:$NF$60,MATCH(1,(GMWQ!$NE$2:$NE$60=J$3)*(GMWQ!$ND$2:$ND$60=J$4)*(GMWQ!$NF$2:$NF$60=J$1),0),$F48-1966)} -> 466.02 | K48: {=INDEX(GMWQ!$A$2:$NF$60,MATCH(1,(GMWQ!$NE$2:$NE$60=K$3)*(GMWQ!$ND$2:$ND$60=K$4)*(GMWQ!$NF$2:$NF$60=K$1),0),$F48-1966)} -> 320.182 | L48: {=INDEX(GMWQ!$A$2:$NF$60,MATCH(1,(GMWQ!$NE$2:$NE$60=L$3)*(GMWQ!$ND$2:$ND$60=L$4)*(GMWQ!$NF$2:$NF$60=L$1),0),$F48-1966)} -> 299.975 | M48: {=INDEX(GMWQ!$A$2:$NF$60,MATCH(1,(GMWQ!$NE$2:$NE$60=M$3)*(GMWQ!$ND$2:$ND$60=M$4)*(GMWQ!$NF$2:$NF$60=M$1),0),$F48-1966)} -> 228806.3 | N48: {=INDEX(GMWQ!$A$2:$NF$60,MATCH(1,(GMWQ!$NE$2:$NE$60=N$3)*(GMWQ!$ND$2:$ND$60=N$4)*(GMWQ!$NF$2:$NF$60=N$1),0),$F48-1966)} -> -4050 | ... AL48: {=INDEX(GMWQ!$A$2:$NF$60,MATCH(1,(GMWQ!$NE$2:$NE$60=AL$3)*(GMWQ!$ND$2:$ND$60=AL$4)*(GMWQ!$NF$2:$NF$60=AL$1),0),$F48-1966)} -> -5.553814
B49: =+B45+1 -> 1983 | C49: =+C45+1 -> 1983 | F49: =+F48+1 -> 2015 | G49: {=INDEX(GMWQ!$A$2:$NF$60,MATCH(1,(GMWQ!$NE$2:$NE$60=G$3)*(GMWQ!$ND$2:$ND$60=G$4)*(GMWQ!$NF$2:$NF$60=G$1),0),$F49-1966)} -> 303085 | H49: {=INDEX(GMWQ!$A$2:$NF$60,MATCH(1,(GMWQ!$NE$2:$NE$60=H$3)*(GMWQ!$ND$2:$ND$60=H$4)*(GMWQ!$NF$2:$NF$60=H$1),0),$F49-1966)} -> 1929.925 | I49: {=INDEX(GMWQ!$A$2:$NF$60,MATCH(1,(GMWQ!$NE$2:$NE$60=I$3)*(GMWQ!$ND$2:$ND$60=I$4)*(GMWQ!$NF$2:$NF$60=I$1),0),$F49-1966)} -> 76764.23 | J49: {=INDEX(GMWQ!$A$2:$NF$60,MATCH(1,(GMWQ!$NE$2:$NE$60=J$3)*(GMWQ!$ND$2:$ND$60=J$4)*(GMWQ!$NF$2:$NF$60=J$1),0),$F49-1966)} -> 464.95 | K49: {=INDEX(GMWQ!$A$2:$NF$60,MATCH(1,(GMWQ!$NE$2:$NE$60=K$3)*(GMWQ!$ND$2:$ND$60=K$4)*(GMWQ!$NF$2:$NF$60=K$1),0),$F49-1966)} -> 320.696 | L49: {=INDEX(GMWQ!$A$2:$NF$60,MATCH(1,(GMWQ!$NE$2:$NE$60=L$3)*(GMWQ!$ND$2:$ND$60=L$4)*(GMWQ!$NF$2:$NF$60=L$1),0),$F49-1966)} -> 305.559 | M49: {=INDEX(GMWQ!$A$2:$NF$60,MATCH(1,(GMWQ!$NE$2:$NE$60=M$3)*(GMWQ!$ND$2:$ND$60=M$4)*(GMWQ!$NF$2:$NF$60=M$1),0),$F49-1966)} -> 231376.8 | N49: {=INDEX(GMWQ!$A$2:$NF$60,MATCH(1,(GMWQ!$NE$2:$NE$60=N$3)*(GMWQ!$ND$2:$ND$60=N$4)*(GMWQ!$NF$2:$NF$60=N$1),0),$F49-1966)} -> -4112 | ... AL49: {=INDEX(GMWQ!$A$2:$NF$60,MATCH(1,(GMWQ!$NE$2:$NE$60=AL$3)*(GMWQ!$ND$2:$ND$60=AL$4)*(GMWQ!$NF$2:$NF$60=AL$1),0),$F49-1966)} -> -5.372965
B50: =+B46+1 -> 1983 | C50: =+C46+1 -> 1983 | E50: =+E46+1 -> 1983 | F50: =+F49+1 -> 2016 | G50: {=INDEX(GMWQ!$A$2:$NF$60,MATCH(1,(GMWQ!$NE$2:$NE$60=G$3)*(GMWQ!$ND$2:$ND$60=G$4)*(GMWQ!$NF$2:$NF$60=G$1),0),$F50-1966)} -> 305361 | H50: {=INDEX(GMWQ!$A$2:$NF$60,MATCH(1,(GMWQ!$NE$2:$NE$60=H$3)*(GMWQ!$ND$2:$ND$60=H$4)*(GMWQ!$NF$2:$NF$60=H$1),0),$F50-1966)} -> 1970.2 | I50: {=INDEX(GMWQ!$A$2:$NF$60,MATCH(1,(GMWQ!$NE$2:$NE$60=I$3)*(GMWQ!$ND$2:$ND$60=I$4)*(GMWQ!$NF$2:$NF$60=I$1),0),$F50-1966)} -> 77307.77 | J50: {=INDEX(GMWQ!$A$2:$NF$60,MATCH(1,(GMWQ!$NE$2:$NE$60=J$3)*(GMWQ!$ND$2:$ND$60=J$4)*(GMWQ!$NF$2:$NF$60=J$1),0),$F50-1966)} -> 471.39 | K50: {=INDEX(GMWQ!$A$2:$NF$60,MATCH(1,(GMWQ!$NE$2:$NE$60=K$3)*(GMWQ!$ND$2:$ND$60=K$4)*(GMWQ!$NF$2:$NF$60=K$1),0),$F50-1966)} -> 322.692 | L50: {=INDEX(GMWQ!$A$2:$NF$60,MATCH(1,(GMWQ!$NE$2:$NE$60=L$3)*(GMWQ!$ND$2:$ND$60=L$4)*(GMWQ!$NF$2:$NF$60=L$1),0),$F50-1966)} -> 312.334 | M50: {=INDEX(GMWQ!$A$2:$NF$60,MATCH(1,(GMWQ!$NE$2:$NE$60=M$3)*(GMWQ!$ND$2:$ND$60=M$4)*(GMWQ!$NF$2:$NF$60=M$1),0),$F50-1966)} -> 234253.3 | N50: {=INDEX(GMWQ!$A$2:$NF$60,MATCH(1,(GMWQ!$NE$2:$NE$60=N$3)*(GMWQ!$ND$2:$ND$60=N$4)*(GMWQ!$NF$2:$NF$60=N$1),0),$F50-1966)} -> -893 | ... AL50: {=INDEX(GMWQ!$A$2:$NF$60,MATCH(1,(GMWQ!$NE$2:$NE$60=AL$3)*(GMWQ!$ND$2:$ND$60=AL$4)*(GMWQ!$NF$2:$NF$60=AL$1),0),$F50-1966)} -> -4.968634
A51: 1984 | B51: =+B47+1 -> 1984 | C51: =+C47+1 -> 1983 | D51: =+D47+1 -> 1983 | F51: =+F50+1 -> 2017 | G51: {=INDEX(GMWQ!$A$2:$NF$60,MATCH(1,(GMWQ!$NE$2:$NE$60=G$3)*(GMWQ!$ND$2:$ND$60=G$4)*(GMWQ!$NF$2:$NF$60=G$1),0),$F51-1966)} -> 307964 | H51: {=INDEX(GMWQ!$A$2:$NF$60,MATCH(1,(GMWQ!$NE$2:$NE$60=H$3)*(GMWQ!$ND$2:$ND$60=H$4)*(GMWQ!$NF$2:$NF$60=H$1),0),$F51-1966)} -> 2008.7 | I51: {=INDEX(GMWQ!$A$2:$NF$60,MATCH(1,(GMWQ!$NE$2:$NE$60=I$3)*(GMWQ!$ND$2:$ND$60=I$4)*(GMWQ!$NF$2:$NF$60=I$1),0),$F51-1966)} -> 78032.58 | J51: {=INDEX(GMWQ!$A$2:$NF$60,MATCH(1,(GMWQ!$NE$2:$NE$60=J$3)*(GMWQ!$ND$2:$ND$60=J$4)*(GMWQ!$NF$2:$NF$60=J$1),0),$F51-1966)} -> 477.6 | K51: {=INDEX(GMWQ!$A$2:$NF$60,MATCH(1,(GMWQ!$NE$2:$NE$60=K$3)*(GMWQ!$ND$2:$ND$60=K$4)*(GMWQ!$NF$2:$NF$60=K$1),0),$F51-1966)} -> 324.129 | L51: {=INDEX(GMWQ!$A$2:$NF$60,MATCH(1,(GMWQ!$NE$2:$NE$60=L$3)*(GMWQ!$ND$2:$ND$60=L$4)*(GMWQ!$NF$2:$NF$60=L$1),0),$F51-1966)} -> 311.719 | M51: {=INDEX(GMWQ!$A$2:$NF$60,MATCH(1,(GMWQ!$NE$2:$NE$60=M$3)*(GMWQ!$ND$2:$ND$60=M$4)*(GMWQ!$NF$2:$NF$60=M$1),0),$F51-1966)} -> 238310.5 | N51: {=INDEX(GMWQ!$A$2:$NF$60,MATCH(1,(GMWQ!$NE$2:$NE$60=N$3)*(GMWQ!$ND$2:$ND$60=N$4)*(GMWQ!$NF$2:$NF$60=N$1),0),$F51-1966)} -> -2747 | ... AL51: {=INDEX(GMWQ!$A$2:$NF$60,MATCH(1,(GMWQ!$NE$2:$NE$60=AL$3)*(GMWQ!$ND$2:$ND$60=AL$4)*(GMWQ!$NF$2:$NF$60=AL$1),0),$F51-1966)} -> -4.934276
B52: =+B48+1 -> 1984 | C52: =+C48+1 -> 1984 | F52: =+F51+1 -> 2018 | G52: {=INDEX(GMWQ!$A$2:$NF$60,MATCH(1,(GMWQ!$NE$2:$NE$60=G$3)*(GMWQ!$ND$2:$ND$60=G$4)*(GMWQ!$NF$2:$NF$60=G$1),0),$F52-1966)} -> 304892 | H52: {=INDEX(GMWQ!$A$2:$NF$60,MATCH(1,(GMWQ!$NE$2:$NE$60=H$3)*(GMWQ!$ND$2:$ND$60=H$4)*(GMWQ!$NF$2:$NF$60=H$1),0),$F52-1966)} -> 2043.425 | I52: {=INDEX(GMWQ!$A$2:$NF$60,MATCH(1,(GMWQ!$NE$2:$NE$60=I$3)*(GMWQ!$ND$2:$ND$60=I$4)*(GMWQ!$NF$2:$NF$60=I$1),0),$F52-1966)} -> 79658.95 | J52: {=INDEX(GMWQ!$A$2:$NF$60,MATCH(1,(GMWQ!$NE$2:$NE$60=J$3)*(GMWQ!$ND$2:$ND$60=J$4)*(GMWQ!$NF$2:$NF$60=J$1),0),$F52-1966)} -> 470.16 | K52: {=INDEX(GMWQ!$A$2:$NF$60,MATCH(1,(GMWQ!$NE$2:$NE$60=K$3)*(GMWQ!$ND$2:$ND$60=K$4)*(GMWQ!$NF$2:$NF$60=K$1),0),$F52-1966)} -> 325.672 | L52: {=INDEX(GMWQ!$A$2:$NF$60,MATCH(1,(GMWQ!$NE$2:$NE$60=L$3)*(GMWQ!$ND$2:$ND$60=L$4)*(GMWQ!$NF$2:$NF$60=L$1),0),$F52-1966)} -> 312.725 | M52: {=INDEX(GMWQ!$A$2:$NF$60,MATCH(1,(GMWQ!$NE$2:$NE$60=M$3)*(GMWQ!$ND$2:$ND$60=M$4)*(GMWQ!$NF$2:$NF$60=M$1),0),$F52-1966)} -> 242935.3 | N52: {=INDEX(GMWQ!$A$2:$NF$60,MATCH(1,(GMWQ!$NE$2:$NE$60=N$3)*(GMWQ!$ND$2:$ND$60=N$4)*(GMWQ!$NF$2:$NF$60=N$1),0),$F52-1966)} -> -4927 | ... AL52: {=INDEX(GMWQ!$A$2:$NF$60,MATCH(1,(GMWQ!$NE$2:$NE$60=AL$3)*(GMWQ!$ND$2:$ND$60=AL$4)*(GMWQ!$NF$2:$NF$60=AL$1),0),$F52-1966)} -> -4.913958
B53: =+B49+1 -> 1984 | C53: =+C49+1 -> 1984 | F53: =+F52+1 -> 2019 | G53: {=INDEX(GMWQ!$A$2:$NF$60,MATCH(1,(GMWQ!$NE$2:$NE$60=G$3)*(GMWQ!$ND$2:$ND$60=G$4)*(GMWQ!$NF$2:$NF$60=G$1),0),$F53-1966)} -> 307122 | H53: {=INDEX(GMWQ!$A$2:$NF$60,MATCH(1,(GMWQ!$NE$2:$NE$60=H$3)*(GMWQ!$ND$2:$ND$60=H$4)*(GMWQ!$NF$2:$NF$60=H$1),0),$F53-1966)} -> 2063.125 | I53: {=INDEX(GMWQ!$A$2:$NF$60,MATCH(1,(GMWQ!$NE$2:$NE$60=I$3)*(GMWQ!$ND$2:$ND$60=I$4)*(GMWQ!$NF$2:$NF$60=I$1),0),$F53-1966)} -> 80246.33 | J53: {=INDEX(GMWQ!$A$2:$NF$60,MATCH(1,(GMWQ!$NE$2:$NE$60=J$3)*(GMWQ!$ND$2:$ND$60=J$4)*(GMWQ!$NF$2:$NF$60=J$1),0),$F53-1966)} -> 482.9 | K53: {=INDEX(GMWQ!$A$2:$NF$60,MATCH(1,(GMWQ!$NE$2:$NE$60=K$3)*(GMWQ!$ND$2:$ND$60=K$4)*(GMWQ!$NF$2:$NF$60=K$1),0),$F53-1966)} -> 327.777 | L53: {=INDEX(GMWQ!$A$2:$NF$60,MATCH(1,(GMWQ!$NE$2:$NE$60=L$3)*(GMWQ!$ND$2:$ND$60=L$4)*(GMWQ!$NF$2:$NF$60=L$1),0),$F53-1966)} -> 316.407 | M53: {=INDEX(GMWQ!$A$2:$NF$60,MATCH(1,(GMWQ!$NE$2:$NE$60=M$3)*(GMWQ!$ND$2:$ND$60=M$4)*(GMWQ!$NF$2:$NF$60=M$1),0),$F53-1966)} -> 243979.8 | N53: {=INDEX(GMWQ!$A$2:$NF$60,MATCH(1,(GMWQ!$NE$2:$NE$60=N$3)*(GMWQ!$ND$2:$ND$60=N$4)*(GMWQ!$NF$2:$NF$60=N$1),0),$F53-1966)} -> -2934 | ... AL53: {=INDEX(GMWQ!$A$2:$NF$60,MATCH(1,(GMWQ!$NE$2:$NE$60=AL$3)*(GMWQ!$ND$2:$ND$60=AL$4)*(GMWQ!$NF$2:$NF$60=AL$1),0),$F53-1966)} -> -4.905092
B54: =+B50+1 -> 1984 | C54: =+C50+1 -> 1984 | E54: =+E50+1 -> 1984 | F54: =+F53+1 -> 2020 | G54: {=INDEX(GMWQ!$A$2:$NF$60,MATCH(1,(GMWQ!$NE$2:$NE$60=G$3)*(GMWQ!$ND$2:$ND$60=G$4)*(GMWQ!$NF$2:$NF$60=G$1),0),$F54-1966)} -> 312697 | H54: {=INDEX(GMWQ!$A$2:$NF$60,MATCH(1,(GMWQ!$NE$2:$NE$60=H$3)*(GMWQ!$ND$2:$ND$60=H$4)*(GMWQ!$NF$2:$NF$60=H$1),0),$F54-1966)} -> 2080.05 | I54: {=INDEX(GMWQ!$A$2:$NF$60,MATCH(1,(GMWQ!$NE$2:$NE$60=I$3)*(GMWQ!$ND$2:$ND$60=I$4)*(GMWQ!$NF$2:$NF$60=I$1),0),$F54-1966)} -> 80542.25 | J54: {=INDEX(GMWQ!$A$2:$NF$60,MATCH(1,(GMWQ!$NE$2:$NE$60=J$3)*(GMWQ!$ND$2:$ND$60=J$4)*(GMWQ!$NF$2:$NF$60=J$1),0),$F54-1966)} -> 486.95 | K54: {=INDEX(GMWQ!$A$2:$NF$60,MATCH(1,(GMWQ!$NE$2:$NE$60=K$3)*(GMWQ!$ND$2:$ND$60=K$4)*(GMWQ!$NF$2:$NF$60=K$1),0),$F54-1966)} -> 327.475 | L54: {=INDEX(GMWQ!$A$2:$NF$60,MATCH(1,(GMWQ!$NE$2:$NE$60=L$3)*(GMWQ!$ND$2:$ND$60=L$4)*(GMWQ!$NF$2:$NF$60=L$1),0),$F54-1966)} -> 316.458 | M54: {=INDEX(GMWQ!$A$2:$NF$60,MATCH(1,(GMWQ!$NE$2:$NE$60=M$3)*(GMWQ!$ND$2:$ND$60=M$4)*(GMWQ!$NF$2:$NF$60=M$1),0),$F54-1966)} -> 247787.5 | N54: {=INDEX(GMWQ!$A$2:$NF$60,MATCH(1,(GMWQ!$NE$2:$NE$60=N$3)*(GMWQ!$ND$2:$ND$60=N$4)*(GMWQ!$NF$2:$NF$60=N$1),0),$F54-1966)} -> -1815 | ... AL54: {=INDEX(GMWQ!$A$2:$NF$60,MATCH(1,(GMWQ!$NE$2:$NE$60=AL$3)*(GMWQ!$ND$2:$ND$60=AL$4)*(GMWQ!$NF$2:$NF$60=AL$1),0),$F54-1966)} -> -4.924763
A55: 1985 | B55: =+B51+1 -> 1985 | C55: =+C51+1 -> 1984 | D55: =+D51+1 -> 1984 | F55: =+F54+1 -> 2021 | G55: {=INDEX(GMWQ!$A$2:$NF$60,MATCH(1,(GMWQ!$NE$2:$NE$60=G$3)*(GMWQ!$ND$2:$ND$60=G$4)*(GMWQ!$NF$2:$NF$60=G$1),0),$F55-1966)} -> 315753 | H55: {=INDEX(GMWQ!$A$2:$NF$60,MATCH(1,(GMWQ!$NE$2:$NE$60=H$3)*(GMWQ!$ND$2:$ND$60=H$4)*(GMWQ!$NF$2:$NF$60=H$1),0),$F55-1966)} -> 2100.2 | I55: {=INDEX(GMWQ!$A$2:$NF$60,MATCH(1,(GMWQ!$NE$2:$NE$60=I$3)*(GMWQ!$ND$2:$ND$60=I$4)*(GMWQ!$NF$2:$NF$60=I$1),0),$F55-1966)} -> 81627.42 | J55: {=INDEX(GMWQ!$A$2:$NF$60,MATCH(1,(GMWQ!$NE$2:$NE$60=J$3)*(GMWQ!$ND$2:$ND$60=J$4)*(GMWQ!$NF$2:$NF$60=J$1),0),$F55-1966)} -> 484.39 | K55: {=INDEX(GMWQ!$A$2:$NF$60,MATCH(1,(GMWQ!$NE$2:$NE$60=K$3)*(GMWQ!$ND$2:$ND$60=K$4)*(GMWQ!$NF$2:$NF$60=K$1),0),$F55-1966)} -> 328.296 | L55: {=INDEX(GMWQ!$A$2:$NF$60,MATCH(1,(GMWQ!$NE$2:$NE$60=L$3)*(GMWQ!$ND$2:$ND$60=L$4)*(GMWQ!$NF$2:$NF$60=L$1),0),$F55-1966)} -> 318.265 | M55: {=INDEX(GMWQ!$A$2:$NF$60,MATCH(1,(GMWQ!$NE$2:$NE$60=M$3)*(GMWQ!$ND$2:$ND$60=M$4)*(GMWQ!$NF$2:$NF$60=M$1),0),$F55-1966)} -> 251594.5 | N55: {=INDEX(GMWQ!$A$2:$NF$60,MATCH(1,(GMWQ!$NE$2:$NE$60=N$3)*(GMWQ!$ND$2:$ND$60=N$4)*(GMWQ!$NF$2:$NF$60=N$1),0),$F55-1966)} -> -2859 | ... AL55: {=INDEX(GMWQ!$A$2:$NF$60,MATCH(1,(GMWQ!$NE$2:$NE$60=AL$3)*(GMWQ!$ND$2:$ND$60=AL$4)*(GMWQ!$NF$2:$NF$60=AL$1),0),$F55-1966)} -> -4.955983
B56: =+B52+1 -> 1985 | C56: =+C52+1 -> 1985 | F56: =+F55+1 -> 2022 | G56: {=INDEX(GMWQ!$A$2:$NF$60,MATCH(1,(GMWQ!$NE$2:$NE$60=G$3)*(GMWQ!$ND$2:$ND$60=G$4)*(GMWQ!$NF$2:$NF$60=G$1),0),$F56-1966)} -> 322451 | H56: {=INDEX(GMWQ!$A$2:$NF$60,MATCH(1,(GMWQ!$NE$2:$NE$60=H$3)*(GMWQ!$ND$2:$ND$60=H$4)*(GMWQ!$NF$2:$NF$60=H$1),0),$F56-1966)} -> 2118.7 | I56: {=INDEX(GMWQ!$A$2:$NF$60,MATCH(1,(GMWQ!$NE$2:$NE$60=I$3)*(GMWQ!$ND$2:$ND$60=I$4)*(GMWQ!$NF$2:$NF$60=I$1),0),$F56-1966)} -> 83146.85 | J56: {=INDEX(GMWQ!$A$2:$NF$60,MATCH(1,(GMWQ!$NE$2:$NE$60=J$3)*(GMWQ!$ND$2:$ND$60=J$4)*(GMWQ!$NF$2:$NF$60=J$1),0),$F56-1966)} -> 489.11 | K56: {=INDEX(GMWQ!$A$2:$NF$60,MATCH(1,(GMWQ!$NE$2:$NE$60=K$3)*(GMWQ!$ND$2:$ND$60=K$4)*(GMWQ!$NF$2:$NF$60=K$1),0),$F56-1966)} -> 331.027 | L56: {=INDEX(GMWQ!$A$2:$NF$60,MATCH(1,(GMWQ!$NE$2:$NE$60=L$3)*(GMWQ!$ND$2:$ND$60=L$4)*(GMWQ!$NF$2:$NF$60=L$1),0),$F56-1966)} -> 322.471 | M56: {=INDEX(GMWQ!$A$2:$NF$60,MATCH(1,(GMWQ!$NE$2:$NE$60=M$3)*(GMWQ!$ND$2:$ND$60=M$4)*(GMWQ!$NF$2:$NF$60=M$1),0),$F56-1966)} -> 252403.8 | N56: {=INDEX(GMWQ!$A$2:$NF$60,MATCH(1,(GMWQ!$NE$2:$NE$60=N$3)*(GMWQ!$ND$2:$ND$60=N$4)*(GMWQ!$NF$2:$NF$60=N$1),0),$F56-1966)} -> -4910 | ... AL56: {=INDEX(GMWQ!$A$2:$NF$60,MATCH(1,(GMWQ!$NE$2:$NE$60=AL$3)*(GMWQ!$ND$2:$ND$60=AL$4)*(GMWQ!$NF$2:$NF$60=AL$1),0),$F56-1966)} -> -4.999279
B57: =+B53+1 -> 1985 | C57: =+C53+1 -> 1985 | F57: =+F56+1 -> 2023 | G57: {=INDEX(GMWQ!$A$2:$NF$60,MATCH(1,(GMWQ!$NE$2:$NE$60=G$3)*(GMWQ!$ND$2:$ND$60=G$4)*(GMWQ!$NF$2:$NF$60=G$1),0),$F57-1966)} -> 322392 | H57: {=INDEX(GMWQ!$A$2:$NF$60,MATCH(1,(GMWQ!$NE$2:$NE$60=H$3)*(GMWQ!$ND$2:$ND$60=H$4)*(GMWQ!$NF$2:$NF$60=H$1),0),$F57-1966)} -> 2151.05 | I57: {=INDEX(GMWQ!$A$2:$NF$60,MATCH(1,(GMWQ!$NE$2:$NE$60=I$3)*(GMWQ!$ND$2:$ND$60=I$4)*(GMWQ!$NF$2:$NF$60=I$1),0),$F57-1966)} -> 84384.77 | J57: {=INDEX(GMWQ!$A$2:$NF$60,MATCH(1,(GMWQ!$NE$2:$NE$60=J$3)*(GMWQ!$ND$2:$ND$60=J$4)*(GMWQ!$NF$2:$NF$60=J$1),0),$F57-1966)} -> 495.57 | K57: {=INDEX(GMWQ!$A$2:$NF$60,MATCH(1,(GMWQ!$NE$2:$NE$60=K$3)*(GMWQ!$ND$2:$ND$60=K$4)*(GMWQ!$NF$2:$NF$60=K$1),0),$F57-1966)} -> 332.921 | L57: {=INDEX(GMWQ!$A$2:$NF$60,MATCH(1,(GMWQ!$NE$2:$NE$60=L$3)*(GMWQ!$ND$2:$ND$60=L$4)*(GMWQ!$NF$2:$NF$60=L$1),0),$F57-1966)} -> 325.052 | M57: {=INDEX(GMWQ!$A$2:$NF$60,MATCH(1,(GMWQ!$NE$2:$NE$60=M$3)*(GMWQ!$ND$2:$ND$60=M$4)*(GMWQ!$NF$2:$NF$60=M$1),0),$F57-1966)} -> 255608 | N57: {=INDEX(GMWQ!$A$2:$NF$60,MATCH(1,(GMWQ!$NE$2:$NE$60=N$3)*(GMWQ!$ND$2:$ND$60=N$4)*(GMWQ!$NF$2:$NF$60=N$1),0),$F57-1966)} -> -1575 | ... AL57: {=INDEX(GMWQ!$A$2:$NF$60,MATCH(1,(GMWQ!$NE$2:$NE$60=AL$3)*(GMWQ!$ND$2:$ND$60=AL$4)*(GMWQ!$NF$2:$NF$60=AL$1),0),$F57-1966)} -> -5.105565
B58: =+B54+1 -> 1985 | C58: =+C54+1 -> 1985 | E58: =+E54+1 -> 1985 | F58: =+F57+1 -> 2024 | G58: {=INDEX(GMWQ!$A$2:$NF$60,MATCH(1,(GMWQ!$NE$2:$NE$60=G$3)*(GMWQ!$ND$2:$ND$60=G$4)*(GMWQ!$NF$2:$NF$60=G$1),0),$F58-1966)} -> 322604 | H58: {=INDEX(GMWQ!$A$2:$NF$60,MATCH(1,(GMWQ!$NE$2:$NE$60=H$3)*(GMWQ!$ND$2:$ND$60=H$4)*(GMWQ!$NF$2:$NF$60=H$1),0),$F58-1966)} -> 2167.05 | I58: {=INDEX(GMWQ!$A$2:$NF$60,MATCH(1,(GMWQ!$NE$2:$NE$60=I$3)*(GMWQ!$ND$2:$ND$60=I$4)*(GMWQ!$NF$2:$NF$60=I$1),0),$F58-1966)} -> 85720.3 | J58: {=INDEX(GMWQ!$A$2:$NF$60,MATCH(1,(GMWQ!$NE$2:$NE$60=J$3)*(GMWQ!$ND$2:$ND$60=J$4)*(GMWQ!$NF$2:$NF$60=J$1),0),$F58-1966)} -> 498.46 | K58: {=INDEX(GMWQ!$A$2:$NF$60,MATCH(1,(GMWQ!$NE$2:$NE$60=K$3)*(GMWQ!$ND$2:$ND$60=K$4)*(GMWQ!$NF$2:$NF$60=K$1),0),$F58-1966)} -> 334.602 | L58: {=INDEX(GMWQ!$A$2:$NF$60,MATCH(1,(GMWQ!$NE$2:$NE$60=L$3)*(GMWQ!$ND$2:$ND$60=L$4)*(GMWQ!$NF$2:$NF$60=L$1),0),$F58-1966)} -> 327.22 | M58: {=INDEX(GMWQ!$A$2:$NF$60,MATCH(1,(GMWQ!$NE$2:$NE$60=M$3)*(GMWQ!$ND$2:$ND$60=M$4)*(GMWQ!$NF$2:$NF$60=M$1),0),$F58-1966)} -> 259505 | N58: {=INDEX(GMWQ!$A$2:$NF$60,MATCH(1,(GMWQ!$NE$2:$NE$60=N$3)*(GMWQ!$ND$2:$ND$60=N$4)*(GMWQ!$NF$2:$NF$60=N$1),0),$F58-1966)} -> -1219 | ... AL58: {=INDEX(GMWQ!$A$2:$NF$60,MATCH(1,(GMWQ!$NE$2:$NE$60=AL$3)*(GMWQ!$ND$2:$ND$60=AL$4)*(GMWQ!$NF$2:$NF$60=AL$1),0),$F58-1966)} -> -5.154252
A59: 1986 | B59: =+B55+1 -> 1986 | C59: =+C55+1 -> 1985 | D59: =+D55+1 -> 1985 | F59: =+F58+1 -> 2025 | G59: {=INDEX(GMWQ!$A$2:$NF$60,MATCH(1,(GMWQ!$NE$2:$NE$60=G$3)*(GMWQ!$ND$2:$ND$60=G$4)*(GMWQ!$NF$2:$NF$60=G$1),0),$F59-1966)} -> 325968 | H59: {=INDEX(GMWQ!$A$2:$NF$60,MATCH(1,(GMWQ!$NE$2:$NE$60=H$3)*(GMWQ!$ND$2:$ND$60=H$4)*(GMWQ!$NF$2:$NF$60=H$1),0),$F59-1966)} -> 2187.275 | I59: {=INDEX(GMWQ!$A$2:$NF$60,MATCH(1,(GMWQ!$NE$2:$NE$60=I$3)*(GMWQ!$ND$2:$ND$60=I$4)*(GMWQ!$NF$2:$NF$60=I$1),0),$F59-1966)} -> 85758.42 | J59: {=INDEX(GMWQ!$A$2:$NF$60,MATCH(1,(GMWQ!$NE$2:$NE$60=J$3)*(GMWQ!$ND$2:$ND$60=J$4)*(GMWQ!$NF$2:$NF$60=J$1),0),$F59-1966)} -> 495.73 | K59: {=INDEX(GMWQ!$A$2:$NF$60,MATCH(1,(GMWQ!$NE$2:$NE$60=K$3)*(GMWQ!$ND$2:$ND$60=K$4)*(GMWQ!$NF$2:$NF$60=K$1),0),$F59-1966)} -> 335.636 | L59: {=INDEX(GMWQ!$A$2:$NF$60,MATCH(1,(GMWQ!$NE$2:$NE$60=L$3)*(GMWQ!$ND$2:$ND$60=L$4)*(GMWQ!$NF$2:$NF$60=L$1),0),$F59-1966)} -> 329.26 | M59: {=INDEX(GMWQ!$A$2:$NF$60,MATCH(1,(GMWQ!$NE$2:$NE$60=M$3)*(GMWQ!$ND$2:$ND$60=M$4)*(GMWQ!$NF$2:$NF$60=M$1),0),$F59-1966)} -> 259373.5 | N59: {=INDEX(GMWQ!$A$2:$NF$60,MATCH(1,(GMWQ!$NE$2:$NE$60=N$3)*(GMWQ!$ND$2:$ND$60=N$4)*(GMWQ!$NF$2:$NF$60=N$1),0),$F59-1966)} -> -1330 | ... AL59: {=INDEX(GMWQ!$A$2:$NF$60,MATCH(1,(GMWQ!$NE$2:$NE$60=AL$3)*(GMWQ!$ND$2:$ND$60=AL$4)*(GMWQ!$NF$2:$NF$60=AL$1),0),$F59-1966)} -> -4.900334
B60: =+B56+1 -> 1986 | C60: =+C56+1 -> 1986 | F60: =+F59+1 -> 2026 | G60: {=INDEX(GMWQ!$A$2:$NF$60,MATCH(1,(GMWQ!$NE$2:$NE$60=G$3)*(GMWQ!$ND$2:$ND$60=G$4)*(GMWQ!$NF$2:$NF$60=G$1),0),$F60-1966)} -> 328872 | H60: {=INDEX(GMWQ!$A$2:$NF$60,MATCH(1,(GMWQ!$NE$2:$NE$60=H$3)*(GMWQ!$ND$2:$ND$60=H$4)*(GMWQ!$NF$2:$NF$60=H$1),0),$F60-1966)} -> 2197.125 | I60: {=INDEX(GMWQ!$A$2:$NF$60,MATCH(1,(GMWQ!$NE$2:$NE$60=I$3)*(GMWQ!$ND$2:$ND$60=I$4)*(GMWQ!$NF$2:$NF$60=I$1),0),$F60-1966)} -> 86018.4 | J60: {=INDEX(GMWQ!$A$2:$NF$60,MATCH(1,(GMWQ!$NE$2:$NE$60=J$3)*(GMWQ!$ND$2:$ND$60=J$4)*(GMWQ!$NF$2:$NF$60=J$1),0),$F60-1966)} -> 501.44 | K60: {=INDEX(GMWQ!$A$2:$NF$60,MATCH(1,(GMWQ!$NE$2:$NE$60=K$3)*(GMWQ!$ND$2:$ND$60=K$4)*(GMWQ!$NF$2:$NF$60=K$1),0),$F60-1966)} -> 339.318 | L60: {=INDEX(GMWQ!$A$2:$NF$60,MATCH(1,(GMWQ!$NE$2:$NE$60=L$3)*(GMWQ!$ND$2:$ND$60=L$4)*(GMWQ!$NF$2:$NF$60=L$1),0),$F60-1966)} -> 331.389 | M60: {=INDEX(GMWQ!$A$2:$NF$60,MATCH(1,(GMWQ!$NE$2:$NE$60=M$3)*(GMWQ!$ND$2:$ND$60=M$4)*(GMWQ!$NF$2:$NF$60=M$1),0),$F60-1966)} -> 260864.3 | N60: {=INDEX(GMWQ!$A$2:$NF$60,MATCH(1,(GMWQ!$NE$2:$NE$60=N$3)*(GMWQ!$ND$2:$ND$60=N$4)*(GMWQ!$NF$2:$NF$60=N$1),0),$F60-1966)} -> -3563 | ... AL60: {=INDEX(GMWQ!$A$2:$NF$60,MATCH(1,(GMWQ!$NE$2:$NE$60=AL$3)*(GMWQ!$ND$2:$ND$60=AL$4)*(GMWQ!$NF$2:$NF$60=AL$1),0),$F60-1966)} -> -4.378255
B61: =+B57+1 -> 1986 | C61: =+C57+1 -> 1986 | F61: =+F60+1 -> 2027 | G61: {=INDEX(GMWQ!$A$2:$NF$60,MATCH(1,(GMWQ!$NE$2:$NE$60=G$3)*(GMWQ!$ND$2:$ND$60=G$4)*(GMWQ!$NF$2:$NF$60=G$1),0),$F61-1966)} -> 330966 | H61: {=INDEX(GMWQ!$A$2:$NF$60,MATCH(1,(GMWQ!$NE$2:$NE$60=H$3)*(GMWQ!$ND$2:$ND$60=H$4)*(GMWQ!$NF$2:$NF$60=H$1),0),$F61-1966)} -> 2218.15 | I61: {=INDEX(GMWQ!$A$2:$NF$60,MATCH(1,(GMWQ!$NE$2:$NE$60=I$3)*(GMWQ!$ND$2:$ND$60=I$4)*(GMWQ!$NF$2:$NF$60=I$1),0),$F61-1966)} -> 86623.83 | J61: {=INDEX(GMWQ!$A$2:$NF$60,MATCH(1,(GMWQ!$NE$2:$NE$60=J$3)*(GMWQ!$ND$2:$ND$60=J$4)*(GMWQ!$NF$2:$NF$60=J$1),0),$F61-1966)} -> 505.16 | K61: {=INDEX(GMWQ!$A$2:$NF$60,MATCH(1,(GMWQ!$NE$2:$NE$60=K$3)*(GMWQ!$ND$2:$ND$60=K$4)*(GMWQ!$NF$2:$NF$60=K$1),0),$F61-1966)} -> 341.16 | L61: {=INDEX(GMWQ!$A$2:$NF$60,MATCH(1,(GMWQ!$NE$2:$NE$60=L$3)*(GMWQ!$ND$2:$ND$60=L$4)*(GMWQ!$NF$2:$NF$60=L$1),0),$F61-1966)} -> 334.698 | M61: {=INDEX(GMWQ!$A$2:$NF$60,MATCH(1,(GMWQ!$NE$2:$NE$60=M$3)*(GMWQ!$ND$2:$ND$60=M$4)*(GMWQ!$NF$2:$NF$60=M$1),0),$F61-1966)} -> 261192.3 | N61: {=INDEX(GMWQ!$A$2:$NF$60,MATCH(1,(GMWQ!$NE$2:$NE$60=N$3)*(GMWQ!$ND$2:$ND$60=N$4)*(GMWQ!$NF$2:$NF$60=N$1),0),$F61-1966)} -> -3984 | ... AL61: {=INDEX(GMWQ!$A$2:$NF$60,MATCH(1,(GMWQ!$NE$2:$NE$60=AL$3)*(GMWQ!$ND$2:$ND$60=AL$4)*(GMWQ!$NF$2:$NF$60=AL$1),0),$F61-1966)} -> 0.9490862
B62: =+B58+1 -> 1986 | C62: =+C58+1 -> 1986 | E62: =+E58+1 -> 1986 | F62: =+F61+1 -> 2028 | G62: {=INDEX(GMWQ!$A$2:$NF$60,MATCH(1,(GMWQ!$NE$2:$NE$60=G$3)*(GMWQ!$ND$2:$ND$60=G$4)*(GMWQ!$NF$2:$NF$60=G$1),0),$F62-1966)} -> 337367 | H62: {=INDEX(GMWQ!$A$2:$NF$60,MATCH(1,(GMWQ!$NE$2:$NE$60=H$3)*(GMWQ!$ND$2:$ND$60=H$4)*(GMWQ!$NF$2:$NF$60=H$1),0),$F62-1966)} -> 2230.05 | I62: {=INDEX(GMWQ!$A$2:$NF$60,MATCH(1,(GMWQ!$NE$2:$NE$60=I$3)*(GMWQ!$ND$2:$ND$60=I$4)*(GMWQ!$NF$2:$NF$60=I$1),0),$F62-1966)} -> 87631.63 | J62: {=INDEX(GMWQ!$A$2:$NF$60,MATCH(1,(GMWQ!$NE$2:$NE$60=J$3)*(GMWQ!$ND$2:$ND$60=J$4)*(GMWQ!$NF$2:$NF$60=J$1),0),$F62-1966)} -> 510.13 | K62: {=INDEX(GMWQ!$A$2:$NF$60,MATCH(1,(GMWQ!$NE$2:$NE$60=K$3)*(GMWQ!$ND$2:$ND$60=K$4)*(GMWQ!$NF$2:$NF$60=K$1),0),$F62-1966)} -> 341.586 | L62: {=INDEX(GMWQ!$A$2:$NF$60,MATCH(1,(GMWQ!$NE$2:$NE$60=L$3)*(GMWQ!$ND$2:$ND$60=L$4)*(GMWQ!$NF$2:$NF$60=L$1),0),$F62-1966)} -> 336.071 | M62: {=INDEX(GMWQ!$A$2:$NF$60,MATCH(1,(GMWQ!$NE$2:$NE$60=M$3)*(GMWQ!$ND$2:$ND$60=M$4)*(GMWQ!$NF$2:$NF$60=M$1),0),$F62-1966)} -> 259301.5 | N62: {=INDEX(GMWQ!$A$2:$NF$60,MATCH(1,(GMWQ!$NE$2:$NE$60=N$3)*(GMWQ!$ND$2:$ND$60=N$4)*(GMWQ!$NF$2:$NF$60=N$1),0),$F62-1966)} -> -338 | ... AL62: {=INDEX(GMWQ!$A$2:$NF$60,MATCH(1,(GMWQ!$NE$2:$NE$60=AL$3)*(GMWQ!$ND$2:$ND$60=AL$4)*(GMWQ!$NF$2:$NF$60=AL$1),0),$F62-1966)} -> 1.545274
A63: 1987 | B63: =+B59+1 -> 1987 | C63: =+C59+1 -> 1986 | D63: =+D59+1 -> 1986 | F63: =+F62+1 -> 2029 | G63: {=INDEX(GMWQ!$A$2:$NF$60,MATCH(1,(GMWQ!$NE$2:$NE$60=G$3)*(GMWQ!$ND$2:$ND$60=G$4)*(GMWQ!$NF$2:$NF$60=G$1),0),$F63-1966)} -> 339754 | H63: {=INDEX(GMWQ!$A$2:$NF$60,MATCH(1,(GMWQ!$NE$2:$NE$60=H$3)*(GMWQ!$ND$2:$ND$60=H$4)*(GMWQ!$NF$2:$NF$60=H$1),0),$F63-1966)} -> 2246.6 | I63: {=INDEX(GMWQ!$A$2:$NF$60,MATCH(1,(GMWQ!$NE$2:$NE$60=I$3)*(GMWQ!$ND$2:$ND$60=I$4)*(GMWQ!$NF$2:$NF$60=I$1),0),$F63-1966)} -> 87931.4 | J63: {=INDEX(GMWQ!$A$2:$NF$60,MATCH(1,(GMWQ!$NE$2:$NE$60=J$3)*(GMWQ!$ND$2:$ND$60=J$4)*(GMWQ!$NF$2:$NF$60=J$1),0),$F63-1966)} -> 497.3 | K63: {=INDEX(GMWQ!$A$2:$NF$60,MATCH(1,(GMWQ!$NE$2:$NE$60=K$3)*(GMWQ!$ND$2:$ND$60=K$4)*(GMWQ!$NF$2:$NF$60=K$1),0),$F63-1966)} -> 341.867 | L63: {=INDEX(GMWQ!$A$2:$NF$60,MATCH(1,(GMWQ!$NE$2:$NE$60=L$3)*(GMWQ!$ND$2:$ND$60=L$4)*(GMWQ!$NF$2:$NF$60=L$1),0),$F63-1966)} -> 337.449 | M63: {=INDEX(GMWQ!$A$2:$NF$60,MATCH(1,(GMWQ!$NE$2:$NE$60=M$3)*(GMWQ!$ND$2:$ND$60=M$4)*(GMWQ!$NF$2:$NF$60=M$1),0),$F63-1966)} -> 265295 | N63: {=INDEX(GMWQ!$A$2:$NF$60,MATCH(1,(GMWQ!$NE$2:$NE$60=N$3)*(GMWQ!$ND$2:$ND$60=N$4)*(GMWQ!$NF$2:$NF$60=N$1),0),$F63-1966)} -> -855 | ... AL63: {=INDEX(GMWQ!$A$2:$NF$60,MATCH(1,(GMWQ!$NE$2:$NE$60=AL$3)*(GMWQ!$ND$2:$ND$60=AL$4)*(GMWQ!$NF$2:$NF$60=AL$1),0),$F63-1966)} -> 1.211997
B64: =+B60+1 -> 1987 | C64: =+C60+1 -> 1987 | F64: =+F63+1 -> 2030 | G64: {=INDEX(GMWQ!$A$2:$NF$60,MATCH(1,(GMWQ!$NE$2:$NE$60=G$3)*(GMWQ!$ND$2:$ND$60=G$4)*(GMWQ!$NF$2:$NF$60=G$1),0),$F64-1966)} -> 344795 | H64: {=INDEX(GMWQ!$A$2:$NF$60,MATCH(1,(GMWQ!$NE$2:$NE$60=H$3)*(GMWQ!$ND$2:$ND$60=H$4)*(GMWQ!$NF$2:$NF$60=H$1),0),$F64-1966)} -> 2270.825 | I64: {=INDEX(GMWQ!$A$2:$NF$60,MATCH(1,(GMWQ!$NE$2:$NE$60=I$3)*(GMWQ!$ND$2:$ND$60=I$4)*(GMWQ!$NF$2:$NF$60=I$1),0),$F64-1966)} -> 89458.15 | J64: {=INDEX(GMWQ!$A$2:$NF$60,MATCH(1,(GMWQ!$NE$2:$NE$60=J$3)*(GMWQ!$ND$2:$ND$60=J$4)*(GMWQ!$NF$2:$NF$60=J$1),0),$F64-1966)} -> 508.47 | K64: {=INDEX(GMWQ!$A$2:$NF$60,MATCH(1,(GMWQ!$NE$2:$NE$60=K$3)*(GMWQ!$ND$2:$ND$60=K$4)*(GMWQ!$NF$2:$NF$60=K$1),0),$F64-1966)} -> 346.957 | L64: {=INDEX(GMWQ!$A$2:$NF$60,MATCH(1,(GMWQ!$NE$2:$NE$60=L$3)*(GMWQ!$ND$2:$ND$60=L$4)*(GMWQ!$NF$2:$NF$60=L$1),0),$F64-1966)} -> 342.558 | M64: {=INDEX(GMWQ!$A$2:$NF$60,MATCH(1,(GMWQ!$NE$2:$NE$60=M$3)*(GMWQ!$ND$2:$ND$60=M$4)*(GMWQ!$NF$2:$NF$60=M$1),0),$F64-1966)} -> 268693.5 | N64: {=INDEX(GMWQ!$A$2:$NF$60,MATCH(1,(GMWQ!$NE$2:$NE$60=N$3)*(GMWQ!$ND$2:$ND$60=N$4)*(GMWQ!$NF$2:$NF$60=N$1),0),$F64-1966)} -> -4353 | ... AL64: {=INDEX(GMWQ!$A$2:$NF$60,MATCH(1,(GMWQ!$NE$2:$NE$60=AL$3)*(GMWQ!$ND$2:$ND$60=AL$4)*(GMWQ!$NF$2:$NF$60=AL$1),0),$F64-1966)} -> 0.570601
B65: =+B61+1 -> 1987 | C65: =+C61+1 -> 1987 | F65: =+F64+1 -> 2031 | G65: {=INDEX(GMWQ!$A$2:$NF$60,MATCH(1,(GMWQ!$NE$2:$NE$60=G$3)*(GMWQ!$ND$2:$ND$60=G$4)*(GMWQ!$NF$2:$NF$60=G$1),0),$F65-1966)} -> 353365 | H65: {=INDEX(GMWQ!$A$2:$NF$60,MATCH(1,(GMWQ!$NE$2:$NE$60=H$3)*(GMWQ!$ND$2:$ND$60=H$4)*(GMWQ!$NF$2:$NF$60=H$1),0),$F65-1966)} -> 2290.5 | I65: {=INDEX(GMWQ!$A$2:$NF$60,MATCH(1,(GMWQ!$NE$2:$NE$60=I$3)*(GMWQ!$ND$2:$ND$60=I$4)*(GMWQ!$NF$2:$NF$60=I$1),0),$F65-1966)} -> 91089.55 | J65: {=INDEX(GMWQ!$A$2:$NF$60,MATCH(1,(GMWQ!$NE$2:$NE$60=J$3)*(GMWQ!$ND$2:$ND$60=J$4)*(GMWQ!$NF$2:$NF$60=J$1),0),$F65-1966)} -> 512.03 | K65: {=INDEX(GMWQ!$A$2:$NF$60,MATCH(1,(GMWQ!$NE$2:$NE$60=K$3)*(GMWQ!$ND$2:$ND$60=K$4)*(GMWQ!$NF$2:$NF$60=K$1),0),$F65-1966)} -> 349.29 | L65: {=INDEX(GMWQ!$A$2:$NF$60,MATCH(1,(GMWQ!$NE$2:$NE$60=L$3)*(GMWQ!$ND$2:$ND$60=L$4)*(GMWQ!$NF$2:$NF$60=L$1),0),$F65-1966)} -> 343.547 | M65: {=INDEX(GMWQ!$A$2:$NF$60,MATCH(1,(GMWQ!$NE$2:$NE$60=M$3)*(GMWQ!$ND$2:$ND$60=M$4)*(GMWQ!$NF$2:$NF$60=M$1),0),$F65-1966)} -> 272798.8 | N65: {=INDEX(GMWQ!$A$2:$NF$60,MATCH(1,(GMWQ!$NE$2:$NE$60=N$3)*(GMWQ!$ND$2:$ND$60=N$4)*(GMWQ!$NF$2:$NF$60=N$1),0),$F65-1966)} -> -1823 | ... AL65: {=INDEX(GMWQ!$A$2:$NF$60,MATCH(1,(GMWQ!$NE$2:$NE$60=AL$3)*(GMWQ!$ND$2:$ND$60=AL$4)*(GMWQ!$NF$2:$NF$60=AL$1),0),$F65-1966)} -> 2.099236
B66: =+B62+1 -> 1987 | C66: =+C62+1 -> 1987 | E66: =+E62+1 -> 1987 | F66: =+F65+1 -> 2032 | G66: {=INDEX(GMWQ!$A$2:$NF$60,MATCH(1,(GMWQ!$NE$2:$NE$60=G$3)*(GMWQ!$ND$2:$ND$60=G$4)*(GMWQ!$NF$2:$NF$60=G$1),0),$F66-1966)} -> 357439 | H66: {=INDEX(GMWQ!$A$2:$NF$60,MATCH(1,(GMWQ!$NE$2:$NE$60=H$3)*(GMWQ!$ND$2:$ND$60=H$4)*(GMWQ!$NF$2:$NF$60=H$1),0),$F66-1966)} -> 2329.825 | I66: {=INDEX(GMWQ!$A$2:$NF$60,MATCH(1,(GMWQ!$NE$2:$NE$60=I$3)*(GMWQ!$ND$2:$ND$60=I$4)*(GMWQ!$NF$2:$NF$60=I$1),0),$F66-1966)} -> 93422.8 | J66: {=INDEX(GMWQ!$A$2:$NF$60,MATCH(1,(GMWQ!$NE$2:$NE$60=J$3)*(GMWQ!$ND$2:$ND$60=J$4)*(GMWQ!$NF$2:$NF$60=J$1),0),$F66-1966)} -> 520.15 | K66: {=INDEX(GMWQ!$A$2:$NF$60,MATCH(1,(GMWQ!$NE$2:$NE$60=K$3)*(GMWQ!$ND$2:$ND$60=K$4)*(GMWQ!$NF$2:$NF$60=K$1),0),$F66-1966)} -> 354.442 | L66: {=INDEX(GMWQ!$A$2:$NF$60,MATCH(1,(GMWQ!$NE$2:$NE$60=L$3)*(GMWQ!$ND$2:$ND$60=L$4)*(GMWQ!$NF$2:$NF$60=L$1),0),$F66-1966)} -> 347.243 | M66: {=INDEX(GMWQ!$A$2:$NF$60,MATCH(1,(GMWQ!$NE$2:$NE$60=M$3)*(GMWQ!$ND$2:$ND$60=M$4)*(GMWQ!$NF$2:$NF$60=M$1),0),$F66-1966)} -> 276323 | N66: {=INDEX(GMWQ!$A$2:$NF$60,MATCH(1,(GMWQ!$NE$2:$NE$60=N$3)*(GMWQ!$ND$2:$ND$60=N$4)*(GMWQ!$NF$2:$NF$60=N$1),0),$F66-1966)} -> 101 | ... AL66: {=INDEX(GMWQ!$A$2:$NF$60,MATCH(1,(GMWQ!$NE$2:$NE$60=AL$3)*(GMWQ!$ND$2:$ND$60=AL$4)*(GMWQ!$NF$2:$NF$60=AL$1),0),$F66-1966)} -> 2.178898
A67: 1988 | B67: =+B63+1 -> 1988 | C67: =+C63+1 -> 1987 | D67: =+D63+1 -> 1987 | F67: =+F66+1 -> 2033 | G67: {=INDEX(GMWQ!$A$2:$NF$60,MATCH(1,(GMWQ!$NE$2:$NE$60=G$3)*(GMWQ!$ND$2:$ND$60=G$4)*(GMWQ!$NF$2:$NF$60=G$1),0),$F67-1966)} -> 363267 | H67: {=INDEX(GMWQ!$A$2:$NF$60,MATCH(1,(GMWQ!$NE$2:$NE$60=H$3)*(GMWQ!$ND$2:$ND$60=H$4)*(GMWQ!$NF$2:$NF$60=H$1),0),$F67-1966)} -> 2341.875 | I67: {=INDEX(GMWQ!$A$2:$NF$60,MATCH(1,(GMWQ!$NE$2:$NE$60=I$3)*(GMWQ!$ND$2:$ND$60=I$4)*(GMWQ!$NF$2:$NF$60=I$1),0),$F67-1966)} -> 94866.7 | J67: {=INDEX(GMWQ!$A$2:$NF$60,MATCH(1,(GMWQ!$NE$2:$NE$60=J$3)*(GMWQ!$ND$2:$ND$60=J$4)*(GMWQ!$NF$2:$NF$60=J$1),0),$F67-1966)} -> 515.6 | K67: {=INDEX(GMWQ!$A$2:$NF$60,MATCH(1,(GMWQ!$NE$2:$NE$60=K$3)*(GMWQ!$ND$2:$ND$60=K$4)*(GMWQ!$NF$2:$NF$60=K$1),0),$F67-1966)} -> 358.993 | L67: {=INDEX(GMWQ!$A$2:$NF$60,MATCH(1,(GMWQ!$NE$2:$NE$60=L$3)*(GMWQ!$ND$2:$ND$60=L$4)*(GMWQ!$NF$2:$NF$60=L$1),0),$F67-1966)} -> 352.354 | M67: {=INDEX(GMWQ!$A$2:$NF$60,MATCH(1,(GMWQ!$NE$2:$NE$60=M$3)*(GMWQ!$ND$2:$ND$60=M$4)*(GMWQ!$NF$2:$NF$60=M$1),0),$F67-1966)} -> 280349 | N67: {=INDEX(GMWQ!$A$2:$NF$60,MATCH(1,(GMWQ!$NE$2:$NE$60=N$3)*(GMWQ!$ND$2:$ND$60=N$4)*(GMWQ!$NF$2:$NF$60=N$1),0),$F67-1966)} -> 1001 | ... AL67: {=INDEX(GMWQ!$A$2:$NF$60,MATCH(1,(GMWQ!$NE$2:$NE$60=AL$3)*(GMWQ!$ND$2:$ND$60=AL$4)*(GMWQ!$NF$2:$NF$60=AL$1),0),$F67-1966)} -> 1.284725
B68: =+B64+1 -> 1988 | C68: =+C64+1 -> 1988 | F68: =+F67+1 -> 2034 | G68: {=INDEX(GMWQ!$A$2:$NF$60,MATCH(1,(GMWQ!$NE$2:$NE$60=G$3)*(GMWQ!$ND$2:$ND$60=G$4)*(GMWQ!$NF$2:$NF$60=G$1),0),$F68-1966)} -> 365209 | H68: {=INDEX(GMWQ!$A$2:$NF$60,MATCH(1,(GMWQ!$NE$2:$NE$60=H$3)*(GMWQ!$ND$2:$ND$60=H$4)*(GMWQ!$NF$2:$NF$60=H$1),0),$F68-1966)} -> 2372.65 | I68: {=INDEX(GMWQ!$A$2:$NF$60,MATCH(1,(GMWQ!$NE$2:$NE$60=I$3)*(GMWQ!$ND$2:$ND$60=I$4)*(GMWQ!$NF$2:$NF$60=I$1),0),$F68-1966)} -> 95559.08 | J68: {=INDEX(GMWQ!$A$2:$NF$60,MATCH(1,(GMWQ!$NE$2:$NE$60=J$3)*(GMWQ!$ND$2:$ND$60=J$4)*(GMWQ!$NF$2:$NF$60=J$1),0),$F68-1966)} -> 524.95 | K68: {=INDEX(GMWQ!$A$2:$NF$60,MATCH(1,(GMWQ!$NE$2:$NE$60=K$3)*(GMWQ!$ND$2:$ND$60=K$4)*(GMWQ!$NF$2:$NF$60=K$1),0),$F68-1966)} -> 362.135 | L68: {=INDEX(GMWQ!$A$2:$NF$60,MATCH(1,(GMWQ!$NE$2:$NE$60=L$3)*(GMWQ!$ND$2:$ND$60=L$4)*(GMWQ!$NF$2:$NF$60=L$1),0),$F68-1966)} -> 354.592 | M68: {=INDEX(GMWQ!$A$2:$NF$60,MATCH(1,(GMWQ!$NE$2:$NE$60=M$3)*(GMWQ!$ND$2:$ND$60=M$4)*(GMWQ!$NF$2:$NF$60=M$1),0),$F68-1966)} -> 282836.8 | N68: {=INDEX(GMWQ!$A$2:$NF$60,MATCH(1,(GMWQ!$NE$2:$NE$60=N$3)*(GMWQ!$ND$2:$ND$60=N$4)*(GMWQ!$NF$2:$NF$60=N$1),0),$F68-1966)} -> -1693 | ... AL68: {=INDEX(GMWQ!$A$2:$NF$60,MATCH(1,(GMWQ!$NE$2:$NE$60=AL$3)*(GMWQ!$ND$2:$ND$60=AL$4)*(GMWQ!$NF$2:$NF$60=AL$1),0),$F68-1966)} -> 1.69728
B69: =+B65+1 -> 1988 | C69: =+C65+1 -> 1988 | F69: =+F68+1 -> 2035 | G69: {=INDEX(GMWQ!$A$2:$NF$60,MATCH(1,(GMWQ!$NE$2:$NE$60=G$3)*(GMWQ!$ND$2:$ND$60=G$4)*(GMWQ!$NF$2:$NF$60=G$1),0),$F69-1966)} -> 369774 | H69: {=INDEX(GMWQ!$A$2:$NF$60,MATCH(1,(GMWQ!$NE$2:$NE$60=H$3)*(GMWQ!$ND$2:$ND$60=H$4)*(GMWQ!$NF$2:$NF$60=H$1),0),$F69-1966)} -> 2386.55 | I69: {=INDEX(GMWQ!$A$2:$NF$60,MATCH(1,(GMWQ!$NE$2:$NE$60=I$3)*(GMWQ!$ND$2:$ND$60=I$4)*(GMWQ!$NF$2:$NF$60=I$1),0),$F69-1966)} -> 97321.1 | J69: {=INDEX(GMWQ!$A$2:$NF$60,MATCH(1,(GMWQ!$NE$2:$NE$60=J$3)*(GMWQ!$ND$2:$ND$60=J$4)*(GMWQ!$NF$2:$NF$60=J$1),0),$F69-1966)} -> 530.74 | K69: {=INDEX(GMWQ!$A$2:$NF$60,MATCH(1,(GMWQ!$NE$2:$NE$60=K$3)*(GMWQ!$ND$2:$ND$60=K$4)*(GMWQ!$NF$2:$NF$60=K$1),0),$F69-1966)} -> 366.718 | L69: {=INDEX(GMWQ!$A$2:$NF$60,MATCH(1,(GMWQ!$NE$2:$NE$60=L$3)*(GMWQ!$ND$2:$ND$60=L$4)*(GMWQ!$NF$2:$NF$60=L$1),0),$F69-1966)} -> 359.252 | M69: {=INDEX(GMWQ!$A$2:$NF$60,MATCH(1,(GMWQ!$NE$2:$NE$60=M$3)*(GMWQ!$ND$2:$ND$60=M$4)*(GMWQ!$NF$2:$NF$60=M$1),0),$F69-1966)} -> 282878.8 | N69: {=INDEX(GMWQ!$A$2:$NF$60,MATCH(1,(GMWQ!$NE$2:$NE$60=N$3)*(GMWQ!$ND$2:$ND$60=N$4)*(GMWQ!$NF$2:$NF$60=N$1),0),$F69-1966)} -> 1095 | ... AL69: {=INDEX(GMWQ!$A$2:$NF$60,MATCH(1,(GMWQ!$NE$2:$NE$60=AL$3)*(GMWQ!$ND$2:$ND$60=AL$4)*(GMWQ!$NF$2:$NF$60=AL$1),0),$F69-1966)} -> 2.115235
B70: =+B66+1 -> 1988 | C70: =+C66+1 -> 1988 | E70: =+E66+1 -> 1988 | F70: =+F69+1 -> 2036 | G70: {=INDEX(GMWQ!$A$2:$NF$60,MATCH(1,(GMWQ!$NE$2:$NE$60=G$3)*(GMWQ!$ND$2:$ND$60=G$4)*(GMWQ!$NF$2:$NF$60=G$1),0),$F70-1966)} -> 372752 | H70: {=INDEX(GMWQ!$A$2:$NF$60,MATCH(1,(GMWQ!$NE$2:$NE$60=H$3)*(GMWQ!$ND$2:$ND$60=H$4)*(GMWQ!$NF$2:$NF$60=H$1),0),$F70-1966)} -> 2418.35 | I70: {=INDEX(GMWQ!$A$2:$NF$60,MATCH(1,(GMWQ!$NE$2:$NE$60=I$3)*(GMWQ!$ND$2:$ND$60=I$4)*(GMWQ!$NF$2:$NF$60=I$1),0),$F70-1966)} -> 98386.73 | J70: {=INDEX(GMWQ!$A$2:$NF$60,MATCH(1,(GMWQ!$NE$2:$NE$60=J$3)*(GMWQ!$ND$2:$ND$60=J$4)*(GMWQ!$NF$2:$NF$60=J$1),0),$F70-1966)} -> 537.11 | K70: {=INDEX(GMWQ!$A$2:$NF$60,MATCH(1,(GMWQ!$NE$2:$NE$60=K$3)*(GMWQ!$ND$2:$ND$60=K$4)*(GMWQ!$NF$2:$NF$60=K$1),0),$F70-1966)} -> 369.743 | L70: {=INDEX(GMWQ!$A$2:$NF$60,MATCH(1,(GMWQ!$NE$2:$NE$60=L$3)*(GMWQ!$ND$2:$ND$60=L$4)*(GMWQ!$NF$2:$NF$60=L$1),0),$F70-1966)} -> 363.541 | M70: {=INDEX(GMWQ!$A$2:$NF$60,MATCH(1,(GMWQ!$NE$2:$NE$60=M$3)*(GMWQ!$ND$2:$ND$60=M$4)*(GMWQ!$NF$2:$NF$60=M$1),0),$F70-1966)} -> 284820 | N70: {=INDEX(GMWQ!$A$2:$NF$60,MATCH(1,(GMWQ!$NE$2:$NE$60=N$3)*(GMWQ!$ND$2:$ND$60=N$4)*(GMWQ!$NF$2:$NF$60=N$1),0),$F70-1966)} -> 2730 | ... AL70: {=INDEX(GMWQ!$A$2:$NF$60,MATCH(1,(GMWQ!$NE$2:$NE$60=AL$3)*(GMWQ!$ND$2:$ND$60=AL$4)*(GMWQ!$NF$2:$NF$60=AL$1),0),$F70-1966)} -> 1.314812
A71: 1989 | B71: =+B67+1 -> 1989 | C71: =+C67+1 -> 1988 | D71: =+D67+1 -> 1988 | F71: =+F70+1 -> 2037 | G71: {=INDEX(GMWQ!$A$2:$NF$60,MATCH(1,(GMWQ!$NE$2:$NE$60=G$3)*(GMWQ!$ND$2:$ND$60=G$4)*(GMWQ!$NF$2:$NF$60=G$1),0),$F71-1966)} -> 374612 | H71: {=INDEX(GMWQ!$A$2:$NF$60,MATCH(1,(GMWQ!$NE$2:$NE$60=H$3)*(GMWQ!$ND$2:$ND$60=H$4)*(GMWQ!$NF$2:$NF$60=H$1),0),$F71-1966)} -> 2442.925 | I71: {=INDEX(GMWQ!$A$2:$NF$60,MATCH(1,(GMWQ!$NE$2:$NE$60=I$3)*(GMWQ!$ND$2:$ND$60=I$4)*(GMWQ!$NF$2:$NF$60=I$1),0),$F71-1966)} -> 100718.5 | J71: {=INDEX(GMWQ!$A$2:$NF$60,MATCH(1,(GMWQ!$NE$2:$NE$60=J$3)*(GMWQ!$ND$2:$ND$60=J$4)*(GMWQ!$NF$2:$NF$60=J$1),0),$F71-1966)} -> 542.57 | K71: {=INDEX(GMWQ!$A$2:$NF$60,MATCH(1,(GMWQ!$NE$2:$NE$60=K$3)*(GMWQ!$ND$2:$ND$60=K$4)*(GMWQ!$NF$2:$NF$60=K$1),0),$F71-1966)} -> 374.552 | L71: {=INDEX(GMWQ!$A$2:$NF$60,MATCH(1,(GMWQ!$NE$2:$NE$60=L$3)*(GMWQ!$ND$2:$ND$60=L$4)*(GMWQ!$NF$2:$NF$60=L$1),0),$F71-1966)} -> 365.798 | M71: {=INDEX(GMWQ!$A$2:$NF$60,MATCH(1,(GMWQ!$NE$2:$NE$60=M$3)*(GMWQ!$ND$2:$ND$60=M$4)*(GMWQ!$NF$2:$NF$60=M$1),0),$F71-1966)} -> 288111 | N71: {=INDEX(GMWQ!$A$2:$NF$60,MATCH(1,(GMWQ!$NE$2:$NE$60=N$3)*(GMWQ!$ND$2:$ND$60=N$4)*(GMWQ!$NF$2:$NF$60=N$1),0),$F71-1966)} -> 3398 | ... AL71: {=INDEX(GMWQ!$A$2:$NF$60,MATCH(1,(GMWQ!$NE$2:$NE$60=AL$3)*(GMWQ!$ND$2:$ND$60=AL$4)*(GMWQ!$NF$2:$NF$60=AL$1),0),$F71-1966)} -> 1.392154
B72: =+B68+1 -> 1989 | C72: =+C68+1 -> 1989 | F72: =+F71+1 -> 2038 | G72: {=INDEX(GMWQ!$A$2:$NF$60,MATCH(1,(GMWQ!$NE$2:$NE$60=G$3)*(GMWQ!$ND$2:$ND$60=G$4)*(GMWQ!$NF$2:$NF$60=G$1),0),$F72-1966)} -> 376951 | H72: {=INDEX(GMWQ!$A$2:$NF$60,MATCH(1,(GMWQ!$NE$2:$NE$60=H$3)*(GMWQ!$ND$2:$ND$60=H$4)*(GMWQ!$NF$2:$NF$60=H$1),0),$F72-1966)} -> 2461.575 | I72: {=INDEX(GMWQ!$A$2:$NF$60,MATCH(1,(GMWQ!$NE$2:$NE$60=I$3)*(GMWQ!$ND$2:$ND$60=I$4)*(GMWQ!$NF$2:$NF$60=I$1),0),$F72-1966)} -> 99521.33 | J72: {=INDEX(GMWQ!$A$2:$NF$60,MATCH(1,(GMWQ!$NE$2:$NE$60=J$3)*(GMWQ!$ND$2:$ND$60=J$4)*(GMWQ!$NF$2:$NF$60=J$1),0),$F72-1966)} -> 544.81 | K72: {=INDEX(GMWQ!$A$2:$NF$60,MATCH(1,(GMWQ!$NE$2:$NE$60=K$3)*(GMWQ!$ND$2:$ND$60=K$4)*(GMWQ!$NF$2:$NF$60=K$1),0),$F72-1966)} -> 378.731 | L72: {=INDEX(GMWQ!$A$2:$NF$60,MATCH(1,(GMWQ!$NE$2:$NE$60=L$3)*(GMWQ!$ND$2:$ND$60=L$4)*(GMWQ!$NF$2:$NF$60=L$1),0),$F72-1966)} -> 367.382 | M72: {=INDEX(GMWQ!$A$2:$NF$60,MATCH(1,(GMWQ!$NE$2:$NE$60=M$3)*(GMWQ!$ND$2:$ND$60=M$4)*(GMWQ!$NF$2:$NF$60=M$1),0),$F72-1966)} -> 289231.8 | N72: {=INDEX(GMWQ!$A$2:$NF$60,MATCH(1,(GMWQ!$NE$2:$NE$60=N$3)*(GMWQ!$ND$2:$ND$60=N$4)*(GMWQ!$NF$2:$NF$60=N$1),0),$F72-1966)} -> -2035 | ... AL72: {=INDEX(GMWQ!$A$2:$NF$60,MATCH(1,(GMWQ!$NE$2:$NE$60=AL$3)*(GMWQ!$ND$2:$ND$60=AL$4)*(GMWQ!$NF$2:$NF$60=AL$1),0),$F72-1966)} -> 1.187382
B73: =+B69+1 -> 1989 | C73: =+C69+1 -> 1989 | F73: =+F72+1 -> 2039 | G73: {=INDEX(GMWQ!$A$2:$NF$60,MATCH(1,(GMWQ!$NE$2:$NE$60=G$3)*(GMWQ!$ND$2:$ND$60=G$4)*(GMWQ!$NF$2:$NF$60=G$1),0),$F73-1966)} -> 377573 | H73: {=INDEX(GMWQ!$A$2:$NF$60,MATCH(1,(GMWQ!$NE$2:$NE$60=H$3)*(GMWQ!$ND$2:$ND$60=H$4)*(GMWQ!$NF$2:$NF$60=H$1),0),$F73-1966)} -> 2479.8 | I73: {=INDEX(GMWQ!$A$2:$NF$60,MATCH(1,(GMWQ!$NE$2:$NE$60=I$3)*(GMWQ!$ND$2:$ND$60=I$4)*(GMWQ!$NF$2:$NF$60=I$1),0),$F73-1966)} -> 101067.9 | J73: {=INDEX(GMWQ!$A$2:$NF$60,MATCH(1,(GMWQ!$NE$2:$NE$60=J$3)*(GMWQ!$ND$2:$ND$60=J$4)*(GMWQ!$NF$2:$NF$60=J$1),0),$F73-1966)} -> 549.78 | K73: {=INDEX(GMWQ!$A$2:$NF$60,MATCH(1,(GMWQ!$NE$2:$NE$60=K$3)*(GMWQ!$ND$2:$ND$60=K$4)*(GMWQ!$NF$2:$NF$60=K$1),0),$F73-1966)} -> 382.998 | L73: {=INDEX(GMWQ!$A$2:$NF$60,MATCH(1,(GMWQ!$NE$2:$NE$60=L$3)*(GMWQ!$ND$2:$ND$60=L$4)*(GMWQ!$NF$2:$NF$60=L$1),0),$F73-1966)} -> 371.212 | M73: {=INDEX(GMWQ!$A$2:$NF$60,MATCH(1,(GMWQ!$NE$2:$NE$60=M$3)*(GMWQ!$ND$2:$ND$60=M$4)*(GMWQ!$NF$2:$NF$60=M$1),0),$F73-1966)} -> 290276 | N73: {=INDEX(GMWQ!$A$2:$NF$60,MATCH(1,(GMWQ!$NE$2:$NE$60=N$3)*(GMWQ!$ND$2:$ND$60=N$4)*(GMWQ!$NF$2:$NF$60=N$1),0),$F73-1966)} -> -784 | ... AL73: {=INDEX(GMWQ!$A$2:$NF$60,MATCH(1,(GMWQ!$NE$2:$NE$60=AL$3)*(GMWQ!$ND$2:$ND$60=AL$4)*(GMWQ!$NF$2:$NF$60=AL$1),0),$F73-1966)} -> 0.7066491
B74: =+B70+1 -> 1989 | C74: =+C70+1 -> 1989 | E74: =+E70+1 -> 1989 | F74: =+F73+1 -> 2040 | G74: {=INDEX(GMWQ!$A$2:$NF$60,MATCH(1,(GMWQ!$NE$2:$NE$60=G$3)*(GMWQ!$ND$2:$ND$60=G$4)*(GMWQ!$NF$2:$NF$60=G$1),0),$F74-1966)} -> 377508 | H74: {=INDEX(GMWQ!$A$2:$NF$60,MATCH(1,(GMWQ!$NE$2:$NE$60=H$3)*(GMWQ!$ND$2:$ND$60=H$4)*(GMWQ!$NF$2:$NF$60=H$1),0),$F74-1966)} -> 2484.7 | I74: {=INDEX(GMWQ!$A$2:$NF$60,MATCH(1,(GMWQ!$NE$2:$NE$60=I$3)*(GMWQ!$ND$2:$ND$60=I$4)*(GMWQ!$NF$2:$NF$60=I$1),0),$F74-1966)} -> 103823.8 | J74: {=INDEX(GMWQ!$A$2:$NF$60,MATCH(1,(GMWQ!$NE$2:$NE$60=J$3)*(GMWQ!$ND$2:$ND$60=J$4)*(GMWQ!$NF$2:$NF$60=J$1),0),$F74-1966)} -> 556.15 | K74: {=INDEX(GMWQ!$A$2:$NF$60,MATCH(1,(GMWQ!$NE$2:$NE$60=K$3)*(GMWQ!$ND$2:$ND$60=K$4)*(GMWQ!$NF$2:$NF$60=K$1),0),$F74-1966)} -> 388.135 | L74: {=INDEX(GMWQ!$A$2:$NF$60,MATCH(1,(GMWQ!$NE$2:$NE$60=L$3)*(GMWQ!$ND$2:$ND$60=L$4)*(GMWQ!$NF$2:$NF$60=L$1),0),$F74-1966)} -> 375.032 | M74: {=INDEX(GMWQ!$A$2:$NF$60,MATCH(1,(GMWQ!$NE$2:$NE$60=M$3)*(GMWQ!$ND$2:$ND$60=M$4)*(GMWQ!$NF$2:$NF$60=M$1),0),$F74-1966)} -> 289698.3 | N74: {=INDEX(GMWQ!$A$2:$NF$60,MATCH(1,(GMWQ!$NE$2:$NE$60=N$3)*(GMWQ!$ND$2:$ND$60=N$4)*(GMWQ!$NF$2:$NF$60=N$1),0),$F74-1966)} -> 2538 | ... AL74: {=INDEX(GMWQ!$A$2:$NF$60,MATCH(1,(GMWQ!$NE$2:$NE$60=AL$3)*(GMWQ!$ND$2:$ND$60=AL$4)*(GMWQ!$NF$2:$NF$60=AL$1),0),$F74-1966)} -> 0.7228332
A75: 1990 | B75: =+B71+1 -> 1990 | C75: =+C71+1 -> 1989 | D75: =+D71+1 -> 1989 | F75: =+F74+1 -> 2041 | G75: {=INDEX(GMWQ!$A$2:$NF$60,MATCH(1,(GMWQ!$NE$2:$NE$60=G$3)*(GMWQ!$ND$2:$ND$60=G$4)*(GMWQ!$NF$2:$NF$60=G$1),0),$F75-1966)} -> 379458 | H75: {=INDEX(GMWQ!$A$2:$NF$60,MATCH(1,(GMWQ!$NE$2:$NE$60=H$3)*(GMWQ!$ND$2:$ND$60=H$4)*(GMWQ!$NF$2:$NF$60=H$1),0),$F75-1966)} -> 2511.85 | I75: {=INDEX(GMWQ!$A$2:$NF$60,MATCH(1,(GMWQ!$NE$2:$NE$60=I$3)*(GMWQ!$ND$2:$ND$60=I$4)*(GMWQ!$NF$2:$NF$60=I$1),0),$F75-1966)} -> 103264 | J75: {=INDEX(GMWQ!$A$2:$NF$60,MATCH(1,(GMWQ!$NE$2:$NE$60=J$3)*(GMWQ!$ND$2:$ND$60=J$4)*(GMWQ!$NF$2:$NF$60=J$1),0),$F75-1966)} -> 567.64 | K75: {=INDEX(GMWQ!$A$2:$NF$60,MATCH(1,(GMWQ!$NE$2:$NE$60=K$3)*(GMWQ!$ND$2:$ND$60=K$4)*(GMWQ!$NF$2:$NF$60=K$1),0),$F75-1966)} -> 388.956 | L75: {=INDEX(GMWQ!$A$2:$NF$60,MATCH(1,(GMWQ!$NE$2:$NE$60=L$3)*(GMWQ!$ND$2:$ND$60=L$4)*(GMWQ!$NF$2:$NF$60=L$1),0),$F75-1966)} -> 376.526 | M75: {=INDEX(GMWQ!$A$2:$NF$60,MATCH(1,(GMWQ!$NE$2:$NE$60=M$3)*(GMWQ!$ND$2:$ND$60=M$4)*(GMWQ!$NF$2:$NF$60=M$1),0),$F75-1966)} -> 292484.3 | N75: {=INDEX(GMWQ!$A$2:$NF$60,MATCH(1,(GMWQ!$NE$2:$NE$60=N$3)*(GMWQ!$ND$2:$ND$60=N$4)*(GMWQ!$NF$2:$NF$60=N$1),0),$F75-1966)} -> 157 | ... AL75: {=INDEX(GMWQ!$A$2:$NF$60,MATCH(1,(GMWQ!$NE$2:$NE$60=AL$3)*(GMWQ!$ND$2:$ND$60=AL$4)*(GMWQ!$NF$2:$NF$60=AL$1),0),$F75-1966)} -> 1.260385
B76: =+B72+1 -> 1990 | C76: =+C72+1 -> 1990 | F76: =+F75+1 -> 2042 | G76: {=INDEX(GMWQ!$A$2:$NF$60,MATCH(1,(GMWQ!$NE$2:$NE$60=G$3)*(GMWQ!$ND$2:$ND$60=G$4)*(GMWQ!$NF$2:$NF$60=G$1),0),$F76-1966)} -> 381997 | H76: {=INDEX(GMWQ!$A$2:$NF$60,MATCH(1,(GMWQ!$NE$2:$NE$60=H$3)*(GMWQ!$ND$2:$ND$60=H$4)*(GMWQ!$NF$2:$NF$60=H$1),0),$F76-1966)} -> 2520.975 | I76: {=INDEX(GMWQ!$A$2:$NF$60,MATCH(1,(GMWQ!$NE$2:$NE$60=I$3)*(GMWQ!$ND$2:$ND$60=I$4)*(GMWQ!$NF$2:$NF$60=I$1),0),$F76-1966)} -> 105791 | J76: {=INDEX(GMWQ!$A$2:$NF$60,MATCH(1,(GMWQ!$NE$2:$NE$60=J$3)*(GMWQ!$ND$2:$ND$60=J$4)*(GMWQ!$NF$2:$NF$60=J$1),0),$F76-1966)} -> 570.55 | K76: {=INDEX(GMWQ!$A$2:$NF$60,MATCH(1,(GMWQ!$NE$2:$NE$60=K$3)*(GMWQ!$ND$2:$ND$60=K$4)*(GMWQ!$NF$2:$NF$60=K$1),0),$F76-1966)} -> 391.046 | L76: {=INDEX(GMWQ!$A$2:$NF$60,MATCH(1,(GMWQ!$NE$2:$NE$60=L$3)*(GMWQ!$ND$2:$ND$60=L$4)*(GMWQ!$NF$2:$NF$60=L$1),0),$F76-1966)} -> 377.674 | M76: {=INDEX(GMWQ!$A$2:$NF$60,MATCH(1,(GMWQ!$NE$2:$NE$60=M$3)*(GMWQ!$ND$2:$ND$60=M$4)*(GMWQ!$NF$2:$NF$60=M$1),0),$F76-1966)} -> 291310.8 | N76: {=INDEX(GMWQ!$A$2:$NF$60,MATCH(1,(GMWQ!$NE$2:$NE$60=N$3)*(GMWQ!$ND$2:$ND$60=N$4)*(GMWQ!$NF$2:$NF$60=N$1),0),$F76-1966)} -> -3212 | ... AL76: {=INDEX(GMWQ!$A$2:$NF$60,MATCH(1,(GMWQ!$NE$2:$NE$60=AL$3)*(GMWQ!$ND$2:$ND$60=AL$4)*(GMWQ!$NF$2:$NF$60=AL$1),0),$F76-1966)} -> 0.7745686
B77: =+B73+1 -> 1990 | C77: =+C73+1 -> 1990 | F77: =+F76+1 -> 2043 | G77: {=INDEX(GMWQ!$A$2:$NF$60,MATCH(1,(GMWQ!$NE$2:$NE$60=G$3)*(GMWQ!$ND$2:$ND$60=G$4)*(GMWQ!$NF$2:$NF$60=G$1),0),$F77-1966)} -> 377831 | H77: {=INDEX(GMWQ!$A$2:$NF$60,MATCH(1,(GMWQ!$NE$2:$NE$60=H$3)*(GMWQ!$ND$2:$ND$60=H$4)*(GMWQ!$NF$2:$NF$60=H$1),0),$F77-1966)} -> 2522.65 | I77: {=INDEX(GMWQ!$A$2:$NF$60,MATCH(1,(GMWQ!$NE$2:$NE$60=I$3)*(GMWQ!$ND$2:$ND$60=I$4)*(GMWQ!$NF$2:$NF$60=I$1),0),$F77-1966)} -> 107937.8 | J77: {=INDEX(GMWQ!$A$2:$NF$60,MATCH(1,(GMWQ!$NE$2:$NE$60=J$3)*(GMWQ!$ND$2:$ND$60=J$4)*(GMWQ!$NF$2:$NF$60=J$1),0),$F77-1966)} -> 582.54 | K77: {=INDEX(GMWQ!$A$2:$NF$60,MATCH(1,(GMWQ!$NE$2:$NE$60=K$3)*(GMWQ!$ND$2:$ND$60=K$4)*(GMWQ!$NF$2:$NF$60=K$1),0),$F77-1966)} -> 393.587 | L77: {=INDEX(GMWQ!$A$2:$NF$60,MATCH(1,(GMWQ!$NE$2:$NE$60=L$3)*(GMWQ!$ND$2:$ND$60=L$4)*(GMWQ!$NF$2:$NF$60=L$1),0),$F77-1966)} -> 378.281 | M77: {=INDEX(GMWQ!$A$2:$NF$60,MATCH(1,(GMWQ!$NE$2:$NE$60=M$3)*(GMWQ!$ND$2:$ND$60=M$4)*(GMWQ!$NF$2:$NF$60=M$1),0),$F77-1966)} -> 289223 | N77: {=INDEX(GMWQ!$A$2:$NF$60,MATCH(1,(GMWQ!$NE$2:$NE$60=N$3)*(GMWQ!$ND$2:$ND$60=N$4)*(GMWQ!$NF$2:$NF$60=N$1),0),$F77-1966)} -> -1084 | ... AL77: {=INDEX(GMWQ!$A$2:$NF$60,MATCH(1,(GMWQ!$NE$2:$NE$60=AL$3)*(GMWQ!$ND$2:$ND$60=AL$4)*(GMWQ!$NF$2:$NF$60=AL$1),0),$F77-1966)} -> 1.404238
B78: =+B74+1 -> 1990 | C78: =+C74+1 -> 1990 | E78: =+E74+1 -> 1990 | F78: =+F77+1 -> 2044 | G78: {=INDEX(GMWQ!$A$2:$NF$60,MATCH(1,(GMWQ!$NE$2:$NE$60=G$3)*(GMWQ!$ND$2:$ND$60=G$4)*(GMWQ!$NF$2:$NF$60=G$1),0),$F78-1966)} -> 375916 | H78: {=INDEX(GMWQ!$A$2:$NF$60,MATCH(1,(GMWQ!$NE$2:$NE$60=H$3)*(GMWQ!$ND$2:$ND$60=H$4)*(GMWQ!$NF$2:$NF$60=H$1),0),$F78-1966)} -> 2499.675 | I78: {=INDEX(GMWQ!$A$2:$NF$60,MATCH(1,(GMWQ!$NE$2:$NE$60=I$3)*(GMWQ!$ND$2:$ND$60=I$4)*(GMWQ!$NF$2:$NF$60=I$1),0),$F78-1966)} -> 107869 | J78: {=INDEX(GMWQ!$A$2:$NF$60,MATCH(1,(GMWQ!$NE$2:$NE$60=J$3)*(GMWQ!$ND$2:$ND$60=J$4)*(GMWQ!$NF$2:$NF$60=J$1),0),$F78-1966)} -> 592.8 | K78: {=INDEX(GMWQ!$A$2:$NF$60,MATCH(1,(GMWQ!$NE$2:$NE$60=K$3)*(GMWQ!$ND$2:$ND$60=K$4)*(GMWQ!$NF$2:$NF$60=K$1),0),$F78-1966)} -> 393.398 | L78: {=INDEX(GMWQ!$A$2:$NF$60,MATCH(1,(GMWQ!$NE$2:$NE$60=L$3)*(GMWQ!$ND$2:$ND$60=L$4)*(GMWQ!$NF$2:$NF$60=L$1),0),$F78-1966)} -> 375.822 | M78: {=INDEX(GMWQ!$A$2:$NF$60,MATCH(1,(GMWQ!$NE$2:$NE$60=M$3)*(GMWQ!$ND$2:$ND$60=M$4)*(GMWQ!$NF$2:$NF$60=M$1),0),$F78-1966)} -> 286647.8 | N78: {=INDEX(GMWQ!$A$2:$NF$60,MATCH(1,(GMWQ!$NE$2:$NE$60=N$3)*(GMWQ!$ND$2:$ND$60=N$4)*(GMWQ!$NF$2:$NF$60=N$1),0),$F78-1966)} -> -1129 | ... AL78: {=INDEX(GMWQ!$A$2:$NF$60,MATCH(1,(GMWQ!$NE$2:$NE$60=AL$3)*(GMWQ!$ND$2:$ND$60=AL$4)*(GMWQ!$NF$2:$NF$60=AL$1),0),$F78-1966)} -> 0.977968
A79: 1991 | B79: =+B75+1 -> 1991 | C79: =+C75+1 -> 1990 | D79: =+D75+1 -> 1990 | F79: =+F78+1 -> 2045 | G79: {=INDEX(GMWQ!$A$2:$NF$60,MATCH(1,(GMWQ!$NE$2:$NE$60=G$3)*(GMWQ!$ND$2:$ND$60=G$4)*(GMWQ!$NF$2:$NF$60=G$1),0),$F79-1966)} -> 374060 | H79: {=INDEX(GMWQ!$A$2:$NF$60,MATCH(1,(GMWQ!$NE$2:$NE$60=H$3)*(GMWQ!$ND$2:$ND$60=H$4)*(GMWQ!$NF$2:$NF$60=H$1),0),$F79-1966)} -> 2487.975 | I79: {=INDEX(GMWQ!$A$2:$NF$60,MATCH(1,(GMWQ!$NE$2:$NE$60=I$3)*(GMWQ!$ND$2:$ND$60=I$4)*(GMWQ!$NF$2:$NF$60=I$1),0),$F79-1966)} -> 109030.2 | J79: {=INDEX(GMWQ!$A$2:$NF$60,MATCH(1,(GMWQ!$NE$2:$NE$60=J$3)*(GMWQ!$ND$2:$ND$60=J$4)*(GMWQ!$NF$2:$NF$60=J$1),0),$F79-1966)} -> 610.84 | K79: {=INDEX(GMWQ!$A$2:$NF$60,MATCH(1,(GMWQ!$NE$2:$NE$60=K$3)*(GMWQ!$ND$2:$ND$60=K$4)*(GMWQ!$NF$2:$NF$60=K$1),0),$F79-1966)} -> 394.433 | L79: {=INDEX(GMWQ!$A$2:$NF$60,MATCH(1,(GMWQ!$NE$2:$NE$60=L$3)*(GMWQ!$ND$2:$ND$60=L$4)*(GMWQ!$NF$2:$NF$60=L$1),0),$F79-1966)} -> 379.581 | M79: {=INDEX(GMWQ!$A$2:$NF$60,MATCH(1,(GMWQ!$NE$2:$NE$60=M$3)*(GMWQ!$ND$2:$ND$60=M$4)*(GMWQ!$NF$2:$NF$60=M$1),0),$F79-1966)} -> 282524 | N79: {=INDEX(GMWQ!$A$2:$NF$60,MATCH(1,(GMWQ!$NE$2:$NE$60=N$3)*(GMWQ!$ND$2:$ND$60=N$4)*(GMWQ!$NF$2:$NF$60=N$1),0),$F79-1966)} -> -1890 | ... AL79: {=INDEX(GMWQ!$A$2:$NF$60,MATCH(1,(GMWQ!$NE$2:$NE$60=AL$3)*(GMWQ!$ND$2:$ND$60=AL$4)*(GMWQ!$NF$2:$NF$60=AL$1),0),$F79-1966)} -> 0.1843631
B80: =+B76+1 -> 1991 | C80: =+C76+1 -> 1991 | F80: =+F79+1 -> 2046 | G80: {=INDEX(GMWQ!$A$2:$NF$60,MATCH(1,(GMWQ!$NE$2:$NE$60=G$3)*(GMWQ!$ND$2:$ND$60=G$4)*(GMWQ!$NF$2:$NF$60=G$1),0),$F80-1966)} -> 373608 | H80: {=INDEX(GMWQ!$A$2:$NF$60,MATCH(1,(GMWQ!$NE$2:$NE$60=H$3)*(GMWQ!$ND$2:$ND$60=H$4)*(GMWQ!$NF$2:$NF$60=H$1),0),$F80-1966)} -> 2507.375 | I80: {=INDEX(GMWQ!$A$2:$NF$60,MATCH(1,(GMWQ!$NE$2:$NE$60=I$3)*(GMWQ!$ND$2:$ND$60=I$4)*(GMWQ!$NF$2:$NF$60=I$1),0),$F80-1966)} -> 109977.8 | J80: {=INDEX(GMWQ!$A$2:$NF$60,MATCH(1,(GMWQ!$NE$2:$NE$60=J$3)*(GMWQ!$ND$2:$ND$60=J$4)*(GMWQ!$NF$2:$NF$60=J$1),0),$F80-1966)} -> 607.91 | K80: {=INDEX(GMWQ!$A$2:$NF$60,MATCH(1,(GMWQ!$NE$2:$NE$60=K$3)*(GMWQ!$ND$2:$ND$60=K$4)*(GMWQ!$NF$2:$NF$60=K$1),0),$F80-1966)} -> 395.89 | L80: {=INDEX(GMWQ!$A$2:$NF$60,MATCH(1,(GMWQ!$NE$2:$NE$60=L$3)*(GMWQ!$ND$2:$ND$60=L$4)*(GMWQ!$NF$2:$NF$60=L$1),0),$F80-1966)} -> 377.503 | M80: {=INDEX(GMWQ!$A$2:$NF$60,MATCH(1,(GMWQ!$NE$2:$NE$60=M$3)*(GMWQ!$ND$2:$ND$60=M$4)*(GMWQ!$NF$2:$NF$60=M$1),0),$F80-1966)} -> 283880 | N80: {=INDEX(GMWQ!$A$2:$NF$60,MATCH(1,(GMWQ!$NE$2:$NE$60=N$3)*(GMWQ!$ND$2:$ND$60=N$4)*(GMWQ!$NF$2:$NF$60=N$1),0),$F80-1966)} -> -7462 | ... AL80: {=INDEX(GMWQ!$A$2:$NF$60,MATCH(1,(GMWQ!$NE$2:$NE$60=AL$3)*(GMWQ!$ND$2:$ND$60=AL$4)*(GMWQ!$NF$2:$NF$60=AL$1),0),$F80-1966)} -> 0.3360157
B81: =+B77+1 -> 1991 | C81: =+C77+1 -> 1991 | F81: =+F80+1 -> 2047 | G81: {=INDEX(GMWQ!$A$2:$NF$60,MATCH(1,(GMWQ!$NE$2:$NE$60=G$3)*(GMWQ!$ND$2:$ND$60=G$4)*(GMWQ!$NF$2:$NF$60=G$1),0),$F81-1966)} -> 372878 | H81: {=INDEX(GMWQ!$A$2:$NF$60,MATCH(1,(GMWQ!$NE$2:$NE$60=H$3)*(GMWQ!$ND$2:$ND$60=H$4)*(GMWQ!$NF$2:$NF$60=H$1),0),$F81-1966)} -> 2520.05 | I81: {=INDEX(GMWQ!$A$2:$NF$60,MATCH(1,(GMWQ!$NE$2:$NE$60=I$3)*(GMWQ!$ND$2:$ND$60=I$4)*(GMWQ!$NF$2:$NF$60=I$1),0),$F81-1966)} -> 109973 | J81: {=INDEX(GMWQ!$A$2:$NF$60,MATCH(1,(GMWQ!$NE$2:$NE$60=J$3)*(GMWQ!$ND$2:$ND$60=J$4)*(GMWQ!$NF$2:$NF$60=J$1),0),$F81-1966)} -> 606.96 | K81: {=INDEX(GMWQ!$A$2:$NF$60,MATCH(1,(GMWQ!$NE$2:$NE$60=K$3)*(GMWQ!$ND$2:$ND$60=K$4)*(GMWQ!$NF$2:$NF$60=K$1),0),$F81-1966)} -> 397.495 | L81: {=INDEX(GMWQ!$A$2:$NF$60,MATCH(1,(GMWQ!$NE$2:$NE$60=L$3)*(GMWQ!$ND$2:$ND$60=L$4)*(GMWQ!$NF$2:$NF$60=L$1),0),$F81-1966)} -> 377.639 | M81: {=INDEX(GMWQ!$A$2:$NF$60,MATCH(1,(GMWQ!$NE$2:$NE$60=M$3)*(GMWQ!$ND$2:$ND$60=M$4)*(GMWQ!$NF$2:$NF$60=M$1),0),$F81-1966)} -> 284256.5 | N81: {=INDEX(GMWQ!$A$2:$NF$60,MATCH(1,(GMWQ!$NE$2:$NE$60=N$3)*(GMWQ!$ND$2:$ND$60=N$4)*(GMWQ!$NF$2:$NF$60=N$1),0),$F81-1966)} -> -5732 | ... AL81: {=INDEX(GMWQ!$A$2:$NF$60,MATCH(1,(GMWQ!$NE$2:$NE$60=AL$3)*(GMWQ!$ND$2:$ND$60=AL$4)*(GMWQ!$NF$2:$NF$60=AL$1),0),$F81-1966)} -> 0.2244358
B82: =+B78+1 -> 1991 | C82: =+C78+1 -> 1991 | E82: =+E78+1 -> 1991 | F82: =+F81+1 -> 2048 | G82: {=INDEX(GMWQ!$A$2:$NF$60,MATCH(1,(GMWQ!$NE$2:$NE$60=G$3)*(GMWQ!$ND$2:$ND$60=G$4)*(GMWQ!$NF$2:$NF$60=G$1),0),$F82-1966)} -> 373357 | H82: {=INDEX(GMWQ!$A$2:$NF$60,MATCH(1,(GMWQ!$NE$2:$NE$60=H$3)*(GMWQ!$ND$2:$ND$60=H$4)*(GMWQ!$NF$2:$NF$60=H$1),0),$F82-1966)} -> 2528.825 | I82: {=INDEX(GMWQ!$A$2:$NF$60,MATCH(1,(GMWQ!$NE$2:$NE$60=I$3)*(GMWQ!$ND$2:$ND$60=I$4)*(GMWQ!$NF$2:$NF$60=I$1),0),$F82-1966)} -> 110813.9 | J82: {=INDEX(GMWQ!$A$2:$NF$60,MATCH(1,(GMWQ!$NE$2:$NE$60=J$3)*(GMWQ!$ND$2:$ND$60=J$4)*(GMWQ!$NF$2:$NF$60=J$1),0),$F82-1966)} -> 615.67 | K82: {=INDEX(GMWQ!$A$2:$NF$60,MATCH(1,(GMWQ!$NE$2:$NE$60=K$3)*(GMWQ!$ND$2:$ND$60=K$4)*(GMWQ!$NF$2:$NF$60=K$1),0),$F82-1966)} -> 399.413 | L82: {=INDEX(GMWQ!$A$2:$NF$60,MATCH(1,(GMWQ!$NE$2:$NE$60=L$3)*(GMWQ!$ND$2:$ND$60=L$4)*(GMWQ!$NF$2:$NF$60=L$1),0),$F82-1966)} -> 382.071 | M82: {=INDEX(GMWQ!$A$2:$NF$60,MATCH(1,(GMWQ!$NE$2:$NE$60=M$3)*(GMWQ!$ND$2:$ND$60=M$4)*(GMWQ!$NF$2:$NF$60=M$1),0),$F82-1966)} -> 284756 | N82: {=INDEX(GMWQ!$A$2:$NF$60,MATCH(1,(GMWQ!$NE$2:$NE$60=N$3)*(GMWQ!$ND$2:$ND$60=N$4)*(GMWQ!$NF$2:$NF$60=N$1),0),$F82-1966)} -> -4106 | ... AL82: {=INDEX(GMWQ!$A$2:$NF$60,MATCH(1,(GMWQ!$NE$2:$NE$60=AL$3)*(GMWQ!$ND$2:$ND$60=AL$4)*(GMWQ!$NF$2:$NF$60=AL$1),0),$F82-1966)} -> -0.07293487
A83: 1992 | B83: =+B79+1 -> 1992 | C83: =+C79+1 -> 1991 | D83: =+D79+1 -> 1991 | F83: =+F82+1 -> 2049 | G83: {=INDEX(GMWQ!$A$2:$NF$60,MATCH(1,(GMWQ!$NE$2:$NE$60=G$3)*(GMWQ!$ND$2:$ND$60=G$4)*(GMWQ!$NF$2:$NF$60=G$1),0),$F83-1966)} -> 373317 | H83: {=INDEX(GMWQ!$A$2:$NF$60,MATCH(1,(GMWQ!$NE$2:$NE$60=H$3)*(GMWQ!$ND$2:$ND$60=H$4)*(GMWQ!$NF$2:$NF$60=H$1),0),$F83-1966)} -> 2559.1 | I83: {=INDEX(GMWQ!$A$2:$NF$60,MATCH(1,(GMWQ!$NE$2:$NE$60=I$3)*(GMWQ!$ND$2:$ND$60=I$4)*(GMWQ!$NF$2:$NF$60=I$1),0),$F83-1966)} -> 110645.6 | J83: {=INDEX(GMWQ!$A$2:$NF$60,MATCH(1,(GMWQ!$NE$2:$NE$60=J$3)*(GMWQ!$ND$2:$ND$60=J$4)*(GMWQ!$NF$2:$NF$60=J$1),0),$F83-1966)} -> 624.15 | K83: {=INDEX(GMWQ!$A$2:$NF$60,MATCH(1,(GMWQ!$NE$2:$NE$60=K$3)*(GMWQ!$ND$2:$ND$60=K$4)*(GMWQ!$NF$2:$NF$60=K$1),0),$F83-1966)} -> 402.27 | L83: {=INDEX(GMWQ!$A$2:$NF$60,MATCH(1,(GMWQ!$NE$2:$NE$60=L$3)*(GMWQ!$ND$2:$ND$60=L$4)*(GMWQ!$NF$2:$NF$60=L$1),0),$F83-1966)} -> 383.1 | M83: {=INDEX(GMWQ!$A$2:$NF$60,MATCH(1,(GMWQ!$NE$2:$NE$60=M$3)*(GMWQ!$ND$2:$ND$60=M$4)*(GMWQ!$NF$2:$NF$60=M$1),0),$F83-1966)} -> 284957 | N83: {=INDEX(GMWQ!$A$2:$NF$60,MATCH(1,(GMWQ!$NE$2:$NE$60=N$3)*(GMWQ!$ND$2:$ND$60=N$4)*(GMWQ!$NF$2:$NF$60=N$1),0),$F83-1966)} -> -6464 | ... AL83: {=INDEX(GMWQ!$A$2:$NF$60,MATCH(1,(GMWQ!$NE$2:$NE$60=AL$3)*(GMWQ!$ND$2:$ND$60=AL$4)*(GMWQ!$NF$2:$NF$60=AL$1),0),$F83-1966)} -> 0.05642724
B84: =+B80+1 -> 1992 | C84: =+C80+1 -> 1992 | F84: =+F83+1 -> 2050 | G84: {=INDEX(GMWQ!$A$2:$NF$60,MATCH(1,(GMWQ!$NE$2:$NE$60=G$3)*(GMWQ!$ND$2:$ND$60=G$4)*(GMWQ!$NF$2:$NF$60=G$1),0),$F84-1966)} -> 372751 | H84: {=INDEX(GMWQ!$A$2:$NF$60,MATCH(1,(GMWQ!$NE$2:$NE$60=H$3)*(GMWQ!$ND$2:$ND$60=H$4)*(GMWQ!$NF$2:$NF$60=H$1),0),$F84-1966)} -> 2586.85 | I84: {=INDEX(GMWQ!$A$2:$NF$60,MATCH(1,(GMWQ!$NE$2:$NE$60=I$3)*(GMWQ!$ND$2:$ND$60=I$4)*(GMWQ!$NF$2:$NF$60=I$1),0),$F84-1966)} -> 110982.4 | J84: {=INDEX(GMWQ!$A$2:$NF$60,MATCH(1,(GMWQ!$NE$2:$NE$60=J$3)*(GMWQ!$ND$2:$ND$60=J$4)*(GMWQ!$NF$2:$NF$60=J$1),0),$F84-1966)} -> 620.27 | K84: {=INDEX(GMWQ!$A$2:$NF$60,MATCH(1,(GMWQ!$NE$2:$NE$60=K$3)*(GMWQ!$ND$2:$ND$60=K$4)*(GMWQ!$NF$2:$NF$60=K$1),0),$F84-1966)} -> 402.721 | L84: {=INDEX(GMWQ!$A$2:$NF$60,MATCH(1,(GMWQ!$NE$2:$NE$60=L$3)*(GMWQ!$ND$2:$ND$60=L$4)*(GMWQ!$NF$2:$NF$60=L$1),0),$F84-1966)} -> 382.879 | M84: {=INDEX(GMWQ!$A$2:$NF$60,MATCH(1,(GMWQ!$NE$2:$NE$60=M$3)*(GMWQ!$ND$2:$ND$60=M$4)*(GMWQ!$NF$2:$NF$60=M$1),0),$F84-1966)} -> 285281.8 | N84: {=INDEX(GMWQ!$A$2:$NF$60,MATCH(1,(GMWQ!$NE$2:$NE$60=N$3)*(GMWQ!$ND$2:$ND$60=N$4)*(GMWQ!$NF$2:$NF$60=N$1),0),$F84-1966)} -> -13625 | ... AL84: {=INDEX(GMWQ!$A$2:$NF$60,MATCH(1,(GMWQ!$NE$2:$NE$60=AL$3)*(GMWQ!$ND$2:$ND$60=AL$4)*(GMWQ!$NF$2:$NF$60=AL$1),0),$F84-1966)} -> 0.6536562
B85: =+B81+1 -> 1992 | C85: =+C81+1 -> 1992 | F85: =+F84+1 -> 2051 | G85: {=INDEX(GMWQ!$A$2:$NF$60,MATCH(1,(GMWQ!$NE$2:$NE$60=G$3)*(GMWQ!$ND$2:$ND$60=G$4)*(GMWQ!$NF$2:$NF$60=G$1),0),$F85-1966)} -> 374537 | H85: {=INDEX(GMWQ!$A$2:$NF$60,MATCH(1,(GMWQ!$NE$2:$NE$60=H$3)*(GMWQ!$ND$2:$ND$60=H$4)*(GMWQ!$NF$2:$NF$60=H$1),0),$F85-1966)} -> 2612.425 | I85: {=INDEX(GMWQ!$A$2:$NF$60,MATCH(1,(GMWQ!$NE$2:$NE$60=I$3)*(GMWQ!$ND$2:$ND$60=I$4)*(GMWQ!$NF$2:$NF$60=I$1),0),$F85-1966)} -> 111402.7 | J85: {=INDEX(GMWQ!$A$2:$NF$60,MATCH(1,(GMWQ!$NE$2:$NE$60=J$3)*(GMWQ!$ND$2:$ND$60=J$4)*(GMWQ!$NF$2:$NF$60=J$1),0),$F85-1966)} -> 618.8 | K85: {=INDEX(GMWQ!$A$2:$NF$60,MATCH(1,(GMWQ!$NE$2:$NE$60=K$3)*(GMWQ!$ND$2:$ND$60=K$4)*(GMWQ!$NF$2:$NF$60=K$1),0),$F85-1966)} -> 402.258 | L85: {=INDEX(GMWQ!$A$2:$NF$60,MATCH(1,(GMWQ!$NE$2:$NE$60=L$3)*(GMWQ!$ND$2:$ND$60=L$4)*(GMWQ!$NF$2:$NF$60=L$1),0),$F85-1966)} -> 382.028 | M85: {=INDEX(GMWQ!$A$2:$NF$60,MATCH(1,(GMWQ!$NE$2:$NE$60=M$3)*(GMWQ!$ND$2:$ND$60=M$4)*(GMWQ!$NF$2:$NF$60=M$1),0),$F85-1966)} -> 286827 | N85: {=INDEX(GMWQ!$A$2:$NF$60,MATCH(1,(GMWQ!$NE$2:$NE$60=N$3)*(GMWQ!$ND$2:$ND$60=N$4)*(GMWQ!$NF$2:$NF$60=N$1),0),$F85-1966)} -> -10937 | ... AL85: {=INDEX(GMWQ!$A$2:$NF$60,MATCH(1,(GMWQ!$NE$2:$NE$60=AL$3)*(GMWQ!$ND$2:$ND$60=AL$4)*(GMWQ!$NF$2:$NF$60=AL$1),0),$F85-1966)} -> 0.5085204
