Workbook
Name _DLX1.INC: HAVERM!$A$1:$G$6
Name _DLX2.INC: HAVERQ!$A$2:$BM$7
Name Data: [1]sheet0!$C$2

Sheet CHARTS>>

Sheet DATA>>

Sheet Chart Data
A1: Labour income cont to PEDY! | F1: Labour income cont to PEDY | M1: LFS unemployment - single-month & three-month rates | Q1: LFS unemployment - single-month range & 3-month rate | X1: Change in jobs since 2019 - private vs public | AB1: Composition of public sector employment | AJ1: Composition of public sector employment (shares) | AR1: Change in WFJ since 2019 | AS1: =HAVERQ!T186 -> 361 | AT1: =HAVERQ!U186 -> 46 | AU1: =HAVERQ!V186 -> 2580 | AV1: =HAVERQ!W186 -> 141 | AW1: =HAVERQ!X186 -> 242 | AX1: =HAVERQ!Y186 -> 2227 | AY1: =HAVERQ!Z186 -> 4741 | AZ1: =HAVERQ!AA186 -> 1883 | ... BJ1: =HAVERQ!AK186 -> 1100 | BK1: =HAVERQ!AL186+HAVERQ!AK186 -> 2028 | BO1: Change in WFJ since 2019 | CK1: Unit wage costs & profits | CO1: BoE DMP | CW1: Measures of labour market health | CX1: Av | CY1: =AVERAGE(HAVERQ!AQ$128:AQ$183) -> 5.5214286 | CZ1: =AVERAGE(DL$5:DL$59) -> 1.6315868 | DA1: =AVERAGE(DO$5:DO$59) -> 9.6646096 | DB1: =AVERAGE(HAVERQ!AR$128:AR$183) -> 4.6142857 | DC1: =AVERAGE(DM$5:DM$59) -> 0.46379323 | DD1: =AVERAGE(DN$29:DN$59) -> 1.1947846 | DE1: =AVERAGE(HAVERQ!AZ$128:AZ$167,AZ$174:AZ$183) -> 31.9575 | DF1: =AVERAGE(HAVERQ!AS$128:AS$183) -> 0.9985119 | DG1: =AVERAGE(DP$5:DP$59) -> 2.9941664 | DH1: =AVERAGE(HAVERQ!AX$128:AX$183) -> 63.439286 | DJ1: =AVERAGE(DR$5:DR$59) -> 62.615979 | DU1: -ve | DV1: -ve | DW1: -ve | DX1: -ve
CP2: =RANK(CP5,$CP$5:$CU$5) -> 4 | CQ2: =RANK(CQ5,$CP$5:$CU$5) -> 3 | CR2: =RANK(CR5,$CP$5:$CU$5) -> 2 | CS2: =RANK(CS5,$CP$5:$CU$5) -> 1 | CT2: =RANK(CT5,$CP$5:$CU$5) -> 5 | CU2: =RANK(CU5,$CP$5:$CU$5) -> 6 | CX2: STDEV | CY2: =STDEV(HAVERQ!AQ$128:AQ$183) -> 1.6422506 | CZ2: =STDEV(DL$5:DL$59) -> 0.7489078 | DA2: =STDEV(DO$5:DO$59) -> 1.5084142 | DB2: =STDEV(HAVERQ!AR$128:AR$183) -> 1.8546677 | DC2: =STDEV(DM$5:DM$59) -> 0.23599838 | DD2: =STDEV(DN$29:DN$59) -> 1.4625982 | DE2: =STDEV(HAVERQ!AZ$128:AZ$167,AZ$174:AZ$183) -> 0.23302635 | DF2: =STDEV(HAVERQ!AS$128:AS$183) -> 1.8996791 | DG2: =STDEV(DP$5:DP$59) -> 1.942251 | DH2: =STDEV(HAVERQ!AZ$128:AZ$183) -> 1.0292965 | DJ2: =STDEV(DR$5:DR$59) -> 9.9243632
B3: Labour income | C3: Other | D3: Nominal household income | G3: Labour income | H3: Other | I3: Real household income | K3: PC | N3: Single month rate | O3: Three-month rate | R3: Single month range - min | S3: Range of single-month estimates | T3: Three-month rate | V3: Single month range - max | Y3: Public sector | Z3: Private sector | AC3: NHS | AD3: Education | AE3: Public administration | AF3: Police | AG3: HM forces | AH3: Other | AK3: NHS | AL3: Education | AM3: Public administration | AN3: Police | AO3: HM forces | AP3: Other | AS3: Agriculture | AT3: Extraction | AU3: Manufacturing | AV3: Utilities | AW3: Water | AX3: Construction | AY3: Wholesale & retail | AZ3: Transport | BA3: Accommodation & food | BB3: Communications | BC3: Financial services | BD3: Real estate | BE3: Professional services | BF3: Administrative services | BG3: Public admin | BH3: Education | BI3: Health | BJ3: Art & recreation | BK3: Other services | BM3: Other services | BP3: Agriculture | BQ3: Extraction & utilities | BR3: Manufacturing | BS3: Construction | BT3: Distribution, accommodation & food | BU3: Transport & comms | BV3: Financial services | BW3: Business services | BX3: Public services | BZ3: Agriculture | CA3: Extraction & utilities | CB3: Manufacturing | CC3: Construction | CD3: Distribution, accommodation & food | CE3: Transport & comms | CF3: Financial services | CG3: Business services | CH3: Public services | CI3: Check | CL3: Unit wage costs (LHS) | CM3: Corporate profits (RHS) | CP3: ='DMP - NICs Reaction'!B3 -> Lower employee wages | CQ3: ='DMP - NICs Reaction'!C3 -> Lower number of employees | CR3: ='DMP - NICs Reaction'!D3 -> Higher prices | CS3: ='DMP - NICs Reaction'!E3 -> Lower profit margins | CT3: ='DMP - NICs Reaction'!F3 -> Other | CU3: ='DMP - NICs Reaction'!G3 -> None of the above | CY3: Unemployment rate | CZ3: Unemployed >12 months | DA3: Underemployment | DB3: Redundancy rate | DC3: Vacancy/ Unemployed ratio | DD3: HMRC payroll employment | DE3: Average hours | DF3: BoE recruitment difficulties | DG3: Private sector regular pay growth | DH3: Participation rate | DJ3: BCC recruitment difficulties | DL3: Unemployed >12 months | DM3: V/U ratio | DN3: Employment growth | DO3: Underemployment rate | DP3: Private sector regular pay growth | DR3: BCC recruitment difficulties | DU3: =CY3&"*" -> Unemployment rate* | DV3: =CZ3&"*" -> Unemployed >12 months* | DW3: =DA3&"*" -> Underemployment* | DX3: =DB3&"*" -> Redundancy rate* | DY3: =DC3&"*" -> Vacancy/ Unemployed ratio* | DZ3: =DE3&"*" -> Average hours* | EA3: =DD3 -> HMRC payroll employment | EB3: =DF3 -> BoE recruitment difficulties | EC3: =DG3 -> Private sector regular pay growth | ED3: =DH3&"*" -> Participation rate* | EF3: =DJ3 -> BCC recruitment difficulties
A4: 2014 | B4: =100*((DataA!G48-DataA!G47)/DataA!H47) -> 2.2545386 | C4: =D4-B4 -> 1.2449333 | D4: =100*((DataA!H48/DataA!H47)-1) -> 3.4994719 | F4: 2014 | G4: =B4-K4 -> 1.0973014 | H4: =I4-G4 -> 1.1592146 | I4: =100*((DataA!I48/DataA!I47)-1) -> 2.2565161 | K4: =100*((DataA!J48/DataA!J47)-1) -> 1.1572372 | M4: 42370 | N4: =HAVERM!C439 -> 4.926 | O4: =HAVERM!B439 -> 5.1 | Q4: 42370 | R4: =MIN(HAVERM!C438:C440) -> 4.926 | S4: =V4-R4 -> 0.327 | T4: =HAVERM!B439 -> 5.1 | V4: =MAX(HAVERM!C438:C440) -> 5.253 | X4: 43466 | Y4: =HAVERQ!E164-AVERAGE(HAVERQ!E$164:E$167) -> -30.75 | Z4: =HAVERQ!F164-AVERAGE(HAVERQ!F$164:F$167) -> -64.75 | AB4: 36526 | AC4: =HAVERQ!P88 -> 1197 | AD4: =HAVERQ!O88 -> 1406 | AE4: =HAVERQ!N88 -> 1184 | AF4: =HAVERQ!M88 -> 225 | AG4: =HAVERQ!L88 -> 217 | AH4: =HAVERQ!E88-AC4-AD4-AE4-AF4-AG4 -> 800 | AJ4: 36526 | AK4: =100*(AC4/SUM($AC4:$AH4)) -> 23.801949 | AL4: =100*(AD4/SUM($AC4:$AH4)) -> 27.957845 | AM4: =100*(AE4/SUM($AC4:$AH4)) -> 23.543448 | AN4: =100*(AF4/SUM($AC4:$AH4)) -> 4.4740505 | AO4: =100*(AG4/SUM($AC4:$AH4)) -> 4.3149732 | AP4: =100*(AH4/SUM($AC4:$AH4)) -> 15.907735 | AR4: 43466 | AS4: =HAVERQ!T164-AVERAGE(HAVERQ!T$164:T$167) -> -11.25 | AT4: =HAVERQ!U164-AVERAGE(HAVERQ!U$164:U$167) -> 0.75 | AU4: =HAVERQ!V164-AVERAGE(HAVERQ!V$164:V$167) -> 14.25 | AV4: =HAVERQ!W164-AVERAGE(HAVERQ!W$164:W$167) -> -0.75 | AW4: =HAVERQ!X164-AVERAGE(HAVERQ!X$164:X$167) -> 5.5 | AX4: =HAVERQ!Y164-AVERAGE(HAVERQ!Y$164:Y$167) -> 27.75 | AY4: =HAVERQ!Z164-AVERAGE(HAVERQ!Z$164:Z$167) -> 27.5 | AZ4: =HAVERQ!AA164-AVERAGE(HAVERQ!AA$164:AA$167) -> -20 | ... BJ4: =HAVERQ!AK164-AVERAGE(HAVERQ!AK$164:AK$167) -> -5.75 | BK4: =BM4-AVERAGE(BM$4:BM$7) -> -9.5 | BM4: =HAVERQ!AL164+HAVERQ!AM164 -> 1008 | BO4: 43466 | BP4: =BZ4-AVERAGE(BZ$4:BZ$7) -> -11.25 | BQ4: =CA4-AVERAGE(CA$4:CA$7) -> 5.5 | BR4: =CB4-AVERAGE(CB$4:CB$7) -> 14.25 | BS4: =CC4-AVERAGE(CC$4:CC$7) -> 27.75 | BT4: =CD4-AVERAGE(CD$4:CD$7) -> -5.5 | BU4: =CE4-AVERAGE(CE$4:CE$7) -> -36.25 | BV4: =CF4-AVERAGE(CF$4:CF$7) -> -3.25 | BW4: =CG4-AVERAGE(CG$4:CG$7) -> -57.25 | BX4: =CH4-AVERAGE(CH$4:CH$7) -> -59.25 | BZ4: =HAVERQ!T164 -> 387 | CA4: =HAVERQ!U164+HAVERQ!W164+HAVERQ!X164 -> 431 | CB4: =HAVERQ!V164 -> 2705 | CC4: =HAVERQ!Y164 -> 2361 | CD4: =HAVERQ!Z164+HAVERQ!AB164 -> 7499 | CE4: =HAVERQ!AA164+HAVERQ!AC164 -> 3270 | CF4: =HAVERQ!AD164 -> 1132 | CG4: =HAVERQ!AE164+HAVERQ!AF164+HAVERQ!AG164 -> 6774 | CH4: =HAVERQ!AH164+HAVERQ!AI164+HAVERQ!AJ164+HAVERQ!AK164+HAVERQ!AL164+HAVERQ!AM164 -> 10881 | CI4: =HAVERQ!S164-SUM('Chart Data'!BZ4:CH4) -> -2 | CK4: 2012 | CL4: =100*((DataQ!F163/DataQ!F159)-1) -> -1.0460326 | CM4: =100*(DataQ!I163/DataQ!J163) -> 21.990625 | CO4: ='DMP - NICs Reaction'!A4 -> 45597 | CP4: ='DMP - NICs Reaction'!B4 -> 37.88 | CQ4: ='DMP - NICs Reaction'!C4 -> 53.68 | CR4: ='DMP - NICs Reaction'!D4 -> 53.64 | CS4: ='DMP - NICs Reaction'!E4 -> 58.72 | CT4: ='DMP - NICs Reaction'!F4 -> 7.51 | CU4: ='DMP - NICs Reaction'!G4 -> 2.67 | CX4: 2010 | CY4: =(HAVERQ!AQ128-AVERAGE(HAVERQ!AQ$128:AQ$183))/STDEV(HAVERQ!AQ$128:AQ$183) -> 1.5092529 | CZ4: =(DL4-AVERAGE(DL$5:DL$59))/STDEV(DL$5:DL$59) -> 1.0741155 | DA4: =(DO4-AVERAGE(DO$5:DO$59))/STDEV(DO$5:DO$59) -> 0.90570461 | DB4: =(HAVERQ!AR128-AVERAGE(HAVERQ!AR$128:AR$183))/STDEV(HAVERQ!AR$128:AR$183) -> 1.3402478 | DC4: =(DM4-AVERAGE(DM$5:DM$59))/STDEV(DM$5:DM$59) -> -1.2243516 | DD4: =(DN4-AVERAGE(DN$29:DN$59))/STDEV(DN$29:DN$59) -> #N/A | DE4: =(HAVERQ!AZ128-AVERAGE(HAVERQ!AZ$128:AZ$183))/STDEV(HAVERQ!AZ$128:AZ$183) -> -0.026023322 | DF4: =(HAVERQ!AS128-AVERAGE(HAVERQ!AS$128:AS$183))/STDEV(HAVERQ!AS$128:AS$183) -> -2.052195 | DG4: =(DP4-AVERAGE(DP$5:DP$59))/STDEV(DP$5:DP$59) -> -1.0724467 | DH4: =(HAVERQ!AX128-AVERAGE(HAVERQ!AX$128:AX$183))/STDEV(HAVERQ!AX$128:AX$183) -> -1.3285019 | DJ4: =(DR4-AVERAGE(DR$5:DR$59))/STDEV(DR$5:DR$59) -> -1.9765479 | DL4: =100*(HAVERQ!AV128/(HAVERQ!AW128*HAVERQ!AX128/100)) -> 2.4360003 | DM4: =HAVERQ!AO128/HAVERQ!AP128 -> 0.17484824 | DN4: =100*((AVERAGE(HAVERQ!BC125:BC128)/AVERAGE(HAVERQ!BC121:BC124))-1) -> #N/A | DO4: =100*(HAVERQ!BE128+HAVERQ!BF128)/(HAVERQ!BB128+HAVERQ!BG128) -> 11.030787 | DP4: =100*((AVERAGE(HAVERQ!BA125:BA128)/AVERAGE(HAVERQ!BA121:BA124))-1) -> 0.91120589 | DR4: =(HAVERQ!AT128*HAVERQ!$AT$1)+(HAVERQ!AU128*HAVERQ!$AU$1) -> 43 | DT4: Latest (Q3 2024) | DU4: =-CY62 -> 0.74375286 | DV4: =-CZ62 -> 0.88680621 | DW4: =-DA62 -> 1.1066331 | DX4: =-DB62 -> 0.76255478 | DY4: =DC62 -> 0.43375455 | DZ4: =DE62 -> 0.61151881 | EA4: =DD62 -> -0.10928383 | EB4: =DF62 -> 0.00078334033 | EC4: =DG62 -> 1.2174405 | ED4: =DH62 -> -0.72365552 | EF4: =DJ62 -> 1.2019085
A5: 2015 | B5: =100*((DataA!G49-DataA!G48)/DataA!H48) -> 2.0418208 | C5: =D5-B5 -> 3.649196 | D5: =100*((DataA!H49/DataA!H48)-1) -> 5.6910168 | F5: 2015 | G5: =B5-K5 -> 2.4131255 | H5: =I5-G5 -> 3.6485662 | I5: =100*((DataA!I49/DataA!I48)-1) -> 6.0616917 | K5: =100*((DataA!J49/DataA!J48)-1) -> -0.37130467 | M5: 42401 | N5: =HAVERM!C440 -> 5.116 | O5: =HAVERM!B440 -> 5.1 | Q5: 42401 | R5: =MIN(HAVERM!C439:C441) -> 4.926 | S5: =V5-R5 -> 0.24 | T5: =HAVERM!B440 -> 5.1 | V5: =MAX(HAVERM!C439:C441) -> 5.166 | X5: 43556 | Y5: =HAVERQ!E165-AVERAGE(HAVERQ!E$164:E$167) -> -10.75 | Z5: =HAVERQ!F165-AVERAGE(HAVERQ!F$164:F$167) -> -22.75 | AB5: 36617 | AC5: =HAVERQ!P89 -> 1204 | AD5: =HAVERQ!O89 -> 1441 | AE5: =HAVERQ!N89 -> 1178 | AF5: =HAVERQ!M89 -> 225 | AG5: =HAVERQ!L89 -> 217 | AH5: =HAVERQ!E89-AC5-AD5-AE5-AF5-AG5 -> 784 | AJ5: 36617 | AK5: =100*(AC5/SUM($AC5:$AH5)) -> 23.846306 | AL5: =100*(AD5/SUM($AC5:$AH5)) -> 28.540305 | AM5: =100*(AE5/SUM($AC5:$AH5)) -> 23.331353 | AN5: =100*(AF5/SUM($AC5:$AH5)) -> 4.456328 | AO5: =100*(AG5/SUM($AC5:$AH5)) -> 4.2978808 | AP5: =100*(AH5/SUM($AC5:$AH5)) -> 15.527827 | AR5: 43556 | AS5: =HAVERQ!T165-AVERAGE(HAVERQ!T$164:T$167) -> -0.25 | AT5: =HAVERQ!U165-AVERAGE(HAVERQ!U$164:U$167) -> -1.25 | AU5: =HAVERQ!V165-AVERAGE(HAVERQ!V$164:V$167) -> -1.75 | AV5: =HAVERQ!W165-AVERAGE(HAVERQ!W$164:W$167) -> -0.75 | AW5: =HAVERQ!X165-AVERAGE(HAVERQ!X$164:X$167) -> 0.5 | AX5: =HAVERQ!Y165-AVERAGE(HAVERQ!Y$164:Y$167) -> 5.75 | AY5: =HAVERQ!Z165-AVERAGE(HAVERQ!Z$164:Z$167) -> 11.5 | AZ5: =HAVERQ!AA165-AVERAGE(HAVERQ!AA$164:AA$167) -> 13 | ... BJ5: =HAVERQ!AK165-AVERAGE(HAVERQ!AK$164:AK$167) -> -9.75 | BK5: =BM5-AVERAGE(BM$4:BM$7) -> -8.5 | BM5: =HAVERQ!AL165+HAVERQ!AM165 -> 1009 | BO5: 43556 | BP5: =BZ5-AVERAGE(BZ$4:BZ$7) -> -0.25 | BQ5: =CA5-AVERAGE(CA$4:CA$7) -> -1.5 | BR5: =CB5-AVERAGE(CB$4:CB$7) -> -1.75 | BS5: =CC5-AVERAGE(CC$4:CC$7) -> 5.75 | BT5: =CD5-AVERAGE(CD$4:CD$7) -> 24.5 | BU5: =CE5-AVERAGE(CE$4:CE$7) -> 1.75 | BV5: =CF5-AVERAGE(CF$4:CF$7) -> -0.25 | BW5: =CG5-AVERAGE(CG$4:CG$7) -> -8.25 | BX5: =CH5-AVERAGE(CH$4:CH$7) -> -40.25 | BZ5: =HAVERQ!T165 -> 398 | CA5: =HAVERQ!U165+HAVERQ!W165+HAVERQ!X165 -> 424 | CB5: =HAVERQ!V165 -> 2689 | CC5: =HAVERQ!Y165 -> 2339 | CD5: =HAVERQ!Z165+HAVERQ!AB165 -> 7529 | CE5: =HAVERQ!AA165+HAVERQ!AC165 -> 3308 | CF5: =HAVERQ!AD165 -> 1135 | CG5: =HAVERQ!AE165+HAVERQ!AF165+HAVERQ!AG165 -> 6823 | CH5: =HAVERQ!AH165+HAVERQ!AI165+HAVERQ!AJ165+HAVERQ!AK165+HAVERQ!AL165+HAVERQ!AM165 -> 10900 | CI5: =HAVERQ!S165-SUM('Chart Data'!BZ5:CH5) -> 1 | CL5: =100*((DataQ!F164/DataQ!F160)-1) -> 0.71283454 | CM5: =100*(DataQ!I164/DataQ!J164) -> 21.877964 | CO5: ='DMP - NICs Reaction'!A5 -> 45627 | CP5: ='DMP - NICs Reaction'!B5 -> 40.67 | CQ5: ='DMP - NICs Reaction'!C5 -> 52.76 | CR5: ='DMP - NICs Reaction'!D5 -> 54.45 | CS5: ='DMP - NICs Reaction'!E5 -> 63.5 | CT5: ='DMP - NICs Reaction'!F5 -> 7.33 | CU5: ='DMP - NICs Reaction'!G5 -> 3.75 | CY5: =(HAVERQ!AQ129-AVERAGE(HAVERQ!AQ$128:AQ$183))/STDEV(HAVERQ!AQ$128:AQ$183) -> 1.4483608 | CZ5: =(DL5-AVERAGE(DL$5:DL$59))/STDEV(DL$5:DL$59) -> 1.204019 | DA5: =(DO5-AVERAGE(DO$5:DO$59))/STDEV(DO$5:DO$59) -> 0.80200723 | DB5: =(HAVERQ!AR129-AVERAGE(HAVERQ!AR$128:AR$183))/STDEV(HAVERQ!AR$128:AR$183) -> 0.80106765 | DC5: =(DM5-AVERAGE(DM$5:DM$59))/STDEV(DM$5:DM$59) -> -1.1295838 | DD5: =(DN5-AVERAGE(DN$29:DN$59))/STDEV(DN$29:DN$59) -> #N/A | DE5: =(HAVERQ!AZ129-AVERAGE(HAVERQ!AZ$128:AZ$167,AZ$174:AZ$183))/STDEV(HAVERQ!AZ$128:AZ$167,AZ$174:AZ$183) -> -1.5341612 | DF5: =(HAVERQ!AS129-AVERAGE(HAVERQ!AS$128:AS$183))/STDEV(HAVERQ!AS$128:AS$183) -> -1.753899 | DG5: =(DP5-AVERAGE(DP$5:DP$59))/STDEV(DP$5:DP$59) -> -1.1127899 | DH5: =(HAVERQ!AX129-AVERAGE(HAVERQ!AX$128:AX$183))/STDEV(HAVERQ!AX$128:AX$183) -> -0.72365552 | DJ5: =(DR5-AVERAGE(DR$5:DR$59))/STDEV(DR$5:DR$59) -> -1.0305242 | DL5: =100*(HAVERQ!AV129/(HAVERQ!AW129*HAVERQ!AX129/100)) -> 2.5332861 | DM5: =HAVERQ!AO129/HAVERQ!AP129 -> 0.19721329 | DN5: =100*((AVERAGE(HAVERQ!BC126:BC129)/AVERAGE(HAVERQ!BC122:BC125))-1) -> #N/A | DO5: =100*(HAVERQ!BE129+HAVERQ!BF129)/(HAVERQ!BB129+HAVERQ!BG129) -> 10.874369 | DP5: =100*((AVERAGE(HAVERQ!BA126:BA129)/AVERAGE(HAVERQ!BA122:BA125))-1) -> 0.83284912 | DR5: =(HAVERQ!AT129*HAVERQ!$AT$1)+(HAVERQ!AU129*HAVERQ!$AU$1) -> 52.388683 | DT5: 2023 | DU5: =-AVERAGE(CY$56:CY$59) -> 0.89598297 | DV5: =-AVERAGE(CZ$56:CZ$59) -> 1.0785846 | DW5: =-AVERAGE(DA$56:DA$59) -> 1.3531895 | DX5: =-AVERAGE(DB$56:DB$59) -> 0.72211627 | DY5: =AVERAGE(DC$56:DC$59) -> 1.0951349 | DZ5: =AVERAGE(DE$56:DE$59) -> -1.4268772 | EA5: =AVERAGE(DD$56:DD$59) -> 0.68602673 | EB5: =AVERAGE(DF$56:DF$59) -> 0.52718804 | EC5: =AVERAGE(DG$56:DG$59) -> 1.9522052 | ED5: =AVERAGE(DH$56:DH$59) -> -0.95047292 | EF5: =AVERAGE(DJ$56:DJ$59) -> 1.3393442
A6: 2016 | B6: =100*((DataA!G50-DataA!G49)/DataA!H49) -> 2.0449227 | C6: =D6-B6 -> -0.089021233 | D6: =100*((DataA!H50/DataA!H49)-1) -> 1.9559014 | F6: 2016 | G6: =B6-K6 -> 0.77782891 | H6: =I6-G6 -> -0.083554616 | I6: =100*((DataA!I50/DataA!I49)-1) -> 0.6942743 | K6: =100*((DataA!J50/DataA!J49)-1) -> 1.2670938 | M6: 42430 | N6: =HAVERM!C441 -> 5.166 | O6: =HAVERM!B441 -> 5 | Q6: 42430 | R6: =MIN(HAVERM!C440:C442) -> 4.728 | S6: =V6-R6 -> 0.438 | T6: =HAVERM!B441 -> 5 | V6: =MAX(HAVERM!C440:C442) -> 5.166 | X6: 43647 | Y6: =HAVERQ!E166-AVERAGE(HAVERQ!E$164:E$167) -> 13.25 | Z6: =HAVERQ!F166-AVERAGE(HAVERQ!F$164:F$167) -> -47.75 | AB6: 36708 | AC6: =HAVERQ!P90 -> 1213 | AD6: =HAVERQ!O90 -> 1455 | AE6: =HAVERQ!N90 -> 1177 | AF6: =HAVERQ!M90 -> 226 | AG6: =HAVERQ!L90 -> 216 | AH6: =HAVERQ!E90-AC6-AD6-AE6-AF6-AG6 -> 785 | AJ6: 36708 | AK6: =100*(AC6/SUM($AC6:$AH6)) -> 23.915615 | AL6: =100*(AD6/SUM($AC6:$AH6)) -> 28.686909 | AM6: =100*(AE6/SUM($AC6:$AH6)) -> 23.205836 | AN6: =100*(AF6/SUM($AC6:$AH6)) -> 4.455836 | AO6: =100*(AG6/SUM($AC6:$AH6)) -> 4.2586751 | AP6: =100*(AH6/SUM($AC6:$AH6)) -> 15.477129 | AR6: 43647 | AS6: =HAVERQ!T166-AVERAGE(HAVERQ!T$164:T$167) -> 4.75 | AT6: =HAVERQ!U166-AVERAGE(HAVERQ!U$164:U$167) -> -0.25 | AU6: =HAVERQ!V166-AVERAGE(HAVERQ!V$164:V$167) -> 3.25 | AV6: =HAVERQ!W166-AVERAGE(HAVERQ!W$164:W$167) -> -2.75 | AW6: =HAVERQ!X166-AVERAGE(HAVERQ!X$164:X$167) -> -2.5 | AX6: =HAVERQ!Y166-AVERAGE(HAVERQ!Y$164:Y$167) -> -25.25 | AY6: =HAVERQ!Z166-AVERAGE(HAVERQ!Z$164:Z$167) -> -4.5 | AZ6: =HAVERQ!AA166-AVERAGE(HAVERQ!AA$164:AA$167) -> 2 | ... BJ6: =HAVERQ!AK166-AVERAGE(HAVERQ!AK$164:AK$167) -> 2.25 | BK6: =BM6-AVERAGE(BM$4:BM$7) -> 1.5 | BM6: =HAVERQ!AL166+HAVERQ!AM166 -> 1019 | BO6: 43647 | BP6: =BZ6-AVERAGE(BZ$4:BZ$7) -> 4.75 | BQ6: =CA6-AVERAGE(CA$4:CA$7) -> -5.5 | BR6: =CB6-AVERAGE(CB$4:CB$7) -> 3.25 | BS6: =CC6-AVERAGE(CC$4:CC$7) -> -25.25 | BT6: =CD6-AVERAGE(CD$4:CD$7) -> 2.5 | BU6: =CE6-AVERAGE(CE$4:CE$7) -> 1.75 | BV6: =CF6-AVERAGE(CF$4:CF$7) -> 7.75 | BW6: =CG6-AVERAGE(CG$4:CG$7) -> 39.75 | BX6: =CH6-AVERAGE(CH$4:CH$7) -> 21.75 | BZ6: =HAVERQ!T166 -> 403 | CA6: =HAVERQ!U166+HAVERQ!W166+HAVERQ!X166 -> 420 | CB6: =HAVERQ!V166 -> 2694 | CC6: =HAVERQ!Y166 -> 2308 | CD6: =HAVERQ!Z166+HAVERQ!AB166 -> 7507 | CE6: =HAVERQ!AA166+HAVERQ!AC166 -> 3308 | CF6: =HAVERQ!AD166 -> 1143 | CG6: =HAVERQ!AE166+HAVERQ!AF166+HAVERQ!AG166 -> 6871 | CH6: =HAVERQ!AH166+HAVERQ!AI166+HAVERQ!AJ166+HAVERQ!AK166+HAVERQ!AL166+HAVERQ!AM166 -> 10962 | CI6: =HAVERQ!S166-SUM('Chart Data'!BZ6:CH6) -> -1 | CL6: =100*((DataQ!F165/DataQ!F161)-1) -> 0.63328293 | CM6: =100*(DataQ!I165/DataQ!J165) -> 22.746912 | CY6: =(HAVERQ!AQ130-AVERAGE(HAVERQ!AQ$128:AQ$183))/STDEV(HAVERQ!AQ$128:AQ$183) -> 1.3874688 | CZ6: =(DL6-AVERAGE(DL$5:DL$59))/STDEV(DL$5:DL$59) -> 1.2695637 | DA6: =(DO6-AVERAGE(DO$5:DO$59))/STDEV(DO$5:DO$59) -> 1.014221 | DB6: =(HAVERQ!AR130-AVERAGE(HAVERQ!AR$128:AR$183))/STDEV(HAVERQ!AR$128:AR$183) -> 0.63931361 | DC6: =(DM6-AVERAGE(DM$5:DM$59))/STDEV(DM$5:DM$59) -> -1.1583761 | DD6: =(DN6-AVERAGE(DN$29:DN$59))/STDEV(DN$29:DN$59) -> #N/A | DE6: =(HAVERQ!AZ130-AVERAGE(HAVERQ!AZ$128:AZ$167,AZ$174:AZ$183))/STDEV(HAVERQ!AZ$128:AZ$167,AZ$174:AZ$183) -> -1.5341612 | DF6: =(HAVERQ!AS130-AVERAGE(HAVERQ!AS$128:AS$183))/STDEV(HAVERQ!AS$128:AS$183) -> -1.3678689 | DG6: =(DP6-AVERAGE(DP$5:DP$59))/STDEV(DP$5:DP$59) -> -0.8528448 | DH6: =(HAVERQ!AX130-AVERAGE(HAVERQ!AX$128:AX$183))/STDEV(HAVERQ!AX$128:AX$183) -> -0.11880912 | DJ6: =(DR6-AVERAGE(DR$5:DR$59))/STDEV(DR$5:DR$59) -> -1.4090085 | DL6: =100*(HAVERQ!AV130/(HAVERQ!AW130*HAVERQ!AX130/100)) -> 2.582373 | DM6: =HAVERQ!AO130/HAVERQ!AP130 -> 0.19041835 | DN6: =100*((AVERAGE(HAVERQ!BC127:BC130)/AVERAGE(HAVERQ!BC123:BC126))-1) -> #N/A | DO6: =100*(HAVERQ!BE130+HAVERQ!BF130)/(HAVERQ!BB130+HAVERQ!BG130) -> 11.194475 | DP6: =100*((AVERAGE(HAVERQ!BA127:BA130)/AVERAGE(HAVERQ!BA123:BA126))-1) -> 1.3377278 | DR6: =(HAVERQ!AT130*HAVERQ!$AT$1)+(HAVERQ!AU130*HAVERQ!$AU$1) -> 48.632467 | DT6: 2019 | DU6: =-AVERAGE(CY$40:CY$44) -> 0.99949945 | DV6: =-AVERAGE(CZ$40:CZ$44) -> 0.9306432 | DW6: =-AVERAGE(DA$40:DA$44) -> 0.99695734 | DX6: =-AVERAGE(DB$40:DB$44) -> 0.42826309 | DY6: =AVERAGE(DC$40:DC$44) -> 0.62782346 | DZ6: =AVERAGE(DE$40:DE$44) -> -0.33258041 | EA6: =AVERAGE(DD$40:DD$44) -> -0.086403277 | EB6: =AVERAGE(DF$40:DF$44) -> 0.99568823 | EC6: =AVERAGE(DG$40:DG$44) -> 0.21155322 | ED6: =AVERAGE(DH$40:DH$44) -> 1.9981533 | EF6: =AVERAGE(DJ$40:DJ$44) -> 0.66405934
A7: 2017 | B7: =100*((DataA!G51-DataA!G50)/DataA!H50) -> 2.4443958 | C7: =D7-B7 -> 0.27841176 | D7: =100*((DataA!H51/DataA!H50)-1) -> 2.7228076 | F7: 2017 | G7: =B7-K7 -> 0.59145313 | H7: =I7-G7 -> 0.29775587 | I7: =100*((DataA!I51/DataA!I50)-1) -> 0.889209 | K7: =100*((DataA!J51/DataA!J50)-1) -> 1.8529427 | M7: 42461 | N7: =HAVERM!C442 -> 4.728 | O7: =HAVERM!B442 -> 4.9 | Q7: 42461 | R7: =MIN(HAVERM!C441:C443) -> 4.728 | S7: =V7-R7 -> 0.438 | T7: =HAVERM!B442 -> 4.9 | V7: =MAX(HAVERM!C441:C443) -> 5.166 | X7: 43739 | Y7: =HAVERQ!E167-AVERAGE(HAVERQ!E$164:E$167) -> 28.25 | Z7: =HAVERQ!F167-AVERAGE(HAVERQ!F$164:F$167) -> 135.25 | AB7: 36800 | AC7: =HAVERQ!P91 -> 1223 | AD7: =HAVERQ!O91 -> 1457 | AE7: =HAVERQ!N91 -> 1177 | AF7: =HAVERQ!M91 -> 227 | AG7: =HAVERQ!L91 -> 215 | AH7: =HAVERQ!E91-AC7-AD7-AE7-AF7-AG7 -> 782 | AJ7: 36800 | AK7: =100*(AC7/SUM($AC7:$AH7)) -> 24.070065 | AL7: =100*(AD7/SUM($AC7:$AH7)) -> 28.675458 | AM7: =100*(AE7/SUM($AC7:$AH7)) -> 23.164731 | AN7: =100*(AF7/SUM($AC7:$AH7)) -> 4.4676245 | AO7: =100*(AG7/SUM($AC7:$AH7)) -> 4.2314505 | AP7: =100*(AH7/SUM($AC7:$AH7)) -> 15.390671 | AR7: 43739 | AS7: =HAVERQ!T167-AVERAGE(HAVERQ!T$164:T$167) -> 6.75 | AT7: =HAVERQ!U167-AVERAGE(HAVERQ!U$164:U$167) -> 0.75 | AU7: =HAVERQ!V167-AVERAGE(HAVERQ!V$164:V$167) -> -15.75 | AV7: =HAVERQ!W167-AVERAGE(HAVERQ!W$164:W$167) -> 4.25 | AW7: =HAVERQ!X167-AVERAGE(HAVERQ!X$164:X$167) -> -3.5 | AX7: =HAVERQ!Y167-AVERAGE(HAVERQ!Y$164:Y$167) -> -8.25 | AY7: =HAVERQ!Z167-AVERAGE(HAVERQ!Z$164:Z$167) -> -34.5 | AZ7: =HAVERQ!AA167-AVERAGE(HAVERQ!AA$164:AA$167) -> 5 | ... BJ7: =HAVERQ!AK167-AVERAGE(HAVERQ!AK$164:AK$167) -> 13.25 | BK7: =BM7-AVERAGE(BM$4:BM$7) -> 16.5 | BM7: =HAVERQ!AL167+HAVERQ!AM167 -> 1034 | BO7: 43739 | BP7: =BZ7-AVERAGE(BZ$4:BZ$7) -> 6.75 | BQ7: =CA7-AVERAGE(CA$4:CA$7) -> 1.5 | BR7: =CB7-AVERAGE(CB$4:CB$7) -> -15.75 | BS7: =CC7-AVERAGE(CC$4:CC$7) -> -8.25 | BT7: =CD7-AVERAGE(CD$4:CD$7) -> -21.5 | BU7: =CE7-AVERAGE(CE$4:CE$7) -> 32.75 | BV7: =CF7-AVERAGE(CF$4:CF$7) -> -4.25 | BW7: =CG7-AVERAGE(CG$4:CG$7) -> 25.75 | BX7: =CH7-AVERAGE(CH$4:CH$7) -> 77.75 | BZ7: =HAVERQ!T167 -> 405 | CA7: =HAVERQ!U167+HAVERQ!W167+HAVERQ!X167 -> 427 | CB7: =HAVERQ!V167 -> 2675 | CC7: =HAVERQ!Y167 -> 2325 | CD7: =HAVERQ!Z167+HAVERQ!AB167 -> 7483 | CE7: =HAVERQ!AA167+HAVERQ!AC167 -> 3339 | CF7: =HAVERQ!AD167 -> 1131 | CG7: =HAVERQ!AE167+HAVERQ!AF167+HAVERQ!AG167 -> 6857 | CH7: =HAVERQ!AH167+HAVERQ!AI167+HAVERQ!AJ167+HAVERQ!AK167+HAVERQ!AL167+HAVERQ!AM167 -> 11018 | CI7: =HAVERQ!S167-SUM('Chart Data'!BZ7:CH7) -> 1 | CL7: =100*((DataQ!F166/DataQ!F162)-1) -> 1.2250741 | CM7: =100*(DataQ!I166/DataQ!J166) -> 22.658746 | CP7: 1 | CQ7: 2 | CR7: 3 | CS7: 4 | CT7: 5 | CU7: 6 | CY7: =(HAVERQ!AQ131-AVERAGE(HAVERQ!AQ$128:AQ$183))/STDEV(HAVERQ!AQ$128:AQ$183) -> 1.4483608 | CZ7: =(DL7-AVERAGE(DL$5:DL$59))/STDEV(DL$5:DL$59) -> 1.3354819 | DA7: =(DO7-AVERAGE(DO$5:DO$59))/STDEV(DO$5:DO$59) -> 1.0874051 | DB7: =(HAVERQ!AR131-AVERAGE(HAVERQ!AR$128:AR$183))/STDEV(HAVERQ!AR$128:AR$183) -> 0.69323162 | DC7: =(DM7-AVERAGE(DM$5:DM$59))/STDEV(DM$5:DM$59) -> -1.1470063 | DD7: =(DN7-AVERAGE(DN$29:DN$59))/STDEV(DN$29:DN$59) -> #N/A | DE7: =(HAVERQ!AZ131-AVERAGE(HAVERQ!AZ$128:AZ$167,AZ$174:AZ$183))/STDEV(HAVERQ!AZ$128:AZ$167,AZ$174:AZ$183) -> -0.67588921 | DF7: =(HAVERQ!AS131-AVERAGE(HAVERQ!AS$128:AS$183))/STDEV(HAVERQ!AS$128:AS$183) -> -1.157307 | DG7: =(DP7-AVERAGE(DP$5:DP$59))/STDEV(DP$5:DP$59) -> -0.58221745 | DH7: =(HAVERQ!AX131-AVERAGE(HAVERQ!AX$128:AX$183))/STDEV(HAVERQ!AX$128:AX$183) -> -0.72365552 | DJ7: =(DR7-AVERAGE(DR$5:DR$59))/STDEV(DR$5:DR$59) -> -1.3641422 | DL7: =100*(HAVERQ!AV131/(HAVERQ!AW131*HAVERQ!AX131/100)) -> 2.6317396 | DM7: =HAVERQ!AO131/HAVERQ!AP131 -> 0.19310161 | DN7: =100*((AVERAGE(HAVERQ!BC128:BC131)/AVERAGE(HAVERQ!BC124:BC127))-1) -> #N/A | DO7: =100*(HAVERQ!BE131+HAVERQ!BF131)/(HAVERQ!BB131+HAVERQ!BG131) -> 11.304867 | DP7: =100*((AVERAGE(HAVERQ!BA128:BA131)/AVERAGE(HAVERQ!BA124:BA127))-1) -> 1.863354 | DR7: =(HAVERQ!AT131*HAVERQ!$AT$1)+(HAVERQ!AU131*HAVERQ!$AU$1) -> 49.077737 | DT7: Post-2010 average | DU7: 0 | DV7: 0 | DW7: 0 | DX7: 0 | DY7: 0 | DZ7: 0 | EA7: 0 | EB7: 0 | EC7: 0 | ED7: 0 | EF7: 0
A8: 2018 | B8: =100*((DataA!G52-DataA!G51)/DataA!H51) -> 2.6151515 | C8: =D8-B8 -> 1.494945 | D8: =100*((DataA!H52/DataA!H51)-1) -> 4.1100965 | F8: 2018 | G8: =B8-K8 -> 0.51580887 | H8: =I8-G8 -> 1.4675349 | I8: =100*((DataA!I52/DataA!I51)-1) -> 1.9833437 | K8: =100*((DataA!J52/DataA!J51)-1) -> 2.0993427 | M8: 42491 | N8: =HAVERM!C443 -> 4.881 | O8: =HAVERM!B443 -> 4.9 | Q8: 42491 | R8: =MIN(HAVERM!C442:C444) -> 4.728 | S8: =V8-R8 -> 0.417 | T8: =HAVERM!B443 -> 4.9 | V8: =MAX(HAVERM!C442:C444) -> 5.145 | X8: 43831 | Y8: =HAVERQ!E168-AVERAGE(HAVERQ!E$164:E$167) -> 53.25 | Z8: =HAVERQ!F168-AVERAGE(HAVERQ!F$164:F$167) -> -172.75 | AB8: 36892 | AC8: =HAVERQ!P92 -> 1235 | AD8: =HAVERQ!O92 -> 1463 | AE8: =HAVERQ!N92 -> 1181 | AF8: =HAVERQ!M92 -> 228 | AG8: =HAVERQ!L92 -> 215 | AH8: =HAVERQ!E92-AC8-AD8-AE8-AF8-AG8 -> 785 | AJ8: 36892 | AK8: =100*(AC8/SUM($AC8:$AH8)) -> 24.182495 | AL8: =100*(AD8/SUM($AC8:$AH8)) -> 28.646955 | AM8: =100*(AE8/SUM($AC8:$AH8)) -> 23.125122 | AN8: =100*(AF8/SUM($AC8:$AH8)) -> 4.4644605 | AO8: =100*(AG8/SUM($AC8:$AH8)) -> 4.209908 | AP8: =100*(AH8/SUM($AC8:$AH8)) -> 15.371059 | AR8: 43831 | AS8: =HAVERQ!T168-AVERAGE(HAVERQ!T$164:T$167) -> -14.25 | AT8: =HAVERQ!U168-AVERAGE(HAVERQ!U$164:U$167) -> 6.75 | AU8: =HAVERQ!V168-AVERAGE(HAVERQ!V$164:V$167) -> -14.75 | AV8: =HAVERQ!W168-AVERAGE(HAVERQ!W$164:W$167) -> 5.25 | AW8: =HAVERQ!X168-AVERAGE(HAVERQ!X$164:X$167) -> -3.5 | AX8: =HAVERQ!Y168-AVERAGE(HAVERQ!Y$164:Y$167) -> -40.25 | AY8: =HAVERQ!Z168-AVERAGE(HAVERQ!Z$164:Z$167) -> -67.5 | AZ8: =HAVERQ!AA168-AVERAGE(HAVERQ!AA$164:AA$167) -> 1 | ... BJ8: =HAVERQ!AK168-AVERAGE(HAVERQ!AK$164:AK$167) -> -4.75 | BK8: =BM8-AVERAGE(BM$4:BM$7) -> -28.5 | BM8: =HAVERQ!AL168+HAVERQ!AM168 -> 989 | BO8: 43831 | BP8: =BZ8-AVERAGE(BZ$4:BZ$7) -> -14.25 | BQ8: =CA8-AVERAGE(CA$4:CA$7) -> 8.5 | BR8: =CB8-AVERAGE(CB$4:CB$7) -> -14.75 | BS8: =CC8-AVERAGE(CC$4:CC$7) -> -40.25 | BT8: =CD8-AVERAGE(CD$4:CD$7) -> -47.5 | BU8: =CE8-AVERAGE(CE$4:CE$7) -> 49.75 | BV8: =CF8-AVERAGE(CF$4:CF$7) -> 1.75 | BW8: =CG8-AVERAGE(CG$4:CG$7) -> 66.75 | BX8: =CH8-AVERAGE(CH$4:CH$7) -> 34.75 | BZ8: =HAVERQ!T168 -> 384 | CA8: =HAVERQ!U168+HAVERQ!W168+HAVERQ!X168 -> 434 | CB8: =HAVERQ!V168 -> 2676 | CC8: =HAVERQ!Y168 -> 2293 | CD8: =HAVERQ!Z168+HAVERQ!AB168 -> 7457 | CE8: =HAVERQ!AA168+HAVERQ!AC168 -> 3356 | CF8: =HAVERQ!AD168 -> 1137 | CG8: =HAVERQ!AE168+HAVERQ!AF168+HAVERQ!AG168 -> 6898 | CH8: =HAVERQ!AH168+HAVERQ!AI168+HAVERQ!AJ168+HAVERQ!AK168+HAVERQ!AL168+HAVERQ!AM168 -> 10975 | CI8: =HAVERQ!S168-SUM('Chart Data'!BZ8:CH8) -> -1 | CK8: 2013 | CL8: =100*((DataQ!F167/DataQ!F163)-1) -> 0.66949357 | CM8: =100*(DataQ!I167/DataQ!J167) -> 22.990853 | CP8: =HLOOKUP(CP$7,$CP$2:$CU$5,2,FALSE) -> Lower profit margins | CQ8: =HLOOKUP(CQ$7,$CP$2:$CU$5,2,FALSE) -> Higher prices | CR8: =HLOOKUP(CR$7,$CP$2:$CU$5,2,FALSE) -> Lower number of employees | CS8: =HLOOKUP(CS$7,$CP$2:$CU$5,2,FALSE) -> Lower employee wages | CT8: =HLOOKUP(CT$7,$CP$2:$CU$5,2,FALSE) -> Other | CU8: =HLOOKUP(CU$7,$CP$2:$CU$5,2,FALSE) -> None of the above | CX8: 2011 | CY8: =(HAVERQ!AQ132-AVERAGE(HAVERQ!AQ$128:AQ$183))/STDEV(HAVERQ!AQ$128:AQ$183) -> 1.3874688 | CZ8: =(DL8-AVERAGE(DL$5:DL$59))/STDEV(DL$5:DL$59) -> 1.415412 | DA8: =(DO8-AVERAGE(DO$5:DO$59))/STDEV(DO$5:DO$59) -> 1.0314069 | DB8: =(HAVERQ!AR132-AVERAGE(HAVERQ!AR$128:AR$183))/STDEV(HAVERQ!AR$128:AR$183) -> 0.15405147 | DC8: =(DM8-AVERAGE(DM$5:DM$59))/STDEV(DM$5:DM$59) -> -1.1819412 | DD8: =(DN8-AVERAGE(DN$29:DN$59))/STDEV(DN$29:DN$59) -> #N/A | DE8: =(HAVERQ!AZ132-AVERAGE(HAVERQ!AZ$128:AZ$167,AZ$174:AZ$183))/STDEV(HAVERQ!AZ$128:AZ$167,AZ$174:AZ$183) -> -1.1050252 | DF8: =(HAVERQ!AS132-AVERAGE(HAVERQ!AS$128:AS$183))/STDEV(HAVERQ!AS$128:AS$183) -> -0.96429195 | DG8: =(DP8-AVERAGE(DP$5:DP$59))/STDEV(DP$5:DP$59) -> -0.75025463 | DH8: =(HAVERQ!AX132-AVERAGE(HAVERQ!AX$128:AX$183))/STDEV(HAVERQ!AX$128:AX$183) -> -0.72365552 | DJ8: =(DR8-AVERAGE(DR$5:DR$59))/STDEV(DR$5:DR$59) -> -1.6810288 | DL8: =100*(HAVERQ!AV132/(HAVERQ!AW132*HAVERQ!AX132/100)) -> 2.6915999 | DM8: =HAVERQ!AO132/HAVERQ!AP132 -> 0.18485703 | DN8: =100*((AVERAGE(HAVERQ!BC129:BC132)/AVERAGE(HAVERQ!BC125:BC128))-1) -> #N/A | DO8: =100*(HAVERQ!BE132+HAVERQ!BF132)/(HAVERQ!BB132+HAVERQ!BG132) -> 11.220398 | DP8: =100*((AVERAGE(HAVERQ!BA129:BA132)/AVERAGE(HAVERQ!BA125:BA128))-1) -> 1.5369837 | DR8: =(HAVERQ!AT132*HAVERQ!$AT$1)+(HAVERQ!AU132*HAVERQ!$AU$1) -> 45.932838
A9: 2019 | B9: =100*((DataA!G53-DataA!G52)/DataA!H52) -> 2.1285774 | C9: =D9-B9 -> 1.4739322 | D9: =100*((DataA!H53/DataA!H52)-1) -> 3.6025096 | F9: 2019 | G9: =B9-K9 -> 0.64390525 | H9: =I9-G9 -> 1.409085 | I9: =100*((DataA!I53/DataA!I52)-1) -> 2.0529903 | K9: =100*((DataA!J53/DataA!J52)-1) -> 1.4846722 | M9: 42522 | N9: =HAVERM!C444 -> 5.145 | O9: =HAVERM!B444 -> 4.9 | Q9: 42522 | R9: =MIN(HAVERM!C443:C445) -> 4.657 | S9: =V9-R9 -> 0.488 | T9: =HAVERM!B444 -> 4.9 | V9: =MAX(HAVERM!C443:C445) -> 5.145 | X9: 43922 | Y9: =HAVERQ!E169-AVERAGE(HAVERQ!E$164:E$167) -> 97.25 | Z9: =HAVERQ!F169-AVERAGE(HAVERQ!F$164:F$167) -> -458.75 | AB9: 36982 | AC9: =HAVERQ!P93 -> 1249 | AD9: =HAVERQ!O93 -> 1468 | AE9: =HAVERQ!N93 -> 1185 | AF9: =HAVERQ!M93 -> 229 | AG9: =HAVERQ!L93 -> 214 | AH9: =HAVERQ!E93-AC9-AD9-AE9-AF9-AG9 -> 792 | AJ9: 36982 | AK9: =100*(AC9/SUM($AC9:$AH9)) -> 24.313802 | AL9: =100*(AD9/SUM($AC9:$AH9)) -> 28.57699 | AM9: =100*(AE9/SUM($AC9:$AH9)) -> 23.067938 | AN9: =100*(AF9/SUM($AC9:$AH9)) -> 4.4578548 | AO9: =100*(AG9/SUM($AC9:$AH9)) -> 4.1658556 | AP9: =100*(AH9/SUM($AC9:$AH9)) -> 15.417559 | AR9: 43922 | AS9: =HAVERQ!T169-AVERAGE(HAVERQ!T$164:T$167) -> -21.25 | AT9: =HAVERQ!U169-AVERAGE(HAVERQ!U$164:U$167) -> -0.25 | AU9: =HAVERQ!V169-AVERAGE(HAVERQ!V$164:V$167) -> -72.75 | AV9: =HAVERQ!W169-AVERAGE(HAVERQ!W$164:W$167) -> 4.25 | AW9: =HAVERQ!X169-AVERAGE(HAVERQ!X$164:X$167) -> -4.5 | AX9: =HAVERQ!Y169-AVERAGE(HAVERQ!Y$164:Y$167) -> -57.25 | AY9: =HAVERQ!Z169-AVERAGE(HAVERQ!Z$164:Z$167) -> -29.5 | AZ9: =HAVERQ!AA169-AVERAGE(HAVERQ!AA$164:AA$167) -> 1 | ... BJ9: =HAVERQ!AK169-AVERAGE(HAVERQ!AK$164:AK$167) -> -51.75 | BK9: =BM9-AVERAGE(BM$4:BM$7) -> -40.5 | BM9: =HAVERQ!AL169+HAVERQ!AM169 -> 977 | BO9: 43922 | BP9: =BZ9-AVERAGE(BZ$4:BZ$7) -> -21.25 | BQ9: =CA9-AVERAGE(CA$4:CA$7) -> -0.5 | BR9: =CB9-AVERAGE(CB$4:CB$7) -> -72.75 | BS9: =CC9-AVERAGE(CC$4:CC$7) -> -57.25 | BT9: =CD9-AVERAGE(CD$4:CD$7) -> -181.5 | BU9: =CE9-AVERAGE(CE$4:CE$7) -> 21.75 | BV9: =CF9-AVERAGE(CF$4:CF$7) -> -6.25 | BW9: =CG9-AVERAGE(CG$4:CG$7) -> -150.25 | BX9: =CH9-AVERAGE(CH$4:CH$7) -> 36.75 | BZ9: =HAVERQ!T169 -> 377 | CA9: =HAVERQ!U169+HAVERQ!W169+HAVERQ!X169 -> 425 | CB9: =HAVERQ!V169 -> 2618 | CC9: =HAVERQ!Y169 -> 2276 | CD9: =HAVERQ!Z169+HAVERQ!AB169 -> 7323 | CE9: =HAVERQ!AA169+HAVERQ!AC169 -> 3328 | CF9: =HAVERQ!AD169 -> 1129 | CG9: =HAVERQ!AE169+HAVERQ!AF169+HAVERQ!AG169 -> 6681 | CH9: =HAVERQ!AH169+HAVERQ!AI169+HAVERQ!AJ169+HAVERQ!AK169+HAVERQ!AL169+HAVERQ!AM169 -> 10977 | CI9: =HAVERQ!S169-SUM('Chart Data'!BZ9:CH9) -> 1 | CL9: =100*((DataQ!F168/DataQ!F164)-1) -> 2.583742 | CM9: =100*(DataQ!I168/DataQ!J168) -> 21.880591 | CO9: =CO4 -> 45597 | CP9: =HLOOKUP(CP$7,$CP$2:$CU$5,3,FALSE) -> 58.72 | CQ9: =HLOOKUP(CQ$7,$CP$2:$CU$5,3,FALSE) -> 53.64 | CR9: =HLOOKUP(CR$7,$CP$2:$CU$5,3,FALSE) -> 53.68 | CS9: =HLOOKUP(CS$7,$CP$2:$CU$5,3,FALSE) -> 37.88 | CT9: =HLOOKUP(CT$7,$CP$2:$CU$5,3,FALSE) -> 7.51 | CU9: =HLOOKUP(CU$7,$CP$2:$CU$5,3,FALSE) -> 2.67 | CY9: =(HAVERQ!AQ133-AVERAGE(HAVERQ!AQ$128:AQ$183))/STDEV(HAVERQ!AQ$128:AQ$183) -> 1.4483608 | CZ9: =(DL9-AVERAGE(DL$5:DL$59))/STDEV(DL$5:DL$59) -> 1.3530474 | DA9: =(DO9-AVERAGE(DO$5:DO$59))/STDEV(DO$5:DO$59) -> 1.0250466 | DB9: =(HAVERQ!AR133-AVERAGE(HAVERQ!AR$128:AR$183))/STDEV(HAVERQ!AR$128:AR$183) -> 0.85498567 | DC9: =(DM9-AVERAGE(DM$5:DM$59))/STDEV(DM$5:DM$59) -> -1.1850611 | DD9: =(DN9-AVERAGE(DN$29:DN$59))/STDEV(DN$29:DN$59) -> #N/A | DE9: =(HAVERQ!AZ133-AVERAGE(HAVERQ!AZ$128:AZ$167,AZ$174:AZ$183))/STDEV(HAVERQ!AZ$128:AZ$167,AZ$174:AZ$183) -> -2.8215693 | DF9: =(HAVERQ!AS133-AVERAGE(HAVERQ!AS$128:AS$183))/STDEV(HAVERQ!AS$128:AS$183) -> -0.85901101 | DG9: =(DP9-AVERAGE(DP$5:DP$59))/STDEV(DP$5:DP$59) -> -0.43393086 | DH9: =(HAVERQ!AX133-AVERAGE(HAVERQ!AX$128:AX$183))/STDEV(HAVERQ!AX$128:AX$183) -> -0.72365552 | DJ9: =(DR9-AVERAGE(DR$5:DR$59))/STDEV(DR$5:DR$59) -> -1.4795046 | DL9: =100*(HAVERQ!AV133/(HAVERQ!AW133*HAVERQ!AX133/100)) -> 2.6448946 | DM9: =HAVERQ!AO133/HAVERQ!AP133 -> 0.18412073 | DN9: =100*((AVERAGE(HAVERQ!BC130:BC133)/AVERAGE(HAVERQ!BC126:BC129))-1) -> #N/A | DO9: =100*(HAVERQ!BE133+HAVERQ!BF133)/(HAVERQ!BB133+HAVERQ!BG133) -> 11.210804 | DP9: =100*((AVERAGE(HAVERQ!BA130:BA133)/AVERAGE(HAVERQ!BA126:BA129))-1) -> 2.1513638 | DR9: =(HAVERQ!AT133*HAVERQ!$AT$1)+(HAVERQ!AU133*HAVERQ!$AU$1) -> 47.932838
A10: 2020 | B10: =100*((DataA!G54-DataA!G53)/DataA!H53) -> 0.0012388486 | C10: =D10-B10 -> 0.098281992 | D10: =100*((DataA!H54/DataA!H53)-1) -> 0.099520841 | F10: 2020 | G10: =B10-K10 -> -0.067846845 | H10: =I10-G10 -> -0.30916746 | I10: =100*((DataA!I54/DataA!I53)-1) -> -0.3770143 | K10: =100*((DataA!J54/DataA!J53)-1) -> 0.069085694 | M10: 42552 | N10: =HAVERM!C445 -> 4.657 | O10: =HAVERM!B445 -> 5 | Q10: 42552 | R10: =MIN(HAVERM!C444:C446) -> 4.657 | S10: =V10-R10 -> 0.488 | T10: =HAVERM!B445 -> 5 | V10: =MAX(HAVERM!C444:C446) -> 5.145 | X10: 44013 | Y10: =HAVERQ!E170-AVERAGE(HAVERQ!E$164:E$167) -> 104.25 | Z10: =HAVERQ!F170-AVERAGE(HAVERQ!F$164:F$167) -> -723.75 | AB10: 37073 | AC10: =HAVERQ!P94 -> 1263 | AD10: =HAVERQ!O94 -> 1465 | AE10: =HAVERQ!N94 -> 1188 | AF10: =HAVERQ!M94 -> 231 | AG10: =HAVERQ!L94 -> 214 | AH10: =HAVERQ!E94-AC10-AD10-AE10-AF10-AG10 -> 795 | AJ10: 37073 | AK10: =100*(AC10/SUM($AC10:$AH10)) -> 24.495733 | AL10: =100*(AD10/SUM($AC10:$AH10)) -> 28.413499 | AM10: =100*(AE10/SUM($AC10:$AH10)) -> 23.041117 | AN10: =100*(AF10/SUM($AC10:$AH10)) -> 4.4802172 | AO10: =100*(AG10/SUM($AC10:$AH10)) -> 4.1505043 | AP10: =100*(AH10/SUM($AC10:$AH10)) -> 15.418929 | AR10: 44013 | AS10: =HAVERQ!T170-AVERAGE(HAVERQ!T$164:T$167) -> 18.75 | AT10: =HAVERQ!U170-AVERAGE(HAVERQ!U$164:U$167) -> -7.25 | AU10: =HAVERQ!V170-AVERAGE(HAVERQ!V$164:V$167) -> -120.75 | AV10: =HAVERQ!W170-AVERAGE(HAVERQ!W$164:W$167) -> 1.25 | AW10: =HAVERQ!X170-AVERAGE(HAVERQ!X$164:X$167) -> 0.5 | AX10: =HAVERQ!Y170-AVERAGE(HAVERQ!Y$164:Y$167) -> -190.25 | AY10: =HAVERQ!Z170-AVERAGE(HAVERQ!Z$164:Z$167) -> -163.5 | AZ10: =HAVERQ!AA170-AVERAGE(HAVERQ!AA$164:AA$167) -> -16 | ... BJ10: =HAVERQ!AK170-AVERAGE(HAVERQ!AK$164:AK$167) -> -105.75 | BK10: =BM10-AVERAGE(BM$4:BM$7) -> -78.5 | BM10: =HAVERQ!AL170+HAVERQ!AM170 -> 939 | BO10: 44013 | BP10: =BZ10-AVERAGE(BZ$4:BZ$7) -> 18.75 | BQ10: =CA10-AVERAGE(CA$4:CA$7) -> -5.5 | BR10: =CB10-AVERAGE(CB$4:CB$7) -> -120.75 | BS10: =CC10-AVERAGE(CC$4:CC$7) -> -190.25 | BT10: =CD10-AVERAGE(CD$4:CD$7) -> -377.5 | BU10: =CE10-AVERAGE(CE$4:CE$7) -> -4.25 | BV10: =CF10-AVERAGE(CF$4:CF$7) -> -20.25 | BW10: =CG10-AVERAGE(CG$4:CG$7) -> -174.25 | BX10: =CH10-AVERAGE(CH$4:CH$7) -> -97.25 | BZ10: =HAVERQ!T170 -> 417 | CA10: =HAVERQ!U170+HAVERQ!W170+HAVERQ!X170 -> 420 | CB10: =HAVERQ!V170 -> 2570 | CC10: =HAVERQ!Y170 -> 2143 | CD10: =HAVERQ!Z170+HAVERQ!AB170 -> 7127 | CE10: =HAVERQ!AA170+HAVERQ!AC170 -> 3302 | CF10: =HAVERQ!AD170 -> 1115 | CG10: =HAVERQ!AE170+HAVERQ!AF170+HAVERQ!AG170 -> 6657 | CH10: =HAVERQ!AH170+HAVERQ!AI170+HAVERQ!AJ170+HAVERQ!AK170+HAVERQ!AL170+HAVERQ!AM170 -> 10843 | CI10: =HAVERQ!S170-SUM('Chart Data'!BZ10:CH10) -> 0 | CL10: =100*((DataQ!F169/DataQ!F165)-1) -> 2.7966777 | CM10: =100*(DataQ!I169/DataQ!J169) -> 22.178476 | CO10: =CO5 -> 45627 | CP10: =HLOOKUP(CP$7,$CP$2:$CU$5,4,FALSE) -> 63.5 | CQ10: =HLOOKUP(CQ$7,$CP$2:$CU$5,4,FALSE) -> 54.45 | CR10: =HLOOKUP(CR$7,$CP$2:$CU$5,4,FALSE) -> 52.76 | CS10: =HLOOKUP(CS$7,$CP$2:$CU$5,4,FALSE) -> 40.67 | CT10: =HLOOKUP(CT$7,$CP$2:$CU$5,4,FALSE) -> 7.33 | CU10: =HLOOKUP(CU$7,$CP$2:$CU$5,4,FALSE) -> 3.75 | CY10: =(HAVERQ!AQ134-AVERAGE(HAVERQ!AQ$128:AQ$183))/STDEV(HAVERQ!AQ$128:AQ$183) -> 1.691929 | CZ10: =(DL10-AVERAGE(DL$5:DL$59))/STDEV(DL$5:DL$59) -> 1.4915247 | DA10: =(DO10-AVERAGE(DO$5:DO$59))/STDEV(DO$5:DO$59) -> 0.98916196 | DB10: =(HAVERQ!AR134-AVERAGE(HAVERQ!AR$128:AR$183))/STDEV(HAVERQ!AR$128:AR$183) -> 0.69323162 | DC10: =(DM10-AVERAGE(DM$5:DM$59))/STDEV(DM$5:DM$59) -> -1.2046133 | DD10: =(DN10-AVERAGE(DN$29:DN$59))/STDEV(DN$29:DN$59) -> #N/A | DE10: =(HAVERQ!AZ134-AVERAGE(HAVERQ!AZ$128:AZ$167,AZ$174:AZ$183))/STDEV(HAVERQ!AZ$128:AZ$167,AZ$174:AZ$183) -> -1.1050252 | DF10: =(HAVERQ!AS134-AVERAGE(HAVERQ!AS$128:AS$183))/STDEV(HAVERQ!AS$128:AS$183) -> -0.84146419 | DG10: =(DP10-AVERAGE(DP$5:DP$59))/STDEV(DP$5:DP$59) -> -0.36943008 | DH10: =(HAVERQ!AX134-AVERAGE(HAVERQ!AX$128:AX$183))/STDEV(HAVERQ!AX$128:AX$183) -> -1.3285019 | DJ10: =(DR10-AVERAGE(DR$5:DR$59))/STDEV(DR$5:DR$59) -> -1.4022411 | DL10: =100*(HAVERQ!AV134/(HAVERQ!AW134*HAVERQ!AX134/100)) -> 2.7486013 | DM10: =HAVERQ!AO134/HAVERQ!AP134 -> 0.17950645 | DN10: =100*((AVERAGE(HAVERQ!BC131:BC134)/AVERAGE(HAVERQ!BC127:BC130))-1) -> #N/A | DO10: =100*(HAVERQ!BE134+HAVERQ!BF134)/(HAVERQ!BB134+HAVERQ!BG134) -> 11.156676 | DP10: =100*((AVERAGE(HAVERQ!BA131:BA134)/AVERAGE(HAVERQ!BA127:BA130))-1) -> 2.2766405 | DR10: =(HAVERQ!AT134*HAVERQ!$AT$1)+(HAVERQ!AU134*HAVERQ!$AU$1) -> 48.699629
A11: 2021 | B11: =100*((DataA!G55-DataA!G54)/DataA!H54) -> 3.8447946 | C11: =D11-B11 -> 0.29847196 | D11: =100*((DataA!H55/DataA!H54)-1) -> 4.1432665 | F11: 2021 | G11: =B11-K11 -> 1.1780466 | H11: =I11-G11 -> 0.41896108 | I11: =100*((DataA!I55/DataA!I54)-1) -> 1.5970077 | K11: =100*((DataA!J55/DataA!J54)-1) -> 2.666748 | M11: 42583 | N11: =HAVERM!C446 -> 5.106 | O11: =HAVERM!B446 -> 4.8 | Q11: 42583 | R11: =MIN(HAVERM!C445:C447) -> 4.657 | S11: =V11-R11 -> 0.449 | T11: =HAVERM!B446 -> 4.8 | V11: =MAX(HAVERM!C445:C447) -> 5.106 | X11: 44105 | Y11: =HAVERQ!E171-AVERAGE(HAVERQ!E$164:E$167) -> 134.25 | Z11: =HAVERQ!F171-AVERAGE(HAVERQ!F$164:F$167) -> -801.75 | AB11: 37165 | AC11: =HAVERQ!P95 -> 1278 | AD11: =HAVERQ!O95 -> 1467 | AE11: =HAVERQ!N95 -> 1197 | AF11: =HAVERQ!M95 -> 234 | AG11: =HAVERQ!L95 -> 214 | AH11: =HAVERQ!E95-AC11-AD11-AE11-AF11-AG11 -> 769 | AJ11: 37165 | AK11: =100*(AC11/SUM($AC11:$AH11)) -> 24.772243 | AL11: =100*(AD11/SUM($AC11:$AH11)) -> 28.435743 | AM11: =100*(AE11/SUM($AC11:$AH11)) -> 23.202171 | AN11: =100*(AF11/SUM($AC11:$AH11)) -> 4.5357627 | AO11: =100*(AG11/SUM($AC11:$AH11)) -> 4.1480907 | AP11: =100*(AH11/SUM($AC11:$AH11)) -> 14.90599 | AR11: 44105 | AS11: =HAVERQ!T171-AVERAGE(HAVERQ!T$164:T$167) -> -18.25 | AT11: =HAVERQ!U171-AVERAGE(HAVERQ!U$164:U$167) -> -8.25 | AU11: =HAVERQ!V171-AVERAGE(HAVERQ!V$164:V$167) -> -134.75 | AV11: =HAVERQ!W171-AVERAGE(HAVERQ!W$164:W$167) -> 4.25 | AW11: =HAVERQ!X171-AVERAGE(HAVERQ!X$164:X$167) -> 0.5 | AX11: =HAVERQ!Y171-AVERAGE(HAVERQ!Y$164:Y$167) -> -179.25 | AY11: =HAVERQ!Z171-AVERAGE(HAVERQ!Z$164:Z$167) -> -174.5 | AZ11: =HAVERQ!AA171-AVERAGE(HAVERQ!AA$164:AA$167) -> -47 | ... BJ11: =HAVERQ!AK171-AVERAGE(HAVERQ!AK$164:AK$167) -> -119.75 | BK11: =BM11-AVERAGE(BM$4:BM$7) -> -88.5 | BM11: =HAVERQ!AL171+HAVERQ!AM171 -> 929 | BO11: 44105 | BP11: =BZ11-AVERAGE(BZ$4:BZ$7) -> -18.25 | BQ11: =CA11-AVERAGE(CA$4:CA$7) -> -3.5 | BR11: =CB11-AVERAGE(CB$4:CB$7) -> -134.75 | BS11: =CC11-AVERAGE(CC$4:CC$7) -> -179.25 | BT11: =CD11-AVERAGE(CD$4:CD$7) -> -478.5 | BU11: =CE11-AVERAGE(CE$4:CE$7) -> -42.25 | BV11: =CF11-AVERAGE(CF$4:CF$7) -> 7.75 | BW11: =CG11-AVERAGE(CG$4:CG$7) -> -126.25 | BX11: =CH11-AVERAGE(CH$4:CH$7) -> -66.25 | BZ11: =HAVERQ!T171 -> 380 | CA11: =HAVERQ!U171+HAVERQ!W171+HAVERQ!X171 -> 422 | CB11: =HAVERQ!V171 -> 2556 | CC11: =HAVERQ!Y171 -> 2154 | CD11: =HAVERQ!Z171+HAVERQ!AB171 -> 7026 | CE11: =HAVERQ!AA171+HAVERQ!AC171 -> 3264 | CF11: =HAVERQ!AD171 -> 1143 | CG11: =HAVERQ!AE171+HAVERQ!AF171+HAVERQ!AG171 -> 6705 | CH11: =HAVERQ!AH171+HAVERQ!AI171+HAVERQ!AJ171+HAVERQ!AK171+HAVERQ!AL171+HAVERQ!AM171 -> 10874 | CI11: =HAVERQ!S171-SUM('Chart Data'!BZ11:CH11) -> -2 | CL11: =100*((DataQ!F170/DataQ!F166)-1) -> 2.2815277 | CM11: =100*(DataQ!I170/DataQ!J170) -> 22.016086 | CY11: =(HAVERQ!AQ135-AVERAGE(HAVERQ!AQ$128:AQ$183))/STDEV(HAVERQ!AQ$128:AQ$183) -> 1.7528211 | CZ11: =(DL11-AVERAGE(DL$5:DL$59))/STDEV(DL$5:DL$59) -> 1.4338152 | DA11: =(DO11-AVERAGE(DO$5:DO$59))/STDEV(DO$5:DO$59) -> 1.1824207 | DB11: =(HAVERQ!AR135-AVERAGE(HAVERQ!AR$128:AR$183))/STDEV(HAVERQ!AR$128:AR$183) -> 1.0706577 | DC11: =(DM11-AVERAGE(DM$5:DM$59))/STDEV(DM$5:DM$59) -> -1.2285428 | DD11: =(DN11-AVERAGE(DN$29:DN$59))/STDEV(DN$29:DN$59) -> #N/A | DE11: =(HAVERQ!AZ135-AVERAGE(HAVERQ!AZ$128:AZ$167,AZ$174:AZ$183))/STDEV(HAVERQ!AZ$128:AZ$167,AZ$174:AZ$183) -> -1.5341612 | DF11: =(HAVERQ!AS135-AVERAGE(HAVERQ!AS$128:AS$183))/STDEV(HAVERQ!AS$128:AS$183) -> -1.0169324 | DG11: =(DP11-AVERAGE(DP$5:DP$59))/STDEV(DP$5:DP$59) -> -0.29563478 | DH11: =(HAVERQ!AX135-AVERAGE(HAVERQ!AX$128:AX$183))/STDEV(HAVERQ!AX$128:AX$183) -> -1.0260787 | DJ11: =(DR11-AVERAGE(DR$5:DR$59))/STDEV(DR$5:DR$59) -> -0.72040489 | DL11: =100*(HAVERQ!AV135/(HAVERQ!AW135*HAVERQ!AX135/100)) -> 2.7053822 | DM11: =HAVERQ!AO135/HAVERQ!AP135 -> 0.17385913 | DN11: =100*((AVERAGE(HAVERQ!BC132:BC135)/AVERAGE(HAVERQ!BC128:BC131))-1) -> #N/A | DO11: =100*(HAVERQ!BE135+HAVERQ!BF135)/(HAVERQ!BB135+HAVERQ!BG135) -> 11.44819 | DP11: =100*((AVERAGE(HAVERQ!BA132:BA135)/AVERAGE(HAVERQ!BA128:BA131))-1) -> 2.4199695 | DR11: =(HAVERQ!AT135*HAVERQ!$AT$1)+(HAVERQ!AU135*HAVERQ!$AU$1) -> 55.466419 | DT11: Table 1: Most labor market variables continue to move in a looser direction
A12: 2022 | B12: =100*((DataA!G56-DataA!G55)/DataA!H55) -> 4.5968489 | C12: =D12-B12 -> 1.6454431 | D12: =100*((DataA!H56/DataA!H55)-1) -> 6.242292 | F12: 2022 | G12: =B12-K12 -> -3.898532 | H12: =I12-G12 -> 2.148227 | I12: =100*((DataA!I56/DataA!I55)-1) -> -1.750305 | K12: =100*((DataA!J56/DataA!J55)-1) -> 8.4953809 | M12: 42614 | N12: =HAVERM!C447 -> 4.736 | O12: =HAVERM!B447 -> 4.8 | Q12: 42614 | R12: =MIN(HAVERM!C446:C448) -> 4.659 | S12: =V12-R12 -> 0.447 | T12: =HAVERM!B447 -> 4.8 | V12: =MAX(HAVERM!C446:C448) -> 5.106 | X12: 44197 | Y12: =HAVERQ!E172-AVERAGE(HAVERQ!E$164:E$167) -> 214.25 | Z12: =HAVERQ!F172-AVERAGE(HAVERQ!F$164:F$167) -> -840.75 | AB12: 37257 | AC12: =HAVERQ!P96 -> 1292 | AD12: =HAVERQ!O96 -> 1471 | AE12: =HAVERQ!N96 -> 1204 | AF12: =HAVERQ!M96 -> 236 | AG12: =HAVERQ!L96 -> 214 | AH12: =HAVERQ!E96-AC12-AD12-AE12-AF12-AG12 -> 782 | AJ12: 37257 | AK12: =100*(AC12/SUM($AC12:$AH12)) -> 24.850933 | AL12: =100*(AD12/SUM($AC12:$AH12)) -> 28.293903 | AM12: =100*(AE12/SUM($AC12:$AH12)) -> 23.1583 | AN12: =100*(AF12/SUM($AC12:$AH12)) -> 4.5393345 | AO12: =100*(AG12/SUM($AC12:$AH12)) -> 4.1161762 | AP12: =100*(AH12/SUM($AC12:$AH12)) -> 15.041354 | AR12: 44197 | AS12: =HAVERQ!T172-AVERAGE(HAVERQ!T$164:T$167) -> -23.25 | AT12: =HAVERQ!U172-AVERAGE(HAVERQ!U$164:U$167) -> -8.25 | AU12: =HAVERQ!V172-AVERAGE(HAVERQ!V$164:V$167) -> -153.75 | AV12: =HAVERQ!W172-AVERAGE(HAVERQ!W$164:W$167) -> 3.25 | AW12: =HAVERQ!X172-AVERAGE(HAVERQ!X$164:X$167) -> -4.5 | AX12: =HAVERQ!Y172-AVERAGE(HAVERQ!Y$164:Y$167) -> -162.25 | AY12: =HAVERQ!Z172-AVERAGE(HAVERQ!Z$164:Z$167) -> -196.5 | AZ12: =HAVERQ!AA172-AVERAGE(HAVERQ!AA$164:AA$167) -> 24 | ... BJ12: =HAVERQ!AK172-AVERAGE(HAVERQ!AK$164:AK$167) -> -142.75 | BK12: =BM12-AVERAGE(BM$4:BM$7) -> -60.5 | BM12: =HAVERQ!AL172+HAVERQ!AM172 -> 957 | BO12: 44197 | BP12: =BZ12-AVERAGE(BZ$4:BZ$7) -> -23.25 | BQ12: =CA12-AVERAGE(CA$4:CA$7) -> -9.5 | BR12: =CB12-AVERAGE(CB$4:CB$7) -> -153.75 | BS12: =CC12-AVERAGE(CC$4:CC$7) -> -162.25 | BT12: =CD12-AVERAGE(CD$4:CD$7) -> -460.5 | BU12: =CE12-AVERAGE(CE$4:CE$7) -> 35.75 | BV12: =CF12-AVERAGE(CF$4:CF$7) -> 19.75 | BW12: =CG12-AVERAGE(CG$4:CG$7) -> -100.25 | BX12: =CH12-AVERAGE(CH$4:CH$7) -> 23.75 | BZ12: =HAVERQ!T172 -> 375 | CA12: =HAVERQ!U172+HAVERQ!W172+HAVERQ!X172 -> 416 | CB12: =HAVERQ!V172 -> 2537 | CC12: =HAVERQ!Y172 -> 2171 | CD12: =HAVERQ!Z172+HAVERQ!AB172 -> 7044 | CE12: =HAVERQ!AA172+HAVERQ!AC172 -> 3342 | CF12: =HAVERQ!AD172 -> 1155 | CG12: =HAVERQ!AE172+HAVERQ!AF172+HAVERQ!AG172 -> 6731 | CH12: =HAVERQ!AH172+HAVERQ!AI172+HAVERQ!AJ172+HAVERQ!AK172+HAVERQ!AL172+HAVERQ!AM172 -> 10964 | CI12: =HAVERQ!S172-SUM('Chart Data'!BZ12:CH12) -> -1 | CK12: 2014 | CL12: =100*((DataQ!F171/DataQ!F167)-1) -> 2.457354 | CM12: =100*(DataQ!I171/DataQ!J171) -> 21.695584 | CX12: 2012 | CY12: =(HAVERQ!AQ136-AVERAGE(HAVERQ!AQ$128:AQ$183))/STDEV(HAVERQ!AQ$128:AQ$183) -> 1.631037 | CZ12: =(DL12-AVERAGE(DL$5:DL$59))/STDEV(DL$5:DL$59) -> 1.5109721 | DA12: =(DO12-AVERAGE(DO$5:DO$59))/STDEV(DO$5:DO$59) -> 1.4091393 | DB12: =(HAVERQ!AR136-AVERAGE(HAVERQ!AR$128:AR$183))/STDEV(HAVERQ!AR$128:AR$183) -> 1.2324118 | DC12: =(DM12-AVERAGE(DM$5:DM$59))/STDEV(DM$5:DM$59) -> -1.2507048 | DD12: =(DN12-AVERAGE(DN$29:DN$59))/STDEV(DN$29:DN$59) -> #N/A | DE12: =(HAVERQ!AZ136-AVERAGE(HAVERQ!AZ$128:AZ$167,AZ$174:AZ$183))/STDEV(HAVERQ!AZ$128:AZ$167,AZ$174:AZ$183) -> -1.1050252 | DF12: =(HAVERQ!AS136-AVERAGE(HAVERQ!AS$128:AS$183))/STDEV(HAVERQ!AS$128:AS$183) -> -1.0695729 | DG12: =(DP12-AVERAGE(DP$5:DP$59))/STDEV(DP$5:DP$59) -> -0.60636075 | DH12: =(HAVERQ!AX136-AVERAGE(HAVERQ!AX$128:AX$183))/STDEV(HAVERQ!AX$128:AX$183) -> -1.0260787 | DJ12: =(DR12-AVERAGE(DR$5:DR$59))/STDEV(DR$5:DR$59) -> -1.114555 | DL12: =100*(HAVERQ!AV136/(HAVERQ!AW136*HAVERQ!AX136/100)) -> 2.7631656 | DM12: =HAVERQ!AO136/HAVERQ!AP136 -> 0.16862894 | DN12: =100*((AVERAGE(HAVERQ!BC133:BC136)/AVERAGE(HAVERQ!BC129:BC132))-1) -> #N/A | DO12: =100*(HAVERQ!BE136+HAVERQ!BF136)/(HAVERQ!BB136+HAVERQ!BG136) -> 11.790175 | DP12: =100*((AVERAGE(HAVERQ!BA133:BA136)/AVERAGE(HAVERQ!BA129:BA132))-1) -> 1.8164617 | DR12: =(HAVERQ!AT136*HAVERQ!$AT$1)+(HAVERQ!AU136*HAVERQ!$AU$1) -> 51.554731 | DU12: April indicators versus: | DV12: 45352 | DX12: 2019 | DY12: Data source
A13: 2023 | B13: =100*((DataA!G57-DataA!G56)/DataA!H56) -> 5.4343165 | C13: =D13-B13 -> 3.6829069 | D13: =100*((DataA!H57/DataA!H56)-1) -> 9.1172234 | F13: 2023 | G13: =B13-K13 -> -1.4588863 | H13: =I13-G13 -> 3.5919099 | I13: =100*((DataA!I57/DataA!I56)-1) -> 2.1330236 | K13: =100*((DataA!J57/DataA!J56)-1) -> 6.8932028 | M13: 42644 | N13: =HAVERM!C448 -> 4.659 | O13: =HAVERM!B448 -> 4.8 | Q13: 42644 | R13: =MIN(HAVERM!C447:C449) -> 4.659 | S13: =V13-R13 -> 0.293 | T13: =HAVERM!B448 -> 4.8 | V13: =MAX(HAVERM!C447:C449) -> 4.952 | X13: 44287 | Y13: =HAVERQ!E173-AVERAGE(HAVERQ!E$164:E$167) -> 225.25 | Z13: =HAVERQ!F173-AVERAGE(HAVERQ!F$164:F$167) -> -639.75 | AB13: 37347 | AC13: =HAVERQ!P97 -> 1309 | AD13: =HAVERQ!O97 -> 1473 | AE13: =HAVERQ!N97 -> 1212 | AF13: =HAVERQ!M97 -> 238 | AG13: =HAVERQ!L97 -> 214 | AH13: =HAVERQ!E97-AC13-AD13-AE13-AF13-AG13 -> 780 | AJ13: 37347 | AK13: =100*(AC13/SUM($AC13:$AH13)) -> 25.047838 | AL13: =100*(AD13/SUM($AC13:$AH13)) -> 28.185993 | AM13: =100*(AE13/SUM($AC13:$AH13)) -> 23.191734 | AN13: =100*(AF13/SUM($AC13:$AH13)) -> 4.5541523 | AO13: =100*(AG13/SUM($AC13:$AH13)) -> 4.0949101 | AP13: =100*(AH13/SUM($AC13:$AH13)) -> 14.925373 | AR13: 44287 | AS13: =HAVERQ!T173-AVERAGE(HAVERQ!T$164:T$167) -> -24.25 | AT13: =HAVERQ!U173-AVERAGE(HAVERQ!U$164:U$167) -> -7.25 | AU13: =HAVERQ!V173-AVERAGE(HAVERQ!V$164:V$167) -> -146.75 | AV13: =HAVERQ!W173-AVERAGE(HAVERQ!W$164:W$167) -> 5.25 | AW13: =HAVERQ!X173-AVERAGE(HAVERQ!X$164:X$167) -> 7.5 | AX13: =HAVERQ!Y173-AVERAGE(HAVERQ!Y$164:Y$167) -> -92.25 | AY13: =HAVERQ!Z173-AVERAGE(HAVERQ!Z$164:Z$167) -> -234.5 | AZ13: =HAVERQ!AA173-AVERAGE(HAVERQ!AA$164:AA$167) -> 10 | ... BJ13: =HAVERQ!AK173-AVERAGE(HAVERQ!AK$164:AK$167) -> -77.75 | BK13: =BM13-AVERAGE(BM$4:BM$7) -> -36.5 | BM13: =HAVERQ!AL173+HAVERQ!AM173 -> 981 | BO13: 44287 | BP13: =BZ13-AVERAGE(BZ$4:BZ$7) -> -24.25 | BQ13: =CA13-AVERAGE(CA$4:CA$7) -> 5.5 | BR13: =CB13-AVERAGE(CB$4:CB$7) -> -146.75 | BS13: =CC13-AVERAGE(CC$4:CC$7) -> -92.25 | BT13: =CD13-AVERAGE(CD$4:CD$7) -> -363.5 | BU13: =CE13-AVERAGE(CE$4:CE$7) -> -0.25 | BV13: =CF13-AVERAGE(CF$4:CF$7) -> 26.75 | BW13: =CG13-AVERAGE(CG$4:CG$7) -> -36.25 | BX13: =CH13-AVERAGE(CH$4:CH$7) -> 137.75 | BZ13: =HAVERQ!T173 -> 374 | CA13: =HAVERQ!U173+HAVERQ!W173+HAVERQ!X173 -> 431 | CB13: =HAVERQ!V173 -> 2544 | CC13: =HAVERQ!Y173 -> 2241 | CD13: =HAVERQ!Z173+HAVERQ!AB173 -> 7141 | CE13: =HAVERQ!AA173+HAVERQ!AC173 -> 3306 | CF13: =HAVERQ!AD173 -> 1162 | CG13: =HAVERQ!AE173+HAVERQ!AF173+HAVERQ!AG173 -> 6795 | CH13: =HAVERQ!AH173+HAVERQ!AI173+HAVERQ!AJ173+HAVERQ!AK173+HAVERQ!AL173+HAVERQ!AM173 -> 11078 | CI13: =HAVERQ!S173-SUM('Chart Data'!BZ13:CH13) -> 0 | CL13: =100*((DataQ!F172/DataQ!F168)-1) -> -1.5163896 | CM13: =100*(DataQ!I172/DataQ!J172) -> 22.422755 | CY13: =(HAVERQ!AQ137-AVERAGE(HAVERQ!AQ$128:AQ$183))/STDEV(HAVERQ!AQ$128:AQ$183) -> 1.5092529 | CZ13: =(DL13-AVERAGE(DL$5:DL$59))/STDEV(DL$5:DL$59) -> 1.4973913 | DA13: =(DO13-AVERAGE(DO$5:DO$59))/STDEV(DO$5:DO$59) -> 1.4934211 | DB13: =(HAVERQ!AR137-AVERAGE(HAVERQ!AR$128:AR$183))/STDEV(HAVERQ!AR$128:AR$183) -> 0.74714964 | DC13: =(DM13-AVERAGE(DM$5:DM$59))/STDEV(DM$5:DM$59) -> -1.1715306 | DD13: =(DN13-AVERAGE(DN$29:DN$59))/STDEV(DN$29:DN$59) -> #N/A | DE13: =(HAVERQ!AZ137-AVERAGE(HAVERQ!AZ$128:AZ$167,AZ$174:AZ$183))/STDEV(HAVERQ!AZ$128:AZ$167,AZ$174:AZ$183) -> -1.1050252 | DF13: =(HAVERQ!AS137-AVERAGE(HAVERQ!AS$128:AS$183))/STDEV(HAVERQ!AS$128:AS$183) -> -1.1046665 | DG13: =(DP13-AVERAGE(DP$5:DP$59))/STDEV(DP$5:DP$59) -> -0.68961686 | DH13: =(HAVERQ!AX137-AVERAGE(HAVERQ!AX$128:AX$183))/STDEV(HAVERQ!AX$128:AX$183) -> -0.42123232 | DJ13: =(DR13-AVERAGE(DR$5:DR$59))/STDEV(DR$5:DR$59) -> -1.5792011 | DL13: =100*(HAVERQ!AV137/(HAVERQ!AW137*HAVERQ!AX137/100)) -> 2.7529949 | DM13: =HAVERQ!AO137/HAVERQ!AP137 -> 0.18731392 | DN13: =100*((AVERAGE(HAVERQ!BC134:BC137)/AVERAGE(HAVERQ!BC130:BC133))-1) -> #N/A | DO13: =100*(HAVERQ!BE137+HAVERQ!BF137)/(HAVERQ!BB137+HAVERQ!BG137) -> 11.917307 | DP13: =100*((AVERAGE(HAVERQ!BA134:BA137)/AVERAGE(HAVERQ!BA130:BA133))-1) -> 1.6547574 | DR13: =(HAVERQ!AT137*HAVERQ!$AT$1)+(HAVERQ!AU137*HAVERQ!$AU$1) -> 46.943413 | DT13: Unemployment | DU13: U3 unemployment rate. | DV13: looser | DX13: looser | DY13: April household survey
A14: 2024 | B14: =100*((DataA!G58-DataA!G57)/DataA!H57) -> 3.3538561 | C14: =D14-B14 -> 3.2079907 | D14: =100*((DataA!H58/DataA!H57)-1) -> 6.5618469 | F14: 2024 | G14: =B14-K14 -> 0.8069626 | H14: =I14-G14 -> 3.0342877 | I14: =100*((DataA!I58/DataA!I57)-1) -> 3.8412503 | K14: =100*((DataA!J58/DataA!J57)-1) -> 2.5468935 | M14: 42675 | N14: =HAVERM!C449 -> 4.952 | O14: =HAVERM!B449 -> 4.7 | Q14: 42675 | R14: =MIN(HAVERM!C448:C450) -> 4.594 | S14: =V14-R14 -> 0.358 | T14: =HAVERM!B449 -> 4.7 | V14: =MAX(HAVERM!C448:C450) -> 4.952 | X14: 44378 | Y14: =HAVERQ!E174-AVERAGE(HAVERQ!E$164:E$167) -> 242.25 | Z14: =HAVERQ!F174-AVERAGE(HAVERQ!F$164:F$167) -> -491.75 | AB14: 37438 | AC14: =HAVERQ!P98 -> 1325 | AD14: =HAVERQ!O98 -> 1500 | AE14: =HAVERQ!N98 -> 1215 | AF14: =HAVERQ!M98 -> 240 | AG14: =HAVERQ!L98 -> 215 | AH14: =HAVERQ!E98-AC14-AD14-AE14-AF14-AG14 -> 767 | AJ14: 37438 | AK14: =100*(AC14/SUM($AC14:$AH14)) -> 25.18054 | AL14: =100*(AD14/SUM($AC14:$AH14)) -> 28.506271 | AM14: =100*(AE14/SUM($AC14:$AH14)) -> 23.09008 | AN14: =100*(AF14/SUM($AC14:$AH14)) -> 4.5610034 | AO14: =100*(AG14/SUM($AC14:$AH14)) -> 4.0858989 | AP14: =100*(AH14/SUM($AC14:$AH14)) -> 14.576207 | AR14: 44378 | AS14: =HAVERQ!T174-AVERAGE(HAVERQ!T$164:T$167) -> -31.25 | AT14: =HAVERQ!U174-AVERAGE(HAVERQ!U$164:U$167) -> -9.25 | AU14: =HAVERQ!V174-AVERAGE(HAVERQ!V$164:V$167) -> -153.75 | AV14: =HAVERQ!W174-AVERAGE(HAVERQ!W$164:W$167) -> 4.25 | AW14: =HAVERQ!X174-AVERAGE(HAVERQ!X$164:X$167) -> 12.5 | AX14: =HAVERQ!Y174-AVERAGE(HAVERQ!Y$164:Y$167) -> -108.25 | AY14: =HAVERQ!Z174-AVERAGE(HAVERQ!Z$164:Z$167) -> -182.5 | AZ14: =HAVERQ!AA174-AVERAGE(HAVERQ!AA$164:AA$167) -> 16 | ... BJ14: =HAVERQ!AK174-AVERAGE(HAVERQ!AK$164:AK$167) -> -58.75 | BK14: =BM14-AVERAGE(BM$4:BM$7) -> -34.5 | BM14: =HAVERQ!AL174+HAVERQ!AM174 -> 983 | BO14: 44378 | BP14: =BZ14-AVERAGE(BZ$4:BZ$7) -> -31.25 | BQ14: =CA14-AVERAGE(CA$4:CA$7) -> 7.5 | BR14: =CB14-AVERAGE(CB$4:CB$7) -> -153.75 | BS14: =CC14-AVERAGE(CC$4:CC$7) -> -108.25 | BT14: =CD14-AVERAGE(CD$4:CD$7) -> -217.5 | BU14: =CE14-AVERAGE(CE$4:CE$7) -> 43.75 | BV14: =CF14-AVERAGE(CF$4:CF$7) -> 25.75 | BW14: =CG14-AVERAGE(CG$4:CG$7) -> -22.25 | BX14: =CH14-AVERAGE(CH$4:CH$7) -> 175.75 | BZ14: =HAVERQ!T174 -> 367 | CA14: =HAVERQ!U174+HAVERQ!W174+HAVERQ!X174 -> 433 | CB14: =HAVERQ!V174 -> 2537 | CC14: =HAVERQ!Y174 -> 2225 | CD14: =HAVERQ!Z174+HAVERQ!AB174 -> 7287 | CE14: =HAVERQ!AA174+HAVERQ!AC174 -> 3350 | CF14: =HAVERQ!AD174 -> 1161 | CG14: =HAVERQ!AE174+HAVERQ!AF174+HAVERQ!AG174 -> 6809 | CH14: =HAVERQ!AH174+HAVERQ!AI174+HAVERQ!AJ174+HAVERQ!AK174+HAVERQ!AL174+HAVERQ!AM174 -> 11116 | CI14: =HAVERQ!S174-SUM('Chart Data'!BZ14:CH14) -> 1 | CL14: =100*((DataQ!F173/DataQ!F169)-1) -> -1.8918891 | CM14: =100*(DataQ!I173/DataQ!J173) -> 23.797129 | CY14: =(HAVERQ!AQ138-AVERAGE(HAVERQ!AQ$128:AQ$183))/STDEV(HAVERQ!AQ$128:AQ$183) -> 1.3874688 | CZ14: =(DL14-AVERAGE(DL$5:DL$59))/STDEV(DL$5:DL$59) -> 1.5489093 | DA14: =(DO14-AVERAGE(DO$5:DO$59))/STDEV(DO$5:DO$59) -> 1.3390521 | DB14: =(HAVERQ!AR138-AVERAGE(HAVERQ!AR$128:AR$183))/STDEV(HAVERQ!AR$128:AR$183) -> 0.2618875 | DC14: =(DM14-AVERAGE(DM$5:DM$59))/STDEV(DM$5:DM$59) -> -1.128465 | DD14: =(DN14-AVERAGE(DN$29:DN$59))/STDEV(DN$29:DN$59) -> #N/A | DE14: =(HAVERQ!AZ138-AVERAGE(HAVERQ!AZ$128:AZ$167,AZ$174:AZ$183))/STDEV(HAVERQ!AZ$128:AZ$167,AZ$174:AZ$183) -> 0.1823828 | DF14: =(HAVERQ!AS138-AVERAGE(HAVERQ!AS$128:AS$183))/STDEV(HAVERQ!AS$128:AS$183) -> -0.87655783 | DG14: =(DP14-AVERAGE(DP$5:DP$59))/STDEV(DP$5:DP$59) -> -0.74223352 | DH14: =(HAVERQ!AX138-AVERAGE(HAVERQ!AX$128:AX$183))/STDEV(HAVERQ!AX$128:AX$183) -> -0.42123232 | DJ14: =(DR14-AVERAGE(DR$5:DR$59))/STDEV(DR$5:DR$59) -> -0.9521952 | DL14: =100*(HAVERQ!AV138/(HAVERQ!AW138*HAVERQ!AX138/100)) -> 2.7915771 | DM14: =HAVERQ!AO138/HAVERQ!AP138 -> 0.19747734 | DN14: =100*((AVERAGE(HAVERQ!BC135:BC138)/AVERAGE(HAVERQ!BC131:BC134))-1) -> #N/A | DO14: =100*(HAVERQ!BE138+HAVERQ!BF138)/(HAVERQ!BB138+HAVERQ!BG138) -> 11.684455 | DP14: =100*((AVERAGE(HAVERQ!BA135:BA138)/AVERAGE(HAVERQ!BA131:BA134))-1) -> 1.5525627 | DR14: =(HAVERQ!AT138*HAVERQ!$AT$1)+(HAVERQ!AU138*HAVERQ!$AU$1) -> 53.166048 | DU14: U6 unemployment rate | DV14: looser | DX14: looser | DY14: April household survey
A15: 2025 | B15: =100*((DataA!G59-DataA!G58)/DataA!H58) -> 2.8757414 | C15: =D15-B15 -> 1.0558234 | D15: =100*((DataA!H59/DataA!H58)-1) -> 3.9315649 | F15: 2025 | G15: =B15-K15 -> 0.10644856 | H15: =I15-G15 -> 1.020778 | I15: =100*((DataA!I59/DataA!I58)-1) -> 1.1272265 | K15: =100*((DataA!J59/DataA!J58)-1) -> 2.7692929 | M15: 42705 | N15: =HAVERM!C450 -> 4.594 | O15: =HAVERM!B450 -> 4.7 | Q15: 42705 | R15: =MIN(HAVERM!C449:C451) -> 4.593 | S15: =V15-R15 -> 0.359 | T15: =HAVERM!B450 -> 4.7 | V15: =MAX(HAVERM!C449:C451) -> 4.952 | X15: 44470 | Y15: =HAVERQ!E175-AVERAGE(HAVERQ!E$164:E$167) -> 261.25 | Z15: =HAVERQ!F175-AVERAGE(HAVERQ!F$164:F$167) -> -460.75 | AB15: 37530 | AC15: =HAVERQ!P99 -> 1341 | AD15: =HAVERQ!O99 -> 1510 | AE15: =HAVERQ!N99 -> 1236 | AF15: =HAVERQ!M99 -> 242 | AG15: =HAVERQ!L99 -> 215 | AH15: =HAVERQ!E99-AC15-AD15-AE15-AF15-AG15 -> 781 | AJ15: 37530 | AK15: =100*(AC15/SUM($AC15:$AH15)) -> 25.183099 | AL15: =100*(AD15/SUM($AC15:$AH15)) -> 28.356808 | AM15: =100*(AE15/SUM($AC15:$AH15)) -> 23.211268 | AN15: =100*(AF15/SUM($AC15:$AH15)) -> 4.5446009 | AO15: =100*(AG15/SUM($AC15:$AH15)) -> 4.0375587 | AP15: =100*(AH15/SUM($AC15:$AH15)) -> 14.666667 | AR15: 44470 | AS15: =HAVERQ!T175-AVERAGE(HAVERQ!T$164:T$167) -> -50.25 | AT15: =HAVERQ!U175-AVERAGE(HAVERQ!U$164:U$167) -> -10.25 | AU15: =HAVERQ!V175-AVERAGE(HAVERQ!V$164:V$167) -> -137.75 | AV15: =HAVERQ!W175-AVERAGE(HAVERQ!W$164:W$167) -> -1.75 | AW15: =HAVERQ!X175-AVERAGE(HAVERQ!X$164:X$167) -> 8.5 | AX15: =HAVERQ!Y175-AVERAGE(HAVERQ!Y$164:Y$167) -> -110.25 | AY15: =HAVERQ!Z175-AVERAGE(HAVERQ!Z$164:Z$167) -> -245.5 | AZ15: =HAVERQ!AA175-AVERAGE(HAVERQ!AA$164:AA$167) -> 23 | ... BJ15: =HAVERQ!AK175-AVERAGE(HAVERQ!AK$164:AK$167) -> -49.75 | BK15: =BM15-AVERAGE(BM$4:BM$7) -> -45.5 | BM15: =HAVERQ!AL175+HAVERQ!AM175 -> 972 | BO15: 44470 | BP15: =BZ15-AVERAGE(BZ$4:BZ$7) -> -50.25 | BQ15: =CA15-AVERAGE(CA$4:CA$7) -> -3.5 | BR15: =CB15-AVERAGE(CB$4:CB$7) -> -137.75 | BS15: =CC15-AVERAGE(CC$4:CC$7) -> -110.25 | BT15: =CD15-AVERAGE(CD$4:CD$7) -> -249.5 | BU15: =CE15-AVERAGE(CE$4:CE$7) -> 81.75 | BV15: =CF15-AVERAGE(CF$4:CF$7) -> 7.75 | BW15: =CG15-AVERAGE(CG$4:CG$7) -> 21.75 | BX15: =CH15-AVERAGE(CH$4:CH$7) -> 202.75 | BZ15: =HAVERQ!T175 -> 348 | CA15: =HAVERQ!U175+HAVERQ!W175+HAVERQ!X175 -> 422 | CB15: =HAVERQ!V175 -> 2553 | CC15: =HAVERQ!Y175 -> 2223 | CD15: =HAVERQ!Z175+HAVERQ!AB175 -> 7255 | CE15: =HAVERQ!AA175+HAVERQ!AC175 -> 3388 | CF15: =HAVERQ!AD175 -> 1143 | CG15: =HAVERQ!AE175+HAVERQ!AF175+HAVERQ!AG175 -> 6853 | CH15: =HAVERQ!AH175+HAVERQ!AI175+HAVERQ!AJ175+HAVERQ!AK175+HAVERQ!AL175+HAVERQ!AM175 -> 11143 | CI15: =HAVERQ!S175-SUM('Chart Data'!BZ15:CH15) -> 0 | CL15: =100*((DataQ!F174/DataQ!F170)-1) -> -1.6332789 | CM15: =100*(DataQ!I174/DataQ!J174) -> 23.392813 | CY15: =(HAVERQ!AQ139-AVERAGE(HAVERQ!AQ$128:AQ$183))/STDEV(HAVERQ!AQ$128:AQ$183) -> 1.3874688 | CZ15: =(DL15-AVERAGE(DL$5:DL$59))/STDEV(DL$5:DL$59) -> 1.4607208 | DA15: =(DO15-AVERAGE(DO$5:DO$59))/STDEV(DO$5:DO$59) -> 1.2186359 | DB15: =(HAVERQ!AR139-AVERAGE(HAVERQ!AR$128:AR$183))/STDEV(HAVERQ!AR$128:AR$183) -> 0.63931361 | DC15: =(DM15-AVERAGE(DM$5:DM$59))/STDEV(DM$5:DM$59) -> -1.1230151 | DD15: =(DN15-AVERAGE(DN$29:DN$59))/STDEV(DN$29:DN$59) -> #N/A | DE15: =(HAVERQ!AZ139-AVERAGE(HAVERQ!AZ$128:AZ$167,AZ$174:AZ$183))/STDEV(HAVERQ!AZ$128:AZ$167,AZ$174:AZ$183) -> -0.24675321 | DF15: =(HAVERQ!AS139-AVERAGE(HAVERQ!AS$128:AS$183))/STDEV(HAVERQ!AS$128:AS$183) -> -0.84146419 | DG15: =(DP15-AVERAGE(DP$5:DP$59))/STDEV(DP$5:DP$59) -> -0.88065113 | DH15: =(HAVERQ!AX139-AVERAGE(HAVERQ!AX$128:AX$183))/STDEV(HAVERQ!AX$128:AX$183) -> 0.18361409 | DJ15: =(DR15-AVERAGE(DR$5:DR$59))/STDEV(DR$5:DR$59) -> -0.71933934 | DL15: =100*(HAVERQ!AV139/(HAVERQ!AW139*HAVERQ!AX139/100)) -> 2.725532 | DM15: =HAVERQ!AO139/HAVERQ!AP139 -> 0.19876348 | DN15: =100*((AVERAGE(HAVERQ!BC136:BC139)/AVERAGE(HAVERQ!BC132:BC135))-1) -> #N/A | DO15: =100*(HAVERQ!BE139+HAVERQ!BF139)/(HAVERQ!BB139+HAVERQ!BG139) -> 11.502817 | DP15: =100*((AVERAGE(HAVERQ!BA136:BA139)/AVERAGE(HAVERQ!BA132:BA135))-1) -> 1.2837209 | DR15: =(HAVERQ!AT139*HAVERQ!$AT$1)+(HAVERQ!AU139*HAVERQ!$AU$1) -> 55.476994 | DU15: Initial claims | DV15: tighter | DX15: tighter | DY15: Weekly jobless claims report
A16: 2026 | B16: =100*((DataA!G60-DataA!G59)/DataA!H59) -> 2.4081599 | C16: =D16-B16 -> 1.0274839 | D16: =100*((DataA!H60/DataA!H59)-1) -> 3.4356438 | F16: 2026 | G16: =B16-K16 -> 0.032380026 | H16: =I16-G16 -> 1.00452 | I16: =100*((DataA!I60/DataA!I59)-1) -> 1.0369 | K16: =100*((DataA!J60/DataA!J59)-1) -> 2.3757798 | M16: 42736 | N16: =HAVERM!C451 -> 4.593 | O16: =HAVERM!B451 -> 4.6 | Q16: 42736 | R16: =MIN(HAVERM!C450:C452) -> 4.593 | S16: =V16-R16 -> 0.116 | T16: =HAVERM!B451 -> 4.6 | V16: =MAX(HAVERM!C450:C452) -> 4.709 | X16: 44562 | Y16: =HAVERQ!E176-AVERAGE(HAVERQ!E$164:E$167) -> 280.25 | Z16: =HAVERQ!F176-AVERAGE(HAVERQ!F$164:F$167) -> -343.75 | AB16: 37622 | AC16: =HAVERQ!P100 -> 1359 | AD16: =HAVERQ!O100 -> 1516 | AE16: =HAVERQ!N100 -> 1246 | AF16: =HAVERQ!M100 -> 246 | AG16: =HAVERQ!L100 -> 221 | AH16: =HAVERQ!E100-AC16-AD16-AE16-AF16-AG16 -> 786 | AJ16: 37622 | AK16: =100*(AC16/SUM($AC16:$AH16)) -> 25.288426 | AL16: =100*(AD16/SUM($AC16:$AH16)) -> 28.2099 | AM16: =100*(AE16/SUM($AC16:$AH16)) -> 23.185709 | AN16: =100*(AF16/SUM($AC16:$AH16)) -> 4.5775958 | AO16: =100*(AG16/SUM($AC16:$AH16)) -> 4.112393 | AP16: =100*(AH16/SUM($AC16:$AH16)) -> 14.625977 | AR16: 44562 | AS16: =HAVERQ!T176-AVERAGE(HAVERQ!T$164:T$167) -> -53.25 | AT16: =HAVERQ!U176-AVERAGE(HAVERQ!U$164:U$167) -> -10.25 | AU16: =HAVERQ!V176-AVERAGE(HAVERQ!V$164:V$167) -> -78.75 | AV16: =HAVERQ!W176-AVERAGE(HAVERQ!W$164:W$167) -> -12.75 | AW16: =HAVERQ!X176-AVERAGE(HAVERQ!X$164:X$167) -> 16.5 | AX16: =HAVERQ!Y176-AVERAGE(HAVERQ!Y$164:Y$167) -> -78.25 | AY16: =HAVERQ!Z176-AVERAGE(HAVERQ!Z$164:Z$167) -> -208.5 | AZ16: =HAVERQ!AA176-AVERAGE(HAVERQ!AA$164:AA$167) -> 22 | ... BJ16: =HAVERQ!AK176-AVERAGE(HAVERQ!AK$164:AK$167) -> -47.75 | BK16: =BM16-AVERAGE(BM$4:BM$7) -> -47.5 | BM16: =HAVERQ!AL176+HAVERQ!AM176 -> 970 | BO16: 44562 | BP16: =BZ16-AVERAGE(BZ$4:BZ$7) -> -53.25 | BQ16: =CA16-AVERAGE(CA$4:CA$7) -> -6.5 | BR16: =CB16-AVERAGE(CB$4:CB$7) -> -78.75 | BS16: =CC16-AVERAGE(CC$4:CC$7) -> -78.25 | BT16: =CD16-AVERAGE(CD$4:CD$7) -> -149.5 | BU16: =CE16-AVERAGE(CE$4:CE$7) -> 93.75 | BV16: =CF16-AVERAGE(CF$4:CF$7) -> -21.25 | BW16: =CG16-AVERAGE(CG$4:CG$7) -> 141.75 | BX16: =CH16-AVERAGE(CH$4:CH$7) -> 297.75 | BZ16: =HAVERQ!T176 -> 345 | CA16: =HAVERQ!U176+HAVERQ!W176+HAVERQ!X176 -> 419 | CB16: =HAVERQ!V176 -> 2612 | CC16: =HAVERQ!Y176 -> 2255 | CD16: =HAVERQ!Z176+HAVERQ!AB176 -> 7355 | CE16: =HAVERQ!AA176+HAVERQ!AC176 -> 3400 | CF16: =HAVERQ!AD176 -> 1114 | CG16: =HAVERQ!AE176+HAVERQ!AF176+HAVERQ!AG176 -> 6973 | CH16: =HAVERQ!AH176+HAVERQ!AI176+HAVERQ!AJ176+HAVERQ!AK176+HAVERQ!AL176+HAVERQ!AM176 -> 11238 | CI16: =HAVERQ!S176-SUM('Chart Data'!BZ16:CH16) -> 1 | CK16: 2015 | CL16: =100*((DataQ!F175/DataQ!F171)-1) -> -0.69899237 | CM16: =100*(DataQ!I175/DataQ!J175) -> 22.828221 | CX16: 2013 | CY16: =(HAVERQ!AQ140-AVERAGE(HAVERQ!AQ$128:AQ$183))/STDEV(HAVERQ!AQ$128:AQ$183) -> 1.3874688 | CZ16: =(DL16-AVERAGE(DL$5:DL$59))/STDEV(DL$5:DL$59) -> 1.556401 | DA16: =(DO16-AVERAGE(DO$5:DO$59))/STDEV(DO$5:DO$59) -> 1.2499728 | DB16: =(HAVERQ!AR140-AVERAGE(HAVERQ!AR$128:AR$183))/STDEV(HAVERQ!AR$128:AR$183) -> 0.53147758 | DC16: =(DM16-AVERAGE(DM$5:DM$59))/STDEV(DM$5:DM$59) -> -1.1600376 | DD16: =(DN16-AVERAGE(DN$29:DN$59))/STDEV(DN$29:DN$59) -> #N/A | DE16: =(HAVERQ!AZ140-AVERAGE(HAVERQ!AZ$128:AZ$167,AZ$174:AZ$183))/STDEV(HAVERQ!AZ$128:AZ$167,AZ$174:AZ$183) -> 0.1823828 | DF16: =(HAVERQ!AS140-AVERAGE(HAVERQ!AS$128:AS$183))/STDEV(HAVERQ!AS$128:AS$183) -> -0.82391736 | DG16: =(DP16-AVERAGE(DP$5:DP$59))/STDEV(DP$5:DP$59) -> -0.88138811 | DH16: =(HAVERQ!AX140-AVERAGE(HAVERQ!AX$128:AX$183))/STDEV(HAVERQ!AX$128:AX$183) -> -0.42123232 | DJ16: =(DR16-AVERAGE(DR$5:DR$59))/STDEV(DR$5:DR$59) -> -0.75173648 | DL16: =100*(HAVERQ!AV140/(HAVERQ!AW140*HAVERQ!AX140/100)) -> 2.7971877 | DM16: =HAVERQ!AO140/HAVERQ!AP140 -> 0.19002625 | DN16: =100*((AVERAGE(HAVERQ!BC137:BC140)/AVERAGE(HAVERQ!BC133:BC136))-1) -> #N/A | DO16: =100*(HAVERQ!BE140+HAVERQ!BF140)/(HAVERQ!BB140+HAVERQ!BG140) -> 11.550086 | DP16: =100*((AVERAGE(HAVERQ!BA137:BA140)/AVERAGE(HAVERQ!BA133:BA136))-1) -> 1.2822895 | DR16: =(HAVERQ!AT140*HAVERQ!$AT$1)+(HAVERQ!AU140*HAVERQ!$AU$1) -> 55.155473 | DU16: Long-term unemployment | DV16: looser | DX16: tighter | DY16: April household survey
M17: 42767 | N17: =HAVERM!C452 -> 4.709 | O17: =HAVERM!B452 -> 4.6 | Q17: 42767 | R17: =MIN(HAVERM!C451:C453) -> 4.371 | S17: =V17-R17 -> 0.338 | T17: =HAVERM!B452 -> 4.6 | V17: =MAX(HAVERM!C451:C453) -> 4.709 | X17: 44652 | Y17: =HAVERQ!E177-AVERAGE(HAVERQ!E$164:E$167) -> 293.25 | Z17: =HAVERQ!F177-AVERAGE(HAVERQ!F$164:F$167) -> -314.75 | AB17: 37712 | AC17: =HAVERQ!P101 -> 1374 | AD17: =HAVERQ!O101 -> 1531 | AE17: =HAVERQ!N101 -> 1257 | AF17: =HAVERQ!M101 -> 248 | AG17: =HAVERQ!L101 -> 223 | AH17: =HAVERQ!E101-AC17-AD17-AE17-AF17-AG17 -> 788 | AJ17: 37712 | AK17: =100*(AC17/SUM($AC17:$AH17)) -> 25.345877 | AL17: =100*(AD17/SUM($AC17:$AH17)) -> 28.242022 | AM17: =100*(AE17/SUM($AC17:$AH17)) -> 23.187604 | AN17: =100*(AF17/SUM($AC17:$AH17)) -> 4.5748017 | AO17: =100*(AG17/SUM($AC17:$AH17)) -> 4.1136322 | AP17: =100*(AH17/SUM($AC17:$AH17)) -> 14.536063 | AR17: 44652 | AS17: =HAVERQ!T177-AVERAGE(HAVERQ!T$164:T$167) -> -30.25 | AT17: =HAVERQ!U177-AVERAGE(HAVERQ!U$164:U$167) -> -10.25 | AU17: =HAVERQ!V177-AVERAGE(HAVERQ!V$164:V$167) -> -78.75 | AV17: =HAVERQ!W177-AVERAGE(HAVERQ!W$164:W$167) -> -10.75 | AW17: =HAVERQ!X177-AVERAGE(HAVERQ!X$164:X$167) -> 14.5 | AX17: =HAVERQ!Y177-AVERAGE(HAVERQ!Y$164:Y$167) -> -82.25 | AY17: =HAVERQ!Z177-AVERAGE(HAVERQ!Z$164:Z$167) -> -254.5 | AZ17: =HAVERQ!AA177-AVERAGE(HAVERQ!AA$164:AA$167) -> 42 | ... BJ17: =HAVERQ!AK177-AVERAGE(HAVERQ!AK$164:AK$167) -> -17.75 | BK17: =BM17-AVERAGE(BM$4:BM$7) -> -26.5 | BM17: =HAVERQ!AL177+HAVERQ!AM177 -> 991 | BO17: 44652 | BP17: =BZ17-AVERAGE(BZ$4:BZ$7) -> -30.25 | BQ17: =CA17-AVERAGE(CA$4:CA$7) -> -6.5 | BR17: =CB17-AVERAGE(CB$4:CB$7) -> -78.75 | BS17: =CC17-AVERAGE(CC$4:CC$7) -> -82.25 | BT17: =CD17-AVERAGE(CD$4:CD$7) -> -158.5 | BU17: =CE17-AVERAGE(CE$4:CE$7) -> 144.75 | BV17: =CF17-AVERAGE(CF$4:CF$7) -> -41.25 | BW17: =CG17-AVERAGE(CG$4:CG$7) -> 217.75 | BX17: =CH17-AVERAGE(CH$4:CH$7) -> 390.75 | BZ17: =HAVERQ!T177 -> 368 | CA17: =HAVERQ!U177+HAVERQ!W177+HAVERQ!X177 -> 419 | CB17: =HAVERQ!V177 -> 2612 | CC17: =HAVERQ!Y177 -> 2251 | CD17: =HAVERQ!Z177+HAVERQ!AB177 -> 7346 | CE17: =HAVERQ!AA177+HAVERQ!AC177 -> 3451 | CF17: =HAVERQ!AD177 -> 1094 | CG17: =HAVERQ!AE177+HAVERQ!AF177+HAVERQ!AG177 -> 7049 | CH17: =HAVERQ!AH177+HAVERQ!AI177+HAVERQ!AJ177+HAVERQ!AK177+HAVERQ!AL177+HAVERQ!AM177 -> 11331 | CI17: =HAVERQ!S177-SUM('Chart Data'!BZ17:CH17) -> -1 | CL17: =100*((DataQ!F176/DataQ!F172)-1) -> 0.6717141 | CM17: =100*(DataQ!I176/DataQ!J176) -> 22.391736 | CY17: =(HAVERQ!AQ141-AVERAGE(HAVERQ!AQ$128:AQ$183))/STDEV(HAVERQ!AQ$128:AQ$183) -> 1.3265767 | CZ17: =(DL17-AVERAGE(DL$5:DL$59))/STDEV(DL$5:DL$59) -> 1.5744418 | DA17: =(DO17-AVERAGE(DO$5:DO$59))/STDEV(DO$5:DO$59) -> 1.2512872 | DB17: =(HAVERQ!AR141-AVERAGE(HAVERQ!AR$128:AR$183))/STDEV(HAVERQ!AR$128:AR$183) -> 0.15405147 | DC17: =(DM17-AVERAGE(DM$5:DM$59))/STDEV(DM$5:DM$59) -> -1.0520677 | DD17: =(DN17-AVERAGE(DN$29:DN$59))/STDEV(DN$29:DN$59) -> #N/A | DE17: =(HAVERQ!AZ141-AVERAGE(HAVERQ!AZ$128:AZ$167,AZ$174:AZ$183))/STDEV(HAVERQ!AZ$128:AZ$167,AZ$174:AZ$183) -> 0.1823828 | DF17: =(HAVERQ!AS141-AVERAGE(HAVERQ!AS$128:AS$183))/STDEV(HAVERQ!AS$128:AS$183) -> -0.80637054 | DG17: =(DP17-AVERAGE(DP$5:DP$59))/STDEV(DP$5:DP$59) -> -0.79872539 | DH17: =(HAVERQ!AX141-AVERAGE(HAVERQ!AX$128:AX$183))/STDEV(HAVERQ!AX$128:AX$183) -> -0.42123232 | DJ17: =(DR17-AVERAGE(DR$5:DR$59))/STDEV(DR$5:DR$59) -> -2.4636272 | DL17: =100*(HAVERQ!AV141/(HAVERQ!AW141*HAVERQ!AX141/100)) -> 2.8106986 | DM17: =HAVERQ!AO141/HAVERQ!AP141 -> 0.21550696 | DN17: =100*((AVERAGE(HAVERQ!BC138:BC141)/AVERAGE(HAVERQ!BC134:BC137))-1) -> #N/A | DO17: =100*(HAVERQ!BE141+HAVERQ!BF141)/(HAVERQ!BB141+HAVERQ!BG141) -> 11.552069 | DP17: =100*((AVERAGE(HAVERQ!BA138:BA141)/AVERAGE(HAVERQ!BA134:BA137))-1) -> 1.4428413 | DR17: =(HAVERQ!AT141*HAVERQ!$AT$1)+(HAVERQ!AU141*HAVERQ!$AU$1) -> 38.166048 | DU17: Challenger job cuts | DV17: tighter | DX17: looser | DY17: Challenger
M18: 42795 | N18: =HAVERM!C453 -> 4.371 | O18: =HAVERM!B453 -> 4.5 | Q18: 42795 | R18: =MIN(HAVERM!C452:C454) -> 4.371 | S18: =V18-R18 -> 0.338 | T18: =HAVERM!B453 -> 4.5 | V18: =MAX(HAVERM!C452:C454) -> 4.709 | X18: 44743 | Y18: =HAVERQ!E178-AVERAGE(HAVERQ!E$164:E$167) -> 309.25 | Z18: =HAVERQ!F178-AVERAGE(HAVERQ!F$164:F$167) -> -280.75 | AB18: 37803 | AC18: =HAVERQ!P102 -> 1391 | AD18: =HAVERQ!O102 -> 1535 | AE18: =HAVERQ!N102 -> 1260 | AF18: =HAVERQ!M102 -> 252 | AG18: =HAVERQ!L102 -> 222 | AH18: =HAVERQ!E102-AC18-AD18-AE18-AF18-AG18 -> 806 | AJ18: 37803 | AK18: =100*(AC18/SUM($AC18:$AH18)) -> 25.448225 | AL18: =100*(AD18/SUM($AC18:$AH18)) -> 28.082693 | AM18: =100*(AE18/SUM($AC18:$AH18)) -> 23.051592 | AN18: =100*(AF18/SUM($AC18:$AH18)) -> 4.6103183 | AO18: =100*(AG18/SUM($AC18:$AH18)) -> 4.0614709 | AP18: =100*(AH18/SUM($AC18:$AH18)) -> 14.745701 | AR18: 44743 | AS18: =HAVERQ!T178-AVERAGE(HAVERQ!T$164:T$167) -> -36.25 | AT18: =HAVERQ!U178-AVERAGE(HAVERQ!U$164:U$167) -> -9.25 | AU18: =HAVERQ!V178-AVERAGE(HAVERQ!V$164:V$167) -> -73.75 | AV18: =HAVERQ!W178-AVERAGE(HAVERQ!W$164:W$167) -> -18.75 | AW18: =HAVERQ!X178-AVERAGE(HAVERQ!X$164:X$167) -> 17.5 | AX18: =HAVERQ!Y178-AVERAGE(HAVERQ!Y$164:Y$167) -> -132.25 | AY18: =HAVERQ!Z178-AVERAGE(HAVERQ!Z$164:Z$167) -> -256.5 | AZ18: =HAVERQ!AA178-AVERAGE(HAVERQ!AA$164:AA$167) -> 76 | ... BJ18: =HAVERQ!AK178-AVERAGE(HAVERQ!AK$164:AK$167) -> -13.75 | BK18: =BM18-AVERAGE(BM$4:BM$7) -> -18.5 | BM18: =HAVERQ!AL178+HAVERQ!AM178 -> 999 | BO18: 44743 | BP18: =BZ18-AVERAGE(BZ$4:BZ$7) -> -36.25 | BQ18: =CA18-AVERAGE(CA$4:CA$7) -> -10.5 | BR18: =CB18-AVERAGE(CB$4:CB$7) -> -73.75 | BS18: =CC18-AVERAGE(CC$4:CC$7) -> -132.25 | BT18: =CD18-AVERAGE(CD$4:CD$7) -> -85.5 | BU18: =CE18-AVERAGE(CE$4:CE$7) -> 194.75 | BV18: =CF18-AVERAGE(CF$4:CF$7) -> -48.25 | BW18: =CG18-AVERAGE(CG$4:CG$7) -> 234.75 | BX18: =CH18-AVERAGE(CH$4:CH$7) -> 375.75 | BZ18: =HAVERQ!T178 -> 362 | CA18: =HAVERQ!U178+HAVERQ!W178+HAVERQ!X178 -> 415 | CB18: =HAVERQ!V178 -> 2617 | CC18: =HAVERQ!Y178 -> 2201 | CD18: =HAVERQ!Z178+HAVERQ!AB178 -> 7419 | CE18: =HAVERQ!AA178+HAVERQ!AC178 -> 3501 | CF18: =HAVERQ!AD178 -> 1087 | CG18: =HAVERQ!AE178+HAVERQ!AF178+HAVERQ!AG178 -> 7066 | CH18: =HAVERQ!AH178+HAVERQ!AI178+HAVERQ!AJ178+HAVERQ!AK178+HAVERQ!AL178+HAVERQ!AM178 -> 11316 | CI18: =HAVERQ!S178-SUM('Chart Data'!BZ18:CH18) -> 1 | CL18: =100*((DataQ!F177/DataQ!F173)-1) -> 2.4865872 | CM18: =100*(DataQ!I177/DataQ!J177) -> 21.61113 | CY18: =(HAVERQ!AQ142-AVERAGE(HAVERQ!AQ$128:AQ$183))/STDEV(HAVERQ!AQ$128:AQ$183) -> 1.2656847 | CZ18: =(DL18-AVERAGE(DL$5:DL$59))/STDEV(DL$5:DL$59) -> 1.4738333 | DA18: =(DO18-AVERAGE(DO$5:DO$59))/STDEV(DO$5:DO$59) -> 1.3156844 | DB18: =(HAVERQ!AR142-AVERAGE(HAVERQ!AR$128:AR$183))/STDEV(HAVERQ!AR$128:AR$183) -> 0.15405147 | DC18: =(DM18-AVERAGE(DM$5:DM$59))/STDEV(DM$5:DM$59) -> -1.0084439 | DD18: =(DN18-AVERAGE(DN$29:DN$59))/STDEV(DN$29:DN$59) -> #N/A | DE18: =(HAVERQ!AZ142-AVERAGE(HAVERQ!AZ$128:AZ$167,AZ$174:AZ$183))/STDEV(HAVERQ!AZ$128:AZ$167,AZ$174:AZ$183) -> 1.0406548 | DF18: =(HAVERQ!AS142-AVERAGE(HAVERQ!AS$128:AS$183))/STDEV(HAVERQ!AS$128:AS$183) -> -0.82391736 | DG18: =(DP18-AVERAGE(DP$5:DP$59))/STDEV(DP$5:DP$59) -> -0.89670891 | DH18: =(HAVERQ!AX142-AVERAGE(HAVERQ!AX$128:AX$183))/STDEV(HAVERQ!AX$128:AX$183) -> 0.18361409 | DJ18: =(DR18-AVERAGE(DR$5:DR$59))/STDEV(DR$5:DR$59) -> -0.76633673 | DL18: =100*(HAVERQ!AV142/(HAVERQ!AW142*HAVERQ!AX142/100)) -> 2.7353521 | DM18: =HAVERQ!AO142/HAVERQ!AP142 -> 0.22580212 | DN18: =100*((AVERAGE(HAVERQ!BC139:BC142)/AVERAGE(HAVERQ!BC135:BC138))-1) -> #N/A | DO18: =100*(HAVERQ!BE142+HAVERQ!BF142)/(HAVERQ!BB142+HAVERQ!BG142) -> 11.649207 | DP18: =100*((AVERAGE(HAVERQ!BA139:BA142)/AVERAGE(HAVERQ!BA135:BA138))-1) -> 1.2525327 | DR18: =(HAVERQ!AT142*HAVERQ!$AT$1)+(HAVERQ!AU142*HAVERQ!$AU$1) -> 55.010575 | DU18: Involuntary part-time employment | DV18: looser | DX18: tighter | DY18: April household survey
M19: 42826 | N19: =HAVERM!C454 -> 4.56 | O19: =HAVERM!B454 -> 4.4 | Q19: 42826 | R19: =MIN(HAVERM!C453:C455) -> 4.371 | S19: =V19-R19 -> 0.189 | T19: =HAVERM!B454 -> 4.4 | V19: =MAX(HAVERM!C453:C455) -> 4.56 | X19: 44835 | Y19: =HAVERQ!E179-AVERAGE(HAVERQ!E$164:E$167) -> 337.25 | Z19: =HAVERQ!F179-AVERAGE(HAVERQ!F$164:F$167) -> -112.75 | AB19: 37895 | AC19: =HAVERQ!P103 -> 1408 | AD19: =HAVERQ!O103 -> 1557 | AE19: =HAVERQ!N103 -> 1258 | AF19: =HAVERQ!M103 -> 256 | AG19: =HAVERQ!L103 -> 221 | AH19: =HAVERQ!E103-AC19-AD19-AE19-AF19-AG19 -> 801 | AJ19: 37895 | AK19: =100*(AC19/SUM($AC19:$AH19)) -> 25.595346 | AL19: =100*(AD19/SUM($AC19:$AH19)) -> 28.303945 | AM19: =100*(AE19/SUM($AC19:$AH19)) -> 22.868569 | AN19: =100*(AF19/SUM($AC19:$AH19)) -> 4.6536993 | AO19: =100*(AG19/SUM($AC19:$AH19)) -> 4.0174514 | AP19: =100*(AH19/SUM($AC19:$AH19)) -> 14.560989 | AR19: 44835 | AS19: =HAVERQ!T179-AVERAGE(HAVERQ!T$164:T$167) -> -48.25 | AT19: =HAVERQ!U179-AVERAGE(HAVERQ!U$164:U$167) -> -8.25 | AU19: =HAVERQ!V179-AVERAGE(HAVERQ!V$164:V$167) -> -69.75 | AV19: =HAVERQ!W179-AVERAGE(HAVERQ!W$164:W$167) -> -20.75 | AW19: =HAVERQ!X179-AVERAGE(HAVERQ!X$164:X$167) -> 18.5 | AX19: =HAVERQ!Y179-AVERAGE(HAVERQ!Y$164:Y$167) -> -108.25 | AY19: =HAVERQ!Z179-AVERAGE(HAVERQ!Z$164:Z$167) -> -262.5 | AZ19: =HAVERQ!AA179-AVERAGE(HAVERQ!AA$164:AA$167) -> 89 | ... BJ19: =HAVERQ!AK179-AVERAGE(HAVERQ!AK$164:AK$167) -> -7.75 | BK19: =BM19-AVERAGE(BM$4:BM$7) -> -15.5 | BM19: =HAVERQ!AL179+HAVERQ!AM179 -> 1002 | BO19: 44835 | BP19: =BZ19-AVERAGE(BZ$4:BZ$7) -> -48.25 | BQ19: =CA19-AVERAGE(CA$4:CA$7) -> -10.5 | BR19: =CB19-AVERAGE(CB$4:CB$7) -> -69.75 | BS19: =CC19-AVERAGE(CC$4:CC$7) -> -108.25 | BT19: =CD19-AVERAGE(CD$4:CD$7) -> -48.5 | BU19: =CE19-AVERAGE(CE$4:CE$7) -> 207.75 | BV19: =CF19-AVERAGE(CF$4:CF$7) -> -16.25 | BW19: =CG19-AVERAGE(CG$4:CG$7) -> 302.75 | BX19: =CH19-AVERAGE(CH$4:CH$7) -> 406.75 | BZ19: =HAVERQ!T179 -> 350 | CA19: =HAVERQ!U179+HAVERQ!W179+HAVERQ!X179 -> 415 | CB19: =HAVERQ!V179 -> 2621 | CC19: =HAVERQ!Y179 -> 2225 | CD19: =HAVERQ!Z179+HAVERQ!AB179 -> 7456 | CE19: =HAVERQ!AA179+HAVERQ!AC179 -> 3514 | CF19: =HAVERQ!AD179 -> 1119 | CG19: =HAVERQ!AE179+HAVERQ!AF179+HAVERQ!AG179 -> 7134 | CH19: =HAVERQ!AH179+HAVERQ!AI179+HAVERQ!AJ179+HAVERQ!AK179+HAVERQ!AL179+HAVERQ!AM179 -> 11347 | CI19: =HAVERQ!S179-SUM('Chart Data'!BZ19:CH19) -> 0 | CL19: =100*((DataQ!F178/DataQ!F174)-1) -> 1.9929284 | CM19: =100*(DataQ!I178/DataQ!J178) -> 22.060521 | CY19: =(HAVERQ!AQ143-AVERAGE(HAVERQ!AQ$128:AQ$183))/STDEV(HAVERQ!AQ$128:AQ$183) -> 1.0221165 | CZ19: =(DL19-AVERAGE(DL$5:DL$59))/STDEV(DL$5:DL$59) -> 1.2790308 | DA19: =(DO19-AVERAGE(DO$5:DO$59))/STDEV(DO$5:DO$59) -> 1.183487 | DB19: =(HAVERQ!AR143-AVERAGE(HAVERQ!AR$128:AR$183))/STDEV(HAVERQ!AR$128:AR$183) -> -0.16945662 | DC19: =(DM19-AVERAGE(DM$5:DM$59))/STDEV(DM$5:DM$59) -> -0.93256522 | DD19: =(DN19-AVERAGE(DN$29:DN$59))/STDEV(DN$29:DN$59) -> #N/A | DE19: =(HAVERQ!AZ143-AVERAGE(HAVERQ!AZ$128:AZ$167,AZ$174:AZ$183))/STDEV(HAVERQ!AZ$128:AZ$167,AZ$174:AZ$183) -> 0.1823828 | DF19: =(HAVERQ!AS143-AVERAGE(HAVERQ!AS$128:AS$183))/STDEV(HAVERQ!AS$128:AS$183) -> -0.64844913 | DG19: =(DP19-AVERAGE(DP$5:DP$59))/STDEV(DP$5:DP$59) -> -0.86065577 | DH19: =(HAVERQ!AX143-AVERAGE(HAVERQ!AX$128:AX$183))/STDEV(HAVERQ!AX$128:AX$183) -> 0.18361409 | DJ19: =(DR19-AVERAGE(DR$5:DR$59))/STDEV(DR$5:DR$59) -> -0.099100741 | DL19: =100*(HAVERQ!AV143/(HAVERQ!AW143*HAVERQ!AX143/100)) -> 2.589463 | DM19: =HAVERQ!AO143/HAVERQ!AP143 -> 0.24370936 | DN19: =100*((AVERAGE(HAVERQ!BC140:BC143)/AVERAGE(HAVERQ!BC136:BC139))-1) -> #N/A | DO19: =100*(HAVERQ!BE143+HAVERQ!BF143)/(HAVERQ!BB143+HAVERQ!BG143) -> 11.449798 | DP19: =100*((AVERAGE(HAVERQ!BA140:BA143)/AVERAGE(HAVERQ!BA136:BA139))-1) -> 1.3225569 | DR19: =(HAVERQ!AT143*HAVERQ!$AT$1)+(HAVERQ!AU143*HAVERQ!$AU$1) -> 61.632467 | DU19: Flows from unemployed to employed | DV19: tighter | DX19: looser | DY19: April household survey
M20: 42856 | N20: =HAVERM!C455 -> 4.391 | O20: =HAVERM!B455 -> 4.4 | Q20: 42856 | R20: =MIN(HAVERM!C454:C456) -> 4.311 | S20: =V20-R20 -> 0.249 | T20: =HAVERM!B455 -> 4.4 | V20: =MAX(HAVERM!C454:C456) -> 4.56 | X20: 44927 | Y20: =HAVERQ!E180-AVERAGE(HAVERQ!E$164:E$167) -> 373.25 | Z20: =HAVERQ!F180-AVERAGE(HAVERQ!F$164:F$167) -> 163.25 | AB20: 37987 | AC20: =HAVERQ!P104 -> 1426 | AD20: =HAVERQ!O104 -> 1560 | AE20: =HAVERQ!N104 -> 1267 | AF20: =HAVERQ!M104 -> 260 | AG20: =HAVERQ!L104 -> 219 | AH20: =HAVERQ!E104-AC20-AD20-AE20-AF20-AG20 -> 802 | AJ20: 37987 | AK20: =100*(AC20/SUM($AC20:$AH20)) -> 25.76798 | AL20: =100*(AD20/SUM($AC20:$AH20)) -> 28.189375 | AM20: =100*(AE20/SUM($AC20:$AH20)) -> 22.894832 | AN20: =100*(AF20/SUM($AC20:$AH20)) -> 4.6982291 | AO20: =100*(AG20/SUM($AC20:$AH20)) -> 3.9573545 | AP20: =100*(AH20/SUM($AC20:$AH20)) -> 14.49223 | AR20: 44927 | AS20: =HAVERQ!T180-AVERAGE(HAVERQ!T$164:T$167) -> -31.25 | AT20: =HAVERQ!U180-AVERAGE(HAVERQ!U$164:U$167) -> -4.25 | AU20: =HAVERQ!V180-AVERAGE(HAVERQ!V$164:V$167) -> -77.75 | AV20: =HAVERQ!W180-AVERAGE(HAVERQ!W$164:W$167) -> -20.75 | AW20: =HAVERQ!X180-AVERAGE(HAVERQ!X$164:X$167) -> 28.5 | AX20: =HAVERQ!Y180-AVERAGE(HAVERQ!Y$164:Y$167) -> -75.25 | AY20: =HAVERQ!Z180-AVERAGE(HAVERQ!Z$164:Z$167) -> -230.5 | AZ20: =HAVERQ!AA180-AVERAGE(HAVERQ!AA$164:AA$167) -> 95 | ... BJ20: =HAVERQ!AK180-AVERAGE(HAVERQ!AK$164:AK$167) -> -1.75 | BK20: =BM20-AVERAGE(BM$4:BM$7) -> -22.5 | BM20: =HAVERQ!AL180+HAVERQ!AM180 -> 995 | BO20: 44927 | BP20: =BZ20-AVERAGE(BZ$4:BZ$7) -> -31.25 | BQ20: =CA20-AVERAGE(CA$4:CA$7) -> 3.5 | BR20: =CB20-AVERAGE(CB$4:CB$7) -> -77.75 | BS20: =CC20-AVERAGE(CC$4:CC$7) -> -75.25 | BT20: =CD20-AVERAGE(CD$4:CD$7) -> -30.5 | BU20: =CE20-AVERAGE(CE$4:CE$7) -> 245.75 | BV20: =CF20-AVERAGE(CF$4:CF$7) -> 4.75 | BW20: =CG20-AVERAGE(CG$4:CG$7) -> 393.75 | BX20: =CH20-AVERAGE(CH$4:CH$7) -> 538.75 | BZ20: =HAVERQ!T180 -> 367 | CA20: =HAVERQ!U180+HAVERQ!W180+HAVERQ!X180 -> 429 | CB20: =HAVERQ!V180 -> 2613 | CC20: =HAVERQ!Y180 -> 2258 | CD20: =HAVERQ!Z180+HAVERQ!AB180 -> 7474 | CE20: =HAVERQ!AA180+HAVERQ!AC180 -> 3552 | CF20: =HAVERQ!AD180 -> 1140 | CG20: =HAVERQ!AE180+HAVERQ!AF180+HAVERQ!AG180 -> 7225 | CH20: =HAVERQ!AH180+HAVERQ!AI180+HAVERQ!AJ180+HAVERQ!AK180+HAVERQ!AL180+HAVERQ!AM180 -> 11479 | CI20: =HAVERQ!S180-SUM('Chart Data'!BZ20:CH20) -> 0 | CK20: 2016 | CL20: =100*((DataQ!F179/DataQ!F175)-1) -> 1.5236579 | CM20: =100*(DataQ!I179/DataQ!J179) -> 21.961555 | CX20: 2014 | CY20: =(HAVERQ!AQ144-AVERAGE(HAVERQ!AQ$128:AQ$183))/STDEV(HAVERQ!AQ$128:AQ$183) -> 0.71765627 | CZ20: =(DL20-AVERAGE(DL$5:DL$59))/STDEV(DL$5:DL$59) -> 1.1449321 | DA20: =(DO20-AVERAGE(DO$5:DO$59))/STDEV(DO$5:DO$59) -> 1.1221869 | DB20: =(HAVERQ!AR144-AVERAGE(HAVERQ!AR$128:AR$183))/STDEV(HAVERQ!AR$128:AR$183) -> 0.15405147 | DC20: =(DM20-AVERAGE(DM$5:DM$59))/STDEV(DM$5:DM$59) -> -0.83056266 | DD20: =(DN20-AVERAGE(DN$29:DN$59))/STDEV(DN$29:DN$59) -> #N/A | DE20: =(HAVERQ!AZ144-AVERAGE(HAVERQ!AZ$128:AZ$167,AZ$174:AZ$183))/STDEV(HAVERQ!AZ$128:AZ$167,AZ$174:AZ$183) -> 0.61151881 | DF20: =(HAVERQ!AS144-AVERAGE(HAVERQ!AS$128:AS$183))/STDEV(HAVERQ!AS$128:AS$183) -> -0.33260631 | DG20: =(DP20-AVERAGE(DP$5:DP$59))/STDEV(DP$5:DP$59) -> -0.67246359 | DH20: =(HAVERQ!AX144-AVERAGE(HAVERQ!AX$128:AX$183))/STDEV(HAVERQ!AX$128:AX$183) -> 0.48603729 | DJ20: =(DR20-AVERAGE(DR$5:DR$59))/STDEV(DR$5:DR$59) -> 0.016261637 | DL20: =100*(HAVERQ!AV144/(HAVERQ!AW144*HAVERQ!AX144/100)) -> 2.4890354 | DM20: =HAVERQ!AO144/HAVERQ!AP144 -> 0.2677818 | DN20: =100*((AVERAGE(HAVERQ!BC141:BC144)/AVERAGE(HAVERQ!BC137:BC140))-1) -> #N/A | DO20: =100*(HAVERQ!BE144+HAVERQ!BF144)/(HAVERQ!BB144+HAVERQ!BG144) -> 11.357332 | DP20: =100*((AVERAGE(HAVERQ!BA141:BA144)/AVERAGE(HAVERQ!BA137:BA140))-1) -> 1.6880734 | DR20: =(HAVERQ!AT144*HAVERQ!$AT$1)+(HAVERQ!AU144*HAVERQ!$AU$1) -> 62.777365 | DU20: Job losers | DV20: looser | DX20: looser | DY20: April household survey
M21: 42887 | N21: =HAVERM!C456 -> 4.311 | O21: =HAVERM!B456 -> 4.3 | Q21: 42887 | R21: =MIN(HAVERM!C455:C457) -> 4.311 | S21: =V21-R21 -> 0.08 | T21: =HAVERM!B456 -> 4.3 | V21: =MAX(HAVERM!C455:C457) -> 4.391 | X21: 45017 | Y21: =HAVERQ!E181-AVERAGE(HAVERQ!E$164:E$167) -> 412.25 | Z21: =HAVERQ!F181-AVERAGE(HAVERQ!F$164:F$167) -> -68.75 | AB21: 38078 | AC21: =HAVERQ!P105 -> 1430 | AD21: =HAVERQ!O105 -> 1569 | AE21: =HAVERQ!N105 -> 1270 | AF21: =HAVERQ!M105 -> 264 | AG21: =HAVERQ!L105 -> 218 | AH21: =HAVERQ!E105-AC21-AD21-AE21-AF21-AG21 -> 794 | AJ21: 38078 | AK21: =100*(AC21/SUM($AC21:$AH21)) -> 25.788999 | AL21: =100*(AD21/SUM($AC21:$AH21)) -> 28.295762 | AM21: =100*(AE21/SUM($AC21:$AH21)) -> 22.903517 | AN21: =100*(AF21/SUM($AC21:$AH21)) -> 4.761046 | AO21: =100*(AG21/SUM($AC21:$AH21)) -> 3.9314698 | AP21: =100*(AH21/SUM($AC21:$AH21)) -> 14.319206 | AR21: 45017 | AS21: =HAVERQ!T181-AVERAGE(HAVERQ!T$164:T$167) -> -60.25 | AT21: =HAVERQ!U181-AVERAGE(HAVERQ!U$164:U$167) -> -11.25 | AU21: =HAVERQ!V181-AVERAGE(HAVERQ!V$164:V$167) -> -114.75 | AV21: =HAVERQ!W181-AVERAGE(HAVERQ!W$164:W$167) -> -14.75 | AW21: =HAVERQ!X181-AVERAGE(HAVERQ!X$164:X$167) -> 27.5 | AX21: =HAVERQ!Y181-AVERAGE(HAVERQ!Y$164:Y$167) -> -73.25 | AY21: =HAVERQ!Z181-AVERAGE(HAVERQ!Z$164:Z$167) -> -292.5 | AZ21: =HAVERQ!AA181-AVERAGE(HAVERQ!AA$164:AA$167) -> 45 | ... BJ21: =HAVERQ!AK181-AVERAGE(HAVERQ!AK$164:AK$167) -> 12.25 | BK21: =BM21-AVERAGE(BM$4:BM$7) -> -66.5 | BM21: =HAVERQ!AL181+HAVERQ!AM181 -> 951 | BO21: 45017 | BP21: =BZ21-AVERAGE(BZ$4:BZ$7) -> -60.25 | BQ21: =CA21-AVERAGE(CA$4:CA$7) -> 1.5 | BR21: =CB21-AVERAGE(CB$4:CB$7) -> -114.75 | BS21: =CC21-AVERAGE(CC$4:CC$7) -> -73.25 | BT21: =CD21-AVERAGE(CD$4:CD$7) -> -90.5 | BU21: =CE21-AVERAGE(CE$4:CE$7) -> 185.75 | BV21: =CF21-AVERAGE(CF$4:CF$7) -> 1.75 | BW21: =CG21-AVERAGE(CG$4:CG$7) -> 350.75 | BX21: =CH21-AVERAGE(CH$4:CH$7) -> 537.75 | BZ21: =HAVERQ!T181 -> 338 | CA21: =HAVERQ!U181+HAVERQ!W181+HAVERQ!X181 -> 427 | CB21: =HAVERQ!V181 -> 2576 | CC21: =HAVERQ!Y181 -> 2260 | CD21: =HAVERQ!Z181+HAVERQ!AB181 -> 7414 | CE21: =HAVERQ!AA181+HAVERQ!AC181 -> 3492 | CF21: =HAVERQ!AD181 -> 1137 | CG21: =HAVERQ!AE181+HAVERQ!AF181+HAVERQ!AG181 -> 7182 | CH21: =HAVERQ!AH181+HAVERQ!AI181+HAVERQ!AJ181+HAVERQ!AK181+HAVERQ!AL181+HAVERQ!AM181 -> 11478 | CI21: =HAVERQ!S181-SUM('Chart Data'!BZ21:CH21) -> 0 | CL21: =100*((DataQ!F180/DataQ!F176)-1) -> 2.6310611 | CM21: =100*(DataQ!I180/DataQ!J180) -> 21.599725 | CY21: =(HAVERQ!AQ145-AVERAGE(HAVERQ!AQ$128:AQ$183))/STDEV(HAVERQ!AQ$128:AQ$183) -> 0.47408808 | CZ21: =(DL21-AVERAGE(DL$5:DL$59))/STDEV(DL$5:DL$59) -> 0.83060629 | DA21: =(DO21-AVERAGE(DO$5:DO$59))/STDEV(DO$5:DO$59) -> 0.96299355 | DB21: =(HAVERQ!AR145-AVERAGE(HAVERQ!AR$128:AR$183))/STDEV(HAVERQ!AR$128:AR$183) -> -0.1155386 | DC21: =(DM21-AVERAGE(DM$5:DM$59))/STDEV(DM$5:DM$59) -> -0.58912182 | DD21: =(DN21-AVERAGE(DN$29:DN$59))/STDEV(DN$29:DN$59) -> #N/A | DE21: =(HAVERQ!AZ145-AVERAGE(HAVERQ!AZ$128:AZ$167,AZ$174:AZ$183))/STDEV(HAVERQ!AZ$128:AZ$167,AZ$174:AZ$183) -> 1.0406548 | DF21: =(HAVERQ!AS145-AVERAGE(HAVERQ!AS$128:AS$183))/STDEV(HAVERQ!AS$128:AS$183) -> -0.19223172 | DG21: =(DP21-AVERAGE(DP$5:DP$59))/STDEV(DP$5:DP$59) -> -0.98767329 | DH21: =(HAVERQ!AX145-AVERAGE(HAVERQ!AX$128:AX$183))/STDEV(HAVERQ!AX$128:AX$183) -> 0.18361409 | DJ21: =(DR21-AVERAGE(DR$5:DR$59))/STDEV(DR$5:DR$59) -> -0.9130307 | DL21: =100*(HAVERQ!AV145/(HAVERQ!AW145*HAVERQ!AX145/100)) -> 2.2536344 | DM21: =HAVERQ!AO145/HAVERQ!AP145 -> 0.32476144 | DN21: =100*((AVERAGE(HAVERQ!BC142:BC145)/AVERAGE(HAVERQ!BC138:BC141))-1) -> #N/A | DO21: =100*(HAVERQ!BE145+HAVERQ!BF145)/(HAVERQ!BB145+HAVERQ!BG145) -> 11.117203 | DP21: =100*((AVERAGE(HAVERQ!BA142:BA145)/AVERAGE(HAVERQ!BA138:BA141))-1) -> 1.075857 | DR21: =(HAVERQ!AT145*HAVERQ!$AT$1)+(HAVERQ!AU145*HAVERQ!$AU$1) -> 53.554731 | DT21: Hiring | DU21: Private payroll employment | DV21: looser | DX21: tighter | DY21: April establishment survey
M22: 42917 | N22: =HAVERM!C457 -> 4.331 | O22: =HAVERM!B457 -> 4.3 | Q22: 42917 | R22: =MIN(HAVERM!C456:C458) -> 4.311 | S22: =V22-R22 -> 0.02 | T22: =HAVERM!B457 -> 4.3 | V22: =MAX(HAVERM!C456:C458) -> 4.331 | X22: 45108 | Y22: =HAVERQ!E182-AVERAGE(HAVERQ!E$164:E$167) -> 461.25 | Z22: =HAVERQ!F182-AVERAGE(HAVERQ!F$164:F$167) -> -39.75 | AB22: 38169 | AC22: =HAVERQ!P106 -> 1443 | AD22: =HAVERQ!O106 -> 1573 | AE22: =HAVERQ!N106 -> 1279 | AF22: =HAVERQ!M106 -> 265 | AG22: =HAVERQ!L106 -> 216 | AH22: =HAVERQ!E106-AC22-AD22-AE22-AF22-AG22 -> 801 | AJ22: 38169 | AK22: =100*(AC22/SUM($AC22:$AH22)) -> 25.874126 | AL22: =100*(AD22/SUM($AC22:$AH22)) -> 28.205128 | AM22: =100*(AE22/SUM($AC22:$AH22)) -> 22.933477 | AN22: =100*(AF22/SUM($AC22:$AH22)) -> 4.7516586 | AO22: =100*(AG22/SUM($AC22:$AH22)) -> 3.87305 | AP22: =100*(AH22/SUM($AC22:$AH22)) -> 14.362561 | AR22: 45108 | AS22: =HAVERQ!T182-AVERAGE(HAVERQ!T$164:T$167) -> -21.25 | AT22: =HAVERQ!U182-AVERAGE(HAVERQ!U$164:U$167) -> -10.25 | AU22: =HAVERQ!V182-AVERAGE(HAVERQ!V$164:V$167) -> -91.75 | AV22: =HAVERQ!W182-AVERAGE(HAVERQ!W$164:W$167) -> -15.75 | AW22: =HAVERQ!X182-AVERAGE(HAVERQ!X$164:X$167) -> 19.5 | AX22: =HAVERQ!Y182-AVERAGE(HAVERQ!Y$164:Y$167) -> -86.25 | AY22: =HAVERQ!Z182-AVERAGE(HAVERQ!Z$164:Z$167) -> -244.5 | AZ22: =HAVERQ!AA182-AVERAGE(HAVERQ!AA$164:AA$167) -> 47 | ... BJ22: =HAVERQ!AK182-AVERAGE(HAVERQ!AK$164:AK$167) -> 41.25 | BK22: =BM22-AVERAGE(BM$4:BM$7) -> -47.5 | BM22: =HAVERQ!AL182+HAVERQ!AM182 -> 970 | BO22: 45108 | BP22: =BZ22-AVERAGE(BZ$4:BZ$7) -> -21.25 | BQ22: =CA22-AVERAGE(CA$4:CA$7) -> -6.5 | BR22: =CB22-AVERAGE(CB$4:CB$7) -> -91.75 | BS22: =CC22-AVERAGE(CC$4:CC$7) -> -86.25 | BT22: =CD22-AVERAGE(CD$4:CD$7) -> -63.5 | BU22: =CE22-AVERAGE(CE$4:CE$7) -> 130.75 | BV22: =CF22-AVERAGE(CF$4:CF$7) -> -4.25 | BW22: =CG22-AVERAGE(CG$4:CG$7) -> 372.75 | BX22: =CH22-AVERAGE(CH$4:CH$7) -> 631.75 | BZ22: =HAVERQ!T182 -> 377 | CA22: =HAVERQ!U182+HAVERQ!W182+HAVERQ!X182 -> 419 | CB22: =HAVERQ!V182 -> 2599 | CC22: =HAVERQ!Y182 -> 2247 | CD22: =HAVERQ!Z182+HAVERQ!AB182 -> 7441 | CE22: =HAVERQ!AA182+HAVERQ!AC182 -> 3437 | CF22: =HAVERQ!AD182 -> 1131 | CG22: =HAVERQ!AE182+HAVERQ!AF182+HAVERQ!AG182 -> 7204 | CH22: =HAVERQ!AH182+HAVERQ!AI182+HAVERQ!AJ182+HAVERQ!AK182+HAVERQ!AL182+HAVERQ!AM182 -> 11572 | CI22: =HAVERQ!S182-SUM('Chart Data'!BZ22:CH22) -> 2 | CL22: =100*((DataQ!F181/DataQ!F177)-1) -> 2.2021638 | CM22: =100*(DataQ!I181/DataQ!J181) -> 22.110978 | CY22: =(HAVERQ!AQ146-AVERAGE(HAVERQ!AQ$128:AQ$183))/STDEV(HAVERQ!AQ$128:AQ$183) -> 0.29141194 | CZ22: =(DL22-AVERAGE(DL$5:DL$59))/STDEV(DL$5:DL$59) -> 0.62644391 | DA22: =(DO22-AVERAGE(DO$5:DO$59))/STDEV(DO$5:DO$59) -> 0.8858793 | DB22: =(HAVERQ!AR146-AVERAGE(HAVERQ!AR$128:AR$183))/STDEV(HAVERQ!AR$128:AR$183) -> -0.60080074 | DC22: =(DM22-AVERAGE(DM$5:DM$59))/STDEV(DM$5:DM$59) -> -0.45417402 | DD22: =(DN22-AVERAGE(DN$29:DN$59))/STDEV(DN$29:DN$59) -> #N/A | DE22: =(HAVERQ!AZ146-AVERAGE(HAVERQ!AZ$128:AZ$167,AZ$174:AZ$183))/STDEV(HAVERQ!AZ$128:AZ$167,AZ$174:AZ$183) -> 1.0406548 | DF22: =(HAVERQ!AS146-AVERAGE(HAVERQ!AS$128:AS$183))/STDEV(HAVERQ!AS$128:AS$183) -> 0.1937984 | DG22: =(DP22-AVERAGE(DP$5:DP$59))/STDEV(DP$5:DP$59) -> -0.97025064 | DH22: =(HAVERQ!AX146-AVERAGE(HAVERQ!AX$128:AX$183))/STDEV(HAVERQ!AX$128:AX$183) -> -0.11880912 | DJ22: =(DR22-AVERAGE(DR$5:DR$59))/STDEV(DR$5:DR$59) -> -0.3554553 | DL22: =100*(HAVERQ!AV146/(HAVERQ!AW146*HAVERQ!AX146/100)) -> 2.1007356 | DM22: =HAVERQ!AO146/HAVERQ!AP146 -> 0.3566089 | DN22: =100*((AVERAGE(HAVERQ!BC143:BC146)/AVERAGE(HAVERQ!BC139:BC142))-1) -> #N/A | DO22: =100*(HAVERQ!BE146+HAVERQ!BF146)/(HAVERQ!BB146+HAVERQ!BG146) -> 11.000883 | DP22: =100*((AVERAGE(HAVERQ!BA143:BA146)/AVERAGE(HAVERQ!BA139:BA142))-1) -> 1.1096962 | DR22: =(HAVERQ!AT146*HAVERQ!$AT$1)+(HAVERQ!AU146*HAVERQ!$AU$1) -> 59.088311 | DU22: Temporary jobs | DV22: looser | DX22: looser | DY22: April establishment survey
M23: 42948 | N23: =HAVERM!C458 -> 4.331 | O23: =HAVERM!B458 -> 4.3 | Q23: 42948 | R23: =MIN(HAVERM!C457:C459) -> 4.133 | S23: =V23-R23 -> 0.198 | T23: =HAVERM!B458 -> 4.3 | V23: =MAX(HAVERM!C457:C459) -> 4.331 | X23: 45200 | Y23: =HAVERQ!E183-AVERAGE(HAVERQ!E$164:E$167) -> 493.25 | Z23: =HAVERQ!F183-AVERAGE(HAVERQ!F$164:F$167) -> -109.75 | AB23: 38261 | AC23: =HAVERQ!P107 -> 1456 | AD23: =HAVERQ!O107 -> 1576 | AE23: =HAVERQ!N107 -> 1278 | AF23: =HAVERQ!M107 -> 267 | AG23: =HAVERQ!L107 -> 214 | AH23: =HAVERQ!E107-AC23-AD23-AE23-AF23-AG23 -> 806 | AJ23: 38261 | AK23: =100*(AC23/SUM($AC23:$AH23)) -> 26.013936 | AL23: =100*(AD23/SUM($AC23:$AH23)) -> 28.157942 | AM23: =100*(AE23/SUM($AC23:$AH23)) -> 22.833661 | AN23: =100*(AF23/SUM($AC23:$AH23)) -> 4.7704127 | AO23: =100*(AG23/SUM($AC23:$AH23)) -> 3.8234769 | AP23: =100*(AH23/SUM($AC23:$AH23)) -> 14.400572 | AR23: 45200 | AS23: =HAVERQ!T183-AVERAGE(HAVERQ!T$164:T$167) -> 4.75 | AT23: =HAVERQ!U183-AVERAGE(HAVERQ!U$164:U$167) -> -11.25 | AU23: =HAVERQ!V183-AVERAGE(HAVERQ!V$164:V$167) -> -91.75 | AV23: =HAVERQ!W183-AVERAGE(HAVERQ!W$164:W$167) -> -11.75 | AW23: =HAVERQ!X183-AVERAGE(HAVERQ!X$164:X$167) -> 17.5 | AX23: =HAVERQ!Y183-AVERAGE(HAVERQ!Y$164:Y$167) -> -120.25 | AY23: =HAVERQ!Z183-AVERAGE(HAVERQ!Z$164:Z$167) -> -239.5 | AZ23: =HAVERQ!AA183-AVERAGE(HAVERQ!AA$164:AA$167) -> 108 | ... BJ23: =HAVERQ!AK183-AVERAGE(HAVERQ!AK$164:AK$167) -> 47.25 | BK23: =BM23-AVERAGE(BM$4:BM$7) -> -62.5 | BM23: =HAVERQ!AL183+HAVERQ!AM183 -> 955 | BO23: 45200 | BP23: =BZ23-AVERAGE(BZ$4:BZ$7) -> 4.75 | BQ23: =CA23-AVERAGE(CA$4:CA$7) -> -5.5 | BR23: =CB23-AVERAGE(CB$4:CB$7) -> -91.75 | BS23: =CC23-AVERAGE(CC$4:CC$7) -> -120.25 | BT23: =CD23-AVERAGE(CD$4:CD$7) -> -95.5 | BU23: =CE23-AVERAGE(CE$4:CE$7) -> 235.75 | BV23: =CF23-AVERAGE(CF$4:CF$7) -> 28.75 | BW23: =CG23-AVERAGE(CG$4:CG$7) -> 250.75 | BX23: =CH23-AVERAGE(CH$4:CH$7) -> 732.75 | BZ23: =HAVERQ!T183 -> 403 | CA23: =HAVERQ!U183+HAVERQ!W183+HAVERQ!X183 -> 420 | CB23: =HAVERQ!V183 -> 2599 | CC23: =HAVERQ!Y183 -> 2213 | CD23: =HAVERQ!Z183+HAVERQ!AB183 -> 7409 | CE23: =HAVERQ!AA183+HAVERQ!AC183 -> 3542 | CF23: =HAVERQ!AD183 -> 1164 | CG23: =HAVERQ!AE183+HAVERQ!AF183+HAVERQ!AG183 -> 7082 | CH23: =HAVERQ!AH183+HAVERQ!AI183+HAVERQ!AJ183+HAVERQ!AK183+HAVERQ!AL183+HAVERQ!AM183 -> 11673 | CI23: =HAVERQ!S183-SUM('Chart Data'!BZ23:CH23) -> 1 | CL23: =100*((DataQ!F182/DataQ!F178)-1) -> 1.7339906 | CM23: =100*(DataQ!I182/DataQ!J182) -> 22.577352 | CY23: =(HAVERQ!AQ147-AVERAGE(HAVERQ!AQ$128:AQ$183))/STDEV(HAVERQ!AQ$128:AQ$183) -> 0.1087358 | CZ23: =(DL23-AVERAGE(DL$5:DL$59))/STDEV(DL$5:DL$59) -> 0.41434024 | DA23: =(DO23-AVERAGE(DO$5:DO$59))/STDEV(DO$5:DO$59) -> 0.83169867 | DB23: =(HAVERQ!AR147-AVERAGE(HAVERQ!AR$128:AR$183))/STDEV(HAVERQ!AR$128:AR$183) -> -0.27729265 | DC23: =(DM23-AVERAGE(DM$5:DM$59))/STDEV(DM$5:DM$59) -> -0.3571734 | DD23: =(DN23-AVERAGE(DN$29:DN$59))/STDEV(DN$29:DN$59) -> #N/A | DE23: =(HAVERQ!AZ147-AVERAGE(HAVERQ!AZ$128:AZ$167,AZ$174:AZ$183))/STDEV(HAVERQ!AZ$128:AZ$167,AZ$174:AZ$183) -> 1.0406548 | DF23: =(HAVERQ!AS147-AVERAGE(HAVERQ!AS$128:AS$183))/STDEV(HAVERQ!AS$128:AS$183) -> 0.36926663 | DG23: =(DP23-AVERAGE(DP$5:DP$59))/STDEV(DP$5:DP$59) -> -0.83220782 | DH23: =(HAVERQ!AX147-AVERAGE(HAVERQ!AX$128:AX$183))/STDEV(HAVERQ!AX$128:AX$183) -> -0.42123232 | DJ23: =(DR23-AVERAGE(DR$5:DR$59))/STDEV(DR$5:DR$59) -> -0.67340749 | DL23: =100*(HAVERQ!AV147/(HAVERQ!AW147*HAVERQ!AX147/100)) -> 1.9418895 | DM23: =HAVERQ!AO147/HAVERQ!AP147 -> 0.37950089 | DN23: =100*((AVERAGE(HAVERQ!BC144:BC147)/AVERAGE(HAVERQ!BC140:BC143))-1) -> #N/A | DO23: =100*(HAVERQ!BE147+HAVERQ!BF147)/(HAVERQ!BB147+HAVERQ!BG147) -> 10.919156 | DP23: =100*((AVERAGE(HAVERQ!BA144:BA147)/AVERAGE(HAVERQ!BA140:BA143))-1) -> 1.37781 | DR23: =(HAVERQ!AT147*HAVERQ!$AT$1)+(HAVERQ!AU147*HAVERQ!$AU$1) -> 55.932838 | DU23: Average hours worked | DV23: looser | DX23: tighter | DY23: April establishment survey
M24: 42979 | N24: =HAVERM!C459 -> 4.133 | O24: =HAVERM!B459 -> 4.2 | Q24: 42979 | R24: =MIN(HAVERM!C458:C460) -> 4.133 | S24: =V24-R24 -> 0.198 | T24: =HAVERM!B459 -> 4.2 | V24: =MAX(HAVERM!C458:C460) -> 4.331 | X24: 45292 | Y24: =HAVERQ!E184-AVERAGE(HAVERQ!E$164:E$167) -> 519.25 | Z24: =HAVERQ!F184-AVERAGE(HAVERQ!F$164:F$167) -> -110.75 | AB24: 38353 | AC24: =HAVERQ!P108 -> 1466 | AD24: =HAVERQ!O108 -> 1581 | AE24: =HAVERQ!N108 -> 1280 | AF24: =HAVERQ!M108 -> 271 | AG24: =HAVERQ!L108 -> 212 | AH24: =HAVERQ!E108-AC24-AD24-AE24-AF24-AG24 -> 805 | AJ24: 38353 | AK24: =100*(AC24/SUM($AC24:$AH24)) -> 26.108638 | AL24: =100*(AD24/SUM($AC24:$AH24)) -> 28.156723 | AM24: =100*(AE24/SUM($AC24:$AH24)) -> 22.796082 | AN24: =100*(AF24/SUM($AC24:$AH24)) -> 4.826358 | AO24: =100*(AG24/SUM($AC24:$AH24)) -> 3.7756011 | AP24: =100*(AH24/SUM($AC24:$AH24)) -> 14.336598 | AR24: 45292 | AS24: =HAVERQ!T184-AVERAGE(HAVERQ!T$164:T$167) -> -26.25 | AT24: =HAVERQ!U184-AVERAGE(HAVERQ!U$164:U$167) -> -13.25 | AU24: =HAVERQ!V184-AVERAGE(HAVERQ!V$164:V$167) -> -111.75 | AV24: =HAVERQ!W184-AVERAGE(HAVERQ!W$164:W$167) -> -10.75 | AW24: =HAVERQ!X184-AVERAGE(HAVERQ!X$164:X$167) -> 23.5 | AX24: =HAVERQ!Y184-AVERAGE(HAVERQ!Y$164:Y$167) -> -99.25 | AY24: =HAVERQ!Z184-AVERAGE(HAVERQ!Z$164:Z$167) -> -229.5 | AZ24: =HAVERQ!AA184-AVERAGE(HAVERQ!AA$164:AA$167) -> 106 | ... BJ24: =HAVERQ!AK184-AVERAGE(HAVERQ!AK$164:AK$167) -> 80.25 | BK24: =BM24-AVERAGE(BM$4:BM$7) -> 22.5 | BM24: =HAVERQ!AL184+HAVERQ!AM184 -> 1040 | BO24: 45292 | BP24: =BZ24-AVERAGE(BZ$4:BZ$7) -> -26.25 | BQ24: =CA24-AVERAGE(CA$4:CA$7) -> -0.5 | BR24: =CB24-AVERAGE(CB$4:CB$7) -> -111.75 | BS24: =CC24-AVERAGE(CC$4:CC$7) -> -99.25 | BT24: =CD24-AVERAGE(CD$4:CD$7) -> -62.5 | BU24: =CE24-AVERAGE(CE$4:CE$7) -> 223.75 | BV24: =CF24-AVERAGE(CF$4:CF$7) -> 20.75 | BW24: =CG24-AVERAGE(CG$4:CG$7) -> 317.75 | BX24: =CH24-AVERAGE(CH$4:CH$7) -> 962.75 | BZ24: =HAVERQ!T184 -> 372 | CA24: =HAVERQ!U184+HAVERQ!W184+HAVERQ!X184 -> 425 | CB24: =HAVERQ!V184 -> 2579 | CC24: =HAVERQ!Y184 -> 2234 | CD24: =HAVERQ!Z184+HAVERQ!AB184 -> 7442 | CE24: =HAVERQ!AA184+HAVERQ!AC184 -> 3530 | CF24: =HAVERQ!AD184 -> 1156 | CG24: =HAVERQ!AE184+HAVERQ!AF184+HAVERQ!AG184 -> 7149 | CH24: =HAVERQ!AH184+HAVERQ!AI184+HAVERQ!AJ184+HAVERQ!AK184+HAVERQ!AL184+HAVERQ!AM184 -> 11903 | CI24: =HAVERQ!S184-SUM('Chart Data'!BZ24:CH24) -> 1 | CK24: 2017 | CL24: =100*((DataQ!F183/DataQ!F179)-1) -> 1.7811314 | CM24: =100*(DataQ!I183/DataQ!J183) -> 22.554465 | CX24: 2015 | CY24: =(HAVERQ!AQ148-AVERAGE(HAVERQ!AQ$128:AQ$183))/STDEV(HAVERQ!AQ$128:AQ$183) -> -0.013048296 | CZ24: =(DL24-AVERAGE(DL$5:DL$59))/STDEV(DL$5:DL$59) -> 0.20320335 | DA24: =(DO24-AVERAGE(DO$5:DO$59))/STDEV(DO$5:DO$59) -> 0.88360899 | DB24: =(HAVERQ!AR148-AVERAGE(HAVERQ!AR$128:AR$183))/STDEV(HAVERQ!AR$128:AR$183) -> -0.22337463 | DC24: =(DM24-AVERAGE(DM$5:DM$59))/STDEV(DM$5:DM$59) -> -0.32461296 | DD24: =(DN24-AVERAGE(DN$29:DN$59))/STDEV(DN$29:DN$59) -> #N/A | DE24: =(HAVERQ!AZ148-AVERAGE(HAVERQ!AZ$128:AZ$167,AZ$174:AZ$183))/STDEV(HAVERQ!AZ$128:AZ$167,AZ$174:AZ$183) -> 0.61151881 | DF24: =(HAVERQ!AS148-AVERAGE(HAVERQ!AS$128:AS$183))/STDEV(HAVERQ!AS$128:AS$183) -> 0.28153252 | DG24: =(DP24-AVERAGE(DP$5:DP$59))/STDEV(DP$5:DP$59) -> -0.72405269 | DH24: =(HAVERQ!AX148-AVERAGE(HAVERQ!AX$128:AX$183))/STDEV(HAVERQ!AX$128:AX$183) -> 0.18361409 | DJ24: =(DR24-AVERAGE(DR$5:DR$59))/STDEV(DR$5:DR$59) -> 0.27155064 | DL24: =100*(HAVERQ!AV148/(HAVERQ!AW148*HAVERQ!AX148/100)) -> 1.7837674 | DM24: =HAVERQ!AO148/HAVERQ!AP148 -> 0.3871851 | DN24: =100*((AVERAGE(HAVERQ!BC145:BC148)/AVERAGE(HAVERQ!BC141:BC144))-1) -> #N/A | DO24: =100*(HAVERQ!BE148+HAVERQ!BF148)/(HAVERQ!BB148+HAVERQ!BG148) -> 10.997458 | DP24: =100*((AVERAGE(HAVERQ!BA145:BA148)/AVERAGE(HAVERQ!BA141:BA144))-1) -> 1.5878744 | DR24: =(HAVERQ!AT148*HAVERQ!$AT$1)+(HAVERQ!AU148*HAVERQ!$AU$1) -> 65.310946 | DU24: JOLTS hiring rate | DV24: looser | DX24: looser | DY24: March JOLTS report
M25: 43009 | N25: =HAVERM!C460 -> 4.288 | O25: =HAVERM!B460 -> 4.3 | Q25: 43009 | R25: =MIN(HAVERM!C459:C461) -> 4.133 | S25: =V25-R25 -> 0.247 | T25: =HAVERM!B460 -> 4.3 | V25: =MAX(HAVERM!C459:C461) -> 4.38 | X25: 45383 | Y25: =HAVERQ!E185-AVERAGE(HAVERQ!E$164:E$167) -> 544.25 | Z25: =HAVERQ!F185-AVERAGE(HAVERQ!F$164:F$167) -> 113.25 | AB25: 38443 | AC25: =HAVERQ!P109 -> 1480 | AD25: =HAVERQ!O109 -> 1583 | AE25: =HAVERQ!N109 -> 1287 | AF25: =HAVERQ!M109 -> 272 | AG25: =HAVERQ!L109 -> 210 | AH25: =HAVERQ!E109-AC25-AD25-AE25-AF25-AG25 -> 814 | AJ25: 38443 | AK25: =100*(AC25/SUM($AC25:$AH25)) -> 26.213248 | AL25: =100*(AD25/SUM($AC25:$AH25)) -> 28.037549 | AM25: =100*(AE25/SUM($AC25:$AH25)) -> 22.794899 | AN25: =100*(AF25/SUM($AC25:$AH25)) -> 4.81757 | AO25: =100*(AG25/SUM($AC25:$AH25)) -> 3.7194474 | AP25: =100*(AH25/SUM($AC25:$AH25)) -> 14.417287 | AR25: 45383 | AS25: =HAVERQ!T185-AVERAGE(HAVERQ!T$164:T$167) -> -48.25 | AT25: =HAVERQ!U185-AVERAGE(HAVERQ!U$164:U$167) -> -11.25 | AU25: =HAVERQ!V185-AVERAGE(HAVERQ!V$164:V$167) -> -118.75 | AV25: =HAVERQ!W185-AVERAGE(HAVERQ!W$164:W$167) -> -4.75 | AW25: =HAVERQ!X185-AVERAGE(HAVERQ!X$164:X$167) -> 19.5 | AX25: =HAVERQ!Y185-AVERAGE(HAVERQ!Y$164:Y$167) -> -175.25 | AY25: =HAVERQ!Z185-AVERAGE(HAVERQ!Z$164:Z$167) -> -253.5 | AZ25: =HAVERQ!AA185-AVERAGE(HAVERQ!AA$164:AA$167) -> 81 | ... BJ25: =HAVERQ!AK185-AVERAGE(HAVERQ!AK$164:AK$167) -> 79.25 | BK25: =BM25-AVERAGE(BM$4:BM$7) -> -20.5 | BM25: =HAVERQ!AL185+HAVERQ!AM185 -> 997 | BO25: 45383 | BP25: =BZ25-AVERAGE(BZ$4:BZ$7) -> -48.25 | BQ25: =CA25-AVERAGE(CA$4:CA$7) -> 3.5 | BR25: =CB25-AVERAGE(CB$4:CB$7) -> -118.75 | BS25: =CC25-AVERAGE(CC$4:CC$7) -> -175.25 | BT25: =CD25-AVERAGE(CD$4:CD$7) -> -69.5 | BU25: =CE25-AVERAGE(CE$4:CE$7) -> 190.75 | BV25: =CF25-AVERAGE(CF$4:CF$7) -> 32.75 | BW25: =CG25-AVERAGE(CG$4:CG$7) -> 332.75 | BX25: =CH25-AVERAGE(CH$4:CH$7) -> 1008.75 | BZ25: =HAVERQ!T185 -> 350 | CA25: =HAVERQ!U185+HAVERQ!W185+HAVERQ!X185 -> 429 | CB25: =HAVERQ!V185 -> 2572 | CC25: =HAVERQ!Y185 -> 2158 | CD25: =HAVERQ!Z185+HAVERQ!AB185 -> 7435 | CE25: =HAVERQ!AA185+HAVERQ!AC185 -> 3497 | CF25: =HAVERQ!AD185 -> 1168 | CG25: =HAVERQ!AE185+HAVERQ!AF185+HAVERQ!AG185 -> 7164 | CH25: =HAVERQ!AH185+HAVERQ!AI185+HAVERQ!AJ185+HAVERQ!AK185+HAVERQ!AL185+HAVERQ!AM185 -> 11949 | CI25: =HAVERQ!S185-SUM('Chart Data'!BZ25:CH25) -> -2 | CL25: =100*((DataQ!F184/DataQ!F180)-1) -> 1.3309109 | CM25: =100*(DataQ!I184/DataQ!J184) -> 22.210696 | CY25: =(HAVERQ!AQ149-AVERAGE(HAVERQ!AQ$128:AQ$183))/STDEV(HAVERQ!AQ$128:AQ$183) -> 0.047843751 | CZ25: =(DL25-AVERAGE(DL$5:DL$59))/STDEV(DL$5:DL$59) -> 0.15405101 | DA25: =(DO25-AVERAGE(DO$5:DO$59))/STDEV(DO$5:DO$59) -> 0.87730305 | DB25: =(HAVERQ!AR149-AVERAGE(HAVERQ!AR$128:AR$183))/STDEV(HAVERQ!AR$128:AR$183) -> -0.16945662 | DC25: =(DM25-AVERAGE(DM$5:DM$59))/STDEV(DM$5:DM$59) -> -0.2753566 | DD25: =(DN25-AVERAGE(DN$29:DN$59))/STDEV(DN$29:DN$59) -> #N/A | DE25: =(HAVERQ!AZ149-AVERAGE(HAVERQ!AZ$128:AZ$167,AZ$174:AZ$183))/STDEV(HAVERQ!AZ$128:AZ$167,AZ$174:AZ$183) -> 0.61151881 | DF25: =(HAVERQ!AS149-AVERAGE(HAVERQ!AS$128:AS$183))/STDEV(HAVERQ!AS$128:AS$183) -> 0.33417299 | DG25: =(DP25-AVERAGE(DP$5:DP$59))/STDEV(DP$5:DP$59) -> -0.36194518 | DH25: =(HAVERQ!AX149-AVERAGE(HAVERQ!AX$128:AX$183))/STDEV(HAVERQ!AX$128:AX$183) -> -0.11880912 | DJ25: =(DR25-AVERAGE(DR$5:DR$59))/STDEV(DR$5:DR$59) -> 0.36554543 | DL25: =100*(HAVERQ!AV149/(HAVERQ!AW149*HAVERQ!AX149/100)) -> 1.7469568 | DM25: =HAVERQ!AO149/HAVERQ!AP149 -> 0.39880952 | DN25: =100*((AVERAGE(HAVERQ!BC146:BC149)/AVERAGE(HAVERQ!BC142:BC145))-1) -> #N/A | DO25: =100*(HAVERQ!BE149+HAVERQ!BF149)/(HAVERQ!BB149+HAVERQ!BG149) -> 10.987946 | DP25: =100*((AVERAGE(HAVERQ!BA146:BA149)/AVERAGE(HAVERQ!BA142:BA145))-1) -> 2.2911781 | DR25: =(HAVERQ!AT149*HAVERQ!$AT$1)+(HAVERQ!AU149*HAVERQ!$AU$1) -> 66.243785 | DU25: ISM manufacturing employment | DV25: tighter | DX25: looser | DY25: ISM manufacturing service
M26: 43040 | N26: =HAVERM!C461 -> 4.38 | O26: =HAVERM!B461 -> 4.4 | Q26: 43040 | R26: =MIN(HAVERM!C460:C462) -> 4.288 | S26: =V26-R26 -> 0.106 | T26: =HAVERM!B461 -> 4.4 | V26: =MAX(HAVERM!C460:C462) -> 4.394 | X26: 45474 | Y26: =HAVERQ!E186-AVERAGE(HAVERQ!E$164:E$167) -> 559.25 | Z26: =HAVERQ!F186-AVERAGE(HAVERQ!F$164:F$167) -> 271.25 | AB26: 38534 | AC26: =HAVERQ!P110 -> 1485 | AD26: =HAVERQ!O110 -> 1593 | AE26: =HAVERQ!N110 -> 1284 | AF26: =HAVERQ!M110 -> 271 | AG26: =HAVERQ!L110 -> 208 | AH26: =HAVERQ!E110-AC26-AD26-AE26-AF26-AG26 -> 799 | AJ26: 38534 | AK26: =100*(AC26/SUM($AC26:$AH26)) -> 26.329787 | AL26: =100*(AD26/SUM($AC26:$AH26)) -> 28.244681 | AM26: =100*(AE26/SUM($AC26:$AH26)) -> 22.765957 | AN26: =100*(AF26/SUM($AC26:$AH26)) -> 4.8049645 | AO26: =100*(AG26/SUM($AC26:$AH26)) -> 3.6879433 | AP26: =100*(AH26/SUM($AC26:$AH26)) -> 14.166667 | AR26: 45474 | AS26: =HAVERQ!T186-AVERAGE(HAVERQ!T$164:T$167) -> -37.25 | AT26: =HAVERQ!U186-AVERAGE(HAVERQ!U$164:U$167) -> -15.25 | AU26: =HAVERQ!V186-AVERAGE(HAVERQ!V$164:V$167) -> -110.75 | AV26: =HAVERQ!W186-AVERAGE(HAVERQ!W$164:W$167) -> -0.75 | AW26: =HAVERQ!X186-AVERAGE(HAVERQ!X$164:X$167) -> 19.5 | AX26: =HAVERQ!Y186-AVERAGE(HAVERQ!Y$164:Y$167) -> -106.25 | AY26: =HAVERQ!Z186-AVERAGE(HAVERQ!Z$164:Z$167) -> -264.5 | AZ26: =HAVERQ!AA186-AVERAGE(HAVERQ!AA$164:AA$167) -> 82 | ... BJ26: =HAVERQ!AK186-AVERAGE(HAVERQ!AK$164:AK$167) -> 63.25 | BK26: =BM26-AVERAGE(BM$4:BM$7) -> -51.5 | BM26: =HAVERQ!AL186+HAVERQ!AM186 -> 966 | BO26: 45474 | BP26: =BZ26-AVERAGE(BZ$4:BZ$7) -> -37.25 | BQ26: =CA26-AVERAGE(CA$4:CA$7) -> 3.5 | BR26: =CB26-AVERAGE(CB$4:CB$7) -> -110.75 | BS26: =CC26-AVERAGE(CC$4:CC$7) -> -106.25 | BT26: =CD26-AVERAGE(CD$4:CD$7) -> -61.5 | BU26: =CE26-AVERAGE(CE$4:CE$7) -> 214.75 | BV26: =CF26-AVERAGE(CF$4:CF$7) -> 47.75 | BW26: =CG26-AVERAGE(CG$4:CG$7) -> 317.75 | BX26: =CH26-AVERAGE(CH$4:CH$7) -> 958.75 | BZ26: =HAVERQ!T186 -> 361 | CA26: =HAVERQ!U186+HAVERQ!W186+HAVERQ!X186 -> 429 | CB26: =HAVERQ!V186 -> 2580 | CC26: =HAVERQ!Y186 -> 2227 | CD26: =HAVERQ!Z186+HAVERQ!AB186 -> 7443 | CE26: =HAVERQ!AA186+HAVERQ!AC186 -> 3521 | CF26: =HAVERQ!AD186 -> 1183 | CG26: =HAVERQ!AE186+HAVERQ!AF186+HAVERQ!AG186 -> 7149 | CH26: =HAVERQ!AH186+HAVERQ!AI186+HAVERQ!AJ186+HAVERQ!AK186+HAVERQ!AL186+HAVERQ!AM186 -> 11899 | CI26: =HAVERQ!S186-SUM('Chart Data'!BZ26:CH26) -> 1 | CL26: =100*((DataQ!F185/DataQ!F181)-1) -> 0.72085025 | CM26: =100*(DataQ!I185/DataQ!J185) -> 22.087185 | CY26: =(HAVERQ!AQ150-AVERAGE(HAVERQ!AQ$128:AQ$183))/STDEV(HAVERQ!AQ$128:AQ$183) -> -0.13483239 | CZ26: =(DL26-AVERAGE(DL$5:DL$59))/STDEV(DL$5:DL$59) -> -0.09983282 | DA26: =(DO26-AVERAGE(DO$5:DO$59))/STDEV(DO$5:DO$59) -> 0.62367849 | DB26: =(HAVERQ!AR150-AVERAGE(HAVERQ!AR$128:AR$183))/STDEV(HAVERQ!AR$128:AR$183) -> -0.22337463 | DC26: =(DM26-AVERAGE(DM$5:DM$59))/STDEV(DM$5:DM$59) -> -0.14752628 | DD26: =(DN26-AVERAGE(DN$29:DN$59))/STDEV(DN$29:DN$59) -> #N/A | DE26: =(HAVERQ!AZ150-AVERAGE(HAVERQ!AZ$128:AZ$167,AZ$174:AZ$183))/STDEV(HAVERQ!AZ$128:AZ$167,AZ$174:AZ$183) -> -0.24675321 | DF26: =(HAVERQ!AS150-AVERAGE(HAVERQ!AS$128:AS$183))/STDEV(HAVERQ!AS$128:AS$183) -> 0.68510946 | DG26: =(DP26-AVERAGE(DP$5:DP$59))/STDEV(DP$5:DP$59) -> -0.068696155 | DH26: =(HAVERQ!AX150-AVERAGE(HAVERQ!AX$128:AX$183))/STDEV(HAVERQ!AX$128:AX$183) -> 0.18361409 | DJ26: =(DR26-AVERAGE(DR$5:DR$59))/STDEV(DR$5:DR$59) -> 0.10919087 | DL26: =100*(HAVERQ!AV150/(HAVERQ!AW150*HAVERQ!AX150/100)) -> 1.5568213 | DM26: =HAVERQ!AO150/HAVERQ!AP150 -> 0.42897727 | DN26: =100*((AVERAGE(HAVERQ!BC147:BC150)/AVERAGE(HAVERQ!BC143:BC146))-1) -> #N/A | DO26: =100*(HAVERQ!BE150+HAVERQ!BF150)/(HAVERQ!BB150+HAVERQ!BG150) -> 10.605375 | DP26: =100*((AVERAGE(HAVERQ!BA147:BA150)/AVERAGE(HAVERQ!BA143:BA146))-1) -> 2.8607413 | DR26: =(HAVERQ!AT150*HAVERQ!$AT$1)+(HAVERQ!AU150*HAVERQ!$AU$1) -> 63.699629 | DU26: NFIB plans to hire | DV26: tighter | DX26: looser | DY26: NFIB small business optimism survey
M27: 43070 | N27: =HAVERM!C462 -> 4.394 | O27: =HAVERM!B462 -> 4.3 | Q27: 43070 | R27: =MIN(HAVERM!C461:C463) -> 4.173 | S27: =V27-R27 -> 0.221 | T27: =HAVERM!B462 -> 4.3 | V27: =MAX(HAVERM!C461:C463) -> 4.394 | X27: 45566 | AB27: 38626 | AC27: =HAVERQ!P111 -> 1488 | AD27: =HAVERQ!O111 -> 1599 | AE27: =HAVERQ!N111 -> 1284 | AF27: =HAVERQ!M111 -> 274 | AG27: =HAVERQ!L111 -> 206 | AH27: =HAVERQ!E111-AC27-AD27-AE27-AF27-AG27 -> 795 | AJ27: 38626 | AK27: =100*(AC27/SUM($AC27:$AH27)) -> 26.354942 | AL27: =100*(AD27/SUM($AC27:$AH27)) -> 28.320935 | AM27: =100*(AE27/SUM($AC27:$AH27)) -> 22.741764 | AN27: =100*(AF27/SUM($AC27:$AH27)) -> 4.8529933 | AO27: =100*(AG27/SUM($AC27:$AH27)) -> 3.6486008 | AP27: =100*(AH27/SUM($AC27:$AH27)) -> 14.080765 | AR27: 45566 | BO27: 45566 | CL27: =100*((DataQ!F186/DataQ!F182)-1) -> 1.1563939 | CM27: =100*(DataQ!I186/DataQ!J186) -> 22.839615 | CY27: =(HAVERQ!AQ151-AVERAGE(HAVERQ!AQ$128:AQ$183))/STDEV(HAVERQ!AQ$128:AQ$183) -> -0.25661648 | CZ27: =(DL27-AVERAGE(DL$5:DL$59))/STDEV(DL$5:DL$59) -> -0.2146515 | DA27: =(DO27-AVERAGE(DO$5:DO$59))/STDEV(DO$5:DO$59) -> 0.53500126 | DB27: =(HAVERQ!AR151-AVERAGE(HAVERQ!AR$128:AR$183))/STDEV(HAVERQ!AR$128:AR$183) -> -0.49296471 | DC27: =(DM27-AVERAGE(DM$5:DM$59))/STDEV(DM$5:DM$59) -> -0.090075576 | DD27: =(DN27-AVERAGE(DN$29:DN$59))/STDEV(DN$29:DN$59) -> #N/A | DE27: =(HAVERQ!AZ151-AVERAGE(HAVERQ!AZ$128:AZ$167,AZ$174:AZ$183))/STDEV(HAVERQ!AZ$128:AZ$167,AZ$174:AZ$183) -> 1.4697908 | DF27: =(HAVERQ!AS151-AVERAGE(HAVERQ!AS$128:AS$183))/STDEV(HAVERQ!AS$128:AS$183) -> 0.70265628 | DG27: =(DP27-AVERAGE(DP$5:DP$59))/STDEV(DP$5:DP$59) -> -0.13289474 | DH27: =(HAVERQ!AX151-AVERAGE(HAVERQ!AX$128:AX$183))/STDEV(HAVERQ!AX$128:AX$183) -> 0.78846049 | DJ27: =(DR27-AVERAGE(DR$5:DR$59))/STDEV(DR$5:DR$59) -> 0.2569504 | DL27: =100*(HAVERQ!AV151/(HAVERQ!AW151*HAVERQ!AX151/100)) -> 1.4708327 | DM27: =HAVERQ!AO151/HAVERQ!AP151 -> 0.44253555 | DN27: =100*((AVERAGE(HAVERQ!BC148:BC151)/AVERAGE(HAVERQ!BC144:BC147))-1) -> #N/A | DO27: =100*(HAVERQ!BE151+HAVERQ!BF151)/(HAVERQ!BB151+HAVERQ!BG151) -> 10.471613 | DP27: =100*((AVERAGE(HAVERQ!BA148:BA151)/AVERAGE(HAVERQ!BA144:BA147))-1) -> 2.7360515 | DR27: =(HAVERQ!AT151*HAVERQ!$AT$1)+(HAVERQ!AU151*HAVERQ!$AU$1) -> 65.166048 | DT27: Balance | DU27: NFIB vacancies | DV27: tighter | DX27: tighter | DY27: NFIB small business optimism survey
M28: 43101 | N28: =HAVERM!C463 -> 4.173 | O28: =HAVERM!B463 -> 4.2 | Q28: 43101 | R28: =MIN(HAVERM!C462:C464) -> 4.058 | S28: =V28-R28 -> 0.336 | T28: =HAVERM!B463 -> 4.2 | V28: =MAX(HAVERM!C462:C464) -> 4.394 | AB28: 38718 | AC28: =HAVERQ!P112 -> 1484 | AD28: =HAVERQ!O112 -> 1603 | AE28: =HAVERQ!N112 -> 1284 | AF28: =HAVERQ!M112 -> 274 | AG28: =HAVERQ!L112 -> 205 | AH28: =HAVERQ!E112-AC28-AD28-AE28-AF28-AG28 -> 781 | AJ28: 38718 | AK28: =100*(AC28/SUM($AC28:$AH28)) -> 26.354111 | AL28: =100*(AD28/SUM($AC28:$AH28)) -> 28.467413 | AM28: =100*(AE28/SUM($AC28:$AH28)) -> 22.802344 | AN28: =100*(AF28/SUM($AC28:$AH28)) -> 4.8659208 | AO28: =100*(AG28/SUM($AC28:$AH28)) -> 3.6405612 | AP28: =100*(AH28/SUM($AC28:$AH28)) -> 13.86965 | CK28: 2018 | CL28: =100*((DataQ!F187/DataQ!F183)-1) -> 2.5453424 | CM28: =100*(DataQ!I187/DataQ!J187) -> 21.870311 | CX28: 2016 | CY28: =(HAVERQ!AQ152-AVERAGE(HAVERQ!AQ$128:AQ$183))/STDEV(HAVERQ!AQ$128:AQ$183) -> -0.25661648 | CZ28: =(DL28-AVERAGE(DL$5:DL$59))/STDEV(DL$5:DL$59) -> -0.30353743 | DA28: =(DO28-AVERAGE(DO$5:DO$59))/STDEV(DO$5:DO$59) -> 0.34489344 | DB28: =(HAVERQ!AR152-AVERAGE(HAVERQ!AR$128:AR$183))/STDEV(HAVERQ!AR$128:AR$183) -> -0.22337463 | DC28: =(DM28-AVERAGE(DM$5:DM$59))/STDEV(DM$5:DM$59) -> -0.14613803 | DD28: =(DN28-AVERAGE(DN$29:DN$59))/STDEV(DN$29:DN$59) -> #N/A | DE28: =(HAVERQ!AZ152-AVERAGE(HAVERQ!AZ$128:AZ$167,AZ$174:AZ$183))/STDEV(HAVERQ!AZ$128:AZ$167,AZ$174:AZ$183) -> 0.61151881 | DF28: =(HAVERQ!AS152-AVERAGE(HAVERQ!AS$128:AS$183))/STDEV(HAVERQ!AS$128:AS$183) -> 0.33417299 | DG28: =(DP28-AVERAGE(DP$5:DP$59))/STDEV(DP$5:DP$59) -> -0.17898307 | DH28: =(HAVERQ!AX152-AVERAGE(HAVERQ!AX$128:AX$183))/STDEV(HAVERQ!AX$128:AX$183) -> 0.48603729 | DJ28: =(DR28-AVERAGE(DR$5:DR$59))/STDEV(DR$5:DR$59) -> 0.57383704 | DL28: =100*(HAVERQ!AV152/(HAVERQ!AW152*HAVERQ!AX152/100)) -> 1.4042653 | DM28: =HAVERQ!AO152/HAVERQ!AP152 -> 0.4293049 | DN28: =100*((AVERAGE(HAVERQ!BC149:BC152)/AVERAGE(HAVERQ!BC145:BC148))-1) -> #N/A | DO28: =100*(HAVERQ!BE152+HAVERQ!BF152)/(HAVERQ!BB152+HAVERQ!BG152) -> 10.184852 | DP28: =100*((AVERAGE(HAVERQ!BA149:BA152)/AVERAGE(HAVERQ!BA145:BA148))-1) -> 2.6465364 | DR28: =(HAVERQ!AT152*HAVERQ!$AT$1)+(HAVERQ!AU152*HAVERQ!$AU$1) -> 68.310946 | DU28: Job leavers | DV28: looser | DX28: looser | DY28: April household survey
M29: 43132 | N29: =HAVERM!C464 -> 4.058 | O29: =HAVERM!B464 -> 4.2 | Q29: 43132 | R29: =MIN(HAVERM!C463:C465) -> 4.058 | S29: =V29-R29 -> 0.326 | T29: =HAVERM!B464 -> 4.2 | V29: =MAX(HAVERM!C463:C465) -> 4.384 | AB29: 38808 | AC29: =HAVERQ!P113 -> 1477 | AD29: =HAVERQ!O113 -> 1609 | AE29: =HAVERQ!N113 -> 1283 | AF29: =HAVERQ!M113 -> 274 | AG29: =HAVERQ!L113 -> 204 | AH29: =HAVERQ!E113-AC29-AD29-AE29-AF29-AG29 -> 776 | AJ29: 38808 | AK29: =100*(AC29/SUM($AC29:$AH29)) -> 26.267117 | AL29: =100*(AD29/SUM($AC29:$AH29)) -> 28.614619 | AM29: =100*(AE29/SUM($AC29:$AH29)) -> 22.817002 | AN29: =100*(AF29/SUM($AC29:$AH29)) -> 4.8728437 | AO29: =100*(AG29/SUM($AC29:$AH29)) -> 3.6279566 | AP29: =100*(AH29/SUM($AC29:$AH29)) -> 13.800462 | CL29: =100*((DataQ!F188/DataQ!F184)-1) -> 1.4605074 | CM29: =100*(DataQ!I188/DataQ!J188) -> 22.015766 | CY29: =(HAVERQ!AQ153-AVERAGE(HAVERQ!AQ$128:AQ$183))/STDEV(HAVERQ!AQ$128:AQ$183) -> -0.37840058 | CZ29: =(DL29-AVERAGE(DL$5:DL$59))/STDEV(DL$5:DL$59) -> -0.39399524 | DA29: =(DO29-AVERAGE(DO$5:DO$59))/STDEV(DO$5:DO$59) -> 0.22076121 | DB29: =(HAVERQ!AR153-AVERAGE(HAVERQ!AR$128:AR$183))/STDEV(HAVERQ!AR$128:AR$183) -> -0.22337463 | DC29: =(DM29-AVERAGE(DM$5:DM$59))/STDEV(DM$5:DM$59) -> -0.023028006 | DD29: =(DN29-AVERAGE(DN$29:DN$59))/STDEV(DN$29:DN$59) -> 0.75705595 | DE29: =(HAVERQ!AZ153-AVERAGE(HAVERQ!AZ$128:AZ$167,AZ$174:AZ$183))/STDEV(HAVERQ!AZ$128:AZ$167,AZ$174:AZ$183) -> 0.1823828 | DF29: =(HAVERQ!AS153-AVERAGE(HAVERQ!AS$128:AS$183))/STDEV(HAVERQ!AS$128:AS$183) -> 0.21134522 | DG29: =(DP29-AVERAGE(DP$5:DP$59))/STDEV(DP$5:DP$59) -> -0.21583747 | DH29: =(HAVERQ!AX153-AVERAGE(HAVERQ!AX$128:AX$183))/STDEV(HAVERQ!AX$128:AX$183) -> 0.78846049 | DJ29: =(DR29-AVERAGE(DR$5:DR$59))/STDEV(DR$5:DR$59) -> 0.17078851 | DL29: =100*(HAVERQ!AV153/(HAVERQ!AW153*HAVERQ!AX153/100)) -> 1.3365207 | DM29: =HAVERQ!AO153/HAVERQ!AP153 -> 0.45835866 | DN29: =100*((AVERAGE(HAVERQ!BC150:BC153)/AVERAGE(HAVERQ!BC146:BC149))-1) -> 2.3020532 | DO29: =100*(HAVERQ!BE153+HAVERQ!BF153)/(HAVERQ!BB153+HAVERQ!BG153) -> 9.9976089 | DP29: =100*((AVERAGE(HAVERQ!BA150:BA153)/AVERAGE(HAVERQ!BA146:BA149))-1) -> 2.5749559 | DR29: =(HAVERQ!AT153*HAVERQ!$AT$1)+(HAVERQ!AU153*HAVERQ!$AU$1) -> 64.310946 | DU29: JOLTS quits rate | DV29: looser | DX29: looser | DY29: March JOLTS report
M30: 43160 | N30: =HAVERM!C465 -> 4.384 | O30: =HAVERM!B465 -> 4.2 | Q30: 43160 | R30: =MIN(HAVERM!C464:C466) -> 4.058 | S30: =V30-R30 -> 0.326 | T30: =HAVERM!B465 -> 4.2 | V30: =MAX(HAVERM!C464:C466) -> 4.384 | AB30: 38899 | AC30: =HAVERQ!P114 -> 1460 | AD30: =HAVERQ!O114 -> 1611 | AE30: =HAVERQ!N114 -> 1283 | AF30: =HAVERQ!M114 -> 276 | AG30: =HAVERQ!L114 -> 203 | AH30: =HAVERQ!E114-AC30-AD30-AE30-AF30-AG30 -> 768 | AJ30: 38899 | AK30: =100*(AC30/SUM($AC30:$AH30)) -> 26.066774 | AL30: =100*(AD30/SUM($AC30:$AH30)) -> 28.762721 | AM30: =100*(AE30/SUM($AC30:$AH30)) -> 22.906624 | AN30: =100*(AF30/SUM($AC30:$AH30)) -> 4.9276915 | AO30: =100*(AG30/SUM($AC30:$AH30)) -> 3.6243528 | AP30: =100*(AH30/SUM($AC30:$AH30)) -> 13.711837 | AS30: =RANK(AS26,$AS26:$BK26) -> 14 | AT30: =RANK(AT26,$AS26:$BK26) -> 13 | AU30: =RANK(AU26,$AS26:$BK26) -> 18 | AV30: =RANK(AV26,$AS26:$BK26) -> 12 | AW30: =RANK(AW26,$AS26:$BK26) -> 11 | AX30: =RANK(AX26,$AS26:$BK26) -> 17 | AY30: =RANK(AY26,$AS26:$BK26) -> 19 | AZ30: =RANK(AZ26,$AS26:$BK26) -> 7 | ... BK30: =RANK(BK26,$AS26:$BK26) -> 15 | CL30: =100*((DataQ!F189/DataQ!F185)-1) -> 3.0151689 | CM30: =100*(DataQ!I189/DataQ!J189) -> 21.743782 | CY30: =(HAVERQ!AQ154-AVERAGE(HAVERQ!AQ$128:AQ$183))/STDEV(HAVERQ!AQ$128:AQ$183) -> -0.43929262 | CZ30: =(DL30-AVERAGE(DL$5:DL$59))/STDEV(DL$5:DL$59) -> -0.44856616 | DA30: =(DO30-AVERAGE(DO$5:DO$59))/STDEV(DO$5:DO$59) -> 0.27241824 | DB30: =(HAVERQ!AR154-AVERAGE(HAVERQ!AR$128:AR$183))/STDEV(HAVERQ!AR$128:AR$183) -> -0.16945662 | DC30: =(DM30-AVERAGE(DM$5:DM$59))/STDEV(DM$5:DM$59) -> 0.04742119 | DD30: =(DN30-AVERAGE(DN$29:DN$59))/STDEV(DN$29:DN$59) -> 0.5381902 | DE30: =(HAVERQ!AZ154-AVERAGE(HAVERQ!AZ$128:AZ$167,AZ$174:AZ$183))/STDEV(HAVERQ!AZ$128:AZ$167,AZ$174:AZ$183) -> 0.1823828 | DF30: =(HAVERQ!AS154-AVERAGE(HAVERQ!AS$128:AS$183))/STDEV(HAVERQ!AS$128:AS$183) -> 0.15870475 | DG30: =(DP30-AVERAGE(DP$5:DP$59))/STDEV(DP$5:DP$59) -> -0.31679552 | DH30: =(HAVERQ!AX154-AVERAGE(HAVERQ!AX$128:AX$183))/STDEV(HAVERQ!AX$128:AX$183) -> 0.78846049 | DJ30: =(DR30-AVERAGE(DR$5:DR$59))/STDEV(DR$5:DR$59) -> -0.60397696 | DL30: =100*(HAVERQ!AV154/(HAVERQ!AW154*HAVERQ!AX154/100)) -> 1.2956521 | DM30: =HAVERQ!AO154/HAVERQ!AP154 -> 0.47498456 | DN30: =100*((AVERAGE(HAVERQ!BC151:BC154)/AVERAGE(HAVERQ!BC147:BC150))-1) -> 1.9819406 | DO30: =100*(HAVERQ!BE154+HAVERQ!BF154)/(HAVERQ!BB154+HAVERQ!BG154) -> 10.075529 | DP30: =100*((AVERAGE(HAVERQ!BA151:BA154)/AVERAGE(HAVERQ!BA147:BA150))-1) -> 2.37887 | DR30: =(HAVERQ!AT154*HAVERQ!$AT$1)+(HAVERQ!AU154*HAVERQ!$AU$1) -> 56.621892 | DU30: Conference Board jobs plentiful | DV30: looser | DX30: looser | DY30: April consumer confidence report
M31: 43191 | N31: =HAVERM!C466 -> 4.159 | O31: =HAVERM!B466 -> 4.2 | Q31: 43191 | R31: =MIN(HAVERM!C465:C467) -> 3.938 | S31: =V31-R31 -> 0.446 | T31: =HAVERM!B466 -> 4.2 | V31: =MAX(HAVERM!C465:C467) -> 4.384 | AB31: 38991 | AC31: =HAVERQ!P115 -> 1447 | AD31: =HAVERQ!O115 -> 1611 | AE31: =HAVERQ!N115 -> 1280 | AF31: =HAVERQ!M115 -> 279 | AG31: =HAVERQ!L115 -> 202 | AH31: =HAVERQ!E115-AC31-AD31-AE31-AF31-AG31 -> 763 | AJ31: 38991 | AK31: =100*(AC31/SUM($AC31:$AH31)) -> 25.922608 | AL31: =100*(AD31/SUM($AC31:$AH31)) -> 28.860623 | AM31: =100*(AE31/SUM($AC31:$AH31)) -> 22.930849 | AN31: =100*(AF31/SUM($AC31:$AH31)) -> 4.9982085 | AO31: =100*(AG31/SUM($AC31:$AH31)) -> 3.6187746 | AP31: =100*(AH31/SUM($AC31:$AH31)) -> 13.668936 | AS31: =AS3 -> Agriculture | AT31: =AT3 -> Extraction | AU31: =AU3 -> Manufacturing | AV31: =AV3 -> Utilities | AW31: =AW3 -> Water | AX31: =AX3 -> Construction | AY31: =AY3 -> Wholesale & retail | AZ31: =AZ3 -> Transport | ... BK31: =BK3 -> Other services | BM31: Total | CL31: =100*((DataQ!F190/DataQ!F186)-1) -> 4.2156007 | CM31: =100*(DataQ!I190/DataQ!J190) -> 21.46495 | CY31: =(HAVERQ!AQ155-AVERAGE(HAVERQ!AQ$128:AQ$183))/STDEV(HAVERQ!AQ$128:AQ$183) -> -0.50018467 | CZ31: =(DL31-AVERAGE(DL$5:DL$59))/STDEV(DL$5:DL$59) -> -0.56773682 | DA31: =(DO31-AVERAGE(DO$5:DO$59))/STDEV(DO$5:DO$59) -> 0.13309842 | DB31: =(HAVERQ!AR155-AVERAGE(HAVERQ!AR$128:AR$183))/STDEV(HAVERQ!AR$128:AR$183) -> -0.061620589 | DC31: =(DM31-AVERAGE(DM$5:DM$59))/STDEV(DM$5:DM$59) -> 0.050623891 | DD31: =(DN31-AVERAGE(DN$29:DN$59))/STDEV(DN$29:DN$59) -> 0.30279673 | DE31: =(HAVERQ!AZ155-AVERAGE(HAVERQ!AZ$128:AZ$167,AZ$174:AZ$183))/STDEV(HAVERQ!AZ$128:AZ$167,AZ$174:AZ$183) -> 0.61151881 | DF31: =(HAVERQ!AS155-AVERAGE(HAVERQ!AS$128:AS$183))/STDEV(HAVERQ!AS$128:AS$183) -> 0.053423811 | DG31: =(DP31-AVERAGE(DP$5:DP$59))/STDEV(DP$5:DP$59) -> -0.22418303 | DH31: =(HAVERQ!AX155-AVERAGE(HAVERQ!AX$128:AX$183))/STDEV(HAVERQ!AX$128:AX$183) -> 0.48603729 | DJ31: =(DR31-AVERAGE(DR$5:DR$59))/STDEV(DR$5:DR$59) -> -0.97462834 | DL31: =100*(HAVERQ!AV155/(HAVERQ!AW155*HAVERQ!AX155/100)) -> 1.2064043 | DM31: =HAVERQ!AO155/HAVERQ!AP155 -> 0.47574039 | DN31: =100*((AVERAGE(HAVERQ!BC152:BC155)/AVERAGE(HAVERQ!BC148:BC151))-1) -> 1.6376545 | DO31: =100*(HAVERQ!BE155+HAVERQ!BF155)/(HAVERQ!BB155+HAVERQ!BG155) -> 9.8653772 | DP31: =100*((AVERAGE(HAVERQ!BA152:BA155)/AVERAGE(HAVERQ!BA148:BA151))-1) -> 2.5587467 | DR31: =(HAVERQ!AT155*HAVERQ!$AT$1)+(HAVERQ!AU155*HAVERQ!$AU$1) -> 52.943413 | DU31: Average hourly earnings | DV31: looser | DX31: looser | DY31: April establishment survey
M32: 43221 | N32: =HAVERM!C467 -> 3.938 | O32: =HAVERM!B467 -> 4 | Q32: 43221 | R32: =MIN(HAVERM!C466:C468) -> 3.938 | S32: =V32-R32 -> 0.221 | T32: =HAVERM!B467 -> 4 | V32: =MAX(HAVERM!C466:C468) -> 4.159 | AB32: 39083 | AC32: =HAVERQ!P116 -> 1448 | AD32: =HAVERQ!O116 -> 1618 | AE32: =HAVERQ!N116 -> 1276 | AF32: =HAVERQ!M116 -> 282 | AG32: =HAVERQ!L116 -> 199 | AH32: =HAVERQ!E116-AC32-AD32-AE32-AF32-AG32 -> 764 | AJ32: 39083 | AK32: =100*(AC32/SUM($AC32:$AH32)) -> 25.917308 | AL32: =100*(AD32/SUM($AC32:$AH32)) -> 28.960086 | AM32: =100*(AE32/SUM($AC32:$AH32)) -> 22.838733 | AN32: =100*(AF32/SUM($AC32:$AH32)) -> 5.0474315 | AO32: =100*(AG32/SUM($AC32:$AH32)) -> 3.56184 | AP32: =100*(AH32/SUM($AC32:$AH32)) -> 13.674602 | AR32: =AR26 -> 45474 | AS32: =AS26 -> -37.25 | AT32: =AT26 -> -15.25 | AU32: =AU26 -> -110.75 | AV32: =AV26 -> -0.75 | AW32: =AW26 -> 19.5 | AX32: =AX26 -> -106.25 | AY32: =AY26 -> -264.5 | ... BK32: =BK26 -> -51.5 | BM32: =SUM(AS32:BK32) -> 1226.75 | CK32: 2019 | CL32: =100*((DataQ!F191/DataQ!F187)-1) -> 2.4656823 | CM32: =100*(DataQ!I191/DataQ!J191) -> 21.221907 | CX32: 2017 | CY32: =(HAVERQ!AQ156-AVERAGE(HAVERQ!AQ$128:AQ$183))/STDEV(HAVERQ!AQ$128:AQ$183) -> -0.56107672 | CZ32: =(DL32-AVERAGE(DL$5:DL$59))/STDEV(DL$5:DL$59) -> -0.6455344 | DA32: =(DO32-AVERAGE(DO$5:DO$59))/STDEV(DO$5:DO$59) -> -0.19601019 | DB32: =(HAVERQ!AR156-AVERAGE(HAVERQ!AR$128:AR$183))/STDEV(HAVERQ!AR$128:AR$183) -> -0.60080074 | DC32: =(DM32-AVERAGE(DM$5:DM$59))/STDEV(DM$5:DM$59) -> 0.10356876 | DD32: =(DN32-AVERAGE(DN$29:DN$59))/STDEV(DN$29:DN$59) -> 0.15216179 | DE32: =(HAVERQ!AZ156-AVERAGE(HAVERQ!AZ$128:AZ$167,AZ$174:AZ$183))/STDEV(HAVERQ!AZ$128:AZ$167,AZ$174:AZ$183) -> 1.0406548 | DF32: =(HAVERQ!AS156-AVERAGE(HAVERQ!AS$128:AS$183))/STDEV(HAVERQ!AS$128:AS$183) -> 0.15870475 | DG32: =(DP32-AVERAGE(DP$5:DP$59))/STDEV(DP$5:DP$59) -> -0.23193386 | DH32: =(HAVERQ!AX156-AVERAGE(HAVERQ!AX$128:AX$183))/STDEV(HAVERQ!AX$128:AX$183) -> 0.48603729 | DJ32: =(DR32-AVERAGE(DR$5:DR$59))/STDEV(DR$5:DR$59) -> -0.3397895 | DL32: =100*(HAVERQ!AV156/(HAVERQ!AW156*HAVERQ!AX156/100)) -> 1.1481411 | DM32: =HAVERQ!AO156/HAVERQ!AP156 -> 0.48823529 | DN32: =100*((AVERAGE(HAVERQ!BC153:BC156)/AVERAGE(HAVERQ!BC149:BC152))-1) -> 1.4173361 | DO32: =100*(HAVERQ!BE156+HAVERQ!BF156)/(HAVERQ!BB156+HAVERQ!BG156) -> 9.3689451 | DP32: =100*((AVERAGE(HAVERQ!BA153:BA156)/AVERAGE(HAVERQ!BA149:BA152))-1) -> 2.5436927 | DR32: =(HAVERQ!AT156*HAVERQ!$AT$1)+(HAVERQ!AU156*HAVERQ!$AU$1) -> 59.243785 | DT32: Labor supply | DU32: Employment-to-population ratio | DV32: looser | DX32: looser | DY32: April household survey
M33: 43252 | N33: =HAVERM!C468 -> 4.036 | O33: =HAVERM!B468 -> 4 | Q33: 43252 | R33: =MIN(HAVERM!C467:C469) -> 3.938 | S33: =V33-R33 -> 0.195 | T33: =HAVERM!B468 -> 4 | V33: =MAX(HAVERM!C467:C469) -> 4.133 | AB33: 39173 | AC33: =HAVERQ!P117 -> 1443 | AD33: =HAVERQ!O117 -> 1623 | AE33: =HAVERQ!N117 -> 1269 | AF33: =HAVERQ!M117 -> 283 | AG33: =HAVERQ!L117 -> 197 | AH33: =HAVERQ!E117-AC33-AD33-AE33-AF33-AG33 -> 765 | AJ33: 39173 | AK33: =100*(AC33/SUM($AC33:$AH33)) -> 25.860215 | AL33: =100*(AD33/SUM($AC33:$AH33)) -> 29.086022 | AM33: =100*(AE33/SUM($AC33:$AH33)) -> 22.741935 | AN33: =100*(AF33/SUM($AC33:$AH33)) -> 5.0716846 | AO33: =100*(AG33/SUM($AC33:$AH33)) -> 3.5304659 | AP33: =100*(AH33/SUM($AC33:$AH33)) -> 13.709677 | CL33: =100*((DataQ!F192/DataQ!F188)-1) -> 4.4057963 | CM33: =100*(DataQ!I192/DataQ!J192) -> 21.285047 | CY33: =(HAVERQ!AQ157-AVERAGE(HAVERQ!AQ$128:AQ$183))/STDEV(HAVERQ!AQ$128:AQ$183) -> -0.68286081 | CZ33: =(DL33-AVERAGE(DL$5:DL$59))/STDEV(DL$5:DL$59) -> -0.69758888 | DA33: =(DO33-AVERAGE(DO$5:DO$59))/STDEV(DO$5:DO$59) -> -0.35452439 | DB33: =(HAVERQ!AR157-AVERAGE(HAVERQ!AR$128:AR$183))/STDEV(HAVERQ!AR$128:AR$183) -> -0.27729265 | DC33: =(DM33-AVERAGE(DM$5:DM$59))/STDEV(DM$5:DM$59) -> 0.29959941 | DD33: =(DN33-AVERAGE(DN$29:DN$59))/STDEV(DN$29:DN$59) -> 0.09124887 | DE33: =(HAVERQ!AZ157-AVERAGE(HAVERQ!AZ$128:AZ$167,AZ$174:AZ$183))/STDEV(HAVERQ!AZ$128:AZ$167,AZ$174:AZ$183) -> 1.4697908 | DF33: =(HAVERQ!AS157-AVERAGE(HAVERQ!AS$128:AS$183))/STDEV(HAVERQ!AS$128:AS$183) -> 0.4219071 | DG33: =(DP33-AVERAGE(DP$5:DP$59))/STDEV(DP$5:DP$59) -> -0.24026562 | DH33: =(HAVERQ!AX157-AVERAGE(HAVERQ!AX$128:AX$183))/STDEV(HAVERQ!AX$128:AX$183) -> 0.78846049 | DJ33: =(DR33-AVERAGE(DR$5:DR$59))/STDEV(DR$5:DR$59) -> 0.28721644 | DL33: =100*(HAVERQ!AV157/(HAVERQ!AW157*HAVERQ!AX157/100)) -> 1.1091571 | DM33: =HAVERQ!AO157/HAVERQ!AP157 -> 0.53449821 | DN33: =100*((AVERAGE(HAVERQ!BC154:BC157)/AVERAGE(HAVERQ!BC150:BC153))-1) -> 1.328245 | DO33: =100*(HAVERQ!BE157+HAVERQ!BF157)/(HAVERQ!BB157+HAVERQ!BG157) -> 9.12984 | DP33: =100*((AVERAGE(HAVERQ!BA154:BA157)/AVERAGE(HAVERQ!BA150:BA153))-1) -> 2.5275103 | DR33: =(HAVERQ!AT157*HAVERQ!$AT$1)+(HAVERQ!AU157*HAVERQ!$AU$1) -> 65.466419 | DU33: Labor force participation rate | DV33: neutral | DX33: looser | DY33: April household survey
M34: 43282 | N34: =HAVERM!C469 -> 4.133 | O34: =HAVERM!B469 -> 4 | Q34: 43282 | R34: =MIN(HAVERM!C468:C470) -> 3.926 | S34: =V34-R34 -> 0.207 | T34: =HAVERM!B469 -> 4 | V34: =MAX(HAVERM!C468:C470) -> 4.133 | AB34: 39264 | AC34: =HAVERQ!P118 -> 1444 | AD34: =HAVERQ!O118 -> 1628 | AE34: =HAVERQ!N118 -> 1269 | AF34: =HAVERQ!M118 -> 284 | AG34: =HAVERQ!L118 -> 195 | AH34: =HAVERQ!E118-AC34-AD34-AE34-AF34-AG34 -> 744 | AJ34: 39264 | AK34: =100*(AC34/SUM($AC34:$AH34)) -> 25.952552 | AL34: =100*(AD34/SUM($AC34:$AH34)) -> 29.259526 | AM34: =100*(AE34/SUM($AC34:$AH34)) -> 22.807333 | AN34: =100*(AF34/SUM($AC34:$AH34)) -> 5.1042416 | AO34: =100*(AG34/SUM($AC34:$AH34)) -> 3.5046729 | AP34: =100*(AH34/SUM($AC34:$AH34)) -> 13.371675 | AS34: 1 | AT34: =+AS34+1 -> 2 | AU34: =+AT34+1 -> 3 | AV34: =+AU34+1 -> 4 | AW34: =+AV34+1 -> 5 | AX34: =+AW34+1 -> 6 | AY34: =+AX34+1 -> 7 | AZ34: =+AY34+1 -> 8 | BA34: =+AZ34+1 -> 9 | ... BK34: =+BJ34+1 -> 19 | BM34: Total | CL34: =100*((DataQ!F193/DataQ!F189)-1) -> 2.5605318 | CM34: =100*(DataQ!I193/DataQ!J193) -> 22.040536 | CY34: =(HAVERQ!AQ158-AVERAGE(HAVERQ!AQ$128:AQ$183))/STDEV(HAVERQ!AQ$128:AQ$183) -> -0.74375286 | CZ34: =(DL34-AVERAGE(DL$5:DL$59))/STDEV(DL$5:DL$59) -> -0.62326119 | DA34: =(DO34-AVERAGE(DO$5:DO$59))/STDEV(DO$5:DO$59) -> -0.33975509 | DB34: =(HAVERQ!AR158-AVERAGE(HAVERQ!AR$128:AR$183))/STDEV(HAVERQ!AR$128:AR$183) -> -0.43904669 | DC34: =(DM34-AVERAGE(DM$5:DM$59))/STDEV(DM$5:DM$59) -> 0.45326696 | DD34: =(DN34-AVERAGE(DN$29:DN$59))/STDEV(DN$29:DN$59) -> 0.070371307 | DE34: =(HAVERQ!AZ158-AVERAGE(HAVERQ!AZ$128:AZ$167,AZ$174:AZ$183))/STDEV(HAVERQ!AZ$128:AZ$167,AZ$174:AZ$183) -> 0.1823828 | DF34: =(HAVERQ!AS158-AVERAGE(HAVERQ!AS$128:AS$183))/STDEV(HAVERQ!AS$128:AS$183) -> 0.55350828 | DG34: =(DP34-AVERAGE(DP$5:DP$59))/STDEV(DP$5:DP$59) -> -0.24849204 | DH34: =(HAVERQ!AX158-AVERAGE(HAVERQ!AX$128:AX$183))/STDEV(HAVERQ!AX$128:AX$183) -> 0.18361409 | DJ34: =(DR34-AVERAGE(DR$5:DR$59))/STDEV(DR$5:DR$59) -> 0.4965736 | DL34: =100*(HAVERQ!AV158/(HAVERQ!AW158*HAVERQ!AX158/100)) -> 1.1648217 | DM34: =HAVERQ!AO158/HAVERQ!AP158 -> 0.5707635 | DN34: =100*((AVERAGE(HAVERQ!BC155:BC158)/AVERAGE(HAVERQ!BC151:BC154))-1) -> 1.2977095 | DO34: =100*(HAVERQ!BE158+HAVERQ!BF158)/(HAVERQ!BB158+HAVERQ!BG158) -> 9.1521182 | DP34: =100*((AVERAGE(HAVERQ!BA155:BA158)/AVERAGE(HAVERQ!BA151:BA154))-1) -> 2.5115325 | DR34: =(HAVERQ!AT158*HAVERQ!$AT$1)+(HAVERQ!AU158*HAVERQ!$AU$1) -> 67.544156 | DT34: Source: Oxford Economics/Haver Analytics
M35: 43313 | N35: =HAVERM!C470 -> 3.926 | O35: =HAVERM!B470 -> 4.1 | Q35: 43313 | R35: =MIN(HAVERM!C469:C471) -> 3.926 | S35: =V35-R35 -> 0.259 | T35: =HAVERM!B470 -> 4.1 | V35: =MAX(HAVERM!C469:C471) -> 4.185 | AB35: 39356 | AC35: =HAVERQ!P119 -> 1447 | AD35: =HAVERQ!O119 -> 1634 | AE35: =HAVERQ!N119 -> 1257 | AF35: =HAVERQ!M119 -> 284 | AG35: =HAVERQ!L119 -> 195 | AH35: =HAVERQ!E119-AC35-AD35-AE35-AF35-AG35 -> 736 | AJ35: 39356 | AK35: =100*(AC35/SUM($AC35:$AH35)) -> 26.057987 | AL35: =100*(AD35/SUM($AC35:$AH35)) -> 29.425536 | AM35: =100*(AE35/SUM($AC35:$AH35)) -> 22.636413 | AN35: =100*(AF35/SUM($AC35:$AH35)) -> 5.1143526 | AO35: =100*(AG35/SUM($AC35:$AH35)) -> 3.5116153 | AP35: =100*(AH35/SUM($AC35:$AH35)) -> 13.254097 | AS35: =HLOOKUP(AS$34,$AS$30:$BK$32,2,FALSE) -> Health | AT35: =HLOOKUP(AT$34,$AS$30:$BK$32,2,FALSE) -> Professional services | AU35: =HLOOKUP(AU$34,$AS$30:$BK$32,2,FALSE) -> Accommodation & food | AV35: =HLOOKUP(AV$34,$AS$30:$BK$32,2,FALSE) -> Public admin | AW35: =HLOOKUP(AW$34,$AS$30:$BK$32,2,FALSE) -> Communications | AX35: =HLOOKUP(AX$34,$AS$30:$BK$32,2,FALSE) -> Education | AY35: =HLOOKUP(AY$34,$AS$30:$BK$32,2,FALSE) -> Transport | AZ35: =HLOOKUP(AZ$34,$AS$30:$BK$32,2,FALSE) -> Real estate | ... BK35: =HLOOKUP(BK$34,$AS$30:$BK$32,2,FALSE) -> Wholesale & retail | CL35: =100*((DataQ!F194/DataQ!F190)-1) -> 1.4104639 | CM35: =100*(DataQ!I194/DataQ!J194) -> 22.276662 | CY35: =(HAVERQ!AQ159-AVERAGE(HAVERQ!AQ$128:AQ$183))/STDEV(HAVERQ!AQ$128:AQ$183) -> -0.68286081 | CZ35: =(DL35-AVERAGE(DL$5:DL$59))/STDEV(DL$5:DL$59) -> -0.71893237 | DA35: =(DO35-AVERAGE(DO$5:DO$59))/STDEV(DO$5:DO$59) -> -0.47604246 | DB35: =(HAVERQ!AR159-AVERAGE(HAVERQ!AR$128:AR$183))/STDEV(HAVERQ!AR$128:AR$183) -> -0.38512868 | DC35: =(DM35-AVERAGE(DM$5:DM$59))/STDEV(DM$5:DM$59) -> 0.39941696 | DD35: =(DN35-AVERAGE(DN$29:DN$59))/STDEV(DN$29:DN$59) -> 0.084055524 | DE35: =(HAVERQ!AZ159-AVERAGE(HAVERQ!AZ$128:AZ$167,AZ$174:AZ$183))/STDEV(HAVERQ!AZ$128:AZ$167,AZ$174:AZ$183) -> -0.24675321 | DF35: =(HAVERQ!AS159-AVERAGE(HAVERQ!AS$128:AS$183))/STDEV(HAVERQ!AS$128:AS$183) -> 0.73774993 | DG35: =(DP35-AVERAGE(DP$5:DP$59))/STDEV(DP$5:DP$59) -> -0.23957448 | DH35: =(HAVERQ!AX159-AVERAGE(HAVERQ!AX$128:AX$183))/STDEV(HAVERQ!AX$128:AX$183) -> 0.48603729 | DJ35: =(DR35-AVERAGE(DR$5:DR$59))/STDEV(DR$5:DR$59) -> 0.87612344 | DL35: =100*(HAVERQ!AV159/(HAVERQ!AW159*HAVERQ!AX159/100)) -> 1.0931728 | DM35: =HAVERQ!AO159/HAVERQ!AP159 -> 0.55805499 | DN35: =100*((AVERAGE(HAVERQ!BC156:BC159)/AVERAGE(HAVERQ!BC152:BC155))-1) -> 1.317724 | DO35: =100*(HAVERQ!BE159+HAVERQ!BF159)/(HAVERQ!BB159+HAVERQ!BG159) -> 8.9465404 | DP35: =100*((AVERAGE(HAVERQ!BA156:BA159)/AVERAGE(HAVERQ!BA152:BA155))-1) -> 2.5288527 | DR35: =(HAVERQ!AT159*HAVERQ!$AT$1)+(HAVERQ!AU159*HAVERQ!$AU$1) -> 71.310946
M36: 43344 | N36: =HAVERM!C471 -> 4.185 | O36: =HAVERM!B471 -> 4.1 | Q36: 43344 | R36: =MIN(HAVERM!C470:C472) -> 3.926 | S36: =V36-R36 -> 0.259 | T36: =HAVERM!B471 -> 4.1 | V36: =MAX(HAVERM!C470:C472) -> 4.185 | AB36: 39448 | AC36: =HAVERQ!P120 -> 1451 | AD36: =HAVERQ!O120 -> 1630 | AE36: =HAVERQ!N120 -> 1234 | AF36: =HAVERQ!M120 -> 286 | AG36: =HAVERQ!L120 -> 193 | AH36: =HAVERQ!E120-AC36-AD36-AE36-AF36-AG36 -> 751 | AJ36: 39448 | AK36: =100*(AC36/SUM($AC36:$AH36)) -> 26.167719 | AL36: =100*(AD36/SUM($AC36:$AH36)) -> 29.395852 | AM36: =100*(AE36/SUM($AC36:$AH36)) -> 22.254283 | AN36: =100*(AF36/SUM($AC36:$AH36)) -> 5.1577998 | AO36: =100*(AG36/SUM($AC36:$AH36)) -> 3.4806132 | AP36: =100*(AH36/SUM($AC36:$AH36)) -> 13.543733 | AR36: =AR32 -> 45474 | AS36: =HLOOKUP(AS$34,$AS$30:$BK$32,3,FALSE) -> 629.75 | AT36: =HLOOKUP(AT$34,$AS$30:$BK$32,3,FALSE) -> 316 | AU36: =HLOOKUP(AU$34,$AS$30:$BK$32,3,FALSE) -> 203 | AV36: =HLOOKUP(AV$34,$AS$30:$BK$32,3,FALSE) -> 202.25 | AW36: =HLOOKUP(AW$34,$AS$30:$BK$32,3,FALSE) -> 132.75 | AX36: =HLOOKUP(AX$34,$AS$30:$BK$32,3,FALSE) -> 115 | AY36: =HLOOKUP(AY$34,$AS$30:$BK$32,3,FALSE) -> 82 | AZ36: =HLOOKUP(AZ$34,$AS$30:$BK$32,3,FALSE) -> 76.25 | ... BK36: =HLOOKUP(BK$34,$AS$30:$BK$32,3,FALSE) -> -264.5 | BM36: =SUM(AS36:BK36) -> 1226.75 | CK36: 2020 | CL36: =100*((DataQ!F195/DataQ!F191)-1) -> 3.872899 | CM36: =100*(DataQ!I195/DataQ!J195) -> 21.597939 | CX36: 2018 | CY36: =(HAVERQ!AQ160-AVERAGE(HAVERQ!AQ$128:AQ$183))/STDEV(HAVERQ!AQ$128:AQ$183) -> -0.8046449 | CZ36: =(DL36-AVERAGE(DL$5:DL$59))/STDEV(DL$5:DL$59) -> -0.76483893 | DA36: =(DO36-AVERAGE(DO$5:DO$59))/STDEV(DO$5:DO$59) -> -0.51482851 | DB36: =(HAVERQ!AR160-AVERAGE(HAVERQ!AR$128:AR$183))/STDEV(HAVERQ!AR$128:AR$183) -> -0.60080074 | DC36: =(DM36-AVERAGE(DM$5:DM$59))/STDEV(DM$5:DM$59) -> 0.3918059 | DD36: =(DN36-AVERAGE(DN$29:DN$59))/STDEV(DN$29:DN$59) -> 0.095732606 | DE36: =(HAVERQ!AZ160-AVERAGE(HAVERQ!AZ$128:AZ$167,AZ$174:AZ$183))/STDEV(HAVERQ!AZ$128:AZ$167,AZ$174:AZ$183) -> -0.24675321 | DF36: =(HAVERQ!AS160-AVERAGE(HAVERQ!AS$128:AS$183))/STDEV(HAVERQ!AS$128:AS$183) -> 0.84303087 | DG36: =(DP36-AVERAGE(DP$5:DP$59))/STDEV(DP$5:DP$59) -> -0.16885036 | DH36: =(HAVERQ!AX160-AVERAGE(HAVERQ!AX$128:AX$183))/STDEV(HAVERQ!AX$128:AX$183) -> 1.0908837 | DJ36: =(DR36-AVERAGE(DR$5:DR$59))/STDEV(DR$5:DR$59) -> -0.19309553 | DL36: =100*(HAVERQ!AV160/(HAVERQ!AW160*HAVERQ!AX160/100)) -> 1.058793 | DM36: =HAVERQ!AO160/HAVERQ!AP160 -> 0.55625879 | DN36: =100*((AVERAGE(HAVERQ!BC157:BC160)/AVERAGE(HAVERQ!BC153:BC156))-1) -> 1.3348029 | DO36: =100*(HAVERQ!BE160+HAVERQ!BF160)/(HAVERQ!BB160+HAVERQ!BG160) -> 8.888035 | DP36: =100*((AVERAGE(HAVERQ!BA157:BA160)/AVERAGE(HAVERQ!BA153:BA156))-1) -> 2.6662167 | DR36: =(HAVERQ!AT160*HAVERQ!$AT$1)+(HAVERQ!AU160*HAVERQ!$AU$1) -> 60.699629
M37: 43374 | N37: =HAVERM!C472 -> 4.101 | O37: =HAVERM!B472 -> 4 | Q37: 43374 | R37: =MIN(HAVERM!C471:C473) -> 3.829 | S37: =V37-R37 -> 0.356 | T37: =HAVERM!B472 -> 4 | V37: =MAX(HAVERM!C471:C473) -> 4.185 | AB37: 39539 | AC37: =HAVERQ!P121 -> 1463 | AD37: =HAVERQ!O121 -> 1637 | AE37: =HAVERQ!N121 -> 1226 | AF37: =HAVERQ!M121 -> 286 | AG37: =HAVERQ!L121 -> 193 | AH37: =HAVERQ!E121-AC37-AD37-AE37-AF37-AG37 -> 753 | AJ37: 39539 | AK37: =100*(AC37/SUM($AC37:$AH37)) -> 26.322418 | AL37: =100*(AD37/SUM($AC37:$AH37)) -> 29.453041 | AM37: =100*(AE37/SUM($AC37:$AH37)) -> 22.058294 | AN37: =100*(AF37/SUM($AC37:$AH37)) -> 5.1457359 | AO37: =100*(AG37/SUM($AC37:$AH37)) -> 3.4724721 | AP37: =100*(AH37/SUM($AC37:$AH37)) -> 13.548039 | AS37: =AS36/$BM$36 -> 0.51334828 | AV37: =AV36/$BM$36 -> 0.16486652 | AX37: =AX36/$BM$36 -> 0.093743632 | CL37: =100*((DataQ!F196/DataQ!F192)-1) -> 24.742239 | CM37: =100*(DataQ!I196/DataQ!J196) -> 24.290995 | CY37: =(HAVERQ!AQ161-AVERAGE(HAVERQ!AQ$128:AQ$183))/STDEV(HAVERQ!AQ$128:AQ$183) -> -0.926429 | CZ37: =(DL37-AVERAGE(DL$5:DL$59))/STDEV(DL$5:DL$59) -> -0.780235 | DA37: =(DO37-AVERAGE(DO$5:DO$59))/STDEV(DO$5:DO$59) -> -0.69078018 | DB37: =(HAVERQ!AR161-AVERAGE(HAVERQ!AR$128:AR$183))/STDEV(HAVERQ!AR$128:AR$183) -> -0.54688272 | DC37: =(DM37-AVERAGE(DM$5:DM$59))/STDEV(DM$5:DM$59) -> 0.64679166 | DD37: =(DN37-AVERAGE(DN$29:DN$59))/STDEV(DN$29:DN$59) -> 0.057526309 | DE37: =(HAVERQ!AZ161-AVERAGE(HAVERQ!AZ$128:AZ$167,AZ$174:AZ$183))/STDEV(HAVERQ!AZ$128:AZ$167,AZ$174:AZ$183) -> -0.24675321 | DF37: =(HAVERQ!AS161-AVERAGE(HAVERQ!AS$128:AS$183))/STDEV(HAVERQ!AS$128:AS$183) -> 0.7903904 | DG37: =(DP37-AVERAGE(DP$5:DP$59))/STDEV(DP$5:DP$59) -> -0.19463686 | DH37: =(HAVERQ!AX161-AVERAGE(HAVERQ!AX$128:AX$183))/STDEV(HAVERQ!AX$128:AX$183) -> 0.78846049 | DJ37: =(DR37-AVERAGE(DR$5:DR$59))/STDEV(DR$5:DR$59) -> 0.10135797 | DL37: =100*(HAVERQ!AV161/(HAVERQ!AW161*HAVERQ!AX161/100)) -> 1.0472628 | DM37: =HAVERQ!AO161/HAVERQ!AP161 -> 0.61643502 | DN37: =100*((AVERAGE(HAVERQ!BC158:BC161)/AVERAGE(HAVERQ!BC154:BC157))-1) -> 1.2789224 | DO37: =100*(HAVERQ!BE161+HAVERQ!BF161)/(HAVERQ!BB161+HAVERQ!BG161) -> 8.622627 | DP37: =100*((AVERAGE(HAVERQ!BA158:BA161)/AVERAGE(HAVERQ!BA154:BA157))-1) -> 2.6161328 | DR37: =(HAVERQ!AT161*HAVERQ!$AT$1)+(HAVERQ!AU161*HAVERQ!$AU$1) -> 63.621892
M38: 43405 | N38: =HAVERM!C473 -> 3.829 | O38: =HAVERM!B473 -> 4 | Q38: 43405 | R38: =MIN(HAVERM!C472:C474) -> 3.829 | S38: =V38-R38 -> 0.314 | T38: =HAVERM!B473 -> 4 | V38: =MAX(HAVERM!C472:C474) -> 4.143 | AB38: 39630 | AC38: =HAVERQ!P122 -> 1483 | AD38: =HAVERQ!O122 -> 1646 | AE38: =HAVERQ!N122 -> 1208 | AF38: =HAVERQ!M122 -> 287 | AG38: =HAVERQ!L122 -> 194 | AH38: =HAVERQ!E122-AC38-AD38-AE38-AF38-AG38 -> 769 | AJ38: 39630 | AK38: =100*(AC38/SUM($AC38:$AH38)) -> 26.543762 | AL38: =100*(AD38/SUM($AC38:$AH38)) -> 29.461249 | AM38: =100*(AE38/SUM($AC38:$AH38)) -> 21.621622 | AN38: =100*(AF38/SUM($AC38:$AH38)) -> 5.136925 | AO38: =100*(AG38/SUM($AC38:$AH38)) -> 3.4723465 | AP38: =100*(AH38/SUM($AC38:$AH38)) -> 13.764095 | CL38: =100*((DataQ!F197/DataQ!F193)-1) -> 10.361268 | CM38: =100*(DataQ!I197/DataQ!J197) -> 23.602395 | CY38: =(HAVERQ!AQ162-AVERAGE(HAVERQ!AQ$128:AQ$183))/STDEV(HAVERQ!AQ$128:AQ$183) -> -0.86553695 | CZ38: =(DL38-AVERAGE(DL$5:DL$59))/STDEV(DL$5:DL$59) -> -0.72928583 | DA38: =(DO38-AVERAGE(DO$5:DO$59))/STDEV(DO$5:DO$59) -> -0.91240817 | DB38: =(HAVERQ!AR162-AVERAGE(HAVERQ!AR$128:AR$183))/STDEV(HAVERQ!AR$128:AR$183) -> -0.8164728 | DC38: =(DM38-AVERAGE(DM$5:DM$59))/STDEV(DM$5:DM$59) -> 0.68385073 | DD38: =(DN38-AVERAGE(DN$29:DN$59))/STDEV(DN$29:DN$59) -> 0.019987603 | DE38: =(HAVERQ!AZ162-AVERAGE(HAVERQ!AZ$128:AZ$167,AZ$174:AZ$183))/STDEV(HAVERQ!AZ$128:AZ$167,AZ$174:AZ$183) -> 1.0406548 | DF38: =(HAVERQ!AS162-AVERAGE(HAVERQ!AS$128:AS$183))/STDEV(HAVERQ!AS$128:AS$183) -> 0.89567134 | DG38: =(DP38-AVERAGE(DP$5:DP$59))/STDEV(DP$5:DP$59) -> -0.10855091 | DH38: =(HAVERQ!AX162-AVERAGE(HAVERQ!AX$128:AX$183))/STDEV(HAVERQ!AX$128:AX$183) -> 1.0908837 | DJ38: =(DR38-AVERAGE(DR$5:DR$59))/STDEV(DR$5:DR$59) -> 0.96905267 | DL38: =100*(HAVERQ!AV162/(HAVERQ!AW162*HAVERQ!AX162/100)) -> 1.085419 | DM38: =HAVERQ!AO162/HAVERQ!AP162 -> 0.6251809 | DN38: =100*((AVERAGE(HAVERQ!BC159:BC162)/AVERAGE(HAVERQ!BC155:BC158))-1) -> 1.2240184 | DO38: =100*(HAVERQ!BE162+HAVERQ!BF162)/(HAVERQ!BB162+HAVERQ!BG162) -> 8.2883202 | DP38: =100*((AVERAGE(HAVERQ!BA159:BA162)/AVERAGE(HAVERQ!BA155:BA158))-1) -> 2.7833333 | DR38: =(HAVERQ!AT162*HAVERQ!$AT$1)+(HAVERQ!AU162*HAVERQ!$AU$1) -> 72.23321
M39: 43435 | N39: =HAVERM!C474 -> 4.143 | O39: =HAVERM!B474 -> 3.9 | Q39: 43435 | R39: =MIN(HAVERM!C473:C475) -> 3.829 | S39: =V39-R39 -> 0.314 | T39: =HAVERM!B474 -> 3.9 | V39: =MAX(HAVERM!C473:C475) -> 4.143 | AB39: 39722 | AC39: =HAVERQ!P123 -> 1503 | AD39: =HAVERQ!O123 -> 1649 | AE39: =HAVERQ!N123 -> 1210 | AF39: =HAVERQ!M123 -> 289 | AG39: =HAVERQ!L123 -> 193 | AH39: =HAVERQ!E123-AC39-AD39-AE39-AF39-AG39 -> 764 | AJ39: 39722 | AK39: =100*(AC39/SUM($AC39:$AH39)) -> 26.800999 | AL39: =100*(AD39/SUM($AC39:$AH39)) -> 29.404422 | AM39: =100*(AE39/SUM($AC39:$AH39)) -> 21.57632 | AN39: =100*(AF39/SUM($AC39:$AH39)) -> 5.1533524 | AO39: =100*(AG39/SUM($AC39:$AH39)) -> 3.4415121 | AP39: =100*(AH39/SUM($AC39:$AH39)) -> 13.623395 | CL39: =100*((DataQ!F198/DataQ!F194)-1) -> 11.727665 | CM39: =100*(DataQ!I198/DataQ!J198) -> 21.764451 | CY39: =(HAVERQ!AQ163-AVERAGE(HAVERQ!AQ$128:AQ$183))/STDEV(HAVERQ!AQ$128:AQ$183) -> -0.926429 | CZ39: =(DL39-AVERAGE(DL$5:DL$59))/STDEV(DL$5:DL$59) -> -0.80655046 | DA39: =(DO39-AVERAGE(DO$5:DO$59))/STDEV(DO$5:DO$59) -> -1.088046 | DB39: =(HAVERQ!AR163-AVERAGE(HAVERQ!AR$128:AR$183))/STDEV(HAVERQ!AR$128:AR$183) -> -0.70863677 | DC39: =(DM39-AVERAGE(DM$5:DM$59))/STDEV(DM$5:DM$59) -> 0.67392761 | DD39: =(DN39-AVERAGE(DN$29:DN$59))/STDEV(DN$29:DN$59) -> -0.03221039 | DE39: =(HAVERQ!AZ163-AVERAGE(HAVERQ!AZ$128:AZ$167,AZ$174:AZ$183))/STDEV(HAVERQ!AZ$128:AZ$167,AZ$174:AZ$183) -> 0.1823828 | DF39: =(HAVERQ!AS163-AVERAGE(HAVERQ!AS$128:AS$183))/STDEV(HAVERQ!AS$128:AS$183) -> 1.1062332 | DG39: =(DP39-AVERAGE(DP$5:DP$59))/STDEV(DP$5:DP$59) -> 0.018088979 | DH39: =(HAVERQ!AX163-AVERAGE(HAVERQ!AX$128:AX$183))/STDEV(HAVERQ!AX$128:AX$183) -> 1.6957301 | DJ39: =(DR39-AVERAGE(DR$5:DR$59))/STDEV(DR$5:DR$59) -> 0.8301916 | DL39: =100*(HAVERQ!AV163/(HAVERQ!AW163*HAVERQ!AX163/100)) -> 1.0275549 | DM39: =HAVERQ!AO163/HAVERQ!AP163 -> 0.62283906 | DN39: =100*((AVERAGE(HAVERQ!BC160:BC163)/AVERAGE(HAVERQ!BC156:BC159))-1) -> 1.1476737 | DO39: =100*(HAVERQ!BE163+HAVERQ!BF163)/(HAVERQ!BB163+HAVERQ!BG163) -> 8.0233856 | DP39: =100*((AVERAGE(HAVERQ!BA160:BA163)/AVERAGE(HAVERQ!BA156:BA159))-1) -> 3.0292998 | DR39: =(HAVERQ!AT163*HAVERQ!$AT$1)+(HAVERQ!AU163*HAVERQ!$AU$1) -> 70.855102
M40: 43466 | N40: =HAVERM!C475 -> 3.864 | O40: =HAVERM!B475 -> 4 | Q40: 43466 | R40: =MIN(HAVERM!C474:C476) -> 3.822 | S40: =V40-R40 -> 0.321 | T40: =HAVERM!B475 -> 4 | V40: =MAX(HAVERM!C474:C476) -> 4.143 | AB40: 39814 | AC40: =HAVERQ!P124 -> 1503 | AD40: =HAVERQ!O124 -> 1662 | AE40: =HAVERQ!N124 -> 1208 | AF40: =HAVERQ!M124 -> 293 | AG40: =HAVERQ!L124 -> 196 | AH40: =HAVERQ!E124-AC40-AD40-AE40-AF40-AG40 -> 750 | AJ40: 39814 | AK40: =100*(AC40/SUM($AC40:$AH40)) -> 26.781896 | AL40: =100*(AD40/SUM($AC40:$AH40)) -> 29.61511 | AM40: =100*(AE40/SUM($AC40:$AH40)) -> 21.525303 | AN40: =100*(AF40/SUM($AC40:$AH40)) -> 5.2209551 | AO40: =100*(AG40/SUM($AC40:$AH40)) -> 3.492516 | AP40: =100*(AH40/SUM($AC40:$AH40)) -> 13.36422 | AS40: Big 4 | AT40: =AU1+AX1+BF1+AY1 -> 12506 | CK40: 2021 | CL40: =100*((DataQ!F199/DataQ!F195)-1) -> 9.9731084 | CM40: =100*(DataQ!I199/DataQ!J199) -> 21.955159 | CX40: 2019 | CY40: =(HAVERQ!AQ164-AVERAGE(HAVERQ!AQ$128:AQ$183))/STDEV(HAVERQ!AQ$128:AQ$183) -> -1.0482131 | CZ40: =(DL40-AVERAGE(DL$5:DL$59))/STDEV(DL$5:DL$59) -> -0.82606805 | DA40: =(DO40-AVERAGE(DO$5:DO$59))/STDEV(DO$5:DO$59) -> -1.012425 | DB40: =(HAVERQ!AR164-AVERAGE(HAVERQ!AR$128:AR$183))/STDEV(HAVERQ!AR$128:AR$183) -> -0.70863677 | DC40: =(DM40-AVERAGE(DM$5:DM$59))/STDEV(DM$5:DM$59) -> 0.69824844 | DD40: =(DN40-AVERAGE(DN$29:DN$59))/STDEV(DN$29:DN$59) -> -0.04728341 | DE40: =(HAVERQ!AZ164-AVERAGE(HAVERQ!AZ$128:AZ$167,AZ$174:AZ$183))/STDEV(HAVERQ!AZ$128:AZ$167,AZ$174:AZ$183) -> 1.4697908 | DF40: =(HAVERQ!AS164-AVERAGE(HAVERQ!AS$128:AS$183))/STDEV(HAVERQ!AS$128:AS$183) -> 1.1851939 | DG40: =(DP40-AVERAGE(DP$5:DP$59))/STDEV(DP$5:DP$59) -> 0.057841355 | DH40: =(HAVERQ!AX164-AVERAGE(HAVERQ!AX$128:AX$183))/STDEV(HAVERQ!AX$128:AX$183) -> 1.3933069 | DJ40: =(DR40-AVERAGE(DR$5:DR$59))/STDEV(DR$5:DR$59) -> 0.8145258 | DL40: =100*(HAVERQ!AV164/(HAVERQ!AW164*HAVERQ!AX164/100)) -> 1.012938 | DM40: =HAVERQ!AO164/HAVERQ!AP164 -> 0.62857873 | DN40: =100*((AVERAGE(HAVERQ!BC161:BC164)/AVERAGE(HAVERQ!BC157:BC160))-1) -> 1.1256279 | DO40: =100*(HAVERQ!BE164+HAVERQ!BF164)/(HAVERQ!BB164+HAVERQ!BG164) -> 8.1374534 | DP40: =100*((AVERAGE(HAVERQ!BA161:BA164)/AVERAGE(HAVERQ!BA157:BA160))-1) -> 3.1065089 | DR40: =(HAVERQ!AT164*HAVERQ!$AT$1)+(HAVERQ!AU164*HAVERQ!$AU$1) -> 70.699629
M41: 43497 | N41: =HAVERM!C476 -> 3.822 | O41: =HAVERM!B476 -> 3.8 | Q41: 43497 | R41: =MIN(HAVERM!C475:C477) -> 3.814 | S41: =V41-R41 -> 0.05 | T41: =HAVERM!B476 -> 3.8 | V41: =MAX(HAVERM!C475:C477) -> 3.864 | AB41: 39904 | AC41: =HAVERQ!P125 -> 1530 | AD41: =HAVERQ!O125 -> 1657 | AE41: =HAVERQ!N125 -> 1208 | AF41: =HAVERQ!M125 -> 294 | AG41: =HAVERQ!L125 -> 197 | AH41: =HAVERQ!E125-AC41-AD41-AE41-AF41-AG41 -> 735 | AJ41: 39904 | AK41: =100*(AC41/SUM($AC41:$AH41)) -> 27.219356 | AL41: =100*(AD41/SUM($AC41:$AH41)) -> 29.47874 | AM41: =100*(AE41/SUM($AC41:$AH41)) -> 21.490838 | AN41: =100*(AF41/SUM($AC41:$AH41)) -> 5.2303861 | AO41: =100*(AG41/SUM($AC41:$AH41)) -> 3.5047145 | AP41: =100*(AH41/SUM($AC41:$AH41)) -> 13.075965 | AS41: Total | AT41: =HAVERQ!S186 -> 36793 | CL41: =100*((DataQ!F200/DataQ!F196)-1) -> -13.621606 | CM41: =100*(DataQ!I200/DataQ!J200) -> 22.586677 | CY41: =(HAVERQ!AQ165-AVERAGE(HAVERQ!AQ$128:AQ$183))/STDEV(HAVERQ!AQ$128:AQ$183) -> -0.98732104 | CZ41: =(DL41-AVERAGE(DL$5:DL$59))/STDEV(DL$5:DL$59) -> -0.85778361 | DA41: =(DO41-AVERAGE(DO$5:DO$59))/STDEV(DO$5:DO$59) -> -1.0623375 | DB41: =(HAVERQ!AR165-AVERAGE(HAVERQ!AR$128:AR$183))/STDEV(HAVERQ!AR$128:AR$183) -> -0.49296471 | DC41: =(DM41-AVERAGE(DM$5:DM$59))/STDEV(DM$5:DM$59) -> 0.69939996 | DD41: =(DN41-AVERAGE(DN$29:DN$59))/STDEV(DN$29:DN$59) -> -0.037467363 | DE41: =(HAVERQ!AZ165-AVERAGE(HAVERQ!AZ$128:AZ$167,AZ$174:AZ$183))/STDEV(HAVERQ!AZ$128:AZ$167,AZ$174:AZ$183) -> 0.61151881 | DF41: =(HAVERQ!AS165-AVERAGE(HAVERQ!AS$128:AS$183))/STDEV(HAVERQ!AS$128:AS$183) -> 1.1062332 | DG41: =(DP41-AVERAGE(DP$5:DP$59))/STDEV(DP$5:DP$59) -> 0.28429109 | DH41: =(HAVERQ!AX165-AVERAGE(HAVERQ!AX$128:AX$183))/STDEV(HAVERQ!AX$128:AX$183) -> 2.3005765 | DJ41: =(DR41-AVERAGE(DR$5:DR$59))/STDEV(DR$5:DR$59) -> -0.3711211 | DL41: =100*(HAVERQ!AV165/(HAVERQ!AW165*HAVERQ!AX165/100)) -> 0.98918601 | DM41: =HAVERQ!AO165/HAVERQ!AP165 -> 0.62885049 | DN41: =100*((AVERAGE(HAVERQ!BC162:BC165)/AVERAGE(HAVERQ!BC158:BC161))-1) -> 1.1399849 | DO41: =100*(HAVERQ!BE165+HAVERQ!BF165)/(HAVERQ!BB165+HAVERQ!BG165) -> 8.0621647 | DP41: =100*((AVERAGE(HAVERQ!BA162:BA165)/AVERAGE(HAVERQ!BA158:BA161))-1) -> 3.5463311 | DR41: =(HAVERQ!AT165*HAVERQ!$AT$1)+(HAVERQ!AU165*HAVERQ!$AU$1) -> 58.932838
M42: 43525 | N42: =HAVERM!C477 -> 3.814 | O42: =HAVERM!B477 -> 3.8 | Q42: 43525 | R42: =MIN(HAVERM!C476:C478) -> 3.814 | S42: =V42-R42 -> 0.075 | T42: =HAVERM!B477 -> 3.8 | V42: =MAX(HAVERM!C476:C478) -> 3.889 | AB42: 39995 | AC42: =HAVERQ!P126 -> 1546 | AD42: =HAVERQ!O126 -> 1656 | AE42: =HAVERQ!N126 -> 1220 | AF42: =HAVERQ!M126 -> 296 | AG42: =HAVERQ!L126 -> 199 | AH42: =HAVERQ!E126-AC42-AD42-AE42-AF42-AG42 -> 729 | AJ42: 39995 | AK42: =100*(AC42/SUM($AC42:$AH42)) -> 27.382217 | AL42: =100*(AD42/SUM($AC42:$AH42)) -> 29.330499 | AM42: =100*(AE42/SUM($AC42:$AH42)) -> 21.608218 | AN42: =100*(AF42/SUM($AC42:$AH42)) -> 5.2426497 | AO42: =100*(AG42/SUM($AC42:$AH42)) -> 3.5246192 | AP42: =100*(AH42/SUM($AC42:$AH42)) -> 12.911796 | AS42: Share | AT42: =AT40/AT41 -> 0.33990161 | CL42: =100*((DataQ!F201/DataQ!F197)-1) -> -2.4675534 | CM42: =100*(DataQ!I201/DataQ!J201) -> 21.710195 | CY42: =(HAVERQ!AQ166-AVERAGE(HAVERQ!AQ$128:AQ$183))/STDEV(HAVERQ!AQ$128:AQ$183) -> -0.98732104 | CZ42: =(DL42-AVERAGE(DL$5:DL$59))/STDEV(DL$5:DL$59) -> -0.96432107 | DA42: =(DO42-AVERAGE(DO$5:DO$59))/STDEV(DO$5:DO$59) -> -1.0582164 | DB42: =(HAVERQ!AR166-AVERAGE(HAVERQ!AR$128:AR$183))/STDEV(HAVERQ!AR$128:AR$183) -> -0.16945662 | DC42: =(DM42-AVERAGE(DM$5:DM$59))/STDEV(DM$5:DM$59) -> 0.70838243 | DD42: =(DN42-AVERAGE(DN$29:DN$59))/STDEV(DN$29:DN$59) -> -0.060399735 | DE42: =(HAVERQ!AZ166-AVERAGE(HAVERQ!AZ$128:AZ$167,AZ$174:AZ$183))/STDEV(HAVERQ!AZ$128:AZ$167,AZ$174:AZ$183) -> 0.1823828 | DF42: =(HAVERQ!AS166-AVERAGE(HAVERQ!AS$128:AS$183))/STDEV(HAVERQ!AS$128:AS$183) -> 1.0535927 | DG42: =(DP42-AVERAGE(DP$5:DP$59))/STDEV(DP$5:DP$59) -> 0.38696185 | DH42: =(HAVERQ!AX166-AVERAGE(HAVERQ!AX$128:AX$183))/STDEV(HAVERQ!AX$128:AX$183) -> 1.6957301 | DJ42: =(DR42-AVERAGE(DR$5:DR$59))/STDEV(DR$5:DR$59) -> 0.90745503 | DL42: =100*(HAVERQ!AV166/(HAVERQ!AW166*HAVERQ!AX166/100)) -> 0.90939927 | DM42: =HAVERQ!AO166/HAVERQ!AP166 -> 0.63097034 | DN42: =100*((AVERAGE(HAVERQ!BC163:BC166)/AVERAGE(HAVERQ!BC159:BC162))-1) -> 1.106444 | DO42: =100*(HAVERQ!BE166+HAVERQ!BF166)/(HAVERQ!BB166+HAVERQ!BG166) -> 8.0683811 | DP42: =100*((AVERAGE(HAVERQ!BA163:BA166)/AVERAGE(HAVERQ!BA159:BA162))-1) -> 3.7457435 | DR42: =(HAVERQ!AT166*HAVERQ!$AT$1)+(HAVERQ!AU166*HAVERQ!$AU$1) -> 71.621892
M43: 43556 | N43: =HAVERM!C478 -> 3.889 | O43: =HAVERM!B478 -> 3.8 | Q43: 43556 | R43: =MIN(HAVERM!C477:C479) -> 3.688 | S43: =V43-R43 -> 0.201 | T43: =HAVERM!B478 -> 3.8 | V43: =MAX(HAVERM!C477:C479) -> 3.889 | AB43: 40087 | AC43: =HAVERQ!P127 -> 1552 | AD43: =HAVERQ!O127 -> 1673 | AE43: =HAVERQ!N127 -> 1213 | AF43: =HAVERQ!M127 -> 295 | AG43: =HAVERQ!L127 -> 199 | AH43: =HAVERQ!E127-AC43-AD43-AE43-AF43-AG43 -> 726 | AJ43: 40087 | AK43: =100*(AC43/SUM($AC43:$AH43)) -> 27.430187 | AL43: =100*(AD43/SUM($AC43:$AH43)) -> 29.568752 | AM43: =100*(AE43/SUM($AC43:$AH43)) -> 21.438671 | AN43: =100*(AF43/SUM($AC43:$AH43)) -> 5.2138565 | AO43: =100*(AG43/SUM($AC43:$AH43)) -> 3.5171439 | AP43: =100*(AH43/SUM($AC43:$AH43)) -> 12.831389 | CL43: =100*((DataQ!F202/DataQ!F198)-1) -> -4.2998264 | CM43: =100*(DataQ!I202/DataQ!J202) -> 21.584472 | CY43: =(HAVERQ!AQ167-AVERAGE(HAVERQ!AQ$128:AQ$183))/STDEV(HAVERQ!AQ$128:AQ$183) -> -1.1091051 | CZ43: =(DL43-AVERAGE(DL$5:DL$59))/STDEV(DL$5:DL$59) -> -1.0351297 | DA43: =(DO43-AVERAGE(DO$5:DO$59))/STDEV(DO$5:DO$59) -> -0.93790899 | DB43: =(HAVERQ!AR167-AVERAGE(HAVERQ!AR$128:AR$183))/STDEV(HAVERQ!AR$128:AR$183) -> -0.33121066 | DC43: =(DM43-AVERAGE(DM$5:DM$59))/STDEV(DM$5:DM$59) -> 0.68596955 | DD43: =(DN43-AVERAGE(DN$29:DN$59))/STDEV(DN$29:DN$59) -> -0.10060954 | DE43: =(HAVERQ!AZ167-AVERAGE(HAVERQ!AZ$128:AZ$167,AZ$174:AZ$183))/STDEV(HAVERQ!AZ$128:AZ$167,AZ$174:AZ$183) -> -0.67588921 | DF43: =(HAVERQ!AS167-AVERAGE(HAVERQ!AS$128:AS$183))/STDEV(HAVERQ!AS$128:AS$183) -> 0.94831181 | DG43: =(DP43-AVERAGE(DP$5:DP$59))/STDEV(DP$5:DP$59) -> 0.23694349 | DH43: =(HAVERQ!AX167-AVERAGE(HAVERQ!AX$128:AX$183))/STDEV(HAVERQ!AX$128:AX$183) -> 2.3005765 | DJ43: =(DR43-AVERAGE(DR$5:DR$59))/STDEV(DR$5:DR$59) -> 0.98471847 | DL43: =100*(HAVERQ!AV167/(HAVERQ!AW167*HAVERQ!AX167/100)) -> 0.85637013 | DM43: =HAVERQ!AO167/HAVERQ!AP167 -> 0.62568093 | DN43: =100*((AVERAGE(HAVERQ!BC164:BC167)/AVERAGE(HAVERQ!BC160:BC163))-1) -> 1.0476332 | DO43: =100*(HAVERQ!BE167+HAVERQ!BF167)/(HAVERQ!BB167+HAVERQ!BG167) -> 8.2498544 | DP43: =100*((AVERAGE(HAVERQ!BA164:BA167)/AVERAGE(HAVERQ!BA160:BA163))-1) -> 3.4543702 | DR43: =(HAVERQ!AT167*HAVERQ!$AT$1)+(HAVERQ!AU167*HAVERQ!$AU$1) -> 72.388683
M44: 43586 | N44: =HAVERM!C479 -> 3.688 | O44: =HAVERM!B479 -> 3.9 | Q44: 43586 | R44: =MIN(HAVERM!C478:C480) -> 3.688 | S44: =V44-R44 -> 0.395 | T44: =HAVERM!B479 -> 3.9 | V44: =MAX(HAVERM!C478:C480) -> 4.083 | AB44: 40179 | AC44: =HAVERQ!P128 -> 1557 | AD44: =HAVERQ!O128 -> 1671 | AE44: =HAVERQ!N128 -> 1213 | AF44: =HAVERQ!M128 -> 295 | AG44: =HAVERQ!L128 -> 199 | AH44: =HAVERQ!E128-AC44-AD44-AE44-AF44-AG44 -> 717 | AJ44: 40179 | AK44: =100*(AC44/SUM($AC44:$AH44)) -> 27.547771 | AL44: =100*(AD44/SUM($AC44:$AH44)) -> 29.564756 | AM44: =100*(AE44/SUM($AC44:$AH44)) -> 21.46143 | AN44: =100*(AF44/SUM($AC44:$AH44)) -> 5.2193914 | AO44: =100*(AG44/SUM($AC44:$AH44)) -> 3.5208776 | AP44: =100*(AH44/SUM($AC44:$AH44)) -> 12.685775 | CK44: 2022 | CL44: =100*((DataQ!F203/DataQ!F199)-1) -> -3.5561128 | CM44: =100*(DataQ!I203/DataQ!J203) -> 21.094265 | CX44: 2020 | CY44: =(HAVERQ!AQ168-AVERAGE(HAVERQ!AQ$128:AQ$183))/STDEV(HAVERQ!AQ$128:AQ$183) -> -0.86553695 | CZ44: =(DL44-AVERAGE(DL$5:DL$59))/STDEV(DL$5:DL$59) -> -0.96991355 | DA44: =(DO44-AVERAGE(DO$5:DO$59))/STDEV(DO$5:DO$59) -> -0.91389887 | DB44: =(HAVERQ!AR168-AVERAGE(HAVERQ!AR$128:AR$183))/STDEV(HAVERQ!AR$128:AR$183) -> -0.43904669 | DC44: =(DM44-AVERAGE(DM$5:DM$59))/STDEV(DM$5:DM$59) -> 0.34711691 | DD44: =(DN44-AVERAGE(DN$29:DN$59))/STDEV(DN$29:DN$59) -> -0.18625634 | DE44: =(HAVERQ!AZ168-AVERAGE(HAVERQ!AZ$128:AZ$167,AZ$174:AZ$183))/STDEV(HAVERQ!AZ$128:AZ$167,AZ$174:AZ$183) -> -3.2507053 | DF44: =(HAVERQ!AS168-AVERAGE(HAVERQ!AS$128:AS$183))/STDEV(HAVERQ!AS$128:AS$183) -> 0.68510946 | DG44: =(DP44-AVERAGE(DP$5:DP$59))/STDEV(DP$5:DP$59) -> 0.091728307 | DH44: =(HAVERQ!AX168-AVERAGE(HAVERQ!AX$128:AX$183))/STDEV(HAVERQ!AX$128:AX$183) -> 2.3005765 | DJ44: =(DR44-AVERAGE(DR$5:DR$59))/STDEV(DR$5:DR$59) -> 0.98471847 | DL44: =100*(HAVERQ!AV168/(HAVERQ!AW168*HAVERQ!AX168/100)) -> 0.90521102 | DM44: =HAVERQ!AO168/HAVERQ!AP168 -> 0.54571226 | DN44: =100*((AVERAGE(HAVERQ!BC165:BC168)/AVERAGE(HAVERQ!BC161:BC164))-1) -> 0.92236637 | DO44: =100*(HAVERQ!BE168+HAVERQ!BF168)/(HAVERQ!BB168+HAVERQ!BG168) -> 8.2860716 | DP44: =100*((AVERAGE(HAVERQ!BA165:BA168)/AVERAGE(HAVERQ!BA161:BA164))-1) -> 3.1723258 | DR44: =(HAVERQ!AT168*HAVERQ!$AT$1)+(HAVERQ!AU168*HAVERQ!$AU$1) -> 72.388683
M45: 43617 | N45: =HAVERM!C480 -> 4.083 | O45: =HAVERM!B480 -> 3.9 | Q45: 43617 | R45: =MIN(HAVERM!C479:C481) -> 3.688 | S45: =V45-R45 -> 0.395 | T45: =HAVERM!B480 -> 3.9 | V45: =MAX(HAVERM!C479:C481) -> 4.083 | AB45: 40269 | AC45: =HAVERQ!P129 -> 1559 | AD45: =HAVERQ!O129 -> 1688 | AE45: =HAVERQ!N129 -> 1200 | AF45: =HAVERQ!M129 -> 292 | AG45: =HAVERQ!L129 -> 197 | AH45: =HAVERQ!E129-AC45-AD45-AE45-AF45-AG45 -> 697 | AJ45: 40269 | AK45: =100*(AC45/SUM($AC45:$AH45)) -> 27.676194 | AL45: =100*(AD45/SUM($AC45:$AH45)) -> 29.96627 | AM45: =100*(AE45/SUM($AC45:$AH45)) -> 21.303036 | AN45: =100*(AF45/SUM($AC45:$AH45)) -> 5.1837387 | AO45: =100*(AG45/SUM($AC45:$AH45)) -> 3.4972484 | AP45: =100*(AH45/SUM($AC45:$AH45)) -> 12.373513 | CL45: =100*((DataQ!F204/DataQ!F200)-1) -> 2.3235521 | CM45: =100*(DataQ!I204/DataQ!J204) -> 21.380345 | CY45: =(HAVERQ!AQ169-AVERAGE(HAVERQ!AQ$128:AQ$183))/STDEV(HAVERQ!AQ$128:AQ$183) -> -0.86553695 | CZ45: =(DL45-AVERAGE(DL$5:DL$59))/STDEV(DL$5:DL$59) -> -1.2166463 | DA45: =(DO45-AVERAGE(DO$5:DO$59))/STDEV(DO$5:DO$59) -> -0.27919018 | DB45: =(HAVERQ!AR169-AVERAGE(HAVERQ!AR$128:AR$183))/STDEV(HAVERQ!AR$128:AR$183) -> 0.10013346 | DC45: =(DM45-AVERAGE(DM$5:DM$59))/STDEV(DM$5:DM$59) -> -0.91099781 | DD45: =(DN45-AVERAGE(DN$29:DN$59))/STDEV(DN$29:DN$59) -> -0.66086019 | DE45: =(HAVERQ!AZ169-AVERAGE(HAVERQ!AZ$128:AZ$167,AZ$174:AZ$183))/STDEV(HAVERQ!AZ$128:AZ$167,AZ$174:AZ$183) -> -25.994914 | DF45: =(HAVERQ!AS169-AVERAGE(HAVERQ!AS$128:AS$183))/STDEV(HAVERQ!AS$128:AS$183) -> -0.49930113 | DG45: =(DP45-AVERAGE(DP$5:DP$59))/STDEV(DP$5:DP$59) -> -0.74524317 | DH45: =(HAVERQ!AX169-AVERAGE(HAVERQ!AX$128:AX$183))/STDEV(HAVERQ!AX$128:AX$183) -> 0.18361409 | DJ45: =(DR45-AVERAGE(DR$5:DR$59))/STDEV(DR$5:DR$59) -> 0.25588485 | DL45: =100*(HAVERQ!AV169/(HAVERQ!AW169*HAVERQ!AX169/100)) -> 0.72043091 | DM45: =HAVERQ!AO169/HAVERQ!AP169 -> 0.24879923 | DN45: =100*((AVERAGE(HAVERQ!BC166:BC169)/AVERAGE(HAVERQ!BC162:BC165))-1) -> 0.22821166 | DO45: =100*(HAVERQ!BE169+HAVERQ!BF169)/(HAVERQ!BB169+HAVERQ!BG169) -> 9.2434752 | DP45: =100*((AVERAGE(HAVERQ!BA166:BA169)/AVERAGE(HAVERQ!BA162:BA165))-1) -> 1.5467172 | DR45: =(HAVERQ!AT169*HAVERQ!$AT$1)+(HAVERQ!AU169*HAVERQ!$AU$1) -> 65.155473
M46: 43647 | N46: =HAVERM!C481 -> 3.782 | O46: =HAVERM!B481 -> 3.9 | Q46: 43647 | R46: =MIN(HAVERM!C480:C482) -> 3.775 | S46: =V46-R46 -> 0.308 | T46: =HAVERM!B481 -> 3.9 | V46: =MAX(HAVERM!C480:C482) -> 4.083 | AB46: 40360 | AC46: =HAVERQ!P130 -> 1551 | AD46: =HAVERQ!O130 -> 1664 | AE46: =HAVERQ!N130 -> 1181 | AF46: =HAVERQ!M130 -> 290 | AG46: =HAVERQ!L130 -> 196 | AH46: =HAVERQ!E130-AC46-AD46-AE46-AF46-AG46 -> 696 | AJ46: 40360 | AK46: =100*(AC46/SUM($AC46:$AH46)) -> 27.805665 | AL46: =100*(AD46/SUM($AC46:$AH46)) -> 29.831481 | AM46: =100*(AE46/SUM($AC46:$AH46)) -> 21.172463 | AN46: =100*(AF46/SUM($AC46:$AH46)) -> 5.1989961 | AO46: =100*(AG46/SUM($AC46:$AH46)) -> 3.5138042 | AP46: =100*(AH46/SUM($AC46:$AH46)) -> 12.477591 | CL46: =100*((DataQ!F205/DataQ!F201)-1) -> 4.6629561 | CM46: =100*(DataQ!I205/DataQ!J205) -> 21.146079 | CY46: =(HAVERQ!AQ170-AVERAGE(HAVERQ!AQ$128:AQ$183))/STDEV(HAVERQ!AQ$128:AQ$183) -> -0.31750853 | CZ46: =(DL46-AVERAGE(DL$5:DL$59))/STDEV(DL$5:DL$59) -> -0.80990769 | DA46: =(DO46-AVERAGE(DO$5:DO$59))/STDEV(DO$5:DO$59) -> -0.67013968 | DB46: =(HAVERQ!AR170-AVERAGE(HAVERQ!AR$128:AR$183))/STDEV(HAVERQ!AR$128:AR$183) -> 3.6587225 | DC46: =(DM46-AVERAGE(DM$5:DM$59))/STDEV(DM$5:DM$59) -> -0.69228984 | DD46: =(DN46-AVERAGE(DN$29:DN$59))/STDEV(DN$29:DN$59) -> -1.2267539 | DE46: =(HAVERQ!AZ170-AVERAGE(HAVERQ!AZ$128:AZ$167,AZ$174:AZ$183))/STDEV(HAVERQ!AZ$128:AZ$167,AZ$174:AZ$183) -> -16.124786 | DF46: =(HAVERQ!AS170-AVERAGE(HAVERQ!AS$128:AS$183))/STDEV(HAVERQ!AS$128:AS$183) -> -1.6573915 | DG46: =(DP46-AVERAGE(DP$5:DP$59))/STDEV(DP$5:DP$59) -> -1.1311835 | DH46: =(HAVERQ!AX170-AVERAGE(HAVERQ!AX$128:AX$183))/STDEV(HAVERQ!AX$128:AX$183) -> 0.18361409 | DJ46: =(DR46-AVERAGE(DR$5:DR$59))/STDEV(DR$5:DR$59) -> -0.31735636 | DL46: =100*(HAVERQ!AV170/(HAVERQ!AW170*HAVERQ!AX170/100)) -> 1.0250407 | DM46: =HAVERQ!AO170/HAVERQ!AP170 -> 0.30041396 | DN46: =100*((AVERAGE(HAVERQ!BC167:BC170)/AVERAGE(HAVERQ!BC163:BC166))-1) -> -0.59946351 | DO46: =100*(HAVERQ!BE170+HAVERQ!BF170)/(HAVERQ!BB170+HAVERQ!BG170) -> 8.6537614 | DP46: =100*((AVERAGE(HAVERQ!BA167:BA170)/AVERAGE(HAVERQ!BA163:BA166))-1) -> 0.7971241 | DR46: =(HAVERQ!AT170*HAVERQ!$AT$1)+(HAVERQ!AU170*HAVERQ!$AU$1) -> 59.466419
M47: 43678 | N47: =HAVERM!C482 -> 3.775 | O47: =HAVERM!B482 -> 3.9 | Q47: 43678 | R47: =MIN(HAVERM!C481:C483) -> 3.775 | S47: =V47-R47 -> 0.301 | T47: =HAVERM!B482 -> 3.9 | V47: =MAX(HAVERM!C481:C483) -> 4.076 | AB47: 40452 | AC47: =HAVERQ!P131 -> 1545 | AD47: =HAVERQ!O131 -> 1658 | AE47: =HAVERQ!N131 -> 1175 | AF47: =HAVERQ!M131 -> 286 | AG47: =HAVERQ!L131 -> 196 | AH47: =HAVERQ!E131-AC47-AD47-AE47-AF47-AG47 -> 687 | AJ47: 40452 | AK47: =100*(AC47/SUM($AC47:$AH47)) -> 27.852893 | AL47: =100*(AD47/SUM($AC47:$AH47)) -> 29.890031 | AM47: =100*(AE47/SUM($AC47:$AH47)) -> 21.182621 | AN47: =100*(AF47/SUM($AC47:$AH47)) -> 5.1559401 | AO47: =100*(AG47/SUM($AC47:$AH47)) -> 3.5334415 | AP47: =100*(AH47/SUM($AC47:$AH47)) -> 12.385073 | CL47: =100*((DataQ!F206/DataQ!F202)-1) -> 7.3192565 | CM47: =100*(DataQ!I206/DataQ!J206) -> 22.653969 | CY47: =(HAVERQ!AQ171-AVERAGE(HAVERQ!AQ$128:AQ$183))/STDEV(HAVERQ!AQ$128:AQ$183) -> -0.13483239 | CZ47: =(DL47-AVERAGE(DL$5:DL$59))/STDEV(DL$5:DL$59) -> -0.65665724 | DA47: =(DO47-AVERAGE(DO$5:DO$59))/STDEV(DO$5:DO$59) -> -0.47057629 | DB47: =(HAVERQ!AR171-AVERAGE(HAVERQ!AR$128:AR$183))/STDEV(HAVERQ!AR$128:AR$183) -> 4.3596566 | DC47: =(DM47-AVERAGE(DM$5:DM$59))/STDEV(DM$5:DM$59) -> -0.57090819 | DD47: =(DN47-AVERAGE(DN$29:DN$59))/STDEV(DN$29:DN$59) -> -1.8735791 | DE47: =(HAVERQ!AZ171-AVERAGE(HAVERQ!AZ$128:AZ$167,AZ$174:AZ$183))/STDEV(HAVERQ!AZ$128:AZ$167,AZ$174:AZ$183) -> -7.5420654 | DF47: =(HAVERQ!AS171-AVERAGE(HAVERQ!AS$128:AS$183))/STDEV(HAVERQ!AS$128:AS$183) -> -1.8153129 | DG47: =(DP47-AVERAGE(DP$5:DP$59))/STDEV(DP$5:DP$59) -> -0.86193067 | DH47: =(HAVERQ!AX171-AVERAGE(HAVERQ!AX$128:AX$183))/STDEV(HAVERQ!AX$128:AX$183) -> -0.11880912 | DJ47: =(DR47-AVERAGE(DR$5:DR$59))/STDEV(DR$5:DR$59) -> -0.84466572 | DL47: =100*(HAVERQ!AV171/(HAVERQ!AW171*HAVERQ!AX171/100)) -> 1.1398111 | DM47: =HAVERQ!AO171/HAVERQ!AP171 -> 0.32905983 | DN47: =100*((AVERAGE(HAVERQ!BC168:BC171)/AVERAGE(HAVERQ!BC164:BC167))-1) -> -1.5455089 | DO47: =100*(HAVERQ!BE171+HAVERQ!BF171)/(HAVERQ!BB171+HAVERQ!BG171) -> 8.9547857 | DP47: =100*((AVERAGE(HAVERQ!BA168:BA171)/AVERAGE(HAVERQ!BA164:BA167))-1) -> 1.3200808 | DR47: =(HAVERQ!AT171*HAVERQ!$AT$1)+(HAVERQ!AU171*HAVERQ!$AU$1) -> 54.23321
M48: 43709 | N48: =HAVERM!C483 -> 4.076 | O48: =HAVERM!B483 -> 3.8 | Q48: 43709 | R48: =MIN(HAVERM!C482:C484) -> 3.549 | S48: =V48-R48 -> 0.527 | T48: =HAVERM!B483 -> 3.8 | V48: =MAX(HAVERM!C482:C484) -> 4.076 | AB48: 40544 | AC48: =HAVERQ!P132 -> 1539 | AD48: =HAVERQ!O132 -> 1659 | AE48: =HAVERQ!N132 -> 1164 | AF48: =HAVERQ!M132 -> 282 | AG48: =HAVERQ!L132 -> 194 | AH48: =HAVERQ!E132-AC48-AD48-AE48-AF48-AG48 -> 688 | AJ48: 40544 | AK48: =100*(AC48/SUM($AC48:$AH48)) -> 27.850163 | AL48: =100*(AD48/SUM($AC48:$AH48)) -> 30.021716 | AM48: =100*(AE48/SUM($AC48:$AH48)) -> 21.064061 | AN48: =100*(AF48/SUM($AC48:$AH48)) -> 5.1031488 | AO48: =100*(AG48/SUM($AC48:$AH48)) -> 3.5106768 | AP48: =100*(AH48/SUM($AC48:$AH48)) -> 12.450235 | CK48: 2023 | CL48: =100*((DataQ!F207/DataQ!F203)-1) -> 7.5866246 | CM48: =100*(DataQ!I207/DataQ!J207) -> 23.524103 | CX48: 2021 | CY48: =(HAVERQ!AQ172-AVERAGE(HAVERQ!AQ$128:AQ$183))/STDEV(HAVERQ!AQ$128:AQ$183) -> -0.37840058 | CZ48: =(DL48-AVERAGE(DL$5:DL$59))/STDEV(DL$5:DL$59) -> -0.618605 | DA48: =(DO48-AVERAGE(DO$5:DO$59))/STDEV(DO$5:DO$59) -> -0.60402137 | DB48: =(HAVERQ!AR172-AVERAGE(HAVERQ!AR$128:AR$183))/STDEV(HAVERQ!AR$128:AR$183) -> 0.47755956 | DC48: =(DM48-AVERAGE(DM$5:DM$59))/STDEV(DM$5:DM$59) -> -0.43417884 | DD48: =(DN48-AVERAGE(DN$29:DN$59))/STDEV(DN$29:DN$59) -> -2.4976598 | DE48: =(HAVERQ!AZ172-AVERAGE(HAVERQ!AZ$128:AZ$167,AZ$174:AZ$183))/STDEV(HAVERQ!AZ$128:AZ$167,AZ$174:AZ$183) -> -10.546017 | DF48: =(HAVERQ!AS172-AVERAGE(HAVERQ!AS$128:AS$183))/STDEV(HAVERQ!AS$128:AS$183) -> -1.8153129 | DG48: =(DP48-AVERAGE(DP$5:DP$59))/STDEV(DP$5:DP$59) -> -0.61878215 | DH48: =(HAVERQ!AX172-AVERAGE(HAVERQ!AX$128:AX$183))/STDEV(HAVERQ!AX$128:AX$183) -> -0.72365552 | DJ48: =(DR48-AVERAGE(DR$5:DR$59))/STDEV(DR$5:DR$59) -> 0.05436058 | DL48: =100*(HAVERQ!AV172/(HAVERQ!AW172*HAVERQ!AX172/100)) -> 1.1683087 | DM48: =HAVERQ!AO172/HAVERQ!AP172 -> 0.36132773 | DN48: =100*((AVERAGE(HAVERQ!BC169:BC172)/AVERAGE(HAVERQ!BC165:BC168))-1) -> -2.4582881 | DO48: =100*(HAVERQ!BE172+HAVERQ!BF172)/(HAVERQ!BB172+HAVERQ!BG172) -> 8.7534952 | DP48: =100*((AVERAGE(HAVERQ!BA169:BA172)/AVERAGE(HAVERQ!BA165:BA168))-1) -> 1.7923362 | DR48: =(HAVERQ!AT172*HAVERQ!$AT$1)+(HAVERQ!AU172*HAVERQ!$AU$1) -> 63.155473
M49: 43739 | N49: =HAVERM!C484 -> 3.549 | O49: =HAVERM!B484 -> 3.8 | Q49: 43739 | R49: =MIN(HAVERM!C483:C485) -> 3.549 | S49: =V49-R49 -> 0.527 | T49: =HAVERM!B484 -> 3.8 | V49: =MAX(HAVERM!C483:C485) -> 4.076 | AB49: 40634 | AC49: =HAVERQ!P133 -> 1531 | AD49: =HAVERQ!O133 -> 1662 | AE49: =HAVERQ!N133 -> 1120 | AF49: =HAVERQ!M133 -> 277 | AG49: =HAVERQ!L133 -> 193 | AH49: =HAVERQ!E133-AC49-AD49-AE49-AF49-AG49 -> 671 | AJ49: 40634 | AK49: =100*(AC49/SUM($AC49:$AH49)) -> 28.07114 | AL49: =100*(AD49/SUM($AC49:$AH49)) -> 30.473047 | AM49: =100*(AE49/SUM($AC49:$AH49)) -> 20.535387 | AN49: =100*(AF49/SUM($AC49:$AH49)) -> 5.0788412 | AO49: =100*(AG49/SUM($AC49:$AH49)) -> 3.5386872 | AP49: =100*(AH49/SUM($AC49:$AH49)) -> 12.302897 | CL49: =100*((DataQ!F208/DataQ!F204)-1) -> 8.0728132 | CM49: =100*(DataQ!I208/DataQ!J208) -> 21.631861 | CY49: =(HAVERQ!AQ173-AVERAGE(HAVERQ!AQ$128:AQ$183))/STDEV(HAVERQ!AQ$128:AQ$183) -> -0.50018467 | CZ49: =(DL49-AVERAGE(DL$5:DL$59))/STDEV(DL$5:DL$59) -> -0.42065202 | DA49: =(DO49-AVERAGE(DO$5:DO$59))/STDEV(DO$5:DO$59) -> -0.89392688 | DB49: =(HAVERQ!AR173-AVERAGE(HAVERQ!AR$128:AR$183))/STDEV(HAVERQ!AR$128:AR$183) -> -0.54688272 | DC49: =(DM49-AVERAGE(DM$5:DM$59))/STDEV(DM$5:DM$59) -> 0.40246423 | DD49: =(DN49-AVERAGE(DN$29:DN$59))/STDEV(DN$29:DN$59) -> -2.1946618 | DE49: =(HAVERQ!AZ173-AVERAGE(HAVERQ!AZ$128:AZ$167,AZ$174:AZ$183))/STDEV(HAVERQ!AZ$128:AZ$167,AZ$174:AZ$183) -> -4.1089773 | DF49: =(HAVERQ!AS173-AVERAGE(HAVERQ!AS$128:AS$183))/STDEV(HAVERQ!AS$128:AS$183) -> -0.94674513 | DG49: =(DP49-AVERAGE(DP$5:DP$59))/STDEV(DP$5:DP$59) -> 0.98712356 | DH49: =(HAVERQ!AX173-AVERAGE(HAVERQ!AX$128:AX$183))/STDEV(HAVERQ!AX$128:AX$183) -> -0.72365552 | DJ49: =(DR49-AVERAGE(DR$5:DR$59))/STDEV(DR$5:DR$59) -> 0.65893338 | DL49: =100*(HAVERQ!AV173/(HAVERQ!AW173*HAVERQ!AX173/100)) -> 1.3165573 | DM49: =HAVERQ!AO173/HAVERQ!AP173 -> 0.55877414 | DN49: =100*((AVERAGE(HAVERQ!BC170:BC173)/AVERAGE(HAVERQ!BC166:BC169))-1) -> -2.0151238 | DO49: =100*(HAVERQ!BE173+HAVERQ!BF173)/(HAVERQ!BB173+HAVERQ!BG173) -> 8.3161976 | DP49: =100*((AVERAGE(HAVERQ!BA170:BA173)/AVERAGE(HAVERQ!BA166:BA169))-1) -> 4.9114081 | DR49: =(HAVERQ!AT173*HAVERQ!$AT$1)+(HAVERQ!AU173*HAVERQ!$AU$1) -> 69.155473
M50: 43770 | N50: =HAVERM!C485 -> 3.869 | O50: =HAVERM!B485 -> 3.7 | Q50: 43770 | R50: =MIN(HAVERM!C484:C486) -> 3.549 | S50: =V50-R50 -> 0.32 | T50: =HAVERM!B485 -> 3.7 | V50: =MAX(HAVERM!C484:C486) -> 3.869 | AB50: 40725 | AC50: =HAVERQ!P134 -> 1523 | AD50: =HAVERQ!O134 -> 1668 | AE50: =HAVERQ!N134 -> 1109 | AF50: =HAVERQ!M134 -> 273 | AG50: =HAVERQ!L134 -> 191 | AH50: =HAVERQ!E134-AC50-AD50-AE50-AF50-AG50 -> 656 | AJ50: 40725 | AK50: =100*(AC50/SUM($AC50:$AH50)) -> 28.099631 | AL50: =100*(AD50/SUM($AC50:$AH50)) -> 30.774908 | AM50: =100*(AE50/SUM($AC50:$AH50)) -> 20.461255 | AN50: =100*(AF50/SUM($AC50:$AH50)) -> 5.0369004 | AO50: =100*(AG50/SUM($AC50:$AH50)) -> 3.5239852 | AP50: =100*(AH50/SUM($AC50:$AH50)) -> 12.103321 | CL50: =100*((DataQ!F209/DataQ!F205)-1) -> 7.2288043 | CM50: =100*(DataQ!I209/DataQ!J209) -> 21.010605 | CY50: =(HAVERQ!AQ174-AVERAGE(HAVERQ!AQ$128:AQ$183))/STDEV(HAVERQ!AQ$128:AQ$183) -> -0.68286081 | CZ50: =(DL50-AVERAGE(DL$5:DL$59))/STDEV(DL$5:DL$59) -> -0.33988358 | DA50: =(DO50-AVERAGE(DO$5:DO$59))/STDEV(DO$5:DO$59) -> -1.0201481 | DB50: =(HAVERQ!AR174-AVERAGE(HAVERQ!AR$128:AR$183))/STDEV(HAVERQ!AR$128:AR$183) -> -0.43904669 | DC50: =(DM50-AVERAGE(DM$5:DM$59))/STDEV(DM$5:DM$59) -> 1.2626551 | DD50: =(DN50-AVERAGE(DN$29:DN$59))/STDEV(DN$29:DN$59) -> -1.4000155 | DE50: =(HAVERQ!AZ174-AVERAGE(HAVERQ!AZ$128:AZ$167,AZ$174:AZ$183))/STDEV(HAVERQ!AZ$128:AZ$167,AZ$174:AZ$183) -> -1.5341612 | DF50: =(HAVERQ!AS174-AVERAGE(HAVERQ!AS$128:AS$183))/STDEV(HAVERQ!AS$128:AS$183) -> 0.97463204 | DG50: =(DP50-AVERAGE(DP$5:DP$59))/STDEV(DP$5:DP$59) -> 1.73969 | DH50: =(HAVERQ!AX174-AVERAGE(HAVERQ!AX$128:AX$183))/STDEV(HAVERQ!AX$128:AX$183) -> -0.11880912 | DJ50: =(DR50-AVERAGE(DR$5:DR$59))/STDEV(DR$5:DR$59) -> 1.2870049 | DL50: =100*(HAVERQ!AV174/(HAVERQ!AW174*HAVERQ!AX174/100)) -> 1.3770454 | DM50: =HAVERQ!AO174/HAVERQ!AP174 -> 0.76177778 | DN50: =100*((AVERAGE(HAVERQ!BC171:BC174)/AVERAGE(HAVERQ!BC167:BC170))-1) -> -0.85287549 | DO50: =100*(HAVERQ!BE174+HAVERQ!BF174)/(HAVERQ!BB174+HAVERQ!BG174) -> 8.1258038 | DP50: =100*((AVERAGE(HAVERQ!BA171:BA174)/AVERAGE(HAVERQ!BA167:BA170))-1) -> 6.3730811 | DR50: =(HAVERQ!AT174*HAVERQ!$AT$1)+(HAVERQ!AU174*HAVERQ!$AU$1) -> 75.388683
M51: 43800 | N51: =HAVERM!C486 -> 3.804 | O51: =HAVERM!B486 -> 3.9 | Q51: 43800 | R51: =MIN(HAVERM!C485:C487) -> 3.804 | S51: =V51-R51 -> 0.191 | T51: =HAVERM!B486 -> 3.9 | V51: =MAX(HAVERM!C485:C487) -> 3.995 | AB51: 40817 | AC51: =HAVERQ!P135 -> 1515 | AD51: =HAVERQ!O135 -> 1664 | AE51: =HAVERQ!N135 -> 1093 | AF51: =HAVERQ!M135 -> 270 | AG51: =HAVERQ!L135 -> 190 | AH51: =HAVERQ!E135-AC51-AD51-AE51-AF51-AG51 -> 656 | AJ51: 40817 | AK51: =100*(AC51/SUM($AC51:$AH51)) -> 28.11804 | AL51: =100*(AD51/SUM($AC51:$AH51)) -> 30.883445 | AM51: =100*(AE51/SUM($AC51:$AH51)) -> 20.28582 | AN51: =100*(AF51/SUM($AC51:$AH51)) -> 5.0111359 | AO51: =100*(AG51/SUM($AC51:$AH51)) -> 3.5263549 | AP51: =100*(AH51/SUM($AC51:$AH51)) -> 12.175204 | CL51: =100*((DataQ!F210/DataQ!F206)-1) -> 6.7720967 | CM51: =100*(DataQ!I210/DataQ!J210) -> 20.546876 | CY51: =(HAVERQ!AQ175-AVERAGE(HAVERQ!AQ$128:AQ$183))/STDEV(HAVERQ!AQ$128:AQ$183) -> -0.8046449 | CZ51: =(DL51-AVERAGE(DL$5:DL$59))/STDEV(DL$5:DL$59) -> -0.48286394 | DA51: =(DO51-AVERAGE(DO$5:DO$59))/STDEV(DO$5:DO$59) -> -1.2563269 | DB51: =(HAVERQ!AR175-AVERAGE(HAVERQ!AR$128:AR$183))/STDEV(HAVERQ!AR$128:AR$183) -> -1.0860629 | DC51: =(DM51-AVERAGE(DM$5:DM$59))/STDEV(DM$5:DM$59) -> 1.6715447 | DD51: =(DN51-AVERAGE(DN$29:DN$59))/STDEV(DN$29:DN$59) -> -0.26708978 | DE51: =(HAVERQ!AZ175-AVERAGE(HAVERQ!AZ$128:AZ$167,AZ$174:AZ$183))/STDEV(HAVERQ!AZ$128:AZ$167,AZ$174:AZ$183) -> -1.1050252 | DF51: =(HAVERQ!AS175-AVERAGE(HAVERQ!AS$128:AS$183))/STDEV(HAVERQ!AS$128:AS$183) -> 1.5799975 | DG51: =(DP51-AVERAGE(DP$5:DP$59))/STDEV(DP$5:DP$59) -> 1.788779 | DH51: =(HAVERQ!AX175-AVERAGE(HAVERQ!AX$128:AX$183))/STDEV(HAVERQ!AX$128:AX$183) -> -0.72365552 | DJ51: =(DR51-AVERAGE(DR$5:DR$59))/STDEV(DR$5:DR$59) -> 1.2948378 | DL51: =100*(HAVERQ!AV175/(HAVERQ!AW175*HAVERQ!AX175/100)) -> 1.2699663 | DM51: =HAVERQ!AO175/HAVERQ!AP175 -> 0.85827506 | DN51: =100*((AVERAGE(HAVERQ!BC172:BC175)/AVERAGE(HAVERQ!BC168:BC171))-1) -> 0.80413954 | DO51: =100*(HAVERQ!BE175+HAVERQ!BF175)/(HAVERQ!BB175+HAVERQ!BG175) -> 7.7695483 | DP51: =100*((AVERAGE(HAVERQ!BA172:BA175)/AVERAGE(HAVERQ!BA168:BA171))-1) -> 6.4684243 | DR51: =(HAVERQ!AT175*HAVERQ!$AT$1)+(HAVERQ!AU175*HAVERQ!$AU$1) -> 75.466419
M52: 43831 | N52: =HAVERM!C487 -> 3.995 | O52: =HAVERM!B487 -> 3.9 | Q52: 43831 | R52: =MIN(HAVERM!C486:C488) -> 3.804 | S52: =V52-R52 -> 0.251 | T52: =HAVERM!B487 -> 3.9 | V52: =MAX(HAVERM!C486:C488) -> 4.055 | AB52: 40909 | AC52: =HAVERQ!P136 -> 1507 | AD52: =HAVERQ!O136 -> 1683 | AE52: =HAVERQ!N136 -> 1080 | AF52: =HAVERQ!M136 -> 268 | AG52: =HAVERQ!L136 -> 187 | AH52: =HAVERQ!E136-AC52-AD52-AE52-AF52-AG52 -> 628 | AJ52: 40909 | AK52: =100*(AC52/SUM($AC52:$AH52)) -> 28.152438 | AL52: =100*(AD52/SUM($AC52:$AH52)) -> 31.440314 | AM52: =100*(AE52/SUM($AC52:$AH52)) -> 20.175602 | AN52: =100*(AF52/SUM($AC52:$AH52)) -> 5.0065384 | AO52: =100*(AG52/SUM($AC52:$AH52)) -> 3.4933682 | AP52: =100*(AH52/SUM($AC52:$AH52)) -> 11.731739 | CK52: 2024 | CL52: =100*((DataQ!F211/DataQ!F207)-1) -> 5.5341423 | CM52: =100*(DataQ!I211/DataQ!J211) -> 20.505521 | CX52: 2022 | CY52: =(HAVERQ!AQ176-AVERAGE(HAVERQ!AQ$128:AQ$183))/STDEV(HAVERQ!AQ$128:AQ$183) -> -1.0482131 | CZ52: =(DL52-AVERAGE(DL$5:DL$59))/STDEV(DL$5:DL$59) -> -0.70588346 | DA52: =(DO52-AVERAGE(DO$5:DO$59))/STDEV(DO$5:DO$59) -> -1.1403604 | DB52: =(HAVERQ!AR176-AVERAGE(HAVERQ!AR$128:AR$183))/STDEV(HAVERQ!AR$128:AR$183) -> -1.1399809 | DC52: =(DM52-AVERAGE(DM$5:DM$59))/STDEV(DM$5:DM$59) -> 2.1691563 | DD52: =(DN52-AVERAGE(DN$29:DN$59))/STDEV(DN$29:DN$59) -> 1.0031502 | DE52: =(HAVERQ!AZ176-AVERAGE(HAVERQ!AZ$128:AZ$167,AZ$174:AZ$183))/STDEV(HAVERQ!AZ$128:AZ$167,AZ$174:AZ$183) -> -0.67588921 | DF52: =(HAVERQ!AS176-AVERAGE(HAVERQ!AS$128:AS$183))/STDEV(HAVERQ!AS$128:AS$183) -> 1.5799975 | DG52: =(DP52-AVERAGE(DP$5:DP$59))/STDEV(DP$5:DP$59) -> 2.3269365 | DH52: =(HAVERQ!AX176-AVERAGE(HAVERQ!AX$128:AX$183))/STDEV(HAVERQ!AX$128:AX$183) -> -1.6309251 | DJ52: =(DR52-AVERAGE(DR$5:DR$59))/STDEV(DR$5:DR$59) -> 1.387767 | DL52: =100*(HAVERQ!AV176/(HAVERQ!AW176*HAVERQ!AX176/100)) -> 1.1029452 | DM52: =HAVERQ!AO176/HAVERQ!AP176 -> 0.97571059 | DN52: =100*((AVERAGE(HAVERQ!BC173:BC176)/AVERAGE(HAVERQ!BC169:BC172))-1) -> 2.6619902 | DO52: =100*(HAVERQ!BE176+HAVERQ!BF176)/(HAVERQ!BB176+HAVERQ!BG176) -> 7.9444738 | DP52: =100*((AVERAGE(HAVERQ!BA173:BA176)/AVERAGE(HAVERQ!BA169:BA172))-1) -> 7.5136612 | DR52: =(HAVERQ!AT176*HAVERQ!$AT$1)+(HAVERQ!AU176*HAVERQ!$AU$1) -> 76.388683
M53: 43862 | N53: =HAVERM!C488 -> 4.055 | O53: =HAVERM!B488 -> 4.1 | Q53: 43862 | R53: =MIN(HAVERM!C487:C489) -> 3.995 | S53: =V53-R53 -> 0.258 | T53: =HAVERM!B488 -> 4.1 | V53: =MAX(HAVERM!C487:C489) -> 4.253 | AB53: 41000 | AC53: =HAVERQ!P137 -> 1504 | AD53: =HAVERQ!O137 -> 1663 | AE53: =HAVERQ!N137 -> 1078 | AF53: =HAVERQ!M137 -> 266 | AG53: =HAVERQ!L137 -> 186 | AH53: =HAVERQ!E137-AC53-AD53-AE53-AF53-AG53 -> 621 | AJ53: 41000 | AK53: =100*(AC53/SUM($AC53:$AH53)) -> 28.281309 | AL53: =100*(AD53/SUM($AC53:$AH53)) -> 31.271155 | AM53: =100*(AE53/SUM($AC53:$AH53)) -> 20.270778 | AN53: =100*(AF53/SUM($AC53:$AH53)) -> 5.0018804 | AO53: =100*(AG53/SUM($AC53:$AH53)) -> 3.4975555 | AP53: =100*(AH53/SUM($AC53:$AH53)) -> 11.677322 | CL53: =100*((DataQ!F212/DataQ!F208)-1) -> 4.6888589 | CM53: =100*(DataQ!I212/DataQ!J212) -> 20.250685 | CY53: =(HAVERQ!AQ177-AVERAGE(HAVERQ!AQ$128:AQ$183))/STDEV(HAVERQ!AQ$128:AQ$183) -> -1.0482131 | CZ53: =(DL53-AVERAGE(DL$5:DL$59))/STDEV(DL$5:DL$59) -> -0.77623103 | DA53: =(DO53-AVERAGE(DO$5:DO$59))/STDEV(DO$5:DO$59) -> -1.2431622 | DB53: =(HAVERQ!AR177-AVERAGE(HAVERQ!AR$128:AR$183))/STDEV(HAVERQ!AR$128:AR$183) -> -1.463489 | DC53: =(DM53-AVERAGE(DM$5:DM$59))/STDEV(DM$5:DM$59) -> 2.3516369 | DD53: =(DN53-AVERAGE(DN$29:DN$59))/STDEV(DN$29:DN$59) -> 1.5968062 | DE53: =(HAVERQ!AZ177-AVERAGE(HAVERQ!AZ$128:AZ$167,AZ$174:AZ$183))/STDEV(HAVERQ!AZ$128:AZ$167,AZ$174:AZ$183) -> -1.1050252 | DF53: =(HAVERQ!AS177-AVERAGE(HAVERQ!AS$128:AS$183))/STDEV(HAVERQ!AS$128:AS$183) -> 1.5799975 | DG53: =(DP53-AVERAGE(DP$5:DP$59))/STDEV(DP$5:DP$59) -> 1.7764326 | DH53: =(HAVERQ!AX177-AVERAGE(HAVERQ!AX$128:AX$183))/STDEV(HAVERQ!AX$128:AX$183) -> -1.0260787 | DJ53: =(DR53-AVERAGE(DR$5:DR$59))/STDEV(DR$5:DR$59) -> 1.0082172 | DL53: =100*(HAVERQ!AV177/(HAVERQ!AW177*HAVERQ!AX177/100)) -> 1.0502614 | DM53: =HAVERQ!AO177/HAVERQ!AP177 -> 1.0187757 | DN53: =100*((AVERAGE(HAVERQ!BC174:BC177)/AVERAGE(HAVERQ!BC170:BC173))-1) -> 3.5302704 | DO53: =100*(HAVERQ!BE177+HAVERQ!BF177)/(HAVERQ!BB177+HAVERQ!BG177) -> 7.7894062 | DP53: =100*((AVERAGE(HAVERQ!BA174:BA177)/AVERAGE(HAVERQ!BA170:BA173))-1) -> 6.4444444 | DR53: =(HAVERQ!AT177*HAVERQ!$AT$1)+(HAVERQ!AU177*HAVERQ!$AU$1) -> 72.621892
M54: 43891 | N54: =HAVERM!C489 -> 4.253 | O54: =HAVERM!B489 -> 4.1 | Q54: 43891 | R54: =MIN(HAVERM!C488:C490) -> 3.967 | S54: =V54-R54 -> 0.286 | T54: =HAVERM!B489 -> 4.1 | V54: =MAX(HAVERM!C488:C490) -> 4.253 | AB54: 41091 | AC54: =HAVERQ!P138 -> 1502 | AD54: =HAVERQ!O138 -> 1660 | AE54: =HAVERQ!N138 -> 1070 | AF54: =HAVERQ!M138 -> 264 | AG54: =HAVERQ!L138 -> 183 | AH54: =HAVERQ!E138-AC54-AD54-AE54-AF54-AG54 -> 620 | AJ54: 41091 | AK54: =100*(AC54/SUM($AC54:$AH54)) -> 28.344971 | AL54: =100*(AD54/SUM($AC54:$AH54)) -> 31.326665 | AM54: =100*(AE54/SUM($AC54:$AH54)) -> 20.192489 | AN54: =100*(AF54/SUM($AC54:$AH54)) -> 4.9820721 | AO54: =100*(AG54/SUM($AC54:$AH54)) -> 3.4534818 | AP54: =100*(AH54/SUM($AC54:$AH54)) -> 11.700321 | CL54: =100*((DataQ!F213/DataQ!F209)-1) -> 4.4570365 | CM54: =100*(DataQ!I213/DataQ!J213) -> 20.136897 | CY54: =(HAVERQ!AQ178-AVERAGE(HAVERQ!AQ$128:AQ$183))/STDEV(HAVERQ!AQ$128:AQ$183) -> -1.1091051 | CZ54: =(DL54-AVERAGE(DL$5:DL$59))/STDEV(DL$5:DL$59) -> -0.91393292 | DA54: =(DO54-AVERAGE(DO$5:DO$59))/STDEV(DO$5:DO$59) -> -1.3334924 | DB54: =(HAVERQ!AR178-AVERAGE(HAVERQ!AR$128:AR$183))/STDEV(HAVERQ!AR$128:AR$183) -> -1.0321449 | DC54: =(DM54-AVERAGE(DM$5:DM$59))/STDEV(DM$5:DM$59) -> 2.191399 | DD54: =(DN54-AVERAGE(DN$29:DN$59))/STDEV(DN$29:DN$59) -> 1.6452552 | DE54: =(HAVERQ!AZ178-AVERAGE(HAVERQ!AZ$128:AZ$167,AZ$174:AZ$183))/STDEV(HAVERQ!AZ$128:AZ$167,AZ$174:AZ$183) -> -0.67588921 | DF54: =(HAVERQ!AS178-AVERAGE(HAVERQ!AS$128:AS$183))/STDEV(HAVERQ!AS$128:AS$183) -> 1.5799975 | DG54: =(DP54-AVERAGE(DP$5:DP$59))/STDEV(DP$5:DP$59) -> 1.7607548 | DH54: =(HAVERQ!AX178-AVERAGE(HAVERQ!AX$128:AX$183))/STDEV(HAVERQ!AX$128:AX$183) -> -1.9333483 | DJ54: =(DR54-AVERAGE(DR$5:DR$59))/STDEV(DR$5:DR$59) -> 1.1011464 | DL54: =100*(HAVERQ!AV178/(HAVERQ!AW178*HAVERQ!AX178/100)) -> 0.94713535 | DM54: =HAVERQ!AO178/HAVERQ!AP178 -> 0.98095983 | DN54: =100*((AVERAGE(HAVERQ!BC175:BC178)/AVERAGE(HAVERQ!BC171:BC174))-1) -> 3.6011318 | DO54: =100*(HAVERQ!BE178+HAVERQ!BF178)/(HAVERQ!BB178+HAVERQ!BG178) -> 7.6531508 | DP54: =100*((AVERAGE(HAVERQ!BA175:BA178)/AVERAGE(HAVERQ!BA171:BA174))-1) -> 6.4139942 | DR54: =(HAVERQ!AT178*HAVERQ!$AT$1)+(HAVERQ!AU178*HAVERQ!$AU$1) -> 73.544156
M55: 43922 | N55: =HAVERM!C490 -> 3.967 | O55: =HAVERM!B490 -> 4.1 | Q55: 43922 | R55: =MIN(HAVERM!C489:C491) -> 3.967 | S55: =V55-R55 -> 0.286 | T55: =HAVERM!B490 -> 4.1 | V55: =MAX(HAVERM!C489:C491) -> 4.253 | AB55: 41183 | AC55: =HAVERQ!P139 -> 1505 | AD55: =HAVERQ!O139 -> 1659 | AE55: =HAVERQ!N139 -> 1069 | AF55: =HAVERQ!M139 -> 263 | AG55: =HAVERQ!L139 -> 179 | AH55: =HAVERQ!E139-AC55-AD55-AE55-AF55-AG55 -> 609 | AJ55: 41183 | AK55: =100*(AC55/SUM($AC55:$AH55)) -> 28.48221 | AL55: =100*(AD55/SUM($AC55:$AH55)) -> 31.396669 | AM55: =100*(AE55/SUM($AC55:$AH55)) -> 20.230886 | AN55: =100*(AF55/SUM($AC55:$AH55)) -> 4.9772899 | AO55: =100*(AG55/SUM($AC55:$AH55)) -> 3.3875852 | AP55: =100*(AH55/SUM($AC55:$AH55)) -> 11.52536 | CL55: =100*((DataQ!F214/DataQ!F210)-1) -> 4.7574472 | CM55: =100*(DataQ!I214/DataQ!J214) -> 20.16358 | CY55: =(HAVERQ!AQ179-AVERAGE(HAVERQ!AQ$128:AQ$183))/STDEV(HAVERQ!AQ$128:AQ$183) -> -0.98732104 | CZ55: =(DL55-AVERAGE(DL$5:DL$59))/STDEV(DL$5:DL$59) -> -1.0747764 | DA55: =(DO55-AVERAGE(DO$5:DO$59))/STDEV(DO$5:DO$59) -> -1.4045869 | DB55: =(HAVERQ!AR179-AVERAGE(HAVERQ!AR$128:AR$183))/STDEV(HAVERQ!AR$128:AR$183) -> -0.65471875 | DC55: =(DM55-AVERAGE(DM$5:DM$59))/STDEV(DM$5:DM$59) -> 1.5893124 | DD55: =(DN55-AVERAGE(DN$29:DN$59))/STDEV(DN$29:DN$59) -> 1.4264015 | DE55: =(HAVERQ!AZ179-AVERAGE(HAVERQ!AZ$128:AZ$167,AZ$174:AZ$183))/STDEV(HAVERQ!AZ$128:AZ$167,AZ$174:AZ$183) -> -1.1050252 | DF55: =(HAVERQ!AS179-AVERAGE(HAVERQ!AS$128:AS$183))/STDEV(HAVERQ!AS$128:AS$183) -> 1.0535927 | DG55: =(DP55-AVERAGE(DP$5:DP$59))/STDEV(DP$5:DP$59) -> 1.9644774 | DH55: =(HAVERQ!AX179-AVERAGE(HAVERQ!AX$128:AX$183))/STDEV(HAVERQ!AX$128:AX$183) -> -1.0260787 | DJ55: =(DR55-AVERAGE(DR$5:DR$59))/STDEV(DR$5:DR$59) -> 1.6978863 | DL55: =100*(HAVERQ!AV179/(HAVERQ!AW179*HAVERQ!AX179/100)) -> 0.82667843 | DM55: =HAVERQ!AO179/HAVERQ!AP179 -> 0.83886839 | DN55: =100*((AVERAGE(HAVERQ!BC176:BC179)/AVERAGE(HAVERQ!BC172:BC175))-1) -> 3.2810368 | DO55: =100*(HAVERQ!BE179+HAVERQ!BF179)/(HAVERQ!BB179+HAVERQ!BG179) -> 7.5459108 | DP55: =100*((AVERAGE(HAVERQ!BA176:BA179)/AVERAGE(HAVERQ!BA172:BA175))-1) -> 6.8096746 | DR55: =(HAVERQ!AT179*HAVERQ!$AT$1)+(HAVERQ!AU179*HAVERQ!$AU$1) -> 79.466419
M56: 43952 | N56: =HAVERM!C491 -> 4.159 | O56: =HAVERM!B491 -> 4.1 | Q56: 43952 | R56: =MIN(HAVERM!C490:C492) -> 3.967 | S56: =V56-R56 -> 0.192 | T56: =HAVERM!B491 -> 4.1 | V56: =MAX(HAVERM!C490:C492) -> 4.159 | AB56: 41275 | AC56: =HAVERQ!P140 -> 1508 | AD56: =HAVERQ!O140 -> 1659 | AE56: =HAVERQ!N140 -> 1072 | AF56: =HAVERQ!M140 -> 261 | AG56: =HAVERQ!L140 -> 178 | AH56: =HAVERQ!E140-AC56-AD56-AE56-AF56-AG56 -> 602 | AJ56: 41275 | AK56: =100*(AC56/SUM($AC56:$AH56)) -> 28.560606 | AL56: =100*(AD56/SUM($AC56:$AH56)) -> 31.420455 | AM56: =100*(AE56/SUM($AC56:$AH56)) -> 20.30303 | AN56: =100*(AF56/SUM($AC56:$AH56)) -> 4.9431818 | AO56: =100*(AG56/SUM($AC56:$AH56)) -> 3.3712121 | AP56: =100*(AH56/SUM($AC56:$AH56)) -> 11.401515 | CK56: 2025 | CL56: =100*((DataQ!F215/DataQ!F211)-1) -> 4.2462663 | CM56: =100*(DataQ!I215/DataQ!J215) -> 20.345112 | CX56: 2023 | CY56: =(HAVERQ!AQ180-AVERAGE(HAVERQ!AQ$128:AQ$183))/STDEV(HAVERQ!AQ$128:AQ$183) -> -0.926429 | CZ56: =(DL56-AVERAGE(DL$5:DL$59))/STDEV(DL$5:DL$59) -> -0.91986142 | DA56: =(DO56-AVERAGE(DO$5:DO$59))/STDEV(DO$5:DO$59) -> -1.268742 | DB56: =(HAVERQ!AR180-AVERAGE(HAVERQ!AR$128:AR$183))/STDEV(HAVERQ!AR$128:AR$183) -> -0.97822684 | DC56: =(DM56-AVERAGE(DM$5:DM$59))/STDEV(DM$5:DM$59) -> 1.3773296 | DD56: =(DN56-AVERAGE(DN$29:DN$59))/STDEV(DN$29:DN$59) -> 1.0309956 | DE56: =(HAVERQ!AZ180-AVERAGE(HAVERQ!AZ$128:AZ$167,AZ$174:AZ$183))/STDEV(HAVERQ!AZ$128:AZ$167,AZ$174:AZ$183) -> -1.1050252 | DF56: =(HAVERQ!AS180-AVERAGE(HAVERQ!AS$128:AS$183))/STDEV(HAVERQ!AS$128:AS$183) -> 0.52718804 | DG56: =(DP56-AVERAGE(DP$5:DP$59))/STDEV(DP$5:DP$59) -> 1.7294746 | DH56: =(HAVERQ!AX180-AVERAGE(HAVERQ!AX$128:AX$183))/STDEV(HAVERQ!AX$128:AX$183) -> -0.42123232 | DJ56: =(DR56-AVERAGE(DR$5:DR$59))/STDEV(DR$5:DR$59) -> 1.7751497 | DL56: =100*(HAVERQ!AV180/(HAVERQ!AW180*HAVERQ!AX180/100)) -> 0.94269545 | DM56: =HAVERQ!AO180/HAVERQ!AP180 -> 0.78884079 | DN56: =100*((AVERAGE(HAVERQ!BC177:BC180)/AVERAGE(HAVERQ!BC173:BC176))-1) -> 2.7027168 | DO56: =100*(HAVERQ!BE180+HAVERQ!BF180)/(HAVERQ!BB180+HAVERQ!BG180) -> 7.7508212 | DP56: =100*((AVERAGE(HAVERQ!BA177:BA180)/AVERAGE(HAVERQ!BA173:BA176))-1) -> 6.3532402 | DR56: =(HAVERQ!AT180*HAVERQ!$AT$1)+(HAVERQ!AU180*HAVERQ!$AU$1) -> 80.23321
M57: 43983 | N57: =HAVERM!C492 -> 4.115 | O57: =HAVERM!B492 -> 4.4 | Q57: 43983 | R57: =MIN(HAVERM!C491:C493) -> 4.115 | S57: =V57-R57 -> 0.694 | T57: =HAVERM!B492 -> 4.4 | V57: =MAX(HAVERM!C491:C493) -> 4.809 | AB57: 41365 | AC57: =HAVERQ!P141 -> 1505 | AD57: =HAVERQ!O141 -> 1683 | AE57: =HAVERQ!N141 -> 1072 | AF57: =HAVERQ!M141 -> 261 | AG57: =HAVERQ!L141 -> 175 | AH57: =HAVERQ!E141-AC57-AD57-AE57-AF57-AG57 -> 589 | AJ57: 41365 | AK57: =100*(AC57/SUM($AC57:$AH57)) -> 28.476821 | AL57: =100*(AD57/SUM($AC57:$AH57)) -> 31.844844 | AM57: =100*(AE57/SUM($AC57:$AH57)) -> 20.283822 | AN57: =100*(AF57/SUM($AC57:$AH57)) -> 4.9385052 | AO57: =100*(AG57/SUM($AC57:$AH57)) -> 3.3112583 | AP57: =100*(AH57/SUM($AC57:$AH57)) -> 11.144749 | CL57: =100*((DataQ!F216/DataQ!F212)-1) -> 5.5232756 | CM57: =100*(DataQ!I216/DataQ!J216) -> 19.868672 | CY57: =(HAVERQ!AQ181-AVERAGE(HAVERQ!AQ$128:AQ$183))/STDEV(HAVERQ!AQ$128:AQ$183) -> -0.8046449 | CZ57: =(DL57-AVERAGE(DL$5:DL$59))/STDEV(DL$5:DL$59) -> -1.0290576 | DA57: =(DO57-AVERAGE(DO$5:DO$59))/STDEV(DO$5:DO$59) -> -1.4825182 | DB57: =(HAVERQ!AR181-AVERAGE(HAVERQ!AR$128:AR$183))/STDEV(HAVERQ!AR$128:AR$183) -> -0.43904669 | DC57: =(DM57-AVERAGE(DM$5:DM$59))/STDEV(DM$5:DM$59) -> 1.0892806 | DD57: =(DN57-AVERAGE(DN$29:DN$59))/STDEV(DN$29:DN$59) -> 0.74362518 | DE57: =(HAVERQ!AZ181-AVERAGE(HAVERQ!AZ$128:AZ$167,AZ$174:AZ$183))/STDEV(HAVERQ!AZ$128:AZ$167,AZ$174:AZ$183) -> -1.1050252 | DF57: =(HAVERQ!AS181-AVERAGE(HAVERQ!AS$128:AS$183))/STDEV(HAVERQ!AS$128:AS$183) -> 0.52718804 | DG57: =(DP57-AVERAGE(DP$5:DP$59))/STDEV(DP$5:DP$59) -> 1.9696718 | DH57: =(HAVERQ!AX181-AVERAGE(HAVERQ!AX$128:AX$183))/STDEV(HAVERQ!AX$128:AX$183) -> -0.11880912 | DJ57: =(DR57-AVERAGE(DR$5:DR$59))/STDEV(DR$5:DR$59) -> 1.5041949 | DL57: =100*(HAVERQ!AV181/(HAVERQ!AW181*HAVERQ!AX181/100)) -> 0.86091756 | DM57: =HAVERQ!AO181/HAVERQ!AP181 -> 0.72086168 | DN57: =100*((AVERAGE(HAVERQ!BC178:BC181)/AVERAGE(HAVERQ!BC174:BC177))-1) -> 2.2824094 | DO57: =100*(HAVERQ!BE181+HAVERQ!BF181)/(HAVERQ!BB181+HAVERQ!BG181) -> 7.4283581 | DP57: =100*((AVERAGE(HAVERQ!BA178:BA181)/AVERAGE(HAVERQ!BA174:BA177))-1) -> 6.8197634 | DR57: =(HAVERQ!AT181*HAVERQ!$AT$1)+(HAVERQ!AU181*HAVERQ!$AU$1) -> 77.544156
M58: 44013 | N58: =HAVERM!C493 -> 4.809 | O58: =HAVERM!B493 -> 4.6 | Q58: 44013 | R58: =MIN(HAVERM!C492:C494) -> 4.115 | S58: =V58-R58 -> 0.849 | T58: =HAVERM!B493 -> 4.6 | V58: =MAX(HAVERM!C492:C494) -> 4.964 | AB58: 41456 | AC58: =HAVERQ!P142 -> 1512 | AD58: =HAVERQ!O142 -> 1693 | AE58: =HAVERQ!N142 -> 1073 | AF58: =HAVERQ!M142 -> 259 | AG58: =HAVERQ!L142 -> 174 | AH58: =HAVERQ!E142-AC58-AD58-AE58-AF58-AG58 -> 589 | AJ58: 41456 | AK58: =100*(AC58/SUM($AC58:$AH58)) -> 28.528302 | AL58: =100*(AD58/SUM($AC58:$AH58)) -> 31.943396 | AM58: =100*(AE58/SUM($AC58:$AH58)) -> 20.245283 | AN58: =100*(AF58/SUM($AC58:$AH58)) -> 4.8867925 | AO58: =100*(AG58/SUM($AC58:$AH58)) -> 3.2830189 | AP58: =100*(AH58/SUM($AC58:$AH58)) -> 11.113208 | CL58: =100*((DataQ!F217/DataQ!F213)-1) -> 5.5411766 | CM58: =100*(DataQ!I217/DataQ!J217) -> 20.157701 | CY58: =(HAVERQ!AQ182-AVERAGE(HAVERQ!AQ$128:AQ$183))/STDEV(HAVERQ!AQ$128:AQ$183) -> -0.86553695 | CZ58: =(DL58-AVERAGE(DL$5:DL$59))/STDEV(DL$5:DL$59) -> -1.2097303 | DA58: =(DO58-AVERAGE(DO$5:DO$59))/STDEV(DO$5:DO$59) -> -1.4344512 | DB58: =(HAVERQ!AR182-AVERAGE(HAVERQ!AR$128:AR$183))/STDEV(HAVERQ!AR$128:AR$183) -> -1.0860629 | DC58: =(DM58-AVERAGE(DM$5:DM$59))/STDEV(DM$5:DM$59) -> 1.0038462 | DD58: =(DN58-AVERAGE(DN$29:DN$59))/STDEV(DN$29:DN$59) -> 0.56950398 | DE58: =(HAVERQ!AZ182-AVERAGE(HAVERQ!AZ$128:AZ$167,AZ$174:AZ$183))/STDEV(HAVERQ!AZ$128:AZ$167,AZ$174:AZ$183) -> -1.9632972 | DF58: =(HAVERQ!AS182-AVERAGE(HAVERQ!AS$128:AS$183))/STDEV(HAVERQ!AS$128:AS$183) -> 0.52718804 | DG58: =(DP58-AVERAGE(DP$5:DP$59))/STDEV(DP$5:DP$59) -> 2.1188933 | DH58: =(HAVERQ!AX182-AVERAGE(HAVERQ!AX$128:AX$183))/STDEV(HAVERQ!AX$128:AX$183) -> -1.3285019 | DJ58: =(DR58-AVERAGE(DR$5:DR$59))/STDEV(DR$5:DR$59) -> 0.79886 | DL58: =100*(HAVERQ!AV182/(HAVERQ!AW182*HAVERQ!AX182/100)) -> 0.72561042 | DM58: =HAVERQ!AO182/HAVERQ!AP182 -> 0.7006993 | DN58: =100*((AVERAGE(HAVERQ!BC179:BC182)/AVERAGE(HAVERQ!BC175:BC178))-1) -> 2.02774 | DO58: =100*(HAVERQ!BE182+HAVERQ!BF182)/(HAVERQ!BB182+HAVERQ!BG182) -> 7.5008632 | DP58: =100*((AVERAGE(HAVERQ!BA179:BA182)/AVERAGE(HAVERQ!BA175:BA178))-1) -> 7.109589 | DR58: =(HAVERQ!AT182*HAVERQ!$AT$1)+(HAVERQ!AU182*HAVERQ!$AU$1) -> 70.544156
M59: 44044 | N59: =HAVERM!C494 -> 4.964 | O59: =HAVERM!B494 -> 5 | Q59: 44044 | R59: =MIN(HAVERM!C493:C495) -> 4.809 | S59: =V59-R59 -> 0.326 | T59: =HAVERM!B494 -> 5 | V59: =MAX(HAVERM!C493:C495) -> 5.135 | AB59: 41548 | AC59: =HAVERQ!P143 -> 1516 | AD59: =HAVERQ!O143 -> 1699 | AE59: =HAVERQ!N143 -> 1061 | AF59: =HAVERQ!M143 -> 258 | AG59: =HAVERQ!L143 -> 169 | AH59: =HAVERQ!E143-AC59-AD59-AE59-AF59-AG59 -> 584 | AJ59: 41548 | AK59: =100*(AC59/SUM($AC59:$AH59)) -> 28.674106 | AL59: =100*(AD59/SUM($AC59:$AH59)) -> 32.135427 | AM59: =100*(AE59/SUM($AC59:$AH59)) -> 20.068092 | AN59: =100*(AF59/SUM($AC59:$AH59)) -> 4.8798941 | AO59: =100*(AG59/SUM($AC59:$AH59)) -> 3.1965198 | AP59: =100*(AH59/SUM($AC59:$AH59)) -> 11.045962 | CL59: =100*((DataQ!F218/DataQ!F214)-1) -> 4.4765856 | CM59: =100*(DataQ!I218/DataQ!J218) -> 20.239626 | CY59: =(HAVERQ!AQ183-AVERAGE(HAVERQ!AQ$128:AQ$183))/STDEV(HAVERQ!AQ$128:AQ$183) -> -0.98732104 | CZ59: =(DL59-AVERAGE(DL$5:DL$59))/STDEV(DL$5:DL$59) -> -1.1556891 | DA59: =(DO59-AVERAGE(DO$5:DO$59))/STDEV(DO$5:DO$59) -> -1.2270467 | DB59: =(HAVERQ!AR183-AVERAGE(HAVERQ!AR$128:AR$183))/STDEV(HAVERQ!AR$128:AR$183) -> -0.38512868 | DC59: =(DM59-AVERAGE(DM$5:DM$59))/STDEV(DM$5:DM$59) -> 0.91008336 | DD59: =(DN59-AVERAGE(DN$29:DN$59))/STDEV(DN$29:DN$59) -> 0.39998217 | DE59: =(HAVERQ!AZ183-AVERAGE(HAVERQ!AZ$128:AZ$167,AZ$174:AZ$183))/STDEV(HAVERQ!AZ$128:AZ$167,AZ$174:AZ$183) -> -1.5341612 | DF59: =(HAVERQ!AS183-AVERAGE(HAVERQ!AS$128:AS$183))/STDEV(HAVERQ!AS$128:AS$183) -> 0.52718804 | DG59: =(DP59-AVERAGE(DP$5:DP$59))/STDEV(DP$5:DP$59) -> 1.9907811 | DH59: =(HAVERQ!AX183-AVERAGE(HAVERQ!AX$128:AX$183))/STDEV(HAVERQ!AX$128:AX$183) -> -1.9333483 | DJ59: =(DR59-AVERAGE(DR$5:DR$59))/STDEV(DR$5:DR$59) -> 1.279172 | DL59: =100*(HAVERQ!AV183/(HAVERQ!AW183*HAVERQ!AX183/100)) -> 0.76608226 | DM59: =HAVERQ!AO183/HAVERQ!AP183 -> 0.67857143 | DN59: =100*((AVERAGE(HAVERQ!BC180:BC183)/AVERAGE(HAVERQ!BC176:BC179))-1) -> 1.7797978 | DO59: =100*(HAVERQ!BE183+HAVERQ!BF183)/(HAVERQ!BB183+HAVERQ!BG183) -> 7.813715 | DP59: =100*((AVERAGE(HAVERQ!BA180:BA183)/AVERAGE(HAVERQ!BA176:BA179))-1) -> 6.8607629 | DR59: =(HAVERQ!AT183*HAVERQ!$AT$1)+(HAVERQ!AU183*HAVERQ!$AU$1) -> 75.310946
M60: 44075 | N60: =HAVERM!C495 -> 5.135 | O60: =HAVERM!B495 -> 5.2 | Q60: 44075 | R60: =MIN(HAVERM!C494:C496) -> 4.964 | S60: =V60-R60 -> 0.413 | T60: =HAVERM!B495 -> 5.2 | V60: =MAX(HAVERM!C494:C496) -> 5.377 | AB60: 41640 | AC60: =HAVERQ!P144 -> 1523 | AD60: =HAVERQ!O144 -> 1699 | AE60: =HAVERQ!N144 -> 1059 | AF60: =HAVERQ!M144 -> 257 | AG60: =HAVERQ!L144 -> 166 | AH60: =HAVERQ!E144-AC60-AD60-AE60-AF60-AG60 -> 576 | AJ60: 41640 | AK60: =100*(AC60/SUM($AC60:$AH60)) -> 28.844697 | AL60: =100*(AD60/SUM($AC60:$AH60)) -> 32.17803 | AM60: =100*(AE60/SUM($AC60:$AH60)) -> 20.056818 | AN60: =100*(AF60/SUM($AC60:$AH60)) -> 4.8674242 | AO60: =100*(AG60/SUM($AC60:$AH60)) -> 3.1439394 | AP60: =100*(AH60/SUM($AC60:$AH60)) -> 10.909091 | CK60: 2026 | CL60: =100*((DataQ!F219/DataQ!F215)-1) -> 4.4014767 | CM60: =100*(DataQ!I219/DataQ!J219) -> 20.335936 | CX60: 2024 | CY60: =(HAVERQ!AQ184-AVERAGE(HAVERQ!AQ$128:AQ$183))/STDEV(HAVERQ!AQ$128:AQ$183) -> -0.74375286 | CZ60: =(DL60-AVERAGE(DL$5:DL$59))/STDEV(DL$5:DL$59) -> -0.87114645 | DA60: =(DO60-AVERAGE(DO$5:DO$59))/STDEV(DO$5:DO$59) -> -1.5911941 | DB60: =(HAVERQ!AR184-AVERAGE(HAVERQ!AR$128:AR$183))/STDEV(HAVERQ!AR$128:AR$183) -> -0.8164728 | DC60: =(DM60-AVERAGE(DM$5:DM$59))/STDEV(DM$5:DM$59) -> 0.55844348 | DD60: =(DN60-AVERAGE(DN$29:DN$59))/STDEV(DN$29:DN$59) -> 0.25433655 | DE60: =(HAVERQ!AZ184-AVERAGE(HAVERQ!AZ$128:AZ$167,AZ$174:AZ$183))/STDEV(HAVERQ!AZ$128:AZ$167,AZ$174:AZ$183) -> 0.1823828 | DF60: =(HAVERQ!AS184-AVERAGE(HAVERQ!AS$128:AS$183))/STDEV(HAVERQ!AS$128:AS$183) -> 0.52718804 | DG60: =(DP60-AVERAGE(DP$5:DP$59))/STDEV(DP$5:DP$59) -> 1.9578286 | DH60: =(HAVERQ!AX184-AVERAGE(HAVERQ!AX$128:AX$183))/STDEV(HAVERQ!AX$128:AX$183) -> -1.9333483 | DJ60: =(DR60-AVERAGE(DR$5:DR$59))/STDEV(DR$5:DR$59) -> 0.27155064 | DL60: =100*(HAVERQ!AV184/(HAVERQ!AW184*HAVERQ!AX184/100)) -> 0.97917847 | DM60: =HAVERQ!AO184/HAVERQ!AP184 -> 0.59558499 | DN60: =100*((AVERAGE(HAVERQ!BC181:BC184)/AVERAGE(HAVERQ!BC177:BC180))-1) -> 1.5667767 | DO60: =100*(HAVERQ!BE184+HAVERQ!BF184)/(HAVERQ!BB184+HAVERQ!BG184) -> 7.2644298 | DP60: =100*((AVERAGE(HAVERQ!BA181:BA184)/AVERAGE(HAVERQ!BA177:BA180))-1) -> 6.7967609 | DR60: =(HAVERQ!AT184*HAVERQ!$AT$1)+(HAVERQ!AU184*HAVERQ!$AU$1) -> 65.310946
M61: 44105 | N61: =HAVERM!C496 -> 5.377 | O61: =HAVERM!B496 -> 5.2 | Q61: 44105 | R61: =MIN(HAVERM!C495:C497) -> 5.135 | S61: =V61-R61 -> 0.242 | T61: =HAVERM!B496 -> 5.2 | V61: =MAX(HAVERM!C495:C497) -> 5.377 | AB61: 41730 | AC61: =HAVERQ!P145 -> 1528 | AD61: =HAVERQ!O145 -> 1694 | AE61: =HAVERQ!N145 -> 1059 | AF61: =HAVERQ!M145 -> 256 | AG61: =HAVERQ!L145 -> 164 | AH61: =HAVERQ!E145-AC61-AD61-AE61-AF61-AG61 -> 570 | AJ61: 41730 | AK61: =100*(AC61/SUM($AC61:$AH61)) -> 28.988807 | AL61: =100*(AD61/SUM($AC61:$AH61)) -> 32.138114 | AM61: =100*(AE61/SUM($AC61:$AH61)) -> 20.091064 | AN61: =100*(AF61/SUM($AC61:$AH61)) -> 4.8567634 | AO61: =100*(AG61/SUM($AC61:$AH61)) -> 3.1113641 | AP61: =100*(AH61/SUM($AC61:$AH61)) -> 10.813887 | CL61: =100*((DataQ!F220/DataQ!F216)-1) -> 2.3454881 | CM61: =100*(DataQ!I220/DataQ!J220) -> 20.360531 | CY61: =(HAVERQ!AQ185-AVERAGE(HAVERQ!AQ$128:AQ$183))/STDEV(HAVERQ!AQ$128:AQ$183) -> -0.8046449 | CZ61: =(DL61-AVERAGE(DL$5:DL$59))/STDEV(DL$5:DL$59) -> -0.88086783 | DA61: =(DO61-AVERAGE(DO$5:DO$59))/STDEV(DO$5:DO$59) -> -1.2986356 | DB61: =(HAVERQ!AR185-AVERAGE(HAVERQ!AR$128:AR$183))/STDEV(HAVERQ!AR$128:AR$183) -> -0.43904669 | DC61: =(DM61-AVERAGE(DM$5:DM$59))/STDEV(DM$5:DM$59) -> 0.63789098 | DD61: =(DN61-AVERAGE(DN$29:DN$59))/STDEV(DN$29:DN$59) -> 0.065791843 | DE61: =(HAVERQ!AZ185-AVERAGE(HAVERQ!AZ$128:AZ$167,AZ$174:AZ$183))/STDEV(HAVERQ!AZ$128:AZ$167,AZ$174:AZ$183) -> 0.1823828 | DF61: =(HAVERQ!AS185-AVERAGE(HAVERQ!AS$128:AS$183))/STDEV(HAVERQ!AS$128:AS$183) -> 0.52718804 | DG61: =(DP61-AVERAGE(DP$5:DP$59))/STDEV(DP$5:DP$59) -> 1.6113325 | DH61: =(HAVERQ!AX185-AVERAGE(HAVERQ!AX$128:AX$183))/STDEV(HAVERQ!AX$128:AX$183) -> -1.6309251 | DJ61: =(DR61-AVERAGE(DR$5:DR$59))/STDEV(DR$5:DR$59) -> 1.1862427 | DL61: =100*(HAVERQ!AV185/(HAVERQ!AW185*HAVERQ!AX185/100)) -> 0.97189805 | DM61: =HAVERQ!AO185/HAVERQ!AP185 -> 0.61433447 | DN61: =100*((AVERAGE(HAVERQ!BC182:BC185)/AVERAGE(HAVERQ!BC178:BC181))-1) -> 1.2910116 | DO61: =100*(HAVERQ!BE185+HAVERQ!BF185)/(HAVERQ!BB185+HAVERQ!BG185) -> 7.7057292 | DP61: =100*((AVERAGE(HAVERQ!BA182:BA185)/AVERAGE(HAVERQ!BA178:BA181))-1) -> 6.1237785 | DR61: =(HAVERQ!AT185*HAVERQ!$AT$1)+(HAVERQ!AU185*HAVERQ!$AU$1) -> 74.388683
M62: 44136 | N62: =HAVERM!C497 -> 5.173 | O62: =HAVERM!B497 -> 5.3 | Q62: 44136 | R62: =MIN(HAVERM!C496:C498) -> 5.173 | S62: =V62-R62 -> 0.204 | T62: =HAVERM!B497 -> 5.3 | V62: =MAX(HAVERM!C496:C498) -> 5.377 | AB62: 41821 | AC62: =HAVERQ!P146 -> 1534 | AD62: =HAVERQ!O146 -> 1689 | AE62: =HAVERQ!N146 -> 1053 | AF62: =HAVERQ!M146 -> 256 | AG62: =HAVERQ!L146 -> 163 | AH62: =HAVERQ!E146-AC62-AD62-AE62-AF62-AG62 -> 563 | AJ62: 41821 | AK62: =100*(AC62/SUM($AC62:$AH62)) -> 29.174591 | AL62: =100*(AD62/SUM($AC62:$AH62)) -> 32.12248 | AM62: =100*(AE62/SUM($AC62:$AH62)) -> 20.026626 | AN62: =100*(AF62/SUM($AC62:$AH62)) -> 4.8687714 | AO62: =100*(AG62/SUM($AC62:$AH62)) -> 3.100038 | AP62: =100*(AH62/SUM($AC62:$AH62)) -> 10.707493 | CL62: =100*((DataQ!F221/DataQ!F217)-1) -> 2.118229 | CM62: =100*(DataQ!I221/DataQ!J221) -> 20.423383 | CY62: =(HAVERQ!AQ186-AVERAGE(HAVERQ!AQ$128:AQ$183))/STDEV(HAVERQ!AQ$128:AQ$183) -> -0.74375286 | CZ62: =(DL62-AVERAGE(DL$5:DL$59))/STDEV(DL$5:DL$59) -> -0.88680621 | DA62: =(DO62-AVERAGE(DO$5:DO$59))/STDEV(DO$5:DO$59) -> -1.1066331 | DB62: =(HAVERQ!AR186-AVERAGE(HAVERQ!AR$128:AR$183))/STDEV(HAVERQ!AR$128:AR$183) -> -0.76255478 | DC62: =(DM62-AVERAGE(DM$5:DM$59))/STDEV(DM$5:DM$59) -> 0.43375455 | DD62: =(DN62-AVERAGE(DN$29:DN$59))/STDEV(DN$29:DN$59) -> -0.10928383 | DE62: =(HAVERQ!AZ186-AVERAGE(HAVERQ!AZ$128:AZ$167,AZ$174:AZ$183))/STDEV(HAVERQ!AZ$128:AZ$167,AZ$174:AZ$183) -> 0.61151881 | DF62: =(HAVERQ!AS186-AVERAGE(HAVERQ!AS$128:AS$183))/STDEV(HAVERQ!AS$128:AS$183) -> 0.00078334033 | DG62: =(DP62-AVERAGE(DP$5:DP$59))/STDEV(DP$5:DP$59) -> 1.2174405 | DH62: =(HAVERQ!AX186-AVERAGE(HAVERQ!AX$128:AX$183))/STDEV(HAVERQ!AX$128:AX$183) -> -0.72365552 | DJ62: =(DR62-AVERAGE(DR$5:DR$59))/STDEV(DR$5:DR$59) -> 1.2019085 | DL62: =100*(HAVERQ!AV186/(HAVERQ!AW186*HAVERQ!AX186/100)) -> 0.96745076 | DM62: =HAVERQ!AO186/HAVERQ!AP186 -> 0.5661586 | DN62: =100*((AVERAGE(HAVERQ!BC183:BC186)/AVERAGE(HAVERQ!BC179:BC182))-1) -> 1.0349462 | DO62: =100*(HAVERQ!BE186+HAVERQ!BF186)/(HAVERQ!BB186+HAVERQ!BG186) -> 7.9953486 | DP62: =100*((AVERAGE(HAVERQ!BA183:BA186)/AVERAGE(HAVERQ!BA179:BA182))-1) -> 5.3587415 | DR62: =(HAVERQ!AT186*HAVERQ!$AT$1)+(HAVERQ!AU186*HAVERQ!$AU$1) -> 74.544156
M63: 44166 | N63: =HAVERM!C498 -> 5.261 | O63: =HAVERM!B498 -> 5.2 | Q63: 44166 | R63: =MIN(HAVERM!C497:C499) -> 5.052 | S63: =V63-R63 -> 0.209 | T63: =HAVERM!B498 -> 5.2 | V63: =MAX(HAVERM!C497:C499) -> 5.261 | AB63: 41913 | AC63: =HAVERQ!P147 -> 1538 | AD63: =HAVERQ!O147 -> 1691 | AE63: =HAVERQ!N147 -> 1045 | AF63: =HAVERQ!M147 -> 255 | AG63: =HAVERQ!L147 -> 162 | AH63: =HAVERQ!E147-AC63-AD63-AE63-AF63-AG63 -> 563 | AJ63: 41913 | AK63: =100*(AC63/SUM($AC63:$AH63)) -> 29.272935 | AL63: =100*(AD63/SUM($AC63:$AH63)) -> 32.185002 | AM63: =100*(AE63/SUM($AC63:$AH63)) -> 19.889608 | AN63: =100*(AF63/SUM($AC63:$AH63)) -> 4.853445 | AO63: =100*(AG63/SUM($AC63:$AH63)) -> 3.0833651 | AP63: =100*(AH63/SUM($AC63:$AH63)) -> 10.715645 | CL63: =100*((DataQ!F222/DataQ!F218)-1) -> 1.9566747 | CM63: =100*(DataQ!I222/DataQ!J222) -> 20.503419
M64: 44197 | N64: =HAVERM!C499 -> 5.052 | O64: =HAVERM!B499 -> 5 | Q64: 44197 | R64: =MIN(HAVERM!C498:C500) -> 4.836 | S64: =V64-R64 -> 0.425 | T64: =HAVERM!B499 -> 5 | V64: =MAX(HAVERM!C498:C500) -> 5.261 | AB64: 42005 | AC64: =HAVERQ!P148 -> 1545 | AD64: =HAVERQ!O148 -> 1688 | AE64: =HAVERQ!N148 -> 1034 | AF64: =HAVERQ!M148 -> 255 | AG64: =HAVERQ!L148 -> 160 | AH64: =HAVERQ!E148-AC64-AD64-AE64-AF64-AG64 -> 562 | AJ64: 42005 | AK64: =100*(AC64/SUM($AC64:$AH64)) -> 29.462243 | AL64: =100*(AD64/SUM($AC64:$AH64)) -> 32.189169 | AM64: =100*(AE64/SUM($AC64:$AH64)) -> 19.717773 | AN64: =100*(AF64/SUM($AC64:$AH64)) -> 4.8627002 | AO64: =100*(AG64/SUM($AC64:$AH64)) -> 3.051106 | AP64: =100*(AH64/SUM($AC64:$AH64)) -> 10.71701 | CK64: 2027 | CL64: =100*((DataQ!F223/DataQ!F219)-1) -> 1.9052587 | CM64: =100*(DataQ!I223/DataQ!J223) -> 20.747984
M65: 44228 | N65: =HAVERM!C500 -> 4.836 | O65: =HAVERM!B500 -> 4.9 | Q65: 44228 | R65: =MIN(HAVERM!C499:C501) -> 4.836 | S65: =V65-R65 -> 0.216 | T65: =HAVERM!B500 -> 4.9 | V65: =MAX(HAVERM!C499:C501) -> 5.052 | AB65: 42095 | AC65: =HAVERQ!P149 -> 1551 | AD65: =HAVERQ!O149 -> 1689 | AE65: =HAVERQ!N149 -> 1020 | AF65: =HAVERQ!M149 -> 254 | AG65: =HAVERQ!L149 -> 159 | AH65: =HAVERQ!E149-AC65-AD65-AE65-AF65-AG65 -> 555 | AJ65: 42095 | AK65: =100*(AC65/SUM($AC65:$AH65)) -> 29.667177 | AL65: =100*(AD65/SUM($AC65:$AH65)) -> 32.306809 | AM65: =100*(AE65/SUM($AC65:$AH65)) -> 19.510329 | AN65: =100*(AF65/SUM($AC65:$AH65)) -> 4.8584545 | AO65: =100*(AG65/SUM($AC65:$AH65)) -> 3.041316 | AP65: =100*(AH65/SUM($AC65:$AH65)) -> 10.615914 | CL65: =100*((DataQ!F224/DataQ!F220)-1) -> 1.8503486 | CM65: =100*(DataQ!I224/DataQ!J224) -> 20.703421
M66: 44256 | N66: =HAVERM!C501 -> 4.844 | O66: =HAVERM!B501 -> 4.8 | Q66: 44256 | R66: =MIN(HAVERM!C500:C502) -> 4.782 | S66: =V66-R66 -> 0.062 | T66: =HAVERM!B501 -> 4.8 | V66: =MAX(HAVERM!C500:C502) -> 4.844 | AB66: 42186 | AC66: =HAVERQ!P150 -> 1559 | AD66: =HAVERQ!O150 -> 1682 | AE66: =HAVERQ!N150 -> 1016 | AF66: =HAVERQ!M150 -> 252 | AG66: =HAVERQ!L150 -> 159 | AH66: =HAVERQ!E150-AC66-AD66-AE66-AF66-AG66 -> 548 | AJ66: 42186 | AK66: =100*(AC66/SUM($AC66:$AH66)) -> 29.888804 | AL66: =100*(AD66/SUM($AC66:$AH66)) -> 32.246933 | AM66: =100*(AE66/SUM($AC66:$AH66)) -> 19.478528 | AN66: =100*(AF66/SUM($AC66:$AH66)) -> 4.8312883 | AO66: =100*(AG66/SUM($AC66:$AH66)) -> 3.0483129 | AP66: =100*(AH66/SUM($AC66:$AH66)) -> 10.506135 | CL66: =100*((DataQ!F225/DataQ!F221)-1) -> 1.8152223 | CM66: =100*(DataQ!I225/DataQ!J225) -> 20.877364
M67: 44287 | N67: =HAVERM!C502 -> 4.782 | O67: =HAVERM!B502 -> 4.8 | Q67: 44287 | R67: =MIN(HAVERM!C501:C503) -> 4.759 | S67: =V67-R67 -> 0.085 | T67: =HAVERM!B502 -> 4.8 | V67: =MAX(HAVERM!C501:C503) -> 4.844 | AB67: 42278 | AC67: =HAVERQ!P151 -> 1571 | AD67: =HAVERQ!O151 -> 1681 | AE67: =HAVERQ!N151 -> 1015 | AF67: =HAVERQ!M151 -> 250 | AG67: =HAVERQ!L151 -> 159 | AH67: =HAVERQ!E151-AC67-AD67-AE67-AF67-AG67 -> 549 | AJ67: 42278 | AK67: =100*(AC67/SUM($AC67:$AH67)) -> 30.066986 | AL67: =100*(AD67/SUM($AC67:$AH67)) -> 32.172249 | AM67: =100*(AE67/SUM($AC67:$AH67)) -> 19.425837 | AN67: =100*(AF67/SUM($AC67:$AH67)) -> 4.784689 | AO67: =100*(AG67/SUM($AC67:$AH67)) -> 3.0430622 | AP67: =100*(AH67/SUM($AC67:$AH67)) -> 10.507177 | CL67: =100*((DataQ!F226/DataQ!F222)-1) -> 1.784681 | CM67: =100*(DataQ!I226/DataQ!J226) -> 20.929373
M68: 44317 | N68: =HAVERM!C503 -> 4.759 | O68: =HAVERM!B503 -> 4.7 | Q68: 44317 | R68: =MIN(HAVERM!C502:C504) -> 4.466 | S68: =V68-R68 -> 0.316 | T68: =HAVERM!B503 -> 4.7 | V68: =MAX(HAVERM!C502:C504) -> 4.782 | AB68: 42370 | AC68: =HAVERQ!P152 -> 1579 | AD68: =HAVERQ!O152 -> 1680 | AE68: =HAVERQ!N152 -> 1010 | AF68: =HAVERQ!M152 -> 248 | AG68: =HAVERQ!L152 -> 158 | AH68: =HAVERQ!E152-AC68-AD68-AE68-AF68-AG68 -> 549 | AJ68: 42370 | AK68: =100*(AC68/SUM($AC68:$AH68)) -> 30.225881 | AL68: =100*(AD68/SUM($AC68:$AH68)) -> 32.159265 | AM68: =100*(AE68/SUM($AC68:$AH68)) -> 19.333844 | AN68: =100*(AF68/SUM($AC68:$AH68)) -> 4.7473201 | AO68: =100*(AG68/SUM($AC68:$AH68)) -> 3.0245023 | AP68: =100*(AH68/SUM($AC68:$AH68)) -> 10.509188
M69: 44348 | N69: =HAVERM!C504 -> 4.466 | O69: =HAVERM!B504 -> 4.6 | Q69: 44348 | R69: =MIN(HAVERM!C503:C505) -> 4.466 | S69: =V69-R69 -> 0.293 | T69: =HAVERM!B504 -> 4.6 | V69: =MAX(HAVERM!C503:C505) -> 4.759 | AB69: 42461 | AC69: =HAVERQ!P153 -> 1589 | AD69: =HAVERQ!O153 -> 1676 | AE69: =HAVERQ!N153 -> 1003 | AF69: =HAVERQ!M153 -> 247 | AG69: =HAVERQ!L153 -> 158 | AH69: =HAVERQ!E153-AC69-AD69-AE69-AF69-AG69 -> 545 | AJ69: 42461 | AK69: =100*(AC69/SUM($AC69:$AH69)) -> 30.452281 | AL69: =100*(AD69/SUM($AC69:$AH69)) -> 32.119586 | AM69: =100*(AE69/SUM($AC69:$AH69)) -> 19.221924 | AN69: =100*(AF69/SUM($AC69:$AH69)) -> 4.7336144 | AO69: =100*(AG69/SUM($AC69:$AH69)) -> 3.0279801 | AP69: =100*(AH69/SUM($AC69:$AH69)) -> 10.444615
M70: 44378 | N70: =HAVERM!C505 -> 4.489 | O70: =HAVERM!B505 -> 4.5 | Q70: 44378 | R70: =MIN(HAVERM!C504:C506) -> 4.466 | S70: =V70-R70 -> 0.135 | T70: =HAVERM!B505 -> 4.5 | V70: =MAX(HAVERM!C504:C506) -> 4.601 | AB70: 42552 | AC70: =HAVERQ!P154 -> 1596 | AD70: =HAVERQ!O154 -> 1678 | AE70: =HAVERQ!N154 -> 1002 | AF70: =HAVERQ!M154 -> 247 | AG70: =HAVERQ!L154 -> 158 | AH70: =HAVERQ!E154-AC70-AD70-AE70-AF70-AG70 -> 537 | AJ70: 42552 | AK70: =100*(AC70/SUM($AC70:$AH70)) -> 30.586432 | AL70: =100*(AD70/SUM($AC70:$AH70)) -> 32.157915 | AM70: =100*(AE70/SUM($AC70:$AH70)) -> 19.20276 | AN70: =100*(AF70/SUM($AC70:$AH70)) -> 4.7336144 | AO70: =100*(AG70/SUM($AC70:$AH70)) -> 3.0279801 | AP70: =100*(AH70/SUM($AC70:$AH70)) -> 10.291299
M71: 44409 | N71: =HAVERM!C506 -> 4.601 | O71: =HAVERM!B506 -> 4.4 | Q71: 44409 | R71: =MIN(HAVERM!C505:C507) -> 4.069 | S71: =V71-R71 -> 0.532 | T71: =HAVERM!B506 -> 4.4 | V71: =MAX(HAVERM!C505:C507) -> 4.601 | AB71: 42644 | AC71: =HAVERQ!P155 -> 1601 | AD71: =HAVERQ!O155 -> 1671 | AE71: =HAVERQ!N155 -> 1003 | AF71: =HAVERQ!M155 -> 246 | AG71: =HAVERQ!L155 -> 158 | AH71: =HAVERQ!E155-AC71-AD71-AE71-AF71-AG71 -> 529 | AJ71: 42644 | AK71: =100*(AC71/SUM($AC71:$AH71)) -> 30.741167 | AL71: =100*(AD71/SUM($AC71:$AH71)) -> 32.085253 | AM71: =100*(AE71/SUM($AC71:$AH71)) -> 19.258833 | AN71: =100*(AF71/SUM($AC71:$AH71)) -> 4.7235023 | AO71: =100*(AG71/SUM($AC71:$AH71)) -> 3.0337942 | AP71: =100*(AH71/SUM($AC71:$AH71)) -> 10.15745
M72: 44440 | N72: =HAVERM!C507 -> 4.069 | O72: =HAVERM!B507 -> 4.3 | Q72: 44440 | R72: =MIN(HAVERM!C506:C508) -> 4.069 | S72: =V72-R72 -> 0.532 | T72: =HAVERM!B507 -> 4.3 | V72: =MAX(HAVERM!C506:C508) -> 4.601 | AB72: 42736 | AC72: =HAVERQ!P156 -> 1613 | AD72: =HAVERQ!O156 -> 1668 | AE72: =HAVERQ!N156 -> 1005 | AF72: =HAVERQ!M156 -> 245 | AG72: =HAVERQ!L156 -> 157 | AH72: =HAVERQ!E156-AC72-AD72-AE72-AF72-AG72 -> 522 | AJ72: 42736 | AK72: =100*(AC72/SUM($AC72:$AH72)) -> 30.959693 | AL72: =100*(AD72/SUM($AC72:$AH72)) -> 32.015355 | AM72: =100*(AE72/SUM($AC72:$AH72)) -> 19.289827 | AN72: =100*(AF72/SUM($AC72:$AH72)) -> 4.7024952 | AO72: =100*(AG72/SUM($AC72:$AH72)) -> 3.0134357 | AP72: =100*(AH72/SUM($AC72:$AH72)) -> 10.019194
M73: 44470 | N73: =HAVERM!C508 -> 4.25 | O73: =HAVERM!B508 -> 4.2 | Q73: 44470 | R73: =MIN(HAVERM!C507:C509) -> 4.069 | S73: =V73-R73 -> 0.302 | T73: =HAVERM!B508 -> 4.2 | V73: =MAX(HAVERM!C507:C509) -> 4.371 | AB73: 42826 | AC73: =HAVERQ!P157 -> 1623 | AD73: =HAVERQ!O157 -> 1662 | AE73: =HAVERQ!N157 -> 1012 | AF73: =HAVERQ!M157 -> 245 | AG73: =HAVERQ!L157 -> 156 | AH73: =HAVERQ!E157-AC73-AD73-AE73-AF73-AG73 -> 521 | AJ73: 42826 | AK73: =100*(AC73/SUM($AC73:$AH73)) -> 31.097911 | AL73: =100*(AD73/SUM($AC73:$AH73)) -> 31.845181 | AM73: =100*(AE73/SUM($AC73:$AH73)) -> 19.390688 | AN73: =100*(AF73/SUM($AC73:$AH73)) -> 4.6943859 | AO73: =100*(AG73/SUM($AC73:$AH73)) -> 2.9890784 | AP73: =100*(AH73/SUM($AC73:$AH73)) -> 9.9827553
M74: 44501 | N74: =HAVERM!C509 -> 4.371 | O74: =HAVERM!B509 -> 4.2 | Q74: 44501 | R74: =MIN(HAVERM!C508:C510) -> 3.931 | S74: =V74-R74 -> 0.44 | T74: =HAVERM!B509 -> 4.2 | V74: =MAX(HAVERM!C508:C510) -> 4.371 | AB74: 42917 | AC74: =HAVERQ!P158 -> 1629 | AD74: =HAVERQ!O158 -> 1650 | AE74: =HAVERQ!N158 -> 1017 | AF74: =HAVERQ!M158 -> 245 | AG74: =HAVERQ!L158 -> 156 | AH74: =HAVERQ!E158-AC74-AD74-AE74-AF74-AG74 -> 519 | AJ74: 42917 | AK74: =100*(AC74/SUM($AC74:$AH74)) -> 31.230828 | AL74: =100*(AD74/SUM($AC74:$AH74)) -> 31.633436 | AM74: =100*(AE74/SUM($AC74:$AH74)) -> 19.497699 | AN74: =100*(AF74/SUM($AC74:$AH74)) -> 4.6970859 | AO74: =100*(AG74/SUM($AC74:$AH74)) -> 2.9907975 | AP74: =100*(AH74/SUM($AC74:$AH74)) -> 9.9501534
M75: 44531 | N75: =HAVERM!C510 -> 3.931 | O75: =HAVERM!B510 -> 4.1 | Q75: 44531 | R75: =MIN(HAVERM!C509:C511) -> 3.931 | S75: =V75-R75 -> 0.44 | T75: =HAVERM!B510 -> 4.1 | V75: =MAX(HAVERM!C509:C511) -> 4.371 | AB75: 43009 | AC75: =HAVERQ!P159 -> 1639 | AD75: =HAVERQ!O159 -> 1644 | AE75: =HAVERQ!N159 -> 1017 | AF75: =HAVERQ!M159 -> 246 | AG75: =HAVERQ!L159 -> 156 | AH75: =HAVERQ!E159-AC75-AD75-AE75-AF75-AG75 -> 520 | AJ75: 43009 | AK75: =100*(AC75/SUM($AC75:$AH75)) -> 31.386442 | AL75: =100*(AD75/SUM($AC75:$AH75)) -> 31.482191 | AM75: =100*(AE75/SUM($AC75:$AH75)) -> 19.475297 | AN75: =100*(AF75/SUM($AC75:$AH75)) -> 4.7108388 | AO75: =100*(AG75/SUM($AC75:$AH75)) -> 2.9873612 | AP75: =100*(AH75/SUM($AC75:$AH75)) -> 9.9578705
M76: 44562 | N76: =HAVERM!C511 -> 3.974 | O76: =HAVERM!B511 -> 3.9 | Q76: 44562 | R76: =MIN(HAVERM!C510:C512) -> 3.884 | S76: =V76-R76 -> 0.09 | T76: =HAVERM!B511 -> 3.9 | V76: =MAX(HAVERM!C510:C512) -> 3.974 | AB76: 43101 | AC76: =HAVERQ!P160 -> 1642 | AD76: =HAVERQ!O160 -> 1644 | AE76: =HAVERQ!N160 -> 1022 | AF76: =HAVERQ!M160 -> 246 | AG76: =HAVERQ!L160 -> 155 | AH76: =HAVERQ!E160-AC76-AD76-AE76-AF76-AG76 -> 521 | AJ76: 43101 | AK76: =100*(AC76/SUM($AC76:$AH76)) -> 31.395793 | AL76: =100*(AD76/SUM($AC76:$AH76)) -> 31.434034 | AM76: =100*(AE76/SUM($AC76:$AH76)) -> 19.541109 | AN76: =100*(AF76/SUM($AC76:$AH76)) -> 4.7036329 | AO76: =100*(AG76/SUM($AC76:$AH76)) -> 2.9636711 | AP76: =100*(AH76/SUM($AC76:$AH76)) -> 9.9617591
M77: 44593 | N77: =HAVERM!C512 -> 3.884 | O77: =HAVERM!B512 -> 3.8 | Q77: 44593 | R77: =MIN(HAVERM!C511:C513) -> 3.483 | S77: =V77-R77 -> 0.491 | T77: =HAVERM!B512 -> 3.8 | V77: =MAX(HAVERM!C511:C513) -> 3.974 | AB77: 43191 | AC77: =HAVERQ!P161 -> 1650 | AD77: =HAVERQ!O161 -> 1644 | AE77: =HAVERQ!N161 -> 1028 | AF77: =HAVERQ!M161 -> 247 | AG77: =HAVERQ!L161 -> 154 | AH77: =HAVERQ!E161-AC77-AD77-AE77-AF77-AG77 -> 521 | AJ77: 43191 | AK77: =100*(AC77/SUM($AC77:$AH77)) -> 31.464531 | AL77: =100*(AD77/SUM($AC77:$AH77)) -> 31.350114 | AM77: =100*(AE77/SUM($AC77:$AH77)) -> 19.603356 | AN77: =100*(AF77/SUM($AC77:$AH77)) -> 4.7101449 | AO77: =100*(AG77/SUM($AC77:$AH77)) -> 2.9366895 | AP77: =100*(AH77/SUM($AC77:$AH77)) -> 9.935164
M78: 44621 | N78: =HAVERM!C513 -> 3.483 | O78: =HAVERM!B513 -> 3.8 | Q78: 44621 | R78: =MIN(HAVERM!C512:C514) -> 3.483 | S78: =V78-R78 -> 0.597 | T78: =HAVERM!B513 -> 3.8 | V78: =MAX(HAVERM!C512:C514) -> 4.08 | AB78: 43282 | AC78: =HAVERQ!P162 -> 1663 | AD78: =HAVERQ!O162 -> 1636 | AE78: =HAVERQ!N162 -> 1033 | AF78: =HAVERQ!M162 -> 247 | AG78: =HAVERQ!L162 -> 153 | AH78: =HAVERQ!E162-AC78-AD78-AE78-AF78-AG78 -> 523 | AJ78: 43282 | AK78: =100*(AC78/SUM($AC78:$AH78)) -> 31.646051 | AL78: =100*(AD78/SUM($AC78:$AH78)) -> 31.132255 | AM78: =100*(AE78/SUM($AC78:$AH78)) -> 19.657469 | AN78: =100*(AF78/SUM($AC78:$AH78)) -> 4.7002854 | AO78: =100*(AG78/SUM($AC78:$AH78)) -> 2.9115128 | AP78: =100*(AH78/SUM($AC78:$AH78)) -> 9.9524263
M79: 44652 | N79: =HAVERM!C514 -> 4.08 | O79: =HAVERM!B514 -> 3.7 | Q79: 44652 | R79: =MIN(HAVERM!C513:C515) -> 3.483 | S79: =V79-R79 -> 0.597 | T79: =HAVERM!B514 -> 3.7 | V79: =MAX(HAVERM!C513:C515) -> 4.08 | AB79: 43374 | AC79: =HAVERQ!P163 -> 1671 | AD79: =HAVERQ!O163 -> 1637 | AE79: =HAVERQ!N163 -> 1038 | AF79: =HAVERQ!M163 -> 247 | AG79: =HAVERQ!L163 -> 153 | AH79: =HAVERQ!E163-AC79-AD79-AE79-AF79-AG79 -> 523 | AJ79: 43374 | AK79: =100*(AC79/SUM($AC79:$AH79)) -> 31.713798 | AL79: =100*(AD79/SUM($AC79:$AH79)) -> 31.068514 | AM79: =100*(AE79/SUM($AC79:$AH79)) -> 19.700133 | AN79: =100*(AF79/SUM($AC79:$AH79)) -> 4.6877965 | AO79: =100*(AG79/SUM($AC79:$AH79)) -> 2.9037768 | AP79: =100*(AH79/SUM($AC79:$AH79)) -> 9.9259822
... M102: 45352 | N102: =HAVERM!C537 -> 4.427 | O102: =HAVERM!B537 -> 4.4 | Q102: 45352 | R102: =MIN(HAVERM!C536:C538) -> 4.325 | S102: =V102-R102 -> 0.102 | T102: =HAVERM!B537 -> 4.4 | V102: =MAX(HAVERM!C536:C538) -> 4.427 | AB102: 45474 | AC102: =HAVERQ!P186 -> 2040 | AD102: =HAVERQ!O186 -> 1658 | AE102: =HAVERQ!N186 -> 1220 | AF102: =HAVERQ!M186 -> 282 | AG102: =HAVERQ!L186 -> 147 | AH102: =HAVERQ!E186-AC102-AD102-AE102-AF102-AG102 -> 528 | AJ102: 45474 | AK102: =100*(AC102/SUM($AC102:$AH102)) -> 34.723404 | AL102: =100*(AD102/SUM($AC102:$AH102)) -> 28.221277 | AM102: =100*(AE102/SUM($AC102:$AH102)) -> 20.765957 | AN102: =100*(AF102/SUM($AC102:$AH102)) -> 4.8 | AO102: =100*(AG102/SUM($AC102:$AH102)) -> 2.5021277 | AP102: =100*(AH102/SUM($AC102:$AH102)) -> 8.987234
M103: 45383 | N103: =HAVERM!C538 -> 4.343 | O103: =HAVERM!B538 -> 4.4 | Q103: 45383 | R103: =MIN(HAVERM!C537:C539) -> 4.343 | S103: =V103-R103 -> 0.155 | T103: =HAVERM!B538 -> 4.4 | V103: =MAX(HAVERM!C537:C539) -> 4.498 | AB103: 45566 | AJ103: 45566
M104: 45413 | N104: =HAVERM!C539 -> 4.498 | O104: =HAVERM!B539 -> 4.2 | Q104: 45413 | R104: =MIN(HAVERM!C538:C540) -> 3.77 | S104: =V104-R104 -> 0.728 | T104: =HAVERM!B539 -> 4.2 | V104: =MAX(HAVERM!C538:C540) -> 4.498
M105: 45444 | N105: =HAVERM!C540 -> 3.77 | O105: =HAVERM!B540 -> 4.2 | Q105: 45444 | R105: =MIN(HAVERM!C539:C541) -> 3.77 | S105: =V105-R105 -> 0.728 | T105: =HAVERM!B540 -> 4.2 | V105: =MAX(HAVERM!C539:C541) -> 4.498
M106: 45474 | N106: =HAVERM!C541 -> 4.35 | O106: =HAVERM!B541 -> 4.1 | Q106: 45474 | R106: =MIN(HAVERM!C540:C542) -> 3.77 | S106: =V106-R106 -> 0.58 | T106: =HAVERM!B541 -> 4.1 | V106: =MAX(HAVERM!C540:C542) -> 4.35
M107: 45505 | N107: =HAVERM!C542 -> 4.107 | O107: =HAVERM!B542 -> 4.3 | Q107: 45505 | R107: =MIN(HAVERM!C541:C543) -> 4.107 | S107: =V107-R107 -> 0.285 | T107: =HAVERM!B542 -> 4.3 | V107: =MAX(HAVERM!C541:C543) -> 4.392
M108: 45536 | N108: =HAVERM!C543 -> 4.392 | O108: =HAVERM!B543 -> 4.3 | Q108: 45536 | R108: =MIN(HAVERM!C542:C544) -> 4.107 | S108: =V108-R108 -> 0.285 | T108: =HAVERM!B543 -> 4.3 | V108: =MAX(HAVERM!C542:C544) -> 4.392
M109: 45566 | N109: =HAVERM!C544 -> 4.322 | Q109: 45566 | R109: =MIN(HAVERM!C543:C545) -> 4.322 | S109: =V109-R109 -> 0.07 | V109: =MAX(HAVERM!C543:C545) -> 4.392
M110: 45597 | Q110: 45597
M111: 45627 | Q111: 45627

Sheet DMP - NICs Reaction
A1: Reaction to the Change in National Insurance contribution following the November Budget
B3: Lower employee wages | C3: Lower number of employees | D3: Higher prices | E3: Lower profit margins | F3: Other | G3: None of the above
A4: 45597 | B4: 37.88 | C4: 53.68 | D4: 53.64 | E4: 58.72 | F4: 7.51 | G4: 2.67
A5: 45627 | B5: 40.67 | C5: 52.76 | D5: 54.45 | E5: 63.5 | F5: 7.33 | G5: 3.75
A33: Source: Decision Maker Panel
A35: Notes:
