Workbook
Name _DLX1.INC: 'Haver Q'!$P$3:$T$8
Name _DLX2.INC: 'Haver Q'!$A$3:$L$8
Name _DLX3.INC: 'Series construction'!$A$4:$K$9
Name _DLX4.INC: 'Haver Q'!$W$3:$BA$8
Name Annual_Data: GMWQ!$A$1:$A$2

Sheet Notes
A2: Notes:
A4: - | B4: First step is to have everything setup in a proper workfile structure so Eviews imports the data from an excel file (incl REPO and WORMRT), generates certain variables, then can try and save various regressions - Alessandro won't help unless the Eviews work is set out nicely
A6: - | B6: Try logging everything (e.g. ARR/NOMORT, PEDIP_UNADJ/PEDY!, MRTPE/PEDY!, maybe HHLIAB), have UPILO in levels as already stationary (and the differenced UPILO series is essentially just noise). Logged ratios is fine because these ratios never really come too close to zero.
A7: - | B7: Can try adding MRTPE/MVH (mortgage liabilities as % of housing value) because greater liabilities aren't a huge issue if the collateralised asset has appreciated markedly
A8: - | B8: Can try adding RBM as an explanatory variable
A9: - | B9: Can try adding a variable for personal loans (as % of incomes) as a big jump in credit card payments could make you miss mortgage payments (unlikely in my opinion).
A10: - | B10: Generally it's best to not have self-lags as it's a false fit (over fit). Means the forecast will be very sticky in scenarios which is silly
A11: - | B11: Can spread coefficients over more than one lag, e.g. if coeff on PEDIP_UNADJ/PEDY!(-1) is 0.5 then can adjust this to 0.05 on contemporaneous and 0.45 on first lag
A12: - | B12: Andy is happy for the forecast to be driven by the data rather than pure narrative, so a gradual fall from here is absolutely fine (will want a residual transformation which always smoothes back to zero/1)
A13: - | B13: If nothing works then can try ARR/WORMRT (but it's sequentially illogical to model arrears that way, but could try something like that with REPO?)
A15: - | B15: When doing REPO, sensible to just have this running off ARR (e.g. REPO(-1) X% of arrears turn into repossessions)
A16: - | B16: If adding a behavioural equation, can do the eviews work with a pandemic dummy to get senisble coefficients, then remove the dummy when adding it to the model and adjust the coefficient.
Q19: R2 | R19: Adj R2 | S19: SE | T19: RSS | U19: AIC | V19: SBC | W19: HQN
B20: arr/nomort = c(1) + c(2) * log(pedip_unadj_pedy(-1)) + c(3) * log(mrtpe/mvh(-1)) + c(4) * upilo(-1) | P20: 1 | Q20: 0.90663364 | R20: 0.90204185 | S20: 1.0774257 | T20: 70.811609 | U20: 3.0465897 | V20: 3.1803981 | W20: 3.0993857
B21: arr/nomort = c(1) + c(2) * log(pedip_unadj_pedy(-1)) + c(3) * log(mrtpe/mvh(-1)) + c(4) * upilo(-2) | P21: 2 | Q21: 0.90365432 | R21: 0.89883703 | S21: 1.1027297 | T21: 72.960771 | U21: 3.0939159 | V21: 3.2288461 | W21: 3.1470717
B22: arr/nomort = c(1) + c(2) * log(pedip_unadj_pedy(-1)) + c(3) * log(mrtpe/mvh(-2)) + c(4) * upilo(-2) | P22: 3 | Q22: 0.90343464 | R22: 0.89860637 | S22: 1.1039862 | T22: 73.127131 | U22: 3.0961934 | V22: 3.2311236 | W22: 3.1493492
B23: arr/nomort = c(1) + c(2) * log(pedip_unadj_pedy(-2)) + c(3) * log(mrtpe/mvh(-2)) + c(4) * upilo(-2) | P23: 4 | Q23: 0.91418844 | R23: 0.90989786 | S23: 1.0407007 | T23: 64.983482 | U23: 2.9781271 | V23: 3.1130573 | W23: 3.0312829
B25: arr/nomort = c(1) + c(2) * log(pedip_unadj_pedy(-1)) + c(3) * log(pedip_unadj_pedy(-2)) + c(4) * log(mrtpe/mvh(-1)) + c(5) * upilo(-1) | P25: 5 | Q25: 0.93533384 | R25: 0.93094969 | S25: 0.91104772 | T25: 48.970468 | U25: 2.7264614 | V25: 2.8951242 | W25: 2.7929062
B26: arr/nomort = c(1) + c(2) * log(pedip_unadj_pedy(-1)) + c(3) * log(pedip_unadj_pedy(-2)) + c(4) * log(mrtpe/mvh(-1)) + c(5) * upilo(-2) | P26: 6 | Q26: 0.91513996 | R26: 0.90938674 | S26: 1.0436484 | T26: 64.262912 | U26: 2.9982267 | V26: 3.1668894 | W26: 3.0646714
B28: arr/nomort = c(1) + c(2) * log(pedip_unadj_pedy(-1)) + c(3) * log(mrtpe/mvh(-1)) + c(4) * upilo(-1) + c(5) * pinsolv_popw(-1) | P28: 7 | Q28: 0.93817004 | R28: 0.93404804 | S28: 0.88405828 | T28: 46.893542 | U28: 2.6652159 | V28: 2.8324765 | W28: 2.7312109
B29: arr/nomort = c(1) + c(2) * log(pedip_unadj_pedy(-1)) + c(3) * upilo(-1) + c(4) * pinsolv_popw(-1) | P29: 8 | Q29: 0.93145155 | R29: 0.92808031 | S29: 0.92318965 | T29: 51.989027 | U29: 2.7375994 | V29: 2.8714078 | W29: 2.7903954
B30: arr/nomort = c(1) + c(2) * log(pedip_unadj_pedy(-1)) + c(3) * upilo(-2) + c(4) * pinsolv_popw(-2) | P30: 9 | Q30: 0.93106026 | R30: 0.92761327 | S30: 0.93279837 | T30: 52.206768 | U30: 2.7592061 | V30: 2.8941363 | W30: 2.8123619
B31: arr/nomort = c(1) + c(2) * log(pedip_unadj_pedy(-2)) + c(3) * upilo(-2) + c(4) * pinsolv_popw(-2) | P31: 10 | Q31: 0.93512962 | R31: 0.9318861 | S31: 0.90484912 | T31: 49.125116 | U31: 2.6983644 | V31: 2.8332946 | W31: 2.7515202
B32: arr/nomort = c(1) + c(2) * log(pedip_unadj_pedy(-2)) + c(3) * upilo(-2) + c(4) * pinsolv_popw(-2) | P32: 11 | Q32: 0.93512962 | R32: 0.9318861 | S32: 0.90484912 | T32: 49.125116 | U32: 2.6983644 | V32: 2.8332946 | W32: 2.7515202
A33: * | B33: arr/nomort = c(1) + c(2) * log(pedip_unadj_pedy(-1)) + c(3) * upilo(-1) + c(4) * pinsolv_popw(-1) + c(5) * rrh(-1) | P33: 12 | Q33: 0.9549819 | R33: 0.9519807 | S33: 0.75435357 | T33: 34.142959 | U33: 2.3478923 | V33: 2.5151529 | W33: 2.4138873
B34: arr/nomort = c(1) + c(2) * log(pedip_unadj_pedy(-1)) + c(3) * upilo(-2) + c(4) * pinsolv_popw(-1) + c(5) * rrh(-1) | P34: 13 | Q34: 0.95386652 | R34: 0.95073883 | S34: 0.76950361 | T34: 34.936012 | U34: 2.3887621 | V34: 2.5574249 | W34: 2.4552069
B35: arr/nomort = c(1) + c(2) * log(pedip_unadj_pedy(-1)) + c(3) * upilo(-2) + c(4) * pinsolv_popw(-2) + c(5) * rrh(-2) | P35: 14 | Q35: 0.95045896 | R35: 0.94710025 | S35: 0.79741633 | T35: 37.516496 | U35: 2.4600247 | V35: 2.6286874 | W35: 2.5264695
B36: arr/nomort = c(1) + c(2) * log(pedip_unadj_pedy(-2)) + c(3) * upilo(-2) + c(4) * pinsolv_popw(-2) + c(5) * rrh(-2) | P36: 15 | Q36: 0.94928193 | R36: 0.94584341 | S36: 0.80683356 | T36: 38.407843 | U36: 2.4835057 | V36: 2.6521684 | W36: 2.5499504
A37: * | B37: arr/nomort = c(1) + c(2) * log(pedip_unadj_pedy(-1)) + c(3) * upilo(-1) + c(4) * pinsolv(-1) + c(5) * rrh(-1) | P37: 16 | Q37: 0.95592001 | R37: 0.95298134 | S37: 0.74645247 | T37: 33.431477 | U37: 2.3268338 | V37: 2.4940944 | W37: 2.3928288
A39: * | B39: arr/nomort = c(1) + c(2) * log(pedip_unadj_pedy(-1)) + c(3) * upilo(-1) + c(4) * rrh(-1) | P39: 17 | Q39: 0.94205151 | R39: 0.93920158 | S39: 0.84881524 | T39: 43.949726 | U39: 2.5696131 | V39: 2.7034216 | W39: 2.6224091
A40: * | B40: arr/nomort = c(1) + c(2) * log(pedip_unadj_pedy(-1)) + c(3) * upilo(-2) + c(4) * rrh(-1) | P40: 18 | Q40: 0.93991231 | R40: 0.93690793 | S40: 0.87085469 | T40: 45.503273 | U40: 2.6217782 | V40: 2.7567084 | W40: 2.6749341
B41: arr/nomort = c(1) + c(2) * log(pedip_unadj_pedy(-1)) + c(3) * upilo(-2) + c(4) * rrh(-2) | P41: 19 | Q41: 0.93718986 | R41: 0.93404935 | S41: 0.89036452 | T41: 47.564939 | U41: 2.6660899 | V41: 2.8010201 | W41: 2.7192457
A42: * | B42: arr/nomort = c(1) + c(2) * log(pedip_unadj_pedy(-1)) + c(3) * upilo(-1) + c(4) * mrtpe_mvh(-1) + c(5) * rrh(-1) | P42: 20 | Q42: 0.94298727 | R42: 0.93918642 | S42: 0.84892105 | T42: 43.240017 | U42: 2.5841023 | V42: 2.7513629 | W42: 2.6500973
B44: arr/nomort = c(1) + c(2) * log(pedip_unadj_pedy(-1)) + c(3) * upilo(-1) + c(4) * rbm(-1) | P44: 21 | Q44: 0.92921076 | R44: 0.92572932 | S44: 0.93815744 | T44: 53.688502 | U44: 2.7697656 | V44: 2.903574 | W44: 2.8225616
B45: arr/nomort = c(1) + c(2) * log(pedip_unadj_pedy(-1)) + c(3) * upilo(-2) + c(4) * rbm(-1) | P45: 22 | Q45: 0.93486561 | R45: 0.93160889 | S45: 0.90668853 | T45: 49.325045 | U45: 2.7024259 | V45: 2.8373561 | W45: 2.7555818
B46: arr/nomort = c(1) + c(2) * log(pedip_unadj_pedy(-1)) + c(3) * upilo(-2) + c(4) * rbm(-2) | P46: 23 | Q46: 0.90894113 | R46: 0.90438819 | S46: 1.0720476 | T46: 68.957169 | U46: 3.0374796 | V46: 3.1724097 | W46: 3.0906354
B47: arr/nomort = c(1) + c(2) * log(pedip_unadj_pedy(-1)) + c(3) * upilo(-1) + c(4) * mrtpe_mvh(-1) + c(5) * rbm(-1) | P47: 24 | Q47: 0.93400029 | R47: 0.92960031 | S47: 0.91338193 | T47: 50.055993 | U47: 2.7304782 | V47: 2.8977388 | W47: 2.7964732
B49: arr/nomort = c(1) + c(2) * log(pedip_unadj_pedy(-1)) + c(3) * upilo(-1) + c(4) * rrh(-1) + c(5) * hhliaby(-1)
Q55: R2 | R55: Adj R2 | S55: SE | T55: RSS | U55: AIC | V55: SBC | W55: HQN
B56: log(arr_nomort) = c(1) + c(2) * log(pedip_unadj_pedy(-1)) + c(3) * upilo_1(-1) + c(4) * rrh_1(-1) | Q56: 0.78342012 | R56: 0.77767021 | S56: 0.20731925 | T56: 4.8568836 | U56: -0.2755238 | V56: -0.18109051 | W56: -0.23718505
B57: log(arr_nomort) = c(1) + c(2) * log(pedip_unadj_pedy(-1)) + c(3) * upilo_1(-1) + c(4) * rbm_1(-1) | Q57: 0.91247221 | R57: 0.91014846 | S57: 0.1317964 | T57: 1.962843 | U57: -1.1815269 | V57: -1.0870936 | W57: -1.1431881
A58: x | B58: log(arr_nomort) = c(1) + c(2) * log(pedip_unadj_pedy(-1)) + c(3) * upilo_1(-1) + c(4) * rbm_1(-1) + c(5) * log(mrtpe_mvh(-1)) | Q58: 0.93275548 | R58: 0.93035389 | S58: 0.11603506 | T58: 1.5079831 | U58: -1.4280537 | V58: -1.3100121 | W58: -1.3801303
B59: log(arr_nomort) = c(1) + c(2) * log(pedip_unadj_pedy(-1)) + c(3) * upilo_1(-1) + c(4) * upilo_1(-2) + c(5) * rbm_1(-1) + c(6) * log(mrtpe_mvh(-1)) | Q59: 0.93475555 | R59: 0.93178989 | S59: 0.11143887 | T59: 1.3660483 | U59: -1.5003427 | V59: -1.3579156 | W59: -1.4425254
B60: log(arr_nomort) = c(1) + c(2) * log(pedip_unadj_pedy(-1)) + c(3) * log(pedip_unadj_pedy(-2)) + c(4) * upilo_1(-1) + c(5) * rbm_1(-1) + c(6) * log(mrtpe_mvh(-1)) | Q60: 0.92940151 | R60: 0.92619248 | S60: 0.11592113 | T60: 1.4781479 | U60: -1.4214749 | V60: -1.2790479 | W60: -1.3636577
B62: log(arr_nomort) = c(1) + c(2) * log(pedip_unadj_pedy(-1)) + c(3) * upilo_1(-1) + c(4) * rrh_1(-1) + c(5) * log(mrtpe_mvh(-1)) | Q62: 0.85893736 | R62: 0.85389941 | S62: 0.16806094 | T62: 3.1633817 | U62: -0.68718518 | V62: -0.56914356 | W62: -0.63926174 | Y62: (bad coeff)
B64: log(arr_nomort) = c(1) + c(2) * log(pedip_unadj_pedy(-1)) + 2 * upilo_1(-1) + c(4) * rrh_1(-1) + c(5) * log(mrtpe_mvh(-1))
B66: log(arr_nomort) = c(1) -0.7 * log(pedip_unadj_pedy(-1)) + 2 * upilo_1(-1) + c(4) * rrh_1(-1) + c(5) * log(mrtpe_mvh(-1))
B68: log(arr_nomort) = c(1) + c(2) * log(pedip_unadj_pedy(-1)) + c(3) * upilo_1(-1) + c(4) * rbm_1(-1)

Sheet Data >>>

Sheet Series construction
A1: Very old discontinued Haver UKF data >>> | J1: Historical interpolations >>> | V1: 2008-2015 UKF backseries from client >>> | AA1: Splicing history together via changes >>> | AF1: Splicing total history with new UKF haver data >>>
B3: Arrears | G3: Repossessions | J3: Arrears | R3: Repossessions
A4: 19901 !Q | B4: UNMARP22@UK | C4: UNMARP24@UK | D4: UNMARP26@UK | E4: UNMARP28@UK | G4: UNMARP44@UK
A5: .DESC | B5: UK: CML: No of Mortgages between 2.5% & 5% in Arrears DISC(NSA EOPNumber) | C5: UK: CML: No of Mortgages between 5% & 7.5% in Arrears DISC(NSA EOPNumber) | D5: UK: CML: No of Mortgages btw 7.5% & 10% in Arrears DISC(NSA EOP Number) | E5: UK: CML: Number of Mortgages 10% or Over in Arrears DISC(NSA,EOP, Number) | G5: UK: CML: Number of Properties in Possession DISC(NSA, EOP, Number) | J5: Arrears (2.5% - 5%) | K5: Arrears (5% - 7.5%) | L5: Arrears (7.5% - 10%) | M5: Arrears (10+%) | N5: TOTAL (calcs) | O5: CHANGES (calcs) | R5: Calc repo | S5: CHANGES | W5: Homeowner + BTL arrears (over 2.5% of balance) | X5: Mortgage repossessions (homeowner + BTL) | AB5: Note: red = discontinued haver series (pre-2008, blue = old client data (2008-2015) | AG5: Note: red = discontinued haver series (pre-2008, blue = old client data (2008-2015), green = new haver data (2015-current)
A6: .T1 | B6: Q4-1994 | C6: Q2-1993 | D6: Q2-1993 | E6: Q2-1993 | G6: Q4-1990 | AB6: ARR | AC6: REPO | AG6: ARR | AH6: REPO | AJ6: ARR/NOMORT | AK6: REPO/NOMORT
A7: .TN | B7: Q3-2008 | C7: Q3-2008 | D7: Q3-2008 | E7: Q3-2008 | G7: Q3-2008 | V7: Date | AA7: Date | AF7: Date
A8: .LSOURCE | B8: Discontinued | C8: Discontinued | D8: Discontinued | E8: Discontinued | G8: Discontinued
A9: .DTLM | B9: Nov-21-2008 10:42 | C9: Nov-21-2008 10:42 | D9: Nov-21-2008 10:42 | E9: Nov-21-2008 10:42 | G9: Nov-21-2008 10:42
A10: 19901 | B10: #N/A | C10: #N/A | D10: #N/A | E10: #N/A | G10: #N/A | J10: =NA() -> #N/A | K10: =NA() -> #N/A | L10: =NA() -> #N/A | M10: =NA() -> #N/A | N10: =SUM(J10:M10) -> #N/A | R10: =NA() -> #N/A | V10: ='Eviews input'!A2 -> 39479 | W10: ='Eviews input'!B2 -> 127000 | X10: ='Eviews input'!C2 -> 15600 | AA10: 32905 | AB10: =NA() -> #N/A | AC10: =NA() -> #N/A | AF10: 32905 | AG10: =NA() -> #N/A | AH10: =NA() -> #N/A | AJ10: =AG10/(DataQ!C75*1000) -> #N/A | AK10: =AH10/(DataQ!D75*1000) -> #N/A
A11: 19902 | B11: #N/A | C11: #N/A | D11: #N/A | E11: #N/A | G11: #N/A | J11: =NA() -> #N/A | K11: =NA() -> #N/A | L11: =NA() -> #N/A | M11: =NA() -> #N/A | N11: =SUM(J11:M11) -> #N/A | R11: =NA() -> #N/A | V11: ='Eviews input'!A3 -> 39569 | W11: ='Eviews input'!B3 -> 139700 | X11: ='Eviews input'!C3 -> 18700 | AA11: 32994 | AB11: =NA() -> #N/A | AC11: =NA() -> #N/A | AF11: 32994 | AG11: =NA() -> #N/A | AH11: =NA() -> #N/A | AJ11: =AG11/(DataQ!C76*1000) -> #N/A | AK11: =AH11/(DataQ!D76*1000) -> #N/A
A12: 19903 | B12: #N/A | C12: #N/A | D12: #N/A | E12: #N/A | G12: #N/A | J12: =NA() -> #N/A | K12: =NA() -> #N/A | L12: =NA() -> #N/A | M12: =NA() -> #N/A | N12: =SUM(J12:M12) -> #N/A | R12: =NA() -> #N/A | V12: ='Eviews input'!A4 -> 39661 | W12: ='Eviews input'!B4 -> 150800 | X12: ='Eviews input'!C4 -> 22600 | AA12: 33086 | AB12: =NA() -> #N/A | AC12: =NA() -> #N/A | AF12: 33086 | AG12: =NA() -> #N/A | AH12: =NA() -> #N/A | AJ12: =AG12/(DataQ!C77*1000) -> #N/A | AK12: =AH12/(DataQ!D77*1000) -> #N/A
A13: 19904 | B13: #N/A | C13: #N/A | D13: #N/A | E13: #N/A | G13: 36200 | J13: =NA() -> #N/A | K13: =NA() -> #N/A | L13: =NA() -> #N/A | M13: =NA() -> #N/A | N13: =SUM(J13:M13) -> #N/A | R13: =G13 -> 36200 | S13: =R14-R13 -> 8650 | V13: ='Eviews input'!A5 -> 39753 | W13: ='Eviews input'!B5 -> 182600 | X13: ='Eviews input'!C5 -> 22700 | AA13: 33178 | AB13: =NA() -> #N/A | AC13: =AC14-(R14-R13) -> 36100 | AF13: 33178 | AG13: =NA() -> #N/A | AH13: =AC13 -> 36100 | AJ13: =AG13/(DataQ!C78*1000) -> #N/A | AK13: =AH13/(DataQ!D78*1000) -> 0.0031413157
A14: 19911 | B14: #N/A | C14: #N/A | D14: #N/A | E14: #N/A | G14: #N/A | J14: =NA() -> #N/A | K14: =NA() -> #N/A | L14: =NA() -> #N/A | M14: =NA() -> #N/A | N14: =SUM(J14:M14) -> #N/A | R14: =R13+0.5*(R15-R13) -> 44850 | S14: =R15-R14 -> 8650 | V14: ='Eviews input'!A6 -> 39845 | W14: ='Eviews input'!B6 -> 209600 | X14: ='Eviews input'!C6 -> 24400 | AA14: 33270 | AB14: =NA() -> #N/A | AC14: =AC15-(R15-R14) -> 44750 | AF14: 33270 | AG14: =NA() -> #N/A | AH14: =AC14 -> 44750 | AJ14: =AG14/(DataQ!C79*1000) -> #N/A | AK14: =AH14/(DataQ!D79*1000) -> 0.0039069321
A15: 19912 | B15: #N/A | C15: #N/A | D15: #N/A | E15: #N/A | G15: 53500 | J15: =NA() -> #N/A | K15: =NA() -> #N/A | L15: =NA() -> #N/A | M15: =NA() -> #N/A | N15: =SUM(J15:M15) -> #N/A | R15: =G15 -> 53500 | S15: =R16-R15 -> 6950 | V15: ='Eviews input'!A7 -> 39934 | W15: ='Eviews input'!B7 -> 216400 | X15: ='Eviews input'!C7 -> 21900 | AA15: 33359 | AB15: =NA() -> #N/A | AC15: =AC16-(R16-R15) -> 53400 | AF15: 33359 | AG15: =NA() -> #N/A | AH15: =AC15 -> 53400 | AJ15: =AG15/(DataQ!C80*1000) -> #N/A | AK15: =AH15/(DataQ!D80*1000) -> 0.0049476513
A16: 19913 | B16: #N/A | C16: #N/A | D16: #N/A | E16: #N/A | G16: #N/A | J16: =NA() -> #N/A | K16: =NA() -> #N/A | L16: =NA() -> #N/A | M16: =NA() -> #N/A | N16: =SUM(J16:M16) -> #N/A | R16: =R15+0.5*(R17-R15) -> 60450 | S16: =R17-R16 -> 6950 | V16: ='Eviews input'!A8 -> 40026 | W16: ='Eviews input'!B8 -> 207200 | X16: ='Eviews input'!C8 -> 19300 | AA16: 33451 | AB16: =NA() -> #N/A | AC16: =AC17-(R17-R16) -> 60350 | AF16: 33451 | AG16: =NA() -> #N/A | AH16: =AC16 -> 60350 | AJ16: =AG16/(DataQ!C81*1000) -> #N/A | AK16: =AH16/(DataQ!D81*1000) -> 0.0058872305
A17: 19914 | B17: #N/A | C17: #N/A | D17: #N/A | E17: #N/A | G17: 67400 | J17: =NA() -> #N/A | K17: =NA() -> #N/A | L17: =NA() -> #N/A | M17: =NA() -> #N/A | N17: =SUM(J17:M17) -> #N/A | R17: =G17 -> 67400 | S17: =R18-R17 -> 550 | V17: ='Eviews input'!A9 -> 40118 | W17: ='Eviews input'!B9 -> 199600 | X17: ='Eviews input'!C9 -> 16200 | AA17: 33543 | AB17: =NA() -> #N/A | AC17: =AC18-(R18-R17) -> 67300 | AF17: 33543 | AG17: =NA() -> #N/A | AH17: =AC17 -> 67300 | AJ17: =AG17/(DataQ!C82*1000) -> #N/A | AK17: =AH17/(DataQ!D82*1000) -> 0.0067536377
A18: 19921 | B18: #N/A | C18: #N/A | D18: #N/A | E18: #N/A | G18: #N/A | J18: =NA() -> #N/A | K18: =NA() -> #N/A | L18: =NA() -> #N/A | M18: =NA() -> #N/A | N18: =SUM(J18:M18) -> #N/A | R18: =R17+0.5*(R19-R17) -> 67950 | S18: =R19-R18 -> 550 | V18: ='Eviews input'!A10 -> 40210 | W18: ='Eviews input'!B10 -> 196500 | X18: ='Eviews input'!C10 -> 15900 | AA18: 33635 | AB18: =NA() -> #N/A | AC18: =AC19-(R19-R18) -> 67850 | AF18: 33635 | AG18: =NA() -> #N/A | AH18: =AC18 -> 67850 | AJ18: =AG18/(DataQ!C83*1000) -> #N/A | AK18: =AH18/(DataQ!D83*1000) -> 0.0061275174
A19: 19922 | B19: #N/A | C19: #N/A | D19: #N/A | E19: #N/A | G19: 68500 | J19: =NA() -> #N/A | K19: =NA() -> #N/A | L19: =NA() -> #N/A | M19: =NA() -> #N/A | N19: =SUM(J19:M19) -> #N/A | R19: =G19 -> 68500 | S19: =R20-R19 -> -1750 | V19: ='Eviews input'!A11 -> 40299 | W19: ='Eviews input'!B11 -> 185500 | X19: ='Eviews input'!C11 -> 15200 | AA19: 33725 | AB19: =NA() -> #N/A | AC19: =AC20-(R20-R19) -> 68400 | AF19: 33725 | AG19: =NA() -> #N/A | AH19: =AC19 -> 68400 | AJ19: =AG19/(DataQ!C84*1000) -> #N/A | AK19: =AH19/(DataQ!D84*1000) -> 0.0067843682
A20: 19923 | B20: #N/A | C20: #N/A | D20: #N/A | E20: #N/A | G20: #N/A | J20: =NA() -> #N/A | K20: =NA() -> #N/A | L20: =NA() -> #N/A | M20: =NA() -> #N/A | N20: =SUM(J20:M20) -> #N/A | R20: =R19+0.5*(R21-R19) -> 66750 | S20: =R21-R20 -> -1750 | V20: ='Eviews input'!A12 -> 40391 | W20: ='Eviews input'!B12 -> 179800 | X20: ='Eviews input'!C12 -> 14700 | AA20: 33817 | AB20: =NA() -> #N/A | AC20: =AC21-(R21-R20) -> 66650 | AF20: 33817 | AG20: =NA() -> #N/A | AH20: =AC20 -> 66650 | AJ20: =AG20/(DataQ!C85*1000) -> #N/A | AK20: =AH20/(DataQ!D85*1000) -> 0.0068839083
A21: 19924 | B21: #N/A | C21: #N/A | D21: #N/A | E21: #N/A | G21: 65000 | J21: =NA() -> #N/A | K21: =NA() -> #N/A | L21: =NA() -> #N/A | M21: =NA() -> #N/A | N21: =SUM(J21:M21) -> #N/A | R21: =G21 -> 65000 | S21: =R22-R21 -> -5350 | V21: ='Eviews input'!A13 -> 40483 | W21: ='Eviews input'!B13 -> 175800 | X21: ='Eviews input'!C13 -> 13700 | AA21: 33909 | AB21: =NA() -> #N/A | AC21: =AC22-(R22-R21) -> 64900 | AF21: 33909 | AG21: =NA() -> #N/A | AH21: =AC21 -> 64900 | AJ21: =AG21/(DataQ!C86*1000) -> #N/A | AK21: =AH21/(DataQ!D86*1000) -> 0.0076932195
A22: 19931 | B22: #N/A | C22: #N/A | D22: #N/A | E22: #N/A | G22: #N/A | J22: =NA() -> #N/A | K22: =NA() -> #N/A | L22: =NA() -> #N/A | M22: =NA() -> #N/A | N22: =SUM(J22:M22) -> #N/A | R22: =R21+0.5*(R23-R21) -> 59650 | S22: =R23-R22 -> -5350 | V22: ='Eviews input'!A14 -> 40575 | W22: ='Eviews input'!B14 -> 171900 | X22: ='Eviews input'!C14 -> 14200 | AA22: 34001 | AB22: =NA() -> #N/A | AC22: =AC23-(R23-R22) -> 59550 | AF22: 34001 | AG22: =NA() -> #N/A | AH22: =AC22 -> 59550 | AJ22: =AG22/(DataQ!C87*1000) -> #N/A | AK22: =AH22/(DataQ!D87*1000) -> 0.0078895072
A23: 19932 | B23: #N/A | C23: 121200 | D23: 78100 | E23: 177700 | G23: 54300 | J23: =NA() -> #N/A | K23: =C23 -> 121200 | L23: =D23 -> 78100 | M23: =E23 -> 177700 | N23: =SUM(J23:M23) -> #N/A | R23: =G23 -> 54300 | S23: =R24-R23 -> -7200 | V23: ='Eviews input'!A15 -> 40664 | W23: ='Eviews input'!B15 -> 169200 | X23: ='Eviews input'!C15 -> 14500 | AA23: 34090 | AB23: =NA() -> #N/A | AC23: =AC24-(R24-R23) -> 54200 | AF23: 34090 | AG23: =NA() -> #N/A | AH23: =AC23 -> 54200 | AJ23: =AG23/(DataQ!C88*1000) -> #N/A | AK23: =AH23/(DataQ!D88*1000) -> 0.0074003277
A24: 19933 | B24: #N/A | C24: #N/A | D24: #N/A | E24: #N/A | G24: #N/A | J24: =NA() -> #N/A | K24: =K23+0.5*(K25-K23) -> 114400 | L24: =L23+0.5*(L25-L23) -> 73950 | M24: =M23+0.5*(M25-M23) -> 171850 | N24: =SUM(J24:M24) -> #N/A | R24: =R23+0.5*(R25-R23) -> 47100 | S24: =R25-R24 -> -7200 | V24: ='Eviews input'!A16 -> 40756 | W24: ='Eviews input'!B16 -> 165300 | X24: ='Eviews input'!C16 -> 14700 | AA24: 34182 | AB24: =NA() -> #N/A | AC24: =AC25-(R25-R24) -> 47000 | AF24: 34182 | AG24: =NA() -> #N/A | AH24: =AC24 -> 47000 | AJ24: =AG24/(DataQ!C89*1000) -> #N/A | AK24: =AH24/(DataQ!D89*1000) -> 0.0063772049
A25: 19934 | B25: #N/A | C25: 107600 | D25: 69800 | E25: 166000 | G25: 39900 | J25: =NA() -> #N/A | K25: =C25 -> 107600 | L25: =D25 -> 69800 | M25: =E25 -> 166000 | N25: =SUM(J25:M25) -> #N/A | R25: =G25 -> 39900 | S25: =R26-R25 -> -3350 | V25: ='Eviews input'!A17 -> 40848 | W25: ='Eviews input'!B17 -> 161400 | X25: ='Eviews input'!C17 -> 13900 | AA25: 34274 | AB25: =NA() -> #N/A | AC25: =AC26-(R26-R25) -> 39800 | AF25: 34274 | AG25: =NA() -> #N/A | AH25: =AC25 -> 39800 | AJ25: =AG25/(DataQ!C90*1000) -> #N/A | AK25: =AH25/(DataQ!D90*1000) -> 0.0054260395
A26: 19941 | B26: #N/A | C26: #N/A | D26: #N/A | E26: #N/A | G26: #N/A | J26: =NA() -> #N/A | K26: =K25+0.5*(K27-K25) -> 102750 | L26: =L25+0.5*(L27-L25) -> 66350 | M26: =M25+0.5*(M27-M25) -> 158450 | N26: =SUM(J26:M26) -> #N/A | R26: =R25+0.5*(R27-R25) -> 36550 | S26: =R27-R26 -> -3350 | V26: ='Eviews input'!A18 -> 40940 | W26: ='Eviews input'!B18 -> 159100 | X26: ='Eviews input'!C18 -> 13900 | AA26: 34366 | AB26: =NA() -> #N/A | AC26: =AC27-(R27-R26) -> 36450 | AF26: 34366 | AG26: =NA() -> #N/A | AH26: =AC26 -> 36450 | AJ26: =AG26/(DataQ!C91*1000) -> #N/A | AK26: =AH26/(DataQ!D91*1000) -> 0.0050020585
A27: 19942 | B27: #N/A | C27: 97900 | D27: 62900 | E27: 150900 | G27: 33200 | J27: =NA() -> #N/A | K27: =C27 -> 97900 | L27: =D27 -> 62900 | M27: =E27 -> 150900 | N27: =SUM(J27:M27) -> #N/A | R27: =G27 -> 33200 | S27: =R28-R27 -> -1900 | V27: ='Eviews input'!A19 -> 41030 | W27: ='Eviews input'!B19 -> 158700 | X27: ='Eviews input'!C19 -> 13500 | AA27: 34455 | AB27: =NA() -> #N/A | AC27: =AC28-(R28-R27) -> 33100 | AF27: 34455 | AG27: =NA() -> #N/A | AH27: =AC27 -> 33100 | AJ27: =AG27/(DataQ!C92*1000) -> #N/A | AK27: =AH27/(DataQ!D92*1000) -> 0.0042864543
A28: 19943 | B28: #N/A | C28: #N/A | D28: #N/A | E28: #N/A | G28: #N/A | J28: =NA() -> #N/A | K28: =K27+0.5*(K29-K27) -> 90300 | L28: =L27+0.5*(L29-L27) -> 56250 | M28: =M27+0.5*(M29-M27) -> 133600 | R28: =R27+0.5*(R29-R27) -> 31300 | S28: =R29-R28 -> -1900 | V28: ='Eviews input'!A20 -> 41122 | W28: ='Eviews input'!B20 -> 159100 | X28: ='Eviews input'!C20 -> 13000 | AA28: 34547 | AB28: =NA() -> #N/A | AC28: =AC29-(R29-R28) -> 31200 | AF28: 34547 | AG28: =NA() -> #N/A | AH28: =AC28 -> 31200 | AJ28: =AG28/(DataQ!C93*1000) -> #N/A | AK28: =AH28/(DataQ!D93*1000) -> 0.0041677799
A29: 19944 | B29: 176600 | C29: 82700 | D29: 49600 | E29: 116300 | G29: 29400 | J29: =B29 -> 176600 | K29: =C29 -> 82700 | L29: =D29 -> 49600 | M29: =E29 -> 116300 | N29: =SUM(J29:M29) -> 425200 | O29: =N30-N29 -> 2300 | R29: =G29 -> 29400 | S29: =R30-R29 -> 200 | V29: ='Eviews input'!A21 -> 41214 | W29: ='Eviews input'!B21 -> 157900 | X29: ='Eviews input'!C21 -> 11500 | AA29: 34639 | AB29: =AB30-(N30-N29) -> 423600 | AC29: =AC30-(R30-R29) -> 29300 | AF29: 34639 | AG29: =AB29 -> 423600 | AH29: =AC29 -> 29300 | AJ29: =AG29/(DataQ!C94*1000) -> 0.040691643 | AK29: =AH29/(DataQ!D94*1000) -> 0.0037953368 | AM29: =AG29/(DataQ!C94) -> 40.691643
A30: 19951 | B30: #N/A | C30: #N/A | D30: #N/A | E30: #N/A | G30: #N/A | J30: =J29+0.5*(J31-J29) -> 181150 | K30: =K29+0.5*(K31-K29) -> 82500 | L30: =L29+0.5*(L31-L29) -> 50750 | M30: =M29+0.5*(M31-M29) -> 113100 | N30: =SUM(J30:M30) -> 427500 | O30: =N31-N30 -> 2300 | R30: =R29+0.5*(R31-R29) -> 29600 | S30: =R31-R30 -> 200 | V30: ='Eviews input'!A22 -> 41306 | W30: ='Eviews input'!B22 -> 159600 | X30: ='Eviews input'!C22 -> 11100 | AA30: 34731 | AB30: =AB31-(N31-N30) -> 425900 | AC30: =AC31-(R31-R30) -> 29500 | AF30: 34731 | AG30: =AB30 -> 425900 | AH30: =AC30 -> 29500 | AJ30: =AG30/(DataQ!C95*1000) -> 0.04084784 | AK30: =AH30/(DataQ!D95*1000) -> 0.0035615115 | AM30: =AG30/(DataQ!C95) -> 40.84784
A31: 19952 | B31: 185700 | C31: 82300 | D31: 51900 | E31: 109900 | G31: 29800 | J31: =B31 -> 185700 | K31: =C31 -> 82300 | L31: =D31 -> 51900 | M31: =E31 -> 109900 | N31: =SUM(J31:M31) -> 429800 | O31: =N32-N31 -> -16050 | R31: =G31 -> 29800 | S31: =R32-R31 -> -1300 | V31: ='Eviews input'!A23 -> 41395 | W31: ='Eviews input'!B23 -> 154900 | X31: ='Eviews input'!C23 -> 10300 | AA31: 34820 | AB31: =AB32-(N32-N31) -> 428200 | AC31: =AC32-(R32-R31) -> 29700 | AF31: 34820 | AG31: =AB31 -> 428200 | AH31: =AC31 -> 29700 | AJ31: =AG31/(DataQ!C96*1000) -> 0.041003543 | AK31: =AH31/(DataQ!D96*1000) -> 0.0034635569 | AM31: =AG31/(DataQ!C96) -> 41.003543
A32: 19953 | B32: #N/A | C32: #N/A | D32: #N/A | E32: #N/A | G32: #N/A | J32: =J31+0.5*(J33-J31) -> 180050 | K32: =K31+0.5*(K33-K31) -> 81100 | L32: =L31+0.5*(L33-L31) -> 48700 | M32: =M31+0.5*(M33-M31) -> 103900 | N32: =SUM(J32:M32) -> 413750 | O32: =N33-N32 -> -16050 | R32: =R31+0.5*(R33-R31) -> 28500 | S32: =R33-R32 -> -1300 | V32: ='Eviews input'!A24 -> 41487 | W32: ='Eviews input'!B24 -> 149400 | X32: ='Eviews input'!C24 -> 9900 | AA32: 34912 | AB32: =AB33-(N33-N32) -> 412150 | AC32: =AC33-(R33-R32) -> 28400 | AF32: 34912 | AG32: =AB32 -> 412150 | AH32: =AC32 -> 28400 | AJ32: =AG32/(DataQ!C97*1000) -> 0.039319786 | AK32: =AH32/(DataQ!D97*1000) -> 0.00337132 | AM32: =AG32/(DataQ!C97) -> 39.319786
A33: 19954 | B33: 174400 | C33: 79900 | D33: 45500 | E33: 97900 | G33: 27200 | J33: =B33 -> 174400 | K33: =C33 -> 79900 | L33: =D33 -> 45500 | M33: =E33 -> 97900 | N33: =SUM(J33:M33) -> 397700 | O33: =N34-N33 -> -23900 | R33: =G33 -> 27200 | S33: =R34-R33 -> -1600 | V33: ='Eviews input'!A25 -> 41579 | W33: ='Eviews input'!B25 -> 144600 | X33: ='Eviews input'!C25 -> 8400 | AA33: 35004 | AB33: =AB34-(N34-N33) -> 396100 | AC33: =AC34-(R34-R33) -> 27100 | AF33: 35004 | AG33: =AB33 -> 396100 | AH33: =AC33 -> 27100 | AJ33: =AG33/(DataQ!C98*1000) -> 0.037648512 | AK33: =AH33/(DataQ!D98*1000) -> 0.0033271946 | AM33: =AG33/(DataQ!C98) -> 37.648512
A34: 19961 | B34: #N/A | C34: #N/A | D34: #N/A | E34: #N/A | G34: #N/A | J34: =J33+0.5*(J35-J33) -> 164050 | K34: =K33+0.5*(K35-K33) -> 75100 | L34: =L33+0.5*(L35-L33) -> 42700 | M34: =M33+0.5*(M35-M33) -> 91950 | N34: =SUM(J34:M34) -> 373800 | O34: =N35-N34 -> -23900 | R34: =R33+0.5*(R35-R33) -> 25600 | S34: =R35-R34 -> -1600 | V34: ='Eviews input'!A26 -> 41671 | W34: ='Eviews input'!B26 -> 138200 | X34: ='Eviews input'!C26 -> 8500 | AA34: 35096 | AB34: =AB35-(N35-N34) -> 372200 | AC34: =AC35-(R35-R34) -> 25500 | AF34: 35096 | AG34: =AB34 -> 372200 | AH34: =AC34 -> 25500 | AJ34: =AG34/(DataQ!C99*1000) -> 0.035259568 | AK34: =AH34/(DataQ!D99*1000) -> 0.0031851112 | AM34: =AG34/(DataQ!C99) -> 35.259568
A35: 19962 | B35: 153700 | C35: 70300 | D35: 39900 | E35: 86000 | G35: 24000 | J35: =B35 -> 153700 | K35: =C35 -> 70300 | L35: =D35 -> 39900 | M35: =E35 -> 86000 | N35: =SUM(J35:M35) -> 349900 | O35: =N36-N35 -> -26550 | R35: =G35 -> 24000 | S35: =R36-R35 -> -3900 | V35: ='Eviews input'!A27 -> 41760 | W35: ='Eviews input'!B27 -> 129170 | X35: ='Eviews input'!C27 -> 7880 | AA35: 35186 | AB35: =AB36-(N36-N35) -> 348300 | AC35: =AC36-(R36-R35) -> 23900 | AF35: 35186 | AG35: =AB35 -> 348300 | AH35: =AC35 -> 23900 | AJ35: =AG35/(DataQ!C100*1000) -> 0.032886413 | AK35: =AH35/(DataQ!D100*1000) -> 0.0030755373 | AM35: =AG35/(DataQ!C100) -> 32.886413
A36: 19963 | B36: #N/A | C36: #N/A | D36: #N/A | E36: #N/A | G36: #N/A | J36: =J35+0.5*(J37-J35) -> 141700 | K36: =K35+0.5*(K37-K35) -> 64700 | L36: =L35+0.5*(L37-L35) -> 36600 | M36: =M35+0.5*(M37-M35) -> 80350 | N36: =SUM(J36:M36) -> 323350 | O36: =N37-N36 -> -26550 | R36: =R35+0.5*(R37-R35) -> 20100 | S36: =R37-R36 -> -3900 | V36: ='Eviews input'!A28 -> 41852 | W36: ='Eviews input'!B28 -> 122110 | X36: ='Eviews input'!C28 -> 7150 | AA36: 35278 | AB36: =AB37-(N37-N36) -> 321750 | AC36: =AC37-(R37-R36) -> 20000 | AF36: 35278 | AG36: =AB36 -> 321750 | AH36: =AC36 -> 20000 | AJ36: =AG36/(DataQ!C101*1000) -> 0.030313737 | AK36: =AH36/(DataQ!D101*1000) -> 0.0026364355 | AM36: =AG36/(DataQ!C101) -> 30.313737
A37: 19964 | B37: 129700 | C37: 59100 | D37: 33300 | E37: 74700 | G37: 16200 | J37: =B37 -> 129700 | K37: =C37 -> 59100 | L37: =D37 -> 33300 | M37: =E37 -> 74700 | N37: =SUM(J37:M37) -> 296800 | O37: =N38-N37 -> -15000 | R37: =G37 -> 16200 | S37: =R38-R37 -> -1050 | V37: ='Eviews input'!A29 -> 41944 | W37: ='Eviews input'!B29 -> 114410 | X37: ='Eviews input'!C29 -> 6170 | AA37: 35370 | AB37: =AB38-(N38-N37) -> 295200 | AC37: =AC38-(R38-R37) -> 16100 | AF37: 35370 | AG37: =AB37 -> 295200 | AH37: =AC37 -> 16100 | AJ37: =AG37/(DataQ!C102*1000) -> 0.027752186 | AK37: =AH37/(DataQ!D102*1000) -> 0.0021633969 | AM37: =AG37/(DataQ!C102) -> 27.752186
A38: 19971 | B38: #N/A | C38: #N/A | D38: #N/A | E38: #N/A | G38: #N/A | J38: =J37+0.5*(J39-J37) -> 125400 | K38: =K37+0.5*(K39-K37) -> 56200 | L38: =L37+0.5*(L39-L37) -> 30850 | M38: =M37+0.5*(M39-M37) -> 69350 | N38: =SUM(J38:M38) -> 281800 | O38: =N39-N38 -> -15000 | R38: =R37+0.5*(R39-R37) -> 15150 | S38: =R39-R38 -> -1050 | V38: ='Eviews input'!A30 -> 42036 | W38: ='Eviews input'!B30 -> 111190 | X38: ='Eviews input'!C30 -> 4880 | AA38: 35462 | AB38: =AB39-(N39-N38) -> 280200 | AC38: =AC39-(R39-R38) -> 15050 | AF38: 35462 | AG38: =AB38 -> 280200 | AH38: =AC38 -> 15050 | AJ38: =AG38/(DataQ!C103*1000) -> 0.026242098 | AK38: =AH38/(DataQ!D103*1000) -> 0.0019351935 | AM38: =AG38/(DataQ!C103) -> 26.242098
A39: 19972 | B39: 121100 | C39: 53300 | D39: 28400 | E39: 64000 | G39: 14100 | J39: =B39 -> 121100 | K39: =C39 -> 53300 | L39: =D39 -> 28400 | M39: =E39 -> 64000 | N39: =SUM(J39:M39) -> 266800 | O39: =N40-N39 -> -6450 | R39: =G39 -> 14100 | S39: =R40-R39 -> -100 | AA39: 35551 | AB39: =AB40-(N40-N39) -> 265200 | AC39: =AC40-(R40-R39) -> 14000 | AF39: 35551 | AG39: =AB39 -> 265200 | AH39: =AC39 -> 14000 | AJ39: =AG39/(DataQ!C104*1000) -> 0.024743422 | AK39: =AH39/(DataQ!D104*1000) -> 0.0017687934 | AM39: =AG39/(DataQ!C104) -> 24.743422
A40: 19973 | B40: #N/A | C40: #N/A | D40: #N/A | E40: #N/A | G40: #N/A | J40: =J39+0.5*(J41-J39) -> 119450 | K40: =K39+0.5*(K41-K39) -> 51350 | L40: =L39+0.5*(L41-L39) -> 27350 | M40: =M39+0.5*(M41-M39) -> 62200 | N40: =SUM(J40:M40) -> 260350 | O40: =N41-N40 -> -6450 | R40: =R39+0.5*(R41-R39) -> 14000 | S40: =R41-R40 -> -100 | AA40: 35643 | AB40: =AB41-(N41-N40) -> 258750 | AC40: =AC41-(R41-R40) -> 13900 | AF40: 35643 | AG40: =AB40 -> 258750 | AH40: =AC40 -> 13900 | AJ40: =AG40/(DataQ!C105*1000) -> 0.024119128 | AK40: =AH40/(DataQ!D105*1000) -> 0.0016228838 | AM40: =AG40/(DataQ!C105) -> 24.119128
A41: 19974 | B41: 117800 | C41: 49400 | D41: 26300 | E41: 60400 | G41: 13900 | J41: =B41 -> 117800 | K41: =C41 -> 49400 | L41: =D41 -> 26300 | M41: =E41 -> 60400 | N41: =SUM(J41:M41) -> 253900 | O41: =N42-N41 -> 3350 | R41: =G41 -> 13900 | S41: =R42-R41 -> 650 | AA41: 35735 | AB41: =AB42-(N42-N41) -> 252300 | AC41: =AC42-(R42-R41) -> 13800 | AF41: 35735 | AG41: =AB41 -> 252300 | AH41: =AC41 -> 13800 | AJ41: =AG41/(DataQ!C106*1000) -> 0.023495996 | AK41: =AH41/(DataQ!D106*1000) -> 0.0015040872 | AM41: =AG41/(DataQ!C106) -> 23.495996
A42: 19981 | B42: #N/A | C42: #N/A | D42: #N/A | E42: #N/A | G42: #N/A | J42: =J41+0.5*(J43-J41) -> 123150 | K42: =K41+0.5*(K43-K41) -> 50550 | L42: =L41+0.5*(L43-L41) -> 26250 | M42: =M41+0.5*(M43-M41) -> 57300 | N42: =SUM(J42:M42) -> 257250 | O42: =N43-N42 -> 3350 | R42: =R41+0.5*(R43-R41) -> 14550 | S42: =R43-R42 -> 650 | AA42: 35827 | AB42: =AB43-(N43-N42) -> 255650 | AC42: =AC43-(R43-R42) -> 14450 | AF42: 35827 | AG42: =AB42 -> 255650 | AH42: =AC42 -> 14450 | AJ42: =AG42/(DataQ!C107*1000) -> 0.023753775 | AK42: =AH42/(DataQ!D107*1000) -> 0.001667436 | AM42: =AG42/(DataQ!C107) -> 23.753775
A43: 19982 | B43: 128500 | C43: 51700 | D43: 26200 | E43: 54200 | G43: 15200 | J43: =B43 -> 128500 | K43: =C43 -> 51700 | L43: =D43 -> 26200 | M43: =E43 -> 54200 | N43: =SUM(J43:M43) -> 260600 | O43: =N44-N43 -> 200 | R43: =G43 -> 15200 | S43: =R44-R43 -> -650 | AA43: 35916 | AB43: =AB44-(N44-N43) -> 259000 | AC43: =AC44-(R44-R43) -> 15100 | AF43: 35916 | AG43: =AB43 -> 259000 | AH43: =AC43 -> 15100 | AJ43: =AG43/(DataQ!C108*1000) -> 0.024010383 | AK43: =AH43/(DataQ!D108*1000) -> 0.0016560649 | AM43: =AG43/(DataQ!C108) -> 24.010383
A44: 19983 | B44: #N/A | C44: #N/A | D44: #N/A | E44: #N/A | G44: #N/A | J44: =J43+0.5*(J45-J43) -> 129550 | K44: =K43+0.5*(K45-K43) -> 52250 | L44: =L43+0.5*(L45-L43) -> 25900 | M44: =M43+0.5*(M45-M43) -> 53100 | N44: =SUM(J44:M44) -> 260800 | O44: =N45-N44 -> 200 | R44: =R43+0.5*(R45-R43) -> 14550 | S44: =R45-R44 -> -650 | AA44: 36008 | AB44: =AB45-(N45-N44) -> 259200 | AC44: =AC45-(R45-R44) -> 14450 | AF44: 36008 | AG44: =AB44 -> 259200 | AH44: =AC44 -> 14450 | AJ44: =AG44/(DataQ!C109*1000) -> 0.023991114 | AK44: =AH44/(DataQ!D109*1000) -> 0.0014994293 | AM44: =AG44/(DataQ!C109) -> 23.991114
A45: 19984 | B45: 130600 | C45: 52800 | D45: 25600 | E45: 52000 | G45: 13900 | J45: =B45 -> 130600 | K45: =C45 -> 52800 | L45: =D45 -> 25600 | M45: =E45 -> 52000 | N45: =SUM(J45:M45) -> 261000 | O45: =N46-N45 -> -14300 | R45: =G45 -> 13900 | S45: =R46-R45 -> -400 | AA45: 36100 | AB45: =AB46-(N46-N45) -> 259400 | AC45: =AC46-(R46-R45) -> 13800 | AF45: 36100 | AG45: =AB45 -> 259400 | AH45: =AC45 -> 13800 | AJ45: =AG45/(DataQ!C110*1000) -> 0.023971906 | AK45: =AH45/(DataQ!D110*1000) -> 0.0014140793 | AM45: =AG45/(DataQ!C110) -> 23.971906
A46: 19991 | B46: #N/A | C46: #N/A | D46: #N/A | E46: #N/A | G46: #N/A | J46: =J45+0.5*(J47-J45) -> 122550 | K46: =K45+0.5*(K47-K45) -> 50200 | L46: =L45+0.5*(L47-L45) -> 24500 | M46: =M45+0.5*(M47-M45) -> 49450 | N46: =SUM(J46:M46) -> 246700 | O46: =N47-N46 -> -14300 | R46: =R45+0.5*(R47-R45) -> 13500 | S46: =R47-R46 -> -400 | AA46: 36192 | AB46: =AB47-(N47-N46) -> 245100 | AC46: =AC47-(R47-R46) -> 13400 | AF46: 36192 | AG46: =AB46 -> 245100 | AH46: =AC46 -> 13400 | AJ46: =AG46/(DataQ!C111*1000) -> 0.022566983 | AK46: =AH46/(DataQ!D111*1000) -> 0.0014696205 | AM46: =AG46/(DataQ!C111) -> 22.566983
A47: 19992 | B47: 114500 | C47: 47600 | D47: 23400 | E47: 46900 | G47: 13100 | J47: =B47 -> 114500 | K47: =C47 -> 47600 | L47: =D47 -> 23400 | M47: =E47 -> 46900 | N47: =SUM(J47:M47) -> 232400 | O47: =N48-N47 -> -12000 | R47: =G47 -> 13100 | S47: =R48-R47 -> -1150 | AA47: 36281 | AB47: =AB48-(N48-N47) -> 230800 | AC47: =AC48-(R48-R47) -> 13000 | AF47: 36281 | AG47: =AB47 -> 230800 | AH47: =AC47 -> 13000 | AJ47: =AG47/(DataQ!C112*1000) -> 0.02117237 | AK47: =AH47/(DataQ!D112*1000) -> 0.0014363054 | AM47: =AG47/(DataQ!C112) -> 21.17237
A48: 19993 | B48: #N/A | C48: #N/A | D48: #N/A | E48: #N/A | G48: #N/A | J48: =J47+0.5*(J49-J47) -> 109550 | K48: =K47+0.5*(K49-K47) -> 44750 | L48: =L47+0.5*(L49-L47) -> 21850 | M48: =M47+0.5*(M49-M47) -> 44250 | N48: =SUM(J48:M48) -> 220400 | O48: =N49-N48 -> -12000 | R48: =R47+0.5*(R49-R47) -> 11950 | S48: =R49-R48 -> -1150 | AA48: 36373 | AB48: =AB49-(N49-N48) -> 218800 | AC48: =AC49-(R49-R48) -> 11850 | AF48: 36373 | AG48: =AB48 -> 218800 | AH48: =AC48 -> 11850 | AJ48: =AG48/(DataQ!C113*1000) -> 0.019997258 | AK48: =AH48/(DataQ!D113*1000) -> 0.0014654959 | AM48: =AG48/(DataQ!C113) -> 19.997258
A49: 19994 | B49: 104600 | C49: 41900 | D49: 20300 | E49: 41600 | G49: 10800 | J49: =B49 -> 104600 | K49: =C49 -> 41900 | L49: =D49 -> 20300 | M49: =E49 -> 41600 | N49: =SUM(J49:M49) -> 208400 | O49: =N50-N49 -> -4000 | R49: =G49 -> 10800 | S49: =R50-R49 -> -800 | AA49: 36465 | AB49: =AB50-(N50-N49) -> 206800 | AC49: =AC50-(R50-R49) -> 10700 | AF49: 36465 | AG49: =AB49 -> 206800 | AH49: =AC49 -> 10700 | AJ49: =AG49/(DataQ!C114*1000) -> 0.018830814 | AK49: =AH49/(DataQ!D114*1000) -> 0.0011804943 | AM49: =AG49/(DataQ!C114) -> 18.830814
A50: 20001 | B50: #N/A | C50: #N/A | D50: #N/A | E50: #N/A | G50: #N/A | J50: =J49+0.5*(J51-J49) -> 104100 | K50: =K49+0.5*(K51-K49) -> 40450 | L50: =L49+0.5*(L51-L49) -> 19400 | M50: =M49+0.5*(M51-M49) -> 40450 | N50: =SUM(J50:M50) -> 204400 | O50: =N51-N50 -> -4000 | R50: =R49+0.5*(R51-R49) -> 10000 | S50: =R51-R50 -> -800 | AA50: 36557 | AB50: =AB51-(N51-N50) -> 202800 | AC50: =AC51-(R51-R50) -> 9900 | AF50: 36557 | AG50: =AB50 -> 202800 | AH50: =AC50 -> 9900 | AJ50: =AG50/(DataQ!C115*1000) -> 0.018328061 | AK50: =AH50/(DataQ!D115*1000) -> 0.00096181871 | AM50: =AG50/(DataQ!C115) -> 18.328061
A51: 20002 | B51: 103600 | C51: 39000 | D51: 18500 | E51: 39300 | G51: 9200 | J51: =B51 -> 103600 | K51: =C51 -> 39000 | L51: =D51 -> 18500 | M51: =E51 -> 39300 | N51: =SUM(J51:M51) -> 200400 | O51: =N52-N51 -> -16400 | R51: =G51 -> 9200 | S51: =R52-R51 -> -650 | AA51: 36647 | AB51: =AB52-(N52-N51) -> 198800 | AC51: =AC52-(R52-R51) -> 9100 | AF51: 36647 | AG51: =AB51 -> 198800 | AH51: =AC51 -> 9100 | AJ51: =AG51/(DataQ!C116*1000) -> 0.017832795 | AK51: =AH51/(DataQ!D116*1000) -> 0.00085102403 | AM51: =AG51/(DataQ!C116) -> 17.832795
A52: 20003 | B52: #N/A | C52: #N/A | D52: #N/A | E52: #N/A | G52: #N/A | J52: =J51+0.5*(J53-J51) -> 99450 | K52: =K51+0.5*(K53-K51) -> 35750 | L52: =L51+0.5*(L53-L51) -> 16550 | M52: =M51+0.5*(M53-M51) -> 32250 | N52: =SUM(J52:M52) -> 184000 | O52: =N53-N52 -> -16400 | R52: =R51+0.5*(R53-R51) -> 8550 | S52: =R53-R52 -> -650 | AA52: 36739 | AB52: =AB53-(N53-N52) -> 182400 | AC52: =AC53-(R53-R52) -> 8450 | AF52: 36739 | AG52: =AB52 -> 182400 | AH52: =AC52 -> 8450 | AJ52: =AG52/(DataQ!C117*1000) -> 0.016343354 | AK52: =AH52/(DataQ!D117*1000) -> 0.0007976213 | AM52: =AG52/(DataQ!C117) -> 16.343354
A53: 20004 | B53: 95300 | C53: 32500 | D53: 14600 | E53: 25200 | G53: 7900 | J53: =B53 -> 95300 | K53: =C53 -> 32500 | L53: =D53 -> 14600 | M53: =E53 -> 25200 | N53: =SUM(J53:M53) -> 167600 | O53: =N54-N53 -> -5050 | R53: =G53 -> 7900 | S53: =R54-R53 -> -300 | AA53: 36831 | AB53: =AB54-(N54-N53) -> 166000 | AC53: =AC54-(R54-R53) -> 7800 | AF53: 36831 | AG53: =AB53 -> 166000 | AH53: =AC53 -> 7800 | AJ53: =AG53/(DataQ!C118*1000) -> 0.014857245 | AK53: =AH53/(DataQ!D118*1000) -> 0.00072801941 | AM53: =AG53/(DataQ!C118) -> 14.857245
A54: 20011 | B54: #N/A | C54: #N/A | D54: #N/A | E54: #N/A | G54: #N/A | J54: =J53+0.5*(J55-J53) -> 92600 | K54: =K53+0.5*(K55-K53) -> 31600 | L54: =L53+0.5*(L55-L53) -> 14000 | M54: =M53+0.5*(M55-M53) -> 24350 | N54: =SUM(J54:M54) -> 162550 | O54: =N55-N54 -> -5050 | R54: =R53+0.5*(R55-R53) -> 7600 | S54: =R55-R54 -> -300 | AA54: 36923 | AB54: =AB55-(N55-N54) -> 160950 | AC54: =AC55-(R55-R54) -> 7500 | AF54: 36923 | AG54: =AB54 -> 160950 | AH54: =AC54 -> 7500 | AJ54: =AG54/(DataQ!C119*1000) -> 0.014388521 | AK54: =AH54/(DataQ!D119*1000) -> 0.0006863104 | AM54: =AG54/(DataQ!C119) -> 14.388521
A55: 20012 | B55: 89900 | C55: 30700 | D55: 13400 | E55: 23500 | G55: 7300 | J55: =B55 -> 89900 | K55: =C55 -> 30700 | L55: =D55 -> 13400 | M55: =E55 -> 23500 | N55: =SUM(J55:M55) -> 157500 | O55: =N56-N55 -> -8650 | R55: =G55 -> 7300 | S55: =R56-R55 -> -850 | AA55: 37012 | AB55: =AB56-(N56-N55) -> 155900 | AC55: =AC56-(R56-R55) -> 7200 | AF55: 37012 | AG55: =AB55 -> 155900 | AH55: =AC55 -> 7200 | AJ55: =AG55/(DataQ!C120*1000) -> 0.013920886 | AK55: =AH55/(DataQ!D120*1000) -> 0.00069117788 | AM55: =AG55/(DataQ!C120) -> 13.920886
A56: 20013 | B56: #N/A | C56: #N/A | D56: #N/A | E56: #N/A | G56: #N/A | J56: =J55+0.5*(J57-J55) -> 84550 | K56: =K55+0.5*(K57-K55) -> 29100 | L56: =L55+0.5*(L57-L55) -> 12600 | M56: =M55+0.5*(M57-M55) -> 22600 | N56: =SUM(J56:M56) -> 148850 | O56: =N57-N56 -> -8650 | R56: =R55+0.5*(R57-R55) -> 6450 | S56: =R57-R56 -> -850 | AA56: 37104 | AB56: =AB57-(N57-N56) -> 147250 | AC56: =AC57-(R57-R56) -> 6350 | AF56: 37104 | AG56: =AB56 -> 147250 | AH56: =AC56 -> 6350 | AJ56: =AG56/(DataQ!C121*1000) -> 0.013120378 | AK56: =AH56/(DataQ!D121*1000) -> 0.00064134936 | AM56: =AG56/(DataQ!C121) -> 13.120378
A57: 20014 | B57: 79200 | C57: 27500 | D57: 11800 | E57: 21700 | G57: 5600 | J57: =B57 -> 79200 | K57: =C57 -> 27500 | L57: =D57 -> 11800 | M57: =E57 -> 21700 | N57: =SUM(J57:M57) -> 140200 | O57: =N58-N57 -> -10250 | R57: =G57 -> 5600 | S57: =R58-R57 -> -750 | AA57: 37196 | AB57: =AB58-(N58-N57) -> 138600 | AC57: =AC58-(R58-R57) -> 5500 | AF57: 37196 | AG57: =AB57 -> 138600 | AH57: =AC57 -> 5500 | AJ57: =AG57/(DataQ!C122*1000) -> 0.012323286 | AK57: =AH57/(DataQ!D122*1000) -> 0.00061902082 | AM57: =AG57/(DataQ!C122) -> 12.323286
A58: 20021 | B58: #N/A | C58: #N/A | D58: #N/A | E58: #N/A | G58: #N/A | J58: =J57+0.5*(J59-J57) -> 73100 | K58: =K57+0.5*(K59-K57) -> 25700 | L58: =L57+0.5*(L59-L57) -> 11050 | M58: =M57+0.5*(M59-M57) -> 20100 | N58: =SUM(J58:M58) -> 129950 | O58: =N59-N58 -> -10250 | R58: =R57+0.5*(R59-R57) -> 4850 | S58: =R59-R58 -> -750 | AA58: 37288 | AB58: =AB59-(N59-N58) -> 128350 | AC58: =AC59-(R59-R58) -> 4750 | AF58: 37288 | AG58: =AB58 -> 128350 | AH58: =AC58 -> 4750 | AJ58: =AG58/(DataQ!C123*1000) -> 0.011400275 | AK58: =AH58/(DataQ!D123*1000) -> 0.00053557335 | AM58: =AG58/(DataQ!C123) -> 11.400275
A59: 20022 | B59: 67000 | C59: 23900 | D59: 10300 | E59: 18500 | G59: 4100 | J59: =B59 -> 67000 | K59: =C59 -> 23900 | L59: =D59 -> 10300 | M59: =E59 -> 18500 | N59: =SUM(J59:M59) -> 119700 | O59: =N60-N59 -> -8250 | R59: =G59 -> 4100 | S59: =R60-R59 -> -650 | AA59: 37377 | AB59: =AB60-(N60-N59) -> 118100 | AC59: =AC60-(R60-R59) -> 4000 | AF59: 37377 | AG59: =AB59 -> 118100 | AH59: =AC59 -> 4000 | AJ59: =AG59/(DataQ!C124*1000) -> 0.010479148 | AK59: =AH59/(DataQ!D124*1000) -> 0.00043544524 | AM59: =AG59/(DataQ!C124) -> 10.479148
A60: 20023 | B60: #N/A | C60: #N/A | D60: #N/A | E60: #N/A | G60: #N/A | J60: =J59+0.5*(J61-J59) -> 62850 | K60: =K59+0.5*(K61-K59) -> 21650 | L60: =L59+0.5*(L61-L59) -> 9450 | M60: =M59+0.5*(M61-M59) -> 17500 | N60: =SUM(J60:M60) -> 111450 | O60: =N61-N60 -> -8250 | R60: =R59+0.5*(R61-R59) -> 3450 | S60: =R61-R60 -> -650 | AA60: 37469 | AB60: =AB61-(N61-N60) -> 109850 | AC60: =AC61-(R61-R60) -> 3350 | AF60: 37469 | AG60: =AB60 -> 109850 | AH60: =AC60 -> 3350 | AJ60: =AG60/(DataQ!C125*1000) -> 0.009706636 | AK60: =AH60/(DataQ!D125*1000) -> 0.00035680051 | AM60: =AG60/(DataQ!C125) -> 9.706636
A61: 20024 | B61: 58700 | C61: 19400 | D61: 8600 | E61: 16500 | G61: 2800 | J61: =B61 -> 58700 | K61: =C61 -> 19400 | L61: =D61 -> 8600 | M61: =E61 -> 16500 | N61: =SUM(J61:M61) -> 103200 | O61: =N62-N61 -> 350 | R61: =G61 -> 2800 | S61: =R62-R61 -> -50 | AA61: 37561 | AB61: =AB62-(N62-N61) -> 101600 | AC61: =AC62-(R62-R61) -> 2700 | AF61: 37561 | AG61: =AB61 -> 101600 | AH61: =AC61 -> 2700 | AJ61: =AG61/(DataQ!C126*1000) -> 0.0089405139 | AK61: =AH61/(DataQ!D126*1000) -> 0.00027930071 | AM61: =AG61/(DataQ!C126) -> 8.9405139
A62: 20031 | B62: #N/A | C62: #N/A | D62: #N/A | E62: #N/A | G62: #N/A | J62: =J61+0.5*(J63-J61) -> 58950 | K62: =K61+0.5*(K63-K61) -> 19900 | L62: =L61+0.5*(L63-L61) -> 8600 | M62: =M61+0.5*(M63-M61) -> 16100 | N62: =SUM(J62:M62) -> 103550 | O62: =N63-N62 -> 350 | R62: =R61+0.5*(R63-R61) -> 2750 | S62: =R63-R62 -> -50 | AA62: 37653 | AB62: =AB63-(N63-N62) -> 101950 | AC62: =AC63-(R63-R62) -> 2650 | AF62: 37653 | AG62: =AB62 -> 101950 | AH62: =AC62 -> 2650 | AJ62: =AG62/(DataQ!C127*1000) -> 0.0089500483 | AK62: =AH62/(DataQ!D127*1000) -> 0.00027087805 | AM62: =AG62/(DataQ!C127) -> 8.9500483
A63: 20032 | B63: 59200 | C63: 20400 | D63: 8600 | E63: 15700 | G63: 2700 | J63: =B63 -> 59200 | K63: =C63 -> 20400 | L63: =D63 -> 8600 | M63: =E63 -> 15700 | N63: =SUM(J63:M63) -> 103900 | O63: =N64-N63 -> -5050 | R63: =G63 -> 2700 | S63: =R64-R63 -> 0 | AA63: 37742 | AB63: =AB64-(N64-N63) -> 102300 | AC63: =AC64-(R64-R63) -> 2600 | AF63: 37742 | AG63: =AB63 -> 102300 | AH63: =AC63 -> 2600 | AJ63: =AG63/(DataQ!C128*1000) -> 0.0089595376 | AK63: =AH63/(DataQ!D128*1000) -> 0.0002684841 | AM63: =AG63/(DataQ!C128) -> 8.9595376
A64: 20033 | B64: #N/A | C64: #N/A | D64: #N/A | E64: #N/A | G64: #N/A | J64: =J63+0.5*(J65-J63) -> 56050 | K64: =K63+0.5*(K65-K63) -> 19350 | L64: =L63+0.5*(L65-L63) -> 8250 | M64: =M63+0.5*(M65-M63) -> 15200 | N64: =SUM(J64:M64) -> 98850 | O64: =N65-N64 -> -5050 | R64: =R63+0.5*(R65-R63) -> 2700 | S64: =R65-R64 -> 0 | AA64: 37834 | AB64: =AB65-(N65-N64) -> 97250 | AC64: =AC65-(R65-R64) -> 2600 | AF64: 37834 | AG64: =AB64 -> 97250 | AH64: =AC64 -> 2600 | AJ64: =AG64/(DataQ!C129*1000) -> 0.0085060789 | AK64: =AH64/(DataQ!D129*1000) -> 0.0002771855 | AM64: =AG64/(DataQ!C129) -> 8.5060789
A65: 20034 | B65: 52900 | C65: 18300 | D65: 7900 | E65: 14700 | G65: 2700 | J65: =B65 -> 52900 | K65: =C65 -> 18300 | L65: =D65 -> 7900 | M65: =E65 -> 14700 | N65: =SUM(J65:M65) -> 93800 | O65: =N66-N65 -> -50 | R65: =G65 -> 2700 | S65: =R66-R65 -> -50 | AA65: 37926 | AB65: =AB66-(N66-N65) -> 92200 | AC65: =AC66-(R66-R65) -> 2600 | AF65: 37926 | AG65: =AB65 -> 92200 | AH65: =AC65 -> 2600 | AJ65: =AG65/(DataQ!C130*1000) -> 0.0080538085 | AK65: =AH65/(DataQ!D130*1000) -> 0.00026595745 | AM65: =AG65/(DataQ!C130) -> 8.0538085
A66: 20041 | B66: #N/A | C66: #N/A | D66: #N/A | E66: #N/A | G66: #N/A | J66: =J65+0.5*(J67-J65) -> 53550 | K66: =K65+0.5*(K67-K65) -> 18000 | L66: =L65+0.5*(L67-L65) -> 7650 | M66: =M65+0.5*(M67-M65) -> 14550 | N66: =SUM(J66:M66) -> 93750 | O66: =N67-N66 -> -50 | R66: =R65+0.5*(R67-R65) -> 2650 | S66: =R67-R66 -> -50 | AA66: 38018 | AB66: =AB67-(N67-N66) -> 92150 | AC66: =AC67-(R67-R66) -> 2550 | AF66: 38018 | AG66: =AB66 -> 92150 | AH66: =AC66 -> 2550 | AJ66: =AG66/(DataQ!C131*1000) -> 0.0080210645 | AK66: =AH66/(DataQ!D131*1000) -> 0.00023409529 | AM66: =AG66/(DataQ!C131) -> 8.0210645
A67: 20042 | B67: 54200 | C67: 17700 | D67: 7400 | E67: 14400 | G67: 2600 | J67: =B67 -> 54200 | K67: =C67 -> 17700 | L67: =D67 -> 7400 | M67: =E67 -> 14400 | N67: =SUM(J67:M67) -> 93700 | O67: =N68-N67 -> 5550 | R67: =G67 -> 2600 | S67: =R68-R67 -> 500 | AA67: 38108 | AB67: =AB68-(N68-N67) -> 92100 | AC67: =AC68-(R68-R67) -> 2500 | AF67: 38108 | AG67: =AB67 -> 92100 | AH67: =AC67 -> 2500 | AJ67: =AG67/(DataQ!C132*1000) -> 0.0079885506 | AK67: =AH67/(DataQ!D132*1000) -> 0.00020882058 | AM67: =AG67/(DataQ!C132) -> 7.9885506
A68: 20043 | B68: #N/A | C68: #N/A | D68: #N/A | E68: #N/A | G68: #N/A | J68: =J67+0.5*(J69-J67) -> 58050 | K68: =K67+0.5*(K69-K67) -> 19050 | L68: =L67+0.5*(L69-L67) -> 7800 | M68: =M67+0.5*(M69-M67) -> 14350 | N68: =SUM(J68:M68) -> 99250 | O68: =N69-N68 -> 5550 | R68: =R67+0.5*(R69-R67) -> 3100 | S68: =R69-R68 -> 500 | AA68: 38200 | AB68: =AB69-(N69-N68) -> 97650 | AC68: =AC69-(R69-R68) -> 3000 | AF68: 38200 | AG68: =AB68 -> 97650 | AH68: =AC68 -> 3000 | AJ68: =AG68/(DataQ!C133*1000) -> 0.0084765625 | AK68: =AH68/(DataQ!D133*1000) -> 0.00022176227 | AM68: =AG68/(DataQ!C133) -> 8.4765625
A69: 20044 | B69: 61900 | C69: 20400 | D69: 8200 | E69: 14300 | G69: 3600 | J69: =B69 -> 61900 | K69: =C69 -> 20400 | L69: =D69 -> 8200 | M69: =E69 -> 14300 | N69: =SUM(J69:M69) -> 104800 | O69: =N70-N69 -> 7250 | R69: =G69 -> 3600 | S69: =R70-R69 -> 1200 | AA69: 38292 | AB69: =AB70-(N70-N69) -> 103200 | AC69: =AC70-(R70-R69) -> 3500 | AF69: 38292 | AG69: =AB69 -> 103200 | AH69: =AC69 -> 3500 | AJ69: =AG69/(DataQ!C134*1000) -> 0.0089653375 | AK69: =AH69/(DataQ!D134*1000) -> 0.00025016082 | AM69: =AG69/(DataQ!C134) -> 8.9653375
A70: 20051 | B70: #N/A | C70: #N/A | D70: #N/A | E70: #N/A | G70: #N/A | J70: =J69+0.5*(J71-J69) -> 65900 | K70: =K69+0.5*(K71-K69) -> 22150 | L70: =L69+0.5*(L71-L69) -> 8950 | M70: =M69+0.5*(M71-M69) -> 15050 | N70: =SUM(J70:M70) -> 112050 | O70: =N71-N70 -> 7250 | R70: =R69+0.5*(R71-R69) -> 4800 | S70: =R71-R70 -> 1200 | AA70: 38384 | AB70: =AB71-(N71-N70) -> 110450 | AC70: =AC71-(R71-R70) -> 4700 | AF70: 38384 | AG70: =AB70 -> 110450 | AH70: =AC70 -> 4700 | AJ70: =AG70/(DataQ!C135*1000) -> 0.0095801891 | AK70: =AH70/(DataQ!D135*1000) -> 0.00033920323 | AM70: =AG70/(DataQ!C135) -> 9.5801891
A71: 20052 | B71: 69900 | C71: 23900 | D71: 9700 | E71: 15800 | G71: 6000 | J71: =B71 -> 69900 | K71: =C71 -> 23900 | L71: =D71 -> 9700 | M71: =E71 -> 15800 | N71: =SUM(J71:M71) -> 119300 | O71: =N72-N71 -> 0 | R71: =G71 -> 6000 | S71: =R72-R71 -> -50 | AA71: 38473 | AB71: =AB72-(N72-N71) -> 117700 | AC71: =AC72-(R72-R71) -> 5900 | AF71: 38473 | AG71: =AB71 -> 117700 | AH71: =AC71 -> 5900 | AJ71: =AG71/(DataQ!C136*1000) -> 0.010193124 | AK71: =AH71/(DataQ!D136*1000) -> 0.00039940428 | AM71: =AG71/(DataQ!C136) -> 10.193124
A72: 20053 | B72: #N/A | C72: #N/A | D72: #N/A | E72: #N/A | G72: #N/A | J72: =J71+0.5*(J73-J71) -> 69300 | K72: =K71+0.5*(K73-K71) -> 23750 | L72: =L71+0.5*(L73-L71) -> 9900 | M72: =M71+0.5*(M73-M71) -> 16350 | N72: =SUM(J72:M72) -> 119300 | O72: =N73-N72 -> 0 | R72: =R71+0.5*(R73-R71) -> 5950 | S72: =R73-R72 -> -50 | AA72: 38565 | AB72: =AB73-(N73-N72) -> 117700 | AC72: =AC73-(R73-R72) -> 5850 | AF72: 38565 | AG72: =AB72 -> 117700 | AH72: =AC72 -> 5850 | AJ72: =AG72/(DataQ!C137*1000) -> 0.010168027 | AK72: =AH72/(DataQ!D137*1000) -> 0.00039370079 | AM72: =AG72/(DataQ!C137) -> 10.168027
A73: 20054 | B73: 68700 | C73: 23600 | D73: 10100 | E73: 16900 | G73: 5900 | J73: =B73 -> 68700 | K73: =C73 -> 23600 | L73: =D73 -> 10100 | M73: =E73 -> 16900 | N73: =SUM(J73:M73) -> 119300 | O73: =N74-N73 -> -800 | R73: =G73 -> 5900 | S73: =R74-R73 -> 1100 | AA73: 38657 | AB73: =AB74-(N74-N73) -> 117700 | AC73: =AC74-(R74-R73) -> 5800 | AF73: 38657 | AG73: =AB73 -> 117700 | AH73: =AC73 -> 5800 | AJ73: =AG73/(DataQ!C138*1000) -> 0.010143054 | AK73: =AH73/(DataQ!D138*1000) -> 0.00038824553 | AM73: =AG73/(DataQ!C138) -> 10.143054
A74: 20061 | B74: #N/A | C74: #N/A | D74: #N/A | E74: #N/A | G74: #N/A | J74: =J73+0.5*(J75-J73) -> 67250 | K74: =K73+0.5*(K75-K73) -> 23500 | L74: =L73+0.5*(L75-L73) -> 10100 | M74: =M73+0.5*(M75-M73) -> 17650 | N74: =SUM(J74:M74) -> 118500 | O74: =N75-N74 -> -800 | R74: =R73+0.5*(R75-R73) -> 7000 | S74: =R75-R74 -> 1100 | AA74: 38749 | AB74: =AB75-(N75-N74) -> 116900 | AC74: =AC75-(R75-R74) -> 6900 | AF74: 38749 | AG74: =AB74 -> 116900 | AH74: =AC74 -> 6900 | AJ74: =AG74/(DataQ!C139*1000) -> 0.010045113 | AK74: =AH74/(DataQ!D139*1000) -> 0.00045326151 | AM74: =AG74/(DataQ!C139) -> 10.045113
A75: 20062 | B75: 65800 | C75: 23400 | D75: 10100 | E75: 18400 | G75: 8100 | J75: =B75 -> 65800 | K75: =C75 -> 23400 | L75: =D75 -> 10100 | M75: =E75 -> 18400 | N75: =SUM(J75:M75) -> 117700 | O75: =N76-N75 -> -2350 | R75: =G75 -> 8100 | S75: =R76-R75 -> 200 | AA75: 38838 | AB75: =AB76-(N76-N75) -> 116100 | AC75: =AC76-(R76-R75) -> 8000 | AF75: 38838 | AG75: =AB75 -> 116100 | AH75: =AC75 -> 8000 | AJ75: =AG75/(DataQ!C140*1000) -> 0.0099477337 | AK75: =AH75/(DataQ!D140*1000) -> 0.00051569651 | AM75: =AG75/(DataQ!C140) -> 9.9477337
A76: 20063 | B76: #N/A | C76: #N/A | D76: #N/A | E76: #N/A | G76: #N/A | J76: =J75+0.5*(J77-J75) -> 64750 | K76: =K75+0.5*(K77-K75) -> 22500 | L76: =L75+0.5*(L77-L75) -> 9950 | M76: =M75+0.5*(M77-M75) -> 18150 | N76: =SUM(J76:M76) -> 115350 | O76: =N77-N76 -> -2350 | R76: =R75+0.5*(R77-R75) -> 8300 | S76: =R77-R76 -> 200 | AA76: 38930 | AB76: =AB77-(N77-N76) -> 113750 | AC76: =AC77-(R77-R76) -> 8200 | AF76: 38930 | AG76: =AB76 -> 113750 | AH76: =AC76 -> 8200 | AJ76: =AG76/(DataQ!C141*1000) -> 0.009716824 | AK76: =AH76/(DataQ!D141*1000) -> 0.00050362363 | AM76: =AG76/(DataQ!C141) -> 9.716824
A77: 20064 | B77: 63700 | C77: 21600 | D77: 9800 | E77: 17900 | G77: 8500 | J77: =B77 -> 63700 | K77: =C77 -> 21600 | L77: =D77 -> 9800 | M77: =E77 -> 17900 | N77: =SUM(J77:M77) -> 113000 | O77: =N78-N77 -> 4100 | R77: =G77 -> 8500 | S77: =R78-R77 -> 700 | AA77: 39022 | AB77: =AB78-(N78-N77) -> 111400 | AC77: =AC78-(R78-R77) -> 8400 | AF77: 39022 | AG77: =AB77 -> 111400 | AH77: =AC77 -> 8400 | AJ77: =AG77/(DataQ!C142*1000) -> 0.0094873105 | AK77: =AH77/(DataQ!D142*1000) -> 0.00048521257 | AM77: =AG77/(DataQ!C142) -> 9.4873105
A78: 20071 | B78: #N/A | C78: #N/A | D78: #N/A | E78: #N/A | G78: #N/A | J78: =J77+0.5*(J79-J77) -> 66500 | K78: =K77+0.5*(K79-K77) -> 22450 | L78: =L77+0.5*(L79-L77) -> 9950 | M78: =M77+0.5*(M79-M77) -> 18200 | N78: =SUM(J78:M78) -> 117100 | O78: =N79-N78 -> 4100 | R78: =R77+0.5*(R79-R77) -> 9200 | S78: =R79-R78 -> 700 | AA78: 39114 | AB78: =AB79-(N79-N78) -> 115500 | AC78: =AC79-(R79-R78) -> 9100 | AF78: 39114 | AG78: =AB78 -> 115500 | AH78: =AC78 -> 9100 | AJ78: =AG78/(DataQ!C143*1000) -> 0.0097972686 | AK78: =AH78/(DataQ!D143*1000) -> 0.00049461898 | AM78: =AG78/(DataQ!C143) -> 9.7972686
A79: 20072 | B79: 69300 | C79: 23300 | D79: 10100 | E79: 18500 | G79: 9900 | J79: =B79 -> 69300 | K79: =C79 -> 23300 | L79: =D79 -> 10100 | M79: =E79 -> 18500 | N79: =SUM(J79:M79) -> 121200 | O79: =N80-N79 -> 4150 | R79: =G79 -> 9900 | S79: =R80-R79 -> 1200 | AA79: 39203 | AB79: =AB80-(N80-N79) -> 119600 | AC79: =AC80-(R80-R79) -> 9800 | AF79: 39203 | AG79: =AB79 -> 119600 | AH79: =AC79 -> 9800 | AJ79: =AG79/(DataQ!C144*1000) -> 0.010104765 | AK79: =AH79/(DataQ!D144*1000) -> 0.00050313174 | AM79: =AG79/(DataQ!C144) -> 10.104765
A80: 20073 | B80: #N/A | C80: #N/A | D80: #N/A | E80: #N/A | G80: #N/A | J80: =J79+0.5*(J81-J79) -> 71300 | K80: =K79+0.5*(K81-K79) -> 24600 | L80: =L79+0.5*(L81-L79) -> 10750 | M80: =M79+0.5*(M81-M79) -> 18700 | N80: =SUM(J80:M80) -> 125350 | O80: =N81-N80 -> 4150 | R80: =R79+0.5*(R81-R79) -> 11100 | S80: =R81-R80 -> 1200 | AA80: 39295 | AB80: =AB81-(N81-N80) -> 123750 | AC80: =AC81-(R81-R80) -> 11000 | AF80: 39295 | AG80: =AB80 -> 123750 | AH80: =AC80 -> 11000 | AJ80: =AG80/(DataQ!C145*1000) -> 0.010461577 | AK80: =AH80/(DataQ!D145*1000) -> 0.00053905714 | AM80: =AG80/(DataQ!C145) -> 10.461577
A81: 20074 | B81: 73300 | C81: 25900 | D81: 11400 | E81: 18900 | G81: 12300 | J81: =B81 -> 73300 | K81: =C81 -> 25900 | L81: =D81 -> 11400 | M81: =E81 -> 18900 | N81: =SUM(J81:M81) -> 129500 | O81: =N82-N81 -> -900 | R81: =G81 -> 12300 | S81: =R82-R81 -> 3400 | AA81: 39387 | AB81: =AB82-(N82-N81) -> 127900 | AC81: =AC82-(R82-R81) -> 12200 | AF81: 39387 | AG81: =AB81 -> 127900 | AH81: =AC81 -> 12200 | AJ81: =AG81/(DataQ!C146*1000) -> 0.010818812 | AK81: =AH81/(DataQ!D146*1000) -> 0.00055098907 | AM81: =AG81/(DataQ!C146) -> 10.818812
A82: 20081 | B82: 74700 | C82: 25600 | D82: 10800 | E82: 17500 | G82: 15700 | J82: =B82 -> 74700 | K82: =C82 -> 25600 | L82: =D82 -> 10800 | M82: =E82 -> 17500 | N82: =SUM(J82:M82) -> 128600 | R82: =G82 -> 15700 | AA82: 39479 | AB82: =W10 -> 127000 | AC82: =X10 -> 15600 | AF82: 39479 | AG82: =AB82 -> 127000 | AH82: =AC82 -> 15600 | AJ82: =AG82/(DataQ!C147*1000) -> 0.010791061 | AK82: =AH82/(DataQ!D147*1000) -> 0.00066998797 | AM82: =AG82/(DataQ!C147) -> 10.791061
A83: 20082 | B83: 81000 | C83: 28400 | D83: 12500 | E83: 19600 | G83: 18900 | J83: =B83 -> 81000 | K83: =C83 -> 28400 | L83: =D83 -> 12500 | M83: =E83 -> 19600 | N83: =SUM(J83:M83) -> 141500 | R83: =G83 -> 18900 | AA83: 39569 | AB83: =W11 -> 139700 | AC83: =X11 -> 18700 | AF83: 39569 | AG83: =AB83 -> 139700 | AH83: =AC83 -> 18700 | AJ83: =AG83/(DataQ!C148*1000) -> 0.01190253 | AK83: =AH83/(DataQ!D148*1000) -> 0.00082367969 | AM83: =AG83/(DataQ!C148) -> 11.90253
A84: 20083 | B84: 89500 | C84: 29900 | D84: 12900 | E84: 20400 | G84: 22900 | J84: =B84 -> 89500 | K84: =C84 -> 29900 | L84: =D84 -> 12900 | M84: =E84 -> 20400 | N84: =SUM(J84:M84) -> 152700 | R84: =G84 -> 22900 | AA84: 39661 | AB84: =W12 -> 150800 | AC84: =X12 -> 22600 | AF84: 39661 | AG84: =AB84 -> 150800 | AH84: =AC84 -> 22600 | AJ84: =AG84/(DataQ!C149*1000) -> 0.012897708 | AK84: =AH84/(DataQ!D149*1000) -> 0.00098698576 | AM84: =AG84/(DataQ!C149) -> 12.897708
AA85: 39753 | AB85: =W13 -> 182600 | AC85: =X13 -> 22700 | AF85: 39753 | AG85: =AB85 -> 182600 | AH85: =AC85 -> 22700 | AJ85: =AG85/(DataQ!C150*1000) -> 0.015650981 | AK85: =AH85/(DataQ!D150*1000) -> 0.0010348758 | AM85: =AG85/(DataQ!C150) -> 15.650981
AA86: 39845 | AB86: =W14 -> 209600 | AC86: =X14 -> 24400 | AF86: 39845 | AG86: =AB86 -> 209600 | AH86: =AC86 -> 24400 | AJ86: =AG86/(DataQ!C151*1000) -> 0.018142474 | AK86: =AH86/(DataQ!D151*1000) -> 0.0020449212 | AM86: =AG86/(DataQ!C151) -> 18.142474
AA87: 39934 | AB87: =W15 -> 216400 | AC87: =X15 -> 21900 | AF87: 39934 | AG87: =AB87 -> 216400 | AH87: =AC87 -> 21900 | AJ87: =AG87/(DataQ!C152*1000) -> 0.018753791 | AK87: =AH87/(DataQ!D152*1000) -> 0.0023994741 | AM87: =AG87/(DataQ!C152) -> 18.753791
AA88: 40026 | AB88: =W16 -> 207200 | AC88: =X16 -> 19300 | AF88: 40026 | AG88: =AB88 -> 207200 | AH88: =AC88 -> 19300 | AJ88: =AG88/(DataQ!C153*1000) -> 0.017978308 | AK88: =AH88/(DataQ!D153*1000) -> 0.0024677151 | AM88: =AG88/(DataQ!C153) -> 17.978308
AA89: 40118 | AB89: =W17 -> 199600 | AC89: =X17 -> 16200 | AF89: 40118 | AG89: =AB89 -> 199600 | AH89: =AC89 -> 16200 | AJ89: =AG89/(DataQ!C154*1000) -> 0.017350487 | AK89: =AH89/(DataQ!D154*1000) -> 0.0022264981 | AM89: =AG89/(DataQ!C154) -> 17.350487
AA90: 40210 | AB90: =W18 -> 196500 | AC90: =X18 -> 15900 | AF90: 40210 | AG90: =AB90 -> 196500 | AH90: =AC90 -> 15900 | AJ90: =AG90/(DataQ!C155*1000) -> 0.017097364 | AK90: =AH90/(DataQ!D155*1000) -> 0.0031547619 | AM90: =AG90/(DataQ!C155) -> 17.097364
AA91: 40299 | AB91: =W19 -> 185500 | AC91: =X19 -> 15200 | AF91: 40299 | AG91: =AB91 -> 185500 | AH91: =AC91 -> 15200 | AJ91: =AG91/(DataQ!C156*1000) -> 0.016143068 | AK91: =AH91/(DataQ!D156*1000) -> 0.002770689 | AM91: =AG91/(DataQ!C156) -> 16.143068
AA92: 40391 | AB92: =W20 -> 179800 | AC92: =X20 -> 14700 | AF92: 40391 | AG92: =AB92 -> 179800 | AH92: =AC92 -> 14700 | AJ92: =AG92/(DataQ!C157*1000) -> 0.015662021 | AK92: =AH92/(DataQ!D157*1000) -> 0.0027647169 | AM92: =AG92/(DataQ!C157) -> 15.662021
AA93: 40483 | AB93: =W21 -> 175800 | AC93: =X21 -> 13700 | AF93: 40483 | AG93: =AB93 -> 175800 | AH93: =AC93 -> 13700 | AJ93: =AG93/(DataQ!C158*1000) -> 0.015316257 | AK93: =AH93/(DataQ!D158*1000) -> 0.0022693391 | AM93: =AG93/(DataQ!C158) -> 15.316257
AA94: 40575 | AB94: =W22 -> 171900 | AC94: =X22 -> 14200 | AF94: 40575 | AG94: =AB94 -> 171900 | AH94: =AC94 -> 14200 | AJ94: =AG94/(DataQ!C159*1000) -> 0.015007858 | AK94: =AH94/(DataQ!D159*1000) -> 0.0024449036 | AM94: =AG94/(DataQ!C159) -> 15.007858
AA95: 40664 | AB95: =W23 -> 169200 | AC95: =X23 -> 14500 | AF95: 40664 | AG95: =AB95 -> 169200 | AH95: =AC95 -> 14500 | AJ95: =AG95/(DataQ!C160*1000) -> 0.014794089 | AK95: =AH95/(DataQ!D160*1000) -> 0.0025017253 | AM95: =AG95/(DataQ!C160) -> 14.794089
AA96: 40756 | AB96: =W24 -> 165300 | AC96: =X24 -> 14700 | AF96: 40756 | AG96: =AB96 -> 165300 | AH96: =AC96 -> 14700 | AJ96: =AG96/(DataQ!C161*1000) -> 0.014483484 | AK96: =AH96/(DataQ!D161*1000) -> 0.002512391 | AM96: =AG96/(DataQ!C161) -> 14.483484
... AA110: 42036 | AB110: =W38 -> 111190 | AC110: =X38 -> 4880 | AF110: 42036 | AG110: =AB110 -> 111190 | AH110: =AC110 -> 4880 | AJ110: =AG110/(DataQ!C175*1000) -> 0.010000899 | AK110: =AH110/(DataQ!D175*1000) -> 0.00071137026 | AM110: =AG110/(DataQ!C175) -> 10.000899
AF111: 42125 | AG111: ='Haver Q'!E10 -> 106730 | AH111: ='Haver Q'!L10 -> 2500 | AJ111: =AG111/(DataQ!C176*1000) -> 0.0096066607 | AK111: =AH111/(DataQ!D176*1000) -> 0.00035171638 | AM111: =AG111/(DataQ!C176) -> 9.6066607
AF112: 42217 | AG112: ='Haver Q'!E11 -> 104970 | AH112: ='Haver Q'!L11 -> 2490 | AJ112: =AG112/(DataQ!C177*1000) -> 0.0094482448 | AK112: =AH112/(DataQ!D177*1000) -> 0.00035642714 | AM112: =AG112/(DataQ!C177) -> 9.4482448
AF113: 42309 | AG113: ='Haver Q'!E12 -> 101540 | AH113: ='Haver Q'!L12 -> 2170 | AJ113: =AG113/(DataQ!C178*1000) -> 0.009139514 | AK113: =AH113/(DataQ!D178*1000) -> 0.00030235474 | AM113: =AG113/(DataQ!C178) -> 9.139514
AF114: 42401 | AG114: ='Haver Q'!E13 -> 95590 | AH114: ='Haver Q'!L13 -> 2110 | AJ114: =AG114/(DataQ!C179*1000) -> 0.008596223 | AK114: =AH114/(DataQ!D179*1000) -> 0.00030784943 | AM114: =AG114/(DataQ!C179) -> 8.596223
...

Sheet GMWQ
A1: Location | B1: Indicator | C1: Scenario | D1: Units | E1: Scale | F1: Measurement | G1: 1973 Q1 | H1: 1973 Q2 | I1: 1973 Q3 | J1: 1973 Q4 | K1: 1974 Q1 | L1: 1974 Q2 | M1: 1974 Q3 | N1: 1974 Q4 | O1: 1975 Q1 | P1: 1975 Q2 | Q1: 1975 Q3 | R1: 1975 Q4 | S1: 1976 Q1 | T1: 1976 Q2 | U1: 1976 Q3 | V1: 1976 Q4 | W1: 1977 Q1 | X1: 1977 Q2 | Y1: 1977 Q3 | Z1: 1977 Q4 | AA1: 1978 Q1 | AB1: 1978 Q2 | AC1: 1978 Q3 | AD1: 1978 Q4 | AE1: 1979 Q1 | AF1: 1979 Q2 | AG1: 1979 Q3 | AH1: 1979 Q4 | AI1: 1980 Q1 | AJ1: 1980 Q2 | AK1: 1980 Q3 | AL1: 1980 Q4 | AM1: 1981 Q1 | AN1: 1981 Q2 | AO1: 1981 Q3 | AP1: 1981 Q4 | AQ1: 1982 Q1 | AR1: 1982 Q2 | AS1: 1982 Q3 | AT1: 1982 Q4 | AU1: 1983 Q1 | AV1: 1983 Q2 | AW1: 1983 Q3 | AX1: 1983 Q4 | AY1: 1984 Q1 | AZ1: 1984 Q2 | BA1: 1984 Q3 | BB1: 1984 Q4 | BC1: 1985 Q1 | BD1: 1985 Q2 | BE1: 1985 Q3 | BF1: 1985 Q4 | BG1: 1986 Q1 | BH1: 1986 Q2 | BI1: 1986 Q3 | BJ1: 1986 Q4 | BK1: 1987 Q1 | BL1: 1987 Q2 | BM1: 1987 Q3 | BN1: 1987 Q4 | BO1: 1988 Q1 | BP1: 1988 Q2 | BQ1: 1988 Q3 | BR1: 1988 Q4 | BS1: 1989 Q1 | BT1: 1989 Q2 | BU1: 1989 Q3 | BV1: 1989 Q4 | BW1: 1990 Q1 | BX1: 1990 Q2 | BY1: 1990 Q3 | BZ1: 1990 Q4 | CA1: 1991 Q1 | CB1: 1991 Q2 | CC1: 1991 Q3 | CD1: 1991 Q4 | CE1: 1992 Q1 | CF1: 1992 Q2 | CG1: 1992 Q3 | CH1: 1992 Q4 | CI1: 1993 Q1 | CJ1: 1993 Q2 | CK1: 1993 Q3 | CL1: 1993 Q4 | CM1: 1994 Q1 | CN1: 1994 Q2 | CO1: 1994 Q3 | CP1: 1994 Q4 | CQ1: 1995 Q1 | CR1: 1995 Q2 | CS1: 1995 Q3 | CT1: 1995 Q4 | CU1: 1996 Q1 | CV1: 1996 Q2 | CW1: 1996 Q3 | CX1: 1996 Q4 | CY1: 1997 Q1 | CZ1: 1997 Q2 | DA1: 1997 Q3 | DB1: 1997 Q4 | DC1: 1998 Q1 | DD1: 1998 Q2 | DE1: 1998 Q3 | DF1: 1998 Q4 | DG1: 1999 Q1 | DH1: 1999 Q2 | DI1: 1999 Q3 | DJ1: 1999 Q4 | DK1: 2000 Q1 | DL1: 2000 Q2 | DM1: 2000 Q3 | DN1: 2000 Q4 | DO1: 2001 Q1 | DP1: 2001 Q2 | DQ1: 2001 Q3 | DR1: 2001 Q4 | DS1: 2002 Q1 | DT1: 2002 Q2 | DU1: 2002 Q3 | DV1: 2002 Q4 | DW1: 2003 Q1 | DX1: 2003 Q2 | DY1: 2003 Q3 | DZ1: 2003 Q4 | EA1: 2004 Q1 | EB1: 2004 Q2 | EC1: 2004 Q3 | ED1: 2004 Q4 | EE1: 2005 Q1 | EF1: 2005 Q2 | EG1: 2005 Q3 | EH1: 2005 Q4 | EI1: 2006 Q1 | EJ1: 2006 Q2 | EK1: 2006 Q3 | EL1: 2006 Q4 | EM1: 2007 Q1 | EN1: 2007 Q2 | EO1: 2007 Q3 | EP1: 2007 Q4 | EQ1: 2008 Q1 | ER1: 2008 Q2 | ES1: 2008 Q3 | ET1: 2008 Q4 | EU1: 2009 Q1 | EV1: 2009 Q2 | EW1: 2009 Q3 | EX1: 2009 Q4 | EY1: 2010 Q1 | EZ1: 2010 Q2 | FA1: 2010 Q3 | FB1: 2010 Q4 | FC1: 2011 Q1 | FD1: 2011 Q2 | FE1: 2011 Q3 | FF1: 2011 Q4 | FG1: 2012 Q1 | FH1: 2012 Q2 | FI1: 2012 Q3 | FJ1: 2012 Q4 | FK1: 2013 Q1 | FL1: 2013 Q2 | FM1: 2013 Q3 | FN1: 2013 Q4 | FO1: 2014 Q1 | FP1: 2014 Q2 | FQ1: 2014 Q3 | FR1: 2014 Q4 | FS1: 2015 Q1 | FT1: 2015 Q2 | FU1: 2015 Q3 | FV1: 2015 Q4 | FW1: 2016 Q1 | FX1: 2016 Q2 | FY1: 2016 Q3 | FZ1: 2016 Q4 | GA1: 2017 Q1 | GB1: 2017 Q2 | GC1: 2017 Q3 | GD1: 2017 Q4 | GE1: 2018 Q1 | GF1: 2018 Q2 | GG1: 2018 Q3 | GH1: 2018 Q4 | GI1: 2019 Q1 | GJ1: 2019 Q2 | GK1: 2019 Q3 | GL1: 2019 Q4 | GM1: 2020 Q1 | GN1: 2020 Q2 | GO1: 2020 Q3 | GP1: 2020 Q4 | GQ1: 2021 Q1 | GR1: 2021 Q2 | GS1: 2021 Q3 | GT1: 2021 Q4 | GU1: 2022 Q1 | GV1: 2022 Q2 | GW1: 2022 Q3 | GX1: 2022 Q4 | GY1: 2023 Q1 | GZ1: 2023 Q2 | HA1: 2023 Q3 | HB1: 2023 Q4 | HC1: 2024 Q1 | HD1: 2024 Q2 | HE1: 2024 Q3 | HF1: 2024 Q4 | HG1: 2025 Q1 | HH1: 2025 Q2 | HI1: 2025 Q3 | HJ1: 2025 Q4 | HK1: 2026 Q1 | HL1: 2026 Q2 | HM1: 2026 Q3 | HN1: 2026 Q4 | HO1: 2027 Q1 | HP1: 2027 Q2 | HQ1: 2027 Q3 | HR1: 2027 Q4 | HS1: 2028 Q1 | HT1: 2028 Q2 | HU1: 2028 Q3 | HV1: 2028 Q4 | HW1: 2029 Q1 | HX1: 2029 Q2 | HY1: 2029 Q3 | HZ1: 2029 Q4 | IA1: 2030 Q1 | IB1: 2030 Q2 | IC1: 2030 Q3 | ID1: 2030 Q4 | IE1: 2031 Q1 | IF1: 2031 Q2 | IG1: 2031 Q3 | IH1: 2031 Q4 | II1: 2032 Q1 | IJ1: 2032 Q2 | IK1: 2032 Q3 | IL1: 2032 Q4 | IM1: 2033 Q1 | IN1: 2033 Q2 | IO1: 2033 Q3 | IP1: 2033 Q4 | IQ1: 2034 Q1 | IR1: 2034 Q2 | IS1: 2034 Q3 | IT1: 2034 Q4 | IU1: 2035 Q1 | IV1: 2035 Q2 | IW1: 2035 Q3 | IX1: 2035 Q4 | IY1: 2036 Q1 | IZ1: 2036 Q2 | JA1: 2036 Q3 | JB1: 2036 Q4 | JC1: 2037 Q1 | JD1: 2037 Q2 | JE1: 2037 Q3 | JF1: 2037 Q4 | JG1: 2038 Q1 | JH1: 2038 Q2 | JI1: 2038 Q3 | JJ1: 2038 Q4 | JK1: 2039 Q1 | JL1: 2039 Q2 | JM1: 2039 Q3 | JN1: 2039 Q4 | JO1: 2040 Q1 | JP1: 2040 Q2 | JQ1: 2040 Q3 | JR1: 2040 Q4 | JS1: 2041 Q1 | JT1: 2041 Q2 | JU1: 2041 Q3 | JV1: 2041 Q4 | JW1: 2042 Q1 | JX1: 2042 Q2 | JY1: 2042 Q3 | JZ1: 2042 Q4 | KA1: 2043 Q1 | KB1: 2043 Q2 | KC1: 2043 Q3 | KD1: 2043 Q4 | KE1: 2044 Q1 | KF1: 2044 Q2 | KG1: 2044 Q3 | KH1: 2044 Q4 | KI1: 2045 Q1 | KJ1: 2045 Q2 | KK1: 2045 Q3 | KL1: 2045 Q4 | KM1: 2046 Q1 | KN1: 2046 Q2 | KO1: 2046 Q3 | KP1: 2046 Q4 | KQ1: 2047 Q1 | KR1: 2047 Q2 | KS1: 2047 Q3 | KT1: 2047 Q4 | KU1: 2048 Q1 | KV1: 2048 Q2 | KW1: 2048 Q3 | KX1: 2048 Q4 | KY1: 2049 Q1 | KZ1: 2049 Q2 | LA1: 2049 Q3 | LB1: 2049 Q4 | LC1: 2050 Q1 | LD1: 2050 Q2 | LE1: 2050 Q3 | LF1: 2050 Q4 | LG1: 2051 Q1 | LH1: 2051 Q2 | LI1: 2051 Q3 | LJ1: 2051 Q4 | LK1: 2052 Q1 | LL1: 2052 Q2 | LM1: 2052 Q3 | LN1: 2052 Q4 | LO1: 2053 Q1 | LP1: 2053 Q2 | LQ1: 2053 Q3 | LR1: 2053 Q4 | LS1: 2054 Q1 | LT1: 2054 Q2 | LU1: 2054 Q3 | LV1: 2054 Q4 | LW1: 2055 Q1 | LX1: 2055 Q2 | LY1: 2055 Q3 | LZ1: 2055 Q4 | MA1: 2056 Q1 | MB1: 2056 Q2 | MC1: 2056 Q3 | MD1: 2056 Q4 | ME1: 2057 Q1 | MF1: 2057 Q2 | MG1: 2057 Q3 | MH1: 2057 Q4 | MI1: 2058 Q1 | MJ1: 2058 Q2 | MK1: 2058 Q3 | ML1: 2058 Q4 | MM1: 2059 Q1 | MN1: 2059 Q2 | MO1: 2059 Q3 | MP1: 2059 Q4 | MQ1: 2060 Q1 | MR1: 2060 Q2 | MS1: 2060 Q3 | MT1: 2060 Q4 | MU1: Source | MV1: Seasonally adjusted | MW1: Base year price | MX1: Base year index | MY1: Historical end year | MZ1: Historical end quarter | NA1: Date of last update | NB1: Source details | NC1: Additional source details | ND1: Location code | NE1: Indicator code | NF1: Databank code
A2: United Kingdom | B2: Number of mortgage repossessions | C2: JAN003G | D2: Number | E2: Thousands | F2: Level | G2: 0.001 | H2: 0.001 | I2: 0.001 | J2: 0.001 | K2: 0.001 | L2: 0.001 | M2: 0.001 | N2: 0.001 | O2: 0.001 | P2: 0.001 | Q2: 0.001 | R2: 0.001 | S2: 0.001 | T2: 0.001 | U2: 0.001 | V2: 0.001 | W2: 0.001 | X2: 0.001 | Y2: 0.001 | Z2: 0.001 | AA2: 0.001 | AB2: 0.001 | AC2: 0.001 | AD2: 0.001 | AE2: 0.001 | AF2: 0.001 | AG2: 0.001 | AH2: 0.001 | AI2: 0.001 | AJ2: 0.001 | AK2: 0.001 | AL2: 0.001 | AM2: 0.001 | AN2: 0.001 | AO2: 0.001 | AP2: 0.001 | AQ2: 0.001 | AR2: 0.001 | AS2: 0.001 | AT2: 0.001 | AU2: 0.001 | AV2: 0.001 | AW2: 0.001 | AX2: 0.001 | AY2: 0.001 | AZ2: 0.001 | BA2: 0.001 | BB2: 0.001 | BC2: 0.001 | BD2: 0.001 | BE2: 0.001 | BF2: 0.001 | BG2: 0.001 | BH2: 0.001 | BI2: 0.001 | BJ2: 0.001 | BK2: 0.001 | BL2: 0.001 | BM2: 0.001 | BN2: 0.001 | BO2: 0.001 | BP2: 0.001 | BQ2: 0.001 | BR2: 0.001 | BS2: 0.001 | BT2: 0.001 | BU2: 0.001 | BV2: 0.001 | BW2: 0.001 | BX2: 0.001 | BY2: 0.001 | BZ2: 36.2 | CA2: 44.85 | CB2: 53.5 | CC2: 60.45 | CD2: 67.4 | CE2: 67.95 | CF2: 68.5 | CG2: 66.75 | CH2: 65 | CI2: 59.65 | CJ2: 54.3 | CK2: 47.1 | CL2: 39.9 | CM2: 36.55 | CN2: 33.2 | CO2: 31.3 | CP2: 29.4 | CQ2: 29.6 | CR2: 29.8 | CS2: 28.5 | CT2: 27.2 | CU2: 25.6 | CV2: 24 | CW2: 20.1 | CX2: 16.2 | CY2: 15.15 | CZ2: 14.1 | DA2: 14 | DB2: 13.9 | DC2: 14.55 | DD2: 15.2 | DE2: 14.55 | DF2: 13.9 | DG2: 13.5 | DH2: 13.1 | DI2: 11.95 | DJ2: 10.8 | DK2: 10 | DL2: 9.2 | DM2: 8.55 | DN2: 7.9 | DO2: 7.6 | DP2: 7.3 | DQ2: 6.45 | DR2: 5.6 | DS2: 4.85 | DT2: 4.1 | DU2: 3.45 | DV2: 2.8 | DW2: 2.75 | DX2: 2.7 | DY2: 2.7 | DZ2: 2.7 | EA2: 2.65 | EB2: 2.6 | EC2: 3.1 | ED2: 3.6 | EE2: 4.8 | EF2: 6 | EG2: 5.95 | EH2: 5.9 | EI2: 7 | EJ2: 8.1 | EK2: 8.3 | EL2: 8.5 | EM2: 9.2 | EN2: 9.9 | EO2: 11.1 | EP2: 12.3 | EQ2: 15.6 | ER2: 18.7 | ES2: 22.6 | ET2: 22.7 | EU2: 24.4 | EV2: 21.9 | EW2: 19.3 | EX2: 16.2 | EY2: 15.9 | EZ2: 15.2 | FA2: 14.7 | FB2: 13.7 | FC2: 14.2 | FD2: 14.5 | FE2: 14.7 | FF2: 13.9 | FG2: 13.9 | FH2: 13.5 | FI2: 13 | FJ2: 11.5 | FK2: 11.1 | FL2: 10.3 | FM2: 9.9 | FN2: 8.4 | FO2: 8.5 | FP2: 7.88 | FQ2: 7.15 | FR2: 6.17 | FS2: 4.88 | FT2: 2.5 | FU2: 2.49 | FV2: 2.17 | FW2: 2.11 | FX2: 1.89 | FY2: 1.86 | FZ2: 1.8 | GA2: 1.88 | GB2: 1.8 | GC2: 1.95 | GD2: 1.79 | GE2: 1.91 | GF2: 1.68 | GG2: 1.69 | GH2: 1.69 | GI2: 1.98 | GJ2: 1.92 | GK2: 2.13 | GL2: 1.99 | GM2: 1.71 | GN2: 0.22 | GO2: 0.37 | GP2: 0.33 | GQ2: 0.38 | GR2: 0.45 | GS2: 0.73 | GT2: 0.72 | GU2: 1.04 | GV2: 1.18 | GW2: 1.28 | GX2: 1.09 | GY2: 1.26 | GZ2: 1.22 | HA2: 1.12 | HB2: 1.18 | HC2: 1.54 | HD2: 1.69 | HE2: 1.7 | HF2: 1.746393 | HG2: 1.784214 | HH2: 1.797525 | HI2: 1.809034 | HJ2: 1.813369 | HK2: 1.816119 | HL2: 1.817599 | HM2: 1.816996 | HN2: 1.818873 | HO2: 1.820224 | HP2: 1.820462 | HQ2: 1.816683 | HR2: 1.809648 | HS2: 1.798269 | HT2: 1.790842 | HU2: 1.78359 | HV2: 1.774141 | HW2: 1.767284 | HX2: 1.763394 | HY2: 1.761174 | HZ2: 1.759614 | IA2: 1.75839 | IB2: 1.757393 | IC2: 1.756232 | ID2: 1.754842 | IE2: 1.754077 | IF2: 1.755198 | IG2: 1.756245 | IH2: 1.757191 | II2: 1.758213 | IJ2: 1.759779 | IK2: 1.761361 | IL2: 1.762824 | IM2: 1.764329 | IN2: 1.766207 | IO2: 1.767966 | IP2: 1.769603 | IQ2: 1.77128 | IR2: 1.773313 | IS2: 1.775176 | IT2: 1.77689 | IU2: 1.778688 | IV2: 1.780937 | IW2: 1.783163 | IX2: 1.785373 | IY2: 1.787682 | IZ2: 1.790295 | JA2: 1.79277 | JB2: 1.795356 | JC2: 1.798006 | JD2: 1.800921 | JE2: 1.803647 | JF2: 1.806466 | JG2: 1.809328 | JH2: 1.812451 | JI2: 1.815395 | JJ2: 1.818422 | JK2: 1.821479 | JL2: 1.824765 | JM2: 1.827839 | JN2: 1.830988 | JO2: 1.834153 | JP2: 1.837544 | JQ2: 1.840711 | JR2: 1.843955 | JS2: 1.847198 | JT2: 1.850646 | JU2: 1.85383 | JV2: 1.85708 | JW2: 1.860328 | JX2: 1.8638 | JY2: 1.867037 | JZ2: 1.870338 | KA2: 1.873635 | KB2: 1.877151 | KC2: 1.880428 | KD2: 1.883766 | KE2: 1.8871 | KF2: 1.890648 | KG2: 1.893957 | KH2: 1.897328 | KI2: 1.900684 | KJ2: 1.904254 | KK2: 1.907586 | KL2: 1.910976 | KM2: 1.914351 | KN2: 1.917939 | KO2: 1.921285 | KP2: 1.92469 | KQ2: 1.928079 | KR2: 1.93168 | KS2: 1.935032 | KT2: 1.938447 | KU2: 1.941841 | KV2: 1.945452 | KW2: 1.948812 | KX2: 1.952236 | KY2: 1.95563 | KZ2: 1.959243 | LA2: 1.962609 | LB2: 1.966029 | LC2: 1.969425 | LD2: 1.973042 | LE2: 1.97642 | LF2: 1.97986 | LG2: 1.98275 | LH2: 1.986012 | LI2: 1.988874 | LJ2: 1.99218 | LK2: 1.994921 | LL2: 1.998069 | LM2: 2.000919 | LN2: 2.0042 | LO2: 2.006899 | LP2: 2.010019 | LQ2: 2.012831 | LR2: 2.016087 | LS2: 2.01879 | LT2: 2.021909 | LU2: 2.02472 | LV2: 2.027972 | LW2: 2.030661 | LX2: 2.033758 | LY2: 2.036548 | LZ2: 2.039783 | MA2: 2.042448 | MB2: 2.045532 | MC2: 2.048303 | MD2: 2.051521 | ME2: 2.054188 | MF2: 2.057265 | MG2: 2.060032 | MH2: 2.063253 | MI2: 2.065929 | MJ2: 2.069016 | MK2: 2.071795 | ML2: 2.075014 | MM2: 2.077675 | MN2: 2.080746 | MO2: 2.083511 | MP2: 2.086728 | MQ2: 2.089398 | MR2: 2.092476 | MS2: 2.095242 | MT2: 2.098455 | MU2: CML\Haver Analytics | MV2: False | MW2: NA | MX2: NA | MY2: 2024 | MZ2: 3 | NA2: NA | NB2: Number of mortgage repossessions | NC2: UNMARP42@UK, interpolated/1000 | ND2: GBR | NE2: REPO | NF2: JAN003G.db
A3: United Kingdom | B3: Loans, liabilities of the household sector, LCU | C3: JAN003G | D3: Pound | E3: Millions | F3: Level | G3: 0 | H3: 0 | I3: 0 | J3: 0 | K3: 0 | L3: 0 | M3: 0 | N3: 0 | O3: 0 | P3: 0 | Q3: 0 | R3: 0 | S3: 0 | T3: 0 | U3: 0 | V3: 0 | W3: 0 | X3: 0 | Y3: 0 | Z3: 0 | AA3: 0 | AB3: 0 | AC3: 0 | AD3: 0 | AE3: 0 | AF3: 0 | AG3: 0 | AH3: 0 | AI3: 64761.59 | AJ3: 67638.73 | AK3: 70091.01 | AL3: 72610.32 | AM3: 75025.47 | AN3: 78545.08 | AO3: 81974.97 | AP3: 87375.55 | AQ3: 88820.3 | AR3: 93446.43 | AS3: 98690.26 | AT3: 103494.8 | AU3: 108127.1 | AV3: 113141 | AW3: 118131.1 | AX3: 122827.4 | AY3: 133258.3 | AZ3: 139291 | BA3: 145310.4 | BB3: 150762.5 | BC3: 156486.9 | BD3: 162450.5 | BE3: 169618.6 | BF3: 177527.2 | BG3: 183769.3 | BH3: 192567.8 | BI3: 200615.5 | BJ3: 209439.8 | BK3: 216611 | BL3: 225716 | BM3: 235970 | BN3: 246373 | BO3: 255791 | BP3: 269794 | BQ3: 285703 | BR3: 297630 | BS3: 307440 | BT3: 318905 | BU3: 331089 | BV3: 342452 | BW3: 351756 | BX3: 366288 | BY3: 376714 | BZ3: 386248 | CA3: 392051 | CB3: 402389 | CC3: 409627 | CD3: 413615 | CE3: 415419 | CF3: 420035 | CG3: 427788 | CH3: 430722 | CI3: 431530 | CJ3: 435635 | CK3: 441328 | CL3: 447646 | CM3: 452748 | CN3: 457911 | CO3: 464101 | CP3: 471362 | CQ3: 475489 | CR3: 481275 | CS3: 488139 | CT3: 493365 | CU3: 495738 | CV3: 503790 | CW3: 510436 | CX3: 514960 | CY3: 518156 | CZ3: 528534 | DA3: 538689 | DB3: 547859 | DC3: 561587 | DD3: 571995 | DE3: 584273 | DF3: 594941 | DG3: 607994 | DH3: 620553 | DI3: 636829 | DJ3: 655674 | DK3: 667552 | DL3: 688202 | DM3: 703014 | DN3: 715604 | DO3: 729342 | DP3: 747987 | DQ3: 769137 | DR3: 790305 | DS3: 809928 | DT3: 834201 | DU3: 865435 | DV3: 890807 | DW3: 910822 | DX3: 939241 | DY3: 971319 | DZ3: 1003798 | EA3: 1032893 | EB3: 1065242 | EC3: 1099554 | ED3: 1128681 | EE3: 1146523 | EF3: 1175403 | EG3: 1199192 | EH3: 1222723 | EI3: 1243570 | EJ3: 1276132 | EK3: 1317180 | EL3: 1346853 | EM3: 1372001 | EN3: 1406912 | EO3: 1441224 | EP3: 1461726 | EQ3: 1483670 | ER3: 1502996 | ES3: 1515434 | ET3: 1516691 | EU3: 1514202 | EV3: 1512964 | EW3: 1513803 | EX3: 1517589 | EY3: 1528845 | EZ3: 1524838 | FA3: 1529150 | FB3: 1525911 | FC3: 1524719 | FD3: 1528931 | FE3: 1531162 | FF3: 1533793 | FG3: 1532024 | FH3: 1543909 | FI3: 1552045 | FJ3: 1555841 | FK3: 1567829 | FL3: 1574108 | FM3: 1586260 | FN3: 1596106 | FO3: 1600626 | FP3: 1610589 | FQ3: 1624951 | FR3: 1641938 | FS3: 1649383 | FT3: 1660855 | FU3: 1675207 | FV3: 1685986 | FW3: 1701053 | FX3: 1721660 | FY3: 1739143 | FZ3: 1751607 | GA3: 1773709 | GB3: 1781329 | GC3: 1799927 | GD3: 1812901 | GE3: 1818355 | GF3: 1831264 | GG3: 1851239 | GH3: 1865855 | GI3: 1848327 | GJ3: 1873490 | GK3: 1893215 | GL3: 1910658 | GM3: 1915251 | GN3: 1913499 | GO3: 1932687 | GP3: 1950608 | GQ3: 1961737 | GR3: 1989263 | GS3: 2002133 | GT3: 2001814 | GU3: 2019506 | GV3: 2037978 | GW3: 2062121 | GX3: 2077011 | GY3: 2081928 | GZ3: 2090036 | HA3: 2117180 | HB3: 2117452 | HC3: 2127290 | HD3: 2138212 | HE3: 2156961 | HF3: 2178342 | HG3: 2204166 | HH3: 2220027 | HI3: 2239353 | HJ3: 2260036 | HK3: 2281944 | HL3: 2304880 | HM3: 2328195 | HN3: 2351317 | HO3: 2374451 | HP3: 2397886 | HQ3: 2422010 | HR3: 2446894 | HS3: 2472476 | HT3: 2498685 | HU3: 2525553 | HV3: 2553163 | HW3: 2581601 | HX3: 2610791 | HY3: 2640770 | HZ3: 2671465 | IA3: 2702893 | IB3: 2734964 | IC3: 2767595 | ID3: 2800649 | IE3: 2834093 | IF3: 2867798 | IG3: 2901650 | IH3: 2935533 | II3: 2969464 | IJ3: 3003360 | IK3: 3037159 | IL3: 3070795 | IM3: 3104337 | IN3: 3137746 | IO3: 3170999 | IP3: 3204058 | IQ3: 3237016 | IR3: 3269851 | IS3: 3302543 | IT3: 3335056 | IU3: 3366632 | IV3: 3397367 | IW3: 3427348 | IX3: 3456639 | IY3: 3485321 | IZ3: 3513454 | JA3: 3541098 | JB3: 3568299 | JC3: 3595101 | JD3: 3621544 | JE3: 3647663 | JF3: 3673491 | JG3: 3699059 | JH3: 3724395 | JI3: 3749530 | JJ3: 3774490 | JK3: 3799294 | JL3: 3823964 | JM3: 3848518 | JN3: 3872971 | JO3: 3897341 | JP3: 3921641 | JQ3: 3945885 | JR3: 3970085 | JS3: 3994254 | JT3: 4018399 | JU3: 4042522 | JV3: 4066631 | JW3: 4090734 | JX3: 4114840 | JY3: 4138956 | JZ3: 4163089 | KA3: 4187247 | KB3: 4211435 | KC3: 4235661 | KD3: 4259929 | KE3: 4284246 | KF3: 4308616 | KG3: 4333045 | KH3: 4357536 | KI3: 4382095 | KJ3: 4406724 | KK3: 4431429 | KL3: 4456214 | KM3: 4481082 | KN3: 4506037 | KO3: 4531081 | KP3: 4556219 | KQ3: 4581453 | KR3: 4606787 | KS3: 4632223 | KT3: 4657765 | KU3: 4683414 | KV3: 4709175 | KW3: 4735050 | KX3: 4761040 | KY3: 4787150 | KZ3: 4813380 | LA3: 4839735 | LB3: 4866215 | LC3: 4892824 | LD3: 4919563 | LE3: 4946438 | LF3: 4973451 | LG3: 5000604 | LH3: 5027896 | LI3: 5055304 | LJ3: 5082826 | LK3: 5110460 | LL3: 5138204 | LM3: 5166061 | LN3: 5194033 | LO3: 5222113 | LP3: 5250304 | LQ3: 5278606 | LR3: 5307022 | LS3: 5335554 | LT3: 5364203 | LU3: 5392973 | LV3: 5421863 | LW3: 5450874 | LX3: 5480006 | LY3: 5509261 | LZ3: 5538642 | MA3: 5568145 | MB3: 5597775 | MC3: 5627531 | MD3: 5657416 | ME3: 5687432 | MF3: 5717581 | MG3: 5747865 | MH3: 5778285 | MI3: 5808850 | MJ3: 5839559 | MK3: 5870416 | ML3: 5901423 | MM3: 5932579 | MN3: 5963887 | MO3: 5995349 | MP3: 6026967 | MQ3: 6058747 | MR3: 6090691 | MS3: 6122801 | MT3: 6155078 | MU3: Office for National Statistics\Haver Analytics | MV3: False | MW3: NA | MX3: NA | MY3: 2024 | MZ3: 3 | NA3: NA | NB3: NNREQ@UK | NC3: UK: HH & NPISH: Financial Liabilities: Level: Total Loans (NSA, Mil.GBP) | ND3: GBR | NE3: LNPE | NF3: JAN003G.db
A4: United Kingdom | B4: Stock of owner-occupied houses | C4: JAN003G | D4: Number | E4: Thousands | F4: Level | G4: 13384.75 | H4: 13421.5 | I4: 13458.25 | J4: 13495 | K4: 13514.5 | L4: 13534 | M4: 13553.5 | N4: 13573 | O4: 10185.5 | P4: 6798 | Q4: 3410.5 | R4: 23 | S4: 3455 | T4: 6887 | U4: 10319 | V4: 13751 | W4: 13719 | X4: 13687 | Y4: 13655 | Z4: 13623 | AA4: 13658.5 | AB4: 13694 | AC4: 13729.5 | AD4: 13765 | AE4: 13800 | AF4: 13835 | AG4: 13870 | AH4: 13905 | AI4: 13935.75 | AJ4: 13966.5 | AK4: 13997.25 | AL4: 14028 | AM4: 14077 | AN4: 14126 | AO4: 14175 | AP4: 14224 | AQ4: 14307.5 | AR4: 14391 | AS4: 14474.5 | AT4: 14558 | AU4: 14633.75 | AV4: 14709.5 | AW4: 14785.25 | AX4: 14861 | AY4: 14930.5 | AZ4: 15000 | BA4: 15069.5 | BB4: 15139 | BC4: 15205 | BD4: 15271 | BE4: 15337 | BF4: 15403 | BG4: 15471 | BH4: 15539 | BI4: 15607 | BJ4: 15675 | BK4: 15783 | BL4: 15891 | BM4: 15999 | BN4: 16107 | BO4: 16205.5 | BP4: 16304 | BQ4: 16402.5 | BR4: 16501 | BS4: 16601 | BT4: 16701 | BU4: 16801 | BV4: 16901 | BW4: 16981.25 | BX4: 17061.5 | BY4: 17141.75 | BZ4: 17222 | CA4: 17202.75 | CB4: 17183.5 | CC4: 17164.25 | CD4: 17145 | CE4: 17215 | CF4: 17285 | CG4: 17355 | CH4: 17425 | CI4: 17479.5 | CJ4: 17534 | CK4: 17588.5 | CL4: 17643 | CM4: 17702 | CN4: 17761 | CO4: 17820 | CP4: 17879 | CQ4: 17940.25 | CR4: 18001.5 | CS4: 18062.75 | CT4: 18124 | CU4: 18179.25 | CV4: 18234.5 | CW4: 18289.75 | CX4: 18345 | CY4: 18402.75 | CZ4: 18460.5 | DA4: 18518.25 | DB4: 18576 | DC4: 18639 | DD4: 18702 | DE4: 18765 | DF4: 18828 | DG4: 18885.5 | DH4: 18943 | DI4: 19000.5 | DJ4: 19058 | DK4: 19118.25 | DL4: 19178.5 | DM4: 19238.75 | DN4: 19299 | DO4: 19354.25 | DP4: 19409.5 | DQ4: 19464.75 | DR4: 19520 | DS4: 19576.25 | DT4: 19632.5 | DU4: 19688.75 | DV4: 19745 | DW4: 19822.75 | DX4: 19900.5 | DY4: 19978.25 | DZ4: 20056 | EA4: 20135.25 | EB4: 20214.5 | EC4: 20293.75 | ED4: 20373 | EE4: 20449.5 | EF4: 20526 | EG4: 20602.5 | EH4: 20679 | EI4: 20745 | EJ4: 20811 | EK4: 20877 | EL4: 20943 | EM4: 21012.25 | EN4: 21081.5 | EO4: 21150.75 | EP4: 21220 | EQ4: 21289.5 | ER4: 21359 | ES4: 21428.5 | ET4: 21498 | EU4: 21547 | EV4: 21596 | EW4: 21645 | EX4: 21694 | EY4: 21732.25 | EZ4: 21770.5 | FA4: 21808.75 | FB4: 21847 | FC4: 21883.5 | FD4: 21920 | FE4: 21956.5 | FF4: 21993 | FG4: 22024 | FH4: 22055 | FI4: 22086 | FJ4: 22117 | FK4: 22149.5 | FL4: 22182 | FM4: 22214.5 | FN4: 22247 | FO4: 22288.5 | FP4: 22330 | FQ4: 22371.5 | FR4: 22413 | FS4: 22458 | FT4: 22503 | FU4: 22548 | FV4: 22593 | FW4: 22643 | FX4: 22693 | FY4: 22743 | FZ4: 22793 | GA4: 22853 | GB4: 22913 | GC4: 22973 | GD4: 23033 | GE4: 23097.5 | GF4: 23162 | GG4: 23226.5 | GH4: 23291 | GI4: 23374.8 | GJ4: 23458.59 | GK4: 23542.39 | GL4: 23626.19 | GM4: 23686.86 | GN4: 23747.54 | GO4: 23808.21 | GP4: 23868.88 | GQ4: 23919.73 | GR4: 23970.58 | GS4: 24021.43 | GT4: 24072.28 | GU4: 24160.58 | GV4: 24248.89 | GW4: 24337.19 | GX4: 24425.5 | GY4: 24489.61 | GZ4: 24553.71 | HA4: 24617.82 | HB4: 24681.93 | HC4: 24731.67 | HD4: 24789.1 | HE4: 24835 | HF4: 24882.48 | HG4: 24934.87 | HH4: 24992.58 | HI4: 25050.26 | HJ4: 25108.84 | HK4: 25168.53 | HL4: 25230.78 | HM4: 25289.96 | HN4: 25349.83 | HO4: 25410.61 | HP4: 25474.44 | HQ4: 25535.02 | HR4: 25596.08 | HS4: 25657.87 | HT4: 25722.4 | HU4: 25783.39 | HV4: 25844.97 | HW4: 25906.97 | HX4: 25971.93 | HY4: 26033.36 | HZ4: 26095.29 | IA4: 26157.49 | IB4: 26222.69 | IC4: 26284.33 | ID4: 26346.5 | IE4: 26408.9 | IF4: 26474.33 | IG4: 26536.17 | IH4: 26598.58 | II4: 26661.18 | IJ4: 26726.83 | IK4: 26788.87 | IL4: 26851.5 | IM4: 26914.29 | IN4: 26980.16 | IO4: 27042.4 | IP4: 27105.26 | IQ4: 27168.23 | IR4: 27234.31 | IS4: 27296.74 | IT4: 27359.81 | IU4: 27422.97 | IV4: 27489.26 | IW4: 27551.87 | IX4: 27615.16 | IY4: 27678.5 | IZ4: 27744.98 | JA4: 27807.78 | JB4: 27871.27 | JC4: 27934.78 | JD4: 28001.47 | JE4: 28064.44 | JF4: 28128.14 | JG4: 28191.82 | JH4: 28258.7 | JI4: 28321.85 | JJ4: 28385.76 | JK4: 28449.61 | JL4: 28516.68 | JM4: 28580 | JN4: 28644.11 | JO4: 28708.13 | JP4: 28775.39 | JQ4: 28838.89 | JR4: 28903.2 | JS4: 28967.38 | JT4: 29034.84 | JU4: 29098.51 | JV4: 29163.01 | JW4: 29227.36 | JX4: 29295.01 | JY4: 29358.85 | JZ4: 29423.55 | KA4: 29488.07 | KB4: 29555.9 | KC4: 29619.91 | KD4: 29684.8 | KE4: 29749.48 | KF4: 29817.5 | KG4: 29881.68 | KH4: 29946.77 | KI4: 30011.61 | KJ4: 30079.81 | KK4: 30144.15 | KL4: 30209.43 | KM4: 30274.43 | KN4: 30342.81 | KO4: 30407.32 | KP4: 30472.78 | KQ4: 30537.93 | KR4: 30606.49 | KS4: 30671.15 | KT4: 30736.79 | KU4: 30802.1 | KV4: 30870.83 | KW4: 30935.65 | KX4: 31001.47 | KY4: 31066.92 | KZ4: 31135.81 | LA4: 31200.78 | LB4: 31266.77 | LC4: 31332.36 | LD4: 31401.42 | LE4: 31466.54 | LF4: 31532.69 | LG4: 31590.09 | LH4: 31654.1 | LI4: 31713.26 | LJ4: 31779.58 | LK4: 31837.11 | LL4: 31901.27 | LM4: 31960.56 | LN4: 32027.03 | LO4: 32084.69 | LP4: 32149 | LQ4: 32208.43 | LR4: 32275.05 | LS4: 32332.83 | LT4: 32397.28 | LU4: 32456.84 | LV4: 32523.6 | LW4: 32581.51 | LX4: 32646.09 | LY4: 32705.77 | LZ4: 32772.67 | MA4: 32830.69 | MB4: 32895.41 | MC4: 32955.21 | MD4: 33022.25 | ME4: 33080.38 | MF4: 33145.23 | MG4: 33205.14 | MH4: 33272.32 | MI4: 33330.57 | MJ4: 33395.55 | MK4: 33455.58 | ML4: 33522.89 | MM4: 33581.25 | MN4: 33646.35 | MO4: 33706.5 | MP4: 33773.93 | MQ4: 33832.4 | MR4: 33897.63 | MS4: 33957.89 | MT4: 34025.46 | MU4: Department for Communities and Local Government\Haver Analytics | MV4: False | MW4: NA | MX4: NA | MY4: 2023 | MZ4: 4 | NA4: NA | NB4: UKBHKW@UK + UKBHKP@UK | NC4: Great Britain: Dwelling Stock: Owner Occupied (Thous) + Great Britain: Dwelling Stock: Rented Priv or with a Job/Business (Thous) | ND4: GBR | NE4: HSA | NF4: JAN003G.db
A5: United Kingdom | B5: Consumer price index | C5: JAN003G | D5: Index | E5: NA | F5: Level | G5: 11.88749 | H5: 12.3046 | I5: 12.51315 | J5: 13.00846 | K5: 13.47771 | L5: 14.23371 | M5: 14.57261 | N5: 15.2504 | O5: 16.05854 | P5: 17.46627 | Q5: 18.22228 | R5: 18.84793 | S5: 19.42145 | T5: 20.12532 | U5: 20.59456 | V5: 21.50698 | W5: 22.47153 | X5: 23.41002 | Y5: 23.82713 | Z5: 24.13995 | AA5: 24.45278 | AB5: 25.07844 | AC5: 25.46948 | AD5: 25.86051 | AE5: 26.43403 | AF5: 27.26824 | AG5: 28.91059 | AH5: 29.71873 | AI5: 30.60508 | AJ5: 32.24743 | AK5: 32.9513 | AL5: 33.55088 | AM5: 34.3851 | AN5: 36.07959 | AO5: 36.73131 | AP5: 37.43518 | AQ5: 37.87835 | AR5: 39.1818 | AS5: 39.41642 | AT5: 39.88567 | AU5: 40.17243 | AV5: 40.85022 | AW5: 41.2934 | AX5: 41.76264 | AY5: 41.86692 | AZ5: 42.77934 | BA5: 42.98789 | BB5: 43.43106 | BC5: 43.87423 | BD5: 44.9952 | BE5: 45.12555 | BF5: 45.49052 | BG5: 45.64693 | BH5: 46.3508 | BI5: 46.53328 | BJ5: 46.92432 | BK5: 47.23714 | BL5: 47.83673 | BM5: 47.88887 | BN5: 48.43632 | BO5: 48.56667 | BP5: 49.5 | BQ5: 49.9 | BR5: 50.46667 | BS5: 51 | BT5: 52.13334 | BU5: 52.46667 | BV5: 53.26667 | BW5: 53.93333 | BX5: 55.6 | BY5: 56.4 | BZ5: 57.46667 | CA5: 57.66667 | CB5: 60.26667 | CC5: 60.83333 | CD5: 61.46667 | CE5: 61.7 | CF5: 62.83333 | CG5: 62.73333 | CH5: 63.13334 | CI5: 63.2 | CJ5: 64.43333 | CK5: 64.5 | CL5: 64.66666 | CM5: 64.76667 | CN5: 65.7 | CO5: 65.63333 | CP5: 65.8 | CQ5: 66.33334 | CR5: 67.26667 | CS5: 67.4 | CT5: 67.73333 | CU5: 68.1 | CV5: 68.86667 | CW5: 68.93333 | CX5: 69.36667 | CY5: 69.36667 | CZ5: 70 | DA5: 70.26667 | DB5: 70.63333 | DC5: 70.5 | DD5: 71.26667 | DE5: 71.23333 | DF5: 71.63333 | DG5: 71.6 | DH5: 72.3 | DI5: 72.13333 | DJ5: 72.43333 | DK5: 72.13333 | DL5: 72.76667 | DM5: 72.7 | DN5: 73.16666 | DO5: 72.76667 | DP5: 73.83334 | DQ5: 73.86667 | DR5: 73.9 | DS5: 73.86667 | DT5: 74.53333 | DU5: 74.6 | DV5: 75 | DW5: 75 | DX5: 75.46667 | DY5: 75.6 | DZ5: 76.03333 | EA5: 75.96667 | EB5: 76.53333 | EC5: 76.56667 | ED5: 77.1 | EE5: 77.23333 | EF5: 78 | EG5: 78.4 | EH5: 78.76667 | EI5: 78.73333 | EJ5: 79.8 | EK5: 80.3 | EL5: 80.9 | EM5: 81 | EN5: 81.8 | EO5: 81.73333 | EP5: 82.6 | EQ5: 82.93333 | ER5: 84.6 | ES5: 85.63333 | ET5: 85.73333 | EU5: 85.43333 | EV5: 86.36667 | EW5: 86.93333 | EX5: 87.56667 | EY5: 88.23333 | EZ5: 89.36667 | FA5: 89.63333 | FB5: 90.5 | FC5: 91.83334 | FD5: 93.3 | FE5: 93.83334 | FF5: 94.73333 | FG5: 95.03333 | FH5: 95.8 | FI5: 96.06667 | FJ5: 97.26667 | FK5: 97.66666 | FL5: 98.36667 | FM5: 98.7 | FN5: 99.3 | FO5: 99.4 | FP5: 100.1 | FQ5: 100.1333 | FR5: 100.2 | FS5: 99.5 | FT5: 100.0667 | FU5: 100.1667 | FV5: 100.3 | FW5: 99.83334 | FX5: 100.4 | FY5: 100.8667 | FZ5: 101.5 | GA5: 102 | GB5: 103.1667 | GC5: 103.7 | GD5: 104.5667 | GE5: 104.7667 | GF5: 105.6667 | GG5: 106.3 | GH5: 106.9333 | GI5: 106.7 | GJ5: 107.8 | GK5: 108.2667 | GL5: 108.4333 | GM5: 108.4667 | GN5: 108.5333 | GO5: 108.9333 | GP5: 109.0667 | GQ5: 109.1667 | GR5: 110.7333 | GS5: 111.9333 | GT5: 114.4 | GU5: 115.9333 | GV5: 120.8667 | GW5: 123.1333 | GX5: 126.7 | GY5: 127.7333 | GZ5: 131.0667 | HA5: 131.4 | HB5: 131.9667 | HC5: 132.2667 | HD5: 133.8333 | HE5: 134.1 | HF5: 135.3304 | HG5: 135.8286 | HH5: 137.4183 | HI5: 138.2367 | HJ5: 139.1495 | HK5: 139.4458 | HL5: 140.7172 | HM5: 141.3141 | HN5: 142.0627 | HO5: 142.3412 | HP5: 143.5906 | HQ5: 144.21 | HR5: 144.9618 | HS5: 145.3065 | HT5: 146.6218 | HU5: 147.3075 | HV5: 148.1067 | HW5: 148.4103 | HX5: 149.7147 | HY5: 150.389 | HZ5: 151.1608 | IA5: 151.4411 | IB5: 152.7486 | IC5: 153.4264 | ID5: 154.1881 | IE5: 154.4699 | IF5: 155.8036 | IG5: 156.4949 | IH5: 157.2719 | II5: 157.5593 | IJ5: 158.9196 | IK5: 159.6248 | IL5: 160.4173 | IM5: 160.7104 | IN5: 162.098 | IO5: 162.8173 | IP5: 163.6257 | IQ5: 163.9247 | IR5: 165.34 | IS5: 166.0737 | IT5: 166.8982 | IU5: 167.2032 | IV5: 168.6468 | IW5: 169.3952 | IX5: 170.2362 | IY5: 170.5472 | IZ5: 172.0197 | JA5: 172.7831 | JB5: 173.6409 | JC5: 173.9582 | JD5: 175.4601 | JE5: 176.2387 | JF5: 177.1137 | JG5: 177.4373 | JH5: 178.9693 | JI5: 179.7635 | JJ5: 180.656 | JK5: 180.9861 | JL5: 182.5487 | JM5: 183.3588 | JN5: 184.2691 | JO5: 184.6058 | JP5: 186.1997 | JQ5: 187.0259 | JR5: 187.9545 | JS5: 188.2979 | JT5: 189.9237 | JU5: 190.7665 | JV5: 191.7136 | JW5: 192.0639 | JX5: 193.7221 | JY5: 194.5818 | JZ5: 195.5479 | KA5: 195.9052 | KB5: 197.5966 | KC5: 198.4734 | KD5: 199.4588 | KE5: 199.8233 | KF5: 201.5485 | KG5: 202.4429 | KH5: 203.448 | KI5: 203.8197 | KJ5: 205.5795 | KK5: 206.4918 | KL5: 207.5169 | KM5: 207.8961 | KN5: 209.6911 | KO5: 210.6216 | KP5: 211.6673 | KQ5: 212.054 | KR5: 213.8849 | KS5: 214.834 | KT5: 215.9006 | KU5: 216.2951 | KV5: 218.1626 | KW5: 219.1307 | KX5: 220.2186 | KY5: 220.621 | KZ5: 222.5258 | LA5: 223.5133 | LB5: 224.623 | LC5: 225.0334 | LD5: 226.9763 | LE5: 227.9836 | LF5: 229.1155 | LG5: 229.5341 | LH5: 231.5159 | LI5: 232.5433 | LJ5: 233.6978 | LK5: 234.1248 | LL5: 236.1462 | LM5: 237.1941 | LN5: 238.3717 | LO5: 238.8073 | LP5: 240.8691 | LQ5: 241.938 | LR5: 243.1392 | LS5: 243.5834 | LT5: 245.6865 | LU5: 246.7768 | LV5: 248.002 | LW5: 248.4551 | LX5: 250.6002 | LY5: 251.7123 | LZ5: 252.962 | MA5: 253.4242 | MB5: 255.6122 | MC5: 256.7466 | MD5: 258.0212 | ME5: 258.4927 | MF5: 260.7245 | MG5: 261.8815 | MH5: 263.1817 | MI5: 263.6625 | MJ5: 265.939 | MK5: 267.1191 | ML5: 268.4453 | MM5: 268.9358 | MN5: 271.2578 | MO5: 272.4615 | MP5: 273.8142 | MQ5: 274.3145 | MR5: 276.6829 | MS5: 277.9107 | MT5: 279.2905 | MU5: Office for National Statistics\Haver Analytics | MV5: False | MW5: NA | MX5: 2015 | MY5: 2024 | MZ5: 3 | NA5: NA | NB5: D7BT@UK | NC5: UK: Consumer Price Index: All Items (NSA, 2015=100) | ND5: GBR | NE5: CPI | NF5: JAN003G.db
A6: United Kingdom | B6: Personal sector debt interest payments | C6: JAN003G | D6: Pound | E6: Millions | F6: Level | G6: 0.001 | H6: 0.001 | I6: 0.001 | J6: 0.001 | K6: 0.001 | L6: 0.001 | M6: 0.001 | N6: 0.001 | O6: 0.001 | P6: 0.001 | Q6: 0.001 | R6: 0.001 | S6: 0.001 | T6: 0.001 | U6: 0.001 | V6: 0.001 | W6: 0.001 | X6: 0.001 | Y6: 0.001 | Z6: 0.001 | AA6: 0.001 | AB6: 0.001 | AC6: 0.001 | AD6: 0.001 | AE6: 0.001 | AF6: 0.001 | AG6: 0.001 | AH6: 0.001 | AI6: 0.001 | AJ6: 0.001 | AK6: 0.001 | AL6: 0.001 | AM6: 0.001 | AN6: 0.001 | AO6: 0.001 | AP6: 0.001 | AQ6: 0.001 | AR6: 0.001 | AS6: 0.001 | AT6: 0.001 | AU6: 0.001 | AV6: 0.001 | AW6: 0.001 | AX6: 0.001 | AY6: 0.001 | AZ6: 0.001 | BA6: 0.001 | BB6: 0.001 | BC6: 0.001 | BD6: 0.001 | BE6: 0.001 | BF6: 0.001 | BG6: 0.001 | BH6: 0.001 | BI6: 0.001 | BJ6: 0.001 | BK6: 5414 | BL6: 5168 | BM6: 5394 | BN6: 5967 | BO6: 5380 | BP6: 5508 | BQ6: 6312 | BR6: 7269 | BS6: 8124 | BT6: 9068 | BU6: 9245 | BV6: 9778 | BW6: 10584 | BX6: 11491 | BY6: 11880 | BZ6: 11492 | CA6: 11454 | CB6: 10793 | CC6: 10251 | CD6: 9965 | CE6: 11073 | CF6: 10082 | CG6: 9682 | CH6: 8436 | CI6: 7548 | CJ6: 7324 | CK6: 7370 | CL6: 7335 | CM6: 7287 | CN6: 7722 | CO6: 7486 | CP6: 7720 | CQ6: 8283 | CR6: 8575 | CS6: 8424 | CT6: 8145 | CU6: 8006 | CV6: 7771 | CW6: 7586 | CX6: 7442 | CY6: 7777 | CZ6: 7915 | DA6: 8565 | DB6: 9175 | DC6: 8666 | DD6: 9118 | DE6: 9637 | DF6: 9759 | DG6: 9118 | DH6: 9051 | DI6: 8086 | DJ6: 9064 | DK6: 10293 | DL6: 10693 | DM6: 10594 | DN6: 10714 | DO6: 10928 | DP6: 10417 | DQ6: 9901 | DR6: 8885 | DS6: 8869 | DT6: 9186 | DU6: 9389 | DV6: 9667 | DW6: 9783 | DX6: 9684 | DY6: 9380 | DZ6: 9776 | EA6: 10893 | EB6: 11972 | EC6: 13528 | ED6: 13991 | EE6: 13856 | EF6: 14772 | EG6: 14859 | EH6: 14939 | EI6: 15223 | EJ6: 15513 | EK6: 16282 | EL6: 17312 | EM6: 18398 | EN6: 19478 | EO6: 20406 | EP6: 22142 | EQ6: 23284 | ER6: 22703 | ES6: 22898 | ET6: 21935 | EU6: 11932 | EV6: 9127 | EW6: 7821 | EX6: 7276 | EY6: 5040 | EZ6: 5486 | FA6: 5317 | FB6: 6037 | FC6: 5808 | FD6: 5796 | FE6: 5851 | FF6: 6471 | FG6: 7183 | FH6: 6818 | FI6: 5954 | FJ6: 5688 | FK6: 6172 | FL6: 5864 | FM6: 5556 | FN6: 5019 | FO6: 6151 | FP6: 7292 | FQ6: 7395 | FR6: 7328 | FS6: 6860 | FT6: 7108 | FU6: 6986 | FV6: 7177 | FW6: 6854 | FX6: 7376 | FY6: 7320 | FZ6: 7133 | GA6: 6108 | GB6: 6097 | GC6: 5495 | GD6: 6078 | GE6: 6779 | GF6: 7442 | GG6: 7727 | GH6: 8288 | GI6: 7874 | GJ6: 6868 | GK6: 6617 | GL6: 6347 | GM6: 5789 | GN6: 4314 | GO6: 4477 | GP6: 4795 | GQ6: 5434 | GR6: 5323 | GS6: 5045 | GT6: 5673 | GU6: 7327 | GV6: 9213 | GW6: 11382 | GX6: 15233 | GY6: 19264 | GZ6: 20144 | HA6: 21848 | HB6: 22912 | HC6: 24190 | HD6: 23230 | HE6: 23505 | HF6: 23314.19 | HG6: 23363.61 | HH6: 23324.59 | HI6: 23113.33 | HJ6: 22980.23 | HK6: 22943.94 | HL6: 22875.24 | HM6: 23135.77 | HN6: 23309.79 | HO6: 23508.72 | HP6: 23500.42 | HQ6: 23444.81 | HR6: 23070.77 | HS6: 22974.02 | HT6: 23043.73 | HU6: 22999.57 | HV6: 23056.78 | HW6: 23195.33 | HX6: 23340 | HY6: 23554.71 | HZ6: 23807.87 | IA6: 24071.61 | IB6: 24347.58 | IC6: 24635.88 | ID6: 24935.67 | IE6: 25237.72 | IF6: 25547.97 | IG6: 25863.64 | IH6: 26187.2 | II6: 26530.95 | IJ6: 26886.22 | IK6: 27241.23 | IL6: 27595.28 | IM6: 27948.95 | IN6: 28301.94 | IO6: 28654.12 | IP6: 29005.06 | IQ6: 29355.55 | IR6: 29705.43 | IS6: 30054.61 | IT6: 30402.64 | IU6: 30742.56 | IV6: 31075.27 | IW6: 31401.69 | IX6: 31722.33 | IY6: 32037.88 | IZ6: 32348.9 | JA6: 32655.96 | JB6: 32959.48 | JC6: 33259.88 | JD6: 33557.52 | JE6: 33852.74 | JF6: 34145.83 | JG6: 34437.07 | JH6: 34726.74 | JI6: 35015.14 | JJ6: 35302.49 | JK6: 35589.03 | JL6: 35874.91 | JM6: 36160.31 | JN6: 36445.43 | JO6: 36730.36 | JP6: 37015.27 | JQ6: 37300.28 | JR6: 37585.5 | JS6: 37871.06 | JT6: 38157.04 | JU6: 38443.4 | JV6: 38730.23 | JW6: 39017.61 | JX6: 39305.59 | JY6: 39594.3 | JZ6: 39883.77 | KA6: 40174.09 | KB6: 40465.31 | KC6: 40757.48 | KD6: 41050.69 | KE6: 41344.98 | KF6: 41640.42 | KG6: 41937.05 | KH6: 42234.89 | KI6: 42534.01 | KJ6: 42834.46 | KK6: 43136.29 | KL6: 43439.52 | KM6: 43744.2 | KN6: 44050.36 | KO6: 44358.05 | KP6: 44667.3 | KQ6: 44978.17 | KR6: 45290.65 | KS6: 45604.81 | KT6: 45920.64 | KU6: 46238.22 | KV6: 46557.57 | KW6: 46878.71 | KX6: 47201.66 | KY6: 47526.47 | KZ6: 47853.17 | LA6: 48181.79 | LB6: 48512.34 | LC6: 48844.87 | LD6: 49179.38 | LE6: 49515.97 | LF6: 49854.67 | LG6: 50195.5 | LH6: 50538.45 | LI6: 50883.21 | LJ6: 51229.77 | LK6: 51578.07 | LL6: 51928.16 | LM6: 52280.02 | LN6: 52633.66 | LO6: 52989.02 | LP6: 53346.14 | LQ6: 53705.01 | LR6: 54065.64 | LS6: 54428.12 | LT6: 54792.4 | LU6: 55158.58 | LV6: 55526.6 | LW6: 55896.52 | LX6: 56268.32 | LY6: 56642.04 | LZ6: 57017.66 | MA6: 57395.2 | MB6: 57774.69 | MC6: 58156.16 | MD6: 58539.59 | ME6: 58925.02 | MF6: 59312.5 | MG6: 59702.07 | MH6: 60093.71 | MI6: 60487.54 | MJ6: 60883.58 | MK6: 61281.86 | ML6: 61682.41 | MM6: 62085.21 | MN6: 62490.34 | MO6: 62897.79 | MP6: 63307.58 | MQ6: 63719.81 | MR6: 64134.52 | MS6: 64551.71 | MT6: 64971.43 | MU6: Office for National Statistics\Haver Analytics | MV6: True | MW6: NA | MX6: NA | MY6: 2024 | MZ6: 3 | NA6: NA | NB6: ROYUQ@UK | NC6: UK: HH & NPISH: Interest, Paid (SA, Mil.GBP) | ND6: GBR | NE6: PEDIP | NF6: JAN003G.db
A7: United Kingdom | B7: Income, personal disposable, nominal, LCU | C7: JAN003G | D7: Pound | E7: Millions | F7: Level | G7: 12419 | H7: 12849 | I7: 13247 | J7: 13917 | K7: 14267 | L7: 14694 | M7: 15881 | N7: 16728 | O7: 18231 | P7: 18613 | Q7: 19564 | R7: 20194 | S7: 21295 | T7: 21568 | U7: 22876 | V7: 23450 | W7: 23884 | X7: 24509 | Y7: 25439 | Z7: 26940 | AA7: 27797 | AB7: 29144 | AC7: 30465 | AD7: 31463 | AE7: 32879 | AF7: 34157 | AG7: 36483 | AH7: 39802 | AI7: 40290 | AJ7: 41818 | AK7: 43433 | AL7: 44864 | AM7: 46552 | AN7: 47036 | AO7: 47924 | AP7: 49843 | AQ7: 50837 | AR7: 52380 | AS7: 52615 | AT7: 53960 | AU7: 54514 | AV7: 57136 | AW7: 57119 | AX7: 58206 | AY7: 59961 | AZ7: 60260 | BA7: 62678 | BB7: 64883 | BC7: 65471 | BD7: 66622 | BE7: 67715 | BF7: 69185 | BG7: 70501 | BH7: 73909 | BI7: 73297 | BJ7: 74329 | BK7: 74158 | BL7: 76563 | BM7: 78295 | BN7: 79796 | BO7: 82285 | BP7: 84810 | BQ7: 86563 | BR7: 88240 | BS7: 90548 | BT7: 93363 | BU7: 97490 | BV7: 98361 | BW7: 102928 | BX7: 103890 | BY7: 107142 | BZ7: 110535 | CA7: 113229 | CB7: 113790 | CC7: 118607 | CD7: 119800 | CE7: 121876 | CF7: 123668 | CG7: 125292 | CH7: 126339 | CI7: 127313 | CJ7: 131724 | CK7: 133457 | CL7: 135003 | CM7: 134597 | CN7: 135173 | CO7: 138183 | CP7: 138391 | CQ7: 141861 | CR7: 143287 | CS7: 146426 | CT7: 147725 | CU7: 151630 | CV7: 153565 | CW7: 156382 | CX7: 154146 | CY7: 156641 | CZ7: 159690 | DA7: 162111 | DB7: 160529 | DC7: 161179 | DD7: 163132 | DE7: 163306 | DF7: 166168 | DG7: 165049 | DH7: 172636 | DI7: 172330 | DJ7: 177162 | DK7: 178102 | DL7: 179721 | DM7: 183528 | DN7: 186259 | DO7: 189667 | DP7: 188957 | DQ7: 190102 | DR7: 191388 | DS7: 194378 | DT7: 196467 | DU7: 196149 | DV7: 198304 | DW7: 200276 | DX7: 201618 | DY7: 204034 | DZ7: 207685 | EA7: 208995 | EB7: 212236 | EC7: 214798 | ED7: 216771 | EE7: 218799 | EF7: 221465 | EG7: 224312 | EH7: 226448 | EI7: 229729 | EJ7: 231892 | EK7: 236075 | EL7: 237463 | EM7: 243111 | EN7: 244614 | EO7: 248998 | EP7: 249640 | EQ7: 249920 | ER7: 256466 | ES7: 255800 | ET7: 258834 | EU7: 256355 | EV7: 263934 | EW7: 262968 | EX7: 263925 | EY7: 264273 | EZ7: 267166 | FA7: 267993 | FB7: 268198 | FC7: 265811 | FD7: 271167 | FE7: 273285 | FF7: 273407 | FG7: 279309 | FH7: 283629 | FI7: 282123 | FJ7: 283875 | FK7: 284075 | FL7: 292417 | FM7: 298338 | FN7: 300976 | FO7: 301406 | FP7: 304476 | FQ7: 303765 | FR7: 307306 | FS7: 311832 | FT7: 319853 | FU7: 327096 | FV7: 327429 | FW7: 326493 | FX7: 328471 | FY7: 328528 | FZ7: 327875 | GA7: 328068 | GB7: 337489 | GC7: 339566 | GD7: 341950 | GE7: 347760 | GF7: 347383 | GG7: 350601 | GH7: 356695 | GI7: 356202 | GJ7: 363432 | GK7: 365191 | GL7: 368137 | GM7: 361420 | GN7: 356361 | GO7: 367470 | GP7: 369157 | GQ7: 374602 | GR7: 378013 | GS7: 380321 | GT7: 381732 | GU7: 386958 | GV7: 395902 | GW7: 403706 | GX7: 422652 | GY7: 428670 | GZ7: 439405 | HA7: 440937 | HB7: 446922 | HC7: 457594 | HD7: 468096 | HE7: 470726 | HF7: 474570.3 | HG7: 479158 | HH7: 483315.9 | HI7: 488358.8 | HJ7: 493110.7 | HK7: 497438.8 | HL7: 501263.1 | HM7: 505136.5 | HN7: 509092.5 | HO7: 513486.7 | HP7: 518220.2 | HQ7: 523262.3 | HR7: 528406.6 | HS7: 533396.8 | HT7: 539115.2 | HU7: 544658.4 | HV7: 549988.1 | HW7: 555188.7 | HX7: 560444.6 | HY7: 565354.6 | HZ7: 570286.1 | IA7: 575331.9 | IB7: 580800.3 | IC7: 585894.5 | ID7: 590941.1 | IE7: 596328.8 | IF7: 602066.1 | IG7: 607532.9 | IH7: 612881.1 | II7: 618276.3 | IJ7: 624033.9 | IK7: 629473.7 | IL7: 634892.9 | IM7: 640504.4 | IN7: 646471.6 | IO7: 652099.4 | IP7: 657694.7 | IQ7: 663476 | IR7: 669560.5 | IS7: 675222 | IT7: 680880.6 | IU7: 686715.4 | IV7: 692963.6 | IW7: 698910.8 | IX7: 704911.9 | IY7: 710972.1 | IZ7: 717144.4 | JA7: 723371.2 | JB7: 729652.5 | JC7: 735988.3 | JD7: 742379.6 | JE7: 748827.3 | JF7: 755331 | JG7: 761892.1 | JH7: 768574.1 | JI7: 775315.6 | JJ7: 782118.1 | JK7: 788981.5 | JL7: 795906.4 | JM7: 802893.4 | JN7: 809943.6 | JO7: 817057.5 | JP7: 824235.6 | JQ7: 831477.1 | JR7: 838782.4 | JS7: 846152.1 | JT7: 853484.4 | JU7: 860879.5 | JV7: 868337.9 | JW7: 875860.1 | JX7: 883446.4 | JY7: 891096.9 | JZ7: 898812.3 | KA7: 906594.3 | KB7: 914441.3 | KC7: 922355.3 | KD7: 930335.6 | KE7: 938383.9 | KF7: 946499 | KG7: 954682.4 | KH7: 962934.6 | KI7: 971255.4 | KJ7: 979646.4 | KK7: 988107.3 | KL7: 996639.8 | KM7: 1005243 | KN7: 1013918 | KO7: 1022666 | KP7: 1031487 | KQ7: 1040381 | KR7: 1049350 | KS7: 1058393 | KT7: 1067512 | KU7: 1076708 | KV7: 1085980 | KW7: 1095330 | KX7: 1104758 | KY7: 1114264 | KZ7: 1123849 | LA7: 1133515 | LB7: 1143260 | LC7: 1153086 | LD7: 1163033 | LE7: 1173062 | LF7: 1183173 | LG7: 1193367 | LH7: 1203356 | LI7: 1213422 | LJ7: 1223517 | LK7: 1233690 | LL7: 1243940 | LM7: 1254270 | LN7: 1264589 | LO7: 1274986 | LP7: 1285460 | LQ7: 1296013 | LR7: 1306646 | LS7: 1317358 | LT7: 1328152 | LU7: 1339026 | LV7: 1349936 | LW7: 1360928 | LX7: 1372001 | LY7: 1383155 | LZ7: 1394355 | MA7: 1405638 | MB7: 1417002 | MC7: 1428450 | MD7: 1439983 | ME7: 1451601 | MF7: 1463304 | MG7: 1475093 | MH7: 1487018 | MI7: 1499031 | MJ7: 1511133 | MK7: 1523325 | ML7: 1535593 | MM7: 1547952 | MN7: 1560402 | MO7: 1572945 | MP7: 1585634 | MQ7: 1598418 | MR7: 1611297 | MS7: 1624272 | MT7: 1637345 | MU7: Office for National Statistics\Haver Analytics | MV7: True | MW7: NA | MX7: NA | MY7: 2024 | MZ7: 3 | NA7: NA | NB7: RPHQQ@UK | NC7: UK: HH & NPISH: Gross Disposable Income (SA, Mil.GBP) | ND7: GBR | NE7: PEDY! | NF7: JAN003G.db
A8: United Kingdom | B8: Mortgage liabilities, household, LCU | C8: JAN003G | D8: Pound | E8: Millions | F8: Level | G8: 15412.93 | H8: 16069.96 | I8: 16751.57 | J8: 17259.36 | K8: 17697.98 | L8: 18131.15 | M8: 18742.68 | N8: 19459.77 | O8: 20188.7 | P8: 20997.7 | Q8: 21876.78 | R8: 22896.9 | S8: 23636.74 | T8: 24579.52 | U8: 25544.14 | V8: 26363.15 | W8: 27088.43 | X8: 27957.5 | Y8: 29076.82 | Z8: 30241.64 | AA8: 31384.62 | AB8: 32667.74 | AC8: 33930.84 | AD8: 35192.12 | AE8: 36493.45 | AF8: 37975.86 | AG8: 39632.09 | AH8: 41122.7 | AI8: 42551.42 | AJ8: 44142.13 | AK8: 45938.5 | AL8: 47827.69 | AM8: 49649.54 | AN8: 51874.53 | AO8: 54199.62 | AP8: 56936.95 | AQ8: 59117.34 | AR8: 62344.26 | AS8: 65846 | AT8: 69524.28 | AU8: 72844.93 | AV8: 76218.35 | AW8: 79988.55 | AX8: 83288.27 | AY8: 86173.92 | AZ8: 90325.41 | BA8: 94470.54 | BB8: 98572.89 | BC8: 102043.7 | BD8: 106177 | BE8: 110989.1 | BF8: 115955.1 | BG8: 120178.5 | BH8: 126107.2 | BI8: 133482 | BJ8: 140406.3 | BK8: 145476 | BL8: 151660 | BM8: 158214 | BN8: 165158 | BO8: 172898 | BP8: 182137 | BQ8: 192178 | BR8: 207268 | BS8: 214900 | BT8: 239325 | BU8: 247567 | BV8: 256572 | BW8: 265313 | BX8: 277370 | BY8: 285601 | BZ8: 293665 | CA8: 301031 | CB8: 307831 | CC8: 314190 | CD8: 319578 | CE8: 325268 | CF8: 330110 | CG8: 336612 | CH8: 339609 | CI8: 342497 | CJ8: 345814 | CK8: 349832 | CL8: 354185 | CM8: 358465 | CN8: 362955 | CO8: 367364 | CP8: 371737 | CQ8: 375738 | CR8: 379402 | CS8: 383252 | CT8: 385484 | CU8: 389315 | CV8: 393930 | CW8: 398362 | CX8: 404008 | CY8: 409822 | CZ8: 414521 | DA8: 418433 | DB8: 423935 | DC8: 428886 | DD8: 434659 | DE8: 440789 | DF8: 448121 | DG8: 456464 | DH8: 465011 | DI8: 474696 | DJ8: 484544 | DK8: 495178 | DL8: 505425 | DM8: 514353 | DN8: 524511 | DO8: 535960 | DP8: 548728 | DQ8: 562531 | DR8: 576559 | DS8: 593114 | DT8: 611788 | DU8: 635900 | DV8: 658331 | DW8: 680848 | DX8: 702297 | DY8: 727495 | DZ8: 755573 | EA8: 783271 | EB8: 808854 | EC8: 833125 | ED8: 857085 | EE8: 875484 | EF8: 897360 | EG8: 918440 | EH8: 941951 | EI8: 965881 | EJ8: 990667 | EK8: 1020748 | EL8: 1050772 | EM8: 1075311 | EN8: 1102655 | EO8: 1135109 | EP8: 1155240 | EQ8: 1163881 | ER8: 1175517 | ES8: 1182695 | ET8: 1184812 | EU8: 1186027 | EV8: 1186228 | EW8: 1188233 | EX8: 1191082 | EY8: 1194551 | EZ8: 1194779 | FA8: 1196087 | FB8: 1196963 | FC8: 1197882 | FD8: 1198695 | FE8: 1199968 | FF8: 1201405 | FG8: 1206854 | FH8: 1220395 | FI8: 1222625 | FJ8: 1224381 | FK8: 1225503 | FL8: 1227711 | FM8: 1230592 | FN8: 1236037 | FO8: 1241977 | FP8: 1248084 | FQ8: 1252854 | FR8: 1255120 | FS8: 1261864 | FT8: 1268659 | FU8: 1276485 | FV8: 1287064 | FW8: 1301745 | FX8: 1307124 | FY8: 1316484 | FZ8: 1322655 | GA8: 1334527 | GB8: 1346308 | GC8: 1357267 | GD8: 1367608 | GE8: 1377742 | GF8: 1382707 | GG8: 1393016 | GH8: 1407469 | GI8: 1415069 | GJ8: 1425628 | GK8: 1437356 | GL8: 1452725 | GM8: 1466672 | GN8: 1469098 | GO8: 1480003 | GP8: 1499098 | GQ8: 1520447 | GR8: 1545627 | GS8: 1552632 | GT8: 1562224 | GU8: 1581336 | GV8: 1596562 | GW8: 1609662 | GX8: 1618526 | GY8: 1619740 | GZ8: 1618505 | HA8: 1619052 | HB8: 1617260 | HC8: 1620501 | HD8: 1626782 | HE8: 1635412 | HF8: 1649396 | HG8: 1667479 | HH8: 1675855 | HI8: 1687204 | HJ8: 1699407 | HK8: 1712318 | HL8: 1725822 | HM8: 1739801 | HN8: 1754228 | HO8: 1769048 | HP8: 1784193 | HQ8: 1800041 | HR8: 1816664 | HS8: 1834053 | HT8: 1852232 | HU8: 1871228 | HV8: 1891058 | HW8: 1911831 | HX8: 1933530 | HY8: 1956105 | HZ8: 1979467 | IA8: 2003614 | IB8: 2028442 | IC8: 2053844 | ID8: 2079679 | IE8: 2105910 | IF8: 2132393 | IG8: 2158997 | IH8: 2185607 | II8: 2212240 | IJ8: 2238809 | IK8: 2265240 | IL8: 2291470 | IM8: 2317569 | IN8: 2343494 | IO8: 2369207 | IP8: 2394678 | IQ8: 2420002 | IR8: 2445152 | IS8: 2470098 | IT8: 2494816 | IU8: 2518550 | IV8: 2541391 | IW8: 2563416 | IX8: 2584694 | IY8: 2605307 | IZ8: 2625314 | JA8: 2644770 | JB8: 2663722 | JC8: 2682211 | JD8: 2700275 | JE8: 2717950 | JF8: 2735266 | JG8: 2752253 | JH8: 2768939 | JI8: 2785352 | JJ8: 2801514 | JK8: 2817445 | JL8: 2833165 | JM8: 2848689 | JN8: 2864035 | JO8: 2879216 | JP8: 2894245 | JQ8: 2909135 | JR8: 2923897 | JS8: 2938541 | JT8: 2953077 | JU8: 2967505 | JV8: 2981836 | JW8: 2996075 | JX8: 3010232 | JY8: 3024313 | JZ8: 3038325 | KA8: 3052274 | KB8: 3066166 | KC8: 3080006 | KD8: 3093800 | KE8: 3107552 | KF8: 3121266 | KG8: 3134947 | KH8: 3148598 | KI8: 3162223 | KJ8: 3175825 | KK8: 3189408 | KL8: 3202975 | KM8: 3216528 | KN8: 3230071 | KO8: 3243605 | KP8: 3257133 | KQ8: 3270658 | KR8: 3284181 | KS8: 3297705 | KT8: 3311232 | KU8: 3324764 | KV8: 3338303 | KW8: 3351850 | KX8: 3365406 | KY8: 3378975 | KZ8: 3392557 | LA8: 3406153 | LB8: 3419766 | LC8: 3433396 | LD8: 3447045 | LE8: 3460716 | LF8: 3474411 | LG8: 3488131 | LH8: 3501873 | LI8: 3515622 | LJ8: 3529380 | LK8: 3543144 | LL8: 3556916 | LM8: 3570698 | LN8: 3584491 | LO8: 3598292 | LP8: 3612103 | LQ8: 3625924 | LR8: 3639759 | LS8: 3653607 | LT8: 3667472 | LU8: 3681353 | LV8: 3695253 | LW8: 3709168 | LX8: 3723102 | LY8: 3737053 | LZ8: 3751024 | MA8: 3765012 | MB8: 3779020 | MC8: 3793047 | MD8: 3807095 | ME8: 3821165 | MF8: 3835257 | MG8: 3849373 | MH8: 3863513 | MI8: 3877681 | MJ8: 3891877 | MK8: 3906102 | ML8: 3920357 | MM8: 3934640 | MN8: 3948953 | MO8: 3963296 | MP8: 3977670 | MQ8: 3992078 | MR8: 4006520 | MS8: 4020997 | MT8: 4035509 | MU8: Bank of England\Haver Analytics | MV8: True | MW8: NA | MX8: NA | MY8: 2024 | MZ8: 3 | NA8: NA | NB8: USVTXKQ@UK | NC8: UK: Lending to Individuals: Mortgages: Net Amount Outstanding (SA, EOP, Mil.GBP) | ND8: GBR | NE8: MRTPE | NF8: JAN003G.db
A9: United Kingdom | B9: Market value of housing stock, LCU | C9: JAN003G | D9: Pound | E9: Millions | F9: Level | G9: 0.001 | H9: 0.001 | I9: 0.001 | J9: 119832.7 | K9: 122370.3 | L9: 124907.9 | M9: 127445.5 | N9: 129983.1 | O9: 132076.7 | P9: 134170.3 | Q9: 136263.8 | R9: 138357.3 | S9: 141704 | T9: 145050.5 | U9: 148397.2 | V9: 151743.8 | W9: 154147.8 | X9: 156551.9 | Y9: 158956 | Z9: 161360.1 | AA9: 168454.4 | AB9: 175548.7 | AC9: 182643 | AD9: 189737.3 | AE9: 204302.3 | AF9: 218867.3 | AG9: 233432.2 | AH9: 247997.2 | AI9: 261614.8 | AJ9: 275232.3 | AK9: 288850 | AL9: 302467.6 | AM9: 307923.7 | AN9: 313379.8 | AO9: 318835.9 | AP9: 324292.1 | AQ9: 328158.8 | AR9: 332025.5 | AS9: 335892.2 | AT9: 339758.9 | AU9: 351743.8 | AV9: 363728.6 | AW9: 375713.4 | AX9: 387698.2 | AY9: 398707.5 | AZ9: 409716.8 | BA9: 420726 | BB9: 431735.3 | BC9: 443187 | BD9: 454638.7 | BE9: 466090.4 | BF9: 477542.2 | BG9: 496159.2 | BH9: 514776.2 | BI9: 533393.1 | BJ9: 552010.1 | BK9: 579627 | BL9: 607243.8 | BM9: 634860.6 | BN9: 662477.5 | BO9: 713302.1 | BP9: 764126.7 | BQ9: 814951.3 | BR9: 865775.9 | BS9: 913980.9 | BT9: 962185.9 | BU9: 1010391 | BV9: 1058596 | BW9: 1060352 | BX9: 1062108 | BY9: 1063864 | BZ9: 1065620 | CA9: 1060645 | CB9: 1055669 | CC9: 1050693 | CD9: 1045717 | CE9: 1039421 | CF9: 1033124 | CG9: 1026827 | CH9: 1020530 | CI9: 1019349 | CJ9: 1018168 | CK9: 1016986 | CL9: 1015805 | CM9: 1026040 | CN9: 1036275 | CO9: 1046509 | CP9: 1056744 | CQ9: 1063008 | CR9: 1069272 | CS9: 1075537 | CT9: 1081801 | CU9: 1102866 | CV9: 1123930 | CW9: 1144995 | CX9: 1166060 | CY9: 1198325 | CZ9: 1230590 | DA9: 1262855 | DB9: 1295120 | DC9: 1319074 | DD9: 1343028 | DE9: 1366983 | DF9: 1390937 | DG9: 1439044 | DH9: 1487151 | DI9: 1535258 | DJ9: 1583365 | DK9: 1633432 | DL9: 1683498 | DM9: 1733565 | DN9: 1783632 | DO9: 1842200 | DP9: 1900768 | DQ9: 1959335 | DR9: 2017903 | DS9: 2136497 | DT9: 2255090 | DU9: 2373684 | DV9: 2492278 | DW9: 2580357 | DX9: 2668436 | DY9: 2756516 | DZ9: 2844595 | EA9: 2948841 | EB9: 3053088 | EC9: 3157334 | ED9: 3261580 | EE9: 3307858 | EF9: 3354137 | EG9: 3400416 | EH9: 3446694 | EI9: 3539721 | EJ9: 3632748 | EK9: 3725775 | EL9: 3818802 | EM9: 3898800 | EN9: 3978798 | EO9: 4058797 | EP9: 4138795 | EQ9: 3988680 | ER9: 3838566 | ES9: 3688451 | ET9: 3538336 | EU9: 3579251 | EV9: 3620166 | EW9: 3661080 | EX9: 3701995 | EY9: 3715905 | EZ9: 3729815 | FA9: 3743725 | FB9: 3757635 | FC9: 3751216 | FD9: 3744798 | FE9: 3738380 | FF9: 3731961 | FG9: 3750445 | FH9: 3768928 | FI9: 3787412 | FJ9: 3805896 | FK9: 3863304 | FL9: 3920712 | FM9: 3978120 | FN9: 4035528 | FO9: 4123194 | FP9: 4210860 | FQ9: 4298526 | FR9: 4386192 | FS9: 4479918 | FT9: 4573644 | FU9: 4667370 | FV9: 4761096 | FW9: 4827210 | FX9: 4893324 | FY9: 4959437 | FZ9: 5025551 | GA9: 5084209 | GB9: 5142867 | GC9: 5201525 | GD9: 5260183 | GE9: 5284850 | GF9: 5309518 | GG9: 5334185 | GH9: 5358852 | GI9: 5376679 | GJ9: 5394506 | GK9: 5412333 | GL9: 5430160 | GM9: 5519583 | GN9: 5609006 | GO9: 5698429 | GP9: 5787852 | GQ9: 5904761 | GR9: 6021670 | GS9: 6138579 | GT9: 6255488 | GU9: 6398738 | GV9: 6541989 | GW9: 6685240 | GX9: 6828490 | GY9: 6788943 | GZ9: 6749396 | HA9: 6709850 | HB9: 6670303 | HC9: 6717539 | HD9: 6833211 | HE9: 6932252 | HF9: 7014472 | HG9: 7144432 | HH9: 7162375 | HI9: 7230575 | HJ9: 7296540 | HK9: 7360890 | HL9: 7428287 | HM9: 7495517 | HN9: 7562274 | HO9: 7628459 | HP9: 7695886 | HQ9: 7764108 | HR9: 7836701 | HS9: 7916221 | HT9: 8003151 | HU9: 8096226 | HV9: 8196165 | HW9: 8301058 | HX9: 8409529 | HY9: 8518840 | HZ9: 8627789 | IA9: 8735075 | IB9: 8841114 | IC9: 8944082 | ID9: 9044942 | IE9: 9143549 | IF9: 9241627 | IG9: 9338049 | IH9: 9434383 | II9: 9530528 | IJ9: 9627598 | IK9: 9723935 | IL9: 9820716 | IM9: 9918182 | IN9: 10017970 | IO9: 10118600 | IP9: 10221370 | IQ9: 10325920 | IR9: 10433560 | IS9: 10542190 | IT9: 10652610 | IU9: 10764150 | IV9: 10877920 | IW9: 10991840 | IX9: 11107110 | IY9: 11228170 | IZ9: 11351900 | JA9: 11476370 | JB9: 11602450 | JC9: 11729860 | JD9: 11859960 | JE9: 11989850 | JF9: 12121440 | JG9: 12254400 | JH9: 12390170 | JI9: 12526770 | JJ9: 12665160 | JK9: 12805020 | JL9: 12947850 | JM9: 13090500 | JN9: 13235040 | JO9: 13381100 | JP9: 13530260 | JQ9: 13679250 | JR9: 13830200 | JS9: 13982690 | JT9: 14138380 | JU9: 14292180 | JV9: 14447970 | JW9: 14605310 | JX9: 14765920 | JY9: 14926270 | JZ9: 15088700 | KA9: 15252720 | KB9: 15420170 | KC9: 15587330 | KD9: 15756680 | KE9: 15927630 | KF9: 16102150 | KG9: 16276360 | KH9: 16452840 | KI9: 16630970 | KJ9: 16812800 | KK9: 16994330 | KL9: 17178220 | KM9: 17363820 | KN9: 17553260 | KO9: 17742370 | KP9: 17933970 | KQ9: 18127340 | KR9: 18324700 | KS9: 18521730 | KT9: 18721330 | KU9: 18922750 | KV9: 19128350 | KW9: 19333600 | KX9: 19541520 | KY9: 19751350 | KZ9: 19965480 | LA9: 20179260 | LB9: 20395860 | LC9: 20614360 | LD9: 20837360 | LE9: 21060680 | LF9: 21286970 | LG9: 21509520 | LH9: 21738810 | LI9: 21961740 | LJ9: 22191760 | LK9: 22416900 | LL9: 22648830 | LM9: 22879450 | LN9: 23117430 | LO9: 23349600 | LP9: 23588760 | LQ9: 23826500 | LR9: 24071790 | LS9: 24312740 | LT9: 24560940 | LU9: 24807690 | LV9: 25062240 | LW9: 25311430 | LX9: 25568100 | LY9: 25823250 | LZ9: 26086460 | MA9: 26344260 | MB9: 26609760 | MC9: 26873650 | MD9: 27145860 | ME9: 27413230 | MF9: 27688580 | MG9: 27962260 | MH9: 28244560 | MI9: 28522750 | MJ9: 28809230 | MK9: 29094010 | ML9: 29387770 | MM9: 29675990 | MN9: 29972850 | MO9: 30267930 | MP9: 30572270 | MQ9: 30872260 | MR9: 31181160 | MS9: 31488310 | MT9: 31805030 | MU9: Office for National Statistics\Haver Analytics | MV9: False | MW9: NA | MX9: NA | MY9: 2023 | MZ9: 4 | NA9: NA | NB9: E46VA@UK + E42YA@UK | NC9: UK: Households: Tangible Fixed Assets: Dwellings (Mil.GBP) +UK: Households: Tangible Assets: Natural Resources (Mil.GBP) | ND9: GBR | NE9: MVH | NF9: JAN003G.db
A10: United Kingdom | B10: Employment, total | C10: JAN003G | D10: Person | E10: Thousands | F10: Level | G10: 27035 | H10: 27023 | I10: 27055 | J10: 27083 | K10: 27055 | L10: 27113 | M10: 27211 | N10: 27154 | O10: 27066 | P10: 27023 | Q10: 26954 | R10: 26881 | S10: 26804 | T10: 26784 | U10: 26775 | V10: 26816 | W10: 26823 | X10: 26823 | Y10: 26846 | Z10: 26872 | AA10: 26943 | AB10: 26988 | AC10: 27092 | AD10: 27274 | AE10: 27303 | AF10: 27413 | AG10: 27493 | AH10: 27542 | AI10: 27465 | AJ10: 27369 | AK10: 27108 | AL10: 26813 | AM10: 26551 | AN10: 26348 | AO10: 26240 | AP10: 26046 | AQ10: 25997 | AR10: 25900 | AS10: 25779 | AT10: 25588 | AU10: 25528 | AV10: 25593 | AW10: 25869 | AX10: 26044 | AY10: 26180 | AZ10: 26296 | BA10: 26406 | BB10: 26508 | BC10: 26566 | BD10: 26610 | BE10: 26667 | BF10: 26655 | BG10: 26622 | BH10: 26654 | BI10: 26754 | BJ10: 26818 | BK10: 26886 | BL10: 27187 | BM10: 27468 | BN10: 27735 | BO10: 27956 | BP10: 28157 | BQ10: 28435 | BR10: 28644 | BS10: 28955 | BT10: 29046 | BU10: 29152 | BV10: 29267 | BW10: 29291 | BX10: 29370 | BY10: 29254 | BZ10: 29046 | CA10: 28742 | CB10: 28445 | CC10: 28265 | CD10: 28129 | CE10: 28124 | CF10: 27966 | CG10: 27542 | CH10: 27417 | CI10: 27533 | CJ10: 27519 | CK10: 27576 | CL10: 27649 | CM10: 27630 | CN10: 27678 | CO10: 27874 | CP10: 27941 | CQ10: 27930 | CR10: 28047 | CS10: 28046 | CT10: 28192 | CU10: 28105 | CV10: 28248 | CW10: 28394 | CX10: 28493 | CY10: 28505 | CZ10: 28760 | DA10: 28897 | DB10: 29022 | DC10: 29045 | DD10: 28948 | DE10: 29049 | DF10: 29213 | DG10: 29237 | DH10: 29327 | DI10: 29584 | DJ10: 29715 | DK10: 29644 | DL10: 29775 | DM10: 29957 | DN10: 30012 | DO10: 30026 | DP10: 30136 | DQ10: 30316 | DR10: 30322 | DS10: 30313 | DT10: 30419 | DU10: 30507 | DV10: 30487 | DW10: 30533 | DX10: 30706 | DY10: 30878 | DZ10: 30898 | EA10: 30976 | EB10: 31030 | EC10: 31065 | ED10: 31215 | EE10: 31353 | EF10: 31401 | EG10: 31543 | EH10: 31633 | EI10: 31702 | EJ10: 31807 | EK10: 31951 | EL10: 32071 | EM10: 31996 | EN10: 32084 | EO10: 32221 | EP10: 32259 | EQ10: 32277 | ER10: 32347 | ES10: 32317 | ET10: 32130 | EU10: 31906 | EV10: 31728 | EW10: 31613 | EX10: 31478 | EY10: 31476 | EZ10: 31558 | FA10: 31514 | FB10: 31567 | FC10: 31634 | FD10: 31557 | FE10: 31785 | FF10: 31803 | FG10: 32147 | FH10: 32093 | FI10: 32035 | FJ10: 31990 | FK10: 32173 | FL10: 32236 | FM10: 32464 | FN10: 32836 | FO10: 33134 | FP10: 33446 | FQ10: 33575 | FR10: 33686 | FS10: 33806 | FT10: 33892 | FU10: 34083 | FV10: 34157 | FW10: 34369 | FX10: 34562 | FY10: 34595 | FZ10: 34669 | GA10: 34846 | GB10: 34856 | GC10: 34960 | GD10: 34874 | GE10: 34946 | GF10: 34972 | GG10: 35075 | GH10: 35244 | GI10: 35438 | GJ10: 35546 | GK10: 35615 | GL10: 35661 | GM10: 35609 | GN10: 35135 | GO10: 34594 | GP10: 34522 | GQ10: 34734 | GR10: 35072 | GS10: 35286 | GT10: 35328 | GU10: 35712 | GV10: 35920 | GW10: 35985 | GX10: 36181 | GY10: 36537 | GZ10: 36304 | HA10: 36429 | HB10: 36506 | HC10: 36791 | HD10: 36720 | HE10: 36793 | HF10: 36930.35 | HG10: 37002.64 | HH10: 37068.86 | HI10: 37149.06 | HJ10: 37253.75 | HK10: 37367.38 | HL10: 37466.47 | HM10: 37575.12 | HN10: 37685.95 | HO10: 37799 | HP10: 37917.33 | HQ10: 38034.12 | HR10: 38145.55 | HS10: 38252.36 | HT10: 38361.37 | HU10: 38466.87 | HV10: 38570.72 | HW10: 38667.38 | HX10: 38754.39 | HY10: 38839.65 | HZ10: 38928.98 | IA10: 39018.52 | IB10: 39108.26 | IC10: 39194.29 | ID10: 39280.52 | IE10: 39366.94 | IF10: 39453.55 | IG10: 39538.37 | IH10: 39621.39 | II10: 39704.61 | IJ10: 39784.01 | IK10: 39863.57 | IL10: 39935.33 | IM10: 40009.92 | IN10: 40078.81 | IO10: 40144.43 | IP10: 40202.44 | IQ10: 40264.46 | IR10: 40318.01 | IS10: 40365.25 | IT10: 40408.67 | IU10: 40454.2 | IV10: 40499.74 | IW10: 40545.27 | IX10: 40590.8 | IY10: 40636.33 | IZ10: 40681.86 | JA10: 40727.4 | JB10: 40772.94 | JC10: 40818.46 | JD10: 40864 | JE10: 40909.54 | JF10: 40955.07 | JG10: 41000.59 | JH10: 41046.13 | JI10: 41091.67 | JJ10: 41137.2 | JK10: 41182.73 | JL10: 41228.26 | JM10: 41273.79 | JN10: 41319.32 | JO10: 41364.86 | JP10: 41410.39 | JQ10: 41455.91 | JR10: 41501.45 | JS10: 41539.61 | JT10: 41577.76 | JU10: 41615.91 | JV10: 41654.06 | JW10: 41692.21 | JX10: 41730.36 | JY10: 41768.5 | JZ10: 41806.67 | KA10: 41844.82 | KB10: 41882.96 | KC10: 41921.12 | KD10: 41959.27 | KE10: 41997.41 | KF10: 42035.57 | KG10: 42073.72 | KH10: 42111.87 | KI10: 42150.03 | KJ10: 42188.17 | KK10: 42226.32 | KL10: 42264.48 | KM10: 42302.63 | KN10: 42340.77 | KO10: 42378.94 | KP10: 42417.08 | KQ10: 42455.23 | KR10: 42493.39 | KS10: 42531.54 | KT10: 42569.69 | KU10: 42607.84 | KV10: 42645.99 | KW10: 42684.14 | KX10: 42722.3 | KY10: 42760.44 | KZ10: 42798.59 | LA10: 42836.75 | LB10: 42874.89 | LC10: 42913.04 | LD10: 42951.2 | LE10: 42989.34 | LF10: 43027.5 | LG10: 43049.7 | LH10: 43071.91 | LI10: 43091.43 | LJ10: 43110.93 | LK10: 43130.44 | LL10: 43149.94 | LM10: 43164.77 | LN10: 43179.61 | LO10: 43194.45 | LP10: 43209.28 | LQ10: 43224.18 | LR10: 43239.09 | LS10: 43253.98 | LT10: 43268.89 | LU10: 43281.6 | LV10: 43294.3 | LW10: 43307.02 | LX10: 43319.72 | LY10: 43330.68 | LZ10: 43341.66 | MA10: 43352.62 | MB10: 43363.58 | MC10: 43374.64 | MD10: 43385.69 | ME10: 43396.75 | MF10: 43407.81 | MG10: 43421.05 | MH10: 43434.3 | MI10: 43447.55 | MJ10: 43460.79 | MK10: 43473.42 | ML10: 43486.04 | MM10: 43498.67 | MN10: 43511.29 | MO10: 43526.16 | MP10: 43541.04 | MQ10: 43555.93 | MR10: 43570.81 | MS10: 43585.71 | MT10: 43600.59 | MU10: Office for National Statistics\Haver Analytics | MV10: True | MW10: NA | MX10: NA | MY10: 2024 | MZ10: 3 | NA10: NA | NB10: DYDCQ@UK | NC10: UK: Total Workforce Jobs [Count of Jobs, Not People] (SA, Thous) | ND10: GBR | NE10: ET | NF10: JAN003G.db
A11: United Kingdom | B11: House price index | C11: JAN003G | D11: Index | E11: NA | F11: Level | G11: 4.095676 | H11: 4.341768 | I11: 4.571398 | J11: 4.696696 | K11: 4.680645 | L11: 4.706662 | M11: 4.742951 | N11: 4.854481 | O11: 4.841668 | P11: 4.966115 | Q11: 5.127897 | R11: 5.224214 | S11: 5.271078 | T11: 5.441458 | U11: 5.563152 | V11: 5.700979 | W11: 5.648953 | X11: 5.759603 | Y11: 5.939249 | Z11: 6.179624 | AA11: 6.242641 | AB11: 6.558394 | AC11: 7.002246 | AD11: 7.579219 | AE11: 7.904714 | AF11: 8.530061 | AG11: 9.177482 | AH11: 9.84895 | AI11: 10.20975 | AJ11: 10.5537 | AK11: 10.96792 | AL11: 11.16152 | AM11: 11.06818 | AN11: 11.35285 | AO11: 11.48035 | AP11: 11.4465 | AQ11: 11.07209 | AR11: 11.50871 | AS11: 11.7407 | AT11: 12.09703 | AU11: 12.35841 | AV11: 12.73169 | AW11: 13.23485 | AX11: 13.54825 | AY11: 13.53342 | AZ11: 13.90046 | BA11: 14.42683 | BB11: 14.82312 | BC11: 14.70458 | BD11: 15.1878 | BE11: 15.51199 | BF11: 16.19555 | BG11: 16.46287 | BH11: 17.18394 | BI11: 17.80274 | BJ11: 18.4965 | BK11: 19.03265 | BL11: 19.86715 | BM11: 20.66235 | BN11: 22.15681 | BO11: 23.03534 | BP11: 24.43553 | BQ11: 27.39136 | BR11: 29.42515 | BS11: 29.96565 | BT11: 31.10817 | BU11: 31.81997 | BV11: 31.62332 | BW11: 30.78288 | BX11: 30.62963 | BY11: 30.78761 | BZ11: 30.83373 | CA11: 30.10122 | CB11: 30.12707 | CC11: 30.35683 | CD11: 30.68695 | CE11: 29.80656 | CF11: 29.16698 | CG11: 28.99895 | CH11: 28.46493 | CI11: 28.18504 | CJ11: 28.48866 | CK11: 28.85863 | CL11: 28.91638 | CM11: 28.77634 | CN11: 29.2086 | CO11: 29.54454 | CP11: 29.96207 | CQ11: 29.21951 | CR11: 29.56666 | CS11: 29.63446 | CT11: 29.85018 | CU11: 29.84769 | CV11: 29.87448 | CW11: 30.82396 | CX11: 32.06892 | CY11: 32.08657 | CZ11: 32.62696 | DA11: 34.04021 | DB11: 34.59001 | DC11: 35.09729 | DD11: 36.75145 | DE11: 38.09626 | DF11: 38.74983 | DG11: 38.70591 | DH11: 39.93301 | DI11: 42.09533 | DJ11: 44.12192 | DK11: 44.94179 | DL11: 46.83976 | DM11: 47.6519 | DN11: 49.97213 | DO11: 49.54191 | DP11: 50.6189 | DQ11: 52.45398 | DR11: 52.23203 | DS11: 54.68787 | DT11: 57.79953 | DU11: 61.26804 | DV11: 65.4624 | DW11: 66.0878 | DX11: 67.73132 | DY11: 69.41682 | DZ11: 72.05366 | EA11: 72.03481 | EB11: 75.88959 | EC11: 79.0879 | ED11: 80.96807 | EE11: 79.623 | EF11: 80.64267 | EG11: 81.70267 | EH11: 82.841 | EI11: 84.707 | EJ11: 86.47266 | EK11: 88.194 | EL11: 90.939 | EM11: 93.66566 | EN11: 95.678 | EO11: 97.267 | EP11: 98.38834 | EQ11: 97.20233 | ER11: 95.07967 | ES11: 90.24033 | ET11: 85.28133 | EU11: 82.117 | EV11: 81.97933 | EW11: 84.097 | EX11: 86.843 | EY11: 88.43266 | EZ11: 88.789 | FA11: 88.88966 | FB11: 88.12267 | FC11: 87.697 | FD11: 87.23033 | FE11: 87.121 | FF11: 87.06167 | FG11: 87.26933 | FH11: 87.73933 | FI11: 87.582 | FJ11: 87.89034 | FK11: 88.39267 | FL11: 89.127 | FM11: 90.14867 | FN11: 91.80233 | FO11: 94.063 | FP11: 96.39167 | FQ11: 98.209 | FR11: 99.56633 | FS11: 100.4063 | FT11: 101.486 | FU11: 103.594 | FV11: 106.041 | FW11: 108.3227 | FX11: 109.635 | FY11: 110.5617 | FZ11: 111.7123 | GA11: 113.0747 | GB11: 114.4267 | GC11: 115.8453 | GD11: 116.88 | GE11: 117.8067 | GF11: 118.479 | GG11: 119.2883 | GH11: 119.7237 | GI11: 119.6083 | GJ11: 119.6167 | GK11: 120.208 | GL11: 120.376 | GM11: 121.501 | GN11: 121.1477 | GO11: 123.2433 | GP11: 127.5473 | GQ11: 130.9 | GR11: 133.0667 | GS11: 133.2333 | GT11: 136.3667 | GU11: 141.6667 | GV11: 144.7667 | GW11: 147.8667 | GX11: 148.8667 | GY11: 147.3667 | GZ11: 146.0667 | HA11: 145.9333 | HB11: 145.0333 | HC11: 145.7667 | HD11: 147.9333 | HE11: 149.8 | HF11: 151.2876 | HG11: 153.7669 | HH11: 153.7972 | HI11: 154.9042 | HJ11: 155.9527 | HK11: 156.9549 | HL11: 158.0012 | HM11: 159.0581 | HN11: 160.0957 | HO11: 161.1105 | HP11: 162.1274 | HQ11: 163.1766 | HR11: 164.3093 | HS11: 165.5768 | HT11: 166.9751 | HU11: 168.5174 | HV11: 170.191 | HW11: 171.9567 | HX11: 173.7679 | HY11: 175.6113 | HZ11: 177.4351 | IA11: 179.2143 | IB11: 180.9387 | IC11: 182.6167 | ID11: 184.2402 | IE11: 185.8086 | IF11: 187.3376 | IG11: 188.8509 | IH11: 190.3515 | II11: 191.8399 | IJ11: 193.3178 | IK11: 194.8 | IL11: 196.2798 | IM11: 197.7652 | IN11: 199.2672 | IO11: 200.8056 | IP11: 202.3749 | IQ11: 203.971 | IR11: 205.5969 | IS11: 207.2624 | IT11: 208.9506 | IU11: 210.6523 | IV11: 212.3654 | IW11: 214.1017 | IX11: 215.8511 | IY11: 217.7045 | IZ11: 219.5761 | JA11: 221.4824 | JB11: 223.4054 | JC11: 225.3453 | JD11: 227.3021 | JE11: 229.2759 | JF11: 231.2673 | JG11: 233.2759 | JH11: 235.3022 | JI11: 237.3659 | JJ11: 239.4479 | JK11: 241.5488 | JL11: 243.6685 | JM11: 245.8071 | JN11: 247.965 | JO11: 250.1423 | JP11: 252.3394 | JQ11: 254.5563 | JR11: 256.7927 | JS11: 259.0489 | JT11: 261.325 | JU11: 263.5895 | JV11: 265.8734 | JW11: 268.1768 | JX11: 270.5 | JY11: 272.8429 | JZ11: 275.2057 | KA11: 277.5885 | KB11: 279.9918 | KC11: 282.4153 | KD11: 284.8595 | KE11: 287.3241 | KF11: 289.8097 | KG11: 292.3159 | KH11: 294.8433 | KI11: 297.3919 | KJ11: 299.9617 | KK11: 302.5532 | KL11: 305.1662 | KM11: 307.8014 | KN11: 310.4583 | KO11: 313.1376 | KP11: 315.8392 | KQ11: 318.5635 | KR11: 321.3104 | KS11: 324.0803 | KT11: 326.8733 | KU11: 329.6896 | KV11: 332.5296 | KW11: 335.3932 | KX11: 338.2807 | KY11: 341.1925 | KZ11: 344.1284 | LA11: 347.0887 | LB11: 350.0738 | LC11: 353.0834 | LD11: 356.1182 | LE11: 359.1902 | LF11: 362.2876 | LG11: 365.4102 | LH11: 368.5586 | LI11: 371.6434 | LJ11: 374.7523 | LK11: 377.8701 | LL11: 381.0117 | LM11: 384.1775 | LN11: 387.3677 | LO11: 390.5547 | LP11: 393.7656 | LQ11: 397.0004 | LR11: 400.2596 | LS11: 403.5435 | LT11: 406.8519 | LU11: 410.1853 | LV11: 413.5437 | LW11: 416.9132 | LX11: 420.3079 | LY11: 423.7277 | LZ11: 427.1725 | MA11: 430.6317 | MB11: 434.116 | MC11: 437.6257 | MD11: 441.1613 | ME11: 444.7232 | MF11: 448.3112 | MG11: 451.9257 | MH11: 455.5667 | MI11: 459.2495 | MJ11: 462.9597 | MK11: 466.6972 | ML11: 470.4626 | MM11: 474.2513 | MN11: 478.0685 | MO11: 481.9135 | MP11: 485.787 | MQ11: 489.706 | MR11: 493.654 | MS11: 497.6316 | MT11: 501.6388 | MU11: HM Land Registry/Haver Analytics | MV11: True | MW11: NA | MX11: Jan-2015 | MY11: 2024 | MZ11: 3 | NA11: NA | NB11: UKSHJ@UK | NC11: UK: House Price Index (SA, Jan-2015=100) | ND11: GBR | NE11: PH | NF11: JAN003G.db
A12: United Kingdom | B12: Population of working age | C12: JAN003G | D12: Person | E12: Thousands | F12: Level | G12: 32742.71 | H12: 32761.06 | I12: 32762.95 | J12: 32764.85 | K12: 32766.74 | L12: 32768.64 | M12: 32767.18 | N12: 32765.72 | O12: 32764.27 | P12: 32762.81 | Q12: 32761.35 | R12: 32759.89 | S12: 32758.44 | T12: 32756.98 | U12: 32808.13 | V12: 32859.29 | W12: 32910.44 | X12: 32961.59 | Y12: 33012.75 | Z12: 33063.9 | AA12: 33115.05 | AB12: 33166.21 | AC12: 33217.36 | AD12: 33268.52 | AE12: 33319.67 | AF12: 33370.82 | AG12: 33421.97 | AH12: 33473.13 | AI12: 33524.28 | AJ12: 33575.43 | AK12: 33626.59 | AL12: 33677.74 | AM12: 33728.89 | AN12: 33780.05 | AO12: 33814.08 | AP12: 33848.12 | AQ12: 33882.15 | AR12: 33916.18 | AS12: 33977.16 | AT12: 34038.13 | AU12: 34099.11 | AV12: 34160.08 | AW12: 34223.9 | AX12: 34287.72 | AY12: 34351.54 | AZ12: 34415.35 | BA12: 34457.95 | BB12: 34500.55 | BC12: 34543.15 | BD12: 34585.75 | BE12: 34620.6 | BF12: 34655.45 | BG12: 34690.29 | BH12: 34725.14 | BI12: 34762.92 | BJ12: 34800.7 | BK12: 34838.48 | BL12: 34876.26 | BM12: 34903.01 | BN12: 34929.77 | BO12: 34956.53 | BP12: 34983.28 | BQ12: 35007.24 | BR12: 35031.2 | BS12: 35055.16 | BT12: 35079.12 | BU12: 35096.11 | BV12: 35113.1 | BW12: 35130.09 | BX12: 35147.07 | BY12: 35159.49 | BZ12: 35171.9 | CA12: 35184.32 | CB12: 35196.73 | CC12: 35199 | CD12: 35201.28 | CE12: 35203.55 | CF12: 35205.82 | CG12: 35206.36 | CH12: 35206.89 | CI12: 35207.43 | CJ12: 35207.96 | CK12: 35219.89 | CL12: 35231.82 | CM12: 35243.75 | CN12: 35255.68 | CO12: 35283.11 | CP12: 35310.53 | CQ12: 35337.95 | CR12: 35365.38 | CS12: 35398.47 | CT12: 35431.57 | CU12: 35464.66 | CV12: 35497.76 | CW12: 35529.27 | CX12: 35560.78 | CY12: 35592.29 | CZ12: 35623.8 | DA12: 35654.31 | DB12: 35684.82 | DC12: 35715.33 | DD12: 35745.84 | DE12: 35791.39 | DF12: 35836.95 | DG12: 35882.5 | DH12: 35928.06 | DI12: 35980.61 | DJ12: 36033.17 | DK12: 36085.72 | DL12: 36138.28 | DM12: 36204.84 | DN12: 36271.4 | DO12: 36337.96 | DP12: 36404.52 | DQ12: 36468.3 | DR12: 36532.09 | DS12: 36595.88 | DT12: 36659.67 | DU12: 36715.11 | DV12: 36770.55 | DW12: 36826 | DX12: 36881.44 | DY12: 36946.64 | DZ12: 37011.85 | EA12: 37077.05 | EB12: 37142.26 | EC12: 37236.98 | ED12: 37331.7 | EE12: 37426.43 | EF12: 37521.15 | EG12: 37602.98 | EH12: 37684.81 | EI12: 37766.64 | EJ12: 37848.46 | EK12: 37914.59 | EL12: 37980.71 | EM12: 38046.83 | EN12: 38112.96 | EO12: 38173.57 | EP12: 38234.18 | EQ12: 38294.8 | ER12: 38355.41 | ES12: 38398.92 | ET12: 38442.42 | EU12: 38485.93 | EV12: 38529.43 | EW12: 38600.79 | EX12: 38672.15 | EY12: 38743.51 | EZ12: 38814.87 | FA12: 38922.02 | FB12: 39029.18 | FC12: 39136.33 | FD12: 39243.48 | FE12: 39301.55 | FF12: 39359.62 | FG12: 39417.69 | FH12: 39475.76 | FI12: 39553.68 | FJ12: 39631.61 | FK12: 39709.53 | FL12: 39787.45 | FM12: 39873.86 | FN12: 39960.25 | FO12: 40046.66 | FP12: 40133.06 | FQ12: 40230.97 | FR12: 40328.88 | FS12: 40426.8 | FT12: 40524.71 | FU12: 40634.79 | FV12: 40744.87 | FW12: 40854.94 | FX12: 40965.02 | FY12: 41060.54 | FZ12: 41156.06 | GA12: 41251.59 | GB12: 41347.11 | GC12: 41441.53 | GD12: 41535.95 | GE12: 41630.37 | GF12: 41724.79 | GG12: 41850.37 | GH12: 41975.95 | GI12: 42101.52 | GJ12: 42227.09 | GK12: 42324.05 | GL12: 42421 | GM12: 42517.95 | GN12: 42614.9 | GO12: 42672.65 | GP12: 42730.41 | GQ12: 42788.16 | GR12: 42845.91 | GS12: 42934.23 | GT12: 43022.56 | GU12: 43110.88 | GV12: 43199.2 | GW12: 43303.79 | GX12: 43408.38 | GY12: 43512.96 | GZ12: 43617.55 | HA12: 43834.18 | HB12: 44050.8 | HC12: 44267.43 | HD12: 44484.05 | HE12: 44578.69 | HF12: 44673.32 | HG12: 44767.96 | HH12: 44862.59 | HI12: 44967.32 | HJ12: 45072.06 | HK12: 45176.79 | HL12: 45281.52 | HM12: 45437.18 | HN12: 45592.84 | HO12: 45748.5 | HP12: 45904.16 | HQ12: 46011.28 | HR12: 46118.41 | HS12: 46225.53 | HT12: 46332.66 | HU12: 46357.18 | HV12: 46381.7 | HW12: 46406.22 | HX12: 46430.75 | HY12: 46446.85 | HZ12: 46462.96 | IA12: 46479.06 | IB12: 46495.17 | IC12: 46506.75 | ID12: 46518.33 | IE12: 46529.91 | IF12: 46541.49 | IG12: 46552.98 | IH12: 46564.46 | II12: 46575.95 | IJ12: 46587.44 | IK12: 46595.95 | IL12: 46604.47 | IM12: 46612.99 | IN12: 46621.51 | IO12: 46626.02 | IP12: 46630.52 | IQ12: 46635.02 | IR12: 46639.53 | IS12: 46643.79 | IT12: 46648.05 | IU12: 46652.3 | IV12: 46656.57 | IW12: 46658.51 | IX12: 46660.45 | IY12: 46662.39 | IZ12: 46664.34 | JA12: 46665.86 | JB12: 46667.38 | JC12: 46668.89 | JD12: 46670.41 | JE12: 46670.68 | JF12: 46670.94 | JG12: 46671.21 | JH12: 46671.47 | JI12: 46672.02 | JJ12: 46672.57 | JK12: 46673.11 | JL12: 46673.66 | JM12: 46693.42 | JN12: 46713.18 | JO12: 46732.95 | JP12: 46752.71 | JQ12: 46781.91 | JR12: 46811.11 | JS12: 46840.32 | JT12: 46869.52 | JU12: 46901.75 | JV12: 46933.98 | JW12: 46966.21 | JX12: 46998.44 | JY12: 47034.39 | JZ12: 47070.35 | KA12: 47106.31 | KB12: 47142.27 | KC12: 47210.38 | KD12: 47278.48 | KE12: 47346.59 | KF12: 47414.7 | KG12: 47544.25 | KH12: 47673.81 | KI12: 47803.36 | KJ12: 47932.92 | KK12: 48034.71 | KL12: 48136.5 | KM12: 48238.3 | KN12: 48340.09 | KO12: 48362.24 | KP12: 48384.4 | KQ12: 48406.55 | KR12: 48428.71 | KS12: 48442.05 | KT12: 48455.4 | KU12: 48468.75 | KV12: 48482.09 | KW12: 48495.46 | KX12: 48508.83 | KY12: 48522.2 | KZ12: 48535.57 | LA12: 48550.09 | LB12: 48564.6 | LC12: 48579.12 | LD12: 48593.63 | LE12: 48606.64 | LF12: 48619.64 | LG12: 48632.64 | LH12: 48645.65 | LI12: 48658.29 | LJ12: 48670.93 | LK12: 48683.58 | LL12: 48696.22 | LM12: 48701.98 | LN12: 48707.75 | LO12: 48713.52 | LP12: 48719.28 | LQ12: 48723.69 | LR12: 48728.09 | LS12: 48732.5 | LT12: 48736.91 | LU12: 48738.93 | LV12: 48740.95 | LW12: 48742.96 | LX12: 48744.98 | LY12: 48741.22 | LZ12: 48737.46 | MA12: 48733.71 | MB12: 48729.95 | MC12: 48727.29 | MD12: 48724.64 | ME12: 48721.99 | MF12: 48719.33 | MG12: 48713.58 | MH12: 48707.82 | MI12: 48702.07 | MJ12: 48696.31 | MK12: 48687.7 | ML12: 48679.1 | MM12: 48670.49 | MN12: 48661.89 | MO12: 48653.8 | MP12: 48645.7 | MQ12: 48637.61 | MR12: 48629.52 | MS12: 48621.43 | MT12: 48613.34 | MU12: Office for National Statistics Population Estimates | MV12: False | MW12: NA | MX12: NA | MY12: 2023 | MZ12: 2 | NA12: NA | NB12: Calculated by Oxford Economics using ONS single-year population estimates. Allows for changing state pension age | NC12: NA | ND12: GBR | NE12: POPW | NF12: JAN003G.db
A13: United Kingdom | B13: Interest rate on housing loans | C13: JAN003G | D13: % | E13: NA | F13: Level | G13: 8.5 | H13: 9.5 | I13: 10 | J13: 11 | K13: 11 | L13: 11 | M13: 11 | N13: 11 | O13: 11 | P13: 11 | Q13: 11 | R13: 11 | S13: 11 | T13: 10.5 | U13: 10.5 | V13: 12.25 | W13: 12.25 | X13: 11.25 | Y13: 10.5 | Z13: 9.5 | AA13: 8.5 | AB13: 8.5 | AC13: 9.75 | AD13: 10.42 | AE13: 11.75 | AF13: 11.246 | AG13: 11.75 | AH13: 13.38 | AI13: 14.7821 | AJ13: 14.8755 | AK13: 14.8876 | AL13: 14.9682 | AM13: 13.8888 | AN13: 13.0457 | AO13: 12.6246 | AP13: 14.7041 | AQ13: 14.5939 | AR13: 13.4576 | AS13: 12.6124 | AT13: 10.9634 | AU13: 9.92754 | AV13: 10.0759 | AW13: 11.2349 | AX13: 11.2541 | AY13: 11.47 | AZ13: 10.51 | BA13: 13.08 | BB13: 12.19 | BC13: 13.25 | BD13: 14.26 | BE13: 13.06 | BF13: 13.01 | BG13: 13 | BH13: 11.06 | BI13: 11.04 | BJ13: 12.32 | BK13: 12.32 | BL13: 11.28 | BM13: 11.28 | BN13: 10.34 | BO13: 10.26 | BP13: 9.78 | BQ13: 11.54 | BR13: 12.75 | BS13: 13.46 | BT13: 13.43 | BU13: 13.48 | BV13: 14.44 | BW13: 15.24 | BX13: 15.25 | BY13: 15.25 | BZ13: 14.34 | CA13: 14.24 | CB13: 12.75 | CC13: 11.82 | CD13: 11.39 | CE13: 10.96 | CF13: 10.82 | CG13: 10.6 | CH13: 8.98 | CI13: 8.04 | CJ13: 8.01 | CK13: 8 | CL13: 7.94 | CM13: 7.66 | CN13: 7.61 | CO13: 7.57 | CP13: 7.84 | CQ13: 8 | CR13: 7.95 | CS13: 7.9 | CT13: 7.48 | CU13: 7.03 | CV13: 6.71 | CW13: 6.45 | CX13: 6.51 | CY13: 6.66 | CZ13: 6.98 | DA13: 7.5 | DB13: 7.58 | DC13: 7.77 | DD13: 7.78 | DE13: 7.99 | DF13: 7.29 | DG13: 7.17 | DH13: 6.74 | DI13: 6.616667 | DJ13: 6.756667 | DK13: 7.056667 | DL13: 7.143333 | DM13: 7.113333 | DN13: 7.056667 | DO13: 6.936666 | DP13: 6.613333 | DQ13: 6.35 | DR13: 5.846667 | DS13: 5.513333 | DT13: 5.436666 | DU13: 5.313334 | DV13: 5.296667 | DW13: 5.173333 | DX13: 5.01 | DY13: 4.85 | DZ13: 4.806667 | EA13: 4.983333 | EB13: 5.103333 | EC13: 5.463333 | ED13: 5.573333 | EE13: 5.53 | EF13: 5.503334 | EG13: 5.476666 | EH13: 5.35 | EI13: 5.326667 | EJ13: 5.31 | EK13: 5.33 | EL13: 5.45 | EM13: 5.623333 | EN13: 5.703333 | EO13: 5.883333 | EP13: 5.95 | EQ13: 5.856667 | ER13: 5.763333 | ES13: 5.796667 | ET13: 5.386667 | EU13: 4.083333 | EV13: 3.6 | EW13: 3.576667 | EX13: 3.573333 | EY13: 3.666667 | EZ13: 3.66 | FA13: 3.57 | FB13: 3.506667 | FC13: 3.496667 | FD13: 3.47 | FE13: 3.4 | FF13: 3.366667 | FG13: 3.366667 | FH13: 3.38 | FI13: 3.373333 | FJ13: 3.38 | FK13: 3.366667 | FL13: 3.343333 | FM13: 3.316667 | FN13: 3.28 | FO13: 3.25 | FP13: 3.233333 | FQ13: 3.213333 | FR13: 3.186667 | FS13: 3.153333 | FT13: 3.106667 | FU13: 3.056667 | FV13: 3.01 | FW13: 2.95 | FX13: 2.903333 | FY13: 2.82 | FZ13: 2.686667 | GA13: 2.626667 | GB13: 2.586667 | GC13: 2.533333 | GD13: 2.516667 | GE13: 2.52 | GF13: 2.483333 | GG13: 2.48 | GH13: 2.493333 | GI13: 2.463333 | GJ13: 2.436667 | GK13: 2.413333 | GL13: 2.386667 | GM13: 2.356667 | GN13: 2.183333 | GO13: 2.143333 | GP13: 2.12 | GQ13: 2.09 | GR13: 2.073333 | GS13: 2.053333 | GT13: 2.02 | GU13: 2.026667 | GV13: 2.083333 | GW13: 2.186667 | GX13: 2.396667 | GY13: 2.65 | GZ13: 2.84 | HA13: 3.07 | HB13: 3.29 | HC13: 3.473333 | HD13: 3.62 | HE13: 3.726667 | HF13: 3.785922 | HG13: 3.828435 | HH13: 3.864858 | HI13: 3.851563 | HJ13: 3.854572 | HK13: 3.875977 | HL13: 3.884705 | HM13: 3.927681 | HN13: 3.965974 | HO13: 3.994157 | HP13: 3.988577 | HQ13: 3.954865 | HR13: 3.863932 | HS13: 3.81515 | HT13: 3.775739 | HU13: 3.708153 | HV13: 3.661746 | HW13: 3.631224 | HX13: 3.600939 | HY13: 3.583342 | HZ13: 3.571728 | IA13: 3.560345 | IB13: 3.549635 | IC13: 3.539686 | ID13: 3.530546 | IE13: 3.521797 | IF13: 3.5142 | IG13: 3.507375 | IH13: 3.501946 | II13: 3.499975 | IJ13: 3.499979 | IK13: 3.499983 | IL13: 3.499985 | IM13: 3.499987 | IN13: 3.499988 | IO13: 3.499989 | IP13: 3.499989 | IQ13: 3.499991 | IR13: 3.499992 | IS13: 3.499991 | IT13: 3.49999 | IU13: 3.499992 | IV13: 3.499994 | IW13: 3.499996 | IX13: 3.499997 | IY13: 3.499998 | IZ13: 3.499999 | JA13: 3.499999 | JB13: 3.499999 | JC13: 3.499999 | JD13: 3.499998 | JE13: 3.499998 | JF13: 3.499999 | JG13: 3.499999 | JH13: 3.499999 | JI13: 3.5 | JJ13: 3.5 | JK13: 3.5 | JL13: 3.5 | JM13: 3.5 | JN13: 3.5 | JO13: 3.500001 | JP13: 3.500001 | JQ13: 3.5 | JR13: 3.5 | JS13: 3.5 | JT13: 3.499999 | JU13: 3.499998 | JV13: 3.499999 | JW13: 3.499998 | JX13: 3.499998 | JY13: 3.499998 | JZ13: 3.499999 | KA13: 3.499999 | KB13: 3.499999 | KC13: 3.5 | KD13: 3.499999 | KE13: 3.499999 | KF13: 3.499998 | KG13: 3.499999 | KH13: 3.5 | KI13: 3.5 | KJ13: 3.499999 | KK13: 3.5 | KL13: 3.5 | KM13: 3.5 | KN13: 3.5 | KO13: 3.5 | KP13: 3.5 | KQ13: 3.5 | KR13: 3.500001 | KS13: 3.500001 | KT13: 3.500001 | KU13: 3.500001 | KV13: 3.5 | KW13: 3.500001 | KX13: 3.500001 | KY13: 3.500001 | KZ13: 3.500001 | LA13: 3.500001 | LB13: 3.500001 | LC13: 3.5 | LD13: 3.500001 | LE13: 3.500001 | LF13: 3.5 | LG13: 3.500001 | LH13: 3.500001 | LI13: 3.500001 | LJ13: 3.500001 | LK13: 3.5 | LL13: 3.5 | LM13: 3.500001 | LN13: 3.500001 | LO13: 3.5 | LP13: 3.5 | LQ13: 3.500001 | LR13: 3.500001 | LS13: 3.5 | LT13: 3.5 | LU13: 3.5 | LV13: 3.5 | LW13: 3.5 | LX13: 3.5 | LY13: 3.5 | LZ13: 3.500001 | MA13: 3.5 | MB13: 3.5 | MC13: 3.5 | MD13: 3.5 | ME13: 3.500001 | MF13: 3.5 | MG13: 3.5 | MH13: 3.500001 | MI13: 3.5 | MJ13: 3.5 | MK13: 3.5 | ML13: 3.5 | MM13: 3.5 | MN13: 3.499999 | MO13: 3.5 | MP13: 3.5 | MQ13: 3.500001 | MR13: 3.5 | MS13: 3.5 | MT13: 3.499999 | MU13: Bank of England\Haver Analytics | MV13: False | MW13: NA | MX13: NA | MY13: 2024 | MZ13: 3 | NA13: NA | NB13: UNHSDE@UK,EOP | NC13: UK: Banks Weighted Avg Interest Rate, HH Loans Secured on Dwellings (%) | ND13: GBR | NE13: RBM | NF13: JAN003G.db
... A29: United Kingdom | B29: GDP, nominal, LCU | C29: JAN003G | D29: Pound | E29: Millions | F29: Level | G29: 20046 | H29: 19874 | I29: 20558 | J29: 21315 | K29: 21132 | L29: 22651 | M29: 23896 | N29: 24994 | O29: 26814 | P29: 28129 | Q29: 29260 | R29: 30890 | S29: 32449 | T29: 33322 | U29: 34550 | V29: 36678 | W29: 38038 | X29: 39244 | Y29: 40339 | Z29: 42165 | AA29: 44140 | AB29: 45905 | AC29: 47207 | AD29: 48906 | AE29: 50459 | AF29: 53966 | AG29: 56767 | AH29: 59789 | AI29: 62107 | AJ29: 63704 | AK29: 66021 | AL29: 68138 | AM29: 69940 | AN29: 71334 | AO29: 73310 | AP29: 75596 | AQ29: 77468 | AR29: 78993 | AS29: 80430 | AT29: 82667 | AU29: 85727 | AV29: 86288 | AW29: 88637 | AX29: 90695 | AY29: 91663 | AZ29: 93433 | BA29: 94862 | BB29: 97962 | BC29: 99412 | BD29: 103208 | BE29: 105169 | BF29: 106841 | BG29: 108753 | BH29: 110079 | BI29: 111989 | BJ29: 115779 | BK29: 118136 | BL29: 121739 | BM29: 127119 | BN29: 129815 | BO29: 133283 | BP29: 136630 | BQ29: 140801 | BR29: 144969 | BS29: 148623 | BT29: 151262 | BU29: 155370 | BV29: 159376 | BW29: 163056 | BX29: 166719 | BY29: 170068 | BZ29: 170954 | CA29: 173192 | CB29: 175822 | CC29: 177280 | CD29: 179590 | CE29: 181438 | CF29: 181889 | CG29: 182558 | CH29: 184989 | CI29: 189580 | CJ29: 189802 | CK29: 193552 | CL29: 196921 | CM29: 199796 | CN29: 200691 | CO29: 203292 | CP29: 207015 | CQ29: 208657 | CR29: 210748 | CS29: 214616 | CT29: 217824 | CU29: 221433 | CV29: 226187 | CW29: 229912 | CX29: 232461 | CY29: 232749 | CZ29: 235998 | DA29: 243388 | DB29: 241270 | DC29: 245958 | DD29: 248081 | DE29: 250560 | DF29: 253902 | DG29: 255903 | DH29: 258404 | DI29: 261604 | DJ29: 267337 | DK29: 272305 | DL29: 273916 | DM29: 276174 | DN29: 278357 | DO29: 282889 | DP29: 286728 | DQ29: 288166 | DR29: 288352 | DS29: 292486 | DT29: 295516 | DU29: 299230 | DV29: 304207 | DW29: 307485 | DX29: 312948 | DY29: 317463 | DZ29: 320438 | EA29: 322778 | EB29: 329732 | EC29: 331592 | ED29: 338535 | EE29: 341254 | EF29: 348491 | EG29: 352001 | EH29: 357003 | EI29: 361213 | EJ29: 367042 | EK29: 370883 | EL29: 372900 | EM29: 376958 | EN29: 386144 | EO29: 389291 | EP29: 392244 | EQ29: 397800 | ER29: 400685 | ES29: 399994 | ET29: 395121 | EU29: 386874 | EV29: 386553 | EW29: 388596 | EX29: 386779 | EY29: 396176 | EZ29: 401223 | FA29: 404365 | FB29: 406789 | FC29: 414806 | FD29: 412364 | FE29: 416115 | FF29: 419305 | FG29: 424540 | FH29: 424939 | FI29: 430964 | FJ29: 433272 | FK29: 438283 | FL29: 442095 | FM29: 448800 | FN29: 452183 | FO29: 457683 | FP29: 461549 | FQ29: 470624 | FR29: 472658 | FS29: 474680 | FT29: 476591 | FU29: 479924 | FV29: 485256 | FW29: 489683 | FX29: 493710 | FY29: 500801 | FZ29: 507451 | GA29: 513814 | GB29: 517656 | GC29: 521257 | GD29: 529755 | GE29: 531131 | GF29: 535707 | GG29: 540205 | GH29: 545261 | GI29: 549060 | GJ29: 556104 | GK29: 562999 | GL29: 565758 | GM29: 555891 | GN29: 476160 | GO29: 533806 | GP29: 537629 | GQ29: 537992 | GR29: 568521 | GS29: 581805 | GT29: 597082 | GU29: 610346 | GV29: 625467 | GW29: 636553 | GX29: 654062 | GY29: 667103 | GZ29: 679433 | HA29: 685035 | HB29: 685749 | HC29: 697617 | HD29: 704470 | HE29: 712652 | HF29: 719720.4 | HG29: 729288.2 | HH29: 737176.1 | HI29: 744686.1 | HJ29: 752089.5 | HK29: 759365.1 | HL29: 766253.6 | HM29: 773550.1 | HN29: 780877.1 | HO29: 788391.3 | HP29: 796057.8 | HQ29: 803837.6 | HR29: 811572.8 | HS29: 819300.7 | HT29: 827143.4 | HU29: 834895.3 | HV29: 842677.6 | HW29: 850447.9 | HX29: 858161.3 | HY29: 865815.8 | HZ29: 873538.4 | IA29: 881417.8 | IB29: 889457 | IC29: 897703 | ID29: 906092.9 | IE29: 914561.5 | IF29: 923109.6 | IG29: 931690.8 | IH29: 940304.7 | II29: 948998.8 | IJ29: 957773.3 | IK29: 966724.7 | IL29: 975662.8 | IM29: 984848.1 | IN29: 994074.5 | IO29: 1003302 | IP29: 1012523 | IQ29: 1021980 | IR29: 1031356 | IS29: 1040759 | IT29: 1050146 | IU29: 1059725 | IV29: 1069390 | IW29: 1079139 | IX29: 1088974 | IY29: 1098991 | IZ29: 1109100 | JA29: 1119304 | JB29: 1129602 | JC29: 1139995 | JD29: 1150484 | JE29: 1161070 | JF29: 1171756 | JG29: 1182649 | JH29: 1193646 | JI29: 1204747 | JJ29: 1215953 | JK29: 1227266 | JL29: 1238685 | JM29: 1250214 | JN29: 1261853 | JO29: 1273602 | JP29: 1285460 | JQ29: 1297429 | JR29: 1309510 | JS29: 1321545 | JT29: 1333689 | JU29: 1345945 | JV29: 1358310 | JW29: 1370788 | JX29: 1383379 | JY29: 1396083 | JZ29: 1408904 | KA29: 1421824 | KB29: 1434861 | KC29: 1448015 | KD29: 1461286 | KE29: 1474676 | KF29: 1488185 | KG29: 1501815 | KH29: 1515566 | KI29: 1529439 | KJ29: 1543436 | KK29: 1557558 | KL29: 1571805 | KM29: 1586179 | KN29: 1600679 | KO29: 1615309 | KP29: 1630069 | KQ29: 1644961 | KR29: 1659984 | KS29: 1675140 | KT29: 1690432 | KU29: 1705860 | KV29: 1721424 | KW29: 1737126 | KX29: 1752968 | KY29: 1768949 | KZ29: 1785073 | LA29: 1801338 | LB29: 1817747 | LC29: 1834300 | LD29: 1850998 | LE29: 1867839 | LF29: 1884828 | LG29: 1901508 | LH29: 1918327 | LI29: 1935206 | LJ29: 1952224 | LK29: 1969380 | LL29: 1986678 | LM29: 2003976 | LN29: 2021412 | LO29: 2038987 | LP29: 2056704 | LQ29: 2074564 | LR29: 2092567 | LS29: 2110714 | LT29: 2129007 | LU29: 2147375 | LV29: 2165889 | LW29: 2184549 | LX29: 2203355 | LY29: 2222254 | LZ29: 2241301 | MA29: 2260493 | MB29: 2279839 | MC29: 2299340 | MD29: 2318992 | ME29: 2338801 | MF29: 2358764 | MG29: 2378962 | MH29: 2399320 | MI29: 2419841 | MJ29: 2440524 | MK29: 2461347 | ML29: 2482336 | MM29: 2503516 | MN29: 2524865 | MO29: 2546468 | MP29: 2568243 | MQ29: 2590193 | MR29: 2612318 | MS29: 2634618 | MT29: 2657099 | MU29: Office for National Statistics\Haver Analytics | MV29: True | MW29: NA | MX29: NA | MY29: 2024 | MZ29: 3 | NA29: NA | NB29: YBHAQ@UK | NC29: U.K.: Gross Domestic Product (SA, Mil.Pounds) | ND29: GBR | NE29: GDP! | NF29: JAN003G.db

Sheet DataQ
C1: JAN003G.db | D1: =$C$1 -> JAN003G.db | E1: =$C$1 -> JAN003G.db | F1: =$C$1 -> JAN003G.db | G1: =$C$1 -> JAN003G.db | H1: =$C$1 -> JAN003G.db | I1: =$C$1 -> JAN003G.db | J1: =$C$1 -> JAN003G.db | K1: =$C$1 -> JAN003G.db | ... W1: =$C$1 -> JAN003G.db
C2: UK | D2: UK | E2: UK | F2: UK | G2: UK | H2: UK | I2: UK | J2: UK | K2: UK | L2: UK | M2: UK | N2: UK | O2: UK | P2: UK | Q2: UK | R2: UK | S2: UK | T2: UK | U2: UK | V2: UK | W2: UK
C3: NOMORT | D3: PEDIP | E3: PEDY! | F3: UPILO | G3: LNPE | H3: PEDIP_UNADJ | I3: MRTPE | J3: RBM | K3: WORMRT | L3: HHLIAB | M3: HHLIAB% | N3: HHLIAB%Y | O3: PINSOLV | P3: RRH | Q3: PCC | R3: OLPE | S3: MVH | T3: POPW | U3: RCON | V3: ARR | W3: REPO
C4: GBR | D4: GBR | E4: GBR | F4: GBR | G4: GBR | H4: GBR | I4: GBR | J4: GBR | K4: GBR | L4: GBR | M4: GBR | N4: GBR | O4: GBR | P4: GBR | Q4: GBR | R4: GBR | S4: GBR | T4: GBR | U4: GBR | V4: GBR | W4: GBR
C5: L | D5: L | E5: L | F5: L | G5: L | H5: L | I5: L | J5: L | K5: L | L5: L | M5: L | N5: L | O5: L | P5: L | Q5: L | R5: L | S5: L | T5: L | U5: L | V5: L | W5: L
B6: =B358+5 -> 2329 | C6: {=_xlfn.CONCAT(INDEX(GMWQ!$A$2:$NF$60,MATCH(1,(GMWQ!$NE$2:$NE$60=C$3)*(GMWQ!$NF$2:$NF$60=C$1),0),$B6-1966),"0",(INDEX(GMWQ!$A$2:$NF$60,MATCH(1,(GMWQ!$NE$2:$NE$60=C$3)*(GMWQ!$NF$2:$NF$60=C$1),0),$B6-1965)))} -> 202304 | D6: {=_xlfn.CONCAT(INDEX(GMWQ!$A$2:$NF$60,MATCH(1,(GMWQ!$NE$2:$NE$60=D$3)*(GMWQ!$NF$2:$NF$60=D$1),0),$B6-1966),"0",(INDEX(GMWQ!$A$2:$NF$60,MATCH(1,(GMWQ!$NE$2:$NE$60=D$3)*(GMWQ!$NF$2:$NF$60=D$1),0),$B6-1965)))} -> 202403 | E6: {=_xlfn.CONCAT(INDEX(GMWQ!$A$2:$NF$60,MATCH(1,(GMWQ!$NE$2:$NE$60=E$3)*(GMWQ!$NF$2:$NF$60=E$1),0),$B6-1966),"0",(INDEX(GMWQ!$A$2:$NF$60,MATCH(1,(GMWQ!$NE$2:$NE$60=E$3)*(GMWQ!$NF$2:$NF$60=E$1),0),$B6-1965)))} -> 202403 | F6: {=_xlfn.CONCAT(INDEX(GMWQ!$A$2:$NF$60,MATCH(1,(GMWQ!$NE$2:$NE$60=F$3)*(GMWQ!$NF$2:$NF$60=F$1),0),$B6-1966),"0",(INDEX(GMWQ!$A$2:$NF$60,MATCH(1,(GMWQ!$NE$2:$NE$60=F$3)*(GMWQ!$NF$2:$NF$60=F$1),0),$B6-1965)))} -> 202403 | G6: {=_xlfn.CONCAT(INDEX(GMWQ!$A$2:$NF$60,MATCH(1,(GMWQ!$NE$2:$NE$60=G$3)*(GMWQ!$NF$2:$NF$60=G$1),0),$B6-1966),"0",(INDEX(GMWQ!$A$2:$NF$60,MATCH(1,(GMWQ!$NE$2:$NE$60=G$3)*(GMWQ!$NF$2:$NF$60=G$1),0),$B6-1965)))} -> 202403 | H6: {=_xlfn.CONCAT(INDEX(GMWQ!$A$2:$NF$60,MATCH(1,(GMWQ!$NE$2:$NE$60=H$3)*(GMWQ!$NF$2:$NF$60=H$1),0),$B6-1966),"0",(INDEX(GMWQ!$A$2:$NF$60,MATCH(1,(GMWQ!$NE$2:$NE$60=H$3)*(GMWQ!$NF$2:$NF$60=H$1),0),$B6-1965)))} -> 202403 | I6: {=_xlfn.CONCAT(INDEX(GMWQ!$A$2:$NF$60,MATCH(1,(GMWQ!$NE$2:$NE$60=I$3)*(GMWQ!$NF$2:$NF$60=I$1),0),$B6-1966),"0",(INDEX(GMWQ!$A$2:$NF$60,MATCH(1,(GMWQ!$NE$2:$NE$60=I$3)*(GMWQ!$NF$2:$NF$60=I$1),0),$B6-1965)))} -> 202403 | J6: {=_xlfn.CONCAT(INDEX(GMWQ!$A$2:$NF$60,MATCH(1,(GMWQ!$NE$2:$NE$60=J$3)*(GMWQ!$NF$2:$NF$60=J$1),0),$B6-1966),"0",(INDEX(GMWQ!$A$2:$NF$60,MATCH(1,(GMWQ!$NE$2:$NE$60=J$3)*(GMWQ!$NF$2:$NF$60=J$1),0),$B6-1965)))} -> 202403 | ... W6: {=_xlfn.CONCAT(INDEX(GMWQ!$A$2:$NF$60,MATCH(1,(GMWQ!$NE$2:$NE$60=W$3)*(GMWQ!$NF$2:$NF$60=W$1),0),$B6-1966),"0",(INDEX(GMWQ!$A$2:$NF$60,MATCH(1,(GMWQ!$NE$2:$NE$60=W$3)*(GMWQ!$NF$2:$NF$60=W$1),0),$B6-1965)))} -> 202403
A7: 1973 | B7: 1973 | C7: {=INDEX(GMWQ!$A$2:$NF$60,MATCH(1,(GMWQ!$NE$2:$NE$60=C$3)*(GMWQ!$NF$2:$NF$60=C$1),0),$B7-1966)} -> 4793 | D7: {=INDEX(GMWQ!$A$2:$NF$60,MATCH(1,(GMWQ!$NE$2:$NE$60=D$3)*(GMWQ!$NF$2:$NF$60=D$1),0),$B7-1966)} -> 0.001 | E7: {=INDEX(GMWQ!$A$2:$NF$60,MATCH(1,(GMWQ!$NE$2:$NE$60=E$3)*(GMWQ!$NF$2:$NF$60=E$1),0),$B7-1966)} -> 12419 | F7: {=INDEX(GMWQ!$A$2:$NF$60,MATCH(1,(GMWQ!$NE$2:$NE$60=F$3)*(GMWQ!$NF$2:$NF$60=F$1),0),$B7-1966)} -> 3.9 | G7: {=INDEX(GMWQ!$A$2:$NF$60,MATCH(1,(GMWQ!$NE$2:$NE$60=G$3)*(GMWQ!$NF$2:$NF$60=G$1),0),$B7-1966)} -> 0 | H7: {=INDEX(GMWQ!$A$2:$NF$60,MATCH(1,(GMWQ!$NE$2:$NE$60=H$3)*(GMWQ!$NF$2:$NF$60=H$1),0),$B7-1966)} -> 0.001 | I7: {=INDEX(GMWQ!$A$2:$NF$60,MATCH(1,(GMWQ!$NE$2:$NE$60=I$3)*(GMWQ!$NF$2:$NF$60=I$1),0),$B7-1966)} -> 15412.93 | J7: {=INDEX(GMWQ!$A$2:$NF$60,MATCH(1,(GMWQ!$NE$2:$NE$60=J$3)*(GMWQ!$NF$2:$NF$60=J$1),0),$B7-1966)} -> 8.5 | ... W7: {=INDEX(GMWQ!$A$2:$NF$60,MATCH(1,(GMWQ!$NE$2:$NE$60=W$3)*(GMWQ!$NF$2:$NF$60=W$1),0),$B7-1966)} -> 0.001
B8: =+B7+1 -> 1974 | C8: {=INDEX(GMWQ!$A$2:$NF$60,MATCH(1,(GMWQ!$NE$2:$NE$60=C$3)*(GMWQ!$NF$2:$NF$60=C$1),0),$B8-1966)} -> 4816 | D8: {=INDEX(GMWQ!$A$2:$NF$60,MATCH(1,(GMWQ!$NE$2:$NE$60=D$3)*(GMWQ!$NF$2:$NF$60=D$1),0),$B8-1966)} -> 0.001 | E8: {=INDEX(GMWQ!$A$2:$NF$60,MATCH(1,(GMWQ!$NE$2:$NE$60=E$3)*(GMWQ!$NF$2:$NF$60=E$1),0),$B8-1966)} -> 12849 | F8: {=INDEX(GMWQ!$A$2:$NF$60,MATCH(1,(GMWQ!$NE$2:$NE$60=F$3)*(GMWQ!$NF$2:$NF$60=F$1),0),$B8-1966)} -> 3.7 | G8: {=INDEX(GMWQ!$A$2:$NF$60,MATCH(1,(GMWQ!$NE$2:$NE$60=G$3)*(GMWQ!$NF$2:$NF$60=G$1),0),$B8-1966)} -> 0 | H8: {=INDEX(GMWQ!$A$2:$NF$60,MATCH(1,(GMWQ!$NE$2:$NE$60=H$3)*(GMWQ!$NF$2:$NF$60=H$1),0),$B8-1966)} -> 0.001 | I8: {=INDEX(GMWQ!$A$2:$NF$60,MATCH(1,(GMWQ!$NE$2:$NE$60=I$3)*(GMWQ!$NF$2:$NF$60=I$1),0),$B8-1966)} -> 16069.96 | J8: {=INDEX(GMWQ!$A$2:$NF$60,MATCH(1,(GMWQ!$NE$2:$NE$60=J$3)*(GMWQ!$NF$2:$NF$60=J$1),0),$B8-1966)} -> 9.5 | ... W8: {=INDEX(GMWQ!$A$2:$NF$60,MATCH(1,(GMWQ!$NE$2:$NE$60=W$3)*(GMWQ!$NF$2:$NF$60=W$1),0),$B8-1966)} -> 0.001
B9: =+B8+1 -> 1975 | C9: {=INDEX(GMWQ!$A$2:$NF$60,MATCH(1,(GMWQ!$NE$2:$NE$60=C$3)*(GMWQ!$NF$2:$NF$60=C$1),0),$B9-1966)} -> 4839 | D9: {=INDEX(GMWQ!$A$2:$NF$60,MATCH(1,(GMWQ!$NE$2:$NE$60=D$3)*(GMWQ!$NF$2:$NF$60=D$1),0),$B9-1966)} -> 0.001 | E9: {=INDEX(GMWQ!$A$2:$NF$60,MATCH(1,(GMWQ!$NE$2:$NE$60=E$3)*(GMWQ!$NF$2:$NF$60=E$1),0),$B9-1966)} -> 13247 | F9: {=INDEX(GMWQ!$A$2:$NF$60,MATCH(1,(GMWQ!$NE$2:$NE$60=F$3)*(GMWQ!$NF$2:$NF$60=F$1),0),$B9-1966)} -> 3.6 | G9: {=INDEX(GMWQ!$A$2:$NF$60,MATCH(1,(GMWQ!$NE$2:$NE$60=G$3)*(GMWQ!$NF$2:$NF$60=G$1),0),$B9-1966)} -> 0 | H9: {=INDEX(GMWQ!$A$2:$NF$60,MATCH(1,(GMWQ!$NE$2:$NE$60=H$3)*(GMWQ!$NF$2:$NF$60=H$1),0),$B9-1966)} -> 0.001 | I9: {=INDEX(GMWQ!$A$2:$NF$60,MATCH(1,(GMWQ!$NE$2:$NE$60=I$3)*(GMWQ!$NF$2:$NF$60=I$1),0),$B9-1966)} -> 16751.57 | J9: {=INDEX(GMWQ!$A$2:$NF$60,MATCH(1,(GMWQ!$NE$2:$NE$60=J$3)*(GMWQ!$NF$2:$NF$60=J$1),0),$B9-1966)} -> 10 | ... W9: {=INDEX(GMWQ!$A$2:$NF$60,MATCH(1,(GMWQ!$NE$2:$NE$60=W$3)*(GMWQ!$NF$2:$NF$60=W$1),0),$B9-1966)} -> 0.001
B10: =+B9+1 -> 1976 | C10: {=INDEX(GMWQ!$A$2:$NF$60,MATCH(1,(GMWQ!$NE$2:$NE$60=C$3)*(GMWQ!$NF$2:$NF$60=C$1),0),$B10-1966)} -> 4862 | D10: {=INDEX(GMWQ!$A$2:$NF$60,MATCH(1,(GMWQ!$NE$2:$NE$60=D$3)*(GMWQ!$NF$2:$NF$60=D$1),0),$B10-1966)} -> 0.001 | E10: {=INDEX(GMWQ!$A$2:$NF$60,MATCH(1,(GMWQ!$NE$2:$NE$60=E$3)*(GMWQ!$NF$2:$NF$60=E$1),0),$B10-1966)} -> 13917 | F10: {=INDEX(GMWQ!$A$2:$NF$60,MATCH(1,(GMWQ!$NE$2:$NE$60=F$3)*(GMWQ!$NF$2:$NF$60=F$1),0),$B10-1966)} -> 3.4 | G10: {=INDEX(GMWQ!$A$2:$NF$60,MATCH(1,(GMWQ!$NE$2:$NE$60=G$3)*(GMWQ!$NF$2:$NF$60=G$1),0),$B10-1966)} -> 0 | H10: {=INDEX(GMWQ!$A$2:$NF$60,MATCH(1,(GMWQ!$NE$2:$NE$60=H$3)*(GMWQ!$NF$2:$NF$60=H$1),0),$B10-1966)} -> 0.001 | I10: {=INDEX(GMWQ!$A$2:$NF$60,MATCH(1,(GMWQ!$NE$2:$NE$60=I$3)*(GMWQ!$NF$2:$NF$60=I$1),0),$B10-1966)} -> 17259.36 | J10: {=INDEX(GMWQ!$A$2:$NF$60,MATCH(1,(GMWQ!$NE$2:$NE$60=J$3)*(GMWQ!$NF$2:$NF$60=J$1),0),$B10-1966)} -> 11 | ... W10: {=INDEX(GMWQ!$A$2:$NF$60,MATCH(1,(GMWQ!$NE$2:$NE$60=W$3)*(GMWQ!$NF$2:$NF$60=W$1),0),$B10-1966)} -> 0.001
A11: 1974 | B11: =+B10+1 -> 1977 | C11: {=INDEX(GMWQ!$A$2:$NF$60,MATCH(1,(GMWQ!$NE$2:$NE$60=C$3)*(GMWQ!$NF$2:$NF$60=C$1),0),$B11-1966)} -> 4874 | D11: {=INDEX(GMWQ!$A$2:$NF$60,MATCH(1,(GMWQ!$NE$2:$NE$60=D$3)*(GMWQ!$NF$2:$NF$60=D$1),0),$B11-1966)} -> 0.001 | E11: {=INDEX(GMWQ!$A$2:$NF$60,MATCH(1,(GMWQ!$NE$2:$NE$60=E$3)*(GMWQ!$NF$2:$NF$60=E$1),0),$B11-1966)} -> 14267 | F11: {=INDEX(GMWQ!$A$2:$NF$60,MATCH(1,(GMWQ!$NE$2:$NE$60=F$3)*(GMWQ!$NF$2:$NF$60=F$1),0),$B11-1966)} -> 3.6 | G11: {=INDEX(GMWQ!$A$2:$NF$60,MATCH(1,(GMWQ!$NE$2:$NE$60=G$3)*(GMWQ!$NF$2:$NF$60=G$1),0),$B11-1966)} -> 0 | H11: {=INDEX(GMWQ!$A$2:$NF$60,MATCH(1,(GMWQ!$NE$2:$NE$60=H$3)*(GMWQ!$NF$2:$NF$60=H$1),0),$B11-1966)} -> 0.001 | I11: {=INDEX(GMWQ!$A$2:$NF$60,MATCH(1,(GMWQ!$NE$2:$NE$60=I$3)*(GMWQ!$NF$2:$NF$60=I$1),0),$B11-1966)} -> 17697.98 | J11: {=INDEX(GMWQ!$A$2:$NF$60,MATCH(1,(GMWQ!$NE$2:$NE$60=J$3)*(GMWQ!$NF$2:$NF$60=J$1),0),$B11-1966)} -> 11 | ... W11: {=INDEX(GMWQ!$A$2:$NF$60,MATCH(1,(GMWQ!$NE$2:$NE$60=W$3)*(GMWQ!$NF$2:$NF$60=W$1),0),$B11-1966)} -> 0.001
B12: =+B11+1 -> 1978 | C12: {=INDEX(GMWQ!$A$2:$NF$60,MATCH(1,(GMWQ!$NE$2:$NE$60=C$3)*(GMWQ!$NF$2:$NF$60=C$1),0),$B12-1966)} -> 4886 | D12: {=INDEX(GMWQ!$A$2:$NF$60,MATCH(1,(GMWQ!$NE$2:$NE$60=D$3)*(GMWQ!$NF$2:$NF$60=D$1),0),$B12-1966)} -> 0.001 | E12: {=INDEX(GMWQ!$A$2:$NF$60,MATCH(1,(GMWQ!$NE$2:$NE$60=E$3)*(GMWQ!$NF$2:$NF$60=E$1),0),$B12-1966)} -> 14694 | F12: {=INDEX(GMWQ!$A$2:$NF$60,MATCH(1,(GMWQ!$NE$2:$NE$60=F$3)*(GMWQ!$NF$2:$NF$60=F$1),0),$B12-1966)} -> 3.6 | G12: {=INDEX(GMWQ!$A$2:$NF$60,MATCH(1,(GMWQ!$NE$2:$NE$60=G$3)*(GMWQ!$NF$2:$NF$60=G$1),0),$B12-1966)} -> 0 | H12: {=INDEX(GMWQ!$A$2:$NF$60,MATCH(1,(GMWQ!$NE$2:$NE$60=H$3)*(GMWQ!$NF$2:$NF$60=H$1),0),$B12-1966)} -> 0.001 | I12: {=INDEX(GMWQ!$A$2:$NF$60,MATCH(1,(GMWQ!$NE$2:$NE$60=I$3)*(GMWQ!$NF$2:$NF$60=I$1),0),$B12-1966)} -> 18131.15 | J12: {=INDEX(GMWQ!$A$2:$NF$60,MATCH(1,(GMWQ!$NE$2:$NE$60=J$3)*(GMWQ!$NF$2:$NF$60=J$1),0),$B12-1966)} -> 11 | ... W12: {=INDEX(GMWQ!$A$2:$NF$60,MATCH(1,(GMWQ!$NE$2:$NE$60=W$3)*(GMWQ!$NF$2:$NF$60=W$1),0),$B12-1966)} -> 0.001
B13: =+B12+1 -> 1979 | C13: {=INDEX(GMWQ!$A$2:$NF$60,MATCH(1,(GMWQ!$NE$2:$NE$60=C$3)*(GMWQ!$NF$2:$NF$60=C$1),0),$B13-1966)} -> 4898 | D13: {=INDEX(GMWQ!$A$2:$NF$60,MATCH(1,(GMWQ!$NE$2:$NE$60=D$3)*(GMWQ!$NF$2:$NF$60=D$1),0),$B13-1966)} -> 0.001 | E13: {=INDEX(GMWQ!$A$2:$NF$60,MATCH(1,(GMWQ!$NE$2:$NE$60=E$3)*(GMWQ!$NF$2:$NF$60=E$1),0),$B13-1966)} -> 15881 | F13: {=INDEX(GMWQ!$A$2:$NF$60,MATCH(1,(GMWQ!$NE$2:$NE$60=F$3)*(GMWQ!$NF$2:$NF$60=F$1),0),$B13-1966)} -> 3.7 | G13: {=INDEX(GMWQ!$A$2:$NF$60,MATCH(1,(GMWQ!$NE$2:$NE$60=G$3)*(GMWQ!$NF$2:$NF$60=G$1),0),$B13-1966)} -> 0 | H13: {=INDEX(GMWQ!$A$2:$NF$60,MATCH(1,(GMWQ!$NE$2:$NE$60=H$3)*(GMWQ!$NF$2:$NF$60=H$1),0),$B13-1966)} -> 0.001 | I13: {=INDEX(GMWQ!$A$2:$NF$60,MATCH(1,(GMWQ!$NE$2:$NE$60=I$3)*(GMWQ!$NF$2:$NF$60=I$1),0),$B13-1966)} -> 18742.68 | J13: {=INDEX(GMWQ!$A$2:$NF$60,MATCH(1,(GMWQ!$NE$2:$NE$60=J$3)*(GMWQ!$NF$2:$NF$60=J$1),0),$B13-1966)} -> 11 | ... W13: {=INDEX(GMWQ!$A$2:$NF$60,MATCH(1,(GMWQ!$NE$2:$NE$60=W$3)*(GMWQ!$NF$2:$NF$60=W$1),0),$B13-1966)} -> 0.001
B14: =+B13+1 -> 1980 | C14: {=INDEX(GMWQ!$A$2:$NF$60,MATCH(1,(GMWQ!$NE$2:$NE$60=C$3)*(GMWQ!$NF$2:$NF$60=C$1),0),$B14-1966)} -> 4910 | D14: {=INDEX(GMWQ!$A$2:$NF$60,MATCH(1,(GMWQ!$NE$2:$NE$60=D$3)*(GMWQ!$NF$2:$NF$60=D$1),0),$B14-1966)} -> 0.001 | E14: {=INDEX(GMWQ!$A$2:$NF$60,MATCH(1,(GMWQ!$NE$2:$NE$60=E$3)*(GMWQ!$NF$2:$NF$60=E$1),0),$B14-1966)} -> 16728 | F14: {=INDEX(GMWQ!$A$2:$NF$60,MATCH(1,(GMWQ!$NE$2:$NE$60=F$3)*(GMWQ!$NF$2:$NF$60=F$1),0),$B14-1966)} -> 3.7 | G14: {=INDEX(GMWQ!$A$2:$NF$60,MATCH(1,(GMWQ!$NE$2:$NE$60=G$3)*(GMWQ!$NF$2:$NF$60=G$1),0),$B14-1966)} -> 0 | H14: {=INDEX(GMWQ!$A$2:$NF$60,MATCH(1,(GMWQ!$NE$2:$NE$60=H$3)*(GMWQ!$NF$2:$NF$60=H$1),0),$B14-1966)} -> 0.001 | I14: {=INDEX(GMWQ!$A$2:$NF$60,MATCH(1,(GMWQ!$NE$2:$NE$60=I$3)*(GMWQ!$NF$2:$NF$60=I$1),0),$B14-1966)} -> 19459.77 | J14: {=INDEX(GMWQ!$A$2:$NF$60,MATCH(1,(GMWQ!$NE$2:$NE$60=J$3)*(GMWQ!$NF$2:$NF$60=J$1),0),$B14-1966)} -> 11 | ... W14: {=INDEX(GMWQ!$A$2:$NF$60,MATCH(1,(GMWQ!$NE$2:$NE$60=W$3)*(GMWQ!$NF$2:$NF$60=W$1),0),$B14-1966)} -> 0.001
A15: 1975 | B15: =+B14+1 -> 1981 | C15: {=INDEX(GMWQ!$A$2:$NF$60,MATCH(1,(GMWQ!$NE$2:$NE$60=C$3)*(GMWQ!$NF$2:$NF$60=C$1),0),$B15-1966)} -> 4951.5 | D15: {=INDEX(GMWQ!$A$2:$NF$60,MATCH(1,(GMWQ!$NE$2:$NE$60=D$3)*(GMWQ!$NF$2:$NF$60=D$1),0),$B15-1966)} -> 0.001 | E15: {=INDEX(GMWQ!$A$2:$NF$60,MATCH(1,(GMWQ!$NE$2:$NE$60=E$3)*(GMWQ!$NF$2:$NF$60=E$1),0),$B15-1966)} -> 18231 | F15: {=INDEX(GMWQ!$A$2:$NF$60,MATCH(1,(GMWQ!$NE$2:$NE$60=F$3)*(GMWQ!$NF$2:$NF$60=F$1),0),$B15-1966)} -> 4 | G15: {=INDEX(GMWQ!$A$2:$NF$60,MATCH(1,(GMWQ!$NE$2:$NE$60=G$3)*(GMWQ!$NF$2:$NF$60=G$1),0),$B15-1966)} -> 0 | H15: {=INDEX(GMWQ!$A$2:$NF$60,MATCH(1,(GMWQ!$NE$2:$NE$60=H$3)*(GMWQ!$NF$2:$NF$60=H$1),0),$B15-1966)} -> 0.001 | I15: {=INDEX(GMWQ!$A$2:$NF$60,MATCH(1,(GMWQ!$NE$2:$NE$60=I$3)*(GMWQ!$NF$2:$NF$60=I$1),0),$B15-1966)} -> 20188.7 | J15: {=INDEX(GMWQ!$A$2:$NF$60,MATCH(1,(GMWQ!$NE$2:$NE$60=J$3)*(GMWQ!$NF$2:$NF$60=J$1),0),$B15-1966)} -> 11 | ... W15: {=INDEX(GMWQ!$A$2:$NF$60,MATCH(1,(GMWQ!$NE$2:$NE$60=W$3)*(GMWQ!$NF$2:$NF$60=W$1),0),$B15-1966)} -> 0.001
B16: =+B15+1 -> 1982 | C16: {=INDEX(GMWQ!$A$2:$NF$60,MATCH(1,(GMWQ!$NE$2:$NE$60=C$3)*(GMWQ!$NF$2:$NF$60=C$1),0),$B16-1966)} -> 4993 | D16: {=INDEX(GMWQ!$A$2:$NF$60,MATCH(1,(GMWQ!$NE$2:$NE$60=D$3)*(GMWQ!$NF$2:$NF$60=D$1),0),$B16-1966)} -> 0.001 | E16: {=INDEX(GMWQ!$A$2:$NF$60,MATCH(1,(GMWQ!$NE$2:$NE$60=E$3)*(GMWQ!$NF$2:$NF$60=E$1),0),$B16-1966)} -> 18613 | F16: {=INDEX(GMWQ!$A$2:$NF$60,MATCH(1,(GMWQ!$NE$2:$NE$60=F$3)*(GMWQ!$NF$2:$NF$60=F$1),0),$B16-1966)} -> 4.3 | G16: {=INDEX(GMWQ!$A$2:$NF$60,MATCH(1,(GMWQ!$NE$2:$NE$60=G$3)*(GMWQ!$NF$2:$NF$60=G$1),0),$B16-1966)} -> 0 | H16: {=INDEX(GMWQ!$A$2:$NF$60,MATCH(1,(GMWQ!$NE$2:$NE$60=H$3)*(GMWQ!$NF$2:$NF$60=H$1),0),$B16-1966)} -> 0.001 | I16: {=INDEX(GMWQ!$A$2:$NF$60,MATCH(1,(GMWQ!$NE$2:$NE$60=I$3)*(GMWQ!$NF$2:$NF$60=I$1),0),$B16-1966)} -> 20997.7 | J16: {=INDEX(GMWQ!$A$2:$NF$60,MATCH(1,(GMWQ!$NE$2:$NE$60=J$3)*(GMWQ!$NF$2:$NF$60=J$1),0),$B16-1966)} -> 11 | ... W16: {=INDEX(GMWQ!$A$2:$NF$60,MATCH(1,(GMWQ!$NE$2:$NE$60=W$3)*(GMWQ!$NF$2:$NF$60=W$1),0),$B16-1966)} -> 0.001
B17: =+B16+1 -> 1983 | C17: {=INDEX(GMWQ!$A$2:$NF$60,MATCH(1,(GMWQ!$NE$2:$NE$60=C$3)*(GMWQ!$NF$2:$NF$60=C$1),0),$B17-1966)} -> 5034.5 | D17: {=INDEX(GMWQ!$A$2:$NF$60,MATCH(1,(GMWQ!$NE$2:$NE$60=D$3)*(GMWQ!$NF$2:$NF$60=D$1),0),$B17-1966)} -> 0.001 | E17: {=INDEX(GMWQ!$A$2:$NF$60,MATCH(1,(GMWQ!$NE$2:$NE$60=E$3)*(GMWQ!$NF$2:$NF$60=E$1),0),$B17-1966)} -> 19564 | F17: {=INDEX(GMWQ!$A$2:$NF$60,MATCH(1,(GMWQ!$NE$2:$NE$60=F$3)*(GMWQ!$NF$2:$NF$60=F$1),0),$B17-1966)} -> 4.7 | G17: {=INDEX(GMWQ!$A$2:$NF$60,MATCH(1,(GMWQ!$NE$2:$NE$60=G$3)*(GMWQ!$NF$2:$NF$60=G$1),0),$B17-1966)} -> 0 | H17: {=INDEX(GMWQ!$A$2:$NF$60,MATCH(1,(GMWQ!$NE$2:$NE$60=H$3)*(GMWQ!$NF$2:$NF$60=H$1),0),$B17-1966)} -> 0.001 | I17: {=INDEX(GMWQ!$A$2:$NF$60,MATCH(1,(GMWQ!$NE$2:$NE$60=I$3)*(GMWQ!$NF$2:$NF$60=I$1),0),$B17-1966)} -> 21876.78 | J17: {=INDEX(GMWQ!$A$2:$NF$60,MATCH(1,(GMWQ!$NE$2:$NE$60=J$3)*(GMWQ!$NF$2:$NF$60=J$1),0),$B17-1966)} -> 11 | ... W17: {=INDEX(GMWQ!$A$2:$NF$60,MATCH(1,(GMWQ!$NE$2:$NE$60=W$3)*(GMWQ!$NF$2:$NF$60=W$1),0),$B17-1966)} -> 0.001
B18: =+B17+1 -> 1984 | C18: {=INDEX(GMWQ!$A$2:$NF$60,MATCH(1,(GMWQ!$NE$2:$NE$60=C$3)*(GMWQ!$NF$2:$NF$60=C$1),0),$B18-1966)} -> 5076 | D18: {=INDEX(GMWQ!$A$2:$NF$60,MATCH(1,(GMWQ!$NE$2:$NE$60=D$3)*(GMWQ!$NF$2:$NF$60=D$1),0),$B18-1966)} -> 0.001 | E18: {=INDEX(GMWQ!$A$2:$NF$60,MATCH(1,(GMWQ!$NE$2:$NE$60=E$3)*(GMWQ!$NF$2:$NF$60=E$1),0),$B18-1966)} -> 20194 | F18: {=INDEX(GMWQ!$A$2:$NF$60,MATCH(1,(GMWQ!$NE$2:$NE$60=F$3)*(GMWQ!$NF$2:$NF$60=F$1),0),$B18-1966)} -> 5 | G18: {=INDEX(GMWQ!$A$2:$NF$60,MATCH(1,(GMWQ!$NE$2:$NE$60=G$3)*(GMWQ!$NF$2:$NF$60=G$1),0),$B18-1966)} -> 0 | H18: {=INDEX(GMWQ!$A$2:$NF$60,MATCH(1,(GMWQ!$NE$2:$NE$60=H$3)*(GMWQ!$NF$2:$NF$60=H$1),0),$B18-1966)} -> 0.001 | I18: {=INDEX(GMWQ!$A$2:$NF$60,MATCH(1,(GMWQ!$NE$2:$NE$60=I$3)*(GMWQ!$NF$2:$NF$60=I$1),0),$B18-1966)} -> 22896.9 | J18: {=INDEX(GMWQ!$A$2:$NF$60,MATCH(1,(GMWQ!$NE$2:$NE$60=J$3)*(GMWQ!$NF$2:$NF$60=J$1),0),$B18-1966)} -> 11 | ... W18: {=INDEX(GMWQ!$A$2:$NF$60,MATCH(1,(GMWQ!$NE$2:$NE$60=W$3)*(GMWQ!$NF$2:$NF$60=W$1),0),$B18-1966)} -> 0.001
A19: 1976 | B19: =+B18+1 -> 1985 | C19: {=INDEX(GMWQ!$A$2:$NF$60,MATCH(1,(GMWQ!$NE$2:$NE$60=C$3)*(GMWQ!$NF$2:$NF$60=C$1),0),$B19-1966)} -> 5137.5 | D19: {=INDEX(GMWQ!$A$2:$NF$60,MATCH(1,(GMWQ!$NE$2:$NE$60=D$3)*(GMWQ!$NF$2:$NF$60=D$1),0),$B19-1966)} -> 0.001 | E19: {=INDEX(GMWQ!$A$2:$NF$60,MATCH(1,(GMWQ!$NE$2:$NE$60=E$3)*(GMWQ!$NF$2:$NF$60=E$1),0),$B19-1966)} -> 21295 | F19: {=INDEX(GMWQ!$A$2:$NF$60,MATCH(1,(GMWQ!$NE$2:$NE$60=F$3)*(GMWQ!$NF$2:$NF$60=F$1),0),$B19-1966)} -> 5.3 | G19: {=INDEX(GMWQ!$A$2:$NF$60,MATCH(1,(GMWQ!$NE$2:$NE$60=G$3)*(GMWQ!$NF$2:$NF$60=G$1),0),$B19-1966)} -> 0 | H19: {=INDEX(GMWQ!$A$2:$NF$60,MATCH(1,(GMWQ!$NE$2:$NE$60=H$3)*(GMWQ!$NF$2:$NF$60=H$1),0),$B19-1966)} -> 0.001 | I19: {=INDEX(GMWQ!$A$2:$NF$60,MATCH(1,(GMWQ!$NE$2:$NE$60=I$3)*(GMWQ!$NF$2:$NF$60=I$1),0),$B19-1966)} -> 23636.74 | J19: {=INDEX(GMWQ!$A$2:$NF$60,MATCH(1,(GMWQ!$NE$2:$NE$60=J$3)*(GMWQ!$NF$2:$NF$60=J$1),0),$B19-1966)} -> 11 | ... W19: {=INDEX(GMWQ!$A$2:$NF$60,MATCH(1,(GMWQ!$NE$2:$NE$60=W$3)*(GMWQ!$NF$2:$NF$60=W$1),0),$B19-1966)} -> 0.001
B20: =+B19+1 -> 1986 | C20: {=INDEX(GMWQ!$A$2:$NF$60,MATCH(1,(GMWQ!$NE$2:$NE$60=C$3)*(GMWQ!$NF$2:$NF$60=C$1),0),$B20-1966)} -> 5199 | D20: {=INDEX(GMWQ!$A$2:$NF$60,MATCH(1,(GMWQ!$NE$2:$NE$60=D$3)*(GMWQ!$NF$2:$NF$60=D$1),0),$B20-1966)} -> 0.001 | E20: {=INDEX(GMWQ!$A$2:$NF$60,MATCH(1,(GMWQ!$NE$2:$NE$60=E$3)*(GMWQ!$NF$2:$NF$60=E$1),0),$B20-1966)} -> 21568 | F20: {=INDEX(GMWQ!$A$2:$NF$60,MATCH(1,(GMWQ!$NE$2:$NE$60=F$3)*(GMWQ!$NF$2:$NF$60=F$1),0),$B20-1966)} -> 5.4 | G20: {=INDEX(GMWQ!$A$2:$NF$60,MATCH(1,(GMWQ!$NE$2:$NE$60=G$3)*(GMWQ!$NF$2:$NF$60=G$1),0),$B20-1966)} -> 0 | H20: {=INDEX(GMWQ!$A$2:$NF$60,MATCH(1,(GMWQ!$NE$2:$NE$60=H$3)*(GMWQ!$NF$2:$NF$60=H$1),0),$B20-1966)} -> 0.001 | I20: {=INDEX(GMWQ!$A$2:$NF$60,MATCH(1,(GMWQ!$NE$2:$NE$60=I$3)*(GMWQ!$NF$2:$NF$60=I$1),0),$B20-1966)} -> 24579.52 | J20: {=INDEX(GMWQ!$A$2:$NF$60,MATCH(1,(GMWQ!$NE$2:$NE$60=J$3)*(GMWQ!$NF$2:$NF$60=J$1),0),$B20-1966)} -> 10.5 | ... W20: {=INDEX(GMWQ!$A$2:$NF$60,MATCH(1,(GMWQ!$NE$2:$NE$60=W$3)*(GMWQ!$NF$2:$NF$60=W$1),0),$B20-1966)} -> 0.001
B21: =+B20+1 -> 1987 | C21: {=INDEX(GMWQ!$A$2:$NF$60,MATCH(1,(GMWQ!$NE$2:$NE$60=C$3)*(GMWQ!$NF$2:$NF$60=C$1),0),$B21-1966)} -> 5260.5 | D21: {=INDEX(GMWQ!$A$2:$NF$60,MATCH(1,(GMWQ!$NE$2:$NE$60=D$3)*(GMWQ!$NF$2:$NF$60=D$1),0),$B21-1966)} -> 0.001 | E21: {=INDEX(GMWQ!$A$2:$NF$60,MATCH(1,(GMWQ!$NE$2:$NE$60=E$3)*(GMWQ!$NF$2:$NF$60=E$1),0),$B21-1966)} -> 22876 | F21: {=INDEX(GMWQ!$A$2:$NF$60,MATCH(1,(GMWQ!$NE$2:$NE$60=F$3)*(GMWQ!$NF$2:$NF$60=F$1),0),$B21-1966)} -> 5.5 | G21: {=INDEX(GMWQ!$A$2:$NF$60,MATCH(1,(GMWQ!$NE$2:$NE$60=G$3)*(GMWQ!$NF$2:$NF$60=G$1),0),$B21-1966)} -> 0 | H21: {=INDEX(GMWQ!$A$2:$NF$60,MATCH(1,(GMWQ!$NE$2:$NE$60=H$3)*(GMWQ!$NF$2:$NF$60=H$1),0),$B21-1966)} -> 0.001 | I21: {=INDEX(GMWQ!$A$2:$NF$60,MATCH(1,(GMWQ!$NE$2:$NE$60=I$3)*(GMWQ!$NF$2:$NF$60=I$1),0),$B21-1966)} -> 25544.14 | J21: {=INDEX(GMWQ!$A$2:$NF$60,MATCH(1,(GMWQ!$NE$2:$NE$60=J$3)*(GMWQ!$NF$2:$NF$60=J$1),0),$B21-1966)} -> 10.5 | ... W21: {=INDEX(GMWQ!$A$2:$NF$60,MATCH(1,(GMWQ!$NE$2:$NE$60=W$3)*(GMWQ!$NF$2:$NF$60=W$1),0),$B21-1966)} -> 0.001
B22: =+B21+1 -> 1988 | C22: {=INDEX(GMWQ!$A$2:$NF$60,MATCH(1,(GMWQ!$NE$2:$NE$60=C$3)*(GMWQ!$NF$2:$NF$60=C$1),0),$B22-1966)} -> 5322 | D22: {=INDEX(GMWQ!$A$2:$NF$60,MATCH(1,(GMWQ!$NE$2:$NE$60=D$3)*(GMWQ!$NF$2:$NF$60=D$1),0),$B22-1966)} -> 0.001 | E22: {=INDEX(GMWQ!$A$2:$NF$60,MATCH(1,(GMWQ!$NE$2:$NE$60=E$3)*(GMWQ!$NF$2:$NF$60=E$1),0),$B22-1966)} -> 23450 | F22: {=INDEX(GMWQ!$A$2:$NF$60,MATCH(1,(GMWQ!$NE$2:$NE$60=F$3)*(GMWQ!$NF$2:$NF$60=F$1),0),$B22-1966)} -> 5.5 | G22: {=INDEX(GMWQ!$A$2:$NF$60,MATCH(1,(GMWQ!$NE$2:$NE$60=G$3)*(GMWQ!$NF$2:$NF$60=G$1),0),$B22-1966)} -> 0 | H22: {=INDEX(GMWQ!$A$2:$NF$60,MATCH(1,(GMWQ!$NE$2:$NE$60=H$3)*(GMWQ!$NF$2:$NF$60=H$1),0),$B22-1966)} -> 0.001 | I22: {=INDEX(GMWQ!$A$2:$NF$60,MATCH(1,(GMWQ!$NE$2:$NE$60=I$3)*(GMWQ!$NF$2:$NF$60=I$1),0),$B22-1966)} -> 26363.15 | J22: {=INDEX(GMWQ!$A$2:$NF$60,MATCH(1,(GMWQ!$NE$2:$NE$60=J$3)*(GMWQ!$NF$2:$NF$60=J$1),0),$B22-1966)} -> 12.25 | ... W22: {=INDEX(GMWQ!$A$2:$NF$60,MATCH(1,(GMWQ!$NE$2:$NE$60=W$3)*(GMWQ!$NF$2:$NF$60=W$1),0),$B22-1966)} -> 0.001
A23: 1977 | B23: =+B22+1 -> 1989 | C23: {=INDEX(GMWQ!$A$2:$NF$60,MATCH(1,(GMWQ!$NE$2:$NE$60=C$3)*(GMWQ!$NF$2:$NF$60=C$1),0),$B23-1966)} -> 5387 | D23: {=INDEX(GMWQ!$A$2:$NF$60,MATCH(1,(GMWQ!$NE$2:$NE$60=D$3)*(GMWQ!$NF$2:$NF$60=D$1),0),$B23-1966)} -> 0.001 | E23: {=INDEX(GMWQ!$A$2:$NF$60,MATCH(1,(GMWQ!$NE$2:$NE$60=E$3)*(GMWQ!$NF$2:$NF$60=E$1),0),$B23-1966)} -> 23884 | F23: {=INDEX(GMWQ!$A$2:$NF$60,MATCH(1,(GMWQ!$NE$2:$NE$60=F$3)*(GMWQ!$NF$2:$NF$60=F$1),0),$B23-1966)} -> 5.5 | G23: {=INDEX(GMWQ!$A$2:$NF$60,MATCH(1,(GMWQ!$NE$2:$NE$60=G$3)*(GMWQ!$NF$2:$NF$60=G$1),0),$B23-1966)} -> 0 | H23: {=INDEX(GMWQ!$A$2:$NF$60,MATCH(1,(GMWQ!$NE$2:$NE$60=H$3)*(GMWQ!$NF$2:$NF$60=H$1),0),$B23-1966)} -> 0.001 | I23: {=INDEX(GMWQ!$A$2:$NF$60,MATCH(1,(GMWQ!$NE$2:$NE$60=I$3)*(GMWQ!$NF$2:$NF$60=I$1),0),$B23-1966)} -> 27088.43 | J23: {=INDEX(GMWQ!$A$2:$NF$60,MATCH(1,(GMWQ!$NE$2:$NE$60=J$3)*(GMWQ!$NF$2:$NF$60=J$1),0),$B23-1966)} -> 12.25 | ... W23: {=INDEX(GMWQ!$A$2:$NF$60,MATCH(1,(GMWQ!$NE$2:$NE$60=W$3)*(GMWQ!$NF$2:$NF$60=W$1),0),$B23-1966)} -> 0.001
B24: =+B23+1 -> 1990 | C24: {=INDEX(GMWQ!$A$2:$NF$60,MATCH(1,(GMWQ!$NE$2:$NE$60=C$3)*(GMWQ!$NF$2:$NF$60=C$1),0),$B24-1966)} -> 5452 | D24: {=INDEX(GMWQ!$A$2:$NF$60,MATCH(1,(GMWQ!$NE$2:$NE$60=D$3)*(GMWQ!$NF$2:$NF$60=D$1),0),$B24-1966)} -> 0.001 | E24: {=INDEX(GMWQ!$A$2:$NF$60,MATCH(1,(GMWQ!$NE$2:$NE$60=E$3)*(GMWQ!$NF$2:$NF$60=E$1),0),$B24-1966)} -> 24509 | F24: {=INDEX(GMWQ!$A$2:$NF$60,MATCH(1,(GMWQ!$NE$2:$NE$60=F$3)*(GMWQ!$NF$2:$NF$60=F$1),0),$B24-1966)} -> 5.5 | G24: {=INDEX(GMWQ!$A$2:$NF$60,MATCH(1,(GMWQ!$NE$2:$NE$60=G$3)*(GMWQ!$NF$2:$NF$60=G$1),0),$B24-1966)} -> 0 | H24: {=INDEX(GMWQ!$A$2:$NF$60,MATCH(1,(GMWQ!$NE$2:$NE$60=H$3)*(GMWQ!$NF$2:$NF$60=H$1),0),$B24-1966)} -> 0.001 | I24: {=INDEX(GMWQ!$A$2:$NF$60,MATCH(1,(GMWQ!$NE$2:$NE$60=I$3)*(GMWQ!$NF$2:$NF$60=I$1),0),$B24-1966)} -> 27957.5 | J24: {=INDEX(GMWQ!$A$2:$NF$60,MATCH(1,(GMWQ!$NE$2:$NE$60=J$3)*(GMWQ!$NF$2:$NF$60=J$1),0),$B24-1966)} -> 11.25 | ... W24: {=INDEX(GMWQ!$A$2:$NF$60,MATCH(1,(GMWQ!$NE$2:$NE$60=W$3)*(GMWQ!$NF$2:$NF$60=W$1),0),$B24-1966)} -> 0.001
B25: =+B24+1 -> 1991 | C25: {=INDEX(GMWQ!$A$2:$NF$60,MATCH(1,(GMWQ!$NE$2:$NE$60=C$3)*(GMWQ!$NF$2:$NF$60=C$1),0),$B25-1966)} -> 5517 | D25: {=INDEX(GMWQ!$A$2:$NF$60,MATCH(1,(GMWQ!$NE$2:$NE$60=D$3)*(GMWQ!$NF$2:$NF$60=D$1),0),$B25-1966)} -> 0.001 | E25: {=INDEX(GMWQ!$A$2:$NF$60,MATCH(1,(GMWQ!$NE$2:$NE$60=E$3)*(GMWQ!$NF$2:$NF$60=E$1),0),$B25-1966)} -> 25439 | F25: {=INDEX(GMWQ!$A$2:$NF$60,MATCH(1,(GMWQ!$NE$2:$NE$60=F$3)*(GMWQ!$NF$2:$NF$60=F$1),0),$B25-1966)} -> 5.7 | G25: {=INDEX(GMWQ!$A$2:$NF$60,MATCH(1,(GMWQ!$NE$2:$NE$60=G$3)*(GMWQ!$NF$2:$NF$60=G$1),0),$B25-1966)} -> 0 | H25: {=INDEX(GMWQ!$A$2:$NF$60,MATCH(1,(GMWQ!$NE$2:$NE$60=H$3)*(GMWQ!$NF$2:$NF$60=H$1),0),$B25-1966)} -> 0.001 | I25: {=INDEX(GMWQ!$A$2:$NF$60,MATCH(1,(GMWQ!$NE$2:$NE$60=I$3)*(GMWQ!$NF$2:$NF$60=I$1),0),$B25-1966)} -> 29076.82 | J25: {=INDEX(GMWQ!$A$2:$NF$60,MATCH(1,(GMWQ!$NE$2:$NE$60=J$3)*(GMWQ!$NF$2:$NF$60=J$1),0),$B25-1966)} -> 10.5 | ... W25: {=INDEX(GMWQ!$A$2:$NF$60,MATCH(1,(GMWQ!$NE$2:$NE$60=W$3)*(GMWQ!$NF$2:$NF$60=W$1),0),$B25-1966)} -> 0.001
B26: =+B25+1 -> 1992 | C26: {=INDEX(GMWQ!$A$2:$NF$60,MATCH(1,(GMWQ!$NE$2:$NE$60=C$3)*(GMWQ!$NF$2:$NF$60=C$1),0),$B26-1966)} -> 5582 | D26: {=INDEX(GMWQ!$A$2:$NF$60,MATCH(1,(GMWQ!$NE$2:$NE$60=D$3)*(GMWQ!$NF$2:$NF$60=D$1),0),$B26-1966)} -> 0.001 | E26: {=INDEX(GMWQ!$A$2:$NF$60,MATCH(1,(GMWQ!$NE$2:$NE$60=E$3)*(GMWQ!$NF$2:$NF$60=E$1),0),$B26-1966)} -> 26940 | F26: {=INDEX(GMWQ!$A$2:$NF$60,MATCH(1,(GMWQ!$NE$2:$NE$60=F$3)*(GMWQ!$NF$2:$NF$60=F$1),0),$B26-1966)} -> 5.7 | G26: {=INDEX(GMWQ!$A$2:$NF$60,MATCH(1,(GMWQ!$NE$2:$NE$60=G$3)*(GMWQ!$NF$2:$NF$60=G$1),0),$B26-1966)} -> 0 | H26: {=INDEX(GMWQ!$A$2:$NF$60,MATCH(1,(GMWQ!$NE$2:$NE$60=H$3)*(GMWQ!$NF$2:$NF$60=H$1),0),$B26-1966)} -> 0.001 | I26: {=INDEX(GMWQ!$A$2:$NF$60,MATCH(1,(GMWQ!$NE$2:$NE$60=I$3)*(GMWQ!$NF$2:$NF$60=I$1),0),$B26-1966)} -> 30241.64 | J26: {=INDEX(GMWQ!$A$2:$NF$60,MATCH(1,(GMWQ!$NE$2:$NE$60=J$3)*(GMWQ!$NF$2:$NF$60=J$1),0),$B26-1966)} -> 9.5 | ... W26: {=INDEX(GMWQ!$A$2:$NF$60,MATCH(1,(GMWQ!$NE$2:$NE$60=W$3)*(GMWQ!$NF$2:$NF$60=W$1),0),$B26-1966)} -> 0.001
A27: 1978 | B27: =+B26+1 -> 1993 | C27: {=INDEX(GMWQ!$A$2:$NF$60,MATCH(1,(GMWQ!$NE$2:$NE$60=C$3)*(GMWQ!$NF$2:$NF$60=C$1),0),$B27-1966)} -> 5660.5 | D27: {=INDEX(GMWQ!$A$2:$NF$60,MATCH(1,(GMWQ!$NE$2:$NE$60=D$3)*(GMWQ!$NF$2:$NF$60=D$1),0),$B27-1966)} -> 0.001 | E27: {=INDEX(GMWQ!$A$2:$NF$60,MATCH(1,(GMWQ!$NE$2:$NE$60=E$3)*(GMWQ!$NF$2:$NF$60=E$1),0),$B27-1966)} -> 27797 | F27: {=INDEX(GMWQ!$A$2:$NF$60,MATCH(1,(GMWQ!$NE$2:$NE$60=F$3)*(GMWQ!$NF$2:$NF$60=F$1),0),$B27-1966)} -> 5.6 | G27: {=INDEX(GMWQ!$A$2:$NF$60,MATCH(1,(GMWQ!$NE$2:$NE$60=G$3)*(GMWQ!$NF$2:$NF$60=G$1),0),$B27-1966)} -> 0 | H27: {=INDEX(GMWQ!$A$2:$NF$60,MATCH(1,(GMWQ!$NE$2:$NE$60=H$3)*(GMWQ!$NF$2:$NF$60=H$1),0),$B27-1966)} -> 0.001 | I27: {=INDEX(GMWQ!$A$2:$NF$60,MATCH(1,(GMWQ!$NE$2:$NE$60=I$3)*(GMWQ!$NF$2:$NF$60=I$1),0),$B27-1966)} -> 31384.62 | J27: {=INDEX(GMWQ!$A$2:$NF$60,MATCH(1,(GMWQ!$NE$2:$NE$60=J$3)*(GMWQ!$NF$2:$NF$60=J$1),0),$B27-1966)} -> 8.5 | ... W27: {=INDEX(GMWQ!$A$2:$NF$60,MATCH(1,(GMWQ!$NE$2:$NE$60=W$3)*(GMWQ!$NF$2:$NF$60=W$1),0),$B27-1966)} -> 0.001
B28: =+B27+1 -> 1994 | C28: {=INDEX(GMWQ!$A$2:$NF$60,MATCH(1,(GMWQ!$NE$2:$NE$60=C$3)*(GMWQ!$NF$2:$NF$60=C$1),0),$B28-1966)} -> 5739 | D28: {=INDEX(GMWQ!$A$2:$NF$60,MATCH(1,(GMWQ!$NE$2:$NE$60=D$3)*(GMWQ!$NF$2:$NF$60=D$1),0),$B28-1966)} -> 0.001 | E28: {=INDEX(GMWQ!$A$2:$NF$60,MATCH(1,(GMWQ!$NE$2:$NE$60=E$3)*(GMWQ!$NF$2:$NF$60=E$1),0),$B28-1966)} -> 29144 | F28: {=INDEX(GMWQ!$A$2:$NF$60,MATCH(1,(GMWQ!$NE$2:$NE$60=F$3)*(GMWQ!$NF$2:$NF$60=F$1),0),$B28-1966)} -> 5.6 | G28: {=INDEX(GMWQ!$A$2:$NF$60,MATCH(1,(GMWQ!$NE$2:$NE$60=G$3)*(GMWQ!$NF$2:$NF$60=G$1),0),$B28-1966)} -> 0 | H28: {=INDEX(GMWQ!$A$2:$NF$60,MATCH(1,(GMWQ!$NE$2:$NE$60=H$3)*(GMWQ!$NF$2:$NF$60=H$1),0),$B28-1966)} -> 0.001 | I28: {=INDEX(GMWQ!$A$2:$NF$60,MATCH(1,(GMWQ!$NE$2:$NE$60=I$3)*(GMWQ!$NF$2:$NF$60=I$1),0),$B28-1966)} -> 32667.74 | J28: {=INDEX(GMWQ!$A$2:$NF$60,MATCH(1,(GMWQ!$NE$2:$NE$60=J$3)*(GMWQ!$NF$2:$NF$60=J$1),0),$B28-1966)} -> 8.5 | ... W28: {=INDEX(GMWQ!$A$2:$NF$60,MATCH(1,(GMWQ!$NE$2:$NE$60=W$3)*(GMWQ!$NF$2:$NF$60=W$1),0),$B28-1966)} -> 0.001
B29: =+B28+1 -> 1995 | C29: {=INDEX(GMWQ!$A$2:$NF$60,MATCH(1,(GMWQ!$NE$2:$NE$60=C$3)*(GMWQ!$NF$2:$NF$60=C$1),0),$B29-1966)} -> 5817.5 | D29: {=INDEX(GMWQ!$A$2:$NF$60,MATCH(1,(GMWQ!$NE$2:$NE$60=D$3)*(GMWQ!$NF$2:$NF$60=D$1),0),$B29-1966)} -> 0.001 | E29: {=INDEX(GMWQ!$A$2:$NF$60,MATCH(1,(GMWQ!$NE$2:$NE$60=E$3)*(GMWQ!$NF$2:$NF$60=E$1),0),$B29-1966)} -> 30465 | F29: {=INDEX(GMWQ!$A$2:$NF$60,MATCH(1,(GMWQ!$NE$2:$NE$60=F$3)*(GMWQ!$NF$2:$NF$60=F$1),0),$B29-1966)} -> 5.5 | G29: {=INDEX(GMWQ!$A$2:$NF$60,MATCH(1,(GMWQ!$NE$2:$NE$60=G$3)*(GMWQ!$NF$2:$NF$60=G$1),0),$B29-1966)} -> 0 | H29: {=INDEX(GMWQ!$A$2:$NF$60,MATCH(1,(GMWQ!$NE$2:$NE$60=H$3)*(GMWQ!$NF$2:$NF$60=H$1),0),$B29-1966)} -> 0.001 | I29: {=INDEX(GMWQ!$A$2:$NF$60,MATCH(1,(GMWQ!$NE$2:$NE$60=I$3)*(GMWQ!$NF$2:$NF$60=I$1),0),$B29-1966)} -> 33930.84 | J29: {=INDEX(GMWQ!$A$2:$NF$60,MATCH(1,(GMWQ!$NE$2:$NE$60=J$3)*(GMWQ!$NF$2:$NF$60=J$1),0),$B29-1966)} -> 9.75 | ... W29: {=INDEX(GMWQ!$A$2:$NF$60,MATCH(1,(GMWQ!$NE$2:$NE$60=W$3)*(GMWQ!$NF$2:$NF$60=W$1),0),$B29-1966)} -> 0.001
B30: =+B29+1 -> 1996 | C30: {=INDEX(GMWQ!$A$2:$NF$60,MATCH(1,(GMWQ!$NE$2:$NE$60=C$3)*(GMWQ!$NF$2:$NF$60=C$1),0),$B30-1966)} -> 5896 | D30: {=INDEX(GMWQ!$A$2:$NF$60,MATCH(1,(GMWQ!$NE$2:$NE$60=D$3)*(GMWQ!$NF$2:$NF$60=D$1),0),$B30-1966)} -> 0.001 | E30: {=INDEX(GMWQ!$A$2:$NF$60,MATCH(1,(GMWQ!$NE$2:$NE$60=E$3)*(GMWQ!$NF$2:$NF$60=E$1),0),$B30-1966)} -> 31463 | F30: {=INDEX(GMWQ!$A$2:$NF$60,MATCH(1,(GMWQ!$NE$2:$NE$60=F$3)*(GMWQ!$NF$2:$NF$60=F$1),0),$B30-1966)} -> 5.4 | G30: {=INDEX(GMWQ!$A$2:$NF$60,MATCH(1,(GMWQ!$NE$2:$NE$60=G$3)*(GMWQ!$NF$2:$NF$60=G$1),0),$B30-1966)} -> 0 | H30: {=INDEX(GMWQ!$A$2:$NF$60,MATCH(1,(GMWQ!$NE$2:$NE$60=H$3)*(GMWQ!$NF$2:$NF$60=H$1),0),$B30-1966)} -> 0.001 | I30: {=INDEX(GMWQ!$A$2:$NF$60,MATCH(1,(GMWQ!$NE$2:$NE$60=I$3)*(GMWQ!$NF$2:$NF$60=I$1),0),$B30-1966)} -> 35192.12 | J30: {=INDEX(GMWQ!$A$2:$NF$60,MATCH(1,(GMWQ!$NE$2:$NE$60=J$3)*(GMWQ!$NF$2:$NF$60=J$1),0),$B30-1966)} -> 10.42 | ... W30: {=INDEX(GMWQ!$A$2:$NF$60,MATCH(1,(GMWQ!$NE$2:$NE$60=W$3)*(GMWQ!$NF$2:$NF$60=W$1),0),$B30-1966)} -> 0.001
A31: 1979 | B31: =+B30+1 -> 1997 | C31: {=INDEX(GMWQ!$A$2:$NF$60,MATCH(1,(GMWQ!$NE$2:$NE$60=C$3)*(GMWQ!$NF$2:$NF$60=C$1),0),$B31-1966)} -> 5936.5 | D31: {=INDEX(GMWQ!$A$2:$NF$60,MATCH(1,(GMWQ!$NE$2:$NE$60=D$3)*(GMWQ!$NF$2:$NF$60=D$1),0),$B31-1966)} -> 0.001 | E31: {=INDEX(GMWQ!$A$2:$NF$60,MATCH(1,(GMWQ!$NE$2:$NE$60=E$3)*(GMWQ!$NF$2:$NF$60=E$1),0),$B31-1966)} -> 32879 | F31: {=INDEX(GMWQ!$A$2:$NF$60,MATCH(1,(GMWQ!$NE$2:$NE$60=F$3)*(GMWQ!$NF$2:$NF$60=F$1),0),$B31-1966)} -> 5.4 | G31: {=INDEX(GMWQ!$A$2:$NF$60,MATCH(1,(GMWQ!$NE$2:$NE$60=G$3)*(GMWQ!$NF$2:$NF$60=G$1),0),$B31-1966)} -> 0 | H31: {=INDEX(GMWQ!$A$2:$NF$60,MATCH(1,(GMWQ!$NE$2:$NE$60=H$3)*(GMWQ!$NF$2:$NF$60=H$1),0),$B31-1966)} -> 0.001 | I31: {=INDEX(GMWQ!$A$2:$NF$60,MATCH(1,(GMWQ!$NE$2:$NE$60=I$3)*(GMWQ!$NF$2:$NF$60=I$1),0),$B31-1966)} -> 36493.45 | J31: {=INDEX(GMWQ!$A$2:$NF$60,MATCH(1,(GMWQ!$NE$2:$NE$60=J$3)*(GMWQ!$NF$2:$NF$60=J$1),0),$B31-1966)} -> 11.75 | ... W31: {=INDEX(GMWQ!$A$2:$NF$60,MATCH(1,(GMWQ!$NE$2:$NE$60=W$3)*(GMWQ!$NF$2:$NF$60=W$1),0),$B31-1966)} -> 0.001
B32: =+B31+1 -> 1998 | C32: {=INDEX(GMWQ!$A$2:$NF$60,MATCH(1,(GMWQ!$NE$2:$NE$60=C$3)*(GMWQ!$NF$2:$NF$60=C$1),0),$B32-1966)} -> 5977 | D32: {=INDEX(GMWQ!$A$2:$NF$60,MATCH(1,(GMWQ!$NE$2:$NE$60=D$3)*(GMWQ!$NF$2:$NF$60=D$1),0),$B32-1966)} -> 0.001 | E32: {=INDEX(GMWQ!$A$2:$NF$60,MATCH(1,(GMWQ!$NE$2:$NE$60=E$3)*(GMWQ!$NF$2:$NF$60=E$1),0),$B32-1966)} -> 34157 | F32: {=INDEX(GMWQ!$A$2:$NF$60,MATCH(1,(GMWQ!$NE$2:$NE$60=F$3)*(GMWQ!$NF$2:$NF$60=F$1),0),$B32-1966)} -> 5.3 | G32: {=INDEX(GMWQ!$A$2:$NF$60,MATCH(1,(GMWQ!$NE$2:$NE$60=G$3)*(GMWQ!$NF$2:$NF$60=G$1),0),$B32-1966)} -> 0 | H32: {=INDEX(GMWQ!$A$2:$NF$60,MATCH(1,(GMWQ!$NE$2:$NE$60=H$3)*(GMWQ!$NF$2:$NF$60=H$1),0),$B32-1966)} -> 0.001 | I32: {=INDEX(GMWQ!$A$2:$NF$60,MATCH(1,(GMWQ!$NE$2:$NE$60=I$3)*(GMWQ!$NF$2:$NF$60=I$1),0),$B32-1966)} -> 37975.86 | J32: {=INDEX(GMWQ!$A$2:$NF$60,MATCH(1,(GMWQ!$NE$2:$NE$60=J$3)*(GMWQ!$NF$2:$NF$60=J$1),0),$B32-1966)} -> 11.246 | ... W32: {=INDEX(GMWQ!$A$2:$NF$60,MATCH(1,(GMWQ!$NE$2:$NE$60=W$3)*(GMWQ!$NF$2:$NF$60=W$1),0),$B32-1966)} -> 0.001
B33: =+B32+1 -> 1999 | C33: {=INDEX(GMWQ!$A$2:$NF$60,MATCH(1,(GMWQ!$NE$2:$NE$60=C$3)*(GMWQ!$NF$2:$NF$60=C$1),0),$B33-1966)} -> 6017.5 | D33: {=INDEX(GMWQ!$A$2:$NF$60,MATCH(1,(GMWQ!$NE$2:$NE$60=D$3)*(GMWQ!$NF$2:$NF$60=D$1),0),$B33-1966)} -> 0.001 | E33: {=INDEX(GMWQ!$A$2:$NF$60,MATCH(1,(GMWQ!$NE$2:$NE$60=E$3)*(GMWQ!$NF$2:$NF$60=E$1),0),$B33-1966)} -> 36483 | F33: {=INDEX(GMWQ!$A$2:$NF$60,MATCH(1,(GMWQ!$NE$2:$NE$60=F$3)*(GMWQ!$NF$2:$NF$60=F$1),0),$B33-1966)} -> 5.4 | G33: {=INDEX(GMWQ!$A$2:$NF$60,MATCH(1,(GMWQ!$NE$2:$NE$60=G$3)*(GMWQ!$NF$2:$NF$60=G$1),0),$B33-1966)} -> 0 | H33: {=INDEX(GMWQ!$A$2:$NF$60,MATCH(1,(GMWQ!$NE$2:$NE$60=H$3)*(GMWQ!$NF$2:$NF$60=H$1),0),$B33-1966)} -> 0.001 | I33: {=INDEX(GMWQ!$A$2:$NF$60,MATCH(1,(GMWQ!$NE$2:$NE$60=I$3)*(GMWQ!$NF$2:$NF$60=I$1),0),$B33-1966)} -> 39632.09 | J33: {=INDEX(GMWQ!$A$2:$NF$60,MATCH(1,(GMWQ!$NE$2:$NE$60=J$3)*(GMWQ!$NF$2:$NF$60=J$1),0),$B33-1966)} -> 11.75 | ... W33: {=INDEX(GMWQ!$A$2:$NF$60,MATCH(1,(GMWQ!$NE$2:$NE$60=W$3)*(GMWQ!$NF$2:$NF$60=W$1),0),$B33-1966)} -> 0.001
B34: =+B33+1 -> 2000 | C34: {=INDEX(GMWQ!$A$2:$NF$60,MATCH(1,(GMWQ!$NE$2:$NE$60=C$3)*(GMWQ!$NF$2:$NF$60=C$1),0),$B34-1966)} -> 6058 | D34: {=INDEX(GMWQ!$A$2:$NF$60,MATCH(1,(GMWQ!$NE$2:$NE$60=D$3)*(GMWQ!$NF$2:$NF$60=D$1),0),$B34-1966)} -> 0.001 | E34: {=INDEX(GMWQ!$A$2:$NF$60,MATCH(1,(GMWQ!$NE$2:$NE$60=E$3)*(GMWQ!$NF$2:$NF$60=E$1),0),$B34-1966)} -> 39802 | F34: {=INDEX(GMWQ!$A$2:$NF$60,MATCH(1,(GMWQ!$NE$2:$NE$60=F$3)*(GMWQ!$NF$2:$NF$60=F$1),0),$B34-1966)} -> 5.5 | G34: {=INDEX(GMWQ!$A$2:$NF$60,MATCH(1,(GMWQ!$NE$2:$NE$60=G$3)*(GMWQ!$NF$2:$NF$60=G$1),0),$B34-1966)} -> 0 | H34: {=INDEX(GMWQ!$A$2:$NF$60,MATCH(1,(GMWQ!$NE$2:$NE$60=H$3)*(GMWQ!$NF$2:$NF$60=H$1),0),$B34-1966)} -> 0.001 | I34: {=INDEX(GMWQ!$A$2:$NF$60,MATCH(1,(GMWQ!$NE$2:$NE$60=I$3)*(GMWQ!$NF$2:$NF$60=I$1),0),$B34-1966)} -> 41122.7 | J34: {=INDEX(GMWQ!$A$2:$NF$60,MATCH(1,(GMWQ!$NE$2:$NE$60=J$3)*(GMWQ!$NF$2:$NF$60=J$1),0),$B34-1966)} -> 13.38 | ... W34: {=INDEX(GMWQ!$A$2:$NF$60,MATCH(1,(GMWQ!$NE$2:$NE$60=W$3)*(GMWQ!$NF$2:$NF$60=W$1),0),$B34-1966)} -> 0.001
A35: 1980 | B35: =+B34+1 -> 2001 | C35: {=INDEX(GMWQ!$A$2:$NF$60,MATCH(1,(GMWQ!$NE$2:$NE$60=C$3)*(GMWQ!$NF$2:$NF$60=C$1),0),$B35-1966)} -> 6096 | D35: {=INDEX(GMWQ!$A$2:$NF$60,MATCH(1,(GMWQ!$NE$2:$NE$60=D$3)*(GMWQ!$NF$2:$NF$60=D$1),0),$B35-1966)} -> 0.001 | E35: {=INDEX(GMWQ!$A$2:$NF$60,MATCH(1,(GMWQ!$NE$2:$NE$60=E$3)*(GMWQ!$NF$2:$NF$60=E$1),0),$B35-1966)} -> 40290 | F35: {=INDEX(GMWQ!$A$2:$NF$60,MATCH(1,(GMWQ!$NE$2:$NE$60=F$3)*(GMWQ!$NF$2:$NF$60=F$1),0),$B35-1966)} -> 5.8 | G35: {=INDEX(GMWQ!$A$2:$NF$60,MATCH(1,(GMWQ!$NE$2:$NE$60=G$3)*(GMWQ!$NF$2:$NF$60=G$1),0),$B35-1966)} -> 64761.59 | H35: {=INDEX(GMWQ!$A$2:$NF$60,MATCH(1,(GMWQ!$NE$2:$NE$60=H$3)*(GMWQ!$NF$2:$NF$60=H$1),0),$B35-1966)} -> 0.001 | I35: {=INDEX(GMWQ!$A$2:$NF$60,MATCH(1,(GMWQ!$NE$2:$NE$60=I$3)*(GMWQ!$NF$2:$NF$60=I$1),0),$B35-1966)} -> 42551.42 | J35: {=INDEX(GMWQ!$A$2:$NF$60,MATCH(1,(GMWQ!$NE$2:$NE$60=J$3)*(GMWQ!$NF$2:$NF$60=J$1),0),$B35-1966)} -> 14.7821 | ... W35: {=INDEX(GMWQ!$A$2:$NF$60,MATCH(1,(GMWQ!$NE$2:$NE$60=W$3)*(GMWQ!$NF$2:$NF$60=W$1),0),$B35-1966)} -> 0.001
B36: =+B35+1 -> 2002 | C36: {=INDEX(GMWQ!$A$2:$NF$60,MATCH(1,(GMWQ!$NE$2:$NE$60=C$3)*(GMWQ!$NF$2:$NF$60=C$1),0),$B36-1966)} -> 6134 | D36: {=INDEX(GMWQ!$A$2:$NF$60,MATCH(1,(GMWQ!$NE$2:$NE$60=D$3)*(GMWQ!$NF$2:$NF$60=D$1),0),$B36-1966)} -> 0.001 | E36: {=INDEX(GMWQ!$A$2:$NF$60,MATCH(1,(GMWQ!$NE$2:$NE$60=E$3)*(GMWQ!$NF$2:$NF$60=E$1),0),$B36-1966)} -> 41818 | F36: {=INDEX(GMWQ!$A$2:$NF$60,MATCH(1,(GMWQ!$NE$2:$NE$60=F$3)*(GMWQ!$NF$2:$NF$60=F$1),0),$B36-1966)} -> 6.3 | G36: {=INDEX(GMWQ!$A$2:$NF$60,MATCH(1,(GMWQ!$NE$2:$NE$60=G$3)*(GMWQ!$NF$2:$NF$60=G$1),0),$B36-1966)} -> 67638.73 | H36: {=INDEX(GMWQ!$A$2:$NF$60,MATCH(1,(GMWQ!$NE$2:$NE$60=H$3)*(GMWQ!$NF$2:$NF$60=H$1),0),$B36-1966)} -> 0.001 | I36: {=INDEX(GMWQ!$A$2:$NF$60,MATCH(1,(GMWQ!$NE$2:$NE$60=I$3)*(GMWQ!$NF$2:$NF$60=I$1),0),$B36-1966)} -> 44142.13 | J36: {=INDEX(GMWQ!$A$2:$NF$60,MATCH(1,(GMWQ!$NE$2:$NE$60=J$3)*(GMWQ!$NF$2:$NF$60=J$1),0),$B36-1966)} -> 14.8755 | ... W36: {=INDEX(GMWQ!$A$2:$NF$60,MATCH(1,(GMWQ!$NE$2:$NE$60=W$3)*(GMWQ!$NF$2:$NF$60=W$1),0),$B36-1966)} -> 0.001
B37: =+B36+1 -> 2003 | C37: {=INDEX(GMWQ!$A$2:$NF$60,MATCH(1,(GMWQ!$NE$2:$NE$60=C$3)*(GMWQ!$NF$2:$NF$60=C$1),0),$B37-1966)} -> 6172 | D37: {=INDEX(GMWQ!$A$2:$NF$60,MATCH(1,(GMWQ!$NE$2:$NE$60=D$3)*(GMWQ!$NF$2:$NF$60=D$1),0),$B37-1966)} -> 0.001 | E37: {=INDEX(GMWQ!$A$2:$NF$60,MATCH(1,(GMWQ!$NE$2:$NE$60=E$3)*(GMWQ!$NF$2:$NF$60=E$1),0),$B37-1966)} -> 43433 | F37: {=INDEX(GMWQ!$A$2:$NF$60,MATCH(1,(GMWQ!$NE$2:$NE$60=F$3)*(GMWQ!$NF$2:$NF$60=F$1),0),$B37-1966)} -> 7.1 | G37: {=INDEX(GMWQ!$A$2:$NF$60,MATCH(1,(GMWQ!$NE$2:$NE$60=G$3)*(GMWQ!$NF$2:$NF$60=G$1),0),$B37-1966)} -> 70091.01 | H37: {=INDEX(GMWQ!$A$2:$NF$60,MATCH(1,(GMWQ!$NE$2:$NE$60=H$3)*(GMWQ!$NF$2:$NF$60=H$1),0),$B37-1966)} -> 0.001 | I37: {=INDEX(GMWQ!$A$2:$NF$60,MATCH(1,(GMWQ!$NE$2:$NE$60=I$3)*(GMWQ!$NF$2:$NF$60=I$1),0),$B37-1966)} -> 45938.5 | J37: {=INDEX(GMWQ!$A$2:$NF$60,MATCH(1,(GMWQ!$NE$2:$NE$60=J$3)*(GMWQ!$NF$2:$NF$60=J$1),0),$B37-1966)} -> 14.8876 | ... W37: {=INDEX(GMWQ!$A$2:$NF$60,MATCH(1,(GMWQ!$NE$2:$NE$60=W$3)*(GMWQ!$NF$2:$NF$60=W$1),0),$B37-1966)} -> 0.001
B38: =+B37+1 -> 2004 | C38: {=INDEX(GMWQ!$A$2:$NF$60,MATCH(1,(GMWQ!$NE$2:$NE$60=C$3)*(GMWQ!$NF$2:$NF$60=C$1),0),$B38-1966)} -> 6210 | D38: {=INDEX(GMWQ!$A$2:$NF$60,MATCH(1,(GMWQ!$NE$2:$NE$60=D$3)*(GMWQ!$NF$2:$NF$60=D$1),0),$B38-1966)} -> 0.001 | E38: {=INDEX(GMWQ!$A$2:$NF$60,MATCH(1,(GMWQ!$NE$2:$NE$60=E$3)*(GMWQ!$NF$2:$NF$60=E$1),0),$B38-1966)} -> 44864 | F38: {=INDEX(GMWQ!$A$2:$NF$60,MATCH(1,(GMWQ!$NE$2:$NE$60=F$3)*(GMWQ!$NF$2:$NF$60=F$1),0),$B38-1966)} -> 8 | G38: {=INDEX(GMWQ!$A$2:$NF$60,MATCH(1,(GMWQ!$NE$2:$NE$60=G$3)*(GMWQ!$NF$2:$NF$60=G$1),0),$B38-1966)} -> 72610.32 | H38: {=INDEX(GMWQ!$A$2:$NF$60,MATCH(1,(GMWQ!$NE$2:$NE$60=H$3)*(GMWQ!$NF$2:$NF$60=H$1),0),$B38-1966)} -> 0.001 | I38: {=INDEX(GMWQ!$A$2:$NF$60,MATCH(1,(GMWQ!$NE$2:$NE$60=I$3)*(GMWQ!$NF$2:$NF$60=I$1),0),$B38-1966)} -> 47827.69 | J38: {=INDEX(GMWQ!$A$2:$NF$60,MATCH(1,(GMWQ!$NE$2:$NE$60=J$3)*(GMWQ!$NF$2:$NF$60=J$1),0),$B38-1966)} -> 14.9682 | ... W38: {=INDEX(GMWQ!$A$2:$NF$60,MATCH(1,(GMWQ!$NE$2:$NE$60=W$3)*(GMWQ!$NF$2:$NF$60=W$1),0),$B38-1966)} -> 0.001
A39: 1981 | B39: =+B38+1 -> 2005 | C39: {=INDEX(GMWQ!$A$2:$NF$60,MATCH(1,(GMWQ!$NE$2:$NE$60=C$3)*(GMWQ!$NF$2:$NF$60=C$1),0),$B39-1966)} -> 6241.5 | D39: {=INDEX(GMWQ!$A$2:$NF$60,MATCH(1,(GMWQ!$NE$2:$NE$60=D$3)*(GMWQ!$NF$2:$NF$60=D$1),0),$B39-1966)} -> 0.001 | E39: {=INDEX(GMWQ!$A$2:$NF$60,MATCH(1,(GMWQ!$NE$2:$NE$60=E$3)*(GMWQ!$NF$2:$NF$60=E$1),0),$B39-1966)} -> 46552 | F39: {=INDEX(GMWQ!$A$2:$NF$60,MATCH(1,(GMWQ!$NE$2:$NE$60=F$3)*(GMWQ!$NF$2:$NF$60=F$1),0),$B39-1966)} -> 8.9 | G39: {=INDEX(GMWQ!$A$2:$NF$60,MATCH(1,(GMWQ!$NE$2:$NE$60=G$3)*(GMWQ!$NF$2:$NF$60=G$1),0),$B39-1966)} -> 75025.47 | H39: {=INDEX(GMWQ!$A$2:$NF$60,MATCH(1,(GMWQ!$NE$2:$NE$60=H$3)*(GMWQ!$NF$2:$NF$60=H$1),0),$B39-1966)} -> 0.001 | I39: {=INDEX(GMWQ!$A$2:$NF$60,MATCH(1,(GMWQ!$NE$2:$NE$60=I$3)*(GMWQ!$NF$2:$NF$60=I$1),0),$B39-1966)} -> 49649.54 | J39: {=INDEX(GMWQ!$A$2:$NF$60,MATCH(1,(GMWQ!$NE$2:$NE$60=J$3)*(GMWQ!$NF$2:$NF$60=J$1),0),$B39-1966)} -> 13.8888 | ... W39: {=INDEX(GMWQ!$A$2:$NF$60,MATCH(1,(GMWQ!$NE$2:$NE$60=W$3)*(GMWQ!$NF$2:$NF$60=W$1),0),$B39-1966)} -> 0.001
B40: =+B39+1 -> 2006 | C40: {=INDEX(GMWQ!$A$2:$NF$60,MATCH(1,(GMWQ!$NE$2:$NE$60=C$3)*(GMWQ!$NF$2:$NF$60=C$1),0),$B40-1966)} -> 6273 | D40: {=INDEX(GMWQ!$A$2:$NF$60,MATCH(1,(GMWQ!$NE$2:$NE$60=D$3)*(GMWQ!$NF$2:$NF$60=D$1),0),$B40-1966)} -> 0.001 | E40: {=INDEX(GMWQ!$A$2:$NF$60,MATCH(1,(GMWQ!$NE$2:$NE$60=E$3)*(GMWQ!$NF$2:$NF$60=E$1),0),$B40-1966)} -> 47036 | F40: {=INDEX(GMWQ!$A$2:$NF$60,MATCH(1,(GMWQ!$NE$2:$NE$60=F$3)*(GMWQ!$NF$2:$NF$60=F$1),0),$B40-1966)} -> 9.6 | G40: {=INDEX(GMWQ!$A$2:$NF$60,MATCH(1,(GMWQ!$NE$2:$NE$60=G$3)*(GMWQ!$NF$2:$NF$60=G$1),0),$B40-1966)} -> 78545.08 | H40: {=INDEX(GMWQ!$A$2:$NF$60,MATCH(1,(GMWQ!$NE$2:$NE$60=H$3)*(GMWQ!$NF$2:$NF$60=H$1),0),$B40-1966)} -> 0.001 | I40: {=INDEX(GMWQ!$A$2:$NF$60,MATCH(1,(GMWQ!$NE$2:$NE$60=I$3)*(GMWQ!$NF$2:$NF$60=I$1),0),$B40-1966)} -> 51874.53 | J40: {=INDEX(GMWQ!$A$2:$NF$60,MATCH(1,(GMWQ!$NE$2:$NE$60=J$3)*(GMWQ!$NF$2:$NF$60=J$1),0),$B40-1966)} -> 13.0457 | ... W40: {=INDEX(GMWQ!$A$2:$NF$60,MATCH(1,(GMWQ!$NE$2:$NE$60=W$3)*(GMWQ!$NF$2:$NF$60=W$1),0),$B40-1966)} -> 0.001
B41: =+B40+1 -> 2007 | C41: {=INDEX(GMWQ!$A$2:$NF$60,MATCH(1,(GMWQ!$NE$2:$NE$60=C$3)*(GMWQ!$NF$2:$NF$60=C$1),0),$B41-1966)} -> 6304.5 | D41: {=INDEX(GMWQ!$A$2:$NF$60,MATCH(1,(GMWQ!$NE$2:$NE$60=D$3)*(GMWQ!$NF$2:$NF$60=D$1),0),$B41-1966)} -> 0.001 | E41: {=INDEX(GMWQ!$A$2:$NF$60,MATCH(1,(GMWQ!$NE$2:$NE$60=E$3)*(GMWQ!$NF$2:$NF$60=E$1),0),$B41-1966)} -> 47924 | F41: {=INDEX(GMWQ!$A$2:$NF$60,MATCH(1,(GMWQ!$NE$2:$NE$60=F$3)*(GMWQ!$NF$2:$NF$60=F$1),0),$B41-1966)} -> 9.9 | G41: {=INDEX(GMWQ!$A$2:$NF$60,MATCH(1,(GMWQ!$NE$2:$NE$60=G$3)*(GMWQ!$NF$2:$NF$60=G$1),0),$B41-1966)} -> 81974.97 | H41: {=INDEX(GMWQ!$A$2:$NF$60,MATCH(1,(GMWQ!$NE$2:$NE$60=H$3)*(GMWQ!$NF$2:$NF$60=H$1),0),$B41-1966)} -> 0.001 | I41: {=INDEX(GMWQ!$A$2:$NF$60,MATCH(1,(GMWQ!$NE$2:$NE$60=I$3)*(GMWQ!$NF$2:$NF$60=I$1),0),$B41-1966)} -> 54199.62 | J41: {=INDEX(GMWQ!$A$2:$NF$60,MATCH(1,(GMWQ!$NE$2:$NE$60=J$3)*(GMWQ!$NF$2:$NF$60=J$1),0),$B41-1966)} -> 12.6246 | ... W41: {=INDEX(GMWQ!$A$2:$NF$60,MATCH(1,(GMWQ!$NE$2:$NE$60=W$3)*(GMWQ!$NF$2:$NF$60=W$1),0),$B41-1966)} -> 0.001
B42: =+B41+1 -> 2008 | C42: {=INDEX(GMWQ!$A$2:$NF$60,MATCH(1,(GMWQ!$NE$2:$NE$60=C$3)*(GMWQ!$NF$2:$NF$60=C$1),0),$B42-1966)} -> 6336 | D42: {=INDEX(GMWQ!$A$2:$NF$60,MATCH(1,(GMWQ!$NE$2:$NE$60=D$3)*(GMWQ!$NF$2:$NF$60=D$1),0),$B42-1966)} -> 0.001 | E42: {=INDEX(GMWQ!$A$2:$NF$60,MATCH(1,(GMWQ!$NE$2:$NE$60=E$3)*(GMWQ!$NF$2:$NF$60=E$1),0),$B42-1966)} -> 49843 | F42: {=INDEX(GMWQ!$A$2:$NF$60,MATCH(1,(GMWQ!$NE$2:$NE$60=F$3)*(GMWQ!$NF$2:$NF$60=F$1),0),$B42-1966)} -> 10.2 | G42: {=INDEX(GMWQ!$A$2:$NF$60,MATCH(1,(GMWQ!$NE$2:$NE$60=G$3)*(GMWQ!$NF$2:$NF$60=G$1),0),$B42-1966)} -> 87375.55 | H42: {=INDEX(GMWQ!$A$2:$NF$60,MATCH(1,(GMWQ!$NE$2:$NE$60=H$3)*(GMWQ!$NF$2:$NF$60=H$1),0),$B42-1966)} -> 0.001 | I42: {=INDEX(GMWQ!$A$2:$NF$60,MATCH(1,(GMWQ!$NE$2:$NE$60=I$3)*(GMWQ!$NF$2:$NF$60=I$1),0),$B42-1966)} -> 56936.95 | J42: {=INDEX(GMWQ!$A$2:$NF$60,MATCH(1,(GMWQ!$NE$2:$NE$60=J$3)*(GMWQ!$NF$2:$NF$60=J$1),0),$B42-1966)} -> 14.7041 | ... W42: {=INDEX(GMWQ!$A$2:$NF$60,MATCH(1,(GMWQ!$NE$2:$NE$60=W$3)*(GMWQ!$NF$2:$NF$60=W$1),0),$B42-1966)} -> 0.001
A43: 1982 | B43: =+B42+1 -> 2009 | C43: {=INDEX(GMWQ!$A$2:$NF$60,MATCH(1,(GMWQ!$NE$2:$NE$60=C$3)*(GMWQ!$NF$2:$NF$60=C$1),0),$B43-1966)} -> 6373 | D43: {=INDEX(GMWQ!$A$2:$NF$60,MATCH(1,(GMWQ!$NE$2:$NE$60=D$3)*(GMWQ!$NF$2:$NF$60=D$1),0),$B43-1966)} -> 0.001 | E43: {=INDEX(GMWQ!$A$2:$NF$60,MATCH(1,(GMWQ!$NE$2:$NE$60=E$3)*(GMWQ!$NF$2:$NF$60=E$1),0),$B43-1966)} -> 50837 | F43: {=INDEX(GMWQ!$A$2:$NF$60,MATCH(1,(GMWQ!$NE$2:$NE$60=F$3)*(GMWQ!$NF$2:$NF$60=F$1),0),$B43-1966)} -> 10.4 | G43: {=INDEX(GMWQ!$A$2:$NF$60,MATCH(1,(GMWQ!$NE$2:$NE$60=G$3)*(GMWQ!$NF$2:$NF$60=G$1),0),$B43-1966)} -> 88820.3 | H43: {=INDEX(GMWQ!$A$2:$NF$60,MATCH(1,(GMWQ!$NE$2:$NE$60=H$3)*(GMWQ!$NF$2:$NF$60=H$1),0),$B43-1966)} -> 0.001 | I43: {=INDEX(GMWQ!$A$2:$NF$60,MATCH(1,(GMWQ!$NE$2:$NE$60=I$3)*(GMWQ!$NF$2:$NF$60=I$1),0),$B43-1966)} -> 59117.34 | J43: {=INDEX(GMWQ!$A$2:$NF$60,MATCH(1,(GMWQ!$NE$2:$NE$60=J$3)*(GMWQ!$NF$2:$NF$60=J$1),0),$B43-1966)} -> 14.5939 | ... W43: {=INDEX(GMWQ!$A$2:$NF$60,MATCH(1,(GMWQ!$NE$2:$NE$60=W$3)*(GMWQ!$NF$2:$NF$60=W$1),0),$B43-1966)} -> 0.001
B44: =+B43+1 -> 2010 | C44: {=INDEX(GMWQ!$A$2:$NF$60,MATCH(1,(GMWQ!$NE$2:$NE$60=C$3)*(GMWQ!$NF$2:$NF$60=C$1),0),$B44-1966)} -> 6410 | D44: {=INDEX(GMWQ!$A$2:$NF$60,MATCH(1,(GMWQ!$NE$2:$NE$60=D$3)*(GMWQ!$NF$2:$NF$60=D$1),0),$B44-1966)} -> 0.001 | E44: {=INDEX(GMWQ!$A$2:$NF$60,MATCH(1,(GMWQ!$NE$2:$NE$60=E$3)*(GMWQ!$NF$2:$NF$60=E$1),0),$B44-1966)} -> 52380 | F44: {=INDEX(GMWQ!$A$2:$NF$60,MATCH(1,(GMWQ!$NE$2:$NE$60=F$3)*(GMWQ!$NF$2:$NF$60=F$1),0),$B44-1966)} -> 10.6 | G44: {=INDEX(GMWQ!$A$2:$NF$60,MATCH(1,(GMWQ!$NE$2:$NE$60=G$3)*(GMWQ!$NF$2:$NF$60=G$1),0),$B44-1966)} -> 93446.43 | H44: {=INDEX(GMWQ!$A$2:$NF$60,MATCH(1,(GMWQ!$NE$2:$NE$60=H$3)*(GMWQ!$NF$2:$NF$60=H$1),0),$B44-1966)} -> 0.001 | I44: {=INDEX(GMWQ!$A$2:$NF$60,MATCH(1,(GMWQ!$NE$2:$NE$60=I$3)*(GMWQ!$NF$2:$NF$60=I$1),0),$B44-1966)} -> 62344.26 | J44: {=INDEX(GMWQ!$A$2:$NF$60,MATCH(1,(GMWQ!$NE$2:$NE$60=J$3)*(GMWQ!$NF$2:$NF$60=J$1),0),$B44-1966)} -> 13.4576 | ... W44: {=INDEX(GMWQ!$A$2:$NF$60,MATCH(1,(GMWQ!$NE$2:$NE$60=W$3)*(GMWQ!$NF$2:$NF$60=W$1),0),$B44-1966)} -> 0.001
B45: =+B44+1 -> 2011 | C45: {=INDEX(GMWQ!$A$2:$NF$60,MATCH(1,(GMWQ!$NE$2:$NE$60=C$3)*(GMWQ!$NF$2:$NF$60=C$1),0),$B45-1966)} -> 6464 | D45: {=INDEX(GMWQ!$A$2:$NF$60,MATCH(1,(GMWQ!$NE$2:$NE$60=D$3)*(GMWQ!$NF$2:$NF$60=D$1),0),$B45-1966)} -> 0.001 | E45: {=INDEX(GMWQ!$A$2:$NF$60,MATCH(1,(GMWQ!$NE$2:$NE$60=E$3)*(GMWQ!$NF$2:$NF$60=E$1),0),$B45-1966)} -> 52615 | F45: {=INDEX(GMWQ!$A$2:$NF$60,MATCH(1,(GMWQ!$NE$2:$NE$60=F$3)*(GMWQ!$NF$2:$NF$60=F$1),0),$B45-1966)} -> 10.8 | G45: {=INDEX(GMWQ!$A$2:$NF$60,MATCH(1,(GMWQ!$NE$2:$NE$60=G$3)*(GMWQ!$NF$2:$NF$60=G$1),0),$B45-1966)} -> 98690.26 | H45: {=INDEX(GMWQ!$A$2:$NF$60,MATCH(1,(GMWQ!$NE$2:$NE$60=H$3)*(GMWQ!$NF$2:$NF$60=H$1),0),$B45-1966)} -> 0.001 | I45: {=INDEX(GMWQ!$A$2:$NF$60,MATCH(1,(GMWQ!$NE$2:$NE$60=I$3)*(GMWQ!$NF$2:$NF$60=I$1),0),$B45-1966)} -> 65846 | J45: {=INDEX(GMWQ!$A$2:$NF$60,MATCH(1,(GMWQ!$NE$2:$NE$60=J$3)*(GMWQ!$NF$2:$NF$60=J$1),0),$B45-1966)} -> 12.6124 | ... W45: {=INDEX(GMWQ!$A$2:$NF$60,MATCH(1,(GMWQ!$NE$2:$NE$60=W$3)*(GMWQ!$NF$2:$NF$60=W$1),0),$B45-1966)} -> 0.001
B46: =+B45+1 -> 2012 | C46: {=INDEX(GMWQ!$A$2:$NF$60,MATCH(1,(GMWQ!$NE$2:$NE$60=C$3)*(GMWQ!$NF$2:$NF$60=C$1),0),$B46-1966)} -> 6518 | D46: {=INDEX(GMWQ!$A$2:$NF$60,MATCH(1,(GMWQ!$NE$2:$NE$60=D$3)*(GMWQ!$NF$2:$NF$60=D$1),0),$B46-1966)} -> 0.001 | E46: {=INDEX(GMWQ!$A$2:$NF$60,MATCH(1,(GMWQ!$NE$2:$NE$60=E$3)*(GMWQ!$NF$2:$NF$60=E$1),0),$B46-1966)} -> 53960 | F46: {=INDEX(GMWQ!$A$2:$NF$60,MATCH(1,(GMWQ!$NE$2:$NE$60=F$3)*(GMWQ!$NF$2:$NF$60=F$1),0),$B46-1966)} -> 11.1 | G46: {=INDEX(GMWQ!$A$2:$NF$60,MATCH(1,(GMWQ!$NE$2:$NE$60=G$3)*(GMWQ!$NF$2:$NF$60=G$1),0),$B46-1966)} -> 103494.8 | H46: {=INDEX(GMWQ!$A$2:$NF$60,MATCH(1,(GMWQ!$NE$2:$NE$60=H$3)*(GMWQ!$NF$2:$NF$60=H$1),0),$B46-1966)} -> 0.001 | I46: {=INDEX(GMWQ!$A$2:$NF$60,MATCH(1,(GMWQ!$NE$2:$NE$60=I$3)*(GMWQ!$NF$2:$NF$60=I$1),0),$B46-1966)} -> 69524.28 | J46: {=INDEX(GMWQ!$A$2:$NF$60,MATCH(1,(GMWQ!$NE$2:$NE$60=J$3)*(GMWQ!$NF$2:$NF$60=J$1),0),$B46-1966)} -> 10.9634 | ... W46: {=INDEX(GMWQ!$A$2:$NF$60,MATCH(1,(GMWQ!$NE$2:$NE$60=W$3)*(GMWQ!$NF$2:$NF$60=W$1),0),$B46-1966)} -> 0.001
A47: 1983 | B47: =+B46+1 -> 2013 | C47: {=INDEX(GMWQ!$A$2:$NF$60,MATCH(1,(GMWQ!$NE$2:$NE$60=C$3)*(GMWQ!$NF$2:$NF$60=C$1),0),$B47-1966)} -> 6565.5 | D47: {=INDEX(GMWQ!$A$2:$NF$60,MATCH(1,(GMWQ!$NE$2:$NE$60=D$3)*(GMWQ!$NF$2:$NF$60=D$1),0),$B47-1966)} -> 0.001 | E47: {=INDEX(GMWQ!$A$2:$NF$60,MATCH(1,(GMWQ!$NE$2:$NE$60=E$3)*(GMWQ!$NF$2:$NF$60=E$1),0),$B47-1966)} -> 54514 | F47: {=INDEX(GMWQ!$A$2:$NF$60,MATCH(1,(GMWQ!$NE$2:$NE$60=F$3)*(GMWQ!$NF$2:$NF$60=F$1),0),$B47-1966)} -> 11.3 | G47: {=INDEX(GMWQ!$A$2:$NF$60,MATCH(1,(GMWQ!$NE$2:$NE$60=G$3)*(GMWQ!$NF$2:$NF$60=G$1),0),$B47-1966)} -> 108127.1 | H47: {=INDEX(GMWQ!$A$2:$NF$60,MATCH(1,(GMWQ!$NE$2:$NE$60=H$3)*(GMWQ!$NF$2:$NF$60=H$1),0),$B47-1966)} -> 0.001 | I47: {=INDEX(GMWQ!$A$2:$NF$60,MATCH(1,(GMWQ!$NE$2:$NE$60=I$3)*(GMWQ!$NF$2:$NF$60=I$1),0),$B47-1966)} -> 72844.93 | J47: {=INDEX(GMWQ!$A$2:$NF$60,MATCH(1,(GMWQ!$NE$2:$NE$60=J$3)*(GMWQ!$NF$2:$NF$60=J$1),0),$B47-1966)} -> 9.92754 | ... W47: {=INDEX(GMWQ!$A$2:$NF$60,MATCH(1,(GMWQ!$NE$2:$NE$60=W$3)*(GMWQ!$NF$2:$NF$60=W$1),0),$B47-1966)} -> 0.001
B48: =+B47+1 -> 2014 | C48: {=INDEX(GMWQ!$A$2:$NF$60,MATCH(1,(GMWQ!$NE$2:$NE$60=C$3)*(GMWQ!$NF$2:$NF$60=C$1),0),$B48-1966)} -> 6613 | D48: {=INDEX(GMWQ!$A$2:$NF$60,MATCH(1,(GMWQ!$NE$2:$NE$60=D$3)*(GMWQ!$NF$2:$NF$60=D$1),0),$B48-1966)} -> 0.001 | E48: {=INDEX(GMWQ!$A$2:$NF$60,MATCH(1,(GMWQ!$NE$2:$NE$60=E$3)*(GMWQ!$NF$2:$NF$60=E$1),0),$B48-1966)} -> 57136 | F48: {=INDEX(GMWQ!$A$2:$NF$60,MATCH(1,(GMWQ!$NE$2:$NE$60=F$3)*(GMWQ!$NF$2:$NF$60=F$1),0),$B48-1966)} -> 11.4 | G48: {=INDEX(GMWQ!$A$2:$NF$60,MATCH(1,(GMWQ!$NE$2:$NE$60=G$3)*(GMWQ!$NF$2:$NF$60=G$1),0),$B48-1966)} -> 113141 | H48: {=INDEX(GMWQ!$A$2:$NF$60,MATCH(1,(GMWQ!$NE$2:$NE$60=H$3)*(GMWQ!$NF$2:$NF$60=H$1),0),$B48-1966)} -> 0.001 | I48: {=INDEX(GMWQ!$A$2:$NF$60,MATCH(1,(GMWQ!$NE$2:$NE$60=I$3)*(GMWQ!$NF$2:$NF$60=I$1),0),$B48-1966)} -> 76218.35 | J48: {=INDEX(GMWQ!$A$2:$NF$60,MATCH(1,(GMWQ!$NE$2:$NE$60=J$3)*(GMWQ!$NF$2:$NF$60=J$1),0),$B48-1966)} -> 10.0759 | ... W48: {=INDEX(GMWQ!$A$2:$NF$60,MATCH(1,(GMWQ!$NE$2:$NE$60=W$3)*(GMWQ!$NF$2:$NF$60=W$1),0),$B48-1966)} -> 0.001
B49: =+B48+1 -> 2015 | C49: {=INDEX(GMWQ!$A$2:$NF$60,MATCH(1,(GMWQ!$NE$2:$NE$60=C$3)*(GMWQ!$NF$2:$NF$60=C$1),0),$B49-1966)} -> 6729.5 | D49: {=INDEX(GMWQ!$A$2:$NF$60,MATCH(1,(GMWQ!$NE$2:$NE$60=D$3)*(GMWQ!$NF$2:$NF$60=D$1),0),$B49-1966)} -> 0.001 | E49: {=INDEX(GMWQ!$A$2:$NF$60,MATCH(1,(GMWQ!$NE$2:$NE$60=E$3)*(GMWQ!$NF$2:$NF$60=E$1),0),$B49-1966)} -> 57119 | F49: {=INDEX(GMWQ!$A$2:$NF$60,MATCH(1,(GMWQ!$NE$2:$NE$60=F$3)*(GMWQ!$NF$2:$NF$60=F$1),0),$B49-1966)} -> 11.5 | G49: {=INDEX(GMWQ!$A$2:$NF$60,MATCH(1,(GMWQ!$NE$2:$NE$60=G$3)*(GMWQ!$NF$2:$NF$60=G$1),0),$B49-1966)} -> 118131.1 | H49: {=INDEX(GMWQ!$A$2:$NF$60,MATCH(1,(GMWQ!$NE$2:$NE$60=H$3)*(GMWQ!$NF$2:$NF$60=H$1),0),$B49-1966)} -> 0.001 | I49: {=INDEX(GMWQ!$A$2:$NF$60,MATCH(1,(GMWQ!$NE$2:$NE$60=I$3)*(GMWQ!$NF$2:$NF$60=I$1),0),$B49-1966)} -> 79988.55 | J49: {=INDEX(GMWQ!$A$2:$NF$60,MATCH(1,(GMWQ!$NE$2:$NE$60=J$3)*(GMWQ!$NF$2:$NF$60=J$1),0),$B49-1966)} -> 11.2349 | ... W49: {=INDEX(GMWQ!$A$2:$NF$60,MATCH(1,(GMWQ!$NE$2:$NE$60=W$3)*(GMWQ!$NF$2:$NF$60=W$1),0),$B49-1966)} -> 0.001
B50: =+B49+1 -> 2016 | C50: {=INDEX(GMWQ!$A$2:$NF$60,MATCH(1,(GMWQ!$NE$2:$NE$60=C$3)*(GMWQ!$NF$2:$NF$60=C$1),0),$B50-1966)} -> 6846 | D50: {=INDEX(GMWQ!$A$2:$NF$60,MATCH(1,(GMWQ!$NE$2:$NE$60=D$3)*(GMWQ!$NF$2:$NF$60=D$1),0),$B50-1966)} -> 0.001 | E50: {=INDEX(GMWQ!$A$2:$NF$60,MATCH(1,(GMWQ!$NE$2:$NE$60=E$3)*(GMWQ!$NF$2:$NF$60=E$1),0),$B50-1966)} -> 58206 | F50: {=INDEX(GMWQ!$A$2:$NF$60,MATCH(1,(GMWQ!$NE$2:$NE$60=F$3)*(GMWQ!$NF$2:$NF$60=F$1),0),$B50-1966)} -> 11.7 | G50: {=INDEX(GMWQ!$A$2:$NF$60,MATCH(1,(GMWQ!$NE$2:$NE$60=G$3)*(GMWQ!$NF$2:$NF$60=G$1),0),$B50-1966)} -> 122827.4 | H50: {=INDEX(GMWQ!$A$2:$NF$60,MATCH(1,(GMWQ!$NE$2:$NE$60=H$3)*(GMWQ!$NF$2:$NF$60=H$1),0),$B50-1966)} -> 0.001 | I50: {=INDEX(GMWQ!$A$2:$NF$60,MATCH(1,(GMWQ!$NE$2:$NE$60=I$3)*(GMWQ!$NF$2:$NF$60=I$1),0),$B50-1966)} -> 83288.27 | J50: {=INDEX(GMWQ!$A$2:$NF$60,MATCH(1,(GMWQ!$NE$2:$NE$60=J$3)*(GMWQ!$NF$2:$NF$60=J$1),0),$B50-1966)} -> 11.2541 | ... W50: {=INDEX(GMWQ!$A$2:$NF$60,MATCH(1,(GMWQ!$NE$2:$NE$60=W$3)*(GMWQ!$NF$2:$NF$60=W$1),0),$B50-1966)} -> 0.001
A51: 1984 | B51: =+B50+1 -> 2017 | C51: {=INDEX(GMWQ!$A$2:$NF$60,MATCH(1,(GMWQ!$NE$2:$NE$60=C$3)*(GMWQ!$NF$2:$NF$60=C$1),0),$B51-1966)} -> 6950 | D51: {=INDEX(GMWQ!$A$2:$NF$60,MATCH(1,(GMWQ!$NE$2:$NE$60=D$3)*(GMWQ!$NF$2:$NF$60=D$1),0),$B51-1966)} -> 0.001 | E51: {=INDEX(GMWQ!$A$2:$NF$60,MATCH(1,(GMWQ!$NE$2:$NE$60=E$3)*(GMWQ!$NF$2:$NF$60=E$1),0),$B51-1966)} -> 59961 | F51: {=INDEX(GMWQ!$A$2:$NF$60,MATCH(1,(GMWQ!$NE$2:$NE$60=F$3)*(GMWQ!$NF$2:$NF$60=F$1),0),$B51-1966)} -> 11.8 | G51: {=INDEX(GMWQ!$A$2:$NF$60,MATCH(1,(GMWQ!$NE$2:$NE$60=G$3)*(GMWQ!$NF$2:$NF$60=G$1),0),$B51-1966)} -> 133258.3 | H51: {=INDEX(GMWQ!$A$2:$NF$60,MATCH(1,(GMWQ!$NE$2:$NE$60=H$3)*(GMWQ!$NF$2:$NF$60=H$1),0),$B51-1966)} -> 0.001 | I51: {=INDEX(GMWQ!$A$2:$NF$60,MATCH(1,(GMWQ!$NE$2:$NE$60=I$3)*(GMWQ!$NF$2:$NF$60=I$1),0),$B51-1966)} -> 86173.92 | J51: {=INDEX(GMWQ!$A$2:$NF$60,MATCH(1,(GMWQ!$NE$2:$NE$60=J$3)*(GMWQ!$NF$2:$NF$60=J$1),0),$B51-1966)} -> 11.47 | ... W51: {=INDEX(GMWQ!$A$2:$NF$60,MATCH(1,(GMWQ!$NE$2:$NE$60=W$3)*(GMWQ!$NF$2:$NF$60=W$1),0),$B51-1966)} -> 0.001
B52: =+B51+1 -> 2018 | C52: {=INDEX(GMWQ!$A$2:$NF$60,MATCH(1,(GMWQ!$NE$2:$NE$60=C$3)*(GMWQ!$NF$2:$NF$60=C$1),0),$B52-1966)} -> 7054 | D52: {=INDEX(GMWQ!$A$2:$NF$60,MATCH(1,(GMWQ!$NE$2:$NE$60=D$3)*(GMWQ!$NF$2:$NF$60=D$1),0),$B52-1966)} -> 0.001 | E52: {=INDEX(GMWQ!$A$2:$NF$60,MATCH(1,(GMWQ!$NE$2:$NE$60=E$3)*(GMWQ!$NF$2:$NF$60=E$1),0),$B52-1966)} -> 60260 | F52: {=INDEX(GMWQ!$A$2:$NF$60,MATCH(1,(GMWQ!$NE$2:$NE$60=F$3)*(GMWQ!$NF$2:$NF$60=F$1),0),$B52-1966)} -> 11.9 | G52: {=INDEX(GMWQ!$A$2:$NF$60,MATCH(1,(GMWQ!$NE$2:$NE$60=G$3)*(GMWQ!$NF$2:$NF$60=G$1),0),$B52-1966)} -> 139291 | H52: {=INDEX(GMWQ!$A$2:$NF$60,MATCH(1,(GMWQ!$NE$2:$NE$60=H$3)*(GMWQ!$NF$2:$NF$60=H$1),0),$B52-1966)} -> 0.001 | I52: {=INDEX(GMWQ!$A$2:$NF$60,MATCH(1,(GMWQ!$NE$2:$NE$60=I$3)*(GMWQ!$NF$2:$NF$60=I$1),0),$B52-1966)} -> 90325.41 | J52: {=INDEX(GMWQ!$A$2:$NF$60,MATCH(1,(GMWQ!$NE$2:$NE$60=J$3)*(GMWQ!$NF$2:$NF$60=J$1),0),$B52-1966)} -> 10.51 | ... W52: {=INDEX(GMWQ!$A$2:$NF$60,MATCH(1,(GMWQ!$NE$2:$NE$60=W$3)*(GMWQ!$NF$2:$NF$60=W$1),0),$B52-1966)} -> 0.001
B53: =+B52+1 -> 2019 | C53: {=INDEX(GMWQ!$A$2:$NF$60,MATCH(1,(GMWQ!$NE$2:$NE$60=C$3)*(GMWQ!$NF$2:$NF$60=C$1),0),$B53-1966)} -> 7183.5 | D53: {=INDEX(GMWQ!$A$2:$NF$60,MATCH(1,(GMWQ!$NE$2:$NE$60=D$3)*(GMWQ!$NF$2:$NF$60=D$1),0),$B53-1966)} -> 0.001 | E53: {=INDEX(GMWQ!$A$2:$NF$60,MATCH(1,(GMWQ!$NE$2:$NE$60=E$3)*(GMWQ!$NF$2:$NF$60=E$1),0),$B53-1966)} -> 62678 | F53: {=INDEX(GMWQ!$A$2:$NF$60,MATCH(1,(GMWQ!$NE$2:$NE$60=F$3)*(GMWQ!$NF$2:$NF$60=F$1),0),$B53-1966)} -> 11.7 | G53: {=INDEX(GMWQ!$A$2:$NF$60,MATCH(1,(GMWQ!$NE$2:$NE$60=G$3)*(GMWQ!$NF$2:$NF$60=G$1),0),$B53-1966)} -> 145310.4 | H53: {=INDEX(GMWQ!$A$2:$NF$60,MATCH(1,(GMWQ!$NE$2:$NE$60=H$3)*(GMWQ!$NF$2:$NF$60=H$1),0),$B53-1966)} -> 0.001 | I53: {=INDEX(GMWQ!$A$2:$NF$60,MATCH(1,(GMWQ!$NE$2:$NE$60=I$3)*(GMWQ!$NF$2:$NF$60=I$1),0),$B53-1966)} -> 94470.54 | J53: {=INDEX(GMWQ!$A$2:$NF$60,MATCH(1,(GMWQ!$NE$2:$NE$60=J$3)*(GMWQ!$NF$2:$NF$60=J$1),0),$B53-1966)} -> 13.08 | ... W53: {=INDEX(GMWQ!$A$2:$NF$60,MATCH(1,(GMWQ!$NE$2:$NE$60=W$3)*(GMWQ!$NF$2:$NF$60=W$1),0),$B53-1966)} -> 0.001
B54: =+B53+1 -> 2020 | C54: {=INDEX(GMWQ!$A$2:$NF$60,MATCH(1,(GMWQ!$NE$2:$NE$60=C$3)*(GMWQ!$NF$2:$NF$60=C$1),0),$B54-1966)} -> 7313 | D54: {=INDEX(GMWQ!$A$2:$NF$60,MATCH(1,(GMWQ!$NE$2:$NE$60=D$3)*(GMWQ!$NF$2:$NF$60=D$1),0),$B54-1966)} -> 0.001 | E54: {=INDEX(GMWQ!$A$2:$NF$60,MATCH(1,(GMWQ!$NE$2:$NE$60=E$3)*(GMWQ!$NF$2:$NF$60=E$1),0),$B54-1966)} -> 64883 | F54: {=INDEX(GMWQ!$A$2:$NF$60,MATCH(1,(GMWQ!$NE$2:$NE$60=F$3)*(GMWQ!$NF$2:$NF$60=F$1),0),$B54-1966)} -> 11.6 | G54: {=INDEX(GMWQ!$A$2:$NF$60,MATCH(1,(GMWQ!$NE$2:$NE$60=G$3)*(GMWQ!$NF$2:$NF$60=G$1),0),$B54-1966)} -> 150762.5 | H54: {=INDEX(GMWQ!$A$2:$NF$60,MATCH(1,(GMWQ!$NE$2:$NE$60=H$3)*(GMWQ!$NF$2:$NF$60=H$1),0),$B54-1966)} -> 0.001 | I54: {=INDEX(GMWQ!$A$2:$NF$60,MATCH(1,(GMWQ!$NE$2:$NE$60=I$3)*(GMWQ!$NF$2:$NF$60=I$1),0),$B54-1966)} -> 98572.89 | J54: {=INDEX(GMWQ!$A$2:$NF$60,MATCH(1,(GMWQ!$NE$2:$NE$60=J$3)*(GMWQ!$NF$2:$NF$60=J$1),0),$B54-1966)} -> 12.19 | ... W54: {=INDEX(GMWQ!$A$2:$NF$60,MATCH(1,(GMWQ!$NE$2:$NE$60=W$3)*(GMWQ!$NF$2:$NF$60=W$1),0),$B54-1966)} -> 0.001
A55: 1985 | B55: =+B54+1 -> 2021 | C55: {=INDEX(GMWQ!$A$2:$NF$60,MATCH(1,(GMWQ!$NE$2:$NE$60=C$3)*(GMWQ!$NF$2:$NF$60=C$1),0),$B55-1966)} -> 7413 | D55: {=INDEX(GMWQ!$A$2:$NF$60,MATCH(1,(GMWQ!$NE$2:$NE$60=D$3)*(GMWQ!$NF$2:$NF$60=D$1),0),$B55-1966)} -> 0.001 | E55: {=INDEX(GMWQ!$A$2:$NF$60,MATCH(1,(GMWQ!$NE$2:$NE$60=E$3)*(GMWQ!$NF$2:$NF$60=E$1),0),$B55-1966)} -> 65471 | F55: {=INDEX(GMWQ!$A$2:$NF$60,MATCH(1,(GMWQ!$NE$2:$NE$60=F$3)*(GMWQ!$NF$2:$NF$60=F$1),0),$B55-1966)} -> 11.5 | G55: {=INDEX(GMWQ!$A$2:$NF$60,MATCH(1,(GMWQ!$NE$2:$NE$60=G$3)*(GMWQ!$NF$2:$NF$60=G$1),0),$B55-1966)} -> 156486.9 | H55: {=INDEX(GMWQ!$A$2:$NF$60,MATCH(1,(GMWQ!$NE$2:$NE$60=H$3)*(GMWQ!$NF$2:$NF$60=H$1),0),$B55-1966)} -> 0.001 | I55: {=INDEX(GMWQ!$A$2:$NF$60,MATCH(1,(GMWQ!$NE$2:$NE$60=I$3)*(GMWQ!$NF$2:$NF$60=I$1),0),$B55-1966)} -> 102043.7 | J55: {=INDEX(GMWQ!$A$2:$NF$60,MATCH(1,(GMWQ!$NE$2:$NE$60=J$3)*(GMWQ!$NF$2:$NF$60=J$1),0),$B55-1966)} -> 13.25 | ... W55: {=INDEX(GMWQ!$A$2:$NF$60,MATCH(1,(GMWQ!$NE$2:$NE$60=W$3)*(GMWQ!$NF$2:$NF$60=W$1),0),$B55-1966)} -> 0.001
B56: =+B55+1 -> 2022 | C56: {=INDEX(GMWQ!$A$2:$NF$60,MATCH(1,(GMWQ!$NE$2:$NE$60=C$3)*(GMWQ!$NF$2:$NF$60=C$1),0),$B56-1966)} -> 7513 | D56: {=INDEX(GMWQ!$A$2:$NF$60,MATCH(1,(GMWQ!$NE$2:$NE$60=D$3)*(GMWQ!$NF$2:$NF$60=D$1),0),$B56-1966)} -> 0.001 | E56: {=INDEX(GMWQ!$A$2:$NF$60,MATCH(1,(GMWQ!$NE$2:$NE$60=E$3)*(GMWQ!$NF$2:$NF$60=E$1),0),$B56-1966)} -> 66622 | F56: {=INDEX(GMWQ!$A$2:$NF$60,MATCH(1,(GMWQ!$NE$2:$NE$60=F$3)*(GMWQ!$NF$2:$NF$60=F$1),0),$B56-1966)} -> 11.4 | G56: {=INDEX(GMWQ!$A$2:$NF$60,MATCH(1,(GMWQ!$NE$2:$NE$60=G$3)*(GMWQ!$NF$2:$NF$60=G$1),0),$B56-1966)} -> 162450.5 | H56: {=INDEX(GMWQ!$A$2:$NF$60,MATCH(1,(GMWQ!$NE$2:$NE$60=H$3)*(GMWQ!$NF$2:$NF$60=H$1),0),$B56-1966)} -> 0.001 | I56: {=INDEX(GMWQ!$A$2:$NF$60,MATCH(1,(GMWQ!$NE$2:$NE$60=I$3)*(GMWQ!$NF$2:$NF$60=I$1),0),$B56-1966)} -> 106177 | J56: {=INDEX(GMWQ!$A$2:$NF$60,MATCH(1,(GMWQ!$NE$2:$NE$60=J$3)*(GMWQ!$NF$2:$NF$60=J$1),0),$B56-1966)} -> 14.26 | ... W56: {=INDEX(GMWQ!$A$2:$NF$60,MATCH(1,(GMWQ!$NE$2:$NE$60=W$3)*(GMWQ!$NF$2:$NF$60=W$1),0),$B56-1966)} -> 0.001
B57: =+B56+1 -> 2023 | C57: {=INDEX(GMWQ!$A$2:$NF$60,MATCH(1,(GMWQ!$NE$2:$NE$60=C$3)*(GMWQ!$NF$2:$NF$60=C$1),0),$B57-1966)} -> 7615 | D57: {=INDEX(GMWQ!$A$2:$NF$60,MATCH(1,(GMWQ!$NE$2:$NE$60=D$3)*(GMWQ!$NF$2:$NF$60=D$1),0),$B57-1966)} -> 0.001 | E57: {=INDEX(GMWQ!$A$2:$NF$60,MATCH(1,(GMWQ!$NE$2:$NE$60=E$3)*(GMWQ!$NF$2:$NF$60=E$1),0),$B57-1966)} -> 67715 | F57: {=INDEX(GMWQ!$A$2:$NF$60,MATCH(1,(GMWQ!$NE$2:$NE$60=F$3)*(GMWQ!$NF$2:$NF$60=F$1),0),$B57-1966)} -> 11.3 | G57: {=INDEX(GMWQ!$A$2:$NF$60,MATCH(1,(GMWQ!$NE$2:$NE$60=G$3)*(GMWQ!$NF$2:$NF$60=G$1),0),$B57-1966)} -> 169618.6 | H57: {=INDEX(GMWQ!$A$2:$NF$60,MATCH(1,(GMWQ!$NE$2:$NE$60=H$3)*(GMWQ!$NF$2:$NF$60=H$1),0),$B57-1966)} -> 0.001 | I57: {=INDEX(GMWQ!$A$2:$NF$60,MATCH(1,(GMWQ!$NE$2:$NE$60=I$3)*(GMWQ!$NF$2:$NF$60=I$1),0),$B57-1966)} -> 110989.1 | J57: {=INDEX(GMWQ!$A$2:$NF$60,MATCH(1,(GMWQ!$NE$2:$NE$60=J$3)*(GMWQ!$NF$2:$NF$60=J$1),0),$B57-1966)} -> 13.06 | ... W57: {=INDEX(GMWQ!$A$2:$NF$60,MATCH(1,(GMWQ!$NE$2:$NE$60=W$3)*(GMWQ!$NF$2:$NF$60=W$1),0),$B57-1966)} -> 0.001
B58: =+B57+1 -> 2024 | C58: {=INDEX(GMWQ!$A$2:$NF$60,MATCH(1,(GMWQ!$NE$2:$NE$60=C$3)*(GMWQ!$NF$2:$NF$60=C$1),0),$B58-1966)} -> 7717 | D58: {=INDEX(GMWQ!$A$2:$NF$60,MATCH(1,(GMWQ!$NE$2:$NE$60=D$3)*(GMWQ!$NF$2:$NF$60=D$1),0),$B58-1966)} -> 0.001 | E58: {=INDEX(GMWQ!$A$2:$NF$60,MATCH(1,(GMWQ!$NE$2:$NE$60=E$3)*(GMWQ!$NF$2:$NF$60=E$1),0),$B58-1966)} -> 69185 | F58: {=INDEX(GMWQ!$A$2:$NF$60,MATCH(1,(GMWQ!$NE$2:$NE$60=F$3)*(GMWQ!$NF$2:$NF$60=F$1),0),$B58-1966)} -> 11.3 | G58: {=INDEX(GMWQ!$A$2:$NF$60,MATCH(1,(GMWQ!$NE$2:$NE$60=G$3)*(GMWQ!$NF$2:$NF$60=G$1),0),$B58-1966)} -> 177527.2 | H58: {=INDEX(GMWQ!$A$2:$NF$60,MATCH(1,(GMWQ!$NE$2:$NE$60=H$3)*(GMWQ!$NF$2:$NF$60=H$1),0),$B58-1966)} -> 0.001 | I58: {=INDEX(GMWQ!$A$2:$NF$60,MATCH(1,(GMWQ!$NE$2:$NE$60=I$3)*(GMWQ!$NF$2:$NF$60=I$1),0),$B58-1966)} -> 115955.1 | J58: {=INDEX(GMWQ!$A$2:$NF$60,MATCH(1,(GMWQ!$NE$2:$NE$60=J$3)*(GMWQ!$NF$2:$NF$60=J$1),0),$B58-1966)} -> 13.01 | ... W58: {=INDEX(GMWQ!$A$2:$NF$60,MATCH(1,(GMWQ!$NE$2:$NE$60=W$3)*(GMWQ!$NF$2:$NF$60=W$1),0),$B58-1966)} -> 0.001
A59: 1986 | B59: =+B58+1 -> 2025 | C59: {=INDEX(GMWQ!$A$2:$NF$60,MATCH(1,(GMWQ!$NE$2:$NE$60=C$3)*(GMWQ!$NF$2:$NF$60=C$1),0),$B59-1966)} -> 7830.5 | D59: {=INDEX(GMWQ!$A$2:$NF$60,MATCH(1,(GMWQ!$NE$2:$NE$60=D$3)*(GMWQ!$NF$2:$NF$60=D$1),0),$B59-1966)} -> 0.001 | E59: {=INDEX(GMWQ!$A$2:$NF$60,MATCH(1,(GMWQ!$NE$2:$NE$60=E$3)*(GMWQ!$NF$2:$NF$60=E$1),0),$B59-1966)} -> 70501 | F59: {=INDEX(GMWQ!$A$2:$NF$60,MATCH(1,(GMWQ!$NE$2:$NE$60=F$3)*(GMWQ!$NF$2:$NF$60=F$1),0),$B59-1966)} -> 11.3 | G59: {=INDEX(GMWQ!$A$2:$NF$60,MATCH(1,(GMWQ!$NE$2:$NE$60=G$3)*(GMWQ!$NF$2:$NF$60=G$1),0),$B59-1966)} -> 183769.3 | H59: {=INDEX(GMWQ!$A$2:$NF$60,MATCH(1,(GMWQ!$NE$2:$NE$60=H$3)*(GMWQ!$NF$2:$NF$60=H$1),0),$B59-1966)} -> 0.001 | I59: {=INDEX(GMWQ!$A$2:$NF$60,MATCH(1,(GMWQ!$NE$2:$NE$60=I$3)*(GMWQ!$NF$2:$NF$60=I$1),0),$B59-1966)} -> 120178.5 | J59: {=INDEX(GMWQ!$A$2:$NF$60,MATCH(1,(GMWQ!$NE$2:$NE$60=J$3)*(GMWQ!$NF$2:$NF$60=J$1),0),$B59-1966)} -> 13 | ... W59: {=INDEX(GMWQ!$A$2:$NF$60,MATCH(1,(GMWQ!$NE$2:$NE$60=W$3)*(GMWQ!$NF$2:$NF$60=W$1),0),$B59-1966)} -> 0.001
B60: =+B59+1 -> 2026 | C60: {=INDEX(GMWQ!$A$2:$NF$60,MATCH(1,(GMWQ!$NE$2:$NE$60=C$3)*(GMWQ!$NF$2:$NF$60=C$1),0),$B60-1966)} -> 7944 | D60: {=INDEX(GMWQ!$A$2:$NF$60,MATCH(1,(GMWQ!$NE$2:$NE$60=D$3)*(GMWQ!$NF$2:$NF$60=D$1),0),$B60-1966)} -> 0.001 | E60: {=INDEX(GMWQ!$A$2:$NF$60,MATCH(1,(GMWQ!$NE$2:$NE$60=E$3)*(GMWQ!$NF$2:$NF$60=E$1),0),$B60-1966)} -> 73909 | F60: {=INDEX(GMWQ!$A$2:$NF$60,MATCH(1,(GMWQ!$NE$2:$NE$60=F$3)*(GMWQ!$NF$2:$NF$60=F$1),0),$B60-1966)} -> 11.3 | G60: {=INDEX(GMWQ!$A$2:$NF$60,MATCH(1,(GMWQ!$NE$2:$NE$60=G$3)*(GMWQ!$NF$2:$NF$60=G$1),0),$B60-1966)} -> 192567.8 | H60: {=INDEX(GMWQ!$A$2:$NF$60,MATCH(1,(GMWQ!$NE$2:$NE$60=H$3)*(GMWQ!$NF$2:$NF$60=H$1),0),$B60-1966)} -> 0.001 | I60: {=INDEX(GMWQ!$A$2:$NF$60,MATCH(1,(GMWQ!$NE$2:$NE$60=I$3)*(GMWQ!$NF$2:$NF$60=I$1),0),$B60-1966)} -> 126107.2 | J60: {=INDEX(GMWQ!$A$2:$NF$60,MATCH(1,(GMWQ!$NE$2:$NE$60=J$3)*(GMWQ!$NF$2:$NF$60=J$1),0),$B60-1966)} -> 11.06 | ... W60: {=INDEX(GMWQ!$A$2:$NF$60,MATCH(1,(GMWQ!$NE$2:$NE$60=W$3)*(GMWQ!$NF$2:$NF$60=W$1),0),$B60-1966)} -> 0.001
B61: =+B60+1 -> 2027 | C61: {=INDEX(GMWQ!$A$2:$NF$60,MATCH(1,(GMWQ!$NE$2:$NE$60=C$3)*(GMWQ!$NF$2:$NF$60=C$1),0),$B61-1966)} -> 8041 | D61: {=INDEX(GMWQ!$A$2:$NF$60,MATCH(1,(GMWQ!$NE$2:$NE$60=D$3)*(GMWQ!$NF$2:$NF$60=D$1),0),$B61-1966)} -> 0.001 | E61: {=INDEX(GMWQ!$A$2:$NF$60,MATCH(1,(GMWQ!$NE$2:$NE$60=E$3)*(GMWQ!$NF$2:$NF$60=E$1),0),$B61-1966)} -> 73297 | F61: {=INDEX(GMWQ!$A$2:$NF$60,MATCH(1,(GMWQ!$NE$2:$NE$60=F$3)*(GMWQ!$NF$2:$NF$60=F$1),0),$B61-1966)} -> 11.4 | G61: {=INDEX(GMWQ!$A$2:$NF$60,MATCH(1,(GMWQ!$NE$2:$NE$60=G$3)*(GMWQ!$NF$2:$NF$60=G$1),0),$B61-1966)} -> 200615.5 | H61: {=INDEX(GMWQ!$A$2:$NF$60,MATCH(1,(GMWQ!$NE$2:$NE$60=H$3)*(GMWQ!$NF$2:$NF$60=H$1),0),$B61-1966)} -> 0.001 | I61: {=INDEX(GMWQ!$A$2:$NF$60,MATCH(1,(GMWQ!$NE$2:$NE$60=I$3)*(GMWQ!$NF$2:$NF$60=I$1),0),$B61-1966)} -> 133482 | J61: {=INDEX(GMWQ!$A$2:$NF$60,MATCH(1,(GMWQ!$NE$2:$NE$60=J$3)*(GMWQ!$NF$2:$NF$60=J$1),0),$B61-1966)} -> 11.04 | ... W61: {=INDEX(GMWQ!$A$2:$NF$60,MATCH(1,(GMWQ!$NE$2:$NE$60=W$3)*(GMWQ!$NF$2:$NF$60=W$1),0),$B61-1966)} -> 0.001
B62: =+B61+1 -> 2028 | C62: {=INDEX(GMWQ!$A$2:$NF$60,MATCH(1,(GMWQ!$NE$2:$NE$60=C$3)*(GMWQ!$NF$2:$NF$60=C$1),0),$B62-1966)} -> 8138 | D62: {=INDEX(GMWQ!$A$2:$NF$60,MATCH(1,(GMWQ!$NE$2:$NE$60=D$3)*(GMWQ!$NF$2:$NF$60=D$1),0),$B62-1966)} -> 0.001 | E62: {=INDEX(GMWQ!$A$2:$NF$60,MATCH(1,(GMWQ!$NE$2:$NE$60=E$3)*(GMWQ!$NF$2:$NF$60=E$1),0),$B62-1966)} -> 74329 | F62: {=INDEX(GMWQ!$A$2:$NF$60,MATCH(1,(GMWQ!$NE$2:$NE$60=F$3)*(GMWQ!$NF$2:$NF$60=F$1),0),$B62-1966)} -> 11.3 | G62: {=INDEX(GMWQ!$A$2:$NF$60,MATCH(1,(GMWQ!$NE$2:$NE$60=G$3)*(GMWQ!$NF$2:$NF$60=G$1),0),$B62-1966)} -> 209439.8 | H62: {=INDEX(GMWQ!$A$2:$NF$60,MATCH(1,(GMWQ!$NE$2:$NE$60=H$3)*(GMWQ!$NF$2:$NF$60=H$1),0),$B62-1966)} -> 0.001 | I62: {=INDEX(GMWQ!$A$2:$NF$60,MATCH(1,(GMWQ!$NE$2:$NE$60=I$3)*(GMWQ!$NF$2:$NF$60=I$1),0),$B62-1966)} -> 140406.3 | J62: {=INDEX(GMWQ!$A$2:$NF$60,MATCH(1,(GMWQ!$NE$2:$NE$60=J$3)*(GMWQ!$NF$2:$NF$60=J$1),0),$B62-1966)} -> 12.32 | ... W62: {=INDEX(GMWQ!$A$2:$NF$60,MATCH(1,(GMWQ!$NE$2:$NE$60=W$3)*(GMWQ!$NF$2:$NF$60=W$1),0),$B62-1966)} -> 0.001
