Workbook
Name _DLX1.INC: HAVERM!$A$1:$G$6
Name _DLX2.INC: HAVERQ!$A$2:$CM$7
Name _DLX3.INC: HAVERA!$A$1:$E$6
Name Data: [1]sheet0!$C$2

Sheet CHARTS>>

Sheet DATA>>

Sheet Chart Data
A1: Labour income cont to PEDY! | F1: Labour income cont to PEDY | M1: Unit wage costs & profits | Q1: BoE DMP | Y1: NICs simulation | BC1: ASHE annual pay by sector | BK1: ASHE annual pay by sector | BR1: ASHE annual pay by sector | BY1: NICs & NLW calculation - FT workers | DQ1: NICs & NLW calculation - all workers | FI1: NICs timeseries | FJ1: NLW | FR1: Median | FZ1: Business surveys | GH1: MEAN | GI1: =AVERAGE(GL4:GL103) -> 18.023755 | GJ1: =AVERAGE(GM4:GM103) -> 7.3895901 | GR1: Company profits | GV1: Company profits | GZ1: Employment forecasts - ETILO | HK1: Employment forecasts - ET | HV1: CIPD - impact of employment allowance
R2: =RANK(R6,$R$6:$W$6) -> 4 | S2: =RANK(S6,$R$6:$W$6) -> 3 | T2: =RANK(T6,$R$6:$W$6) -> 2 | U2: =RANK(U6,$R$6:$W$6) -> 1 | V2: =RANK(V6,$R$6:$W$6) -> 5 | W2: =RANK(W6,$R$6:$W$6) -> 6 | Z2: Unemployment | AH2: Employment | AQ2: Earnings | AT2: Earnings | BZ2: Salary | CM2: Employers NICs | DA2: Salary + NICs | DN2: Employers NICs | DR2: Salary | EE2: Employers NICs | ES2: Salary + NICs | FF2: Employers NICs | FO2: Employers NICs | FW2: Employers NICs | GC2: Range of surveys (LHS) | GH2: STDEV | GI2: =STDEV(GL4:GL103) -> 10.904487 | GJ2: =STDEV(GM4:GM103) -> 16.407212 | GL2: Weighted averages
B3: Labour income | C3: Other | D3: Nominal household income | G3: Labour income | H3: Other | I3: Real household income | K3: PC | N3: Unit wage costs (LHS) | O3: Corporate profits (RHS) | R3: ='DMP - NICs Reaction'!B3 -> Lower employee wages | S3: ='DMP - NICs Reaction'!C3 -> Lower number of employees | T3: ='DMP - NICs Reaction'!D3 -> Higher prices | U3: ='DMP - NICs Reaction'!E3 -> Lower profit margins | V3: ='DMP - NICs Reaction'!F3 -> Other | W3: ='DMP - NICs Reaction'!G3 -> None of the above | Z3: Baseline | AA3: No NICs rise | AC3: 45566 | AD3: NICs scenario | AE3: Diff | AH3: Baseline | AI3: No NICs rise | AJ3: Diff | AL3: 45566 | AM3: NICs scenario | AN3: Diff | AQ3: Baseline | AR3: No NICs rise | AS3: Diff | AT3: Baseline | AU3: No NICs rise | AV3: Diff | AX3: 45566 | AY3: NICs scenario | AZ3: Diff | BC3: Sector | BD3: 10 | BE3: 25 | BF3: Median | BG3: 75 | BK3: Sector | BL3: 10 | BM3: 25 | BN3: Median | BO3: 75 | BR3: Sector | BS3: 10 | BT3: 25 | BU3: Median | BV3: 75 | BZ3: 10 | CA3: 20 | CB3: 30 | CC3: 40 | CD3: Median | CE3: 60 | CF3: 70 | CG3: 80 | CH3: 90 | CJ3: NLW | CK3: Mean | CM3: 10 | CN3: 20 | CO3: 30 | CP3: 40 | CQ3: Median | CR3: 60 | CS3: 70 | CT3: 80 | CU3: 90 | CW3: NLW | CX3: Mean | DA3: 10 | DB3: 20 | DC3: 30 | DD3: 40 | DE3: Median | DF3: 60 | DG3: 70 | DH3: 80 | DI3: 90 | DK3: NLW | DL3: Mean | DN3: Rate | DO3: Seconday threshold | DR3: 10 | DS3: 20 | DT3: 30 | DU3: 40 | DV3: Median | DW3: 60 | DX3: 70 | DY3: 80 | DZ3: 90 | EB3: NLW | EC3: Mean | EE3: 10 | EF3: 20 | EG3: 30 | EH3: 40 | EI3: Median | EJ3: 60 | EK3: 70 | EL3: 80 | EM3: 90 | EO3: NLW | EP3: Mean | ES3: 10 | ET3: 20 | EU3: 30 | EV3: 40 | EW3: Median | EX3: 60 | EY3: 70 | EZ3: 80 | FA3: 90 | FC3: NLW | FD3: Mean | FF3: Rate | FG3: Seconday threshold | FJ3: NLW | FK3: NICs payable | FL3: Total cost | FO3: Rate | FP3: Seconday threshold | FR3: Median | FS3: NICs payable | FT3: Total cost | FW3: Rate | FX3: Seconday threshold | GA3: ONS workforce jobs (LHS) | GB3: Min | GC3: Range of CBI & BCC surveys, advanced three months (RHS) | GD3: Average | GF3: Max | GI3: BCC | GJ3: CBI | GL3: BCC | GM3: CBI | GO3: BoE agents | GP3: BoE DMP | GS3: Corporate profits | GT3: Average 2020-2024 | GW3: Corporate profits (LHS) | GX3: Unit wage costs (RHS) | HA3: 45566 | HB3: 45689 | HC3: Difference | HE3: 45566 | HF3: 45689 | HH3: 45566 | HI3: 45689 | HL3: 45566 | HM3: 45689 | HN3: Difference | HP3: 45566 | HQ3: 45689 | HS3: 45566 | HT3: 45689 | HW3: All small firms (2-49 employees) | HX3: 2 to 9 employees | HY3: 10 to 49 employees
A4: 2014 | B4: =100*((DataA!G48-DataA!G47)/DataA!H47) -> 2.2545386 | C4: =D4-B4 -> 1.2449333 | D4: =100*((DataA!H48/DataA!H47)-1) -> 3.4994719 | F4: 2014 | G4: =B4-K4 -> 1.0973014 | H4: =I4-G4 -> 1.1592146 | I4: =100*((DataA!I48/DataA!I47)-1) -> 2.2565161 | K4: =100*((DataA!J48/DataA!J47)-1) -> 1.1572372 | M4: 2012 | N4: =100*((DataQ!F163/DataQ!F159)-1) -> -1.0460326 | O4: =100*(DataQ!I163/DataQ!J163) -> 21.990625 | Q4: ='DMP - NICs Reaction'!A4 -> 45597 | R4: ='DMP - NICs Reaction'!B4 -> 37.88 | S4: ='DMP - NICs Reaction'!C4 -> 53.68 | T4: ='DMP - NICs Reaction'!D4 -> 53.64 | U4: ='DMP - NICs Reaction'!E4 -> 58.72 | V4: ='DMP - NICs Reaction'!F4 -> 7.51 | W4: ='DMP - NICs Reaction'!G4 -> 2.67 | Y4: 44562 | Z4: =DataQ!Q203 -> 3.8 | AA4: =Z4 -> 3.8 | AC4: =DataQ!V203 -> 3.9 | AD4: =DataQ!AB203 -> 3.9 | AE4: =AD4-AC4 -> 0 | AG4: 44562 | AH4: =DataQ!O203 -> 32784 | AI4: =AH4 -> 32784 | AJ4: =AI4-AH4 -> 0 | AL4: =DataQ!T203 -> 32775 | AM4: =DataQ!Z203 -> 32775 | AN4: =AM4-AL4 -> 0 | AP4: 44562 | AQ4: =100*((DataQ!R203/DataQ!R199)-1) -> 5.98157 | AR4: =AQ4 -> 5.98157 | AS4: =AR4-AQ4 -> 0 | AT4: =DataQ!R203 -> 8707.29 | AU4: =AT4 -> 8707.29 | AV4: =AU4-AT4 -> 0 | AX4: =DataQ!U203 -> 8762.161 | AY4: =DataQ!AA203 -> 8762.161 | AZ4: =AY4-AX4 -> 0 | BB4: =RANK(BE4,$BE$4:$BE$22) -> 14 | BC4: Agriculture | BD4: ='ASHE Annual pay All SIC'!H26 -> 9753 | BE4: ='ASHE Annual pay All SIC'!J26 -> 18000 | BF4: ='ASHE Annual pay All SIC'!D26 -> 27288 | BG4: ='ASHE Annual pay All SIC'!O26 -> 36266 | BH4: 1.5 | BJ4: 1 | BK4: =VLOOKUP($BJ4,$BB$4:$BG$22,2,FALSE) -> Utilities | BL4: =VLOOKUP($BJ4,$BB$4:$BG$22,3,FALSE) -> 25643 | BM4: =VLOOKUP($BJ4,$BB$4:$BG$22,4,FALSE) -> 37550 | BN4: =VLOOKUP($BJ4,$BB$4:$BG$22,5,FALSE) -> 51886 | BO4: =VLOOKUP($BJ4,$BB$4:$BG$22,6,FALSE) -> 73580 | BP4: 1.5 | BR4: Agriculture | BS4: =BD4 -> 9753 | BT4: =BE4-BS4 -> 8247 | BU4: =BF4-BT4 -> 19041 | BV4: =BG4-BU4 -> 17225 | BW4: 0.5 | BY4: 2024-2025 | BZ4: ='ASHE Annual pay FT'!H6 -> 22763 | CA4: ='ASHE Annual pay FT'!I6 -> 26250 | CB4: ='ASHE Annual pay FT'!K6 -> 29731 | CC4: ='ASHE Annual pay FT'!L6 -> 33276 | CD4: ='ASHE Annual pay FT'!D6 -> 37430 | CE4: ='ASHE Annual pay FT'!M6 -> 42148 | CF4: ='ASHE Annual pay FT'!N6 -> 47898 | CG4: ='ASHE Annual pay FT'!O6 -> 51391 | CH4: ='ASHE Annual pay FT'!P6 -> 55912 | CJ4: =HAVERM!D549*$CJ$8*52 -> 20820.8 | CK4: ='ASHE Annual pay FT'!F6 -> 45836 | CM4: =(BZ4-$DO4)*$DN4 -> 1885.494 | CN4: =(CA4-$DO4)*$DN4 -> 2366.7 | CO4: =(CB4-$DO4)*$DN4 -> 2847.078 | CP4: =(CC4-$DO4)*$DN4 -> 3336.288 | CQ4: =(CD4-$DO4)*$DN4 -> 3909.54 | CR4: =(CE4-$DO4)*$DN4 -> 4560.624 | CS4: =(CF4-$DO4)*$DN4 -> 5354.124 | CT4: =(CG4-$DO4)*$DN4 -> 5836.158 | CU4: =(CH4-$DO4)*$DN4 -> 6460.056 | CW4: =(CJ4-$DO4)*$DN4 -> 1617.4704 | CX4: =(CK4-$DO4)*$DN4 -> 5069.568 | DA4: =BZ4+CM4 -> 24648.494 | DB4: =CA4+CN4 -> 28616.7 | DC4: =CB4+CO4 -> 32578.078 | DD4: =CC4+CP4 -> 36612.288 | DE4: =CD4+CQ4 -> 41339.54 | DF4: =CE4+CR4 -> 46708.624 | DG4: =CF4+CS4 -> 53252.124 | DH4: =CG4+CT4 -> 57227.158 | DI4: =CH4+CU4 -> 62372.056 | DK4: =CJ4+CW4 -> 22438.27 | DL4: =CK4+CX4 -> 50905.568 | DN4: 0.138 | DO4: 9100 | DQ4: 2024-2025 | DR4: ='ASHE Annual pay All SIC'!H6 -> 11004 | DS4: ='ASHE Annual pay All SIC'!I6 -> 17995 | DT4: ='ASHE Annual pay All SIC'!K6 -> 23541 | DU4: ='ASHE Annual pay All SIC'!L6 -> 27440 | DV4: ='ASHE Annual pay All SIC'!D6 -> 31602 | DW4: ='ASHE Annual pay All SIC'!M6 -> 36538 | DX4: ='ASHE Annual pay All SIC'!N6 -> 42519 | DY4: ='ASHE Annual pay All SIC'!P6 -> 50344 | DZ4: ='ASHE Annual pay All SIC'!Q6 -> 65227 | EB4: =HAVERM!D549*$EB$8*52 -> 20820.8 | EC4: ='ASHE Annual pay All SIC'!F6 -> 38224 | EE4: =(DR4-$FG4)*$FF4 -> 262.752 | EF4: =(DS4-$FG4)*$FF4 -> 1227.51 | EG4: =(DT4-$FG4)*$FF4 -> 1992.858 | EH4: =(DU4-$FG4)*$FF4 -> 2530.92 | EI4: =(DV4-$FG4)*$FF4 -> 3105.276 | EJ4: =(DW4-$FG4)*$FF4 -> 3786.444 | EK4: =(DX4-$FG4)*$FF4 -> 4611.822 | EL4: =(DY4-$FG4)*$FF4 -> 5691.672 | EM4: =(DZ4-$FG4)*$FF4 -> 7745.526 | EO4: =(EB4-$FG4)*$FF4 -> 1617.4704 | EP4: =(EC4-$FG4)*$FF4 -> 4019.112 | ES4: =DR4+EE4 -> 11266.752 | ET4: =DS4+EF4 -> 19222.51 | EU4: =DT4+EG4 -> 25533.858 | EV4: =DU4+EH4 -> 29970.92 | EW4: =DV4+EI4 -> 34707.276 | EX4: =DW4+EJ4 -> 40324.444 | EY4: =DX4+EK4 -> 47130.822 | EZ4: =DY4+EL4 -> 56035.672 | FA4: =DZ4+EM4 -> 72972.526 | FC4: =EB4+EO4 -> 22438.27 | FD4: =EC4+EP4 -> 42243.112 | FF4: 0.138 | FG4: 9100 | FI4: FY19 | FJ4: =HAVERM!D478*35*52 -> 14942.2 | FK4: =(FJ4-$FP4)*$FO4 -> 870.8076 | FL4: =+FK4+FJ4 -> 15813.008 | FO4: 0.138 | FP4: 8632 | FR4: =HAVERA!B26 -> 30378 | FS4: =(FR4-$FX4)*$FW4 -> 3000.948 | FT4: =+FS4+FR4 -> 33378.948 | FW4: 0.138 | FX4: 8632 | FZ4: 36526 | GA4: =100*((HAVERQ!S88/HAVERQ!S84)-1) -> 1.3920717 | GB4: =MIN(GI3:GJ3) -> 0 | GC4: =+GF4-GB4 -> 0 | GD4: =AVERAGE(GB4,GF4) -> 0 | GF4: =MAX(GI3:GJ3) -> 0 | GH4: 36526 | GI4: =(GL4-GI$1)/GI$2 -> 0.66633495 | GJ4: =(GM4-GJ$1)/GJ$2 -> 1.0550526 | GL4: =(HAVERQ!BJ88*HAVERQ!$BJ$1)+(HAVERQ!BK88*HAVERQ!$BK$1) -> 25.289796 | GM4: =(HAVERQ!BL88*HAVERQ!$BL$1)+(HAVERQ!BM88*HAVERQ!$BM$1)+(HAVERQ!BN88*HAVERQ!$BN$1)+(HAVERQ!BO88*HAVERQ!$BO$1) -> 24.700061 | GR4: 36526 | GS4: =100*(HAVERQ!BP88/HAVERQ!BR88) -> 25.409106 | GT4: =AVERAGE($GS$4:$GS$103) -> 24.605137 | GV4: 36526 | GW4: =100*(HAVERQ!BP88/HAVERQ!BR88) -> 25.409106 | GX4: =100*((DataQ!F119/DataQ!F115)-1) -> 6.6139866 | GZ4: 44927 | HA4: =HH4-HH$11 -> 44.09 | HB4: =HI4-HI$11 -> -455.7 | HC4: =HB4-HA4 -> -499.79 | HE4: =100*(HH4/$HH$11) -> 100.13297 | HF4: =100*(HI4/$HI$11) -> 98.650805 | HH4: =DataQ!AE207 -> 33201 | HI4: =DataQ!O207 -> 33320 | HK4: 44927 | HL4: =HS4-HS$11 -> -366.92 | HM4: =HT4-HT$11 -> -393.34 | HN4: =HM4-HL4 -> -26.42 | HP4: =100*(HS4/HS$11) -> 99.010942 | HQ4: =100*(HT4/HT$11) -> 98.934914 | HS4: =DataQ!AF207 -> 36731 | HT4: =DataQ!P207 -> 36537 | HV4: Lower to a large extent | HW4: 5 | HX4: 5 | HY4: 5
A5: 2015 | B5: =100*((DataA!G49-DataA!G48)/DataA!H48) -> 2.0418208 | C5: =D5-B5 -> 3.649196 | D5: =100*((DataA!H49/DataA!H48)-1) -> 5.6910168 | F5: 2015 | G5: =B5-K5 -> 2.4131255 | H5: =I5-G5 -> 3.6485662 | I5: =100*((DataA!I49/DataA!I48)-1) -> 6.0616917 | K5: =100*((DataA!J49/DataA!J48)-1) -> -0.37130467 | N5: =100*((DataQ!F164/DataQ!F160)-1) -> 0.71283454 | O5: =100*(DataQ!I164/DataQ!J164) -> 21.877964 | Q5: ='DMP - NICs Reaction'!A5 -> 45627 | R5: ='DMP - NICs Reaction'!B5 -> 40.67 | S5: ='DMP - NICs Reaction'!C5 -> 52.76 | T5: ='DMP - NICs Reaction'!D5 -> 54.45 | U5: ='DMP - NICs Reaction'!E5 -> 63.5 | V5: ='DMP - NICs Reaction'!F5 -> 7.33 | W5: ='DMP - NICs Reaction'!G5 -> 3.75 | Y5: 44652 | Z5: =DataQ!Q204 -> 3.8 | AA5: =Z5 -> 3.8 | AC5: =DataQ!V204 -> 3.9 | AD5: =DataQ!AB204 -> 3.9 | AE5: =AD5-AC5 -> 0 | AG5: 44652 | AH5: =DataQ!O204 -> 33007 | AI5: =AH5 -> 33007 | AJ5: =AI5-AH5 -> 0 | AL5: =DataQ!T204 -> 32958 | AM5: =DataQ!Z204 -> 32958 | AN5: =AM5-AL5 -> 0 | AP5: 44652 | AQ5: =100*((DataQ!R204/DataQ!R200)-1) -> 3.9892354 | AR5: =AQ5 -> 3.9892354 | AS5: =AR5-AQ5 -> 0 | AT5: =DataQ!R204 -> 8783.535 | AU5: =AT5 -> 8783.535 | AV5: =AU5-AT5 -> 0 | AX5: =DataQ!U204 -> 8858.754 | AY5: =DataQ!AA204 -> 8858.754 | AZ5: =AY5-AX5 -> 0 | BB5: =RANK(BE5,$BE$4:$BE$22) -> 2 | BC5: Extraction | BD5: ='ASHE Annual pay All SIC'!H30 -> 25213 | BE5: ='ASHE Annual pay All SIC'!J30 -> 33999 | BF5: ='ASHE Annual pay All SIC'!D30 -> 47022 | BG5: ='ASHE Annual pay All SIC'!O30 -> 64863 | BH5: =+BH4+1 -> 2.5 | BJ5: 2 | BK5: =VLOOKUP($BJ5,$BB$4:$BG$22,2,FALSE) -> Extraction | BL5: =VLOOKUP($BJ5,$BB$4:$BG$22,3,FALSE) -> 25213 | BM5: =VLOOKUP($BJ5,$BB$4:$BG$22,4,FALSE) -> 33999 | BN5: =VLOOKUP($BJ5,$BB$4:$BG$22,5,FALSE) -> 47022 | BO5: =VLOOKUP($BJ5,$BB$4:$BG$22,6,FALSE) -> 64863 | BP5: =+BP4+1 -> 2.5 | BR5: Extraction | BS5: =BD5 -> 25213 | BT5: =BE5-BS5 -> 8786 | BU5: =BF5-BT5 -> 38236 | BV5: =BG5-BU5 -> 26627 | BW5: =+BW4+1 -> 1.5 | BY5: 2025-2026 | BZ5: =BZ4*DataQ!$H$216/DataQ!$H$212 -> 23926.006 | CA5: =CA4*DataQ!$H$216/DataQ!$H$212 -> 27591.164 | CB5: =CB4*DataQ!$H$216/DataQ!$H$212 -> 31250.015 | CC5: =CC4*DataQ!$H$216/DataQ!$H$212 -> 34976.136 | CD5: =CD4*DataQ!$H$216/DataQ!$H$212 -> 39342.372 | CE5: =CE4*DataQ!$H$216/DataQ!$H$212 -> 44301.424 | CF5: =CF4*DataQ!$H$216/DataQ!$H$212 -> 50345.202 | CG5: =CG4*DataQ!$H$216/DataQ!$H$212 -> 54016.667 | CH5: =CH4*DataQ!$H$216/DataQ!$H$212 -> 58768.653 | CJ5: =HAVERM!D550*$CJ$8*52 -> 22222.2 | CK5: =CK4*DataQ!$H$216/DataQ!$H$212 -> 48177.851 | CM5: =(BZ5-$DO5)*$DN5 -> 2838.9009 | CN5: =(CA5-$DO5)*$DN5 -> 3388.6746 | CO5: =(CB5-$DO5)*$DN5 -> 3937.5022 | CP5: =(CC5-$DO5)*$DN5 -> 4496.4204 | CQ5: =(CD5-$DO5)*$DN5 -> 5151.3558 | CR5: =(CE5-$DO5)*$DN5 -> 5895.2135 | CS5: =(CF5-$DO5)*$DN5 -> 6801.7803 | CT5: =(CG5-$DO5)*$DN5 -> 7352.5 | CU5: =(CH5-$DO5)*$DN5 -> 8065.298 | CW5: =(CJ5-$DO5)*$DN5 -> 2583.33 | CX5: =(CK5-$DO5)*$DN5 -> 6476.6776 | DA5: =BZ5+CM5 -> 26764.907 | DB5: =CA5+CN5 -> 30979.838 | DC5: =CB5+CO5 -> 35187.517 | DD5: =CC5+CP5 -> 39472.556 | DE5: =CD5+CQ5 -> 44493.728 | DF5: =CE5+CR5 -> 50196.637 | DG5: =CF5+CS5 -> 57146.983 | DH5: =CG5+CT5 -> 61369.166 | DI5: =CH5+CU5 -> 66833.951 | DK5: =CJ5+CW5 -> 24805.53 | DL5: =CK5+CX5 -> 54654.528 | DN5: 0.15 | DO5: 5000 | DQ5: 2025-2026 | DR5: =DR4*EB5/EB4 -> 11744.654 | DS5: =DS4*DR5/DR4 -> 19206.202 | DT5: =DT4*DataQ!$H$216/DataQ!$H$212 -> 24743.756 | DU5: =DU4*DataQ!$H$216/DataQ!$H$212 -> 28841.963 | DV5: =DV4*DataQ!$H$216/DataQ!$H$212 -> 33216.608 | DW5: =DW4*DataQ!$H$216/DataQ!$H$212 -> 38404.798 | DX5: =DX4*DataQ!$H$216/DataQ!$H$212 -> 44691.379 | DY5: =DY4*DataQ!$H$216/DataQ!$H$212 -> 52916.173 | DZ5: =DZ4*DataQ!$H$216/DataQ!$H$212 -> 68559.575 | EB5: =HAVERM!D550*$EB$8*52 -> 22222.2 | EC5: =EC4*DataQ!$H$216/DataQ!$H$212 -> 40176.939 | EE5: =(DR5-$FG5)*$FF5 -> 1011.6981 | EF5: =(DS5-$FG5)*$FF5 -> 2130.9303 | EG5: =(DT5-$FG5)*$FF5 -> 2961.5633 | EH5: =(DU5-$FG5)*$FF5 -> 3576.2945 | EI5: =(DV5-$FG5)*$FF5 -> 4232.4912 | EJ5: =(DW5-$FG5)*$FF5 -> 5010.7197 | EK5: =(DX5-$FG5)*$FF5 -> 5953.7068 | EL5: =(DY5-$FG5)*$FF5 -> 7187.426 | EM5: =(DZ5-$FG5)*$FF5 -> 9533.9362 | EO5: =(EB5-$FG5)*$FF5 -> 2583.33 | EP5: =(EC5-$FG5)*$FF5 -> 5276.5408 | ES5: =DR5+EE5 -> 12756.352 | ET5: =DS5+EF5 -> 21337.132 | EU5: =DT5+EG5 -> 27705.319 | EV5: =DU5+EH5 -> 32418.258 | EW5: =DV5+EI5 -> 37449.099 | EX5: =DW5+EJ5 -> 43415.517 | EY5: =DX5+EK5 -> 50645.086 | EZ5: =DY5+EL5 -> 60103.599 | FA5: =DZ5+EM5 -> 78093.511 | FC5: =EB5+EO5 -> 24805.53 | FD5: =EC5+EP5 -> 45453.48 | FF5: 0.15 | FG5: 5000 | FI5: FY20 | FJ5: =HAVERM!D490*35*52 -> 15870.4 | FK5: =(FJ5-$FP5)*$FO5 -> 977.3712 | FL5: =+FK5+FJ5 -> 16847.771 | FM5: =100*((FL5/FL4)-1) -> 6.5437495 | FO5: 0.138 | FP5: 8788 | FR5: =HAVERA!B27 -> 31487 | FS5: =(FR5-$FX5)*$FW5 -> 3132.462 | FT5: =+FS5+FR5 -> 34619.462 | FU5: =100*((FT5/FT4)-1) -> 3.7164563 | FW5: 0.138 | FX5: 8788 | FZ5: 36617 | GA5: =100*((HAVERQ!S89/HAVERQ!S85)-1) -> 1.5276026 | GB5: =MIN(GI4:GJ4) -> 0.66633495 | GC5: =+GF5-GB5 -> 0.38871763 | GD5: =AVERAGE(GB5,GF5) -> 0.86069377 | GF5: =MAX(GI4:GJ4) -> 1.0550526 | GH5: 36617 | GI5: =(GL5-GI$1)/GI$2 -> 1.0688007 | GJ5: =(GM5-GJ$1)/GJ$2 -> 1.1152209 | GL5: =(HAVERQ!BJ89*HAVERQ!$BJ$1)+(HAVERQ!BK89*HAVERQ!$BK$1) -> 29.678479 | GM5: =(HAVERQ!BL89*HAVERQ!$BL$1)+(HAVERQ!BM89*HAVERQ!$BM$1)+(HAVERQ!BN89*HAVERQ!$BN$1)+(HAVERQ!BO89*HAVERQ!$BO$1) -> 25.687255 | GR5: 36617 | GS5: =100*(HAVERQ!BP89/HAVERQ!BR89) -> 24.420992 | GT5: =AVERAGE($GS$4:$GS$103) -> 24.605137 | GV5: 36617 | GW5: =100*(HAVERQ!BP89/HAVERQ!BR89) -> 24.420992 | GX5: =100*((DataQ!F120/DataQ!F116)-1) -> 4.3324967 | GZ5: 45017 | HA5: =HH5-HH$11 -> 6.09 | HB5: =HI5-HI$11 -> -419.7 | HC5: =HB5-HA5 -> -425.79 | HE5: =100*(HH5/$HH$11) -> 100.01837 | HF5: =100*(HI5/$HI$11) -> 98.757391 | HH5: =DataQ!AE208 -> 33163 | HI5: =DataQ!O208 -> 33356 | HK5: 45017 | HL5: =HS5-HS$11 -> -511.92 | HM5: =HT5-HT$11 -> -626.34 | HN5: =HM5-HL5 -> -114.42 | HP5: =100*(HS5/HS$11) -> 98.620084 | HQ5: =100*(HT5/HT$11) -> 98.303996 | HS5: =DataQ!AF208 -> 36586 | HT5: =DataQ!P208 -> 36304 | HV5: Lower to some extent | HW5: 23 | HX5: 18.33 | HY5: 27
A6: 2016 | B6: =100*((DataA!G50-DataA!G49)/DataA!H49) -> 2.0449227 | C6: =D6-B6 -> -0.089021233 | D6: =100*((DataA!H50/DataA!H49)-1) -> 1.9559014 | F6: 2016 | G6: =B6-K6 -> 0.77782891 | H6: =I6-G6 -> -0.083554616 | I6: =100*((DataA!I50/DataA!I49)-1) -> 0.6942743 | K6: =100*((DataA!J50/DataA!J49)-1) -> 1.2670938 | N6: =100*((DataQ!F165/DataQ!F161)-1) -> 0.63328293 | O6: =100*(DataQ!I165/DataQ!J165) -> 22.746912 | Q6: ='DMP - NICs Reaction'!A6 -> 45658 | R6: ='DMP - NICs Reaction'!B6 -> 36.63 | S6: ='DMP - NICs Reaction'!C6 -> 53.63 | T6: ='DMP - NICs Reaction'!D6 -> 61.1 | U6: ='DMP - NICs Reaction'!E6 -> 63.46 | V6: ='DMP - NICs Reaction'!F6 -> 11.88 | W6: ='DMP - NICs Reaction'!G6 -> 2.94 | Y6: 44743 | Z6: =DataQ!Q205 -> 3.7 | AA6: =Z6 -> 3.7 | AC6: =DataQ!V205 -> 3.8 | AD6: =DataQ!AB205 -> 3.8 | AE6: =AD6-AC6 -> 0 | AG6: 44743 | AH6: =DataQ!O205 -> 32904 | AI6: =AH6 -> 32904 | AJ6: =AI6-AH6 -> 0 | AL6: =DataQ!T205 -> 32916 | AM6: =DataQ!Z205 -> 32916 | AN6: =AM6-AL6 -> 0 | AP6: 44743 | AQ6: =100*((DataQ!R205/DataQ!R201)-1) -> 6.1822603 | AR6: =AQ6 -> 6.1822603 | AS6: =AR6-AQ6 -> 0 | AT6: =DataQ!R205 -> 8975.527 | AU6: =AT6 -> 8975.527 | AV6: =AU6-AT6 -> 0 | AX6: =DataQ!U205 -> 8972.382 | AY6: =DataQ!AA205 -> 8972.382 | AZ6: =AY6-AX6 -> 0 | BB6: =RANK(BE6,$BE$4:$BE$22) -> 8 | BC6: Manufacturing | BD6: ='ASHE Annual pay All SIC'!H36 -> 21424 | BE6: ='ASHE Annual pay All SIC'!J36 -> 26686 | BF6: ='ASHE Annual pay All SIC'!D36 -> 35518 | BG6: ='ASHE Annual pay All SIC'!O36 -> 49243 | BH6: =+BH5+1 -> 3.5 | BJ6: 3 | BK6: =VLOOKUP($BJ6,$BB$4:$BG$22,2,FALSE) -> Communications | BL6: =VLOOKUP($BJ6,$BB$4:$BG$22,3,FALSE) -> 23599 | BM6: =VLOOKUP($BJ6,$BB$4:$BG$22,4,FALSE) -> 32656 | BN6: =VLOOKUP($BJ6,$BB$4:$BG$22,5,FALSE) -> 46063 | BO6: =VLOOKUP($BJ6,$BB$4:$BG$22,6,FALSE) -> 68998 | BP6: =+BP5+1 -> 3.5 | BR6: Manufacturing | BS6: =BD6 -> 21424 | BT6: =BE6-BS6 -> 5262 | BU6: =BF6-BT6 -> 30256 | BV6: =BG6-BU6 -> 18987 | BW6: =+BW5+1 -> 2.5 | BZ6: =100*((BZ5/BZ4)-1) -> 5.1091952 | CA6: =100*((CA5/CA4)-1) -> 5.1091952 | CB6: =100*((CB5/CB4)-1) -> 5.1091952 | CC6: =100*((CC5/CC4)-1) -> 5.1091952 | CD6: =100*((CD5/CD4)-1) -> 5.1091952 | CE6: =100*((CE5/CE4)-1) -> 5.1091952 | CF6: =100*((CF5/CF4)-1) -> 5.1091952 | CG6: =100*((CG5/CG4)-1) -> 5.1091952 | CH6: =100*((CH5/CH4)-1) -> 5.1091952 | CJ6: =100*((CJ5/CJ4)-1) -> 6.7307692 | CK6: =100*((CK5/CK4)-1) -> 5.1091952 | DR6: =100*((DR5/DR4)-1) -> 6.7307692 | DS6: =100*((DS5/DS4)-1) -> 6.7307692 | DT6: =100*((DT5/DT4)-1) -> 5.1091952 | DU6: =100*((DU5/DU4)-1) -> 5.1091952 | DV6: =100*((DV5/DV4)-1) -> 5.1091952 | DW6: =100*((DW5/DW4)-1) -> 5.1091952 | DX6: =100*((DX5/DX4)-1) -> 5.1091952 | DY6: =100*((DY5/DY4)-1) -> 5.1091952 | DZ6: =100*((DZ5/DZ4)-1) -> 5.1091952 | EB6: =100*((EB5/EB4)-1) -> 6.7307692 | EC6: =100*((EC5/EC4)-1) -> 5.1091952 | FI6: FY21 | FJ6: =HAVERM!D502*35*52 -> 16216.2 | FK6: =(FJ6-$FP6)*$FO6 -> 1017.9156 | FL6: =+FK6+FJ6 -> 17234.116 | FM6: =100*((FL6/FL5)-1) -> 2.2931484 | FO6: 0.138 | FP6: 8840 | FR6: =HAVERA!B28 -> 31285 | FS6: =(FR6-$FX6)*$FW6 -> 3097.41 | FT6: =+FS6+FR6 -> 34382.41 | FU6: =100*((FT6/FT5)-1) -> -0.68473623 | FW6: 0.138 | FX6: 8840 | FZ6: 36708 | GA6: =100*((HAVERQ!S90/HAVERQ!S86)-1) -> 1.2608167 | GB6: =MIN(GI5:GJ5) -> 1.0688007 | GC6: =+GF6-GB6 -> 0.046420155 | GD6: =AVERAGE(GB6,GF6) -> 1.0920108 | GF6: =MAX(GI5:GJ5) -> 1.1152209 | GH6: 36708 | GI6: =(GL6-GI$1)/GI$2 -> 0.77942689 | GJ6: =(GM6-GJ$1)/GJ$2 -> 1.0055043 | GL6: =(HAVERQ!BJ90*HAVERQ!$BJ$1)+(HAVERQ!BK90*HAVERQ!$BK$1) -> 26.523006 | GM6: =(HAVERQ!BL90*HAVERQ!$BL$1)+(HAVERQ!BM90*HAVERQ!$BM$1)+(HAVERQ!BN90*HAVERQ!$BN$1)+(HAVERQ!BO90*HAVERQ!$BO$1) -> 23.887112 | GR6: 36708 | GS6: =100*(HAVERQ!BP90/HAVERQ!BR90) -> 23.762266 | GT6: =AVERAGE($GS$4:$GS$103) -> 24.605137 | GV6: 36708 | GW6: =100*(HAVERQ!BP90/HAVERQ!BR90) -> 23.762266 | GX6: =100*((DataQ!F121/DataQ!F117)-1) -> 2.8586523 | GZ6: 45108 | HA6: =HH6-HH$11 -> -54.91 | HB6: =HI6-HI$11 -> -449.7 | HC6: =HB6-HA6 -> -394.79 | HE6: =100*(HH6/$HH$11) -> 99.834393 | HF6: =100*(HI6/$HI$11) -> 98.668569 | HH6: =DataQ!AE209 -> 33102 | HI6: =DataQ!O209 -> 33326 | HK6: 45108 | HL6: =HS6-HS$11 -> -312.92 | HM6: =HT6-HT$11 -> -501.34 | HN6: =HM6-HL6 -> -188.42 | HP6: =100*(HS6/HS$11) -> 99.156503 | HQ6: =100*(HT6/HT$11) -> 98.642471 | HS6: =DataQ!AF209 -> 36785 | HT6: =DataQ!P209 -> 36429 | HV6: Lower to a small extent | HW6: 24 | HX6: 25.33 | HY6: 23
A7: 2017 | B7: =100*((DataA!G51-DataA!G50)/DataA!H50) -> 2.4443958 | C7: =D7-B7 -> 0.27841176 | D7: =100*((DataA!H51/DataA!H50)-1) -> 2.7228076 | F7: 2017 | G7: =B7-K7 -> 0.59145313 | H7: =I7-G7 -> 0.29775587 | I7: =100*((DataA!I51/DataA!I50)-1) -> 0.889209 | K7: =100*((DataA!J51/DataA!J50)-1) -> 1.8529427 | N7: =100*((DataQ!F166/DataQ!F162)-1) -> 1.2250741 | O7: =100*(DataQ!I166/DataQ!J166) -> 22.658746 | Y7: 44835 | Z7: =DataQ!Q206 -> 3.9 | AA7: =Z7 -> 3.9 | AC7: =DataQ!V206 -> 3.9 | AD7: =DataQ!AB206 -> 3.9 | AE7: =AD7-AC7 -> 0 | AG7: 44835 | AH7: =DataQ!O206 -> 33114 | AI7: =AH7 -> 33114 | AJ7: =AI7-AH7 -> 0 | AL7: =DataQ!T206 -> 33067 | AM7: =DataQ!Z206 -> 33067 | AN7: =AM7-AL7 -> 0 | AP7: 44835 | AQ7: =100*((DataQ!R206/DataQ!R202)-1) -> 7.6937643 | AR7: =AQ7 -> 7.6937643 | AS7: =AR7-AQ7 -> 0 | AT7: =DataQ!R206 -> 9173.315 | AU7: =AT7 -> 9173.315 | AV7: =AU7-AT7 -> 0 | AX7: =DataQ!U206 -> 9187.092 | AY7: =DataQ!AA206 -> 9187.092 | AZ7: =AY7-AX7 -> 0 | BB7: =RANK(BE7,$BE$4:$BE$22) -> 1 | BC7: Utilities | BD7: ='ASHE Annual pay All SIC'!H61 -> 25643 | BE7: ='ASHE Annual pay All SIC'!J61 -> 37550 | BF7: ='ASHE Annual pay All SIC'!D61 -> 51886 | BG7: ='ASHE Annual pay All SIC'!O61 -> 73580 | BH7: =+BH6+1 -> 4.5 | BJ7: 4 | BK7: =VLOOKUP($BJ7,$BB$4:$BG$22,2,FALSE) -> Financial services | BL7: =VLOOKUP($BJ7,$BB$4:$BG$22,3,FALSE) -> 21567 | BM7: =VLOOKUP($BJ7,$BB$4:$BG$22,4,FALSE) -> 29873 | BN7: =VLOOKUP($BJ7,$BB$4:$BG$22,5,FALSE) -> 47248 | BO7: =VLOOKUP($BJ7,$BB$4:$BG$22,6,FALSE) -> 78520 | BP7: =+BP6+1 -> 4.5 | BR7: Utilities | BS7: =BD7 -> 25643 | BT7: =BE7-BS7 -> 11907 | BU7: =BF7-BT7 -> 39979 | BV7: =BG7-BU7 -> 33601 | BW7: =+BW6+1 -> 3.5 | DA7: =DA4/1000 -> 24.648494 | DB7: =DB4/1000 -> 28.6167 | DC7: =DC4/1000 -> 32.578078 | DD7: =DD4/1000 -> 36.612288 | DE7: =DE4/1000 -> 41.33954 | DF7: =DF4/1000 -> 46.708624 | DG7: =DG4/1000 -> 53.252124 | DH7: =DH4/1000 -> 57.227158 | DI7: =DI4/1000 -> 62.372056 | DK7: =DK4/1000 -> 22.43827 | DL7: =DL4/1000 -> 50.905568 | ES7: =ES4/1000 -> 11.266752 | ET7: =ET4/1000 -> 19.22251 | EU7: =EU4/1000 -> 25.533858 | EV7: =EV4/1000 -> 29.97092 | EW7: =EW4/1000 -> 34.707276 | EX7: =EX4/1000 -> 40.324444 | EY7: =EY4/1000 -> 47.130822 | EZ7: =EZ4/1000 -> 56.035672 | FA7: =FA4/1000 -> 72.972526 | FC7: =FC4/1000 -> 22.43827 | FD7: =FD4/1000 -> 42.243112 | FI7: FY22 | FJ7: =HAVERM!D514*35*52 -> 17290 | FK7: =(FJ7-$FP7)*$FO7 -> 1181.4075 | FL7: =+FK7+FJ7 -> 18471.408 | FM7: =100*((FL7/FL6)-1) -> 7.1793176 | FO7: =AVERAGE(0.1505,0.138) -> 0.14425 | FP7: 9100 | FR7: =HAVERA!B29 -> 33061 | FS7: =(FR7-$FX7)*$FW7 -> 3456.3742 | FT7: =+FS7+FR7 -> 36517.374 | FU7: =100*((FT7/FT6)-1) -> 6.2094666 | FW7: =AVERAGE(0.1505,0.138) -> 0.14425 | FX7: 9100 | FZ7: 36800 | GA7: =100*((HAVERQ!S91/HAVERQ!S87)-1) -> 0.9994952 | GB7: =MIN(GI6:GJ6) -> 0.77942689 | GC7: =+GF7-GB7 -> 0.22607741 | GD7: =AVERAGE(GB7,GF7) -> 0.8924656 | GF7: =MAX(GI6:GJ6) -> 1.0055043 | GH7: 36800 | GI7: =(GL7-GI$1)/GI$2 -> 0.40547657 | GJ7: =(GM7-GJ$1)/GJ$2 -> 0.83773775 | GL7: =(HAVERQ!BJ91*HAVERQ!$BJ$1)+(HAVERQ!BK91*HAVERQ!$BK$1) -> 22.445269 | GM7: =(HAVERQ!BL91*HAVERQ!$BL$1)+(HAVERQ!BM91*HAVERQ!$BM$1)+(HAVERQ!BN91*HAVERQ!$BN$1)+(HAVERQ!BO91*HAVERQ!$BO$1) -> 21.134531 | GR7: 36800 | GS7: =100*(HAVERQ!BP91/HAVERQ!BR91) -> 22.877807 | GT7: =AVERAGE($GS$4:$GS$103) -> 24.605137 | GV7: 36800 | GW7: =100*(HAVERQ!BP91/HAVERQ!BR91) -> 22.877807 | GX7: =100*((DataQ!F122/DataQ!F118)-1) -> 1.4319515 | GZ7: 45200 | HA7: =HH7-HH$11 -> 17.09 | HB7: =HI7-HI$11 -> -398.7 | HC7: =HB7-HA7 -> -415.79 | HE7: =100*(HH7/$HH$11) -> 100.05154 | HF7: =100*(HI7/$HI$11) -> 98.819566 | HH7: =DataQ!AE210 -> 33174 | HI7: =DataQ!O210 -> 33377 | HK7: 45200 | HL7: =HS7-HS$11 -> -233.92 | HM7: =HT7-HT$11 -> -424.34 | HN7: =HM7-HL7 -> -190.42 | HP7: =100*(HS7/HS$11) -> 99.369453 | HQ7: =100*(HT7/HT$11) -> 98.850972 | HS7: =DataQ!AF210 -> 36864 | HT7: =DataQ!P210 -> 36506 | HV7: Not lower at all | HW7: 29 | HX7: 33.34 | HY7: 24
A8: 2018 | B8: =100*((DataA!G52-DataA!G51)/DataA!H51) -> 2.6151515 | C8: =D8-B8 -> 1.494945 | D8: =100*((DataA!H52/DataA!H51)-1) -> 4.1100965 | F8: 2018 | G8: =B8-K8 -> 0.51580887 | H8: =I8-G8 -> 1.4675349 | I8: =100*((DataA!I52/DataA!I51)-1) -> 1.9833437 | K8: =100*((DataA!J52/DataA!J51)-1) -> 2.0993427 | M8: 2013 | N8: =100*((DataQ!F167/DataQ!F163)-1) -> 0.66949357 | O8: =100*(DataQ!I167/DataQ!J167) -> 22.990853 | R8: 1 | S8: 2 | T8: 3 | U8: 4 | V8: 5 | W8: 6 | Y8: 44927 | Z8: =DataQ!Q207 -> 4 | AA8: =Z8 -> 4 | AC8: =DataQ!V207 -> 4 | AD8: =DataQ!AB207 -> 4 | AE8: =AD8-AC8 -> 0 | AG8: 44927 | AH8: =DataQ!O207 -> 33320 | AI8: =AH8 -> 33320 | AJ8: =AI8-AH8 -> 0 | AL8: =DataQ!T207 -> 33201 | AM8: =DataQ!Z207 -> 33201 | AN8: =AM8-AL8 -> 0 | AP8: 44927 | AQ8: =100*((DataQ!R207/DataQ!R203)-1) -> 7.9306076 | AR8: =AQ8 -> 7.9306076 | AS8: =AR8-AQ8 -> 0 | AT8: =DataQ!R207 -> 9397.831 | AU8: =AT8 -> 9397.831 | AV8: =AU8-AT8 -> 0 | AX8: =DataQ!U207 -> 9460.302 | AY8: =DataQ!AA207 -> 9460.302 | AZ8: =AY8-AX8 -> 0 | BB8: =RANK(BE8,$BE$4:$BE$22) -> 5 | BC8: Water | BD8: ='ASHE Annual pay All SIC'!H63 -> 23302 | BE8: ='ASHE Annual pay All SIC'!J63 -> 29282 | BF8: ='ASHE Annual pay All SIC'!D63 -> 38435 | BG8: ='ASHE Annual pay All SIC'!O63 -> 48565 | BH8: =+BH7+1 -> 5.5 | BJ8: 5 | BK8: =VLOOKUP($BJ8,$BB$4:$BG$22,2,FALSE) -> Water | BL8: =VLOOKUP($BJ8,$BB$4:$BG$22,3,FALSE) -> 23302 | BM8: =VLOOKUP($BJ8,$BB$4:$BG$22,4,FALSE) -> 29282 | BN8: =VLOOKUP($BJ8,$BB$4:$BG$22,5,FALSE) -> 38435 | BO8: =VLOOKUP($BJ8,$BB$4:$BG$22,6,FALSE) -> 48565 | BP8: =+BP7+1 -> 5.5 | BR8: Water | BS8: =BD8 -> 23302 | BT8: =BE8-BS8 -> 5980 | BU8: =BF8-BT8 -> 32455 | BV8: =BG8-BU8 -> 16110 | BW8: =+BW7+1 -> 4.5 | BY8: Hours/week | CJ8: 35 | CZ8: 2025-2026 change | DA8: =100*((DA5/DA4)-1) -> 8.5863786 | DB8: =100*((DB5/DB4)-1) -> 8.2578994 | DC8: =100*((DC5/DC4)-1) -> 8.0098005 | DD8: =100*((DD5/DD4)-1) -> 7.8123175 | DE8: =100*((DE5/DE4)-1) -> 7.6299531 | DF8: =100*((DF5/DF4)-1) -> 7.4675998 | DG8: =100*((DG5/DG4)-1) -> 7.3139968 | DH8: =100*((DH5/DH4)-1) -> 7.2378371 | DI8: =100*((DI5/DI4)-1) -> 7.1536766 | DK8: =100*((DK5/DK4)-1) -> 10.550098 | DL8: =100*((DL5/DL4)-1) -> 7.3645388 | DQ8: Hours/week | EB8: 35 | ER8: 2025-2026 change | ES8: =100*((ES5/ES4)-1) -> 13.221201 | ET8: =100*((ET5/ET4)-1) -> 11.00076 | EU8: =100*((EU5/EU4)-1) -> 8.5042417 | EV8: =100*((EV5/EV4)-1) -> 8.1657074 | EW8: =100*((EW5/EW4)-1) -> 7.8998509 | EX8: =100*((EX5/EX4)-1) -> 7.6655078 | EY8: =100*((EY5/EY4)-1) -> 7.4564019 | EZ8: =100*((EZ5/EZ4)-1) -> 7.2595314 | FA8: =100*((FA5/FA4)-1) -> 7.0176891 | FC8: =100*((FC5/FC4)-1) -> 10.550098 | FD8: =100*((FD5/FD4)-1) -> 7.5997422 | FI8: FY23 | FJ8: =HAVERM!D526*35*52 -> 18964.4 | FK8: =(FJ8-$FP8)*$FO8 -> 1361.2872 | FL8: =+FK8+FJ8 -> 20325.687 | FM8: =100*((FL8/FL7)-1) -> 10.038649 | FO8: 0.138 | FP8: 9100 | FR8: =HAVERA!B30 -> 34963 | FS8: =(FR8-$FX8)*$FW8 -> 3569.094 | FT8: =+FS8+FR8 -> 38532.094 | FU8: =100*((FT8/FT7)-1) -> 5.5171539 | FW8: 0.138 | FX8: 9100 | FZ8: 36892 | GA8: =100*((HAVERQ!S92/HAVERQ!S88)-1) -> 1.288625 | GB8: =MIN(GI7:GJ7) -> 0.40547657 | GC8: =+GF8-GB8 -> 0.43226118 | GD8: =AVERAGE(GB8,GF8) -> 0.62160716 | GF8: =MAX(GI7:GJ7) -> 0.83773775 | GH8: 36892 | GI8: =(GL8-GI$1)/GI$2 -> 0.38505978 | GJ8: =(GM8-GJ$1)/GJ$2 -> 0.21956 | GL8: =(HAVERQ!BJ92*HAVERQ!$BJ$1)+(HAVERQ!BK92*HAVERQ!$BK$1) -> 22.222635 | GM8: =(HAVERQ!BL92*HAVERQ!$BL$1)+(HAVERQ!BM92*HAVERQ!$BM$1)+(HAVERQ!BN92*HAVERQ!$BN$1)+(HAVERQ!BO92*HAVERQ!$BO$1) -> 10.991957 | GR8: 36892 | GS8: =100*(HAVERQ!BP92/HAVERQ!BR92) -> 22.598775 | GT8: =AVERAGE($GS$4:$GS$103) -> 24.605137 | GV8: 36892 | GW8: =100*(HAVERQ!BP92/HAVERQ!BR92) -> 22.598775 | GX8: =100*((DataQ!F123/DataQ!F119)-1) -> 0.28021329 | GZ8: 45292 | HA8: =HH8-HH$11 -> -159.91 | HB8: =HI8-HI$11 -> -444.7 | HC8: =HB8-HA8 -> -284.79 | HE8: =100*(HH8/$HH$11) -> 99.517717 | HF8: =100*(HI8/$HI$11) -> 98.683373 | HH8: =DataQ!AE211 -> 32997 | HI8: =DataQ!O211 -> 33331 | HK8: 45292 | HL8: =HS8-HS$11 -> 19.08 | HM8: =HT8-HT$11 -> -139.34 | HN8: =HM8-HL8 -> -158.42 | HP8: =100*(HS8/HS$11) -> 100.05143 | HQ8: =100*(HT8/HT$11) -> 99.622695 | HS8: =DataQ!AF211 -> 37117 | HT8: =DataQ!P211 -> 36791 | HV8: Don't know | HW8: 19 | HX8: 18 | HY8: 21
A9: 2019 | B9: =100*((DataA!G53-DataA!G52)/DataA!H52) -> 2.1285774 | C9: =D9-B9 -> 1.4739322 | D9: =100*((DataA!H53/DataA!H52)-1) -> 3.6025096 | F9: 2019 | G9: =B9-K9 -> 0.64390525 | H9: =I9-G9 -> 1.409085 | I9: =100*((DataA!I53/DataA!I52)-1) -> 2.0529903 | K9: =100*((DataA!J53/DataA!J52)-1) -> 1.4846722 | N9: =100*((DataQ!F168/DataQ!F164)-1) -> 2.583742 | O9: =100*(DataQ!I168/DataQ!J168) -> 21.880591 | R9: =HLOOKUP(R$8,$R$2:$W$6,2,FALSE) -> Lower profit margins | S9: =HLOOKUP(S$8,$R$2:$W$6,2,FALSE) -> Higher prices | T9: =HLOOKUP(T$8,$R$2:$W$6,2,FALSE) -> Lower number of employees | U9: =HLOOKUP(U$8,$R$2:$W$6,2,FALSE) -> Lower employee wages | V9: =HLOOKUP(V$8,$R$2:$W$6,2,FALSE) -> Other | W9: =HLOOKUP(W$8,$R$2:$W$6,2,FALSE) -> None of the above | Y9: 45017 | Z9: =DataQ!Q208 -> 4.2 | AA9: =Z9 -> 4.2 | AC9: =DataQ!V208 -> 4.2 | AD9: =DataQ!AB208 -> 4.2 | AE9: =AD9-AC9 -> 0 | AG9: 45017 | AH9: =DataQ!O208 -> 33356 | AI9: =AH9 -> 33356 | AJ9: =AI9-AH9 -> 0 | AL9: =DataQ!T208 -> 33163 | AM9: =DataQ!Z208 -> 33163 | AN9: =AM9-AL9 -> 0 | AP9: 45017 | AQ9: =100*((DataQ!R208/DataQ!R204)-1) -> 9.0108254 | AR9: =AQ9 -> 9.0108254 | AS9: =AR9-AQ9 -> 0 | AT9: =DataQ!R208 -> 9575.004 | AU9: =AT9 -> 9575.004 | AV9: =AU9-AT9 -> 0 | AX9: =DataQ!U208 -> 9660.59 | AY9: =DataQ!AA208 -> 9660.59 | AZ9: =AY9-AX9 -> 0 | BB9: =RANK(BE9,$BE$4:$BE$22) -> 7 | BC9: Construction | BD9: ='ASHE Annual pay All SIC'!H68 -> 14049 | BE9: ='ASHE Annual pay All SIC'!J68 -> 26871 | BF9: ='ASHE Annual pay All SIC'!D68 -> 38209 | BG9: ='ASHE Annual pay All SIC'!O68 -> 53463 | BH9: =+BH8+1 -> 6.5 | BJ9: 6 | BK9: =VLOOKUP($BJ9,$BB$4:$BG$22,2,FALSE) -> Transport | BL9: =VLOOKUP($BJ9,$BB$4:$BG$22,3,FALSE) -> 19034 | BM9: =VLOOKUP($BJ9,$BB$4:$BG$22,4,FALSE) -> 27347 | BN9: =VLOOKUP($BJ9,$BB$4:$BG$22,5,FALSE) -> 35868 | BO9: =VLOOKUP($BJ9,$BB$4:$BG$22,6,FALSE) -> 47741 | BP9: =+BP8+1 -> 6.5 | BR9: Construction | BS9: =BD9 -> 14049 | BT9: =BE9-BS9 -> 12822 | BU9: =BF9-BT9 -> 25387 | BV9: =BG9-BU9 -> 28076 | BW9: =+BW8+1 -> 5.5 | FI9: FY24 | FJ9: =HAVERM!D538*35*52 -> 20820.8 | FK9: =(FJ9-$FP9)*$FO9 -> 1617.4704 | FL9: =+FK9+FJ9 -> 22438.27 | FM9: =100*((FL9/FL8)-1) -> 10.393662 | FO9: 0.138 | FP9: 9100 | FR9: =HAVERA!B31 -> 37430 | FS9: =(FR9-$FX9)*$FW9 -> 3909.54 | FT9: =+FS9+FR9 -> 41339.54 | FU9: =100*((FT9/FT8)-1) -> 7.2859939 | FW9: 0.138 | FX9: 9100 | FZ9: 36982 | GA9: =100*((HAVERQ!S93/HAVERQ!S89)-1) -> 1.2124265 | GB9: =MIN(GI8:GJ8) -> 0.21956 | GC9: =+GF9-GB9 -> 0.16549978 | GD9: =AVERAGE(GB9,GF9) -> 0.30230989 | GF9: =MAX(GI8:GJ8) -> 0.38505978 | GH9: 36982 | GI9: =(GL9-GI$1)/GI$2 -> 0.22206584 | GJ9: =(GM9-GJ$1)/GJ$2 -> 0.0754623 | GL9: =(HAVERQ!BJ93*HAVERQ!$BJ$1)+(HAVERQ!BK93*HAVERQ!$BK$1) -> 20.445269 | GM9: =(HAVERQ!BL93*HAVERQ!$BL$1)+(HAVERQ!BM93*HAVERQ!$BM$1)+(HAVERQ!BN93*HAVERQ!$BN$1)+(HAVERQ!BO93*HAVERQ!$BO$1) -> 8.627716 | GR9: 36982 | GS9: =100*(HAVERQ!BP93/HAVERQ!BR93) -> 23.450622 | GT9: =AVERAGE($GS$4:$GS$103) -> 24.605137 | GV9: 36982 | GW9: =100*(HAVERQ!BP93/HAVERQ!BR93) -> 23.450622 | GX9: =100*((DataQ!F124/DataQ!F120)-1) -> 0.75233745 | GZ9: 45383 | HA9: =HH9-HH$11 -> -62.91 | HB9: =HI9-HI$11 -> -279.7 | HC9: =HB9-HA9 -> -216.79 | HE9: =100*(HH9/$HH$11) -> 99.810266 | HF9: =100*(HI9/$HI$11) -> 99.17189 | HH9: =DataQ!AE212 -> 33094 | HI9: =DataQ!O212 -> 33496 | HK9: 45383 | HL9: =HS9-HS$11 -> -8.92 | HM9: =HT9-HT$11 -> -210.34 | HN9: =HM9-HL9 -> -201.42 | HP9: =100*(HS9/HS$11) -> 99.975956 | HQ9: =100*(HT9/HT$11) -> 99.430441 | HS9: =DataQ!AF212 -> 37089 | HT9: =DataQ!P212 -> 36720 | HW9: =SUM(HW4:HW8) -> 100 | HX9: =SUM(HX4:HX8) -> 100 | HY9: =SUM(HY4:HY8) -> 100
A10: 2020 | B10: =100*((DataA!G54-DataA!G53)/DataA!H53) -> 0.0012388486 | C10: =D10-B10 -> 0.098281992 | D10: =100*((DataA!H54/DataA!H53)-1) -> 0.099520841 | F10: 2020 | G10: =B10-K10 -> -0.067846845 | H10: =I10-G10 -> -0.30916746 | I10: =100*((DataA!I54/DataA!I53)-1) -> -0.3770143 | K10: =100*((DataA!J54/DataA!J53)-1) -> 0.069085694 | N10: =100*((DataQ!F169/DataQ!F165)-1) -> 2.7966777 | O10: =100*(DataQ!I169/DataQ!J169) -> 22.178476 | Q10: =Q4 -> 45597 | R10: =HLOOKUP(R$8,$R$2:$W$6,3,FALSE) -> 58.72 | S10: =HLOOKUP(S$8,$R$2:$W$6,3,FALSE) -> 53.64 | T10: =HLOOKUP(T$8,$R$2:$W$6,3,FALSE) -> 53.68 | U10: =HLOOKUP(U$8,$R$2:$W$6,3,FALSE) -> 37.88 | V10: =HLOOKUP(V$8,$R$2:$W$6,3,FALSE) -> 7.51 | W10: =HLOOKUP(W$8,$R$2:$W$6,3,FALSE) -> 2.67 | Y10: 45108 | Z10: =DataQ!Q209 -> 4.1 | AA10: =Z10 -> 4.1 | AC10: =DataQ!V209 -> 4.1 | AD10: =DataQ!AB209 -> 4.1 | AE10: =AD10-AC10 -> 0 | AG10: 45108 | AH10: =DataQ!O209 -> 33326 | AI10: =AH10 -> 33326 | AJ10: =AI10-AH10 -> 0 | AL10: =DataQ!T209 -> 33102 | AM10: =DataQ!Z209 -> 33102 | AN10: =AM10-AL10 -> 0 | AP10: 45108 | AQ10: =100*((DataQ!R209/DataQ!R205)-1) -> 7.6947348 | AR10: =AQ10 -> 7.6947348 | AS10: =AR10-AQ10 -> 0 | AT10: =DataQ!R209 -> 9666.17 | AU10: =AT10 -> 9666.17 | AV10: =AU10-AT10 -> 0 | AX10: =DataQ!U209 -> 9771.033 | AY10: =DataQ!AA209 -> 9771.033 | AZ10: =AY10-AX10 -> 0 | BB10: =RANK(BE10,$BE$4:$BE$22) -> 16 | BC10: Wholesale & retail | BD10: ='ASHE Annual pay All SIC'!H72 -> 9031 | BE10: ='ASHE Annual pay All SIC'!J72 -> 15193 | BF10: ='ASHE Annual pay All SIC'!D72 -> 25560 | BG10: ='ASHE Annual pay All SIC'!O72 -> 37000 | BH10: =+BH9+1 -> 7.5 | BJ10: 7 | BK10: =VLOOKUP($BJ10,$BB$4:$BG$22,2,FALSE) -> Construction | BL10: =VLOOKUP($BJ10,$BB$4:$BG$22,3,FALSE) -> 14049 | BM10: =VLOOKUP($BJ10,$BB$4:$BG$22,4,FALSE) -> 26871 | BN10: =VLOOKUP($BJ10,$BB$4:$BG$22,5,FALSE) -> 38209 | BO10: =VLOOKUP($BJ10,$BB$4:$BG$22,6,FALSE) -> 53463 | BP10: =+BP9+1 -> 7.5 | BR10: Wholesale & retail | BS10: =BD10 -> 9031 | BT10: =BE10-BS10 -> 6162 | BU10: =BF10-BT10 -> 19398 | BV10: =BG10-BU10 -> 17602 | BW10: =+BW9+1 -> 6.5 | BY10: How much NI does an employer pay in the UK? It depends on the National Insurance category of your employees but for most employees in the tax year 2024/25, employers need to pay a 13.8% contribution on any employee earnings exceeding the secondary threshold, which is £175/week or £758/month | DQ10: How much NI does an employer pay in the UK? It depends on the National Insurance category of your employees but for most employees in the tax year 2024/25, employers need to pay a 13.8% contribution on any employee earnings exceeding the secondary threshold, which is £175/week or £758/month | FI10: FY25 | FJ10: =HAVERM!D550*35*52 -> 22222.2 | FK10: =(FJ10-$FP10)*$FO10 -> 2583.33 | FL10: =+FK10+FJ10 -> 24805.53 | FM10: =100*((FL10/FL9)-1) -> 10.550098 | FO10: 0.15 | FP10: 5000 | FR10: =CD5 -> 39342.372 | FS10: =(FR10-$FX10)*$FW10 -> 5151.3558 | FT10: =+FS10+FR10 -> 44493.728 | FU10: =100*((FT10/FT9)-1) -> 7.6299531 | FW10: 0.15 | FX10: 5000 | FZ10: 37073 | GA10: =100*((HAVERQ!S94/HAVERQ!S90)-1) -> 1.1983844 | GB10: =MIN(GI9:GJ9) -> 0.0754623 | GC10: =+GF10-GB10 -> 0.14660354 | GD10: =AVERAGE(GB10,GF10) -> 0.14876407 | GF10: =MAX(GI9:GJ9) -> 0.22206584 | GH10: 37073 | GI10: =(GL10-GI$1)/GI$2 -> -0.32103749 | GJ10: =(GM10-GJ$1)/GJ$2 -> -0.5335829 | GL10: =(HAVERQ!BJ94*HAVERQ!$BJ$1)+(HAVERQ!BK94*HAVERQ!$BK$1) -> 14.523006 | GM10: =(HAVERQ!BL94*HAVERQ!$BL$1)+(HAVERQ!BM94*HAVERQ!$BM$1)+(HAVERQ!BN94*HAVERQ!$BN$1)+(HAVERQ!BO94*HAVERQ!$BO$1) -> -1.3650174 | GR10: 37073 | GS10: =100*(HAVERQ!BP94/HAVERQ!BR94) -> 23.511473 | GT10: =AVERAGE($GS$4:$GS$103) -> 24.605137 | GV10: 37073 | GW10: =100*(HAVERQ!BP94/HAVERQ!BR94) -> 23.511473 | GX10: =100*((DataQ!F125/DataQ!F121)-1) -> 0.69965392 | GZ10: 45474 | HA10: =HH10-HH$11 -> 150 | HB10: =HI10-HI$11 -> -26.7 | HC10: =HB10-HA10 -> -176.7 | HE10: =100*(HH10/$HH$11) -> 100.45239 | HF10: =100*(HI10/$HI$11) -> 99.920949 | HH10: =DataQ!AE213 -> 33306.91 | HI10: =DataQ!O213 -> 33749 | HK10: 45474 | HL10: =HS10-HS$11 -> -33.49 | HM10: =HT10-HT$11 -> -137.34 | HN10: =HM10-HL10 -> -103.85 | HP10: =100*(HS10/HS$11) -> 99.909725 | HQ10: =100*(HT10/HT$11) -> 99.628111 | HS10: =DataQ!AF213 -> 37064.43 | HT10: =DataQ!P213 -> 36793
A11: 2021 | B11: =100*((DataA!G55-DataA!G54)/DataA!H54) -> 3.8447946 | C11: =D11-B11 -> 0.29847196 | D11: =100*((DataA!H55/DataA!H54)-1) -> 4.1432665 | F11: 2021 | G11: =B11-K11 -> 1.1780466 | H11: =I11-G11 -> 0.41896108 | I11: =100*((DataA!I55/DataA!I54)-1) -> 1.5970077 | K11: =100*((DataA!J55/DataA!J54)-1) -> 2.666748 | N11: =100*((DataQ!F170/DataQ!F166)-1) -> 2.2815277 | O11: =100*(DataQ!I170/DataQ!J170) -> 22.016086 | Q11: =Q5 -> 45627 | R11: =HLOOKUP(R$8,$R$2:$W$6,4,FALSE) -> 63.5 | S11: =HLOOKUP(S$8,$R$2:$W$6,4,FALSE) -> 54.45 | T11: =HLOOKUP(T$8,$R$2:$W$6,4,FALSE) -> 52.76 | U11: =HLOOKUP(U$8,$R$2:$W$6,4,FALSE) -> 40.67 | V11: =HLOOKUP(V$8,$R$2:$W$6,4,FALSE) -> 7.33 | W11: =HLOOKUP(W$8,$R$2:$W$6,4,FALSE) -> 3.75 | Y11: 45200 | Z11: =DataQ!Q210 -> 3.9 | AA11: =Z11 -> 3.9 | AC11: =DataQ!V210 -> 3.8 | AD11: =DataQ!AB210 -> 3.8 | AE11: =AD11-AC11 -> 0 | AG11: 45200 | AH11: =DataQ!O210 -> 33377 | AI11: =AH11 -> 33377 | AJ11: =AI11-AH11 -> 0 | AL11: =DataQ!T210 -> 33174 | AM11: =DataQ!Z210 -> 33174 | AN11: =AM11-AL11 -> 0 | AP11: 45200 | AQ11: =100*((DataQ!R210/DataQ!R206)-1) -> 5.9569959 | AR11: =AQ11 -> 5.9569959 | AS11: =AR11-AQ11 -> 0 | AT11: =DataQ!R210 -> 9719.769 | AU11: =AT11 -> 9719.769 | AV11: =AU11-AT11 -> 0 | AX11: =DataQ!U210 -> 9774.984 | AY11: =DataQ!AA210 -> 9774.984 | AZ11: =AY11-AX11 -> 0 | BB11: =RANK(BE11,$BE$4:$BE$22) -> 6 | BC11: Transport | BD11: ='ASHE Annual pay All SIC'!H76 -> 19034 | BE11: ='ASHE Annual pay All SIC'!J76 -> 27347 | BF11: ='ASHE Annual pay All SIC'!D76 -> 35868 | BG11: ='ASHE Annual pay All SIC'!O76 -> 47741 | BH11: =+BH10+1 -> 8.5 | BJ11: 8 | BK11: =VLOOKUP($BJ11,$BB$4:$BG$22,2,FALSE) -> Manufacturing | BL11: =VLOOKUP($BJ11,$BB$4:$BG$22,3,FALSE) -> 21424 | BM11: =VLOOKUP($BJ11,$BB$4:$BG$22,4,FALSE) -> 26686 | BN11: =VLOOKUP($BJ11,$BB$4:$BG$22,5,FALSE) -> 35518 | BO11: =VLOOKUP($BJ11,$BB$4:$BG$22,6,FALSE) -> 49243 | BP11: =+BP10+1 -> 8.5 | BR11: Transport | BS11: =BD11 -> 19034 | BT11: =BE11-BS11 -> 8313 | BU11: =BF11-BT11 -> 27555 | BV11: =BG11-BU11 -> 20186 | BW11: =+BW10+1 -> 7.5 | BY11: The government will increase the rate of employer NICs from 13.8% to 15% from 6 April 2025. | DQ11: The government will increase the rate of employer NICs from 13.8% to 15% from 6 April 2025. | FZ11: 37165 | GA11: =100*((HAVERQ!S95/HAVERQ!S91)-1) -> 1.0329202 | GB11: =MIN(GI10:GJ10) -> -0.5335829 | GC11: =+GF11-GB11 -> 0.2125454 | GD11: =AVERAGE(GB11,GF11) -> -0.42731019 | GF11: =MAX(GI10:GJ10) -> -0.32103749 | GH11: 37165 | GI11: =(GL11-GI$1)/GI$2 -> -0.63179787 | GJ11: =(GM11-GJ$1)/GJ$2 -> -1.5733116 | GL11: =(HAVERQ!BJ95*HAVERQ!$BJ$1)+(HAVERQ!BK95*HAVERQ!$BK$1) -> 11.134323 | GM11: =(HAVERQ!BL95*HAVERQ!$BL$1)+(HAVERQ!BM95*HAVERQ!$BM$1)+(HAVERQ!BN95*HAVERQ!$BN$1)+(HAVERQ!BO95*HAVERQ!$BO$1) -> -18.424066 | GR11: 37165 | GS11: =100*(HAVERQ!BP95/HAVERQ!BR95) -> 23.194699 | GT11: =AVERAGE($GS$4:$GS$103) -> 24.605137 | GV11: 37165 | GW11: =100*(HAVERQ!BP95/HAVERQ!BR95) -> 23.194699 | GX11: =100*((DataQ!F126/DataQ!F122)-1) -> 0.80160473 | GZ11: 45566 | HA11: =HH11-HH$11 -> 0 | HB11: =HI11-HI$11 -> 0 | HC11: =HB11-HA11 -> 0 | HE11: =100*(HH11/$HH$11) -> 100 | HF11: =100*(HI11/$HI$11) -> 100 | HH11: =DataQ!AE214 -> 33156.91 | HI11: =DataQ!O214 -> 33775.7 | HK11: 45566 | HL11: =HS11-HS$11 -> 0 | HM11: =HT11-HT$11 -> 0 | HN11: =HM11-HL11 -> 0 | HP11: =100*(HS11/HS$11) -> 100 | HQ11: =100*(HT11/HT$11) -> 100 | HS11: =DataQ!AF214 -> 37097.92 | HT11: =DataQ!P214 -> 36930.34
A12: 2022 | B12: =100*((DataA!G56-DataA!G55)/DataA!H55) -> 4.5968489 | C12: =D12-B12 -> 1.6454431 | D12: =100*((DataA!H56/DataA!H55)-1) -> 6.242292 | F12: 2022 | G12: =B12-K12 -> -3.898532 | H12: =I12-G12 -> 2.148227 | I12: =100*((DataA!I56/DataA!I55)-1) -> -1.750305 | K12: =100*((DataA!J56/DataA!J55)-1) -> 8.4953809 | M12: 2014 | N12: =100*((DataQ!F171/DataQ!F167)-1) -> 2.457354 | O12: =100*(DataQ!I171/DataQ!J171) -> 21.695584 | Q12: =Q6 -> 45658 | R12: =HLOOKUP(R$8,$R$2:$W$6,5,FALSE) -> 63.46 | S12: =HLOOKUP(S$8,$R$2:$W$6,5,FALSE) -> 61.1 | T12: =HLOOKUP(T$8,$R$2:$W$6,5,FALSE) -> 53.63 | U12: =HLOOKUP(U$8,$R$2:$W$6,5,FALSE) -> 36.63 | V12: =HLOOKUP(V$8,$R$2:$W$6,5,FALSE) -> 11.88 | W12: =HLOOKUP(W$8,$R$2:$W$6,5,FALSE) -> 2.94 | Y12: 45292 | Z12: =DataQ!Q211 -> 4.3 | AA12: =Z12 -> 4.3 | AC12: =DataQ!V211 -> 4.3 | AD12: =DataQ!AB211 -> 4.3 | AE12: =AD12-AC12 -> 0 | AG12: 45292 | AH12: =DataQ!O211 -> 33331 | AI12: =AH12 -> 33331 | AJ12: =AI12-AH12 -> 0 | AL12: =DataQ!T211 -> 32997 | AM12: =DataQ!Z211 -> 32997 | AN12: =AM12-AL12 -> 0 | AP12: 45292 | AQ12: =100*((AT12/AT8)-1) -> 4.8107058 | AR12: =100*((AU12/AU8)-1) -> 4.8107058 | AS12: =AR12-AQ12 -> 0 | AT12: =DataQ!R211 -> 9849.933 | AU12: =AT12 -> 9849.933 | AV12: =AU12-AT12 -> 0 | AX12: =DataQ!U211 -> 9898.726 | AY12: =DataQ!AA211 -> 9898.726 | AZ12: =AY12-AX12 -> 0 | BB12: =RANK(BE12,$BE$4:$BE$22) -> 19 | BC12: Accommodation & food | BD12: ='ASHE Annual pay All SIC'!H82 -> 4239 | BE12: ='ASHE Annual pay All SIC'!J82 -> 8951 | BF12: ='ASHE Annual pay All SIC'!D82 -> 16800 | BG12: ='ASHE Annual pay All SIC'!O82 -> 27056 | BH12: =+BH11+1 -> 9.5 | BJ12: 9 | BK12: =VLOOKUP($BJ12,$BB$4:$BG$22,2,FALSE) -> Public admin | BL12: =VLOOKUP($BJ12,$BB$4:$BG$22,3,FALSE) -> 16564 | BM12: =VLOOKUP($BJ12,$BB$4:$BG$22,4,FALSE) -> 26528 | BN12: =VLOOKUP($BJ12,$BB$4:$BG$22,5,FALSE) -> 36109 | BO12: =VLOOKUP($BJ12,$BB$4:$BG$22,6,FALSE) -> 47310 | BP12: =+BP11+1 -> 9.5 | BR12: Accommodation & food | BS12: =BD12 -> 4239 | BT12: =BE12-BS12 -> 4712 | BU12: =BF12-BT12 -> 12088 | BV12: =BG12-BU12 -> 14968 | BW12: =+BW11+1 -> 8.5 | BY12: The Secondary Threshold is the point at which employers become liable to pay NICs on employees’ earnings, and is currently set at £9,100 a year. The government will reduce the Secondary Threshold to £5,000 a year from 6 April 2025 until 6 April 2028, and then increase it by Consumer Price Index (CPI) thereafter | DQ12: The Secondary Threshold is the point at which employers become liable to pay NICs on employees’ earnings, and is currently set at £9,100 a year. The government will reduce the Secondary Threshold to £5,000 a year from 6 April 2025 until 6 April 2028, and then increase it by Consumer Price Index (CPI) thereafter | FL12: =100*((FL10/FL6)-1) -> 43.932712 | FT12: =100*((FT10/FT6)-1) -> 29.408403 | FZ12: 37257 | GA12: =100*((HAVERQ!S96/HAVERQ!S92)-1) -> 0.95583827 | GB12: =MIN(GI11:GJ11) -> -1.5733116 | GC12: =+GF12-GB12 -> 0.94151371 | GD12: =AVERAGE(GB12,GF12) -> -1.1025547 | GF12: =MAX(GI11:GJ11) -> -0.63179787 | GH12: 37257 | GI12: =(GL12-GI$1)/GI$2 -> 0.433992 | GJ12: =(GM12-GJ$1)/GJ$2 -> 0.11417725 | GL12: =(HAVERQ!BJ96*HAVERQ!$BJ$1)+(HAVERQ!BK96*HAVERQ!$BK$1) -> 22.756215 | GM12: =(HAVERQ!BL96*HAVERQ!$BL$1)+(HAVERQ!BM96*HAVERQ!$BM$1)+(HAVERQ!BN96*HAVERQ!$BN$1)+(HAVERQ!BO96*HAVERQ!$BO$1) -> 9.2629203 | GR12: 37257 | GS12: =100*(HAVERQ!BP96/HAVERQ!BR96) -> 23.492579 | GT12: =AVERAGE($GS$4:$GS$103) -> 24.605137 | GV12: 37257 | GW12: =100*(HAVERQ!BP96/HAVERQ!BR96) -> 23.492579 | GX12: =100*((DataQ!F127/DataQ!F123)-1) -> 1.1604897 | GZ12: 45658 | HA12: =HH12-HH$11 -> 103.93 | HB12: =HI12-HI$11 -> -20 | HC12: =HB12-HA12 -> -123.93 | HE12: =100*(HH12/$HH$11) -> 100.31345 | HF12: =100*(HI12/$HI$11) -> 99.940786 | HH12: =DataQ!AE215 -> 33260.84 | HI12: =DataQ!O215 -> 33755.7 | HK12: 45658 | HL12: =HS12-HS$11 -> 86.29 | HM12: =HT12-HT$11 -> 72.29 | HN12: =HM12-HL12 -> -14 | HP12: =100*(HS12/HS$11) -> 100.2326 | HQ12: =100*(HT12/HT$11) -> 100.19575 | HS12: =DataQ!AF215 -> 37184.21 | HT12: =DataQ!P215 -> 37002.63
A13: 2023 | B13: =100*((DataA!G57-DataA!G56)/DataA!H56) -> 5.4343165 | C13: =D13-B13 -> 3.6829069 | D13: =100*((DataA!H57/DataA!H56)-1) -> 9.1172234 | F13: 2023 | G13: =B13-K13 -> -1.4588863 | H13: =I13-G13 -> 3.5919099 | I13: =100*((DataA!I57/DataA!I56)-1) -> 2.1330236 | K13: =100*((DataA!J57/DataA!J56)-1) -> 6.8932028 | N13: =100*((DataQ!F172/DataQ!F168)-1) -> -1.5163896 | O13: =100*(DataQ!I172/DataQ!J172) -> 22.422755 | Y13: 45383 | Z13: =DataQ!Q212 -> 4.2 | AA13: =Z13 -> 4.2 | AC13: =DataQ!V212 -> 4.2 | AD13: =DataQ!AB212 -> 4.2 | AE13: =AD13-AC13 -> 0 | AG13: 45383 | AH13: =DataQ!O212 -> 33496 | AI13: =AH13 -> 33496 | AJ13: =AI13-AH13 -> 0 | AL13: =DataQ!T212 -> 33094 | AM13: =DataQ!Z212 -> 33094 | AN13: =AM13-AL13 -> 0 | AP13: 45383 | AQ13: =100*((AT13/AT9)-1) -> 4.4659616 | AR13: =100*((AU13/AU9)-1) -> 4.4659616 | AS13: =AR13-AQ13 -> 0 | AT13: =DataQ!R212 -> 10002.62 | AU13: =AT13 -> 10002.62 | AV13: =AU13-AT13 -> 0 | AX13: =DataQ!U212 -> 10025.21 | AY13: =DataQ!AA212 -> 10025.21 | AZ13: =AY13-AX13 -> 0 | BB13: =RANK(BE13,$BE$4:$BE$22) -> 3 | BC13: Communications | BD13: ='ASHE Annual pay All SIC'!H85 -> 23599 | BE13: ='ASHE Annual pay All SIC'!J85 -> 32656 | BF13: ='ASHE Annual pay All SIC'!D85 -> 46063 | BG13: ='ASHE Annual pay All SIC'!O85 -> 68998 | BH13: =+BH12+1 -> 10.5 | BJ13: 10 | BK13: =VLOOKUP($BJ13,$BB$4:$BG$22,2,FALSE) -> Professional services | BL13: =VLOOKUP($BJ13,$BB$4:$BG$22,3,FALSE) -> 15685 | BM13: =VLOOKUP($BJ13,$BB$4:$BG$22,4,FALSE) -> 26405 | BN13: =VLOOKUP($BJ13,$BB$4:$BG$22,5,FALSE) -> 39880 | BO13: =VLOOKUP($BJ13,$BB$4:$BG$22,6,FALSE) -> 59607 | BP13: =+BP12+1 -> 10.5 | BR13: Communications | BS13: =BD13 -> 23599 | BT13: =BE13-BS13 -> 9057 | BU13: =BF13-BT13 -> 37006 | BV13: =BG13-BU13 -> 31992 | BW13: =+BW12+1 -> 9.5 | FZ13: 37347 | GA13: =100*((HAVERQ!S97/HAVERQ!S93)-1) -> 0.93907619 | GB13: =MIN(GI12:GJ12) -> 0.11417725 | GC13: =+GF13-GB13 -> 0.31981475 | GD13: =AVERAGE(GB13,GF13) -> 0.27408462 | GF13: =MAX(GI12:GJ12) -> 0.433992 | GH13: 37347 | GI13: =(GL13-GI$1)/GI$2 -> 0.18026248 | GJ13: =(GM13-GJ$1)/GJ$2 -> -0.30226419 | GL13: =(HAVERQ!BJ97*HAVERQ!$BJ$1)+(HAVERQ!BK97*HAVERQ!$BK$1) -> 19.989425 | GM13: =(HAVERQ!BL97*HAVERQ!$BL$1)+(HAVERQ!BM97*HAVERQ!$BM$1)+(HAVERQ!BN97*HAVERQ!$BN$1)+(HAVERQ!BO97*HAVERQ!$BO$1) -> 2.4302776 | GR13: 37347 | GS13: =100*(HAVERQ!BP97/HAVERQ!BR97) -> 23.852336 | GT13: =AVERAGE($GS$4:$GS$103) -> 24.605137 | GV13: 37347 | GW13: =100*(HAVERQ!BP97/HAVERQ!BR97) -> 23.852336 | GX13: =100*((DataQ!F128/DataQ!F124)-1) -> 1.440918 | GZ13: 45748 | HA13: =HH13-HH$11 -> 218.14 | HB13: =HI13-HI$11 -> 41.5 | HC13: =HB13-HA13 -> -176.64 | HE13: =100*(HH13/$HH$11) -> 100.6579 | HF13: =100*(HI13/$HI$11) -> 100.12287 | HH13: =DataQ!AE216 -> 33375.05 | HI13: =DataQ!O216 -> 33817.2 | HK13: 45748 | HL13: =HS13-HS$11 -> 193.97 | HM13: =HT13-HT$11 -> 138.52 | HN13: =HM13-HL13 -> -55.45 | HP13: =100*(HS13/HS$11) -> 100.52286 | HQ13: =100*(HT13/HT$11) -> 100.37508 | HS13: =DataQ!AF216 -> 37291.89 | HT13: =DataQ!P216 -> 37068.86
A14: 2024 | B14: =100*((DataA!G58-DataA!G57)/DataA!H57) -> 3.3758444 | C14: =D14-B14 -> 3.2222111 | D14: =100*((DataA!H58/DataA!H57)-1) -> 6.5980555 | F14: 2024 | G14: =B14-K14 -> 0.8032885 | H14: =I14-G14 -> 3.0470276 | I14: =100*((DataA!I58/DataA!I57)-1) -> 3.8503161 | K14: =100*((DataA!J58/DataA!J57)-1) -> 2.5725559 | N14: =100*((DataQ!F173/DataQ!F169)-1) -> -1.8918891 | O14: =100*(DataQ!I173/DataQ!J173) -> 23.797129 | Y14: 45474 | Z14: =DataQ!Q213 -> 4.3 | AA14: =Z14 -> 4.3 | AC14: =DataQ!V213 -> 4.243108 | AD14: =DataQ!AB213 -> 4.243108 | AE14: =AD14-AC14 -> 0 | AG14: 45474 | AH14: =DataQ!O213 -> 33749 | AI14: =AH14 -> 33749 | AJ14: =AI14-AH14 -> 0 | AL14: =DataQ!T213 -> 33306.91 | AM14: =DataQ!Z213 -> 33306.91 | AN14: =AM14-AL14 -> 0 | AP14: 45474 | AQ14: =100*((AT14/AT10)-1) -> 3.2989798 | AR14: =100*((AU14/AU10)-1) -> 3.2989798 | AS14: =AR14-AQ14 -> 0 | AT14: =DataQ!R213 -> 9985.055 | AU14: =AT14 -> 9985.055 | AV14: =AU14-AT14 -> 0 | AX14: =DataQ!U213 -> 10139.5 | AY14: =DataQ!AA213 -> 10139.5 | AZ14: =AY14-AX14 -> 0 | BB14: =RANK(BE14,$BE$4:$BE$22) -> 4 | BC14: Financial services | BD14: ='ASHE Annual pay All SIC'!H92 -> 21567 | BE14: ='ASHE Annual pay All SIC'!J92 -> 29873 | BF14: ='ASHE Annual pay All SIC'!D92 -> 47248 | BG14: ='ASHE Annual pay All SIC'!O92 -> 78520 | BH14: =+BH13+1 -> 11.5 | BJ14: 11 | BK14: =VLOOKUP($BJ14,$BB$4:$BG$22,2,FALSE) -> Real estate | BL14: =VLOOKUP($BJ14,$BB$4:$BG$22,3,FALSE) -> 12244 | BM14: =VLOOKUP($BJ14,$BB$4:$BG$22,4,FALSE) -> 22774 | BN14: =VLOOKUP($BJ14,$BB$4:$BG$22,5,FALSE) -> 30891 | BO14: =VLOOKUP($BJ14,$BB$4:$BG$22,6,FALSE) -> 41645 | BP14: =+BP13+1 -> 11.5 | BR14: Financial services | BS14: =BD14 -> 21567 | BT14: =BE14-BS14 -> 8306 | BU14: =BF14-BT14 -> 38942 | BV14: =BG14-BU14 -> 39578 | BW14: =+BW13+1 -> 10.5 | BY14: https://zelt.app/blog/how-to-calculate-employers-ni-employer-s-ni-calculator-2024-2025-2026/#:~:text=How%20much%20NI%20does%20an,week%20or%20%C2%A3758%2Fmonth. | DQ14: https://zelt.app/blog/how-to-calculate-employers-ni-employer-s-ni-calculator-2024-2025-2026/#:~:text=How%20much%20NI%20does%20an,week%20or%20%C2%A3758%2Fmonth. | FZ14: 37438 | GA14: =100*((HAVERQ!S98/HAVERQ!S94)-1) -> 0.63003035 | GB14: =MIN(GI13:GJ13) -> -0.30226419 | GC14: =+GF14-GB14 -> 0.48252666 | GD14: =AVERAGE(GB14,GF14) -> -0.061000856 | GF14: =MAX(GI13:GJ13) -> 0.18026248 | GH14: 37438 | GI14: =(GL14-GI$1)/GI$2 -> -0.17943013 | GJ14: =(GM14-GJ$1)/GJ$2 -> -0.79337559 | GL14: =(HAVERQ!BJ98*HAVERQ!$BJ$1)+(HAVERQ!BK98*HAVERQ!$BK$1) -> 16.067162 | GM14: =(HAVERQ!BL98*HAVERQ!$BL$1)+(HAVERQ!BM98*HAVERQ!$BM$1)+(HAVERQ!BN98*HAVERQ!$BN$1)+(HAVERQ!BO98*HAVERQ!$BO$1) -> -5.6274912 | GR14: 37438 | GS14: =100*(HAVERQ!BP98/HAVERQ!BR98) -> 24.361057 | GT14: =AVERAGE($GS$4:$GS$103) -> 24.605137 | GV14: 37438 | GW14: =100*(HAVERQ!BP98/HAVERQ!BR98) -> 24.361057 | GX14: =100*((DataQ!F129/DataQ!F125)-1) -> 2.9935054 | GZ14: 45839 | HA14: =HH14-HH$11 -> 327.98 | HB14: =HI14-HI$11 -> 116.09 | HC14: =HB14-HA14 -> -211.89 | HE14: =100*(HH14/$HH$11) -> 100.98918 | HF14: =100*(HI14/$HI$11) -> 100.34371 | HH14: =DataQ!AE217 -> 33484.89 | HI14: =DataQ!O217 -> 33891.79 | HK14: 45839 | HL14: =HS14-HS$11 -> 296.71 | HM14: =HT14-HT$11 -> 218.72 | HN14: =HM14-HL14 -> -77.99 | HP14: =100*(HS14/HS$11) -> 100.7998 | HQ14: =100*(HT14/HT$11) -> 100.59225 | HS14: =DataQ!AF217 -> 37394.63 | HT14: =DataQ!P217 -> 37149.06
A15: 2025 | B15: =100*((DataA!G59-DataA!G58)/DataA!H58) -> 3.0681355 | C15: =D15-B15 -> 0.98726808 | D15: =100*((DataA!H59/DataA!H58)-1) -> 4.0554036 | F15: 2025 | G15: =B15-K15 -> -0.033234759 | H15: =I15-G15 -> 0.95504008 | I15: =100*((DataA!I59/DataA!I58)-1) -> 0.92180532 | K15: =100*((DataA!J59/DataA!J58)-1) -> 3.1013703 | N15: =100*((DataQ!F174/DataQ!F170)-1) -> -1.6332789 | O15: =100*(DataQ!I174/DataQ!J174) -> 23.392813 | Y15: 45566 | Z15: =DataQ!Q214 -> 4.408384 | AA15: =Z15 -> 4.408384 | AC15: =DataQ!V214 -> 4.408679 | AD15: =DataQ!AB214 -> 4.408679 | AE15: =AD15-AC15 -> 0 | AG15: 45566 | AH15: =DataQ!O214 -> 33775.7 | AI15: =AH15 -> 33775.7 | AJ15: =AI15-AH15 -> 0 | AL15: =DataQ!T214 -> 33156.91 | AM15: =DataQ!Z214 -> 33156.91 | AN15: =AM15-AL15 -> 0 | AP15: 45566 | AQ15: =100*((AT15/AT11)-1) -> 4.7839717 | AR15: =100*((AU15/AU11)-1) -> 4.7839717 | AS15: =AR15-AQ15 -> 0 | AT15: =DataQ!R214 -> 10184.76 | AU15: =AT15 -> 10184.76 | AV15: =AU15-AT15 -> 0 | AX15: =DataQ!U214 -> 10244.95 | AY15: =DataQ!AA214 -> 10244.95 | AZ15: =AY15-AX15 -> 0 | BB15: =RANK(BE15,$BE$4:$BE$22) -> 11 | BC15: Real estate | BD15: ='ASHE Annual pay All SIC'!H96 -> 12244 | BE15: ='ASHE Annual pay All SIC'!J96 -> 22774 | BF15: ='ASHE Annual pay All SIC'!D96 -> 30891 | BG15: ='ASHE Annual pay All SIC'!O96 -> 41645 | BH15: =+BH14+1 -> 12.5 | BJ15: 12 | BK15: =VLOOKUP($BJ15,$BB$4:$BG$22,2,FALSE) -> Education | BL15: =VLOOKUP($BJ15,$BB$4:$BG$22,3,FALSE) -> 10561 | BM15: =VLOOKUP($BJ15,$BB$4:$BG$22,4,FALSE) -> 19555 | BN15: =VLOOKUP($BJ15,$BB$4:$BG$22,5,FALSE) -> 31094 | BO15: =VLOOKUP($BJ15,$BB$4:$BG$22,6,FALSE) -> 44533 | BP15: =+BP14+1 -> 12.5 | BR15: Real estate | BS15: =BD15 -> 12244 | BT15: =BE15-BS15 -> 10530 | BU15: =BF15-BT15 -> 20361 | BV15: =BG15-BU15 -> 21284 | BW15: =+BW14+1 -> 11.5 | FZ15: 37530 | GA15: =100*((HAVERQ!S99/HAVERQ!S95)-1) -> 0.54415936 | GB15: =MIN(GI14:GJ14) -> -0.79337559 | GC15: =+GF15-GB15 -> 0.61394547 | GD15: =AVERAGE(GB15,GF15) -> -0.48640286 | GF15: =MAX(GI14:GJ14) -> -0.17943013 | GH15: 37530 | GI15: =(GL15-GI$1)/GI$2 -> -0.82849654 | GJ15: =(GM15-GJ$1)/GJ$2 -> -0.13299086 | GL15: =(HAVERQ!BJ99*HAVERQ!$BJ$1)+(HAVERQ!BK99*HAVERQ!$BK$1) -> 8.9894251 | GM15: =(HAVERQ!BL99*HAVERQ!$BL$1)+(HAVERQ!BM99*HAVERQ!$BM$1)+(HAVERQ!BN99*HAVERQ!$BN$1)+(HAVERQ!BO99*HAVERQ!$BO$1) -> 5.207581 | GR15: 37530 | GS15: =100*(HAVERQ!BP99/HAVERQ!BR99) -> 24.914941 | GT15: =AVERAGE($GS$4:$GS$103) -> 24.605137 | GV15: 37530 | GW15: =100*(HAVERQ!BP99/HAVERQ!BR99) -> 24.914941 | GX15: =100*((DataQ!F130/DataQ!F126)-1) -> 3.0185753 | GZ15: 45931 | HA15: =HH15-HH$11 -> 443.66 | HB15: =HI15-HI$11 -> 212.07 | HC15: =HB15-HA15 -> -231.59 | HE15: =100*(HH15/$HH$11) -> 101.33806 | HF15: =100*(HI15/$HI$11) -> 100.62788 | HH15: =DataQ!AE218 -> 33600.57 | HI15: =DataQ!O218 -> 33987.77 | HK15: 45931 | HL15: =HS15-HS$11 -> 405.88 | HM15: =HT15-HT$11 -> 323.4 | HN15: =HM15-HL15 -> -82.48 | HP15: =100*(HS15/HS$11) -> 101.09408 | HQ15: =100*(HT15/HT$11) -> 100.8757 | HS15: =DataQ!AF218 -> 37503.8 | HT15: =DataQ!P218 -> 37253.74
A16: 2026 | B16: =100*((DataA!G60-DataA!G59)/DataA!H59) -> 2.4224673 | C16: =D16-B16 -> 1.1063715 | D16: =100*((DataA!H60/DataA!H59)-1) -> 3.5288388 | F16: 2026 | G16: =B16-K16 -> -0.067460705 | H16: =I16-G16 -> 1.082811 | I16: =100*((DataA!I60/DataA!I59)-1) -> 1.0153503 | K16: =100*((DataA!J60/DataA!J59)-1) -> 2.489928 | M16: 2015 | N16: =100*((DataQ!F175/DataQ!F171)-1) -> -0.69899237 | O16: =100*(DataQ!I175/DataQ!J175) -> 22.828221 | Y16: 45658 | Z16: =DataQ!Q215 -> 4.492019 | AA16: =Z16+AC16-AD16 -> 4.492019 | AC16: =DataQ!V215 -> 4.380091 | AD16: =DataQ!AB215 -> 4.380091 | AE16: =AD16-AC16 -> 0 | AG16: 45658 | AH16: =DataQ!O215 -> 33755.7 | AI16: =AH16*AL16/AM16 -> 33755.7 | AJ16: =AI16-AH16 -> 0 | AL16: =DataQ!T215 -> 33260.84 | AM16: =DataQ!Z215 -> 33260.84 | AN16: =AM16-AL16 -> 0 | AP16: 45658 | AQ16: =100*((AT16/AT12)-1) -> 4.4331977 | AR16: =100*((AU16/AU12)-1) -> 4.4331977 | AS16: =AR16-AQ16 -> 0 | AT16: =DataQ!R215 -> 10286.6 | AU16: =AT16*AX16/AY16 -> 10286.6 | AV16: =AU16-AT16 -> 0 | AX16: =DataQ!U215 -> 10327.93 | AY16: =DataQ!AA215 -> 10327.93 | AZ16: =AY16-AX16 -> 0 | BB16: =RANK(BE16,$BE$4:$BE$22) -> 10 | BC16: Professional services | BD16: ='ASHE Annual pay All SIC'!H98 -> 15685 | BE16: ='ASHE Annual pay All SIC'!J98 -> 26405 | BF16: ='ASHE Annual pay All SIC'!D98 -> 39880 | BG16: ='ASHE Annual pay All SIC'!O98 -> 59607 | BH16: =+BH15+1 -> 13.5 | BJ16: 13 | BK16: =VLOOKUP($BJ16,$BB$4:$BG$22,2,FALSE) -> Health | BL16: =VLOOKUP($BJ16,$BB$4:$BG$22,3,FALSE) -> 11105 | BM16: =VLOOKUP($BJ16,$BB$4:$BG$22,4,FALSE) -> 18893 | BN16: =VLOOKUP($BJ16,$BB$4:$BG$22,5,FALSE) -> 28150 | BO16: =VLOOKUP($BJ16,$BB$4:$BG$22,6,FALSE) -> 40481 | BP16: =+BP15+1 -> 13.5 | BR16: Professional services | BS16: =BD16 -> 15685 | BT16: =BE16-BS16 -> 10720 | BU16: =BF16-BT16 -> 29160 | BV16: =BG16-BU16 -> 30447 | BW16: =+BW15+1 -> 12.5 | FZ16: 37622 | GA16: =100*((HAVERQ!S100/HAVERQ!S96)-1) -> 0.72576122 | GB16: =MIN(GI15:GJ15) -> -0.82849654 | GC16: =+GF16-GB16 -> 0.69550569 | GD16: =AVERAGE(GB16,GF16) -> -0.4807437 | GF16: =MAX(GI15:GJ15) -> -0.13299086 | GH16: 37622 | GI16: =(GL16-GI$1)/GI$2 -> -0.55338045 | GJ16: =(GM16-GJ$1)/GJ$2 -> -0.66977625 | GL16: =(HAVERQ!BJ100*HAVERQ!$BJ$1)+(HAVERQ!BK100*HAVERQ!$BK$1) -> 11.989425 | GM16: =(HAVERQ!BL100*HAVERQ!$BL$1)+(HAVERQ!BM100*HAVERQ!$BM$1)+(HAVERQ!BN100*HAVERQ!$BN$1)+(HAVERQ!BO100*HAVERQ!$BO$1) -> -3.5995706 | GR16: 37622 | GS16: =100*(HAVERQ!BP100/HAVERQ!BR100) -> 24.61206 | GT16: =AVERAGE($GS$4:$GS$103) -> 24.605137 | GV16: 37622 | GW16: =100*(HAVERQ!BP100/HAVERQ!BR100) -> 24.61206 | GX16: =100*((DataQ!F131/DataQ!F127)-1) -> 4.0886884 | GZ16: 46023 | HA16: =HH16-HH$11 -> 557.91 | HB16: =HI16-HI$11 -> 319.16 | HC16: =HB16-HA16 -> -238.75 | HE16: =100*(HH16/$HH$11) -> 101.68264 | HF16: =100*(HI16/$HI$11) -> 100.94494 | HH16: =DataQ!AE219 -> 33714.82 | HI16: =DataQ!O219 -> 34094.86 | HK16: 46023 | HL16: =HS16-HS$11 -> 513.41 | HM16: =HT16-HT$11 -> 437.05 | HN16: =HM16-HL16 -> -76.36 | HP16: =100*(HS16/HS$11) -> 101.38393 | HQ16: =100*(HT16/HT$11) -> 101.18344 | HS16: =DataQ!AF219 -> 37611.33 | HT16: =DataQ!P219 -> 37367.39
N17: =100*((DataQ!F176/DataQ!F172)-1) -> 0.6717141 | O17: =100*(DataQ!I176/DataQ!J176) -> 22.391736 | Y17: 45748 | Z17: =DataQ!Q216 -> 4.502507 | AA17: =Z17+AC17-AD17 -> 4.42974 | AC17: =DataQ!V216 -> 4.351475 | AD17: =DataQ!AB216 -> 4.424242 | AE17: =AD17-AC17 -> 0.072767 | AG17: 45748 | AH17: =DataQ!O216 -> 33817.2 | AI17: =AH17*AL17/AM17 -> 33842.926 | AJ17: =AI17-AH17 -> 25.725655 | AL17: =DataQ!T216 -> 33375.05 | AM17: =DataQ!Z216 -> 33349.68 | AN17: =AM17-AL17 -> -25.37 | AP17: 45748 | AQ17: =100*((AT17/AT13)-1) -> 4.0731328 | AR17: =100*((AU17/AU13)-1) -> 4.1253998 | AS17: =AR17-AQ17 -> 0.052266962 | AT17: =DataQ!R216 -> 10410.04 | AU17: =AT17*AX17/AY17 -> 10415.268 | AV17: =AU17-AT17 -> 5.2280656 | AX17: =DataQ!U216 -> 10399.2 | AY17: =DataQ!AA216 -> 10393.98 | AZ17: =AY17-AX17 -> -5.22 | BB17: =RANK(BE17,$BE$4:$BE$22) -> 15 | BC17: Administrative services | BD17: ='ASHE Annual pay All SIC'!H106 -> 7394 | BE17: ='ASHE Annual pay All SIC'!J106 -> 15239 | BF17: ='ASHE Annual pay All SIC'!D106 -> 26803 | BG17: ='ASHE Annual pay All SIC'!O106 -> 40000 | BH17: =+BH16+1 -> 14.5 | BJ17: 14 | BK17: =VLOOKUP($BJ17,$BB$4:$BG$22,2,FALSE) -> Agriculture | BL17: =VLOOKUP($BJ17,$BB$4:$BG$22,3,FALSE) -> 9753 | BM17: =VLOOKUP($BJ17,$BB$4:$BG$22,4,FALSE) -> 18000 | BN17: =VLOOKUP($BJ17,$BB$4:$BG$22,5,FALSE) -> 27288 | BO17: =VLOOKUP($BJ17,$BB$4:$BG$22,6,FALSE) -> 36266 | BP17: =+BP16+1 -> 14.5 | BR17: Administrative services | BS17: =BD17 -> 7394 | BT17: =BE17-BS17 -> 7845 | BU17: =BF17-BT17 -> 18958 | BV17: =BG17-BU17 -> 21042 | BW17: =+BW16+1 -> 13.5 | FZ17: 37712 | GA17: =100*((HAVERQ!S101/HAVERQ!S97)-1) -> 0.94348927 | GB17: =MIN(GI16:GJ16) -> -0.66977625 | GC17: =+GF17-GB17 -> 0.1163958 | GD17: =AVERAGE(GB17,GF17) -> -0.61157835 | GF17: =MAX(GI16:GJ16) -> -0.55338045 | GH17: 37712 | GI17: =(GL17-GI$1)/GI$2 -> -0.39135629 | GJ17: =(GM17-GJ$1)/GJ$2 -> -0.69616021 | GL17: =(HAVERQ!BJ101*HAVERQ!$BJ$1)+(HAVERQ!BK101*HAVERQ!$BK$1) -> 13.756215 | GM17: =(HAVERQ!BL101*HAVERQ!$BL$1)+(HAVERQ!BM101*HAVERQ!$BM$1)+(HAVERQ!BN101*HAVERQ!$BN$1)+(HAVERQ!BO101*HAVERQ!$BO$1) -> -4.0324578 | GR17: 37712 | GS17: =100*(HAVERQ!BP101/HAVERQ!BR101) -> 25.268379 | GT17: =AVERAGE($GS$4:$GS$103) -> 24.605137 | GV17: 37712 | GW17: =100*(HAVERQ!BP101/HAVERQ!BR101) -> 25.268379 | GX17: =100*((DataQ!F132/DataQ!F128)-1) -> 3.882517 | GZ17: 46113 | HA17: =HH17-HH$11 -> 669.22 | HB17: =HI17-HI$11 -> 416.37 | HC17: =HB17-HA17 -> -252.85 | HE17: =100*(HH17/$HH$11) -> 102.01834 | HF17: =100*(HI17/$HI$11) -> 101.23275 | HH17: =DataQ!AE220 -> 33826.13 | HI17: =DataQ!O220 -> 34192.07 | HK17: 46113 | HL17: =HS17-HS$11 -> 617.58 | HM17: =HT17-HT$11 -> 536.12 | HN17: =HM17-HL17 -> -81.46 | HP17: =100*(HS17/HS$11) -> 101.66473 | HQ17: =100*(HT17/HT$11) -> 101.45171 | HS17: =DataQ!AF220 -> 37715.5 | HT17: =DataQ!P220 -> 37466.46
N18: =100*((DataQ!F177/DataQ!F173)-1) -> 2.4865872 | O18: =100*(DataQ!I177/DataQ!J177) -> 21.61113 | Y18: 45839 | Z18: =DataQ!Q217 -> 4.512015 | AA18: =Z18+AC18-AD18 -> 4.410825 | AC18: =DataQ!V217 -> 4.322893 | AD18: =DataQ!AB217 -> 4.424083 | AE18: =AD18-AC18 -> 0.10119 | AG18: 45839 | AH18: =DataQ!O217 -> 33891.79 | AI18: =AH18*AL18/AM18 -> 33927.678 | AJ18: =AI18-AH18 -> 35.888377 | AL18: =DataQ!T217 -> 33484.89 | AM18: =DataQ!Z217 -> 33449.47 | AN18: =AM18-AL18 -> -35.42 | AP18: 45839 | AQ18: =100*((AT18/AT14)-1) -> 5.0902574 | AR18: =100*((AU18/AU14)-1) -> 5.1886053 | AS18: =AR18-AQ18 -> 0.098347948 | AT18: =DataQ!R217 -> 10493.32 | AU18: =AT18*AX18/AY18 -> 10503.14 | AV18: =AU18-AT18 -> 9.8200967 | AX18: =DataQ!U217 -> 10470.95 | AY18: =DataQ!AA217 -> 10461.16 | AZ18: =AY18-AX18 -> -9.79 | BB18: =RANK(BE18,$BE$4:$BE$22) -> 9 | BC18: Public admin | BD18: ='ASHE Annual pay All SIC'!H113 -> 16564 | BE18: ='ASHE Annual pay All SIC'!J113 -> 26528 | BF18: ='ASHE Annual pay All SIC'!D113 -> 36109 | BG18: ='ASHE Annual pay All SIC'!O113 -> 47310 | BH18: =+BH17+1 -> 15.5 | BJ18: 15 | BK18: =VLOOKUP($BJ18,$BB$4:$BG$22,2,FALSE) -> Administrative services | BL18: =VLOOKUP($BJ18,$BB$4:$BG$22,3,FALSE) -> 7394 | BM18: =VLOOKUP($BJ18,$BB$4:$BG$22,4,FALSE) -> 15239 | BN18: =VLOOKUP($BJ18,$BB$4:$BG$22,5,FALSE) -> 26803 | BO18: =VLOOKUP($BJ18,$BB$4:$BG$22,6,FALSE) -> 40000 | BP18: =+BP17+1 -> 15.5 | BR18: Public admin | BS18: =BD18 -> 16564 | BT18: =BE18-BS18 -> 9964 | BU18: =BF18-BT18 -> 26145 | BV18: =BG18-BU18 -> 21165 | BW18: =+BW17+1 -> 14.5 | FZ18: 37803 | GA18: =100*((HAVERQ!S102/HAVERQ!S98)-1) -> 1.2161143 | GB18: =MIN(GI17:GJ17) -> -0.69616021 | GC18: =+GF18-GB18 -> 0.30480392 | GD18: =AVERAGE(GB18,GF18) -> -0.54375825 | GF18: =MAX(GI17:GJ17) -> -0.39135629 | GH18: 37803 | GI18: =(GL18-GI$1)/GI$2 -> -0.10911133 | GJ18: =(GM18-GJ$1)/GJ$2 -> -0.40960735 | GL18: =(HAVERQ!BJ102*HAVERQ!$BJ$1)+(HAVERQ!BK102*HAVERQ!$BK$1) -> 16.833952 | GM18: =(HAVERQ!BL102*HAVERQ!$BL$1)+(HAVERQ!BM102*HAVERQ!$BM$1)+(HAVERQ!BN102*HAVERQ!$BN$1)+(HAVERQ!BO102*HAVERQ!$BO$1) -> 0.66907557 | GR18: 37803 | GS18: =100*(HAVERQ!BP102/HAVERQ!BR102) -> 25.178479 | GT18: =AVERAGE($GS$4:$GS$103) -> 24.605137 | GV18: 37803 | GW18: =100*(HAVERQ!BP102/HAVERQ!BR102) -> 25.178479 | GX18: =100*((DataQ!F133/DataQ!F129)-1) -> 4.0445545 | GZ18: 46204 | HA18: =HH18-HH$11 -> 770.7 | HB18: =HI18-HI$11 -> 520.66 | HC18: =HB18-HA18 -> -250.04 | HE18: =100*(HH18/$HH$11) -> 102.3244 | HF18: =100*(HI18/$HI$11) -> 101.54152 | HH18: =DataQ!AE221 -> 33927.61 | HI18: =DataQ!O221 -> 34296.36 | HK18: 46204 | HL18: =HS18-HS$11 -> 710.73 | HM18: =HT18-HT$11 -> 644.78 | HN18: =HM18-HL18 -> -65.95 | HP18: =100*(HS18/HS$11) -> 101.91582 | HQ18: =100*(HT18/HT$11) -> 101.74594 | HS18: =DataQ!AF221 -> 37808.65 | HT18: =DataQ!P221 -> 37575.12
N19: =100*((DataQ!F178/DataQ!F174)-1) -> 1.9929284 | O19: =100*(DataQ!I178/DataQ!J178) -> 22.060521 | Y19: 45931 | Z19: =DataQ!Q218 -> 4.502531 | AA19: =Z19+AC19-AD19 -> 4.370104 | AC19: =DataQ!V218 -> 4.284726 | AD19: =DataQ!AB218 -> 4.417153 | AE19: =AD19-AC19 -> 0.132427 | AG19: 45931 | AH19: =DataQ!O218 -> 33987.77 | AI19: =AH19*AL19/AM19 -> 34034.891 | AJ19: =AI19-AH19 -> 47.121318 | AL19: =DataQ!T218 -> 33600.57 | AM19: =DataQ!Z218 -> 33554.05 | AN19: =AM19-AL19 -> -46.52 | AP19: 45931 | AQ19: =100*((AT19/AT15)-1) -> 3.7508984 | AR19: =100*((AU19/AU15)-1) -> 3.8928145 | AS19: =AR19-AQ19 -> 0.14191607 | AT19: =DataQ!R218 -> 10566.78 | AU19: =AT19*AX19/AY19 -> 10581.234 | AV19: =AU19-AT19 -> 14.453811 | AX19: =DataQ!U218 -> 10541.84 | AY19: =DataQ!AA218 -> 10527.44 | AZ19: =AY19-AX19 -> -14.4 | BB19: =RANK(BE19,$BE$4:$BE$22) -> 12 | BC19: Education | BD19: ='ASHE Annual pay All SIC'!H115 -> 10561 | BE19: ='ASHE Annual pay All SIC'!J115 -> 19555 | BF19: ='ASHE Annual pay All SIC'!D115 -> 31094 | BG19: ='ASHE Annual pay All SIC'!O115 -> 44533 | BH19: =+BH18+1 -> 16.5 | BJ19: 16 | BK19: =VLOOKUP($BJ19,$BB$4:$BG$22,2,FALSE) -> Wholesale & retail | BL19: =VLOOKUP($BJ19,$BB$4:$BG$22,3,FALSE) -> 9031 | BM19: =VLOOKUP($BJ19,$BB$4:$BG$22,4,FALSE) -> 15193 | BN19: =VLOOKUP($BJ19,$BB$4:$BG$22,5,FALSE) -> 25560 | BO19: =VLOOKUP($BJ19,$BB$4:$BG$22,6,FALSE) -> 37000 | BP19: =+BP18+1 -> 16.5 | BR19: Education | BS19: =BD19 -> 10561 | BT19: =BE19-BS19 -> 8994 | BU19: =BF19-BT19 -> 22100 | BV19: =BG19-BU19 -> 22433 | BW19: =+BW18+1 -> 15.5 | FZ19: 37895 | GA19: =100*((HAVERQ!S103/HAVERQ!S99)-1) -> 1.3481156 | GB19: =MIN(GI18:GJ18) -> -0.40960735 | GC19: =+GF19-GB19 -> 0.30049602 | GD19: =AVERAGE(GB19,GF19) -> -0.25935934 | GF19: =MAX(GI18:GJ18) -> -0.10911133 | GH19: 37895 | GI19: =(GL19-GI$1)/GI$2 -> -0.22220327 | GJ19: =(GM19-GJ$1)/GJ$2 -> -0.80139648 | GL19: =(HAVERQ!BJ103*HAVERQ!$BJ$1)+(HAVERQ!BK103*HAVERQ!$BK$1) -> 15.600742 | GM19: =(HAVERQ!BL103*HAVERQ!$BL$1)+(HAVERQ!BM103*HAVERQ!$BM$1)+(HAVERQ!BN103*HAVERQ!$BN$1)+(HAVERQ!BO103*HAVERQ!$BO$1) -> -5.7590916 | GR19: 37895 | GS19: =100*(HAVERQ!BP103/HAVERQ!BR103) -> 24.53782 | GT19: =AVERAGE($GS$4:$GS$103) -> 24.605137 | GV19: 37895 | GW19: =100*(HAVERQ!BP103/HAVERQ!BR103) -> 24.53782 | GX19: =100*((DataQ!F134/DataQ!F130)-1) -> 4.8799041 | GZ19: 46296 | HA19: =HH19-HH$11 -> 870.77 | HB19: =HI19-HI$11 -> 623.53 | HC19: =HB19-HA19 -> -247.24 | HE19: =100*(HH19/$HH$11) -> 102.62621 | HF19: =100*(HI19/$HI$11) -> 101.84609 | HH19: =DataQ!AE222 -> 34027.68 | HI19: =DataQ!O222 -> 34399.23 | HK19: 46296 | HL19: =HS19-HS$11 -> 802.24 | HM19: =HT19-HT$11 -> 755.62 | HN19: =HM19-HL19 -> -46.62 | HP19: =100*(HS19/HS$11) -> 102.16249 | HQ19: =100*(HT19/HT$11) -> 102.04607 | HS19: =DataQ!AF222 -> 37900.16 | HT19: =DataQ!P222 -> 37685.96
M20: 2016 | N20: =100*((DataQ!F179/DataQ!F175)-1) -> 1.5236579 | O20: =100*(DataQ!I179/DataQ!J179) -> 21.961555 | Y20: 46023 | Z20: =DataQ!Q219 -> 4.483452 | AA20: =Z20+AC20-AD20 -> 4.334413 | AC20: =DataQ!V219 -> 4.2179 | AD20: =DataQ!AB219 -> 4.366939 | AE20: =AD20-AC20 -> 0.149039 | AG20: 46023 | AH20: =DataQ!O219 -> 34094.86 | AI20: =AH20*AL20/AM20 -> 34147.994 | AJ20: =AI20-AH20 -> 53.134015 | AL20: =DataQ!T219 -> 33714.82 | AM20: =DataQ!Z219 -> 33662.36 | AN20: =AM20-AL20 -> -52.46 | AP20: 46023 | AQ20: =100*((AT20/AT16)-1) -> 3.4427313 | AR20: =100*((AU20/AU16)-1) -> 3.6184941 | AS20: =AR20-AQ20 -> 0.17576276 | AT20: =DataQ!R219 -> 10640.74 | AU20: =AT20*AX20/AY20 -> 10658.82 | AV20: =AU20-AT20 -> 18.080012 | AX20: =DataQ!U219 -> 10611.65 | AY20: =DataQ!AA219 -> 10593.65 | AZ20: =AY20-AX20 -> -18 | BB20: =RANK(BE20,$BE$4:$BE$22) -> 13 | BC20: Health | BD20: ='ASHE Annual pay All SIC'!H117 -> 11105 | BE20: ='ASHE Annual pay All SIC'!J117 -> 18893 | BF20: ='ASHE Annual pay All SIC'!D117 -> 28150 | BG20: ='ASHE Annual pay All SIC'!O117 -> 40481 | BH20: =+BH19+1 -> 17.5 | BJ20: 17 | BK20: =VLOOKUP($BJ20,$BB$4:$BG$22,2,FALSE) -> Other services | BL20: =VLOOKUP($BJ20,$BB$4:$BG$22,3,FALSE) -> 7693 | BM20: =VLOOKUP($BJ20,$BB$4:$BG$22,4,FALSE) -> 14665 | BN20: =VLOOKUP($BJ20,$BB$4:$BG$22,5,FALSE) -> 25747 | BO20: =VLOOKUP($BJ20,$BB$4:$BG$22,6,FALSE) -> 36952 | BP20: =+BP19+1 -> 17.5 | BR20: Health | BS20: =BD20 -> 11105 | BT20: =BE20-BS20 -> 7788 | BU20: =BF20-BT20 -> 20362 | BV20: =BG20-BU20 -> 20119 | BW20: =+BW19+1 -> 16.5 | FZ20: 37987 | GA20: =100*((HAVERQ!S104/HAVERQ!S100)-1) -> 1.4508892 | GB20: =MIN(GI19:GJ19) -> -0.80139648 | GC20: =+GF20-GB20 -> 0.57919321 | GD20: =AVERAGE(GB20,GF20) -> -0.51179988 | GF20: =MAX(GI19:GJ19) -> -0.22220327 | GH20: 37987 | GI20: =(GL20-GI$1)/GI$2 -> 0.71623695 | GJ20: =(GM20-GJ$1)/GJ$2 -> 0.31785502 | GL20: =(HAVERQ!BJ104*HAVERQ!$BJ$1)+(HAVERQ!BK104*HAVERQ!$BK$1) -> 25.833952 | GM20: =(HAVERQ!BL104*HAVERQ!$BL$1)+(HAVERQ!BM104*HAVERQ!$BM$1)+(HAVERQ!BN104*HAVERQ!$BN$1)+(HAVERQ!BO104*HAVERQ!$BO$1) -> 12.604705 | GR20: 37987 | GS20: =100*(HAVERQ!BP104/HAVERQ!BR104) -> 23.526333 | GT20: =AVERAGE($GS$4:$GS$103) -> 24.605137 | GV20: 37987 | GW20: =100*(HAVERQ!BP104/HAVERQ!BR104) -> 23.526333 | GX20: =100*((DataQ!F135/DataQ!F131)-1) -> 4.4804438
N21: =100*((DataQ!F180/DataQ!F176)-1) -> 2.6310611 | O21: =100*(DataQ!I180/DataQ!J180) -> 21.599725 | Y21: 46113 | Z21: =DataQ!Q220 -> 4.473944 | AA21: =Z21+AC21-AD21 -> 4.318119 | AC21: =DataQ!V220 -> 4.151092 | AD21: =DataQ!AB220 -> 4.306917 | AE21: =AD21-AC21 -> 0.155825 | AG21: 46113 | AH21: =DataQ!O220 -> 34192.07 | AI21: =AH21*AL21/AM21 -> 34247.756 | AJ21: =AI21-AH21 -> 55.68558 | AL21: =DataQ!T220 -> 33826.11 | AM21: =DataQ!Z220 -> 33771.11 | AN21: =AM21-AL21 -> -55 | AP21: 46113 | AQ21: =100*((AT21/AT17)-1) -> 2.911228 | AR21: =100*((AU21/AU17)-1) -> 3.0563066 | AS21: =AR21-AQ21 -> 0.14507856 | AT21: =DataQ!R220 -> 10713.1 | AU21: =AT21*AX21/AY21 -> 10733.591 | AV21: =AU21-AT21 -> 20.490587 | AX21: =DataQ!U220 -> 10680.9 | AY21: =DataQ!AA220 -> 10660.51 | AZ21: =AY21-AX21 -> -20.39 | BB21: =RANK(BE21,$BE$4:$BE$22) -> 18 | BC21: Art & recreation | BD21: ='ASHE Annual pay All SIC'!H121 -> 3691 | BE21: ='ASHE Annual pay All SIC'!J121 -> 10437 | BF21: ='ASHE Annual pay All SIC'!D121 -> 23786 | BG21: ='ASHE Annual pay All SIC'!O121 -> 34323 | BH21: =+BH20+1 -> 18.5 | BJ21: 18 | BK21: =VLOOKUP($BJ21,$BB$4:$BG$22,2,FALSE) -> Art & recreation | BL21: =VLOOKUP($BJ21,$BB$4:$BG$22,3,FALSE) -> 3691 | BM21: =VLOOKUP($BJ21,$BB$4:$BG$22,4,FALSE) -> 10437 | BN21: =VLOOKUP($BJ21,$BB$4:$BG$22,5,FALSE) -> 23786 | BO21: =VLOOKUP($BJ21,$BB$4:$BG$22,6,FALSE) -> 34323 | BP21: =+BP20+1 -> 18.5 | BR21: Art & recreation | BS21: =BD21 -> 3691 | BT21: =BE21-BS21 -> 6746 | BU21: =BF21-BT21 -> 17040 | BV21: =BG21-BU21 -> 17283 | BW21: =+BW20+1 -> 17.5 | FZ21: 38078 | GA21: =100*((HAVERQ!S105/HAVERQ!S101)-1) -> 1.0551684 | GB21: =MIN(GI20:GJ20) -> 0.31785502 | GC21: =+GF21-GB21 -> 0.39838193 | GD21: =AVERAGE(GB21,GF21) -> 0.51704599 | GF21: =MAX(GI20:GJ20) -> 0.71623695 | GH21: 38078 | GI21: =(GL21-GI$1)/GI$2 -> 0.98422419 | GJ21: =(GM21-GJ$1)/GJ$2 -> 0.12719382 | GL21: =(HAVERQ!BJ105*HAVERQ!$BJ$1)+(HAVERQ!BK105*HAVERQ!$BK$1) -> 28.756215 | GM21: =(HAVERQ!BL105*HAVERQ!$BL$1)+(HAVERQ!BM105*HAVERQ!$BM$1)+(HAVERQ!BN105*HAVERQ!$BN$1)+(HAVERQ!BO105*HAVERQ!$BO$1) -> 9.4764859 | GR21: 38078 | GS21: =100*(HAVERQ!BP105/HAVERQ!BR105) -> 24.977399 | GT21: =AVERAGE($GS$4:$GS$103) -> 24.605137 | GV21: 38078 | GW21: =100*(HAVERQ!BP105/HAVERQ!BR105) -> 24.977399 | GX21: =100*((DataQ!F136/DataQ!F132)-1) -> 3.7992269
N22: =100*((DataQ!F181/DataQ!F177)-1) -> 2.2021638 | O22: =100*(DataQ!I181/DataQ!J181) -> 22.110978 | Y22: 46204 | Z22: =DataQ!Q221 -> 4.459678 | AA22: =Z22+AC22-AD22 -> 4.306159 | AC22: =DataQ!V221 -> 4.093759 | AD22: =DataQ!AB221 -> 4.247278 | AE22: =AD22-AC22 -> 0.153519 | AG22: 46204 | AH22: =DataQ!O221 -> 34296.36 | AI22: =AH22*AL22/AM22 -> 34351.348 | AJ22: =AI22-AH22 -> 54.988353 | AL22: =DataQ!T221 -> 33927.58 | AM22: =DataQ!Z221 -> 33873.27 | AN22: =AM22-AL22 -> -54.31 | AP22: 46204 | AQ22: =100*((AT22/AT18)-1) -> 2.7887265 | AR22: =100*((AU22/AU18)-1) -> 2.8982267 | AS22: =AR22-AQ22 -> 0.10950011 | AT22: =DataQ!R221 -> 10785.95 | AU22: =AT22*AX22/AY22 -> 10807.545 | AV22: =AU22-AT22 -> 21.594902 | AX22: =DataQ!U221 -> 10750.04 | AY22: =DataQ!AA221 -> 10728.56 | AZ22: =AY22-AX22 -> -21.48 | BB22: =RANK(BE22,$BE$4:$BE$22) -> 17 | BC22: Other services | BD22: ='ASHE Annual pay All SIC'!H126 -> 7693 | BE22: ='ASHE Annual pay All SIC'!J126 -> 14665 | BF22: ='ASHE Annual pay All SIC'!D126 -> 25747 | BG22: ='ASHE Annual pay All SIC'!O126 -> 36952 | BH22: =+BH21+1 -> 19.5 | BJ22: 19 | BK22: =VLOOKUP($BJ22,$BB$4:$BG$22,2,FALSE) -> Accommodation & food | BL22: =VLOOKUP($BJ22,$BB$4:$BG$22,3,FALSE) -> 4239 | BM22: =VLOOKUP($BJ22,$BB$4:$BG$22,4,FALSE) -> 8951 | BN22: =VLOOKUP($BJ22,$BB$4:$BG$22,5,FALSE) -> 16800 | BO22: =VLOOKUP($BJ22,$BB$4:$BG$22,6,FALSE) -> 27056 | BP22: =+BP21+1 -> 19.5 | BR22: Other services | BS22: =BD22 -> 7693 | BT22: =BE22-BS22 -> 6972 | BU22: =BF22-BT22 -> 18775 | BV22: =BG22-BU22 -> 18177 | BW22: =+BW21+1 -> 18.5 | FZ22: 38169 | GA22: =100*((HAVERQ!S106/HAVERQ!S102)-1) -> 0.60560917 | GB22: =MIN(GI21:GJ21) -> 0.12719382 | GC22: =+GF22-GB22 -> 0.85703037 | GD22: =AVERAGE(GB22,GF22) -> 0.555709 | GF22: =MAX(GI21:GJ21) -> 0.98422419 | GH22: 38169 | GI22: =(GL22-GI$1)/GI$2 -> 0.08855711 | GJ22: =(GM22-GJ$1)/GJ$2 -> 0.64237175 | GL22: =(HAVERQ!BJ106*HAVERQ!$BJ$1)+(HAVERQ!BK106*HAVERQ!$BK$1) -> 18.989425 | GM22: =(HAVERQ!BL106*HAVERQ!$BL$1)+(HAVERQ!BM106*HAVERQ!$BM$1)+(HAVERQ!BN106*HAVERQ!$BN$1)+(HAVERQ!BO106*HAVERQ!$BO$1) -> 17.929119 | GR22: 38169 | GS22: =100*(HAVERQ!BP106/HAVERQ!BR106) -> 24.186306 | GT22: =AVERAGE($GS$4:$GS$103) -> 24.605137 | GV22: 38169 | GW22: =100*(HAVERQ!BP106/HAVERQ!BR106) -> 24.186306 | GX22: =100*((DataQ!F137/DataQ!F133)-1) -> 2.9573152
N23: =100*((DataQ!F182/DataQ!F178)-1) -> 1.7339906 | O23: =100*(DataQ!I182/DataQ!J182) -> 22.577352 | Y23: 46296 | Z23: =DataQ!Q222 -> 4.435829 | AA23: =Z23+AC23-AD23 -> 4.289327 | AC23: =DataQ!V222 -> 4.045897 | AD23: =DataQ!AB222 -> 4.192399 | AE23: =AD23-AC23 -> 0.146502 | AG23: 46296 | AH23: =DataQ!O222 -> 34399.23 | AI23: =AH23*AL23/AM23 -> 34451.838 | AJ23: =AI23-AH23 -> 52.607716 | AL23: =DataQ!T222 -> 34027.66 | AM23: =DataQ!Z222 -> 33975.7 | AN23: =AM23-AL23 -> -51.96 | AP23: 46296 | AQ23: =100*((AT23/AT19)-1) -> 2.7699072 | AR23: =100*((AU23/AU19)-1) -> 2.8340884 | AS23: =AR23-AQ23 -> 0.064181223 | AT23: =DataQ!R222 -> 10859.47 | AU23: =AT23*AX23/AY23 -> 10881.115 | AV23: =AU23-AT23 -> 21.645334 | AX23: =DataQ!U222 -> 10818.11 | AY23: =DataQ!AA222 -> 10796.59 | AZ23: =AY23-AX23 -> -21.52 | BH23: =+BH22+1 -> 20.5 | BP23: =+BP22+1 -> 20.5 | BW23: =+BW22+1 -> 19.5 | FZ23: 38261 | GA23: =100*((HAVERQ!S107/HAVERQ!S103)-1) -> 1.0259564 | GB23: =MIN(GI22:GJ22) -> 0.08855711 | GC23: =+GF23-GB23 -> 0.55381464 | GD23: =AVERAGE(GB23,GF23) -> 0.36546443 | GF23: =MAX(GI22:GJ22) -> 0.64237175 | GH23: 38261 | GI23: =(GL23-GI$1)/GI$2 -> -0.017405969 | GJ23: =(GM23-GJ$1)/GJ$2 -> 0.22131829 | GL23: =(HAVERQ!BJ107*HAVERQ!$BJ$1)+(HAVERQ!BK107*HAVERQ!$BK$1) -> 17.833952 | GM23: =(HAVERQ!BL107*HAVERQ!$BL$1)+(HAVERQ!BM107*HAVERQ!$BM$1)+(HAVERQ!BN107*HAVERQ!$BN$1)+(HAVERQ!BO107*HAVERQ!$BO$1) -> 11.020806 | GR23: 38261 | GS23: =100*(HAVERQ!BP107/HAVERQ!BR107) -> 24.557865 | GT23: =AVERAGE($GS$4:$GS$103) -> 24.605137 | GV23: 38261 | GW23: =100*(HAVERQ!BP107/HAVERQ!BR107) -> 24.557865 | GX23: =100*((DataQ!F138/DataQ!F134)-1) -> 0.84362975
M24: 2017 | N24: =100*((DataQ!F183/DataQ!F179)-1) -> 1.7811314 | O24: =100*(DataQ!I183/DataQ!J183) -> 22.554465 | Y24: 46388 | Z24: =DataQ!Q223 -> 4.404385 | AA24: =Z24+AC24-AD24 -> 4.266211 | AC24: =DataQ!V223 -> 3.998046 | AD24: =DataQ!AB223 -> 4.13622 | AE24: =AD24-AC24 -> 0.138174 | AG24: 46388 | AH24: =DataQ!O223 -> 34506.91 | AI24: =AH24*AL24/AM24 -> 34556.649 | AJ24: =AI24-AH24 -> 49.739384 | AL24: =DataQ!T223 -> 34126.33 | AM24: =DataQ!Z223 -> 34077.21 | AN24: =AM24-AL24 -> -49.12 | AP24: 46388 | AQ24: =100*((AT24/AT20)-1) -> 2.7464255 | AR24: =100*((AU24/AU20)-1) -> 2.7697978 | AS24: =AR24-AQ24 -> 0.023372313 | AT24: =DataQ!R223 -> 10932.98 | AU24: =AT24*AX24/AY24 -> 10954.048 | AV24: =AU24-AT24 -> 21.067779 | AX24: =DataQ!U223 -> 10887.61 | AY24: =DataQ!AA223 -> 10866.67 | AZ24: =AY24-AX24 -> -20.94 | BC24: Total | BD24: ='ASHE Annual pay All SIC'!H6 -> 11004 | BE24: ='ASHE Annual pay All SIC'!J6 -> 21216 | BF24: ='ASHE Annual pay All SIC'!D6 -> 31602 | BG24: ='ASHE Annual pay All SIC'!O6 -> 46084 | BH24: =+BH23+1 -> 21.5 | BK24: =BC24 -> Total | BL24: =BD24 -> 11004 | BM24: =BE24 -> 21216 | BN24: =BF24 -> 31602 | BO24: =BG24 -> 46084 | BP24: =+BP23+1 -> 21.5 | BR24: Total | BS24: =BD24 -> 11004 | BT24: =BE24-BS24 -> 10212 | BU24: =BF24-BT24 -> 21390 | BV24: =BG24-BU24 -> 24694 | BW24: =+BW23+1 -> 20.5 | FZ24: 38353 | GA24: =100*((HAVERQ!S108/HAVERQ!S104)-1) -> 1.2170713 | GB24: =MIN(GI23:GJ23) -> -0.017405969 | GC24: =+GF24-GB24 -> 0.23872426 | GD24: =AVERAGE(GB24,GF24) -> 0.10195616 | GF24: =MAX(GI23:GJ23) -> 0.22131829 | GH24: 38353 | GI24: =(GL24-GI$1)/GI$2 -> 0.78752552 | GJ24: =(GM24-GJ$1)/GJ$2 -> 0.56822104 | GL24: =(HAVERQ!BJ108*HAVERQ!$BJ$1)+(HAVERQ!BK108*HAVERQ!$BK$1) -> 26.611317 | GM24: =(HAVERQ!BL108*HAVERQ!$BL$1)+(HAVERQ!BM108*HAVERQ!$BM$1)+(HAVERQ!BN108*HAVERQ!$BN$1)+(HAVERQ!BO108*HAVERQ!$BO$1) -> 16.712513 | GR24: 38353 | GS24: =100*(HAVERQ!BP108/HAVERQ!BR108) -> 23.978383 | GT24: =AVERAGE($GS$4:$GS$103) -> 24.605137 | GV24: 38353 | GW24: =100*(HAVERQ!BP108/HAVERQ!BR108) -> 23.978383 | GX24: =100*((DataQ!F139/DataQ!F135)-1) -> 2.2525081
N25: =100*((DataQ!F184/DataQ!F180)-1) -> 1.3309109 | O25: =100*(DataQ!I184/DataQ!J184) -> 22.210696 | Y25: 46478 | Z25: =DataQ!Q224 -> 4.356714 | AA25: =Z25+AC25-AD25 -> 4.225626 | AC25: =DataQ!V224 -> 3.959662 | AD25: =DataQ!AB224 -> 4.09075 | AE25: =AD25-AC25 -> 0.131088 | AG25: 46478 | AH25: =DataQ!O224 -> 34617.35 | AI25: =AH25*AL25/AM25 -> 34664.66 | AJ25: =AI25-AH25 -> 47.309574 | AL25: =DataQ!T224 -> 34225.34 | AM25: =DataQ!Z224 -> 34178.63 | AN25: =AM25-AL25 -> -46.71 | AP25: 46478 | AQ25: =100*((AT25/AT21)-1) -> 2.7315156 | AR25: =100*((AU25/AU21)-1) -> 2.7242088 | AS25: =AR25-AQ25 -> -0.0073068128 | AT25: =DataQ!R224 -> 11005.73 | AU25: =AT25*AX25/AY25 -> 11025.996 | AV25: =AU25-AT25 -> 20.266007 | AX25: =DataQ!U224 -> 10957.44 | AY25: =DataQ!AA224 -> 10937.3 | AZ25: =AY25-AX25 -> -20.14 | FZ25: 38443 | GA25: =100*((HAVERQ!S109/HAVERQ!S105)-1) -> 1.1956171 | GB25: =MIN(GI24:GJ24) -> 0.56822104 | GC25: =+GF25-GB25 -> 0.21930449 | GD25: =AVERAGE(GB25,GF25) -> 0.67787328 | GF25: =MAX(GI24:GJ24) -> 0.78752552 | GH25: 38443 | GI25: =(GL25-GI$1)/GI$2 -> -0.36996972 | GJ25: =(GM25-GJ$1)/GJ$2 -> 0.36537412 | GL25: =(HAVERQ!BJ109*HAVERQ!$BJ$1)+(HAVERQ!BK109*HAVERQ!$BK$1) -> 13.989425 | GM25: =(HAVERQ!BL109*HAVERQ!$BL$1)+(HAVERQ!BM109*HAVERQ!$BM$1)+(HAVERQ!BN109*HAVERQ!$BN$1)+(HAVERQ!BO109*HAVERQ!$BO$1) -> 13.384361 | GR25: 38443 | GS25: =100*(HAVERQ!BP109/HAVERQ!BR109) -> 25.25845 | GT25: =AVERAGE($GS$4:$GS$103) -> 24.605137 | GV25: 38443 | GW25: =100*(HAVERQ!BP109/HAVERQ!BR109) -> 25.25845 | GX25: =100*((DataQ!F140/DataQ!F136)-1) -> 2.4903054
N26: =100*((DataQ!F185/DataQ!F181)-1) -> 0.72085025 | O26: =100*(DataQ!I185/DataQ!J185) -> 22.087185 | Y26: 46569 | Z26: =DataQ!Q225 -> 4.301379 | AA26: =Z26+AC26-AD26 -> 4.177982 | AC26: =DataQ!V225 -> 3.921238 | AD26: =DataQ!AB225 -> 4.044635 | AE26: =AD26-AC26 -> 0.123397 | AG26: 46569 | AH26: =DataQ!O225 -> 34725.69 | AI26: =AH26*AL26/AM26 -> 34770.345 | AJ26: =AI26-AH26 -> 44.654615 | AL26: =DataQ!T225 -> 34322.92 | AM26: =DataQ!Z225 -> 34278.84 | AN26: =AM26-AL26 -> -44.08 | AP26: 46569 | AQ26: =100*((AT26/AT22)-1) -> 2.7144572 | AR26: =100*((AU26/AU22)-1) -> 2.6879121 | AS26: =AR26-AQ26 -> -0.02654509 | AT26: =DataQ!R225 -> 11078.73 | AU26: =AT26*AX26/AY26 -> 11098.042 | AV26: =AU26-AT26 -> 19.312214 | AX26: =DataQ!U225 -> 11027.81 | AY26: =DataQ!AA225 -> 11008.62 | AZ26: =AY26-AX26 -> -19.19 | FZ26: 38534 | GA26: =100*((HAVERQ!S110/HAVERQ!S106)-1) -> 1.5387092 | GB26: =MIN(GI25:GJ25) -> -0.36996972 | GC26: =+GF26-GB26 -> 0.73534384 | GD26: =AVERAGE(GB26,GF26) -> -0.0022977979 | GF26: =MAX(GI25:GJ25) -> 0.36537412 | GH26: 38534 | GI26: =(GL26-GI$1)/GI$2 -> -0.080595906 | GJ26: =(GM26-GJ$1)/GJ$2 -> -0.16108523 | GL26: =(HAVERQ!BJ110*HAVERQ!$BJ$1)+(HAVERQ!BK110*HAVERQ!$BK$1) -> 17.144898 | GM26: =(HAVERQ!BL110*HAVERQ!$BL$1)+(HAVERQ!BM110*HAVERQ!$BM$1)+(HAVERQ!BN110*HAVERQ!$BN$1)+(HAVERQ!BO110*HAVERQ!$BO$1) -> 4.7466306 | GR26: 38534 | GS26: =100*(HAVERQ!BP110/HAVERQ!BR110) -> 24.699612 | GT26: =AVERAGE($GS$4:$GS$103) -> 24.605137 | GV26: 38534 | GW26: =100*(HAVERQ!BP110/HAVERQ!BR110) -> 24.699612 | GX26: =100*((DataQ!F141/DataQ!F137)-1) -> 2.8823212
N27: =100*((DataQ!F186/DataQ!F182)-1) -> 1.1563939 | O27: =100*(DataQ!I186/DataQ!J186) -> 22.839615 | Y27: 46661 | Z27: =DataQ!Q226 -> 4.251255 | AA27: =Z27+AC27-AD27 -> 4.135245 | AC27: =DataQ!V226 -> 3.882746 | AD27: =DataQ!AB226 -> 3.998756 | AE27: =AD27-AC27 -> 0.11601 | AG27: 46661 | AH27: =DataQ!O226 -> 34830.73 | AI27: =AH27*AL27/AM27 -> 34872.819 | AJ27: =AI27-AH27 -> 42.089356 | AL27: =DataQ!T226 -> 34425.94 | AM27: =DataQ!Z226 -> 34384.39 | AN27: =AM27-AL27 -> -41.55 | AP27: 46661 | AQ27: =100*((AT27/AT23)-1) -> 2.6922124 | AR27: =100*((AU27/AU23)-1) -> 2.6561919 | AS27: =AR27-AQ27 -> -0.036020559 | AT27: =DataQ!R226 -> 11151.83 | AU27: =AT27*AX27/AY27 -> 11170.139 | AV27: =AU27-AT27 -> 18.308634 | AX27: =DataQ!U226 -> 11097.76 | AY27: =DataQ!AA226 -> 11079.57 | AZ27: =AY27-AX27 -> -18.19 | FZ27: 38626 | GA27: =100*((HAVERQ!S111/HAVERQ!S107)-1) -> 1.3390998 | GB27: =MIN(GI26:GJ26) -> -0.16108523 | GC27: =+GF27-GB27 -> 0.080489325 | GD27: =AVERAGE(GB27,GF27) -> -0.12084057 | GF27: =MAX(GI26:GJ26) -> -0.080595906 | GH27: 38626 | GI27: =(GL27-GI$1)/GI$2 -> -0.26400664 | GJ27: =(GM27-GJ$1)/GJ$2 -> -0.099608333 | GL27: =(HAVERQ!BJ111*HAVERQ!$BJ$1)+(HAVERQ!BK111*HAVERQ!$BK$1) -> 15.144898 | GM27: =(HAVERQ!BL111*HAVERQ!$BL$1)+(HAVERQ!BM111*HAVERQ!$BM$1)+(HAVERQ!BN111*HAVERQ!$BN$1)+(HAVERQ!BO111*HAVERQ!$BO$1) -> 5.7552951 | GR27: 38626 | GS27: =100*(HAVERQ!BP111/HAVERQ!BR111) -> 25.487953 | GT27: =AVERAGE($GS$4:$GS$103) -> 24.605137 | GV27: 38626 | GW27: =100*(HAVERQ!BP111/HAVERQ!BR111) -> 25.487953 | GX27: =100*((DataQ!F142/DataQ!F138)-1) -> 5.6848524
M28: 2018 | N28: =100*((DataQ!F187/DataQ!F183)-1) -> 2.5453424 | O28: =100*(DataQ!I187/DataQ!J187) -> 21.870311 | FZ28: 38718 | GA28: =100*((HAVERQ!S112/HAVERQ!S108)-1) -> 1.1131311 | GB28: =MIN(GI27:GJ27) -> -0.26400664 | GC28: =+GF28-GB28 -> 0.1643983 | GD28: =AVERAGE(GB28,GF28) -> -0.18180748 | GF28: =MAX(GI27:GJ27) -> -0.099608333 | GH28: 38718 | GI28: =(GL28-GI$1)/GI$2 -> 0.71623695 | GJ28: =(GM28-GJ$1)/GJ$2 -> 0.31897616 | GL28: =(HAVERQ!BJ112*HAVERQ!$BJ$1)+(HAVERQ!BK112*HAVERQ!$BK$1) -> 25.833952 | GM28: =(HAVERQ!BL112*HAVERQ!$BL$1)+(HAVERQ!BM112*HAVERQ!$BM$1)+(HAVERQ!BN112*HAVERQ!$BN$1)+(HAVERQ!BO112*HAVERQ!$BO$1) -> 12.623099 | GR28: 38718 | GS28: =100*(HAVERQ!BP112/HAVERQ!BR112) -> 23.950713 | GT28: =AVERAGE($GS$4:$GS$103) -> 24.605137 | GV28: 38718 | GW28: =100*(HAVERQ!BP112/HAVERQ!BR112) -> 23.950713 | GX28: =100*((DataQ!F143/DataQ!F139)-1) -> 4.2592502
N29: =100*((DataQ!F188/DataQ!F184)-1) -> 1.4605074 | O29: =100*(DataQ!I188/DataQ!J188) -> 22.015766 | FZ29: 38808 | GA29: =100*((HAVERQ!S113/HAVERQ!S109)-1) -> 1.2929525 | GB29: =MIN(GI28:GJ28) -> 0.31897616 | GC29: =+GF29-GB29 -> 0.39726079 | GD29: =AVERAGE(GB29,GF29) -> 0.51760656 | GF29: =MAX(GI28:GJ28) -> 0.71623695 | GH29: 38808 | GI29: =(GL29-GI$1)/GI$2 -> 0.44112086 | GJ29: =(GM29-GJ$1)/GJ$2 -> -0.48603436 | GL29: =(HAVERQ!BJ113*HAVERQ!$BJ$1)+(HAVERQ!BK113*HAVERQ!$BK$1) -> 22.833952 | GM29: =(HAVERQ!BL113*HAVERQ!$BL$1)+(HAVERQ!BM113*HAVERQ!$BM$1)+(HAVERQ!BN113*HAVERQ!$BN$1)+(HAVERQ!BO113*HAVERQ!$BO$1) -> -0.58487854 | GR29: 38808 | GS29: =100*(HAVERQ!BP113/HAVERQ!BR113) -> 25.379889 | GT29: =AVERAGE($GS$4:$GS$103) -> 24.605137 | GV29: 38808 | GW29: =100*(HAVERQ!BP113/HAVERQ!BR113) -> 25.379889 | GX29: =100*((DataQ!F144/DataQ!F140)-1) -> 4.8015293
N30: =100*((DataQ!F189/DataQ!F185)-1) -> 3.0151689 | O30: =100*(DataQ!I189/DataQ!J189) -> 21.743782 | FZ30: 38899 | GA30: =100*((HAVERQ!S114/HAVERQ!S110)-1) -> 1.2934724 | GB30: =MIN(GI29:GJ29) -> -0.48603436 | GC30: =+GF30-GB30 -> 0.92715522 | GD30: =AVERAGE(GB30,GF30) -> -0.022456752 | GF30: =MAX(GI29:GJ29) -> 0.44112086 | GH30: 38899 | GI30: =(GL30-GI$1)/GI$2 -> 0.96283762 | GJ30: =(GM30-GJ$1)/GJ$2 -> 0.54167556 | GL30: =(HAVERQ!BJ114*HAVERQ!$BJ$1)+(HAVERQ!BK114*HAVERQ!$BK$1) -> 28.523006 | GM30: =(HAVERQ!BL114*HAVERQ!$BL$1)+(HAVERQ!BM114*HAVERQ!$BM$1)+(HAVERQ!BN114*HAVERQ!$BN$1)+(HAVERQ!BO114*HAVERQ!$BO$1) -> 16.276976 | GR30: 38899 | GS30: =100*(HAVERQ!BP114/HAVERQ!BR114) -> 24.980084 | GT30: =AVERAGE($GS$4:$GS$103) -> 24.605137 | GV30: 38899 | GW30: =100*(HAVERQ!BP114/HAVERQ!BR114) -> 24.980084 | GX30: =100*((DataQ!F145/DataQ!F141)-1) -> 4.9529406
N31: =100*((DataQ!F190/DataQ!F186)-1) -> 4.2156007 | O31: =100*(DataQ!I190/DataQ!J190) -> 21.46495 | FZ31: 38991 | GA31: =100*((HAVERQ!S115/HAVERQ!S111)-1) -> 1.38463 | GB31: =MIN(GI30:GJ30) -> 0.54167556 | GC31: =+GF31-GB31 -> 0.42116206 | GD31: =AVERAGE(GB31,GF31) -> 0.75225659 | GF31: =MAX(GI30:GJ30) -> 0.96283762 | GH31: 38991 | GI31: =(GL31-GI$1)/GI$2 -> 0.29335441 | GJ31: =(GM31-GJ$1)/GJ$2 -> 0.40222326 | GL31: =(HAVERQ!BJ115*HAVERQ!$BJ$1)+(HAVERQ!BK115*HAVERQ!$BK$1) -> 21.222635 | GM31: =(HAVERQ!BL115*HAVERQ!$BL$1)+(HAVERQ!BM115*HAVERQ!$BM$1)+(HAVERQ!BN115*HAVERQ!$BN$1)+(HAVERQ!BO115*HAVERQ!$BO$1) -> 13.988952 | GR31: 38991 | GS31: =100*(HAVERQ!BP115/HAVERQ!BR115) -> 23.598797 | GT31: =AVERAGE($GS$4:$GS$103) -> 24.605137 | GV31: 38991 | GW31: =100*(HAVERQ!BP115/HAVERQ!BR115) -> 23.598797 | GX31: =100*((DataQ!F146/DataQ!F142)-1) -> 2.0615974
M32: 2019 | N32: =100*((DataQ!F191/DataQ!F187)-1) -> 2.4656823 | O32: =100*(DataQ!I191/DataQ!J191) -> 21.221907 | FZ32: 39083 | GA32: =100*((HAVERQ!S116/HAVERQ!S112)-1) -> 0.92738628 | GB32: =MIN(GI31:GJ31) -> 0.29335441 | GC32: =+GF32-GB32 -> 0.10886885 | GD32: =AVERAGE(GB32,GF32) -> 0.34778884 | GF32: =MAX(GI31:GJ31) -> 0.40222326 | GH32: 39083 | GI32: =(GL32-GI$1)/GI$2 -> 0.7936846 | GJ32: =(GM32-GJ$1)/GJ$2 -> 1.2397539 | GL32: =(HAVERQ!BJ116*HAVERQ!$BJ$1)+(HAVERQ!BK116*HAVERQ!$BK$1) -> 26.678479 | GM32: =(HAVERQ!BL116*HAVERQ!$BL$1)+(HAVERQ!BM116*HAVERQ!$BM$1)+(HAVERQ!BN116*HAVERQ!$BN$1)+(HAVERQ!BO116*HAVERQ!$BO$1) -> 27.730494 | GR32: 39083 | GS32: =100*(HAVERQ!BP116/HAVERQ!BR116) -> 22.905026 | GT32: =AVERAGE($GS$4:$GS$103) -> 24.605137 | GV32: 39083 | GW32: =100*(HAVERQ!BP116/HAVERQ!BR116) -> 22.905026 | GX32: =100*((DataQ!F147/DataQ!F143)-1) -> 2.2665178
N33: =100*((DataQ!F192/DataQ!F188)-1) -> 4.4057963 | O33: =100*(DataQ!I192/DataQ!J192) -> 21.285047 | FZ33: 39173 | GA33: =100*((HAVERQ!S117/HAVERQ!S113)-1) -> 0.87087748 | GB33: =MIN(GI32:GJ32) -> 0.7936846 | GC33: =+GF33-GB33 -> 0.44606925 | GD33: =AVERAGE(GB33,GF33) -> 1.0167192 | GF33: =MAX(GI32:GJ32) -> 1.2397539 | GH33: 39173 | GI33: =(GL33-GI$1)/GI$2 -> 1.2379537 | GJ33: =(GM33-GJ$1)/GJ$2 -> 0.75435728 | GL33: =(HAVERQ!BJ117*HAVERQ!$BJ$1)+(HAVERQ!BK117*HAVERQ!$BK$1) -> 31.523006 | GM33: =(HAVERQ!BL117*HAVERQ!$BL$1)+(HAVERQ!BM117*HAVERQ!$BM$1)+(HAVERQ!BN117*HAVERQ!$BN$1)+(HAVERQ!BO117*HAVERQ!$BO$1) -> 19.76649 | GR33: 39173 | GS33: =100*(HAVERQ!BP117/HAVERQ!BR117) -> 24.629007 | GT33: =AVERAGE($GS$4:$GS$103) -> 24.605137 | GV33: 39173 | GW33: =100*(HAVERQ!BP117/HAVERQ!BR117) -> 24.629007 | GX33: =100*((DataQ!F148/DataQ!F144)-1) -> 1.7386136
N34: =100*((DataQ!F193/DataQ!F189)-1) -> 2.5605318 | O34: =100*(DataQ!I193/DataQ!J193) -> 22.040536 | FZ34: 39264 | GA34: =100*((HAVERQ!S118/HAVERQ!S114)-1) -> 0.84504397 | GB34: =MIN(GI33:GJ33) -> 0.75435728 | GC34: =+GF34-GB34 -> 0.48359643 | GD34: =AVERAGE(GB34,GF34) -> 0.9961555 | GF34: =MAX(GI33:GJ33) -> 1.2379537 | GH34: 39264 | GI34: =(GL34-GI$1)/GI$2 -> 0.51240943 | GJ34: =(GM34-GJ$1)/GJ$2 -> 0.26034933 | GL34: =(HAVERQ!BJ118*HAVERQ!$BJ$1)+(HAVERQ!BK118*HAVERQ!$BK$1) -> 23.611317 | GM34: =(HAVERQ!BL118*HAVERQ!$BL$1)+(HAVERQ!BM118*HAVERQ!$BM$1)+(HAVERQ!BN118*HAVERQ!$BN$1)+(HAVERQ!BO118*HAVERQ!$BO$1) -> 11.661197 | GR34: 39264 | GS34: =100*(HAVERQ!BP118/HAVERQ!BR118) -> 23.963198 | GT34: =AVERAGE($GS$4:$GS$103) -> 24.605137 | GV34: 39264 | GW34: =100*(HAVERQ!BP118/HAVERQ!BR118) -> 23.963198 | GX34: =100*((DataQ!F149/DataQ!F145)-1) -> 1.3920933
N35: =100*((DataQ!F194/DataQ!F190)-1) -> 1.4104639 | O35: =100*(DataQ!I194/DataQ!J194) -> 22.276662 | FZ35: 39356 | GA35: =100*((HAVERQ!S119/HAVERQ!S115)-1) -> 0.58619937 | GB35: =MIN(GI34:GJ34) -> 0.26034933 | GC35: =+GF35-GB35 -> 0.2520601 | GD35: =AVERAGE(GB35,GF35) -> 0.38637938 | GF35: =MAX(GI34:GJ34) -> 0.51240943 | GH35: 39356 | GI35: =(GL35-GI$1)/GI$2 -> 0.85687454 | GJ35: =(GM35-GJ$1)/GJ$2 -> 0.95220065 | GL35: =(HAVERQ!BJ119*HAVERQ!$BJ$1)+(HAVERQ!BK119*HAVERQ!$BK$1) -> 27.367533 | GM35: =(HAVERQ!BL119*HAVERQ!$BL$1)+(HAVERQ!BM119*HAVERQ!$BM$1)+(HAVERQ!BN119*HAVERQ!$BN$1)+(HAVERQ!BO119*HAVERQ!$BO$1) -> 23.012548 | GR35: 39356 | GS35: =100*(HAVERQ!BP119/HAVERQ!BR119) -> 24.445938 | GT35: =AVERAGE($GS$4:$GS$103) -> 24.605137 | GV35: 39356 | GW35: =100*(HAVERQ!BP119/HAVERQ!BR119) -> 24.445938 | GX35: =100*((DataQ!F150/DataQ!F146)-1) -> 3.7176578
M36: 2020 | N36: =100*((DataQ!F195/DataQ!F191)-1) -> 3.872899 | O36: =100*(DataQ!I195/DataQ!J195) -> 21.597939 | FZ36: 39448 | GA36: =100*((HAVERQ!S120/HAVERQ!S116)-1) -> 0.87823478 | GB36: =MIN(GI35:GJ35) -> 0.85687454 | GC36: =+GF36-GB36 -> 0.09532611 | GD36: =AVERAGE(GB36,GF36) -> 0.9045376 | GF36: =MAX(GI35:GJ35) -> 0.95220065 | GH36: 39448 | GI36: =(GL36-GI$1)/GI$2 -> 0.18739133 | GJ36: =(GM36-GJ$1)/GJ$2 -> -0.54386495 | GL36: =(HAVERQ!BJ120*HAVERQ!$BJ$1)+(HAVERQ!BK120*HAVERQ!$BK$1) -> 20.067162 | GM36: =(HAVERQ!BL120*HAVERQ!$BL$1)+(HAVERQ!BM120*HAVERQ!$BM$1)+(HAVERQ!BN120*HAVERQ!$BN$1)+(HAVERQ!BO120*HAVERQ!$BO$1) -> -1.5337172 | GR36: 39448 | GS36: =100*(HAVERQ!BP120/HAVERQ!BR120) -> 23.895795 | GT36: =AVERAGE($GS$4:$GS$103) -> 24.605137 | GV36: 39448 | GW36: =100*(HAVERQ!BP120/HAVERQ!BR120) -> 23.895795 | GX36: =100*((DataQ!F151/DataQ!F147)-1) -> 2.8709781
N37: =100*((DataQ!F196/DataQ!F192)-1) -> 24.742239 | O37: =100*(DataQ!I196/DataQ!J196) -> 24.290995 | FZ37: 39539 | GA37: =100*((HAVERQ!S121/HAVERQ!S117)-1) -> 0.81972323 | GB37: =MIN(GI36:GJ36) -> -0.54386495 | GC37: =+GF37-GB37 -> 0.73125628 | GD37: =AVERAGE(GB37,GF37) -> -0.17823681 | GF37: =MAX(GI36:GJ36) -> 0.18739133 | GH37: 39539 | GI37: =(GL37-GI$1)/GI$2 -> -0.98339184 | GJ37: =(GM37-GJ$1)/GJ$2 -> -0.58218848 | GL37: =(HAVERQ!BJ121*HAVERQ!$BJ$1)+(HAVERQ!BK121*HAVERQ!$BK$1) -> 7.3003712 | GM37: =(HAVERQ!BL121*HAVERQ!$BL$1)+(HAVERQ!BM121*HAVERQ!$BM$1)+(HAVERQ!BN121*HAVERQ!$BN$1)+(HAVERQ!BO121*HAVERQ!$BO$1) -> -2.1624995 | GR37: 39539 | GS37: =100*(HAVERQ!BP121/HAVERQ!BR121) -> 24.654432 | GT37: =AVERAGE($GS$4:$GS$103) -> 24.605137 | GV37: 39539 | GW37: =100*(HAVERQ!BP121/HAVERQ!BR121) -> 24.654432 | GX37: =100*((DataQ!F152/DataQ!F148)-1) -> 5.2942512
N38: =100*((DataQ!F197/DataQ!F193)-1) -> 10.361268 | O38: =100*(DataQ!I197/DataQ!J197) -> 23.602395 | FZ38: 39630 | GA38: =100*((HAVERQ!S122/HAVERQ!S118)-1) -> 0.29794234 | GB38: =MIN(GI37:GJ37) -> -0.98339184 | GC38: =+GF38-GB38 -> 0.40120336 | GD38: =AVERAGE(GB38,GF38) -> -0.78279016 | GF38: =MAX(GI37:GJ37) -> -0.58218848 | GH38: 39630 | GI38: =(GL38-GI$1)/GI$2 -> -1.477563 | GJ38: =(GM38-GJ$1)/GJ$2 -> -1.3485565 | GL38: =(HAVERQ!BJ122*HAVERQ!$BJ$1)+(HAVERQ!BK122*HAVERQ!$BK$1) -> 1.9116885 | GM38: =(HAVERQ!BL122*HAVERQ!$BL$1)+(HAVERQ!BM122*HAVERQ!$BM$1)+(HAVERQ!BN122*HAVERQ!$BN$1)+(HAVERQ!BO122*HAVERQ!$BO$1) -> -14.736461 | GR38: 39630 | GS38: =100*(HAVERQ!BP122/HAVERQ!BR122) -> 25.293319 | GT38: =AVERAGE($GS$4:$GS$103) -> 24.605137 | GV38: 39630 | GW38: =100*(HAVERQ!BP122/HAVERQ!BR122) -> 25.293319 | GX38: =100*((DataQ!F153/DataQ!F149)-1) -> 3.6689065
N39: =100*((DataQ!F198/DataQ!F194)-1) -> 11.727665 | O39: =100*(DataQ!I198/DataQ!J198) -> 21.764451 | FZ39: 39722 | GA39: =100*((HAVERQ!S123/HAVERQ!S119)-1) -> -0.3998884 | GB39: =MIN(GI38:GJ38) -> -1.477563 | GC39: =+GF39-GB39 -> 0.12900648 | GD39: =AVERAGE(GB39,GF39) -> -1.4130597 | GF39: =MAX(GI38:GJ38) -> -1.3485565 | GH39: 39722 | GI39: =(GL39-GI$1)/GI$2 -> -3.9749944 | GJ39: =(GM39-GJ$1)/GJ$2 -> -2.726387 | GL39: =(HAVERQ!BJ123*HAVERQ!$BJ$1)+(HAVERQ!BK123*HAVERQ!$BK$1) -> -25.321521 | GM39: =(HAVERQ!BL123*HAVERQ!$BL$1)+(HAVERQ!BM123*HAVERQ!$BM$1)+(HAVERQ!BN123*HAVERQ!$BN$1)+(HAVERQ!BO123*HAVERQ!$BO$1) -> -37.342818 | GR39: 39722 | GS39: =100*(HAVERQ!BP123/HAVERQ!BR123) -> 24.704002 | GT39: =AVERAGE($GS$4:$GS$103) -> 24.605137 | GV39: 39722 | GW39: =100*(HAVERQ!BP123/HAVERQ!BR123) -> 24.704002 | GX39: =100*((DataQ!F154/DataQ!F150)-1) -> 3.1545328
M40: 2021 | N40: =100*((DataQ!F199/DataQ!F195)-1) -> 9.9731084 | O40: =100*(DataQ!I199/DataQ!J199) -> 21.955159 | FZ40: 39814 | GA40: =100*((HAVERQ!S124/HAVERQ!S120)-1) -> -1.1494253 | GB40: =MIN(GI39:GJ39) -> -3.9749944 | GC40: =+GF40-GB40 -> 1.2486074 | GD40: =AVERAGE(GB40,GF40) -> -3.3506907 | GF40: =MAX(GI39:GJ39) -> -2.726387 | GH40: 39814 | GI40: =(GL40-GI$1)/GI$2 -> -2.9173032 | GJ40: =(GM40-GJ$1)/GJ$2 -> -3.3141966 | GL40: =(HAVERQ!BJ124*HAVERQ!$BJ$1)+(HAVERQ!BK124*HAVERQ!$BK$1) -> -13.78794 | GM40: =(HAVERQ!BL124*HAVERQ!$BL$1)+(HAVERQ!BM124*HAVERQ!$BM$1)+(HAVERQ!BN124*HAVERQ!$BN$1)+(HAVERQ!BO124*HAVERQ!$BO$1) -> -46.987134 | GR40: 39814 | GS40: =100*(HAVERQ!BP124/HAVERQ!BR124) -> 25.039942 | GT40: =AVERAGE($GS$4:$GS$103) -> 24.605137 | GV40: 39814 | GW40: =100*(HAVERQ!BP124/HAVERQ!BR124) -> 25.039942 | GX40: =100*((DataQ!F155/DataQ!F151)-1) -> 2.1337791
N41: =100*((DataQ!F200/DataQ!F196)-1) -> -13.621606 | O41: =100*(DataQ!I200/DataQ!J200) -> 22.586677 | FZ41: 39904 | GA41: =100*((HAVERQ!S125/HAVERQ!S121)-1) -> -1.9136241 | GB41: =MIN(GI40:GJ40) -> -3.3141966 | GC41: =+GF41-GB41 -> 0.39689342 | GD41: =AVERAGE(GB41,GF41) -> -3.1157499 | GF41: =MAX(GI40:GJ40) -> -2.9173032 | GH41: 39904 | GI41: =(GL41-GI$1)/GI$2 -> -2.5281253 | GJ41: =(GM41-GJ$1)/GJ$2 -> -1.9320853 | GL41: =(HAVERQ!BJ125*HAVERQ!$BJ$1)+(HAVERQ!BK125*HAVERQ!$BK$1) -> -9.5441557 | GM41: =(HAVERQ!BL125*HAVERQ!$BL$1)+(HAVERQ!BM125*HAVERQ!$BM$1)+(HAVERQ!BN125*HAVERQ!$BN$1)+(HAVERQ!BO125*HAVERQ!$BO$1) -> -24.310542 | GR41: 39904 | GS41: =100*(HAVERQ!BP125/HAVERQ!BR125) -> 24.251617 | GT41: =AVERAGE($GS$4:$GS$103) -> 24.605137 | GV41: 39904 | GW41: =100*(HAVERQ!BP125/HAVERQ!BR125) -> 24.251617 | GX41: =100*((DataQ!F156/DataQ!F152)-1) -> -0.55002363
N42: =100*((DataQ!F201/DataQ!F197)-1) -> -2.4675534 | O42: =100*(DataQ!I201/DataQ!J201) -> 21.710195 | FZ42: 39995 | GA42: =100*((HAVERQ!S126/HAVERQ!S122)-1) -> -2.17842 | GB42: =MIN(GI41:GJ41) -> -2.5281253 | GC42: =+GF42-GB42 -> 0.59604008 | GD42: =AVERAGE(GB42,GF42) -> -2.2301053 | GF42: =MAX(GI41:GJ41) -> -1.9320853 | GH42: 39995 | GI42: =(GL42-GI$1)/GI$2 -> -1.2656368 | GJ42: =(GM42-GJ$1)/GJ$2 -> -1.3759029 | GL42: =(HAVERQ!BJ126*HAVERQ!$BJ$1)+(HAVERQ!BK126*HAVERQ!$BK$1) -> 4.2226347 | GM42: =(HAVERQ!BL126*HAVERQ!$BL$1)+(HAVERQ!BM126*HAVERQ!$BM$1)+(HAVERQ!BN126*HAVERQ!$BN$1)+(HAVERQ!BO126*HAVERQ!$BO$1) -> -15.18514 | GR42: 39995 | GS42: =100*(HAVERQ!BP126/HAVERQ!BR126) -> 24.857717 | GT42: =AVERAGE($GS$4:$GS$103) -> 24.605137 | GV42: 39995 | GW42: =100*(HAVERQ!BP126/HAVERQ!BR126) -> 24.857717 | GX42: =100*((DataQ!F157/DataQ!F153)-1) -> 0.27595267
N43: =100*((DataQ!F202/DataQ!F198)-1) -> -4.2998264 | O43: =100*(DataQ!I202/DataQ!J202) -> 21.584472 | FZ43: 40087 | GA43: =100*((HAVERQ!S127/HAVERQ!S123)-1) -> -2.0292561 | GB43: =MIN(GI42:GJ42) -> -1.3759029 | GC43: =+GF43-GB43 -> 0.11026612 | GD43: =AVERAGE(GB43,GF43) -> -1.3207699 | GF43: =MAX(GI42:GJ42) -> -1.2656368 | GH43: 40087 | GI43: =(GL43-GI$1)/GI$2 -> -1.3216979 | GJ43: =(GM43-GJ$1)/GJ$2 -> -1.2727235 | GL43: =(HAVERQ!BJ127*HAVERQ!$BJ$1)+(HAVERQ!BK127*HAVERQ!$BK$1) -> 3.6113173 | GM43: =(HAVERQ!BL127*HAVERQ!$BL$1)+(HAVERQ!BM127*HAVERQ!$BM$1)+(HAVERQ!BN127*HAVERQ!$BN$1)+(HAVERQ!BO127*HAVERQ!$BO$1) -> -13.492254 | GR43: 40087 | GS43: =100*(HAVERQ!BP127/HAVERQ!BR127) -> 23.610408 | GT43: =AVERAGE($GS$4:$GS$103) -> 24.605137 | GV43: 40087 | GW43: =100*(HAVERQ!BP127/HAVERQ!BR127) -> 23.610408 | GX43: =100*((DataQ!F158/DataQ!F154)-1) -> -0.83705362
M44: 2022 | N44: =100*((DataQ!F203/DataQ!F199)-1) -> -3.5561128 | O44: =100*(DataQ!I203/DataQ!J203) -> 21.094265 | FZ44: 40179 | GA44: =100*((HAVERQ!S128/HAVERQ!S124)-1) -> -1.3477089 | GB44: =MIN(GI43:GJ43) -> -1.3216979 | GC44: =+GF44-GB44 -> 0.048974348 | GD44: =AVERAGE(GB44,GF44) -> -1.2972107 | GF44: =MAX(GI43:GJ43) -> -1.2727235 | GH44: 40179 | GI44: =(GL44-GI$1)/GI$2 -> -0.9905207 | GJ44: =(GM44-GJ$1)/GJ$2 -> -1.6345113 | GL44: =(HAVERQ!BJ128*HAVERQ!$BJ$1)+(HAVERQ!BK128*HAVERQ!$BK$1) -> 7.2226347 | GM44: =(HAVERQ!BL128*HAVERQ!$BL$1)+(HAVERQ!BM128*HAVERQ!$BM$1)+(HAVERQ!BN128*HAVERQ!$BN$1)+(HAVERQ!BO128*HAVERQ!$BO$1) -> -19.428183 | GR44: 40179 | GS44: =100*(HAVERQ!BP128/HAVERQ!BR128) -> 24.556805 | GT44: =AVERAGE($GS$4:$GS$103) -> 24.605137 | GV44: 40179 | GW44: =100*(HAVERQ!BP128/HAVERQ!BR128) -> 24.556805 | GX44: =100*((DataQ!F159/DataQ!F155)-1) -> 1.6050904
N45: =100*((DataQ!F204/DataQ!F200)-1) -> 2.3235521 | O45: =100*(DataQ!I204/DataQ!J204) -> 21.380345 | FZ45: 40269 | GA45: =100*((HAVERQ!S129/HAVERQ!S125)-1) -> -0.53580434 | GB45: =MIN(GI44:GJ44) -> -1.6345113 | GC45: =+GF45-GB45 -> 0.64399059 | GD45: =AVERAGE(GB45,GF45) -> -1.312516 | GF45: =MAX(GI44:GJ44) -> -0.9905207 | GH45: 40269 | GI45: =(GL45-GI$1)/GI$2 -> -0.62272946 | GJ45: =(GM45-GJ$1)/GJ$2 -> -0.75759867 | GL45: =(HAVERQ!BJ129*HAVERQ!$BJ$1)+(HAVERQ!BK129*HAVERQ!$BK$1) -> 11.23321 | GM45: =(HAVERQ!BL129*HAVERQ!$BL$1)+(HAVERQ!BM129*HAVERQ!$BM$1)+(HAVERQ!BN129*HAVERQ!$BN$1)+(HAVERQ!BO129*HAVERQ!$BO$1) -> -5.0404917 | GR45: 40269 | GS45: =100*(HAVERQ!BP129/HAVERQ!BR129) -> 24.260172 | GT45: =AVERAGE($GS$4:$GS$103) -> 24.605137 | GV45: 40269 | GW45: =100*(HAVERQ!BP129/HAVERQ!BR129) -> 24.260172 | GX45: =100*((DataQ!F160/DataQ!F156)-1) -> 1.5795253
N46: =100*((DataQ!F205/DataQ!F201)-1) -> 4.6629561 | O46: =100*(DataQ!I205/DataQ!J205) -> 21.146079 | FZ46: 40360 | GA46: =100*((HAVERQ!S130/HAVERQ!S126)-1) -> -0.31316231 | GB46: =MIN(GI45:GJ45) -> -0.75759867 | GC46: =+GF46-GB46 -> 0.13486921 | GD46: =AVERAGE(GB46,GF46) -> -0.69016407 | GF46: =MAX(GI45:GJ45) -> -0.62272946 | GH46: 40360 | GI46: =(GL46-GI$1)/GI$2 -> -1.5112677 | GJ46: =(GM46-GJ$1)/GJ$2 -> -0.18032767 | GL46: =(HAVERQ!BJ130*HAVERQ!$BJ$1)+(HAVERQ!BK130*HAVERQ!$BK$1) -> 1.5441557 | GM46: =(HAVERQ!BL130*HAVERQ!$BL$1)+(HAVERQ!BM130*HAVERQ!$BM$1)+(HAVERQ!BN130*HAVERQ!$BN$1)+(HAVERQ!BO130*HAVERQ!$BO$1) -> 4.4309159 | GR46: 40360 | GS46: =100*(HAVERQ!BP130/HAVERQ!BR130) -> 25.080111 | GT46: =AVERAGE($GS$4:$GS$103) -> 24.605137 | GV46: 40360 | GW46: =100*(HAVERQ!BP130/HAVERQ!BR130) -> 25.080111 | GX46: =100*((DataQ!F161/DataQ!F157)-1) -> 0.44323333
N47: =100*((DataQ!F206/DataQ!F202)-1) -> 7.3192565 | O47: =100*(DataQ!I206/DataQ!J206) -> 22.653969 | FZ47: 40452 | GA47: =100*((HAVERQ!S131/HAVERQ!S127)-1) -> 0.28273715 | GB47: =MIN(GI46:GJ46) -> -1.5112677 | GC47: =+GF47-GB47 -> 1.33094 | GD47: =AVERAGE(GB47,GF47) -> -0.84579768 | GF47: =MAX(GI46:GJ46) -> -0.18032767 | GH47: 40452 | GI47: =(GL47-GI$1)/GI$2 -> -1.3207281 | GJ47: =(GM47-GJ$1)/GJ$2 -> -0.79454066 | GL47: =(HAVERQ!BJ131*HAVERQ!$BJ$1)+(HAVERQ!BK131*HAVERQ!$BK$1) -> 3.6218923 | GM47: =(HAVERQ!BL131*HAVERQ!$BL$1)+(HAVERQ!BM131*HAVERQ!$BM$1)+(HAVERQ!BN131*HAVERQ!$BN$1)+(HAVERQ!BO131*HAVERQ!$BO$1) -> -5.6466067 | GR47: 40452 | GS47: =100*(HAVERQ!BP131/HAVERQ!BR131) -> 25.241015 | GT47: =AVERAGE($GS$4:$GS$103) -> 24.605137 | GV47: 40452 | GW47: =100*(HAVERQ!BP131/HAVERQ!BR131) -> 25.241015 | GX47: =100*((DataQ!F162/DataQ!F158)-1) -> 0.54747967
M48: 2023 | N48: =100*((DataQ!F207/DataQ!F203)-1) -> 7.5866246 | O48: =100*(DataQ!I207/DataQ!J207) -> 23.524103 | FZ48: 40544 | GA48: =100*((HAVERQ!S132/HAVERQ!S128)-1) -> 0.50196975 | GB48: =MIN(GI47:GJ47) -> -1.3207281 | GC48: =+GF48-GB48 -> 0.52618744 | GD48: =AVERAGE(GB48,GF48) -> -1.0576344 | GF48: =MAX(GI47:GJ47) -> -0.79454066 | GH48: 40544 | GI48: =(GL48-GI$1)/GI$2 -> -0.74295026 | GJ48: =(GM48-GJ$1)/GJ$2 -> -0.25402973 | GL48: =(HAVERQ!BJ132*HAVERQ!$BJ$1)+(HAVERQ!BK132*HAVERQ!$BK$1) -> 9.9222635 | GM48: =(HAVERQ!BL132*HAVERQ!$BL$1)+(HAVERQ!BM132*HAVERQ!$BM$1)+(HAVERQ!BN132*HAVERQ!$BN$1)+(HAVERQ!BO132*HAVERQ!$BO$1) -> 3.2216705 | GR48: 40544 | GS48: =100*(HAVERQ!BP132/HAVERQ!BR132) -> 24.608564 | GT48: =AVERAGE($GS$4:$GS$103) -> 24.605137 | GV48: 40544 | GW48: =100*(HAVERQ!BP132/HAVERQ!BR132) -> 24.608564 | GX48: =100*((DataQ!F163/DataQ!F159)-1) -> -1.0460326
N49: =100*((DataQ!F208/DataQ!F204)-1) -> 8.0728132 | O49: =100*(DataQ!I208/DataQ!J208) -> 21.631861 | FZ49: 40634 | GA49: =100*((HAVERQ!S133/HAVERQ!S129)-1) -> -0.0031687686 | GB49: =MIN(GI48:GJ48) -> -0.74295026 | GC49: =+GF49-GB49 -> 0.48892053 | GD49: =AVERAGE(GB49,GF49) -> -0.49848999 | GF49: =MAX(GI48:GJ48) -> -0.25402973 | GH49: 40634 | GI49: =(GL49-GI$1)/GI$2 -> -0.5310241 | GJ49: =(GM49-GJ$1)/GJ$2 -> 0.25922357 | GL49: =(HAVERQ!BJ133*HAVERQ!$BJ$1)+(HAVERQ!BK133*HAVERQ!$BK$1) -> 12.23321 | GM49: =(HAVERQ!BL133*HAVERQ!$BL$1)+(HAVERQ!BM133*HAVERQ!$BM$1)+(HAVERQ!BN133*HAVERQ!$BN$1)+(HAVERQ!BO133*HAVERQ!$BO$1) -> 11.642726 | GR49: 40634 | GS49: =100*(HAVERQ!BP133/HAVERQ!BR133) -> 24.799101 | GT49: =AVERAGE($GS$4:$GS$103) -> 24.605137 | GV49: 40634 | GW49: =100*(HAVERQ!BP133/HAVERQ!BR133) -> 24.799101 | GX49: =100*((DataQ!F164/DataQ!F160)-1) -> 0.71283454
N50: =100*((DataQ!F209/DataQ!F205)-1) -> 7.2288043 | O50: =100*(DataQ!I209/DataQ!J209) -> 21.010605 | FZ50: 40725 | GA50: =100*((HAVERQ!S134/HAVERQ!S130)-1) -> 0.85993527 | GB50: =MIN(GI49:GJ49) -> -0.5310241 | GC50: =+GF50-GB50 -> 0.79024766 | GD50: =AVERAGE(GB50,GF50) -> -0.13590027 | GF50: =MAX(GI49:GJ49) -> 0.25922357 | GH50: 40725 | GI50: =(GL50-GI$1)/GI$2 -> -1.0741274 | GJ50: =(GM50-GJ$1)/GJ$2 -> -0.39458624 | GL50: =(HAVERQ!BJ134*HAVERQ!$BJ$1)+(HAVERQ!BK134*HAVERQ!$BK$1) -> 6.3109461 | GM50: =(HAVERQ!BL134*HAVERQ!$BL$1)+(HAVERQ!BM134*HAVERQ!$BM$1)+(HAVERQ!BN134*HAVERQ!$BN$1)+(HAVERQ!BO134*HAVERQ!$BO$1) -> 0.91553014 | GR50: 40725 | GS50: =100*(HAVERQ!BP134/HAVERQ!BR134) -> 25.150204 | GT50: =AVERAGE($GS$4:$GS$103) -> 24.605137 | GV50: 40725 | GW50: =100*(HAVERQ!BP134/HAVERQ!BR134) -> 25.150204 | GX50: =100*((DataQ!F165/DataQ!F161)-1) -> 0.63328293
N51: =100*((DataQ!F210/DataQ!F206)-1) -> 6.7720967 | O51: =100*(DataQ!I210/DataQ!J210) -> 20.546876 | FZ51: 40817 | GA51: =100*((HAVERQ!S135/HAVERQ!S131)-1) -> 0.74761618 | GB51: =MIN(GI50:GJ50) -> -1.0741274 | GC51: =+GF51-GB51 -> 0.67954119 | GD51: =AVERAGE(GB51,GF51) -> -0.73435684 | GF51: =MAX(GI50:GJ50) -> -0.39458624 | GH51: 40817 | GI51: =(GL51-GI$1)/GI$2 -> -1.5407529 | GJ51: =(GM51-GJ$1)/GJ$2 -> -1.2346204 | GL51: =(HAVERQ!BJ135*HAVERQ!$BJ$1)+(HAVERQ!BK135*HAVERQ!$BK$1) -> 1.2226347 | GM51: =(HAVERQ!BL135*HAVERQ!$BL$1)+(HAVERQ!BM135*HAVERQ!$BM$1)+(HAVERQ!BN135*HAVERQ!$BN$1)+(HAVERQ!BO135*HAVERQ!$BO$1) -> -12.867089 | GR51: 40817 | GS51: =100*(HAVERQ!BP135/HAVERQ!BR135) -> 25.779681 | GT51: =AVERAGE($GS$4:$GS$103) -> 24.605137 | GV51: 40817 | GW51: =100*(HAVERQ!BP135/HAVERQ!BR135) -> 25.779681 | GX51: =100*((DataQ!F166/DataQ!F162)-1) -> 1.2250741
M52: 2024 | N52: =100*((DataQ!F211/DataQ!F207)-1) -> 5.5341423 | O52: =100*(DataQ!I211/DataQ!J211) -> 20.505521 | FZ52: 40909 | GA52: =100*((HAVERQ!S136/HAVERQ!S132)-1) -> 1.6216729 | GB52: =MIN(GI51:GJ51) -> -1.5407529 | GC52: =+GF52-GB52 -> 0.30613247 | GD52: =AVERAGE(GB52,GF52) -> -1.3876867 | GF52: =MAX(GI51:GJ51) -> -1.2346204 | GH52: 40909 | GI52: =(GL52-GI$1)/GI$2 -> -0.61560061 | GJ52: =(GM52-GJ$1)/GJ$2 -> -0.60983723 | GL52: =(HAVERQ!BJ136*HAVERQ!$BJ$1)+(HAVERQ!BK136*HAVERQ!$BK$1) -> 11.310946 | GM52: =(HAVERQ!BL136*HAVERQ!$BL$1)+(HAVERQ!BM136*HAVERQ!$BM$1)+(HAVERQ!BN136*HAVERQ!$BN$1)+(HAVERQ!BO136*HAVERQ!$BO$1) -> -2.6161384 | GR52: 40909 | GS52: =100*(HAVERQ!BP136/HAVERQ!BR136) -> 25.042717 | GT52: =AVERAGE($GS$4:$GS$103) -> 24.605137 | GV52: 40909 | GW52: =100*(HAVERQ!BP136/HAVERQ!BR136) -> 25.042717 | GX52: =100*((DataQ!F167/DataQ!F163)-1) -> 0.66949357
N53: =100*((DataQ!F212/DataQ!F208)-1) -> 4.6888589 | O53: =100*(DataQ!I212/DataQ!J212) -> 20.250685 | FZ53: 41000 | GA53: =100*((HAVERQ!S137/HAVERQ!S133)-1) -> 1.6985138 | GB53: =MIN(GI52:GJ52) -> -0.61560061 | GC53: =+GF53-GB53 -> 0.0057633733 | GD53: =AVERAGE(GB53,GF53) -> -0.61271892 | GF53: =MAX(GI52:GJ52) -> -0.60983723 | GH53: 41000 | GI53: =(GL53-GI$1)/GI$2 -> -0.54528181 | GJ53: =(GM53-GJ$1)/GJ$2 -> 0.14755075 | GL53: =(HAVERQ!BJ137*HAVERQ!$BJ$1)+(HAVERQ!BK137*HAVERQ!$BK$1) -> 12.077737 | GM53: =(HAVERQ!BL137*HAVERQ!$BL$1)+(HAVERQ!BM137*HAVERQ!$BM$1)+(HAVERQ!BN137*HAVERQ!$BN$1)+(HAVERQ!BO137*HAVERQ!$BO$1) -> 9.8104865 | GR53: 41000 | GS53: =100*(HAVERQ!BP137/HAVERQ!BR137) -> 24.820656 | GT53: =AVERAGE($GS$4:$GS$103) -> 24.605137 | GV53: 41000 | GW53: =100*(HAVERQ!BP137/HAVERQ!BR137) -> 24.820656 | GX53: =100*((DataQ!F168/DataQ!F164)-1) -> 2.583742
N54: =100*((DataQ!F213/DataQ!F209)-1) -> 4.4570365 | O54: =100*(DataQ!I213/DataQ!J213) -> 20.136897 | FZ54: 41091 | GA54: =100*((HAVERQ!S138/HAVERQ!S134)-1) -> 0.78653453 | GB54: =MIN(GI53:GJ53) -> -0.54528181 | GC54: =+GF54-GB54 -> 0.69283256 | GD54: =AVERAGE(GB54,GF54) -> -0.19886553 | GF54: =MAX(GI53:GJ53) -> 0.14755075 | GH54: 41091 | GI54: =(GL54-GI$1)/GI$2 -> -0.88455762 | GJ54: =(GM54-GJ$1)/GJ$2 -> -0.38870042 | GL54: =(HAVERQ!BJ138*HAVERQ!$BJ$1)+(HAVERQ!BK138*HAVERQ!$BK$1) -> 8.3781077 | GM54: =(HAVERQ!BL138*HAVERQ!$BL$1)+(HAVERQ!BM138*HAVERQ!$BM$1)+(HAVERQ!BN138*HAVERQ!$BN$1)+(HAVERQ!BO138*HAVERQ!$BO$1) -> 1.0121 | GR54: 41091 | GS54: =100*(HAVERQ!BP138/HAVERQ!BR138) -> 25.841767 | GT54: =AVERAGE($GS$4:$GS$103) -> 24.605137 | GV54: 41091 | GW54: =100*(HAVERQ!BP138/HAVERQ!BR138) -> 25.841767 | GX54: =100*((DataQ!F169/DataQ!F165)-1) -> 2.7966777
N55: =100*((DataQ!F214/DataQ!F210)-1) -> 4.9998341 | O55: =100*(DataQ!I214/DataQ!J214) -> 20.247055 | FZ55: 41183 | GA55: =100*((HAVERQ!S139/HAVERQ!S135)-1) -> 0.58799484 | GB55: =MIN(GI54:GJ54) -> -0.88455762 | GC55: =+GF55-GB55 -> 0.4958572 | GD55: =AVERAGE(GB55,GF55) -> -0.63662902 | GF55: =MAX(GI54:GJ54) -> -0.38870042 | GH55: 41183 | GI55: =(GL55-GI$1)/GI$2 -> -0.53815296 | GJ55: =(GM55-GJ$1)/GJ$2 -> -0.10085964 | GL55: =(HAVERQ!BJ139*HAVERQ!$BJ$1)+(HAVERQ!BK139*HAVERQ!$BK$1) -> 12.155473 | GM55: =(HAVERQ!BL139*HAVERQ!$BL$1)+(HAVERQ!BM139*HAVERQ!$BM$1)+(HAVERQ!BN139*HAVERQ!$BN$1)+(HAVERQ!BO139*HAVERQ!$BO$1) -> 5.7347646 | GR55: 41183 | GS55: =100*(HAVERQ!BP139/HAVERQ!BR139) -> 25.8083 | GT55: =AVERAGE($GS$4:$GS$103) -> 24.605137 | GV55: 41183 | GW55: =100*(HAVERQ!BP139/HAVERQ!BR139) -> 25.8083 | GX55: =100*((DataQ!F170/DataQ!F166)-1) -> 2.2815277
M56: 2025 | N56: =100*((DataQ!F215/DataQ!F211)-1) -> 4.5127993 | O56: =100*(DataQ!I215/DataQ!J215) -> 19.969051 | FZ56: 41275 | GA56: =100*((HAVERQ!S140/HAVERQ!S136)-1) -> 0.080878465 | GB56: =MIN(GI55:GJ55) -> -0.53815296 | GC56: =+GF56-GB56 -> 0.43729331 | GD56: =AVERAGE(GB56,GF56) -> -0.3195063 | GF56: =MAX(GI55:GJ55) -> -0.10085964 | GH56: 41275 | GI56: =(GL56-GI$1)/GI$2 -> -0.62272946 | GJ56: =(GM56-GJ$1)/GJ$2 -> 0.3400583 | GL56: =(HAVERQ!BJ140*HAVERQ!$BJ$1)+(HAVERQ!BK140*HAVERQ!$BK$1) -> 11.23321 | GM56: =(HAVERQ!BL140*HAVERQ!$BL$1)+(HAVERQ!BM140*HAVERQ!$BM$1)+(HAVERQ!BN140*HAVERQ!$BN$1)+(HAVERQ!BO140*HAVERQ!$BO$1) -> 12.968998 | GR56: 41275 | GS56: =100*(HAVERQ!BP140/HAVERQ!BR140) -> 26.176467 | GT56: =AVERAGE($GS$4:$GS$103) -> 24.605137 | GV56: 41275 | GW56: =100*(HAVERQ!BP140/HAVERQ!BR140) -> 26.176467 | GX56: =100*((DataQ!F171/DataQ!F167)-1) -> 2.457354
N57: =100*((DataQ!F216/DataQ!F212)-1) -> 6.1732039 | O57: =100*(DataQ!I216/DataQ!J216) -> 19.495674 | FZ57: 41365 | GA57: =100*((HAVERQ!S141/HAVERQ!S137)-1) -> 0.44558003 | GB57: =MIN(GI56:GJ56) -> -0.62272946 | GC57: =+GF57-GB57 -> 0.96278776 | GD57: =AVERAGE(GB57,GF57) -> -0.14133558 | GF57: =MAX(GI56:GJ56) -> 0.3400583 | GH57: 41365 | GI57: =(GL57-GI$1)/GI$2 -> 0.35038527 | GJ57: =(GM57-GJ$1)/GJ$2 -> 0.23757651 | GL57: =(HAVERQ!BJ141*HAVERQ!$BJ$1)+(HAVERQ!BK141*HAVERQ!$BK$1) -> 21.844527 | GM57: =(HAVERQ!BL141*HAVERQ!$BL$1)+(HAVERQ!BM141*HAVERQ!$BM$1)+(HAVERQ!BN141*HAVERQ!$BN$1)+(HAVERQ!BO141*HAVERQ!$BO$1) -> 11.287558 | GR57: 41365 | GS57: =100*(HAVERQ!BP141/HAVERQ!BR141) -> 24.875472 | GT57: =AVERAGE($GS$4:$GS$103) -> 24.605137 | GV57: 41365 | GW57: =100*(HAVERQ!BP141/HAVERQ!BR141) -> 24.875472 | GX57: =100*((DataQ!F172/DataQ!F168)-1) -> -1.5163896
N58: =100*((DataQ!F217/DataQ!F213)-1) -> 6.1262414 | O58: =100*(DataQ!I217/DataQ!J217) -> 19.836178 | FZ58: 41456 | GA58: =100*((HAVERQ!S142/HAVERQ!S138)-1) -> 1.3391603 | GB58: =MIN(GI57:GJ57) -> 0.23757651 | GC58: =+GF58-GB58 -> 0.11280876 | GD58: =AVERAGE(GB58,GF58) -> 0.29398089 | GF58: =MAX(GI57:GJ57) -> 0.35038527 | GH58: 41456 | GI58: =(GL58-GI$1)/GI$2 -> 0.75285102 | GJ58: =(GM58-GJ$1)/GJ$2 -> 0.45221092 | GL58: =(HAVERQ!BJ142*HAVERQ!$BJ$1)+(HAVERQ!BK142*HAVERQ!$BK$1) -> 26.23321 | GM58: =(HAVERQ!BL142*HAVERQ!$BL$1)+(HAVERQ!BM142*HAVERQ!$BM$1)+(HAVERQ!BN142*HAVERQ!$BN$1)+(HAVERQ!BO142*HAVERQ!$BO$1) -> 14.80911 | GR58: 41456 | GS58: =100*(HAVERQ!BP142/HAVERQ!BR142) -> 25.316208 | GT58: =AVERAGE($GS$4:$GS$103) -> 24.605137 | GV58: 41456 | GW58: =100*(HAVERQ!BP142/HAVERQ!BR142) -> 25.316208 | GX58: =100*((DataQ!F173/DataQ!F169)-1) -> -1.8918891
N59: =100*((DataQ!F218/DataQ!F214)-1) -> 4.7491124 | O59: =100*(DataQ!I218/DataQ!J218) -> 19.972282 | FZ59: 41548 | GA59: =100*((HAVERQ!S143/HAVERQ!S139)-1) -> 2.6445764 | GB59: =MIN(GI58:GJ58) -> 0.45221092 | GC59: =+GF59-GB59 -> 0.30064009 | GD59: =AVERAGE(GB59,GF59) -> 0.60253097 | GF59: =MAX(GI58:GJ58) -> 0.75285102 | GH59: 41548 | GI59: =(GL59-GI$1)/GI$2 -> 0.85168524 | GJ59: =(GM59-GJ$1)/GJ$2 -> 0.58946544 | GL59: =(HAVERQ!BJ143*HAVERQ!$BJ$1)+(HAVERQ!BK143*HAVERQ!$BK$1) -> 27.310946 | GM59: =(HAVERQ!BL143*HAVERQ!$BL$1)+(HAVERQ!BM143*HAVERQ!$BM$1)+(HAVERQ!BN143*HAVERQ!$BN$1)+(HAVERQ!BO143*HAVERQ!$BO$1) -> 17.061074 | GR59: 41548 | GS59: =100*(HAVERQ!BP143/HAVERQ!BR143) -> 25.096551 | GT59: =AVERAGE($GS$4:$GS$103) -> 24.605137 | GV59: 41548 | GW59: =100*(HAVERQ!BP143/HAVERQ!BR143) -> 25.096551 | GX59: =100*((DataQ!F174/DataQ!F170)-1) -> -1.6332789
M60: 2026 | N60: =100*((DataQ!F219/DataQ!F215)-1) -> 4.6594114 | O60: =100*(DataQ!I219/DataQ!J219) -> 20.081067 | FZ60: 41640 | GA60: =100*((HAVERQ!S144/HAVERQ!S140)-1) -> 2.9869767 | GB60: =MIN(GI59:GJ59) -> 0.58946544 | GC60: =+GF60-GB60 -> 0.2622198 | GD60: =AVERAGE(GB60,GF60) -> 0.72057534 | GF60: =MAX(GI59:GJ59) -> 0.85168524 | GH60: 41640 | GI60: =(GL60-GI$1)/GI$2 -> 1.084998 | GJ60: =(GM60-GJ$1)/GJ$2 -> 0.94623077 | GL60: =(HAVERQ!BJ144*HAVERQ!$BJ$1)+(HAVERQ!BK144*HAVERQ!$BK$1) -> 29.855102 | GM60: =(HAVERQ!BL144*HAVERQ!$BL$1)+(HAVERQ!BM144*HAVERQ!$BM$1)+(HAVERQ!BN144*HAVERQ!$BN$1)+(HAVERQ!BO144*HAVERQ!$BO$1) -> 22.914598 | GR60: 41640 | GS60: =100*(HAVERQ!BP144/HAVERQ!BR144) -> 24.792516 | GT60: =AVERAGE($GS$4:$GS$103) -> 24.605137 | GV60: 41640 | GW60: =100*(HAVERQ!BP144/HAVERQ!BR144) -> 24.792516 | GX60: =100*((DataQ!F175/DataQ!F171)-1) -> -0.69899237
N61: =100*((DataQ!F220/DataQ!F216)-1) -> 2.2913729 | O61: =100*(DataQ!I220/DataQ!J220) -> 20.109055 | FZ61: 41730 | GA61: =100*((HAVERQ!S145/HAVERQ!S141)-1) -> 3.7535674 | GB61: =MIN(GI60:GJ60) -> 0.94623077 | GC61: =+GF61-GB61 -> 0.1387672 | GD61: =AVERAGE(GB61,GF61) -> 1.0156144 | GF61: =MAX(GI60:GJ60) -> 1.084998 | GH61: 41730 | GI61: =(GL61-GI$1)/GI$2 -> 0.76710873 | GJ61: =(GM61-GJ$1)/GJ$2 -> 1.0652926 | GL61: =(HAVERQ!BJ145*HAVERQ!$BJ$1)+(HAVERQ!BK145*HAVERQ!$BK$1) -> 26.388683 | GM61: =(HAVERQ!BL145*HAVERQ!$BL$1)+(HAVERQ!BM145*HAVERQ!$BM$1)+(HAVERQ!BN145*HAVERQ!$BN$1)+(HAVERQ!BO145*HAVERQ!$BO$1) -> 24.868071 | GR61: 41730 | GS61: =100*(HAVERQ!BP145/HAVERQ!BR145) -> 25.535611 | GT61: =AVERAGE($GS$4:$GS$103) -> 24.605137 | GV61: 41730 | GW61: =100*(HAVERQ!BP145/HAVERQ!BR145) -> 25.535611 | GX61: =100*((DataQ!F176/DataQ!F172)-1) -> 0.6717141
N62: =100*((DataQ!F221/DataQ!F217)-1) -> 2.1923963 | O62: =100*(DataQ!I221/DataQ!J221) -> 20.168789 | FZ62: 41821 | GA62: =100*((HAVERQ!S146/HAVERQ!S142)-1) -> 3.4222523 | GB62: =MIN(GI61:GJ61) -> 0.76710873 | GC62: =+GF62-GB62 -> 0.29818385 | GD62: =AVERAGE(GB62,GF62) -> 0.91620066 | GF62: =MAX(GI61:GJ61) -> 1.0652926 | GH62: 41821 | GI62: =(GL62-GI$1)/GI$2 -> 1.1268013 | GJ62: =(GM62-GJ$1)/GJ$2 -> 1.6814581 | GL62: =(HAVERQ!BJ146*HAVERQ!$BJ$1)+(HAVERQ!BK146*HAVERQ!$BK$1) -> 30.310946 | GM62: =(HAVERQ!BL146*HAVERQ!$BL$1)+(HAVERQ!BM146*HAVERQ!$BM$1)+(HAVERQ!BN146*HAVERQ!$BN$1)+(HAVERQ!BO146*HAVERQ!$BO$1) -> 34.977629 | GR62: 41821 | GS62: =100*(HAVERQ!BP146/HAVERQ!BR146) -> 27.084774 | GT62: =AVERAGE($GS$4:$GS$103) -> 24.605137 | GV62: 41821 | GW62: =100*(HAVERQ!BP146/HAVERQ!BR146) -> 27.084774 | GX62: =100*((DataQ!F177/DataQ!F173)-1) -> 2.4865872
N63: =100*((DataQ!F222/DataQ!F218)-1) -> 2.1480977 | O63: =100*(DataQ!I222/DataQ!J222) -> 20.253001 | FZ63: 41913 | GA63: =100*((HAVERQ!S147/HAVERQ!S143)-1) -> 2.5886222 | GB63: =MIN(GI62:GJ62) -> 1.1268013 | GC63: =+GF63-GB63 -> 0.55465675 | GD63: =AVERAGE(GB63,GF63) -> 1.4041297 | GF63: =MAX(GI62:GJ62) -> 1.6814581 | GH63: 41913 | GI63: =(GL63-GI$1)/GI$2 -> 0.86594295 | GJ63: =(GM63-GJ$1)/GJ$2 -> 1.4819577 | GL63: =(HAVERQ!BJ147*HAVERQ!$BJ$1)+(HAVERQ!BK147*HAVERQ!$BK$1) -> 27.466419 | GM63: =(HAVERQ!BL147*HAVERQ!$BL$1)+(HAVERQ!BM147*HAVERQ!$BM$1)+(HAVERQ!BN147*HAVERQ!$BN$1)+(HAVERQ!BO147*HAVERQ!$BO$1) -> 31.704383 | GR63: 41913 | GS63: =100*(HAVERQ!BP147/HAVERQ!BR147) -> 26.644753 | GT63: =AVERAGE($GS$4:$GS$103) -> 24.605137 | GV63: 41913 | GW63: =100*(HAVERQ!BP147/HAVERQ!BR147) -> 26.644753 | GX63: =100*((DataQ!F178/DataQ!F174)-1) -> 1.9929284
M64: 2027 | N64: =100*((DataQ!F223/DataQ!F219)-1) -> 2.1358853 | O64: =100*(DataQ!I223/DataQ!J223) -> 20.429212 | FZ64: 42005 | GA64: =100*((HAVERQ!S148/HAVERQ!S144)-1) -> 2.0281282 | GB64: =MIN(GI63:GJ63) -> 0.86594295 | GC64: =+GF64-GB64 -> 0.61601472 | GD64: =AVERAGE(GB64,GF64) -> 1.1739503 | GF64: =MAX(GI63:GJ63) -> 1.4819577 | GH64: 42005 | GI64: =(GL64-GI$1)/GI$2 -> 0.77423759 | GJ64: =(GM64-GJ$1)/GJ$2 -> 1.3965166 | GL64: =(HAVERQ!BJ148*HAVERQ!$BJ$1)+(HAVERQ!BK148*HAVERQ!$BK$1) -> 26.466419 | GM64: =(HAVERQ!BL148*HAVERQ!$BL$1)+(HAVERQ!BM148*HAVERQ!$BM$1)+(HAVERQ!BN148*HAVERQ!$BN$1)+(HAVERQ!BO148*HAVERQ!$BO$1) -> 30.302533 | GR64: 42005 | GS64: =100*(HAVERQ!BP148/HAVERQ!BR148) -> 25.999256 | GT64: =AVERAGE($GS$4:$GS$103) -> 24.605137 | GV64: 42005 | GW64: =100*(HAVERQ!BP148/HAVERQ!BR148) -> 25.999256 | GX64: =100*((DataQ!F179/DataQ!F175)-1) -> 1.5236579
N65: =100*((DataQ!F224/DataQ!F220)-1) -> 2.0523019 | O65: =100*(DataQ!I224/DataQ!J224) -> 20.547707 | FZ65: 42095 | GA65: =100*((HAVERQ!S149/HAVERQ!S145)-1) -> 1.3334928 | GB65: =MIN(GI64:GJ64) -> 0.77423759 | GC65: =+GF65-GB65 -> 0.62227898 | GD65: =AVERAGE(GB65,GF65) -> 1.0853771 | GF65: =MAX(GI64:GJ64) -> 1.3965166 | GH65: 42095 | GI65: =(GL65-GI$1)/GI$2 -> 1.0768993 | GJ65: =(GM65-GJ$1)/GJ$2 -> 1.0652075 | GL65: =(HAVERQ!BJ149*HAVERQ!$BJ$1)+(HAVERQ!BK149*HAVERQ!$BK$1) -> 29.76679 | GM65: =(HAVERQ!BL149*HAVERQ!$BL$1)+(HAVERQ!BM149*HAVERQ!$BM$1)+(HAVERQ!BN149*HAVERQ!$BN$1)+(HAVERQ!BO149*HAVERQ!$BO$1) -> 24.866675 | GR65: 42095 | GS65: =100*(HAVERQ!BP149/HAVERQ!BR149) -> 25.462523 | GT65: =AVERAGE($GS$4:$GS$103) -> 24.605137 | GV65: 42095 | GW65: =100*(HAVERQ!BP149/HAVERQ!BR149) -> 25.462523 | GX65: =100*((DataQ!F180/DataQ!F176)-1) -> 2.6310611
N66: =100*((DataQ!F225/DataQ!F221)-1) -> 1.9574986 | O66: =100*(DataQ!I225/DataQ!J225) -> 20.644647 | FZ66: 42186 | GA66: =100*((HAVERQ!S150/HAVERQ!S146)-1) -> 1.5130305 | GB66: =MIN(GI65:GJ65) -> 1.0652075 | GC66: =+GF66-GB66 -> 0.011691841 | GD66: =AVERAGE(GB66,GF66) -> 1.0710534 | GF66: =MAX(GI65:GJ65) -> 1.0768993 | GH66: 42186 | GI66: =(GL66-GI$1)/GI$2 -> 0.533796 | GJ66: =(GM66-GJ$1)/GJ$2 -> 0.37244142 | GL66: =(HAVERQ!BJ150*HAVERQ!$BJ$1)+(HAVERQ!BK150*HAVERQ!$BK$1) -> 23.844527 | GM66: =(HAVERQ!BL150*HAVERQ!$BL$1)+(HAVERQ!BM150*HAVERQ!$BM$1)+(HAVERQ!BN150*HAVERQ!$BN$1)+(HAVERQ!BO150*HAVERQ!$BO$1) -> 13.500315 | GR66: 42186 | GS66: =100*(HAVERQ!BP150/HAVERQ!BR150) -> 24.656131 | GT66: =AVERAGE($GS$4:$GS$103) -> 24.605137 | GV66: 42186 | GW66: =100*(HAVERQ!BP150/HAVERQ!BR150) -> 24.656131 | GX66: =100*((DataQ!F181/DataQ!F177)-1) -> 2.2021638
N67: =100*((DataQ!F226/DataQ!F222)-1) -> 1.8719194 | O67: =100*(DataQ!I226/DataQ!J226) -> 20.686951 | FZ67: 42278 | GA67: =100*((HAVERQ!S151/HAVERQ!S147)-1) -> 1.398207 | GB67: =MIN(GI66:GJ66) -> 0.37244142 | GC67: =+GF67-GB67 -> 0.16135458 | GD67: =AVERAGE(GB67,GF67) -> 0.45311871 | GF67: =MAX(GI66:GJ66) -> 0.533796 | GH67: 42278 | GI67: =(GL67-GI$1)/GI$2 -> 0.24442219 | GJ67: =(GM67-GJ$1)/GJ$2 -> 1.0269009 | GL67: =(HAVERQ!BJ151*HAVERQ!$BJ$1)+(HAVERQ!BK151*HAVERQ!$BK$1) -> 20.689054 | GM67: =(HAVERQ!BL151*HAVERQ!$BL$1)+(HAVERQ!BM151*HAVERQ!$BM$1)+(HAVERQ!BN151*HAVERQ!$BN$1)+(HAVERQ!BO151*HAVERQ!$BO$1) -> 24.23817 | GR67: 42278 | GS67: =100*(HAVERQ!BP151/HAVERQ!BR151) -> 25.117434 | GT67: =AVERAGE($GS$4:$GS$103) -> 24.605137 | GV67: 42278 | GW67: =100*(HAVERQ!BP151/HAVERQ!BR151) -> 25.117434 | GX67: =100*((DataQ!F182/DataQ!F178)-1) -> 1.7339906
FZ68: 42370 | GA68: =100*((HAVERQ!S152/HAVERQ!S148)-1) -> 1.6653848 | GB68: =MIN(GI67:GJ67) -> 0.24442219 | GC68: =+GF68-GB68 -> 0.7824787 | GD68: =AVERAGE(GB68,GF68) -> 0.63566154 | GF68: =MAX(GI67:GJ67) -> 1.0269009 | GH68: 42370 | GI68: =(GL68-GI$1)/GI$2 -> 0.72336581 | GJ68: =(GM68-GJ$1)/GJ$2 -> 0.91659118 | GL68: =(HAVERQ!BJ152*HAVERQ!$BJ$1)+(HAVERQ!BK152*HAVERQ!$BK$1) -> 25.911689 | GM68: =(HAVERQ!BL152*HAVERQ!$BL$1)+(HAVERQ!BM152*HAVERQ!$BM$1)+(HAVERQ!BN152*HAVERQ!$BN$1)+(HAVERQ!BO152*HAVERQ!$BO$1) -> 22.428295 | GR68: 42370 | GS68: =100*(HAVERQ!BP152/HAVERQ!BR152) -> 25.047163 | GT68: =AVERAGE($GS$4:$GS$103) -> 24.605137 | GV68: 42370 | GW68: =100*(HAVERQ!BP152/HAVERQ!BR152) -> 25.047163 | GX68: =100*((DataQ!F183/DataQ!F179)-1) -> 1.7811314
FZ69: 42461 | GA69: =100*((HAVERQ!S153/HAVERQ!S149)-1) -> 1.9768677 | GB69: =MIN(GI68:GJ68) -> 0.72336581 | GC69: =+GF69-GB69 -> 0.19322537 | GD69: =AVERAGE(GB69,GF69) -> 0.81997849 | GF69: =MAX(GI68:GJ68) -> 0.91659118 | GH69: 42461 | GI69: =(GL69-GI$1)/GI$2 -> 0.85071546 | GJ69: =(GM69-GJ$1)/GJ$2 -> 1.2151476 | GL69: =(HAVERQ!BJ153*HAVERQ!$BJ$1)+(HAVERQ!BK153*HAVERQ!$BK$1) -> 27.300371 | GM69: =(HAVERQ!BL153*HAVERQ!$BL$1)+(HAVERQ!BM153*HAVERQ!$BM$1)+(HAVERQ!BN153*HAVERQ!$BN$1)+(HAVERQ!BO153*HAVERQ!$BO$1) -> 27.326774 | GR69: 42461 | GS69: =100*(HAVERQ!BP153/HAVERQ!BR153) -> 24.558979 | GT69: =AVERAGE($GS$4:$GS$103) -> 24.605137 | GV69: 42461 | GW69: =100*(HAVERQ!BP153/HAVERQ!BR153) -> 24.558979 | GX69: =100*((DataQ!F184/DataQ!F180)-1) -> 1.3309109
FZ70: 42552 | GA70: =100*((HAVERQ!S154/HAVERQ!S150)-1) -> 1.5022152 | GB70: =MIN(GI69:GJ69) -> 0.85071546 | GC70: =+GF70-GB70 -> 0.36443217 | GD70: =AVERAGE(GB70,GF70) -> 1.0329315 | GF70: =MAX(GI69:GJ69) -> 1.2151476 | GH70: 42552 | GI70: =(GL70-GI$1)/GI$2 -> -0.27016572 | GJ70: =(GM70-GJ$1)/GJ$2 -> 0.094673748 | GL70: =(HAVERQ!BJ154*HAVERQ!$BJ$1)+(HAVERQ!BK154*HAVERQ!$BK$1) -> 15.077737 | GM70: =(HAVERQ!BL154*HAVERQ!$BL$1)+(HAVERQ!BM154*HAVERQ!$BM$1)+(HAVERQ!BN154*HAVERQ!$BN$1)+(HAVERQ!BO154*HAVERQ!$BO$1) -> 8.9429223 | GR70: 42552 | GS70: =100*(HAVERQ!BP154/HAVERQ!BR154) -> 25.155901 | GT70: =AVERAGE($GS$4:$GS$103) -> 24.605137 | GV70: 42552 | GW70: =100*(HAVERQ!BP154/HAVERQ!BR154) -> 25.155901 | GX70: =100*((DataQ!F185/DataQ!F181)-1) -> 0.72085025
FZ71: 42644 | GA71: =100*((HAVERQ!S155/HAVERQ!S151)-1) -> 1.4989607 | GB71: =MIN(GI70:GJ70) -> -0.27016572 | GC71: =+GF71-GB71 -> 0.36483946 | GD71: =AVERAGE(GB71,GF71) -> -0.087745984 | GF71: =MAX(GI70:GJ70) -> 0.094673748 | GH71: 42644 | GI71: =(GL71-GI$1)/GI$2 -> 0.0049503794 | GJ71: =(GM71-GJ$1)/GJ$2 -> 0.55775463 | GL71: =(HAVERQ!BJ155*HAVERQ!$BJ$1)+(HAVERQ!BK155*HAVERQ!$BK$1) -> 18.077737 | GM71: =(HAVERQ!BL155*HAVERQ!$BL$1)+(HAVERQ!BM155*HAVERQ!$BM$1)+(HAVERQ!BN155*HAVERQ!$BN$1)+(HAVERQ!BO155*HAVERQ!$BO$1) -> 16.540788 | GP71: =HAVERQ!BH155 -> 1.3 | GR71: 42644 | GS71: =100*(HAVERQ!BP155/HAVERQ!BR155) -> 25.698142 | GT71: =AVERAGE($GS$4:$GS$103) -> 24.605137 | GV71: 42644 | GW71: =100*(HAVERQ!BP155/HAVERQ!BR155) -> 25.698142 | GX71: =100*((DataQ!F186/DataQ!F182)-1) -> 1.1563939
FZ72: 42736 | GA72: =100*((HAVERQ!S156/HAVERQ!S152)-1) -> 1.3878786 | GB72: =MIN(GI71:GJ71) -> 0.0049503794 | GC72: =+GF72-GB72 -> 0.55280425 | GD72: =AVERAGE(GB72,GF72) -> 0.28135251 | GF72: =MAX(GI71:GJ71) -> 0.55775463 | GH72: 42736 | GI72: =(GL72-GI$1)/GI$2 -> 0.46347721 | GJ72: =(GM72-GJ$1)/GJ$2 -> 0.63383375 | GL72: =(HAVERQ!BJ156*HAVERQ!$BJ$1)+(HAVERQ!BK156*HAVERQ!$BK$1) -> 23.077737 | GM72: =(HAVERQ!BL156*HAVERQ!$BL$1)+(HAVERQ!BM156*HAVERQ!$BM$1)+(HAVERQ!BN156*HAVERQ!$BN$1)+(HAVERQ!BO156*HAVERQ!$BO$1) -> 17.789034 | GP72: =HAVERQ!BH156 -> 0.9 | GR72: 42736 | GS72: =100*(HAVERQ!BP156/HAVERQ!BR156) -> 25.666706 | GT72: =AVERAGE($GS$4:$GS$103) -> 24.605137 | GV72: 42736 | GW72: =100*(HAVERQ!BP156/HAVERQ!BR156) -> 25.666706 | GX72: =100*((DataQ!F187/DataQ!F183)-1) -> 2.5453424
FZ73: 42826 | GA73: =100*((HAVERQ!S157/HAVERQ!S153)-1) -> 0.85064522 | GB73: =MIN(GI72:GJ72) -> 0.46347721 | GC73: =+GF73-GB73 -> 0.17035654 | GD73: =AVERAGE(GB73,GF73) -> 0.54865548 | GF73: =MAX(GI72:GJ72) -> 0.63383375 | GH73: 42826 | GI73: =(GL73-GI$1)/GI$2 -> 0.32996848 | GJ73: =(GM73-GJ$1)/GJ$2 -> 0.80666628 | GL73: =(HAVERQ!BJ157*HAVERQ!$BJ$1)+(HAVERQ!BK157*HAVERQ!$BK$1) -> 21.621892 | GM73: =(HAVERQ!BL157*HAVERQ!$BL$1)+(HAVERQ!BM157*HAVERQ!$BM$1)+(HAVERQ!BN157*HAVERQ!$BN$1)+(HAVERQ!BO157*HAVERQ!$BO$1) -> 20.624734 | GP73: =HAVERQ!BH157 -> 0.5 | GR73: 42826 | GS73: =100*(HAVERQ!BP157/HAVERQ!BR157) -> 25.243045 | GT73: =AVERAGE($GS$4:$GS$103) -> 24.605137 | GV73: 42826 | GW73: =100*(HAVERQ!BP157/HAVERQ!BR157) -> 25.243045 | GX73: =100*((DataQ!F188/DataQ!F184)-1) -> 1.4605074
FZ74: 42917 | GA74: =100*((HAVERQ!S158/HAVERQ!S154)-1) -> 1.0550658 | GB74: =MIN(GI73:GJ73) -> 0.32996848 | GC74: =+GF74-GB74 -> 0.4766978 | GD74: =AVERAGE(GB74,GF74) -> 0.56831738 | GF74: =MAX(GI73:GJ73) -> 0.80666628 | GH74: 42917 | GI74: =(GL74-GI$1)/GI$2 -> 0.32996848 | GJ74: =(GM74-GJ$1)/GJ$2 -> 1.0186842 | GL74: =(HAVERQ!BJ158*HAVERQ!$BJ$1)+(HAVERQ!BK158*HAVERQ!$BK$1) -> 21.621892 | GM74: =(HAVERQ!BL158*HAVERQ!$BL$1)+(HAVERQ!BM158*HAVERQ!$BM$1)+(HAVERQ!BN158*HAVERQ!$BN$1)+(HAVERQ!BO158*HAVERQ!$BO$1) -> 24.103357 | GP74: =HAVERQ!BH158 -> 0.9 | GR74: 42917 | GS74: =100*(HAVERQ!BP158/HAVERQ!BR158) -> 25.189307 | GT74: =AVERAGE($GS$4:$GS$103) -> 24.605137 | GV74: 42917 | GW74: =100*(HAVERQ!BP158/HAVERQ!BR158) -> 25.189307 | GX74: =100*((DataQ!F189/DataQ!F185)-1) -> 3.0151689
FZ75: 43009 | GA75: =100*((HAVERQ!S159/HAVERQ!S155)-1) -> 0.59130635 | GB75: =MIN(GI74:GJ74) -> 0.32996848 | GC75: =+GF75-GB75 -> 0.68871571 | GD75: =AVERAGE(GB75,GF75) -> 0.67432633 | GF75: =MAX(GI74:GJ74) -> 1.0186842 | GH75: 43009 | GI75: =(GL75-GI$1)/GI$2 -> 0.11804232 | GJ75: =(GM75-GJ$1)/GJ$2 -> 0.35196952 | GL75: =(HAVERQ!BJ159*HAVERQ!$BJ$1)+(HAVERQ!BK159*HAVERQ!$BK$1) -> 19.310946 | GM75: =(HAVERQ!BL159*HAVERQ!$BL$1)+(HAVERQ!BM159*HAVERQ!$BM$1)+(HAVERQ!BN159*HAVERQ!$BN$1)+(HAVERQ!BO159*HAVERQ!$BO$1) -> 13.164428 | GO75: =HAVERQ!BI159 -> 0.8 | GP75: =HAVERQ!BH159 -> 1.2 | GR75: 43009 | GS75: =100*(HAVERQ!BP159/HAVERQ!BR159) -> 25.970341 | GT75: =AVERAGE($GS$4:$GS$103) -> 24.605137 | GV75: 43009 | GW75: =100*(HAVERQ!BP159/HAVERQ!BR159) -> 25.970341 | GX75: =100*((DataQ!F190/DataQ!F186)-1) -> 4.2156007
FZ76: 43101 | GA76: =100*((HAVERQ!S160/HAVERQ!S156)-1) -> 0.28697698 | GB76: =MIN(GI75:GJ75) -> 0.11804232 | GC76: =+GF76-GB76 -> 0.2339272 | GD76: =AVERAGE(GB76,GF76) -> 0.23500592 | GF76: =MAX(GI75:GJ75) -> 0.35196952 | GH76: 43101 | GI76: =(GL76-GI$1)/GI$2 -> 0.42167384 | GJ76: =(GM76-GJ$1)/GJ$2 -> 0.68239783 | GL76: =(HAVERQ!BJ160*HAVERQ!$BJ$1)+(HAVERQ!BK160*HAVERQ!$BK$1) -> 22.621892 | GM76: =(HAVERQ!BL160*HAVERQ!$BL$1)+(HAVERQ!BM160*HAVERQ!$BM$1)+(HAVERQ!BN160*HAVERQ!$BN$1)+(HAVERQ!BO160*HAVERQ!$BO$1) -> 18.585836 | GO76: =HAVERQ!BI160 -> 0.65 | GP76: =HAVERQ!BH160 -> 1.1 | GR76: 43101 | GS76: =100*(HAVERQ!BP160/HAVERQ!BR160) -> 24.820089 | GT76: =AVERAGE($GS$4:$GS$103) -> 24.605137 | GV76: 43101 | GW76: =100*(HAVERQ!BP160/HAVERQ!BR160) -> 24.820089 | GX76: =100*((DataQ!F191/DataQ!F187)-1) -> 2.4656823
FZ77: 43191 | GA77: =100*((HAVERQ!S161/HAVERQ!S157)-1) -> 0.3327978 | GB77: =MIN(GI76:GJ76) -> 0.42167384 | GC77: =+GF77-GB77 -> 0.26072399 | GD77: =AVERAGE(GB77,GF77) -> 0.55203584 | GF77: =MAX(GI76:GJ76) -> 0.68239783 | GH77: 43191 | GI77: =(GL77-GI$1)/GI$2 -> 0.49912149 | GJ77: =(GM77-GJ$1)/GJ$2 -> 0.28858492 | GL77: =(HAVERQ!BJ161*HAVERQ!$BJ$1)+(HAVERQ!BK161*HAVERQ!$BK$1) -> 23.466419 | GM77: =(HAVERQ!BL161*HAVERQ!$BL$1)+(HAVERQ!BM161*HAVERQ!$BM$1)+(HAVERQ!BN161*HAVERQ!$BN$1)+(HAVERQ!BO161*HAVERQ!$BO$1) -> 12.124464 | GO77: =HAVERQ!BI161 -> 0.45 | GP77: =HAVERQ!BH161 -> 1.2 | GR77: 43191 | GS77: =100*(HAVERQ!BP161/HAVERQ!BR161) -> 25.072439 | GT77: =AVERAGE($GS$4:$GS$103) -> 24.605137 | GV77: 43191 | GW77: =100*(HAVERQ!BP161/HAVERQ!BR161) -> 25.072439 | GX77: =100*((DataQ!F192/DataQ!F188)-1) -> 4.4057963
FZ78: 43282 | GA78: =100*((HAVERQ!S162/HAVERQ!S158)-1) -> 0.32894737 | GB78: =MIN(GI77:GJ77) -> 0.28858492 | GC78: =+GF78-GB78 -> 0.21053657 | GD78: =AVERAGE(GB78,GF78) -> 0.3938532 | GF78: =MAX(GI77:GJ77) -> 0.49912149 | GH78: 43282 | GI78: =(GL78-GI$1)/GI$2 -> 0.37177184 | GJ78: =(GM78-GJ$1)/GJ$2 -> 0.39320026 | GL78: =(HAVERQ!BJ162*HAVERQ!$BJ$1)+(HAVERQ!BK162*HAVERQ!$BK$1) -> 22.077737 | GM78: =(HAVERQ!BL162*HAVERQ!$BL$1)+(HAVERQ!BM162*HAVERQ!$BM$1)+(HAVERQ!BN162*HAVERQ!$BN$1)+(HAVERQ!BO162*HAVERQ!$BO$1) -> 13.84091 | GO78: =HAVERQ!BI162 -> 0.6 | GP78: =HAVERQ!BH162 -> 1.1 | GR78: 43282 | GS78: =100*(HAVERQ!BP162/HAVERQ!BR162) -> 24.724311 | GT78: =AVERAGE($GS$4:$GS$103) -> 24.605137 | GV78: 43282 | GW78: =100*(HAVERQ!BP162/HAVERQ!BR162) -> 24.724311 | GX78: =100*((DataQ!F193/DataQ!F189)-1) -> 2.5605318
FZ79: 43374 | GA79: =100*((HAVERQ!S163/HAVERQ!S159)-1) -> 1.0609623 | GB79: =MIN(GI78:GJ78) -> 0.37177184 | GC79: =+GF79-GB79 -> 0.021428417 | GD79: =AVERAGE(GB79,GF79) -> 0.38248605 | GF79: =MAX(GI78:GJ78) -> 0.39320026 | GH79: 43374 | GI79: =(GL79-GI$1)/GI$2 -> 0.20261882 | GJ79: =(GM79-GJ$1)/GJ$2 -> 0.39468719 | GL79: =(HAVERQ!BJ163*HAVERQ!$BJ$1)+(HAVERQ!BK163*HAVERQ!$BK$1) -> 20.23321 | GM79: =(HAVERQ!BL163*HAVERQ!$BL$1)+(HAVERQ!BM163*HAVERQ!$BM$1)+(HAVERQ!BN163*HAVERQ!$BN$1)+(HAVERQ!BO163*HAVERQ!$BO$1) -> 13.865306 | GO79: =HAVERQ!BI163 -> 0.3 | GP79: =HAVERQ!BH163 -> 1 | GR79: 43374 | GS79: =100*(HAVERQ!BP163/HAVERQ!BR163) -> 24.399701 | GT79: =AVERAGE($GS$4:$GS$103) -> 24.605137 | GV79: 43374 | GW79: =100*(HAVERQ!BP163/HAVERQ!BR163) -> 24.399701 | GX79: =100*((DataQ!F194/DataQ!F190)-1) -> 1.4104639
FZ80: 43466 | GA80: =100*((HAVERQ!S164/HAVERQ!S160)-1) -> 1.4078865 | GB80: =MIN(GI79:GJ79) -> 0.20261882 | GC80: =+GF80-GB80 -> 0.19206837 | GD80: =AVERAGE(GB80,GF80) -> 0.29865301 | GF80: =MAX(GI79:GJ79) -> 0.39468719 | GH80: 43466 | GI80: =(GL80-GI$1)/GI$2 -> 0.096655745 | GJ80: =(GM80-GJ$1)/GJ$2 -> -0.21249618 | GL80: =(HAVERQ!BJ164*HAVERQ!$BJ$1)+(HAVERQ!BK164*HAVERQ!$BK$1) -> 19.077737 | GM80: =(HAVERQ!BL164*HAVERQ!$BL$1)+(HAVERQ!BM164*HAVERQ!$BM$1)+(HAVERQ!BN164*HAVERQ!$BN$1)+(HAVERQ!BO164*HAVERQ!$BO$1) -> 3.9031203 | GO80: =HAVERQ!BI164 -> 0.15 | GP80: =HAVERQ!BH164 -> 0.7 | GR80: 43466 | GS80: =100*(HAVERQ!BP164/HAVERQ!BR164) -> 24.128477 | GT80: =AVERAGE($GS$4:$GS$103) -> 24.605137 | GV80: 43466 | GW80: =100*(HAVERQ!BP164/HAVERQ!BR164) -> 24.128477 | GX80: =100*((DataQ!F195/DataQ!F191)-1) -> 3.872899
FZ81: 43556 | GA81: =100*((HAVERQ!S165/HAVERQ!S161)-1) -> 1.6413131 | GB81: =MIN(GI80:GJ80) -> -0.21249618 | GC81: =+GF81-GB81 -> 0.30915192 | GD81: =AVERAGE(GB81,GF81) -> -0.057920217 | GF81: =MAX(GI80:GJ80) -> 0.096655745 | GH81: 43556 | GI81: =(GL81-GI$1)/GI$2 -> 0.20974768 | GJ81: =(GM81-GJ$1)/GJ$2 -> 0.50475699 | GL81: =(HAVERQ!BJ165*HAVERQ!$BJ$1)+(HAVERQ!BK165*HAVERQ!$BK$1) -> 20.310946 | GM81: =(HAVERQ!BL165*HAVERQ!$BL$1)+(HAVERQ!BM165*HAVERQ!$BM$1)+(HAVERQ!BN165*HAVERQ!$BN$1)+(HAVERQ!BO165*HAVERQ!$BO$1) -> 15.671245 | GO81: =HAVERQ!BI165 -> -0.05 | GP81: =HAVERQ!BH165 -> 0.8 | GR81: 43556 | GS81: =100*(HAVERQ!BP165/HAVERQ!BR165) -> 24.163632 | GT81: =AVERAGE($GS$4:$GS$103) -> 24.605137 | GV81: 43556 | GW81: =100*(HAVERQ!BP165/HAVERQ!BR165) -> 24.163632 | GX81: =100*((DataQ!F196/DataQ!F192)-1) -> 24.742239
FZ82: 43647 | GA82: =100*((HAVERQ!S166/HAVERQ!S162)-1) -> 1.5395581 | GB82: =MIN(GI81:GJ81) -> 0.20974768 | GC82: =+GF82-GB82 -> 0.29500931 | GD82: =AVERAGE(GB82,GF82) -> 0.35725234 | GF82: =MAX(GI81:GJ81) -> 0.50475699 | GH82: 43647 | GI82: =(GL82-GI$1)/GI$2 -> -0.016436192 | GJ82: =(GM82-GJ$1)/GJ$2 -> -0.0092241456 | GL82: =(HAVERQ!BJ166*HAVERQ!$BJ$1)+(HAVERQ!BK166*HAVERQ!$BK$1) -> 17.844527 | GM82: =(HAVERQ!BL166*HAVERQ!$BL$1)+(HAVERQ!BM166*HAVERQ!$BM$1)+(HAVERQ!BN166*HAVERQ!$BN$1)+(HAVERQ!BO166*HAVERQ!$BO$1) -> 7.2382476 | GO82: =HAVERQ!BI166 -> -0.1 | GP82: =HAVERQ!BH166 -> 0.9 | GR82: 43647 | GS82: =100*(HAVERQ!BP166/HAVERQ!BR166) -> 25.011035 | GT82: =AVERAGE($GS$4:$GS$103) -> 24.605137 | GV82: 43647 | GW82: =100*(HAVERQ!BP166/HAVERQ!BR166) -> 25.011035 | GX82: =100*((DataQ!F197/DataQ!F193)-1) -> 10.361268
FZ83: 43739 | GA83: =100*((HAVERQ!S167/HAVERQ!S163)-1) -> 1.1831801 | GB83: =MIN(GI82:GJ82) -> -0.016436192 | GC83: =+GF83-GB83 -> 0.0072120464 | GD83: =AVERAGE(GB83,GF83) -> -0.012830169 | GF83: =MAX(GI82:GJ82) -> -0.0092241456 | GH83: 43739 | GI83: =(GL83-GI$1)/GI$2 -> -0.030693906 | GJ83: =(GM83-GJ$1)/GJ$2 -> -0.63518723 | GL83: =(HAVERQ!BJ167*HAVERQ!$BJ$1)+(HAVERQ!BK167*HAVERQ!$BK$1) -> 17.689054 | GM83: =(HAVERQ!BL167*HAVERQ!$BL$1)+(HAVERQ!BM167*HAVERQ!$BM$1)+(HAVERQ!BN167*HAVERQ!$BN$1)+(HAVERQ!BO167*HAVERQ!$BO$1) -> -3.0320612 | GO83: =HAVERQ!BI167 -> -0.25 | GP83: =HAVERQ!BH167 -> -1.5 | GR83: 43739 | GS83: =100*(HAVERQ!BP167/HAVERQ!BR167) -> 25.232794 | GT83: =AVERAGE($GS$4:$GS$103) -> 24.605137 | GV83: 43739 | GW83: =100*(HAVERQ!BP167/HAVERQ!BR167) -> 25.232794 | GX83: =100*((DataQ!F198/DataQ!F194)-1) -> 11.727665
FZ84: 43831 | GA84: =100*((HAVERQ!S168/HAVERQ!S164)-1) -> 0.48253287 | GB84: =MIN(GI83:GJ83) -> -0.63518723 | GC84: =+GF84-GB84 -> 0.60449332 | GD84: =AVERAGE(GB84,GF84) -> -0.33294057 | GF84: =MAX(GI83:GJ83) -> -0.030693906 | GH84: 43831 | GI84: =(GL84-GI$1)/GI$2 -> 0.47060606 | GJ84: =(GM84-GJ$1)/GJ$2 -> 0.29987531 | GL84: =(HAVERQ!BJ168*HAVERQ!$BJ$1)+(HAVERQ!BK168*HAVERQ!$BK$1) -> 23.155473 | GM84: =(HAVERQ!BL168*HAVERQ!$BL$1)+(HAVERQ!BM168*HAVERQ!$BM$1)+(HAVERQ!BN168*HAVERQ!$BN$1)+(HAVERQ!BO168*HAVERQ!$BO$1) -> 12.309708 | GO84: =HAVERQ!BI168 -> -0.3 | GP84: =HAVERQ!BH168 -> -4.9 | GR84: 43831 | GS84: =100*(HAVERQ!BP168/HAVERQ!BR168) -> 24.337594 | GT84: =AVERAGE($GS$4:$GS$103) -> 24.605137 | GV84: 43831 | GW84: =100*(HAVERQ!BP168/HAVERQ!BR168) -> 24.337594 | GX84: =100*((DataQ!F199/DataQ!F195)-1) -> 9.9731084
FZ85: 43922 | GA85: =100*((HAVERQ!S169/HAVERQ!S165)-1) -> -1.1562482 | GB85: =MIN(GI84:GJ84) -> 0.29987531 | GC85: =+GF85-GB85 -> 0.17073075 | GD85: =AVERAGE(GB85,GF85) -> 0.38524069 | GF85: =MAX(GI84:GJ84) -> 0.47060606 | GH85: 43922 | GI85: =(GL85-GI$1)/GI$2 -> -3.2332528 | GJ85: =(GM85-GJ$1)/GJ$2 -> -3.4133843 | GL85: =(HAVERQ!BJ169*HAVERQ!$BJ$1)+(HAVERQ!BK169*HAVERQ!$BK$1) -> -17.23321 | GM85: =(HAVERQ!BL169*HAVERQ!$BL$1)+(HAVERQ!BM169*HAVERQ!$BM$1)+(HAVERQ!BN169*HAVERQ!$BN$1)+(HAVERQ!BO169*HAVERQ!$BO$1) -> -48.614529 | GO85: =HAVERQ!BI169 -> -4 | GP85: =HAVERQ!BH169 -> -1.9 | GR85: 43922 | GS85: =100*(HAVERQ!BP169/HAVERQ!BR169) -> 24.093354 | GT85: =AVERAGE($GS$4:$GS$103) -> 24.605137 | GV85: 43922 | GW85: =100*(HAVERQ!BP169/HAVERQ!BR169) -> 24.093354 | GX85: =100*((DataQ!F200/DataQ!F196)-1) -> -13.621606
FZ86: 44013 | GA86: =100*((HAVERQ!S170/HAVERQ!S166)-1) -> -2.8667696 | GB86: =MIN(GI85:GJ85) -> -3.4133843 | GC86: =+GF86-GB86 -> 0.18013152 | GD86: =AVERAGE(GB86,GF86) -> -3.3233186 | GF86: =MAX(GI85:GJ85) -> -3.2332528 | GH86: 44013 | GI86: =(GL86-GI$1)/GI$2 -> -1.9279911 | GJ86: =(GM86-GJ$1)/GJ$2 -> -2.392262 | GL86: =(HAVERQ!BJ170*HAVERQ!$BJ$1)+(HAVERQ!BK170*HAVERQ!$BK$1) -> -3 | GM86: =(HAVERQ!BL170*HAVERQ!$BL$1)+(HAVERQ!BM170*HAVERQ!$BM$1)+(HAVERQ!BN170*HAVERQ!$BN$1)+(HAVERQ!BO170*HAVERQ!$BO$1) -> -31.860758 | GO86: =HAVERQ!BI170 -> -4.9 | GP86: =HAVERQ!BH170 -> 1.6 | GR86: 44013 | GS86: =100*(HAVERQ!BP170/HAVERQ!BR170) -> 25.24976 | GT86: =AVERAGE($GS$4:$GS$103) -> 24.605137 | GV86: 44013 | GW86: =100*(HAVERQ!BP170/HAVERQ!BR170) -> 25.24976 | GX86: =100*((DataQ!F201/DataQ!F197)-1) -> -2.4675534
... FZ102: 45474 | GA102: =100*((HAVERQ!S186/HAVERQ!S182)-1) -> 0.99920393 | GB102: =MIN(GI101:GJ101) -> 0.21435383 | GC102: =+GF102-GB102 -> 0.63733141 | GD102: =AVERAGE(GB102,GF102) -> 0.53301953 | GF102: =MAX(GI101:GJ101) -> 0.85168524 | GH102: 45474 | GI102: =(GL102-GI$1)/GI$2 -> 0.44921949 | GJ102: =(GM102-GJ$1)/GJ$2 -> -0.085119931 | GL102: =(HAVERQ!BJ186*HAVERQ!$BJ$1)+(HAVERQ!BK186*HAVERQ!$BK$1) -> 22.922263 | GM102: =(HAVERQ!BL186*HAVERQ!$BL$1)+(HAVERQ!BM186*HAVERQ!$BM$1)+(HAVERQ!BN186*HAVERQ!$BN$1)+(HAVERQ!BO186*HAVERQ!$BO$1) -> 5.9930093 | GO102: =HAVERQ!BI186 -> 1 | GP102: =HAVERQ!BH186 -> 0 | GR102: 45474 | GS102: =100*(HAVERQ!BP186/HAVERQ!BR186) -> 23.244692 | GT102: =AVERAGE($GS$4:$GS$103) -> 24.605137 | GV102: 45474 | GW102: =100*(HAVERQ!BP186/HAVERQ!BR186) -> 23.244692 | GX102: =100*((DataQ!F217/DataQ!F213)-1) -> 6.1262414
FZ103: 45566 | GB103: =MIN(GI102:GJ102) -> -0.085119931 | GC103: =+GF103-GB103 -> 0.53433942 | GD103: =AVERAGE(GB103,GF103) -> 0.18204978 | GF103: =MAX(GI102:GJ102) -> 0.44921949 | GH103: 45566 | GI103: =(GL103-GI$1)/GI$2 -> -0.29155229 | GJ103: =(GM103-GJ$1)/GJ$2 -> -1.2579475 | GL103: =(HAVERQ!BJ187*HAVERQ!$BJ$1)+(HAVERQ!BK187*HAVERQ!$BK$1) -> 14.844527 | GM103: =(HAVERQ!BL187*HAVERQ!$BL$1)+(HAVERQ!BM187*HAVERQ!$BM$1)+(HAVERQ!BN187*HAVERQ!$BN$1)+(HAVERQ!BO187*HAVERQ!$BO$1) -> -13.24982 | GO103: =HAVERQ!BI187 -> 1.5 | GR103: 45566 | GS103: =100*(HAVERQ!BP187/HAVERQ!BR187) -> 22.709182 | GT103: =AVERAGE($GS$4:$GS$103) -> 24.605137 | GV103: 45566 | GW103: =100*(HAVERQ!BP187/HAVERQ!BR187) -> 22.709182
FZ104: 45658 | GB104: =MIN(GI103:GJ103) -> -1.2579475 | GC104: =+GF104-GB104 -> 0.9663952 | GD104: =AVERAGE(GB104,GF104) -> -0.77474989 | GF104: =MAX(GI103:GJ103) -> -0.29155229

Sheet NICs rates 25-26
A1: Employer (secondary) contribution rates | J1: Class 1 National Insurance thresholds
A2: You pay secondary contributions (employer’s National Insurance) to HMRC as part of your PAYE bill. Find out more about running payroll and paying HMRC.
A3: Pay employers’ PAYE tax and National Insurance.
A4: National Insurance category letter | B4: Earnings above secondary threshold up to and including lower earnings limit | C4: Earnings above lower earnings limit up to and including Freeport and Investment Zone upper secondary thresholds | D4: Earnings above Freeport and Investment Zone upper secondary thresholds up to and including upper earnings limit, upper secondary thresholds for under 21s, apprentices and veterans | E4: Balance of earnings above upper earnings limit, upper secondary thresholds for under 21s, apprentices and veterans | J4: Class 1 National Insurance thresholds | K4: 2025 to 2026
A5: A | B5: 0.15 | C5: 0.15 | D5: 0.15 | E5: 0.15 | J5: Lower earnings limit | K5: £125 per week
A6: B | B6: 0.15 | C6: 0.15 | D6: 0.15 | E6: 0.15 | K6: £542 per month
A7: C | B7: 0.15 | C7: 0.15 | D7: 0.15 | E7: 0.15 | K7: £6,500 per year
A8: D (Investment Zone — deferment) | B8: 0 | C8: 0 | D8: 0.15 | E8: 0.15 | J8: Primary threshold | K8: £242 per week
A9: E (Investment Zone — married women and widows reduced rate) | B9: 0 | C9: 0 | D9: 0.15 | E9: 0.15 | K9: £1,048 per month
A10: F (Freeport) | B10: 0 | C10: 0 | D10: 0.15 | E10: 0.15 | K10: £12,570 per year
A11: H (apprentice under 25) | B11: 0 | C11: 0 | D11: 0 | E11: 0.15 | J11: Secondary threshold | K11: £96 per week
A12: I (Freeport — married women and widows reduced rate) | B12: 0 | C12: 0 | D12: 0.15 | E12: 0.15 | K12: £417 per month
A13: J | B13: 0.15 | C13: 0.15 | D13: 0.15 | E13: 0.15 | K13: £5,000 per year
A14: K (Investment Zone — state pensioner) | B14: 0 | C14: 0 | D14: 0.15 | E14: 0.15 | J14: Freeport upper secondary threshold | K14: £481 per week
A15: L (Freeport — deferment) | B15: 0 | C15: 0 | D15: 0.15 | E15: 0.15 | K15: £2,083 per month
A16: M (under 21) | B16: 0 | C16: 0 | D16: 0 | E16: 0.15 | K16: £25,000 per year
A17: N (Investment Zone) | B17: 0 | C17: 0 | D17: 0.15 | E17: 0.15 | J17: Investment Zone upper secondary threshold | K17: £481 per week
A18: S (Freeport — state pensioner) | B18: 0 | C18: 0 | D18: 0.15 | E18: 0.15 | K18: £2,083 per month
A19: V (veteran) | B19: 0 | C19: 0 | D19: 0 | E19: 0.15 | K19: £25,000 per year
A20: Z (under 21 — deferment) | B20: 0 | C20: 0 | D20: 0 | E20: 0.15 | J20: Upper secondary threshold (under 21) | K20: £967 per week
K21: £4,189 per month
K22: £50,270 per year
J23: Apprentice upper secondary threshold | K23: £967 per week
J24: (apprentice under 25) | K24: £4,189 per month
K25: £50,270 per year
J26: Veterans upper secondary threshold | K26: £967 per week
K27: £4,189 per month
K28: £50,270 per year
J29: Upper earnings limit | K29: £967 per week
K30: £4,189 per month
K31: £50,270 per year

Sheet DMP - NICs Reaction
A1: Reaction to the Change in National Insurance contribution following the November Budget
B3: Lower employee wages | C3: Lower number of employees | D3: Higher prices | E3: Lower profit margins | F3: Other | G3: None of the above
A4: 45597 | B4: 37.88 | C4: 53.68 | D4: 53.64 | E4: 58.72 | F4: 7.51 | G4: 2.67
A5: 45627 | B5: 40.67 | C5: 52.76 | D5: 54.45 | E5: 63.5 | F5: 7.33 | G5: 3.75
A6: 45658 | B6: 36.63 | C6: 53.63 | D6: 61.1 | E6: 63.46 | F6: 11.88 | G6: 2.94
A33: Source: Decision Maker Panel
A35: Notes:
A37: Data are based on responses to the question: 'How do you expect your business to respond to the changes to employer National Insurance contributions announced in the November 2024 Budget?’ Breaking down into NLW, the firms, the following question was used: ‘Approximately, what percentage of your employees were paid at the compulsory National Living Wage/National Minimum Wage in each of the following periods?’ Firms could chose multiple options
A39: Data are average percentage impacts.
A41: Return to Contents

Sheet ASHE Annual pay All SIC
A1: SIC2007 Table 5.7a Annual pay - Gross (£) - For all employee jobsa: United Kingdom, 2024
C3: Number | E3: Annual | G3: Annual
C4: of jobsb | E4: percentage | G4: percentage | H4: Percentiles
A5: Description | B5: Code | C5: (thousand) | D5: Median | E5: change | F5: Mean | G5: change | H5: 10 | I5: 20 | J5: 25 | K5: 30 | L5: 40 | M5: 60 | N5: 70 | O5: 75 | P5: 80 | Q5: 90
A6: United Kingdom | B6: K02000001 | C6: 23385 | D6: 31602 | E6: 7.1 | F6: 38224 | G6: 8 | H6: 11004 | I6: 17995 | J6: 21216 | K6: 23541 | L6: 27440 | M6: 36538 | N6: 42519 | O6: 46084 | P6: 50344 | Q6: 65227
A7: Great Britain | B7: K03000001 | C7: 22563 | D7: 31717 | E7: 7 | F7: 38422 | G7: 8.1 | H7: 11045 | I7: 18035 | J7: 21266 | K7: 23615 | L7: 27536 | M7: 36655 | N7: 42714 | O7: 46329 | P7: 50562 | Q7: 65591 | S7: Key | T7: Statistical robustness
A8: England and Wales | B8: K04000001 | C8: 20470 | D8: 31701 | E8: 6.9 | F8: 38668 | G8: 8.1 | H8: 10999 | I8: 18000 | J8: 21240 | K8: 23587 | L8: 27512 | M8: 36651 | N8: 42752 | O8: 46383 | P8: 50756 | Q8: 66106 | S8: CV <= 5% | T8: Estimates are considered precise
A9: England | B9: E92000001 | C9: 19428 | D9: 31875 | E9: 6.9 | F9: 39030 | G9: 8.1 | H9: 11060 | I9: 18079 | J9: 21334 | K9: 23700 | L9: 27645 | M9: 36879 | N9: 43018 | O9: 46714 | P9: 51162 | Q9: 66979 | S9: CV > 5% and <= 10% | T9: Estimates are considered reasonably precise
A10: North East | B10: E12000001 | C10: 807 | D10: 28153 | E10: 6.4 | F10: 31978 | G10: 7.2 | H10: 10658 | I10: 16604 | J10: 19376 | K10: 21752 | L10: 24989 | M10: 31865 | N10: 36989 | O10: 39681 | P10: 43469 | Q10: 53719 | S10: CV > 10% and <= 20% | T10: Estimates are considered acceptable
A11: North West | B11: E12000002 | C11: 2455 | D11: 30296 | E11: 6.7 | F11: 35029 | G11: 7.9 | H11: 11147 | I11: 18043 | J11: 21070 | K11: 23150 | L11: 26563 | M11: 34717 | N11: 40215 | O11: 43674 | P11: 47703 | Q11: 60422 | S11: x = CV > 20% | T11: Estimates are considered unreliable for practical purposes
A12: Yorkshire and The Humber | B12: E12000003 | C12: 1863 | D12: 29811 | E12: 9.2 | F12: 33676 | G12: 8.2 | H12: 11105 | I12: 17839 | J12: 20682 | K12: 22816 | L12: 26081 | M12: 33857 | N12: 38833 | O12: 42114 | P12: 45889 | Q12: 57023 | S12: .. = disclosive
A13: East Midlands | B13: E12000004 | C13: 1577 | D13: 28897 | E13: 7.2 | F13: 32536 | G13: 6.6 | H13: 10239 | I13: 16378 | J13: 19374 | K13: 21930 | L13: 25288 | M13: 32740 | N13: 37791 | O13: 40832 | P13: 44697 | Q13: 55997 | S13: : = not applicable
A14: West Midlands | B14: E12000005 | C14: 1874 | D14: 29891 | E14: 5.8 | F14: 34774 | G14: 6.5 | H14: 10758 | I14: 17417 | J14: 20475 | K14: 22581 | L14: 26042 | M14: 34081 | N14: 39429 | O14: 42914 | P14: 46776 | Q14: 58517 | S14: - = nil or negligible
A15: East | B15: E12000006 | C15: 2073 | D15: 30455 | E15: 6.2 | F15: 35782 | G15: 8.9 | H15: 9567 | I15: 15589 | J15: 18937 | K15: 21920 | L15: 26186 | M15: 35107 | N15: 40908 | O15: 44509 | P15: 48733 | Q15: 62002
A16: London | B16: E12000007 | C16: 3561 | D16: 41581 | E16: 6.3 | F16: 56752 | G16: 7.9 | H16: 13004 | I16: 23776 | J16: 26992 | K16: 30000 | L16: 35750 | M16: 48209 | N16: 57066 | O16: 62548 | P16: 69870 | Q16: 96646
A17: South East | B17: E12000008 | C17: 3279 | D17: 32823 | E17: 6.7 | F17: 38463 | G17: 7.4 | H17: 11310 | I17: 18492 | J17: 21788 | K17: 24225 | L17: 28500 | M17: 38041 | N17: 44215 | O17: 48000 | P17: 52377 | Q17: 67088
A18: South West | B18: E12000009 | C18: 1940 | D18: 29569 | E18: 5.6 | F18: 33455 | G18: 5.1 | H18: 10006 | I18: 16426 | J18: 19728 | K18: 22250 | L18: 26000 | M18: 34191 | N18: 39274 | O18: 42426 | P18: 45771 | Q18: 58134
A19: Wales | B19: W92000004 | C19: 1042 | D19: 29067 | E19: 6.2 | F19: 31925 | G19: 6.6 | H19: 9966 | I19: 16597 | J19: 19638 | K19: 21985 | L19: 25436 | M19: 33032 | N19: 37953 | O19: 41134 | P19: 44767 | Q19: 53668
A20: Scotland | B20: S92000003 | C20: 2093 | D20: 31836 | E20: 8 | F20: 36017 | G20: 8.3 | H20: 11568 | I20: 18474 | J20: 21503 | K20: 23857 | L20: 27781 | M20: 36697 | N20: 42450 | O20: 45769 | P20: 48964 | Q20: 60698
A21: Northern Ireland | B21: N92000002 | C21: 822 | D21: 28825 | E21: 7.6 | F21: 32796 | G21: 4.4 | H21: 10028 | I21: 16396 | J21: 19510 | K21: 21996 | L21: 25465 | M21: 33154 | N21: 38201 | O21: 41094 | P21: 43871 | Q21: 55472
A22: All Industries and Services | C22: 23376 | D22: 31604 | E22: 7.1 | F22: 38226 | G22: 8 | H22: 11009 | I22: 17997 | J22: 21216 | K22: 23542 | L22: 27441 | M22: 36539 | N22: 42520 | O22: 46086 | P22: 50346 | Q22: 65227
A23: All Index of Production Industries | C23: 2498 | D23: 36398 | E23: 6 | F23: 42087 | G23: 6.6 | H23: 21637 | I23: 25483 | J23: 27064 | K23: 28809 | L23: 32486 | M23: 41097 | N23: 46708 | O23: 50016 | P23: 53998 | Q23: 67481
A24: All Manufacturing | C24: 2184 | D24: 35518 | E24: 5.6 | F24: 41220 | G24: 6.3 | H24: 21424 | I24: 25178 | J24: 26686 | K24: 28304 | L24: 31815 | M24: 40140 | N24: 45649 | O24: 49243 | P24: 52987 | Q24: 65939
A25: All Service Industries | C25: 19868 | D25: 30647 | E25: 7.3 | F25: 37559 | G25: 8.2 | H25: 10199 | I25: 16627 | J25: 19826 | K25: 22481 | L25: 26500 | M25: 35621 | N25: 41602 | O25: 45285 | P25: 49576 | Q25: 64466
A26: AGRICULTURE, FORESTRY AND FISHING | B26: A | C26: 129 | D26: 27288 | E26: 2.9 | F26: 28977 | G26: 3.7 | H26: 9753 | I26: 14427 | J26: 18000 | K26: 21045 | L26: 24402 | M26: 30645 | N26: 34589 | O26: 36266 | P26: 38992 | Q26: x
A27: Crop and animal production, hunting and related service activities | B27: 1 | C27: 115 | D27: 26620 | E27: 3.5 | F27: 27887 | G27: 3.8 | H27: 9562 | I27: 13947 | J27: 16697 | K27: 20008 | L27: 23627 | M27: 30000 | N27: 33632 | O27: 35372 | P27: 37679 | Q27: x
A28: Forestry and logging | B28: 2 | C28: 10 | D28: 27941 | E28: 2.2 | F28: 30070 | G28: 2.1 | H28: x | I28: 21212 | J28: 24027 | K28: 24855 | L28: 27179 | M28: 31175 | N28: 37290 | O28: x | P28: x | Q28: x
A29: Fishing and aquaculture | B29: 3 | C29: x | D29: x | F29: x | H29: x | I29: x | J29: x | K29: x | L29: x | M29: x | N29: x | O29: x | P29: x | Q29: x
A30: MINING AND QUARRYING | B30: B | C30: 25 | D30: 47022 | E30: 5.6 | F30: 55436 | G30: 7.2 | H30: 25213 | I30: 31216 | J30: 33999 | K30: 35674 | L30: 40939 | M30: 55032 | N30: 61270 | O30: 64863 | P30: x | Q30: x
A31: Mining of coal and lignite | B31: 5 | C31: :
A32: Extraction of crude petroleum and natural gas | B32: 6 | C32: x | D32: x | F32: 91994 | G32: 6.3 | H32: x | I32: x | J32: x | K32: x | L32: x | M32: x | N32: x | O32: x | P32: x | Q32: x
A33: Mining of metal ores | B33: 7 | C33: :
A34: Other mining and quarrying | B34: 8 | C34: 15 | D34: 38951 | E34: -2.5 | F34: 41276 | G34: -3 | H34: x | I34: 28547 | J34: 30596 | K34: 32022 | L34: 35773 | M34: 43919 | N34: 47320 | O34: 50052 | P34: x | Q34: x
A35: Mining support service activities | B35: 9 | C35: x | D35: 58577 | E35: 29.5 | F35: 64759 | G35: 27.8 | H35: x | I35: x | J35: x | K35: x | L35: 48362 | M35: x | N35: x | O35: x | P35: x | Q35: x
A36: MANUFACTURING | B36: C | C36: 2184 | D36: 35518 | E36: 5.6 | F36: 41220 | G36: 6.3 | H36: 21424 | I36: 25178 | J36: 26686 | K36: 28304 | L36: 31815 | M36: 40140 | N36: 45649 | O36: 49243 | P36: 52987 | Q36: 65939
A37: Manufacture of food products | B37: 10 | C37: 313 | D37: 30314 | E37: 8.6 | F37: 35847 | G37: 11.9 | H37: 18473 | I37: 22428 | J37: 24022 | K37: 25062 | L37: 27555 | M37: 33439 | N37: 37815 | O37: 40750 | P37: 44192 | Q37: 55185
A38: Manufacture of beverages | B38: 11 | C38: 44 | D38: 36909 | E38: -1.2 | F38: 42438 | G38: 0.6 | H38: 23364 | I38: 27376 | J38: 28457 | K38: 30503 | L38: 33432 | M38: 41387 | N38: 46499 | O38: 49533 | P38: 52607 | Q38: x
A39: Manufacture of tobacco products | B39: 12 | C39: :
A40: Manufacture of textiles | B40: 13 | C40: 41 | D40: 26864 | E40: 4 | F40: 30817 | G40: 1.1 | H40: 16780 | I40: 21288 | J40: 22115 | K40: 22912 | L40: 24524 | M40: 29451 | N40: 33405 | O40: 35613 | P40: 37557 | Q40: x
A41: Manufacture of wearing apparel | B41: 14 | C41: 11 | D41: 21207 | E41: 11 | F41: 22244 | G41: 9.3 | H41: 9542 | I41: 11956 | J41: 14560 | K41: 16255 | L41: 18975 | M41: 23557 | N41: 25086 | O41: x | P41: x | Q41: x
A42: Manufacture of leather and related products | B42: 15 | C42: 7 | D42: 26098 | E42: 9.5 | F42: 30279 | G42: 14.8 | H42: x | I42: 21673 | J42: 22393 | K42: 23625 | L42: 24195 | M42: 31094 | N42: x | O42: x | P42: x | Q42: x
A43: Manufacture of wood and of products of wood and cork, except furniture; manufacture of articles of straw and plaiting materials | B43: 16 | C43: 52 | D43: 31620 | E43: 8 | F43: 35949 | G43: -2.4 | H43: 17746 | I43: 23118 | J43: 25008 | K43: 26602 | L43: 28724 | M43: 35254 | N43: 39080 | O43: 41464 | P43: 44474 | Q43: x
A44: Manufacture of paper and paper products | B44: 17 | C44: 42 | D44: 34781 | E44: 5.6 | F44: 39132 | G44: 3.2 | H44: 22595 | I44: 25559 | J44: 26423 | K44: 27885 | L44: 30875 | M44: 38650 | N44: 42980 | O44: 44843 | P44: 49334 | Q44: x
A45: Printing and reproduction of recorded media | B45: 18 | C45: 57 | D45: 29304 | E45: 7.4 | F45: 32959 | G45: 5.2 | H45: 13788 | I45: 21253 | J45: 22664 | K45: 23909 | L45: 26594 | M45: 31949 | N45: 36563 | O45: 40166 | P45: 43196 | Q45: x
A46: Manufacture of coke and refined petroleum products | B46: 19 | C46: 9 | D46: 60982 | E46: 1.8 | F46: 63441 | G46: 4.9 | H46: x | I46: 33667 | J46: 36486 | K46: x | L46: 52611 | M46: 66834 | N46: x | O46: x | P46: x | Q46: x
A47: Manufacture of chemicals and chemical products | B47: 20 | C47: 82 | D47: 36044 | E47: 0.4 | F47: 43448 | G47: -0.1 | H47: 22611 | I47: 26996 | J47: 28364 | K47: 29770 | L47: 32020 | M47: 41159 | N47: 47180 | O47: 49997 | P47: 54530 | Q47: x
A48: Manufacture of basic pharmaceutical products and pharmaceutical preparations | B48: 21 | C48: 42 | D48: 35961 | E48: 1.2 | F48: 42458 | G48: 6.2 | H48: 24025 | I48: 27530 | J48: 28656 | K48: 30460 | L48: 33438 | M48: 40015 | N48: 44146 | O48: 47283 | P48: x | Q48: x
A49: Manufacture of rubber and plastic products | B49: 22 | C49: 146 | D49: 31415 | E49: 5.6 | F49: 36778 | G49: 6.5 | H49: 21034 | I49: 23611 | J49: 24875 | K49: 25906 | L49: 28247 | M49: 34589 | N49: 39004 | O49: 42540 | P49: 45267 | Q49: x
A50: Manufacture of other non-metallic mineral products | B50: 23 | C50: 80 | D50: 35144 | E50: 4.3 | F50: 41040 | G50: 10.5 | H50: 22331 | I50: 26454 | J50: 27838 | K50: 29858 | L50: 32096 | M50: 39982 | N50: 44919 | O50: 47790 | P50: 50968 | Q50: x
A51: Manufacture of basic metals | B51: 24 | C51: 70 | D51: 42192 | E51: 5.5 | F51: 46677 | G51: 6.9 | H51: 25555 | I51: 30393 | J51: 32053 | K51: 34423 | L51: 38235 | M51: 45788 | N51: 53753 | O51: 56541 | P51: 63440 | Q51: x
A52: Manufacture of fabricated metal products, except machinery and equipment | B52: 25 | C52: 256 | D52: 35164 | E52: 7.7 | F52: 39375 | G52: 6.1 | H52: 21888 | I52: 25684 | J52: 27254 | K52: 28829 | L52: 31770 | M52: 39052 | N52: 43711 | O52: 46251 | P52: 49340 | Q52: 59387
A53: Manufacture of computer, electronic and optical products | B53: 26 | C53: 124 | D53: 37633 | E53: 0.7 | F53: 45935 | G53: 4.5 | H53: 21693 | I53: 26309 | J53: 27845 | K53: 30000 | L53: 34081 | M53: 45601 | N53: 51585 | O53: 55656 | P53: 60337 | Q53: x
A54: Manufacture of electrical equipment | B54: 27 | C54: 98 | D54: 37669 | E54: 9.3 | F54: 43939 | G54: 5.4 | H54: 22516 | I54: 25690 | J54: 27234 | K54: 28900 | L54: 32720 | M54: 41740 | N54: 49760 | O54: 53737 | P54: 56303 | Q54: x
A55: Manufacture of machinery and equipment n.e.c. | B55: 28 | C55: 185 | D55: 38968 | E55: 5.2 | F55: 46420 | G55: 6.9 | H55: 24049 | I55: 27756 | J55: 29239 | K55: 31762 | L55: 35498 | M55: 43254 | N55: 48773 | O55: 51486 | P55: 55644 | Q55: x
A56: Manufacture of motor vehicles, trailers and semi-trailers | B56: 29 | C56: 111 | D56: 39869 | E56: 1.2 | F56: 44252 | G56: 3.8 | H56: 23829 | I56: 27766 | J56: 29935 | K56: 31803 | L56: 35289 | M56: 44091 | N56: 49937 | O56: 53595 | P56: 57571 | Q56: x
A57: Manufacture of other transport equipment | B57: 30 | C57: 192 | D57: 48398 | E57: 6.2 | F57: 51074 | G57: 6.2 | H57: 29152 | I57: 34469 | J57: 37477 | K57: 40165 | L57: 44508 | M57: 52873 | N57: 57262 | O57: 60755 | P57: 64109 | Q57: 74410
A58: Manufacture of furniture | B58: 31 | C58: 68 | D58: 28746 | E58: 5.6 | F58: 31794 | G58: 2.6 | H58: 19323 | I58: 22818 | J58: 23804 | K58: 24694 | L58: 26487 | M58: 31475 | N58: 34828 | O58: 37126 | P58: 40123 | Q58: x
A59: Other manufacturing | B59: 32 | C59: 75 | D59: 32398 | E59: 6.5 | F59: 38508 | G59: 7.5 | H59: 14278 | I59: 22165 | J59: 23851 | K59: 25240 | L59: 28568 | M59: 36216 | N59: 42039 | O59: 44989 | P59: 49573 | Q59: x
A60: Repair and installation of machinery and equipment | B60: 33 | C60: 80 | D60: 40328 | E60: 11.4 | F60: 45016 | G60: 11.3 | H60: 22865 | I60: 27368 | J60: 29582 | K60: 32112 | L60: 36145 | M60: 47249 | N60: 52106 | O60: 55051 | P60: 58158 | Q60: x
A61: ELECTRICITY, GAS, STEAM AND AIR CONDITIONING SUPPLY | B61: D | C61: 104 | D61: 51886 | E61: 4.4 | F61: 58605 | G61: 6.7 | H61: 25643 | I61: 34761 | J61: 37550 | K61: 39799 | L61: 45328 | M61: 58546 | N61: 68766 | O61: 73580 | P61: 78153 | Q61: x
A62: Electricity, gas, steam and air conditioning supply | B62: 35 | C62: 104 | D62: 51886 | E62: 4.4 | F62: 58605 | G62: 6.7 | H62: 25643 | I62: 34761 | J62: 37550 | K62: 39799 | L62: 45328 | M62: 58546 | N62: 68766 | O62: 73580 | P62: 78153 | Q62: x
A63: WATER SUPPLY; SEWERAGE, WASTE MANAGEMENT AND REMEDIATION ACTIVITIES | B63: E | C63: 185 | D63: 38435 | E63: 9.2 | F63: 41206 | G63: 8.7 | H63: 23302 | I63: 27373 | J63: 29282 | K63: 31499 | L63: 35256 | M63: 41927 | N63: 45998 | O63: 48565 | P63: 51223 | Q63: x
A64: Water collection, treatment and supply | B64: 36 | C64: 63 | D64: 41568 | E64: 9.7 | F64: 43281 | G64: 3.5 | H64: 25667 | I64: 31929 | J64: 33585 | K64: 35533 | L64: 38315 | M64: 44437 | N64: 47700 | O64: 49900 | P64: 52230 | Q64: x
A65: Sewerage | B65: 37 | C65: 18 | D65: 40031 | E65: 6.1 | F65: 42935 | G65: 9 | H65: 25865 | I65: 29895 | J65: 31855 | K65: 33305 | L65: 37899 | M65: 43890 | N65: 49637 | O65: 51587 | P65: x | Q65: x
A66: Waste collection, treatment and disposal activities; materials recovery | B66: 38 | C66: 99 | D66: 35716 | E66: 8.7 | F66: 39641 | G66: 10.6 | H66: x | I66: 25392 | J66: 27064 | K66: 28685 | L66: 32353 | M66: 39411 | N66: 43479 | O66: 46257 | P66: 49317 | Q66: x
A67: Remediation activities and other waste management services | B67: 39 | C67: x | D67: 35973 | E67: 11.7 | F67: 39419 | G67: 20.3 | H67: x | I67: x | J67: x | K67: x | L67: 33907 | M67: x | N67: x | O67: x | P67: x | Q67: x
A68: CONSTRUCTION | B68: F | C68: 877 | D68: 38209 | E68: 9.5 | F68: 43626 | G68: 9.3 | H68: 14049 | I68: 24000 | J68: 26871 | K68: 29221 | L68: 33835 | M68: 42827 | N68: 49207 | O68: 53463 | P68: 58991 | Q68: 74034
A69: Construction of buildings | B69: 41 | C69: 278 | D69: 42113 | E69: 9.5 | F69: 51073 | G69: 10.3 | H69: 16824 | I69: 25462 | J69: 28875 | K69: 31472 | L69: 36681 | M69: 48370 | N69: 58163 | O69: 63156 | P69: 68799 | Q69: 88559
A70: Civil engineering | B70: 42 | C70: 146 | D70: 41948 | E70: 8.5 | F70: 47171 | G70: 9.2 | H70: 21770 | I70: 27705 | J70: 30522 | K70: 33037 | L70: 37746 | M70: 48350 | N70: 55550 | O70: 60000 | P70: 64056 | Q70: x
A71: Specialised construction activities | B71: 43 | C71: 453 | D71: 35313 | E71: 7.6 | F71: 37914 | G71: 8.9 | H71: 12570 | I71: 22049 | J71: 24762 | K71: 27226 | L71: 31475 | M71: 39479 | N71: 43665 | O71: 46702 | P71: 50412 | Q71: 62110
A72: WHOLESALE AND RETAIL TRADE; REPAIR OF MOTOR VEHICLES AND MOTORCYCLES | B72: G | C72: 3045 | D72: 25560 | E72: 8 | F72: 30854 | G72: 8.5 | H72: 9031 | I72: 12973 | J72: 15193 | K72: 17829 | L72: 22460 | M72: 29275 | N72: 34132 | O72: 37000 | P72: 41018 | Q72: 54968
A73: Wholesale and retail trade and repair of motor vehicles and motorcycles | B73: 45 | C73: 382 | D73: 31785 | E73: 8.3 | F73: 35554 | G73: 10 | H73: 15203 | I73: 23025 | J73: 24530 | K73: 25863 | L73: 28709 | M73: 35000 | N73: 38575 | O73: 41078 | P73: 44338 | Q73: 53610
A74: Wholesale trade, except of motor vehicles and motorcycles | B74: 46 | C74: 931 | D74: 33599 | E74: 6.8 | F74: 41331 | G74: 5.4 | H74: 18541 | I74: 24000 | J74: 25367 | K74: 26789 | L74: 29991 | M74: 37922 | N74: 44100 | O74: 47748 | P74: 53090 | Q74: 71297
A75: Retail trade, except of motor vehicles and motorcycles | B75: 47 | C75: 1732 | D75: 19600 | E75: 8.6 | F75: 24188 | G75: 10 | H75: 7278 | I75: 10162 | J75: 11566 | K75: 12843 | L75: 16021 | M75: 23052 | N75: 26523 | O75: 28848 | P75: 31925 | Q75: 42274
A76: TRANSPORTATION AND STORAGE | B76: H | C76: 980 | D76: 35868 | E76: 10.2 | F76: 40641 | G76: 8 | H76: 19034 | I76: 25371 | J76: 27347 | K76: 29230 | L76: 32313 | M76: 39648 | N76: 44897 | O76: 47741 | P76: 51714 | Q76: 64874
A77: Land transport and transport via pipelines | B77: 49 | C77: 379 | D77: 36759 | E77: 5 | F77: 40261 | G77: 5.7 | H77: 16193 | I77: 25303 | J77: 27564 | K77: 29618 | L77: 33239 | M77: 40753 | N77: 45597 | O77: 48202 | P77: 51900 | Q77: 63923
A78: Water transport | B78: 50 | C78: 11 | D78: 36543 | E78: -0.9 | F78: 39566 | G78: -12.9 | H78: x | I78: 22596 | J78: 24838 | K78: 26316 | L78: 31124 | M78: 41609 | N78: 48736 | O78: x | P78: x | Q78: x
A79: Air transport | B79: 51 | C79: 53 | D79: 37103 | E79: 21 | F79: 51276 | G79: 9.7 | H79: 23681 | I79: 27512 | J79: 30127 | K79: 31303 | L79: 34457 | M79: 44267 | N79: 52962 | O79: 61638 | P79: 75939 | Q79: x
A80: Warehousing and support activities for transportation | B80: 52 | C80: 337 | D80: 36457 | E80: 8.3 | F80: 42278 | G80: 8.4 | H80: 20184 | I80: 24849 | J80: 26709 | K80: 28197 | L80: 31976 | M80: 40910 | N80: 46881 | O80: 50365 | P80: 55187 | Q80: 70901
A81: Postal and courier activities | B81: 53 | C81: 199 | D81: 33561 | E81: 15.9 | F81: 35837 | G81: 12.8 | H81: 20476 | I81: 26123 | J81: 27941 | K81: 29420 | L81: 31222 | M81: 35926 | N81: 38988 | O81: 40994 | P81: 43688 | Q81: 52265
A82: ACCOMMODATION AND FOOD SERVICE ACTIVITIES | B82: I | C82: 969 | D82: 16800 | E82: 11.8 | F82: 20160 | G82: 8.1 | H82: 4239 | I82: 7614 | J82: 8951 | K82: 10323 | L82: 13178 | M82: 21032 | N82: 24960 | O82: 27056 | P82: 29853 | Q82: 38071
A83: Accommodation | B83: 55 | C83: 247 | D83: 21729 | E83: 9.9 | F83: 23701 | G83: 5.2 | H83: 6610 | I83: 10140 | J83: 12009 | K83: 13697 | L83: 17926 | M83: 24417 | N83: 27506 | O83: 29566 | P83: 31704 | Q83: 41834
A84: Food and beverage service activities | B84: 56 | C84: 723 | D84: 15239 | E84: 11.8 | F84: 18950 | G84: 9.2 | H84: 3662 | I84: 6921 | J84: 8308 | K84: 9497 | L84: 12185 | M84: 19262 | N84: 23735 | O84: 26111 | P84: 28778 | Q84: 36950
A85: INFORMATION AND COMMUNICATION | B85: J | C85: 1015 | D85: 46063 | E85: 5.9 | F85: 56613 | G85: 10.5 | H85: 23599 | I85: 29874 | J85: 32656 | K85: 35308 | L85: 40279 | M85: 53159 | N85: 63358 | O85: 68998 | P85: 75248 | Q85: 97242
A86: Publishing activities | B86: 58 | C86: 84 | D86: 39504 | E86: 8 | F86: 46693 | G86: 11.3 | H86: 21630 | I86: 26280 | J86: 27962 | K86: 29664 | L86: 34399 | M86: 44647 | N86: 49826 | O86: 56990 | P86: 63121 | Q86: x
A87: Motion picture, video and television programme production, sound recording and music publishing activities | B87: 59 | C87: 47 | D87: 35517 | E87: 10.9 | F87: 42281 | H87: 9600 | I87: 16012 | J87: 20954 | K87: 24755 | L87: 29984 | M87: 39959 | N87: 46653 | O87: x | P87: x | Q87: x
A88: Programming and broadcasting activities | B88: 60 | C88: 33 | D88: 47269 | E88: -1.1 | F88: 58843 | G88: 18.9 | H88: 28861 | I88: 34809 | J88: 37361 | K88: 40023 | L88: 43060 | M88: 56583 | N88: 65537 | O88: 69997 | P88: 79094 | Q88: x
A89: Telecommunications | B89: 61 | C89: 234 | D89: 43957 | E89: 1.5 | F89: 51534 | G89: 2.8 | H89: 25792 | I89: 31819 | J89: 34575 | K89: 36253 | L89: 39153 | M89: 48138 | N89: 55936 | O89: 61781 | P89: 67753 | Q89: 83579
A90: Computer programming, consultancy and related activities | B90: 62 | C90: 563 | D90: 48873 | E90: 8.6 | F90: 57605 | G90: 8.7 | H90: 23708 | I90: 30079 | J90: 33140 | K90: 35850 | L90: 42066 | M90: 56547 | N90: 66493 | O90: 72022 | P90: 78704 | Q90: 100000
A91: Information service activities | B91: 63 | C91: 53 | D91: 67217 | E91: 42.9 | F91: 95572 | G91: 62.5 | H91: 25926 | I91: 33982 | J91: 36234 | K91: 44131 | L91: 55443 | M91: 78073 | N91: 96036 | O91: 108196 | P91: x | Q91: x
A92: FINANCIAL AND INSURANCE ACTIVITIES | B92: K | C92: 1000 | D92: 47248 | E92: 7.6 | F92: 78379 | G92: 12.8 | H92: 21567 | I92: 27480 | J92: 29873 | K92: 32547 | L92: 39357 | M92: 57365 | N92: 70462 | O92: 78520 | P92: 88623 | Q92: 126000
A93: Financial service activities, except insurance and pension funding | B93: 64 | C93: 560 | D93: 50502 | E93: 0 | F93: 82983 | G93: 7.5 | H93: 22090 | I93: 28241 | J93: 30648 | K93: 34145 | L93: 41551 | M93: 61752 | N93: 75409 | O93: 83879 | P93: 94969 | Q93: 130454
A94: Insurance, reinsurance and pension funding, except compulsory social security | B94: 65 | C94: 95 | D94: 46840 | E94: 12.6 | F94: 60807 | G94: 18.8 | H94: 24353 | I94: 28436 | J94: 30868 | K94: 33628 | L94: 38657 | M94: 55762 | N94: 66775 | O94: 74081 | P94: 83633 | Q94: x
A95: Activities auxiliary to financial services and insurance activities | B95: 66 | C95: 345 | D95: 43331 | E95: 12.9 | F95: 75774 | G95: 20.1 | H95: 19957 | I95: 26094 | J95: 28323 | K95: 30961 | L95: 36426 | M95: 51493 | N95: 63255 | O95: 70847 | P95: 79984 | Q95: x
A96: REAL ESTATE ACTIVITIES | B96: L | C96: 326 | D96: 30891 | E96: 4.1 | F96: 35489 | G96: 3.1 | H96: 12244 | I96: 20165 | J96: 22774 | K96: 24375 | L96: 27826 | M96: 34579 | N96: 38978 | O96: 41645 | P96: 45813 | Q96: 58019
A97: Real estate activities | B97: 68 | C97: 326 | D97: 30891 | E97: 4.1 | F97: 35489 | G97: 3.1 | H97: 12244 | I97: 20165 | J97: 22774 | K97: 24375 | L97: 27826 | M97: 34579 | N97: 38978 | O97: 41645 | P97: 45813 | Q97: 58019
A98: PROFESSIONAL, SCIENTIFIC AND TECHNICAL ACTIVITIES | B98: M | C98: 1823 | D98: 39880 | E98: 5.8 | F98: 50336 | G98: 7 | H98: 15685 | I98: 24000 | J98: 26405 | K98: 28796 | L98: 33860 | M98: 46138 | N98: 54273 | O98: 59607 | P98: 66315 | Q98: 88504
A99: Legal and accounting activities | B99: 69 | C99: 552 | D99: 37326 | E99: 9.7 | F99: 49807 | G99: 5.9 | H99: 15305 | I99: 22529 | J99: 24461 | K99: 26070 | L99: 30620 | M99: 45254 | N99: 54791 | O99: 60694 | P99: 69339 | Q99: 92627
A100: Activities of head offices; management consultancy activities | B100: 70 | C100: 401 | D100: 40497 | E100: 4.5 | F100: 55557 | G100: 8 | H100: 12915 | I100: 23480 | J100: 26209 | K100: 29175 | L100: 34828 | M100: 48287 | N100: 57787 | O100: 64724 | P100: 72463 | Q100: 100840
A101: Architectural and engineering activities; technical testing and analysis | B101: 71 | C101: 422 | D101: 40888 | E101: 4.6 | F101: 49788 | G101: 12.5 | H101: 20615 | I101: 27000 | J101: 29269 | K101: 31366 | L101: 35900 | M101: 46022 | N101: 52609 | O101: 57769 | P101: 63220 | Q101: 79163
...

Sheet ASHE Annual pay FT
A1: Table 1.7a Annual pay - Gross (£) - For full-time employee jobsa: United Kingdom, 2024
C3: Number | E3: Annual | G3: Annual
C4: of jobsb | E4: percentage | G4: percentage | H4: Percentiles
A5: Description | B5: Code | C5: (thousand) | D5: Median | E5: change | F5: Mean | G5: change | H5: 10 | I5: 20 | J5: 25 | K5: 30 | L5: 40 | M5: 60 | N5: 70 | O5: 75 | P5: 80 | Q5: 90
A6: All Employees | C6: 17248 | D6: 37430 | E6: 6.9 | F6: 45836 | G6: 8.2 | H6: 22763 | I6: 26250 | J6: 27986 | K6: 29731 | L6: 33276 | M6: 42148 | N6: 47898 | O6: 51391 | P6: 55912 | Q6: 72150
A7: a Employees on adult rates who have been in the same job for more than a year. Estimates for 2020 and 2021 include employees who have been furloughed under the Coronavirus Job Retention Scheme (CJRS). | S7: Key | T7: Statistical robustness
A8: b Figures for Number of Jobs are for indicative purposes only and should not be considered an accurate estimate of employee job counts. | S8: CV <= 5% | T8: Estimates are considered precise
A9: KEY - The colour coding indicates the quality of each estimate; jobs, median, mean and percentiles but not the annual percentage change. | S9: CV > 5% and <= 10% | T9: Estimates are considered reasonably precise
A10: The quality of an estimate is measured by its coefficient of variation (CV), which is the ratio of the standard error of an estimate to the estimate. | S10: CV > 10% and <= 20% | T10: Estimates are considered acceptable
A11: Source: Annual Survey of Hours and Earnings, Office for National Statistics. | S11: x = CV > 20% | T11: Estimates are considered unreliable for practical purposes
S12: .. = disclosive
S13: : = not applicable
S14: - = nil or negligible

Sheet ASHE Annual pay FT SIC
A1: SIC2007 Table 5.7a Annual pay - Gross (£) - For full-time employee jobsa: United Kingdom, 2024
C3: Number | E3: Annual | G3: Annual
C4: of jobsb | E4: percentage | G4: percentage | H4: Percentiles
A5: Description | B5: Code | C5: (thousand) | D5: Median | E5: change | F5: Mean | G5: change | H5: 10 | I5: 20 | J5: 25 | K5: 30 | L5: 40 | M5: 60 | N5: 70 | O5: 75 | P5: 80 | Q5: 90
A6: United Kingdom | B6: K02000001 | C6: 17248 | D6: 37430 | E6: 6.9 | F6: 45836 | G6: 8.2 | H6: 22763 | I6: 26250 | J6: 27986 | K6: 29731 | L6: 33276 | M6: 42148 | N6: 47898 | O6: 51391 | P6: 55912 | Q6: 72150
A7: Great Britain | B7: K03000001 | C7: 16654 | D7: 37514 | E7: 6.9 | F7: 46058 | G7: 8.3 | H7: 22799 | I7: 26306 | J7: 28033 | K7: 29807 | L7: 33394 | M7: 42308 | N7: 48084 | O7: 51609 | P7: 56144 | Q7: 72500 | S7: Key | T7: Statistical robustness
A8: England and Wales | B8: K04000001 | C8: 15148 | D8: 37468 | E8: 6.9 | F8: 46320 | G8: 8.3 | H8: 22709 | I8: 26222 | J8: 27996 | K8: 29754 | L8: 33304 | M8: 42265 | N8: 48155 | O8: 51832 | P8: 56435 | Q8: 73092 | S8: CV <= 5% | T8: Estimates are considered precise
A9: England | B9: E92000001 | C9: 14397 | D9: 37630 | E9: 6.9 | F9: 46739 | G9: 8.4 | H9: 22760 | I9: 26307 | J9: 28070 | K9: 29856 | L9: 33479 | M9: 42516 | N9: 48481 | O9: 52266 | P9: 56952 | Q9: 74092 | S9: CV > 5% and <= 10% | T9: Estimates are considered reasonably precise
A10: North East | B10: E12000001 | C10: 581 | D10: 32960 | E10: 6 | F10: 38321 | G10: 8.9 | H10: 21635 | I10: 24500 | J10: 25609 | K10: 26906 | L10: 29777 | M10: 37040 | N10: 41705 | O10: 44724 | P10: 47752 | Q10: 59640 | S10: CV > 10% and <= 20% | T10: Estimates are considered acceptable
A11: North West | B11: E12000002 | C11: 1840 | D11: 35170 | E11: 6.3 | F11: 41105 | G11: 7.9 | H11: 22137 | I11: 25281 | J11: 26729 | K11: 28301 | L11: 31488 | M11: 39566 | N11: 44945 | O11: 48284 | P11: 52353 | Q11: 65572 | S11: x = CV > 20% | T11: Estimates are considered unreliable for practical purposes
A12: Yorkshire and The Humber | B12: E12000003 | C12: 1365 | D12: 34401 | E12: 7.8 | F12: 39732 | G12: 7.8 | H12: 22103 | I12: 25146 | J12: 26505 | K12: 28024 | L12: 31036 | M12: 38431 | N12: 43729 | O12: 46618 | P12: 50249 | Q12: 62733 | S12: .. = disclosive
A13: East Midlands | B13: E12000004 | C13: 1133 | D13: 33973 | E13: 7.2 | F13: 39271 | G13: 7.3 | H13: 21931 | I13: 24830 | J13: 26216 | K13: 27768 | L13: 30590 | M13: 37942 | N13: 42929 | O13: 45777 | P13: 49737 | Q13: 61599 | S13: : = not applicable
A14: West Midlands | B14: E12000005 | C14: 1380 | D14: 34938 | E14: 4.8 | F14: 41482 | G14: 6.4 | H14: 22035 | I14: 25061 | J14: 26585 | K14: 28176 | L14: 31407 | M14: 39058 | N14: 44698 | O14: 47717 | P14: 51461 | Q14: 63713 | S14: - = nil or negligible
A15: East | B15: E12000006 | C15: 1460 | D15: 36949 | E15: 6 | F15: 44093 | G15: 8.1 | H15: 22451 | I15: 26072 | J15: 27904 | K15: 29720 | L15: 33000 | M15: 41368 | N15: 47268 | O15: 50409 | P15: 54202 | Q15: 70052
A16: London | B16: E12000007 | C16: 2840 | D16: 47455 | E16: 6.2 | F16: 65994 | G16: 8.6 | H16: 26121 | I16: 31566 | J16: 34365 | K16: 36627 | L16: 41788 | M16: 54213 | N16: 63000 | O16: 69054 | P16: 77114 | Q16: 105146
A17: South East | B17: E12000008 | C17: 2435 | D17: 39038 | E17: 6.9 | F17: 46006 | G17: 7.8 | H17: 23310 | I17: 27128 | J17: 29047 | K17: 30752 | L17: 34654 | M17: 43858 | N17: 49973 | O17: 53597 | P17: 58183 | Q17: 74189
A18: South West | B18: E12000009 | C18: 1363 | D18: 35634 | E18: 6 | F18: 40509 | G18: 5.2 | H18: 22269 | I18: 25513 | J18: 26916 | K18: 28409 | L18: 31748 | M18: 39589 | N18: 44413 | O18: 47012 | P18: 51125 | Q18: 63735
A19: Wales | B19: W92000004 | C19: 751 | D19: 34303 | E19: 6 | F19: 38295 | G19: 7.2 | H19: 21923 | I19: 24873 | J19: 26340 | K19: 27816 | L19: 30825 | M19: 38018 | N19: 42997 | O19: 45470 | P19: 48403 | Q19: 57750
A20: Scotland | B20: S92000003 | C20: 1506 | D20: 38315 | E20: 7.8 | F20: 43425 | G20: 8.4 | H20: 23680 | I20: 27105 | J20: 28682 | K20: 30468 | L20: 34280 | M20: 42684 | N20: 47803 | O20: 50275 | P20: 54035 | Q20: 66995
A21: Northern Ireland | B21: N92000002 | C21: 594 | D21: 34378 | E21: 5 | F21: 39612 | G21: 4.4 | H21: 22128 | I21: 24955 | J21: 26360 | K21: 27555 | L21: 30711 | M21: 38343 | N21: 42872 | O21: 45083 | P21: 48643 | Q21: 60098
A22: All Industries and Services | C22: 17242 | D22: 37433 | E22: 6.9 | F22: 45837 | G22: 8.2 | H22: 22763 | I22: 26250 | J22: 27987 | K22: 29733 | L22: 33277 | M22: 42150 | N22: 47899 | O22: 51391 | P22: 55913 | Q22: 72151
A23: All Index of Production Industries | C23: 2297 | D23: 37867 | E23: 5.9 | F23: 44016 | G23: 6.5 | H23: 23856 | I23: 27039 | J23: 28695 | K23: 30386 | L23: 34010 | M23: 42557 | N23: 48223 | O23: 51295 | P23: 55315 | Q23: 69382
A24: All Manufacturing | C24: 2003 | D24: 37071 | E24: 5.5 | F24: 43164 | G24: 6.2 | H24: 23638 | I24: 26740 | J24: 28257 | K24: 29901 | L24: 33278 | M24: 41728 | N24: 47252 | O24: 50481 | P24: 54276 | Q24: 67235
A25: All Service Industries | C25: 14099 | D25: 37167 | E25: 6.8 | F25: 46071 | G25: 8.5 | H25: 22500 | I25: 26023 | J25: 27742 | K25: 29468 | L25: 32983 | M25: 41939 | N25: 47700 | O25: 51170 | P25: 55752 | Q25: 72500
A26: AGRICULTURE, FORESTRY AND FISHING | B26: A | C26: 93 | D26: 31795 | E26: 8 | F26: 34848 | G26: 6.1 | H26: 21722 | I26: 24338 | J26: 25521 | K26: 26582 | L26: 29055 | M26: 34645 | N26: 37674 | O26: 39587 | P26: 42186 | Q26: x
A27: Crop and animal production, hunting and related service activities | B27: 1 | C27: 81 | D27: 31219 | E27: 7.7 | F27: 33828 | G27: 6.9 | H27: 21373 | I27: 23956 | J27: 25025 | K27: 26030 | L27: 28855 | M27: 34066 | N27: 36588 | O27: 38855 | P27: 41063 | Q27: x
A28: Forestry and logging | B28: 2 | C28: 8 | D28: 30394 | E28: 2.1 | F28: 33347 | G28: -0.3 | H28: x | I28: 25222 | J28: 26900 | K28: 27323 | L28: 27941 | M28: 35360 | N28: 39578 | O28: x | P28: x | Q28: x
A29: Fishing and aquaculture | B29: 3 | C29: x | D29: 41005 | E29: -3.8 | F29: 57035 | G29: 8.2 | H29: x | I29: x | J29: x | K29: x | L29: 39274 | M29: x | N29: x | O29: x | P29: x | Q29: x
A30: MINING AND QUARRYING | B30: B | C30: 23 | D30: 47599 | E30: 6 | F30: 57424 | G30: 6 | H30: 27234 | I30: 33318 | J30: 35531 | K30: 37602 | L30: 42734 | M30: 56657 | N30: 62056 | O30: x | P30: x | Q30: x
A31: Mining of coal and lignite | B31: 5 | C31: :
A32: Extraction of crude petroleum and natural gas | B32: 6 | C32: x | D32: 79052 | E32: -8 | F32: 94756 | G32: 3.5 | H32: x | I32: x | J32: x | K32: x | L32: x | M32: x | N32: x | O32: x | P32: x | Q32: x
A33: Mining of metal ores | B33: 7 | C33: :
A34: Other mining and quarrying | B34: 8 | C34: 14 | D34: 40820 | E34: 0.1 | F34: 42868 | G34: -4 | H34: 25551 | I34: 30191 | J34: 31130 | K34: 33839 | L34: 37179 | M34: 44639 | N34: 47497 | O34: 50528 | P34: x | Q34: x
A35: Mining support service activities | B35: 9 | C35: x | D35: 59625 | E35: 26.5 | F35: 66970 | G35: 24.9 | H35: x | I35: x | J35: x | K35: 39412 | L35: 53961 | M35: x | N35: x | O35: x | P35: x | Q35: x
A36: MANUFACTURING | B36: C | C36: 2003 | D36: 37071 | E36: 5.5 | F36: 43164 | G36: 6.2 | H36: 23638 | I36: 26740 | J36: 28257 | K36: 29901 | L36: 33278 | M36: 41728 | N36: 47252 | O36: 50481 | P36: 54276 | Q36: 67235
A37: Manufacture of food products | B37: 10 | C37: 274 | D37: 32139 | E37: 10.4 | F37: 38334 | G37: 12 | H37: 21861 | I37: 24654 | J37: 25621 | K37: 26643 | L37: 29042 | M37: 35132 | N37: 39710 | O37: 42199 | P37: 45914 | Q37: 57038
A38: Manufacture of beverages | B38: 11 | C38: 40 | D38: 38487 | E38: 0.9 | F38: 44867 | G38: 1.9 | H38: 26007 | I38: 28752 | J38: 30741 | K38: 32051 | L38: 35236 | M38: 42645 | N38: 48317 | O38: 50807 | P38: 55351 | Q38: x
A39: Manufacture of tobacco products | B39: 12 | C39: :
A40: Manufacture of textiles | B40: 13 | C40: 35 | D40: 28024 | E40: 2.1 | F40: 33059 | G40: 3.8 | H40: 21210 | I40: 22739 | J40: 23332 | K40: 24194 | L40: 25992 | M40: 30794 | N40: 34085 | O40: 36439 | P40: x | Q40: x
A41: Manufacture of wearing apparel | B41: 14 | C41: 7 | D41: 24945 | E41: 8.5 | F41: 28153 | G41: 11.5 | H41: x | I41: 21165 | J41: 21983 | K41: 22834 | L41: 23743 | M41: 26625 | N41: x | O41: x | P41: x | Q41: x
A42: Manufacture of leather and related products | B42: 15 | C42: x | D42: 27969 | E42: 7.6 | F42: 31110 | G42: 5.4 | H42: x | I42: x | J42: 23353 | K42: 23954 | L42: 24540 | M42: 32006 | N42: x | O42: x | P42: x | Q42: x
A43: Manufacture of wood and of products of wood and cork, except furniture; manufacture of articles of straw and plaiting materials | B43: 16 | C43: 44 | D43: 33872 | E43: 6.1 | F43: 38997 | G43: -3.1 | H43: 22636 | I43: 26122 | J43: 26947 | K43: 28093 | L43: 30211 | M43: 36741 | N43: 40727 | O43: 43449 | P43: 47007 | Q43: x
A44: Manufacture of paper and paper products | B44: 17 | C44: 40 | D44: 35534 | E44: 3.6 | F44: 40159 | G44: 2.2 | H44: 23166 | I44: 26078 | J44: 26998 | K44: 28573 | L44: 31870 | M44: 39204 | N44: 43276 | O44: 46258 | P44: 49535 | Q44: x
A45: Printing and reproduction of recorded media | B45: 18 | C45: 46 | D45: 31000 | E45: 4.3 | F45: 36813 | G45: 7.2 | H45: 22077 | I45: 24762 | J45: 25938 | K45: 26719 | L45: 28634 | M45: 34894 | N45: 39686 | O45: 42370 | P45: 46279 | Q45: x
A46: Manufacture of coke and refined petroleum products | B46: 19 | C46: 9 | D46: 62159 | E46: 1.7 | F46: 64306 | G46: 4.7 | H46: x | I46: 34951 | J46: x | K46: x | L46: 55015 | M46: 68117 | N46: x | O46: x | P46: x | Q46: x
A47: Manufacture of chemicals and chemical products | B47: 20 | C47: 77 | D47: 37484 | E47: 3.5 | F47: 45051 | G47: 1.2 | H47: 24816 | I47: 27948 | J47: 29245 | K47: 30280 | L47: 33006 | M47: 42305 | N47: 47950 | O47: 51660 | P47: 55129 | Q47: x
A48: Manufacture of basic pharmaceutical products and pharmaceutical preparations | B48: 21 | C48: 39 | D48: 36853 | E48: 2 | F48: 43804 | G48: 7.3 | H48: 25807 | I48: 28419 | J48: 30007 | K48: 31359 | L48: 34210 | M48: 41298 | N48: 44965 | O48: 49008 | P48: x | Q48: x
A49: Manufacture of rubber and plastic products | B49: 22 | C49: 134 | D49: 32305 | E49: 4.4 | F49: 38199 | G49: 6.1 | H49: 22523 | I49: 24951 | J49: 25912 | K49: 27032 | L49: 29428 | M49: 36109 | N49: 40346 | O49: 43496 | P49: 46283 | Q49: x
A50: Manufacture of other non-metallic mineral products | B50: 23 | C50: 73 | D50: 36264 | E50: 3.2 | F50: 41025 | G50: 6.9 | H50: 24705 | I50: 27695 | J50: 29677 | K50: 31281 | L50: 32875 | M50: 41262 | N50: 45378 | O50: 48156 | P50: 51181 | Q50: x
A51: Manufacture of basic metals | B51: 24 | C51: 67 | D51: 42719 | E51: 3.2 | F51: 47712 | G51: 5.8 | H51: 26759 | I51: 31333 | J51: 33449 | K51: 35151 | L51: 38772 | M51: 47654 | N51: 53866 | O51: 58039 | P51: 63440 | Q51: x
A52: Manufacture of fabricated metal products, except machinery and equipment | B52: 25 | C52: 236 | D52: 36346 | E52: 6.5 | F52: 41134 | G52: 5.5 | H52: 24033 | I52: 27204 | J52: 28752 | K52: 29987 | L52: 33085 | M52: 40378 | N52: 44741 | O52: 47416 | P52: 50260 | Q52: 60181
A53: Manufacture of computer, electronic and optical products | B53: 26 | C53: 117 | D53: 40000 | E53: -1.6 | F53: 47642 | G53: 3.8 | H53: 23738 | I53: 27622 | J53: 29655 | K53: 31375 | L53: 35045 | M53: 46999 | N53: 52411 | O53: 56796 | P53: 60692 | Q53: x
A54: Manufacture of electrical equipment | B54: 27 | C54: 91 | D54: 38479 | E54: 8 | F54: 45711 | G54: 6.3 | H54: 23148 | I54: 26987 | J54: 28581 | K54: 30020 | L54: 34221 | M54: 43473 | N54: 51818 | O54: 54485 | P54: 57827 | Q54: x
A55: Manufacture of machinery and equipment n.e.c. | B55: 28 | C55: 175 | D55: 40000 | E55: 4.6 | F55: 47769 | G55: 6.6 | H55: 25340 | I55: 28582 | J55: 30595 | K55: 32694 | L55: 36152 | M55: 44329 | N55: 49735 | O55: 52669 | P55: 56447 | Q55: x
A56: Manufacture of motor vehicles, trailers and semi-trailers | B56: 29 | C56: 107 | D56: 40463 | E56: 1.3 | F56: 45160 | G56: 4.1 | H56: 24584 | I56: 28650 | J56: 30680 | K56: 32374 | L56: 36147 | M56: 44792 | N56: 50992 | O56: 54182 | P56: 58604 | Q56: x
A57: Manufacture of other transport equipment | B57: 30 | C57: 186 | D57: 48815 | E57: 5.7 | F57: 51676 | G57: 5.9 | H57: 29927 | I57: 34973 | J57: 38286 | K57: 40668 | L57: 44973 | M57: 53265 | N57: 57805 | O57: 61005 | P57: 64530 | Q57: 74780
A58: Manufacture of furniture | B58: 31 | C58: 60 | D58: 30114 | E58: 6.8 | F58: 33782 | G58: 3 | H58: 22065 | I58: 24201 | J58: 24918 | K58: 25761 | L58: 27759 | M58: 32601 | N58: 36496 | O58: 38548 | P58: x | Q58: x
A59: Other manufacturing | B59: 32 | C59: 65 | D59: 34312 | E59: 7.6 | F59: 42296 | G59: 9.8 | H59: 22440 | I59: 24948 | J59: 26003 | K59: 28020 | L59: 31551 | M59: 38381 | N59: 44293 | O59: 47220 | P59: 53873 | Q59: x
A60: Repair and installation of machinery and equipment | B60: 33 | C60: 74 | D60: 42828 | E60: 7.5 | F60: 47284 | G60: 10.4 | H60: 25317 | I60: 29742 | J60: 32225 | K60: 34347 | L60: 37428 | M60: 48597 | N60: 53007 | O60: 56177 | P60: 59728 | Q60: x
A61: ELECTRICITY, GAS, STEAM AND AIR CONDITIONING SUPPLY | B61: D | C61: 99 | D61: 53161 | E61: 4.7 | F61: 60036 | G61: 6.1 | H61: 27775 | I61: 35935 | J61: 38434 | K61: 40803 | L61: 46973 | M61: 59721 | N61: 69700 | O61: 74759 | P61: 79392 | Q61: x
A62: Electricity, gas, steam and air conditioning supply | B62: 35 | C62: 99 | D62: 53161 | E62: 4.7 | F62: 60036 | G62: 6.1 | H62: 27775 | I62: 35935 | J62: 38434 | K62: 40803 | L62: 46973 | M62: 59721 | N62: 69700 | O62: 74759 | P62: 79392 | Q62: x
A63: WATER SUPPLY; SEWERAGE, WASTE MANAGEMENT AND REMEDIATION ACTIVITIES | B63: E | C63: 172 | D63: 39447 | E63: 8.6 | F63: 42857 | G63: 8.7 | H63: 25161 | I63: 28983 | J63: 31075 | K63: 33118 | L63: 36295 | M63: 42993 | N63: 46754 | O63: 49467 | P63: 51871 | Q63: x
A64: Water collection, treatment and supply | B64: 36 | C64: 60 | D64: 42193 | E64: 9.8 | F64: 44536 | G64: 4.4 | H64: 27182 | I64: 33134 | J64: 34347 | K64: 36405 | L64: 39167 | M64: 45046 | N64: 48642 | O64: 50345 | P64: 52680 | Q64: x
A65: Sewerage | B65: 37 | C65: 18 | D65: 40329 | E65: 3.5 | F65: 43893 | G65: 6.5 | H65: 27583 | I65: 31685 | J65: 32946 | K65: 34915 | L65: 38551 | M65: 44531 | N65: 50271 | O65: 51676 | P65: x | Q65: x
A66: Waste collection, treatment and disposal activities; materials recovery | B66: 38 | C66: 91 | D66: 36827 | E66: 8 | F66: 41586 | G66: 10.9 | H66: x | I66: 27019 | J66: 28635 | K66: 30017 | L66: 33877 | M66: 40660 | N66: 44828 | O66: 47493 | P66: 50909 | Q66: x
A67: Remediation activities and other waste management services | B67: 39 | C67: x | D67: 36446 | E67: 7.3 | F67: 42030 | G67: 18.8 | H67: x | I67: x | J67: x | K67: x | L67: 34857 | M67: x | N67: x | O67: x | P67: x | Q67: x
A68: CONSTRUCTION | B68: F | C68: 750 | D68: 41319 | E68: 7.7 | F68: 48311 | G68: 8.6 | H68: 24574 | I68: 29419 | J68: 31545 | K68: 33461 | L68: 37361 | M68: 45872 | N68: 52664 | O68: 57098 | P68: 62124 | Q68: 76974
A69: Construction of buildings | B69: 41 | C69: 242 | D69: 45717 | E69: 8.9 | F69: 56282 | G69: 9.5 | H69: 25318 | I69: 31128 | J69: 33116 | K69: 35655 | L69: 40912 | M69: 53278 | N69: 62121 | O69: 66630 | P69: 72332 | Q69: 92301
A70: Civil engineering | B70: 42 | C70: 135 | D70: 44018 | E70: 8.7 | F70: 49586 | G70: 9.3 | H70: 25074 | I70: 30771 | J70: 33037 | K70: 35494 | L70: 39291 | M70: 50000 | N70: 57412 | O70: 61474 | P70: 66019 | Q70: x
A71: Specialised construction activities | B71: 43 | C71: 373 | D71: 38719 | E71: 8.1 | F71: 42680 | G71: 7.8 | H71: 23999 | I71: 28198 | J71: 30023 | K71: 31898 | L71: 35077 | M71: 42167 | N71: 46695 | O71: 49805 | P71: 53379 | Q71: 65275
A72: WHOLESALE AND RETAIL TRADE; REPAIR OF MOTOR VEHICLES AND MOTORCYCLES | B72: G | C72: 2013 | D72: 32126 | E72: 8.3 | F72: 39813 | G72: 8.8 | H72: 21617 | I72: 24061 | J72: 25152 | K72: 26326 | L72: 28992 | M72: 35716 | N72: 40866 | O72: 43977 | P72: 48471 | Q72: 64111
A73: Wholesale and retail trade and repair of motor vehicles and motorcycles | B73: 45 | C73: 331 | D73: 33751 | E73: 8.4 | F73: 38194 | G73: 8.9 | H73: 23125 | I73: 25635 | J73: 26945 | K73: 28233 | L73: 30970 | M73: 36680 | N73: 40089 | O73: 42596 | P73: 46423 | Q73: 55963
A74: Wholesale trade, except of motor vehicles and motorcycles | B74: 46 | C74: 820 | D74: 35489 | E74: 6.1 | F74: 44528 | G74: 5.5 | H74: 23571 | I74: 26156 | J74: 27540 | K74: 29032 | L74: 32141 | M74: 40490 | N74: 46368 | O74: 50449 | P74: 56039 | Q74: 74663
A75: Retail trade, except of motor vehicles and motorcycles | B75: 47 | C75: 862 | D75: 28384 | E75: 9.2 | F75: 35951 | G75: 11.9 | H75: 19921 | I75: 22346 | J75: 23172 | K75: 24002 | L75: 25984 | M75: 31275 | N75: 35531 | O75: 38342 | P75: 42002 | Q75: 56803
A76: TRANSPORTATION AND STORAGE | B76: H | C76: 832 | D76: 38101 | E76: 8.2 | F76: 43648 | G76: 7.8 | H76: 24846 | I76: 28618 | J76: 30196 | K76: 31563 | L76: 34988 | M76: 41907 | N76: 46842 | O76: 49941 | P76: 54126 | Q76: 66981
A77: Land transport and transport via pipelines | B77: 49 | C77: 325 | D77: 39521 | E77: 5.3 | F77: 44138 | G77: 6.2 | H77: 25357 | I77: 29501 | J77: 31200 | K77: 32824 | L77: 36012 | M77: 43137 | N77: 47610 | O77: 50611 | P77: 54629 | Q77: 65496
A78: Water transport | B78: 50 | C78: 9 | D78: 40791 | E78: -3 | F78: 44701 | G78: -10.6 | H78: x | I78: x | J78: 29481 | K78: 32736 | L78: 37621 | M78: 46430 | N78: x | O78: x | P78: x | Q78: x
A79: Air transport | B79: 51 | C79: 31 | D79: 42790 | E79: 17.5 | F79: 51356 | G79: 9.9 | H79: 26937 | I79: 31092 | J79: 32064 | K79: 33498 | L79: 37821 | M79: 48150 | N79: 54513 | O79: 63229 | P79: x | Q79: x
A80: Warehousing and support activities for transportation | B80: 52 | C80: 303 | D80: 38274 | E80: 6.6 | F80: 44976 | G80: 8.4 | H80: 23902 | I80: 27150 | J80: 28694 | K80: 30385 | L80: 34507 | M80: 43063 | N80: 48713 | O80: 52335 | P80: 57116 | Q80: 73298
A81: Postal and courier activities | B81: 53 | C81: 163 | D81: 35387 | E81: 15.1 | F81: 38687 | G81: 11.6 | H81: 26107 | I81: 29477 | J81: 30202 | K81: 31060 | L81: 33054 | M81: 37655 | N81: 40843 | O81: 43137 | P81: 45831 | Q81: 54338
A82: ACCOMMODATION AND FOOD SERVICE ACTIVITIES | B82: I | C82: 459 | D82: 27414 | E82: 7.3 | F82: 31122 | G82: 7.3 | H82: 17194 | I82: 20817 | J82: 22085 | K82: 23120 | L82: 25207 | M82: 30045 | N82: 33164 | O82: 35442 | P82: 38500 | Q82: 47283
A83: Accommodation | B83: 55 | C83: 142 | D83: 27578 | E83: 3.3 | F83: 32482 | G83: 3.1 | H83: 18975 | I83: 22256 | J83: 23060 | K83: 24078 | L83: 25925 | M83: 30002 | N83: 32880 | O83: 35152 | P83: 38745 | Q83: x
A84: Food and beverage service activities | B84: 56 | C84: 318 | D84: 27304 | E84: 8.9 | F84: 30515 | G84: 9.4 | H84: 16338 | I84: 20159 | J84: 21444 | K84: 22666 | L84: 24824 | M84: 30060 | N84: 33302 | O84: 35592 | P84: 38355 | Q84: 45723
A85: INFORMATION AND COMMUNICATION | B85: J | C85: 930 | D85: 48320 | E85: 6.4 | F85: 59858 | G85: 10.3 | H85: 27331 | I85: 32984 | J85: 35480 | K85: 37951 | L85: 42837 | M85: 55928 | N85: 66000 | O85: 71062 | P85: 77446 | Q85: 100000
A86: Publishing activities | B86: 58 | C86: 73 | D86: 43104 | E86: 9.9 | F86: 50724 | G86: 14.4 | H86: 25992 | I86: 29359 | J86: 31421 | K86: 33183 | L86: 37197 | M86: 47331 | N86: 55113 | O86: 61698 | P86: 65525 | Q86: x
A87: Motion picture, video and television programme production, sound recording and music publishing activities | B87: 59 | C87: 36 | D87: 40136 | F87: 51412 | H87: 24383 | I87: 29001 | J87: 30475 | K87: 33904 | L87: 37033 | M87: 46118 | N87: 52523 | O87: x | P87: x | Q87: x
A88: Programming and broadcasting activities | B88: 60 | C88: 32 | D88: 47538 | E88: -2.4 | F88: 60121 | G88: 17.5 | H88: 30881 | I88: 36553 | J88: 38057 | K88: 41339 | L88: 43345 | M88: 57893 | N88: 67218 | O88: 70569 | P88: x | Q88: x
A89: Telecommunications | B89: 61 | C89: 223 | D89: 44618 | E89: 0.4 | F89: 53083 | G89: 2.7 | H89: 28012 | I89: 33373 | J89: 35584 | K89: 36958 | L89: 40281 | M89: 49101 | N89: 57548 | O89: 63420 | P89: 68449 | Q89: 84135
A90: Computer programming, consultancy and related activities | B90: 62 | C90: 515 | D90: 51443 | E90: 8.7 | F90: 60732 | G90: 8.7 | H90: 27322 | I90: 33273 | J90: 36000 | K90: 39081 | L90: 44693 | M90: 59155 | N90: 69033 | O90: 74348 | P90: 80249 | Q90: 102328
A91: Information service activities | B91: 63 | C91: 50 | D91: 72083 | E91: 41.2 | F91: 100096 | G91: 57.9 | H91: 29815 | I91: 35536 | J91: 41144 | K91: 49786 | L91: 59726 | M91: 80038 | N91: 99462 | O91: 113230 | P91: x | Q91: x
A92: FINANCIAL AND INSURANCE ACTIVITIES | B92: K | C92: 883 | D92: 52247 | E92: 7.5 | F92: 85538 | G92: 13.3 | H92: 26196 | I92: 31019 | J92: 33831 | K92: 36911 | L92: 43858 | M92: 62501 | N92: 75449 | O92: 83558 | P92: 94454 | Q92: 133576
A93: Financial service activities, except insurance and pension funding | B93: 64 | C93: 498 | D93: 55644 | E93: 2 | F93: 90043 | G93: 8 | H93: 26874 | I93: 31817 | J93: 35206 | K93: 38554 | L93: 45929 | M93: 66071 | N93: 80483 | O93: 88336 | P93: 99736 | Q93: 137393
A94: Insurance, reinsurance and pension funding, except compulsory social security | B94: 65 | C94: 86 | D94: 49886 | E94: 13.2 | F94: 64090 | G94: 19.1 | H94: 26023 | I94: 30312 | J94: 33489 | K94: 35394 | L94: 42038 | M94: 59330 | N94: 70801 | O94: 78431 | P94: 87185 | Q94: x
A95: Activities auxiliary to financial services and insurance activities | B95: 66 | C95: 299 | D95: 48562 | E95: 14.9 | F95: 84226 | G95: 20.8 | H95: 25521 | I95: 30025 | J95: 32216 | K95: 35027 | L95: 41230 | M95: 56967 | N95: 68553 | O95: 76348 | P95: 86539 | Q95: x
A96: REAL ESTATE ACTIVITIES | B96: L | C96: 254 | D96: 34623 | E96: 6 | F96: 40940 | G96: 2.8 | H96: 23332 | I96: 25980 | J96: 27582 | K96: 29077 | L96: 31610 | M96: 38144 | N96: 42366 | O96: 46006 | P96: 50000 | Q96: 62417
A97: Real estate activities | B97: 68 | C97: 254 | D97: 34623 | E97: 6 | F97: 40940 | G97: 2.8 | H97: 23332 | I97: 25980 | J97: 27582 | K97: 29077 | L97: 31610 | M97: 38144 | N97: 42366 | O97: 46006 | P97: 50000 | Q97: 62417
A98: PROFESSIONAL, SCIENTIFIC AND TECHNICAL ACTIVITIES | B98: M | C98: 1521 | D98: 44212 | E98: 5.7 | F98: 56240 | G98: 6.8 | H98: 24336 | I98: 28846 | J98: 31129 | K98: 33407 | L98: 38792 | M98: 50457 | N98: 59000 | O98: 64365 | P98: 71036 | Q98: 93772
A99: Legal and accounting activities | B99: 69 | C99: 447 | D99: 43391 | E99: 8.5 | F99: 56224 | G99: 4.1 | H99: 22777 | I99: 26200 | J99: 28235 | K99: 30307 | L99: 36442 | M99: 50432 | N99: 60712 | O99: 68262 | P99: 74910 | Q99: 99053
A100: Activities of head offices; management consultancy activities | B100: 70 | C100: 329 | D100: 46874 | E100: 5.9 | F100: 63447 | G100: 8.2 | H100: 25171 | I100: 30000 | J100: 32278 | K100: 35105 | L100: 40357 | M100: 54302 | N100: 64571 | O100: 71348 | P100: 80189 | Q100: 110149
A101: Architectural and engineering activities; technical testing and analysis | B101: 71 | C101: 371 | D101: 43284 | E101: 4.3 | F101: 53525 | G101: 12.8 | H101: 25969 | I101: 30014 | J101: 32328 | K101: 34269 | L101: 39003 | M101: 48220 | N101: 55310 | O101: 60505 | P101: 65569 | Q101: 81095
...

Sheet HAVERM
A1: 198001 !M | B1: MGSX@UK | C1: UKSEURA@UK | D1: UKNEMW@UK
A2: .DESC | B2: UK: LFS: Unemployment Rate: Aged 16 and Over (SA, %) | C2: UK: LFS: Unemployment Rate: Aged 16 and Over (SA, %) | D2: UK: National Minimum Wage/National Living Wage (NSA, GBP/hr)
A3: .T1 | B3: Feb-1971 | C3: Jun-1992 | D3: Apr-1999
A4: .TN | B4: Oct-2024 | C4: Nov-2024 | D4: Mar-2026
A5: .LSOURCE | B5: Office for National Statistics | C5: Office for National Statistics | D5: Low Pay Commission
A6: .DTLM | B6: Jan-21-2025 07:06 | C6: Jan-21-2025 07:05 | D6: Oct-30-2024 11:52
A7: 198001 | B7: 5.7 | C7: #N/A | D7: #N/A
A8: 198002 | B8: 5.8 | C8: #N/A | D8: #N/A
A9: 198003 | B9: 6 | C9: #N/A | D9: #N/A
A10: 198004 | B10: 6.1 | C10: #N/A | D10: #N/A
A11: 198005 | B11: 6.3 | C11: #N/A | D11: #N/A
A12: 198006 | B12: 6.5 | C12: #N/A | D12: #N/A
A13: 198007 | B13: 6.8 | C13: #N/A | D13: #N/A
A14: 198008 | B14: 7.1 | C14: #N/A | D14: #N/A
A15: 198009 | B15: 7.4 | C15: #N/A | D15: #N/A
A16: 198010 | B16: 7.7 | C16: #N/A | D16: #N/A
A17: 198011 | B17: 8 | C17: #N/A | D17: #N/A
A18: 198012 | B18: 8.3 | C18: #N/A | D18: #N/A
... A155: 199205 | B155: 9.8 | C155: #N/A | D155: #N/A
A156: 199206 | B156: 9.9 | C156: 9.977 | D156: #N/A
A157: 199207 | B157: 9.9 | C157: 9.865 | D157: #N/A
A158: 199208 | B158: 9.9 | C158: 9.947 | D158: #N/A
A159: 199209 | B159: 10.1 | C159: 10.027 | D159: #N/A
A160: 199210 | B160: 10.2 | C160: 10.227 | D160: #N/A
A161: 199211 | B161: 10.4 | C161: 10.439 | D161: #N/A
A162: 199212 | B162: 10.5 | C162: 10.489 | D162: #N/A
A163: 199301 | B163: 10.7 | C163: 10.696 | D163: #N/A
A164: 199302 | B164: 10.6 | C164: 10.837 | D164: #N/A
A165: 199303 | B165: 10.6 | C165: 10.363 | D165: #N/A
A166: 199304 | B166: 10.5 | C166: 10.519 | D166: #N/A
A167: 199305 | B167: 10.4 | C167: 10.457 | D167: #N/A
... A237: 199903 | B237: 6.2 | C237: 6.115 | D237: #N/A
A238: 199904 | B238: 6.1 | C238: 6.139 | D238: 3.6
A239: 199905 | B239: 6 | C239: 6.079 | D239: 3.6
A240: 199906 | B240: 6 | C240: 5.915 | D240: 3.6
A241: 199907 | B241: 5.9 | C241: 5.922 | D241: 3.6
A242: 199908 | B242: 5.9 | C242: 5.887 | D242: 3.6
A243: 199909 | B243: 5.8 | C243: 5.845 | D243: 3.6
A244: 199910 | B244: 5.8 | C244: 5.773 | D244: 3.6
A245: 199911 | B245: 5.8 | C245: 5.937 | D245: 3.6
A246: 199912 | B246: 5.9 | C246: 5.696 | D246: 3.6
A247: 200001 | B247: 5.8 | C247: 5.96 | D247: 3.6
A248: 200002 | B248: 5.8 | C248: 5.795 | D248: 3.6
A249: 200003 | B249: 5.7 | C249: 5.611 | D249: 3.6
... A544: 202410 | B544: 4.4 | C544: 4.326 | D544: 11.44
A545: 202411 | C545: 4.589 | D545: 11.44
A546: 202412 | D546: 11.44
A547: 202501 | D547: 11.44
A548: 202502 | D548: 11.44
A549: 202503 | D549: 11.44
A550: 202504 | D550: 12.21
A551: 202505 | D551: 12.21
A552: 202506 | D552: 12.21
A553: 202507 | D553: 12.21
A554: 202508 | D554: 12.21
A555: 202509 | D555: 12.21
A556: 202510 | D556: 12.21
A557: 202511 | D557: 12.21
... A561: 202603 | D561: 12.21

Sheet HAVERQ
A1: 2023 weights | V1: =AVERAGE(V$180:V$183) -> 2596.75 | Z1: =AVERAGE(Z$180:Z$183) -> 4753.75 | AA1: =AVERAGE(AA$180:AA$183) -> 1874.75 | AB1: =AVERAGE(AB$180:AB$183) -> 2680.75 | AC1: =AVERAGE(AC$180:AC$183) -> 1631 | AD1: =AVERAGE(AD$180:AD$183) -> 1143 | AE1: =AVERAGE(AE$180:AE$183) -> 694.25 | AF1: =AVERAGE(AF$180:AF$183) -> 3398.75 | AG1: =AVERAGE(AG$180:AG$183) -> 3080.25 | AK1: =AVERAGE(AK$180:AK$183) -> 1061.5 | AL1: =AB1+AK1 -> 3742.25 | AM1: =SUM(AA1,AC1:AG1) -> 11822 | AN1: =AVERAGE(AN$180:AN$183) -> 30807.75 | AT1: =V1/(V1+AN1) -> 0.077736533 | AU1: =1-AT1 -> 0.92226347 | BJ1: =V1/(V1+AN1) -> 0.077736533 | BK1: =1-BJ1 -> 0.92226347 | BL1: =V1/(V1+AN1) -> 0.077736533 | BM1: =Z1/(Z1+AL1+AM1) -> 0.23396742 | BN1: =1-BM1-BO1 -> 0.58184861 | BO1: =AL1/(Z1+AL1+AM1) -> 0.18418397
A2: 19801 !Q | B2: G7AUQ@UK | C2: G7K5Q@UK | D2: G7GOQ@UK | E2: MFY7Q@UK | F2: MFZ2Q@UK | G2: G9BZQ@UK | H2: G9C2Q@UK | I2: MFY9Q@UK | J2: MFY5Q@UK | K2: G7ERQ@UK | L2: G7EUQ@UK | M2: G7EXQ@UK | N2: G7F2Q@UK | O2: G7F5Q@UK | P2: G7FGQ@UK | Q2: G7FJQ@UK | R2: G7FMQ@UK | S2: DYDCQ@UK | T2: JWR5Q@UK | U2: JWR6Q@UK | V2: JWR7Q@UK | W2: JWR8Q@UK | X2: JWR9Q@UK | Y2: JWS2Q@UK | Z2: JWS3Q@UK | AA2: JWS4Q@UK | AB2: JWS5Q@UK | AC2: JWS6Q@UK | AD2: JWS7Q@UK | AE2: JWS8Q@UK | AF2: JWS9Q@UK | AG2: JWT2Q@UK | AH2: JWT3Q@UK | AI2: JWT4Q@UK | AJ2: JWT5Q@UK | AK2: JWT6Q@UK | AL2: JWT7Q@UK | AM2: KW78Q@UK | AN2: JWT8Q@UK | AO2: UKNEJ@UK | AP2: MGSCQ@UK | AQ2: MGSXQ@UK | AR2: BEIRQ@UK | AS2: UNVAL1@UK | AT2: UBCMERD@UK | AU2: UBCSERD@UK | AV2: YBWHQ@UK | AW2: MGSLQ@UK | AX2: MGWGQ@UK | AY2: LF24Q@UK | AZ2: YBUVQ@UK | BA2: KAC4@UK | BB2: MGRZQ@UK | BC2: UKSEPEP@UK | BD2: MGRNQ@UK | BE2: YCCXQ@UK | BF2: LFM2Q@UK | BG2: MGSCQ@UK | BH2: UQVDEE@UK | BI2: UNVAL7@UK | BJ2: UBCMEE@UK | BK2: UBCSEE@UK | BL2: UCBIEF@UK | BM2: UCBDEE@UK | BN2: UCBSBEN@UK | BO2: UCBSCEN@UK | BP2: CGBZQ@UK | BQ2: YBHAQ@UK | BR2: CGCBQ@UK
A3: .DESC | B3: UK: Total Public Sector Employment (SA, Thous) | C3: UK: Total Private Sector Employment (SA, Thous) | D3: UK: Total Employment [Labor Force Survey] (SA, Thous) | E3: UK: Public Sector Employment ex Major Reclassifications (SA. Thous) | F3: UK: Private Sector Employment ex Major Reclassifications (SA. Thous) | G3: UK: Public Sector Employment as % of Total Employment (SA, %) | H3: UK: Private Sector Employment as % of Total Employment (SA, %) | I3: UK: Public Sector Employment ex Major Reclassifications (SA. % of Employed) | J3: UK: Private Sector Employment ex Major Reclassifications (SA. % of Employed) | K3: UK: Public Sector Employment: Construction (SA, Thous) | L3: UK: Public Sector Employment: HM Forces (SA, Thous) | M3: UK: Public Sector Employment: Police [including Civilians] (SA, Thous) | N3: UK: Public Sector Employment: Public Administration (SA, Thous) | O3: UK: Public Sector Employment: Education (SA, Thous) | P3: UK: Public Sector Employment: National Health Service (SA, Thous) | Q3: UK: Public Sector Employment: Other Health and Social Work (SA, Thous) | R3: UK: Public Sector Employment: Other Public Sector (SA, Thous) | S3: UK: Total Workforce Jobs [Count of Jobs, Not People] (SA, Thous) | T3: UK: Workforce Jobs: Agriculture, Forestry & Fishing(SA, Thous) | U3: UK: Workforce Jobs: Mining & Quarrying(SA, Thous) | V3: UK: Workforce Jobs: Manufacturing(SA, Thous) | W3: UK: Workforce Jobs: Electricity, Gas, Steam & Air-Conditioning Supply(SA, Thous) | X3: UK: Workforce Jobs: Water Supply, Waste Management & Remediation(SA, Thous) | Y3: UK: Workforce Jobs: Construction(SA, Thous) | Z3: UK: Workforce Jobs: Wholesale/Retail Trade, Motor Vehicle Repair(SA, Thous) | AA3: UK: Workforce Jobs: Transportation & Storage(SA, Thous) | AB3: UK: Workforce Jobs: Accommodation & Food Services(SA, Thous) | AC3: UK: Workforce Jobs: Information & Communication(SA, Thous) | AD3: UK: Workforce Jobs: Financial & Insurance Activities(SA, Thous) | AE3: UK: Workforce Jobs: Real Estate Activities(SA, Thous) | AF3: UK: Workforce Jobs: Professional Scientific & Technical Activities(SA, Thous) | AG3: UK: Workforce Jobs: Administrative & Support Services(SA, Thous) | AH3: UK: Workforce Jobs: Public Administration, Defense, Social Security(SA, Thous) | AI3: UK: Workforce Jobs: Education(SA, Thous) | AJ3: UK: Workforce Jobs: Human Health & Social Work Activities(SA, Thous) | AK3: UK: Workforce Jobs: Arts, Entertainment & Recreation(SA, Thous) | AL3: UK: Workforce Jobs: Other Service Activities(SA, Thous) | AM3: UK: Workforce Jobs: People Employed by Households, etc. (SA, Thous) | AN3: UK: Workforce Jobs: Total Services(SA, Thous) | AO3: UK: Job Vacancies Excluding Agriculture, Forestry & Fishing (NSA, Thous) | AP3: UK: LFS: Unemployed: Aged 16 & Over (SA, Thous) | AQ3: UK: LFS: Unemployment Rate: Aged 16 and Over (SA, %) | AR3: UK: LFS: ILO Redundancy Rate (SA, Per 1000 Employees) | AS3: UK: BoE Agents' Survey: Labor Market: Recruitment Difficulties (NSA, % Bal) | AT3: UK: BCC Survey: Manufacturing: Recruitment Difficulties (% of Cos) | AU3: UK: BCC Survey: Service: Recruitment Difficulties (% of Cos) | AV3: UK: LFS: Unemployed: Aged 16 & Over: Over 12 Months (SA, Thous) | AW3: UK: LFS: Working Age Population: Age 16 & Over (NSA, Thous) | AX3: UK: LFS: Economic Activity Rate: Aged 16 and Over (SA, %) | AY3: UK: LFS: Employment Rate: Aged 16 to 64 (SA, %) | AZ3: UK: LFS: Average Actual Weekly Hours Worked: All Workers (SA, Hours) | BA3: Great Britain: AWE, Total Pay: Private Sector (SA, GBP) | BB3: UK: LFS: Employment: Aged 16 and Over (SA, Thous) | BC3: UK: Paid Employees: PAYE Real Time Information [RTI] (SA, Number) | BD3: UK: LFS: Employees (SA, Thous) | BE3: UK: LFS: Part-Time Workers: Couldn't Find Full-Time Job (SA, Thous) | BF3: UK: LFS: Economically Inactive: Wants a Job (SA, Thous) | BG3: UK: LFS: Unemployed: Aged 16 & Over (SA, Thous) | BH3: United Kingdom: BoE DMP: Avg Exp Annual Growth in Employment Over Next Year (%) | BI3: UK: BoE Agents' Survey: Employment Intentions (NSA, % Bal) | BJ3: UK: BCC Survey: Manufacturing: Employment Expectations, Balance (% Bal) | BK3: UK: BCC Survey: Service: Employment Expectations, Balance (% Bal) | BL3: UK: CBI Industrial Trends: Numbers Employed Over Next 3 Months(% Balance) | BM3: UK: Dist Trades: Total: Employment with Year Ago: Expected, Bal (% Bal) | BN3: UK: Service Sector: Numbers Employed: Next 3 Months: Business (% Bal) | BO3: UK: Service Sector: Numbers Employed: Next 3 Months: Consumer, Bal (% Bal) | BP3: UK: Gross Operating Surplus of Corporations (SA, Mil.Pounds) | BQ3: UK: Gross Domestic Product [GDP] (SA, Mil.Pounds) | BR3: UK: Gross Value Added at Factor Cost (SA, Mil.Pounds)
A4: .T1 | B4: Q2-1991 | C4: Q1-1999 | D4: Q1-1999 | E4: Q1-1999 | F4: Q1-1999 | G4: Q1-1999 | H4: Q1-1999 | I4: Q1-1999 | J4: Q1-1999 | K4: Q1-1999 | L4: Q1-1999 | M4: Q1-1999 | N4: Q1-1999 | O4: Q1-1999 | P4: Q1-1999 | Q4: Q1-1999 | R4: Q1-1999 | S4: Q2-1959 | T4: Q2-1978 | U4: Q2-1978 | V4: Q2-1978 | W4: Q2-1978 | X4: Q2-1978 | Y4: Q2-1978 | Z4: Q2-1978 | AA4: Q2-1978 | AB4: Q2-1978 | AC4: Q2-1978 | AD4: Q2-1978 | AE4: Q2-1978 | AF4: Q2-1978 | AG4: Q2-1978 | AH4: Q2-1978 | AI4: Q2-1978 | AJ4: Q2-1978 | AK4: Q2-1978 | AL4: Q2-1978 | AM4: Q2-1978 | AN4: Q2-1978 | AO4: Q2-2001 <- Apr-2001 | AP4: Q1-1971 | AQ4: Q1-1971 | AR4: Q2-1995 | AS4: Q1-2005 <- Jan-2005 | AT4: Q1-1989 | AU4: Q1-1989 | AV4: Q2-1992 | AW4: Q1-1971 | AX4: Q1-1971 | AY4: Q1-1971 | AZ4: Q2-1992 | BA4: Q1-2000 <- Jan-2000 | BB4: Q1-1971 | BC4: Q3-2014 <- Jul-2014 | BD4: Q2-1992 | BE4: Q2-1992 | BF4: Q2-1992 | BG4: Q1-1971 | BH4: Q4-2016 | BI4: Q4-2017 <- Oct-2017 | BJ4: Q1-1989 | BK4: Q1-1989 | BL4: Q2-1958 | BM4: Q4-1983 | BN4: Q4-1998 | BO4: Q4-1998 | BP4: Q1-1955 | BQ4: Q1-1955 | BR4: Q1-1955
A5: .TN | B5: Q3-2024 | C5: Q3-2024 | D5: Q3-2024 | E5: Q3-2024 | F5: Q3-2024 | G5: Q3-2024 | H5: Q3-2024 | I5: Q3-2024 | J5: Q3-2024 | K5: Q3-2024 | L5: Q3-2024 | M5: Q3-2024 | N5: Q3-2024 | O5: Q3-2024 | P5: Q3-2024 | Q5: Q3-2024 | R5: Q3-2024 | S5: Q3-2024 | T5: Q3-2024 | U5: Q3-2024 | V5: Q3-2024 | W5: Q3-2024 | X5: Q3-2024 | Y5: Q3-2024 | Z5: Q3-2024 | AA5: Q3-2024 | AB5: Q3-2024 | AC5: Q3-2024 | AD5: Q3-2024 | AE5: Q3-2024 | AF5: Q3-2024 | AG5: Q3-2024 | AH5: Q3-2024 | AI5: Q3-2024 | AJ5: Q3-2024 | AK5: Q3-2024 | AL5: Q3-2024 | AM5: Q3-2024 | AN5: Q3-2024 | AO5: Q4-2024 <- Dec-2024 | AP5: Q3-2024 | AQ5: Q3-2024 | AR5: Q3-2024 | AS5: Q4-2024 <- Jan-2025 | AT5: Q4-2024 | AU5: Q4-2024 | AV5: Q3-2024 | AW5: Q3-2024 | AX5: Q3-2024 | AY5: Q3-2024 | AZ5: Q3-2024 | BA5: Q3-2024 <- Nov-2024 | BB5: Q3-2024 | BC5: Q4-2024 <- Dec-2024 | BD5: Q3-2024 | BE5: Q3-2024 | BF5: Q3-2024 | BG5: Q3-2024 | BH5: Q3-2024 | BI5: Q4-2024 <- Jan-2025 | BJ5: Q4-2024 | BK5: Q4-2024 | BL5: Q1-2025 | BM5: Q1-2025 | BN5: Q4-2024 | BO5: Q4-2024 | BP5: Q4-2024 | BQ5: Q4-2024 | BR5: Q4-2024
A6: .LSOURCE | B6: Office for National Statistics | C6: Office for National Statistics | D6: Office for National Statistics | E6: Office for National Statistics | F6: Office for National Statistics | G6: Office for National Statistics | H6: Office for National Statistics | I6: Office for National Statistics | J6: Office for National Statistics | K6: Office for National Statistics | L6: Office for National Statistics | M6: Office for National Statistics | N6: Office for National Statistics | O6: Office for National Statistics | P6: Office for National Statistics | Q6: Office for National Statistics | R6: Office for National Statistics | S6: Office for National Statistics | T6: Office for National Statistics | U6: Office for National Statistics | V6: Office for National Statistics | W6: Office for National Statistics | X6: Office for National Statistics | Y6: Office for National Statistics | Z6: Office for National Statistics | AA6: Office for National Statistics | AB6: Office for National Statistics | AC6: Office for National Statistics | AD6: Office for National Statistics | AE6: Office for National Statistics | AF6: Office for National Statistics | AG6: Office for National Statistics | AH6: Office for National Statistics | AI6: Office for National Statistics | AJ6: Office for National Statistics | AK6: Office for National Statistics | AL6: Office for National Statistics | AM6: Office for National Statistics | AN6: Office for National Statistics | AO6: Office for National Statistics | AP6: Office for National Statistics | AQ6: Office for National Statistics | AR6: Office for National Statistics | AS6: Bank of England | AT6: The British Chambers of Commerce | AU6: The British Chambers of Commerce | AV6: Office for National Statistics | AW6: Office for National Statistics | AX6: Office for National Statistics | AY6: Office for National Statistics | AZ6: Office for National Statistics | BA6: Office for National Statistics | BB6: Office for National Statistics | BC6: Office for National Statistics | BD6: Office for National Statistics | BE6: Office for National Statistics | BF6: Office for National Statistics | BG6: Office for National Statistics | BH6: Bank of England | BI6: Bank of England | BJ6: The British Chambers of Commerce | BK6: The British Chambers of Commerce | BL6: Confederation of British Industry | BM6: Confederation of British Industry | BN6: Confederation of British Industry | BO6: Confederation of British Industry | BP6: Office for National Statistics | BQ6: Office for National Statistics | BR6: Office for National Statistics
A7: .DTLM | B7: Dec-17-2024 07:20 | C7: Dec-17-2024 07:20 | D7: Dec-17-2024 07:20 | E7: Dec-17-2024 07:20 | F7: Dec-17-2024 07:20 | G7: Dec-17-2024 07:20 | H7: Dec-17-2024 07:20 | I7: Dec-17-2024 07:20 | J7: Dec-17-2024 07:20 | K7: Dec-17-2024 07:20 | L7: Dec-17-2024 07:20 | M7: Dec-17-2024 07:04 | N7: Dec-17-2024 07:20 | O7: Dec-17-2024 07:20 | P7: Dec-17-2024 07:20 | Q7: Dec-17-2024 07:20 | R7: Dec-17-2024 07:20 | S7: Dec-17-2024 07:20 | T7: Dec-17-2024 07:20 | U7: Dec-17-2024 07:20 | V7: Dec-17-2024 07:20 | W7: Dec-17-2024 07:20 | X7: Dec-17-2024 07:20 | Y7: Dec-17-2024 07:20 | Z7: Dec-17-2024 07:20 | AA7: Dec-17-2024 07:20 | AB7: Dec-17-2024 07:20 | AC7: Dec-17-2024 07:20 | AD7: Dec-17-2024 07:20 | AE7: Dec-17-2024 07:20 | AF7: Dec-17-2024 07:20 | AG7: Dec-17-2024 07:20 | AH7: Dec-17-2024 07:20 | AI7: Dec-17-2024 07:20 | AJ7: Dec-17-2024 07:20 | AK7: Dec-17-2024 07:20 | AL7: Dec-17-2024 07:20 | AM7: Dec-17-2024 07:20 | AN7: Dec-17-2024 07:20 | AO7: Jan-21-2025 07:04 | AP7: Dec-17-2024 07:18 | AQ7: Dec-17-2024 07:20 | AR7: Dec-17-2024 07:20 | AS7: Feb-06-2025 12:09 | AT7: Jan-06-2025 00:01 | AU7: Jan-06-2025 00:01 | AV7: Dec-17-2024 07:20 | AW7: Dec-17-2024 07:20 | AX7: Dec-17-2024 07:20 | AY7: Dec-17-2024 07:20 | AZ7: Dec-17-2024 07:20 | BA7: Jan-21-2025 07:03 | BB7: Dec-17-2024 07:20 | BC7: Jan-21-2025 07:04 | BD7: Dec-17-2024 07:20 | BE7: Dec-17-2024 07:20 | BF7: Dec-17-2024 07:20 | BG7: Dec-17-2024 07:18 | BH7: Feb-06-2025 14:10 | BI7: Feb-06-2025 12:09 | BJ7: Jan-06-2025 00:01 | BK7: Jan-06-2025 00:01 | BL7: Jan-23-2025 11:00 | BM7: Nov-26-2024 11:03 | BN7: Nov-28-2024 00:01 | BO7: Nov-28-2024 00:01 | BP7: Feb-13-2025 07:03 | BQ7: Feb-13-2025 07:03 | BR7: Feb-13-2025 07:03
