Workbook

Sheet CHARTS>>

Sheet DATA>>

Sheet Chart Data
A1: Budget policy decisions | I1: OBR fiscal impulse | M1: Headroom | P1: Revenues & spending | T1: Inflation forecasts | Z1: Real government spending across fiscal events | CF1: Real government spending across fiscal events | FB1: GDP forecasts compared
Z2: Real PSCE in RDEL per head (2024-2025=100) | AI2: Real PSGI in RDEL per head (2025-2026=100) | AR2: Real PSCE in RDEL per head (2024-2025 prices) | BA2: Real PSGI in RDEL per head (2024-2025 prices) | BJ2: PSCE in RDEL per head | BS2: PSGI in RDEL per head | CF2: Real PSCE in RDEL (2025-2026=100) | CP2: Real PSGI in RDEL (2025-2026=100) | CZ2: Real PSCE in RDEL (2024-2025 prices) | DI2: Real PSGI in RDEL (2024-2025 prices) | DR2: PSCE in RDEL | EA2: PSGI in RDEL | EJ2: GDP deflator (2025-2026 = 100) | ES2: GDP deflator (raw)
Z3: 44621 | AA3: 44866 | AB3: 44986 | AC3: 45231 | AD3: 45352 | AE3: 45566 | AF3: 45717 | AG3: 45962 | AI3: =Z3 -> 44621 | AJ3: =AA3 -> 44866 | AK3: =AB3 -> 44986 | AL3: =AC3 -> 45231 | AM3: =AD3 -> 45352 | AN3: =AE3 -> 45566 | AO3: =AF3 -> 45717 | AP3: 45962 | AR3: =Z3 -> 44621 | AS3: =AA3 -> 44866 | AT3: =AB3 -> 44986 | AU3: =AC3 -> 45231 | AV3: =AD3 -> 45352 | AW3: =AE3 -> 45566 | AX3: =AF3 -> 45717 | AY3: 45962 | BA3: =Z3 -> 44621 | BB3: =AA3 -> 44866 | BC3: =AB3 -> 44986 | BD3: =AC3 -> 45231 | BE3: =AD3 -> 45352 | BF3: =AE3 -> 45566 | BG3: =AF3 -> 45717 | BH3: 45962 | BJ3: =Z3 -> 44621 | BK3: =AA3 -> 44866 | BL3: =AB3 -> 44986 | BM3: =AC3 -> 45231 | BN3: =AD3 -> 45352 | BO3: =AE3 -> 45566 | BP3: =AF3 -> 45717 | BQ3: 45962 | BS3: =Z3 -> 44621 | BT3: =AA3 -> 44866 | BU3: =AB3 -> 44986 | BV3: =AC3 -> 45231 | BW3: =AD3 -> 45352 | BX3: =AE3 -> 45566 | BY3: =AF3 -> 45717 | BZ3: 45962 | CF3: =Z3 -> 44621 | CG3: =AA3 -> 44866 | CH3: =AB3 -> 44986 | CI3: =AC3 -> 45231 | CJ3: =AD3 -> 45352 | CK3: =AE3 -> 45566 | CL3: =AF3 -> 45717 | CM3: 45962 | CP3: =Z3 -> 44621 | CQ3: =AA3 -> 44866 | CR3: =AB3 -> 44986 | CS3: =AC3 -> 45231 | CT3: =AD3 -> 45352 | CU3: =AE3 -> 45566 | CV3: =AF3 -> 45717 | CW3: 45962 | CZ3: =Z3 -> 44621 | DA3: =AA3 -> 44866 | DB3: =AB3 -> 44986 | DC3: =AC3 -> 45231 | DD3: =AD3 -> 45352 | DE3: =AE3 -> 45566 | DF3: =AF3 -> 45717 | DG3: 45962 | DI3: =Z3 -> 44621 | DJ3: =AA3 -> 44866 | DK3: =AB3 -> 44986 | DL3: =AC3 -> 45231 | DM3: =AD3 -> 45352 | DN3: =AE3 -> 45566 | DO3: =AF3 -> 45717 | DP3: 45962 | DR3: =Z3 -> 44621 | DS3: =AA3 -> 44866 | DT3: =AB3 -> 44986 | DU3: =AC3 -> 45231 | DV3: =AD3 -> 45352 | DW3: =AE3 -> 45566 | DX3: =AF3 -> 45717 | DY3: 45962 | EA3: =Z3 -> 44621 | EB3: =AA3 -> 44866 | EC3: =AB3 -> 44986 | ED3: =AC3 -> 45231 | EE3: =AD3 -> 45352 | EF3: =AE3 -> 45566 | EG3: =AF3 -> 45717 | EH3: 45962 | EJ3: =Z3 -> 44621 | EK3: =AA3 -> 44866 | EL3: =AB3 -> 44986 | EM3: =AC3 -> 45231 | EN3: =AD3 -> 45352 | EO3: =AE3 -> 45566 | EP3: =AF3 -> 45717 | EQ3: 45962 | ES3: =Z3 -> 44621 | ET3: =AA3 -> 44866 | EU3: =AB3 -> 44986 | EV3: =AC3 -> 45231 | EW3: =AD3 -> 45352 | EX3: =AE3 -> 45566 | EY3: =AF3 -> 45717 | EZ3: 45962
B4: 2025-2026 | C4: 2026-2027 | D4: 2027-2028 | E4: 2028-2029 | F4: 2029-2030 | G4: 2030-2031 | K4: Fiscal impulse | N4: Headroom | Q4: Revenues | R4: Spending | U4: OE November forecast | V4: OE post-Budget forecast | W4: 2% LINE | Z4: Spring Statement (Mar22) | AA4: AS22 | AB4: Budget (Mar23) | AC4: AS23 | AD4: Budget (Mar24) | AE4: Budget (Oct24) | AF4: Spring forecast (Mar25) | AG4: Budget (Nov25) | AI4: =Z4 -> Spring Statement (Mar22) | AJ4: =AA4 -> AS22 | AK4: =AB4 -> Budget (Mar23) | AL4: =AC4 -> AS23 | AM4: =AD4 -> Budget (Mar24) | AN4: =AE4 -> Budget (Oct24) | AO4: =AF4 -> Spring forecast (Mar25) | AP4: Budget (Nov25) | AR4: =Z4 -> Spring Statement (Mar22) | AS4: =AA4 -> AS22 | AT4: =AB4 -> Budget (Mar23) | AU4: =AC4 -> AS23 | AV4: =AD4 -> Budget (Mar24) | AW4: =AE4 -> Budget (Oct24) | AX4: =AF4 -> Spring forecast (Mar25) | AY4: Budget (Nov25) | BA4: =Z4 -> Spring Statement (Mar22) | BB4: =AA4 -> AS22 | BC4: =AB4 -> Budget (Mar23) | BD4: =AC4 -> AS23 | BE4: =AD4 -> Budget (Mar24) | BF4: =AE4 -> Budget (Oct24) | BG4: =AF4 -> Spring forecast (Mar25) | BH4: Budget (Nov25) | BJ4: =Z4 -> Spring Statement (Mar22) | BK4: =AA4 -> AS22 | BL4: =AB4 -> Budget (Mar23) | BM4: =AC4 -> AS23 | BN4: =AD4 -> Budget (Mar24) | BO4: =AE4 -> Budget (Oct24) | BP4: =AF4 -> Spring forecast (Mar25) | BQ4: Budget (Nov25) | BS4: =Z4 -> Spring Statement (Mar22) | BT4: =AA4 -> AS22 | BU4: =AB4 -> Budget (Mar23) | BV4: =AC4 -> AS23 | BW4: =AD4 -> Budget (Mar24) | BX4: =AE4 -> Budget (Oct24) | BY4: =AF4 -> Spring forecast (Mar25) | BZ4: Budget (Nov25) | CC4: Population | CF4: =Z4 -> Spring Statement (Mar22) | CG4: =AA4 -> AS22 | CH4: =AB4 -> Budget (Mar23) | CI4: =AC4 -> AS23 | CJ4: =AD4 -> Budget (Mar24) | CK4: =AE4 -> Budget (Oct24) | CL4: =AF4 -> Spring forecast (Mar25) | CM4: Budget (Nov25) | CN4: 100 LINE | CP4: =Z4 -> Spring Statement (Mar22) | CQ4: =AA4 -> AS22 | CR4: =AB4 -> Budget (Mar23) | CS4: =AC4 -> AS23 | CT4: =AD4 -> Budget (Mar24) | CU4: =AE4 -> Budget (Oct24) | CV4: =AF4 -> Spring forecast (Mar25) | CW4: Budget (Nov25) | CX4: 100 LINE | CZ4: =Z4 -> Spring Statement (Mar22) | DA4: =AA4 -> AS22 | DB4: =AB4 -> Budget (Mar23) | DC4: =AC4 -> AS23 | DD4: =AD4 -> Budget (Mar24) | DE4: =AE4 -> Budget (Oct24) | DF4: =AF4 -> Spring forecast (Mar25) | DG4: Budget (Nov25) | DI4: =Z4 -> Spring Statement (Mar22) | DJ4: =AA4 -> AS22 | DK4: =AB4 -> Budget (Mar23) | DL4: =AC4 -> AS23 | DM4: =AD4 -> Budget (Mar24) | DN4: =AE4 -> Budget (Oct24) | DO4: =AF4 -> Spring forecast (Mar25) | DP4: Budget (Nov25) | DR4: =Z4 -> Spring Statement (Mar22) | DS4: =AA4 -> AS22 | DT4: =AB4 -> Budget (Mar23) | DU4: =AC4 -> AS23 | DV4: =AD4 -> Budget (Mar24) | DW4: =AE4 -> Budget (Oct24) | DX4: =AF4 -> Spring forecast (Mar25) | DY4: Budget (Nov25) | EA4: =Z4 -> Spring Statement (Mar22) | EB4: =AA4 -> AS22 | EC4: =AB4 -> Budget (Mar23) | ED4: =AC4 -> AS23 | EE4: =AD4 -> Budget (Mar24) | EF4: =AE4 -> Budget (Oct24) | EG4: =AF4 -> Spring forecast (Mar25) | EH4: Budget (Nov25) | EJ4: =Z4 -> Spring Statement (Mar22) | EK4: =AA4 -> AS22 | EL4: =AB4 -> Budget (Mar23) | EM4: =AC4 -> AS23 | EN4: =AD4 -> Budget (Mar24) | EO4: =AE4 -> Budget (Oct24) | EP4: =AF4 -> Spring forecast (Mar25) | EQ4: Budget (Nov25) | ES4: =Z4 -> Spring Statement (Mar22) | ET4: =AA4 -> AS22 | EU4: =AB4 -> Budget (Mar23) | EV4: =AC4 -> AS23 | EW4: =AD4 -> Budget (Mar24) | EX4: =AE4 -> Budget (Oct24) | EY4: =AF4 -> Spring forecast (Mar25) | EZ4: Budget (Nov25) | FC4: OBR (Nov25) | FD4: OBR (Mar25) | FE4: OE (Nov25)
A5: Tax | B5: =PresentationalScorecardRounded!I108 -> 70 | C5: =PresentationalScorecardRounded!J108 -> -1905 | D5: =PresentationalScorecardRounded!K108 -> 2890 | E5: =PresentationalScorecardRounded!L108 -> 10730 | F5: =PresentationalScorecardRounded!M108 -> 23150 | G5: =PresentationalScorecardRounded!N108 -> 26645 | I5: ='Aggregates (per cent of GDP)'!B57 -> 2000-01 | J5: =LEFT(I5,4) -> 2000 | K5: =-('Aggregates (per cent of GDP)'!M57-'Aggregates (per cent of GDP)'!M56) -> -0.014043284 | M5: 2010-2019 | N5: =AVERAGE(OBR_NOV25_C7.3!C27:C45) -> 33.984636 | P5: ='Aggregates (per cent of GDP)'!B5 -> 1948-49 | Q5: ='Aggregates (per cent of GDP)'!C5 -> 42.940919 | R5: ='Aggregates (per cent of GDP)'!D5 -> 38.599562 | T5: ='[1]CPI Forecast'!A342 -> 45292 | U5: ='[3]CPI Forecast'!F342 -> 3.9811146 | V5: ='[3]CPI Forecast'!D342 -> 3.9811146 | W5: 2 | Y5: 19-20 | Z5: =100*(AR5/AR$10) -> 90.99234 | AI5: =100*(BA5/BA$11) -> 70.963367 | AR5: =100*(BJ5/EJ5) -> 5.5851589 | BA5: =100*(BS5/EJ5) -> 1.0059249 | BJ5: =DR5/($CC5/1000) -> 4.8181184 | BS5: =EA5/($CC5/1000) -> 0.86777571 | CB5: 202001 | CC5: =VLOOKUP(CB5,DataQ!$C$7:$E$358,3,FALSE) -> 66712 | CE5: =Y5 -> 19-20 | CF5: =100*(CZ5/CZ$11) -> 85.577018 | CN5: 100 | CP5: =100*(DI5/DI$11) -> 67.606994 | CX5: 100 | CZ5: =100*(DR5/EJ5) -> 372.59712 | DI5: =100*(EA5/EJ5) -> 67.107261 | DR5: ='[2]Chart Data'!CJ5 -> 321.42632 | EA5: ='[2]Chart Data'!CR5 -> 57.891053 | EJ5: =100*(ES5/ES$11) -> 86.266451 | EK5: =100*(ET5/ET$11) -> 85.633753 | EL5: =100*(EU5/EU$11) -> 85.312398 | EM5: =100*(EV5/EV$11) -> 81.67592 | EN5: =100*(EW5/EW$11) -> 82.241835 | EO5: =100*(EX5/EX$11) -> 80.45333 | EP5: =100*(EY5/EY$11) -> 78.844029 | EQ5: =100*(EZ5/EZ$11) -> #DIV/0! | ES5: ='[2]Chart Data'!DH5 -> 100.74871 | ET5: ='[2]Chart Data'!DI5 -> 100.88484 | EU5: ='[2]Chart Data'!DJ5 -> 100.88484 | EV5: ='[2]Chart Data'!DK5 -> 100.73409 | EW5: ='[2]Chart Data'!DL5 -> 100.73409 | EX5: ='[2]Chart Data'!DM5 -> 100.73409 | EY5: ='[2]Chart Data'!DN5 -> 90.938577 | FB5: 2024 | FC5: =100*(OBR_NOV25_ST1.1!R114/OBR_NOV25_ST1.1!$R$114) -> 100 | FD5: =100*(OBR_MAR25_ST1.1!R110/OBR_MAR25_ST1.1!$R$110) -> 100 | FE5: =100*(FG5/$FG$5) -> 100 | FG5: =SUMIF(DataQ!A:A,'Chart Data'!FB5,DataQ!F:F) -> 2783075
A6: Spending | B6: =PresentationalScorecardRounded!I107 -> -4200 | C6: =PresentationalScorecardRounded!J107 -> -7410 | D6: =PresentationalScorecardRounded!K107 -> -10330 | E6: =PresentationalScorecardRounded!L107 -> -7305 | F6: =PresentationalScorecardRounded!M107 -> -2615 | G6: =PresentationalScorecardRounded!N107 -> -2535 | I6: ='Aggregates (per cent of GDP)'!B58 -> 2001-02 | J6: =LEFT(I6,4) -> 2001 | K6: =-('Aggregates (per cent of GDP)'!M58-'Aggregates (per cent of GDP)'!M57) -> 1.9511056 | M6: Sunak | N6: =AVERAGE(OBR_NOV25_C7.3!C46:C48) -> 26.014549 | P6: =OBR_NOV25_C4.1!B30 -> 1949-50 | Q6: ='Aggregates (per cent of GDP)'!C6 -> 43.298545 | R6: ='Aggregates (per cent of GDP)'!D6 -> 38.474813 | T6: ='[1]CPI Forecast'!A343 -> 45323 | U6: ='[3]CPI Forecast'!F343 -> 3.4114722 | V6: ='[3]CPI Forecast'!D343 -> 3.4114722 | W6: 2 | Y6: 20-21 | Z6: =100*(AR6/AR$10) -> 116.01458 | AI6: =100*(BA6/BA$11) -> 83.964623 | AR6: =100*(BJ6/EJ6) -> 7.1210373 | BA6: =100*(BS6/EJ6) -> 1.1902212 | BJ6: =DR6/($CC6/1000) -> 6.4932374 | BS6: =EA6/($CC6/1000) -> 1.0852897 | CB6: =+CB5+100 -> 202101 | CC6: =VLOOKUP(CB6,DataQ!$C$7:$E$358,3,FALSE) -> 66918.5 | CE6: =Y6 -> 20-21 | CF6: =100*(CZ6/CZ$11) -> 109.44782 | CN6: 100 | CP6: =100*(DI6/DI$11) -> 80.240938 | CX6: 100 | CZ6: =100*(DR6/EJ6) -> 476.52914 | DI6: =100*(EA6/EJ6) -> 79.647818 | DR6: ='[2]Chart Data'!CJ6 -> 434.5177 | EA6: ='[2]Chart Data'!CR6 -> 72.625962 | EJ6: =100*(ES6/ES$11) -> 91.183869 | EK6: =100*(ET6/ET$11) -> 91.036341 | EL6: =100*(EU6/EU$11) -> 90.569204 | EM6: =100*(EV6/EV$11) -> 86.027982 | EN6: =100*(EW6/EW$11) -> 86.624052 | EO6: =100*(EX6/EX$11) -> 84.740247 | EP6: =100*(EY6/EY$11) -> 82.977176 | EQ6: =100*(EZ6/EZ$11) -> #DIV/0! | ES6: ='[2]Chart Data'!DH6 -> 106.49166 | ET6: ='[2]Chart Data'!DI6 -> 107.24961 | EU6: ='[2]Chart Data'!DJ6 -> 107.10119 | EV6: ='[2]Chart Data'!DK6 -> 106.10166 | EW6: ='[2]Chart Data'!DL6 -> 106.10166 | EX6: ='[2]Chart Data'!DM6 -> 106.10166 | EY6: ='[2]Chart Data'!DN6 -> 95.705742 | FB6: 2025 | FC6: =100*(OBR_NOV25_ST1.1!R115/OBR_NOV25_ST1.1!$R$114) -> 101.48334 | FD6: =100*(OBR_MAR25_ST1.1!R111/OBR_MAR25_ST1.1!$R$110) -> 100.97159 | FE6: =100*(FG6/$FG$5) -> 101.41727 | FG6: =SUMIF(DataQ!A:A,'Chart Data'!FB6,DataQ!F:F) -> 2822518.8
A7: Total | B7: =SUM(B5:B6) -> -4130 | C7: =SUM(C5:C6) -> -9315 | D7: =SUM(D5:D6) -> -7440 | E7: =SUM(E5:E6) -> 3425 | F7: =SUM(F5:F6) -> 20535 | G7: =SUM(G5:G6) -> 24110 | I7: ='Aggregates (per cent of GDP)'!B59 -> 2002-03 | J7: =LEFT(I7,4) -> 2002 | K7: =-('Aggregates (per cent of GDP)'!M59-'Aggregates (per cent of GDP)'!M58) -> 2.0209111 | M7: Hunt | N7: =AVERAGE(OBR_NOV25_C7.3!C50:C52) -> 9.9622058 | P7: =OBR_NOV25_C4.1!B31 -> 1950-51 | Q7: ='Aggregates (per cent of GDP)'!C7 -> 42.841444 | R7: ='Aggregates (per cent of GDP)'!D7 -> 39.183673 | T7: ='[1]CPI Forecast'!A344 -> 45352 | U7: ='[3]CPI Forecast'!F344 -> 3.2280593 | V7: ='[3]CPI Forecast'!D344 -> 3.2280593 | W7: 2 | Y7: 21-22 | Z7: =100*(AR7/AR$10) -> 108.21144 | AA7: =100*(AS7/AS$10) -> 110.92075 | AB7: =100*(AT7/AT$10) -> 110.06915 | AI7: =100*(BA7/BA$11) -> 80.06318 | AJ7: =100*(BB7/BB$11) -> 92.126901 | AK7: =100*(BC7/BC$11) -> 91.416586 | AR7: =100*(BJ7/EJ7) -> 6.6420763 | AS7: =100*(BK7/EK7) -> 6.7598794 | AT7: =100*(BL7/EL7) -> 6.8111688 | BA7: =100*(BS7/EJ7) -> 1.1349172 | BB7: =100*(BT7/EK7) -> 1.2578242 | BC7: =100*(BU7/EL7) -> 1.2673677 | BJ7: =DR7/($CC7/1000) -> 6.0029462 | BK7: =DS7/($CC7/1000) -> 6.1323736 | BL7: =DT7/($CC7/1000) -> 6.1323736 | BS7: =EA7/($CC7/1000) -> 1.0257104 | BT7: =EB7/($CC7/1000) -> 1.141063 | BU7: =EC7/($CC7/1000) -> 1.141063 | CB7: =+CB6+100 -> 202201 | CC7: =VLOOKUP(CB7,DataQ!$C$7:$E$358,3,FALSE) -> 67471.5 | CE7: =Y7 -> 21-22 | CF7: =100*(CZ7/CZ$11) -> 102.92998 | CG7: =100*(DA7/DA$11) -> 105.98934 | CH7: =100*(DB7/DB$11) -> 105.44094 | CN7: 100 | CP7: =100*(DI7/DI$11) -> 77.1448 | CQ7: =100*(DJ7/DJ$11) -> 88.768787 | CR7: =100*(DK7/DK$11) -> 88.084363 | CX7: 100 | CZ7: =100*(DR7/EJ7) -> 448.15085 | DA7: =100*(DS7/EK7) -> 456.0992 | DB7: =100*(DT7/EL7) -> 459.55977 | DI7: =100*(EA7/EJ7) -> 76.574566 | DJ7: =100*(EB7/EK7) -> 84.867286 | DK7: =100*(EC7/EL7) -> 85.511201 | DR7: ='[2]Chart Data'!CJ7 -> 405.02778 | DS7: ='[2]Chart Data'!CK7 -> 413.76045 | DT7: ='[2]Chart Data'!CL7 -> 413.76045 | EA7: ='[2]Chart Data'!CR7 -> 69.20622 | EB7: ='[2]Chart Data'!CS7 -> 76.989229 | EC7: ='[2]Chart Data'!CT7 -> 76.989229 | EJ7: =100*(ES7/ES$11) -> 90.377554 | EK7: =100*(ET7/ET$11) -> 90.717204 | EL7: =100*(EU7/EU$11) -> 90.034087 | EM7: =100*(EV7/EV$11) -> 85.45606 | EN7: =100*(EW7/EW$11) -> 86.029411 | EO7: =100*(EX7/EX$11) -> 84.158538 | EP7: =100*(EY7/EY$11) -> 82.608053 | EQ7: =100*(EZ7/EZ$11) -> #DIV/0! | ES7: ='[2]Chart Data'!DH7 -> 105.54998 | ET7: ='[2]Chart Data'!DI7 -> 106.87364 | EU7: ='[2]Chart Data'!DJ7 -> 106.4684 | EV7: ='[2]Chart Data'!DK7 -> 105.39629 | EW7: ='[2]Chart Data'!DL7 -> 105.37331 | EX7: ='[2]Chart Data'!DM7 -> 105.37331 | EY7: ='[2]Chart Data'!DN7 -> 95.279996 | FB7: 2026 | FC7: =100*(OBR_NOV25_ST1.1!R116/OBR_NOV25_ST1.1!$R$114) -> 102.87515 | FD7: =100*(OBR_MAR25_ST1.1!R112/OBR_MAR25_ST1.1!$R$110) -> 102.8514 | FE7: =100*(FG7/$FG$5) -> 102.33453 | FG7: =SUMIF(DataQ!A:A,'Chart Data'!FB7,DataQ!F:F) -> 2848046.6
I8: ='Aggregates (per cent of GDP)'!B60 -> 2003-04 | J8: =LEFT(I8,4) -> 2003 | K8: =-('Aggregates (per cent of GDP)'!M60-'Aggregates (per cent of GDP)'!M59) -> 0.43914094 | P8: =OBR_NOV25_C4.1!B32 -> 1951-52 | Q8: ='Aggregates (per cent of GDP)'!C8 -> 41.131231 | R8: ='Aggregates (per cent of GDP)'!D8 -> 40.648815 | T8: ='[1]CPI Forecast'!A345 -> 45383 | U8: ='[3]CPI Forecast'!F345 -> 2.3330701 | V8: ='[3]CPI Forecast'!D345 -> 2.3330701 | W8: 2 | Y8: 22-23 | Z8: =100*(AR8/AR$10) -> 103.23134 | AA8: =100*(AS8/AS$10) -> 104.94869 | AB8: =100*(AT8/AT$10) -> 103.37416 | AC8: =100*(AU8/AU$10) -> 103.89247 | AD8: =100*(AV8/AV$10) -> 103.67212 | AI8: =100*(BA8/BA$11) -> 94.449425 | AJ8: =100*(BB8/BB$11) -> 100.13982 | AK8: =100*(BC8/BC$11) -> 95.858372 | AL8: =100*(BD8/BD$11) -> 103.87881 | AM8: =100*(BE8/BE$11) -> 102.1785 | AR8: =100*(BJ8/EJ8) -> 6.3363951 | AS8: =100*(BK8/EK8) -> 6.3959221 | AT8: =100*(BL8/EL8) -> 6.3968773 | AU8: =100*(BM8/EM8) -> 6.610211 | AV8: =100*(BN8/EN8) -> 6.4932717 | BA8: =100*(BS8/EJ8) -> 1.3388461 | BB8: =100*(BT8/EK8) -> 1.367226 | BC8: =100*(BU8/EL8) -> 1.3289471 | BD8: =100*(BV8/EM8) -> 1.4422606 | BE8: =100*(BW8/EN8) -> 1.4309267 | BJ8: =DR8/($CC8/1000) -> 5.9583347 | BK8: =DS8/($CC8/1000) -> 6.0827772 | BL8: =DT8/($CC8/1000) -> 6.082774 | BM8: =DU8/($CC8/1000) -> 6.02511 | BN8: =DV8/($CC8/1000) -> 5.9654001 | BS8: =EA8/($CC8/1000) -> 1.258964 | BT8: =EB8/($CC8/1000) -> 1.3002865 | BU8: =EC8/($CC8/1000) -> 1.2636923 | BV8: =ED8/($CC8/1000) -> 1.3145993 | BW8: =EE8/($CC8/1000) -> 1.3145993 | CB8: =+CB7+100 -> 202301 | CC8: =VLOOKUP(CB8,DataQ!$C$7:$E$358,3,FALSE) -> 68303.5 | CE8: =Y8 -> 22-23 | CF8: =100*(CZ8/CZ$11) -> 99.403771 | CG8: =100*(DA8/DA$11) -> 101.51939 | CH8: =100*(DB8/DB$11) -> 100.24858 | CI8: =100*(DC8/DC$11) -> 101.40112 | CJ8: =100*(DD8/DD$11) -> 100.79035 | CN8: 100 | CP8: =100*(DI8/DI$11) -> 92.128867 | CQ8: =100*(DJ8/DJ$11) -> 97.679454 | CR8: =100*(DK8/DK$11) -> 93.503197 | CS8: =100*(DL8/DL$11) -> 101.32658 | CT8: =100*(DM8/DM$11) -> 99.668046 | CX8: 100 | CZ8: =100*(DR8/EJ8) -> 432.79796 | DA8: =100*(DS8/EK8) -> 436.86387 | DB8: =100*(DT8/EL8) -> 436.92911 | DC8: =100*(DU8/EM8) -> 451.50055 | DD8: =100*(DV8/EN8) -> 443.51319 | DI8: =100*(EA8/EJ8) -> 91.447875 | DJ8: =100*(EB8/EK8) -> 93.386318 | DK8: =100*(EC8/EL8) -> 90.771738 | DL8: =100*(ED8/EM8) -> 98.511446 | DM8: =100*(EE8/EN8) -> 97.737304 | DR8: ='[2]Chart Data'!CJ8 -> 406.97511 | DS8: ='[2]Chart Data'!CK8 -> 415.47497 | DT8: ='[2]Chart Data'!CL8 -> 415.47476 | DU8: ='[2]Chart Data'!CM8 -> 411.5361 | DV8: ='[2]Chart Data'!CN8 -> 407.4577 | EA8: ='[2]Chart Data'!CR8 -> 85.991647 | EB8: ='[2]Chart Data'!CS8 -> 88.814116 | EC8: ='[2]Chart Data'!CT8 -> 86.31461 | ED8: ='[2]Chart Data'!CU8 -> 89.791733 | EE8: ='[2]Chart Data'!CV8 -> 89.791733 | EJ8: =100*(ES8/ES$11) -> 94.03351 | EK8: =100*(ET8/ET$11) -> 95.103991 | EL8: =100*(EU8/EU$11) -> 95.089741 | EM8: =100*(EV8/EV$11) -> 91.148528 | EN8: =100*(EW8/EW$11) -> 91.870482 | EO8: =100*(EX8/EX$11) -> 89.815286 | EP8: =100*(EY8/EY$11) -> 88.449975 | EQ8: =100*(EZ8/EZ$11) -> #DIV/0! | ES8: ='[2]Chart Data'!DH8 -> 109.81969 | ET8: ='[2]Chart Data'!DI8 -> 112.0417 | EU8: ='[2]Chart Data'!DJ8 -> 112.44689 | EV8: ='[2]Chart Data'!DK8 -> 112.41703 | EW8: ='[2]Chart Data'!DL8 -> 112.52776 | EX8: ='[2]Chart Data'!DM8 -> 112.45602 | EY8: ='[2]Chart Data'!DN8 -> 102.01806 | FB8: 2027 | FC8: =100*(OBR_NOV25_ST1.1!R117/OBR_NOV25_ST1.1!$R$114) -> 104.46214 | FD8: =100*(OBR_MAR25_ST1.1!R113/OBR_MAR25_ST1.1!$R$110) -> 104.69281 | FE8: =100*(FG8/$FG$5) -> 103.6345 | FG8: =SUMIF(DataQ!A:A,'Chart Data'!FB8,DataQ!F:F) -> 2884225.9
A9: check | B9: =PresentationalScorecardRounded!I106 -> -4125 | C9: =PresentationalScorecardRounded!J106 -> -9315 | D9: =PresentationalScorecardRounded!K106 -> -7445 | E9: =PresentationalScorecardRounded!L106 -> 3425 | F9: =PresentationalScorecardRounded!M106 -> 20535 | G9: =PresentationalScorecardRounded!N106 -> 24110 | I9: ='Aggregates (per cent of GDP)'!B61 -> 2004-05 | J9: =LEFT(I9,4) -> 2004 | K9: =-('Aggregates (per cent of GDP)'!M61-'Aggregates (per cent of GDP)'!M60) -> 0.49799101 | M9: Budget (Oct24) | N9: =OBR_NOV25_C7.3!C53 -> 9.9293595 | P9: =OBR_NOV25_C4.1!B33 -> 1952-53 | Q9: ='Aggregates (per cent of GDP)'!C9 -> 39.926622 | R9: ='Aggregates (per cent of GDP)'!D9 -> 41.271885 | T9: ='[1]CPI Forecast'!A346 -> 45413 | U9: ='[3]CPI Forecast'!F346 -> 1.9899778 | V9: ='[3]CPI Forecast'!D346 -> 1.9899778 | W9: 2 | Y9: 23-24 | Z9: =100*(AR9/AR$10) -> 99.906763 | AA9: =100*(AS9/AS$10) -> 101.51973 | AB9: =100*(AT9/AT$10) -> 101.14166 | AC9: =100*(AU9/AU$10) -> 100.33612 | AD9: =100*(AV9/AV$10) -> 99.838846 | AI9: =100*(BA9/BA$11) -> 100.35011 | AJ9: =100*(BB9/BB$11) -> 101.97794 | AK9: =100*(BC9/BC$11) -> 102.89491 | AL9: =100*(BD9/BD$11) -> 103.49245 | AM9: =100*(BE9/BE$11) -> 100.91231 | AN9: =100*(BF9/BF$11) -> 92.20828 | AO9: =100*(BG9/BG$11) -> 93.686949 | AR9: =100*(BJ9/EJ9) -> 6.132331 | AS9: =100*(BK9/EK9) -> 6.1869498 | AT9: =100*(BL9/EL9) -> 6.2587288 | AU9: =100*(BM9/EM9) -> 6.3839363 | AV9: =100*(BN9/EN9) -> 6.2531833 | AW9: =100*(BO9/EO9) -> 6.4125332 | AX9: =100*(BP9/EP9) -> 6.5177315 | BA9: =100*(BS9/EJ9) -> 1.42249 | BB9: =100*(BT9/EK9) -> 1.3923221 | BC9: =100*(BU9/EL9) -> 1.4264992 | BD9: =100*(BV9/EM9) -> 1.4368964 | BE9: =100*(BW9/EN9) -> 1.4131948 | BF9: =100*(BX9/EO9) -> 1.4651178 | BG9: =100*(BY9/EP9) -> 1.4891532 | BJ9: =DR9/($CC9/1000) -> 5.9054235 | BK9: =DS9/($CC9/1000) -> 6.0742993 | BL9: =DT9/($CC9/1000) -> 6.1032518 | BM9: =DU9/($CC9/1000) -> 6.1731424 | BN9: =DV9/($CC9/1000) -> 6.1214461 | BO9: =DW9/($CC9/1000) -> 6.1182863 | BP9: =DX9/($CC9/1000) -> 6.1182863 | BS9: =EA9/($CC9/1000) -> 1.3698552 | BT9: =EB9/($CC9/1000) -> 1.366971 | BU9: =EC9/($CC9/1000) -> 1.3910627 | BV9: =ED9/($CC9/1000) -> 1.3894509 | BW9: =EE9/($CC9/1000) -> 1.3834227 | BX9: =EF9/($CC9/1000) -> 1.3978891 | BY9: =EG9/($CC9/1000) -> 1.3978891 | CB9: =+CB8+100 -> 202401 | CC9: =VLOOKUP(CB9,DataQ!$C$7:$E$358,3,FALSE) -> 69092.25 | CE9: =Y9 -> 23-24 | CF9: =100*(CZ9/CZ$11) -> 97.313385 | CG9: =100*(DA9/DA$11) -> 99.336486 | CH9: =100*(DB9/DB$11) -> 99.216234 | CI9: =100*(DC9/DC$11) -> 99.060918 | CJ9: =100*(DD9/DD$11) -> 98.184498 | CN9: 100 | CP9: =100*(DI9/DI$11) -> 99.014923 | CQ9: =100*(DJ9/DJ$11) -> 100.62109 | CR9: =100*(DK9/DK$11) -> 101.52586 | CS9: =100*(DL9/DL$11) -> 102.11545 | CT9: =100*(DM9/DM$11) -> 99.569641 | CU9: =100*(DN9/DN$11) -> 90.981421 | CV9: =100*(DO9/DO$11) -> 92.440416 | CX9: 100 | CZ9: =100*(DR9/EJ9) -> 423.69655 | DA9: =100*(DS9/EK9) -> 427.47028 | DB9: =100*(DT9/EL9) -> 432.42965 | DC9: =100*(DU9/EM9) -> 441.08053 | DD9: =100*(DV9/EN9) -> 432.0465 | DE9: =100*(DW9/EO9) -> 443.05635 | DF9: =100*(DX9/EP9) -> 450.32474 | DI9: =100*(EA9/EJ9) -> 98.283031 | DJ9: =100*(EB9/EK9) -> 96.198666 | DK9: =100*(EC9/EL9) -> 98.560042 | DL9: =100*(ED9/EM9) -> 99.278405 | DM9: =100*(EE9/EN9) -> 97.640805 | DN9: =100*(EF9/EO9) -> 101.22829 | DO9: =100*(EG9/EP9) -> 102.88895 | DR9: ='[2]Chart Data'!CJ9 -> 408.019 | DS9: ='[2]Chart Data'!CK9 -> 419.68701 | DT9: ='[2]Chart Data'!CL9 -> 421.6874 | DU9: ='[2]Chart Data'!CM9 -> 426.51629 | DV9: ='[2]Chart Data'!CN9 -> 422.94449 | DW9: ='[2]Chart Data'!CO9 -> 422.72616 | DX9: ='[2]Chart Data'!CP9 -> 422.72616 | EA9: ='[2]Chart Data'!CR9 -> 94.646379 | EB9: ='[2]Chart Data'!CS9 -> 94.447103 | EC9: ='[2]Chart Data'!CT9 -> 96.111651 | ED9: ='[2]Chart Data'!CU9 -> 96.000288 | EE9: ='[2]Chart Data'!CV9 -> 95.583786 | EF9: ='[2]Chart Data'!CW9 -> 96.583303 | EG9: ='[2]Chart Data'!CX9 -> 96.583303 | EJ9: =100*(ES9/ES$11) -> 96.299816 | EK9: =100*(ET9/ET$11) -> 98.179224 | EL9: =100*(EU9/EU$11) -> 97.515837 | EM9: =100*(EV9/EV$11) -> 96.698056 | EN9: =100*(EW9/EW$11) -> 97.893279 | EO9: =100*(EX9/EX$11) -> 95.411377 | EP9: =100*(EY9/EY$11) -> 93.871407 | EQ9: =100*(EZ9/EZ$11) -> #DIV/0! | ES9: ='[2]Chart Data'!DH9 -> 112.46646 | ET9: ='[2]Chart Data'!DI9 -> 115.66462 | EU9: ='[2]Chart Data'!DJ9 -> 115.31583 | EV9: ='[2]Chart Data'!DK9 -> 119.26148 | EW9: ='[2]Chart Data'!DL9 -> 119.9048 | EX9: ='[2]Chart Data'!DM9 -> 119.46278 | EY9: ='[2]Chart Data'!DN9 -> 108.27113 | FB9: 2028 | FC9: =100*(OBR_NOV25_ST1.1!R118/OBR_NOV25_ST1.1!$R$114) -> 105.99506 | FD9: =100*(OBR_MAR25_ST1.1!R114/OBR_MAR25_ST1.1!$R$110) -> 106.49628 | FE9: =100*(FG9/$FG$5) -> 105.32973 | FG9: =SUMIF(DataQ!A:A,'Chart Data'!FB9,DataQ!F:F) -> 2931405.4
I10: ='Aggregates (per cent of GDP)'!B62 -> 2005-06 | J10: =LEFT(I10,4) -> 2005 | K10: =-('Aggregates (per cent of GDP)'!M62-'Aggregates (per cent of GDP)'!M61) -> -0.69891444 | M10: Spring forecast (Mar25) | N10: =OBR_NOV25_C7.3!C54 -> 9.9316225 | P10: =OBR_NOV25_C4.1!B34 -> 1953-54 | Q10: ='Aggregates (per cent of GDP)'!C10 -> 37.998202 | R10: ='Aggregates (per cent of GDP)'!D10 -> 40.503446 | T10: ='[1]CPI Forecast'!A347 -> 45444 | U10: ='[3]CPI Forecast'!F347 -> 1.9753105 | V10: ='[3]CPI Forecast'!D347 -> 1.9753105 | W10: 2 | Y10: 24-25 | Z10: =100*(AR10/AR$10) -> 100 | AA10: =100*(AS10/AS$10) -> 100 | AB10: =100*(AT10/AT$10) -> 100 | AC10: =100*(AU10/AU$10) -> 100 | AD10: =100*(AV10/AV$10) -> 100 | AE10: =100*(AW10/AW$10) -> 100 | AF10: =100*(AX10/AX$10) -> 100 | AI10: =100*(BA10/BA$11) -> 98.011095 | AJ10: =100*(BB10/BB$11) -> 100.19157 | AK10: =100*(BC10/BC$11) -> 101.36185 | AL10: =100*(BD10/BD$11) -> 104.39257 | AM10: =100*(BE10/BE$11) -> 103.13113 | AN10: =100*(BF10/BF$11) -> 91.655284 | AO10: =100*(BG10/BG$11) -> 95.455059 | AP10: =100*(BH10/BH$11) -> #DIV/0! | AR10: =100*(BJ10/EJ10) -> 6.1380539 | AS10: =100*(BK10/EK10) -> 6.0943325 | AT10: =100*(BL10/EL10) -> 6.1880818 | AU10: =100*(BM10/EM10) -> 6.3625508 | AV10: =100*(BN10/EN10) -> 6.2632768 | AW10: =100*(BO10/EO10) -> 6.6682366 | AX10: =100*(BP10/EP10) -> 6.6467268 | AY10: =100*(BQ10/EQ10) -> #DIV/0! | BA10: =100*(BS10/EJ10) -> 1.3893337 | BB10: =100*(BT10/EK10) -> 1.3679324 | BC10: =100*(BU10/EL10) -> 1.4052454 | BD10: =100*(BV10/EM10) -> 1.4493936 | BE10: =100*(BW10/EN10) -> 1.4442676 | BF10: =100*(BX10/EO10) -> 1.4563311 | BG10: =100*(BY10/EP10) -> 1.5172573 | BH10: =100*(BZ10/EQ10) -> #DIV/0! | BJ10: =DR10/($CC10/1000) -> 6.0204819 | BK10: =DS10/($CC10/1000) -> 6.0621868 | BL10: =DT10/($CC10/1000) -> 6.1290571 | BM10: =DU10/($CC10/1000) -> 6.2554091 | BN10: =DV10/($CC10/1000) -> 6.1798964 | BO10: =DW10/($CC10/1000) -> 6.5125227 | BP10: =DX10/($CC10/1000) -> 6.4747094 | BQ10: =DY10/($CC10/1000) -> 0 | BS10: =EA10/($CC10/1000) -> 1.3627216 | BT10: =EB10/($CC10/1000) -> 1.360717 | BU10: =EC10/($CC10/1000) -> 1.3918416 | BV10: =ED10/($CC10/1000) -> 1.4249867 | BW10: =EE10/($CC10/1000) -> 1.4250407 | BX10: =EF10/($CC10/1000) -> 1.4223235 | BY10: =EG10/($CC10/1000) -> 1.4779907 | BZ10: =EH10/($CC10/1000) -> 0 | CB10: =+CB9+100 -> 202501 | CC10: =VLOOKUP(CB10,DataQ!$C$7:$E$358,3,FALSE) -> 69612.07 | CE10: =Y10 -> 24-25 | CF10: =100*(CZ10/CZ$11) -> 98.137028 | CG10: =100*(DA10/DA$11) -> 98.585616 | CH10: =100*(DB10/DB$11) -> 98.83434 | CI10: =100*(DC10/DC$11) -> 99.471869 | CJ10: =100*(DD10/DD$11) -> 99.082872 | CK10: =100*(DE10/DE$11) -> 96.992273 | CL10: =100*(DF10/DF$11) -> 96.199486 | CN10: 100 | CP10: =100*(DI10/DI$11) -> 97.434609 | CQ10: =100*(DJ10/DJ$11) -> 99.602254 | CR10: =100*(DK10/DK$11) -> 100.76566 | CS10: =100*(DL10/DL$11) -> 103.77854 | CT10: =100*(DM10/DM$11) -> 102.52453 | CU10: =100*(DN10/DN$11) -> 91.116182 | CV10: =100*(DO10/DO$11) -> 94.893607 | CW10: =100*(DP10/DP$11) -> #DIV/0! | CX10: 100 | CZ10: =100*(DR10/EJ10) -> 427.28264 | DA10: =100*(DS10/EK10) -> 424.2391 | DB10: =100*(DT10/EL10) -> 430.76518 | DC10: =100*(DU10/EM10) -> 442.91033 | DD10: =100*(DV10/EN10) -> 435.99966 | DE10: =100*(DW10/EO10) -> 464.18975 | DF10: =100*(DX10/EP10) -> 462.69241 | DI10: =100*(EA10/EJ10) -> 96.714398 | DJ10: =100*(EB10/EK10) -> 95.224609 | DK10: =100*(EC10/EL10) -> 97.822043 | DL10: =100*(ED10/EM10) -> 100.89529 | DM10: =100*(EE10/EN10) -> 100.53846 | DN10: =100*(EF10/EO10) -> 101.37823 | DO10: =100*(EG10/EP10) -> 105.61942 | DP10: =100*(EH10/EQ10) -> #DIV/0! | DR10: ='[2]Chart Data'!CJ10 -> 419.09821 | DS10: ='[2]Chart Data'!CK10 -> 422.00137 | DT10: ='[2]Chart Data'!CL10 -> 426.65635 | DU10: ='[2]Chart Data'!CM10 -> 435.45198 | DV10: ='[2]Chart Data'!CN10 -> 430.19538 | DW10: ='[2]Chart Data'!CO10 -> 453.35019 | DX10: ='[2]Chart Data'!CP10 -> 450.71792 | EA10: ='[2]Chart Data'!CR10 -> 94.861872 | EB10: ='[2]Chart Data'!CS10 -> 94.722329 | EC10: ='[2]Chart Data'!CT10 -> 96.888973 | ED10: ='[2]Chart Data'!CU10 -> 99.196273 | EE10: ='[2]Chart Data'!CV10 -> 99.20003 | EF10: ='[2]Chart Data'!CW10 -> 99.010883 | EG10: ='[2]Chart Data'!CX10 -> 102.88599 | EJ10: =100*(ES10/ES$11) -> 98.084539 | EK10: =100*(ET10/ET$11) -> 99.472532 | EL10: =100*(EU10/EU$11) -> 99.046155 | EM10: =100*(EV10/EV$11) -> 98.316057 | EN10: =100*(EW10/EW$11) -> 98.668741 | EO10: =100*(EX10/EX$11) -> 97.664841 | EP10: =100*(EY10/EY$11) -> 97.411998 | EQ10: =100*(EZ10/EZ$11) -> #DIV/0! | ES10: ='[2]Chart Data'!DH10 -> 114.5508 | ET10: ='[2]Chart Data'!DI10 -> 117.18826 | EU10: ='[2]Chart Data'!DJ10 -> 117.12548 | EV10: ='[2]Chart Data'!DK10 -> 121.25702 | EW10: ='[2]Chart Data'!DL10 -> 120.85462 | EX10: ='[2]Chart Data'!DM10 -> 122.2843 | EY10: ='[2]Chart Data'!DN10 -> 112.35484 | FB10: 2029 | FC10: =100*(OBR_NOV25_ST1.1!R119/OBR_NOV25_ST1.1!$R$114) -> 107.60945 | FD10: =100*(OBR_MAR25_ST1.1!R115/OBR_MAR25_ST1.1!$R$110) -> 108.41408 | FE10: =100*(FG10/$FG$5) -> 107.07962 | FG10: =SUMIF(DataQ!A:A,'Chart Data'!FB10,DataQ!F:F) -> 2980106
A11: GDP! | B11: 3051.124 | C11: 3165.0453 | D11: 3277.5845 | E11: 3388.4929 | F11: 3504.0992 | G11: 3627.9775 | I11: ='Aggregates (per cent of GDP)'!B63 -> 2006-07 | J11: =LEFT(I11,4) -> 2006 | K11: =-('Aggregates (per cent of GDP)'!M63-'Aggregates (per cent of GDP)'!M62) -> -0.72216082 | M11: Budget (Nov25) | N11: =OBR_NOV25_C7.3!C55 -> 21.699459 | P11: =OBR_NOV25_C4.1!B35 -> 1954-55 | Q11: ='Aggregates (per cent of GDP)'!C11 -> 37.46378 | R11: ='Aggregates (per cent of GDP)'!D11 -> 38.923925 | T11: ='[1]CPI Forecast'!A348 -> 45474 | U11: ='[3]CPI Forecast'!F348 -> 2.2344448 | V11: ='[3]CPI Forecast'!D348 -> 2.2344448 | W11: 2 | Y11: 25-26 | Z11: =100*(AR11/AR$10) -> 101.29899 | AA11: =100*(AS11/AS$10) -> 100.83805 | AB11: =100*(AT11/AT$10) -> 100.58429 | AC11: =100*(AU11/AU$10) -> 99.939628 | AD11: =100*(AV11/AV$10) -> 100.33199 | AE11: =100*(AW11/AW$10) -> 102.49457 | AF11: =100*(AX11/AX$10) -> 103.33924 | AG11: =100*(AY11/AY$11) -> #DIV/0! | AI11: =100*(BA11/BA$11) -> 100 | AJ11: =100*(BB11/BB$11) -> 100 | AK11: =100*(BC11/BC$11) -> 100 | AL11: =100*(BD11/BD$11) -> 100 | AM11: =100*(BE11/BE$11) -> 100 | AN11: =100*(BF11/BF$11) -> 100 | AO11: =100*(BG11/BG$11) -> 100 | AP11: =100*(BH11/BH$11) -> #DIV/0! | AR11: =100*(BJ11/EJ11) -> 6.2177865 | AS11: =100*(BK11/EK11) -> 6.1454062 | AT11: =100*(BL11/EL11) -> 6.2242379 | AU11: =100*(BM11/EM11) -> 6.3587096 | AV11: =100*(BN11/EN11) -> 6.2840702 | AW11: =100*(BO11/EO11) -> 6.8345806 | AX11: =100*(BP11/EP11) -> 6.8686768 | AY11: =100*(BQ11/EQ11) -> #DIV/0! | BA11: =100*(BS11/EJ11) -> 1.417527 | BB11: =100*(BT11/EK11) -> 1.365317 | BC11: =100*(BU11/EL11) -> 1.3863652 | BD11: =100*(BV11/EM11) -> 1.388407 | BE11: =100*(BW11/EN11) -> 1.4004186 | BF11: =100*(BX11/EO11) -> 1.5889222 | BG11: =100*(BY11/EP11) -> 1.5894991 | BH11: =100*(BZ11/EQ11) -> #DIV/0! | BJ11: =DR11/($CC11/1000) -> 6.2177865 | BK11: =DS11/($CC11/1000) -> 6.1454062 | BL11: =DT11/($CC11/1000) -> 6.2242379 | BM11: =DU11/($CC11/1000) -> 6.3587096 | BN11: =DV11/($CC11/1000) -> 6.2840702 | BO11: =DW11/($CC11/1000) -> 6.8345806 | BP11: =DX11/($CC11/1000) -> 6.8686768 | BQ11: =DY11/($CC11/1000) -> 0 | BS11: =EA11/($CC11/1000) -> 1.417527 | BT11: =EB11/($CC11/1000) -> 1.365317 | BU11: =EC11/($CC11/1000) -> 1.3863652 | BV11: =ED11/($CC11/1000) -> 1.388407 | BW11: =EE11/($CC11/1000) -> 1.4004186 | BX11: =EF11/($CC11/1000) -> 1.5889222 | BY11: =EG11/($CC11/1000) -> 1.5894991 | BZ11: =EH11/($CC11/1000) -> 0 | CB11: =+CB10+100 -> 202601 | CC11: =VLOOKUP(CB11,DataQ!$C$7:$E$358,3,FALSE) -> 70023.94 | CE11: =Y11 -> 25-26 | CF11: =100*(CZ11/CZ$11) -> 100 | CG11: =100*(DA11/DA$11) -> 100 | CH11: =100*(DB11/DB$11) -> 100 | CI11: =100*(DC11/DC$11) -> 100 | CJ11: =100*(DD11/DD$11) -> 100 | CK11: =100*(DE11/DE$11) -> 100 | CL11: =100*(DF11/DF$11) -> 100 | CM11: =100*(DG11/DG$11) -> #DIV/0! | CN11: 100 | CP11: =100*(DI11/DI$11) -> 100 | CQ11: =100*(DJ11/DJ$11) -> 100 | CR11: =100*(DK11/DK$11) -> 100 | CS11: =100*(DL11/DL$11) -> 100 | CT11: =100*(DM11/DM$11) -> 100 | CU11: =100*(DN11/DN$11) -> 100 | CV11: =100*(DO11/DO$11) -> 100 | CW11: =100*(DP11/DP$11) -> #DIV/0! | CX11: 100 | CZ11: =100*(DR11/EJ11) -> 435.39391 | DA11: =100*(DS11/EK11) -> 430.32556 | DB11: =100*(DT11/EL11) -> 435.84566 | DC11: =100*(DU11/EM11) -> 445.2619 | DD11: =100*(DV11/EN11) -> 440.03535 | DE11: =100*(DW11/EO11) -> 478.58426 | DF11: =100*(DX11/EP11) -> 480.97181 | DI11: =100*(EA11/EJ11) -> 99.260827 | DJ11: =100*(EB11/EK11) -> 95.604873 | DK11: =100*(EC11/EL11) -> 97.078752 | DL11: =100*(ED11/EM11) -> 97.221725 | DM11: =100*(EE11/EN11) -> 98.062828 | DN11: =100*(EF11/EO11) -> 111.26259 | DO11: =100*(EG11/EP11) -> 111.30299 | DP11: =100*(EH11/EQ11) -> #DIV/0! | DR11: ='[2]Chart Data'!CJ11 -> 435.39391 | DS11: ='[2]Chart Data'!CK11 -> 430.32556 | DT11: ='[2]Chart Data'!CL11 -> 435.84566 | DU11: ='[2]Chart Data'!CM11 -> 445.2619 | DV11: ='[2]Chart Data'!CN11 -> 440.03535 | DW11: ='[2]Chart Data'!CO11 -> 478.58426 | DX11: ='[2]Chart Data'!CP11 -> 480.97181 | EA11: ='[2]Chart Data'!CR11 -> 99.260827 | EB11: ='[2]Chart Data'!CS11 -> 95.604873 | EC11: ='[2]Chart Data'!CT11 -> 97.078752 | ED11: ='[2]Chart Data'!CU11 -> 97.221725 | EE11: ='[2]Chart Data'!CV11 -> 98.062828 | EF11: ='[2]Chart Data'!CW11 -> 111.26259 | EG11: ='[2]Chart Data'!CX11 -> 111.30299 | EJ11: =100*(ES11/ES$11) -> 100 | EK11: =100*(ET11/ET$11) -> 100 | EL11: =100*(EU11/EU$11) -> 100 | EM11: =100*(EV11/EV$11) -> 100 | EN11: =100*(EW11/EW$11) -> 100 | EO11: =100*(EX11/EX$11) -> 100 | EP11: =100*(EY11/EY$11) -> 100 | EQ11: =100*(EZ11/EZ$11) -> #DIV/0! | ES11: ='[2]Chart Data'!DH11 -> 116.78782 | ET11: ='[2]Chart Data'!DI11 -> 117.80967 | EU11: ='[2]Chart Data'!DJ11 -> 118.25344 | EV11: ='[2]Chart Data'!DK11 -> 123.33389 | EW11: ='[2]Chart Data'!DL11 -> 122.48522 | EX11: ='[2]Chart Data'!DM11 -> 125.20811 | EY11: ='[2]Chart Data'!DN11 -> 115.33984 | FB11: 2030 | FC11: =100*(OBR_NOV25_ST1.1!R120/OBR_NOV25_ST1.1!$R$114) -> 109.27672 | FE11: =100*(FG11/$FG$5) -> 108.77203 | FG11: =SUMIF(DataQ!A:A,'Chart Data'!FB11,DataQ!F:F) -> 3027207.1
I12: ='Aggregates (per cent of GDP)'!B64 -> 2007-08 | J12: =LEFT(I12,4) -> 2007 | K12: =-('Aggregates (per cent of GDP)'!M64-'Aggregates (per cent of GDP)'!M63) -> 0.4997265 | P12: =OBR_NOV25_C4.1!B36 -> 1955-56 | Q12: ='Aggregates (per cent of GDP)'!C12 -> 35.96424 | R12: ='Aggregates (per cent of GDP)'!D12 -> 35.770115 | T12: ='[1]CPI Forecast'!A349 -> 45505 | U12: ='[3]CPI Forecast'!F349 -> 2.2162837 | V12: ='[3]CPI Forecast'!D349 -> 2.2162837 | W12: 2 | Y12: 26-27 | Z12: =100*(AR12/AR$10) -> 102.46105 | AA12: =100*(AS12/AS$10) -> 101.3154 | AB12: =100*(AT12/AT$10) -> 101.20752 | AC12: =100*(AU12/AU$10) -> 100.38453 | AD12: =100*(AV12/AV$10) -> 100.82299 | AE12: =100*(AW12/AW$10) -> 103.35738 | AF12: =100*(AX12/AX$10) -> 104.70414 | AG12: =100*(AY12/AY$11) -> #DIV/0! | AI12: =100*(BA12/BA$11) -> 101.13994 | AJ12: =100*(BB12/BB$11) -> 98.700442 | AK12: =100*(BC12/BC$11) -> 98.701289 | AL12: =100*(BD12/BD$11) -> 98.172123 | AM12: =100*(BE12/BE$11) -> 98.053064 | AN12: =100*(BF12/BF$11) -> 102.75911 | AO12: =100*(BG12/BG$11) -> 103.71948 | AP12: =100*(BH12/BH$11) -> #DIV/0! | AR12: =100*(BJ12/EJ12) -> 6.2891148 | AS12: =100*(BK12/EK12) -> 6.1744972 | AT12: =100*(BL12/EL12) -> 6.2628038 | AU12: =100*(BM12/EM12) -> 6.387017 | AV12: =100*(BN12/EN12) -> 6.3148232 | AW12: =100*(BO12/EO12) -> 6.8921145 | AX12: =100*(BP12/EP12) -> 6.9593979 | AY12: =100*(BQ12/EQ12) -> #DIV/0! | BA12: =100*(BS12/EJ12) -> 1.433686 | BB12: =100*(BT12/EK12) -> 1.3475739 | BC12: =100*(BU12/EL12) -> 1.3683603 | BD12: =100*(BV12/EM12) -> 1.3630286 | BE12: =100*(BW12/EN12) -> 1.3731533 | BF12: =100*(BX12/EO12) -> 1.6327623 | BG12: =100*(BY12/EP12) -> 1.6486202 | BH12: =100*(BZ12/EQ12) -> #DIV/0! | BJ12: =DR12/($CC12/1000) -> 6.4149476 | BK12: =DS12/($CC12/1000) -> 6.2497144 | BL12: =DT12/($CC12/1000) -> 6.3378433 | BM12: =DU12/($CC12/1000) -> 6.4907966 | BN12: =DV12/($CC12/1000) -> 6.4249291 | BO12: =DW12/($CC12/1000) -> 7.0278983 | BP12: =DX12/($CC12/1000) -> 7.0746904 | BQ12: =DY12/($CC12/1000) -> 0 | BS12: =EA12/($CC12/1000) -> 1.4623713 | BT12: =EB12/($CC12/1000) -> 1.3639899 | BU12: =EC12/($CC12/1000) -> 1.3847557 | BV12: =ED12/($CC12/1000) -> 1.3851758 | BW12: =EE12/($CC12/1000) -> 1.3970958 | BX12: =EF12/($CC12/1000) -> 1.6649299 | BY12: =EG12/($CC12/1000) -> 1.675932 | BZ12: =EH12/($CC12/1000) -> 0 | CB12: =+CB11+100 -> 202701 | CC12: =VLOOKUP(CB12,DataQ!$C$7:$E$358,3,FALSE) -> 70394.69 | CE12: =Y12 -> 26-27 | CF12: =100*(CZ12/CZ$11) -> 101.6827 | CG12: =100*(DA12/DA$11) -> 101.00535 | CH12: =100*(DB12/DB$11) -> 101.15235 | CI12: =100*(DC12/DC$11) -> 100.97699 | CJ12: =100*(DD12/DD$11) -> 101.02143 | CK12: =100*(DE12/DE$11) -> 101.37572 | CL12: =100*(DF12/DF$11) -> 101.85725 | CM12: =100*(DG12/DG$11) -> #DIV/0! | CN12: 100 | CP12: =100*(DI12/DI$11) -> 101.67544 | CQ12: =100*(DJ12/DJ$11) -> 99.223023 | CR12: =100*(DK12/DK$11) -> 99.223875 | CS12: =100*(DL12/DL$11) -> 98.691906 | CT12: =100*(DM12/DM$11) -> 98.572217 | CU12: =100*(DN12/DN$11) -> 103.30318 | CV12: =100*(DO12/DO$11) -> 104.26863 | CW12: =100*(DP12/DP$11) -> #DIV/0! | CX12: 100 | CZ12: =100*(DR12/EJ12) -> 442.72029 | DA12: =100*(DS12/EK12) -> 434.65182 | DB12: =100*(DT12/EL12) -> 440.86813 | DC12: =100*(DU12/EM12) -> 449.61208 | DD12: =100*(DV12/EN12) -> 444.53002 | DE12: =100*(DW12/EO12) -> 485.16826 | DF12: =100*(DX12/EP12) -> 489.90465 | DI12: =100*(EA12/EJ12) -> 100.92388 | DJ12: =100*(EB12/EK12) -> 94.862045 | DK12: =100*(EC12/EL12) -> 96.3253 | DL12: =100*(ED12/EM12) -> 95.949974 | DM12: =100*(EE12/EN12) -> 96.662704 | DN12: =100*(EF12/EO12) -> 114.9378 | DO12: =100*(EG12/EP12) -> 116.05411 | DP12: =100*(EH12/EQ12) -> #DIV/0! | DR12: ='[2]Chart Data'!CJ12 -> 451.57825 | DS12: ='[2]Chart Data'!CK12 -> 439.94671 | DT12: ='[2]Chart Data'!CL12 -> 446.15051 | DU12: ='[2]Chart Data'!CM12 -> 456.91761 | DV12: ='[2]Chart Data'!CN12 -> 452.28089 | DW12: ='[2]Chart Data'!CO12 -> 494.72672 | DX12: ='[2]Chart Data'!CP12 -> 498.02064 | EA12: ='[2]Chart Data'!CR12 -> 102.94317 | EB12: ='[2]Chart Data'!CS12 -> 96.017646 | EC12: ='[2]Chart Data'!CT12 -> 97.479447 | ED12: ='[2]Chart Data'!CU12 -> 97.50902 | EE12: ='[2]Chart Data'!CV12 -> 98.348124 | EF12: ='[2]Chart Data'!CW12 -> 117.20222 | EG12: ='[2]Chart Data'!CX12 -> 117.97671 | EJ12: =100*(ES12/ES$11) -> 102.0008 | EK12: =100*(ET12/ET$11) -> 101.21819 | EL12: =100*(EU12/EU$11) -> 101.19818 | EM12: =100*(EV12/EV$11) -> 101.62485 | EN12: =100*(EW12/EW$11) -> 101.74361 | EO12: =100*(EX12/EX$11) -> 101.97013 | EP12: =100*(EY12/EY$11) -> 101.65665 | EQ12: =100*(EZ12/EZ$11) -> #DIV/0! | ES12: ='[2]Chart Data'!DH12 -> 119.12452 | ET12: ='[2]Chart Data'!DI12 -> 119.24482 | EU12: ='[2]Chart Data'!DJ12 -> 119.67032 | EV12: ='[2]Chart Data'!DK12 -> 125.33789 | EW12: ='[2]Chart Data'!DL12 -> 124.62088 | EX12: ='[2]Chart Data'!DM12 -> 127.67488 | EY12: ='[2]Chart Data'!DN12 -> 117.25061
A13: % of GDP | B13: =B4 -> 2025-2026 | C13: =C4 -> 2026-2027 | D13: =D4 -> 2027-2028 | E13: =E4 -> 2028-2029 | F13: =F4 -> 2029-2030 | G13: =G4 -> 2030-2031 | I13: ='Aggregates (per cent of GDP)'!B65 -> 2008-09 | J13: =LEFT(I13,4) -> 2008 | K13: =-('Aggregates (per cent of GDP)'!M65-'Aggregates (per cent of GDP)'!M64) -> 3.595098 | P13: =OBR_NOV25_C4.1!B37 -> 1956-57 | Q13: ='Aggregates (per cent of GDP)'!C13 -> 35.569836 | R13: ='Aggregates (per cent of GDP)'!D13 -> 35.957286 | T13: ='[1]CPI Forecast'!A350 -> 45536 | U13: ='[3]CPI Forecast'!F350 -> 1.6803412 | V13: ='[3]CPI Forecast'!D350 -> 1.6803412 | W13: 2 | Y13: 27-28 | AA13: =100*(AS13/AS$10) -> 101.97263 | AB13: =100*(AT13/AT$10) -> 101.97889 | AC13: =100*(AU13/AU$10) -> 101.01745 | AD13: =100*(AV13/AV$10) -> 101.44433 | AE13: =100*(AW13/AW$10) -> 104.27074 | AF13: =100*(AX13/AX$10) -> 105.31285 | AG13: =100*(AY13/AY$11) -> #DIV/0! | AJ13: =100*(BB13/BB$11) -> 96.730307 | AK13: =100*(BC13/BC$11) -> 96.833521 | AL13: =100*(BD13/BD$11) -> 96.140004 | AM13: =100*(BE13/BE$11) -> 95.835608 | AN13: =100*(BF13/BF$11) -> 103.32073 | AO13: =100*(BG13/BG$11) -> 106.44075 | AP13: =100*(BH13/BH$11) -> #DIV/0! | AS13: =100*(BK13/EK13) -> 6.2145509 | AT13: =100*(BL13/EL13) -> 6.3105369 | AU13: =100*(BM13/EM13) -> 6.4272865 | AV13: =100*(BN13/EN13) -> 6.3537395 | AW13: =100*(BO13/EO13) -> 6.9530199 | AX13: =100*(BP13/EP13) -> 6.9998576 | AY13: =100*(BQ13/EQ13) -> #DIV/0! | BB13: =100*(BT13/EK13) -> 1.3206753 | BC13: =100*(BU13/EL13) -> 1.3424662 | BD13: =100*(BV13/EM13) -> 1.3348145 | BE13: =100*(BW13/EN13) -> 1.3420997 | BF13: =100*(BX13/EO13) -> 1.641686 | BG13: =100*(BY13/EP13) -> 1.6918748 | BH13: =100*(BZ13/EQ13) -> #DIV/0! | BK13: =DS13/($CC13/1000) -> 6.4032493 | BL13: =DT13/($CC13/1000) -> 6.491662 | BM13: =DU13/($CC13/1000) -> 6.6476064 | BN13: =DV13/($CC13/1000) -> 6.5855903 | BO13: =DW13/($CC13/1000) -> 7.2287978 | BP13: =DX13/($CC13/1000) -> 7.2607503 | BQ13: =DY13/($CC13/1000) -> 0 | BT13: =EB13/($CC13/1000) -> 1.3607762 | BU13: =EC13/($CC13/1000) -> 1.3809977 | BV13: =ED13/($CC13/1000) -> 1.3805704 | BW13: =EE13/($CC13/1000) -> 1.3910735 | BX13: =EF13/($CC13/1000) -> 1.7068003 | BY13: =EG13/($CC13/1000) -> 1.754933 | BZ13: =EH13/($CC13/1000) -> 0 | CB13: =+CB12+100 -> 202801 | CC13: =VLOOKUP(CB13,DataQ!$C$7:$E$358,3,FALSE) -> 70693.4 | CE13: =Y13 -> 27-28 | CG13: =100*(DA13/DA$11) -> 102.09195 | CH13: =100*(DB13/DB$11) -> 102.3558 | CI13: =100*(DC13/DC$11) -> 102.04483 | CJ13: =100*(DD13/DD$11) -> 102.07531 | CK13: =100*(DE13/DE$11) -> 102.70555 | CL13: =100*(DF13/DF$11) -> 102.88414 | CM13: =100*(DG13/DG$11) -> #DIV/0! | CN13: 100 | CQ13: =100*(DJ13/DJ$11) -> 97.655092 | CR13: =100*(DK13/DK$11) -> 97.759292 | CS13: =100*(DL13/DL$11) -> 97.059146 | CT13: =100*(DM13/DM$11) -> 96.751839 | CU13: =100*(DN13/DN$11) -> 104.30852 | CV13: =100*(DO13/DO$11) -> 107.45837 | CW13: =100*(DP13/DP$11) -> #DIV/0! | CX13: 100 | DA13: =100*(DS13/EK13) -> 439.32773 | DB13: =100*(DT13/EL13) -> 446.11331 | DC13: =100*(DU13/EM13) -> 454.36674 | DD13: =100*(DV13/EN13) -> 449.16745 | DE13: =100*(DW13/EO13) -> 491.53262 | DF13: =100*(DX13/EP13) -> 494.84373 | DJ13: =100*(EB13/EK13) -> 93.363026 | DK13: =100*(EC13/EL13) -> 94.903502 | DL13: =100*(ED13/EM13) -> 94.362576 | DM13: =100*(EE13/EN13) -> 94.87759 | DN13: =100*(EF13/EO13) -> 116.05637 | DO13: =100*(EG13/EP13) -> 119.60439 | DP13: =100*(EH13/EQ13) -> #DIV/0! | DS13: ='[2]Chart Data'!CK13 -> 452.66747 | DT13: ='[2]Chart Data'!CL13 -> 458.91766 | DU13: ='[2]Chart Data'!CM13 -> 469.9419 | DV13: ='[2]Chart Data'!CN13 -> 465.55777 | DW13: ='[2]Chart Data'!CO13 -> 511.0283 | DX13: ='[2]Chart Data'!CP13 -> 513.28713 | EB13: ='[2]Chart Data'!CS13 -> 96.197899 | EC13: ='[2]Chart Data'!CT13 -> 97.627423 | ED13: ='[2]Chart Data'!CU13 -> 97.597216 | EE13: ='[2]Chart Data'!CV13 -> 98.339717 | EF13: ='[2]Chart Data'!CW13 -> 120.65952 | EG13: ='[2]Chart Data'!CX13 -> 124.06218 | EK13: =100*(ET13/ET$11) -> 103.0364 | EL13: =100*(EU13/EU$11) -> 102.8702 | EM13: =100*(EV13/EV$11) -> 103.42788 | EN13: =100*(EW13/EW$11) -> 103.64905 | EO13: =100*(EX13/EX$11) -> 103.9663 | EP13: =100*(EY13/EY$11) -> 103.72711 | EQ13: =100*(EZ13/EZ$11) -> #DIV/0! | ET13: ='[2]Chart Data'!DI13 -> 121.38684 | EU13: ='[2]Chart Data'!DJ13 -> 121.64755 | EV13: ='[2]Chart Data'!DK13 -> 127.56164 | EW13: ='[2]Chart Data'!DL13 -> 126.95476 | EX13: ='[2]Chart Data'!DM13 -> 130.17424 | EY13: ='[2]Chart Data'!DN13 -> 119.63869
A14: Tax | B14: =-100*((B5/1000)/B$11) -> -0.0022942365 | C14: =-100*((C5/1000)/C$11) -> 0.060188711 | D14: =-100*((D5/1000)/D$11) -> -0.088174691 | E14: =-100*((E5/1000)/E$11) -> -0.31665995 | F14: =-100*((F5/1000)/F$11) -> -0.66065481 | G14: =-100*((G5/1000)/G$11) -> -0.73443124 | I14: ='Aggregates (per cent of GDP)'!B66 -> 2009-10 | J14: =LEFT(I14,4) -> 2009 | K14: =-('Aggregates (per cent of GDP)'!M66-'Aggregates (per cent of GDP)'!M65) -> 1.40712 | P14: =OBR_NOV25_C4.1!B38 -> 1957-58 | Q14: ='Aggregates (per cent of GDP)'!C14 -> 35.163468 | R14: ='Aggregates (per cent of GDP)'!D14 -> 35.190121 | T14: ='[1]CPI Forecast'!A351 -> 45566 | U14: ='[3]CPI Forecast'!F351 -> 2.2809915 | V14: ='[3]CPI Forecast'!D351 -> 2.2809915 | W14: 2 | Y14: 28-29 | AC14: =100*(AU14/AU$10) -> 101.65135 | AD14: =100*(AV14/AV$10) -> 102.03401 | AE14: =100*(AW14/AW$10) -> 105.20128 | AF14: =100*(AX14/AX$10) -> 105.9112 | AG14: =100*(AY14/AY$11) -> #DIV/0! | AL14: =100*(BD14/BD$11) -> 93.771106 | AM14: =100*(BE14/BE$11) -> 92.721614 | AN14: =100*(BF14/BF$11) -> 101.58432 | AO14: =100*(BG14/BG$11) -> 105.07532 | AP14: =100*(BH14/BH$11) -> #DIV/0! | AU14: =100*(BM14/EM14) -> 6.467619 | AV14: =100*(BN14/EN14) -> 6.3906724 | AW14: =100*(BO14/EO14) -> 7.0150702 | AX14: =100*(BP14/EP14) -> 7.0396282 | AY14: =100*(BQ14/EQ14) -> #DIV/0! | BD14: =100*(BV14/EM14) -> 1.3019246 | BE14: =100*(BW14/EN14) -> 1.2984907 | BF14: =100*(BX14/EO14) -> 1.6140958 | BG14: =100*(BY14/EP14) -> 1.6701712 | BH14: =100*(BZ14/EQ14) -> #DIV/0! | BM14: =DU14/($CC14/1000) -> 6.8151302 | BN14: =DV14/($CC14/1000) -> 6.7518911 | BO14: =DW14/($CC14/1000) -> 7.4370465 | BP14: =DX14/($CC14/1000) -> 7.4441901 | BQ14: =DY14/($CC14/1000) -> 0 | BV14: =ED14/($CC14/1000) -> 1.3718782 | BW14: =EE14/($CC14/1000) -> 1.3718851 | BX14: =EF14/($CC14/1000) -> 1.7111883 | BY14: =EG14/($CC14/1000) -> 1.7661547 | BZ14: =EH14/($CC14/1000) -> 0 | CB14: =+CB13+100 -> 202901 | CC14: =VLOOKUP(CB14,DataQ!$C$7:$E$358,3,FALSE) -> 70966.62 | CE14: =Y14 -> 28-29 | CI14: =100*(DC14/DC$11) -> 103.08204 | CJ14: =100*(DD14/DD$11) -> 103.06545 | CK14: =100*(DE14/DE$11) -> 104.0226 | CL14: =100*(DF14/DF$11) -> 103.86859 | CM14: =100*(DG14/DG$11) -> #DIV/0! | CN14: 100 | CS14: =100*(DL14/DL$11) -> 95.033476 | CT14: =100*(DM14/DM$11) -> 93.969856 | CU14: =100*(DN14/DN$11) -> 102.95188 | CV14: =100*(DO14/DO$11) -> 106.48987 | CW14: =100*(DP14/DP$11) -> #DIV/0! | CX14: 100 | DC14: =100*(DU14/EM14) -> 458.98506 | DD14: =100*(DV14/EN14) -> 453.52442 | DE14: =100*(DW14/EO14) -> 497.83582 | DF14: =100*(DX14/EP14) -> 499.57862 | DL14: =100*(ED14/EM14) -> 92.393186 | DM14: =100*(EE14/EN14) -> 92.149498 | DN14: =100*(EF14/EO14) -> 114.54693 | DO14: =100*(EG14/EP14) -> 118.52641 | DP14: =100*(EH14/EQ14) -> #DIV/0! | DU14: ='[2]Chart Data'!CM14 -> 483.64675 | DV14: ='[2]Chart Data'!CN14 -> 479.15889 | DW14: ='[2]Chart Data'!CO14 -> 527.78205 | DX14: ='[2]Chart Data'!CP14 -> 528.28901 | ED14: ='[2]Chart Data'!CU14 -> 97.357557 | EE14: ='[2]Chart Data'!CV14 -> 97.358047 | EF14: ='[2]Chart Data'!CW14 -> 121.43725 | EG14: ='[2]Chart Data'!CX14 -> 125.33803 | EM14: =100*(EV14/EV$11) -> 105.37309 | EN14: =100*(EW14/EW$11) -> 105.65228 | EO14: =100*(EX14/EX$11) -> 106.01528 | EP14: =100*(EY14/EY$11) -> 105.74692 | EQ14: =100*(EZ14/EZ$11) -> #DIV/0! | EV14: ='[2]Chart Data'!DK14 -> 129.96074 | EW14: ='[2]Chart Data'!DL14 -> 129.40843 | EX14: ='[2]Chart Data'!DM14 -> 132.73973 | EY14: ='[2]Chart Data'!DN14 -> 121.96833
A15: Current spending | B15: =-100*((B6/1000)/B$11) -> 0.13765419 | C15: =-100*((C6/1000)/C$11) -> 0.23411987 | D15: =-100*((D6/1000)/D$11) -> 0.31517113 | E15: =-100*((E6/1000)/E$11) -> 0.21558256 | F15: =-100*((F6/1000)/F$11) -> 0.074626882 | G15: =-100*((G6/1000)/G$11) -> 0.069873642 | I15: ='Aggregates (per cent of GDP)'!B67 -> 2010-11 | J15: =LEFT(I15,4) -> 2010 | K15: =-('Aggregates (per cent of GDP)'!M67-'Aggregates (per cent of GDP)'!M66) -> -2.1274984 | P15: =OBR_NOV25_C4.1!B39 -> 1958-59 | Q15: ='Aggregates (per cent of GDP)'!C15 -> 35.644201 | R15: ='Aggregates (per cent of GDP)'!D15 -> 35.948413 | T15: ='[1]CPI Forecast'!A352 -> 45597 | U15: ='[3]CPI Forecast'!F352 -> 2.6221267 | V15: ='[3]CPI Forecast'!D352 -> 2.6221267 | W15: 2 | Y15: 29-30 | AE15: =100*(AW15/AW$10) -> 106.25128 | AF15: =100*(AX15/AX$10) -> 106.59255 | AG15: =100*(AY15/AY$11) -> #DIV/0! | AN15: =100*(BF15/BF$11) -> 100.1593 | AO15: =100*(BG15/BG$11) -> 104.05386 | AP15: =100*(BH15/BH$11) -> #DIV/0! | AW15: =100*(BO15/EO15) -> 7.0850871 | AX15: =100*(BP15/EP15) -> 7.0849154 | AY15: =100*(BQ15/EQ15) -> #DIV/0! | BF15: =100*(BX15/EO15) -> 1.5914533 | BG15: =100*(BY15/EP15) -> 1.6539352 | BH15: =100*(BZ15/EQ15) -> #DIV/0! | BO15: =DW15/($CC15/1000) -> 7.6594427 | BP15: =DX15/($CC15/1000) -> 7.6330148 | BQ15: =DY15/($CC15/1000) -> 0 | BX15: =EF15/($CC15/1000) -> 1.7204651 | BY15: =EG15/($CC15/1000) -> 1.781886 | BZ15: =EH15/($CC15/1000) -> 0 | CB15: =+CB14+100 -> 203001 | CC15: =VLOOKUP(CB15,DataQ!$C$7:$E$358,3,FALSE) -> 71232.75 | CE15: =Y15 -> 29-30 | CK15: =100*(DE15/DE$11) -> 105.45483 | CL15: =100*(DF15/DF$11) -> 104.92881 | CM15: =100*(DG15/DG$11) -> #DIV/0! | CN15: 100 | CU15: =100*(DN15/DN$11) -> 101.88833 | CV15: =100*(DO15/DO$11) -> 105.85012 | CW15: =100*(DP15/DP$11) -> #DIV/0! | CX15: 100 | DE15: =100*(DW15/EO15) -> 504.69023 | DF15: =100*(DX15/EP15) -> 504.67801 | DN15: =100*(EF15/EO15) -> 113.36359 | DO15: =100*(EG15/EP15) -> 117.81435 | DP15: =100*(EH15/EQ15) -> #DIV/0! | DW15: ='[2]Chart Data'!CO15 -> 545.60317 | DX15: ='[2]Chart Data'!CP15 -> 543.72063 | EF15: ='[2]Chart Data'!CW15 -> 122.55346 | EG15: ='[2]Chart Data'!CX15 -> 126.92864 | EO15: =100*(EX15/EX$11) -> 108.10654 | EP15: =100*(EY15/EY$11) -> 107.73615 | EQ15: =100*(EZ15/EZ$11) -> #DIV/0! | EX15: ='[2]Chart Data'!DM15 -> 135.35816 | EY15: ='[2]Chart Data'!DN15 -> 124.2627
A16: Total | B16: =-100*((B7/1000)/B$11) -> 0.13535995 | C16: =-100*((C7/1000)/C$11) -> 0.29430858 | D16: =-100*((D7/1000)/D$11) -> 0.22699644 | E16: =-100*((E7/1000)/E$11) -> -0.10107738 | F16: =-100*((F7/1000)/F$11) -> -0.58602793 | G16: =-100*((G7/1000)/G$11) -> -0.6645576 | I16: ='Aggregates (per cent of GDP)'!B68 -> 2011-12 | J16: =LEFT(I16,4) -> 2011 | K16: =-('Aggregates (per cent of GDP)'!M68-'Aggregates (per cent of GDP)'!M67) -> -1.3607901 | P16: =OBR_NOV25_C4.1!B40 -> 1959-60 | Q16: ='Aggregates (per cent of GDP)'!C16 -> 33.652223 | R16: ='Aggregates (per cent of GDP)'!D16 -> 35.939384 | T16: ='[1]CPI Forecast'!A353 -> 45627 | U16: ='[3]CPI Forecast'!F353 -> 2.5029869 | V16: ='[3]CPI Forecast'!D353 -> 2.5029869 | W16: 2 | Y16: 30-31 | AG16: =100*(AY16/AY$11) -> #DIV/0! | AP16: =100*(BH16/BH$11) -> #DIV/0! | AY16: =100*(BQ16/EQ16) -> #DIV/0! | BH16: =100*(BZ16/EQ16) -> #DIV/0! | BQ16: =DY16/($CC16/1000) -> 0 | BZ16: =EH16/($CC16/1000) -> 0 | CB16: =+CB15+100 -> 203101 | CC16: =VLOOKUP(CB16,DataQ!$C$7:$E$358,3,FALSE) -> 71491.27 | CE16: =Y16 -> 30-31 | CM16: =100*(DG16/DG$11) -> #DIV/0! | CN16: 100 | CW16: =100*(DP16/DP$11) -> #DIV/0! | CX16: 100 | DP16: =100*(EH16/EQ16) -> #DIV/0! | EQ16: =100*(EZ16/EZ$11) -> #DIV/0!
I17: ='Aggregates (per cent of GDP)'!B69 -> 2012-13 | J17: =LEFT(I17,4) -> 2012 | K17: =-('Aggregates (per cent of GDP)'!M69-'Aggregates (per cent of GDP)'!M68) -> 0.35827152 | P17: =OBR_NOV25_C4.1!B41 -> 1960-61 | Q17: ='Aggregates (per cent of GDP)'!C17 -> 33.452184 | R17: ='Aggregates (per cent of GDP)'!D17 -> 35.936796 | T17: ='[1]CPI Forecast'!A354 -> 45658 | U17: ='[3]CPI Forecast'!F354 -> 2.9829405 | V17: ='[3]CPI Forecast'!D354 -> 2.9829405 | W17: 2
I18: ='Aggregates (per cent of GDP)'!B70 -> 2013-14 | J18: =LEFT(I18,4) -> 2013 | K18: =-('Aggregates (per cent of GDP)'!M70-'Aggregates (per cent of GDP)'!M69) -> -0.959001 | P18: =OBR_NOV25_C4.1!B42 -> 1961-62 | Q18: ='Aggregates (per cent of GDP)'!C18 -> 35.456709 | R18: ='Aggregates (per cent of GDP)'!D18 -> 37.623903 | T18: ='[1]CPI Forecast'!A355 -> 45689 | U18: ='[3]CPI Forecast'!F355 -> 2.8361877 | V18: ='[3]CPI Forecast'!D355 -> 2.8361877 | W18: 2
I19: ='Aggregates (per cent of GDP)'!B71 -> 2014-15 | J19: =LEFT(I19,4) -> 2014 | K19: =-('Aggregates (per cent of GDP)'!M71-'Aggregates (per cent of GDP)'!M70) -> 0.36972494 | P19: =OBR_NOV25_C4.1!B43 -> 1962-63 | Q19: ='Aggregates (per cent of GDP)'!C19 -> 35.472044 | R19: ='Aggregates (per cent of GDP)'!D19 -> 37.298435 | T19: ='[1]CPI Forecast'!A356 -> 45717 | U19: ='[3]CPI Forecast'!F356 -> 2.5941517 | V19: ='[3]CPI Forecast'!D356 -> 2.5941517 | W19: 2
I20: ='Aggregates (per cent of GDP)'!B72 -> 2015-16 | J20: =LEFT(I20,4) -> 2015 | K20: =-('Aggregates (per cent of GDP)'!M72-'Aggregates (per cent of GDP)'!M71) -> -0.4917689 | P20: =OBR_NOV25_C4.1!B44 -> 1963-64 | Q20: ='Aggregates (per cent of GDP)'!C20 -> 34.626828 | R20: ='Aggregates (per cent of GDP)'!D20 -> 37.3297 | T20: ='[1]CPI Forecast'!A357 -> 45748 | U20: ='[3]CPI Forecast'!F357 -> 3.5273316 | V20: ='[3]CPI Forecast'!D357 -> 3.5273316 | W20: 2
I21: ='Aggregates (per cent of GDP)'!B73 -> 2016-17 | J21: =LEFT(I21,4) -> 2016 | K21: =-('Aggregates (per cent of GDP)'!M73-'Aggregates (per cent of GDP)'!M72) -> -1.4453522 | P21: =OBR_NOV25_C4.1!B45 -> 1964-65 | Q21: ='Aggregates (per cent of GDP)'!C21 -> 35.156609 | R21: ='Aggregates (per cent of GDP)'!D21 -> 37.023864 | T21: ='[1]CPI Forecast'!A358 -> 45778 | U21: ='[3]CPI Forecast'!F358 -> 3.3579498 | V21: ='[3]CPI Forecast'!D358 -> 3.3579498 | W21: 2
I22: ='Aggregates (per cent of GDP)'!B74 -> 2017-18 | J22: =LEFT(I22,4) -> 2017 | K22: =-('Aggregates (per cent of GDP)'!M74-'Aggregates (per cent of GDP)'!M73) -> 0.086068042 | P22: =OBR_NOV25_C4.1!B46 -> 1965-66 | Q22: ='Aggregates (per cent of GDP)'!C22 -> 36.94927 | R22: ='Aggregates (per cent of GDP)'!D22 -> 38.473034 | T22: ='[1]CPI Forecast'!A359 -> 45809 | U22: ='[3]CPI Forecast'!F359 -> 3.5764899 | V22: ='[3]CPI Forecast'!D359 -> 3.5764899 | W22: 2
I23: ='Aggregates (per cent of GDP)'!B75 -> 2018-19 | J23: =LEFT(I23,4) -> 2018 | K23: =-('Aggregates (per cent of GDP)'!M75-'Aggregates (per cent of GDP)'!M74) -> -0.2307328 | P23: =OBR_NOV25_C4.1!B47 -> 1966-67 | Q23: ='Aggregates (per cent of GDP)'!C23 -> 37.628247 | R23: ='Aggregates (per cent of GDP)'!D23 -> 40.023022 | T23: ='[1]CPI Forecast'!A360 -> 45839 | U23: ='[3]CPI Forecast'!F360 -> 3.8294852 | V23: ='[3]CPI Forecast'!D360 -> 3.8294852 | W23: 2
I24: ='Aggregates (per cent of GDP)'!B76 -> 2019-20 | J24: =LEFT(I24,4) -> 2019 | K24: =-('Aggregates (per cent of GDP)'!M76-'Aggregates (per cent of GDP)'!M75) -> 0.92709237 | P24: =OBR_NOV25_C4.1!B48 -> 1967-68 | Q24: ='Aggregates (per cent of GDP)'!C24 -> 39.075729 | R24: ='Aggregates (per cent of GDP)'!D24 -> 42.925682 | T24: ='[1]CPI Forecast'!A361 -> 45870 | U24: ='[3]CPI Forecast'!F361 -> 3.7882569 | V24: ='[3]CPI Forecast'!D361 -> 3.7882569 | W24: 2
I25: ='Aggregates (per cent of GDP)'!B77 -> 2020-21 | J25: =LEFT(I25,4) -> 2020 | K25: =-('Aggregates (per cent of GDP)'!M77-'Aggregates (per cent of GDP)'!M76) -> 12.139105 | P25: =OBR_NOV25_C4.1!B49 -> 1968-69 | Q25: ='Aggregates (per cent of GDP)'!C25 -> 40.793946 | R25: ='Aggregates (per cent of GDP)'!D25 -> 41.371128 | T25: ='[1]CPI Forecast'!A362 -> 45901 | U25: ='[3]CPI Forecast'!F362 -> 3.7827367 | V25: ='[3]CPI Forecast'!D362 -> 3.7827367 | W25: 2
I26: ='Aggregates (per cent of GDP)'!B78 -> 2021-22 | J26: =LEFT(I26,4) -> 2021 | K26: =-('Aggregates (per cent of GDP)'!M78-'Aggregates (per cent of GDP)'!M77) -> -9.8878906 | P26: =OBR_NOV25_C4.1!B50 -> 1969-70 | Q26: ='Aggregates (per cent of GDP)'!C26 -> 41.841671 | R26: ='Aggregates (per cent of GDP)'!D26 -> 40.127025 | T26: ='[1]CPI Forecast'!A363 -> 45931 | U26: ='[3]CPI Forecast'!F363 -> 3.5588638 | V26: ='[3]CPI Forecast'!D363 -> 3.5588638 | W26: 2
I27: ='Aggregates (per cent of GDP)'!B79 -> 2022-23 | J27: =LEFT(I27,4) -> 2022 | K27: =-('Aggregates (per cent of GDP)'!M79-'Aggregates (per cent of GDP)'!M78) -> -1.7832895 | P27: =OBR_NOV25_C4.1!B51 -> 1970-71 | Q27: ='Aggregates (per cent of GDP)'!C27 -> 40.037063 | R27: ='Aggregates (per cent of GDP)'!D27 -> 39.477649 | T27: ='[1]CPI Forecast'!A364 -> 45962 | U27: ='[3]CPI Forecast'!F364 -> 3.6037818 | V27: ='[3]CPI Forecast'!D364 -> 3.6111748 | W27: 2
I28: ='Aggregates (per cent of GDP)'!B80 -> 2023-24 | J28: =LEFT(I28,4) -> 2023 | K28: =-('Aggregates (per cent of GDP)'!M80-'Aggregates (per cent of GDP)'!M79) -> 0.023723999 | P28: =OBR_NOV25_C4.1!B52 -> 1971-72 | Q28: ='Aggregates (per cent of GDP)'!C28 -> 38.364478 | R28: ='Aggregates (per cent of GDP)'!D28 -> 39.346039 | T28: ='[1]CPI Forecast'!A365 -> 45992 | U28: ='[3]CPI Forecast'!F365 -> 3.7805448 | V28: ='[3]CPI Forecast'!D365 -> 3.767209 | W28: 2
... I35: ='Aggregates (per cent of GDP)'!B87 -> 2030-31 | J35: =LEFT(I35,4) -> 2030 | K35: =-('Aggregates (per cent of GDP)'!M87-'Aggregates (per cent of GDP)'!M86) -> -0.044477868 | P35: =OBR_NOV25_C4.1!B59 -> 1978-79 | Q35: ='Aggregates (per cent of GDP)'!C35 -> 36.905288 | R35: ='Aggregates (per cent of GDP)'!D35 -> 41.420706 | T35: ='[1]CPI Forecast'!A372 -> 46204 | U35: ='[3]CPI Forecast'!F372 -> 2.533463 | V35: ='[3]CPI Forecast'!D372 -> 2.4565987 | W35: 2
P36: =OBR_NOV25_C4.1!B60 -> 1979-80 | Q36: ='Aggregates (per cent of GDP)'!C36 -> 37.271293 | R36: ='Aggregates (per cent of GDP)'!D36 -> 40.946091 | T36: ='[1]CPI Forecast'!A373 -> 46235 | U36: ='[3]CPI Forecast'!F373 -> 2.6664216 | V36: ='[3]CPI Forecast'!D373 -> 2.5889284 | W36: 2
P37: =OBR_NOV25_C4.1!B61 -> 1980-81 | Q37: ='Aggregates (per cent of GDP)'!C37 -> 38.491785 | R37: ='Aggregates (per cent of GDP)'!D37 -> 42.803908 | T37: ='[1]CPI Forecast'!A374 -> 46266 | U37: ='[3]CPI Forecast'!F374 -> 2.7912075 | V37: ='[3]CPI Forecast'!D374 -> 2.7384588 | W37: 2
P38: =OBR_NOV25_C4.1!B62 -> 1981-82 | Q38: ='Aggregates (per cent of GDP)'!C38 -> 40.812214 | R38: ='Aggregates (per cent of GDP)'!D38 -> 42.820321 | T38: ='[1]CPI Forecast'!A375 -> 46296 | U38: ='[3]CPI Forecast'!F375 -> 2.6235579 | V38: ='[3]CPI Forecast'!D375 -> 2.5612302 | W38: 2
P39: =OBR_NOV25_C4.1!B63 -> 1982-83 | Q39: ='Aggregates (per cent of GDP)'!C39 -> 40.523009 | R39: ='Aggregates (per cent of GDP)'!D39 -> 43.127992 | T39: ='[1]CPI Forecast'!A376 -> 46327 | U39: ='[3]CPI Forecast'!F376 -> 2.603508 | V39: ='[3]CPI Forecast'!D376 -> 2.5329938 | W39: 2
P40: =OBR_NOV25_C4.1!B64 -> 1983-84 | Q40: ='Aggregates (per cent of GDP)'!C40 -> 39.415409 | R40: ='Aggregates (per cent of GDP)'!D40 -> 42.706138 | T40: ='[1]CPI Forecast'!A377 -> 46357 | U40: ='[3]CPI Forecast'!F377 -> 2.584902 | V40: ='[3]CPI Forecast'!D377 -> 2.5341351 | W40: 2
P41: =OBR_NOV25_C4.1!B65 -> 1984-85 | Q41: ='Aggregates (per cent of GDP)'!C41 -> 39.140924 | R41: ='Aggregates (per cent of GDP)'!D41 -> 42.382304 | T41: ='[1]CPI Forecast'!A378 -> 46388 | U41: ='[3]CPI Forecast'!F378 -> 2.628996 | V41: ='[3]CPI Forecast'!D378 -> 2.497903 | W41: 2
P42: =OBR_NOV25_C4.1!B66 -> 1985-86 | Q42: ='Aggregates (per cent of GDP)'!C42 -> 38.214948 | R42: ='Aggregates (per cent of GDP)'!D42 -> 40.342803 | T42: ='[1]CPI Forecast'!A379 -> 46419 | U42: ='[3]CPI Forecast'!F379 -> 2.631464 | V42: ='[3]CPI Forecast'!D379 -> 2.5012822 | W42: 2
P43: =OBR_NOV25_C4.1!B67 -> 1986-87 | Q43: ='Aggregates (per cent of GDP)'!C43 -> 37.312392 | R43: ='Aggregates (per cent of GDP)'!D43 -> 39.228198 | T43: ='[1]CPI Forecast'!A380 -> 46447 | U43: ='[3]CPI Forecast'!F380 -> 2.6234877 | V43: ='[3]CPI Forecast'!D380 -> 2.4941755 | W43: 2
P44: =OBR_NOV25_C4.1!B68 -> 1987-88 | Q44: ='Aggregates (per cent of GDP)'!C44 -> 36.058787 | R44: ='Aggregates (per cent of GDP)'!D44 -> 37.048195 | T44: ='[1]CPI Forecast'!A381 -> 46478 | U44: ='[3]CPI Forecast'!F381 -> 2.5896898 | V44: ='[3]CPI Forecast'!D381 -> 2.6381523 | W44: 2
P45: =OBR_NOV25_C4.1!B69 -> 1988-89 | Q45: ='Aggregates (per cent of GDP)'!C45 -> 35.4042 | R45: ='Aggregates (per cent of GDP)'!D45 -> 34.437469 | T45: ='[1]CPI Forecast'!A382 -> 46508 | U45: ='[3]CPI Forecast'!F382 -> 2.5814426 | V45: ='[3]CPI Forecast'!D382 -> 2.6302195 | W45: 2
P46: =OBR_NOV25_C4.1!B70 -> 1989-90 | Q46: ='Aggregates (per cent of GDP)'!C46 -> 34.584797 | R46: ='Aggregates (per cent of GDP)'!D46 -> 34.60443 | T46: ='[1]CPI Forecast'!A383 -> 46539 | U46: ='[3]CPI Forecast'!F383 -> 2.5781021 | V46: ='[3]CPI Forecast'!D383 -> 2.6272637 | W46: 2
P47: =OBR_NOV25_C4.1!B71 -> 1990-91 | Q47: ='Aggregates (per cent of GDP)'!C47 -> 33.774932 | R47: ='Aggregates (per cent of GDP)'!D47 -> 34.848356 | T47: ='[1]CPI Forecast'!A384 -> 46569 | U47: ='[3]CPI Forecast'!F384 -> 2.55558 | V47: ='[3]CPI Forecast'!D384 -> 2.6376911 | W47: 2
... P52: =OBR_NOV25_C4.1!B76 -> 1995-96 | Q52: ='Aggregates (per cent of GDP)'!C52 -> 33.141634 | R52: ='Aggregates (per cent of GDP)'!D52 -> 37.243632 | T52: ='[1]CPI Forecast'!A389 -> 46722 | U52: ='[3]CPI Forecast'!F389 -> 2.4603515 | V52: ='[3]CPI Forecast'!D389 -> 2.5498435 | W52: 2
P53: =OBR_NOV25_C4.1!B77 -> 1996-97 | Q53: ='Aggregates (per cent of GDP)'!C53 -> 32.304539 | R53: ='Aggregates (per cent of GDP)'!D53 -> 35.426214
P54: =OBR_NOV25_C4.1!B78 -> 1997-98 | Q54: ='Aggregates (per cent of GDP)'!C54 -> 34.385421 | R54: ='Aggregates (per cent of GDP)'!D54 -> 35.470966
P55: =OBR_NOV25_C4.1!B79 -> 1998-99 | Q55: ='Aggregates (per cent of GDP)'!C55 -> 34.976304 | R55: ='Aggregates (per cent of GDP)'!D55 -> 34.988433
P56: =OBR_NOV25_C4.1!B80 -> 1999-00 | Q56: ='Aggregates (per cent of GDP)'!C56 -> 35.676214 | R56: ='Aggregates (per cent of GDP)'!D56 -> 34.601352
P57: =OBR_NOV25_C4.1!B81 -> 2000-01 | Q57: ='Aggregates (per cent of GDP)'!C57 -> 36.363636 | R57: ='Aggregates (per cent of GDP)'!D57 -> 34.905644
P58: =OBR_NOV25_C4.1!B82 -> 2001-02 | Q58: ='Aggregates (per cent of GDP)'!C58 -> 35.565396 | R58: ='Aggregates (per cent of GDP)'!D58 -> 36.051346
P59: =OBR_NOV25_C4.1!B83 -> 2002-03 | Q59: ='Aggregates (per cent of GDP)'!C59 -> 34.523355 | R59: ='Aggregates (per cent of GDP)'!D59 -> 37.416808
P60: =OBR_NOV25_C4.1!B84 -> 2003-04 | Q60: ='Aggregates (per cent of GDP)'!C60 -> 35.290945 | R60: ='Aggregates (per cent of GDP)'!D60 -> 38.697505
P61: =OBR_NOV25_C4.1!B85 -> 2004-05 | Q61: ='Aggregates (per cent of GDP)'!C61 -> 35.888956 | R61: ='Aggregates (per cent of GDP)'!D61 -> 39.725954
P62: =OBR_NOV25_C4.1!B86 -> 2005-06 | Q62: ='Aggregates (per cent of GDP)'!C62 -> 36.509111 | R62: ='Aggregates (per cent of GDP)'!D62 -> 39.696338
P63: =OBR_NOV25_C4.1!B87 -> 2006-07 | Q63: ='Aggregates (per cent of GDP)'!C63 -> 36.928035 | R63: ='Aggregates (per cent of GDP)'!D63 -> 39.669141
P64: =OBR_NOV25_C4.1!B88 -> 2007-08 | Q64: ='Aggregates (per cent of GDP)'!C64 -> 37.16114 | R64: ='Aggregates (per cent of GDP)'!D64 -> 40.02724
... P80: =OBR_NOV25_C4.1!B104 -> 2023-24 | Q80: ='Aggregates (per cent of GDP)'!C80 -> 39.307805 | R80: ='Aggregates (per cent of GDP)'!D80 -> 44.130674
P81: =OBR_NOV25_C4.1!B105 -> 2024-25 | Q81: {=TRANSPOSE(OBR_NOV25_TA.9!C7:I7)} -> 38.902214 | R81: {=TRANSPOSE(OBR_NOV25_TA.9!C9:I9)} -> 44.008647
P82: =OBR_NOV25_C4.1!B106 -> 2025-26 | Q82: 40.471753 | R82: 45.015764
P83: =OBR_NOV25_C4.1!B107 -> 2026-27 | Q83: 41.193638 | R83: 44.735425
P84: =OBR_NOV25_C4.1!B108 -> 2027-28 | Q84: 41.808726 | R84: 44.813096
P85: =OBR_NOV25_C4.1!B109 -> 2028-29 | Q85: 41.928354 | R85: 44.494142
P86: =OBR_NOV25_C4.1!B110 -> 2029-30 | Q86: 42.33151 | R86: 44.268372
P87: =OBR_NOV25_C4.1!B111 -> 2030-31 | Q87: 42.433163 | R87: 44.284248

Sheet DataQ
E1: =GMW!NF2 -> NOV021L.db | F1: =$E$1 -> NOV021L.db | G1: =$E$1 -> NOV021L.db | H1: =$E$1 -> NOV021L.db
E2: UK | F2: UK | G2: UK | H2: UK
E3: POP | F3: GDP | G3: CPI | H3: WAGEWKLY
E4: GBR | F4: GBR | G4: GBR | H4: GBR
E5: L | F5: L | G5: L | H5: L
A6: CYs | B6: FYs | D6: =D358+5 -> 2329 | E6: {=_xlfn.CONCAT(INDEX(GMW!$A$2:$NF$60,MATCH(1,(GMW!$NE$2:$NE$60=E$3)*(GMW!$ND$2:$ND$60=E$4),0),$D6-1966),"0",(INDEX(GMW!$A$2:$NF$60,MATCH(1,(GMW!$NE$2:$NE$60=E$3)*(GMW!$ND$2:$ND$60=E$4),0),$D6-1965)))} -> 202402 | F6: {=_xlfn.CONCAT(INDEX(GMW!$A$2:$NF$60,MATCH(1,(GMW!$NE$2:$NE$60=F$3)*(GMW!$ND$2:$ND$60=F$4),0),$D6-1966),"0",(INDEX(GMW!$A$2:$NF$60,MATCH(1,(GMW!$NE$2:$NE$60=F$3)*(GMW!$ND$2:$ND$60=F$4),0),$D6-1965)))} -> 202503 | G6: {=_xlfn.CONCAT(INDEX(GMW!$A$2:$NF$60,MATCH(1,(GMW!$NE$2:$NE$60=G$3)*(GMW!$ND$2:$ND$60=G$4),0),$D6-1966),"0",(INDEX(GMW!$A$2:$NF$60,MATCH(1,(GMW!$NE$2:$NE$60=G$3)*(GMW!$ND$2:$ND$60=G$4),0),$D6-1965)))} -> 202503 | H6: {=_xlfn.CONCAT(INDEX(GMW!$A$2:$NF$60,MATCH(1,(GMW!$NE$2:$NE$60=H$3)*(GMW!$ND$2:$ND$60=H$4),0),$D6-1966),"0",(INDEX(GMW!$A$2:$NF$60,MATCH(1,(GMW!$NE$2:$NE$60=H$3)*(GMW!$ND$2:$ND$60=H$4),0),$D6-1965)))} -> 202503
A7: 1973 | C7: 197301 | D7: 1973 | E7: {=INDEX(GMW!$A$2:$NF$60,MATCH(1,(GMW!$NE$2:$NE$60=E$3)*(GMW!$ND$2:$ND$60=E$4),0),$D7-1966)} -> 56191.5 | F7: {=INDEX(GMW!$A$2:$NF$60,MATCH(1,(GMW!$NE$2:$NE$60=F$3)*(GMW!$ND$2:$ND$60=F$4),0),$D7-1966)} -> 267015 | G7: {=INDEX(GMW!$A$2:$NF$60,MATCH(1,(GMW!$NE$2:$NE$60=G$3)*(GMW!$ND$2:$ND$60=G$4),0),$D7-1966)} -> 11.88749 | H7: {=INDEX(GMW!$A$2:$NF$60,MATCH(1,(GMW!$NE$2:$NE$60=H$3)*(GMW!$ND$2:$ND$60=H$4),0),$D7-1966)} -> 14.85115
A8: 1973 | B8: 1973 | C8: =+C7+1 -> 197302 | D8: =+D7+1 -> 1974 | E8: {=INDEX(GMW!$A$2:$NF$60,MATCH(1,(GMW!$NE$2:$NE$60=E$3)*(GMW!$ND$2:$ND$60=E$4),0),$D8-1966)} -> 56223 | F8: {=INDEX(GMW!$A$2:$NF$60,MATCH(1,(GMW!$NE$2:$NE$60=F$3)*(GMW!$ND$2:$ND$60=F$4),0),$D8-1966)} -> 267521 | G8: {=INDEX(GMW!$A$2:$NF$60,MATCH(1,(GMW!$NE$2:$NE$60=G$3)*(GMW!$ND$2:$ND$60=G$4),0),$D8-1966)} -> 12.3046 | H8: {=INDEX(GMW!$A$2:$NF$60,MATCH(1,(GMW!$NE$2:$NE$60=H$3)*(GMW!$ND$2:$ND$60=H$4),0),$D8-1966)} -> 15.59743
A9: 1973 | B9: 1973 | C9: =+C8+1 -> 197303 | D9: =+D8+1 -> 1975 | E9: {=INDEX(GMW!$A$2:$NF$60,MATCH(1,(GMW!$NE$2:$NE$60=E$3)*(GMW!$ND$2:$ND$60=E$4),0),$D9-1966)} -> 56226.25 | F9: {=INDEX(GMW!$A$2:$NF$60,MATCH(1,(GMW!$NE$2:$NE$60=F$3)*(GMW!$ND$2:$ND$60=F$4),0),$D9-1966)} -> 265025 | G9: {=INDEX(GMW!$A$2:$NF$60,MATCH(1,(GMW!$NE$2:$NE$60=G$3)*(GMW!$ND$2:$ND$60=G$4),0),$D9-1966)} -> 12.51315 | H9: {=INDEX(GMW!$A$2:$NF$60,MATCH(1,(GMW!$NE$2:$NE$60=H$3)*(GMW!$ND$2:$ND$60=H$4),0),$D9-1966)} -> 16.40707
A10: 1973 | B10: 1973 | C10: =+C9+1 -> 197304 | D10: =+D9+1 -> 1976 | E10: {=INDEX(GMW!$A$2:$NF$60,MATCH(1,(GMW!$NE$2:$NE$60=E$3)*(GMW!$ND$2:$ND$60=E$4),0),$D10-1966)} -> 56229.5 | F10: {=INDEX(GMW!$A$2:$NF$60,MATCH(1,(GMW!$NE$2:$NE$60=F$3)*(GMW!$ND$2:$ND$60=F$4),0),$D10-1966)} -> 263989 | G10: {=INDEX(GMW!$A$2:$NF$60,MATCH(1,(GMW!$NE$2:$NE$60=G$3)*(GMW!$ND$2:$ND$60=G$4),0),$D10-1966)} -> 13.00846 | H10: {=INDEX(GMW!$A$2:$NF$60,MATCH(1,(GMW!$NE$2:$NE$60=H$3)*(GMW!$ND$2:$ND$60=H$4),0),$D10-1966)} -> 16.90761
A11: =+A7+1 -> 1974 | B11: 1973 | C11: =+C7+100 -> 197401 | D11: =+D10+1 -> 1977 | E11: {=INDEX(GMW!$A$2:$NF$60,MATCH(1,(GMW!$NE$2:$NE$60=E$3)*(GMW!$ND$2:$ND$60=E$4),0),$D11-1966)} -> 56232.75 | F11: {=INDEX(GMW!$A$2:$NF$60,MATCH(1,(GMW!$NE$2:$NE$60=F$3)*(GMW!$ND$2:$ND$60=F$4),0),$D11-1966)} -> 256670 | G11: {=INDEX(GMW!$A$2:$NF$60,MATCH(1,(GMW!$NE$2:$NE$60=G$3)*(GMW!$ND$2:$ND$60=G$4),0),$D11-1966)} -> 13.47771 | H11: {=INDEX(GMW!$A$2:$NF$60,MATCH(1,(GMW!$NE$2:$NE$60=H$3)*(GMW!$ND$2:$ND$60=H$4),0),$D11-1966)} -> 16.78086
A12: =+A8+1 -> 1974 | B12: =+B8+1 -> 1974 | C12: =+C8+100 -> 197402 | D12: =+D11+1 -> 1978 | E12: {=INDEX(GMW!$A$2:$NF$60,MATCH(1,(GMW!$NE$2:$NE$60=E$3)*(GMW!$ND$2:$ND$60=E$4),0),$D12-1966)} -> 56236 | F12: {=INDEX(GMW!$A$2:$NF$60,MATCH(1,(GMW!$NE$2:$NE$60=F$3)*(GMW!$ND$2:$ND$60=F$4),0),$D12-1966)} -> 260347 | G12: {=INDEX(GMW!$A$2:$NF$60,MATCH(1,(GMW!$NE$2:$NE$60=G$3)*(GMW!$ND$2:$ND$60=G$4),0),$D12-1966)} -> 14.23371 | H12: {=INDEX(GMW!$A$2:$NF$60,MATCH(1,(GMW!$NE$2:$NE$60=H$3)*(GMW!$ND$2:$ND$60=H$4),0),$D12-1966)} -> 18.25341
A13: =+A9+1 -> 1974 | B13: =+B9+1 -> 1974 | C13: =+C9+100 -> 197403 | D13: =+D12+1 -> 1979 | E13: {=INDEX(GMW!$A$2:$NF$60,MATCH(1,(GMW!$NE$2:$NE$60=E$3)*(GMW!$ND$2:$ND$60=E$4),0),$D13-1966)} -> 56233.5 | F13: {=INDEX(GMW!$A$2:$NF$60,MATCH(1,(GMW!$NE$2:$NE$60=F$3)*(GMW!$ND$2:$ND$60=F$4),0),$D13-1966)} -> 261890 | G13: {=INDEX(GMW!$A$2:$NF$60,MATCH(1,(GMW!$NE$2:$NE$60=G$3)*(GMW!$ND$2:$ND$60=G$4),0),$D13-1966)} -> 14.57261 | H13: {=INDEX(GMW!$A$2:$NF$60,MATCH(1,(GMW!$NE$2:$NE$60=H$3)*(GMW!$ND$2:$ND$60=H$4),0),$D13-1966)} -> 20.2429
A14: =+A10+1 -> 1974 | B14: =+B10+1 -> 1974 | C14: =+C10+100 -> 197404 | D14: =+D13+1 -> 1980 | E14: {=INDEX(GMW!$A$2:$NF$60,MATCH(1,(GMW!$NE$2:$NE$60=E$3)*(GMW!$ND$2:$ND$60=E$4),0),$D14-1966)} -> 56231 | F14: {=INDEX(GMW!$A$2:$NF$60,MATCH(1,(GMW!$NE$2:$NE$60=F$3)*(GMW!$ND$2:$ND$60=F$4),0),$D14-1966)} -> 258066 | G14: {=INDEX(GMW!$A$2:$NF$60,MATCH(1,(GMW!$NE$2:$NE$60=G$3)*(GMW!$ND$2:$ND$60=G$4),0),$D14-1966)} -> 15.2504 | H14: {=INDEX(GMW!$A$2:$NF$60,MATCH(1,(GMW!$NE$2:$NE$60=H$3)*(GMW!$ND$2:$ND$60=H$4),0),$D14-1966)} -> 21.92424
A15: =+A11+1 -> 1975 | B15: =+B11+1 -> 1974 | C15: =+C11+100 -> 197501 | D15: =+D14+1 -> 1981 | E15: {=INDEX(GMW!$A$2:$NF$60,MATCH(1,(GMW!$NE$2:$NE$60=E$3)*(GMW!$ND$2:$ND$60=E$4),0),$D15-1966)} -> 56228.5 | F15: {=INDEX(GMW!$A$2:$NF$60,MATCH(1,(GMW!$NE$2:$NE$60=F$3)*(GMW!$ND$2:$ND$60=F$4),0),$D15-1966)} -> 258116 | G15: {=INDEX(GMW!$A$2:$NF$60,MATCH(1,(GMW!$NE$2:$NE$60=G$3)*(GMW!$ND$2:$ND$60=G$4),0),$D15-1966)} -> 16.05854 | H15: {=INDEX(GMW!$A$2:$NF$60,MATCH(1,(GMW!$NE$2:$NE$60=H$3)*(GMW!$ND$2:$ND$60=H$4),0),$D15-1966)} -> 23.39659
A16: =+A12+1 -> 1975 | B16: =+B12+1 -> 1975 | C16: =+C12+100 -> 197502 | D16: =+D15+1 -> 1982 | E16: {=INDEX(GMW!$A$2:$NF$60,MATCH(1,(GMW!$NE$2:$NE$60=E$3)*(GMW!$ND$2:$ND$60=E$4),0),$D16-1966)} -> 56226 | F16: {=INDEX(GMW!$A$2:$NF$60,MATCH(1,(GMW!$NE$2:$NE$60=F$3)*(GMW!$ND$2:$ND$60=F$4),0),$D16-1966)} -> 253935 | G16: {=INDEX(GMW!$A$2:$NF$60,MATCH(1,(GMW!$NE$2:$NE$60=G$3)*(GMW!$ND$2:$ND$60=G$4),0),$D16-1966)} -> 17.46627 | H16: {=INDEX(GMW!$A$2:$NF$60,MATCH(1,(GMW!$NE$2:$NE$60=H$3)*(GMW!$ND$2:$ND$60=H$4),0),$D16-1966)} -> 24.96419
A17: =+A13+1 -> 1975 | B17: =+B13+1 -> 1975 | C17: =+C13+100 -> 197503 | D17: =+D16+1 -> 1983 | E17: {=INDEX(GMW!$A$2:$NF$60,MATCH(1,(GMW!$NE$2:$NE$60=E$3)*(GMW!$ND$2:$ND$60=E$4),0),$D17-1966)} -> 56223.5 | F17: {=INDEX(GMW!$A$2:$NF$60,MATCH(1,(GMW!$NE$2:$NE$60=F$3)*(GMW!$ND$2:$ND$60=F$4),0),$D17-1966)} -> 253168 | G17: {=INDEX(GMW!$A$2:$NF$60,MATCH(1,(GMW!$NE$2:$NE$60=G$3)*(GMW!$ND$2:$ND$60=G$4),0),$D17-1966)} -> 18.22228 | H17: {=INDEX(GMW!$A$2:$NF$60,MATCH(1,(GMW!$NE$2:$NE$60=H$3)*(GMW!$ND$2:$ND$60=H$4),0),$D17-1966)} -> 27.02938
A18: =+A14+1 -> 1975 | B18: =+B14+1 -> 1975 | C18: =+C14+100 -> 197504 | D18: =+D17+1 -> 1984 | E18: {=INDEX(GMW!$A$2:$NF$60,MATCH(1,(GMW!$NE$2:$NE$60=E$3)*(GMW!$ND$2:$ND$60=E$4),0),$D18-1966)} -> 56221 | F18: {=INDEX(GMW!$A$2:$NF$60,MATCH(1,(GMW!$NE$2:$NE$60=F$3)*(GMW!$ND$2:$ND$60=F$4),0),$D18-1966)} -> 255985 | G18: {=INDEX(GMW!$A$2:$NF$60,MATCH(1,(GMW!$NE$2:$NE$60=G$3)*(GMW!$ND$2:$ND$60=G$4),0),$D18-1966)} -> 18.84793 | H18: {=INDEX(GMW!$A$2:$NF$60,MATCH(1,(GMW!$NE$2:$NE$60=H$3)*(GMW!$ND$2:$ND$60=H$4),0),$D18-1966)} -> 28.37567
A19: =+A15+1 -> 1976 | B19: =+B15+1 -> 1975 | C19: =+C15+100 -> 197601 | D19: =+D18+1 -> 1985 | E19: {=INDEX(GMW!$A$2:$NF$60,MATCH(1,(GMW!$NE$2:$NE$60=E$3)*(GMW!$ND$2:$ND$60=E$4),0),$D19-1966)} -> 56218.5 | F19: {=INDEX(GMW!$A$2:$NF$60,MATCH(1,(GMW!$NE$2:$NE$60=F$3)*(GMW!$ND$2:$ND$60=F$4),0),$D19-1966)} -> 260268 | G19: {=INDEX(GMW!$A$2:$NF$60,MATCH(1,(GMW!$NE$2:$NE$60=G$3)*(GMW!$ND$2:$ND$60=G$4),0),$D19-1966)} -> 19.42145 | H19: {=INDEX(GMW!$A$2:$NF$60,MATCH(1,(GMW!$NE$2:$NE$60=H$3)*(GMW!$ND$2:$ND$60=H$4),0),$D19-1966)} -> 29.35714
A20: =+A16+1 -> 1976 | B20: =+B16+1 -> 1976 | C20: =+C16+100 -> 197602 | D20: =+D19+1 -> 1986 | E20: {=INDEX(GMW!$A$2:$NF$60,MATCH(1,(GMW!$NE$2:$NE$60=E$3)*(GMW!$ND$2:$ND$60=E$4),0),$D20-1966)} -> 56216 | F20: {=INDEX(GMW!$A$2:$NF$60,MATCH(1,(GMW!$NE$2:$NE$60=F$3)*(GMW!$ND$2:$ND$60=F$4),0),$D20-1966)} -> 259911 | G20: {=INDEX(GMW!$A$2:$NF$60,MATCH(1,(GMW!$NE$2:$NE$60=G$3)*(GMW!$ND$2:$ND$60=G$4),0),$D20-1966)} -> 20.12532 | H20: {=INDEX(GMW!$A$2:$NF$60,MATCH(1,(GMW!$NE$2:$NE$60=H$3)*(GMW!$ND$2:$ND$60=H$4),0),$D20-1966)} -> 30.79358
A21: =+A17+1 -> 1976 | B21: =+B17+1 -> 1976 | C21: =+C17+100 -> 197603 | D21: =+D20+1 -> 1987 | E21: {=INDEX(GMW!$A$2:$NF$60,MATCH(1,(GMW!$NE$2:$NE$60=E$3)*(GMW!$ND$2:$ND$60=E$4),0),$D21-1966)} -> 56209.5 | F21: {=INDEX(GMW!$A$2:$NF$60,MATCH(1,(GMW!$NE$2:$NE$60=F$3)*(GMW!$ND$2:$ND$60=F$4),0),$D21-1966)} -> 263132 | G21: {=INDEX(GMW!$A$2:$NF$60,MATCH(1,(GMW!$NE$2:$NE$60=G$3)*(GMW!$ND$2:$ND$60=G$4),0),$D21-1966)} -> 20.59456 | H21: {=INDEX(GMW!$A$2:$NF$60,MATCH(1,(GMW!$NE$2:$NE$60=H$3)*(GMW!$ND$2:$ND$60=H$4),0),$D21-1966)} -> 32.30147
A22: =+A18+1 -> 1976 | B22: =+B18+1 -> 1976 | C22: =+C18+100 -> 197604 | D22: =+D21+1 -> 1988 | E22: {=INDEX(GMW!$A$2:$NF$60,MATCH(1,(GMW!$NE$2:$NE$60=E$3)*(GMW!$ND$2:$ND$60=E$4),0),$D22-1966)} -> 56203 | F22: {=INDEX(GMW!$A$2:$NF$60,MATCH(1,(GMW!$NE$2:$NE$60=F$3)*(GMW!$ND$2:$ND$60=F$4),0),$D22-1966)} -> 268662 | G22: {=INDEX(GMW!$A$2:$NF$60,MATCH(1,(GMW!$NE$2:$NE$60=G$3)*(GMW!$ND$2:$ND$60=G$4),0),$D22-1966)} -> 21.50698 | H22: {=INDEX(GMW!$A$2:$NF$60,MATCH(1,(GMW!$NE$2:$NE$60=H$3)*(GMW!$ND$2:$ND$60=H$4),0),$D22-1966)} -> 33.18535
A23: =+A19+1 -> 1977 | B23: =+B19+1 -> 1976 | C23: =+C19+100 -> 197701 | D23: =+D22+1 -> 1989 | E23: {=INDEX(GMW!$A$2:$NF$60,MATCH(1,(GMW!$NE$2:$NE$60=E$3)*(GMW!$ND$2:$ND$60=E$4),0),$D23-1966)} -> 56196.5 | F23: {=INDEX(GMW!$A$2:$NF$60,MATCH(1,(GMW!$NE$2:$NE$60=F$3)*(GMW!$ND$2:$ND$60=F$4),0),$D23-1966)} -> 268833 | G23: {=INDEX(GMW!$A$2:$NF$60,MATCH(1,(GMW!$NE$2:$NE$60=G$3)*(GMW!$ND$2:$ND$60=G$4),0),$D23-1966)} -> 22.47153 | H23: {=INDEX(GMW!$A$2:$NF$60,MATCH(1,(GMW!$NE$2:$NE$60=H$3)*(GMW!$ND$2:$ND$60=H$4),0),$D23-1966)} -> 33.54049
... A358: =+A354+1 -> 2060 | B358: =+B354+1 -> 2060 | C358: =+C354+100 -> 206004 | D358: =+D357+1 -> 2324 | E358: {=INDEX(GMW!$A$2:$NF$60,MATCH(1,(GMW!$NE$2:$NE$60=E$3)*(GMW!$ND$2:$ND$60=E$4),0),$D358-1966)} -> 76216.81 | F358: {=INDEX(GMW!$A$2:$NF$60,MATCH(1,(GMW!$NE$2:$NE$60=F$3)*(GMW!$ND$2:$ND$60=F$4),0),$D358-1966)} -> 1163001 | G358: {=INDEX(GMW!$A$2:$NF$60,MATCH(1,(GMW!$NE$2:$NE$60=G$3)*(GMW!$ND$2:$ND$60=G$4),0),$D358-1966)} -> 284.1589 | H358: {=INDEX(GMW!$A$2:$NF$60,MATCH(1,(GMW!$NE$2:$NE$60=H$3)*(GMW!$ND$2:$ND$60=H$4),0),$D358-1966)} -> 2135.989

Sheet GMW
A1: Location | B1: Indicator | C1: Scenario | D1: Units | E1: Scale | F1: Measurement | G1: 1973 Q1 | H1: 1973 Q2 | I1: 1973 Q3 | J1: 1973 Q4 | K1: 1974 Q1 | L1: 1974 Q2 | M1: 1974 Q3 | N1: 1974 Q4 | O1: 1975 Q1 | P1: 1975 Q2 | Q1: 1975 Q3 | R1: 1975 Q4 | S1: 1976 Q1 | T1: 1976 Q2 | U1: 1976 Q3 | V1: 1976 Q4 | W1: 1977 Q1 | X1: 1977 Q2 | Y1: 1977 Q3 | Z1: 1977 Q4 | AA1: 1978 Q1 | AB1: 1978 Q2 | AC1: 1978 Q3 | AD1: 1978 Q4 | AE1: 1979 Q1 | AF1: 1979 Q2 | AG1: 1979 Q3 | AH1: 1979 Q4 | AI1: 1980 Q1 | AJ1: 1980 Q2 | AK1: 1980 Q3 | AL1: 1980 Q4 | AM1: 1981 Q1 | AN1: 1981 Q2 | AO1: 1981 Q3 | AP1: 1981 Q4 | AQ1: 1982 Q1 | AR1: 1982 Q2 | AS1: 1982 Q3 | AT1: 1982 Q4 | AU1: 1983 Q1 | AV1: 1983 Q2 | AW1: 1983 Q3 | AX1: 1983 Q4 | AY1: 1984 Q1 | AZ1: 1984 Q2 | BA1: 1984 Q3 | BB1: 1984 Q4 | BC1: 1985 Q1 | BD1: 1985 Q2 | BE1: 1985 Q3 | BF1: 1985 Q4 | BG1: 1986 Q1 | BH1: 1986 Q2 | BI1: 1986 Q3 | BJ1: 1986 Q4 | BK1: 1987 Q1 | BL1: 1987 Q2 | BM1: 1987 Q3 | BN1: 1987 Q4 | BO1: 1988 Q1 | BP1: 1988 Q2 | BQ1: 1988 Q3 | BR1: 1988 Q4 | BS1: 1989 Q1 | BT1: 1989 Q2 | BU1: 1989 Q3 | BV1: 1989 Q4 | BW1: 1990 Q1 | BX1: 1990 Q2 | BY1: 1990 Q3 | BZ1: 1990 Q4 | CA1: 1991 Q1 | CB1: 1991 Q2 | CC1: 1991 Q3 | CD1: 1991 Q4 | CE1: 1992 Q1 | CF1: 1992 Q2 | CG1: 1992 Q3 | CH1: 1992 Q4 | CI1: 1993 Q1 | CJ1: 1993 Q2 | CK1: 1993 Q3 | CL1: 1993 Q4 | CM1: 1994 Q1 | CN1: 1994 Q2 | CO1: 1994 Q3 | CP1: 1994 Q4 | CQ1: 1995 Q1 | CR1: 1995 Q2 | CS1: 1995 Q3 | CT1: 1995 Q4 | CU1: 1996 Q1 | CV1: 1996 Q2 | CW1: 1996 Q3 | CX1: 1996 Q4 | CY1: 1997 Q1 | CZ1: 1997 Q2 | DA1: 1997 Q3 | DB1: 1997 Q4 | DC1: 1998 Q1 | DD1: 1998 Q2 | DE1: 1998 Q3 | DF1: 1998 Q4 | DG1: 1999 Q1 | DH1: 1999 Q2 | DI1: 1999 Q3 | DJ1: 1999 Q4 | DK1: 2000 Q1 | DL1: 2000 Q2 | DM1: 2000 Q3 | DN1: 2000 Q4 | DO1: 2001 Q1 | DP1: 2001 Q2 | DQ1: 2001 Q3 | DR1: 2001 Q4 | DS1: 2002 Q1 | DT1: 2002 Q2 | DU1: 2002 Q3 | DV1: 2002 Q4 | DW1: 2003 Q1 | DX1: 2003 Q2 | DY1: 2003 Q3 | DZ1: 2003 Q4 | EA1: 2004 Q1 | EB1: 2004 Q2 | EC1: 2004 Q3 | ED1: 2004 Q4 | EE1: 2005 Q1 | EF1: 2005 Q2 | EG1: 2005 Q3 | EH1: 2005 Q4 | EI1: 2006 Q1 | EJ1: 2006 Q2 | EK1: 2006 Q3 | EL1: 2006 Q4 | EM1: 2007 Q1 | EN1: 2007 Q2 | EO1: 2007 Q3 | EP1: 2007 Q4 | EQ1: 2008 Q1 | ER1: 2008 Q2 | ES1: 2008 Q3 | ET1: 2008 Q4 | EU1: 2009 Q1 | EV1: 2009 Q2 | EW1: 2009 Q3 | EX1: 2009 Q4 | EY1: 2010 Q1 | EZ1: 2010 Q2 | FA1: 2010 Q3 | FB1: 2010 Q4 | FC1: 2011 Q1 | FD1: 2011 Q2 | FE1: 2011 Q3 | FF1: 2011 Q4 | FG1: 2012 Q1 | FH1: 2012 Q2 | FI1: 2012 Q3 | FJ1: 2012 Q4 | FK1: 2013 Q1 | FL1: 2013 Q2 | FM1: 2013 Q3 | FN1: 2013 Q4 | FO1: 2014 Q1 | FP1: 2014 Q2 | FQ1: 2014 Q3 | FR1: 2014 Q4 | FS1: 2015 Q1 | FT1: 2015 Q2 | FU1: 2015 Q3 | FV1: 2015 Q4 | FW1: 2016 Q1 | FX1: 2016 Q2 | FY1: 2016 Q3 | FZ1: 2016 Q4 | GA1: 2017 Q1 | GB1: 2017 Q2 | GC1: 2017 Q3 | GD1: 2017 Q4 | GE1: 2018 Q1 | GF1: 2018 Q2 | GG1: 2018 Q3 | GH1: 2018 Q4 | GI1: 2019 Q1 | GJ1: 2019 Q2 | GK1: 2019 Q3 | GL1: 2019 Q4 | GM1: 2020 Q1 | GN1: 2020 Q2 | GO1: 2020 Q3 | GP1: 2020 Q4 | GQ1: 2021 Q1 | GR1: 2021 Q2 | GS1: 2021 Q3 | GT1: 2021 Q4 | GU1: 2022 Q1 | GV1: 2022 Q2 | GW1: 2022 Q3 | GX1: 2022 Q4 | GY1: 2023 Q1 | GZ1: 2023 Q2 | HA1: 2023 Q3 | HB1: 2023 Q4 | HC1: 2024 Q1 | HD1: 2024 Q2 | HE1: 2024 Q3 | HF1: 2024 Q4 | HG1: 2025 Q1 | HH1: 2025 Q2 | HI1: 2025 Q3 | HJ1: 2025 Q4 | HK1: 2026 Q1 | HL1: 2026 Q2 | HM1: 2026 Q3 | HN1: 2026 Q4 | HO1: 2027 Q1 | HP1: 2027 Q2 | HQ1: 2027 Q3 | HR1: 2027 Q4 | HS1: 2028 Q1 | HT1: 2028 Q2 | HU1: 2028 Q3 | HV1: 2028 Q4 | HW1: 2029 Q1 | HX1: 2029 Q2 | HY1: 2029 Q3 | HZ1: 2029 Q4 | IA1: 2030 Q1 | IB1: 2030 Q2 | IC1: 2030 Q3 | ID1: 2030 Q4 | IE1: 2031 Q1 | IF1: 2031 Q2 | IG1: 2031 Q3 | IH1: 2031 Q4 | II1: 2032 Q1 | IJ1: 2032 Q2 | IK1: 2032 Q3 | IL1: 2032 Q4 | IM1: 2033 Q1 | IN1: 2033 Q2 | IO1: 2033 Q3 | IP1: 2033 Q4 | IQ1: 2034 Q1 | IR1: 2034 Q2 | IS1: 2034 Q3 | IT1: 2034 Q4 | IU1: 2035 Q1 | IV1: 2035 Q2 | IW1: 2035 Q3 | IX1: 2035 Q4 | IY1: 2036 Q1 | IZ1: 2036 Q2 | JA1: 2036 Q3 | JB1: 2036 Q4 | JC1: 2037 Q1 | JD1: 2037 Q2 | JE1: 2037 Q3 | JF1: 2037 Q4 | JG1: 2038 Q1 | JH1: 2038 Q2 | JI1: 2038 Q3 | JJ1: 2038 Q4 | JK1: 2039 Q1 | JL1: 2039 Q2 | JM1: 2039 Q3 | JN1: 2039 Q4 | JO1: 2040 Q1 | JP1: 2040 Q2 | JQ1: 2040 Q3 | JR1: 2040 Q4 | JS1: 2041 Q1 | JT1: 2041 Q2 | JU1: 2041 Q3 | JV1: 2041 Q4 | JW1: 2042 Q1 | JX1: 2042 Q2 | JY1: 2042 Q3 | JZ1: 2042 Q4 | KA1: 2043 Q1 | KB1: 2043 Q2 | KC1: 2043 Q3 | KD1: 2043 Q4 | KE1: 2044 Q1 | KF1: 2044 Q2 | KG1: 2044 Q3 | KH1: 2044 Q4 | KI1: 2045 Q1 | KJ1: 2045 Q2 | KK1: 2045 Q3 | KL1: 2045 Q4 | KM1: 2046 Q1 | KN1: 2046 Q2 | KO1: 2046 Q3 | KP1: 2046 Q4 | KQ1: 2047 Q1 | KR1: 2047 Q2 | KS1: 2047 Q3 | KT1: 2047 Q4 | KU1: 2048 Q1 | KV1: 2048 Q2 | KW1: 2048 Q3 | KX1: 2048 Q4 | KY1: 2049 Q1 | KZ1: 2049 Q2 | LA1: 2049 Q3 | LB1: 2049 Q4 | LC1: 2050 Q1 | LD1: 2050 Q2 | LE1: 2050 Q3 | LF1: 2050 Q4 | LG1: 2051 Q1 | LH1: 2051 Q2 | LI1: 2051 Q3 | LJ1: 2051 Q4 | LK1: 2052 Q1 | LL1: 2052 Q2 | LM1: 2052 Q3 | LN1: 2052 Q4 | LO1: 2053 Q1 | LP1: 2053 Q2 | LQ1: 2053 Q3 | LR1: 2053 Q4 | LS1: 2054 Q1 | LT1: 2054 Q2 | LU1: 2054 Q3 | LV1: 2054 Q4 | LW1: 2055 Q1 | LX1: 2055 Q2 | LY1: 2055 Q3 | LZ1: 2055 Q4 | MA1: 2056 Q1 | MB1: 2056 Q2 | MC1: 2056 Q3 | MD1: 2056 Q4 | ME1: 2057 Q1 | MF1: 2057 Q2 | MG1: 2057 Q3 | MH1: 2057 Q4 | MI1: 2058 Q1 | MJ1: 2058 Q2 | MK1: 2058 Q3 | ML1: 2058 Q4 | MM1: 2059 Q1 | MN1: 2059 Q2 | MO1: 2059 Q3 | MP1: 2059 Q4 | MQ1: 2060 Q1 | MR1: 2060 Q2 | MS1: 2060 Q3 | MT1: 2060 Q4 | MU1: Source | MV1: Seasonally adjusted | MW1: Base year price | MX1: Base year index | MY1: Historical end year | MZ1: Historical end quarter | NA1: Date of last update | NB1: Source details | NC1: Additional source details | ND1: Location code | NE1: Indicator code | NF1: Databank code
A2: United Kingdom | B2: Population, total | C2: NOV021L | D2: Person | E2: Thousands | F2: Level | G2: 56191.5 | H2: 56223 | I2: 56226.25 | J2: 56229.5 | K2: 56232.75 | L2: 56236 | M2: 56233.5 | N2: 56231 | O2: 56228.5 | P2: 56226 | Q2: 56223.5 | R2: 56221 | S2: 56218.5 | T2: 56216 | U2: 56209.5 | V2: 56203 | W2: 56196.5 | X2: 56190 | Y2: 56187 | Z2: 56184 | AA2: 56181 | AB2: 56178 | AC2: 56193.5 | AD2: 56209 | AE2: 56224.5 | AF2: 56240 | AG2: 56262.5 | AH2: 56285 | AI2: 56307.5 | AJ2: 56330 | AK2: 56337 | AL2: 56344 | AM2: 56351 | AN2: 56358 | AO2: 56341.25 | AP2: 56324.5 | AQ2: 56307.75 | AR2: 56291 | AS2: 56297.25 | AT2: 56303.5 | AU2: 56309.75 | AV2: 56316 | AW2: 56339.25 | AX2: 56362.5 | AY2: 56385.75 | AZ2: 56409 | BA2: 56445.25 | BB2: 56481.5 | BC2: 56517.75 | BD2: 56554 | BE2: 56586.5 | BF2: 56619 | BG2: 56651.5 | BH2: 56684 | BI2: 56714 | BJ2: 56744 | BK2: 56774 | BL2: 56804 | BM2: 56832 | BN2: 56860 | BO2: 56888 | BP2: 56916 | BQ2: 56956.25 | BR2: 56996.5 | BS2: 57036.75 | BT2: 57077 | BU2: 57117.25 | BV2: 57157.5 | BW2: 57197.75 | BX2: 57238 | BY2: 57288.25 | BZ2: 57338.5 | CA2: 57388.75 | CB2: 57439 | CC2: 57475.5 | CD2: 57512 | CE2: 57548.5 | CF2: 57585 | CG2: 57617.25 | CH2: 57649.5 | CI2: 57681.75 | CJ2: 57714 | CK2: 57751 | CL2: 57788 | CM2: 57825 | CN2: 57862 | CO2: 57902.75 | CP2: 57943.5 | CQ2: 57984.25 | CR2: 58025 | CS2: 58059.75 | CT2: 58094.5 | CU2: 58129.25 | CV2: 58164 | CW2: 58201.5 | CX2: 58239 | CY2: 58276.5 | CZ2: 58314 | DA2: 58354.25 | DB2: 58394.5 | DC2: 58434.75 | DD2: 58475 | DE2: 58527.25 | DF2: 58579.5 | DG2: 58631.75 | DH2: 58684 | DI2: 58734.5 | DJ2: 58785 | DK2: 58835.5 | DL2: 58886 | DM2: 58942.75 | DN2: 58999.5 | DO2: 59056.25 | DP2: 59113 | DQ2: 59176.25 | DR2: 59239.5 | DS2: 59302.75 | DT2: 59366 | DU2: 59433.75 | DV2: 59501.5 | DW2: 59569.25 | DX2: 59637 | DY2: 59715.25 | DZ2: 59793.5 | EA2: 59871.75 | EB2: 59950 | EC2: 60065.75 | ED2: 60181.5 | EE2: 60297.25 | EF2: 60413 | EG2: 60516.5 | EH2: 60620 | EI2: 60723.5 | EJ2: 60827 | EK2: 60950 | EL2: 61073 | EM2: 61196 | EN2: 61319 | EO2: 61445.25 | EP2: 61571.5 | EQ2: 61697.75 | ER2: 61824 | ES2: 61933.25 | ET2: 62042.5 | EU2: 62151.75 | EV2: 62261 | EW2: 62385.75 | EX2: 62510.5 | EY2: 62635.25 | EZ2: 62760 | FA2: 62891.25 | FB2: 63022.5 | FC2: 63153.75 | FD2: 63285 | FE2: 63391.5 | FF2: 63498 | FG2: 63604.5 | FH2: 63711 | FI2: 63817.75 | FJ2: 63924.5 | FK2: 64031.25 | FL2: 64138 | FM2: 64258.25 | FN2: 64378.5 | FO2: 64498.75 | FP2: 64619 | FQ2: 64736 | FR2: 64853 | FS2: 64970 | FT2: 65087 | FU2: 65216.75 | FV2: 65346.5 | FW2: 65476.25 | FX2: 65606 | FY2: 65695.5 | FZ2: 65785 | GA2: 65874.5 | GB2: 65964 | GC2: 66044.75 | GD2: 66125.5 | GE2: 66206.25 | GF2: 66287 | GG2: 66372.25 | GH2: 66457.5 | GI2: 66542.75 | GJ2: 66628 | GK2: 66656 | GL2: 66684 | GM2: 66712 | GN2: 66740 | GO2: 66799.5 | GP2: 66859 | GQ2: 66918.5 | GR2: 66978 | GS2: 67142.5 | GT2: 67307 | GU2: 67471.5 | GV2: 67636 | GW2: 67858.5 | GX2: 68081 | GY2: 68303.5 | GZ2: 68526 | HA2: 68714.75 | HB2: 68903.5 | HC2: 69092.25 | HD2: 69281 | HE2: 69391.65 | HF2: 69501.86 | HG2: 69612.07 | HH2: 69722.28 | HI2: 69822.84 | HJ2: 69923.38 | HK2: 70023.94 | HL2: 70124.48 | HM2: 70214.55 | HN2: 70304.63 | HO2: 70394.69 | HP2: 70484.76 | HQ2: 70554.3 | HR2: 70623.85 | HS2: 70693.4 | HT2: 70762.95 | HU2: 70830.84 | HV2: 70898.73 | HW2: 70966.62 | HX2: 71034.51 | HY2: 71100.59 | HZ2: 71166.67 | IA2: 71232.75 | IB2: 71298.84 | IC2: 71362.98 | ID2: 71427.13 | IE2: 71491.27 | IF2: 71555.42 | IG2: 71617.57 | IH2: 71679.72 | II2: 71741.87 | IJ2: 71804.02 | IK2: 71864.23 | IL2: 71924.45 | IM2: 71984.66 | IN2: 72044.87 | IO2: 72103.26 | IP2: 72161.66 | IQ2: 72220.05 | IR2: 72278.45 | IS2: 72335.09 | IT2: 72391.73 | IU2: 72448.38 | IV2: 72505.02 | IW2: 72559.99 | IX2: 72614.98 | IY2: 72669.95 | IZ2: 72724.94 | JA2: 72778.4 | JB2: 72831.86 | JC2: 72885.32 | JD2: 72938.79 | JE2: 72990.88 | JF2: 73042.98 | JG2: 73095.08 | JH2: 73147.18 | JI2: 73198.03 | JJ2: 73248.88 | JK2: 73299.73 | JL2: 73350.59 | JM2: 73400.27 | JN2: 73449.95 | JO2: 73499.64 | JP2: 73549.32 | JQ2: 73597.93 | JR2: 73646.53 | JS2: 73695.13 | JT2: 73743.73 | JU2: 73791.32 | JV2: 73838.9 | JW2: 73886.48 | JX2: 73934.05 | JY2: 73980.56 | JZ2: 74027.07 | KA2: 74073.58 | KB2: 74120.08 | KC2: 74165.4 | KD2: 74210.72 | KE2: 74256.04 | KF2: 74301.35 | KG2: 74345.4 | KH2: 74389.45 | KI2: 74433.48 | KJ2: 74477.53 | KK2: 74520.23 | KL2: 74562.93 | KM2: 74605.63 | KN2: 74648.33 | KO2: 74689.59 | KP2: 74730.85 | KQ2: 74772.12 | KR2: 74813.38 | KS2: 74852.86 | KT2: 74892.34 | KU2: 74931.83 | KV2: 74971.3 | KW2: 75008.6 | KX2: 75045.89 | KY2: 75083.19 | KZ2: 75120.48 | LA2: 75155.45 | LB2: 75190.41 | LC2: 75225.37 | LD2: 75260.33 | LE2: 75292.87 | LF2: 75325.41 | LG2: 75357.95 | LH2: 75390.49 | LI2: 75420.59 | LJ2: 75450.7 | LK2: 75480.8 | LL2: 75510.9 | LM2: 75538.56 | LN2: 75566.23 | LO2: 75593.89 | LP2: 75621.55 | LQ2: 75646.84 | LR2: 75672.12 | LS2: 75697.4 | LT2: 75722.68 | LU2: 75745.76 | LV2: 75768.83 | LW2: 75791.91 | LX2: 75814.98 | LY2: 75836.13 | LZ2: 75857.29 | MA2: 75878.45 | MB2: 75899.6 | MC2: 75919.14 | MD2: 75938.67 | ME2: 75958.21 | MF2: 75977.74 | MG2: 75995.92 | MH2: 76014.1 | MI2: 76032.28 | MJ2: 76050.45 | MK2: 76067.56 | ML2: 76084.67 | MM2: 76101.77 | MN2: 76118.88 | MO2: 76135.2 | MP2: 76151.52 | MQ2: 76167.84 | MR2: 76184.16 | MS2: 76200.48 | MT2: 76216.81 | MU2: Office for National Statistics\Haver Analytics | MV2: FALSE | MW2: NA | MX2: NA | MY2: 2024 | MZ2: 2 | NA2: NA | NB2: DYAYA@UK | NC2: U.K.: Population: Midyear Estimates (Thous.Persons) | ND2: GBR | NE2: POP | NF2: NOV021L.db
A3: United Kingdom | B3: GDP, real, LCU | C3: NOV021L | D3: Pound | E3: Millions | F3: Level | G3: 267015 | H3: 267521 | I3: 265025 | J3: 263989 | K3: 256670 | L3: 260347 | M3: 261890 | N3: 258066 | O3: 258116 | P3: 253935 | Q3: 253168 | R3: 255985 | S3: 260268 | T3: 259911 | U3: 263132 | V3: 268662 | W3: 268833 | X3: 266987 | Y3: 268717 | Z3: 273279 | AA3: 275841 | AB3: 279001 | AC3: 282797 | AD3: 285314 | AE3: 284457 | AF3: 296841 | AG3: 290297 | AH3: 293265 | AI3: 290378 | AJ3: 284713 | AK3: 284402 | AL3: 281496 | AM3: 281257 | AN3: 282155 | AO3: 285437 | AP3: 285814 | AQ3: 286275 | AR3: 289232 | AS3: 289852 | AT3: 291832 | AU3: 297563 | AV3: 299623 | AW3: 303085 | AX3: 305361 | AY3: 307964 | AZ3: 304892 | BA3: 307122 | BB3: 312697 | BC3: 315753 | BD3: 322451 | BE3: 322392 | BF3: 322604 | BG3: 325968 | BH3: 328872 | BI3: 330966 | BJ3: 337367 | BK3: 339754 | BL3: 344795 | BM3: 353365 | BN3: 357439 | BO3: 363267 | BP3: 365209 | BQ3: 369774 | BR3: 372752 | BS3: 374612 | BT3: 376951 | BU3: 377573 | BV3: 377508 | BW3: 379458 | BX3: 381997 | BY3: 377831 | BZ3: 375916 | CA3: 374060 | CB3: 373608 | CC3: 372878 | CD3: 373357 | CE3: 373317 | CF3: 372751 | CG3: 374537 | CH3: 377418 | CI3: 379370 | CJ3: 381045 | CK3: 384524 | CL3: 387143 | CM3: 391026 | CN3: 394588 | CO3: 398566 | CP3: 400279 | CQ3: 402390 | CR3: 403259 | CS3: 407795 | CT3: 409132 | CU3: 412022 | CV3: 413325 | CW3: 417019 | CX3: 422639 | CY3: 429418 | CZ3: 434199 | DA3: 438100 | DB3: 444540 | DC3: 447712 | DD3: 450292 | DE3: 451005 | DF3: 453937 | DG3: 457044 | DH3: 458710 | DI3: 466387 | DJ3: 473892 | DK3: 480212 | DL3: 483672 | DM3: 486617 | DN3: 489506 | DO3: 493575 | DP3: 495602 | DQ3: 497938 | DR3: 499278 | DS3: 500794 | DT3: 503433 | DU3: 506386 | DV3: 509728 | DW3: 514031 | DX3: 518802 | DY3: 524213 | DZ3: 528320 | EA3: 529996 | EB3: 532543 | EC3: 534447 | ED3: 536886 | EE3: 541028 | EF3: 545530 | EG3: 550552 | EH3: 556311 | EI3: 558314 | EJ3: 559795 | EK3: 560675 | EL3: 562669 | EM3: 568845 | EN3: 574194 | EO3: 579605 | EP3: 584504 | EQ3: 586690 | ER3: 583541 | ES3: 573961 | ET3: 561816 | EU3: 550451 | EV3: 548859 | EW3: 549540 | EX3: 551372 | EY3: 556002 | EZ3: 562353 | FA3: 565659 | FB3: 565945 | FC3: 566873 | FD3: 566601 | FE3: 567586 | FF3: 568056 | FG3: 573416 | FH3: 573112 | FI3: 579051 | FJ3: 578215 | FK3: 579749 | FL3: 583605 | FM3: 588076 | FN3: 591954 | FO3: 596696 | FP3: 602310 | FQ3: 607213 | FR3: 611220 | FS3: 613076 | FT3: 615875 | FU3: 618263 | FV3: 621968 | FW3: 625099 | FX3: 629697 | FY3: 632477 | FZ3: 636392 | GA3: 642463 | GB3: 647944 | GC3: 652329 | GD3: 657225 | GE3: 657741 | GF3: 659172 | GG3: 661262 | GH3: 662120 | GI3: 665456 | GJ3: 666875 | GK3: 670547 | GL3: 670587 | GM3: 652180 | GN3: 522356 | GO3: 610972 | GP3: 619330 | GQ3: 612665 | GR3: 655443 | GS3: 666498 | GT3: 675680 | GU3: 682527 | GV3: 686335 | GW3: 687029 | GX3: 688817 | GY3: 689206 | GZ3: 689491 | HA3: 687839 | HB3: 685628 | HC3: 691337 | HD3: 695578 | HE3: 697248 | HF3: 698912 | HG3: 703532 | HH3: 705486 | HI3: 706062 | HJ3: 707438.8 | HK3: 709335.8 | HL3: 711025.3 | HM3: 712848.6 | HN3: 714836.9 | HO3: 717052.9 | HP3: 719581.1 | HQ3: 722315.3 | HR3: 725276.6 | HS3: 728250.5 | HT3: 731163.1 | HU3: 734416.8 | HV3: 737575 | HW3: 740599 | HX3: 743524.2 | HY3: 746498.4 | HZ3: 749484.4 | IA3: 752370 | IB3: 755304.3 | IC3: 758249.9 | ID3: 761282.9 | IE3: 764328.1 | IF3: 767385.4 | IG3: 770378.1 | IH3: 773421.1 | II3: 776514.8 | IJ3: 779543.3 | IK3: 782583.4 | IL3: 785674.7 | IM3: 788668.2 | IN3: 791678.2 | IO3: 794734.4 | IP3: 797738.4 | IQ3: 800822.5 | IR3: 803846.1 | IS3: 806845.6 | IT3: 809805.3 | IU3: 812870.9 | IV3: 815949.8 | IW3: 819041.6 | IX3: 822146.2 | IY3: 825332.6 | IZ3: 828535.6 | JA3: 831754.9 | JB3: 834990.6 | JC3: 838242.6 | JD3: 841510.7 | JE3: 844795.3 | JF3: 848096.3 | JG3: 851413.8 | JH3: 854747.4 | JI3: 858097.9 | JJ3: 861465.5 | JK3: 864850.1 | JL3: 868251.3 | JM3: 871669.8 | JN3: 875105.4 | JO3: 878558.1 | JP3: 882026.5 | JQ3: 885510.6 | JR3: 889010.3 | JS3: 892595.1 | JT3: 896196.6 | JU3: 899826.2 | JV3: 903472.6 | JW3: 907136 | JX3: 910816.2 | JY3: 914438.8 | JZ3: 918076.8 | KA3: 921730.4 | KB3: 925399.6 | KC3: 928921.3 | KD3: 932455.2 | KE3: 936001.4 | KF3: 939559.5 | KG3: 942980.4 | KH3: 946410.9 | KI3: 949850.8 | KJ3: 953300.2 | KK3: 956694.8 | KL3: 960097.6 | KM3: 963509.2 | KN3: 966929.1 | KO3: 970391.1 | KP3: 973862.5 | KQ3: 977343 | KR3: 980832.9 | KS3: 984275.8 | KT3: 987727.3 | KU3: 991187.3 | KV3: 994655.9 | KW3: 998108.8 | KX3: 1001570 | KY3: 1005039 | KZ3: 1008516 | LA3: 1011923 | LB3: 1015336 | LC3: 1018757 | LD3: 1022182 | LE3: 1025587 | LF3: 1028997 | LG3: 1032413 | LH3: 1035834 | LI3: 1039222 | LJ3: 1042614 | LK3: 1046011 | LL3: 1049414 | LM3: 1052740 | LN3: 1056070 | LO3: 1059403 | LP3: 1062739 | LQ3: 1066079 | LR3: 1069422 | LS3: 1072769 | LT3: 1076120 | LU3: 1079439 | LV3: 1082761 | LW3: 1086087 | LX3: 1089416 | LY3: 1092714 | LZ3: 1096014 | MA3: 1099318 | MB3: 1102624 | MC3: 1105932 | MD3: 1109243 | ME3: 1112557 | MF3: 1115874 | MG3: 1119221 | MH3: 1122571 | MI3: 1125926 | MJ3: 1129284 | MK3: 1132624 | ML3: 1135967 | MM3: 1139314 | MN3: 1142665 | MO3: 1146044 | MP3: 1149426 | MQ3: 1152814 | MR3: 1156205 | MS3: 1159600 | MT3: 1163001 | MU3: Office for National Statistics\Haver Analytics | MV3: TRUE | MW3: chained 2023 | MX3: NA | MY3: 2025 | MZ3: 3 | NA3: NA | NB3: ABMIQ@UK | NC3: U.K.: Real Gross Domestic Product (SA, Mil.Chn.2023.GBP) | ND3: GBR | NE3: GDP | NF3: NOV021L.db
A4: United Kingdom | B4: Consumer price index | C4: NOV021L | D4: Index | E4: NA | F4: Level | G4: 11.88749 | H4: 12.3046 | I4: 12.51315 | J4: 13.00846 | K4: 13.47771 | L4: 14.23371 | M4: 14.57261 | N4: 15.2504 | O4: 16.05854 | P4: 17.46627 | Q4: 18.22228 | R4: 18.84793 | S4: 19.42145 | T4: 20.12532 | U4: 20.59456 | V4: 21.50698 | W4: 22.47153 | X4: 23.41002 | Y4: 23.82713 | Z4: 24.13995 | AA4: 24.45278 | AB4: 25.07844 | AC4: 25.46948 | AD4: 25.86051 | AE4: 26.43403 | AF4: 27.26824 | AG4: 28.91059 | AH4: 29.71873 | AI4: 30.60508 | AJ4: 32.24743 | AK4: 32.9513 | AL4: 33.55088 | AM4: 34.3851 | AN4: 36.07959 | AO4: 36.73131 | AP4: 37.43518 | AQ4: 37.87835 | AR4: 39.1818 | AS4: 39.41642 | AT4: 39.88567 | AU4: 40.17243 | AV4: 40.85022 | AW4: 41.2934 | AX4: 41.76264 | AY4: 41.86692 | AZ4: 42.77934 | BA4: 42.98789 | BB4: 43.43106 | BC4: 43.87423 | BD4: 44.9952 | BE4: 45.12555 | BF4: 45.49052 | BG4: 45.64693 | BH4: 46.3508 | BI4: 46.53328 | BJ4: 46.92432 | BK4: 47.23714 | BL4: 47.83673 | BM4: 47.88887 | BN4: 48.43632 | BO4: 48.56667 | BP4: 49.5 | BQ4: 49.9 | BR4: 50.46667 | BS4: 51 | BT4: 52.13334 | BU4: 52.46667 | BV4: 53.26667 | BW4: 53.93333 | BX4: 55.6 | BY4: 56.4 | BZ4: 57.46667 | CA4: 57.66667 | CB4: 60.26667 | CC4: 60.83333 | CD4: 61.46667 | CE4: 61.7 | CF4: 62.83333 | CG4: 62.73333 | CH4: 63.13334 | CI4: 63.2 | CJ4: 64.43333 | CK4: 64.5 | CL4: 64.66666 | CM4: 64.76667 | CN4: 65.7 | CO4: 65.63333 | CP4: 65.8 | CQ4: 66.33334 | CR4: 67.26667 | CS4: 67.4 | CT4: 67.73333 | CU4: 68.1 | CV4: 68.86667 | CW4: 68.93333 | CX4: 69.36667 | CY4: 69.36667 | CZ4: 70 | DA4: 70.26667 | DB4: 70.63333 | DC4: 70.5 | DD4: 71.26667 | DE4: 71.23333 | DF4: 71.63333 | DG4: 71.6 | DH4: 72.3 | DI4: 72.13333 | DJ4: 72.43333 | DK4: 72.13333 | DL4: 72.76667 | DM4: 72.7 | DN4: 73.16666 | DO4: 72.76667 | DP4: 73.83334 | DQ4: 73.86667 | DR4: 73.9 | DS4: 73.86667 | DT4: 74.53333 | DU4: 74.6 | DV4: 75 | DW4: 75 | DX4: 75.46667 | DY4: 75.6 | DZ4: 76.03333 | EA4: 75.96667 | EB4: 76.53333 | EC4: 76.56667 | ED4: 77.1 | EE4: 77.23333 | EF4: 78 | EG4: 78.4 | EH4: 78.76667 | EI4: 78.73333 | EJ4: 79.8 | EK4: 80.3 | EL4: 80.9 | EM4: 81 | EN4: 81.8 | EO4: 81.73333 | EP4: 82.6 | EQ4: 82.93333 | ER4: 84.6 | ES4: 85.63333 | ET4: 85.73333 | EU4: 85.43333 | EV4: 86.36667 | EW4: 86.93333 | EX4: 87.56667 | EY4: 88.23333 | EZ4: 89.36667 | FA4: 89.63333 | FB4: 90.5 | FC4: 91.83334 | FD4: 93.3 | FE4: 93.83334 | FF4: 94.73333 | FG4: 95.03333 | FH4: 95.8 | FI4: 96.06667 | FJ4: 97.26667 | FK4: 97.66666 | FL4: 98.36667 | FM4: 98.7 | FN4: 99.3 | FO4: 99.4 | FP4: 100.1 | FQ4: 100.1333 | FR4: 100.2 | FS4: 99.5 | FT4: 100.0667 | FU4: 100.1667 | FV4: 100.3 | FW4: 99.83334 | FX4: 100.4 | FY4: 100.8667 | FZ4: 101.5 | GA4: 102 | GB4: 103.1667 | GC4: 103.7 | GD4: 104.5667 | GE4: 104.7667 | GF4: 105.6667 | GG4: 106.3 | GH4: 106.9333 | GI4: 106.7 | GJ4: 107.8 | GK4: 108.2667 | GL4: 108.4333 | GM4: 108.4667 | GN4: 108.5333 | GO4: 108.9333 | GP4: 109.0667 | GQ4: 109.1667 | GR4: 110.7333 | GS4: 111.9333 | GT4: 114.4 | GU4: 115.9333 | GV4: 120.8667 | GW4: 123.1333 | GX4: 126.7 | GY4: 127.7333 | GZ4: 131.0667 | HA4: 131.4 | HB4: 131.9667 | HC4: 132.2667 | HD4: 133.8333 | HE4: 134.1 | HF4: 135.2333 | HG4: 135.9667 | HH4: 138.5 | HI4: 139.2 | HJ4: 140.1288 | HK4: 140.5075 | HL4: 142.0277 | HM4: 142.9096 | HN4: 143.815 | HO4: 144.2112 | HP4: 145.6805 | HQ4: 146.5034 | HR4: 147.3055 | HS4: 147.5331 | HT4: 148.9488 | HU4: 149.7613 | HV4: 150.5015 | HW4: 150.7888 | HX4: 152.2261 | HY4: 153.0527 | HZ4: 153.7369 | IA4: 153.9671 | IB4: 155.3997 | IC4: 156.2374 | ID4: 156.8838 | IE4: 157.0918 | IF4: 158.5541 | IG4: 159.4264 | IH4: 160.0367 | II4: 160.2166 | IJ4: 161.7164 | IK4: 162.6398 | IL4: 163.2308 | IM4: 163.3983 | IN4: 164.9536 | IO4: 165.9362 | IP4: 166.494 | IQ4: 166.6343 | IR4: 168.2397 | IS4: 169.2868 | IT4: 169.8128 | IU4: 169.932 | IV4: 171.5994 | IW4: 172.719 | IX4: 173.2036 | IY4: 173.3307 | IZ4: 175.0314 | JA4: 176.1734 | JB4: 176.6677 | JC4: 176.7973 | JD4: 178.532 | JE4: 179.6969 | JF4: 180.2011 | JG4: 180.3332 | JH4: 182.1026 | JI4: 183.2908 | JJ4: 183.8051 | JK4: 183.9399 | JL4: 185.7447 | JM4: 186.9566 | JN4: 187.4812 | JO4: 187.6187 | JP4: 189.4596 | JQ4: 190.6957 | JR4: 191.2308 | JS4: 191.3711 | JT4: 193.2488 | JU4: 194.5096 | JV4: 195.0554 | JW4: 195.1985 | JX4: 197.1138 | JY4: 198.3998 | JZ4: 198.9565 | KA4: 199.1025 | KB4: 201.056 | KC4: 202.3678 | KD4: 202.9357 | KE4: 203.0845 | KF4: 205.0772 | KG4: 206.4152 | KH4: 206.9944 | KI4: 207.1462 | KJ4: 209.1787 | KK4: 210.5435 | KL4: 211.1343 | KM4: 211.2891 | KN4: 213.3623 | KO4: 214.7544 | KP4: 215.3569 | KQ4: 215.5149 | KR4: 217.6295 | KS4: 219.0495 | KT4: 219.6641 | KU4: 219.8252 | KV4: 221.9821 | KW4: 223.4305 | KX4: 224.0574 | KY4: 224.2217 | KZ4: 226.4218 | LA4: 227.899 | LB4: 228.5385 | LC4: 228.7061 | LD4: 230.9502 | LE4: 232.457 | LF4: 233.1093 | LG4: 233.2803 | LH4: 235.5692 | LI4: 237.1062 | LJ4: 237.7715 | LK4: 237.9459 | LL4: 240.2806 | LM4: 241.8483 | LN4: 242.5269 | LO4: 242.7048 | LP4: 245.0862 | LQ4: 246.6853 | LR4: 247.3774 | LS4: 247.5589 | LT4: 249.9879 | LU4: 251.619 | LV4: 252.325 | LW4: 252.5101 | LX4: 254.9877 | LY4: 256.6513 | LZ4: 257.3715 | MA4: 257.5603 | MB4: 260.0874 | MC4: 261.7844 | MD4: 262.5189 | ME4: 262.7115 | MF4: 265.2892 | MG4: 267.0201 | MH4: 267.7693 | MI4: 267.9657 | MJ4: 270.5949 | MK4: 272.3605 | ML4: 273.1247 | MM4: 273.325 | MN4: 276.0069 | MO4: 277.8077 | MP4: 278.5872 | MQ4: 278.7915 | MR4: 281.527 | MS4: 283.3638 | MT4: 284.1589 | MU4: Office for National Statistics\Haver Analytics | MV4: FALSE | MW4: NA | MX4: 2015 | MY4: 2025 | MZ4: 3 | NA4: NA | NB4: D7BT@UK | NC4: UK: Consumer Price Index: All Items (NSA, 2015=100) | ND4: GBR | NE4: CPI | NF4: NOV021L.db
A5: United Kingdom | B5: Average Weekly Earnings (total pay) | C5: NOV021L | D5: Pound per Employee | E5: NA | F5: Level | G5: 14.85115 | H5: 15.59743 | I5: 16.40707 | J5: 16.90761 | K5: 16.78086 | L5: 18.25341 | M5: 20.2429 | N5: 21.92424 | O5: 23.39659 | P5: 24.96419 | Q5: 27.02938 | R5: 28.37567 | S5: 29.35714 | T5: 30.79358 | U5: 32.30147 | V5: 33.18535 | W5: 33.54049 | X5: 34.54346 | Y5: 35.59764 | Z5: 36.68552 | AA5: 37.64326 | AB5: 39.86473 | AC5: 42.09901 | AD5: 43.30621 | AE5: 43.96501 | AF5: 46.83842 | AG5: 50.12706 | AH5: 52.64415 | AI5: 54.9067 | AJ5: 59.1701 | AK5: 63.64214 | AL5: 66.77174 | AM5: 67.32769 | AN5: 69.61449 | AO5: 73.35294 | AP5: 76.17709 | AQ5: 76.58652 | AR5: 78.91912 | AS5: 82.15866 | AT5: 83.43923 | AU5: 84.92252 | AV5: 88.03934 | AW5: 90.43758 | AX5: 91.53184 | AY5: 92.07954 | AZ5: 94.12758 | BA5: 96.73234 | BB5: 99.44635 | BC5: 100.1239 | BD5: 104.4909 | BE5: 107.6677 | BF5: 109.6371 | BG5: 110.8912 | BH5: 115.3305 | BI5: 118.2911 | BJ5: 120.3198 | BK5: 121.4108 | BL5: 125.7916 | BM5: 130.0642 | BN5: 132.7039 | BO5: 134.4686 | BP5: 139.0533 | BQ5: 144.164 | BR5: 148.042 | BS5: 150.6279 | BT5: 155.5334 | BU5: 160.6419 | BV5: 165.395 | BW5: 167.1534 | BX5: 174.4332 | BY5: 181.6447 | BZ5: 185.4139 | CA5: 187.0954 | CB5: 192.8908 | CC5: 198.7286 | CD5: 202.2243 | CE5: 203.9918 | CF5: 209.3937 | CG5: 213.1408 | CH5: 215.0164 | CI5: 213.9543 | CJ5: 217.7845 | CK5: 221.5908 | CL5: 222.9062 | CM5: 222.8023 | CN5: 227.5204 | CO5: 232.0582 | CP5: 233.2474 | CQ5: 232.6693 | CR5: 237.6907 | CS5: 240.2794 | CT5: 241.9046 | CU5: 241.4031 | CV5: 247.3156 | CW5: 251.5293 | CX5: 253.9439 | CY5: 253.9303 | CZ5: 259.937 | DA5: 264.7916 | DB5: 268.6183 | DC5: 269.5669 | DD5: 278.0302 | DE5: 282.8819 | DF5: 285.1571 | DG5: 284.6907 | DH5: 293.5073 | DI5: 299.8239 | DJ5: 303.6802 | DK5: 305.3333 | DL5: 310.3333 | DM5: 315 | DN5: 320.3333 | DO5: 324 | DP5: 327 | DQ5: 330 | DR5: 333.6667 | DS5: 333.6667 | DT5: 339 | DU5: 341.3333 | DV5: 342.6667 | DW5: 343 | DX5: 348 | DY5: 352.6667 | DZ5: 356.6667 | EA5: 359 | EB5: 363 | EC5: 367 | ED5: 372.3333 | EE5: 375.3333 | EF5: 379.6667 | EG5: 385.3333 | EH5: 389.3333 | EI5: 393.6667 | EJ5: 397.6667 | EK5: 401.3333 | EL5: 408 | EM5: 416.6667 | EN5: 415.3333 | EO5: 422 | EP5: 425 | EQ5: 433.6667 | ER5: 433 | ES5: 435 | ET5: 436.3333 | EU5: 421 | EV5: 437.6667 | EW5: 438 | EX5: 439.6667 | EY5: 442 | EZ5: 442.3333 | FA5: 444.6667 | FB5: 448 | FC5: 454.6667 | FD5: 453.3333 | FE5: 454.6667 | FF5: 456.6667 | FG5: 457 | FH5: 460.3333 | FI5: 463 | FJ5: 462 | FK5: 459.3333 | FL5: 470.6667 | FM5: 466 | FN5: 466.6667 | FO5: 467.3333 | FP5: 469.3333 | FQ5: 470 | FR5: 476 | FS5: 478 | FT5: 481.3333 | FU5: 483.6667 | FV5: 485 | FW5: 488.3333 | FX5: 493.6667 | FY5: 495 | FZ5: 497 | GA5: 499 | GB5: 504.3333 | GC5: 506.6667 | GD5: 510.3333 | GE5: 512 | GF5: 516.6667 | GG5: 522.3333 | GH5: 528 | GI5: 529 | GJ5: 537 | GK5: 542.3333 | GL5: 542.6667 | GM5: 540.6667 | GN5: 531 | GO5: 550.3333 | GP5: 567 | GQ5: 563.3333 | GR5: 578.3333 | GS5: 583 | GT5: 595 | GU5: 604.3333 | GV5: 609 | GW5: 617.6667 | GX5: 632 | GY5: 642 | GZ5: 659 | HA5: 666.6667 | HB5: 669 | HC5: 680 | HD5: 690.3333 | HE5: 698 | HF5: 709 | HG5: 718 | HH5: 722.6667 | HI5: 731.3333 | HJ5: 736.0806 | HK5: 741.601 | HL5: 746.7926 | HM5: 752.0198 | HN5: 757.2836 | HO5: 762.585 | HP5: 768.037 | HQ5: 773.4269 | HR5: 778.6572 | HS5: 783.7202 | HT5: 788.7657 | HU5: 793.8633 | HV5: 798.9536 | HW5: 804.1984 | HX5: 809.5425 | HY5: 815.0037 | HZ5: 820.494 | IA5: 826.0298 | IB5: 831.6682 | IC5: 837.4399 | ID5: 843.2614 | IE5: 849.1404 | IF5: 855.0742 | IG5: 861.0914 | IH5: 867.1021 | II5: 873.1498 | IJ5: 879.2849 | IK5: 885.5434 | IL5: 891.8294 | IM5: 898.1378 | IN5: 904.5451 | IO5: 911.0946 | IP5: 917.6609 | IQ5: 924.2736 | IR5: 931.0272 | IS5: 937.949 | IT5: 944.8918 | IU5: 951.9104 | IV5: 959.0699 | IW5: 966.3892 | IX5: 973.7133 | IY5: 981.1097 | IZ5: 988.5878 | JA5: 996.1475 | JB5: 1003.792 | JC5: 1011.502 | JD5: 1019.277 | JE5: 1027.118 | JF5: 1035.025 | JG5: 1043 | JH5: 1051.041 | JI5: 1059.151 | JJ5: 1067.33 | JK5: 1075.579 | JL5: 1083.897 | JM5: 1092.286 | JN5: 1100.747 | JO5: 1109.28 | JP5: 1117.884 | JQ5: 1126.56 | JR5: 1135.309 | JS5: 1144.116 | JT5: 1152.983 | JU5: 1161.909 | JV5: 1170.892 | JW5: 1179.948 | JX5: 1189.079 | JY5: 1198.297 | JZ5: 1207.604 | KA5: 1217 | KB5: 1226.485 | KC5: 1236.077 | KD5: 1245.774 | KE5: 1255.577 | KF5: 1265.486 | KG5: 1275.499 | KH5: 1285.617 | KI5: 1295.839 | KJ5: 1306.167 | KK5: 1316.587 | KL5: 1327.097 | KM5: 1337.698 | KN5: 1348.393 | KO5: 1359.162 | KP5: 1370.006 | KQ5: 1380.928 | KR5: 1391.924 | KS5: 1403.016 | KT5: 1414.203 | KU5: 1425.485 | KV5: 1436.864 | KW5: 1448.332 | KX5: 1459.892 | KY5: 1471.544 | KZ5: 1483.289 | LA5: 1495.138 | LB5: 1507.09 | LC5: 1519.146 | LD5: 1531.308 | LE5: 1543.564 | LF5: 1555.915 | LG5: 1568.359 | LH5: 1580.9 | LI5: 1593.539 | LJ5: 1606.278 | LK5: 1619.12 | LL5: 1632.062 | LM5: 1645.116 | LN5: 1658.281 | LO5: 1671.56 | LP5: 1684.95 | LQ5: 1698.436 | LR5: 1712.021 | LS5: 1725.702 | LT5: 1739.484 | LU5: 1753.373 | LV5: 1767.367 | LW5: 1781.472 | LX5: 1795.684 | LY5: 1810.006 | LZ5: 1824.437 | MA5: 1838.981 | MB5: 1853.636 | MC5: 1868.395 | MD5: 1883.261 | ME5: 1898.232 | MF5: 1913.312 | MG5: 1928.495 | MH5: 1943.783 | MI5: 1959.174 | MJ5: 1974.668 | MK5: 1990.281 | ML5: 2006.012 | MM5: 2021.863 | MN5: 2037.831 | MO5: 2053.91 | MP5: 2070.098 | MQ5: 2086.397 | MR5: 2102.81 | MS5: 2119.338 | MT5: 2135.989 | MU5: Office for National Statistics\Haver Analytics | MV5: TRUE | MW5: NA | MX5: NA | MY5: 2025 | MZ5: 3 | NA5: NA | NB5: KAB9@UK | NC5: GB: AWE, Total Pay: Whole Economy (SA, GBP) | ND5: GBR | NE5: WAGEWKLY | NF5: NOV021L.db

Sheet Aggregates (£bn)
C1: £ billion
C3: Receipts and expenditure | K3: Deficit | Q3: Fiscal targets | T3: Financing | X3: Other Debt and Deficit measures | AE3: Economic indicators
C4: Public sector current receipts | D4: Total managed expenditure | E4: Public sector current expenditure | F4: Public sector net investment | G4: Depreciation | H4: Public sector gross investment | I4: National account taxes | K4: Cyclically-adjusted current budget deficit | L4: Primary balance | M4: Cyclically-adjusted primary balance | N4: Cyclically-adjusted net borrowing | O4: Public sector net borrowing | Q4: Current budget deficit | R4: Public sector net financial liabilities | T4: Central government net cash requirement | U4: Public sector net cash requirement | V4: Central government debt interest, net of APF | X4: Public sector net debt | Y4: Public Sector Net Debt ex BoE | Z4: Public sector net worth (inverted) | AA4: General government net borrowing | AB4: Cyclically-adjusted general government net borrowing | AC4: General Government Gross Debt | AE4: Nominal GDP (£ billion) | AF4: Nominal GDP, centred end-March (£ billion) | AG4: Output gap (per cent of GDP) | AH4: GDP Deflator (2024-25=100)
B5: ONS code | C5: JW2O | D5: KX5Q | E5: JW2Q | F5: -JW2Z | G5: -JW2S | L5: (J5II+JW2P-JW2L+JW2M) | O5: -J5II | Q5: -JW2T | T5: RUUW | U5: JW38 | V5: NMFX+MU74 | X5: HF6W | Y5: CPPH | AA5: -NNBK | AC5: BKPX | AE5: BKTL | AF5: BKTL | AH5: YBGB
B6: Derivation | C6: a | D6: b | E6: c | F6: d | G6: e
D7: (c+d+e) | H7: (d+e) | O7: (b-a) | Q7: (c+e-a)
B8: 1946-47 | C8: 3.648 | D8: 4.277 | E8: 3.734 | F8: 0.412 | G8: 0.131 | H8: 0.543 | I8: 3.547 | K8: - | L8: -0.066 | M8: - | N8: - | O8: 0.629 | Q8: 0.217 | T8: 0.439 | U8: 0.629 | V8: 0.504 | AA8: 0.632 | AB8: - | AC8: - | AE8: - | AF8: - | AG8: - | AH8: -
B9: 1947-48 | C9: 3.949 | D9: 4.028 | E9: 3.449 | F9: 0.371 | G9: 0.208 | H9: 0.579 | I9: 3.717 | K9: - | L9: 0.428 | M9: - | N9: - | O9: 0.079 | Q9: -0.292 | T9: -0.197 | U9: 0.079 | V9: 0.527 | AA9: 0.119 | AB9: - | AC9: - | AE9: - | AF9: - | AG9: - | AH9: -
B10: 1948-49 | C10: 4.906 | D10: 4.41 | E10: 3.797 | F10: 0.301 | G10: 0.312 | H10: 0.613 | I10: 4.251 | K10: - | L10: 0.879 | M10: - | N10: - | O10: -0.496 | Q10: -0.797 | T10: -0.677 | U10: -0.496 | V10: 0.52 | AA10: -0.434 | AB10: - | AC10: - | AE10: 11.425 | AF10: - | AG10: - | AH10: -
B11: 1949-50 | C11: 5.269 | D11: 4.682 | E11: 3.989 | F11: 0.364 | G11: 0.329 | H11: 0.693 | I11: 4.494 | K11: - | L11: 0.958 | M11: - | N11: - | O11: -0.587 | Q11: -0.951 | T11: -0.794 | U11: -0.587 | V11: 0.519 | AA11: -0.515 | AB11: - | AC11: - | AE11: 12.169 | AF11: - | AG11: - | AH11: -
B12: 1950-51 | C12: 5.458 | D12: 4.992 | E12: 4.157 | F12: 0.479 | G12: 0.356 | H12: 0.835 | I12: 4.596 | K12: - | L12: 0.824 | M12: - | N12: - | O12: -0.466 | Q12: -0.945 | T12: -0.745 | U12: -0.466 | V12: 0.531 | AA12: -0.417 | AB12: - | AC12: - | AE12: 12.74 | AF12: - | AG12: - | AH12: -
B13: 1951-52 | C13: 5.883 | D13: 5.814 | E13: 4.62 | F13: 0.778 | G13: 0.416 | H13: 1.194 | I13: 4.975 | K13: - | L13: 0.488 | M13: - | N13: - | O13: -0.069 | Q13: -0.847 | T13: -0.384 | U13: -0.069 | V13: 0.579 | AA13: -0.001 | AB13: - | AC13: - | AE13: 14.303 | AF13: - | AG13: - | AH13: -
B14: 1952-53 | C14: 6.203 | D14: 6.412 | E14: 5.055 | F14: 0.897 | G14: 0.46 | H14: 1.357 | I14: 5.275 | K14: - | L14: 0.297 | M14: - | N14: - | O14: 0.209 | Q14: -0.688 | T14: -0.3 | U14: 0.209 | V14: 0.634 | AA14: 0.154 | AB14: - | AC14: - | AE14: 15.536 | AF14: - | AG14: - | AH14: -
B15: 1953-54 | C15: 6.34 | D15: 6.758 | E15: 5.273 | F15: 1.011 | G15: 0.474 | H15: 1.485 | I15: 5.29 | K15: - | L15: 0.076 | M15: - | N15: - | O15: 0.418 | Q15: -0.593 | T15: -0.158 | U15: 0.418 | V15: 0.657 | AA15: 0.294 | AB15: - | AC15: - | AE15: 16.685 | AF15: - | AG15: - | AH15: -
B16: 1954-55 | C16: 6.594 | D16: 6.851 | E16: 5.478 | F16: 0.874 | G16: 0.499 | H16: 1.373 | I16: 5.441 | K16: - | L16: 0.19 | M16: - | N16: - | O16: 0.257 | Q16: -0.617 | T16: -0.307 | U16: 0.257 | V16: 0.656 | AA16: 0.113 | AB16: - | AC16: - | AE16: 17.601 | AF16: - | AG16: - | AH16: -
B17: 1955-56 | C17: 7.04 | D17: 7.002 | E17: 5.611 | F17: 0.844 | G17: 0.547 | H17: 1.391 | I17: 5.803 | K17: - | L17: 0.539 | M17: - | N17: - | O17: -0.038 | Q17: -0.882 | T17: -0.556 | U17: -0.038 | V17: 0.742 | AA17: -0.108 | AB17: - | AC17: - | AE17: 19.575 | AF17: - | AG17: - | AH17: 3.1780167
B18: 1956-57 | C18: 7.528 | D18: 7.61 | E18: 6.113 | F18: 0.899 | G18: 0.598 | H18: 1.497 | I18: 6.19 | K18: - | L18: 0.391 | M18: - | N18: - | O18: 0.082 | Q18: -0.817 | T18: -0.38 | U18: 0.082 | V18: 0.731 | AA18: 0.032 | AB18: - | AC18: - | AE18: 21.164 | AF18: 21.812 | AG18: - | AH18: 3.3691756
B19: 1957-58 | C19: 7.916 | D19: 7.922 | E19: 6.388 | F19: 0.892 | G19: 0.642 | H19: 1.534 | I19: 6.509 | K19: - | L19: 0.501 | M19: - | N19: - | O19: 0.006 | Q19: -0.886 | T19: -0.468 | U19: 0.006 | V19: 0.769 | AA19: -0.098 | AB19: - | AC19: - | AE19: 22.512 | AF19: 23.008 | AG19: - | AH19: 3.5125448
B20: 1958-59 | C20: 8.319 | D20: 8.39 | E20: 6.766 | F20: 0.951 | G20: 0.673 | H20: 1.624 | I20: 6.892 | K20: - | L20: 0.546 | M20: - | N20: - | O20: 0.071 | Q20: -0.88 | T20: -0.52 | U20: 0.071 | V20: 0.793 | AA20: -0.17 | AB20: - | AC20: - | AE20: 23.339 | AF20: 23.962 | AG20: - | AH20: 3.6320191
B21: 1959-60 | C21: 8.372 | D21: 8.941 | E21: 7.232 | F21: 1.024 | G21: 0.685 | H21: 1.709 | I21: 7.072 | K21: - | L21: 0.363 | M21: - | N21: - | O21: 0.569 | Q21: -0.455 | T21: -0.282 | U21: 0.569 | V21: 0.819 | AA21: 0.057 | AB21: - | AC21: - | AE21: 24.878 | AF21: 25.796 | AG21: - | AH21: 3.6320191
B22: 1960-61 | C22: 8.913 | D22: 9.575 | E22: 7.767 | F22: 1.066 | G22: 0.742 | H22: 1.808 | I22: 7.429 | K22: - | L22: 0.367 | M22: - | N22: - | O22: 0.662 | Q22: -0.404 | T22: -0.211 | U22: 0.662 | V22: 0.887 | AA22: 0.168 | AB22: - | AC22: - | AE22: 26.644 | AF22: 27.588 | AG22: - | AH22: 3.6798088
B23: 1961-62 | C23: 9.98 | D23: 10.59 | E23: 8.486 | F23: 1.239 | G23: 0.865 | H23: 2.104 | I23: 8.4 | K23: - | L23: 0.508 | M23: - | N23: - | O23: 0.61 | Q23: -0.629 | T23: -0.47 | U23: 0.61 | V23: 0.949 | AA23: 0.047 | AB23: - | AC23: - | AE23: 28.147 | AF23: 28.849 | AG23: - | AH23: 3.8470729
B24: 1962-63 | C24: 10.449 | D24: 10.987 | E24: 8.808 | F24: 1.258 | G24: 0.921 | H24: 2.179 | I24: 8.731 | K24: - | L24: 0.55 | M24: - | N24: - | O24: 0.538 | Q24: -0.72 | T24: -0.384 | U24: 0.646 | V24: 0.935 | AA24: 0.067 | AB24: - | AC24: - | AE24: 29.457 | AF24: 30.39 | AG24: - | AH24: 3.9426523
B25: 1963-64 | C25: 11.056 | D25: 11.919 | E25: 9.15 | F25: 1.767 | G25: 1.002 | H25: 2.769 | I25: 9.16 | K25: - | L25: 0.289 | M25: - | N25: - | O25: 0.863 | Q25: -0.904 | T25: 0.303 | U25: 0.989 | V25: 0.984 | AA25: 0.773 | AB25: - | AC25: - | AE25: 31.929 | AF25: 33.349 | AG25: - | AH25: 4.0143369
B26: 1964-65 | C26: 12.257 | D26: 12.908 | E26: 9.724 | F26: 2.096 | G26: 1.088 | H26: 3.184 | I26: 10.137 | K26: - | L26: 0.539 | M26: - | N26: - | O26: 0.651 | Q26: -1.445 | T26: 0.326 | U26: 0.914 | V26: 0.986 | AA26: 0.031 | AB26: - | AC26: - | AE26: 34.864 | AF26: 36.173 | AG26: - | AH26: 4.2054958
B27: 1965-66 | C27: 13.846 | D27: 14.417 | E27: 10.966 | F27: 2.251 | G27: 1.2 | H27: 3.451 | I27: 11.498 | K27: - | L27: 0.662 | M27: - | N27: - | O27: 0.571 | Q27: -1.68 | T27: 0.469 | U27: 0.922 | V27: 1.014 | AA27: 0.457 | AB27: - | AC27: - | AE27: 37.473 | AF27: 38.766 | AG27: - | AH27: 4.4205496
B28: 1966-67 | C28: 15.037 | D28: 15.994 | E28: 11.958 | F28: 2.697 | G28: 1.339 | H28: 4.036 | I28: 12.541 | K28: - | L28: 0.38 | M28: - | N28: - | O28: 0.957 | Q28: -1.74 | T28: 0.743 | U28: 1.166 | V28: 1.115 | AA28: 0.032 | AB28: - | AC28: - | AE28: 39.962 | AF28: 41.161 | AG28: - | AH28: 4.6594982
B29: 1967-68 | C29: 16.615 | D29: 18.252 | E29: 13.419 | F29: 3.386 | G29: 1.447 | H29: 4.833 | I29: 13.861 | K29: - | L29: -0.078 | M29: - | N29: - | O29: 1.637 | Q29: -1.749 | T29: 1.374 | U29: 2.021 | V29: 1.224 | AA29: 0.631 | AB29: - | AC29: - | AE29: 42.52 | AF29: 44.405 | AG29: - | AH29: 4.8028674
... B33: 1971-72 | C33: 24.78 | D33: 25.414 | E33: 19.495 | F33: 3.47 | G33: 2.449 | H33: 5.919 | I33: 20.708 | K33: - | L33: 1.276 | M33: - | N33: - | O33: 0.634 | Q33: -2.836 | T33: 0.488 | U33: 0.85 | V33: 1.544 | AA33: -0.407 | AB33: - | AC33: - | AE33: 64.591 | AF33: 68.145 | AG33: - | AH33: 6.3560335
B34: 1972-73 | C34: 26.524 | D34: 28.437 | E34: 22.036 | F34: 3.634 | G34: 2.767 | H34: 6.401 | I34: 22.053 | K34: - | L34: 0.11 | M34: - | N34: - | O34: 1.913 | Q34: -1.721 | T34: 1.908 | U34: 2.449 | V34: 1.726 | AA34: 1.453 | AB34: - | AC34: - | AE34: 73.942 | AF34: 79.237 | AG34: 2.5446864 | AH34: 6.9295102
B35: 1973-74 | C35: 29.974 | D35: 33.357 | E35: 25.684 | F35: 4.345 | G35: 3.328 | H35: 7.673 | I35: 24.688 | K35: - | L35: -0.871 | M35: - | N35: - | O35: 3.383 | Q35: -0.962 | T35: 2.135 | U35: 4.371 | V35: 2.017 | AA35: 3.034 | AB35: - | AC35: - | AE35: 82.871 | AF35: 88.839 | AG35: 6.5394316 | AH35: 7.5268817
B36: 1974-75 | C36: 38.303 | D36: 43.895 | E36: 34.139 | F36: 5.426 | G36: 4.33 | H36: 9.756 | I36: 31.902 | K36: - | L36: -2.255 | M36: - | N36: - | O36: 5.592 | Q36: 0.166 | T36: 5.094 | U36: 7.987 | V36: 2.372 | X36: 52.1 | AA36: 3.371 | AB36: - | AC36: 53.67 | AE36: 98.192 | AF36: 109.117 | AG36: 3.1047807 | AH36: 9.0561529
B37: 1975-76 | C37: 48.482 | D37: 56.133 | E37: 43.92 | F37: 6.72 | G37: 5.493 | H37: 12.213 | I37: 40.306 | K37: 0.63181964 | L37: -3.622 | M37: -3.3228196 | N37: 7.3518196 | O37: 7.651 | Q37: 0.931 | T37: 8.753 | U37: 10.281 | V37: 3.109 | X37: 64.7 | AA37: 5.09 | AB37: 4.7908196 | AC37: 65.638 | AE37: 120.844 | AF37: 131.155 | AG37: -1.7370637 | AH37: 11.30227
B38: 1976-77 | C38: 57.128 | D38: 64.132 | E38: 51.266 | F38: 6.399 | G38: 6.467 | H38: 12.866 | I38: 46.543 | K38: -0.34295234 | L38: -1.857 | M38: -0.90904766 | N38: 6.0560477 | O38: 7.004 | Q38: 0.605 | T38: 5.839 | U38: 8.246 | V38: 4.079 | X38: 73.6 | AA38: 5.14 | AB38: 4.1920477 | AC38: 75.991 | AE38: 142.072 | AF38: 153.998 | AG38: -0.63964205 | AH38: 12.831541
B39: 1977-78 | C39: 63.759 | D39: 70.183 | E39: 57.555 | F39: 5.233 | G39: 7.395 | H39: 12.628 | I39: 52.516 | K39: 0.58899443 | L39: -0.536 | M39: 0.066005572 | N39: 5.8219944 | O39: 6.424 | Q39: 1.191 | T39: 4.678 | U39: 5.568 | V39: 4.907 | X39: 79.5 | AA39: 5.349 | AB39: 4.7469944 | AC39: 86.357 | AE39: 166.087 | AF39: 179.359 | AG39: -0.46907117 | AH39: 14.599761
B40: 1978-79 | C40: 70.984 | D40: 79.669 | E40: 66.071 | F40: 5.243 | G40: 8.355 | H40: 13.598 | I40: 58.432 | K40: 4.7630931 | L40: -2.027 | M40: -3.3480931 | N40: 10.006093 | O40: 8.685 | Q40: 3.442 | T40: 7.755 | U40: 9.029 | V40: 5.856 | X40: 88.6 | AA40: 7.24 | AB40: 8.5610931 | AC40: 96.731 | AE40: 192.341 | AF40: 210.039 | AG40: 1.5613273 | AH40: 16.248507
B41: 1979-80 | C41: 86.677 | D41: 95.223 | E41: 79.491 | F41: 5.876 | G41: 9.856 | H41: 15.732 | I41: 72.543 | K41: 3.2822834 | L41: -0.162 | M41: -0.77428343 | N41: 9.1582834 | O41: 8.546 | Q41: 2.67 | T41: 8.064 | U41: 9.723 | V41: 7.587 | X41: 98.2 | AA41: 6.072 | AB41: 6.6842834 | AC41: 107.499 | AE41: 232.557 | AF41: 251.26 | AG41: -0.097964602 | AH41: 19.020311
B42: 1980-81 | C42: 102.984 | D42: 114.521 | E42: 96.636 | F42: 6.018 | G42: 11.867 | H42: 17.885 | I42: 85.908 | K42: 1.6986928 | L42: -1.489 | M42: 2.3313072 | N42: 7.7166928 | O42: 11.537 | Q42: 5.519 | T42: 12.497 | U42: 12.267 | V42: 9.163 | X42: 113.8 | AA42: 8.953 | AB42: 5.1326928 | AC42: 126.222 | AE42: 267.548 | AF42: 282.412 | AG42: -2.8166062 | AH42: 22.628435
B43: 1981-82 | C43: 121.922 | D43: 127.921 | E43: 110.587 | F43: 4.368 | G43: 12.966 | H43: 17.334 | I43: 101.48 | K43: -4.7764327 | L43: 5.746 | M43: 12.153433 | N43: -0.40843274 | O43: 5.999 | Q43: 1.631 | T43: 7.635 | U43: 8.672 | V43: 11.232 | X43: 125.2 | AA43: 8.318 | AB43: 1.9105673 | AC43: 133.648 | AE43: 298.739 | AF43: 313.329 | AG43: -3.1630102 | AH43: 24.994026
B44: 1982-83 | C44: 132.879 | D44: 141.421 | E44: 121.436 | F44: 6.337 | G44: 13.648 | H44: 19.985 | I44: 110.421 | K44: -4.3162036 | L44: 3.366 | M44: 9.8872036 | N44: 2.0207964 | O44: 8.542 | Q44: 2.205 | T44: 12.819 | U44: 8.998 | V44: 12.087 | X44: 132.5 | AA44: 8.705 | AB44: 2.1837964 | AC44: 142.889 | AE44: 327.91 | AF44: 343.235 | AG44: -2.7122309 | AH44: 26.88172
B45: 1983-84 | C45: 141.361 | D45: 153.163 | E45: 131.027 | F45: 7.83 | G45: 14.306 | H45: 22.136 | I45: 118.31 | K45: -0.64220296 | L45: 0.581 | M45: 5.195203 | N45: 7.187797 | O45: 11.802 | Q45: 3.972 | T45: 12.288 | U45: 9.795 | V45: 13.225 | X45: 143.6 | AA45: 11.76 | AB45: 7.145797 | AC45: 155.148 | AE45: 358.644 | AF45: 370.538 | AG45: -1.4882459 | AH45: 28.100358
B46: 1984-85 | C46: 151.365 | D46: 163.9 | E46: 141.819 | F46: 7.468 | G46: 14.613 | H46: 22.081 | I46: 129.747 | K46: 3.1955958 | L46: 1.42 | M46: 3.2914042 | N46: 10.663596 | O46: 12.535 | Q46: 5.067 | T46: 10.274 | U46: 10.259 | V46: 14.72 | X46: 157 | AA46: 11.057 | AB46: 9.1855958 | AC46: 166.482 | AE46: 386.718 | AF46: 406.585 | AG46: -0.37254084 | AH46: 29.772999
B47: 1985-86 | C47: 162.245 | D47: 171.279 | E47: 150.561 | F47: 6.331 | G47: 14.387 | H47: 20.718 | I47: 138.577 | K47: 2.6347637 | L47: 5.551 | M47: 5.6192363 | N47: 8.9657637 | O47: 9.034 | Q47: 2.703 | T47: 11.114 | U47: 5.739 | V47: 16.601 | X47: 162.5 | AA47: 9.649 | AB47: 9.5807637 | AC47: 179.283 | AE47: 424.559 | AF47: 439.123 | AG47: 0.11687178 | AH47: 31.397849
B48: 1986-87 | C48: 170.221 | D48: 178.961 | E48: 158.854 | F48: 4.283 | G48: 15.824 | H48: 20.107 | I48: 147.979 | K48: 5.1559441 | L48: 6.179 | M48: 5.4800559 | N48: 9.4389441 | O48: 8.74 | Q48: 4.457 | T48: 10.433 | U48: 3.687 | V48: 17.36 | X48: 167.8 | AA48: 9.714 | AB48: 10.412944 | AC48: 190.684 | AE48: 456.205 | AF48: 482.448 | AG48: 0.25966798 | AH48: 32.664277
... B58: 1996-97 | C58: 299.319 | D58: 328.243 | E58: 303.275 | F58: 4.244 | G58: 20.724 | H58: 24.968 | I58: 273.893 | K58: 22.47309 | L58: -4.718 | M58: -2.5110898 | N58: 26.71709 | O58: 28.924 | Q58: 24.68 | T58: 25.105 | U58: 22.621 | V58: 27.991 | X58: 347 | AA58: 30.835 | AB58: 28.62809 | AC58: 408.366 | AE58: 926.554 | AF58: 954.271 | AG58: -0.18763206 | AH58: 52.520908
B59: 1997-98 | C59: 333.672 | D59: 344.206 | E59: 316.819 | F59: 6.151 | G59: 21.236 | H59: 27.387 | I59: 301.039 | K59: 9.8937316 | L59: 14.957 | M59: 9.4462684 | N59: 16.044732 | O59: 10.534 | Q59: 4.383 | T59: 3.543 | U59: 0.901 | V59: 29.82 | X59: 360.4 | Y59: 361.2 | AA59: 9.546 | AB59: 15.056732 | AC59: 412.278 | AE59: 970.388 | AF59: 988.45 | AG59: 1.2108318 | AH59: 52.664277
B60: 1998-99 | C60: 354.694 | D60: 354.817 | E60: 326.466 | F60: 6.429 | G60: 21.922 | H60: 28.351 | I60: 321.166 | K60: 0.8266093 | L60: 24.907 | M60: 17.774391 | N60: 7.2556093 | O60: 0.123 | Q60: -6.306 | T60: -4.545 | U60: -7.688 | V60: 29.442 | X60: 363.1 | Y60: 364 | AA60: -1.273 | AB60: 5.8596093 | AC60: 415.121 | AE60: 1014.098 | AF60: 1035.612 | AG60: 0.92235761 | AH60: 53.428913
B61: 1999-00 | C61: 378.515 | D61: 367.111 | E61: 338.083 | F61: 5.97 | G61: 23.058 | H61: 29.028 | I61: 344.323 | K61: -10.777719 | L61: 33.513 | M61: 26.916719 | N61: -4.8077189 | O61: -11.404 | Q61: -17.374 | R61: 299.659 | T61: -9.137 | U61: -8.76 | V61: 25.899 | X61: 353.3 | Y61: 354.4 | Z61: 357.605 | AA61: -11.285 | AB61: -4.6887189 | AC61: 408.327 | AE61: 1060.973 | AF61: 1092.097 | AG61: 0.87449691 | AH61: 54.050179
B62: 2000-01 | C62: 406.412 | D62: 390.117 | E62: 360.497 | F62: 5.562 | G62: 24.058 | H62: 29.62 | I62: 368.484 | K62: -12.803127 | L62: 37.565 | M62: 28.511127 | N62: -7.2411267 | O62: -16.295 | Q62: -21.857 | R62: 306.701 | T62: -35.569 | U62: -38.028 | V62: 26.891 | X62: 322 | Y62: 323.2 | Z62: 377.819 | AA62: -15.523 | AB62: -6.4691267 | AC62: 398.365 | AE62: 1117.633 | AF62: 1141.518 | AG62: 1.2703884 | AH62: 54.551971
B63: 2001-02 | C63: 412.411 | D63: 418.046 | E63: 379.226 | F63: 13.439 | G63: 25.381 | H63: 38.82 | I63: 374.529 | K63: -0.80460534 | L63: 13.956 | M63: 6.9566053 | N63: 12.634395 | O63: 5.635 | Q63: -7.804 | R63: 333.739 | T63: 2.771 | U63: 3.995 | V63: 23.015 | X63: 330.6 | Y63: 331.8 | Z63: 409.75 | AA63: 4.944 | AB63: 11.943395 | AC63: 397.654 | AE63: 1159.585 | AF63: 1181.628 | AG63: 0.69906871 | AH63: 55.651135
B64: 2002-03 | C64: 417.783 | D64: 452.798 | E64: 407.403 | F64: 18.459 | G64: 26.936 | H64: 45.395 | I64: 380.164 | K64: 18.693042 | L64: -15.059 | M64: -17.196042 | N64: 37.152042 | O64: 35.015 | Q64: 16.556 | R64: 388.404 | T64: 21.751 | U64: 23.382 | V64: 21.748 | X64: 369.2 | Y64: 370.3 | Z64: 464.178 | AA64: 30.427 | AB64: 32.564042 | AC64: 422.005 | AE64: 1210.146 | AF64: 1241.798 | AG64: 0.073560053 | AH64: 56.774194
B65: 2003-04 | C65: 450.875 | D65: 494.397 | E65: 444.904 | F65: 21.698 | G65: 27.795 | H65: 49.493 | I65: 411.702 | K65: 24.463909 | L65: -21.125 | M65: -23.764909 | N65: 46.161909 | O65: 43.522 | Q65: 21.824 | R65: 409.014 | T65: 39.391 | U65: 39.985 | V65: 23.221 | X65: 404.5 | Y65: 405.9 | Z65: 494.695 | AA65: 37.511 | AB65: 40.150909 | AC65: 467.675 | AE65: 1277.594 | AF65: 1311.875 | AG65: 0.38383864 | AH65: 58.18399
B66: 2004-05 | C66: 483.215 | D66: 534.877 | E66: 478.073 | F66: 27.502 | G66: 29.302 | H66: 56.804 | I66: 442.165 | K66: 28.444142 | L66: -27.466 | M66: -31.750142 | N66: 55.946142 | O66: 51.662 | Q66: 24.16 | R66: 459.695 | T66: 41.111 | U66: 42.364 | V66: 25.885 | X66: 460.9 | Y66: 462.4 | Z66: 520.154 | AA66: 44.538 | AB66: 48.822142 | AC66: 525.618 | AE66: 1346.417 | AF66: 1381.902 | AG66: 0.48284129 | AH66: 59.928315
B67: 2005-06 | C67: 519.728 | D67: 565.1 | E67: 507.201 | F67: 26.396 | G67: 31.503 | H67: 57.899 | I67: 473.17 | K67: 22.613751 | L67: -19.982 | M67: -23.619751 | N67: 49.009751 | O67: 45.372 | Q67: 18.976 | R67: 471.421 | T67: 43.04 | U67: 43.04 | V67: 27.797 | X67: 499.4 | Y67: 501.6 | Z67: 517.862 | AA67: 41.962 | AB67: 45.599751 | AC67: 574.744 | AE67: 1423.557 | AF67: 1461.229 | AG67: 0.31794263 | AH67: 61.553166
B68: 2006-07 | C68: 551.501 | D68: 592.438 | E68: 531.892 | F68: 27.078 | G68: 33.468 | H68: 60.546 | I68: 502.328 | K68: 14.867291 | L68: -12.986 | M68: -13.994291 | N68: 41.945291 | O68: 40.937 | Q68: 13.859 | R68: 494.652 | T68: 37.442 | U68: 35.755 | V68: 30.763 | X68: 535.2 | Y68: 537.2 | Z68: 542.518 | AA68: 38.547 | AB68: 39.555291 | AC68: 618.021 | AE68: 1493.448 | AF68: 1532.173 | AG68: 0.0078515864 | AH68: 63.416965
B69: 2007-08 | C69: 584.146 | D69: 629.199 | E69: 565.261 | F69: 28.63 | G69: 35.308 | H69: 63.938 | I69: 528.843 | K69: 21.823011 | L69: -17.185 | M69: -22.585011 | N69: 50.453011 | O69: 45.053 | Q69: 16.423 | R69: 544.843 | T69: 33.263 | U69: 29.123 | V69: 33.699 | X69: 567.2 | Y69: 569.3 | Z69: 609.022 | AA69: 45.218 | AB69: 50.618011 | AC69: 661.926 | AE69: 1571.927 | AF69: 1599.232 | AG69: 0.6839156 | AH69: 64.635603
B70: 2008-09 | C70: 569.48 | D70: 685.772 | E70: 598.947 | F70: 48.556 | G70: 38.269 | H70: 86.825 | I70: 510.197 | K70: 62.232129 | L70: -85.675 | M70: -80.171129 | N70: 110.78813 | O70: 116.292 | Q70: 67.736 | R70: 739.66 | T70: 163.829 | U70: 173.91 | V70: 33.518 | X70: 787.2 | Y70: 787.7 | Z70: 765.117 | AA70: 106.928 | AB70: 101.42413 | AC70: 847.407 | AE70: 1593.267 | AF70: 1566.77 | AG70: -0.96445749 | AH70: 67.072879
B71: 2009-10 | C71: 560.698 | D71: 720.343 | E71: 632.602 | F71: 47.708 | G71: 40.033 | H71: 87.741 | I71: 503.858 | K71: 84.527485 | L71: -128.313 | M71: -100.90348 | N71: 132.23548 | O71: 159.645 | Q71: 111.937 | R71: 867.406 | T71: 198.592 | U71: 200.777 | V71: 28.059 | X71: 1027.9 | Y71: 1015.4 | Z71: 887.796 | AA71: 156.175 | AB71: 128.76548 | AC71: 1102.32 | AE71: 1567.07 | AF71: 1596.478 | AG71: -3.1124034 | AH71: 67.933094
B72: 2010-11 | C72: 601.037 | D72: 743.023 | E72: 661.304 | F72: 40.913 | G72: 40.806 | H72: 81.719 | I72: 540.866 | K72: 71.427472 | L72: -100.049 | M72: -70.403472 | N72: 112.34047 | O72: 141.986 | Q72: 101.073 | R72: 970.167 | T72: 134.013 | U72: 126.043 | V72: 41.004 | X72: 1168.7 | Y72: 1164.1 | Z72: 825.297 | AA72: 143.143 | AB72: 113.49747 | AC72: 1240.638 | AE72: 1632.926 | AF72: 1654.846 | AG72: -2.3860088 | AH72: 69.103943
... B91: 2029-30 | C91: 1445.0065 | D91: 1519.0489 | E91: 1351.1647 | F91: 83.974012 | G91: 83.910202 | H91: 167.88421 | I91: 1300.3608 | K91: -9.9318251 | L91: 35.512066 | M91: 35.512269 | N91: 74.042187 | O91: 74.04239 | Q91: -9.9316225 | R91: 2918.8394 | T91: 110.12621 | U91: 107.43677 | V91: 131.57704 | X91: 3391.3069 | Y91: 3351.2341 | Z91: 2439.8569 | AA91: 95.853207 | AB91: 95.853005 | AC91: 3668.0838 | AE91: 3464.0106 | AF91: 3528.4196 | AG91: -8.3554894e-06 | AH91: 110.58606
B92: Notes: | C92: Outturn fiscal data consistent with the ONS/HM Treasury Public Sector Finances Statistical Bulletin released on 21 October 2025.
C93: Forecast years from 2025-26 are consistent with the OBR Economic and fiscal outlook forecast published March 2025.
C94: A full list of sources is available in the glossary.
C95: Cyclically adjusted aggregates are OBR calculations based on estimates of the size of the output gap. For more information see Working paper No. 3: Cyclically-adjusting the public finances (https://obr.uk/download/working-paper-no-3-cyclically-adjusting-the-public-finances/)

Sheet Aggregates (per cent of GDP)
C1: Per cent of GDP1
C3: Receipts and expenditure | K3: Deficit | Q3: Fiscal targets | T3: Financing | X3: Other Debt and Deficit measures | AE3: Economic indicators
C4: Public sector current receipts | D4: Total managed expenditure | E4: Public sector current expenditure | F4: Public sector net investment | G4: Depreciation | H4: Public sector gross investment | I4: National account taxes | K4: Cyclically-adjusted current budget deficit | L4: Primary balance | M4: Cyclically-adjusted primary balance | N4: Cyclically-adjusted net borrowing | O4: Public sector net borrowing | Q4: Current budget deficit | R4: Public sector net financial liabilities | T4: Central government net cash requirement | U4: Public sector net cash requirement | V4: Central government debt interest, net of APF | X4: Public sector net debt2 | Y4: Public sector net debt (ex BOE)2 | Z4: Public sector net worth (inverted) | AA4: General government net borrowing | AB4: Cyclically-adjusted general government net borrowing | AC4: General Government Gross Debt | AE4: Nominal GDP (£ billion) | AF4: Nominal GDP, centred end-March (£ billion) | AG4: Output gap (per cent of GDP) | BS4: Forecast
B5: 1948-49 | C5: 42.940919 | D5: 38.599562 | E5: 33.234136 | F5: 2.6345733 | G5: 2.7308534 | H5: 5.3654267 | I5: 37.207877 | K5: - | L5: 7.6936543 | M5: - | N5: - | O5: -4.3413567 | Q5: -6.97593 | T5: -5.9256018 | U5: -4.3413567 | V5: 4.5514223 | X5: - | AA5: -3.7986871 | AB5: - | AC5: - | AE5: 11.425 | AF5: - | AG5: -
B6: 1949-50 | C6: 43.298545 | D6: 38.474813 | E6: 32.780015 | F6: 2.9912072 | G6: 2.7035911 | H6: 5.6947983 | I6: 36.929904 | K6: - | L6: 7.8724628 | M6: - | N6: - | O6: -4.8237324 | Q6: -7.8149396 | T6: -6.5247761 | U6: -4.8237324 | V6: 4.2649355 | X6: - | AA6: -4.2320651 | AB6: - | AC6: - | AE6: 12.169 | AF6: - | AG6: -
B7: 1950-51 | C7: 42.841444 | D7: 39.183673 | E7: 32.629513 | F7: 3.7598116 | G7: 2.7943485 | H7: 6.5541601 | I7: 36.075353 | K7: - | L7: 6.4678179 | M7: - | N7: - | O7: -3.6577708 | Q7: -7.4175824 | T7: -5.8477237 | U7: -3.6577708 | V7: 4.1679749 | X7: - | AA7: -3.2731554 | AB7: - | AC7: - | AE7: 12.74 | AF7: - | AG7: -
B8: 1951-52 | C8: 41.131231 | D8: 40.648815 | E8: 32.300916 | F8: 5.4394183 | G8: 2.9084807 | H8: 8.347899 | I8: 34.782913 | K8: - | L8: 3.4118716 | M8: - | N8: - | O8: -0.48241628 | Q8: -5.9218346 | T8: -2.6847515 | U8: -0.48241628 | V8: 4.0481018 | X8: - | AA8: -0.0069915402 | AB8: - | AC8: - | AE8: 14.303 | AF8: - | AG8: -
B9: 1952-53 | C9: 39.926622 | D9: 41.271885 | E9: 32.537333 | F9: 5.7736869 | G9: 2.9608651 | H9: 8.734552 | I9: 33.953399 | K9: - | L9: 1.911689 | M9: - | N9: - | O9: 1.3452626 | Q9: -4.4284243 | T9: -1.930999 | U9: 1.3452626 | V9: 4.0808445 | X9: - | AA9: 0.99124614 | AB9: - | AC9: - | AE9: 15.536 | AF9: - | AG9: -
B10: 1953-54 | C10: 37.998202 | D10: 40.503446 | E10: 31.603236 | F10: 6.0593347 | G10: 2.840875 | H10: 8.9002098 | I10: 31.705124 | K10: - | L10: 0.45549895 | M10: - | N10: - | O10: 2.5052442 | Q10: -3.5540905 | T10: -0.94695835 | U10: 2.5052442 | V10: 3.9376686 | X10: - | AA10: 1.7620617 | AB10: - | AC10: - | AE10: 16.685 | AF10: - | AG10: -
B11: 1954-55 | C11: 37.46378 | D11: 38.923925 | E11: 31.123232 | F11: 4.965627 | G11: 2.8350662 | H11: 7.8006931 | I11: 30.913016 | K11: - | L11: 1.0794841 | M11: - | N11: - | O11: 1.4601443 | Q11: -3.5054826 | T11: -1.7442191 | U11: 1.4601443 | V11: 3.727061 | X11: - | AA11: 0.64200898 | AB11: - | AC11: - | AE11: 17.601 | AF11: - | AG11: -
B12: 1955-56 | C12: 35.96424 | D12: 35.770115 | E12: 28.664112 | F12: 4.311622 | G12: 2.7943806 | H12: 7.1060026 | I12: 29.644955 | K12: - | L12: 2.7535121 | M12: - | N12: - | O12: -0.19412516 | Q12: -4.5057471 | T12: -2.8403576 | U12: -0.19412516 | V12: 3.7905492 | X12: - | AA12: -0.55172414 | AB12: - | AC12: - | AE12: 19.575 | AF12: - | AG12: -
B13: 1956-57 | C13: 35.569836 | D13: 35.957286 | E13: 28.883954 | F13: 4.2477792 | G13: 2.8255528 | H13: 7.0733321 | I13: 29.247779 | K13: - | L13: 1.8474768 | M13: - | N13: - | O13: 0.38745039 | Q13: -3.8603289 | T13: -1.7955018 | U13: 0.38745039 | V13: 3.4539785 | X13: - | AA13: 0.15120015 | AB13: - | AC13: - | AE13: 21.164 | AF13: 21.812 | AG13: -
B14: 1957-58 | C14: 35.163468 | D14: 35.190121 | E14: 28.375977 | F14: 3.9623312 | G14: 2.8518124 | H14: 6.8141436 | I14: 28.913468 | K14: - | L14: 2.2254797 | M14: - | N14: - | O14: 0.026652452 | Q14: -3.9356787 | T14: -2.0788913 | U14: 0.026652452 | V14: 3.4159559 | X14: - | AA14: -0.43532338 | AB14: - | AC14: - | AE14: 22.512 | AF14: 23.008 | AG14: -
B15: 1958-59 | C15: 35.644201 | D15: 35.948413 | E15: 28.990102 | F15: 4.0747247 | G15: 2.8835854 | H15: 6.9583101 | I15: 29.529971 | K15: - | L15: 2.3394319 | M15: - | N15: - | O15: 0.30421183 | Q15: -3.7705129 | T15: -2.2280303 | U15: 0.30421183 | V15: 3.3977463 | X15: - | AA15: -0.72839453 | AB15: - | AC15: - | AE15: 23.339 | AF15: 23.962 | AG15: -
B16: 1959-60 | C16: 33.652223 | D16: 35.939384 | E16: 29.069861 | F16: 4.1160865 | G16: 2.7534368 | H16: 6.8695233 | I16: 28.426722 | K16: - | L16: 1.4591205 | M16: - | N16: - | O16: 2.2871613 | Q16: -1.8289252 | T16: -1.1335316 | U16: 2.2871613 | V16: 3.2920653 | X16: - | AA16: 0.2291181 | AB16: - | AC16: - | AE16: 24.878 | AF16: 25.796 | AG16: -
B17: 1960-61 | C17: 33.452184 | D17: 35.936796 | E17: 29.151028 | F17: 4.0009008 | G17: 2.7848671 | H17: 6.7857679 | I17: 27.88245 | K17: - | L17: 1.3774208 | M17: - | N17: - | O17: 2.4846119 | Q17: -1.5162888 | T17: -0.79192313 | U17: 2.4846119 | V17: 3.3290797 | X17: - | AA17: 0.63053596 | AB17: - | AC17: - | AE17: 26.644 | AF17: 27.588 | AG17: -
B18: 1961-62 | C18: 35.456709 | D18: 37.623903 | E18: 30.148861 | F18: 4.4018901 | G18: 3.0731517 | H18: 7.4750417 | I18: 29.843323 | K18: - | L18: 1.8048105 | M18: - | N18: - | O18: 2.1671937 | Q18: -2.2346964 | T18: -1.669805 | U18: 2.1671937 | V18: 3.3715849 | X18: - | AA18: 0.1669805 | AB18: - | AC18: - | AE18: 28.147 | AF18: 28.849 | AG18: -
B19: 1962-63 | C19: 35.472044 | D19: 37.298435 | E19: 29.901212 | F19: 4.2706318 | G19: 3.1265913 | H19: 7.3972231 | I19: 29.639814 | K19: - | L19: 1.8671284 | M19: - | N19: - | O19: 1.826391 | Q19: -2.4442408 | T19: -1.3035951 | U19: 2.1930271 | V19: 3.1741182 | X19: - | AA19: 0.22745018 | AB19: - | AC19: - | AE19: 29.457 | AF19: 30.39 | AG19: -
B20: 1963-64 | C20: 34.626828 | D20: 37.3297 | E20: 28.657333 | F20: 5.5341539 | G20: 3.1382129 | H20: 8.6723668 | I20: 28.688653 | K20: - | L20: 0.90513326 | M20: - | N20: - | O20: 2.702872 | Q20: -2.8312819 | T20: 0.94898055 | U20: 3.0974976 | V20: 3.0818378 | X20: - | AA20: 2.4209966 | AB20: - | AC20: - | AE20: 31.929 | AF20: 33.349 | AG20: -
B21: 1964-65 | C21: 35.156609 | D21: 37.023864 | E21: 27.891235 | F21: 6.0119321 | G21: 3.1206976 | H21: 9.1326296 | I21: 29.075838 | K21: - | L21: 1.5460073 | M21: - | N21: - | O21: 1.8672556 | Q21: -4.1446765 | T21: 0.93506196 | U21: 2.6216154 | V21: 2.8281322 | X21: - | AA21: 0.088916934 | AB21: - | AC21: - | AE21: 34.864 | AF21: 36.173 | AG21: -
B22: 1965-66 | C22: 36.94927 | D22: 38.473034 | E22: 29.263737 | F22: 6.0069917 | G22: 3.2023057 | H22: 9.2092974 | I22: 30.683425 | K22: - | L22: 1.7666053 | M22: - | N22: - | O22: 1.5237638 | Q22: -4.4832279 | T22: 1.2515678 | U22: 2.4604382 | V22: 2.7059483 | X22: - | AA22: 1.2195447 | AB22: - | AC22: - | AE22: 37.473 | AF22: 38.766 | AG22: -
B23: 1966-67 | C23: 37.628247 | D23: 40.023022 | E23: 29.923427 | F23: 6.7489115 | G23: 3.3506831 | H23: 10.099595 | I23: 31.382313 | K23: - | L23: 0.95090336 | M23: - | N23: - | O23: 2.394775 | Q23: -4.3541364 | T23: 1.8592663 | U23: 2.9177719 | V23: 2.7901506 | X23: - | AA23: 0.080076072 | AB23: - | AC23: - | AE23: 39.962 | AF23: 41.161 | AG23: -
B24: 1967-68 | C24: 39.075729 | D24: 42.925682 | E24: 31.559266 | F24: 7.9633114 | G24: 3.4031044 | H24: 11.366416 | I24: 32.598777 | K24: - | L24: -0.18344309 | M24: - | N24: - | O24: 3.849953 | Q24: -4.1133584 | T24: 3.2314205 | U24: 4.7530574 | V24: 2.8786453 | X24: - | AA24: 1.4840075 | AB24: - | AC24: - | AE24: 42.52 | AF24: 44.405 | AG24: -
... B28: 1971-72 | C28: 38.364478 | D28: 39.346039 | E28: 30.182224 | F28: 5.3722655 | G28: 3.7915499 | H28: 9.1638154 | I28: 32.060194 | K28: - | L28: 1.9755074 | M28: - | N28: - | O28: 0.9815609 | Q28: -4.3907046 | T28: 0.75552322 | U28: 1.3159728 | V28: 2.3904259 | X28: - | AA28: -0.63011875 | AB28: - | AC28: - | AE28: 64.591 | AF28: 68.145 | AG28: -
B29: 1972-73 | C29: 35.871359 | D29: 38.458522 | E29: 29.801736 | F29: 4.9146628 | G29: 3.7421222 | H29: 8.656785 | I29: 29.824727 | K29: - | L29: 0.14876525 | M29: - | N29: - | O29: 2.5871629 | Q29: -2.3274999 | T29: 2.5804009 | U29: 3.3120554 | V29: 2.334262 | X29: - | AA29: 1.9650537 | AB29: - | AC29: - | AE29: 73.942 | AF29: 79.237 | AG29: 2.5446864
B30: 1973-74 | C30: 36.169468 | D30: 40.251717 | E30: 30.992748 | F30: 5.2430887 | G30: 4.0158801 | H30: 9.2589688 | I30: 29.79088 | K30: - | L30: -1.0510311 | M30: - | N30: - | O30: 4.0822483 | Q30: -1.1608403 | T30: 2.5762933 | U30: 5.2744627 | V30: 2.4339033 | X30: - | AA30: 3.6611118 | AB30: - | AC30: - | AE30: 82.871 | AF30: 88.839 | AG30: 6.5394316
B31: 1974-75 | C31: 39.00827 | D31: 44.703234 | E31: 34.767598 | F31: 5.5259084 | G31: 4.4097279 | H31: 9.9356363 | I31: 32.489409 | K31: - | L31: -2.2965211 | M31: - | N31: - | O31: 5.694965 | Q31: 0.16905654 | T31: 5.1877953 | U31: 8.1340639 | V31: 2.4156754 | X31: 47.746914 | AA31: 3.4330699 | AB31: - | AC31: 54.658221 | AE31: 98.192 | AF31: 109.117 | AG31: 3.1047807
B32: 1975-76 | C32: 40.119493 | D32: 46.450796 | E32: 36.344378 | F32: 5.5608884 | G32: 4.5455298 | H32: 10.106418 | I32: 33.353745 | K32: 0.52283906 | L32: -2.9972527 | M32: -2.749677 | N32: 6.0837275 | O32: 6.3313032 | Q32: 0.77041475 | T32: 7.2432227 | U32: 8.5076628 | V32: 2.5727384 | X32: 49.330944 | AA32: 4.212042 | AB32: 3.9644663 | AC32: 54.316309 | AE32: 120.844 | AF32: 131.155 | AG32: -1.7370637
B33: 1976-77 | C33: 40.210597 | D33: 45.140492 | E33: 36.084521 | F33: 4.5040543 | G33: 4.5519173 | H33: 9.0559716 | I33: 32.76015 | K33: -0.24139334 | L33: -1.3070837 | M33: -0.63984998 | N33: 4.2626609 | O33: 4.9298947 | Q33: 0.42584042 | T33: 4.1098879 | U33: 5.8040993 | V33: 2.8710795 | X33: 47.792828 | AA33: 3.6178839 | AB33: 2.9506501 | AC33: 53.487668 | AE33: 142.072 | AF33: 153.998 | AG33: -0.63964205
B34: 1977-78 | C34: 38.388917 | D34: 42.256769 | E34: 34.653525 | F34: 3.1507583 | G34: 4.4524857 | H34: 7.6032441 | I34: 31.619573 | K34: 0.35463006 | L34: -0.32272243 | M34: 0.039741564 | N34: 3.5053884 | O34: 3.8678524 | Q34: 0.71709405 | T34: 2.8165961 | U34: 3.3524599 | V34: 2.9544757 | X34: 44.324511 | AA34: 3.2206013 | AB34: 2.8581373 | AC34: 51.995039 | AE34: 166.087 | AF34: 179.359 | AG34: -0.46907117
B35: 1978-79 | C35: 36.905288 | D35: 41.420706 | E35: 34.35097 | F35: 2.7258879 | G35: 4.3438476 | H35: 7.0697355 | I35: 30.379378 | K35: 2.4763795 | L35: -1.0538575 | M35: -1.7407069 | N35: 5.2022674 | O35: 4.5154179 | Q35: 1.7895301 | T35: 4.0319017 | U35: 4.694267 | V35: 3.0445927 | X35: 42.182642 | AA35: 3.764148 | AB35: 4.4509975 | AC35: 50.29141 | AE35: 192.341 | AF35: 210.039 | AG35: 1.5613273
B36: 1979-80 | C36: 37.271293 | D36: 40.946091 | E36: 34.181297 | F36: 2.5266924 | G36: 4.2381008 | H36: 6.7647931 | I36: 31.193643 | K36: 1.4113888 | L36: -0.069660341 | M36: -0.33294351 | N36: 3.9380812 | O36: 3.674798 | Q36: 1.1481056 | T36: 3.467537 | U36: 4.1809105 | V36: 3.262426 | X36: 39.083022 | AA36: 2.6109728 | AB36: 2.874256 | AC36: 46.224797 | AE36: 232.557 | AF36: 251.26 | AG36: -0.097964602
B37: 1980-81 | C37: 38.491785 | D37: 42.803908 | E37: 36.119126 | F37: 2.249316 | G37: 4.4354658 | H37: 6.6847818 | I37: 32.109379 | K37: 0.63491141 | L37: -0.55653565 | M37: 0.87136036 | N37: 2.8842274 | O37: 4.3121234 | Q37: 2.0628074 | T37: 4.6709376 | U37: 4.5849717 | V37: 3.424806 | X37: 40.295738 | AA37: 3.3463154 | AB37: 1.9184194 | AC37: 47.177329 | AE37: 267.548 | AF37: 282.412 | AG37: -2.8166062
B38: 1981-82 | C38: 40.812214 | D38: 42.820321 | E38: 37.017932 | F38: 1.4621459 | G38: 4.3402435 | H38: 5.8023894 | I38: 33.969452 | K38: -1.5988648 | L38: 1.9234181 | M38: 4.0682444 | N38: -0.13671892 | O38: 2.0081074 | Q38: 0.54596152 | T38: 2.5557426 | U38: 2.9028684 | V38: 3.7598037 | X38: 39.957999 | AA38: 2.7843703 | AB38: 0.63954397 | AC38: 44.737379 | AE38: 298.739 | AF38: 313.329 | AG38: -3.1630102
B39: 1982-83 | C39: 40.523009 | D39: 43.127992 | E39: 37.033332 | F39: 1.9325425 | G39: 4.1621177 | H39: 6.0946601 | I39: 33.674179 | K39: -1.3162769 | L39: 1.0265012 | M39: 3.0152187 | N39: 0.61626556 | O39: 2.6049831 | Q39: 0.67244061 | T39: 3.9093044 | U39: 2.7440456 | V39: 3.6860724 | X39: 38.603289 | AA39: 2.6546918 | AB39: 0.66597433 | AC39: 43.575676 | AE39: 327.91 | AF39: 343.235 | AG39: -2.7122309
B40: 1983-84 | C40: 39.415409 | D40: 42.706138 | E40: 36.534 | F40: 2.1832235 | G40: 3.9889138 | H40: 6.1721373 | I40: 32.988144 | K40: -0.17906419 | L40: 0.16199909 | M40: 1.4485682 | N40: 2.0041593 | O40: 3.2907284 | Q40: 1.1075049 | T40: 3.4262388 | U40: 2.7311206 | V40: 3.6875007 | X40: 38.75446 | AA40: 3.2790176 | AB40: 1.9924485 | AC40: 43.259611 | AE40: 358.644 | AF40: 370.538 | AG40: -1.4882459
B41: 1984-85 | C41: 39.140924 | D41: 42.382304 | E41: 36.672459 | F41: 1.9311229 | G41: 3.7787225 | H41: 5.7098454 | I41: 33.550804 | K41: 0.82633749 | L41: 0.36719263 | M41: 0.85111222 | N41: 2.7574604 | O41: 3.24138 | Q41: 1.3102571 | T41: 2.6567163 | U41: 2.6528375 | V41: 3.8063912 | X41: 38.614312 | AA41: 2.8591894 | AB41: 2.3752698 | AC41: 43.049974 | AE41: 386.718 | AF41: 406.585 | AG41: -0.37254084
B42: 1985-86 | C42: 38.214948 | D42: 40.342803 | E42: 35.462916 | F42: 1.4911944 | G42: 3.3886927 | H42: 4.8798871 | I42: 32.640222 | K42: 0.62058835 | L42: 1.3074743 | M42: 1.3235466 | N42: 2.1117827 | O42: 2.127855 | Q42: 0.63666063 | T42: 2.6177752 | U42: 1.3517556 | V42: 3.910175 | X42: 37.005577 | AA42: 2.2727112 | AB42: 2.2566389 | AC42: 42.228053 | AE42: 424.559 | AF42: 439.123 | AG42: 0.11687178
B43: 1986-87 | C43: 37.312392 | D43: 39.228198 | E43: 34.820749 | F43: 0.93883232 | G43: 3.4686161 | H43: 4.4074484 | I43: 32.436953 | K43: 1.1301814 | L43: 1.354435 | M43: 1.2012266 | N43: 2.0690137 | O43: 1.9158054 | Q43: 0.97697307 | T43: 2.2869105 | U43: 0.8081893 | V43: 3.8053068 | X43: 34.78095 | AA43: 2.1293059 | AB43: 2.2825142 | AC43: 41.797876 | AE43: 456.205 | AF43: 482.448 | AG43: 0.25966798
... B55: 1998-99 | C55: 34.976304 | D55: 34.988433 | E55: 32.192747 | F55: 0.6339624 | G55: 2.161724 | H55: 2.7956864 | I55: 31.670115 | K55: 0.081511777 | L55: 2.4560743 | M55: 1.7527291 | N55: 0.71547417 | O55: 0.012129005 | Q55: -0.62183339 | T55: -0.44818154 | U55: -0.75811214 | V55: 2.9032697 | X55: 35.061394 | AA55: -0.12553027 | AB55: 0.5778149 | AC55: 40.934998 | AE55: 1014.098 | AF55: 1035.612 | AG55: 0.92235761
B56: 1999-00 | C56: 35.676214 | D56: 34.601352 | E56: 31.865373 | F56: 0.56269104 | G56: 2.1732881 | H56: 2.7359791 | I56: 32.453512 | K56: -1.0158335 | L56: 3.1587043 | M56: 2.5369843 | N56: -0.45314244 | O56: -1.0748624 | Q56: -1.6375535 | R56: 27.438863 | T56: -0.86119062 | U56: -0.8256572 | V56: 2.4410612 | X56: 32.350606 | Y56: 32.45133 | Z56: 32.744802 | AA56: -1.0636463 | AB56: -0.44192632 | AC56: 38.486088 | AE56: 1060.973 | AF56: 1092.097 | AG56: 0.87449691
B57: 2000-01 | C57: 36.363636 | D57: 34.905644 | E57: 32.2554 | F57: 0.49765889 | G57: 2.152585 | H57: 2.6502439 | I57: 32.970036 | K57: -1.1455573 | L57: 3.3611212 | M57: 2.5510276 | N57: -0.64789843 | O57: -1.457992 | Q57: -1.9556509 | R57: 26.86782 | T57: -3.1825295 | U57: -3.4025481 | V57: 2.4060671 | X57: 28.208053 | Y57: 28.313176 | Z57: 33.097945 | AA57: -1.3889175 | AB57: -0.57882388 | AC57: 35.643633 | AE57: 1117.633 | AF57: 1141.518 | AG57: 1.2703884
B58: 2001-02 | C58: 35.565396 | D58: 36.051346 | E58: 32.703597 | F58: 1.1589491 | G58: 2.1888003 | H58: 3.3477494 | I58: 32.298538 | K58: -0.069387354 | L58: 1.203534 | M58: 0.59992198 | N58: 1.0895618 | O58: 0.48594971 | Q58: -0.67299939 | R58: 28.243999 | T58: 0.2389648 | U58: 0.34451981 | V58: 1.9847618 | X58: 27.978349 | Y58: 28.079903 | Z58: 34.676734 | AA58: 0.42635943 | AB58: 1.0299715 | AC58: 34.292786 | AE58: 1159.585 | AF58: 1181.628 | AG58: 0.69906871
B59: 2002-03 | C59: 34.523355 | D59: 37.416808 | E59: 33.665607 | F59: 1.5253531 | G59: 2.2258471 | H59: 3.7512003 | I59: 31.414722 | K59: 1.5446932 | L59: -1.2443953 | M59: -1.4209891 | N59: 3.0700463 | O59: 2.8934525 | Q59: 1.3680994 | R59: 31.277551 | T59: 1.7973864 | U59: 1.9321636 | V59: 1.7971385 | X59: 29.731083 | Y59: 29.819665 | Z59: 37.379509 | AA59: 2.5143247 | AB59: 2.6909185 | AC59: 34.872239 | AE59: 1210.146 | AF59: 1241.798 | AG59: 0.073560053
B60: 2003-04 | C60: 35.290945 | D60: 38.697505 | E60: 34.823582 | F60: 1.6983486 | G60: 2.1755738 | H60: 3.8739224 | I60: 32.224791 | K60: 1.9148422 | L60: -1.6534987 | M60: -1.86013 | N60: 3.6131908 | O60: 3.4065595 | Q60: 1.7082109 | R60: 31.177818 | T60: 3.0832174 | U60: 3.129711 | V60: 1.8175571 | X60: 30.83373 | Y60: 30.940448 | Z60: 37.709004 | AA60: 2.9360658 | AB60: 3.1426971 | AC60: 36.605917 | AE60: 1277.594 | AF60: 1311.875 | AG60: 0.38383864
B61: 2004-05 | C61: 35.888956 | D61: 39.725954 | E61: 35.507053 | F61: 2.0426064 | G61: 2.1762946 | H61: 4.218901 | I61: 32.840123 | K61: 2.1125805 | L61: -2.0399327 | M61: -2.358121 | N61: 4.1551869 | O61: 3.8369985 | Q61: 1.7943921 | R61: 33.265384 | T61: 3.0533631 | U61: 3.1464249 | V61: 1.9225099 | X61: 33.352582 | Y61: 33.461128 | Z61: 37.64044 | AA61: 3.3078905 | AB61: 3.6260789 | AC61: 39.038277 | AE61: 1346.417 | AF61: 1381.902 | AG61: 0.48284129
B62: 2005-06 | C62: 36.509111 | D62: 39.696338 | E62: 35.629132 | F62: 1.8542285 | G62: 2.2129778 | H62: 4.0672063 | I62: 33.238571 | K62: 1.5885385 | L62: -1.403667 | M62: -1.6592066 | N62: 3.4427671 | O62: 3.1872275 | Q62: 1.332999 | R62: 32.261952 | T62: 3.0234125 | U62: 3.0234125 | V62: 1.952644 | X62: 34.17671 | Y62: 34.327268 | Z62: 35.440167 | AA62: 2.9476867 | AB62: 3.2032262 | AC62: 40.373796 | AE62: 1423.557 | AF62: 1461.229 | AG62: 0.31794263
B63: 2006-07 | C63: 36.928035 | D63: 39.669141 | E63: 35.615033 | F63: 1.8131197 | G63: 2.2409886 | H63: 4.0541083 | I63: 33.635453 | K63: 0.9955011 | L63: -0.86953145 | M63: -0.93704576 | N63: 2.8086208 | O63: 2.7411065 | Q63: 0.92798678 | R63: 32.284344 | T63: 2.5070843 | U63: 2.3941242 | V63: 2.0598642 | X63: 34.930781 | Y63: 35.061315 | Z63: 35.408404 | AA63: 2.5810741 | AB63: 2.6485885 | AC63: 41.382157 | AE63: 1493.448 | AF63: 1532.173 | AG63: 0.0078515864
B64: 2007-08 | C64: 37.16114 | D64: 40.02724 | E64: 35.959749 | F64: 1.8213314 | G64: 2.2461603 | H64: 4.0674917 | I64: 33.642975 | K64: 1.3882967 | L64: -1.0932442 | M64: -1.4367723 | N64: 3.2096281 | O64: 2.8661 | Q64: 1.0447686 | R64: 34.069041 | T64: 2.1160652 | U64: 1.8526942 | V64: 2.1438018 | X64: 35.467024 | Y64: 35.598337 | Z64: 38.082154 | AA64: 2.8765967 | AB64: 3.2201248 | AC64: 42.109207 | AE64: 1571.927 | AF64: 1599.232 | AG64: 0.6839156
B65: 2008-09 | C65: 35.742911 | D65: 43.041876 | E65: 37.592381 | F65: 3.0475746 | G65: 2.4019201 | H65: 5.4494947 | I65: 32.022065 | K65: 3.9059448 | L65: -5.3773159 | M65: -5.0318703 | N65: 6.9535193 | O65: 7.298965 | Q65: 4.2513904 | R65: 47.209227 | T65: 10.282583 | U65: 10.915308 | V65: 2.1037277 | X65: 50.243495 | Y65: 50.275407 | Z65: 48.834034 | AA65: 6.7112417 | AB65: 6.3657961 | AC65: 53.186754 | AE65: 1593.267 | AF65: 1566.77 | AG65: -0.96445749
B66: 2009-10 | C66: 35.780023 | D66: 45.967506 | E66: 40.368458 | F66: 3.0444077 | G66: 2.5546402 | H66: 5.5990479 | I66: 32.152871 | K66: 5.3939827 | L66: -8.1880835 | M66: -6.4389903 | N66: 8.4383904 | O66: 10.187484 | Q66: 7.1430759 | R66: 54.332474 | T66: 12.672823 | U66: 12.812255 | V66: 1.790539 | X66: 64.385479 | Y66: 63.602505 | Z66: 55.609661 | AA66: 9.9660513 | AB66: 8.2169581 | AC66: 70.342742 | AE66: 1567.07 | AF66: 1596.478 | AG66: -3.1124034
B67: 2010-11 | C67: 36.807363 | D67: 45.502552 | E67: 40.4981 | F67: 2.5055024 | G67: 2.4989497 | H67: 5.0044521 | I67: 33.122505 | K67: 4.3742014 | L67: -6.126977 | M67: -4.3114919 | N67: 6.8797038 | O67: 8.6951889 | Q67: 6.1896865 | R67: 58.625818 | T67: 8.2069243 | U67: 7.7188434 | V67: 2.5110752 | X67: 70.622886 | Y67: 70.344914 | Z67: 49.871529 | AA67: 8.7660433 | AB67: 6.9505582 | AC67: 75.976376 | AE67: 1632.926 | AF67: 1654.846 | AG67: -2.3860088
... B76: 2019-20 | C76: 36.516555 | D76: 39.0956 | E76: 34.914156 | F76: 1.8742072 | G76: 2.3072366 | H76: 4.1814438 | I76: 32.851954 | K76: 1.0568206 | L76: -1.2130212 | M76: -1.5650038 | N76: 2.9310278 | O76: 2.5790452 | Q76: 0.70483799 | R76: 73.780819 | T76: 2.4775588 | U76: 1.1509453 | V76: 1.7312779 | X76: 84.499793 | Y76: 76.477013 | Z76: 65.810903 | AA76: 2.847982 | AB76: 3.1999646 | AC76: 83.8998 | AE76: 2263.357 | AF76: 2148.881 | AG76: 0.55236491
B77: 2020-21 | C77: 37.532488 | D77: 52.268393 | E77: 46.335396 | F77: 3.4057884 | G77: 2.5272086 | H77: 5.932997 | I77: 33.716841 | K77: 11.296853 | L77: -13.737372 | M77: -13.704109 | N77: 14.702641 | O77: 14.735905 | Q77: 11.330116 | R77: 81.856184 | T77: 16.018182 | U77: 15.74894 | V77: 1.194552 | X77: 95.381028 | Y77: 85.42734 | Z77: 71.835798 | AA77: 14.986284 | AB77: 14.953021 | AC77: 106.37243 | AE77: 2109.996 | AF77: 2259.464 | AG77: -0.28747247 | BS77: 60
B78: 2021-22 | C78: 38.35089 | D78: 43.362517 | E78: 38.863097 | F78: 2.2014266 | G78: 2.2979939 | H78: 4.4994205 | I78: 34.668084 | K78: 3.6434134 | L78: -2.9830053 | M78: -3.8162181 | N78: 5.84484 | O78: 5.0116272 | Q78: 2.8102006 | R78: 78.543902 | T78: 5.3656935 | U78: 3.2630006 | V78: 2.3068674 | X78: 94.317872 | Y78: 81.229282 | Z78: 65.212278 | AA78: 5.6265669 | AB78: 6.4597797 | AC78: 99.373187 | AE78: 2400.398 | AF78: 2524.336 | AG78: 1.7814146 | BS78: 60
B79: 2022-23 | C79: 39.233036 | D79: 44.057668 | E79: 39.980132 | F79: 1.7720594 | G79: 2.3054766 | H79: 4.077536 | I79: 35.193081 | K79: 3.9230444 | L79: -1.1624561 | M79: -2.0329287 | N79: 5.6951039 | O79: 4.8246313 | Q79: 3.0525719 | R79: 79.02943 | T79: 4.2273271 | U79: 1.6546105 | V79: 4.2557973 | X79: 93.21417 | Y79: 82.49573 | Z79: 67.2728 | AA79: 5.2379044 | AB79: 6.1083769 | AC79: 96.359652 | AE79: 2634.336 | AF79: 2730.808 | AG79: 1.0283793 | BS79: 60
B80: 2023-24 | C80: 39.307805 | D80: 44.130674 | E80: 39.342298 | F80: 2.448025 | G80: 2.3403513 | H80: 4.7883763 | I80: 34.938578 | K80: 2.5883877 | L80: -1.8431091 | M80: -2.0566527 | N80: 5.0364127 | O80: 4.8228691 | Q80: 2.3748442 | R80: 79.743717 | T80: 5.6435984 | U80: 2.1958542 | V80: 3.8573559 | X80: 94.3869 | Y80: 85.966652 | Z80: 69.132869 | AA80: 5.729221 | AB80: 5.9427646 | AC80: 98.119207 | AE80: 2788.983 | AF80: 2845.522 | AG80: 0.015735383 | BS80: 60
B81: 2024-25 | C81: 38.902214 | D81: 44.008647 | E81: 39.132908 | F81: 2.5159747 | G81: 2.3597641 | H81: 4.8757388 | I81: 34.679403 | K81: 2.4006732 | L81: -2.2652929 | M81: -2.0666614 | N81: 4.9166479 | O81: 5.106433 | Q81: 2.5904583 | R81: 81.3 | T81: 6.157882 | U81: 2.4901446 | V81: 3.6292656 | X81: 93.7 | Y81: 88.2 | Z81: 71.368974 | AA81: 5.7426188 | AB81: 5.5528337 | AC81: 99.94711 | AE81: 2926.818 | AF81: 2934.0705 | AG81: -0.39250353 | BS81: 60
B82: 2025-26 | C82: 41.067448 | D82: 44.998421 | E82: 39.799125 | F82: 2.7238044 | G82: 2.4754914 | H82: 5.1992957 | I82: 36.793962 | K82: 0.87689986 | L82: -0.90450281 | M82: -1.1415346 | N82: 3.6007042 | O82: 3.930973 | Q82: 1.2071686 | R82: 82.916459 | T82: 4.7763548 | U82: 2.3904098 | V82: 3.7147454 | X82: 95.118117 | Y82: 91.961247 | Z82: 69.696046 | AA82: 4.3048149 | AB82: 3.9745461 | AC82: 103.67514 | AE82: 2993.8517 | AF82: 3045.8937 | AG82: -0.50353612 | BS82: 60
B83: 2026-27 | C83: 41.669877 | D83: 44.8028 | E83: 39.639199 | F83: 2.7002322 | G83: 2.4633688 | H83: 5.163601 | I83: 37.437998 | K83: 0.27138729 | L83: -0.20675091 | M83: -0.32917965 | N83: 2.9716195 | O83: 3.1329234 | Q83: 0.43269119 | R83: 83.493896 | T83: 4.1872493 | U83: 3.7773447 | V83: 3.5912069 | X83: 95.765323 | Y83: 93.405878 | Z83: 70.027665 | AA83: 3.7422648 | AB83: 3.5809609 | AC83: 105.01601 | AE83: 3101.2963 | AF83: 3160.1125 | AG83: -0.12119334
B84: 2027-28 | C84: 41.949115 | D84: 44.438892 | E84: 39.305363 | F84: 2.6761999 | G84: 2.4573293 | H84: 5.1335292 | I84: 37.732087 | K84: -0.21066556 | L84: 0.5201636 | M84: 0.096025455 | N84: 2.4655343 | O84: 2.4897772 | Q84: -0.18642271 | R84: 83.383325 | T84: 4.0906417 | U84: 4.0705623 | V84: 3.6605944 | X84: 96.138698 | Y84: 94.183081 | Z84: 69.744933 | AA84: 3.1201124 | AB84: 3.0958695 | AC84: 105.48751 | AE84: 3219.7467 | AF84: 3278.7391 | AG84: -8.3554894e-06
B85: 2028-29 | C85: 41.743448 | D85: 44.061903 | E85: 39.08563 | F85: 2.5316442 | G85: 2.4446292 | H85: 4.9762734 | I85: 37.547024 | K85: -0.21319463 | L85: 0.76503161 | M85: 0.60980437 | N85: 2.3184496 | O85: 2.3184554 | Q85: -0.21318878 | R85: 83.151761 | T85: 4.1437785 | U85: 4.097547 | V85: 3.7203486 | X85: 96.261883 | Y85: 94.771691 | Z85: 69.616298 | AA85: 3.0321029 | AB85: 3.032097 | AC85: 105.86187 | AE85: 3339.4941 | AF85: 3400.7858 | AG85: -8.3554894e-06
B86: 2029-30 | C86: 41.714841 | D86: 43.852317 | E86: 39.00579 | F86: 2.4241846 | G86: 2.4223426 | H86: 4.8465272 | I86: 37.539168 | K86: -0.28671463 | L86: 1.025172 | M86: 1.3166059 | N86: 2.13747 | O86: 2.1374759 | Q86: -0.28670878 | R86: 82.723703 | T86: 3.1791534 | U86: 3.1015141 | V86: 3.7984017 | X86: 96.114047 | Y86: 94.978332 | Z86: 69.148717 | AA86: 2.7671165 | AB86: 2.7671106 | AC86: 105.89124 | AE86: 3464.0106 | AF86: 3528.4196 | AG86: -8.3554894e-06
B87: 2030-31 | M87: 1.3610838
B88: Notes: | C88: 1 Outturn data presented as a per cent of GDP is consistent with the latest available ONS GDP data (Quarterly National Accounts published 30th September 2025).
C89: 2 Debt at end March; GDP centred on end-March.
C90: Outturn fiscal data consistent with the ONS/HM Treasury Public Sector Finances Statistical Bulletin released on 21 October 2025.
C91: Forecast years from 2025-26 are consistent with the OBR Economic and fiscal outlook forecast published March 2025.
C92: A full list of sources is available in the glossary.
C93: Cyclically adjusted aggregates are OBR estimates based on internal calculations of the size of the output gap. For more information see Working paper No. 3: Cyclically-adjusting the public finances (https://obr.uk/download/working-paper-no-3-cyclically-adjusting-the-public-finances/)

Sheet OBR_MAR25_ST1.1
A1: Back to contents
B2: 1.1 GDP expenditure components (£ billion chain-linked volumes, seasonally adjusted)
C3: Private consumption | D3: Government consumption | E3: Fixed investment | J3: Net acquisition of valuables | K3: Final domestic demand | L3: Change in inventories | M3: Total domestic demand | N3: Exports | O3: Total final expenditure | P3: Imports | Q3: Statistical discrepancy | R3: Real GDP | S3: Non-oil GVA
E4: of which: | F4: Business investment | G4: Private dwellings | H4: General government | I4: Public corps dwellings
B5: 2008Q1 | C5: 343.246 | D5: 107.345 | E5: 92.244 | F5: 49.124 | G5: 27.947 | H5: 14.053 | I5: 1.671 | J5: 0.546 | K5: 543.381 | L5: -2.614 | M5: 540.767 | N5: 164.284 | O5: 708.797 | P5: 164.791 | Q5: 0 | R5: 542.804 | S5: 469.299
B6: 2008Q2 | C6: 339.223 | D6: 106.712 | E6: 93.278 | F6: 50.99 | G6: 26.652 | H6: 14.461 | I6: 1.623 | J6: -0.267 | K6: 538.946 | L6: -1.434 | M6: 537.512 | N6: 164.307 | O6: 704.893 | P6: 163.78 | Q6: 0 | R6: 539.918 | S6: 467.566
B7: 2008Q3 | C7: 333.807 | D7: 108.635 | E7: 88.414 | F7: 49.052 | G7: 21.944 | H7: 14.475 | I7: 3.112 | J7: -0.925 | K7: 529.931 | L7: -1.88 | M7: 528.051 | N7: 164.942 | O7: 693.642 | P7: 160.848 | Q7: 0 | R7: 531.619 | S7: 460.34
B8: 2008Q4 | C8: 325.752 | D8: 109.824 | E8: 86.953 | F8: 47.384 | G8: 20.99 | H8: 15.546 | I8: 3.055 | J8: 0.326 | K8: 522.855 | L8: -4.599 | M8: 518.256 | N8: 158.58 | O8: 674.04 | P8: 152.35 | Q8: 0 | R8: 520.23 | S8: 450.519
B9: 2009Q1 | C9: 324.515 | D9: 109.105 | E9: 81.803 | F9: 43.119 | G9: 19.739 | H9: 15.857 | I9: 3.01 | J9: 1.791 | K9: 517.214 | L9: -7.599 | M9: 509.615 | N9: 148.383 | O9: 657.371 | P9: 146.327 | Q9: 0 | R9: 509.646 | S9: 441.6
B10: 2009Q2 | C10: 324.306 | D10: 108.831 | E10: 78.328 | F10: 40.877 | G10: 19.168 | H10: 15.175 | I10: 2.969 | J10: 0.92 | K10: 512.385 | L10: -7.395 | M10: 504.99 | N10: 146.862 | O10: 656.014 | P10: 146.677 | Q10: 0 | R10: 508.009 | S10: 439.638
B11: 2009Q3 | C11: 326.128 | D11: 109.697 | E11: 78.858 | F11: 39.978 | G11: 19.235 | H11: 16.45 | I11: 3.003 | J11: 1.476 | K11: 516.159 | L11: -7.922 | M11: 508.237 | N11: 146.171 | O11: 660.256 | P11: 150.636 | Q11: 0 | R11: 508.398 | S11: 440.388
B12: 2009Q4 | C12: 328.611 | D12: 110.527 | E12: 77.537 | F12: 39.618 | G12: 18.358 | H12: 16.22 | I12: 3.064 | J12: -0.089 | K12: 516.586 | L12: -6.248 | M12: 510.338 | N12: 152.995 | O12: 664.168 | P12: 153.109 | Q12: 0 | R12: 509.889 | S12: 442.004
B13: 2010Q1 | C13: 326.985 | D13: 109.05 | E13: 81.644 | F13: 41.479 | G13: 19.726 | H13: 17.177 | I13: 3.043 | J13: -0.247 | K13: 517.432 | L13: -1.247 | M13: 516.185 | N13: 152.875 | O13: 671.646 | P13: 155.913 | Q13: 0 | R13: 514.595 | S13: 446.639
B14: 2010Q2 | C14: 334.907 | D14: 109.456 | E14: 80.431 | F14: 40.858 | G14: 20.834 | H14: 15.7 | I14: 3.03 | J14: -0.477 | K14: 524.317 | L14: -0.801 | M14: 523.516 | N14: 157.927 | O14: 682.036 | P14: 160.853 | Q14: 0 | R14: 520.128 | S14: 452.041
B15: 2010Q3 | C15: 335.176 | D15: 109.504 | E15: 83.557 | F15: 42.697 | G15: 21.916 | H15: 15.983 | I15: 3.007 | J15: 0.867 | K15: 529.104 | L15: 0.246 | M15: 529.35 | N15: 159.59 | O15: 690.159 | P15: 166.05 | Q15: 0 | R15: 523.173 | S15: 454.977
B16: 2010Q4 | C16: 334.596 | D16: 110.174 | E16: 85.811 | F16: 45.515 | G16: 21.362 | H16: 15.903 | I16: 2.939 | J16: 0.744 | K16: 531.325 | L16: -3.44 | M16: 527.885 | N16: 162.838 | O16: 691.901 | P16: 167.478 | Q16: 0 | R16: 523.515 | S16: 455.955
... B93: 2030Q1 | C93: 439.46705 | D93: 151.03342 | E93: 128.81396 | F93: 67.873213 | G93: 37.388865 | H93: 21.471434 | I93: 2.0804523 | J93: -1.6735 | K93: 717.64093 | L93: 1.6609617 | M93: 719.3019 | N93: 208.44857 | O93: 927.75046 | P93: 226.49987 | Q93: 0.395 | R93: 701.64559 | S93: 624.44806
B94: 2008 | C94: 1342.028 | D94: 432.516 | E94: 360.889 | F94: 196.55 | G94: 97.533 | H94: 58.535 | I94: 9.461 | J94: -0.32 | K94: 2135.113 | L94: -10.527 | M94: 2124.586 | N94: 652.113 | O94: 2781.372 | P94: 641.769 | Q94: 0 | R94: 2134.571 | S94: 1847.724
B95: 2009 | C95: 1303.56 | D95: 438.16 | E95: 316.526 | F95: 163.592 | G95: 76.5 | H95: 63.702 | I95: 12.046 | J95: 4.098 | K95: 2062.344 | L95: -29.164 | M95: 2033.18 | N95: 594.411 | O95: 2637.809 | P95: 596.749 | Q95: 0 | R95: 2035.942 | S95: 1763.63
B96: 2010 | C96: 1331.664 | D96: 438.184 | E96: 331.443 | F96: 170.549 | G96: 83.838 | H96: 64.763 | I96: 12.019 | J96: 0.887 | K96: 2102.178 | L96: -5.242 | M96: 2096.936 | N96: 633.23 | O96: 2735.742 | P96: 650.294 | Q96: 0 | R96: 2081.411 | S96: 1809.612
B97: 2011 | C97: 1327.201 | D97: 437.852 | E97: 331.794 | F97: 180.663 | G97: 80.003 | H97: 59.324 | I97: 11.2 | J97: 0.299 | K97: 2097.146 | L97: -1.076 | M97: 2096.07 | N97: 677.165 | O97: 2778.331 | P97: 669.364 | Q97: 0 | R97: 2105.105 | S97: 1839.933
B98: 2012 | C98: 1350.173 | D98: 444.341 | E98: 337.186 | F98: 193.379 | G98: 78.282 | H98: 54.289 | I98: 10.171 | J98: -0.137 | K98: 2131.563 | L98: 8.801 | M98: 2140.364 | N98: 682.23 | O98: 2826.703 | P98: 685.845 | Q98: 0 | R98: 2136.871 | S98: 1878.029
B99: 2013 | C99: 1384.389 | D99: 445.366 | E99: 348.041 | F99: 200.33 | G99: 86.611 | H99: 50.821 | I99: 9.572 | J99: 10.075 | K99: 2187.871 | L99: 8.889 | M99: 2196.76 | N99: 684.213 | O99: 2887.354 | P99: 708.062 | Q99: 0 | R99: 2175.333 | S99: 1914.927
B100: 2014 | C100: 1421.865 | D100: 456.853 | E100: 372.53 | F100: 211.329 | G100: 92.264 | H100: 56.941 | I100: 11.094 | J100: 9.134 | K100: 2260.382 | L100: 17.951 | M100: 2278.333 | N100: 691.115 | O100: 2992.803 | P100: 744.137 | Q100: 0 | R100: 2244.827 | S100: 1977.646
B101: 2015 | C101: 1462.152 | D101: 462.638 | E101: 399.154 | F101: 231.101 | G101: 98.216 | H101: 57.919 | I101: 10.839 | J101: 2.177 | K101: 2326.121 | L101: 13.952 | M101: 2340.073 | N101: 717.177 | O101: 3078.451 | P101: 781.01 | Q101: 0 | R101: 2294.727 | S101: 2015.309
B102: 2016 | C102: 1515.983 | D102: 465.996 | E102: 419.678 | F102: 246.803 | G102: 105.084 | H102: 55.892 | I102: 10.942 | J102: 3.784 | K102: 2405.441 | L102: 7.387 | M102: 2412.828 | N102: 737.028 | O102: 3151.988 | P102: 812.091 | Q102: 0 | R102: 2338.825 | S102: 2054.688
B103: 2017 | C103: 1543.709 | D103: 468.998 | E103: 434.377 | F103: 246.164 | G103: 114.383 | H103: 61.97 | I103: 10.792 | J103: 2.296 | K103: 2449.38 | L103: 15.967 | M103: 2465.347 | N103: 786.896 | O103: 3239.479 | P103: 837.777 | Q103: 0 | R103: 2400.956 | S103: 2112.002
B104: 2018 | C104: 1574.039 | D104: 472 | E104: 432.395 | F104: 242.048 | G104: 121.311 | H104: 61.957 | I104: 5.99 | J104: 5.388 | K104: 2483.822 | L104: 2.843 | M104: 2486.665 | N104: 811.128 | O104: 3298.363 | P104: 863.727 | Q104: 0 | R104: 2434.694 | S104: 2138.981
B105: 2019 | C105: 1590.908 | D105: 490.746 | E105: 441.621 | F105: 247.308 | G105: 123.136 | H105: 63.652 | I105: 6.3976633 | J105: 6.638 | K105: 2529.913 | L105: 3.363 | M105: 2533.276 | N105: 827.359 | O105: 3360.903 | P105: 887.222 | Q105: 0 | R105: 2474.245 | S105: 2176.776
... B115: 2029 | C115: 1737.8472 | D115: 598.0478 | E115: 510.8966 | F115: 268.72175 | G115: 147.56007 | H115: 86.405621 | I115: 8.2091561 | J115: -6.694 | K115: 2840.0976 | L115: 6.0033605 | M115: 2846.1009 | N115: 829.01788 | O115: 3675.1188 | P115: 901.51202 | Q115: 1.58 | R115: 2775.1868 | S115: 2468.4898
B116: 2008-09 | C116: 1323.297 | D116: 434.276 | E116: 350.448 | F116: 190.545 | G116: 89.325 | H116: 60.339 | I116: 10.8 | J116: 0.925 | K116: 2108.946 | L116: -15.512 | M116: 2093.434 | N116: 636.212 | O116: 2729.946 | P116: 623.305 | Q116: 0 | R116: 2101.413 | S116: 1820.025
B117: 2009-10 | C117: 1306.03 | D117: 438.105 | E117: 316.367 | F117: 161.952 | G117: 76.487 | H117: 65.022 | I117: 12.079 | J117: 2.06 | K117: 2062.562 | L117: -22.812 | M117: 2039.75 | N117: 598.903 | O117: 2652.084 | P117: 606.335 | Q117: 0 | R117: 2040.891 | S117: 1768.669
B118: 2010-11 | C118: 1336.331 | D118: 439.938 | E118: 332.295 | F118: 171.4 | G118: 84.407 | H118: 64.427 | I118: 11.922 | J118: -1.281 | K118: 2107.283 | L118: -5.532 | M118: 2101.751 | N118: 649.897 | O118: 2753.617 | P118: 657.932 | Q118: 0 | R118: 2091.771 | S118: 1820.857
B119: 2011-12 | C119: 1328.201 | D119: 440.049 | E119: 334.789 | F119: 187.46 | G119: 78.591 | H119: 56.918 | I119: 10.835 | J119: 0.702 | K119: 2103.741 | L119: -4.105 | M119: 2099.636 | N119: 683.311 | O119: 2792.664 | P119: 676.394 | Q119: 0 | R119: 2112.45 | S119: 1848.905
B120: 2012-13 | C120: 1358.783 | D120: 441.664 | E120: 335.032 | F120: 192.791 | G120: 79.525 | H120: 51.957 | I120: 9.95 | J120: 3.095 | K120: 2138.574 | L120: 15.413 | M120: 2153.987 | N120: 677.616 | O120: 2831.631 | P120: 685.053 | Q120: 0 | R120: 2142.545 | S120: 1884.778
B121: 2013-14 | C121: 1393.96 | D121: 448.779 | E121: 356.641 | F121: 203.85 | G121: 89.285 | H121: 53.176 | I121: 9.606 | J121: 11.089 | K121: 2210.469 | L121: 5.482 | M121: 2215.951 | N121: 682.501 | O121: 2912.996 | P121: 717.428 | Q121: 0 | R121: 2191.542 | S121: 1929.012
B122: 2014-15 | C122: 1433.021 | D122: 457.554 | E122: 379.612 | F122: 217.23 | G122: 92.306 | H122: 57.444 | I122: 11.632 | J122: 11.021 | K122: 2281.208 | L122: 25.128 | M122: 2306.336 | N122: 698.492 | O122: 3024.825 | P122: 761.669 | Q122: 0 | R122: 2259.794 | S122: 1991.088
B123: 2015-16 | C123: 1475.228 | D123: 464.582 | E123: 403.187 | F123: 234.825 | G123: 100.352 | H123: 56.441 | I123: 10.583 | J123: 0.092 | K123: 2343.089 | L123: 9.112 | M123: 2352.201 | N123: 721.355 | O123: 3091.707 | P123: 783.379 | Q123: 0 | R123: 2305.687 | S123: 2023.19
B124: 2016-17 | C124: 1525.007 | D124: 466.181 | E124: 424.285 | F124: 247.159 | G124: 108.425 | H124: 56.713 | I124: 11.044 | J124: 1.483 | K124: 2416.956 | L124: 12.207 | M124: 2429.163 | N124: 747.683 | O124: 3172.81 | P124: 818.796 | Q124: 0 | R124: 2353.138 | S124: 2068.956
B125: 2017-18 | C125: 1550.872 | D125: 469.692 | E125: 435.815 | F125: 245.466 | G125: 115.898 | H125: 63.731 | I125: 9.571 | J125: 3.555 | K125: 2459.934 | L125: 9.857 | M125: 2469.791 | N125: 796.33 | O125: 3258.231 | P125: 844.329 | Q125: 0 | R125: 2413.318 | S125: 2121.662
B126: 2018-19 | C126: 1580.51 | D126: 475.873 | E126: 434.246 | F126: 241.907 | G126: 122.609 | H126: 62.642 | I126: 6.0093984 | J126: 20.039 | K126: 2510.668 | L126: 11.305 | M126: 2521.973 | N126: 810.933 | O126: 3331.45 | P126: 889.989 | Q126: 0 | R126: 2442.845 | S126: 2146.491
B127: 2019-20 | C127: 1578.33 | D127: 489.358 | E127: 436.89 | F127: 246.706 | G127: 120.299 | H127: 62.674 | I127: 6.2604297 | J127: -8.191 | K127: 2496.387 | L127: -5.525 | M127: 2490.862 | N127: 826.007 | O127: 3318.749 | P127: 853.473 | Q127: 0 | R127: 2464.028 | S127: 2170.002
... B137: 2029-30 | C137: 1745.8457 | D137: 600.46022 | E137: 512.64111 | F137: 269.81987 | G137: 148.36926 | H137: 86.197748 | I137: 8.2542392 | J137: -6.694 | K137: 2852.253 | L137: 6.2492863 | M137: 2858.5023 | N137: 830.93497 | O137: 3689.4373 | P137: 903.28197 | Q137: 1.58 | R137: 2787.7353 | S137: 2480.208
B138: Definitions:
B139: Household and non-profit institutions serving households final consumption expenditure (ONS Economic Accounts Table 1.1.2, identifier: ABJR + HAYO)
B140: General government final consumption (ONS Economic Accounts Table 1.1.2, identifier: NMRY)
B141: Total gross fixed capital formation (ONS Economic Accounts Table 1.1.2, identifier: NPQT)
B142: Business investment (ONS Economic Accounts Table 1.1.8, identifier: NPEL)
B143: Private sector investment in dwellings, including transfer costs (ONS Economic Accounts Table 1.1.8, identifier: L636 + L637)
B144: General government gross fixed capital formation (ONS Economic Accounts Table 1.1.8, identifier: DLWF)
B145: Public corporations investment in dwellings, including transfer costs (ONS Economic Accounts Table 1.1.8, identifier: L634 + L635)
B146: Net acquisitions of valuables (ONS Economic Accounts Table 1.1.2, identifier: NPJR)
B147: Final domestic demand is the sum of private consumption, government consumption, fixed investment and net acquisition of valuables
B148: Change in inventories (ONS Economic Accounts Table 1.1.2, identifier: CAFU)
B149: Total domestic demand is the sum of final domestic demand and change in inventories
... B154: Gross domestic product at market prices (ONS Economic Accounts Table 1.1.2, identifier: ABMI)

Sheet OBR_NOV25_ST1.1
A1: Back to contents
B2: 1.1 GDP expenditure components (£ billion chain-linked volumes, seasonally adjusted)
C3: Private consumption | D3: Government consumption | E3: Fixed investment | J3: Net acquisition of valuables | K3: Final domestic demand | L3: Change in inventories | M3: Total domestic demand | N3: Exports | O3: Total final expenditure | P3: Imports | Q3: Statistical discrepancy | R3: Real GDP | S3: Non-oil GVA
E4: of which: | F4: Business investment | G4: Private dwellings | H4: General government | I4: Public corps dwellings
B5: 2008Q1 | C5: 366.795 | D5: 115.993 | E5: 101.666 | F5: 52.099 | G5: 31.883 | H5: 16.775 | I5: 1.784 | J5: 0.505 | K5: 584.959 | L5: -4.672 | M5: 580.287 | N5: 168.251 | O5: 756.225 | P5: 169.186 | Q5: 0 | R5: 586.69 | S5: 513.251
B6: 2008Q2 | C6: 362.064 | D6: 115.307 | E6: 103.272 | F6: 57.108 | G6: 30.069 | H6: 15.255 | I6: 1.66 | J6: -0.216 | K6: 580.427 | L6: -0.281 | M6: 580.146 | N6: 168.428 | O6: 752.599 | P6: 168.738 | Q6: 0 | R6: 583.541 | S6: 511.331
B7: 2008Q3 | C7: 356.567 | D7: 117.362 | E7: 98.198 | F7: 54.942 | G7: 24.559 | H7: 15.861 | I7: 3.419 | J7: -1.304 | K7: 570.823 | L7: -0.858 | M7: 569.965 | N7: 169.106 | O7: 738.868 | P7: 164.573 | Q7: 0 | R7: 573.961 | S7: 503.224
B8: 2008Q4 | C8: 347.875 | D8: 118.565 | E8: 96.036 | F8: 52.434 | G8: 23.384 | H8: 17.411 | I8: 3.329 | J8: 0.241 | K8: 562.717 | L8: -2.768 | M8: 559.949 | N8: 161.069 | O8: 717.793 | P8: 155.485 | Q8: 0 | R8: 561.816 | S8: 492.727
B9: 2009Q1 | C9: 346.435 | D9: 117.859 | E9: 90.795 | F9: 48.456 | G9: 21.958 | H9: 17.521 | I9: 3.285 | J9: 1.402 | K9: 556.491 | L9: -7.604 | M9: 548.887 | N9: 152.669 | O9: 700.234 | P9: 149.466 | Q9: 0 | R9: 550.451 | S9: 483.023
B10: 2009Q2 | C10: 345.972 | D10: 117.61 | E10: 87.418 | F10: 46.751 | G10: 21.178 | H10: 16.507 | I10: 3.256 | J10: 0.533 | K10: 551.533 | L10: -7.752 | M10: 543.781 | N10: 151.805 | O10: 698.826 | P10: 149.706 | Q10: 0 | R10: 548.859 | S10: 480.942
B11: 2009Q3 | C11: 347.113 | D11: 118.717 | E11: 87.976 | F11: 45.581 | G11: 21.321 | H11: 18.129 | I11: 3.289 | J11: 0.773 | K11: 554.579 | L11: -8.53 | M11: 546.049 | N11: 151.597 | O11: 703.47 | P11: 153.651 | Q11: 0 | R11: 549.54 | S11: 482.029
B12: 2009Q4 | C12: 349.909 | D12: 119.548 | E12: 86.66 | F12: 45.414 | G12: 20.128 | H12: 17.924 | I12: 3.378 | J12: -0.322 | K12: 555.795 | L12: -5.121 | M12: 550.674 | N12: 157.882 | O12: 709.156 | P12: 157.472 | Q12: 0 | R12: 551.372 | S12: 484.18
B13: 2010Q1 | C13: 349.45 | D13: 117.946 | E13: 90.007 | F13: 47.159 | G13: 20.935 | H13: 18.677 | I13: 3.422 | J13: -0.48 | K13: 556.923 | L13: -2.406 | M13: 554.517 | N13: 157.938 | O13: 715.447 | P13: 159.135 | Q13: 0 | R13: 556.002 | S13: 488.699
B14: 2010Q2 | C14: 358.968 | D14: 118.254 | E14: 87.938 | F14: 46.055 | G14: 21.505 | H14: 17.329 | I14: 3.4 | J14: -0.745 | K14: 564.415 | L14: -1.128 | M14: 563.287 | N14: 162.473 | O14: 726.669 | P14: 163.978 | Q14: 0 | R14: 562.353 | S14: 494.936
B15: 2010Q3 | C15: 359.801 | D15: 118.609 | E15: 90.701 | F15: 47.527 | G15: 22.204 | H15: 17.948 | I15: 3.383 | J15: 0.346 | K15: 569.457 | L15: -0.989 | M15: 568.468 | N15: 164.197 | O15: 735.142 | P15: 169.102 | Q15: 0 | R15: 565.659 | S15: 498.167
B16: 2010Q4 | C16: 358.905 | D16: 118.817 | E16: 92.57 | F16: 50.337 | G16: 21.612 | H16: 17.522 | I16: 3.262 | J16: 0.364 | K16: 570.656 | L16: -2.502 | M16: 568.154 | N16: 167.102 | O16: 737.228 | P16: 170.871 | Q16: 0 | R16: 565.945 | S16: 498.906
... B97: 2031Q1 | C97: 469.62083 | D97: 164.05882 | E97: 150.32552 | F97: 79.969458 | G97: 41.526984 | H97: 26.561055 | I97: 2.2680235 | J97: 2.571 | K97: 786.57617 | L97: 1.3310574 | M97: 787.90722 | N97: 236.19704 | O97: 1024.1043 | P97: 256.74636 | Q97: 0.391 | R97: 767.7489 | S97: 693.87741
B98: 2008 | C98: 1433.301 | D98: 467.227 | E98: 399.172 | F98: 216.583 | G98: 109.895 | H98: 65.302 | I98: 10.192 | J98: -0.774 | K98: 2298.926 | L98: -8.579 | M98: 2290.347 | N98: 666.854 | O98: 2965.485 | P98: 657.982 | Q98: 0 | R98: 2306.008 | S98: 2020.533
B99: 2009 | C99: 1389.429 | D99: 473.734 | E99: 352.849 | F99: 186.202 | G99: 84.585 | H99: 70.081 | I99: 13.208 | J99: 2.386 | K99: 2218.398 | L99: -29.007 | M99: 2189.391 | N99: 613.953 | O99: 2811.686 | P99: 610.295 | Q99: 0 | R99: 2200.222 | S99: 1930.174
B100: 2010 | C100: 1427.124 | D100: 473.626 | E100: 361.216 | F100: 191.078 | G100: 86.256 | H100: 71.476 | I100: 13.467 | J100: -0.515 | K100: 2261.451 | L100: -7.025 | M100: 2254.426 | N100: 651.71 | O100: 2914.486 | P100: 663.086 | Q100: 0 | R100: 2249.959 | S100: 1980.708
B101: 2011 | C101: 1418.187 | D101: 472.11 | E101: 360.603 | F101: 199.419 | G101: 82.73 | H101: 66.506 | I101: 12.301 | J101: -0.775 | K101: 2250.125 | L101: 0.43 | M101: 2250.555 | N101: 695.989 | O101: 2952.109 | P101: 681.262 | Q101: 0 | R101: 2269.116 | S101: 2007.666
B102: 2012 | C102: 1446.168 | D102: 479.021 | E102: 367.983 | F102: 211.73 | G102: 82.477 | H102: 61.929 | I102: 11.296 | J102: -1.609 | K102: 2291.563 | L102: 4.545 | M102: 2296.108 | N102: 699.711 | O102: 3002.459 | P102: 696.649 | Q102: 0 | R102: 2303.794 | S102: 2049.074
B103: 2013 | C103: 1477.994 | D103: 479.189 | E103: 383.415 | F103: 221.254 | G103: 92.359 | H103: 58.295 | I103: 10.777 | J103: 6.577 | K103: 2347.175 | L103: 0.648 | M103: 2347.823 | N103: 702.7 | O103: 3064.553 | P103: 718.796 | Q103: 0 | R103: 2343.384 | S103: 2087.782
B104: 2014 | C104: 1518.913 | D104: 490.334 | E104: 411.507 | F104: 235.726 | G104: 97.12 | H104: 65.43 | I104: 12.568 | J104: 4.943 | K104: 2425.697 | L104: 20.925 | M104: 2446.622 | N104: 712.184 | O104: 3175.387 | P104: 755.205 | Q104: 0 | R104: 2417.439 | S104: 2155.831
B105: 2015 | C105: 1563.941 | D105: 495.189 | E105: 439.379 | F105: 256.423 | G105: 103.508 | H105: 66.528 | I105: 12.047 | J105: -0.831 | K105: 2497.678 | L105: 8.939 | M105: 2506.617 | N105: 738.202 | O105: 3263.96 | P105: 792.45 | Q105: 0 | R105: 2469.182 | S105: 2195.071
B106: 2016 | C106: 1619.767 | D106: 499.524 | E106: 466.345 | F106: 276.239 | G106: 111.832 | H106: 65.012 | I106: 12.218 | J106: -0.412 | K106: 2585.224 | L106: -15.807 | M106: 2569.417 | N106: 765.88 | O106: 3352.776 | P106: 827.957 | Q106: 0 | R106: 2523.665 | S106: 2244.315
B107: 2017 | C107: 1653.27 | D107: 504.596 | E107: 484.361 | F107: 278.862 | G107: 121.82 | H107: 71.075 | I107: 12.088 | J107: -0.766 | K107: 2641.461 | L107: -6.229 | M107: 2635.232 | N107: 815.172 | O107: 3454.44 | P107: 853.305 | Q107: 0 | R107: 2599.961 | S107: 2315.596
B108: 2018 | C108: 1687.414 | D108: 507.841 | E108: 483.363 | F108: 276.188 | G108: 130.036 | H108: 70.542 | I108: 6.334 | J108: 1.699 | K108: 2680.317 | L108: -1.5 | M108: 2678.817 | N108: 846.41 | O108: 3523.695 | P108: 882.424 | Q108: 0 | R108: 2640.295 | S108: 2348.685
B109: 2019 | C109: 1706.496 | D109: 522.794 | E109: 492.227 | F109: 280.224 | G109: 132.696 | H109: 72.89 | I109: 6.0812308 | J109: 1.436 | K109: 2722.953 | L109: -1.02 | M109: 2721.933 | N109: 862.521 | O109: 3583.95 | P109: 909.625 | Q109: 0 | R109: 2673.465 | S109: 2381.148
... B120: 2030 | C120: 1858.8175 | D120: 648.5633 | E120: 595.99815 | F120: 316.88042 | G120: 164.58474 | H120: 105.55641 | I120: 8.9765785 | J120: 10.284 | K120: 3113.663 | L120: 5.4339452 | M120: 3119.0969 | N120: 939.77742 | O120: 4058.8743 | P120: 1019.087 | Q120: 1.564 | R120: 3041.3513 | S120: 2747.7458
B121: 2008-09 | C121: 1412.941 | D121: 469.093 | E121: 388.301 | F121: 212.94 | G121: 99.97 | H121: 66.048 | I121: 11.693 | J121: 0.123 | K121: 2270.458 | L121: -11.511 | M121: 2258.947 | N121: 651.272 | O121: 2909.494 | P121: 638.262 | Q121: 0 | R121: 2269.769 | S121: 1990.305
B122: 2009-10 | C122: 1392.444 | D122: 473.821 | E122: 352.061 | F122: 184.905 | G122: 83.562 | H122: 71.237 | I122: 13.345 | J122: 0.504 | K122: 2218.83 | L122: -23.809 | M122: 2195.021 | N122: 619.222 | O122: 2826.899 | P122: 619.964 | Q122: 0 | R122: 2205.773 | S122: 1935.85
B123: 2010-11 | C123: 1432.915 | D123: 474.904 | E123: 360.567 | F123: 190.979 | G123: 86.298 | H123: 71.25 | I123: 13.206 | J123: -2.813 | K123: 2265.573 | L123: -4.686 | M123: 2260.887 | N123: 669.16 | O123: 2933.663 | P123: 671.346 | Q123: 0 | R123: 2260.83 | S123: 1992.087
B124: 2011-12 | C124: 1417.864 | D124: 474.358 | E124: 364.452 | F124: 206.141 | G124: 81.576 | H124: 64.597 | I124: 11.977 | J124: -0.13 | K124: 2256.544 | L124: -5.038 | M124: 2251.506 | N124: 701.65 | O124: 2964.894 | P124: 687.367 | Q124: 0 | R124: 2275.659 | S124: 2016.794
B125: 2012-13 | C125: 1456.88 | D125: 476.464 | E125: 367.582 | F125: 211.68 | G125: 84.167 | H125: 59.997 | I125: 11.248 | J125: 1.278 | K125: 2302.204 | L125: 9.344 | M125: 2311.548 | N125: 694.342 | O125: 3008.674 | P125: 696.599 | Q125: 0 | R125: 2310.127 | S125: 2056.462
B126: 2013-14 | C126: 1485.969 | D126: 482.447 | E126: 391.595 | F126: 224.303 | G126: 95.087 | H126: 60.709 | I126: 10.787 | J126: 6.848 | K126: 2366.859 | L126: 1.477 | M126: 2368.336 | N126: 702.864 | O126: 3091.332 | P126: 728.399 | Q126: 0 | R126: 2360.331 | S126: 2102.784
B127: 2014-15 | C127: 1532.817 | D127: 490.519 | E127: 420.537 | F127: 242.948 | G127: 97.726 | H127: 66.023 | I127: 13.09 | J127: 6.385 | K127: 2450.258 | L127: 25.945 | M127: 2476.203 | N127: 717.582 | O127: 3207.738 | P127: 771.184 | Q127: 0 | R127: 2433.819 | S127: 2170.395
B128: 2015-16 | C128: 1577.102 | D128: 497.553 | E128: 442.761 | F128: 261.559 | G128: 105.417 | H128: 63.153 | I128: 11.724 | J128: -2.874 | K128: 2514.542 | L128: -1.845 | M128: 2512.697 | N128: 745.131 | O128: 3280.497 | P128: 797.216 | Q128: 0 | R128: 2481.205 | S128: 2204.23
B129: 2016-17 | C129: 1630.199 | D129: 500.049 | E129: 471.326 | F129: 276.504 | G129: 114.953 | H129: 66.582 | I129: 12.315 | J129: -1.797 | K129: 2599.777 | L129: -12.356 | M129: 2587.421 | N129: 776.567 | O129: 3375.12 | P129: 832.926 | Q129: 0 | R129: 2541.029 | S129: 2261.286
B130: 2017-18 | C130: 1661.473 | D130: 505.834 | E130: 488.823 | F130: 280.546 | G130: 123.854 | H130: 73.337 | I130: 10.667 | J130: 0.262 | K130: 2656.392 | L130: -6.743 | M130: 2649.649 | N130: 825.668 | O130: 3476.53 | P130: 860.204 | Q130: 0 | R130: 2615.239 | S130: 2328.357
B131: 2018-19 | C131: 1694.832 | D131: 510.194 | E131: 484.947 | F131: 274.929 | G131: 132.073 | H131: 71.535 | I131: 6.1691512 | J131: 13.868 | K131: 2703.841 | L131: 10.005 | M131: 2713.846 | N131: 847.958 | O131: 3561.413 | P131: 912.718 | Q131: 0 | R131: 2648.01 | S131: 2355.839
B132: 2019-20 | C132: 1693.402 | D132: 523.336 | E132: 484.933 | F132: 278.852 | G132: 129.036 | H132: 70.716 | I132: 6.0650272 | J132: -10.111 | K132: 2691.56 | L132: -13.14 | M132: 2678.42 | N132: 858.752 | O132: 3536.522 | P132: 874.999 | Q132: 0 | R132: 2660.189 | S132: 2371.79
... B143: 2030-31 | C143: 1866.6715 | D143: 651.60801 | E143: 598.15573 | F143: 318.05248 | G143: 165.24243 | H143: 105.84331 | I143: 9.0175098 | J143: 10.284 | K143: 3126.7193 | L143: 5.3637651 | M143: 3132.083 | N143: 941.75854 | O143: 4073.8416 | P143: 1022.2374 | Q143: 1.564 | R143: 3053.1682 | S143: 2758.8185
B144: Definitions:
B145: Household and non-profit institutions serving households final consumption expenditure (ONS Economic Accounts Table 1.1.2, identifier: ABJR + HAYO)
B146: General government final consumption (ONS Economic Accounts Table 1.1.2, identifier: NMRY)
B147: Total gross fixed capital formation (ONS Economic Accounts Table 1.1.2, identifier: NPQT)
B148: Business investment (ONS Economic Accounts Table 1.1.8, identifier: NPEL)
B149: Private sector investment in dwellings, including transfer costs (ONS Economic Accounts Table 1.1.8, identifier: L636 + L637)
B150: General government gross fixed capital formation (ONS Economic Accounts Table 1.1.8, identifier: DLWF)
B151: Public corporations investment in dwellings, including transfer costs (ONS Economic Accounts Table 1.1.8, identifier: L634 + L635)
B152: Net acquisitions of valuables (ONS Economic Accounts Table 1.1.2, identifier: NPJR)
B153: Final domestic demand is the sum of private consumption, government consumption, fixed investment and net acquisition of valuables
B154: Change in inventories (ONS Economic Accounts Table 1.1.2, identifier: CAFU)
B155: Total domestic demand is the sum of final domestic demand and change in inventories
... B160: Gross domestic product at market prices (ONS Economic Accounts Table 1.1.2, identifier: ABMI)

Sheet OBR_NOV25_C4.1
A1: Back to contents
B2: Chart 4.1: National Accounts taxes as a share of GDP
B25: Year | C25: Outturn | D25: March 2025 restated forecast | E25: November 2025 pre-measures forecast | F25: November 2025 forecast
B26: 1945-46
B27: 1946-47
B28: 1947-48
B29: 1948-49 | C29: 37.207877
B30: 1949-50 | C30: 36.929904
B31: 1950-51 | C31: 36.075353
B32: 1951-52 | C32: 34.782913
B33: 1952-53 | C33: 33.953399
B34: 1953-54 | C34: 31.705124
B35: 1954-55 | C35: 30.913016
B36: 1955-56 | C36: 29.644955
B37: 1956-57 | C37: 29.247779
B38: 1957-58 | C38: 28.913468
B39: 1958-59 | C39: 29.529971
B40: 1959-60 | C40: 28.426722
... B104: 2023-24 | C104: 34.938578
B105: 2024-25 | C105: 34.679403 | D105: 34.908722 | E105: 34.679403 | F105: 34.679403
B106: 2025-26 | D106: 36.324617 | E106: 36.226501 | F106: 36.259415
B107: 2026-27 | D107: 36.960438 | E107: 37.025141 | F107: 37.028377
B108: 2027-28 | D108: 37.250776 | E108: 37.468544 | F108: 37.626717
B109: 2028-29 | D109: 37.068074 | E109: 37.371204 | F109: 37.759573
B110: 2029-30 | D110: 37.060318 | E110: 37.467175 | F110: 38.163528
B111: 2030-31 | E111: 37.491966 | F111: 38.269002

Sheet OBR_NOV25_C5.1
A1: Back to contents
B2: Chart 5.1: Public spending as a share of GDP
B25: Year | C25: Outturn | D25: March 2025 restated forecast | E25: November 2025 pre-measures | F25: November 2025 forecast
B26: 1945-46 | C26: 55.123752
B27: 1946-47 | C27: 43.473826
B28: 1947-48 | C28: 37.721182
B29: 1948-49 | C29: 38.599562
B30: 1949-50 | C30: 38.474813
B31: 1950-51 | C31: 39.183673
B32: 1951-52 | C32: 40.648815
B33: 1952-53 | C33: 41.271885
B34: 1953-54 | C34: 40.503446
B35: 1954-55 | C35: 38.923925
B36: 1955-56 | C36: 35.770115
B37: 1956-57 | C37: 35.957286
... B103: 2022-23 | C103: 44.057668
B104: 2023-24 | C104: 44.130674 | D104: 44.099803 | E104: 44.130674 | F104: 44.130674
B105: 2024-25 | C105: 44.008647 | D105: 43.942652 | E105: 44.008647 | F105: 44.008647
B106: 2025-26 | D106: 44.42442 | E106: 44.848606 | F106: 45.015764
B107: 2026-27 | D107: 44.231295 | E107: 44.602668 | F107: 44.735425
B108: 2027-28 | D108: 43.872029 | E108: 44.307118 | F108: 44.813096
B109: 2028-29 | D109: 43.499849 | E109: 44.067475 | F109: 44.494142
B110: 2029-30 | D110: 43.292936 | E110: 43.873983 | F110: 44.268372
B111: 2030-31 | E111: 43.846836 | F111: 44.284248

Sheet OBR_NOV25_C7.3
A1: Back to contents
B2: Chart 7.3: Probability of meeting and headroom against fiscal mandate
B26: Date | C26: Headroom (left axis) | D26: Probability of meeting fiscal mandate (right axis)
B27: Nov 10 | C27: 32.650819 | D27: 70
B28: Mar 11 | C28: 29.022951 | D28: 70
B29: Nov 11 | C29: 18.139344 | D29: 60
B30: Mar 12 | C30: 18.139344 | D30: 60
B31: Dec 12 | C31: 32.650819 | D31: 70
B32: Mar 13 | C32: 14.511475 | D32: 70
B33: Dec 13 | C33: 58.045901 | D33: 80
B34: Mar 14 | C34: 54.418032 | D34: 75
B35: Dec 14 | C35: 83.440983 | D35: 80
B36: Mar 15 | C36: 29.022951 | D36: 65
B37: Jul 15 | C37: 39.906557 | D37: 55
B38: Nov 15 | C38: 18.139344 | D38: 55
... B55: Nov 25 | C55: 21.699459 | D55: 59
B56: Average headroom of previous Chancellors (left axis) | C56: 29.423276

Sheet OBR_NOV25_TA.5
A1: Back to contents
B2: Table A.5: Current receipts
D3: £ billion
D4: Outturn | E4: Forecast
D5: 2024-25 | E5: 2025-26 | F5: 2026-27 | G5: 2027-28 | H5: 2028-29 | I5: 2029-30 | J5: 2030-31
B6: Income tax1 | D6: 305.905 | E6: 328.9612 | F6: 358.91903 | G6: 382.99334 | H6: 393.35755 | I6: 410.93251 | J6: 426.94697
B7: of which: | C7: Pay as you earn | D7: 262.131 | E7: 281.42134 | F7: 298.07126 | G7: 311.49314 | H7: 324.95986 | I7: 343.96024 | J7: 359.76234
C8: Self assessment | D8: 48.165 | E8: 53.277193 | F8: 62.488228 | G8: 68.755297 | H8: 72.43797 | I8: 73.63122 | J8: 74.071159
C9: Other income tax | D9: -4.391 | E9: -5.7373308 | F9: -1.6404589 | G9: 2.7449064 | H9: -4.0402817 | I9: -6.6589534 | J9: -6.886526
B10: National insurance contributions | D10: 171.402 | E10: 205.36409 | F10: 213.74561 | G10: 220.73516 | H10: 228.19271 | I10: 239.19487 | J10: 247.17347
B11: Value added tax | D11: 173.29 | E11: 179.61063 | F11: 188.8561 | G11: 197.99578 | H11: 205.72625 | I11: 214.8309 | J11: 223.96471
B12: Corporation tax2 | D12: 94.92 | E12: 98.78926 | F12: 104.1978 | G12: 109.95268 | H12: 114.12151 | I12: 117.8069 | J12: 122.82968
B13: of which: | C13: Onshore | D13: 92.687 | E13: 98.027181 | F13: 103.32507 | G13: 109.42438 | H13: 113.76839 | I13: 117.6136 | J13: 122.65242
C14: Offshore | D14: 2.233 | E14: 0.76207938 | F14: 0.8727224 | G14: 0.5282992 | H14: 0.35311334 | I14: 0.19329795 | J14: 0.17725845
B15: Petroleum revenue tax | D15: -0.35 | E15: -0.47175454 | F15: -0.20269365 | G15: -0.17519694 | H15: -0.14137822 | I15: -0.078599423 | J15: -0.094692
B16: Fuel duties | D16: 24.359 | E16: 23.979045 | F16: 24.217584 | G16: 26.172674 | H16: 26.257946 | I16: 25.996124 | J16: 25.344493
B17: Business rates | D17: 32.054 | E17: 33.621417 | F17: 37.062888 | G17: 37.950206 | H17: 38.838129 | I17: 41.919146 | J17: 41.989839
B18: Council tax3 | D18: 47.417 | E18: 50.91247 | F18: 53.554763 | G18: 56.563564 | H18: 60.129026 | I18: 63.331611 | J18: 66.67983
B19: VAT refunds | D19: 29.435 | E19: 30.495147 | F19: 31.360923 | G19: 32.688523 | H19: 33.365729 | I19: 34.371043 | J19: 35.871075
B20: Capital gains tax | D20: 13.686 | E20: 20.265673 | F20: 19.787229 | G20: 21.838455 | H20: 24.770296 | I20: 27.343346 | J20: 29.77483
B21: Inheritance tax | D21: 8.286 | E21: 8.6589015 | F21: 9.4696734 | G21: 11.074676 | H21: 12.596854 | I21: 13.528384 | J21: 14.456885
B22: Property transaction taxes4 | D22: 15.227 | E22: 16.433769 | F22: 19.230639 | G22: 21.610851 | H22: 24.10419 | I22: 26.261361 | J22: 27.970016
B23: Stamp taxes on shares | D23: 4.322 | E23: 4.4338848 | F23: 4.6436828 | G23: 4.8030225 | H23: 4.9540793 | I23: 5.1164691 | J23: 5.2758204
B24: Tobacco duties | D24: 7.909 | E24: 7.9689044 | F24: 7.7982073 | G24: 7.6504414 | H24: 7.4577445 | I24: 7.1739943 | J24: 7.0382649
B25: Alcohol duties | D25: 12.545 | E25: 11.900199 | F25: 12.321965 | G25: 12.75223 | H25: 13.200005 | I25: 13.661303 | J25: 14.058343
B26: Air passenger duty | D26: 4.131 | E26: 4.5514407 | F26: 5.2196256 | G26: 5.5594917 | H26: 5.854306 | I26: 6.1738015 | J26: 6.4801596
... B46: Memo: UK oil and gas revenues6 | D46: 4.597 | E46: 2.6959469 | F46: 2.4191167 | G46: 1.9650852 | H46: 1.6485947 | I46: 1.1914846 | J46: 0.2989223
B47: 1 Includes PAYE, self assessment, tax on savings income, and other minor components, such as income tax repayments.
B48: 2 National Accounts measure, includes Pillar 2 taxes.
B49: 3 Includes high-value council tax surcharge.
B50: 4 Includes stamp duty land tax, devolved property transaction taxes, and the annual tax on enveloped dwellings.
B51: 5 Consists of landfill tax and aggregates levy (ex devolved), betting & gaming duties, customs duties, diverted profits tax, soft drinks industry levy, residential property developer tax, the carbon border adjustment mechanism, vaping tax and plastic packaging tax.
B52: 6 Consists of offshore corporation tax, petroleum revenue tax, and energy profits levy.

Sheet OBR_NOV25_TA.9
A1: Back to contents
B2: Table A.9: Fiscal aggregates
C3: Per cent of GDP
C4: Outturn | D4: Forecast
C5: 2024-25 | D5: 2025-26 | E5: 2026-27 | F5: 2027-28 | G5: 2028-29 | H5: 2029-30 | I5: 2030-31
B6: Receipts and expenditure
B7: Public sector current receipts (a) | C7: 38.902214 | D7: 40.471753 | E7: 41.193638 | F7: 41.808726 | G7: 41.928354 | H7: 42.33151 | I7: 42.433163
B8: National Accounts taxes | C8: 34.679403 | D8: 36.259415 | E8: 37.028377 | F8: 37.626717 | G8: 37.759573 | H8: 38.163528 | I8: 38.269002
B9: Total managed expenditure (b) | C9: 44.008647 | D9: 45.015764 | E9: 44.735425 | F9: 44.813096 | G9: 44.494142 | H9: 44.268372 | I9: 44.284248
B10: Public sector current expenditure (c) | C10: 39.132908 | D10: 39.786591 | E10: 39.686255 | F10: 39.510777 | G10: 39.359746 | H10: 39.256917 | I10: 39.297379
B11: Public sector net investment (d) | C11: 2.5159747 | D11: 2.8230484 | E11: 2.6322266 | F11: 2.8648856 | G11: 2.6812157 | H11: 2.5561402 | I11: 2.528668
B12: Depreciation (e) | C12: 2.3597641 | D12: 2.4061243 | E12: 2.4169437 | F12: 2.437433 | G12: 2.4531798 | H12: 2.4553156 | I12: 2.4582007
B13: Fiscal mandate and supplementary target
B14: Current budget deficit (c+e-a) | C14: 2.5904583 | D14: 1.720962 | E14: 0.90956091 | F14: 0.1394846 | G14: -0.1154278 | H14: -0.61927729 | I14: -0.67758353
B15: Public sector net financial liabilities1 | C15: 81.253357 | D15: 83.064695 | E15: 83.283403 | F15: 83.64635 | G15: 83.67858 | H15: 82.995442 | I15: 82.179624
B16: Other deficit measures
B17: Public sector net borrowing (b-a) | C17: 5.106433 | D17: 4.5440104 | E17: 3.5417875 | F17: 3.0043702 | G17: 2.5657879 | H17: 1.9368629 | I17: 1.8510844
B18: Cyclically adjusted net borrowing | C18: 4.9194524 | D18: 4.1787901 | E18: 3.2288256 | F18: 2.8416596 | G18: 2.5005556 | H18: 1.9179287 | I18: 1.8475965
B19: Cyclically adjusted current budget deficit | C19: 2.4034777 | D19: 1.3557416 | E19: 0.59659901 | F19: -0.023226061 | G19: -0.18066013 | H19: -0.63821146 | I19: -0.68107147
B20: Primary deficit | C20: 2.253642 | D20: 1.5067549 | E20: 0.64214155 | F20: 0.066685204 | G20: -0.54457204 | H20: -1.2976717 | I20: -1.3575958
B21: Cyclically adjusted primary deficit | C21: 2.0666614 | D21: 1.1415346 | E21: 0.32917965 | F21: -0.096025455 | G21: -0.60980437 | H21: -1.3166059 | I21: -1.3610838
B22: Financing
B23: Central government net cash requirement | C23: 6.157882 | D23: 4.9212196 | E23: 4.2459236 | F23: 4.3197796 | G23: 4.1379396 | H23: 2.7559474 | I23: 3.1261318
B24: Public sector net cash requirement | C24: 2.4901446 | D24: 3.7056753 | E24: 3.5244144 | F24: 4.3862721 | G24: 4.1773454 | H24: 2.747832 | I24: 2.6752046
B25: Alternative balance sheet metrics
B26: Public sector net debt1 | C26: 93.621758 | D26: 95.026166 | E26: 95.296185 | F26: 96.346622 | G26: 96.987821 | H26: 96.835817 | I26: 96.06548
B27: Public sector net debt ex Bank of England1 | C27: 88.106638 | D27: 91.309569 | E27: 92.763843 | F27: 94.154287 | G27: 95.186976 | H27: 95.320848 | I27: 95.322636
B28: Public sector net worth (inverted)1 | C28: 69.763691 | D28: 70.425811 | E28: 70.19668 | F28: 70.257834 | G28: 70.258854 | H28: 69.512875 | I28: 68.03909
B29: International comparisons2
B30: General government net borrowing (GGNB) | C30: 5.7560126 | D30: 5.0180923 | E30: 4.1339898 | F30: 3.6155248 | G30: 3.2420245 | H30: 2.6126397 | I30: 2.4247895
B31: Cyclically adjusted GGNB | C31: 5.6788333 | D31: 5.0207486 | E31: 4.3480053 | F31: 3.8214385 | G31: 3.3606125 | H31: 2.6491293 | I31: 2.438259
B32: General government gross debt | C32: 99.794678 | D32: 101.39147 | E32: 103.11835 | F32: 104.13102 | G32: 104.88804 | H32: 105.02209 | I32: 104.80711
C33: £ billion
B34: Current budget deficit | C34: 75.818 | D34: 52.36728 | E34: 28.787103 | F34: 4.5715916 | G34: -3.9111533 | H34: -21.699459 | I34: -24.581842
B35: Public sector net investment | C35: 73.638 | D35: 85.902752 | E35: 83.308527 | F35: 93.896297 | G35: 90.850261 | H35: 89.567079 | I35: 91.736757
B36: Public sector net borrowing | C36: 149.456 | D36: 138.27003 | E36: 112.09563 | F36: 98.467888 | G36: 86.939108 | H36: 67.86762 | I36: 67.154915
B37: Cyclically adjusted net borrowing | C37: 143.98342 | D37: 127.15672 | E37: 102.19056 | F37: 93.135065 | G37: 84.728777 | H37: 67.204168 | I37: 67.028378
B38: Cyclically adjusted current budget deficit | C38: 70.345419 | D38: 41.253963 | E38: 18.882031 | F38: -0.76123147 | G38: -6.1214841 | H38: -22.362912 | I38: -24.708379
B39: Public sector net financial liabilities | C39: 2438.888 | D39: 2570.1865 | E39: 2682.7527 | F39: 2787.7383 | G39: 2882.3998 | H39: 2958.4603 | I39: 3033.7004
B40: Public sector net debt | C40: 2810.136 | D40: 2940.2982 | E40: 3069.7124 | F40: 3211.0088 | G40: 3340.851 | H40: 3451.8151 | I40: 3546.3035
B41: Public sector net debt ex Bank of England | C41: 2644.595 | D41: 2825.2993 | E41: 2988.1397 | F41: 3137.9434 | G41: 3278.819 | H41: 3397.8125 | I41: 3518.8811
B42: Net debt interest | C42: 83.155 | D42: 92.420874 | E42: 91.772203 | F42: 96.282288 | G42: 105.39138 | H42: 113.338 | I42: 116.40671
B43: Non-interest receipts | C43: 1095.803 | D43: 1189.0482 | E43: 1260.0402 | F43: 1324.675 | G43: 1374.135 | H43: 1434.6823 | I43: 1488.9289
B44: Memo: output gap (per cent of GDP) | C44: -0.38031648 | D44: -0.57831408 | E44: -0.39459817 | F44: -0.16758205 | G44: -0.063431833 | H44: -0.012495608 | I44: -0.0019776201
B45: 1 Position at end-March; GDP centred on end-March.
B46: 2 Calendar year basis.

Sheet PresentationalScorecardRounded
F1: Table 4.1 Budget 2025 policy decisions (£ million)1,2
H2: Head3 | I2: 2025-26 | J2: 2026-27 | K2: 2027-28 | L2: 2028-29 | M2: 2029-30 | N2: 2030-31
F3: Getting inflation down and tackling the cost of living
F4: 1 | G4: Renewables Obligation: Fund 75% of the domestic share of the Renewables Obligation via the Exchequer over the Spending Review period | H4: Spend | I4: 0 | J4: -2580 | K4: -2100 | L4: -2195 | M4: 0 | N4: 0
F5: 2 | G5: Warm Homes Plan: Increase funding for the Warm Homes Plan and expand the Warm Home Discount Scheme | H5: Spend | I5: 0 | J5: -355 | K5: -535 | L5: -535 | M5: -355 | N5: 0
F6: 3 | G6: Fuel Duty: Cancel uprating for 2026-27; extend the 5p cut in rates to 31 August 2026, then increase by 1p from 1 September 2026, 2p from 1 December 2026, and 2p from 1 March 2027 | H6: Tax | I6: -45 | J6: -2370 | K6: -855 | L6: -855 | M6: -850 | N6: -840
F7: 4 | G7: Rail Fares: Freeze rail fares in England for one year from 1 March 2026 | H7: Spend | I7: 0 | J7: -145 | K7: -150 | L7: -155 | M7: -160 | N7: -165
F8: 5 | G8: Health and Social Care: Freeze NHS prescription charges in England for one year from 1 April 2026 | H8: Spend | I8: 0 | J8: -15 | K8: -15 | L8: -15 | M8: -15 | N8: -15
F10: Tackling child poverty and reforming welfare
F11: 6 | G11: Universal Credit Child Element: Remove the two child limit from April 2026, taking 450,000 children out of poverty | H11: Spend | I11: 0 | J11: -2365 | K11: -2590 | L11: -2815 | M11: -3095 | N11: -3235
F12: 7 | G12: Universal Credit: Extend the £2,500 surplus earnings threshold for one year from 6 April 2026 | H12: Spend | I12: 0 | J12: -145 | K12: 0 | L12: 0 | M12: 0 | N12: 0
F13: 8 | G13: Child Benefit: Exempt 16–19-year-olds with an illness or disability from the 12-hour weekly rule and equalise the treatment of non-standard educational settings from 1 September 2025 | H13: Spend | I13: -15 | J13: -25 | K13: -25 | L13: -25 | M13: -25 | N13: -25
F14: 9 | G14: Carer’s Allowance Review: Reassess overpayments from 2015 to 2025 caused by incorrect operational guidance | H14: Spend | I14: 0 | J14: -20 | K14: -35 | L14: -20 | M14: 0 | N14: 0
F15: 10 | G15: Housing Benefit: Reduce the financial cliff edge for claimants in supported housing and temporary accommodation from Autumn 2026 | H15: Spend | I15: 0 | J15: -10 | K15: -20 | L15: -25 | M15: -25 | N15: -25
F16: 11 | G16: DWP Fraud and Error: Extend Targeted Case Review of Universal Credit to 2030-31 | H16: Spend | I16: 0 | J16: 0 | K16: 0 | L16: 0 | M16: 0 | N16: 1265
F17: 12 | G17: DWP Fraud and Error: Improve accuracy in Pension Credit claims from April 2026 | H17: Spend | I17: 0 | J17: 15 | K17: 85 | L17: 135 | M17: 75 | N17: 60
F18: 13 | G18: Health and Disability Benefits: Improve operations by increasing face-to-face assessments, increasing WCA reassessment capability, and PIP award review changes, starting from April 2026 | H18: Spend | I18: 0 | J18: 85 | K18: 310 | L18: 520 | M18: 580 | N18: 455
F19: 14 | G19: Motability: Introduce VAT at the standard rate on Advance Payments paid to Motability or equivalent schemes, and Insurance Premium Tax at the standard rate on insurance related to vehicle leases, from 1 July 2026 | H19: Tax | I19: 0 | J19: 90 | K19: 165 | L19: 225 | M19: 280 | N19: 305
F20: 15 | G20: Housing Benefit and Pension Credit Administration: Bring together the administration of pensioner Housing Benefit and Pension Credit from Autumn 2026 | H20: Spend | I20: 0 | J20: -5 | K20: -10 | L20: 105 | M20: 225 | N20: 265
F21: 16 | G21: National Insurance: Remove access to Class 2 National Insurance contributions (NICs) and increase the initial residency and contributions history requirements for Class 3 NICs for individuals abroad from 6 April 2026 | H21: Spend | I21: 0 | J21: -5 | K21: 5 | L21: 10 | M21: 10 | N21: 15
F23: Growth, business & entrepreneurship
F24: 17 | G24: Rebuilding Britain: Accelerate delivery of growth-enhancing capital investment, including the Lower Thames Crossing | H24: Spend | I24: 0 | J24: -3210 | K24: -1015 | L24: 1100 | M24: 1525 | N24: -310
F25: 18 | G25: Business Rates: Introduce both a three year Transitional Relief scheme, partially funded by a 1p Transitional Relief Supplement in 2026/27, and a Supporting Small Business scheme from 1 April 2026 | H25: Tax | I25: 40 | J25: -2140 | K25: -1390 | L25: -885 | M25: 15 | N25: -5
F26: 19 | G26: Business Rates: Introduce two new lower multipliers for eligible retail, hospitality and leisure properties funded by a new high-value multiplier from 1 April 2026 | H26: Tax | I26: 0 | J26: -50 | K26: 40 | L26: 35 | M26: 35 | N26: 35
F27: 20 | G27: Enterprise Management Incentives (EMI): Increase eligibility to allow scale-ups, as well as start-ups, to access the scheme from 6 April 2026 | H27: Tax | I27: 0 | J27: -70 | K27: -230 | L27: -410 | M27: -585 | N27: -695
F28: 21 | G28: Venture Capital Schemes: Increase the Venture Capital Trust (VCT) scheme and the Enterprise Investment Scheme (EIS) annual and lifetime investment limits and the gross assets test from 6 April 2026 | H28: Tax | I28: 0 | J28: 0 | K28: -60 | L28: -45 | M28: -50 | N28: -55
F29: 22 | G29: Venture Capital Schemes: Reduce the VCT scheme Income Tax relief from 6 April 2026 | H29: Tax | I29: 0 | J29: 0 | K29: 125 | L29: 95 | M29: 95 | N29: 100
F30: 23 | G30: UK Listing Relief: Stamp Duty Reserve Tax relief for transfers of a company's securities for a three-year period from the point of listing, effective from 27 November 2025 | H30: Tax | I30: -25 | J30: -35 | K30: -45 | L30: -50 | M30: -50 | N30: -50
F31: 24 | G31: Jobs and Skills: Invest in Youth Guarantee, Growth and Skills Levy, and employment & skills support4 | H31: Spend | I31: 0 | J31: -520 | K31: -555 | L31: -495 | M31: -110 | N31: -105
F32: 25 | G32: Planning Capacity and Capability: Fund additional capacity in the planning system to get Britain building | H32: Spend | I32: 0 | J32: -20 | K32: -20 | L32: -20 | M32: 0 | N32: 0
F33: 26 | G33: British Business Bank: Expand the Growth Guarantee Scheme to support businesses impacted by changes in global tariffs | H33: Spend | I33: -50 | J33: 0 | K33: 0 | L33: 0 | M33: 0 | N33: 0
F34: 27 | G34: Clamping Down on Illegal High Street Operations: Invest in a new cross-government taskforce, additional Insolvency Service staff and enhanced Trading Standards and law enforcement capabilities | H34: Spend | I34: 0 | J34: -15 | K34: -15 | L34: -15 | M34: 0 | N34: 0
F35: 28 | G35: VAT: Introduce a relief for business donations of goods to charity for onward distribution or use in the delivery of their services, from 1 April 2026 | H35: Tax | I35: 0 | J35: -10 | K35: -10 | L35: -10 | M35: -10 | N35: -10
... F43: 36 | G43: Port Talbot: Remediate contaminated brownfield land adjacent to the Celtic Freeport | H43: Spend | I43: 0 | J43: -5 | K43: 0 | L43: 0 | M43: 0 | N43: 0
F45: Cutting waste and investing in public services
F46: 37 | G46: RDEL: Go further on efficiencies and savings | H46: Spend | I46: 0 | J46: 0 | K46: 0 | L46: 1415 | M46: 3950 | N46: 4900
F47: 38 | G47: Health and Social Care: Bringing forward SR25 funding to support the abolition of NHS England and unlock savings | H47: Spend | I47: -510 | J47: -510 | K47: 70 | L47: 955 | M47: 975 | N47: 1010
F48: 39 | G48: NHS: Investing in NHS technology to improve productivity | H48: Spend | I48: 0 | J48: 0 | K48: -355 | L48: 0 | M48: 0 | N48: 0
F49: 40 | G49: Home Office: Provide additional funding to tackle people smuggling gangs | H49: Spend | I49: -100 | J49: 0 | K49: 0 | L49: 0 | M49: 0 | N49: 0
F50: 41 | G50: Systems & Compliance: Invest in HMRC, DWP and other departments to: reduce fraud and error in the welfare system & public sector; ensure tax compliance and implement Budget tax measures; and increase departmental resilience to economic shocks | H50: Spend | I50: 0 | J50: -410 | K50: -490 | L50: -295 | M50: -165 | N50: -220
F51: 42 | G51: National Year of Reading: Fund state-funded secondary schools in England to increase book supplies | H51: Spend | I51: 0 | J51: -5 | K51: 0 | L51: 0 | M51: 0 | N51: 0
F52: 43 | G52: Investing in Communities: Provide funding to refurbish and improve up to 200 playgrounds in England | H52: Spend | I52: 0 | J52: -10 | K52: -10 | L52: 0 | M52: 0 | N52: 0
F53: 44 | G53: Environmental Regeneration: Launch a new grant scheme for public bodies to support land remediation and reinvest water company fines in projects to clean up rivers, lakes and seas | H53: Spend | I53: 0 | J53: -20 | K53: -5 | L53: 35 | M53: 10 | N53: 10
F54: 45 | G54: UK-EU Deal: Fund DEFRA costs in 2025-26 for domestic implementation of UK-EU Sanitary and Phytosanitary Agreement | H54: Spend | I54: -30 | J54: 0 | K54: 0 | L54: 0 | M54: 0 | N54: 0
F56: Raising revenue fairly
F57: 46 | G57: Personal Tax: Maintain the personal income tax and equivalent national insurance thresholds at current levels for a further three years until April 2031 | H57: Tax | I57: 0 | J57: 0 | K57: -25 | L57: 3365 | M57: 7780 | N57: 12435
F58: 47 | G58: National Insurance: Maintain the secondary threshold for employer contributions at current level for a further three years until April 2031 | H58: Tax | I58: 0 | J58: 0 | K58: -5 | L58: 290 | M58: 615 | N58: 925
F59: 48 | G59: Student Loans: Freeze Plan 2 repayment threshold for three years from 6 April 2027 | H59: Spend | I59: 285 | J59: 5915 | K59: 255 | L59: 290 | M59: 355 | N59: 380
F60: 49 | G60: Property Income: Introduce separate tax rates for property income at 22% for the property basic rate, 42% for the property higher rate and 47% for the property additional rate, from 6 April 2027 | H60: Tax | I60: 0 | J60: 0 | K60: 5 | L60: 590 | M60: 435 | N60: 445
F61: 50 | G61: Dividend Income: Increase tax rates on dividend income by 2ppts at the ordinary and upper rate from 6 April 2026 | H61: Tax | I61: 0 | J61: 280 | K61: 985 | L61: 1160 | M61: 1325 | N61: 1390
F62: 51 | G62: Savings Income: Increase tax rates on savings income by 2ppts at the basic, higher and additional rate from 6 April 2027 and maintain the Starting Rate of Savings limit at £5000 from April 2026 to April 2031 | H62: Tax | I62: 0 | J62: 5 | K62: 55 | L62: 525 | M62: 470 | N62: 505
F63: 52 | G63: Salary Sacrifice: Limit the value of salary sacrificed pension contributions that can receive employee and employer NICs relief to £2,000 per year from 6 April 2029 | H63: Tax | I63: 0 | J63: -40 | K63: -55 | L63: -75 | M63: 4845 | N63: 2585
F64: 53 | G64: Capital Gains Tax: Reduce Capital Gains Tax relief on qualifying disposals to employee ownership trusts from 100% to 50% from 26 November 2025 | H64: Tax | I64: 0 | J64: 185 | K64: 775 | L64: 825 | M64: 905 | N64: 985
F65: 54 | G65: High Value Council Tax Surcharge: Introduce a surcharge on owners of residential properties valued over £2m in England from 1 April 2028 | H65: Tax | I65: -60 | J65: -120 | K65: -155 | L65: 400 | M65: 430 | N65: 435
F66: 55 | G66: Inheritance Tax: Maintain the nil-rate band, residence nil-rate band, and allowance for 100% rate of agricultural property relief and business property relief for a further year, from April 2030 until April 2031 | H66: Tax | I66: 0 | J66: 0 | K66: 0 | L66: 0 | M66: 0 | N66: 130
F67: 56 | G67: Cap trust charges at £5m for pre-30 October 2024 excluded property trusts for charges applying from 6 April 2025 and close post-departure trade profits loophole from 6 April 2026 | H67: Tax | I67: 0 | J67: -5 | K67: 110 | L67: 155 | M67: 140 | N67: 110
F68: 57 | G68: Writing-down Allowances: Reduce the main rate writing-down allowance to 14% from April 2026 and introduce a new 40% first-year allowance from 1 January 2026 | H68: Tax | I68: 35 | J68: 1035 | K68: 1505 | L68: 1490 | M68: 1470 | N68: 1450
... F70: 59 | G70: HMRC: Further measures to close the tax gap5 | H70: Tax | I70: 75 | J70: 435 | K70: 695 | L70: 1250 | M70: 2415 | N70: 2590
F72: Modernising the tax system
F73: 60 | G73: Gambling Duty: Increase Remote Gaming Duty to 40% from 1 April 2026, introduce a new Remote Betting Rate at 25% (excluding Self-Service Betting Terminals, spread betting, pool betting & UK horseracing) from 1 April 2027, and abolish Bingo Duty from 1 April 2026 | H73: Tax | I73: 0 | J73: 810 | K73: 1065 | L73: 1100 | M73: 1135 | N73: 1155
F74: 61 | G74: Gambling Commission: Provide funding to tackle the illegal market | H74: Spend | I74: 0 | J74: -5 | K74: -10 | L74: -10 | M74: 0 | N74: 0
F75: 62 | G75: Tour Operators' Margin Scheme: Exclude Private Hire Vehicle Services from the scope of the scheme from 2 January 2026 | H75: Tax | I75: 190 | J75: 725 | K75: 665 | L75: 655 | M75: 650 | N75: 675
F76: 63 | G76: Low Value Imports: Reform the customs treatment of low value imports from March 2029 | H76: Tax | I76: 0 | J76: 0 | K76: 0 | L76: 40 | M76: 535 | N76: 555
F77: 64 | G77: Emissions Trading Scheme (ETS): Expansion of the UK ETS to International Maritime Routes from 2028 | H77: Tax | I77: 0 | J77: 0 | K77: 0 | L77: 75 | M77: 290 | N77: 285
F78: 65 | G78: Defined Benefit (DB) Pension Scheme Surplus Extraction: Introduce flexibilities for employers and direct payments to members from April 2027 | H78: Tax | I78: 0 | J78: 30 | K78: 120 | L78: 125 | M78: 135 | N78: 145
F79: 66 | G79: Landfill Tax: Increase the lower rate by the cash increase of the standard rate from 1 April 2026 and in each year of the forecast period | H79: Tax | I79: 0 | J79: 35 | K79: 60 | L79: 85 | M79: 110 | N79: 130
F80: 67 | G80: Soft Drink Industry Levy: Reduce the levy threshold from 5g to 4.5g/100ml and extend to milk-based drinks and milk substitutes from 1 January 2028 | H80: Tax | I80: 0 | J80: 0 | K80: 10 | L80: 40 | M80: 40 | N80: 40
F81: 68 | G81: Non-reimbursed Homeworking Expenses: Remove the tax relief available from 6 April 2026 | H81: Tax | I81: 0 | J81: 10 | K81: 30 | L81: 25 | M81: 25 | N81: 25
F82: 69 | G82: Carbon Border Adjustment Mechanism (CBAM): Remove indirect emissions from scope of the CBAM from 1 January 2027 | H82: Tax | I82: 0 | J82: -40 | K82: -170 | L82: -180 | M82: -170 | N82: -165
F83: 70 | G83: Advanced Corporation Tax (ACT) reform: Abolish shadow ACT restrictions to relax the limits on companies’ use of surplus ACT balances from 1 April 2026 | H83: Tax | I83: 0 | J83: -10 | K83: -10 | L83: -15 | M83: -15 | N83: -10
F85: Modernising motoring tax and supporting the British automative industry
F86: 71 | G86: Electric Vehicle Excise Duty (eVED): Introduce a new mileage supplement for electric and plug-in hybrid cars from 1 April 2028 | H86: Tax | I86: -5 | J86: -10 | K86: -15 | L86: 1100 | M86: 1435 | N86: 1865
F87: 72 | G87: Support for British automotive industry: Provide additional Electric Car Grant funding & extend to 2029-30 and invest in EV charging infrastructure | H87: Spend | I87: -50 | J87: -215 | K87: -340 | L87: -440 | M87: -425 | N87: -25
F88: 73 | G88: Support for British automotive industry: Increase the Expensive Car Supplement threshold for zero emission vehicles to £50,000, from 1 April 2026 | H88: Tax | I88: 0 | J88: -50 | K88: -110 | L88: -190 | M88: -325 | N88: -505
