Workbook
Name _DLX1.INC: HAVERM!$A$2:$CG$7
Name _DLX2.INC: HAVERQ!$A$2:$CY$7
Name Data: [1]sheet0!$C$2

Sheet CHARTS>>

Sheet DATA>>

Sheet Chart Data
A1: Change in jobs since 2019 - private vs public | E1: Composition of public sector employment | M1: Composition of public sector employment (shares) | U1: Composition of public sector employment (change since 2000) | AD1: Change in WFJ since 2019 | AE1: =HAVERQ!T186 -> 360 | AF1: =HAVERQ!U186 -> 47 | AG1: =HAVERQ!V186 -> 2589 | AH1: =HAVERQ!W186 -> 139 | AI1: =HAVERQ!X186 -> 245 | AJ1: =HAVERQ!Y186 -> 2220 | AK1: =HAVERQ!Z186 -> 4704 | AL1: =HAVERQ!AA186 -> 1879 | ... AV1: =HAVERQ!AK186 -> 1103 | AW1: =HAVERQ!AL186+HAVERQ!AK186 -> 2027 | BA1: Change in WFJ since 2019 | BU1: Change in WFJ since 2019 | CF1: Vacancies per 100 jobs | DB1: Productivity (output per job) | DW1: WFJ forecast | FD1: WFJ forecast - public sector, private sector by pay level | FJ1: WFJ forecast - public sector, private sector by pay level | FP1: HMRC RTI by sector (3m/3m) | GL1: HMRC RTI by sector (3m/3m) | GW1: HMRC RTI by sector (level) | HH1: Pay vs HMRC RTI | HL1: Pay vs vacancies | HP1: Government spending (% of GDP) | HU1: Government spending (per head) | HZ1: Public & private sector employment | IE1: Change in jobs since 2019 - private vs public | II1: Change in jobs since 2019 - private vs public | IM1: WFJ - public emlpoyment vs other | IQ1: Change in jobs since 2019 - private vs public
B3: Public sector | C3: Private sector | F3: NHS | G3: Education | H3: Public administration | I3: Police | J3: HM forces | K3: Other | N3: NHS | O3: Education | P3: Public administration | Q3: Police | R3: HM forces | S3: Other | V3: NHS | W3: Education | X3: Public administration | Y3: Police | Z3: HM forces | AA3: Other | AB3: Total | AE3: Agriculture | AF3: Extraction | AG3: Manufacturing | AH3: Utilities | AI3: Water | AJ3: Construction | AK3: Wholesale & retail | AL3: Transport | AM3: Accommodation & food | AN3: Communications | AO3: Financial services | AP3: Real estate | AQ3: Professional services | AR3: Administrative services | AS3: Public admin | AT3: Education | AU3: Health | AV3: Art & recreation | AW3: Other services | AY3: Other services | BB3: Agriculture | BC3: Extraction & utilities | BD3: Manufacturing | BE3: Construction | BF3: Distribution, accommodation & food | BG3: Transport, storage & comms | BH3: Business services & finance | BI3: Government & other services | BK3: Agriculture | BL3: Extraction & utilities | BM3: Manufacturing | BN3: Construction | BO3: Distribution, accommodation & food | BP3: Transport, storage & comms | BQ3: Business services & finance | BR3: Government & other services | BS3: Check | BV3: Agriculture | BW3: Extraction & utilities | BX3: Manufacturing | BY3: Construction | BZ3: Distribution, accommodation & food | CA3: Transport, storage & comms | CB3: Business services & finance | CC3: Government & other services | CD3: Check | CG3: Total | CI3: Extraction | CJ3: Manufacturing | CK3: Utilities | CL3: Water | CM3: Construction | CN3: Wholesale & retail | CO3: Transport | CP3: Accommodation & food | CQ3: Communications | CR3: Financial services | CS3: Real estate | CT3: Professional services | CU3: Administrative services | CV3: Public admin | CW3: Education | CX3: Health | CY3: Art & recreation | CZ3: Other services | DC3: Agriculture | DD3: Extraction | DE3: Manufacturing | DF3: Utilities | DG3: Water | DH3: Construction | DI3: Wholesale & retail | DJ3: Transport | DK3: Accommodation & food | DL3: Communications | DM3: Financial services | DN3: Real estate | DO3: Professional services | DP3: Administrative services | DQ3: Public admin | DR3: Education | DS3: Health | DT3: Art & recreation | DU3: Other services | DX3: Total | DY3: Agriculture | DZ3: Extraction | EA3: Manufacturing | EB3: Utilities | EC3: Water | ED3: Construction | EE3: Wholesale & retail | EF3: Transport | EG3: Accommodation & food | EH3: Communications | EI3: Financial services | EJ3: Real estate | EK3: Professional services | EL3: Administrative services | EM3: Public admin | EN3: Education | EO3: Health | EP3: Art & recreation | EQ3: Other services | ET3: Agriculture | EU3: Extraction & utilities | EV3: Manufacturing | EW3: Construction | EX3: Distribution, accommodation & food | EY3: Transport, storage & comms | EZ3: Business services & finance | FA3: Government & other services | FB3: Check | FE3: Government & other services | FF3: Private sector - higher paid* | FG3: Private sector - lower paid* | FH3: Check | FK3: Government & other services | FL3: Private sector - higher paid* | FM3: Private sector - lower paid* | FN3: Total | FQ3: Total | FR3: Agriculture | FS3: Extraction | FT3: Manufacturing | FU3: Utilities | FV3: Water | FW3: Construction | FX3: Wholesale & retail | FY3: Transport | FZ3: Accommodation & food | GA3: Communications | GB3: Financial services | GC3: Real estate | GD3: Professional services | GE3: Administrative services | GF3: Public admin | GG3: Education | GH3: Health | GI3: Art & recreation | GJ3: Other services | GM3: Agriculture | GN3: Extraction & utilities | GO3: Manufacturing | GP3: Construction | GQ3: Distribution, accommodation & food | GR3: Transport & comms | GS3: Financial services | GT3: Business services | GU3: Public services | GX3: Agriculture | GY3: Extraction & utilities | GZ3: Manufacturing | HA3: Construction | HB3: Distribution, accommodation & food | HC3: Transport & comms | HD3: Financial services | HE3: Business services | HF3: Public services | HH3: Sector | HI3: Median pay | HJ3: Employee growth | HL3: Sector | HM3: Median pay | HN3: Vacancies per 100 jobs | HQ3: Current spending | HR3: Capital spending | HS3: Total | HV3: Current spending | HW3: Capital spending | HX3: Total | IA3: Public sector | IB3: Private sector | IC3: Check | IF3: Public sector | IG3: Private sector | IJ3: Public sector | IK3: Private sector | IN3: Government & other services | IO3: Mainly private sector | IR3: Government & other services | IS3: Mainly private sector
A4: 43466 | B4: =HAVERQ!E164-AVERAGE(HAVERQ!E$164:E$167) -> -30.75 | C4: =HAVERQ!F164-AVERAGE(HAVERQ!F$164:F$167) -> -66 | E4: 36526 | F4: =HAVERQ!P88 -> 1197 | G4: =HAVERQ!O88 -> 1406 | H4: =HAVERQ!N88 -> 1184 | I4: =HAVERQ!M88 -> 225 | J4: =HAVERQ!L88 -> 217 | K4: =HAVERQ!E88-F4-G4-H4-I4-J4 -> 800 | M4: 36526 | N4: =100*(F4/SUM($F4:$K4)) -> 23.801949 | O4: =100*(G4/SUM($F4:$K4)) -> 27.957845 | P4: =100*(H4/SUM($F4:$K4)) -> 23.543448 | Q4: =100*(I4/SUM($F4:$K4)) -> 4.4740505 | R4: =100*(J4/SUM($F4:$K4)) -> 4.3149732 | S4: =100*(K4/SUM($F4:$K4)) -> 15.907735 | U4: 36526 | V4: =F4-AVERAGE(F$4:F$7) -> -12.25 | W4: =G4-AVERAGE(G$4:G$7) -> -33.75 | X4: =H4-AVERAGE(H$4:H$7) -> 5 | Y4: =I4-AVERAGE(I$4:I$7) -> -0.75 | Z4: =J4-AVERAGE(J$4:J$7) -> 0.75 | AA4: =K4-AVERAGE(K$4:K$7) -> 12.25 | AB4: =SUM(V4:AA4) -> -28.75 | AD4: 43466 | AE4: =HAVERQ!T164-AVERAGE(HAVERQ!T$164:T$167) -> -11.25 | AF4: =HAVERQ!U164-AVERAGE(HAVERQ!U$164:U$167) -> 0.75 | AG4: =HAVERQ!V164-AVERAGE(HAVERQ!V$164:V$167) -> 14.25 | AH4: =HAVERQ!W164-AVERAGE(HAVERQ!W$164:W$167) -> -0.75 | AI4: =HAVERQ!X164-AVERAGE(HAVERQ!X$164:X$167) -> 5.5 | AJ4: =HAVERQ!Y164-AVERAGE(HAVERQ!Y$164:Y$167) -> 27.75 | AK4: =HAVERQ!Z164-AVERAGE(HAVERQ!Z$164:Z$167) -> 27.5 | AL4: =HAVERQ!AA164-AVERAGE(HAVERQ!AA$164:AA$167) -> -20 | ... AV4: =HAVERQ!AK164-AVERAGE(HAVERQ!AK$164:AK$167) -> -5.75 | AW4: =AY4-AVERAGE(AY$4:AY$7) -> -9.5 | AY4: =HAVERQ!AL164+HAVERQ!AM164 -> 1008 | BA4: 43466 | BB4: =BK4-AVERAGE(BK$4:BK$7) -> -11.25 | BC4: =BL4-AVERAGE(BL$4:BL$7) -> 5.5 | BD4: =BM4-AVERAGE(BM$4:BM$7) -> 14.25 | BE4: =BN4-AVERAGE(BN$4:BN$7) -> 27.75 | BF4: =BO4-AVERAGE(BO$4:BO$7) -> -5.5 | BG4: =BP4-AVERAGE(BP$4:BP$7) -> -36.25 | BH4: =BQ4-AVERAGE(BQ$4:BQ$7) -> -60.5 | BI4: =BR4-AVERAGE(BR$4:BR$7) -> -59.25 | BK4: =HAVERQ!T164 -> 387 | BL4: =HAVERQ!U164+HAVERQ!W164+HAVERQ!X164 -> 431 | BM4: =HAVERQ!V164 -> 2705 | BN4: =HAVERQ!Y164 -> 2361 | BO4: =HAVERQ!Z164+HAVERQ!AB164 -> 7499 | BP4: =HAVERQ!AA164+HAVERQ!AC164 -> 3270 | BQ4: =HAVERQ!AD164+HAVERQ!AE164+HAVERQ!AF164+HAVERQ!AG164 -> 7906 | BR4: =HAVERQ!AH164+HAVERQ!AI164+HAVERQ!AJ164+HAVERQ!AK164+HAVERQ!AL164+HAVERQ!AM164 -> 10881 | BS4: =HAVERQ!S164-SUM('Chart Data'!BK4:BR4) -> -2 | BU4: 34335 | BV4: =HAVERQ!T64 -> 492 | BW4: =HAVERQ!U64+HAVERQ!W64+HAVERQ!X64 -> 369 | BX4: =HAVERQ!V64 -> 4096 | BY4: =HAVERQ!Y64 -> 1867 | BZ4: =HAVERQ!Z64+HAVERQ!AB64 -> 6146 | CA4: =HAVERQ!AA64+HAVERQ!AC64 -> 2072 | CB4: =HAVERQ!AD64+HAVERQ!AE64+HAVERQ!AF64+HAVERQ!AG64 -> 4497 | CC4: =HAVERQ!AH64+HAVERQ!AI64+HAVERQ!AJ64+HAVERQ!AK64+HAVERQ!AL64+HAVERQ!AM64 -> 8091 | CD4: =HAVERQ!S64-SUM('Chart Data'!BV4:CC4) -> 0 | CF4: Q1 2025 | CG4: =AVERAGE(HAVERM!X548:X550) -> 2.4333333 | CI4: =AVERAGE(HAVERM!Y548:Y550) -> 3.2666667 | CJ4: =AVERAGE(HAVERM!Z548:Z550) -> 2.1666667 | CK4: =AVERAGE(HAVERM!AA548:AA550) -> 3 | CL4: =AVERAGE(HAVERM!AB548:AB550) -> 2.6666667 | CM4: =AVERAGE(HAVERM!AC548:AC550) -> 2.6 | CN4: =AVERAGE(HAVERM!AD548:AD550) -> 2.2666667 | CO4: =AVERAGE(HAVERM!AE548:AE550) -> 2.1 | CP4: =AVERAGE(HAVERM!AF548:AF550) -> 3.2333333 | ... CZ4: =AVERAGE(HAVERM!AP548:AP550) -> 2.1666667 | DB4: 36161 | DC4: =HAVERQ!BI84/HAVERQ!T84 -> 6.7752294 | DD4: =HAVERQ!BJ84/HAVERQ!U84 -> 601.54545 | DE4: =HAVERQ!BK84/HAVERQ!V84 -> 8.9590026 | DF4: =HAVERQ!BL84/HAVERQ!W84 -> 84.490196 | DG4: =HAVERQ!BM84/HAVERQ!X84 -> 41.506098 | DH4: =HAVERQ!BN84/HAVERQ!Y84 -> 17.63482 | DI4: =HAVERQ!BO84/HAVERQ!Z84 -> 9.5327448 | DJ4: =HAVERQ!BP84/HAVERQ!AA84 -> 13.231055 | ... DT4: =HAVERQ!BZ84/HAVERQ!AK84 -> 9.4086957 | DU4: =(HAVERQ!CA84+HAVERQ!CB84)/HAVERQ!AL84 -> 11.871099 | DW4: 2019 | DX4: =DataA!B53 -> 35565 | DY4: =DataA!C53 -> 398.25 | DZ4: =DataA!D53 -> 61.25 | EA4: =DataA!E53 -> 2690.75 | EB4: =DataA!F53 -> 141.75 | EC4: =DataA!G53 -> 222.5 | ED4: =DataA!H53 -> 2333.25 | EE4: =DataA!I53 -> 5005.5 | ... EQ4: =DataA!U53 -> 1017.5 | ES4: 2019 | ET4: =DY4 -> 398.25 | EU4: =DZ4+EB4+EC4 -> 425.5 | EV4: =EA4 -> 2690.75 | EW4: =ED4 -> 2333.25 | EX4: =EE4+EG4 -> 7504.5 | EY4: =EF4+EH4 -> 3306.25 | EZ4: =EI4+EJ4+EK4+EL4 -> 7966.5 | FA4: =EM4+EN4+EO4+EP4+EQ4 -> 10940.25 | FB4: =DX4-(SUM(ET4:FA4)) -> -0.25 | FD4: 43831 | FE4: =DataQ!U195+DataQ!V195+DataQ!W195+DataQ!X195+DataQ!Y195 -> 10975 | FF4: =DataQ!J195+DataQ!Q195+DataQ!H195+DataQ!P195+DataQ!S195+DataQ!K195+DataQ!L195 -> 8638 | FG4: =DataQ!N195+DataQ!I195+DataQ!R195+DataQ!G195+DataQ!T195+DataQ!M195+DataQ!O195 -> 15997 | FH4: =DataQ!F195-'Chart Data'!FE4-'Chart Data'!FF4-'Chart Data'!FG4 -> -1 | FJ4: 43831 | FK4: =FE4-(AVERAGE(FE$20:FE$23)) -> -955.75 | FL4: =FF4-(AVERAGE(FF$20:FF$23)) -> -307.25 | FM4: =FG4-(AVERAGE(FG$20:FG$23)) -> 78.75 | FN4: =SUM(FK4:FM4) -> -1184.25 | FP4: 42005 | FQ4: =100*((AVERAGE(HAVERM!AS426:AS428)/AVERAGE(HAVERM!AS423:AS425))-1) -> 0.64681 | FR4: =100*((AVERAGE(HAVERM!AT426:AT428)/AVERAGE(HAVERM!AT423:AT425))-1) -> 0.56278373 | FS4: =100*((AVERAGE(HAVERM!AU426:AU428)/AVERAGE(HAVERM!AU423:AU425))-1) -> -0.047955747 | FT4: =100*((AVERAGE(HAVERM!AV426:AV428)/AVERAGE(HAVERM!AV423:AV425))-1) -> -0.0031208153 | FU4: =100*((AVERAGE(HAVERM!AW426:AW428)/AVERAGE(HAVERM!AW423:AW425))-1) -> 0.46099291 | FV4: =100*((AVERAGE(HAVERM!AX426:AX428)/AVERAGE(HAVERM!AX423:AX425))-1) -> 0.63793926 | FW4: =100*((AVERAGE(HAVERM!AY426:AY428)/AVERAGE(HAVERM!AY423:AY425))-1) -> 0.89082514 | FX4: =100*((AVERAGE(HAVERM!AZ426:AZ428)/AVERAGE(HAVERM!AZ423:AZ425))-1) -> 0.93050514 | ... GI4: =100*((AVERAGE(HAVERM!BK426:BK428)/AVERAGE(HAVERM!BK423:BK425))-1) -> 1.1622119 | GJ4: =100*(((AVERAGE(HAVERM!BL426:BL428)+(AVERAGE(HAVERM!BM426:BM428)))/(AVERAGE(HAVERM!BL423:BL425)+AVERAGE(HAVERM!BM423:BM425))-1)) -> 0.99844185 | GL4: 42005 | GW4: 42005 | GX4: =HAVERM!AT428 -> 178218 | GY4: =HAVERM!AU428+HAVERM!AW428+HAVERM!AX428 -> 308670 | GZ4: =HAVERM!AV428 -> 2365273 | HA4: =HAVERM!AY428 -> 1114777 | HB4: =HAVERM!AZ428+HAVERM!BB428 -> 6149563 | HC4: =HAVERM!BA428+HAVERM!BC428 -> 2256758 | HD4: =HAVERM!BD428 -> 1068174 | HE4: =HAVERM!BE428+HAVERM!BF428+HAVERM!BG428 -> 4641583 | HF4: =HAVERM!BH428+HAVERM!BI428+HAVERM!BJ428+HAVERM!BK428+HAVERM!BL428+HAVERM!BM428 -> 9075119 | HH4: Agriculture | HI4: ='ASHE Annual pay All SIC'!D26 -> 27288 | HJ4: {=TRANSPOSE(FR128:GJ128)} -> -0.89380511 | HP4: 2007 | HQ4: {=TRANSPOSE('OBR MAR25 EDT 4.3'!E10:AA10)} -> 16.34162 | HR4: {=TRANSPOSE('OBR MAR25 EDT 4.3'!E16:AA16)} -> 3.0882622 | HS4: =HQ4+HR4 -> 19.429882 | HU4: 2007 | HV4: {=TRANSPOSE('OBR MAR25 EDT 4.3'!E11:AA11)} -> 6431.6118 | HW4: {=TRANSPOSE('OBR MAR25 EDT 4.3'!E17:AA17)} -> 1215.455 | HX4: =HV4+HW4 -> 7647.0668 | HZ4: 43466 | IA4: =HAVERQ!E164 -> 5285 | IB4: =HAVERQ!F164 -> 27558 | IC4: =DataQ!Z191-('Chart Data'!IA4+'Chart Data'!IB4) -> -67 | IE4: 43466 | IF4: =IA4-AVERAGE(IA$4:IA$7) -> -30.75 | IG4: =IB4-AVERAGE(IB$4:IB$7) -> -66 | II4: 43466 | IJ4: =100*(IA4/AVERAGE(IA$4:IA$7)) -> 99.42153 | IK4: =100*(IB4/AVERAGE(IB$4:IB$7)) -> 99.761077 | IM4: 43466 | IN4: =SUM(DataQ!U191:Y191) -> 10881 | IO4: =DataQ!F191-'Chart Data'!IN4 -> 24557 | IQ4: 43466 | IR4: =100*(IN4/AVERAGE(IN$4:IN$7)) -> 99.458422 | IS4: =100*(IO4/AVERAGE(IO$4:IO$7)) -> 99.72487
A5: 43556 | B5: =HAVERQ!E165-AVERAGE(HAVERQ!E$164:E$167) -> -10.75 | C5: =HAVERQ!F165-AVERAGE(HAVERQ!F$164:F$167) -> -23 | E5: 36617 | F5: =HAVERQ!P89 -> 1204 | G5: =HAVERQ!O89 -> 1441 | H5: =HAVERQ!N89 -> 1178 | I5: =HAVERQ!M89 -> 225 | J5: =HAVERQ!L89 -> 217 | K5: =HAVERQ!E89-F5-G5-H5-I5-J5 -> 784 | M5: 36617 | N5: =100*(F5/SUM($F5:$K5)) -> 23.846306 | O5: =100*(G5/SUM($F5:$K5)) -> 28.540305 | P5: =100*(H5/SUM($F5:$K5)) -> 23.331353 | Q5: =100*(I5/SUM($F5:$K5)) -> 4.456328 | R5: =100*(J5/SUM($F5:$K5)) -> 4.2978808 | S5: =100*(K5/SUM($F5:$K5)) -> 15.527827 | U5: 36617 | V5: =F5-AVERAGE(F$4:F$7) -> -5.25 | W5: =G5-AVERAGE(G$4:G$7) -> 1.25 | X5: =H5-AVERAGE(H$4:H$7) -> -1 | Y5: =I5-AVERAGE(I$4:I$7) -> -0.75 | Z5: =J5-AVERAGE(J$4:J$7) -> 0.75 | AA5: =K5-AVERAGE(K$4:K$7) -> -3.75 | AB5: =SUM(V5:AA5) -> -8.75 | AD5: 43556 | AE5: =HAVERQ!T165-AVERAGE(HAVERQ!T$164:T$167) -> -0.25 | AF5: =HAVERQ!U165-AVERAGE(HAVERQ!U$164:U$167) -> -1.25 | AG5: =HAVERQ!V165-AVERAGE(HAVERQ!V$164:V$167) -> -1.75 | AH5: =HAVERQ!W165-AVERAGE(HAVERQ!W$164:W$167) -> -0.75 | AI5: =HAVERQ!X165-AVERAGE(HAVERQ!X$164:X$167) -> 0.5 | AJ5: =HAVERQ!Y165-AVERAGE(HAVERQ!Y$164:Y$167) -> 5.75 | AK5: =HAVERQ!Z165-AVERAGE(HAVERQ!Z$164:Z$167) -> 11.5 | AL5: =HAVERQ!AA165-AVERAGE(HAVERQ!AA$164:AA$167) -> 13 | ... AV5: =HAVERQ!AK165-AVERAGE(HAVERQ!AK$164:AK$167) -> -9.75 | AW5: =AY5-AVERAGE(AY$4:AY$7) -> -8.5 | AY5: =HAVERQ!AL165+HAVERQ!AM165 -> 1009 | BA5: 43556 | BB5: =BK5-AVERAGE(BK$4:BK$7) -> -0.25 | BC5: =BL5-AVERAGE(BL$4:BL$7) -> -1.5 | BD5: =BM5-AVERAGE(BM$4:BM$7) -> -1.75 | BE5: =BN5-AVERAGE(BN$4:BN$7) -> 5.75 | BF5: =BO5-AVERAGE(BO$4:BO$7) -> 24.5 | BG5: =BP5-AVERAGE(BP$4:BP$7) -> 1.75 | BH5: =BQ5-AVERAGE(BQ$4:BQ$7) -> -8.5 | BI5: =BR5-AVERAGE(BR$4:BR$7) -> -40.25 | BK5: =HAVERQ!T165 -> 398 | BL5: =HAVERQ!U165+HAVERQ!W165+HAVERQ!X165 -> 424 | BM5: =HAVERQ!V165 -> 2689 | BN5: =HAVERQ!Y165 -> 2339 | BO5: =HAVERQ!Z165+HAVERQ!AB165 -> 7529 | BP5: =HAVERQ!AA165+HAVERQ!AC165 -> 3308 | BQ5: =HAVERQ!AD165+HAVERQ!AE165+HAVERQ!AF165+HAVERQ!AG165 -> 7958 | BR5: =HAVERQ!AH165+HAVERQ!AI165+HAVERQ!AJ165+HAVERQ!AK165+HAVERQ!AL165+HAVERQ!AM165 -> 10900 | BS5: =HAVERQ!S165-SUM('Chart Data'!BK5:BR5) -> 1 | BU5: 34425 | BV5: =HAVERQ!T65 -> 487 | BW5: =HAVERQ!U65+HAVERQ!W65+HAVERQ!X65 -> 359 | BX5: =HAVERQ!V65 -> 4121 | BY5: =HAVERQ!Y65 -> 1874 | BZ5: =HAVERQ!Z65+HAVERQ!AB65 -> 6185 | CA5: =HAVERQ!AA65+HAVERQ!AC65 -> 2084 | CB5: =HAVERQ!AD65+HAVERQ!AE65+HAVERQ!AF65+HAVERQ!AG65 -> 4507 | CC5: =HAVERQ!AH65+HAVERQ!AI65+HAVERQ!AJ65+HAVERQ!AK65+HAVERQ!AL65+HAVERQ!AM65 -> 8062 | CD5: =HAVERQ!S65-SUM('Chart Data'!BV5:CC5) -> -1 | CF5: 2024 average | CG5: =AVERAGE(HAVERM!X536:X547) -> 2.6583333 | CI5: =AVERAGE(HAVERM!Y536:Y547) -> 3.6583333 | CJ5: =AVERAGE(HAVERM!Z536:Z547) -> 2.5333333 | CK5: =AVERAGE(HAVERM!AA536:AA547) -> 3.425 | CL5: =AVERAGE(HAVERM!AB536:AB547) -> 2.6916667 | CM5: =AVERAGE(HAVERM!AC536:AC547) -> 2.4333333 | CN5: =AVERAGE(HAVERM!AD536:AD547) -> 2.3833333 | CO5: =AVERAGE(HAVERM!AE536:AE547) -> 2.1833333 | CP5: =AVERAGE(HAVERM!AF536:AF547) -> 3.7666667 | ... CZ5: =AVERAGE(HAVERM!AP536:AP547) -> 2.625 | DB5: 36251 | DC5: =HAVERQ!BI85/HAVERQ!T85 -> 7.1132075 | DD5: =HAVERQ!BJ85/HAVERQ!U85 -> 603.77632 | DE5: =HAVERQ!BK85/HAVERQ!V85 -> 9.1518895 | DF5: =HAVERQ!BL85/HAVERQ!W85 -> 88.156863 | DG5: =HAVERQ!BM85/HAVERQ!X85 -> 41.793939 | DH5: =HAVERQ!BN85/HAVERQ!Y85 -> 17.60241 | DI5: =HAVERQ!BO85/HAVERQ!Z85 -> 9.3493432 | DJ5: =HAVERQ!BP85/HAVERQ!AA85 -> 13.476969 | ... DT5: =HAVERQ!BZ85/HAVERQ!AK85 -> 9.2092697 | DU5: =(HAVERQ!CA85+HAVERQ!CB85)/HAVERQ!AL85 -> 11.891247 | DW5: 2024 | DX5: =DataA!B58 -> 36792.75 | DY5: =DataA!C58 -> 360.25 | DZ5: =DataA!D58 -> 48.25 | EA5: =DataA!E58 -> 2588 | EB5: =DataA!F58 -> 135.75 | EC5: =DataA!G58 -> 246 | ED5: =DataA!H58 -> 2209 | EE5: =DataA!I58 -> 4722.5 | ... EQ5: =DataA!U58 -> 997.5 | ES5: 2024 | ET5: =DY5 -> 360.25 | EU5: =DZ5+EB5+EC5 -> 430 | EV5: =EA5 -> 2588 | EW5: =ED5 -> 2209 | EX5: =EE5+EG5 -> 7388.75 | EY5: =EF5+EH5 -> 3516.25 | EZ5: =EI5+EJ5+EK5+EL5 -> 8371.25 | FA5: =EM5+EN5+EO5+EP5+EQ5 -> 11930.75 | FB5: =DX5-(SUM(ET5:FA5)) -> -1.5 | FD5: 43922 | FE5: =DataQ!U196+DataQ!V196+DataQ!W196+DataQ!X196+DataQ!Y196 -> 10977 | FF5: =DataQ!J196+DataQ!Q196+DataQ!H196+DataQ!P196+DataQ!S196+DataQ!K196+DataQ!L196 -> 8483 | FG5: =DataQ!N196+DataQ!I196+DataQ!R196+DataQ!G196+DataQ!T196+DataQ!M196+DataQ!O196 -> 15674 | FH5: =DataQ!F196-'Chart Data'!FE5-'Chart Data'!FF5-'Chart Data'!FG5 -> 1 | FJ5: 43922 | FK5: =FE5-(AVERAGE(FE$20:FE$23)) -> -953.75 | FL5: =FF5-(AVERAGE(FF$20:FF$23)) -> -462.25 | FM5: =FG5-(AVERAGE(FG$20:FG$23)) -> -244.25 | FN5: =SUM(FK5:FM5) -> -1660.25 | FP5: 42036 | FQ5: =100*((AVERAGE(HAVERM!AS427:AS429)/AVERAGE(HAVERM!AS424:AS426))-1) -> 0.70473908 | FR5: =100*((AVERAGE(HAVERM!AT427:AT429)/AVERAGE(HAVERM!AT424:AT426))-1) -> 1.0495907 | FS5: =100*((AVERAGE(HAVERM!AU427:AU429)/AVERAGE(HAVERM!AU424:AU426))-1) -> -0.81304885 | FT5: =100*((AVERAGE(HAVERM!AV427:AV429)/AVERAGE(HAVERM!AV424:AV426))-1) -> -0.06784322 | FU5: =100*((AVERAGE(HAVERM!AW427:AW429)/AVERAGE(HAVERM!AW424:AW426))-1) -> 0.71990879 | FV5: =100*((AVERAGE(HAVERM!AX427:AX429)/AVERAGE(HAVERM!AX424:AX426))-1) -> 0.80109771 | FW5: =100*((AVERAGE(HAVERM!AY427:AY429)/AVERAGE(HAVERM!AY424:AY426))-1) -> 0.85794421 | FX5: =100*((AVERAGE(HAVERM!AZ427:AZ429)/AVERAGE(HAVERM!AZ424:AZ426))-1) -> 1.0578494 | ... GI5: =100*((AVERAGE(HAVERM!BK427:BK429)/AVERAGE(HAVERM!BK424:BK426))-1) -> 1.2562187 | GJ5: =100*(((AVERAGE(HAVERM!BL427:BL429)+(AVERAGE(HAVERM!BM427:BM429)))/(AVERAGE(HAVERM!BL424:BL426)+AVERAGE(HAVERM!BM424:BM426))-1)) -> 0.95573114 | GL5: 42036 | GW5: 42036 | GX5: =HAVERM!AT429 -> 178345 | GY5: =HAVERM!AU429+HAVERM!AW429+HAVERM!AX429 -> 308696 | GZ5: =HAVERM!AV429 -> 2371584 | HA5: =HAVERM!AY429 -> 1118179 | HB5: =HAVERM!AZ429+HAVERM!BB429 -> 6155052 | HC5: =HAVERM!BA429+HAVERM!BC429 -> 2266463 | HD5: =HAVERM!BD429 -> 1069126 | HE5: =HAVERM!BE429+HAVERM!BF429+HAVERM!BG429 -> 4662777 | HF5: =HAVERM!BH429+HAVERM!BI429+HAVERM!BJ429+HAVERM!BK429+HAVERM!BL429+HAVERM!BM429 -> 9084632 | HH5: Extraction | HI5: ='ASHE Annual pay All SIC'!D30 -> 47022 | HJ5: -0.92967819 | HL5: Extraction | HM5: ='ASHE Annual pay All SIC'!D30 -> 47022 | HN5: {=TRANSPOSE(CI11:CZ11)} -> 0.77916667 | HP5: 2008 | HQ5: 16.925615 | HR5: 3.2968634 | HS5: =HQ5+HR5 -> 20.222479 | HU5: 2008 | HV5: 6446.2125 | HW5: 1255.6283 | HX5: =HV5+HW5 -> 7701.8408 | HZ5: 43556 | IA5: =HAVERQ!E165 -> 5305 | IB5: =HAVERQ!F165 -> 27601 | IC5: =DataQ!Z192-('Chart Data'!IA5+'Chart Data'!IB5) -> 57 | IE5: 43556 | IF5: =IA5-AVERAGE(IA$4:IA$7) -> -10.75 | IG5: =IB5-AVERAGE(IB$4:IB$7) -> -23 | II5: 43556 | IJ5: =100*(IA5/AVERAGE(IA$4:IA$7)) -> 99.797771 | IK5: =100*(IB5/AVERAGE(IB$4:IB$7)) -> 99.916739 | IM5: 43556 | IN5: =SUM(DataQ!U192:Y192) -> 10900 | IO5: =DataQ!F192-'Chart Data'!IN5 -> 24646 | IQ5: 43556 | IR5: =100*(IN5/AVERAGE(IN$4:IN$7)) -> 99.632093 | IS5: =100*(IO5/AVERAGE(IO$4:IO$7)) -> 100.0863
A6: 43647 | B6: =HAVERQ!E166-AVERAGE(HAVERQ!E$164:E$167) -> 13.25 | C6: =HAVERQ!F166-AVERAGE(HAVERQ!F$164:F$167) -> -46 | E6: 36708 | F6: =HAVERQ!P90 -> 1213 | G6: =HAVERQ!O90 -> 1455 | H6: =HAVERQ!N90 -> 1177 | I6: =HAVERQ!M90 -> 226 | J6: =HAVERQ!L90 -> 216 | K6: =HAVERQ!E90-F6-G6-H6-I6-J6 -> 785 | M6: 36708 | N6: =100*(F6/SUM($F6:$K6)) -> 23.915615 | O6: =100*(G6/SUM($F6:$K6)) -> 28.686909 | P6: =100*(H6/SUM($F6:$K6)) -> 23.205836 | Q6: =100*(I6/SUM($F6:$K6)) -> 4.455836 | R6: =100*(J6/SUM($F6:$K6)) -> 4.2586751 | S6: =100*(K6/SUM($F6:$K6)) -> 15.477129 | U6: 36708 | V6: =F6-AVERAGE(F$4:F$7) -> 3.75 | W6: =G6-AVERAGE(G$4:G$7) -> 15.25 | X6: =H6-AVERAGE(H$4:H$7) -> -2 | Y6: =I6-AVERAGE(I$4:I$7) -> 0.25 | Z6: =J6-AVERAGE(J$4:J$7) -> -0.25 | AA6: =K6-AVERAGE(K$4:K$7) -> -2.75 | AB6: =SUM(V6:AA6) -> 14.25 | AD6: 43647 | AE6: =HAVERQ!T166-AVERAGE(HAVERQ!T$164:T$167) -> 4.75 | AF6: =HAVERQ!U166-AVERAGE(HAVERQ!U$164:U$167) -> -0.25 | AG6: =HAVERQ!V166-AVERAGE(HAVERQ!V$164:V$167) -> 3.25 | AH6: =HAVERQ!W166-AVERAGE(HAVERQ!W$164:W$167) -> -2.75 | AI6: =HAVERQ!X166-AVERAGE(HAVERQ!X$164:X$167) -> -2.5 | AJ6: =HAVERQ!Y166-AVERAGE(HAVERQ!Y$164:Y$167) -> -25.25 | AK6: =HAVERQ!Z166-AVERAGE(HAVERQ!Z$164:Z$167) -> -4.5 | AL6: =HAVERQ!AA166-AVERAGE(HAVERQ!AA$164:AA$167) -> 2 | ... AV6: =HAVERQ!AK166-AVERAGE(HAVERQ!AK$164:AK$167) -> 2.25 | AW6: =AY6-AVERAGE(AY$4:AY$7) -> 1.5 | AY6: =HAVERQ!AL166+HAVERQ!AM166 -> 1019 | BA6: 43647 | BB6: =BK6-AVERAGE(BK$4:BK$7) -> 4.75 | BC6: =BL6-AVERAGE(BL$4:BL$7) -> -5.5 | BD6: =BM6-AVERAGE(BM$4:BM$7) -> 3.25 | BE6: =BN6-AVERAGE(BN$4:BN$7) -> -25.25 | BF6: =BO6-AVERAGE(BO$4:BO$7) -> 2.5 | BG6: =BP6-AVERAGE(BP$4:BP$7) -> 1.75 | BH6: =BQ6-AVERAGE(BQ$4:BQ$7) -> 47.5 | BI6: =BR6-AVERAGE(BR$4:BR$7) -> 21.75 | BK6: =HAVERQ!T166 -> 403 | BL6: =HAVERQ!U166+HAVERQ!W166+HAVERQ!X166 -> 420 | BM6: =HAVERQ!V166 -> 2694 | BN6: =HAVERQ!Y166 -> 2308 | BO6: =HAVERQ!Z166+HAVERQ!AB166 -> 7507 | BP6: =HAVERQ!AA166+HAVERQ!AC166 -> 3308 | BQ6: =HAVERQ!AD166+HAVERQ!AE166+HAVERQ!AF166+HAVERQ!AG166 -> 8014 | BR6: =HAVERQ!AH166+HAVERQ!AI166+HAVERQ!AJ166+HAVERQ!AK166+HAVERQ!AL166+HAVERQ!AM166 -> 10962 | BS6: =HAVERQ!S166-SUM('Chart Data'!BK6:BR6) -> -1 | BU6: 34516 | BV6: =HAVERQ!T66 -> 484 | BW6: =HAVERQ!U66+HAVERQ!W66+HAVERQ!X66 -> 352 | BX6: =HAVERQ!V66 -> 4151 | BY6: =HAVERQ!Y66 -> 1888 | BZ6: =HAVERQ!Z66+HAVERQ!AB66 -> 6243 | CA6: =HAVERQ!AA66+HAVERQ!AC66 -> 2094 | CB6: =HAVERQ!AD66+HAVERQ!AE66+HAVERQ!AF66+HAVERQ!AG66 -> 4617 | CC6: =HAVERQ!AH66+HAVERQ!AI66+HAVERQ!AJ66+HAVERQ!AK66+HAVERQ!AL66+HAVERQ!AM66 -> 8044 | CD6: =HAVERQ!S66-SUM('Chart Data'!BV6:CC6) -> 1 | CF6: 2010-2019 average | CG6: =AVERAGE(HAVERM!X368:X487) -> 2.2725 | CI6: =AVERAGE(HAVERM!Y368:Y487) -> 2.435 | CJ6: =AVERAGE(HAVERM!Z368:Z487) -> 1.8916667 | CK6: =AVERAGE(HAVERM!AA368:AA487) -> 2.8666667 | CL6: =AVERAGE(HAVERM!AB368:AB487) -> 1.3358333 | CM6: =AVERAGE(HAVERM!AC368:AC487) -> 1.4525 | CN6: =AVERAGE(HAVERM!AD368:AD487) -> 2.5666667 | CO6: =AVERAGE(HAVERM!AE368:AE487) -> 2.0358333 | CP6: =AVERAGE(HAVERM!AF368:AF487) -> 3.37 | ... CZ6: =AVERAGE(HAVERM!AP368:AP487) -> 2.8533333 | DB6: 36342 | DC6: =HAVERQ!BI86/HAVERQ!T86 -> 7.3333333 | DD6: =HAVERQ!BJ86/HAVERQ!U86 -> 612.98684 | DE6: =HAVERQ!BK86/HAVERQ!V86 -> 9.3891734 | DF6: =HAVERQ!BL86/HAVERQ!W86 -> 91.919192 | DG6: =HAVERQ!BM86/HAVERQ!X86 -> 42.453988 | DH6: =HAVERQ!BN86/HAVERQ!Y86 -> 17.804167 | DI6: =HAVERQ!BO86/HAVERQ!Z86 -> 9.4105866 | DJ6: =HAVERQ!BP86/HAVERQ!AA86 -> 13.401026 | ... DT6: =HAVERQ!BZ86/HAVERQ!AK86 -> 8.8510929 | DU6: =(HAVERQ!CA86+HAVERQ!CB86)/HAVERQ!AL86 -> 11.178893 | DW6: 2029 | DX6: =DataA!B63 -> 38728.525 | DY6: =DataA!C63 -> 362.614 | DZ6: =DataA!D63 -> 43.125685 | EA6: =DataA!E63 -> 2436.3983 | EB6: =DataA!F63 -> 134.91768 | EC6: =DataA!G63 -> 252.23687 | ED6: =DataA!H63 -> 2413.8517 | EE6: =DataA!I63 -> 4946.7212 | ... EQ6: =DataA!U63 -> 1072.053 | ES6: 2029 | ET6: =DY6 -> 362.614 | EU6: =DZ6+EB6+EC6 -> 430.28024 | EV6: =EA6 -> 2436.3983 | EW6: =ED6 -> 2413.8517 | EX6: =EE6+EG6 -> 7715.6932 | EY6: =EF6+EH6 -> 3800.511 | EZ6: =EI6+EJ6+EK6+EL6 -> 8929.9667 | FA6: =EM6+EN6+EO6+EP6+EQ6 -> 12638.21 | FB6: =DX6-(SUM(ET6:FA6)) -> 0.999365 | FD6: 44013 | FE6: =DataQ!U197+DataQ!V197+DataQ!W197+DataQ!X197+DataQ!Y197 -> 10843 | FF6: =DataQ!J197+DataQ!Q197+DataQ!H197+DataQ!P197+DataQ!S197+DataQ!K197+DataQ!L197 -> 8311 | FG6: =DataQ!N197+DataQ!I197+DataQ!R197+DataQ!G197+DataQ!T197+DataQ!M197+DataQ!O197 -> 15440 | FH6: =DataQ!F197-'Chart Data'!FE6-'Chart Data'!FF6-'Chart Data'!FG6 -> 0 | FJ6: 44013 | FK6: =FE6-(AVERAGE(FE$20:FE$23)) -> -1087.75 | FL6: =FF6-(AVERAGE(FF$20:FF$23)) -> -634.25 | FM6: =FG6-(AVERAGE(FG$20:FG$23)) -> -478.25 | FN6: =SUM(FK6:FM6) -> -2200.25 | FP6: 42064 | FQ6: =100*((AVERAGE(HAVERM!AS428:AS430)/AVERAGE(HAVERM!AS425:AS427))-1) -> 0.93672645 | FR6: =100*((AVERAGE(HAVERM!AT428:AT430)/AVERAGE(HAVERM!AT425:AT427))-1) -> 1.0161343 | FS6: =100*((AVERAGE(HAVERM!AU428:AU430)/AVERAGE(HAVERM!AU425:AU427))-1) -> -0.9793484 | FT6: =100*((AVERAGE(HAVERM!AV428:AV430)/AVERAGE(HAVERM!AV425:AV427))-1) -> 1.0623043 | FU6: =100*((AVERAGE(HAVERM!AW428:AW430)/AVERAGE(HAVERM!AW425:AW427))-1) -> 0.78776846 | FV6: =100*((AVERAGE(HAVERM!AX428:AX430)/AVERAGE(HAVERM!AX425:AX427))-1) -> 1.1945727 | FW6: =100*((AVERAGE(HAVERM!AY428:AY430)/AVERAGE(HAVERM!AY425:AY427))-1) -> 2.3760033 | FX6: =100*((AVERAGE(HAVERM!AZ428:AZ430)/AVERAGE(HAVERM!AZ425:AZ427))-1) -> 1.0585566 | ... GI6: =100*((AVERAGE(HAVERM!BK428:BK430)/AVERAGE(HAVERM!BK425:BK427))-1) -> 1.1866166 | GJ6: =100*(((AVERAGE(HAVERM!BL428:BL430)+(AVERAGE(HAVERM!BM428:BM430)))/(AVERAGE(HAVERM!BL425:BL427)+AVERAGE(HAVERM!BM425:BM427))-1)) -> 0.99081627 | GL6: 42064 | GW6: 42064 | GX6: =HAVERM!AT430 -> 178374 | GY6: =HAVERM!AU430+HAVERM!AW430+HAVERM!AX430 -> 309557 | GZ6: =HAVERM!AV430 -> 2374578 | HA6: =HAVERM!AY430 -> 1124033 | HB6: =HAVERM!AZ430+HAVERM!BB430 -> 6178886 | HC6: =HAVERM!BA430+HAVERM!BC430 -> 2274102 | HD6: =HAVERM!BD430 -> 1070374 | HE6: =HAVERM!BE430+HAVERM!BF430+HAVERM!BG430 -> 4690460 | HF6: =HAVERM!BH430+HAVERM!BI430+HAVERM!BJ430+HAVERM!BK430+HAVERM!BL430+HAVERM!BM430 -> 9094299 | HH6: Manufacturing | HI6: ='ASHE Annual pay All SIC'!D36 -> 35518 | HJ6: -0.42959079 | HL6: Manufacturing | HM6: ='ASHE Annual pay All SIC'!D36 -> 35518 | HN6: -0.30583333 | HP6: 2009 | HQ6: 18.265633 | HR6: 3.8046863 | HS6: =HQ6+HR6 -> 22.07032 | HU6: 2009 | HV6: 6720.9846 | HW6: 1399.9645 | HX6: =HV6+HW6 -> 8120.9491 | HZ6: 43647 | IA6: =HAVERQ!E166 -> 5329 | IB6: =HAVERQ!F166 -> 27578 | IC6: =DataQ!Z193-('Chart Data'!IA6+'Chart Data'!IB6) -> -11 | IE6: 43647 | IF6: =IA6-AVERAGE(IA$4:IA$7) -> 13.25 | IG6: =IB6-AVERAGE(IB$4:IB$7) -> -46 | II6: 43647 | IJ6: =100*(IA6/AVERAGE(IA$4:IA$7)) -> 100.24926 | IK6: =100*(IB6/AVERAGE(IB$4:IB$7)) -> 99.833478 | IM6: 43647 | IN6: =SUM(DataQ!U193:Y193) -> 10962 | IO6: =DataQ!F193-'Chart Data'!IN6 -> 24653 | IQ6: 43647 | IR6: =100*(IN6/AVERAGE(IN$4:IN$7)) -> 100.19881 | IS6: =100*(IO6/AVERAGE(IO$4:IO$7)) -> 100.11472
A7: 43739 | B7: =HAVERQ!E167-AVERAGE(HAVERQ!E$164:E$167) -> 28.25 | C7: =HAVERQ!F167-AVERAGE(HAVERQ!F$164:F$167) -> 135 | E7: 36800 | F7: =HAVERQ!P91 -> 1223 | G7: =HAVERQ!O91 -> 1457 | H7: =HAVERQ!N91 -> 1177 | I7: =HAVERQ!M91 -> 227 | J7: =HAVERQ!L91 -> 215 | K7: =HAVERQ!E91-F7-G7-H7-I7-J7 -> 782 | M7: 36800 | N7: =100*(F7/SUM($F7:$K7)) -> 24.070065 | O7: =100*(G7/SUM($F7:$K7)) -> 28.675458 | P7: =100*(H7/SUM($F7:$K7)) -> 23.164731 | Q7: =100*(I7/SUM($F7:$K7)) -> 4.4676245 | R7: =100*(J7/SUM($F7:$K7)) -> 4.2314505 | S7: =100*(K7/SUM($F7:$K7)) -> 15.390671 | U7: 36800 | V7: =F7-AVERAGE(F$4:F$7) -> 13.75 | W7: =G7-AVERAGE(G$4:G$7) -> 17.25 | X7: =H7-AVERAGE(H$4:H$7) -> -2 | Y7: =I7-AVERAGE(I$4:I$7) -> 1.25 | Z7: =J7-AVERAGE(J$4:J$7) -> -1.25 | AA7: =K7-AVERAGE(K$4:K$7) -> -5.75 | AB7: =SUM(V7:AA7) -> 23.25 | AD7: 43739 | AE7: =HAVERQ!T167-AVERAGE(HAVERQ!T$164:T$167) -> 6.75 | AF7: =HAVERQ!U167-AVERAGE(HAVERQ!U$164:U$167) -> 0.75 | AG7: =HAVERQ!V167-AVERAGE(HAVERQ!V$164:V$167) -> -15.75 | AH7: =HAVERQ!W167-AVERAGE(HAVERQ!W$164:W$167) -> 4.25 | AI7: =HAVERQ!X167-AVERAGE(HAVERQ!X$164:X$167) -> -3.5 | AJ7: =HAVERQ!Y167-AVERAGE(HAVERQ!Y$164:Y$167) -> -8.25 | AK7: =HAVERQ!Z167-AVERAGE(HAVERQ!Z$164:Z$167) -> -34.5 | AL7: =HAVERQ!AA167-AVERAGE(HAVERQ!AA$164:AA$167) -> 5 | ... AV7: =HAVERQ!AK167-AVERAGE(HAVERQ!AK$164:AK$167) -> 13.25 | AW7: =AY7-AVERAGE(AY$4:AY$7) -> 16.5 | AY7: =HAVERQ!AL167+HAVERQ!AM167 -> 1034 | BA7: 43739 | BB7: =BK7-AVERAGE(BK$4:BK$7) -> 6.75 | BC7: =BL7-AVERAGE(BL$4:BL$7) -> 1.5 | BD7: =BM7-AVERAGE(BM$4:BM$7) -> -15.75 | BE7: =BN7-AVERAGE(BN$4:BN$7) -> -8.25 | BF7: =BO7-AVERAGE(BO$4:BO$7) -> -21.5 | BG7: =BP7-AVERAGE(BP$4:BP$7) -> 32.75 | BH7: =BQ7-AVERAGE(BQ$4:BQ$7) -> 21.5 | BI7: =BR7-AVERAGE(BR$4:BR$7) -> 77.75 | BK7: =HAVERQ!T167 -> 405 | BL7: =HAVERQ!U167+HAVERQ!W167+HAVERQ!X167 -> 427 | BM7: =HAVERQ!V167 -> 2675 | BN7: =HAVERQ!Y167 -> 2325 | BO7: =HAVERQ!Z167+HAVERQ!AB167 -> 7483 | BP7: =HAVERQ!AA167+HAVERQ!AC167 -> 3339 | BQ7: =HAVERQ!AD167+HAVERQ!AE167+HAVERQ!AF167+HAVERQ!AG167 -> 7988 | BR7: =HAVERQ!AH167+HAVERQ!AI167+HAVERQ!AJ167+HAVERQ!AK167+HAVERQ!AL167+HAVERQ!AM167 -> 11018 | BS7: =HAVERQ!S167-SUM('Chart Data'!BK7:BR7) -> 1 | BU7: 34608 | BV7: =HAVERQ!T67 -> 470 | BW7: =HAVERQ!U67+HAVERQ!W67+HAVERQ!X67 -> 346 | BX7: =HAVERQ!V67 -> 4176 | BY7: =HAVERQ!Y67 -> 1879 | BZ7: =HAVERQ!Z67+HAVERQ!AB67 -> 6269 | CA7: =HAVERQ!AA67+HAVERQ!AC67 -> 2095 | CB7: =HAVERQ!AD67+HAVERQ!AE67+HAVERQ!AF67+HAVERQ!AG67 -> 4650 | CC7: =HAVERQ!AH67+HAVERQ!AI67+HAVERQ!AJ67+HAVERQ!AK67+HAVERQ!AL67+HAVERQ!AM67 -> 8056 | CD7: =HAVERQ!S67-SUM('Chart Data'!BV7:CC7) -> 0 | DB7: 36434 | DC7: =HAVERQ!BI87/HAVERQ!T87 -> 7.8059701 | DD7: =HAVERQ!BJ87/HAVERQ!U87 -> 604.47368 | DE7: =HAVERQ!BK87/HAVERQ!V87 -> 9.4796668 | DF7: =HAVERQ!BL87/HAVERQ!W87 -> 91.947917 | DG7: =HAVERQ!BM87/HAVERQ!X87 -> 46.025974 | DH7: =HAVERQ!BN87/HAVERQ!Y87 -> 17.802301 | DI7: =HAVERQ!BO87/HAVERQ!Z87 -> 9.8149663 | DJ7: =HAVERQ!BP87/HAVERQ!AA87 -> 12.945284 | ... DT7: =HAVERQ!BZ87/HAVERQ!AK87 -> 8.9661705 | DU7: =(HAVERQ!CA87+HAVERQ!CB87)/HAVERQ!AL87 -> 10.438202 | FD7: 44105 | FE7: =DataQ!U198+DataQ!V198+DataQ!W198+DataQ!X198+DataQ!Y198 -> 10874 | FF7: =DataQ!J198+DataQ!Q198+DataQ!H198+DataQ!P198+DataQ!S198+DataQ!K198+DataQ!L198 -> 8369 | FG7: =DataQ!N198+DataQ!I198+DataQ!R198+DataQ!G198+DataQ!T198+DataQ!M198+DataQ!O198 -> 15281 | FH7: =DataQ!F198-'Chart Data'!FE7-'Chart Data'!FF7-'Chart Data'!FG7 -> -2 | FJ7: 44105 | FK7: =FE7-(AVERAGE(FE$20:FE$23)) -> -1056.75 | FL7: =FF7-(AVERAGE(FF$20:FF$23)) -> -576.25 | FM7: =FG7-(AVERAGE(FG$20:FG$23)) -> -637.25 | FN7: =SUM(FK7:FM7) -> -2270.25 | FP7: 42095 | FQ7: =100*((AVERAGE(HAVERM!AS429:AS431)/AVERAGE(HAVERM!AS426:AS428))-1) -> 0.85010909 | FR7: =100*((AVERAGE(HAVERM!AT429:AT431)/AVERAGE(HAVERM!AT426:AT428))-1) -> 0.67591939 | FS7: =100*((AVERAGE(HAVERM!AU429:AU431)/AVERAGE(HAVERM!AU426:AU428))-1) -> -2.0363076 | FT7: =100*((AVERAGE(HAVERM!AV429:AV431)/AVERAGE(HAVERM!AV426:AV428))-1) -> 1.0286386 | FU7: =100*((AVERAGE(HAVERM!AW429:AW431)/AVERAGE(HAVERM!AW426:AW428))-1) -> 0.22187484 | FV7: =100*((AVERAGE(HAVERM!AX429:AX431)/AVERAGE(HAVERM!AX426:AX428))-1) -> 1.1093169 | FW7: =100*((AVERAGE(HAVERM!AY429:AY431)/AVERAGE(HAVERM!AY426:AY428))-1) -> 2.2008213 | FX7: =100*((AVERAGE(HAVERM!AZ429:AZ431)/AVERAGE(HAVERM!AZ426:AZ428))-1) -> 0.69672764 | ... GI7: =100*((AVERAGE(HAVERM!BK429:BK431)/AVERAGE(HAVERM!BK426:BK428))-1) -> 1.122939 | GJ7: =100*(((AVERAGE(HAVERM!BL429:BL431)+(AVERAGE(HAVERM!BM429:BM431)))/(AVERAGE(HAVERM!BL426:BL428)+AVERAGE(HAVERM!BM426:BM428))-1)) -> 0.87699487 | GL7: 42095 | GW7: 42095 | GX7: =HAVERM!AT431 -> 179191 | GY7: =HAVERM!AU431+HAVERM!AW431+HAVERM!AX431 -> 307089 | GZ7: =HAVERM!AV431 -> 2375569 | HA7: =HAVERM!AY431 -> 1129528 | HB7: =HAVERM!AZ431+HAVERM!BB431 -> 6187420 | HC7: =HAVERM!BA431+HAVERM!BC431 -> 2272257 | HD7: =HAVERM!BD431 -> 1079581 | HE7: =HAVERM!BE431+HAVERM!BF431+HAVERM!BG431 -> 4704084 | HF7: =HAVERM!BH431+HAVERM!BI431+HAVERM!BJ431+HAVERM!BK431+HAVERM!BL431+HAVERM!BM431 -> 9106124 | HH7: Utilities | HI7: ='ASHE Annual pay All SIC'!D61 -> 51886 | HJ7: 0.94272776 | HL7: Utilities | HM7: ='ASHE Annual pay All SIC'!D61 -> 51886 | HN7: -0.30333333 | HP7: 2010 | HQ7: 17.883927 | HR7: 3.1295946 | HS7: =HQ7+HR7 -> 21.013521 | HU7: 2010 | HV7: 6680.62 | HW7: 1169.0739 | HX7: =HV7+HW7 -> 7849.6939 | HZ7: 43739 | IA7: =HAVERQ!E167 -> 5344 | IB7: =HAVERQ!F167 -> 27759 | IC7: =DataQ!Z194-('Chart Data'!IA7+'Chart Data'!IB7) -> -46 | IE7: 43739 | IF7: =IA7-AVERAGE(IA$4:IA$7) -> 28.25 | IG7: =IB7-AVERAGE(IB$4:IB$7) -> 135 | II7: 43739 | IJ7: =100*(IA7/AVERAGE(IA$4:IA$7)) -> 100.53144 | IK7: =100*(IB7/AVERAGE(IB$4:IB$7)) -> 100.48871 | IM7: 43739 | IN7: =SUM(DataQ!U194:Y194) -> 11018 | IO7: =DataQ!F194-'Chart Data'!IN7 -> 24643 | IQ7: 43739 | IR7: =100*(IN7/AVERAGE(IN$4:IN$7)) -> 100.71068 | IS7: =100*(IO7/AVERAGE(IO$4:IO$7)) -> 100.07411
A8: 43831 | B8: =HAVERQ!E168-AVERAGE(HAVERQ!E$164:E$167) -> 53.25 | C8: =HAVERQ!F168-AVERAGE(HAVERQ!F$164:F$167) -> -174 | E8: 36892 | F8: =HAVERQ!P92 -> 1235 | G8: =HAVERQ!O92 -> 1463 | H8: =HAVERQ!N92 -> 1181 | I8: =HAVERQ!M92 -> 228 | J8: =HAVERQ!L92 -> 215 | K8: =HAVERQ!E92-F8-G8-H8-I8-J8 -> 785 | M8: 36892 | N8: =100*(F8/SUM($F8:$K8)) -> 24.182495 | O8: =100*(G8/SUM($F8:$K8)) -> 28.646955 | P8: =100*(H8/SUM($F8:$K8)) -> 23.125122 | Q8: =100*(I8/SUM($F8:$K8)) -> 4.4644605 | R8: =100*(J8/SUM($F8:$K8)) -> 4.209908 | S8: =100*(K8/SUM($F8:$K8)) -> 15.371059 | U8: 36892 | V8: =F8-AVERAGE(F$4:F$7) -> 25.75 | W8: =G8-AVERAGE(G$4:G$7) -> 23.25 | X8: =H8-AVERAGE(H$4:H$7) -> 2 | Y8: =I8-AVERAGE(I$4:I$7) -> 2.25 | Z8: =J8-AVERAGE(J$4:J$7) -> -1.25 | AA8: =K8-AVERAGE(K$4:K$7) -> -2.75 | AB8: =SUM(V8:AA8) -> 49.25 | AD8: 43831 | AE8: =HAVERQ!T168-AVERAGE(HAVERQ!T$164:T$167) -> -14.25 | AF8: =HAVERQ!U168-AVERAGE(HAVERQ!U$164:U$167) -> 6.75 | AG8: =HAVERQ!V168-AVERAGE(HAVERQ!V$164:V$167) -> -14.75 | AH8: =HAVERQ!W168-AVERAGE(HAVERQ!W$164:W$167) -> 5.25 | AI8: =HAVERQ!X168-AVERAGE(HAVERQ!X$164:X$167) -> -3.5 | AJ8: =HAVERQ!Y168-AVERAGE(HAVERQ!Y$164:Y$167) -> -40.25 | AK8: =HAVERQ!Z168-AVERAGE(HAVERQ!Z$164:Z$167) -> -67.5 | AL8: =HAVERQ!AA168-AVERAGE(HAVERQ!AA$164:AA$167) -> 1 | ... AV8: =HAVERQ!AK168-AVERAGE(HAVERQ!AK$164:AK$167) -> -4.75 | AW8: =AY8-AVERAGE(AY$4:AY$7) -> -28.5 | AY8: =HAVERQ!AL168+HAVERQ!AM168 -> 989 | BA8: 43831 | BB8: =BK8-AVERAGE(BK$4:BK$7) -> -14.25 | BC8: =BL8-AVERAGE(BL$4:BL$7) -> 8.5 | BD8: =BM8-AVERAGE(BM$4:BM$7) -> -14.75 | BE8: =BN8-AVERAGE(BN$4:BN$7) -> -40.25 | BF8: =BO8-AVERAGE(BO$4:BO$7) -> -47.5 | BG8: =BP8-AVERAGE(BP$4:BP$7) -> 49.75 | BH8: =BQ8-AVERAGE(BQ$4:BQ$7) -> 68.5 | BI8: =BR8-AVERAGE(BR$4:BR$7) -> 34.75 | BK8: =HAVERQ!T168 -> 384 | BL8: =HAVERQ!U168+HAVERQ!W168+HAVERQ!X168 -> 434 | BM8: =HAVERQ!V168 -> 2676 | BN8: =HAVERQ!Y168 -> 2293 | BO8: =HAVERQ!Z168+HAVERQ!AB168 -> 7457 | BP8: =HAVERQ!AA168+HAVERQ!AC168 -> 3356 | BQ8: =HAVERQ!AD168+HAVERQ!AE168+HAVERQ!AF168+HAVERQ!AG168 -> 8035 | BR8: =HAVERQ!AH168+HAVERQ!AI168+HAVERQ!AJ168+HAVERQ!AK168+HAVERQ!AL168+HAVERQ!AM168 -> 10975 | BS8: =HAVERQ!S168-SUM('Chart Data'!BK8:BR8) -> -1 | BU8: 34700 | BV8: =HAVERQ!T68 -> 469 | BW8: =HAVERQ!U68+HAVERQ!W68+HAVERQ!X68 -> 340 | BX8: =HAVERQ!V68 -> 4199 | BY8: =HAVERQ!Y68 -> 1844 | BZ8: =HAVERQ!Z68+HAVERQ!AB68 -> 6287 | CA8: =HAVERQ!AA68+HAVERQ!AC68 -> 2097 | CB8: =HAVERQ!AD68+HAVERQ!AE68+HAVERQ!AF68+HAVERQ!AG68 -> 4659 | CC8: =HAVERQ!AH68+HAVERQ!AI68+HAVERQ!AJ68+HAVERQ!AK68+HAVERQ!AL68+HAVERQ!AM68 -> 8034 | CD8: =HAVERQ!S68-SUM('Chart Data'!BV8:CC8) -> 1 | CF8: Height | CG8: 0.5 | CH8: =+CG8+1 -> 1.5 | CI8: =+CH8+1 -> 2.5 | CJ8: =+CI8+1 -> 3.5 | CK8: =+CJ8+1 -> 4.5 | CL8: =+CK8+1 -> 5.5 | CM8: =+CL8+1 -> 6.5 | CN8: =+CM8+1 -> 7.5 | CO8: =+CN8+1 -> 8.5 | ... CZ8: =+CY8+1 -> 19.5 | DB8: 36526 | DC8: =HAVERQ!BI88/HAVERQ!T88 -> 8.1234257 | DD8: =HAVERQ!BJ88/HAVERQ!U88 -> 593.73684 | DE8: =HAVERQ!BK88/HAVERQ!V88 -> 9.6789331 | DF8: =HAVERQ!BL88/HAVERQ!W88 -> 81.489583 | DG8: =HAVERQ!BM88/HAVERQ!X88 -> 45.165605 | DH8: =HAVERQ!BN88/HAVERQ!Y88 -> 18.102148 | DI8: =HAVERQ!BO88/HAVERQ!Z88 -> 10.235186 | DJ8: =HAVERQ!BP88/HAVERQ!AA88 -> 13.541728 | ... DT8: =HAVERQ!BZ88/HAVERQ!AK88 -> 9.1008065 | DU8: =(HAVERQ!CA88+HAVERQ!CB88)/HAVERQ!AL88 -> 11.153465 | DW8: 2019-2024 | DX8: =DX5-DX4 -> 1227.75 | DY8: =DY5-DY4 -> -38 | DZ8: =DZ5-DZ4 -> -13 | EA8: =EA5-EA4 -> -102.75 | EB8: =EB5-EB4 -> -6 | EC8: =EC5-EC4 -> 23.5 | ED8: =ED5-ED4 -> -124.25 | EE8: =EE5-EE4 -> -283 | ... EQ8: =EQ5-EQ4 -> -20 | ES8: 2019-2024 | ET8: =ET5-ET4 -> -38 | EU8: =EU5-EU4 -> 4.5 | EV8: =EV5-EV4 -> -102.75 | EW8: =EW5-EW4 -> -124.25 | EX8: =EX5-EX4 -> -115.75 | EY8: =EY5-EY4 -> 210 | EZ8: =EZ5-EZ4 -> 404.75 | FA8: =FA5-FA4 -> 990.5 | FD8: 44197 | FE8: =DataQ!U199+DataQ!V199+DataQ!W199+DataQ!X199+DataQ!Y199 -> 10964 | FF8: =DataQ!J199+DataQ!Q199+DataQ!H199+DataQ!P199+DataQ!S199+DataQ!K199+DataQ!L199 -> 8418 | FG8: =DataQ!N199+DataQ!I199+DataQ!R199+DataQ!G199+DataQ!T199+DataQ!M199+DataQ!O199 -> 15353 | FH8: =DataQ!F199-'Chart Data'!FE8-'Chart Data'!FF8-'Chart Data'!FG8 -> -1 | FJ8: 44197 | FK8: =FE8-(AVERAGE(FE$20:FE$23)) -> -966.75 | FL8: =FF8-(AVERAGE(FF$20:FF$23)) -> -527.25 | FM8: =FG8-(AVERAGE(FG$20:FG$23)) -> -565.25 | FN8: =SUM(FK8:FM8) -> -2059.25 | FP8: 42125 | FQ8: =100*((AVERAGE(HAVERM!AS430:AS432)/AVERAGE(HAVERM!AS427:AS429))-1) -> 0.81416259 | FR8: =100*((AVERAGE(HAVERM!AT430:AT432)/AVERAGE(HAVERM!AT427:AT429))-1) -> 0.61407697 | FS8: =100*((AVERAGE(HAVERM!AU430:AU432)/AVERAGE(HAVERM!AU427:AU429))-1) -> -2.5842577 | FT8: =100*((AVERAGE(HAVERM!AV430:AV432)/AVERAGE(HAVERM!AV427:AV429))-1) -> 0.9353508 | FU8: =100*((AVERAGE(HAVERM!AW430:AW432)/AVERAGE(HAVERM!AW427:AW429))-1) -> -0.20842766 | FV8: =100*((AVERAGE(HAVERM!AX430:AX432)/AVERAGE(HAVERM!AX427:AX429))-1) -> 0.97402112 | FW8: =100*((AVERAGE(HAVERM!AY430:AY432)/AVERAGE(HAVERM!AY427:AY429))-1) -> 2.2063106 | FX8: =100*((AVERAGE(HAVERM!AZ430:AZ432)/AVERAGE(HAVERM!AZ427:AZ429))-1) -> 0.48713175 | ... GI8: =100*((AVERAGE(HAVERM!BK430:BK432)/AVERAGE(HAVERM!BK427:BK429))-1) -> 1.0562295 | GJ8: =100*(((AVERAGE(HAVERM!BL430:BL432)+(AVERAGE(HAVERM!BM430:BM432)))/(AVERAGE(HAVERM!BL427:BL429)+AVERAGE(HAVERM!BM427:BM429))-1)) -> 0.80609794 | GL8: 42125 | GW8: 42125 | GX8: =HAVERM!AT432 -> 179850 | GY8: =HAVERM!AU432+HAVERM!AW432+HAVERM!AX432 -> 307190 | GZ8: =HAVERM!AV432 -> 2375914 | HA8: =HAVERM!AY432 -> 1134708 | HB8: =HAVERM!AZ432+HAVERM!BB432 -> 6205823 | HC8: =HAVERM!BA432+HAVERM!BC432 -> 2279115 | HD8: =HAVERM!BD432 -> 1080051 | HE8: =HAVERM!BE432+HAVERM!BF432+HAVERM!BG432 -> 4714370 | HF8: =HAVERM!BH432+HAVERM!BI432+HAVERM!BJ432+HAVERM!BK432+HAVERM!BL432+HAVERM!BM432 -> 9122668 | HH8: Water | HI8: ='ASHE Annual pay All SIC'!D63 -> 38435 | HJ8: 0.59868603 | HL8: Water | HM8: ='ASHE Annual pay All SIC'!D63 -> 38435 | HN8: 0.45916667 | HP8: 2011 | HQ8: 17.154498 | HR8: 2.6298741 | HS8: =HQ8+HR8 -> 19.784372 | HU8: 2011 | HV8: 6418.6721 | HW8: 984.01593 | HX8: =HV8+HW8 -> 7402.688 | HZ8: 43831 | IA8: =HAVERQ!E168 -> 5369 | IB8: =HAVERQ!F168 -> 27450 | IC8: =DataQ!Z195-('Chart Data'!IA8+'Chart Data'!IB8) -> 157 | IE8: 43831 | IF8: =IA8-AVERAGE(IA$4:IA$7) -> 53.25 | IG8: =IB8-AVERAGE(IB$4:IB$7) -> -174 | II8: 43831 | IJ8: =100*(IA8/AVERAGE(IA$4:IA$7)) -> 101.00174 | IK8: =100*(IB8/AVERAGE(IB$4:IB$7)) -> 99.370113 | IM8: 43831 | IN8: =SUM(DataQ!U195:Y195) -> 10975 | IO8: =DataQ!F195-'Chart Data'!IN8 -> 24634 | IQ8: 43831 | IR8: =100*(IN8/AVERAGE(IN$4:IN$7)) -> 100.31763 | IS8: =100*(IO8/AVERAGE(IO$4:IO$7)) -> 100.03756
A9: 43922 | B9: =HAVERQ!E169-AVERAGE(HAVERQ!E$164:E$167) -> 97.25 | C9: =HAVERQ!F169-AVERAGE(HAVERQ!F$164:F$167) -> -461 | E9: 36982 | F9: =HAVERQ!P93 -> 1249 | G9: =HAVERQ!O93 -> 1468 | H9: =HAVERQ!N93 -> 1185 | I9: =HAVERQ!M93 -> 229 | J9: =HAVERQ!L93 -> 214 | K9: =HAVERQ!E93-F9-G9-H9-I9-J9 -> 792 | M9: 36982 | N9: =100*(F9/SUM($F9:$K9)) -> 24.313802 | O9: =100*(G9/SUM($F9:$K9)) -> 28.57699 | P9: =100*(H9/SUM($F9:$K9)) -> 23.067938 | Q9: =100*(I9/SUM($F9:$K9)) -> 4.4578548 | R9: =100*(J9/SUM($F9:$K9)) -> 4.1658556 | S9: =100*(K9/SUM($F9:$K9)) -> 15.417559 | U9: 36982 | V9: =F9-AVERAGE(F$4:F$7) -> 39.75 | W9: =G9-AVERAGE(G$4:G$7) -> 28.25 | X9: =H9-AVERAGE(H$4:H$7) -> 6 | Y9: =I9-AVERAGE(I$4:I$7) -> 3.25 | Z9: =J9-AVERAGE(J$4:J$7) -> -2.25 | AA9: =K9-AVERAGE(K$4:K$7) -> 4.25 | AB9: =SUM(V9:AA9) -> 79.25 | AD9: 43922 | AE9: =HAVERQ!T169-AVERAGE(HAVERQ!T$164:T$167) -> -21.25 | AF9: =HAVERQ!U169-AVERAGE(HAVERQ!U$164:U$167) -> -0.25 | AG9: =HAVERQ!V169-AVERAGE(HAVERQ!V$164:V$167) -> -72.75 | AH9: =HAVERQ!W169-AVERAGE(HAVERQ!W$164:W$167) -> 4.25 | AI9: =HAVERQ!X169-AVERAGE(HAVERQ!X$164:X$167) -> -4.5 | AJ9: =HAVERQ!Y169-AVERAGE(HAVERQ!Y$164:Y$167) -> -57.25 | AK9: =HAVERQ!Z169-AVERAGE(HAVERQ!Z$164:Z$167) -> -29.5 | AL9: =HAVERQ!AA169-AVERAGE(HAVERQ!AA$164:AA$167) -> 1 | ... AV9: =HAVERQ!AK169-AVERAGE(HAVERQ!AK$164:AK$167) -> -51.75 | AW9: =AY9-AVERAGE(AY$4:AY$7) -> -40.5 | AY9: =HAVERQ!AL169+HAVERQ!AM169 -> 977 | BA9: 43922 | BB9: =BK9-AVERAGE(BK$4:BK$7) -> -21.25 | BC9: =BL9-AVERAGE(BL$4:BL$7) -> -0.5 | BD9: =BM9-AVERAGE(BM$4:BM$7) -> -72.75 | BE9: =BN9-AVERAGE(BN$4:BN$7) -> -57.25 | BF9: =BO9-AVERAGE(BO$4:BO$7) -> -181.5 | BG9: =BP9-AVERAGE(BP$4:BP$7) -> 21.75 | BH9: =BQ9-AVERAGE(BQ$4:BQ$7) -> -156.5 | BI9: =BR9-AVERAGE(BR$4:BR$7) -> 36.75 | BK9: =HAVERQ!T169 -> 377 | BL9: =HAVERQ!U169+HAVERQ!W169+HAVERQ!X169 -> 425 | BM9: =HAVERQ!V169 -> 2618 | BN9: =HAVERQ!Y169 -> 2276 | BO9: =HAVERQ!Z169+HAVERQ!AB169 -> 7323 | BP9: =HAVERQ!AA169+HAVERQ!AC169 -> 3328 | BQ9: =HAVERQ!AD169+HAVERQ!AE169+HAVERQ!AF169+HAVERQ!AG169 -> 7810 | BR9: =HAVERQ!AH169+HAVERQ!AI169+HAVERQ!AJ169+HAVERQ!AK169+HAVERQ!AL169+HAVERQ!AM169 -> 10977 | BS9: =HAVERQ!S169-SUM('Chart Data'!BK9:BR9) -> 1 | BU9: 34790 | BV9: =HAVERQ!T69 -> 465 | BW9: =HAVERQ!U69+HAVERQ!W69+HAVERQ!X69 -> 337 | BX9: =HAVERQ!V69 -> 4214 | BY9: =HAVERQ!Y69 -> 1856 | BZ9: =HAVERQ!Z69+HAVERQ!AB69 -> 6312 | CA9: =HAVERQ!AA69+HAVERQ!AC69 -> 2109 | CB9: =HAVERQ!AD69+HAVERQ!AE69+HAVERQ!AF69+HAVERQ!AG69 -> 4693 | CC9: =HAVERQ!AH69+HAVERQ!AI69+HAVERQ!AJ69+HAVERQ!AK69+HAVERQ!AL69+HAVERQ!AM69 -> 8061 | CD9: =HAVERQ!S69-SUM('Chart Data'!BV9:CC9) -> 0 | DB9: 36617 | DC9: =HAVERQ!BI89/HAVERQ!T89 -> 8.2481203 | DD9: =HAVERQ!BJ89/HAVERQ!U89 -> 542.57692 | DE9: =HAVERQ!BK89/HAVERQ!V89 -> 9.9065467 | DF9: =HAVERQ!BL89/HAVERQ!W89 -> 77.8 | DG9: =HAVERQ!BM89/HAVERQ!X89 -> 44.962733 | DH9: =HAVERQ!BN89/HAVERQ!Y89 -> 17.232261 | DI9: =HAVERQ!BO89/HAVERQ!Z89 -> 10.494168 | DJ9: =HAVERQ!BP89/HAVERQ!AA89 -> 13.292127 | ... DT9: =HAVERQ!BZ89/HAVERQ!AK89 -> 8.8544474 | DU9: =(HAVERQ!CA89+HAVERQ!CB89)/HAVERQ!AL89 -> 11.009816 | DW9: 2024-2029 | DX9: =DX6-DX5 -> 1935.775 | DY9: =DY6-DY5 -> 2.364 | DZ9: =DZ6-DZ5 -> -5.124315 | EA9: =EA6-EA5 -> -151.60175 | EB9: =EB6-EB5 -> -0.832325 | EC9: =EC6-EC5 -> 6.236875 | ED9: =ED6-ED5 -> 204.85175 | EE9: =EE6-EE5 -> 224.22125 | ... EQ9: =EQ6-EQ5 -> 74.553 | ES9: 2025-2029 | ET9: =ET6-ET5 -> 2.364 | EU9: =EU6-EU5 -> 0.280235 | EV9: =EV6-EV5 -> -151.60175 | EW9: =EW6-EW5 -> 204.85175 | EX9: =EX6-EX5 -> 326.94325 | EY9: =EY6-EY5 -> 284.261 | EZ9: =EZ6-EZ5 -> 558.71665 | FA9: =FA6-FA5 -> 707.4605 | FD9: 44287 | FE9: =DataQ!U200+DataQ!V200+DataQ!W200+DataQ!X200+DataQ!Y200 -> 11078 | FF9: =DataQ!J200+DataQ!Q200+DataQ!H200+DataQ!P200+DataQ!S200+DataQ!K200+DataQ!L200 -> 8495 | FG9: =DataQ!N200+DataQ!I200+DataQ!R200+DataQ!G200+DataQ!T200+DataQ!M200+DataQ!O200 -> 15499 | FH9: =DataQ!F200-'Chart Data'!FE9-'Chart Data'!FF9-'Chart Data'!FG9 -> 0 | FJ9: 44287 | FK9: =FE9-(AVERAGE(FE$20:FE$23)) -> -852.75 | FL9: =FF9-(AVERAGE(FF$20:FF$23)) -> -450.25 | FM9: =FG9-(AVERAGE(FG$20:FG$23)) -> -419.25 | FN9: =SUM(FK9:FM9) -> -1722.25 | FP9: 42156 | FQ9: =100*((AVERAGE(HAVERM!AS431:AS433)/AVERAGE(HAVERM!AS428:AS430))-1) -> 0.65543456 | FR9: =100*((AVERAGE(HAVERM!AT431:AT433)/AVERAGE(HAVERM!AT428:AT430))-1) -> 0.99806145 | FS9: =100*((AVERAGE(HAVERM!AU431:AU433)/AVERAGE(HAVERM!AU428:AU430))-1) -> -3.7028281 | FT9: =100*((AVERAGE(HAVERM!AV431:AV433)/AVERAGE(HAVERM!AV428:AV430))-1) -> 0.3002207 | FU9: =100*((AVERAGE(HAVERM!AW431:AW433)/AVERAGE(HAVERM!AW428:AW430))-1) -> -0.59203194 | FV9: =100*((AVERAGE(HAVERM!AX431:AX433)/AVERAGE(HAVERM!AX428:AX430))-1) -> 0.71836269 | FW9: =100*((AVERAGE(HAVERM!AY431:AY433)/AVERAGE(HAVERM!AY428:AY430))-1) -> 1.4416788 | FX9: =100*((AVERAGE(HAVERM!AZ431:AZ433)/AVERAGE(HAVERM!AZ428:AZ430))-1) -> 0.36596838 | ... GI9: =100*((AVERAGE(HAVERM!BK431:BK433)/AVERAGE(HAVERM!BK428:BK430))-1) -> 1.1236907 | GJ9: =100*(((AVERAGE(HAVERM!BL431:BL433)+(AVERAGE(HAVERM!BM431:BM433)))/(AVERAGE(HAVERM!BL428:BL430)+AVERAGE(HAVERM!BM428:BM430))-1)) -> 0.51072785 | GL9: 42156 | GW9: 42156 | GX9: =HAVERM!AT433 -> 181235 | GY9: =HAVERM!AU433+HAVERM!AW433+HAVERM!AX433 -> 307792 | GZ9: =HAVERM!AV433 -> 2381302 | HA9: =HAVERM!AY433 -> 1141150 | HB9: =HAVERM!AZ433+HAVERM!BB433 -> 6232523 | HC9: =HAVERM!BA433+HAVERM!BC433 -> 2291343 | HD9: =HAVERM!BD433 -> 1085127 | HE9: =HAVERM!BE433+HAVERM!BF433+HAVERM!BG433 -> 4724364 | HF9: =HAVERM!BH433+HAVERM!BI433+HAVERM!BJ433+HAVERM!BK433+HAVERM!BL433+HAVERM!BM433 -> 9117559 | HH9: Construction | HI9: ='ASHE Annual pay All SIC'!D68 -> 38209 | HJ9: -1.3505204 | HL9: Construction | HM9: ='ASHE Annual pay All SIC'!D68 -> 38209 | HN9: 0.53333333 | HP9: 2012 | HQ9: 16.411266 | HR9: 2.4708379 | HS9: =HQ9+HR9 -> 18.882104 | HU9: 2012 | HV9: 6178.2958 | HW9: 930.18829 | HX9: =HV9+HW9 -> 7108.4841 | HZ9: 43922 | IA9: =HAVERQ!E169 -> 5413 | IB9: =HAVERQ!F169 -> 27163 | IC9: =DataQ!Z196-('Chart Data'!IA9+'Chart Data'!IB9) -> 58 | IE9: 43922 | IF9: =IA9-AVERAGE(IA$4:IA$7) -> 97.25 | IG9: =IB9-AVERAGE(IB$4:IB$7) -> -461 | II9: 43922 | IJ9: =100*(IA9/AVERAGE(IA$4:IA$7)) -> 101.82947 | IK9: =100*(IB9/AVERAGE(IB$4:IB$7)) -> 98.331161 | IM9: 43922 | IN9: =SUM(DataQ!U196:Y196) -> 10977 | IO9: =DataQ!F196-'Chart Data'!IN9 -> 24158 | IQ9: 43922 | IR9: =100*(IN9/AVERAGE(IN$4:IN$7)) -> 100.33592 | IS9: =100*(IO9/AVERAGE(IO$4:IO$7)) -> 98.104549
A10: 44013 | B10: =HAVERQ!E170-AVERAGE(HAVERQ!E$164:E$167) -> 104.25 | C10: =HAVERQ!F170-AVERAGE(HAVERQ!F$164:F$167) -> -721 | E10: 37073 | F10: =HAVERQ!P94 -> 1263 | G10: =HAVERQ!O94 -> 1465 | H10: =HAVERQ!N94 -> 1188 | I10: =HAVERQ!M94 -> 231 | J10: =HAVERQ!L94 -> 214 | K10: =HAVERQ!E94-F10-G10-H10-I10-J10 -> 795 | M10: 37073 | N10: =100*(F10/SUM($F10:$K10)) -> 24.495733 | O10: =100*(G10/SUM($F10:$K10)) -> 28.413499 | P10: =100*(H10/SUM($F10:$K10)) -> 23.041117 | Q10: =100*(I10/SUM($F10:$K10)) -> 4.4802172 | R10: =100*(J10/SUM($F10:$K10)) -> 4.1505043 | S10: =100*(K10/SUM($F10:$K10)) -> 15.418929 | U10: 37073 | V10: =F10-AVERAGE(F$4:F$7) -> 53.75 | W10: =G10-AVERAGE(G$4:G$7) -> 25.25 | X10: =H10-AVERAGE(H$4:H$7) -> 9 | Y10: =I10-AVERAGE(I$4:I$7) -> 5.25 | Z10: =J10-AVERAGE(J$4:J$7) -> -2.25 | AA10: =K10-AVERAGE(K$4:K$7) -> 7.25 | AB10: =SUM(V10:AA10) -> 98.25 | AD10: 44013 | AE10: =HAVERQ!T170-AVERAGE(HAVERQ!T$164:T$167) -> 18.75 | AF10: =HAVERQ!U170-AVERAGE(HAVERQ!U$164:U$167) -> -7.25 | AG10: =HAVERQ!V170-AVERAGE(HAVERQ!V$164:V$167) -> -120.75 | AH10: =HAVERQ!W170-AVERAGE(HAVERQ!W$164:W$167) -> 1.25 | AI10: =HAVERQ!X170-AVERAGE(HAVERQ!X$164:X$167) -> 0.5 | AJ10: =HAVERQ!Y170-AVERAGE(HAVERQ!Y$164:Y$167) -> -190.25 | AK10: =HAVERQ!Z170-AVERAGE(HAVERQ!Z$164:Z$167) -> -163.5 | AL10: =HAVERQ!AA170-AVERAGE(HAVERQ!AA$164:AA$167) -> -16 | ... AV10: =HAVERQ!AK170-AVERAGE(HAVERQ!AK$164:AK$167) -> -105.75 | AW10: =AY10-AVERAGE(AY$4:AY$7) -> -78.5 | AY10: =HAVERQ!AL170+HAVERQ!AM170 -> 939 | BA10: 44013 | BB10: =BK10-AVERAGE(BK$4:BK$7) -> 18.75 | BC10: =BL10-AVERAGE(BL$4:BL$7) -> -5.5 | BD10: =BM10-AVERAGE(BM$4:BM$7) -> -120.75 | BE10: =BN10-AVERAGE(BN$4:BN$7) -> -190.25 | BF10: =BO10-AVERAGE(BO$4:BO$7) -> -377.5 | BG10: =BP10-AVERAGE(BP$4:BP$7) -> -4.25 | BH10: =BQ10-AVERAGE(BQ$4:BQ$7) -> -194.5 | BI10: =BR10-AVERAGE(BR$4:BR$7) -> -97.25 | BK10: =HAVERQ!T170 -> 417 | BL10: =HAVERQ!U170+HAVERQ!W170+HAVERQ!X170 -> 420 | BM10: =HAVERQ!V170 -> 2570 | BN10: =HAVERQ!Y170 -> 2143 | BO10: =HAVERQ!Z170+HAVERQ!AB170 -> 7127 | BP10: =HAVERQ!AA170+HAVERQ!AC170 -> 3302 | BQ10: =HAVERQ!AD170+HAVERQ!AE170+HAVERQ!AF170+HAVERQ!AG170 -> 7772 | BR10: =HAVERQ!AH170+HAVERQ!AI170+HAVERQ!AJ170+HAVERQ!AK170+HAVERQ!AL170+HAVERQ!AM170 -> 10843 | BS10: =HAVERQ!S170-SUM('Chart Data'!BK10:BR10) -> 0 | BU10: 34881 | BV10: =HAVERQ!T70 -> 469 | BW10: =HAVERQ!U70+HAVERQ!W70+HAVERQ!X70 -> 333 | BX10: =HAVERQ!V70 -> 4219 | BY10: =HAVERQ!Y70 -> 1843 | BZ10: =HAVERQ!Z70+HAVERQ!AB70 -> 6294 | CA10: =HAVERQ!AA70+HAVERQ!AC70 -> 2109 | CB10: =HAVERQ!AD70+HAVERQ!AE70+HAVERQ!AF70+HAVERQ!AG70 -> 4754 | CC10: =HAVERQ!AH70+HAVERQ!AI70+HAVERQ!AJ70+HAVERQ!AK70+HAVERQ!AL70+HAVERQ!AM70 -> 8024 | CD10: =HAVERQ!S70-SUM('Chart Data'!BV10:CC10) -> 1 | CF10: 2014-2024 average | CI10: =AVERAGE(HAVERM!Y428:Y547) -> 2.4875 | CJ10: =AVERAGE(HAVERM!Z428:Z547) -> 2.4725 | CK10: =AVERAGE(HAVERM!AA428:AA547) -> 3.3033333 | CL10: =AVERAGE(HAVERM!AB428:AB547) -> 2.2075 | CM10: =AVERAGE(HAVERM!AC428:AC547) -> 2.0666667 | CN10: =AVERAGE(HAVERM!AD428:AD547) -> 2.8 | CO10: =AVERAGE(HAVERM!AE428:AE547) -> 2.4191667 | CP10: =AVERAGE(HAVERM!AF428:AF547) -> 4.145 | ... CZ10: =AVERAGE(HAVERM!AP428:AP547) -> 3.2266667 | DB10: 36708 | DC10: =HAVERQ!BI90/HAVERQ!T90 -> 8.5575448 | DD10: =HAVERQ!BJ90/HAVERQ!U90 -> 537.97368 | DE10: =HAVERQ!BK90/HAVERQ!V90 -> 10.103535 | DF10: =HAVERQ!BL90/HAVERQ!W90 -> 77.6 | DG10: =HAVERQ!BM90/HAVERQ!X90 -> 45.378049 | DH10: =HAVERQ!BN90/HAVERQ!Y90 -> 16.968557 | DI10: =HAVERQ!BO90/HAVERQ!Z90 -> 10.304304 | DJ10: =HAVERQ!BP90/HAVERQ!AA90 -> 13.564493 | ... DT10: =HAVERQ!BZ90/HAVERQ!AK90 -> 8.9796472 | DU10: =(HAVERQ!CA90+HAVERQ!CB90)/HAVERQ!AL90 -> 11.081181 | FD10: 44378 | FE10: =DataQ!U201+DataQ!V201+DataQ!W201+DataQ!X201+DataQ!Y201 -> 11116 | FF10: =DataQ!J201+DataQ!Q201+DataQ!H201+DataQ!P201+DataQ!S201+DataQ!K201+DataQ!L201 -> 8537 | FG10: =DataQ!N201+DataQ!I201+DataQ!R201+DataQ!G201+DataQ!T201+DataQ!M201+DataQ!O201 -> 15632 | FH10: =DataQ!F201-'Chart Data'!FE10-'Chart Data'!FF10-'Chart Data'!FG10 -> 1 | FJ10: 44378 | FK10: =FE10-(AVERAGE(FE$20:FE$23)) -> -814.75 | FL10: =FF10-(AVERAGE(FF$20:FF$23)) -> -408.25 | FM10: =FG10-(AVERAGE(FG$20:FG$23)) -> -286.25 | FN10: =SUM(FK10:FM10) -> -1509.25 | FP10: 42186 | FQ10: =100*((AVERAGE(HAVERM!AS432:AS434)/AVERAGE(HAVERM!AS429:AS431))-1) -> 0.65023295 | FR10: =100*((AVERAGE(HAVERM!AT432:AT434)/AVERAGE(HAVERM!AT429:AT431))-1) -> 1.2809987 | FS10: =100*((AVERAGE(HAVERM!AU432:AU434)/AVERAGE(HAVERM!AU429:AU431))-1) -> -3.6868721 | FT10: =100*((AVERAGE(HAVERM!AV432:AV434)/AVERAGE(HAVERM!AV429:AV431))-1) -> 0.24089649 | FU10: =100*((AVERAGE(HAVERM!AW432:AW434)/AVERAGE(HAVERM!AW429:AW431))-1) -> 0.27026056 | FV10: =100*((AVERAGE(HAVERM!AX432:AX434)/AVERAGE(HAVERM!AX429:AX431))-1) -> 0.74316643 | FW10: =100*((AVERAGE(HAVERM!AY432:AY434)/AVERAGE(HAVERM!AY429:AY431))-1) -> 1.4286985 | FX10: =100*((AVERAGE(HAVERM!AZ432:AZ434)/AVERAGE(HAVERM!AZ429:AZ431))-1) -> 0.53111343 | ... GI10: =100*((AVERAGE(HAVERM!BK432:BK434)/AVERAGE(HAVERM!BK429:BK431))-1) -> 1.2911406 | GJ10: =100*(((AVERAGE(HAVERM!BL432:BL434)+(AVERAGE(HAVERM!BM432:BM434)))/(AVERAGE(HAVERM!BL429:BL431)+AVERAGE(HAVERM!BM429:BM431))-1)) -> 0.56328082 | GL10: 42186 | GW10: 42186 | GX10: =HAVERM!AT434 -> 181690 | GY10: =HAVERM!AU434+HAVERM!AW434+HAVERM!AX434 -> 308142 | GZ10: =HAVERM!AV434 -> 2381671 | HA10: =HAVERM!AY434 -> 1144054 | HB10: =HAVERM!AZ434+HAVERM!BB434 -> 6249550 | HC10: =HAVERM!BA434+HAVERM!BC434 -> 2298406 | HD10: =HAVERM!BD434 -> 1086447 | HE10: =HAVERM!BE434+HAVERM!BF434+HAVERM!BG434 -> 4744180 | HF10: =HAVERM!BH434+HAVERM!BI434+HAVERM!BJ434+HAVERM!BK434+HAVERM!BL434+HAVERM!BM434 -> 9126353 | HH10: Wholesale & retail | HI10: ='ASHE Annual pay All SIC'!D72 -> 25560 | HJ10: -0.61715835 | HL10: Wholesale & retail | HM10: ='ASHE Annual pay All SIC'!D72 -> 25560 | HN10: -0.53333333 | HP10: 2013 | HQ10: 15.944478 | HR10: 2.5544611 | HS10: =HQ10+HR10 -> 18.498939 | HU10: 2013 | HV10: 6114.5109 | HW10: 979.60436 | HX10: =HV10+HW10 -> 7094.1152 | HZ10: 44013 | IA10: =HAVERQ!E170 -> 5420 | IB10: =HAVERQ!F170 -> 26903 | IC10: =DataQ!Z197-('Chart Data'!IA10+'Chart Data'!IB10) -> 34 | IE10: 44013 | IF10: =IA10-AVERAGE(IA$4:IA$7) -> 104.25 | IG10: =IB10-AVERAGE(IB$4:IB$7) -> -721 | II10: 44013 | IJ10: =100*(IA10/AVERAGE(IA$4:IA$7)) -> 101.96115 | IK10: =100*(IB10/AVERAGE(IB$4:IB$7)) -> 97.389951 | IM10: 44013 | IN10: =SUM(DataQ!U197:Y197) -> 10843 | IO10: =DataQ!F197-'Chart Data'!IN10 -> 23751 | IQ10: 44013 | IR10: =100*(IN10/AVERAGE(IN$4:IN$7)) -> 99.111081 | IS10: =100*(IO10/AVERAGE(IO$4:IO$7)) -> 96.451741
A11: 44105 | B11: =HAVERQ!E171-AVERAGE(HAVERQ!E$164:E$167) -> 134.25 | C11: =HAVERQ!F171-AVERAGE(HAVERQ!F$164:F$167) -> -804 | E11: 37165 | F11: =HAVERQ!P95 -> 1278 | G11: =HAVERQ!O95 -> 1467 | H11: =HAVERQ!N95 -> 1197 | I11: =HAVERQ!M95 -> 234 | J11: =HAVERQ!L95 -> 214 | K11: =HAVERQ!E95-F11-G11-H11-I11-J11 -> 769 | M11: 37165 | N11: =100*(F11/SUM($F11:$K11)) -> 24.772243 | O11: =100*(G11/SUM($F11:$K11)) -> 28.435743 | P11: =100*(H11/SUM($F11:$K11)) -> 23.202171 | Q11: =100*(I11/SUM($F11:$K11)) -> 4.5357627 | R11: =100*(J11/SUM($F11:$K11)) -> 4.1480907 | S11: =100*(K11/SUM($F11:$K11)) -> 14.90599 | U11: 37165 | V11: =F11-AVERAGE(F$4:F$7) -> 68.75 | W11: =G11-AVERAGE(G$4:G$7) -> 27.25 | X11: =H11-AVERAGE(H$4:H$7) -> 18 | Y11: =I11-AVERAGE(I$4:I$7) -> 8.25 | Z11: =J11-AVERAGE(J$4:J$7) -> -2.25 | AA11: =K11-AVERAGE(K$4:K$7) -> -18.75 | AB11: =SUM(V11:AA11) -> 101.25 | AD11: 44105 | AE11: =HAVERQ!T171-AVERAGE(HAVERQ!T$164:T$167) -> -18.25 | AF11: =HAVERQ!U171-AVERAGE(HAVERQ!U$164:U$167) -> -8.25 | AG11: =HAVERQ!V171-AVERAGE(HAVERQ!V$164:V$167) -> -134.75 | AH11: =HAVERQ!W171-AVERAGE(HAVERQ!W$164:W$167) -> 4.25 | AI11: =HAVERQ!X171-AVERAGE(HAVERQ!X$164:X$167) -> 0.5 | AJ11: =HAVERQ!Y171-AVERAGE(HAVERQ!Y$164:Y$167) -> -179.25 | AK11: =HAVERQ!Z171-AVERAGE(HAVERQ!Z$164:Z$167) -> -174.5 | AL11: =HAVERQ!AA171-AVERAGE(HAVERQ!AA$164:AA$167) -> -47 | ... AV11: =HAVERQ!AK171-AVERAGE(HAVERQ!AK$164:AK$167) -> -119.75 | AW11: =AY11-AVERAGE(AY$4:AY$7) -> -88.5 | AY11: =HAVERQ!AL171+HAVERQ!AM171 -> 929 | BA11: 44105 | BB11: =BK11-AVERAGE(BK$4:BK$7) -> -18.25 | BC11: =BL11-AVERAGE(BL$4:BL$7) -> -3.5 | BD11: =BM11-AVERAGE(BM$4:BM$7) -> -134.75 | BE11: =BN11-AVERAGE(BN$4:BN$7) -> -179.25 | BF11: =BO11-AVERAGE(BO$4:BO$7) -> -478.5 | BG11: =BP11-AVERAGE(BP$4:BP$7) -> -42.25 | BH11: =BQ11-AVERAGE(BQ$4:BQ$7) -> -118.5 | BI11: =BR11-AVERAGE(BR$4:BR$7) -> -66.25 | BK11: =HAVERQ!T171 -> 380 | BL11: =HAVERQ!U171+HAVERQ!W171+HAVERQ!X171 -> 422 | BM11: =HAVERQ!V171 -> 2556 | BN11: =HAVERQ!Y171 -> 2154 | BO11: =HAVERQ!Z171+HAVERQ!AB171 -> 7026 | BP11: =HAVERQ!AA171+HAVERQ!AC171 -> 3264 | BQ11: =HAVERQ!AD171+HAVERQ!AE171+HAVERQ!AF171+HAVERQ!AG171 -> 7848 | BR11: =HAVERQ!AH171+HAVERQ!AI171+HAVERQ!AJ171+HAVERQ!AK171+HAVERQ!AL171+HAVERQ!AM171 -> 10874 | BS11: =HAVERQ!S171-SUM('Chart Data'!BK11:BR11) -> -2 | BU11: 34973 | BV11: =HAVERQ!T71 -> 471 | BW11: =HAVERQ!U71+HAVERQ!W71+HAVERQ!X71 -> 337 | BX11: =HAVERQ!V71 -> 4273 | BY11: =HAVERQ!Y71 -> 1837 | BZ11: =HAVERQ!Z71+HAVERQ!AB71 -> 6334 | CA11: =HAVERQ!AA71+HAVERQ!AC71 -> 2100 | CB11: =HAVERQ!AD71+HAVERQ!AE71+HAVERQ!AF71+HAVERQ!AG71 -> 4798 | CC11: =HAVERQ!AH71+HAVERQ!AI71+HAVERQ!AJ71+HAVERQ!AK71+HAVERQ!AL71+HAVERQ!AM71 -> 8042 | CD11: =HAVERQ!S71-SUM('Chart Data'!BV11:CC11) -> 0 | CF11: Diff vs average of past 10 years | CI11: =CI4-CI10 -> 0.77916667 | CJ11: =CJ4-CJ10 -> -0.30583333 | CK11: =CK4-CK10 -> -0.30333333 | CL11: =CL4-CL10 -> 0.45916667 | CM11: =CM4-CM10 -> 0.53333333 | CN11: =CN4-CN10 -> -0.53333333 | CO11: =CO4-CO10 -> -0.31916667 | CP11: =CP4-CP10 -> -0.91166667 | ... CZ11: =CZ4-CZ10 -> -1.06 | DB11: 36800 | DC11: =HAVERQ!BI91/HAVERQ!T91 -> 8.9177719 | DD11: =HAVERQ!BJ91/HAVERQ!U91 -> 519.67105 | DE11: =HAVERQ!BK91/HAVERQ!V91 -> 10.453893 | DF11: =HAVERQ!BL91/HAVERQ!W91 -> 80.737374 | DG11: =HAVERQ!BM91/HAVERQ!X91 -> 44.939394 | DH11: =HAVERQ!BN91/HAVERQ!Y91 -> 17.304236 | DI11: =HAVERQ!BO91/HAVERQ!Z91 -> 10.183711 | DJ11: =HAVERQ!BP91/HAVERQ!AA91 -> 13.234832 | ... DT11: =HAVERQ!BZ91/HAVERQ!AK91 -> 9.0147651 | DU11: =(HAVERQ!CA91+HAVERQ!CB91)/HAVERQ!AL91 -> 10.566998 | DW11: 2019-2024 | DX11: =100*((DX5/DX4)^(1/5)-1) -> 0.68108504 | DY11: =100*((DY5/DY4)^(1/5)-1) -> -1.9856552 | DZ11: =100*((DZ5/DZ4)^(1/5)-1) -> -4.65932 | EA11: =100*((EA5/EA4)^(1/5)-1) -> -0.77566782 | EB11: =100*((EB5/EB4)^(1/5)-1) -> -0.86126932 | EC11: =100*((EC5/EC4)^(1/5)-1) -> 2.0283864 | ED11: =100*((ED5/ED4)^(1/5)-1) -> -1.0884772 | EE11: =100*((EE5/EE4)^(1/5)-1) -> -1.1572317 | ... EQ11: =100*((EQ5/EQ4)^(1/5)-1) -> -0.39624823 | ES11: 2019-2024 | ET11: =100*((ET5/ET4)^(1/5)-1) -> -1.9856552 | EU11: =100*((EU5/EU4)^(1/5)-1) -> 0.21062672 | EV11: =100*((EV5/EV4)^(1/5)-1) -> -0.77566782 | EW11: =100*((EW5/EW4)^(1/5)-1) -> -1.0884772 | EX11: =100*((EX5/EX4)^(1/5)-1) -> -0.3104026 | EY11: =100*((EY5/EY4)^(1/5)-1) -> 1.2392248 | EZ11: =100*((EZ5/EZ4)^(1/5)-1) -> 0.99608759 | FA11: =100*((FA5/FA4)^(1/5)-1) -> 1.7485198 | FD11: 44470 | FE11: =DataQ!U202+DataQ!V202+DataQ!W202+DataQ!X202+DataQ!Y202 -> 11143 | FF11: =DataQ!J202+DataQ!Q202+DataQ!H202+DataQ!P202+DataQ!S202+DataQ!K202+DataQ!L202 -> 8560 | FG11: =DataQ!N202+DataQ!I202+DataQ!R202+DataQ!G202+DataQ!T202+DataQ!M202+DataQ!O202 -> 15625 | FH11: =DataQ!F202-'Chart Data'!FE11-'Chart Data'!FF11-'Chart Data'!FG11 -> 0 | FJ11: 44470 | FK11: =FE11-(AVERAGE(FE$20:FE$23)) -> -787.75 | FL11: =FF11-(AVERAGE(FF$20:FF$23)) -> -385.25 | FM11: =FG11-(AVERAGE(FG$20:FG$23)) -> -293.25 | FN11: =SUM(FK11:FM11) -> -1466.25 | FP11: 42217 | FQ11: =100*((AVERAGE(HAVERM!AS433:AS435)/AVERAGE(HAVERM!AS430:AS432))-1) -> 0.61887583 | FR11: =100*((AVERAGE(HAVERM!AT433:AT435)/AVERAGE(HAVERM!AT430:AT432))-1) -> 1.3148126 | FS11: =100*((AVERAGE(HAVERM!AU433:AU435)/AVERAGE(HAVERM!AU430:AU432))-1) -> -3.7137081 | FT11: =100*((AVERAGE(HAVERM!AV433:AV435)/AVERAGE(HAVERM!AV430:AV432))-1) -> 0.26612177 | FU11: =100*((AVERAGE(HAVERM!AW433:AW435)/AVERAGE(HAVERM!AW430:AW432))-1) -> 1.0183871 | FV11: =100*((AVERAGE(HAVERM!AX433:AX435)/AVERAGE(HAVERM!AX430:AX432))-1) -> 0.82981493 | FW11: =100*((AVERAGE(HAVERM!AY433:AY435)/AVERAGE(HAVERM!AY430:AY432))-1) -> 1.3114366 | FX11: =100*((AVERAGE(HAVERM!AZ433:AZ435)/AVERAGE(HAVERM!AZ430:AZ432))-1) -> 0.62974745 | ... GI11: =100*((AVERAGE(HAVERM!BK433:BK435)/AVERAGE(HAVERM!BK430:BK432))-1) -> 1.456907 | GJ11: =100*(((AVERAGE(HAVERM!BL433:BL435)+(AVERAGE(HAVERM!BM433:BM435)))/(AVERAGE(HAVERM!BL430:BL432)+AVERAGE(HAVERM!BM430:BM432))-1)) -> 0.60773993 | GL11: 42217 | GW11: 42217 | GX11: =HAVERM!AT435 -> 181556 | GY11: =HAVERM!AU435+HAVERM!AW435+HAVERM!AX435 -> 308203 | GZ11: =HAVERM!AV435 -> 2382052 | HA11: =HAVERM!AY435 -> 1147500 | HB11: =HAVERM!AZ435+HAVERM!BB435 -> 6262436 | HC11: =HAVERM!BA435+HAVERM!BC435 -> 2304318 | HD11: =HAVERM!BD435 -> 1084526 | HE11: =HAVERM!BE435+HAVERM!BF435+HAVERM!BG435 -> 4756642 | HF11: =HAVERM!BH435+HAVERM!BI435+HAVERM!BJ435+HAVERM!BK435+HAVERM!BL435+HAVERM!BM435 -> 9132772 | HH11: Transport | HI11: ='ASHE Annual pay All SIC'!D76 -> 35868 | HJ11: 0.17328294 | HL11: Transport | HM11: ='ASHE Annual pay All SIC'!D76 -> 35868 | HN11: -0.31916667 | HP11: 2014 | HQ11: 15.434557 | HR11: 2.6648364 | HS11: =HQ11+HR11 -> 18.099394 | HU11: 2014 | HV11: 6035.0367 | HW11: 1041.9726 | HX11: =HV11+HW11 -> 7077.0093 | HZ11: 44105 | IA11: =HAVERQ!E171 -> 5450 | IB11: =HAVERQ!F171 -> 26820 | IC11: =DataQ!Z198-('Chart Data'!IA11+'Chart Data'!IB11) -> -2 | IE11: 44105 | IF11: =IA11-AVERAGE(IA$4:IA$7) -> 134.25 | IG11: =IB11-AVERAGE(IB$4:IB$7) -> -804 | II11: 44105 | IJ11: =100*(IA11/AVERAGE(IA$4:IA$7)) -> 102.52551 | IK11: =100*(IB11/AVERAGE(IB$4:IB$7)) -> 97.089487 | IM11: 44105 | IN11: =SUM(DataQ!U198:Y198) -> 10874 | IO11: =DataQ!F198-'Chart Data'!IN11 -> 23648 | IQ11: 44105 | IR11: =100*(IN11/AVERAGE(IN$4:IN$7)) -> 99.394438 | IS11: =100*(IO11/AVERAGE(IO$4:IO$7)) -> 96.033462
A12: 44197 | B12: =HAVERQ!E172-AVERAGE(HAVERQ!E$164:E$167) -> 214.25 | C12: =HAVERQ!F172-AVERAGE(HAVERQ!F$164:F$167) -> -844 | E12: 37257 | F12: =HAVERQ!P96 -> 1292 | G12: =HAVERQ!O96 -> 1471 | H12: =HAVERQ!N96 -> 1204 | I12: =HAVERQ!M96 -> 236 | J12: =HAVERQ!L96 -> 214 | K12: =HAVERQ!E96-F12-G12-H12-I12-J12 -> 782 | M12: 37257 | N12: =100*(F12/SUM($F12:$K12)) -> 24.850933 | O12: =100*(G12/SUM($F12:$K12)) -> 28.293903 | P12: =100*(H12/SUM($F12:$K12)) -> 23.1583 | Q12: =100*(I12/SUM($F12:$K12)) -> 4.5393345 | R12: =100*(J12/SUM($F12:$K12)) -> 4.1161762 | S12: =100*(K12/SUM($F12:$K12)) -> 15.041354 | U12: 37257 | V12: =F12-AVERAGE(F$4:F$7) -> 82.75 | W12: =G12-AVERAGE(G$4:G$7) -> 31.25 | X12: =H12-AVERAGE(H$4:H$7) -> 25 | Y12: =I12-AVERAGE(I$4:I$7) -> 10.25 | Z12: =J12-AVERAGE(J$4:J$7) -> -2.25 | AA12: =K12-AVERAGE(K$4:K$7) -> -5.75 | AB12: =SUM(V12:AA12) -> 141.25 | AD12: 44197 | AE12: =HAVERQ!T172-AVERAGE(HAVERQ!T$164:T$167) -> -23.25 | AF12: =HAVERQ!U172-AVERAGE(HAVERQ!U$164:U$167) -> -8.25 | AG12: =HAVERQ!V172-AVERAGE(HAVERQ!V$164:V$167) -> -153.75 | AH12: =HAVERQ!W172-AVERAGE(HAVERQ!W$164:W$167) -> 3.25 | AI12: =HAVERQ!X172-AVERAGE(HAVERQ!X$164:X$167) -> -4.5 | AJ12: =HAVERQ!Y172-AVERAGE(HAVERQ!Y$164:Y$167) -> -162.25 | AK12: =HAVERQ!Z172-AVERAGE(HAVERQ!Z$164:Z$167) -> -196.5 | AL12: =HAVERQ!AA172-AVERAGE(HAVERQ!AA$164:AA$167) -> 24 | ... AV12: =HAVERQ!AK172-AVERAGE(HAVERQ!AK$164:AK$167) -> -142.75 | AW12: =AY12-AVERAGE(AY$4:AY$7) -> -60.5 | AY12: =HAVERQ!AL172+HAVERQ!AM172 -> 957 | BA12: 44197 | BB12: =BK12-AVERAGE(BK$4:BK$7) -> -23.25 | BC12: =BL12-AVERAGE(BL$4:BL$7) -> -9.5 | BD12: =BM12-AVERAGE(BM$4:BM$7) -> -153.75 | BE12: =BN12-AVERAGE(BN$4:BN$7) -> -162.25 | BF12: =BO12-AVERAGE(BO$4:BO$7) -> -460.5 | BG12: =BP12-AVERAGE(BP$4:BP$7) -> 35.75 | BH12: =BQ12-AVERAGE(BQ$4:BQ$7) -> -80.5 | BI12: =BR12-AVERAGE(BR$4:BR$7) -> 23.75 | BK12: =HAVERQ!T172 -> 375 | BL12: =HAVERQ!U172+HAVERQ!W172+HAVERQ!X172 -> 416 | BM12: =HAVERQ!V172 -> 2537 | BN12: =HAVERQ!Y172 -> 2171 | BO12: =HAVERQ!Z172+HAVERQ!AB172 -> 7044 | BP12: =HAVERQ!AA172+HAVERQ!AC172 -> 3342 | BQ12: =HAVERQ!AD172+HAVERQ!AE172+HAVERQ!AF172+HAVERQ!AG172 -> 7886 | BR12: =HAVERQ!AH172+HAVERQ!AI172+HAVERQ!AJ172+HAVERQ!AK172+HAVERQ!AL172+HAVERQ!AM172 -> 10964 | BS12: =HAVERQ!S172-SUM('Chart Data'!BK12:BR12) -> -1 | BU12: 35065 | BV12: =HAVERQ!T72 -> 468 | BW12: =HAVERQ!U72+HAVERQ!W72+HAVERQ!X72 -> 330 | BX12: =HAVERQ!V72 -> 4263 | BY12: =HAVERQ!Y72 -> 1815 | BZ12: =HAVERQ!Z72+HAVERQ!AB72 -> 6328 | CA12: =HAVERQ!AA72+HAVERQ!AC72 -> 2076 | CB12: =HAVERQ!AD72+HAVERQ!AE72+HAVERQ!AF72+HAVERQ!AG72 -> 4757 | CC12: =HAVERQ!AH72+HAVERQ!AI72+HAVERQ!AJ72+HAVERQ!AK72+HAVERQ!AL72+HAVERQ!AM72 -> 8070 | CD12: =HAVERQ!S72-SUM('Chart Data'!BV12:CC12) -> -2 | DB12: 36892 | DC12: =HAVERQ!BI92/HAVERQ!T92 -> 9.2605042 | DD12: =HAVERQ!BJ92/HAVERQ!U92 -> 512.86842 | DE12: =HAVERQ!BK92/HAVERQ!V92 -> 10.618201 | DF12: =HAVERQ!BL92/HAVERQ!W92 -> 93.17 | DG12: =HAVERQ!BM92/HAVERQ!X92 -> 43.905325 | DH12: =HAVERQ!BN92/HAVERQ!Y92 -> 17.231802 | DI12: =HAVERQ!BO92/HAVERQ!Z92 -> 10.136473 | DJ12: =HAVERQ!BP92/HAVERQ!AA92 -> 12.904286 | ... DT12: =HAVERQ!BZ92/HAVERQ!AK92 -> 9.04 | DU12: =(HAVERQ!CA92+HAVERQ!CB92)/HAVERQ!AL92 -> 10.657107 | DW12: 2024-2029 | DX12: =100*((DX6/DX5)^(1/5)-1) -> 1.0307883 | DY12: =100*((DY6/DY5)^(1/5)-1) -> 0.13089905 | DZ12: =100*((DZ6/DZ5)^(1/5)-1) -> -2.2205168 | EA12: =100*((EA6/EA5)^(1/5)-1) -> -1.2000326 | EB12: =100*((EB6/EB5)^(1/5)-1) -> -0.12292801 | EC12: =100*((EC6/EC5)^(1/5)-1) -> 0.50199761 | ED12: =100*((ED6/ED5)^(1/5)-1) -> 1.7894987 | EE12: =100*((EE6/EE5)^(1/5)-1) -> 0.93205004 | ... EQ12: =100*((EQ6/EQ5)^(1/5)-1) -> 1.4520134 | ES12: 2025-2029 | ET12: =100*((ET6/ET5)^(1/5)-1) -> 0.13089905 | EU12: =100*((EU6/EU5)^(1/5)-1) -> 0.01303079 | EV12: =100*((EV6/EV5)^(1/5)-1) -> -1.2000326 | EW12: =100*((EW6/EW5)^(1/5)-1) -> 1.7894987 | EX12: =100*((EX6/EX5)^(1/5)-1) -> 0.86971556 | EY12: =100*((EY6/EY5)^(1/5)-1) -> 1.5669591 | EZ12: =100*((EZ6/EZ5)^(1/5)-1) -> 1.3005737 | FA12: =100*((FA6/FA5)^(1/5)-1) -> 1.1587765 | FD12: 44562 | FE12: =DataQ!U203+DataQ!V203+DataQ!W203+DataQ!X203+DataQ!Y203 -> 11238 | FF12: =DataQ!J203+DataQ!Q203+DataQ!H203+DataQ!P203+DataQ!S203+DataQ!K203+DataQ!L203 -> 8638 | FG12: =DataQ!N203+DataQ!I203+DataQ!R203+DataQ!G203+DataQ!T203+DataQ!M203+DataQ!O203 -> 15835 | FH12: =DataQ!F203-'Chart Data'!FE12-'Chart Data'!FF12-'Chart Data'!FG12 -> 1 | FJ12: 44562 | FK12: =FE12-(AVERAGE(FE$20:FE$23)) -> -692.75 | FL12: =FF12-(AVERAGE(FF$20:FF$23)) -> -307.25 | FM12: =FG12-(AVERAGE(FG$20:FG$23)) -> -83.25 | FN12: =SUM(FK12:FM12) -> -1083.25 | FP12: 42248 | FQ12: =100*((AVERAGE(HAVERM!AS434:AS436)/AVERAGE(HAVERM!AS431:AS433))-1) -> 0.5981332 | FR12: =100*((AVERAGE(HAVERM!AT434:AT436)/AVERAGE(HAVERM!AT431:AT433))-1) -> 0.83475853 | FS12: =100*((AVERAGE(HAVERM!AU434:AU436)/AVERAGE(HAVERM!AU431:AU433))-1) -> -3.3512597 | FT12: =100*((AVERAGE(HAVERM!AV434:AV436)/AVERAGE(HAVERM!AV431:AV433))-1) -> 0.22873254 | FU12: =100*((AVERAGE(HAVERM!AW434:AW436)/AVERAGE(HAVERM!AW431:AW433))-1) -> 1.6219217 | FV12: =100*((AVERAGE(HAVERM!AX434:AX436)/AVERAGE(HAVERM!AX431:AX433))-1) -> 0.80234115 | FW12: =100*((AVERAGE(HAVERM!AY434:AY436)/AVERAGE(HAVERM!AY431:AY433))-1) -> 1.0994642 | FX12: =100*((AVERAGE(HAVERM!AZ434:AZ436)/AVERAGE(HAVERM!AZ431:AZ433))-1) -> 0.63866256 | ... GI12: =100*((AVERAGE(HAVERM!BK434:BK436)/AVERAGE(HAVERM!BK431:BK433))-1) -> 1.4946817 | GJ12: =100*(((AVERAGE(HAVERM!BL434:BL436)+(AVERAGE(HAVERM!BM434:BM436)))/(AVERAGE(HAVERM!BL431:BL433)+AVERAGE(HAVERM!BM431:BM433))-1)) -> 1.0222636 | GL12: 42248 | GW12: 42248 | GX12: =HAVERM!AT436 -> 181540 | GY12: =HAVERM!AU436+HAVERM!AW436+HAVERM!AX436 -> 308292 | GZ12: =HAVERM!AV436 -> 2385377 | HA12: =HAVERM!AY436 -> 1151273 | HB12: =HAVERM!AZ436+HAVERM!BB436 -> 6278677 | HC12: =HAVERM!BA436+HAVERM!BC436 -> 2310447 | HD12: =HAVERM!BD436 -> 1084442 | HE12: =HAVERM!BE436+HAVERM!BF436+HAVERM!BG436 -> 4769925 | HF12: =HAVERM!BH436+HAVERM!BI436+HAVERM!BJ436+HAVERM!BK436+HAVERM!BL436+HAVERM!BM436 -> 9144139 | HH12: Accommodation & food | HI12: ='ASHE Annual pay All SIC'!D82 -> 16800 | HJ12: -2.11741 | HL12: Accommodation & food | HM12: ='ASHE Annual pay All SIC'!D82 -> 16800 | HN12: -0.91166667 | HP12: 2015 | HQ12: 14.908865 | HR12: 2.4902157 | HS12: =HQ12+HR12 -> 17.39908 | HU12: 2015 | HV12: 5919.976 | HW12: 988.80881 | HX12: =HV12+HW12 -> 6908.7848 | HZ12: 44197 | IA12: =HAVERQ!E172 -> 5530 | IB12: =HAVERQ!F172 -> 26780 | IC12: =DataQ!Z199-('Chart Data'!IA12+'Chart Data'!IB12) -> 4 | IE12: 44197 | IF12: =IA12-AVERAGE(IA$4:IA$7) -> 214.25 | IG12: =IB12-AVERAGE(IB$4:IB$7) -> -844 | II12: 44197 | IJ12: =100*(IA12/AVERAGE(IA$4:IA$7)) -> 104.03048 | IK12: =100*(IB12/AVERAGE(IB$4:IB$7)) -> 96.944686 | IM12: 44197 | IN12: =SUM(DataQ!U199:Y199) -> 10964 | IO12: =DataQ!F199-'Chart Data'!IN12 -> 23770 | IQ12: 44197 | IR12: =100*(IN12/AVERAGE(IN$4:IN$7)) -> 100.21709 | IS12: =100*(IO12/AVERAGE(IO$4:IO$7)) -> 96.528899
A13: 44287 | B13: =HAVERQ!E173-AVERAGE(HAVERQ!E$164:E$167) -> 225.25 | C13: =HAVERQ!F173-AVERAGE(HAVERQ!F$164:F$167) -> -644 | E13: 37347 | F13: =HAVERQ!P97 -> 1309 | G13: =HAVERQ!O97 -> 1473 | H13: =HAVERQ!N97 -> 1212 | I13: =HAVERQ!M97 -> 238 | J13: =HAVERQ!L97 -> 214 | K13: =HAVERQ!E97-F13-G13-H13-I13-J13 -> 780 | M13: 37347 | N13: =100*(F13/SUM($F13:$K13)) -> 25.047838 | O13: =100*(G13/SUM($F13:$K13)) -> 28.185993 | P13: =100*(H13/SUM($F13:$K13)) -> 23.191734 | Q13: =100*(I13/SUM($F13:$K13)) -> 4.5541523 | R13: =100*(J13/SUM($F13:$K13)) -> 4.0949101 | S13: =100*(K13/SUM($F13:$K13)) -> 14.925373 | U13: 37347 | V13: =F13-AVERAGE(F$4:F$7) -> 99.75 | W13: =G13-AVERAGE(G$4:G$7) -> 33.25 | X13: =H13-AVERAGE(H$4:H$7) -> 33 | Y13: =I13-AVERAGE(I$4:I$7) -> 12.25 | Z13: =J13-AVERAGE(J$4:J$7) -> -2.25 | AA13: =K13-AVERAGE(K$4:K$7) -> -7.75 | AB13: =SUM(V13:AA13) -> 168.25 | AD13: 44287 | AE13: =HAVERQ!T173-AVERAGE(HAVERQ!T$164:T$167) -> -24.25 | AF13: =HAVERQ!U173-AVERAGE(HAVERQ!U$164:U$167) -> -7.25 | AG13: =HAVERQ!V173-AVERAGE(HAVERQ!V$164:V$167) -> -146.75 | AH13: =HAVERQ!W173-AVERAGE(HAVERQ!W$164:W$167) -> 5.25 | AI13: =HAVERQ!X173-AVERAGE(HAVERQ!X$164:X$167) -> 7.5 | AJ13: =HAVERQ!Y173-AVERAGE(HAVERQ!Y$164:Y$167) -> -92.25 | AK13: =HAVERQ!Z173-AVERAGE(HAVERQ!Z$164:Z$167) -> -234.5 | AL13: =HAVERQ!AA173-AVERAGE(HAVERQ!AA$164:AA$167) -> 10 | ... AV13: =HAVERQ!AK173-AVERAGE(HAVERQ!AK$164:AK$167) -> -77.75 | AW13: =AY13-AVERAGE(AY$4:AY$7) -> -36.5 | AY13: =HAVERQ!AL173+HAVERQ!AM173 -> 981 | BA13: 44287 | BB13: =BK13-AVERAGE(BK$4:BK$7) -> -24.25 | BC13: =BL13-AVERAGE(BL$4:BL$7) -> 5.5 | BD13: =BM13-AVERAGE(BM$4:BM$7) -> -146.75 | BE13: =BN13-AVERAGE(BN$4:BN$7) -> -92.25 | BF13: =BO13-AVERAGE(BO$4:BO$7) -> -363.5 | BG13: =BP13-AVERAGE(BP$4:BP$7) -> -0.25 | BH13: =BQ13-AVERAGE(BQ$4:BQ$7) -> -9.5 | BI13: =BR13-AVERAGE(BR$4:BR$7) -> 137.75 | BK13: =HAVERQ!T173 -> 374 | BL13: =HAVERQ!U173+HAVERQ!W173+HAVERQ!X173 -> 431 | BM13: =HAVERQ!V173 -> 2544 | BN13: =HAVERQ!Y173 -> 2241 | BO13: =HAVERQ!Z173+HAVERQ!AB173 -> 7141 | BP13: =HAVERQ!AA173+HAVERQ!AC173 -> 3306 | BQ13: =HAVERQ!AD173+HAVERQ!AE173+HAVERQ!AF173+HAVERQ!AG173 -> 7957 | BR13: =HAVERQ!AH173+HAVERQ!AI173+HAVERQ!AJ173+HAVERQ!AK173+HAVERQ!AL173+HAVERQ!AM173 -> 11078 | BS13: =HAVERQ!S173-SUM('Chart Data'!BK13:BR13) -> 0 | BU13: 35156 | BV13: =HAVERQ!T73 -> 473 | BW13: =HAVERQ!U73+HAVERQ!W73+HAVERQ!X73 -> 338 | BX13: =HAVERQ!V73 -> 4248 | BY13: =HAVERQ!Y73 -> 1838 | BZ13: =HAVERQ!Z73+HAVERQ!AB73 -> 6402 | CA13: =HAVERQ!AA73+HAVERQ!AC73 -> 2097 | CB13: =HAVERQ!AD73+HAVERQ!AE73+HAVERQ!AF73+HAVERQ!AG73 -> 4782 | CC13: =HAVERQ!AH73+HAVERQ!AI73+HAVERQ!AJ73+HAVERQ!AK73+HAVERQ!AL73+HAVERQ!AM73 -> 8074 | CD13: =HAVERQ!S73-SUM('Chart Data'!BV13:CC13) -> -4 | DB13: 36982 | DC13: =HAVERQ!BI93/HAVERQ!T93 -> 9.0055249 | DD13: =HAVERQ!BJ93/HAVERQ!U93 -> 528.52 | DE13: =HAVERQ!BK93/HAVERQ!V93 -> 10.806889 | DF13: =HAVERQ!BL93/HAVERQ!W93 -> 97.039216 | DG13: =HAVERQ!BM93/HAVERQ!X93 -> 43.258824 | DH13: =HAVERQ!BN93/HAVERQ!Y93 -> 17.220365 | DI13: =HAVERQ!BO93/HAVERQ!Z93 -> 10.020662 | DJ13: =HAVERQ!BP93/HAVERQ!AA93 -> 12.949008 | ... DT13: =HAVERQ!BZ93/HAVERQ!AK93 -> 9.2413333 | DU13: =(HAVERQ!CA93+HAVERQ!CB93)/HAVERQ!AL93 -> 10.734895 | FD13: 44652 | FE13: =DataQ!U204+DataQ!V204+DataQ!W204+DataQ!X204+DataQ!Y204 -> 11331 | FF13: =DataQ!J204+DataQ!Q204+DataQ!H204+DataQ!P204+DataQ!S204+DataQ!K204+DataQ!L204 -> 8633 | FG13: =DataQ!N204+DataQ!I204+DataQ!R204+DataQ!G204+DataQ!T204+DataQ!M204+DataQ!O204 -> 15957 | FH13: =DataQ!F204-'Chart Data'!FE13-'Chart Data'!FF13-'Chart Data'!FG13 -> -1 | FJ13: 44652 | FK13: =FE13-(AVERAGE(FE$20:FE$23)) -> -599.75 | FL13: =FF13-(AVERAGE(FF$20:FF$23)) -> -312.25 | FM13: =FG13-(AVERAGE(FG$20:FG$23)) -> 38.75 | FN13: =SUM(FK13:FM13) -> -873.25 | FP13: 42278 | FQ13: =100*((AVERAGE(HAVERM!AS435:AS437)/AVERAGE(HAVERM!AS432:AS434))-1) -> 0.56410107 | FR13: =100*((AVERAGE(HAVERM!AT435:AT437)/AVERAGE(HAVERM!AT432:AT434))-1) -> 0.34434158 | FS13: =100*((AVERAGE(HAVERM!AU435:AU437)/AVERAGE(HAVERM!AU432:AU434))-1) -> -3.1876397 | FT13: =100*((AVERAGE(HAVERM!AV435:AV437)/AVERAGE(HAVERM!AV432:AV434))-1) -> 0.23565298 | FU13: =100*((AVERAGE(HAVERM!AW435:AW437)/AVERAGE(HAVERM!AW432:AW434))-1) -> 1.5792001 | FV13: =100*((AVERAGE(HAVERM!AX435:AX437)/AVERAGE(HAVERM!AX432:AX434))-1) -> 0.65936842 | FW13: =100*((AVERAGE(HAVERM!AY435:AY437)/AVERAGE(HAVERM!AY432:AY434))-1) -> 0.96367977 | FX13: =100*((AVERAGE(HAVERM!AZ435:AZ437)/AVERAGE(HAVERM!AZ432:AZ434))-1) -> 0.58194835 | ... GI13: =100*((AVERAGE(HAVERM!BK435:BK437)/AVERAGE(HAVERM!BK432:BK434))-1) -> 1.5218007 | GJ13: =100*(((AVERAGE(HAVERM!BL435:BL437)+(AVERAGE(HAVERM!BM435:BM437)))/(AVERAGE(HAVERM!BL432:BL434)+AVERAGE(HAVERM!BM432:BM434))-1)) -> 1.0571169 | GL13: 42278 | GW13: 42278 | GX13: =HAVERM!AT437 -> 181548 | GY13: =HAVERM!AU437+HAVERM!AW437+HAVERM!AX437 -> 308776 | GZ13: =HAVERM!AV437 -> 2388281 | HA13: =HAVERM!AY437 -> 1154096 | HB13: =HAVERM!AZ437+HAVERM!BB437 -> 6296498 | HC13: =HAVERM!BA437+HAVERM!BC437 -> 2317622 | HD13: =HAVERM!BD437 -> 1086115 | HE13: =HAVERM!BE437+HAVERM!BF437+HAVERM!BG437 -> 4785352 | HF13: =HAVERM!BH437+HAVERM!BI437+HAVERM!BJ437+HAVERM!BK437+HAVERM!BL437+HAVERM!BM437 -> 9154892 | HH13: Communications | HI13: ='ASHE Annual pay All SIC'!D85 -> 46063 | HJ13: -1.2342766 | HL13: Communications | HM13: ='ASHE Annual pay All SIC'!D85 -> 46063 | HN13: -0.86416667 | HP13: 2016 | HQ13: 14.473744 | HR13: 2.440091 | HS13: =HQ13+HR13 -> 16.913835 | HU13: 2016 | HV13: 5815.8845 | HW13: 980.48493 | HX13: =HV13+HW13 -> 6796.3694 | HZ13: 44287 | IA13: =HAVERQ!E173 -> 5541 | IB13: =HAVERQ!F173 -> 26980 | IC13: =DataQ!Z200-('Chart Data'!IA13+'Chart Data'!IB13) -> -71 | IE13: 44287 | IF13: =IA13-AVERAGE(IA$4:IA$7) -> 225.25 | IG13: =IB13-AVERAGE(IB$4:IB$7) -> -644 | II13: 44287 | IJ13: =100*(IA13/AVERAGE(IA$4:IA$7)) -> 104.23741 | IK13: =100*(IB13/AVERAGE(IB$4:IB$7)) -> 97.668694 | IM13: 44287 | IN13: =SUM(DataQ!U200:Y200) -> 11078 | IO13: =DataQ!F200-'Chart Data'!IN13 -> 23994 | IQ13: 44287 | IR13: =100*(IN13/AVERAGE(IN$4:IN$7)) -> 101.25911 | IS13: =100*(IO13/AVERAGE(IO$4:IO$7)) -> 97.438553
A14: 44378 | B14: =HAVERQ!E174-AVERAGE(HAVERQ!E$164:E$167) -> 242.25 | C14: =HAVERQ!F174-AVERAGE(HAVERQ!F$164:F$167) -> -487 | E14: 37438 | F14: =HAVERQ!P98 -> 1325 | G14: =HAVERQ!O98 -> 1500 | H14: =HAVERQ!N98 -> 1215 | I14: =HAVERQ!M98 -> 240 | J14: =HAVERQ!L98 -> 215 | K14: =HAVERQ!E98-F14-G14-H14-I14-J14 -> 767 | M14: 37438 | N14: =100*(F14/SUM($F14:$K14)) -> 25.18054 | O14: =100*(G14/SUM($F14:$K14)) -> 28.506271 | P14: =100*(H14/SUM($F14:$K14)) -> 23.09008 | Q14: =100*(I14/SUM($F14:$K14)) -> 4.5610034 | R14: =100*(J14/SUM($F14:$K14)) -> 4.0858989 | S14: =100*(K14/SUM($F14:$K14)) -> 14.576207 | U14: 37438 | V14: =F14-AVERAGE(F$4:F$7) -> 115.75 | W14: =G14-AVERAGE(G$4:G$7) -> 60.25 | X14: =H14-AVERAGE(H$4:H$7) -> 36 | Y14: =I14-AVERAGE(I$4:I$7) -> 14.25 | Z14: =J14-AVERAGE(J$4:J$7) -> -1.25 | AA14: =K14-AVERAGE(K$4:K$7) -> -20.75 | AB14: =SUM(V14:AA14) -> 204.25 | AD14: 44378 | AE14: =HAVERQ!T174-AVERAGE(HAVERQ!T$164:T$167) -> -31.25 | AF14: =HAVERQ!U174-AVERAGE(HAVERQ!U$164:U$167) -> -9.25 | AG14: =HAVERQ!V174-AVERAGE(HAVERQ!V$164:V$167) -> -153.75 | AH14: =HAVERQ!W174-AVERAGE(HAVERQ!W$164:W$167) -> 4.25 | AI14: =HAVERQ!X174-AVERAGE(HAVERQ!X$164:X$167) -> 12.5 | AJ14: =HAVERQ!Y174-AVERAGE(HAVERQ!Y$164:Y$167) -> -108.25 | AK14: =HAVERQ!Z174-AVERAGE(HAVERQ!Z$164:Z$167) -> -182.5 | AL14: =HAVERQ!AA174-AVERAGE(HAVERQ!AA$164:AA$167) -> 16 | ... AV14: =HAVERQ!AK174-AVERAGE(HAVERQ!AK$164:AK$167) -> -58.75 | AW14: =AY14-AVERAGE(AY$4:AY$7) -> -34.5 | AY14: =HAVERQ!AL174+HAVERQ!AM174 -> 983 | BA14: 44378 | BB14: =BK14-AVERAGE(BK$4:BK$7) -> -31.25 | BC14: =BL14-AVERAGE(BL$4:BL$7) -> 7.5 | BD14: =BM14-AVERAGE(BM$4:BM$7) -> -153.75 | BE14: =BN14-AVERAGE(BN$4:BN$7) -> -108.25 | BF14: =BO14-AVERAGE(BO$4:BO$7) -> -217.5 | BG14: =BP14-AVERAGE(BP$4:BP$7) -> 43.75 | BH14: =BQ14-AVERAGE(BQ$4:BQ$7) -> 3.5 | BI14: =BR14-AVERAGE(BR$4:BR$7) -> 175.75 | BK14: =HAVERQ!T174 -> 367 | BL14: =HAVERQ!U174+HAVERQ!W174+HAVERQ!X174 -> 433 | BM14: =HAVERQ!V174 -> 2537 | BN14: =HAVERQ!Y174 -> 2225 | BO14: =HAVERQ!Z174+HAVERQ!AB174 -> 7287 | BP14: =HAVERQ!AA174+HAVERQ!AC174 -> 3350 | BQ14: =HAVERQ!AD174+HAVERQ!AE174+HAVERQ!AF174+HAVERQ!AG174 -> 7970 | BR14: =HAVERQ!AH174+HAVERQ!AI174+HAVERQ!AJ174+HAVERQ!AK174+HAVERQ!AL174+HAVERQ!AM174 -> 11116 | BS14: =HAVERQ!S174-SUM('Chart Data'!BK14:BR14) -> 1 | BU14: 35247 | BV14: =HAVERQ!T74 -> 484 | BW14: =HAVERQ!U74+HAVERQ!W74+HAVERQ!X74 -> 357 | BX14: =HAVERQ!V74 -> 4277 | BY14: =HAVERQ!Y74 -> 1812 | BZ14: =HAVERQ!Z74+HAVERQ!AB74 -> 6431 | CA14: =HAVERQ!AA74+HAVERQ!AC74 -> 2120 | CB14: =HAVERQ!AD74+HAVERQ!AE74+HAVERQ!AF74+HAVERQ!AG74 -> 4795 | CC14: =HAVERQ!AH74+HAVERQ!AI74+HAVERQ!AJ74+HAVERQ!AK74+HAVERQ!AL74+HAVERQ!AM74 -> 8115 | CD14: =HAVERQ!S74-SUM('Chart Data'!BV14:CC14) -> 3 | DB14: 37073 | DC14: =HAVERQ!BI94/HAVERQ!T94 -> 9.027027 | DD14: =HAVERQ!BJ94/HAVERQ!U94 -> 527.93333 | DE14: =HAVERQ!BK94/HAVERQ!V94 -> 11.049007 | DF14: =HAVERQ!BL94/HAVERQ!W94 -> 100.63725 | DG14: =HAVERQ!BM94/HAVERQ!X94 -> 41.390805 | DH14: =HAVERQ!BN94/HAVERQ!Y94 -> 16.823 | DI14: =HAVERQ!BO94/HAVERQ!Z94 -> 10.071515 | DJ14: =HAVERQ!BP94/HAVERQ!AA94 -> 13.104775 | ... DT14: =HAVERQ!BZ94/HAVERQ!AK94 -> 8.7956016 | DU14: =(HAVERQ!CA94+HAVERQ!CB94)/HAVERQ!AL94 -> 10.30355 | FD14: 44743 | FE14: =DataQ!U205+DataQ!V205+DataQ!W205+DataQ!X205+DataQ!Y205 -> 11316 | FF14: =DataQ!J205+DataQ!Q205+DataQ!H205+DataQ!P205+DataQ!S205+DataQ!K205+DataQ!L205 -> 8603 | FG14: =DataQ!N205+DataQ!I205+DataQ!R205+DataQ!G205+DataQ!T205+DataQ!M205+DataQ!O205 -> 16065 | FH14: =DataQ!F205-'Chart Data'!FE14-'Chart Data'!FF14-'Chart Data'!FG14 -> 1 | FJ14: 44743 | FK14: =FE14-(AVERAGE(FE$20:FE$23)) -> -614.75 | FL14: =FF14-(AVERAGE(FF$20:FF$23)) -> -342.25 | FM14: =FG14-(AVERAGE(FG$20:FG$23)) -> 146.75 | FN14: =SUM(FK14:FM14) -> -810.25 | FP14: 42309 | FQ14: =100*((AVERAGE(HAVERM!AS436:AS438)/AVERAGE(HAVERM!AS433:AS435))-1) -> 0.56126819 | FR14: =100*((AVERAGE(HAVERM!AT436:AT438)/AVERAGE(HAVERM!AT433:AT435))-1) -> 0.031222393 | FS14: =100*((AVERAGE(HAVERM!AU436:AU438)/AVERAGE(HAVERM!AU433:AU435))-1) -> -2.9597019 | FT14: =100*((AVERAGE(HAVERM!AV436:AV438)/AVERAGE(HAVERM!AV433:AV435))-1) -> 0.27344901 | FU14: =100*((AVERAGE(HAVERM!AW436:AW438)/AVERAGE(HAVERM!AW433:AW435))-1) -> 1.6857858 | FV14: =100*((AVERAGE(HAVERM!AX436:AX438)/AVERAGE(HAVERM!AX433:AX435))-1) -> 0.49429514 | FW14: =100*((AVERAGE(HAVERM!AY436:AY438)/AVERAGE(HAVERM!AY433:AY435))-1) -> 0.89993195 | FX14: =100*((AVERAGE(HAVERM!AZ436:AZ438)/AVERAGE(HAVERM!AZ433:AZ435))-1) -> 0.57686991 | ... GI14: =100*((AVERAGE(HAVERM!BK436:BK438)/AVERAGE(HAVERM!BK433:BK435))-1) -> 1.4138546 | GJ14: =100*(((AVERAGE(HAVERM!BL436:BL438)+(AVERAGE(HAVERM!BM436:BM438)))/(AVERAGE(HAVERM!BL433:BL435)+AVERAGE(HAVERM!BM433:BM435))-1)) -> 1.0792386 | GL14: 42309 | GW14: 42309 | GX14: =HAVERM!AT438 -> 181563 | GY14: =HAVERM!AU438+HAVERM!AW438+HAVERM!AX438 -> 309205 | GZ14: =HAVERM!AV438 -> 2390905 | HA14: =HAVERM!AY438 -> 1158227 | HB14: =HAVERM!AZ438+HAVERM!BB438 -> 6313203 | HC14: =HAVERM!BA438+HAVERM!BC438 -> 2323113 | HD14: =HAVERM!BD438 -> 1086729 | HE14: =HAVERM!BE438+HAVERM!BF438+HAVERM!BG438 -> 4787004 | HF14: =HAVERM!BH438+HAVERM!BI438+HAVERM!BJ438+HAVERM!BK438+HAVERM!BL438+HAVERM!BM438 -> 9168936 | HH14: Financial services | HI14: ='ASHE Annual pay All SIC'!D92 -> 47248 | HJ14: 0.20692457 | HL14: Financial services | HM14: ='ASHE Annual pay All SIC'!D92 -> 47248 | HN14: -0.21583333 | HP14: 2017 | HQ14: 14.042248 | HR14: 2.5056882 | HS14: =HQ14+HR14 -> 16.547936 | HU14: 2017 | HV14: 5759.7455 | HW14: 1027.7646 | HX14: =HV14+HW14 -> 6787.5101 | HZ14: 44378 | IA14: =HAVERQ!E174 -> 5558 | IB14: =HAVERQ!F174 -> 27137 | IC14: =DataQ!Z201-('Chart Data'!IA14+'Chart Data'!IB14) -> 29 | IE14: 44378 | IF14: =IA14-AVERAGE(IA$4:IA$7) -> 242.25 | IG14: =IB14-AVERAGE(IB$4:IB$7) -> -487 | II14: 44378 | IJ14: =100*(IA14/AVERAGE(IA$4:IA$7)) -> 104.55721 | IK14: =100*(IB14/AVERAGE(IB$4:IB$7)) -> 98.23704 | IM14: 44378 | IN14: =SUM(DataQ!U201:Y201) -> 11116 | IO14: =DataQ!F201-'Chart Data'!IN14 -> 24170 | IQ14: 44378 | IR14: =100*(IN14/AVERAGE(IN$4:IN$7)) -> 101.60645 | IS14: =100*(IO14/AVERAGE(IO$4:IO$7)) -> 98.153281
A15: 44470 | B15: =HAVERQ!E175-AVERAGE(HAVERQ!E$164:E$167) -> 261.25 | C15: =HAVERQ!F175-AVERAGE(HAVERQ!F$164:F$167) -> -466 | E15: 37530 | F15: =HAVERQ!P99 -> 1341 | G15: =HAVERQ!O99 -> 1510 | H15: =HAVERQ!N99 -> 1236 | I15: =HAVERQ!M99 -> 242 | J15: =HAVERQ!L99 -> 215 | K15: =HAVERQ!E99-F15-G15-H15-I15-J15 -> 781 | M15: 37530 | N15: =100*(F15/SUM($F15:$K15)) -> 25.183099 | O15: =100*(G15/SUM($F15:$K15)) -> 28.356808 | P15: =100*(H15/SUM($F15:$K15)) -> 23.211268 | Q15: =100*(I15/SUM($F15:$K15)) -> 4.5446009 | R15: =100*(J15/SUM($F15:$K15)) -> 4.0375587 | S15: =100*(K15/SUM($F15:$K15)) -> 14.666667 | U15: 37530 | V15: =F15-AVERAGE(F$4:F$7) -> 131.75 | W15: =G15-AVERAGE(G$4:G$7) -> 70.25 | X15: =H15-AVERAGE(H$4:H$7) -> 57 | Y15: =I15-AVERAGE(I$4:I$7) -> 16.25 | Z15: =J15-AVERAGE(J$4:J$7) -> -1.25 | AA15: =K15-AVERAGE(K$4:K$7) -> -6.75 | AB15: =SUM(V15:AA15) -> 267.25 | AD15: 44470 | AE15: =HAVERQ!T175-AVERAGE(HAVERQ!T$164:T$167) -> -50.25 | AF15: =HAVERQ!U175-AVERAGE(HAVERQ!U$164:U$167) -> -10.25 | AG15: =HAVERQ!V175-AVERAGE(HAVERQ!V$164:V$167) -> -137.75 | AH15: =HAVERQ!W175-AVERAGE(HAVERQ!W$164:W$167) -> -1.75 | AI15: =HAVERQ!X175-AVERAGE(HAVERQ!X$164:X$167) -> 8.5 | AJ15: =HAVERQ!Y175-AVERAGE(HAVERQ!Y$164:Y$167) -> -110.25 | AK15: =HAVERQ!Z175-AVERAGE(HAVERQ!Z$164:Z$167) -> -245.5 | AL15: =HAVERQ!AA175-AVERAGE(HAVERQ!AA$164:AA$167) -> 23 | ... AV15: =HAVERQ!AK175-AVERAGE(HAVERQ!AK$164:AK$167) -> -49.75 | AW15: =AY15-AVERAGE(AY$4:AY$7) -> -45.5 | AY15: =HAVERQ!AL175+HAVERQ!AM175 -> 972 | BA15: 44470 | BB15: =BK15-AVERAGE(BK$4:BK$7) -> -50.25 | BC15: =BL15-AVERAGE(BL$4:BL$7) -> -3.5 | BD15: =BM15-AVERAGE(BM$4:BM$7) -> -137.75 | BE15: =BN15-AVERAGE(BN$4:BN$7) -> -110.25 | BF15: =BO15-AVERAGE(BO$4:BO$7) -> -249.5 | BG15: =BP15-AVERAGE(BP$4:BP$7) -> 81.75 | BH15: =BQ15-AVERAGE(BQ$4:BQ$7) -> 29.5 | BI15: =BR15-AVERAGE(BR$4:BR$7) -> 202.75 | BK15: =HAVERQ!T175 -> 348 | BL15: =HAVERQ!U175+HAVERQ!W175+HAVERQ!X175 -> 422 | BM15: =HAVERQ!V175 -> 2553 | BN15: =HAVERQ!Y175 -> 2223 | BO15: =HAVERQ!Z175+HAVERQ!AB175 -> 7255 | BP15: =HAVERQ!AA175+HAVERQ!AC175 -> 3388 | BQ15: =HAVERQ!AD175+HAVERQ!AE175+HAVERQ!AF175+HAVERQ!AG175 -> 7996 | BR15: =HAVERQ!AH175+HAVERQ!AI175+HAVERQ!AJ175+HAVERQ!AK175+HAVERQ!AL175+HAVERQ!AM175 -> 11143 | BS15: =HAVERQ!S175-SUM('Chart Data'!BK15:BR15) -> 0 | BU15: 35339 | BV15: =HAVERQ!T75 -> 483 | BW15: =HAVERQ!U75+HAVERQ!W75+HAVERQ!X75 -> 349 | BX15: =HAVERQ!V75 -> 4272 | BY15: =HAVERQ!Y75 -> 1814 | BZ15: =HAVERQ!Z75+HAVERQ!AB75 -> 6447 | CA15: =HAVERQ!AA75+HAVERQ!AC75 -> 2142 | CB15: =HAVERQ!AD75+HAVERQ!AE75+HAVERQ!AF75+HAVERQ!AG75 -> 4873 | CC15: =HAVERQ!AH75+HAVERQ!AI75+HAVERQ!AJ75+HAVERQ!AK75+HAVERQ!AL75+HAVERQ!AM75 -> 8112 | CD15: =HAVERQ!S75-SUM('Chart Data'!BV15:CC15) -> 1 | DB15: 37165 | DC15: =HAVERQ!BI95/HAVERQ!T95 -> 9.4502762 | DD15: =HAVERQ!BJ95/HAVERQ!U95 -> 525.67568 | DE15: =HAVERQ!BK95/HAVERQ!V95 -> 11.144928 | DF15: =HAVERQ!BL95/HAVERQ!W95 -> 99.323529 | DG15: =HAVERQ!BM95/HAVERQ!X95 -> 40.207865 | DH15: =HAVERQ!BN95/HAVERQ!Y95 -> 16.724666 | DI15: =HAVERQ!BO95/HAVERQ!Z95 -> 10.233347 | DJ15: =HAVERQ!BP95/HAVERQ!AA95 -> 12.430693 | ... DT15: =HAVERQ!BZ95/HAVERQ!AK95 -> 8.9445876 | DU15: =(HAVERQ!CA95+HAVERQ!CB95)/HAVERQ!AL95 -> 10.619804 | DW15: 2024 | DX15: =DataA!B58 -> 36792.75 | DY15: =DataA!C58 -> 360.25 | DZ15: =DataA!D58 -> 48.25 | EA15: =DataA!E58 -> 2588 | EB15: =DataA!F58 -> 135.75 | EC15: =DataA!G58 -> 246 | ED15: =DataA!H58 -> 2209 | EE15: =DataA!I58 -> 4722.5 | ... EQ15: =DataA!U58 -> 997.5 | FD15: 44835 | FE15: =DataQ!U206+DataQ!V206+DataQ!W206+DataQ!X206+DataQ!Y206 -> 11347 | FF15: =DataQ!J206+DataQ!Q206+DataQ!H206+DataQ!P206+DataQ!S206+DataQ!K206+DataQ!L206 -> 8736 | FG15: =DataQ!N206+DataQ!I206+DataQ!R206+DataQ!G206+DataQ!T206+DataQ!M206+DataQ!O206 -> 16098 | FH15: =DataQ!F206-'Chart Data'!FE15-'Chart Data'!FF15-'Chart Data'!FG15 -> 0 | FJ15: 44835 | FK15: =FE15-(AVERAGE(FE$20:FE$23)) -> -583.75 | FL15: =FF15-(AVERAGE(FF$20:FF$23)) -> -209.25 | FM15: =FG15-(AVERAGE(FG$20:FG$23)) -> 179.75 | FN15: =SUM(FK15:FM15) -> -613.25 | FP15: 42339 | FQ15: =100*((AVERAGE(HAVERM!AS437:AS439)/AVERAGE(HAVERM!AS434:AS436))-1) -> 0.46409554 | FR15: =100*((AVERAGE(HAVERM!AT437:AT439)/AVERAGE(HAVERM!AT434:AT436))-1) -> -0.086823083 | FS15: =100*((AVERAGE(HAVERM!AU437:AU439)/AVERAGE(HAVERM!AU434:AU436))-1) -> -3.0876331 | FT15: =100*((AVERAGE(HAVERM!AV437:AV439)/AVERAGE(HAVERM!AV434:AV436))-1) -> -0.0065742541 | FU15: =100*((AVERAGE(HAVERM!AW437:AW439)/AVERAGE(HAVERM!AW434:AW436))-1) -> 1.9280844 | FV15: =100*((AVERAGE(HAVERM!AX437:AX439)/AVERAGE(HAVERM!AX434:AX436))-1) -> 0.44741042 | FW15: =100*((AVERAGE(HAVERM!AY437:AY439)/AVERAGE(HAVERM!AY434:AY436))-1) -> 0.31747166 | FX15: =100*((AVERAGE(HAVERM!AZ437:AZ439)/AVERAGE(HAVERM!AZ434:AZ436))-1) -> 0.5565621 | ... GI15: =100*((AVERAGE(HAVERM!BK437:BK439)/AVERAGE(HAVERM!BK434:BK436))-1) -> 1.2250507 | GJ15: =100*(((AVERAGE(HAVERM!BL437:BL439)+(AVERAGE(HAVERM!BM437:BM439)))/(AVERAGE(HAVERM!BL434:BL436)+AVERAGE(HAVERM!BM434:BM436))-1)) -> 0.87925802 | GL15: 42339 | GW15: 42339 | GX15: =HAVERM!AT439 -> 181202 | GY15: =HAVERM!AU439+HAVERM!AW439+HAVERM!AX439 -> 309122 | GZ15: =HAVERM!AV439 -> 2369444 | HA15: =HAVERM!AY439 -> 1141434 | HB15: =HAVERM!AZ439+HAVERM!BB439 -> 6317991 | HC15: =HAVERM!BA439+HAVERM!BC439 -> 2325634 | HD15: =HAVERM!BD439 -> 1086782 | HE15: =HAVERM!BE439+HAVERM!BF439+HAVERM!BG439 -> 4787052 | HF15: =HAVERM!BH439+HAVERM!BI439+HAVERM!BJ439+HAVERM!BK439+HAVERM!BL439+HAVERM!BM439 -> 9167668 | HH15: Real estate | HI15: ='ASHE Annual pay All SIC'!D96 -> 30891 | HJ15: -0.37967138 | HL15: Real estate | HM15: ='ASHE Annual pay All SIC'!D96 -> 30891 | HN15: 0.0033333333 | HP15: 2018 | HQ15: 13.875543 | HR15: 2.5853081 | HS15: =HQ15+HR15 -> 16.460851 | HU15: 2018 | HV15: 5744.5676 | HW15: 1070.3349 | HX15: =HV15+HW15 -> 6814.9025 | HZ15: 44470 | IA15: =HAVERQ!E175 -> 5577 | IB15: =HAVERQ!F175 -> 27158 | IC15: =DataQ!Z202-('Chart Data'!IA15+'Chart Data'!IB15) -> -3 | IE15: 44470 | IF15: =IA15-AVERAGE(IA$4:IA$7) -> 261.25 | IG15: =IB15-AVERAGE(IB$4:IB$7) -> -466 | II15: 44470 | IJ15: =100*(IA15/AVERAGE(IA$4:IA$7)) -> 104.91464 | IK15: =100*(IB15/AVERAGE(IB$4:IB$7)) -> 98.313061 | IM15: 44470 | IN15: =SUM(DataQ!U202:Y202) -> 11143 | IO15: =DataQ!F202-'Chart Data'!IN15 -> 24185 | IQ15: 44470 | IR15: =100*(IN15/AVERAGE(IN$4:IN$7)) -> 101.85325 | IS15: =100*(IO15/AVERAGE(IO$4:IO$7)) -> 98.214195
A16: 44562 | B16: =HAVERQ!E176-AVERAGE(HAVERQ!E$164:E$167) -> 280.25 | C16: =HAVERQ!F176-AVERAGE(HAVERQ!F$164:F$167) -> -347 | E16: 37622 | F16: =HAVERQ!P100 -> 1359 | G16: =HAVERQ!O100 -> 1516 | H16: =HAVERQ!N100 -> 1246 | I16: =HAVERQ!M100 -> 246 | J16: =HAVERQ!L100 -> 221 | K16: =HAVERQ!E100-F16-G16-H16-I16-J16 -> 786 | M16: 37622 | N16: =100*(F16/SUM($F16:$K16)) -> 25.288426 | O16: =100*(G16/SUM($F16:$K16)) -> 28.2099 | P16: =100*(H16/SUM($F16:$K16)) -> 23.185709 | Q16: =100*(I16/SUM($F16:$K16)) -> 4.5775958 | R16: =100*(J16/SUM($F16:$K16)) -> 4.112393 | S16: =100*(K16/SUM($F16:$K16)) -> 14.625977 | U16: 37622 | V16: =F16-AVERAGE(F$4:F$7) -> 149.75 | W16: =G16-AVERAGE(G$4:G$7) -> 76.25 | X16: =H16-AVERAGE(H$4:H$7) -> 67 | Y16: =I16-AVERAGE(I$4:I$7) -> 20.25 | Z16: =J16-AVERAGE(J$4:J$7) -> 4.75 | AA16: =K16-AVERAGE(K$4:K$7) -> -1.75 | AB16: =SUM(V16:AA16) -> 316.25 | AD16: 44562 | AE16: =HAVERQ!T176-AVERAGE(HAVERQ!T$164:T$167) -> -53.25 | AF16: =HAVERQ!U176-AVERAGE(HAVERQ!U$164:U$167) -> -10.25 | AG16: =HAVERQ!V176-AVERAGE(HAVERQ!V$164:V$167) -> -78.75 | AH16: =HAVERQ!W176-AVERAGE(HAVERQ!W$164:W$167) -> -12.75 | AI16: =HAVERQ!X176-AVERAGE(HAVERQ!X$164:X$167) -> 16.5 | AJ16: =HAVERQ!Y176-AVERAGE(HAVERQ!Y$164:Y$167) -> -78.25 | AK16: =HAVERQ!Z176-AVERAGE(HAVERQ!Z$164:Z$167) -> -208.5 | AL16: =HAVERQ!AA176-AVERAGE(HAVERQ!AA$164:AA$167) -> 22 | ... AV16: =HAVERQ!AK176-AVERAGE(HAVERQ!AK$164:AK$167) -> -47.75 | AW16: =AY16-AVERAGE(AY$4:AY$7) -> -47.5 | AY16: =HAVERQ!AL176+HAVERQ!AM176 -> 970 | BA16: 44562 | BB16: =BK16-AVERAGE(BK$4:BK$7) -> -53.25 | BC16: =BL16-AVERAGE(BL$4:BL$7) -> -6.5 | BD16: =BM16-AVERAGE(BM$4:BM$7) -> -78.75 | BE16: =BN16-AVERAGE(BN$4:BN$7) -> -78.25 | BF16: =BO16-AVERAGE(BO$4:BO$7) -> -149.5 | BG16: =BP16-AVERAGE(BP$4:BP$7) -> 93.75 | BH16: =BQ16-AVERAGE(BQ$4:BQ$7) -> 120.5 | BI16: =BR16-AVERAGE(BR$4:BR$7) -> 297.75 | BK16: =HAVERQ!T176 -> 345 | BL16: =HAVERQ!U176+HAVERQ!W176+HAVERQ!X176 -> 419 | BM16: =HAVERQ!V176 -> 2612 | BN16: =HAVERQ!Y176 -> 2255 | BO16: =HAVERQ!Z176+HAVERQ!AB176 -> 7355 | BP16: =HAVERQ!AA176+HAVERQ!AC176 -> 3400 | BQ16: =HAVERQ!AD176+HAVERQ!AE176+HAVERQ!AF176+HAVERQ!AG176 -> 8087 | BR16: =HAVERQ!AH176+HAVERQ!AI176+HAVERQ!AJ176+HAVERQ!AK176+HAVERQ!AL176+HAVERQ!AM176 -> 11238 | BS16: =HAVERQ!S176-SUM('Chart Data'!BK16:BR16) -> 1 | BU16: 35431 | BV16: =HAVERQ!T76 -> 479 | BW16: =HAVERQ!U76+HAVERQ!W76+HAVERQ!X76 -> 352 | BX16: =HAVERQ!V76 -> 4262 | BY16: =HAVERQ!Y76 -> 1793 | BZ16: =HAVERQ!Z76+HAVERQ!AB76 -> 6518 | CA16: =HAVERQ!AA76+HAVERQ!AC76 -> 2169 | CB16: =HAVERQ!AD76+HAVERQ!AE76+HAVERQ!AF76+HAVERQ!AG76 -> 4886 | CC16: =HAVERQ!AH76+HAVERQ!AI76+HAVERQ!AJ76+HAVERQ!AK76+HAVERQ!AL76+HAVERQ!AM76 -> 8046 | CD16: =HAVERQ!S76-SUM('Chart Data'!BV16:CC16) -> 0 | DB16: 37257 | DC16: =HAVERQ!BI96/HAVERQ!T96 -> 10.921409 | DD16: =HAVERQ!BJ96/HAVERQ!U96 -> 515.82432 | DE16: =HAVERQ!BK96/HAVERQ!V96 -> 11.389554 | DF16: =HAVERQ!BL96/HAVERQ!W96 -> 92.529412 | DG16: =HAVERQ!BM96/HAVERQ!X96 -> 42.440476 | DH16: =HAVERQ!BN96/HAVERQ!Y96 -> 16.764353 | DI16: =HAVERQ!BO96/HAVERQ!Z96 -> 10.0872 | DJ16: =HAVERQ!BP96/HAVERQ!AA96 -> 12.283476 | ... DT16: =HAVERQ!BZ96/HAVERQ!AK96 -> 9.2737789 | DU16: =(HAVERQ!CA96+HAVERQ!CB96)/HAVERQ!AL96 -> 10.574939 | DW16: Q4 2026 | DX16: =DataQ!F222 -> 37395.06 | DY16: =DataQ!G222 -> 360.722 | DZ16: =DataQ!H222 -> 46.68387 | EA16: =DataQ!I222 -> 2518.3 | EB16: =DataQ!J222 -> 137.0633 | EC16: =DataQ!K222 -> 248.3022 | ED16: =DataQ!L222 -> 2275.208 | EE16: =DataQ!M222 -> 4726.462 | ... EQ16: =DataQ!Y222 -> 1023.017 | FD16: 44927 | FE16: =DataQ!U207+DataQ!V207+DataQ!W207+DataQ!X207+DataQ!Y207 -> 11479 | FF16: =DataQ!J207+DataQ!Q207+DataQ!H207+DataQ!P207+DataQ!S207+DataQ!K207+DataQ!L207 -> 8902 | FG16: =DataQ!N207+DataQ!I207+DataQ!R207+DataQ!G207+DataQ!T207+DataQ!M207+DataQ!O207 -> 16156 | FH16: =DataQ!F207-'Chart Data'!FE16-'Chart Data'!FF16-'Chart Data'!FG16 -> 0 | FJ16: 44927 | FK16: =FE16-(AVERAGE(FE$20:FE$23)) -> -451.75 | FL16: =FF16-(AVERAGE(FF$20:FF$23)) -> -43.25 | FM16: =FG16-(AVERAGE(FG$20:FG$23)) -> 237.75 | FN16: =SUM(FK16:FM16) -> -257.25 | FP16: 42370 | FQ16: =100*((AVERAGE(HAVERM!AS438:AS440)/AVERAGE(HAVERM!AS435:AS437))-1) -> 0.38754915 | FR16: =100*((AVERAGE(HAVERM!AT438:AT440)/AVERAGE(HAVERM!AT435:AT437))-1) -> -0.11071452 | FS16: =100*((AVERAGE(HAVERM!AU438:AU440)/AVERAGE(HAVERM!AU435:AU437))-1) -> -3.0861596 | FT16: =100*((AVERAGE(HAVERM!AV438:AV440)/AVERAGE(HAVERM!AV435:AV437))-1) -> -0.057520498 | FU16: =100*((AVERAGE(HAVERM!AW438:AW440)/AVERAGE(HAVERM!AW435:AW437))-1) -> 2.166135 | FV16: =100*((AVERAGE(HAVERM!AX438:AX440)/AVERAGE(HAVERM!AX435:AX437))-1) -> 0.54629266 | FW16: =100*((AVERAGE(HAVERM!AY438:AY440)/AVERAGE(HAVERM!AY435:AY437))-1) -> 0.39228248 | FX16: =100*((AVERAGE(HAVERM!AZ438:AZ440)/AVERAGE(HAVERM!AZ435:AZ437))-1) -> 0.50159448 | ... GI16: =100*((AVERAGE(HAVERM!BK438:BK440)/AVERAGE(HAVERM!BK435:BK437))-1) -> 0.89157136 | GJ16: =100*(((AVERAGE(HAVERM!BL438:BL440)+(AVERAGE(HAVERM!BM438:BM440)))/(AVERAGE(HAVERM!BL435:BL437)+AVERAGE(HAVERM!BM435:BM437))-1)) -> 0.66907649 | GL16: 42370 | GM16: =100*((AVERAGE(GX14:GX16)/AVERAGE(GX11:GX13))-1) -> -0.11071452 | GN16: =100*((AVERAGE(GY14:GY16)/AVERAGE(GY11:GY13))-1) -> 0.39966669 | GO16: =100*((AVERAGE(GZ14:GZ16)/AVERAGE(GZ11:GZ13))-1) -> -0.057520498 | GP16: =100*((AVERAGE(HA14:HA16)/AVERAGE(HA11:HA13))-1) -> 0.39228248 | GQ16: =100*((AVERAGE(HB14:HB16)/AVERAGE(HB11:HB13))-1) -> 0.65939359 | GR16: =100*((AVERAGE(HC14:HC16)/AVERAGE(HC11:HC13))-1) -> 0.70891888 | GS16: =100*((AVERAGE(HD14:HD16)/AVERAGE(HD11:HD13))-1) -> 0.18967258 | GT16: =100*((AVERAGE(HE14:HE16)/AVERAGE(HE11:HE13))-1) -> 0.3736536 | GU16: =100*((AVERAGE(HF14:HF16)/AVERAGE(HF11:HF13))-1) -> 0.27538839 | GW16: 42370 | GX16: =HAVERM!AT440 -> 181276 | GY16: =HAVERM!AU440+HAVERM!AW440+HAVERM!AX440 -> 310642 | GZ16: =HAVERM!AV440 -> 2391245 | HA16: =HAVERM!AY440 -> 1166753 | HB16: =HAVERM!AZ440+HAVERM!BB440 -> 6330631 | HC16: =HAVERM!BA440+HAVERM!BC440 -> 2332785 | HD16: =HAVERM!BD440 -> 1087746 | HE16: =HAVERM!BE440+HAVERM!BF440+HAVERM!BG440 -> 4791340 | HF16: =HAVERM!BH440+HAVERM!BI440+HAVERM!BJ440+HAVERM!BK440+HAVERM!BL440+HAVERM!BM440 -> 9170743 | HH16: Professional services | HI16: ='ASHE Annual pay All SIC'!D98 -> 39880 | HJ16: -0.75272014 | HL16: Professional services | HM16: ='ASHE Annual pay All SIC'!D98 -> 39880 | HN16: -0.33333333 | HP16: 2019 | HQ16: 14.456319 | HR16: 2.6305178 | HS16: =HQ16+HR16 -> 17.086836 | HU16: 2019 | HV16: 6005.2356 | HW16: 1092.7318 | HX16: =HV16+HW16 -> 7097.9673 | HZ16: 44562 | IA16: =HAVERQ!E176 -> 5596 | IB16: =HAVERQ!F176 -> 27277 | IC16: =DataQ!Z203-('Chart Data'!IA16+'Chart Data'!IB16) -> -83 | IE16: 44562 | IF16: =IA16-AVERAGE(IA$4:IA$7) -> 280.25 | IG16: =IB16-AVERAGE(IB$4:IB$7) -> -347 | II16: 44562 | IJ16: =100*(IA16/AVERAGE(IA$4:IA$7)) -> 105.27207 | IK16: =100*(IB16/AVERAGE(IB$4:IB$7)) -> 98.743846 | IM16: 44562 | IN16: =SUM(DataQ!U203:Y203) -> 11238 | IO16: =DataQ!F203-'Chart Data'!IN16 -> 24474 | IQ16: 44562 | IR16: =100*(IN16/AVERAGE(IN$4:IN$7)) -> 102.7216 | IS16: =100*(IO16/AVERAGE(IO$4:IO$7)) -> 99.387811
A17: 44652 | B17: =HAVERQ!E177-AVERAGE(HAVERQ!E$164:E$167) -> 293.25 | C17: =HAVERQ!F177-AVERAGE(HAVERQ!F$164:F$167) -> -321 | E17: 37712 | F17: =HAVERQ!P101 -> 1374 | G17: =HAVERQ!O101 -> 1531 | H17: =HAVERQ!N101 -> 1257 | I17: =HAVERQ!M101 -> 248 | J17: =HAVERQ!L101 -> 223 | K17: =HAVERQ!E101-F17-G17-H17-I17-J17 -> 788 | M17: 37712 | N17: =100*(F17/SUM($F17:$K17)) -> 25.345877 | O17: =100*(G17/SUM($F17:$K17)) -> 28.242022 | P17: =100*(H17/SUM($F17:$K17)) -> 23.187604 | Q17: =100*(I17/SUM($F17:$K17)) -> 4.5748017 | R17: =100*(J17/SUM($F17:$K17)) -> 4.1136322 | S17: =100*(K17/SUM($F17:$K17)) -> 14.536063 | U17: 37712 | V17: =F17-AVERAGE(F$4:F$7) -> 164.75 | W17: =G17-AVERAGE(G$4:G$7) -> 91.25 | X17: =H17-AVERAGE(H$4:H$7) -> 78 | Y17: =I17-AVERAGE(I$4:I$7) -> 22.25 | Z17: =J17-AVERAGE(J$4:J$7) -> 6.75 | AA17: =K17-AVERAGE(K$4:K$7) -> 0.25 | AB17: =SUM(V17:AA17) -> 363.25 | AD17: 44652 | AE17: =HAVERQ!T177-AVERAGE(HAVERQ!T$164:T$167) -> -30.25 | AF17: =HAVERQ!U177-AVERAGE(HAVERQ!U$164:U$167) -> -10.25 | AG17: =HAVERQ!V177-AVERAGE(HAVERQ!V$164:V$167) -> -78.75 | AH17: =HAVERQ!W177-AVERAGE(HAVERQ!W$164:W$167) -> -10.75 | AI17: =HAVERQ!X177-AVERAGE(HAVERQ!X$164:X$167) -> 14.5 | AJ17: =HAVERQ!Y177-AVERAGE(HAVERQ!Y$164:Y$167) -> -82.25 | AK17: =HAVERQ!Z177-AVERAGE(HAVERQ!Z$164:Z$167) -> -254.5 | AL17: =HAVERQ!AA177-AVERAGE(HAVERQ!AA$164:AA$167) -> 42 | ... AV17: =HAVERQ!AK177-AVERAGE(HAVERQ!AK$164:AK$167) -> -17.75 | AW17: =AY17-AVERAGE(AY$4:AY$7) -> -26.5 | AY17: =HAVERQ!AL177+HAVERQ!AM177 -> 991 | BA17: 44652 | BB17: =BK17-AVERAGE(BK$4:BK$7) -> -30.25 | BC17: =BL17-AVERAGE(BL$4:BL$7) -> -6.5 | BD17: =BM17-AVERAGE(BM$4:BM$7) -> -78.75 | BE17: =BN17-AVERAGE(BN$4:BN$7) -> -82.25 | BF17: =BO17-AVERAGE(BO$4:BO$7) -> -158.5 | BG17: =BP17-AVERAGE(BP$4:BP$7) -> 144.75 | BH17: =BQ17-AVERAGE(BQ$4:BQ$7) -> 176.5 | BI17: =BR17-AVERAGE(BR$4:BR$7) -> 390.75 | BK17: =HAVERQ!T177 -> 368 | BL17: =HAVERQ!U177+HAVERQ!W177+HAVERQ!X177 -> 419 | BM17: =HAVERQ!V177 -> 2612 | BN17: =HAVERQ!Y177 -> 2251 | BO17: =HAVERQ!Z177+HAVERQ!AB177 -> 7346 | BP17: =HAVERQ!AA177+HAVERQ!AC177 -> 3451 | BQ17: =HAVERQ!AD177+HAVERQ!AE177+HAVERQ!AF177+HAVERQ!AG177 -> 8143 | BR17: =HAVERQ!AH177+HAVERQ!AI177+HAVERQ!AJ177+HAVERQ!AK177+HAVERQ!AL177+HAVERQ!AM177 -> 11331 | BS17: =HAVERQ!S177-SUM('Chart Data'!BK17:BR17) -> -1 | BU17: 35521 | BV17: =HAVERQ!T77 -> 499 | BW17: =HAVERQ!U77+HAVERQ!W77+HAVERQ!X77 -> 348 | BX17: =HAVERQ!V77 -> 4285 | BY17: =HAVERQ!Y77 -> 1794 | BZ17: =HAVERQ!Z77+HAVERQ!AB77 -> 6580 | CA17: =HAVERQ!AA77+HAVERQ!AC77 -> 2192 | CB17: =HAVERQ!AD77+HAVERQ!AE77+HAVERQ!AF77+HAVERQ!AG77 -> 4976 | CC17: =HAVERQ!AH77+HAVERQ!AI77+HAVERQ!AJ77+HAVERQ!AK77+HAVERQ!AL77+HAVERQ!AM77 -> 8085 | CD17: =HAVERQ!S77-SUM('Chart Data'!BV17:CC17) -> 1 | DB17: 37347 | DC17: =HAVERQ!BI97/HAVERQ!T97 -> 11.304945 | DD17: =HAVERQ!BJ97/HAVERQ!U97 -> 561.77143 | DE17: =HAVERQ!BK97/HAVERQ!V97 -> 11.40264 | DF17: =HAVERQ!BL97/HAVERQ!W97 -> 90.3 | DG17: =HAVERQ!BM97/HAVERQ!X97 -> 42.865854 | DH17: =HAVERQ!BN97/HAVERQ!Y97 -> 16.662994 | DI17: =HAVERQ!BO97/HAVERQ!Z97 -> 10.033406 | DJ17: =HAVERQ!BP97/HAVERQ!AA97 -> 12.135557 | ... DT17: =HAVERQ!BZ97/HAVERQ!AK97 -> 9.0871212 | DU17: =(HAVERQ!CA97+HAVERQ!CB97)/HAVERQ!AL97 -> 10.265476 | DX17: =100*((DX16/DX15)^(1/2)-1) -> 0.81519452 | DY17: =100*((DY16/DY15)^(1/2)-1) -> 0.065488619 | DZ17: =100*((DZ16/DZ15)^(1/2)-1) -> -1.6363204 | EA17: =100*((EA16/EA15)^(1/2)-1) -> -1.3557905 | EB17: =100*((EB16/EB15)^(1/2)-1) -> 0.48255577 | EC17: =100*((EC16/EC15)^(1/2)-1) -> 0.46683714 | ED17: =100*((ED16/ED15)^(1/2)-1) -> 1.4875329 | EE17: =100*((EE16/EE15)^(1/2)-1) -> 0.041939326 | ... EQ17: =100*((EQ16/EQ15)^(1/2)-1) -> 1.2709708 | FD17: 45017 | FE17: =DataQ!U208+DataQ!V208+DataQ!W208+DataQ!X208+DataQ!Y208 -> 11491 | FF17: =DataQ!J208+DataQ!Q208+DataQ!H208+DataQ!P208+DataQ!S208+DataQ!K208+DataQ!L208 -> 8846 | FG17: =DataQ!N208+DataQ!I208+DataQ!R208+DataQ!G208+DataQ!T208+DataQ!M208+DataQ!O208 -> 15993 | FH17: =DataQ!F208-'Chart Data'!FE17-'Chart Data'!FF17-'Chart Data'!FG17 -> 0 | FJ17: 45017 | FK17: =FE17-(AVERAGE(FE$20:FE$23)) -> -439.75 | FL17: =FF17-(AVERAGE(FF$20:FF$23)) -> -99.25 | FM17: =FG17-(AVERAGE(FG$20:FG$23)) -> 74.75 | FN17: =SUM(FK17:FM17) -> -464.25 | FP17: 42401 | FQ17: =100*((AVERAGE(HAVERM!AS439:AS441)/AVERAGE(HAVERM!AS436:AS438))-1) -> 0.29142047 | FR17: =100*((AVERAGE(HAVERM!AT439:AT441)/AVERAGE(HAVERM!AT436:AT438))-1) -> -0.14688305 | FS17: =100*((AVERAGE(HAVERM!AU439:AU441)/AVERAGE(HAVERM!AU436:AU438))-1) -> -3.1146945 | FT17: =100*((AVERAGE(HAVERM!AV439:AV441)/AVERAGE(HAVERM!AV436:AV438))-1) -> -0.20422739 | FU17: =100*((AVERAGE(HAVERM!AW439:AW441)/AVERAGE(HAVERM!AW436:AW438))-1) -> 2.2930682 | FV17: =100*((AVERAGE(HAVERM!AX439:AX441)/AVERAGE(HAVERM!AX436:AX438))-1) -> 0.54366101 | FW17: =100*((AVERAGE(HAVERM!AY439:AY441)/AVERAGE(HAVERM!AY436:AY438))-1) -> 0.32217961 | FX17: =100*((AVERAGE(HAVERM!AZ439:AZ441)/AVERAGE(HAVERM!AZ436:AZ438))-1) -> 0.38970588 | ... GI17: =100*((AVERAGE(HAVERM!BK439:BK441)/AVERAGE(HAVERM!BK436:BK438))-1) -> 0.81261907 | GJ17: =100*(((AVERAGE(HAVERM!BL439:BL441)+(AVERAGE(HAVERM!BM439:BM441)))/(AVERAGE(HAVERM!BL436:BL438)+AVERAGE(HAVERM!BM436:BM438))-1)) -> 0.59789222 | GL17: 42401 | GM17: =100*((AVERAGE(GX15:GX17)/AVERAGE(GX12:GX14))-1) -> -0.14688305 | GN17: =100*((AVERAGE(GY15:GY17)/AVERAGE(GY12:GY14))-1) -> 0.44166245 | GO17: =100*((AVERAGE(GZ15:GZ17)/AVERAGE(GZ12:GZ14))-1) -> -0.20422739 | GP17: =100*((AVERAGE(HA15:HA17)/AVERAGE(HA12:HA14))-1) -> 0.32217961 | GQ17: =100*((AVERAGE(HB15:HB17)/AVERAGE(HB12:HB14))-1) -> 0.54690773 | GR17: =100*((AVERAGE(HC15:HC17)/AVERAGE(HC12:HC14))-1) -> 0.67516575 | GS17: =100*((AVERAGE(HD15:HD17)/AVERAGE(HD12:HD14))-1) -> 0.10517959 | GT17: =100*((AVERAGE(HE15:HE17)/AVERAGE(HE12:HE14))-1) -> 0.24477278 | GU17: =100*((AVERAGE(HF15:HF17)/AVERAGE(HF12:HF14))-1) -> 0.19410974 | GW17: 42401 | GX17: =HAVERM!AT441 -> 181373 | GY17: =HAVERM!AU441+HAVERM!AW441+HAVERM!AX441 -> 310600 | GZ17: =HAVERM!AV441 -> 2389242 | HA17: =HAVERM!AY441 -> 1166568 | HB17: =HAVERM!AZ441+HAVERM!BB441 -> 6343058 | HC17: =HAVERM!BA441+HAVERM!BC441 -> 2339695 | HD17: =HAVERM!BD441 -> 1086184 | HE17: =HAVERM!BE441+HAVERM!BF441+HAVERM!BG441 -> 4798995 | HF17: =HAVERM!BH441+HAVERM!BI441+HAVERM!BJ441+HAVERM!BK441+HAVERM!BL441+HAVERM!BM441 -> 9182874 | HH17: Administrative services | HI17: ='ASHE Annual pay All SIC'!D106 -> 26803 | HJ17: -0.3244337 | HL17: Administrative services | HM17: ='ASHE Annual pay All SIC'!D106 -> 26803 | HN17: -0.15333333 | HP17: 2020 | HQ17: 19.681002 | HR17: 3.6179197 | HS17: =HQ17+HR17 -> 23.298922 | HU17: 2020 | HV17: 7207.8481 | HW17: 1325.0045 | HX17: =HV17+HW17 -> 8532.8525 | HZ17: 44652 | IA17: =HAVERQ!E177 -> 5609 | IB17: =HAVERQ!F177 -> 27303 | IC17: =DataQ!Z204-('Chart Data'!IA17+'Chart Data'!IB17) -> 90 | IE17: 44652 | IF17: =IA17-AVERAGE(IA$4:IA$7) -> 293.25 | IG17: =IB17-AVERAGE(IB$4:IB$7) -> -321 | II17: 44652 | IJ17: =100*(IA17/AVERAGE(IA$4:IA$7)) -> 105.51663 | IK17: =100*(IB17/AVERAGE(IB$4:IB$7)) -> 98.837967 | IM17: 44652 | IN17: =SUM(DataQ!U204:Y204) -> 11331 | IO17: =DataQ!F204-'Chart Data'!IN17 -> 24589 | IQ17: 44652 | IR17: =100*(IN17/AVERAGE(IN$4:IN$7)) -> 103.57167 | IS17: =100*(IO17/AVERAGE(IO$4:IO$7)) -> 99.854821
A18: 44743 | B18: =HAVERQ!E178-AVERAGE(HAVERQ!E$164:E$167) -> 309.25 | C18: =HAVERQ!F178-AVERAGE(HAVERQ!F$164:F$167) -> -273 | E18: 37803 | F18: =HAVERQ!P102 -> 1391 | G18: =HAVERQ!O102 -> 1535 | H18: =HAVERQ!N102 -> 1260 | I18: =HAVERQ!M102 -> 252 | J18: =HAVERQ!L102 -> 222 | K18: =HAVERQ!E102-F18-G18-H18-I18-J18 -> 806 | M18: 37803 | N18: =100*(F18/SUM($F18:$K18)) -> 25.448225 | O18: =100*(G18/SUM($F18:$K18)) -> 28.082693 | P18: =100*(H18/SUM($F18:$K18)) -> 23.051592 | Q18: =100*(I18/SUM($F18:$K18)) -> 4.6103183 | R18: =100*(J18/SUM($F18:$K18)) -> 4.0614709 | S18: =100*(K18/SUM($F18:$K18)) -> 14.745701 | U18: 37803 | V18: =F18-AVERAGE(F$4:F$7) -> 181.75 | W18: =G18-AVERAGE(G$4:G$7) -> 95.25 | X18: =H18-AVERAGE(H$4:H$7) -> 81 | Y18: =I18-AVERAGE(I$4:I$7) -> 26.25 | Z18: =J18-AVERAGE(J$4:J$7) -> 5.75 | AA18: =K18-AVERAGE(K$4:K$7) -> 18.25 | AB18: =SUM(V18:AA18) -> 408.25 | AD18: 44743 | AE18: =HAVERQ!T178-AVERAGE(HAVERQ!T$164:T$167) -> -36.25 | AF18: =HAVERQ!U178-AVERAGE(HAVERQ!U$164:U$167) -> -9.25 | AG18: =HAVERQ!V178-AVERAGE(HAVERQ!V$164:V$167) -> -73.75 | AH18: =HAVERQ!W178-AVERAGE(HAVERQ!W$164:W$167) -> -18.75 | AI18: =HAVERQ!X178-AVERAGE(HAVERQ!X$164:X$167) -> 17.5 | AJ18: =HAVERQ!Y178-AVERAGE(HAVERQ!Y$164:Y$167) -> -132.25 | AK18: =HAVERQ!Z178-AVERAGE(HAVERQ!Z$164:Z$167) -> -256.5 | AL18: =HAVERQ!AA178-AVERAGE(HAVERQ!AA$164:AA$167) -> 76 | ... AV18: =HAVERQ!AK178-AVERAGE(HAVERQ!AK$164:AK$167) -> -13.75 | AW18: =AY18-AVERAGE(AY$4:AY$7) -> -18.5 | AY18: =HAVERQ!AL178+HAVERQ!AM178 -> 999 | BA18: 44743 | BB18: =BK18-AVERAGE(BK$4:BK$7) -> -36.25 | BC18: =BL18-AVERAGE(BL$4:BL$7) -> -10.5 | BD18: =BM18-AVERAGE(BM$4:BM$7) -> -73.75 | BE18: =BN18-AVERAGE(BN$4:BN$7) -> -132.25 | BF18: =BO18-AVERAGE(BO$4:BO$7) -> -85.5 | BG18: =BP18-AVERAGE(BP$4:BP$7) -> 194.75 | BH18: =BQ18-AVERAGE(BQ$4:BQ$7) -> 186.5 | BI18: =BR18-AVERAGE(BR$4:BR$7) -> 375.75 | BK18: =HAVERQ!T178 -> 362 | BL18: =HAVERQ!U178+HAVERQ!W178+HAVERQ!X178 -> 415 | BM18: =HAVERQ!V178 -> 2617 | BN18: =HAVERQ!Y178 -> 2201 | BO18: =HAVERQ!Z178+HAVERQ!AB178 -> 7419 | BP18: =HAVERQ!AA178+HAVERQ!AC178 -> 3501 | BQ18: =HAVERQ!AD178+HAVERQ!AE178+HAVERQ!AF178+HAVERQ!AG178 -> 8153 | BR18: =HAVERQ!AH178+HAVERQ!AI178+HAVERQ!AJ178+HAVERQ!AK178+HAVERQ!AL178+HAVERQ!AM178 -> 11316 | BS18: =HAVERQ!S178-SUM('Chart Data'!BK18:BR18) -> 1 | BU18: 35612 | BV18: =HAVERQ!T78 -> 497 | BW18: =HAVERQ!U78+HAVERQ!W78+HAVERQ!X78 -> 345 | BX18: =HAVERQ!V78 -> 4275 | BY18: =HAVERQ!Y78 -> 1836 | BZ18: =HAVERQ!Z78+HAVERQ!AB78 -> 6636 | CA18: =HAVERQ!AA78+HAVERQ!AC78 -> 2195 | CB18: =HAVERQ!AD78+HAVERQ!AE78+HAVERQ!AF78+HAVERQ!AG78 -> 5022 | CC18: =HAVERQ!AH78+HAVERQ!AI78+HAVERQ!AJ78+HAVERQ!AK78+HAVERQ!AL78+HAVERQ!AM78 -> 8091 | CD18: =HAVERQ!S78-SUM('Chart Data'!BV18:CC18) -> 0 | DB18: 37438 | DC18: =HAVERQ!BI98/HAVERQ!T98 -> 11.673295 | DD18: =HAVERQ!BJ98/HAVERQ!U98 -> 535.40299 | DE18: =HAVERQ!BK98/HAVERQ!V98 -> 12.387664 | DF18: =HAVERQ!BL98/HAVERQ!W98 -> 92.895833 | DG18: =HAVERQ!BM98/HAVERQ!X98 -> 42.950311 | DH18: =HAVERQ!BN98/HAVERQ!Y98 -> 16.685204 | DI18: =HAVERQ!BO98/HAVERQ!Z98 -> 9.9781529 | DJ18: =HAVERQ!BP98/HAVERQ!AA98 -> 12.066104 | ... DT18: =HAVERQ!BZ98/HAVERQ!AK98 -> 9.489899 | DU18: =(HAVERQ!CA98+HAVERQ!CB98)/HAVERQ!AL98 -> 10.493445 | FD18: 45108 | FE18: =DataQ!U209+DataQ!V209+DataQ!W209+DataQ!X209+DataQ!Y209 -> 11569 | FF18: =DataQ!J209+DataQ!Q209+DataQ!H209+DataQ!P209+DataQ!S209+DataQ!K209+DataQ!L209 -> 8827 | FG18: =DataQ!N209+DataQ!I209+DataQ!R209+DataQ!G209+DataQ!T209+DataQ!M209+DataQ!O209 -> 16018 | FH18: =DataQ!F209-'Chart Data'!FE18-'Chart Data'!FF18-'Chart Data'!FG18 -> 1 | FJ18: 45108 | FK18: =FE18-(AVERAGE(FE$20:FE$23)) -> -361.75 | FL18: =FF18-(AVERAGE(FF$20:FF$23)) -> -118.25 | FM18: =FG18-(AVERAGE(FG$20:FG$23)) -> 99.75 | FN18: =SUM(FK18:FM18) -> -380.25 | FP18: 42430 | FQ18: =100*((AVERAGE(HAVERM!AS440:AS442)/AVERAGE(HAVERM!AS437:AS439))-1) -> 0.36732054 | FR18: =100*((AVERAGE(HAVERM!AT440:AT442)/AVERAGE(HAVERM!AT437:AT439))-1) -> -0.095716986 | FS18: =100*((AVERAGE(HAVERM!AU440:AU442)/AVERAGE(HAVERM!AU437:AU439))-1) -> -2.3522143 | FT18: =100*((AVERAGE(HAVERM!AV440:AV442)/AVERAGE(HAVERM!AV437:AV439))-1) -> 0.28329904 | FU18: =100*((AVERAGE(HAVERM!AW440:AW442)/AVERAGE(HAVERM!AW437:AW439))-1) -> 2.2567094 | FV18: =100*((AVERAGE(HAVERM!AX440:AX442)/AVERAGE(HAVERM!AX437:AX439))-1) -> 0.50839329 | FW18: =100*((AVERAGE(HAVERM!AY440:AY442)/AVERAGE(HAVERM!AY437:AY439))-1) -> 1.4110142 | FX18: =100*((AVERAGE(HAVERM!AZ440:AZ442)/AVERAGE(HAVERM!AZ437:AZ439))-1) -> 0.3427628 | ... GI18: =100*((AVERAGE(HAVERM!BK440:BK442)/AVERAGE(HAVERM!BK437:BK439))-1) -> 0.92094576 | GJ18: =100*(((AVERAGE(HAVERM!BL440:BL442)+(AVERAGE(HAVERM!BM440:BM442)))/(AVERAGE(HAVERM!BL437:BL439)+AVERAGE(HAVERM!BM437:BM439))-1)) -> 0.54678342 | GL18: 42430 | GM18: =100*((AVERAGE(GX16:GX18)/AVERAGE(GX13:GX15))-1) -> -0.095716986 | GN18: =100*((AVERAGE(GY16:GY18)/AVERAGE(GY13:GY15))-1) -> 0.55581742 | GO18: =100*((AVERAGE(GZ16:GZ18)/AVERAGE(GZ13:GZ15))-1) -> 0.28329904 | GP18: =100*((AVERAGE(HA16:HA18)/AVERAGE(HA13:HA15))-1) -> 1.4110142 | GQ18: =100*((AVERAGE(HB16:HB18)/AVERAGE(HB13:HB15))-1) -> 0.52135781 | GR18: =100*((AVERAGE(HC16:HC18)/AVERAGE(HC13:HC15))-1) -> 0.71003991 | GS18: =100*((AVERAGE(HD16:HD18)/AVERAGE(HD13:HD15))-1) -> -0.057337866 | GT18: =100*((AVERAGE(HE16:HE18)/AVERAGE(HE13:HE15))-1) -> 0.26120854 | GU18: =100*((AVERAGE(HF16:HF18)/AVERAGE(HF13:HF15))-1) -> 0.17374464 | GW18: 42430 | GX18: =HAVERM!AT442 -> 181143 | GY18: =HAVERM!AU442+HAVERM!AW442+HAVERM!AX442 -> 311014 | GZ18: =HAVERM!AV442 -> 2388395 | HA18: =HAVERM!AY442 -> 1169169 | HB18: =HAVERM!AZ442+HAVERM!BB442 -> 6352684 | HC18: =HAVERM!BA442+HAVERM!BC442 -> 2343353 | HD18: =HAVERM!BD442 -> 1083827 | HE18: =HAVERM!BE442+HAVERM!BF442+HAVERM!BG442 -> 4806581 | HF18: =HAVERM!BH442+HAVERM!BI442+HAVERM!BJ442+HAVERM!BK442+HAVERM!BL442+HAVERM!BM442 -> 9185644 | HH18: Public admin | HI18: ='ASHE Annual pay All SIC'!D113 -> 36109 | HJ18: 0.43966566 | HL18: Public admin | HM18: ='ASHE Annual pay All SIC'!D113 -> 36109 | HN18: 0.1775 | HP18: 2021 | HQ18: 17.02542 | HR18: 3.2788112 | HS18: =HQ18+HR18 -> 20.304231 | HU18: 2021 | HV18: 7042.4536 | HW18: 1356.2588 | HX18: =HV18+HW18 -> 8398.7124 | HZ18: 44743 | IA18: =HAVERQ!E178 -> 5625 | IB18: =HAVERQ!F178 -> 27351 | IC18: =DataQ!Z205-('Chart Data'!IA18+'Chart Data'!IB18) -> -55 | IE18: 44743 | IF18: =IA18-AVERAGE(IA$4:IA$7) -> 309.25 | IG18: =IB18-AVERAGE(IB$4:IB$7) -> -273 | II18: 44743 | IJ18: =100*(IA18/AVERAGE(IA$4:IA$7)) -> 105.81762 | IK18: =100*(IB18/AVERAGE(IB$4:IB$7)) -> 99.011729 | IM18: 44743 | IN18: =SUM(DataQ!U205:Y205) -> 11316 | IO18: =DataQ!F205-'Chart Data'!IN18 -> 24669 | IQ18: 44743 | IR18: =100*(IN18/AVERAGE(IN$4:IN$7)) -> 103.43457 | IS18: =100*(IO18/AVERAGE(IO$4:IO$7)) -> 100.1797
A19: 44835 | B19: =HAVERQ!E179-AVERAGE(HAVERQ!E$164:E$167) -> 337.25 | C19: =HAVERQ!F179-AVERAGE(HAVERQ!F$164:F$167) -> -121 | E19: 37895 | F19: =HAVERQ!P103 -> 1408 | G19: =HAVERQ!O103 -> 1557 | H19: =HAVERQ!N103 -> 1258 | I19: =HAVERQ!M103 -> 256 | J19: =HAVERQ!L103 -> 221 | K19: =HAVERQ!E103-F19-G19-H19-I19-J19 -> 801 | M19: 37895 | N19: =100*(F19/SUM($F19:$K19)) -> 25.595346 | O19: =100*(G19/SUM($F19:$K19)) -> 28.303945 | P19: =100*(H19/SUM($F19:$K19)) -> 22.868569 | Q19: =100*(I19/SUM($F19:$K19)) -> 4.6536993 | R19: =100*(J19/SUM($F19:$K19)) -> 4.0174514 | S19: =100*(K19/SUM($F19:$K19)) -> 14.560989 | U19: 37895 | V19: =F19-AVERAGE(F$4:F$7) -> 198.75 | W19: =G19-AVERAGE(G$4:G$7) -> 117.25 | X19: =H19-AVERAGE(H$4:H$7) -> 79 | Y19: =I19-AVERAGE(I$4:I$7) -> 30.25 | Z19: =J19-AVERAGE(J$4:J$7) -> 4.75 | AA19: =K19-AVERAGE(K$4:K$7) -> 13.25 | AB19: =SUM(V19:AA19) -> 443.25 | AD19: 44835 | AE19: =HAVERQ!T179-AVERAGE(HAVERQ!T$164:T$167) -> -48.25 | AF19: =HAVERQ!U179-AVERAGE(HAVERQ!U$164:U$167) -> -8.25 | AG19: =HAVERQ!V179-AVERAGE(HAVERQ!V$164:V$167) -> -69.75 | AH19: =HAVERQ!W179-AVERAGE(HAVERQ!W$164:W$167) -> -20.75 | AI19: =HAVERQ!X179-AVERAGE(HAVERQ!X$164:X$167) -> 18.5 | AJ19: =HAVERQ!Y179-AVERAGE(HAVERQ!Y$164:Y$167) -> -108.25 | AK19: =HAVERQ!Z179-AVERAGE(HAVERQ!Z$164:Z$167) -> -262.5 | AL19: =HAVERQ!AA179-AVERAGE(HAVERQ!AA$164:AA$167) -> 89 | ... AV19: =HAVERQ!AK179-AVERAGE(HAVERQ!AK$164:AK$167) -> -7.75 | AW19: =AY19-AVERAGE(AY$4:AY$7) -> -15.5 | AY19: =HAVERQ!AL179+HAVERQ!AM179 -> 1002 | BA19: 44835 | BB19: =BK19-AVERAGE(BK$4:BK$7) -> -48.25 | BC19: =BL19-AVERAGE(BL$4:BL$7) -> -10.5 | BD19: =BM19-AVERAGE(BM$4:BM$7) -> -69.75 | BE19: =BN19-AVERAGE(BN$4:BN$7) -> -108.25 | BF19: =BO19-AVERAGE(BO$4:BO$7) -> -48.5 | BG19: =BP19-AVERAGE(BP$4:BP$7) -> 207.75 | BH19: =BQ19-AVERAGE(BQ$4:BQ$7) -> 286.5 | BI19: =BR19-AVERAGE(BR$4:BR$7) -> 406.75 | BK19: =HAVERQ!T179 -> 350 | BL19: =HAVERQ!U179+HAVERQ!W179+HAVERQ!X179 -> 415 | BM19: =HAVERQ!V179 -> 2621 | BN19: =HAVERQ!Y179 -> 2225 | BO19: =HAVERQ!Z179+HAVERQ!AB179 -> 7456 | BP19: =HAVERQ!AA179+HAVERQ!AC179 -> 3514 | BQ19: =HAVERQ!AD179+HAVERQ!AE179+HAVERQ!AF179+HAVERQ!AG179 -> 8253 | BR19: =HAVERQ!AH179+HAVERQ!AI179+HAVERQ!AJ179+HAVERQ!AK179+HAVERQ!AL179+HAVERQ!AM179 -> 11347 | BS19: =HAVERQ!S179-SUM('Chart Data'!BK19:BR19) -> 0 | BU19: 35704 | BV19: =HAVERQ!T79 -> 484 | BW19: =HAVERQ!U79+HAVERQ!W79+HAVERQ!X79 -> 351 | BX19: =HAVERQ!V79 -> 4301 | BY19: =HAVERQ!Y79 -> 1896 | BZ19: =HAVERQ!Z79+HAVERQ!AB79 -> 6627 | CA19: =HAVERQ!AA79+HAVERQ!AC79 -> 2233 | CB19: =HAVERQ!AD79+HAVERQ!AE79+HAVERQ!AF79+HAVERQ!AG79 -> 5058 | CC19: =HAVERQ!AH79+HAVERQ!AI79+HAVERQ!AJ79+HAVERQ!AK79+HAVERQ!AL79+HAVERQ!AM79 -> 8070 | CD19: =HAVERQ!S79-SUM('Chart Data'!BV19:CC19) -> 2 | DB19: 37530 | DC19: =HAVERQ!BI99/HAVERQ!T99 -> 12.244776 | DD19: =HAVERQ!BJ99/HAVERQ!U99 -> 576.06154 | DE19: =HAVERQ!BK99/HAVERQ!V99 -> 12.462952 | DF19: =HAVERQ!BL99/HAVERQ!W99 -> 97.393617 | DG19: =HAVERQ!BM99/HAVERQ!X99 -> 44.408805 | DH19: =HAVERQ!BN99/HAVERQ!Y99 -> 16.678377 | DI19: =HAVERQ!BO99/HAVERQ!Z99 -> 10.000992 | DJ19: =HAVERQ!BP99/HAVERQ!AA99 -> 11.905462 | ... DT19: =HAVERQ!BZ99/HAVERQ!AK99 -> 9.4358974 | DU19: =(HAVERQ!CA99+HAVERQ!CB99)/HAVERQ!AL99 -> 10.444712 | DW19: 2024 | DX19: =DataA!B58 -> 36792.75 | DY19: =DataA!C58 -> 360.25 | DZ19: =DataA!D58 -> 48.25 | EA19: =DataA!E58 -> 2588 | EB19: =DataA!F58 -> 135.75 | EC19: =DataA!G58 -> 246 | ED19: =DataA!H58 -> 2209 | EE19: =DataA!I58 -> 4722.5 | ... EQ19: =DataA!U58 -> 997.5 | FD19: 45200 | FE19: =DataQ!U210+DataQ!V210+DataQ!W210+DataQ!X210+DataQ!Y210 -> 11671 | FF19: =DataQ!J210+DataQ!Q210+DataQ!H210+DataQ!P210+DataQ!S210+DataQ!K210+DataQ!L210 -> 8810 | FG19: =DataQ!N210+DataQ!I210+DataQ!R210+DataQ!G210+DataQ!T210+DataQ!M210+DataQ!O210 -> 16025 | FH19: =DataQ!F210-'Chart Data'!FE19-'Chart Data'!FF19-'Chart Data'!FG19 -> -3 | FJ19: 45200 | FK19: =FE19-(AVERAGE(FE$20:FE$23)) -> -259.75 | FL19: =FF19-(AVERAGE(FF$20:FF$23)) -> -135.25 | FM19: =FG19-(AVERAGE(FG$20:FG$23)) -> 106.75 | FN19: =SUM(FK19:FM19) -> -288.25 | FP19: 42461 | FQ19: =100*((AVERAGE(HAVERM!AS441:AS443)/AVERAGE(HAVERM!AS438:AS440))-1) -> 0.3257308 | FR19: =100*((AVERAGE(HAVERM!AT441:AT443)/AVERAGE(HAVERM!AT438:AT440))-1) -> -0.083817212 | FS19: =100*((AVERAGE(HAVERM!AU441:AU443)/AVERAGE(HAVERM!AU438:AU440))-1) -> -2.4508754 | FT19: =100*((AVERAGE(HAVERM!AV441:AV443)/AVERAGE(HAVERM!AV438:AV440))-1) -> 0.22694241 | FU19: =100*((AVERAGE(HAVERM!AW441:AW443)/AVERAGE(HAVERM!AW438:AW440))-1) -> 2.068058 | FV19: =100*((AVERAGE(HAVERM!AX441:AX443)/AVERAGE(HAVERM!AX438:AX440))-1) -> 0.44431132 | FW19: =100*((AVERAGE(HAVERM!AY441:AY443)/AVERAGE(HAVERM!AY438:AY440))-1) -> 1.209867 | FX19: =100*((AVERAGE(HAVERM!AZ441:AZ443)/AVERAGE(HAVERM!AZ438:AZ440))-1) -> 0.29603308 | ... GI19: =100*((AVERAGE(HAVERM!BK441:BK443)/AVERAGE(HAVERM!BK438:BK440))-1) -> 1.1445171 | GJ19: =100*(((AVERAGE(HAVERM!BL441:BL443)+(AVERAGE(HAVERM!BM441:BM443)))/(AVERAGE(HAVERM!BL438:BL440)+AVERAGE(HAVERM!BM438:BM440))-1)) -> 0.51966207 | GL19: 42461 | GM19: =100*((AVERAGE(GX17:GX19)/AVERAGE(GX14:GX16))-1) -> -0.083817212 | GN19: =100*((AVERAGE(GY17:GY19)/AVERAGE(GY14:GY16))-1) -> 0.45588174 | GO19: =100*((AVERAGE(GZ17:GZ19)/AVERAGE(GZ14:GZ16))-1) -> 0.22694241 | GP19: =100*((AVERAGE(HA17:HA19)/AVERAGE(HA14:HA16))-1) -> 1.209867 | GQ19: =100*((AVERAGE(HB17:HB19)/AVERAGE(HB14:HB16))-1) -> 0.50226705 | GR19: =100*((AVERAGE(HC17:HC19)/AVERAGE(HC14:HC16))-1) -> 0.70208086 | GS19: =100*((AVERAGE(HD17:HD19)/AVERAGE(HD14:HD16))-1) -> -0.18925218 | GT19: =100*((AVERAGE(HE17:HE19)/AVERAGE(HE14:HE16))-1) -> 0.16309331 | GU19: =100*((AVERAGE(HF17:HF19)/AVERAGE(HF14:HF16))-1) -> 0.17247756 | GW19: 42461 | GX19: =HAVERM!AT443 -> 181069 | GY19: =HAVERM!AU443+HAVERM!AW443+HAVERM!AX443 -> 311590 | GZ19: =HAVERM!AV443 -> 2390187 | HA19: =HAVERM!AY443 -> 1172616 | HB19: =HAVERM!AZ443+HAVERM!BB443 -> 6361322 | HC19: =HAVERM!BA443+HAVERM!BC443 -> 2347500 | HD19: =HAVERM!BD443 -> 1085074 | HE19: =HAVERM!BE443+HAVERM!BF443+HAVERM!BG443 -> 4783249 | HF19: =HAVERM!BH443+HAVERM!BI443+HAVERM!BJ443+HAVERM!BK443+HAVERM!BL443+HAVERM!BM443 -> 9186273 | HH19: Education | HI19: ='ASHE Annual pay All SIC'!D115 -> 31094 | HJ19: 0.18869368 | HL19: Education | HM19: ='ASHE Annual pay All SIC'!D115 -> 31094 | HN19: -0.165 | HP19: 2022 | HQ19: 15.77166 | HR19: 3.4746544 | HS19: =HQ19+HR19 -> 19.246314 | HU19: 2022 | HV19: 6608.8712 | HW19: 1456.0004 | HX19: =HV19+HW19 -> 8064.8716 | HZ19: 44835 | IA19: =HAVERQ!E179 -> 5653 | IB19: =HAVERQ!F179 -> 27503 | IC19: =DataQ!Z206-('Chart Data'!IA19+'Chart Data'!IB19) -> -40 | IE19: 44835 | IF19: =IA19-AVERAGE(IA$4:IA$7) -> 337.25 | IG19: =IB19-AVERAGE(IB$4:IB$7) -> -121 | II19: 44835 | IJ19: =100*(IA19/AVERAGE(IA$4:IA$7)) -> 106.34435 | IK19: =100*(IB19/AVERAGE(IB$4:IB$7)) -> 99.561975 | IM19: 44835 | IN19: =SUM(DataQ!U206:Y206) -> 11347 | IO19: =DataQ!F206-'Chart Data'!IN19 -> 24834 | IQ19: 44835 | IR19: =100*(IN19/AVERAGE(IN$4:IN$7)) -> 103.71792 | IS19: =100*(IO19/AVERAGE(IO$4:IO$7)) -> 100.84975
A20: 44927 | B20: =HAVERQ!E180-AVERAGE(HAVERQ!E$164:E$167) -> 373.25 | C20: =HAVERQ!F180-AVERAGE(HAVERQ!F$164:F$167) -> 160 | E20: 37987 | F20: =HAVERQ!P104 -> 1426 | G20: =HAVERQ!O104 -> 1560 | H20: =HAVERQ!N104 -> 1267 | I20: =HAVERQ!M104 -> 260 | J20: =HAVERQ!L104 -> 219 | K20: =HAVERQ!E104-F20-G20-H20-I20-J20 -> 802 | M20: 37987 | N20: =100*(F20/SUM($F20:$K20)) -> 25.76798 | O20: =100*(G20/SUM($F20:$K20)) -> 28.189375 | P20: =100*(H20/SUM($F20:$K20)) -> 22.894832 | Q20: =100*(I20/SUM($F20:$K20)) -> 4.6982291 | R20: =100*(J20/SUM($F20:$K20)) -> 3.9573545 | S20: =100*(K20/SUM($F20:$K20)) -> 14.49223 | U20: 37987 | V20: =F20-AVERAGE(F$4:F$7) -> 216.75 | W20: =G20-AVERAGE(G$4:G$7) -> 120.25 | X20: =H20-AVERAGE(H$4:H$7) -> 88 | Y20: =I20-AVERAGE(I$4:I$7) -> 34.25 | Z20: =J20-AVERAGE(J$4:J$7) -> 2.75 | AA20: =K20-AVERAGE(K$4:K$7) -> 14.25 | AB20: =SUM(V20:AA20) -> 476.25 | AD20: 44927 | AE20: =HAVERQ!T180-AVERAGE(HAVERQ!T$164:T$167) -> -31.25 | AF20: =HAVERQ!U180-AVERAGE(HAVERQ!U$164:U$167) -> -4.25 | AG20: =HAVERQ!V180-AVERAGE(HAVERQ!V$164:V$167) -> -77.75 | AH20: =HAVERQ!W180-AVERAGE(HAVERQ!W$164:W$167) -> -20.75 | AI20: =HAVERQ!X180-AVERAGE(HAVERQ!X$164:X$167) -> 28.5 | AJ20: =HAVERQ!Y180-AVERAGE(HAVERQ!Y$164:Y$167) -> -75.25 | AK20: =HAVERQ!Z180-AVERAGE(HAVERQ!Z$164:Z$167) -> -230.5 | AL20: =HAVERQ!AA180-AVERAGE(HAVERQ!AA$164:AA$167) -> 95 | ... AV20: =HAVERQ!AK180-AVERAGE(HAVERQ!AK$164:AK$167) -> -1.75 | AW20: =AY20-AVERAGE(AY$4:AY$7) -> -22.5 | AY20: =HAVERQ!AL180+HAVERQ!AM180 -> 995 | BA20: 44927 | BB20: =BK20-AVERAGE(BK$4:BK$7) -> -31.25 | BC20: =BL20-AVERAGE(BL$4:BL$7) -> 3.5 | BD20: =BM20-AVERAGE(BM$4:BM$7) -> -77.75 | BE20: =BN20-AVERAGE(BN$4:BN$7) -> -75.25 | BF20: =BO20-AVERAGE(BO$4:BO$7) -> -30.5 | BG20: =BP20-AVERAGE(BP$4:BP$7) -> 245.75 | BH20: =BQ20-AVERAGE(BQ$4:BQ$7) -> 398.5 | BI20: =BR20-AVERAGE(BR$4:BR$7) -> 538.75 | BK20: =HAVERQ!T180 -> 367 | BL20: =HAVERQ!U180+HAVERQ!W180+HAVERQ!X180 -> 429 | BM20: =HAVERQ!V180 -> 2613 | BN20: =HAVERQ!Y180 -> 2258 | BO20: =HAVERQ!Z180+HAVERQ!AB180 -> 7474 | BP20: =HAVERQ!AA180+HAVERQ!AC180 -> 3552 | BQ20: =HAVERQ!AD180+HAVERQ!AE180+HAVERQ!AF180+HAVERQ!AG180 -> 8365 | BR20: =HAVERQ!AH180+HAVERQ!AI180+HAVERQ!AJ180+HAVERQ!AK180+HAVERQ!AL180+HAVERQ!AM180 -> 11479 | BS20: =HAVERQ!S180-SUM('Chart Data'!BK20:BR20) -> 0 | BU20: 35796 | BV20: =HAVERQ!T80 -> 483 | BW20: =HAVERQ!U80+HAVERQ!W80+HAVERQ!X80 -> 347 | BX20: =HAVERQ!V80 -> 4313 | BY20: =HAVERQ!Y80 -> 1885 | BZ20: =HAVERQ!Z80+HAVERQ!AB80 -> 6631 | CA20: =HAVERQ!AA80+HAVERQ!AC80 -> 2269 | CB20: =HAVERQ!AD80+HAVERQ!AE80+HAVERQ!AF80+HAVERQ!AG80 -> 5053 | CC20: =HAVERQ!AH80+HAVERQ!AI80+HAVERQ!AJ80+HAVERQ!AK80+HAVERQ!AL80+HAVERQ!AM80 -> 8062 | CD20: =HAVERQ!S80-SUM('Chart Data'!BV20:CC20) -> 2 | DB20: 37622 | DC20: =HAVERQ!BI100/HAVERQ!T100 -> 11.988131 | DD20: =HAVERQ!BJ100/HAVERQ!U100 -> 597.96825 | DE20: =HAVERQ!BK100/HAVERQ!V100 -> 12.592391 | DF20: =HAVERQ!BL100/HAVERQ!W100 -> 108.58696 | DG20: =HAVERQ!BM100/HAVERQ!X100 -> 47.264516 | DH20: =HAVERQ!BN100/HAVERQ!Y100 -> 15.995074 | DI20: =HAVERQ!BO100/HAVERQ!Z100 -> 9.9359438 | DJ20: =HAVERQ!BP100/HAVERQ!AA100 -> 12.237395 | ... DT20: =HAVERQ!BZ100/HAVERQ!AK100 -> 9.8567807 | DU20: =(HAVERQ!CA100+HAVERQ!CB100)/HAVERQ!AL100 -> 10.091898 | DW20: 2025 | DX20: =DataA!B59 -> 37080.365 | DY20: =DataA!C59 -> 356.82673 | DZ20: =DataA!D59 -> 48.869173 | EA20: =DataA!E59 -> 2573.1775 | EB20: =DataA!F59 -> 138.58163 | EC20: =DataA!G59 -> 247.17445 | ED20: =DataA!H59 -> 2241.2733 | EE20: =DataA!I59 -> 4692.6525 | ... EQ20: =DataA!U59 -> 1019.1907 | FD20: 45292 | FE20: =DataQ!U211+DataQ!V211+DataQ!W211+DataQ!X211+DataQ!Y211 -> 11914 | FF20: =DataQ!J211+DataQ!Q211+DataQ!H211+DataQ!P211+DataQ!S211+DataQ!K211+DataQ!L211 -> 8905 | FG20: =DataQ!N211+DataQ!I211+DataQ!R211+DataQ!G211+DataQ!T211+DataQ!M211+DataQ!O211 -> 15971 | FH20: =DataQ!F211-'Chart Data'!FE20-'Chart Data'!FF20-'Chart Data'!FG20 -> -1 | FJ20: 45292 | FK20: =FE20-(AVERAGE(FE$20:FE$23)) -> -16.75 | FL20: =FF20-(AVERAGE(FF$20:FF$23)) -> -40.25 | FM20: =FG20-(AVERAGE(FG$20:FG$23)) -> 52.75 | FN20: =SUM(FK20:FM20) -> -4.25 | FP20: 42491 | FQ20: =100*((AVERAGE(HAVERM!AS442:AS444)/AVERAGE(HAVERM!AS439:AS441))-1) -> 0.32067047 | FR20: =100*((AVERAGE(HAVERM!AT442:AT444)/AVERAGE(HAVERM!AT439:AT441))-1) -> -0.17412858 | FS20: =100*((AVERAGE(HAVERM!AU442:AU444)/AVERAGE(HAVERM!AU439:AU441))-1) -> -2.5219814 | FT20: =100*((AVERAGE(HAVERM!AV442:AV444)/AVERAGE(HAVERM!AV439:AV441))-1) -> 0.30054835 | FU20: =100*((AVERAGE(HAVERM!AW442:AW444)/AVERAGE(HAVERM!AW439:AW441))-1) -> 1.7783215 | FV20: =100*((AVERAGE(HAVERM!AX442:AX444)/AVERAGE(HAVERM!AX439:AX441))-1) -> 0.66660573 | FW20: =100*((AVERAGE(HAVERM!AY442:AY444)/AVERAGE(HAVERM!AY439:AY441))-1) -> 1.2488362 | FX20: =100*((AVERAGE(HAVERM!AZ442:AZ444)/AVERAGE(HAVERM!AZ439:AZ441))-1) -> 0.27697237 | ... GI20: =100*((AVERAGE(HAVERM!BK442:BK444)/AVERAGE(HAVERM!BK439:BK441))-1) -> 1.1819997 | GJ20: =100*(((AVERAGE(HAVERM!BL442:BL444)+(AVERAGE(HAVERM!BM442:BM444)))/(AVERAGE(HAVERM!BL439:BL441)+AVERAGE(HAVERM!BM439:BM441))-1)) -> 0.016891103 | GL20: 42491 | GM20: =100*((AVERAGE(GX18:GX20)/AVERAGE(GX15:GX17))-1) -> -0.17412858 | GN20: =100*((AVERAGE(GY18:GY20)/AVERAGE(GY15:GY17))-1) -> 0.47658766 | GO20: =100*((AVERAGE(GZ18:GZ20)/AVERAGE(GZ15:GZ17))-1) -> 0.30054835 | GP20: =100*((AVERAGE(HA18:HA20)/AVERAGE(HA15:HA17))-1) -> 1.2488362 | GQ20: =100*((AVERAGE(HB18:HB20)/AVERAGE(HB15:HB17))-1) -> 0.4919628 | GR20: =100*((AVERAGE(HC18:HC20)/AVERAGE(HC15:HC17))-1) -> 0.72502391 | GS20: =100*((AVERAGE(HD18:HD20)/AVERAGE(HD15:HD17))-1) -> -0.21768252 | GT20: =100*((AVERAGE(HE18:HE20)/AVERAGE(HE15:HE17))-1) -> 0.048819719 | GU20: =100*((AVERAGE(HF18:HF20)/AVERAGE(HF15:HF17))-1) -> 0.19799221 | GW20: 42491 | GX20: =HAVERM!AT444 -> 180692 | GY20: =HAVERM!AU444+HAVERM!AW444+HAVERM!AX444 -> 312194 | GZ20: =HAVERM!AV444 -> 2392838 | HA20: =HAVERM!AY444 -> 1176364 | HB20: =HAVERM!AZ444+HAVERM!BB444 -> 6371106 | HC20: =HAVERM!BA444+HAVERM!BC444 -> 2357999 | HD20: =HAVERM!BD444 -> 1084713 | HE20: =HAVERM!BE444+HAVERM!BF444+HAVERM!BG444 -> 4794576 | HF20: =HAVERM!BH444+HAVERM!BI444+HAVERM!BJ444+HAVERM!BK444+HAVERM!BL444+HAVERM!BM444 -> 9203858 | HH20: Health | HI20: ='ASHE Annual pay All SIC'!D117 -> 28150 | HJ20: 0.14747605 | HL20: Health | HM20: ='ASHE Annual pay All SIC'!D117 -> 28150 | HN20: -0.55666667 | HP20: 2023 | HQ20: 15.363386 | HR20: 3.5101838 | HS20: =HQ20+HR20 -> 18.873569 | HU20: 2023 | HV20: 6380.8276 | HW20: 1457.8738 | HX20: =HV20+HW20 -> 7838.7014 | HZ20: 44927 | IA20: =HAVERQ!E180 -> 5689 | IB20: =HAVERQ!F180 -> 27784 | IC20: =DataQ!Z207-('Chart Data'!IA20+'Chart Data'!IB20) -> -148 | IE20: 44927 | IF20: =IA20-AVERAGE(IA$4:IA$7) -> 373.25 | IG20: =IB20-AVERAGE(IB$4:IB$7) -> 160 | II20: 44927 | IJ20: =100*(IA20/AVERAGE(IA$4:IA$7)) -> 107.02159 | IK20: =100*(IB20/AVERAGE(IB$4:IB$7)) -> 100.57921 | IM20: 44927 | IN20: =SUM(DataQ!U207:Y207) -> 11479 | IO20: =DataQ!F207-'Chart Data'!IN20 -> 25058 | IQ20: 44927 | IR20: =100*(IN20/AVERAGE(IN$4:IN$7)) -> 104.92448 | IS20: =100*(IO20/AVERAGE(IO$4:IO$7)) -> 101.75941
A21: 45017 | B21: =HAVERQ!E181-AVERAGE(HAVERQ!E$164:E$167) -> 412.25 | C21: =HAVERQ!F181-AVERAGE(HAVERQ!F$164:F$167) -> -77 | E21: 38078 | F21: =HAVERQ!P105 -> 1430 | G21: =HAVERQ!O105 -> 1569 | H21: =HAVERQ!N105 -> 1270 | I21: =HAVERQ!M105 -> 264 | J21: =HAVERQ!L105 -> 218 | K21: =HAVERQ!E105-F21-G21-H21-I21-J21 -> 794 | M21: 38078 | N21: =100*(F21/SUM($F21:$K21)) -> 25.788999 | O21: =100*(G21/SUM($F21:$K21)) -> 28.295762 | P21: =100*(H21/SUM($F21:$K21)) -> 22.903517 | Q21: =100*(I21/SUM($F21:$K21)) -> 4.761046 | R21: =100*(J21/SUM($F21:$K21)) -> 3.9314698 | S21: =100*(K21/SUM($F21:$K21)) -> 14.319206 | U21: 38078 | V21: =F21-AVERAGE(F$4:F$7) -> 220.75 | W21: =G21-AVERAGE(G$4:G$7) -> 129.25 | X21: =H21-AVERAGE(H$4:H$7) -> 91 | Y21: =I21-AVERAGE(I$4:I$7) -> 38.25 | Z21: =J21-AVERAGE(J$4:J$7) -> 1.75 | AA21: =K21-AVERAGE(K$4:K$7) -> 6.25 | AB21: =SUM(V21:AA21) -> 487.25 | AD21: 45017 | AE21: =HAVERQ!T181-AVERAGE(HAVERQ!T$164:T$167) -> -60.25 | AF21: =HAVERQ!U181-AVERAGE(HAVERQ!U$164:U$167) -> -9.25 | AG21: =HAVERQ!V181-AVERAGE(HAVERQ!V$164:V$167) -> -112.75 | AH21: =HAVERQ!W181-AVERAGE(HAVERQ!W$164:W$167) -> -13.75 | AI21: =HAVERQ!X181-AVERAGE(HAVERQ!X$164:X$167) -> 27.5 | AJ21: =HAVERQ!Y181-AVERAGE(HAVERQ!Y$164:Y$167) -> -74.25 | AK21: =HAVERQ!Z181-AVERAGE(HAVERQ!Z$164:Z$167) -> -291.5 | AL21: =HAVERQ!AA181-AVERAGE(HAVERQ!AA$164:AA$167) -> 46 | ... AV21: =HAVERQ!AK181-AVERAGE(HAVERQ!AK$164:AK$167) -> 13.25 | AW21: =AY21-AVERAGE(AY$4:AY$7) -> -59.5 | AY21: =HAVERQ!AL181+HAVERQ!AM181 -> 958 | BA21: 45017 | BB21: =BK21-AVERAGE(BK$4:BK$7) -> -60.25 | BC21: =BL21-AVERAGE(BL$4:BL$7) -> 4.5 | BD21: =BM21-AVERAGE(BM$4:BM$7) -> -112.75 | BE21: =BN21-AVERAGE(BN$4:BN$7) -> -74.25 | BF21: =BO21-AVERAGE(BO$4:BO$7) -> -81.5 | BG21: =BP21-AVERAGE(BP$4:BP$7) -> 184.75 | BH21: =BQ21-AVERAGE(BQ$4:BQ$7) -> 353.5 | BI21: =BR21-AVERAGE(BR$4:BR$7) -> 550.75 | BK21: =HAVERQ!T181 -> 338 | BL21: =HAVERQ!U181+HAVERQ!W181+HAVERQ!X181 -> 430 | BM21: =HAVERQ!V181 -> 2578 | BN21: =HAVERQ!Y181 -> 2259 | BO21: =HAVERQ!Z181+HAVERQ!AB181 -> 7423 | BP21: =HAVERQ!AA181+HAVERQ!AC181 -> 3491 | BQ21: =HAVERQ!AD181+HAVERQ!AE181+HAVERQ!AF181+HAVERQ!AG181 -> 8320 | BR21: =HAVERQ!AH181+HAVERQ!AI181+HAVERQ!AJ181+HAVERQ!AK181+HAVERQ!AL181+HAVERQ!AM181 -> 11491 | BS21: =HAVERQ!S181-SUM('Chart Data'!BK21:BR21) -> 0 | BU21: 35886 | BV21: =HAVERQ!T81 -> 475 | BW21: =HAVERQ!U81+HAVERQ!W81+HAVERQ!X81 -> 343 | BX21: =HAVERQ!V81 -> 4299 | BY21: =HAVERQ!Y81 -> 1869 | BZ21: =HAVERQ!Z81+HAVERQ!AB81 -> 6610 | CA21: =HAVERQ!AA81+HAVERQ!AC81 -> 2287 | CB21: =HAVERQ!AD81+HAVERQ!AE81+HAVERQ!AF81+HAVERQ!AG81 -> 5058 | CC21: =HAVERQ!AH81+HAVERQ!AI81+HAVERQ!AJ81+HAVERQ!AK81+HAVERQ!AL81+HAVERQ!AM81 -> 8007 | CD21: =HAVERQ!S81-SUM('Chart Data'!BV21:CC21) -> 0 | DB21: 37712 | DC21: =HAVERQ!BI101/HAVERQ!T101 -> 11.528736 | DD21: =HAVERQ!BJ101/HAVERQ!U101 -> 572.59016 | DE21: =HAVERQ!BK101/HAVERQ!V101 -> 12.710297 | DF21: =HAVERQ!BL101/HAVERQ!W101 -> 110.95699 | DG21: =HAVERQ!BM101/HAVERQ!X101 -> 47.36129 | DH21: =HAVERQ!BN101/HAVERQ!Y101 -> 15.956733 | DI21: =HAVERQ!BO101/HAVERQ!Z101 -> 10.081221 | DJ21: =HAVERQ!BP101/HAVERQ!AA101 -> 12.474234 | ... DT21: =HAVERQ!BZ101/HAVERQ!AK101 -> 10.056818 | DU21: =(HAVERQ!CA101+HAVERQ!CB101)/HAVERQ!AL101 -> 9.8407186 | DX21: =100*((DX20/DX19)-1) -> 0.78171651 | DY21: =100*((DY20/DY19)-1) -> -0.95024983 | DZ21: =100*((DZ20/DZ19)-1) -> 1.2832591 | EA21: =100*((EA20/EA19)-1) -> -0.57273957 | EB21: =100*((EB20/EB19)-1) -> 2.0859116 | EC21: =100*((EC20/EC19)-1) -> 0.4774187 | ED21: =100*((ED20/ED19)-1) -> 1.4609891 | EE21: =100*((EE20/EE19)-1) -> -0.63202753 | ... EQ21: =100*((EQ20/EQ19)-1) -> 2.1745113 | FD21: 45383 | FE21: =DataQ!U212+DataQ!V212+DataQ!W212+DataQ!X212+DataQ!Y212 -> 11937 | FF21: =DataQ!J212+DataQ!Q212+DataQ!H212+DataQ!P212+DataQ!S212+DataQ!K212+DataQ!L212 -> 8855 | FG21: =DataQ!N212+DataQ!I212+DataQ!R212+DataQ!G212+DataQ!T212+DataQ!M212+DataQ!O212 -> 15919 | FH21: =DataQ!F212-'Chart Data'!FE21-'Chart Data'!FF21-'Chart Data'!FG21 -> -1 | FJ21: 45383 | FK21: =FE21-(AVERAGE(FE$20:FE$23)) -> 6.25 | FL21: =FF21-(AVERAGE(FF$20:FF$23)) -> -90.25 | FM21: =FG21-(AVERAGE(FG$20:FG$23)) -> 0.75 | FN21: =SUM(FK21:FM21) -> -83.25 | FP21: 42522 | FQ21: =100*((AVERAGE(HAVERM!AS443:AS445)/AVERAGE(HAVERM!AS440:AS442))-1) -> 0.26699029 | FR21: =100*((AVERAGE(HAVERM!AT443:AT445)/AVERAGE(HAVERM!AT440:AT442))-1) -> -0.11989878 | FS21: =100*((AVERAGE(HAVERM!AU443:AU445)/AVERAGE(HAVERM!AU440:AU442))-1) -> -3.1611307 | FT21: =100*((AVERAGE(HAVERM!AV443:AV445)/AVERAGE(HAVERM!AV440:AV442))-1) -> 0.11110519 | FU21: =100*((AVERAGE(HAVERM!AW443:AW445)/AVERAGE(HAVERM!AW440:AW442))-1) -> 1.5132486 | FV21: =100*((AVERAGE(HAVERM!AX443:AX445)/AVERAGE(HAVERM!AX440:AX442))-1) -> 1.003552 | FW21: =100*((AVERAGE(HAVERM!AY443:AY445)/AVERAGE(HAVERM!AY440:AY442))-1) -> 0.74007349 | FX21: =100*((AVERAGE(HAVERM!AZ443:AZ445)/AVERAGE(HAVERM!AZ440:AZ442))-1) -> 0.27352665 | ... GI21: =100*((AVERAGE(HAVERM!BK443:BK445)/AVERAGE(HAVERM!BK440:BK442))-1) -> 1.0223033 | GJ21: =100*(((AVERAGE(HAVERM!BL443:BL445)+(AVERAGE(HAVERM!BM443:BM445)))/(AVERAGE(HAVERM!BL440:BL442)+AVERAGE(HAVERM!BM440:BM442))-1)) -> -0.3513924 | GL21: 42522 | GM21: =100*((AVERAGE(GX19:GX21)/AVERAGE(GX16:GX18))-1) -> -0.11989878 | GN21: =100*((AVERAGE(GY19:GY21)/AVERAGE(GY16:GY18))-1) -> 0.46521556 | GO21: =100*((AVERAGE(GZ19:GZ21)/AVERAGE(GZ16:GZ18))-1) -> 0.11110519 | GP21: =100*((AVERAGE(HA19:HA21)/AVERAGE(HA16:HA18))-1) -> 0.74007349 | GQ21: =100*((AVERAGE(HB19:HB21)/AVERAGE(HB16:HB18))-1) -> 0.44675357 | GR21: =100*((AVERAGE(HC19:HC21)/AVERAGE(HC16:HC18))-1) -> 0.74860676 | GS21: =100*((AVERAGE(HD19:HD21)/AVERAGE(HD16:HD18))-1) -> -0.10762006 | GT21: =100*((AVERAGE(HE19:HE21)/AVERAGE(HE16:HE18))-1) -> -0.13276454 | GU21: =100*((AVERAGE(HF19:HF21)/AVERAGE(HF16:HF18))-1) -> 0.25472361 | GW21: 42522 | GX21: =HAVERM!AT445 -> 181379 | GY21: =HAVERM!AU445+HAVERM!AW445+HAVERM!AX445 -> 312809 | GZ21: =HAVERM!AV445 -> 2393822 | HA21: =HAVERM!AY445 -> 1179431 | HB21: =HAVERM!AZ445+HAVERM!BB445 -> 6378946 | HC21: =HAVERM!BA445+HAVERM!BC445 -> 2362855 | HD21: =HAVERM!BD445 -> 1084464 | HE21: =HAVERM!BE445+HAVERM!BF445+HAVERM!BG445 -> 4799977 | HF21: =HAVERM!BH445+HAVERM!BI445+HAVERM!BJ445+HAVERM!BK445+HAVERM!BL445+HAVERM!BM445 -> 9219279 | HH21: Art & recreation | HI21: ='ASHE Annual pay All SIC'!D121 -> 23786 | HJ21: 0.19611278 | HL21: Art & recreation | HM21: ='ASHE Annual pay All SIC'!D121 -> 23786 | HN21: -0.52 | HP21: 2024 | HQ21: 15.668948 | HR21: 3.576772 | HS21: =HQ21+HR21 -> 19.24572 | HU21: 2024 | HV21: 6489.8948 | HW21: 1481.4571 | HX21: =HV21+HW21 -> 7971.3518 | HZ21: 45017 | IA21: =HAVERQ!E181 -> 5728 | IB21: =HAVERQ!F181 -> 27547 | IC21: =DataQ!Z208-('Chart Data'!IA21+'Chart Data'!IB21) -> 75 | IE21: 45017 | IF21: =IA21-AVERAGE(IA$4:IA$7) -> 412.25 | IG21: =IB21-AVERAGE(IB$4:IB$7) -> -77 | II21: 45017 | IJ21: =100*(IA21/AVERAGE(IA$4:IA$7)) -> 107.75526 | IK21: =100*(IB21/AVERAGE(IB$4:IB$7)) -> 99.721257 | IM21: 45017 | IN21: =SUM(DataQ!U208:Y208) -> 11491 | IO21: =DataQ!F208-'Chart Data'!IN21 -> 24839 | IQ21: 45017 | IR21: =100*(IN21/AVERAGE(IN$4:IN$7)) -> 105.03416 | IS21: =100*(IO21/AVERAGE(IO$4:IO$7)) -> 100.87006
A22: 45108 | B22: =HAVERQ!E182-AVERAGE(HAVERQ!E$164:E$167) -> 461.25 | C22: =HAVERQ!F182-AVERAGE(HAVERQ!F$164:F$167) -> -30 | E22: 38169 | F22: =HAVERQ!P106 -> 1443 | G22: =HAVERQ!O106 -> 1573 | H22: =HAVERQ!N106 -> 1279 | I22: =HAVERQ!M106 -> 265 | J22: =HAVERQ!L106 -> 216 | K22: =HAVERQ!E106-F22-G22-H22-I22-J22 -> 801 | M22: 38169 | N22: =100*(F22/SUM($F22:$K22)) -> 25.874126 | O22: =100*(G22/SUM($F22:$K22)) -> 28.205128 | P22: =100*(H22/SUM($F22:$K22)) -> 22.933477 | Q22: =100*(I22/SUM($F22:$K22)) -> 4.7516586 | R22: =100*(J22/SUM($F22:$K22)) -> 3.87305 | S22: =100*(K22/SUM($F22:$K22)) -> 14.362561 | U22: 38169 | V22: =F22-AVERAGE(F$4:F$7) -> 233.75 | W22: =G22-AVERAGE(G$4:G$7) -> 133.25 | X22: =H22-AVERAGE(H$4:H$7) -> 100 | Y22: =I22-AVERAGE(I$4:I$7) -> 39.25 | Z22: =J22-AVERAGE(J$4:J$7) -> -0.25 | AA22: =K22-AVERAGE(K$4:K$7) -> 13.25 | AB22: =SUM(V22:AA22) -> 519.25 | AD22: 45108 | AE22: =HAVERQ!T182-AVERAGE(HAVERQ!T$164:T$167) -> -22.25 | AF22: =HAVERQ!U182-AVERAGE(HAVERQ!U$164:U$167) -> -10.25 | AG22: =HAVERQ!V182-AVERAGE(HAVERQ!V$164:V$167) -> -91.75 | AH22: =HAVERQ!W182-AVERAGE(HAVERQ!W$164:W$167) -> -15.75 | AI22: =HAVERQ!X182-AVERAGE(HAVERQ!X$164:X$167) -> 19.5 | AJ22: =HAVERQ!Y182-AVERAGE(HAVERQ!Y$164:Y$167) -> -85.25 | AK22: =HAVERQ!Z182-AVERAGE(HAVERQ!Z$164:Z$167) -> -249.5 | AL22: =HAVERQ!AA182-AVERAGE(HAVERQ!AA$164:AA$167) -> 47 | ... AV22: =HAVERQ!AK182-AVERAGE(HAVERQ!AK$164:AK$167) -> 40.25 | AW22: =AY22-AVERAGE(AY$4:AY$7) -> -47.5 | AY22: =HAVERQ!AL182+HAVERQ!AM182 -> 970 | BA22: 45108 | BB22: =BK22-AVERAGE(BK$4:BK$7) -> -22.25 | BC22: =BL22-AVERAGE(BL$4:BL$7) -> -6.5 | BD22: =BM22-AVERAGE(BM$4:BM$7) -> -91.75 | BE22: =BN22-AVERAGE(BN$4:BN$7) -> -85.25 | BF22: =BO22-AVERAGE(BO$4:BO$7) -> -70.5 | BG22: =BP22-AVERAGE(BP$4:BP$7) -> 131.75 | BH22: =BQ22-AVERAGE(BQ$4:BQ$7) -> 364.5 | BI22: =BR22-AVERAGE(BR$4:BR$7) -> 628.75 | BK22: =HAVERQ!T182 -> 376 | BL22: =HAVERQ!U182+HAVERQ!W182+HAVERQ!X182 -> 419 | BM22: =HAVERQ!V182 -> 2599 | BN22: =HAVERQ!Y182 -> 2248 | BO22: =HAVERQ!Z182+HAVERQ!AB182 -> 7434 | BP22: =HAVERQ!AA182+HAVERQ!AC182 -> 3438 | BQ22: =HAVERQ!AD182+HAVERQ!AE182+HAVERQ!AF182+HAVERQ!AG182 -> 8331 | BR22: =HAVERQ!AH182+HAVERQ!AI182+HAVERQ!AJ182+HAVERQ!AK182+HAVERQ!AL182+HAVERQ!AM182 -> 11569 | BS22: =HAVERQ!S182-SUM('Chart Data'!BK22:BR22) -> 1 | BU22: 35977 | BV22: =HAVERQ!T82 -> 446 | BW22: =HAVERQ!U82+HAVERQ!W82+HAVERQ!X82 -> 345 | BX22: =HAVERQ!V82 -> 4295 | BY22: =HAVERQ!Y82 -> 1887 | BZ22: =HAVERQ!Z82+HAVERQ!AB82 -> 6679 | CA22: =HAVERQ!AA82+HAVERQ!AC82 -> 2300 | CB22: =HAVERQ!AD82+HAVERQ!AE82+HAVERQ!AF82+HAVERQ!AG82 -> 5091 | CC22: =HAVERQ!AH82+HAVERQ!AI82+HAVERQ!AJ82+HAVERQ!AK82+HAVERQ!AL82+HAVERQ!AM82 -> 8006 | CD22: =HAVERQ!S82-SUM('Chart Data'!BV22:CC22) -> 0 | DB22: 37803 | DC22: =HAVERQ!BI102/HAVERQ!T102 -> 10.542005 | DD22: =HAVERQ!BJ102/HAVERQ!U102 -> 565.86885 | DE22: =HAVERQ!BK102/HAVERQ!V102 -> 12.930964 | DF22: =HAVERQ!BL102/HAVERQ!W102 -> 115.77174 | DG22: =HAVERQ!BM102/HAVERQ!X102 -> 46.389937 | DH22: =HAVERQ!BN102/HAVERQ!Y102 -> 15.76901 | DI22: =HAVERQ!BO102/HAVERQ!Z102 -> 10.068349 | DJ22: =HAVERQ!BP102/HAVERQ!AA102 -> 12.544755 | ... DT22: =HAVERQ!BZ102/HAVERQ!AK102 -> 10.118372 | DU22: =(HAVERQ!CA102+HAVERQ!CB102)/HAVERQ!AL102 -> 9.6730083 | FD22: 45474 | FE22: =DataQ!U213+DataQ!V213+DataQ!W213+DataQ!X213+DataQ!Y213 -> 11905 | FF22: =DataQ!J213+DataQ!Q213+DataQ!H213+DataQ!P213+DataQ!S213+DataQ!K213+DataQ!L213 -> 8993 | FG22: =DataQ!N213+DataQ!I213+DataQ!R213+DataQ!G213+DataQ!T213+DataQ!M213+DataQ!O213 -> 15870 | FH22: =DataQ!F213-'Chart Data'!FE22-'Chart Data'!FF22-'Chart Data'!FG22 -> -2 | FJ22: 45474 | FK22: =FE22-(AVERAGE(FE$20:FE$23)) -> -25.75 | FL22: =FF22-(AVERAGE(FF$20:FF$23)) -> 47.75 | FM22: =FG22-(AVERAGE(FG$20:FG$23)) -> -48.25 | FN22: =SUM(FK22:FM22) -> -26.25 | FP22: 42552 | FQ22: =100*((AVERAGE(HAVERM!AS444:AS446)/AVERAGE(HAVERM!AS441:AS443))-1) -> 0.35977541 | FR22: =100*((AVERAGE(HAVERM!AT444:AT446)/AVERAGE(HAVERM!AT441:AT443))-1) -> 0.0040472051 | FS22: =100*((AVERAGE(HAVERM!AU444:AU446)/AVERAGE(HAVERM!AU441:AU443))-1) -> -2.759886 | FT22: =100*((AVERAGE(HAVERM!AV444:AV446)/AVERAGE(HAVERM!AV441:AV443))-1) -> 0.18560724 | FU22: =100*((AVERAGE(HAVERM!AW444:AW446)/AVERAGE(HAVERM!AW441:AW443))-1) -> 1.3000152 | FV22: =100*((AVERAGE(HAVERM!AX444:AX446)/AVERAGE(HAVERM!AX441:AX443))-1) -> 1.1760686 | FW22: =100*((AVERAGE(HAVERM!AY444:AY446)/AVERAGE(HAVERM!AY441:AY443))-1) -> 0.82232318 | FX22: =100*((AVERAGE(HAVERM!AZ444:AZ446)/AVERAGE(HAVERM!AZ441:AZ443))-1) -> 0.2633339 | ... GI22: =100*((AVERAGE(HAVERM!BK444:BK446)/AVERAGE(HAVERM!BK441:BK443))-1) -> 0.80106272 | GJ22: =100*(((AVERAGE(HAVERM!BL444:BL446)+(AVERAGE(HAVERM!BM444:BM446)))/(AVERAGE(HAVERM!BL441:BL443)+AVERAGE(HAVERM!BM441:BM443))-1)) -> -0.27283918 | GL22: 42552 | GM22: =100*((AVERAGE(GX20:GX22)/AVERAGE(GX17:GX19))-1) -> 0.0040472051 | GN22: =100*((AVERAGE(GY20:GY22)/AVERAGE(GY17:GY19))-1) -> 0.5624708 | GO22: =100*((AVERAGE(GZ20:GZ22)/AVERAGE(GZ17:GZ19))-1) -> 0.18560724 | GP22: =100*((AVERAGE(HA20:HA22)/AVERAGE(HA17:HA19))-1) -> 0.82232318 | GQ22: =100*((AVERAGE(HB20:HB22)/AVERAGE(HB17:HB19))-1) -> 0.41250321 | GR22: =100*((AVERAGE(HC20:HC22)/AVERAGE(HC17:HC19))-1) -> 0.82472945 | GS22: =100*((AVERAGE(HD20:HD22)/AVERAGE(HD17:HD19))-1) -> -0.082179114 | GT22: =100*((AVERAGE(HE20:HE22)/AVERAGE(HE17:HE19))-1) -> 0.057607206 | GU22: =100*((AVERAGE(HF20:HF22)/AVERAGE(HF17:HF19))-1) -> 0.40122605 | GW22: 42552 | GX22: =HAVERM!AT446 -> 181536 | GY22: =HAVERM!AU446+HAVERM!AW446+HAVERM!AX446 -> 313450 | GZ22: =HAVERM!AV446 -> 2394468 | HA22: =HAVERM!AY446 -> 1181408 | HB22: =HAVERM!AZ446+HAVERM!BB446 -> 6385623 | HC22: =HAVERM!BA446+HAVERM!BC446 -> 2367677 | HD22: =HAVERM!BD446 -> 1083233 | HE22: =HAVERM!BE446+HAVERM!BF446+HAVERM!BG446 -> 4802561 | HF22: =HAVERM!BH446+HAVERM!BI446+HAVERM!BJ446+HAVERM!BK446+HAVERM!BL446+HAVERM!BM446 -> 9242211 | HH22: Other services | HI22: ='ASHE Annual pay All SIC'!D126 -> 25747 | HJ22: -1.4157511 | HL22: Other services | HM22: ='ASHE Annual pay All SIC'!D126 -> 25747 | HN22: -1.06 | HP22: 2025 | HQ22: 16.065318 | HR22: 3.7177189 | HS22: =HQ22+HR22 -> 19.783037 | HU22: 2025 | HV22: 6710.5817 | HW22: 1552.9139 | HX22: =HV22+HW22 -> 8263.4956 | HZ22: 45108 | IA22: =HAVERQ!E182 -> 5777 | IB22: =HAVERQ!F182 -> 27594 | IC22: =DataQ!Z209-('Chart Data'!IA22+'Chart Data'!IB22) -> -21 | IE22: 45108 | IF22: =IA22-AVERAGE(IA$4:IA$7) -> 461.25 | IG22: =IB22-AVERAGE(IB$4:IB$7) -> -30 | II22: 45108 | IJ22: =100*(IA22/AVERAGE(IA$4:IA$7)) -> 108.67704 | IK22: =100*(IB22/AVERAGE(IB$4:IB$7)) -> 99.891399 | IM22: 45108 | IN22: =SUM(DataQ!U209:Y209) -> 11569 | IO22: =DataQ!F209-'Chart Data'!IN22 -> 24846 | IQ22: 45108 | IR22: =100*(IN22/AVERAGE(IN$4:IN$7)) -> 105.74713 | IS22: =100*(IO22/AVERAGE(IO$4:IO$7)) -> 100.89849
A23: 45200 | B23: =HAVERQ!E183-AVERAGE(HAVERQ!E$164:E$167) -> 493.25 | C23: =HAVERQ!F183-AVERAGE(HAVERQ!F$164:F$167) -> -119 | E23: 38261 | F23: =HAVERQ!P107 -> 1456 | G23: =HAVERQ!O107 -> 1576 | H23: =HAVERQ!N107 -> 1278 | I23: =HAVERQ!M107 -> 267 | J23: =HAVERQ!L107 -> 214 | K23: =HAVERQ!E107-F23-G23-H23-I23-J23 -> 806 | M23: 38261 | N23: =100*(F23/SUM($F23:$K23)) -> 26.013936 | O23: =100*(G23/SUM($F23:$K23)) -> 28.157942 | P23: =100*(H23/SUM($F23:$K23)) -> 22.833661 | Q23: =100*(I23/SUM($F23:$K23)) -> 4.7704127 | R23: =100*(J23/SUM($F23:$K23)) -> 3.8234769 | S23: =100*(K23/SUM($F23:$K23)) -> 14.400572 | U23: 38261 | V23: =F23-AVERAGE(F$4:F$7) -> 246.75 | W23: =G23-AVERAGE(G$4:G$7) -> 136.25 | X23: =H23-AVERAGE(H$4:H$7) -> 99 | Y23: =I23-AVERAGE(I$4:I$7) -> 41.25 | Z23: =J23-AVERAGE(J$4:J$7) -> -2.25 | AA23: =K23-AVERAGE(K$4:K$7) -> 18.25 | AB23: =SUM(V23:AA23) -> 539.25 | AD23: 45200 | AE23: =HAVERQ!T183-AVERAGE(HAVERQ!T$164:T$167) -> 3.75 | AF23: =HAVERQ!U183-AVERAGE(HAVERQ!U$164:U$167) -> -10.25 | AG23: =HAVERQ!V183-AVERAGE(HAVERQ!V$164:V$167) -> -100.75 | AH23: =HAVERQ!W183-AVERAGE(HAVERQ!W$164:W$167) -> -10.75 | AI23: =HAVERQ!X183-AVERAGE(HAVERQ!X$164:X$167) -> 17.5 | AJ23: =HAVERQ!Y183-AVERAGE(HAVERQ!Y$164:Y$167) -> -120.25 | AK23: =HAVERQ!Z183-AVERAGE(HAVERQ!Z$164:Z$167) -> -232.5 | AL23: =HAVERQ!AA183-AVERAGE(HAVERQ!AA$164:AA$167) -> 94 | ... AV23: =HAVERQ!AK183-AVERAGE(HAVERQ!AK$164:AK$167) -> 50.25 | AW23: =AY23-AVERAGE(AY$4:AY$7) -> -68.5 | AY23: =HAVERQ!AL183+HAVERQ!AM183 -> 949 | BA23: 45200 | BB23: =BK23-AVERAGE(BK$4:BK$7) -> 3.75 | BC23: =BL23-AVERAGE(BL$4:BL$7) -> -3.5 | BD23: =BM23-AVERAGE(BM$4:BM$7) -> -100.75 | BE23: =BN23-AVERAGE(BN$4:BN$7) -> -120.25 | BF23: =BO23-AVERAGE(BO$4:BO$7) -> -95.5 | BG23: =BP23-AVERAGE(BP$4:BP$7) -> 217.75 | BH23: =BQ23-AVERAGE(BQ$4:BQ$7) -> 308.5 | BI23: =BR23-AVERAGE(BR$4:BR$7) -> 730.75 | BK23: =HAVERQ!T183 -> 402 | BL23: =HAVERQ!U183+HAVERQ!W183+HAVERQ!X183 -> 422 | BM23: =HAVERQ!V183 -> 2590 | BN23: =HAVERQ!Y183 -> 2213 | BO23: =HAVERQ!Z183+HAVERQ!AB183 -> 7409 | BP23: =HAVERQ!AA183+HAVERQ!AC183 -> 3524 | BQ23: =HAVERQ!AD183+HAVERQ!AE183+HAVERQ!AF183+HAVERQ!AG183 -> 8275 | BR23: =HAVERQ!AH183+HAVERQ!AI183+HAVERQ!AJ183+HAVERQ!AK183+HAVERQ!AL183+HAVERQ!AM183 -> 11671 | BS23: =HAVERQ!S183-SUM('Chart Data'!BK23:BR23) -> -3 | BU23: 36069 | BV23: =HAVERQ!T83 -> 428 | BW23: =HAVERQ!U83+HAVERQ!W83+HAVERQ!X83 -> 349 | BX23: =HAVERQ!V83 -> 4230 | BY23: =HAVERQ!Y83 -> 1918 | BZ23: =HAVERQ!Z83+HAVERQ!AB83 -> 6678 | CA23: =HAVERQ!AA83+HAVERQ!AC83 -> 2357 | CB23: =HAVERQ!AD83+HAVERQ!AE83+HAVERQ!AF83+HAVERQ!AG83 -> 5143 | CC23: =HAVERQ!AH83+HAVERQ!AI83+HAVERQ!AJ83+HAVERQ!AK83+HAVERQ!AL83+HAVERQ!AM83 -> 8110 | CD23: =HAVERQ!S83-SUM('Chart Data'!BV23:CC23) -> 0 | DB23: 37895 | DC23: =HAVERQ!BI103/HAVERQ!T103 -> 10.142857 | DD23: =HAVERQ!BJ103/HAVERQ!U103 -> 564.62295 | DE23: =HAVERQ!BK103/HAVERQ!V103 -> 13.371684 | DF23: =HAVERQ!BL103/HAVERQ!W103 -> 118.18889 | DG23: =HAVERQ!BM103/HAVERQ!X103 -> 45.826923 | DH23: =HAVERQ!BN103/HAVERQ!Y103 -> 15.800955 | DI23: =HAVERQ!BO103/HAVERQ!Z103 -> 9.9593496 | DJ23: =HAVERQ!BP103/HAVERQ!AA103 -> 12.545518 | ... DT23: =HAVERQ!BZ103/HAVERQ!AK103 -> 10.254878 | DU23: =(HAVERQ!CA103+HAVERQ!CB103)/HAVERQ!AL103 -> 9.3701068 | FD23: 45566 | FE23: =DataQ!U214+DataQ!V214+DataQ!W214+DataQ!X214+DataQ!Y214 -> 11967 | FF23: =DataQ!J214+DataQ!Q214+DataQ!H214+DataQ!P214+DataQ!S214+DataQ!K214+DataQ!L214 -> 9028 | FG23: =DataQ!N214+DataQ!I214+DataQ!R214+DataQ!G214+DataQ!T214+DataQ!M214+DataQ!O214 -> 15913 | FH23: =DataQ!F214-'Chart Data'!FE23-'Chart Data'!FF23-'Chart Data'!FG23 -> -2 | FJ23: 45566 | FK23: =FE23-(AVERAGE(FE$20:FE$23)) -> 36.25 | FL23: =FF23-(AVERAGE(FF$20:FF$23)) -> 82.75 | FM23: =FG23-(AVERAGE(FG$20:FG$23)) -> -5.25 | FN23: =SUM(FK23:FM23) -> 113.75 | FP23: 42583 | FQ23: =100*((AVERAGE(HAVERM!AS445:AS447)/AVERAGE(HAVERM!AS442:AS444))-1) -> 0.3661353 | FR23: =100*((AVERAGE(HAVERM!AT445:AT447)/AVERAGE(HAVERM!AT442:AT444))-1) -> 0.34315459 | FS23: =100*((AVERAGE(HAVERM!AU445:AU447)/AVERAGE(HAVERM!AU442:AU444))-1) -> -2.3444333 | FT23: =100*((AVERAGE(HAVERM!AV445:AV447)/AVERAGE(HAVERM!AV442:AV444))-1) -> 0.21959389 | FU23: =100*((AVERAGE(HAVERM!AW445:AW447)/AVERAGE(HAVERM!AW442:AW444))-1) -> 1.2320654 | FV23: =100*((AVERAGE(HAVERM!AX445:AX447)/AVERAGE(HAVERM!AX442:AX444))-1) -> 1.1498072 | FW23: =100*((AVERAGE(HAVERM!AY445:AY447)/AVERAGE(HAVERM!AY442:AY444))-1) -> 0.78862493 | FX23: =100*((AVERAGE(HAVERM!AZ445:AZ447)/AVERAGE(HAVERM!AZ442:AZ444))-1) -> 0.26438943 | ... GI23: =100*((AVERAGE(HAVERM!BK445:BK447)/AVERAGE(HAVERM!BK442:BK444))-1) -> 0.71661583 | GJ23: =100*(((AVERAGE(HAVERM!BL445:BL447)+(AVERAGE(HAVERM!BM445:BM447)))/(AVERAGE(HAVERM!BL442:BL444)+AVERAGE(HAVERM!BM442:BM444))-1)) -> 0.56241675 | GL23: 42583 | GM23: =100*((AVERAGE(GX21:GX23)/AVERAGE(GX18:GX20))-1) -> 0.34315459 | GN23: =100*((AVERAGE(GY21:GY23)/AVERAGE(GY18:GY20))-1) -> 0.60323193 | GO23: =100*((AVERAGE(GZ21:GZ23)/AVERAGE(GZ18:GZ20))-1) -> 0.21959389 | GP23: =100*((AVERAGE(HA21:HA23)/AVERAGE(HA18:HA20))-1) -> 0.78862493 | GQ23: =100*((AVERAGE(HB21:HB23)/AVERAGE(HB18:HB20))-1) -> 0.40315194 | GR23: =100*((AVERAGE(HC21:HC23)/AVERAGE(HC18:HC20))-1) -> 0.79500889 | GS23: =100*((AVERAGE(HD21:HD23)/AVERAGE(HD18:HD20))-1) -> -0.070198862 | GT23: =100*((AVERAGE(HE21:HE23)/AVERAGE(HE18:HE20))-1) -> 0.15097599 | GU23: =100*((AVERAGE(HF21:HF23)/AVERAGE(HF18:HF20))-1) -> 0.37121713 | GW23: 42583 | GX23: =HAVERM!AT447 -> 181852 | GY23: =HAVERM!AU447+HAVERM!AW447+HAVERM!AX447 -> 314178 | GZ23: =HAVERM!AV447 -> 2398878 | HA23: =HAVERM!AY447 -> 1185055 | HB23: =HAVERM!AZ447+HAVERM!BB447 -> 6397485 | HC23: =HAVERM!BA447+HAVERM!BC447 -> 2374359 | HD23: =HAVERM!BD447 -> 1083633 | HE23: =HAVERM!BE447+HAVERM!BF447+HAVERM!BG447 -> 4803585 | HF23: =HAVERM!BH447+HAVERM!BI447+HAVERM!BJ447+HAVERM!BK447+HAVERM!BL447+HAVERM!BM447 -> 9216651 | HP23: 2026 | HQ23: 16.058467 | HR23: 3.8041097 | HS23: =HQ23+HR23 -> 19.862577 | HU23: 2026 | HV23: 6809.606 | HW23: 1613.1358 | HX23: =HV23+HW23 -> 8422.7418 | HZ23: 45200 | IA23: =HAVERQ!E183 -> 5809 | IB23: =HAVERQ!F183 -> 27505 | IC23: =DataQ!Z210-('Chart Data'!IA23+'Chart Data'!IB23) -> 65 | IE23: 45200 | IF23: =IA23-AVERAGE(IA$4:IA$7) -> 493.25 | IG23: =IB23-AVERAGE(IB$4:IB$7) -> -119 | II23: 45200 | IJ23: =100*(IA23/AVERAGE(IA$4:IA$7)) -> 109.27903 | IK23: =100*(IB23/AVERAGE(IB$4:IB$7)) -> 99.569215 | IM23: 45200 | IN23: =SUM(DataQ!U210:Y210) -> 11671 | IO23: =DataQ!F210-'Chart Data'!IN23 -> 24832 | IQ23: 45200 | IR23: =100*(IN23/AVERAGE(IN$4:IN$7)) -> 106.67946 | IS23: =100*(IO23/AVERAGE(IO$4:IO$7)) -> 100.84163
A24: 45292 | B24: =HAVERQ!E184-AVERAGE(HAVERQ!E$164:E$167) -> 520.25 | C24: =HAVERQ!F184-AVERAGE(HAVERQ!F$164:F$167) -> -116 | E24: 38353 | F24: =HAVERQ!P108 -> 1466 | G24: =HAVERQ!O108 -> 1581 | H24: =HAVERQ!N108 -> 1280 | I24: =HAVERQ!M108 -> 271 | J24: =HAVERQ!L108 -> 212 | K24: =HAVERQ!E108-F24-G24-H24-I24-J24 -> 805 | M24: 38353 | N24: =100*(F24/SUM($F24:$K24)) -> 26.108638 | O24: =100*(G24/SUM($F24:$K24)) -> 28.156723 | P24: =100*(H24/SUM($F24:$K24)) -> 22.796082 | Q24: =100*(I24/SUM($F24:$K24)) -> 4.826358 | R24: =100*(J24/SUM($F24:$K24)) -> 3.7756011 | S24: =100*(K24/SUM($F24:$K24)) -> 14.336598 | U24: 38353 | V24: =F24-AVERAGE(F$4:F$7) -> 256.75 | W24: =G24-AVERAGE(G$4:G$7) -> 141.25 | X24: =H24-AVERAGE(H$4:H$7) -> 101 | Y24: =I24-AVERAGE(I$4:I$7) -> 45.25 | Z24: =J24-AVERAGE(J$4:J$7) -> -4.25 | AA24: =K24-AVERAGE(K$4:K$7) -> 17.25 | AB24: =SUM(V24:AA24) -> 557.25 | AD24: 45292 | AE24: =HAVERQ!T184-AVERAGE(HAVERQ!T$164:T$167) -> -27.25 | AF24: =HAVERQ!U184-AVERAGE(HAVERQ!U$164:U$167) -> -13.25 | AG24: =HAVERQ!V184-AVERAGE(HAVERQ!V$164:V$167) -> -110.75 | AH24: =HAVERQ!W184-AVERAGE(HAVERQ!W$164:W$167) -> -10.75 | AI24: =HAVERQ!X184-AVERAGE(HAVERQ!X$164:X$167) -> 23.5 | AJ24: =HAVERQ!Y184-AVERAGE(HAVERQ!Y$164:Y$167) -> -101.25 | AK24: =HAVERQ!Z184-AVERAGE(HAVERQ!Z$164:Z$167) -> -251.5 | AL24: =HAVERQ!AA184-AVERAGE(HAVERQ!AA$164:AA$167) -> 95 | ... AV24: =HAVERQ!AK184-AVERAGE(HAVERQ!AK$164:AK$167) -> 85.25 | AW24: =AY24-AVERAGE(AY$4:AY$7) -> 20.5 | AY24: =HAVERQ!AL184+HAVERQ!AM184 -> 1038 | BA24: 45292 | BB24: =BK24-AVERAGE(BK$4:BK$7) -> -27.25 | BC24: =BL24-AVERAGE(BL$4:BL$7) -> -0.5 | BD24: =BM24-AVERAGE(BM$4:BM$7) -> -110.75 | BE24: =BN24-AVERAGE(BN$4:BN$7) -> -101.25 | BF24: =BO24-AVERAGE(BO$4:BO$7) -> -87.5 | BG24: =BP24-AVERAGE(BP$4:BP$7) -> 209.75 | BH24: =BQ24-AVERAGE(BQ$4:BQ$7) -> 368.5 | BI24: =BR24-AVERAGE(BR$4:BR$7) -> 973.75 | BK24: =HAVERQ!T184 -> 371 | BL24: =HAVERQ!U184+HAVERQ!W184+HAVERQ!X184 -> 425 | BM24: =HAVERQ!V184 -> 2580 | BN24: =HAVERQ!Y184 -> 2232 | BO24: =HAVERQ!Z184+HAVERQ!AB184 -> 7417 | BP24: =HAVERQ!AA184+HAVERQ!AC184 -> 3516 | BQ24: =HAVERQ!AD184+HAVERQ!AE184+HAVERQ!AF184+HAVERQ!AG184 -> 8335 | BR24: =HAVERQ!AH184+HAVERQ!AI184+HAVERQ!AJ184+HAVERQ!AK184+HAVERQ!AL184+HAVERQ!AM184 -> 11914 | BS24: =HAVERQ!S184-SUM('Chart Data'!BK24:BR24) -> -1 | BU24: 36161 | BV24: =HAVERQ!T84 -> 436 | BW24: =HAVERQ!U84+HAVERQ!W84+HAVERQ!X84 -> 343 | BX24: =HAVERQ!V84 -> 4171 | BY24: =HAVERQ!Y84 -> 1884 | BZ24: =HAVERQ!Z84+HAVERQ!AB84 -> 6660 | CA24: =HAVERQ!AA84+HAVERQ!AC84 -> 2373 | CB24: =HAVERQ!AD84+HAVERQ!AE84+HAVERQ!AF84+HAVERQ!AG84 -> 5161 | CC24: =HAVERQ!AH84+HAVERQ!AI84+HAVERQ!AJ84+HAVERQ!AK84+HAVERQ!AL84+HAVERQ!AM84 -> 8208 | CD24: =HAVERQ!S84-SUM('Chart Data'!BV24:CC24) -> 1 | DB24: 37987 | DC24: =HAVERQ!BI104/HAVERQ!T104 -> 10.252101 | DD24: =HAVERQ!BJ104/HAVERQ!U104 -> 583.51724 | DE24: =HAVERQ!BK104/HAVERQ!V104 -> 13.781533 | DF24: =HAVERQ!BL104/HAVERQ!W104 -> 116.28409 | DG24: =HAVERQ!BM104/HAVERQ!X104 -> 44.477419 | DH24: =HAVERQ!BN104/HAVERQ!Y104 -> 15.972525 | DI24: =HAVERQ!BO104/HAVERQ!Z104 -> 10.096742 | DJ24: =HAVERQ!BP104/HAVERQ!AA104 -> 12.800704 | ... DT24: =HAVERQ!BZ104/HAVERQ!AK104 -> 10.28519 | DU24: =(HAVERQ!CA104+HAVERQ!CB104)/HAVERQ!AL104 -> 9.7284689 | FD24: 45658 | FE24: =DataQ!U215+DataQ!V215+DataQ!W215+DataQ!X215+DataQ!Y215 -> 12183 | FF24: =DataQ!J215+DataQ!Q215+DataQ!H215+DataQ!P215+DataQ!S215+DataQ!K215+DataQ!L215 -> 8986 | FG24: =DataQ!N215+DataQ!I215+DataQ!R215+DataQ!G215+DataQ!T215+DataQ!M215+DataQ!O215 -> 15924 | FH24: =DataQ!F215-'Chart Data'!FE24-'Chart Data'!FF24-'Chart Data'!FG24 -> 1 | FJ24: 45658 | FK24: =FE24-(AVERAGE(FE$20:FE$23)) -> 252.25 | FL24: =FF24-(AVERAGE(FF$20:FF$23)) -> 40.75 | FM24: =FG24-(AVERAGE(FG$20:FG$23)) -> 5.75 | FN24: =SUM(FK24:FM24) -> 298.75 | FP24: 42614 | FQ24: =100*((AVERAGE(HAVERM!AS446:AS448)/AVERAGE(HAVERM!AS443:AS445))-1) -> 0.34811181 | FR24: =100*((AVERAGE(HAVERM!AT446:AT448)/AVERAGE(HAVERM!AT443:AT445))-1) -> 0.49490003 | FS24: =100*((AVERAGE(HAVERM!AU446:AU448)/AVERAGE(HAVERM!AU443:AU445))-1) -> -1.8129979 | FT24: =100*((AVERAGE(HAVERM!AV446:AV448)/AVERAGE(HAVERM!AV443:AV445))-1) -> 0.21896802 | FU24: =100*((AVERAGE(HAVERM!AW446:AW448)/AVERAGE(HAVERM!AW443:AW445))-1) -> 1.237213 | FV24: =100*((AVERAGE(HAVERM!AX446:AX448)/AVERAGE(HAVERM!AX443:AX445))-1) -> 1.0829353 | FW24: =100*((AVERAGE(HAVERM!AY446:AY448)/AVERAGE(HAVERM!AY443:AY445))-1) -> 0.75895353 | FX24: =100*((AVERAGE(HAVERM!AZ446:AZ448)/AVERAGE(HAVERM!AZ443:AZ445))-1) -> 0.2773581 | ... GI24: =100*((AVERAGE(HAVERM!BK446:BK448)/AVERAGE(HAVERM!BK443:BK445))-1) -> 0.74991431 | GJ24: =100*(((AVERAGE(HAVERM!BL446:BL448)+(AVERAGE(HAVERM!BM446:BM448)))/(AVERAGE(HAVERM!BL443:BL445)+AVERAGE(HAVERM!BM443:BM445))-1)) -> 1.2463672 | GL24: 42614 | GM24: =100*((AVERAGE(GX22:GX24)/AVERAGE(GX19:GX21))-1) -> 0.49490003 | GN24: =100*((AVERAGE(GY22:GY24)/AVERAGE(GY19:GY21))-1) -> 0.66357532 | GO24: =100*((AVERAGE(GZ22:GZ24)/AVERAGE(GZ19:GZ21))-1) -> 0.21896802 | GP24: =100*((AVERAGE(HA22:HA24)/AVERAGE(HA19:HA21))-1) -> 0.75895353 | GQ24: =100*((AVERAGE(HB22:HB24)/AVERAGE(HB19:HB21))-1) -> 0.43713236 | GR24: =100*((AVERAGE(HC22:HC24)/AVERAGE(HC19:HC21))-1) -> 0.72859961 | GS24: =100*((AVERAGE(HD22:HD24)/AVERAGE(HD19:HD21))-1) -> -0.1800107 | GT24: =100*((AVERAGE(HE22:HE24)/AVERAGE(HE19:HE21))-1) -> 0.25398875 | GU24: =100*((AVERAGE(HF22:HF24)/AVERAGE(HF19:HF21))-1) -> 0.2678326 | GW24: 42614 | GX24: =HAVERM!AT448 -> 182440 | GY24: =HAVERM!AU448+HAVERM!AW448+HAVERM!AX448 -> 315180 | GZ24: =HAVERM!AV448 -> 2399216 | HA24: =HAVERM!AY448 -> 1188727 | HB24: =HAVERM!AZ448+HAVERM!BB448 -> 6411808 | HC24: =HAVERM!BA448+HAVERM!BC448 -> 2377818 | HD24: =HAVERM!BD448 -> 1081527 | HE24: =HAVERM!BE448+HAVERM!BF448+HAVERM!BG448 -> 4808174 | HF24: =HAVERM!BH448+HAVERM!BI448+HAVERM!BJ448+HAVERM!BK448+HAVERM!BL448+HAVERM!BM448 -> 9224495 | HH24: Total | HI24: ='ASHE Annual pay All SIC'!D6 -> 31602 | HJ24: =FQ128 -> -0.42082583 | HP24: 2027 | HQ24: 15.941848 | HR24: 3.8531658 | HS24: =HQ24+HR24 -> 19.795014 | HU24: 2027 | HV24: 6852.2566 | HW24: 1656.1995 | HX24: =HV24+HW24 -> 8508.4561 | HZ24: 45292 | IA24: =HAVERQ!E184 -> 5836 | IB24: =HAVERQ!F184 -> 27508 | IC24: =DataQ!Z211-('Chart Data'!IA24+'Chart Data'!IB24) -> -9 | IE24: 45292 | IF24: =IA24-AVERAGE(IA$4:IA$7) -> 520.25 | IG24: =IB24-AVERAGE(IB$4:IB$7) -> -116 | II24: 45292 | IJ24: =100*(IA24/AVERAGE(IA$4:IA$7)) -> 109.78695 | IK24: =100*(IB24/AVERAGE(IB$4:IB$7)) -> 99.580075 | IM24: 45292 | IN24: =SUM(DataQ!U211:Y211) -> 11914 | IO24: =DataQ!F211-'Chart Data'!IN24 -> 24875 | IQ24: 45292 | IR24: =100*(IN24/AVERAGE(IN$4:IN$7)) -> 108.90062 | IS24: =100*(IO24/AVERAGE(IO$4:IO$7)) -> 101.01625
A25: 45383 | B25: =HAVERQ!E185-AVERAGE(HAVERQ!E$164:E$167) -> 544.25 | C25: =HAVERQ!F185-AVERAGE(HAVERQ!F$164:F$167) -> 105 | E25: 38443 | F25: =HAVERQ!P109 -> 1480 | G25: =HAVERQ!O109 -> 1583 | H25: =HAVERQ!N109 -> 1287 | I25: =HAVERQ!M109 -> 272 | J25: =HAVERQ!L109 -> 210 | K25: =HAVERQ!E109-F25-G25-H25-I25-J25 -> 814 | M25: 38443 | N25: =100*(F25/SUM($F25:$K25)) -> 26.213248 | O25: =100*(G25/SUM($F25:$K25)) -> 28.037549 | P25: =100*(H25/SUM($F25:$K25)) -> 22.794899 | Q25: =100*(I25/SUM($F25:$K25)) -> 4.81757 | R25: =100*(J25/SUM($F25:$K25)) -> 3.7194474 | S25: =100*(K25/SUM($F25:$K25)) -> 14.417287 | U25: 38443 | V25: =F25-AVERAGE(F$4:F$7) -> 270.75 | W25: =G25-AVERAGE(G$4:G$7) -> 143.25 | X25: =H25-AVERAGE(H$4:H$7) -> 108 | Y25: =I25-AVERAGE(I$4:I$7) -> 46.25 | Z25: =J25-AVERAGE(J$4:J$7) -> -6.25 | AA25: =K25-AVERAGE(K$4:K$7) -> 26.25 | AB25: =SUM(V25:AA25) -> 588.25 | AD25: 45383 | AE25: =HAVERQ!T185-AVERAGE(HAVERQ!T$164:T$167) -> -48.25 | AF25: =HAVERQ!U185-AVERAGE(HAVERQ!U$164:U$167) -> -11.25 | AG25: =HAVERQ!V185-AVERAGE(HAVERQ!V$164:V$167) -> -114.75 | AH25: =HAVERQ!W185-AVERAGE(HAVERQ!W$164:W$167) -> -7.75 | AI25: =HAVERQ!X185-AVERAGE(HAVERQ!X$164:X$167) -> 20.5 | AJ25: =HAVERQ!Y185-AVERAGE(HAVERQ!Y$164:Y$167) -> -178.25 | AK25: =HAVERQ!Z185-AVERAGE(HAVERQ!Z$164:Z$167) -> -270.5 | AL25: =HAVERQ!AA185-AVERAGE(HAVERQ!AA$164:AA$167) -> 77 | ... AV25: =HAVERQ!AK185-AVERAGE(HAVERQ!AK$164:AK$167) -> 80.25 | AW25: =AY25-AVERAGE(AY$4:AY$7) -> -28.5 | AY25: =HAVERQ!AL185+HAVERQ!AM185 -> 989 | BA25: 45383 | BB25: =BK25-AVERAGE(BK$4:BK$7) -> -48.25 | BC25: =BL25-AVERAGE(BL$4:BL$7) -> 1.5 | BD25: =BM25-AVERAGE(BM$4:BM$7) -> -114.75 | BE25: =BN25-AVERAGE(BN$4:BN$7) -> -178.25 | BF25: =BO25-AVERAGE(BO$4:BO$7) -> -104.5 | BG25: =BP25-AVERAGE(BP$4:BP$7) -> 179.75 | BH25: =BQ25-AVERAGE(BQ$4:BQ$7) -> 413.5 | BI25: =BR25-AVERAGE(BR$4:BR$7) -> 996.75 | BK25: =HAVERQ!T185 -> 350 | BL25: =HAVERQ!U185+HAVERQ!W185+HAVERQ!X185 -> 427 | BM25: =HAVERQ!V185 -> 2576 | BN25: =HAVERQ!Y185 -> 2155 | BO25: =HAVERQ!Z185+HAVERQ!AB185 -> 7400 | BP25: =HAVERQ!AA185+HAVERQ!AC185 -> 3486 | BQ25: =HAVERQ!AD185+HAVERQ!AE185+HAVERQ!AF185+HAVERQ!AG185 -> 8380 | BR25: =HAVERQ!AH185+HAVERQ!AI185+HAVERQ!AJ185+HAVERQ!AK185+HAVERQ!AL185+HAVERQ!AM185 -> 11937 | BS25: =HAVERQ!S185-SUM('Chart Data'!BK25:BR25) -> -1 | BU25: 36251 | BV25: =HAVERQ!T85 -> 424 | BW25: =HAVERQ!U85+HAVERQ!W85+HAVERQ!X85 -> 343 | BX25: =HAVERQ!V85 -> 4128 | BY25: =HAVERQ!Y85 -> 1909 | BZ25: =HAVERQ!Z85+HAVERQ!AB85 -> 6672 | CA25: =HAVERQ!AA85+HAVERQ!AC85 -> 2411 | CB25: =HAVERQ!AD85+HAVERQ!AE85+HAVERQ!AF85+HAVERQ!AG85 -> 5211 | CC25: =HAVERQ!AH85+HAVERQ!AI85+HAVERQ!AJ85+HAVERQ!AK85+HAVERQ!AL85+HAVERQ!AM85 -> 8230 | CD25: =HAVERQ!S85-SUM('Chart Data'!BV25:CC25) -> -1 | DB25: 38078 | DC25: =HAVERQ!BI105/HAVERQ!T105 -> 9.8407821 | DD25: =HAVERQ!BJ105/HAVERQ!U105 -> 588.32759 | DE25: =HAVERQ!BK105/HAVERQ!V105 -> 13.842249 | DF25: =HAVERQ!BL105/HAVERQ!W105 -> 114.68675 | DG25: =HAVERQ!BM105/HAVERQ!X105 -> 44.574194 | DH25: =HAVERQ!BN105/HAVERQ!Y105 -> 15.356907 | DI25: =HAVERQ!BO105/HAVERQ!Z105 -> 10.196461 | DJ25: =HAVERQ!BP105/HAVERQ!AA105 -> 12.822004 | ... DT25: =HAVERQ!BZ105/HAVERQ!AK105 -> 10.616039 | DU25: =(HAVERQ!CA105+HAVERQ!CB105)/HAVERQ!AL105 -> 10.085749 | FD25: 45748 | FE25: =DataQ!U216+DataQ!V216+DataQ!W216+DataQ!X216+DataQ!Y216 -> 12170.202 | FF25: =DataQ!J216+DataQ!Q216+DataQ!H216+DataQ!P216+DataQ!S216+DataQ!K216+DataQ!L216 -> 9014.6196 | FG25: =DataQ!N216+DataQ!I216+DataQ!R216+DataQ!G216+DataQ!T216+DataQ!M216+DataQ!O216 -> 15893.094 | FH25: =DataQ!F216-'Chart Data'!FE25-'Chart Data'!FF25-'Chart Data'!FG25 -> 0.99458 | FJ25: 45748 | FK25: =FE25-(AVERAGE(FE$20:FE$23)) -> 239.452 | FL25: =FF25-(AVERAGE(FF$20:FF$23)) -> 69.36962 | FM25: =FG25-(AVERAGE(FG$20:FG$23)) -> -25.1562 | FN25: =SUM(FK25:FM25) -> 283.66542 | FP25: 42644 | FQ25: =100*((AVERAGE(HAVERM!AS447:AS449)/AVERAGE(HAVERM!AS444:AS446))-1) -> 0.26649679 | FR25: =100*((AVERAGE(HAVERM!AT447:AT449)/AVERAGE(HAVERM!AT444:AT446))-1) -> 0.59528299 | FS25: =100*((AVERAGE(HAVERM!AU447:AU449)/AVERAGE(HAVERM!AU444:AU446))-1) -> -1.682202 | FT25: =100*((AVERAGE(HAVERM!AV447:AV449)/AVERAGE(HAVERM!AV444:AV446))-1) -> 0.22067564 | FU25: =100*((AVERAGE(HAVERM!AW447:AW449)/AVERAGE(HAVERM!AW444:AW446))-1) -> 1.2395742 | FV25: =100*((AVERAGE(HAVERM!AX447:AX449)/AVERAGE(HAVERM!AX444:AX446))-1) -> 1.1230987 | FW25: =100*((AVERAGE(HAVERM!AY447:AY449)/AVERAGE(HAVERM!AY444:AY446))-1) -> 0.80815266 | FX25: =100*((AVERAGE(HAVERM!AZ447:AZ449)/AVERAGE(HAVERM!AZ444:AZ446))-1) -> 0.31528415 | ... GI25: =100*((AVERAGE(HAVERM!BK447:BK449)/AVERAGE(HAVERM!BK444:BK446))-1) -> 0.91562626 | GJ25: =100*(((AVERAGE(HAVERM!BL447:BL449)+(AVERAGE(HAVERM!BM447:BM449)))/(AVERAGE(HAVERM!BL444:BL446)+AVERAGE(HAVERM!BM444:BM446))-1)) -> 1.4301067 | GL25: 42644 | GM25: =100*((AVERAGE(GX23:GX25)/AVERAGE(GX20:GX22))-1) -> 0.59528299 | GN25: =100*((AVERAGE(GY23:GY25)/AVERAGE(GY20:GY22))-1) -> 0.71031794 | GO25: =100*((AVERAGE(GZ23:GZ25)/AVERAGE(GZ20:GZ22))-1) -> 0.22067564 | GP25: =100*((AVERAGE(HA23:HA25)/AVERAGE(HA20:HA22))-1) -> 0.80815266 | GQ25: =100*((AVERAGE(HB23:HB25)/AVERAGE(HB20:HB22))-1) -> 0.49469381 | GR25: =100*((AVERAGE(HC23:HC25)/AVERAGE(HC20:HC22))-1) -> 0.6580489 | GS25: =100*((AVERAGE(HD23:HD25)/AVERAGE(HD20:HD22))-1) -> -0.22312685 | GT25: =100*((AVERAGE(HE23:HE25)/AVERAGE(HE20:HE22))-1) -> 0.11944755 | GU25: =100*((AVERAGE(HF23:HF25)/AVERAGE(HF20:HF22))-1) -> 0.063559656 | GW25: 42644 | GX25: =HAVERM!AT449 -> 182551 | GY25: =HAVERM!AU449+HAVERM!AW449+HAVERM!AX449 -> 315761 | GZ25: =HAVERM!AV449 -> 2398881 | HA25: =HAVERM!AY449 -> 1192007 | HB25: =HAVERM!AZ449+HAVERM!BB449 -> 6421045 | HC25: =HAVERM!BA449+HAVERM!BC449 -> 2383000 | HD25: =HAVERM!BD449 -> 1079993 | HE25: =HAVERM!BE449+HAVERM!BF449+HAVERM!BG449 -> 4802552 | HF25: =HAVERM!BH449+HAVERM!BI449+HAVERM!BJ449+HAVERM!BK449+HAVERM!BL449+HAVERM!BM449 -> 9241786 | HP25: 2028 | HQ25: 15.819432 | HR25: 3.7532041 | HS25: =HQ25+HR25 -> 19.572637 | HU25: 2028 | HV25: 6889.2274 | HW25: 1634.4882 | HX25: =HV25+HW25 -> 8523.7156 | HZ25: 45383 | IA25: =HAVERQ!E185 -> 5860 | IB25: =HAVERQ!F185 -> 27729 | IC25: =DataQ!Z212-('Chart Data'!IA25+'Chart Data'!IB25) -> -100 | IE25: 45383 | IF25: =IA25-AVERAGE(IA$4:IA$7) -> 544.25 | IG25: =IB25-AVERAGE(IB$4:IB$7) -> 105 | II25: 45383 | IJ25: =100*(IA25/AVERAGE(IA$4:IA$7)) -> 110.23844 | IK25: =100*(IB25/AVERAGE(IB$4:IB$7)) -> 100.3801 | IM25: 45383 | IN25: =SUM(DataQ!U212:Y212) -> 11937 | IO25: =DataQ!F212-'Chart Data'!IN25 -> 24773 | IQ25: 45383 | IR25: =100*(IN25/AVERAGE(IN$4:IN$7)) -> 109.11085 | IS25: =100*(IO25/AVERAGE(IO$4:IO$7)) -> 100.60204
A26: 45474 | B26: =HAVERQ!E186-AVERAGE(HAVERQ!E$164:E$167) -> 563.25 | C26: =HAVERQ!F186-AVERAGE(HAVERQ!F$164:F$167) -> 275 | E26: 38534 | F26: =HAVERQ!P110 -> 1485 | G26: =HAVERQ!O110 -> 1593 | H26: =HAVERQ!N110 -> 1284 | I26: =HAVERQ!M110 -> 271 | J26: =HAVERQ!L110 -> 208 | K26: =HAVERQ!E110-F26-G26-H26-I26-J26 -> 799 | M26: 38534 | N26: =100*(F26/SUM($F26:$K26)) -> 26.329787 | O26: =100*(G26/SUM($F26:$K26)) -> 28.244681 | P26: =100*(H26/SUM($F26:$K26)) -> 22.765957 | Q26: =100*(I26/SUM($F26:$K26)) -> 4.8049645 | R26: =100*(J26/SUM($F26:$K26)) -> 3.6879433 | S26: =100*(K26/SUM($F26:$K26)) -> 14.166667 | U26: 38534 | V26: =F26-AVERAGE(F$4:F$7) -> 275.75 | W26: =G26-AVERAGE(G$4:G$7) -> 153.25 | X26: =H26-AVERAGE(H$4:H$7) -> 105 | Y26: =I26-AVERAGE(I$4:I$7) -> 45.25 | Z26: =J26-AVERAGE(J$4:J$7) -> -8.25 | AA26: =K26-AVERAGE(K$4:K$7) -> 11.25 | AB26: =SUM(V26:AA26) -> 582.25 | AD26: 45474 | AE26: =HAVERQ!T186-AVERAGE(HAVERQ!T$164:T$167) -> -38.25 | AF26: =HAVERQ!U186-AVERAGE(HAVERQ!U$164:U$167) -> -14.25 | AG26: =HAVERQ!V186-AVERAGE(HAVERQ!V$164:V$167) -> -101.75 | AH26: =HAVERQ!W186-AVERAGE(HAVERQ!W$164:W$167) -> -2.75 | AI26: =HAVERQ!X186-AVERAGE(HAVERQ!X$164:X$167) -> 22.5 | AJ26: =HAVERQ!Y186-AVERAGE(HAVERQ!Y$164:Y$167) -> -113.25 | AK26: =HAVERQ!Z186-AVERAGE(HAVERQ!Z$164:Z$167) -> -301.5 | AL26: =HAVERQ!AA186-AVERAGE(HAVERQ!AA$164:AA$167) -> 78 | ... AV26: =HAVERQ!AK186-AVERAGE(HAVERQ!AK$164:AK$167) -> 66.25 | AW26: =AY26-AVERAGE(AY$4:AY$7) -> -55.5 | AY26: =HAVERQ!AL186+HAVERQ!AM186 -> 962 | BA26: 45474 | BB26: =BK26-AVERAGE(BK$4:BK$7) -> -38.25 | BC26: =BL26-AVERAGE(BL$4:BL$7) -> 5.5 | BD26: =BM26-AVERAGE(BM$4:BM$7) -> -101.75 | BE26: =BN26-AVERAGE(BN$4:BN$7) -> -113.25 | BF26: =BO26-AVERAGE(BO$4:BO$7) -> -121.5 | BG26: =BP26-AVERAGE(BP$4:BP$7) -> 208.75 | BH26: =BQ26-AVERAGE(BQ$4:BQ$7) -> 398.5 | BI26: =BR26-AVERAGE(BR$4:BR$7) -> 964.75 | BK26: =HAVERQ!T186 -> 360 | BL26: =HAVERQ!U186+HAVERQ!W186+HAVERQ!X186 -> 431 | BM26: =HAVERQ!V186 -> 2589 | BN26: =HAVERQ!Y186 -> 2220 | BO26: =HAVERQ!Z186+HAVERQ!AB186 -> 7383 | BP26: =HAVERQ!AA186+HAVERQ!AC186 -> 3515 | BQ26: =HAVERQ!AD186+HAVERQ!AE186+HAVERQ!AF186+HAVERQ!AG186 -> 8365 | BR26: =HAVERQ!AH186+HAVERQ!AI186+HAVERQ!AJ186+HAVERQ!AK186+HAVERQ!AL186+HAVERQ!AM186 -> 11905 | BS26: =HAVERQ!S186-SUM('Chart Data'!BK26:BR26) -> -2 | BU26: 36342 | BV26: =HAVERQ!T86 -> 420 | BW26: =HAVERQ!U86+HAVERQ!W86+HAVERQ!X86 -> 338 | BX26: =HAVERQ!V86 -> 4101 | BY26: =HAVERQ!Y86 -> 1920 | BZ26: =HAVERQ!Z86+HAVERQ!AB86 -> 6710 | CA26: =HAVERQ!AA86+HAVERQ!AC86 -> 2443 | CB26: =HAVERQ!AD86+HAVERQ!AE86+HAVERQ!AF86+HAVERQ!AG86 -> 5299 | CC26: =HAVERQ!AH86+HAVERQ!AI86+HAVERQ!AJ86+HAVERQ!AK86+HAVERQ!AL86+HAVERQ!AM86 -> 8354 | CD26: =HAVERQ!S86-SUM('Chart Data'!BV26:CC26) -> -1 | DB26: 38169 | DC26: =HAVERQ!BI106/HAVERQ!T106 -> 9.2392473 | DD26: =HAVERQ!BJ106/HAVERQ!U106 -> 537.98361 | DE26: =HAVERQ!BK106/HAVERQ!V106 -> 13.863187 | DF26: =HAVERQ!BL106/HAVERQ!W106 -> 110.9625 | DG26: =HAVERQ!BM106/HAVERQ!X106 -> 43.058065 | DH26: =HAVERQ!BN106/HAVERQ!Y106 -> 15.129699 | DI26: =HAVERQ!BO106/HAVERQ!Z106 -> 10.266362 | DJ26: =HAVERQ!BP106/HAVERQ!AA106 -> 12.724042 | ... DT26: =HAVERQ!BZ106/HAVERQ!AK106 -> 10.418317 | DU26: =(HAVERQ!CA106+HAVERQ!CB106)/HAVERQ!AL106 -> 9.996368 | FD26: 45839 | FE26: =DataQ!U217+DataQ!V217+DataQ!W217+DataQ!X217+DataQ!Y217 -> 12205.913 | FF26: =DataQ!J217+DataQ!Q217+DataQ!H217+DataQ!P217+DataQ!S217+DataQ!K217+DataQ!L217 -> 8995.6916 | FG26: =DataQ!N217+DataQ!I217+DataQ!R217+DataQ!G217+DataQ!T217+DataQ!M217+DataQ!O217 -> 15853.578 | FH26: =DataQ!F217-'Chart Data'!FE26-'Chart Data'!FF26-'Chart Data'!FG26 -> 0.99704 | FJ26: 45839 | FK26: =FE26-(AVERAGE(FE$20:FE$23)) -> 275.163 | FL26: =FF26-(AVERAGE(FF$20:FF$23)) -> 50.44156 | FM26: =FG26-(AVERAGE(FG$20:FG$23)) -> -64.6716 | FN26: =SUM(FK26:FM26) -> 260.93296 | FP26: 42675 | FQ26: =100*((AVERAGE(HAVERM!AS448:AS450)/AVERAGE(HAVERM!AS445:AS447))-1) -> 0.28532892 | FR26: =100*((AVERAGE(HAVERM!AT448:AT450)/AVERAGE(HAVERM!AT445:AT447))-1) -> 0.31407923 | FS26: =100*((AVERAGE(HAVERM!AU448:AU450)/AVERAGE(HAVERM!AU445:AU447))-1) -> -1.5178249 | FT26: =100*((AVERAGE(HAVERM!AV448:AV450)/AVERAGE(HAVERM!AV445:AV447))-1) -> 0.17602204 | FU26: =100*((AVERAGE(HAVERM!AW448:AW450)/AVERAGE(HAVERM!AW445:AW447))-1) -> 1.1432278 | FV26: =100*((AVERAGE(HAVERM!AX448:AX450)/AVERAGE(HAVERM!AX445:AX447))-1) -> 1.2311929 | FW26: =100*((AVERAGE(HAVERM!AY448:AY450)/AVERAGE(HAVERM!AY445:AY447))-1) -> 0.86652336 | FX26: =100*((AVERAGE(HAVERM!AZ448:AZ450)/AVERAGE(HAVERM!AZ445:AZ447))-1) -> 0.36585158 | ... GI26: =100*((AVERAGE(HAVERM!BK448:BK450)/AVERAGE(HAVERM!BK445:BK447))-1) -> 0.89239527 | GJ26: =100*(((AVERAGE(HAVERM!BL448:BL450)+(AVERAGE(HAVERM!BM448:BM450)))/(AVERAGE(HAVERM!BL445:BL447)+AVERAGE(HAVERM!BM445:BM447))-1)) -> 1.0413235 | GL26: 42675 | GM26: =100*((AVERAGE(GX24:GX26)/AVERAGE(GX21:GX23))-1) -> 0.31407923 | GN26: =100*((AVERAGE(GY24:GY26)/AVERAGE(GY21:GY23))-1) -> 0.76570786 | GO26: =100*((AVERAGE(GZ24:GZ26)/AVERAGE(GZ21:GZ23))-1) -> 0.17602204 | GP26: =100*((AVERAGE(HA24:HA26)/AVERAGE(HA21:HA23))-1) -> 0.86652336 | GQ26: =100*((AVERAGE(HB24:HB26)/AVERAGE(HB21:HB23))-1) -> 0.53586113 | GR26: =100*((AVERAGE(HC24:HC26)/AVERAGE(HC21:HC23))-1) -> 0.61796866 | GS26: =100*((AVERAGE(HD24:HD26)/AVERAGE(HD21:HD23))-1) -> -0.28326869 | GT26: =100*((AVERAGE(HE24:HE26)/AVERAGE(HE21:HE23))-1) -> 0.096583932 | GU26: =100*((AVERAGE(HF24:HF26)/AVERAGE(HF21:HF23))-1) -> 0.12856355 | GW26: 42675 | GX26: =HAVERM!AT450 -> 181487 | GY26: =HAVERM!AU450+HAVERM!AW450+HAVERM!AX450 -> 316697 | GZ26: =HAVERM!AV450 -> 2401722 | HA26: =HAVERM!AY450 -> 1195886 | HB26: =HAVERM!AZ450+HAVERM!BB450 -> 6431883 | HC26: =HAVERM!BA450+HAVERM!BC450 -> 2387979 | HD26: =HAVERM!BD450 -> 1080600 | HE26: =HAVERM!BE450+HAVERM!BF450+HAVERM!BG450 -> 4809311 | HF26: =HAVERM!BH450+HAVERM!BI450+HAVERM!BJ450+HAVERM!BK450+HAVERM!BL450+HAVERM!BM450 -> 9247444 | HP26: 2029 | HQ26: 15.696275 | HR26: 3.6642106 | HS26: =HQ26+HR26 -> 19.360486 | HU26: 2029 | HV26: 6928.9315 | HW26: 1617.5216 | HX26: =HV26+HW26 -> 8546.4531 | HZ26: 45474 | IA26: =HAVERQ!E186 -> 5879 | IB26: =HAVERQ!F186 -> 27899 | IC26: =DataQ!Z213-('Chart Data'!IA26+'Chart Data'!IB26) -> -3 | IE26: 45474 | IF26: =IA26-AVERAGE(IA$4:IA$7) -> 563.25 | IG26: =IB26-AVERAGE(IB$4:IB$7) -> 275 | II26: 45474 | IJ26: =100*(IA26/AVERAGE(IA$4:IA$7)) -> 110.59587 | IK26: =100*(IB26/AVERAGE(IB$4:IB$7)) -> 100.99551 | IM26: 45474 | IN26: =SUM(DataQ!U213:Y213) -> 11905 | IO26: =DataQ!F213-'Chart Data'!IN26 -> 24861 | IQ26: 45474 | IR26: =100*(IN26/AVERAGE(IN$4:IN$7)) -> 108.81835 | IS26: =100*(IO26/AVERAGE(IO$4:IO$7)) -> 100.9594
A27: 45566 | B27: =HAVERQ!E187-AVERAGE(HAVERQ!E$164:E$167) -> 581.25 | C27: =HAVERQ!F187-AVERAGE(HAVERQ!F$164:F$167) -> 401 | E27: 38626 | F27: =HAVERQ!P111 -> 1488 | G27: =HAVERQ!O111 -> 1599 | H27: =HAVERQ!N111 -> 1284 | I27: =HAVERQ!M111 -> 274 | J27: =HAVERQ!L111 -> 206 | K27: =HAVERQ!E111-F27-G27-H27-I27-J27 -> 795 | M27: 38626 | N27: =100*(F27/SUM($F27:$K27)) -> 26.354942 | O27: =100*(G27/SUM($F27:$K27)) -> 28.320935 | P27: =100*(H27/SUM($F27:$K27)) -> 22.741764 | Q27: =100*(I27/SUM($F27:$K27)) -> 4.8529933 | R27: =100*(J27/SUM($F27:$K27)) -> 3.6486008 | S27: =100*(K27/SUM($F27:$K27)) -> 14.080765 | U27: 38626 | V27: =F27-AVERAGE(F$4:F$7) -> 278.75 | W27: =G27-AVERAGE(G$4:G$7) -> 159.25 | X27: =H27-AVERAGE(H$4:H$7) -> 105 | Y27: =I27-AVERAGE(I$4:I$7) -> 48.25 | Z27: =J27-AVERAGE(J$4:J$7) -> -10.25 | AA27: =K27-AVERAGE(K$4:K$7) -> 7.25 | AB27: =SUM(V27:AA27) -> 588.25 | AD27: 45566 | AE27: =HAVERQ!T187-AVERAGE(HAVERQ!T$164:T$167) -> -38.25 | AF27: =HAVERQ!U187-AVERAGE(HAVERQ!U$164:U$167) -> -13.25 | AG27: =HAVERQ!V187-AVERAGE(HAVERQ!V$164:V$167) -> -83.75 | AH27: =HAVERQ!W187-AVERAGE(HAVERQ!W$164:W$167) -> -2.75 | AI27: =HAVERQ!X187-AVERAGE(HAVERQ!X$164:X$167) -> 27.5 | AJ27: =HAVERQ!Y187-AVERAGE(HAVERQ!Y$164:Y$167) -> -104.25 | AK27: =HAVERQ!Z187-AVERAGE(HAVERQ!Z$164:Z$167) -> -308.5 | AL27: =HAVERQ!AA187-AVERAGE(HAVERQ!AA$164:AA$167) -> 99 | ... AV27: =HAVERQ!AK187-AVERAGE(HAVERQ!AK$164:AK$167) -> 87.25 | AW27: =AY27-AVERAGE(AY$4:AY$7) -> -16.5 | AY27: =HAVERQ!AL187+HAVERQ!AM187 -> 1001 | BA27: 45566 | BB27: =BK27-AVERAGE(BK$4:BK$7) -> -38.25 | BC27: =BL27-AVERAGE(BL$4:BL$7) -> 11.5 | BD27: =BM27-AVERAGE(BM$4:BM$7) -> -83.75 | BE27: =BN27-AVERAGE(BN$4:BN$7) -> -104.25 | BF27: =BO27-AVERAGE(BO$4:BO$7) -> -149.5 | BG27: =BP27-AVERAGE(BP$4:BP$7) -> 241.75 | BH27: =BQ27-AVERAGE(BQ$4:BQ$7) -> 438.5 | BI27: =BR27-AVERAGE(BR$4:BR$7) -> 1026.75 | BK27: =HAVERQ!T187 -> 360 | BL27: =HAVERQ!U187+HAVERQ!W187+HAVERQ!X187 -> 437 | BM27: =HAVERQ!V187 -> 2607 | BN27: =HAVERQ!Y187 -> 2229 | BO27: =HAVERQ!Z187+HAVERQ!AB187 -> 7355 | BP27: =HAVERQ!AA187+HAVERQ!AC187 -> 3548 | BQ27: =HAVERQ!AD187+HAVERQ!AE187+HAVERQ!AF187+HAVERQ!AG187 -> 8405 | BR27: =HAVERQ!AH187+HAVERQ!AI187+HAVERQ!AJ187+HAVERQ!AK187+HAVERQ!AL187+HAVERQ!AM187 -> 11967 | BS27: =HAVERQ!S187-SUM('Chart Data'!BK27:BR27) -> -2 | BU27: 36434 | BV27: =HAVERQ!T87 -> 402 | BW27: =HAVERQ!U87+HAVERQ!W87+HAVERQ!X87 -> 326 | BX27: =HAVERQ!V87 -> 4082 | BY27: =HAVERQ!Y87 -> 1912 | BZ27: =HAVERQ!Z87+HAVERQ!AB87 -> 6717 | CA27: =HAVERQ!AA87+HAVERQ!AC87 -> 2481 | CB27: =HAVERQ!AD87+HAVERQ!AE87+HAVERQ!AF87+HAVERQ!AG87 -> 5336 | CC27: =HAVERQ!AH87+HAVERQ!AI87+HAVERQ!AJ87+HAVERQ!AK87+HAVERQ!AL87+HAVERQ!AM87 -> 8458 | CD27: =HAVERQ!S87-SUM('Chart Data'!BV27:CC27) -> 1 | DB27: 38261 | DC27: =HAVERQ!BI107/HAVERQ!T107 -> 8.997319 | DD27: =HAVERQ!BJ107/HAVERQ!U107 -> 547.9322 | DE27: =HAVERQ!BK107/HAVERQ!V107 -> 14.043343 | DF27: =HAVERQ!BL107/HAVERQ!W107 -> 105.48052 | DG27: =HAVERQ!BM107/HAVERQ!X107 -> 42.417722 | DH27: =HAVERQ!BN107/HAVERQ!Y107 -> 14.614927 | DI27: =HAVERQ!BO107/HAVERQ!Z107 -> 10.253899 | DJ27: =HAVERQ!BP107/HAVERQ!AA107 -> 13.033241 | ... DT27: =HAVERQ!BZ107/HAVERQ!AK107 -> 10.33701 | DU27: =(HAVERQ!CA107+HAVERQ!CB107)/HAVERQ!AL107 -> 9.9854897 | FD27: 45931 | FE27: =DataQ!U218+DataQ!V218+DataQ!W218+DataQ!X218+DataQ!Y218 -> 12237.33 | FF27: =DataQ!J218+DataQ!Q218+DataQ!H218+DataQ!P218+DataQ!S218+DataQ!K218+DataQ!L218 -> 9007.7898 | FG27: =DataQ!N218+DataQ!I218+DataQ!R218+DataQ!G218+DataQ!T218+DataQ!M218+DataQ!O218 -> 15846.246 | FH27: =DataQ!F218-'Chart Data'!FE27-'Chart Data'!FF27-'Chart Data'!FG27 -> 1.00409 | FJ27: 45931 | FK27: =FE27-(AVERAGE(FE$20:FE$23)) -> 306.58 | FL27: =FF27-(AVERAGE(FF$20:FF$23)) -> 62.53981 | FM27: =FG27-(AVERAGE(FG$20:FG$23)) -> -72.0039 | FN27: =SUM(FK27:FM27) -> 297.11591 | FP27: 42705 | FQ27: =100*((AVERAGE(HAVERM!AS449:AS451)/AVERAGE(HAVERM!AS446:AS448))-1) -> 0.3072986 | FR27: =100*((AVERAGE(HAVERM!AT449:AT451)/AVERAGE(HAVERM!AT446:AT448))-1) -> -0.017038334 | FS27: =100*((AVERAGE(HAVERM!AU449:AU451)/AVERAGE(HAVERM!AU446:AU448))-1) -> -1.2596626 | FT27: =100*((AVERAGE(HAVERM!AV449:AV451)/AVERAGE(HAVERM!AV446:AV448))-1) -> 0.21388762 | FU27: =100*((AVERAGE(HAVERM!AW449:AW451)/AVERAGE(HAVERM!AW446:AW448))-1) -> 0.97071945 | FV27: =100*((AVERAGE(HAVERM!AX449:AX451)/AVERAGE(HAVERM!AX446:AX448))-1) -> 1.1891964 | FW27: =100*((AVERAGE(HAVERM!AY449:AY451)/AVERAGE(HAVERM!AY446:AY448))-1) -> 0.81857791 | FX27: =100*((AVERAGE(HAVERM!AZ449:AZ451)/AVERAGE(HAVERM!AZ446:AZ448))-1) -> 0.39049055 | ... GI27: =100*((AVERAGE(HAVERM!BK449:BK451)/AVERAGE(HAVERM!BK446:BK448))-1) -> 0.86116143 | GJ27: =100*(((AVERAGE(HAVERM!BL449:BL451)+(AVERAGE(HAVERM!BM449:BM451)))/(AVERAGE(HAVERM!BL446:BL448)+AVERAGE(HAVERM!BM446:BM448))-1)) -> 0.7190913 | GL27: 42705 | GM27: =100*((AVERAGE(GX25:GX27)/AVERAGE(GX22:GX24))-1) -> -0.017038334 | GN27: =100*((AVERAGE(GY25:GY27)/AVERAGE(GY22:GY24))-1) -> 0.73281092 | GO27: =100*((AVERAGE(GZ25:GZ27)/AVERAGE(GZ22:GZ24))-1) -> 0.21388762 | GP27: =100*((AVERAGE(HA25:HA27)/AVERAGE(HA22:HA24))-1) -> 0.81857791 | GQ27: =100*((AVERAGE(HB25:HB27)/AVERAGE(HB22:HB24))-1) -> 0.53414665 | GR27: =100*((AVERAGE(HC25:HC27)/AVERAGE(HC22:HC24))-1) -> 0.59373408 | GS27: =100*((AVERAGE(HD25:HD27)/AVERAGE(HD22:HD24))-1) -> -0.26028255 | GT27: =100*((AVERAGE(HE25:HE27)/AVERAGE(HE22:HE24))-1) -> 0.083306046 | GU27: =100*((AVERAGE(HF25:HF27)/AVERAGE(HF22:HF24))-1) -> 0.21006845 | GW27: 42705 | GX27: =HAVERM!AT451 -> 181697 | GY27: =HAVERM!AU451+HAVERM!AW451+HAVERM!AX451 -> 317259 | GZ27: =HAVERM!AV451 -> 2407343 | HA27: =HAVERM!AY451 -> 1196399 | HB27: =HAVERM!AZ451+HAVERM!BB451 -> 6444517 | HC27: =HAVERM!BA451+HAVERM!BC451 -> 2391148 | HD27: =HAVERM!BD451 -> 1079345 | HE27: =HAVERM!BE451+HAVERM!BF451+HAVERM!BG451 -> 4814465 | HF27: =HAVERM!BH451+HAVERM!BI451+HAVERM!BJ451+HAVERM!BK451+HAVERM!BL451+HAVERM!BM451 -> 9252281 | HZ27: 45566 | IA27: =HAVERQ!E187 -> 5897 | IB27: =HAVERQ!F187 -> 28025 | IC27: =DataQ!Z214-('Chart Data'!IA27+'Chart Data'!IB27) -> -59 | IE27: 45566 | IF27: =IA27-AVERAGE(IA$4:IA$7) -> 581.25 | IG27: =IB27-AVERAGE(IB$4:IB$7) -> 401 | II27: 45566 | IJ27: =100*(IA27/AVERAGE(IA$4:IA$7)) -> 110.93449 | IK27: =100*(IB27/AVERAGE(IB$4:IB$7)) -> 101.45164 | IM27: 45566 | IN27: =SUM(DataQ!U214:Y214) -> 11967 | IO27: =DataQ!F214-'Chart Data'!IN27 -> 24939 | IQ27: 45566 | IR27: =100*(IN27/AVERAGE(IN$4:IN$7)) -> 109.38507 | IS27: =100*(IO27/AVERAGE(IO$4:IO$7)) -> 101.27616
A28: 45658 | B28: =HAVERQ!E188-AVERAGE(HAVERQ!E$164:E$167) -> 590.25 | C28: =HAVERQ!F188-AVERAGE(HAVERQ!F$164:F$167) -> 481 | E28: 38718 | F28: =HAVERQ!P112 -> 1484 | G28: =HAVERQ!O112 -> 1603 | H28: =HAVERQ!N112 -> 1284 | I28: =HAVERQ!M112 -> 274 | J28: =HAVERQ!L112 -> 205 | K28: =HAVERQ!E112-F28-G28-H28-I28-J28 -> 781 | M28: 38718 | N28: =100*(F28/SUM($F28:$K28)) -> 26.354111 | O28: =100*(G28/SUM($F28:$K28)) -> 28.467413 | P28: =100*(H28/SUM($F28:$K28)) -> 22.802344 | Q28: =100*(I28/SUM($F28:$K28)) -> 4.8659208 | R28: =100*(J28/SUM($F28:$K28)) -> 3.6405612 | S28: =100*(K28/SUM($F28:$K28)) -> 13.86965 | U28: 38718 | V28: =F28-AVERAGE(F$4:F$7) -> 274.75 | W28: =G28-AVERAGE(G$4:G$7) -> 163.25 | X28: =H28-AVERAGE(H$4:H$7) -> 105 | Y28: =I28-AVERAGE(I$4:I$7) -> 48.25 | Z28: =J28-AVERAGE(J$4:J$7) -> -11.25 | AA28: =K28-AVERAGE(K$4:K$7) -> -6.75 | AB28: =SUM(V28:AA28) -> 573.25 | AD28: 45658 | AE28: =HAVERQ!T188-AVERAGE(HAVERQ!T$164:T$167) -> -48.25 | AF28: =HAVERQ!U188-AVERAGE(HAVERQ!U$164:U$167) -> -10.25 | AG28: =HAVERQ!V188-AVERAGE(HAVERQ!V$164:V$167) -> -100.75 | AH28: =HAVERQ!W188-AVERAGE(HAVERQ!W$164:W$167) -> -2.75 | AI28: =HAVERQ!X188-AVERAGE(HAVERQ!X$164:X$167) -> 25.5 | AJ28: =HAVERQ!Y188-AVERAGE(HAVERQ!Y$164:Y$167) -> -84.25 | AK28: =HAVERQ!Z188-AVERAGE(HAVERQ!Z$164:Z$167) -> -297.5 | AL28: =HAVERQ!AA188-AVERAGE(HAVERQ!AA$164:AA$167) -> 86 | ... AV28: =HAVERQ!AK188-AVERAGE(HAVERQ!AK$164:AK$167) -> 113.25 | AW28: =AY28-AVERAGE(AY$4:AY$7) -> 27.5 | AY28: =HAVERQ!AL188+HAVERQ!AM188 -> 1045 | BA28: 45658 | BB28: =BK28-AVERAGE(BK$4:BK$7) -> -48.25 | BC28: =BL28-AVERAGE(BL$4:BL$7) -> 12.5 | BD28: =BM28-AVERAGE(BM$4:BM$7) -> -100.75 | BE28: =BN28-AVERAGE(BN$4:BN$7) -> -84.25 | BF28: =BO28-AVERAGE(BO$4:BO$7) -> -163.5 | BG28: =BP28-AVERAGE(BP$4:BP$7) -> 206.75 | BH28: =BQ28-AVERAGE(BQ$4:BQ$7) -> 462.5 | BI28: =BR28-AVERAGE(BR$4:BR$7) -> 1242.75 | BK28: =HAVERQ!T188 -> 350 | BL28: =HAVERQ!U188+HAVERQ!W188+HAVERQ!X188 -> 438 | BM28: =HAVERQ!V188 -> 2590 | BN28: =HAVERQ!Y188 -> 2249 | BO28: =HAVERQ!Z188+HAVERQ!AB188 -> 7341 | BP28: =HAVERQ!AA188+HAVERQ!AC188 -> 3513 | BQ28: =HAVERQ!AD188+HAVERQ!AE188+HAVERQ!AF188+HAVERQ!AG188 -> 8429 | BR28: =HAVERQ!AH188+HAVERQ!AI188+HAVERQ!AJ188+HAVERQ!AK188+HAVERQ!AL188+HAVERQ!AM188 -> 12183 | BS28: =HAVERQ!S188-SUM('Chart Data'!BK28:BR28) -> 1 | BU28: 36526 | BV28: =HAVERQ!T88 -> 397 | BW28: =HAVERQ!U88+HAVERQ!W88+HAVERQ!X88 -> 329 | BX28: =HAVERQ!V88 -> 4049 | BY28: =HAVERQ!Y88 -> 1909 | BZ28: =HAVERQ!Z88+HAVERQ!AB88 -> 6700 | CA28: =HAVERQ!AA88+HAVERQ!AC88 -> 2466 | CB28: =HAVERQ!AD88+HAVERQ!AE88+HAVERQ!AF88+HAVERQ!AG88 -> 5311 | CC28: =HAVERQ!AH88+HAVERQ!AI88+HAVERQ!AJ88+HAVERQ!AK88+HAVERQ!AL88+HAVERQ!AM88 -> 8481 | CD28: =HAVERQ!S88-SUM('Chart Data'!BV28:CC28) -> 2 | DB28: 38353 | DC28: =HAVERQ!BI108/HAVERQ!T108 -> 9.530303 | DD28: =HAVERQ!BJ108/HAVERQ!U108 -> 542.87931 | DE28: =HAVERQ!BK108/HAVERQ!V108 -> 14.260555 | DF28: =HAVERQ!BL108/HAVERQ!W108 -> 100.76 | DG28: =HAVERQ!BM108/HAVERQ!X108 -> 43.43125 | DH28: =HAVERQ!BN108/HAVERQ!Y108 -> 14.640667 | DI28: =HAVERQ!BO108/HAVERQ!Z108 -> 10.346725 | DJ28: =HAVERQ!BP108/HAVERQ!AA108 -> 12.896291 | ... DT28: =HAVERQ!BZ108/HAVERQ!AK108 -> 10.349574 | DU28: =(HAVERQ!CA108+HAVERQ!CB108)/HAVERQ!AL108 -> 9.8814994 | DX28: High paid | DY28: Low paid | FD28: 46023 | FE28: =DataQ!U219+DataQ!V219+DataQ!W219+DataQ!X219+DataQ!Y219 -> 12256.296 | FF28: =DataQ!J219+DataQ!Q219+DataQ!H219+DataQ!P219+DataQ!S219+DataQ!K219+DataQ!L219 -> 9032.9761 | FG28: =DataQ!N219+DataQ!I219+DataQ!R219+DataQ!G219+DataQ!T219+DataQ!M219+DataQ!O219 -> 15866.228 | FH28: =DataQ!F219-'Chart Data'!FE28-'Chart Data'!FF28-'Chart Data'!FG28 -> 1.0002 | FJ28: 46023 | FK28: =FE28-(AVERAGE(FE$20:FE$23)) -> 325.546 | FL28: =FF28-(AVERAGE(FF$20:FF$23)) -> 87.7261 | FM28: =FG28-(AVERAGE(FG$20:FG$23)) -> -52.0223 | FN28: =SUM(FK28:FM28) -> 361.2498 | FP28: 42736 | FQ28: =100*((AVERAGE(HAVERM!AS450:AS452)/AVERAGE(HAVERM!AS447:AS449))-1) -> 0.31820107 | FR28: =100*((AVERAGE(HAVERM!AT450:AT452)/AVERAGE(HAVERM!AT447:AT449))-1) -> -0.35567796 | FS28: =100*((AVERAGE(HAVERM!AU450:AU452)/AVERAGE(HAVERM!AU447:AU449))-1) -> -1.1061932 | FT28: =100*((AVERAGE(HAVERM!AV450:AV452)/AVERAGE(HAVERM!AV447:AV449))-1) -> 0.19359523 | FU28: =100*((AVERAGE(HAVERM!AW450:AW452)/AVERAGE(HAVERM!AW447:AW449))-1) -> 0.77568231 | FV28: =100*((AVERAGE(HAVERM!AX450:AX452)/AVERAGE(HAVERM!AX447:AX449))-1) -> 1.147464 | FW28: =100*((AVERAGE(HAVERM!AY450:AY452)/AVERAGE(HAVERM!AY447:AY449))-1) -> 0.6603868 | FX28: =100*((AVERAGE(HAVERM!AZ450:AZ452)/AVERAGE(HAVERM!AZ447:AZ449))-1) -> 0.40976982 | ... GI28: =100*((AVERAGE(HAVERM!BK450:BK452)/AVERAGE(HAVERM!BK447:BK449))-1) -> 0.66224665 | GJ28: =100*(((AVERAGE(HAVERM!BL450:BL452)+(AVERAGE(HAVERM!BM450:BM452)))/(AVERAGE(HAVERM!BL447:BL449)+AVERAGE(HAVERM!BM447:BM449))-1)) -> 0.53570874 | GL28: 42736 | GM28: =100*((AVERAGE(GX26:GX28)/AVERAGE(GX23:GX25))-1) -> -0.35567796 | GN28: =100*((AVERAGE(GY26:GY28)/AVERAGE(GY23:GY25))-1) -> 0.67536469 | GO28: =100*((AVERAGE(GZ26:GZ28)/AVERAGE(GZ23:GZ25))-1) -> 0.19359523 | GP28: =100*((AVERAGE(HA26:HA28)/AVERAGE(HA23:HA25))-1) -> 0.6603868 | GQ28: =100*((AVERAGE(HB26:HB28)/AVERAGE(HB23:HB25))-1) -> 0.50570094 | GR28: =100*((AVERAGE(HC26:HC28)/AVERAGE(HC23:HC25))-1) -> 0.5228742 | GS28: =100*((AVERAGE(HD26:HD28)/AVERAGE(HD23:HD25))-1) -> -0.23721532 | GT28: =100*((AVERAGE(HE26:HE28)/AVERAGE(HE23:HE25))-1) -> 0.16899177 | GU28: =100*((AVERAGE(HF26:HF28)/AVERAGE(HF23:HF25))-1) -> 0.26740303 | GW28: 42736 | GX28: =HAVERM!AT452 -> 181714 | GY28: =HAVERM!AU452+HAVERM!AW452+HAVERM!AX452 -> 317546 | GZ28: =HAVERM!AV452 -> 2401843 | HA28: =HAVERM!AY452 -> 1197052 | HB28: =HAVERM!AZ452+HAVERM!BB452 -> 6451186 | HC28: =HAVERM!BA452+HAVERM!BC452 -> 2393358 | HD28: =HAVERM!BD452 -> 1077510 | HE28: =HAVERM!BE452+HAVERM!BF452+HAVERM!BG452 -> 4814894 | HF28: =HAVERM!BH452+HAVERM!BI452+HAVERM!BJ452+HAVERM!BK452+HAVERM!BL452+HAVERM!BM452 -> 9257232 | HZ28: 45658 | IA28: =HAVERQ!E188 -> 5906 | IB28: =HAVERQ!F188 -> 28105 | IC28: =DataQ!Z215-('Chart Data'!IA28+'Chart Data'!IB28) -> -36 | IE28: 45658 | IF28: =IA28-AVERAGE(IA$4:IA$7) -> 590.25 | IG28: =IB28-AVERAGE(IB$4:IB$7) -> 481 | II28: 45658 | IJ28: =100*(IA28/AVERAGE(IA$4:IA$7)) -> 111.1038 | IK28: =100*(IB28/AVERAGE(IB$4:IB$7)) -> 101.74124 | IM28: 45658 | IN28: =SUM(DataQ!U215:Y215) -> 12183 | IO28: =DataQ!F215-'Chart Data'!IN28 -> 24911 | IQ28: 45658 | IR28: =100*(IN28/AVERAGE(IN$4:IN$7)) -> 111.35943 | IS28: =100*(IO28/AVERAGE(IO$4:IO$7)) -> 101.16245
E29: 38808 | F29: =HAVERQ!P113 -> 1477 | G29: =HAVERQ!O113 -> 1609 | H29: =HAVERQ!N113 -> 1283 | I29: =HAVERQ!M113 -> 274 | J29: =HAVERQ!L113 -> 204 | K29: =HAVERQ!E113-F29-G29-H29-I29-J29 -> 776 | M29: 38808 | N29: =100*(F29/SUM($F29:$K29)) -> 26.267117 | O29: =100*(G29/SUM($F29:$K29)) -> 28.614619 | P29: =100*(H29/SUM($F29:$K29)) -> 22.817002 | Q29: =100*(I29/SUM($F29:$K29)) -> 4.8728437 | R29: =100*(J29/SUM($F29:$K29)) -> 3.6279566 | S29: =100*(K29/SUM($F29:$K29)) -> 13.800462 | U29: 38808 | V29: =F29-AVERAGE(F$4:F$7) -> 267.75 | W29: =G29-AVERAGE(G$4:G$7) -> 169.25 | X29: =H29-AVERAGE(H$4:H$7) -> 104 | Y29: =I29-AVERAGE(I$4:I$7) -> 48.25 | Z29: =J29-AVERAGE(J$4:J$7) -> -12.25 | AA29: =K29-AVERAGE(K$4:K$7) -> -11.75 | AB29: =SUM(V29:AA29) -> 565.25 | BU29: 36617 | BV29: =HAVERQ!T89 -> 399 | BW29: =HAVERQ!U89+HAVERQ!W89+HAVERQ!X89 -> 334 | BX29: =HAVERQ!V89 -> 4002 | BY29: =HAVERQ!Y89 -> 1959 | BZ29: =HAVERQ!Z89+HAVERQ!AB89 -> 6712 | CA29: =HAVERQ!AA89+HAVERQ!AC89 -> 2491 | CB29: =HAVERQ!AD89+HAVERQ!AE89+HAVERQ!AF89+HAVERQ!AG89 -> 5340 | CC29: =HAVERQ!AH89+HAVERQ!AI89+HAVERQ!AJ89+HAVERQ!AK89+HAVERQ!AL89+HAVERQ!AM89 -> 8538 | CD29: =HAVERQ!S89-SUM('Chart Data'!BV29:CC29) -> 0 | DB29: 38443 | DC29: =HAVERQ!BI109/HAVERQ!T109 -> 9.7583548 | DD29: =HAVERQ!BJ109/HAVERQ!U109 -> 536.93103 | DE29: =HAVERQ!BK109/HAVERQ!V109 -> 14.739103 | DF29: =HAVERQ!BL109/HAVERQ!W109 -> 101.17808 | DG29: =HAVERQ!BM109/HAVERQ!X109 -> 44.71519 | DH29: =HAVERQ!BN109/HAVERQ!Y109 -> 14.838035 | DI29: =HAVERQ!BO109/HAVERQ!Z109 -> 10.560864 | DJ29: =HAVERQ!BP109/HAVERQ!AA109 -> 12.532291 | ... DT29: =HAVERQ!BZ109/HAVERQ!AK109 -> 10.213192 | DU29: =(HAVERQ!CA109+HAVERQ!CB109)/HAVERQ!AL109 -> 10.164649 | DX29: =FH39 -> Utilities | DY29: =FH46 -> Transport | FD29: 46113 | FE29: =DataQ!U220+DataQ!V220+DataQ!W220+DataQ!X220+DataQ!Y220 -> 12270.83 | FF29: =DataQ!J220+DataQ!Q220+DataQ!H220+DataQ!P220+DataQ!S220+DataQ!K220+DataQ!L220 -> 9061.5958 | FG29: =DataQ!N220+DataQ!I220+DataQ!R220+DataQ!G220+DataQ!T220+DataQ!M220+DataQ!O220 -> 15891.446 | FH29: =DataQ!F220-'Chart Data'!FE29-'Chart Data'!FF29-'Chart Data'!FG29 -> 0.99835 | FJ29: 46113 | FK29: =FE29-(AVERAGE(FE$20:FE$23)) -> 340.08 | FL29: =FF29-(AVERAGE(FF$20:FF$23)) -> 116.34585 | FM29: =FG29-(AVERAGE(FG$20:FG$23)) -> -26.8042 | FN29: =SUM(FK29:FM29) -> 429.62165 | FP29: 42767 | FQ29: =100*((AVERAGE(HAVERM!AS451:AS453)/AVERAGE(HAVERM!AS448:AS450))-1) -> 0.2965371 | FR29: =100*((AVERAGE(HAVERM!AT451:AT453)/AVERAGE(HAVERM!AT448:AT450))-1) -> -0.22416273 | FS29: =100*((AVERAGE(HAVERM!AU451:AU453)/AVERAGE(HAVERM!AU448:AU450))-1) -> -0.92703816 | FT29: =100*((AVERAGE(HAVERM!AV451:AV453)/AVERAGE(HAVERM!AV448:AV450))-1) -> 0.20090783 | FU29: =100*((AVERAGE(HAVERM!AW451:AW453)/AVERAGE(HAVERM!AW448:AW450))-1) -> 0.56400188 | FV29: =100*((AVERAGE(HAVERM!AX451:AX453)/AVERAGE(HAVERM!AX448:AX450))-1) -> 1.0723282 | FW29: =100*((AVERAGE(HAVERM!AY451:AY453)/AVERAGE(HAVERM!AY448:AY450))-1) -> 0.57302705 | FX29: =100*((AVERAGE(HAVERM!AZ451:AZ453)/AVERAGE(HAVERM!AZ448:AZ450))-1) -> 0.31954841 | ... GI29: =100*((AVERAGE(HAVERM!BK451:BK453)/AVERAGE(HAVERM!BK448:BK450))-1) -> 0.7453017 | GJ29: =100*(((AVERAGE(HAVERM!BL451:BL453)+(AVERAGE(HAVERM!BM451:BM453)))/(AVERAGE(HAVERM!BL448:BL450)+AVERAGE(HAVERM!BM448:BM450))-1)) -> 0.52202967 | GL29: 42767 | GM29: =100*((AVERAGE(GX27:GX29)/AVERAGE(GX24:GX26))-1) -> -0.22416273 | GN29: =100*((AVERAGE(GY27:GY29)/AVERAGE(GY24:GY26))-1) -> 0.59832974 | GO29: =100*((AVERAGE(GZ27:GZ29)/AVERAGE(GZ24:GZ26))-1) -> 0.20090783 | GP29: =100*((AVERAGE(HA27:HA29)/AVERAGE(HA24:HA26))-1) -> 0.57302705 | GQ29: =100*((AVERAGE(HB27:HB29)/AVERAGE(HB24:HB26))-1) -> 0.44083137 | GR29: =100*((AVERAGE(HC27:HC29)/AVERAGE(HC24:HC26))-1) -> 0.50307765 | GS29: =100*((AVERAGE(HD27:HD29)/AVERAGE(HD24:HD26))-1) -> -0.2213675 | GT29: =100*((AVERAGE(HE27:HE29)/AVERAGE(HE24:HE26))-1) -> 0.21400084 | GU29: =100*((AVERAGE(HF27:HF29)/AVERAGE(HF24:HF26))-1) -> 0.23559085 | GW29: 42767 | GX29: =HAVERM!AT453 -> 181842 | GY29: =HAVERM!AU453+HAVERM!AW453+HAVERM!AX453 -> 318503 | GZ29: =HAVERM!AV453 -> 2405098 | HA29: =HAVERM!AY453 -> 1203664 | HB29: =HAVERM!AZ453+HAVERM!BB453 -> 6453958 | HC29: =HAVERM!BA453+HAVERM!BC453 -> 2400255 | HD29: =HAVERM!BD453 -> 1078088 | HE29: =HAVERM!BE453+HAVERM!BF453+HAVERM!BG453 -> 4821537 | HF29: =HAVERM!BH453+HAVERM!BI453+HAVERM!BJ453+HAVERM!BK453+HAVERM!BL453+HAVERM!BM453 -> 9269503 | HZ29: 45748 | IA29: =IA28+(DataQ!AA216-DataQ!AA215) -> 5917.396 | IB29: =IB28+(DataQ!Z216-DataQ!Z215-(DataQ!AA216-DataQ!AA215)) -> 28079.784 | IC29: =DataQ!Z216-('Chart Data'!IA29+'Chart Data'!IB29) -> -36 | IE29: 45748 | IF29: =IA29-AVERAGE(IA$4:IA$7) -> 601.646 | IG29: =IB29-AVERAGE(IB$4:IB$7) -> 455.784 | II29: 45748 | IJ29: =100*(IA29/AVERAGE(IA$4:IA$7)) -> 111.31818 | IK29: =100*(IB29/AVERAGE(IB$4:IB$7)) -> 101.64996 | IM29: 45748 | IN29: =SUM(DataQ!U216:Y216) -> 12170.202 | IO29: =DataQ!F216-'Chart Data'!IN29 -> 24908.708 | IQ29: 45748 | IR29: =100*(IN29/AVERAGE(IN$4:IN$7)) -> 111.24245 | IS29: =100*(IO29/AVERAGE(IO$4:IO$7)) -> 101.15314
E30: 38899 | F30: =HAVERQ!P114 -> 1460 | G30: =HAVERQ!O114 -> 1611 | H30: =HAVERQ!N114 -> 1283 | I30: =HAVERQ!M114 -> 276 | J30: =HAVERQ!L114 -> 203 | K30: =HAVERQ!E114-F30-G30-H30-I30-J30 -> 768 | M30: 38899 | N30: =100*(F30/SUM($F30:$K30)) -> 26.066774 | O30: =100*(G30/SUM($F30:$K30)) -> 28.762721 | P30: =100*(H30/SUM($F30:$K30)) -> 22.906624 | Q30: =100*(I30/SUM($F30:$K30)) -> 4.9276915 | R30: =100*(J30/SUM($F30:$K30)) -> 3.6243528 | S30: =100*(K30/SUM($F30:$K30)) -> 13.711837 | U30: 38899 | V30: =F30-AVERAGE(F$4:F$7) -> 250.75 | W30: =G30-AVERAGE(G$4:G$7) -> 171.25 | X30: =H30-AVERAGE(H$4:H$7) -> 104 | Y30: =I30-AVERAGE(I$4:I$7) -> 50.25 | Z30: =J30-AVERAGE(J$4:J$7) -> -13.25 | AA30: =K30-AVERAGE(K$4:K$7) -> -19.75 | AB30: =SUM(V30:AA30) -> 543.25 | AE30: =RANK(AE26,$AE26:$AW26) -> 14 | AF30: =RANK(AF26,$AE26:$AW26) -> 13 | AG30: =RANK(AG26,$AE26:$AW26) -> 17 | AH30: =RANK(AH26,$AE26:$AW26) -> 12 | AI30: =RANK(AI26,$AE26:$AW26) -> 11 | AJ30: =RANK(AJ26,$AE26:$AW26) -> 18 | AK30: =RANK(AK26,$AE26:$AW26) -> 19 | AL30: =RANK(AL26,$AE26:$AW26) -> 8 | ... AW30: =RANK(AW26,$AE26:$AW26) -> 15 | BU30: 36708 | BV30: =HAVERQ!T90 -> 391 | BW30: =HAVERQ!U90+HAVERQ!W90+HAVERQ!X90 -> 335 | BX30: =HAVERQ!V90 -> 3960 | BY30: =HAVERQ!Y90 -> 1940 | BZ30: =HAVERQ!Z90+HAVERQ!AB90 -> 6746 | CA30: =HAVERQ!AA90+HAVERQ!AC90 -> 2541 | CB30: =HAVERQ!AD90+HAVERQ!AE90+HAVERQ!AF90+HAVERQ!AG90 -> 5424 | CC30: =HAVERQ!AH90+HAVERQ!AI90+HAVERQ!AJ90+HAVERQ!AK90+HAVERQ!AL90+HAVERQ!AM90 -> 8620 | CD30: =HAVERQ!S90-SUM('Chart Data'!BV30:CC30) -> 0 | DB30: 38534 | DC30: =HAVERQ!BI110/HAVERQ!T110 -> 10.096354 | DD30: =HAVERQ!BJ110/HAVERQ!U110 -> 472.95 | DE30: =HAVERQ!BK110/HAVERQ!V110 -> 14.854146 | DF30: =HAVERQ!BL110/HAVERQ!W110 -> 96.453333 | DG30: =HAVERQ!BM110/HAVERQ!X110 -> 44.765823 | DH30: =HAVERQ!BN110/HAVERQ!Y110 -> 14.37254 | DI30: =HAVERQ!BO110/HAVERQ!Z110 -> 10.678607 | DJ30: =HAVERQ!BP110/HAVERQ!AA110 -> 12.503719 | ... DT30: =HAVERQ!BZ110/HAVERQ!AK110 -> 10.634865 | DU30: =(HAVERQ!CA110+HAVERQ!CB110)/HAVERQ!AL110 -> 10.035067 | DX30: =FH40 -> Financial services | DY30: =FH47 -> Manufacturing | FD30: 46204 | FE30: =DataQ!U221+DataQ!V221+DataQ!W221+DataQ!X221+DataQ!Y221 -> 12287.432 | FF30: =DataQ!J221+DataQ!Q221+DataQ!H221+DataQ!P221+DataQ!S221+DataQ!K221+DataQ!L221 -> 9092.541 | FG30: =DataQ!N221+DataQ!I221+DataQ!R221+DataQ!G221+DataQ!T221+DataQ!M221+DataQ!O221 -> 15920.816 | FH30: =DataQ!F221-'Chart Data'!FE30-'Chart Data'!FF30-'Chart Data'!FG30 -> 1.00087 | FJ30: 46204 | FK30: =FE30-(AVERAGE(FE$20:FE$23)) -> 356.682 | FL30: =FF30-(AVERAGE(FF$20:FF$23)) -> 147.29103 | FM30: =FG30-(AVERAGE(FG$20:FG$23)) -> 2.5661 | FN30: =SUM(FK30:FM30) -> 506.53913 | FP30: 42795 | FQ30: =100*((AVERAGE(HAVERM!AS452:AS454)/AVERAGE(HAVERM!AS449:AS451))-1) -> 0.28697865 | FR30: =100*((AVERAGE(HAVERM!AT452:AT454)/AVERAGE(HAVERM!AT449:AT451))-1) -> -0.054605257 | FS30: =100*((AVERAGE(HAVERM!AU452:AU454)/AVERAGE(HAVERM!AU449:AU451))-1) -> -0.52213811 | FT30: =100*((AVERAGE(HAVERM!AV452:AV454)/AVERAGE(HAVERM!AV449:AV451))-1) -> 0.075056056 | FU30: =100*((AVERAGE(HAVERM!AW452:AW454)/AVERAGE(HAVERM!AW449:AW451))-1) -> 0.3781915 | FV30: =100*((AVERAGE(HAVERM!AX452:AX454)/AVERAGE(HAVERM!AX449:AX451))-1) -> 1.1446955 | FW30: =100*((AVERAGE(HAVERM!AY452:AY454)/AVERAGE(HAVERM!AY449:AY451))-1) -> 0.68761139 | FX30: =100*((AVERAGE(HAVERM!AZ452:AZ454)/AVERAGE(HAVERM!AZ449:AZ451))-1) -> 0.16148736 | ... GI30: =100*((AVERAGE(HAVERM!BK452:BK454)/AVERAGE(HAVERM!BK449:BK451))-1) -> 0.65558765 | GJ30: =100*(((AVERAGE(HAVERM!BL452:BL454)+(AVERAGE(HAVERM!BM452:BM454)))/(AVERAGE(HAVERM!BL449:BL451)+AVERAGE(HAVERM!BM449:BM451))-1)) -> 0.48742187 | GL30: 42795 | GM30: =100*((AVERAGE(GX28:GX30)/AVERAGE(GX25:GX27))-1) -> -0.054605257 | GN30: =100*((AVERAGE(GY28:GY30)/AVERAGE(GY25:GY27))-1) -> 0.64082248 | GO30: =100*((AVERAGE(GZ28:GZ30)/AVERAGE(GZ25:GZ27))-1) -> 0.075056056 | GP30: =100*((AVERAGE(HA28:HA30)/AVERAGE(HA25:HA27))-1) -> 0.68761139 | GQ30: =100*((AVERAGE(HB28:HB30)/AVERAGE(HB25:HB27))-1) -> 0.35878843 | GR30: =100*((AVERAGE(HC28:HC30)/AVERAGE(HC25:HC27))-1) -> 0.57052884 | GS30: =100*((AVERAGE(HD28:HD30)/AVERAGE(HD25:HD27))-1) -> -0.25142456 | GT30: =100*((AVERAGE(HE28:HE30)/AVERAGE(HE25:HE27))-1) -> 0.2846601 | GU30: =100*((AVERAGE(HF28:HF30)/AVERAGE(HF25:HF27))-1) -> 0.22580962 | GW30: 42795 | GX30: =HAVERM!AT454 -> 181881 | GY30: =HAVERM!AU454+HAVERM!AW454+HAVERM!AX454 -> 319754 | GZ30: =HAVERM!AV454 -> 2406415 | HA30: =HAVERM!AY454 -> 1208222 | HB30: =HAVERM!AZ454+HAVERM!BB454 -> 6461538 | HC30: =HAVERM!BA454+HAVERM!BC454 -> 2409376 | HD30: =HAVERM!BD454 -> 1076194 | HE30: =HAVERM!BE454+HAVERM!BF454+HAVERM!BG454 -> 4830963 | HF30: =HAVERM!BH454+HAVERM!BI454+HAVERM!BJ454+HAVERM!BK454+HAVERM!BL454+HAVERM!BM454 -> 9277419 | HZ30: 45839 | IA30: =IA29+(DataQ!AA217-DataQ!AA216) -> 5941.052 | IB30: =IB29+(DataQ!Z217-DataQ!Z216-(DataQ!AA217-DataQ!AA216)) -> 28035.308 | IC30: =DataQ!Z217-('Chart Data'!IA30+'Chart Data'!IB30) -> -36 | IE30: 45839 | IF30: =IA30-AVERAGE(IA$4:IA$7) -> 625.302 | IG30: =IB30-AVERAGE(IB$4:IB$7) -> 411.308 | II30: 45839 | IJ30: =100*(IA30/AVERAGE(IA$4:IA$7)) -> 111.76319 | IK30: =100*(IB30/AVERAGE(IB$4:IB$7)) -> 101.48895 | IM30: 45839 | IN30: =SUM(DataQ!U217:Y217) -> 12205.913 | IO30: =DataQ!F217-'Chart Data'!IN30 -> 24850.267 | IQ30: 45839 | IR30: =100*(IN30/AVERAGE(IN$4:IN$7)) -> 111.56887 | IS30: =100*(IO30/AVERAGE(IO$4:IO$7)) -> 100.91581
E31: 38991 | F31: =HAVERQ!P115 -> 1447 | G31: =HAVERQ!O115 -> 1611 | H31: =HAVERQ!N115 -> 1280 | I31: =HAVERQ!M115 -> 279 | J31: =HAVERQ!L115 -> 202 | K31: =HAVERQ!E115-F31-G31-H31-I31-J31 -> 763 | M31: 38991 | N31: =100*(F31/SUM($F31:$K31)) -> 25.922608 | O31: =100*(G31/SUM($F31:$K31)) -> 28.860623 | P31: =100*(H31/SUM($F31:$K31)) -> 22.930849 | Q31: =100*(I31/SUM($F31:$K31)) -> 4.9982085 | R31: =100*(J31/SUM($F31:$K31)) -> 3.6187746 | S31: =100*(K31/SUM($F31:$K31)) -> 13.668936 | U31: 38991 | V31: =F31-AVERAGE(F$4:F$7) -> 237.75 | W31: =G31-AVERAGE(G$4:G$7) -> 171.25 | X31: =H31-AVERAGE(H$4:H$7) -> 101 | Y31: =I31-AVERAGE(I$4:I$7) -> 53.25 | Z31: =J31-AVERAGE(J$4:J$7) -> -14.25 | AA31: =K31-AVERAGE(K$4:K$7) -> -24.75 | AB31: =SUM(V31:AA31) -> 524.25 | AE31: =AE3 -> Agriculture | AF31: =AF3 -> Extraction | AG31: =AG3 -> Manufacturing | AH31: =AH3 -> Utilities | AI31: =AI3 -> Water | AJ31: =AJ3 -> Construction | AK31: =AK3 -> Wholesale & retail | AL31: =AL3 -> Transport | ... AW31: =AW3 -> Other services | AY31: Total | BU31: 36800 | BV31: =HAVERQ!T91 -> 377 | BW31: =HAVERQ!U91+HAVERQ!W91+HAVERQ!X91 -> 340 | BX31: =HAVERQ!V91 -> 3904 | BY31: =HAVERQ!Y91 -> 1936 | BZ31: =HAVERQ!Z91+HAVERQ!AB91 -> 6769 | CA31: =HAVERQ!AA91+HAVERQ!AC91 -> 2596 | CB31: =HAVERQ!AD91+HAVERQ!AE91+HAVERQ!AF91+HAVERQ!AG91 -> 5502 | CC31: =HAVERQ!AH91+HAVERQ!AI91+HAVERQ!AJ91+HAVERQ!AK91+HAVERQ!AL91+HAVERQ!AM91 -> 8589 | CD31: =HAVERQ!S91-SUM('Chart Data'!BV31:CC31) -> -1 | DB31: 38626 | DC31: =HAVERQ!BI111/HAVERQ!T111 -> 9.9870466 | DD31: =HAVERQ!BJ111/HAVERQ!U111 -> 460.98361 | DE31: =HAVERQ!BK111/HAVERQ!V111 -> 15.261264 | DF31: =HAVERQ!BL111/HAVERQ!W111 -> 102.52055 | DG31: =HAVERQ!BM111/HAVERQ!X111 -> 44.987097 | DH31: =HAVERQ!BN111/HAVERQ!Y111 -> 14.311022 | DI31: =HAVERQ!BO111/HAVERQ!Z111 -> 10.973726 | DJ31: =HAVERQ!BP111/HAVERQ!AA111 -> 12.703481 | ... DT31: =HAVERQ!BZ111/HAVERQ!AK111 -> 10.532634 | DU31: =(HAVERQ!CA111+HAVERQ!CB111)/HAVERQ!AL111 -> 9.7956989 | DX31: =FH41 -> Extraction | DY31: =FH48 -> Real estate | FD31: 46296 | FE31: =DataQ!U222+DataQ!V222+DataQ!W222+DataQ!X222+DataQ!Y222 -> 12310.986 | FF31: =DataQ!J222+DataQ!Q222+DataQ!H222+DataQ!P222+DataQ!S222+DataQ!K222+DataQ!L222 -> 9125.2474 | FG31: =DataQ!N222+DataQ!I222+DataQ!R222+DataQ!G222+DataQ!T222+DataQ!M222+DataQ!O222 -> 15957.822 | FH31: =DataQ!F222-'Chart Data'!FE31-'Chart Data'!FF31-'Chart Data'!FG31 -> 1.00493 | FJ31: 46296 | FK31: =FE31-(AVERAGE(FE$20:FE$23)) -> 380.236 | FL31: =FF31-(AVERAGE(FF$20:FF$23)) -> 179.99737 | FM31: =FG31-(AVERAGE(FG$20:FG$23)) -> 39.5717 | FN31: =SUM(FK31:FM31) -> 599.80507 | FP31: 42826 | FQ31: =100*((AVERAGE(HAVERM!AS453:AS455)/AVERAGE(HAVERM!AS450:AS452))-1) -> 0.33291897 | FR31: =100*((AVERAGE(HAVERM!AT453:AT455)/AVERAGE(HAVERM!AT450:AT452))-1) -> 0.20792882 | FS31: =100*((AVERAGE(HAVERM!AU453:AU455)/AVERAGE(HAVERM!AU450:AU452))-1) -> -0.18654167 | FT31: =100*((AVERAGE(HAVERM!AV453:AV455)/AVERAGE(HAVERM!AV450:AV452))-1) -> 0.14430915 | FU31: =100*((AVERAGE(HAVERM!AW453:AW455)/AVERAGE(HAVERM!AW450:AW452))-1) -> 0.34835106 | FV31: =100*((AVERAGE(HAVERM!AX453:AX455)/AVERAGE(HAVERM!AX450:AX452))-1) -> 0.97235424 | FW31: =100*((AVERAGE(HAVERM!AY453:AY455)/AVERAGE(HAVERM!AY450:AY452))-1) -> 0.86403144 | FX31: =100*((AVERAGE(HAVERM!AZ453:AZ455)/AVERAGE(HAVERM!AZ450:AZ452))-1) -> 0.060240504 | ... GI31: =100*((AVERAGE(HAVERM!BK453:BK455)/AVERAGE(HAVERM!BK450:BK452))-1) -> 0.72962809 | GJ31: =100*(((AVERAGE(HAVERM!BL453:BL455)+(AVERAGE(HAVERM!BM453:BM455)))/(AVERAGE(HAVERM!BL450:BL452)+AVERAGE(HAVERM!BM450:BM452))-1)) -> 0.49259457 | GL31: 42826 | GM31: =100*((AVERAGE(GX29:GX31)/AVERAGE(GX26:GX28))-1) -> 0.20792882 | GN31: =100*((AVERAGE(GY29:GY31)/AVERAGE(GY26:GY28))-1) -> 0.59379802 | GO31: =100*((AVERAGE(GZ29:GZ31)/AVERAGE(GZ26:GZ28))-1) -> 0.14430915 | GP31: =100*((AVERAGE(HA29:HA31)/AVERAGE(HA26:HA28))-1) -> 0.86403144 | GQ31: =100*((AVERAGE(HB29:HB31)/AVERAGE(HB26:HB28))-1) -> 0.31538858 | GR31: =100*((AVERAGE(HC29:HC31)/AVERAGE(HC26:HC28))-1) -> 0.6950032 | GS31: =100*((AVERAGE(HD29:HD31)/AVERAGE(HD26:HD28))-1) -> -0.17068963 | GT31: =100*((AVERAGE(HE29:HE31)/AVERAGE(HE26:HE28))-1) -> 0.41231637 | GU31: =100*((AVERAGE(HF29:HF31)/AVERAGE(HF26:HF28))-1) -> 0.24285083 | GW31: 42826 | GX31: =HAVERM!AT455 -> 182308 | GY31: =HAVERM!AU455+HAVERM!AW455+HAVERM!AX455 -> 318895 | GZ31: =HAVERM!AV455 -> 2409801 | HA31: =HAVERM!AY455 -> 1208464 | HB31: =HAVERM!AZ455+HAVERM!BB455 -> 6473047 | HC31: =HAVERM!BA455+HAVERM!BC455 -> 2412703 | HD31: =HAVERM!BD455 -> 1077647 | HE31: =HAVERM!BE455+HAVERM!BF455+HAVERM!BG455 -> 4845703 | HF31: =HAVERM!BH455+HAVERM!BI455+HAVERM!BJ455+HAVERM!BK455+HAVERM!BL455+HAVERM!BM455 -> 9277443 | HZ31: 45931 | IA31: =IA30+(DataQ!AA218-DataQ!AA217) -> 5957.568 | IB31: =IB30+(DataQ!Z218-DataQ!Z217-(DataQ!AA218-DataQ!AA217)) -> 28051.932 | IC31: =DataQ!Z218-('Chart Data'!IA31+'Chart Data'!IB31) -> -36 | IE31: 45931 | IF31: =IA31-AVERAGE(IA$4:IA$7) -> 641.818 | IG31: =IB31-AVERAGE(IB$4:IB$7) -> 427.932 | II31: 45931 | IJ31: =100*(IA31/AVERAGE(IA$4:IA$7)) -> 112.07389 | IK31: =100*(IB31/AVERAGE(IB$4:IB$7)) -> 101.54913 | IM31: 45931 | IN31: =SUM(DataQ!U218:Y218) -> 12237.33 | IO31: =DataQ!F218-'Chart Data'!IN31 -> 24855.04 | IQ31: 45931 | IR31: =100*(IN31/AVERAGE(IN$4:IN$7)) -> 111.85604 | IS31: =100*(IO31/AVERAGE(IO$4:IO$7)) -> 100.9352
E32: 39083 | F32: =HAVERQ!P116 -> 1448 | G32: =HAVERQ!O116 -> 1618 | H32: =HAVERQ!N116 -> 1276 | I32: =HAVERQ!M116 -> 282 | J32: =HAVERQ!L116 -> 199 | K32: =HAVERQ!E116-F32-G32-H32-I32-J32 -> 764 | M32: 39083 | N32: =100*(F32/SUM($F32:$K32)) -> 25.917308 | O32: =100*(G32/SUM($F32:$K32)) -> 28.960086 | P32: =100*(H32/SUM($F32:$K32)) -> 22.838733 | Q32: =100*(I32/SUM($F32:$K32)) -> 5.0474315 | R32: =100*(J32/SUM($F32:$K32)) -> 3.56184 | S32: =100*(K32/SUM($F32:$K32)) -> 13.674602 | U32: 39083 | V32: =F32-AVERAGE(F$4:F$7) -> 238.75 | W32: =G32-AVERAGE(G$4:G$7) -> 178.25 | X32: =H32-AVERAGE(H$4:H$7) -> 97 | Y32: =I32-AVERAGE(I$4:I$7) -> 56.25 | Z32: =J32-AVERAGE(J$4:J$7) -> -17.25 | AA32: =K32-AVERAGE(K$4:K$7) -> -23.75 | AB32: =SUM(V32:AA32) -> 529.25 | AD32: =AD28 -> 45658 | AE32: =AE28 -> -48.25 | AF32: =AF28 -> -10.25 | AG32: =AG28 -> -100.75 | AH32: =AH28 -> -2.75 | AI32: =AI28 -> 25.5 | AJ32: =AJ28 -> -84.25 | AK32: =AK28 -> -297.5 | ... AW32: =AW28 -> 27.5 | AY32: =SUM(AE32:AW32) -> 1527.75 | BU32: 36892 | BV32: =HAVERQ!T92 -> 357 | BW32: =HAVERQ!U92+HAVERQ!W92+HAVERQ!X92 -> 345 | BX32: =HAVERQ!V92 -> 3879 | BY32: =HAVERQ!Y92 -> 1937 | BZ32: =HAVERQ!Z92+HAVERQ!AB92 -> 6814 | CA32: =HAVERQ!AA92+HAVERQ!AC92 -> 2596 | CB32: =HAVERQ!AD92+HAVERQ!AE92+HAVERQ!AF92+HAVERQ!AG92 -> 5516 | CC32: =HAVERQ!AH92+HAVERQ!AI92+HAVERQ!AJ92+HAVERQ!AK92+HAVERQ!AL92+HAVERQ!AM92 -> 8581 | CD32: =HAVERQ!S92-SUM('Chart Data'!BV32:CC32) -> 1 | DB32: 38718 | DC32: =HAVERQ!BI112/HAVERQ!T112 -> 10.379679 | DD32: =HAVERQ!BJ112/HAVERQ!U112 -> 481.37288 | DE32: =HAVERQ!BK112/HAVERQ!V112 -> 15.750822 | DF32: =HAVERQ!BL112/HAVERQ!W112 -> 111.34247 | DG32: =HAVERQ!BM112/HAVERQ!X112 -> 41.446541 | DH32: =HAVERQ!BN112/HAVERQ!Y112 -> 14.400709 | DI32: =HAVERQ!BO112/HAVERQ!Z112 -> 11.208226 | DJ32: =HAVERQ!BP112/HAVERQ!AA112 -> 12.690776 | ... DT32: =HAVERQ!BZ112/HAVERQ!AK112 -> 10.428405 | DU32: =(HAVERQ!CA112+HAVERQ!CB112)/HAVERQ!AL112 -> 9.9032258 | DX32: =FH42 -> Communications | DY32: =FH49 -> Agriculture | FD32: 46388 | FE32: =DataQ!U223+DataQ!V223+DataQ!W223+DataQ!X223+DataQ!Y223 -> 12340.11 | FF32: =DataQ!J223+DataQ!Q223+DataQ!H223+DataQ!P223+DataQ!S223+DataQ!K223+DataQ!L223 -> 9159.4116 | FG32: =DataQ!N223+DataQ!I223+DataQ!R223+DataQ!G223+DataQ!T223+DataQ!M223+DataQ!O223 -> 15995.803 | FH32: =DataQ!F223-'Chart Data'!FE32-'Chart Data'!FF32-'Chart Data'!FG32 -> 0.99529 | FJ32: 46388 | FK32: =FE32-(AVERAGE(FE$20:FE$23)) -> 409.36 | FL32: =FF32-(AVERAGE(FF$20:FF$23)) -> 214.16161 | FM32: =FG32-(AVERAGE(FG$20:FG$23)) -> 77.5531 | FN32: =SUM(FK32:FM32) -> 701.07471 | FP32: 42856 | FQ32: =100*((AVERAGE(HAVERM!AS454:AS456)/AVERAGE(HAVERM!AS451:AS453))-1) -> 0.37391157 | FR32: =100*((AVERAGE(HAVERM!AT454:AT456)/AVERAGE(HAVERM!AT451:AT453))-1) -> 0.2508927 | FS32: =100*((AVERAGE(HAVERM!AU454:AU456)/AVERAGE(HAVERM!AU451:AU453))-1) -> 0.030140083 | FT32: =100*((AVERAGE(HAVERM!AV454:AV456)/AVERAGE(HAVERM!AV451:AV453))-1) -> 0.18690698 | FU32: =100*((AVERAGE(HAVERM!AW454:AW456)/AVERAGE(HAVERM!AW451:AW453))-1) -> 0.3557974 | FV32: =100*((AVERAGE(HAVERM!AX454:AX456)/AVERAGE(HAVERM!AX451:AX453))-1) -> 0.80314078 | FW32: =100*((AVERAGE(HAVERM!AY454:AY456)/AVERAGE(HAVERM!AY451:AY453))-1) -> 0.85743714 | FX32: =100*((AVERAGE(HAVERM!AZ454:AZ456)/AVERAGE(HAVERM!AZ451:AZ453))-1) -> 0.069786616 | ... GI32: =100*((AVERAGE(HAVERM!BK454:BK456)/AVERAGE(HAVERM!BK451:BK453))-1) -> 0.6080079 | GJ32: =100*(((AVERAGE(HAVERM!BL454:BL456)+(AVERAGE(HAVERM!BM454:BM456)))/(AVERAGE(HAVERM!BL451:BL453)+AVERAGE(HAVERM!BM451:BM453))-1)) -> 0.51926551 | GL32: 42856 | GM32: =100*((AVERAGE(GX30:GX32)/AVERAGE(GX27:GX29))-1) -> 0.2508927 | GN32: =100*((AVERAGE(GY30:GY32)/AVERAGE(GY27:GY29))-1) -> 0.54127312 | GO32: =100*((AVERAGE(GZ30:GZ32)/AVERAGE(GZ27:GZ29))-1) -> 0.18690698 | GP32: =100*((AVERAGE(HA30:HA32)/AVERAGE(HA27:HA29))-1) -> 0.85743714 | GQ32: =100*((AVERAGE(HB30:HB32)/AVERAGE(HB27:HB29))-1) -> 0.31208299 | GR32: =100*((AVERAGE(HC30:HC32)/AVERAGE(HC27:HC29))-1) -> 0.76340744 | GS32: =100*((AVERAGE(HD30:HD32)/AVERAGE(HD27:HD29))-1) -> -0.16037377 | GT32: =100*((AVERAGE(HE30:HE32)/AVERAGE(HE27:HE29))-1) -> 0.61884744 | GU32: =100*((AVERAGE(HF30:HF32)/AVERAGE(HF27:HF29))-1) -> 0.23367638 | GW32: 42856 | GX32: =HAVERM!AT456 -> 182432 | GY32: =HAVERM!AU456+HAVERM!AW456+HAVERM!AX456 -> 319819 | GZ32: =HAVERM!AV456 -> 2411552 | HA32: =HAVERM!AY456 -> 1211272 | HB32: =HAVERM!AZ456+HAVERM!BB456 -> 6475463 | HC32: =HAVERM!BA456+HAVERM!BC456 -> 2417531 | HD32: =HAVERM!BD456 -> 1075914 | HE32: =HAVERM!BE456+HAVERM!BF456+HAVERM!BG456 -> 4863659 | HF32: =HAVERM!BH456+HAVERM!BI456+HAVERM!BJ456+HAVERM!BK456+HAVERM!BL456+HAVERM!BM456 -> 9289067 | HZ32: 46023 | IA32: =IA31+(DataQ!AA219-DataQ!AA218) -> 5965.523 | IB32: =IB31+(DataQ!Z219-DataQ!Z218-(DataQ!AA219-DataQ!AA218)) -> 28100.887 | IC32: =DataQ!Z219-('Chart Data'!IA32+'Chart Data'!IB32) -> -36 | IE32: 46023 | IF32: =IA32-AVERAGE(IA$4:IA$7) -> 649.773 | IG32: =IB32-AVERAGE(IB$4:IB$7) -> 476.887 | II32: 46023 | IJ32: =100*(IA32/AVERAGE(IA$4:IA$7)) -> 112.22354 | IK32: =100*(IB32/AVERAGE(IB$4:IB$7)) -> 101.72635 | IM32: 46023 | IN32: =SUM(DataQ!U219:Y219) -> 12256.296 | IO32: =DataQ!F219-'Chart Data'!IN32 -> 24900.204 | IQ32: 46023 | IR32: =100*(IN32/AVERAGE(IN$4:IN$7)) -> 112.0294 | IS32: =100*(IO32/AVERAGE(IO$4:IO$7)) -> 101.11861
