Workbook
Name _1_: #REF!
Name _2ecm: #REF!
Name _3ecw: #REF!
Name _bot1: #REF!
Name _bot1: #REF!
Name _bot2: #REF!
Name _bot2: #REF!
Name _bot3: #REF!
Name _bot3: #REF!
Name _bot4: #REF!
Name _bot4: #REF!
Name _bot5: #REF!
Name _bot5: #REF!
Name _bot6: #REF!
Name _bot6: #REF!
Name _DLX1.INC: HAVERM!$B$2:$AH$7
Name _DLX2.INC: #REF!
Name _DLX2.INC: HAVERD!$G$3:$GV$8
Name _DLX3.INC: #REF!
Name _DLX3.INC: HAVERQ!$B$2:$H$7
Name _DLX6.INC: #REF!
Name _DLX7.INC: #REF!
Name _MYE4: #REF!
Name _MYE5: #REF!
Name _MYE6: #REF!
Name _OEP.MPCScenarios: 'Table - MPC scenarios'!$B$3:$E$12
Name _top1: #REF!
Name _top1: #REF!
Name _top2: #REF!
Name _top2: #REF!
Name _top3: #REF!
Name _top3: #REF!
Name _top4: #REF!
Name _top4: #REF!
Name _top5: #REF!
Name _top5: #REF!
Name _top6: #REF!
Name _top6: #REF!
Name a: SERIES1s:SERIES1e
Name About_these_data: #REF!
Name AllNSAData: #REF!
Name AllSAData: #REF!
Name AME: OFFSET(#REF!,0,0,MAX(#REF!),1)
Name Amytest: #REF!
Name Ann: #REF!
Name Ann_chg: #REF!
Name appended: OFFSET(#REF!,0,0,MAX(#REF!)+MAX(#REF!),#REF!)
Name approx2: #REF!
Name approx3: #REF!
Name approx4: #REF!
Name approx5: #REF!
Name approx6: #REF!
Name approx7: #REF!
Name Apr_50: #REF!
Name Apr_51: #REF!
Name Apr_52: #REF!
Name Apr_53: #REF!
Name Apr_54: #REF!
Name Apr_55: #REF!
Name Apr_56: #REF!

Sheet >> MARKET PRICING CHARTS

Sheet >> DATA

Sheet Chart Data
A1: Services inflation | H1: Private sector pay growth | L1: Inflation forecasts | S1: BoE DMP | Y1: BoE DMP
B2: Outturn | C2: BoE staff forecast (May) | D2: BoE staff forecast (Aug) | E2: BoE staff forecast (Nov) | F2: BoE staff forecast (Feb)
B3: Outturn | F3: BoE forecast | I3: Outturn | J3: BoE forecast | M3: CPI inflation | N3: BoE forecast, market interest rate expectations (Feb) | O3: OE (Mar) | P3: HMT consensus (Feb) | Q3: 2% LINE | T3: Prices - past year | U3: Prices - next year | V3: Wages - past year | W3: Wages - next year | Z3: Prices - past year | AA3: Prices - next year | AB3: Wages - past year | AC3: Wages - next year
A4: 44562 | B4: =100*((HAVERM!D152/HAVERM!D140)-1) -> 3.2685512 | H4: 44562 | I4: =HAVERM!E152 -> 4.2 | L4: 44927 | M4: =100*((HAVERQ!F40/HAVERQ!F36)-1) -> 10.178263 | Q4: 2 | S4: 43466 | T4: =HAVERM!F116 -> 2.79 | U4: =HAVERM!G116 -> 2.531 | V4: =HAVERM!H116 -> #N/A | W4: =HAVERM!I116 -> #N/A | Y4: 43466 | Z4: =HAVERM!J116 -> 2.525 | AA4: =HAVERM!K116 -> 2.471 | AB4: =HAVERM!L116 -> #N/A | AC4: =HAVERM!M116 -> #N/A
A5: 44593 | B5: =100*((HAVERM!D153/HAVERM!D141)-1) -> 3.4391534 | H5: 44593 | I5: =HAVERM!E153 -> 4.6 | L5: 45017 | M5: =100*((HAVERQ!F41/HAVERQ!F37)-1) -> 8.4390513 | Q5: 2 | S5: 43497 | T5: =HAVERM!F117 -> 2.23 | U5: =HAVERM!G117 -> 2.56 | V5: =HAVERM!H117 -> #N/A | W5: =HAVERM!I117 -> #N/A | Y5: 43497 | Z5: =HAVERM!J117 -> 2.415 | AA5: =HAVERM!K117 -> 2.424 | AB5: =HAVERM!L117 -> #N/A | AC5: =HAVERM!M117 -> #N/A
A6: 44621 | B6: =100*((HAVERM!D154/HAVERM!D142)-1) -> 3.9612676 | H6: 44621 | I6: =HAVERM!E154 -> 4.9 | L6: 45108 | M6: =100*((HAVERQ!F42/HAVERQ!F38)-1) -> 6.7135896 | Q6: 2 | S6: 43525 | T6: =HAVERM!F118 -> 2.4 | U6: =HAVERM!G118 -> 2.066 | V6: =HAVERM!H118 -> #N/A | W6: =HAVERM!I118 -> #N/A | Y6: 43525 | Z6: =HAVERM!J118 -> 2.474 | AA6: =HAVERM!K118 -> 2.386 | AB6: =HAVERM!L118 -> #N/A | AC6: =HAVERM!M118 -> #N/A
A7: 44652 | B7: =100*((HAVERM!D155/HAVERM!D143)-1) -> 4.7244094 | H7: 44652 | I7: =HAVERM!E155 -> 4.8 | L7: 45200 | M7: =100*((HAVERQ!F43/HAVERQ!F39)-1) -> 4.1568008 | Q7: 2 | S7: 43556 | T7: =HAVERM!F119 -> 2.87 | U7: =HAVERM!G119 -> 2.705 | V7: =HAVERM!H119 -> #N/A | W7: =HAVERM!I119 -> #N/A | Y7: 43556 | Z7: =HAVERM!J119 -> 2.501 | AA7: =HAVERM!K119 -> 2.444 | AB7: =HAVERM!L119 -> #N/A | AC7: =HAVERM!M119 -> #N/A
A8: 44682 | B8: =100*((HAVERM!D156/HAVERM!D144)-1) -> 4.886562 | H8: 44682 | I8: =HAVERM!E156 -> 5.1 | L8: 45292 | M8: =100*((HAVERQ!F44/HAVERQ!F40)-1) -> 3.5490605 | O8: =100*((GMW!B211/GMW!B207)-1) -> 3.5491137 | Q8: 2 | S8: 43586 | T8: =HAVERM!F120 -> 1.78 | U8: =HAVERM!G120 -> 2.318 | V8: =HAVERM!H120 -> #N/A | W8: =HAVERM!I120 -> #N/A | Y8: 43586 | Z8: =HAVERM!J120 -> 2.348 | AA8: =HAVERM!K120 -> 2.363 | AB8: =HAVERM!L120 -> #N/A | AC8: =HAVERM!M120 -> #N/A
A9: 44713 | B9: =100*((HAVERM!D157/HAVERM!D145)-1) -> 5.2173913 | H9: 44713 | I9: =HAVERM!E157 -> 5.4 | L9: 45383 | M9: =100*((HAVERQ!F45/HAVERQ!F41)-1) -> 2.110885 | O9: =100*((GMW!B212/GMW!B208)-1) -> 2.1108336 | Q9: 2 | S9: 43617 | T9: =HAVERM!F121 -> 2.7 | U9: =HAVERM!G121 -> 2.158 | V9: =HAVERM!H121 -> #N/A | W9: =HAVERM!I121 -> #N/A | Y9: 43617 | Z9: =HAVERM!J121 -> 2.449 | AA9: =HAVERM!K121 -> 2.394 | AB9: =HAVERM!L121 -> #N/A | AC9: =HAVERM!M121 -> #N/A
A10: 44743 | B10: =100*((HAVERM!D158/HAVERM!D146)-1) -> 5.7241977 | H10: 44743 | I10: =HAVERM!E158 -> 6 | L10: 45474 | M10: =100*((HAVERQ!F46/HAVERQ!F42)-1) -> 2.0547945 | O10: =100*((GMW!B213/GMW!B209)-1) -> 2.0547945 | Q10: 2 | S10: 43647 | T10: =HAVERM!F122 -> 2.26 | U10: =HAVERM!G122 -> 2.099 | V10: =HAVERM!H122 -> #N/A | W10: =HAVERM!I122 -> #N/A | Y10: 43647 | Z10: =HAVERM!J122 -> 2.246 | AA10: =HAVERM!K122 -> 2.192 | AB10: =HAVERM!L122 -> #N/A | AC10: =HAVERM!M122 -> #N/A
A11: 44774 | B11: =100*((HAVERM!D159/HAVERM!D147)-1) -> 5.9585492 | H11: 44774 | I11: =HAVERM!E159 -> 6.2 | L11: 45566 | M11: =100*((HAVERQ!F47/HAVERQ!F43)-1) -> 2.4753726 | O11: =100*((GMW!B214/GMW!B210)-1) -> 2.4753214 | Q11: 2 | S11: 43678 | T11: =HAVERM!F123 -> 1.91 | U11: =HAVERM!G123 -> 2.281 | V11: =HAVERM!H123 -> #N/A | W11: =HAVERM!I123 -> #N/A | Y11: 43678 | Z11: =HAVERM!J123 -> 2.291 | AA11: =HAVERM!K123 -> 2.179 | AB11: =HAVERM!L123 -> #N/A | AC11: =HAVERM!M123 -> #N/A
A12: 44805 | B12: =100*((HAVERM!D160/HAVERM!D148)-1) -> 6.1312608 | H12: 44805 | I12: =HAVERM!E160 -> 6.6 | L12: 45658 | N12: =HAVERQ!C48 -> 2.8 | O12: =100*((GMW!B215/GMW!B211)-1) -> 2.7942785 | Q12: 2 | S12: 43709 | T12: =HAVERM!F124 -> 2.26 | U12: =HAVERM!G124 -> 2.345 | V12: =HAVERM!H124 -> #N/A | W12: =HAVERM!I124 -> #N/A | Y12: 43709 | Z12: =HAVERM!J124 -> 2.142 | AA12: =HAVERM!K124 -> 2.241 | AB12: =HAVERM!L124 -> #N/A | AC12: =HAVERM!M124 -> #N/A
A13: 44835 | B13: =100*((HAVERM!D161/HAVERM!D149)-1) -> 6.2660944 | H13: 44835 | I13: =HAVERM!E161 -> 6.9 | L13: 45748 | N13: =HAVERQ!C49 -> 3.5 | O13: =100*((GMW!B216/GMW!B212)-1) -> 3.1688675 | Q13: 2 | S13: 43739 | T13: =HAVERM!F125 -> 1.99 | U13: =HAVERM!G125 -> 2.214 | V13: =HAVERM!H125 -> #N/A | W13: =HAVERM!I125 -> #N/A | Y13: 43739 | Z13: =HAVERM!J125 -> 2.053 | AA13: =HAVERM!K125 -> 2.28 | AB13: =HAVERM!L125 -> #N/A | AC13: =HAVERM!M125 -> #N/A
A14: 44866 | B14: =100*((HAVERM!D162/HAVERM!D150)-1) -> 6.3464837 | H14: 44866 | I14: =HAVERM!E162 -> 7.3 | L14: 45839 | N14: =HAVERQ!C50 -> 3.7 | O14: =100*((GMW!B217/GMW!B213)-1) -> 3.4616704 | Q14: 2 | S14: 43770 | T14: =HAVERM!F126 -> 1.86 | U14: =HAVERM!G126 -> 2.152 | V14: =HAVERM!H126 -> #N/A | W14: =HAVERM!I126 -> #N/A | Y14: 43770 | Z14: =HAVERM!J126 -> 2.037 | AA14: =HAVERM!K126 -> 2.237 | AB14: =HAVERM!L126 -> #N/A | AC14: =HAVERM!M126 -> #N/A
A15: 44896 | B15: =100*((HAVERM!D163/HAVERM!D151)-1) -> 6.8376068 | H15: 44896 | I15: =HAVERM!E163 -> 7.3 | L15: 45931 | N15: =HAVERQ!C51 -> 3.5 | O15: =100*((GMW!B218/GMW!B214)-1) -> 3.1802078 | P15: 2.8 | Q15: 2 | S15: 43800 | T15: =HAVERM!F127 -> 1.99 | U15: =HAVERM!G127 -> 2.372 | V15: =HAVERM!H127 -> #N/A | W15: =HAVERM!I127 -> #N/A | Y15: 43800 | Z15: =HAVERM!J127 -> 1.948 | AA15: =HAVERM!K127 -> 2.246 | AB15: =HAVERM!L127 -> #N/A | AC15: =HAVERM!M127 -> #N/A
A16: 44927 | B16: =100*((HAVERM!D164/HAVERM!D152)-1) -> 5.9024808 | H16: 44927 | I16: =HAVERM!E164 -> 7.1 | L16: 46023 | N16: =HAVERQ!C52 -> 3 | O16: =100*((GMW!B219/GMW!B215)-1) -> 3.1185782 | Q16: 2 | S16: 43831 | T16: =HAVERM!F128 -> 2.06 | U16: =HAVERM!G128 -> 2.117 | V16: =HAVERM!H128 -> #N/A | W16: =HAVERM!I128 -> #N/A | Y16: 43831 | Z16: =HAVERM!J128 -> 1.971 | AA16: =HAVERM!K128 -> 2.214 | AB16: =HAVERM!L128 -> #N/A | AC16: =HAVERM!M128 -> #N/A
A17: 44958 | B17: =100*((HAVERM!D165/HAVERM!D153)-1) -> 6.6496164 | H17: 44958 | I17: =HAVERM!E165 -> 7.1 | L17: 46113 | N17: =HAVERQ!C53 -> 2.6 | O17: =100*((GMW!B220/GMW!B216)-1) -> 2.5062593 | Q17: 2 | S17: 43862 | T17: =HAVERM!F129 -> 1.74 | U17: =HAVERM!G129 -> 2.094 | V17: =HAVERM!H129 -> #N/A | W17: =HAVERM!I129 -> #N/A | Y17: 43862 | Z17: =HAVERM!J129 -> 1.931 | AA17: =HAVERM!K129 -> 2.195 | AB17: =HAVERM!L129 -> #N/A | AC17: =HAVERM!M129 -> #N/A
A18: 44986 | B18: =100*((HAVERM!D166/HAVERM!D154)-1) -> 6.6892464 | H18: 44986 | I18: =HAVERM!E166 -> 7.2 | L18: 46204 | N18: =HAVERQ!C54 -> 2.6 | O18: =100*((GMW!B221/GMW!B217)-1) -> 2.4448239 | Q18: 2 | S18: 43891 | T18: =HAVERM!F130 -> 1.69 | U18: =HAVERM!G130 -> 1.598 | V18: =HAVERM!H130 -> #N/A | W18: =HAVERM!I130 -> #N/A | Y18: 43891 | Z18: =HAVERM!J130 -> 1.83 | AA18: =HAVERM!K130 -> 1.937 | AB18: =HAVERM!L130 -> #N/A | AC18: =HAVERM!M130 -> #N/A
A19: 45017 | B19: =100*((HAVERM!D167/HAVERM!D155)-1) -> 6.9340017 | H19: 45017 | I19: =HAVERM!E167 -> 7.7 | L19: 46296 | N19: =HAVERQ!C55 -> 2.4 | O19: =100*((GMW!B222/GMW!B218)-1) -> 2.374475 | P19: 2.3 | Q19: 2 | S19: 43922 | T19: =HAVERM!F131 -> 1.87 | U19: =HAVERM!G131 -> 1.213 | V19: =HAVERM!H131 -> #N/A | W19: =HAVERM!I131 -> #N/A | Y19: 43922 | Z19: =HAVERM!J131 -> 1.765 | AA19: =HAVERM!K131 -> 1.635 | AB19: =HAVERM!L131 -> #N/A | AC19: =HAVERM!M131 -> #N/A
A20: 45047 | B20: =100*((HAVERM!D168/HAVERM!D156)-1) -> 7.3211314 | H20: 45047 | I20: =HAVERM!E168 -> 7.9 | L20: 46388 | N20: =HAVERQ!C56 -> 2.3 | O20: =100*((GMW!B223/GMW!B219)-1) -> 2.1515991 | Q20: 2 | S20: 43952 | T20: =HAVERM!F132 -> 1.72 | U20: =HAVERM!G132 -> 1.389 | V20: =HAVERM!H132 -> #N/A | W20: =HAVERM!I132 -> #N/A | Y20: 43952 | Z20: =HAVERM!J132 -> 1.759 | AA20: =HAVERM!K132 -> 1.4 | AB20: =HAVERM!L132 -> #N/A | AC20: =HAVERM!M132 -> #N/A
A21: 45078 | B21: =100*((HAVERM!D169/HAVERM!D157)-1) -> 7.1900826 | H21: 45078 | I21: =HAVERM!E169 -> 8.1 | L21: 46478 | N21: =HAVERQ!C57 -> 2.2 | O21: =100*((GMW!B224/GMW!B220)-1) -> 2.1662517 | Q21: 2 | S21: 43983 | T21: =HAVERM!F133 -> 1.18 | U21: =HAVERM!G133 -> 1.431 | V21: =HAVERM!H133 -> #N/A | W21: =HAVERM!I133 -> #N/A | Y21: 43983 | Z21: =HAVERM!J133 -> 1.59 | AA21: =HAVERM!K133 -> 1.344 | AB21: =HAVERM!L133 -> #N/A | AC21: =HAVERM!M133 -> #N/A
A22: 45108 | B22: =100*((HAVERM!D170/HAVERM!D158)-1) -> 7.4651354 | H22: 45108 | I22: =HAVERM!E170 -> 8.1 | L22: 46569 | N22: =HAVERQ!C58 -> 2.1 | O22: =100*((GMW!B225/GMW!B221)-1) -> 2.2200162 | Q22: 2 | S22: 44013 | T22: =HAVERM!F134 -> 1.34 | U22: =HAVERM!G134 -> 1.661 | V22: =HAVERM!H134 -> #N/A | W22: =HAVERM!I134 -> #N/A | Y22: 44013 | Z22: =HAVERM!J134 -> 1.414 | AA22: =HAVERM!K134 -> 1.494 | AB22: =HAVERM!L134 -> #N/A | AC22: =HAVERM!M134 -> #N/A
A23: 45139 | B23: =100*((HAVERM!D171/HAVERM!D159)-1) -> 6.7644662 | H23: 45139 | I23: =HAVERM!E171 -> 8.1 | L23: 46661 | N23: =HAVERQ!C59 -> 2 | O23: =100*((GMW!B226/GMW!B222)-1) -> 2.2619974 | Q23: 2 | S23: 44044 | T23: =HAVERM!F135 -> 1.04 | U23: =HAVERM!G135 -> 2.16 | V23: =HAVERM!H135 -> #N/A | W23: =HAVERM!I135 -> #N/A | Y23: 44044 | Z23: =HAVERM!J135 -> 1.187 | AA23: =HAVERM!K135 -> 1.751 | AB23: =HAVERM!L135 -> #N/A | AC23: =HAVERM!M135 -> #N/A
A24: 45170 | B24: =100*((HAVERM!D172/HAVERM!D160)-1) -> 6.916192 | H24: 45170 | I24: =HAVERM!E172 -> 7.9 | L24: 46753 | N24: =HAVERQ!C60 -> 1.9 | O24: =100*((GMW!B227/GMW!B223)-1) -> 2.2554921 | Q24: 2 | S24: 44075 | T24: =HAVERM!F136 -> 1.57 | U24: =HAVERM!G136 -> 1.853 | V24: =HAVERM!H136 -> #N/A | W24: =HAVERM!I136 -> #N/A | Y24: 44075 | Z24: =HAVERM!J136 -> 1.317 | AA24: =HAVERM!K136 -> 1.891 | AB24: =HAVERM!L136 -> #N/A | AC24: =HAVERM!M136 -> #N/A
A25: 45200 | B25: =100*((HAVERM!D173/HAVERM!D161)-1) -> 6.542811 | H25: 45200 | I25: =HAVERM!E173 -> 7.3 | S25: 44105 | T25: =HAVERM!F137 -> 2.21 | U25: =HAVERM!G137 -> 2.354 | V25: =HAVERM!H137 -> #N/A | W25: =HAVERM!I137 -> #N/A | Y25: 44105 | Z25: =HAVERM!J137 -> 1.606 | AA25: =HAVERM!K137 -> 2.122 | AB25: =HAVERM!L137 -> #N/A | AC25: =HAVERM!M137 -> #N/A
A26: 45231 | B26: =100*((HAVERM!D174/HAVERM!D162)-1) -> 6.2096774 | H26: 45231 | I26: =HAVERM!E174 -> 6.7 | S26: 44136 | T26: =HAVERM!F138 -> 1.69 | U26: =HAVERM!G138 -> 2.092 | V26: =HAVERM!H138 -> #N/A | W26: =HAVERM!I138 -> #N/A | Y26: 44136 | Z26: =HAVERM!J138 -> 1.823 | AA26: =HAVERM!K138 -> 2.099 | AB26: =HAVERM!L138 -> #N/A | AC26: =HAVERM!M138 -> #N/A
A27: 45261 | B27: =100*((HAVERM!D175/HAVERM!D163)-1) -> 6.4 | H27: 45261 | I27: =HAVERM!E175 -> 6.2 | S27: 44166 | T27: =HAVERM!F139 -> 0.88 | U27: =HAVERM!G139 -> 2.705 | V27: =HAVERM!H139 -> #N/A | W27: =HAVERM!I139 -> #N/A | Y27: 44166 | Z27: =HAVERM!J139 -> 1.591 | AA27: =HAVERM!K139 -> 2.383 | AB27: =HAVERM!L139 -> #N/A | AC27: =HAVERM!M139 -> #N/A
A28: 45292 | B28: =100*((HAVERM!D176/HAVERM!D164)-1) -> 6.542811 | H28: 45292 | I28: =HAVERM!E176 -> 6.1 | S28: 44197 | T28: =HAVERM!F140 -> 1.83 | U28: =HAVERM!G140 -> 2.517 | V28: =HAVERM!H140 -> #N/A | W28: =HAVERM!I140 -> #N/A | Y28: 44197 | Z28: =HAVERM!J140 -> 1.467 | AA28: =HAVERM!K140 -> 2.438 | AB28: =HAVERM!L140 -> #N/A | AC28: =HAVERM!M140 -> #N/A
A29: 45323 | B29: =100*((HAVERM!D177/HAVERM!D165)-1) -> 6.0751399 | H29: 45323 | I29: =HAVERM!E177 -> 6 | S29: 44228 | T29: =HAVERM!F141 -> 2.05 | U29: =HAVERM!G141 -> 2.719 | V29: =HAVERM!H141 -> #N/A | W29: =HAVERM!I141 -> #N/A | Y29: 44228 | Z29: =HAVERM!J141 -> 1.589 | AA29: =HAVERM!K141 -> 2.647 | AB29: =HAVERM!L141 -> #N/A | AC29: =HAVERM!M141 -> #N/A
A30: 45352 | B30: =100*((HAVERM!D178/HAVERM!D166)-1) -> 5.952381 | H30: 45352 | I30: =HAVERM!E178 -> 5.9 | S30: 44256 | T30: =HAVERM!F142 -> 1.65 | U30: =HAVERM!G142 -> 2.973 | V30: =HAVERM!H142 -> #N/A | W30: =HAVERM!I142 -> #N/A | Y30: 44256 | Z30: =HAVERM!J142 -> 1.847 | AA30: =HAVERM!K142 -> 2.736 | AB30: =HAVERM!L142 -> #N/A | AC30: =HAVERM!M142 -> #N/A
A31: 45383 | B31: =100*((HAVERM!D179/HAVERM!D167)-1) -> 5.859375 | C31: ='MPR Chart 2.16 (May)'!L70 -> 5.52 | H31: 45383 | I31: =HAVERM!E179 -> 5.9 | S31: 44287 | T31: =HAVERM!F143 -> 2.79 | U31: =HAVERM!G143 -> 3.139 | V31: =HAVERM!H143 -> #N/A | W31: =HAVERM!I143 -> #N/A | Y31: 44287 | Z31: =HAVERM!J143 -> 2.165 | AA31: =HAVERM!K143 -> 2.944 | AB31: =HAVERM!L143 -> #N/A | AC31: =HAVERM!M143 -> #N/A
A32: 45413 | B32: =100*((HAVERM!D180/HAVERM!D168)-1) -> 5.7364341 | C32: ='MPR Chart 2.16 (May)'!L71 -> 5.258 | H32: 45413 | I32: =HAVERM!E180 -> 5.6 | S32: 44317 | T32: =HAVERM!F144 -> 2.83 | U32: =HAVERM!G144 -> 3.442 | V32: =HAVERM!H144 -> #N/A | W32: =HAVERM!I144 -> #N/A | Y32: 44317 | Z32: =HAVERM!J144 -> 2.424 | AA32: =HAVERM!K144 -> 3.185 | AB32: =HAVERM!L144 -> #N/A | AC32: =HAVERM!M144 -> #N/A
A33: 45444 | B33: =100*((HAVERM!D181/HAVERM!D169)-1) -> 5.7054742 | C33: ='MPR Chart 2.16 (May)'!L72 -> 5.134 | H33: 45444 | I33: =HAVERM!E181 -> 5.3 | S33: 44348 | T33: =HAVERM!F145 -> 3.13 | U33: =HAVERM!G145 -> 3.258 | V33: =HAVERM!H145 -> #N/A | W33: =HAVERM!I145 -> #N/A | Y33: 44348 | Z33: =HAVERM!J145 -> 2.915 | AA33: =HAVERM!K145 -> 3.28 | AB33: =HAVERM!L145 -> #N/A | AC33: =HAVERM!M145 -> #N/A
A34: 45474 | B34: =100*((HAVERM!D182/HAVERM!D170)-1) -> 5.1908397 | C34: ='MPR Chart 2.16 (May)'!L73 -> 4.949 | D34: ='MPR Chart 2.16 (Aug)'!L49 -> 5.563 | H34: 45474 | I34: =HAVERM!E182 -> 5 | S34: 44378 | T34: =HAVERM!F146 -> 3.77 | U34: =HAVERM!G146 -> 2.931 | V34: =HAVERM!H146 -> #N/A | W34: =HAVERM!I146 -> #N/A | Y34: 44378 | Z34: =HAVERM!J146 -> 3.24 | AA34: =HAVERM!K146 -> 3.21 | AB34: =HAVERM!L146 -> #N/A | AC34: =HAVERM!M146 -> #N/A
A35: 45505 | B35: =100*((HAVERM!D183/HAVERM!D171)-1) -> 5.5725191 | C35: ='MPR Chart 2.16 (May)'!L74 -> 5.001 | D35: ='MPR Chart 2.16 (Aug)'!L50 -> 5.84 | H35: 45505 | I35: =HAVERM!E183 -> 4.8 | S35: 44409 | T35: =HAVERM!F147 -> 3.45 | U35: =HAVERM!G147 -> 3.23 | V35: =HAVERM!H147 -> #N/A | W35: =HAVERM!I147 -> #N/A | Y35: 44409 | Z35: =HAVERM!J147 -> 3.445 | AA35: =HAVERM!K147 -> 3.14 | AB35: =HAVERM!L147 -> #N/A | AC35: =HAVERM!M147 -> #N/A
A36: 45536 | B36: =100*((HAVERM!D184/HAVERM!D172)-1) -> 4.9467275 | C36: ='MPR Chart 2.16 (May)'!L75 -> 4.728 | D36: ='MPR Chart 2.16 (Aug)'!L51 -> 5.52 | H36: 45536 | I36: =HAVERM!E184 -> 4.9 | S36: 44440 | T36: =HAVERM!F148 -> 4.53 | U36: =HAVERM!G148 -> 4.098 | V36: =HAVERM!H148 -> #N/A | W36: =HAVERM!I148 -> #N/A | Y36: 44440 | Z36: =HAVERM!J148 -> 3.913 | AA36: =HAVERM!K148 -> 3.42 | AB36: =HAVERM!L148 -> #N/A | AC36: =HAVERM!M148 -> #N/A
A37: 45566 | B37: =100*((HAVERM!D185/HAVERM!D173)-1) -> 5.0037908 | D37: ='MPR Chart 2.16 (Aug)'!L52 -> 5.502 | E37: ='MPR Chart 2.22 (Nov)'!L52 -> 4.972 | H37: 45566 | I37: =HAVERM!E185 -> 5.5 | S37: 44470 | T37: =HAVERM!F149 -> 5.41 | U37: =HAVERM!G149 -> 4.724 | V37: =HAVERM!H149 -> #N/A | W37: =HAVERM!I149 -> #N/A | Y37: 44470 | Z37: =HAVERM!J149 -> 4.461 | AA37: =HAVERM!K149 -> 4.017 | AB37: =HAVERM!L149 -> #N/A | AC37: =HAVERM!M149 -> #N/A
A38: 45597 | B38: =100*((HAVERM!D186/HAVERM!D174)-1) -> 5.0113895 | D38: ='MPR Chart 2.16 (Aug)'!L53 -> 5.395 | E38: ='MPR Chart 2.22 (Nov)'!L53 -> 4.913 | H38: 45597 | I38: =HAVERM!E186 -> 5.9 | S38: 44501 | T38: =HAVERM!F150 -> 4.81 | U38: =HAVERM!G150 -> 4.411 | V38: =HAVERM!H150 -> #N/A | W38: =HAVERM!I150 -> #N/A | Y38: 44501 | Z38: =HAVERM!J150 -> 4.916 | AA38: =HAVERM!K150 -> 4.411 | AB38: =HAVERM!L150 -> #N/A | AC38: =HAVERM!M150 -> #N/A
A39: 45627 | B39: =100*((HAVERM!D187/HAVERM!D175)-1) -> 4.3609023 | D39: ='MPR Chart 2.16 (Aug)'!L54 -> 5.286 | E39: ='MPR Chart 2.22 (Nov)'!L54 -> 4.739 | H39: 45627 | I39: =HAVERM!E187 -> 6.2 | J39: ='MPR Chart 2.22 (Feb)'!C34 -> 6.292 | S39: 44531 | T39: =HAVERM!F151 -> 5.48 | U39: =HAVERM!G151 -> 5.094 | V39: =HAVERM!H151 -> #N/A | W39: =HAVERM!I151 -> #N/A | Y39: 44531 | Z39: =HAVERM!J151 -> 5.233 | AA39: =HAVERM!K151 -> 4.743 | AB39: =HAVERM!L151 -> #N/A | AC39: =HAVERM!M151 -> #N/A
A40: 45658 | B40: =100*((HAVERM!D188/HAVERM!D176)-1) -> 5.0037908 | E40: ='MPR Chart 2.22 (Nov)'!L55 -> 5.112 | F40: ='MPR Chart 2.20 (Feb)'!B69 -> 5.161 | H40: 45658 | S40: 44562 | T40: =HAVERM!F152 -> 5.41 | U40: =HAVERM!G152 -> 4.542 | V40: =HAVERM!H152 -> #N/A | W40: =HAVERM!I152 -> #N/A | Y40: 44562 | Z40: =HAVERM!J152 -> 5.235 | AA40: =HAVERM!K152 -> 4.682 | AB40: =HAVERM!L152 -> #N/A | AC40: =HAVERM!M152 -> #N/A
A41: 45689 | E41: ='MPR Chart 2.22 (Nov)'!L56 -> 4.965 | F41: ='MPR Chart 2.20 (Feb)'!B70 -> 5.066 | H41: 45689 | S41: 44593 | T41: =HAVERM!F153 -> 5.24 | U41: =HAVERM!G153 -> 4.863 | V41: =HAVERM!H153 -> #N/A | W41: =HAVERM!I153 -> #N/A | Y41: 44593 | Z41: =HAVERM!J153 -> 5.378 | AA41: =HAVERM!K153 -> 4.833 | AB41: =HAVERM!L153 -> #N/A | AC41: =HAVERM!M153 -> #N/A
A42: 45717 | E42: ='MPR Chart 2.22 (Nov)'!L57 -> 4.894 | F42: ='MPR Chart 2.20 (Feb)'!B71 -> 4.926 | H42: 45717 | J42: ='MPR Chart 2.22 (Feb)'!C35 -> 6.224 | S42: 44621 | T42: =HAVERM!F154 -> 6.82 | U42: =HAVERM!G154 -> 5.857 | V42: =HAVERM!H154 -> #N/A | W42: =HAVERM!I154 -> #N/A | Y42: 44621 | Z42: =HAVERM!J154 -> 5.825 | AA42: =HAVERM!K154 -> 5.087 | AB42: =HAVERM!L154 -> #N/A | AC42: =HAVERM!M154 -> #N/A
A43: 45748 | F43: ='MPR Chart 2.20 (Feb)'!B72 -> 5.077 | H43: 45748 | S43: 44652 | T43: =HAVERM!F155 -> 6.5 | U43: =HAVERM!G155 -> 5.999 | V43: =HAVERM!H155 -> #N/A | W43: =HAVERM!I155 -> #N/A | Y43: 44652 | Z43: =HAVERM!J155 -> 6.187 | AA43: =HAVERM!K155 -> 5.573 | AB43: =HAVERM!L155 -> #N/A | AC43: =HAVERM!M155 -> #N/A
A44: 45778 | F44: ='MPR Chart 2.20 (Feb)'!B73 -> 4.782 | H44: 45778 | S44: 44682 | T44: =HAVERM!F156 -> 7.27 | U44: =HAVERM!G156 -> 5.842 | V44: =HAVERM!H156 -> 5.5 | W44: =HAVERM!I156 -> 4.8 | Y44: 44682 | Z44: =HAVERM!J156 -> 6.863 | AA44: =HAVERM!K156 -> 5.899 | AB44: =HAVERM!L156 -> 5.465 | AC44: =HAVERM!M156 -> 4.787
A45: 45809 | F45: ='MPR Chart 2.20 (Feb)'!B74 -> 4.651 | H45: 45809 | J45: ='MPR Chart 2.22 (Feb)'!C36 -> 5.669 | S45: 44713 | T45: =HAVERM!F157 -> 7.46 | U45: =HAVERM!G157 -> 6.298 | V45: =HAVERM!H157 -> 5.7 | W45: =HAVERM!I157 -> 5.1 | Y45: 44713 | Z45: =HAVERM!J157 -> 7.077 | AA45: =HAVERM!K157 -> 6.046 | AB45: =HAVERM!L157 -> 5.578 | AC45: =HAVERM!M157 -> 4.931
H46: 45839 | S46: 44743 | T46: =HAVERM!F158 -> 7.98 | U46: =HAVERM!G158 -> 6.678 | V46: =HAVERM!H158 -> 5.5 | W46: =HAVERM!I158 -> 5.2 | Y46: 44743 | Z46: =HAVERM!J158 -> 7.568 | AA46: =HAVERM!K158 -> 6.272 | AB46: =HAVERM!L158 -> 5.541 | AC46: =HAVERM!M158 -> 5.014
H47: 45870 | S47: 44774 | T47: =HAVERM!F159 -> 7.65 | U47: =HAVERM!G159 -> 6.416 | V47: =HAVERM!H159 -> 6.4 | W47: =HAVERM!I159 -> 5.5 | Y47: 44774 | Z47: =HAVERM!J159 -> 7.695 | AA47: =HAVERM!K159 -> 6.464 | AB47: =HAVERM!L159 -> 5.844 | AC47: =HAVERM!M159 -> 5.244
H48: 45901 | J48: ='MPR Chart 2.22 (Feb)'!C37 -> 5.157 | S48: 44805 | T48: =HAVERM!F160 -> 7.41 | U48: =HAVERM!G160 -> 6.629 | V48: =HAVERM!H160 -> 6.5 | W48: =HAVERM!I160 -> 5.8 | Y48: 44805 | Z48: =HAVERM!J160 -> 7.677 | AA48: =HAVERM!K160 -> 6.574 | AB48: =HAVERM!L160 -> 6.098 | AC48: =HAVERM!M160 -> 5.501
H49: 45931 | S49: 44835 | T49: =HAVERM!F161 -> 7.76 | U49: =HAVERM!G161 -> 6.221 | V49: =HAVERM!H161 -> 6.1 | W49: =HAVERM!I161 -> 5.9 | Y49: 44835 | Z49: =HAVERM!J161 -> 7.604 | AA49: =HAVERM!K161 -> 6.422 | AB49: =HAVERM!L161 -> 6.306 | AC49: =HAVERM!M161 -> 5.729
H50: 45962 | S50: 44866 | T50: =HAVERM!F162 -> 7.17 | U50: =HAVERM!G162 -> 5.708 | V50: =HAVERM!H162 -> 6.1 | W50: =HAVERM!I162 -> 5.8 | Y50: 44866 | Z50: =HAVERM!J162 -> 7.445 | AA50: =HAVERM!K162 -> 6.186 | AB50: =HAVERM!L162 -> 6.219 | AC50: =HAVERM!M162 -> 5.833
H51: 45992 | J51: ='MPR Chart 2.22 (Feb)'!C38 -> 3.867 | S51: 44896 | T51: =HAVERM!F163 -> 8.6 | U51: =HAVERM!G163 -> 5.785 | V51: =HAVERM!H163 -> 6.6 | W51: =HAVERM!I163 -> 6.3 | Y51: 44896 | Z51: =HAVERM!J163 -> 7.843 | AA51: =HAVERM!K163 -> 5.904 | AB51: =HAVERM!L163 -> 6.26 | AC51: =HAVERM!M163 -> 5.982
S52: 44927 | T52: =HAVERM!F164 -> 7.9 | U52: =HAVERM!G164 -> 5.8 | V52: =HAVERM!H164 -> 6.3 | W52: =HAVERM!I164 -> 5.7 | Y52: 44927 | Z52: =HAVERM!J164 -> 7.892 | AA52: =HAVERM!K164 -> 5.764 | AB52: =HAVERM!L164 -> 6.339 | AC52: =HAVERM!M164 -> 5.94
S53: 44958 | T53: =HAVERM!F165 -> 7.76 | U53: =HAVERM!G165 -> 5.364 | V53: =HAVERM!H165 -> 6.6 | W53: =HAVERM!I165 -> 5.8 | Y53: 44958 | Z53: =HAVERM!J165 -> 8.089 | AA53: =HAVERM!K165 -> 5.65 | AB53: =HAVERM!L165 -> 6.51 | AC53: =HAVERM!M165 -> 5.928
S54: 44986 | T54: =HAVERM!F166 -> 7.82 | U54: =HAVERM!G166 -> 5.314 | V54: =HAVERM!H166 -> 6.5 | W54: =HAVERM!I166 -> 5.6 | Y54: 44986 | Z54: =HAVERM!J166 -> 7.83 | AA54: =HAVERM!K166 -> 5.492 | AB54: =HAVERM!L166 -> 6.478 | AC54: =HAVERM!M166 -> 5.682
S55: 45017 | T55: =HAVERM!F167 -> 7.44 | U55: =HAVERM!G167 -> 5.957 | V55: =HAVERM!H167 -> 6.6 | W55: =HAVERM!I167 -> 5.4 | Y55: 45017 | Z55: =HAVERM!J167 -> 7.674 | AA55: =HAVERM!K167 -> 5.545 | AB55: =HAVERM!L167 -> 6.564 | AC55: =HAVERM!M167 -> 5.565
S56: 45047 | T56: =HAVERM!F168 -> 7.77 | U56: =HAVERM!G168 -> 5.06 | V56: =HAVERM!H168 -> 6.8 | W56: =HAVERM!I168 -> 5.2 | Y56: 45047 | Z56: =HAVERM!J168 -> 7.677 | AA56: =HAVERM!K168 -> 5.444 | AB56: =HAVERM!L168 -> 6.609 | AC56: =HAVERM!M168 -> 5.384
S57: 45078 | T57: =HAVERM!F169 -> 6.9 | U57: =HAVERM!G169 -> 4.875 | V57: =HAVERM!H169 -> 7.1 | W57: =HAVERM!I169 -> 5.3 | Y57: 45078 | Z57: =HAVERM!J169 -> 7.37 | AA57: =HAVERM!K169 -> 5.297 | AB57: =HAVERM!L169 -> 6.825 | AC57: =HAVERM!M169 -> 5.312
S58: 45108 | T58: =HAVERM!F170 -> 7.84 | U58: =HAVERM!G170 -> 5.591 | V58: =HAVERM!H170 -> 6.7 | W58: =HAVERM!I170 -> 5 | Y58: 45108 | Z58: =HAVERM!J170 -> 7.503 | AA58: =HAVERM!K170 -> 5.175 | AB58: =HAVERM!L170 -> 6.849 | AC58: =HAVERM!M170 -> 5.184
S59: 45139 | T59: =HAVERM!F171 -> 7.45 | U59: =HAVERM!G171 -> 4.464 | V59: =HAVERM!H171 -> 6.9 | W59: =HAVERM!I171 -> 5 | Y59: 45139 | Z59: =HAVERM!J171 -> 7.395 | AA59: =HAVERM!K171 -> 4.977 | AB59: =HAVERM!L171 -> 6.895 | AC59: =HAVERM!M171 -> 5.112
S60: 45170 | T60: =HAVERM!F172 -> 6.91 | U60: =HAVERM!G172 -> 4.395 | V60: =HAVERM!H172 -> 7.1 | W60: =HAVERM!I172 -> 5.2 | Y60: 45170 | Z60: =HAVERM!J172 -> 7.397 | AA60: =HAVERM!K172 -> 4.817 | AB60: =HAVERM!L172 -> 6.869 | AC60: =HAVERM!M172 -> 5.071
S61: 45200 | T61: =HAVERM!F173 -> 6.82 | U61: =HAVERM!G173 -> 4.702 | V61: =HAVERM!H173 -> 6.8 | W61: =HAVERM!I173 -> 5.1 | Y61: 45200 | Z61: =HAVERM!J173 -> 7.059 | AA61: =HAVERM!K173 -> 4.52 | AB61: =HAVERM!L173 -> 6.919 | AC61: =HAVERM!M173 -> 5.1
S62: 45231 | T62: =HAVERM!F174 -> 5.95 | U62: =HAVERM!G174 -> 4.235 | V62: =HAVERM!H174 -> 7 | W62: =HAVERM!I174 -> 5.1 | Y62: 45231 | Z62: =HAVERM!J174 -> 6.562 | AA62: =HAVERM!K174 -> 4.444 | AB62: =HAVERM!L174 -> 6.953 | AC62: =HAVERM!M174 -> 5.139
S63: 45261 | T63: =HAVERM!F175 -> 4.91 | U63: =HAVERM!G175 -> 4.156 | V63: =HAVERM!H175 -> 7 | W63: =HAVERM!I175 -> 5.4 | Y63: 45261 | Z63: =HAVERM!J175 -> 5.896 | AA63: =HAVERM!K175 -> 4.364 | AB63: =HAVERM!L175 -> 6.944 | AC63: =HAVERM!M175 -> 5.209
... S77: 45689 | T77: =HAVERM!F189 -> 3.45 | U77: =HAVERM!G189 -> 3.957 | V77: =HAVERM!H189 -> 5.2 | W77: =HAVERM!I189 -> 4 | Y77: 45689 | Z77: =HAVERM!J189 -> 3.708 | AA77: =HAVERM!K189 -> 3.96 | AB77: =HAVERM!L189 -> 5.175 | AC77: =HAVERM!M189 -> 3.932

Sheet Market pricing dates
A2: February 2025 MPR | B2: 45685 | D2: March 2025 | E2: 45727
A4: Last 5 working days | D4: Last 5 working days
A5: =TEXT(B5,"dddd") -> Wednesday | B5: =IF(A6="Monday",B6-3,B6-1) -> 45679 | D5: =TEXT(E5,"dddd") -> Wednesday | E5: =IF(D6="Monday",E6-3,E6-1) -> 45721
A6: =TEXT(B6,"dddd") -> Thursday | B6: =IF(A7="Monday",B7-3,B7-1) -> 45680 | D6: =TEXT(E6,"dddd") -> Thursday | E6: =IF(D7="Monday",E7-3,E7-1) -> 45722
A7: =TEXT(B7,"dddd") -> Friday | B7: =IF(A8="Monday",B8-3,B8-1) -> 45681 | D7: =TEXT(E7,"dddd") -> Friday | E7: =IF(D8="Monday",E8-3,E8-1) -> 45723
A8: =TEXT(B8,"dddd") -> Monday | B8: =IF(A9="Monday",B9-3,B9-1) -> 45684 | D8: =TEXT(E8,"dddd") -> Monday | E8: =IF(D9="Monday",E9-3,E9-1) -> 45726
A9: =TEXT(B9,"dddd") -> Tuesday | B9: =B2 -> 45685 | D9: =TEXT(E9,"dddd") -> Tuesday | E9: =E2 -> 45727
B11: =TEXT(B9,"dd mmm yyyy") -> 28 Jan 2025 | E11: =TEXT(E9,"dd mmm yyyy") -> 11 Mar 2025
A12: ="15 working days to "&B11 -> 15 working days to 28 Jan 2025 | D12: ="15 working days to "&E11 -> 15 working days to 11 Mar 2025

Sheet Market expectations - RCB
A1: ='Market pricing dates'!A2 -> February 2025 MPR | C1: ='Market pricing dates'!A12 -> 15 working days to 28 Jan 2025 | BA1: ='Market pricing dates'!D2 -> March 2025 | BC1: ='Market pricing dates'!D12 -> 15 working days to 11 Mar 2025
A2: Column # | B2: =HAVERD!I$1 -> 9 | C2: =+B2+1 -> 10 | D2: =+C2+1 -> 11 | E2: =+D2+1 -> 12 | F2: =+E2+1 -> 13 | G2: =+F2+1 -> 14 | H2: =+G2+1 -> 15 | I2: =+H2+1 -> 16 | J2: =+I2+1 -> 17 | ... AX2: =+AW2+1 -> 57 | BA2: Column # | BB2: =HAVERD!I$1 -> 9 | BC2: =+BB2+1 -> 10 | BD2: =+BC2+1 -> 11 | BE2: =+BD2+1 -> 12 | BF2: =+BE2+1 -> 13 | BG2: =+BF2+1 -> 14 | BH2: =+BG2+1 -> 15 | BI2: =+BH2+1 -> 16 | BJ2: =+BI2+1 -> 17 | ... CX2: =+CW2+1 -> 57
A3: Months | B3: =HAVERD!I$2 -> Overnight | C3: =HAVERD!J$2 -> 1 | D3: =HAVERD!K$2 -> 2 | E3: =HAVERD!L$2 -> 3 | F3: =HAVERD!M$2 -> 4 | G3: =HAVERD!N$2 -> 5 | H3: =HAVERD!O$2 -> 6 | I3: =HAVERD!P$2 -> 7 | ... AX3: =HAVERD!BE$2 -> 48 | BA3: Months | BB3: =HAVERD!I$2 -> Overnight | BC3: =HAVERD!J$2 -> 1 | BD3: =HAVERD!K$2 -> 2 | BE3: =HAVERD!L$2 -> 3 | BF3: =HAVERD!M$2 -> 4 | BG3: =HAVERD!N$2 -> 5 | BH3: =HAVERD!O$2 -> 6 | BI3: =HAVERD!P$2 -> 7 | ... CX3: =HAVERD!BE$2 -> 48
A4: Days | C4: 30.416667 | D4: =+C4+30.4166667 -> 60.833333 | E4: =+D4+30.4166667 -> 91.25 | F4: =+E4+30.4166667 -> 121.66667 | G4: =+F4+30.4166667 -> 152.08333 | H4: =+G4+30.4166667 -> 182.5 | I4: =+H4+30.4166667 -> 212.91667 | J4: =+I4+30.4166667 -> 243.33333 | K4: =+J4+30.4166667 -> 273.75 | ... AX4: =+AW4+30.4166667 -> 1460 | BA4: Days | BC4: 30.416667 | BD4: =+BC4+30.4166667 -> 60.833333 | BE4: =+BD4+30.4166667 -> 91.25 | BF4: =+BE4+30.4166667 -> 121.66667 | BG4: =+BF4+30.4166667 -> 152.08333 | BH4: =+BG4+30.4166667 -> 182.5 | BI4: =+BH4+30.4166667 -> 212.91667 | BJ4: =+BI4+30.4166667 -> 243.33333 | BK4: =+BJ4+30.4166667 -> 273.75 | ... CX4: =+CW4+30.4166667 -> 1460
A5: Dates | BA5: Dates
A6: =A11-7 -> 45665 | B6: =A6 -> 45665 | C6: =$B6+C$4 -> 45695.417 | D6: =$B6+D$4 -> 45725.833 | E6: =$B6+E$4 -> 45756.25 | F6: =$B6+F$4 -> 45786.667 | G6: =$B6+G$4 -> 45817.083 | H6: =$B6+H$4 -> 45847.5 | I6: =$B6+I$4 -> 45877.917 | J6: =$B6+J$4 -> 45908.333 | ... AX6: =$B6+AX$4 -> 47125 | BA6: =BA11-7 -> 45707 | BB6: =BA6 -> 45707 | BC6: =$BA6+BC$4 -> 45737.417 | BD6: =$BA6+BD$4 -> 45767.833 | BE6: =$BA6+BE$4 -> 45798.25 | BF6: =$BA6+BF$4 -> 45828.667 | BG6: =$BA6+BG$4 -> 45859.083 | BH6: =$BA6+BH$4 -> 45889.5 | BI6: =$BA6+BI$4 -> 45919.917 | BJ6: =$BA6+BJ$4 -> 45950.333 | ... CX6: =$BA6+CX$4 -> 47167
A7: =A12-7 -> 45666 | B7: =A7 -> 45666 | C7: =$B7+C$4 -> 45696.417 | D7: =$B7+D$4 -> 45726.833 | E7: =$B7+E$4 -> 45757.25 | F7: =$B7+F$4 -> 45787.667 | G7: =$B7+G$4 -> 45818.083 | H7: =$B7+H$4 -> 45848.5 | I7: =$B7+I$4 -> 45878.917 | J7: =$B7+J$4 -> 45909.333 | ... AX7: =$B7+AX$4 -> 47126 | BA7: =BA12-7 -> 45708 | BB7: =BA7 -> 45708 | BC7: =$BA7+BC$4 -> 45738.417 | BD7: =$BA7+BD$4 -> 45768.833 | BE7: =$BA7+BE$4 -> 45799.25 | BF7: =$BA7+BF$4 -> 45829.667 | BG7: =$BA7+BG$4 -> 45860.083 | BH7: =$BA7+BH$4 -> 45890.5 | BI7: =$BA7+BI$4 -> 45920.917 | BJ7: =$BA7+BJ$4 -> 45951.333 | ... CX7: =$BA7+CX$4 -> 47168
A8: =A13-7 -> 45667 | B8: =A8 -> 45667 | C8: =$B8+C$4 -> 45697.417 | D8: =$B8+D$4 -> 45727.833 | E8: =$B8+E$4 -> 45758.25 | F8: =$B8+F$4 -> 45788.667 | G8: =$B8+G$4 -> 45819.083 | H8: =$B8+H$4 -> 45849.5 | I8: =$B8+I$4 -> 45879.917 | J8: =$B8+J$4 -> 45910.333 | ... AX8: =$B8+AX$4 -> 47127 | BA8: =BA13-7 -> 45709 | BB8: =BA8 -> 45709 | BC8: =$BA8+BC$4 -> 45739.417 | BD8: =$BA8+BD$4 -> 45769.833 | BE8: =$BA8+BE$4 -> 45800.25 | BF8: =$BA8+BF$4 -> 45830.667 | BG8: =$BA8+BG$4 -> 45861.083 | BH8: =$BA8+BH$4 -> 45891.5 | BI8: =$BA8+BI$4 -> 45921.917 | BJ8: =$BA8+BJ$4 -> 45952.333 | ... CX8: =$BA8+CX$4 -> 47169
A9: =A14-7 -> 45670 | B9: =A9 -> 45670 | C9: =$B9+C$4 -> 45700.417 | D9: =$B9+D$4 -> 45730.833 | E9: =$B9+E$4 -> 45761.25 | F9: =$B9+F$4 -> 45791.667 | G9: =$B9+G$4 -> 45822.083 | H9: =$B9+H$4 -> 45852.5 | I9: =$B9+I$4 -> 45882.917 | J9: =$B9+J$4 -> 45913.333 | ... AX9: =$B9+AX$4 -> 47130 | BA9: =BA14-7 -> 45712 | BB9: =BA9 -> 45712 | BC9: =$BA9+BC$4 -> 45742.417 | BD9: =$BA9+BD$4 -> 45772.833 | BE9: =$BA9+BE$4 -> 45803.25 | BF9: =$BA9+BF$4 -> 45833.667 | BG9: =$BA9+BG$4 -> 45864.083 | BH9: =$BA9+BH$4 -> 45894.5 | BI9: =$BA9+BI$4 -> 45924.917 | BJ9: =$BA9+BJ$4 -> 45955.333 | ... CX9: =$BA9+CX$4 -> 47172
A10: =A15-7 -> 45671 | B10: =A10 -> 45671 | C10: =$B10+C$4 -> 45701.417 | D10: =$B10+D$4 -> 45731.833 | E10: =$B10+E$4 -> 45762.25 | F10: =$B10+F$4 -> 45792.667 | G10: =$B10+G$4 -> 45823.083 | H10: =$B10+H$4 -> 45853.5 | I10: =$B10+I$4 -> 45883.917 | J10: =$B10+J$4 -> 45914.333 | ... AX10: =$B10+AX$4 -> 47131 | BA10: =BA15-7 -> 45713 | BB10: =BA10 -> 45713 | BC10: =$BA10+BC$4 -> 45743.417 | BD10: =$BA10+BD$4 -> 45773.833 | BE10: =$BA10+BE$4 -> 45804.25 | BF10: =$BA10+BF$4 -> 45834.667 | BG10: =$BA10+BG$4 -> 45865.083 | BH10: =$BA10+BH$4 -> 45895.5 | BI10: =$BA10+BI$4 -> 45925.917 | BJ10: =$BA10+BJ$4 -> 45956.333 | ... CX10: =$BA10+CX$4 -> 47173
A11: =A16-7 -> 45672 | B11: =A11 -> 45672 | C11: =$B11+C$4 -> 45702.417 | D11: =$B11+D$4 -> 45732.833 | E11: =$B11+E$4 -> 45763.25 | F11: =$B11+F$4 -> 45793.667 | G11: =$B11+G$4 -> 45824.083 | H11: =$B11+H$4 -> 45854.5 | I11: =$B11+I$4 -> 45884.917 | J11: =$B11+J$4 -> 45915.333 | ... AX11: =$B11+AX$4 -> 47132 | BA11: =BA16-7 -> 45714 | BB11: =BA11 -> 45714 | BC11: =$BA11+BC$4 -> 45744.417 | BD11: =$BA11+BD$4 -> 45774.833 | BE11: =$BA11+BE$4 -> 45805.25 | BF11: =$BA11+BF$4 -> 45835.667 | BG11: =$BA11+BG$4 -> 45866.083 | BH11: =$BA11+BH$4 -> 45896.5 | BI11: =$BA11+BI$4 -> 45926.917 | BJ11: =$BA11+BJ$4 -> 45957.333 | ... CX11: =$BA11+CX$4 -> 47174
A12: =A17-7 -> 45673 | B12: =A12 -> 45673 | C12: =$B12+C$4 -> 45703.417 | D12: =$B12+D$4 -> 45733.833 | E12: =$B12+E$4 -> 45764.25 | F12: =$B12+F$4 -> 45794.667 | G12: =$B12+G$4 -> 45825.083 | H12: =$B12+H$4 -> 45855.5 | I12: =$B12+I$4 -> 45885.917 | J12: =$B12+J$4 -> 45916.333 | ... AX12: =$B12+AX$4 -> 47133 | BA12: =BA17-7 -> 45715 | BB12: =BA12 -> 45715 | BC12: =$BA12+BC$4 -> 45745.417 | BD12: =$BA12+BD$4 -> 45775.833 | BE12: =$BA12+BE$4 -> 45806.25 | BF12: =$BA12+BF$4 -> 45836.667 | BG12: =$BA12+BG$4 -> 45867.083 | BH12: =$BA12+BH$4 -> 45897.5 | BI12: =$BA12+BI$4 -> 45927.917 | BJ12: =$BA12+BJ$4 -> 45958.333 | ... CX12: =$BA12+CX$4 -> 47175
A13: =A18-7 -> 45674 | B13: =A13 -> 45674 | C13: =$B13+C$4 -> 45704.417 | D13: =$B13+D$4 -> 45734.833 | E13: =$B13+E$4 -> 45765.25 | F13: =$B13+F$4 -> 45795.667 | G13: =$B13+G$4 -> 45826.083 | H13: =$B13+H$4 -> 45856.5 | I13: =$B13+I$4 -> 45886.917 | J13: =$B13+J$4 -> 45917.333 | ... AX13: =$B13+AX$4 -> 47134 | BA13: =BA18-7 -> 45716 | BB13: =BA13 -> 45716 | BC13: =$BA13+BC$4 -> 45746.417 | BD13: =$BA13+BD$4 -> 45776.833 | BE13: =$BA13+BE$4 -> 45807.25 | BF13: =$BA13+BF$4 -> 45837.667 | BG13: =$BA13+BG$4 -> 45868.083 | BH13: =$BA13+BH$4 -> 45898.5 | BI13: =$BA13+BI$4 -> 45928.917 | BJ13: =$BA13+BJ$4 -> 45959.333 | ... CX13: =$BA13+CX$4 -> 47176
A14: =A19-7 -> 45677 | B14: =A14 -> 45677 | C14: =$B14+C$4 -> 45707.417 | D14: =$B14+D$4 -> 45737.833 | E14: =$B14+E$4 -> 45768.25 | F14: =$B14+F$4 -> 45798.667 | G14: =$B14+G$4 -> 45829.083 | H14: =$B14+H$4 -> 45859.5 | I14: =$B14+I$4 -> 45889.917 | J14: =$B14+J$4 -> 45920.333 | ... AX14: =$B14+AX$4 -> 47137 | BA14: =BA19-7 -> 45719 | BB14: =BA14 -> 45719 | BC14: =$BA14+BC$4 -> 45749.417 | BD14: =$BA14+BD$4 -> 45779.833 | BE14: =$BA14+BE$4 -> 45810.25 | BF14: =$BA14+BF$4 -> 45840.667 | BG14: =$BA14+BG$4 -> 45871.083 | BH14: =$BA14+BH$4 -> 45901.5 | BI14: =$BA14+BI$4 -> 45931.917 | BJ14: =$BA14+BJ$4 -> 45962.333 | ... CX14: =$BA14+CX$4 -> 47179
A15: =A20-7 -> 45678 | B15: =A15 -> 45678 | C15: =$B15+C$4 -> 45708.417 | D15: =$B15+D$4 -> 45738.833 | E15: =$B15+E$4 -> 45769.25 | F15: =$B15+F$4 -> 45799.667 | G15: =$B15+G$4 -> 45830.083 | H15: =$B15+H$4 -> 45860.5 | I15: =$B15+I$4 -> 45890.917 | J15: =$B15+J$4 -> 45921.333 | ... AX15: =$B15+AX$4 -> 47138 | BA15: =BA20-7 -> 45720 | BB15: =BA15 -> 45720 | BC15: =$BA15+BC$4 -> 45750.417 | BD15: =$BA15+BD$4 -> 45780.833 | BE15: =$BA15+BE$4 -> 45811.25 | BF15: =$BA15+BF$4 -> 45841.667 | BG15: =$BA15+BG$4 -> 45872.083 | BH15: =$BA15+BH$4 -> 45902.5 | BI15: =$BA15+BI$4 -> 45932.917 | BJ15: =$BA15+BJ$4 -> 45963.333 | ... CX15: =$BA15+CX$4 -> 47180
A16: ='Market pricing dates'!B5 -> 45679 | B16: =A16 -> 45679 | C16: =$B16+C$4 -> 45709.417 | D16: =$B16+D$4 -> 45739.833 | E16: =$B16+E$4 -> 45770.25 | F16: =$B16+F$4 -> 45800.667 | G16: =$B16+G$4 -> 45831.083 | H16: =$B16+H$4 -> 45861.5 | I16: =$B16+I$4 -> 45891.917 | J16: =$B16+J$4 -> 45922.333 | ... AX16: =$B16+AX$4 -> 47139 | BA16: ='Market pricing dates'!E5 -> 45721 | BB16: =BA16 -> 45721 | BC16: =$BA16+BC$4 -> 45751.417 | BD16: =$BA16+BD$4 -> 45781.833 | BE16: =$BA16+BE$4 -> 45812.25 | BF16: =$BA16+BF$4 -> 45842.667 | BG16: =$BA16+BG$4 -> 45873.083 | BH16: =$BA16+BH$4 -> 45903.5 | BI16: =$BA16+BI$4 -> 45933.917 | BJ16: =$BA16+BJ$4 -> 45964.333 | ... CX16: =$BA16+CX$4 -> 47181
A17: ='Market pricing dates'!B6 -> 45680 | B17: =A17 -> 45680 | C17: =$B17+C$4 -> 45710.417 | D17: =$B17+D$4 -> 45740.833 | E17: =$B17+E$4 -> 45771.25 | F17: =$B17+F$4 -> 45801.667 | G17: =$B17+G$4 -> 45832.083 | H17: =$B17+H$4 -> 45862.5 | I17: =$B17+I$4 -> 45892.917 | J17: =$B17+J$4 -> 45923.333 | ... AX17: =$B17+AX$4 -> 47140 | BA17: ='Market pricing dates'!E6 -> 45722 | BB17: =BA17 -> 45722 | BC17: =$BA17+BC$4 -> 45752.417 | BD17: =$BA17+BD$4 -> 45782.833 | BE17: =$BA17+BE$4 -> 45813.25 | BF17: =$BA17+BF$4 -> 45843.667 | BG17: =$BA17+BG$4 -> 45874.083 | BH17: =$BA17+BH$4 -> 45904.5 | BI17: =$BA17+BI$4 -> 45934.917 | BJ17: =$BA17+BJ$4 -> 45965.333 | ... CX17: =$BA17+CX$4 -> 47182
A18: ='Market pricing dates'!B7 -> 45681 | B18: =A18 -> 45681 | C18: =$B18+C$4 -> 45711.417 | D18: =$B18+D$4 -> 45741.833 | E18: =$B18+E$4 -> 45772.25 | F18: =$B18+F$4 -> 45802.667 | G18: =$B18+G$4 -> 45833.083 | H18: =$B18+H$4 -> 45863.5 | I18: =$B18+I$4 -> 45893.917 | J18: =$B18+J$4 -> 45924.333 | ... AX18: =$B18+AX$4 -> 47141 | BA18: ='Market pricing dates'!E7 -> 45723 | BB18: =BA18 -> 45723 | BC18: =$BA18+BC$4 -> 45753.417 | BD18: =$BA18+BD$4 -> 45783.833 | BE18: =$BA18+BE$4 -> 45814.25 | BF18: =$BA18+BF$4 -> 45844.667 | BG18: =$BA18+BG$4 -> 45875.083 | BH18: =$BA18+BH$4 -> 45905.5 | BI18: =$BA18+BI$4 -> 45935.917 | BJ18: =$BA18+BJ$4 -> 45966.333 | ... CX18: =$BA18+CX$4 -> 47183
A19: ='Market pricing dates'!B8 -> 45684 | B19: =A19 -> 45684 | C19: =$B19+C$4 -> 45714.417 | D19: =$B19+D$4 -> 45744.833 | E19: =$B19+E$4 -> 45775.25 | F19: =$B19+F$4 -> 45805.667 | G19: =$B19+G$4 -> 45836.083 | H19: =$B19+H$4 -> 45866.5 | I19: =$B19+I$4 -> 45896.917 | J19: =$B19+J$4 -> 45927.333 | ... AX19: =$B19+AX$4 -> 47144 | BA19: ='Market pricing dates'!E8 -> 45726 | BB19: =BA19 -> 45726 | BC19: =$BA19+BC$4 -> 45756.417 | BD19: =$BA19+BD$4 -> 45786.833 | BE19: =$BA19+BE$4 -> 45817.25 | BF19: =$BA19+BF$4 -> 45847.667 | BG19: =$BA19+BG$4 -> 45878.083 | BH19: =$BA19+BH$4 -> 45908.5 | BI19: =$BA19+BI$4 -> 45938.917 | BJ19: =$BA19+BJ$4 -> 45969.333 | ... CX19: =$BA19+CX$4 -> 47186
A20: ='Market pricing dates'!B9 -> 45685 | B20: =A20 -> 45685 | C20: =$B20+C$4 -> 45715.417 | D20: =$B20+D$4 -> 45745.833 | E20: =$B20+E$4 -> 45776.25 | F20: =$B20+F$4 -> 45806.667 | G20: =$B20+G$4 -> 45837.083 | H20: =$B20+H$4 -> 45867.5 | I20: =$B20+I$4 -> 45897.917 | J20: =$B20+J$4 -> 45928.333 | ... AX20: =$B20+AX$4 -> 47145 | BA20: ='Market pricing dates'!E9 -> 45727 | BB20: =BA20 -> 45727 | BC20: =$BA20+BC$4 -> 45757.417 | BD20: =$BA20+BD$4 -> 45787.833 | BE20: =$BA20+BE$4 -> 45818.25 | BF20: =$BA20+BF$4 -> 45848.667 | BG20: =$BA20+BG$4 -> 45879.083 | BH20: =$BA20+BH$4 -> 45909.5 | BI20: =$BA20+BI$4 -> 45939.917 | BJ20: =$BA20+BJ$4 -> 45970.333 | ... CX20: =$BA20+CX$4 -> 47187
A22: Market expectations | BA22: Market expectations
A23: =A6 -> 45665 | B23: =VLOOKUP($A23,HAVERD!$A:$BS,B$2,FALSE) -> 4.7 | C23: =VLOOKUP($A23,HAVERD!$A:$BS,C$2,FALSE) -> 4.6151373 | D23: =VLOOKUP($A23,HAVERD!$A:$BS,D$2,FALSE) -> 4.5287964 | E23: =VLOOKUP($A23,HAVERD!$A:$BS,E$2,FALSE) -> 4.4759515 | F23: =VLOOKUP($A23,HAVERD!$A:$BS,F$2,FALSE) -> 4.4368204 | G23: =VLOOKUP($A23,HAVERD!$A:$BS,G$2,FALSE) -> 4.4010511 | H23: =VLOOKUP($A23,HAVERD!$A:$BS,H$2,FALSE) -> 4.3672281 | I23: =VLOOKUP($A23,HAVERD!$A:$BS,I$2,FALSE) -> 4.3364382 | ... AX23: =VLOOKUP($A23,HAVERD!$A:$BS,AX$2,FALSE) -> 4.0454322 | BA23: =BA6 -> 45707 | BB23: =_xlfn.IFNA(VLOOKUP($BA23,HAVERD!$A:$BS,BB$2,FALSE),"") -> 4.4543 | BC23: =_xlfn.IFNA(VLOOKUP($BA23,HAVERD!$A:$BS,BC$2,FALSE),"") -> 4.4582888 | BD23: =_xlfn.IFNA(VLOOKUP($BA23,HAVERD!$A:$BS,BD$2,FALSE),"") -> 4.3867693 | BE23: =_xlfn.IFNA(VLOOKUP($BA23,HAVERD!$A:$BS,BE$2,FALSE),"") -> 4.3006902 | BF23: =_xlfn.IFNA(VLOOKUP($BA23,HAVERD!$A:$BS,BF$2,FALSE),"") -> 4.2136923 | BG23: =_xlfn.IFNA(VLOOKUP($BA23,HAVERD!$A:$BS,BG$2,FALSE),"") -> 4.136256 | BH23: =_xlfn.IFNA(VLOOKUP($BA23,HAVERD!$A:$BS,BH$2,FALSE),"") -> 4.0726368 | BI23: =_xlfn.IFNA(VLOOKUP($BA23,HAVERD!$A:$BS,BI$2,FALSE),"") -> 4.0244765 | ... CX23: =_xlfn.IFNA(VLOOKUP($BA23,HAVERD!$A:$BS,CX$2,FALSE),"") -> 3.9044401
A24: =A7 -> 45666 | B24: =VLOOKUP($A24,HAVERD!$A:$BS,B$2,FALSE) -> 4.7 | C24: =VLOOKUP($A24,HAVERD!$A:$BS,C$2,FALSE) -> 4.604997 | D24: =VLOOKUP($A24,HAVERD!$A:$BS,D$2,FALSE) -> 4.5109165 | E24: =VLOOKUP($A24,HAVERD!$A:$BS,E$2,FALSE) -> 4.454254 | F24: =VLOOKUP($A24,HAVERD!$A:$BS,F$2,FALSE) -> 4.4128636 | G24: =VLOOKUP($A24,HAVERD!$A:$BS,G$2,FALSE) -> 4.3754509 | H24: =VLOOKUP($A24,HAVERD!$A:$BS,H$2,FALSE) -> 4.3405305 | I24: =VLOOKUP($A24,HAVERD!$A:$BS,I$2,FALSE) -> 4.3092492 | ... AX24: =VLOOKUP($A24,HAVERD!$A:$BS,AX$2,FALSE) -> 4.0525498 | BA24: =BA7 -> 45708 | BB24: =_xlfn.IFNA(VLOOKUP($BA24,HAVERD!$A:$BS,BB$2,FALSE),"") -> 4.4543 | BC24: =_xlfn.IFNA(VLOOKUP($BA24,HAVERD!$A:$BS,BC$2,FALSE),"") -> 4.4549439 | BD24: =_xlfn.IFNA(VLOOKUP($BA24,HAVERD!$A:$BS,BD$2,FALSE),"") -> 4.3888295 | BE24: =_xlfn.IFNA(VLOOKUP($BA24,HAVERD!$A:$BS,BE$2,FALSE),"") -> 4.3059671 | BF24: =_xlfn.IFNA(VLOOKUP($BA24,HAVERD!$A:$BS,BF$2,FALSE),"") -> 4.220164 | BG24: =_xlfn.IFNA(VLOOKUP($BA24,HAVERD!$A:$BS,BG$2,FALSE),"") -> 4.1421522 | BH24: =_xlfn.IFNA(VLOOKUP($BA24,HAVERD!$A:$BS,BH$2,FALSE),"") -> 4.0768151 | BI24: =_xlfn.IFNA(VLOOKUP($BA24,HAVERD!$A:$BS,BI$2,FALSE),"") -> 4.0261351 | ... CX24: =_xlfn.IFNA(VLOOKUP($BA24,HAVERD!$A:$BS,CX$2,FALSE),"") -> 3.9258982
A25: =A8 -> 45667 | B25: =VLOOKUP($A25,HAVERD!$A:$BS,B$2,FALSE) -> 4.7 | C25: =VLOOKUP($A25,HAVERD!$A:$BS,C$2,FALSE) -> 4.6000014 | D25: =VLOOKUP($A25,HAVERD!$A:$BS,D$2,FALSE) -> 4.5105074 | E25: =VLOOKUP($A25,HAVERD!$A:$BS,E$2,FALSE) -> 4.456478 | F25: =VLOOKUP($A25,HAVERD!$A:$BS,F$2,FALSE) -> 4.4178169 | G25: =VLOOKUP($A25,HAVERD!$A:$BS,G$2,FALSE) -> 4.3838371 | H25: =VLOOKUP($A25,HAVERD!$A:$BS,H$2,FALSE) -> 4.352702 | I25: =VLOOKUP($A25,HAVERD!$A:$BS,I$2,FALSE) -> 4.3253638 | ... AX25: =VLOOKUP($A25,HAVERD!$A:$BS,AX$2,FALSE) -> 4.0711338 | BA25: =BA8 -> 45709 | BB25: =_xlfn.IFNA(VLOOKUP($BA25,HAVERD!$A:$BS,BB$2,FALSE),"") -> 4.4549 | BC25: =_xlfn.IFNA(VLOOKUP($BA25,HAVERD!$A:$BS,BC$2,FALSE),"") -> 4.4505201 | BD25: =_xlfn.IFNA(VLOOKUP($BA25,HAVERD!$A:$BS,BD$2,FALSE),"") -> 4.3800096 | BE25: =_xlfn.IFNA(VLOOKUP($BA25,HAVERD!$A:$BS,BE$2,FALSE),"") -> 4.2952907 | BF25: =_xlfn.IFNA(VLOOKUP($BA25,HAVERD!$A:$BS,BF$2,FALSE),"") -> 4.2094131 | BG25: =_xlfn.IFNA(VLOOKUP($BA25,HAVERD!$A:$BS,BG$2,FALSE),"") -> 4.1322403 | BH25: =_xlfn.IFNA(VLOOKUP($BA25,HAVERD!$A:$BS,BH$2,FALSE),"") -> 4.0680501 | BI25: =_xlfn.IFNA(VLOOKUP($BA25,HAVERD!$A:$BS,BI$2,FALSE),"") -> 4.0181879 | ... CX25: =_xlfn.IFNA(VLOOKUP($BA25,HAVERD!$A:$BS,CX$2,FALSE),"") -> 3.8754043
A26: =A9 -> 45670 | B26: =VLOOKUP($A26,HAVERD!$A:$BS,B$2,FALSE) -> 4.7 | C26: =VLOOKUP($A26,HAVERD!$A:$BS,C$2,FALSE) -> 4.583527 | D26: =VLOOKUP($A26,HAVERD!$A:$BS,D$2,FALSE) -> 4.5112586 | E26: =VLOOKUP($A26,HAVERD!$A:$BS,E$2,FALSE) -> 4.4690879 | F26: =VLOOKUP($A26,HAVERD!$A:$BS,F$2,FALSE) -> 4.438039 | G26: =VLOOKUP($A26,HAVERD!$A:$BS,G$2,FALSE) -> 4.4093316 | H26: =VLOOKUP($A26,HAVERD!$A:$BS,H$2,FALSE) -> 4.3818388 | I26: =VLOOKUP($A26,HAVERD!$A:$BS,I$2,FALSE) -> 4.3565668 | ... AX26: =VLOOKUP($A26,HAVERD!$A:$BS,AX$2,FALSE) -> 4.0874707 | BA26: =BA9 -> 45712 | BB26: =_xlfn.IFNA(VLOOKUP($BA26,HAVERD!$A:$BS,BB$2,FALSE),"") -> 4.4545 | BC26: =_xlfn.IFNA(VLOOKUP($BA26,HAVERD!$A:$BS,BC$2,FALSE),"") -> 4.4488754 | BD26: =_xlfn.IFNA(VLOOKUP($BA26,HAVERD!$A:$BS,BD$2,FALSE),"") -> 4.3767178 | BE26: =_xlfn.IFNA(VLOOKUP($BA26,HAVERD!$A:$BS,BE$2,FALSE),"") -> 4.2936555 | BF26: =_xlfn.IFNA(VLOOKUP($BA26,HAVERD!$A:$BS,BF$2,FALSE),"") -> 4.2122104 | BG26: =_xlfn.IFNA(VLOOKUP($BA26,HAVERD!$A:$BS,BG$2,FALSE),"") -> 4.1388356 | BH26: =_xlfn.IFNA(VLOOKUP($BA26,HAVERD!$A:$BS,BH$2,FALSE),"") -> 4.0762553 | BI26: =_xlfn.IFNA(VLOOKUP($BA26,HAVERD!$A:$BS,BI$2,FALSE),"") -> 4.0252535 | ... CX26: =_xlfn.IFNA(VLOOKUP($BA26,HAVERD!$A:$BS,CX$2,FALSE),"") -> 3.8839484
A27: =A10 -> 45671 | B27: =VLOOKUP($A27,HAVERD!$A:$BS,B$2,FALSE) -> 4.7 | C27: =VLOOKUP($A27,HAVERD!$A:$BS,C$2,FALSE) -> 4.5928108 | D27: =VLOOKUP($A27,HAVERD!$A:$BS,D$2,FALSE) -> 4.5365359 | E27: =VLOOKUP($A27,HAVERD!$A:$BS,E$2,FALSE) -> 4.5032957 | F27: =VLOOKUP($A27,HAVERD!$A:$BS,F$2,FALSE) -> 4.4752949 | G27: =VLOOKUP($A27,HAVERD!$A:$BS,G$2,FALSE) -> 4.446087 | H27: =VLOOKUP($A27,HAVERD!$A:$BS,H$2,FALSE) -> 4.4172097 | I27: =VLOOKUP($A27,HAVERD!$A:$BS,I$2,FALSE) -> 4.3922553 | ... AX27: =VLOOKUP($A27,HAVERD!$A:$BS,AX$2,FALSE) -> 4.1407446 | BA27: =BA10 -> 45713 | BB27: =_xlfn.IFNA(VLOOKUP($BA27,HAVERD!$A:$BS,BB$2,FALSE),"") -> 4.4547 | BC27: =_xlfn.IFNA(VLOOKUP($BA27,HAVERD!$A:$BS,BC$2,FALSE),"") -> 4.4468471 | BD27: =_xlfn.IFNA(VLOOKUP($BA27,HAVERD!$A:$BS,BD$2,FALSE),"") -> 4.3716378 | BE27: =_xlfn.IFNA(VLOOKUP($BA27,HAVERD!$A:$BS,BE$2,FALSE),"") -> 4.2849921 | BF27: =_xlfn.IFNA(VLOOKUP($BA27,HAVERD!$A:$BS,BF$2,FALSE),"") -> 4.1996561 | BG27: =_xlfn.IFNA(VLOOKUP($BA27,HAVERD!$A:$BS,BG$2,FALSE),"") -> 4.1218341 | BH27: =_xlfn.IFNA(VLOOKUP($BA27,HAVERD!$A:$BS,BH$2,FALSE),"") -> 4.0542254 | BI27: =_xlfn.IFNA(VLOOKUP($BA27,HAVERD!$A:$BS,BI$2,FALSE),"") -> 3.9980307 | ... CX27: =_xlfn.IFNA(VLOOKUP($BA27,HAVERD!$A:$BS,CX$2,FALSE),"") -> 3.7948826
A28: =A11 -> 45672 | B28: =VLOOKUP($A28,HAVERD!$A:$BS,B$2,FALSE) -> 4.7001 | C28: =VLOOKUP($A28,HAVERD!$A:$BS,C$2,FALSE) -> 4.5407893 | D28: =VLOOKUP($A28,HAVERD!$A:$BS,D$2,FALSE) -> 4.4591869 | E28: =VLOOKUP($A28,HAVERD!$A:$BS,E$2,FALSE) -> 4.406464 | F28: =VLOOKUP($A28,HAVERD!$A:$BS,F$2,FALSE) -> 4.3616584 | G28: =VLOOKUP($A28,HAVERD!$A:$BS,G$2,FALSE) -> 4.3170663 | H28: =VLOOKUP($A28,HAVERD!$A:$BS,H$2,FALSE) -> 4.2738664 | I28: =VLOOKUP($A28,HAVERD!$A:$BS,I$2,FALSE) -> 4.2354391 | ... AX28: =VLOOKUP($A28,HAVERD!$A:$BS,AX$2,FALSE) -> 3.9786814 | BA28: =BA11 -> 45714 | BB28: =_xlfn.IFNA(VLOOKUP($BA28,HAVERD!$A:$BS,BB$2,FALSE),"") -> 4.4547 | BC28: =_xlfn.IFNA(VLOOKUP($BA28,HAVERD!$A:$BS,BC$2,FALSE),"") -> 4.4461588 | BD28: =_xlfn.IFNA(VLOOKUP($BA28,HAVERD!$A:$BS,BD$2,FALSE),"") -> 4.368999 | BE28: =_xlfn.IFNA(VLOOKUP($BA28,HAVERD!$A:$BS,BE$2,FALSE),"") -> 4.2811278 | BF28: =_xlfn.IFNA(VLOOKUP($BA28,HAVERD!$A:$BS,BF$2,FALSE),"") -> 4.1959818 | BG28: =_xlfn.IFNA(VLOOKUP($BA28,HAVERD!$A:$BS,BG$2,FALSE),"") -> 4.118973 | BH28: =_xlfn.IFNA(VLOOKUP($BA28,HAVERD!$A:$BS,BH$2,FALSE),"") -> 4.0520088 | BI28: =_xlfn.IFNA(VLOOKUP($BA28,HAVERD!$A:$BS,BI$2,FALSE),"") -> 3.9965994 | ... CX28: =_xlfn.IFNA(VLOOKUP($BA28,HAVERD!$A:$BS,CX$2,FALSE),"") -> 3.7896401
A29: =A12 -> 45673 | B29: =VLOOKUP($A29,HAVERD!$A:$BS,B$2,FALSE) -> 4.7 | C29: =VLOOKUP($A29,HAVERD!$A:$BS,C$2,FALSE) -> 4.5365792 | D29: =VLOOKUP($A29,HAVERD!$A:$BS,D$2,FALSE) -> 4.4591431 | E29: =VLOOKUP($A29,HAVERD!$A:$BS,E$2,FALSE) -> 4.4049873 | F29: =VLOOKUP($A29,HAVERD!$A:$BS,F$2,FALSE) -> 4.3545297 | G29: =VLOOKUP($A29,HAVERD!$A:$BS,G$2,FALSE) -> 4.3030819 | H29: =VLOOKUP($A29,HAVERD!$A:$BS,H$2,FALSE) -> 4.2536483 | I29: =VLOOKUP($A29,HAVERD!$A:$BS,I$2,FALSE) -> 4.2099764 | ... AX29: =VLOOKUP($A29,HAVERD!$A:$BS,AX$2,FALSE) -> 3.9412115 | BA29: =BA12 -> 45715 | BB29: =_xlfn.IFNA(VLOOKUP($BA29,HAVERD!$A:$BS,BB$2,FALSE),"") -> 4.4547 | BC29: =_xlfn.IFNA(VLOOKUP($BA29,HAVERD!$A:$BS,BC$2,FALSE),"") -> 4.444503 | BD29: =_xlfn.IFNA(VLOOKUP($BA29,HAVERD!$A:$BS,BD$2,FALSE),"") -> 4.3663735 | BE29: =_xlfn.IFNA(VLOOKUP($BA29,HAVERD!$A:$BS,BE$2,FALSE),"") -> 4.2781586 | BF29: =_xlfn.IFNA(VLOOKUP($BA29,HAVERD!$A:$BS,BF$2,FALSE),"") -> 4.1934058 | BG29: =_xlfn.IFNA(VLOOKUP($BA29,HAVERD!$A:$BS,BG$2,FALSE),"") -> 4.1170166 | BH29: =_xlfn.IFNA(VLOOKUP($BA29,HAVERD!$A:$BS,BH$2,FALSE),"") -> 4.0505527 | BI29: =_xlfn.IFNA(VLOOKUP($BA29,HAVERD!$A:$BS,BI$2,FALSE),"") -> 3.9952263 | ... CX29: =_xlfn.IFNA(VLOOKUP($BA29,HAVERD!$A:$BS,CX$2,FALSE),"") -> 3.820733
A30: =A13 -> 45674 | B30: =VLOOKUP($A30,HAVERD!$A:$BS,B$2,FALSE) -> 4.7 | C30: =VLOOKUP($A30,HAVERD!$A:$BS,C$2,FALSE) -> 4.5219514 | D30: =VLOOKUP($A30,HAVERD!$A:$BS,D$2,FALSE) -> 4.4415724 | E30: =VLOOKUP($A30,HAVERD!$A:$BS,E$2,FALSE) -> 4.3810211 | F30: =VLOOKUP($A30,HAVERD!$A:$BS,F$2,FALSE) -> 4.3255362 | G30: =VLOOKUP($A30,HAVERD!$A:$BS,G$2,FALSE) -> 4.2715314 | H30: =VLOOKUP($A30,HAVERD!$A:$BS,H$2,FALSE) -> 4.2216815 | I30: =VLOOKUP($A30,HAVERD!$A:$BS,I$2,FALSE) -> 4.1788801 | ... AX30: =VLOOKUP($A30,HAVERD!$A:$BS,AX$2,FALSE) -> 3.9200765 | BA30: =BA13 -> 45716 | BB30: =_xlfn.IFNA(VLOOKUP($BA30,HAVERD!$A:$BS,BB$2,FALSE),"") -> 4.4552 | BC30: =_xlfn.IFNA(VLOOKUP($BA30,HAVERD!$A:$BS,BC$2,FALSE),"") -> 4.4457987 | BD30: =_xlfn.IFNA(VLOOKUP($BA30,HAVERD!$A:$BS,BD$2,FALSE),"") -> 4.3680602 | BE30: =_xlfn.IFNA(VLOOKUP($BA30,HAVERD!$A:$BS,BE$2,FALSE),"") -> 4.2781697 | BF30: =_xlfn.IFNA(VLOOKUP($BA30,HAVERD!$A:$BS,BF$2,FALSE),"") -> 4.191606 | BG30: =_xlfn.IFNA(VLOOKUP($BA30,HAVERD!$A:$BS,BG$2,FALSE),"") -> 4.1142582 | BH30: =_xlfn.IFNA(VLOOKUP($BA30,HAVERD!$A:$BS,BH$2,FALSE),"") -> 4.046947 | BI30: =_xlfn.IFNA(VLOOKUP($BA30,HAVERD!$A:$BS,BI$2,FALSE),"") -> 3.9904155 | ... CX30: =_xlfn.IFNA(VLOOKUP($BA30,HAVERD!$A:$BS,CX$2,FALSE),"") -> 3.7762567
A31: =A14 -> 45677 | B31: =VLOOKUP($A31,HAVERD!$A:$BS,B$2,FALSE) -> 4.7 | C31: =VLOOKUP($A31,HAVERD!$A:$BS,C$2,FALSE) -> 4.5000267 | D31: =VLOOKUP($A31,HAVERD!$A:$BS,D$2,FALSE) -> 4.4463263 | E31: =VLOOKUP($A31,HAVERD!$A:$BS,E$2,FALSE) -> 4.3909734 | F31: =VLOOKUP($A31,HAVERD!$A:$BS,F$2,FALSE) -> 4.332188 | G31: =VLOOKUP($A31,HAVERD!$A:$BS,G$2,FALSE) -> 4.2745293 | H31: =VLOOKUP($A31,HAVERD!$A:$BS,H$2,FALSE) -> 4.2228441 | I31: =VLOOKUP($A31,HAVERD!$A:$BS,I$2,FALSE) -> 4.1799756 | ... AX31: =VLOOKUP($A31,HAVERD!$A:$BS,AX$2,FALSE) -> 3.9254038 | BA31: =BA14 -> 45719 | BB31: =_xlfn.IFNA(VLOOKUP($BA31,HAVERD!$A:$BS,BB$2,FALSE),"") -> 4.455 | BC31: =_xlfn.IFNA(VLOOKUP($BA31,HAVERD!$A:$BS,BC$2,FALSE),"") -> 4.4462565 | BD31: =_xlfn.IFNA(VLOOKUP($BA31,HAVERD!$A:$BS,BD$2,FALSE),"") -> 4.3679877 | BE31: =_xlfn.IFNA(VLOOKUP($BA31,HAVERD!$A:$BS,BE$2,FALSE),"") -> 4.2797481 | BF31: =_xlfn.IFNA(VLOOKUP($BA31,HAVERD!$A:$BS,BF$2,FALSE),"") -> 4.1987048 | BG31: =_xlfn.IFNA(VLOOKUP($BA31,HAVERD!$A:$BS,BG$2,FALSE),"") -> 4.1278003 | BH31: =_xlfn.IFNA(VLOOKUP($BA31,HAVERD!$A:$BS,BH$2,FALSE),"") -> 4.0667299 | BI31: =_xlfn.IFNA(VLOOKUP($BA31,HAVERD!$A:$BS,BI$2,FALSE),"") -> 4.0163036 | ... CX31: =_xlfn.IFNA(VLOOKUP($BA31,HAVERD!$A:$BS,CX$2,FALSE),"") -> 3.8042811
A32: =A15 -> 45678 | B32: =VLOOKUP($A32,HAVERD!$A:$BS,B$2,FALSE) -> 4.7 | C32: =VLOOKUP($A32,HAVERD!$A:$BS,C$2,FALSE) -> 4.484872 | D32: =VLOOKUP($A32,HAVERD!$A:$BS,D$2,FALSE) -> 4.4384666 | E32: =VLOOKUP($A32,HAVERD!$A:$BS,E$2,FALSE) -> 4.3841836 | F32: =VLOOKUP($A32,HAVERD!$A:$BS,F$2,FALSE) -> 4.3240279 | G32: =VLOOKUP($A32,HAVERD!$A:$BS,G$2,FALSE) -> 4.2650434 | H32: =VLOOKUP($A32,HAVERD!$A:$BS,H$2,FALSE) -> 4.212658 | I32: =VLOOKUP($A32,HAVERD!$A:$BS,I$2,FALSE) -> 4.1700255 | ... AX32: =VLOOKUP($A32,HAVERD!$A:$BS,AX$2,FALSE) -> 3.8604511 | BA32: =BA15 -> 45720 | BB32: =_xlfn.IFNA(VLOOKUP($BA32,HAVERD!$A:$BS,BB$2,FALSE),"") -> 4.4551 | BC32: =_xlfn.IFNA(VLOOKUP($BA32,HAVERD!$A:$BS,BC$2,FALSE),"") -> 4.4415946 | BD32: =_xlfn.IFNA(VLOOKUP($BA32,HAVERD!$A:$BS,BD$2,FALSE),"") -> 4.3611957 | BE32: =_xlfn.IFNA(VLOOKUP($BA32,HAVERD!$A:$BS,BE$2,FALSE),"") -> 4.2711778 | BF32: =_xlfn.IFNA(VLOOKUP($BA32,HAVERD!$A:$BS,BF$2,FALSE),"") -> 4.1885673 | BG32: =_xlfn.IFNA(VLOOKUP($BA32,HAVERD!$A:$BS,BG$2,FALSE),"") -> 4.1154542 | BH32: =_xlfn.IFNA(VLOOKUP($BA32,HAVERD!$A:$BS,BH$2,FALSE),"") -> 4.0511841 | BI32: =_xlfn.IFNA(VLOOKUP($BA32,HAVERD!$A:$BS,BI$2,FALSE),"") -> 3.9966813 | ... CX32: =_xlfn.IFNA(VLOOKUP($BA32,HAVERD!$A:$BS,CX$2,FALSE),"") -> 3.782176
A33: =A16 -> 45679 | B33: =VLOOKUP($A33,HAVERD!$A:$BS,B$2,FALSE) -> 4.7 | C33: =VLOOKUP($A33,HAVERD!$A:$BS,C$2,FALSE) -> 4.4757356 | D33: =VLOOKUP($A33,HAVERD!$A:$BS,D$2,FALSE) -> 4.4383779 | E33: =VLOOKUP($A33,HAVERD!$A:$BS,E$2,FALSE) -> 4.3856464 | F33: =VLOOKUP($A33,HAVERD!$A:$BS,F$2,FALSE) -> 4.3229666 | G33: =VLOOKUP($A33,HAVERD!$A:$BS,G$2,FALSE) -> 4.2598599 | H33: =VLOOKUP($A33,HAVERD!$A:$BS,H$2,FALSE) -> 4.2032262 | I33: =VLOOKUP($A33,HAVERD!$A:$BS,I$2,FALSE) -> 4.1570015 | ... AX33: =VLOOKUP($A33,HAVERD!$A:$BS,AX$2,FALSE) -> 3.8686946 | BA33: =BA16 -> 45721 | BB33: =_xlfn.IFNA(VLOOKUP($BA33,HAVERD!$A:$BS,BB$2,FALSE),"") -> 4.455 | BC33: =_xlfn.IFNA(VLOOKUP($BA33,HAVERD!$A:$BS,BC$2,FALSE),"") -> 4.4465266 | BD33: =_xlfn.IFNA(VLOOKUP($BA33,HAVERD!$A:$BS,BD$2,FALSE),"") -> 4.3696171 | BE33: =_xlfn.IFNA(VLOOKUP($BA33,HAVERD!$A:$BS,BE$2,FALSE),"") -> 4.2858851 | BF33: =_xlfn.IFNA(VLOOKUP($BA33,HAVERD!$A:$BS,BF$2,FALSE),"") -> 4.2090963 | BG33: =_xlfn.IFNA(VLOOKUP($BA33,HAVERD!$A:$BS,BG$2,FALSE),"") -> 4.1413667 | BH33: =_xlfn.IFNA(VLOOKUP($BA33,HAVERD!$A:$BS,BH$2,FALSE),"") -> 4.0831071 | BI33: =_xlfn.IFNA(VLOOKUP($BA33,HAVERD!$A:$BS,BI$2,FALSE),"") -> 4.0356271 | ... CX33: =_xlfn.IFNA(VLOOKUP($BA33,HAVERD!$A:$BS,CX$2,FALSE),"") -> 3.9511751
A34: =A17 -> 45680 | B34: =VLOOKUP($A34,HAVERD!$A:$BS,B$2,FALSE) -> 4.7001 | C34: =VLOOKUP($A34,HAVERD!$A:$BS,C$2,FALSE) -> 4.4650853 | D34: =VLOOKUP($A34,HAVERD!$A:$BS,D$2,FALSE) -> 4.4336144 | E34: =VLOOKUP($A34,HAVERD!$A:$BS,E$2,FALSE) -> 4.3790128 | F34: =VLOOKUP($A34,HAVERD!$A:$BS,F$2,FALSE) -> 4.3105457 | G34: =VLOOKUP($A34,HAVERD!$A:$BS,G$2,FALSE) -> 4.2407452 | H34: =VLOOKUP($A34,HAVERD!$A:$BS,H$2,FALSE) -> 4.178016 | I34: =VLOOKUP($A34,HAVERD!$A:$BS,I$2,FALSE) -> 4.1267057 | ... AX34: =VLOOKUP($A34,HAVERD!$A:$BS,AX$2,FALSE) -> 3.8872239 | BA34: =BA17 -> 45722 | BB34: =_xlfn.IFNA(VLOOKUP($BA34,HAVERD!$A:$BS,BB$2,FALSE),"") -> 4.4557 | BC34: =_xlfn.IFNA(VLOOKUP($BA34,HAVERD!$A:$BS,BC$2,FALSE),"") -> 4.4467328 | BD34: =_xlfn.IFNA(VLOOKUP($BA34,HAVERD!$A:$BS,BD$2,FALSE),"") -> 4.3658811 | BE34: =_xlfn.IFNA(VLOOKUP($BA34,HAVERD!$A:$BS,BE$2,FALSE),"") -> 4.2788619 | BF34: =_xlfn.IFNA(VLOOKUP($BA34,HAVERD!$A:$BS,BF$2,FALSE),"") -> 4.2024214 | BG34: =_xlfn.IFNA(VLOOKUP($BA34,HAVERD!$A:$BS,BG$2,FALSE),"") -> 4.1370563 | BH34: =_xlfn.IFNA(VLOOKUP($BA34,HAVERD!$A:$BS,BH$2,FALSE),"") -> 4.0809187 | BI34: =_xlfn.IFNA(VLOOKUP($BA34,HAVERD!$A:$BS,BI$2,FALSE),"") -> 4.0336996 | ... CX34: =_xlfn.IFNA(VLOOKUP($BA34,HAVERD!$A:$BS,CX$2,FALSE),"") -> 3.937386
... A37: =A20 -> 45685 | B37: =VLOOKUP($A37,HAVERD!$A:$BS,B$2,FALSE) -> 4.7 | C37: =VLOOKUP($A37,HAVERD!$A:$BS,C$2,FALSE) -> 4.4598169 | D37: =VLOOKUP($A37,HAVERD!$A:$BS,D$2,FALSE) -> 4.4206843 | E37: =VLOOKUP($A37,HAVERD!$A:$BS,E$2,FALSE) -> 4.362708 | F37: =VLOOKUP($A37,HAVERD!$A:$BS,F$2,FALSE) -> 4.2944473 | G37: =VLOOKUP($A37,HAVERD!$A:$BS,G$2,FALSE) -> 4.2275019 | H37: =VLOOKUP($A37,HAVERD!$A:$BS,H$2,FALSE) -> 4.1682824 | I37: =VLOOKUP($A37,HAVERD!$A:$BS,I$2,FALSE) -> 4.1201531 | ... AX37: =VLOOKUP($A37,HAVERD!$A:$BS,AX$2,FALSE) -> 3.8577803 | BA37: =BA20 -> 45727 | BB37: =_xlfn.IFNA(VLOOKUP($BA37,HAVERD!$A:$BS,BB$2,FALSE),"") | BC37: =_xlfn.IFNA(VLOOKUP($BA37,HAVERD!$A:$BS,BC$2,FALSE),"") | BD37: =_xlfn.IFNA(VLOOKUP($BA37,HAVERD!$A:$BS,BD$2,FALSE),"") | BE37: =_xlfn.IFNA(VLOOKUP($BA37,HAVERD!$A:$BS,BE$2,FALSE),"") | BF37: =_xlfn.IFNA(VLOOKUP($BA37,HAVERD!$A:$BS,BF$2,FALSE),"") | BG37: =_xlfn.IFNA(VLOOKUP($BA37,HAVERD!$A:$BS,BG$2,FALSE),"") | BH37: =_xlfn.IFNA(VLOOKUP($BA37,HAVERD!$A:$BS,BH$2,FALSE),"") | BI37: =_xlfn.IFNA(VLOOKUP($BA37,HAVERD!$A:$BS,BI$2,FALSE),"") | ... CX37: =_xlfn.IFNA(VLOOKUP($BA37,HAVERD!$A:$BS,CX$2,FALSE),"")
A39: Average | BA39: Average
A40: Month | B40: =MONTH(B20) -> 1 | C40: =MONTH(C20) -> 2 | D40: =MONTH(D20) -> 3 | E40: =MONTH(E20) -> 4 | F40: =MONTH(F20) -> 5 | G40: =MONTH(G20) -> 6 | H40: =MONTH(H20) -> 7 | I40: =MONTH(I20) -> 8 | ... AX40: =MONTH(AX20) -> 1 | BA40: Month | BB40: =MONTH(BB18) -> 3 | BC40: =MONTH(BC18) -> 4 | BD40: =MONTH(BD18) -> 5 | BE40: =MONTH(BE18) -> 6 | BF40: =MONTH(BF18) -> 7 | BG40: =MONTH(BG18) -> 8 | BH40: =MONTH(BH18) -> 9 | BI40: =MONTH(BI18) -> 10 | ... CX40: =MONTH(CX18) -> 3
A41: Year | B41: =YEAR(B20) -> 2025 | C41: =YEAR(C20) -> 2025 | D41: =YEAR(D20) -> 2025 | E41: =YEAR(E20) -> 2025 | F41: =YEAR(F20) -> 2025 | G41: =YEAR(G20) -> 2025 | H41: =YEAR(H20) -> 2025 | I41: =YEAR(I20) -> 2025 | ... AX41: =YEAR(AX20) -> 2029 | BA41: Year | BB41: =YEAR(BB20) -> 2025 | BC41: =YEAR(BC20) -> 2025 | BD41: =YEAR(BD20) -> 2025 | BE41: =YEAR(BE20) -> 2025 | BF41: =YEAR(BF20) -> 2025 | BG41: =YEAR(BG20) -> 2025 | BH41: =YEAR(BH20) -> 2025 | BI41: =YEAR(BI20) -> 2025 | ... CX41: =YEAR(CX20) -> 2029
A42: YYYYMM | B42: =B41*100+B40 -> 202501 | C42: =C41*100+C40 -> 202502 | D42: =D41*100+D40 -> 202503 | E42: =E41*100+E40 -> 202504 | F42: =F41*100+F40 -> 202505 | G42: =G41*100+G40 -> 202506 | H42: =H41*100+H40 -> 202507 | I42: =I41*100+I40 -> 202508 | ... AX42: =AX41*100+AX40 -> 202901 | BA42: YYYYMM | BB42: =BB41*100+BB40 -> 202503 | BC42: =BC41*100+BC40 -> 202504 | BD42: =BD41*100+BD40 -> 202505 | BE42: =BE41*100+BE40 -> 202506 | BF42: =BF41*100+BF40 -> 202507 | BG42: =BG41*100+BG40 -> 202508 | BH42: =BH41*100+BH40 -> 202509 | BI42: =BI41*100+BI40 -> 202510 | ... CX42: =CX41*100+CX40 -> 202903
A43: Quarter | B43: =IF(B40<4,1,IF(B40<7,2,IF(B40<10,3,4))) -> 1 | C43: =IF(C40<4,1,IF(C40<7,2,IF(C40<10,3,4))) -> 1 | D43: =IF(D40<4,1,IF(D40<7,2,IF(D40<10,3,4))) -> 1 | E43: =IF(E40<4,1,IF(E40<7,2,IF(E40<10,3,4))) -> 2 | F43: =IF(F40<4,1,IF(F40<7,2,IF(F40<10,3,4))) -> 2 | G43: =IF(G40<4,1,IF(G40<7,2,IF(G40<10,3,4))) -> 2 | H43: =IF(H40<4,1,IF(H40<7,2,IF(H40<10,3,4))) -> 3 | I43: =IF(I40<4,1,IF(I40<7,2,IF(I40<10,3,4))) -> 3 | ... AX43: =IF(AX40<4,1,IF(AX40<7,2,IF(AX40<10,3,4))) -> 1 | BA43: Quarter | BB43: =IF(BB40<4,1,IF(BB40<7,2,IF(BB40<10,3,4))) -> 1 | BC43: =IF(BC40<4,1,IF(BC40<7,2,IF(BC40<10,3,4))) -> 2 | BD43: =IF(BD40<4,1,IF(BD40<7,2,IF(BD40<10,3,4))) -> 2 | BE43: =IF(BE40<4,1,IF(BE40<7,2,IF(BE40<10,3,4))) -> 2 | BF43: =IF(BF40<4,1,IF(BF40<7,2,IF(BF40<10,3,4))) -> 3 | BG43: =IF(BG40<4,1,IF(BG40<7,2,IF(BG40<10,3,4))) -> 3 | BH43: =IF(BH40<4,1,IF(BH40<7,2,IF(BH40<10,3,4))) -> 3 | BI43: =IF(BI40<4,1,IF(BI40<7,2,IF(BI40<10,3,4))) -> 4 | ... CX43: =IF(CX40<4,1,IF(CX40<7,2,IF(CX40<10,3,4))) -> 1
A44: YYYYQQ | B44: =B41*100+B43 -> 202501 | C44: =C41*100+C43 -> 202501 | D44: =D41*100+D43 -> 202501 | E44: =E41*100+E43 -> 202502 | F44: =F41*100+F43 -> 202502 | G44: =G41*100+G43 -> 202502 | H44: =H41*100+H43 -> 202503 | I44: =I41*100+I43 -> 202503 | ... AX44: =AX41*100+AX43 -> 202901 | BA44: YYYYQQ | BB44: =BB41*100+BB43 -> 202501 | BC44: =BC41*100+BC43 -> 202502 | BD44: =BD41*100+BD43 -> 202502 | BE44: =BE41*100+BE43 -> 202502 | BF44: =BF41*100+BF43 -> 202503 | BG44: =BG41*100+BG43 -> 202503 | BH44: =BH41*100+BH43 -> 202503 | BI44: =BI41*100+BI43 -> 202504 | ... CX44: =CX41*100+CX43 -> 202901
A45: Average | B45: =AVERAGE(B23:B37) -> 4.7000133 | C45: =AVERAGE(C23:C37) -> 4.5272115 | D45: =AVERAGE(D23:D37) -> 4.4663852 | E45: =AVERAGE(E23:E37) -> 4.4136371 | F45: =AVERAGE(F23:F37) -> 4.3614053 | G45: =AVERAGE(G23:G37) -> 4.3101281 | H45: =AVERAGE(H23:H37) -> 4.263141 | I45: =AVERAGE(I23:I37) -> 4.2233264 | ... AX45: =AVERAGE(AX23:AX37) -> 3.9589874 | BA45: Average | BB45: =AVERAGE(BB23:BB37) -> 3.8184357 | BC45: =AVERAGE(BC23:BC37) -> 4.1299947 | BD45: =AVERAGE(BD23:BD37) -> 4.0591924 | BE45: =AVERAGE(BE23:BE37) -> 3.9784002 | BF45: =AVERAGE(BF23:BF37) -> 3.9012087 | BG45: =AVERAGE(BG23:BG37) -> 3.8325264 | BH45: =AVERAGE(BH23:BH37) -> 3.7737238 | BI45: =AVERAGE(BI23:BI37) -> 3.7257269 | ... CX45: =AVERAGE(CX23:CX37) -> 3.5815304
BA46: Latest | BB46: =BB35 -> 0 | BC46: =BC35 -> 4.44288 | BD46: =BD35 -> 4.3566152 | BE46: =BE35 -> 4.2638778 | BF46: =BF35 -> 4.1820019 | BG46: =BG35 -> 4.1121265 | BH46: =BH35 -> 4.0527027 | BI46: =BI35 -> 4.0035401 | ... CX46: =CX35 -> 3.8952036
A48: Quarterly series | BA48: Quarterly series
B49: =B44 -> 202501 | C49: =IF(RIGHT(B49)="4",B49+97,B49+1) -> 202502 | D49: =IF(RIGHT(C49)="4",C49+97,C49+1) -> 202503 | E49: =IF(RIGHT(D49)="4",D49+97,D49+1) -> 202504 | F49: =IF(RIGHT(E49)="4",E49+97,E49+1) -> 202601 | G49: =IF(RIGHT(F49)="4",F49+97,F49+1) -> 202602 | H49: =IF(RIGHT(G49)="4",G49+97,G49+1) -> 202603 | I49: =IF(RIGHT(H49)="4",H49+97,H49+1) -> 202604 | J49: =IF(RIGHT(I49)="4",I49+97,I49+1) -> 202701 | ... R49: =IF(RIGHT(Q49)="4",Q49+97,Q49+1) -> 202901 | BB49: =BB44 -> 202501 | BC49: =IF(RIGHT(BB49)="4",BB49+97,BB49+1) -> 202502 | BD49: =IF(RIGHT(BC49)="4",BC49+97,BC49+1) -> 202503 | BE49: =IF(RIGHT(BD49)="4",BD49+97,BD49+1) -> 202504 | BF49: =IF(RIGHT(BE49)="4",BE49+97,BE49+1) -> 202601 | BG49: =IF(RIGHT(BF49)="4",BF49+97,BF49+1) -> 202602 | BH49: =IF(RIGHT(BG49)="4",BG49+97,BG49+1) -> 202603 | BI49: =IF(RIGHT(BH49)="4",BH49+97,BH49+1) -> 202604 | BJ49: =IF(RIGHT(BI49)="4",BI49+97,BI49+1) -> 202701 | ... BQ49: =IF(RIGHT(BP49)="4",BP49+97,BP49+1) -> 202804
A50: =A1 -> February 2025 MPR | B50: =AVERAGEIF($B$44:$AX$44,B49,$B$45:$AX$45) -> 4.5645367 | C50: =AVERAGEIF($B$44:$AX$44,C49,$B$45:$AX$45) -> 4.3617235 | D50: =AVERAGEIF($B$44:$AX$44,D49,$B$45:$AX$45) -> 4.2263009 | E50: =AVERAGEIF($B$44:$AX$44,E49,$B$45:$AX$45) -> 4.1600072 | F50: =AVERAGEIF($B$44:$AX$44,F49,$B$45:$AX$45) -> 4.1481619 | G50: =AVERAGEIF($B$44:$AX$44,G49,$B$45:$AX$45) -> 4.1427465 | H50: =AVERAGEIF($B$44:$AX$44,H49,$B$45:$AX$45) -> 4.1292652 | I50: =AVERAGEIF($B$44:$AX$44,I49,$B$45:$AX$45) -> 4.106222 | ... R50: =AVERAGEIF($B$44:$AX$44,R49,$B$45:$AX$45) -> 3.9589874 | BA50: =BA1 -> March 2025 | BB50: =AVERAGEIF($BB$44:$CW$44,BB49,$BB$45:$CW$45) -> 3.8184357 | BC50: =AVERAGEIF($BB$44:$CW$44,BC49,$BB$45:$CW$45) -> 4.0558624 | BD50: =AVERAGEIF($BB$44:$CW$44,BD49,$BB$45:$CW$45) -> 3.8358196 | BE50: =AVERAGEIF($BB$44:$CW$44,BE49,$BB$45:$CW$45) -> 3.6923198 | BF50: =AVERAGEIF($BB$44:$CW$44,BF49,$BB$45:$CW$45) -> 3.6382333 | BG50: =AVERAGEIF($BB$44:$CW$44,BG49,$BB$45:$CW$45) -> 3.6320909 | BH50: =AVERAGEIF($BB$44:$CW$44,BH49,$BB$45:$CW$45) -> 3.6343689 | BI50: =AVERAGEIF($BB$44:$CW$44,BI49,$BB$45:$CW$45) -> 3.6303226 | ... BQ50: =AVERAGEIF($BB$44:$CW$44,BQ49,$BB$45:$CW$45) -> 3.5749849
BA52: Comparison - monthly
BB53: 44927 | BC53: 44958 | BD53: 44986 | BE53: 45017 | BF53: 45047 | BG53: 45078 | BH53: 45108 | BI53: 45139 | BJ53: 45170 | BK53: 45200 | BL53: 45231 | BM53: 45261 | BN53: 45292 | BO53: 45323 | BP53: 45352 | BQ53: 45383 | BR53: 45413 | BS53: 45444 | BT53: 45474 | BU53: 45505 | BV53: 45536 | BW53: 45566 | BX53: 45597 | BY53: 45627 | BZ53: 45658 | CA53: 45689 | CB53: 45717 | CC53: 45748 | CD53: 45778 | CE53: 45809 | CF53: 45839 | CG53: 45870 | CH53: 45901 | CI53: 45931 | CJ53: 45962 | CK53: 45992 | CL53: 46023 | CM53: 46054 | CN53: 46082 | CO53: 46113 | CP53: 46143 | CQ53: 46174 | CR53: 46204 | CS53: 46235 | CT53: 46266 | CU53: 46296 | CV53: 46327 | CW53: 46357 | CX53: 46388 | CY53: 46419 | CZ53: 46447 | DA53: 46478 | DB53: 46508 | DC53: 46539 | DD53: 46569 | DE53: 46600 | DF53: 46631 | DG53: 46661 | DH53: 46692 | DI53: 46722
BB54: =MONTH(BB53) -> 1 | BC54: =MONTH(BC53) -> 2 | BD54: =MONTH(BD53) -> 3 | BE54: =MONTH(BE53) -> 4 | BF54: =MONTH(BF53) -> 5 | BG54: =MONTH(BG53) -> 6 | BH54: =MONTH(BH53) -> 7 | BI54: =MONTH(BI53) -> 8 | ... DI54: =MONTH(DI53) -> 12
BB55: 202301 | BC55: =IF(BC54=1,BB55+89,BB55+1) -> 202302 | BD55: =IF(BD54=1,BC55+89,BC55+1) -> 202303 | BE55: =IF(BE54=1,BD55+89,BD55+1) -> 202304 | BF55: =IF(BF54=1,BE55+89,BE55+1) -> 202305 | BG55: =IF(BG54=1,BF55+89,BF55+1) -> 202306 | BH55: =IF(BH54=1,BG55+89,BG55+1) -> 202307 | BI55: =IF(BI54=1,BH55+89,BH55+1) -> 202308 | BJ55: =IF(BJ54=1,BI55+89,BI55+1) -> 202309 | ... DI55: =IF(DI54=1,DH55+89,DH55+1) -> 202712
BA56: Bank Rate | BB56: =VLOOKUP(BB53,HAVERM!$A:$N,14,FALSE) -> 3.5 | BC56: =VLOOKUP(BC53,HAVERM!$A:$N,14,FALSE) -> 4 | BD56: =VLOOKUP(BD53,HAVERM!$A:$N,14,FALSE) -> 4.25 | BE56: =VLOOKUP(BE53,HAVERM!$A:$N,14,FALSE) -> 4.25 | BF56: =VLOOKUP(BF53,HAVERM!$A:$N,14,FALSE) -> 4.5 | BG56: =VLOOKUP(BG53,HAVERM!$A:$N,14,FALSE) -> 5 | BH56: =VLOOKUP(BH53,HAVERM!$A:$N,14,FALSE) -> 5 | BI56: =VLOOKUP(BI53,HAVERM!$A:$N,14,FALSE) -> 5.25 | ... DI56: =VLOOKUP(DI53,HAVERM!$A:$N,14,FALSE) -> #N/A
BA57: =A50 -> February 2025 MPR | BB57: =HLOOKUP(BB$55,$B$42:$AX$45,4,FALSE) -> #N/A | BC57: =HLOOKUP(BC$55,$B$42:$AX$45,4,FALSE) -> #N/A | BD57: =HLOOKUP(BD$55,$B$42:$AX$45,4,FALSE) -> #N/A | BE57: =HLOOKUP(BE$55,$B$42:$AX$45,4,FALSE) -> #N/A | BF57: =HLOOKUP(BF$55,$B$42:$AX$45,4,FALSE) -> #N/A | BG57: =HLOOKUP(BG$55,$B$42:$AX$45,4,FALSE) -> #N/A | BH57: =HLOOKUP(BH$55,$B$42:$AX$45,4,FALSE) -> #N/A | BI57: =HLOOKUP(BI$55,$B$42:$AX$45,4,FALSE) -> #N/A | ... DI57: =HLOOKUP(DI$55,$B$42:$AX$45,4,FALSE) -> 4.0028338
BA58: =BA50 -> March 2025 | BB58: =HLOOKUP(BB$55,$BB$42:$CW$45,4,FALSE) -> #N/A | BC58: =HLOOKUP(BC$55,$BB$42:$CW$45,4,FALSE) -> #N/A | BD58: =HLOOKUP(BD$55,$BB$42:$CW$45,4,FALSE) -> #N/A | BE58: =HLOOKUP(BE$55,$BB$42:$CW$45,4,FALSE) -> #N/A | BF58: =HLOOKUP(BF$55,$BB$42:$CW$45,4,FALSE) -> #N/A | BG58: =HLOOKUP(BG$55,$BB$42:$CW$45,4,FALSE) -> #N/A | BH58: =HLOOKUP(BH$55,$BB$42:$CW$45,4,FALSE) -> #N/A | BI58: =HLOOKUP(BI$55,$BB$42:$CW$45,4,FALSE) -> #N/A | ... DI58: =HLOOKUP(DI$55,$BB$42:$CW$45,4,FALSE) -> 3.581511
BA59: Latest | BB59: =HLOOKUP(BB$55,$BB$42:$CW$46,5,FALSE) -> #N/A | BC59: =HLOOKUP(BC$55,$BB$42:$CW$46,5,FALSE) -> #N/A | BD59: =HLOOKUP(BD$55,$BB$42:$CW$46,5,FALSE) -> #N/A | BE59: =HLOOKUP(BE$55,$BB$42:$CW$46,5,FALSE) -> #N/A | BF59: =HLOOKUP(BF$55,$BB$42:$CW$46,5,FALSE) -> #N/A | BG59: =HLOOKUP(BG$55,$BB$42:$CW$46,5,FALSE) -> #N/A | BH59: =HLOOKUP(BH$55,$BB$42:$CW$46,5,FALSE) -> #N/A | BI59: =HLOOKUP(BI$55,$BB$42:$CW$46,5,FALSE) -> #N/A | ... DI59: =HLOOKUP(DI$55,$BB$42:$CW$46,5,FALSE) -> 3.8733069
BA60: Difference | BQ60: =BQ58-BQ57 -> #N/A | BR60: =BR58-BR57 -> #N/A | BS60: =BS58-BS57 -> #N/A | BT60: =BT58-BT57 -> #N/A | BU60: =BU58-BU57 -> #N/A | BV60: =BV58-BV57 -> #N/A | BW60: =BW58-BW57 -> #N/A | BX60: =BX58-BX57 -> #N/A | ... DI60: =DI58-DI57 -> -0.42132278
BA61: Next 3 years | DC61: =AVERAGE(BW60:DC60) -> #N/A
BA63: Comparison - quarterly
BB64: 44927 | BC64: 45017 | BD64: 45108 | BE64: 45200 | BF64: 45292 | BG64: 45383 | BH64: 45474 | BI64: 45566 | BJ64: 45658 | BK64: 45748 | BL64: 45839 | BM64: 45931 | BN64: 46023 | BO64: 46113 | BP64: 46204 | BQ64: 46296 | BR64: 46388 | BS64: 46478 | BT64: 46569 | BU64: 46661
BB65: 202301 | BC65: =IF(RIGHT(BB65)="4",BB65+97,BB65+1) -> 202302 | BD65: =IF(RIGHT(BC65)="4",BC65+97,BC65+1) -> 202303 | BE65: =IF(RIGHT(BD65)="4",BD65+97,BD65+1) -> 202304 | BF65: =IF(RIGHT(BE65)="4",BE65+97,BE65+1) -> 202401 | BG65: =IF(RIGHT(BF65)="4",BF65+97,BF65+1) -> 202402 | BH65: =IF(RIGHT(BG65)="4",BG65+97,BG65+1) -> 202403 | BI65: =IF(RIGHT(BH65)="4",BH65+97,BH65+1) -> 202404 | BJ65: =IF(RIGHT(BI65)="4",BI65+97,BI65+1) -> 202501 | ... BU65: =IF(RIGHT(BT65)="4",BT65+97,BT65+1) -> 202704
BA66: Bank Rate | BB66: =VLOOKUP(BB64,HAVERQ!$A:$G,7,FALSE) -> 4.25 | BC66: =VLOOKUP(BC64,HAVERQ!$A:$G,7,FALSE) -> 5 | BD66: =VLOOKUP(BD64,HAVERQ!$A:$G,7,FALSE) -> 5.25 | BE66: =VLOOKUP(BE64,HAVERQ!$A:$G,7,FALSE) -> 5.25 | BF66: =VLOOKUP(BF64,HAVERQ!$A:$G,7,FALSE) -> 5.25 | BG66: =VLOOKUP(BG64,HAVERQ!$A:$G,7,FALSE) -> 5.25 | BH66: =VLOOKUP(BH64,HAVERQ!$A:$G,7,FALSE) -> 5 | BI66: =VLOOKUP(BI64,HAVERQ!$A:$G,7,FALSE) -> 4.75
BA67: =A50 -> February 2025 MPR | BB67: =HLOOKUP(BB$65,$B$49:$R$50,2,FALSE) -> #N/A | BC67: =HLOOKUP(BC$65,$B$49:$R$50,2,FALSE) -> #N/A | BD67: =HLOOKUP(BD$65,$B$49:$R$50,2,FALSE) -> #N/A | BE67: =HLOOKUP(BE$65,$B$49:$R$50,2,FALSE) -> #N/A | BF67: =HLOOKUP(BF$65,$B$49:$R$50,2,FALSE) -> #N/A | BG67: =HLOOKUP(BG$65,$B$49:$R$50,2,FALSE) -> #N/A | BH67: =HLOOKUP(BH$65,$B$49:$R$50,2,FALSE) -> #N/A | BI67: =HLOOKUP(BI$65,$B$49:$R$50,2,FALSE) -> #N/A | ... BU67: =HLOOKUP(BU$65,$B$49:$R$50,2,FALSE) -> 4.0092258
BA68: =BA50 -> March 2025 | BB68: =HLOOKUP(BB$65,$BB$49:$BR$50,2,FALSE) -> #N/A | BC68: =HLOOKUP(BC$65,$BB$49:$BR$50,2,FALSE) -> #N/A | BD68: =HLOOKUP(BD$65,$BB$49:$BR$50,2,FALSE) -> #N/A | BE68: =HLOOKUP(BE$65,$BB$49:$BR$50,2,FALSE) -> #N/A | BF68: =HLOOKUP(BF$65,$BB$49:$BR$50,2,FALSE) -> #N/A | BG68: =HLOOKUP(BG$65,$BB$49:$BR$50,2,FALSE) -> #N/A | BH68: =HLOOKUP(BH$65,$BB$49:$BR$50,2,FALSE) -> #N/A | BI68: =BI66 -> 4.75 | BJ68: =HLOOKUP(BJ$65,$BB$49:$BR$50,2,FALSE) -> 3.8184357 | BK68: =HLOOKUP(BK$65,$BB$49:$BR$50,2,FALSE) -> 4.0558624 | BL68: =HLOOKUP(BL$65,$BB$49:$BR$50,2,FALSE) -> 3.8358196 | BM68: =HLOOKUP(BM$65,$BB$49:$BR$50,2,FALSE) -> 3.6923198 | BN68: =HLOOKUP(BN$65,$BB$49:$BR$50,2,FALSE) -> 3.6382333 | BO68: =HLOOKUP(BO$65,$BB$49:$BR$50,2,FALSE) -> 3.6320909 | BP68: =HLOOKUP(BP$65,$BB$49:$BR$50,2,FALSE) -> 3.6343689 | BQ68: =HLOOKUP(BQ$65,$BB$49:$BR$50,2,FALSE) -> 3.6303226 | ... BU68: =HLOOKUP(BU$65,$BB$49:$BR$50,2,FALSE) -> 3.5841959
BA69: Difference | BH69: =BH68-BH67 -> #N/A | BI69: =BI68-BI67 -> #N/A | BJ69: =BJ68-BJ67 -> -0.74610095 | BK69: =BK68-BK67 -> -0.30586105 | BL69: =BL68-BL67 -> -0.39048126 | BM69: =BM68-BM67 -> -0.46768735 | BN69: =BN68-BN67 -> -0.50992865 | BO69: =BO68-BO67 -> -0.51065564 | ... BU69: =BU68-BU67 -> -0.4250299
BA70: Next 3 years | BS70: =AVERAGE(BH69:BS69) -> #N/A

Sheet Market expectations - Gas
A1: ='Market pricing dates'!A2 -> February 2025 MPR | C1: ='Market pricing dates'!A12 -> 15 working days to 28 Jan 2025 | AZ1: ='Market pricing dates'!D2 -> March 2025 | BB1: ='Market pricing dates'!D12 -> 15 working days to 11 Mar 2025
A2: Column # | B2: =HAVERD!BU$1 -> 73 | C2: =+B2+1 -> 74 | D2: =+C2+1 -> 75 | E2: =+D2+1 -> 76 | F2: =+E2+1 -> 77 | G2: =+F2+1 -> 78 | H2: =+G2+1 -> 79 | I2: =+H2+1 -> 80 | J2: =+I2+1 -> 81 | ... AW2: =+AV2+1 -> 120 | AZ2: Column # | BA2: =HAVERD!BU$1 -> 73 | BB2: =+BA2+1 -> 74 | BC2: =+BB2+1 -> 75 | BD2: =+BC2+1 -> 76 | BE2: =+BD2+1 -> 77 | BF2: =+BE2+1 -> 78 | BG2: =+BF2+1 -> 79 | BH2: =+BG2+1 -> 80 | BI2: =+BH2+1 -> 81 | ... CV2: =+CU2+1 -> 120
A3: Months | B3: =HAVERD!BU$2 -> Gas - 1 | C3: =HAVERD!BV$2 -> Gas - 2 | D3: =HAVERD!BW$2 -> Gas - 3 | E3: =HAVERD!BX$2 -> Gas - 4 | F3: =HAVERD!BY$2 -> Gas - 5 | G3: =HAVERD!BZ$2 -> Gas - 6 | H3: =HAVERD!CA$2 -> Gas - 7 | I3: =HAVERD!CB$2 -> Gas - 8 | ... AW3: =HAVERD!DP$2 -> Gas - 48 | AZ3: Months | BA3: =HAVERD!BU$2 -> Gas - 1 | BB3: =HAVERD!BV$2 -> Gas - 2 | BC3: =HAVERD!BW$2 -> Gas - 3 | BD3: =HAVERD!BX$2 -> Gas - 4 | BE3: =HAVERD!BY$2 -> Gas - 5 | BF3: =HAVERD!BZ$2 -> Gas - 6 | BG3: =HAVERD!CA$2 -> Gas - 7 | BH3: =HAVERD!CB$2 -> Gas - 8 | ... CV3: =HAVERD!DP$2 -> Gas - 48
A4: Days | C4: 30.416667 | D4: =+C4+30.4166667 -> 60.833333 | E4: =+D4+30.4166667 -> 91.25 | F4: =+E4+30.4166667 -> 121.66667 | G4: =+F4+30.4166667 -> 152.08333 | H4: =+G4+30.4166667 -> 182.5 | I4: =+H4+30.4166667 -> 212.91667 | J4: =+I4+30.4166667 -> 243.33333 | K4: =+J4+30.4166667 -> 273.75 | ... AW4: =+AV4+30.4166667 -> 1429.5833 | AZ4: Days | BB4: 30.416667 | BC4: =+BB4+30.4166667 -> 60.833333 | BD4: =+BC4+30.4166667 -> 91.25 | BE4: =+BD4+30.4166667 -> 121.66667 | BF4: =+BE4+30.4166667 -> 152.08333 | BG4: =+BF4+30.4166667 -> 182.5 | BH4: =+BG4+30.4166667 -> 212.91667 | BI4: =+BH4+30.4166667 -> 243.33333 | BJ4: =+BI4+30.4166667 -> 273.75 | ... CV4: =+CU4+30.4166667 -> 1429.5833
A5: Dates | AZ5: Dates
A6: =A11-7 -> 45665 | B6: =A6 -> 45665 | C6: =$B6+C$4 -> 45695.417 | D6: =$B6+D$4 -> 45725.833 | E6: =$B6+E$4 -> 45756.25 | F6: =$B6+F$4 -> 45786.667 | G6: =$B6+G$4 -> 45817.083 | H6: =$B6+H$4 -> 45847.5 | I6: =$B6+I$4 -> 45877.917 | J6: =$B6+J$4 -> 45908.333 | ... AW6: =$B6+AW$4 -> 47094.583 | AZ6: =AZ11-7 -> 45707 | BA6: =AZ6 -> 45707 | BB6: =$AZ6+BB$4 -> 45737.417 | BC6: =$AZ6+BC$4 -> 45767.833 | BD6: =$AZ6+BD$4 -> 45798.25 | BE6: =$AZ6+BE$4 -> 45828.667 | BF6: =$AZ6+BF$4 -> 45859.083 | BG6: =$AZ6+BG$4 -> 45889.5 | BH6: =$AZ6+BH$4 -> 45919.917 | BI6: =$AZ6+BI$4 -> 45950.333 | ... CV6: =$AZ6+CV$4 -> 47136.583
A7: =A12-7 -> 45666 | B7: =A7 -> 45666 | C7: =$B7+C$4 -> 45696.417 | D7: =$B7+D$4 -> 45726.833 | E7: =$B7+E$4 -> 45757.25 | F7: =$B7+F$4 -> 45787.667 | G7: =$B7+G$4 -> 45818.083 | H7: =$B7+H$4 -> 45848.5 | I7: =$B7+I$4 -> 45878.917 | J7: =$B7+J$4 -> 45909.333 | ... AW7: =$B7+AW$4 -> 47095.583 | AZ7: =AZ12-7 -> 45708 | BA7: =AZ7 -> 45708 | BB7: =$AZ7+BB$4 -> 45738.417 | BC7: =$AZ7+BC$4 -> 45768.833 | BD7: =$AZ7+BD$4 -> 45799.25 | BE7: =$AZ7+BE$4 -> 45829.667 | BF7: =$AZ7+BF$4 -> 45860.083 | BG7: =$AZ7+BG$4 -> 45890.5 | BH7: =$AZ7+BH$4 -> 45920.917 | BI7: =$AZ7+BI$4 -> 45951.333 | ... CV7: =$AZ7+CV$4 -> 47137.583
A8: =A13-7 -> 45667 | B8: =A8 -> 45667 | C8: =$B8+C$4 -> 45697.417 | D8: =$B8+D$4 -> 45727.833 | E8: =$B8+E$4 -> 45758.25 | F8: =$B8+F$4 -> 45788.667 | G8: =$B8+G$4 -> 45819.083 | H8: =$B8+H$4 -> 45849.5 | I8: =$B8+I$4 -> 45879.917 | J8: =$B8+J$4 -> 45910.333 | ... AW8: =$B8+AW$4 -> 47096.583 | AZ8: =AZ13-7 -> 45709 | BA8: =AZ8 -> 45709 | BB8: =$AZ8+BB$4 -> 45739.417 | BC8: =$AZ8+BC$4 -> 45769.833 | BD8: =$AZ8+BD$4 -> 45800.25 | BE8: =$AZ8+BE$4 -> 45830.667 | BF8: =$AZ8+BF$4 -> 45861.083 | BG8: =$AZ8+BG$4 -> 45891.5 | BH8: =$AZ8+BH$4 -> 45921.917 | BI8: =$AZ8+BI$4 -> 45952.333 | ... CV8: =$AZ8+CV$4 -> 47138.583
A9: =A14-7 -> 45670 | B9: =A9 -> 45670 | C9: =$B9+C$4 -> 45700.417 | D9: =$B9+D$4 -> 45730.833 | E9: =$B9+E$4 -> 45761.25 | F9: =$B9+F$4 -> 45791.667 | G9: =$B9+G$4 -> 45822.083 | H9: =$B9+H$4 -> 45852.5 | I9: =$B9+I$4 -> 45882.917 | J9: =$B9+J$4 -> 45913.333 | ... AW9: =$B9+AW$4 -> 47099.583 | AZ9: =AZ14-7 -> 45712 | BA9: =AZ9 -> 45712 | BB9: =$AZ9+BB$4 -> 45742.417 | BC9: =$AZ9+BC$4 -> 45772.833 | BD9: =$AZ9+BD$4 -> 45803.25 | BE9: =$AZ9+BE$4 -> 45833.667 | BF9: =$AZ9+BF$4 -> 45864.083 | BG9: =$AZ9+BG$4 -> 45894.5 | BH9: =$AZ9+BH$4 -> 45924.917 | BI9: =$AZ9+BI$4 -> 45955.333 | ... CV9: =$AZ9+CV$4 -> 47141.583
A10: =A15-7 -> 45671 | B10: =A10 -> 45671 | C10: =$B10+C$4 -> 45701.417 | D10: =$B10+D$4 -> 45731.833 | E10: =$B10+E$4 -> 45762.25 | F10: =$B10+F$4 -> 45792.667 | G10: =$B10+G$4 -> 45823.083 | H10: =$B10+H$4 -> 45853.5 | I10: =$B10+I$4 -> 45883.917 | J10: =$B10+J$4 -> 45914.333 | ... AW10: =$B10+AW$4 -> 47100.583 | AZ10: =AZ15-7 -> 45713 | BA10: =AZ10 -> 45713 | BB10: =$AZ10+BB$4 -> 45743.417 | BC10: =$AZ10+BC$4 -> 45773.833 | BD10: =$AZ10+BD$4 -> 45804.25 | BE10: =$AZ10+BE$4 -> 45834.667 | BF10: =$AZ10+BF$4 -> 45865.083 | BG10: =$AZ10+BG$4 -> 45895.5 | BH10: =$AZ10+BH$4 -> 45925.917 | BI10: =$AZ10+BI$4 -> 45956.333 | ... CV10: =$AZ10+CV$4 -> 47142.583
A11: =A16-7 -> 45672 | B11: =A11 -> 45672 | C11: =$B11+C$4 -> 45702.417 | D11: =$B11+D$4 -> 45732.833 | E11: =$B11+E$4 -> 45763.25 | F11: =$B11+F$4 -> 45793.667 | G11: =$B11+G$4 -> 45824.083 | H11: =$B11+H$4 -> 45854.5 | I11: =$B11+I$4 -> 45884.917 | J11: =$B11+J$4 -> 45915.333 | ... AW11: =$B11+AW$4 -> 47101.583 | AZ11: =AZ16-7 -> 45714 | BA11: =AZ11 -> 45714 | BB11: =$AZ11+BB$4 -> 45744.417 | BC11: =$AZ11+BC$4 -> 45774.833 | BD11: =$AZ11+BD$4 -> 45805.25 | BE11: =$AZ11+BE$4 -> 45835.667 | BF11: =$AZ11+BF$4 -> 45866.083 | BG11: =$AZ11+BG$4 -> 45896.5 | BH11: =$AZ11+BH$4 -> 45926.917 | BI11: =$AZ11+BI$4 -> 45957.333 | ... CV11: =$AZ11+CV$4 -> 47143.583
A12: =A17-7 -> 45673 | B12: =A12 -> 45673 | C12: =$B12+C$4 -> 45703.417 | D12: =$B12+D$4 -> 45733.833 | E12: =$B12+E$4 -> 45764.25 | F12: =$B12+F$4 -> 45794.667 | G12: =$B12+G$4 -> 45825.083 | H12: =$B12+H$4 -> 45855.5 | I12: =$B12+I$4 -> 45885.917 | J12: =$B12+J$4 -> 45916.333 | ... AW12: =$B12+AW$4 -> 47102.583 | AZ12: =AZ17-7 -> 45715 | BA12: =AZ12 -> 45715 | BB12: =$AZ12+BB$4 -> 45745.417 | BC12: =$AZ12+BC$4 -> 45775.833 | BD12: =$AZ12+BD$4 -> 45806.25 | BE12: =$AZ12+BE$4 -> 45836.667 | BF12: =$AZ12+BF$4 -> 45867.083 | BG12: =$AZ12+BG$4 -> 45897.5 | BH12: =$AZ12+BH$4 -> 45927.917 | BI12: =$AZ12+BI$4 -> 45958.333 | ... CV12: =$AZ12+CV$4 -> 47144.583
A13: =A18-7 -> 45674 | B13: =A13 -> 45674 | C13: =$B13+C$4 -> 45704.417 | D13: =$B13+D$4 -> 45734.833 | E13: =$B13+E$4 -> 45765.25 | F13: =$B13+F$4 -> 45795.667 | G13: =$B13+G$4 -> 45826.083 | H13: =$B13+H$4 -> 45856.5 | I13: =$B13+I$4 -> 45886.917 | J13: =$B13+J$4 -> 45917.333 | ... AW13: =$B13+AW$4 -> 47103.583 | AZ13: =AZ18-7 -> 45716 | BA13: =AZ13 -> 45716 | BB13: =$AZ13+BB$4 -> 45746.417 | BC13: =$AZ13+BC$4 -> 45776.833 | BD13: =$AZ13+BD$4 -> 45807.25 | BE13: =$AZ13+BE$4 -> 45837.667 | BF13: =$AZ13+BF$4 -> 45868.083 | BG13: =$AZ13+BG$4 -> 45898.5 | BH13: =$AZ13+BH$4 -> 45928.917 | BI13: =$AZ13+BI$4 -> 45959.333 | ... CV13: =$AZ13+CV$4 -> 47145.583
A14: =A19-7 -> 45677 | B14: =A14 -> 45677 | C14: =$B14+C$4 -> 45707.417 | D14: =$B14+D$4 -> 45737.833 | E14: =$B14+E$4 -> 45768.25 | F14: =$B14+F$4 -> 45798.667 | G14: =$B14+G$4 -> 45829.083 | H14: =$B14+H$4 -> 45859.5 | I14: =$B14+I$4 -> 45889.917 | J14: =$B14+J$4 -> 45920.333 | ... AW14: =$B14+AW$4 -> 47106.583 | AZ14: =AZ19-7 -> 45719 | BA14: =AZ14 -> 45719 | BB14: =$AZ14+BB$4 -> 45749.417 | BC14: =$AZ14+BC$4 -> 45779.833 | BD14: =$AZ14+BD$4 -> 45810.25 | BE14: =$AZ14+BE$4 -> 45840.667 | BF14: =$AZ14+BF$4 -> 45871.083 | BG14: =$AZ14+BG$4 -> 45901.5 | BH14: =$AZ14+BH$4 -> 45931.917 | BI14: =$AZ14+BI$4 -> 45962.333 | ... CV14: =$AZ14+CV$4 -> 47148.583
A15: =A20-7 -> 45678 | B15: =A15 -> 45678 | C15: =$B15+C$4 -> 45708.417 | D15: =$B15+D$4 -> 45738.833 | E15: =$B15+E$4 -> 45769.25 | F15: =$B15+F$4 -> 45799.667 | G15: =$B15+G$4 -> 45830.083 | H15: =$B15+H$4 -> 45860.5 | I15: =$B15+I$4 -> 45890.917 | J15: =$B15+J$4 -> 45921.333 | ... AW15: =$B15+AW$4 -> 47107.583 | AZ15: =AZ20-7 -> 45720 | BA15: =AZ15 -> 45720 | BB15: =$AZ15+BB$4 -> 45750.417 | BC15: =$AZ15+BC$4 -> 45780.833 | BD15: =$AZ15+BD$4 -> 45811.25 | BE15: =$AZ15+BE$4 -> 45841.667 | BF15: =$AZ15+BF$4 -> 45872.083 | BG15: =$AZ15+BG$4 -> 45902.5 | BH15: =$AZ15+BH$4 -> 45932.917 | BI15: =$AZ15+BI$4 -> 45963.333 | ... CV15: =$AZ15+CV$4 -> 47149.583
A16: ='Market pricing dates'!B5 -> 45679 | B16: =A16 -> 45679 | C16: =$B16+C$4 -> 45709.417 | D16: =$B16+D$4 -> 45739.833 | E16: =$B16+E$4 -> 45770.25 | F16: =$B16+F$4 -> 45800.667 | G16: =$B16+G$4 -> 45831.083 | H16: =$B16+H$4 -> 45861.5 | I16: =$B16+I$4 -> 45891.917 | J16: =$B16+J$4 -> 45922.333 | ... AW16: =$B16+AW$4 -> 47108.583 | AZ16: ='Market pricing dates'!E5 -> 45721 | BA16: =AZ16 -> 45721 | BB16: =$AZ16+BB$4 -> 45751.417 | BC16: =$AZ16+BC$4 -> 45781.833 | BD16: =$AZ16+BD$4 -> 45812.25 | BE16: =$AZ16+BE$4 -> 45842.667 | BF16: =$AZ16+BF$4 -> 45873.083 | BG16: =$AZ16+BG$4 -> 45903.5 | BH16: =$AZ16+BH$4 -> 45933.917 | BI16: =$AZ16+BI$4 -> 45964.333 | ... CV16: =$AZ16+CV$4 -> 47150.583
A17: ='Market pricing dates'!B6 -> 45680 | B17: =A17 -> 45680 | C17: =$B17+C$4 -> 45710.417 | D17: =$B17+D$4 -> 45740.833 | E17: =$B17+E$4 -> 45771.25 | F17: =$B17+F$4 -> 45801.667 | G17: =$B17+G$4 -> 45832.083 | H17: =$B17+H$4 -> 45862.5 | I17: =$B17+I$4 -> 45892.917 | J17: =$B17+J$4 -> 45923.333 | ... AW17: =$B17+AW$4 -> 47109.583 | AZ17: ='Market pricing dates'!E6 -> 45722 | BA17: =AZ17 -> 45722 | BB17: =$AZ17+BB$4 -> 45752.417 | BC17: =$AZ17+BC$4 -> 45782.833 | BD17: =$AZ17+BD$4 -> 45813.25 | BE17: =$AZ17+BE$4 -> 45843.667 | BF17: =$AZ17+BF$4 -> 45874.083 | BG17: =$AZ17+BG$4 -> 45904.5 | BH17: =$AZ17+BH$4 -> 45934.917 | BI17: =$AZ17+BI$4 -> 45965.333 | ... CV17: =$AZ17+CV$4 -> 47151.583
A18: ='Market pricing dates'!B7 -> 45681 | B18: =A18 -> 45681 | C18: =$B18+C$4 -> 45711.417 | D18: =$B18+D$4 -> 45741.833 | E18: =$B18+E$4 -> 45772.25 | F18: =$B18+F$4 -> 45802.667 | G18: =$B18+G$4 -> 45833.083 | H18: =$B18+H$4 -> 45863.5 | I18: =$B18+I$4 -> 45893.917 | J18: =$B18+J$4 -> 45924.333 | ... AW18: =$B18+AW$4 -> 47110.583 | AZ18: ='Market pricing dates'!E7 -> 45723 | BA18: =AZ18 -> 45723 | BB18: =$AZ18+BB$4 -> 45753.417 | BC18: =$AZ18+BC$4 -> 45783.833 | BD18: =$AZ18+BD$4 -> 45814.25 | BE18: =$AZ18+BE$4 -> 45844.667 | BF18: =$AZ18+BF$4 -> 45875.083 | BG18: =$AZ18+BG$4 -> 45905.5 | BH18: =$AZ18+BH$4 -> 45935.917 | BI18: =$AZ18+BI$4 -> 45966.333 | ... CV18: =$AZ18+CV$4 -> 47152.583
A19: ='Market pricing dates'!B8 -> 45684 | B19: =A19 -> 45684 | C19: =$B19+C$4 -> 45714.417 | D19: =$B19+D$4 -> 45744.833 | E19: =$B19+E$4 -> 45775.25 | F19: =$B19+F$4 -> 45805.667 | G19: =$B19+G$4 -> 45836.083 | H19: =$B19+H$4 -> 45866.5 | I19: =$B19+I$4 -> 45896.917 | J19: =$B19+J$4 -> 45927.333 | ... AW19: =$B19+AW$4 -> 47113.583 | AZ19: ='Market pricing dates'!E8 -> 45726 | BA19: =AZ19 -> 45726 | BB19: =$AZ19+BB$4 -> 45756.417 | BC19: =$AZ19+BC$4 -> 45786.833 | BD19: =$AZ19+BD$4 -> 45817.25 | BE19: =$AZ19+BE$4 -> 45847.667 | BF19: =$AZ19+BF$4 -> 45878.083 | BG19: =$AZ19+BG$4 -> 45908.5 | BH19: =$AZ19+BH$4 -> 45938.917 | BI19: =$AZ19+BI$4 -> 45969.333 | ... CV19: =$AZ19+CV$4 -> 47155.583
A20: ='Market pricing dates'!B9 -> 45685 | B20: =A20 -> 45685 | C20: =$B20+C$4 -> 45715.417 | D20: =$B20+D$4 -> 45745.833 | E20: =$B20+E$4 -> 45776.25 | F20: =$B20+F$4 -> 45806.667 | G20: =$B20+G$4 -> 45837.083 | H20: =$B20+H$4 -> 45867.5 | I20: =$B20+I$4 -> 45897.917 | J20: =$B20+J$4 -> 45928.333 | ... AW20: =$B20+AW$4 -> 47114.583 | AZ20: ='Market pricing dates'!E9 -> 45727 | BA20: =AZ20 -> 45727 | BB20: =$AZ20+BB$4 -> 45757.417 | BC20: =$AZ20+BC$4 -> 45787.833 | BD20: =$AZ20+BD$4 -> 45818.25 | BE20: =$AZ20+BE$4 -> 45848.667 | BF20: =$AZ20+BF$4 -> 45879.083 | BG20: =$AZ20+BG$4 -> 45909.5 | BH20: =$AZ20+BH$4 -> 45939.917 | BI20: =$AZ20+BI$4 -> 45970.333 | ... CV20: =$AZ20+CV$4 -> 47156.583
A22: Gas futures | AZ22: Gas futures
A23: =A6 -> 45665 | B23: =VLOOKUP($A23,HAVERD!$A:$DP,B$2,FALSE) -> 114.03 | C23: =VLOOKUP($A23,HAVERD!$A:$DP,C$2,FALSE) -> 112.54 | D23: =VLOOKUP($A23,HAVERD!$A:$DP,D$2,FALSE) -> 112 | E23: =VLOOKUP($A23,HAVERD!$A:$DP,E$2,FALSE) -> 111.38 | F23: =VLOOKUP($A23,HAVERD!$A:$DP,F$2,FALSE) -> 110.6 | G23: =VLOOKUP($A23,HAVERD!$A:$DP,G$2,FALSE) -> 109.45 | H23: =VLOOKUP($A23,HAVERD!$A:$DP,H$2,FALSE) -> 109.71 | I23: =VLOOKUP($A23,HAVERD!$A:$DP,I$2,FALSE) -> 111.22 | ... AW23: =VLOOKUP($A23,HAVERD!$A:$DP,AW$2,FALSE) -> 77.47 | AZ23: =AZ6 -> 45707 | BA23: =_xlfn.IFNA(VLOOKUP($AZ23,HAVERD!$A:$DP,BA$2,FALSE),"") -> 114.98 | BB23: =_xlfn.IFNA(VLOOKUP($AZ23,HAVERD!$A:$DP,BB$2,FALSE),"") -> 115.32 | BC23: =_xlfn.IFNA(VLOOKUP($AZ23,HAVERD!$A:$DP,BC$2,FALSE),"") -> 115.19 | BD23: =_xlfn.IFNA(VLOOKUP($AZ23,HAVERD!$A:$DP,BD$2,FALSE),"") -> 115.61 | BE23: =_xlfn.IFNA(VLOOKUP($AZ23,HAVERD!$A:$DP,BE$2,FALSE),"") -> 114.05 | BF23: =_xlfn.IFNA(VLOOKUP($AZ23,HAVERD!$A:$DP,BF$2,FALSE),"") -> 114.4 | BG23: =_xlfn.IFNA(VLOOKUP($AZ23,HAVERD!$A:$DP,BG$2,FALSE),"") -> 116.29 | BH23: =_xlfn.IFNA(VLOOKUP($AZ23,HAVERD!$A:$DP,BH$2,FALSE),"") -> 114.14 | ... CV23: =_xlfn.IFNA(VLOOKUP($AZ23,HAVERD!$A:$DP,CV$2,FALSE),"") -> 72.31
A24: =A7 -> 45666 | B24: =VLOOKUP($A24,HAVERD!$A:$DP,B$2,FALSE) -> 112.93 | C24: =VLOOKUP($A24,HAVERD!$A:$DP,C$2,FALSE) -> 111.51 | D24: =VLOOKUP($A24,HAVERD!$A:$DP,D$2,FALSE) -> 111 | E24: =VLOOKUP($A24,HAVERD!$A:$DP,E$2,FALSE) -> 110.75 | F24: =VLOOKUP($A24,HAVERD!$A:$DP,F$2,FALSE) -> 110.18 | G24: =VLOOKUP($A24,HAVERD!$A:$DP,G$2,FALSE) -> 108.78 | H24: =VLOOKUP($A24,HAVERD!$A:$DP,H$2,FALSE) -> 109.09 | I24: =VLOOKUP($A24,HAVERD!$A:$DP,I$2,FALSE) -> 110.57 | ... AW24: =VLOOKUP($A24,HAVERD!$A:$DP,AW$2,FALSE) -> 77.38 | AZ24: =AZ7 -> 45708 | BA24: =_xlfn.IFNA(VLOOKUP($AZ24,HAVERD!$A:$DP,BA$2,FALSE),"") -> 113.55 | BB24: =_xlfn.IFNA(VLOOKUP($AZ24,HAVERD!$A:$DP,BB$2,FALSE),"") -> 113.65 | BC24: =_xlfn.IFNA(VLOOKUP($AZ24,HAVERD!$A:$DP,BC$2,FALSE),"") -> 113.54 | BD24: =_xlfn.IFNA(VLOOKUP($AZ24,HAVERD!$A:$DP,BD$2,FALSE),"") -> 113.9 | BE24: =_xlfn.IFNA(VLOOKUP($AZ24,HAVERD!$A:$DP,BE$2,FALSE),"") -> 112.66 | BF24: =_xlfn.IFNA(VLOOKUP($AZ24,HAVERD!$A:$DP,BF$2,FALSE),"") -> 113.2 | BG24: =_xlfn.IFNA(VLOOKUP($AZ24,HAVERD!$A:$DP,BG$2,FALSE),"") -> 114.9 | BH24: =_xlfn.IFNA(VLOOKUP($AZ24,HAVERD!$A:$DP,BH$2,FALSE),"") -> 112.76 | ... CV24: =_xlfn.IFNA(VLOOKUP($AZ24,HAVERD!$A:$DP,CV$2,FALSE),"") -> 72.95
A25: =A8 -> 45667 | B25: =VLOOKUP($A25,HAVERD!$A:$DP,B$2,FALSE) -> 113.07 | C25: =VLOOKUP($A25,HAVERD!$A:$DP,C$2,FALSE) -> 111.79 | D25: =VLOOKUP($A25,HAVERD!$A:$DP,D$2,FALSE) -> 111.44 | E25: =VLOOKUP($A25,HAVERD!$A:$DP,E$2,FALSE) -> 111.34 | F25: =VLOOKUP($A25,HAVERD!$A:$DP,F$2,FALSE) -> 111.03 | G25: =VLOOKUP($A25,HAVERD!$A:$DP,G$2,FALSE) -> 109.52 | H25: =VLOOKUP($A25,HAVERD!$A:$DP,H$2,FALSE) -> 109.92 | I25: =VLOOKUP($A25,HAVERD!$A:$DP,I$2,FALSE) -> 111.28 | ... AW25: =VLOOKUP($A25,HAVERD!$A:$DP,AW$2,FALSE) -> 77.83 | AZ25: =AZ8 -> 45709 | BA25: =_xlfn.IFNA(VLOOKUP($AZ25,HAVERD!$A:$DP,BA$2,FALSE),"") -> 112.33 | BB25: =_xlfn.IFNA(VLOOKUP($AZ25,HAVERD!$A:$DP,BB$2,FALSE),"") -> 112.54 | BC25: =_xlfn.IFNA(VLOOKUP($AZ25,HAVERD!$A:$DP,BC$2,FALSE),"") -> 112.6 | BD25: =_xlfn.IFNA(VLOOKUP($AZ25,HAVERD!$A:$DP,BD$2,FALSE),"") -> 113.11 | BE25: =_xlfn.IFNA(VLOOKUP($AZ25,HAVERD!$A:$DP,BE$2,FALSE),"") -> 111.83 | BF25: =_xlfn.IFNA(VLOOKUP($AZ25,HAVERD!$A:$DP,BF$2,FALSE),"") -> 112.33 | BG25: =_xlfn.IFNA(VLOOKUP($AZ25,HAVERD!$A:$DP,BG$2,FALSE),"") -> 114.11 | BH25: =_xlfn.IFNA(VLOOKUP($AZ25,HAVERD!$A:$DP,BH$2,FALSE),"") -> 112.64 | ... CV25: =_xlfn.IFNA(VLOOKUP($AZ25,HAVERD!$A:$DP,CV$2,FALSE),"") -> 73.29
A26: =A9 -> 45670 | B26: =VLOOKUP($A26,HAVERD!$A:$DP,B$2,FALSE) -> 121.5 | C26: =VLOOKUP($A26,HAVERD!$A:$DP,C$2,FALSE) -> 119.7 | D26: =VLOOKUP($A26,HAVERD!$A:$DP,D$2,FALSE) -> 119.48 | E26: =VLOOKUP($A26,HAVERD!$A:$DP,E$2,FALSE) -> 119.2 | F26: =VLOOKUP($A26,HAVERD!$A:$DP,F$2,FALSE) -> 118.97 | G26: =VLOOKUP($A26,HAVERD!$A:$DP,G$2,FALSE) -> 117.3 | H26: =VLOOKUP($A26,HAVERD!$A:$DP,H$2,FALSE) -> 117.7 | I26: =VLOOKUP($A26,HAVERD!$A:$DP,I$2,FALSE) -> 119.06 | ... AW26: =VLOOKUP($A26,HAVERD!$A:$DP,AW$2,FALSE) -> 79.09 | AZ26: =AZ9 -> 45712 | BA26: =_xlfn.IFNA(VLOOKUP($AZ26,HAVERD!$A:$DP,BA$2,FALSE),"") -> 112.83 | BB26: =_xlfn.IFNA(VLOOKUP($AZ26,HAVERD!$A:$DP,BB$2,FALSE),"") -> 112.74 | BC26: =_xlfn.IFNA(VLOOKUP($AZ26,HAVERD!$A:$DP,BC$2,FALSE),"") -> 112.76 | BD26: =_xlfn.IFNA(VLOOKUP($AZ26,HAVERD!$A:$DP,BD$2,FALSE),"") -> 113.15 | BE26: =_xlfn.IFNA(VLOOKUP($AZ26,HAVERD!$A:$DP,BE$2,FALSE),"") -> 112.07 | BF26: =_xlfn.IFNA(VLOOKUP($AZ26,HAVERD!$A:$DP,BF$2,FALSE),"") -> 112.67 | BG26: =_xlfn.IFNA(VLOOKUP($AZ26,HAVERD!$A:$DP,BG$2,FALSE),"") -> 114.25 | BH26: =_xlfn.IFNA(VLOOKUP($AZ26,HAVERD!$A:$DP,BH$2,FALSE),"") -> 112.19 | ... CV26: =_xlfn.IFNA(VLOOKUP($AZ26,HAVERD!$A:$DP,CV$2,FALSE),"") -> 74.35
A27: =A10 -> 45671 | B27: =VLOOKUP($A27,HAVERD!$A:$DP,B$2,FALSE) -> 118.62 | C27: =VLOOKUP($A27,HAVERD!$A:$DP,C$2,FALSE) -> 117.01 | D27: =VLOOKUP($A27,HAVERD!$A:$DP,D$2,FALSE) -> 116.69 | E27: =VLOOKUP($A27,HAVERD!$A:$DP,E$2,FALSE) -> 116.44 | F27: =VLOOKUP($A27,HAVERD!$A:$DP,F$2,FALSE) -> 115.98 | G27: =VLOOKUP($A27,HAVERD!$A:$DP,G$2,FALSE) -> 114.51 | H27: =VLOOKUP($A27,HAVERD!$A:$DP,H$2,FALSE) -> 114.95 | I27: =VLOOKUP($A27,HAVERD!$A:$DP,I$2,FALSE) -> 116.35 | ... AW27: =VLOOKUP($A27,HAVERD!$A:$DP,AW$2,FALSE) -> 78.65 | AZ27: =AZ10 -> 45713 | BA27: =_xlfn.IFNA(VLOOKUP($AZ27,HAVERD!$A:$DP,BA$2,FALSE),"") -> 105.98 | BB27: =_xlfn.IFNA(VLOOKUP($AZ27,HAVERD!$A:$DP,BB$2,FALSE),"") -> 105.86 | BC27: =_xlfn.IFNA(VLOOKUP($AZ27,HAVERD!$A:$DP,BC$2,FALSE),"") -> 105.95 | BD27: =_xlfn.IFNA(VLOOKUP($AZ27,HAVERD!$A:$DP,BD$2,FALSE),"") -> 106.33 | BE27: =_xlfn.IFNA(VLOOKUP($AZ27,HAVERD!$A:$DP,BE$2,FALSE),"") -> 105.15 | BF27: =_xlfn.IFNA(VLOOKUP($AZ27,HAVERD!$A:$DP,BF$2,FALSE),"") -> 105.85 | BG27: =_xlfn.IFNA(VLOOKUP($AZ27,HAVERD!$A:$DP,BG$2,FALSE),"") -> 107.69 | BH27: =_xlfn.IFNA(VLOOKUP($AZ27,HAVERD!$A:$DP,BH$2,FALSE),"") -> 106.49 | ... CV27: =_xlfn.IFNA(VLOOKUP($AZ27,HAVERD!$A:$DP,CV$2,FALSE),"") -> 73.84
A28: =A11 -> 45672 | B28: =VLOOKUP($A28,HAVERD!$A:$DP,B$2,FALSE) -> 118.45 | C28: =VLOOKUP($A28,HAVERD!$A:$DP,C$2,FALSE) -> 116.93 | D28: =VLOOKUP($A28,HAVERD!$A:$DP,D$2,FALSE) -> 116.39 | E28: =VLOOKUP($A28,HAVERD!$A:$DP,E$2,FALSE) -> 116.05 | F28: =VLOOKUP($A28,HAVERD!$A:$DP,F$2,FALSE) -> 115.64 | G28: =VLOOKUP($A28,HAVERD!$A:$DP,G$2,FALSE) -> 114.26 | H28: =VLOOKUP($A28,HAVERD!$A:$DP,H$2,FALSE) -> 114.74 | I28: =VLOOKUP($A28,HAVERD!$A:$DP,I$2,FALSE) -> 116.12 | ... AW28: =VLOOKUP($A28,HAVERD!$A:$DP,AW$2,FALSE) -> 78.62 | AZ28: =AZ11 -> 45714 | BA28: =_xlfn.IFNA(VLOOKUP($AZ28,HAVERD!$A:$DP,BA$2,FALSE),"") -> 98.78 | BB28: =_xlfn.IFNA(VLOOKUP($AZ28,HAVERD!$A:$DP,BB$2,FALSE),"") -> 98.81 | BC28: =_xlfn.IFNA(VLOOKUP($AZ28,HAVERD!$A:$DP,BC$2,FALSE),"") -> 98.93 | BD28: =_xlfn.IFNA(VLOOKUP($AZ28,HAVERD!$A:$DP,BD$2,FALSE),"") -> 99.35 | BE28: =_xlfn.IFNA(VLOOKUP($AZ28,HAVERD!$A:$DP,BE$2,FALSE),"") -> 98.26 | BF28: =_xlfn.IFNA(VLOOKUP($AZ28,HAVERD!$A:$DP,BF$2,FALSE),"") -> 98.78 | BG28: =_xlfn.IFNA(VLOOKUP($AZ28,HAVERD!$A:$DP,BG$2,FALSE),"") -> 100.77 | BH28: =_xlfn.IFNA(VLOOKUP($AZ28,HAVERD!$A:$DP,BH$2,FALSE),"") -> 100.67 | ... CV28: =_xlfn.IFNA(VLOOKUP($AZ28,HAVERD!$A:$DP,CV$2,FALSE),"") -> 73.59
A29: =A12 -> 45673 | B29: =VLOOKUP($A29,HAVERD!$A:$DP,B$2,FALSE) -> 116.39 | C29: =VLOOKUP($A29,HAVERD!$A:$DP,C$2,FALSE) -> 115.25 | D29: =VLOOKUP($A29,HAVERD!$A:$DP,D$2,FALSE) -> 114.8 | E29: =VLOOKUP($A29,HAVERD!$A:$DP,E$2,FALSE) -> 114.45 | F29: =VLOOKUP($A29,HAVERD!$A:$DP,F$2,FALSE) -> 114.2 | G29: =VLOOKUP($A29,HAVERD!$A:$DP,G$2,FALSE) -> 112.9 | H29: =VLOOKUP($A29,HAVERD!$A:$DP,H$2,FALSE) -> 113.46 | I29: =VLOOKUP($A29,HAVERD!$A:$DP,I$2,FALSE) -> 115 | ... AW29: =VLOOKUP($A29,HAVERD!$A:$DP,AW$2,FALSE) -> 78.19 | AZ29: =AZ12 -> 45715 | BA29: =_xlfn.IFNA(VLOOKUP($AZ29,HAVERD!$A:$DP,BA$2,FALSE),"") -> 106.79 | BB29: =_xlfn.IFNA(VLOOKUP($AZ29,HAVERD!$A:$DP,BB$2,FALSE),"") -> 107.12 | BC29: =_xlfn.IFNA(VLOOKUP($AZ29,HAVERD!$A:$DP,BC$2,FALSE),"") -> 107.3 | BD29: =_xlfn.IFNA(VLOOKUP($AZ29,HAVERD!$A:$DP,BD$2,FALSE),"") -> 107.6 | BE29: =_xlfn.IFNA(VLOOKUP($AZ29,HAVERD!$A:$DP,BE$2,FALSE),"") -> 106.56 | BF29: =_xlfn.IFNA(VLOOKUP($AZ29,HAVERD!$A:$DP,BF$2,FALSE),"") -> 107 | BG29: =_xlfn.IFNA(VLOOKUP($AZ29,HAVERD!$A:$DP,BG$2,FALSE),"") -> 108.96 | BH29: =_xlfn.IFNA(VLOOKUP($AZ29,HAVERD!$A:$DP,BH$2,FALSE),"") -> 108.02 | ... CV29: =_xlfn.IFNA(VLOOKUP($AZ29,HAVERD!$A:$DP,CV$2,FALSE),"") -> 75.01
A30: =A13 -> 45674 | B30: =VLOOKUP($A30,HAVERD!$A:$DP,B$2,FALSE) -> 118.31 | C30: =VLOOKUP($A30,HAVERD!$A:$DP,C$2,FALSE) -> 117.13 | D30: =VLOOKUP($A30,HAVERD!$A:$DP,D$2,FALSE) -> 116.59 | E30: =VLOOKUP($A30,HAVERD!$A:$DP,E$2,FALSE) -> 116.3 | F30: =VLOOKUP($A30,HAVERD!$A:$DP,F$2,FALSE) -> 115.99 | G30: =VLOOKUP($A30,HAVERD!$A:$DP,G$2,FALSE) -> 114.74 | H30: =VLOOKUP($A30,HAVERD!$A:$DP,H$2,FALSE) -> 115.44 | I30: =VLOOKUP($A30,HAVERD!$A:$DP,I$2,FALSE) -> 116.81 | ... AW30: =VLOOKUP($A30,HAVERD!$A:$DP,AW$2,FALSE) -> 78.92 | AZ30: =AZ13 -> 45716 | BA30: =_xlfn.IFNA(VLOOKUP($AZ30,HAVERD!$A:$DP,BA$2,FALSE),"") -> 104.83 | BB30: =_xlfn.IFNA(VLOOKUP($AZ30,HAVERD!$A:$DP,BB$2,FALSE),"") -> 104.86 | BC30: =_xlfn.IFNA(VLOOKUP($AZ30,HAVERD!$A:$DP,BC$2,FALSE),"") -> 105.32 | BD30: =_xlfn.IFNA(VLOOKUP($AZ30,HAVERD!$A:$DP,BD$2,FALSE),"") -> 104.32 | BE30: =_xlfn.IFNA(VLOOKUP($AZ30,HAVERD!$A:$DP,BE$2,FALSE),"") -> 104.81 | BF30: =_xlfn.IFNA(VLOOKUP($AZ30,HAVERD!$A:$DP,BF$2,FALSE),"") -> 106.82 | BG30: =_xlfn.IFNA(VLOOKUP($AZ30,HAVERD!$A:$DP,BG$2,FALSE),"") -> 106.42 | BH30: =_xlfn.IFNA(VLOOKUP($AZ30,HAVERD!$A:$DP,BH$2,FALSE),"") -> 109.96 | ... CV30: =_xlfn.IFNA(VLOOKUP($AZ30,HAVERD!$A:$DP,CV$2,FALSE),"") -> 74.27
A31: =A14 -> 45677 | B31: =VLOOKUP($A31,HAVERD!$A:$DP,B$2,FALSE) -> 121.35 | C31: =VLOOKUP($A31,HAVERD!$A:$DP,C$2,FALSE) -> 119.75 | D31: =VLOOKUP($A31,HAVERD!$A:$DP,D$2,FALSE) -> 118.85 | E31: =VLOOKUP($A31,HAVERD!$A:$DP,E$2,FALSE) -> 118.35 | F31: =VLOOKUP($A31,HAVERD!$A:$DP,F$2,FALSE) -> 118 | G31: =VLOOKUP($A31,HAVERD!$A:$DP,G$2,FALSE) -> 116.68 | H31: =VLOOKUP($A31,HAVERD!$A:$DP,H$2,FALSE) -> 117.38 | I31: =VLOOKUP($A31,HAVERD!$A:$DP,I$2,FALSE) -> 118.79 | ... AW31: =VLOOKUP($A31,HAVERD!$A:$DP,AW$2,FALSE) -> 79.16 | AZ31: =AZ14 -> 45719 | BA31: =_xlfn.IFNA(VLOOKUP($AZ31,HAVERD!$A:$DP,BA$2,FALSE),"") -> 107.16 | BB31: =_xlfn.IFNA(VLOOKUP($AZ31,HAVERD!$A:$DP,BB$2,FALSE),"") -> 106.95 | BC31: =_xlfn.IFNA(VLOOKUP($AZ31,HAVERD!$A:$DP,BC$2,FALSE),"") -> 107.4 | BD31: =_xlfn.IFNA(VLOOKUP($AZ31,HAVERD!$A:$DP,BD$2,FALSE),"") -> 106.51 | BE31: =_xlfn.IFNA(VLOOKUP($AZ31,HAVERD!$A:$DP,BE$2,FALSE),"") -> 106.97 | BF31: =_xlfn.IFNA(VLOOKUP($AZ31,HAVERD!$A:$DP,BF$2,FALSE),"") -> 108.92 | BG31: =_xlfn.IFNA(VLOOKUP($AZ31,HAVERD!$A:$DP,BG$2,FALSE),"") -> 107.86 | BH31: =_xlfn.IFNA(VLOOKUP($AZ31,HAVERD!$A:$DP,BH$2,FALSE),"") -> 111.68 | ... CV31: =_xlfn.IFNA(VLOOKUP($AZ31,HAVERD!$A:$DP,CV$2,FALSE),"") -> 73.96
A32: =A15 -> 45678 | B32: =VLOOKUP($A32,HAVERD!$A:$DP,B$2,FALSE) -> 126.61 | C32: =VLOOKUP($A32,HAVERD!$A:$DP,C$2,FALSE) -> 125.1 | D32: =VLOOKUP($A32,HAVERD!$A:$DP,D$2,FALSE) -> 124.1 | E32: =VLOOKUP($A32,HAVERD!$A:$DP,E$2,FALSE) -> 123.45 | F32: =VLOOKUP($A32,HAVERD!$A:$DP,F$2,FALSE) -> 122.88 | G32: =VLOOKUP($A32,HAVERD!$A:$DP,G$2,FALSE) -> 121.45 | H32: =VLOOKUP($A32,HAVERD!$A:$DP,H$2,FALSE) -> 121.75 | I32: =VLOOKUP($A32,HAVERD!$A:$DP,I$2,FALSE) -> 123.13 | ... AW32: =VLOOKUP($A32,HAVERD!$A:$DP,AW$2,FALSE) -> 79.32 | AZ32: =AZ15 -> 45720 | BA32: =_xlfn.IFNA(VLOOKUP($AZ32,HAVERD!$A:$DP,BA$2,FALSE),"") -> 103.57 | BB32: =_xlfn.IFNA(VLOOKUP($AZ32,HAVERD!$A:$DP,BB$2,FALSE),"") -> 103.3 | BC32: =_xlfn.IFNA(VLOOKUP($AZ32,HAVERD!$A:$DP,BC$2,FALSE),"") -> 103.7 | BD32: =_xlfn.IFNA(VLOOKUP($AZ32,HAVERD!$A:$DP,BD$2,FALSE),"") -> 102.85 | BE32: =_xlfn.IFNA(VLOOKUP($AZ32,HAVERD!$A:$DP,BE$2,FALSE),"") -> 103.36 | BF32: =_xlfn.IFNA(VLOOKUP($AZ32,HAVERD!$A:$DP,BF$2,FALSE),"") -> 105.49 | BG32: =_xlfn.IFNA(VLOOKUP($AZ32,HAVERD!$A:$DP,BG$2,FALSE),"") -> 104.51 | BH32: =_xlfn.IFNA(VLOOKUP($AZ32,HAVERD!$A:$DP,BH$2,FALSE),"") -> 108.01 | ... CV32: =_xlfn.IFNA(VLOOKUP($AZ32,HAVERD!$A:$DP,CV$2,FALSE),"") -> 71.6
A33: =A16 -> 45679 | B33: =VLOOKUP($A33,HAVERD!$A:$DP,B$2,FALSE) -> 122.87 | C33: =VLOOKUP($A33,HAVERD!$A:$DP,C$2,FALSE) -> 121.79 | D33: =VLOOKUP($A33,HAVERD!$A:$DP,D$2,FALSE) -> 120.85 | E33: =VLOOKUP($A33,HAVERD!$A:$DP,E$2,FALSE) -> 120.4 | F33: =VLOOKUP($A33,HAVERD!$A:$DP,F$2,FALSE) -> 119.99 | G33: =VLOOKUP($A33,HAVERD!$A:$DP,G$2,FALSE) -> 118.35 | H33: =VLOOKUP($A33,HAVERD!$A:$DP,H$2,FALSE) -> 118.66 | I33: =VLOOKUP($A33,HAVERD!$A:$DP,I$2,FALSE) -> 119.96 | ... AW33: =VLOOKUP($A33,HAVERD!$A:$DP,AW$2,FALSE) -> 77.55 | AZ33: =AZ16 -> 45721 | BA33: =_xlfn.IFNA(VLOOKUP($AZ33,HAVERD!$A:$DP,BA$2,FALSE),"") -> 100.1 | BB33: =_xlfn.IFNA(VLOOKUP($AZ33,HAVERD!$A:$DP,BB$2,FALSE),"") -> 99.55 | BC33: =_xlfn.IFNA(VLOOKUP($AZ33,HAVERD!$A:$DP,BC$2,FALSE),"") -> 99.97 | BD33: =_xlfn.IFNA(VLOOKUP($AZ33,HAVERD!$A:$DP,BD$2,FALSE),"") -> 99.2 | BE33: =_xlfn.IFNA(VLOOKUP($AZ33,HAVERD!$A:$DP,BE$2,FALSE),"") -> 99.7 | BF33: =_xlfn.IFNA(VLOOKUP($AZ33,HAVERD!$A:$DP,BF$2,FALSE),"") -> 101.9 | BG33: =_xlfn.IFNA(VLOOKUP($AZ33,HAVERD!$A:$DP,BG$2,FALSE),"") -> 100.88 | BH33: =_xlfn.IFNA(VLOOKUP($AZ33,HAVERD!$A:$DP,BH$2,FALSE),"") -> 104.12 | ... CV33: =_xlfn.IFNA(VLOOKUP($AZ33,HAVERD!$A:$DP,CV$2,FALSE),"") -> 71.83
A34: =A17 -> 45680 | B34: =VLOOKUP($A34,HAVERD!$A:$DP,B$2,FALSE) -> 123.5 | C34: =VLOOKUP($A34,HAVERD!$A:$DP,C$2,FALSE) -> 122.24 | D34: =VLOOKUP($A34,HAVERD!$A:$DP,D$2,FALSE) -> 121.52 | E34: =VLOOKUP($A34,HAVERD!$A:$DP,E$2,FALSE) -> 121.4 | F34: =VLOOKUP($A34,HAVERD!$A:$DP,F$2,FALSE) -> 120.97 | G34: =VLOOKUP($A34,HAVERD!$A:$DP,G$2,FALSE) -> 119.9 | H34: =VLOOKUP($A34,HAVERD!$A:$DP,H$2,FALSE) -> 120.22 | I34: =VLOOKUP($A34,HAVERD!$A:$DP,I$2,FALSE) -> 121.41 | ... AW34: =VLOOKUP($A34,HAVERD!$A:$DP,AW$2,FALSE) -> 77.81 | AZ34: =AZ17 -> 45722 | BA34: =_xlfn.IFNA(VLOOKUP($AZ34,HAVERD!$A:$DP,BA$2,FALSE),"") -> 93.03 | BB34: =_xlfn.IFNA(VLOOKUP($AZ34,HAVERD!$A:$DP,BB$2,FALSE),"") -> 92.08 | BC34: =_xlfn.IFNA(VLOOKUP($AZ34,HAVERD!$A:$DP,BC$2,FALSE),"") -> 92.45 | BD34: =_xlfn.IFNA(VLOOKUP($AZ34,HAVERD!$A:$DP,BD$2,FALSE),"") -> 91.77 | BE34: =_xlfn.IFNA(VLOOKUP($AZ34,HAVERD!$A:$DP,BE$2,FALSE),"") -> 92.36 | BF34: =_xlfn.IFNA(VLOOKUP($AZ34,HAVERD!$A:$DP,BF$2,FALSE),"") -> 94.41 | BG34: =_xlfn.IFNA(VLOOKUP($AZ34,HAVERD!$A:$DP,BG$2,FALSE),"") -> 93.92 | BH34: =_xlfn.IFNA(VLOOKUP($AZ34,HAVERD!$A:$DP,BH$2,FALSE),"") -> 97.46 | ... CV34: =_xlfn.IFNA(VLOOKUP($AZ34,HAVERD!$A:$DP,CV$2,FALSE),"") -> 71.33
... A37: =A20 -> 45685 | B37: =VLOOKUP($A37,HAVERD!$A:$DP,B$2,FALSE) -> 121.2 | C37: =VLOOKUP($A37,HAVERD!$A:$DP,C$2,FALSE) -> 118.7 | D37: =VLOOKUP($A37,HAVERD!$A:$DP,D$2,FALSE) -> 118.25 | E37: =VLOOKUP($A37,HAVERD!$A:$DP,E$2,FALSE) -> 117.9 | F37: =VLOOKUP($A37,HAVERD!$A:$DP,F$2,FALSE) -> 117.92 | G37: =VLOOKUP($A37,HAVERD!$A:$DP,G$2,FALSE) -> 116.79 | H37: =VLOOKUP($A37,HAVERD!$A:$DP,H$2,FALSE) -> 117.23 | I37: =VLOOKUP($A37,HAVERD!$A:$DP,I$2,FALSE) -> 118.58 | ... AW37: =VLOOKUP($A37,HAVERD!$A:$DP,AW$2,FALSE) -> 76.08 | AZ37: =AZ20 -> 45727 | BA37: =_xlfn.IFNA(VLOOKUP($AZ37,HAVERD!$A:$DP,BA$2,FALSE),"") | BB37: =_xlfn.IFNA(VLOOKUP($AZ37,HAVERD!$A:$DP,BB$2,FALSE),"") | BC37: =_xlfn.IFNA(VLOOKUP($AZ37,HAVERD!$A:$DP,BC$2,FALSE),"") | BD37: =_xlfn.IFNA(VLOOKUP($AZ37,HAVERD!$A:$DP,BD$2,FALSE),"") | BE37: =_xlfn.IFNA(VLOOKUP($AZ37,HAVERD!$A:$DP,BE$2,FALSE),"") | BF37: =_xlfn.IFNA(VLOOKUP($AZ37,HAVERD!$A:$DP,BF$2,FALSE),"") | BG37: =_xlfn.IFNA(VLOOKUP($AZ37,HAVERD!$A:$DP,BG$2,FALSE),"") | BH37: =_xlfn.IFNA(VLOOKUP($AZ37,HAVERD!$A:$DP,BH$2,FALSE),"") | ... CV37: =_xlfn.IFNA(VLOOKUP($AZ37,HAVERD!$A:$DP,CV$2,FALSE),"")
A39: Average | AZ39: Average
A40: Month | B40: =MONTH(B20) -> 1 | C40: =MONTH(C20) -> 2 | D40: =MONTH(D20) -> 3 | E40: =MONTH(E20) -> 4 | F40: =MONTH(F20) -> 5 | G40: =MONTH(G20) -> 6 | H40: =MONTH(H20) -> 7 | I40: =MONTH(I20) -> 8 | ... AW40: =MONTH(AW20) -> 12 | AZ40: Month | BA40: =MONTH(BA18) -> 3 | BB40: =MONTH(BB18) -> 4 | BC40: =MONTH(BC18) -> 5 | BD40: =MONTH(BD18) -> 6 | BE40: =MONTH(BE18) -> 7 | BF40: =MONTH(BF18) -> 8 | BG40: =MONTH(BG18) -> 9 | BH40: =MONTH(BH18) -> 10 | ... CV40: =MONTH(CV18) -> 2
A41: Year | B41: =YEAR(B20) -> 2025 | C41: =YEAR(C20) -> 2025 | D41: =YEAR(D20) -> 2025 | E41: =YEAR(E20) -> 2025 | F41: =YEAR(F20) -> 2025 | G41: =YEAR(G20) -> 2025 | H41: =YEAR(H20) -> 2025 | I41: =YEAR(I20) -> 2025 | ... AW41: =YEAR(AW20) -> 2028 | AZ41: Year | BA41: =YEAR(BA20) -> 2025 | BB41: =YEAR(BB20) -> 2025 | BC41: =YEAR(BC20) -> 2025 | BD41: =YEAR(BD20) -> 2025 | BE41: =YEAR(BE20) -> 2025 | BF41: =YEAR(BF20) -> 2025 | BG41: =YEAR(BG20) -> 2025 | BH41: =YEAR(BH20) -> 2025 | ... CV41: =YEAR(CV20) -> 2029
A42: YYYYMM | B42: =B41*100+B40 -> 202501 | C42: =C41*100+C40 -> 202502 | D42: =D41*100+D40 -> 202503 | E42: =E41*100+E40 -> 202504 | F42: =F41*100+F40 -> 202505 | G42: =G41*100+G40 -> 202506 | H42: =H41*100+H40 -> 202507 | I42: =I41*100+I40 -> 202508 | ... AW42: =AW41*100+AW40 -> 202812 | AZ42: YYYYMM | BA42: =BA41*100+BA40 -> 202503 | BB42: =BB41*100+BB40 -> 202504 | BC42: =BC41*100+BC40 -> 202505 | BD42: =BD41*100+BD40 -> 202506 | BE42: =BE41*100+BE40 -> 202507 | BF42: =BF41*100+BF40 -> 202508 | BG42: =BG41*100+BG40 -> 202509 | BH42: =BH41*100+BH40 -> 202510 | ... CV42: =CV41*100+CV40 -> 202902
A43: Quarter | B43: =IF(B40<4,1,IF(B40<7,2,IF(B40<10,3,4))) -> 1 | C43: =IF(C40<4,1,IF(C40<7,2,IF(C40<10,3,4))) -> 1 | D43: =IF(D40<4,1,IF(D40<7,2,IF(D40<10,3,4))) -> 1 | E43: =IF(E40<4,1,IF(E40<7,2,IF(E40<10,3,4))) -> 2 | F43: =IF(F40<4,1,IF(F40<7,2,IF(F40<10,3,4))) -> 2 | G43: =IF(G40<4,1,IF(G40<7,2,IF(G40<10,3,4))) -> 2 | H43: =IF(H40<4,1,IF(H40<7,2,IF(H40<10,3,4))) -> 3 | I43: =IF(I40<4,1,IF(I40<7,2,IF(I40<10,3,4))) -> 3 | ... AW43: =IF(AW40<4,1,IF(AW40<7,2,IF(AW40<10,3,4))) -> 4 | AZ43: Quarter | BA43: =IF(BA40<4,1,IF(BA40<7,2,IF(BA40<10,3,4))) -> 1 | BB43: =IF(BB40<4,1,IF(BB40<7,2,IF(BB40<10,3,4))) -> 2 | BC43: =IF(BC40<4,1,IF(BC40<7,2,IF(BC40<10,3,4))) -> 2 | BD43: =IF(BD40<4,1,IF(BD40<7,2,IF(BD40<10,3,4))) -> 2 | BE43: =IF(BE40<4,1,IF(BE40<7,2,IF(BE40<10,3,4))) -> 3 | BF43: =IF(BF40<4,1,IF(BF40<7,2,IF(BF40<10,3,4))) -> 3 | BG43: =IF(BG40<4,1,IF(BG40<7,2,IF(BG40<10,3,4))) -> 3 | BH43: =IF(BH40<4,1,IF(BH40<7,2,IF(BH40<10,3,4))) -> 4 | ... CV43: =IF(CV40<4,1,IF(CV40<7,2,IF(CV40<10,3,4))) -> 1
A44: YYYYQQ | B44: =B41*100+B43 -> 202501 | C44: =C41*100+C43 -> 202501 | D44: =D41*100+D43 -> 202501 | E44: =E41*100+E43 -> 202502 | F44: =F41*100+F43 -> 202502 | G44: =G41*100+G43 -> 202502 | H44: =H41*100+H43 -> 202503 | I44: =I41*100+I43 -> 202503 | ... AW44: =AW41*100+AW43 -> 202804 | AZ44: YYYYQQ | BA44: =BA41*100+BA43 -> 202501 | BB44: =BB41*100+BB43 -> 202502 | BC44: =BC41*100+BC43 -> 202502 | BD44: =BD41*100+BD43 -> 202502 | BE44: =BE41*100+BE43 -> 202503 | BF44: =BF41*100+BF43 -> 202503 | BG44: =BG41*100+BG43 -> 202503 | BH44: =BH41*100+BH43 -> 202504 | ... CV44: =CV41*100+CV43 -> 202901
A45: Average | B45: =AVERAGE(B23:B37) -> 119.58067 | C45: =AVERAGE(C23:C37) -> 118.076 | D45: =AVERAGE(D23:D37) -> 117.50933 | E45: =AVERAGE(E23:E37) -> 117.17133 | F45: =AVERAGE(F23:F37) -> 116.80667 | G45: =AVERAGE(G23:G37) -> 115.504 | H45: =AVERAGE(H23:H37) -> 115.91733 | I45: =AVERAGE(I23:I37) -> 117.27267 | ... AW45: =AVERAGE(AW23:AW37) -> 78.03 | AZ45: Average | BA45: =AVERAGE(BA23:BA37) -> 105.17429 | BB45: =AVERAGE(BB23:BB37) -> 104.90214 | BC45: =AVERAGE(BC23:BC37) -> 105.12357 | BD45: =AVERAGE(BD23:BD37) -> 104.88714 | BE45: =AVERAGE(BE23:BE37) -> 104.54214 | BF45: =AVERAGE(BF23:BF37) -> 105.85214 | BG45: =AVERAGE(BG23:BG37) -> 106.34286 | BH45: =AVERAGE(BH23:BH37) -> 107.41 | ... CV45: =AVERAGE(CV23:CV37) -> 73.234286
A47: Quarterly series | AZ47: Quarterly series
B48: =B44 -> 202501 | C48: =IF(RIGHT(B48)="4",B48+97,B48+1) -> 202502 | D48: =IF(RIGHT(C48)="4",C48+97,C48+1) -> 202503 | E48: =IF(RIGHT(D48)="4",D48+97,D48+1) -> 202504 | F48: =IF(RIGHT(E48)="4",E48+97,E48+1) -> 202601 | G48: =IF(RIGHT(F48)="4",F48+97,F48+1) -> 202602 | H48: =IF(RIGHT(G48)="4",G48+97,G48+1) -> 202603 | I48: =IF(RIGHT(H48)="4",H48+97,H48+1) -> 202604 | J48: =IF(RIGHT(I48)="4",I48+97,I48+1) -> 202701 | ... R48: =IF(RIGHT(Q48)="4",Q48+97,Q48+1) -> 202901 | BA48: =BA44 -> 202501 | BB48: =IF(RIGHT(BA48)="4",BA48+97,BA48+1) -> 202502 | BC48: =IF(RIGHT(BB48)="4",BB48+97,BB48+1) -> 202503 | BD48: =IF(RIGHT(BC48)="4",BC48+97,BC48+1) -> 202504 | BE48: =IF(RIGHT(BD48)="4",BD48+97,BD48+1) -> 202601 | BF48: =IF(RIGHT(BE48)="4",BE48+97,BE48+1) -> 202602 | BG48: =IF(RIGHT(BF48)="4",BF48+97,BF48+1) -> 202603 | BH48: =IF(RIGHT(BG48)="4",BG48+97,BG48+1) -> 202604 | BI48: =IF(RIGHT(BH48)="4",BH48+97,BH48+1) -> 202701 | ... BP48: =IF(RIGHT(BO48)="4",BO48+97,BO48+1) -> 202804
A49: =A1 -> February 2025 MPR | B49: =AVERAGEIF($B$44:$AW$44,B48,$B$45:$AW$45) -> 118.38867 | C49: =AVERAGEIF($B$44:$AW$44,C48,$B$45:$AW$45) -> 116.494 | D49: =AVERAGEIF($B$44:$AW$44,D48,$B$45:$AW$45) -> 115.86778 | E49: =AVERAGEIF($B$44:$AW$44,E48,$B$45:$AW$45) -> 115.53667 | F49: =AVERAGEIF($B$44:$AW$44,F48,$B$45:$AW$45) -> 108.84178 | G49: =AVERAGEIF($B$44:$AW$44,G48,$B$45:$AW$45) -> 93.649556 | H49: =AVERAGEIF($B$44:$AW$44,H48,$B$45:$AW$45) -> 94.520444 | I49: =AVERAGEIF($B$44:$AW$44,I48,$B$45:$AW$45) -> 98.187556 | ... R49: =AVERAGEIF($B$44:$AW$44,R48,$B$45:$AW$45) -> #DIV/0! | AZ49: =AZ1 -> March 2025 | BA49: =AVERAGEIF($BA$44:$CV$44,BA48,$BA$45:$CV$45) -> 105.17429 | BB49: =AVERAGEIF($BA$44:$CV$44,BB48,$BA$45:$CV$45) -> 104.97095 | BC49: =AVERAGEIF($BA$44:$CV$44,BC48,$BA$45:$CV$45) -> 105.57905 | BD49: =AVERAGEIF($BA$44:$CV$44,BD48,$BA$45:$CV$45) -> 108.89714 | BE49: =AVERAGEIF($BA$44:$CV$44,BE48,$BA$45:$CV$45) -> 104.32619 | BF49: =AVERAGEIF($BA$44:$CV$44,BF48,$BA$45:$CV$45) -> 84.125714 | BG49: =AVERAGEIF($BA$44:$CV$44,BG48,$BA$45:$CV$45) -> 82.807857 | BH49: =AVERAGEIF($BA$44:$CV$44,BH48,$BA$45:$CV$45) -> 88.617619 | ... BP49: =AVERAGEIF($BA$44:$CV$44,BP48,$BA$45:$CV$45) -> 74.056429
AZ51: Comparison - monthly
BA52: 44927 | BB52: 44958 | BC52: 44986 | BD52: 45017 | BE52: 45047 | BF52: 45078 | BG52: 45108 | BH52: 45139 | BI52: 45170 | BJ52: 45200 | BK52: 45231 | BL52: 45261 | BM52: 45292 | BN52: 45323 | BO52: 45352 | BP52: 45383 | BQ52: 45413 | BR52: 45444 | BS52: 45474 | BT52: 45505 | BU52: 45536 | BV52: 45566 | BW52: 45597 | BX52: 45627 | BY52: 45658 | BZ52: 45689 | CA52: 45717 | CB52: 45748 | CC52: 45778 | CD52: 45809 | CE52: 45839 | CF52: 45870 | CG52: 45901 | CH52: 45931 | CI52: 45962 | CJ52: 45992 | CK52: 46023 | CL52: 46054 | CM52: 46082 | CN52: 46113 | CO52: 46143 | CP52: 46174 | CQ52: 46204 | CR52: 46235 | CS52: 46266 | CT52: 46296 | CU52: 46327 | CV52: 46357 | CW52: 46388 | CX52: 46419 | CY52: 46447 | CZ52: 46478 | DA52: 46508 | DB52: 46539 | DC52: 46569 | DD52: 46600 | DE52: 46631 | DF52: 46661 | DG52: 46692 | DH52: 46722
BA53: =MONTH(BA52) -> 1 | BB53: =MONTH(BB52) -> 2 | BC53: =MONTH(BC52) -> 3 | BD53: =MONTH(BD52) -> 4 | BE53: =MONTH(BE52) -> 5 | BF53: =MONTH(BF52) -> 6 | BG53: =MONTH(BG52) -> 7 | BH53: =MONTH(BH52) -> 8 | ... DH53: =MONTH(DH52) -> 12
BA54: 202301 | BB54: =IF(BB53=1,BA54+89,BA54+1) -> 202302 | BC54: =IF(BC53=1,BB54+89,BB54+1) -> 202303 | BD54: =IF(BD53=1,BC54+89,BC54+1) -> 202304 | BE54: =IF(BE53=1,BD54+89,BD54+1) -> 202305 | BF54: =IF(BF53=1,BE54+89,BE54+1) -> 202306 | BG54: =IF(BG53=1,BF54+89,BF54+1) -> 202307 | BH54: =IF(BH53=1,BG54+89,BG54+1) -> 202308 | BI54: =IF(BI53=1,BH54+89,BH54+1) -> 202309 | ... DH54: =IF(DH53=1,DG54+89,DG54+1) -> 202712
AZ55: =A49 -> February 2025 MPR | BA55: =HLOOKUP(BA$54,$B$42:$AW$45,4,FALSE) -> #N/A | BB55: =HLOOKUP(BB$54,$B$42:$AW$45,4,FALSE) -> #N/A | BC55: =HLOOKUP(BC$54,$B$42:$AW$45,4,FALSE) -> #N/A | BD55: =HLOOKUP(BD$54,$B$42:$AW$45,4,FALSE) -> #N/A | BE55: =HLOOKUP(BE$54,$B$42:$AW$45,4,FALSE) -> #N/A | BF55: =HLOOKUP(BF$54,$B$42:$AW$45,4,FALSE) -> #N/A | BG55: =HLOOKUP(BG$54,$B$42:$AW$45,4,FALSE) -> #N/A | BH55: =HLOOKUP(BH$54,$B$42:$AW$45,4,FALSE) -> #N/A | ... DH55: =HLOOKUP(DH$54,$B$42:$AW$45,4,FALSE) -> 85.953333
AZ56: =AZ49 -> March 2025 | BA56: =HLOOKUP(BA$54,$BA$42:$CV$45,4,FALSE) -> #N/A | BB56: =HLOOKUP(BB$54,$BA$42:$CV$45,4,FALSE) -> #N/A | BC56: =HLOOKUP(BC$54,$BA$42:$CV$45,4,FALSE) -> #N/A | BD56: =HLOOKUP(BD$54,$BA$42:$CV$45,4,FALSE) -> #N/A | BE56: =HLOOKUP(BE$54,$BA$42:$CV$45,4,FALSE) -> #N/A | BF56: =HLOOKUP(BF$54,$BA$42:$CV$45,4,FALSE) -> #N/A | BG56: =HLOOKUP(BG$54,$BA$42:$CV$45,4,FALSE) -> #N/A | BH56: =HLOOKUP(BH$54,$BA$42:$CV$45,4,FALSE) -> #N/A | ... DH56: =HLOOKUP(DH$54,$BA$42:$CV$45,4,FALSE) -> 81.12
AZ57: Difference | BP57: =BP56-BP55 -> #N/A | BQ57: =BQ56-BQ55 -> #N/A | BR57: =BR56-BR55 -> #N/A | BS57: =BS56-BS55 -> #N/A | BT57: =BT56-BT55 -> #N/A | BU57: =BU56-BU55 -> #N/A | BV57: =BV56-BV55 -> #N/A | BW57: =BW56-BW55 -> #N/A | ... DH57: =DH56-DH55 -> -4.8333333
AZ58: Next 3 years | DB58: =AVERAGE(BV57:DB57) -> #N/A
AZ60: Comparison - quarterly
BA61: 44927 | BB61: 45017 | BC61: 45108 | BD61: 45200 | BE61: 45292 | BF61: 45383 | BG61: 45474 | BH61: 45566 | BI61: 45658 | BJ61: 45748 | BK61: 45839 | BL61: 45931 | BM61: 46023 | BN61: 46113 | BO61: 46204 | BP61: 46296 | BQ61: 46388 | BR61: 46478 | BS61: 46569 | BT61: 46661
BA62: 202301 | BB62: =IF(RIGHT(BA62)="4",BA62+97,BA62+1) -> 202302 | BC62: =IF(RIGHT(BB62)="4",BB62+97,BB62+1) -> 202303 | BD62: =IF(RIGHT(BC62)="4",BC62+97,BC62+1) -> 202304 | BE62: =IF(RIGHT(BD62)="4",BD62+97,BD62+1) -> 202401 | BF62: =IF(RIGHT(BE62)="4",BE62+97,BE62+1) -> 202402 | BG62: =IF(RIGHT(BF62)="4",BF62+97,BF62+1) -> 202403 | BH62: =IF(RIGHT(BG62)="4",BG62+97,BG62+1) -> 202404 | BI62: =IF(RIGHT(BH62)="4",BH62+97,BH62+1) -> 202501 | ... BT62: =IF(RIGHT(BS62)="4",BS62+97,BS62+1) -> 202704
AZ63: =A49 -> February 2025 MPR | BA63: =HLOOKUP(BA$62,$B$48:$R$49,2,FALSE) -> #N/A | BB63: =HLOOKUP(BB$62,$B$48:$R$49,2,FALSE) -> #N/A | BC63: =HLOOKUP(BC$62,$B$48:$R$49,2,FALSE) -> #N/A | BD63: =HLOOKUP(BD$62,$B$48:$R$49,2,FALSE) -> #N/A | BE63: =HLOOKUP(BE$62,$B$48:$R$49,2,FALSE) -> #N/A | BF63: =HLOOKUP(BF$62,$B$48:$R$49,2,FALSE) -> #N/A | BG63: =HLOOKUP(BG$62,$B$48:$R$49,2,FALSE) -> #N/A | BH63: =HLOOKUP(BH$62,$B$48:$R$49,2,FALSE) -> #N/A | ... BT63: =HLOOKUP(BT$62,$B$48:$R$49,2,FALSE) -> 84.113333
AZ64: =AZ49 -> March 2025 | BA64: =HLOOKUP(BA$62,$BA$48:$BQ$49,2,FALSE) -> #N/A | BB64: =HLOOKUP(BB$62,$BA$48:$BQ$49,2,FALSE) -> #N/A | BC64: =HLOOKUP(BC$62,$BA$48:$BQ$49,2,FALSE) -> #N/A | BD64: =HLOOKUP(BD$62,$BA$48:$BQ$49,2,FALSE) -> #N/A | BE64: =HLOOKUP(BE$62,$BA$48:$BQ$49,2,FALSE) -> #N/A | BF64: =HLOOKUP(BF$62,$BA$48:$BQ$49,2,FALSE) -> #N/A | BG64: =HLOOKUP(BG$62,$BA$48:$BQ$49,2,FALSE) -> #N/A | BH64: =HLOOKUP(BH$62,$BA$48:$BQ$49,2,FALSE) -> #N/A | ... BT64: =HLOOKUP(BT$62,$BA$48:$BQ$49,2,FALSE) -> 79.145
AZ65: Difference | BG65: =BG64-BG63 -> #N/A | BH65: =BH64-BH63 -> #N/A | BI65: =BI64-BI63 -> -13.214381 | BJ65: =BJ64-BJ63 -> -11.523048 | BK65: =BK64-BK63 -> -10.28873 | BL65: =BL64-BL63 -> -6.6395238 | BM65: =BM64-BM63 -> -4.5155873 | BN65: =BN64-BN63 -> -9.5238413 | ... BT65: =BT64-BT63 -> -4.9683333
AZ66: Next 3 years | BR66: =AVERAGE(BG65:BR65) -> #N/A

Sheet Market expectations - Electrici
A1: ='Market pricing dates'!A2 -> February 2025 MPR | C1: ='Market pricing dates'!A12 -> 15 working days to 28 Jan 2025 | AZ1: ='Market pricing dates'!D2 -> March 2025 | BB1: ='Market pricing dates'!D12 -> 15 working days to 11 Mar 2025
A2: Column # | B2: =HAVERD!DR$1 -> 122 | C2: =+B2+1 -> 123 | D2: =+C2+1 -> 124 | E2: =+D2+1 -> 125 | F2: =+E2+1 -> 126 | G2: =+F2+1 -> 127 | H2: =+G2+1 -> 128 | I2: =+H2+1 -> 129 | J2: =+I2+1 -> 130 | ... AW2: =+AV2+1 -> 169 | AZ2: Column # | BA2: =HAVERD!DR$1 -> 122 | BB2: =+BA2+1 -> 123 | BC2: =+BB2+1 -> 124 | BD2: =+BC2+1 -> 125 | BE2: =+BD2+1 -> 126 | BF2: =+BE2+1 -> 127 | BG2: =+BF2+1 -> 128 | BH2: =+BG2+1 -> 129 | BI2: =+BH2+1 -> 130 | ... CV2: =+CU2+1 -> 169
A3: Months | B3: =HAVERD!DR$2 -> Electricity - 1 | C3: =HAVERD!DS$2 -> Electricity - 2 | D3: =HAVERD!DT$2 -> Electricity - 3 | E3: =HAVERD!DU$2 -> Electricity - 4 | F3: =HAVERD!DV$2 -> Electricity - 5 | G3: =HAVERD!DW$2 -> Electricity - 6 | H3: =HAVERD!DX$2 -> Electricity - 7 | I3: =HAVERD!DY$2 -> Electricity - 8 | ... AW3: =HAVERD!FM$2 -> Electricity - 48 | AZ3: Months | BA3: =HAVERD!DR$2 -> Electricity - 1 | BB3: =HAVERD!DS$2 -> Electricity - 2 | BC3: =HAVERD!DT$2 -> Electricity - 3 | BD3: =HAVERD!DU$2 -> Electricity - 4 | BE3: =HAVERD!DV$2 -> Electricity - 5 | BF3: =HAVERD!DW$2 -> Electricity - 6 | BG3: =HAVERD!DX$2 -> Electricity - 7 | BH3: =HAVERD!DY$2 -> Electricity - 8 | ... CV3: =HAVERD!FM$2 -> Electricity - 48
A4: Days | C4: 30.416667 | D4: =+C4+30.4166667 -> 60.833333 | E4: =+D4+30.4166667 -> 91.25 | F4: =+E4+30.4166667 -> 121.66667 | G4: =+F4+30.4166667 -> 152.08333 | H4: =+G4+30.4166667 -> 182.5 | I4: =+H4+30.4166667 -> 212.91667 | J4: =+I4+30.4166667 -> 243.33333 | K4: =+J4+30.4166667 -> 273.75 | ... AW4: =+AV4+30.4166667 -> 1429.5833 | AZ4: Days | BB4: 30.416667 | BC4: =+BB4+30.4166667 -> 60.833333 | BD4: =+BC4+30.4166667 -> 91.25 | BE4: =+BD4+30.4166667 -> 121.66667 | BF4: =+BE4+30.4166667 -> 152.08333 | BG4: =+BF4+30.4166667 -> 182.5 | BH4: =+BG4+30.4166667 -> 212.91667 | BI4: =+BH4+30.4166667 -> 243.33333 | BJ4: =+BI4+30.4166667 -> 273.75 | ... CV4: =+CU4+30.4166667 -> 1429.5833
A5: Dates | AZ5: Dates
A6: =A11-7 -> 45665 | B6: =A6 -> 45665 | C6: =$B6+C$4 -> 45695.417 | D6: =$B6+D$4 -> 45725.833 | E6: =$B6+E$4 -> 45756.25 | F6: =$B6+F$4 -> 45786.667 | G6: =$B6+G$4 -> 45817.083 | H6: =$B6+H$4 -> 45847.5 | I6: =$B6+I$4 -> 45877.917 | J6: =$B6+J$4 -> 45908.333 | ... AW6: =$B6+AW$4 -> 47094.583 | AZ6: =AZ11-7 -> 45707 | BA6: =AZ6 -> 45707 | BB6: =$AZ6+BB$4 -> 45737.417 | BC6: =$AZ6+BC$4 -> 45767.833 | BD6: =$AZ6+BD$4 -> 45798.25 | BE6: =$AZ6+BE$4 -> 45828.667 | BF6: =$AZ6+BF$4 -> 45859.083 | BG6: =$AZ6+BG$4 -> 45889.5 | BH6: =$AZ6+BH$4 -> 45919.917 | BI6: =$AZ6+BI$4 -> 45950.333 | ... CV6: =$AZ6+CV$4 -> 47136.583
A7: =A12-7 -> 45666 | B7: =A7 -> 45666 | C7: =$B7+C$4 -> 45696.417 | D7: =$B7+D$4 -> 45726.833 | E7: =$B7+E$4 -> 45757.25 | F7: =$B7+F$4 -> 45787.667 | G7: =$B7+G$4 -> 45818.083 | H7: =$B7+H$4 -> 45848.5 | I7: =$B7+I$4 -> 45878.917 | J7: =$B7+J$4 -> 45909.333 | ... AW7: =$B7+AW$4 -> 47095.583 | AZ7: =AZ12-7 -> 45708 | BA7: =AZ7 -> 45708 | BB7: =$AZ7+BB$4 -> 45738.417 | BC7: =$AZ7+BC$4 -> 45768.833 | BD7: =$AZ7+BD$4 -> 45799.25 | BE7: =$AZ7+BE$4 -> 45829.667 | BF7: =$AZ7+BF$4 -> 45860.083 | BG7: =$AZ7+BG$4 -> 45890.5 | BH7: =$AZ7+BH$4 -> 45920.917 | BI7: =$AZ7+BI$4 -> 45951.333 | ... CV7: =$AZ7+CV$4 -> 47137.583
A8: =A13-7 -> 45667 | B8: =A8 -> 45667 | C8: =$B8+C$4 -> 45697.417 | D8: =$B8+D$4 -> 45727.833 | E8: =$B8+E$4 -> 45758.25 | F8: =$B8+F$4 -> 45788.667 | G8: =$B8+G$4 -> 45819.083 | H8: =$B8+H$4 -> 45849.5 | I8: =$B8+I$4 -> 45879.917 | J8: =$B8+J$4 -> 45910.333 | ... AW8: =$B8+AW$4 -> 47096.583 | AZ8: =AZ13-7 -> 45709 | BA8: =AZ8 -> 45709 | BB8: =$AZ8+BB$4 -> 45739.417 | BC8: =$AZ8+BC$4 -> 45769.833 | BD8: =$AZ8+BD$4 -> 45800.25 | BE8: =$AZ8+BE$4 -> 45830.667 | BF8: =$AZ8+BF$4 -> 45861.083 | BG8: =$AZ8+BG$4 -> 45891.5 | BH8: =$AZ8+BH$4 -> 45921.917 | BI8: =$AZ8+BI$4 -> 45952.333 | ... CV8: =$AZ8+CV$4 -> 47138.583
A9: =A14-7 -> 45670 | B9: =A9 -> 45670 | C9: =$B9+C$4 -> 45700.417 | D9: =$B9+D$4 -> 45730.833 | E9: =$B9+E$4 -> 45761.25 | F9: =$B9+F$4 -> 45791.667 | G9: =$B9+G$4 -> 45822.083 | H9: =$B9+H$4 -> 45852.5 | I9: =$B9+I$4 -> 45882.917 | J9: =$B9+J$4 -> 45913.333 | ... AW9: =$B9+AW$4 -> 47099.583 | AZ9: =AZ14-7 -> 45712 | BA9: =AZ9 -> 45712 | BB9: =$AZ9+BB$4 -> 45742.417 | BC9: =$AZ9+BC$4 -> 45772.833 | BD9: =$AZ9+BD$4 -> 45803.25 | BE9: =$AZ9+BE$4 -> 45833.667 | BF9: =$AZ9+BF$4 -> 45864.083 | BG9: =$AZ9+BG$4 -> 45894.5 | BH9: =$AZ9+BH$4 -> 45924.917 | BI9: =$AZ9+BI$4 -> 45955.333 | ... CV9: =$AZ9+CV$4 -> 47141.583
A10: =A15-7 -> 45671 | B10: =A10 -> 45671 | C10: =$B10+C$4 -> 45701.417 | D10: =$B10+D$4 -> 45731.833 | E10: =$B10+E$4 -> 45762.25 | F10: =$B10+F$4 -> 45792.667 | G10: =$B10+G$4 -> 45823.083 | H10: =$B10+H$4 -> 45853.5 | I10: =$B10+I$4 -> 45883.917 | J10: =$B10+J$4 -> 45914.333 | ... AW10: =$B10+AW$4 -> 47100.583 | AZ10: =AZ15-7 -> 45713 | BA10: =AZ10 -> 45713 | BB10: =$AZ10+BB$4 -> 45743.417 | BC10: =$AZ10+BC$4 -> 45773.833 | BD10: =$AZ10+BD$4 -> 45804.25 | BE10: =$AZ10+BE$4 -> 45834.667 | BF10: =$AZ10+BF$4 -> 45865.083 | BG10: =$AZ10+BG$4 -> 45895.5 | BH10: =$AZ10+BH$4 -> 45925.917 | BI10: =$AZ10+BI$4 -> 45956.333 | ... CV10: =$AZ10+CV$4 -> 47142.583
A11: =A16-7 -> 45672 | B11: =A11 -> 45672 | C11: =$B11+C$4 -> 45702.417 | D11: =$B11+D$4 -> 45732.833 | E11: =$B11+E$4 -> 45763.25 | F11: =$B11+F$4 -> 45793.667 | G11: =$B11+G$4 -> 45824.083 | H11: =$B11+H$4 -> 45854.5 | I11: =$B11+I$4 -> 45884.917 | J11: =$B11+J$4 -> 45915.333 | ... AW11: =$B11+AW$4 -> 47101.583 | AZ11: =AZ16-7 -> 45714 | BA11: =AZ11 -> 45714 | BB11: =$AZ11+BB$4 -> 45744.417 | BC11: =$AZ11+BC$4 -> 45774.833 | BD11: =$AZ11+BD$4 -> 45805.25 | BE11: =$AZ11+BE$4 -> 45835.667 | BF11: =$AZ11+BF$4 -> 45866.083 | BG11: =$AZ11+BG$4 -> 45896.5 | BH11: =$AZ11+BH$4 -> 45926.917 | BI11: =$AZ11+BI$4 -> 45957.333 | ... CV11: =$AZ11+CV$4 -> 47143.583
A12: =A17-7 -> 45673 | B12: =A12 -> 45673 | C12: =$B12+C$4 -> 45703.417 | D12: =$B12+D$4 -> 45733.833 | E12: =$B12+E$4 -> 45764.25 | F12: =$B12+F$4 -> 45794.667 | G12: =$B12+G$4 -> 45825.083 | H12: =$B12+H$4 -> 45855.5 | I12: =$B12+I$4 -> 45885.917 | J12: =$B12+J$4 -> 45916.333 | ... AW12: =$B12+AW$4 -> 47102.583 | AZ12: =AZ17-7 -> 45715 | BA12: =AZ12 -> 45715 | BB12: =$AZ12+BB$4 -> 45745.417 | BC12: =$AZ12+BC$4 -> 45775.833 | BD12: =$AZ12+BD$4 -> 45806.25 | BE12: =$AZ12+BE$4 -> 45836.667 | BF12: =$AZ12+BF$4 -> 45867.083 | BG12: =$AZ12+BG$4 -> 45897.5 | BH12: =$AZ12+BH$4 -> 45927.917 | BI12: =$AZ12+BI$4 -> 45958.333 | ... CV12: =$AZ12+CV$4 -> 47144.583
A13: =A18-7 -> 45674 | B13: =A13 -> 45674 | C13: =$B13+C$4 -> 45704.417 | D13: =$B13+D$4 -> 45734.833 | E13: =$B13+E$4 -> 45765.25 | F13: =$B13+F$4 -> 45795.667 | G13: =$B13+G$4 -> 45826.083 | H13: =$B13+H$4 -> 45856.5 | I13: =$B13+I$4 -> 45886.917 | J13: =$B13+J$4 -> 45917.333 | ... AW13: =$B13+AW$4 -> 47103.583 | AZ13: =AZ18-7 -> 45716 | BA13: =AZ13 -> 45716 | BB13: =$AZ13+BB$4 -> 45746.417 | BC13: =$AZ13+BC$4 -> 45776.833 | BD13: =$AZ13+BD$4 -> 45807.25 | BE13: =$AZ13+BE$4 -> 45837.667 | BF13: =$AZ13+BF$4 -> 45868.083 | BG13: =$AZ13+BG$4 -> 45898.5 | BH13: =$AZ13+BH$4 -> 45928.917 | BI13: =$AZ13+BI$4 -> 45959.333 | ... CV13: =$AZ13+CV$4 -> 47145.583
A14: =A19-7 -> 45677 | B14: =A14 -> 45677 | C14: =$B14+C$4 -> 45707.417 | D14: =$B14+D$4 -> 45737.833 | E14: =$B14+E$4 -> 45768.25 | F14: =$B14+F$4 -> 45798.667 | G14: =$B14+G$4 -> 45829.083 | H14: =$B14+H$4 -> 45859.5 | I14: =$B14+I$4 -> 45889.917 | J14: =$B14+J$4 -> 45920.333 | ... AW14: =$B14+AW$4 -> 47106.583 | AZ14: =AZ19-7 -> 45719 | BA14: =AZ14 -> 45719 | BB14: =$AZ14+BB$4 -> 45749.417 | BC14: =$AZ14+BC$4 -> 45779.833 | BD14: =$AZ14+BD$4 -> 45810.25 | BE14: =$AZ14+BE$4 -> 45840.667 | BF14: =$AZ14+BF$4 -> 45871.083 | BG14: =$AZ14+BG$4 -> 45901.5 | BH14: =$AZ14+BH$4 -> 45931.917 | BI14: =$AZ14+BI$4 -> 45962.333 | ... CV14: =$AZ14+CV$4 -> 47148.583
A15: =A20-7 -> 45678 | B15: =A15 -> 45678 | C15: =$B15+C$4 -> 45708.417 | D15: =$B15+D$4 -> 45738.833 | E15: =$B15+E$4 -> 45769.25 | F15: =$B15+F$4 -> 45799.667 | G15: =$B15+G$4 -> 45830.083 | H15: =$B15+H$4 -> 45860.5 | I15: =$B15+I$4 -> 45890.917 | J15: =$B15+J$4 -> 45921.333 | ... AW15: =$B15+AW$4 -> 47107.583 | AZ15: =AZ20-7 -> 45720 | BA15: =AZ15 -> 45720 | BB15: =$AZ15+BB$4 -> 45750.417 | BC15: =$AZ15+BC$4 -> 45780.833 | BD15: =$AZ15+BD$4 -> 45811.25 | BE15: =$AZ15+BE$4 -> 45841.667 | BF15: =$AZ15+BF$4 -> 45872.083 | BG15: =$AZ15+BG$4 -> 45902.5 | BH15: =$AZ15+BH$4 -> 45932.917 | BI15: =$AZ15+BI$4 -> 45963.333 | ... CV15: =$AZ15+CV$4 -> 47149.583
A16: ='Market pricing dates'!B5 -> 45679 | B16: =A16 -> 45679 | C16: =$B16+C$4 -> 45709.417 | D16: =$B16+D$4 -> 45739.833 | E16: =$B16+E$4 -> 45770.25 | F16: =$B16+F$4 -> 45800.667 | G16: =$B16+G$4 -> 45831.083 | H16: =$B16+H$4 -> 45861.5 | I16: =$B16+I$4 -> 45891.917 | J16: =$B16+J$4 -> 45922.333 | ... AW16: =$B16+AW$4 -> 47108.583 | AZ16: ='Market pricing dates'!E5 -> 45721 | BA16: =AZ16 -> 45721 | BB16: =$AZ16+BB$4 -> 45751.417 | BC16: =$AZ16+BC$4 -> 45781.833 | BD16: =$AZ16+BD$4 -> 45812.25 | BE16: =$AZ16+BE$4 -> 45842.667 | BF16: =$AZ16+BF$4 -> 45873.083 | BG16: =$AZ16+BG$4 -> 45903.5 | BH16: =$AZ16+BH$4 -> 45933.917 | BI16: =$AZ16+BI$4 -> 45964.333 | ... CV16: =$AZ16+CV$4 -> 47150.583
A17: ='Market pricing dates'!B6 -> 45680 | B17: =A17 -> 45680 | C17: =$B17+C$4 -> 45710.417 | D17: =$B17+D$4 -> 45740.833 | E17: =$B17+E$4 -> 45771.25 | F17: =$B17+F$4 -> 45801.667 | G17: =$B17+G$4 -> 45832.083 | H17: =$B17+H$4 -> 45862.5 | I17: =$B17+I$4 -> 45892.917 | J17: =$B17+J$4 -> 45923.333 | ... AW17: =$B17+AW$4 -> 47109.583 | AZ17: ='Market pricing dates'!E6 -> 45722 | BA17: =AZ17 -> 45722 | BB17: =$AZ17+BB$4 -> 45752.417 | BC17: =$AZ17+BC$4 -> 45782.833 | BD17: =$AZ17+BD$4 -> 45813.25 | BE17: =$AZ17+BE$4 -> 45843.667 | BF17: =$AZ17+BF$4 -> 45874.083 | BG17: =$AZ17+BG$4 -> 45904.5 | BH17: =$AZ17+BH$4 -> 45934.917 | BI17: =$AZ17+BI$4 -> 45965.333 | ... CV17: =$AZ17+CV$4 -> 47151.583
A18: ='Market pricing dates'!B7 -> 45681 | B18: =A18 -> 45681 | C18: =$B18+C$4 -> 45711.417 | D18: =$B18+D$4 -> 45741.833 | E18: =$B18+E$4 -> 45772.25 | F18: =$B18+F$4 -> 45802.667 | G18: =$B18+G$4 -> 45833.083 | H18: =$B18+H$4 -> 45863.5 | I18: =$B18+I$4 -> 45893.917 | J18: =$B18+J$4 -> 45924.333 | ... AW18: =$B18+AW$4 -> 47110.583 | AZ18: ='Market pricing dates'!E7 -> 45723 | BA18: =AZ18 -> 45723 | BB18: =$AZ18+BB$4 -> 45753.417 | BC18: =$AZ18+BC$4 -> 45783.833 | BD18: =$AZ18+BD$4 -> 45814.25 | BE18: =$AZ18+BE$4 -> 45844.667 | BF18: =$AZ18+BF$4 -> 45875.083 | BG18: =$AZ18+BG$4 -> 45905.5 | BH18: =$AZ18+BH$4 -> 45935.917 | BI18: =$AZ18+BI$4 -> 45966.333 | ... CV18: =$AZ18+CV$4 -> 47152.583
A19: ='Market pricing dates'!B8 -> 45684 | B19: =A19 -> 45684 | C19: =$B19+C$4 -> 45714.417 | D19: =$B19+D$4 -> 45744.833 | E19: =$B19+E$4 -> 45775.25 | F19: =$B19+F$4 -> 45805.667 | G19: =$B19+G$4 -> 45836.083 | H19: =$B19+H$4 -> 45866.5 | I19: =$B19+I$4 -> 45896.917 | J19: =$B19+J$4 -> 45927.333 | ... AW19: =$B19+AW$4 -> 47113.583 | AZ19: ='Market pricing dates'!E8 -> 45726 | BA19: =AZ19 -> 45726 | BB19: =$AZ19+BB$4 -> 45756.417 | BC19: =$AZ19+BC$4 -> 45786.833 | BD19: =$AZ19+BD$4 -> 45817.25 | BE19: =$AZ19+BE$4 -> 45847.667 | BF19: =$AZ19+BF$4 -> 45878.083 | BG19: =$AZ19+BG$4 -> 45908.5 | BH19: =$AZ19+BH$4 -> 45938.917 | BI19: =$AZ19+BI$4 -> 45969.333 | ... CV19: =$AZ19+CV$4 -> 47155.583
A20: ='Market pricing dates'!B9 -> 45685 | B20: =A20 -> 45685 | C20: =$B20+C$4 -> 45715.417 | D20: =$B20+D$4 -> 45745.833 | E20: =$B20+E$4 -> 45776.25 | F20: =$B20+F$4 -> 45806.667 | G20: =$B20+G$4 -> 45837.083 | H20: =$B20+H$4 -> 45867.5 | I20: =$B20+I$4 -> 45897.917 | J20: =$B20+J$4 -> 45928.333 | ... AW20: =$B20+AW$4 -> 47114.583 | AZ20: ='Market pricing dates'!E9 -> 45727 | BA20: =AZ20 -> 45727 | BB20: =$AZ20+BB$4 -> 45757.417 | BC20: =$AZ20+BC$4 -> 45787.833 | BD20: =$AZ20+BD$4 -> 45818.25 | BE20: =$AZ20+BE$4 -> 45848.667 | BF20: =$AZ20+BF$4 -> 45879.083 | BG20: =$AZ20+BG$4 -> 45909.5 | BH20: =$AZ20+BH$4 -> 45939.917 | BI20: =$AZ20+BI$4 -> 45970.333 | ... CV20: =$AZ20+CV$4 -> 47156.583
A22: Electricity futures | AZ22: Electricity futures
A23: =A6 -> 45665 | B23: =VLOOKUP($A23,HAVERD!$A:$FM,B$2,FALSE) -> 94.5 | C23: =VLOOKUP($A23,HAVERD!$A:$FM,C$2,FALSE) -> 89.8 | D23: =VLOOKUP($A23,HAVERD!$A:$FM,D$2,FALSE) -> 86.95 | E23: =VLOOKUP($A23,HAVERD!$A:$FM,E$2,FALSE) -> 84.45 | F23: =VLOOKUP($A23,HAVERD!$A:$FM,F$2,FALSE) -> 84 | G23: =VLOOKUP($A23,HAVERD!$A:$FM,G$2,FALSE) -> 82.35 | H23: =VLOOKUP($A23,HAVERD!$A:$FM,H$2,FALSE) -> 82.3 | I23: =VLOOKUP($A23,HAVERD!$A:$FM,I$2,FALSE) -> 85 | ... AW23: =VLOOKUP($A23,HAVERD!$A:$FM,AW$2,FALSE) -> 71.05 | AZ23: =AZ6 -> 45707 | BA23: =_xlfn.IFNA(VLOOKUP($AZ23,HAVERD!$A:$FM,BA$2,FALSE),"") -> 93.5 | BB23: =_xlfn.IFNA(VLOOKUP($AZ23,HAVERD!$A:$FM,BB$2,FALSE),"") -> 90.8 | BC23: =_xlfn.IFNA(VLOOKUP($AZ23,HAVERD!$A:$FM,BC$2,FALSE),"") -> 87.1 | BD23: =_xlfn.IFNA(VLOOKUP($AZ23,HAVERD!$A:$FM,BD$2,FALSE),"") -> 85.3 | BE23: =_xlfn.IFNA(VLOOKUP($AZ23,HAVERD!$A:$FM,BE$2,FALSE),"") -> 88.4 | BF23: =_xlfn.IFNA(VLOOKUP($AZ23,HAVERD!$A:$FM,BF$2,FALSE),"") -> 89.05 | BG23: =_xlfn.IFNA(VLOOKUP($AZ23,HAVERD!$A:$FM,BG$2,FALSE),"") -> 89.75 | BH23: =_xlfn.IFNA(VLOOKUP($AZ23,HAVERD!$A:$FM,BH$2,FALSE),"") -> 93.7 | ... CV23: =_xlfn.IFNA(VLOOKUP($AZ23,HAVERD!$A:$FM,CV$2,FALSE),"") -> 70.05
A24: =A7 -> 45666 | B24: =VLOOKUP($A24,HAVERD!$A:$FM,B$2,FALSE) -> 92.9 | C24: =VLOOKUP($A24,HAVERD!$A:$FM,C$2,FALSE) -> 88.9 | D24: =VLOOKUP($A24,HAVERD!$A:$FM,D$2,FALSE) -> 86.2 | E24: =VLOOKUP($A24,HAVERD!$A:$FM,E$2,FALSE) -> 83.25 | F24: =VLOOKUP($A24,HAVERD!$A:$FM,F$2,FALSE) -> 81.7 | G24: =VLOOKUP($A24,HAVERD!$A:$FM,G$2,FALSE) -> 82.05 | H24: =VLOOKUP($A24,HAVERD!$A:$FM,H$2,FALSE) -> 82 | I24: =VLOOKUP($A24,HAVERD!$A:$FM,I$2,FALSE) -> 84.7 | ... AW24: =VLOOKUP($A24,HAVERD!$A:$FM,AW$2,FALSE) -> 71.45 | AZ24: =AZ7 -> 45708 | BA24: =_xlfn.IFNA(VLOOKUP($AZ24,HAVERD!$A:$FM,BA$2,FALSE),"") -> 91.55 | BB24: =_xlfn.IFNA(VLOOKUP($AZ24,HAVERD!$A:$FM,BB$2,FALSE),"") -> 88.15 | BC24: =_xlfn.IFNA(VLOOKUP($AZ24,HAVERD!$A:$FM,BC$2,FALSE),"") -> 85.5 | BD24: =_xlfn.IFNA(VLOOKUP($AZ24,HAVERD!$A:$FM,BD$2,FALSE),"") -> 83.55 | BE24: =_xlfn.IFNA(VLOOKUP($AZ24,HAVERD!$A:$FM,BE$2,FALSE),"") -> 86.45 | BF24: =_xlfn.IFNA(VLOOKUP($AZ24,HAVERD!$A:$FM,BF$2,FALSE),"") -> 87.15 | BG24: =_xlfn.IFNA(VLOOKUP($AZ24,HAVERD!$A:$FM,BG$2,FALSE),"") -> 87.85 | BH24: =_xlfn.IFNA(VLOOKUP($AZ24,HAVERD!$A:$FM,BH$2,FALSE),"") -> 92.15 | ... CV24: =_xlfn.IFNA(VLOOKUP($AZ24,HAVERD!$A:$FM,CV$2,FALSE),"") -> 70.3
A25: =A8 -> 45667 | B25: =VLOOKUP($A25,HAVERD!$A:$FM,B$2,FALSE) -> 93.15 | C25: =VLOOKUP($A25,HAVERD!$A:$FM,C$2,FALSE) -> 89.95 | D25: =VLOOKUP($A25,HAVERD!$A:$FM,D$2,FALSE) -> 86.9 | E25: =VLOOKUP($A25,HAVERD!$A:$FM,E$2,FALSE) -> 84 | F25: =VLOOKUP($A25,HAVERD!$A:$FM,F$2,FALSE) -> 82.5 | G25: =VLOOKUP($A25,HAVERD!$A:$FM,G$2,FALSE) -> 83.05 | H25: =VLOOKUP($A25,HAVERD!$A:$FM,H$2,FALSE) -> 83 | I25: =VLOOKUP($A25,HAVERD!$A:$FM,I$2,FALSE) -> 85.7 | ... AW25: =VLOOKUP($A25,HAVERD!$A:$FM,AW$2,FALSE) -> 71.65 | AZ25: =AZ8 -> 45709 | BA25: =_xlfn.IFNA(VLOOKUP($AZ25,HAVERD!$A:$FM,BA$2,FALSE),"") -> 91.5 | BB25: =_xlfn.IFNA(VLOOKUP($AZ25,HAVERD!$A:$FM,BB$2,FALSE),"") -> 88.6 | BC25: =_xlfn.IFNA(VLOOKUP($AZ25,HAVERD!$A:$FM,BC$2,FALSE),"") -> 85.25 | BD25: =_xlfn.IFNA(VLOOKUP($AZ25,HAVERD!$A:$FM,BD$2,FALSE),"") -> 83.3 | BE25: =_xlfn.IFNA(VLOOKUP($AZ25,HAVERD!$A:$FM,BE$2,FALSE),"") -> 87.1 | BF25: =_xlfn.IFNA(VLOOKUP($AZ25,HAVERD!$A:$FM,BF$2,FALSE),"") -> 87.8 | BG25: =_xlfn.IFNA(VLOOKUP($AZ25,HAVERD!$A:$FM,BG$2,FALSE),"") -> 88.5 | BH25: =_xlfn.IFNA(VLOOKUP($AZ25,HAVERD!$A:$FM,BH$2,FALSE),"") -> 92.7 | ... CV25: =_xlfn.IFNA(VLOOKUP($AZ25,HAVERD!$A:$FM,CV$2,FALSE),"") -> 70.15
A26: =A9 -> 45670 | B26: =VLOOKUP($A26,HAVERD!$A:$FM,B$2,FALSE) -> 99.65 | C26: =VLOOKUP($A26,HAVERD!$A:$FM,C$2,FALSE) -> 95 | D26: =VLOOKUP($A26,HAVERD!$A:$FM,D$2,FALSE) -> 91.8 | E26: =VLOOKUP($A26,HAVERD!$A:$FM,E$2,FALSE) -> 89.35 | F26: =VLOOKUP($A26,HAVERD!$A:$FM,F$2,FALSE) -> 88.05 | G26: =VLOOKUP($A26,HAVERD!$A:$FM,G$2,FALSE) -> 88.1 | H26: =VLOOKUP($A26,HAVERD!$A:$FM,H$2,FALSE) -> 88.05 | I26: =VLOOKUP($A26,HAVERD!$A:$FM,I$2,FALSE) -> 90.75 | ... AW26: =VLOOKUP($A26,HAVERD!$A:$FM,AW$2,FALSE) -> 72.05 | AZ26: =AZ9 -> 45712 | BA26: =_xlfn.IFNA(VLOOKUP($AZ26,HAVERD!$A:$FM,BA$2,FALSE),"") -> 93.8 | BB26: =_xlfn.IFNA(VLOOKUP($AZ26,HAVERD!$A:$FM,BB$2,FALSE),"") -> 88.7 | BC26: =_xlfn.IFNA(VLOOKUP($AZ26,HAVERD!$A:$FM,BC$2,FALSE),"") -> 84.3 | BD26: =_xlfn.IFNA(VLOOKUP($AZ26,HAVERD!$A:$FM,BD$2,FALSE),"") -> 82.75 | BE26: =_xlfn.IFNA(VLOOKUP($AZ26,HAVERD!$A:$FM,BE$2,FALSE),"") -> 87.05 | BF26: =_xlfn.IFNA(VLOOKUP($AZ26,HAVERD!$A:$FM,BF$2,FALSE),"") -> 87.7 | BG26: =_xlfn.IFNA(VLOOKUP($AZ26,HAVERD!$A:$FM,BG$2,FALSE),"") -> 88.4 | BH26: =_xlfn.IFNA(VLOOKUP($AZ26,HAVERD!$A:$FM,BH$2,FALSE),"") -> 92.35 | ... CV26: =_xlfn.IFNA(VLOOKUP($AZ26,HAVERD!$A:$FM,CV$2,FALSE),"") -> 69.65
A27: =A10 -> 45671 | B27: =VLOOKUP($A27,HAVERD!$A:$FM,B$2,FALSE) -> 97.5 | C27: =VLOOKUP($A27,HAVERD!$A:$FM,C$2,FALSE) -> 92.85 | D27: =VLOOKUP($A27,HAVERD!$A:$FM,D$2,FALSE) -> 89.7 | E27: =VLOOKUP($A27,HAVERD!$A:$FM,E$2,FALSE) -> 87.3 | F27: =VLOOKUP($A27,HAVERD!$A:$FM,F$2,FALSE) -> 85.05 | G27: =VLOOKUP($A27,HAVERD!$A:$FM,G$2,FALSE) -> 86 | H27: =VLOOKUP($A27,HAVERD!$A:$FM,H$2,FALSE) -> 85.95 | I27: =VLOOKUP($A27,HAVERD!$A:$FM,I$2,FALSE) -> 88.65 | ... AW27: =VLOOKUP($A27,HAVERD!$A:$FM,AW$2,FALSE) -> 72.05 | AZ27: =AZ10 -> 45713 | BA27: =_xlfn.IFNA(VLOOKUP($AZ27,HAVERD!$A:$FM,BA$2,FALSE),"") -> 89.35 | BB27: =_xlfn.IFNA(VLOOKUP($AZ27,HAVERD!$A:$FM,BB$2,FALSE),"") -> 83.85 | BC27: =_xlfn.IFNA(VLOOKUP($AZ27,HAVERD!$A:$FM,BC$2,FALSE),"") -> 80.15 | BD27: =_xlfn.IFNA(VLOOKUP($AZ27,HAVERD!$A:$FM,BD$2,FALSE),"") -> 79.25 | BE27: =_xlfn.IFNA(VLOOKUP($AZ27,HAVERD!$A:$FM,BE$2,FALSE),"") -> 82.65 | BF27: =_xlfn.IFNA(VLOOKUP($AZ27,HAVERD!$A:$FM,BF$2,FALSE),"") -> 83.4 | BG27: =_xlfn.IFNA(VLOOKUP($AZ27,HAVERD!$A:$FM,BG$2,FALSE),"") -> 84.1 | BH27: =_xlfn.IFNA(VLOOKUP($AZ27,HAVERD!$A:$FM,BH$2,FALSE),"") -> 88.95 | ... CV27: =_xlfn.IFNA(VLOOKUP($AZ27,HAVERD!$A:$FM,CV$2,FALSE),"") -> 70
A28: =A11 -> 45672 | B28: =VLOOKUP($A28,HAVERD!$A:$FM,B$2,FALSE) -> 98.3 | C28: =VLOOKUP($A28,HAVERD!$A:$FM,C$2,FALSE) -> 93.15 | D28: =VLOOKUP($A28,HAVERD!$A:$FM,D$2,FALSE) -> 88.65 | E28: =VLOOKUP($A28,HAVERD!$A:$FM,E$2,FALSE) -> 86.25 | F28: =VLOOKUP($A28,HAVERD!$A:$FM,F$2,FALSE) -> 85.35 | G28: =VLOOKUP($A28,HAVERD!$A:$FM,G$2,FALSE) -> 85.25 | H28: =VLOOKUP($A28,HAVERD!$A:$FM,H$2,FALSE) -> 85.2 | I28: =VLOOKUP($A28,HAVERD!$A:$FM,I$2,FALSE) -> 87.9 | ... AW28: =VLOOKUP($A28,HAVERD!$A:$FM,AW$2,FALSE) -> 72.2 | AZ28: =AZ11 -> 45714 | BA28: =_xlfn.IFNA(VLOOKUP($AZ28,HAVERD!$A:$FM,BA$2,FALSE),"") -> 85 | BB28: =_xlfn.IFNA(VLOOKUP($AZ28,HAVERD!$A:$FM,BB$2,FALSE),"") -> 79.9 | BC28: =_xlfn.IFNA(VLOOKUP($AZ28,HAVERD!$A:$FM,BC$2,FALSE),"") -> 76.05 | BD28: =_xlfn.IFNA(VLOOKUP($AZ28,HAVERD!$A:$FM,BD$2,FALSE),"") -> 76.5 | BE28: =_xlfn.IFNA(VLOOKUP($AZ28,HAVERD!$A:$FM,BE$2,FALSE),"") -> 79.4 | BF28: =_xlfn.IFNA(VLOOKUP($AZ28,HAVERD!$A:$FM,BF$2,FALSE),"") -> 80.05 | BG28: =_xlfn.IFNA(VLOOKUP($AZ28,HAVERD!$A:$FM,BG$2,FALSE),"") -> 80.75 | BH28: =_xlfn.IFNA(VLOOKUP($AZ28,HAVERD!$A:$FM,BH$2,FALSE),"") -> 85.6 | ... CV28: =_xlfn.IFNA(VLOOKUP($AZ28,HAVERD!$A:$FM,CV$2,FALSE),"") -> 71.45
A29: =A12 -> 45673 | B29: =VLOOKUP($A29,HAVERD!$A:$FM,B$2,FALSE) -> 95.7 | C29: =VLOOKUP($A29,HAVERD!$A:$FM,C$2,FALSE) -> 91.65 | D29: =VLOOKUP($A29,HAVERD!$A:$FM,D$2,FALSE) -> 87.35 | E29: =VLOOKUP($A29,HAVERD!$A:$FM,E$2,FALSE) -> 84.95 | F29: =VLOOKUP($A29,HAVERD!$A:$FM,F$2,FALSE) -> 84.1 | G29: =VLOOKUP($A29,HAVERD!$A:$FM,G$2,FALSE) -> 83.7 | H29: =VLOOKUP($A29,HAVERD!$A:$FM,H$2,FALSE) -> 83.65 | I29: =VLOOKUP($A29,HAVERD!$A:$FM,I$2,FALSE) -> 86.35 | ... AW29: =VLOOKUP($A29,HAVERD!$A:$FM,AW$2,FALSE) -> 72.45 | AZ29: =AZ12 -> 45715 | BA29: =_xlfn.IFNA(VLOOKUP($AZ29,HAVERD!$A:$FM,BA$2,FALSE),"") -> 92.2 | BB29: =_xlfn.IFNA(VLOOKUP($AZ29,HAVERD!$A:$FM,BB$2,FALSE),"") -> 86.95 | BC29: =_xlfn.IFNA(VLOOKUP($AZ29,HAVERD!$A:$FM,BC$2,FALSE),"") -> 83 | BD29: =_xlfn.IFNA(VLOOKUP($AZ29,HAVERD!$A:$FM,BD$2,FALSE),"") -> 81.4 | BE29: =_xlfn.IFNA(VLOOKUP($AZ29,HAVERD!$A:$FM,BE$2,FALSE),"") -> 85.6 | BF29: =_xlfn.IFNA(VLOOKUP($AZ29,HAVERD!$A:$FM,BF$2,FALSE),"") -> 86.15 | BG29: =_xlfn.IFNA(VLOOKUP($AZ29,HAVERD!$A:$FM,BG$2,FALSE),"") -> 86.85 | BH29: =_xlfn.IFNA(VLOOKUP($AZ29,HAVERD!$A:$FM,BH$2,FALSE),"") -> 91.3 | ... CV29: =_xlfn.IFNA(VLOOKUP($AZ29,HAVERD!$A:$FM,CV$2,FALSE),"") -> 69.85
A30: =A13 -> 45674 | B30: =VLOOKUP($A30,HAVERD!$A:$FM,B$2,FALSE) -> 96.5 | C30: =VLOOKUP($A30,HAVERD!$A:$FM,C$2,FALSE) -> 92.7 | D30: =VLOOKUP($A30,HAVERD!$A:$FM,D$2,FALSE) -> 88.5 | E30: =VLOOKUP($A30,HAVERD!$A:$FM,E$2,FALSE) -> 86.1 | F30: =VLOOKUP($A30,HAVERD!$A:$FM,F$2,FALSE) -> 85.35 | G30: =VLOOKUP($A30,HAVERD!$A:$FM,G$2,FALSE) -> 85.1 | H30: =VLOOKUP($A30,HAVERD!$A:$FM,H$2,FALSE) -> 85.05 | I30: =VLOOKUP($A30,HAVERD!$A:$FM,I$2,FALSE) -> 87.75 | ... AW30: =VLOOKUP($A30,HAVERD!$A:$FM,AW$2,FALSE) -> 72.05 | AZ30: =AZ13 -> 45716 | BA30: =_xlfn.IFNA(VLOOKUP($AZ30,HAVERD!$A:$FM,BA$2,FALSE),"") -> 85.9 | BB30: =_xlfn.IFNA(VLOOKUP($AZ30,HAVERD!$A:$FM,BB$2,FALSE),"") -> 81.15 | BC30: =_xlfn.IFNA(VLOOKUP($AZ30,HAVERD!$A:$FM,BC$2,FALSE),"") -> 80.8 | BD30: =_xlfn.IFNA(VLOOKUP($AZ30,HAVERD!$A:$FM,BD$2,FALSE),"") -> 84.45 | BE30: =_xlfn.IFNA(VLOOKUP($AZ30,HAVERD!$A:$FM,BE$2,FALSE),"") -> 85.15 | BF30: =_xlfn.IFNA(VLOOKUP($AZ30,HAVERD!$A:$FM,BF$2,FALSE),"") -> 85.85 | BG30: =_xlfn.IFNA(VLOOKUP($AZ30,HAVERD!$A:$FM,BG$2,FALSE),"") -> 89.75 | BH30: =_xlfn.IFNA(VLOOKUP($AZ30,HAVERD!$A:$FM,BH$2,FALSE),"") -> 89.85 | ... CV30: =_xlfn.IFNA(VLOOKUP($AZ30,HAVERD!$A:$FM,CV$2,FALSE),"") -> 68.05
A31: =A14 -> 45677 | B31: =VLOOKUP($A31,HAVERD!$A:$FM,B$2,FALSE) -> 98.85 | C31: =VLOOKUP($A31,HAVERD!$A:$FM,C$2,FALSE) -> 94.5 | D31: =VLOOKUP($A31,HAVERD!$A:$FM,D$2,FALSE) -> 88.45 | E31: =VLOOKUP($A31,HAVERD!$A:$FM,E$2,FALSE) -> 88.1 | F31: =VLOOKUP($A31,HAVERD!$A:$FM,F$2,FALSE) -> 87.85 | G31: =VLOOKUP($A31,HAVERD!$A:$FM,G$2,FALSE) -> 87 | H31: =VLOOKUP($A31,HAVERD!$A:$FM,H$2,FALSE) -> 86.95 | I31: =VLOOKUP($A31,HAVERD!$A:$FM,I$2,FALSE) -> 89.65 | ... AW31: =VLOOKUP($A31,HAVERD!$A:$FM,AW$2,FALSE) -> 72.1 | AZ31: =AZ14 -> 45719 | BA31: =_xlfn.IFNA(VLOOKUP($AZ31,HAVERD!$A:$FM,BA$2,FALSE),"") -> 87.1 | BB31: =_xlfn.IFNA(VLOOKUP($AZ31,HAVERD!$A:$FM,BB$2,FALSE),"") -> 81.4 | BC31: =_xlfn.IFNA(VLOOKUP($AZ31,HAVERD!$A:$FM,BC$2,FALSE),"") -> 80.75 | BD31: =_xlfn.IFNA(VLOOKUP($AZ31,HAVERD!$A:$FM,BD$2,FALSE),"") -> 85.3 | BE31: =_xlfn.IFNA(VLOOKUP($AZ31,HAVERD!$A:$FM,BE$2,FALSE),"") -> 85.6 | BF31: =_xlfn.IFNA(VLOOKUP($AZ31,HAVERD!$A:$FM,BF$2,FALSE),"") -> 87.3 | BG31: =_xlfn.IFNA(VLOOKUP($AZ31,HAVERD!$A:$FM,BG$2,FALSE),"") -> 91.4 | BH31: =_xlfn.IFNA(VLOOKUP($AZ31,HAVERD!$A:$FM,BH$2,FALSE),"") -> 91.85 | ... CV31: =_xlfn.IFNA(VLOOKUP($AZ31,HAVERD!$A:$FM,CV$2,FALSE),"") -> 67.55
A32: =A15 -> 45678 | B32: =VLOOKUP($A32,HAVERD!$A:$FM,B$2,FALSE) -> 102.45 | C32: =VLOOKUP($A32,HAVERD!$A:$FM,C$2,FALSE) -> 98 | D32: =VLOOKUP($A32,HAVERD!$A:$FM,D$2,FALSE) -> 91.8 | E32: =VLOOKUP($A32,HAVERD!$A:$FM,E$2,FALSE) -> 91.25 | F32: =VLOOKUP($A32,HAVERD!$A:$FM,F$2,FALSE) -> 90.8 | G32: =VLOOKUP($A32,HAVERD!$A:$FM,G$2,FALSE) -> 89.4 | H32: =VLOOKUP($A32,HAVERD!$A:$FM,H$2,FALSE) -> 89.35 | I32: =VLOOKUP($A32,HAVERD!$A:$FM,I$2,FALSE) -> 92.05 | ... AW32: =VLOOKUP($A32,HAVERD!$A:$FM,AW$2,FALSE) -> 72.25 | AZ32: =AZ15 -> 45720 | BA32: =_xlfn.IFNA(VLOOKUP($AZ32,HAVERD!$A:$FM,BA$2,FALSE),"") -> 84.6 | BB32: =_xlfn.IFNA(VLOOKUP($AZ32,HAVERD!$A:$FM,BB$2,FALSE),"") -> 78.95 | BC32: =_xlfn.IFNA(VLOOKUP($AZ32,HAVERD!$A:$FM,BC$2,FALSE),"") -> 79.15 | BD32: =_xlfn.IFNA(VLOOKUP($AZ32,HAVERD!$A:$FM,BD$2,FALSE),"") -> 82.9 | BE32: =_xlfn.IFNA(VLOOKUP($AZ32,HAVERD!$A:$FM,BE$2,FALSE),"") -> 83.05 | BF32: =_xlfn.IFNA(VLOOKUP($AZ32,HAVERD!$A:$FM,BF$2,FALSE),"") -> 85.25 | BG32: =_xlfn.IFNA(VLOOKUP($AZ32,HAVERD!$A:$FM,BG$2,FALSE),"") -> 88.15 | BH32: =_xlfn.IFNA(VLOOKUP($AZ32,HAVERD!$A:$FM,BH$2,FALSE),"") -> 88.6 | ... CV32: =_xlfn.IFNA(VLOOKUP($AZ32,HAVERD!$A:$FM,CV$2,FALSE),"") -> 65.4
A33: =A16 -> 45679 | B33: =VLOOKUP($A33,HAVERD!$A:$FM,B$2,FALSE) -> 100.9 | C33: =VLOOKUP($A33,HAVERD!$A:$FM,C$2,FALSE) -> 95.55 | D33: =VLOOKUP($A33,HAVERD!$A:$FM,D$2,FALSE) -> 89.6 | E33: =VLOOKUP($A33,HAVERD!$A:$FM,E$2,FALSE) -> 89.25 | F33: =VLOOKUP($A33,HAVERD!$A:$FM,F$2,FALSE) -> 88.95 | G33: =VLOOKUP($A33,HAVERD!$A:$FM,G$2,FALSE) -> 87.7 | H33: =VLOOKUP($A33,HAVERD!$A:$FM,H$2,FALSE) -> 87.65 | I33: =VLOOKUP($A33,HAVERD!$A:$FM,I$2,FALSE) -> 90.35 | ... AW33: =VLOOKUP($A33,HAVERD!$A:$FM,AW$2,FALSE) -> 70.6 | AZ33: =AZ16 -> 45721 | BA33: =_xlfn.IFNA(VLOOKUP($AZ33,HAVERD!$A:$FM,BA$2,FALSE),"") -> 82.25 | BB33: =_xlfn.IFNA(VLOOKUP($AZ33,HAVERD!$A:$FM,BB$2,FALSE),"") -> 76.9 | BC33: =_xlfn.IFNA(VLOOKUP($AZ33,HAVERD!$A:$FM,BC$2,FALSE),"") -> 76.8 | BD33: =_xlfn.IFNA(VLOOKUP($AZ33,HAVERD!$A:$FM,BD$2,FALSE),"") -> 80.5 | BE33: =_xlfn.IFNA(VLOOKUP($AZ33,HAVERD!$A:$FM,BE$2,FALSE),"") -> 80.95 | BF33: =_xlfn.IFNA(VLOOKUP($AZ33,HAVERD!$A:$FM,BF$2,FALSE),"") -> 82.45 | BG33: =_xlfn.IFNA(VLOOKUP($AZ33,HAVERD!$A:$FM,BG$2,FALSE),"") -> 85.25 | BH33: =_xlfn.IFNA(VLOOKUP($AZ33,HAVERD!$A:$FM,BH$2,FALSE),"") -> 85.7 | ... CV33: =_xlfn.IFNA(VLOOKUP($AZ33,HAVERD!$A:$FM,CV$2,FALSE),"") -> 65.1
A34: =A17 -> 45680 | B34: =VLOOKUP($A34,HAVERD!$A:$FM,B$2,FALSE) -> 102.75 | C34: =VLOOKUP($A34,HAVERD!$A:$FM,C$2,FALSE) -> 97.05 | D34: =VLOOKUP($A34,HAVERD!$A:$FM,D$2,FALSE) -> 91.55 | E34: =VLOOKUP($A34,HAVERD!$A:$FM,E$2,FALSE) -> 91.45 | F34: =VLOOKUP($A34,HAVERD!$A:$FM,F$2,FALSE) -> 91.15 | G34: =VLOOKUP($A34,HAVERD!$A:$FM,G$2,FALSE) -> 89.6 | H34: =VLOOKUP($A34,HAVERD!$A:$FM,H$2,FALSE) -> 89.55 | I34: =VLOOKUP($A34,HAVERD!$A:$FM,I$2,FALSE) -> 92.25 | ... AW34: =VLOOKUP($A34,HAVERD!$A:$FM,AW$2,FALSE) -> 70.85 | AZ34: =AZ17 -> 45722 | BA34: =_xlfn.IFNA(VLOOKUP($AZ34,HAVERD!$A:$FM,BA$2,FALSE),"") -> 78.1 | BB34: =_xlfn.IFNA(VLOOKUP($AZ34,HAVERD!$A:$FM,BB$2,FALSE),"") -> 72.15 | BC34: =_xlfn.IFNA(VLOOKUP($AZ34,HAVERD!$A:$FM,BC$2,FALSE),"") -> 74.05 | BD34: =_xlfn.IFNA(VLOOKUP($AZ34,HAVERD!$A:$FM,BD$2,FALSE),"") -> 76.3 | BE34: =_xlfn.IFNA(VLOOKUP($AZ34,HAVERD!$A:$FM,BE$2,FALSE),"") -> 76.85 | BF34: =_xlfn.IFNA(VLOOKUP($AZ34,HAVERD!$A:$FM,BF$2,FALSE),"") -> 78.25 | BG34: =_xlfn.IFNA(VLOOKUP($AZ34,HAVERD!$A:$FM,BG$2,FALSE),"") -> 81.05 | BH34: =_xlfn.IFNA(VLOOKUP($AZ34,HAVERD!$A:$FM,BH$2,FALSE),"") -> 81.5 | ... CV34: =_xlfn.IFNA(VLOOKUP($AZ34,HAVERD!$A:$FM,CV$2,FALSE),"") -> 64.75
... A37: =A20 -> 45685 | B37: =VLOOKUP($A37,HAVERD!$A:$FM,B$2,FALSE) -> 104.3 | C37: =VLOOKUP($A37,HAVERD!$A:$FM,C$2,FALSE) -> 97.15 | D37: =VLOOKUP($A37,HAVERD!$A:$FM,D$2,FALSE) -> 91.05 | E37: =VLOOKUP($A37,HAVERD!$A:$FM,E$2,FALSE) -> 90.85 | F37: =VLOOKUP($A37,HAVERD!$A:$FM,F$2,FALSE) -> 90.8 | G37: =VLOOKUP($A37,HAVERD!$A:$FM,G$2,FALSE) -> 90.1 | H37: =VLOOKUP($A37,HAVERD!$A:$FM,H$2,FALSE) -> 90.05 | I37: =VLOOKUP($A37,HAVERD!$A:$FM,I$2,FALSE) -> 90.75 | ... AW37: =VLOOKUP($A37,HAVERD!$A:$FM,AW$2,FALSE) -> 69.05 | AZ37: =AZ20 -> 45727 | BA37: =_xlfn.IFNA(VLOOKUP($AZ37,HAVERD!$A:$FM,BA$2,FALSE),"") | BB37: =_xlfn.IFNA(VLOOKUP($AZ37,HAVERD!$A:$FM,BB$2,FALSE),"") | BC37: =_xlfn.IFNA(VLOOKUP($AZ37,HAVERD!$A:$FM,BC$2,FALSE),"") | BD37: =_xlfn.IFNA(VLOOKUP($AZ37,HAVERD!$A:$FM,BD$2,FALSE),"") | BE37: =_xlfn.IFNA(VLOOKUP($AZ37,HAVERD!$A:$FM,BE$2,FALSE),"") | BF37: =_xlfn.IFNA(VLOOKUP($AZ37,HAVERD!$A:$FM,BF$2,FALSE),"") | BG37: =_xlfn.IFNA(VLOOKUP($AZ37,HAVERD!$A:$FM,BG$2,FALSE),"") | BH37: =_xlfn.IFNA(VLOOKUP($AZ37,HAVERD!$A:$FM,BH$2,FALSE),"") | ... CV37: =_xlfn.IFNA(VLOOKUP($AZ37,HAVERD!$A:$FM,CV$2,FALSE),"")
A39: Average | AZ39: Average
A40: Month | B40: =MONTH(B20) -> 1 | C40: =MONTH(C20) -> 2 | D40: =MONTH(D20) -> 3 | E40: =MONTH(E20) -> 4 | F40: =MONTH(F20) -> 5 | G40: =MONTH(G20) -> 6 | H40: =MONTH(H20) -> 7 | I40: =MONTH(I20) -> 8 | ... AW40: =MONTH(AW20) -> 12 | AZ40: Month | BA40: =MONTH(BA20) -> 3 | BB40: =MONTH(BB20) -> 4 | BC40: =MONTH(BC20) -> 5 | BD40: =MONTH(BD20) -> 6 | BE40: =MONTH(BE20) -> 7 | BF40: =MONTH(BF20) -> 8 | BG40: =MONTH(BG20) -> 9 | BH40: =MONTH(BH20) -> 10 | ... CV40: =MONTH(CV20) -> 2
A41: Year | B41: =YEAR(B20) -> 2025 | C41: =YEAR(C20) -> 2025 | D41: =YEAR(D20) -> 2025 | E41: =YEAR(E20) -> 2025 | F41: =YEAR(F20) -> 2025 | G41: =YEAR(G20) -> 2025 | H41: =YEAR(H20) -> 2025 | I41: =YEAR(I20) -> 2025 | ... AW41: =YEAR(AW20) -> 2028 | AZ41: Year | BA41: =YEAR(BA20) -> 2025 | BB41: =YEAR(BB20) -> 2025 | BC41: =YEAR(BC20) -> 2025 | BD41: =YEAR(BD20) -> 2025 | BE41: =YEAR(BE20) -> 2025 | BF41: =YEAR(BF20) -> 2025 | BG41: =YEAR(BG20) -> 2025 | BH41: =YEAR(BH20) -> 2025 | ... CV41: =YEAR(CV20) -> 2029
A42: YYYYMM | B42: =B41*100+B40 -> 202501 | C42: =C41*100+C40 -> 202502 | D42: =D41*100+D40 -> 202503 | E42: =E41*100+E40 -> 202504 | F42: =F41*100+F40 -> 202505 | G42: =G41*100+G40 -> 202506 | H42: =H41*100+H40 -> 202507 | I42: =I41*100+I40 -> 202508 | ... AW42: =AW41*100+AW40 -> 202812 | AZ42: YYYYMM | BA42: =BA41*100+BA40 -> 202503 | BB42: =BB41*100+BB40 -> 202504 | BC42: =BC41*100+BC40 -> 202505 | BD42: =BD41*100+BD40 -> 202506 | BE42: =BE41*100+BE40 -> 202507 | BF42: =BF41*100+BF40 -> 202508 | BG42: =BG41*100+BG40 -> 202509 | BH42: =BH41*100+BH40 -> 202510 | ... CV42: =CV41*100+CV40 -> 202902
A43: Quarter | B43: =IF(B40<4,1,IF(B40<7,2,IF(B40<10,3,4))) -> 1 | C43: =IF(C40<4,1,IF(C40<7,2,IF(C40<10,3,4))) -> 1 | D43: =IF(D40<4,1,IF(D40<7,2,IF(D40<10,3,4))) -> 1 | E43: =IF(E40<4,1,IF(E40<7,2,IF(E40<10,3,4))) -> 2 | F43: =IF(F40<4,1,IF(F40<7,2,IF(F40<10,3,4))) -> 2 | G43: =IF(G40<4,1,IF(G40<7,2,IF(G40<10,3,4))) -> 2 | H43: =IF(H40<4,1,IF(H40<7,2,IF(H40<10,3,4))) -> 3 | I43: =IF(I40<4,1,IF(I40<7,2,IF(I40<10,3,4))) -> 3 | ... AW43: =IF(AW40<4,1,IF(AW40<7,2,IF(AW40<10,3,4))) -> 4 | AZ43: Quarter | BA43: =IF(BA40<4,1,IF(BA40<7,2,IF(BA40<10,3,4))) -> 1 | BB43: =IF(BB40<4,1,IF(BB40<7,2,IF(BB40<10,3,4))) -> 2 | BC43: =IF(BC40<4,1,IF(BC40<7,2,IF(BC40<10,3,4))) -> 2 | BD43: =IF(BD40<4,1,IF(BD40<7,2,IF(BD40<10,3,4))) -> 2 | BE43: =IF(BE40<4,1,IF(BE40<7,2,IF(BE40<10,3,4))) -> 3 | BF43: =IF(BF40<4,1,IF(BF40<7,2,IF(BF40<10,3,4))) -> 3 | BG43: =IF(BG40<4,1,IF(BG40<7,2,IF(BG40<10,3,4))) -> 3 | BH43: =IF(BH40<4,1,IF(BH40<7,2,IF(BH40<10,3,4))) -> 4 | ... CV43: =IF(CV40<4,1,IF(CV40<7,2,IF(CV40<10,3,4))) -> 1
A44: YYYYQQ | B44: =B41*100+B43 -> 202501 | C44: =C41*100+C43 -> 202501 | D44: =D41*100+D43 -> 202501 | E44: =E41*100+E43 -> 202502 | F44: =F41*100+F43 -> 202502 | G44: =G41*100+G43 -> 202502 | H44: =H41*100+H43 -> 202503 | I44: =I41*100+I43 -> 202503 | ... AW44: =AW41*100+AW43 -> 202804 | AZ44: YYYYQQ | BA44: =BA41*100+BA43 -> 202501 | BB44: =BB41*100+BB43 -> 202502 | BC44: =BC41*100+BC43 -> 202502 | BD44: =BD41*100+BD43 -> 202502 | BE44: =BE41*100+BE43 -> 202503 | BF44: =BF41*100+BF43 -> 202503 | BG44: =BG41*100+BG43 -> 202503 | BH44: =BH41*100+BH43 -> 202504 | ... CV44: =CV41*100+CV43 -> 202901
A45: Average | B45: =AVERAGE(B23:B37) -> 99.103333 | C45: =AVERAGE(C23:C37) -> 93.96 | D45: =AVERAGE(D23:D37) -> 89.423333 | E45: =AVERAGE(E23:E37) -> 87.936667 | F45: =AVERAGE(F23:F37) -> 87.19 | G45: =AVERAGE(G23:G37) -> 86.583333 | H45: =AVERAGE(H23:H37) -> 86.533333 | I45: =AVERAGE(I23:I37) -> 88.833333 | ... AW45: =AVERAGE(AW23:AW37) -> 71.58 | AZ45: Average | BA45: =AVERAGE(BA23:BA37) -> 87.135714 | BB45: =AVERAGE(BB23:BB37) -> 82.292857 | BC45: =AVERAGE(BC23:BC37) -> 80.489286 | BD45: =AVERAGE(BD23:BD37) -> 81.464286 | BE45: =AVERAGE(BE23:BE37) -> 83.392857 | BF45: =AVERAGE(BF23:BF37) -> 84.560714 | BG45: =AVERAGE(BG23:BG37) -> 86.417857 | BH45: =AVERAGE(BH23:BH37) -> 88.9 | ... CV45: =AVERAGE(CV23:CV37) -> 68.607143
A47: Quarterly series | AZ47: Quarterly series
B48: =B44 -> 202501 | C48: =IF(RIGHT(B48)="4",B48+97,B48+1) -> 202502 | D48: =IF(RIGHT(C48)="4",C48+97,C48+1) -> 202503 | E48: =IF(RIGHT(D48)="4",D48+97,D48+1) -> 202504 | F48: =IF(RIGHT(E48)="4",E48+97,E48+1) -> 202601 | G48: =IF(RIGHT(F48)="4",F48+97,F48+1) -> 202602 | H48: =IF(RIGHT(G48)="4",G48+97,G48+1) -> 202603 | I48: =IF(RIGHT(H48)="4",H48+97,H48+1) -> 202604 | J48: =IF(RIGHT(I48)="4",I48+97,I48+1) -> 202701 | ... R48: =IF(RIGHT(Q48)="4",Q48+97,Q48+1) -> 202901 | BA48: =BA44 -> 202501 | BB48: =IF(RIGHT(BA48)="4",BA48+97,BA48+1) -> 202502 | BC48: =IF(RIGHT(BB48)="4",BB48+97,BB48+1) -> 202503 | BD48: =IF(RIGHT(BC48)="4",BC48+97,BC48+1) -> 202504 | BE48: =IF(RIGHT(BD48)="4",BD48+97,BD48+1) -> 202601 | BF48: =IF(RIGHT(BE48)="4",BE48+97,BE48+1) -> 202602 | BG48: =IF(RIGHT(BF48)="4",BF48+97,BF48+1) -> 202603 | BH48: =IF(RIGHT(BG48)="4",BG48+97,BG48+1) -> 202604 | BI48: =IF(RIGHT(BH48)="4",BH48+97,BH48+1) -> 202701 | ... BP48: =IF(RIGHT(BO48)="4",BO48+97,BO48+1) -> 202804
A49: =A1 -> February 2025 MPR | B49: =AVERAGEIF($B$44:$AW$44,B48,$B$45:$AW$45) -> 94.162222 | C49: =AVERAGEIF($B$44:$AW$44,C48,$B$45:$AW$45) -> 87.236667 | D49: =AVERAGEIF($B$44:$AW$44,D48,$B$45:$AW$45) -> 88.384444 | E49: =AVERAGEIF($B$44:$AW$44,E48,$B$45:$AW$45) -> 92.22 | F49: =AVERAGEIF($B$44:$AW$44,F48,$B$45:$AW$45) -> 86.757778 | G49: =AVERAGEIF($B$44:$AW$44,G48,$B$45:$AW$45) -> 70.134444 | H49: =AVERAGEIF($B$44:$AW$44,H48,$B$45:$AW$45) -> 73.342222 | I49: =AVERAGEIF($B$44:$AW$44,I48,$B$45:$AW$45) -> 80.523333 | ... R49: =AVERAGEIF($B$44:$AW$44,R48,$B$45:$AW$45) -> #DIV/0! | AZ49: =AZ1 -> March 2025 | BA49: =AVERAGEIF($BA$44:$CV$44,BA48,$BA$45:$CV$45) -> 87.135714 | BB49: =AVERAGEIF($BA$44:$CV$44,BB48,$BA$45:$CV$45) -> 81.415476 | BC49: =AVERAGEIF($BA$44:$CV$44,BC48,$BA$45:$CV$45) -> 84.790476 | BD49: =AVERAGEIF($BA$44:$CV$44,BD48,$BA$45:$CV$45) -> 89.634524 | BE49: =AVERAGEIF($BA$44:$CV$44,BE48,$BA$45:$CV$45) -> 87.508333 | BF49: =AVERAGEIF($BA$44:$CV$44,BF48,$BA$45:$CV$45) -> 68.032143 | BG49: =AVERAGEIF($BA$44:$CV$44,BG48,$BA$45:$CV$45) -> 69.934524 | BH49: =AVERAGEIF($BA$44:$CV$44,BH48,$BA$45:$CV$45) -> 78.484524 | ... BP49: =AVERAGEIF($BA$44:$CV$44,BP48,$BA$45:$CV$45) -> 69.67619
AZ51: Comparison - monthly
BA52: 44927 | BB52: 44958 | BC52: 44986 | BD52: 45017 | BE52: 45047 | BF52: 45078 | BG52: 45108 | BH52: 45139 | BI52: 45170 | BJ52: 45200 | BK52: 45231 | BL52: 45261 | BM52: 45292 | BN52: 45323 | BO52: 45352 | BP52: 45383 | BQ52: 45413 | BR52: 45444 | BS52: 45474 | BT52: 45505 | BU52: 45536 | BV52: 45566 | BW52: 45597 | BX52: 45627 | BY52: 45658 | BZ52: 45689 | CA52: 45717 | CB52: 45748 | CC52: 45778 | CD52: 45809 | CE52: 45839 | CF52: 45870 | CG52: 45901 | CH52: 45931 | CI52: 45962 | CJ52: 45992 | CK52: 46023 | CL52: 46054 | CM52: 46082 | CN52: 46113 | CO52: 46143 | CP52: 46174 | CQ52: 46204 | CR52: 46235 | CS52: 46266 | CT52: 46296 | CU52: 46327 | CV52: 46357 | CW52: 46388 | CX52: 46419 | CY52: 46447 | CZ52: 46478 | DA52: 46508 | DB52: 46539 | DC52: 46569 | DD52: 46600 | DE52: 46631 | DF52: 46661 | DG52: 46692 | DH52: 46722
BA53: =MONTH(BA52) -> 1 | BB53: =MONTH(BB52) -> 2 | BC53: =MONTH(BC52) -> 3 | BD53: =MONTH(BD52) -> 4 | BE53: =MONTH(BE52) -> 5 | BF53: =MONTH(BF52) -> 6 | BG53: =MONTH(BG52) -> 7 | BH53: =MONTH(BH52) -> 8 | ... DH53: =MONTH(DH52) -> 12
BA54: 202301 | BB54: =IF(BB53=1,BA54+89,BA54+1) -> 202302 | BC54: =IF(BC53=1,BB54+89,BB54+1) -> 202303 | BD54: =IF(BD53=1,BC54+89,BC54+1) -> 202304 | BE54: =IF(BE53=1,BD54+89,BD54+1) -> 202305 | BF54: =IF(BF53=1,BE54+89,BE54+1) -> 202306 | BG54: =IF(BG53=1,BF54+89,BF54+1) -> 202307 | BH54: =IF(BH53=1,BG54+89,BG54+1) -> 202308 | BI54: =IF(BI53=1,BH54+89,BH54+1) -> 202309 | ... DH54: =IF(DH53=1,DG54+89,DG54+1) -> 202712
AZ55: =A49 -> February 2025 MPR | BA55: =HLOOKUP(BA$54,$B$42:$AW$45,4,FALSE) -> #N/A | BB55: =HLOOKUP(BB$54,$B$42:$AW$45,4,FALSE) -> #N/A | BC55: =HLOOKUP(BC$54,$B$42:$AW$45,4,FALSE) -> #N/A | BD55: =HLOOKUP(BD$54,$B$42:$AW$45,4,FALSE) -> #N/A | BE55: =HLOOKUP(BE$54,$B$42:$AW$45,4,FALSE) -> #N/A | BF55: =HLOOKUP(BF$54,$B$42:$AW$45,4,FALSE) -> #N/A | BG55: =HLOOKUP(BG$54,$B$42:$AW$45,4,FALSE) -> #N/A | BH55: =HLOOKUP(BH$54,$B$42:$AW$45,4,FALSE) -> #N/A | ... DH55: =HLOOKUP(DH$54,$B$42:$AW$45,4,FALSE) -> 73.55
AZ56: =AZ49 -> March 2025 | BA56: =HLOOKUP(BA$54,$BA$42:$CV$45,4,FALSE) -> #N/A | BB56: =HLOOKUP(BB$54,$BA$42:$CV$45,4,FALSE) -> #N/A | BC56: =HLOOKUP(BC$54,$BA$42:$CV$45,4,FALSE) -> #N/A | BD56: =HLOOKUP(BD$54,$BA$42:$CV$45,4,FALSE) -> #N/A | BE56: =HLOOKUP(BE$54,$BA$42:$CV$45,4,FALSE) -> #N/A | BF56: =HLOOKUP(BF$54,$BA$42:$CV$45,4,FALSE) -> #N/A | BG56: =HLOOKUP(BG$54,$BA$42:$CV$45,4,FALSE) -> #N/A | BH56: =HLOOKUP(BH$54,$BA$42:$CV$45,4,FALSE) -> #N/A | ... DH56: =HLOOKUP(DH$54,$BA$42:$CV$45,4,FALSE) -> 73.935714
AZ57: Difference | BP57: =BP56-BP55 -> #N/A | BQ57: =BQ56-BQ55 -> #N/A | BR57: =BR56-BR55 -> #N/A | BS57: =BS56-BS55 -> #N/A | BT57: =BT56-BT55 -> #N/A | BU57: =BU56-BU55 -> #N/A | BV57: =BV56-BV55 -> #N/A | BW57: =BW56-BW55 -> #N/A | ... DH57: =DH56-DH55 -> 0.38571429
AZ58: Next 3 years | DB58: =AVERAGE(BV57:DB57) -> #N/A
AZ60: Comparison - quarterly
BA61: 44927 | BB61: 45017 | BC61: 45108 | BD61: 45200 | BE61: 45292 | BF61: 45383 | BG61: 45474 | BH61: 45566 | BI61: 45658 | BJ61: 45748 | BK61: 45839 | BL61: 45931 | BM61: 46023 | BN61: 46113 | BO61: 46204 | BP61: 46296 | BQ61: 46388 | BR61: 46478 | BS61: 46569 | BT61: 46661
BA62: 202301 | BB62: =IF(RIGHT(BA62)="4",BA62+97,BA62+1) -> 202302 | BC62: =IF(RIGHT(BB62)="4",BB62+97,BB62+1) -> 202303 | BD62: =IF(RIGHT(BC62)="4",BC62+97,BC62+1) -> 202304 | BE62: =IF(RIGHT(BD62)="4",BD62+97,BD62+1) -> 202401 | BF62: =IF(RIGHT(BE62)="4",BE62+97,BE62+1) -> 202402 | BG62: =IF(RIGHT(BF62)="4",BF62+97,BF62+1) -> 202403 | BH62: =IF(RIGHT(BG62)="4",BG62+97,BG62+1) -> 202404 | BI62: =IF(RIGHT(BH62)="4",BH62+97,BH62+1) -> 202501 | ... BT62: =IF(RIGHT(BS62)="4",BS62+97,BS62+1) -> 202704
AZ63: =A49 -> February 2025 MPR | BA63: =HLOOKUP(BA$62,$B$48:$R$49,2,FALSE) -> #N/A | BB63: =HLOOKUP(BB$62,$B$48:$R$49,2,FALSE) -> #N/A | BC63: =HLOOKUP(BC$62,$B$48:$R$49,2,FALSE) -> #N/A | BD63: =HLOOKUP(BD$62,$B$48:$R$49,2,FALSE) -> #N/A | BE63: =HLOOKUP(BE$62,$B$48:$R$49,2,FALSE) -> #N/A | BF63: =HLOOKUP(BF$62,$B$48:$R$49,2,FALSE) -> #N/A | BG63: =HLOOKUP(BG$62,$B$48:$R$49,2,FALSE) -> #N/A | BH63: =HLOOKUP(BH$62,$B$48:$R$49,2,FALSE) -> #N/A | ... BT63: =HLOOKUP(BT$62,$B$48:$R$49,2,FALSE) -> 73.541111
AZ64: =AZ49 -> March 2025 | BA64: =HLOOKUP(BA$62,$BA$48:$BQ$49,2,FALSE) -> #N/A | BB64: =HLOOKUP(BB$62,$BA$48:$BQ$49,2,FALSE) -> #N/A | BC64: =HLOOKUP(BC$62,$BA$48:$BQ$49,2,FALSE) -> #N/A | BD64: =HLOOKUP(BD$62,$BA$48:$BQ$49,2,FALSE) -> #N/A | BE64: =HLOOKUP(BE$62,$BA$48:$BQ$49,2,FALSE) -> #N/A | BF64: =HLOOKUP(BF$62,$BA$48:$BQ$49,2,FALSE) -> #N/A | BG64: =HLOOKUP(BG$62,$BA$48:$BQ$49,2,FALSE) -> #N/A | BH64: =HLOOKUP(BH$62,$BA$48:$BQ$49,2,FALSE) -> #N/A | ... BT64: =HLOOKUP(BT$62,$BA$48:$BQ$49,2,FALSE) -> 73.427381
AZ65: Difference | BG65: =BG64-BG63 -> #N/A | BH65: =BH64-BH63 -> #N/A | BI65: =BI64-BI63 -> -7.0265079 | BJ65: =BJ64-BJ63 -> -5.8211905 | BK65: =BK64-BK63 -> -3.5939683 | BL65: =BL64-BL63 -> -2.5854762 | BM65: =BM64-BM63 -> 0.75055556 | BN65: =BN64-BN63 -> -2.1023016 | ... BT65: =BT64-BT63 -> -0.11373016
AZ66: Next 3 years | BR66: =AVERAGE(BG65:BR65) -> #N/A

Sheet Market expectations - Oil
A1: ='Market pricing dates'!A2 -> February 2025 MPR | C1: ='Market pricing dates'!A12 -> 15 working days to 28 Jan 2025 | N1: ='Market pricing dates'!D2 -> March 2025 | P1: ='Market pricing dates'!D12 -> 15 working days to 11 Mar 2025
A2: Column # | B2: =HAVERD!FX$1 -> 180 | C2: =+B2+1 -> 181 | D2: =+C2+1 -> 182 | E2: =+D2+1 -> 183 | F2: =+E2+1 -> 184 | N2: Column # | O2: =HAVERD!FX$1 -> 180 | P2: =HAVERD!FY$1 -> 181 | Q2: =HAVERD!FZ$1 -> 182 | R2: =HAVERD!GA$1 -> 183 | S2: =HAVERD!GB$1 -> 184
A3: Months | B3: =HAVERD!FX$2 -> Oil - 1 | C3: =HAVERD!FY$2 -> Oil - 3 | D3: =HAVERD!FZ$2 -> Oil - 6 | E3: =HAVERD!GA$2 -> Oil - 12 | F3: =HAVERD!GB$2 -> Oil - 24 | N3: Months | O3: =HAVERD!FX$2 -> Oil - 1 | P3: =HAVERD!FY$2 -> Oil - 3 | Q3: =HAVERD!FZ$2 -> Oil - 6 | R3: =HAVERD!GA$2 -> Oil - 12 | S3: =HAVERD!GB$2 -> Oil - 24
A4: Days | C4: =365/4 -> 91.25 | D4: =365/2 -> 182.5 | E4: 365 | F4: =365*2 -> 730 | N4: Days | P4: =365/4 -> 91.25 | Q4: =365/2 -> 182.5 | R4: 365 | S4: =365*2 -> 730
A5: Dates | N5: Dates
A6: =A11-7 -> 45665 | B6: =A6 -> 45665 | C6: =$B6+C$4 -> 45756.25 | D6: =$B6+D$4 -> 45847.5 | E6: =$B6+E$4 -> 46030 | F6: =$B6+F$4 -> 46395 | N6: =N11-7 -> 45707 | O6: =N6 -> 45707 | P6: =$N6+P$4 -> 45798.25 | Q6: =$N6+Q$4 -> 45889.5 | R6: =$N6+R$4 -> 46072 | S6: =$N6+S$4 -> 46437
A7: =A12-7 -> 45666 | B7: =A7 -> 45666 | C7: =$B7+C$4 -> 45757.25 | D7: =$B7+D$4 -> 45848.5 | E7: =$B7+E$4 -> 46031 | F7: =$B7+F$4 -> 46396 | N7: =N12-7 -> 45708 | O7: =N7 -> 45708 | P7: =$N7+P$4 -> 45799.25 | Q7: =$N7+Q$4 -> 45890.5 | R7: =$N7+R$4 -> 46073 | S7: =$N7+S$4 -> 46438
A8: =A13-7 -> 45667 | B8: =A8 -> 45667 | C8: =$B8+C$4 -> 45758.25 | D8: =$B8+D$4 -> 45849.5 | E8: =$B8+E$4 -> 46032 | F8: =$B8+F$4 -> 46397 | N8: =N13-7 -> 45709 | O8: =N8 -> 45709 | P8: =$N8+P$4 -> 45800.25 | Q8: =$N8+Q$4 -> 45891.5 | R8: =$N8+R$4 -> 46074 | S8: =$N8+S$4 -> 46439
A9: =A14-7 -> 45670 | B9: =A9 -> 45670 | C9: =$B9+C$4 -> 45761.25 | D9: =$B9+D$4 -> 45852.5 | E9: =$B9+E$4 -> 46035 | F9: =$B9+F$4 -> 46400 | N9: =N14-7 -> 45712 | O9: =N9 -> 45712 | P9: =$N9+P$4 -> 45803.25 | Q9: =$N9+Q$4 -> 45894.5 | R9: =$N9+R$4 -> 46077 | S9: =$N9+S$4 -> 46442
A10: =A15-7 -> 45671 | B10: =A10 -> 45671 | C10: =$B10+C$4 -> 45762.25 | D10: =$B10+D$4 -> 45853.5 | E10: =$B10+E$4 -> 46036 | F10: =$B10+F$4 -> 46401 | N10: =N15-7 -> 45713 | O10: =N10 -> 45713 | P10: =$N10+P$4 -> 45804.25 | Q10: =$N10+Q$4 -> 45895.5 | R10: =$N10+R$4 -> 46078 | S10: =$N10+S$4 -> 46443
A11: =A16-7 -> 45672 | B11: =A11 -> 45672 | C11: =$B11+C$4 -> 45763.25 | D11: =$B11+D$4 -> 45854.5 | E11: =$B11+E$4 -> 46037 | F11: =$B11+F$4 -> 46402 | N11: =N16-7 -> 45714 | O11: =N11 -> 45714 | P11: =$N11+P$4 -> 45805.25 | Q11: =$N11+Q$4 -> 45896.5 | R11: =$N11+R$4 -> 46079 | S11: =$N11+S$4 -> 46444
A12: =A17-7 -> 45673 | B12: =A12 -> 45673 | C12: =$B12+C$4 -> 45764.25 | D12: =$B12+D$4 -> 45855.5 | E12: =$B12+E$4 -> 46038 | F12: =$B12+F$4 -> 46403 | N12: =N17-7 -> 45715 | O12: =N12 -> 45715 | P12: =$N12+P$4 -> 45806.25 | Q12: =$N12+Q$4 -> 45897.5 | R12: =$N12+R$4 -> 46080 | S12: =$N12+S$4 -> 46445
A13: =A18-7 -> 45674 | B13: =A13 -> 45674 | C13: =$B13+C$4 -> 45765.25 | D13: =$B13+D$4 -> 45856.5 | E13: =$B13+E$4 -> 46039 | F13: =$B13+F$4 -> 46404 | N13: =N18-7 -> 45716 | O13: =N13 -> 45716 | P13: =$N13+P$4 -> 45807.25 | Q13: =$N13+Q$4 -> 45898.5 | R13: =$N13+R$4 -> 46081 | S13: =$N13+S$4 -> 46446
A14: =A19-7 -> 45677 | B14: =A14 -> 45677 | C14: =$B14+C$4 -> 45768.25 | D14: =$B14+D$4 -> 45859.5 | E14: =$B14+E$4 -> 46042 | F14: =$B14+F$4 -> 46407 | N14: =N19-7 -> 45719 | O14: =N14 -> 45719 | P14: =$N14+P$4 -> 45810.25 | Q14: =$N14+Q$4 -> 45901.5 | R14: =$N14+R$4 -> 46084 | S14: =$N14+S$4 -> 46449
A15: =A20-7 -> 45678 | B15: =A15 -> 45678 | C15: =$B15+C$4 -> 45769.25 | D15: =$B15+D$4 -> 45860.5 | E15: =$B15+E$4 -> 46043 | F15: =$B15+F$4 -> 46408 | N15: =N20-7 -> 45720 | O15: =N15 -> 45720 | P15: =$N15+P$4 -> 45811.25 | Q15: =$N15+Q$4 -> 45902.5 | R15: =$N15+R$4 -> 46085 | S15: =$N15+S$4 -> 46450
A16: ='Market pricing dates'!B5 -> 45679 | B16: =A16 -> 45679 | C16: =$B16+C$4 -> 45770.25 | D16: =$B16+D$4 -> 45861.5 | E16: =$B16+E$4 -> 46044 | F16: =$B16+F$4 -> 46409 | N16: ='Market pricing dates'!E5 -> 45721 | O16: =N16 -> 45721 | P16: =$N16+P$4 -> 45812.25 | Q16: =$N16+Q$4 -> 45903.5 | R16: =$N16+R$4 -> 46086 | S16: =$N16+S$4 -> 46451
A17: ='Market pricing dates'!B6 -> 45680 | B17: =A17 -> 45680 | C17: =$B17+C$4 -> 45771.25 | D17: =$B17+D$4 -> 45862.5 | E17: =$B17+E$4 -> 46045 | F17: =$B17+F$4 -> 46410 | N17: ='Market pricing dates'!E6 -> 45722 | O17: =N17 -> 45722 | P17: =$N17+P$4 -> 45813.25 | Q17: =$N17+Q$4 -> 45904.5 | R17: =$N17+R$4 -> 46087 | S17: =$N17+S$4 -> 46452
A18: ='Market pricing dates'!B7 -> 45681 | B18: =A18 -> 45681 | C18: =$B18+C$4 -> 45772.25 | D18: =$B18+D$4 -> 45863.5 | E18: =$B18+E$4 -> 46046 | F18: =$B18+F$4 -> 46411 | N18: ='Market pricing dates'!E7 -> 45723 | O18: =N18 -> 45723 | P18: =$N18+P$4 -> 45814.25 | Q18: =$N18+Q$4 -> 45905.5 | R18: =$N18+R$4 -> 46088 | S18: =$N18+S$4 -> 46453
A19: ='Market pricing dates'!B8 -> 45684 | B19: =A19 -> 45684 | C19: =$B19+C$4 -> 45775.25 | D19: =$B19+D$4 -> 45866.5 | E19: =$B19+E$4 -> 46049 | F19: =$B19+F$4 -> 46414 | N19: ='Market pricing dates'!E8 -> 45726 | O19: =N19 -> 45726 | P19: =$N19+P$4 -> 45817.25 | Q19: =$N19+Q$4 -> 45908.5 | R19: =$N19+R$4 -> 46091 | S19: =$N19+S$4 -> 46456
A20: ='Market pricing dates'!B9 -> 45685 | B20: =A20 -> 45685 | C20: =$B20+C$4 -> 45776.25 | D20: =$B20+D$4 -> 45867.5 | E20: =$B20+E$4 -> 46050 | F20: =$B20+F$4 -> 46415 | N20: ='Market pricing dates'!E9 -> 45727 | O20: =N20 -> 45727 | P20: =$N20+P$4 -> 45818.25 | Q20: =$N20+Q$4 -> 45909.5 | R20: =$N20+R$4 -> 46092 | S20: =$N20+S$4 -> 46457
A22: Oil futures | N22: Oil futures
A23: =A6 -> 45665 | B23: =VLOOKUP($A23,HAVERD!$A:$GB,B$2,FALSE) -> 76.16 | C23: =VLOOKUP($A23,HAVERD!$A:$GB,C$2,FALSE) -> 75.11 | D23: =VLOOKUP($A23,HAVERD!$A:$GB,D$2,FALSE) -> 74 | E23: =VLOOKUP($A23,HAVERD!$A:$GB,E$2,FALSE) -> 72.12 | F23: =VLOOKUP($A23,HAVERD!$A:$GB,F$2,FALSE) -> 70.01 | N23: =N6 -> 45707 | O23: =_xlfn.IFNA(VLOOKUP($N23,HAVERD!$A:$GB,O$2,FALSE),"") -> 76.04 | P23: =_xlfn.IFNA(VLOOKUP($N23,HAVERD!$A:$GB,P$2,FALSE),"") -> 75.24 | Q23: =_xlfn.IFNA(VLOOKUP($N23,HAVERD!$A:$GB,Q$2,FALSE),"") -> 73.9 | R23: =_xlfn.IFNA(VLOOKUP($N23,HAVERD!$A:$GB,R$2,FALSE),"") -> 71.8 | S23: =_xlfn.IFNA(VLOOKUP($N23,HAVERD!$A:$GB,S$2,FALSE),"") -> 69.72
A24: =A7 -> 45666 | B24: =VLOOKUP($A24,HAVERD!$A:$GB,B$2,FALSE) -> 76.92 | C24: =VLOOKUP($A24,HAVERD!$A:$GB,C$2,FALSE) -> 75.71 | D24: =VLOOKUP($A24,HAVERD!$A:$GB,D$2,FALSE) -> 74.46 | E24: =VLOOKUP($A24,HAVERD!$A:$GB,E$2,FALSE) -> 72.41 | F24: =VLOOKUP($A24,HAVERD!$A:$GB,F$2,FALSE) -> 70.11 | N24: =N7 -> 45708 | O24: =_xlfn.IFNA(VLOOKUP($N24,HAVERD!$A:$GB,O$2,FALSE),"") -> 76.48 | P24: =_xlfn.IFNA(VLOOKUP($N24,HAVERD!$A:$GB,P$2,FALSE),"") -> 75.61 | Q24: =_xlfn.IFNA(VLOOKUP($N24,HAVERD!$A:$GB,Q$2,FALSE),"") -> 74.3 | R24: =_xlfn.IFNA(VLOOKUP($N24,HAVERD!$A:$GB,R$2,FALSE),"") -> 72.17 | S24: =_xlfn.IFNA(VLOOKUP($N24,HAVERD!$A:$GB,S$2,FALSE),"") -> 70.05
A25: =A8 -> 45667 | B25: =VLOOKUP($A25,HAVERD!$A:$GB,B$2,FALSE) -> 79.76 | C25: =VLOOKUP($A25,HAVERD!$A:$GB,C$2,FALSE) -> 78.06 | D25: =VLOOKUP($A25,HAVERD!$A:$GB,D$2,FALSE) -> 76.17 | E25: =VLOOKUP($A25,HAVERD!$A:$GB,E$2,FALSE) -> 73.5 | F25: =VLOOKUP($A25,HAVERD!$A:$GB,F$2,FALSE) -> 70.64 | N25: =N8 -> 45709 | O25: =_xlfn.IFNA(VLOOKUP($N25,HAVERD!$A:$GB,O$2,FALSE),"") -> 74.43 | P25: =_xlfn.IFNA(VLOOKUP($N25,HAVERD!$A:$GB,P$2,FALSE),"") -> 73.68 | Q25: =_xlfn.IFNA(VLOOKUP($N25,HAVERD!$A:$GB,Q$2,FALSE),"") -> 72.51 | R25: =_xlfn.IFNA(VLOOKUP($N25,HAVERD!$A:$GB,R$2,FALSE),"") -> 70.64 | S25: =_xlfn.IFNA(VLOOKUP($N25,HAVERD!$A:$GB,S$2,FALSE),"") -> 68.92
A26: =A9 -> 45670 | B26: =VLOOKUP($A26,HAVERD!$A:$GB,B$2,FALSE) -> 81.01 | C26: =VLOOKUP($A26,HAVERD!$A:$GB,C$2,FALSE) -> 78.52 | D26: =VLOOKUP($A26,HAVERD!$A:$GB,D$2,FALSE) -> 76.11 | E26: =VLOOKUP($A26,HAVERD!$A:$GB,E$2,FALSE) -> 73.13 | F26: =VLOOKUP($A26,HAVERD!$A:$GB,F$2,FALSE) -> 70.38 | N26: =N9 -> 45712 | O26: =_xlfn.IFNA(VLOOKUP($N26,HAVERD!$A:$GB,O$2,FALSE),"") -> 74.78 | P26: =_xlfn.IFNA(VLOOKUP($N26,HAVERD!$A:$GB,P$2,FALSE),"") -> 73.89 | Q26: =_xlfn.IFNA(VLOOKUP($N26,HAVERD!$A:$GB,Q$2,FALSE),"") -> 72.66 | R26: =_xlfn.IFNA(VLOOKUP($N26,HAVERD!$A:$GB,R$2,FALSE),"") -> 70.72 | S26: =_xlfn.IFNA(VLOOKUP($N26,HAVERD!$A:$GB,S$2,FALSE),"") -> 68.96
A27: =A10 -> 45671 | B27: =VLOOKUP($A27,HAVERD!$A:$GB,B$2,FALSE) -> 79.92 | C27: =VLOOKUP($A27,HAVERD!$A:$GB,C$2,FALSE) -> 77.93 | D27: =VLOOKUP($A27,HAVERD!$A:$GB,D$2,FALSE) -> 75.88 | E27: =VLOOKUP($A27,HAVERD!$A:$GB,E$2,FALSE) -> 73.26 | F27: =VLOOKUP($A27,HAVERD!$A:$GB,F$2,FALSE) -> 70.78 | N27: =N10 -> 45713 | O27: =_xlfn.IFNA(VLOOKUP($N27,HAVERD!$A:$GB,O$2,FALSE),"") -> 73.02 | P27: =_xlfn.IFNA(VLOOKUP($N27,HAVERD!$A:$GB,P$2,FALSE),"") -> 72.09 | Q27: =_xlfn.IFNA(VLOOKUP($N27,HAVERD!$A:$GB,Q$2,FALSE),"") -> 70.94 | R27: =_xlfn.IFNA(VLOOKUP($N27,HAVERD!$A:$GB,R$2,FALSE),"") -> 69.21 | S27: =_xlfn.IFNA(VLOOKUP($N27,HAVERD!$A:$GB,S$2,FALSE),"") -> 67.87
A28: =A11 -> 45672 | B28: =VLOOKUP($A28,HAVERD!$A:$GB,B$2,FALSE) -> 82.03 | C28: =VLOOKUP($A28,HAVERD!$A:$GB,C$2,FALSE) -> 79.48 | D28: =VLOOKUP($A28,HAVERD!$A:$GB,D$2,FALSE) -> 76.98 | E28: =VLOOKUP($A28,HAVERD!$A:$GB,E$2,FALSE) -> 73.93 | F28: =VLOOKUP($A28,HAVERD!$A:$GB,F$2,FALSE) -> 71.2 | N28: =N11 -> 45714 | O28: =_xlfn.IFNA(VLOOKUP($N28,HAVERD!$A:$GB,O$2,FALSE),"") -> 72.53 | P28: =_xlfn.IFNA(VLOOKUP($N28,HAVERD!$A:$GB,P$2,FALSE),"") -> 71.61 | Q28: =_xlfn.IFNA(VLOOKUP($N28,HAVERD!$A:$GB,Q$2,FALSE),"") -> 70.37 | R28: =_xlfn.IFNA(VLOOKUP($N28,HAVERD!$A:$GB,R$2,FALSE),"") -> 68.65 | S28: =_xlfn.IFNA(VLOOKUP($N28,HAVERD!$A:$GB,S$2,FALSE),"") -> 67.4
A29: =A12 -> 45673 | B29: =VLOOKUP($A29,HAVERD!$A:$GB,B$2,FALSE) -> 81.29 | C29: =VLOOKUP($A29,HAVERD!$A:$GB,C$2,FALSE) -> 78.72 | D29: =VLOOKUP($A29,HAVERD!$A:$GB,D$2,FALSE) -> 76.24 | E29: =VLOOKUP($A29,HAVERD!$A:$GB,E$2,FALSE) -> 73.23 | F29: =VLOOKUP($A29,HAVERD!$A:$GB,F$2,FALSE) -> 70.66 | N29: =N12 -> 45715 | O29: =_xlfn.IFNA(VLOOKUP($N29,HAVERD!$A:$GB,O$2,FALSE),"") -> 74.04 | P29: =_xlfn.IFNA(VLOOKUP($N29,HAVERD!$A:$GB,P$2,FALSE),"") -> 73.06 | Q29: =_xlfn.IFNA(VLOOKUP($N29,HAVERD!$A:$GB,Q$2,FALSE),"") -> 71.62 | R29: =_xlfn.IFNA(VLOOKUP($N29,HAVERD!$A:$GB,R$2,FALSE),"") -> 69.65 | S29: =_xlfn.IFNA(VLOOKUP($N29,HAVERD!$A:$GB,S$2,FALSE),"") -> 68.04
A30: =A13 -> 45674 | B30: =VLOOKUP($A30,HAVERD!$A:$GB,B$2,FALSE) -> 80.79 | C30: =VLOOKUP($A30,HAVERD!$A:$GB,C$2,FALSE) -> 78.43 | D30: =VLOOKUP($A30,HAVERD!$A:$GB,D$2,FALSE) -> 75.98 | E30: =VLOOKUP($A30,HAVERD!$A:$GB,E$2,FALSE) -> 73 | F30: =VLOOKUP($A30,HAVERD!$A:$GB,F$2,FALSE) -> 70.53 | N30: =N13 -> 45716 | O30: =_xlfn.IFNA(VLOOKUP($N30,HAVERD!$A:$GB,O$2,FALSE),"") -> 73.18 | P30: =_xlfn.IFNA(VLOOKUP($N30,HAVERD!$A:$GB,P$2,FALSE),"") -> 72.28 | Q30: =_xlfn.IFNA(VLOOKUP($N30,HAVERD!$A:$GB,Q$2,FALSE),"") -> 70.85 | R30: =_xlfn.IFNA(VLOOKUP($N30,HAVERD!$A:$GB,R$2,FALSE),"") -> 68.95 | S30: =_xlfn.IFNA(VLOOKUP($N30,HAVERD!$A:$GB,S$2,FALSE),"") -> 67.51
A31: =A14 -> 45677 | B31: =VLOOKUP($A31,HAVERD!$A:$GB,B$2,FALSE) -> 80.15 | C31: =VLOOKUP($A31,HAVERD!$A:$GB,C$2,FALSE) -> 78.13 | D31: =VLOOKUP($A31,HAVERD!$A:$GB,D$2,FALSE) -> 75.91 | E31: =VLOOKUP($A31,HAVERD!$A:$GB,E$2,FALSE) -> 73.16 | F31: =VLOOKUP($A31,HAVERD!$A:$GB,F$2,FALSE) -> 70.89 | N31: =N14 -> 45719 | O31: =_xlfn.IFNA(VLOOKUP($N31,HAVERD!$A:$GB,O$2,FALSE),"") -> 71.62 | P31: =_xlfn.IFNA(VLOOKUP($N31,HAVERD!$A:$GB,P$2,FALSE),"") -> 70.76 | Q31: =_xlfn.IFNA(VLOOKUP($N31,HAVERD!$A:$GB,Q$2,FALSE),"") -> 69.63 | R31: =_xlfn.IFNA(VLOOKUP($N31,HAVERD!$A:$GB,R$2,FALSE),"") -> 68.19 | S31: =_xlfn.IFNA(VLOOKUP($N31,HAVERD!$A:$GB,S$2,FALSE),"") -> 67.11
A32: =A15 -> 45678 | B32: =VLOOKUP($A32,HAVERD!$A:$GB,B$2,FALSE) -> 79.29 | C32: =VLOOKUP($A32,HAVERD!$A:$GB,C$2,FALSE) -> 77.58 | D32: =VLOOKUP($A32,HAVERD!$A:$GB,D$2,FALSE) -> 75.58 | E32: =VLOOKUP($A32,HAVERD!$A:$GB,E$2,FALSE) -> 72.91 | F32: =VLOOKUP($A32,HAVERD!$A:$GB,F$2,FALSE) -> 70.61 | N32: =N15 -> 45720 | O32: =_xlfn.IFNA(VLOOKUP($N32,HAVERD!$A:$GB,O$2,FALSE),"") -> 71.04 | P32: =_xlfn.IFNA(VLOOKUP($N32,HAVERD!$A:$GB,P$2,FALSE),"") -> 70.16 | Q32: =_xlfn.IFNA(VLOOKUP($N32,HAVERD!$A:$GB,Q$2,FALSE),"") -> 69.12 | R32: =_xlfn.IFNA(VLOOKUP($N32,HAVERD!$A:$GB,R$2,FALSE),"") -> 67.9 | S32: =_xlfn.IFNA(VLOOKUP($N32,HAVERD!$A:$GB,S$2,FALSE),"") -> 66.99
A33: =A16 -> 45679 | B33: =VLOOKUP($A33,HAVERD!$A:$GB,B$2,FALSE) -> 79 | C33: =VLOOKUP($A33,HAVERD!$A:$GB,C$2,FALSE) -> 77.37 | D33: =VLOOKUP($A33,HAVERD!$A:$GB,D$2,FALSE) -> 75.53 | E33: =VLOOKUP($A33,HAVERD!$A:$GB,E$2,FALSE) -> 72.98 | F33: =VLOOKUP($A33,HAVERD!$A:$GB,F$2,FALSE) -> 70.59 | N33: =N16 -> 45721 | O33: =_xlfn.IFNA(VLOOKUP($N33,HAVERD!$A:$GB,O$2,FALSE),"") -> 69.3 | P33: =_xlfn.IFNA(VLOOKUP($N33,HAVERD!$A:$GB,P$2,FALSE),"") -> 68.56 | Q33: =_xlfn.IFNA(VLOOKUP($N33,HAVERD!$A:$GB,Q$2,FALSE),"") -> 67.62 | R33: =_xlfn.IFNA(VLOOKUP($N33,HAVERD!$A:$GB,R$2,FALSE),"") -> 66.58 | S33: =_xlfn.IFNA(VLOOKUP($N33,HAVERD!$A:$GB,S$2,FALSE),"") -> 65.92
A34: =A17 -> 45680 | B34: =VLOOKUP($A34,HAVERD!$A:$GB,B$2,FALSE) -> 78.29 | C34: =VLOOKUP($A34,HAVERD!$A:$GB,C$2,FALSE) -> 76.91 | D34: =VLOOKUP($A34,HAVERD!$A:$GB,D$2,FALSE) -> 75.26 | E34: =VLOOKUP($A34,HAVERD!$A:$GB,E$2,FALSE) -> 72.86 | F34: =VLOOKUP($A34,HAVERD!$A:$GB,F$2,FALSE) -> 70.6 | N34: =N17 -> 45722 | O34: =_xlfn.IFNA(VLOOKUP($N34,HAVERD!$A:$GB,O$2,FALSE),"") -> 69.46 | P34: =_xlfn.IFNA(VLOOKUP($N34,HAVERD!$A:$GB,P$2,FALSE),"") -> 68.58 | Q34: =_xlfn.IFNA(VLOOKUP($N34,HAVERD!$A:$GB,Q$2,FALSE),"") -> 67.55 | R34: =_xlfn.IFNA(VLOOKUP($N34,HAVERD!$A:$GB,R$2,FALSE),"") -> 66.43 | S34: =_xlfn.IFNA(VLOOKUP($N34,HAVERD!$A:$GB,S$2,FALSE),"") -> 65.76
... A37: =A20 -> 45685 | B37: =VLOOKUP($A37,HAVERD!$A:$GB,B$2,FALSE) -> 77.49 | C37: =VLOOKUP($A37,HAVERD!$A:$GB,C$2,FALSE) -> 75.6 | D37: =VLOOKUP($A37,HAVERD!$A:$GB,D$2,FALSE) -> 73.65 | E37: =VLOOKUP($A37,HAVERD!$A:$GB,E$2,FALSE) -> 71.26 | F37: =VLOOKUP($A37,HAVERD!$A:$GB,F$2,FALSE) -> 69.14 | N37: =N20 -> 45727 | O37: =_xlfn.IFNA(VLOOKUP($N37,HAVERD!$A:$GB,O$2,FALSE),"") | P37: =_xlfn.IFNA(VLOOKUP($N37,HAVERD!$A:$GB,P$2,FALSE),"") | Q37: =_xlfn.IFNA(VLOOKUP($N37,HAVERD!$A:$GB,Q$2,FALSE),"") | R37: =_xlfn.IFNA(VLOOKUP($N37,HAVERD!$A:$GB,R$2,FALSE),"") | S37: =_xlfn.IFNA(VLOOKUP($N37,HAVERD!$A:$GB,S$2,FALSE),"")
A39: Average | N39: Average
A40: Month | B40: =MONTH(B20) -> 1 | C40: =MONTH(C20) -> 4 | D40: =MONTH(D20) -> 7 | E40: =MONTH(E20) -> 1 | F40: =MONTH(F20) -> 1 | N40: Month | O40: =MONTH(O20) -> 3 | P40: =MONTH(P20) -> 6 | Q40: =MONTH(Q20) -> 9 | R40: =MONTH(R20) -> 3 | S40: =MONTH(S20) -> 3
A41: Year | B41: =YEAR(B20) -> 2025 | C41: =YEAR(C20) -> 2025 | D41: =YEAR(D20) -> 2025 | E41: =YEAR(E20) -> 2026 | F41: =YEAR(F20) -> 2027 | N41: Year | O41: =YEAR(O20) -> 2025 | P41: =YEAR(P20) -> 2025 | Q41: =YEAR(Q20) -> 2025 | R41: =YEAR(R20) -> 2026 | S41: =YEAR(S20) -> 2027
A42: YYYYMM | B42: =B41*100+B40 -> 202501 | C42: =C41*100+C40 -> 202504 | D42: =D41*100+D40 -> 202507 | E42: =E41*100+E40 -> 202601 | F42: =F41*100+F40 -> 202701 | N42: YYYYMM | O42: =O41*100+O40 -> 202503 | P42: =P41*100+P40 -> 202506 | Q42: =Q41*100+Q40 -> 202509 | R42: =R41*100+R40 -> 202603 | S42: =S41*100+S40 -> 202703
A43: Quarter | B43: =IF(B40<4,1,IF(B40<7,2,IF(B40<10,3,4))) -> 1 | C43: =IF(C40<4,1,IF(C40<7,2,IF(C40<10,3,4))) -> 2 | D43: =IF(D40<4,1,IF(D40<7,2,IF(D40<10,3,4))) -> 3 | E43: =IF(E40<4,1,IF(E40<7,2,IF(E40<10,3,4))) -> 1 | F43: =IF(F40<4,1,IF(F40<7,2,IF(F40<10,3,4))) -> 1 | N43: Quarter | O43: =IF(O40<4,1,IF(O40<7,2,IF(O40<10,3,4))) -> 1 | P43: =IF(P40<4,1,IF(P40<7,2,IF(P40<10,3,4))) -> 2 | Q43: =IF(Q40<4,1,IF(Q40<7,2,IF(Q40<10,3,4))) -> 3 | R43: =IF(R40<4,1,IF(R40<7,2,IF(R40<10,3,4))) -> 1 | S43: =IF(S40<4,1,IF(S40<7,2,IF(S40<10,3,4))) -> 1
A44: YYYYQQ | B44: =B41*100+B43 -> 202501 | C44: =C41*100+C43 -> 202502 | D44: =D41*100+D43 -> 202503 | E44: =E41*100+E43 -> 202601 | F44: =F41*100+F43 -> 202701 | N44: YYYYQQ | O44: =O41*100+O43 -> 202501 | P44: =P41*100+P43 -> 202502 | Q44: =Q41*100+Q43 -> 202503 | R44: =R41*100+R43 -> 202601 | S44: =S41*100+S43 -> 202701
A45: Average | B45: =AVERAGE(B23:B37) -> 79.178667 | C45: =AVERAGE(C23:C37) -> 77.317333 | D45: =AVERAGE(D23:D37) -> 75.368667 | E45: =AVERAGE(E23:E37) -> 72.79 | F45: =AVERAGE(F23:F37) -> 70.393333 | N45: Average | O45: =AVERAGE(O23:O37) -> 72.54 | P45: =AVERAGE(P23:P37) -> 71.664286 | Q45: =AVERAGE(Q23:Q37) -> 70.475 | R45: =AVERAGE(R23:R37) -> 68.87 | S45: =AVERAGE(S23:S37) -> 67.581429
A47: Quarterly series | N47: Quarterly series
B48: =B44 -> 202501 | C48: =IF(RIGHT(B48)="4",B48+97,B48+1) -> 202502 | D48: =IF(RIGHT(C48)="4",C48+97,C48+1) -> 202503 | E48: =IF(RIGHT(D48)="4",D48+97,D48+1) -> 202504 | F48: =IF(RIGHT(E48)="4",E48+97,E48+1) -> 202601 | G48: =IF(RIGHT(F48)="4",F48+97,F48+1) -> 202602 | H48: =IF(RIGHT(G48)="4",G48+97,G48+1) -> 202603 | I48: =IF(RIGHT(H48)="4",H48+97,H48+1) -> 202604 | J48: =IF(RIGHT(I48)="4",I48+97,I48+1) -> 202701 | O48: =O44 -> 202501 | P48: =IF(RIGHT(O48)="4",O48+97,O48+1) -> 202502 | Q48: =IF(RIGHT(P48)="4",P48+97,P48+1) -> 202503 | R48: =IF(RIGHT(Q48)="4",Q48+97,Q48+1) -> 202504 | S48: =IF(RIGHT(R48)="4",R48+97,R48+1) -> 202601 | T48: =IF(RIGHT(S48)="4",S48+97,S48+1) -> 202602 | U48: =IF(RIGHT(T48)="4",T48+97,T48+1) -> 202603 | V48: =IF(RIGHT(U48)="4",U48+97,U48+1) -> 202604 | W48: =IF(RIGHT(V48)="4",V48+97,V48+1) -> 202701
A49: =A1 -> February 2025 MPR | B49: =AVERAGEIF($B$44:$F$44,B48,$B$45:$F$45) -> 79.178667 | C49: =AVERAGEIF($B$44:$F$44,C48,$B$45:$F$45) -> 77.317333 | D49: =AVERAGEIF($B$44:$F$44,D48,$B$45:$F$45) -> 75.368667 | E49: =AVERAGE(D49,F49) -> 74.079333 | F49: =AVERAGEIF($B$44:$F$44,F48,$B$45:$F$45) -> 72.79 | G49: =F49+(J49-F49)*1/4 -> 72.190833 | H49: =G49+(J49-F49)*1/4 -> 71.591667 | I49: =H49+(J49-F49)*1/4 -> 70.9925 | J49: =AVERAGEIF($B$44:$F$44,J48,$B$45:$F$45) -> 70.393333 | N49: =N1 -> March 2025 | O49: =AVERAGEIF($O$44:$BJ$44,O48,$O$45:$BJ$45) -> 72.54 | P49: =AVERAGEIF($O$44:$BJ$44,P48,$O$45:$BJ$45) -> 71.664286 | Q49: =AVERAGEIF($O$44:$BJ$44,Q48,$O$45:$BJ$45) -> 70.475 | R49: =AVERAGE(Q49,S49) -> 69.6725 | S49: =AVERAGEIF($O$44:$BJ$44,S48,$O$45:$BJ$45) -> 68.87 | T49: =S49+(W49-S49)*1/4 -> 68.547857 | U49: =T49+(W49-S49)*1/4 -> 68.225714 | V49: =U49+(W49-S49)*1/4 -> 67.903571 | W49: =AVERAGEIF($O$44:$BJ$44,W48,$O$45:$BJ$45) -> 67.581429
N52: Comparison - quarterly
O53: 44927 | P53: 45017 | Q53: 45108 | R53: 45200 | S53: 45292 | T53: 45383 | U53: 45474 | V53: 45566 | W53: 45658 | X53: 45748 | Y53: 45839 | Z53: 45931 | AA53: 46023 | AB53: 46113 | AC53: 46204 | AD53: 46296 | AE53: 46388 | AF53: 46478 | AG53: 46569 | AH53: 46661
O54: 202301 | P54: =IF(RIGHT(O54)="4",O54+97,O54+1) -> 202302 | Q54: =IF(RIGHT(P54)="4",P54+97,P54+1) -> 202303 | R54: =IF(RIGHT(Q54)="4",Q54+97,Q54+1) -> 202304 | S54: =IF(RIGHT(R54)="4",R54+97,R54+1) -> 202401 | T54: =IF(RIGHT(S54)="4",S54+97,S54+1) -> 202402 | U54: =IF(RIGHT(T54)="4",T54+97,T54+1) -> 202403 | V54: =IF(RIGHT(U54)="4",U54+97,U54+1) -> 202404 | W54: =IF(RIGHT(V54)="4",V54+97,V54+1) -> 202501 | ... AH54: =IF(RIGHT(AG54)="4",AG54+97,AG54+1) -> 202704
N55: =A49 -> February 2025 MPR | O55: =HLOOKUP(O$54,$B$48:$J$49,2,FALSE) -> #N/A | P55: =HLOOKUP(P$54,$B$48:$J$49,2,FALSE) -> #N/A | Q55: =HLOOKUP(Q$54,$B$48:$J$49,2,FALSE) -> #N/A | R55: =HLOOKUP(R$54,$B$48:$J$49,2,FALSE) -> #N/A | S55: =HLOOKUP(S$54,$B$48:$J$49,2,FALSE) -> #N/A | T55: =HLOOKUP(T$54,$B$48:$J$49,2,FALSE) -> #N/A | U55: =HLOOKUP(U$54,$B$48:$J$49,2,FALSE) -> #N/A | V55: =HLOOKUP(V$54,$B$48:$J$49,2,FALSE) -> #N/A | ... AH55: =HLOOKUP(AH$54,$B$48:$J$49,2,FALSE) -> #N/A
N56: =N49 -> March 2025 | O56: =HLOOKUP(O$54,$O$48:$AE$49,2,FALSE) -> #N/A | P56: =HLOOKUP(P$54,$O$48:$AE$49,2,FALSE) -> #N/A | Q56: =HLOOKUP(Q$54,$O$48:$AE$49,2,FALSE) -> #N/A | R56: =HLOOKUP(R$54,$O$48:$AE$49,2,FALSE) -> #N/A | S56: =HLOOKUP(S$54,$O$48:$AE$49,2,FALSE) -> #N/A | T56: =HLOOKUP(T$54,$O$48:$AE$49,2,FALSE) -> #N/A | U56: =HLOOKUP(U$54,$O$48:$AE$49,2,FALSE) -> #N/A | V56: =HLOOKUP(V$54,$O$48:$AE$49,2,FALSE) -> #N/A | ... AH56: =HLOOKUP(AH$54,$O$48:$AE$49,2,FALSE) -> #N/A
N57: Difference | U57: =U56-U55 -> #N/A | V57: =V56-V55 -> #N/A | W57: =W56-W55 -> -6.6386667 | X57: =X56-X55 -> -5.6530476 | Y57: =Y56-Y55 -> -4.8936667 | Z57: =Z56-Z55 -> -4.4068333 | AA57: =AA56-AA55 -> -3.92 | AB57: =AB56-AB55 -> -3.6429762 | ... AH57: =AH56-AH55 -> #N/A
N58: Difference % | U58: =100*((U56/U55)-1) -> #N/A | V58: =100*((V56/V55)-1) -> #N/A | W58: =100*((W56/W55)-1) -> -8.3844133 | X58: =100*((X56/X55)-1) -> -7.3114881 | Y58: =100*((Y56/Y55)-1) -> -6.4929723 | Z58: =100*((Z56/Z55)-1) -> -5.9488026 | AA58: =100*((AA56/AA55)-1) -> -5.3853551 | AB58: =100*((AB56/AB55)-1) -> -5.0463141 | ... AH58: =100*((AH56/AH55)-1) -> #N/A

Sheet Market expectations - Other
A1: ='Market pricing dates'!A2 -> February 2025 MPR | C1: ='Market pricing dates'!A12 -> 15 working days to 28 Jan 2025 | G1: ='Market pricing dates'!D2 -> March 2025 | I1: ='Market pricing dates'!D12 -> 15 working days to 11 Mar 2025
A2: Column # | B2: =HAVERD!FO$1 -> 171 | C2: =+B2+1 -> 172 | D2: =+C2+1 -> 173 | E2: =+D2+1 -> 174 | G2: Column # | H2: =HAVERD!FO$1 -> 171 | I2: =+H2+1 -> 172 | J2: =+I2+1 -> 173 | K2: =+J2+1 -> 174
A3: Months | B3: =HAVERD!FO$2 -> £EER broad | C3: =HAVERD!FP$2 -> Oil price | D3: =HAVERD!FQ$2 -> RXD | E3: =HAVERD!FR$2 -> £ oil price | G3: Months | H3: =HAVERD!FO$2 -> £EER broad | I3: =HAVERD!FP$2 -> Oil price | J3: =HAVERD!FQ$2 -> RXD | K3: =HAVERD!FR$2 -> £ oil price
A4: Days | C4: 30.416667 | D4: =+C4+30.4166667 -> 60.833333 | E4: =+D4+30.4166667 -> 91.25 | G4: Days | I4: 30.416667 | J4: =+I4+30.4166667 -> 60.833333 | K4: =+J4+30.4166667 -> 91.25
A5: Dates | G5: Dates
A6: =A11-7 -> 45665 | B6: =A6 -> 45665 | C6: =$B6+C$4 -> 45695.417 | D6: =$B6+D$4 -> 45725.833 | E6: =$B6+E$4 -> 45756.25 | G6: =G11-7 -> 45707 | H6: =G6 -> 45707 | I6: =$G6+I$4 -> 45737.417 | J6: =$G6+J$4 -> 45767.833 | K6: =$G6+K$4 -> 45798.25
A7: =A12-7 -> 45666 | B7: =A7 -> 45666 | C7: =$B7+C$4 -> 45696.417 | D7: =$B7+D$4 -> 45726.833 | E7: =$B7+E$4 -> 45757.25 | G7: =G12-7 -> 45708 | H7: =G7 -> 45708 | I7: =$G7+I$4 -> 45738.417 | J7: =$G7+J$4 -> 45768.833 | K7: =$G7+K$4 -> 45799.25
A8: =A13-7 -> 45667 | B8: =A8 -> 45667 | C8: =$B8+C$4 -> 45697.417 | D8: =$B8+D$4 -> 45727.833 | E8: =$B8+E$4 -> 45758.25 | G8: =G13-7 -> 45709 | H8: =G8 -> 45709 | I8: =$G8+I$4 -> 45739.417 | J8: =$G8+J$4 -> 45769.833 | K8: =$G8+K$4 -> 45800.25
A9: =A14-7 -> 45670 | B9: =A9 -> 45670 | C9: =$B9+C$4 -> 45700.417 | D9: =$B9+D$4 -> 45730.833 | E9: =$B9+E$4 -> 45761.25 | G9: =G14-7 -> 45712 | H9: =G9 -> 45712 | I9: =$G9+I$4 -> 45742.417 | J9: =$G9+J$4 -> 45772.833 | K9: =$G9+K$4 -> 45803.25
A10: =A15-7 -> 45671 | B10: =A10 -> 45671 | C10: =$B10+C$4 -> 45701.417 | D10: =$B10+D$4 -> 45731.833 | E10: =$B10+E$4 -> 45762.25 | G10: =G15-7 -> 45713 | H10: =G10 -> 45713 | I10: =$G10+I$4 -> 45743.417 | J10: =$G10+J$4 -> 45773.833 | K10: =$G10+K$4 -> 45804.25
A11: =A16-7 -> 45672 | B11: =A11 -> 45672 | C11: =$B11+C$4 -> 45702.417 | D11: =$B11+D$4 -> 45732.833 | E11: =$B11+E$4 -> 45763.25 | G11: =G16-7 -> 45714 | H11: =G11 -> 45714 | I11: =$G11+I$4 -> 45744.417 | J11: =$G11+J$4 -> 45774.833 | K11: =$G11+K$4 -> 45805.25
A12: =A17-7 -> 45673 | B12: =A12 -> 45673 | C12: =$B12+C$4 -> 45703.417 | D12: =$B12+D$4 -> 45733.833 | E12: =$B12+E$4 -> 45764.25 | G12: =G17-7 -> 45715 | H12: =G12 -> 45715 | I12: =$G12+I$4 -> 45745.417 | J12: =$G12+J$4 -> 45775.833 | K12: =$G12+K$4 -> 45806.25
A13: =A18-7 -> 45674 | B13: =A13 -> 45674 | C13: =$B13+C$4 -> 45704.417 | D13: =$B13+D$4 -> 45734.833 | E13: =$B13+E$4 -> 45765.25 | G13: =G18-7 -> 45716 | H13: =G13 -> 45716 | I13: =$G13+I$4 -> 45746.417 | J13: =$G13+J$4 -> 45776.833 | K13: =$G13+K$4 -> 45807.25
A14: =A19-7 -> 45677 | B14: =A14 -> 45677 | C14: =$B14+C$4 -> 45707.417 | D14: =$B14+D$4 -> 45737.833 | E14: =$B14+E$4 -> 45768.25 | G14: =G19-7 -> 45719 | H14: =G14 -> 45719 | I14: =$G14+I$4 -> 45749.417 | J14: =$G14+J$4 -> 45779.833 | K14: =$G14+K$4 -> 45810.25
A15: =A20-7 -> 45678 | B15: =A15 -> 45678 | C15: =$B15+C$4 -> 45708.417 | D15: =$B15+D$4 -> 45738.833 | E15: =$B15+E$4 -> 45769.25 | G15: =G20-7 -> 45720 | H15: =G15 -> 45720 | I15: =$G15+I$4 -> 45750.417 | J15: =$G15+J$4 -> 45780.833 | K15: =$G15+K$4 -> 45811.25
A16: ='Market pricing dates'!B5 -> 45679 | B16: =A16 -> 45679 | C16: =$B16+C$4 -> 45709.417 | D16: =$B16+D$4 -> 45739.833 | E16: =$B16+E$4 -> 45770.25 | G16: ='Market pricing dates'!E5 -> 45721 | H16: =G16 -> 45721 | I16: =$G16+I$4 -> 45751.417 | J16: =$G16+J$4 -> 45781.833 | K16: =$G16+K$4 -> 45812.25
A17: ='Market pricing dates'!B6 -> 45680 | B17: =A17 -> 45680 | C17: =$B17+C$4 -> 45710.417 | D17: =$B17+D$4 -> 45740.833 | E17: =$B17+E$4 -> 45771.25 | G17: ='Market pricing dates'!E6 -> 45722 | H17: =G17 -> 45722 | I17: =$G17+I$4 -> 45752.417 | J17: =$G17+J$4 -> 45782.833 | K17: =$G17+K$4 -> 45813.25
A18: ='Market pricing dates'!B7 -> 45681 | B18: =A18 -> 45681 | C18: =$B18+C$4 -> 45711.417 | D18: =$B18+D$4 -> 45741.833 | E18: =$B18+E$4 -> 45772.25 | G18: ='Market pricing dates'!E7 -> 45723 | H18: =G18 -> 45723 | I18: =$G18+I$4 -> 45753.417 | J18: =$G18+J$4 -> 45783.833 | K18: =$G18+K$4 -> 45814.25
A19: ='Market pricing dates'!B8 -> 45684 | B19: =A19 -> 45684 | C19: =$B19+C$4 -> 45714.417 | D19: =$B19+D$4 -> 45744.833 | E19: =$B19+E$4 -> 45775.25 | G19: ='Market pricing dates'!E8 -> 45726 | H19: =G19 -> 45726 | I19: =$G19+I$4 -> 45756.417 | J19: =$G19+J$4 -> 45786.833 | K19: =$G19+K$4 -> 45817.25
A20: ='Market pricing dates'!B9 -> 45685 | B20: =A20 -> 45685 | C20: =$B20+C$4 -> 45715.417 | D20: =$B20+D$4 -> 45745.833 | E20: =$B20+E$4 -> 45776.25 | G20: ='Market pricing dates'!E9 -> 45727 | H20: =G20 -> 45727 | I20: =$G20+I$4 -> 45757.417 | J20: =$G20+J$4 -> 45787.833 | K20: =$G20+K$4 -> 45818.25
A22: Average levels | G22: Average levels
A23: =A6 -> 45665 | B23: =VLOOKUP($A23,HAVERD!$A:$FV,B$2,FALSE) -> 83.3468 | C23: =VLOOKUP($A23,HAVERD!$A:$FV,C$2,FALSE) -> 77.37 | D23: =VLOOKUP($A23,HAVERD!$A:$FV,D$2,FALSE) -> 1.2342 | E23: =VLOOKUP($A23,HAVERD!$A:$FV,E$2,FALSE) -> 62.688381 | G23: =G6 -> 45707 | H23: =_xlfn.IFNA(VLOOKUP($G23,HAVERD!$A:$FV,H$2,FALSE),"") -> 84.1031 | I23: =_xlfn.IFNA(VLOOKUP($G23,HAVERD!$A:$FV,I$2,FALSE),"") -> 76.34 | J23: =_xlfn.IFNA(VLOOKUP($G23,HAVERD!$A:$FV,J$2,FALSE),"") -> 1.259 | K23: =_xlfn.IFNA(VLOOKUP($G23,HAVERD!$A:$FV,K$2,FALSE),"") -> 0
A24: =A7 -> 45666 | B24: =VLOOKUP($A24,HAVERD!$A:$FV,B$2,FALSE) -> 83.0697 | C24: =VLOOKUP($A24,HAVERD!$A:$FV,C$2,FALSE) -> 78.44 | D24: =VLOOKUP($A24,HAVERD!$A:$FV,D$2,FALSE) -> 1.2303 | E24: =VLOOKUP($A24,HAVERD!$A:$FV,E$2,FALSE) -> 63.756807 | G24: =G7 -> 45708 | H24: =_xlfn.IFNA(VLOOKUP($G24,HAVERD!$A:$FV,H$2,FALSE),"") -> 84.1108 | I24: =_xlfn.IFNA(VLOOKUP($G24,HAVERD!$A:$FV,I$2,FALSE),"") -> 76.95 | J24: =_xlfn.IFNA(VLOOKUP($G24,HAVERD!$A:$FV,J$2,FALSE),"") -> 1.2641 | K24: =_xlfn.IFNA(VLOOKUP($G24,HAVERD!$A:$FV,K$2,FALSE),"") -> 0
A25: =A8 -> 45667 | B25: =VLOOKUP($A25,HAVERD!$A:$FV,B$2,FALSE) -> 82.8108 | C25: =VLOOKUP($A25,HAVERD!$A:$FV,C$2,FALSE) -> 79.76 | D25: =VLOOKUP($A25,HAVERD!$A:$FV,D$2,FALSE) -> 1.223 | E25: =VLOOKUP($A25,HAVERD!$A:$FV,E$2,FALSE) -> 65.21668 | G25: =G8 -> 45709 | H25: =_xlfn.IFNA(VLOOKUP($G25,HAVERD!$A:$FV,H$2,FALSE),"") -> 84.1895 | I25: =_xlfn.IFNA(VLOOKUP($G25,HAVERD!$A:$FV,I$2,FALSE),"") -> 74.88 | J25: =_xlfn.IFNA(VLOOKUP($G25,HAVERD!$A:$FV,J$2,FALSE),"") -> 1.2638 | K25: =_xlfn.IFNA(VLOOKUP($G25,HAVERD!$A:$FV,K$2,FALSE),"") -> 0
A26: =A9 -> 45670 | B26: =VLOOKUP($A26,HAVERD!$A:$FV,B$2,FALSE) -> 82.5152 | C26: =VLOOKUP($A26,HAVERD!$A:$FV,C$2,FALSE) -> 82.69 | D26: =VLOOKUP($A26,HAVERD!$A:$FV,D$2,FALSE) -> 1.2152 | E26: =VLOOKUP($A26,HAVERD!$A:$FV,E$2,FALSE) -> 68.046412 | G26: =G9 -> 45712 | H26: =_xlfn.IFNA(VLOOKUP($G26,HAVERD!$A:$FV,H$2,FALSE),"") -> 83.9928 | I26: =_xlfn.IFNA(VLOOKUP($G26,HAVERD!$A:$FV,I$2,FALSE),"") -> 74.89 | J26: =_xlfn.IFNA(VLOOKUP($G26,HAVERD!$A:$FV,J$2,FALSE),"") -> 1.2621 | K26: =_xlfn.IFNA(VLOOKUP($G26,HAVERD!$A:$FV,K$2,FALSE),"") -> 0
A27: =A10 -> 45671 | B27: =VLOOKUP($A27,HAVERD!$A:$FV,B$2,FALSE) -> 82.4118 | C27: =VLOOKUP($A27,HAVERD!$A:$FV,C$2,FALSE) -> 82.39 | D27: =VLOOKUP($A27,HAVERD!$A:$FV,D$2,FALSE) -> 1.2201 | E27: =VLOOKUP($A27,HAVERD!$A:$FV,E$2,FALSE) -> 67.527252 | G27: =G10 -> 45713 | H27: =_xlfn.IFNA(VLOOKUP($G27,HAVERD!$A:$FV,H$2,FALSE),"") -> 84.1297 | I27: =_xlfn.IFNA(VLOOKUP($G27,HAVERD!$A:$FV,I$2,FALSE),"") -> 73.11 | J27: =_xlfn.IFNA(VLOOKUP($G27,HAVERD!$A:$FV,J$2,FALSE),"") -> 1.2655 | K27: =_xlfn.IFNA(VLOOKUP($G27,HAVERD!$A:$FV,K$2,FALSE),"") -> 0
A28: =A11 -> 45672 | B28: =VLOOKUP($A28,HAVERD!$A:$FV,B$2,FALSE) -> 82.6918 | C28: =VLOOKUP($A28,HAVERD!$A:$FV,C$2,FALSE) -> 83.48 | D28: =VLOOKUP($A28,HAVERD!$A:$FV,D$2,FALSE) -> 1.2258 | E28: =VLOOKUP($A28,HAVERD!$A:$FV,E$2,FALSE) -> 68.102464 | G28: =G11 -> 45714 | H28: =_xlfn.IFNA(VLOOKUP($G28,HAVERD!$A:$FV,H$2,FALSE),"") -> 84.3909 | I28: =_xlfn.IFNA(VLOOKUP($G28,HAVERD!$A:$FV,I$2,FALSE),"") -> 73.49 | J28: =_xlfn.IFNA(VLOOKUP($G28,HAVERD!$A:$FV,J$2,FALSE),"") -> 1.2695 | K28: =_xlfn.IFNA(VLOOKUP($G28,HAVERD!$A:$FV,K$2,FALSE),"") -> 0
A29: =A12 -> 45673 | B29: =VLOOKUP($A29,HAVERD!$A:$FV,B$2,FALSE) -> 82.5585 | C29: =VLOOKUP($A29,HAVERD!$A:$FV,C$2,FALSE) -> 82.39 | D29: =VLOOKUP($A29,HAVERD!$A:$FV,D$2,FALSE) -> 1.2235 | E29: =VLOOKUP($A29,HAVERD!$A:$FV,E$2,FALSE) -> 67.3396 | G29: =G12 -> 45715 | H29: =_xlfn.IFNA(VLOOKUP($G29,HAVERD!$A:$FV,H$2,FALSE),"") -> 84.4341 | I29: =_xlfn.IFNA(VLOOKUP($G29,HAVERD!$A:$FV,I$2,FALSE),"") -> 75.01 | J29: =_xlfn.IFNA(VLOOKUP($G29,HAVERD!$A:$FV,J$2,FALSE),"") -> 1.2628 | K29: =_xlfn.IFNA(VLOOKUP($G29,HAVERD!$A:$FV,K$2,FALSE),"") -> 0
A30: =A13 -> 45674 | B30: =VLOOKUP($A30,HAVERD!$A:$FV,B$2,FALSE) -> 82.3222 | C30: =VLOOKUP($A30,HAVERD!$A:$FV,C$2,FALSE) -> 83.02 | D30: =VLOOKUP($A30,HAVERD!$A:$FV,D$2,FALSE) -> 1.2198 | E30: =VLOOKUP($A30,HAVERD!$A:$FV,E$2,FALSE) -> 68.060338 | G30: =G13 -> 45716 | H30: =_xlfn.IFNA(VLOOKUP($G30,HAVERD!$A:$FV,H$2,FALSE),"") -> 84.3066 | I30: =_xlfn.IFNA(VLOOKUP($G30,HAVERD!$A:$FV,I$2,FALSE),"") -> 74.76 | J30: =_xlfn.IFNA(VLOOKUP($G30,HAVERD!$A:$FV,J$2,FALSE),"") -> 1.2592 | K30: =_xlfn.IFNA(VLOOKUP($G30,HAVERD!$A:$FV,K$2,FALSE),"") -> 0
A31: =A14 -> 45677 | B31: =VLOOKUP($A31,HAVERD!$A:$FV,B$2,FALSE) -> 82.4225 | C31: =VLOOKUP($A31,HAVERD!$A:$FV,C$2,FALSE) -> 81.68 | D31: =VLOOKUP($A31,HAVERD!$A:$FV,D$2,FALSE) -> 1.2293 | E31: =VLOOKUP($A31,HAVERD!$A:$FV,E$2,FALSE) -> 66.444318 | G31: =G14 -> 45719 | H31: =_xlfn.IFNA(VLOOKUP($G31,HAVERD!$A:$FV,H$2,FALSE),"") -> 84.6563 | I31: =_xlfn.IFNA(VLOOKUP($G31,HAVERD!$A:$FV,I$2,FALSE),"") -> 72.85 | J31: =_xlfn.IFNA(VLOOKUP($G31,HAVERD!$A:$FV,J$2,FALSE),"") -> 1.2699 | K31: =_xlfn.IFNA(VLOOKUP($G31,HAVERD!$A:$FV,K$2,FALSE),"") -> 0
A32: =A15 -> 45678 | B32: =VLOOKUP($A32,HAVERD!$A:$FV,B$2,FALSE) -> 82.4474 | C32: =VLOOKUP($A32,HAVERD!$A:$FV,C$2,FALSE) -> 80.57 | D32: =VLOOKUP($A32,HAVERD!$A:$FV,D$2,FALSE) -> 1.2299 | E32: =VLOOKUP($A32,HAVERD!$A:$FV,E$2,FALSE) -> 65.509391 | G32: =G15 -> 45720 | H32: =_xlfn.IFNA(VLOOKUP($G32,HAVERD!$A:$FV,H$2,FALSE),"") -> 84.5454 | I32: =_xlfn.IFNA(VLOOKUP($G32,HAVERD!$A:$FV,I$2,FALSE),"") -> 72.31 | J32: =_xlfn.IFNA(VLOOKUP($G32,HAVERD!$A:$FV,J$2,FALSE),"") -> 1.2716 | K32: =_xlfn.IFNA(VLOOKUP($G32,HAVERD!$A:$FV,K$2,FALSE),"") -> 0
A33: =A16 -> 45679 | B33: =VLOOKUP($A33,HAVERD!$A:$FV,B$2,FALSE) -> 82.4974 | C33: =VLOOKUP($A33,HAVERD!$A:$FV,C$2,FALSE) -> 80 | D33: =VLOOKUP($A33,HAVERD!$A:$FV,D$2,FALSE) -> 1.2318 | E33: =VLOOKUP($A33,HAVERD!$A:$FV,E$2,FALSE) -> 64.945608 | G33: =G16 -> 45721 | H33: =_xlfn.IFNA(VLOOKUP($G33,HAVERD!$A:$FV,H$2,FALSE),"") -> 84.5349 | I33: =_xlfn.IFNA(VLOOKUP($G33,HAVERD!$A:$FV,I$2,FALSE),"") -> 70.92 | J33: =_xlfn.IFNA(VLOOKUP($G33,HAVERD!$A:$FV,J$2,FALSE),"") -> 1.2868 | K33: =_xlfn.IFNA(VLOOKUP($G33,HAVERD!$A:$FV,K$2,FALSE),"") -> 0
A34: =A17 -> 45680 | B34: =VLOOKUP($A34,HAVERD!$A:$FV,B$2,FALSE) -> 82.6385 | C34: =VLOOKUP($A34,HAVERD!$A:$FV,C$2,FALSE) -> 78.62 | D34: =VLOOKUP($A34,HAVERD!$A:$FV,D$2,FALSE) -> 1.2324 | E34: =VLOOKUP($A34,HAVERD!$A:$FV,E$2,FALSE) -> 63.794223 | G34: =G17 -> 45722 | H34: =_xlfn.IFNA(VLOOKUP($G34,HAVERD!$A:$FV,H$2,FALSE),"") -> 84.459 | I34: =_xlfn.IFNA(VLOOKUP($G34,HAVERD!$A:$FV,I$2,FALSE),"") -> 71.08 | J34: =_xlfn.IFNA(VLOOKUP($G34,HAVERD!$A:$FV,J$2,FALSE),"") -> 1.2891 | K34: =_xlfn.IFNA(VLOOKUP($G34,HAVERD!$A:$FV,K$2,FALSE),"") -> 0
... A37: =A20 -> 45685 | B37: =VLOOKUP($A37,HAVERD!$A:$FV,B$2,FALSE) -> 83.2352 | C37: =VLOOKUP($A37,HAVERD!$A:$FV,C$2,FALSE) -> 78.01 | D37: =VLOOKUP($A37,HAVERD!$A:$FV,D$2,FALSE) -> 1.2432 | E37: =VLOOKUP($A37,HAVERD!$A:$FV,E$2,FALSE) -> 0 | G37: =G20 -> 45727 | H37: =_xlfn.IFNA(VLOOKUP($G37,HAVERD!$A:$FV,H$2,FALSE),"") | I37: =_xlfn.IFNA(VLOOKUP($G37,HAVERD!$A:$FV,I$2,FALSE),"") | J37: =_xlfn.IFNA(VLOOKUP($G37,HAVERD!$A:$FV,J$2,FALSE),"") | K37: =_xlfn.IFNA(VLOOKUP($G37,HAVERD!$A:$FV,K$2,FALSE),"")
A38: Average | B38: =AVERAGE(B23:B37) -> 82.747187 | C38: =AVERAGE(C23:C37) -> 80.295333 | D38: =AVERAGE(D23:D37) -> 1.23028 | E38: =AVERAGE(E23:E37) -> 61.096936 | G38: Average | H38: =AVERAGE(H23:H37) -> 78.306793 | I38: =AVERAGE(I23:I37) -> 68.505714 | J38: =AVERAGE(J23:J37) -> 1.1797 | K38: =AVERAGE(K23:K37) -> 0
G40: % diff | H40: =100*((H38/B38)-1) -> -5.3662173 | I40: =100*((I38/C38)-1) -> -14.68282 | J40: =100*((J38/D38)-1) -> -4.1112592 | K40: =100*((K38/E38)-1) -> -100

Sheet MPR Chart 2.16 (Aug)
A1: Section 2: Current economic conditions
A3: Chart 2.16 - Contributions to CPI inflation
B5: Contributions | H5: Inflation rates
A6: Date | B6: Food | C6: Electricity and gas | D6: Fuels and lubricants | E6: Other goods | F6: Services | H6: Food | I6: Electricity and gas | J6: Fuels and lubricants | K6: Other goods | L6: Services | M6: Total CPI
A7: 44227 | B7: -0.1 | C7: -0.3 | D7: -0.3 | E7: 0.4 | F7: 0.8 | H7: -0.7 | I7: -8.4 | J7: -8.2 | K7: 1.4 | L7: 1.7 | M7: 0.7
A8: 44255 | B8: 0 | C8: -0.3 | D8: -0.1 | E8: 0.1 | F8: 0.7 | H8: -0.6 | I8: -7.9 | J8: -3.5 | K8: 0.5 | L8: 1.5 | M8: 0.4
A9: 44286 | B9: -0.1 | C9: -0.2 | D9: 0.1 | E9: 0.3 | F9: 0.7 | H9: -1.4 | I9: -7.3 | J9: 3.5 | K9: 0.9 | L9: 1.5 | M9: 0.7
A10: 44316 | B10: 0 | C10: 0.1 | D10: 0.4 | E10: 0.4 | F10: 0.7 | H10: -0.4 | I10: 2.4 | J10: 13.6 | K10: 1.2 | L10: 1.6 | M10: 1.5
A11: 44347 | B11: -0.1 | C11: 0.1 | D11: 0.5 | E11: 0.8 | F11: 0.9 | H11: -1.3 | I11: 2.6 | J11: 17.9 | K11: 2.2 | L11: 1.9 | M11: 2.1
A12: 44377 | B12: 0 | C12: 0.1 | D12: 0.5 | E12: 1 | F12: 0.9 | H12: -0.6 | I12: 2.5 | J12: 20.3 | K12: 2.7 | L12: 2.1 | M12: 2.5
A13: 44408 | B13: -0.1 | C13: 0.1 | D13: 0.5 | E13: 0.8 | F13: 0.7 | H13: -0.6 | I13: 2.6 | J13: 17.7 | K13: 2.3 | L13: 1.6 | M13: 2
A14: 44439 | B14: 0.1 | C14: 0.1 | D14: 0.5 | E14: 1.2 | F14: 1.4 | H14: 0.3 | I14: 2.6 | J14: 17.7 | K14: 3.2 | L14: 3 | M14: 3.2
A15: 44469 | B15: 0.1 | C15: 0.1 | D15: 0.5 | E15: 1.3 | F15: 1.1 | H15: 0.8 | I15: 2.8 | J15: 17.8 | K15: 3.3 | L15: 2.6 | M15: 3.1
A16: 44500 | B16: 0.2 | C16: 0.8 | D16: 0.6 | E16: 1.3 | F16: 1.4 | H16: 1.2 | I16: 22.9 | J16: 21.5 | K16: 3.4 | L16: 3.2 | M16: 4.2
A17: 44530 | B17: 0.3 | C17: 0.8 | D17: 0.7 | E17: 1.9 | F17: 1.5 | H17: 2.5 | I17: 23.2 | J17: 28.5 | K17: 4.8 | L17: 3.3 | M17: 5.1
A18: 44561 | B18: 0.5 | C18: 0.7 | D18: 0.7 | E18: 2 | F18: 1.5 | H18: 4.2 | I18: 22.7 | J18: 26.8 | K18: 5 | L18: 3.4 | M18: 5.4
... A48: 45444 | B48: 0.2 | C48: -1.3 | D48: 0.1 | E48: 0.3 | F48: 2.7 | H48: 1.5 | I48: -27.2 | J48: 2.6 | K48: 0.8 | L48: 5.7 | M48: 2
A49: July 2024 (Bank staff projections) | B49: 0.159 | C49: -0.828 | D49: 0.054 | E49: 0.281 | F49: 2.7 | H49: 1.31 | I49: -20.122 | J49: 1.894 | K49: 0.831 | L49: 5.563 | M49: 2.366
A50: August 2024 (Bank staff projections) | B50: 0.156 | C50: -0.838 | D50: -0.024 | E50: 0.245 | F50: 2.827 | H50: 1.313 | I50: -20.372 | J50: -1.018 | K50: 0.735 | L50: 5.84 | M50: 2.367
A51: September 2024 (Bank staff projections) | B51: 0.142 | C51: -0.84 | D51: -0.086 | E51: 0.21 | F51: 2.67 | H51: 1.191 | I51: -20.502 | J51: -3.285 | K51: 0.647 | L51: 5.52 | M51: 2.097
A52: October 2024 (Bank staff projections) | B52: 0.112 | C52: -0.329 | D52: -0.109 | E52: 0.249 | F52: 2.675 | H52: 0.928 | I52: -8.466 | J52: -4.125 | K52: 0.768 | L52: 5.502 | M52: 2.6
A53: November 2024 (Bank staff projections) | B53: 0.091 | C53: -0.324 | D53: -0.025 | E53: 0.396 | F53: 2.625 | H53: 0.764 | I53: -8.329 | J53: -1.368 | K53: 1.207 | L53: 5.395 | M53: 2.763
A54: December 2024 (Bank staff projections) | B54: 0.081 | C54: -0.32 | D54: 0.132 | E54: 0.31 | F54: 2.596 | H54: 0.719 | I54: -8.249 | J54: 4.225 | K54: 0.953 | L54: 5.286 | M54: 2.8
A56: 2025 Q1 (Bank staff projection) | B56: n.a. | C56: n.a. | D56: n.a. | E56: n.a. | F56: n.a. | H56: n.a. | I56: n.a. | J56: n.a. | K56: n.a. | L56: n.a. | M56: 2.67

Sheet MPR Chart 2.16 (May)
A1: Section 2: Current economic conditions
A3: Chart 2.16 - Contributions to CPI inflation
B5: Contributions | H5: Inflation rates
A6: Date | B6: Food | C6: Electricity and gas | D6: Fuels and lubricants | E6: Other goods | F6: Services | H6: Food | I6: Electricity and gas | J6: Fuels and lubricants | K6: Other goods | L6: Services | M6: CPI
A7: 43496 | B7: 0.1 | C7: 0.1 | D7: 0 | E7: 0.5 | F7: 1.2 | H7: 0.9 | I7: 1.4 | J7: 0.7 | K7: 1.4 | L7: 2.5 | M7: 1.8
A8: 43524 | B8: 0.1 | C8: 0.1 | D8: 0 | E8: 0.5 | F8: 1.2 | H8: 1.1 | I8: 1.6 | J8: 0.5 | K8: 1.4 | L8: 2.5 | M8: 1.9
A9: 43555 | B9: 0.1 | C9: 0.1 | D9: 0.1 | E9: 0.5 | F9: 1.2 | H9: 0.8 | I9: 1.5 | J9: 2.9 | K9: 1.3 | L9: 2.5 | M9: 1.9
A10: 43585 | B10: 0.1 | C10: 0.3 | D10: 0.1 | E10: 0.2 | F10: 1.4 | H10: 0.7 | I10: 10.5 | J10: 4.3 | K10: 0.5 | L10: 2.9 | M10: 2.1
A11: 43616 | B11: 0.1 | C11: 0.3 | D11: 0.1 | E11: 0.2 | F11: 1.2 | H11: 1 | I11: 10.4 | J11: 3.4 | K11: 0.7 | L11: 2.6 | M11: 2
A12: 43646 | B12: 0.2 | C12: 0.3 | D12: 0 | E12: 0.3 | F12: 1.2 | H12: 1.6 | I12: 7.9 | J12: 0.7 | K12: 1 | L12: 2.5 | M12: 2
A13: 43677 | B13: 0.1 | C13: 0.2 | D13: 0 | E13: 0.5 | F13: 1.2 | H13: 1.4 | I13: 6.5 | J13: 0.2 | K13: 1.5 | L13: 2.5 | M13: 2.1
A14: 43708 | B14: 0.2 | C14: 0.2 | D14: 0 | E14: 0.3 | F14: 1.1 | H14: 1.8 | I14: 6.5 | J14: -0.1 | K14: 0.8 | L14: 2.2 | M14: 1.7
A15: 43738 | B15: 0.2 | C15: 0.2 | D15: -0.1 | E15: 0.2 | F15: 1.2 | H15: 1.8 | I15: 4.9 | J15: -2.1 | K15: 0.7 | L15: 2.5 | M15: 1.7
A16: 43769 | B16: 0.1 | C16: -0.1 | D16: -0.1 | E16: 0.3 | F16: 1.2 | H16: 1.3 | I16: -1.9 | J16: -3.3 | K16: 0.8 | L16: 2.6 | M16: 1.5
A17: 43799 | B17: 0.2 | C17: -0.1 | D17: -0.1 | E17: 0.2 | F17: 1.2 | H17: 2.1 | I17: -1.7 | J17: -2.9 | K17: 0.7 | L17: 2.5 | M17: 1.5
A18: 43830 | B18: 0.2 | C18: -0.1 | D18: 0 | E18: 0.2 | F18: 1 | H18: 1.7 | I18: -1.6 | J18: 1 | K18: 0.4 | L18: 2.1 | M18: 1.3
... A69: 45352 | B69: 0.5 | C69: -0.9 | D69: -0.1 | E69: 0.9 | F69: 2.8 | H69: 4 | I69: -18.2 | J69: -3.7 | K69: 2.7 | L69: 6 | M69: 3.2
A70: Apr 2024 (Bank staff projections) | B70: 0.306 | C70: -1.262 | D70: 0.007 | E70: 0.416 | F70: 2.598 | H70: 2.529 | I70: -26.609 | J70: -0.274 | K70: 1.24 | L70: 5.52 | M70: 2.064
A71: May 2024 (Bank staff projections) | B71: 0.164 | C71: -1.245 | D71: 0.127 | E71: 0.405 | F71: 2.486 | H71: 1.334 | I71: -26.457 | J71: 3.782 | K71: 1.229 | L71: 5.258 | M71: 1.938
A72: Jun 2024 (Bank staff projections) | B72: 0.171 | C72: -1.239 | D72: 0.235 | E72: 0.377 | F72: 2.442 | H72: 1.423 | I72: -26.397 | J72: 7.722 | K72: 1.143 | L72: 5.134 | M72: 1.987
A73: Jul 2024 (Bank staff projections) | B73: 0.142 | C73: -0.814 | D73: 0.26 | E73: 0.406 | F73: 2.4 | H73: 1.166 | I73: -19.79 | J73: 8.5 | K73: 1.215 | L73: 4.949 | M73: 2.394
A74: Aug 2024 (Bank staff projections) | B74: 0.137 | C74: -0.825 | D74: 0.167 | E74: 0.359 | F74: 2.418 | H74: 1.145 | I74: -20.067 | J74: 4.878 | K74: 1.084 | L74: 5.001 | M74: 2.256
A75: Sep 2024 (Bank staff projections) | B75: 0.125 | C75: -0.828 | D75: 0.068 | E75: 0.334 | F75: 2.285 | H75: 1.033 | I75: -20.207 | J75: 1.339 | K75: 1.024 | L75: 4.728 | M75: 1.984

Sheet MPR Chart 2.21 (Aug)
A1: Section 2: Current economic conditions
A3: Chart 2.21 - Measures of annual pay growth
B5: Quarterly frequency | F5: Monthly frequency
A6: Date | B6: AWE private sector regular pay | C6: Indicator-based model | E6: Date | F6: AWE private sector regular pay | G6: KPMG/REC survey (advanced 12 months) | H6: HMRC RTI private sector median | I6: Indeed Wage Tracker
A7: 2018 Q1 | B7: 3 | C7: 2.9 | E7: 43131 | F7: 2.7 | G7: No permissions | H7: 3.1 | I7: n.a.
A8: 2018 Q2 | B8: 2.8 | C8: 3 | E8: 43159 | F8: 2.9 | H8: 3.2 | I8: n.a.
A9: 2018 Q3 | B9: 3.3 | C9: 3.2 | E9: 43190 | F9: 3 | H9: 3.2 | I9: n.a.
A10: 2018 Q4 | B10: 3.5 | C10: 3.4 | E10: 43220 | F10: 3 | H10: 3 | I10: n.a.
A11: 2019 Q1 | B11: 3.6 | C11: 3.4 | E11: 43251 | F11: 2.9 | H11: 3.2 | I11: n.a.
A12: 2019 Q2 | B12: 3.9 | C12: 3.5 | E12: 43281 | F12: 2.8 | H12: 3.4 | I12: n.a.
A13: 2019 Q3 | B13: 3.7 | C13: 3.4 | E13: 43312 | F13: 3 | H13: 3.7 | I13: n.a.
A14: 2019 Q4 | B14: 3.2 | C14: 3.2 | E14: 43343 | F14: 3.2 | H14: 3.9 | I14: n.a.
A15: 2020 Q1 | B15: 2.5 | C15: 3 | E15: 43373 | F15: 3.3 | H15: 3.8 | I15: n.a.
A16: 2020 Q2 | B16: -1.2 | C16: 2.2 | E16: 43404 | F16: 3.4 | H16: 3.8 | I16: n.a.
A17: 2020 Q3 | B17: 1.4 | C17: 1.4 | E17: 43434 | F17: 3.4 | H17: 3.7 | I17: n.a.
A18: 2020 Q4 | B18: 4 | C18: 1.3 | E18: 43465 | F18: 3.5 | H18: 3.7 | I18: n.a.
A19: 2021 Q1 | B19: 4.3 | C19: 1.1 | E19: 43496 | F19: 3.6 | H19: 3.7 | I19: n.a.
... A31: 2024 Q1 | B31: 5.9 | C31: 5.6 | E31: 43861 | F31: 3 | H31: 3.3 | I31: n.a.
A32: 2024 Q2 (Bank Staff Projection) | B32: 5.141 | C32: n.a. | E32: 43890 | F32: 2.9 | H32: 3.7 | I32: n.a.
A33: 2024 Q3 (Bank Staff Projection) | B33: 4.83 | C33: n.a. | E33: 43921 | F33: 2.5 | H33: 3.2 | I33: n.a.
E34: 43951 | F34: 1.3 | H34: 1.2 | I34: 5.5
E35: 43982 | F35: -0.1 | H35: -1 | I35: 4.6
E36: 44012 | F36: -1.2 | H36: -1.8 | I36: 3.8
E37: 44043 | F37: -0.8 | H37: -0.6 | I37: 3.5
E38: 44074 | F38: 0.1 | H38: 1.2 | I38: 3.2
E39: 44104 | F39: 1.4 | H39: 2.7 | I39: 3.2
E40: 44135 | F40: 2.5 | H40: 3.7 | I40: 3.2
E41: 44165 | F41: 3.3 | H41: 4.3 | I41: 3.2
E42: 44196 | F42: 4 | H42: 4.5 | I42: 3.4
E43: 44227 | F43: 4.1 | H43: 4.3 | I43: 3.6
E44: 44255 | F44: 4.2 | H44: 4 | I44: 3.3
E45: 44286 | F45: 4.3 | H45: 4.5 | I45: 2.8
... E83: 45443 | F83: 5.6 | H83: 6.3 | I83: 6.9
E84: 45473 | F84: n.a. | H84: 6.2 | I84: 6.8

Sheet MPR Chart 2.22 (Nov)
A1: Section 2: Current economic conditions
A3: Chart 2.22 - Contributions to CPI inflation
B5: Contributions | H5: Inflation rates
A6: Date | B6: Food | C6: Electricity and gas | D6: Fuels and lubricants | E6: Other goods | F6: Services | H6: Food | I6: Electricity and gas | J6: Fuels and lubricants | K6: Other goods | L6: Services | M6: Total CPI
A7: 44227 | B7: -0.1 | C7: -0.3 | D7: -0.3 | E7: 0.4 | F7: 0.8 | H7: -0.7 | I7: -8.4 | J7: -8.2 | K7: 1.4 | L7: 1.7 | M7: 0.7
A8: 44255 | B8: 0 | C8: -0.3 | D8: -0.1 | E8: 0.1 | F8: 0.7 | H8: -0.6 | I8: -7.9 | J8: -3.5 | K8: 0.5 | L8: 1.5 | M8: 0.4
A9: 44286 | B9: -0.1 | C9: -0.2 | D9: 0.1 | E9: 0.3 | F9: 0.7 | H9: -1.4 | I9: -7.3 | J9: 3.5 | K9: 0.9 | L9: 1.5 | M9: 0.7
A10: 44316 | B10: 0 | C10: 0.1 | D10: 0.4 | E10: 0.4 | F10: 0.7 | H10: -0.4 | I10: 2.4 | J10: 13.6 | K10: 1.2 | L10: 1.6 | M10: 1.5
A11: 44347 | B11: -0.1 | C11: 0.1 | D11: 0.5 | E11: 0.8 | F11: 0.9 | H11: -1.3 | I11: 2.6 | J11: 17.9 | K11: 2.2 | L11: 1.9 | M11: 2.1
A12: 44377 | B12: 0 | C12: 0.1 | D12: 0.5 | E12: 1 | F12: 0.9 | H12: -0.6 | I12: 2.5 | J12: 20.3 | K12: 2.7 | L12: 2.1 | M12: 2.5
A13: 44408 | B13: -0.1 | C13: 0.1 | D13: 0.5 | E13: 0.8 | F13: 0.7 | H13: -0.6 | I13: 2.6 | J13: 17.7 | K13: 2.3 | L13: 1.6 | M13: 2
A14: 44439 | B14: 0.1 | C14: 0.1 | D14: 0.5 | E14: 1.2 | F14: 1.4 | H14: 0.3 | I14: 2.6 | J14: 17.7 | K14: 3.2 | L14: 3 | M14: 3.2
A15: 44469 | B15: 0.1 | C15: 0.1 | D15: 0.5 | E15: 1.3 | F15: 1.1 | H15: 0.8 | I15: 2.8 | J15: 17.8 | K15: 3.3 | L15: 2.6 | M15: 3.1
A16: 44500 | B16: 0.2 | C16: 0.8 | D16: 0.6 | E16: 1.3 | F16: 1.4 | H16: 1.2 | I16: 22.9 | J16: 21.5 | K16: 3.4 | L16: 3.2 | M16: 4.2
A17: 44530 | B17: 0.3 | C17: 0.8 | D17: 0.7 | E17: 1.9 | F17: 1.5 | H17: 2.5 | I17: 23.2 | J17: 28.5 | K17: 4.8 | L17: 3.3 | M17: 5.1
A18: 44561 | B18: 0.5 | C18: 0.7 | D18: 0.7 | E18: 2 | F18: 1.5 | H18: 4.2 | I18: 22.7 | J18: 26.8 | K18: 5 | L18: 3.4 | M18: 5.4
... A51: 45536 | B51: 0.2 | C51: -0.8 | D51: -0.3 | E51: 0.2 | F51: 2.4 | H51: 1.9 | I51: -20.7 | J51: -10.4 | K51: 0.8 | L51: 4.9 | M51: 1.7
A52: October 2024 (Bank staff projections) | B52: 0.156 | C52: -0.275 | D52: -0.435 | E52: 0.319 | F52: 2.416 | H52: 1.319 | I52: -7.075 | J52: -13.738 | K52: 0.982 | L52: 4.972 | M52: 2.182
A53: November 2024 (Bank staff projections) | B53: 0.131 | C53: -0.269 | D53: -0.319 | E53: 0.49 | F53: 2.389 | H53: 1.121 | I53: -6.902 | J53: -10.245 | K53: 1.496 | L53: 4.913 | M53: 2.423
A54: December 2024 (Bank staff projections) | B54: 0.125 | C54: -0.264 | D54: -0.116 | E54: 0.391 | F54: 2.327 | H54: 1.105 | I54: -6.809 | J54: -3.718 | K54: 1.2 | L54: 4.739 | M54: 2.463
A55: January 2025 (Bank staff projections) | B55: 0.117 | C55: -0.443 | D55: -0.012 | E55: 0.326 | F55: 2.51 | H55: 1.038 | I55: -10.859 | J55: -0.477 | K55: 1.017 | L55: 5.112 | M55: 2.498
A56: February 2025 (Bank staff projections) | B56: 0.118 | C56: -0.445 | D56: -0.043 | E56: 0.38 | F56: 2.432 | H56: 1.048 | I56: -10.973 | J56: -1.475 | K56: 1.172 | L56: 4.965 | M56: 2.443
A57: March 2025 (Bank staff projections) | B57: 0.116 | C57: -0.437 | D57: -0.081 | E57: 0.384 | F57: 2.391 | H57: 1.031 | I57: -10.841 | J57: -2.668 | K57: 1.17 | L57: 4.894 | M57: 2.373

Sheet MPR Chart 2.29 (Nov)
A1: Section 2: Current economic conditions
A3: Chart 2.29 - Measures of annual private sector wage growth
A5: Date | B5: AWE private sector regular pay | C5: Indicator-based model | E5: Date | F5: AWE private sector regular pay | G5: KPMG/REC survey (advanced 12 months) | H5: HMRC RTI private sector median | I5: Indeed Wage Tracker
A6: 2018 Q1 | B6: 3 | C6: 2.8 | E6: 43131 | F6: 2.7 | G6: No permission | H6: 3.1 | I6: n.a.
A7: 2018 Q2 | B7: 2.8 | C7: 3 | E7: 43159 | F7: 2.9 | H7: 3.3 | I7: n.a.
A8: 2018 Q3 | B8: 3.3 | C8: 3.2 | E8: 43190 | F8: 3 | H8: 3.2 | I8: n.a.
A9: 2018 Q4 | B9: 3.5 | C9: 3.4 | E9: 43220 | F9: 3 | H9: 2.9 | I9: n.a.
A10: 2019 Q1 | B10: 3.6 | C10: 3.4 | E10: 43251 | F10: 2.9 | H10: 3.1 | I10: n.a.
A11: 2019 Q2 | B11: 3.9 | C11: 3.5 | E11: 43281 | F11: 2.8 | H11: 3.4 | I11: n.a.
A12: 2019 Q3 | B12: 3.7 | C12: 3.4 | E12: 43312 | F12: 3 | H12: 3.8 | I12: n.a.
A13: 2019 Q4 | B13: 3.2 | C13: 3.2 | E13: 43343 | F13: 3.2 | H13: 3.9 | I13: n.a.
A14: 2020 Q1 | B14: 2.5 | C14: 3 | E14: 43373 | F14: 3.3 | H14: 3.7 | I14: n.a.
A15: 2020 Q2 | B15: -1.2 | C15: 2.2 | E15: 43404 | F15: 3.4 | H15: 3.8 | I15: n.a.
A16: 2020 Q3 | B16: 1.4 | C16: 1.3 | E16: 43434 | F16: 3.4 | H16: 3.7 | I16: n.a.
A17: 2020 Q4 | B17: 4 | C17: 1.1 | E17: 43465 | F17: 3.5 | H17: 3.7 | I17: n.a.
A18: 2021 Q1 | B18: 4.3 | C18: 0.9 | E18: 43496 | F18: 3.6 | H18: 3.7 | I18: n.a.
... A31: 2024 Q2 | B31: 5.3 | C31: 5.2 | E31: 43890 | F31: 2.9 | H31: 3.7 | I31: n.a.
A32: 2024 Q3 (Bank Staff Projection) | B32: 4.753 | C32: n.a. | E32: 43921 | F32: 2.5 | H32: 3.3 | I32: n.a.
A33: 2024 Q4 (Bank Staff Projection) | B33: 5.065 | C33: n.a. | E33: 43951 | F33: 1.3 | H33: 1.3 | I33: 5.5
A34: 2025 Q1 (Bank Staff Projection) | B34: 4.76 | C34: n.a. | E34: 43982 | F34: -0.1 | H34: -1 | I34: 4.6
A35: 2025 Q2 (Bank Staff Projection) | B35: 3.935 | C35: n.a. | E35: 44012 | F35: -1.2 | H35: -1.9 | I35: 3.8
A36: 2025 Q3 (Bank Staff Projection) | B36: 3.512 | C36: n.a. | E36: 44043 | F36: -0.8 | H36: -0.6 | I36: 3.5
A37: 2025 Q4 (Bank Staff Projection) | B37: 3.238 | C37: n.a. | E37: 44074 | F37: 0.1 | H37: 1.3 | I37: 3.2
E38: 44104 | F38: 1.4 | H38: 2.8 | I38: 3.2
E39: 44135 | F39: 2.5 | H39: 3.8 | I39: 3.2
E40: 44165 | F40: 3.3 | H40: 4.3 | I40: 3.2
E41: 44196 | F41: 4 | H41: 4.5 | I41: 3.4
E42: 44227 | F42: 4.1 | H42: 4.3 | I42: 3.6
E43: 44255 | F43: 4.2 | H43: 4.1 | I43: 3.3
E44: 44286 | F44: 4.3 | H44: 4.5 | I44: 2.8
E45: 44316 | F45: 5.7 | H45: 7 | I45: 0.3
E46: 44347 | F46: 7.2 | H46: 9.4 | I46: 1.3
E47: 44377 | F47: 8.4 | H47: 10.9 | I47: 2.5
E48: 44408 | F48: 7.8 | H48: 9.5 | I48: 3.4
E49: 44439 | F49: 6.7 | H49: 7.8 | I49: 3.7
... E85: 45535 | F85: 4.8 | H85: 6.1 | I85: 6.8
E86: 45565 | F86: n.a. | H86: 5.8 | I86: 6.8

Sheet MPR Chart 2.20 (Feb)
A1: Section 2: Current economic conditions
A3: 2.20 - Annual inflation rates for components of CPI, per cent
B5: Inflation rates
A6: Date | B6: Services | C6: Core goods | D6: Food and non-alcoholic beverages
A7: 2010-19 averages | B7: 3 | C7: 0.8 | D7: 1.6
A9: 43861 | B9: 2.3 | C9: 0.5 | D9: 1.4
A10: 43890 | B10: 2.5 | C10: 0.4 | D10: 1.2
A11: 43921 | B11: 2.5 | C11: 0.2 | D11: 1.3
A12: 43951 | B12: 2 | C12: 0.5 | D12: 1.3
A13: 43982 | B13: 1.9 | C13: 0.1 | D13: 1.8
A14: 44012 | B14: 1.8 | C14: 0.9 | D14: 1.1
A15: 44043 | B15: 2.1 | C15: 1.3 | D15: 0.8
A16: 44074 | B16: 0.6 | C16: 1.2 | D16: 0.4
A17: 44104 | B17: 1.4 | C17: 1 | D17: -0.1
A18: 44135 | B18: 1.4 | C18: 1.6 | D18: 0.6
A19: 44165 | B19: 1.4 | C19: 0.6 | D19: -0.6
A20: 44196 | B20: 1.5 | C20: 1.2 | D20: -1.4
... A68: 45627 | B68: 4.4 | C68: 1.2 | D68: 2
A69: January 2025 (Bank staff projections) | B69: 5.161 | C69: 1.128 | D69: 2.389
A70: February 2025 (Bank staff projections) | B70: 5.066 | C70: 1.213 | D70: 2.732
A71: March 2025 (Bank staff projections) | B71: 4.926 | C71: 1.168 | D71: 2.564
A72: April 2025 (Bank staff projections) | B72: 5.077 | C72: 1.529 | D72: 2.738
A73: May 2025 (Bank staff projections) | B73: 4.782 | C73: 1.734 | D73: 3.183
A74: June 2025 (Bank staff projections) | B74: 4.651 | C74: 1.744 | D74: 3.076

Sheet MPR Chart 2.22 (Feb)
A1: Section 2: Current economic conditions
A3: Chart 2.22 - Measures of annual private sector wage growth, per cent
B5: Quarterly | G5: Monthly
A6: Date | B6: Indicator-based model | C6: Private sector regular pay forecast | D6: BOE Agents' pay survey - expected settlements | F6: Date | G6: Private sector regular pay | H6: BOE DMP survey - one-year ahead wage expectation
A7: 2018 Q1 | B7: 2.8 | C7: n.a. | D7: n.a. | F7: 43101 | G7: 2.7 | H7: n.a.
A8: 2018 Q2 | B8: 3 | C8: n.a. | D8: n.a. | F8: 43159 | G8: 2.9 | H8: n.a.
A9: 2018 Q3 | B9: 3.2 | C9: n.a. | D9: n.a. | F9: 43190 | G9: 3 | H9: n.a.
A10: 2018 Q4 | B10: 3.4 | C10: n.a. | D10: n.a. | F10: 43220 | G10: 3 | H10: n.a.
A11: 2019 Q1 | B11: 3.4 | C11: n.a. | D11: n.a. | F11: 43251 | G11: 2.9 | H11: n.a.
A12: 2019 Q2 | B12: 3.5 | C12: n.a. | D12: n.a. | F12: 43281 | G12: 2.8 | H12: n.a.
A13: 2019 Q3 | B13: 3.4 | C13: n.a. | D13: n.a. | F13: 43312 | G13: 3 | H13: n.a.
A14: 2019 Q4 | B14: 3.2 | C14: n.a. | D14: n.a. | F14: 43343 | G14: 3.2 | H14: n.a.
A15: 2020 Q1 | B15: 3 | C15: n.a. | D15: n.a. | F15: 43373 | G15: 3.3 | H15: n.a.
A16: 2020 Q2 | B16: 2 | C16: n.a. | D16: n.a. | F16: 43404 | G16: 3.4 | H16: n.a.
A17: 2020 Q3 | B17: 1.2 | C17: n.a. | D17: n.a. | F17: 43434 | G17: 3.4 | H17: n.a.
A18: 2020 Q4 | B18: 1 | C18: n.a. | D18: n.a. | F18: 43465 | G18: 3.5 | H18: n.a.
... A33: 2024 Q3 | B33: 5.1 | C33: n.a. | D33: n.a. | F33: 43921 | G33: 2.5 | H33: n.a.
A34: 2024 Q4 (Bank Staff Projections) | B34: 5.2 | C34: 6.292 | D34: n.a. | F34: 43951 | G34: 1.3 | H34: n.a.
A35: 2025 Q1 (Bank Staff Projections) | B35: n.a. | C35: 6.224 | D35: n.a. | F35: 43982 | G35: -0.1 | H35: n.a.
A36: 2025 Q2 (Bank Staff Projections) | B36: n.a. | C36: 5.669 | D36: n.a. | F36: 44012 | G36: -1.2 | H36: n.a.
A37: 2025 Q3 (Bank Staff Projections) | B37: n.a. | C37: 5.157 | D37: n.a. | F37: 44043 | G37: -0.8 | H37: n.a.
A38: 2025 Q4 (Bank Staff Projections) | B38: n.a. | C38: 3.867 | D38: 3.7 | F38: 44074 | G38: 0.1 | H38: n.a.
F39: 44104 | G39: 1.4 | H39: n.a.
F40: 44135 | G40: 2.5 | H40: n.a.
F41: 44165 | G41: 3.3 | H41: n.a.
F42: 44196 | G42: 4 | H42: n.a.
F43: 44227 | G43: 4.1 | H43: n.a.
F44: 44255 | G44: 4.2 | H44: n.a.
F45: 44286 | G45: 4.3 | H45: n.a.
F46: 44316 | G46: 5.7 | H46: n.a.
F47: 44347 | G47: 7.2 | H47: n.a.
F48: 44377 | G48: 8.4 | H48: n.a.
F49: 44408 | G49: 7.8 | H49: n.a.
F50: 44439 | G50: 6.7 | H50: n.a.
... F89: 45626 | G89: 6 | H89: n.a.
F91: Jan 2026 (Expectation) | G91: n.a. | H91: 3.9

Sheet HAVERM
A1: 1 | B1: =+A1+1 -> 2 | C1: =+B1+1 -> 3 | D1: =+C1+1 -> 4 | E1: =+D1+1 -> 5 | F1: =+E1+1 -> 6 | G1: =+F1+1 -> 7 | H1: =+G1+1 -> 8 | I1: =+H1+1 -> 9 | ... N1: =+M1+1 -> 14
B2: 201001 !M | C2: D7BT@UK | D2: D7F5@UK | E2: KAJ4@UK | F2: UNVDPR1@UK | G2: UNVDPE1@UK | H2: UNVDWR@UK | I2: UNVDWE@UK | J2: UNVDPR3@UK | K2: UNVDPE3@UK | L2: UNVDWR3@UK | M2: UNVDWE3@UK | N2: AGG(R112RD@INTDAILY,EOP)
B3: .DESC | C3: UK: Consumer Price Index: All Items (NSA, 2015=100) | D3: UK: Consumer Price Index: All Services (NSA, 2015=100) | E3: Great Britain: AWE, Regular Pay: Private Sector [3Mo Mvg Avg vs Yr Ago] (SA, %) | F3: UK: BoE DMP: Realized Price Growth Over the Past Year: Single Month (%) | G3: UK: BoE DMP: Expected Price Growth Over the Next Year: Single Month (%) | H3: UK: BoE DMP: Realized Wage Growth Over the Past Year: Single Month (%) | I3: UK: BoE DMP: Expected Wage Growth Over the Next Year: Single Month (%) | J3: UK: BoE DMP: Realized Price Growth Over the Past Year: 3 Month Average (%) | K3: UK: BoE DMP: Expected Price Growth Over the Next Year: 3 Month Average (%) | L3: UK: BoE DMP: Realized Wage Growth Over the Past Year: 3 Month Average (%) | M3: UK: BoE DMP: Expected Wage Growth Over the Next Year: 3 Month Average (%) | N3: United Kingdom: Official Bank Rate (%)
B4: .T1 | C4: Jan-1988 | D4: Jan-1988 | E4: Mar-2001 | F4: Jan-2017 | G4: Jan-2017 | H4: Aug-2017 | I4: Aug-2017 | J4: Jan-2017 | K4: Jan-2017 | L4: Aug-2017 | M4: Aug-2017 | N4: Jan-1954 <- 01-Jan-1954
B5: .TN | C5: Jan-2025 | D5: Jan-2025 | E5: Dec-2024 | F5: Feb-2025 | G5: Feb-2025 | H5: Feb-2025 | I5: Feb-2025 | J5: Feb-2025 | K5: Feb-2025 | L5: Feb-2025 | M5: Feb-2025 | N5: Feb-2025 <- 10-Mar-2025
B6: .LSOURCE | C6: Office for National Statistics | D6: Office for National Statistics | E6: Office for National Statistics | F6: Bank of England | G6: Bank of England | H6: Bank of England | I6: Bank of England | J6: Bank of England | K6: Bank of England | L6: Bank of England | M6: Bank of England | N6: H24
B7: .DTLM | C7: Feb-19-2025 07:02 | D7: Feb-19-2025 07:02 | E7: Feb-18-2025 07:06 | F7: Mar-06-2025 09:31 | G7: Mar-06-2025 09:31 | H7: Mar-06-2025 09:31 | I7: Mar-06-2025 09:31 | J7: Mar-06-2025 09:31 | K7: Mar-06-2025 09:31 | L7: Mar-06-2025 09:31 | M7: Mar-06-2025 09:31 | N7: Mar-10-2025 13:11
