Workbook
Name A: #REF!
Name Data: [1]sheet0!$C$2
Name S: {#N/A,#N/A,FALSE,"CGBR95C"}

Sheet >> CHARTS

Sheet >> DATA

Sheet Chart Data
A1: GDP | G1: GDP | L1: Non-fuel goods exports | Q1: Non-fuel goods exports | V1: Business investment | AC1: Business investment | AH1: Investment | AM1: CPI inflation | AR1: Potential output | AW1: Potential output - April forecast | BH1: Potential output - March forecast
AX2: ESTAR * AVHR | AY2: EDUC / POP15_64 | AZ2: K | BA2: TREND | BB2: YHAT | BC2: GDP | BE2: Potential output | BF2: GDP | BI2: ESTAR * AVHR | BJ2: EDUC / POP15_64 | BK2: K | BL2: TREND | BM2: YHAT | BN2: GDP | BP2: Potential output | BQ2: GDP
B3: April 2025 | C3: March 2025 | D3: January 2025 | H3: April 2025 | I3: March 2025 | M3: April 2025 | N3: March 2025 | R3: April 2025 | S3: March 2025 | W3: April 2025 | X3: March 2025 | Y3: January 2025 | AD3: April 2025 | AE3: March 2025 | AI3: April 2025 | AJ3: March 2025 | AN3: April 2025 | AO3: March 2025 | AP3: 2% target | AS3: April 2025 | AT3: March 2025 | AW3: 1980 | AX3: ='Annual Data'!K14*'Annual Data'!L14 -> 24.76553 | AY3: ='Annual Data'!M14/'Annual Data'!N14 -> 8.4961678 | AZ3: ='Annual Data'!O14 -> 1265800.5 | BA3: ='Annual Data'!P14 -> -7.645228 | BB3: ='Annual Data'!J14 -> 1080987.1 | BC3: ='Annual Data'!B14 -> 1059660 | BH3: 1980 | BI3: ='Annual Data'!Z14*'Annual Data'!AA14 -> 24.76553 | BJ3: ='Annual Data'!AB14/'Annual Data'!AC14 -> 8.4961678 | BK3: ='Annual Data'!AD14 -> 1265800.5 | BL3: ='Annual Data'!AE14 -> -7.645228 | BM3: ='Annual Data'!Y14 -> 1080987.1 | BN3: ='Annual Data'!Q14 -> 1059660
A4: 44927 | B4: ='Quarterly Data'!D207 -> 634428 | C4: ='Quarterly Data'!S207 -> 634807 | D4: ='Quarterly Data'!AH207 -> 634807 | E4: =100*((B4/C4)-1) -> -0.059703185 | G4: 44927 | H4: =100*('Quarterly Data'!D207/'Quarterly Data'!$D$215) -> 98.22544 | I4: =100*('Quarterly Data'!S207/'Quarterly Data'!$S$215) -> 98.723744 | J4: =100*((H4/I4)-1) -> -0.50474555 | L4: 44927 | M4: ='Quarterly Data'!G207 -> 87398 | N4: ='Quarterly Data'!V207 -> 87198 | O4: =100*((M4/N4)-1) -> 0.22936306 | Q4: 44927 | R4: =100*('Quarterly Data'!G207/'Quarterly Data'!$G$215) -> 110.82122 | S4: =100*('Quarterly Data'!V207/'Quarterly Data'!$V$215) -> 114.53659 | T4: =100*((R4/S4)-1) -> -3.2438307 | V4: 44927 | W4: ='Quarterly Data'!K207 -> 62765 | X4: ='Quarterly Data'!Z207 -> 62590 | Y4: ='Quarterly Data'!AO207 -> 62590 | Z4: =100*((W4/X4)-1) -> 0.27959738 | AA4: =100*((W4/Y4)-1) -> 0.27959738 | AC4: 44927 | AD4: =100*('Quarterly Data'!K207/'Quarterly Data'!$K$215) -> 98.297764 | AE4: =100*('Quarterly Data'!Z207/'Quarterly Data'!$Z$215) -> 98.445183 | AF4: =100*((AD4/AE4)-1) -> -0.14974665 | AH4: 44927 | AI4: =100*('Quarterly Data'!J207/'Quarterly Data'!$J$215) -> 99.433535 | AJ4: =100*('Quarterly Data'!Y207/'Quarterly Data'!$Y$215) -> 101.25094 | AK4: =100*((AI4/AJ4)-1) -> -1.7949539 | AM4: 44927 | AN4: =100*(('Quarterly Data'!E207/'Quarterly Data'!E203)-1) -> 10.178266 | AO4: =100*(('Quarterly Data'!T207/'Quarterly Data'!T203)-1) -> 10.178266 | AP4: 2 | AR4: 44927 | AS4: ='Quarterly Data'!L207 -> 628265.6 | AT4: ='Quarterly Data'!AA207 -> 628224.8 | AU4: =100*((AS4/AT4)-1) -> 0.0064944905 | AW4: 1981 | AX4: ='Annual Data'!K15*'Annual Data'!L15 -> 24.65965 | AY4: ='Annual Data'!M15/'Annual Data'!N15 -> 8.5228977 | AZ4: ='Annual Data'!O15 -> 1278218.5 | BA4: ='Annual Data'!P15 -> -7.595809 | BB4: ='Annual Data'!J15 -> 1096885.7 | BC4: ='Annual Data'!B15 -> 1052374 | BE4: =100*((BB4/BB3)-1) -> 1.4707484 | BF4: =100*((BC4/BC3)-1) -> -0.68757903 | BH4: 1981 | BI4: ='Annual Data'!Z15*'Annual Data'!AA15 -> 24.65965 | BJ4: ='Annual Data'!AB15/'Annual Data'!AC15 -> 8.5228977 | BK4: ='Annual Data'!AD15 -> 1278218.5 | BL4: ='Annual Data'!AE15 -> -7.595809 | BM4: ='Annual Data'!Y15 -> 1096885.7 | BN4: ='Annual Data'!Q15 -> 1052374 | BP4: =100*((BM4/BM3)-1) -> 1.4707484 | BQ4: =100*((BN4/BN3)-1) -> -0.68757903
A5: 45017 | B5: ='Quarterly Data'!D208 -> 634694 | C5: ='Quarterly Data'!S208 -> 634866 | D5: ='Quarterly Data'!AH208 -> 634866 | E5: =100*((B5/C5)-1) -> -0.027092331 | G5: 45017 | H5: =100*('Quarterly Data'!D208/'Quarterly Data'!$D$215) -> 98.266624 | I5: =100*('Quarterly Data'!S208/'Quarterly Data'!$S$215) -> 98.732919 | J5: =100*((H5/I5)-1) -> -0.47227992 | L5: 45017 | M5: ='Quarterly Data'!G208 -> 87193 | N5: ='Quarterly Data'!V208 -> 87228 | O5: =100*((M5/N5)-1) -> -0.040124731 | Q5: 45017 | R5: =100*('Quarterly Data'!G208/'Quarterly Data'!$G$215) -> 110.56128 | S5: =100*('Quarterly Data'!V208/'Quarterly Data'!$V$215) -> 114.576 | T5: =100*((R5/S5)-1) -> -3.50398 | V5: 45017 | W5: ='Quarterly Data'!K208 -> 63006 | X5: ='Quarterly Data'!Z208 -> 63199 | Y5: ='Quarterly Data'!AO208 -> 63199 | Z5: =100*((W5/X5)-1) -> -0.30538458 | AA5: =100*((W5/Y5)-1) -> -0.30538458 | AC5: 45017 | AD5: =100*('Quarterly Data'!K208/'Quarterly Data'!$K$215) -> 98.6752 | AE5: =100*('Quarterly Data'!Z208/'Quarterly Data'!$Z$215) -> 99.403053 | AF5: =100*((AD5/AE5)-1) -> -0.73222403 | AH5: 45017 | AI5: =100*('Quarterly Data'!J208/'Quarterly Data'!$J$215) -> 97.968315 | AJ5: =100*('Quarterly Data'!Y208/'Quarterly Data'!$Y$215) -> 100.05864 | AK5: =100*((AI5/AJ5)-1) -> -2.0891047 | AM5: 45017 | AN5: =100*(('Quarterly Data'!E208/'Quarterly Data'!E204)-1) -> 8.439049 | AO5: =100*(('Quarterly Data'!T208/'Quarterly Data'!T204)-1) -> 8.439049 | AP5: 2 | AR5: 45017 | AS5: ='Quarterly Data'!L208 -> 629361.4 | AT5: ='Quarterly Data'!AA208 -> 630809.5 | AU5: =100*((AS5/AT5)-1) -> -0.22956217 | AW5: 1982 | AX5: ='Annual Data'!K16*'Annual Data'!L16 -> 24.297707 | AY5: ='Annual Data'!M16/'Annual Data'!N16 -> 8.5398115 | AZ5: ='Annual Data'!O16 -> 1288706.5 | BA5: ='Annual Data'!P16 -> -7.546708 | BB5: ='Annual Data'!J16 -> 1103412.6 | BC5: ='Annual Data'!B16 -> 1073055 | BE5: =100*((BB5/BB4)-1) -> 0.59503921 | BF5: =100*((BC5/BC4)-1) -> 1.9651759 | BH5: 1982 | BI5: ='Annual Data'!Z16*'Annual Data'!AA16 -> 24.297707 | BJ5: ='Annual Data'!AB16/'Annual Data'!AC16 -> 8.5398115 | BK5: ='Annual Data'!AD16 -> 1288706.5 | BL5: ='Annual Data'!AE16 -> -7.546708 | BM5: ='Annual Data'!Y16 -> 1103412.6 | BN5: ='Annual Data'!Q16 -> 1073055 | BP5: =100*((BM5/BM4)-1) -> 0.59503921 | BQ5: =100*((BN5/BN4)-1) -> 1.9651759
A6: 45108 | B6: ='Quarterly Data'!D209 -> 634327 | C6: ='Quarterly Data'!S209 -> 634052 | D6: ='Quarterly Data'!AH209 -> 634052 | E6: =100*((B6/C6)-1) -> 0.043371837 | G6: 45108 | H6: =100*('Quarterly Data'!D209/'Quarterly Data'!$D$215) -> 98.209803 | I6: =100*('Quarterly Data'!S209/'Quarterly Data'!$S$215) -> 98.606328 | J6: =100*((H6/I6)-1) -> -0.40212953 | L6: 45108 | M6: ='Quarterly Data'!G209 -> 83160 | N6: ='Quarterly Data'!V209 -> 83531 | O6: =100*((M6/N6)-1) -> -0.44414648 | Q6: 45108 | R6: =100*('Quarterly Data'!G209/'Quarterly Data'!$G$215) -> 105.44741 | S6: =100*('Quarterly Data'!V209/'Quarterly Data'!$V$215) -> 109.7199 | T6: =100*((R6/S6)-1) -> -3.8940014 | V6: 45108 | W6: ='Quarterly Data'!K209 -> 61551 | X6: ='Quarterly Data'!Z209 -> 61724 | Y6: ='Quarterly Data'!AO209 -> 61724 | Z6: =100*((W6/X6)-1) -> -0.28027996 | AA6: =100*((W6/Y6)-1) -> -0.28027996 | AC6: 45108 | AD6: =100*('Quarterly Data'!K209/'Quarterly Data'!$K$215) -> 96.39649 | AE6: =100*('Quarterly Data'!Z209/'Quarterly Data'!$Z$215) -> 97.083088 | AF6: =100*((AD6/AE6)-1) -> -0.70722689 | AH6: 45108 | AI6: =100*('Quarterly Data'!J209/'Quarterly Data'!$J$215) -> 96.436534 | AJ6: =100*('Quarterly Data'!Y209/'Quarterly Data'!$Y$215) -> 98.459802 | AK6: =100*((AI6/AJ6)-1) -> -2.0549181 | AM6: 45108 | AN6: =100*(('Quarterly Data'!E209/'Quarterly Data'!E205)-1) -> 6.7136185 | AO6: =100*(('Quarterly Data'!T209/'Quarterly Data'!T205)-1) -> 6.7136185 | AP6: 2 | AR6: 45108 | AS6: ='Quarterly Data'!L209 -> 628663.1 | AT6: ='Quarterly Data'!AA209 -> 628564.2 | AU6: =100*((AS6/AT6)-1) -> 0.015734272 | AW6: 1983 | AX6: ='Annual Data'!K17*'Annual Data'!L17 -> 24.304682 | AY6: ='Annual Data'!M17/'Annual Data'!N17 -> 8.5563187 | AZ6: ='Annual Data'!O17 -> 1301611.5 | BA6: ='Annual Data'!P17 -> -7.497925 | BB6: ='Annual Data'!J17 -> 1121588.5 | BC6: ='Annual Data'!B17 -> 1117759 | BE6: =100*((BB6/BB5)-1) -> 1.6472442 | BF6: =100*((BC6/BC5)-1) -> 4.1660493 | BH6: 1983 | BI6: ='Annual Data'!Z17*'Annual Data'!AA17 -> 24.304682 | BJ6: ='Annual Data'!AB17/'Annual Data'!AC17 -> 8.5563187 | BK6: ='Annual Data'!AD17 -> 1301611.5 | BL6: ='Annual Data'!AE17 -> -7.497925 | BM6: ='Annual Data'!Y17 -> 1121588.5 | BN6: ='Annual Data'!Q17 -> 1117759 | BP6: =100*((BM6/BM5)-1) -> 1.6472442 | BQ6: =100*((BN6/BN5)-1) -> 4.1660493
A7: 45200 | B7: ='Quarterly Data'!D210 -> 633011 | C7: ='Quarterly Data'!S210 -> 632365 | D7: ='Quarterly Data'!AH210 -> 632365 | E7: =100*((B7/C7)-1) -> 0.10215619 | G7: 45200 | H7: =100*('Quarterly Data'!D210/'Quarterly Data'!$D$215) -> 98.006053 | I7: =100*('Quarterly Data'!S210/'Quarterly Data'!$S$215) -> 98.343969 | J7: =100*((H7/I7)-1) -> -0.34360695 | L7: 45200 | M7: ='Quarterly Data'!G210 -> 86003 | N7: ='Quarterly Data'!V210 -> 85834 | O7: =100*((M7/N7)-1) -> 0.19689167 | Q7: 45200 | R7: =100*('Quarterly Data'!G210/'Quarterly Data'!$G$215) -> 109.05235 | S7: =100*('Quarterly Data'!V210/'Quarterly Data'!$V$215) -> 112.74494 | T7: =100*((R7/S7)-1) -> -3.2751768 | V7: 45200 | W7: ='Quarterly Data'!K210 -> 62681 | X7: ='Quarterly Data'!Z210 -> 62795 | Y7: ='Quarterly Data'!AO210 -> 62795 | Z7: =100*((W7/X7)-1) -> -0.18154312 | AA7: =100*((W7/Y7)-1) -> -0.18154312 | AC7: 45200 | AD7: =100*('Quarterly Data'!K210/'Quarterly Data'!$K$215) -> 98.16621 | AE7: =100*('Quarterly Data'!Z210/'Quarterly Data'!$Z$215) -> 98.767619 | AF7: =100*((AD7/AE7)-1) -> -0.60891279 | AH7: 45200 | AI7: =100*('Quarterly Data'!J210/'Quarterly Data'!$J$215) -> 97.33209 | AJ7: =100*('Quarterly Data'!Y210/'Quarterly Data'!$Y$215) -> 99.31875 | AK7: =100*((AI7/AJ7)-1) -> -2.0002873 | AM7: 45200 | AN7: =100*(('Quarterly Data'!E210/'Quarterly Data'!E206)-1) -> 4.1568272 | AO7: =100*(('Quarterly Data'!T210/'Quarterly Data'!T206)-1) -> 4.1568272 | AP7: 2 | AR7: 45200 | AS7: ='Quarterly Data'!L210 -> 631659.5 | AT7: ='Quarterly Data'!AA210 -> 630612.8 | AU7: =100*((AS7/AT7)-1) -> 0.16598141 | AW7: 1984 | AX7: ='Annual Data'!K18*'Annual Data'!L18 -> 24.910802 | AY7: ='Annual Data'!M18/'Annual Data'!N18 -> 8.5981632 | AZ7: ='Annual Data'!O18 -> 1322354.2 | BA7: ='Annual Data'!P18 -> -7.449458 | BB7: ='Annual Data'!J18 -> 1160834.9 | BC7: ='Annual Data'!B18 -> 1142579 | BE7: =100*((BB7/BB6)-1) -> 3.49918 | BF7: =100*((BC7/BC6)-1) -> 2.2205144 | BH7: 1984 | BI7: ='Annual Data'!Z18*'Annual Data'!AA18 -> 24.910802 | BJ7: ='Annual Data'!AB18/'Annual Data'!AC18 -> 8.5981632 | BK7: ='Annual Data'!AD18 -> 1322354.2 | BL7: ='Annual Data'!AE18 -> -7.449458 | BM7: ='Annual Data'!Y18 -> 1160834.9 | BN7: ='Annual Data'!Q18 -> 1142579 | BP7: =100*((BM7/BM6)-1) -> 3.49918 | BQ7: =100*((BN7/BN6)-1) -> 2.2205144
A8: 45292 | B8: ='Quarterly Data'!D211 -> 638746 | C8: ='Quarterly Data'!S211 -> 637729 | D8: ='Quarterly Data'!AH211 -> 637023 | E8: =100*((B8/C8)-1) -> 0.15947213 | G8: 45292 | H8: =100*('Quarterly Data'!D211/'Quarterly Data'!$D$215) -> 98.893975 | I8: =100*('Quarterly Data'!S211/'Quarterly Data'!$S$215) -> 99.178167 | J8: =100*((H8/I8)-1) -> -0.28654625 | L8: 45292 | M8: ='Quarterly Data'!G211 -> 82999 | N8: ='Quarterly Data'!V211 -> 82683 | O8: =100*((M8/N8)-1) -> 0.38218255 | Q8: 45292 | R8: =100*('Quarterly Data'!G211/'Quarterly Data'!$G$215) -> 105.24326 | S8: =100*('Quarterly Data'!V211/'Quarterly Data'!$V$215) -> 108.60603 | T8: =100*((R8/S8)-1) -> -3.0963067 | V8: 45292 | W8: ='Quarterly Data'!K211 -> 62527 | X8: ='Quarterly Data'!Z211 -> 62349 | Y8: ='Quarterly Data'!AO211 -> 62978 | Z8: =100*((W8/X8)-1) -> 0.28548974 | AA8: =100*((W8/Y8)-1) -> -0.71612309 | AC8: 45292 | AD8: =100*('Quarterly Data'!K211/'Quarterly Data'!$K$215) -> 97.925027 | AE8: =100*('Quarterly Data'!Z211/'Quarterly Data'!$Z$215) -> 98.066124 | AF8: =100*((AD8/AE8)-1) -> -0.14387951 | AH8: 45292 | AI8: =100*('Quarterly Data'!J211/'Quarterly Data'!$J$215) -> 98.072912 | AJ8: =100*('Quarterly Data'!Y211/'Quarterly Data'!$Y$215) -> 100.2553 | AK8: =100*((AI8/AJ8)-1) -> -2.1768341 | AM8: 45292 | AN8: =100*(('Quarterly Data'!E211/'Quarterly Data'!E207)-1) -> 3.5491137 | AO8: =100*(('Quarterly Data'!T211/'Quarterly Data'!T207)-1) -> 3.5491137 | AP8: 2 | AR8: 45292 | AS8: ='Quarterly Data'!L211 -> 638150.9 | AT8: ='Quarterly Data'!AA211 -> 638391.4 | AU8: =100*((AS8/AT8)-1) -> -0.037672813 | AW8: 1985 | AX8: ='Annual Data'!K19*'Annual Data'!L19 -> 25.107865 | AY8: ='Annual Data'!M19/'Annual Data'!N19 -> 8.6987735 | AZ8: ='Annual Data'!O19 -> 1348477 | BA8: ='Annual Data'!P19 -> -7.401305 | BB8: ='Annual Data'!J19 -> 1193082.3 | BC8: ='Annual Data'!B19 -> 1189278 | BE8: =100*((BB8/BB7)-1) -> 2.7779489 | BF8: =100*((BC8/BC7)-1) -> 4.0871572 | BH8: 1985 | BI8: ='Annual Data'!Z19*'Annual Data'!AA19 -> 25.107865 | BJ8: ='Annual Data'!AB19/'Annual Data'!AC19 -> 8.6987735 | BK8: ='Annual Data'!AD19 -> 1348477 | BL8: ='Annual Data'!AE19 -> -7.401305 | BM8: ='Annual Data'!Y19 -> 1193082.3 | BN8: ='Annual Data'!Q19 -> 1189278 | BP8: =100*((BM8/BM7)-1) -> 2.7779489 | BQ8: =100*((BN8/BN7)-1) -> 4.0871572
A9: 45383 | B9: ='Quarterly Data'!D212 -> 641670 | C9: ='Quarterly Data'!S212 -> 640592 | D9: ='Quarterly Data'!AH212 -> 639269 | E9: =100*((B9/C9)-1) -> 0.16828184 | G9: 45383 | H9: =100*('Quarterly Data'!D212/'Quarterly Data'!$D$215) -> 99.346684 | I9: =100*('Quarterly Data'!S212/'Quarterly Data'!$S$215) -> 99.623414 | J9: =100*((H9/I9)-1) -> -0.27777577 | L9: 45383 | M9: ='Quarterly Data'!G212 -> 79136 | N9: ='Quarterly Data'!V212 -> 78994 | O9: =100*((M9/N9)-1) -> 0.17976049 | Q9: 45383 | R9: =100*('Quarterly Data'!G212/'Quarterly Data'!$G$215) -> 100.34495 | S9: =100*('Quarterly Data'!V212/'Quarterly Data'!$V$215) -> 103.76045 | T9: =100*((R9/S9)-1) -> -3.2917144 | V9: 45383 | W9: ='Quarterly Data'!K212 -> 63634 | X9: ='Quarterly Data'!Z212 -> 63236 | Y9: ='Quarterly Data'!AO212 -> 64099 | Z9: =100*((W9/X9)-1) -> 0.62938832 | AA9: =100*((W9/Y9)-1) -> -0.72544033 | AC9: 45383 | AD9: =100*('Quarterly Data'!K212/'Quarterly Data'!$K$215) -> 99.658726 | AE9: =100*('Quarterly Data'!Z212/'Quarterly Data'!$Z$215) -> 99.461249 | AF9: =100*((AD9/AE9)-1) -> 0.19854667 | AH9: 45383 | AI9: =100*('Quarterly Data'!J212/'Quarterly Data'!$J$215) -> 99.141355 | AJ9: =100*('Quarterly Data'!Y212/'Quarterly Data'!$Y$215) -> 100.93964 | AK9: =100*((AI9/AJ9)-1) -> -1.7815446 | AM9: 45383 | AN9: =100*(('Quarterly Data'!E212/'Quarterly Data'!E208)-1) -> 2.1108336 | AO9: =100*(('Quarterly Data'!T212/'Quarterly Data'!T208)-1) -> 2.1108336 | AP9: 2 | AR9: 45383 | AS9: ='Quarterly Data'!L212 -> 640407.3 | AT9: ='Quarterly Data'!AA212 -> 640919.3 | AU9: =100*((AS9/AT9)-1) -> -0.079885252 | AW9: 1986 | AX9: ='Annual Data'!K20*'Annual Data'!L20 -> 846672.54 | AY9: ='Annual Data'!M20/'Annual Data'!N20 -> 8.811239 | AZ9: ='Annual Data'!O20 -> 1372084.8 | BA9: ='Annual Data'!P20 -> -7.353953 | BB9: ='Annual Data'!J20 -> 1223572.5 | BC9: ='Annual Data'!B20 -> 1226237 | BE9: =100*((BB9/BB8)-1) -> 2.5555823 | BF9: =100*((BC9/BC8)-1) -> 3.1076838 | BH9: 1986 | BI9: ='Annual Data'!Z20*'Annual Data'!AA20 -> 846672.54 | BJ9: ='Annual Data'!AB20/'Annual Data'!AC20 -> 8.811239 | BK9: ='Annual Data'!AD20 -> 1372084.8 | BL9: ='Annual Data'!AE20 -> -7.353953 | BM9: ='Annual Data'!Y20 -> 1223572.5 | BN9: ='Annual Data'!Q20 -> 1226237 | BP9: =100*((BM9/BM8)-1) -> 2.5555823 | BQ9: =100*((BN9/BN8)-1) -> 3.1076838
A10: 45474 | B10: ='Quarterly Data'!D213 -> 641675 | C10: ='Quarterly Data'!S213 -> 640417 | D10: ='Quarterly Data'!AH213 -> 639452 | E10: =100*((B10/C10)-1) -> 0.19643451 | G10: 45474 | H10: =100*('Quarterly Data'!D213/'Quarterly Data'!$D$215) -> 99.347458 | I10: =100*('Quarterly Data'!S213/'Quarterly Data'!$S$215) -> 99.596198 | J10: =100*((H10/I10)-1) -> -0.24974846 | L10: 45474 | M10: ='Quarterly Data'!G213 -> 79947 | N10: ='Quarterly Data'!V213 -> 79804 | O10: =100*((M10/N10)-1) -> 0.17918901 | Q10: 45474 | R10: =100*('Quarterly Data'!G213/'Quarterly Data'!$G$215) -> 101.3733 | S10: =100*('Quarterly Data'!V213/'Quarterly Data'!$V$215) -> 104.8244 | T10: =100*((R10/S10)-1) -> -3.292266 | V10: 45474 | W10: ='Quarterly Data'!K213 -> 65023 | X10: ='Quarterly Data'!Z213 -> 64412 | Y10: ='Quarterly Data'!AO213 -> 65327 | Z10: =100*((W10/X10)-1) -> 0.94858101 | AA10: =100*((W10/Y10)-1) -> -0.46535123 | AC10: 45474 | AD10: =100*('Quarterly Data'!K213/'Quarterly Data'!$K$215) -> 101.83407 | AE10: =100*('Quarterly Data'!Z213/'Quarterly Data'!$Z$215) -> 101.31093 | AF10: =100*((AD10/AE10)-1) -> 0.51637275 | AH10: 45474 | AI10: =100*('Quarterly Data'!J213/'Quarterly Data'!$J$215) -> 100.12941 | AJ10: =100*('Quarterly Data'!Y213/'Quarterly Data'!$Y$215) -> 101.91941 | AK10: =100*((AI10/AJ10)-1) -> -1.7562888 | AM10: 45474 | AN10: =100*(('Quarterly Data'!E213/'Quarterly Data'!E209)-1) -> 2.0547945 | AO10: =100*(('Quarterly Data'!T213/'Quarterly Data'!T209)-1) -> 2.0547945 | AP10: 2 | AR10: 45474 | AS10: ='Quarterly Data'!L213 -> 646654.9 | AT10: ='Quarterly Data'!AA213 -> 646929.4 | AU10: =100*((AS10/AT10)-1) -> -0.042431214 | AW10: 1987 | AX10: ='Annual Data'!K21*'Annual Data'!L21 -> 854924.76 | AY10: ='Annual Data'!M21/'Annual Data'!N21 -> 8.9162746 | AZ10: ='Annual Data'!O21 -> 1399611 | BA10: ='Annual Data'!P21 -> -7.308859 | BB10: ='Annual Data'!J21 -> 1257734.5 | BC10: ='Annual Data'!B21 -> 1292703 | BE10: =100*((BB10/BB9)-1) -> 2.7919882 | BF10: =100*((BC10/BC9)-1) -> 5.4203225 | BH10: 1987 | BI10: ='Annual Data'!Z21*'Annual Data'!AA21 -> 854924.76 | BJ10: ='Annual Data'!AB21/'Annual Data'!AC21 -> 8.9162746 | BK10: ='Annual Data'!AD21 -> 1399611 | BL10: ='Annual Data'!AE21 -> -7.308859 | BM10: ='Annual Data'!Y21 -> 1257734.5 | BN10: ='Annual Data'!Q21 -> 1292703 | BP10: =100*((BM10/BM9)-1) -> 2.7919882 | BQ10: =100*((BN10/BN9)-1) -> 5.4203225
A11: 45566 | B11: ='Quarterly Data'!D214 -> 642287 | C11: ='Quarterly Data'!S214 -> 641065 | D11: ='Quarterly Data'!AH214 -> 640033.9 | E11: =100*((B11/C11)-1) -> 0.1906203 | G11: 45566 | H11: =100*('Quarterly Data'!D214/'Quarterly Data'!$D$215) -> 99.442211 | I11: =100*('Quarterly Data'!S214/'Quarterly Data'!$S$215) -> 99.696974 | J11: =100*((H11/I11)-1) -> -0.25553678 | L11: 45566 | M11: ='Quarterly Data'!G214 -> 75593 | N11: ='Quarterly Data'!V214 -> 75407 | O11: =100*((M11/N11)-1) -> 0.24666145 | Q11: 45566 | R11: =100*('Quarterly Data'!G214/'Quarterly Data'!$G$215) -> 95.852402 | S11: =100*('Quarterly Data'!V214/'Quarterly Data'!$V$215) -> 99.048838 | T11: =100*((R11/S11)-1) -> -3.2271317 | V11: 45566 | W11: ='Quarterly Data'!K214 -> 63820 | X11: ='Quarterly Data'!Z214 -> 62338 | Y11: ='Quarterly Data'!AO214 -> 64366.69 | Z11: =100*((W11/X11)-1) -> 2.3773621 | AA11: =100*((W11/Y11)-1) -> -0.84933682 | AC11: 45566 | AD11: =100*('Quarterly Data'!K214/'Quarterly Data'!$K$215) -> 99.950025 | AE11: =100*('Quarterly Data'!Z214/'Quarterly Data'!$Z$215) -> 98.048822 | AF11: =100*((AD11/AE11)-1) -> 1.9390366 | AH11: 45566 | AI11: =100*('Quarterly Data'!J214/'Quarterly Data'!$J$215) -> 99.509605 | AJ11: =100*('Quarterly Data'!Y214/'Quarterly Data'!$Y$215) -> 101.00843 | AK11: =100*((AI11/AJ11)-1) -> -1.4838575 | AM11: 45566 | AN11: =100*(('Quarterly Data'!E214/'Quarterly Data'!E210)-1) -> 2.4753214 | AO11: =100*(('Quarterly Data'!T214/'Quarterly Data'!T210)-1) -> 2.4753214 | AP11: 2 | AR11: 45566 | AS11: ='Quarterly Data'!L214 -> 645443.6 | AT11: ='Quarterly Data'!AA214 -> 646080.4 | AU11: =100*((AS11/AT11)-1) -> -0.098563584 | AW11: 1988 | AX11: ='Annual Data'!K22*'Annual Data'!L22 -> 869416.89 | AY11: ='Annual Data'!M22/'Annual Data'!N22 -> 9.0335851 | AZ11: ='Annual Data'!O22 -> 1439126.5 | BA11: ='Annual Data'!P22 -> -7.264205 | BB11: ='Annual Data'!J22 -> 1302509.7 | BC11: ='Annual Data'!B22 -> 1362204 | BE11: =100*((BB11/BB10)-1) -> 3.5599882 | BF11: =100*((BC11/BC10)-1) -> 5.376409 | BH11: 1988 | BI11: ='Annual Data'!Z22*'Annual Data'!AA22 -> 869416.89 | BJ11: ='Annual Data'!AB22/'Annual Data'!AC22 -> 9.0335851 | BK11: ='Annual Data'!AD22 -> 1439126.5 | BL11: ='Annual Data'!AE22 -> -7.264205 | BM11: ='Annual Data'!Y22 -> 1302509.7 | BN11: ='Annual Data'!Q22 -> 1362204 | BP11: =100*((BM11/BM10)-1) -> 3.5599882 | BQ11: =100*((BN11/BN10)-1) -> 5.376409
A12: 45658 | B12: ='Quarterly Data'!D215 -> 645889.7 | C12: ='Quarterly Data'!S215 -> 643013.5 | D12: ='Quarterly Data'!AH215 -> 642502.8 | E12: =100*((B12/C12)-1) -> 0.4473001 | G12: 45658 | H12: =100*('Quarterly Data'!D215/'Quarterly Data'!$D$215) -> 100 | I12: =100*('Quarterly Data'!S215/'Quarterly Data'!$S$215) -> 100 | J12: =100*((H12/I12)-1) -> 0 | L12: 45658 | M12: ='Quarterly Data'!G215 -> 78863.96 | N12: ='Quarterly Data'!V215 -> 76131.13 | O12: =100*((M12/N12)-1) -> 3.5896354 | Q12: 45658 | R12: =100*('Quarterly Data'!G215/'Quarterly Data'!$G$215) -> 100 | S12: =100*('Quarterly Data'!V215/'Quarterly Data'!$V$215) -> 100 | T12: =100*((R12/S12)-1) -> 0 | V12: 45658 | W12: ='Quarterly Data'!K215 -> 63851.91 | X12: ='Quarterly Data'!Z215 -> 63578.53 | Y12: ='Quarterly Data'!AO215 -> 64431.09 | Z12: =100*((W12/X12)-1) -> 0.42998792 | AA12: =100*((W12/Y12)-1) -> -0.89891386 | AC12: 45658 | AD12: =100*('Quarterly Data'!K215/'Quarterly Data'!$K$215) -> 100 | AE12: =100*('Quarterly Data'!Z215/'Quarterly Data'!$Z$215) -> 100 | AF12: =100*((AD12/AE12)-1) -> 0 | AH12: 45658 | AI12: =100*('Quarterly Data'!J215/'Quarterly Data'!$J$215) -> 100 | AJ12: =100*('Quarterly Data'!Y215/'Quarterly Data'!$Y$215) -> 100 | AK12: =100*((AI12/AJ12)-1) -> 0 | AM12: 45658 | AN12: =100*(('Quarterly Data'!E215/'Quarterly Data'!E211)-1) -> 2.7868693 | AO12: =100*(('Quarterly Data'!T215/'Quarterly Data'!T211)-1) -> 2.7942785 | AP12: 2 | AR12: 45658 | AS12: ='Quarterly Data'!L215 -> 649760.7 | AT12: ='Quarterly Data'!AA215 -> 649314.1 | AU12: =100*((AS12/AT12)-1) -> 0.068780271 | AW12: 1989 | AX12: ='Annual Data'!K23*'Annual Data'!L23 -> 881201.46 | AY12: ='Annual Data'!M23/'Annual Data'!N23 -> 9.1558676 | AZ12: ='Annual Data'!O23 -> 1489091 | BA12: ='Annual Data'!P23 -> -7.219823 | BB12: ='Annual Data'!J23 -> 1349436.2 | BC12: ='Annual Data'!B23 -> 1394928 | BE12: =100*((BB12/BB11)-1) -> 3.6027755 | BF12: =100*((BC12/BC11)-1) -> 2.4022834 | BH12: 1989 | BI12: ='Annual Data'!Z23*'Annual Data'!AA23 -> 881201.46 | BJ12: ='Annual Data'!AB23/'Annual Data'!AC23 -> 9.1558676 | BK12: ='Annual Data'!AD23 -> 1489091 | BL12: ='Annual Data'!AE23 -> -7.219823 | BM12: ='Annual Data'!Y23 -> 1349436.2 | BN12: ='Annual Data'!Q23 -> 1394928 | BP12: =100*((BM12/BM11)-1) -> 3.6027755 | BQ12: =100*((BN12/BN11)-1) -> 2.4022834
A13: 45748 | B13: ='Quarterly Data'!D216 -> 647140.2 | C13: ='Quarterly Data'!S216 -> 645036.8 | D13: ='Quarterly Data'!AH216 -> 644937.6 | E13: =100*((B13/C13)-1) -> 0.32608992 | G13: 45748 | H13: =100*('Quarterly Data'!D216/'Quarterly Data'!$D$215) -> 100.19361 | I13: =100*('Quarterly Data'!S216/'Quarterly Data'!$S$215) -> 100.31466 | J13: =100*((H13/I13)-1) -> -0.12067041 | L13: 45748 | M13: ='Quarterly Data'!G216 -> 76532.99 | N13: ='Quarterly Data'!V216 -> 76218.15 | O13: =100*((M13/N13)-1) -> 0.41307746 | Q13: 45748 | R13: =100*('Quarterly Data'!G216/'Quarterly Data'!$G$215) -> 97.044315 | S13: =100*('Quarterly Data'!V216/'Quarterly Data'!$V$215) -> 100.1143 | T13: =100*((R13/S13)-1) -> -3.0664824 | V13: 45748 | W13: ='Quarterly Data'!K216 -> 63839.13 | X13: ='Quarterly Data'!Z216 -> 63756.54 | Y13: ='Quarterly Data'!AO216 -> 64650.15 | Z13: =100*((W13/X13)-1) -> 0.12953965 | AA13: =100*((W13/Y13)-1) -> -1.254475 | AC13: 45748 | AD13: =100*('Quarterly Data'!K216/'Quarterly Data'!$K$215) -> 99.979985 | AE13: =100*('Quarterly Data'!Z216/'Quarterly Data'!$Z$215) -> 100.27998 | AF13: =100*((AD13/AE13)-1) -> -0.29916191 | AH13: 45748 | AI13: =100*('Quarterly Data'!J216/'Quarterly Data'!$J$215) -> 100.07261 | AJ13: =100*('Quarterly Data'!Y216/'Quarterly Data'!$Y$215) -> 100.5913 | AK13: =100*((AI13/AJ13)-1) -> -0.5156369 | AM13: 45748 | AN13: =100*(('Quarterly Data'!E216/'Quarterly Data'!E212)-1) -> 3.0628401 | AO13: =100*(('Quarterly Data'!T216/'Quarterly Data'!T212)-1) -> 3.1688675 | AP13: 2 | AR13: 45748 | AS13: ='Quarterly Data'!L216 -> 651663.3 | AT13: ='Quarterly Data'!AA216 -> 651120.4 | AU13: =100*((AS13/AT13)-1) -> 0.083379357 | AW13: 1990 | AX13: ='Annual Data'!K24*'Annual Data'!L24 -> 879722.64 | AY13: ='Annual Data'!M24/'Annual Data'!N24 -> 9.2673131 | AZ13: ='Annual Data'!O24 -> 1546268.5 | BA13: ='Annual Data'!P24 -> -7.175712 | BB13: ='Annual Data'!J24 -> 1385653.3 | BC13: ='Annual Data'!B24 -> 1402748 | BE13: =100*((BB13/BB12)-1) -> 2.683869 | BF13: =100*((BC13/BC12)-1) -> 0.56060241 | BH13: 1990 | BI13: ='Annual Data'!Z24*'Annual Data'!AA24 -> 879722.64 | BJ13: ='Annual Data'!AB24/'Annual Data'!AC24 -> 9.2673131 | BK13: ='Annual Data'!AD24 -> 1546268.5 | BL13: ='Annual Data'!AE24 -> -7.175712 | BM13: ='Annual Data'!Y24 -> 1385653.3 | BN13: ='Annual Data'!Q24 -> 1402748 | BP13: =100*((BM13/BM12)-1) -> 2.683869 | BQ13: =100*((BN13/BN12)-1) -> 0.56060241
A14: 45839 | B14: ='Quarterly Data'!D217 -> 648105.8 | C14: ='Quarterly Data'!S217 -> 647093.9 | D14: ='Quarterly Data'!AH217 -> 647364.9 | E14: =100*((B14/C14)-1) -> 0.15637607 | G14: 45839 | H14: =100*('Quarterly Data'!D217/'Quarterly Data'!$D$215) -> 100.34311 | I14: =100*('Quarterly Data'!S217/'Quarterly Data'!$S$215) -> 100.63457 | J14: =100*((H14/I14)-1) -> -0.28962852 | L14: 45839 | M14: ='Quarterly Data'!G217 -> 75001.37 | N14: ='Quarterly Data'!V217 -> 76140.98 | O14: =100*((M14/N14)-1) -> -1.4967104 | Q14: 45839 | R14: =100*('Quarterly Data'!G217/'Quarterly Data'!$G$215) -> 95.102211 | S14: =100*('Quarterly Data'!V217/'Quarterly Data'!$V$215) -> 100.01294 | T14: =100*((R14/S14)-1) -> -4.9100915 | V14: 45839 | W14: ='Quarterly Data'!K217 -> 63871.05 | X14: ='Quarterly Data'!Z217 -> 63966.93 | Y14: ='Quarterly Data'!AO217 -> 64934.61 | Z14: =100*((W14/X14)-1) -> -0.14988995 | AA14: =100*((W14/Y14)-1) -> -1.6378939 | AC14: 45839 | AD14: =100*('Quarterly Data'!K217/'Quarterly Data'!$K$215) -> 100.02998 | AE14: =100*('Quarterly Data'!Z217/'Quarterly Data'!$Z$215) -> 100.6109 | AF14: =100*((AD14/AE14)-1) -> -0.57739514 | AH14: 45839 | AI14: =100*('Quarterly Data'!J217/'Quarterly Data'!$J$215) -> 100.25233 | AJ14: =100*('Quarterly Data'!Y217/'Quarterly Data'!$Y$215) -> 101.46541 | AK14: =100*((AI14/AJ14)-1) -> -1.195566 | AM14: 45839 | AN14: =100*(('Quarterly Data'!E217/'Quarterly Data'!E213)-1) -> 3.2803132 | AO14: =100*(('Quarterly Data'!T217/'Quarterly Data'!T213)-1) -> 3.4616704 | AP14: 2 | AR14: 45839 | AS14: ='Quarterly Data'!L217 -> 653590.9 | AT14: ='Quarterly Data'!AA217 -> 653146.6 | AU14: =100*((AS14/AT14)-1) -> 0.068024545 | AW14: 1991 | AX14: ='Annual Data'!K25*'Annual Data'!L25 -> 861885.22 | AY14: ='Annual Data'!M25/'Annual Data'!N25 -> 9.375413 | AZ14: ='Annual Data'!O25 -> 1600385.2 | BA14: ='Annual Data'!P25 -> -7.13187 | BB14: ='Annual Data'!J25 -> 1404835.5 | BC14: ='Annual Data'!B25 -> 1383043 | BE14: =100*((BB14/BB13)-1) -> 1.3843434 | BF14: =100*((BC14/BC13)-1) -> -1.4047427 | BH14: 1991 | BI14: ='Annual Data'!Z25*'Annual Data'!AA25 -> 861885.22 | BJ14: ='Annual Data'!AB25/'Annual Data'!AC25 -> 9.375413 | BK14: ='Annual Data'!AD25 -> 1600385.2 | BL14: ='Annual Data'!AE25 -> -7.13187 | BM14: ='Annual Data'!Y25 -> 1404835.5 | BN14: ='Annual Data'!Q25 -> 1383043 | BP14: =100*((BM14/BM13)-1) -> 1.3843434 | BQ14: =100*((BN14/BN13)-1) -> -1.4047427
A15: 45931 | B15: ='Quarterly Data'!D218 -> 649184.3 | C15: ='Quarterly Data'!S218 -> 649337.3 | D15: ='Quarterly Data'!AH218 -> 649965.9 | E15: =100*((B15/C15)-1) -> -0.023562484 | G15: 45931 | H15: =100*('Quarterly Data'!D218/'Quarterly Data'!$D$215) -> 100.51009 | I15: =100*('Quarterly Data'!S218/'Quarterly Data'!$S$215) -> 100.98346 | J15: =100*((H15/I15)-1) -> -0.46876579 | L15: 45931 | M15: ='Quarterly Data'!G218 -> 73106.27 | N15: ='Quarterly Data'!V218 -> 76067.3 | O15: =100*((M15/N15)-1) -> -3.8926451 | Q15: 45931 | R15: =100*('Quarterly Data'!G218/'Quarterly Data'!$G$215) -> 92.699213 | S15: =100*('Quarterly Data'!V218/'Quarterly Data'!$V$215) -> 99.916158 | T15: =100*((R15/S15)-1) -> -7.2230011 | V15: 45931 | W15: ='Quarterly Data'!K218 -> 63826.35 | X15: ='Quarterly Data'!Z218 -> 64171.65 | Y15: ='Quarterly Data'!AO218 -> 65226.83 | Z15: =100*((W15/X15)-1) -> -0.53808808 | AA15: =100*((W15/Y15)-1) -> -2.1470919 | AC15: 45931 | AD15: =100*('Quarterly Data'!K218/'Quarterly Data'!$K$215) -> 99.95997 | AE15: =100*('Quarterly Data'!Z218/'Quarterly Data'!$Z$215) -> 100.93289 | AF15: =100*((AD15/AE15)-1) -> -0.96393122 | AH15: 45931 | AI15: =100*('Quarterly Data'!J218/'Quarterly Data'!$J$215) -> 100.43913 | AJ15: =100*('Quarterly Data'!Y218/'Quarterly Data'!$Y$215) -> 102.28221 | AK15: =100*((AI15/AJ15)-1) -> -1.8019514 | AM15: 45931 | AN15: =100*(('Quarterly Data'!E218/'Quarterly Data'!E214)-1) -> 2.9612529 | AO15: =100*(('Quarterly Data'!T218/'Quarterly Data'!T214)-1) -> 3.1802078 | AP15: 2 | AR15: 45931 | AS15: ='Quarterly Data'!L218 -> 655545.4 | AT15: ='Quarterly Data'!AA218 -> 655401.6 | AU15: =100*((AS15/AT15)-1) -> 0.021940746 | AW15: 1992 | AX15: ='Annual Data'!K26*'Annual Data'!L26 -> 848974.47 | AY15: ='Annual Data'!M26/'Annual Data'!N26 -> 9.4785341 | AZ15: ='Annual Data'!O26 -> 1638555.8 | BA15: ='Annual Data'!P26 -> -7.088298 | BB15: ='Annual Data'!J26 -> 1424319.6 | BC15: ='Annual Data'!B26 -> 1386437 | BE15: =100*((BB15/BB14)-1) -> 1.3869311 | BF15: =100*((BC15/BC14)-1) -> 0.2454009 | BH15: 1992 | BI15: ='Annual Data'!Z26*'Annual Data'!AA26 -> 848974.47 | BJ15: ='Annual Data'!AB26/'Annual Data'!AC26 -> 9.4785341 | BK15: ='Annual Data'!AD26 -> 1638555.8 | BL15: ='Annual Data'!AE26 -> -7.088298 | BM15: ='Annual Data'!Y26 -> 1424319.6 | BN15: ='Annual Data'!Q26 -> 1386437 | BP15: =100*((BM15/BM14)-1) -> 1.3869311 | BQ15: =100*((BN15/BN14)-1) -> 0.2454009
... A19: 46296 | B19: ='Quarterly Data'!D222 -> 655799.6 | C19: ='Quarterly Data'!S222 -> 659363.1 | D19: ='Quarterly Data'!AH222 -> 661119.8 | E19: =100*((B19/C19)-1) -> -0.54044577 | G19: 46296 | H19: =100*('Quarterly Data'!D222/'Quarterly Data'!$D$215) -> 101.5343 | I19: =100*('Quarterly Data'!S222/'Quarterly Data'!$S$215) -> 102.54265 | J19: =100*((H19/I19)-1) -> -0.98334735 | L19: 46296 | M19: ='Quarterly Data'!G222 -> 72199.7 | N19: ='Quarterly Data'!V222 -> 76212.55 | O19: =100*((M19/N19)-1) -> -5.2653402 | Q19: 46296 | R19: =100*('Quarterly Data'!G222/'Quarterly Data'!$G$215) -> 91.549676 | S19: =100*('Quarterly Data'!V222/'Quarterly Data'!$V$215) -> 100.10695 | T19: =100*((R19/S19)-1) -> -8.5481289 | V19: 46296 | W19: ='Quarterly Data'!K222 -> 63992.46 | X19: ='Quarterly Data'!Z222 -> 65686.47 | Y19: ='Quarterly Data'!AO222 -> 67079.09 | Z19: =100*((W19/X19)-1) -> -2.5789329 | AA19: =100*((W19/Y19)-1) -> -4.6014786 | AC19: 46296 | AD19: =100*('Quarterly Data'!K222/'Quarterly Data'!$K$215) -> 100.22012 | AE19: =100*('Quarterly Data'!Z222/'Quarterly Data'!$Z$215) -> 103.31549 | AF19: =100*((AD19/AE19)-1) -> -2.9960382 | AH19: 46296 | AI19: =100*('Quarterly Data'!J222/'Quarterly Data'!$J$215) -> 101.77486 | AJ19: =100*('Quarterly Data'!Y222/'Quarterly Data'!$Y$215) -> 105.30334 | AK19: =100*((AI19/AJ19)-1) -> -3.3507793 | AM19: 46296 | AN19: =100*(('Quarterly Data'!E222/'Quarterly Data'!E218)-1) -> 2.3620006 | AO19: =100*(('Quarterly Data'!T222/'Quarterly Data'!T218)-1) -> 2.374475 | AP19: 2 | AR19: 46296 | AS19: ='Quarterly Data'!L222 -> 664151.9 | AT19: ='Quarterly Data'!AA222 -> 665473.2 | AU19: =100*((AS19/AT19)-1) -> -0.19855045 | AW19: 1996 | AX19: ='Annual Data'!K30*'Annual Data'!L30 -> 866753.37 | AY19: ='Annual Data'!M30/'Annual Data'!N30 -> 9.720396 | AZ19: ='Annual Data'!O30 -> 1787124 | BA19: ='Annual Data'!P30 -> -6.916649 | BB19: ='Annual Data'!J30 -> 1564487.6 | BC19: ='Annual Data'!B30 -> 1539846 | BE19: =100*((BB19/BB18)-1) -> 2.6900477 | BF19: =100*((BC19/BC18)-1) -> 2.5819939 | BH19: 1996 | BI19: ='Annual Data'!Z30*'Annual Data'!AA30 -> 866753.37 | BJ19: ='Annual Data'!AB30/'Annual Data'!AC30 -> 9.720396 | BK19: ='Annual Data'!AD30 -> 1787124 | BL19: ='Annual Data'!AE30 -> -6.916649 | BM19: ='Annual Data'!Y30 -> 1564487.6 | BN19: ='Annual Data'!Q30 -> 1539846 | BP19: =100*((BM19/BM18)-1) -> 2.6900477 | BQ19: =100*((BN19/BN18)-1) -> 2.5819939
AR20: 46388 | AS20: ='Quarterly Data'!L223 -> 666314.6 | AT20: ='Quarterly Data'!AA223 -> 667995 | AU20: =100*((AS20/AT20)-1) -> -0.25155877 | AW20: 1997 | AX20: ='Annual Data'!K31*'Annual Data'!L31 -> 877828.58 | AY20: ='Annual Data'!M31/'Annual Data'!N31 -> 9.7395739 | AZ20: ='Annual Data'!O31 -> 1838121.5 | BA20: ='Annual Data'!P31 -> -6.87919 | BB20: ='Annual Data'!J31 -> 1608111.9 | BC20: ='Annual Data'!B31 -> 1615678 | BE20: =100*((BB20/BB19)-1) -> 2.7884082 | BF20: =100*((BC20/BC19)-1) -> 4.9246483 | BH20: 1997 | BI20: ='Annual Data'!Z31*'Annual Data'!AA31 -> 877828.58 | BJ20: ='Annual Data'!AB31/'Annual Data'!AC31 -> 9.7395739 | BK20: ='Annual Data'!AD31 -> 1838121.5 | BL20: ='Annual Data'!AE31 -> -6.87919 | BM20: ='Annual Data'!Y31 -> 1608111.9 | BN20: ='Annual Data'!Q31 -> 1615678 | BP20: =100*((BM20/BM19)-1) -> 2.7884082 | BQ20: =100*((BN20/BN19)-1) -> 4.9246483
AR21: 46478 | AS21: ='Quarterly Data'!L224 -> 668574.9 | AT21: ='Quarterly Data'!AA224 -> 670454.7 | AU21: =100*((AS21/AT21)-1) -> -0.28037688 | AW21: 1998 | AX21: ='Annual Data'!K32*'Annual Data'!L32 -> 884900.37 | AY21: ='Annual Data'!M32/'Annual Data'!N32 -> 9.7651542 | AZ21: ='Annual Data'!O32 -> 1907750 | BA21: ='Annual Data'!P32 -> -6.861095 | BB21: ='Annual Data'!J32 -> 1644834.7 | BC21: ='Annual Data'!B32 -> 1670654 | BE21: =100*((BB21/BB20)-1) -> 2.2835973 | BF21: =100*((BC21/BC20)-1) -> 3.4026582 | BH21: 1998 | BI21: ='Annual Data'!Z32*'Annual Data'!AA32 -> 884900.37 | BJ21: ='Annual Data'!AB32/'Annual Data'!AC32 -> 9.7651542 | BK21: ='Annual Data'!AD32 -> 1907750 | BL21: ='Annual Data'!AE32 -> -6.861095 | BM21: ='Annual Data'!Y32 -> 1644834.7 | BN21: ='Annual Data'!Q32 -> 1670654 | BP21: =100*((BM21/BM20)-1) -> 2.2835973 | BQ21: =100*((BN21/BN20)-1) -> 3.4026582
AR22: 46569 | AS22: ='Quarterly Data'!L225 -> 670903.7 | AT22: ='Quarterly Data'!AA225 -> 672935 | AU22: =100*((AS22/AT22)-1) -> -0.30185679 | AW22: 1999 | AX22: ='Annual Data'!K33*'Annual Data'!L33 -> 895986.1 | AY22: ='Annual Data'!M33/'Annual Data'!N33 -> 9.8328067 | AZ22: ='Annual Data'!O33 -> 1982625 | BA22: ='Annual Data'!P33 -> -6.844647 | BB22: ='Annual Data'!J33 -> 1691774 | BC22: ='Annual Data'!B33 -> 1721748 | BE22: =100*((BB22/BB21)-1) -> 2.8537396 | BF22: =100*((BC22/BC21)-1) -> 3.0583233 | BH22: 1999 | BI22: ='Annual Data'!Z33*'Annual Data'!AA33 -> 895986.1 | BJ22: ='Annual Data'!AB33/'Annual Data'!AC33 -> 9.8328067 | BK22: ='Annual Data'!AD33 -> 1982625 | BL22: ='Annual Data'!AE33 -> -6.844647 | BM22: ='Annual Data'!Y33 -> 1691774 | BN22: ='Annual Data'!Q33 -> 1721748 | BP22: =100*((BM22/BM21)-1) -> 2.8537396 | BQ22: =100*((BN22/BN21)-1) -> 3.0583233
AR23: 46661 | AS23: ='Quarterly Data'!L226 -> 673270.1 | AT23: ='Quarterly Data'!AA226 -> 675409.1 | AU23: =100*((AS23/AT23)-1) -> -0.31669695 | AW23: 2000 | AX23: ='Annual Data'!K34*'Annual Data'!L34 -> 897004.57 | AY23: ='Annual Data'!M34/'Annual Data'!N34 -> 9.9743923 | AZ23: ='Annual Data'!O34 -> 2062500 | BA23: ='Annual Data'!P34 -> -6.828236 | BB23: ='Annual Data'!J34 -> 1730478.3 | BC23: ='Annual Data'!B34 -> 1796500 | BE23: =100*((BB23/BB22)-1) -> 2.2877938 | BF23: =100*((BC23/BC22)-1) -> 4.3416342 | BH23: 2000 | BI23: ='Annual Data'!Z34*'Annual Data'!AA34 -> 897004.57 | BJ23: ='Annual Data'!AB34/'Annual Data'!AC34 -> 9.9743923 | BK23: ='Annual Data'!AD34 -> 2062500 | BL23: ='Annual Data'!AE34 -> -6.828236 | BM23: ='Annual Data'!Y34 -> 1730478.3 | BN23: ='Annual Data'!Q34 -> 1796500 | BP23: =100*((BM23/BM22)-1) -> 2.2877938 | BQ23: =100*((BN23/BN22)-1) -> 4.3416342
AR24: 46753 | AS24: ='Quarterly Data'!L227 -> 675708.6 | AT24: ='Quarterly Data'!AA227 -> 677887.6 | AU24: =100*((AS24/AT24)-1) -> -0.32143972 | AW24: 2001 | AX24: ='Annual Data'!K35*'Annual Data'!L35 -> 906197.83 | AY24: ='Annual Data'!M35/'Annual Data'!N35 -> 10.222142 | AZ24: ='Annual Data'!O35 -> 2140250 | BA24: ='Annual Data'!P35 -> -6.811865 | BB24: ='Annual Data'!J35 -> 1785942.4 | BC24: ='Annual Data'!B35 -> 1842720 | BE24: =100*((BB24/BB23)-1) -> 3.2051312 | BF24: =100*((BC24/BC23)-1) -> 2.5727804 | BH24: 2001 | BI24: ='Annual Data'!Z35*'Annual Data'!AA35 -> 906197.83 | BJ24: ='Annual Data'!AB35/'Annual Data'!AC35 -> 10.222142 | BK24: ='Annual Data'!AD35 -> 2140250 | BL24: ='Annual Data'!AE35 -> -6.811865 | BM24: ='Annual Data'!Y35 -> 1785942.4 | BN24: ='Annual Data'!Q35 -> 1842720 | BP24: =100*((BM24/BM23)-1) -> 3.2051312 | BQ24: =100*((BN24/BN23)-1) -> 2.5727804
AR25: 46844 | AS25: ='Quarterly Data'!L228 -> 678119.8 | AT25: ='Quarterly Data'!AA228 -> 680403.3 | AU25: =100*((AS25/AT25)-1) -> -0.33560978 | AW25: 2002 | AX25: ='Annual Data'!K36*'Annual Data'!L36 -> 905078.99 | AY25: ='Annual Data'!M36/'Annual Data'!N36 -> 10.55383 | AZ25: ='Annual Data'!O36 -> 2206750 | BA25: ='Annual Data'!P36 -> -6.795533 | BB25: ='Annual Data'!J36 -> 1829581.9 | BC25: ='Annual Data'!B36 -> 1875809 | BE25: =100*((BB25/BB24)-1) -> 2.4434999 | BF25: =100*((BC25/BC24)-1) -> 1.7956608 | BH25: 2002 | BI25: ='Annual Data'!Z36*'Annual Data'!AA36 -> 905078.99 | BJ25: ='Annual Data'!AB36/'Annual Data'!AC36 -> 10.55383 | BK25: ='Annual Data'!AD36 -> 2206750 | BL25: ='Annual Data'!AE36 -> -6.795533 | BM25: ='Annual Data'!Y36 -> 1829581.9 | BN25: ='Annual Data'!Q36 -> 1875809 | BP25: =100*((BM25/BM24)-1) -> 2.4434999 | BQ25: =100*((BN25/BN24)-1) -> 1.7956608
AR26: 46935 | AS26: ='Quarterly Data'!L229 -> 680510.3 | AT26: ='Quarterly Data'!AA229 -> 682909.3 | AU26: =100*((AS26/AT26)-1) -> -0.35129116 | AW26: 2003 | AX26: ='Annual Data'!K37*'Annual Data'!L37 -> 907432.95 | AY26: ='Annual Data'!M37/'Annual Data'!N37 -> 10.921333 | AZ26: ='Annual Data'!O37 -> 2263125 | BA26: ='Annual Data'!P37 -> -6.77924 | BB26: ='Annual Data'!J37 -> 1876404.4 | BC26: ='Annual Data'!B37 -> 1934941 | BE26: =100*((BB26/BB25)-1) -> 2.5591913 | BF26: =100*((BC26/BC25)-1) -> 3.1523465 | BH26: 2003 | BI26: ='Annual Data'!Z37*'Annual Data'!AA37 -> 907432.95 | BJ26: ='Annual Data'!AB37/'Annual Data'!AC37 -> 10.921333 | BK26: ='Annual Data'!AD37 -> 2263125 | BL26: ='Annual Data'!AE37 -> -6.77924 | BM26: ='Annual Data'!Y37 -> 1876404.4 | BN26: ='Annual Data'!Q37 -> 1934941 | BP26: =100*((BM26/BM25)-1) -> 2.5591913 | BQ26: =100*((BN26/BN25)-1) -> 3.1523465
AR27: 47027 | AS27: ='Quarterly Data'!L230 -> 682872.2 | AT27: ='Quarterly Data'!AA230 -> 685382.8 | AU27: =100*((AS27/AT27)-1) -> -0.36630625 | AW27: 2004 | AX27: ='Annual Data'!K38*'Annual Data'!L38 -> 912728.2 | AY27: ='Annual Data'!M38/'Annual Data'!N38 -> 11.276552 | AZ27: ='Annual Data'!O38 -> 2318000 | BA27: ='Annual Data'!P38 -> -6.762987 | BB27: ='Annual Data'!J38 -> 1925416.5 | BC27: ='Annual Data'!B38 -> 1982500 | BE27: =100*((BB27/BB26)-1) -> 2.6120222 | BF27: =100*((BC27/BC26)-1) -> 2.4579044 | BH27: 2004 | BI27: ='Annual Data'!Z38*'Annual Data'!AA38 -> 912728.2 | BJ27: ='Annual Data'!AB38/'Annual Data'!AC38 -> 11.276552 | BK27: ='Annual Data'!AD38 -> 2318000 | BL27: ='Annual Data'!AE38 -> -6.762987 | BM27: ='Annual Data'!Y38 -> 1925416.5 | BN27: ='Annual Data'!Q38 -> 1982500 | BP27: =100*((BM27/BM26)-1) -> 2.6120222 | BQ27: =100*((BN27/BN26)-1) -> 2.4579044
AR28: 47119 | AS28: ='Quarterly Data'!L231 -> 685260.5 | AT28: ='Quarterly Data'!AA231 -> 687829.1 | AU28: =100*((AS28/AT28)-1) -> -0.37343579 | AW28: 2005 | AX28: ='Annual Data'!K39*'Annual Data'!L39 -> 926585.3 | AY28: ='Annual Data'!M39/'Annual Data'!N39 -> 11.571259 | AZ28: ='Annual Data'!O39 -> 2377750 | BA28: ='Annual Data'!P39 -> -6.746771 | BB28: ='Annual Data'!J39 -> 1984701.9 | BC28: ='Annual Data'!B39 -> 2036675 | BE28: =100*((BB28/BB27)-1) -> 3.0790948 | BF28: =100*((BC28/BC27)-1) -> 2.7326608 | BH28: 2005 | BI28: ='Annual Data'!Z39*'Annual Data'!AA39 -> 926585.3 | BJ28: ='Annual Data'!AB39/'Annual Data'!AC39 -> 11.571259 | BK28: ='Annual Data'!AD39 -> 2377750 | BL28: ='Annual Data'!AE39 -> -6.746771 | BM28: ='Annual Data'!Y39 -> 1984701.9 | BN28: ='Annual Data'!Q39 -> 2036675 | BP28: =100*((BM28/BM27)-1) -> 3.0790948 | BQ28: =100*((BN28/BN27)-1) -> 2.7326608
AR29: 47209 | AS29: ='Quarterly Data'!L232 -> 687617.9 | AT29: ='Quarterly Data'!AA232 -> 690238.7 | AU29: =100*((AS29/AT29)-1) -> -0.37969473 | AW29: 2006 | AX29: ='Annual Data'!K40*'Annual Data'!L40 -> 938041.8 | AY29: ='Annual Data'!M40/'Annual Data'!N40 -> 11.80839 | AZ29: ='Annual Data'!O40 -> 2443500 | BA29: ='Annual Data'!P40 -> -6.730595 | BB29: ='Annual Data'!J40 -> 2040054.2 | BC29: ='Annual Data'!B40 -> 2085162 | BE29: =100*((BB29/BB28)-1) -> 2.7889478 | BF29: =100*((BC29/BC28)-1) -> 2.380694 | BH29: 2006 | BI29: ='Annual Data'!Z40*'Annual Data'!AA40 -> 938041.8 | BJ29: ='Annual Data'!AB40/'Annual Data'!AC40 -> 11.80839 | BK29: ='Annual Data'!AD40 -> 2443500 | BL29: ='Annual Data'!AE40 -> -6.730595 | BM29: ='Annual Data'!Y40 -> 2040054.2 | BN29: ='Annual Data'!Q40 -> 2085162 | BP29: =100*((BM29/BM28)-1) -> 2.7889478 | BQ29: =100*((BN29/BN28)-1) -> 2.380694
AR30: 47300 | AS30: ='Quarterly Data'!L233 -> 690014.9 | AT30: ='Quarterly Data'!AA233 -> 692664.1 | AU30: =100*((AS30/AT30)-1) -> -0.38246532 | AW30: 2007 | AX30: ='Annual Data'!K41*'Annual Data'!L41 -> 945614.3 | AY30: ='Annual Data'!M41/'Annual Data'!N41 -> 12.020052 | AZ30: ='Annual Data'!O41 -> 2521500 | BA30: ='Annual Data'!P41 -> -6.722856 | BB30: ='Annual Data'!J41 -> 2087491.9 | BC30: ='Annual Data'!B41 -> 2139895 | BE30: =100*((BB30/BB29)-1) -> 2.3253157 | BF30: =100*((BC30/BC29)-1) -> 2.62488 | BH30: 2007 | BI30: ='Annual Data'!Z41*'Annual Data'!AA41 -> 945614.3 | BJ30: ='Annual Data'!AB41/'Annual Data'!AC41 -> 12.020052 | BK30: ='Annual Data'!AD41 -> 2521500 | BL30: ='Annual Data'!AE41 -> -6.722856 | BM30: ='Annual Data'!Y41 -> 2087491.9 | BN30: ='Annual Data'!Q41 -> 2139895 | BP30: =100*((BM30/BM29)-1) -> 2.3253157 | BQ30: =100*((BN30/BN29)-1) -> 2.62488
AR31: 47392 | AS31: ='Quarterly Data'!L234 -> 692387.9 | AT31: ='Quarterly Data'!AA234 -> 695095.9 | AU31: =100*((AS31/AT31)-1) -> -0.38958653 | AW31: 2008 | AX31: ='Annual Data'!K42*'Annual Data'!L42 -> 954262.3 | AY31: ='Annual Data'!M42/'Annual Data'!N42 -> 12.201912 | AZ31: ='Annual Data'!O42 -> 2595500 | BA31: ='Annual Data'!P42 -> -6.72336 | BB31: ='Annual Data'!J42 -> 2131891.2 | BC31: ='Annual Data'!B42 -> 2134571 | BE31: =100*((BB31/BB30)-1) -> 2.1269208 | BF31: =100*((BC31/BC30)-1) -> -0.24879725 | BH31: 2008 | BI31: ='Annual Data'!Z42*'Annual Data'!AA42 -> 954262.3 | BJ31: ='Annual Data'!AB42/'Annual Data'!AC42 -> 12.201912 | BK31: ='Annual Data'!AD42 -> 2595500 | BL31: ='Annual Data'!AE42 -> -6.72336 | BM31: ='Annual Data'!Y42 -> 2131891.2 | BN31: ='Annual Data'!Q42 -> 2134571 | BP31: =100*((BM31/BM30)-1) -> 2.1269208 | BQ31: =100*((BN31/BN30)-1) -> -0.24879725
... AR51: 49218 | AS51: ='Quarterly Data'!L254 -> 745421.2 | AT51: ='Quarterly Data'!AA254 -> 750348.9 | AU51: =100*((AS51/AT51)-1) -> -0.65672116 | AW51: 2028 | AX51: ='Annual Data'!K62*'Annual Data'!L62 -> 1125837.6 | AY51: ='Annual Data'!M62/'Annual Data'!N62 -> 14.148503 | AZ51: ='Annual Data'!O62 -> 3506825.5 | BA51: ='Annual Data'!P62 -> -6.786471 | BB51: ='Annual Data'!J62 -> 2717210.9 | BC51: ='Annual Data'!B62 -> 2696080.6 | BE51: =100*((BB51/BB50)-1) -> 1.4239156 | BF51: =100*((BC51/BC50)-1) -> 1.839685 | BH51: 2028 | BI51: ='Annual Data'!Z62*'Annual Data'!AA62 -> 1124608.3 | BJ51: ='Annual Data'!AB62/'Annual Data'!AC62 -> 14.148503 | BK51: ='Annual Data'!AD62 -> 3518260.2 | BL51: ='Annual Data'!AE62 -> -6.773676 | BM51: ='Annual Data'!Y62 -> 2726583 | BN51: ='Annual Data'!Q62 -> 2714647.4 | BP51: =100*((BM51/BM50)-1) -> 1.4809175 | BQ51: =100*((BN51/BN50)-1) -> 1.8343594
AW52: 2029 | AX52: ='Annual Data'!K63*'Annual Data'!L63 -> 1136256.8 | AY52: ='Annual Data'!M63/'Annual Data'!N63 -> 14.226979 | AZ52: ='Annual Data'!O63 -> 3554214.8 | BA52: ='Annual Data'!P63 -> -6.780026 | BB52: ='Annual Data'!J63 -> 2755281.2 | BC52: ='Annual Data'!B63 -> 2743598.4 | BE52: =100*((BB52/BB51)-1) -> 1.4010801 | BF52: =100*((BC52/BC51)-1) -> 1.762477 | BH52: 2029 | BI52: ='Annual Data'!Z63*'Annual Data'!AA63 -> 1134648.4 | BJ52: ='Annual Data'!AB63/'Annual Data'!AC63 -> 14.226979 | BK52: ='Annual Data'!AD63 -> 3572777.8 | BL52: ='Annual Data'!AE63 -> -6.767708 | BM52: ='Annual Data'!Y63 -> 2765827.8 | BN52: ='Annual Data'!Q63 -> 2760086 | BP52: =100*((BM52/BM51)-1) -> 1.43934 | BQ52: =100*((BN52/BN51)-1) -> 1.6738306
AW53: 2030 | AX53: ='Annual Data'!K64*'Annual Data'!L64 -> 1145515.5 | AY53: ='Annual Data'!M64/'Annual Data'!N64 -> 14.302916 | AZ53: ='Annual Data'!O64 -> 3603829.8 | BA53: ='Annual Data'!P64 -> -6.770878 | BB53: ='Annual Data'!J64 -> 2794047.7 | BC53: ='Annual Data'!B64 -> 2787932 | BE53: =100*((BB53/BB52)-1) -> 1.4069889 | BF53: =100*((BC53/BC52)-1) -> 1.6158925 | BH53: 2030 | BI53: ='Annual Data'!Z64*'Annual Data'!AA64 -> 1144251.4 | BJ53: ='Annual Data'!AB64/'Annual Data'!AC64 -> 14.302916 | BK53: ='Annual Data'!AD64 -> 3628879 | BL53: ='Annual Data'!AE64 -> -6.759888 | BM53: ='Annual Data'!Y64 -> 2806111 | BN53: ='Annual Data'!Q64 -> 2804164.9 | BP53: =100*((BM53/BM52)-1) -> 1.4564609 | BQ53: =100*((BN53/BN52)-1) -> 1.5970118
AW54: 2031 | AX54: ='Annual Data'!K65*'Annual Data'!L65 -> 1154388.8 | AY54: ='Annual Data'!M65/'Annual Data'!N65 -> 14.375743 | AZ54: ='Annual Data'!O65 -> 3656608.5 | BA54: ='Annual Data'!P65 -> -6.759206 | BB54: ='Annual Data'!J65 -> 2834792.3 | BC54: ='Annual Data'!B65 -> 2832594.8 | BE54: =100*((BB54/BB53)-1) -> 1.4582643 | BF54: =100*((BC54/BC53)-1) -> 1.6020046 | BH54: 2031 | BI54: ='Annual Data'!Z65*'Annual Data'!AA65 -> 1153862.9 | BJ54: ='Annual Data'!AB65/'Annual Data'!AC65 -> 14.375743 | BK54: ='Annual Data'!AD65 -> 3687931.5 | BL54: ='Annual Data'!AE65 -> -6.749416 | BM54: ='Annual Data'!Y65 -> 2849000.3 | BN54: ='Annual Data'!Q65 -> 2848839.6 | BP54: =100*((BM54/BM53)-1) -> 1.5284249 | BQ54: =100*((BN54/BN53)-1) -> 1.5931552
AW55: 2032 | AX55: ='Annual Data'!K66*'Annual Data'!L66 -> 1162996.9 | AY55: ='Annual Data'!M66/'Annual Data'!N66 -> 14.444172 | AZ55: ='Annual Data'!O66 -> 3713127.5 | BA55: ='Annual Data'!P66 -> -6.745538 | BB55: ='Annual Data'!J66 -> 2877552.9 | BC55: ='Annual Data'!B66 -> 2877149.6 | BE55: =100*((BB55/BB54)-1) -> 1.5084209 | BF55: =100*((BC55/BC54)-1) -> 1.5729324 | BH55: 2032 | BI55: ='Annual Data'!Z66*'Annual Data'!AA66 -> 1163032.8 | BJ55: ='Annual Data'!AB66/'Annual Data'!AC66 -> 14.444172 | BK55: ='Annual Data'!AD66 -> 3750560.8 | BL55: ='Annual Data'!AE66 -> -6.736639 | BM55: ='Annual Data'!Y66 -> 2893790.1 | BN55: ='Annual Data'!Q66 -> 2893722.4 | BP55: =100*((BM55/BM54)-1) -> 1.5721234 | BQ55: =100*((BN55/BN54)-1) -> 1.5754766
AW56: 2033 | AX56: ='Annual Data'!K67*'Annual Data'!L67 -> 1171104 | AY56: ='Annual Data'!M67/'Annual Data'!N67 -> 14.507863 | AZ56: ='Annual Data'!O67 -> 3773137.5 | BA56: ='Annual Data'!P67 -> -6.729813 | BB56: ='Annual Data'!J67 -> 2921984.8 | BC56: ='Annual Data'!B67 -> 2921985.5 | BE56: =100*((BB56/BB55)-1) -> 1.5440863 | BF56: =100*((BC56/BC55)-1) -> 1.5583444 | BH56: 2033 | BI56: ='Annual Data'!Z67*'Annual Data'!AA67 -> 1171186.6 | BJ56: ='Annual Data'!AB67/'Annual Data'!AC67 -> 14.507863 | BK56: ='Annual Data'!AD67 -> 3816466.8 | BL56: ='Annual Data'!AE67 -> -6.721356 | BM56: ='Annual Data'!Y67 -> 2939683.8 | BN56: ='Annual Data'!Q67 -> 2939685.7 | BP56: =100*((BM56/BM55)-1) -> 1.5859374 | BQ56: =100*((BN56/BN55)-1) -> 1.5883797
AW57: 2034 | AX57: ='Annual Data'!K68*'Annual Data'!L68 -> 1177582.8 | AY57: ='Annual Data'!M68/'Annual Data'!N68 -> 14.566618 | AZ57: ='Annual Data'!O68 -> 3836108.2 | BA57: ='Annual Data'!P68 -> -6.712835 | BB57: ='Annual Data'!J68 -> 2965535.8 | BC57: ='Annual Data'!B68 -> 2965535.9 | BE57: =100*((BB57/BB56)-1) -> 1.4904595 | BF57: =100*((BC57/BC56)-1) -> 1.4904386 | BH57: 2034 | BI57: ='Annual Data'!Z68*'Annual Data'!AA68 -> 1177591.6 | BJ57: ='Annual Data'!AB68/'Annual Data'!AC68 -> 14.566618 | BK57: ='Annual Data'!AD68 -> 3884986 | BL57: ='Annual Data'!AE68 -> -6.704401 | BM57: ='Annual Data'!Y68 -> 2984695.2 | BN57: ='Annual Data'!Q68 -> 2984697.2 | BP57: =100*((BM57/BM56)-1) -> 1.5311647 | BQ57: =100*((BN57/BN56)-1) -> 1.5311671
AW58: 2035 | AX58: ='Annual Data'!K69*'Annual Data'!L69 -> 1183325.2 | AY58: ='Annual Data'!M69/'Annual Data'!N69 -> 14.6204 | AZ58: ='Annual Data'!O69 -> 3901801.5 | BA58: ='Annual Data'!P69 -> -6.694562 | BB58: ='Annual Data'!J69 -> 3009580.5 | BC58: ='Annual Data'!B69 -> 3009581 | BE58: =100*((BB58/BB57)-1) -> 1.485219 | BF58: =100*((BC58/BC57)-1) -> 1.4852324 | BH58: 2035 | BI58: ='Annual Data'!Z69*'Annual Data'!AA69 -> 1183325.2 | BJ58: ='Annual Data'!AB69/'Annual Data'!AC69 -> 14.6204 | BK58: ='Annual Data'!AD69 -> 3955891.2 | BL58: ='Annual Data'!AE69 -> -6.68615 | BM58: ='Annual Data'!Y69 -> 3030201.1 | BN58: ='Annual Data'!Q69 -> 3030203.2 | BP58: =100*((BM58/BM57)-1) -> 1.5246414 | BQ58: =100*((BN58/BN57)-1) -> 1.5246438
AW59: 2036 | AX59: ='Annual Data'!K70*'Annual Data'!L70 -> 1189094.3 | AY59: ='Annual Data'!M70/'Annual Data'!N70 -> 14.66993 | AZ59: ='Annual Data'!O70 -> 3970259.5 | BA59: ='Annual Data'!P70 -> -6.675002 | BB59: ='Annual Data'!J70 -> 3055423.2 | BC59: ='Annual Data'!B70 -> 3055424.1 | BE59: =100*((BB59/BB58)-1) -> 1.5232256 | BF59: =100*((BC59/BC58)-1) -> 1.5232386 | BH59: 2036 | BI59: ='Annual Data'!Z70*'Annual Data'!AA70 -> 1189094.3 | BJ59: ='Annual Data'!AB70/'Annual Data'!AC70 -> 14.66993 | BK59: ='Annual Data'!AD70 -> 4029250 | BL59: ='Annual Data'!AE70 -> -6.666616 | BM59: ='Annual Data'!Y70 -> 3077430.1 | BN59: ='Annual Data'!Q70 -> 3077431 | BP59: =100*((BM59/BM58)-1) -> 1.5586094 | BQ59: =100*((BN59/BN58)-1) -> 1.5585687
AW60: 2037 | AX60: ='Annual Data'!K71*'Annual Data'!L71 -> 1194862.7 | AY60: ='Annual Data'!M71/'Annual Data'!N71 -> 14.716929 | AZ60: ='Annual Data'!O71 -> 4041537 | BA60: ='Annual Data'!P71 -> -6.655 | BB60: ='Annual Data'!J71 -> 3102526.6 | BC60: ='Annual Data'!B71 -> 3102529.7 | BE60: =100*((BB60/BB59)-1) -> 1.5416326 | BF60: =100*((BC60/BC59)-1) -> 1.5417041 | BH60: 2037 | BI60: ='Annual Data'!Z71*'Annual Data'!AA71 -> 1194862.7 | BJ60: ='Annual Data'!AB71/'Annual Data'!AC71 -> 14.716929 | BK60: ='Annual Data'!AD71 -> 4105132.5 | BL60: ='Annual Data'!AE71 -> -6.646638 | BM60: ='Annual Data'!Y71 -> 3125831 | BN60: ='Annual Data'!Q71 -> 3125832.8 | BP60: =100*((BM60/BM59)-1) -> 1.5727701 | BQ60: =100*((BN60/BN59)-1) -> 1.5727989
AW61: 2038 | AX61: ='Annual Data'!K72*'Annual Data'!L72 -> 1200630.3 | AY61: ='Annual Data'!M72/'Annual Data'!N72 -> 14.761935 | AZ61: ='Annual Data'!O72 -> 4115651 | BA61: ='Annual Data'!P72 -> -6.634227 | BB61: ='Annual Data'!J72 -> 3151203.9 | BC61: ='Annual Data'!B72 -> 3151203.3 | BE61: =100*((BB61/BB60)-1) -> 1.5689567 | BF61: =100*((BC61/BC60)-1) -> 1.5688359 | BH61: 2038 | BI61: ='Annual Data'!Z72*'Annual Data'!AA72 -> 1200630.3 | BJ61: ='Annual Data'!AB72/'Annual Data'!AC72 -> 14.761935 | BK61: ='Annual Data'!AD72 -> 4183569.5 | BL61: ='Annual Data'!AE72 -> -6.625892 | BM61: ='Annual Data'!Y72 -> 3175720.1 | BN61: ='Annual Data'!Q72 -> 3175719.7 | BP61: =100*((BM61/BM60)-1) -> 1.5960268 | BQ61: =100*((BN61/BN60)-1) -> 1.5959555
AW62: 2039 | AX62: ='Annual Data'!K73*'Annual Data'!L73 -> 1206396.9 | AY62: ='Annual Data'!M73/'Annual Data'!N73 -> 14.805608 | AZ62: ='Annual Data'!O73 -> 4192666.2 | BA62: ='Annual Data'!P73 -> -6.613024 | BB62: ='Annual Data'!J73 -> 3201256.6 | BC62: ='Annual Data'!B73 -> 3201256.9 | BE62: =100*((BB62/BB61)-1) -> 1.5883675 | BF62: =100*((BC62/BC61)-1) -> 1.5883964 | BH62: 2039 | BI62: ='Annual Data'!Z73*'Annual Data'!AA73 -> 1206396.9 | BJ62: ='Annual Data'!AB73/'Annual Data'!AC73 -> 14.805608 | BK62: ='Annual Data'!AD73 -> 4264640.5 | BL62: ='Annual Data'!AE73 -> -6.604714 | BM62: ='Annual Data'!Y73 -> 3226906.7 | BN62: ='Annual Data'!Q73 -> 3226906.8 | BP62: =100*((BM62/BM61)-1) -> 1.6118108 | BQ62: =100*((BN62/BN61)-1) -> 1.6118268
AW63: 2040 | AX63: ='Annual Data'!K74*'Annual Data'!L74 -> 1212162.7 | AY63: ='Annual Data'!M74/'Annual Data'!N74 -> 14.848457 | AZ63: ='Annual Data'!O74 -> 4272483.2 | BA63: ='Annual Data'!P74 -> -6.591888 | BB63: ='Annual Data'!J74 -> 3252318.9 | BC63: ='Annual Data'!B74 -> 3252321.1 | BE63: =100*((BB63/BB62)-1) -> 1.5950705 | BF63: =100*((BC63/BC62)-1) -> 1.5951297 | BH63: 2040 | BI63: ='Annual Data'!Z74*'Annual Data'!AA74 -> 1212162.7 | BJ63: ='Annual Data'!AB74/'Annual Data'!AC74 -> 14.848457 | BK63: ='Annual Data'!AD74 -> 4348240.8 | BL63: ='Annual Data'!AE74 -> -6.583605 | BM63: ='Annual Data'!Y74 -> 3279023.8 | BN63: ='Annual Data'!Q74 -> 3279023.8 | BP63: =100*((BM63/BM62)-1) -> 1.6150792 | BQ63: =100*((BN63/BN62)-1) -> 1.6150761
... AW73: 2050 | AX73: ='Annual Data'!K84*'Annual Data'!L84 -> 1251721.8 | AY73: ='Annual Data'!M84/'Annual Data'!N84 -> 15.237496 | AZ73: ='Annual Data'!O84 -> 5199644.2 | BA73: ='Annual Data'!P84 -> -6.384205 | BB73: ='Annual Data'!J84 -> 3775772.8 | BC73: ='Annual Data'!B84 -> 3775776 | BE73: =100*((BB73/BB72)-1) -> 1.3708929 | BF73: =100*((BC73/BC72)-1) -> 1.3709326 | BH73: 2050 | BI73: ='Annual Data'!Z84*'Annual Data'!AA84 -> 1251721.8 | BJ73: ='Annual Data'!AB84/'Annual Data'!AC84 -> 15.237496 | BK73: ='Annual Data'!AD84 -> 5298187 | BL73: ='Annual Data'!AE84 -> -6.376183 | BM73: ='Annual Data'!Y84 -> 3808355.3 | BN73: ='Annual Data'!Q84 -> 3808353.4 | BP73: =100*((BM73/BM72)-1) -> 1.3652152 | BQ73: =100*((BN73/BN72)-1) -> 1.3651646
AW75: Contributions to growth | BH75: Contributions to growth
AX76: Labour supply | AY76: Human capital | AZ76: Capital stock | BA76: Total factor productivity | BB76: Potential output | BC76: GDP | BI76: Labour supply | BJ76: Human capital | BK76: Capital stock | BL76: Total factor productivity | BM76: Potential output | BN76: GDP
AW77: 1990s | AX77: =0.65*(100*((AX22/AX12)^(1/10)-1)) -> 0.10824108 | AY77: =0.3*(100*((AY22/AY12)^(1/10)-1)) -> 0.21475344 | AZ77: =0.35*(100*((AZ22/AZ12)^(1/10)-1)) -> 1.0163732 | BA77: =BB77-AX77-AY77-AZ77 -> 0.94729256 | BB77: =100*((BB22/BB12)^(1/10)-1) -> 2.2866603 | BC77: =100*((BC22/BC12)^(1/10)-1) -> 2.1272833 | BH77: 1990s | BI77: =0.65*(100*((BI22/BI12)^(1/10)-1)) -> 0.10824108 | BJ77: =0.3*(100*((BJ22/BJ12)^(1/10)-1)) -> 0.21475344 | BK77: =0.35*(100*((BK22/BK12)^(1/10)-1)) -> 1.0163732 | BL77: =BM77-BI77-BJ77-BK77 -> 0.94729256 | BM77: =100*((BM22/BM12)^(1/10)-1) -> 2.2866603 | BN77: =100*((BN22/BN12)^(1/10)-1) -> 2.1272833
AW78: 2000s | AX78: =0.65*(100*((AX32/AX22)^(1/10)-1)) -> 0.35329754 | AY78: =0.3*(100*((AY32/AY22)^(1/10)-1)) -> 0.69157841 | AZ78: =0.35*(100*((AZ32/AZ22)^(1/10)-1)) -> 1.0121312 | BA78: =BB78-AX78-AY78-AZ78 -> 0.32329053 | BB78: =100*((BB32/BB22)^(1/10)-1) -> 2.3802976 | BC78: =100*((BC32/BC22)^(1/10)-1) -> 1.6903124 | BH78: 2000s | BI78: =0.65*(100*((BI32/BI22)^(1/10)-1)) -> 0.35329754 | BJ78: =0.3*(100*((BJ32/BJ22)^(1/10)-1)) -> 0.69157841 | BK78: =0.35*(100*((BK32/BK22)^(1/10)-1)) -> 1.0121312 | BL78: =BM78-BI78-BJ78-BK78 -> 0.32329053 | BM78: =100*((BM32/BM22)^(1/10)-1) -> 2.3802976 | BN78: =100*((BN32/BN22)^(1/10)-1) -> 1.6903124
AW79: 2010s | AX79: =0.65*(100*((AX42/AX32)^(1/10)-1)) -> 0.68323656 | AY79: =0.3*(100*((AY42/AY32)^(1/10)-1)) -> 0.23771068 | AZ79: =0.35*(100*((AZ42/AZ32)^(1/10)-1)) -> 0.60924065 | BA79: =BB79-AX79-AY79-AZ79 -> -0.023636277 | BB79: =100*((BB42/BB32)^(1/10)-1) -> 1.5065516 | BC79: =100*((BC42/BC32)^(1/10)-1) -> 1.968899 | BH79: 2010s | BI79: =0.65*(100*((BI42/BI32)^(1/10)-1)) -> 0.68309273 | BJ79: =0.3*(100*((BJ42/BJ32)^(1/10)-1)) -> 0.23771068 | BK79: =0.35*(100*((BK42/BK32)^(1/10)-1)) -> 0.60924065 | BL79: =BM79-BI79-BJ79-BK79 -> -0.023637415 | BM79: =100*((BM42/BM32)^(1/10)-1) -> 1.5064066 | BN79: =100*((BN42/BN32)^(1/10)-1) -> 1.968899
AW80: 2020s | AX80: =0.65*(100*((AX52/AX42)^(1/10)-1)) -> 0.51421511 | AY80: =0.3*(100*((AY52/AY42)^(1/10)-1)) -> 0.18833433 | AZ80: =0.35*(100*((AZ52/AZ42)^(1/10)-1)) -> 0.44401454 | BA80: =BB80-AX80-AY80-AZ80 -> -0.11155222 | BB80: =100*((BB52/BB42)^(1/10)-1) -> 1.0350118 | BC80: =100*((BC52/BC42)^(1/10)-1) -> 1.0387079 | BH80: 2020s | BI80: =0.65*(100*((BI52/BI42)^(1/10)-1)) -> 0.50507865 | BJ80: =0.3*(100*((BJ52/BJ42)^(1/10)-1)) -> 0.18833433 | BK80: =0.35*(100*((BK52/BK42)^(1/10)-1)) -> 0.46248292 | BL80: =BM80-BI80-BJ80-BK80 -> -0.082132298 | BM80: =100*((BM52/BM42)^(1/10)-1) -> 1.0737636 | BN80: =100*((BN52/BN42)^(1/10)-1) -> 1.0992634
AW81: 2030s | AX81: =0.65*(100*((AX62/AX52)^(1/10)-1)) -> 0.39051042 | AY81: =0.3*(100*((AY62/AY52)^(1/10)-1)) -> 0.11983648 | AZ81: =0.35*(100*((AZ62/AZ52)^(1/10)-1)) -> 0.583012 | BA81: =BB81-AX81-AY81-AZ81 -> 0.41819032 | BB81: =100*((BB62/BB52)^(1/10)-1) -> 1.5115492 | BC81: =100*((BC62/BC52)^(1/10)-1) -> 1.5546932 | BH81: 2030s | BI81: =0.65*(100*((BI62/BI52)^(1/10)-1)) -> 0.39977411 | BJ81: =0.3*(100*((BJ62/BJ52)^(1/10)-1)) -> 0.11983648 | BK81: =0.35*(100*((BK62/BK52)^(1/10)-1)) -> 0.62506677 | BL81: =BM81-BI81-BJ81-BK81 -> 0.40911058 | BM81: =100*((BM62/BM52)^(1/10)-1) -> 1.5537879 | BN81: =100*((BN62/BN52)^(1/10)-1) -> 1.5748947
AW82: 2040s | AX82: =0.65*(100*((AX72/AX62)^(1/10)-1)) -> 0.2309095 | AY82: =0.3*(100*((AY72/AY62)^(1/10)-1)) -> 0.079378486 | AZ82: =0.35*(100*((AZ72/AZ62)^(1/10)-1)) -> 0.69147348 | BA82: =BB82-AX82-AY82-AZ82 -> 0.52422301 | BB82: =100*((BB72/BB62)^(1/10)-1) -> 1.5259845 | BC82: =100*((BC72/BC62)^(1/10)-1) -> 1.5259882 | BH82: 2040s | BI82: =0.65*(100*((BI72/BI62)^(1/10)-1)) -> 0.2309095 | BJ82: =0.3*(100*((BJ72/BJ62)^(1/10)-1)) -> 0.079378486 | BK82: =0.35*(100*((BK72/BK62)^(1/10)-1)) -> 0.69828094 | BL82: =BM82-BI82-BJ82-BK82 -> 0.52419538 | BM82: =100*((BM72/BM62)^(1/10)-1) -> 1.5327643 | BN82: =100*((BN72/BN62)^(1/10)-1) -> 1.532764
AW84: diff vs 10-19 | BH84: diff vs 10-19
AW85: 2020-30 | AX85: =AX80-AX$78 -> 0.16091757 | AY85: =AY80-AY$78 -> -0.50324408 | AZ85: =AZ80-AZ$78 -> -0.56811661 | BA85: =BA80-BA$78 -> -0.43484274 | BB85: =BB80-BB$78 -> -1.3452859 | BC85: =BC80-BC$78 -> -0.65160443 | BH85: 2020-30 | BI85: =BI80-BI$78 -> 0.15178111 | BJ85: =BJ80-BJ$78 -> -0.50324408 | BK85: =BK80-BK$78 -> -0.54964823 | BL85: =BL80-BL$78 -> -0.40542283 | BM85: =BM80-BM$78 -> -1.306534 | BN85: =BN80-BN$78 -> -0.591049
AW86: 2030-40 | AX86: =AX81-AX$78 -> 0.037212879 | AY86: =AY81-AY$78 -> -0.57174193 | AZ86: =AZ81-AZ$78 -> -0.42911915 | BA86: =BA81-BA$78 -> 0.094899789 | BB86: =BB81-BB$78 -> -0.86874841 | BC86: =BC81-BC$78 -> -0.13561914 | BH86: 2030-40 | BI86: =BI81-BI$78 -> 0.046476572 | BJ86: =BJ81-BJ$78 -> -0.57174193 | BK86: =BK81-BK$78 -> -0.38706438 | BL86: =BL81-BL$78 -> 0.08582005 | BM86: =BM81-BM$78 -> -0.82650969 | BN86: =BN81-BN$78 -> -0.11541768
AW87: 2040-50 | AX87: =AX82-AX$78 -> -0.12238804 | AY87: =AY82-AY$78 -> -0.61219992 | AZ87: =AZ82-AZ$78 -> -0.32065767 | BA87: =BA82-BA$78 -> 0.20093248 | BB87: =BB82-BB$78 -> -0.85431314 | BC87: =BC82-BC$78 -> -0.16432422 | BH87: 2040-50 | BI87: =BI82-BI$78 -> -0.12238804 | BJ87: =BJ82-BJ$78 -> -0.61219992 | BK87: =BK82-BK$78 -> -0.31385021 | BL87: =BL82-BL$78 -> 0.20090485 | BM87: =BM82-BM$78 -> -0.84753332 | BN87: =BN82-BN$78 -> -0.15754839
AW88: diff | BH88: diff
AW90: diff vs March
AW91: 2020-30 | AX91: =AX85-BI85 -> 0.0091364621 | AY91: =AY85-BJ85 -> 0 | AZ91: =AZ85-BK85 -> -0.018468383 | BA91: =BA85-BL85 -> -0.029419919 | BB91: =BB85-BM85 -> -0.038751839 | BC91: =BC85-BN85 -> -0.060555432
AW92: 2030-40 | AX92: =AX86-BI86 -> -0.0092636933 | AY92: =AY86-BJ86 -> 0 | AZ92: =AZ86-BK86 -> -0.042054763 | BA92: =BA86-BL86 -> 0.0090797385 | BB92: =BB86-BM86 -> -0.042238718 | BC92: =BC86-BN86 -> -0.020201463
AW93: 2040-50 | AX93: =AX87-BI87 -> 0 | AY93: =AY87-BJ87 -> 0 | AZ93: =AZ87-BK87 -> -0.0068074601 | BA93: =BA87-BL87 -> 2.7633587e-05 | BB93: =BB87-BM87 -> -0.0067798265 | BC93: =BC87-BN87 -> -0.0067758295
AW94: diff

Sheet Annual Data
B1: ='Quarterly Data'!D1 -> APR014A.db | C1: ='Quarterly Data'!E1 -> APR014A.db | D1: ='Quarterly Data'!F1 -> APR014A.db | E1: ='Quarterly Data'!G1 -> APR014A.db | F1: ='Quarterly Data'!H1 -> APR014A.db | G1: ='Quarterly Data'!I1 -> APR014A.db | H1: ='Quarterly Data'!J1 -> APR014A.db | I1: ='Quarterly Data'!K1 -> APR014A.db | ... AE1: ='Quarterly Data'!AG1 -> MAR010I.db
B2: ='Quarterly Data'!D2 -> UK | C2: ='Quarterly Data'!E2 -> UK | D2: ='Quarterly Data'!F2 -> UK | E2: ='Quarterly Data'!G2 -> UK | F2: ='Quarterly Data'!H2 -> UK | G2: ='Quarterly Data'!I2 -> UK | H2: ='Quarterly Data'!J2 -> UK | I2: ='Quarterly Data'!K2 -> UK | ... AE2: ='Quarterly Data'!AG2 -> UK
B3: ='Quarterly Data'!D3 -> GDP | C3: ='Quarterly Data'!E3 -> CPI | D3: ='Quarterly Data'!F3 -> X | E3: ='Quarterly Data'!G3 -> XGNF | F3: ='Quarterly Data'!H3 -> M | G3: ='Quarterly Data'!I3 -> MGNF | H3: ='Quarterly Data'!J3 -> IF | I3: ='Quarterly Data'!K3 -> IPNR | ... AE3: ='Quarterly Data'!AG3 -> TREND
B4: ='Quarterly Data'!D4 -> GBR | C4: ='Quarterly Data'!E4 -> GBR | D4: ='Quarterly Data'!F4 -> GBR | E4: ='Quarterly Data'!G4 -> GBR | F4: ='Quarterly Data'!H4 -> GBR | G4: ='Quarterly Data'!I4 -> GBR | H4: ='Quarterly Data'!J4 -> GBR | I4: ='Quarterly Data'!K4 -> GBR | ... AE4: ='Quarterly Data'!AG4 -> GBR
B5: ='Quarterly Data'!D5 -> L | C5: ='Quarterly Data'!E5 -> L | D5: ='Quarterly Data'!F5 -> L | E5: ='Quarterly Data'!G5 -> L | F5: ='Quarterly Data'!H5 -> L | G5: ='Quarterly Data'!I5 -> L | H5: ='Quarterly Data'!J5 -> L | I5: ='Quarterly Data'!K5 -> L | ... AE5: ='Quarterly Data'!AG5 -> L
B6: ='Quarterly Data'!D6 -> 202404 | C6: ='Quarterly Data'!E6 -> 202404 | D6: ='Quarterly Data'!F6 -> 202404 | E6: ='Quarterly Data'!G6 -> 202404 | F6: ='Quarterly Data'!H6 -> 202404 | G6: ='Quarterly Data'!I6 -> 202404 | H6: ='Quarterly Data'!J6 -> 202404 | I6: ='Quarterly Data'!K6 -> 202404 | ... AE6: ='Quarterly Data'!AG6 -> 202302
A7: 1973 | B7: =SUMIF('Quarterly Data'!$B:$B,'Annual Data'!$A7,'Quarterly Data'!D:D) -> 987527 | C7: =AVERAGEIF('Quarterly Data'!$B:$B,'Annual Data'!$A7,'Quarterly Data'!E:E) -> 12.428425 | D7: =SUMIF('Quarterly Data'!$B:$B,'Annual Data'!$A7,'Quarterly Data'!F:F) -> 148219 | E7: =SUMIF('Quarterly Data'!$B:$B,'Annual Data'!$A7,'Quarterly Data'!G:G) -> 57084.06 | F7: =SUMIF('Quarterly Data'!$B:$B,'Annual Data'!$A7,'Quarterly Data'!H:H) -> 141214 | G7: =SUMIF('Quarterly Data'!$B:$B,'Annual Data'!$A7,'Quarterly Data'!I:I) -> -16816.35 | H7: =SUMIF('Quarterly Data'!$B:$B,'Annual Data'!$A7,'Quarterly Data'!J:J) -> 193673 | I7: =SUMIF('Quarterly Data'!$B:$B,'Annual Data'!$A7,'Quarterly Data'!K:K) -> 64130.86 | J7: =SUMIF('Quarterly Data'!$B:$B,'Annual Data'!$A7,'Quarterly Data'!L:L) -> 995761.2 | K7: =AVERAGEIF('Quarterly Data'!$B:$B,'Annual Data'!$A7,'Quarterly Data'!M:M) -> 24874.8 | L7: =AVERAGEIF('Quarterly Data'!$B:$B,'Annual Data'!$A7,'Quarterly Data'!N:N) -> 0.001 | M7: =AVERAGEIF('Quarterly Data'!$B:$B,'Annual Data'!$A7,'Quarterly Data'!O:O) -> 286021.4 | N7: =AVERAGEIF('Quarterly Data'!$B:$B,'Annual Data'!$A7,'Quarterly Data'!P:P) -> 35322.815 | O7: =AVERAGEIF('Quarterly Data'!$B:$B,'Annual Data'!$A7,'Quarterly Data'!Q:Q) -> 1074461.5 | P7: =SUMIF('Quarterly Data'!$B:$B,'Annual Data'!$A7,'Quarterly Data'!R:R) -> -7.690755 | Q7: =SUMIF('Quarterly Data'!$B:$B,'Annual Data'!$A7,'Quarterly Data'!S:S) -> 987527 | R7: =AVERAGEIF('Quarterly Data'!$B:$B,'Annual Data'!$A7,'Quarterly Data'!T:T) -> 12.428425 | S7: =SUMIF('Quarterly Data'!$B:$B,'Annual Data'!$A7,'Quarterly Data'!U:U) -> 148219 | T7: =SUMIF('Quarterly Data'!$B:$B,'Annual Data'!$A7,'Quarterly Data'!V:V) -> 57084.06 | U7: =SUMIF('Quarterly Data'!$B:$B,'Annual Data'!$A7,'Quarterly Data'!W:W) -> 141214 | V7: =SUMIF('Quarterly Data'!$B:$B,'Annual Data'!$A7,'Quarterly Data'!X:X) -> -16816.35 | W7: =SUMIF('Quarterly Data'!$B:$B,'Annual Data'!$A7,'Quarterly Data'!Y:Y) -> 193673 | X7: =SUMIF('Quarterly Data'!$B:$B,'Annual Data'!$A7,'Quarterly Data'!Z:Z) -> 64130.86 | Y7: =SUMIF('Quarterly Data'!$B:$B,'Annual Data'!$A7,'Quarterly Data'!AA:AA) -> 995761.2 | Z7: =AVERAGEIF('Quarterly Data'!$B:$B,'Annual Data'!$A7,'Quarterly Data'!AB:AB) -> 24874.8 | AA7: =AVERAGEIF('Quarterly Data'!$B:$B,'Annual Data'!$A7,'Quarterly Data'!AC:AC) -> 0.001 | AB7: =AVERAGEIF('Quarterly Data'!$B:$B,'Annual Data'!$A7,'Quarterly Data'!AD:AD) -> 286021.4 | AC7: =AVERAGEIF('Quarterly Data'!$B:$B,'Annual Data'!$A7,'Quarterly Data'!AE:AE) -> 35322.815 | AD7: =AVERAGEIF('Quarterly Data'!$B:$B,'Annual Data'!$A7,'Quarterly Data'!AF:AF) -> 1074461.5 | AE7: =SUMIF('Quarterly Data'!$B:$B,'Annual Data'!$A7,'Quarterly Data'!AG:AG) -> -7.690755
A8: 1974 | B8: =SUMIF('Quarterly Data'!$B:$B,'Annual Data'!$A8,'Quarterly Data'!D:D) -> 962880 | C8: =AVERAGEIF('Quarterly Data'!$B:$B,'Annual Data'!$A8,'Quarterly Data'!E:E) -> 14.383608 | D8: =SUMIF('Quarterly Data'!$B:$B,'Annual Data'!$A8,'Quarterly Data'!F:F) -> 158966 | E8: =SUMIF('Quarterly Data'!$B:$B,'Annual Data'!$A8,'Quarterly Data'!G:G) -> 63320.36 | F8: =SUMIF('Quarterly Data'!$B:$B,'Annual Data'!$A8,'Quarterly Data'!H:H) -> 142566 | G8: =SUMIF('Quarterly Data'!$B:$B,'Annual Data'!$A8,'Quarterly Data'!I:I) -> -9135.5 | H8: =SUMIF('Quarterly Data'!$B:$B,'Annual Data'!$A8,'Quarterly Data'!J:J) -> 179218 | I8: =SUMIF('Quarterly Data'!$B:$B,'Annual Data'!$A8,'Quarterly Data'!K:K) -> 67920.03 | J8: =SUMIF('Quarterly Data'!$B:$B,'Annual Data'!$A8,'Quarterly Data'!L:L) -> 1007843.7 | K8: =AVERAGEIF('Quarterly Data'!$B:$B,'Annual Data'!$A8,'Quarterly Data'!M:M) -> 24938.64 | L8: =AVERAGEIF('Quarterly Data'!$B:$B,'Annual Data'!$A8,'Quarterly Data'!N:N) -> 0.001 | M8: =AVERAGEIF('Quarterly Data'!$B:$B,'Annual Data'!$A8,'Quarterly Data'!O:O) -> 288869 | N8: =AVERAGEIF('Quarterly Data'!$B:$B,'Annual Data'!$A8,'Quarterly Data'!P:P) -> 35332.713 | O8: =AVERAGEIF('Quarterly Data'!$B:$B,'Annual Data'!$A8,'Quarterly Data'!Q:Q) -> 1107914 | P8: =SUMIF('Quarterly Data'!$B:$B,'Annual Data'!$A8,'Quarterly Data'!R:R) -> -7.706507 | Q8: =SUMIF('Quarterly Data'!$B:$B,'Annual Data'!$A8,'Quarterly Data'!S:S) -> 962880 | R8: =AVERAGEIF('Quarterly Data'!$B:$B,'Annual Data'!$A8,'Quarterly Data'!T:T) -> 14.383608 | S8: =SUMIF('Quarterly Data'!$B:$B,'Annual Data'!$A8,'Quarterly Data'!U:U) -> 158966 | T8: =SUMIF('Quarterly Data'!$B:$B,'Annual Data'!$A8,'Quarterly Data'!V:V) -> 63320.36 | U8: =SUMIF('Quarterly Data'!$B:$B,'Annual Data'!$A8,'Quarterly Data'!W:W) -> 142566 | V8: =SUMIF('Quarterly Data'!$B:$B,'Annual Data'!$A8,'Quarterly Data'!X:X) -> -9135.5 | W8: =SUMIF('Quarterly Data'!$B:$B,'Annual Data'!$A8,'Quarterly Data'!Y:Y) -> 179218 | X8: =SUMIF('Quarterly Data'!$B:$B,'Annual Data'!$A8,'Quarterly Data'!Z:Z) -> 67920.03 | Y8: =SUMIF('Quarterly Data'!$B:$B,'Annual Data'!$A8,'Quarterly Data'!AA:AA) -> 1007843.7 | Z8: =AVERAGEIF('Quarterly Data'!$B:$B,'Annual Data'!$A8,'Quarterly Data'!AB:AB) -> 24938.64 | AA8: =AVERAGEIF('Quarterly Data'!$B:$B,'Annual Data'!$A8,'Quarterly Data'!AC:AC) -> 0.001 | AB8: =AVERAGEIF('Quarterly Data'!$B:$B,'Annual Data'!$A8,'Quarterly Data'!AD:AD) -> 288869 | AC8: =AVERAGEIF('Quarterly Data'!$B:$B,'Annual Data'!$A8,'Quarterly Data'!AE:AE) -> 35332.713 | AD8: =AVERAGEIF('Quarterly Data'!$B:$B,'Annual Data'!$A8,'Quarterly Data'!AF:AF) -> 1107914 | AE8: =SUMIF('Quarterly Data'!$B:$B,'Annual Data'!$A8,'Quarterly Data'!AG:AG) -> -7.706507
A9: 1975 | B9: =SUMIF('Quarterly Data'!$B:$B,'Annual Data'!$A9,'Quarterly Data'!D:D) -> 948361 | C9: =AVERAGEIF('Quarterly Data'!$B:$B,'Annual Data'!$A9,'Quarterly Data'!E:E) -> 17.648755 | D9: =SUMIF('Quarterly Data'!$B:$B,'Annual Data'!$A9,'Quarterly Data'!F:F) -> 154269 | E9: =SUMIF('Quarterly Data'!$B:$B,'Annual Data'!$A9,'Quarterly Data'!G:G) -> 61668.59 | F9: =SUMIF('Quarterly Data'!$B:$B,'Annual Data'!$A9,'Quarterly Data'!H:H) -> 133122 | G9: =SUMIF('Quarterly Data'!$B:$B,'Annual Data'!$A9,'Quarterly Data'!I:I) -> 190.6 | H9: =SUMIF('Quarterly Data'!$B:$B,'Annual Data'!$A9,'Quarterly Data'!J:J) -> 168504 | I9: =SUMIF('Quarterly Data'!$B:$B,'Annual Data'!$A9,'Quarterly Data'!K:K) -> 67112.32 | J9: =SUMIF('Quarterly Data'!$B:$B,'Annual Data'!$A9,'Quarterly Data'!L:L) -> 1015923.8 | K9: =AVERAGEIF('Quarterly Data'!$B:$B,'Annual Data'!$A9,'Quarterly Data'!M:M) -> 24932.055 | L9: =AVERAGEIF('Quarterly Data'!$B:$B,'Annual Data'!$A9,'Quarterly Data'!N:N) -> 0.001 | M9: =AVERAGEIF('Quarterly Data'!$B:$B,'Annual Data'!$A9,'Quarterly Data'!O:O) -> 291532.5 | N9: =AVERAGEIF('Quarterly Data'!$B:$B,'Annual Data'!$A9,'Quarterly Data'!P:P) -> 35327.333 | O9: =AVERAGEIF('Quarterly Data'!$B:$B,'Annual Data'!$A9,'Quarterly Data'!Q:Q) -> 1137370.5 | P9: =SUMIF('Quarterly Data'!$B:$B,'Annual Data'!$A9,'Quarterly Data'!R:R) -> -7.722293 | Q9: =SUMIF('Quarterly Data'!$B:$B,'Annual Data'!$A9,'Quarterly Data'!S:S) -> 948361 | R9: =AVERAGEIF('Quarterly Data'!$B:$B,'Annual Data'!$A9,'Quarterly Data'!T:T) -> 17.648755 | S9: =SUMIF('Quarterly Data'!$B:$B,'Annual Data'!$A9,'Quarterly Data'!U:U) -> 154269 | T9: =SUMIF('Quarterly Data'!$B:$B,'Annual Data'!$A9,'Quarterly Data'!V:V) -> 61668.59 | U9: =SUMIF('Quarterly Data'!$B:$B,'Annual Data'!$A9,'Quarterly Data'!W:W) -> 133122 | V9: =SUMIF('Quarterly Data'!$B:$B,'Annual Data'!$A9,'Quarterly Data'!X:X) -> 190.6 | W9: =SUMIF('Quarterly Data'!$B:$B,'Annual Data'!$A9,'Quarterly Data'!Y:Y) -> 168504 | X9: =SUMIF('Quarterly Data'!$B:$B,'Annual Data'!$A9,'Quarterly Data'!Z:Z) -> 67112.32 | Y9: =SUMIF('Quarterly Data'!$B:$B,'Annual Data'!$A9,'Quarterly Data'!AA:AA) -> 1015923.8 | Z9: =AVERAGEIF('Quarterly Data'!$B:$B,'Annual Data'!$A9,'Quarterly Data'!AB:AB) -> 24932.055 | AA9: =AVERAGEIF('Quarterly Data'!$B:$B,'Annual Data'!$A9,'Quarterly Data'!AC:AC) -> 0.001 | AB9: =AVERAGEIF('Quarterly Data'!$B:$B,'Annual Data'!$A9,'Quarterly Data'!AD:AD) -> 291532.5 | AC9: =AVERAGEIF('Quarterly Data'!$B:$B,'Annual Data'!$A9,'Quarterly Data'!AE:AE) -> 35327.333 | AD9: =AVERAGEIF('Quarterly Data'!$B:$B,'Annual Data'!$A9,'Quarterly Data'!AF:AF) -> 1137370.5 | AE9: =SUMIF('Quarterly Data'!$B:$B,'Annual Data'!$A9,'Quarterly Data'!AG:AG) -> -7.722293
A10: 1976 | B10: =SUMIF('Quarterly Data'!$B:$B,'Annual Data'!$A10,'Quarterly Data'!D:D) -> 976967 | C10: =AVERAGEIF('Quarterly Data'!$B:$B,'Annual Data'!$A10,'Quarterly Data'!E:E) -> 20.412077 | D10: =SUMIF('Quarterly Data'!$B:$B,'Annual Data'!$A10,'Quarterly Data'!F:F) -> 167901 | E10: =SUMIF('Quarterly Data'!$B:$B,'Annual Data'!$A10,'Quarterly Data'!G:G) -> 67181.58 | F10: =SUMIF('Quarterly Data'!$B:$B,'Annual Data'!$A10,'Quarterly Data'!H:H) -> 139646 | G10: =SUMIF('Quarterly Data'!$B:$B,'Annual Data'!$A10,'Quarterly Data'!I:I) -> 6920.575 | H10: =SUMIF('Quarterly Data'!$B:$B,'Annual Data'!$A10,'Quarterly Data'!J:J) -> 169648 | I10: =SUMIF('Quarterly Data'!$B:$B,'Annual Data'!$A10,'Quarterly Data'!K:K) -> 68650.5 | J10: =SUMIF('Quarterly Data'!$B:$B,'Annual Data'!$A10,'Quarterly Data'!L:L) -> 1020748.1 | K10: =AVERAGEIF('Quarterly Data'!$B:$B,'Annual Data'!$A10,'Quarterly Data'!M:M) -> 24850.212 | L10: =AVERAGEIF('Quarterly Data'!$B:$B,'Annual Data'!$A10,'Quarterly Data'!N:N) -> 0.001 | M10: =AVERAGEIF('Quarterly Data'!$B:$B,'Annual Data'!$A10,'Quarterly Data'!O:O) -> 293842.92 | N10: =AVERAGEIF('Quarterly Data'!$B:$B,'Annual Data'!$A10,'Quarterly Data'!P:P) -> 35352.077 | O10: =AVERAGEIF('Quarterly Data'!$B:$B,'Annual Data'!$A10,'Quarterly Data'!Q:Q) -> 1165169.5 | P10: =SUMIF('Quarterly Data'!$B:$B,'Annual Data'!$A10,'Quarterly Data'!R:R) -> -7.738109 | Q10: =SUMIF('Quarterly Data'!$B:$B,'Annual Data'!$A10,'Quarterly Data'!S:S) -> 976967 | R10: =AVERAGEIF('Quarterly Data'!$B:$B,'Annual Data'!$A10,'Quarterly Data'!T:T) -> 20.412077 | S10: =SUMIF('Quarterly Data'!$B:$B,'Annual Data'!$A10,'Quarterly Data'!U:U) -> 167901 | T10: =SUMIF('Quarterly Data'!$B:$B,'Annual Data'!$A10,'Quarterly Data'!V:V) -> 67181.58 | U10: =SUMIF('Quarterly Data'!$B:$B,'Annual Data'!$A10,'Quarterly Data'!W:W) -> 139646 | V10: =SUMIF('Quarterly Data'!$B:$B,'Annual Data'!$A10,'Quarterly Data'!X:X) -> 6920.575 | W10: =SUMIF('Quarterly Data'!$B:$B,'Annual Data'!$A10,'Quarterly Data'!Y:Y) -> 169648 | X10: =SUMIF('Quarterly Data'!$B:$B,'Annual Data'!$A10,'Quarterly Data'!Z:Z) -> 68650.5 | Y10: =SUMIF('Quarterly Data'!$B:$B,'Annual Data'!$A10,'Quarterly Data'!AA:AA) -> 1020748.1 | Z10: =AVERAGEIF('Quarterly Data'!$B:$B,'Annual Data'!$A10,'Quarterly Data'!AB:AB) -> 24850.212 | AA10: =AVERAGEIF('Quarterly Data'!$B:$B,'Annual Data'!$A10,'Quarterly Data'!AC:AC) -> 0.001 | AB10: =AVERAGEIF('Quarterly Data'!$B:$B,'Annual Data'!$A10,'Quarterly Data'!AD:AD) -> 293842.92 | AC10: =AVERAGEIF('Quarterly Data'!$B:$B,'Annual Data'!$A10,'Quarterly Data'!AE:AE) -> 35352.077 | AD10: =AVERAGEIF('Quarterly Data'!$B:$B,'Annual Data'!$A10,'Quarterly Data'!AF:AF) -> 1165169.5 | AE10: =SUMIF('Quarterly Data'!$B:$B,'Annual Data'!$A10,'Quarterly Data'!AG:AG) -> -7.738109
A11: 1977 | B11: =SUMIF('Quarterly Data'!$B:$B,'Annual Data'!$A11,'Quarterly Data'!D:D) -> 1001004 | C11: =AVERAGEIF('Quarterly Data'!$B:$B,'Annual Data'!$A11,'Quarterly Data'!E:E) -> 23.462157 | D11: =SUMIF('Quarterly Data'!$B:$B,'Annual Data'!$A11,'Quarterly Data'!F:F) -> 178972 | E11: =SUMIF('Quarterly Data'!$B:$B,'Annual Data'!$A11,'Quarterly Data'!G:G) -> 70121.68 | F11: =SUMIF('Quarterly Data'!$B:$B,'Annual Data'!$A11,'Quarterly Data'!H:H) -> 142063 | G11: =SUMIF('Quarterly Data'!$B:$B,'Annual Data'!$A11,'Quarterly Data'!I:I) -> 22647.55 | H11: =SUMIF('Quarterly Data'!$B:$B,'Annual Data'!$A11,'Quarterly Data'!J:J) -> 172276 | I11: =SUMIF('Quarterly Data'!$B:$B,'Annual Data'!$A11,'Quarterly Data'!K:K) -> 69620.72 | J11: =SUMIF('Quarterly Data'!$B:$B,'Annual Data'!$A11,'Quarterly Data'!L:L) -> 1024172.3 | K11: =AVERAGEIF('Quarterly Data'!$B:$B,'Annual Data'!$A11,'Quarterly Data'!M:M) -> 24800.743 | L11: =AVERAGEIF('Quarterly Data'!$B:$B,'Annual Data'!$A11,'Quarterly Data'!N:N) -> 0.001 | M11: =AVERAGEIF('Quarterly Data'!$B:$B,'Annual Data'!$A11,'Quarterly Data'!O:O) -> 295875.2 | N11: =AVERAGEIF('Quarterly Data'!$B:$B,'Annual Data'!$A11,'Quarterly Data'!P:P) -> 35501.052 | O11: =AVERAGEIF('Quarterly Data'!$B:$B,'Annual Data'!$A11,'Quarterly Data'!Q:Q) -> 1190688 | P11: =SUMIF('Quarterly Data'!$B:$B,'Annual Data'!$A11,'Quarterly Data'!R:R) -> -7.753957 | Q11: =SUMIF('Quarterly Data'!$B:$B,'Annual Data'!$A11,'Quarterly Data'!S:S) -> 1001004 | R11: =AVERAGEIF('Quarterly Data'!$B:$B,'Annual Data'!$A11,'Quarterly Data'!T:T) -> 23.462157 | S11: =SUMIF('Quarterly Data'!$B:$B,'Annual Data'!$A11,'Quarterly Data'!U:U) -> 178972 | T11: =SUMIF('Quarterly Data'!$B:$B,'Annual Data'!$A11,'Quarterly Data'!V:V) -> 70121.68 | U11: =SUMIF('Quarterly Data'!$B:$B,'Annual Data'!$A11,'Quarterly Data'!W:W) -> 142063 | V11: =SUMIF('Quarterly Data'!$B:$B,'Annual Data'!$A11,'Quarterly Data'!X:X) -> 22647.55 | W11: =SUMIF('Quarterly Data'!$B:$B,'Annual Data'!$A11,'Quarterly Data'!Y:Y) -> 172276 | X11: =SUMIF('Quarterly Data'!$B:$B,'Annual Data'!$A11,'Quarterly Data'!Z:Z) -> 69620.72 | Y11: =SUMIF('Quarterly Data'!$B:$B,'Annual Data'!$A11,'Quarterly Data'!AA:AA) -> 1024172.3 | Z11: =AVERAGEIF('Quarterly Data'!$B:$B,'Annual Data'!$A11,'Quarterly Data'!AB:AB) -> 24800.743 | AA11: =AVERAGEIF('Quarterly Data'!$B:$B,'Annual Data'!$A11,'Quarterly Data'!AC:AC) -> 0.001 | AB11: =AVERAGEIF('Quarterly Data'!$B:$B,'Annual Data'!$A11,'Quarterly Data'!AD:AD) -> 295875.2 | AC11: =AVERAGEIF('Quarterly Data'!$B:$B,'Annual Data'!$A11,'Quarterly Data'!AE:AE) -> 35501.052 | AD11: =AVERAGEIF('Quarterly Data'!$B:$B,'Annual Data'!$A11,'Quarterly Data'!AF:AF) -> 1190688 | AE11: =SUMIF('Quarterly Data'!$B:$B,'Annual Data'!$A11,'Quarterly Data'!AG:AG) -> -7.753957
A12: 1978 | B12: =SUMIF('Quarterly Data'!$B:$B,'Annual Data'!$A12,'Quarterly Data'!D:D) -> 1042953 | C12: =AVERAGEIF('Quarterly Data'!$B:$B,'Annual Data'!$A12,'Quarterly Data'!E:E) -> 25.215303 | D12: =SUMIF('Quarterly Data'!$B:$B,'Annual Data'!$A12,'Quarterly Data'!F:F) -> 181926 | E12: =SUMIF('Quarterly Data'!$B:$B,'Annual Data'!$A12,'Quarterly Data'!G:G) -> 67878.55 | F12: =SUMIF('Quarterly Data'!$B:$B,'Annual Data'!$A12,'Quarterly Data'!H:H) -> 147034 | G12: =SUMIF('Quarterly Data'!$B:$B,'Annual Data'!$A12,'Quarterly Data'!I:I) -> 30741.1 | H12: =SUMIF('Quarterly Data'!$B:$B,'Annual Data'!$A12,'Quarterly Data'!J:J) -> 184970 | I12: =SUMIF('Quarterly Data'!$B:$B,'Annual Data'!$A12,'Quarterly Data'!K:K) -> 72055.12 | J12: =SUMIF('Quarterly Data'!$B:$B,'Annual Data'!$A12,'Quarterly Data'!L:L) -> 1032547.7 | K12: =AVERAGEIF('Quarterly Data'!$B:$B,'Annual Data'!$A12,'Quarterly Data'!M:M) -> 24703.73 | L12: =AVERAGEIF('Quarterly Data'!$B:$B,'Annual Data'!$A12,'Quarterly Data'!N:N) -> 0.001 | M12: =AVERAGEIF('Quarterly Data'!$B:$B,'Annual Data'!$A12,'Quarterly Data'!O:O) -> 297883.12 | N12: =AVERAGEIF('Quarterly Data'!$B:$B,'Annual Data'!$A12,'Quarterly Data'!P:P) -> 35670.84 | O12: =AVERAGEIF('Quarterly Data'!$B:$B,'Annual Data'!$A12,'Quarterly Data'!Q:Q) -> 1219033 | P12: =SUMIF('Quarterly Data'!$B:$B,'Annual Data'!$A12,'Quarterly Data'!R:R) -> -7.745033 | Q12: =SUMIF('Quarterly Data'!$B:$B,'Annual Data'!$A12,'Quarterly Data'!S:S) -> 1042953 | R12: =AVERAGEIF('Quarterly Data'!$B:$B,'Annual Data'!$A12,'Quarterly Data'!T:T) -> 25.215303 | S12: =SUMIF('Quarterly Data'!$B:$B,'Annual Data'!$A12,'Quarterly Data'!U:U) -> 181926 | T12: =SUMIF('Quarterly Data'!$B:$B,'Annual Data'!$A12,'Quarterly Data'!V:V) -> 67878.55 | U12: =SUMIF('Quarterly Data'!$B:$B,'Annual Data'!$A12,'Quarterly Data'!W:W) -> 147034 | V12: =SUMIF('Quarterly Data'!$B:$B,'Annual Data'!$A12,'Quarterly Data'!X:X) -> 30741.1 | W12: =SUMIF('Quarterly Data'!$B:$B,'Annual Data'!$A12,'Quarterly Data'!Y:Y) -> 184970 | X12: =SUMIF('Quarterly Data'!$B:$B,'Annual Data'!$A12,'Quarterly Data'!Z:Z) -> 72055.12 | Y12: =SUMIF('Quarterly Data'!$B:$B,'Annual Data'!$A12,'Quarterly Data'!AA:AA) -> 1032547.7 | Z12: =AVERAGEIF('Quarterly Data'!$B:$B,'Annual Data'!$A12,'Quarterly Data'!AB:AB) -> 24703.73 | AA12: =AVERAGEIF('Quarterly Data'!$B:$B,'Annual Data'!$A12,'Quarterly Data'!AC:AC) -> 0.001 | AB12: =AVERAGEIF('Quarterly Data'!$B:$B,'Annual Data'!$A12,'Quarterly Data'!AD:AD) -> 297883.12 | AC12: =AVERAGEIF('Quarterly Data'!$B:$B,'Annual Data'!$A12,'Quarterly Data'!AE:AE) -> 35670.84 | AD12: =AVERAGEIF('Quarterly Data'!$B:$B,'Annual Data'!$A12,'Quarterly Data'!AF:AF) -> 1219033 | AE12: =SUMIF('Quarterly Data'!$B:$B,'Annual Data'!$A12,'Quarterly Data'!AG:AG) -> -7.745033
A13: 1979 | B13: =SUMIF('Quarterly Data'!$B:$B,'Annual Data'!$A13,'Quarterly Data'!D:D) -> 1081838 | C13: =AVERAGEIF('Quarterly Data'!$B:$B,'Annual Data'!$A13,'Quarterly Data'!E:E) -> 28.082898 | D13: =SUMIF('Quarterly Data'!$B:$B,'Annual Data'!$A13,'Quarterly Data'!F:F) -> 188405 | E13: =SUMIF('Quarterly Data'!$B:$B,'Annual Data'!$A13,'Quarterly Data'!G:G) -> 60671.4 | F13: =SUMIF('Quarterly Data'!$B:$B,'Annual Data'!$A13,'Quarterly Data'!H:H) -> 160714 | G13: =SUMIF('Quarterly Data'!$B:$B,'Annual Data'!$A13,'Quarterly Data'!I:I) -> 40981.055 | H13: =SUMIF('Quarterly Data'!$B:$B,'Annual Data'!$A13,'Quarterly Data'!J:J) -> 200887 | I13: =SUMIF('Quarterly Data'!$B:$B,'Annual Data'!$A13,'Quarterly Data'!K:K) -> 74494.33 | J13: =SUMIF('Quarterly Data'!$B:$B,'Annual Data'!$A13,'Quarterly Data'!L:L) -> 1054600.4 | K13: =AVERAGEIF('Quarterly Data'!$B:$B,'Annual Data'!$A13,'Quarterly Data'!M:M) -> 24709.438 | L13: =AVERAGEIF('Quarterly Data'!$B:$B,'Annual Data'!$A13,'Quarterly Data'!N:N) -> 0.001 | M13: =AVERAGEIF('Quarterly Data'!$B:$B,'Annual Data'!$A13,'Quarterly Data'!O:O) -> 300120.33 | N13: =AVERAGEIF('Quarterly Data'!$B:$B,'Annual Data'!$A13,'Quarterly Data'!P:P) -> 35882.96 | O13: =AVERAGEIF('Quarterly Data'!$B:$B,'Annual Data'!$A13,'Quarterly Data'!Q:Q) -> 1245311.5 | P13: =SUMIF('Quarterly Data'!$B:$B,'Annual Data'!$A13,'Quarterly Data'!R:R) -> -7.694968 | Q13: =SUMIF('Quarterly Data'!$B:$B,'Annual Data'!$A13,'Quarterly Data'!S:S) -> 1081838 | R13: =AVERAGEIF('Quarterly Data'!$B:$B,'Annual Data'!$A13,'Quarterly Data'!T:T) -> 28.082898 | S13: =SUMIF('Quarterly Data'!$B:$B,'Annual Data'!$A13,'Quarterly Data'!U:U) -> 188405 | T13: =SUMIF('Quarterly Data'!$B:$B,'Annual Data'!$A13,'Quarterly Data'!V:V) -> 60671.4 | U13: =SUMIF('Quarterly Data'!$B:$B,'Annual Data'!$A13,'Quarterly Data'!W:W) -> 160714 | V13: =SUMIF('Quarterly Data'!$B:$B,'Annual Data'!$A13,'Quarterly Data'!X:X) -> 40981.055 | W13: =SUMIF('Quarterly Data'!$B:$B,'Annual Data'!$A13,'Quarterly Data'!Y:Y) -> 200887 | X13: =SUMIF('Quarterly Data'!$B:$B,'Annual Data'!$A13,'Quarterly Data'!Z:Z) -> 74494.33 | Y13: =SUMIF('Quarterly Data'!$B:$B,'Annual Data'!$A13,'Quarterly Data'!AA:AA) -> 1054600.4 | Z13: =AVERAGEIF('Quarterly Data'!$B:$B,'Annual Data'!$A13,'Quarterly Data'!AB:AB) -> 24709.438 | AA13: =AVERAGEIF('Quarterly Data'!$B:$B,'Annual Data'!$A13,'Quarterly Data'!AC:AC) -> 0.001 | AB13: =AVERAGEIF('Quarterly Data'!$B:$B,'Annual Data'!$A13,'Quarterly Data'!AD:AD) -> 300120.33 | AC13: =AVERAGEIF('Quarterly Data'!$B:$B,'Annual Data'!$A13,'Quarterly Data'!AE:AE) -> 35882.96 | AD13: =AVERAGEIF('Quarterly Data'!$B:$B,'Annual Data'!$A13,'Quarterly Data'!AF:AF) -> 1245311.5 | AE13: =SUMIF('Quarterly Data'!$B:$B,'Annual Data'!$A13,'Quarterly Data'!AG:AG) -> -7.694968
A14: 1980 | B14: =SUMIF('Quarterly Data'!$B:$B,'Annual Data'!$A14,'Quarterly Data'!D:D) -> 1059660 | C14: =AVERAGEIF('Quarterly Data'!$B:$B,'Annual Data'!$A14,'Quarterly Data'!E:E) -> 32.338673 | D14: =SUMIF('Quarterly Data'!$B:$B,'Annual Data'!$A14,'Quarterly Data'!F:F) -> 187439 | E14: =SUMIF('Quarterly Data'!$B:$B,'Annual Data'!$A14,'Quarterly Data'!G:G) -> 64610.76 | F14: =SUMIF('Quarterly Data'!$B:$B,'Annual Data'!$A14,'Quarterly Data'!H:H) -> 154997 | G14: =SUMIF('Quarterly Data'!$B:$B,'Annual Data'!$A14,'Quarterly Data'!I:I) -> 43481.54 | H14: =SUMIF('Quarterly Data'!$B:$B,'Annual Data'!$A14,'Quarterly Data'!J:J) -> 187961 | I14: =SUMIF('Quarterly Data'!$B:$B,'Annual Data'!$A14,'Quarterly Data'!K:K) -> 71284.42 | J14: =SUMIF('Quarterly Data'!$B:$B,'Annual Data'!$A14,'Quarterly Data'!L:L) -> 1080987.1 | K14: =AVERAGEIF('Quarterly Data'!$B:$B,'Annual Data'!$A14,'Quarterly Data'!M:M) -> 24765.53 | L14: =AVERAGEIF('Quarterly Data'!$B:$B,'Annual Data'!$A14,'Quarterly Data'!N:N) -> 0.001 | M14: =AVERAGEIF('Quarterly Data'!$B:$B,'Annual Data'!$A14,'Quarterly Data'!O:O) -> 306731.33 | N14: =AVERAGEIF('Quarterly Data'!$B:$B,'Annual Data'!$A14,'Quarterly Data'!P:P) -> 36102.315 | O14: =AVERAGEIF('Quarterly Data'!$B:$B,'Annual Data'!$A14,'Quarterly Data'!Q:Q) -> 1265800.5 | P14: =SUMIF('Quarterly Data'!$B:$B,'Annual Data'!$A14,'Quarterly Data'!R:R) -> -7.645228 | Q14: =SUMIF('Quarterly Data'!$B:$B,'Annual Data'!$A14,'Quarterly Data'!S:S) -> 1059660 | R14: =AVERAGEIF('Quarterly Data'!$B:$B,'Annual Data'!$A14,'Quarterly Data'!T:T) -> 32.338673 | S14: =SUMIF('Quarterly Data'!$B:$B,'Annual Data'!$A14,'Quarterly Data'!U:U) -> 187439 | T14: =SUMIF('Quarterly Data'!$B:$B,'Annual Data'!$A14,'Quarterly Data'!V:V) -> 64610.76 | U14: =SUMIF('Quarterly Data'!$B:$B,'Annual Data'!$A14,'Quarterly Data'!W:W) -> 154997 | V14: =SUMIF('Quarterly Data'!$B:$B,'Annual Data'!$A14,'Quarterly Data'!X:X) -> 43481.54 | W14: =SUMIF('Quarterly Data'!$B:$B,'Annual Data'!$A14,'Quarterly Data'!Y:Y) -> 187961 | X14: =SUMIF('Quarterly Data'!$B:$B,'Annual Data'!$A14,'Quarterly Data'!Z:Z) -> 71284.42 | Y14: =SUMIF('Quarterly Data'!$B:$B,'Annual Data'!$A14,'Quarterly Data'!AA:AA) -> 1080987.1 | Z14: =AVERAGEIF('Quarterly Data'!$B:$B,'Annual Data'!$A14,'Quarterly Data'!AB:AB) -> 24765.53 | AA14: =AVERAGEIF('Quarterly Data'!$B:$B,'Annual Data'!$A14,'Quarterly Data'!AC:AC) -> 0.001 | AB14: =AVERAGEIF('Quarterly Data'!$B:$B,'Annual Data'!$A14,'Quarterly Data'!AD:AD) -> 306731.33 | AC14: =AVERAGEIF('Quarterly Data'!$B:$B,'Annual Data'!$A14,'Quarterly Data'!AE:AE) -> 36102.315 | AD14: =AVERAGEIF('Quarterly Data'!$B:$B,'Annual Data'!$A14,'Quarterly Data'!AF:AF) -> 1265800.5 | AE14: =SUMIF('Quarterly Data'!$B:$B,'Annual Data'!$A14,'Quarterly Data'!AG:AG) -> -7.645228
A15: 1981 | B15: =SUMIF('Quarterly Data'!$B:$B,'Annual Data'!$A15,'Quarterly Data'!D:D) -> 1052374 | C15: =AVERAGEIF('Quarterly Data'!$B:$B,'Annual Data'!$A15,'Quarterly Data'!E:E) -> 36.157795 | D15: =SUMIF('Quarterly Data'!$B:$B,'Annual Data'!$A15,'Quarterly Data'!F:F) -> 186305 | E15: =SUMIF('Quarterly Data'!$B:$B,'Annual Data'!$A15,'Quarterly Data'!G:G) -> 54092.85 | F15: =SUMIF('Quarterly Data'!$B:$B,'Annual Data'!$A15,'Quarterly Data'!H:H) -> 150582 | G15: =SUMIF('Quarterly Data'!$B:$B,'Annual Data'!$A15,'Quarterly Data'!I:I) -> 48510.055 | H15: =SUMIF('Quarterly Data'!$B:$B,'Annual Data'!$A15,'Quarterly Data'!J:J) -> 175495 | I15: =SUMIF('Quarterly Data'!$B:$B,'Annual Data'!$A15,'Quarterly Data'!K:K) -> 66146.92 | J15: =SUMIF('Quarterly Data'!$B:$B,'Annual Data'!$A15,'Quarterly Data'!L:L) -> 1096885.7 | K15: =AVERAGEIF('Quarterly Data'!$B:$B,'Annual Data'!$A15,'Quarterly Data'!M:M) -> 24659.65 | L15: =AVERAGEIF('Quarterly Data'!$B:$B,'Annual Data'!$A15,'Quarterly Data'!N:N) -> 0.001 | M15: =AVERAGEIF('Quarterly Data'!$B:$B,'Annual Data'!$A15,'Quarterly Data'!O:O) -> 309382.7 | N15: =AVERAGEIF('Quarterly Data'!$B:$B,'Annual Data'!$A15,'Quarterly Data'!P:P) -> 36300.177 | O15: =AVERAGEIF('Quarterly Data'!$B:$B,'Annual Data'!$A15,'Quarterly Data'!Q:Q) -> 1278218.5 | P15: =SUMIF('Quarterly Data'!$B:$B,'Annual Data'!$A15,'Quarterly Data'!R:R) -> -7.595809 | Q15: =SUMIF('Quarterly Data'!$B:$B,'Annual Data'!$A15,'Quarterly Data'!S:S) -> 1052374 | R15: =AVERAGEIF('Quarterly Data'!$B:$B,'Annual Data'!$A15,'Quarterly Data'!T:T) -> 36.157795 | S15: =SUMIF('Quarterly Data'!$B:$B,'Annual Data'!$A15,'Quarterly Data'!U:U) -> 186305 | T15: =SUMIF('Quarterly Data'!$B:$B,'Annual Data'!$A15,'Quarterly Data'!V:V) -> 54092.85 | U15: =SUMIF('Quarterly Data'!$B:$B,'Annual Data'!$A15,'Quarterly Data'!W:W) -> 150582 | V15: =SUMIF('Quarterly Data'!$B:$B,'Annual Data'!$A15,'Quarterly Data'!X:X) -> 48510.055 | W15: =SUMIF('Quarterly Data'!$B:$B,'Annual Data'!$A15,'Quarterly Data'!Y:Y) -> 175495 | X15: =SUMIF('Quarterly Data'!$B:$B,'Annual Data'!$A15,'Quarterly Data'!Z:Z) -> 66146.92 | Y15: =SUMIF('Quarterly Data'!$B:$B,'Annual Data'!$A15,'Quarterly Data'!AA:AA) -> 1096885.7 | Z15: =AVERAGEIF('Quarterly Data'!$B:$B,'Annual Data'!$A15,'Quarterly Data'!AB:AB) -> 24659.65 | AA15: =AVERAGEIF('Quarterly Data'!$B:$B,'Annual Data'!$A15,'Quarterly Data'!AC:AC) -> 0.001 | AB15: =AVERAGEIF('Quarterly Data'!$B:$B,'Annual Data'!$A15,'Quarterly Data'!AD:AD) -> 309382.7 | AC15: =AVERAGEIF('Quarterly Data'!$B:$B,'Annual Data'!$A15,'Quarterly Data'!AE:AE) -> 36300.177 | AD15: =AVERAGEIF('Quarterly Data'!$B:$B,'Annual Data'!$A15,'Quarterly Data'!AF:AF) -> 1278218.5 | AE15: =SUMIF('Quarterly Data'!$B:$B,'Annual Data'!$A15,'Quarterly Data'!AG:AG) -> -7.595809
A16: 1982 | B16: =SUMIF('Quarterly Data'!$B:$B,'Annual Data'!$A16,'Quarterly Data'!D:D) -> 1073055 | C16: =AVERAGEIF('Quarterly Data'!$B:$B,'Annual Data'!$A16,'Quarterly Data'!E:E) -> 39.09056 | D16: =SUMIF('Quarterly Data'!$B:$B,'Annual Data'!$A16,'Quarterly Data'!F:F) -> 187924 | E16: =SUMIF('Quarterly Data'!$B:$B,'Annual Data'!$A16,'Quarterly Data'!G:G) -> 54553.54 | F16: =SUMIF('Quarterly Data'!$B:$B,'Annual Data'!$A16,'Quarterly Data'!H:H) -> 157406 | G16: =SUMIF('Quarterly Data'!$B:$B,'Annual Data'!$A16,'Quarterly Data'!I:I) -> 59126.38 | H16: =SUMIF('Quarterly Data'!$B:$B,'Annual Data'!$A16,'Quarterly Data'!J:J) -> 184492 | I16: =SUMIF('Quarterly Data'!$B:$B,'Annual Data'!$A16,'Quarterly Data'!K:K) -> 68777.61 | J16: =SUMIF('Quarterly Data'!$B:$B,'Annual Data'!$A16,'Quarterly Data'!L:L) -> 1103412.6 | K16: =AVERAGEIF('Quarterly Data'!$B:$B,'Annual Data'!$A16,'Quarterly Data'!M:M) -> 24297.707 | L16: =AVERAGEIF('Quarterly Data'!$B:$B,'Annual Data'!$A16,'Quarterly Data'!N:N) -> 0.001 | M16: =AVERAGEIF('Quarterly Data'!$B:$B,'Annual Data'!$A16,'Quarterly Data'!O:O) -> 311708.92 | N16: =AVERAGEIF('Quarterly Data'!$B:$B,'Annual Data'!$A16,'Quarterly Data'!P:P) -> 36500.68 | O16: =AVERAGEIF('Quarterly Data'!$B:$B,'Annual Data'!$A16,'Quarterly Data'!Q:Q) -> 1288706.5 | P16: =SUMIF('Quarterly Data'!$B:$B,'Annual Data'!$A16,'Quarterly Data'!R:R) -> -7.546708 | Q16: =SUMIF('Quarterly Data'!$B:$B,'Annual Data'!$A16,'Quarterly Data'!S:S) -> 1073055 | R16: =AVERAGEIF('Quarterly Data'!$B:$B,'Annual Data'!$A16,'Quarterly Data'!T:T) -> 39.09056 | S16: =SUMIF('Quarterly Data'!$B:$B,'Annual Data'!$A16,'Quarterly Data'!U:U) -> 187924 | T16: =SUMIF('Quarterly Data'!$B:$B,'Annual Data'!$A16,'Quarterly Data'!V:V) -> 54553.54 | U16: =SUMIF('Quarterly Data'!$B:$B,'Annual Data'!$A16,'Quarterly Data'!W:W) -> 157406 | V16: =SUMIF('Quarterly Data'!$B:$B,'Annual Data'!$A16,'Quarterly Data'!X:X) -> 59126.38 | W16: =SUMIF('Quarterly Data'!$B:$B,'Annual Data'!$A16,'Quarterly Data'!Y:Y) -> 184492 | X16: =SUMIF('Quarterly Data'!$B:$B,'Annual Data'!$A16,'Quarterly Data'!Z:Z) -> 68777.61 | Y16: =SUMIF('Quarterly Data'!$B:$B,'Annual Data'!$A16,'Quarterly Data'!AA:AA) -> 1103412.6 | Z16: =AVERAGEIF('Quarterly Data'!$B:$B,'Annual Data'!$A16,'Quarterly Data'!AB:AB) -> 24297.707 | AA16: =AVERAGEIF('Quarterly Data'!$B:$B,'Annual Data'!$A16,'Quarterly Data'!AC:AC) -> 0.001 | AB16: =AVERAGEIF('Quarterly Data'!$B:$B,'Annual Data'!$A16,'Quarterly Data'!AD:AD) -> 311708.92 | AC16: =AVERAGEIF('Quarterly Data'!$B:$B,'Annual Data'!$A16,'Quarterly Data'!AE:AE) -> 36500.68 | AD16: =AVERAGEIF('Quarterly Data'!$B:$B,'Annual Data'!$A16,'Quarterly Data'!AF:AF) -> 1288706.5 | AE16: =SUMIF('Quarterly Data'!$B:$B,'Annual Data'!$A16,'Quarterly Data'!AG:AG) -> -7.546708
A17: 1983 | B17: =SUMIF('Quarterly Data'!$B:$B,'Annual Data'!$A17,'Quarterly Data'!D:D) -> 1117759 | C17: =AVERAGEIF('Quarterly Data'!$B:$B,'Annual Data'!$A17,'Quarterly Data'!E:E) -> 41.019672 | D17: =SUMIF('Quarterly Data'!$B:$B,'Annual Data'!$A17,'Quarterly Data'!F:F) -> 191250 | E17: =SUMIF('Quarterly Data'!$B:$B,'Annual Data'!$A17,'Quarterly Data'!G:G) -> 52090.42 | F17: =SUMIF('Quarterly Data'!$B:$B,'Annual Data'!$A17,'Quarterly Data'!H:H) -> 167113 | G17: =SUMIF('Quarterly Data'!$B:$B,'Annual Data'!$A17,'Quarterly Data'!I:I) -> 74218.83 | H17: =SUMIF('Quarterly Data'!$B:$B,'Annual Data'!$A17,'Quarterly Data'!J:J) -> 197849 | I17: =SUMIF('Quarterly Data'!$B:$B,'Annual Data'!$A17,'Quarterly Data'!K:K) -> 69744.62 | J17: =SUMIF('Quarterly Data'!$B:$B,'Annual Data'!$A17,'Quarterly Data'!L:L) -> 1121588.5 | K17: =AVERAGEIF('Quarterly Data'!$B:$B,'Annual Data'!$A17,'Quarterly Data'!M:M) -> 24304.682 | L17: =AVERAGEIF('Quarterly Data'!$B:$B,'Annual Data'!$A17,'Quarterly Data'!N:N) -> 0.001 | M17: =AVERAGEIF('Quarterly Data'!$B:$B,'Annual Data'!$A17,'Quarterly Data'!O:O) -> 314668.83 | N17: =AVERAGEIF('Quarterly Data'!$B:$B,'Annual Data'!$A17,'Quarterly Data'!P:P) -> 36776.192 | O17: =AVERAGEIF('Quarterly Data'!$B:$B,'Annual Data'!$A17,'Quarterly Data'!Q:Q) -> 1301611.5 | P17: =SUMIF('Quarterly Data'!$B:$B,'Annual Data'!$A17,'Quarterly Data'!R:R) -> -7.497925 | Q17: =SUMIF('Quarterly Data'!$B:$B,'Annual Data'!$A17,'Quarterly Data'!S:S) -> 1117759 | R17: =AVERAGEIF('Quarterly Data'!$B:$B,'Annual Data'!$A17,'Quarterly Data'!T:T) -> 41.019672 | S17: =SUMIF('Quarterly Data'!$B:$B,'Annual Data'!$A17,'Quarterly Data'!U:U) -> 191250 | T17: =SUMIF('Quarterly Data'!$B:$B,'Annual Data'!$A17,'Quarterly Data'!V:V) -> 52090.42 | U17: =SUMIF('Quarterly Data'!$B:$B,'Annual Data'!$A17,'Quarterly Data'!W:W) -> 167113 | V17: =SUMIF('Quarterly Data'!$B:$B,'Annual Data'!$A17,'Quarterly Data'!X:X) -> 74218.83 | W17: =SUMIF('Quarterly Data'!$B:$B,'Annual Data'!$A17,'Quarterly Data'!Y:Y) -> 197849 | X17: =SUMIF('Quarterly Data'!$B:$B,'Annual Data'!$A17,'Quarterly Data'!Z:Z) -> 69744.62 | Y17: =SUMIF('Quarterly Data'!$B:$B,'Annual Data'!$A17,'Quarterly Data'!AA:AA) -> 1121588.5 | Z17: =AVERAGEIF('Quarterly Data'!$B:$B,'Annual Data'!$A17,'Quarterly Data'!AB:AB) -> 24304.682 | AA17: =AVERAGEIF('Quarterly Data'!$B:$B,'Annual Data'!$A17,'Quarterly Data'!AC:AC) -> 0.001 | AB17: =AVERAGEIF('Quarterly Data'!$B:$B,'Annual Data'!$A17,'Quarterly Data'!AD:AD) -> 314668.83 | AC17: =AVERAGEIF('Quarterly Data'!$B:$B,'Annual Data'!$A17,'Quarterly Data'!AE:AE) -> 36776.192 | AD17: =AVERAGEIF('Quarterly Data'!$B:$B,'Annual Data'!$A17,'Quarterly Data'!AF:AF) -> 1301611.5 | AE17: =SUMIF('Quarterly Data'!$B:$B,'Annual Data'!$A17,'Quarterly Data'!AG:AG) -> -7.497925
A18: 1984 | B18: =SUMIF('Quarterly Data'!$B:$B,'Annual Data'!$A18,'Quarterly Data'!D:D) -> 1142579 | C18: =AVERAGEIF('Quarterly Data'!$B:$B,'Annual Data'!$A18,'Quarterly Data'!E:E) -> 42.766303 | D18: =SUMIF('Quarterly Data'!$B:$B,'Annual Data'!$A18,'Quarterly Data'!F:F) -> 203561 | E18: =SUMIF('Quarterly Data'!$B:$B,'Annual Data'!$A18,'Quarterly Data'!G:G) -> 57978.81 | F18: =SUMIF('Quarterly Data'!$B:$B,'Annual Data'!$A18,'Quarterly Data'!H:H) -> 182917 | G18: =SUMIF('Quarterly Data'!$B:$B,'Annual Data'!$A18,'Quarterly Data'!I:I) -> 77955.4 | H18: =SUMIF('Quarterly Data'!$B:$B,'Annual Data'!$A18,'Quarterly Data'!J:J) -> 210577 | I18: =SUMIF('Quarterly Data'!$B:$B,'Annual Data'!$A18,'Quarterly Data'!K:K) -> 77615.76 | J18: =SUMIF('Quarterly Data'!$B:$B,'Annual Data'!$A18,'Quarterly Data'!L:L) -> 1160834.9 | K18: =AVERAGEIF('Quarterly Data'!$B:$B,'Annual Data'!$A18,'Quarterly Data'!M:M) -> 24910.802 | L18: =AVERAGEIF('Quarterly Data'!$B:$B,'Annual Data'!$A18,'Quarterly Data'!N:N) -> 0.001 | M18: =AVERAGEIF('Quarterly Data'!$B:$B,'Annual Data'!$A18,'Quarterly Data'!O:O) -> 318382.53 | N18: =AVERAGEIF('Quarterly Data'!$B:$B,'Annual Data'!$A18,'Quarterly Data'!P:P) -> 37029.132 | O18: =AVERAGEIF('Quarterly Data'!$B:$B,'Annual Data'!$A18,'Quarterly Data'!Q:Q) -> 1322354.2 | P18: =SUMIF('Quarterly Data'!$B:$B,'Annual Data'!$A18,'Quarterly Data'!R:R) -> -7.449458 | Q18: =SUMIF('Quarterly Data'!$B:$B,'Annual Data'!$A18,'Quarterly Data'!S:S) -> 1142579 | R18: =AVERAGEIF('Quarterly Data'!$B:$B,'Annual Data'!$A18,'Quarterly Data'!T:T) -> 42.766303 | S18: =SUMIF('Quarterly Data'!$B:$B,'Annual Data'!$A18,'Quarterly Data'!U:U) -> 203561 | T18: =SUMIF('Quarterly Data'!$B:$B,'Annual Data'!$A18,'Quarterly Data'!V:V) -> 57978.81 | U18: =SUMIF('Quarterly Data'!$B:$B,'Annual Data'!$A18,'Quarterly Data'!W:W) -> 182917 | V18: =SUMIF('Quarterly Data'!$B:$B,'Annual Data'!$A18,'Quarterly Data'!X:X) -> 77955.4 | W18: =SUMIF('Quarterly Data'!$B:$B,'Annual Data'!$A18,'Quarterly Data'!Y:Y) -> 210577 | X18: =SUMIF('Quarterly Data'!$B:$B,'Annual Data'!$A18,'Quarterly Data'!Z:Z) -> 77615.76 | Y18: =SUMIF('Quarterly Data'!$B:$B,'Annual Data'!$A18,'Quarterly Data'!AA:AA) -> 1160834.9 | Z18: =AVERAGEIF('Quarterly Data'!$B:$B,'Annual Data'!$A18,'Quarterly Data'!AB:AB) -> 24910.802 | AA18: =AVERAGEIF('Quarterly Data'!$B:$B,'Annual Data'!$A18,'Quarterly Data'!AC:AC) -> 0.001 | AB18: =AVERAGEIF('Quarterly Data'!$B:$B,'Annual Data'!$A18,'Quarterly Data'!AD:AD) -> 318382.53 | AC18: =AVERAGEIF('Quarterly Data'!$B:$B,'Annual Data'!$A18,'Quarterly Data'!AE:AE) -> 37029.132 | AD18: =AVERAGEIF('Quarterly Data'!$B:$B,'Annual Data'!$A18,'Quarterly Data'!AF:AF) -> 1322354.2 | AE18: =SUMIF('Quarterly Data'!$B:$B,'Annual Data'!$A18,'Quarterly Data'!AG:AG) -> -7.449458
... A358: 2324 | B358: =SUMIF('Quarterly Data'!$B:$B,'Annual Data'!$A358,'Quarterly Data'!D:D) -> 0 | C358: =AVERAGEIF('Quarterly Data'!$B:$B,'Annual Data'!$A358,'Quarterly Data'!E:E) -> #DIV/0! | D358: =SUMIF('Quarterly Data'!$B:$B,'Annual Data'!$A358,'Quarterly Data'!F:F) -> 0 | E358: =SUMIF('Quarterly Data'!$B:$B,'Annual Data'!$A358,'Quarterly Data'!G:G) -> 0 | F358: =SUMIF('Quarterly Data'!$B:$B,'Annual Data'!$A358,'Quarterly Data'!H:H) -> 0 | G358: =SUMIF('Quarterly Data'!$B:$B,'Annual Data'!$A358,'Quarterly Data'!I:I) -> 0 | H358: =SUMIF('Quarterly Data'!$B:$B,'Annual Data'!$A358,'Quarterly Data'!J:J) -> 0 | I358: =SUMIF('Quarterly Data'!$B:$B,'Annual Data'!$A358,'Quarterly Data'!K:K) -> 0 | J358: =SUMIF('Quarterly Data'!$B:$B,'Annual Data'!$A358,'Quarterly Data'!L:L) -> 0 | K358: =AVERAGEIF('Quarterly Data'!$B:$B,'Annual Data'!$A358,'Quarterly Data'!M:M) -> #DIV/0! | L358: =AVERAGEIF('Quarterly Data'!$B:$B,'Annual Data'!$A358,'Quarterly Data'!N:N) -> #DIV/0! | M358: =AVERAGEIF('Quarterly Data'!$B:$B,'Annual Data'!$A358,'Quarterly Data'!O:O) -> #DIV/0! | N358: =AVERAGEIF('Quarterly Data'!$B:$B,'Annual Data'!$A358,'Quarterly Data'!P:P) -> #DIV/0! | O358: =AVERAGEIF('Quarterly Data'!$B:$B,'Annual Data'!$A358,'Quarterly Data'!Q:Q) -> #DIV/0! | P358: =SUMIF('Quarterly Data'!$B:$B,'Annual Data'!$A358,'Quarterly Data'!R:R) -> 0 | Q358: =SUMIF('Quarterly Data'!$B:$B,'Annual Data'!$A358,'Quarterly Data'!S:S) -> 0 | R358: =AVERAGEIF('Quarterly Data'!$B:$B,'Annual Data'!$A358,'Quarterly Data'!T:T) -> #DIV/0! | S358: =SUMIF('Quarterly Data'!$B:$B,'Annual Data'!$A358,'Quarterly Data'!U:U) -> 0 | T358: =SUMIF('Quarterly Data'!$B:$B,'Annual Data'!$A358,'Quarterly Data'!V:V) -> 0 | U358: =SUMIF('Quarterly Data'!$B:$B,'Annual Data'!$A358,'Quarterly Data'!W:W) -> 0 | V358: =SUMIF('Quarterly Data'!$B:$B,'Annual Data'!$A358,'Quarterly Data'!X:X) -> 0 | W358: =SUMIF('Quarterly Data'!$B:$B,'Annual Data'!$A358,'Quarterly Data'!Y:Y) -> 0 | X358: =SUMIF('Quarterly Data'!$B:$B,'Annual Data'!$A358,'Quarterly Data'!Z:Z) -> 0 | Y358: =SUMIF('Quarterly Data'!$B:$B,'Annual Data'!$A358,'Quarterly Data'!AA:AA) -> 0 | Z358: =AVERAGEIF('Quarterly Data'!$B:$B,'Annual Data'!$A358,'Quarterly Data'!AB:AB) -> #DIV/0! | AA358: =AVERAGEIF('Quarterly Data'!$B:$B,'Annual Data'!$A358,'Quarterly Data'!AC:AC) -> #DIV/0! | AB358: =AVERAGEIF('Quarterly Data'!$B:$B,'Annual Data'!$A358,'Quarterly Data'!AD:AD) -> #DIV/0! | AC358: =AVERAGEIF('Quarterly Data'!$B:$B,'Annual Data'!$A358,'Quarterly Data'!AE:AE) -> #DIV/0! | AD358: =AVERAGEIF('Quarterly Data'!$B:$B,'Annual Data'!$A358,'Quarterly Data'!AF:AF) -> #DIV/0! | AE358: =SUMIF('Quarterly Data'!$B:$B,'Annual Data'!$A358,'Quarterly Data'!AG:AG) -> 0

Sheet Quarterly Data
D1: APR014A.db | E1: =$D$1 -> APR014A.db | F1: =$D$1 -> APR014A.db | G1: =$D$1 -> APR014A.db | H1: =$D$1 -> APR014A.db | I1: =$D$1 -> APR014A.db | J1: =$D$1 -> APR014A.db | K1: =$D$1 -> APR014A.db | L1: =$D$1 -> APR014A.db | ... R1: =$D$1 -> APR014A.db | S1: MAR010I.db | T1: =$S$1 -> MAR010I.db | U1: =$S$1 -> MAR010I.db | V1: =$S$1 -> MAR010I.db | W1: =$S$1 -> MAR010I.db | X1: =$S$1 -> MAR010I.db | Y1: =$S$1 -> MAR010I.db | Z1: =$S$1 -> MAR010I.db | AA1: =$S$1 -> MAR010I.db | ... AG1: =$S$1 -> MAR010I.db | AH1: JAN010B.db | AI1: =$AH$1 -> JAN010B.db | AJ1: =$AH$1 -> JAN010B.db | AK1: =$AH$1 -> JAN010B.db | AL1: =$AH$1 -> JAN010B.db | AM1: =$AH$1 -> JAN010B.db | AN1: =$AH$1 -> JAN010B.db | AO1: =$AH$1 -> JAN010B.db | AP1: =$AH$1 -> JAN010B.db | ... AV1: =$AH$1 -> JAN010B.db
D2: UK | E2: UK | F2: UK | G2: UK | H2: UK | I2: UK | J2: UK | K2: UK | L2: UK | M2: UK | N2: UK | O2: UK | P2: UK | Q2: UK | R2: UK | S2: UK | T2: UK | U2: UK | V2: UK | W2: UK | X2: UK | Y2: UK | Z2: UK | AA2: UK | AB2: UK | AC2: UK | AD2: UK | AE2: UK | AF2: UK | AG2: UK | AH2: UK | AI2: UK | AJ2: UK | AK2: UK | AL2: UK | AM2: UK | AN2: UK | AO2: UK | AP2: UK | AQ2: UK | AR2: UK | AS2: UK | AT2: UK | AU2: UK | AV2: UK
D3: GDP | E3: CPI | F3: X | G3: XGNF | H3: M | I3: MGNF | J3: IF | K3: IPNR | L3: YHAT | M3: ESTAR | N3: AVHR | O3: EDUC | P3: POP15_64 | Q3: K | R3: TREND | S3: GDP | T3: CPI | U3: X | V3: XGNF | W3: M | X3: MGNF | Y3: IF | Z3: IPNR | AA3: YHAT | AB3: ESTAR | AC3: AVHR | AD3: EDUC | AE3: POP15_64 | AF3: K | AG3: TREND | AH3: GDP | AI3: CPI | AJ3: X | AK3: XGNF | AL3: M | AM3: MGNF | AN3: IF | AO3: IPNR | AP3: YHAT | AQ3: ESTAR | AR3: AVHR | AS3: EDUC | AT3: POP15_64 | AU3: K | AV3: TREND
D4: GBR | E4: GBR | F4: GBR | G4: GBR | H4: GBR | I4: GBR | J4: GBR | K4: GBR | L4: GBR | M4: GBR | N4: GBR | O4: GBR | P4: GBR | Q4: GBR | R4: GBR | S4: GBR | T4: GBR | U4: GBR | V4: GBR | W4: GBR | X4: GBR | Y4: GBR | Z4: GBR | AA4: GBR | AB4: GBR | AC4: GBR | AD4: GBR | AE4: GBR | AF4: GBR | AG4: GBR | AH4: GBR | AI4: GBR | AJ4: GBR | AK4: GBR | AL4: GBR | AM4: GBR | AN4: GBR | AO4: GBR | AP4: GBR | AQ4: GBR | AR4: GBR | AS4: GBR | AT4: GBR | AU4: GBR | AV4: GBR
D5: L | E5: L | F5: L | G5: L | H5: L | I5: L | J5: L | K5: L | L5: L | M5: L | N5: L | O5: L | P5: L | Q5: L | R5: L | S5: L | T5: L | U5: L | V5: L | W5: L | X5: L | Y5: L | Z5: L | AA5: L | AB5: L | AC5: L | AD5: L | AE5: L | AF5: L | AG5: L | AH5: L | AI5: L | AJ5: L | AK5: L | AL5: L | AM5: L | AN5: L | AO5: L | AP5: L | AQ5: L | AR5: L | AS5: L | AT5: L | AU5: L | AV5: L
C6: =C358+5 -> 2329 | D6: {=_xlfn.CONCAT(INDEX(GMW!$A$2:$NE$150,MATCH(1,(GMW!$NE$2:$NE$150=D$3)*(GMW!$ND$2:$ND$150=D$4)*(GMW!$NF$2:$NF$150=D$1),0),$C6-1966),"0",(INDEX(GMW!$A$2:$NE$150,MATCH(1,(GMW!$NE$2:$NE$150=D$3)*(GMW!$ND$2:$ND$150=D$4)*(GMW!$NF$2:$NF$150=D$1),0),$C6-1965)))} -> 202404 | E6: {=_xlfn.CONCAT(INDEX(GMW!$A$2:$NE$150,MATCH(1,(GMW!$NE$2:$NE$150=E$3)*(GMW!$ND$2:$ND$150=E$4)*(GMW!$NF$2:$NF$150=E$1),0),$C6-1966),"0",(INDEX(GMW!$A$2:$NE$150,MATCH(1,(GMW!$NE$2:$NE$150=E$3)*(GMW!$ND$2:$ND$150=E$4)*(GMW!$NF$2:$NF$150=E$1),0),$C6-1965)))} -> 202404 | F6: {=_xlfn.CONCAT(INDEX(GMW!$A$2:$NE$150,MATCH(1,(GMW!$NE$2:$NE$150=F$3)*(GMW!$ND$2:$ND$150=F$4)*(GMW!$NF$2:$NF$150=F$1),0),$C6-1966),"0",(INDEX(GMW!$A$2:$NE$150,MATCH(1,(GMW!$NE$2:$NE$150=F$3)*(GMW!$ND$2:$ND$150=F$4)*(GMW!$NF$2:$NF$150=F$1),0),$C6-1965)))} -> 202404 | G6: {=_xlfn.CONCAT(INDEX(GMW!$A$2:$NE$150,MATCH(1,(GMW!$NE$2:$NE$150=G$3)*(GMW!$ND$2:$ND$150=G$4)*(GMW!$NF$2:$NF$150=G$1),0),$C6-1966),"0",(INDEX(GMW!$A$2:$NE$150,MATCH(1,(GMW!$NE$2:$NE$150=G$3)*(GMW!$ND$2:$ND$150=G$4)*(GMW!$NF$2:$NF$150=G$1),0),$C6-1965)))} -> 202404 | H6: {=_xlfn.CONCAT(INDEX(GMW!$A$2:$NE$150,MATCH(1,(GMW!$NE$2:$NE$150=H$3)*(GMW!$ND$2:$ND$150=H$4)*(GMW!$NF$2:$NF$150=H$1),0),$C6-1966),"0",(INDEX(GMW!$A$2:$NE$150,MATCH(1,(GMW!$NE$2:$NE$150=H$3)*(GMW!$ND$2:$ND$150=H$4)*(GMW!$NF$2:$NF$150=H$1),0),$C6-1965)))} -> 202404 | I6: {=_xlfn.CONCAT(INDEX(GMW!$A$2:$NE$150,MATCH(1,(GMW!$NE$2:$NE$150=I$3)*(GMW!$ND$2:$ND$150=I$4)*(GMW!$NF$2:$NF$150=I$1),0),$C6-1966),"0",(INDEX(GMW!$A$2:$NE$150,MATCH(1,(GMW!$NE$2:$NE$150=I$3)*(GMW!$ND$2:$ND$150=I$4)*(GMW!$NF$2:$NF$150=I$1),0),$C6-1965)))} -> 202404 | J6: {=_xlfn.CONCAT(INDEX(GMW!$A$2:$NE$150,MATCH(1,(GMW!$NE$2:$NE$150=J$3)*(GMW!$ND$2:$ND$150=J$4)*(GMW!$NF$2:$NF$150=J$1),0),$C6-1966),"0",(INDEX(GMW!$A$2:$NE$150,MATCH(1,(GMW!$NE$2:$NE$150=J$3)*(GMW!$ND$2:$ND$150=J$4)*(GMW!$NF$2:$NF$150=J$1),0),$C6-1965)))} -> 202404 | K6: {=_xlfn.CONCAT(INDEX(GMW!$A$2:$NE$150,MATCH(1,(GMW!$NE$2:$NE$150=K$3)*(GMW!$ND$2:$ND$150=K$4)*(GMW!$NF$2:$NF$150=K$1),0),$C6-1966),"0",(INDEX(GMW!$A$2:$NE$150,MATCH(1,(GMW!$NE$2:$NE$150=K$3)*(GMW!$ND$2:$ND$150=K$4)*(GMW!$NF$2:$NF$150=K$1),0),$C6-1965)))} -> 202404 | ... AV6: {=_xlfn.CONCAT(INDEX(GMW!$A$2:$NE$150,MATCH(1,(GMW!$NE$2:$NE$150=AV$3)*(GMW!$ND$2:$ND$150=AV$4)*(GMW!$NF$2:$NF$150=AV$1),0),$C6-1966),"0",(INDEX(GMW!$A$2:$NE$150,MATCH(1,(GMW!$NE$2:$NE$150=AV$3)*(GMW!$ND$2:$ND$150=AV$4)*(GMW!$NF$2:$NF$150=AV$1),0),$C6-1965)))} -> 202302
A7: 1973 | B7: 1973 | C7: 1973 | D7: {=INDEX(GMW!$A$2:$NF$150,MATCH(1,(GMW!$NE$2:$NE$150=D$3)*(GMW!$ND$2:$ND$150=D$4)*(GMW!$NF$2:$NF$150=D$1),0),$C7-1966)} -> 247921 | E7: {=INDEX(GMW!$A$2:$NF$150,MATCH(1,(GMW!$NE$2:$NE$150=E$3)*(GMW!$ND$2:$ND$150=E$4)*(GMW!$NF$2:$NF$150=E$1),0),$C7-1966)} -> 11.88749 | F7: {=INDEX(GMW!$A$2:$NF$150,MATCH(1,(GMW!$NE$2:$NE$150=F$3)*(GMW!$ND$2:$ND$150=F$4)*(GMW!$NF$2:$NF$150=F$1),0),$C7-1966)} -> 35902 | G7: {=INDEX(GMW!$A$2:$NF$150,MATCH(1,(GMW!$NE$2:$NE$150=G$3)*(GMW!$ND$2:$ND$150=G$4)*(GMW!$NF$2:$NF$150=G$1),0),$C7-1966)} -> 13911.1 | H7: {=INDEX(GMW!$A$2:$NF$150,MATCH(1,(GMW!$NE$2:$NE$150=H$3)*(GMW!$ND$2:$ND$150=H$4)*(GMW!$NF$2:$NF$150=H$1),0),$C7-1966)} -> 34501 | I7: {=INDEX(GMW!$A$2:$NF$150,MATCH(1,(GMW!$NE$2:$NE$150=I$3)*(GMW!$ND$2:$ND$150=I$4)*(GMW!$NF$2:$NF$150=I$1),0),$C7-1966)} -> -2641.15 | J7: {=INDEX(GMW!$A$2:$NF$150,MATCH(1,(GMW!$NE$2:$NE$150=J$3)*(GMW!$ND$2:$ND$150=J$4)*(GMW!$NF$2:$NF$150=J$1),0),$C7-1966)} -> 50184 | K7: {=INDEX(GMW!$A$2:$NF$150,MATCH(1,(GMW!$NE$2:$NE$150=K$3)*(GMW!$ND$2:$ND$150=K$4)*(GMW!$NF$2:$NF$150=K$1),0),$C7-1966)} -> 16141.32 | ... AV7: {=INDEX(GMW!$A$2:$NF$150,MATCH(1,(GMW!$NE$2:$NE$150=AV$3)*(GMW!$ND$2:$ND$150=AV$4)*(GMW!$NF$2:$NF$150=AV$1),0),$C7-1966)} -> -1.921214
B8: 1973 | C8: =+C7+1 -> 1974 | D8: {=INDEX(GMW!$A$2:$NF$150,MATCH(1,(GMW!$NE$2:$NE$150=D$3)*(GMW!$ND$2:$ND$150=D$4)*(GMW!$NF$2:$NF$150=D$1),0),$C8-1966)} -> 248384 | E8: {=INDEX(GMW!$A$2:$NF$150,MATCH(1,(GMW!$NE$2:$NE$150=E$3)*(GMW!$ND$2:$ND$150=E$4)*(GMW!$NF$2:$NF$150=E$1),0),$C8-1966)} -> 12.3046 | F8: {=INDEX(GMW!$A$2:$NF$150,MATCH(1,(GMW!$NE$2:$NE$150=F$3)*(GMW!$ND$2:$ND$150=F$4)*(GMW!$NF$2:$NF$150=F$1),0),$C8-1966)} -> 36730 | G8: {=INDEX(GMW!$A$2:$NF$150,MATCH(1,(GMW!$NE$2:$NE$150=G$3)*(GMW!$ND$2:$ND$150=G$4)*(GMW!$NF$2:$NF$150=G$1),0),$C8-1966)} -> 14383.87 | H8: {=INDEX(GMW!$A$2:$NF$150,MATCH(1,(GMW!$NE$2:$NE$150=H$3)*(GMW!$ND$2:$ND$150=H$4)*(GMW!$NF$2:$NF$150=H$1),0),$C8-1966)} -> 34693 | I8: {=INDEX(GMW!$A$2:$NF$150,MATCH(1,(GMW!$NE$2:$NE$150=I$3)*(GMW!$ND$2:$ND$150=I$4)*(GMW!$NF$2:$NF$150=I$1),0),$C8-1966)} -> -4462.875 | J8: {=INDEX(GMW!$A$2:$NF$150,MATCH(1,(GMW!$NE$2:$NE$150=J$3)*(GMW!$ND$2:$ND$150=J$4)*(GMW!$NF$2:$NF$150=J$1),0),$C8-1966)} -> 48537 | K8: {=INDEX(GMW!$A$2:$NF$150,MATCH(1,(GMW!$NE$2:$NE$150=K$3)*(GMW!$ND$2:$ND$150=K$4)*(GMW!$NF$2:$NF$150=K$1),0),$C8-1966)} -> 15761.6 | ... AV8: {=INDEX(GMW!$A$2:$NF$150,MATCH(1,(GMW!$NE$2:$NE$150=AV$3)*(GMW!$ND$2:$ND$150=AV$4)*(GMW!$NF$2:$NF$150=AV$1),0),$C8-1966)} -> -1.922197
B9: 1973 | C9: =+C8+1 -> 1975 | D9: {=INDEX(GMW!$A$2:$NF$150,MATCH(1,(GMW!$NE$2:$NE$150=D$3)*(GMW!$ND$2:$ND$150=D$4)*(GMW!$NF$2:$NF$150=D$1),0),$C9-1966)} -> 246082 | E9: {=INDEX(GMW!$A$2:$NF$150,MATCH(1,(GMW!$NE$2:$NE$150=E$3)*(GMW!$ND$2:$ND$150=E$4)*(GMW!$NF$2:$NF$150=E$1),0),$C9-1966)} -> 12.51315 | F9: {=INDEX(GMW!$A$2:$NF$150,MATCH(1,(GMW!$NE$2:$NE$150=F$3)*(GMW!$ND$2:$ND$150=F$4)*(GMW!$NF$2:$NF$150=F$1),0),$C9-1966)} -> 37647 | G9: {=INDEX(GMW!$A$2:$NF$150,MATCH(1,(GMW!$NE$2:$NE$150=G$3)*(GMW!$ND$2:$ND$150=G$4)*(GMW!$NF$2:$NF$150=G$1),0),$C9-1966)} -> 14134.28 | H9: {=INDEX(GMW!$A$2:$NF$150,MATCH(1,(GMW!$NE$2:$NE$150=H$3)*(GMW!$ND$2:$ND$150=H$4)*(GMW!$NF$2:$NF$150=H$1),0),$C9-1966)} -> 35714 | I9: {=INDEX(GMW!$A$2:$NF$150,MATCH(1,(GMW!$NE$2:$NE$150=I$3)*(GMW!$ND$2:$ND$150=I$4)*(GMW!$NF$2:$NF$150=I$1),0),$C9-1966)} -> -5844.55 | J9: {=INDEX(GMW!$A$2:$NF$150,MATCH(1,(GMW!$NE$2:$NE$150=J$3)*(GMW!$ND$2:$ND$150=J$4)*(GMW!$NF$2:$NF$150=J$1),0),$C9-1966)} -> 47578 | K9: {=INDEX(GMW!$A$2:$NF$150,MATCH(1,(GMW!$NE$2:$NE$150=K$3)*(GMW!$ND$2:$ND$150=K$4)*(GMW!$NF$2:$NF$150=K$1),0),$C9-1966)} -> 15887.1 | ... AV9: {=INDEX(GMW!$A$2:$NF$150,MATCH(1,(GMW!$NE$2:$NE$150=AV$3)*(GMW!$ND$2:$ND$150=AV$4)*(GMW!$NF$2:$NF$150=AV$1),0),$C9-1966)} -> -1.92318
B10: 1973 | C10: =+C9+1 -> 1976 | D10: {=INDEX(GMW!$A$2:$NF$150,MATCH(1,(GMW!$NE$2:$NE$150=D$3)*(GMW!$ND$2:$ND$150=D$4)*(GMW!$NF$2:$NF$150=D$1),0),$C10-1966)} -> 245140 | E10: {=INDEX(GMW!$A$2:$NF$150,MATCH(1,(GMW!$NE$2:$NE$150=E$3)*(GMW!$ND$2:$ND$150=E$4)*(GMW!$NF$2:$NF$150=E$1),0),$C10-1966)} -> 13.00846 | F10: {=INDEX(GMW!$A$2:$NF$150,MATCH(1,(GMW!$NE$2:$NE$150=F$3)*(GMW!$ND$2:$ND$150=F$4)*(GMW!$NF$2:$NF$150=F$1),0),$C10-1966)} -> 37940 | G10: {=INDEX(GMW!$A$2:$NF$150,MATCH(1,(GMW!$NE$2:$NE$150=G$3)*(GMW!$ND$2:$ND$150=G$4)*(GMW!$NF$2:$NF$150=G$1),0),$C10-1966)} -> 14654.81 | H10: {=INDEX(GMW!$A$2:$NF$150,MATCH(1,(GMW!$NE$2:$NE$150=H$3)*(GMW!$ND$2:$ND$150=H$4)*(GMW!$NF$2:$NF$150=H$1),0),$C10-1966)} -> 36306 | I10: {=INDEX(GMW!$A$2:$NF$150,MATCH(1,(GMW!$NE$2:$NE$150=I$3)*(GMW!$ND$2:$ND$150=I$4)*(GMW!$NF$2:$NF$150=I$1),0),$C10-1966)} -> -3867.775 | J10: {=INDEX(GMW!$A$2:$NF$150,MATCH(1,(GMW!$NE$2:$NE$150=J$3)*(GMW!$ND$2:$ND$150=J$4)*(GMW!$NF$2:$NF$150=J$1),0),$C10-1966)} -> 47374 | K10: {=INDEX(GMW!$A$2:$NF$150,MATCH(1,(GMW!$NE$2:$NE$150=K$3)*(GMW!$ND$2:$ND$150=K$4)*(GMW!$NF$2:$NF$150=K$1),0),$C10-1966)} -> 16340.84 | ... AV10: {=INDEX(GMW!$A$2:$NF$150,MATCH(1,(GMW!$NE$2:$NE$150=AV$3)*(GMW!$ND$2:$ND$150=AV$4)*(GMW!$NF$2:$NF$150=AV$1),0),$C10-1966)} -> -1.924164
A11: 1974 | B11: =+B7+1 -> 1974 | C11: =+C10+1 -> 1977 | D11: {=INDEX(GMW!$A$2:$NF$150,MATCH(1,(GMW!$NE$2:$NE$150=D$3)*(GMW!$ND$2:$ND$150=D$4)*(GMW!$NF$2:$NF$150=D$1),0),$C11-1966)} -> 238319 | E11: {=INDEX(GMW!$A$2:$NF$150,MATCH(1,(GMW!$NE$2:$NE$150=E$3)*(GMW!$ND$2:$ND$150=E$4)*(GMW!$NF$2:$NF$150=E$1),0),$C11-1966)} -> 13.47771 | F11: {=INDEX(GMW!$A$2:$NF$150,MATCH(1,(GMW!$NE$2:$NE$150=F$3)*(GMW!$ND$2:$ND$150=F$4)*(GMW!$NF$2:$NF$150=F$1),0),$C11-1966)} -> 38873 | G11: {=INDEX(GMW!$A$2:$NF$150,MATCH(1,(GMW!$NE$2:$NE$150=G$3)*(GMW!$ND$2:$ND$150=G$4)*(GMW!$NF$2:$NF$150=G$1),0),$C11-1966)} -> 16014.87 | H11: {=INDEX(GMW!$A$2:$NF$150,MATCH(1,(GMW!$NE$2:$NE$150=H$3)*(GMW!$ND$2:$ND$150=H$4)*(GMW!$NF$2:$NF$150=H$1),0),$C11-1966)} -> 35237 | I11: {=INDEX(GMW!$A$2:$NF$150,MATCH(1,(GMW!$NE$2:$NE$150=I$3)*(GMW!$ND$2:$ND$150=I$4)*(GMW!$NF$2:$NF$150=I$1),0),$C11-1966)} -> -2134.15 | J11: {=INDEX(GMW!$A$2:$NF$150,MATCH(1,(GMW!$NE$2:$NE$150=J$3)*(GMW!$ND$2:$ND$150=J$4)*(GMW!$NF$2:$NF$150=J$1),0),$C11-1966)} -> 46939 | K11: {=INDEX(GMW!$A$2:$NF$150,MATCH(1,(GMW!$NE$2:$NE$150=K$3)*(GMW!$ND$2:$ND$150=K$4)*(GMW!$NF$2:$NF$150=K$1),0),$C11-1966)} -> 16527.48 | ... AV11: {=INDEX(GMW!$A$2:$NF$150,MATCH(1,(GMW!$NE$2:$NE$150=AV$3)*(GMW!$ND$2:$ND$150=AV$4)*(GMW!$NF$2:$NF$150=AV$1),0),$C11-1966)} -> -1.925149
B12: =+B8+1 -> 1974 | C12: =+C11+1 -> 1978 | D12: {=INDEX(GMW!$A$2:$NF$150,MATCH(1,(GMW!$NE$2:$NE$150=D$3)*(GMW!$ND$2:$ND$150=D$4)*(GMW!$NF$2:$NF$150=D$1),0),$C12-1966)} -> 241752 | E12: {=INDEX(GMW!$A$2:$NF$150,MATCH(1,(GMW!$NE$2:$NE$150=E$3)*(GMW!$ND$2:$ND$150=E$4)*(GMW!$NF$2:$NF$150=E$1),0),$C12-1966)} -> 14.23371 | F12: {=INDEX(GMW!$A$2:$NF$150,MATCH(1,(GMW!$NE$2:$NE$150=F$3)*(GMW!$ND$2:$ND$150=F$4)*(GMW!$NF$2:$NF$150=F$1),0),$C12-1966)} -> 40111 | G12: {=INDEX(GMW!$A$2:$NF$150,MATCH(1,(GMW!$NE$2:$NE$150=G$3)*(GMW!$ND$2:$ND$150=G$4)*(GMW!$NF$2:$NF$150=G$1),0),$C12-1966)} -> 15888.81 | H12: {=INDEX(GMW!$A$2:$NF$150,MATCH(1,(GMW!$NE$2:$NE$150=H$3)*(GMW!$ND$2:$ND$150=H$4)*(GMW!$NF$2:$NF$150=H$1),0),$C12-1966)} -> 36120 | I12: {=INDEX(GMW!$A$2:$NF$150,MATCH(1,(GMW!$NE$2:$NE$150=I$3)*(GMW!$ND$2:$ND$150=I$4)*(GMW!$NF$2:$NF$150=I$1),0),$C12-1966)} -> -2173.075 | J12: {=INDEX(GMW!$A$2:$NF$150,MATCH(1,(GMW!$NE$2:$NE$150=J$3)*(GMW!$ND$2:$ND$150=J$4)*(GMW!$NF$2:$NF$150=J$1),0),$C12-1966)} -> 44355 | K12: {=INDEX(GMW!$A$2:$NF$150,MATCH(1,(GMW!$NE$2:$NE$150=K$3)*(GMW!$ND$2:$ND$150=K$4)*(GMW!$NF$2:$NF$150=K$1),0),$C12-1966)} -> 17109.93 | ... AV12: {=INDEX(GMW!$A$2:$NF$150,MATCH(1,(GMW!$NE$2:$NE$150=AV$3)*(GMW!$ND$2:$ND$150=AV$4)*(GMW!$NF$2:$NF$150=AV$1),0),$C12-1966)} -> -1.926134
B13: =+B9+1 -> 1974 | C13: =+C12+1 -> 1979 | D13: {=INDEX(GMW!$A$2:$NF$150,MATCH(1,(GMW!$NE$2:$NE$150=D$3)*(GMW!$ND$2:$ND$150=D$4)*(GMW!$NF$2:$NF$150=D$1),0),$C13-1966)} -> 243197 | E13: {=INDEX(GMW!$A$2:$NF$150,MATCH(1,(GMW!$NE$2:$NE$150=E$3)*(GMW!$ND$2:$ND$150=E$4)*(GMW!$NF$2:$NF$150=E$1),0),$C13-1966)} -> 14.57261 | F13: {=INDEX(GMW!$A$2:$NF$150,MATCH(1,(GMW!$NE$2:$NE$150=F$3)*(GMW!$ND$2:$ND$150=F$4)*(GMW!$NF$2:$NF$150=F$1),0),$C13-1966)} -> 40403 | G13: {=INDEX(GMW!$A$2:$NF$150,MATCH(1,(GMW!$NE$2:$NE$150=G$3)*(GMW!$ND$2:$ND$150=G$4)*(GMW!$NF$2:$NF$150=G$1),0),$C13-1966)} -> 16274.34 | H13: {=INDEX(GMW!$A$2:$NF$150,MATCH(1,(GMW!$NE$2:$NE$150=H$3)*(GMW!$ND$2:$ND$150=H$4)*(GMW!$NF$2:$NF$150=H$1),0),$C13-1966)} -> 35827 | I13: {=INDEX(GMW!$A$2:$NF$150,MATCH(1,(GMW!$NE$2:$NE$150=I$3)*(GMW!$ND$2:$ND$150=I$4)*(GMW!$NF$2:$NF$150=I$1),0),$C13-1966)} -> -1830.175 | J13: {=INDEX(GMW!$A$2:$NF$150,MATCH(1,(GMW!$NE$2:$NE$150=J$3)*(GMW!$ND$2:$ND$150=J$4)*(GMW!$NF$2:$NF$150=J$1),0),$C13-1966)} -> 43865 | K13: {=INDEX(GMW!$A$2:$NF$150,MATCH(1,(GMW!$NE$2:$NE$150=K$3)*(GMW!$ND$2:$ND$150=K$4)*(GMW!$NF$2:$NF$150=K$1),0),$C13-1966)} -> 16784.92 | ... AV13: {=INDEX(GMW!$A$2:$NF$150,MATCH(1,(GMW!$NE$2:$NE$150=AV$3)*(GMW!$ND$2:$ND$150=AV$4)*(GMW!$NF$2:$NF$150=AV$1),0),$C13-1966)} -> -1.927119
B14: =+B10+1 -> 1974 | C14: =+C13+1 -> 1980 | D14: {=INDEX(GMW!$A$2:$NF$150,MATCH(1,(GMW!$NE$2:$NE$150=D$3)*(GMW!$ND$2:$ND$150=D$4)*(GMW!$NF$2:$NF$150=D$1),0),$C14-1966)} -> 239612 | E14: {=INDEX(GMW!$A$2:$NF$150,MATCH(1,(GMW!$NE$2:$NE$150=E$3)*(GMW!$ND$2:$ND$150=E$4)*(GMW!$NF$2:$NF$150=E$1),0),$C14-1966)} -> 15.2504 | F14: {=INDEX(GMW!$A$2:$NF$150,MATCH(1,(GMW!$NE$2:$NE$150=F$3)*(GMW!$ND$2:$ND$150=F$4)*(GMW!$NF$2:$NF$150=F$1),0),$C14-1966)} -> 39579 | G14: {=INDEX(GMW!$A$2:$NF$150,MATCH(1,(GMW!$NE$2:$NE$150=G$3)*(GMW!$ND$2:$ND$150=G$4)*(GMW!$NF$2:$NF$150=G$1),0),$C14-1966)} -> 15142.34 | H14: {=INDEX(GMW!$A$2:$NF$150,MATCH(1,(GMW!$NE$2:$NE$150=H$3)*(GMW!$ND$2:$ND$150=H$4)*(GMW!$NF$2:$NF$150=H$1),0),$C14-1966)} -> 35382 | I14: {=INDEX(GMW!$A$2:$NF$150,MATCH(1,(GMW!$NE$2:$NE$150=I$3)*(GMW!$ND$2:$ND$150=I$4)*(GMW!$NF$2:$NF$150=I$1),0),$C14-1966)} -> -2998.1 | J14: {=INDEX(GMW!$A$2:$NF$150,MATCH(1,(GMW!$NE$2:$NE$150=J$3)*(GMW!$ND$2:$ND$150=J$4)*(GMW!$NF$2:$NF$150=J$1),0),$C14-1966)} -> 44059 | K14: {=INDEX(GMW!$A$2:$NF$150,MATCH(1,(GMW!$NE$2:$NE$150=K$3)*(GMW!$ND$2:$ND$150=K$4)*(GMW!$NF$2:$NF$150=K$1),0),$C14-1966)} -> 17497.7 | ... AV14: {=INDEX(GMW!$A$2:$NF$150,MATCH(1,(GMW!$NE$2:$NE$150=AV$3)*(GMW!$ND$2:$ND$150=AV$4)*(GMW!$NF$2:$NF$150=AV$1),0),$C14-1966)} -> -1.928105
A15: 1975 | B15: =+B11+1 -> 1975 | C15: =+C14+1 -> 1981 | D15: {=INDEX(GMW!$A$2:$NF$150,MATCH(1,(GMW!$NE$2:$NE$150=D$3)*(GMW!$ND$2:$ND$150=D$4)*(GMW!$NF$2:$NF$150=D$1),0),$C15-1966)} -> 239702 | E15: {=INDEX(GMW!$A$2:$NF$150,MATCH(1,(GMW!$NE$2:$NE$150=E$3)*(GMW!$ND$2:$ND$150=E$4)*(GMW!$NF$2:$NF$150=E$1),0),$C15-1966)} -> 16.05854 | F15: {=INDEX(GMW!$A$2:$NF$150,MATCH(1,(GMW!$NE$2:$NE$150=F$3)*(GMW!$ND$2:$ND$150=F$4)*(GMW!$NF$2:$NF$150=F$1),0),$C15-1966)} -> 39298 | G15: {=INDEX(GMW!$A$2:$NF$150,MATCH(1,(GMW!$NE$2:$NE$150=G$3)*(GMW!$ND$2:$ND$150=G$4)*(GMW!$NF$2:$NF$150=G$1),0),$C15-1966)} -> 15222.87 | H15: {=INDEX(GMW!$A$2:$NF$150,MATCH(1,(GMW!$NE$2:$NE$150=H$3)*(GMW!$ND$2:$ND$150=H$4)*(GMW!$NF$2:$NF$150=H$1),0),$C15-1966)} -> 33882 | I15: {=INDEX(GMW!$A$2:$NF$150,MATCH(1,(GMW!$NE$2:$NE$150=I$3)*(GMW!$ND$2:$ND$150=I$4)*(GMW!$NF$2:$NF$150=I$1),0),$C15-1966)} -> 75.2 | J15: {=INDEX(GMW!$A$2:$NF$150,MATCH(1,(GMW!$NE$2:$NE$150=J$3)*(GMW!$ND$2:$ND$150=J$4)*(GMW!$NF$2:$NF$150=J$1),0),$C15-1966)} -> 42893 | K15: {=INDEX(GMW!$A$2:$NF$150,MATCH(1,(GMW!$NE$2:$NE$150=K$3)*(GMW!$ND$2:$ND$150=K$4)*(GMW!$NF$2:$NF$150=K$1),0),$C15-1966)} -> 16895.94 | ... AV15: {=INDEX(GMW!$A$2:$NF$150,MATCH(1,(GMW!$NE$2:$NE$150=AV$3)*(GMW!$ND$2:$ND$150=AV$4)*(GMW!$NF$2:$NF$150=AV$1),0),$C15-1966)} -> -1.929092
B16: =+B12+1 -> 1975 | C16: =+C15+1 -> 1982 | D16: {=INDEX(GMW!$A$2:$NF$150,MATCH(1,(GMW!$NE$2:$NE$150=D$3)*(GMW!$ND$2:$ND$150=D$4)*(GMW!$NF$2:$NF$150=D$1),0),$C16-1966)} -> 235807 | E16: {=INDEX(GMW!$A$2:$NF$150,MATCH(1,(GMW!$NE$2:$NE$150=E$3)*(GMW!$ND$2:$ND$150=E$4)*(GMW!$NF$2:$NF$150=E$1),0),$C16-1966)} -> 17.46627 | F16: {=INDEX(GMW!$A$2:$NF$150,MATCH(1,(GMW!$NE$2:$NE$150=F$3)*(GMW!$ND$2:$ND$150=F$4)*(GMW!$NF$2:$NF$150=F$1),0),$C16-1966)} -> 37742 | G16: {=INDEX(GMW!$A$2:$NF$150,MATCH(1,(GMW!$NE$2:$NE$150=G$3)*(GMW!$ND$2:$ND$150=G$4)*(GMW!$NF$2:$NF$150=G$1),0),$C16-1966)} -> 15136.16 | H16: {=INDEX(GMW!$A$2:$NF$150,MATCH(1,(GMW!$NE$2:$NE$150=H$3)*(GMW!$ND$2:$ND$150=H$4)*(GMW!$NF$2:$NF$150=H$1),0),$C16-1966)} -> 32123 | I16: {=INDEX(GMW!$A$2:$NF$150,MATCH(1,(GMW!$NE$2:$NE$150=I$3)*(GMW!$ND$2:$ND$150=I$4)*(GMW!$NF$2:$NF$150=I$1),0),$C16-1966)} -> -88.975 | J16: {=INDEX(GMW!$A$2:$NF$150,MATCH(1,(GMW!$NE$2:$NE$150=J$3)*(GMW!$ND$2:$ND$150=J$4)*(GMW!$NF$2:$NF$150=J$1),0),$C16-1966)} -> 42698 | K16: {=INDEX(GMW!$A$2:$NF$150,MATCH(1,(GMW!$NE$2:$NE$150=K$3)*(GMW!$ND$2:$ND$150=K$4)*(GMW!$NF$2:$NF$150=K$1),0),$C16-1966)} -> 16410.02 | ... AV16: {=INDEX(GMW!$A$2:$NF$150,MATCH(1,(GMW!$NE$2:$NE$150=AV$3)*(GMW!$ND$2:$ND$150=AV$4)*(GMW!$NF$2:$NF$150=AV$1),0),$C16-1966)} -> -1.930079
B17: =+B13+1 -> 1975 | C17: =+C16+1 -> 1983 | D17: {=INDEX(GMW!$A$2:$NF$150,MATCH(1,(GMW!$NE$2:$NE$150=D$3)*(GMW!$ND$2:$ND$150=D$4)*(GMW!$NF$2:$NF$150=D$1),0),$C17-1966)} -> 235105 | E17: {=INDEX(GMW!$A$2:$NF$150,MATCH(1,(GMW!$NE$2:$NE$150=E$3)*(GMW!$ND$2:$ND$150=E$4)*(GMW!$NF$2:$NF$150=E$1),0),$C17-1966)} -> 18.22228 | F17: {=INDEX(GMW!$A$2:$NF$150,MATCH(1,(GMW!$NE$2:$NE$150=F$3)*(GMW!$ND$2:$ND$150=F$4)*(GMW!$NF$2:$NF$150=F$1),0),$C17-1966)} -> 37667 | G17: {=INDEX(GMW!$A$2:$NF$150,MATCH(1,(GMW!$NE$2:$NE$150=G$3)*(GMW!$ND$2:$ND$150=G$4)*(GMW!$NF$2:$NF$150=G$1),0),$C17-1966)} -> 15232.16 | H17: {=INDEX(GMW!$A$2:$NF$150,MATCH(1,(GMW!$NE$2:$NE$150=H$3)*(GMW!$ND$2:$ND$150=H$4)*(GMW!$NF$2:$NF$150=H$1),0),$C17-1966)} -> 33900 | I17: {=INDEX(GMW!$A$2:$NF$150,MATCH(1,(GMW!$NE$2:$NE$150=I$3)*(GMW!$ND$2:$ND$150=I$4)*(GMW!$NF$2:$NF$150=I$1),0),$C17-1966)} -> 146.25 | J17: {=INDEX(GMW!$A$2:$NF$150,MATCH(1,(GMW!$NE$2:$NE$150=J$3)*(GMW!$ND$2:$ND$150=J$4)*(GMW!$NF$2:$NF$150=J$1),0),$C17-1966)} -> 42064 | K17: {=INDEX(GMW!$A$2:$NF$150,MATCH(1,(GMW!$NE$2:$NE$150=K$3)*(GMW!$ND$2:$ND$150=K$4)*(GMW!$NF$2:$NF$150=K$1),0),$C17-1966)} -> 17291.75 | ... AV17: {=INDEX(GMW!$A$2:$NF$150,MATCH(1,(GMW!$NE$2:$NE$150=AV$3)*(GMW!$ND$2:$ND$150=AV$4)*(GMW!$NF$2:$NF$150=AV$1),0),$C17-1966)} -> -1.931067
B18: =+B14+1 -> 1975 | C18: =+C17+1 -> 1984 | D18: {=INDEX(GMW!$A$2:$NF$150,MATCH(1,(GMW!$NE$2:$NE$150=D$3)*(GMW!$ND$2:$ND$150=D$4)*(GMW!$NF$2:$NF$150=D$1),0),$C18-1966)} -> 237747 | E18: {=INDEX(GMW!$A$2:$NF$150,MATCH(1,(GMW!$NE$2:$NE$150=E$3)*(GMW!$ND$2:$ND$150=E$4)*(GMW!$NF$2:$NF$150=E$1),0),$C18-1966)} -> 18.84793 | F18: {=INDEX(GMW!$A$2:$NF$150,MATCH(1,(GMW!$NE$2:$NE$150=F$3)*(GMW!$ND$2:$ND$150=F$4)*(GMW!$NF$2:$NF$150=F$1),0),$C18-1966)} -> 39562 | G18: {=INDEX(GMW!$A$2:$NF$150,MATCH(1,(GMW!$NE$2:$NE$150=G$3)*(GMW!$ND$2:$ND$150=G$4)*(GMW!$NF$2:$NF$150=G$1),0),$C18-1966)} -> 16077.4 | H18: {=INDEX(GMW!$A$2:$NF$150,MATCH(1,(GMW!$NE$2:$NE$150=H$3)*(GMW!$ND$2:$ND$150=H$4)*(GMW!$NF$2:$NF$150=H$1),0),$C18-1966)} -> 33217 | I18: {=INDEX(GMW!$A$2:$NF$150,MATCH(1,(GMW!$NE$2:$NE$150=I$3)*(GMW!$ND$2:$ND$150=I$4)*(GMW!$NF$2:$NF$150=I$1),0),$C18-1966)} -> 58.125 | J18: {=INDEX(GMW!$A$2:$NF$150,MATCH(1,(GMW!$NE$2:$NE$150=J$3)*(GMW!$ND$2:$ND$150=J$4)*(GMW!$NF$2:$NF$150=J$1),0),$C18-1966)} -> 40849 | K18: {=INDEX(GMW!$A$2:$NF$150,MATCH(1,(GMW!$NE$2:$NE$150=K$3)*(GMW!$ND$2:$ND$150=K$4)*(GMW!$NF$2:$NF$150=K$1),0),$C18-1966)} -> 16514.61 | ... AV18: {=INDEX(GMW!$A$2:$NF$150,MATCH(1,(GMW!$NE$2:$NE$150=AV$3)*(GMW!$ND$2:$ND$150=AV$4)*(GMW!$NF$2:$NF$150=AV$1),0),$C18-1966)} -> -1.932055
A19: 1976 | B19: =+B15+1 -> 1976 | C19: =+C18+1 -> 1985 | D19: {=INDEX(GMW!$A$2:$NF$150,MATCH(1,(GMW!$NE$2:$NE$150=D$3)*(GMW!$ND$2:$ND$150=D$4)*(GMW!$NF$2:$NF$150=D$1),0),$C19-1966)} -> 241709 | E19: {=INDEX(GMW!$A$2:$NF$150,MATCH(1,(GMW!$NE$2:$NE$150=E$3)*(GMW!$ND$2:$ND$150=E$4)*(GMW!$NF$2:$NF$150=E$1),0),$C19-1966)} -> 19.42145 | F19: {=INDEX(GMW!$A$2:$NF$150,MATCH(1,(GMW!$NE$2:$NE$150=F$3)*(GMW!$ND$2:$ND$150=F$4)*(GMW!$NF$2:$NF$150=F$1),0),$C19-1966)} -> 40307 | G19: {=INDEX(GMW!$A$2:$NF$150,MATCH(1,(GMW!$NE$2:$NE$150=G$3)*(GMW!$ND$2:$ND$150=G$4)*(GMW!$NF$2:$NF$150=G$1),0),$C19-1966)} -> 16502.87 | H19: {=INDEX(GMW!$A$2:$NF$150,MATCH(1,(GMW!$NE$2:$NE$150=H$3)*(GMW!$ND$2:$ND$150=H$4)*(GMW!$NF$2:$NF$150=H$1),0),$C19-1966)} -> 32702 | I19: {=INDEX(GMW!$A$2:$NF$150,MATCH(1,(GMW!$NE$2:$NE$150=I$3)*(GMW!$ND$2:$ND$150=I$4)*(GMW!$NF$2:$NF$150=I$1),0),$C19-1966)} -> 206.125 | J19: {=INDEX(GMW!$A$2:$NF$150,MATCH(1,(GMW!$NE$2:$NE$150=J$3)*(GMW!$ND$2:$ND$150=J$4)*(GMW!$NF$2:$NF$150=J$1),0),$C19-1966)} -> 42896 | K19: {=INDEX(GMW!$A$2:$NF$150,MATCH(1,(GMW!$NE$2:$NE$150=K$3)*(GMW!$ND$2:$ND$150=K$4)*(GMW!$NF$2:$NF$150=K$1),0),$C19-1966)} -> 16797.79 | ... AV19: {=INDEX(GMW!$A$2:$NF$150,MATCH(1,(GMW!$NE$2:$NE$150=AV$3)*(GMW!$ND$2:$ND$150=AV$4)*(GMW!$NF$2:$NF$150=AV$1),0),$C19-1966)} -> -1.933043
B20: =+B16+1 -> 1976 | C20: =+C19+1 -> 1986 | D20: {=INDEX(GMW!$A$2:$NF$150,MATCH(1,(GMW!$NE$2:$NE$150=D$3)*(GMW!$ND$2:$ND$150=D$4)*(GMW!$NF$2:$NF$150=D$1),0),$C20-1966)} -> 241380 | E20: {=INDEX(GMW!$A$2:$NF$150,MATCH(1,(GMW!$NE$2:$NE$150=E$3)*(GMW!$ND$2:$ND$150=E$4)*(GMW!$NF$2:$NF$150=E$1),0),$C20-1966)} -> 20.12532 | F20: {=INDEX(GMW!$A$2:$NF$150,MATCH(1,(GMW!$NE$2:$NE$150=F$3)*(GMW!$ND$2:$ND$150=F$4)*(GMW!$NF$2:$NF$150=F$1),0),$C20-1966)} -> 41824 | G20: {=INDEX(GMW!$A$2:$NF$150,MATCH(1,(GMW!$NE$2:$NE$150=G$3)*(GMW!$ND$2:$ND$150=G$4)*(GMW!$NF$2:$NF$150=G$1),0),$C20-1966)} -> 17543.1 | H20: {=INDEX(GMW!$A$2:$NF$150,MATCH(1,(GMW!$NE$2:$NE$150=H$3)*(GMW!$ND$2:$ND$150=H$4)*(GMW!$NF$2:$NF$150=H$1),0),$C20-1966)} -> 35374 | I20: {=INDEX(GMW!$A$2:$NF$150,MATCH(1,(GMW!$NE$2:$NE$150=I$3)*(GMW!$ND$2:$ND$150=I$4)*(GMW!$NF$2:$NF$150=I$1),0),$C20-1966)} -> 1742.2 | J20: {=INDEX(GMW!$A$2:$NF$150,MATCH(1,(GMW!$NE$2:$NE$150=J$3)*(GMW!$ND$2:$ND$150=J$4)*(GMW!$NF$2:$NF$150=J$1),0),$C20-1966)} -> 42498 | K20: {=INDEX(GMW!$A$2:$NF$150,MATCH(1,(GMW!$NE$2:$NE$150=K$3)*(GMW!$ND$2:$ND$150=K$4)*(GMW!$NF$2:$NF$150=K$1),0),$C20-1966)} -> 17249.91 | ... AV20: {=INDEX(GMW!$A$2:$NF$150,MATCH(1,(GMW!$NE$2:$NE$150=AV$3)*(GMW!$ND$2:$ND$150=AV$4)*(GMW!$NF$2:$NF$150=AV$1),0),$C20-1966)} -> -1.934032
B21: =+B17+1 -> 1976 | C21: =+C20+1 -> 1987 | D21: {=INDEX(GMW!$A$2:$NF$150,MATCH(1,(GMW!$NE$2:$NE$150=D$3)*(GMW!$ND$2:$ND$150=D$4)*(GMW!$NF$2:$NF$150=D$1),0),$C21-1966)} -> 244367 | E21: {=INDEX(GMW!$A$2:$NF$150,MATCH(1,(GMW!$NE$2:$NE$150=E$3)*(GMW!$ND$2:$ND$150=E$4)*(GMW!$NF$2:$NF$150=E$1),0),$C21-1966)} -> 20.59456 | F21: {=INDEX(GMW!$A$2:$NF$150,MATCH(1,(GMW!$NE$2:$NE$150=F$3)*(GMW!$ND$2:$ND$150=F$4)*(GMW!$NF$2:$NF$150=F$1),0),$C21-1966)} -> 42139 | G21: {=INDEX(GMW!$A$2:$NF$150,MATCH(1,(GMW!$NE$2:$NE$150=G$3)*(GMW!$ND$2:$ND$150=G$4)*(GMW!$NF$2:$NF$150=G$1),0),$C21-1966)} -> 16388.57 | H21: {=INDEX(GMW!$A$2:$NF$150,MATCH(1,(GMW!$NE$2:$NE$150=H$3)*(GMW!$ND$2:$ND$150=H$4)*(GMW!$NF$2:$NF$150=H$1),0),$C21-1966)} -> 35764 | I21: {=INDEX(GMW!$A$2:$NF$150,MATCH(1,(GMW!$NE$2:$NE$150=I$3)*(GMW!$ND$2:$ND$150=I$4)*(GMW!$NF$2:$NF$150=I$1),0),$C21-1966)} -> 2026.2 | J21: {=INDEX(GMW!$A$2:$NF$150,MATCH(1,(GMW!$NE$2:$NE$150=J$3)*(GMW!$ND$2:$ND$150=J$4)*(GMW!$NF$2:$NF$150=J$1),0),$C21-1966)} -> 41983 | K21: {=INDEX(GMW!$A$2:$NF$150,MATCH(1,(GMW!$NE$2:$NE$150=K$3)*(GMW!$ND$2:$ND$150=K$4)*(GMW!$NF$2:$NF$150=K$1),0),$C21-1966)} -> 17314.27 | ... AV21: {=INDEX(GMW!$A$2:$NF$150,MATCH(1,(GMW!$NE$2:$NE$150=AV$3)*(GMW!$ND$2:$ND$150=AV$4)*(GMW!$NF$2:$NF$150=AV$1),0),$C21-1966)} -> -1.935022
B22: =+B18+1 -> 1976 | C22: =+C21+1 -> 1988 | D22: {=INDEX(GMW!$A$2:$NF$150,MATCH(1,(GMW!$NE$2:$NE$150=D$3)*(GMW!$ND$2:$ND$150=D$4)*(GMW!$NF$2:$NF$150=D$1),0),$C22-1966)} -> 249511 | E22: {=INDEX(GMW!$A$2:$NF$150,MATCH(1,(GMW!$NE$2:$NE$150=E$3)*(GMW!$ND$2:$ND$150=E$4)*(GMW!$NF$2:$NF$150=E$1),0),$C22-1966)} -> 21.50698 | F22: {=INDEX(GMW!$A$2:$NF$150,MATCH(1,(GMW!$NE$2:$NE$150=F$3)*(GMW!$ND$2:$ND$150=F$4)*(GMW!$NF$2:$NF$150=F$1),0),$C22-1966)} -> 43631 | G22: {=INDEX(GMW!$A$2:$NF$150,MATCH(1,(GMW!$NE$2:$NE$150=G$3)*(GMW!$ND$2:$ND$150=G$4)*(GMW!$NF$2:$NF$150=G$1),0),$C22-1966)} -> 16747.04 | H22: {=INDEX(GMW!$A$2:$NF$150,MATCH(1,(GMW!$NE$2:$NE$150=H$3)*(GMW!$ND$2:$ND$150=H$4)*(GMW!$NF$2:$NF$150=H$1),0),$C22-1966)} -> 35806 | I22: {=INDEX(GMW!$A$2:$NF$150,MATCH(1,(GMW!$NE$2:$NE$150=I$3)*(GMW!$ND$2:$ND$150=I$4)*(GMW!$NF$2:$NF$150=I$1),0),$C22-1966)} -> 2946.05 | J22: {=INDEX(GMW!$A$2:$NF$150,MATCH(1,(GMW!$NE$2:$NE$150=J$3)*(GMW!$ND$2:$ND$150=J$4)*(GMW!$NF$2:$NF$150=J$1),0),$C22-1966)} -> 42271 | K22: {=INDEX(GMW!$A$2:$NF$150,MATCH(1,(GMW!$NE$2:$NE$150=K$3)*(GMW!$ND$2:$ND$150=K$4)*(GMW!$NF$2:$NF$150=K$1),0),$C22-1966)} -> 17288.53 | ... AV22: {=INDEX(GMW!$A$2:$NF$150,MATCH(1,(GMW!$NE$2:$NE$150=AV$3)*(GMW!$ND$2:$ND$150=AV$4)*(GMW!$NF$2:$NF$150=AV$1),0),$C22-1966)} -> -1.936012
A23: 1977 | B23: =+B19+1 -> 1977 | C23: =+C22+1 -> 1989 | D23: {=INDEX(GMW!$A$2:$NF$150,MATCH(1,(GMW!$NE$2:$NE$150=D$3)*(GMW!$ND$2:$ND$150=D$4)*(GMW!$NF$2:$NF$150=D$1),0),$C23-1966)} -> 249671 | E23: {=INDEX(GMW!$A$2:$NF$150,MATCH(1,(GMW!$NE$2:$NE$150=E$3)*(GMW!$ND$2:$ND$150=E$4)*(GMW!$NF$2:$NF$150=E$1),0),$C23-1966)} -> 22.47153 | F23: {=INDEX(GMW!$A$2:$NF$150,MATCH(1,(GMW!$NE$2:$NE$150=F$3)*(GMW!$ND$2:$ND$150=F$4)*(GMW!$NF$2:$NF$150=F$1),0),$C23-1966)} -> 43666 | G23: {=INDEX(GMW!$A$2:$NF$150,MATCH(1,(GMW!$NE$2:$NE$150=G$3)*(GMW!$ND$2:$ND$150=G$4)*(GMW!$NF$2:$NF$150=G$1),0),$C23-1966)} -> 17034.98 | H23: {=INDEX(GMW!$A$2:$NF$150,MATCH(1,(GMW!$NE$2:$NE$150=H$3)*(GMW!$ND$2:$ND$150=H$4)*(GMW!$NF$2:$NF$150=H$1),0),$C23-1966)} -> 35437 | I23: {=INDEX(GMW!$A$2:$NF$150,MATCH(1,(GMW!$NE$2:$NE$150=I$3)*(GMW!$ND$2:$ND$150=I$4)*(GMW!$NF$2:$NF$150=I$1),0),$C23-1966)} -> 5013.775 | J23: {=INDEX(GMW!$A$2:$NF$150,MATCH(1,(GMW!$NE$2:$NE$150=J$3)*(GMW!$ND$2:$ND$150=J$4)*(GMW!$NF$2:$NF$150=J$1),0),$C23-1966)} -> 41191 | K23: {=INDEX(GMW!$A$2:$NF$150,MATCH(1,(GMW!$NE$2:$NE$150=K$3)*(GMW!$ND$2:$ND$150=K$4)*(GMW!$NF$2:$NF$150=K$1),0),$C23-1966)} -> 16509.78 | ... AV23: {=INDEX(GMW!$A$2:$NF$150,MATCH(1,(GMW!$NE$2:$NE$150=AV$3)*(GMW!$ND$2:$ND$150=AV$4)*(GMW!$NF$2:$NF$150=AV$1),0),$C23-1966)} -> -1.937002
B24: =+B20+1 -> 1977 | C24: =+C23+1 -> 1990 | D24: {=INDEX(GMW!$A$2:$NF$150,MATCH(1,(GMW!$NE$2:$NE$150=D$3)*(GMW!$ND$2:$ND$150=D$4)*(GMW!$NF$2:$NF$150=D$1),0),$C24-1966)} -> 247936 | E24: {=INDEX(GMW!$A$2:$NF$150,MATCH(1,(GMW!$NE$2:$NE$150=E$3)*(GMW!$ND$2:$ND$150=E$4)*(GMW!$NF$2:$NF$150=E$1),0),$C24-1966)} -> 23.41002 | F24: {=INDEX(GMW!$A$2:$NF$150,MATCH(1,(GMW!$NE$2:$NE$150=F$3)*(GMW!$ND$2:$ND$150=F$4)*(GMW!$NF$2:$NF$150=F$1),0),$C24-1966)} -> 44615 | G24: {=INDEX(GMW!$A$2:$NF$150,MATCH(1,(GMW!$NE$2:$NE$150=G$3)*(GMW!$ND$2:$ND$150=G$4)*(GMW!$NF$2:$NF$150=G$1),0),$C24-1966)} -> 17530.21 | H24: {=INDEX(GMW!$A$2:$NF$150,MATCH(1,(GMW!$NE$2:$NE$150=H$3)*(GMW!$ND$2:$ND$150=H$4)*(GMW!$NF$2:$NF$150=H$1),0),$C24-1966)} -> 36298 | I24: {=INDEX(GMW!$A$2:$NF$150,MATCH(1,(GMW!$NE$2:$NE$150=I$3)*(GMW!$ND$2:$ND$150=I$4)*(GMW!$NF$2:$NF$150=I$1),0),$C24-1966)} -> 5804.775 | J24: {=INDEX(GMW!$A$2:$NF$150,MATCH(1,(GMW!$NE$2:$NE$150=J$3)*(GMW!$ND$2:$ND$150=J$4)*(GMW!$NF$2:$NF$150=J$1),0),$C24-1966)} -> 43482 | K24: {=INDEX(GMW!$A$2:$NF$150,MATCH(1,(GMW!$NE$2:$NE$150=K$3)*(GMW!$ND$2:$ND$150=K$4)*(GMW!$NF$2:$NF$150=K$1),0),$C24-1966)} -> 17850.06 | ... AV24: {=INDEX(GMW!$A$2:$NF$150,MATCH(1,(GMW!$NE$2:$NE$150=AV$3)*(GMW!$ND$2:$ND$150=AV$4)*(GMW!$NF$2:$NF$150=AV$1),0),$C24-1966)} -> -1.937993
B25: =+B21+1 -> 1977 | C25: =+C24+1 -> 1991 | D25: {=INDEX(GMW!$A$2:$NF$150,MATCH(1,(GMW!$NE$2:$NE$150=D$3)*(GMW!$ND$2:$ND$150=D$4)*(GMW!$NF$2:$NF$150=D$1),0),$C25-1966)} -> 249578 | E25: {=INDEX(GMW!$A$2:$NF$150,MATCH(1,(GMW!$NE$2:$NE$150=E$3)*(GMW!$ND$2:$ND$150=E$4)*(GMW!$NF$2:$NF$150=E$1),0),$C25-1966)} -> 23.82713 | F25: {=INDEX(GMW!$A$2:$NF$150,MATCH(1,(GMW!$NE$2:$NE$150=F$3)*(GMW!$ND$2:$ND$150=F$4)*(GMW!$NF$2:$NF$150=F$1),0),$C25-1966)} -> 46225 | G25: {=INDEX(GMW!$A$2:$NF$150,MATCH(1,(GMW!$NE$2:$NE$150=G$3)*(GMW!$ND$2:$ND$150=G$4)*(GMW!$NF$2:$NF$150=G$1),0),$C25-1966)} -> 18027.45 | H25: {=INDEX(GMW!$A$2:$NF$150,MATCH(1,(GMW!$NE$2:$NE$150=H$3)*(GMW!$ND$2:$ND$150=H$4)*(GMW!$NF$2:$NF$150=H$1),0),$C25-1966)} -> 35391 | I25: {=INDEX(GMW!$A$2:$NF$150,MATCH(1,(GMW!$NE$2:$NE$150=I$3)*(GMW!$ND$2:$ND$150=I$4)*(GMW!$NF$2:$NF$150=I$1),0),$C25-1966)} -> 5769.575 | J25: {=INDEX(GMW!$A$2:$NF$150,MATCH(1,(GMW!$NE$2:$NE$150=J$3)*(GMW!$ND$2:$ND$150=J$4)*(GMW!$NF$2:$NF$150=J$1),0),$C25-1966)} -> 43006 | K25: {=INDEX(GMW!$A$2:$NF$150,MATCH(1,(GMW!$NE$2:$NE$150=K$3)*(GMW!$ND$2:$ND$150=K$4)*(GMW!$NF$2:$NF$150=K$1),0),$C25-1966)} -> 17277.27 | ... AV25: {=INDEX(GMW!$A$2:$NF$150,MATCH(1,(GMW!$NE$2:$NE$150=AV$3)*(GMW!$ND$2:$ND$150=AV$4)*(GMW!$NF$2:$NF$150=AV$1),0),$C25-1966)} -> -1.938985
B26: =+B22+1 -> 1977 | C26: =+C25+1 -> 1992 | D26: {=INDEX(GMW!$A$2:$NF$150,MATCH(1,(GMW!$NE$2:$NE$150=D$3)*(GMW!$ND$2:$ND$150=D$4)*(GMW!$NF$2:$NF$150=D$1),0),$C26-1966)} -> 253819 | E26: {=INDEX(GMW!$A$2:$NF$150,MATCH(1,(GMW!$NE$2:$NE$150=E$3)*(GMW!$ND$2:$ND$150=E$4)*(GMW!$NF$2:$NF$150=E$1),0),$C26-1966)} -> 24.13995 | F26: {=INDEX(GMW!$A$2:$NF$150,MATCH(1,(GMW!$NE$2:$NE$150=F$3)*(GMW!$ND$2:$ND$150=F$4)*(GMW!$NF$2:$NF$150=F$1),0),$C26-1966)} -> 44466 | G26: {=INDEX(GMW!$A$2:$NF$150,MATCH(1,(GMW!$NE$2:$NE$150=G$3)*(GMW!$ND$2:$ND$150=G$4)*(GMW!$NF$2:$NF$150=G$1),0),$C26-1966)} -> 17529.04 | H26: {=INDEX(GMW!$A$2:$NF$150,MATCH(1,(GMW!$NE$2:$NE$150=H$3)*(GMW!$ND$2:$ND$150=H$4)*(GMW!$NF$2:$NF$150=H$1),0),$C26-1966)} -> 34937 | I26: {=INDEX(GMW!$A$2:$NF$150,MATCH(1,(GMW!$NE$2:$NE$150=I$3)*(GMW!$ND$2:$ND$150=I$4)*(GMW!$NF$2:$NF$150=I$1),0),$C26-1966)} -> 6059.425 | J26: {=INDEX(GMW!$A$2:$NF$150,MATCH(1,(GMW!$NE$2:$NE$150=J$3)*(GMW!$ND$2:$ND$150=J$4)*(GMW!$NF$2:$NF$150=J$1),0),$C26-1966)} -> 44597 | K26: {=INDEX(GMW!$A$2:$NF$150,MATCH(1,(GMW!$NE$2:$NE$150=K$3)*(GMW!$ND$2:$ND$150=K$4)*(GMW!$NF$2:$NF$150=K$1),0),$C26-1966)} -> 17983.61 | ... AV26: {=INDEX(GMW!$A$2:$NF$150,MATCH(1,(GMW!$NE$2:$NE$150=AV$3)*(GMW!$ND$2:$ND$150=AV$4)*(GMW!$NF$2:$NF$150=AV$1),0),$C26-1966)} -> -1.939977
A27: 1978 | B27: =+B23+1 -> 1978 | C27: =+C26+1 -> 1993 | D27: {=INDEX(GMW!$A$2:$NF$150,MATCH(1,(GMW!$NE$2:$NE$150=D$3)*(GMW!$ND$2:$ND$150=D$4)*(GMW!$NF$2:$NF$150=D$1),0),$C27-1966)} -> 256193 | E27: {=INDEX(GMW!$A$2:$NF$150,MATCH(1,(GMW!$NE$2:$NE$150=E$3)*(GMW!$ND$2:$ND$150=E$4)*(GMW!$NF$2:$NF$150=E$1),0),$C27-1966)} -> 24.45278 | F27: {=INDEX(GMW!$A$2:$NF$150,MATCH(1,(GMW!$NE$2:$NE$150=F$3)*(GMW!$ND$2:$ND$150=F$4)*(GMW!$NF$2:$NF$150=F$1),0),$C27-1966)} -> 44831 | G27: {=INDEX(GMW!$A$2:$NF$150,MATCH(1,(GMW!$NE$2:$NE$150=G$3)*(GMW!$ND$2:$ND$150=G$4)*(GMW!$NF$2:$NF$150=G$1),0),$C27-1966)} -> 17137.45 | H27: {=INDEX(GMW!$A$2:$NF$150,MATCH(1,(GMW!$NE$2:$NE$150=H$3)*(GMW!$ND$2:$ND$150=H$4)*(GMW!$NF$2:$NF$150=H$1),0),$C27-1966)} -> 37167 | I27: {=INDEX(GMW!$A$2:$NF$150,MATCH(1,(GMW!$NE$2:$NE$150=I$3)*(GMW!$ND$2:$ND$150=I$4)*(GMW!$NF$2:$NF$150=I$1),0),$C27-1966)} -> 7081.675 | J27: {=INDEX(GMW!$A$2:$NF$150,MATCH(1,(GMW!$NE$2:$NE$150=J$3)*(GMW!$ND$2:$ND$150=J$4)*(GMW!$NF$2:$NF$150=J$1),0),$C27-1966)} -> 46164 | K27: {=INDEX(GMW!$A$2:$NF$150,MATCH(1,(GMW!$NE$2:$NE$150=K$3)*(GMW!$ND$2:$ND$150=K$4)*(GMW!$NF$2:$NF$150=K$1),0),$C27-1966)} -> 18171.86 | ... AV27: {=INDEX(GMW!$A$2:$NF$150,MATCH(1,(GMW!$NE$2:$NE$150=AV$3)*(GMW!$ND$2:$ND$150=AV$4)*(GMW!$NF$2:$NF$150=AV$1),0),$C27-1966)} -> -1.94097
B28: =+B24+1 -> 1978 | C28: =+C27+1 -> 1994 | D28: {=INDEX(GMW!$A$2:$NF$150,MATCH(1,(GMW!$NE$2:$NE$150=D$3)*(GMW!$ND$2:$ND$150=D$4)*(GMW!$NF$2:$NF$150=D$1),0),$C28-1966)} -> 259127 | E28: {=INDEX(GMW!$A$2:$NF$150,MATCH(1,(GMW!$NE$2:$NE$150=E$3)*(GMW!$ND$2:$ND$150=E$4)*(GMW!$NF$2:$NF$150=E$1),0),$C28-1966)} -> 25.07844 | F28: {=INDEX(GMW!$A$2:$NF$150,MATCH(1,(GMW!$NE$2:$NE$150=F$3)*(GMW!$ND$2:$ND$150=F$4)*(GMW!$NF$2:$NF$150=F$1),0),$C28-1966)} -> 45606 | G28: {=INDEX(GMW!$A$2:$NF$150,MATCH(1,(GMW!$NE$2:$NE$150=G$3)*(GMW!$ND$2:$ND$150=G$4)*(GMW!$NF$2:$NF$150=G$1),0),$C28-1966)} -> 18068.15 | H28: {=INDEX(GMW!$A$2:$NF$150,MATCH(1,(GMW!$NE$2:$NE$150=H$3)*(GMW!$ND$2:$ND$150=H$4)*(GMW!$NF$2:$NF$150=H$1),0),$C28-1966)} -> 37390 | I28: {=INDEX(GMW!$A$2:$NF$150,MATCH(1,(GMW!$NE$2:$NE$150=I$3)*(GMW!$ND$2:$ND$150=I$4)*(GMW!$NF$2:$NF$150=I$1),0),$C28-1966)} -> 9653.3 | J28: {=INDEX(GMW!$A$2:$NF$150,MATCH(1,(GMW!$NE$2:$NE$150=J$3)*(GMW!$ND$2:$ND$150=J$4)*(GMW!$NF$2:$NF$150=J$1),0),$C28-1966)} -> 46246 | K28: {=INDEX(GMW!$A$2:$NF$150,MATCH(1,(GMW!$NE$2:$NE$150=K$3)*(GMW!$ND$2:$ND$150=K$4)*(GMW!$NF$2:$NF$150=K$1),0),$C28-1966)} -> 18430.91 | ... AV28: {=INDEX(GMW!$A$2:$NF$150,MATCH(1,(GMW!$NE$2:$NE$150=AV$3)*(GMW!$ND$2:$ND$150=AV$4)*(GMW!$NF$2:$NF$150=AV$1),0),$C28-1966)} -> -1.937825
B29: =+B25+1 -> 1978 | C29: =+C28+1 -> 1995 | D29: {=INDEX(GMW!$A$2:$NF$150,MATCH(1,(GMW!$NE$2:$NE$150=D$3)*(GMW!$ND$2:$ND$150=D$4)*(GMW!$NF$2:$NF$150=D$1),0),$C29-1966)} -> 262661 | E29: {=INDEX(GMW!$A$2:$NF$150,MATCH(1,(GMW!$NE$2:$NE$150=E$3)*(GMW!$ND$2:$ND$150=E$4)*(GMW!$NF$2:$NF$150=E$1),0),$C29-1966)} -> 25.46948 | F29: {=INDEX(GMW!$A$2:$NF$150,MATCH(1,(GMW!$NE$2:$NE$150=F$3)*(GMW!$ND$2:$ND$150=F$4)*(GMW!$NF$2:$NF$150=F$1),0),$C29-1966)} -> 45784 | G29: {=INDEX(GMW!$A$2:$NF$150,MATCH(1,(GMW!$NE$2:$NE$150=G$3)*(GMW!$ND$2:$ND$150=G$4)*(GMW!$NF$2:$NF$150=G$1),0),$C29-1966)} -> 16110.09 | H29: {=INDEX(GMW!$A$2:$NF$150,MATCH(1,(GMW!$NE$2:$NE$150=H$3)*(GMW!$ND$2:$ND$150=H$4)*(GMW!$NF$2:$NF$150=H$1),0),$C29-1966)} -> 37335 | I29: {=INDEX(GMW!$A$2:$NF$150,MATCH(1,(GMW!$NE$2:$NE$150=I$3)*(GMW!$ND$2:$ND$150=I$4)*(GMW!$NF$2:$NF$150=I$1),0),$C29-1966)} -> 7523.625 | J29: {=INDEX(GMW!$A$2:$NF$150,MATCH(1,(GMW!$NE$2:$NE$150=J$3)*(GMW!$ND$2:$ND$150=J$4)*(GMW!$NF$2:$NF$150=J$1),0),$C29-1966)} -> 46206 | K29: {=INDEX(GMW!$A$2:$NF$150,MATCH(1,(GMW!$NE$2:$NE$150=K$3)*(GMW!$ND$2:$ND$150=K$4)*(GMW!$NF$2:$NF$150=K$1),0),$C29-1966)} -> 17861.33 | ... AV29: {=INDEX(GMW!$A$2:$NF$150,MATCH(1,(GMW!$NE$2:$NE$150=AV$3)*(GMW!$ND$2:$ND$150=AV$4)*(GMW!$NF$2:$NF$150=AV$1),0),$C29-1966)} -> -1.934686
B30: =+B26+1 -> 1978 | C30: =+C29+1 -> 1996 | D30: {=INDEX(GMW!$A$2:$NF$150,MATCH(1,(GMW!$NE$2:$NE$150=D$3)*(GMW!$ND$2:$ND$150=D$4)*(GMW!$NF$2:$NF$150=D$1),0),$C30-1966)} -> 264972 | E30: {=INDEX(GMW!$A$2:$NF$150,MATCH(1,(GMW!$NE$2:$NE$150=E$3)*(GMW!$ND$2:$ND$150=E$4)*(GMW!$NF$2:$NF$150=E$1),0),$C30-1966)} -> 25.86051 | F30: {=INDEX(GMW!$A$2:$NF$150,MATCH(1,(GMW!$NE$2:$NE$150=F$3)*(GMW!$ND$2:$ND$150=F$4)*(GMW!$NF$2:$NF$150=F$1),0),$C30-1966)} -> 45705 | G30: {=INDEX(GMW!$A$2:$NF$150,MATCH(1,(GMW!$NE$2:$NE$150=G$3)*(GMW!$ND$2:$ND$150=G$4)*(GMW!$NF$2:$NF$150=G$1),0),$C30-1966)} -> 16562.86 | H30: {=INDEX(GMW!$A$2:$NF$150,MATCH(1,(GMW!$NE$2:$NE$150=H$3)*(GMW!$ND$2:$ND$150=H$4)*(GMW!$NF$2:$NF$150=H$1),0),$C30-1966)} -> 35142 | I30: {=INDEX(GMW!$A$2:$NF$150,MATCH(1,(GMW!$NE$2:$NE$150=I$3)*(GMW!$ND$2:$ND$150=I$4)*(GMW!$NF$2:$NF$150=I$1),0),$C30-1966)} -> 6482.5 | J30: {=INDEX(GMW!$A$2:$NF$150,MATCH(1,(GMW!$NE$2:$NE$150=J$3)*(GMW!$ND$2:$ND$150=J$4)*(GMW!$NF$2:$NF$150=J$1),0),$C30-1966)} -> 46354 | K30: {=INDEX(GMW!$A$2:$NF$150,MATCH(1,(GMW!$NE$2:$NE$150=K$3)*(GMW!$ND$2:$ND$150=K$4)*(GMW!$NF$2:$NF$150=K$1),0),$C30-1966)} -> 17591.02 | ... AV30: {=INDEX(GMW!$A$2:$NF$150,MATCH(1,(GMW!$NE$2:$NE$150=AV$3)*(GMW!$ND$2:$ND$150=AV$4)*(GMW!$NF$2:$NF$150=AV$1),0),$C30-1966)} -> -1.931552
A31: 1979 | B31: =+B27+1 -> 1979 | C31: =+C30+1 -> 1997 | D31: {=INDEX(GMW!$A$2:$NF$150,MATCH(1,(GMW!$NE$2:$NE$150=D$3)*(GMW!$ND$2:$ND$150=D$4)*(GMW!$NF$2:$NF$150=D$1),0),$C31-1966)} -> 264185 | E31: {=INDEX(GMW!$A$2:$NF$150,MATCH(1,(GMW!$NE$2:$NE$150=E$3)*(GMW!$ND$2:$ND$150=E$4)*(GMW!$NF$2:$NF$150=E$1),0),$C31-1966)} -> 26.43403 | F31: {=INDEX(GMW!$A$2:$NF$150,MATCH(1,(GMW!$NE$2:$NE$150=F$3)*(GMW!$ND$2:$ND$150=F$4)*(GMW!$NF$2:$NF$150=F$1),0),$C31-1966)} -> 42206 | G31: {=INDEX(GMW!$A$2:$NF$150,MATCH(1,(GMW!$NE$2:$NE$150=G$3)*(GMW!$ND$2:$ND$150=G$4)*(GMW!$NF$2:$NF$150=G$1),0),$C31-1966)} -> 12034.5 | H31: {=INDEX(GMW!$A$2:$NF$150,MATCH(1,(GMW!$NE$2:$NE$150=H$3)*(GMW!$ND$2:$ND$150=H$4)*(GMW!$NF$2:$NF$150=H$1),0),$C31-1966)} -> 37420 | I31: {=INDEX(GMW!$A$2:$NF$150,MATCH(1,(GMW!$NE$2:$NE$150=I$3)*(GMW!$ND$2:$ND$150=I$4)*(GMW!$NF$2:$NF$150=I$1),0),$C31-1966)} -> 8583.425 | J31: {=INDEX(GMW!$A$2:$NF$150,MATCH(1,(GMW!$NE$2:$NE$150=J$3)*(GMW!$ND$2:$ND$150=J$4)*(GMW!$NF$2:$NF$150=J$1),0),$C31-1966)} -> 48743 | K31: {=INDEX(GMW!$A$2:$NF$150,MATCH(1,(GMW!$NE$2:$NE$150=K$3)*(GMW!$ND$2:$ND$150=K$4)*(GMW!$NF$2:$NF$150=K$1),0),$C31-1966)} -> 18372.98 | ... AV31: {=INDEX(GMW!$A$2:$NF$150,MATCH(1,(GMW!$NE$2:$NE$150=AV$3)*(GMW!$ND$2:$ND$150=AV$4)*(GMW!$NF$2:$NF$150=AV$1),0),$C31-1966)} -> -1.928423
B32: =+B28+1 -> 1979 | C32: =+C31+1 -> 1998 | D32: {=INDEX(GMW!$A$2:$NF$150,MATCH(1,(GMW!$NE$2:$NE$150=D$3)*(GMW!$ND$2:$ND$150=D$4)*(GMW!$NF$2:$NF$150=D$1),0),$C32-1966)} -> 275695 | E32: {=INDEX(GMW!$A$2:$NF$150,MATCH(1,(GMW!$NE$2:$NE$150=E$3)*(GMW!$ND$2:$ND$150=E$4)*(GMW!$NF$2:$NF$150=E$1),0),$C32-1966)} -> 27.26824 | F32: {=INDEX(GMW!$A$2:$NF$150,MATCH(1,(GMW!$NE$2:$NE$150=F$3)*(GMW!$ND$2:$ND$150=F$4)*(GMW!$NF$2:$NF$150=F$1),0),$C32-1966)} -> 49782 | G32: {=INDEX(GMW!$A$2:$NF$150,MATCH(1,(GMW!$NE$2:$NE$150=G$3)*(GMW!$ND$2:$ND$150=G$4)*(GMW!$NF$2:$NF$150=G$1),0),$C32-1966)} -> 17701.14 | H32: {=INDEX(GMW!$A$2:$NF$150,MATCH(1,(GMW!$NE$2:$NE$150=H$3)*(GMW!$ND$2:$ND$150=H$4)*(GMW!$NF$2:$NF$150=H$1),0),$C32-1966)} -> 40615 | I32: {=INDEX(GMW!$A$2:$NF$150,MATCH(1,(GMW!$NE$2:$NE$150=I$3)*(GMW!$ND$2:$ND$150=I$4)*(GMW!$NF$2:$NF$150=I$1),0),$C32-1966)} -> 10011.58 | J32: {=INDEX(GMW!$A$2:$NF$150,MATCH(1,(GMW!$NE$2:$NE$150=J$3)*(GMW!$ND$2:$ND$150=J$4)*(GMW!$NF$2:$NF$150=J$1),0),$C32-1966)} -> 49861 | K32: {=INDEX(GMW!$A$2:$NF$150,MATCH(1,(GMW!$NE$2:$NE$150=K$3)*(GMW!$ND$2:$ND$150=K$4)*(GMW!$NF$2:$NF$150=K$1),0),$C32-1966)} -> 18646.51 | ... AV32: {=INDEX(GMW!$A$2:$NF$150,MATCH(1,(GMW!$NE$2:$NE$150=AV$3)*(GMW!$ND$2:$ND$150=AV$4)*(GMW!$NF$2:$NF$150=AV$1),0),$C32-1966)} -> -1.925299
B33: =+B29+1 -> 1979 | C33: =+C32+1 -> 1999 | D33: {=INDEX(GMW!$A$2:$NF$150,MATCH(1,(GMW!$NE$2:$NE$150=D$3)*(GMW!$ND$2:$ND$150=D$4)*(GMW!$NF$2:$NF$150=D$1),0),$C33-1966)} -> 269599 | E33: {=INDEX(GMW!$A$2:$NF$150,MATCH(1,(GMW!$NE$2:$NE$150=E$3)*(GMW!$ND$2:$ND$150=E$4)*(GMW!$NF$2:$NF$150=E$1),0),$C33-1966)} -> 28.91059 | F33: {=INDEX(GMW!$A$2:$NF$150,MATCH(1,(GMW!$NE$2:$NE$150=F$3)*(GMW!$ND$2:$ND$150=F$4)*(GMW!$NF$2:$NF$150=F$1),0),$C33-1966)} -> 48026 | G33: {=INDEX(GMW!$A$2:$NF$150,MATCH(1,(GMW!$NE$2:$NE$150=G$3)*(GMW!$ND$2:$ND$150=G$4)*(GMW!$NF$2:$NF$150=G$1),0),$C33-1966)} -> 14802.85 | H33: {=INDEX(GMW!$A$2:$NF$150,MATCH(1,(GMW!$NE$2:$NE$150=H$3)*(GMW!$ND$2:$ND$150=H$4)*(GMW!$NF$2:$NF$150=H$1),0),$C33-1966)} -> 41427 | I33: {=INDEX(GMW!$A$2:$NF$150,MATCH(1,(GMW!$NE$2:$NE$150=I$3)*(GMW!$ND$2:$ND$150=I$4)*(GMW!$NF$2:$NF$150=I$1),0),$C33-1966)} -> 11078.58 | J33: {=INDEX(GMW!$A$2:$NF$150,MATCH(1,(GMW!$NE$2:$NE$150=J$3)*(GMW!$ND$2:$ND$150=J$4)*(GMW!$NF$2:$NF$150=J$1),0),$C33-1966)} -> 50787 | K33: {=INDEX(GMW!$A$2:$NF$150,MATCH(1,(GMW!$NE$2:$NE$150=K$3)*(GMW!$ND$2:$ND$150=K$4)*(GMW!$NF$2:$NF$150=K$1),0),$C33-1966)} -> 18905.56 | ... AV33: {=INDEX(GMW!$A$2:$NF$150,MATCH(1,(GMW!$NE$2:$NE$150=AV$3)*(GMW!$ND$2:$ND$150=AV$4)*(GMW!$NF$2:$NF$150=AV$1),0),$C33-1966)} -> -1.92218
B34: =+B30+1 -> 1979 | C34: =+C33+1 -> 2000 | D34: {=INDEX(GMW!$A$2:$NF$150,MATCH(1,(GMW!$NE$2:$NE$150=D$3)*(GMW!$ND$2:$ND$150=D$4)*(GMW!$NF$2:$NF$150=D$1),0),$C34-1966)} -> 272359 | E34: {=INDEX(GMW!$A$2:$NF$150,MATCH(1,(GMW!$NE$2:$NE$150=E$3)*(GMW!$ND$2:$ND$150=E$4)*(GMW!$NF$2:$NF$150=E$1),0),$C34-1966)} -> 29.71873 | F34: {=INDEX(GMW!$A$2:$NF$150,MATCH(1,(GMW!$NE$2:$NE$150=F$3)*(GMW!$ND$2:$ND$150=F$4)*(GMW!$NF$2:$NF$150=F$1),0),$C34-1966)} -> 48391 | G34: {=INDEX(GMW!$A$2:$NF$150,MATCH(1,(GMW!$NE$2:$NE$150=G$3)*(GMW!$ND$2:$ND$150=G$4)*(GMW!$NF$2:$NF$150=G$1),0),$C34-1966)} -> 16132.91 | H34: {=INDEX(GMW!$A$2:$NF$150,MATCH(1,(GMW!$NE$2:$NE$150=H$3)*(GMW!$ND$2:$ND$150=H$4)*(GMW!$NF$2:$NF$150=H$1),0),$C34-1966)} -> 41252 | I34: {=INDEX(GMW!$A$2:$NF$150,MATCH(1,(GMW!$NE$2:$NE$150=I$3)*(GMW!$ND$2:$ND$150=I$4)*(GMW!$NF$2:$NF$150=I$1),0),$C34-1966)} -> 11307.47 | J34: {=INDEX(GMW!$A$2:$NF$150,MATCH(1,(GMW!$NE$2:$NE$150=J$3)*(GMW!$ND$2:$ND$150=J$4)*(GMW!$NF$2:$NF$150=J$1),0),$C34-1966)} -> 51496 | K34: {=INDEX(GMW!$A$2:$NF$150,MATCH(1,(GMW!$NE$2:$NE$150=K$3)*(GMW!$ND$2:$ND$150=K$4)*(GMW!$NF$2:$NF$150=K$1),0),$C34-1966)} -> 18569.28 | ... AV34: {=INDEX(GMW!$A$2:$NF$150,MATCH(1,(GMW!$NE$2:$NE$150=AV$3)*(GMW!$ND$2:$ND$150=AV$4)*(GMW!$NF$2:$NF$150=AV$1),0),$C34-1966)} -> -1.919066
A35: 1980 | B35: =+B31+1 -> 1980 | C35: =+C34+1 -> 2001 | D35: {=INDEX(GMW!$A$2:$NF$150,MATCH(1,(GMW!$NE$2:$NE$150=D$3)*(GMW!$ND$2:$ND$150=D$4)*(GMW!$NF$2:$NF$150=D$1),0),$C35-1966)} -> 269776 | E35: {=INDEX(GMW!$A$2:$NF$150,MATCH(1,(GMW!$NE$2:$NE$150=E$3)*(GMW!$ND$2:$ND$150=E$4)*(GMW!$NF$2:$NF$150=E$1),0),$C35-1966)} -> 30.60508 | F35: {=INDEX(GMW!$A$2:$NF$150,MATCH(1,(GMW!$NE$2:$NE$150=F$3)*(GMW!$ND$2:$ND$150=F$4)*(GMW!$NF$2:$NF$150=F$1),0),$C35-1966)} -> 49049 | G35: {=INDEX(GMW!$A$2:$NF$150,MATCH(1,(GMW!$NE$2:$NE$150=G$3)*(GMW!$ND$2:$ND$150=G$4)*(GMW!$NF$2:$NF$150=G$1),0),$C35-1966)} -> 17320.91 | H35: {=INDEX(GMW!$A$2:$NF$150,MATCH(1,(GMW!$NE$2:$NE$150=H$3)*(GMW!$ND$2:$ND$150=H$4)*(GMW!$NF$2:$NF$150=H$1),0),$C35-1966)} -> 41769 | I35: {=INDEX(GMW!$A$2:$NF$150,MATCH(1,(GMW!$NE$2:$NE$150=I$3)*(GMW!$ND$2:$ND$150=I$4)*(GMW!$NF$2:$NF$150=I$1),0),$C35-1966)} -> 11899.42 | J35: {=INDEX(GMW!$A$2:$NF$150,MATCH(1,(GMW!$NE$2:$NE$150=J$3)*(GMW!$ND$2:$ND$150=J$4)*(GMW!$NF$2:$NF$150=J$1),0),$C35-1966)} -> 49012 | K35: {=INDEX(GMW!$A$2:$NF$150,MATCH(1,(GMW!$NE$2:$NE$150=K$3)*(GMW!$ND$2:$ND$150=K$4)*(GMW!$NF$2:$NF$150=K$1),0),$C35-1966)} -> 18319.89 | ... AV35: {=INDEX(GMW!$A$2:$NF$150,MATCH(1,(GMW!$NE$2:$NE$150=AV$3)*(GMW!$ND$2:$ND$150=AV$4)*(GMW!$NF$2:$NF$150=AV$1),0),$C35-1966)} -> -1.915958
B36: =+B32+1 -> 1980 | C36: =+C35+1 -> 2002 | D36: {=INDEX(GMW!$A$2:$NF$150,MATCH(1,(GMW!$NE$2:$NE$150=D$3)*(GMW!$ND$2:$ND$150=D$4)*(GMW!$NF$2:$NF$150=D$1),0),$C36-1966)} -> 264448 | E36: {=INDEX(GMW!$A$2:$NF$150,MATCH(1,(GMW!$NE$2:$NE$150=E$3)*(GMW!$ND$2:$ND$150=E$4)*(GMW!$NF$2:$NF$150=E$1),0),$C36-1966)} -> 32.24743 | F36: {=INDEX(GMW!$A$2:$NF$150,MATCH(1,(GMW!$NE$2:$NE$150=F$3)*(GMW!$ND$2:$ND$150=F$4)*(GMW!$NF$2:$NF$150=F$1),0),$C36-1966)} -> 47032 | G36: {=INDEX(GMW!$A$2:$NF$150,MATCH(1,(GMW!$NE$2:$NE$150=G$3)*(GMW!$ND$2:$ND$150=G$4)*(GMW!$NF$2:$NF$150=G$1),0),$C36-1966)} -> 16153.44 | H36: {=INDEX(GMW!$A$2:$NF$150,MATCH(1,(GMW!$NE$2:$NE$150=H$3)*(GMW!$ND$2:$ND$150=H$4)*(GMW!$NF$2:$NF$150=H$1),0),$C36-1966)} -> 40270 | I36: {=INDEX(GMW!$A$2:$NF$150,MATCH(1,(GMW!$NE$2:$NE$150=I$3)*(GMW!$ND$2:$ND$150=I$4)*(GMW!$NF$2:$NF$150=I$1),0),$C36-1966)} -> 11463.22 | J36: {=INDEX(GMW!$A$2:$NF$150,MATCH(1,(GMW!$NE$2:$NE$150=J$3)*(GMW!$ND$2:$ND$150=J$4)*(GMW!$NF$2:$NF$150=J$1),0),$C36-1966)} -> 47095 | K36: {=INDEX(GMW!$A$2:$NF$150,MATCH(1,(GMW!$NE$2:$NE$150=K$3)*(GMW!$ND$2:$ND$150=K$4)*(GMW!$NF$2:$NF$150=K$1),0),$C36-1966)} -> 18007.75 | ... AV36: {=INDEX(GMW!$A$2:$NF$150,MATCH(1,(GMW!$NE$2:$NE$150=AV$3)*(GMW!$ND$2:$ND$150=AV$4)*(GMW!$NF$2:$NF$150=AV$1),0),$C36-1966)} -> -1.912854
B37: =+B33+1 -> 1980 | C37: =+C36+1 -> 2003 | D37: {=INDEX(GMW!$A$2:$NF$150,MATCH(1,(GMW!$NE$2:$NE$150=D$3)*(GMW!$ND$2:$ND$150=D$4)*(GMW!$NF$2:$NF$150=D$1),0),$C37-1966)} -> 264139 | E37: {=INDEX(GMW!$A$2:$NF$150,MATCH(1,(GMW!$NE$2:$NE$150=E$3)*(GMW!$ND$2:$ND$150=E$4)*(GMW!$NF$2:$NF$150=E$1),0),$C37-1966)} -> 32.9513 | F37: {=INDEX(GMW!$A$2:$NF$150,MATCH(1,(GMW!$NE$2:$NE$150=F$3)*(GMW!$ND$2:$ND$150=F$4)*(GMW!$NF$2:$NF$150=F$1),0),$C37-1966)} -> 45832 | G37: {=INDEX(GMW!$A$2:$NF$150,MATCH(1,(GMW!$NE$2:$NE$150=G$3)*(GMW!$ND$2:$ND$150=G$4)*(GMW!$NF$2:$NF$150=G$1),0),$C37-1966)} -> 15567.97 | H37: {=INDEX(GMW!$A$2:$NF$150,MATCH(1,(GMW!$NE$2:$NE$150=H$3)*(GMW!$ND$2:$ND$150=H$4)*(GMW!$NF$2:$NF$150=H$1),0),$C37-1966)} -> 36904 | I37: {=INDEX(GMW!$A$2:$NF$150,MATCH(1,(GMW!$NE$2:$NE$150=I$3)*(GMW!$ND$2:$ND$150=I$4)*(GMW!$NF$2:$NF$150=I$1),0),$C37-1966)} -> 10143 | J37: {=INDEX(GMW!$A$2:$NF$150,MATCH(1,(GMW!$NE$2:$NE$150=J$3)*(GMW!$ND$2:$ND$150=J$4)*(GMW!$NF$2:$NF$150=J$1),0),$C37-1966)} -> 46257 | K37: {=INDEX(GMW!$A$2:$NF$150,MATCH(1,(GMW!$NE$2:$NE$150=K$3)*(GMW!$ND$2:$ND$150=K$4)*(GMW!$NF$2:$NF$150=K$1),0),$C37-1966)} -> 17697.21 | ... AV37: {=INDEX(GMW!$A$2:$NF$150,MATCH(1,(GMW!$NE$2:$NE$150=AV$3)*(GMW!$ND$2:$ND$150=AV$4)*(GMW!$NF$2:$NF$150=AV$1),0),$C37-1966)} -> -1.909755
B38: =+B34+1 -> 1980 | C38: =+C37+1 -> 2004 | D38: {=INDEX(GMW!$A$2:$NF$150,MATCH(1,(GMW!$NE$2:$NE$150=D$3)*(GMW!$ND$2:$ND$150=D$4)*(GMW!$NF$2:$NF$150=D$1),0),$C38-1966)} -> 261297 | E38: {=INDEX(GMW!$A$2:$NF$150,MATCH(1,(GMW!$NE$2:$NE$150=E$3)*(GMW!$ND$2:$ND$150=E$4)*(GMW!$NF$2:$NF$150=E$1),0),$C38-1966)} -> 33.55088 | F38: {=INDEX(GMW!$A$2:$NF$150,MATCH(1,(GMW!$NE$2:$NE$150=F$3)*(GMW!$ND$2:$ND$150=F$4)*(GMW!$NF$2:$NF$150=F$1),0),$C38-1966)} -> 45526 | G38: {=INDEX(GMW!$A$2:$NF$150,MATCH(1,(GMW!$NE$2:$NE$150=G$3)*(GMW!$ND$2:$ND$150=G$4)*(GMW!$NF$2:$NF$150=G$1),0),$C38-1966)} -> 15568.44 | H38: {=INDEX(GMW!$A$2:$NF$150,MATCH(1,(GMW!$NE$2:$NE$150=H$3)*(GMW!$ND$2:$ND$150=H$4)*(GMW!$NF$2:$NF$150=H$1),0),$C38-1966)} -> 36054 | I38: {=INDEX(GMW!$A$2:$NF$150,MATCH(1,(GMW!$NE$2:$NE$150=I$3)*(GMW!$ND$2:$ND$150=I$4)*(GMW!$NF$2:$NF$150=I$1),0),$C38-1966)} -> 9975.9 | J38: {=INDEX(GMW!$A$2:$NF$150,MATCH(1,(GMW!$NE$2:$NE$150=J$3)*(GMW!$ND$2:$ND$150=J$4)*(GMW!$NF$2:$NF$150=J$1),0),$C38-1966)} -> 45597 | K38: {=INDEX(GMW!$A$2:$NF$150,MATCH(1,(GMW!$NE$2:$NE$150=K$3)*(GMW!$ND$2:$ND$150=K$4)*(GMW!$NF$2:$NF$150=K$1),0),$C38-1966)} -> 17259.57 | ... AV38: {=INDEX(GMW!$A$2:$NF$150,MATCH(1,(GMW!$NE$2:$NE$150=AV$3)*(GMW!$ND$2:$ND$150=AV$4)*(GMW!$NF$2:$NF$150=AV$1),0),$C38-1966)} -> -1.906661
A39: 1981 | B39: =+B35+1 -> 1981 | C39: =+C38+1 -> 2005 | D39: {=INDEX(GMW!$A$2:$NF$150,MATCH(1,(GMW!$NE$2:$NE$150=D$3)*(GMW!$ND$2:$ND$150=D$4)*(GMW!$NF$2:$NF$150=D$1),0),$C39-1966)} -> 261131 | E39: {=INDEX(GMW!$A$2:$NF$150,MATCH(1,(GMW!$NE$2:$NE$150=E$3)*(GMW!$ND$2:$ND$150=E$4)*(GMW!$NF$2:$NF$150=E$1),0),$C39-1966)} -> 34.3851 | F39: {=INDEX(GMW!$A$2:$NF$150,MATCH(1,(GMW!$NE$2:$NE$150=F$3)*(GMW!$ND$2:$ND$150=F$4)*(GMW!$NF$2:$NF$150=F$1),0),$C39-1966)} -> 45162 | G39: {=INDEX(GMW!$A$2:$NF$150,MATCH(1,(GMW!$NE$2:$NE$150=G$3)*(GMW!$ND$2:$ND$150=G$4)*(GMW!$NF$2:$NF$150=G$1),0),$C39-1966)} -> 12698.02 | H39: {=INDEX(GMW!$A$2:$NF$150,MATCH(1,(GMW!$NE$2:$NE$150=H$3)*(GMW!$ND$2:$ND$150=H$4)*(GMW!$NF$2:$NF$150=H$1),0),$C39-1966)} -> 34504 | I39: {=INDEX(GMW!$A$2:$NF$150,MATCH(1,(GMW!$NE$2:$NE$150=I$3)*(GMW!$ND$2:$ND$150=I$4)*(GMW!$NF$2:$NF$150=I$1),0),$C39-1966)} -> 9966.725 | J39: {=INDEX(GMW!$A$2:$NF$150,MATCH(1,(GMW!$NE$2:$NE$150=J$3)*(GMW!$ND$2:$ND$150=J$4)*(GMW!$NF$2:$NF$150=J$1),0),$C39-1966)} -> 43073 | K39: {=INDEX(GMW!$A$2:$NF$150,MATCH(1,(GMW!$NE$2:$NE$150=K$3)*(GMW!$ND$2:$ND$150=K$4)*(GMW!$NF$2:$NF$150=K$1),0),$C39-1966)} -> 16474.38 | ... AV39: {=INDEX(GMW!$A$2:$NF$150,MATCH(1,(GMW!$NE$2:$NE$150=AV$3)*(GMW!$ND$2:$ND$150=AV$4)*(GMW!$NF$2:$NF$150=AV$1),0),$C39-1966)} -> -1.903573
B40: =+B36+1 -> 1981 | C40: =+C39+1 -> 2006 | D40: {=INDEX(GMW!$A$2:$NF$150,MATCH(1,(GMW!$NE$2:$NE$150=D$3)*(GMW!$ND$2:$ND$150=D$4)*(GMW!$NF$2:$NF$150=D$1),0),$C40-1966)} -> 261739 | E40: {=INDEX(GMW!$A$2:$NF$150,MATCH(1,(GMW!$NE$2:$NE$150=E$3)*(GMW!$ND$2:$ND$150=E$4)*(GMW!$NF$2:$NF$150=E$1),0),$C40-1966)} -> 36.07959 | F40: {=INDEX(GMW!$A$2:$NF$150,MATCH(1,(GMW!$NE$2:$NE$150=F$3)*(GMW!$ND$2:$ND$150=F$4)*(GMW!$NF$2:$NF$150=F$1),0),$C40-1966)} -> 45719 | G40: {=INDEX(GMW!$A$2:$NF$150,MATCH(1,(GMW!$NE$2:$NE$150=G$3)*(GMW!$ND$2:$ND$150=G$4)*(GMW!$NF$2:$NF$150=G$1),0),$C40-1966)} -> 13291.79 | H40: {=INDEX(GMW!$A$2:$NF$150,MATCH(1,(GMW!$NE$2:$NE$150=H$3)*(GMW!$ND$2:$ND$150=H$4)*(GMW!$NF$2:$NF$150=H$1),0),$C40-1966)} -> 36432 | I40: {=INDEX(GMW!$A$2:$NF$150,MATCH(1,(GMW!$NE$2:$NE$150=I$3)*(GMW!$ND$2:$ND$150=I$4)*(GMW!$NF$2:$NF$150=I$1),0),$C40-1966)} -> 11496.63 | J40: {=INDEX(GMW!$A$2:$NF$150,MATCH(1,(GMW!$NE$2:$NE$150=J$3)*(GMW!$ND$2:$ND$150=J$4)*(GMW!$NF$2:$NF$150=J$1),0),$C40-1966)} -> 44079 | K40: {=INDEX(GMW!$A$2:$NF$150,MATCH(1,(GMW!$NE$2:$NE$150=K$3)*(GMW!$ND$2:$ND$150=K$4)*(GMW!$NF$2:$NF$150=K$1),0),$C40-1966)} -> 16442.2 | ... AV40: {=INDEX(GMW!$A$2:$NF$150,MATCH(1,(GMW!$NE$2:$NE$150=AV$3)*(GMW!$ND$2:$ND$150=AV$4)*(GMW!$NF$2:$NF$150=AV$1),0),$C40-1966)} -> -1.900489
B41: =+B37+1 -> 1981 | C41: =+C40+1 -> 2007 | D41: {=INDEX(GMW!$A$2:$NF$150,MATCH(1,(GMW!$NE$2:$NE$150=D$3)*(GMW!$ND$2:$ND$150=D$4)*(GMW!$NF$2:$NF$150=D$1),0),$C41-1966)} -> 264602 | E41: {=INDEX(GMW!$A$2:$NF$150,MATCH(1,(GMW!$NE$2:$NE$150=E$3)*(GMW!$ND$2:$ND$150=E$4)*(GMW!$NF$2:$NF$150=E$1),0),$C41-1966)} -> 36.73131 | F41: {=INDEX(GMW!$A$2:$NF$150,MATCH(1,(GMW!$NE$2:$NE$150=F$3)*(GMW!$ND$2:$ND$150=F$4)*(GMW!$NF$2:$NF$150=F$1),0),$C41-1966)} -> 47827 | G41: {=INDEX(GMW!$A$2:$NF$150,MATCH(1,(GMW!$NE$2:$NE$150=G$3)*(GMW!$ND$2:$ND$150=G$4)*(GMW!$NF$2:$NF$150=G$1),0),$C41-1966)} -> 13837.25 | H41: {=INDEX(GMW!$A$2:$NF$150,MATCH(1,(GMW!$NE$2:$NE$150=H$3)*(GMW!$ND$2:$ND$150=H$4)*(GMW!$NF$2:$NF$150=H$1),0),$C41-1966)} -> 40446 | I41: {=INDEX(GMW!$A$2:$NF$150,MATCH(1,(GMW!$NE$2:$NE$150=I$3)*(GMW!$ND$2:$ND$150=I$4)*(GMW!$NF$2:$NF$150=I$1),0),$C41-1966)} -> 14028.85 | J41: {=INDEX(GMW!$A$2:$NF$150,MATCH(1,(GMW!$NE$2:$NE$150=J$3)*(GMW!$ND$2:$ND$150=J$4)*(GMW!$NF$2:$NF$150=J$1),0),$C41-1966)} -> 44442 | K41: {=INDEX(GMW!$A$2:$NF$150,MATCH(1,(GMW!$NE$2:$NE$150=K$3)*(GMW!$ND$2:$ND$150=K$4)*(GMW!$NF$2:$NF$150=K$1),0),$C41-1966)} -> 16635.28 | ... AV41: {=INDEX(GMW!$A$2:$NF$150,MATCH(1,(GMW!$NE$2:$NE$150=AV$3)*(GMW!$ND$2:$ND$150=AV$4)*(GMW!$NF$2:$NF$150=AV$1),0),$C41-1966)} -> -1.89741
B42: =+B38+1 -> 1981 | C42: =+C41+1 -> 2008 | D42: {=INDEX(GMW!$A$2:$NF$150,MATCH(1,(GMW!$NE$2:$NE$150=D$3)*(GMW!$ND$2:$ND$150=D$4)*(GMW!$NF$2:$NF$150=D$1),0),$C42-1966)} -> 264902 | E42: {=INDEX(GMW!$A$2:$NF$150,MATCH(1,(GMW!$NE$2:$NE$150=E$3)*(GMW!$ND$2:$ND$150=E$4)*(GMW!$NF$2:$NF$150=E$1),0),$C42-1966)} -> 37.43518 | F42: {=INDEX(GMW!$A$2:$NF$150,MATCH(1,(GMW!$NE$2:$NE$150=F$3)*(GMW!$ND$2:$ND$150=F$4)*(GMW!$NF$2:$NF$150=F$1),0),$C42-1966)} -> 47597 | G42: {=INDEX(GMW!$A$2:$NF$150,MATCH(1,(GMW!$NE$2:$NE$150=G$3)*(GMW!$ND$2:$ND$150=G$4)*(GMW!$NF$2:$NF$150=G$1),0),$C42-1966)} -> 14265.79 | H42: {=INDEX(GMW!$A$2:$NF$150,MATCH(1,(GMW!$NE$2:$NE$150=H$3)*(GMW!$ND$2:$ND$150=H$4)*(GMW!$NF$2:$NF$150=H$1),0),$C42-1966)} -> 39200 | I42: {=INDEX(GMW!$A$2:$NF$150,MATCH(1,(GMW!$NE$2:$NE$150=I$3)*(GMW!$ND$2:$ND$150=I$4)*(GMW!$NF$2:$NF$150=I$1),0),$C42-1966)} -> 13017.85 | J42: {=INDEX(GMW!$A$2:$NF$150,MATCH(1,(GMW!$NE$2:$NE$150=J$3)*(GMW!$ND$2:$ND$150=J$4)*(GMW!$NF$2:$NF$150=J$1),0),$C42-1966)} -> 43901 | K42: {=INDEX(GMW!$A$2:$NF$150,MATCH(1,(GMW!$NE$2:$NE$150=K$3)*(GMW!$ND$2:$ND$150=K$4)*(GMW!$NF$2:$NF$150=K$1),0),$C42-1966)} -> 16595.06 | ... AV42: {=INDEX(GMW!$A$2:$NF$150,MATCH(1,(GMW!$NE$2:$NE$150=AV$3)*(GMW!$ND$2:$ND$150=AV$4)*(GMW!$NF$2:$NF$150=AV$1),0),$C42-1966)} -> -1.894337
A43: 1982 | B43: =+B39+1 -> 1982 | C43: =+C42+1 -> 2009 | D43: {=INDEX(GMW!$A$2:$NF$150,MATCH(1,(GMW!$NE$2:$NE$150=D$3)*(GMW!$ND$2:$ND$150=D$4)*(GMW!$NF$2:$NF$150=D$1),0),$C43-1966)} -> 265408 | E43: {=INDEX(GMW!$A$2:$NF$150,MATCH(1,(GMW!$NE$2:$NE$150=E$3)*(GMW!$ND$2:$ND$150=E$4)*(GMW!$NF$2:$NF$150=E$1),0),$C43-1966)} -> 37.87835 | F43: {=INDEX(GMW!$A$2:$NF$150,MATCH(1,(GMW!$NE$2:$NE$150=F$3)*(GMW!$ND$2:$ND$150=F$4)*(GMW!$NF$2:$NF$150=F$1),0),$C43-1966)} -> 46524 | G43: {=INDEX(GMW!$A$2:$NF$150,MATCH(1,(GMW!$NE$2:$NE$150=G$3)*(GMW!$ND$2:$ND$150=G$4)*(GMW!$NF$2:$NF$150=G$1),0),$C43-1966)} -> 14239.55 | H43: {=INDEX(GMW!$A$2:$NF$150,MATCH(1,(GMW!$NE$2:$NE$150=H$3)*(GMW!$ND$2:$ND$150=H$4)*(GMW!$NF$2:$NF$150=H$1),0),$C43-1966)} -> 38853 | I43: {=INDEX(GMW!$A$2:$NF$150,MATCH(1,(GMW!$NE$2:$NE$150=I$3)*(GMW!$ND$2:$ND$150=I$4)*(GMW!$NF$2:$NF$150=I$1),0),$C43-1966)} -> 13541.75 | J43: {=INDEX(GMW!$A$2:$NF$150,MATCH(1,(GMW!$NE$2:$NE$150=J$3)*(GMW!$ND$2:$ND$150=J$4)*(GMW!$NF$2:$NF$150=J$1),0),$C43-1966)} -> 43821 | K43: {=INDEX(GMW!$A$2:$NF$150,MATCH(1,(GMW!$NE$2:$NE$150=K$3)*(GMW!$ND$2:$ND$150=K$4)*(GMW!$NF$2:$NF$150=K$1),0),$C43-1966)} -> 16825.14 | ... AV43: {=INDEX(GMW!$A$2:$NF$150,MATCH(1,(GMW!$NE$2:$NE$150=AV$3)*(GMW!$ND$2:$ND$150=AV$4)*(GMW!$NF$2:$NF$150=AV$1),0),$C43-1966)} -> -1.891268
B44: =+B40+1 -> 1982 | C44: =+C43+1 -> 2010 | D44: {=INDEX(GMW!$A$2:$NF$150,MATCH(1,(GMW!$NE$2:$NE$150=D$3)*(GMW!$ND$2:$ND$150=D$4)*(GMW!$NF$2:$NF$150=D$1),0),$C44-1966)} -> 268196 | E44: {=INDEX(GMW!$A$2:$NF$150,MATCH(1,(GMW!$NE$2:$NE$150=E$3)*(GMW!$ND$2:$ND$150=E$4)*(GMW!$NF$2:$NF$150=E$1),0),$C44-1966)} -> 39.1818 | F44: {=INDEX(GMW!$A$2:$NF$150,MATCH(1,(GMW!$NE$2:$NE$150=F$3)*(GMW!$ND$2:$ND$150=F$4)*(GMW!$NF$2:$NF$150=F$1),0),$C44-1966)} -> 47505 | G44: {=INDEX(GMW!$A$2:$NF$150,MATCH(1,(GMW!$NE$2:$NE$150=G$3)*(GMW!$ND$2:$ND$150=G$4)*(GMW!$NF$2:$NF$150=G$1),0),$C44-1966)} -> 14329.72 | H44: {=INDEX(GMW!$A$2:$NF$150,MATCH(1,(GMW!$NE$2:$NE$150=H$3)*(GMW!$ND$2:$ND$150=H$4)*(GMW!$NF$2:$NF$150=H$1),0),$C44-1966)} -> 40506 | I44: {=INDEX(GMW!$A$2:$NF$150,MATCH(1,(GMW!$NE$2:$NE$150=I$3)*(GMW!$ND$2:$ND$150=I$4)*(GMW!$NF$2:$NF$150=I$1),0),$C44-1966)} -> 14790.67 | J44: {=INDEX(GMW!$A$2:$NF$150,MATCH(1,(GMW!$NE$2:$NE$150=J$3)*(GMW!$ND$2:$ND$150=J$4)*(GMW!$NF$2:$NF$150=J$1),0),$C44-1966)} -> 45825 | K44: {=INDEX(GMW!$A$2:$NF$150,MATCH(1,(GMW!$NE$2:$NE$150=K$3)*(GMW!$ND$2:$ND$150=K$4)*(GMW!$NF$2:$NF$150=K$1),0),$C44-1966)} -> 16926.51 | ... AV44: {=INDEX(GMW!$A$2:$NF$150,MATCH(1,(GMW!$NE$2:$NE$150=AV$3)*(GMW!$ND$2:$ND$150=AV$4)*(GMW!$NF$2:$NF$150=AV$1),0),$C44-1966)} -> -1.888204
B45: =+B41+1 -> 1982 | C45: =+C44+1 -> 2011 | D45: {=INDEX(GMW!$A$2:$NF$150,MATCH(1,(GMW!$NE$2:$NE$150=D$3)*(GMW!$ND$2:$ND$150=D$4)*(GMW!$NF$2:$NF$150=D$1),0),$C45-1966)} -> 268798 | E45: {=INDEX(GMW!$A$2:$NF$150,MATCH(1,(GMW!$NE$2:$NE$150=E$3)*(GMW!$ND$2:$ND$150=E$4)*(GMW!$NF$2:$NF$150=E$1),0),$C45-1966)} -> 39.41642 | F45: {=INDEX(GMW!$A$2:$NF$150,MATCH(1,(GMW!$NE$2:$NE$150=F$3)*(GMW!$ND$2:$ND$150=F$4)*(GMW!$NF$2:$NF$150=F$1),0),$C45-1966)} -> 46534 | G45: {=INDEX(GMW!$A$2:$NF$150,MATCH(1,(GMW!$NE$2:$NE$150=G$3)*(GMW!$ND$2:$ND$150=G$4)*(GMW!$NF$2:$NF$150=G$1),0),$C45-1966)} -> 12844.9 | H45: {=INDEX(GMW!$A$2:$NF$150,MATCH(1,(GMW!$NE$2:$NE$150=H$3)*(GMW!$ND$2:$ND$150=H$4)*(GMW!$NF$2:$NF$150=H$1),0),$C45-1966)} -> 39271 | I45: {=INDEX(GMW!$A$2:$NF$150,MATCH(1,(GMW!$NE$2:$NE$150=I$3)*(GMW!$ND$2:$ND$150=I$4)*(GMW!$NF$2:$NF$150=I$1),0),$C45-1966)} -> 14659.58 | J45: {=INDEX(GMW!$A$2:$NF$150,MATCH(1,(GMW!$NE$2:$NE$150=J$3)*(GMW!$ND$2:$ND$150=J$4)*(GMW!$NF$2:$NF$150=J$1),0),$C45-1966)} -> 47163 | K45: {=INDEX(GMW!$A$2:$NF$150,MATCH(1,(GMW!$NE$2:$NE$150=K$3)*(GMW!$ND$2:$ND$150=K$4)*(GMW!$NF$2:$NF$150=K$1),0),$C45-1966)} -> 17586.19 | ... AV45: {=INDEX(GMW!$A$2:$NF$150,MATCH(1,(GMW!$NE$2:$NE$150=AV$3)*(GMW!$ND$2:$ND$150=AV$4)*(GMW!$NF$2:$NF$150=AV$1),0),$C45-1966)} -> -1.885145
B46: =+B42+1 -> 1982 | C46: =+C45+1 -> 2012 | D46: {=INDEX(GMW!$A$2:$NF$150,MATCH(1,(GMW!$NE$2:$NE$150=D$3)*(GMW!$ND$2:$ND$150=D$4)*(GMW!$NF$2:$NF$150=D$1),0),$C46-1966)} -> 270653 | E46: {=INDEX(GMW!$A$2:$NF$150,MATCH(1,(GMW!$NE$2:$NE$150=E$3)*(GMW!$ND$2:$ND$150=E$4)*(GMW!$NF$2:$NF$150=E$1),0),$C46-1966)} -> 39.88567 | F46: {=INDEX(GMW!$A$2:$NF$150,MATCH(1,(GMW!$NE$2:$NE$150=F$3)*(GMW!$ND$2:$ND$150=F$4)*(GMW!$NF$2:$NF$150=F$1),0),$C46-1966)} -> 47361 | G46: {=INDEX(GMW!$A$2:$NF$150,MATCH(1,(GMW!$NE$2:$NE$150=G$3)*(GMW!$ND$2:$ND$150=G$4)*(GMW!$NF$2:$NF$150=G$1),0),$C46-1966)} -> 13139.37 | H46: {=INDEX(GMW!$A$2:$NF$150,MATCH(1,(GMW!$NE$2:$NE$150=H$3)*(GMW!$ND$2:$ND$150=H$4)*(GMW!$NF$2:$NF$150=H$1),0),$C46-1966)} -> 38776 | I46: {=INDEX(GMW!$A$2:$NF$150,MATCH(1,(GMW!$NE$2:$NE$150=I$3)*(GMW!$ND$2:$ND$150=I$4)*(GMW!$NF$2:$NF$150=I$1),0),$C46-1966)} -> 16134.38 | J46: {=INDEX(GMW!$A$2:$NF$150,MATCH(1,(GMW!$NE$2:$NE$150=J$3)*(GMW!$ND$2:$ND$150=J$4)*(GMW!$NF$2:$NF$150=J$1),0),$C46-1966)} -> 47683 | K46: {=INDEX(GMW!$A$2:$NF$150,MATCH(1,(GMW!$NE$2:$NE$150=K$3)*(GMW!$ND$2:$ND$150=K$4)*(GMW!$NF$2:$NF$150=K$1),0),$C46-1966)} -> 17439.77 | ... AV46: {=INDEX(GMW!$A$2:$NF$150,MATCH(1,(GMW!$NE$2:$NE$150=AV$3)*(GMW!$ND$2:$ND$150=AV$4)*(GMW!$NF$2:$NF$150=AV$1),0),$C46-1966)} -> -1.882091
A47: 1983 | B47: =+B43+1 -> 1983 | C47: =+C46+1 -> 2013 | D47: {=INDEX(GMW!$A$2:$NF$150,MATCH(1,(GMW!$NE$2:$NE$150=D$3)*(GMW!$ND$2:$ND$150=D$4)*(GMW!$NF$2:$NF$150=D$1),0),$C47-1966)} -> 275877 | E47: {=INDEX(GMW!$A$2:$NF$150,MATCH(1,(GMW!$NE$2:$NE$150=E$3)*(GMW!$ND$2:$ND$150=E$4)*(GMW!$NF$2:$NF$150=E$1),0),$C47-1966)} -> 40.17243 | F47: {=INDEX(GMW!$A$2:$NF$150,MATCH(1,(GMW!$NE$2:$NE$150=F$3)*(GMW!$ND$2:$ND$150=F$4)*(GMW!$NF$2:$NF$150=F$1),0),$C47-1966)} -> 47208 | G47: {=INDEX(GMW!$A$2:$NF$150,MATCH(1,(GMW!$NE$2:$NE$150=G$3)*(GMW!$ND$2:$ND$150=G$4)*(GMW!$NF$2:$NF$150=G$1),0),$C47-1966)} -> 13361.43 | H47: {=INDEX(GMW!$A$2:$NF$150,MATCH(1,(GMW!$NE$2:$NE$150=H$3)*(GMW!$ND$2:$ND$150=H$4)*(GMW!$NF$2:$NF$150=H$1),0),$C47-1966)} -> 40491 | I47: {=INDEX(GMW!$A$2:$NF$150,MATCH(1,(GMW!$NE$2:$NE$150=I$3)*(GMW!$ND$2:$ND$150=I$4)*(GMW!$NF$2:$NF$150=I$1),0),$C47-1966)} -> 18293.38 | J47: {=INDEX(GMW!$A$2:$NF$150,MATCH(1,(GMW!$NE$2:$NE$150=J$3)*(GMW!$ND$2:$ND$150=J$4)*(GMW!$NF$2:$NF$150=J$1),0),$C47-1966)} -> 49100 | K47: {=INDEX(GMW!$A$2:$NF$150,MATCH(1,(GMW!$NE$2:$NE$150=K$3)*(GMW!$ND$2:$ND$150=K$4)*(GMW!$NF$2:$NF$150=K$1),0),$C47-1966)} -> 17069.71 | ... AV47: {=INDEX(GMW!$A$2:$NF$150,MATCH(1,(GMW!$NE$2:$NE$150=AV$3)*(GMW!$ND$2:$ND$150=AV$4)*(GMW!$NF$2:$NF$150=AV$1),0),$C47-1966)} -> -1.879043
B48: =+B44+1 -> 1983 | C48: =+C47+1 -> 2014 | D48: {=INDEX(GMW!$A$2:$NF$150,MATCH(1,(GMW!$NE$2:$NE$150=D$3)*(GMW!$ND$2:$ND$150=D$4)*(GMW!$NF$2:$NF$150=D$1),0),$C48-1966)} -> 277790 | E48: {=INDEX(GMW!$A$2:$NF$150,MATCH(1,(GMW!$NE$2:$NE$150=E$3)*(GMW!$ND$2:$ND$150=E$4)*(GMW!$NF$2:$NF$150=E$1),0),$C48-1966)} -> 40.85022 | F48: {=INDEX(GMW!$A$2:$NF$150,MATCH(1,(GMW!$NE$2:$NE$150=F$3)*(GMW!$ND$2:$ND$150=F$4)*(GMW!$NF$2:$NF$150=F$1),0),$C48-1966)} -> 47152 | G48: {=INDEX(GMW!$A$2:$NF$150,MATCH(1,(GMW!$NE$2:$NE$150=G$3)*(GMW!$ND$2:$ND$150=G$4)*(GMW!$NF$2:$NF$150=G$1),0),$C48-1966)} -> 12684.37 | H48: {=INDEX(GMW!$A$2:$NF$150,MATCH(1,(GMW!$NE$2:$NE$150=H$3)*(GMW!$ND$2:$ND$150=H$4)*(GMW!$NF$2:$NF$150=H$1),0),$C48-1966)} -> 41549 | I48: {=INDEX(GMW!$A$2:$NF$150,MATCH(1,(GMW!$NE$2:$NE$150=I$3)*(GMW!$ND$2:$ND$150=I$4)*(GMW!$NF$2:$NF$150=I$1),0),$C48-1966)} -> 17976.5 | J48: {=INDEX(GMW!$A$2:$NF$150,MATCH(1,(GMW!$NE$2:$NE$150=J$3)*(GMW!$ND$2:$ND$150=J$4)*(GMW!$NF$2:$NF$150=J$1),0),$C48-1966)} -> 48513 | K48: {=INDEX(GMW!$A$2:$NF$150,MATCH(1,(GMW!$NE$2:$NE$150=K$3)*(GMW!$ND$2:$ND$150=K$4)*(GMW!$NF$2:$NF$150=K$1),0),$C48-1966)} -> 17183.95 | ... AV48: {=INDEX(GMW!$A$2:$NF$150,MATCH(1,(GMW!$NE$2:$NE$150=AV$3)*(GMW!$ND$2:$ND$150=AV$4)*(GMW!$NF$2:$NF$150=AV$1),0),$C48-1966)} -> -1.875998
B49: =+B45+1 -> 1983 | C49: =+C48+1 -> 2015 | D49: {=INDEX(GMW!$A$2:$NF$150,MATCH(1,(GMW!$NE$2:$NE$150=D$3)*(GMW!$ND$2:$ND$150=D$4)*(GMW!$NF$2:$NF$150=D$1),0),$C49-1966)} -> 280996 | E49: {=INDEX(GMW!$A$2:$NF$150,MATCH(1,(GMW!$NE$2:$NE$150=E$3)*(GMW!$ND$2:$ND$150=E$4)*(GMW!$NF$2:$NF$150=E$1),0),$C49-1966)} -> 41.2934 | F49: {=INDEX(GMW!$A$2:$NF$150,MATCH(1,(GMW!$NE$2:$NE$150=F$3)*(GMW!$ND$2:$ND$150=F$4)*(GMW!$NF$2:$NF$150=F$1),0),$C49-1966)} -> 48076 | G49: {=INDEX(GMW!$A$2:$NF$150,MATCH(1,(GMW!$NE$2:$NE$150=G$3)*(GMW!$ND$2:$ND$150=G$4)*(GMW!$NF$2:$NF$150=G$1),0),$C49-1966)} -> 13444.37 | H49: {=INDEX(GMW!$A$2:$NF$150,MATCH(1,(GMW!$NE$2:$NE$150=H$3)*(GMW!$ND$2:$ND$150=H$4)*(GMW!$NF$2:$NF$150=H$1),0),$C49-1966)} -> 41802 | I49: {=INDEX(GMW!$A$2:$NF$150,MATCH(1,(GMW!$NE$2:$NE$150=I$3)*(GMW!$ND$2:$ND$150=I$4)*(GMW!$NF$2:$NF$150=I$1),0),$C49-1966)} -> 18257.5 | J49: {=INDEX(GMW!$A$2:$NF$150,MATCH(1,(GMW!$NE$2:$NE$150=J$3)*(GMW!$ND$2:$ND$150=J$4)*(GMW!$NF$2:$NF$150=J$1),0),$C49-1966)} -> 48978 | K49: {=INDEX(GMW!$A$2:$NF$150,MATCH(1,(GMW!$NE$2:$NE$150=K$3)*(GMW!$ND$2:$ND$150=K$4)*(GMW!$NF$2:$NF$150=K$1),0),$C49-1966)} -> 17130.85 | ... AV49: {=INDEX(GMW!$A$2:$NF$150,MATCH(1,(GMW!$NE$2:$NE$150=AV$3)*(GMW!$ND$2:$ND$150=AV$4)*(GMW!$NF$2:$NF$150=AV$1),0),$C49-1966)} -> -1.872959
B50: =+B46+1 -> 1983 | C50: =+C49+1 -> 2016 | D50: {=INDEX(GMW!$A$2:$NF$150,MATCH(1,(GMW!$NE$2:$NE$150=D$3)*(GMW!$ND$2:$ND$150=D$4)*(GMW!$NF$2:$NF$150=D$1),0),$C50-1966)} -> 283096 | E50: {=INDEX(GMW!$A$2:$NF$150,MATCH(1,(GMW!$NE$2:$NE$150=E$3)*(GMW!$ND$2:$ND$150=E$4)*(GMW!$NF$2:$NF$150=E$1),0),$C50-1966)} -> 41.76264 | F50: {=INDEX(GMW!$A$2:$NF$150,MATCH(1,(GMW!$NE$2:$NE$150=F$3)*(GMW!$ND$2:$ND$150=F$4)*(GMW!$NF$2:$NF$150=F$1),0),$C50-1966)} -> 48814 | G50: {=INDEX(GMW!$A$2:$NF$150,MATCH(1,(GMW!$NE$2:$NE$150=G$3)*(GMW!$ND$2:$ND$150=G$4)*(GMW!$NF$2:$NF$150=G$1),0),$C50-1966)} -> 12600.25 | H50: {=INDEX(GMW!$A$2:$NF$150,MATCH(1,(GMW!$NE$2:$NE$150=H$3)*(GMW!$ND$2:$ND$150=H$4)*(GMW!$NF$2:$NF$150=H$1),0),$C50-1966)} -> 43271 | I50: {=INDEX(GMW!$A$2:$NF$150,MATCH(1,(GMW!$NE$2:$NE$150=I$3)*(GMW!$ND$2:$ND$150=I$4)*(GMW!$NF$2:$NF$150=I$1),0),$C50-1966)} -> 19691.45 | J50: {=INDEX(GMW!$A$2:$NF$150,MATCH(1,(GMW!$NE$2:$NE$150=J$3)*(GMW!$ND$2:$ND$150=J$4)*(GMW!$NF$2:$NF$150=J$1),0),$C50-1966)} -> 51258 | K50: {=INDEX(GMW!$A$2:$NF$150,MATCH(1,(GMW!$NE$2:$NE$150=K$3)*(GMW!$ND$2:$ND$150=K$4)*(GMW!$NF$2:$NF$150=K$1),0),$C50-1966)} -> 18360.11 | ... AV50: {=INDEX(GMW!$A$2:$NF$150,MATCH(1,(GMW!$NE$2:$NE$150=AV$3)*(GMW!$ND$2:$ND$150=AV$4)*(GMW!$NF$2:$NF$150=AV$1),0),$C50-1966)} -> -1.869925
A51: 1984 | B51: =+B47+1 -> 1984 | C51: =+C50+1 -> 2017 | D51: {=INDEX(GMW!$A$2:$NF$150,MATCH(1,(GMW!$NE$2:$NE$150=D$3)*(GMW!$ND$2:$ND$150=D$4)*(GMW!$NF$2:$NF$150=D$1),0),$C51-1966)} -> 285469 | E51: {=INDEX(GMW!$A$2:$NF$150,MATCH(1,(GMW!$NE$2:$NE$150=E$3)*(GMW!$ND$2:$ND$150=E$4)*(GMW!$NF$2:$NF$150=E$1),0),$C51-1966)} -> 41.86692 | F51: {=INDEX(GMW!$A$2:$NF$150,MATCH(1,(GMW!$NE$2:$NE$150=F$3)*(GMW!$ND$2:$ND$150=F$4)*(GMW!$NF$2:$NF$150=F$1),0),$C51-1966)} -> 49935 | G51: {=INDEX(GMW!$A$2:$NF$150,MATCH(1,(GMW!$NE$2:$NE$150=G$3)*(GMW!$ND$2:$ND$150=G$4)*(GMW!$NF$2:$NF$150=G$1),0),$C51-1966)} -> 14020.54 | H51: {=INDEX(GMW!$A$2:$NF$150,MATCH(1,(GMW!$NE$2:$NE$150=H$3)*(GMW!$ND$2:$ND$150=H$4)*(GMW!$NF$2:$NF$150=H$1),0),$C51-1966)} -> 43672 | I51: {=INDEX(GMW!$A$2:$NF$150,MATCH(1,(GMW!$NE$2:$NE$150=I$3)*(GMW!$ND$2:$ND$150=I$4)*(GMW!$NF$2:$NF$150=I$1),0),$C51-1966)} -> 20075.45 | J51: {=INDEX(GMW!$A$2:$NF$150,MATCH(1,(GMW!$NE$2:$NE$150=J$3)*(GMW!$ND$2:$ND$150=J$4)*(GMW!$NF$2:$NF$150=J$1),0),$C51-1966)} -> 52357 | K51: {=INDEX(GMW!$A$2:$NF$150,MATCH(1,(GMW!$NE$2:$NE$150=K$3)*(GMW!$ND$2:$ND$150=K$4)*(GMW!$NF$2:$NF$150=K$1),0),$C51-1966)} -> 18355.29 | ... AV51: {=INDEX(GMW!$A$2:$NF$150,MATCH(1,(GMW!$NE$2:$NE$150=AV$3)*(GMW!$ND$2:$ND$150=AV$4)*(GMW!$NF$2:$NF$150=AV$1),0),$C51-1966)} -> -1.866896
B52: =+B48+1 -> 1984 | C52: =+C51+1 -> 2018 | D52: {=INDEX(GMW!$A$2:$NF$150,MATCH(1,(GMW!$NE$2:$NE$150=D$3)*(GMW!$ND$2:$ND$150=D$4)*(GMW!$NF$2:$NF$150=D$1),0),$C52-1966)} -> 282605 | E52: {=INDEX(GMW!$A$2:$NF$150,MATCH(1,(GMW!$NE$2:$NE$150=E$3)*(GMW!$ND$2:$ND$150=E$4)*(GMW!$NF$2:$NF$150=E$1),0),$C52-1966)} -> 42.77934 | F52: {=INDEX(GMW!$A$2:$NF$150,MATCH(1,(GMW!$NE$2:$NE$150=F$3)*(GMW!$ND$2:$ND$150=F$4)*(GMW!$NF$2:$NF$150=F$1),0),$C52-1966)} -> 49818 | G52: {=INDEX(GMW!$A$2:$NF$150,MATCH(1,(GMW!$NE$2:$NE$150=G$3)*(GMW!$ND$2:$ND$150=G$4)*(GMW!$NF$2:$NF$150=G$1),0),$C52-1966)} -> 14567.07 | H52: {=INDEX(GMW!$A$2:$NF$150,MATCH(1,(GMW!$NE$2:$NE$150=H$3)*(GMW!$ND$2:$ND$150=H$4)*(GMW!$NF$2:$NF$150=H$1),0),$C52-1966)} -> 45571 | I52: {=INDEX(GMW!$A$2:$NF$150,MATCH(1,(GMW!$NE$2:$NE$150=I$3)*(GMW!$ND$2:$ND$150=I$4)*(GMW!$NF$2:$NF$150=I$1),0),$C52-1966)} -> 19098.85 | J52: {=INDEX(GMW!$A$2:$NF$150,MATCH(1,(GMW!$NE$2:$NE$150=J$3)*(GMW!$ND$2:$ND$150=J$4)*(GMW!$NF$2:$NF$150=J$1),0),$C52-1966)} -> 52558 | K52: {=INDEX(GMW!$A$2:$NF$150,MATCH(1,(GMW!$NE$2:$NE$150=K$3)*(GMW!$ND$2:$ND$150=K$4)*(GMW!$NF$2:$NF$150=K$1),0),$C52-1966)} -> 19235.4 | ... AV52: {=INDEX(GMW!$A$2:$NF$150,MATCH(1,(GMW!$NE$2:$NE$150=AV$3)*(GMW!$ND$2:$ND$150=AV$4)*(GMW!$NF$2:$NF$150=AV$1),0),$C52-1966)} -> -1.863872
B53: =+B49+1 -> 1984 | C53: =+C52+1 -> 2019 | D53: {=INDEX(GMW!$A$2:$NF$150,MATCH(1,(GMW!$NE$2:$NE$150=D$3)*(GMW!$ND$2:$ND$150=D$4)*(GMW!$NF$2:$NF$150=D$1),0),$C53-1966)} -> 284676 | E53: {=INDEX(GMW!$A$2:$NF$150,MATCH(1,(GMW!$NE$2:$NE$150=E$3)*(GMW!$ND$2:$ND$150=E$4)*(GMW!$NF$2:$NF$150=E$1),0),$C53-1966)} -> 42.98789 | F53: {=INDEX(GMW!$A$2:$NF$150,MATCH(1,(GMW!$NE$2:$NE$150=F$3)*(GMW!$ND$2:$ND$150=F$4)*(GMW!$NF$2:$NF$150=F$1),0),$C53-1966)} -> 51338 | G53: {=INDEX(GMW!$A$2:$NF$150,MATCH(1,(GMW!$NE$2:$NE$150=G$3)*(GMW!$ND$2:$ND$150=G$4)*(GMW!$NF$2:$NF$150=G$1),0),$C53-1966)} -> 13787.42 | H53: {=INDEX(GMW!$A$2:$NF$150,MATCH(1,(GMW!$NE$2:$NE$150=H$3)*(GMW!$ND$2:$ND$150=H$4)*(GMW!$NF$2:$NF$150=H$1),0),$C53-1966)} -> 45901 | I53: {=INDEX(GMW!$A$2:$NF$150,MATCH(1,(GMW!$NE$2:$NE$150=I$3)*(GMW!$ND$2:$ND$150=I$4)*(GMW!$NF$2:$NF$150=I$1),0),$C53-1966)} -> 19652.9 | J53: {=INDEX(GMW!$A$2:$NF$150,MATCH(1,(GMW!$NE$2:$NE$150=J$3)*(GMW!$ND$2:$ND$150=J$4)*(GMW!$NF$2:$NF$150=J$1),0),$C53-1966)} -> 52636 | K53: {=INDEX(GMW!$A$2:$NF$150,MATCH(1,(GMW!$NE$2:$NE$150=K$3)*(GMW!$ND$2:$ND$150=K$4)*(GMW!$NF$2:$NF$150=K$1),0),$C53-1966)} -> 19655.34 | ... AV53: {=INDEX(GMW!$A$2:$NF$150,MATCH(1,(GMW!$NE$2:$NE$150=AV$3)*(GMW!$ND$2:$ND$150=AV$4)*(GMW!$NF$2:$NF$150=AV$1),0),$C53-1966)} -> -1.860852
B54: =+B50+1 -> 1984 | C54: =+C53+1 -> 2020 | D54: {=INDEX(GMW!$A$2:$NF$150,MATCH(1,(GMW!$NE$2:$NE$150=D$3)*(GMW!$ND$2:$ND$150=D$4)*(GMW!$NF$2:$NF$150=D$1),0),$C54-1966)} -> 289829 | E54: {=INDEX(GMW!$A$2:$NF$150,MATCH(1,(GMW!$NE$2:$NE$150=E$3)*(GMW!$ND$2:$ND$150=E$4)*(GMW!$NF$2:$NF$150=E$1),0),$C54-1966)} -> 43.43106 | F54: {=INDEX(GMW!$A$2:$NF$150,MATCH(1,(GMW!$NE$2:$NE$150=F$3)*(GMW!$ND$2:$ND$150=F$4)*(GMW!$NF$2:$NF$150=F$1),0),$C54-1966)} -> 52470 | G54: {=INDEX(GMW!$A$2:$NF$150,MATCH(1,(GMW!$NE$2:$NE$150=G$3)*(GMW!$ND$2:$ND$150=G$4)*(GMW!$NF$2:$NF$150=G$1),0),$C54-1966)} -> 15603.78 | H54: {=INDEX(GMW!$A$2:$NF$150,MATCH(1,(GMW!$NE$2:$NE$150=H$3)*(GMW!$ND$2:$ND$150=H$4)*(GMW!$NF$2:$NF$150=H$1),0),$C54-1966)} -> 47773 | I54: {=INDEX(GMW!$A$2:$NF$150,MATCH(1,(GMW!$NE$2:$NE$150=I$3)*(GMW!$ND$2:$ND$150=I$4)*(GMW!$NF$2:$NF$150=I$1),0),$C54-1966)} -> 19128.2 | J54: {=INDEX(GMW!$A$2:$NF$150,MATCH(1,(GMW!$NE$2:$NE$150=J$3)*(GMW!$ND$2:$ND$150=J$4)*(GMW!$NF$2:$NF$150=J$1),0),$C54-1966)} -> 53026 | K54: {=INDEX(GMW!$A$2:$NF$150,MATCH(1,(GMW!$NE$2:$NE$150=K$3)*(GMW!$ND$2:$ND$150=K$4)*(GMW!$NF$2:$NF$150=K$1),0),$C54-1966)} -> 20369.73 | ... AV54: {=INDEX(GMW!$A$2:$NF$150,MATCH(1,(GMW!$NE$2:$NE$150=AV$3)*(GMW!$ND$2:$ND$150=AV$4)*(GMW!$NF$2:$NF$150=AV$1),0),$C54-1966)} -> -1.857838
A55: 1985 | B55: =+B51+1 -> 1985 | C55: =+C54+1 -> 2021 | D55: {=INDEX(GMW!$A$2:$NF$150,MATCH(1,(GMW!$NE$2:$NE$150=D$3)*(GMW!$ND$2:$ND$150=D$4)*(GMW!$NF$2:$NF$150=D$1),0),$C55-1966)} -> 292612 | E55: {=INDEX(GMW!$A$2:$NF$150,MATCH(1,(GMW!$NE$2:$NE$150=E$3)*(GMW!$ND$2:$ND$150=E$4)*(GMW!$NF$2:$NF$150=E$1),0),$C55-1966)} -> 43.87423 | F55: {=INDEX(GMW!$A$2:$NF$150,MATCH(1,(GMW!$NE$2:$NE$150=F$3)*(GMW!$ND$2:$ND$150=F$4)*(GMW!$NF$2:$NF$150=F$1),0),$C55-1966)} -> 52943 | G55: {=INDEX(GMW!$A$2:$NF$150,MATCH(1,(GMW!$NE$2:$NE$150=G$3)*(GMW!$ND$2:$ND$150=G$4)*(GMW!$NF$2:$NF$150=G$1),0),$C55-1966)} -> 14844.18 | H55: {=INDEX(GMW!$A$2:$NF$150,MATCH(1,(GMW!$NE$2:$NE$150=H$3)*(GMW!$ND$2:$ND$150=H$4)*(GMW!$NF$2:$NF$150=H$1),0),$C55-1966)} -> 47820 | I55: {=INDEX(GMW!$A$2:$NF$150,MATCH(1,(GMW!$NE$2:$NE$150=I$3)*(GMW!$ND$2:$ND$150=I$4)*(GMW!$NF$2:$NF$150=I$1),0),$C55-1966)} -> 19211.25 | J55: {=INDEX(GMW!$A$2:$NF$150,MATCH(1,(GMW!$NE$2:$NE$150=J$3)*(GMW!$ND$2:$ND$150=J$4)*(GMW!$NF$2:$NF$150=J$1),0),$C55-1966)} -> 57010 | K55: {=INDEX(GMW!$A$2:$NF$150,MATCH(1,(GMW!$NE$2:$NE$150=K$3)*(GMW!$ND$2:$ND$150=K$4)*(GMW!$NF$2:$NF$150=K$1),0),$C55-1966)} -> 22601.39 | ... AV55: {=INDEX(GMW!$A$2:$NF$150,MATCH(1,(GMW!$NE$2:$NE$150=AV$3)*(GMW!$ND$2:$ND$150=AV$4)*(GMW!$NF$2:$NF$150=AV$1),0),$C55-1966)} -> -1.854828
B56: =+B52+1 -> 1985 | C56: =+C55+1 -> 2022 | D56: {=INDEX(GMW!$A$2:$NF$150,MATCH(1,(GMW!$NE$2:$NE$150=D$3)*(GMW!$ND$2:$ND$150=D$4)*(GMW!$NF$2:$NF$150=D$1),0),$C56-1966)} -> 298873 | E56: {=INDEX(GMW!$A$2:$NF$150,MATCH(1,(GMW!$NE$2:$NE$150=E$3)*(GMW!$ND$2:$ND$150=E$4)*(GMW!$NF$2:$NF$150=E$1),0),$C56-1966)} -> 44.9952 | F56: {=INDEX(GMW!$A$2:$NF$150,MATCH(1,(GMW!$NE$2:$NE$150=F$3)*(GMW!$ND$2:$ND$150=F$4)*(GMW!$NF$2:$NF$150=F$1),0),$C56-1966)} -> 54969 | G56: {=INDEX(GMW!$A$2:$NF$150,MATCH(1,(GMW!$NE$2:$NE$150=G$3)*(GMW!$ND$2:$ND$150=G$4)*(GMW!$NF$2:$NF$150=G$1),0),$C56-1966)} -> 15294.36 | H56: {=INDEX(GMW!$A$2:$NF$150,MATCH(1,(GMW!$NE$2:$NE$150=H$3)*(GMW!$ND$2:$ND$150=H$4)*(GMW!$NF$2:$NF$150=H$1),0),$C56-1966)} -> 46572 | I56: {=INDEX(GMW!$A$2:$NF$150,MATCH(1,(GMW!$NE$2:$NE$150=I$3)*(GMW!$ND$2:$ND$150=I$4)*(GMW!$NF$2:$NF$150=I$1),0),$C56-1966)} -> 21573.72 | J56: {=INDEX(GMW!$A$2:$NF$150,MATCH(1,(GMW!$NE$2:$NE$150=J$3)*(GMW!$ND$2:$ND$150=J$4)*(GMW!$NF$2:$NF$150=J$1),0),$C56-1966)} -> 52362 | K56: {=INDEX(GMW!$A$2:$NF$150,MATCH(1,(GMW!$NE$2:$NE$150=K$3)*(GMW!$ND$2:$ND$150=K$4)*(GMW!$NF$2:$NF$150=K$1),0),$C56-1966)} -> 20033.46 | ... AV56: {=INDEX(GMW!$A$2:$NF$150,MATCH(1,(GMW!$NE$2:$NE$150=AV$3)*(GMW!$ND$2:$ND$150=AV$4)*(GMW!$NF$2:$NF$150=AV$1),0),$C56-1966)} -> -1.851824
B57: =+B53+1 -> 1985 | C57: =+C56+1 -> 2023 | D57: {=INDEX(GMW!$A$2:$NF$150,MATCH(1,(GMW!$NE$2:$NE$150=D$3)*(GMW!$ND$2:$ND$150=D$4)*(GMW!$NF$2:$NF$150=D$1),0),$C57-1966)} -> 298814 | E57: {=INDEX(GMW!$A$2:$NF$150,MATCH(1,(GMW!$NE$2:$NE$150=E$3)*(GMW!$ND$2:$ND$150=E$4)*(GMW!$NF$2:$NF$150=E$1),0),$C57-1966)} -> 45.12555 | F57: {=INDEX(GMW!$A$2:$NF$150,MATCH(1,(GMW!$NE$2:$NE$150=F$3)*(GMW!$ND$2:$ND$150=F$4)*(GMW!$NF$2:$NF$150=F$1),0),$C57-1966)} -> 53412 | G57: {=INDEX(GMW!$A$2:$NF$150,MATCH(1,(GMW!$NE$2:$NE$150=G$3)*(GMW!$ND$2:$ND$150=G$4)*(GMW!$NF$2:$NF$150=G$1),0),$C57-1966)} -> 15276.48 | H57: {=INDEX(GMW!$A$2:$NF$150,MATCH(1,(GMW!$NE$2:$NE$150=H$3)*(GMW!$ND$2:$ND$150=H$4)*(GMW!$NF$2:$NF$150=H$1),0),$C57-1966)} -> 45666 | I57: {=INDEX(GMW!$A$2:$NF$150,MATCH(1,(GMW!$NE$2:$NE$150=I$3)*(GMW!$ND$2:$ND$150=I$4)*(GMW!$NF$2:$NF$150=I$1),0),$C57-1966)} -> 21823.57 | J57: {=INDEX(GMW!$A$2:$NF$150,MATCH(1,(GMW!$NE$2:$NE$150=J$3)*(GMW!$ND$2:$ND$150=J$4)*(GMW!$NF$2:$NF$150=J$1),0),$C57-1966)} -> 52813 | K57: {=INDEX(GMW!$A$2:$NF$150,MATCH(1,(GMW!$NE$2:$NE$150=K$3)*(GMW!$ND$2:$ND$150=K$4)*(GMW!$NF$2:$NF$150=K$1),0),$C57-1966)} -> 20541.89 | ... AV57: {=INDEX(GMW!$A$2:$NF$150,MATCH(1,(GMW!$NE$2:$NE$150=AV$3)*(GMW!$ND$2:$ND$150=AV$4)*(GMW!$NF$2:$NF$150=AV$1),0),$C57-1966)} -> -1.848824
B58: =+B54+1 -> 1985 | C58: =+C57+1 -> 2024 | D58: {=INDEX(GMW!$A$2:$NF$150,MATCH(1,(GMW!$NE$2:$NE$150=D$3)*(GMW!$ND$2:$ND$150=D$4)*(GMW!$NF$2:$NF$150=D$1),0),$C58-1966)} -> 298979 | E58: {=INDEX(GMW!$A$2:$NF$150,MATCH(1,(GMW!$NE$2:$NE$150=E$3)*(GMW!$ND$2:$ND$150=E$4)*(GMW!$NF$2:$NF$150=E$1),0),$C58-1966)} -> 45.49052 | F58: {=INDEX(GMW!$A$2:$NF$150,MATCH(1,(GMW!$NE$2:$NE$150=F$3)*(GMW!$ND$2:$ND$150=F$4)*(GMW!$NF$2:$NF$150=F$1),0),$C58-1966)} -> 53746 | G58: {=INDEX(GMW!$A$2:$NF$150,MATCH(1,(GMW!$NE$2:$NE$150=G$3)*(GMW!$ND$2:$ND$150=G$4)*(GMW!$NF$2:$NF$150=G$1),0),$C58-1966)} -> 14510.18 | H58: {=INDEX(GMW!$A$2:$NF$150,MATCH(1,(GMW!$NE$2:$NE$150=H$3)*(GMW!$ND$2:$ND$150=H$4)*(GMW!$NF$2:$NF$150=H$1),0),$C58-1966)} -> 47146 | I58: {=INDEX(GMW!$A$2:$NF$150,MATCH(1,(GMW!$NE$2:$NE$150=I$3)*(GMW!$ND$2:$ND$150=I$4)*(GMW!$NF$2:$NF$150=I$1),0),$C58-1966)} -> 21130.7 | J58: {=INDEX(GMW!$A$2:$NF$150,MATCH(1,(GMW!$NE$2:$NE$150=J$3)*(GMW!$ND$2:$ND$150=J$4)*(GMW!$NF$2:$NF$150=J$1),0),$C58-1966)} -> 52603 | K58: {=INDEX(GMW!$A$2:$NF$150,MATCH(1,(GMW!$NE$2:$NE$150=K$3)*(GMW!$ND$2:$ND$150=K$4)*(GMW!$NF$2:$NF$150=K$1),0),$C58-1966)} -> 20672.22 | ... AV58: {=INDEX(GMW!$A$2:$NF$150,MATCH(1,(GMW!$NE$2:$NE$150=AV$3)*(GMW!$ND$2:$ND$150=AV$4)*(GMW!$NF$2:$NF$150=AV$1),0),$C58-1966)} -> -1.845829
A59: 1986 | B59: =+B55+1 -> 1986 | C59: =+C58+1 -> 2025 | D59: {=INDEX(GMW!$A$2:$NF$150,MATCH(1,(GMW!$NE$2:$NE$150=D$3)*(GMW!$ND$2:$ND$150=D$4)*(GMW!$NF$2:$NF$150=D$1),0),$C59-1966)} -> 302117 | E59: {=INDEX(GMW!$A$2:$NF$150,MATCH(1,(GMW!$NE$2:$NE$150=E$3)*(GMW!$ND$2:$ND$150=E$4)*(GMW!$NF$2:$NF$150=E$1),0),$C59-1966)} -> 45.64693 | F59: {=INDEX(GMW!$A$2:$NF$150,MATCH(1,(GMW!$NE$2:$NE$150=F$3)*(GMW!$ND$2:$ND$150=F$4)*(GMW!$NF$2:$NF$150=F$1),0),$C59-1966)} -> 54907 | G59: {=INDEX(GMW!$A$2:$NF$150,MATCH(1,(GMW!$NE$2:$NE$150=G$3)*(GMW!$ND$2:$ND$150=G$4)*(GMW!$NF$2:$NF$150=G$1),0),$C59-1966)} -> 14486.36 | H59: {=INDEX(GMW!$A$2:$NF$150,MATCH(1,(GMW!$NE$2:$NE$150=H$3)*(GMW!$ND$2:$ND$150=H$4)*(GMW!$NF$2:$NF$150=H$1),0),$C59-1966)} -> 48298 | I59: {=INDEX(GMW!$A$2:$NF$150,MATCH(1,(GMW!$NE$2:$NE$150=I$3)*(GMW!$ND$2:$ND$150=I$4)*(GMW!$NF$2:$NF$150=I$1),0),$C59-1966)} -> 22871.68 | J59: {=INDEX(GMW!$A$2:$NF$150,MATCH(1,(GMW!$NE$2:$NE$150=J$3)*(GMW!$ND$2:$ND$150=J$4)*(GMW!$NF$2:$NF$150=J$1),0),$C59-1966)} -> 52036 | K59: {=INDEX(GMW!$A$2:$NF$150,MATCH(1,(GMW!$NE$2:$NE$150=K$3)*(GMW!$ND$2:$ND$150=K$4)*(GMW!$NF$2:$NF$150=K$1),0),$C59-1966)} -> 20701.18 | ... AV59: {=INDEX(GMW!$A$2:$NF$150,MATCH(1,(GMW!$NE$2:$NE$150=AV$3)*(GMW!$ND$2:$ND$150=AV$4)*(GMW!$NF$2:$NF$150=AV$1),0),$C59-1966)} -> -1.842839
B60: =+B56+1 -> 1986 | C60: =+C59+1 -> 2026 | D60: {=INDEX(GMW!$A$2:$NF$150,MATCH(1,(GMW!$NE$2:$NE$150=D$3)*(GMW!$ND$2:$ND$150=D$4)*(GMW!$NF$2:$NF$150=D$1),0),$C60-1966)} -> 304797 | E60: {=INDEX(GMW!$A$2:$NF$150,MATCH(1,(GMW!$NE$2:$NE$150=E$3)*(GMW!$ND$2:$ND$150=E$4)*(GMW!$NF$2:$NF$150=E$1),0),$C60-1966)} -> 46.3508 | F60: {=INDEX(GMW!$A$2:$NF$150,MATCH(1,(GMW!$NE$2:$NE$150=F$3)*(GMW!$ND$2:$ND$150=F$4)*(GMW!$NF$2:$NF$150=F$1),0),$C60-1966)} -> 55692 | G60: {=INDEX(GMW!$A$2:$NF$150,MATCH(1,(GMW!$NE$2:$NE$150=G$3)*(GMW!$ND$2:$ND$150=G$4)*(GMW!$NF$2:$NF$150=G$1),0),$C60-1966)} -> 15815.12 | H60: {=INDEX(GMW!$A$2:$NF$150,MATCH(1,(GMW!$NE$2:$NE$150=H$3)*(GMW!$ND$2:$ND$150=H$4)*(GMW!$NF$2:$NF$150=H$1),0),$C60-1966)} -> 49988 | I60: {=INDEX(GMW!$A$2:$NF$150,MATCH(1,(GMW!$NE$2:$NE$150=I$3)*(GMW!$ND$2:$ND$150=I$4)*(GMW!$NF$2:$NF$150=I$1),0),$C60-1966)} -> 22973.88 | J60: {=INDEX(GMW!$A$2:$NF$150,MATCH(1,(GMW!$NE$2:$NE$150=J$3)*(GMW!$ND$2:$ND$150=J$4)*(GMW!$NF$2:$NF$150=J$1),0),$C60-1966)} -> 50598 | K60: {=INDEX(GMW!$A$2:$NF$150,MATCH(1,(GMW!$NE$2:$NE$150=K$3)*(GMW!$ND$2:$ND$150=K$4)*(GMW!$NF$2:$NF$150=K$1),0),$C60-1966)} -> 19684.31 | ... AV60: {=INDEX(GMW!$A$2:$NF$150,MATCH(1,(GMW!$NE$2:$NE$150=AV$3)*(GMW!$ND$2:$ND$150=AV$4)*(GMW!$NF$2:$NF$150=AV$1),0),$C60-1966)} -> -1.839853
B61: =+B57+1 -> 1986 | C61: =+C60+1 -> 2027 | D61: {=INDEX(GMW!$A$2:$NF$150,MATCH(1,(GMW!$NE$2:$NE$150=D$3)*(GMW!$ND$2:$ND$150=D$4)*(GMW!$NF$2:$NF$150=D$1),0),$C61-1966)} -> 306708 | E61: {=INDEX(GMW!$A$2:$NF$150,MATCH(1,(GMW!$NE$2:$NE$150=E$3)*(GMW!$ND$2:$ND$150=E$4)*(GMW!$NF$2:$NF$150=E$1),0),$C61-1966)} -> 46.53328 | F61: {=INDEX(GMW!$A$2:$NF$150,MATCH(1,(GMW!$NE$2:$NE$150=F$3)*(GMW!$ND$2:$ND$150=F$4)*(GMW!$NF$2:$NF$150=F$1),0),$C61-1966)} -> 55751 | G61: {=INDEX(GMW!$A$2:$NF$150,MATCH(1,(GMW!$NE$2:$NE$150=G$3)*(GMW!$ND$2:$ND$150=G$4)*(GMW!$NF$2:$NF$150=G$1),0),$C61-1966)} -> 15054.83 | H61: {=INDEX(GMW!$A$2:$NF$150,MATCH(1,(GMW!$NE$2:$NE$150=H$3)*(GMW!$ND$2:$ND$150=H$4)*(GMW!$NF$2:$NF$150=H$1),0),$C61-1966)} -> 50344 | I61: {=INDEX(GMW!$A$2:$NF$150,MATCH(1,(GMW!$NE$2:$NE$150=I$3)*(GMW!$ND$2:$ND$150=I$4)*(GMW!$NF$2:$NF$150=I$1),0),$C61-1966)} -> 21676.2 | J61: {=INDEX(GMW!$A$2:$NF$150,MATCH(1,(GMW!$NE$2:$NE$150=J$3)*(GMW!$ND$2:$ND$150=J$4)*(GMW!$NF$2:$NF$150=J$1),0),$C61-1966)} -> 53431 | K61: {=INDEX(GMW!$A$2:$NF$150,MATCH(1,(GMW!$NE$2:$NE$150=K$3)*(GMW!$ND$2:$ND$150=K$4)*(GMW!$NF$2:$NF$150=K$1),0),$C61-1966)} -> 20858.86 | ... AV61: {=INDEX(GMW!$A$2:$NF$150,MATCH(1,(GMW!$NE$2:$NE$150=AV$3)*(GMW!$ND$2:$ND$150=AV$4)*(GMW!$NF$2:$NF$150=AV$1),0),$C61-1966)} -> -1.837037
B62: =+B58+1 -> 1986 | C62: =+C61+1 -> 2028 | D62: {=INDEX(GMW!$A$2:$NF$150,MATCH(1,(GMW!$NE$2:$NE$150=D$3)*(GMW!$ND$2:$ND$150=D$4)*(GMW!$NF$2:$NF$150=D$1),0),$C62-1966)} -> 312615 | E62: {=INDEX(GMW!$A$2:$NF$150,MATCH(1,(GMW!$NE$2:$NE$150=E$3)*(GMW!$ND$2:$ND$150=E$4)*(GMW!$NF$2:$NF$150=E$1),0),$C62-1966)} -> 46.92432 | F62: {=INDEX(GMW!$A$2:$NF$150,MATCH(1,(GMW!$NE$2:$NE$150=F$3)*(GMW!$ND$2:$ND$150=F$4)*(GMW!$NF$2:$NF$150=F$1),0),$C62-1966)} -> 57267 | G62: {=INDEX(GMW!$A$2:$NF$150,MATCH(1,(GMW!$NE$2:$NE$150=G$3)*(GMW!$ND$2:$ND$150=G$4)*(GMW!$NF$2:$NF$150=G$1),0),$C62-1966)} -> 16708.36 | H62: {=INDEX(GMW!$A$2:$NF$150,MATCH(1,(GMW!$NE$2:$NE$150=H$3)*(GMW!$ND$2:$ND$150=H$4)*(GMW!$NF$2:$NF$150=H$1),0),$C62-1966)} -> 51050 | I62: {=INDEX(GMW!$A$2:$NF$150,MATCH(1,(GMW!$NE$2:$NE$150=I$3)*(GMW!$ND$2:$ND$150=I$4)*(GMW!$NF$2:$NF$150=I$1),0),$C62-1966)} -> 22789.1 | J62: {=INDEX(GMW!$A$2:$NF$150,MATCH(1,(GMW!$NE$2:$NE$150=J$3)*(GMW!$ND$2:$ND$150=J$4)*(GMW!$NF$2:$NF$150=J$1),0),$C62-1966)} -> 56019 | K62: {=INDEX(GMW!$A$2:$NF$150,MATCH(1,(GMW!$NE$2:$NE$150=K$3)*(GMW!$ND$2:$ND$150=K$4)*(GMW!$NF$2:$NF$150=K$1),0),$C62-1966)} -> 21504.07 | ... AV62: {=INDEX(GMW!$A$2:$NF$150,MATCH(1,(GMW!$NE$2:$NE$150=AV$3)*(GMW!$ND$2:$ND$150=AV$4)*(GMW!$NF$2:$NF$150=AV$1),0),$C62-1966)} -> -1.834224
A63: 1987 | B63: =+B59+1 -> 1987 | C63: =+C62+1 -> 2029 | D63: {=INDEX(GMW!$A$2:$NF$150,MATCH(1,(GMW!$NE$2:$NE$150=D$3)*(GMW!$ND$2:$ND$150=D$4)*(GMW!$NF$2:$NF$150=D$1),0),$C63-1966)} -> 314804 | E63: {=INDEX(GMW!$A$2:$NF$150,MATCH(1,(GMW!$NE$2:$NE$150=E$3)*(GMW!$ND$2:$ND$150=E$4)*(GMW!$NF$2:$NF$150=E$1),0),$C63-1966)} -> 47.23714 | F63: {=INDEX(GMW!$A$2:$NF$150,MATCH(1,(GMW!$NE$2:$NE$150=F$3)*(GMW!$ND$2:$ND$150=F$4)*(GMW!$NF$2:$NF$150=F$1),0),$C63-1966)} -> 58816 | G63: {=INDEX(GMW!$A$2:$NF$150,MATCH(1,(GMW!$NE$2:$NE$150=G$3)*(GMW!$ND$2:$ND$150=G$4)*(GMW!$NF$2:$NF$150=G$1),0),$C63-1966)} -> 18528.42 | H63: {=INDEX(GMW!$A$2:$NF$150,MATCH(1,(GMW!$NE$2:$NE$150=H$3)*(GMW!$ND$2:$ND$150=H$4)*(GMW!$NF$2:$NF$150=H$1),0),$C63-1966)} -> 50423 | I63: {=INDEX(GMW!$A$2:$NF$150,MATCH(1,(GMW!$NE$2:$NE$150=I$3)*(GMW!$ND$2:$ND$150=I$4)*(GMW!$NF$2:$NF$150=I$1),0),$C63-1966)} -> 23610.88 | J63: {=INDEX(GMW!$A$2:$NF$150,MATCH(1,(GMW!$NE$2:$NE$150=J$3)*(GMW!$ND$2:$ND$150=J$4)*(GMW!$NF$2:$NF$150=J$1),0),$C63-1966)} -> 54611 | K63: {=INDEX(GMW!$A$2:$NF$150,MATCH(1,(GMW!$NE$2:$NE$150=K$3)*(GMW!$ND$2:$ND$150=K$4)*(GMW!$NF$2:$NF$150=K$1),0),$C63-1966)} -> 20059.2 | ... AV63: {=INDEX(GMW!$A$2:$NF$150,MATCH(1,(GMW!$NE$2:$NE$150=AV$3)*(GMW!$ND$2:$ND$150=AV$4)*(GMW!$NF$2:$NF$150=AV$1),0),$C63-1966)} -> -1.831416
B64: =+B60+1 -> 1987 | C64: =+C63+1 -> 2030 | D64: {=INDEX(GMW!$A$2:$NF$150,MATCH(1,(GMW!$NE$2:$NE$150=D$3)*(GMW!$ND$2:$ND$150=D$4)*(GMW!$NF$2:$NF$150=D$1),0),$C64-1966)} -> 319478 | E64: {=INDEX(GMW!$A$2:$NF$150,MATCH(1,(GMW!$NE$2:$NE$150=E$3)*(GMW!$ND$2:$ND$150=E$4)*(GMW!$NF$2:$NF$150=E$1),0),$C64-1966)} -> 47.83673 | F64: {=INDEX(GMW!$A$2:$NF$150,MATCH(1,(GMW!$NE$2:$NE$150=F$3)*(GMW!$ND$2:$ND$150=F$4)*(GMW!$NF$2:$NF$150=F$1),0),$C64-1966)} -> 58324 | G64: {=INDEX(GMW!$A$2:$NF$150,MATCH(1,(GMW!$NE$2:$NE$150=G$3)*(GMW!$ND$2:$ND$150=G$4)*(GMW!$NF$2:$NF$150=G$1),0),$C64-1966)} -> 17568.18 | H64: {=INDEX(GMW!$A$2:$NF$150,MATCH(1,(GMW!$NE$2:$NE$150=H$3)*(GMW!$ND$2:$ND$150=H$4)*(GMW!$NF$2:$NF$150=H$1),0),$C64-1966)} -> 52940 | I64: {=INDEX(GMW!$A$2:$NF$150,MATCH(1,(GMW!$NE$2:$NE$150=I$3)*(GMW!$ND$2:$ND$150=I$4)*(GMW!$NF$2:$NF$150=I$1),0),$C64-1966)} -> 25227.9 | J64: {=INDEX(GMW!$A$2:$NF$150,MATCH(1,(GMW!$NE$2:$NE$150=J$3)*(GMW!$ND$2:$ND$150=J$4)*(GMW!$NF$2:$NF$150=J$1),0),$C64-1966)} -> 57244 | K64: {=INDEX(GMW!$A$2:$NF$150,MATCH(1,(GMW!$NE$2:$NE$150=K$3)*(GMW!$ND$2:$ND$150=K$4)*(GMW!$NF$2:$NF$150=K$1),0),$C64-1966)} -> 20730.15 | ... AV64: {=INDEX(GMW!$A$2:$NF$150,MATCH(1,(GMW!$NE$2:$NE$150=AV$3)*(GMW!$ND$2:$ND$150=AV$4)*(GMW!$NF$2:$NF$150=AV$1),0),$C64-1966)} -> -1.828612
B65: =+B61+1 -> 1987 | C65: =+C64+1 -> 2031 | D65: {=INDEX(GMW!$A$2:$NF$150,MATCH(1,(GMW!$NE$2:$NE$150=D$3)*(GMW!$ND$2:$ND$150=D$4)*(GMW!$NF$2:$NF$150=D$1),0),$C65-1966)} -> 327346 | E65: {=INDEX(GMW!$A$2:$NF$150,MATCH(1,(GMW!$NE$2:$NE$150=E$3)*(GMW!$ND$2:$ND$150=E$4)*(GMW!$NF$2:$NF$150=E$1),0),$C65-1966)} -> 47.88887 | F65: {=INDEX(GMW!$A$2:$NF$150,MATCH(1,(GMW!$NE$2:$NE$150=F$3)*(GMW!$ND$2:$ND$150=F$4)*(GMW!$NF$2:$NF$150=F$1),0),$C65-1966)} -> 60470 | G65: {=INDEX(GMW!$A$2:$NF$150,MATCH(1,(GMW!$NE$2:$NE$150=G$3)*(GMW!$ND$2:$ND$150=G$4)*(GMW!$NF$2:$NF$150=G$1),0),$C65-1966)} -> 18760.65 | H65: {=INDEX(GMW!$A$2:$NF$150,MATCH(1,(GMW!$NE$2:$NE$150=H$3)*(GMW!$ND$2:$ND$150=H$4)*(GMW!$NF$2:$NF$150=H$1),0),$C65-1966)} -> 55384 | I65: {=INDEX(GMW!$A$2:$NF$150,MATCH(1,(GMW!$NE$2:$NE$150=I$3)*(GMW!$ND$2:$ND$150=I$4)*(GMW!$NF$2:$NF$150=I$1),0),$C65-1966)} -> 26315 | J65: {=INDEX(GMW!$A$2:$NF$150,MATCH(1,(GMW!$NE$2:$NE$150=J$3)*(GMW!$ND$2:$ND$150=J$4)*(GMW!$NF$2:$NF$150=J$1),0),$C65-1966)} -> 62518 | K65: {=INDEX(GMW!$A$2:$NF$150,MATCH(1,(GMW!$NE$2:$NE$150=K$3)*(GMW!$ND$2:$ND$150=K$4)*(GMW!$NF$2:$NF$150=K$1),0),$C65-1966)} -> 22463.02 | ... AV65: {=INDEX(GMW!$A$2:$NF$150,MATCH(1,(GMW!$NE$2:$NE$150=AV$3)*(GMW!$ND$2:$ND$150=AV$4)*(GMW!$NF$2:$NF$150=AV$1),0),$C65-1966)} -> -1.825813
B66: =+B62+1 -> 1987 | C66: =+C65+1 -> 2032 | D66: {=INDEX(GMW!$A$2:$NF$150,MATCH(1,(GMW!$NE$2:$NE$150=D$3)*(GMW!$ND$2:$ND$150=D$4)*(GMW!$NF$2:$NF$150=D$1),0),$C66-1966)} -> 331075 | E66: {=INDEX(GMW!$A$2:$NF$150,MATCH(1,(GMW!$NE$2:$NE$150=E$3)*(GMW!$ND$2:$ND$150=E$4)*(GMW!$NF$2:$NF$150=E$1),0),$C66-1966)} -> 48.43632 | F66: {=INDEX(GMW!$A$2:$NF$150,MATCH(1,(GMW!$NE$2:$NE$150=F$3)*(GMW!$ND$2:$ND$150=F$4)*(GMW!$NF$2:$NF$150=F$1),0),$C66-1966)} -> 60226 | G66: {=INDEX(GMW!$A$2:$NF$150,MATCH(1,(GMW!$NE$2:$NE$150=G$3)*(GMW!$ND$2:$ND$150=G$4)*(GMW!$NF$2:$NF$150=G$1),0),$C66-1966)} -> 18302.36 | H66: {=INDEX(GMW!$A$2:$NF$150,MATCH(1,(GMW!$NE$2:$NE$150=H$3)*(GMW!$ND$2:$ND$150=H$4)*(GMW!$NF$2:$NF$150=H$1),0),$C66-1966)} -> 56457 | I66: {=INDEX(GMW!$A$2:$NF$150,MATCH(1,(GMW!$NE$2:$NE$150=I$3)*(GMW!$ND$2:$ND$150=I$4)*(GMW!$NF$2:$NF$150=I$1),0),$C66-1966)} -> 26475.05 | J66: {=INDEX(GMW!$A$2:$NF$150,MATCH(1,(GMW!$NE$2:$NE$150=J$3)*(GMW!$ND$2:$ND$150=J$4)*(GMW!$NF$2:$NF$150=J$1),0),$C66-1966)} -> 64025 | K66: {=INDEX(GMW!$A$2:$NF$150,MATCH(1,(GMW!$NE$2:$NE$150=K$3)*(GMW!$ND$2:$ND$150=K$4)*(GMW!$NF$2:$NF$150=K$1),0),$C66-1966)} -> 23907.89 | ... AV66: {=INDEX(GMW!$A$2:$NF$150,MATCH(1,(GMW!$NE$2:$NE$150=AV$3)*(GMW!$ND$2:$ND$150=AV$4)*(GMW!$NF$2:$NF$150=AV$1),0),$C66-1966)} -> -1.823018
A67: 1988 | B67: =+B63+1 -> 1988 | C67: =+C66+1 -> 2033 | D67: {=INDEX(GMW!$A$2:$NF$150,MATCH(1,(GMW!$NE$2:$NE$150=D$3)*(GMW!$ND$2:$ND$150=D$4)*(GMW!$NF$2:$NF$150=D$1),0),$C67-1966)} -> 336442 | E67: {=INDEX(GMW!$A$2:$NF$150,MATCH(1,(GMW!$NE$2:$NE$150=E$3)*(GMW!$ND$2:$ND$150=E$4)*(GMW!$NF$2:$NF$150=E$1),0),$C67-1966)} -> 48.56667 | F67: {=INDEX(GMW!$A$2:$NF$150,MATCH(1,(GMW!$NE$2:$NE$150=F$3)*(GMW!$ND$2:$ND$150=F$4)*(GMW!$NF$2:$NF$150=F$1),0),$C67-1966)} -> 59215 | G67: {=INDEX(GMW!$A$2:$NF$150,MATCH(1,(GMW!$NE$2:$NE$150=G$3)*(GMW!$ND$2:$ND$150=G$4)*(GMW!$NF$2:$NF$150=G$1),0),$C67-1966)} -> 18628.42 | H67: {=INDEX(GMW!$A$2:$NF$150,MATCH(1,(GMW!$NE$2:$NE$150=H$3)*(GMW!$ND$2:$ND$150=H$4)*(GMW!$NF$2:$NF$150=H$1),0),$C67-1966)} -> 57025 | I67: {=INDEX(GMW!$A$2:$NF$150,MATCH(1,(GMW!$NE$2:$NE$150=I$3)*(GMW!$ND$2:$ND$150=I$4)*(GMW!$NF$2:$NF$150=I$1),0),$C67-1966)} -> 28135.82 | J67: {=INDEX(GMW!$A$2:$NF$150,MATCH(1,(GMW!$NE$2:$NE$150=J$3)*(GMW!$ND$2:$ND$150=J$4)*(GMW!$NF$2:$NF$150=J$1),0),$C67-1966)} -> 67204 | K67: {=INDEX(GMW!$A$2:$NF$150,MATCH(1,(GMW!$NE$2:$NE$150=K$3)*(GMW!$ND$2:$ND$150=K$4)*(GMW!$NF$2:$NF$150=K$1),0),$C67-1966)} -> 24942.46 | ... AV67: {=INDEX(GMW!$A$2:$NF$150,MATCH(1,(GMW!$NE$2:$NE$150=AV$3)*(GMW!$ND$2:$ND$150=AV$4)*(GMW!$NF$2:$NF$150=AV$1),0),$C67-1966)} -> -1.820227
B68: =+B64+1 -> 1988 | C68: =+C67+1 -> 2034 | D68: {=INDEX(GMW!$A$2:$NF$150,MATCH(1,(GMW!$NE$2:$NE$150=D$3)*(GMW!$ND$2:$ND$150=D$4)*(GMW!$NF$2:$NF$150=D$1),0),$C68-1966)} -> 338186 | E68: {=INDEX(GMW!$A$2:$NF$150,MATCH(1,(GMW!$NE$2:$NE$150=E$3)*(GMW!$ND$2:$ND$150=E$4)*(GMW!$NF$2:$NF$150=E$1),0),$C68-1966)} -> 49.5 | F68: {=INDEX(GMW!$A$2:$NF$150,MATCH(1,(GMW!$NE$2:$NE$150=F$3)*(GMW!$ND$2:$ND$150=F$4)*(GMW!$NF$2:$NF$150=F$1),0),$C68-1966)} -> 60427 | G68: {=INDEX(GMW!$A$2:$NF$150,MATCH(1,(GMW!$NE$2:$NE$150=G$3)*(GMW!$ND$2:$ND$150=G$4)*(GMW!$NF$2:$NF$150=G$1),0),$C68-1966)} -> 19847.42 | H68: {=INDEX(GMW!$A$2:$NF$150,MATCH(1,(GMW!$NE$2:$NE$150=H$3)*(GMW!$ND$2:$ND$150=H$4)*(GMW!$NF$2:$NF$150=H$1),0),$C68-1966)} -> 59388 | I68: {=INDEX(GMW!$A$2:$NF$150,MATCH(1,(GMW!$NE$2:$NE$150=I$3)*(GMW!$ND$2:$ND$150=I$4)*(GMW!$NF$2:$NF$150=I$1),0),$C68-1966)} -> 30195.9 | J68: {=INDEX(GMW!$A$2:$NF$150,MATCH(1,(GMW!$NE$2:$NE$150=J$3)*(GMW!$ND$2:$ND$150=J$4)*(GMW!$NF$2:$NF$150=J$1),0),$C68-1966)} -> 68999 | K68: {=INDEX(GMW!$A$2:$NF$150,MATCH(1,(GMW!$NE$2:$NE$150=K$3)*(GMW!$ND$2:$ND$150=K$4)*(GMW!$NF$2:$NF$150=K$1),0),$C68-1966)} -> 26202.3 | ... AV68: {=INDEX(GMW!$A$2:$NF$150,MATCH(1,(GMW!$NE$2:$NE$150=AV$3)*(GMW!$ND$2:$ND$150=AV$4)*(GMW!$NF$2:$NF$150=AV$1),0),$C68-1966)} -> -1.81744
B69: =+B65+1 -> 1988 | C69: =+C68+1 -> 2035 | D69: {=INDEX(GMW!$A$2:$NF$150,MATCH(1,(GMW!$NE$2:$NE$150=D$3)*(GMW!$ND$2:$ND$150=D$4)*(GMW!$NF$2:$NF$150=D$1),0),$C69-1966)} -> 342414 | E69: {=INDEX(GMW!$A$2:$NF$150,MATCH(1,(GMW!$NE$2:$NE$150=E$3)*(GMW!$ND$2:$ND$150=E$4)*(GMW!$NF$2:$NF$150=E$1),0),$C69-1966)} -> 49.9 | F69: {=INDEX(GMW!$A$2:$NF$150,MATCH(1,(GMW!$NE$2:$NE$150=F$3)*(GMW!$ND$2:$ND$150=F$4)*(GMW!$NF$2:$NF$150=F$1),0),$C69-1966)} -> 60771 | G69: {=INDEX(GMW!$A$2:$NF$150,MATCH(1,(GMW!$NE$2:$NE$150=G$3)*(GMW!$ND$2:$ND$150=G$4)*(GMW!$NF$2:$NF$150=G$1),0),$C69-1966)} -> 21800.78 | H69: {=INDEX(GMW!$A$2:$NF$150,MATCH(1,(GMW!$NE$2:$NE$150=H$3)*(GMW!$ND$2:$ND$150=H$4)*(GMW!$NF$2:$NF$150=H$1),0),$C69-1966)} -> 60945 | I69: {=INDEX(GMW!$A$2:$NF$150,MATCH(1,(GMW!$NE$2:$NE$150=I$3)*(GMW!$ND$2:$ND$150=I$4)*(GMW!$NF$2:$NF$150=I$1),0),$C69-1966)} -> 31354.05 | J69: {=INDEX(GMW!$A$2:$NF$150,MATCH(1,(GMW!$NE$2:$NE$150=J$3)*(GMW!$ND$2:$ND$150=J$4)*(GMW!$NF$2:$NF$150=J$1),0),$C69-1966)} -> 69601 | K69: {=INDEX(GMW!$A$2:$NF$150,MATCH(1,(GMW!$NE$2:$NE$150=K$3)*(GMW!$ND$2:$ND$150=K$4)*(GMW!$NF$2:$NF$150=K$1),0),$C69-1966)} -> 27618.21 | ... AV69: {=INDEX(GMW!$A$2:$NF$150,MATCH(1,(GMW!$NE$2:$NE$150=AV$3)*(GMW!$ND$2:$ND$150=AV$4)*(GMW!$NF$2:$NF$150=AV$1),0),$C69-1966)} -> -1.814658
B70: =+B66+1 -> 1988 | C70: =+C69+1 -> 2036 | D70: {=INDEX(GMW!$A$2:$NF$150,MATCH(1,(GMW!$NE$2:$NE$150=D$3)*(GMW!$ND$2:$ND$150=D$4)*(GMW!$NF$2:$NF$150=D$1),0),$C70-1966)} -> 345162 | E70: {=INDEX(GMW!$A$2:$NF$150,MATCH(1,(GMW!$NE$2:$NE$150=E$3)*(GMW!$ND$2:$ND$150=E$4)*(GMW!$NF$2:$NF$150=E$1),0),$C70-1966)} -> 50.46667 | F70: {=INDEX(GMW!$A$2:$NF$150,MATCH(1,(GMW!$NE$2:$NE$150=F$3)*(GMW!$ND$2:$ND$150=F$4)*(GMW!$NF$2:$NF$150=F$1),0),$C70-1966)} -> 59544 | G70: {=INDEX(GMW!$A$2:$NF$150,MATCH(1,(GMW!$NE$2:$NE$150=G$3)*(GMW!$ND$2:$ND$150=G$4)*(GMW!$NF$2:$NF$150=G$1),0),$C70-1966)} -> 22991.19 | H70: {=INDEX(GMW!$A$2:$NF$150,MATCH(1,(GMW!$NE$2:$NE$150=H$3)*(GMW!$ND$2:$ND$150=H$4)*(GMW!$NF$2:$NF$150=H$1),0),$C70-1966)} -> 64442 | I70: {=INDEX(GMW!$A$2:$NF$150,MATCH(1,(GMW!$NE$2:$NE$150=I$3)*(GMW!$ND$2:$ND$150=I$4)*(GMW!$NF$2:$NF$150=I$1),0),$C70-1966)} -> 32341.2 | J70: {=INDEX(GMW!$A$2:$NF$150,MATCH(1,(GMW!$NE$2:$NE$150=J$3)*(GMW!$ND$2:$ND$150=J$4)*(GMW!$NF$2:$NF$150=J$1),0),$C70-1966)} -> 69526 | K70: {=INDEX(GMW!$A$2:$NF$150,MATCH(1,(GMW!$NE$2:$NE$150=K$3)*(GMW!$ND$2:$ND$150=K$4)*(GMW!$NF$2:$NF$150=K$1),0),$C70-1966)} -> 28400.17 | ... AV70: {=INDEX(GMW!$A$2:$NF$150,MATCH(1,(GMW!$NE$2:$NE$150=AV$3)*(GMW!$ND$2:$ND$150=AV$4)*(GMW!$NF$2:$NF$150=AV$1),0),$C70-1966)} -> -1.81188
A71: 1989 | B71: =+B67+1 -> 1989 | C71: =+C70+1 -> 2037 | D71: {=INDEX(GMW!$A$2:$NF$150,MATCH(1,(GMW!$NE$2:$NE$150=D$3)*(GMW!$ND$2:$ND$150=D$4)*(GMW!$NF$2:$NF$150=D$1),0),$C71-1966)} -> 346836 | E71: {=INDEX(GMW!$A$2:$NF$150,MATCH(1,(GMW!$NE$2:$NE$150=E$3)*(GMW!$ND$2:$ND$150=E$4)*(GMW!$NF$2:$NF$150=E$1),0),$C71-1966)} -> 51 | F71: {=INDEX(GMW!$A$2:$NF$150,MATCH(1,(GMW!$NE$2:$NE$150=F$3)*(GMW!$ND$2:$ND$150=F$4)*(GMW!$NF$2:$NF$150=F$1),0),$C71-1966)} -> 62278 | G71: {=INDEX(GMW!$A$2:$NF$150,MATCH(1,(GMW!$NE$2:$NE$150=G$3)*(GMW!$ND$2:$ND$150=G$4)*(GMW!$NF$2:$NF$150=G$1),0),$C71-1966)} -> 26502.79 | H71: {=INDEX(GMW!$A$2:$NF$150,MATCH(1,(GMW!$NE$2:$NE$150=H$3)*(GMW!$ND$2:$ND$150=H$4)*(GMW!$NF$2:$NF$150=H$1),0),$C71-1966)} -> 65266 | I71: {=INDEX(GMW!$A$2:$NF$150,MATCH(1,(GMW!$NE$2:$NE$150=I$3)*(GMW!$ND$2:$ND$150=I$4)*(GMW!$NF$2:$NF$150=I$1),0),$C71-1966)} -> 33410.1 | J71: {=INDEX(GMW!$A$2:$NF$150,MATCH(1,(GMW!$NE$2:$NE$150=J$3)*(GMW!$ND$2:$ND$150=J$4)*(GMW!$NF$2:$NF$150=J$1),0),$C71-1966)} -> 73235 | K71: {=INDEX(GMW!$A$2:$NF$150,MATCH(1,(GMW!$NE$2:$NE$150=K$3)*(GMW!$ND$2:$ND$150=K$4)*(GMW!$NF$2:$NF$150=K$1),0),$C71-1966)} -> 29542.55 | ... AV71: {=INDEX(GMW!$A$2:$NF$150,MATCH(1,(GMW!$NE$2:$NE$150=AV$3)*(GMW!$ND$2:$ND$150=AV$4)*(GMW!$NF$2:$NF$150=AV$1),0),$C71-1966)} -> -1.809106
B72: =+B68+1 -> 1989 | C72: =+C71+1 -> 2038 | D72: {=INDEX(GMW!$A$2:$NF$150,MATCH(1,(GMW!$NE$2:$NE$150=D$3)*(GMW!$ND$2:$ND$150=D$4)*(GMW!$NF$2:$NF$150=D$1),0),$C72-1966)} -> 348997 | E72: {=INDEX(GMW!$A$2:$NF$150,MATCH(1,(GMW!$NE$2:$NE$150=E$3)*(GMW!$ND$2:$ND$150=E$4)*(GMW!$NF$2:$NF$150=E$1),0),$C72-1966)} -> 52.13334 | F72: {=INDEX(GMW!$A$2:$NF$150,MATCH(1,(GMW!$NE$2:$NE$150=F$3)*(GMW!$ND$2:$ND$150=F$4)*(GMW!$NF$2:$NF$150=F$1),0),$C72-1966)} -> 61292 | G72: {=INDEX(GMW!$A$2:$NF$150,MATCH(1,(GMW!$NE$2:$NE$150=G$3)*(GMW!$ND$2:$ND$150=G$4)*(GMW!$NF$2:$NF$150=G$1),0),$C72-1966)} -> 25986.32 | H72: {=INDEX(GMW!$A$2:$NF$150,MATCH(1,(GMW!$NE$2:$NE$150=H$3)*(GMW!$ND$2:$ND$150=H$4)*(GMW!$NF$2:$NF$150=H$1),0),$C72-1966)} -> 63935 | I72: {=INDEX(GMW!$A$2:$NF$150,MATCH(1,(GMW!$NE$2:$NE$150=I$3)*(GMW!$ND$2:$ND$150=I$4)*(GMW!$NF$2:$NF$150=I$1),0),$C72-1966)} -> 32296.22 | J72: {=INDEX(GMW!$A$2:$NF$150,MATCH(1,(GMW!$NE$2:$NE$150=J$3)*(GMW!$ND$2:$ND$150=J$4)*(GMW!$NF$2:$NF$150=J$1),0),$C72-1966)} -> 71794 | K72: {=INDEX(GMW!$A$2:$NF$150,MATCH(1,(GMW!$NE$2:$NE$150=K$3)*(GMW!$ND$2:$ND$150=K$4)*(GMW!$NF$2:$NF$150=K$1),0),$C72-1966)} -> 29964.1 | ... AV72: {=INDEX(GMW!$A$2:$NF$150,MATCH(1,(GMW!$NE$2:$NE$150=AV$3)*(GMW!$ND$2:$ND$150=AV$4)*(GMW!$NF$2:$NF$150=AV$1),0),$C72-1966)} -> -1.806336
B73: =+B69+1 -> 1989 | C73: =+C72+1 -> 2039 | D73: {=INDEX(GMW!$A$2:$NF$150,MATCH(1,(GMW!$NE$2:$NE$150=D$3)*(GMW!$ND$2:$ND$150=D$4)*(GMW!$NF$2:$NF$150=D$1),0),$C73-1966)} -> 349572 | E73: {=INDEX(GMW!$A$2:$NF$150,MATCH(1,(GMW!$NE$2:$NE$150=E$3)*(GMW!$ND$2:$ND$150=E$4)*(GMW!$NF$2:$NF$150=E$1),0),$C73-1966)} -> 52.46667 | F73: {=INDEX(GMW!$A$2:$NF$150,MATCH(1,(GMW!$NE$2:$NE$150=F$3)*(GMW!$ND$2:$ND$150=F$4)*(GMW!$NF$2:$NF$150=F$1),0),$C73-1966)} -> 62836 | G73: {=INDEX(GMW!$A$2:$NF$150,MATCH(1,(GMW!$NE$2:$NE$150=G$3)*(GMW!$ND$2:$ND$150=G$4)*(GMW!$NF$2:$NF$150=G$1),0),$C73-1966)} -> 25721.19 | H73: {=INDEX(GMW!$A$2:$NF$150,MATCH(1,(GMW!$NE$2:$NE$150=H$3)*(GMW!$ND$2:$ND$150=H$4)*(GMW!$NF$2:$NF$150=H$1),0),$C73-1966)} -> 65429 | I73: {=INDEX(GMW!$A$2:$NF$150,MATCH(1,(GMW!$NE$2:$NE$150=I$3)*(GMW!$ND$2:$ND$150=I$4)*(GMW!$NF$2:$NF$150=I$1),0),$C73-1966)} -> 34148.13 | J73: {=INDEX(GMW!$A$2:$NF$150,MATCH(1,(GMW!$NE$2:$NE$150=J$3)*(GMW!$ND$2:$ND$150=J$4)*(GMW!$NF$2:$NF$150=J$1),0),$C73-1966)} -> 72584 | K73: {=INDEX(GMW!$A$2:$NF$150,MATCH(1,(GMW!$NE$2:$NE$150=K$3)*(GMW!$ND$2:$ND$150=K$4)*(GMW!$NF$2:$NF$150=K$1),0),$C73-1966)} -> 30734.81 | ... AV73: {=INDEX(GMW!$A$2:$NF$150,MATCH(1,(GMW!$NE$2:$NE$150=AV$3)*(GMW!$ND$2:$ND$150=AV$4)*(GMW!$NF$2:$NF$150=AV$1),0),$C73-1966)} -> -1.803571
B74: =+B70+1 -> 1989 | C74: =+C73+1 -> 2040 | D74: {=INDEX(GMW!$A$2:$NF$150,MATCH(1,(GMW!$NE$2:$NE$150=D$3)*(GMW!$ND$2:$ND$150=D$4)*(GMW!$NF$2:$NF$150=D$1),0),$C74-1966)} -> 349523 | E74: {=INDEX(GMW!$A$2:$NF$150,MATCH(1,(GMW!$NE$2:$NE$150=E$3)*(GMW!$ND$2:$ND$150=E$4)*(GMW!$NF$2:$NF$150=E$1),0),$C74-1966)} -> 53.26667 | F74: {=INDEX(GMW!$A$2:$NF$150,MATCH(1,(GMW!$NE$2:$NE$150=F$3)*(GMW!$ND$2:$ND$150=F$4)*(GMW!$NF$2:$NF$150=F$1),0),$C74-1966)} -> 64551 | G74: {=INDEX(GMW!$A$2:$NF$150,MATCH(1,(GMW!$NE$2:$NE$150=G$3)*(GMW!$ND$2:$ND$150=G$4)*(GMW!$NF$2:$NF$150=G$1),0),$C74-1966)} -> 26584.37 | H74: {=INDEX(GMW!$A$2:$NF$150,MATCH(1,(GMW!$NE$2:$NE$150=H$3)*(GMW!$ND$2:$ND$150=H$4)*(GMW!$NF$2:$NF$150=H$1),0),$C74-1966)} -> 64379 | I74: {=INDEX(GMW!$A$2:$NF$150,MATCH(1,(GMW!$NE$2:$NE$150=I$3)*(GMW!$ND$2:$ND$150=I$4)*(GMW!$NF$2:$NF$150=I$1),0),$C74-1966)} -> 32768.23 | J74: {=INDEX(GMW!$A$2:$NF$150,MATCH(1,(GMW!$NE$2:$NE$150=J$3)*(GMW!$ND$2:$ND$150=J$4)*(GMW!$NF$2:$NF$150=J$1),0),$C74-1966)} -> 71156 | K74: {=INDEX(GMW!$A$2:$NF$150,MATCH(1,(GMW!$NE$2:$NE$150=K$3)*(GMW!$ND$2:$ND$150=K$4)*(GMW!$NF$2:$NF$150=K$1),0),$C74-1966)} -> 29954.45 | ... AV74: {=INDEX(GMW!$A$2:$NF$150,MATCH(1,(GMW!$NE$2:$NE$150=AV$3)*(GMW!$ND$2:$ND$150=AV$4)*(GMW!$NF$2:$NF$150=AV$1),0),$C74-1966)} -> -1.80081
A75: 1990 | B75: =+B71+1 -> 1990 | C75: =+C74+1 -> 2041 | D75: {=INDEX(GMW!$A$2:$NF$150,MATCH(1,(GMW!$NE$2:$NE$150=D$3)*(GMW!$ND$2:$ND$150=D$4)*(GMW!$NF$2:$NF$150=D$1),0),$C75-1966)} -> 351299 | E75: {=INDEX(GMW!$A$2:$NF$150,MATCH(1,(GMW!$NE$2:$NE$150=E$3)*(GMW!$ND$2:$ND$150=E$4)*(GMW!$NF$2:$NF$150=E$1),0),$C75-1966)} -> 53.93333 | F75: {=INDEX(GMW!$A$2:$NF$150,MATCH(1,(GMW!$NE$2:$NE$150=F$3)*(GMW!$ND$2:$ND$150=F$4)*(GMW!$NF$2:$NF$150=F$1),0),$C75-1966)} -> 65996 | G75: {=INDEX(GMW!$A$2:$NF$150,MATCH(1,(GMW!$NE$2:$NE$150=G$3)*(GMW!$ND$2:$ND$150=G$4)*(GMW!$NF$2:$NF$150=G$1),0),$C75-1966)} -> 26486.07 | H75: {=INDEX(GMW!$A$2:$NF$150,MATCH(1,(GMW!$NE$2:$NE$150=H$3)*(GMW!$ND$2:$ND$150=H$4)*(GMW!$NF$2:$NF$150=H$1),0),$C75-1966)} -> 65982 | I75: {=INDEX(GMW!$A$2:$NF$150,MATCH(1,(GMW!$NE$2:$NE$150=I$3)*(GMW!$ND$2:$ND$150=I$4)*(GMW!$NF$2:$NF$150=I$1),0),$C75-1966)} -> 32999.38 | J75: {=INDEX(GMW!$A$2:$NF$150,MATCH(1,(GMW!$NE$2:$NE$150=J$3)*(GMW!$ND$2:$ND$150=J$4)*(GMW!$NF$2:$NF$150=J$1),0),$C75-1966)} -> 71617 | K75: {=INDEX(GMW!$A$2:$NF$150,MATCH(1,(GMW!$NE$2:$NE$150=K$3)*(GMW!$ND$2:$ND$150=K$4)*(GMW!$NF$2:$NF$150=K$1),0),$C75-1966)} -> 30036.51 | ... AV75: {=INDEX(GMW!$A$2:$NF$150,MATCH(1,(GMW!$NE$2:$NE$150=AV$3)*(GMW!$ND$2:$ND$150=AV$4)*(GMW!$NF$2:$NF$150=AV$1),0),$C75-1966)} -> -1.798053
B76: =+B72+1 -> 1990 | C76: =+C75+1 -> 2042 | D76: {=INDEX(GMW!$A$2:$NF$150,MATCH(1,(GMW!$NE$2:$NE$150=D$3)*(GMW!$ND$2:$ND$150=D$4)*(GMW!$NF$2:$NF$150=D$1),0),$C76-1966)} -> 353663 | E76: {=INDEX(GMW!$A$2:$NF$150,MATCH(1,(GMW!$NE$2:$NE$150=E$3)*(GMW!$ND$2:$ND$150=E$4)*(GMW!$NF$2:$NF$150=E$1),0),$C76-1966)} -> 55.6 | F76: {=INDEX(GMW!$A$2:$NF$150,MATCH(1,(GMW!$NE$2:$NE$150=F$3)*(GMW!$ND$2:$ND$150=F$4)*(GMW!$NF$2:$NF$150=F$1),0),$C76-1966)} -> 65850 | G76: {=INDEX(GMW!$A$2:$NF$150,MATCH(1,(GMW!$NE$2:$NE$150=G$3)*(GMW!$ND$2:$ND$150=G$4)*(GMW!$NF$2:$NF$150=G$1),0),$C76-1966)} -> 27016.07 | H76: {=INDEX(GMW!$A$2:$NF$150,MATCH(1,(GMW!$NE$2:$NE$150=H$3)*(GMW!$ND$2:$ND$150=H$4)*(GMW!$NF$2:$NF$150=H$1),0),$C76-1966)} -> 65805 | I76: {=INDEX(GMW!$A$2:$NF$150,MATCH(1,(GMW!$NE$2:$NE$150=I$3)*(GMW!$ND$2:$ND$150=I$4)*(GMW!$NF$2:$NF$150=I$1),0),$C76-1966)} -> 32710.38 | J76: {=INDEX(GMW!$A$2:$NF$150,MATCH(1,(GMW!$NE$2:$NE$150=J$3)*(GMW!$ND$2:$ND$150=J$4)*(GMW!$NF$2:$NF$150=J$1),0),$C76-1966)} -> 70596 | K76: {=INDEX(GMW!$A$2:$NF$150,MATCH(1,(GMW!$NE$2:$NE$150=K$3)*(GMW!$ND$2:$ND$150=K$4)*(GMW!$NF$2:$NF$150=K$1),0),$C76-1966)} -> 30549.77 | ... AV76: {=INDEX(GMW!$A$2:$NF$150,MATCH(1,(GMW!$NE$2:$NE$150=AV$3)*(GMW!$ND$2:$ND$150=AV$4)*(GMW!$NF$2:$NF$150=AV$1),0),$C76-1966)} -> -1.7953
B77: =+B73+1 -> 1990 | C77: =+C76+1 -> 2043 | D77: {=INDEX(GMW!$A$2:$NF$150,MATCH(1,(GMW!$NE$2:$NE$150=D$3)*(GMW!$ND$2:$ND$150=D$4)*(GMW!$NF$2:$NF$150=D$1),0),$C77-1966)} -> 349780 | E77: {=INDEX(GMW!$A$2:$NF$150,MATCH(1,(GMW!$NE$2:$NE$150=E$3)*(GMW!$ND$2:$ND$150=E$4)*(GMW!$NF$2:$NF$150=E$1),0),$C77-1966)} -> 56.4 | F77: {=INDEX(GMW!$A$2:$NF$150,MATCH(1,(GMW!$NE$2:$NE$150=F$3)*(GMW!$ND$2:$ND$150=F$4)*(GMW!$NF$2:$NF$150=F$1),0),$C77-1966)} -> 65770 | G77: {=INDEX(GMW!$A$2:$NF$150,MATCH(1,(GMW!$NE$2:$NE$150=G$3)*(GMW!$ND$2:$ND$150=G$4)*(GMW!$NF$2:$NF$150=G$1),0),$C77-1966)} -> 28534.96 | H77: {=INDEX(GMW!$A$2:$NF$150,MATCH(1,(GMW!$NE$2:$NE$150=H$3)*(GMW!$ND$2:$ND$150=H$4)*(GMW!$NF$2:$NF$150=H$1),0),$C77-1966)} -> 64692 | I77: {=INDEX(GMW!$A$2:$NF$150,MATCH(1,(GMW!$NE$2:$NE$150=I$3)*(GMW!$ND$2:$ND$150=I$4)*(GMW!$NF$2:$NF$150=I$1),0),$C77-1966)} -> 31575.32 | J77: {=INDEX(GMW!$A$2:$NF$150,MATCH(1,(GMW!$NE$2:$NE$150=J$3)*(GMW!$ND$2:$ND$150=J$4)*(GMW!$NF$2:$NF$150=J$1),0),$C77-1966)} -> 69949 | K77: {=INDEX(GMW!$A$2:$NF$150,MATCH(1,(GMW!$NE$2:$NE$150=K$3)*(GMW!$ND$2:$ND$150=K$4)*(GMW!$NF$2:$NF$150=K$1),0),$C77-1966)} -> 29954.45 | ... AV77: {=INDEX(GMW!$A$2:$NF$150,MATCH(1,(GMW!$NE$2:$NE$150=AV$3)*(GMW!$ND$2:$ND$150=AV$4)*(GMW!$NF$2:$NF$150=AV$1),0),$C77-1966)} -> -1.792552
B78: =+B74+1 -> 1990 | C78: =+C77+1 -> 2044 | D78: {=INDEX(GMW!$A$2:$NF$150,MATCH(1,(GMW!$NE$2:$NE$150=D$3)*(GMW!$ND$2:$ND$150=D$4)*(GMW!$NF$2:$NF$150=D$1),0),$C78-1966)} -> 348006 | E78: {=INDEX(GMW!$A$2:$NF$150,MATCH(1,(GMW!$NE$2:$NE$150=E$3)*(GMW!$ND$2:$ND$150=E$4)*(GMW!$NF$2:$NF$150=E$1),0),$C78-1966)} -> 57.46667 | F78: {=INDEX(GMW!$A$2:$NF$150,MATCH(1,(GMW!$NE$2:$NE$150=F$3)*(GMW!$ND$2:$ND$150=F$4)*(GMW!$NF$2:$NF$150=F$1),0),$C78-1966)} -> 66306 | G78: {=INDEX(GMW!$A$2:$NF$150,MATCH(1,(GMW!$NE$2:$NE$150=G$3)*(GMW!$ND$2:$ND$150=G$4)*(GMW!$NF$2:$NF$150=G$1),0),$C78-1966)} -> 28512.19 | H78: {=INDEX(GMW!$A$2:$NF$150,MATCH(1,(GMW!$NE$2:$NE$150=H$3)*(GMW!$ND$2:$ND$150=H$4)*(GMW!$NF$2:$NF$150=H$1),0),$C78-1966)} -> 63581 | I78: {=INDEX(GMW!$A$2:$NF$150,MATCH(1,(GMW!$NE$2:$NE$150=I$3)*(GMW!$ND$2:$ND$150=I$4)*(GMW!$NF$2:$NF$150=I$1),0),$C78-1966)} -> 30069.38 | J78: {=INDEX(GMW!$A$2:$NF$150,MATCH(1,(GMW!$NE$2:$NE$150=J$3)*(GMW!$ND$2:$ND$150=J$4)*(GMW!$NF$2:$NF$150=J$1),0),$C78-1966)} -> 69172 | K78: {=INDEX(GMW!$A$2:$NF$150,MATCH(1,(GMW!$NE$2:$NE$150=K$3)*(GMW!$ND$2:$ND$150=K$4)*(GMW!$NF$2:$NF$150=K$1),0),$C78-1966)} -> 29571.51 | ... AV78: {=INDEX(GMW!$A$2:$NF$150,MATCH(1,(GMW!$NE$2:$NE$150=AV$3)*(GMW!$ND$2:$ND$150=AV$4)*(GMW!$NF$2:$NF$150=AV$1),0),$C78-1966)} -> -1.789807
A79: 1991 | B79: =+B75+1 -> 1991 | C79: =+C78+1 -> 2045 | D79: {=INDEX(GMW!$A$2:$NF$150,MATCH(1,(GMW!$NE$2:$NE$150=D$3)*(GMW!$ND$2:$ND$150=D$4)*(GMW!$NF$2:$NF$150=D$1),0),$C79-1966)} -> 346292 | E79: {=INDEX(GMW!$A$2:$NF$150,MATCH(1,(GMW!$NE$2:$NE$150=E$3)*(GMW!$ND$2:$ND$150=E$4)*(GMW!$NF$2:$NF$150=E$1),0),$C79-1966)} -> 57.66667 | F79: {=INDEX(GMW!$A$2:$NF$150,MATCH(1,(GMW!$NE$2:$NE$150=F$3)*(GMW!$ND$2:$ND$150=F$4)*(GMW!$NF$2:$NF$150=F$1),0),$C79-1966)} -> 63795 | G79: {=INDEX(GMW!$A$2:$NF$150,MATCH(1,(GMW!$NE$2:$NE$150=G$3)*(GMW!$ND$2:$ND$150=G$4)*(GMW!$NF$2:$NF$150=G$1),0),$C79-1966)} -> 28390.49 | H79: {=INDEX(GMW!$A$2:$NF$150,MATCH(1,(GMW!$NE$2:$NE$150=H$3)*(GMW!$ND$2:$ND$150=H$4)*(GMW!$NF$2:$NF$150=H$1),0),$C79-1966)} -> 61468 | I79: {=INDEX(GMW!$A$2:$NF$150,MATCH(1,(GMW!$NE$2:$NE$150=I$3)*(GMW!$ND$2:$ND$150=I$4)*(GMW!$NF$2:$NF$150=I$1),0),$C79-1966)} -> 29387.32 | J79: {=INDEX(GMW!$A$2:$NF$150,MATCH(1,(GMW!$NE$2:$NE$150=J$3)*(GMW!$ND$2:$ND$150=J$4)*(GMW!$NF$2:$NF$150=J$1),0),$C79-1966)} -> 66021 | K79: {=INDEX(GMW!$A$2:$NF$150,MATCH(1,(GMW!$NE$2:$NE$150=K$3)*(GMW!$ND$2:$ND$150=K$4)*(GMW!$NF$2:$NF$150=K$1),0),$C79-1966)} -> 29000.32 | ... AV79: {=INDEX(GMW!$A$2:$NF$150,MATCH(1,(GMW!$NE$2:$NE$150=AV$3)*(GMW!$ND$2:$ND$150=AV$4)*(GMW!$NF$2:$NF$150=AV$1),0),$C79-1966)} -> -1.787067
B80: =+B76+1 -> 1991 | C80: =+C79+1 -> 2046 | D80: {=INDEX(GMW!$A$2:$NF$150,MATCH(1,(GMW!$NE$2:$NE$150=D$3)*(GMW!$ND$2:$ND$150=D$4)*(GMW!$NF$2:$NF$150=D$1),0),$C80-1966)} -> 345892 | E80: {=INDEX(GMW!$A$2:$NF$150,MATCH(1,(GMW!$NE$2:$NE$150=E$3)*(GMW!$ND$2:$ND$150=E$4)*(GMW!$NF$2:$NF$150=E$1),0),$C80-1966)} -> 60.26667 | F80: {=INDEX(GMW!$A$2:$NF$150,MATCH(1,(GMW!$NE$2:$NE$150=F$3)*(GMW!$ND$2:$ND$150=F$4)*(GMW!$NF$2:$NF$150=F$1),0),$C80-1966)} -> 65908 | G80: {=INDEX(GMW!$A$2:$NF$150,MATCH(1,(GMW!$NE$2:$NE$150=G$3)*(GMW!$ND$2:$ND$150=G$4)*(GMW!$NF$2:$NF$150=G$1),0),$C80-1966)} -> 29084.43 | H80: {=INDEX(GMW!$A$2:$NF$150,MATCH(1,(GMW!$NE$2:$NE$150=H$3)*(GMW!$ND$2:$ND$150=H$4)*(GMW!$NF$2:$NF$150=H$1),0),$C80-1966)} -> 61739 | I80: {=INDEX(GMW!$A$2:$NF$150,MATCH(1,(GMW!$NE$2:$NE$150=I$3)*(GMW!$ND$2:$ND$150=I$4)*(GMW!$NF$2:$NF$150=I$1),0),$C80-1966)} -> 28073.43 | J80: {=INDEX(GMW!$A$2:$NF$150,MATCH(1,(GMW!$NE$2:$NE$150=J$3)*(GMW!$ND$2:$ND$150=J$4)*(GMW!$NF$2:$NF$150=J$1),0),$C80-1966)} -> 65035 | K80: {=INDEX(GMW!$A$2:$NF$150,MATCH(1,(GMW!$NE$2:$NE$150=K$3)*(GMW!$ND$2:$ND$150=K$4)*(GMW!$NF$2:$NF$150=K$1),0),$C80-1966)} -> 27787.15 | ... AV80: {=INDEX(GMW!$A$2:$NF$150,MATCH(1,(GMW!$NE$2:$NE$150=AV$3)*(GMW!$ND$2:$ND$150=AV$4)*(GMW!$NF$2:$NF$150=AV$1),0),$C80-1966)} -> -1.784331
B81: =+B77+1 -> 1991 | C81: =+C80+1 -> 2047 | D81: {=INDEX(GMW!$A$2:$NF$150,MATCH(1,(GMW!$NE$2:$NE$150=D$3)*(GMW!$ND$2:$ND$150=D$4)*(GMW!$NF$2:$NF$150=D$1),0),$C81-1966)} -> 345216 | E81: {=INDEX(GMW!$A$2:$NF$150,MATCH(1,(GMW!$NE$2:$NE$150=E$3)*(GMW!$ND$2:$ND$150=E$4)*(GMW!$NF$2:$NF$150=E$1),0),$C81-1966)} -> 60.83333 | F81: {=INDEX(GMW!$A$2:$NF$150,MATCH(1,(GMW!$NE$2:$NE$150=F$3)*(GMW!$ND$2:$ND$150=F$4)*(GMW!$NF$2:$NF$150=F$1),0),$C81-1966)} -> 66928 | G81: {=INDEX(GMW!$A$2:$NF$150,MATCH(1,(GMW!$NE$2:$NE$150=G$3)*(GMW!$ND$2:$ND$150=G$4)*(GMW!$NF$2:$NF$150=G$1),0),$C81-1966)} -> 28134.07 | H81: {=INDEX(GMW!$A$2:$NF$150,MATCH(1,(GMW!$NE$2:$NE$150=H$3)*(GMW!$ND$2:$ND$150=H$4)*(GMW!$NF$2:$NF$150=H$1),0),$C81-1966)} -> 62111 | I81: {=INDEX(GMW!$A$2:$NF$150,MATCH(1,(GMW!$NE$2:$NE$150=I$3)*(GMW!$ND$2:$ND$150=I$4)*(GMW!$NF$2:$NF$150=I$1),0),$C81-1966)} -> 28178.53 | J81: {=INDEX(GMW!$A$2:$NF$150,MATCH(1,(GMW!$NE$2:$NE$150=J$3)*(GMW!$ND$2:$ND$150=J$4)*(GMW!$NF$2:$NF$150=J$1),0),$C81-1966)} -> 63852 | K81: {=INDEX(GMW!$A$2:$NF$150,MATCH(1,(GMW!$NE$2:$NE$150=K$3)*(GMW!$ND$2:$ND$150=K$4)*(GMW!$NF$2:$NF$150=K$1),0),$C81-1966)} -> 26511.22 | ... AV81: {=INDEX(GMW!$A$2:$NF$150,MATCH(1,(GMW!$NE$2:$NE$150=AV$3)*(GMW!$ND$2:$ND$150=AV$4)*(GMW!$NF$2:$NF$150=AV$1),0),$C81-1966)} -> -1.7816
