Workbook
Name _DLX1.INC: HAVERM!$A$1:$G$6
Name _DLX2.INC: HAVERQ!$A$2:$BN$7
Name Data: [1]sheet0!$C$2

Sheet CHARTS>>

Sheet DATA>>

Sheet Chart Data
A1: LFS unemployment - single-month & three-month rates | E1: LFS unemployment - single-month range & 3-month rate | L1: Employees - LFS, HMRC, WFJ | Q1: LFS revisions | Y1: Long-term net inward migration
B3: Single month rate | C3: Three-month rate | F3: Single month range - min | G3: Range of single-month estimates | H3: Three-month rate | J3: Single month range - max | M3: Labour Force Survey | N3: HMRC | O3: Workforce jobs | R3: 45200 | S3: 45323 | T3: Current | V3: Diff 000s | W3: Diff % | Z3: Current estimate | AA3: Previous estimate | AB3: January 2024 population projections | AD3: Diff (history) | AE3: Diff vs pproj
A4: 42370 | B4: =HAVERM!C439 -> 4.928 | C4: =HAVERM!B439 -> 5.1 | E4: 42370 | F4: =MIN(HAVERM!C438:C440) -> 4.928 | G4: =J4-F4 -> 0.324 | H4: =HAVERM!B439 -> 5.1 | J4: =MAX(HAVERM!C438:C440) -> 5.252 | L4: 43466 | M4: =HAVERQ!BC164-AVERAGE(HAVERQ!$BC$164:$BC$167) -> -88.25 | N4: =(HAVERQ!BD164-AVERAGE(HAVERQ!$BD$164:$BD$167))/1000 -> -77.403167 | O4: =HAVERQ!BE164-AVERAGE(HAVERQ!$BE$164:$BE$167) -> -111 | Q4: 43466 | R4: =DataQ!Q191 -> 32697 | S4: =DataQ!P191 -> 32721 | T4: =DataQ!O191 -> 32773 | V4: =T4-R4 -> 76 | W4: =100*((T4/R4)-1) -> 0.23243723 | Y4: 41061 | Z4: ='LTIM ye Jun24 - Table 1'!C105 -> 162000 | AA4: ='LTIM ye Dec23 - Table 1'!C100 -> 162000
A5: 42401 | B5: =HAVERM!C440 -> 5.116 | C5: =HAVERM!B440 -> 5.1 | E5: 42401 | F5: =MIN(HAVERM!C439:C441) -> 4.928 | G5: =J5-F5 -> 0.237 | H5: =HAVERM!B440 -> 5.1 | J5: =MAX(HAVERM!C439:C441) -> 5.165 | L5: 43556 | M5: =HAVERQ!BC165-AVERAGE(HAVERQ!$BC$164:$BC$167) -> 31.75 | N5: =(HAVERQ!BD165-AVERAGE(HAVERQ!$BD$164:$BD$167))/1000 -> -12.3305 | O5: =HAVERQ!BE165-AVERAGE(HAVERQ!$BE$164:$BE$167) -> -38 | Q5: 43556 | R5: =DataQ!Q192 -> 32811 | S5: =DataQ!P192 -> 32839 | T5: =DataQ!O192 -> 32965 | V5: =T5-R5 -> 154 | W5: =100*((T5/R5)-1) -> 0.46935479 | Y5: 41153 | Z5: ='LTIM ye Jun24 - Table 1'!C106 -> 157000 | AA5: ='LTIM ye Dec23 - Table 1'!C101 -> 157000
A6: 42430 | B6: =HAVERM!C441 -> 5.165 | C6: =HAVERM!B441 -> 5 | E6: 42430 | F6: =MIN(HAVERM!C440:C442) -> 4.73 | G6: =J6-F6 -> 0.435 | H6: =HAVERM!B441 -> 5 | J6: =MAX(HAVERM!C440:C442) -> 5.165 | L6: 43647 | M6: =HAVERQ!BC166-AVERAGE(HAVERQ!$BC$164:$BC$167) -> -18.25 | N6: =(HAVERQ!BD166-AVERAGE(HAVERQ!$BD$164:$BD$167))/1000 -> 20.369833 | O6: =HAVERQ!BE166-AVERAGE(HAVERQ!$BE$164:$BE$167) -> 94 | Q6: 43647 | R6: =DataQ!Q193 -> 32753 | S6: =DataQ!P193 -> 32779 | T6: =DataQ!O193 -> 32894 | V6: =T6-R6 -> 141 | W6: =100*((T6/R6)-1) -> 0.43049492 | Y6: 41244 | Z6: ='LTIM ye Jun24 - Table 1'!C107 -> 195000 | AA6: ='LTIM ye Dec23 - Table 1'!C102 -> 195000
A7: 42461 | B7: =HAVERM!C442 -> 4.73 | C7: =HAVERM!B442 -> 4.9 | E7: 42461 | F7: =MIN(HAVERM!C441:C443) -> 4.73 | G7: =J7-F7 -> 0.435 | H7: =HAVERM!B442 -> 4.9 | J7: =MAX(HAVERM!C441:C443) -> 5.165 | L7: 43739 | M7: =HAVERQ!BC167-AVERAGE(HAVERQ!$BC$164:$BC$167) -> 74.75 | N7: =(HAVERQ!BD167-AVERAGE(HAVERQ!$BD$164:$BD$167))/1000 -> 69.363833 | O7: =HAVERQ!BE167-AVERAGE(HAVERQ!$BE$164:$BE$167) -> 55 | Q7: 43739 | R7: =DataQ!Q194 -> 32934 | S7: =DataQ!P194 -> 32954 | T7: =DataQ!O194 -> 33055 | V7: =T7-R7 -> 121 | W7: =100*((T7/R7)-1) -> 0.36740147 | Y7: 41334 | Z7: ='LTIM ye Jun24 - Table 1'!C108 -> 204000 | AA7: ='LTIM ye Dec23 - Table 1'!C103 -> 204000
A8: 42491 | B8: =HAVERM!C443 -> 4.88 | C8: =HAVERM!B443 -> 4.9 | E8: 42491 | F8: =MIN(HAVERM!C442:C444) -> 4.73 | G8: =J8-F8 -> 0.415 | H8: =HAVERM!B443 -> 4.9 | J8: =MAX(HAVERM!C442:C444) -> 5.145 | L8: 43831 | M8: =HAVERQ!BC168-AVERAGE(HAVERQ!$BC$164:$BC$167) -> 98.75 | N8: =(HAVERQ!BD168-AVERAGE(HAVERQ!$BD$164:$BD$167))/1000 -> 123.16417 | O8: =HAVERQ!BE168-AVERAGE(HAVERQ!$BE$164:$BE$167) -> 201 | Q8: 43831 | R8: =DataQ!Q195 -> 32984 | S8: =DataQ!P195 -> 33000 | T8: =DataQ!O195 -> 32972 | V8: =T8-R8 -> -12 | W8: =100*((T8/R8)-1) -> -0.036381276 | Y8: 41426 | Z8: ='LTIM ye Jun24 - Table 1'!C109 -> 215000 | AA8: ='LTIM ye Dec23 - Table 1'!C104 -> 215000
A9: 42522 | B9: =HAVERM!C444 -> 5.145 | C9: =HAVERM!B444 -> 4.9 | E9: 42522 | F9: =MIN(HAVERM!C443:C445) -> 4.659 | G9: =J9-F9 -> 0.486 | H9: =HAVERM!B444 -> 4.9 | J9: =MAX(HAVERM!C443:C445) -> 5.145 | L9: 43922 | M9: =HAVERQ!BC169-AVERAGE(HAVERQ!$BC$164:$BC$167) -> 52.75 | N9: =(HAVERQ!BD169-AVERAGE(HAVERQ!$BD$164:$BD$167))/1000 -> -470.3985 | O9: =HAVERQ!BE169-AVERAGE(HAVERQ!$BE$164:$BE$167) -> -96 | Q9: 43922 | R9: =DataQ!Q196 -> 32560 | S9: =DataQ!P196 -> 32571 | T9: =DataQ!O196 -> 32636 | V9: =T9-R9 -> 76 | W9: =100*((T9/R9)-1) -> 0.23341523 | Y9: 41518 | Z9: ='LTIM ye Jun24 - Table 1'!C110 -> 259000 | AA9: ='LTIM ye Dec23 - Table 1'!C105 -> 259000
A10: 42552 | B10: =HAVERM!C445 -> 4.659 | C10: =HAVERM!B445 -> 5 | E10: 42552 | F10: =MIN(HAVERM!C444:C446) -> 4.659 | G10: =J10-F10 -> 0.486 | H10: =HAVERM!B445 -> 5 | J10: =MAX(HAVERM!C444:C446) -> 5.145 | L10: 44013 | M10: =HAVERQ!BC170-AVERAGE(HAVERQ!$BC$164:$BC$167) -> 18.75 | N10: =(HAVERQ!BD170-AVERAGE(HAVERQ!$BD$164:$BD$167))/1000 -> -654.1075 | O10: =HAVERQ!BE170-AVERAGE(HAVERQ!$BE$164:$BE$167) -> -502 | Q10: 44013 | R10: =DataQ!Q197 -> 32333 | S10: =DataQ!P197 -> 32354 | T10: =DataQ!O197 -> 32352 | V10: =T10-R10 -> 19 | W10: =100*((T10/R10)-1) -> 0.058763492 | Y10: 41609 | Z10: ='LTIM ye Jun24 - Table 1'!C111 -> 244000 | AA10: ='LTIM ye Dec23 - Table 1'!C106 -> 244000
A11: 42583 | B11: =HAVERM!C446 -> 5.104 | C11: =HAVERM!B446 -> 4.8 | E11: 42583 | F11: =MIN(HAVERM!C445:C447) -> 4.659 | G11: =J11-F11 -> 0.445 | H11: =HAVERM!B446 -> 4.8 | J11: =MAX(HAVERM!C445:C447) -> 5.104 | L11: 44105 | M11: =HAVERQ!BC171-AVERAGE(HAVERQ!$BC$164:$BC$167) -> 64.75 | N11: =(HAVERQ!BD171-AVERAGE(HAVERQ!$BD$164:$BD$167))/1000 -> -786.03883 | O11: =HAVERQ!BE171-AVERAGE(HAVERQ!$BE$164:$BE$167) -> -507 | Q11: 44105 | R11: =DataQ!Q198 -> 32159 | S11: =DataQ!P198 -> 32198 | T11: =DataQ!O198 -> 32266 | V11: =T11-R11 -> 107 | W11: =100*((T11/R11)-1) -> 0.33272179 | Y11: 41699 | Z11: ='LTIM ye Jun24 - Table 1'!C112 -> 256000 | AA11: ='LTIM ye Dec23 - Table 1'!C107 -> 256000
A12: 42614 | B12: =HAVERM!C447 -> 4.736 | C12: =HAVERM!B447 -> 4.8 | E12: 42614 | F12: =MIN(HAVERM!C446:C448) -> 4.66 | G12: =J12-F12 -> 0.444 | H12: =HAVERM!B447 -> 4.8 | J12: =MAX(HAVERM!C446:C448) -> 5.104 | L12: 44197 | M12: =HAVERQ!BC172-AVERAGE(HAVERQ!$BC$164:$BC$167) -> 164.75 | N12: =(HAVERQ!BD172-AVERAGE(HAVERQ!$BD$164:$BD$167))/1000 -> -736.78817 | O12: =HAVERQ!BE172-AVERAGE(HAVERQ!$BE$164:$BE$167) -> -318 | Q12: 44197 | R12: =DataQ!Q199 -> 32165 | S12: =DataQ!P199 -> 32221 | T12: =DataQ!O199 -> 32308 | V12: =T12-R12 -> 143 | W12: =100*((T12/R12)-1) -> 0.44458262 | Y12: 41791 | Z12: ='LTIM ye Jun24 - Table 1'!C113 -> 248000 | AA12: ='LTIM ye Dec23 - Table 1'!C108 -> 248000
A13: 42644 | B13: =HAVERM!C448 -> 4.66 | C13: =HAVERM!B448 -> 4.8 | E13: 42644 | F13: =MIN(HAVERM!C447:C449) -> 4.66 | G13: =J13-F13 -> 0.291 | H13: =HAVERM!B448 -> 4.8 | J13: =MAX(HAVERM!C447:C449) -> 4.951 | L13: 44287 | M13: =HAVERQ!BC173-AVERAGE(HAVERQ!$BC$164:$BC$167) -> 299.75 | N13: =(HAVERQ!BD173-AVERAGE(HAVERQ!$BD$164:$BD$167))/1000 -> -405.6285 | O13: =HAVERQ!BE173-AVERAGE(HAVERQ!$BE$164:$BE$167) -> -54 | Q13: 44287 | R13: =DataQ!Q200 -> 32303 | S13: =DataQ!P200 -> 32377 | T13: =DataQ!O200 -> 32454 | V13: =T13-R13 -> 151 | W13: =100*((T13/R13)-1) -> 0.46744884 | Y13: 41883 | Z13: ='LTIM ye Jun24 - Table 1'!C114 -> 264000 | AA13: ='LTIM ye Dec23 - Table 1'!C109 -> 264000
A14: 42675 | B14: =HAVERM!C449 -> 4.951 | C14: =HAVERM!B449 -> 4.7 | E14: 42675 | F14: =MIN(HAVERM!C448:C450) -> 4.594 | G14: =J14-F14 -> 0.357 | H14: =HAVERM!B449 -> 4.7 | J14: =MAX(HAVERM!C448:C450) -> 4.951 | L14: 44378 | M14: =HAVERQ!BC174-AVERAGE(HAVERQ!$BC$164:$BC$167) -> 547.75 | N14: =(HAVERQ!BD174-AVERAGE(HAVERQ!$BD$164:$BD$167))/1000 -> 18.3385 | O14: =HAVERQ!BE174-AVERAGE(HAVERQ!$BE$164:$BE$167) -> 279 | Q14: 44378 | R14: =DataQ!Q201 -> 32592 | S14: =DataQ!P201 -> 32687 | T14: =DataQ!O201 -> 32712 | V14: =T14-R14 -> 120 | W14: =100*((T14/R14)-1) -> 0.36818851 | Y14: 41974 | Z14: ='LTIM ye Jun24 - Table 1'!C115 -> 284000 | AA14: ='LTIM ye Dec23 - Table 1'!C110 -> 284000
A15: 42705 | B15: =HAVERM!C450 -> 4.594 | C15: =HAVERM!B450 -> 4.7 | E15: 42705 | F15: =MIN(HAVERM!C449:C451) -> 4.594 | G15: =J15-F15 -> 0.357 | H15: =HAVERM!B450 -> 4.7 | J15: =MAX(HAVERM!C449:C451) -> 4.951 | L15: 44470 | M15: =HAVERQ!BC175-AVERAGE(HAVERQ!$BC$164:$BC$167) -> 638.75 | N15: =(HAVERQ!BD175-AVERAGE(HAVERQ!$BD$164:$BD$167))/1000 -> 252.3115 | O15: =HAVERQ!BE175-AVERAGE(HAVERQ!$BE$164:$BE$167) -> 424 | Q15: 44470 | R15: =DataQ!Q202 -> 32567 | S15: =DataQ!P202 -> 32686 | T15: =DataQ!O202 -> 32729 | V15: =T15-R15 -> 162 | W15: =100*((T15/R15)-1) -> 0.49743605 | Y15: 42064 | Z15: ='LTIM ye Jun24 - Table 1'!C116 -> 296000 | AA15: ='LTIM ye Dec23 - Table 1'!C111 -> 296000
... A21: 42887 | B21: =HAVERM!C456 -> 4.311 | C21: =HAVERM!B456 -> 4.3 | E21: 42887 | F21: =MIN(HAVERM!C455:C457) -> 4.311 | G21: =J21-F21 -> 0.079 | H21: =HAVERM!B456 -> 4.3 | J21: =MAX(HAVERM!C455:C457) -> 4.39 | L21: 45017 | M21: =HAVERQ!BC181-AVERAGE(HAVERQ!$BC$164:$BC$167) -> 1071.75 | N21: =(HAVERQ!BD181-AVERAGE(HAVERQ!$BD$164:$BD$167))/1000 -> 1227.6148 | O21: =HAVERQ!BE181-AVERAGE(HAVERQ!$BE$164:$BE$167) -> 1280 | Q21: 45017 | R21: =DataQ!Q208 -> 32929 | S21: =DataQ!P208 -> 33163 | T21: =DataQ!O208 -> 33356 | V21: =T21-R21 -> 427 | W21: =100*((T21/R21)-1) -> 1.2967293 | Y21: 42614 | Z21: ='LTIM ye Jun24 - Table 1'!C122 -> 290000 | AA21: ='LTIM ye Dec23 - Table 1'!C117 -> 290000
A22: 42917 | B22: =HAVERM!C457 -> 4.332 | C22: =HAVERM!B457 -> 4.3 | E22: 42917 | F22: =MIN(HAVERM!C456:C458) -> 4.311 | G22: =J22-F22 -> 0.021 | H22: =HAVERM!B457 -> 4.3 | J22: =MAX(HAVERM!C456:C458) -> 4.332 | L22: 45108 | M22: =HAVERQ!BC182-AVERAGE(HAVERQ!$BC$164:$BC$167) -> 1048.75 | N22: =(HAVERQ!BD182-AVERAGE(HAVERQ!$BD$164:$BD$167))/1000 -> 1290.1655 | O22: =HAVERQ!BE182-AVERAGE(HAVERQ!$BE$164:$BE$167) -> 1412 | Q22: 45108 | S22: =DataQ!P209 -> 33102 | T22: =DataQ!O209 -> 33326 | Y22: 42705 | Z22: ='LTIM ye Jun24 - Table 1'!C123 -> 249000 | AA22: ='LTIM ye Dec23 - Table 1'!C118 -> 249000
A23: 42948 | B23: =HAVERM!C458 -> 4.33 | C23: =HAVERM!B458 -> 4.3 | E23: 42948 | F23: =MIN(HAVERM!C457:C459) -> 4.134 | G23: =J23-F23 -> 0.198 | H23: =HAVERM!B458 -> 4.3 | J23: =MAX(HAVERM!C457:C459) -> 4.332 | L23: 45200 | M23: =HAVERQ!BC183-AVERAGE(HAVERQ!$BC$164:$BC$167) -> 1038.75 | N23: =(HAVERQ!BD183-AVERAGE(HAVERQ!$BD$164:$BD$167))/1000 -> 1389.6362 | O23: =HAVERQ!BE183-AVERAGE(HAVERQ!$BE$164:$BE$167) -> 1460 | Q23: 45200 | S23: =DataQ!P210 -> 33174 | T23: =DataQ!O210 -> 33377 | Y23: 42795 | Z23: ='LTIM ye Jun24 - Table 1'!C124 -> 240000 | AA23: ='LTIM ye Dec23 - Table 1'!C119 -> 240000
A24: 42979 | B24: =HAVERM!C459 -> 4.134 | C24: =HAVERM!B459 -> 4.2 | E24: 42979 | F24: =MIN(HAVERM!C458:C460) -> 4.134 | G24: =J24-F24 -> 0.196 | H24: =HAVERM!B459 -> 4.2 | J24: =MAX(HAVERM!C458:C460) -> 4.33 | L24: 45292 | M24: =HAVERQ!BC184-AVERAGE(HAVERQ!$BC$164:$BC$167) -> 1146.75 | N24: =(HAVERQ!BD184-AVERAGE(HAVERQ!$BD$164:$BD$167))/1000 -> 1457.8648 | O24: =HAVERQ!BE184-AVERAGE(HAVERQ!$BE$164:$BE$167) -> 1552 | Q24: 45292 | T24: =DataQ!O211 -> 33331 | Y24: 42887 | Z24: ='LTIM ye Jun24 - Table 1'!C125 -> 200000 | AA24: ='LTIM ye Dec23 - Table 1'!C120 -> 200000
A25: 43009 | B25: =HAVERM!C460 -> 4.289 | C25: =HAVERM!B460 -> 4.3 | E25: 43009 | F25: =MIN(HAVERM!C459:C461) -> 4.134 | G25: =J25-F25 -> 0.245 | H25: =HAVERM!B460 -> 4.3 | J25: =MAX(HAVERM!C459:C461) -> 4.379 | L25: 45383 | M25: =HAVERQ!BC185-AVERAGE(HAVERQ!$BC$164:$BC$167) -> 1242.75 | N25: =(HAVERQ!BD185-AVERAGE(HAVERQ!$BD$164:$BD$167))/1000 -> 1491.8655 | O25: =HAVERQ!BE185-AVERAGE(HAVERQ!$BE$164:$BE$167) -> 1576 | Q25: 45383 | T25: =DataQ!O212 -> 33496 | Y25: 42979 | Z25: ='LTIM ye Jun24 - Table 1'!C126 -> 205000 | AA25: ='LTIM ye Dec23 - Table 1'!C121 -> 205000
A26: 43040 | B26: =HAVERM!C461 -> 4.379 | C26: =HAVERM!B461 -> 4.4 | E26: 43040 | F26: =MIN(HAVERM!C460:C462) -> 4.289 | G26: =J26-F26 -> 0.106 | H26: =HAVERM!B461 -> 4.4 | J26: =MAX(HAVERM!C460:C462) -> 4.395 | L26: 45474 | M26: =HAVERQ!BC186-AVERAGE(HAVERQ!$BC$164:$BC$167) -> 1458.75 | N26: =(HAVERQ!BD186-AVERAGE(HAVERQ!$BD$164:$BD$167))/1000 -> 1487.0645 | O26: =HAVERQ!BE186-AVERAGE(HAVERQ!$BE$164:$BE$167) -> 1617 | Q26: 45474 | T26: =DataQ!O213 -> 33749 | Y26: 43070 | Z26: ='LTIM ye Jun24 - Table 1'!C127 -> 208000 | AA26: ='LTIM ye Dec23 - Table 1'!C122 -> 208000
A27: 43070 | B27: =HAVERM!C462 -> 4.395 | C27: =HAVERM!B462 -> 4.3 | E27: 43070 | F27: =MIN(HAVERM!C461:C463) -> 4.173 | G27: =J27-F27 -> 0.222 | H27: =HAVERM!B462 -> 4.3 | J27: =MAX(HAVERM!C461:C463) -> 4.395 | L27: 45566 | N27: =(HAVERQ!BD187-AVERAGE(HAVERQ!$BD$164:$BD$167))/1000 -> 1469.1912 | Q27: 45566 | Y27: 43160 | Z27: ='LTIM ye Jun24 - Table 1'!C128 -> 193000 | AA27: ='LTIM ye Dec23 - Table 1'!C123 -> 193000
A28: 43101 | B28: =HAVERM!C463 -> 4.173 | C28: =HAVERM!B463 -> 4.2 | E28: 43101 | F28: =MIN(HAVERM!C462:C464) -> 4.056 | G28: =J28-F28 -> 0.339 | H28: =HAVERM!B463 -> 4.2 | J28: =MAX(HAVERM!C462:C464) -> 4.395 | Y28: 43252 | Z28: ='LTIM ye Jun24 - Table 1'!C129 -> 216000 | AA28: ='LTIM ye Dec23 - Table 1'!C124 -> 216000
A29: 43132 | B29: =HAVERM!C464 -> 4.056 | C29: =HAVERM!B464 -> 4.2 | E29: 43132 | F29: =MIN(HAVERM!C463:C465) -> 4.056 | G29: =J29-F29 -> 0.329 | H29: =HAVERM!B464 -> 4.2 | J29: =MAX(HAVERM!C463:C465) -> 4.385 | R29: =DataQ!Q6 -> 202302 | S29: =DataQ!P6 -> 202304 | T29: =DataQ!O6 -> 202403 | Y29: 43344 | Z29: ='LTIM ye Jun24 - Table 1'!C130 -> 226000 | AA29: ='LTIM ye Dec23 - Table 1'!C125 -> 226000
A30: 43160 | B30: =HAVERM!C465 -> 4.385 | C30: =HAVERM!B465 -> 4.2 | E30: 43160 | F30: =MIN(HAVERM!C464:C466) -> 4.056 | G30: =J30-F30 -> 0.329 | H30: =HAVERM!B465 -> 4.2 | J30: =MAX(HAVERM!C464:C466) -> 4.385 | Y30: 43435 | Z30: ='LTIM ye Jun24 - Table 1'!C131 -> 276000 | AA30: ='LTIM ye Dec23 - Table 1'!C126 -> 276000
A31: 43191 | B31: =HAVERM!C466 -> 4.16 | C31: =HAVERM!B466 -> 4.2 | E31: 43191 | F31: =MIN(HAVERM!C465:C467) -> 3.936 | G31: =J31-F31 -> 0.449 | H31: =HAVERM!B466 -> 4.2 | J31: =MAX(HAVERM!C465:C467) -> 4.385 | Y31: 43525 | Z31: ='LTIM ye Jun24 - Table 1'!C132 -> 274000 | AA31: ='LTIM ye Dec23 - Table 1'!C127 -> 274000
A32: 43221 | B32: =HAVERM!C467 -> 3.936 | C32: =HAVERM!B467 -> 4 | E32: 43221 | F32: =MIN(HAVERM!C466:C468) -> 3.936 | G32: =J32-F32 -> 0.224 | H32: =HAVERM!B467 -> 4 | J32: =MAX(HAVERM!C466:C468) -> 4.16 | Y32: 43617 | Z32: ='LTIM ye Jun24 - Table 1'!C133 -> 224000 | AA32: ='LTIM ye Dec23 - Table 1'!C128 -> 224000
A33: 43252 | B33: =HAVERM!C468 -> 4.037 | C33: =HAVERM!B468 -> 4 | E33: 43252 | F33: =MIN(HAVERM!C467:C469) -> 3.936 | G33: =J33-F33 -> 0.197 | H33: =HAVERM!B468 -> 4 | J33: =MAX(HAVERM!C467:C469) -> 4.133 | Y33: 43709 | Z33: ='LTIM ye Jun24 - Table 1'!C134 -> 202000 | AA33: ='LTIM ye Dec23 - Table 1'!C129 -> 202000
A34: 43282 | B34: =HAVERM!C469 -> 4.133 | C34: =HAVERM!B469 -> 4 | E34: 43282 | F34: =MIN(HAVERM!C468:C470) -> 3.925 | G34: =J34-F34 -> 0.208 | H34: =HAVERM!B469 -> 4 | J34: =MAX(HAVERM!C468:C470) -> 4.133 | Y34: 43800 | Z34: ='LTIM ye Jun24 - Table 1'!C135 -> 184000 | AA34: ='LTIM ye Dec23 - Table 1'!C130 -> 184000
A35: 43313 | B35: =HAVERM!C470 -> 3.925 | C35: =HAVERM!B470 -> 4.1 | E35: 43313 | F35: =MIN(HAVERM!C469:C471) -> 3.925 | G35: =J35-F35 -> 0.262 | H35: =HAVERM!B470 -> 4.1 | J35: =MAX(HAVERM!C469:C471) -> 4.187 | Y35: 43891 | Z35: ='LTIM ye Jun24 - Table 1'!C136 -> 170000 | AA35: ='LTIM ye Dec23 - Table 1'!C131 -> 170000
A36: 43344 | B36: =HAVERM!C471 -> 4.187 | C36: =HAVERM!B471 -> 4.1 | E36: 43344 | F36: =MIN(HAVERM!C470:C472) -> 3.925 | G36: =J36-F36 -> 0.262 | H36: =HAVERM!B471 -> 4.1 | J36: =MAX(HAVERM!C470:C472) -> 4.187 | Y36: 43983 | Z36: ='LTIM ye Jun24 - Table 1'!C137 -> 111000 | AA36: ='LTIM ye Dec23 - Table 1'!C132 -> 111000
A37: 43374 | B37: =HAVERM!C472 -> 4.101 | C37: =HAVERM!B472 -> 4 | E37: 43374 | F37: =MIN(HAVERM!C471:C473) -> 3.827 | G37: =J37-F37 -> 0.36 | H37: =HAVERM!B472 -> 4 | J37: =MAX(HAVERM!C471:C473) -> 4.187 | Y37: 44075 | Z37: ='LTIM ye Jun24 - Table 1'!C138 -> 35000 | AA37: ='LTIM ye Dec23 - Table 1'!C133 -> 35000
A38: 43405 | B38: =HAVERM!C473 -> 3.827 | C38: =HAVERM!B473 -> 4 | E38: 43405 | F38: =MIN(HAVERM!C472:C474) -> 3.827 | G38: =J38-F38 -> 0.318 | H38: =HAVERM!B473 -> 4 | J38: =MAX(HAVERM!C472:C474) -> 4.145 | Y38: 44166 | Z38: ='LTIM ye Jun24 - Table 1'!C139 -> 93000 | AA38: ='LTIM ye Dec23 - Table 1'!C134 -> 93000
A39: 43435 | B39: =HAVERM!C474 -> 4.145 | C39: =HAVERM!B474 -> 3.9 | E39: 43435 | F39: =MIN(HAVERM!C473:C475) -> 3.827 | G39: =J39-F39 -> 0.318 | H39: =HAVERM!B474 -> 3.9 | J39: =MAX(HAVERM!C473:C475) -> 4.145 | Y39: 44256 | Z39: ='LTIM ye Jun24 - Table 1'!C140 -> 132000 | AA39: ='LTIM ye Dec23 - Table 1'!C135 -> 132000
A40: 43466 | B40: =HAVERM!C475 -> 3.864 | C40: =HAVERM!B475 -> 4 | E40: 43466 | F40: =MIN(HAVERM!C474:C476) -> 3.819 | G40: =J40-F40 -> 0.326 | H40: =HAVERM!B475 -> 4 | J40: =MAX(HAVERM!C474:C476) -> 4.145 | Y40: 44348 | Z40: ='LTIM ye Jun24 - Table 1'!C141 -> 254000 | AA40: ='LTIM ye Dec23 - Table 1'!C136 -> 221000 | AB40: ='Pproj - Jan24'!D12*1000 -> 221500 | AE40: =Z40-AB40 -> 32500
A41: 43497 | B41: =HAVERM!C476 -> 3.819 | C41: =HAVERM!B476 -> 3.8 | E41: 43497 | F41: =MIN(HAVERM!C475:C477) -> 3.816 | G41: =J41-F41 -> 0.048 | H41: =HAVERM!B476 -> 3.8 | J41: =MAX(HAVERM!C475:C477) -> 3.864 | Y41: 44440 | Z41: ='LTIM ye Jun24 - Table 1'!C142 -> 467000 | AA41: ='LTIM ye Dec23 - Table 1'!C137 -> 443000
A42: 43525 | B42: =HAVERM!C477 -> 3.816 | C42: =HAVERM!B477 -> 3.8 | E42: 43525 | F42: =MIN(HAVERM!C476:C478) -> 3.816 | G42: =J42-F42 -> 0.073 | H42: =HAVERM!B477 -> 3.8 | J42: =MAX(HAVERM!C476:C478) -> 3.889 | Y42: 44531 | Z42: ='LTIM ye Jun24 - Table 1'!C143 -> 484000 | AA42: ='LTIM ye Dec23 - Table 1'!C138 -> 466000
A43: 43556 | B43: =HAVERM!C478 -> 3.889 | C43: =HAVERM!B478 -> 3.8 | E43: 43556 | F43: =MIN(HAVERM!C477:C479) -> 3.685 | G43: =J43-F43 -> 0.204 | H43: =HAVERM!B478 -> 3.8 | J43: =MAX(HAVERM!C477:C479) -> 3.889 | Y43: 44621 | Z43: ='LTIM ye Jun24 - Table 1'!C144 -> 548000 | AA43: ='LTIM ye Dec23 - Table 1'!C139 -> 526000
A44: 43586 | B44: =HAVERM!C479 -> 3.685 | C44: =HAVERM!B479 -> 3.9 | E44: 43586 | F44: =MIN(HAVERM!C478:C480) -> 3.685 | G44: =J44-F44 -> 0.401 | H44: =HAVERM!B479 -> 3.9 | J44: =MAX(HAVERM!C478:C480) -> 4.086 | Y44: 44713 | Z44: ='LTIM ye Jun24 - Table 1'!C145 -> 634000 | AA44: ='LTIM ye Dec23 - Table 1'!C140 -> 607000 | AB44: ='Pproj - Jan24'!D13*1000 -> 595900 | AD44: =Z44-AA44 -> 27000 | AE44: =Z44-AB44 -> 38100
A45: 43617 | B45: =HAVERM!C480 -> 4.086 | C45: =HAVERM!B480 -> 3.9 | E45: 43617 | F45: =MIN(HAVERM!C479:C481) -> 3.685 | G45: =J45-F45 -> 0.401 | H45: =HAVERM!B480 -> 3.9 | J45: =MAX(HAVERM!C479:C481) -> 4.086 | Y45: 44805 | Z45: ='LTIM ye Jun24 - Table 1'!C146 -> 789000 | AA45: ='LTIM ye Dec23 - Table 1'!C141 -> 718000
A46: 43647 | B46: =HAVERM!C481 -> 3.783 | C46: =HAVERM!B481 -> 3.9 | E46: 43647 | F46: =MIN(HAVERM!C480:C482) -> 3.771 | G46: =J46-F46 -> 0.315 | H46: =HAVERM!B481 -> 3.9 | J46: =MAX(HAVERM!C480:C482) -> 4.086 | Y46: 44896 | Z46: ='LTIM ye Jun24 - Table 1'!C147 -> 872000 | AA46: ='LTIM ye Dec23 - Table 1'!C142 -> 764000
A47: 43678 | B47: =HAVERM!C482 -> 3.771 | C47: =HAVERM!B482 -> 3.9 | E47: 43678 | F47: =MIN(HAVERM!C481:C483) -> 3.771 | G47: =J47-F47 -> 0.309 | H47: =HAVERM!B482 -> 3.9 | J47: =MAX(HAVERM!C481:C483) -> 4.08 | Y47: 44986 | Z47: ='LTIM ye Jun24 - Table 1'!C148 -> 894000 | AA47: ='LTIM ye Dec23 - Table 1'!C143 -> 750000
A48: 43709 | B48: =HAVERM!C483 -> 4.08 | C48: =HAVERM!B483 -> 3.8 | E48: 43709 | F48: =MIN(HAVERM!C482:C484) -> 3.551 | G48: =J48-F48 -> 0.529 | H48: =HAVERM!B483 -> 3.8 | J48: =MAX(HAVERM!C482:C484) -> 4.08 | Y48: 45078 | Z48: ='LTIM ye Jun24 - Table 1'!C149 -> 906000 | AA48: ='LTIM ye Dec23 - Table 1'!C144 -> 740000 | AB48: ='Pproj - Jan24'!D14*1000 -> 670200 | AD48: =Z48-AA48 -> 166000 | AE48: =Z48-AB48 -> 235800
A49: 43739 | B49: =HAVERM!C484 -> 3.551 | C49: =HAVERM!B484 -> 3.8 | E49: 43739 | F49: =MIN(HAVERM!C483:C485) -> 3.551 | G49: =J49-F49 -> 0.529 | H49: =HAVERM!B484 -> 3.8 | J49: =MAX(HAVERM!C483:C485) -> 4.08 | Y49: 45170 | Z49: ='LTIM ye Jun24 - Table 1'!C150 -> 878000 | AA49: ='LTIM ye Dec23 - Table 1'!C145 -> 724000
A50: 43770 | B50: =HAVERM!C485 -> 3.864 | C50: =HAVERM!B485 -> 3.7 | E50: 43770 | F50: =MIN(HAVERM!C484:C486) -> 3.551 | G50: =J50-F50 -> 0.313 | H50: =HAVERM!B485 -> 3.7 | J50: =MAX(HAVERM!C484:C486) -> 3.864 | Y50: 45261 | Z50: ='LTIM ye Jun24 - Table 1'!C151 -> 866000 | AA50: ='LTIM ye Dec23 - Table 1'!C146 -> 685000 | AD50: =Z50-AA50 -> 181000
A51: 43800 | B51: =HAVERM!C486 -> 3.808 | C51: =HAVERM!B486 -> 3.9 | E51: 43800 | F51: =MIN(HAVERM!C485:C487) -> 3.808 | G51: =J51-F51 -> 0.188 | H51: =HAVERM!B486 -> 3.9 | J51: =MAX(HAVERM!C485:C487) -> 3.996 | Y51: 45352 | Z51: ='LTIM ye Jun24 - Table 1'!C152 -> 824000
A52: 43831 | B52: =HAVERM!C487 -> 3.996 | C52: =HAVERM!B487 -> 3.9 | E52: 43831 | F52: =MIN(HAVERM!C486:C488) -> 3.808 | G52: =J52-F52 -> 0.242 | H52: =HAVERM!B487 -> 3.9 | J52: =MAX(HAVERM!C486:C488) -> 4.05 | Y52: 45444 | Z52: ='LTIM ye Jun24 - Table 1'!C153 -> 728000 | AB52: ='Pproj - Jan24'!G15*1000 -> 599500 | AE52: =Z52-AB52 -> 128500 | AF52: =SUM(AE40:AE52) -> 434900
A53: 43862 | B53: =HAVERM!C488 -> 4.05 | C53: =HAVERM!B488 -> 4.1 | E53: 43862 | F53: =MIN(HAVERM!C487:C489) -> 3.996 | G53: =J53-F53 -> 0.26 | H53: =HAVERM!B488 -> 4.1 | J53: =MAX(HAVERM!C487:C489) -> 4.256
A54: 43891 | B54: =HAVERM!C489 -> 4.256 | C54: =HAVERM!B489 -> 4.1 | E54: 43891 | F54: =MIN(HAVERM!C488:C490) -> 3.969 | G54: =J54-F54 -> 0.287 | H54: =HAVERM!B489 -> 4.1 | J54: =MAX(HAVERM!C488:C490) -> 4.256
A55: 43922 | B55: =HAVERM!C490 -> 3.969 | C55: =HAVERM!B490 -> 4.1 | E55: 43922 | F55: =MIN(HAVERM!C489:C491) -> 3.969 | G55: =J55-F55 -> 0.287 | H55: =HAVERM!B490 -> 4.1 | J55: =MAX(HAVERM!C489:C491) -> 4.256
A56: 43952 | B56: =HAVERM!C491 -> 4.152 | C56: =HAVERM!B491 -> 4.1 | E56: 43952 | F56: =MIN(HAVERM!C490:C492) -> 3.969 | G56: =J56-F56 -> 0.183 | H56: =HAVERM!B491 -> 4.1 | J56: =MAX(HAVERM!C490:C492) -> 4.152
A57: 43983 | B57: =HAVERM!C492 -> 4.119 | C57: =HAVERM!B492 -> 4.4 | E57: 43983 | F57: =MIN(HAVERM!C491:C493) -> 4.119 | G57: =J57-F57 -> 0.693 | H57: =HAVERM!B492 -> 4.4 | J57: =MAX(HAVERM!C491:C493) -> 4.812
A58: 44013 | B58: =HAVERM!C493 -> 4.812 | C58: =HAVERM!B493 -> 4.6 | E58: 44013 | F58: =MIN(HAVERM!C492:C494) -> 4.119 | G58: =J58-F58 -> 0.836 | H58: =HAVERM!B493 -> 4.6 | J58: =MAX(HAVERM!C492:C494) -> 4.955
A59: 44044 | B59: =HAVERM!C494 -> 4.955 | C59: =HAVERM!B494 -> 5 | E59: 44044 | F59: =MIN(HAVERM!C493:C495) -> 4.812 | G59: =J59-F59 -> 0.328 | H59: =HAVERM!B494 -> 5 | J59: =MAX(HAVERM!C493:C495) -> 5.14
A60: 44075 | B60: =HAVERM!C495 -> 5.14 | C60: =HAVERM!B495 -> 5.2 | E60: 44075 | F60: =MIN(HAVERM!C494:C496) -> 4.955 | G60: =J60-F60 -> 0.426 | H60: =HAVERM!B495 -> 5.2 | J60: =MAX(HAVERM!C494:C496) -> 5.381
A61: 44105 | B61: =HAVERM!C496 -> 5.381 | C61: =HAVERM!B496 -> 5.2 | E61: 44105 | F61: =MIN(HAVERM!C495:C497) -> 5.14 | G61: =J61-F61 -> 0.241 | H61: =HAVERM!B496 -> 5.2 | J61: =MAX(HAVERM!C495:C497) -> 5.381
A62: 44136 | B62: =HAVERM!C497 -> 5.163 | C62: =HAVERM!B497 -> 5.3 | E62: 44136 | F62: =MIN(HAVERM!C496:C498) -> 5.163 | G62: =J62-F62 -> 0.218 | H62: =HAVERM!B497 -> 5.3 | J62: =MAX(HAVERM!C496:C498) -> 5.381
A63: 44166 | B63: =HAVERM!C498 -> 5.267 | C63: =HAVERM!B498 -> 5.2 | E63: 44166 | F63: =MIN(HAVERM!C497:C499) -> 5.056 | G63: =J63-F63 -> 0.211 | H63: =HAVERM!B498 -> 5.2 | J63: =MAX(HAVERM!C497:C499) -> 5.267
A64: 44197 | B64: =HAVERM!C499 -> 5.056 | C64: =HAVERM!B499 -> 5 | E64: 44197 | F64: =MIN(HAVERM!C498:C500) -> 4.826 | G64: =J64-F64 -> 0.441 | H64: =HAVERM!B499 -> 5 | J64: =MAX(HAVERM!C498:C500) -> 5.267
... A108: 45536 | B108: =HAVERM!C543 -> 4.391 | C108: =HAVERM!B543 -> 4.3 | E108: 45536 | F108: =MIN(HAVERM!C542:C544) -> 4.1 | G108: =J108-F108 -> 0.291 | H108: =HAVERM!B543 -> 4.3 | J108: =MAX(HAVERM!C542:C544) -> 4.391
A109: 45566 | B109: =HAVERM!C544 -> 4.326 | C109: =HAVERM!B544 -> 4.4 | E109: 45566 | F109: =MIN(HAVERM!C543:C545) -> 4.326 | G109: =J109-F109 -> 0.263 | J109: =MAX(HAVERM!C543:C545) -> 4.589
A110: 45597 | B110: =HAVERM!C545 -> 4.589 | E110: 45597
A111: 45627 | E111: 45627

Sheet HAVERM
A1: 198001 !M | B1: MGSX@UK | C1: UKSEURA@UK | D1: UKNEMW@UK
A2: .DESC | B2: UK: LFS: Unemployment Rate: Aged 16 and Over (SA, %) | C2: UK: LFS: Unemployment Rate: Aged 16 and Over (SA, %) | D2: UK: National Minimum Wage/National Living Wage (NSA, GBP/hr)
A3: .T1 | B3: Feb-1971 | C3: Jun-1992 | D3: Apr-1999
A4: .TN | B4: Oct-2024 | C4: Nov-2024 | D4: Mar-2026
A5: .LSOURCE | B5: Office for National Statistics | C5: Office for National Statistics | D5: Low Pay Commission
A6: .DTLM | B6: Jan-21-2025 07:06 | C6: Jan-21-2025 07:05 | D6: Oct-30-2024 11:52
A7: 198001 | B7: 5.7 | C7: #N/A | D7: #N/A
A8: 198002 | B8: 5.8 | C8: #N/A | D8: #N/A
A9: 198003 | B9: 6 | C9: #N/A | D9: #N/A
A10: 198004 | B10: 6.1 | C10: #N/A | D10: #N/A
A11: 198005 | B11: 6.3 | C11: #N/A | D11: #N/A
A12: 198006 | B12: 6.5 | C12: #N/A | D12: #N/A
A13: 198007 | B13: 6.8 | C13: #N/A | D13: #N/A
A14: 198008 | B14: 7.1 | C14: #N/A | D14: #N/A
A15: 198009 | B15: 7.4 | C15: #N/A | D15: #N/A
A16: 198010 | B16: 7.7 | C16: #N/A | D16: #N/A
A17: 198011 | B17: 8 | C17: #N/A | D17: #N/A
A18: 198012 | B18: 8.3 | C18: #N/A | D18: #N/A
... A155: 199205 | B155: 9.8 | C155: #N/A | D155: #N/A
A156: 199206 | B156: 9.9 | C156: 9.977 | D156: #N/A
A157: 199207 | B157: 9.9 | C157: 9.865 | D157: #N/A
A158: 199208 | B158: 9.9 | C158: 9.947 | D158: #N/A
A159: 199209 | B159: 10.1 | C159: 10.027 | D159: #N/A
A160: 199210 | B160: 10.2 | C160: 10.227 | D160: #N/A
A161: 199211 | B161: 10.4 | C161: 10.439 | D161: #N/A
A162: 199212 | B162: 10.5 | C162: 10.489 | D162: #N/A
A163: 199301 | B163: 10.7 | C163: 10.696 | D163: #N/A
A164: 199302 | B164: 10.6 | C164: 10.837 | D164: #N/A
A165: 199303 | B165: 10.6 | C165: 10.363 | D165: #N/A
A166: 199304 | B166: 10.5 | C166: 10.519 | D166: #N/A
A167: 199305 | B167: 10.4 | C167: 10.457 | D167: #N/A
... A237: 199903 | B237: 6.2 | C237: 6.115 | D237: #N/A
A238: 199904 | B238: 6.1 | C238: 6.139 | D238: 3.6
A239: 199905 | B239: 6 | C239: 6.079 | D239: 3.6
A240: 199906 | B240: 6 | C240: 5.915 | D240: 3.6
A241: 199907 | B241: 5.9 | C241: 5.922 | D241: 3.6
A242: 199908 | B242: 5.9 | C242: 5.887 | D242: 3.6
A243: 199909 | B243: 5.8 | C243: 5.845 | D243: 3.6
A244: 199910 | B244: 5.8 | C244: 5.773 | D244: 3.6
A245: 199911 | B245: 5.8 | C245: 5.937 | D245: 3.6
A246: 199912 | B246: 5.9 | C246: 5.696 | D246: 3.6
A247: 200001 | B247: 5.8 | C247: 5.96 | D247: 3.6
A248: 200002 | B248: 5.8 | C248: 5.795 | D248: 3.6
A249: 200003 | B249: 5.7 | C249: 5.611 | D249: 3.6
... A544: 202410 | B544: 4.4 | C544: 4.326 | D544: 11.44
A545: 202411 | C545: 4.589 | D545: 11.44
A546: 202412 | D546: 11.44
A547: 202501 | D547: 11.44
A548: 202502 | D548: 11.44
A549: 202503 | D549: 11.44
A550: 202504 | D550: 12.21
A551: 202505 | D551: 12.21
A552: 202506 | D552: 12.21
A553: 202507 | D553: 12.21
A554: 202508 | D554: 12.21
A555: 202509 | D555: 12.21
A556: 202510 | D556: 12.21
A557: 202511 | D557: 12.21
... A561: 202603 | D561: 12.21

Sheet HAVERQ
V1: =AVERAGE(V$180:V$183) -> 2596.75 | AN1: =AVERAGE(AN$180:AN$183) -> 30807.75 | AT1: =V1/(V1+AN1) -> 0.077736533 | AU1: =1-AT1 -> 0.92226347
A2: 19801 !Q | B2: G7AUQ@UK | C2: G7K5Q@UK | D2: G7GOQ@UK | E2: MFY7Q@UK | F2: MFZ2Q@UK | G2: G9BZQ@UK | H2: G9C2Q@UK | I2: MFY9Q@UK | J2: MFY5Q@UK | K2: G7ERQ@UK | L2: G7EUQ@UK | M2: G7EXQ@UK | N2: G7F2Q@UK | O2: G7F5Q@UK | P2: G7FGQ@UK | Q2: G7FJQ@UK | R2: G7FMQ@UK | S2: DYDCQ@UK | T2: JWR5Q@UK | U2: JWR6Q@UK | V2: JWR7Q@UK | W2: JWR8Q@UK | X2: JWR9Q@UK | Y2: JWS2Q@UK | Z2: JWS3Q@UK | AA2: JWS4Q@UK | AB2: JWS5Q@UK | AC2: JWS6Q@UK | AD2: JWS7Q@UK | AE2: JWS8Q@UK | AF2: JWS9Q@UK | AG2: JWT2Q@UK | AH2: JWT3Q@UK | AI2: JWT4Q@UK | AJ2: JWT5Q@UK | AK2: JWT6Q@UK | AL2: JWT7Q@UK | AM2: KW78Q@UK | AN2: JWT8Q@UK | AO2: UKNEJ@UK | AP2: MGSCQ@UK | AQ2: MGSXQ@UK | AR2: BEIRQ@UK | AS2: UNVAL1@UK | AT2: UBCMERD@UK | AU2: UBCSERD@UK | AV2: YBWHQ@UK | AW2: MGSLQ@UK | AX2: MGWGQ@UK | AY2: LF24Q@UK | AZ2: YBUVQ@UK | BA2: KAC4@UK | BB2: MGRZQ@UK | BC2: MGRNQ@UK | BD2: UKSEPEP@UK | BE2: BCAJQ@UK | BF2: YCCXQ@UK | BG2: LFM2Q@UK | BH2: MGSCQ@UK
A3: .DESC | B3: UK: Total Public Sector Employment (SA, Thous) | C3: UK: Total Private Sector Employment (SA, Thous) | D3: UK: Total Employment [Labor Force Survey] (SA, Thous) | E3: UK: Public Sector Employment ex Major Reclassifications (SA. Thous) | F3: UK: Private Sector Employment ex Major Reclassifications (SA. Thous) | G3: UK: Public Sector Employment as % of Total Employment (SA, %) | H3: UK: Private Sector Employment as % of Total Employment (SA, %) | I3: UK: Public Sector Employment ex Major Reclassifications (SA. % of Employed) | J3: UK: Private Sector Employment ex Major Reclassifications (SA. % of Employed) | K3: UK: Public Sector Employment: Construction (SA, Thous) | L3: UK: Public Sector Employment: HM Forces (SA, Thous) | M3: UK: Public Sector Employment: Police [including Civilians] (SA, Thous) | N3: UK: Public Sector Employment: Public Administration (SA, Thous) | O3: UK: Public Sector Employment: Education (SA, Thous) | P3: UK: Public Sector Employment: National Health Service (SA, Thous) | Q3: UK: Public Sector Employment: Other Health and Social Work (SA, Thous) | R3: UK: Public Sector Employment: Other Public Sector (SA, Thous) | S3: UK: Total Workforce Jobs [Count of Jobs, Not People] (SA, Thous) | T3: UK: Workforce Jobs: Agriculture, Forestry & Fishing(SA, Thous) | U3: UK: Workforce Jobs: Mining & Quarrying(SA, Thous) | V3: UK: Workforce Jobs: Manufacturing(SA, Thous) | W3: UK: Workforce Jobs: Electricity, Gas, Steam & Air-Conditioning Supply(SA, Thous) | X3: UK: Workforce Jobs: Water Supply, Waste Management & Remediation(SA, Thous) | Y3: UK: Workforce Jobs: Construction(SA, Thous) | Z3: UK: Workforce Jobs: Wholesale/Retail Trade, Motor Vehicle Repair(SA, Thous) | AA3: UK: Workforce Jobs: Transportation & Storage(SA, Thous) | AB3: UK: Workforce Jobs: Accommodation & Food Services(SA, Thous) | AC3: UK: Workforce Jobs: Information & Communication(SA, Thous) | AD3: UK: Workforce Jobs: Financial & Insurance Activities(SA, Thous) | AE3: UK: Workforce Jobs: Real Estate Activities(SA, Thous) | AF3: UK: Workforce Jobs: Professional Scientific & Technical Activities(SA, Thous) | AG3: UK: Workforce Jobs: Administrative & Support Services(SA, Thous) | AH3: UK: Workforce Jobs: Public Administration, Defense, Social Security(SA, Thous) | AI3: UK: Workforce Jobs: Education(SA, Thous) | AJ3: UK: Workforce Jobs: Human Health & Social Work Activities(SA, Thous) | AK3: UK: Workforce Jobs: Arts, Entertainment & Recreation(SA, Thous) | AL3: UK: Workforce Jobs: Other Service Activities(SA, Thous) | AM3: UK: Workforce Jobs: People Employed by Households, etc. (SA, Thous) | AN3: UK: Workforce Jobs: Total Services(SA, Thous) | AO3: UK: Job Vacancies Excluding Agriculture, Forestry & Fishing (NSA, Thous) | AP3: UK: LFS: Unemployed: Aged 16 & Over (SA, Thous) | AQ3: UK: LFS: Unemployment Rate: Aged 16 and Over (SA, %) | AR3: UK: LFS: ILO Redundancy Rate (SA, Per 1000 Employees) | AS3: UK: BoE Agents' Survey: Labor Market: Recruitment Difficulties (NSA, % Bal) | AT3: UK: BCC Survey: Manufacturing: Recruitment Difficulties (% of Cos) | AU3: UK: BCC Survey: Service: Recruitment Difficulties (% of Cos) | AV3: UK: LFS: Unemployed: Aged 16 & Over: Over 12 Months (SA, Thous) | AW3: UK: LFS: Working Age Population: Age 16 & Over (NSA, Thous) | AX3: UK: LFS: Economic Activity Rate: Aged 16 and Over (SA, %) | AY3: UK: LFS: Employment Rate: Aged 16 to 64 (SA, %) | AZ3: UK: LFS: Average Actual Weekly Hours Worked: All Workers (SA, Hours) | BA3: Great Britain: AWE, Total Pay: Private Sector (SA, GBP) | BB3: UK: LFS: Employment: Aged 16 and Over (SA, Thous) | BC3: UK: LFS: Employees (SA, Thous) | BD3: UK: Paid Employees: PAYE Real Time Information [RTI] (SA, Number) | BE3: UK: Workforce Jobs: Employees (SA, Thous) | BF3: UK: LFS: Part-Time Workers: Couldn't Find Full-Time Job (SA, Thous) | BG3: UK: LFS: Economically Inactive: Wants a Job (SA, Thous) | BH3: UK: LFS: Unemployed: Aged 16 & Over (SA, Thous)
A4: .T1 | B4: Q2-1991 | C4: Q1-1999 | D4: Q1-1999 | E4: Q1-1999 | F4: Q1-1999 | G4: Q1-1999 | H4: Q1-1999 | I4: Q1-1999 | J4: Q1-1999 | K4: Q1-1999 | L4: Q1-1999 | M4: Q1-1999 | N4: Q1-1999 | O4: Q1-1999 | P4: Q1-1999 | Q4: Q1-1999 | R4: Q1-1999 | S4: Q2-1959 | T4: Q2-1978 | U4: Q2-1978 | V4: Q2-1978 | W4: Q2-1978 | X4: Q2-1978 | Y4: Q2-1978 | Z4: Q2-1978 | AA4: Q2-1978 | AB4: Q2-1978 | AC4: Q2-1978 | AD4: Q2-1978 | AE4: Q2-1978 | AF4: Q2-1978 | AG4: Q2-1978 | AH4: Q2-1978 | AI4: Q2-1978 | AJ4: Q2-1978 | AK4: Q2-1978 | AL4: Q2-1978 | AM4: Q2-1978 | AN4: Q2-1978 | AO4: Q2-2001 <- Apr-2001 | AP4: Q1-1971 | AQ4: Q1-1971 | AR4: Q2-1995 | AS4: Q1-2005 <- Jan-2005 | AT4: Q1-1989 | AU4: Q1-1989 | AV4: Q2-1992 | AW4: Q1-1971 | AX4: Q1-1971 | AY4: Q1-1971 | AZ4: Q2-1992 | BA4: Q1-2000 <- Jan-2000 | BB4: Q1-1971 | BC4: Q2-1992 | BD4: Q3-2014 <- Jul-2014 | BE4: Q2-1959 | BF4: Q2-1992 | BG4: Q2-1992 | BH4: Q1-1971
A5: .TN | B5: Q3-2024 | C5: Q3-2024 | D5: Q3-2024 | E5: Q3-2024 | F5: Q3-2024 | G5: Q3-2024 | H5: Q3-2024 | I5: Q3-2024 | J5: Q3-2024 | K5: Q3-2024 | L5: Q3-2024 | M5: Q3-2024 | N5: Q3-2024 | O5: Q3-2024 | P5: Q3-2024 | Q5: Q3-2024 | R5: Q3-2024 | S5: Q3-2024 | T5: Q3-2024 | U5: Q3-2024 | V5: Q3-2024 | W5: Q3-2024 | X5: Q3-2024 | Y5: Q3-2024 | Z5: Q3-2024 | AA5: Q3-2024 | AB5: Q3-2024 | AC5: Q3-2024 | AD5: Q3-2024 | AE5: Q3-2024 | AF5: Q3-2024 | AG5: Q3-2024 | AH5: Q3-2024 | AI5: Q3-2024 | AJ5: Q3-2024 | AK5: Q3-2024 | AL5: Q3-2024 | AM5: Q3-2024 | AN5: Q3-2024 | AO5: Q4-2024 <- Dec-2024 | AP5: Q3-2024 | AQ5: Q3-2024 | AR5: Q3-2024 | AS5: Q3-2024 <- Nov-2024 | AT5: Q4-2024 | AU5: Q4-2024 | AV5: Q3-2024 | AW5: Q3-2024 | AX5: Q3-2024 | AY5: Q3-2024 | AZ5: Q3-2024 | BA5: Q3-2024 <- Nov-2024 | BB5: Q3-2024 | BC5: Q3-2024 | BD5: Q4-2024 <- Dec-2024 | BE5: Q3-2024 | BF5: Q3-2024 | BG5: Q3-2024 | BH5: Q3-2024
A6: .LSOURCE | B6: Office for National Statistics | C6: Office for National Statistics | D6: Office for National Statistics | E6: Office for National Statistics | F6: Office for National Statistics | G6: Office for National Statistics | H6: Office for National Statistics | I6: Office for National Statistics | J6: Office for National Statistics | K6: Office for National Statistics | L6: Office for National Statistics | M6: Office for National Statistics | N6: Office for National Statistics | O6: Office for National Statistics | P6: Office for National Statistics | Q6: Office for National Statistics | R6: Office for National Statistics | S6: Office for National Statistics | T6: Office for National Statistics | U6: Office for National Statistics | V6: Office for National Statistics | W6: Office for National Statistics | X6: Office for National Statistics | Y6: Office for National Statistics | Z6: Office for National Statistics | AA6: Office for National Statistics | AB6: Office for National Statistics | AC6: Office for National Statistics | AD6: Office for National Statistics | AE6: Office for National Statistics | AF6: Office for National Statistics | AG6: Office for National Statistics | AH6: Office for National Statistics | AI6: Office for National Statistics | AJ6: Office for National Statistics | AK6: Office for National Statistics | AL6: Office for National Statistics | AM6: Office for National Statistics | AN6: Office for National Statistics | AO6: Office for National Statistics | AP6: Office for National Statistics | AQ6: Office for National Statistics | AR6: Office for National Statistics | AS6: Bank of England | AT6: The British Chambers of Commerce | AU6: The British Chambers of Commerce | AV6: Office for National Statistics | AW6: Office for National Statistics | AX6: Office for National Statistics | AY6: Office for National Statistics | AZ6: Office for National Statistics | BA6: Office for National Statistics | BB6: Office for National Statistics | BC6: Office for National Statistics | BD6: Office for National Statistics | BE6: Office for National Statistics | BF6: Office for National Statistics | BG6: Office for National Statistics | BH6: Office for National Statistics
A7: .DTLM | B7: Dec-17-2024 07:20 | C7: Dec-17-2024 07:20 | D7: Dec-17-2024 07:20 | E7: Dec-17-2024 07:20 | F7: Dec-17-2024 07:20 | G7: Dec-17-2024 07:20 | H7: Dec-17-2024 07:20 | I7: Dec-17-2024 07:20 | J7: Dec-17-2024 07:20 | K7: Dec-17-2024 07:20 | L7: Dec-17-2024 07:20 | M7: Dec-17-2024 07:04 | N7: Dec-17-2024 07:20 | O7: Dec-17-2024 07:20 | P7: Dec-17-2024 07:20 | Q7: Dec-17-2024 07:20 | R7: Dec-17-2024 07:20 | S7: Dec-17-2024 07:20 | T7: Dec-17-2024 07:20 | U7: Dec-17-2024 07:20 | V7: Dec-17-2024 07:20 | W7: Dec-17-2024 07:20 | X7: Dec-17-2024 07:20 | Y7: Dec-17-2024 07:20 | Z7: Dec-17-2024 07:20 | AA7: Dec-17-2024 07:20 | AB7: Dec-17-2024 07:20 | AC7: Dec-17-2024 07:20 | AD7: Dec-17-2024 07:20 | AE7: Dec-17-2024 07:20 | AF7: Dec-17-2024 07:20 | AG7: Dec-17-2024 07:20 | AH7: Dec-17-2024 07:20 | AI7: Dec-17-2024 07:20 | AJ7: Dec-17-2024 07:20 | AK7: Dec-17-2024 07:20 | AL7: Dec-17-2024 07:20 | AM7: Dec-17-2024 07:20 | AN7: Dec-17-2024 07:20 | AO7: Jan-21-2025 07:04 | AP7: Dec-17-2024 07:18 | AQ7: Dec-17-2024 07:20 | AR7: Dec-17-2024 07:20 | AS7: Dec-19-2024 12:02 | AT7: Jan-06-2025 00:01 | AU7: Jan-06-2025 00:01 | AV7: Dec-17-2024 07:20 | AW7: Dec-17-2024 07:20 | AX7: Dec-17-2024 07:20 | AY7: Dec-17-2024 07:20 | AZ7: Dec-17-2024 07:20 | BA7: Jan-21-2025 07:03 | BB7: Dec-17-2024 07:20 | BC7: Dec-17-2024 07:20 | BD7: Jan-21-2025 07:04 | BE7: Dec-17-2024 07:20 | BF7: Dec-17-2024 07:20 | BG7: Dec-17-2024 07:20 | BH7: Dec-17-2024 07:18
A8: 19801 | B8: #N/A | C8: #N/A | D8: #N/A | E8: #N/A | F8: #N/A | G8: #N/A | H8: #N/A | I8: #N/A | J8: #N/A | K8: #N/A | L8: #N/A | M8: #N/A | N8: #N/A | O8: #N/A | P8: #N/A | Q8: #N/A | R8: #N/A | S8: 27465 | T8: 509 | U8: 373 | V8: 6541 | W8: 259 | X8: 156 | Y8: 1962 | Z8: 4153 | AA8: 1408 | AB8: 1257 | AC8: 791 | AD8: 853 | AE8: 176 | AF8: 1023 | AG8: 1120 | AH8: 1992 | AI8: 1747 | AJ8: 2025 | AK8: 510 | AL8: 610 | AM8: 0 | AN8: 17664 | AO8: #N/A | AP8: 1558 | AQ8: 5.8 | AR8: #N/A | AS8: #N/A | AT8: #N/A | AU8: #N/A | AV8: #N/A | AW8: 42610 | AX8: 62.9 | AY8: 71.5 | AZ8: #N/A | BA8: #N/A | BB8: 25250 | BC8: #N/A | BD8: #N/A | BE8: 25010 | BF8: #N/A | BG8: #N/A | BH8: 1558
A9: 19802 | B9: #N/A | C9: #N/A | D9: #N/A | E9: #N/A | F9: #N/A | G9: #N/A | H9: #N/A | I9: #N/A | J9: #N/A | K9: #N/A | L9: #N/A | M9: #N/A | N9: #N/A | O9: #N/A | P9: #N/A | Q9: #N/A | R9: #N/A | S9: 27369 | T9: 510 | U9: 368 | V9: 6423 | W9: 260 | X9: 155 | Y9: 1962 | Z9: 4151 | AA9: 1406 | AB9: 1265 | AC9: 787 | AD9: 860 | AE9: 177 | AF9: 1031 | AG9: 1126 | AH9: 1983 | AI9: 1740 | AJ9: 2044 | AK9: 510 | AL9: 611 | AM9: 0 | AN9: 17691 | AO9: #N/A | AP9: 1700 | AQ9: 6.3 | AR9: #N/A | AS9: #N/A | AT9: #N/A | AU9: #N/A | AV9: #N/A | AW9: 42699 | AX9: 63 | AY9: 71.2 | AZ9: #N/A | BA9: #N/A | BB9: 25190 | BC9: #N/A | BD9: #N/A | BE9: 24879 | BF9: #N/A | BG9: #N/A | BH9: 1700
A10: 19803 | B10: #N/A | C10: #N/A | D10: #N/A | E10: #N/A | F10: #N/A | G10: #N/A | H10: #N/A | I10: #N/A | J10: #N/A | K10: #N/A | L10: #N/A | M10: #N/A | N10: #N/A | O10: #N/A | P10: #N/A | Q10: #N/A | R10: #N/A | S10: 27108 | T10: 513 | U10: 365 | V10: 6228 | W10: 262 | X10: 155 | Y10: 1951 | Z10: 4096 | AA10: 1398 | AB10: 1258 | AC10: 777 | AD10: 874 | AE10: 177 | AF10: 1029 | AG10: 1122 | AH10: 1984 | AI10: 1740 | AJ10: 2058 | AK10: 510 | AL10: 611 | AM10: 0 | AN10: 17634 | AO10: #N/A | AP10: 1905 | AQ10: 7.1 | AR10: #N/A | AS10: #N/A | AT10: #N/A | AU10: #N/A | AV10: #N/A | AW10: 42784 | AX10: 63 | AY10: 70.7 | AZ10: #N/A | BA10: #N/A | BB10: 25050 | BC10: #N/A | BD10: #N/A | BE10: 24581 | BF10: #N/A | BG10: #N/A | BH10: 1905
A11: 19804 | B11: #N/A | C11: #N/A | D11: #N/A | E11: #N/A | F11: #N/A | G11: #N/A | H11: #N/A | I11: #N/A | J11: #N/A | K11: #N/A | L11: #N/A | M11: #N/A | N11: #N/A | O11: #N/A | P11: #N/A | Q11: #N/A | R11: #N/A | S11: 26813 | T11: 503 | U11: 359 | V11: 6045 | W11: 261 | X11: 154 | Y11: 1921 | Z11: 4055 | AA11: 1384 | AB11: 1261 | AC11: 767 | AD11: 876 | AE11: 177 | AF11: 1027 | AG11: 1114 | AH11: 1979 | AI11: 1723 | AJ11: 2077 | AK11: 514 | AL11: 615 | AM11: 0 | AN11: 17570 | AO11: #N/A | AP11: 2169 | AQ11: 8 | AR11: #N/A | AS11: #N/A | AT11: #N/A | AU11: #N/A | AV11: #N/A | AW11: 42862 | AX11: 63.1 | AY11: 69.9 | AZ11: #N/A | BA11: #N/A | BB11: 24855 | BC11: #N/A | BD11: #N/A | BE11: 24254 | BF11: #N/A | BG11: #N/A | BH11: 2169
A12: 19811 | B12: #N/A | C12: #N/A | D12: #N/A | E12: #N/A | F12: #N/A | G12: #N/A | H12: #N/A | I12: #N/A | J12: #N/A | K12: #N/A | L12: #N/A | M12: #N/A | N12: #N/A | O12: #N/A | P12: #N/A | Q12: #N/A | R12: #N/A | S12: 26551 | T12: 503 | U12: 349 | V12: 5901 | W12: 259 | X12: 152 | Y12: 1893 | Z12: 4038 | AA12: 1369 | AB12: 1250 | AC12: 757 | AD12: 879 | AE12: 177 | AF12: 1024 | AG12: 1107 | AH12: 1968 | AI12: 1712 | AJ12: 2090 | AK12: 511 | AL12: 613 | AM12: 0 | AN12: 17494 | AO12: #N/A | AP12: 2403 | AQ12: 8.9 | AR12: #N/A | AS12: #N/A | AT12: #N/A | AU12: #N/A | AV12: #N/A | AW12: 42940 | AX12: 63 | AY12: 69.3 | AZ12: #N/A | BA12: #N/A | BB12: 24661 | BC12: #N/A | BD12: #N/A | BE12: 23962 | BF12: #N/A | BG12: #N/A | BH12: 2403
A13: 19812 | B13: #N/A | C13: #N/A | D13: #N/A | E13: #N/A | F13: #N/A | G13: #N/A | H13: #N/A | I13: #N/A | J13: #N/A | K13: #N/A | L13: #N/A | M13: #N/A | N13: #N/A | O13: #N/A | P13: #N/A | Q13: #N/A | R13: #N/A | S13: 26348 | T13: 492 | U13: 347 | V13: 5789 | W13: 257 | X13: 150 | Y13: 1863 | Z13: 4035 | AA13: 1359 | AB13: 1234 | AC13: 751 | AD13: 878 | AE13: 177 | AF13: 1025 | AG13: 1101 | AH13: 1958 | AI13: 1715 | AJ13: 2098 | AK13: 508 | AL13: 611 | AM13: 0 | AN13: 17450 | AO13: #N/A | AP13: 2588 | AQ13: 9.6 | AR13: #N/A | AS13: #N/A | AT13: #N/A | AU13: #N/A | AV13: #N/A | AW13: 43017 | AX13: 63 | AY13: 68.7 | AZ13: #N/A | BA13: #N/A | BB13: 24495 | BC13: #N/A | BD13: #N/A | BE13: 23728 | BF13: #N/A | BG13: #N/A | BH13: 2588
A14: 19813 | B14: #N/A | C14: #N/A | D14: #N/A | E14: #N/A | F14: #N/A | G14: #N/A | H14: #N/A | I14: #N/A | J14: #N/A | K14: #N/A | L14: #N/A | M14: #N/A | N14: #N/A | O14: #N/A | P14: #N/A | Q14: #N/A | R14: #N/A | S14: 26240 | T14: 485 | U14: 343 | V14: 5714 | W14: 257 | X14: 149 | Y14: 1829 | Z14: 4040 | AA14: 1352 | AB14: 1244 | AC14: 745 | AD14: 874 | AE14: 178 | AF14: 1033 | AG14: 1106 | AH14: 1947 | AI14: 1715 | AJ14: 2111 | AK14: 508 | AL14: 610 | AM14: 0 | AN14: 17463 | AO14: #N/A | AP14: 2684 | AQ14: 9.9 | AR14: #N/A | AS14: #N/A | AT14: #N/A | AU14: #N/A | AV14: #N/A | AW14: 43084 | AX14: 62.8 | AY14: 68.2 | AZ14: #N/A | BA14: #N/A | BB14: 24355 | BC14: #N/A | BD14: #N/A | BE14: 23605 | BF14: #N/A | BG14: #N/A | BH14: 2684
A15: 19814 | B15: #N/A | C15: #N/A | D15: #N/A | E15: #N/A | F15: #N/A | G15: #N/A | H15: #N/A | I15: #N/A | J15: #N/A | K15: #N/A | L15: #N/A | M15: #N/A | N15: #N/A | O15: #N/A | P15: #N/A | Q15: #N/A | R15: #N/A | S15: 26046 | T15: 484 | U15: 338 | V15: 5628 | W15: 254 | X15: 148 | Y15: 1801 | Z15: 3993 | AA15: 1339 | AB15: 1260 | AC15: 742 | AD15: 875 | AE15: 178 | AF15: 1031 | AG15: 1106 | AH15: 1938 | AI15: 1708 | AJ15: 2103 | AK15: 510 | AL15: 612 | AM15: 0 | AN15: 17394 | AO15: #N/A | AP15: 2761 | AQ15: 10.2 | AR15: #N/A | AS15: #N/A | AT15: #N/A | AU15: #N/A | AV15: #N/A | AW15: 43130 | AX15: 62.5 | AY15: 67.7 | AZ15: #N/A | BA15: #N/A | BB15: 24209 | BC15: #N/A | BD15: #N/A | BE15: 23402 | BF15: #N/A | BG15: #N/A | BH15: 2761
A16: 19821 | B16: #N/A | C16: #N/A | D16: #N/A | E16: #N/A | F16: #N/A | G16: #N/A | H16: #N/A | I16: #N/A | J16: #N/A | K16: #N/A | L16: #N/A | M16: #N/A | N16: #N/A | O16: #N/A | P16: #N/A | Q16: #N/A | R16: #N/A | S16: 25997 | T16: 484 | U16: 334 | V16: 5570 | W16: 250 | X16: 148 | Y16: 1800 | Z16: 3989 | AA16: 1333 | AB16: 1271 | AC16: 740 | AD16: 874 | AE16: 179 | AF16: 1034 | AG16: 1111 | AH16: 1921 | AI16: 1707 | AJ16: 2122 | AK16: 514 | AL16: 616 | AM16: 0 | AN16: 17411 | AO16: #N/A | AP16: 2803 | AQ16: 10.4 | AR16: #N/A | AS16: #N/A | AT16: #N/A | AU16: #N/A | AV16: #N/A | AW16: 43176 | AX16: 62.4 | AY16: 67.4 | AZ16: #N/A | BA16: #N/A | BB16: 24120 | BC16: #N/A | BD16: #N/A | BE16: 23343 | BF16: #N/A | BG16: #N/A | BH16: 2803
A17: 19822 | B17: #N/A | C17: #N/A | D17: #N/A | E17: #N/A | F17: #N/A | G17: #N/A | H17: #N/A | I17: #N/A | J17: #N/A | K17: #N/A | L17: #N/A | M17: #N/A | N17: #N/A | O17: #N/A | P17: #N/A | Q17: #N/A | R17: #N/A | S17: 25900 | T17: 488 | U17: 329 | V17: 5472 | W17: 248 | X17: 146 | Y17: 1809 | Z17: 3975 | AA17: 1325 | AB17: 1268 | AC17: 739 | AD17: 873 | AE17: 181 | AF17: 1048 | AG17: 1119 | AH17: 1916 | AI17: 1706 | AJ17: 2129 | AK17: 514 | AL17: 617 | AM17: 0 | AN17: 17409 | AO17: #N/A | AP17: 2841 | AQ17: 10.6 | AR17: #N/A | AS17: #N/A | AT17: #N/A | AU17: #N/A | AV17: #N/A | AW17: 43222 | AX17: 62.2 | AY17: 67.1 | AZ17: #N/A | BA17: #N/A | BB17: 24027 | BC17: #N/A | BD17: #N/A | BE17: 23237 | BF17: #N/A | BG17: #N/A | BH17: 2841
A18: 19823 | B18: #N/A | C18: #N/A | D18: #N/A | E18: #N/A | F18: #N/A | G18: #N/A | H18: #N/A | I18: #N/A | J18: #N/A | K18: #N/A | L18: #N/A | M18: #N/A | N18: #N/A | O18: #N/A | P18: #N/A | Q18: #N/A | R18: #N/A | S18: 25779 | T18: 485 | U18: 325 | V18: 5381 | W18: 246 | X18: 145 | Y18: 1803 | Z18: 3952 | AA18: 1312 | AB18: 1256 | AC18: 730 | AD18: 884 | AE18: 181 | AF18: 1049 | AG18: 1116 | AH18: 1910 | AI18: 1710 | AJ18: 2168 | AK18: 513 | AL18: 614 | AM18: 0 | AN18: 17394 | AO18: #N/A | AP18: 2897 | AQ18: 10.8 | AR18: #N/A | AS18: #N/A | AT18: #N/A | AU18: #N/A | AV18: #N/A | AW18: 43274 | AX18: 61.9 | AY18: 66.6 | AZ18: #N/A | BA18: #N/A | BB18: 23901 | BC18: #N/A | BD18: #N/A | BE18: 23105 | BF18: #N/A | BG18: #N/A | BH18: 2897
A19: 19824 | B19: #N/A | C19: #N/A | D19: #N/A | E19: #N/A | F19: #N/A | G19: #N/A | H19: #N/A | I19: #N/A | J19: #N/A | K19: #N/A | L19: #N/A | M19: #N/A | N19: #N/A | O19: #N/A | P19: #N/A | Q19: #N/A | R19: #N/A | S19: 25588 | T19: 493 | U19: 320 | V19: 5287 | W19: 243 | X19: 144 | Y19: 1800 | Z19: 3914 | AA19: 1307 | AB19: 1231 | AC19: 729 | AD19: 888 | AE19: 181 | AF19: 1049 | AG19: 1122 | AH19: 1907 | AI19: 1706 | AJ19: 2136 | AK19: 515 | AL19: 617 | AM19: 0 | AN19: 17301 | AO19: #N/A | AP19: 2960 | AQ19: 11.1 | AR19: #N/A | AS19: #N/A | AT19: #N/A | AU19: #N/A | AV19: #N/A | AW19: 43337 | AX19: 61.6 | AY19: 66.1 | AZ19: #N/A | BA19: #N/A | BB19: 23755 | BC19: #N/A | BD19: #N/A | BE19: 22903 | BF19: #N/A | BG19: #N/A | BH19: 2960
... A43: 19884 | B43: #N/A | C43: #N/A | D43: #N/A | E43: #N/A | F43: #N/A | G43: #N/A | H43: #N/A | I43: #N/A | J43: #N/A | K43: #N/A | L43: #N/A | M43: #N/A | N43: #N/A | O43: #N/A | P43: #N/A | Q43: #N/A | R43: #N/A | S43: 28644 | T43: 518 | U43: 176 | V43: 5033 | W43: 211 | X43: 145 | Y43: 2114 | Z43: 4484 | AA43: 1331 | AB43: 1558 | AC43: 822 | AD43: 1145 | AE43: 252 | AF43: 1445 | AG43: 1462 | AH43: 1802 | AI43: 2007 | AJ43: 2717 | AK43: 633 | AL43: 789 | AM43: 0 | AN43: 20447 | AO43: #N/A | AP43: 2293 | AQ43: 8 | AR43: #N/A | AS43: #N/A | AT43: #N/A | AU43: #N/A | AV43: #N/A | AW43: 44676 | AX43: 64.1 | AY43: 71.5 | AZ43: #N/A | BA43: #N/A | BB43: 26355 | BC43: #N/A | BD43: #N/A | BE43: 24547 | BF43: #N/A | BG43: #N/A | BH43: 2293
A44: 19891 | B44: #N/A | C44: #N/A | D44: #N/A | E44: #N/A | F44: #N/A | G44: #N/A | H44: #N/A | I44: #N/A | J44: #N/A | K44: #N/A | L44: #N/A | M44: #N/A | N44: #N/A | O44: #N/A | P44: #N/A | Q44: #N/A | R44: #N/A | S44: 28955 | T44: 521 | U44: 172 | V44: 5037 | W44: 210 | X44: 145 | Y44: 2152 | Z44: 4556 | AA44: 1339 | AB44: 1603 | AC44: 831 | AD44: 1158 | AE44: 256 | AF44: 1467 | AG44: 1485 | AH44: 1789 | AI44: 2029 | AJ44: 2754 | AK44: 643 | AL44: 805 | AM44: 0 | AN44: 20717 | AO44: #N/A | AP44: 2179 | AQ44: 7.6 | AR44: #N/A | AS44: #N/A | AT44: 64 | AU44: 58 | AV44: #N/A | AW44: 44713 | AX44: 64.3 | AY44: 72.1 | AZ44: #N/A | BA44: #N/A | BB44: 26590 | BC44: #N/A | BD44: #N/A | BE44: 24729 | BF44: #N/A | BG44: #N/A | BH44: 2179
A45: 19892 | B45: #N/A | C45: #N/A | D45: #N/A | E45: #N/A | F45: #N/A | G45: #N/A | H45: #N/A | I45: #N/A | J45: #N/A | K45: #N/A | L45: #N/A | M45: #N/A | N45: #N/A | O45: #N/A | P45: #N/A | Q45: #N/A | R45: #N/A | S45: 29046 | T45: 517 | U45: 169 | V45: 5031 | W45: 206 | X45: 146 | Y45: 2195 | Z45: 4572 | AA45: 1360 | AB45: 1614 | AC45: 836 | AD45: 1160 | AE45: 260 | AF45: 1487 | AG45: 1499 | AH45: 1792 | AI45: 2037 | AJ45: 2715 | AK45: 643 | AL45: 808 | AM45: 0 | AN45: 20782 | AO45: #N/A | AP45: 2083 | AQ45: 7.2 | AR45: #N/A | AS45: #N/A | AT45: 63 | AU45: 56 | AV45: #N/A | AW45: 44750 | AX45: 64.4 | AY45: 72.4 | AZ45: #N/A | BA45: #N/A | BB45: 26730 | BC45: #N/A | BD45: #N/A | BE45: 24747 | BF45: #N/A | BG45: #N/A | BH45: 2083
A46: 19893 | B46: #N/A | C46: #N/A | D46: #N/A | E46: #N/A | F46: #N/A | G46: #N/A | H46: #N/A | I46: #N/A | J46: #N/A | K46: #N/A | L46: #N/A | M46: #N/A | N46: #N/A | O46: #N/A | P46: #N/A | Q46: #N/A | R46: #N/A | S46: 29152 | T46: 517 | U46: 164 | V46: 5043 | W46: 203 | X46: 147 | Y46: 2207 | Z46: 4585 | AA46: 1370 | AB46: 1635 | AC46: 836 | AD46: 1164 | AE46: 264 | AF46: 1509 | AG46: 1525 | AH46: 1797 | AI46: 2057 | AJ46: 2677 | AK46: 643 | AL46: 810 | AM46: 0 | AN46: 20870 | AO46: #N/A | AP46: 2045 | AQ46: 7.1 | AR46: #N/A | AS46: #N/A | AT46: 66 | AU46: 62 | AV46: #N/A | AW46: 44782 | AX46: 64.4 | AY46: 72.6 | AZ46: #N/A | BA46: #N/A | BB46: 26795 | BC46: #N/A | BD46: #N/A | BE46: 24855 | BF46: #N/A | BG46: #N/A | BH46: 2045
A47: 19894 | B47: #N/A | C47: #N/A | D47: #N/A | E47: #N/A | F47: #N/A | G47: #N/A | H47: #N/A | I47: #N/A | J47: #N/A | K47: #N/A | L47: #N/A | M47: #N/A | N47: #N/A | O47: #N/A | P47: #N/A | Q47: #N/A | R47: #N/A | S47: 29267 | T47: 516 | U47: 163 | V47: 5011 | W47: 200 | X47: 147 | Y47: 2202 | Z47: 4613 | AA47: 1382 | AB47: 1663 | AC47: 842 | AD47: 1165 | AE47: 266 | AF47: 1522 | AG47: 1544 | AH47: 1815 | AI47: 2064 | AJ47: 2718 | AK47: 634 | AL47: 801 | AM47: 0 | AN47: 21028 | AO47: #N/A | AP47: 2021 | AQ47: 7 | AR47: #N/A | AS47: #N/A | AT47: 60 | AU47: 53 | AV47: #N/A | AW47: 44805 | AX47: 64.5 | AY47: 72.8 | AZ47: #N/A | BA47: #N/A | BB47: 26880 | BC47: #N/A | BD47: #N/A | BE47: 24969 | BF47: #N/A | BG47: #N/A | BH47: 2021
A48: 19901 | B48: #N/A | C48: #N/A | D48: #N/A | E48: #N/A | F48: #N/A | G48: #N/A | H48: #N/A | I48: #N/A | J48: #N/A | K48: #N/A | L48: #N/A | M48: #N/A | N48: #N/A | O48: #N/A | P48: #N/A | Q48: #N/A | R48: #N/A | S48: 29291 | T48: 516 | U48: 161 | V48: 4963 | W48: 197 | X48: 146 | Y48: 2212 | Z48: 4618 | AA48: 1388 | AB48: 1669 | AC48: 844 | AD48: 1170 | AE48: 267 | AF48: 1533 | AG48: 1556 | AH48: 1821 | AI48: 2060 | AJ48: 2736 | AK48: 633 | AL48: 800 | AM48: 0 | AN48: 21095 | AO48: #N/A | AP48: 2004 | AQ48: 6.9 | AR48: #N/A | AS48: #N/A | AT48: 67 | AU48: 60 | AV48: #N/A | AW48: 44829 | AX48: 64.5 | AY48: 72.8 | AZ48: #N/A | BA48: #N/A | BB48: 26900 | BC48: #N/A | BD48: #N/A | BE48: 25002 | BF48: #N/A | BG48: #N/A | BH48: 2004
A49: 19902 | B49: #N/A | C49: #N/A | D49: #N/A | E49: #N/A | F49: #N/A | G49: #N/A | H49: #N/A | I49: #N/A | J49: #N/A | K49: #N/A | L49: #N/A | M49: #N/A | N49: #N/A | O49: #N/A | P49: #N/A | Q49: #N/A | R49: #N/A | S49: 29370 | T49: 516 | U49: 159 | V49: 4925 | W49: 197 | X49: 145 | Y49: 2221 | Z49: 4645 | AA49: 1386 | AB49: 1675 | AC49: 847 | AD49: 1172 | AE49: 270 | AF49: 1549 | AG49: 1577 | AH49: 1827 | AI49: 2060 | AJ49: 2752 | AK49: 642 | AL49: 806 | AM49: 0 | AN49: 21208 | AO49: #N/A | AP49: 2002 | AQ49: 6.9 | AR49: #N/A | AS49: #N/A | AT49: 73 | AU49: 60 | AV49: #N/A | AW49: 44852 | AX49: 64.5 | AY49: 72.8 | AZ49: #N/A | BA49: #N/A | BB49: 26935 | BC49: #N/A | BD49: #N/A | BE49: 25061 | BF49: #N/A | BG49: #N/A | BH49: 2002
A50: 19903 | B50: #N/A | C50: #N/A | D50: #N/A | E50: #N/A | F50: #N/A | G50: #N/A | H50: #N/A | I50: #N/A | J50: #N/A | K50: #N/A | L50: #N/A | M50: #N/A | N50: #N/A | O50: #N/A | P50: #N/A | Q50: #N/A | R50: #N/A | S50: 29254 | T50: 509 | U50: 156 | V50: 4875 | W50: 196 | X50: 143 | Y50: 2199 | Z50: 4639 | AA50: 1388 | AB50: 1689 | AC50: 840 | AD50: 1180 | AE50: 269 | AF50: 1545 | AG50: 1571 | AH50: 1830 | AI50: 2034 | AJ50: 2750 | AK50: 640 | AL50: 801 | AM50: 0 | AN50: 21176 | AO50: #N/A | AP50: 2049 | AQ50: 7.1 | AR50: #N/A | AS50: #N/A | AT50: 62 | AU50: 55 | AV50: #N/A | AW50: 44875 | AX50: 64.5 | AY50: 72.7 | AZ50: #N/A | BA50: #N/A | BB50: 26900 | BC50: #N/A | BD50: #N/A | BE50: 25006 | BF50: #N/A | BG50: #N/A | BH50: 2049
A51: 19904 | B51: #N/A | C51: #N/A | D51: #N/A | E51: #N/A | F51: #N/A | G51: #N/A | H51: #N/A | I51: #N/A | J51: #N/A | K51: #N/A | L51: #N/A | M51: #N/A | N51: #N/A | O51: #N/A | P51: #N/A | Q51: #N/A | R51: #N/A | S51: 29046 | T51: 502 | U51: 152 | V51: 4768 | W51: 195 | X51: 140 | Y51: 2168 | Z51: 4608 | AA51: 1381 | AB51: 1694 | AC51: 833 | AD51: 1166 | AE51: 266 | AF51: 1531 | AG51: 1565 | AH51: 1829 | AI51: 2049 | AJ51: 2771 | AK51: 634 | AL51: 793 | AM51: 0 | AN51: 21121 | AO51: #N/A | AP51: 2158 | AQ51: 7.5 | AR51: #N/A | AS51: #N/A | AT51: 57 | AU51: 47 | AV51: #N/A | AW51: 44898 | AX51: 64.4 | AY51: 72.3 | AZ51: #N/A | BA51: #N/A | BB51: 26750 | BC51: #N/A | BD51: #N/A | BE51: 24847 | BF51: #N/A | BG51: #N/A | BH51: 2158
A52: 19911 | B52: #N/A | C52: #N/A | D52: #N/A | E52: #N/A | F52: #N/A | G52: #N/A | H52: #N/A | I52: #N/A | J52: #N/A | K52: #N/A | L52: #N/A | M52: #N/A | N52: #N/A | O52: #N/A | P52: #N/A | Q52: #N/A | R52: #N/A | S52: 28742 | T52: 501 | U52: 148 | V52: 4631 | W52: 193 | X52: 138 | Y52: 2120 | Z52: 4579 | AA52: 1367 | AB52: 1667 | AC52: 821 | AD52: 1160 | AE52: 264 | AF52: 1523 | AG52: 1565 | AH52: 1839 | AI52: 2042 | AJ52: 2783 | AK52: 623 | AL52: 778 | AM52: 0 | AN52: 21012 | AO52: #N/A | AP52: 2306 | AQ52: 8 | AR52: #N/A | AS52: #N/A | AT52: 32 | AU52: 36 | AV52: #N/A | AW52: 44920 | AX52: 64.2 | AY52: 71.7 | AZ52: #N/A | BA52: #N/A | BB52: 26530 | BC52: #N/A | BD52: #N/A | BE52: 24588 | BF52: #N/A | BG52: #N/A | BH52: 2306
A53: 19912 | B53: 5994 | C53: #N/A | D53: #N/A | E53: #N/A | F53: #N/A | G53: #N/A | H53: #N/A | I53: #N/A | J53: #N/A | K53: #N/A | L53: #N/A | M53: #N/A | N53: #N/A | O53: #N/A | P53: #N/A | Q53: #N/A | R53: #N/A | S53: 28445 | T53: 496 | U53: 145 | V53: 4509 | W53: 189 | X53: 138 | Y53: 2078 | Z53: 4553 | AA53: 1356 | AB53: 1636 | AC53: 811 | AD53: 1145 | AE53: 262 | AF53: 1509 | AG53: 1552 | AH53: 1837 | AI53: 2038 | AJ53: 2796 | AK53: 624 | AL53: 773 | AM53: 0 | AN53: 20891 | AO53: #N/A | AP53: 2492 | AQ53: 8.7 | AR53: #N/A | AS53: #N/A | AT53: 34 | AU53: 29 | AV53: #N/A | AW53: 44941 | AX53: 64 | AY53: 71 | AZ53: #N/A | BA53: #N/A | BB53: 26275 | BC53: #N/A | BD53: #N/A | BE53: 24362 | BF53: #N/A | BG53: #N/A | BH53: 2492
A54: 19913 | B54: #N/A | C54: #N/A | D54: #N/A | E54: #N/A | F54: #N/A | G54: #N/A | H54: #N/A | I54: #N/A | J54: #N/A | K54: #N/A | L54: #N/A | M54: #N/A | N54: #N/A | O54: #N/A | P54: #N/A | Q54: #N/A | R54: #N/A | S54: 28265 | T54: 491 | U54: 142 | V54: 4432 | W54: 185 | X54: 137 | Y54: 2039 | Z54: 4556 | AA54: 1349 | AB54: 1619 | AC54: 804 | AD54: 1138 | AE54: 261 | AF54: 1507 | AG54: 1546 | AH54: 1842 | AI54: 2015 | AJ54: 2805 | AK54: 625 | AL54: 771 | AM54: 0 | AN54: 20840 | AO54: #N/A | AP54: 2624 | AQ54: 9.2 | AR54: #N/A | AS54: #N/A | AT54: 27 | AU54: 20 | AV54: #N/A | AW54: 44958 | AX54: 63.7 | AY54: 70.3 | AZ54: #N/A | BA54: #N/A | BB54: 26025 | BC54: #N/A | BD54: #N/A | BE54: 24226 | BF54: #N/A | BG54: #N/A | BH54: 2624
A55: 19914 | B55: #N/A | C55: #N/A | D55: #N/A | E55: #N/A | F55: #N/A | G55: #N/A | H55: #N/A | I55: #N/A | J55: #N/A | K55: #N/A | L55: #N/A | M55: #N/A | N55: #N/A | O55: #N/A | P55: #N/A | Q55: #N/A | R55: #N/A | S55: 28129 | T55: 494 | U55: 133 | V55: 4379 | W55: 179 | X55: 140 | Y55: 2011 | Z55: 4541 | AA55: 1345 | AB55: 1581 | AC55: 802 | AD55: 1126 | AE55: 260 | AF55: 1501 | AG55: 1547 | AH55: 1848 | AI55: 2017 | AJ55: 2821 | AK55: 629 | AL55: 774 | AM55: 0 | AN55: 20793 | AO55: #N/A | AP55: 2697 | AQ55: 9.5 | AR55: #N/A | AS55: #N/A | AT55: 33 | AU55: 33 | AV55: #N/A | AW55: 44975 | AX55: 63.4 | AY55: 69.8 | AZ55: #N/A | BA55: #N/A | BB55: 25820 | BC55: #N/A | BD55: #N/A | BE55: 24101 | BF55: #N/A | BG55: #N/A | BH55: 2697
A56: 19921 | B56: #N/A | C56: #N/A | D56: #N/A | E56: #N/A | F56: #N/A | G56: #N/A | H56: #N/A | I56: #N/A | J56: #N/A | K56: #N/A | L56: #N/A | M56: #N/A | N56: #N/A | O56: #N/A | P56: #N/A | Q56: #N/A | R56: #N/A | S56: 28124 | T56: 496 | U56: 125 | V56: 4327 | W56: 174 | X56: 144 | Y56: 1983 | Z56: 4561 | AA56: 1343 | AB56: 1596 | AC56: 800 | AD56: 1113 | AE56: 261 | AF56: 1505 | AG56: 1551 | AH56: 1848 | AI56: 2030 | AJ56: 2853 | AK56: 636 | AL56: 779 | AM56: 0 | AN56: 20874 | AO56: #N/A | AP56: 2762 | AQ56: 9.7 | AR56: #N/A | AS56: #N/A | AT56: 24 | AU56: 22 | AV56: #N/A | AW56: 44992 | AX56: 63.3 | AY56: 69.4 | AZ56: #N/A | BA56: #N/A | BB56: 25710 | BC56: #N/A | BD56: #N/A | BE56: 24099 | BF56: #N/A | BG56: #N/A | BH56: 2762
A57: 19922 | B57: 5919 | C57: #N/A | D57: #N/A | E57: #N/A | F57: #N/A | G57: #N/A | H57: #N/A | I57: #N/A | J57: #N/A | K57: #N/A | L57: #N/A | M57: #N/A | N57: #N/A | O57: #N/A | P57: #N/A | Q57: #N/A | R57: #N/A | S57: 27966 | T57: 493 | U57: 121 | V57: 4286 | W57: 168 | X57: 146 | Y57: 1953 | Z57: 4524 | AA57: 1326 | AB57: 1607 | AC57: 796 | AD57: 1111 | AE57: 261 | AF57: 1506 | AG57: 1549 | AH57: 1839 | AI57: 2009 | AJ57: 2861 | AK57: 635 | AL57: 775 | AM57: 0 | AN57: 20800 | AO57: #N/A | AP57: 2777 | AQ57: 9.8 | AR57: #N/A | AS57: #N/A | AT57: 23 | AU57: 23 | AV57: 1005 | AW57: 44996 | AX57: 63.1 | AY57: 69.1 | AZ57: 33.2 | BA57: #N/A | BB57: 25605 | BC57: 21576 | BD57: #N/A | BE57: 23970 | BF57: 663 | BG57: 1985 | BH57: 2777
A58: 19923 | B58: #N/A | C58: #N/A | D58: #N/A | E58: #N/A | F58: #N/A | G58: #N/A | H58: #N/A | I58: #N/A | J58: #N/A | K58: #N/A | L58: #N/A | M58: #N/A | N58: #N/A | O58: #N/A | P58: #N/A | Q58: #N/A | R58: #N/A | S58: 27542 | T58: 491 | U58: 117 | V58: 4192 | W58: 166 | X58: 147 | Y58: 1915 | Z58: 4438 | AA58: 1291 | AB58: 1576 | AC58: 782 | AD58: 1089 | AE58: 259 | AF58: 1500 | AG58: 1534 | AH58: 1826 | AI58: 1990 | AJ58: 2839 | AK58: 628 | AL58: 764 | AM58: 0 | AN58: 20515 | AO58: #N/A | AP58: 2815 | AQ58: 9.9 | AR58: #N/A | AS58: #N/A | AT58: 28 | AU58: 28 | AV58: 1088 | AW58: 45003 | AX58: 62.9 | AY58: 68.9 | AZ58: 33 | BA58: #N/A | BB58: 25509 | BC58: 21551 | BD58: #N/A | BE58: 23599 | BF58: 709 | BG58: 1996 | BH58: 2815
A59: 19924 | B59: #N/A | C59: #N/A | D59: #N/A | E59: #N/A | F59: #N/A | G59: #N/A | H59: #N/A | I59: #N/A | J59: #N/A | K59: #N/A | L59: #N/A | M59: #N/A | N59: #N/A | O59: #N/A | P59: #N/A | Q59: #N/A | R59: #N/A | S59: 27417 | T59: 487 | U59: 108 | V59: 4104 | W59: 160 | X59: 149 | Y59: 1883 | Z59: 4439 | AA59: 1290 | AB59: 1583 | AC59: 780 | AD59: 1077 | AE59: 259 | AF59: 1500 | AG59: 1543 | AH59: 1815 | AI59: 1990 | AJ59: 2855 | AK59: 632 | AL59: 765 | AM59: 0 | AN59: 20526 | AO59: #N/A | AP59: 2932 | AQ59: 10.4 | AR59: #N/A | AS59: #N/A | AT59: 34 | AU59: 26 | AV59: 1176 | AW59: 45010 | AX59: 62.8 | AY59: 68.5 | AZ59: 32.9 | BA59: #N/A | BB59: 25336 | BC59: 21429 | BD59: #N/A | BE59: 23532 | BF59: 732 | BG59: 2013 | BH59: 2932
A60: 19931 | B60: #N/A | C60: #N/A | D60: #N/A | E60: #N/A | F60: #N/A | G60: #N/A | H60: #N/A | I60: #N/A | J60: #N/A | K60: #N/A | L60: #N/A | M60: #N/A | N60: #N/A | O60: #N/A | P60: #N/A | Q60: #N/A | R60: #N/A | S60: 27533 | T60: 503 | U60: 102 | V60: 4105 | W60: 156 | X60: 151 | Y60: 1872 | Z60: 4473 | AA60: 1291 | AB60: 1580 | AC60: 787 | AD60: 1076 | AE60: 263 | AF60: 1523 | AG60: 1567 | AH60: 1802 | AI60: 1994 | AJ60: 2866 | AK60: 645 | AL60: 779 | AM60: 0 | AN60: 20644 | AO60: #N/A | AP60: 3004 | AQ60: 10.6 | AR60: #N/A | AS60: #N/A | AT60: 32 | AU60: 28 | AV60: 1243 | AW60: 45016 | AX60: 62.8 | AY60: 68.4 | AZ60: 33 | BA60: #N/A | BB60: 25282 | BC60: 21388 | BD60: #N/A | BE60: 23549 | BF60: 782 | BG60: 2050 | BH60: 3004
A61: 19932 | B61: 5820 | C61: #N/A | D61: #N/A | E61: #N/A | F61: #N/A | G61: #N/A | H61: #N/A | I61: #N/A | J61: #N/A | K61: #N/A | L61: #N/A | M61: #N/A | N61: #N/A | O61: #N/A | P61: #N/A | Q61: #N/A | R61: #N/A | S61: 27519 | T61: 506 | U61: 88 | V61: 4098 | W61: 151 | X61: 154 | Y61: 1851 | Z61: 4495 | AA61: 1283 | AB61: 1564 | AC61: 790 | AD61: 1078 | AE61: 265 | AF61: 1538 | AG61: 1588 | AH61: 1787 | AI61: 1988 | AJ61: 2868 | AK61: 646 | AL61: 781 | AM61: 0 | AN61: 20671 | AO61: #N/A | AP61: 2931 | AQ61: 10.4 | AR61: #N/A | AS61: #N/A | AT61: 32 | AU61: 28 | AV61: 1244 | AW61: 45022 | AX61: 62.7 | AY61: 68.4 | AZ61: 33 | BA61: #N/A | BB61: 25293 | BC61: 21389 | BD61: #N/A | BE61: 23584 | BF61: 812 | BG61: 2177 | BH61: 2931
A62: 19933 | B62: #N/A | C62: #N/A | D62: #N/A | E62: #N/A | F62: #N/A | G62: #N/A | H62: #N/A | I62: #N/A | J62: #N/A | K62: #N/A | L62: #N/A | M62: #N/A | N62: #N/A | O62: #N/A | P62: #N/A | Q62: #N/A | R62: #N/A | S62: 27576 | T62: 505 | U62: 83 | V62: 4086 | W62: 147 | X62: 157 | Y62: 1846 | Z62: 4531 | AA62: 1280 | AB62: 1585 | AC62: 790 | AD62: 1070 | AE62: 269 | AF62: 1556 | AG62: 1601 | AH62: 1774 | AI62: 1992 | AJ62: 2864 | AK62: 653 | AL62: 786 | AM62: 0 | AN62: 20752 | AO62: #N/A | AP62: 2890 | AQ62: 10.2 | AR62: #N/A | AS62: #N/A | AT62: 38 | AU62: 35 | AV62: 1253 | AW62: 45033 | AX62: 62.6 | AY62: 68.5 | AZ62: 33 | BA62: #N/A | BB62: 25316 | BC62: 21431 | BD62: #N/A | BE62: 23655 | BF62: 816 | BG62: 2282 | BH62: 2890
A63: 19934 | B63: #N/A | C63: #N/A | D63: #N/A | E63: #N/A | F63: #N/A | G63: #N/A | H63: #N/A | I63: #N/A | J63: #N/A | K63: #N/A | L63: #N/A | M63: #N/A | N63: #N/A | O63: #N/A | P63: #N/A | Q63: #N/A | R63: #N/A | S63: 27649 | T63: 493 | U63: 78 | V63: 4092 | W63: 146 | X63: 154 | Y63: 1860 | Z63: 4561 | AA63: 1278 | AB63: 1597 | AC63: 794 | AD63: 1085 | AE63: 269 | AF63: 1558 | AG63: 1595 | AH63: 1756 | AI63: 2002 | AJ63: 2887 | AK63: 656 | AL63: 789 | AM63: 0 | AN63: 20826 | AO63: #N/A | AP63: 2892 | AQ63: 10.3 | AR63: #N/A | AS63: #N/A | AT63: 42 | AU63: 38 | AV63: 1274 | AW63: 45046 | AX63: 62.6 | AY63: 68.5 | AZ63: 33 | BA63: #N/A | BB63: 25320 | BC63: 21403 | BD63: #N/A | BE63: 23668 | BF63: 825 | BG63: 2328 | BH63: 2892
A64: 19941 | B64: #N/A | C64: #N/A | D64: #N/A | E64: #N/A | F64: #N/A | G64: #N/A | H64: #N/A | I64: #N/A | J64: #N/A | K64: #N/A | L64: #N/A | M64: #N/A | N64: #N/A | O64: #N/A | P64: #N/A | Q64: #N/A | R64: #N/A | S64: 27630 | T64: 492 | U64: 74 | V64: 4096 | W64: 144 | X64: 151 | Y64: 1867 | Z64: 4582 | AA64: 1278 | AB64: 1564 | AC64: 794 | AD64: 1086 | AE64: 268 | AF64: 1547 | AG64: 1596 | AH64: 1745 | AI64: 1997 | AJ64: 2904 | AK64: 656 | AL64: 789 | AM64: 0 | AN64: 20806 | AO64: #N/A | AP64: 2806 | AQ64: 9.9 | AR64: #N/A | AS64: #N/A | AT64: 37 | AU64: 32 | AV64: 1236 | AW64: 45059 | AX64: 62.6 | AY64: 68.7 | AZ64: 33.1 | BA64: #N/A | BB64: 25408 | BC64: 21443 | BD64: #N/A | BE64: 23633 | BF64: 831 | BG64: 2308 | BH64: 2806
A65: 19942 | B65: 5659 | C65: #N/A | D65: #N/A | E65: #N/A | F65: #N/A | G65: #N/A | H65: #N/A | I65: #N/A | J65: #N/A | K65: #N/A | L65: #N/A | M65: #N/A | N65: #N/A | O65: #N/A | P65: #N/A | Q65: #N/A | R65: #N/A | S65: 27678 | T65: 487 | U65: 70 | V65: 4121 | W65: 140 | X65: 149 | Y65: 1874 | Z65: 4605 | AA65: 1287 | AB65: 1580 | AC65: 797 | AD65: 1086 | AE65: 269 | AF65: 1553 | AG65: 1599 | AH65: 1731 | AI65: 2015 | AJ65: 2883 | AK65: 648 | AL65: 785 | AM65: 0 | AN65: 20837 | AO65: #N/A | AP65: 2736 | AQ65: 9.7 | AR65: #N/A | AS65: #N/A | AT65: 45 | AU65: 44 | AV65: 1219 | AW65: 45072 | AX65: 62.5 | AY65: 68.8 | AZ65: 33.1 | BA65: #N/A | BB65: 25451 | BC65: 21498 | BD65: #N/A | BE65: 23678 | BF65: 830 | BG65: 2323 | BH65: 2736
A66: 19943 | B66: #N/A | C66: #N/A | D66: #N/A | E66: #N/A | F66: #N/A | G66: #N/A | H66: #N/A | I66: #N/A | J66: #N/A | K66: #N/A | L66: #N/A | M66: #N/A | N66: #N/A | O66: #N/A | P66: #N/A | Q66: #N/A | R66: #N/A | S66: 27874 | T66: 484 | U66: 69 | V66: 4151 | W66: 135 | X66: 148 | Y66: 1888 | Z66: 4627 | AA66: 1289 | AB66: 1616 | AC66: 805 | AD66: 1097 | AE66: 278 | AF66: 1599 | AG66: 1643 | AH66: 1716 | AI66: 2010 | AJ66: 2894 | AK66: 643 | AL66: 781 | AM66: 0 | AN66: 20999 | AO66: #N/A | AP66: 2639 | AQ66: 9.4 | AR66: #N/A | AS66: #N/A | AT66: 46 | AU66: 42 | AV66: 1169 | AW66: 45099 | AX66: 62.5 | AY66: 69 | AZ66: 33.2 | BA66: #N/A | BB66: 25559 | BC66: 21558 | BD66: #N/A | BE66: 23872 | BF66: 828 | BG66: 2310 | BH66: 2639
A67: 19944 | B67: #N/A | C67: #N/A | D67: #N/A | E67: #N/A | F67: #N/A | G67: #N/A | H67: #N/A | I67: #N/A | J67: #N/A | K67: #N/A | L67: #N/A | M67: #N/A | N67: #N/A | O67: #N/A | P67: #N/A | Q67: #N/A | R67: #N/A | S67: 27941 | T67: 470 | U67: 68 | V67: 4176 | W67: 131 | X67: 147 | Y67: 1879 | Z67: 4650 | AA67: 1283 | AB67: 1619 | AC67: 812 | AD67: 1102 | AE67: 280 | AF67: 1613 | AG67: 1655 | AH67: 1698 | AI67: 2021 | AJ67: 2898 | AK67: 650 | AL67: 789 | AM67: 0 | AN67: 21070 | AO67: #N/A | AP67: 2521 | AQ67: 9 | AR67: #N/A | AS67: #N/A | AT67: 54 | AU67: 40 | AV67: 1096 | AW67: 45134 | AX67: 62.3 | AY67: 69.1 | AZ67: 33.5 | BA67: #N/A | BB67: 25600 | BC67: 21604 | BD67: #N/A | BE67: 23921 | BF67: 845 | BG67: 2373 | BH67: 2521
A68: 19951 | B68: #N/A | C68: #N/A | D68: #N/A | E68: #N/A | F68: #N/A | G68: #N/A | H68: #N/A | I68: #N/A | J68: #N/A | K68: #N/A | L68: #N/A | M68: #N/A | N68: #N/A | O68: #N/A | P68: #N/A | Q68: #N/A | R68: #N/A | S68: 27930 | T68: 469 | U68: 67 | V68: 4199 | W68: 130 | X68: 143 | Y68: 1844 | Z68: 4649 | AA68: 1284 | AB68: 1638 | AC68: 813 | AD68: 1101 | AE68: 281 | AF68: 1614 | AG68: 1663 | AH68: 1684 | AI68: 2008 | AJ68: 2908 | AK68: 649 | AL68: 785 | AM68: 0 | AN68: 21078 | AO68: #N/A | AP68: 2497 | AQ68: 8.9 | AR68: #N/A | AS68: #N/A | AT68: 48 | AU68: 43 | AV68: 1085 | AW68: 45169 | AX68: 62.4 | AY68: 69.2 | AZ68: 33.3 | BA68: #N/A | BB68: 25670 | BC68: 21671 | BD68: #N/A | BE68: 23935 | BF68: 818 | BG68: 2374 | BH68: 2497
A69: 19952 | B69: 5597 | C69: #N/A | D69: #N/A | E69: #N/A | F69: #N/A | G69: #N/A | H69: #N/A | I69: #N/A | J69: #N/A | K69: #N/A | L69: #N/A | M69: #N/A | N69: #N/A | O69: #N/A | P69: #N/A | Q69: #N/A | R69: #N/A | S69: 28047 | T69: 465 | U69: 67 | V69: 4214 | W69: 122 | X69: 148 | Y69: 1856 | Z69: 4663 | AA69: 1291 | AB69: 1649 | AC69: 818 | AD69: 1104 | AE69: 283 | AF69: 1628 | AG69: 1678 | AH69: 1675 | AI69: 2024 | AJ69: 2915 | AK69: 654 | AL69: 793 | AM69: 0 | AN69: 21174 | AO69: #N/A | AP69: 2445 | AQ69: 8.7 | AR69: 8.2 | AS69: #N/A | AT69: 51 | AU69: 44 | AV69: 1048 | AW69: 45205 | AX69: 62.4 | AY69: 69.4 | AZ69: 33.3 | BA69: #N/A | BB69: 25770 | BC69: 21787 | BD69: #N/A | BE69: 24070 | BF69: 811 | BG69: 2335 | BH69: 2445
A70: 19953 | B70: #N/A | C70: #N/A | D70: #N/A | E70: #N/A | F70: #N/A | G70: #N/A | H70: #N/A | I70: #N/A | J70: #N/A | K70: #N/A | L70: #N/A | M70: #N/A | N70: #N/A | O70: #N/A | P70: #N/A | Q70: #N/A | R70: #N/A | S70: 28046 | T70: 469 | U70: 68 | V70: 4219 | W70: 119 | X70: 146 | Y70: 1843 | Z70: 4642 | AA70: 1288 | AB70: 1652 | AC70: 821 | AD70: 1102 | AE70: 286 | AF70: 1651 | AG70: 1715 | AH70: 1667 | AI70: 1998 | AJ70: 2926 | AK70: 650 | AL70: 783 | AM70: 0 | AN70: 21181 | AO70: #N/A | AP70: 2447 | AQ70: 8.6 | AR70: 7.5 | AS70: #N/A | AT70: 59 | AU70: 46 | AV70: 1028 | AW70: 45242 | AX70: 62.6 | AY70: 69.6 | AZ70: 33.2 | BA70: #N/A | BB70: 25852 | BC70: 21925 | BD70: #N/A | BE70: 24084 | BF70: 836 | BG70: 2277 | BH70: 2447
A71: 19954 | B71: #N/A | C71: #N/A | D71: #N/A | E71: #N/A | F71: #N/A | G71: #N/A | H71: #N/A | I71: #N/A | J71: #N/A | K71: #N/A | L71: #N/A | M71: #N/A | N71: #N/A | O71: #N/A | P71: #N/A | Q71: #N/A | R71: #N/A | S71: 28192 | T71: 471 | U71: 72 | V71: 4273 | W71: 120 | X71: 145 | Y71: 1837 | Z71: 4696 | AA71: 1277 | AB71: 1638 | AC71: 823 | AD71: 1122 | AE71: 286 | AF71: 1650 | AG71: 1740 | AH71: 1662 | AI71: 2024 | AJ71: 2921 | AK71: 653 | AL71: 782 | AM71: 0 | AN71: 21274 | AO71: #N/A | AP71: 2353 | AQ71: 8.3 | AR71: 7.4 | AS71: #N/A | AT71: 63 | AU71: 51 | AV71: 935 | AW71: 45283 | AX71: 62.6 | AY71: 69.9 | AZ71: 33.2 | BA71: #N/A | BB71: 25982 | BC71: 22070 | BD71: #N/A | BE71: 24257 | BF71: 829 | BG71: 2259 | BH71: 2353
A72: 19961 | B72: #N/A | C72: #N/A | D72: #N/A | E72: #N/A | F72: #N/A | G72: #N/A | H72: #N/A | I72: #N/A | J72: #N/A | K72: #N/A | L72: #N/A | M72: #N/A | N72: #N/A | O72: #N/A | P72: #N/A | Q72: #N/A | R72: #N/A | S72: 28105 | T72: 468 | U72: 76 | V72: 4263 | W72: 115 | X72: 139 | Y72: 1815 | Z72: 4689 | AA72: 1263 | AB72: 1639 | AC72: 813 | AD72: 1096 | AE72: 281 | AF72: 1625 | AG72: 1755 | AH72: 1658 | AI72: 2046 | AJ72: 2913 | AK72: 657 | AL72: 699 | AM72: 97 | AN72: 21230 | AO72: #N/A | AP72: 2330 | AQ72: 8.2 | AR72: 8.9 | AS72: #N/A | AT72: 59 | AU72: 54 | AV72: 915 | AW72: 45322 | AX72: 62.4 | AY72: 69.9 | AZ72: 33.2 | BA72: #N/A | BB72: 25970 | BC72: 22110 | BD72: #N/A | BE72: 24213 | BF72: 826 | BG72: 2307 | BH72: 2330
A73: 19962 | B73: 5498 | C73: #N/A | D73: #N/A | E73: #N/A | F73: #N/A | G73: #N/A | H73: #N/A | I73: #N/A | J73: #N/A | K73: #N/A | L73: #N/A | M73: #N/A | N73: #N/A | O73: #N/A | P73: #N/A | Q73: #N/A | R73: #N/A | S73: 28248 | T73: 473 | U73: 80 | V73: 4248 | W73: 106 | X73: 152 | Y73: 1838 | Z73: 4701 | AA73: 1270 | AB73: 1701 | AC73: 827 | AD73: 1080 | AE73: 282 | AF73: 1629 | AG73: 1791 | AH73: 1648 | AI73: 2046 | AJ73: 2920 | AK73: 660 | AL73: 699 | AM73: 101 | AN73: 21353 | AO73: #N/A | AP73: 2340 | AQ73: 8.3 | AR73: 7.2 | AS73: #N/A | AT73: 63 | AU73: 55 | AV73: 902 | AW73: 45361 | AX73: 62.5 | AY73: 69.9 | AZ73: 33.3 | BA73: #N/A | BB73: 26009 | BC73: 22149 | BD73: #N/A | BE73: 24380 | BF73: 816 | BG73: 2358 | BH73: 2340
A74: 19963 | B74: #N/A | C74: #N/A | D74: #N/A | E74: #N/A | F74: #N/A | G74: #N/A | H74: #N/A | I74: #N/A | J74: #N/A | K74: #N/A | L74: #N/A | M74: #N/A | N74: #N/A | O74: #N/A | P74: #N/A | Q74: #N/A | R74: #N/A | S74: 28394 | T74: 484 | U74: 81 | V74: 4277 | W74: 103 | X74: 173 | Y74: 1812 | Z74: 4722 | AA74: 1275 | AB74: 1709 | AC74: 845 | AD74: 1089 | AE74: 275 | AF74: 1629 | AG74: 1802 | AH74: 1642 | AI74: 2059 | AJ74: 2935 | AK74: 673 | AL74: 707 | AM74: 99 | AN74: 21463 | AO74: #N/A | AP74: 2285 | AQ74: 8.1 | AR74: 7.4 | AS74: #N/A | AT74: 64 | AU74: 57 | AV74: 890 | AW74: 45401 | AX74: 62.4 | AY74: 70 | AZ74: 33.2 | BA74: #N/A | BB74: 26062 | BC74: 22184 | BD74: #N/A | BE74: 24488 | BF74: 814 | BG74: 2437 | BH74: 2285
A75: 19964 | B75: #N/A | C75: #N/A | D75: #N/A | E75: #N/A | F75: #N/A | G75: #N/A | H75: #N/A | I75: #N/A | J75: #N/A | K75: #N/A | L75: #N/A | M75: #N/A | N75: #N/A | O75: #N/A | P75: #N/A | Q75: #N/A | R75: #N/A | S75: 28493 | T75: 483 | U75: 82 | V75: 4272 | W75: 103 | X75: 164 | Y75: 1814 | Z75: 4722 | AA75: 1294 | AB75: 1725 | AC75: 848 | AD75: 1079 | AE75: 274 | AF75: 1657 | AG75: 1863 | AH75: 1631 | AI75: 2048 | AJ75: 2956 | AK75: 679 | AL75: 702 | AM75: 96 | AN75: 21575 | AO75: #N/A | AP75: 2229 | AQ75: 7.8 | AR75: 6.7 | AS75: #N/A | AT75: 75 | AU75: 62 | AV75: 872 | AW75: 45441 | AX75: 62.6 | AY75: 70.3 | AZ75: 33.2 | BA75: #N/A | BB75: 26198 | BC75: 22342 | BD75: #N/A | BE75: 24610 | BF75: 835 | BG75: 2456 | BH75: 2229
A76: 19971 | B76: #N/A | C76: #N/A | D76: #N/A | E76: #N/A | F76: #N/A | G76: #N/A | H76: #N/A | I76: #N/A | J76: #N/A | K76: #N/A | L76: #N/A | M76: #N/A | N76: #N/A | O76: #N/A | P76: #N/A | Q76: #N/A | R76: #N/A | S76: 28505 | T76: 479 | U76: 82 | V76: 4262 | W76: 108 | X76: 162 | Y76: 1793 | Z76: 4791 | AA76: 1285 | AB76: 1727 | AC76: 884 | AD76: 1085 | AE76: 287 | AF76: 1626 | AG76: 1888 | AH76: 1620 | AI76: 2044 | AJ76: 2933 | AK76: 667 | AL76: 692 | AM76: 90 | AN76: 21618 | AO76: #N/A | AP76: 2085 | AQ76: 7.3 | AR76: 7 | AS76: #N/A | AT76: 72 | AU76: 66 | AV76: 813 | AW76: 45481 | AX76: 62.6 | AY76: 70.8 | AZ76: 33.2 | BA76: #N/A | BB76: 26381 | BC76: 22563 | BD76: #N/A | BE76: 24700 | BF76: 823 | BG76: 2474 | BH76: 2085
A77: 19972 | B77: 5405 | C77: #N/A | D77: #N/A | E77: #N/A | F77: #N/A | G77: #N/A | H77: #N/A | I77: #N/A | J77: #N/A | K77: #N/A | L77: #N/A | M77: #N/A | N77: #N/A | O77: #N/A | P77: #N/A | Q77: #N/A | R77: #N/A | S77: 28760 | T77: 499 | U77: 81 | V77: 4285 | W77: 108 | X77: 159 | Y77: 1794 | Z77: 4841 | AA77: 1297 | AB77: 1739 | AC77: 895 | AD77: 1101 | AE77: 290 | AF77: 1639 | AG77: 1946 | AH77: 1606 | AI77: 2060 | AJ77: 2937 | AK77: 681 | AL77: 710 | AM77: 91 | AN77: 21835 | AO77: #N/A | AP77: 2051 | AQ77: 7.2 | AR77: 7.5 | AS77: #N/A | AT77: 67 | AU77: 62 | AV77: 746 | AW77: 45520 | AX77: 62.8 | AY77: 71 | AZ77: 33.2 | BA77: #N/A | BB77: 26514 | BC77: 22717 | BD77: #N/A | BE77: 24975 | BF77: 799 | BG77: 2438 | BH77: 2051
A78: 19973 | B78: #N/A | C78: #N/A | D78: #N/A | E78: #N/A | F78: #N/A | G78: #N/A | H78: #N/A | I78: #N/A | J78: #N/A | K78: #N/A | L78: #N/A | M78: #N/A | N78: #N/A | O78: #N/A | P78: #N/A | Q78: #N/A | R78: #N/A | S78: 28897 | T78: 497 | U78: 78 | V78: 4275 | W78: 106 | X78: 161 | Y78: 1836 | Z78: 4872 | AA78: 1296 | AB78: 1764 | AC78: 899 | AD78: 1105 | AE78: 283 | AF78: 1651 | AG78: 1983 | AH78: 1608 | AI78: 2037 | AJ78: 2946 | AK78: 687 | AL78: 732 | AM78: 81 | AN78: 21945 | AO78: #N/A | AP78: 1951 | AQ78: 6.8 | AR78: 6.7 | AS78: #N/A | AT78: 67 | AU78: 61 | AV78: 681 | AW78: 45561 | AX78: 62.6 | AY78: 71.1 | AZ78: 33.2 | BA78: #N/A | BB78: 26572 | BC78: 22788 | BD78: #N/A | BE78: 25110 | BF78: 785 | BG78: 2439 | BH78: 1951
A79: 19974 | B79: #N/A | C79: #N/A | D79: #N/A | E79: #N/A | F79: #N/A | G79: #N/A | H79: #N/A | I79: #N/A | J79: #N/A | K79: #N/A | L79: #N/A | M79: #N/A | N79: #N/A | O79: #N/A | P79: #N/A | Q79: #N/A | R79: #N/A | S79: 29022 | T79: 484 | U79: 78 | V79: 4301 | W79: 106 | X79: 167 | Y79: 1896 | Z79: 4868 | AA79: 1303 | AB79: 1759 | AC79: 930 | AD79: 1104 | AE79: 286 | AF79: 1667 | AG79: 2001 | AH79: 1599 | AI79: 2040 | AJ79: 2927 | AK79: 687 | AL79: 739 | AM79: 78 | AN79: 21989 | AO79: #N/A | AP79: 1864 | AQ79: 6.5 | AR79: 6.3 | AS79: #N/A | AT79: 74 | AU79: 64 | AV79: 611 | AW79: 45605 | AX79: 62.5 | AY79: 71.2 | AZ79: 33.1 | BA79: #N/A | BB79: 26636 | BC79: 22903 | BD79: #N/A | BE79: 25270 | BF79: 759 | BG79: 2442 | BH79: 1864
A80: 19981 | B80: #N/A | C80: #N/A | D80: #N/A | E80: #N/A | F80: #N/A | G80: #N/A | H80: #N/A | I80: #N/A | J80: #N/A | K80: #N/A | L80: #N/A | M80: #N/A | N80: #N/A | O80: #N/A | P80: #N/A | Q80: #N/A | R80: #N/A | S80: 29045 | T80: 483 | U80: 78 | V80: 4313 | W80: 106 | X80: 163 | Y80: 1885 | Z80: 4872 | AA80: 1313 | AB80: 1759 | AC80: 956 | AD80: 1116 | AE80: 281 | AF80: 1673 | AG80: 1983 | AH80: 1600 | AI80: 2057 | AJ80: 2926 | AK80: 667 | AL80: 730 | AM80: 82 | AN80: 22016 | AO80: #N/A | AP80: 1813 | AQ80: 6.4 | AR80: 7.4 | AS80: #N/A | AT80: 74 | AU80: 66 | AV80: 581 | AW80: 45648 | AX80: 62.4 | AY80: 71.3 | AZ80: 33.2 | BA80: #N/A | BB80: 26677 | BC80: 22972 | BD80: #N/A | BE80: 25333 | BF80: 763 | BG80: 2466 | BH80: 1813
A81: 19982 | B81: 5393 | C81: #N/A | D81: #N/A | E81: #N/A | F81: #N/A | G81: #N/A | H81: #N/A | I81: #N/A | J81: #N/A | K81: #N/A | L81: #N/A | M81: #N/A | N81: #N/A | O81: #N/A | P81: #N/A | Q81: #N/A | R81: #N/A | S81: 28948 | T81: 475 | U81: 76 | V81: 4299 | W81: 105 | X81: 162 | Y81: 1869 | Z81: 4870 | AA81: 1317 | AB81: 1740 | AC81: 970 | AD81: 1113 | AE81: 284 | AF81: 1663 | AG81: 1998 | AH81: 1598 | AI81: 2034 | AJ81: 2916 | AK81: 645 | AL81: 732 | AM81: 82 | AN81: 21962 | AO81: #N/A | AP81: 1791 | AQ81: 6.3 | AR81: 7.3 | AS81: #N/A | AT81: 77 | AU81: 70 | AV81: 561 | AW81: 45691 | AX81: 62.4 | AY81: 71.3 | AZ81: 33.2 | BA81: #N/A | BB81: 26714 | BC81: 23090 | BD81: #N/A | BE81: 25322 | BF81: 763 | BG81: 2439 | BH81: 1791
A82: 19983 | B82: #N/A | C82: #N/A | D82: #N/A | E82: #N/A | F82: #N/A | G82: #N/A | H82: #N/A | I82: #N/A | J82: #N/A | K82: #N/A | L82: #N/A | M82: #N/A | N82: #N/A | O82: #N/A | P82: #N/A | Q82: #N/A | R82: #N/A | S82: 29049 | T82: 446 | U82: 76 | V82: 4295 | W82: 105 | X82: 164 | Y82: 1887 | Z82: 4919 | AA82: 1325 | AB82: 1760 | AC82: 975 | AD82: 1105 | AE82: 293 | AF82: 1688 | AG82: 2005 | AH82: 1596 | AI82: 2039 | AJ82: 2904 | AK82: 656 | AL82: 732 | AM82: 79 | AN82: 22076 | AO82: #N/A | AP82: 1786 | AQ82: 6.2 | AR82: 6.8 | AS82: #N/A | AT82: 70 | AU82: 65 | AV82: 525 | AW82: 45743 | AX82: 62.6 | AY82: 71.6 | AZ82: 33.1 | BA82: #N/A | BB82: 26834 | BC82: 23270 | BD82: #N/A | BE82: 25439 | BF82: 731 | BG82: 2413 | BH82: 1786
A83: 19984 | B83: #N/A | C83: #N/A | D83: #N/A | E83: #N/A | F83: #N/A | G83: #N/A | H83: #N/A | I83: #N/A | J83: #N/A | K83: #N/A | L83: #N/A | M83: #N/A | N83: #N/A | O83: #N/A | P83: #N/A | Q83: #N/A | R83: #N/A | S83: 29213 | T83: 428 | U83: 78 | V83: 4230 | W83: 104 | X83: 167 | Y83: 1918 | Z83: 4893 | AA83: 1343 | AB83: 1785 | AC83: 1014 | AD83: 1115 | AE83: 287 | AF83: 1710 | AG83: 2031 | AH83: 1593 | AI83: 2079 | AJ83: 2948 | AK83: 672 | AL83: 731 | AM83: 87 | AN83: 22287 | AO83: #N/A | AP83: 1764 | AQ83: 6.1 | AR83: 7.9 | AS83: #N/A | AT83: 66 | AU83: 64 | AV83: 500 | AW83: 45796 | AX83: 62.7 | AY83: 71.8 | AZ83: 32.8 | BA83: #N/A | BB83: 26955 | BC83: 23397 | BD83: #N/A | BE83: 25579 | BF83: 717 | BG83: 2391 | BH83: 1764
A84: 19991 | B84: 5398 | C84: 21644 | D84: 27042 | E84: 4956 | F84: 22086 | G84: 20 | H84: 80 | I84: 18.3 | J84: 81.7 | K84: 109 | L84: 217 | M84: 228 | N84: 1163 | O84: 1381 | P84: 1173 | Q84: 392 | R84: 732 | S84: 29237 | T84: 436 | U84: 77 | V84: 4171 | W84: 102 | X84: 164 | Y84: 1884 | Z84: 4871 | AA84: 1346 | AB84: 1789 | AC84: 1027 | AD84: 1121 | AE84: 282 | AF84: 1724 | AG84: 2034 | AH84: 1627 | AI84: 2106 | AJ84: 2968 | AK84: 690 | AL84: 737 | AM84: 80 | AN84: 22402 | AO84: #N/A | AP84: 1780 | AQ84: 6.2 | AR84: 8.8 | AS84: #N/A | AT84: 69 | AU84: 64 | AV84: 499 | AW84: 45851 | AX84: 62.8 | AY84: 71.9 | AZ84: 32.9 | BA84: #N/A | BB84: 27036 | BC84: 23473 | BD84: #N/A | BE84: 25637 | BF84: 714 | BG84: 2325 | BH84: 1780
A85: 19992 | B85: 5411 | C85: 21704 | D85: 27115 | E85: 4968 | F85: 22147 | G85: 20 | H85: 80 | I85: 18.3 | J85: 81.7 | K85: 107 | L85: 218 | M85: 227 | N85: 1172 | O85: 1388 | P85: 1179 | Q85: 392 | R85: 731 | S85: 29327 | T85: 424 | U85: 76 | V85: 4128 | W85: 102 | X85: 165 | Y85: 1909 | Z85: 4872 | AA85: 1346 | AB85: 1800 | AC85: 1065 | AD85: 1141 | AE85: 291 | AF85: 1743 | AG85: 2036 | AH85: 1632 | AI85: 2121 | AJ85: 2933 | AK85: 712 | AL85: 754 | AM85: 78 | AN85: 22523 | AO85: #N/A | AP85: 1743 | AQ85: 6 | AR85: 7.7 | AS85: #N/A | AT85: 71 | AU85: 62 | AV85: 496 | AW85: 45905 | AX85: 62.8 | AY85: 71.9 | AZ85: 32.9 | BA85: #N/A | BB85: 27095 | BC85: 23515 | BD85: #N/A | BE85: 25704 | BF85: 703 | BG85: 2361 | BH85: 1743
A86: 19993 | B86: 5432 | C86: 21780 | D86: 27212 | E86: 4991 | F86: 22221 | G86: 20 | H86: 80 | I86: 18.3 | J86: 81.7 | K86: 111 | L86: 218 | M86: 226 | N86: 1177 | O86: 1388 | P86: 1185 | Q86: 396 | R86: 733 | S86: 29584 | T86: 420 | U86: 76 | V86: 4101 | W86: 99 | X86: 163 | Y86: 1920 | Z86: 4893 | AA86: 1364 | AB86: 1817 | AC86: 1079 | AD86: 1153 | AE86: 292 | AF86: 1780 | AG86: 2074 | AH86: 1635 | AI86: 2150 | AJ86: 2977 | AK86: 732 | AL86: 777 | AM86: 83 | AN86: 22806 | AO86: #N/A | AP86: 1702 | AQ86: 5.9 | AR86: 7.1 | AS86: #N/A | AT86: 69 | AU86: 61 | AV86: 494 | AW86: 45965 | AX86: 62.9 | AY86: 72.1 | AZ86: 32.9 | BA86: #N/A | BB86: 27218 | BC86: 23659 | BD86: #N/A | BE86: 25980 | BF86: 703 | BG86: 2336 | BH86: 1702
A87: 19994 | B87: 5460 | C87: 21847 | D87: 27307 | E87: 5018 | F87: 22289 | G87: 20 | H87: 80 | I87: 18.4 | J87: 81.6 | K87: 111 | L87: 217 | M87: 226 | N87: 1181 | O87: 1395 | P87: 1190 | Q87: 399 | R87: 742 | S87: 29715 | T87: 402 | U87: 76 | V87: 4082 | W87: 96 | X87: 154 | Y87: 1912 | Z87: 4891 | AA87: 1389 | AB87: 1826 | AC87: 1092 | AD87: 1169 | AE87: 301 | AF87: 1791 | AG87: 2075 | AH87: 1646 | AI87: 2200 | AJ87: 2985 | AK87: 739 | AL87: 801 | AM87: 87 | AN87: 22993 | AO87: #N/A | AP87: 1684 | AQ87: 5.8 | AR87: 6.8 | AS87: #N/A | AT87: 71 | AU87: 63 | AV87: 483 | AW87: 46028 | AX87: 63 | AY87: 72.3 | AZ87: 32.9 | BA87: #N/A | BB87: 27322 | BC87: 23770 | BD87: #N/A | BE87: 26118 | BF87: 668 | BG87: 2315 | BH87: 1684
A88: 20001 | B88: 5472 | C88: 21934 | D88: 27406 | E88: 5029 | F88: 22377 | G88: 20 | H88: 80 | I88: 18.3 | J88: 81.7 | K88: 108 | L88: 217 | M88: 225 | N88: 1184 | O88: 1406 | P88: 1197 | Q88: 398 | R88: 734 | S88: 29644 | T88: 397 | U88: 76 | V88: 4049 | W88: 96 | X88: 157 | Y88: 1909 | Z88: 4877 | AA88: 1366 | AB88: 1823 | AC88: 1100 | AD88: 1147 | AE88: 304 | AF88: 1793 | AG88: 2067 | AH88: 1647 | AI88: 2217 | AJ88: 2982 | AK88: 744 | AL88: 808 | AM88: 83 | AN88: 22959 | AO88: #N/A | AP88: 1682 | AQ88: 5.8 | AR88: 7.8 | AS88: #N/A | AT88: 68 | AU88: 61 | AV88: 451 | AW88: 46090 | AX88: 63 | AY88: 72.3 | AZ88: 32.4 | BA88: 303.33333 | BB88: 27362 | BC88: 23833 | BD88: #N/A | BE88: 26097 | BF88: 664 | BG88: 2345 | BH88: 1682
A89: 20002 | B89: 5491 | C89: 22037 | D89: 27528 | E89: 5049 | F89: 22479 | G89: 19.9 | H89: 80.1 | I89: 18.3 | J89: 81.7 | K89: 105 | L89: 217 | M89: 225 | N89: 1178 | O89: 1441 | P89: 1204 | Q89: 388 | R89: 736 | S89: 29775 | T89: 399 | U89: 78 | V89: 4002 | W89: 95 | X89: 161 | Y89: 1959 | Z89: 4887 | AA89: 1359 | AB89: 1825 | AC89: 1132 | AD89: 1144 | AE89: 309 | AF89: 1802 | AG89: 2085 | AH89: 1639 | AI89: 2226 | AJ89: 3040 | AK89: 742 | AL89: 815 | AM89: 76 | AN89: 23082 | AO89: #N/A | AP89: 1599 | AQ89: 5.5 | AR89: 7.5 | AS89: #N/A | AT89: 69 | AU89: 60 | AV89: 445 | AW89: 46152 | AX89: 63 | AY89: 72.5 | AZ89: 32.6 | BA89: 309.66667 | BB89: 27468 | BC89: 23956 | BD89: #N/A | BE89: 26268 | BF89: 652 | BG89: 2397 | BH89: 1599
A90: 20003 | B90: 5513 | C90: 22015 | D90: 27528 | E90: 5072 | F90: 22456 | G90: 20 | H90: 80 | I90: 18.4 | J90: 81.6 | K90: 99 | L90: 216 | M90: 226 | N90: 1177 | O90: 1455 | P90: 1213 | Q90: 379 | R90: 751 | S90: 29957 | T90: 391 | U90: 76 | V90: 3960 | W90: 95 | X90: 164 | Y90: 1940 | Z90: 4926 | AA90: 1380 | AB90: 1820 | AC90: 1161 | AD90: 1149 | AE90: 308 | AF90: 1827 | AG90: 2140 | AH90: 1637 | AI90: 2250 | AJ90: 3105 | AK90: 737 | AL90: 813 | AM90: 78 | AN90: 23331 | AO90: #N/A | AP90: 1548 | AQ90: 5.3 | AR90: 6.5 | AS90: #N/A | AT90: 73 | AU90: 66 | AV90: 415 | AW90: 46226 | AX90: 63 | AY90: 72.6 | AZ90: 32.6 | BA90: 315 | BB90: 27555 | BC90: 24030 | BD90: #N/A | BE90: 26438 | BF90: 661 | BG90: 2340 | BH90: 1548
A91: 20004 | B91: 5526 | C91: 22111 | D91: 27637 | E91: 5081 | F91: 22556 | G91: 20 | H91: 80 | I91: 18.4 | J91: 81.6 | K91: 99 | L91: 215 | M91: 227 | N91: 1177 | O91: 1457 | P91: 1223 | Q91: 375 | R91: 754 | S91: 30012 | T91: 377 | U91: 76 | V91: 3904 | W91: 99 | X91: 165 | Y91: 1936 | Z91: 4948 | AA91: 1401 | AB91: 1821 | AC91: 1195 | AD91: 1162 | AE91: 316 | AF91: 1847 | AG91: 2177 | AH91: 1641 | AI91: 2245 | AJ91: 3071 | AK91: 745 | AL91: 806 | AM91: 81 | AN91: 23456 | AO91: #N/A | AP91: 1520 | AQ91: 5.2 | AR91: 6.5 | AS91: #N/A | AT91: 73 | AU91: 65 | AV91: 393 | AW91: 46307 | AX91: 62.8 | AY91: 72.5 | AZ91: 32.8 | BA91: 321 | BB91: 27549 | BC91: 24088 | BD91: #N/A | BE91: 26497 | BF91: 656 | BG91: 2297 | BH91: 1520
A92: 20011 | B92: 5554 | C92: 22109 | D92: 27663 | E92: 5107 | F92: 22556 | G92: 20.1 | H92: 79.9 | I92: 18.5 | J92: 81.5 | K92: 97 | L92: 215 | M92: 228 | N92: 1181 | O92: 1463 | P92: 1235 | Q92: 373 | R92: 759 | S92: 30026 | T92: 357 | U92: 76 | V92: 3879 | W92: 100 | X92: 169 | Y92: 1937 | Z92: 4990 | AA92: 1400 | AB92: 1824 | AC92: 1196 | AD92: 1165 | AE92: 321 | AF92: 1856 | AG92: 2174 | AH92: 1646 | AI92: 2241 | AJ92: 3074 | AK92: 750 | AL92: 802 | AM92: 68 | AN92: 23507 | AO92: #N/A | AP92: 1481 | AQ92: 5.1 | AR92: 6.6 | AS92: #N/A | AT92: 75 | AU92: 66 | AV92: 382 | AW92: 46386 | AX92: 62.7 | AY92: 72.6 | AZ92: 32.7 | BA92: 324.33333 | BB92: 27623 | BC92: 24102 | BD92: #N/A | BE92: 26517 | BF92: 625 | BG92: 2294 | BH92: 1481
A93: 20012 | B93: 5581 | C93: 22118 | D93: 27699 | E93: 5137 | F93: 22562 | G93: 20.1 | H93: 79.9 | I93: 18.5 | J93: 81.5 | K93: 96 | L93: 214 | M93: 229 | N93: 1185 | O93: 1468 | P93: 1249 | Q93: 375 | R93: 771 | S93: 30136 | T93: 362 | U93: 75 | V93: 3832 | W93: 102 | X93: 170 | Y93: 1974 | Z93: 4985 | AA93: 1412 | AB93: 1842 | AC93: 1207 | AD93: 1176 | AE93: 323 | AF93: 1847 | AG93: 2196 | AH93: 1647 | AI93: 2234 | AJ93: 3119 | AK93: 750 | AL93: 811 | AM93: 72 | AN93: 23622 | AO93: 683.33333 | AP93: 1468 | AQ93: 5 | AR93: 7 | AS93: #N/A | AT93: 62 | AU93: 64 | AV93: 378 | AW93: 46467 | AX93: 62.8 | AY93: 72.7 | AZ93: 32.8 | BA93: 326.66667 | BB93: 27707 | BC93: 24188 | BD93: #N/A | BE93: 26628 | BF93: 602 | BG93: 2260 | BH93: 1468
A94: 20013 | B94: 5605 | C94: 22130 | D94: 27735 | E94: 5156 | F94: 22579 | G94: 20.2 | H94: 79.8 | I94: 18.6 | J94: 81.4 | K94: 87 | L94: 214 | M94: 231 | N94: 1188 | O94: 1465 | P94: 1263 | Q94: 378 | R94: 778 | S94: 30316 | T94: 370 | U94: 75 | V94: 3775 | W94: 102 | X94: 174 | Y94: 2000 | Z94: 4978 | AA94: 1403 | AB94: 1865 | AC94: 1213 | AD94: 1195 | AE94: 320 | AF94: 1855 | AG94: 2209 | AH94: 1647 | AI94: 2224 | AJ94: 3167 | AK94: 773 | AL94: 817 | AM94: 153 | AN94: 23819 | AO94: 690 | AP94: 1487 | AQ94: 5.1 | AR94: 7.9 | AS94: #N/A | AT94: 75 | AU94: 66 | AV94: 369 | AW94: 46541 | AX94: 62.7 | AY94: 72.5 | AZ94: 32.7 | BA94: 329.33333 | BB94: 27715 | BC94: 24181 | BD94: #N/A | BE94: 26821 | BF94: 576 | BG94: 2278 | BH94: 1487
A95: 20014 | B95: 5629 | C95: 22140 | D95: 27769 | E95: 5159 | F95: 22610 | G95: 20.3 | H95: 79.7 | I95: 18.6 | J95: 81.4 | K95: 84 | L95: 214 | M95: 234 | N95: 1197 | O95: 1467 | P95: 1278 | Q95: 366 | R95: 788 | S95: 30322 | T95: 362 | U95: 74 | V95: 3726 | W95: 102 | X95: 178 | Y95: 2023 | Z95: 4984 | AA95: 1414 | AB95: 1862 | AC95: 1212 | AD95: 1193 | AE95: 324 | AF95: 1866 | AG95: 2193 | AH95: 1663 | AI95: 2238 | AJ95: 3173 | AK95: 776 | AL95: 818 | AM95: 141 | AN95: 23857 | AO95: 601.66667 | AP95: 1520 | AQ95: 5.2 | AR95: 8 | AS95: #N/A | AT95: 66 | AU95: 60 | AV95: 350 | AW95: 46621 | AX95: 62.9 | AY95: 72.6 | AZ95: 32.5 | BA95: 333.33333 | BB95: 27803 | BC95: 24274 | BD95: #N/A | BE95: 26823 | BF95: 579 | BG95: 2316 | BH95: 1520
A96: 20021 | B96: 5670 | C96: 22186 | D96: 27856 | E96: 5199 | F96: 22657 | G96: 20.4 | H96: 79.6 | I96: 18.7 | J96: 81.3 | K96: 83 | L96: 214 | M96: 236 | N96: 1204 | O96: 1471 | P96: 1292 | Q96: 371 | R96: 797 | S96: 30313 | T96: 369 | U96: 74 | V96: 3676 | W96: 102 | X96: 168 | Y96: 2003 | Z96: 5000 | AA96: 1404 | AB96: 1864 | AC96: 1214 | AD96: 1203 | AE96: 329 | AF96: 1867 | AG96: 2211 | AH96: 1676 | AI96: 2259 | AJ96: 3169 | AK96: 778 | AL96: 814 | AM96: 131 | AN96: 23920 | AO96: 588.66667 | AP96: 1515 | AQ96: 5.2 | AR96: 8.4 | AS96: #N/A | AT96: 60 | AU96: 60 | AV96: 334 | AW96: 46701 | AX96: 62.8 | AY96: 72.5 | AZ96: 32.5 | BA96: 333.33333 | BB96: 27797 | BC96: 24271 | BD96: #N/A | BE96: 26818 | BF96: 568 | BG96: 2357 | BH96: 1515
A97: 20022 | B97: 5695 | C97: 22213 | D97: 27908 | E97: 5226 | F97: 22682 | G97: 20.4 | H97: 79.6 | I97: 18.7 | J97: 81.3 | K97: 82 | L97: 214 | M97: 238 | N97: 1212 | O97: 1473 | P97: 1309 | Q97: 370 | R97: 797 | S97: 30419 | T97: 364 | U97: 70 | V97: 3636 | W97: 100 | X97: 164 | Y97: 1997 | Z97: 5029 | AA97: 1409 | AB97: 1900 | AC97: 1207 | AD97: 1193 | AE97: 332 | AF97: 1861 | AG97: 2213 | AH97: 1685 | AI97: 2290 | AJ97: 3193 | AK97: 792 | AL97: 840 | AM97: 144 | AN97: 24088 | AO97: 619.66667 | AP97: 1520 | AQ97: 5.2 | AR97: 8 | AS97: #N/A | AT97: 66 | AU97: 58 | AV97: 325 | AW97: 46782 | AX97: 63 | AY97: 72.7 | AZ97: 32.2 | BA97: 338.33333 | BB97: 27933 | BC97: 24395 | BD97: #N/A | BE97: 26848 | BF97: 589 | BG97: 2317 | BH97: 1520
A98: 20023 | B98: 5724 | C98: 22299 | D98: 28023 | E98: 5262 | F98: 22761 | G98: 20.4 | H98: 79.6 | I98: 18.8 | J98: 81.2 | K98: 80 | L98: 215 | M98: 240 | N98: 1215 | O98: 1500 | P98: 1325 | Q98: 357 | R98: 791 | S98: 30507 | T98: 352 | U98: 67 | V98: 3583 | W98: 96 | X98: 161 | Y98: 2014 | Z98: 5035 | AA98: 1422 | AB98: 1925 | AC98: 1211 | AD98: 1189 | AE98: 335 | AF98: 1881 | AG98: 2203 | AH98: 1686 | AI98: 2322 | AJ98: 3243 | AK98: 792 | AL98: 839 | AM98: 151 | AN98: 24234 | AO98: 635.33333 | AP98: 1566 | AQ98: 5.3 | AR98: 7.1 | AS98: #N/A | AT98: 62 | AU98: 60 | AV98: 336 | AW98: 46861 | AX98: 63 | AY98: 72.6 | AZ98: 32.4 | BA98: 340.33333 | BB98: 27935 | BC98: 24386 | BD98: #N/A | BE98: 26923 | BF98: 570 | BG98: 2302 | BH98: 1566
A99: 20024 | B99: 5776 | C99: 22305 | D99: 28081 | E99: 5325 | F99: 22756 | G99: 20.6 | H99: 79.4 | I99: 19 | J99: 81 | K99: 77 | L99: 215 | M99: 242 | N99: 1236 | O99: 1510 | P99: 1341 | Q99: 345 | R99: 807 | S99: 30487 | T99: 335 | U99: 65 | V99: 3536 | W99: 94 | X99: 159 | Y99: 2021 | Z99: 5039 | AA99: 1428 | AB99: 1925 | AC99: 1219 | AD99: 1195 | AE99: 331 | AF99: 1894 | AG99: 2195 | AH99: 1712 | AI99: 2349 | AJ99: 3236 | AK99: 780 | AL99: 832 | AM99: 143 | AN99: 24278 | AO99: 602.66667 | AP99: 1516 | AQ99: 5.1 | AR99: 7.1 | AS99: #N/A | AT99: 74 | AU99: 63 | AV99: 308 | AW99: 46940 | AX99: 63.1 | AY99: 72.9 | AZ99: 32.2 | BA99: 340.66667 | BB99: 28110 | BC99: 24576 | BD99: #N/A | BE99: 26917 | BF99: 557 | BG99: 2310 | BH99: 1516
A100: 20031 | B100: 5827 | C100: 22315 | D100: 28142 | E100: 5374 | F100: 22768 | G100: 20.7 | H100: 79.3 | I100: 19.1 | J100: 80.9 | K100: 79 | L100: 221 | M100: 246 | N100: 1246 | O100: 1516 | P100: 1359 | Q100: 345 | R100: 812 | S100: 30533 | T100: 337 | U100: 63 | V100: 3496 | W100: 92 | X100: 155 | Y100: 2030 | Z100: 4980 | AA100: 1428 | AB100: 1941 | AC100: 1229 | AD100: 1191 | AE100: 339 | AF100: 1902 | AG100: 2204 | AH100: 1736 | AI100: 2371 | AJ100: 3256 | AK100: 789 | AL100: 827 | AM100: 166 | AN100: 24360 | AO100: 562.66667 | AP100: 1531 | AQ100: 5.2 | AR100: 7.3 | AS100: #N/A | AT100: 61 | AU100: 62 | AV100: 327 | AW100: 47020 | AX100: 63 | AY100: 72.7 | AZ100: 32.2 | BA100: 342.33333 | BB100: 28099 | BC100: 24495 | BD100: #N/A | BE100: 26865 | BF100: 560 | BG100: 2239 | BH100: 1531
A101: 20032 | B101: 5858 | C101: 22378 | D101: 28236 | E101: 5421 | F101: 22815 | G101: 20.7 | H101: 79.3 | I101: 19.2 | J101: 80.8 | K101: 77 | L101: 223 | M101: 248 | N101: 1257 | O101: 1531 | P101: 1374 | Q101: 350 | R101: 798 | S101: 30706 | T101: 348 | U101: 61 | V101: 3438 | W101: 93 | X101: 155 | Y101: 2057 | Z101: 5011 | AA101: 1436 | AB101: 1950 | AC101: 1241 | AD101: 1194 | AE101: 336 | AF101: 1944 | AG101: 2209 | AH101: 1748 | AI101: 2395 | AJ101: 3293 | AK101: 792 | AL101: 835 | AM101: 173 | AN101: 24555 | AO101: 582.66667 | AP101: 1467 | AQ101: 4.9 | AR101: 6.4 | AS101: #N/A | AT101: 60 | AU101: 59 | AV101: 314 | AW101: 47099 | AX101: 63 | AY101: 72.9 | AZ101: 32.2 | BA101: 346.66667 | BB101: 28226 | BC101: 24492 | BD101: #N/A | BE101: 26967 | BF101: 579 | BG101: 2223 | BH101: 1467
A102: 20033 | B102: 5894 | C102: 22391 | D102: 28285 | E102: 5466 | F102: 22819 | G102: 20.8 | H102: 79.2 | I102: 19.3 | J102: 80.7 | K102: 80 | L102: 222 | M102: 252 | N102: 1260 | O102: 1535 | P102: 1391 | Q102: 354 | R102: 803 | S102: 30878 | T102: 369 | U102: 61 | V102: 3404 | W102: 92 | X102: 159 | Y102: 2091 | Z102: 5033 | AA102: 1430 | AB102: 1969 | AC102: 1227 | AD102: 1194 | AE102: 344 | AF102: 1982 | AG102: 2216 | AH102: 1746 | AI102: 2408 | AJ102: 3335 | AK102: 811 | AL102: 841 | AM102: 167 | AN102: 24702 | AO102: 617.66667 | AP102: 1502 | AQ102: 5 | AR102: 6.3 | AS102: #N/A | AT102: 64 | AU102: 57 | AV102: 315 | AW102: 47186 | AX102: 63.1 | AY102: 72.8 | AZ102: 32.2 | BA102: 349.33333 | BB102: 28256 | BC102: 24391 | BD102: #N/A | BE102: 27040 | BF102: 567 | BG102: 2160 | BH102: 1502
A103: 20034 | B103: 5937 | C103: 22462 | D103: 28399 | E103: 5501 | F103: 22898 | G103: 20.9 | H103: 79.1 | I103: 19.4 | J103: 80.6 | K103: 80 | L103: 221 | M103: 256 | N103: 1258 | O103: 1557 | P103: 1408 | Q103: 363 | R103: 795 | S103: 30898 | T103: 371 | U103: 61 | V103: 3355 | W103: 90 | X103: 156 | Y103: 2095 | Z103: 5043 | AA103: 1428 | AB103: 1967 | AC103: 1207 | AD103: 1180 | AE103: 346 | AF103: 2009 | AG103: 2224 | AH103: 1757 | AI103: 2453 | AJ103: 3345 | AK103: 820 | AL103: 843 | AM103: 148 | AN103: 24771 | AO103: 614.33333 | AP103: 1457 | AQ103: 4.9 | AR103: 5.8 | AS103: #N/A | AT103: 73 | AU103: 63 | AV103: 314 | AW103: 47277 | AX103: 63 | AY103: 72.8 | AZ103: 32 | BA103: 353.33333 | BB103: 28304 | BC103: 24457 | BD103: #N/A | BE103: 27090 | BF103: 566 | BG103: 2186 | BH103: 1457
A104: 20041 | B104: 5970 | C104: 22479 | D104: 28449 | E104: 5534 | F104: 22915 | G104: 21 | H104: 79 | I104: 19.5 | J104: 80.5 | K104: 79 | L104: 219 | M104: 260 | N104: 1267 | O104: 1560 | P104: 1426 | Q104: 365 | R104: 794 | S104: 30976 | T104: 357 | U104: 58 | V104: 3314 | W104: 88 | X104: 155 | Y104: 2111 | Z104: 5034 | AA104: 1420 | AB104: 2009 | AC104: 1203 | AD104: 1174 | AE104: 356 | AF104: 2003 | AG104: 2252 | AH104: 1769 | AI104: 2474 | AJ104: 3373 | AK104: 817 | AL104: 836 | AM104: 175 | AN104: 24894 | AO104: 593 | AP104: 1434 | AQ104: 4.8 | AR104: 5.9 | AS104: #N/A | AT104: 64 | AU104: 63 | AV104: 307 | AW104: 47368 | AX104: 63.1 | AY104: 73 | AZ104: 32.1 | BA104: 354 | BB104: 28459 | BC104: 24622 | BD104: #N/A | BE104: 27163 | BF104: 571 | BG104: 2133 | BH104: 1434
... A107: 20044 | B107: 6039 | C107: 22687 | D107: 28726 | E107: 5597 | F107: 23129 | G107: 21 | H107: 79 | I107: 19.5 | J107: 80.5 | K107: 75 | L107: 214 | M107: 267 | N107: 1278 | O107: 1576 | P107: 1456 | Q107: 368 | R107: 805 | S107: 31215 | T107: 373 | U107: 59 | V107: 3207 | W107: 77 | X107: 158 | Y107: 2184 | Z107: 5065 | AA107: 1444 | AB107: 2021 | AC107: 1164 | AD107: 1172 | AE107: 369 | AF107: 2036 | AG107: 2342 | AH107: 1779 | AI107: 2493 | AJ107: 3471 | AK107: 816 | AL107: 827 | AM107: 160 | AN107: 25157 | AO107: 661 | AP107: 1423 | AQ107: 4.7 | AR107: 5.8 | AS107: #N/A | AT107: 60 | AU107: 66 | AV107: 279 | AW107: 47689 | AX107: 63.1 | AY107: 73 | AZ107: 32.2 | BA107: 370.33333 | BB107: 28673 | BC107: 24830 | BD107: #N/A | BE107: 27438 | BF107: 538 | BG107: 2073 | BH107: 1423
A108: 20051 | B108: 6059 | C108: 22700 | D108: 28759 | E108: 5615 | F108: 23144 | G108: 21.1 | H108: 78.9 | I108: 19.5 | J108: 80.5 | K108: 74 | L108: 212 | M108: 271 | N108: 1280 | O108: 1581 | P108: 1466 | Q108: 370 | R108: 807 | S108: 31353 | T108: 396 | U108: 58 | V108: 3174 | W108: 75 | X108: 160 | Y108: 2218 | Z108: 5053 | AA108: 1456 | AB108: 2023 | AC108: 1185 | AD108: 1178 | AE108: 372 | AF108: 2066 | AG108: 2355 | AH108: 1787 | AI108: 2503 | AJ108: 3499 | AK108: 821 | AL108: 827 | AM108: 147 | AN108: 25273 | AO108: 613.66667 | AP108: 1416 | AQ108: 4.7 | AR108: 5.6 | AS108: 1.9333333 | AT108: 58 | AU108: 64 | AV108: 296 | AW108: 47811 | AX108: 63.2 | AY108: 73.1 | AZ108: 32.2 | BA108: 371 | BB108: 28789 | BC108: 24949 | BD108: #N/A | BE108: 27576 | BF108: 568 | BG108: 2040 | BH108: 1416
A109: 20052 | B109: 6090 | C109: 22765 | D109: 28855 | E109: 5646 | F109: 23209 | G109: 21.1 | H109: 78.9 | I109: 19.6 | J109: 80.4 | K109: 72 | L109: 210 | M109: 272 | N109: 1287 | O109: 1583 | P109: 1480 | Q109: 372 | R109: 814 | S109: 31401 | T109: 389 | U109: 58 | V109: 3120 | W109: 73 | X109: 158 | Y109: 2198 | Z109: 5044 | AA109: 1471 | AB109: 2005 | AC109: 1188 | AD109: 1166 | AE109: 389 | AF109: 2105 | AG109: 2376 | AH109: 1786 | AI109: 2517 | AJ109: 3528 | AK109: 849 | AL109: 826 | AM109: 155 | AN109: 25404 | AO109: 645.33333 | AP109: 1437 | AQ109: 4.8 | AR109: 5.2 | AS109: 1.1333333 | AT109: 44 | AU109: 63 | AV109: 313 | AW109: 47932 | AX109: 63.1 | AY109: 72.9 | AZ109: 32.1 | BA109: 375 | BB109: 28802 | BC109: 24974 | BD109: #N/A | BE109: 27624 | BF109: 588 | BG109: 2144 | BH109: 1437
A110: 20053 | B110: 6091 | C110: 22822 | D110: 28913 | E110: 5640 | F110: 23273 | G110: 21.1 | H110: 78.9 | I110: 19.5 | J110: 80.5 | K110: 69 | L110: 208 | M110: 271 | N110: 1284 | O110: 1593 | P110: 1485 | Q110: 366 | R110: 815 | S110: 31543 | T110: 384 | U110: 60 | V110: 3099 | W110: 75 | X110: 158 | Y110: 2236 | Z110: 5053 | AA110: 1479 | AB110: 2012 | AC110: 1186 | AD110: 1162 | AE110: 392 | AF110: 2143 | AG110: 2399 | AH110: 1778 | AI110: 2547 | AJ110: 3549 | AK110: 849 | AL110: 827 | AM110: 155 | AN110: 25531 | AO110: 646 | AP110: 1437 | AQ110: 4.7 | AR110: 6.2 | AS110: 0.46666667 | AT110: 44 | AU110: 58 | AV110: 290 | AW110: 48044 | AX110: 63.2 | AY110: 73 | AZ110: 32.2 | BA110: 382.33333 | BB110: 28928 | BC110: 25066 | BD110: #N/A | BE110: 27732 | BF110: 598 | BG110: 2117 | BH110: 1437
A111: 20054 | B111: 6087 | C111: 22847 | D111: 28934 | E111: 5646 | F111: 23288 | G111: 21 | H111: 79 | I111: 19.5 | J111: 80.5 | K111: 68 | L111: 206 | M111: 274 | N111: 1284 | O111: 1599 | P111: 1488 | Q111: 366 | R111: 801 | S111: 31633 | T111: 386 | U111: 61 | V111: 3085 | W111: 73 | X111: 155 | Y111: 2241 | Z111: 5024 | AA111: 1494 | AB111: 1994 | AC111: 1195 | AD111: 1154 | AE111: 400 | AF111: 2185 | AG111: 2428 | AH111: 1781 | AI111: 2570 | AJ111: 3569 | AK111: 858 | AL111: 837 | AM111: 144 | AN111: 25632 | AO111: 607.66667 | AP111: 1567 | AQ111: 5.1 | AR111: 5.8 | AS111: -0.23333333 | AT111: 46 | AU111: 61 | AV111: 331 | AW111: 48150 | AX111: 63.2 | AY111: 72.7 | AZ111: 32.2 | BA111: 386 | BB111: 28880 | BC111: 24999 | BD111: #N/A | BE111: 27787 | BF111: 606 | BG111: 2129 | BH111: 1567
A112: 20061 | B112: 6072 | C112: 23013 | D112: 29085 | E112: 5631 | F112: 23454 | G112: 20.9 | H112: 79.1 | I112: 19.4 | J112: 80.6 | K112: 67 | L112: 205 | M112: 274 | N112: 1284 | O112: 1603 | P112: 1484 | Q112: 364 | R112: 794 | S112: 31702 | T112: 374 | U112: 59 | V112: 3042 | W112: 73 | X112: 159 | Y112: 2256 | Z112: 5033 | AA112: 1507 | AB112: 2006 | AC112: 1218 | AD112: 1159 | AE112: 412 | AF112: 2191 | AG112: 2423 | AH112: 1783 | AI112: 2586 | AJ112: 3591 | AK112: 859 | AL112: 837 | AM112: 136 | AN112: 25739 | AO112: 571.33333 | AP112: 1604 | AQ112: 5.2 | AR112: 5.9 | AS112: -0.5 | AT112: 39 | AU112: 62 | AV112: 339 | AW112: 48257 | AX112: 63.5 | AY112: 72.9 | AZ112: 32.1 | BA112: 389.66667 | BB112: 29048 | BC112: 25143 | BD112: #N/A | BE112: 27825 | BF112: 620 | BG112: 2101 | BH112: 1604
A113: 20062 | B113: 6061 | C113: 23079 | D113: 29140 | E113: 5623 | F113: 23517 | G113: 20.8 | H113: 79.2 | I113: 19.3 | J113: 80.7 | K113: 67 | L113: 204 | M113: 274 | N113: 1283 | O113: 1609 | P113: 1477 | Q113: 364 | R113: 782 | S113: 31807 | T113: 381 | U113: 63 | V113: 3025 | W113: 77 | X113: 162 | Y113: 2269 | Z113: 5014 | AA113: 1503 | AB113: 2011 | AC113: 1228 | AD113: 1160 | AE113: 416 | AF113: 2196 | AG113: 2448 | AH113: 1780 | AI113: 2592 | AJ113: 3614 | AK113: 881 | AL113: 847 | AM113: 141 | AN113: 25831 | AO113: 607.66667 | AP113: 1685 | AQ113: 5.5 | AR113: 5.4 | AS113: -0.43333333 | AT113: 43 | AU113: 60 | AV113: 361 | AW113: 48364 | AX113: 63.7 | AY113: 72.8 | AZ113: 32 | BA113: 396 | BB113: 29106 | BC113: 25210 | BD113: #N/A | BE113: 27952 | BF113: 623 | BG113: 2159 | BH113: 1685
A114: 20063 | B114: 6045 | C114: 23144 | D114: 29189 | E114: 5601 | F114: 23588 | G114: 20.7 | H114: 79.3 | I114: 19.2 | J114: 80.8 | K114: 62 | L114: 203 | M114: 276 | N114: 1283 | O114: 1611 | P114: 1460 | Q114: 367 | R114: 780 | S114: 31951 | T114: 376 | U114: 69 | V114: 3018 | W114: 79 | X114: 162 | Y114: 2281 | Z114: 5034 | AA114: 1496 | AB114: 2015 | AC114: 1240 | AD114: 1164 | AE114: 421 | AF114: 2228 | AG114: 2479 | AH114: 1780 | AI114: 2583 | AJ114: 3626 | AK114: 898 | AL114: 847 | AM114: 157 | AN114: 25967 | AO114: 634.66667 | AP114: 1693 | AQ114: 5.5 | AR114: 5.4 | AS114: -0.56666667 | AT114: 48 | AU114: 60 | AV114: 390 | AW114: 48481 | AX114: 63.7 | AY114: 72.8 | AZ114: 32 | BA114: 399.33333 | BB114: 29183 | BC114: 25211 | BD114: #N/A | BE114: 28021 | BF114: 646 | BG114: 2162 | BH114: 1693
A115: 20064 | B115: 6037 | C115: 23165 | D115: 29202 | E115: 5582 | F115: 23620 | G115: 20.7 | H115: 79.3 | I115: 19.1 | J115: 80.9 | K115: 62 | L115: 202 | M115: 279 | N115: 1280 | O115: 1611 | P115: 1447 | Q115: 364 | R115: 791 | S115: 32071 | T115: 387 | U115: 67 | V115: 2999 | W115: 83 | X115: 161 | Y115: 2342 | Z115: 5033 | AA115: 1511 | AB115: 2012 | AC115: 1241 | AD115: 1171 | AE115: 425 | AF115: 2256 | AG115: 2522 | AH115: 1780 | AI115: 2585 | AJ115: 3625 | AK115: 873 | AL115: 853 | AM115: 144 | AN115: 26031 | AO115: 618.66667 | AP115: 1701 | AQ115: 5.5 | AR115: 5.2 | AS115: -0.16666667 | AT115: 43 | AU115: 59 | AV115: 397 | AW115: 48602 | AX115: 63.6 | AY115: 72.7 | AZ115: 32.1 | BA115: 406.33333 | BB115: 29214 | BC115: 25217 | BD115: #N/A | BE115: 28107 | BF115: 664 | BG115: 2167 | BH115: 1701
A116: 20071 | B116: 6033 | C116: 23199 | D116: 29232 | E116: 5587 | F116: 23645 | G116: 20.6 | H116: 79.4 | I116: 19.1 | J116: 80.9 | K116: 62 | L116: 199 | M116: 282 | N116: 1276 | O116: 1618 | P116: 1448 | Q116: 363 | R116: 789 | S116: 31996 | T116: 376 | U116: 66 | V116: 2988 | W116: 85 | X116: 160 | Y116: 2318 | Z116: 5033 | AA116: 1501 | AB116: 2005 | AC116: 1245 | AD116: 1174 | AE116: 439 | AF116: 2256 | AG116: 2511 | AH116: 1777 | AI116: 2586 | AJ116: 3630 | AK116: 857 | AL116: 846 | AM116: 144 | AN116: 26004 | AO116: 615.66667 | AP116: 1704 | AQ116: 5.5 | AR116: 6.1 | AS116: 0.56666667 | AT116: 40 | AU116: 62 | AV116: 393 | AW116: 48722 | AX116: 63.4 | AY116: 72.5 | AZ116: 32.1 | BA116: 415.66667 | BB116: 29194 | BC116: 25169 | BD116: #N/A | BE116: 28035 | BF116: 660 | BG116: 2172 | BH116: 1704
A117: 20072 | B117: 6028 | C117: 23324 | D117: 29352 | E117: 5580 | F117: 23772 | G117: 20.5 | H117: 79.5 | I117: 19 | J117: 81 | K117: 61 | L117: 197 | M117: 283 | N117: 1269 | O117: 1623 | P117: 1443 | Q117: 362 | R117: 788 | S117: 32084 | T117: 376 | U117: 69 | V117: 2985 | W117: 85 | X117: 158 | Y117: 2325 | Z117: 5058 | AA117: 1510 | AB117: 1997 | AC117: 1250 | AD117: 1180 | AE117: 445 | AF117: 2271 | AG117: 2548 | AH117: 1778 | AI117: 2600 | AJ117: 3602 | AK117: 864 | AL117: 837 | AM117: 145 | AN117: 26086 | AO117: 662.66667 | AP117: 1658 | AQ117: 5.4 | AR117: 4.6 | AS117: 1.4 | AT117: 53 | AU117: 62 | AV117: 396 | AW117: 48843 | AX117: 63.4 | AY117: 72.7 | AZ117: 32.2 | BA117: 414.33333 | BB117: 29322 | BC117: 25310 | BD117: #N/A | BE117: 28110 | BF117: 682 | BG117: 2174 | BH117: 1658
A118: 20073 | B118: 6018 | C118: 23452 | D118: 29470 | E118: 5564 | F118: 23906 | G118: 20.4 | H118: 79.6 | I118: 18.9 | J118: 81.1 | K118: 61 | L118: 195 | M118: 284 | N118: 1269 | O118: 1628 | P118: 1444 | Q118: 360 | R118: 774 | S118: 32221 | T118: 379 | U118: 69 | V118: 2973 | W118: 88 | X118: 157 | Y118: 2350 | Z118: 5053 | AA118: 1519 | AB118: 2026 | AC118: 1245 | AD118: 1181 | AE118: 465 | AF118: 2307 | AG118: 2588 | AH118: 1771 | AI118: 2585 | AJ118: 3616 | AK118: 870 | AL118: 817 | AM118: 161 | AN118: 26204 | AO118: 706 | AP118: 1650 | AQ118: 5.3 | AR118: 5.1 | AS118: 1.7333333 | AT118: 66 | AU118: 65 | AV118: 391 | AW118: 48962 | AX118: 63.5 | AY118: 72.7 | AZ118: 32.1 | BA118: 421.66667 | BB118: 29420 | BC118: 25380 | BD118: #N/A | BE118: 28231 | BF118: 694 | BG118: 2176 | BH118: 1650
A119: 20074 | B119: 6023 | C119: 23591 | D119: 29614 | E119: 5553 | F119: 24061 | G119: 20.3 | H119: 79.7 | I119: 18.8 | J119: 81.2 | K119: 59 | L119: 195 | M119: 284 | N119: 1257 | O119: 1634 | P119: 1447 | Q119: 354 | R119: 792 | S119: 32259 | T119: 376 | U119: 67 | V119: 2931 | W119: 85 | X119: 160 | Y119: 2329 | Z119: 5081 | AA119: 1528 | AB119: 2043 | AC119: 1235 | AD119: 1185 | AE119: 470 | AF119: 2308 | AG119: 2607 | AH119: 1767 | AI119: 2595 | AJ119: 3626 | AK119: 865 | AL119: 827 | AM119: 171 | AN119: 26309 | AO119: 685 | AP119: 1608 | AQ119: 5.2 | AR119: 4.3 | AS119: 1.1 | AT119: 48 | AU119: 67 | AV119: 384 | AW119: 49079 | AX119: 63.5 | AY119: 72.9 | AZ119: 31.9 | BA119: 423.66667 | BB119: 29576 | BC119: 25521 | BD119: #N/A | BE119: 28277 | BF119: 729 | BG119: 2175 | BH119: 1608
... A145: 20142 | B145: 5737 | C145: 25033 | D145: 30770 | E145: 5271 | F145: 25499 | G145: 18.6 | H145: 81.4 | I145: 17.1 | J145: 82.9 | K145: 43 | L145: 164 | M145: 256 | N145: 1059 | O145: 1694 | P145: 1528 | Q145: 322 | R145: 668 | S145: 33446 | T145: 437 | U145: 66 | V145: 2621 | W145: 115 | X145: 197 | Y145: 2125 | Z145: 4936 | AA145: 1511 | AB145: 2193 | AC145: 1355 | AD145: 1132 | AE145: 550 | AF145: 2826 | AG145: 2818 | AH145: 1540 | AI145: 2887 | AJ145: 4203 | AK145: 946 | AL145: 893 | AM145: 95 | AN145: 27885 | AO145: 669.33333 | AP145: 2061 | AQ145: 6.3 | AR145: 4.4 | AS145: 0.63333333 | AT145: 72 | AU145: 52 | AV145: 740 | AW145: 51710 | AX145: 63.5 | AY145: 72.8 | AZ145: 32.2 | BA145: 465.33333 | BB145: 30771 | BC145: 25858 | BD145: #N/A | BE145: 28660 | BF145: 1347 | BG145: 2303 | BH145: 2061
A146: 20143 | B146: 5722 | C146: 25192 | D146: 30914 | E146: 5258 | F146: 25656 | G146: 18.5 | H146: 81.5 | I146: 17 | J146: 83 | K146: 43 | L146: 163 | M146: 256 | N146: 1053 | O146: 1689 | P146: 1534 | Q146: 319 | R146: 663 | S146: 33575 | T146: 444 | U146: 68 | V146: 2640 | W146: 121 | X146: 195 | Y146: 2134 | Z146: 4961 | AA146: 1534 | AB146: 2197 | AC146: 1361 | AD146: 1128 | AE146: 539 | AF146: 2813 | AG146: 2842 | AH146: 1530 | AI146: 2884 | AJ146: 4222 | AK146: 970 | AL146: 908 | AM146: 84 | AN146: 27973 | AO146: 699.66667 | AP146: 1962 | AQ146: 6 | AR146: 3.5 | AS146: 1.3666667 | AT146: 72 | AU146: 58 | AV146: 690 | AW146: 51807 | AX146: 63.4 | AY146: 73 | AZ146: 32.2 | BA146: 465 | BB146: 30899 | BC146: 26058 | BD146: 26831444 | BE146: 28812 | BF146: 1336 | BG146: 2279 | BH146: 1962
A147: 20144 | B147: 5711 | C147: 25356 | D147: 31067 | E147: 5254 | F147: 25813 | G147: 18.4 | H147: 81.6 | I147: 16.9 | J147: 83.1 | K147: 42 | L147: 162 | M147: 255 | N147: 1045 | O147: 1691 | P147: 1538 | Q147: 314 | R147: 663 | S147: 33686 | T147: 420 | U147: 70 | V147: 2631 | W147: 125 | X147: 194 | Y147: 2153 | Z147: 4979 | AA147: 1560 | AB147: 2204 | AC147: 1365 | AD147: 1113 | AE147: 566 | AF147: 2840 | AG147: 2894 | AH147: 1519 | AI147: 2902 | AJ147: 4223 | AK147: 943 | AL147: 904 | AM147: 79 | AN147: 28094 | AO147: 709.66667 | AP147: 1870 | AQ147: 5.7 | AR147: 4.1 | AS147: 1.7 | AT147: 67 | AU147: 55 | AV147: 638 | AW147: 51903 | AX147: 63.3 | AY147: 73.2 | AZ147: 32.2 | BA147: 472.33333 | BB147: 31008 | BC147: 26216 | BD147: 26969918 | BE147: 28973 | BF147: 1310 | BG147: 2280 | BH147: 1870
A148: 20151 | B148: 5689 | C148: 25501 | D148: 31190 | E148: 5244 | F148: 25946 | G148: 18.2 | H148: 81.8 | I148: 16.8 | J148: 83.2 | K148: 40 | L148: 160 | M148: 255 | N148: 1034 | O148: 1688 | P148: 1545 | Q148: 308 | R148: 656 | S148: 33806 | T148: 390 | U148: 75 | V148: 2650 | W148: 132 | X148: 195 | Y148: 2141 | Z148: 5032 | AA148: 1544 | AB148: 2209 | AC148: 1388 | AD148: 1118 | AE148: 556 | AF148: 2891 | AG148: 2870 | AH148: 1503 | AI148: 2936 | AJ148: 4223 | AK148: 955 | AL148: 932 | AM148: 66 | AN148: 28223 | AO148: 707 | AP148: 1826 | AQ148: 5.5 | AR148: 4.2 | AS148: 1.5333333 | AT148: 69 | AU148: 65 | AV148: 589 | AW148: 52000 | AX148: 63.5 | AY148: 73.4 | AZ148: 32.1 | BA148: 474 | BB148: 31218 | BC148: 26409 | BD148: 27222686 | BE148: 29198 | BF148: 1325 | BG148: 2309 | BH148: 1826
A149: 20152 | B149: 5671 | C149: 25576 | D149: 31247 | E149: 5228 | F149: 26019 | G149: 18.1 | H149: 81.9 | I149: 16.7 | J149: 83.3 | K149: 40 | L149: 159 | M149: 254 | N149: 1020 | O149: 1689 | P149: 1551 | Q149: 305 | R149: 655 | S149: 33892 | T149: 388 | U149: 74 | V149: 2641 | W149: 133 | X149: 200 | Y149: 2121 | Z149: 5010 | AA149: 1611 | AB149: 2241 | AC149: 1384 | AD149: 1112 | AE149: 569 | AF149: 2914 | AG149: 2851 | AH149: 1491 | AI149: 2952 | AJ149: 4242 | AK149: 988 | AL149: 901 | AM149: 68 | AN149: 28335 | AO149: 737 | AP149: 1848 | AQ149: 5.6 | AR149: 4.3 | AS149: 1.6333333 | AT149: 81 | AU149: 65 | AV149: 577 | AW149: 52096 | AX149: 63.4 | AY149: 73.4 | AZ149: 32.1 | BA149: 478.66667 | BB149: 31170 | BC149: 26385 | BD149: 27400933 | BE149: 29279 | BF149: 1291 | BG149: 2337 | BH149: 1848
A150: 20153 | B150: 5659 | C150: 25838 | D150: 31497 | E150: 5216 | F150: 26281 | G150: 18 | H150: 82 | I150: 16.6 | J150: 83.4 | K150: 38 | L150: 159 | M150: 252 | N150: 1016 | O150: 1682 | P150: 1559 | Q150: 302 | R150: 652 | S150: 34083 | T150: 428 | U150: 67 | V150: 2620 | W150: 134 | X150: 201 | Y150: 2183 | Z150: 5024 | AA150: 1615 | AB150: 2267 | AC150: 1381 | AD150: 1109 | AE150: 564 | AF150: 2949 | AG150: 2919 | AH150: 1478 | AI150: 2957 | AJ150: 4222 | AK150: 983 | AL150: 923 | AM150: 58 | AN150: 28451 | AO150: 755 | AP150: 1760 | AQ150: 5.3 | AR150: 4.2 | AS150: 2.3 | AT150: 72 | AU150: 63 | AV150: 516 | AW150: 52196 | AX150: 63.5 | AY150: 73.7 | AZ150: 31.9 | BA150: 480.66667 | BB150: 31393 | BC150: 26554 | BD150: 27564772 | BE150: 29405 | BF150: 1255 | BG150: 2261 | BH150: 1760
...

Sheet DataA
B1: =DataQ!F1 -> JAN010B.db | C1: =DataQ!G1 -> JAN010B.db | D1: =DataQ!H1 -> JAN010B.db | E1: =DataQ!I1 -> JAN010B.db | F1: =DataQ!J1 -> JAN010B.db | G1: =DataQ!K1 -> JAN010B.db | H1: =DataQ!L1 -> JAN010B.db | I1: =DataQ!M1 -> JAN010B.db | J1: =DataQ!N1 -> JAN010B.db
B2: =DataQ!F2 -> UK | C2: =DataQ!G2 -> UK | D2: =DataQ!H2 -> UK | E2: =DataQ!I2 -> UK | F2: =DataQ!J2 -> UK | G2: =DataQ!K2 -> UK | H2: =DataQ!L2 -> UK | I2: =DataQ!M2 -> UK | J2: =DataQ!N2 -> UK
B3: =DataQ!F3 -> WC | C3: =DataQ!G3 -> TP | D3: =DataQ!H3 -> WAGEWKLY | E3: =DataQ!I3 -> COGTP | F3: =DataQ!J3 -> GDP! | G3: =DataQ!K3 -> PEWFP | H3: =DataQ!L3 -> PEDY! | I3: =DataQ!M3 -> PEDY | J3: =DataQ!N3 -> PC
B4: =DataQ!F4 -> GBR | C4: =DataQ!G4 -> GBR | D4: =DataQ!H4 -> GBR | E4: =DataQ!I4 -> GBR | F4: =DataQ!J4 -> GBR | G4: =DataQ!K4 -> GBR | H4: =DataQ!L4 -> GBR | I4: =DataQ!M4 -> GBR | J4: =DataQ!N4 -> GBR
B5: =DataQ!F5 -> L | C5: =DataQ!G5 -> L | D5: =DataQ!H5 -> L | E5: =DataQ!I5 -> L | F5: =DataQ!J5 -> L | G5: =DataQ!K5 -> L | H5: =DataQ!L5 -> L | I5: =DataQ!M5 -> L | J5: =DataQ!N5 -> L
B6: =DataQ!F6 -> 202403 | C6: =DataQ!G6 -> 202403 | D6: =DataQ!H6 -> 202403 | E6: =DataQ!I6 -> 202403 | F6: =DataQ!J6 -> 202403 | G6: =DataQ!K6 -> 202403 | H6: =DataQ!L6 -> 202403 | I6: =DataQ!M6 -> 202403 | J6: =DataQ!N6 -> 202403
A7: 1973 | B7: =AVERAGEIF(DataQ!$B:$B,DataA!$A7,DataQ!F:F) -> 11.970672 | C7: =SUMIF(DataQ!$B:$B,DataA!$A7,DataQ!G:G) -> 2309.3419 | D7: =AVERAGEIF(DataQ!$B:$B,DataA!$A7,DataQ!H:H) -> 15.940815 | E7: =SUMIF(DataQ!$B:$B,DataA!$A7,DataQ!I:I) -> 17908 | F7: =SUMIF(DataQ!$B:$B,DataA!$A7,DataQ!J:J) -> 81793 | G7: =SUMIF(DataQ!$B:$B,DataA!$A7,DataQ!K:K) -> 39478 | H7: =SUMIF(DataQ!$B:$B,DataA!$A7,DataQ!L:L) -> 52432 | I7: =SUMIF(DataQ!$B:$B,DataA!$A7,DataQ!M:M) -> 560418 | J7: =AVERAGEIF(DataQ!$B:$B,DataA!$A7,DataQ!N:N) -> 9.5139817
A8: 1974 | B8: =AVERAGEIF(DataQ!$B:$B,DataA!$A8,DataQ!F:F) -> 14.668508 | C8: =SUMIF(DataQ!$B:$B,DataA!$A8,DataQ!G:G) -> 3137.9616 | D8: =AVERAGEIF(DataQ!$B:$B,DataA!$A8,DataQ!H:H) -> 19.300352 | E8: =SUMIF(DataQ!$B:$B,DataA!$A8,DataQ!I:I) -> 16624 | F8: =SUMIF(DataQ!$B:$B,DataA!$A8,DataQ!J:J) -> 92673 | G8: =SUMIF(DataQ!$B:$B,DataA!$A8,DataQ!K:K) -> 46712 | H8: =SUMIF(DataQ!$B:$B,DataA!$A8,DataQ!L:L) -> 61570 | I8: =SUMIF(DataQ!$B:$B,DataA!$A8,DataQ!M:M) -> 555668 | J8: =AVERAGEIF(DataQ!$B:$B,DataA!$A8,DataQ!N:N) -> 11.254465
A9: 1975 | B9: =AVERAGEIF(DataQ!$B:$B,DataA!$A9,DataQ!F:F) -> 19.486995 | C9: =SUMIF(DataQ!$B:$B,DataA!$A9,DataQ!G:G) -> 4573.711 | D9: =AVERAGEIF(DataQ!$B:$B,DataA!$A9,DataQ!H:H) -> 25.941457 | E9: =SUMIF(DataQ!$B:$B,DataA!$A9,DataQ!I:I) -> 17697 | F9: =SUMIF(DataQ!$B:$B,DataA!$A9,DataQ!J:J) -> 115093 | G9: =SUMIF(DataQ!$B:$B,DataA!$A9,DataQ!K:K) -> 60461 | H9: =SUMIF(DataQ!$B:$B,DataA!$A9,DataQ!L:L) -> 76602 | I9: =SUMIF(DataQ!$B:$B,DataA!$A9,DataQ!M:M) -> 560371 | J9: =AVERAGEIF(DataQ!$B:$B,DataA!$A9,DataQ!N:N) -> 13.886603
A10: 1976 | B10: =AVERAGEIF(DataQ!$B:$B,DataA!$A10,DataQ!F:F) -> 21.511143 | C10: =SUMIF(DataQ!$B:$B,DataA!$A10,DataQ!G:G) -> 5695.777 | D10: =AVERAGEIF(DataQ!$B:$B,DataA!$A10,DataQ!H:H) -> 31.409385 | E10: =SUMIF(DataQ!$B:$B,DataA!$A10,DataQ!I:I) -> 22080 | F10: =SUMIF(DataQ!$B:$B,DataA!$A10,DataQ!J:J) -> 136999 | G10: =SUMIF(DataQ!$B:$B,DataA!$A10,DataQ!K:K) -> 67888 | H10: =SUMIF(DataQ!$B:$B,DataA!$A10,DataQ!L:L) -> 89189 | I10: =SUMIF(DataQ!$B:$B,DataA!$A10,DataQ!M:M) -> 559606 | J10: =AVERAGEIF(DataQ!$B:$B,DataA!$A10,DataQ!N:N) -> 16.170227
A11: 1977 | B11: =AVERAGEIF(DataQ!$B:$B,DataA!$A11,DataQ!F:F) -> 23.278238 | C11: =SUMIF(DataQ!$B:$B,DataA!$A11,DataQ!G:G) -> 6401.847 | D11: =AVERAGEIF(DataQ!$B:$B,DataA!$A11,DataQ!H:H) -> 35.091777 | E11: =SUMIF(DataQ!$B:$B,DataA!$A11,DataQ!I:I) -> 31652 | F11: =SUMIF(DataQ!$B:$B,DataA!$A11,DataQ!J:J) -> 159786 | G11: =SUMIF(DataQ!$B:$B,DataA!$A11,DataQ!K:K) -> 75102 | H11: =SUMIF(DataQ!$B:$B,DataA!$A11,DataQ!L:L) -> 100772 | I11: =SUMIF(DataQ!$B:$B,DataA!$A11,DataQ!M:M) -> 549407 | J11: =AVERAGEIF(DataQ!$B:$B,DataA!$A11,DataQ!N:N) -> 18.608693
A12: 1978 | B12: =AVERAGEIF(DataQ!$B:$B,DataA!$A12,DataQ!F:F) -> 25.498162 | C12: =SUMIF(DataQ!$B:$B,DataA!$A12,DataQ!G:G) -> 6823.465 | D12: =AVERAGEIF(DataQ!$B:$B,DataA!$A12,DataQ!H:H) -> 40.728302 | E12: =SUMIF(DataQ!$B:$B,DataA!$A12,DataQ!I:I) -> 38107 | F12: =SUMIF(DataQ!$B:$B,DataA!$A12,DataQ!J:J) -> 186158 | G12: =SUMIF(DataQ!$B:$B,DataA!$A12,DataQ!K:K) -> 85868 | H12: =SUMIF(DataQ!$B:$B,DataA!$A12,DataQ!L:L) -> 118869 | I12: =SUMIF(DataQ!$B:$B,DataA!$A12,DataQ!M:M) -> 589523 | J12: =AVERAGEIF(DataQ!$B:$B,DataA!$A12,DataQ!N:N) -> 20.471267
A13: 1979 | B13: =AVERAGEIF(DataQ!$B:$B,DataA!$A13,DataQ!F:F) -> 28.840083 | C13: =SUMIF(DataQ!$B:$B,DataA!$A13,DataQ!G:G) -> 7745.402 | D13: =AVERAGEIF(DataQ!$B:$B,DataA!$A13,DataQ!H:H) -> 48.39366 | E13: =SUMIF(DataQ!$B:$B,DataA!$A13,DataQ!I:I) -> 44855 | F13: =SUMIF(DataQ!$B:$B,DataA!$A13,DataQ!J:J) -> 220981 | G13: =SUMIF(DataQ!$B:$B,DataA!$A13,DataQ!K:K) -> 100636 | H13: =SUMIF(DataQ!$B:$B,DataA!$A13,DataQ!L:L) -> 143321 | I13: =SUMIF(DataQ!$B:$B,DataA!$A13,DataQ!M:M) -> 624803 | J13: =AVERAGEIF(DataQ!$B:$B,DataA!$A13,DataQ!N:N) -> 23.29502
A14: 1980 | B14: =AVERAGEIF(DataQ!$B:$B,DataA!$A14,DataQ!F:F) -> 35.068723 | C14: =SUMIF(DataQ!$B:$B,DataA!$A14,DataQ!G:G) -> 9230.621 | D14: =AVERAGEIF(DataQ!$B:$B,DataA!$A14,DataQ!H:H) -> 61.12267 | E14: =SUMIF(DataQ!$B:$B,DataA!$A14,DataQ!I:I) -> 49635 | F14: =SUMIF(DataQ!$B:$B,DataA!$A14,DataQ!J:J) -> 259970 | G14: =SUMIF(DataQ!$B:$B,DataA!$A14,DataQ!K:K) -> 119333 | H14: =SUMIF(DataQ!$B:$B,DataA!$A14,DataQ!L:L) -> 170405 | I14: =SUMIF(DataQ!$B:$B,DataA!$A14,DataQ!M:M) -> 635239 | J14: =AVERAGEIF(DataQ!$B:$B,DataA!$A14,DataQ!N:N) -> 27.228993
A15: 1981 | B15: =AVERAGEIF(DataQ!$B:$B,DataA!$A15,DataQ!F:F) -> 38.409098 | C15: =SUMIF(DataQ!$B:$B,DataA!$A15,DataQ!G:G) -> 9909.708 | D15: =AVERAGEIF(DataQ!$B:$B,DataA!$A15,DataQ!H:H) -> 71.618053 | E15: =SUMIF(DataQ!$B:$B,DataA!$A15,DataQ!I:I) -> 55572 | F15: =SUMIF(DataQ!$B:$B,DataA!$A15,DataQ!J:J) -> 290180 | G15: =SUMIF(DataQ!$B:$B,DataA!$A15,DataQ!K:K) -> 127973 | H15: =SUMIF(DataQ!$B:$B,DataA!$A15,DataQ!L:L) -> 191355 | I15: =SUMIF(DataQ!$B:$B,DataA!$A15,DataQ!M:M) -> 634794 | J15: =AVERAGEIF(DataQ!$B:$B,DataA!$A15,DataQ!N:N) -> 30.594298
A16: 1982 | B16: =AVERAGEIF(DataQ!$B:$B,DataA!$A16,DataQ!F:F) -> 40.033453 | C16: =SUMIF(DataQ!$B:$B,DataA!$A16,DataQ!G:G) -> 10505.595 | D16: =AVERAGEIF(DataQ!$B:$B,DataA!$A16,DataQ!H:H) -> 80.275882 | E16: =SUMIF(DataQ!$B:$B,DataA!$A16,DataQ!I:I) -> 65451 | F16: =SUMIF(DataQ!$B:$B,DataA!$A16,DataQ!J:J) -> 319558 | G16: =SUMIF(DataQ!$B:$B,DataA!$A16,DataQ!K:K) -> 136108 | H16: =SUMIF(DataQ!$B:$B,DataA!$A16,DataQ!L:L) -> 209792 | I16: =SUMIF(DataQ!$B:$B,DataA!$A16,DataQ!M:M) -> 637451 | J16: =AVERAGEIF(DataQ!$B:$B,DataA!$A16,DataQ!N:N) -> 33.417687
A17: 1983 | B17: =AVERAGEIF(DataQ!$B:$B,DataA!$A17,DataQ!F:F) -> 41.082815 | C17: =SUMIF(DataQ!$B:$B,DataA!$A17,DataQ!G:G) -> 11845.776 | D17: =AVERAGEIF(DataQ!$B:$B,DataA!$A17,DataQ!H:H) -> 88.73282 | E17: =SUMIF(DataQ!$B:$B,DataA!$A17,DataQ!I:I) -> 77853 | F17: =SUMIF(DataQ!$B:$B,DataA!$A17,DataQ!J:J) -> 351347 | G17: =SUMIF(DataQ!$B:$B,DataA!$A17,DataQ!K:K) -> 145939 | H17: =SUMIF(DataQ!$B:$B,DataA!$A17,DataQ!L:L) -> 226975 | I17: =SUMIF(DataQ!$B:$B,DataA!$A17,DataQ!M:M) -> 651689 | J17: =AVERAGEIF(DataQ!$B:$B,DataA!$A17,DataQ!N:N) -> 35.36142
A18: 1984 | B18: =AVERAGEIF(DataQ!$B:$B,DataA!$A18,DataQ!F:F) -> 42.960532 | C18: =SUMIF(DataQ!$B:$B,DataA!$A18,DataQ!G:G) -> 12669.9 | D18: =AVERAGEIF(DataQ!$B:$B,DataA!$A18,DataQ!H:H) -> 95.596452 | E18: =SUMIF(DataQ!$B:$B,DataA!$A18,DataQ!I:I) -> 84738 | F18: =SUMIF(DataQ!$B:$B,DataA!$A18,DataQ!J:J) -> 377920 | G18: =SUMIF(DataQ!$B:$B,DataA!$A18,DataQ!K:K) -> 156357 | H18: =SUMIF(DataQ!$B:$B,DataA!$A18,DataQ!L:L) -> 247782 | I18: =SUMIF(DataQ!$B:$B,DataA!$A18,DataQ!M:M) -> 675496 | J18: =AVERAGEIF(DataQ!$B:$B,DataA!$A18,DataQ!N:N) -> 37.241058
... A94: 2060 | B94: =AVERAGEIF(DataQ!$B:$B,DataA!$A94,DataQ!F:F) -> 317.22028 | C94: =SUMIF(DataQ!$B:$B,DataA!$A94,DataQ!G:G) -> 652982 | D94: =AVERAGEIF(DataQ!$B:$B,DataA!$A94,DataQ!H:H) -> 2103.2103 | E94: =SUMIF(DataQ!$B:$B,DataA!$A94,DataQ!I:I) -> 2249182 | F94: =SUMIF(DataQ!$B:$B,DataA!$A94,DataQ!J:J) -> 10494228 | G94: =SUMIF(DataQ!$B:$B,DataA!$A94,DataQ!K:K) -> 4125109 | H94: =SUMIF(DataQ!$B:$B,DataA!$A94,DataQ!L:L) -> 6423381 | I94: =SUMIF(DataQ!$B:$B,DataA!$A94,DataQ!M:M) -> 2831784.8 | J94: =AVERAGEIF(DataQ!$B:$B,DataA!$A94,DataQ!N:N) -> 226.79618

Sheet DataQ
F1: JAN010B.db | G1: =$F$1 -> JAN010B.db | H1: =$F$1 -> JAN010B.db | I1: =$F$1 -> JAN010B.db | J1: =$F$1 -> JAN010B.db | K1: =$F$1 -> JAN010B.db | L1: =$F$1 -> JAN010B.db | M1: =$F$1 -> JAN010B.db | N1: =$F$1 -> JAN010B.db | O1: =$F$1 -> JAN010B.db | P1: FEB019C.db | Q1: OCT010I.db
F2: UK | G2: UK | H2: UK | I2: UK | J2: UK | K2: UK | L2: UK | M2: UK | N2: UK | O2: UK | P2: UK | Q2: UK
F3: WC | G3: TP | H3: WAGEWKLY | I3: COGTP | J3: GDP! | K3: PEWFP | L3: PEDY! | M3: PEDY | N3: PC | O3: ETILO | P3: ETILO | Q3: ETILO
F4: GBR | G4: GBR | H4: GBR | I4: GBR | J4: GBR | K4: GBR | L4: GBR | M4: GBR | N4: GBR | O4: GBR | P4: GBR | Q4: GBR
F5: L | G5: L | H5: L | I5: L | J5: L | K5: L | L5: L | M5: L | N5: L | O5: L | P5: L | Q5: L
B6: CYs | C6: FYs | D6: FY end | E6: =E358+5 -> 2329 | F6: {=_xlfn.CONCAT(INDEX(GMWQ!$A$2:$NE$60,MATCH(1,(GMWQ!$NE$2:$NE$60=F$3)*(GMWQ!$ND$2:$ND$60=F$4)*(GMWQ!$NF$2:$NF$60=F$1),0),$E6-1966),"0",(INDEX(GMWQ!$A$2:$NE$60,MATCH(1,(GMWQ!$NE$2:$NE$60=F$3)*(GMWQ!$ND$2:$ND$60=F$4)*(GMWQ!$NF$2:$NF$60=F$1),0),$E6-1965)))} -> 202403 | G6: {=_xlfn.CONCAT(INDEX(GMWQ!$A$2:$NE$60,MATCH(1,(GMWQ!$NE$2:$NE$60=G$3)*(GMWQ!$ND$2:$ND$60=G$4)*(GMWQ!$NF$2:$NF$60=G$1),0),$E6-1966),"0",(INDEX(GMWQ!$A$2:$NE$60,MATCH(1,(GMWQ!$NE$2:$NE$60=G$3)*(GMWQ!$ND$2:$ND$60=G$4)*(GMWQ!$NF$2:$NF$60=G$1),0),$E6-1965)))} -> 202403 | H6: {=_xlfn.CONCAT(INDEX(GMWQ!$A$2:$NE$60,MATCH(1,(GMWQ!$NE$2:$NE$60=H$3)*(GMWQ!$ND$2:$ND$60=H$4)*(GMWQ!$NF$2:$NF$60=H$1),0),$E6-1966),"0",(INDEX(GMWQ!$A$2:$NE$60,MATCH(1,(GMWQ!$NE$2:$NE$60=H$3)*(GMWQ!$ND$2:$ND$60=H$4)*(GMWQ!$NF$2:$NF$60=H$1),0),$E6-1965)))} -> 202403 | I6: {=_xlfn.CONCAT(INDEX(GMWQ!$A$2:$NE$60,MATCH(1,(GMWQ!$NE$2:$NE$60=I$3)*(GMWQ!$ND$2:$ND$60=I$4)*(GMWQ!$NF$2:$NF$60=I$1),0),$E6-1966),"0",(INDEX(GMWQ!$A$2:$NE$60,MATCH(1,(GMWQ!$NE$2:$NE$60=I$3)*(GMWQ!$ND$2:$ND$60=I$4)*(GMWQ!$NF$2:$NF$60=I$1),0),$E6-1965)))} -> 202403 | J6: {=_xlfn.CONCAT(INDEX(GMWQ!$A$2:$NE$60,MATCH(1,(GMWQ!$NE$2:$NE$60=J$3)*(GMWQ!$ND$2:$ND$60=J$4)*(GMWQ!$NF$2:$NF$60=J$1),0),$E6-1966),"0",(INDEX(GMWQ!$A$2:$NE$60,MATCH(1,(GMWQ!$NE$2:$NE$60=J$3)*(GMWQ!$ND$2:$ND$60=J$4)*(GMWQ!$NF$2:$NF$60=J$1),0),$E6-1965)))} -> 202403 | K6: {=_xlfn.CONCAT(INDEX(GMWQ!$A$2:$NE$60,MATCH(1,(GMWQ!$NE$2:$NE$60=K$3)*(GMWQ!$ND$2:$ND$60=K$4)*(GMWQ!$NF$2:$NF$60=K$1),0),$E6-1966),"0",(INDEX(GMWQ!$A$2:$NE$60,MATCH(1,(GMWQ!$NE$2:$NE$60=K$3)*(GMWQ!$ND$2:$ND$60=K$4)*(GMWQ!$NF$2:$NF$60=K$1),0),$E6-1965)))} -> 202403 | L6: {=_xlfn.CONCAT(INDEX(GMWQ!$A$2:$NE$60,MATCH(1,(GMWQ!$NE$2:$NE$60=L$3)*(GMWQ!$ND$2:$ND$60=L$4)*(GMWQ!$NF$2:$NF$60=L$1),0),$E6-1966),"0",(INDEX(GMWQ!$A$2:$NE$60,MATCH(1,(GMWQ!$NE$2:$NE$60=L$3)*(GMWQ!$ND$2:$ND$60=L$4)*(GMWQ!$NF$2:$NF$60=L$1),0),$E6-1965)))} -> 202403 | M6: {=_xlfn.CONCAT(INDEX(GMWQ!$A$2:$NE$60,MATCH(1,(GMWQ!$NE$2:$NE$60=M$3)*(GMWQ!$ND$2:$ND$60=M$4)*(GMWQ!$NF$2:$NF$60=M$1),0),$E6-1966),"0",(INDEX(GMWQ!$A$2:$NE$60,MATCH(1,(GMWQ!$NE$2:$NE$60=M$3)*(GMWQ!$ND$2:$ND$60=M$4)*(GMWQ!$NF$2:$NF$60=M$1),0),$E6-1965)))} -> 202403 | ... Q6: {=_xlfn.CONCAT(INDEX(GMWQ!$A$2:$NE$60,MATCH(1,(GMWQ!$NE$2:$NE$60=Q$3)*(GMWQ!$ND$2:$ND$60=Q$4)*(GMWQ!$NF$2:$NF$60=Q$1),0),$E6-1966),"0",(INDEX(GMWQ!$A$2:$NE$60,MATCH(1,(GMWQ!$NE$2:$NE$60=Q$3)*(GMWQ!$ND$2:$ND$60=Q$4)*(GMWQ!$NF$2:$NF$60=Q$1),0),$E6-1965)))} -> 202302
A7: 1973 | B7: 1973 | E7: 1973 | F7: {=INDEX(GMWQ!$A$2:$NF$60,MATCH(1,(GMWQ!$NE$2:$NE$60=F$3)*(GMWQ!$ND$2:$ND$60=F$4)*(GMWQ!$NF$2:$NF$60=F$1),0),$E7-1966)} -> 11.31073 | G7: {=INDEX(GMWQ!$A$2:$NF$60,MATCH(1,(GMWQ!$NE$2:$NE$60=G$3)*(GMWQ!$ND$2:$ND$60=G$4)*(GMWQ!$NF$2:$NF$60=G$1),0),$E7-1966)} -> 552.0384 | H7: {=INDEX(GMWQ!$A$2:$NF$60,MATCH(1,(GMWQ!$NE$2:$NE$60=H$3)*(GMWQ!$ND$2:$ND$60=H$4)*(GMWQ!$NF$2:$NF$60=H$1),0),$E7-1966)} -> 14.85115 | I7: {=INDEX(GMWQ!$A$2:$NF$60,MATCH(1,(GMWQ!$NE$2:$NE$60=I$3)*(GMWQ!$ND$2:$ND$60=I$4)*(GMWQ!$NF$2:$NF$60=I$1),0),$E7-1966)} -> 4698 | J7: {=INDEX(GMWQ!$A$2:$NF$60,MATCH(1,(GMWQ!$NE$2:$NE$60=J$3)*(GMWQ!$ND$2:$ND$60=J$4)*(GMWQ!$NF$2:$NF$60=J$1),0),$E7-1966)} -> 20046 | K7: {=INDEX(GMWQ!$A$2:$NF$60,MATCH(1,(GMWQ!$NE$2:$NE$60=K$3)*(GMWQ!$ND$2:$ND$60=K$4)*(GMWQ!$NF$2:$NF$60=K$1),0),$E7-1966)} -> 9375 | L7: {=INDEX(GMWQ!$A$2:$NF$60,MATCH(1,(GMWQ!$NE$2:$NE$60=L$3)*(GMWQ!$ND$2:$ND$60=L$4)*(GMWQ!$NF$2:$NF$60=L$1),0),$E7-1966)} -> 12419 | M7: {=INDEX(GMWQ!$A$2:$NF$60,MATCH(1,(GMWQ!$NE$2:$NE$60=M$3)*(GMWQ!$ND$2:$ND$60=M$4)*(GMWQ!$NF$2:$NF$60=M$1),0),$E7-1966)} -> 137363 | ... Q7: {=INDEX(GMWQ!$A$2:$NF$60,MATCH(1,(GMWQ!$NE$2:$NE$60=Q$3)*(GMWQ!$ND$2:$ND$60=Q$4)*(GMWQ!$NF$2:$NF$60=Q$1),0),$E7-1966)} -> 24903
B8: 1973 | C8: 1973 | E8: =+E7+1 -> 1974 | F8: {=INDEX(GMWQ!$A$2:$NF$60,MATCH(1,(GMWQ!$NE$2:$NE$60=F$3)*(GMWQ!$ND$2:$ND$60=F$4)*(GMWQ!$NF$2:$NF$60=F$1),0),$E8-1966)} -> 11.68304 | G8: {=INDEX(GMWQ!$A$2:$NF$60,MATCH(1,(GMWQ!$NE$2:$NE$60=G$3)*(GMWQ!$ND$2:$ND$60=G$4)*(GMWQ!$NF$2:$NF$60=G$1),0),$E8-1966)} -> 550.9141 | H8: {=INDEX(GMWQ!$A$2:$NF$60,MATCH(1,(GMWQ!$NE$2:$NE$60=H$3)*(GMWQ!$ND$2:$ND$60=H$4)*(GMWQ!$NF$2:$NF$60=H$1),0),$E8-1966)} -> 15.59743 | I8: {=INDEX(GMWQ!$A$2:$NF$60,MATCH(1,(GMWQ!$NE$2:$NE$60=I$3)*(GMWQ!$ND$2:$ND$60=I$4)*(GMWQ!$NF$2:$NF$60=I$1),0),$E8-1966)} -> 4424 | J8: {=INDEX(GMWQ!$A$2:$NF$60,MATCH(1,(GMWQ!$NE$2:$NE$60=J$3)*(GMWQ!$ND$2:$ND$60=J$4)*(GMWQ!$NF$2:$NF$60=J$1),0),$E8-1966)} -> 19874 | K8: {=INDEX(GMWQ!$A$2:$NF$60,MATCH(1,(GMWQ!$NE$2:$NE$60=K$3)*(GMWQ!$ND$2:$ND$60=K$4)*(GMWQ!$NF$2:$NF$60=K$1),0),$E8-1966)} -> 9711 | L8: {=INDEX(GMWQ!$A$2:$NF$60,MATCH(1,(GMWQ!$NE$2:$NE$60=L$3)*(GMWQ!$ND$2:$ND$60=L$4)*(GMWQ!$NF$2:$NF$60=L$1),0),$E8-1966)} -> 12849 | M8: {=INDEX(GMWQ!$A$2:$NF$60,MATCH(1,(GMWQ!$NE$2:$NE$60=M$3)*(GMWQ!$ND$2:$ND$60=M$4)*(GMWQ!$NF$2:$NF$60=M$1),0),$E8-1966)} -> 140152 | ... Q8: {=INDEX(GMWQ!$A$2:$NF$60,MATCH(1,(GMWQ!$NE$2:$NE$60=Q$3)*(GMWQ!$ND$2:$ND$60=Q$4)*(GMWQ!$NF$2:$NF$60=Q$1),0),$E8-1966)} -> 24986
B9: 1973 | C9: 1973 | E9: =+E8+1 -> 1975 | F9: {=INDEX(GMWQ!$A$2:$NF$60,MATCH(1,(GMWQ!$NE$2:$NE$60=F$3)*(GMWQ!$ND$2:$ND$60=F$4)*(GMWQ!$NF$2:$NF$60=F$1),0),$E9-1966)} -> 12.17741 | G9: {=INDEX(GMWQ!$A$2:$NF$60,MATCH(1,(GMWQ!$NE$2:$NE$60=G$3)*(GMWQ!$ND$2:$ND$60=G$4)*(GMWQ!$NF$2:$NF$60=G$1),0),$E9-1966)} -> 576.7733 | H9: {=INDEX(GMWQ!$A$2:$NF$60,MATCH(1,(GMWQ!$NE$2:$NE$60=H$3)*(GMWQ!$ND$2:$ND$60=H$4)*(GMWQ!$NF$2:$NF$60=H$1),0),$E9-1966)} -> 16.40707 | I9: {=INDEX(GMWQ!$A$2:$NF$60,MATCH(1,(GMWQ!$NE$2:$NE$60=I$3)*(GMWQ!$ND$2:$ND$60=I$4)*(GMWQ!$NF$2:$NF$60=I$1),0),$E9-1966)} -> 4297 | J9: {=INDEX(GMWQ!$A$2:$NF$60,MATCH(1,(GMWQ!$NE$2:$NE$60=J$3)*(GMWQ!$ND$2:$ND$60=J$4)*(GMWQ!$NF$2:$NF$60=J$1),0),$E9-1966)} -> 20558 | K9: {=INDEX(GMWQ!$A$2:$NF$60,MATCH(1,(GMWQ!$NE$2:$NE$60=K$3)*(GMWQ!$ND$2:$ND$60=K$4)*(GMWQ!$NF$2:$NF$60=K$1),0),$E9-1966)} -> 10012 | L9: {=INDEX(GMWQ!$A$2:$NF$60,MATCH(1,(GMWQ!$NE$2:$NE$60=L$3)*(GMWQ!$ND$2:$ND$60=L$4)*(GMWQ!$NF$2:$NF$60=L$1),0),$E9-1966)} -> 13247 | M9: {=INDEX(GMWQ!$A$2:$NF$60,MATCH(1,(GMWQ!$NE$2:$NE$60=M$3)*(GMWQ!$ND$2:$ND$60=M$4)*(GMWQ!$NF$2:$NF$60=M$1),0),$E9-1966)} -> 141286 | ... Q9: {=INDEX(GMWQ!$A$2:$NF$60,MATCH(1,(GMWQ!$NE$2:$NE$60=Q$3)*(GMWQ!$ND$2:$ND$60=Q$4)*(GMWQ!$NF$2:$NF$60=Q$1),0),$E9-1966)} -> 24972
B10: 1973 | C10: 1973 | E10: =+E9+1 -> 1976 | F10: {=INDEX(GMWQ!$A$2:$NF$60,MATCH(1,(GMWQ!$NE$2:$NE$60=F$3)*(GMWQ!$ND$2:$ND$60=F$4)*(GMWQ!$NF$2:$NF$60=F$1),0),$E10-1966)} -> 12.71151 | G10: {=INDEX(GMWQ!$A$2:$NF$60,MATCH(1,(GMWQ!$NE$2:$NE$60=G$3)*(GMWQ!$ND$2:$ND$60=G$4)*(GMWQ!$NF$2:$NF$60=G$1),0),$E10-1966)} -> 629.6161 | H10: {=INDEX(GMWQ!$A$2:$NF$60,MATCH(1,(GMWQ!$NE$2:$NE$60=H$3)*(GMWQ!$ND$2:$ND$60=H$4)*(GMWQ!$NF$2:$NF$60=H$1),0),$E10-1966)} -> 16.90761 | I10: {=INDEX(GMWQ!$A$2:$NF$60,MATCH(1,(GMWQ!$NE$2:$NE$60=I$3)*(GMWQ!$ND$2:$ND$60=I$4)*(GMWQ!$NF$2:$NF$60=I$1),0),$E10-1966)} -> 4489 | J10: {=INDEX(GMWQ!$A$2:$NF$60,MATCH(1,(GMWQ!$NE$2:$NE$60=J$3)*(GMWQ!$ND$2:$ND$60=J$4)*(GMWQ!$NF$2:$NF$60=J$1),0),$E10-1966)} -> 21315 | K10: {=INDEX(GMWQ!$A$2:$NF$60,MATCH(1,(GMWQ!$NE$2:$NE$60=K$3)*(GMWQ!$ND$2:$ND$60=K$4)*(GMWQ!$NF$2:$NF$60=K$1),0),$E10-1966)} -> 10380 | L10: {=INDEX(GMWQ!$A$2:$NF$60,MATCH(1,(GMWQ!$NE$2:$NE$60=L$3)*(GMWQ!$ND$2:$ND$60=L$4)*(GMWQ!$NF$2:$NF$60=L$1),0),$E10-1966)} -> 13917 | M10: {=INDEX(GMWQ!$A$2:$NF$60,MATCH(1,(GMWQ!$NE$2:$NE$60=M$3)*(GMWQ!$ND$2:$ND$60=M$4)*(GMWQ!$NF$2:$NF$60=M$1),0),$E10-1966)} -> 141617 | ... Q10: {=INDEX(GMWQ!$A$2:$NF$60,MATCH(1,(GMWQ!$NE$2:$NE$60=Q$3)*(GMWQ!$ND$2:$ND$60=Q$4)*(GMWQ!$NF$2:$NF$60=Q$1),0),$E10-1966)} -> 24999
A11: 1974 | B11: =+B7+1 -> 1974 | C11: 1973 | D11: 1973 | E11: =+E10+1 -> 1977 | F11: {=INDEX(GMWQ!$A$2:$NF$60,MATCH(1,(GMWQ!$NE$2:$NE$60=F$3)*(GMWQ!$ND$2:$ND$60=F$4)*(GMWQ!$NF$2:$NF$60=F$1),0),$E11-1966)} -> 13.40424 | G11: {=INDEX(GMWQ!$A$2:$NF$60,MATCH(1,(GMWQ!$NE$2:$NE$60=G$3)*(GMWQ!$ND$2:$ND$60=G$4)*(GMWQ!$NF$2:$NF$60=G$1),0),$E11-1966)} -> 677.9616 | H11: {=INDEX(GMWQ!$A$2:$NF$60,MATCH(1,(GMWQ!$NE$2:$NE$60=H$3)*(GMWQ!$ND$2:$ND$60=H$4)*(GMWQ!$NF$2:$NF$60=H$1),0),$E11-1966)} -> 16.78086 | I11: {=INDEX(GMWQ!$A$2:$NF$60,MATCH(1,(GMWQ!$NE$2:$NE$60=I$3)*(GMWQ!$ND$2:$ND$60=I$4)*(GMWQ!$NF$2:$NF$60=I$1),0),$E11-1966)} -> 3797 | J11: {=INDEX(GMWQ!$A$2:$NF$60,MATCH(1,(GMWQ!$NE$2:$NE$60=J$3)*(GMWQ!$ND$2:$ND$60=J$4)*(GMWQ!$NF$2:$NF$60=J$1),0),$E11-1966)} -> 21132 | K11: {=INDEX(GMWQ!$A$2:$NF$60,MATCH(1,(GMWQ!$NE$2:$NE$60=K$3)*(GMWQ!$ND$2:$ND$60=K$4)*(GMWQ!$NF$2:$NF$60=K$1),0),$E11-1966)} -> 10596 | L11: {=INDEX(GMWQ!$A$2:$NF$60,MATCH(1,(GMWQ!$NE$2:$NE$60=L$3)*(GMWQ!$ND$2:$ND$60=L$4)*(GMWQ!$NF$2:$NF$60=L$1),0),$E11-1966)} -> 14267 | M11: {=INDEX(GMWQ!$A$2:$NF$60,MATCH(1,(GMWQ!$NE$2:$NE$60=M$3)*(GMWQ!$ND$2:$ND$60=M$4)*(GMWQ!$NF$2:$NF$60=M$1),0),$E11-1966)} -> 137691 | ... Q11: {=INDEX(GMWQ!$A$2:$NF$60,MATCH(1,(GMWQ!$NE$2:$NE$60=Q$3)*(GMWQ!$ND$2:$ND$60=Q$4)*(GMWQ!$NF$2:$NF$60=Q$1),0),$E11-1966)} -> 24984
B12: =+B8+1 -> 1974 | C12: =+C8+1 -> 1974 | E12: =+E11+1 -> 1978 | F12: {=INDEX(GMWQ!$A$2:$NF$60,MATCH(1,(GMWQ!$NE$2:$NE$60=F$3)*(GMWQ!$ND$2:$ND$60=F$4)*(GMWQ!$NF$2:$NF$60=F$1),0),$E12-1966)} -> 13.85016 | G12: {=INDEX(GMWQ!$A$2:$NF$60,MATCH(1,(GMWQ!$NE$2:$NE$60=G$3)*(GMWQ!$ND$2:$ND$60=G$4)*(GMWQ!$NF$2:$NF$60=G$1),0),$E12-1966)} -> 684.7075 | H12: {=INDEX(GMWQ!$A$2:$NF$60,MATCH(1,(GMWQ!$NE$2:$NE$60=H$3)*(GMWQ!$ND$2:$ND$60=H$4)*(GMWQ!$NF$2:$NF$60=H$1),0),$E12-1966)} -> 18.25341 | I12: {=INDEX(GMWQ!$A$2:$NF$60,MATCH(1,(GMWQ!$NE$2:$NE$60=I$3)*(GMWQ!$ND$2:$ND$60=I$4)*(GMWQ!$NF$2:$NF$60=I$1),0),$E12-1966)} -> 4283 | J12: {=INDEX(GMWQ!$A$2:$NF$60,MATCH(1,(GMWQ!$NE$2:$NE$60=J$3)*(GMWQ!$ND$2:$ND$60=J$4)*(GMWQ!$NF$2:$NF$60=J$1),0),$E12-1966)} -> 22651 | K12: {=INDEX(GMWQ!$A$2:$NF$60,MATCH(1,(GMWQ!$NE$2:$NE$60=K$3)*(GMWQ!$ND$2:$ND$60=K$4)*(GMWQ!$NF$2:$NF$60=K$1),0),$E12-1966)} -> 11121 | L12: {=INDEX(GMWQ!$A$2:$NF$60,MATCH(1,(GMWQ!$NE$2:$NE$60=L$3)*(GMWQ!$ND$2:$ND$60=L$4)*(GMWQ!$NF$2:$NF$60=L$1),0),$E12-1966)} -> 14694 | M12: {=INDEX(GMWQ!$A$2:$NF$60,MATCH(1,(GMWQ!$NE$2:$NE$60=M$3)*(GMWQ!$ND$2:$ND$60=M$4)*(GMWQ!$NF$2:$NF$60=M$1),0),$E12-1966)} -> 136111 | ... Q12: {=INDEX(GMWQ!$A$2:$NF$60,MATCH(1,(GMWQ!$NE$2:$NE$60=Q$3)*(GMWQ!$ND$2:$ND$60=Q$4)*(GMWQ!$NF$2:$NF$60=Q$1),0),$E12-1966)} -> 25002
B13: =+B9+1 -> 1974 | C13: =+C9+1 -> 1974 | E13: =+E12+1 -> 1979 | F13: {=INDEX(GMWQ!$A$2:$NF$60,MATCH(1,(GMWQ!$NE$2:$NE$60=F$3)*(GMWQ!$ND$2:$ND$60=F$4)*(GMWQ!$NF$2:$NF$60=F$1),0),$E13-1966)} -> 15.04939 | G13: {=INDEX(GMWQ!$A$2:$NF$60,MATCH(1,(GMWQ!$NE$2:$NE$60=G$3)*(GMWQ!$ND$2:$ND$60=G$4)*(GMWQ!$NF$2:$NF$60=G$1),0),$E13-1966)} -> 843.2358 | H13: {=INDEX(GMWQ!$A$2:$NF$60,MATCH(1,(GMWQ!$NE$2:$NE$60=H$3)*(GMWQ!$ND$2:$ND$60=H$4)*(GMWQ!$NF$2:$NF$60=H$1),0),$E13-1966)} -> 20.2429 | I13: {=INDEX(GMWQ!$A$2:$NF$60,MATCH(1,(GMWQ!$NE$2:$NE$60=I$3)*(GMWQ!$ND$2:$ND$60=I$4)*(GMWQ!$NF$2:$NF$60=I$1),0),$E13-1966)} -> 4318 | J13: {=INDEX(GMWQ!$A$2:$NF$60,MATCH(1,(GMWQ!$NE$2:$NE$60=J$3)*(GMWQ!$ND$2:$ND$60=J$4)*(GMWQ!$NF$2:$NF$60=J$1),0),$E13-1966)} -> 23896 | K13: {=INDEX(GMWQ!$A$2:$NF$60,MATCH(1,(GMWQ!$NE$2:$NE$60=K$3)*(GMWQ!$ND$2:$ND$60=K$4)*(GMWQ!$NF$2:$NF$60=K$1),0),$E13-1966)} -> 12083 | L13: {=INDEX(GMWQ!$A$2:$NF$60,MATCH(1,(GMWQ!$NE$2:$NE$60=L$3)*(GMWQ!$ND$2:$ND$60=L$4)*(GMWQ!$NF$2:$NF$60=L$1),0),$E13-1966)} -> 15881 | M13: {=INDEX(GMWQ!$A$2:$NF$60,MATCH(1,(GMWQ!$NE$2:$NE$60=M$3)*(GMWQ!$ND$2:$ND$60=M$4)*(GMWQ!$NF$2:$NF$60=M$1),0),$E13-1966)} -> 141095 | ... Q13: {=INDEX(GMWQ!$A$2:$NF$60,MATCH(1,(GMWQ!$NE$2:$NE$60=Q$3)*(GMWQ!$ND$2:$ND$60=Q$4)*(GMWQ!$NF$2:$NF$60=Q$1),0),$E13-1966)} -> 25066
B14: =+B10+1 -> 1974 | C14: =+C10+1 -> 1974 | E14: =+E13+1 -> 1980 | F14: {=INDEX(GMWQ!$A$2:$NF$60,MATCH(1,(GMWQ!$NE$2:$NE$60=F$3)*(GMWQ!$ND$2:$ND$60=F$4)*(GMWQ!$NF$2:$NF$60=F$1),0),$E14-1966)} -> 16.37024 | G14: {=INDEX(GMWQ!$A$2:$NF$60,MATCH(1,(GMWQ!$NE$2:$NE$60=G$3)*(GMWQ!$ND$2:$ND$60=G$4)*(GMWQ!$NF$2:$NF$60=G$1),0),$E14-1966)} -> 932.0567 | H14: {=INDEX(GMWQ!$A$2:$NF$60,MATCH(1,(GMWQ!$NE$2:$NE$60=H$3)*(GMWQ!$ND$2:$ND$60=H$4)*(GMWQ!$NF$2:$NF$60=H$1),0),$E14-1966)} -> 21.92424 | I14: {=INDEX(GMWQ!$A$2:$NF$60,MATCH(1,(GMWQ!$NE$2:$NE$60=I$3)*(GMWQ!$ND$2:$ND$60=I$4)*(GMWQ!$NF$2:$NF$60=I$1),0),$E14-1966)} -> 4226 | J14: {=INDEX(GMWQ!$A$2:$NF$60,MATCH(1,(GMWQ!$NE$2:$NE$60=J$3)*(GMWQ!$ND$2:$ND$60=J$4)*(GMWQ!$NF$2:$NF$60=J$1),0),$E14-1966)} -> 24994 | K14: {=INDEX(GMWQ!$A$2:$NF$60,MATCH(1,(GMWQ!$NE$2:$NE$60=K$3)*(GMWQ!$ND$2:$ND$60=K$4)*(GMWQ!$NF$2:$NF$60=K$1),0),$E14-1966)} -> 12912 | L14: {=INDEX(GMWQ!$A$2:$NF$60,MATCH(1,(GMWQ!$NE$2:$NE$60=L$3)*(GMWQ!$ND$2:$ND$60=L$4)*(GMWQ!$NF$2:$NF$60=L$1),0),$E14-1966)} -> 16728 | M14: {=INDEX(GMWQ!$A$2:$NF$60,MATCH(1,(GMWQ!$NE$2:$NE$60=M$3)*(GMWQ!$ND$2:$ND$60=M$4)*(GMWQ!$NF$2:$NF$60=M$1),0),$E14-1966)} -> 140771 | ... Q14: {=INDEX(GMWQ!$A$2:$NF$60,MATCH(1,(GMWQ!$NE$2:$NE$60=Q$3)*(GMWQ!$ND$2:$ND$60=Q$4)*(GMWQ!$NF$2:$NF$60=Q$1),0),$E14-1966)} -> 25065
A15: 1975 | B15: =+B11+1 -> 1975 | C15: =+C11+1 -> 1974 | D15: =+D11+1 -> 1974 | E15: =+E14+1 -> 1981 | F15: {=INDEX(GMWQ!$A$2:$NF$60,MATCH(1,(GMWQ!$NE$2:$NE$60=F$3)*(GMWQ!$ND$2:$ND$60=F$4)*(GMWQ!$NF$2:$NF$60=F$1),0),$E15-1966)} -> 18.17834 | G15: {=INDEX(GMWQ!$A$2:$NF$60,MATCH(1,(GMWQ!$NE$2:$NE$60=G$3)*(GMWQ!$ND$2:$ND$60=G$4)*(GMWQ!$NF$2:$NF$60=G$1),0),$E15-1966)} -> 1014.132 | H15: {=INDEX(GMWQ!$A$2:$NF$60,MATCH(1,(GMWQ!$NE$2:$NE$60=H$3)*(GMWQ!$ND$2:$ND$60=H$4)*(GMWQ!$NF$2:$NF$60=H$1),0),$E15-1966)} -> 23.39659 | I15: {=INDEX(GMWQ!$A$2:$NF$60,MATCH(1,(GMWQ!$NE$2:$NE$60=I$3)*(GMWQ!$ND$2:$ND$60=I$4)*(GMWQ!$NF$2:$NF$60=I$1),0),$E15-1966)} -> 4199 | J15: {=INDEX(GMWQ!$A$2:$NF$60,MATCH(1,(GMWQ!$NE$2:$NE$60=J$3)*(GMWQ!$ND$2:$ND$60=J$4)*(GMWQ!$NF$2:$NF$60=J$1),0),$E15-1966)} -> 26814 | K15: {=INDEX(GMWQ!$A$2:$NF$60,MATCH(1,(GMWQ!$NE$2:$NE$60=K$3)*(GMWQ!$ND$2:$ND$60=K$4)*(GMWQ!$NF$2:$NF$60=K$1),0),$E15-1966)} -> 14391 | L15: {=INDEX(GMWQ!$A$2:$NF$60,MATCH(1,(GMWQ!$NE$2:$NE$60=L$3)*(GMWQ!$ND$2:$ND$60=L$4)*(GMWQ!$NF$2:$NF$60=L$1),0),$E15-1966)} -> 18231 | M15: {=INDEX(GMWQ!$A$2:$NF$60,MATCH(1,(GMWQ!$NE$2:$NE$60=M$3)*(GMWQ!$ND$2:$ND$60=M$4)*(GMWQ!$NF$2:$NF$60=M$1),0),$E15-1966)} -> 143397 | ... Q15: {=INDEX(GMWQ!$A$2:$NF$60,MATCH(1,(GMWQ!$NE$2:$NE$60=Q$3)*(GMWQ!$ND$2:$ND$60=Q$4)*(GMWQ!$NF$2:$NF$60=Q$1),0),$E15-1966)} -> 24996
B16: =+B12+1 -> 1975 | C16: =+C12+1 -> 1975 | E16: =+E15+1 -> 1982 | F16: {=INDEX(GMWQ!$A$2:$NF$60,MATCH(1,(GMWQ!$NE$2:$NE$60=F$3)*(GMWQ!$ND$2:$ND$60=F$4)*(GMWQ!$NF$2:$NF$60=F$1),0),$E16-1966)} -> 19.0148 | G16: {=INDEX(GMWQ!$A$2:$NF$60,MATCH(1,(GMWQ!$NE$2:$NE$60=G$3)*(GMWQ!$ND$2:$ND$60=G$4)*(GMWQ!$NF$2:$NF$60=G$1),0),$E16-1966)} -> 1131.06 | H16: {=INDEX(GMWQ!$A$2:$NF$60,MATCH(1,(GMWQ!$NE$2:$NE$60=H$3)*(GMWQ!$ND$2:$ND$60=H$4)*(GMWQ!$NF$2:$NF$60=H$1),0),$E16-1966)} -> 24.96419 | I16: {=INDEX(GMWQ!$A$2:$NF$60,MATCH(1,(GMWQ!$NE$2:$NE$60=I$3)*(GMWQ!$ND$2:$ND$60=I$4)*(GMWQ!$NF$2:$NF$60=I$1),0),$E16-1966)} -> 4286 | J16: {=INDEX(GMWQ!$A$2:$NF$60,MATCH(1,(GMWQ!$NE$2:$NE$60=J$3)*(GMWQ!$ND$2:$ND$60=J$4)*(GMWQ!$NF$2:$NF$60=J$1),0),$E16-1966)} -> 28129 | K16: {=INDEX(GMWQ!$A$2:$NF$60,MATCH(1,(GMWQ!$NE$2:$NE$60=K$3)*(GMWQ!$ND$2:$ND$60=K$4)*(GMWQ!$NF$2:$NF$60=K$1),0),$E16-1966)} -> 14659 | L16: {=INDEX(GMWQ!$A$2:$NF$60,MATCH(1,(GMWQ!$NE$2:$NE$60=L$3)*(GMWQ!$ND$2:$ND$60=L$4)*(GMWQ!$NF$2:$NF$60=L$1),0),$E16-1966)} -> 18613 | M16: {=INDEX(GMWQ!$A$2:$NF$60,MATCH(1,(GMWQ!$NE$2:$NE$60=M$3)*(GMWQ!$ND$2:$ND$60=M$4)*(GMWQ!$NF$2:$NF$60=M$1),0),$E16-1966)} -> 138847 | ... Q16: {=INDEX(GMWQ!$A$2:$NF$60,MATCH(1,(GMWQ!$NE$2:$NE$60=Q$3)*(GMWQ!$ND$2:$ND$60=Q$4)*(GMWQ!$NF$2:$NF$60=Q$1),0),$E16-1966)} -> 24955
B17: =+B13+1 -> 1975 | C17: =+C13+1 -> 1975 | E17: =+E16+1 -> 1983 | F17: {=INDEX(GMWQ!$A$2:$NF$60,MATCH(1,(GMWQ!$NE$2:$NE$60=F$3)*(GMWQ!$ND$2:$ND$60=F$4)*(GMWQ!$NF$2:$NF$60=F$1),0),$E17-1966)} -> 20.26476 | G17: {=INDEX(GMWQ!$A$2:$NF$60,MATCH(1,(GMWQ!$NE$2:$NE$60=G$3)*(GMWQ!$ND$2:$ND$60=G$4)*(GMWQ!$NF$2:$NF$60=G$1),0),$E17-1966)} -> 1191.773 | H17: {=INDEX(GMWQ!$A$2:$NF$60,MATCH(1,(GMWQ!$NE$2:$NE$60=H$3)*(GMWQ!$ND$2:$ND$60=H$4)*(GMWQ!$NF$2:$NF$60=H$1),0),$E17-1966)} -> 27.02938 | I17: {=INDEX(GMWQ!$A$2:$NF$60,MATCH(1,(GMWQ!$NE$2:$NE$60=I$3)*(GMWQ!$ND$2:$ND$60=I$4)*(GMWQ!$NF$2:$NF$60=I$1),0),$E17-1966)} -> 4257 | J17: {=INDEX(GMWQ!$A$2:$NF$60,MATCH(1,(GMWQ!$NE$2:$NE$60=J$3)*(GMWQ!$ND$2:$ND$60=J$4)*(GMWQ!$NF$2:$NF$60=J$1),0),$E17-1966)} -> 29260 | K17: {=INDEX(GMWQ!$A$2:$NF$60,MATCH(1,(GMWQ!$NE$2:$NE$60=K$3)*(GMWQ!$ND$2:$ND$60=K$4)*(GMWQ!$NF$2:$NF$60=K$1),0),$E17-1966)} -> 15563 | L17: {=INDEX(GMWQ!$A$2:$NF$60,MATCH(1,(GMWQ!$NE$2:$NE$60=L$3)*(GMWQ!$ND$2:$ND$60=L$4)*(GMWQ!$NF$2:$NF$60=L$1),0),$E17-1966)} -> 19564 | M17: {=INDEX(GMWQ!$A$2:$NF$60,MATCH(1,(GMWQ!$NE$2:$NE$60=M$3)*(GMWQ!$ND$2:$ND$60=M$4)*(GMWQ!$NF$2:$NF$60=M$1),0),$E17-1966)} -> 140319 | ... Q17: {=INDEX(GMWQ!$A$2:$NF$60,MATCH(1,(GMWQ!$NE$2:$NE$60=Q$3)*(GMWQ!$ND$2:$ND$60=Q$4)*(GMWQ!$NF$2:$NF$60=Q$1),0),$E17-1966)} -> 24918
B18: =+B14+1 -> 1975 | C18: =+C14+1 -> 1975 | E18: =+E17+1 -> 1984 | F18: {=INDEX(GMWQ!$A$2:$NF$60,MATCH(1,(GMWQ!$NE$2:$NE$60=F$3)*(GMWQ!$ND$2:$ND$60=F$4)*(GMWQ!$NF$2:$NF$60=F$1),0),$E18-1966)} -> 20.49008 | G18: {=INDEX(GMWQ!$A$2:$NF$60,MATCH(1,(GMWQ!$NE$2:$NE$60=G$3)*(GMWQ!$ND$2:$ND$60=G$4)*(GMWQ!$NF$2:$NF$60=G$1),0),$E18-1966)} -> 1236.746 | H18: {=INDEX(GMWQ!$A$2:$NF$60,MATCH(1,(GMWQ!$NE$2:$NE$60=H$3)*(GMWQ!$ND$2:$ND$60=H$4)*(GMWQ!$NF$2:$NF$60=H$1),0),$E18-1966)} -> 28.37567 | I18: {=INDEX(GMWQ!$A$2:$NF$60,MATCH(1,(GMWQ!$NE$2:$NE$60=I$3)*(GMWQ!$ND$2:$ND$60=I$4)*(GMWQ!$NF$2:$NF$60=I$1),0),$E18-1966)} -> 4955 | J18: {=INDEX(GMWQ!$A$2:$NF$60,MATCH(1,(GMWQ!$NE$2:$NE$60=J$3)*(GMWQ!$ND$2:$ND$60=J$4)*(GMWQ!$NF$2:$NF$60=J$1),0),$E18-1966)} -> 30890 | K18: {=INDEX(GMWQ!$A$2:$NF$60,MATCH(1,(GMWQ!$NE$2:$NE$60=K$3)*(GMWQ!$ND$2:$ND$60=K$4)*(GMWQ!$NF$2:$NF$60=K$1),0),$E18-1966)} -> 15848 | L18: {=INDEX(GMWQ!$A$2:$NF$60,MATCH(1,(GMWQ!$NE$2:$NE$60=L$3)*(GMWQ!$ND$2:$ND$60=L$4)*(GMWQ!$NF$2:$NF$60=L$1),0),$E18-1966)} -> 20194 | M18: {=INDEX(GMWQ!$A$2:$NF$60,MATCH(1,(GMWQ!$NE$2:$NE$60=M$3)*(GMWQ!$ND$2:$ND$60=M$4)*(GMWQ!$NF$2:$NF$60=M$1),0),$E18-1966)} -> 137808 | ... Q18: {=INDEX(GMWQ!$A$2:$NF$60,MATCH(1,(GMWQ!$NE$2:$NE$60=Q$3)*(GMWQ!$ND$2:$ND$60=Q$4)*(GMWQ!$NF$2:$NF$60=Q$1),0),$E18-1966)} -> 24864
A19: 1976 | B19: =+B15+1 -> 1976 | C19: =+C15+1 -> 1975 | D19: =+D15+1 -> 1975 | E19: =+E18+1 -> 1985 | F19: {=INDEX(GMWQ!$A$2:$NF$60,MATCH(1,(GMWQ!$NE$2:$NE$60=F$3)*(GMWQ!$ND$2:$ND$60=F$4)*(GMWQ!$NF$2:$NF$60=F$1),0),$E19-1966)} -> 20.75505 | G19: {=INDEX(GMWQ!$A$2:$NF$60,MATCH(1,(GMWQ!$NE$2:$NE$60=G$3)*(GMWQ!$ND$2:$ND$60=G$4)*(GMWQ!$NF$2:$NF$60=G$1),0),$E19-1966)} -> 1310.951 | H19: {=INDEX(GMWQ!$A$2:$NF$60,MATCH(1,(GMWQ!$NE$2:$NE$60=H$3)*(GMWQ!$ND$2:$ND$60=H$4)*(GMWQ!$NF$2:$NF$60=H$1),0),$E19-1966)} -> 29.35714 | I19: {=INDEX(GMWQ!$A$2:$NF$60,MATCH(1,(GMWQ!$NE$2:$NE$60=I$3)*(GMWQ!$ND$2:$ND$60=I$4)*(GMWQ!$NF$2:$NF$60=I$1),0),$E19-1966)} -> 5071 | J19: {=INDEX(GMWQ!$A$2:$NF$60,MATCH(1,(GMWQ!$NE$2:$NE$60=J$3)*(GMWQ!$ND$2:$ND$60=J$4)*(GMWQ!$NF$2:$NF$60=J$1),0),$E19-1966)} -> 32449 | K19: {=INDEX(GMWQ!$A$2:$NF$60,MATCH(1,(GMWQ!$NE$2:$NE$60=K$3)*(GMWQ!$ND$2:$ND$60=K$4)*(GMWQ!$NF$2:$NF$60=K$1),0),$E19-1966)} -> 16278 | L19: {=INDEX(GMWQ!$A$2:$NF$60,MATCH(1,(GMWQ!$NE$2:$NE$60=L$3)*(GMWQ!$ND$2:$ND$60=L$4)*(GMWQ!$NF$2:$NF$60=L$1),0),$E19-1966)} -> 21295 | M19: {=INDEX(GMWQ!$A$2:$NF$60,MATCH(1,(GMWQ!$NE$2:$NE$60=M$3)*(GMWQ!$ND$2:$ND$60=M$4)*(GMWQ!$NF$2:$NF$60=M$1),0),$E19-1966)} -> 139742 | ... Q19: {=INDEX(GMWQ!$A$2:$NF$60,MATCH(1,(GMWQ!$NE$2:$NE$60=Q$3)*(GMWQ!$ND$2:$ND$60=Q$4)*(GMWQ!$NF$2:$NF$60=Q$1),0),$E19-1966)} -> 24809
B20: =+B16+1 -> 1976 | C20: =+C16+1 -> 1976 | E20: =+E19+1 -> 1986 | F20: {=INDEX(GMWQ!$A$2:$NF$60,MATCH(1,(GMWQ!$NE$2:$NE$60=F$3)*(GMWQ!$ND$2:$ND$60=F$4)*(GMWQ!$NF$2:$NF$60=F$1),0),$E20-1966)} -> 21.47286 | G20: {=INDEX(GMWQ!$A$2:$NF$60,MATCH(1,(GMWQ!$NE$2:$NE$60=G$3)*(GMWQ!$ND$2:$ND$60=G$4)*(GMWQ!$NF$2:$NF$60=G$1),0),$E20-1966)} -> 1421.133 | H20: {=INDEX(GMWQ!$A$2:$NF$60,MATCH(1,(GMWQ!$NE$2:$NE$60=H$3)*(GMWQ!$ND$2:$ND$60=H$4)*(GMWQ!$NF$2:$NF$60=H$1),0),$E20-1966)} -> 30.79358 | I20: {=INDEX(GMWQ!$A$2:$NF$60,MATCH(1,(GMWQ!$NE$2:$NE$60=I$3)*(GMWQ!$ND$2:$ND$60=I$4)*(GMWQ!$NF$2:$NF$60=I$1),0),$E20-1966)} -> 5072 | J20: {=INDEX(GMWQ!$A$2:$NF$60,MATCH(1,(GMWQ!$NE$2:$NE$60=J$3)*(GMWQ!$ND$2:$ND$60=J$4)*(GMWQ!$NF$2:$NF$60=J$1),0),$E20-1966)} -> 33322 | K20: {=INDEX(GMWQ!$A$2:$NF$60,MATCH(1,(GMWQ!$NE$2:$NE$60=K$3)*(GMWQ!$ND$2:$ND$60=K$4)*(GMWQ!$NF$2:$NF$60=K$1),0),$E20-1966)} -> 16723 | L20: {=INDEX(GMWQ!$A$2:$NF$60,MATCH(1,(GMWQ!$NE$2:$NE$60=L$3)*(GMWQ!$ND$2:$ND$60=L$4)*(GMWQ!$NF$2:$NF$60=L$1),0),$E20-1966)} -> 21568 | M20: {=INDEX(GMWQ!$A$2:$NF$60,MATCH(1,(GMWQ!$NE$2:$NE$60=M$3)*(GMWQ!$ND$2:$ND$60=M$4)*(GMWQ!$NF$2:$NF$60=M$1),0),$E20-1966)} -> 138168 | ... Q20: {=INDEX(GMWQ!$A$2:$NF$60,MATCH(1,(GMWQ!$NE$2:$NE$60=Q$3)*(GMWQ!$ND$2:$ND$60=Q$4)*(GMWQ!$NF$2:$NF$60=Q$1),0),$E20-1966)} -> 24779
B21: =+B17+1 -> 1976 | C21: =+C17+1 -> 1976 | E21: =+E20+1 -> 1987 | F21: {=INDEX(GMWQ!$A$2:$NF$60,MATCH(1,(GMWQ!$NE$2:$NE$60=F$3)*(GMWQ!$ND$2:$ND$60=F$4)*(GMWQ!$NF$2:$NF$60=F$1),0),$E21-1966)} -> 21.82996 | G21: {=INDEX(GMWQ!$A$2:$NF$60,MATCH(1,(GMWQ!$NE$2:$NE$60=G$3)*(GMWQ!$ND$2:$ND$60=G$4)*(GMWQ!$NF$2:$NF$60=G$1),0),$E21-1966)} -> 1454.863 | H21: {=INDEX(GMWQ!$A$2:$NF$60,MATCH(1,(GMWQ!$NE$2:$NE$60=H$3)*(GMWQ!$ND$2:$ND$60=H$4)*(GMWQ!$NF$2:$NF$60=H$1),0),$E21-1966)} -> 32.30147 | I21: {=INDEX(GMWQ!$A$2:$NF$60,MATCH(1,(GMWQ!$NE$2:$NE$60=I$3)*(GMWQ!$ND$2:$ND$60=I$4)*(GMWQ!$NF$2:$NF$60=I$1),0),$E21-1966)} -> 5440 | J21: {=INDEX(GMWQ!$A$2:$NF$60,MATCH(1,(GMWQ!$NE$2:$NE$60=J$3)*(GMWQ!$ND$2:$ND$60=J$4)*(GMWQ!$NF$2:$NF$60=J$1),0),$E21-1966)} -> 34550 | K21: {=INDEX(GMWQ!$A$2:$NF$60,MATCH(1,(GMWQ!$NE$2:$NE$60=K$3)*(GMWQ!$ND$2:$ND$60=K$4)*(GMWQ!$NF$2:$NF$60=K$1),0),$E21-1966)} -> 17202 | L21: {=INDEX(GMWQ!$A$2:$NF$60,MATCH(1,(GMWQ!$NE$2:$NE$60=L$3)*(GMWQ!$ND$2:$ND$60=L$4)*(GMWQ!$NF$2:$NF$60=L$1),0),$E21-1966)} -> 22876 | M21: {=INDEX(GMWQ!$A$2:$NF$60,MATCH(1,(GMWQ!$NE$2:$NE$60=M$3)*(GMWQ!$ND$2:$ND$60=M$4)*(GMWQ!$NF$2:$NF$60=M$1),0),$E21-1966)} -> 142668 | ... Q21: {=INDEX(GMWQ!$A$2:$NF$60,MATCH(1,(GMWQ!$NE$2:$NE$60=Q$3)*(GMWQ!$ND$2:$ND$60=Q$4)*(GMWQ!$NF$2:$NF$60=Q$1),0),$E21-1966)} -> 24768
B22: =+B18+1 -> 1976 | C22: =+C18+1 -> 1976 | E22: =+E21+1 -> 1988 | F22: {=INDEX(GMWQ!$A$2:$NF$60,MATCH(1,(GMWQ!$NE$2:$NE$60=F$3)*(GMWQ!$ND$2:$ND$60=F$4)*(GMWQ!$NF$2:$NF$60=F$1),0),$E22-1966)} -> 21.9867 | G22: {=INDEX(GMWQ!$A$2:$NF$60,MATCH(1,(GMWQ!$NE$2:$NE$60=G$3)*(GMWQ!$ND$2:$ND$60=G$4)*(GMWQ!$NF$2:$NF$60=G$1),0),$E22-1966)} -> 1508.83 | H22: {=INDEX(GMWQ!$A$2:$NF$60,MATCH(1,(GMWQ!$NE$2:$NE$60=H$3)*(GMWQ!$ND$2:$ND$60=H$4)*(GMWQ!$NF$2:$NF$60=H$1),0),$E22-1966)} -> 33.18535 | I22: {=INDEX(GMWQ!$A$2:$NF$60,MATCH(1,(GMWQ!$NE$2:$NE$60=I$3)*(GMWQ!$ND$2:$ND$60=I$4)*(GMWQ!$NF$2:$NF$60=I$1),0),$E22-1966)} -> 6497 | J22: {=INDEX(GMWQ!$A$2:$NF$60,MATCH(1,(GMWQ!$NE$2:$NE$60=J$3)*(GMWQ!$ND$2:$ND$60=J$4)*(GMWQ!$NF$2:$NF$60=J$1),0),$E22-1966)} -> 36678 | K22: {=INDEX(GMWQ!$A$2:$NF$60,MATCH(1,(GMWQ!$NE$2:$NE$60=K$3)*(GMWQ!$ND$2:$ND$60=K$4)*(GMWQ!$NF$2:$NF$60=K$1),0),$E22-1966)} -> 17685 | L22: {=INDEX(GMWQ!$A$2:$NF$60,MATCH(1,(GMWQ!$NE$2:$NE$60=L$3)*(GMWQ!$ND$2:$ND$60=L$4)*(GMWQ!$NF$2:$NF$60=L$1),0),$E22-1966)} -> 23450 | M22: {=INDEX(GMWQ!$A$2:$NF$60,MATCH(1,(GMWQ!$NE$2:$NE$60=M$3)*(GMWQ!$ND$2:$ND$60=M$4)*(GMWQ!$NF$2:$NF$60=M$1),0),$E22-1966)} -> 139028 | ... Q22: {=INDEX(GMWQ!$A$2:$NF$60,MATCH(1,(GMWQ!$NE$2:$NE$60=Q$3)*(GMWQ!$ND$2:$ND$60=Q$4)*(GMWQ!$NF$2:$NF$60=Q$1),0),$E22-1966)} -> 24788
A23: 1977 | B23: =+B19+1 -> 1977 | C23: =+C19+1 -> 1976 | D23: =+D19+1 -> 1976 | E23: =+E22+1 -> 1989 | F23: {=INDEX(GMWQ!$A$2:$NF$60,MATCH(1,(GMWQ!$NE$2:$NE$60=F$3)*(GMWQ!$ND$2:$ND$60=F$4)*(GMWQ!$NF$2:$NF$60=F$1),0),$E23-1966)} -> 22.59407 | G23: {=INDEX(GMWQ!$A$2:$NF$60,MATCH(1,(GMWQ!$NE$2:$NE$60=G$3)*(GMWQ!$ND$2:$ND$60=G$4)*(GMWQ!$NF$2:$NF$60=G$1),0),$E23-1966)} -> 1574.04 | H23: {=INDEX(GMWQ!$A$2:$NF$60,MATCH(1,(GMWQ!$NE$2:$NE$60=H$3)*(GMWQ!$ND$2:$ND$60=H$4)*(GMWQ!$NF$2:$NF$60=H$1),0),$E23-1966)} -> 33.54049 | I23: {=INDEX(GMWQ!$A$2:$NF$60,MATCH(1,(GMWQ!$NE$2:$NE$60=I$3)*(GMWQ!$ND$2:$ND$60=I$4)*(GMWQ!$NF$2:$NF$60=I$1),0),$E23-1966)} -> 7199 | J23: {=INDEX(GMWQ!$A$2:$NF$60,MATCH(1,(GMWQ!$NE$2:$NE$60=J$3)*(GMWQ!$ND$2:$ND$60=J$4)*(GMWQ!$NF$2:$NF$60=J$1),0),$E23-1966)} -> 38038 | K23: {=INDEX(GMWQ!$A$2:$NF$60,MATCH(1,(GMWQ!$NE$2:$NE$60=K$3)*(GMWQ!$ND$2:$ND$60=K$4)*(GMWQ!$NF$2:$NF$60=K$1),0),$E23-1966)} -> 18192 | L23: {=INDEX(GMWQ!$A$2:$NF$60,MATCH(1,(GMWQ!$NE$2:$NE$60=L$3)*(GMWQ!$ND$2:$ND$60=L$4)*(GMWQ!$NF$2:$NF$60=L$1),0),$E23-1966)} -> 23884 | M23: {=INDEX(GMWQ!$A$2:$NF$60,MATCH(1,(GMWQ!$NE$2:$NE$60=M$3)*(GMWQ!$ND$2:$ND$60=M$4)*(GMWQ!$NF$2:$NF$60=M$1),0),$E23-1966)} -> 135347 | ... Q23: {=INDEX(GMWQ!$A$2:$NF$60,MATCH(1,(GMWQ!$NE$2:$NE$60=Q$3)*(GMWQ!$ND$2:$ND$60=Q$4)*(GMWQ!$NF$2:$NF$60=Q$1),0),$E23-1966)} -> 24803
B24: =+B20+1 -> 1977 | C24: =+C20+1 -> 1977 | E24: =+E23+1 -> 1990 | F24: {=INDEX(GMWQ!$A$2:$NF$60,MATCH(1,(GMWQ!$NE$2:$NE$60=F$3)*(GMWQ!$ND$2:$ND$60=F$4)*(GMWQ!$NF$2:$NF$60=F$1),0),$E24-1966)} -> 23.13221 | G24: {=INDEX(GMWQ!$A$2:$NF$60,MATCH(1,(GMWQ!$NE$2:$NE$60=G$3)*(GMWQ!$ND$2:$ND$60=G$4)*(GMWQ!$NF$2:$NF$60=G$1),0),$E24-1966)} -> 1571.792 | H24: {=INDEX(GMWQ!$A$2:$NF$60,MATCH(1,(GMWQ!$NE$2:$NE$60=H$3)*(GMWQ!$ND$2:$ND$60=H$4)*(GMWQ!$NF$2:$NF$60=H$1),0),$E24-1966)} -> 34.54346 | I24: {=INDEX(GMWQ!$A$2:$NF$60,MATCH(1,(GMWQ!$NE$2:$NE$60=I$3)*(GMWQ!$ND$2:$ND$60=I$4)*(GMWQ!$NF$2:$NF$60=I$1),0),$E24-1966)} -> 7734 | J24: {=INDEX(GMWQ!$A$2:$NF$60,MATCH(1,(GMWQ!$NE$2:$NE$60=J$3)*(GMWQ!$ND$2:$ND$60=J$4)*(GMWQ!$NF$2:$NF$60=J$1),0),$E24-1966)} -> 39244 | K24: {=INDEX(GMWQ!$A$2:$NF$60,MATCH(1,(GMWQ!$NE$2:$NE$60=K$3)*(GMWQ!$ND$2:$ND$60=K$4)*(GMWQ!$NF$2:$NF$60=K$1),0),$E24-1966)} -> 18494 | L24: {=INDEX(GMWQ!$A$2:$NF$60,MATCH(1,(GMWQ!$NE$2:$NE$60=L$3)*(GMWQ!$ND$2:$ND$60=L$4)*(GMWQ!$NF$2:$NF$60=L$1),0),$E24-1966)} -> 24509 | M24: {=INDEX(GMWQ!$A$2:$NF$60,MATCH(1,(GMWQ!$NE$2:$NE$60=M$3)*(GMWQ!$ND$2:$ND$60=M$4)*(GMWQ!$NF$2:$NF$60=M$1),0),$E24-1966)} -> 134379 | ... Q24: {=INDEX(GMWQ!$A$2:$NF$60,MATCH(1,(GMWQ!$NE$2:$NE$60=Q$3)*(GMWQ!$ND$2:$ND$60=Q$4)*(GMWQ!$NF$2:$NF$60=Q$1),0),$E24-1966)} -> 24802
B25: =+B21+1 -> 1977 | C25: =+C21+1 -> 1977 | E25: =+E24+1 -> 1991 | F25: {=INDEX(GMWQ!$A$2:$NF$60,MATCH(1,(GMWQ!$NE$2:$NE$60=F$3)*(GMWQ!$ND$2:$ND$60=F$4)*(GMWQ!$NF$2:$NF$60=F$1),0),$E25-1966)} -> 23.4834 | G25: {=INDEX(GMWQ!$A$2:$NF$60,MATCH(1,(GMWQ!$NE$2:$NE$60=G$3)*(GMWQ!$ND$2:$ND$60=G$4)*(GMWQ!$NF$2:$NF$60=G$1),0),$E25-1966)} -> 1593.154 | H25: {=INDEX(GMWQ!$A$2:$NF$60,MATCH(1,(GMWQ!$NE$2:$NE$60=H$3)*(GMWQ!$ND$2:$ND$60=H$4)*(GMWQ!$NF$2:$NF$60=H$1),0),$E25-1966)} -> 35.59764 | I25: {=INDEX(GMWQ!$A$2:$NF$60,MATCH(1,(GMWQ!$NE$2:$NE$60=I$3)*(GMWQ!$ND$2:$ND$60=I$4)*(GMWQ!$NF$2:$NF$60=I$1),0),$E25-1966)} -> 8119 | J25: {=INDEX(GMWQ!$A$2:$NF$60,MATCH(1,(GMWQ!$NE$2:$NE$60=J$3)*(GMWQ!$ND$2:$ND$60=J$4)*(GMWQ!$NF$2:$NF$60=J$1),0),$E25-1966)} -> 40339 | K25: {=INDEX(GMWQ!$A$2:$NF$60,MATCH(1,(GMWQ!$NE$2:$NE$60=K$3)*(GMWQ!$ND$2:$ND$60=K$4)*(GMWQ!$NF$2:$NF$60=K$1),0),$E25-1966)} -> 18884 | L25: {=INDEX(GMWQ!$A$2:$NF$60,MATCH(1,(GMWQ!$NE$2:$NE$60=L$3)*(GMWQ!$ND$2:$ND$60=L$4)*(GMWQ!$NF$2:$NF$60=L$1),0),$E25-1966)} -> 25439 | M25: {=INDEX(GMWQ!$A$2:$NF$60,MATCH(1,(GMWQ!$NE$2:$NE$60=M$3)*(GMWQ!$ND$2:$ND$60=M$4)*(GMWQ!$NF$2:$NF$60=M$1),0),$E25-1966)} -> 137012 | ... Q25: {=INDEX(GMWQ!$A$2:$NF$60,MATCH(1,(GMWQ!$NE$2:$NE$60=Q$3)*(GMWQ!$ND$2:$ND$60=Q$4)*(GMWQ!$NF$2:$NF$60=Q$1),0),$E25-1966)} -> 24809
B26: =+B22+1 -> 1977 | C26: =+C22+1 -> 1977 | E26: =+E25+1 -> 1992 | F26: {=INDEX(GMWQ!$A$2:$NF$60,MATCH(1,(GMWQ!$NE$2:$NE$60=F$3)*(GMWQ!$ND$2:$ND$60=F$4)*(GMWQ!$NF$2:$NF$60=F$1),0),$E26-1966)} -> 23.90327 | G26: {=INDEX(GMWQ!$A$2:$NF$60,MATCH(1,(GMWQ!$NE$2:$NE$60=G$3)*(GMWQ!$ND$2:$ND$60=G$4)*(GMWQ!$NF$2:$NF$60=G$1),0),$E26-1966)} -> 1662.861 | H26: {=INDEX(GMWQ!$A$2:$NF$60,MATCH(1,(GMWQ!$NE$2:$NE$60=H$3)*(GMWQ!$ND$2:$ND$60=H$4)*(GMWQ!$NF$2:$NF$60=H$1),0),$E26-1966)} -> 36.68552 | I26: {=INDEX(GMWQ!$A$2:$NF$60,MATCH(1,(GMWQ!$NE$2:$NE$60=I$3)*(GMWQ!$ND$2:$ND$60=I$4)*(GMWQ!$NF$2:$NF$60=I$1),0),$E26-1966)} -> 8600 | J26: {=INDEX(GMWQ!$A$2:$NF$60,MATCH(1,(GMWQ!$NE$2:$NE$60=J$3)*(GMWQ!$ND$2:$ND$60=J$4)*(GMWQ!$NF$2:$NF$60=J$1),0),$E26-1966)} -> 42165 | K26: {=INDEX(GMWQ!$A$2:$NF$60,MATCH(1,(GMWQ!$NE$2:$NE$60=K$3)*(GMWQ!$ND$2:$ND$60=K$4)*(GMWQ!$NF$2:$NF$60=K$1),0),$E26-1966)} -> 19532 | L26: {=INDEX(GMWQ!$A$2:$NF$60,MATCH(1,(GMWQ!$NE$2:$NE$60=L$3)*(GMWQ!$ND$2:$ND$60=L$4)*(GMWQ!$NF$2:$NF$60=L$1),0),$E26-1966)} -> 26940 | M26: {=INDEX(GMWQ!$A$2:$NF$60,MATCH(1,(GMWQ!$NE$2:$NE$60=M$3)*(GMWQ!$ND$2:$ND$60=M$4)*(GMWQ!$NF$2:$NF$60=M$1),0),$E26-1966)} -> 142669 | ... Q26: {=INDEX(GMWQ!$A$2:$NF$60,MATCH(1,(GMWQ!$NE$2:$NE$60=Q$3)*(GMWQ!$ND$2:$ND$60=Q$4)*(GMWQ!$NF$2:$NF$60=Q$1),0),$E26-1966)} -> 24822
A27: 1978 | B27: =+B23+1 -> 1978 | C27: =+C23+1 -> 1977 | D27: =+D23+1 -> 1977 | E27: =+E26+1 -> 1993 | F27: {=INDEX(GMWQ!$A$2:$NF$60,MATCH(1,(GMWQ!$NE$2:$NE$60=F$3)*(GMWQ!$ND$2:$ND$60=F$4)*(GMWQ!$NF$2:$NF$60=F$1),0),$E27-1966)} -> 24.66358 | G27: {=INDEX(GMWQ!$A$2:$NF$60,MATCH(1,(GMWQ!$NE$2:$NE$60=G$3)*(GMWQ!$ND$2:$ND$60=G$4)*(GMWQ!$NF$2:$NF$60=G$1),0),$E27-1966)} -> 1750.558 | H27: {=INDEX(GMWQ!$A$2:$NF$60,MATCH(1,(GMWQ!$NE$2:$NE$60=H$3)*(GMWQ!$ND$2:$ND$60=H$4)*(GMWQ!$NF$2:$NF$60=H$1),0),$E27-1966)} -> 37.64326 | I27: {=INDEX(GMWQ!$A$2:$NF$60,MATCH(1,(GMWQ!$NE$2:$NE$60=I$3)*(GMWQ!$ND$2:$ND$60=I$4)*(GMWQ!$NF$2:$NF$60=I$1),0),$E27-1966)} -> 9233 | J27: {=INDEX(GMWQ!$A$2:$NF$60,MATCH(1,(GMWQ!$NE$2:$NE$60=J$3)*(GMWQ!$ND$2:$ND$60=J$4)*(GMWQ!$NF$2:$NF$60=J$1),0),$E27-1966)} -> 44140 | K27: {=INDEX(GMWQ!$A$2:$NF$60,MATCH(1,(GMWQ!$NE$2:$NE$60=K$3)*(GMWQ!$ND$2:$ND$60=K$4)*(GMWQ!$NF$2:$NF$60=K$1),0),$E27-1966)} -> 20334 | L27: {=INDEX(GMWQ!$A$2:$NF$60,MATCH(1,(GMWQ!$NE$2:$NE$60=L$3)*(GMWQ!$ND$2:$ND$60=L$4)*(GMWQ!$NF$2:$NF$60=L$1),0),$E27-1966)} -> 27797 | M27: {=INDEX(GMWQ!$A$2:$NF$60,MATCH(1,(GMWQ!$NE$2:$NE$60=M$3)*(GMWQ!$ND$2:$ND$60=M$4)*(GMWQ!$NF$2:$NF$60=M$1),0),$E27-1966)} -> 142512 | ... Q27: {=INDEX(GMWQ!$A$2:$NF$60,MATCH(1,(GMWQ!$NE$2:$NE$60=Q$3)*(GMWQ!$ND$2:$ND$60=Q$4)*(GMWQ!$NF$2:$NF$60=Q$1),0),$E27-1966)} -> 24862
B28: =+B24+1 -> 1978 | C28: =+C24+1 -> 1978 | E28: =+E27+1 -> 1994 | F28: {=INDEX(GMWQ!$A$2:$NF$60,MATCH(1,(GMWQ!$NE$2:$NE$60=F$3)*(GMWQ!$ND$2:$ND$60=F$4)*(GMWQ!$NF$2:$NF$60=F$1),0),$E28-1966)} -> 25.33844 | G28: {=INDEX(GMWQ!$A$2:$NF$60,MATCH(1,(GMWQ!$NE$2:$NE$60=G$3)*(GMWQ!$ND$2:$ND$60=G$4)*(GMWQ!$NF$2:$NF$60=G$1),0),$E28-1966)} -> 1639.25 | H28: {=INDEX(GMWQ!$A$2:$NF$60,MATCH(1,(GMWQ!$NE$2:$NE$60=H$3)*(GMWQ!$ND$2:$ND$60=H$4)*(GMWQ!$NF$2:$NF$60=H$1),0),$E28-1966)} -> 39.86473 | I28: {=INDEX(GMWQ!$A$2:$NF$60,MATCH(1,(GMWQ!$NE$2:$NE$60=I$3)*(GMWQ!$ND$2:$ND$60=I$4)*(GMWQ!$NF$2:$NF$60=I$1),0),$E28-1966)} -> 9234 | J28: {=INDEX(GMWQ!$A$2:$NF$60,MATCH(1,(GMWQ!$NE$2:$NE$60=J$3)*(GMWQ!$ND$2:$ND$60=J$4)*(GMWQ!$NF$2:$NF$60=J$1),0),$E28-1966)} -> 45905 | K28: {=INDEX(GMWQ!$A$2:$NF$60,MATCH(1,(GMWQ!$NE$2:$NE$60=K$3)*(GMWQ!$ND$2:$ND$60=K$4)*(GMWQ!$NF$2:$NF$60=K$1),0),$E28-1966)} -> 21257 | L28: {=INDEX(GMWQ!$A$2:$NF$60,MATCH(1,(GMWQ!$NE$2:$NE$60=L$3)*(GMWQ!$ND$2:$ND$60=L$4)*(GMWQ!$NF$2:$NF$60=L$1),0),$E28-1966)} -> 29144 | M28: {=INDEX(GMWQ!$A$2:$NF$60,MATCH(1,(GMWQ!$NE$2:$NE$60=M$3)*(GMWQ!$ND$2:$ND$60=M$4)*(GMWQ!$NF$2:$NF$60=M$1),0),$E28-1966)} -> 146514 | ... Q28: {=INDEX(GMWQ!$A$2:$NF$60,MATCH(1,(GMWQ!$NE$2:$NE$60=Q$3)*(GMWQ!$ND$2:$ND$60=Q$4)*(GMWQ!$NF$2:$NF$60=Q$1),0),$E28-1966)} -> 24897
B29: =+B25+1 -> 1978 | C29: =+C25+1 -> 1978 | E29: =+E28+1 -> 1995 | F29: {=INDEX(GMWQ!$A$2:$NF$60,MATCH(1,(GMWQ!$NE$2:$NE$60=F$3)*(GMWQ!$ND$2:$ND$60=F$4)*(GMWQ!$NF$2:$NF$60=F$1),0),$E29-1966)} -> 25.69147 | G29: {=INDEX(GMWQ!$A$2:$NF$60,MATCH(1,(GMWQ!$NE$2:$NE$60=G$3)*(GMWQ!$ND$2:$ND$60=G$4)*(GMWQ!$NF$2:$NF$60=G$1),0),$E29-1966)} -> 1683.099 | H29: {=INDEX(GMWQ!$A$2:$NF$60,MATCH(1,(GMWQ!$NE$2:$NE$60=H$3)*(GMWQ!$ND$2:$ND$60=H$4)*(GMWQ!$NF$2:$NF$60=H$1),0),$E29-1966)} -> 42.09901 | I29: {=INDEX(GMWQ!$A$2:$NF$60,MATCH(1,(GMWQ!$NE$2:$NE$60=I$3)*(GMWQ!$ND$2:$ND$60=I$4)*(GMWQ!$NF$2:$NF$60=I$1),0),$E29-1966)} -> 9737 | J29: {=INDEX(GMWQ!$A$2:$NF$60,MATCH(1,(GMWQ!$NE$2:$NE$60=J$3)*(GMWQ!$ND$2:$ND$60=J$4)*(GMWQ!$NF$2:$NF$60=J$1),0),$E29-1966)} -> 47207 | K29: {=INDEX(GMWQ!$A$2:$NF$60,MATCH(1,(GMWQ!$NE$2:$NE$60=K$3)*(GMWQ!$ND$2:$ND$60=K$4)*(GMWQ!$NF$2:$NF$60=K$1),0),$E29-1966)} -> 21798 | L29: {=INDEX(GMWQ!$A$2:$NF$60,MATCH(1,(GMWQ!$NE$2:$NE$60=L$3)*(GMWQ!$ND$2:$ND$60=L$4)*(GMWQ!$NF$2:$NF$60=L$1),0),$E29-1966)} -> 30465 | M29: {=INDEX(GMWQ!$A$2:$NF$60,MATCH(1,(GMWQ!$NE$2:$NE$60=M$3)*(GMWQ!$ND$2:$ND$60=M$4)*(GMWQ!$NF$2:$NF$60=M$1),0),$E29-1966)} -> 150300 | ... Q29: {=INDEX(GMWQ!$A$2:$NF$60,MATCH(1,(GMWQ!$NE$2:$NE$60=Q$3)*(GMWQ!$ND$2:$ND$60=Q$4)*(GMWQ!$NF$2:$NF$60=Q$1),0),$E29-1966)} -> 24941
B30: =+B26+1 -> 1978 | C30: =+C26+1 -> 1978 | E30: =+E29+1 -> 1996 | F30: {=INDEX(GMWQ!$A$2:$NF$60,MATCH(1,(GMWQ!$NE$2:$NE$60=F$3)*(GMWQ!$ND$2:$ND$60=F$4)*(GMWQ!$NF$2:$NF$60=F$1),0),$E30-1966)} -> 26.29916 | G30: {=INDEX(GMWQ!$A$2:$NF$60,MATCH(1,(GMWQ!$NE$2:$NE$60=G$3)*(GMWQ!$ND$2:$ND$60=G$4)*(GMWQ!$NF$2:$NF$60=G$1),0),$E30-1966)} -> 1750.558 | H30: {=INDEX(GMWQ!$A$2:$NF$60,MATCH(1,(GMWQ!$NE$2:$NE$60=H$3)*(GMWQ!$ND$2:$ND$60=H$4)*(GMWQ!$NF$2:$NF$60=H$1),0),$E30-1966)} -> 43.30621 | I30: {=INDEX(GMWQ!$A$2:$NF$60,MATCH(1,(GMWQ!$NE$2:$NE$60=I$3)*(GMWQ!$ND$2:$ND$60=I$4)*(GMWQ!$NF$2:$NF$60=I$1),0),$E30-1966)} -> 9903 | J30: {=INDEX(GMWQ!$A$2:$NF$60,MATCH(1,(GMWQ!$NE$2:$NE$60=J$3)*(GMWQ!$ND$2:$ND$60=J$4)*(GMWQ!$NF$2:$NF$60=J$1),0),$E30-1966)} -> 48906 | K30: {=INDEX(GMWQ!$A$2:$NF$60,MATCH(1,(GMWQ!$NE$2:$NE$60=K$3)*(GMWQ!$ND$2:$ND$60=K$4)*(GMWQ!$NF$2:$NF$60=K$1),0),$E30-1966)} -> 22479 | L30: {=INDEX(GMWQ!$A$2:$NF$60,MATCH(1,(GMWQ!$NE$2:$NE$60=L$3)*(GMWQ!$ND$2:$ND$60=L$4)*(GMWQ!$NF$2:$NF$60=L$1),0),$E30-1966)} -> 31463 | M30: {=INDEX(GMWQ!$A$2:$NF$60,MATCH(1,(GMWQ!$NE$2:$NE$60=M$3)*(GMWQ!$ND$2:$ND$60=M$4)*(GMWQ!$NF$2:$NF$60=M$1),0),$E30-1966)} -> 150197 | ... Q30: {=INDEX(GMWQ!$A$2:$NF$60,MATCH(1,(GMWQ!$NE$2:$NE$60=Q$3)*(GMWQ!$ND$2:$ND$60=Q$4)*(GMWQ!$NF$2:$NF$60=Q$1),0),$E30-1966)} -> 25059
A31: 1979 | B31: =+B27+1 -> 1979 | C31: =+C27+1 -> 1978 | D31: =+D27+1 -> 1978 | E31: =+E30+1 -> 1997 | F31: {=INDEX(GMWQ!$A$2:$NF$60,MATCH(1,(GMWQ!$NE$2:$NE$60=F$3)*(GMWQ!$ND$2:$ND$60=F$4)*(GMWQ!$NF$2:$NF$60=F$1),0),$E31-1966)} -> 27.45561 | G31: {=INDEX(GMWQ!$A$2:$NF$60,MATCH(1,(GMWQ!$NE$2:$NE$60=G$3)*(GMWQ!$ND$2:$ND$60=G$4)*(GMWQ!$NF$2:$NF$60=G$1),0),$E31-1966)} -> 1848.373 | H31: {=INDEX(GMWQ!$A$2:$NF$60,MATCH(1,(GMWQ!$NE$2:$NE$60=H$3)*(GMWQ!$ND$2:$ND$60=H$4)*(GMWQ!$NF$2:$NF$60=H$1),0),$E31-1966)} -> 43.96501 | I31: {=INDEX(GMWQ!$A$2:$NF$60,MATCH(1,(GMWQ!$NE$2:$NE$60=I$3)*(GMWQ!$ND$2:$ND$60=I$4)*(GMWQ!$NF$2:$NF$60=I$1),0),$E31-1966)} -> 10109 | J31: {=INDEX(GMWQ!$A$2:$NF$60,MATCH(1,(GMWQ!$NE$2:$NE$60=J$3)*(GMWQ!$ND$2:$ND$60=J$4)*(GMWQ!$NF$2:$NF$60=J$1),0),$E31-1966)} -> 50459 | K31: {=INDEX(GMWQ!$A$2:$NF$60,MATCH(1,(GMWQ!$NE$2:$NE$60=K$3)*(GMWQ!$ND$2:$ND$60=K$4)*(GMWQ!$NF$2:$NF$60=K$1),0),$E31-1966)} -> 23365 | L31: {=INDEX(GMWQ!$A$2:$NF$60,MATCH(1,(GMWQ!$NE$2:$NE$60=L$3)*(GMWQ!$ND$2:$ND$60=L$4)*(GMWQ!$NF$2:$NF$60=L$1),0),$E31-1966)} -> 32879 | M31: {=INDEX(GMWQ!$A$2:$NF$60,MATCH(1,(GMWQ!$NE$2:$NE$60=M$3)*(GMWQ!$ND$2:$ND$60=M$4)*(GMWQ!$NF$2:$NF$60=M$1),0),$E31-1966)} -> 152401 | ... Q31: {=INDEX(GMWQ!$A$2:$NF$60,MATCH(1,(GMWQ!$NE$2:$NE$60=Q$3)*(GMWQ!$ND$2:$ND$60=Q$4)*(GMWQ!$NF$2:$NF$60=Q$1),0),$E31-1966)} -> 25113
B32: =+B28+1 -> 1979 | C32: =+C28+1 -> 1979 | E32: =+E31+1 -> 1998 | F32: {=INDEX(GMWQ!$A$2:$NF$60,MATCH(1,(GMWQ!$NE$2:$NE$60=F$3)*(GMWQ!$ND$2:$ND$60=F$4)*(GMWQ!$NF$2:$NF$60=F$1),0),$E32-1966)} -> 27.49046 | G32: {=INDEX(GMWQ!$A$2:$NF$60,MATCH(1,(GMWQ!$NE$2:$NE$60=G$3)*(GMWQ!$ND$2:$ND$60=G$4)*(GMWQ!$NF$2:$NF$60=G$1),0),$E32-1966)} -> 1895.594 | H32: {=INDEX(GMWQ!$A$2:$NF$60,MATCH(1,(GMWQ!$NE$2:$NE$60=H$3)*(GMWQ!$ND$2:$ND$60=H$4)*(GMWQ!$NF$2:$NF$60=H$1),0),$E32-1966)} -> 46.83842 | I32: {=INDEX(GMWQ!$A$2:$NF$60,MATCH(1,(GMWQ!$NE$2:$NE$60=I$3)*(GMWQ!$ND$2:$ND$60=I$4)*(GMWQ!$NF$2:$NF$60=I$1),0),$E32-1966)} -> 11219 | J32: {=INDEX(GMWQ!$A$2:$NF$60,MATCH(1,(GMWQ!$NE$2:$NE$60=J$3)*(GMWQ!$ND$2:$ND$60=J$4)*(GMWQ!$NF$2:$NF$60=J$1),0),$E32-1966)} -> 53966 | K32: {=INDEX(GMWQ!$A$2:$NF$60,MATCH(1,(GMWQ!$NE$2:$NE$60=K$3)*(GMWQ!$ND$2:$ND$60=K$4)*(GMWQ!$NF$2:$NF$60=K$1),0),$E32-1966)} -> 24427 | L32: {=INDEX(GMWQ!$A$2:$NF$60,MATCH(1,(GMWQ!$NE$2:$NE$60=L$3)*(GMWQ!$ND$2:$ND$60=L$4)*(GMWQ!$NF$2:$NF$60=L$1),0),$E32-1966)} -> 34157 | M32: {=INDEX(GMWQ!$A$2:$NF$60,MATCH(1,(GMWQ!$NE$2:$NE$60=M$3)*(GMWQ!$ND$2:$ND$60=M$4)*(GMWQ!$NF$2:$NF$60=M$1),0),$E32-1966)} -> 155089 | ... Q32: {=INDEX(GMWQ!$A$2:$NF$60,MATCH(1,(GMWQ!$NE$2:$NE$60=Q$3)*(GMWQ!$ND$2:$ND$60=Q$4)*(GMWQ!$NF$2:$NF$60=Q$1),0),$E32-1966)} -> 25159
B33: =+B29+1 -> 1979 | C33: =+C29+1 -> 1979 | E33: =+E32+1 -> 1999 | F33: {=INDEX(GMWQ!$A$2:$NF$60,MATCH(1,(GMWQ!$NE$2:$NE$60=F$3)*(GMWQ!$ND$2:$ND$60=F$4)*(GMWQ!$NF$2:$NF$60=F$1),0),$E33-1966)} -> 29.59866 | G33: {=INDEX(GMWQ!$A$2:$NF$60,MATCH(1,(GMWQ!$NE$2:$NE$60=G$3)*(GMWQ!$ND$2:$ND$60=G$4)*(GMWQ!$NF$2:$NF$60=G$1),0),$E33-1966)} -> 1949.561 | H33: {=INDEX(GMWQ!$A$2:$NF$60,MATCH(1,(GMWQ!$NE$2:$NE$60=H$3)*(GMWQ!$ND$2:$ND$60=H$4)*(GMWQ!$NF$2:$NF$60=H$1),0),$E33-1966)} -> 50.12706 | I33: {=INDEX(GMWQ!$A$2:$NF$60,MATCH(1,(GMWQ!$NE$2:$NE$60=I$3)*(GMWQ!$ND$2:$ND$60=I$4)*(GMWQ!$NF$2:$NF$60=I$1),0),$E33-1966)} -> 11435 | J33: {=INDEX(GMWQ!$A$2:$NF$60,MATCH(1,(GMWQ!$NE$2:$NE$60=J$3)*(GMWQ!$ND$2:$ND$60=J$4)*(GMWQ!$NF$2:$NF$60=J$1),0),$E33-1966)} -> 56767 | K33: {=INDEX(GMWQ!$A$2:$NF$60,MATCH(1,(GMWQ!$NE$2:$NE$60=K$3)*(GMWQ!$ND$2:$ND$60=K$4)*(GMWQ!$NF$2:$NF$60=K$1),0),$E33-1966)} -> 25749 | L33: {=INDEX(GMWQ!$A$2:$NF$60,MATCH(1,(GMWQ!$NE$2:$NE$60=L$3)*(GMWQ!$ND$2:$ND$60=L$4)*(GMWQ!$NF$2:$NF$60=L$1),0),$E33-1966)} -> 36483 | M33: {=INDEX(GMWQ!$A$2:$NF$60,MATCH(1,(GMWQ!$NE$2:$NE$60=M$3)*(GMWQ!$ND$2:$ND$60=M$4)*(GMWQ!$NF$2:$NF$60=M$1),0),$E33-1966)} -> 155140 | ... Q33: {=INDEX(GMWQ!$A$2:$NF$60,MATCH(1,(GMWQ!$NE$2:$NE$60=Q$3)*(GMWQ!$ND$2:$ND$60=Q$4)*(GMWQ!$NF$2:$NF$60=Q$1),0),$E33-1966)} -> 25229
B34: =+B30+1 -> 1979 | C34: =+C30+1 -> 1979 | E34: =+E33+1 -> 2000 | F34: {=INDEX(GMWQ!$A$2:$NF$60,MATCH(1,(GMWQ!$NE$2:$NE$60=F$3)*(GMWQ!$ND$2:$ND$60=F$4)*(GMWQ!$NF$2:$NF$60=F$1),0),$E34-1966)} -> 30.8156 | G34: {=INDEX(GMWQ!$A$2:$NF$60,MATCH(1,(GMWQ!$NE$2:$NE$60=G$3)*(GMWQ!$ND$2:$ND$60=G$4)*(GMWQ!$NF$2:$NF$60=G$1),0),$E34-1966)} -> 2051.874 | H34: {=INDEX(GMWQ!$A$2:$NF$60,MATCH(1,(GMWQ!$NE$2:$NE$60=H$3)*(GMWQ!$ND$2:$ND$60=H$4)*(GMWQ!$NF$2:$NF$60=H$1),0),$E34-1966)} -> 52.64415 | I34: {=INDEX(GMWQ!$A$2:$NF$60,MATCH(1,(GMWQ!$NE$2:$NE$60=I$3)*(GMWQ!$ND$2:$ND$60=I$4)*(GMWQ!$NF$2:$NF$60=I$1),0),$E34-1966)} -> 12092 | J34: {=INDEX(GMWQ!$A$2:$NF$60,MATCH(1,(GMWQ!$NE$2:$NE$60=J$3)*(GMWQ!$ND$2:$ND$60=J$4)*(GMWQ!$NF$2:$NF$60=J$1),0),$E34-1966)} -> 59789 | K34: {=INDEX(GMWQ!$A$2:$NF$60,MATCH(1,(GMWQ!$NE$2:$NE$60=K$3)*(GMWQ!$ND$2:$ND$60=K$4)*(GMWQ!$NF$2:$NF$60=K$1),0),$E34-1966)} -> 27095 | L34: {=INDEX(GMWQ!$A$2:$NF$60,MATCH(1,(GMWQ!$NE$2:$NE$60=L$3)*(GMWQ!$ND$2:$ND$60=L$4)*(GMWQ!$NF$2:$NF$60=L$1),0),$E34-1966)} -> 39802 | M34: {=INDEX(GMWQ!$A$2:$NF$60,MATCH(1,(GMWQ!$NE$2:$NE$60=M$3)*(GMWQ!$ND$2:$ND$60=M$4)*(GMWQ!$NF$2:$NF$60=M$1),0),$E34-1966)} -> 162173 | ... Q34: {=INDEX(GMWQ!$A$2:$NF$60,MATCH(1,(GMWQ!$NE$2:$NE$60=Q$3)*(GMWQ!$ND$2:$ND$60=Q$4)*(GMWQ!$NF$2:$NF$60=Q$1),0),$E34-1966)} -> 25280
A35: 1980 | B35: =+B31+1 -> 1980 | C35: =+C31+1 -> 1979 | D35: =+D31+1 -> 1979 | E35: =+E34+1 -> 2001 | F35: {=INDEX(GMWQ!$A$2:$NF$60,MATCH(1,(GMWQ!$NE$2:$NE$60=F$3)*(GMWQ!$ND$2:$ND$60=F$4)*(GMWQ!$NF$2:$NF$60=F$1),0),$E35-1966)} -> 32.54055 | G35: {=INDEX(GMWQ!$A$2:$NF$60,MATCH(1,(GMWQ!$NE$2:$NE$60=G$3)*(GMWQ!$ND$2:$ND$60=G$4)*(GMWQ!$NF$2:$NF$60=G$1),0),$E35-1966)} -> 2203.656 | H35: {=INDEX(GMWQ!$A$2:$NF$60,MATCH(1,(GMWQ!$NE$2:$NE$60=H$3)*(GMWQ!$ND$2:$ND$60=H$4)*(GMWQ!$NF$2:$NF$60=H$1),0),$E35-1966)} -> 54.9067 | I35: {=INDEX(GMWQ!$A$2:$NF$60,MATCH(1,(GMWQ!$NE$2:$NE$60=I$3)*(GMWQ!$ND$2:$ND$60=I$4)*(GMWQ!$NF$2:$NF$60=I$1),0),$E35-1966)} -> 12467 | J35: {=INDEX(GMWQ!$A$2:$NF$60,MATCH(1,(GMWQ!$NE$2:$NE$60=J$3)*(GMWQ!$ND$2:$ND$60=J$4)*(GMWQ!$NF$2:$NF$60=J$1),0),$E35-1966)} -> 62107 | K35: {=INDEX(GMWQ!$A$2:$NF$60,MATCH(1,(GMWQ!$NE$2:$NE$60=K$3)*(GMWQ!$ND$2:$ND$60=K$4)*(GMWQ!$NF$2:$NF$60=K$1),0),$E35-1966)} -> 28290 | L35: {=INDEX(GMWQ!$A$2:$NF$60,MATCH(1,(GMWQ!$NE$2:$NE$60=L$3)*(GMWQ!$ND$2:$ND$60=L$4)*(GMWQ!$NF$2:$NF$60=L$1),0),$E35-1966)} -> 40290 | M35: {=INDEX(GMWQ!$A$2:$NF$60,MATCH(1,(GMWQ!$NE$2:$NE$60=M$3)*(GMWQ!$ND$2:$ND$60=M$4)*(GMWQ!$NF$2:$NF$60=M$1),0),$E35-1966)} -> 157780 | ... Q35: {=INDEX(GMWQ!$A$2:$NF$60,MATCH(1,(GMWQ!$NE$2:$NE$60=Q$3)*(GMWQ!$ND$2:$ND$60=Q$4)*(GMWQ!$NF$2:$NF$60=Q$1),0),$E35-1966)} -> 25250
B36: =+B32+1 -> 1980 | C36: =+C32+1 -> 1980 | E36: =+E35+1 -> 2002 | F36: {=INDEX(GMWQ!$A$2:$NF$60,MATCH(1,(GMWQ!$NE$2:$NE$60=F$3)*(GMWQ!$ND$2:$ND$60=F$4)*(GMWQ!$NF$2:$NF$60=F$1),0),$E36-1966)} -> 34.72695 | G36: {=INDEX(GMWQ!$A$2:$NF$60,MATCH(1,(GMWQ!$NE$2:$NE$60=G$3)*(GMWQ!$ND$2:$ND$60=G$4)*(GMWQ!$NF$2:$NF$60=G$1),0),$E36-1966)} -> 2273.364 | H36: {=INDEX(GMWQ!$A$2:$NF$60,MATCH(1,(GMWQ!$NE$2:$NE$60=H$3)*(GMWQ!$ND$2:$ND$60=H$4)*(GMWQ!$NF$2:$NF$60=H$1),0),$E36-1966)} -> 59.1701 | I36: {=INDEX(GMWQ!$A$2:$NF$60,MATCH(1,(GMWQ!$NE$2:$NE$60=I$3)*(GMWQ!$ND$2:$ND$60=I$4)*(GMWQ!$NF$2:$NF$60=I$1),0),$E36-1966)} -> 12391 | J36: {=INDEX(GMWQ!$A$2:$NF$60,MATCH(1,(GMWQ!$NE$2:$NE$60=J$3)*(GMWQ!$ND$2:$ND$60=J$4)*(GMWQ!$NF$2:$NF$60=J$1),0),$E36-1966)} -> 63704 | K36: {=INDEX(GMWQ!$A$2:$NF$60,MATCH(1,(GMWQ!$NE$2:$NE$60=K$3)*(GMWQ!$ND$2:$ND$60=K$4)*(GMWQ!$NF$2:$NF$60=K$1),0),$E36-1966)} -> 29578 | L36: {=INDEX(GMWQ!$A$2:$NF$60,MATCH(1,(GMWQ!$NE$2:$NE$60=L$3)*(GMWQ!$ND$2:$ND$60=L$4)*(GMWQ!$NF$2:$NF$60=L$1),0),$E36-1966)} -> 41818 | M36: {=INDEX(GMWQ!$A$2:$NF$60,MATCH(1,(GMWQ!$NE$2:$NE$60=M$3)*(GMWQ!$ND$2:$ND$60=M$4)*(GMWQ!$NF$2:$NF$60=M$1),0),$E36-1966)} -> 158083 | ... Q36: {=INDEX(GMWQ!$A$2:$NF$60,MATCH(1,(GMWQ!$NE$2:$NE$60=Q$3)*(GMWQ!$ND$2:$ND$60=Q$4)*(GMWQ!$NF$2:$NF$60=Q$1),0),$E36-1966)} -> 25190
B37: =+B33+1 -> 1980 | C37: =+C33+1 -> 1980 | E37: =+E36+1 -> 2003 | F37: {=INDEX(GMWQ!$A$2:$NF$60,MATCH(1,(GMWQ!$NE$2:$NE$60=F$3)*(GMWQ!$ND$2:$ND$60=F$4)*(GMWQ!$NF$2:$NF$60=F$1),0),$E37-1966)} -> 35.92819 | G37: {=INDEX(GMWQ!$A$2:$NF$60,MATCH(1,(GMWQ!$NE$2:$NE$60=G$3)*(GMWQ!$ND$2:$ND$60=G$4)*(GMWQ!$NF$2:$NF$60=G$1),0),$E37-1966)} -> 2332.952 | H37: {=INDEX(GMWQ!$A$2:$NF$60,MATCH(1,(GMWQ!$NE$2:$NE$60=H$3)*(GMWQ!$ND$2:$ND$60=H$4)*(GMWQ!$NF$2:$NF$60=H$1),0),$E37-1966)} -> 63.64214 | I37: {=INDEX(GMWQ!$A$2:$NF$60,MATCH(1,(GMWQ!$NE$2:$NE$60=I$3)*(GMWQ!$ND$2:$ND$60=I$4)*(GMWQ!$NF$2:$NF$60=I$1),0),$E37-1966)} -> 11886 | J37: {=INDEX(GMWQ!$A$2:$NF$60,MATCH(1,(GMWQ!$NE$2:$NE$60=J$3)*(GMWQ!$ND$2:$ND$60=J$4)*(GMWQ!$NF$2:$NF$60=J$1),0),$E37-1966)} -> 66021 | K37: {=INDEX(GMWQ!$A$2:$NF$60,MATCH(1,(GMWQ!$NE$2:$NE$60=K$3)*(GMWQ!$ND$2:$ND$60=K$4)*(GMWQ!$NF$2:$NF$60=K$1),0),$E37-1966)} -> 30485 | L37: {=INDEX(GMWQ!$A$2:$NF$60,MATCH(1,(GMWQ!$NE$2:$NE$60=L$3)*(GMWQ!$ND$2:$ND$60=L$4)*(GMWQ!$NF$2:$NF$60=L$1),0),$E37-1966)} -> 43433 | M37: {=INDEX(GMWQ!$A$2:$NF$60,MATCH(1,(GMWQ!$NE$2:$NE$60=M$3)*(GMWQ!$ND$2:$ND$60=M$4)*(GMWQ!$NF$2:$NF$60=M$1),0),$E37-1966)} -> 160445 | ... Q37: {=INDEX(GMWQ!$A$2:$NF$60,MATCH(1,(GMWQ!$NE$2:$NE$60=Q$3)*(GMWQ!$ND$2:$ND$60=Q$4)*(GMWQ!$NF$2:$NF$60=Q$1),0),$E37-1966)} -> 25050
B38: =+B34+1 -> 1980 | C38: =+C34+1 -> 1980 | E38: =+E37+1 -> 2004 | F38: {=INDEX(GMWQ!$A$2:$NF$60,MATCH(1,(GMWQ!$NE$2:$NE$60=F$3)*(GMWQ!$ND$2:$ND$60=F$4)*(GMWQ!$NF$2:$NF$60=F$1),0),$E38-1966)} -> 37.0792 | G38: {=INDEX(GMWQ!$A$2:$NF$60,MATCH(1,(GMWQ!$NE$2:$NE$60=G$3)*(GMWQ!$ND$2:$ND$60=G$4)*(GMWQ!$NF$2:$NF$60=G$1),0),$E38-1966)} -> 2420.649 | H38: {=INDEX(GMWQ!$A$2:$NF$60,MATCH(1,(GMWQ!$NE$2:$NE$60=H$3)*(GMWQ!$ND$2:$ND$60=H$4)*(GMWQ!$NF$2:$NF$60=H$1),0),$E38-1966)} -> 66.77174 | I38: {=INDEX(GMWQ!$A$2:$NF$60,MATCH(1,(GMWQ!$NE$2:$NE$60=I$3)*(GMWQ!$ND$2:$ND$60=I$4)*(GMWQ!$NF$2:$NF$60=I$1),0),$E38-1966)} -> 12891 | J38: {=INDEX(GMWQ!$A$2:$NF$60,MATCH(1,(GMWQ!$NE$2:$NE$60=J$3)*(GMWQ!$ND$2:$ND$60=J$4)*(GMWQ!$NF$2:$NF$60=J$1),0),$E38-1966)} -> 68138 | K38: {=INDEX(GMWQ!$A$2:$NF$60,MATCH(1,(GMWQ!$NE$2:$NE$60=K$3)*(GMWQ!$ND$2:$ND$60=K$4)*(GMWQ!$NF$2:$NF$60=K$1),0),$E38-1966)} -> 30980 | L38: {=INDEX(GMWQ!$A$2:$NF$60,MATCH(1,(GMWQ!$NE$2:$NE$60=L$3)*(GMWQ!$ND$2:$ND$60=L$4)*(GMWQ!$NF$2:$NF$60=L$1),0),$E38-1966)} -> 44864 | M38: {=INDEX(GMWQ!$A$2:$NF$60,MATCH(1,(GMWQ!$NE$2:$NE$60=M$3)*(GMWQ!$ND$2:$ND$60=M$4)*(GMWQ!$NF$2:$NF$60=M$1),0),$E38-1966)} -> 158931 | ... Q38: {=INDEX(GMWQ!$A$2:$NF$60,MATCH(1,(GMWQ!$NE$2:$NE$60=Q$3)*(GMWQ!$ND$2:$ND$60=Q$4)*(GMWQ!$NF$2:$NF$60=Q$1),0),$E38-1966)} -> 24855
A39: 1981 | B39: =+B35+1 -> 1981 | C39: =+C35+1 -> 1980 | D39: =+D35+1 -> 1980 | E39: =+E38+1 -> 2005 | F39: {=INDEX(GMWQ!$A$2:$NF$60,MATCH(1,(GMWQ!$NE$2:$NE$60=F$3)*(GMWQ!$ND$2:$ND$60=F$4)*(GMWQ!$NF$2:$NF$60=F$1),0),$E39-1966)} -> 37.69285 | G39: {=INDEX(GMWQ!$A$2:$NF$60,MATCH(1,(GMWQ!$NE$2:$NE$60=G$3)*(GMWQ!$ND$2:$ND$60=G$4)*(GMWQ!$NF$2:$NF$60=G$1),0),$E39-1966)} -> 2498.227 | H39: {=INDEX(GMWQ!$A$2:$NF$60,MATCH(1,(GMWQ!$NE$2:$NE$60=H$3)*(GMWQ!$ND$2:$ND$60=H$4)*(GMWQ!$NF$2:$NF$60=H$1),0),$E39-1966)} -> 67.32769 | I39: {=INDEX(GMWQ!$A$2:$NF$60,MATCH(1,(GMWQ!$NE$2:$NE$60=I$3)*(GMWQ!$ND$2:$ND$60=I$4)*(GMWQ!$NF$2:$NF$60=I$1),0),$E39-1966)} -> 12538 | J39: {=INDEX(GMWQ!$A$2:$NF$60,MATCH(1,(GMWQ!$NE$2:$NE$60=J$3)*(GMWQ!$ND$2:$ND$60=J$4)*(GMWQ!$NF$2:$NF$60=J$1),0),$E39-1966)} -> 69940 | K39: {=INDEX(GMWQ!$A$2:$NF$60,MATCH(1,(GMWQ!$NE$2:$NE$60=K$3)*(GMWQ!$ND$2:$ND$60=K$4)*(GMWQ!$NF$2:$NF$60=K$1),0),$E39-1966)} -> 31183 | L39: {=INDEX(GMWQ!$A$2:$NF$60,MATCH(1,(GMWQ!$NE$2:$NE$60=L$3)*(GMWQ!$ND$2:$ND$60=L$4)*(GMWQ!$NF$2:$NF$60=L$1),0),$E39-1966)} -> 46552 | M39: {=INDEX(GMWQ!$A$2:$NF$60,MATCH(1,(GMWQ!$NE$2:$NE$60=M$3)*(GMWQ!$ND$2:$ND$60=M$4)*(GMWQ!$NF$2:$NF$60=M$1),0),$E39-1966)} -> 160486 | ... Q39: {=INDEX(GMWQ!$A$2:$NF$60,MATCH(1,(GMWQ!$NE$2:$NE$60=Q$3)*(GMWQ!$ND$2:$ND$60=Q$4)*(GMWQ!$NF$2:$NF$60=Q$1),0),$E39-1966)} -> 24661
B40: =+B36+1 -> 1981 | C40: =+C36+1 -> 1981 | E40: =+E39+1 -> 2006 | F40: {=INDEX(GMWQ!$A$2:$NF$60,MATCH(1,(GMWQ!$NE$2:$NE$60=F$3)*(GMWQ!$ND$2:$ND$60=F$4)*(GMWQ!$NF$2:$NF$60=F$1),0),$E40-1966)} -> 38.15502 | G40: {=INDEX(GMWQ!$A$2:$NF$60,MATCH(1,(GMWQ!$NE$2:$NE$60=G$3)*(GMWQ!$ND$2:$ND$60=G$4)*(GMWQ!$NF$2:$NF$60=G$1),0),$E40-1966)} -> 2399.287 | H40: {=INDEX(GMWQ!$A$2:$NF$60,MATCH(1,(GMWQ!$NE$2:$NE$60=H$3)*(GMWQ!$ND$2:$ND$60=H$4)*(GMWQ!$NF$2:$NF$60=H$1),0),$E40-1966)} -> 69.61449 | I40: {=INDEX(GMWQ!$A$2:$NF$60,MATCH(1,(GMWQ!$NE$2:$NE$60=I$3)*(GMWQ!$ND$2:$ND$60=I$4)*(GMWQ!$NF$2:$NF$60=I$1),0),$E40-1966)} -> 13239 | J40: {=INDEX(GMWQ!$A$2:$NF$60,MATCH(1,(GMWQ!$NE$2:$NE$60=J$3)*(GMWQ!$ND$2:$ND$60=J$4)*(GMWQ!$NF$2:$NF$60=J$1),0),$E40-1966)} -> 71334 | K40: {=INDEX(GMWQ!$A$2:$NF$60,MATCH(1,(GMWQ!$NE$2:$NE$60=K$3)*(GMWQ!$ND$2:$ND$60=K$4)*(GMWQ!$NF$2:$NF$60=K$1),0),$E40-1966)} -> 31633 | L40: {=INDEX(GMWQ!$A$2:$NF$60,MATCH(1,(GMWQ!$NE$2:$NE$60=L$3)*(GMWQ!$ND$2:$ND$60=L$4)*(GMWQ!$NF$2:$NF$60=L$1),0),$E40-1966)} -> 47036 | M40: {=INDEX(GMWQ!$A$2:$NF$60,MATCH(1,(GMWQ!$NE$2:$NE$60=M$3)*(GMWQ!$ND$2:$ND$60=M$4)*(GMWQ!$NF$2:$NF$60=M$1),0),$E40-1966)} -> 158130 | ... Q40: {=INDEX(GMWQ!$A$2:$NF$60,MATCH(1,(GMWQ!$NE$2:$NE$60=Q$3)*(GMWQ!$ND$2:$ND$60=Q$4)*(GMWQ!$NF$2:$NF$60=Q$1),0),$E40-1966)} -> 24495
B41: =+B37+1 -> 1981 | C41: =+C37+1 -> 1981 | E41: =+E40+1 -> 2007 | F41: {=INDEX(GMWQ!$A$2:$NF$60,MATCH(1,(GMWQ!$NE$2:$NE$60=F$3)*(GMWQ!$ND$2:$ND$60=F$4)*(GMWQ!$NF$2:$NF$60=F$1),0),$E41-1966)} -> 38.56902 | G41: {=INDEX(GMWQ!$A$2:$NF$60,MATCH(1,(GMWQ!$NE$2:$NE$60=G$3)*(GMWQ!$ND$2:$ND$60=G$4)*(GMWQ!$NF$2:$NF$60=G$1),0),$E41-1966)} -> 2452.13 | H41: {=INDEX(GMWQ!$A$2:$NF$60,MATCH(1,(GMWQ!$NE$2:$NE$60=H$3)*(GMWQ!$ND$2:$ND$60=H$4)*(GMWQ!$NF$2:$NF$60=H$1),0),$E41-1966)} -> 73.35294 | I41: {=INDEX(GMWQ!$A$2:$NF$60,MATCH(1,(GMWQ!$NE$2:$NE$60=I$3)*(GMWQ!$ND$2:$ND$60=I$4)*(GMWQ!$NF$2:$NF$60=I$1),0),$E41-1966)} -> 14561 | J41: {=INDEX(GMWQ!$A$2:$NF$60,MATCH(1,(GMWQ!$NE$2:$NE$60=J$3)*(GMWQ!$ND$2:$ND$60=J$4)*(GMWQ!$NF$2:$NF$60=J$1),0),$E41-1966)} -> 73310 | K41: {=INDEX(GMWQ!$A$2:$NF$60,MATCH(1,(GMWQ!$NE$2:$NE$60=K$3)*(GMWQ!$ND$2:$ND$60=K$4)*(GMWQ!$NF$2:$NF$60=K$1),0),$E41-1966)} -> 32287 | L41: {=INDEX(GMWQ!$A$2:$NF$60,MATCH(1,(GMWQ!$NE$2:$NE$60=L$3)*(GMWQ!$ND$2:$ND$60=L$4)*(GMWQ!$NF$2:$NF$60=L$1),0),$E41-1966)} -> 47924 | M41: {=INDEX(GMWQ!$A$2:$NF$60,MATCH(1,(GMWQ!$NE$2:$NE$60=M$3)*(GMWQ!$ND$2:$ND$60=M$4)*(GMWQ!$NF$2:$NF$60=M$1),0),$E41-1966)} -> 157598 | ... Q41: {=INDEX(GMWQ!$A$2:$NF$60,MATCH(1,(GMWQ!$NE$2:$NE$60=Q$3)*(GMWQ!$ND$2:$ND$60=Q$4)*(GMWQ!$NF$2:$NF$60=Q$1),0),$E41-1966)} -> 24355
B42: =+B38+1 -> 1981 | C42: =+C38+1 -> 1981 | E42: =+E41+1 -> 2008 | F42: {=INDEX(GMWQ!$A$2:$NF$60,MATCH(1,(GMWQ!$NE$2:$NE$60=F$3)*(GMWQ!$ND$2:$ND$60=F$4)*(GMWQ!$NF$2:$NF$60=F$1),0),$E42-1966)} -> 39.2195 | G42: {=INDEX(GMWQ!$A$2:$NF$60,MATCH(1,(GMWQ!$NE$2:$NE$60=G$3)*(GMWQ!$ND$2:$ND$60=G$4)*(GMWQ!$NF$2:$NF$60=G$1),0),$E42-1966)} -> 2560.064 | H42: {=INDEX(GMWQ!$A$2:$NF$60,MATCH(1,(GMWQ!$NE$2:$NE$60=H$3)*(GMWQ!$ND$2:$ND$60=H$4)*(GMWQ!$NF$2:$NF$60=H$1),0),$E42-1966)} -> 76.17709 | I42: {=INDEX(GMWQ!$A$2:$NF$60,MATCH(1,(GMWQ!$NE$2:$NE$60=I$3)*(GMWQ!$ND$2:$ND$60=I$4)*(GMWQ!$NF$2:$NF$60=I$1),0),$E42-1966)} -> 15234 | J42: {=INDEX(GMWQ!$A$2:$NF$60,MATCH(1,(GMWQ!$NE$2:$NE$60=J$3)*(GMWQ!$ND$2:$ND$60=J$4)*(GMWQ!$NF$2:$NF$60=J$1),0),$E42-1966)} -> 75596 | K42: {=INDEX(GMWQ!$A$2:$NF$60,MATCH(1,(GMWQ!$NE$2:$NE$60=K$3)*(GMWQ!$ND$2:$ND$60=K$4)*(GMWQ!$NF$2:$NF$60=K$1),0),$E42-1966)} -> 32870 | L42: {=INDEX(GMWQ!$A$2:$NF$60,MATCH(1,(GMWQ!$NE$2:$NE$60=L$3)*(GMWQ!$ND$2:$ND$60=L$4)*(GMWQ!$NF$2:$NF$60=L$1),0),$E42-1966)} -> 49843 | M42: {=INDEX(GMWQ!$A$2:$NF$60,MATCH(1,(GMWQ!$NE$2:$NE$60=M$3)*(GMWQ!$ND$2:$ND$60=M$4)*(GMWQ!$NF$2:$NF$60=M$1),0),$E42-1966)} -> 158580 | ... Q42: {=INDEX(GMWQ!$A$2:$NF$60,MATCH(1,(GMWQ!$NE$2:$NE$60=Q$3)*(GMWQ!$ND$2:$ND$60=Q$4)*(GMWQ!$NF$2:$NF$60=Q$1),0),$E42-1966)} -> 24209
A43: 1982 | B43: =+B39+1 -> 1982 | C43: =+C39+1 -> 1981 | D43: =+D39+1 -> 1981 | E43: =+E42+1 -> 2009 | F43: {=INDEX(GMWQ!$A$2:$NF$60,MATCH(1,(GMWQ!$NE$2:$NE$60=F$3)*(GMWQ!$ND$2:$ND$60=F$4)*(GMWQ!$NF$2:$NF$60=F$1),0),$E43-1966)} -> 39.83857 | G43: {=INDEX(GMWQ!$A$2:$NF$60,MATCH(1,(GMWQ!$NE$2:$NE$60=G$3)*(GMWQ!$ND$2:$ND$60=G$4)*(GMWQ!$NF$2:$NF$60=G$1),0),$E43-1966)} -> 2665.75 | H43: {=INDEX(GMWQ!$A$2:$NF$60,MATCH(1,(GMWQ!$NE$2:$NE$60=H$3)*(GMWQ!$ND$2:$ND$60=H$4)*(GMWQ!$NF$2:$NF$60=H$1),0),$E43-1966)} -> 76.58652 | I43: {=INDEX(GMWQ!$A$2:$NF$60,MATCH(1,(GMWQ!$NE$2:$NE$60=I$3)*(GMWQ!$ND$2:$ND$60=I$4)*(GMWQ!$NF$2:$NF$60=I$1),0),$E43-1966)} -> 14539 | J43: {=INDEX(GMWQ!$A$2:$NF$60,MATCH(1,(GMWQ!$NE$2:$NE$60=J$3)*(GMWQ!$ND$2:$ND$60=J$4)*(GMWQ!$NF$2:$NF$60=J$1),0),$E43-1966)} -> 77468 | K43: {=INDEX(GMWQ!$A$2:$NF$60,MATCH(1,(GMWQ!$NE$2:$NE$60=K$3)*(GMWQ!$ND$2:$ND$60=K$4)*(GMWQ!$NF$2:$NF$60=K$1),0),$E43-1966)} -> 33383 | L43: {=INDEX(GMWQ!$A$2:$NF$60,MATCH(1,(GMWQ!$NE$2:$NE$60=L$3)*(GMWQ!$ND$2:$ND$60=L$4)*(GMWQ!$NF$2:$NF$60=L$1),0),$E43-1966)} -> 50837 | M43: {=INDEX(GMWQ!$A$2:$NF$60,MATCH(1,(GMWQ!$NE$2:$NE$60=M$3)*(GMWQ!$ND$2:$ND$60=M$4)*(GMWQ!$NF$2:$NF$60=M$1),0),$E43-1966)} -> 157715 | ... Q43: {=INDEX(GMWQ!$A$2:$NF$60,MATCH(1,(GMWQ!$NE$2:$NE$60=Q$3)*(GMWQ!$ND$2:$ND$60=Q$4)*(GMWQ!$NF$2:$NF$60=Q$1),0),$E43-1966)} -> 24120
B44: =+B40+1 -> 1982 | C44: =+C40+1 -> 1982 | E44: =+E43+1 -> 2010 | F44: {=INDEX(GMWQ!$A$2:$NF$60,MATCH(1,(GMWQ!$NE$2:$NE$60=F$3)*(GMWQ!$ND$2:$ND$60=F$4)*(GMWQ!$NF$2:$NF$60=F$1),0),$E44-1966)} -> 39.87285 | G44: {=INDEX(GMWQ!$A$2:$NF$60,MATCH(1,(GMWQ!$NE$2:$NE$60=G$3)*(GMWQ!$ND$2:$ND$60=G$4)*(GMWQ!$NF$2:$NF$60=G$1),0),$E44-1966)} -> 2569.059 | H44: {=INDEX(GMWQ!$A$2:$NF$60,MATCH(1,(GMWQ!$NE$2:$NE$60=H$3)*(GMWQ!$ND$2:$ND$60=H$4)*(GMWQ!$NF$2:$NF$60=H$1),0),$E44-1966)} -> 78.91912 | I44: {=INDEX(GMWQ!$A$2:$NF$60,MATCH(1,(GMWQ!$NE$2:$NE$60=I$3)*(GMWQ!$ND$2:$ND$60=I$4)*(GMWQ!$NF$2:$NF$60=I$1),0),$E44-1966)} -> 16436 | J44: {=INDEX(GMWQ!$A$2:$NF$60,MATCH(1,(GMWQ!$NE$2:$NE$60=J$3)*(GMWQ!$ND$2:$ND$60=J$4)*(GMWQ!$NF$2:$NF$60=J$1),0),$E44-1966)} -> 78993 | K44: {=INDEX(GMWQ!$A$2:$NF$60,MATCH(1,(GMWQ!$NE$2:$NE$60=K$3)*(GMWQ!$ND$2:$ND$60=K$4)*(GMWQ!$NF$2:$NF$60=K$1),0),$E44-1966)} -> 33923 | L44: {=INDEX(GMWQ!$A$2:$NF$60,MATCH(1,(GMWQ!$NE$2:$NE$60=L$3)*(GMWQ!$ND$2:$ND$60=L$4)*(GMWQ!$NF$2:$NF$60=L$1),0),$E44-1966)} -> 52380 | M44: {=INDEX(GMWQ!$A$2:$NF$60,MATCH(1,(GMWQ!$NE$2:$NE$60=M$3)*(GMWQ!$ND$2:$ND$60=M$4)*(GMWQ!$NF$2:$NF$60=M$1),0),$E44-1966)} -> 160483 | ... Q44: {=INDEX(GMWQ!$A$2:$NF$60,MATCH(1,(GMWQ!$NE$2:$NE$60=Q$3)*(GMWQ!$ND$2:$ND$60=Q$4)*(GMWQ!$NF$2:$NF$60=Q$1),0),$E44-1966)} -> 24027
B45: =+B41+1 -> 1982 | C45: =+C41+1 -> 1982 | E45: =+E44+1 -> 2011 | F45: {=INDEX(GMWQ!$A$2:$NF$60,MATCH(1,(GMWQ!$NE$2:$NE$60=F$3)*(GMWQ!$ND$2:$ND$60=F$4)*(GMWQ!$NF$2:$NF$60=F$1),0),$E45-1966)} -> 40.10712 | G45: {=INDEX(GMWQ!$A$2:$NF$60,MATCH(1,(GMWQ!$NE$2:$NE$60=G$3)*(GMWQ!$ND$2:$ND$60=G$4)*(GMWQ!$NF$2:$NF$60=G$1),0),$E45-1966)} -> 2582.55 | H45: {=INDEX(GMWQ!$A$2:$NF$60,MATCH(1,(GMWQ!$NE$2:$NE$60=H$3)*(GMWQ!$ND$2:$ND$60=H$4)*(GMWQ!$NF$2:$NF$60=H$1),0),$E45-1966)} -> 82.15866 | I45: {=INDEX(GMWQ!$A$2:$NF$60,MATCH(1,(GMWQ!$NE$2:$NE$60=I$3)*(GMWQ!$ND$2:$ND$60=I$4)*(GMWQ!$NF$2:$NF$60=I$1),0),$E45-1966)} -> 16844 | J45: {=INDEX(GMWQ!$A$2:$NF$60,MATCH(1,(GMWQ!$NE$2:$NE$60=J$3)*(GMWQ!$ND$2:$ND$60=J$4)*(GMWQ!$NF$2:$NF$60=J$1),0),$E45-1966)} -> 80430 | K45: {=INDEX(GMWQ!$A$2:$NF$60,MATCH(1,(GMWQ!$NE$2:$NE$60=K$3)*(GMWQ!$ND$2:$ND$60=K$4)*(GMWQ!$NF$2:$NF$60=K$1),0),$E45-1966)} -> 34218 | L45: {=INDEX(GMWQ!$A$2:$NF$60,MATCH(1,(GMWQ!$NE$2:$NE$60=L$3)*(GMWQ!$ND$2:$ND$60=L$4)*(GMWQ!$NF$2:$NF$60=L$1),0),$E45-1966)} -> 52615 | M45: {=INDEX(GMWQ!$A$2:$NF$60,MATCH(1,(GMWQ!$NE$2:$NE$60=M$3)*(GMWQ!$ND$2:$ND$60=M$4)*(GMWQ!$NF$2:$NF$60=M$1),0),$E45-1966)} -> 159367 | ... Q45: {=INDEX(GMWQ!$A$2:$NF$60,MATCH(1,(GMWQ!$NE$2:$NE$60=Q$3)*(GMWQ!$ND$2:$ND$60=Q$4)*(GMWQ!$NF$2:$NF$60=Q$1),0),$E45-1966)} -> 23901
B46: =+B42+1 -> 1982 | C46: =+C42+1 -> 1982 | E46: =+E45+1 -> 2012 | F46: {=INDEX(GMWQ!$A$2:$NF$60,MATCH(1,(GMWQ!$NE$2:$NE$60=F$3)*(GMWQ!$ND$2:$ND$60=F$4)*(GMWQ!$NF$2:$NF$60=F$1),0),$E46-1966)} -> 40.31527 | G46: {=INDEX(GMWQ!$A$2:$NF$60,MATCH(1,(GMWQ!$NE$2:$NE$60=G$3)*(GMWQ!$ND$2:$ND$60=G$4)*(GMWQ!$NF$2:$NF$60=G$1),0),$E46-1966)} -> 2688.236 | H46: {=INDEX(GMWQ!$A$2:$NF$60,MATCH(1,(GMWQ!$NE$2:$NE$60=H$3)*(GMWQ!$ND$2:$ND$60=H$4)*(GMWQ!$NF$2:$NF$60=H$1),0),$E46-1966)} -> 83.43923 | I46: {=INDEX(GMWQ!$A$2:$NF$60,MATCH(1,(GMWQ!$NE$2:$NE$60=I$3)*(GMWQ!$ND$2:$ND$60=I$4)*(GMWQ!$NF$2:$NF$60=I$1),0),$E46-1966)} -> 17632 | J46: {=INDEX(GMWQ!$A$2:$NF$60,MATCH(1,(GMWQ!$NE$2:$NE$60=J$3)*(GMWQ!$ND$2:$ND$60=J$4)*(GMWQ!$NF$2:$NF$60=J$1),0),$E46-1966)} -> 82667 | K46: {=INDEX(GMWQ!$A$2:$NF$60,MATCH(1,(GMWQ!$NE$2:$NE$60=K$3)*(GMWQ!$ND$2:$ND$60=K$4)*(GMWQ!$NF$2:$NF$60=K$1),0),$E46-1966)} -> 34584 | L46: {=INDEX(GMWQ!$A$2:$NF$60,MATCH(1,(GMWQ!$NE$2:$NE$60=L$3)*(GMWQ!$ND$2:$ND$60=L$4)*(GMWQ!$NF$2:$NF$60=L$1),0),$E46-1966)} -> 53960 | M46: {=INDEX(GMWQ!$A$2:$NF$60,MATCH(1,(GMWQ!$NE$2:$NE$60=M$3)*(GMWQ!$ND$2:$ND$60=M$4)*(GMWQ!$NF$2:$NF$60=M$1),0),$E46-1966)} -> 159886 | ... Q46: {=INDEX(GMWQ!$A$2:$NF$60,MATCH(1,(GMWQ!$NE$2:$NE$60=Q$3)*(GMWQ!$ND$2:$ND$60=Q$4)*(GMWQ!$NF$2:$NF$60=Q$1),0),$E46-1966)} -> 23755
A47: 1983 | B47: =+B43+1 -> 1983 | C47: =+C43+1 -> 1982 | D47: =+D43+1 -> 1982 | E47: =+E46+1 -> 2013 | F47: {=INDEX(GMWQ!$A$2:$NF$60,MATCH(1,(GMWQ!$NE$2:$NE$60=F$3)*(GMWQ!$ND$2:$ND$60=F$4)*(GMWQ!$NF$2:$NF$60=F$1),0),$E47-1966)} -> 40.52491 | G47: {=INDEX(GMWQ!$A$2:$NF$60,MATCH(1,(GMWQ!$NE$2:$NE$60=G$3)*(GMWQ!$ND$2:$ND$60=G$4)*(GMWQ!$NF$2:$NF$60=G$1),0),$E47-1966)} -> 2872.623 | H47: {=INDEX(GMWQ!$A$2:$NF$60,MATCH(1,(GMWQ!$NE$2:$NE$60=H$3)*(GMWQ!$ND$2:$ND$60=H$4)*(GMWQ!$NF$2:$NF$60=H$1),0),$E47-1966)} -> 84.92252 | I47: {=INDEX(GMWQ!$A$2:$NF$60,MATCH(1,(GMWQ!$NE$2:$NE$60=I$3)*(GMWQ!$ND$2:$ND$60=I$4)*(GMWQ!$NF$2:$NF$60=I$1),0),$E47-1966)} -> 18610 | J47: {=INDEX(GMWQ!$A$2:$NF$60,MATCH(1,(GMWQ!$NE$2:$NE$60=J$3)*(GMWQ!$ND$2:$ND$60=J$4)*(GMWQ!$NF$2:$NF$60=J$1),0),$E47-1966)} -> 85727 | K47: {=INDEX(GMWQ!$A$2:$NF$60,MATCH(1,(GMWQ!$NE$2:$NE$60=K$3)*(GMWQ!$ND$2:$ND$60=K$4)*(GMWQ!$NF$2:$NF$60=K$1),0),$E47-1966)} -> 35662 | L47: {=INDEX(GMWQ!$A$2:$NF$60,MATCH(1,(GMWQ!$NE$2:$NE$60=L$3)*(GMWQ!$ND$2:$ND$60=L$4)*(GMWQ!$NF$2:$NF$60=L$1),0),$E47-1966)} -> 54514 | M47: {=INDEX(GMWQ!$A$2:$NF$60,MATCH(1,(GMWQ!$NE$2:$NE$60=M$3)*(GMWQ!$ND$2:$ND$60=M$4)*(GMWQ!$NF$2:$NF$60=M$1),0),$E47-1966)} -> 158854 | ... Q47: {=INDEX(GMWQ!$A$2:$NF$60,MATCH(1,(GMWQ!$NE$2:$NE$60=Q$3)*(GMWQ!$ND$2:$ND$60=Q$4)*(GMWQ!$NF$2:$NF$60=Q$1),0),$E47-1966)} -> 23651
B48: =+B44+1 -> 1983 | C48: =+C44+1 -> 1983 | E48: =+E47+1 -> 2014 | F48: {=INDEX(GMWQ!$A$2:$NF$60,MATCH(1,(GMWQ!$NE$2:$NE$60=F$3)*(GMWQ!$ND$2:$ND$60=F$4)*(GMWQ!$NF$2:$NF$60=F$1),0),$E48-1966)} -> 40.86721 | G48: {=INDEX(GMWQ!$A$2:$NF$60,MATCH(1,(GMWQ!$NE$2:$NE$60=G$3)*(GMWQ!$ND$2:$ND$60=G$4)*(GMWQ!$NF$2:$NF$60=G$1),0),$E48-1966)} -> 2925.466 | H48: {=INDEX(GMWQ!$A$2:$NF$60,MATCH(1,(GMWQ!$NE$2:$NE$60=H$3)*(GMWQ!$ND$2:$ND$60=H$4)*(GMWQ!$NF$2:$NF$60=H$1),0),$E48-1966)} -> 88.03934 | I48: {=INDEX(GMWQ!$A$2:$NF$60,MATCH(1,(GMWQ!$NE$2:$NE$60=I$3)*(GMWQ!$ND$2:$ND$60=I$4)*(GMWQ!$NF$2:$NF$60=I$1),0),$E48-1966)} -> 18587 | J48: {=INDEX(GMWQ!$A$2:$NF$60,MATCH(1,(GMWQ!$NE$2:$NE$60=J$3)*(GMWQ!$ND$2:$ND$60=J$4)*(GMWQ!$NF$2:$NF$60=J$1),0),$E48-1966)} -> 86288 | K48: {=INDEX(GMWQ!$A$2:$NF$60,MATCH(1,(GMWQ!$NE$2:$NE$60=K$3)*(GMWQ!$ND$2:$ND$60=K$4)*(GMWQ!$NF$2:$NF$60=K$1),0),$E48-1966)} -> 36167 | L48: {=INDEX(GMWQ!$A$2:$NF$60,MATCH(1,(GMWQ!$NE$2:$NE$60=L$3)*(GMWQ!$ND$2:$ND$60=L$4)*(GMWQ!$NF$2:$NF$60=L$1),0),$E48-1966)} -> 57136 | M48: {=INDEX(GMWQ!$A$2:$NF$60,MATCH(1,(GMWQ!$NE$2:$NE$60=M$3)*(GMWQ!$ND$2:$ND$60=M$4)*(GMWQ!$NF$2:$NF$60=M$1),0),$E48-1966)} -> 165111 | ... Q48: {=INDEX(GMWQ!$A$2:$NF$60,MATCH(1,(GMWQ!$NE$2:$NE$60=Q$3)*(GMWQ!$ND$2:$ND$60=Q$4)*(GMWQ!$NF$2:$NF$60=Q$1),0),$E48-1966)} -> 23647
B49: =+B45+1 -> 1983 | C49: =+C45+1 -> 1983 | E49: =+E48+1 -> 2015 | F49: {=INDEX(GMWQ!$A$2:$NF$60,MATCH(1,(GMWQ!$NE$2:$NE$60=F$3)*(GMWQ!$ND$2:$ND$60=F$4)*(GMWQ!$NF$2:$NF$60=F$1),0),$E49-1966)} -> 41.29321 | G49: {=INDEX(GMWQ!$A$2:$NF$60,MATCH(1,(GMWQ!$NE$2:$NE$60=G$3)*(GMWQ!$ND$2:$ND$60=G$4)*(GMWQ!$NF$2:$NF$60=G$1),0),$E49-1966)} -> 2987.303 | H49: {=INDEX(GMWQ!$A$2:$NF$60,MATCH(1,(GMWQ!$NE$2:$NE$60=H$3)*(GMWQ!$ND$2:$ND$60=H$4)*(GMWQ!$NF$2:$NF$60=H$1),0),$E49-1966)} -> 90.43758 | I49: {=INDEX(GMWQ!$A$2:$NF$60,MATCH(1,(GMWQ!$NE$2:$NE$60=I$3)*(GMWQ!$ND$2:$ND$60=I$4)*(GMWQ!$NF$2:$NF$60=I$1),0),$E49-1966)} -> 19902 | J49: {=INDEX(GMWQ!$A$2:$NF$60,MATCH(1,(GMWQ!$NE$2:$NE$60=J$3)*(GMWQ!$ND$2:$ND$60=J$4)*(GMWQ!$NF$2:$NF$60=J$1),0),$E49-1966)} -> 88637 | K49: {=INDEX(GMWQ!$A$2:$NF$60,MATCH(1,(GMWQ!$NE$2:$NE$60=K$3)*(GMWQ!$ND$2:$ND$60=K$4)*(GMWQ!$NF$2:$NF$60=K$1),0),$E49-1966)} -> 36728 | L49: {=INDEX(GMWQ!$A$2:$NF$60,MATCH(1,(GMWQ!$NE$2:$NE$60=L$3)*(GMWQ!$ND$2:$ND$60=L$4)*(GMWQ!$NF$2:$NF$60=L$1),0),$E49-1966)} -> 57119 | M49: {=INDEX(GMWQ!$A$2:$NF$60,MATCH(1,(GMWQ!$NE$2:$NE$60=M$3)*(GMWQ!$ND$2:$ND$60=M$4)*(GMWQ!$NF$2:$NF$60=M$1),0),$E49-1966)} -> 163522 | ... Q49: {=INDEX(GMWQ!$A$2:$NF$60,MATCH(1,(GMWQ!$NE$2:$NE$60=Q$3)*(GMWQ!$ND$2:$ND$60=Q$4)*(GMWQ!$NF$2:$NF$60=Q$1),0),$E49-1966)} -> 23809
B50: =+B46+1 -> 1983 | C50: =+C46+1 -> 1983 | E50: =+E49+1 -> 2016 | F50: {=INDEX(GMWQ!$A$2:$NF$60,MATCH(1,(GMWQ!$NE$2:$NE$60=F$3)*(GMWQ!$ND$2:$ND$60=F$4)*(GMWQ!$NF$2:$NF$60=F$1),0),$E50-1966)} -> 41.64593 | G50: {=INDEX(GMWQ!$A$2:$NF$60,MATCH(1,(GMWQ!$NE$2:$NE$60=G$3)*(GMWQ!$ND$2:$ND$60=G$4)*(GMWQ!$NF$2:$NF$60=G$1),0),$E50-1966)} -> 3060.384 | H50: {=INDEX(GMWQ!$A$2:$NF$60,MATCH(1,(GMWQ!$NE$2:$NE$60=H$3)*(GMWQ!$ND$2:$ND$60=H$4)*(GMWQ!$NF$2:$NF$60=H$1),0),$E50-1966)} -> 91.53184 | I50: {=INDEX(GMWQ!$A$2:$NF$60,MATCH(1,(GMWQ!$NE$2:$NE$60=I$3)*(GMWQ!$ND$2:$ND$60=I$4)*(GMWQ!$NF$2:$NF$60=I$1),0),$E50-1966)} -> 20754 | J50: {=INDEX(GMWQ!$A$2:$NF$60,MATCH(1,(GMWQ!$NE$2:$NE$60=J$3)*(GMWQ!$ND$2:$ND$60=J$4)*(GMWQ!$NF$2:$NF$60=J$1),0),$E50-1966)} -> 90695 | K50: {=INDEX(GMWQ!$A$2:$NF$60,MATCH(1,(GMWQ!$NE$2:$NE$60=K$3)*(GMWQ!$ND$2:$ND$60=K$4)*(GMWQ!$NF$2:$NF$60=K$1),0),$E50-1966)} -> 37382 | L50: {=INDEX(GMWQ!$A$2:$NF$60,MATCH(1,(GMWQ!$NE$2:$NE$60=L$3)*(GMWQ!$ND$2:$ND$60=L$4)*(GMWQ!$NF$2:$NF$60=L$1),0),$E50-1966)} -> 58206 | M50: {=INDEX(GMWQ!$A$2:$NF$60,MATCH(1,(GMWQ!$NE$2:$NE$60=M$3)*(GMWQ!$ND$2:$ND$60=M$4)*(GMWQ!$NF$2:$NF$60=M$1),0),$E50-1966)} -> 164202 | ... Q50: {=INDEX(GMWQ!$A$2:$NF$60,MATCH(1,(GMWQ!$NE$2:$NE$60=Q$3)*(GMWQ!$ND$2:$ND$60=Q$4)*(GMWQ!$NF$2:$NF$60=Q$1),0),$E50-1966)} -> 23994
A51: 1984 | B51: =+B47+1 -> 1984 | C51: =+C47+1 -> 1983 | D51: =+D47+1 -> 1983 | E51: =+E50+1 -> 2017 | F51: {=INDEX(GMWQ!$A$2:$NF$60,MATCH(1,(GMWQ!$NE$2:$NE$60=F$3)*(GMWQ!$ND$2:$ND$60=F$4)*(GMWQ!$NF$2:$NF$60=F$1),0),$E51-1966)} -> 41.87712 | G51: {=INDEX(GMWQ!$A$2:$NF$60,MATCH(1,(GMWQ!$NE$2:$NE$60=G$3)*(GMWQ!$ND$2:$ND$60=G$4)*(GMWQ!$NF$2:$NF$60=G$1),0),$E51-1966)} -> 3088.492 | H51: {=INDEX(GMWQ!$A$2:$NF$60,MATCH(1,(GMWQ!$NE$2:$NE$60=H$3)*(GMWQ!$ND$2:$ND$60=H$4)*(GMWQ!$NF$2:$NF$60=H$1),0),$E51-1966)} -> 92.07954 | I51: {=INDEX(GMWQ!$A$2:$NF$60,MATCH(1,(GMWQ!$NE$2:$NE$60=I$3)*(GMWQ!$ND$2:$ND$60=I$4)*(GMWQ!$NF$2:$NF$60=I$1),0),$E51-1966)} -> 20091 | J51: {=INDEX(GMWQ!$A$2:$NF$60,MATCH(1,(GMWQ!$NE$2:$NE$60=J$3)*(GMWQ!$ND$2:$ND$60=J$4)*(GMWQ!$NF$2:$NF$60=J$1),0),$E51-1966)} -> 91663 | K51: {=INDEX(GMWQ!$A$2:$NF$60,MATCH(1,(GMWQ!$NE$2:$NE$60=K$3)*(GMWQ!$ND$2:$ND$60=K$4)*(GMWQ!$NF$2:$NF$60=K$1),0),$E51-1966)} -> 38028 | L51: {=INDEX(GMWQ!$A$2:$NF$60,MATCH(1,(GMWQ!$NE$2:$NE$60=L$3)*(GMWQ!$ND$2:$ND$60=L$4)*(GMWQ!$NF$2:$NF$60=L$1),0),$E51-1966)} -> 59961 | M51: {=INDEX(GMWQ!$A$2:$NF$60,MATCH(1,(GMWQ!$NE$2:$NE$60=M$3)*(GMWQ!$ND$2:$ND$60=M$4)*(GMWQ!$NF$2:$NF$60=M$1),0),$E51-1966)} -> 167088 | ... Q51: {=INDEX(GMWQ!$A$2:$NF$60,MATCH(1,(GMWQ!$NE$2:$NE$60=Q$3)*(GMWQ!$ND$2:$ND$60=Q$4)*(GMWQ!$NF$2:$NF$60=Q$1),0),$E51-1966)} -> 24125
B52: =+B48+1 -> 1984 | C52: =+C48+1 -> 1984 | E52: =+E51+1 -> 2018 | F52: {=INDEX(GMWQ!$A$2:$NF$60,MATCH(1,(GMWQ!$NE$2:$NE$60=F$3)*(GMWQ!$ND$2:$ND$60=F$4)*(GMWQ!$NF$2:$NF$60=F$1),0),$E52-1966)} -> 42.86386 | G52: {=INDEX(GMWQ!$A$2:$NF$60,MATCH(1,(GMWQ!$NE$2:$NE$60=G$3)*(GMWQ!$ND$2:$ND$60=G$4)*(GMWQ!$NF$2:$NF$60=G$1),0),$E52-1966)} -> 3128.967 | H52: {=INDEX(GMWQ!$A$2:$NF$60,MATCH(1,(GMWQ!$NE$2:$NE$60=H$3)*(GMWQ!$ND$2:$ND$60=H$4)*(GMWQ!$NF$2:$NF$60=H$1),0),$E52-1966)} -> 94.12758 | I52: {=INDEX(GMWQ!$A$2:$NF$60,MATCH(1,(GMWQ!$NE$2:$NE$60=I$3)*(GMWQ!$ND$2:$ND$60=I$4)*(GMWQ!$NF$2:$NF$60=I$1),0),$E52-1966)} -> 21011 | J52: {=INDEX(GMWQ!$A$2:$NF$60,MATCH(1,(GMWQ!$NE$2:$NE$60=J$3)*(GMWQ!$ND$2:$ND$60=J$4)*(GMWQ!$NF$2:$NF$60=J$1),0),$E52-1966)} -> 93433 | K52: {=INDEX(GMWQ!$A$2:$NF$60,MATCH(1,(GMWQ!$NE$2:$NE$60=K$3)*(GMWQ!$ND$2:$ND$60=K$4)*(GMWQ!$NF$2:$NF$60=K$1),0),$E52-1966)} -> 38664 | L52: {=INDEX(GMWQ!$A$2:$NF$60,MATCH(1,(GMWQ!$NE$2:$NE$60=L$3)*(GMWQ!$ND$2:$ND$60=L$4)*(GMWQ!$NF$2:$NF$60=L$1),0),$E52-1966)} -> 60260 | M52: {=INDEX(GMWQ!$A$2:$NF$60,MATCH(1,(GMWQ!$NE$2:$NE$60=M$3)*(GMWQ!$ND$2:$ND$60=M$4)*(GMWQ!$NF$2:$NF$60=M$1),0),$E52-1966)} -> 165111 | ... Q52: {=INDEX(GMWQ!$A$2:$NF$60,MATCH(1,(GMWQ!$NE$2:$NE$60=Q$3)*(GMWQ!$ND$2:$ND$60=Q$4)*(GMWQ!$NF$2:$NF$60=Q$1),0),$E52-1966)} -> 24245
B53: =+B49+1 -> 1984 | C53: =+C49+1 -> 1984 | E53: =+E52+1 -> 2019 | F53: {=INDEX(GMWQ!$A$2:$NF$60,MATCH(1,(GMWQ!$NE$2:$NE$60=F$3)*(GMWQ!$ND$2:$ND$60=F$4)*(GMWQ!$NF$2:$NF$60=F$1),0),$E53-1966)} -> 43.38656 | G53: {=INDEX(GMWQ!$A$2:$NF$60,MATCH(1,(GMWQ!$NE$2:$NE$60=G$3)*(GMWQ!$ND$2:$ND$60=G$4)*(GMWQ!$NF$2:$NF$60=G$1),0),$E53-1966)} -> 3185.183 | H53: {=INDEX(GMWQ!$A$2:$NF$60,MATCH(1,(GMWQ!$NE$2:$NE$60=H$3)*(GMWQ!$ND$2:$ND$60=H$4)*(GMWQ!$NF$2:$NF$60=H$1),0),$E53-1966)} -> 96.73234 | I53: {=INDEX(GMWQ!$A$2:$NF$60,MATCH(1,(GMWQ!$NE$2:$NE$60=I$3)*(GMWQ!$ND$2:$ND$60=I$4)*(GMWQ!$NF$2:$NF$60=I$1),0),$E53-1966)} -> 20871 | J53: {=INDEX(GMWQ!$A$2:$NF$60,MATCH(1,(GMWQ!$NE$2:$NE$60=J$3)*(GMWQ!$ND$2:$ND$60=J$4)*(GMWQ!$NF$2:$NF$60=J$1),0),$E53-1966)} -> 94862 | K53: {=INDEX(GMWQ!$A$2:$NF$60,MATCH(1,(GMWQ!$NE$2:$NE$60=K$3)*(GMWQ!$ND$2:$ND$60=K$4)*(GMWQ!$NF$2:$NF$60=K$1),0),$E53-1966)} -> 39158 | L53: {=INDEX(GMWQ!$A$2:$NF$60,MATCH(1,(GMWQ!$NE$2:$NE$60=L$3)*(GMWQ!$ND$2:$ND$60=L$4)*(GMWQ!$NF$2:$NF$60=L$1),0),$E53-1966)} -> 62678 | M53: {=INDEX(GMWQ!$A$2:$NF$60,MATCH(1,(GMWQ!$NE$2:$NE$60=M$3)*(GMWQ!$ND$2:$ND$60=M$4)*(GMWQ!$NF$2:$NF$60=M$1),0),$E53-1966)} -> 169770 | ... Q53: {=INDEX(GMWQ!$A$2:$NF$60,MATCH(1,(GMWQ!$NE$2:$NE$60=Q$3)*(GMWQ!$ND$2:$ND$60=Q$4)*(GMWQ!$NF$2:$NF$60=Q$1),0),$E53-1966)} -> 24335
B54: =+B50+1 -> 1984 | C54: =+C50+1 -> 1984 | E54: =+E53+1 -> 2020 | F54: {=INDEX(GMWQ!$A$2:$NF$60,MATCH(1,(GMWQ!$NE$2:$NE$60=F$3)*(GMWQ!$ND$2:$ND$60=F$4)*(GMWQ!$NF$2:$NF$60=F$1),0),$E54-1966)} -> 43.71459 | G54: {=INDEX(GMWQ!$A$2:$NF$60,MATCH(1,(GMWQ!$NE$2:$NE$60=G$3)*(GMWQ!$ND$2:$ND$60=G$4)*(GMWQ!$NF$2:$NF$60=G$1),0),$E54-1966)} -> 3267.258 | H54: {=INDEX(GMWQ!$A$2:$NF$60,MATCH(1,(GMWQ!$NE$2:$NE$60=H$3)*(GMWQ!$ND$2:$ND$60=H$4)*(GMWQ!$NF$2:$NF$60=H$1),0),$E54-1966)} -> 99.44635 | I54: {=INDEX(GMWQ!$A$2:$NF$60,MATCH(1,(GMWQ!$NE$2:$NE$60=I$3)*(GMWQ!$ND$2:$ND$60=I$4)*(GMWQ!$NF$2:$NF$60=I$1),0),$E54-1966)} -> 22765 | J54: {=INDEX(GMWQ!$A$2:$NF$60,MATCH(1,(GMWQ!$NE$2:$NE$60=J$3)*(GMWQ!$ND$2:$ND$60=J$4)*(GMWQ!$NF$2:$NF$60=J$1),0),$E54-1966)} -> 97962 | K54: {=INDEX(GMWQ!$A$2:$NF$60,MATCH(1,(GMWQ!$NE$2:$NE$60=K$3)*(GMWQ!$ND$2:$ND$60=K$4)*(GMWQ!$NF$2:$NF$60=K$1),0),$E54-1966)} -> 40507 | L54: {=INDEX(GMWQ!$A$2:$NF$60,MATCH(1,(GMWQ!$NE$2:$NE$60=L$3)*(GMWQ!$ND$2:$ND$60=L$4)*(GMWQ!$NF$2:$NF$60=L$1),0),$E54-1966)} -> 64883 | M54: {=INDEX(GMWQ!$A$2:$NF$60,MATCH(1,(GMWQ!$NE$2:$NE$60=M$3)*(GMWQ!$ND$2:$ND$60=M$4)*(GMWQ!$NF$2:$NF$60=M$1),0),$E54-1966)} -> 173527 | ... Q54: {=INDEX(GMWQ!$A$2:$NF$60,MATCH(1,(GMWQ!$NE$2:$NE$60=Q$3)*(GMWQ!$ND$2:$ND$60=Q$4)*(GMWQ!$NF$2:$NF$60=Q$1),0),$E54-1966)} -> 24435
A55: 1985 | B55: =+B51+1 -> 1985 | C55: =+C51+1 -> 1984 | D55: =+D51+1 -> 1984 | E55: =+E54+1 -> 2021 | F55: {=INDEX(GMWQ!$A$2:$NF$60,MATCH(1,(GMWQ!$NE$2:$NE$60=F$3)*(GMWQ!$ND$2:$ND$60=F$4)*(GMWQ!$NF$2:$NF$60=F$1),0),$E55-1966)} -> 43.85936 | G55: {=INDEX(GMWQ!$A$2:$NF$60,MATCH(1,(GMWQ!$NE$2:$NE$60=G$3)*(GMWQ!$ND$2:$ND$60=G$4)*(GMWQ!$NF$2:$NF$60=G$1),0),$E55-1966)} -> 3359.452 | H55: {=INDEX(GMWQ!$A$2:$NF$60,MATCH(1,(GMWQ!$NE$2:$NE$60=H$3)*(GMWQ!$ND$2:$ND$60=H$4)*(GMWQ!$NF$2:$NF$60=H$1),0),$E55-1966)} -> 100.1239 | I55: {=INDEX(GMWQ!$A$2:$NF$60,MATCH(1,(GMWQ!$NE$2:$NE$60=I$3)*(GMWQ!$ND$2:$ND$60=I$4)*(GMWQ!$NF$2:$NF$60=I$1),0),$E55-1966)} -> 22241 | J55: {=INDEX(GMWQ!$A$2:$NF$60,MATCH(1,(GMWQ!$NE$2:$NE$60=J$3)*(GMWQ!$ND$2:$ND$60=J$4)*(GMWQ!$NF$2:$NF$60=J$1),0),$E55-1966)} -> 99412 | K55: {=INDEX(GMWQ!$A$2:$NF$60,MATCH(1,(GMWQ!$NE$2:$NE$60=K$3)*(GMWQ!$ND$2:$ND$60=K$4)*(GMWQ!$NF$2:$NF$60=K$1),0),$E55-1966)} -> 41815 | L55: {=INDEX(GMWQ!$A$2:$NF$60,MATCH(1,(GMWQ!$NE$2:$NE$60=L$3)*(GMWQ!$ND$2:$ND$60=L$4)*(GMWQ!$NF$2:$NF$60=L$1),0),$E55-1966)} -> 65471 | M55: {=INDEX(GMWQ!$A$2:$NF$60,MATCH(1,(GMWQ!$NE$2:$NE$60=M$3)*(GMWQ!$ND$2:$ND$60=M$4)*(GMWQ!$NF$2:$NF$60=M$1),0),$E55-1966)} -> 175208 | ... Q55: {=INDEX(GMWQ!$A$2:$NF$60,MATCH(1,(GMWQ!$NE$2:$NE$60=Q$3)*(GMWQ!$ND$2:$ND$60=Q$4)*(GMWQ!$NF$2:$NF$60=Q$1),0),$E55-1966)} -> 24515
B56: =+B52+1 -> 1985 | C56: =+C52+1 -> 1985 | E56: =+E55+1 -> 2022 | F56: {=INDEX(GMWQ!$A$2:$NF$60,MATCH(1,(GMWQ!$NE$2:$NE$60=F$3)*(GMWQ!$ND$2:$ND$60=F$4)*(GMWQ!$NF$2:$NF$60=F$1),0),$E56-1966)} -> 43.82259 | G56: {=INDEX(GMWQ!$A$2:$NF$60,MATCH(1,(GMWQ!$NE$2:$NE$60=G$3)*(GMWQ!$ND$2:$ND$60=G$4)*(GMWQ!$NF$2:$NF$60=G$1),0),$E56-1966)} -> 3403.3 | H56: {=INDEX(GMWQ!$A$2:$NF$60,MATCH(1,(GMWQ!$NE$2:$NE$60=H$3)*(GMWQ!$ND$2:$ND$60=H$4)*(GMWQ!$NF$2:$NF$60=H$1),0),$E56-1966)} -> 104.4909 | I56: {=INDEX(GMWQ!$A$2:$NF$60,MATCH(1,(GMWQ!$NE$2:$NE$60=I$3)*(GMWQ!$ND$2:$ND$60=I$4)*(GMWQ!$NF$2:$NF$60=I$1),0),$E56-1966)} -> 25638 | J56: {=INDEX(GMWQ!$A$2:$NF$60,MATCH(1,(GMWQ!$NE$2:$NE$60=J$3)*(GMWQ!$ND$2:$ND$60=J$4)*(GMWQ!$NF$2:$NF$60=J$1),0),$E56-1966)} -> 103208 | K56: {=INDEX(GMWQ!$A$2:$NF$60,MATCH(1,(GMWQ!$NE$2:$NE$60=K$3)*(GMWQ!$ND$2:$ND$60=K$4)*(GMWQ!$NF$2:$NF$60=K$1),0),$E56-1966)} -> 42291 | L56: {=INDEX(GMWQ!$A$2:$NF$60,MATCH(1,(GMWQ!$NE$2:$NE$60=L$3)*(GMWQ!$ND$2:$ND$60=L$4)*(GMWQ!$NF$2:$NF$60=L$1),0),$E56-1966)} -> 66622 | M56: {=INDEX(GMWQ!$A$2:$NF$60,MATCH(1,(GMWQ!$NE$2:$NE$60=M$3)*(GMWQ!$ND$2:$ND$60=M$4)*(GMWQ!$NF$2:$NF$60=M$1),0),$E56-1966)} -> 175613 | ... Q56: {=INDEX(GMWQ!$A$2:$NF$60,MATCH(1,(GMWQ!$NE$2:$NE$60=Q$3)*(GMWQ!$ND$2:$ND$60=Q$4)*(GMWQ!$NF$2:$NF$60=Q$1),0),$E56-1966)} -> 24570
B57: =+B53+1 -> 1985 | C57: =+C53+1 -> 1985 | E57: =+E56+1 -> 2023 | F57: {=INDEX(GMWQ!$A$2:$NF$60,MATCH(1,(GMWQ!$NE$2:$NE$60=F$3)*(GMWQ!$ND$2:$ND$60=F$4)*(GMWQ!$NF$2:$NF$60=F$1),0),$E57-1966)} -> 44.95419 | G57: {=INDEX(GMWQ!$A$2:$NF$60,MATCH(1,(GMWQ!$NE$2:$NE$60=G$3)*(GMWQ!$ND$2:$ND$60=G$4)*(GMWQ!$NF$2:$NF$60=G$1),0),$E57-1966)} -> 3447.148 | H57: {=INDEX(GMWQ!$A$2:$NF$60,MATCH(1,(GMWQ!$NE$2:$NE$60=H$3)*(GMWQ!$ND$2:$ND$60=H$4)*(GMWQ!$NF$2:$NF$60=H$1),0),$E57-1966)} -> 107.6677 | I57: {=INDEX(GMWQ!$A$2:$NF$60,MATCH(1,(GMWQ!$NE$2:$NE$60=I$3)*(GMWQ!$ND$2:$ND$60=I$4)*(GMWQ!$NF$2:$NF$60=I$1),0),$E57-1966)} -> 25043 | J57: {=INDEX(GMWQ!$A$2:$NF$60,MATCH(1,(GMWQ!$NE$2:$NE$60=J$3)*(GMWQ!$ND$2:$ND$60=J$4)*(GMWQ!$NF$2:$NF$60=J$1),0),$E57-1966)} -> 105169 | K57: {=INDEX(GMWQ!$A$2:$NF$60,MATCH(1,(GMWQ!$NE$2:$NE$60=K$3)*(GMWQ!$ND$2:$ND$60=K$4)*(GMWQ!$NF$2:$NF$60=K$1),0),$E57-1966)} -> 42933 | L57: {=INDEX(GMWQ!$A$2:$NF$60,MATCH(1,(GMWQ!$NE$2:$NE$60=L$3)*(GMWQ!$ND$2:$ND$60=L$4)*(GMWQ!$NF$2:$NF$60=L$1),0),$E57-1966)} -> 67715 | M57: {=INDEX(GMWQ!$A$2:$NF$60,MATCH(1,(GMWQ!$NE$2:$NE$60=M$3)*(GMWQ!$ND$2:$ND$60=M$4)*(GMWQ!$NF$2:$NF$60=M$1),0),$E57-1966)} -> 175957 | ... Q57: {=INDEX(GMWQ!$A$2:$NF$60,MATCH(1,(GMWQ!$NE$2:$NE$60=Q$3)*(GMWQ!$ND$2:$ND$60=Q$4)*(GMWQ!$NF$2:$NF$60=Q$1),0),$E57-1966)} -> 24625
B58: =+B54+1 -> 1985 | C58: =+C54+1 -> 1985 | E58: =+E57+1 -> 2024 | F58: {=INDEX(GMWQ!$A$2:$NF$60,MATCH(1,(GMWQ!$NE$2:$NE$60=F$3)*(GMWQ!$ND$2:$ND$60=F$4)*(GMWQ!$NF$2:$NF$60=F$1),0),$E58-1966)} -> 45.39808 | G58: {=INDEX(GMWQ!$A$2:$NF$60,MATCH(1,(GMWQ!$NE$2:$NE$60=G$3)*(GMWQ!$ND$2:$ND$60=G$4)*(GMWQ!$NF$2:$NF$60=G$1),0),$E58-1966)} -> 3557.331 | H58: {=INDEX(GMWQ!$A$2:$NF$60,MATCH(1,(GMWQ!$NE$2:$NE$60=H$3)*(GMWQ!$ND$2:$ND$60=H$4)*(GMWQ!$NF$2:$NF$60=H$1),0),$E58-1966)} -> 109.6371 | I58: {=INDEX(GMWQ!$A$2:$NF$60,MATCH(1,(GMWQ!$NE$2:$NE$60=I$3)*(GMWQ!$ND$2:$ND$60=I$4)*(GMWQ!$NF$2:$NF$60=I$1),0),$E58-1966)} -> 25785 | J58: {=INDEX(GMWQ!$A$2:$NF$60,MATCH(1,(GMWQ!$NE$2:$NE$60=J$3)*(GMWQ!$ND$2:$ND$60=J$4)*(GMWQ!$NF$2:$NF$60=J$1),0),$E58-1966)} -> 106841 | K58: {=INDEX(GMWQ!$A$2:$NF$60,MATCH(1,(GMWQ!$NE$2:$NE$60=K$3)*(GMWQ!$ND$2:$ND$60=K$4)*(GMWQ!$NF$2:$NF$60=K$1),0),$E58-1966)} -> 43938 | L58: {=INDEX(GMWQ!$A$2:$NF$60,MATCH(1,(GMWQ!$NE$2:$NE$60=L$3)*(GMWQ!$ND$2:$ND$60=L$4)*(GMWQ!$NF$2:$NF$60=L$1),0),$E58-1966)} -> 69185 | M58: {=INDEX(GMWQ!$A$2:$NF$60,MATCH(1,(GMWQ!$NE$2:$NE$60=M$3)*(GMWQ!$ND$2:$ND$60=M$4)*(GMWQ!$NF$2:$NF$60=M$1),0),$E58-1966)} -> 177164 | ... Q58: {=INDEX(GMWQ!$A$2:$NF$60,MATCH(1,(GMWQ!$NE$2:$NE$60=Q$3)*(GMWQ!$ND$2:$ND$60=Q$4)*(GMWQ!$NF$2:$NF$60=Q$1),0),$E58-1966)} -> 24660
A59: 1986 | B59: =+B55+1 -> 1986 | C59: =+C55+1 -> 1985 | D59: =+D55+1 -> 1985 | E59: =+E58+1 -> 2025 | F59: {=INDEX(GMWQ!$A$2:$NF$60,MATCH(1,(GMWQ!$NE$2:$NE$60=F$3)*(GMWQ!$ND$2:$ND$60=F$4)*(GMWQ!$NF$2:$NF$60=F$1),0),$E59-1966)} -> 45.99101 | G59: {=INDEX(GMWQ!$A$2:$NF$60,MATCH(1,(GMWQ!$NE$2:$NE$60=G$3)*(GMWQ!$ND$2:$ND$60=G$4)*(GMWQ!$NF$2:$NF$60=G$1),0),$E59-1966)} -> 3637.157 | H59: {=INDEX(GMWQ!$A$2:$NF$60,MATCH(1,(GMWQ!$NE$2:$NE$60=H$3)*(GMWQ!$ND$2:$ND$60=H$4)*(GMWQ!$NF$2:$NF$60=H$1),0),$E59-1966)} -> 110.8912 | I59: {=INDEX(GMWQ!$A$2:$NF$60,MATCH(1,(GMWQ!$NE$2:$NE$60=I$3)*(GMWQ!$ND$2:$ND$60=I$4)*(GMWQ!$NF$2:$NF$60=I$1),0),$E59-1966)} -> 25399 | J59: {=INDEX(GMWQ!$A$2:$NF$60,MATCH(1,(GMWQ!$NE$2:$NE$60=J$3)*(GMWQ!$ND$2:$ND$60=J$4)*(GMWQ!$NF$2:$NF$60=J$1),0),$E59-1966)} -> 108753 | K59: {=INDEX(GMWQ!$A$2:$NF$60,MATCH(1,(GMWQ!$NE$2:$NE$60=K$3)*(GMWQ!$ND$2:$ND$60=K$4)*(GMWQ!$NF$2:$NF$60=K$1),0),$E59-1966)} -> 44894 | L59: {=INDEX(GMWQ!$A$2:$NF$60,MATCH(1,(GMWQ!$NE$2:$NE$60=L$3)*(GMWQ!$ND$2:$ND$60=L$4)*(GMWQ!$NF$2:$NF$60=L$1),0),$E59-1966)} -> 70501 | M59: {=INDEX(GMWQ!$A$2:$NF$60,MATCH(1,(GMWQ!$NE$2:$NE$60=M$3)*(GMWQ!$ND$2:$ND$60=M$4)*(GMWQ!$NF$2:$NF$60=M$1),0),$E59-1966)} -> 179729 | ... Q59: {=INDEX(GMWQ!$A$2:$NF$60,MATCH(1,(GMWQ!$NE$2:$NE$60=Q$3)*(GMWQ!$ND$2:$ND$60=Q$4)*(GMWQ!$NF$2:$NF$60=Q$1),0),$E59-1966)} -> 24670
B60: =+B56+1 -> 1986 | C60: =+C56+1 -> 1986 | E60: =+E59+1 -> 2026 | F60: {=INDEX(GMWQ!$A$2:$NF$60,MATCH(1,(GMWQ!$NE$2:$NE$60=F$3)*(GMWQ!$ND$2:$ND$60=F$4)*(GMWQ!$NF$2:$NF$60=F$1),0),$E60-1966)} -> 46.48673 | G60: {=INDEX(GMWQ!$A$2:$NF$60,MATCH(1,(GMWQ!$NE$2:$NE$60=G$3)*(GMWQ!$ND$2:$ND$60=G$4)*(GMWQ!$NF$2:$NF$60=G$1),0),$E60-1966)} -> 3792.313 | H60: {=INDEX(GMWQ!$A$2:$NF$60,MATCH(1,(GMWQ!$NE$2:$NE$60=H$3)*(GMWQ!$ND$2:$ND$60=H$4)*(GMWQ!$NF$2:$NF$60=H$1),0),$E60-1966)} -> 115.3305 | I60: {=INDEX(GMWQ!$A$2:$NF$60,MATCH(1,(GMWQ!$NE$2:$NE$60=I$3)*(GMWQ!$ND$2:$ND$60=I$4)*(GMWQ!$NF$2:$NF$60=I$1),0),$E60-1966)} -> 24729 | J60: {=INDEX(GMWQ!$A$2:$NF$60,MATCH(1,(GMWQ!$NE$2:$NE$60=J$3)*(GMWQ!$ND$2:$ND$60=J$4)*(GMWQ!$NF$2:$NF$60=J$1),0),$E60-1966)} -> 110079 | K60: {=INDEX(GMWQ!$A$2:$NF$60,MATCH(1,(GMWQ!$NE$2:$NE$60=K$3)*(GMWQ!$ND$2:$ND$60=K$4)*(GMWQ!$NF$2:$NF$60=K$1),0),$E60-1966)} -> 45788 | L60: {=INDEX(GMWQ!$A$2:$NF$60,MATCH(1,(GMWQ!$NE$2:$NE$60=L$3)*(GMWQ!$ND$2:$ND$60=L$4)*(GMWQ!$NF$2:$NF$60=L$1),0),$E60-1966)} -> 73909 | M60: {=INDEX(GMWQ!$A$2:$NF$60,MATCH(1,(GMWQ!$NE$2:$NE$60=M$3)*(GMWQ!$ND$2:$ND$60=M$4)*(GMWQ!$NF$2:$NF$60=M$1),0),$E60-1966)} -> 186661 | ... Q60: {=INDEX(GMWQ!$A$2:$NF$60,MATCH(1,(GMWQ!$NE$2:$NE$60=Q$3)*(GMWQ!$ND$2:$ND$60=Q$4)*(GMWQ!$NF$2:$NF$60=Q$1),0),$E60-1966)} -> 24695
B61: =+B57+1 -> 1986 | C61: =+C57+1 -> 1986 | E61: =+E60+1 -> 2027 | F61: {=INDEX(GMWQ!$A$2:$NF$60,MATCH(1,(GMWQ!$NE$2:$NE$60=F$3)*(GMWQ!$ND$2:$ND$60=F$4)*(GMWQ!$NF$2:$NF$60=F$1),0),$E61-1966)} -> 46.84827 | G61: {=INDEX(GMWQ!$A$2:$NF$60,MATCH(1,(GMWQ!$NE$2:$NE$60=G$3)*(GMWQ!$ND$2:$ND$60=G$4)*(GMWQ!$NF$2:$NF$60=G$1),0),$E61-1966)} -> 3863.145 | H61: {=INDEX(GMWQ!$A$2:$NF$60,MATCH(1,(GMWQ!$NE$2:$NE$60=H$3)*(GMWQ!$ND$2:$ND$60=H$4)*(GMWQ!$NF$2:$NF$60=H$1),0),$E61-1966)} -> 118.2911 | I61: {=INDEX(GMWQ!$A$2:$NF$60,MATCH(1,(GMWQ!$NE$2:$NE$60=I$3)*(GMWQ!$ND$2:$ND$60=I$4)*(GMWQ!$NF$2:$NF$60=I$1),0),$E61-1966)} -> 25297 | J61: {=INDEX(GMWQ!$A$2:$NF$60,MATCH(1,(GMWQ!$NE$2:$NE$60=J$3)*(GMWQ!$ND$2:$ND$60=J$4)*(GMWQ!$NF$2:$NF$60=J$1),0),$E61-1966)} -> 111989 | K61: {=INDEX(GMWQ!$A$2:$NF$60,MATCH(1,(GMWQ!$NE$2:$NE$60=K$3)*(GMWQ!$ND$2:$ND$60=K$4)*(GMWQ!$NF$2:$NF$60=K$1),0),$E61-1966)} -> 46565 | L61: {=INDEX(GMWQ!$A$2:$NF$60,MATCH(1,(GMWQ!$NE$2:$NE$60=L$3)*(GMWQ!$ND$2:$ND$60=L$4)*(GMWQ!$NF$2:$NF$60=L$1),0),$E61-1966)} -> 73297 | M61: {=INDEX(GMWQ!$A$2:$NF$60,MATCH(1,(GMWQ!$NE$2:$NE$60=M$3)*(GMWQ!$ND$2:$ND$60=M$4)*(GMWQ!$NF$2:$NF$60=M$1),0),$E61-1966)} -> 183119 | ... Q61: {=INDEX(GMWQ!$A$2:$NF$60,MATCH(1,(GMWQ!$NE$2:$NE$60=Q$3)*(GMWQ!$ND$2:$ND$60=Q$4)*(GMWQ!$NF$2:$NF$60=Q$1),0),$E61-1966)} -> 24770
B62: =+B58+1 -> 1986 | C62: =+C58+1 -> 1986 | E62: =+E61+1 -> 2028 | F62: {=INDEX(GMWQ!$A$2:$NF$60,MATCH(1,(GMWQ!$NE$2:$NE$60=F$3)*(GMWQ!$ND$2:$ND$60=F$4)*(GMWQ!$NF$2:$NF$60=F$1),0),$E62-1966)} -> 46.62597 | G62: {=INDEX(GMWQ!$A$2:$NF$60,MATCH(1,(GMWQ!$NE$2:$NE$60=G$3)*(GMWQ!$ND$2:$ND$60=G$4)*(GMWQ!$NF$2:$NF$60=G$1),0),$E62-1966)} -> 3930.603 | H62: {=INDEX(GMWQ!$A$2:$NF$60,MATCH(1,(GMWQ!$NE$2:$NE$60=H$3)*(GMWQ!$ND$2:$ND$60=H$4)*(GMWQ!$NF$2:$NF$60=H$1),0),$E62-1966)} -> 120.3198 | I62: {=INDEX(GMWQ!$A$2:$NF$60,MATCH(1,(GMWQ!$NE$2:$NE$60=I$3)*(GMWQ!$ND$2:$ND$60=I$4)*(GMWQ!$NF$2:$NF$60=I$1),0),$E62-1966)} -> 27509 | J62: {=INDEX(GMWQ!$A$2:$NF$60,MATCH(1,(GMWQ!$NE$2:$NE$60=J$3)*(GMWQ!$ND$2:$ND$60=J$4)*(GMWQ!$NF$2:$NF$60=J$1),0),$E62-1966)} -> 115779 | K62: {=INDEX(GMWQ!$A$2:$NF$60,MATCH(1,(GMWQ!$NE$2:$NE$60=K$3)*(GMWQ!$ND$2:$ND$60=K$4)*(GMWQ!$NF$2:$NF$60=K$1),0),$E62-1966)} -> 47221 | L62: {=INDEX(GMWQ!$A$2:$NF$60,MATCH(1,(GMWQ!$NE$2:$NE$60=L$3)*(GMWQ!$ND$2:$ND$60=L$4)*(GMWQ!$NF$2:$NF$60=L$1),0),$E62-1966)} -> 74329 | M62: {=INDEX(GMWQ!$A$2:$NF$60,MATCH(1,(GMWQ!$NE$2:$NE$60=M$3)*(GMWQ!$ND$2:$ND$60=M$4)*(GMWQ!$NF$2:$NF$60=M$1),0),$E62-1966)} -> 183388 | ... Q62: {=INDEX(GMWQ!$A$2:$NF$60,MATCH(1,(GMWQ!$NE$2:$NE$60=Q$3)*(GMWQ!$ND$2:$ND$60=Q$4)*(GMWQ!$NF$2:$NF$60=Q$1),0),$E62-1966)} -> 24850
A63: 1987 | B63: =+B59+1 -> 1987 | C63: =+C59+1 -> 1986 | D63: =+D59+1 -> 1986 | E63: =+E62+1 -> 2029 | F63: {=INDEX(GMWQ!$A$2:$NF$60,MATCH(1,(GMWQ!$NE$2:$NE$60=F$3)*(GMWQ!$ND$2:$ND$60=F$4)*(GMWQ!$NF$2:$NF$60=F$1),0),$E63-1966)} -> 46.73494 | G63: {=INDEX(GMWQ!$A$2:$NF$60,MATCH(1,(GMWQ!$NE$2:$NE$60=G$3)*(GMWQ!$ND$2:$ND$60=G$4)*(GMWQ!$NF$2:$NF$60=G$1),0),$E63-1966)} -> 4305 | H63: {=INDEX(GMWQ!$A$2:$NF$60,MATCH(1,(GMWQ!$NE$2:$NE$60=H$3)*(GMWQ!$ND$2:$ND$60=H$4)*(GMWQ!$NF$2:$NF$60=H$1),0),$E63-1966)} -> 121.4108 | I63: {=INDEX(GMWQ!$A$2:$NF$60,MATCH(1,(GMWQ!$NE$2:$NE$60=I$3)*(GMWQ!$ND$2:$ND$60=I$4)*(GMWQ!$NF$2:$NF$60=I$1),0),$E63-1966)} -> 27991 | J63: {=INDEX(GMWQ!$A$2:$NF$60,MATCH(1,(GMWQ!$NE$2:$NE$60=J$3)*(GMWQ!$ND$2:$ND$60=J$4)*(GMWQ!$NF$2:$NF$60=J$1),0),$E63-1966)} -> 118136 | K63: {=INDEX(GMWQ!$A$2:$NF$60,MATCH(1,(GMWQ!$NE$2:$NE$60=K$3)*(GMWQ!$ND$2:$ND$60=K$4)*(GMWQ!$NF$2:$NF$60=K$1),0),$E63-1966)} -> 47918 | L63: {=INDEX(GMWQ!$A$2:$NF$60,MATCH(1,(GMWQ!$NE$2:$NE$60=L$3)*(GMWQ!$ND$2:$ND$60=L$4)*(GMWQ!$NF$2:$NF$60=L$1),0),$E63-1966)} -> 74158 | M63: {=INDEX(GMWQ!$A$2:$NF$60,MATCH(1,(GMWQ!$NE$2:$NE$60=M$3)*(GMWQ!$ND$2:$ND$60=M$4)*(GMWQ!$NF$2:$NF$60=M$1),0),$E63-1966)} -> 180901 | ... Q63: {=INDEX(GMWQ!$A$2:$NF$60,MATCH(1,(GMWQ!$NE$2:$NE$60=Q$3)*(GMWQ!$ND$2:$ND$60=Q$4)*(GMWQ!$NF$2:$NF$60=Q$1),0),$E63-1966)} -> 24925
B64: =+B60+1 -> 1987 | C64: =+C60+1 -> 1987 | E64: =+E63+1 -> 2030 | F64: {=INDEX(GMWQ!$A$2:$NF$60,MATCH(1,(GMWQ!$NE$2:$NE$60=F$3)*(GMWQ!$ND$2:$ND$60=F$4)*(GMWQ!$NF$2:$NF$60=F$1),0),$E64-1966)} -> 47.14354 | G64: {=INDEX(GMWQ!$A$2:$NF$60,MATCH(1,(GMWQ!$NE$2:$NE$60=G$3)*(GMWQ!$ND$2:$ND$60=G$4)*(GMWQ!$NF$2:$NF$60=G$1),0),$E64-1966)} -> 4334 | H64: {=INDEX(GMWQ!$A$2:$NF$60,MATCH(1,(GMWQ!$NE$2:$NE$60=H$3)*(GMWQ!$ND$2:$ND$60=H$4)*(GMWQ!$NF$2:$NF$60=H$1),0),$E64-1966)} -> 125.7916 | I64: {=INDEX(GMWQ!$A$2:$NF$60,MATCH(1,(GMWQ!$NE$2:$NE$60=I$3)*(GMWQ!$ND$2:$ND$60=I$4)*(GMWQ!$NF$2:$NF$60=I$1),0),$E64-1966)} -> 29936 | J64: {=INDEX(GMWQ!$A$2:$NF$60,MATCH(1,(GMWQ!$NE$2:$NE$60=J$3)*(GMWQ!$ND$2:$ND$60=J$4)*(GMWQ!$NF$2:$NF$60=J$1),0),$E64-1966)} -> 121739 | K64: {=INDEX(GMWQ!$A$2:$NF$60,MATCH(1,(GMWQ!$NE$2:$NE$60=K$3)*(GMWQ!$ND$2:$ND$60=K$4)*(GMWQ!$NF$2:$NF$60=K$1),0),$E64-1966)} -> 49142 | L64: {=INDEX(GMWQ!$A$2:$NF$60,MATCH(1,(GMWQ!$NE$2:$NE$60=L$3)*(GMWQ!$ND$2:$ND$60=L$4)*(GMWQ!$NF$2:$NF$60=L$1),0),$E64-1966)} -> 76563 | M64: {=INDEX(GMWQ!$A$2:$NF$60,MATCH(1,(GMWQ!$NE$2:$NE$60=M$3)*(GMWQ!$ND$2:$ND$60=M$4)*(GMWQ!$NF$2:$NF$60=M$1),0),$E64-1966)} -> 185020 | ... Q64: {=INDEX(GMWQ!$A$2:$NF$60,MATCH(1,(GMWQ!$NE$2:$NE$60=Q$3)*(GMWQ!$ND$2:$ND$60=Q$4)*(GMWQ!$NF$2:$NF$60=Q$1),0),$E64-1966)} -> 25110
B65: =+B61+1 -> 1987 | C65: =+C61+1 -> 1987 | E65: =+E64+1 -> 2031 | F65: {=INDEX(GMWQ!$A$2:$NF$60,MATCH(1,(GMWQ!$NE$2:$NE$60=F$3)*(GMWQ!$ND$2:$ND$60=F$4)*(GMWQ!$NF$2:$NF$60=F$1),0),$E65-1966)} -> 47.22083 | G65: {=INDEX(GMWQ!$A$2:$NF$60,MATCH(1,(GMWQ!$NE$2:$NE$60=G$3)*(GMWQ!$ND$2:$ND$60=G$4)*(GMWQ!$NF$2:$NF$60=G$1),0),$E65-1966)} -> 4487 | H65: {=INDEX(GMWQ!$A$2:$NF$60,MATCH(1,(GMWQ!$NE$2:$NE$60=H$3)*(GMWQ!$ND$2:$ND$60=H$4)*(GMWQ!$NF$2:$NF$60=H$1),0),$E65-1966)} -> 130.0642 | I65: {=INDEX(GMWQ!$A$2:$NF$60,MATCH(1,(GMWQ!$NE$2:$NE$60=I$3)*(GMWQ!$ND$2:$ND$60=I$4)*(GMWQ!$NF$2:$NF$60=I$1),0),$E65-1966)} -> 32609 | J65: {=INDEX(GMWQ!$A$2:$NF$60,MATCH(1,(GMWQ!$NE$2:$NE$60=J$3)*(GMWQ!$ND$2:$ND$60=J$4)*(GMWQ!$NF$2:$NF$60=J$1),0),$E65-1966)} -> 127119 | K65: {=INDEX(GMWQ!$A$2:$NF$60,MATCH(1,(GMWQ!$NE$2:$NE$60=K$3)*(GMWQ!$ND$2:$ND$60=K$4)*(GMWQ!$NF$2:$NF$60=K$1),0),$E65-1966)} -> 50573 | L65: {=INDEX(GMWQ!$A$2:$NF$60,MATCH(1,(GMWQ!$NE$2:$NE$60=L$3)*(GMWQ!$ND$2:$ND$60=L$4)*(GMWQ!$NF$2:$NF$60=L$1),0),$E65-1966)} -> 78295 | M65: {=INDEX(GMWQ!$A$2:$NF$60,MATCH(1,(GMWQ!$NE$2:$NE$60=M$3)*(GMWQ!$ND$2:$ND$60=M$4)*(GMWQ!$NF$2:$NF$60=M$1),0),$E65-1966)} -> 187551 | ... Q65: {=INDEX(GMWQ!$A$2:$NF$60,MATCH(1,(GMWQ!$NE$2:$NE$60=Q$3)*(GMWQ!$ND$2:$ND$60=Q$4)*(GMWQ!$NF$2:$NF$60=Q$1),0),$E65-1966)} -> 25345
B66: =+B62+1 -> 1987 | C66: =+C62+1 -> 1987 | E66: =+E65+1 -> 2032 | F66: {=INDEX(GMWQ!$A$2:$NF$60,MATCH(1,(GMWQ!$NE$2:$NE$60=F$3)*(GMWQ!$ND$2:$ND$60=F$4)*(GMWQ!$NF$2:$NF$60=F$1),0),$E66-1966)} -> 47.96034 | G66: {=INDEX(GMWQ!$A$2:$NF$60,MATCH(1,(GMWQ!$NE$2:$NE$60=G$3)*(GMWQ!$ND$2:$ND$60=G$4)*(GMWQ!$NF$2:$NF$60=G$1),0),$E66-1966)} -> 4632 | H66: {=INDEX(GMWQ!$A$2:$NF$60,MATCH(1,(GMWQ!$NE$2:$NE$60=H$3)*(GMWQ!$ND$2:$ND$60=H$4)*(GMWQ!$NF$2:$NF$60=H$1),0),$E66-1966)} -> 132.7039 | I66: {=INDEX(GMWQ!$A$2:$NF$60,MATCH(1,(GMWQ!$NE$2:$NE$60=I$3)*(GMWQ!$ND$2:$ND$60=I$4)*(GMWQ!$NF$2:$NF$60=I$1),0),$E66-1966)} -> 32677 | J66: {=INDEX(GMWQ!$A$2:$NF$60,MATCH(1,(GMWQ!$NE$2:$NE$60=J$3)*(GMWQ!$ND$2:$ND$60=J$4)*(GMWQ!$NF$2:$NF$60=J$1),0),$E66-1966)} -> 129815 | K66: {=INDEX(GMWQ!$A$2:$NF$60,MATCH(1,(GMWQ!$NE$2:$NE$60=K$3)*(GMWQ!$ND$2:$ND$60=K$4)*(GMWQ!$NF$2:$NF$60=K$1),0),$E66-1966)} -> 52081 | L66: {=INDEX(GMWQ!$A$2:$NF$60,MATCH(1,(GMWQ!$NE$2:$NE$60=L$3)*(GMWQ!$ND$2:$ND$60=L$4)*(GMWQ!$NF$2:$NF$60=L$1),0),$E66-1966)} -> 79796 | M66: {=INDEX(GMWQ!$A$2:$NF$60,MATCH(1,(GMWQ!$NE$2:$NE$60=M$3)*(GMWQ!$ND$2:$ND$60=M$4)*(GMWQ!$NF$2:$NF$60=M$1),0),$E66-1966)} -> 188860 | ... Q66: {=INDEX(GMWQ!$A$2:$NF$60,MATCH(1,(GMWQ!$NE$2:$NE$60=Q$3)*(GMWQ!$ND$2:$ND$60=Q$4)*(GMWQ!$NF$2:$NF$60=Q$1),0),$E66-1966)} -> 25575
A67: 1988 | B67: =+B63+1 -> 1988 | C67: =+C63+1 -> 1987 | D67: =+D63+1 -> 1987 | E67: =+E66+1 -> 2033 | F67: {=INDEX(GMWQ!$A$2:$NF$60,MATCH(1,(GMWQ!$NE$2:$NE$60=F$3)*(GMWQ!$ND$2:$ND$60=F$4)*(GMWQ!$NF$2:$NF$60=F$1),0),$E67-1966)} -> 48.48625 | G67: {=INDEX(GMWQ!$A$2:$NF$60,MATCH(1,(GMWQ!$NE$2:$NE$60=G$3)*(GMWQ!$ND$2:$ND$60=G$4)*(GMWQ!$NF$2:$NF$60=G$1),0),$E67-1966)} -> 4640 | H67: {=INDEX(GMWQ!$A$2:$NF$60,MATCH(1,(GMWQ!$NE$2:$NE$60=H$3)*(GMWQ!$ND$2:$ND$60=H$4)*(GMWQ!$NF$2:$NF$60=H$1),0),$E67-1966)} -> 134.4686 | I67: {=INDEX(GMWQ!$A$2:$NF$60,MATCH(1,(GMWQ!$NE$2:$NE$60=I$3)*(GMWQ!$ND$2:$ND$60=I$4)*(GMWQ!$NF$2:$NF$60=I$1),0),$E67-1966)} -> 33698 | J67: {=INDEX(GMWQ!$A$2:$NF$60,MATCH(1,(GMWQ!$NE$2:$NE$60=J$3)*(GMWQ!$ND$2:$ND$60=J$4)*(GMWQ!$NF$2:$NF$60=J$1),0),$E67-1966)} -> 133283 | K67: {=INDEX(GMWQ!$A$2:$NF$60,MATCH(1,(GMWQ!$NE$2:$NE$60=K$3)*(GMWQ!$ND$2:$ND$60=K$4)*(GMWQ!$NF$2:$NF$60=K$1),0),$E67-1966)} -> 53600 | L67: {=INDEX(GMWQ!$A$2:$NF$60,MATCH(1,(GMWQ!$NE$2:$NE$60=L$3)*(GMWQ!$ND$2:$ND$60=L$4)*(GMWQ!$NF$2:$NF$60=L$1),0),$E67-1966)} -> 82285 | M67: {=INDEX(GMWQ!$A$2:$NF$60,MATCH(1,(GMWQ!$NE$2:$NE$60=M$3)*(GMWQ!$ND$2:$ND$60=M$4)*(GMWQ!$NF$2:$NF$60=M$1),0),$E67-1966)} -> 191709 | ... Q67: {=INDEX(GMWQ!$A$2:$NF$60,MATCH(1,(GMWQ!$NE$2:$NE$60=Q$3)*(GMWQ!$ND$2:$ND$60=Q$4)*(GMWQ!$NF$2:$NF$60=Q$1),0),$E67-1966)} -> 25795
