Workbook
Name A: #REF!
Name Data: [1]sheet0!$C$2
Name S: {#N/A,#N/A,FALSE,"CGBR95C"}

Sheet >> CHARTS

Sheet >> DATA

Sheet Chart Data
A1: UK trade with US by sector | AX1: Mechanical power generators (consumer) | AY1: Specialised machinery | AZ1: Metal working machinery | BA1: General industrial machinery | BB1: Office machinery | BC1: Telecoms & sound equipment | BD1: Miscellaneous electrical goods | BE1: Road vehicles other than cars | BF1: Cars | BG1: Railway equipment | BH1: Aircraft | BI1: Ships | BJ1: Plumbing, heating & lighting fixtures | BK1: Furniture | BL1: Travel goods, handbags etc | BM1: Clothing | BN1: Footwear | BO1: Scientific instruments | BP1: Photographic & optical goods & clocks | BQ1: Works of art | BR1: Jewellery | BS1: Other manufactures | BT1: Unspecified goods | BV1: GDP growth | CC1: CPI inflation | CI1: Exports | CO1: RXD | CU1: Full blown Trump CPI calculation | CX1: Goods exports to US as % of total exports
B2: Total | C2: ='ONS - UK Exports by type'!E1 -> Live animals | D2: ='ONS - UK Exports by type'!F1 -> Meat & meat preparations | E2: ='ONS - UK Exports by type'!G1 -> Dairy products & eggs | F2: ='ONS - UK Exports by type'!H1 -> Fish and shellfish | G2: ='ONS - UK Exports by type'!I1 -> Cereals | H2: ='ONS - UK Exports by type'!J1 -> Vegetables & fruit | I2: ='ONS - UK Exports by type'!K1 -> Sugar | J2: ='ONS - UK Exports by type'!L1 -> Coffee, tea, cocoa etc | ... AV2: ='ONS - UK Exports by type'!AX1 -> Miscellaneous metal manufactures | AW2: Electric motors | AX2: Mechanical power generators | AY2: Specialised machinery | AZ2: Metal working machinery | BA2: General industrial machinery | BB2: Office machinery | BC2: ='ONS - UK Exports by type'!BO1 -> Telecoms & sound equipment (consumer) | BD2: Miscellaneous electrical goods | BE2: ='ONS - UK Exports by type'!BU1 -> Road vehicles other than cars (consumer) | BF2: ='ONS - UK Exports by type'!BX1 -> Cars | BG2: ='ONS - UK Exports by type'!BY1 -> Railway equipment (intermediate) | BH2: ='ONS - UK Exports by type'!CA1 -> Aircraft | BI2: ='ONS - UK Exports by type'!CB1 -> Ships | BJ2: ='ONS - UK Exports by type'!CC1 -> Plumbing, heating & lighting fixtures (consumer) | BK2: Furniture | BL2: ='ONS - UK Exports by type'!CI1 -> Travel goods, handbags etc | BM2: ='ONS - UK Exports by type'!CJ1 -> Clothing | BN2: ='ONS - UK Exports by type'!CK1 -> Footwear | BO2: ='ONS - UK Exports by type'!CL1 -> Scientific instruments (consumer) | BP2: Photographic & optical goods & clocks | BQ2: ='ONS - UK Exports by type'!CR1 -> Works of art | BR2: ='ONS - UK Exports by type'!CS1 -> Jewellery | BS2: Other manufactures | BT2: ='ONS - UK Exports by type'!CW1 -> Unspecified goods | BW2: Baseline | BX2: Full-blown Trump presidency | BY2: ZERO LINE | CA2: Difference | CD2: Baseline | CE2: Full-blown Trump presidency | CG2: Difference | CJ2: Baseline | CK2: Full-blown Trump presidency | CM2: Difference | CP2: Baseline | CQ2: Full-blown Trump presidency | CS2: Difference | CU2: Tariff increase | CV2: 0.062 | CY2: Share | CZ2: Level | DA2: Original deal | DB2: Pre steel increase | DC2: Pre-trade deal
A3: Exports | BV3: 2023 | BW3: =100*((DataQ!D207/DataQ!D203)-1) -> 0.86831577 | BX3: =100*((DataQ!K207/DataQ!K203)-1) -> 0.86831577 | BY3: 0 | CA3: =100*((DataQ!K207/DataQ!D207)-1) -> 0 | CC3: 2023 | CD3: =100*((DataQ!E207/DataQ!E203)-1) -> 10.178266 | CE3: =100*((DataQ!L207/DataQ!L203)-1) -> 10.178266 | CG3: =100*((DataQ!L207/DataQ!E207)-1) -> 0 | CI3: 2023 | CJ3: =100*((DataQ!F207/DataQ!F203)-1) -> 9.1534853 | CK3: =100*((DataQ!M207/DataQ!M203)-1) -> 9.1534853 | CM3: =100*((DataQ!M207/DataQ!F207)-1) -> 0 | CO3: 2023 | CP3: =DataQ!J207 -> 1.215133 | CQ3: =DataQ!Q207 -> 1.215133 | CS3: =100*((DataQ!Q207/DataQ!J207)-1) -> 0 | CU3: US share in UK goods imports | CV3: =B62/100 -> 0.099705261 | CX3: Exports to US - 10% tariff | CY3: =100*(CZ3/$CZ$8) -> 5.2227766 | CZ3: =DD4-CZ10-CZ4 -> 45084 | DA3: =DD4-DA10-DA4 -> 47201 | DB3: =DD4-CZ10-CZ4 -> 45084 | DC3: =DD4-DC10-DC4 -> 38781 | DE3: =CY3/SUM($CY$3:$CY$4) -> 0.74602859
A4: 2018 | B4: ='ONS - UK Exports by type'!D221 -> 52715 | C4: ='ONS - UK Exports by type'!E221 -> 22 | D4: ='ONS - UK Exports by type'!F221 -> 39 | E4: ='ONS - UK Exports by type'!G221 -> 65 | F4: ='ONS - UK Exports by type'!H221 -> 201 | G4: ='ONS - UK Exports by type'!I221 -> 109 | H4: ='ONS - UK Exports by type'!J221 -> 26 | I4: ='ONS - UK Exports by type'!K221 -> 26 | ... AV4: ='ONS - UK Exports by type'!AX221 -> 715 | AW4: ='ONS - UK Exports by type'!AY221+'ONS - UK Exports by type'!AZ221 -> 194 | AX4: ='ONS - UK Exports by type'!BA221+'ONS - UK Exports by type'!BB221+'ONS - UK Exports by type'!BC221 -> 4849 | AY4: ='ONS - UK Exports by type'!BD221+'ONS - UK Exports by type'!BE221+'ONS - UK Exports by type'!BF221 -> 1604 | AZ4: ='ONS - UK Exports by type'!BG221+'ONS - UK Exports by type'!BH221 -> 186 | BA4: ='ONS - UK Exports by type'!BI221+'ONS - UK Exports by type'!BJ221+'ONS - UK Exports by type'!BK221 -> 2232 | BB4: ='ONS - UK Exports by type'!BL221+'ONS - UK Exports by type'!BK221+'ONS - UK Exports by type'!BM221 -> 1217 | BC4: ='ONS - UK Exports by type'!BO221+'ONS - UK Exports by type'!BP221+'ONS - UK Exports by type'!BQ221 -> 748 | BD4: ='ONS - UK Exports by type'!BR221+'ONS - UK Exports by type'!BS221+'ONS - UK Exports by type'!BT221 -> 1951 | BE4: ='ONS - UK Exports by type'!BU221+'ONS - UK Exports by type'!BV221+'ONS - UK Exports by type'!BW221 -> 832 | BF4: ='ONS - UK Exports by type'!BX221 -> 7898 | BG4: ='ONS - UK Exports by type'!BY221+'ONS - UK Exports by type'!BZ221 -> 9 | BH4: ='ONS - UK Exports by type'!CA221 -> 2355 | BI4: ='ONS - UK Exports by type'!CB221 -> 375 | BJ4: ='ONS - UK Exports by type'!CC221+'ONS - UK Exports by type'!CD221+'ONS - UK Exports by type'!CE221 -> 60 | BK4: ='ONS - UK Exports by type'!CF221+'ONS - UK Exports by type'!CG221+'ONS - UK Exports by type'!CH221 -> 554 | BL4: ='ONS - UK Exports by type'!CI221 -> 39 | BM4: ='ONS - UK Exports by type'!CJ221 -> 316 | BN4: ='ONS - UK Exports by type'!CK221 -> 53 | BO4: ='ONS - UK Exports by type'!CL221+'ONS - UK Exports by type'!CK221+'ONS - UK Exports by type'!CM221 -> 353 | BP4: ='ONS - UK Exports by type'!CO221+'ONS - UK Exports by type'!CP221+'ONS - UK Exports by type'!CQ221 -> 416 | BQ4: ='ONS - UK Exports by type'!CR221 -> 3181 | BR4: ='ONS - UK Exports by type'!CS221 -> 231 | BS4: ='ONS - UK Exports by type'!CT221+'ONS - UK Exports by type'!CU221+'ONS - UK Exports by type'!CV221 -> 1321 | BT4: ='ONS - UK Exports by type'!CW221 -> 279 | BW4: =100*((DataQ!D208/DataQ!D204)-1) -> 0.53322097 | BX4: =100*((DataQ!K208/DataQ!K204)-1) -> 0.53322097 | BY4: 0 | CA4: =100*((DataQ!K208/DataQ!D208)-1) -> 0 | CD4: =100*((DataQ!E208/DataQ!E204)-1) -> 8.439049 | CE4: =100*((DataQ!L208/DataQ!L204)-1) -> 8.439049 | CG4: =100*((DataQ!L208/DataQ!E208)-1) -> 0 | CJ4: =100*((DataQ!F208/DataQ!F204)-1) -> 2.0102585 | CK4: =100*((DataQ!M208/DataQ!M204)-1) -> 2.0102585 | CM4: =100*((DataQ!M208/DataQ!F208)-1) -> 0 | CP4: =DataQ!J208 -> 1.251867 | CQ4: =DataQ!Q208 -> 1.251867 | CS4: =100*((DataQ!Q208/DataQ!J208)-1) -> 0 | CU4: Goods import share of UK CPI basket | CV4: 0.3 | CX4: Exports to US - goods currently exempt | CY4: =100*(CZ4/$CZ$8) -> 1.7779961 | CZ4: =((CY17+CY18+CY19+CY20+CY21)/$CZ$23)*$DD$4 -> 15348 | DA4: =((CY17+CY18+CY19+CY20)/$CZ$23)*$DD$4 -> 13231 | DB4: =((CY13+CY17+CY18+CY19+CY20)/$CZ$23)*$DD$4 -> 15216 | DC4: =((CY17+CY18+CY19+CY20)/$CZ$23)*$DD$4 -> 13231 | DD4: ='ONS Pink Book - 9.4'!AA58 -> 60432 | DE4: =CY4/SUM($CY$3:$CY$4) -> 0.25397141
A5: 2019 | B5: ='ONS - UK Exports by type'!D457 -> 58893 | C5: ='ONS - UK Exports by type'!E457 -> 29 | D5: ='ONS - UK Exports by type'!F457 -> 41 | E5: ='ONS - UK Exports by type'!G457 -> 75 | F5: ='ONS - UK Exports by type'!H457 -> 331 | G5: ='ONS - UK Exports by type'!I457 -> 115 | H5: ='ONS - UK Exports by type'!J457 -> 25 | I5: ='ONS - UK Exports by type'!K457 -> 20 | ... AV5: ='ONS - UK Exports by type'!AX457 -> 755 | AW5: ='ONS - UK Exports by type'!AY457+'ONS - UK Exports by type'!AZ457 -> 211 | AX5: ='ONS - UK Exports by type'!BA457+'ONS - UK Exports by type'!BB457+'ONS - UK Exports by type'!BC457 -> 5425 | AY5: ='ONS - UK Exports by type'!BD457+'ONS - UK Exports by type'!BE457+'ONS - UK Exports by type'!BF457 -> 1772 | AZ5: ='ONS - UK Exports by type'!BG457+'ONS - UK Exports by type'!BH457 -> 181 | BA5: ='ONS - UK Exports by type'!BI457+'ONS - UK Exports by type'!BJ457+'ONS - UK Exports by type'!BK457 -> 2561 | BB5: ='ONS - UK Exports by type'!BL457+'ONS - UK Exports by type'!BK457+'ONS - UK Exports by type'!BM457 -> 1359 | BC5: ='ONS - UK Exports by type'!BO457+'ONS - UK Exports by type'!BP457+'ONS - UK Exports by type'!BQ457 -> 855 | BD5: ='ONS - UK Exports by type'!BR457+'ONS - UK Exports by type'!BS457+'ONS - UK Exports by type'!BT457 -> 2170 | BE5: ='ONS - UK Exports by type'!BU457+'ONS - UK Exports by type'!BV457+'ONS - UK Exports by type'!BW457 -> 866 | BF5: ='ONS - UK Exports by type'!BX457 -> 8685 | BG5: ='ONS - UK Exports by type'!BY457+'ONS - UK Exports by type'!BZ457 -> 5 | BH5: ='ONS - UK Exports by type'!CA457 -> 2438 | BI5: ='ONS - UK Exports by type'!CB457 -> 253 | BJ5: ='ONS - UK Exports by type'!CC457+'ONS - UK Exports by type'!CD457+'ONS - UK Exports by type'!CE457 -> 77 | BK5: ='ONS - UK Exports by type'!CF457+'ONS - UK Exports by type'!CG457+'ONS - UK Exports by type'!CH457 -> 624 | BL5: ='ONS - UK Exports by type'!CI457 -> 41 | BM5: ='ONS - UK Exports by type'!CJ457 -> 399 | BN5: ='ONS - UK Exports by type'!CK457 -> 57 | BO5: ='ONS - UK Exports by type'!CL457+'ONS - UK Exports by type'!CK457+'ONS - UK Exports by type'!CM457 -> 368 | BP5: ='ONS - UK Exports by type'!CO457+'ONS - UK Exports by type'!CP457+'ONS - UK Exports by type'!CQ457 -> 418 | BQ5: ='ONS - UK Exports by type'!CR457 -> 2739 | BR5: ='ONS - UK Exports by type'!CS457 -> 286 | BS5: ='ONS - UK Exports by type'!CT457+'ONS - UK Exports by type'!CU457+'ONS - UK Exports by type'!CV457 -> 1545 | BT5: ='ONS - UK Exports by type'!CW457 -> 2964 | BW5: =100*((DataQ!D209/DataQ!D205)-1) -> 0.31314431 | BX5: =100*((DataQ!K209/DataQ!K205)-1) -> 0.31314431 | BY5: 0 | CA5: =100*((DataQ!K209/DataQ!D209)-1) -> 0 | CD5: =100*((DataQ!E209/DataQ!E205)-1) -> 6.7136185 | CE5: =100*((DataQ!L209/DataQ!L205)-1) -> 6.7136185 | CG5: =100*((DataQ!L209/DataQ!E209)-1) -> 0 | CJ5: =100*((DataQ!F209/DataQ!F205)-1) -> -8.5368404 | CK5: =100*((DataQ!M209/DataQ!M205)-1) -> -8.5368404 | CM5: =100*((DataQ!M209/DataQ!F209)-1) -> 0 | CP5: =DataQ!J209 -> 1.2659 | CQ5: =DataQ!Q209 -> 1.2659 | CS5: =100*((DataQ!Q209/DataQ!J209)-1) -> 0 | CV5: =CV2*CV3*CV4 -> 0.0018545179 | CX5: Exports to US - steel & aluminium | CY5: =100*(CZ5/$CZ$8) -> 0.22995323 | CZ5: =(CY13/$CZ$23)*$DD$4 -> 1985 | DA5: =(CY13/$CZ$23)*$DD$4 -> 1985
A6: 2020 | B6: ='ONS - UK Exports by type'!D693 -> 47423 | C6: ='ONS - UK Exports by type'!E693 -> 23 | D6: ='ONS - UK Exports by type'!F693 -> 31 | E6: ='ONS - UK Exports by type'!G693 -> 67 | F6: ='ONS - UK Exports by type'!H693 -> 204 | G6: ='ONS - UK Exports by type'!I693 -> 104 | H6: ='ONS - UK Exports by type'!J693 -> 29 | I6: ='ONS - UK Exports by type'!K693 -> 56 | ... AV6: ='ONS - UK Exports by type'!AX693 -> 721 | AW6: ='ONS - UK Exports by type'!AY693+'ONS - UK Exports by type'!AZ693 -> 205 | AX6: ='ONS - UK Exports by type'!BA693+'ONS - UK Exports by type'!BB693+'ONS - UK Exports by type'!BC693 -> 3775 | AY6: ='ONS - UK Exports by type'!BD693+'ONS - UK Exports by type'!BE693+'ONS - UK Exports by type'!BF693 -> 1315 | AZ6: ='ONS - UK Exports by type'!BG693+'ONS - UK Exports by type'!BH693 -> 208 | BA6: ='ONS - UK Exports by type'!BI693+'ONS - UK Exports by type'!BJ693+'ONS - UK Exports by type'!BK693 -> 2594 | BB6: ='ONS - UK Exports by type'!BL693+'ONS - UK Exports by type'!BK693+'ONS - UK Exports by type'!BM693 -> 1590 | BC6: ='ONS - UK Exports by type'!BO693+'ONS - UK Exports by type'!BP693+'ONS - UK Exports by type'!BQ693 -> 803 | BD6: ='ONS - UK Exports by type'!BR693+'ONS - UK Exports by type'!BS693+'ONS - UK Exports by type'!BT693 -> 2130 | BE6: ='ONS - UK Exports by type'!BU693+'ONS - UK Exports by type'!BV693+'ONS - UK Exports by type'!BW693 -> 698 | BF6: ='ONS - UK Exports by type'!BX693 -> 5850 | BG6: ='ONS - UK Exports by type'!BY693+'ONS - UK Exports by type'!BZ693 -> 11 | BH6: ='ONS - UK Exports by type'!CA693 -> 2205 | BI6: ='ONS - UK Exports by type'!CB693 -> 379 | BJ6: ='ONS - UK Exports by type'!CC693+'ONS - UK Exports by type'!CD693+'ONS - UK Exports by type'!CE693 -> 73 | BK6: ='ONS - UK Exports by type'!CF693+'ONS - UK Exports by type'!CG693+'ONS - UK Exports by type'!CH693 -> 492 | BL6: ='ONS - UK Exports by type'!CI693 -> 44 | BM6: ='ONS - UK Exports by type'!CJ693 -> 340 | BN6: ='ONS - UK Exports by type'!CK693 -> 43 | BO6: ='ONS - UK Exports by type'!CL693+'ONS - UK Exports by type'!CK693+'ONS - UK Exports by type'!CM693 -> 303 | BP6: ='ONS - UK Exports by type'!CO693+'ONS - UK Exports by type'!CP693+'ONS - UK Exports by type'!CQ693 -> 322 | BQ6: ='ONS - UK Exports by type'!CR693 -> 1626 | BR6: ='ONS - UK Exports by type'!CS693 -> 167 | BS6: ='ONS - UK Exports by type'!CT693+'ONS - UK Exports by type'!CU693+'ONS - UK Exports by type'!CV693 -> 1410 | BT6: ='ONS - UK Exports by type'!CW693 -> 983 | BW6: =100*((DataQ!D210/DataQ!D206)-1) -> -0.34997571 | BX6: =100*((DataQ!K210/DataQ!K206)-1) -> -0.34997571 | BY6: 0 | CA6: =100*((DataQ!K210/DataQ!D210)-1) -> 0 | CD6: =100*((DataQ!E210/DataQ!E206)-1) -> 4.1568272 | CE6: =100*((DataQ!L210/DataQ!L206)-1) -> 4.1568272 | CG6: =100*((DataQ!L210/DataQ!E210)-1) -> 0 | CJ6: =100*((DataQ!F210/DataQ!F206)-1) -> -9.1616093 | CK6: =100*((DataQ!M210/DataQ!M206)-1) -> -9.1616093 | CM6: =100*((DataQ!M210/DataQ!F210)-1) -> 0 | CP6: =DataQ!J210 -> 1.2417 | CQ6: =DataQ!Q210 -> 1.2417 | CS6: =100*((DataQ!Q210/DataQ!J210)-1) -> 0 | CX6: Goods exports to other countries | CY6: =100*(CZ6/$CZ$8) -> 38.586268 | CZ6: ='ONS Pink Book - 9.4'!AA94-'ONS Pink Book - 9.4'!AA58 -> 333084 | DA6: ='ONS Pink Book - 9.4'!AA94-'ONS Pink Book - 9.4'!AA58 -> 333084 | DB6: ='ONS Pink Book - 9.4'!AA94-'ONS Pink Book - 9.4'!AA58 -> 333084 | DC6: ='ONS Pink Book - 9.4'!AA94-'ONS Pink Book - 9.4'!AA58 -> 333084
A7: 2021 | B7: ='ONS - UK Exports by type'!D929 -> 49720 | C7: ='ONS - UK Exports by type'!E929 -> 44 | D7: ='ONS - UK Exports by type'!F929 -> 42 | E7: ='ONS - UK Exports by type'!G929 -> 78 | F7: ='ONS - UK Exports by type'!H929 -> 226 | G7: ='ONS - UK Exports by type'!I929 -> 124 | H7: ='ONS - UK Exports by type'!J929 -> 23 | I7: ='ONS - UK Exports by type'!K929 -> 23 | ... AV7: ='ONS - UK Exports by type'!AX929 -> 720 | AW7: ='ONS - UK Exports by type'!AY929+'ONS - UK Exports by type'!AZ929 -> 191 | AX7: ='ONS - UK Exports by type'!BA929+'ONS - UK Exports by type'!BB929+'ONS - UK Exports by type'!BC929 -> 3558 | AY7: ='ONS - UK Exports by type'!BD929+'ONS - UK Exports by type'!BE929+'ONS - UK Exports by type'!BF929 -> 1530 | AZ7: ='ONS - UK Exports by type'!BG929+'ONS - UK Exports by type'!BH929 -> 235 | BA7: ='ONS - UK Exports by type'!BI929+'ONS - UK Exports by type'!BJ929+'ONS - UK Exports by type'!BK929 -> 2639 | BB7: ='ONS - UK Exports by type'!BL929+'ONS - UK Exports by type'!BK929+'ONS - UK Exports by type'!BM929 -> 1689 | BC7: ='ONS - UK Exports by type'!BO929+'ONS - UK Exports by type'!BP929+'ONS - UK Exports by type'!BQ929 -> 777 | BD7: ='ONS - UK Exports by type'!BR929+'ONS - UK Exports by type'!BS929+'ONS - UK Exports by type'!BT929 -> 2153 | BE7: ='ONS - UK Exports by type'!BU929+'ONS - UK Exports by type'!BV929+'ONS - UK Exports by type'!BW929 -> 886 | BF7: ='ONS - UK Exports by type'!BX929 -> 6803 | BG7: ='ONS - UK Exports by type'!BY929+'ONS - UK Exports by type'!BZ929 -> 17 | BH7: ='ONS - UK Exports by type'!CA929 -> 1985 | BI7: ='ONS - UK Exports by type'!CB929 -> 411 | BJ7: ='ONS - UK Exports by type'!CC929+'ONS - UK Exports by type'!CD929+'ONS - UK Exports by type'!CE929 -> 88 | BK7: ='ONS - UK Exports by type'!CF929+'ONS - UK Exports by type'!CG929+'ONS - UK Exports by type'!CH929 -> 369 | BL7: ='ONS - UK Exports by type'!CI929 -> 47 | BM7: ='ONS - UK Exports by type'!CJ929 -> 603 | BN7: ='ONS - UK Exports by type'!CK929 -> 55 | BO7: ='ONS - UK Exports by type'!CL929+'ONS - UK Exports by type'!CK929+'ONS - UK Exports by type'!CM929 -> 321 | BP7: ='ONS - UK Exports by type'!CO929+'ONS - UK Exports by type'!CP929+'ONS - UK Exports by type'!CQ929 -> 275 | BQ7: ='ONS - UK Exports by type'!CR929 -> 1426 | BR7: ='ONS - UK Exports by type'!CS929 -> 240 | BS7: ='ONS - UK Exports by type'!CT929+'ONS - UK Exports by type'!CU929+'ONS - UK Exports by type'!CV929 -> 1666 | BT7: ='ONS - UK Exports by type'!CW929 -> 253 | BV7: 2024 | BW7: =100*((DataQ!D211/DataQ!D207)-1) -> 0.25369832 | BX7: =100*((DataQ!K211/DataQ!K207)-1) -> 0.25369832 | BY7: 0 | CA7: =100*((DataQ!K211/DataQ!D211)-1) -> 0 | CC7: 2024 | CD7: =100*((DataQ!E211/DataQ!E207)-1) -> 3.5491137 | CE7: =100*((DataQ!L211/DataQ!L207)-1) -> 3.5491137 | CG7: =100*((DataQ!L211/DataQ!E211)-1) -> 0 | CI7: 2024 | CJ7: =100*((DataQ!F211/DataQ!F207)-1) -> -2.5841338 | CK7: =100*((DataQ!M211/DataQ!M207)-1) -> -2.5841338 | CM7: =100*((DataQ!M211/DataQ!F211)-1) -> 0 | CO7: 2024 | CP7: =DataQ!J211 -> 1.267967 | CQ7: =DataQ!Q211 -> 1.267967 | CS7: =100*((DataQ!Q211/DataQ!J211)-1) -> 0 | CX7: Services exports | CY7: =100*(CZ7/$CZ$8) -> 54.183006 | CZ7: ='ONS Pink Book - 9.5'!AA94 -> 467718 | DA7: ='ONS Pink Book - 9.5'!AA94 -> 467718 | DB7: ='ONS Pink Book - 9.5'!AA94 -> 467718 | DC7: ='ONS Pink Book - 9.5'!AA94 -> 467718
A8: 2022 | B8: ='ONS - UK Exports by type'!D1165 -> 59940 | C8: ='ONS - UK Exports by type'!E1165 -> 69 | D8: ='ONS - UK Exports by type'!F1165 -> 41 | E8: ='ONS - UK Exports by type'!G1165 -> 127 | F8: ='ONS - UK Exports by type'!H1165 -> 257 | G8: ='ONS - UK Exports by type'!I1165 -> 166 | H8: ='ONS - UK Exports by type'!J1165 -> 27 | I8: ='ONS - UK Exports by type'!K1165 -> 22 | ... AV8: ='ONS - UK Exports by type'!AX1165 -> 882 | AW8: ='ONS - UK Exports by type'!AY1165+'ONS - UK Exports by type'!AZ1165 -> 244 | AX8: ='ONS - UK Exports by type'!BA1165+'ONS - UK Exports by type'!BB1165+'ONS - UK Exports by type'!BC1165 -> 4475 | AY8: ='ONS - UK Exports by type'!BD1165+'ONS - UK Exports by type'!BE1165+'ONS - UK Exports by type'!BF1165 -> 2004 | AZ8: ='ONS - UK Exports by type'!BG1165+'ONS - UK Exports by type'!BH1165 -> 240 | BA8: ='ONS - UK Exports by type'!BI1165+'ONS - UK Exports by type'!BJ1165+'ONS - UK Exports by type'!BK1165 -> 3380 | BB8: ='ONS - UK Exports by type'!BL1165+'ONS - UK Exports by type'!BK1165+'ONS - UK Exports by type'!BM1165 -> 2218 | BC8: ='ONS - UK Exports by type'!BO1165+'ONS - UK Exports by type'!BP1165+'ONS - UK Exports by type'!BQ1165 -> 952 | BD8: ='ONS - UK Exports by type'!BR1165+'ONS - UK Exports by type'!BS1165+'ONS - UK Exports by type'!BT1165 -> 2416 | BE8: ='ONS - UK Exports by type'!BU1165+'ONS - UK Exports by type'!BV1165+'ONS - UK Exports by type'!BW1165 -> 1268 | BF8: ='ONS - UK Exports by type'!BX1165 -> 7238 | BG8: ='ONS - UK Exports by type'!BY1165+'ONS - UK Exports by type'!BZ1165 -> 14 | BH8: ='ONS - UK Exports by type'!CA1165 -> 1925 | BI8: ='ONS - UK Exports by type'!CB1165 -> 242 | BJ8: ='ONS - UK Exports by type'!CC1165+'ONS - UK Exports by type'!CD1165+'ONS - UK Exports by type'!CE1165 -> 110 | BK8: ='ONS - UK Exports by type'!CF1165+'ONS - UK Exports by type'!CG1165+'ONS - UK Exports by type'!CH1165 -> 464 | BL8: ='ONS - UK Exports by type'!CI1165 -> 68 | BM8: ='ONS - UK Exports by type'!CJ1165 -> 501 | BN8: ='ONS - UK Exports by type'!CK1165 -> 55 | BO8: ='ONS - UK Exports by type'!CL1165+'ONS - UK Exports by type'!CK1165+'ONS - UK Exports by type'!CM1165 -> 350 | BP8: ='ONS - UK Exports by type'!CO1165+'ONS - UK Exports by type'!CP1165+'ONS - UK Exports by type'!CQ1165 -> 324 | BQ8: ='ONS - UK Exports by type'!CR1165 -> 1925 | BR8: ='ONS - UK Exports by type'!CS1165 -> 326 | BS8: ='ONS - UK Exports by type'!CT1165+'ONS - UK Exports by type'!CU1165+'ONS - UK Exports by type'!CV1165 -> 2021 | BT8: ='ONS - UK Exports by type'!CW1165 -> 295 | BW8: =100*((DataQ!D212/DataQ!D208)-1) -> 0.70451165 | BX8: =100*((DataQ!K212/DataQ!K208)-1) -> 0.70451165 | BY8: 0 | CA8: =100*((DataQ!K212/DataQ!D212)-1) -> 0 | CD8: =100*((DataQ!E212/DataQ!E208)-1) -> 2.1108336 | CE8: =100*((DataQ!L212/DataQ!L208)-1) -> 2.1108336 | CG8: =100*((DataQ!L212/DataQ!E212)-1) -> 0 | CJ8: =100*((DataQ!F212/DataQ!F208)-1) -> -2.8735165 | CK8: =100*((DataQ!M212/DataQ!M208)-1) -> -2.8735165 | CM8: =100*((DataQ!M212/DataQ!F212)-1) -> 0 | CP8: =DataQ!J212 -> 1.261867 | CQ8: =DataQ!Q212 -> 1.261867 | CS8: =100*((DataQ!Q212/DataQ!J212)-1) -> 0 | CZ8: =SUM(CZ3:CZ7) -> 863219 | DA8: =SUM(DA3:DA7) -> 863219 | DB8: =SUM(DB3:DB7) -> 861102 | DC8: =SUM(DC3:DC7) -> 852814 | DD8: ='ONS Pink Book - 9.3'!AA94 -> 861234
A9: 2023 | B9: ='ONS - UK Exports by type'!D1401 -> 60432 | C9: ='ONS - UK Exports by type'!E1401 -> 41 | D9: ='ONS - UK Exports by type'!F1401 -> 33 | E9: ='ONS - UK Exports by type'!G1401 -> 99 | F9: ='ONS - UK Exports by type'!H1401 -> 245 | G9: ='ONS - UK Exports by type'!I1401 -> 137 | H9: ='ONS - UK Exports by type'!J1401 -> 30 | I9: ='ONS - UK Exports by type'!K1401 -> 10 | ... AV9: ='ONS - UK Exports by type'!AX1401 -> 931 | AW9: ='ONS - UK Exports by type'!AY1401+'ONS - UK Exports by type'!AZ1401 -> 296 | AX9: ='ONS - UK Exports by type'!BA1401+'ONS - UK Exports by type'!BB1401+'ONS - UK Exports by type'!BC1401 -> 6077 | AY9: ='ONS - UK Exports by type'!BD1401+'ONS - UK Exports by type'!BE1401+'ONS - UK Exports by type'!BF1401 -> 2495 | AZ9: ='ONS - UK Exports by type'!BG1401+'ONS - UK Exports by type'!BH1401 -> 203 | BA9: ='ONS - UK Exports by type'!BI1401+'ONS - UK Exports by type'!BJ1401+'ONS - UK Exports by type'!BK1401 -> 3842 | BB9: ='ONS - UK Exports by type'!BL1401+'ONS - UK Exports by type'!BK1401+'ONS - UK Exports by type'!BM1401 -> 2481 | BC9: ='ONS - UK Exports by type'!BO1401+'ONS - UK Exports by type'!BP1401+'ONS - UK Exports by type'!BQ1401 -> 968 | BD9: ='ONS - UK Exports by type'!BR1401+'ONS - UK Exports by type'!BS1401+'ONS - UK Exports by type'!BT1401 -> 2558 | BE9: ='ONS - UK Exports by type'!BU1401+'ONS - UK Exports by type'!BV1401+'ONS - UK Exports by type'!BW1401 -> 1333 | BF9: ='ONS - UK Exports by type'!BX1401 -> 6435 | BG9: ='ONS - UK Exports by type'!BY1401+'ONS - UK Exports by type'!BZ1401 -> 7 | BH9: ='ONS - UK Exports by type'!CA1401 -> 2117 | BI9: ='ONS - UK Exports by type'!CB1401 -> 290 | BJ9: ='ONS - UK Exports by type'!CC1401+'ONS - UK Exports by type'!CD1401+'ONS - UK Exports by type'!CE1401 -> 109 | BK9: ='ONS - UK Exports by type'!CF1401+'ONS - UK Exports by type'!CG1401+'ONS - UK Exports by type'!CH1401 -> 531 | BL9: ='ONS - UK Exports by type'!CI1401 -> 56 | BM9: ='ONS - UK Exports by type'!CJ1401 -> 409 | BN9: ='ONS - UK Exports by type'!CK1401 -> 54 | BO9: ='ONS - UK Exports by type'!CL1401+'ONS - UK Exports by type'!CK1401+'ONS - UK Exports by type'!CM1401 -> 396 | BP9: ='ONS - UK Exports by type'!CO1401+'ONS - UK Exports by type'!CP1401+'ONS - UK Exports by type'!CQ1401 -> 336 | BQ9: ='ONS - UK Exports by type'!CR1401 -> 1482 | BR9: ='ONS - UK Exports by type'!CS1401 -> 277 | BS9: ='ONS - UK Exports by type'!CT1401+'ONS - UK Exports by type'!CU1401+'ONS - UK Exports by type'!CV1401 -> 2012 | BT9: ='ONS - UK Exports by type'!CW1401 -> 1206 | BW9: =100*((DataQ!D213/DataQ!D209)-1) -> 1.0703897 | BX9: =100*((DataQ!K213/DataQ!K209)-1) -> 1.0703897 | BY9: 0 | CA9: =100*((DataQ!K213/DataQ!D213)-1) -> 0 | CD9: =100*((DataQ!E213/DataQ!E209)-1) -> 2.0547945 | CE9: =100*((DataQ!L213/DataQ!L209)-1) -> 2.0547945 | CG9: =100*((DataQ!L213/DataQ!E213)-1) -> 0 | CJ9: =100*((DataQ!F213/DataQ!F209)-1) -> 0.73738076 | CK9: =100*((DataQ!M213/DataQ!M209)-1) -> 0.73738076 | CM9: =100*((DataQ!M213/DataQ!F213)-1) -> 0 | CP9: =DataQ!J213 -> 1.300467 | CQ9: =DataQ!Q213 -> 1.300467 | CS9: =100*((DataQ!Q213/DataQ!J213)-1) -> 0
BW10: =100*((DataQ!D214/DataQ!D210)-1) -> 1.9092154 | BX10: =100*((DataQ!K214/DataQ!K210)-1) -> 1.9101967 | BY10: 0 | CA10: =100*((DataQ!K214/DataQ!D214)-1) -> 0.00096290053 | CD10: =100*((DataQ!E214/DataQ!E210)-1) -> 2.4228082 | CE10: =100*((DataQ!L214/DataQ!L210)-1) -> 2.427279 | CG10: =100*((DataQ!L214/DataQ!E214)-1) -> 0.0043650676 | CJ10: =100*((DataQ!F214/DataQ!F210)-1) -> 1.7531388 | CK10: =100*((DataQ!M214/DataQ!M210)-1) -> 1.7640714 | CM10: =100*((DataQ!M214/DataQ!F214)-1) -> 0.01074416 | CP10: =DataQ!J214 -> 1.303542 | CQ10: =DataQ!Q214 -> 1.303544 | CS10: =100*((DataQ!Q214/DataQ!J214)-1) -> 0.00015342812 | CX10: Exports to US - sector-specific tariffs | CY10: =100*(CZ10/$CZ$8) -> 0 | CZ10: 0 | DC10: =((CY13+CY14)/$CZ$23)*$DD$4 -> 8420 | DE10: =CY10/SUM($CY$3:$CY$4) -> 0
A11: Imports | BV11: 2025 | BW11: =100*((DataQ!D215/DataQ!D211)-1) -> 1.5549918 | BX11: =100*((DataQ!K215/DataQ!K211)-1) -> 1.5514239 | BY11: 0 | CA11: =100*((DataQ!K215/DataQ!D215)-1) -> -0.0035133054 | CC11: 2025 | CD11: =100*((DataQ!E215/DataQ!E211)-1) -> 2.4920105 | CE11: =100*((DataQ!L215/DataQ!L211)-1) -> 2.5084923 | CG11: =100*((DataQ!L215/DataQ!E215)-1) -> 0.016081108 | CI11: 2025 | CJ11: =100*((DataQ!F215/DataQ!F211)-1) -> 3.2832407 | CK11: =100*((DataQ!M215/DataQ!M211)-1) -> 3.2933509 | CM11: =100*((DataQ!M215/DataQ!F215)-1) -> 0.0097887437 | CO11: 2025 | CP11: =DataQ!J215 -> 1.272145 | CQ11: =DataQ!Q215 -> 1.272144 | CS11: =100*((DataQ!Q215/DataQ!J215)-1) -> -7.8607391e-05
A12: 2018 | B12: ='ONS - UK Imports by type'!D221 -> 41613 | C12: ='ONS - UK Imports by type'!E221 -> 40 | D12: ='ONS - UK Imports by type'!F221 -> 7 | E12: ='ONS - UK Imports by type'!G221 -> 23 | F12: ='ONS - UK Imports by type'!H221 -> 67 | G12: ='ONS - UK Imports by type'!I221 -> 84 | H12: ='ONS - UK Imports by type'!J221 -> 345 | I12: ='ONS - UK Imports by type'!K221 -> 26 | ... AV12: ='ONS - UK Imports by type'!AX221 -> 1021 | AW12: ='ONS - UK Imports by type'!AY221+'ONS - UK Imports by type'!AZ221 -> 265 | AX12: ='ONS - UK Imports by type'!BA221+'ONS - UK Imports by type'!BB221+'ONS - UK Imports by type'!BC221 -> 6298 | AY12: ='ONS - UK Imports by type'!BD221+'ONS - UK Imports by type'!BE221+'ONS - UK Imports by type'!BF221 -> 746 | AZ12: ='ONS - UK Imports by type'!BG221+'ONS - UK Imports by type'!BH221 -> 120 | BA12: ='ONS - UK Imports by type'!BI221+'ONS - UK Imports by type'!BJ221+'ONS - UK Imports by type'!BK221 -> 2364 | BB12: ='ONS - UK Imports by type'!BL221+'ONS - UK Imports by type'!BK221+'ONS - UK Imports by type'!BM221 -> 1371 | BC12: ='ONS - UK Imports by type'!BO221+'ONS - UK Imports by type'!BP221+'ONS - UK Imports by type'!BQ221 -> 1280 | BD12: ='ONS - UK Imports by type'!BR221+'ONS - UK Imports by type'!BS221+'ONS - UK Imports by type'!BT221 -> 2456 | BE12: ='ONS - UK Imports by type'!BU221+'ONS - UK Imports by type'!BV221+'ONS - UK Imports by type'!BW221 -> 607 | BF12: ='ONS - UK Imports by type'!BX221 -> 109 | BG12: ='ONS - UK Imports by type'!BY221+'ONS - UK Imports by type'!BZ221 -> 7 | BH12: ='ONS - UK Imports by type'!CA221 -> 2614 | BI12: ='ONS - UK Imports by type'!CB221 -> 63 | BJ12: ='ONS - UK Imports by type'!CC221+'ONS - UK Imports by type'!CD221+'ONS - UK Imports by type'!CE221 -> 51 | BK12: ='ONS - UK Imports by type'!CF221+'ONS - UK Imports by type'!CG221+'ONS - UK Imports by type'!CH221 -> 362 | BL12: ='ONS - UK Imports by type'!CI221 -> 32 | BM12: ='ONS - UK Imports by type'!CJ221 -> 355 | BN12: ='ONS - UK Imports by type'!CK221 -> 28 | BO12: ='ONS - UK Imports by type'!CL221+'ONS - UK Imports by type'!CK221+'ONS - UK Imports by type'!CM221 -> 263 | BP12: ='ONS - UK Imports by type'!CO221+'ONS - UK Imports by type'!CP221+'ONS - UK Imports by type'!CQ221 -> 239 | BQ12: ='ONS - UK Imports by type'!CR221 -> 1321 | BR12: ='ONS - UK Imports by type'!CS221 -> 175 | BS12: ='ONS - UK Imports by type'!CT221+'ONS - UK Imports by type'!CU221+'ONS - UK Imports by type'!CV221 -> 1616 | BT12: ='ONS - UK Imports by type'!CW221 -> 1651 | BW12: =100*((DataQ!D216/DataQ!D212)-1) -> 1.4791854 | BX12: =100*((DataQ!K216/DataQ!K212)-1) -> 1.4683107 | BY12: 0 | CA12: =100*((DataQ!K216/DataQ!D216)-1) -> -0.01071624 | CD12: =100*((DataQ!E216/DataQ!E212)-1) -> 2.3163891 | CE12: =100*((DataQ!L216/DataQ!L212)-1) -> 2.3495647 | CG12: =100*((DataQ!L216/DataQ!E216)-1) -> 0.032424522 | CJ12: =100*((DataQ!F216/DataQ!F212)-1) -> 4.0953895 | CK12: =100*((DataQ!M216/DataQ!M212)-1) -> 4.1028695 | CM12: =100*((DataQ!M216/DataQ!F216)-1) -> 0.0071857012 | CP12: =DataQ!J216 -> 1.275929 | CQ12: =DataQ!Q216 -> 1.275929 | CS12: =100*((DataQ!Q216/DataQ!J216)-1) -> 0 | CX12: =CX10 -> Exports to US - sector-specific tariffs
A13: 2019 | B13: ='ONS - UK Imports by type'!D457 -> 46839 | C13: ='ONS - UK Imports by type'!E457 -> 26 | D13: ='ONS - UK Imports by type'!F457 -> 6 | E13: ='ONS - UK Imports by type'!G457 -> 20 | F13: ='ONS - UK Imports by type'!H457 -> 71 | G13: ='ONS - UK Imports by type'!I457 -> 64 | H13: ='ONS - UK Imports by type'!J457 -> 339 | I13: ='ONS - UK Imports by type'!K457 -> 28 | ... AV13: ='ONS - UK Imports by type'!AX457 -> 1079 | AW13: ='ONS - UK Imports by type'!AY457+'ONS - UK Imports by type'!AZ457 -> 289 | AX13: ='ONS - UK Imports by type'!BA457+'ONS - UK Imports by type'!BB457+'ONS - UK Imports by type'!BC457 -> 7067 | AY13: ='ONS - UK Imports by type'!BD457+'ONS - UK Imports by type'!BE457+'ONS - UK Imports by type'!BF457 -> 731 | AZ13: ='ONS - UK Imports by type'!BG457+'ONS - UK Imports by type'!BH457 -> 124 | BA13: ='ONS - UK Imports by type'!BI457+'ONS - UK Imports by type'!BJ457+'ONS - UK Imports by type'!BK457 -> 2621 | BB13: ='ONS - UK Imports by type'!BL457+'ONS - UK Imports by type'!BK457+'ONS - UK Imports by type'!BM457 -> 1466 | BC13: ='ONS - UK Imports by type'!BO457+'ONS - UK Imports by type'!BP457+'ONS - UK Imports by type'!BQ457 -> 1343 | BD13: ='ONS - UK Imports by type'!BR457+'ONS - UK Imports by type'!BS457+'ONS - UK Imports by type'!BT457 -> 2731 | BE13: ='ONS - UK Imports by type'!BU457+'ONS - UK Imports by type'!BV457+'ONS - UK Imports by type'!BW457 -> 643 | BF13: ='ONS - UK Imports by type'!BX457 -> 122 | BG13: ='ONS - UK Imports by type'!BY457+'ONS - UK Imports by type'!BZ457 -> 8 | BH13: ='ONS - UK Imports by type'!CA457 -> 2176 | BI13: ='ONS - UK Imports by type'!CB457 -> 41 | BJ13: ='ONS - UK Imports by type'!CC457+'ONS - UK Imports by type'!CD457+'ONS - UK Imports by type'!CE457 -> 64 | BK13: ='ONS - UK Imports by type'!CF457+'ONS - UK Imports by type'!CG457+'ONS - UK Imports by type'!CH457 -> 388 | BL13: ='ONS - UK Imports by type'!CI457 -> 31 | BM13: ='ONS - UK Imports by type'!CJ457 -> 340 | BN13: ='ONS - UK Imports by type'!CK457 -> 30 | BO13: ='ONS - UK Imports by type'!CL457+'ONS - UK Imports by type'!CK457+'ONS - UK Imports by type'!CM457 -> 277 | BP13: ='ONS - UK Imports by type'!CO457+'ONS - UK Imports by type'!CP457+'ONS - UK Imports by type'!CQ457 -> 251 | BQ13: ='ONS - UK Imports by type'!CR457 -> 1350 | BR13: ='ONS - UK Imports by type'!CS457 -> 208 | BS13: ='ONS - UK Imports by type'!CT457+'ONS - UK Imports by type'!CU457+'ONS - UK Imports by type'!CV457 -> 1699 | BT13: ='ONS - UK Imports by type'!CW457 -> 4210 | BW13: =100*((DataQ!D217/DataQ!D213)-1) -> 1.6055609 | BX13: =100*((DataQ!K217/DataQ!K213)-1) -> 1.5896575 | BY13: 0 | CA13: =100*((DataQ!K217/DataQ!D217)-1) -> -0.015652137 | CD13: =100*((DataQ!E217/DataQ!E213)-1) -> 2.7128262 | CE13: =100*((DataQ!L217/DataQ!L213)-1) -> 2.7604773 | CG13: =100*((DataQ!L217/DataQ!E217)-1) -> 0.04639246 | CJ13: =100*((DataQ!F217/DataQ!F213)-1) -> 2.6564633 | CK13: =100*((DataQ!M217/DataQ!M213)-1) -> 2.6645272 | CM13: =100*((DataQ!M217/DataQ!F217)-1) -> 0.0078552637 | CP13: =DataQ!J217 -> 1.279734 | CQ13: =DataQ!Q217 -> 1.279739 | CS13: =100*((DataQ!Q217/DataQ!J217)-1) -> 0.00039070619 | CX13: Steel/aluminium | CY13: ='ONS - UK Exports by type'!AV1401+'ONS - UK Exports by type'!AW1401 -> 1985
A14: 2020 | B14: ='ONS - UK Imports by type'!D693 -> 37577 | C14: ='ONS - UK Imports by type'!E693 -> 8 | D14: ='ONS - UK Imports by type'!F693 -> 6 | E14: ='ONS - UK Imports by type'!G693 -> 23 | F14: ='ONS - UK Imports by type'!H693 -> 74 | G14: ='ONS - UK Imports by type'!I693 -> 66 | H14: ='ONS - UK Imports by type'!J693 -> 326 | I14: ='ONS - UK Imports by type'!K693 -> 34 | ... AV14: ='ONS - UK Imports by type'!AX693 -> 864 | AW14: ='ONS - UK Imports by type'!AY693+'ONS - UK Imports by type'!AZ693 -> 238 | AX14: ='ONS - UK Imports by type'!BA693+'ONS - UK Imports by type'!BB693+'ONS - UK Imports by type'!BC693 -> 4931 | AY14: ='ONS - UK Imports by type'!BD693+'ONS - UK Imports by type'!BE693+'ONS - UK Imports by type'!BF693 -> 704 | AZ14: ='ONS - UK Imports by type'!BG693+'ONS - UK Imports by type'!BH693 -> 92 | BA14: ='ONS - UK Imports by type'!BI693+'ONS - UK Imports by type'!BJ693+'ONS - UK Imports by type'!BK693 -> 1998 | BB14: ='ONS - UK Imports by type'!BL693+'ONS - UK Imports by type'!BK693+'ONS - UK Imports by type'!BM693 -> 1181 | BC14: ='ONS - UK Imports by type'!BO693+'ONS - UK Imports by type'!BP693+'ONS - UK Imports by type'!BQ693 -> 1153 | BD14: ='ONS - UK Imports by type'!BR693+'ONS - UK Imports by type'!BS693+'ONS - UK Imports by type'!BT693 -> 2146 | BE14: ='ONS - UK Imports by type'!BU693+'ONS - UK Imports by type'!BV693+'ONS - UK Imports by type'!BW693 -> 430 | BF14: ='ONS - UK Imports by type'!BX693 -> 60 | BG14: ='ONS - UK Imports by type'!BY693+'ONS - UK Imports by type'!BZ693 -> 9 | BH14: ='ONS - UK Imports by type'!CA693 -> 1733 | BI14: ='ONS - UK Imports by type'!CB693 -> 107 | BJ14: ='ONS - UK Imports by type'!CC693+'ONS - UK Imports by type'!CD693+'ONS - UK Imports by type'!CE693 -> 48 | BK14: ='ONS - UK Imports by type'!CF693+'ONS - UK Imports by type'!CG693+'ONS - UK Imports by type'!CH693 -> 281 | BL14: ='ONS - UK Imports by type'!CI693 -> 22 | BM14: ='ONS - UK Imports by type'!CJ693 -> 292 | BN14: ='ONS - UK Imports by type'!CK693 -> 23 | BO14: ='ONS - UK Imports by type'!CL693+'ONS - UK Imports by type'!CK693+'ONS - UK Imports by type'!CM693 -> 207 | BP14: ='ONS - UK Imports by type'!CO693+'ONS - UK Imports by type'!CP693+'ONS - UK Imports by type'!CQ693 -> 248 | BQ14: ='ONS - UK Imports by type'!CR693 -> 824 | BR14: ='ONS - UK Imports by type'!CS693 -> 168 | BS14: ='ONS - UK Imports by type'!CT693+'ONS - UK Imports by type'!CU693+'ONS - UK Imports by type'!CV693 -> 1476 | BT14: ='ONS - UK Imports by type'!CW693 -> 1781 | BW14: =100*((DataQ!D218/DataQ!D214)-1) -> 1.5139437 | BX14: =100*((DataQ!K218/DataQ!K214)-1) -> 1.4992062 | BY14: 0 | CA14: =100*((DataQ!K218/DataQ!D218)-1) -> -0.013554945 | CD14: =100*((DataQ!E218/DataQ!E214)-1) -> 2.5821964 | CE14: =100*((DataQ!L218/DataQ!L214)-1) -> 2.6645725 | CG14: =100*((DataQ!L218/DataQ!E218)-1) -> 0.084671074 | CJ14: =100*((DataQ!F218/DataQ!F214)-1) -> 2.0264918 | CK14: =100*((DataQ!M218/DataQ!M214)-1) -> 2.0449908 | CM14: =100*((DataQ!M218/DataQ!F218)-1) -> 0.02887767 | CP14: =DataQ!J218 -> 1.283582 | CQ14: =DataQ!Q218 -> 1.276834 | CS14: =100*((DataQ!Q218/DataQ!J218)-1) -> -0.52571632 | CX14: Cars & car parts | CY14: ='ONS - UK Exports by type'!BX1401 -> 6435 | CZ14: =100*(((CY13+CY14)/'ONS - UK Exports by type'!D1423)*(1-CY7/100)) -> 0.98033903
A15: 2021 | B15: ='ONS - UK Imports by type'!D929 -> 39247 | C15: ='ONS - UK Imports by type'!E929 -> 11 | D15: ='ONS - UK Imports by type'!F929 -> 9 | E15: ='ONS - UK Imports by type'!G929 -> 23 | F15: ='ONS - UK Imports by type'!H929 -> 46 | G15: ='ONS - UK Imports by type'!I929 -> 50 | H15: ='ONS - UK Imports by type'!J929 -> 268 | I15: ='ONS - UK Imports by type'!K929 -> 39 | ... AV15: ='ONS - UK Imports by type'!AX929 -> 766 | AW15: ='ONS - UK Imports by type'!AY929+'ONS - UK Imports by type'!AZ929 -> 220 | AX15: ='ONS - UK Imports by type'!BA929+'ONS - UK Imports by type'!BB929+'ONS - UK Imports by type'!BC929 -> 3615 | AY15: ='ONS - UK Imports by type'!BD929+'ONS - UK Imports by type'!BE929+'ONS - UK Imports by type'!BF929 -> 618 | AZ15: ='ONS - UK Imports by type'!BG929+'ONS - UK Imports by type'!BH929 -> 129 | BA15: ='ONS - UK Imports by type'!BI929+'ONS - UK Imports by type'!BJ929+'ONS - UK Imports by type'!BK929 -> 1953 | BB15: ='ONS - UK Imports by type'!BL929+'ONS - UK Imports by type'!BK929+'ONS - UK Imports by type'!BM929 -> 1246 | BC15: ='ONS - UK Imports by type'!BO929+'ONS - UK Imports by type'!BP929+'ONS - UK Imports by type'!BQ929 -> 1145 | BD15: ='ONS - UK Imports by type'!BR929+'ONS - UK Imports by type'!BS929+'ONS - UK Imports by type'!BT929 -> 2070 | BE15: ='ONS - UK Imports by type'!BU929+'ONS - UK Imports by type'!BV929+'ONS - UK Imports by type'!BW929 -> 375 | BF15: ='ONS - UK Imports by type'!BX929 -> 138 | BG15: ='ONS - UK Imports by type'!BY929+'ONS - UK Imports by type'!BZ929 -> 8 | BH15: ='ONS - UK Imports by type'!CA929 -> 1663 | BI15: ='ONS - UK Imports by type'!CB929 -> 35 | BJ15: ='ONS - UK Imports by type'!CC929+'ONS - UK Imports by type'!CD929+'ONS - UK Imports by type'!CE929 -> 48 | BK15: ='ONS - UK Imports by type'!CF929+'ONS - UK Imports by type'!CG929+'ONS - UK Imports by type'!CH929 -> 260 | BL15: ='ONS - UK Imports by type'!CI929 -> 21 | BM15: ='ONS - UK Imports by type'!CJ929 -> 222 | BN15: ='ONS - UK Imports by type'!CK929 -> 20 | BO15: ='ONS - UK Imports by type'!CL929+'ONS - UK Imports by type'!CK929+'ONS - UK Imports by type'!CM929 -> 204 | BP15: ='ONS - UK Imports by type'!CO929+'ONS - UK Imports by type'!CP929+'ONS - UK Imports by type'!CQ929 -> 212 | BQ15: ='ONS - UK Imports by type'!CR929 -> 646 | BR15: ='ONS - UK Imports by type'!CS929 -> 198 | BS15: ='ONS - UK Imports by type'!CT929+'ONS - UK Imports by type'!CU929+'ONS - UK Imports by type'!CV929 -> 1668 | BT15: ='ONS - UK Imports by type'!CW929 -> 2492 | BV15: 2026 | BW15: =100*((DataQ!D219/DataQ!D215)-1) -> 1.5938953 | BX15: =100*((DataQ!K219/DataQ!K215)-1) -> 1.5591576 | BY15: 0 | CA15: =100*((DataQ!K219/DataQ!D219)-1) -> -0.037704886 | CC15: 2026 | CD15: =100*((DataQ!E219/DataQ!E215)-1) -> 2.5346924 | CE15: =100*((DataQ!L219/DataQ!L215)-1) -> 2.6753776 | CG15: =100*((DataQ!L219/DataQ!E219)-1) -> 0.15331057 | CI15: 2026 | CJ15: =100*((DataQ!F219/DataQ!F215)-1) -> 2.0454198 | CK15: =100*((DataQ!M219/DataQ!M215)-1) -> 2.0685487 | CM15: =100*((DataQ!M219/DataQ!F219)-1) -> 0.032456299 | CO15: 2026 | CP15: =DataQ!J219 -> 1.287893 | CQ15: =DataQ!Q219 -> 1.26948 | CS15: =100*((DataQ!Q219/DataQ!J219)-1) -> -1.4296995
A16: 2022 | B16: ='ONS - UK Imports by type'!D1165 -> 61892 | C16: ='ONS - UK Imports by type'!E1165 -> 39 | D16: ='ONS - UK Imports by type'!F1165 -> 5 | E16: ='ONS - UK Imports by type'!G1165 -> 14 | F16: ='ONS - UK Imports by type'!H1165 -> 40 | G16: ='ONS - UK Imports by type'!I1165 -> 78 | H16: ='ONS - UK Imports by type'!J1165 -> 279 | I16: ='ONS - UK Imports by type'!K1165 -> 41 | ... AV16: ='ONS - UK Imports by type'!AX1165 -> 919 | AW16: ='ONS - UK Imports by type'!AY1165+'ONS - UK Imports by type'!AZ1165 -> 252 | AX16: ='ONS - UK Imports by type'!BA1165+'ONS - UK Imports by type'!BB1165+'ONS - UK Imports by type'!BC1165 -> 4946 | AY16: ='ONS - UK Imports by type'!BD1165+'ONS - UK Imports by type'!BE1165+'ONS - UK Imports by type'!BF1165 -> 672 | AZ16: ='ONS - UK Imports by type'!BG1165+'ONS - UK Imports by type'!BH1165 -> 122 | BA16: ='ONS - UK Imports by type'!BI1165+'ONS - UK Imports by type'!BJ1165+'ONS - UK Imports by type'!BK1165 -> 2478 | BB16: ='ONS - UK Imports by type'!BL1165+'ONS - UK Imports by type'!BK1165+'ONS - UK Imports by type'!BM1165 -> 1456 | BC16: ='ONS - UK Imports by type'!BO1165+'ONS - UK Imports by type'!BP1165+'ONS - UK Imports by type'!BQ1165 -> 1470 | BD16: ='ONS - UK Imports by type'!BR1165+'ONS - UK Imports by type'!BS1165+'ONS - UK Imports by type'!BT1165 -> 2580 | BE16: ='ONS - UK Imports by type'!BU1165+'ONS - UK Imports by type'!BV1165+'ONS - UK Imports by type'!BW1165 -> 336 | BF16: ='ONS - UK Imports by type'!BX1165 -> 230 | BG16: ='ONS - UK Imports by type'!BY1165+'ONS - UK Imports by type'!BZ1165 -> 18 | BH16: ='ONS - UK Imports by type'!CA1165 -> 2703 | BI16: ='ONS - UK Imports by type'!CB1165 -> 43 | BJ16: ='ONS - UK Imports by type'!CC1165+'ONS - UK Imports by type'!CD1165+'ONS - UK Imports by type'!CE1165 -> 56 | BK16: ='ONS - UK Imports by type'!CF1165+'ONS - UK Imports by type'!CG1165+'ONS - UK Imports by type'!CH1165 -> 248 | BL16: ='ONS - UK Imports by type'!CI1165 -> 31 | BM16: ='ONS - UK Imports by type'!CJ1165 -> 245 | BN16: ='ONS - UK Imports by type'!CK1165 -> 27 | BO16: ='ONS - UK Imports by type'!CL1165+'ONS - UK Imports by type'!CK1165+'ONS - UK Imports by type'!CM1165 -> 279 | BP16: ='ONS - UK Imports by type'!CO1165+'ONS - UK Imports by type'!CP1165+'ONS - UK Imports by type'!CQ1165 -> 206 | BQ16: ='ONS - UK Imports by type'!CR1165 -> 866 | BR16: ='ONS - UK Imports by type'!CS1165 -> 272 | BS16: ='ONS - UK Imports by type'!CT1165+'ONS - UK Imports by type'!CU1165+'ONS - UK Imports by type'!CV1165 -> 1673 | BT16: ='ONS - UK Imports by type'!CW1165 -> 1825 | BW16: =100*((DataQ!D220/DataQ!D216)-1) -> 1.6329545 | BX16: =100*((DataQ!K220/DataQ!K216)-1) -> 1.5737906 | BY16: 0 | CA16: =100*((DataQ!K220/DataQ!D220)-1) -> -0.068923257 | CD16: =100*((DataQ!E220/DataQ!E216)-1) -> 2.4845655 | CE16: =100*((DataQ!L220/DataQ!L216)-1) -> 2.6578029 | CG16: =100*((DataQ!L220/DataQ!E220)-1) -> 0.20151694 | CJ16: =100*((DataQ!F220/DataQ!F216)-1) -> 2.0323243 | CK16: =100*((DataQ!M220/DataQ!M216)-1) -> 2.0537811 | CM16: =100*((DataQ!M220/DataQ!F220)-1) -> 0.028216626 | CP16: =DataQ!J220 -> 1.29213 | CQ16: =DataQ!Q220 -> 1.262606 | CS16: =100*((DataQ!Q220/DataQ!J220)-1) -> -2.2849094 | CX16: =CX4 -> Exports to US - goods currently exempt
A17: 2023 | B17: ='ONS - UK Imports by type'!D1401 -> 57948 | C17: ='ONS - UK Imports by type'!E1401 -> 10 | D17: ='ONS - UK Imports by type'!F1401 -> 4 | E17: ='ONS - UK Imports by type'!G1401 -> 18 | F17: ='ONS - UK Imports by type'!H1401 -> 31 | G17: ='ONS - UK Imports by type'!I1401 -> 67 | H17: ='ONS - UK Imports by type'!J1401 -> 245 | I17: ='ONS - UK Imports by type'!K1401 -> 46 | ... AV17: ='ONS - UK Imports by type'!AX1401 -> 1093 | AW17: ='ONS - UK Imports by type'!AY1401+'ONS - UK Imports by type'!AZ1401 -> 328 | AX17: ='ONS - UK Imports by type'!BA1401+'ONS - UK Imports by type'!BB1401+'ONS - UK Imports by type'!BC1401 -> 5729 | AY17: ='ONS - UK Imports by type'!BD1401+'ONS - UK Imports by type'!BE1401+'ONS - UK Imports by type'!BF1401 -> 676 | AZ17: ='ONS - UK Imports by type'!BG1401+'ONS - UK Imports by type'!BH1401 -> 147 | BA17: ='ONS - UK Imports by type'!BI1401+'ONS - UK Imports by type'!BJ1401+'ONS - UK Imports by type'!BK1401 -> 2629 | BB17: ='ONS - UK Imports by type'!BL1401+'ONS - UK Imports by type'!BK1401+'ONS - UK Imports by type'!BM1401 -> 1415 | BC17: ='ONS - UK Imports by type'!BO1401+'ONS - UK Imports by type'!BP1401+'ONS - UK Imports by type'!BQ1401 -> 1874 | BD17: ='ONS - UK Imports by type'!BR1401+'ONS - UK Imports by type'!BS1401+'ONS - UK Imports by type'!BT1401 -> 2973 | BE17: ='ONS - UK Imports by type'!BU1401+'ONS - UK Imports by type'!BV1401+'ONS - UK Imports by type'!BW1401 -> 307 | BF17: ='ONS - UK Imports by type'!BX1401 -> 821 | BG17: ='ONS - UK Imports by type'!BY1401+'ONS - UK Imports by type'!BZ1401 -> 34 | BH17: ='ONS - UK Imports by type'!CA1401 -> 3118 | BI17: ='ONS - UK Imports by type'!CB1401 -> 125 | BJ17: ='ONS - UK Imports by type'!CC1401+'ONS - UK Imports by type'!CD1401+'ONS - UK Imports by type'!CE1401 -> 57 | BK17: ='ONS - UK Imports by type'!CF1401+'ONS - UK Imports by type'!CG1401+'ONS - UK Imports by type'!CH1401 -> 249 | BL17: ='ONS - UK Imports by type'!CI1401 -> 38 | BM17: ='ONS - UK Imports by type'!CJ1401 -> 228 | BN17: ='ONS - UK Imports by type'!CK1401 -> 26 | BO17: ='ONS - UK Imports by type'!CL1401+'ONS - UK Imports by type'!CK1401+'ONS - UK Imports by type'!CM1401 -> 323 | BP17: ='ONS - UK Imports by type'!CO1401+'ONS - UK Imports by type'!CP1401+'ONS - UK Imports by type'!CQ1401 -> 183 | BQ17: ='ONS - UK Imports by type'!CR1401 -> 526 | BR17: ='ONS - UK Imports by type'!CS1401 -> 199 | BS17: ='ONS - UK Imports by type'!CT1401+'ONS - UK Imports by type'!CU1401+'ONS - UK Imports by type'!CV1401 -> 1426 | BT17: ='ONS - UK Imports by type'!CW1401 -> 244 | BW17: =100*((DataQ!D221/DataQ!D217)-1) -> 1.6810457 | BX17: =100*((DataQ!K221/DataQ!K217)-1) -> 1.588933 | BY17: 0 | CA17: =100*((DataQ!K221/DataQ!D221)-1) -> -0.10622783 | CD17: =100*((DataQ!E221/DataQ!E217)-1) -> 2.4281625 | CE17: =100*((DataQ!L221/DataQ!L217)-1) -> 2.5469914 | CG17: =100*((DataQ!L221/DataQ!E221)-1) -> 0.16245825 | CJ17: =100*((DataQ!F221/DataQ!F217)-1) -> 2.0035156 | CK17: =100*((DataQ!M221/DataQ!M217)-1) -> 1.987743 | CM17: =100*((DataQ!M221/DataQ!F221)-1) -> -0.0076087463 | CP17: =DataQ!J221 -> 1.296342 | CQ17: =DataQ!Q221 -> 1.267093 | CS17: =100*((DataQ!Q221/DataQ!J221)-1) -> -2.2562719 | CX17: Copper | CY17: ='ONS - UK Exports by type'!AW1401 -> 1570
BW18: =100*((DataQ!D222/DataQ!D218)-1) -> 1.7161233 | BX18: =100*((DataQ!K222/DataQ!K218)-1) -> 1.584185 | BY18: 0 | CA18: =100*((DataQ!K222/DataQ!D222)-1) -> -0.14324967 | CD18: =100*((DataQ!E222/DataQ!E218)-1) -> 2.3596112 | CE18: =100*((DataQ!L222/DataQ!L218)-1) -> 2.368352 | CG18: =100*((DataQ!L222/DataQ!E222)-1) -> 0.093217658 | CJ18: =100*((DataQ!F222/DataQ!F218)-1) -> 1.9487513 | CK18: =100*((DataQ!M222/DataQ!M218)-1) -> 1.8591008 | CM18: =100*((DataQ!M222/DataQ!F222)-1) -> -0.059084507 | CP18: =DataQ!J222 -> 1.301524 | CQ18: =DataQ!Q222 -> 1.275095 | CS18: =100*((DataQ!Q222/DataQ!J222)-1) -> -2.0306195 | CX18: Pharma | CY18: ='ONS - UK Exports by type'!AJ1401 -> 8783
BV19: 2027 | BW19: =100*((DataQ!D223/DataQ!D219)-1) -> 1.7314998 | BX19: =100*((DataQ!K223/DataQ!K219)-1) -> 1.5741898 | BY19: 0 | CA19: =100*((DataQ!K223/DataQ!D223)-1) -> -0.19227907 | CC19: 2027 | CD19: =100*((DataQ!E223/DataQ!E219)-1) -> 2.3175004 | CE19: =100*((DataQ!L223/DataQ!L219)-1) -> 2.204695 | CG19: =100*((DataQ!L223/DataQ!E223)-1) -> 0.042891235 | CI19: 2027 | CJ19: =100*((DataQ!F223/DataQ!F219)-1) -> 1.9084025 | CK19: =100*((DataQ!M223/DataQ!M219)-1) -> 1.7557024 | CM19: =100*((DataQ!M223/DataQ!F223)-1) -> -0.11743278 | CO19: 2027 | CP19: =DataQ!J223 -> 1.307673 | CQ19: =DataQ!Q223 -> 1.283775 | CS19: =100*((DataQ!Q223/DataQ!J223)-1) -> -1.8275211 | CX19: Semiconductors | CY19: ='ONS - UK Exports by type'!AY1401+'ONS - UK Exports by type'!AZ1401+'ONS - UK Exports by type'!BR1401+'ONS - UK Exports by type'!BS1401+'ONS - UK Exports by type'!BT1401 -> 2854
C20: =RANK(C22,$C$22:$BT$22) -> 50 | D20: =RANK(D22,$C$22:$BT$22) -> 53 | E20: =RANK(E22,$C$22:$BT$22) -> 44 | F20: =RANK(F22,$C$22:$BT$22) -> 36 | G20: =RANK(G22,$C$22:$BT$22) -> 42 | H20: =RANK(H22,$C$22:$BT$22) -> 54 | I20: =RANK(I22,$C$22:$BT$22) -> 62 | J20: =RANK(J22,$C$22:$BT$22) -> 46 | ... BT20: =RANK(BT22,$C$22:$BT$22) -> 16 | BW20: =100*((DataQ!D224/DataQ!D220)-1) -> 1.7667293 | BX20: =100*((DataQ!K224/DataQ!K220)-1) -> 1.6195156 | BY20: 0 | CA20: =100*((DataQ!K224/DataQ!D224)-1) -> -0.21348151 | CD20: =100*((DataQ!E224/DataQ!E220)-1) -> 2.2369235 | CE20: =100*((DataQ!L224/DataQ!L220)-1) -> 2.0658036 | CG20: =100*((DataQ!L224/DataQ!E224)-1) -> 0.033803846 | CJ20: =100*((DataQ!F224/DataQ!F220)-1) -> 1.8597027 | CK20: =100*((DataQ!M224/DataQ!M220)-1) -> 1.6662104 | CM20: =100*((DataQ!M224/DataQ!F224)-1) -> -0.16179655 | CP20: =DataQ!J224 -> 1.313792 | CQ20: =DataQ!Q224 -> 1.292182 | CS20: =100*((DataQ!Q224/DataQ!J224)-1) -> -1.644857 | CX20: Lumber | CY20: ='ONS - UK Exports by type'!S1401+'ONS - UK Exports by type'!AR1401 -> 24
C21: =C2 -> Live animals | D21: =D2 -> Meat & meat preparations | E21: =E2 -> Dairy products & eggs | F21: =F2 -> Fish and shellfish | G21: =G2 -> Cereals | H21: =H2 -> Vegetables & fruit | I21: =I2 -> Sugar | J21: =J2 -> Coffee, tea, cocoa etc | ... BT21: =BT2 -> Unspecified goods | BW21: =100*((DataQ!D225/DataQ!D221)-1) -> 1.7717328 | BX21: =100*((DataQ!K225/DataQ!K221)-1) -> 1.6590949 | BY21: 0 | CA21: =100*((DataQ!K225/DataQ!D225)-1) -> -0.21678731 | CD21: =100*((DataQ!E225/DataQ!E221)-1) -> 2.1843263 | CE21: =100*((DataQ!L225/DataQ!L221)-1) -> 2.0747058 | CG21: =100*((DataQ!L225/DataQ!E225)-1) -> 0.05500676 | CJ21: =100*((DataQ!F225/DataQ!F221)-1) -> 1.8303877 | CK21: =100*((DataQ!M225/DataQ!M221)-1) -> 1.6347136 | CM21: =100*((DataQ!M225/DataQ!F225)-1) -> -0.19975093 | CP21: =DataQ!J225 -> 1.319877 | CQ21: =DataQ!Q225 -> 1.300337 | CS21: =100*((DataQ!Q225/DataQ!J225)-1) -> -1.480441 | CX21: Aerospace | CY21: ='ONS - UK Exports by type'!CA1401 -> 2117
C22: =C9+C23 -> 41.001 | D22: =D9+D23 -> 33.002 | E22: =E9+E23 -> 99.003 | F22: =F9+F23 -> 245.004 | G22: =G9+G23 -> 137.005 | H22: =H9+H23 -> 30.006 | I22: =I9+I23 -> 10.007 | J22: =J9+J23 -> 56.008 | ... BT22: =BT9+BT23 -> 1206.07 | BW22: =100*((DataQ!D226/DataQ!D222)-1) -> 1.7665855 | BX22: =100*((DataQ!K226/DataQ!K222)-1) -> 1.696639 | BY22: 0 | CA22: =100*((DataQ!K226/DataQ!D226)-1) -> -0.21188345 | CD22: =100*((DataQ!E226/DataQ!E222)-1) -> 2.11392 | CE22: =100*((DataQ!L226/DataQ!L222)-1) -> 2.1155414 | CG22: =100*((DataQ!L226/DataQ!E226)-1) -> 0.09480694 | CJ22: =100*((DataQ!F226/DataQ!F222)-1) -> 1.7827728 | CK22: =100*((DataQ!M226/DataQ!M222)-1) -> 1.5963626 | CM22: =100*((DataQ!M226/DataQ!F226)-1) -> -0.24212147 | CP22: =DataQ!J226 -> 1.325938 | CQ22: =DataQ!Q226 -> 1.308271 | CS22: =100*((DataQ!Q226/DataQ!J226)-1) -> -1.3324152
C23: 0.001 | D23: =C23+0.001 -> 0.002 | E23: =D23+0.001 -> 0.003 | F23: =E23+0.001 -> 0.004 | G23: =F23+0.001 -> 0.005 | H23: =G23+0.001 -> 0.006 | I23: =H23+0.001 -> 0.007 | J23: =I23+0.001 -> 0.008 | K23: =J23+0.001 -> 0.009 | ... BT23: =BS23+0.001 -> 0.07 | BV23: 2028 | BW23: =100*((DataQ!D227/DataQ!D223)-1) -> 1.7461755 | BX23: =100*((DataQ!K227/DataQ!K223)-1) -> 1.7286691 | BY23: 0 | CA23: =100*((DataQ!K227/DataQ!D227)-1) -> -0.2094519 | CC23: 2028 | CD23: =100*((DataQ!E227/DataQ!E223)-1) -> 2.13071 | CE23: =100*((DataQ!L227/DataQ!L223)-1) -> 2.2128714 | CG23: =100*((DataQ!L227/DataQ!E227)-1) -> 0.12337307 | CI23: 2028 | CJ23: =100*((DataQ!F227/DataQ!F223)-1) -> 1.7096294 | CK23: =100*((DataQ!M227/DataQ!M223)-1) -> 1.5294275 | CM23: =100*((DataQ!M227/DataQ!F227)-1) -> -0.29439764 | CO23: 2028 | CP23: =DataQ!J227 -> 1.331969 | CQ23: =DataQ!Q227 -> 1.316001 | CS23: =100*((DataQ!Q227/DataQ!J227)-1) -> -1.1988267 | CX23: Total exports to US | CZ23: ='ONS - UK Exports by type'!D1401 -> 60432
BW24: =100*((DataQ!D228/DataQ!D224)-1) -> 1.7007559 | BX24: =100*((DataQ!K228/DataQ!K224)-1) -> 1.710968 | BY24: 0 | CA24: =100*((DataQ!K228/DataQ!D228)-1) -> -0.20346163 | CD24: =100*((DataQ!E228/DataQ!E224)-1) -> 2.1394698 | CE24: =100*((DataQ!L228/DataQ!L224)-1) -> 2.2644407 | CG24: =100*((DataQ!L228/DataQ!E228)-1) -> 0.15619839 | CJ24: =100*((DataQ!F228/DataQ!F224)-1) -> 1.6509434 | CK24: =100*((DataQ!M228/DataQ!M224)-1) -> 1.455294 | CM24: =100*((DataQ!M228/DataQ!F228)-1) -> -0.35395696 | CP24: =DataQ!J228 -> 1.337969 | CQ24: =DataQ!Q228 -> 1.323535 | CS24: =100*((DataQ!Q228/DataQ!J228)-1) -> -1.0787993
C25: 1 | D25: =+C25+1 -> 2 | E25: =+D25+1 -> 3 | F25: =+E25+1 -> 4 | G25: =+F25+1 -> 5 | H25: =+G25+1 -> 6 | I25: =+H25+1 -> 7 | J25: =+I25+1 -> 8 | K25: =+J25+1 -> 9 | ... BT25: =+BS25+1 -> 70 | BW25: =100*((DataQ!D229/DataQ!D225)-1) -> 1.6754148 | BX25: =100*((DataQ!K229/DataQ!K225)-1) -> 1.6894826 | BY25: 0 | CA25: =100*((DataQ!K229/DataQ!D229)-1) -> -0.20298133 | CD25: =100*((DataQ!E229/DataQ!E225)-1) -> 2.1573332 | CE25: =100*((DataQ!L229/DataQ!L225)-1) -> 2.2963962 | CG25: =100*((DataQ!L229/DataQ!E229)-1) -> 0.19120796 | CJ25: =100*((DataQ!F229/DataQ!F225)-1) -> 1.6013585 | CK25: =100*((DataQ!M229/DataQ!M225)-1) -> 1.3896206 | CM25: =100*((DataQ!M229/DataQ!F229)-1) -> -0.40773538 | CP25: =DataQ!J229 -> 1.343936 | CQ25: =DataQ!Q229 -> 1.330886 | CS25: =100*((DataQ!Q229/DataQ!J229)-1) -> -0.97102838
C26: =HLOOKUP(C$25,$C$20:$BT$22,2,FALSE) -> Medicinal & pharmaceutical products | D26: =HLOOKUP(D$25,$C$20:$BT$22,2,FALSE) -> Cars | E26: =HLOOKUP(E$25,$C$20:$BT$22,2,FALSE) -> Mechanical power generators | F26: =HLOOKUP(F$25,$C$20:$BT$22,2,FALSE) -> General industrial machinery | G26: =HLOOKUP(G$25,$C$20:$BT$22,2,FALSE) -> Organic chemicals | H26: =HLOOKUP(H$25,$C$20:$BT$22,2,FALSE) -> Miscellaneous electrical goods | I26: =HLOOKUP(I$25,$C$20:$BT$22,2,FALSE) -> Specialised machinery | J26: =HLOOKUP(J$25,$C$20:$BT$22,2,FALSE) -> Office machinery | ... BT26: =HLOOKUP(BT$25,$C$20:$BT$22,2,FALSE) -> Hides, skins & furskins | BW26: =100*((DataQ!D230/DataQ!D226)-1) -> 1.6450527 | BX26: =100*((DataQ!K230/DataQ!K226)-1) -> 1.6502045 | BY26: 0 | CA26: =100*((DataQ!K230/DataQ!D230)-1) -> -0.20682571 | CD26: =100*((DataQ!E230/DataQ!E226)-1) -> 2.1554434 | CE26: =100*((DataQ!L230/DataQ!L226)-1) -> 2.2780369 | CG26: =100*((DataQ!L230/DataQ!E230)-1) -> 0.21492753 | CJ26: =100*((DataQ!F230/DataQ!F226)-1) -> 1.5997698 | CK26: =100*((DataQ!M230/DataQ!M226)-1) -> 1.3828723 | CM26: =100*((DataQ!M230/DataQ!F230)-1) -> -0.45508686 | CP26: =DataQ!J230 -> 1.348955 | CQ26: =DataQ!Q230 -> 1.337163 | CS26: =100*((DataQ!Q230/DataQ!J230)-1) -> -0.87415814
B27: 2023 exports | C27: =HLOOKUP(C$25,$C$20:$BT$22,3,FALSE) -> 8783.032 | D27: =HLOOKUP(D$25,$C$20:$BT$22,3,FALSE) -> 6435.056 | E27: =HLOOKUP(E$25,$C$20:$BT$22,3,FALSE) -> 6077.048 | F27: =HLOOKUP(F$25,$C$20:$BT$22,3,FALSE) -> 3842.051 | G27: =HLOOKUP(G$25,$C$20:$BT$22,3,FALSE) -> 2816.029 | H27: =HLOOKUP(H$25,$C$20:$BT$22,3,FALSE) -> 2558.054 | I27: =HLOOKUP(I$25,$C$20:$BT$22,3,FALSE) -> 2495.049 | J27: =HLOOKUP(J$25,$C$20:$BT$22,3,FALSE) -> 2481.052 | ... BT27: =HLOOKUP(BT$25,$C$20:$BT$22,3,FALSE) -> 0.012 | BV27: 2029 | BW27: =100*((DataQ!D231/DataQ!D227)-1) -> 1.6147268 | BX27: =100*((DataQ!K231/DataQ!K227)-1) -> 1.6138388 | BY27: 0 | CA27: =100*((DataQ!K231/DataQ!D231)-1) -> -0.21032396 | CC27: 2029 | CD27: =100*((DataQ!E231/DataQ!E227)-1) -> 2.1118688 | CE27: =100*((DataQ!L231/DataQ!L227)-1) -> 2.2227234 | CG27: =100*((DataQ!L231/DataQ!E231)-1) -> 0.23206893 | CI27: 2029 | CJ27: =100*((DataQ!F231/DataQ!F227)-1) -> 1.5514616 | CK27: =100*((DataQ!M231/DataQ!M227)-1) -> 1.3469722 | CM27: =100*((DataQ!M231/DataQ!F231)-1) -> -0.49517018 | CO27: 2029 | CP27: =DataQ!J231 -> 1.35303 | CQ27: =DataQ!Q231 -> 1.342386 | CS27: =100*((DataQ!Q231/DataQ!J231)-1) -> -0.78667879
BW28: =100*((DataQ!D232/DataQ!D228)-1) -> 1.5892728 | BX28: =100*((DataQ!K232/DataQ!K228)-1) -> 1.5832445 | BY28: 0 | CA28: =100*((DataQ!K232/DataQ!D232)-1) -> -0.20938355 | CD28: =100*((DataQ!E232/DataQ!E228)-1) -> 2.0792333 | CE28: =100*((DataQ!L232/DataQ!L228)-1) -> 2.1685143 | CG28: =100*((DataQ!L232/DataQ!E232)-1) -> 0.24379744 | CJ28: =100*((DataQ!F232/DataQ!F228)-1) -> 1.509038 | CK28: =100*((DataQ!M232/DataQ!M228)-1) -> 1.3276751 | CM28: =100*((DataQ!M232/DataQ!F232)-1) -> -0.53199134 | CP28: =DataQ!J232 -> 1.357076 | CQ28: =DataQ!Q232 -> 1.347472 | CS28: =100*((DataQ!Q232/DataQ!J232)-1) -> -0.70769802
C29: 1 | D29: 2 | E29: 3 | F29: 4 | G29: 5 | H29: 6 | I29: 7 | BW29: =100*((DataQ!D233/DataQ!D229)-1) -> 1.5590613 | BX29: =100*((DataQ!K233/DataQ!K229)-1) -> 1.5526068 | BY29: 0 | CA29: =100*((DataQ!K233/DataQ!D233)-1) -> -0.20932384 | CD29: =100*((DataQ!E233/DataQ!E229)-1) -> 2.0588806 | CE29: =100*((DataQ!L233/DataQ!L229)-1) -> 2.1232646 | CG29: =100*((DataQ!L233/DataQ!E233)-1) -> 0.25441365 | CJ29: =100*((DataQ!F233/DataQ!F229)-1) -> 1.4939749 | CK29: =100*((DataQ!M233/DataQ!M229)-1) -> 1.3387551 | CM29: =100*((DataQ!M233/DataQ!F233)-1) -> -0.56004683 | CP29: =DataQ!J233 -> 1.3611 | CQ29: =DataQ!Q233 -> 1.352431 | CS29: =100*((DataQ!Q233/DataQ!J233)-1) -> -0.63691132
C30: =C26 -> Medicinal & pharmaceutical products | D30: =D26 -> Cars | E30: =E26 -> Mechanical power generators | F30: =F26 -> General industrial machinery | G30: =G26 -> Organic chemicals | H30: =H26 -> Miscellaneous electrical goods | I30: =I26 -> Specialised machinery | J30: Other | BW30: =100*((DataQ!D234/DataQ!D230)-1) -> 1.5388333 | BX30: =100*((DataQ!K234/DataQ!K230)-1) -> 1.5334259 | BY30: 0 | CA30: =100*((DataQ!K234/DataQ!D234)-1) -> -0.21214019 | CD30: =100*((DataQ!E234/DataQ!E230)-1) -> 2.0308018 | CE30: =100*((DataQ!L234/DataQ!L230)-1) -> 2.0833319 | CG30: =100*((DataQ!L234/DataQ!E234)-1) -> 0.26652279 | CJ30: =100*((DataQ!F234/DataQ!F230)-1) -> 1.5115401 | CK30: =100*((DataQ!M234/DataQ!M230)-1) -> 1.3818041 | CM30: =100*((DataQ!M234/DataQ!F234)-1) -> -0.58230943 | CP30: =DataQ!J234 -> 1.364191 | CQ30: =DataQ!Q234 -> 1.356369 | CS30: =100*((DataQ!Q234/DataQ!J234)-1) -> -0.57338012
B31: =B27 -> 2023 exports | C31: =C27 -> 8783.032 | D31: =D27 -> 6435.056 | E31: =E27 -> 6077.048 | F31: =F27 -> 3842.051 | G31: =G27 -> 2816.029 | H31: =H27 -> 2558.054 | I31: =I27 -> 2495.049 | J31: =B17-SUM(C31:I31) -> 24941.681
A34: US exports as share of total | BV34: =20%*30%*10% -> 0.006
A35: 2023 | B35: =B2 -> Total | C35: =C2 -> Live animals | D35: =D2 -> Meat & meat preparations | E35: =E2 -> Dairy products & eggs | F35: =F2 -> Fish and shellfish | G35: =G2 -> Cereals | H35: =H2 -> Vegetables & fruit | I35: =I2 -> Sugar | ... BT35: =BT2 -> Unspecified goods
A36: Exports to US | B36: ='ONS - UK Exports by type'!D1401 -> 60432 | C36: ='ONS - UK Exports by type'!E1401 -> 41 | D36: ='ONS - UK Exports by type'!F1401 -> 33 | E36: ='ONS - UK Exports by type'!G1401 -> 99 | F36: ='ONS - UK Exports by type'!H1401 -> 245 | G36: ='ONS - UK Exports by type'!I1401 -> 137 | H36: ='ONS - UK Exports by type'!J1401 -> 30 | I36: ='ONS - UK Exports by type'!K1401 -> 10 | ... AV36: ='ONS - UK Exports by type'!AX1401 -> 931 | AW36: ='ONS - UK Exports by type'!AY1401+'ONS - UK Exports by type'!AZ1401 -> 296 | AX36: ='ONS - UK Exports by type'!BA1401+'ONS - UK Exports by type'!BB1401+'ONS - UK Exports by type'!BC1401 -> 6077 | AY36: ='ONS - UK Exports by type'!BD1401+'ONS - UK Exports by type'!BE1401+'ONS - UK Exports by type'!BF1401 -> 2495 | AZ36: ='ONS - UK Exports by type'!BG1401+'ONS - UK Exports by type'!BH1401 -> 203 | BA36: ='ONS - UK Exports by type'!BI1401+'ONS - UK Exports by type'!BJ1401+'ONS - UK Exports by type'!BK1401 -> 3842 | BB36: ='ONS - UK Exports by type'!BL1401+'ONS - UK Exports by type'!BK1401+'ONS - UK Exports by type'!BM1401 -> 2481 | BC36: ='ONS - UK Exports by type'!BO1401+'ONS - UK Exports by type'!BP1401+'ONS - UK Exports by type'!BQ1401 -> 968 | BD36: ='ONS - UK Exports by type'!BR1401+'ONS - UK Exports by type'!BS1401+'ONS - UK Exports by type'!BT1401 -> 2558 | BE36: ='ONS - UK Exports by type'!BU1401+'ONS - UK Exports by type'!BV1401+'ONS - UK Exports by type'!BW1401 -> 1333 | BF36: ='ONS - UK Exports by type'!BX1401 -> 6435 | BG36: ='ONS - UK Exports by type'!BY1401+'ONS - UK Exports by type'!BZ1401 -> 7 | BH36: ='ONS - UK Exports by type'!CA1401 -> 2117 | BI36: ='ONS - UK Exports by type'!CB1401 -> 290 | BJ36: ='ONS - UK Exports by type'!CC1401+'ONS - UK Exports by type'!CD1401+'ONS - UK Exports by type'!CE1401 -> 109 | BK36: ='ONS - UK Exports by type'!CF1401+'ONS - UK Exports by type'!CG1401+'ONS - UK Exports by type'!CH1401 -> 531 | BL36: ='ONS - UK Exports by type'!CI1401 -> 56 | BM36: ='ONS - UK Exports by type'!CJ1401 -> 409 | BN36: ='ONS - UK Exports by type'!CK1401 -> 54 | BO36: ='ONS - UK Exports by type'!CL1401+'ONS - UK Exports by type'!CK1401+'ONS - UK Exports by type'!CM1401 -> 396 | BP36: ='ONS - UK Exports by type'!CO1401+'ONS - UK Exports by type'!CP1401+'ONS - UK Exports by type'!CQ1401 -> 336 | BQ36: ='ONS - UK Exports by type'!CR1401 -> 1482 | BR36: ='ONS - UK Exports by type'!CS1401 -> 277 | BS36: ='ONS - UK Exports by type'!CT1401+'ONS - UK Exports by type'!CU1401+'ONS - UK Exports by type'!CV1401 -> 2012 | BT36: ='ONS - UK Exports by type'!CW1401 -> 1206
A37: Exports to world | B37: ='ONS - UK Exports by type'!D1423 -> 393516 | C37: ='ONS - UK Exports by type'!E1423 -> 618 | D37: ='ONS - UK Exports by type'!F1423 -> 2065 | E37: ='ONS - UK Exports by type'!G1423 -> 2154 | F37: ='ONS - UK Exports by type'!H1423 -> 1806 | G37: ='ONS - UK Exports by type'!I1423 -> 2954 | H37: ='ONS - UK Exports by type'!J1423 -> 1047 | I37: ='ONS - UK Exports by type'!K1423 -> 604 | ... AV37: ='ONS - UK Exports by type'!AX1423 -> 7949 | AW37: ='ONS - UK Exports by type'!AY1423+'ONS - UK Exports by type'!AZ1423 -> 1755 | AX37: ='ONS - UK Exports by type'!BA1423+'ONS - UK Exports by type'!BB1423+'ONS - UK Exports by type'!BC1423 -> 37252 | AY37: ='ONS - UK Exports by type'!BD1423+'ONS - UK Exports by type'!BE1423+'ONS - UK Exports by type'!BF1423 -> 11255 | AZ37: ='ONS - UK Exports by type'!BG1423+'ONS - UK Exports by type'!BH1423 -> 1152 | BA37: ='ONS - UK Exports by type'!BI1423+'ONS - UK Exports by type'!BJ1423+'ONS - UK Exports by type'!BK1423 -> 19259 | BB37: ='ONS - UK Exports by type'!BL1423+'ONS - UK Exports by type'!BK1423+'ONS - UK Exports by type'!BM1423 -> 11596 | BC37: ='ONS - UK Exports by type'!BO1423+'ONS - UK Exports by type'!BP1423+'ONS - UK Exports by type'!BQ1423 -> 7453 | BD37: ='ONS - UK Exports by type'!BR1423+'ONS - UK Exports by type'!BS1423+'ONS - UK Exports by type'!BT1423 -> 16119 | BE37: ='ONS - UK Exports by type'!BU1423+'ONS - UK Exports by type'!BV1423+'ONS - UK Exports by type'!BW1423 -> 9468 | BF37: ='ONS - UK Exports by type'!BX1423 -> 34810 | BG37: ='ONS - UK Exports by type'!BY1423+'ONS - UK Exports by type'!BZ1423 -> 454 | BH37: ='ONS - UK Exports by type'!CA1423 -> 11779 | BI37: ='ONS - UK Exports by type'!CB1423 -> 3500 | BJ37: ='ONS - UK Exports by type'!CC1423+'ONS - UK Exports by type'!CD1423+'ONS - UK Exports by type'!CE1423 -> 959 | BK37: ='ONS - UK Exports by type'!CF1423+'ONS - UK Exports by type'!CG1423+'ONS - UK Exports by type'!CH1423 -> 2442 | BL37: ='ONS - UK Exports by type'!CI1423 -> 743 | BM37: ='ONS - UK Exports by type'!CJ1423 -> 3762 | BN37: ='ONS - UK Exports by type'!CK1423 -> 777 | BO37: ='ONS - UK Exports by type'!CL1423+'ONS - UK Exports by type'!CK1423+'ONS - UK Exports by type'!CM1423 -> 2797 | BP37: ='ONS - UK Exports by type'!CO1423+'ONS - UK Exports by type'!CP1423+'ONS - UK Exports by type'!CQ1423 -> 1925 | BQ37: ='ONS - UK Exports by type'!CR1423 -> 4109 | BR37: ='ONS - UK Exports by type'!CS1423 -> 2792 | BS37: ='ONS - UK Exports by type'!CT1423+'ONS - UK Exports by type'!CU1423+'ONS - UK Exports by type'!CV1423 -> 11290 | BT37: ='ONS - UK Exports by type'!CW1423 -> 19879
B38: =100*(B36/B37) -> 15.356936 | C38: =100*(C36/C37) -> 6.6343042 | D38: =100*(D36/D37) -> 1.598063 | E38: =100*(E36/E37) -> 4.5961003 | F38: =100*(F36/F37) -> 13.565891 | G38: =100*(G36/G37) -> 4.6377793 | H38: =100*(H36/H37) -> 2.8653295 | I38: =100*(I36/I37) -> 1.6556291 | ... BT38: =100*(BT36/BT37) -> 6.0667036
C40: =RANK(C38,$C$38:$BT$38) -> 47 | D40: =RANK(D38,$C$38:$BT$38) -> 63 | E40: =RANK(E38,$C$38:$BT$38) -> 52 | F40: =RANK(F38,$C$38:$BT$38) -> 24 | G40: =RANK(G38,$C$38:$BT$38) -> 51 | H40: =RANK(H38,$C$38:$BT$38) -> 57 | I40: =RANK(I38,$C$38:$BT$38) -> 61 | J40: =RANK(J38,$C$38:$BT$38) -> 59 | ... BT40: =RANK(BT38,$C$38:$BT$38) -> 48
C41: =C35 -> Live animals | D41: =D35 -> Meat & meat preparations | E41: =E35 -> Dairy products & eggs | F41: =F35 -> Fish and shellfish | G41: =G35 -> Cereals | H41: =H35 -> Vegetables & fruit | I41: =I35 -> Sugar | J41: =J35 -> Coffee, tea, cocoa etc | ... BT41: =BT35 -> Unspecified goods
C42: =C38 -> 6.6343042 | D42: =D38 -> 1.598063 | E42: =E38 -> 4.5961003 | F42: =F38 -> 13.565891 | G42: =G38 -> 4.6377793 | H42: =H38 -> 2.8653295 | I42: =I38 -> 1.6556291 | J42: =J38 -> 2.6477541 | ... BT42: =BT38 -> 6.0667036
C44: 1 | D44: =+C44+1 -> 2 | E44: =+D44+1 -> 3 | F44: =+E44+1 -> 4 | G44: =+F44+1 -> 5 | H44: =+G44+1 -> 6 | I44: =+H44+1 -> 7 | J44: =+I44+1 -> 8 | K44: =+J44+1 -> 9 | ... BT44: =+BS44+1 -> 70
C45: =HLOOKUP(C$44,$C$40:$BT$42,2,FALSE) -> Works of art | D45: =HLOOKUP(D$44,$C$40:$BT$42,2,FALSE) -> Medicinal & pharmaceutical products | E45: =HLOOKUP(E$44,$C$40:$BT$42,2,FALSE) -> Organic chemicals | F45: =HLOOKUP(F$44,$C$40:$BT$42,2,FALSE) -> Animal oils & fats | G45: =HLOOKUP(G$44,$C$40:$BT$42,2,FALSE) -> Specialised machinery | H45: =HLOOKUP(H$44,$C$40:$BT$42,2,FALSE) -> Inorganic chemicals | I45: =HLOOKUP(I$44,$C$40:$BT$42,2,FALSE) -> Furniture | J45: =HLOOKUP(J$44,$C$40:$BT$42,2,FALSE) -> Office machinery | ... BT45: =HLOOKUP(BT$44,$C$40:$BT$42,2,FALSE) -> #N/A
B46: Share of exports to US | C46: =HLOOKUP(C$44,$C$40:$BT$42,3,FALSE) -> 36.06717 | D46: =HLOOKUP(D$44,$C$40:$BT$42,3,FALSE) -> 33.856295 | E46: =HLOOKUP(E$44,$C$40:$BT$42,3,FALSE) -> 27.958697 | F46: =HLOOKUP(F$44,$C$40:$BT$42,3,FALSE) -> 26.190476 | G46: =HLOOKUP(G$44,$C$40:$BT$42,3,FALSE) -> 22.167925 | H46: =HLOOKUP(H$44,$C$40:$BT$42,3,FALSE) -> 21.914967 | I46: =HLOOKUP(I$44,$C$40:$BT$42,3,FALSE) -> 21.744472 | J46: =HLOOKUP(J$44,$C$40:$BT$42,3,FALSE) -> 21.395309 | ... BT46: =HLOOKUP(BT$44,$C$40:$BT$42,3,FALSE) -> #N/A
B47: UK export share | C47: =IF(AND($D51<=C49,C$49<=$D52),C$46,"") | D47: =IF(AND($D51<=D49,D$49<=$D52),D$46,"") -> 33.856295 | E47: =IF(AND($D51<=E49,E$49<=$D52),E$46,"") | F47: =IF(AND($D51<=F49,F$49<=$D52),F$46,"") | G47: =IF(AND($D51<=G49,G$49<=$D52),G$46,"") | H47: =IF(AND($D51<=H49,H$49<=$D52),H$46,"") | I47: =IF(AND($D51<=I49,I$49<=$D52),I$46,"") | J47: =IF(AND($D51<=J49,J$49<=$D52),J$46,"") | ... BT47: =IF(AND($D51<=BT49,BT$49<=$D52),BT$46,"") -> #N/A
B48: UK export share | C48: =IF(C47="",C46,"") -> 36.06717 | D48: =IF(D47="",D46,"") | E48: =IF(E47="",E46,"") -> 27.958697 | F48: =IF(F47="",F46,"") -> 26.190476 | G48: =IF(G47="",G46,"") -> 22.167925 | H48: =IF(H47="",H46,"") -> 21.914967 | I48: =IF(I47="",I46,"") -> 21.744472 | J48: =IF(J47="",J46,"") -> 21.395309 | ... BT48: =IF(BT47="",BT46,"") -> #N/A
B49: UK export share | C49: =HLOOKUP(C45,$C$55:$BT$57,3,FALSE) -> 1.0441761 | D49: =HLOOKUP(D45,$C$55:$BT$57,3,FALSE) -> 6.5923622 | E49: =HLOOKUP(E45,$C$55:$BT$57,3,FALSE) -> 2.5594893 | F49: =HLOOKUP(F45,$C$55:$BT$57,3,FALSE) -> 0.032019028 | G49: =HLOOKUP(G45,$C$55:$BT$57,3,FALSE) -> 2.8601124 | H49: =HLOOKUP(H45,$C$55:$BT$57,3,FALSE) -> 0.73516706 | I49: =HLOOKUP(I45,$C$55:$BT$57,3,FALSE) -> 0.62055927 | J49: =HLOOKUP(J45,$C$55:$BT$57,3,FALSE) -> 2.9467671 | ... BT49: =HLOOKUP(BT45,$C$55:$BT$57,3,FALSE) -> #N/A
B51: Min | C51: 0 | D51: 5.01
B52: Max | C52: 5 | D52: 100
B54: Calcuate UK export share
C55: =C2 -> Live animals | D55: =D2 -> Meat & meat preparations | E55: =E2 -> Dairy products & eggs | F55: =F2 -> Fish and shellfish | G55: =G2 -> Cereals | H55: =H2 -> Vegetables & fruit | I55: =I2 -> Sugar | J55: =J2 -> Coffee, tea, cocoa etc | ... BT55: =BT2 -> Unspecified goods
B56: UK exports in 2023 | C56: ='ONS - UK Exports by type'!E1423 -> 618 | D56: ='ONS - UK Exports by type'!F1423 -> 2065 | E56: ='ONS - UK Exports by type'!G1423 -> 2154 | F56: ='ONS - UK Exports by type'!H1423 -> 1806 | G56: ='ONS - UK Exports by type'!I1423 -> 2954 | H56: ='ONS - UK Exports by type'!J1423 -> 1047 | I56: ='ONS - UK Exports by type'!K1423 -> 604 | J56: ='ONS - UK Exports by type'!L1423 -> 2115 | ... AV56: ='ONS - UK Exports by type'!AX1423 -> 7949 | AW56: ='ONS - UK Exports by type'!AY1423+'ONS - UK Exports by type'!AZ1423 -> 1755 | AX56: ='ONS - UK Exports by type'!BA1423+'ONS - UK Exports by type'!BB1423+'ONS - UK Exports by type'!BC1423 -> 37252 | AY56: ='ONS - UK Exports by type'!BD1423+'ONS - UK Exports by type'!BE1423+'ONS - UK Exports by type'!BF1423 -> 11255 | AZ56: ='ONS - UK Exports by type'!BG1423+'ONS - UK Exports by type'!BH1423 -> 1152 | BA56: ='ONS - UK Exports by type'!BI1423+'ONS - UK Exports by type'!BJ1423+'ONS - UK Exports by type'!BK1423 -> 19259 | BB56: ='ONS - UK Exports by type'!BL1423+'ONS - UK Exports by type'!BK1423+'ONS - UK Exports by type'!BM1423 -> 11596 | BC56: ='ONS - UK Exports by type'!BO1423+'ONS - UK Exports by type'!BP1423+'ONS - UK Exports by type'!BQ1423 -> 7453 | BD56: ='ONS - UK Exports by type'!BR1423+'ONS - UK Exports by type'!BS1423+'ONS - UK Exports by type'!BT1423 -> 16119 | BE56: ='ONS - UK Exports by type'!BU1423+'ONS - UK Exports by type'!BV1423+'ONS - UK Exports by type'!BW1423 -> 9468 | BF56: ='ONS - UK Exports by type'!BX1423 -> 34810 | BG56: ='ONS - UK Exports by type'!BY1423+'ONS - UK Exports by type'!BZ1423 -> 454 | BH56: ='ONS - UK Exports by type'!CA1423 -> 11779 | BI56: ='ONS - UK Exports by type'!CB1423 -> 3500 | BJ56: ='ONS - UK Exports by type'!CC1423+'ONS - UK Exports by type'!CD1423+'ONS - UK Exports by type'!CE1423 -> 959 | BK56: ='ONS - UK Exports by type'!CF1423+'ONS - UK Exports by type'!CG1423+'ONS - UK Exports by type'!CH1423 -> 2442 | BL56: ='ONS - UK Exports by type'!CI1423 -> 743 | BM56: ='ONS - UK Exports by type'!CJ1423 -> 3762 | BN56: ='ONS - UK Exports by type'!CK1423 -> 777 | BO56: ='ONS - UK Exports by type'!CL1423+'ONS - UK Exports by type'!CK1423+'ONS - UK Exports by type'!CM1423 -> 2797 | BP56: ='ONS - UK Exports by type'!CO1423+'ONS - UK Exports by type'!CP1423+'ONS - UK Exports by type'!CQ1423 -> 1925 | BQ56: ='ONS - UK Exports by type'!CR1423 -> 4109 | BR56: ='ONS - UK Exports by type'!CS1423 -> 2792 | BS56: ='ONS - UK Exports by type'!CT1423+'ONS - UK Exports by type'!CU1423+'ONS - UK Exports by type'!CV1423 -> 11290 | BT56: ='ONS - UK Exports by type'!CW1423 -> 19879
B57: Share of UK exports | C57: =100*(C56/'ONS - UK Exports by type'!$D$1423) -> 0.15704571 | D57: =100*(D56/'ONS - UK Exports by type'!$D$1423) -> 0.5247563 | E57: =100*(E56/'ONS - UK Exports by type'!$D$1423) -> 0.54737291 | F57: =100*(F56/'ONS - UK Exports by type'!$D$1423) -> 0.45893941 | G57: =100*(G56/'ONS - UK Exports by type'!$D$1423) -> 0.75066833 | H57: =100*(H56/'ONS - UK Exports by type'!$D$1423) -> 0.26606288 | I57: =100*(I56/'ONS - UK Exports by type'!$D$1423) -> 0.15348804 | J57: =100*(J56/'ONS - UK Exports by type'!$D$1423) -> 0.53746226 | ... BT57: =100*(BT56/'ONS - UK Exports by type'!$D$1423) -> 5.051637
A59: 2023
A60: Imports from US | B60: ='ONS - UK Imports by type'!D1401 -> 57948
A61: Imports from world | B61: ='ONS - UK Imports by type'!D1423 -> 581193
B62: =100*(B60/B61) -> 9.9705261

Sheet ONS - UK Exports by type
A1: CountryName | B1: CountryId | C1: Year | D1: Total | E1: Live animals | F1: Meat & meat preparations | G1: Dairy products & eggs | H1: Fish and shellfish | I1: Cereals | J1: Vegetables & fruit | K1: Sugar | L1: Coffee, tea, cocoa etc | M1: Animal feeding stuffs | N1: Miscellaneous foods | O1: Beverages & tobacco | P1: Hides, skins & furskins | Q1: Oil-seeds & oleaginous fruits | R1: Crude rubber | S1: Wood & cork | T1: Pulp & waste paper | U1: Textile fibres | V1: Crude minerals & fertilisers | W1: Metal ores & scrap | X1: Other crude animal & vegetable materials | Y1: Coal, coke & briquettes | Z1: Crude oil | AA1: Refined oil | AB1: Gas | AC1: Electricity | AD1: Animal oils & fats | AE1: Vegetable oils & fats | AF1: Processed oils & fats | AG1: Organic chemicals | AH1: Inorganic chemicals | AI1: Dyeing, tanning & colouring materials | AJ1: Medicinal & pharmaceutical products | AK1: Toilet & cleansing preparations | AL1: Processed fertilisers | AM1: Plastics in primary forms | AN1: Plastics in non-primary forms | AO1: Other chemicals | AP1: Leather manufactures | AQ1: Rubber manufactures | AR1: Wood & cork manufactures | AS1: Paper & paperboard | AT1: Textile fabrics | AU1: Mineral manufactures | AV1: Iron & steel | AW1: Non-ferrous metals | AX1: Miscellaneous metal manufactures | AY1: Electric motors (intermediate) | AZ1: Electric motors (capital) | BA1: Mechanical power generators (consumer) | BB1: Mechanical power generators (intermediate) | BC1: Mechanical power generators (capital) | BD1: Specialised machinery (consumer) | BE1: Specialised machinery (intermediate) | BF1: Specialised machinery (capital) | BG1: Metal working machinery (intermediate) | BH1: Metal working machinery (capital) | BI1: General industrial machinery (consumer) | BJ1: General industrial machinery (intermediate) | BK1: General industrial machinery (capital) | BL1: Office machinery (consumer) | BM1: Office machinery (intermediate) | BN1: Office machinery (capital) | BO1: Telecoms & sound equipment (consumer) | BP1: Telecoms & sound equipment (intermediate) | BQ1: Telecoms & sound equipment (capital) | BR1: Miscellaneous electrical goods (consumer) | BS1: Miscellaneous electrical goods (intermediate) | BT1: Miscellaneous electrical goods (capital) | BU1: Road vehicles other than cars (consumer) | BV1: Road vehicles other than cars (intermediate) | BW1: Road vehicles other than cars (capital) | BX1: Cars | BY1: Railway equipment (intermediate) | BZ1: Railway equipment (capital) | CA1: Aircraft | CB1: Ships | CC1: Plumbing, heating & lighting fixtures (consumer) | CD1: Plumbing, heating & lighting fixtures (intermediate) | CE1: Plumbing, heating & lighting fixtures (capital) | CF1: Furniture (consumer) | CG1: Furniture (intermediate) | CH1: Furniture (capital) | CI1: Travel goods, handbags etc | CJ1: Clothing | CK1: Footwear | CL1: Scientific instruments (consumer) | CM1: Scientific instruments (intermediate) | CN1: Scientific instruments (capital) | CO1: Photographic & optical goods & clocks (consumer) | CP1: Photographic & optical goods & clocks (intermediate) | CQ1: Photographic & optical goods & clocks (capital) | CR1: Works of art | CS1: Jewellery | CT1: Other manufactures (intermediate) | CU1: Other manufactures (capital) | CV1: Other manufactures (consumer) | CW1: Unspecified goods | CX1: Unspecified goods
A2: Andorra | B2: AD | C2: 2018 | D2: 9 | E2: 0 | F2: 0 | G2: 0 | H2: 0 | I2: 0 | J2: 0 | K2: 0 | L2: 0 | M2: 0 | N2: 0 | O2: 6 | P2: 0 | Q2: 0 | R2: 0 | S2: 0 | T2: 0 | U2: 0 | V2: 0 | W2: 0 | X2: 0 | Y2: 0 | Z2: 0 | AA2: 0 | AB2: 0 | AC2: 0 | AD2: 0 | AE2: 0 | AF2: 0 | AG2: 0 | AH2: 0 | AI2: 0 | AJ2: 0 | AK2: 0 | AL2: 0 | AM2: 0 | AN2: 0 | AO2: 0 | AP2: 0 | AQ2: 0 | AR2: 0 | AS2: 0 | AT2: 0 | AU2: 0 | AV2: 0 | AW2: 0 | AX2: 0 | AY2: 0 | AZ2: 0 | BA2: 0 | BB2: 0 | BC2: 0 | BD2: 0 | BE2: 0 | BF2: 0 | BG2: 0 | BH2: 0 | BI2: 0 | BJ2: 0 | BK2: 0 | BL2: 0 | BM2: 0 | BN2: 0 | BO2: 0 | BP2: 0 | BQ2: 0 | BR2: 0 | BS2: 0 | BT2: 0 | BU2: 0 | BV2: 0 | BW2: 0 | BX2: 0 | BY2: 0 | BZ2: 0 | CA2: 0 | CB2: 0 | CC2: 0 | CD2: 0 | CE2: 0 | CF2: 0 | CG2: 0 | CH2: 0 | CI2: 0 | CJ2: 0 | CK2: 0 | CL2: 0 | CM2: 0 | CN2: 0 | CO2: 0 | CP2: 0 | CQ2: 0 | CR2: 1 | CS2: 0 | CT2: 0 | CU2: 0 | CV2: 0 | CW2: 0 | CX2: 0
A3: United Arab Emirates | B3: AE | C3: 2018 | D3: 6458 | E3: 16 | F3: 1 | G3: 21 | H3: 8 | I3: 57 | J3: 26 | K3: 8 | L3: 33 | M3: 8 | N3: 39 | O3: 187 | P3: 0 | Q3: 1 | R3: 1 | S3: 2 | T3: 0 | U3: 21 | V3: 5 | W3: 4 | X3: 1 | Y3: 0 | Z3: 0 | AA3: 6 | AB3: 0 | AC3: 0 | AD3: 0 | AE3: 1 | AF3: 0 | AG3: 19 | AH3: 2 | AI3: 36 | AJ3: 180 | AK3: 127 | AL3: 0 | AM3: 14 | AN3: 28 | AO3: 41 | AP3: 4 | AQ3: 26 | AR3: 4 | AS3: 75 | AT3: 29 | AU3: 36 | AV3: 51 | AW3: 66 | AX3: 86 | AY3: 25 | AZ3: 75 | BA3: 0 | BB3: 2267 | BC3: 53 | BD3: 0 | BE3: 35 | BF3: 47 | BG3: 4 | BH3: 4 | BI3: 5 | BJ3: 167 | BK3: 123 | BL3: 0 | BM3: 7 | BN3: 84 | BO3: 2 | BP3: 20 | BQ3: 163 | BR3: 9 | BS3: 170 | BT3: 69 | BU3: 1 | BV3: 34 | BW3: 6 | BX3: 617 | BY3: 1 | BZ3: 0 | CA3: 148 | CB3: 28 | CC3: 1 | CD3: 31 | CE3: 1 | CF3: 19 | CG3: 17 | CH3: 14 | CI3: 10 | CJ3: 81 | CK3: 10 | CL3: 0 | CM3: 44 | CN3: 194 | CO3: 28 | CP3: 5 | CQ3: 0 | CR3: 95 | CS3: 90 | CT3: 25 | CU3: 9 | CV3: 233 | CW3: 121 | CX3: 121
A4: Afghanistan | B4: AF | C4: 2018 | D4: 111 | E4: 0 | F4: 0 | G4: 0 | H4: 0 | I4: 0 | J4: 0 | K4: 0 | L4: 0 | M4: 0 | N4: 0 | O4: 79 | P4: 0 | Q4: 0 | R4: 0 | S4: 0 | T4: 0 | U4: 0 | V4: 0 | W4: 0 | X4: 0 | Y4: 0 | Z4: 0 | AA4: 0 | AB4: 0 | AC4: 0 | AD4: 0 | AE4: 0 | AF4: 0 | AG4: 0 | AH4: 0 | AI4: 0 | AJ4: 0 | AK4: 0 | AL4: 0 | AM4: 0 | AN4: 0 | AO4: 0 | AP4: 0 | AQ4: 1 | AR4: 0 | AS4: 0 | AT4: 0 | AU4: 0 | AV4: 0 | AW4: 0 | AX4: 0 | AY4: 0 | AZ4: 3 | BA4: 0 | BB4: 1 | BC4: 0 | BD4: 0 | BE4: 0 | BF4: 2 | BG4: 0 | BH4: 0 | BI4: 0 | BJ4: 0 | BK4: 1 | BL4: 0 | BM4: 0 | BN4: 0 | BO4: 0 | BP4: 0 | BQ4: 8 | BR4: 0 | BS4: 0 | BT4: 0 | BU4: 0 | BV4: 0 | BW4: 0 | BX4: 5 | BY4: 0 | BZ4: 0 | CA4: 2 | CB4: 0 | CC4: 0 | CD4: 0 | CE4: 0 | CF4: 0 | CG4: 0 | CH4: 0 | CI4: 0 | CJ4: 0 | CK4: 0 | CL4: 0 | CM4: 0 | CN4: 2 | CO4: 0 | CP4: 0 | CQ4: 0 | CR4: 0 | CS4: 0 | CT4: 0 | CU4: 0 | CV4: 0 | CW4: 0 | CX4: 0
A5: Antigua & Barbuda | B5: AG | C5: 2018 | D5: 18 | E5: 0 | F5: 0 | G5: 1 | H5: 0 | I5: 0 | J5: 0 | K5: 0 | L5: 0 | M5: 0 | N5: 1 | O5: 2 | P5: 0 | Q5: 0 | R5: 0 | S5: 0 | T5: 0 | U5: 0 | V5: 0 | W5: 0 | X5: 0 | Y5: 0 | Z5: 0 | AA5: 0 | AB5: 0 | AC5: 0 | AD5: 0 | AE5: 0 | AF5: 0 | AG5: 0 | AH5: 0 | AI5: 0 | AJ5: 1 | AK5: 0 | AL5: 0 | AM5: 0 | AN5: 0 | AO5: 0 | AP5: 0 | AQ5: 0 | AR5: 0 | AS5: 0 | AT5: 1 | AU5: 1 | AV5: 0 | AW5: 0 | AX5: 1 | AY5: 0 | AZ5: 0 | BA5: 0 | BB5: 0 | BC5: 0 | BD5: 0 | BE5: 0 | BF5: 0 | BG5: 0 | BH5: 0 | BI5: 0 | BJ5: 0 | BK5: 0 | BL5: 0 | BM5: 0 | BN5: 0 | BO5: 0 | BP5: 0 | BQ5: 0 | BR5: 0 | BS5: 0 | BT5: 0 | BU5: 0 | BV5: 0 | BW5: 0 | BX5: 0 | BY5: 0 | BZ5: 0 | CA5: 0 | CB5: 3 | CC5: 0 | CD5: 0 | CE5: 0 | CF5: 1 | CG5: 0 | CH5: 0 | CI5: 0 | CJ5: 0 | CK5: 0 | CL5: 0 | CM5: 0 | CN5: 0 | CO5: 0 | CP5: 0 | CQ5: 0 | CR5: 0 | CS5: 0 | CT5: 0 | CU5: 0 | CV5: 1 | CW5: 0 | CX5: 0
A6: Anguilla | B6: AI | C6: 2018 | D6: 0 | E6: 0 | F6: 0 | G6: 0 | H6: 0 | I6: 0 | J6: 0 | K6: 0 | L6: 0 | M6: 0 | N6: 0 | O6: 0 | P6: 0 | Q6: 0 | R6: 0 | S6: 0 | T6: 0 | U6: 0 | V6: 0 | W6: 0 | X6: 0 | Y6: 0 | Z6: 0 | AA6: 0 | AB6: 0 | AC6: 0 | AD6: 0 | AE6: 0 | AF6: 0 | AG6: 0 | AH6: 0 | AI6: 0 | AJ6: 0 | AK6: 0 | AL6: 0 | AM6: 0 | AN6: 0 | AO6: 0 | AP6: 0 | AQ6: 0 | AR6: 0 | AS6: 0 | AT6: 0 | AU6: 0 | AV6: 0 | AW6: 0 | AX6: 0 | AY6: 0 | AZ6: 0 | BA6: 0 | BB6: 0 | BC6: 0 | BD6: 0 | BE6: 0 | BF6: 0 | BG6: 0 | BH6: 0 | BI6: 0 | BJ6: 0 | BK6: 0 | BL6: 0 | BM6: 0 | BN6: 0 | BO6: 0 | BP6: 0 | BQ6: 0 | BR6: 0 | BS6: 0 | BT6: 0 | BU6: 0 | BV6: 0 | BW6: 0 | BX6: 0 | BY6: 0 | BZ6: 0 | CA6: 0 | CB6: 0 | CC6: 0 | CD6: 0 | CE6: 0 | CF6: 0 | CG6: 0 | CH6: 0 | CI6: 0 | CJ6: 0 | CK6: 0 | CL6: 0 | CM6: 0 | CN6: 0 | CO6: 0 | CP6: 0 | CQ6: 0 | CR6: 0 | CS6: 0 | CT6: 0 | CU6: 0 | CV6: 0 | CW6: 0 | CX6: 0
A7: Albania | B7: AL | C7: 2018 | D7: 18 | E7: 0 | F7: 1 | G7: 0 | H7: 0 | I7: 0 | J7: 0 | K7: 0 | L7: 0 | M7: 0 | N7: 0 | O7: 1 | P7: 0 | Q7: 0 | R7: 0 | S7: 0 | T7: 0 | U7: 0 | V7: 0 | W7: 0 | X7: 0 | Y7: 0 | Z7: 0 | AA7: 0 | AB7: 0 | AC7: 0 | AD7: 0 | AE7: 0 | AF7: 0 | AG7: 0 | AH7: 0 | AI7: 1 | AJ7: 1 | AK7: 1 | AL7: 0 | AM7: 0 | AN7: 0 | AO7: 0 | AP7: 0 | AQ7: 0 | AR7: 0 | AS7: 0 | AT7: 0 | AU7: 1 | AV7: 0 | AW7: 0 | AX7: 1 | AY7: 0 | AZ7: 0 | BA7: 0 | BB7: 0 | BC7: 0 | BD7: 0 | BE7: 0 | BF7: 0 | BG7: 0 | BH7: 0 | BI7: 0 | BJ7: 0 | BK7: 3 | BL7: 0 | BM7: 0 | BN7: 0 | BO7: 0 | BP7: 0 | BQ7: 0 | BR7: 0 | BS7: 1 | BT7: 0 | BU7: 0 | BV7: 1 | BW7: 0 | BX7: 0 | BY7: 0 | BZ7: 0 | CA7: 0 | CB7: 0 | CC7: 0 | CD7: 0 | CE7: 0 | CF7: 0 | CG7: 1 | CH7: 0 | CI7: 0 | CJ7: 0 | CK7: 0 | CL7: 0 | CM7: 0 | CN7: 0 | CO7: 0 | CP7: 0 | CQ7: 0 | CR7: 0 | CS7: 0 | CT7: 0 | CU7: 0 | CV7: 1 | CW7: 0 | CX7: 0
A8: Armenia | B8: AM | C8: 2018 | D8: 17 | E8: 0 | F8: 0 | G8: 0 | H8: 0 | I8: 0 | J8: 0 | K8: 0 | L8: 0 | M8: 0 | N8: 0 | O8: 2 | P8: 0 | Q8: 0 | R8: 0 | S8: 0 | T8: 0 | U8: 0 | V8: 0 | W8: 0 | X8: 0 | Y8: 0 | Z8: 0 | AA8: 0 | AB8: 0 | AC8: 0 | AD8: 0 | AE8: 0 | AF8: 0 | AG8: 0 | AH8: 0 | AI8: 0 | AJ8: 0 | AK8: 2 | AL8: 0 | AM8: 0 | AN8: 0 | AO8: 0 | AP8: 0 | AQ8: 0 | AR8: 0 | AS8: 0 | AT8: 0 | AU8: 0 | AV8: 0 | AW8: 0 | AX8: 0 | AY8: 0 | AZ8: 0 | BA8: 0 | BB8: 0 | BC8: 0 | BD8: 0 | BE8: 1 | BF8: 4 | BG8: 0 | BH8: 0 | BI8: 0 | BJ8: 1 | BK8: 1 | BL8: 0 | BM8: 0 | BN8: 0 | BO8: 0 | BP8: 0 | BQ8: 0 | BR8: 0 | BS8: 0 | BT8: 1 | BU8: 0 | BV8: 0 | BW8: 0 | BX8: 0 | BY8: 0 | BZ8: 0 | CA8: 0 | CB8: 0 | CC8: 0 | CD8: 0 | CE8: 0 | CF8: 0 | CG8: 0 | CH8: 0 | CI8: 0 | CJ8: 0 | CK8: 0 | CL8: 0 | CM8: 0 | CN8: 1 | CO8: 0 | CP8: 0 | CQ8: 0 | CR8: 0 | CS8: 0 | CT8: 0 | CU8: 0 | CV8: 0 | CW8: 0 | CX8: 0
A9: Angola | B9: AO | C9: 2018 | D9: 209 | E9: 0 | F9: 7 | G9: 4 | H9: 0 | I9: 1 | J9: 0 | K9: 0 | L9: 0 | M9: 0 | N9: 0 | O9: 5 | P9: 0 | Q9: 0 | R9: 0 | S9: 0 | T9: 0 | U9: 1 | V9: 0 | W9: 0 | X9: 0 | Y9: 0 | Z9: 0 | AA9: 1 | AB9: 0 | AC9: 0 | AD9: 0 | AE9: 0 | AF9: 0 | AG9: 6 | AH9: 2 | AI9: 9 | AJ9: 0 | AK9: 1 | AL9: 0 | AM9: 2 | AN9: 0 | AO9: 16 | AP9: 0 | AQ9: 6 | AR9: 0 | AS9: 0 | AT9: 1 | AU9: 1 | AV9: 4 | AW9: 0 | AX9: 8 | AY9: 1 | AZ9: 1 | BA9: 0 | BB9: 50 | BC9: 1 | BD9: 0 | BE9: 6 | BF9: 6 | BG9: 0 | BH9: 0 | BI9: 0 | BJ9: 14 | BK9: 10 | BL9: 0 | BM9: 0 | BN9: 2 | BO9: 0 | BP9: 0 | BQ9: 3 | BR9: 0 | BS9: 12 | BT9: 2 | BU9: 0 | BV9: 1 | BW9: 1 | BX9: 1 | BY9: 0 | BZ9: 0 | CA9: 1 | CB9: 1 | CC9: 0 | CD9: 0 | CE9: 0 | CF9: 0 | CG9: 0 | CH9: 0 | CI9: 0 | CJ9: 1 | CK9: 0 | CL9: 0 | CM9: 2 | CN9: 11 | CO9: 0 | CP9: 0 | CQ9: 0 | CR9: 0 | CS9: 0 | CT9: 4 | CU9: 0 | CV9: 1 | CW9: 2 | CX9: 2
A10: Antarctica | B10: AQ | C10: 2018 | D10: 0 | E10: 0 | F10: 0 | G10: 0 | H10: 0 | I10: 0 | J10: 0 | K10: 0 | L10: 0 | M10: 0 | N10: 0 | O10: 0 | P10: 0 | Q10: 0 | R10: 0 | S10: 0 | T10: 0 | U10: 0 | V10: 0 | W10: 0 | X10: 0 | Y10: 0 | Z10: 0 | AA10: 0 | AB10: 0 | AC10: 0 | AD10: 0 | AE10: 0 | AF10: 0 | AG10: 0 | AH10: 0 | AI10: 0 | AJ10: 0 | AK10: 0 | AL10: 0 | AM10: 0 | AN10: 0 | AO10: 0 | AP10: 0 | AQ10: 0 | AR10: 0 | AS10: 0 | AT10: 0 | AU10: 0 | AV10: 0 | AW10: 0 | AX10: 0 | AY10: 0 | AZ10: 0 | BA10: 0 | BB10: 0 | BC10: 0 | BD10: 0 | BE10: 0 | BF10: 0 | BG10: 0 | BH10: 0 | BI10: 0 | BJ10: 0 | BK10: 0 | BL10: 0 | BM10: 0 | BN10: 0 | BO10: 0 | BP10: 0 | BQ10: 0 | BR10: 0 | BS10: 0 | BT10: 0 | BU10: 0 | BV10: 0 | BW10: 0 | BX10: 0 | BY10: 0 | BZ10: 0 | CA10: 0 | CB10: 0 | CC10: 0 | CD10: 0 | CE10: 0 | CF10: 0 | CG10: 0 | CH10: 0 | CI10: 0 | CJ10: 0 | CK10: 0 | CL10: 0 | CM10: 0 | CN10: 0 | CO10: 0 | CP10: 0 | CQ10: 0 | CR10: 0 | CS10: 0 | CT10: 0 | CU10: 0 | CV10: 0 | CW10: 0 | CX10: 0
A11: Argentina | B11: AR | C11: 2018 | D11: 386 | E11: 0 | F11: 0 | G11: 0 | H11: 0 | I11: 0 | J11: 0 | K11: 0 | L11: 3 | M11: 1 | N11: 2 | O11: 16 | P11: 1 | Q11: 0 | R11: 1 | S11: 0 | T11: 0 | U11: 0 | V11: 2 | W11: 0 | X11: 0 | Y11: 0 | Z11: 0 | AA11: 2 | AB11: 0 | AC11: 0 | AD11: 0 | AE11: 0 | AF11: 0 | AG11: 11 | AH11: 2 | AI11: 4 | AJ11: 99 | AK11: 21 | AL11: 1 | AM11: 5 | AN11: 4 | AO11: 17 | AP11: 0 | AQ11: 1 | AR11: 0 | AS11: 2 | AT11: 1 | AU11: 3 | AV11: 3 | AW11: 57 | AX11: 7 | AY11: 0 | AZ11: 3 | BA11: 0 | BB11: 7 | BC11: 2 | BD11: 0 | BE11: 4 | BF11: 13 | BG11: 0 | BH11: 0 | BI11: 0 | BJ11: 10 | BK11: 10 | BL11: 0 | BM11: 0 | BN11: 1 | BO11: 0 | BP11: 0 | BQ11: 3 | BR11: 1 | BS11: 6 | BT11: 7 | BU11: 0 | BV11: 4 | BW11: 1 | BX11: 5 | BY11: 2 | BZ11: 0 | CA11: 1 | CB11: 0 | CC11: 0 | CD11: 0 | CE11: 0 | CF11: 0 | CG11: 0 | CH11: 0 | CI11: 0 | CJ11: 0 | CK11: 0 | CL11: 0 | CM11: 3 | CN11: 15 | CO11: 0 | CP11: 0 | CQ11: 0 | CR11: 3 | CS11: 0 | CT11: 2 | CU11: 0 | CV11: 13 | CW11: 2 | CX11: 2
A12: American Samoa | B12: AS | C12: 2018 | D12: 0 | E12: 0 | F12: 0 | G12: 0 | H12: 0 | I12: 0 | J12: 0 | K12: 0 | L12: 0 | M12: 0 | N12: 0 | O12: 0 | P12: 0 | Q12: 0 | R12: 0 | S12: 0 | T12: 0 | U12: 0 | V12: 0 | W12: 0 | X12: 0 | Y12: 0 | Z12: 0 | AA12: 0 | AB12: 0 | AC12: 0 | AD12: 0 | AE12: 0 | AF12: 0 | AG12: 0 | AH12: 0 | AI12: 0 | AJ12: 0 | AK12: 0 | AL12: 0 | AM12: 0 | AN12: 0 | AO12: 0 | AP12: 0 | AQ12: 0 | AR12: 0 | AS12: 0 | AT12: 0 | AU12: 0 | AV12: 0 | AW12: 0 | AX12: 0 | AY12: 0 | AZ12: 0 | BA12: 0 | BB12: 0 | BC12: 0 | BD12: 0 | BE12: 0 | BF12: 0 | BG12: 0 | BH12: 0 | BI12: 0 | BJ12: 0 | BK12: 0 | BL12: 0 | BM12: 0 | BN12: 0 | BO12: 0 | BP12: 0 | BQ12: 0 | BR12: 0 | BS12: 0 | BT12: 0 | BU12: 0 | BV12: 0 | BW12: 0 | BX12: 0 | BY12: 0 | BZ12: 0 | CA12: 0 | CB12: 0 | CC12: 0 | CD12: 0 | CE12: 0 | CF12: 0 | CG12: 0 | CH12: 0 | CI12: 0 | CJ12: 0 | CK12: 0 | CL12: 0 | CM12: 0 | CN12: 0 | CO12: 0 | CP12: 0 | CQ12: 0 | CR12: 0 | CS12: 0 | CT12: 0 | CU12: 0 | CV12: 0 | CW12: 0 | CX12: 0
A13: Austria | B13: AT | C13: 2018 | D13: 2069 | E13: 0 | F13: 11 | G13: 2 | H13: 2 | I13: 6 | J13: 7 | K13: 4 | L13: 7 | M13: 6 | N13: 16 | O13: 30 | P13: 0 | Q13: 0 | R13: 0 | S13: 0 | T13: 5 | U13: 1 | V13: 2 | W13: 18 | X13: 1 | Y13: 0 | Z13: 0 | AA13: 17 | AB13: 0 | AC13: 0 | AD13: 0 | AE13: 0 | AF13: 0 | AG13: 21 | AH13: 4 | AI13: 40 | AJ13: 200 | AK13: 18 | AL13: 1 | AM13: 36 | AN13: 22 | AO13: 37 | AP13: 1 | AQ13: 17 | AR13: 1 | AS13: 14 | AT13: 27 | AU13: 42 | AV13: 23 | AW13: 77 | AX13: 57 | AY13: 0 | AZ13: 9 | BA13: 0 | BB13: 183 | BC13: 19 | BD13: 0 | BE13: 18 | BF13: 60 | BG13: 2 | BH13: 3 | BI13: 1 | BJ13: 32 | BK13: 61 | BL13: 0 | BM13: 5 | BN13: 34 | BO13: 3 | BP13: 8 | BQ13: 36 | BR13: 3 | BS13: 88 | BT13: 46 | BU13: 2 | BV13: 90 | BW13: 11 | BX13: 246 | BY13: 2 | BZ13: 0 | CA13: 9 | CB13: 3 | CC13: 0 | CD13: 5 | CE13: 0 | CF13: 3 | CG13: 3 | CH13: 8 | CI13: 10 | CJ13: 87 | CK13: 22 | CL13: 0 | CM13: 4 | CN13: 46 | CO13: 6 | CP13: 7 | CQ13: 0 | CR13: 9 | CS13: 4 | CT13: 17 | CU13: 22 | CV13: 73 | CW13: 2 | CX13: 2
... A1423: Whole World | B1423: W1 | C1423: 2023 | D1423: 393516 | E1423: 618 | F1423: 2065 | G1423: 2154 | H1423: 1806 | I1423: 2954 | J1423: 1047 | K1423: 604 | L1423: 2115 | M1423: 1272 | N1423: 2421 | O1423: 12048 | P1423: 75 | Q1423: 58 | R1423: 332 | S1423: 185 | T1423: 545 | U1423: 649 | V1423: 547 | W1423: 6221 | X1423: 403 | Y1423: 194 | Z1423: 20312 | AA1423: 13077 | AB1423: 3882 | AC1423: 719 | AD1423: 126 | AE1423: 261 | AF1423: 246 | AG1423: 10072 | AH1423: 2893 | AI1423: 2465 | AJ1423: 25942 | AK1423: 5543 | AL1423: 371 | AM1423: 3471 | AN1423: 3252 | AO1423: 5879 | AP1423: 218 | AQ1423: 1796 | AR1423: 471 | AS1423: 2286 | AT1423: 2726 | AU1423: 3172 | AV1423: 5370 | AW1423: 10860 | AX1423: 7949 | AY1423: 193 | AZ1423: 1562 | BA1423: 4 | BB1423: 34369 | BC1423: 2879 | BD1423: 221 | BE1423: 2400 | BF1423: 8634 | BG1423: 455 | BH1423: 697 | BI1423: 47 | BJ1423: 8439 | BK1423: 10773 | BL1423: 4 | BM1423: 819 | BN1423: 4384 | BO1423: 123 | BP1423: 864 | BQ1423: 6466 | BR1423: 684 | BS1423: 9964 | BT1423: 5471 | BU1423: 324 | BV1423: 5009 | BW1423: 4135 | BX1423: 34810 | BY1423: 161 | BZ1423: 293 | CA1423: 11779 | CB1423: 3500 | CC1423: 29 | CD1423: 823 | CE1423: 107 | CF1423: 896 | CG1423: 919 | CH1423: 627 | CI1423: 743 | CJ1423: 3762 | CK1423: 777 | CL1423: 9 | CM1423: 2011 | CN1423: 11683 | CO1423: 1251 | CP1423: 655 | CQ1423: 19 | CR1423: 4109 | CS1423: 2792 | CT1423: 2574 | CU1423: 496 | CV1423: 8220 | CW1423: 19879 | CX1423: 19810

Sheet ONS - UK Imports by type
A1: CountryName | B1: CountryId | C1: Year | D1: Total | E1: Live animals | F1: Meat & meat preparations | G1: Dairy products & eggs | H1: Fish and shellfish | I1: Cereals | J1: Vegetables & fruit | K1: Sugar | L1: Coffee, tea, cocoa etc | M1: Animal feeding stuffs | N1: Miscellaneous foods | O1: Beverages & tobacco | P1: Hides, skins & furskins | Q1: Oil-seeds & oleaginous fruits | R1: Crude rubber | S1: Wood & cork | T1: Pulp & waste paper | U1: Textile fibres | V1: Crude minerals & fertilisers | W1: Metal ores & scrap | X1: Other crude animal & vegetable materials | Y1: Coal, coke & briquettes | Z1: Crude oil | AA1: Refined oil | AB1: Gas | AC1: Electricity | AD1: Animal oils & fats | AE1: Vegetable oils & fats | AF1: Processed oils & fats | AG1: Organic chemicals | AH1: Inorganic chemicals | AI1: Dyeing, tanning & colouring materials | AJ1: Medicinal & pharmaceutical products | AK1: Toilet & cleansing preparations | AL1: Processed fertilisers | AM1: Plastics in primary forms | AN1: Plastics in non-primary forms | AO1: Other chemicals | AP1: Leather manufactures | AQ1: Rubber manufactures | AR1: Wood & cork manufactures | AS1: Paper & paperboard | AT1: Textile fabrics | AU1: Mineral manufactures | AV1: Iron & steel | AW1: Non-ferrous metals | AX1: Miscellaneous metal manufactures | AY1: Electric motors (intermediate) | AZ1: Electric motors (capital) | BA1: Mechanical power generators (consumer) | BB1: Mechanical power generators (intermediate) | BC1: Mechanical power generators (capital) | BD1: Specialised machinery (consumer) | BE1: Specialised machinery (intermediate) | BF1: Specialised machinery (capital) | BG1: Metal working machinery (intermediate) | BH1: Metal working machinery (capital) | BI1: General industrial machinery (consumer) | BJ1: General industrial machinery (intermediate) | BK1: General industrial machinery (capital) | BL1: Office machinery (consumer) | BM1: Office machinery (intermediate) | BN1: Office machinery (capital) | BO1: Telecoms & sound equipment (consumer) | BP1: Telecoms & sound equipment (intermediate) | BQ1: Telecoms & sound equipment (capital) | BR1: Miscellaneous electrical goods (consumer) | BS1: Miscellaneous electrical goods (intermediate) | BT1: Miscellaneous electrical goods (capital) | BU1: Road vehicles other than cars (consumer) | BV1: Road vehicles other than cars (intermediate) | BW1: Road vehicles other than cars (capital) | BX1: Cars | BY1: Railway equipment (intermediate) | BZ1: Railway equipment (capital) | CA1: Aircraft | CB1: Ships | CC1: Plumbing, heating & lighting fixtures (consumer) | CD1: Plumbing, heating & lighting fixtures (intermediate) | CE1: Plumbing, heating & lighting fixtures (capital) | CF1: Furniture (consumer) | CG1: Furniture (intermediate) | CH1: Furniture (capital) | CI1: Travel goods, handbags etc | CJ1: Clothing | CK1: Footwear | CL1: Scientific instruments (consumer) | CM1: Scientific instruments (intermediate) | CN1: Scientific instruments (capital) | CO1: Photographic & optical goods & clocks (consumer) | CP1: Photographic & optical goods & clocks (intermediate) | CQ1: Photographic & optical goods & clocks (capital) | CR1: Works of art | CS1: Jewellery | CT1: Other manufactures (intermediate) | CU1: Other manufactures (capital) | CV1: Other manufactures (consumer) | CW1: Unspecified goods
A2: Andorra | B2: AD | C2: 2018 | D2: 2 | E2: 0 | F2: 0 | G2: 0 | H2: 0 | I2: 0 | J2: 0 | K2: 0 | L2: 0 | M2: 0 | N2: 0 | O2: 0 | P2: 0 | Q2: 0 | R2: 0 | S2: 0 | T2: 0 | U2: 0 | V2: 0 | W2: 0 | X2: 0 | Y2: 0 | Z2: 0 | AA2: 0 | AB2: 0 | AC2: 0 | AD2: 0 | AE2: 0 | AF2: 0 | AG2: 0 | AH2: 0 | AI2: 0 | AJ2: 0 | AK2: 0 | AL2: 0 | AM2: 0 | AN2: 0 | AO2: 0 | AP2: 0 | AQ2: 0 | AR2: 0 | AS2: 0 | AT2: 0 | AU2: 0 | AV2: 0 | AW2: 0 | AX2: 0 | AY2: 0 | AZ2: 0 | BA2: 0 | BB2: 0 | BC2: 0 | BD2: 0 | BE2: 0 | BF2: 0 | BG2: 0 | BH2: 0 | BI2: 0 | BJ2: 0 | BK2: 0 | BL2: 0 | BM2: 0 | BN2: 0 | BO2: 0 | BP2: 0 | BQ2: 0 | BR2: 0 | BS2: 0 | BT2: 0 | BU2: 0 | BV2: 0 | BW2: 0 | BX2: 0 | BY2: 0 | BZ2: 0 | CA2: 0 | CB2: 0 | CC2: 0 | CD2: 0 | CE2: 0 | CF2: 0 | CG2: 0 | CH2: 0 | CI2: 0 | CJ2: 0 | CK2: 0 | CL2: 0 | CM2: 0 | CN2: 0 | CO2: 0 | CP2: 0 | CQ2: 0 | CR2: 2 | CS2: 0 | CT2: 0 | CU2: 0 | CV2: 0 | CW2: 0
A3: United Arab Emirates | B3: AE | C3: 2018 | D3: 3704 | E3: 9 | F3: 0 | G3: 0 | H3: 0 | I3: 1 | J3: 4 | K3: 0 | L3: 1 | M3: 0 | N3: 3 | O3: 2 | P3: 0 | Q3: 0 | R3: 0 | S3: 0 | T3: 0 | U3: 2 | V3: 0 | W3: 14 | X3: 0 | Y3: 0 | Z3: 0 | AA3: 1287 | AB3: 0 | AC3: 0 | AD3: 0 | AE3: 0 | AF3: 7 | AG3: 1 | AH3: 7 | AI3: 2 | AJ3: 3 | AK3: 20 | AL3: 0 | AM3: 10 | AN3: 3 | AO3: 1 | AP3: 4 | AQ3: 5 | AR3: 7 | AS3: 6 | AT3: 10 | AU3: 12 | AV3: 61 | AW3: 81 | AX3: 96 | AY3: 1 | AZ3: 20 | BA3: 0 | BB3: 1313 | BC3: 4 | BD3: 0 | BE3: 6 | BF3: 8 | BG3: 0 | BH3: 1 | BI3: 0 | BJ3: 25 | BK3: 29 | BL3: 0 | BM3: 1 | BN3: 16 | BO3: 0 | BP3: 3 | BQ3: 68 | BR3: 0 | BS3: 66 | BT3: 11 | BU3: 0 | BV3: 11 | BW3: 3 | BX3: 10 | BY3: 0 | BZ3: 0 | CA3: 50 | CB3: 0 | CC3: 0 | CD3: 16 | CE3: 0 | CF3: 39 | CG3: 2 | CH3: 1 | CI3: 2 | CJ3: 37 | CK3: 3 | CL3: 0 | CM3: 23 | CN3: 115 | CO3: 6 | CP3: 1 | CQ3: 0 | CR3: 8 | CS3: 52 | CT3: 10 | CU3: 1 | CV3: 28 | CW3: 51
A4: Afghanistan | B4: AF | C4: 2018 | D4: 0 | E4: 0 | F4: 0 | G4: 0 | H4: 0 | I4: 0 | J4: 0 | K4: 0 | L4: 0 | M4: 0 | N4: 0 | O4: 0 | P4: 0 | Q4: 0 | R4: 0 | S4: 0 | T4: 0 | U4: 0 | V4: 0 | W4: 0 | X4: 0 | Y4: 0 | Z4: 0 | AA4: 0 | AB4: 0 | AC4: 0 | AD4: 0 | AE4: 0 | AF4: 0 | AG4: 0 | AH4: 0 | AI4: 0 | AJ4: 0 | AK4: 0 | AL4: 0 | AM4: 0 | AN4: 0 | AO4: 0 | AP4: 0 | AQ4: 0 | AR4: 0 | AS4: 0 | AT4: 0 | AU4: 0 | AV4: 0 | AW4: 0 | AX4: 0 | AY4: 0 | AZ4: 0 | BA4: 0 | BB4: 0 | BC4: 0 | BD4: 0 | BE4: 0 | BF4: 0 | BG4: 0 | BH4: 0 | BI4: 0 | BJ4: 0 | BK4: 0 | BL4: 0 | BM4: 0 | BN4: 0 | BO4: 0 | BP4: 0 | BQ4: 0 | BR4: 0 | BS4: 0 | BT4: 0 | BU4: 0 | BV4: 0 | BW4: 0 | BX4: 0 | BY4: 0 | BZ4: 0 | CA4: 0 | CB4: 0 | CC4: 0 | CD4: 0 | CE4: 0 | CF4: 0 | CG4: 0 | CH4: 0 | CI4: 0 | CJ4: 0 | CK4: 0 | CL4: 0 | CM4: 0 | CN4: 0 | CO4: 0 | CP4: 0 | CQ4: 0 | CR4: 0 | CS4: 0 | CT4: 0 | CU4: 0 | CV4: 0 | CW4: 0
A5: Antigua & Barbuda | B5: AG | C5: 2018 | D5: 4 | E5: 0 | F5: 0 | G5: 0 | H5: 0 | I5: 0 | J5: 0 | K5: 0 | L5: 0 | M5: 0 | N5: 0 | O5: 0 | P5: 0 | Q5: 0 | R5: 0 | S5: 0 | T5: 0 | U5: 0 | V5: 0 | W5: 0 | X5: 0 | Y5: 0 | Z5: 0 | AA5: 0 | AB5: 0 | AC5: 0 | AD5: 0 | AE5: 0 | AF5: 0 | AG5: 0 | AH5: 0 | AI5: 0 | AJ5: 0 | AK5: 0 | AL5: 0 | AM5: 0 | AN5: 0 | AO5: 0 | AP5: 0 | AQ5: 0 | AR5: 0 | AS5: 0 | AT5: 0 | AU5: 0 | AV5: 0 | AW5: 0 | AX5: 0 | AY5: 0 | AZ5: 0 | BA5: 0 | BB5: 1 | BC5: 0 | BD5: 0 | BE5: 0 | BF5: 0 | BG5: 0 | BH5: 0 | BI5: 0 | BJ5: 0 | BK5: 0 | BL5: 0 | BM5: 0 | BN5: 0 | BO5: 0 | BP5: 0 | BQ5: 0 | BR5: 0 | BS5: 0 | BT5: 0 | BU5: 0 | BV5: 0 | BW5: 0 | BX5: 0 | BY5: 0 | BZ5: 0 | CA5: 0 | CB5: 3 | CC5: 0 | CD5: 0 | CE5: 0 | CF5: 0 | CG5: 0 | CH5: 0 | CI5: 0 | CJ5: 0 | CK5: 0 | CL5: 0 | CM5: 0 | CN5: 0 | CO5: 0 | CP5: 0 | CQ5: 0 | CR5: 0 | CS5: 0 | CT5: 0 | CU5: 0 | CV5: 0 | CW5: 0
A6: Anguilla | B6: AI | C6: 2018 | D6: 0 | E6: 0 | F6: 0 | G6: 0 | H6: 0 | I6: 0 | J6: 0 | K6: 0 | L6: 0 | M6: 0 | N6: 0 | O6: 0 | P6: 0 | Q6: 0 | R6: 0 | S6: 0 | T6: 0 | U6: 0 | V6: 0 | W6: 0 | X6: 0 | Y6: 0 | Z6: 0 | AA6: 0 | AB6: 0 | AC6: 0 | AD6: 0 | AE6: 0 | AF6: 0 | AG6: 0 | AH6: 0 | AI6: 0 | AJ6: 0 | AK6: 0 | AL6: 0 | AM6: 0 | AN6: 0 | AO6: 0 | AP6: 0 | AQ6: 0 | AR6: 0 | AS6: 0 | AT6: 0 | AU6: 0 | AV6: 0 | AW6: 0 | AX6: 1 | AY6: 0 | AZ6: 0 | BA6: 0 | BB6: 0 | BC6: 0 | BD6: 0 | BE6: 0 | BF6: 0 | BG6: 0 | BH6: 0 | BI6: 0 | BJ6: 0 | BK6: 0 | BL6: 0 | BM6: 0 | BN6: 0 | BO6: 0 | BP6: 0 | BQ6: 0 | BR6: 0 | BS6: 0 | BT6: 0 | BU6: 0 | BV6: 0 | BW6: 0 | BX6: 0 | BY6: 0 | BZ6: 0 | CA6: 0 | CB6: 0 | CC6: 0 | CD6: 0 | CE6: 0 | CF6: 0 | CG6: 0 | CH6: 0 | CI6: 0 | CJ6: 0 | CK6: 0 | CL6: 0 | CM6: 0 | CN6: 0 | CO6: 0 | CP6: 0 | CQ6: 0 | CR6: 0 | CS6: 0 | CT6: 0 | CU6: 0 | CV6: 0 | CW6: 0
A7: Albania | B7: AL | C7: 2018 | D7: 6 | E7: 0 | F7: 0 | G7: 0 | H7: 0 | I7: 0 | J7: 0 | K7: 0 | L7: 0 | M7: 0 | N7: 0 | O7: 1 | P7: 0 | Q7: 0 | R7: 0 | S7: 0 | T7: 0 | U7: 0 | V7: 0 | W7: 2 | X7: 0 | Y7: 0 | Z7: 0 | AA7: 0 | AB7: 0 | AC7: 0 | AD7: 0 | AE7: 0 | AF7: 0 | AG7: 0 | AH7: 0 | AI7: 0 | AJ7: 0 | AK7: 0 | AL7: 0 | AM7: 0 | AN7: 0 | AO7: 0 | AP7: 0 | AQ7: 0 | AR7: 0 | AS7: 0 | AT7: 0 | AU7: 0 | AV7: 2 | AW7: 0 | AX7: 0 | AY7: 0 | AZ7: 0 | BA7: 0 | BB7: 0 | BC7: 0 | BD7: 0 | BE7: 0 | BF7: 0 | BG7: 0 | BH7: 0 | BI7: 0 | BJ7: 0 | BK7: 0 | BL7: 0 | BM7: 0 | BN7: 0 | BO7: 0 | BP7: 0 | BQ7: 0 | BR7: 0 | BS7: 0 | BT7: 0 | BU7: 0 | BV7: 0 | BW7: 0 | BX7: 0 | BY7: 0 | BZ7: 0 | CA7: 0 | CB7: 0 | CC7: 0 | CD7: 0 | CE7: 0 | CF7: 0 | CG7: 0 | CH7: 0 | CI7: 0 | CJ7: 0 | CK7: 0 | CL7: 0 | CM7: 0 | CN7: 0 | CO7: 0 | CP7: 0 | CQ7: 0 | CR7: 0 | CS7: 0 | CT7: 0 | CU7: 0 | CV7: 0 | CW7: 0
A8: Armenia | B8: AM | C8: 2018 | D8: 1 | E8: 0 | F8: 0 | G8: 0 | H8: 0 | I8: 0 | J8: 0 | K8: 0 | L8: 0 | M8: 0 | N8: 0 | O8: 0 | P8: 0 | Q8: 0 | R8: 0 | S8: 0 | T8: 0 | U8: 0 | V8: 0 | W8: 0 | X8: 0 | Y8: 0 | Z8: 0 | AA8: 0 | AB8: 0 | AC8: 0 | AD8: 0 | AE8: 0 | AF8: 0 | AG8: 0 | AH8: 0 | AI8: 0 | AJ8: 0 | AK8: 1 | AL8: 0 | AM8: 0 | AN8: 0 | AO8: 0 | AP8: 0 | AQ8: 0 | AR8: 0 | AS8: 0 | AT8: 0 | AU8: 0 | AV8: 0 | AW8: 1 | AX8: 0 | AY8: 0 | AZ8: 0 | BA8: 0 | BB8: 0 | BC8: 0 | BD8: 0 | BE8: 0 | BF8: 0 | BG8: 0 | BH8: 0 | BI8: 0 | BJ8: 0 | BK8: 0 | BL8: 0 | BM8: 0 | BN8: 0 | BO8: 0 | BP8: 0 | BQ8: 0 | BR8: 0 | BS8: 0 | BT8: 0 | BU8: 0 | BV8: 0 | BW8: 0 | BX8: 0 | BY8: 0 | BZ8: 0 | CA8: 0 | CB8: 0 | CC8: 0 | CD8: 0 | CE8: 0 | CF8: 0 | CG8: 0 | CH8: 0 | CI8: 0 | CJ8: 0 | CK8: 0 | CL8: 0 | CM8: 0 | CN8: 0 | CO8: 0 | CP8: 0 | CQ8: 0 | CR8: 0 | CS8: 0 | CT8: 0 | CU8: 0 | CV8: 0 | CW8: 0
A9: Angola | B9: AO | C9: 2018 | D9: 89 | E9: 0 | F9: 0 | G9: 0 | H9: 0 | I9: 0 | J9: 0 | K9: 0 | L9: 0 | M9: 1 | N9: 0 | O9: 0 | P9: 0 | Q9: 0 | R9: 0 | S9: 0 | T9: 0 | U9: 0 | V9: 0 | W9: 0 | X9: 0 | Y9: 0 | Z9: 57 | AA9: 0 | AB9: 0 | AC9: 0 | AD9: 0 | AE9: 0 | AF9: 0 | AG9: 0 | AH9: 0 | AI9: 0 | AJ9: 0 | AK9: 0 | AL9: 0 | AM9: 0 | AN9: 0 | AO9: 0 | AP9: 0 | AQ9: 0 | AR9: 0 | AS9: 0 | AT9: 0 | AU9: 0 | AV9: 0 | AW9: 0 | AX9: 0 | AY9: 0 | AZ9: 0 | BA9: 0 | BB9: 13 | BC9: 0 | BD9: 0 | BE9: 4 | BF9: 1 | BG9: 0 | BH9: 0 | BI9: 0 | BJ9: 1 | BK9: 1 | BL9: 0 | BM9: 0 | BN9: 0 | BO9: 0 | BP9: 0 | BQ9: 0 | BR9: 0 | BS9: 0 | BT9: 0 | BU9: 0 | BV9: 0 | BW9: 0 | BX9: 0 | BY9: 0 | BZ9: 0 | CA9: 0 | CB9: 0 | CC9: 0 | CD9: 0 | CE9: 0 | CF9: 0 | CG9: 0 | CH9: 0 | CI9: 0 | CJ9: 0 | CK9: 0 | CL9: 0 | CM9: 5 | CN9: 3 | CO9: 0 | CP9: 0 | CQ9: 0 | CR9: 0 | CS9: 0 | CT9: 0 | CU9: 0 | CV9: 0 | CW9: 0
A10: Antarctica | B10: AQ | C10: 2018 | D10: 0 | E10: 0 | F10: 0 | G10: 0 | H10: 0 | I10: 0 | J10: 0 | K10: 0 | L10: 0 | M10: 0 | N10: 0 | O10: 0 | P10: 0 | Q10: 0 | R10: 0 | S10: 0 | T10: 0 | U10: 0 | V10: 0 | W10: 0 | X10: 0 | Y10: 0 | Z10: 0 | AA10: 0 | AB10: 0 | AC10: 0 | AD10: 0 | AE10: 0 | AF10: 0 | AG10: 0 | AH10: 0 | AI10: 0 | AJ10: 0 | AK10: 0 | AL10: 0 | AM10: 0 | AN10: 0 | AO10: 0 | AP10: 0 | AQ10: 0 | AR10: 0 | AS10: 0 | AT10: 0 | AU10: 0 | AV10: 0 | AW10: 0 | AX10: 0 | AY10: 0 | AZ10: 0 | BA10: 0 | BB10: 0 | BC10: 0 | BD10: 0 | BE10: 0 | BF10: 0 | BG10: 0 | BH10: 0 | BI10: 0 | BJ10: 0 | BK10: 0 | BL10: 0 | BM10: 0 | BN10: 0 | BO10: 0 | BP10: 0 | BQ10: 0 | BR10: 0 | BS10: 0 | BT10: 0 | BU10: 0 | BV10: 0 | BW10: 0 | BX10: 0 | BY10: 0 | BZ10: 0 | CA10: 0 | CB10: 0 | CC10: 0 | CD10: 0 | CE10: 0 | CF10: 0 | CG10: 0 | CH10: 0 | CI10: 0 | CJ10: 0 | CK10: 0 | CL10: 0 | CM10: 0 | CN10: 0 | CO10: 0 | CP10: 0 | CQ10: 0 | CR10: 0 | CS10: 0 | CT10: 0 | CU10: 0 | CV10: 0 | CW10: 0
A11: Argentina | B11: AR | C11: 2018 | D11: 657 | E11: 3 | F11: 11 | G11: 0 | H11: 4 | I11: 36 | J11: 39 | K11: 2 | L11: 2 | M11: 394 | N11: 0 | O11: 84 | P11: 0 | Q11: 29 | R11: 0 | S11: 0 | T11: 0 | U11: 1 | V11: 0 | W11: 1 | X11: 0 | Y11: 0 | Z11: 0 | AA11: 0 | AB11: 0 | AC11: 0 | AD11: 0 | AE11: 2 | AF11: 1 | AG11: 8 | AH11: 4 | AI11: 0 | AJ11: 0 | AK11: 2 | AL11: 0 | AM11: 0 | AN11: 0 | AO11: 3 | AP11: 9 | AQ11: 0 | AR11: 1 | AS11: 0 | AT11: 0 | AU11: 1 | AV11: 3 | AW11: 0 | AX11: 0 | AY11: 0 | AZ11: 0 | BA11: 0 | BB11: 5 | BC11: 0 | BD11: 0 | BE11: 0 | BF11: 0 | BG11: 0 | BH11: 0 | BI11: 0 | BJ11: 3 | BK11: 0 | BL11: 0 | BM11: 0 | BN11: 0 | BO11: 0 | BP11: 0 | BQ11: 0 | BR11: 0 | BS11: 0 | BT11: 0 | BU11: 0 | BV11: 1 | BW11: 0 | BX11: 0 | BY11: 0 | BZ11: 0 | CA11: 0 | CB11: 0 | CC11: 0 | CD11: 0 | CE11: 0 | CF11: 1 | CG11: 0 | CH11: 0 | CI11: 0 | CJ11: 0 | CK11: 0 | CL11: 0 | CM11: 0 | CN11: 1 | CO11: 0 | CP11: 0 | CQ11: 0 | CR11: 2 | CS11: 0 | CT11: 0 | CU11: 0 | CV11: 0 | CW11: 0
A12: American Samoa | B12: AS | C12: 2018 | D12: 0 | E12: 0 | F12: 0 | G12: 0 | H12: 0 | I12: 0 | J12: 0 | K12: 0 | L12: 0 | M12: 0 | N12: 0 | O12: 0 | P12: 0 | Q12: 0 | R12: 0 | S12: 0 | T12: 0 | U12: 0 | V12: 0 | W12: 0 | X12: 0 | Y12: 0 | Z12: 0 | AA12: 0 | AB12: 0 | AC12: 0 | AD12: 0 | AE12: 0 | AF12: 0 | AG12: 0 | AH12: 0 | AI12: 0 | AJ12: 0 | AK12: 0 | AL12: 0 | AM12: 0 | AN12: 0 | AO12: 0 | AP12: 0 | AQ12: 0 | AR12: 0 | AS12: 0 | AT12: 0 | AU12: 0 | AV12: 0 | AW12: 0 | AX12: 0 | AY12: 0 | AZ12: 0 | BA12: 0 | BB12: 0 | BC12: 0 | BD12: 0 | BE12: 0 | BF12: 0 | BG12: 0 | BH12: 0 | BI12: 0 | BJ12: 0 | BK12: 0 | BL12: 0 | BM12: 0 | BN12: 0 | BO12: 0 | BP12: 0 | BQ12: 0 | BR12: 0 | BS12: 0 | BT12: 0 | BU12: 0 | BV12: 0 | BW12: 0 | BX12: 0 | BY12: 0 | BZ12: 0 | CA12: 0 | CB12: 0 | CC12: 0 | CD12: 0 | CE12: 0 | CF12: 0 | CG12: 0 | CH12: 0 | CI12: 0 | CJ12: 0 | CK12: 0 | CL12: 0 | CM12: 0 | CN12: 0 | CO12: 0 | CP12: 0 | CQ12: 0 | CR12: 0 | CS12: 0 | CT12: 0 | CU12: 0 | CV12: 0 | CW12: 0
A13: Austria | B13: AT | C13: 2018 | D13: 4451 | E13: 0 | F13: 30 | G13: 12 | H13: 0 | I13: 40 | J13: 29 | K13: 2 | L13: 6 | M13: 27 | N13: 13 | O13: 72 | P13: 0 | Q13: 1 | R13: 1 | S13: 9 | T13: 66 | U13: 10 | V13: 4 | W13: 17 | X13: 1 | Y13: 0 | Z13: 0 | AA13: 11 | AB13: 0 | AC13: 0 | AD13: 0 | AE13: 0 | AF13: 0 | AG13: 52 | AH13: 55 | AI13: 11 | AJ13: 132 | AK13: 15 | AL13: 1 | AM13: 41 | AN13: 50 | AO13: 37 | AP13: 1 | AQ13: 11 | AR13: 40 | AS13: 141 | AT13: 53 | AU13: 52 | AV13: 93 | AW13: 104 | AX13: 143 | AY13: 3 | AZ13: 23 | BA13: 0 | BB13: 218 | BC13: 7 | BD13: 2 | BE13: 57 | BF13: 191 | BG13: 6 | BH13: 13 | BI13: 0 | BJ13: 53 | BK13: 136 | BL13: 0 | BM13: 12 | BN13: 12 | BO13: 1 | BP13: 7 | BQ13: 21 | BR13: 2 | BS13: 185 | BT13: 76 | BU13: 90 | BV13: 202 | BW13: 93 | BX13: 1154 | BY13: 12 | BZ13: 2 | CA13: 21 | CB13: 0 | CC13: 1 | CD13: 34 | CE13: 10 | CF13: 90 | CG13: 3 | CH13: 4 | CI13: 2 | CJ13: 41 | CK13: 7 | CL13: 0 | CM13: 29 | CN13: 43 | CO13: 14 | CP13: 4 | CQ13: 0 | CR13: 4 | CS13: 18 | CT13: 28 | CU13: 11 | CV13: 119 | CW13: 8
... A1423: Whole World | B1423: W1 | C1423: 2023 | D1423: 581193 | E1423: 670 | F1423: 8054 | G1423: 4101 | H1423: 3424 | I1423: 6684 | J1423: 13472 | K1423: 2020 | L1423: 5176 | M1423: 3528 | N1423: 4848 | O1423: 11674 | P1423: 5 | Q1423: 1069 | R1423: 260 | S1423: 3593 | T1423: 356 | U1423: 412 | V1423: 902 | W1423: 4275 | X1423: 2203 | Y1423: 1138 | Z1423: 26632 | AA1423: 27991 | AB1423: 21245 | AC1423: 3136 | AD1423: 256 | AE1423: 1526 | AF1423: 466 | AG1423: 11398 | AH1423: 3311 | AI1423: 1724 | AJ1423: 25595 | AK1423: 8352 | AL1423: 1101 | AM1423: 5785 | AN1423: 4209 | AO1423: 7593 | AP1423: 295 | AQ1423: 4171 | AR1423: 3100 | AS1423: 7273 | AT1423: 5577 | AU1423: 6872 | AV1423: 7323 | AW1423: 12647 | AX1423: 13135 | AY1423: 320 | AZ1423: 2060 | BA1423: 23 | BB1423: 26410 | BC1423: 1618 | BD1423: 278 | BE1423: 2918 | BF1423: 7366 | BG1423: 503 | BH1423: 994 | BI1423: 294 | BJ1423: 9534 | BK1423: 12978 | BL1423: 19 | BM1423: 1449 | BN1423: 11709 | BO1423: 1701 | BP1423: 1306 | BQ1423: 16922 | BR1423: 5208 | BS1423: 21329 | BT1423: 7709 | BU1423: 1079 | BV1423: 12839 | BW1423: 11972 | BX1423: 39694 | BY1423: 574 | BZ1423: 633 | CA1423: 11765 | CB1423: 5107 | CC1423: 124 | CD1423: 2259 | CE1423: 608 | CF1423: 5435 | CG1423: 1198 | CH1423: 1371 | CI1423: 2268 | CJ1423: 15722 | CK1423: 4023 | CL1423: 26 | CM1423: 1518 | CN1423: 11993 | CO1423: 2396 | CP1423: 1129 | CQ1423: 40 | CR1423: 1626 | CS1423: 2367 | CT1423: 4163 | CU1423: 714 | CV1423: 14353 | CW1423: 2972

Sheet ONS Pink Book - 9.3
A1: 9.3: Trade in goods and services
A2: All tables in this worksheet are in pounds million.
A3: This worksheet is divided into 3 sections: credits, debits and balance.
A4: These tables refer to CDIDs which stands for Central Database Identifier, the codes used to identify specific datasets.
A5: Table 9.3.1: Exports (Credits), (£ million)
A6: Country | B6: CDID | C6: 1999 | D6: 2000 | E6: 2001 | F6: 2002 | G6: 2003 | H6: 2004 | I6: 2005 | J6: 2006 | K6: 2007 | L6: 2008 | M6: 2009 | N6: 2010 | O6: 2011 | P6: 2012 | Q6: 2013 | R6: 2014 | S6: 2015 | T6: 2016 | U6: 2017 | V6: 2018 | W6: 2019 | X6: 2020 | Y6: 2021 | Z6: 2022 | AA6: 2023
A7: European Union (EU), Austria | B7: LGHT | C7: 1618 | D7: 1608 | E7: 1724 | F7: 1796 | G7: 1822 | H7: 1681 | I7: 1943 | J7: 2343 | K7: 2301 | L7: 2371 | M7: 1996 | N7: 2122 | O7: 2512 | P7: 2423 | Q7: 2530 | R7: 2518 | S7: 2485 | T7: 2876 | U7: 3098 | V7: 3449 | W7: 3515 | X7: 2992 | Y7: 2706 | Z7: 3340 | AA7: 3437
A8: European Union (EU), Belgium | B8: A7RS | C8: 10688 | D8: 11711 | E8: 11463 | F8: 12290 | G8: 13271 | H8: 13043 | I8: 14005 | J8: 15871 | K8: 14992 | L8: 16477 | M8: 14545 | N8: 16764 | O8: 19387 | P8: 18381 | Q8: 17612 | R8: 15762 | S8: 15587 | T8: 16209 | U8: 19551 | V8: 19759 | W8: 18545 | X8: 15840 | Y8: 21726 | Z8: 35303 | AA8: 25681
A9: European Union (EU), Bulgaria | B9: ZWLR | C9: 166 | D9: 185 | E9: 177 | F9: 227 | G9: 260 | H9: 288 | I9: 357 | J9: 392 | K9: 474 | L9: 543 | M9: 511 | N9: 564 | O9: 616 | P9: 691 | Q9: 834 | R9: 872 | S9: 861 | T9: 993 | U9: 1027 | V9: 1091 | W9: 1177 | X9: 854 | Y9: 744 | Z9: 953 | AA9: 918
A10: European Union (EU), Croatia | B10: ZWMC | C10: 93 | D10: 94 | E10: 109 | F10: 156 | G10: 226 | H10: 146 | I10: 139 | J10: 248 | K10: 255 | L10: 289 | M10: 366 | N10: 302 | O10: 249 | P10: 269 | Q10: 276 | R10: 310 | S10: 317 | T10: 340 | U10: 459 | V10: 572 | W10: 480 | X10: 436 | Y10: 339 | Z10: 433 | AA10: 598
A11: European Union (EU), Cyprus | B11: A7RT | C11: 559 | D11: 654 | E11: 657 | F11: 683 | G11: 697 | H11: 817 | I11: 934 | J11: 1732 | K11: 1289 | L11: 1430 | M11: 1422 | N11: 1374 | O11: 1693 | P11: 1478 | Q11: 1826 | R11: 1468 | S11: 1376 | T11: 1605 | U11: 1659 | V11: 1554 | W11: 1812 | X11: 1537 | Y11: 1426 | Z11: 1666 | AA11: 1915
A12: European Union (EU), Czech Republic | B12: LGIN | C12: 919 | D12: 1165 | E12: 1319 | F12: 1237 | G12: 1277 | H12: 1370 | I12: 1549 | J12: 2077 | K12: 2016 | L12: 2041 | M12: 1954 | N12: 2317 | O12: 2538 | P12: 2389 | Q12: 2682 | R12: 2844 | S12: 2784 | T12: 3061 | U12: 3243 | V12: 3314 | W12: 3497 | X12: 2940 | Y12: 2691 | Z12: 3275 | AA12: 3633
A13: European Union (EU), Denmark | B13: LGHV | C13: 3199 | D13: 3650 | E13: 4057 | F13: 4448 | G13: 4051 | H13: 3795 | I13: 4105 | J13: 6470 | K13: 4305 | L13: 4926 | M13: 5159 | N13: 5643 | O13: 6304 | P13: 6120 | Q13: 6253 | R13: 5842 | S13: 5216 | T13: 5881 | U13: 6443 | V13: 6756 | W13: 6715 | X13: 6453 | Y13: 7000 | Z13: 8257 | AA13: 8284
A14: European Union (EU), Estonia | B14: ZWLX | C14: 59 | D14: 76 | E14: 88 | F14: 101 | G14: 101 | H14: 109 | I14: 123 | J14: 499 | K14: 271 | L14: 280 | M14: 174 | N14: 247 | O14: 373 | P14: 415 | Q14: 459 | R14: 397 | S14: 356 | T14: 357 | U14: 398 | V14: 383 | W14: 405 | X14: 420 | Y14: 374 | Z14: 448 | AA14: 503
A15: European Union (EU), Finland | B15: LGHW | C15: 2003 | D15: 2303 | E15: 2392 | F15: 2177 | G15: 2294 | H15: 2227 | I15: 2389 | J15: 2918 | K15: 3324 | L15: 3194 | M15: 2676 | N15: 2892 | O15: 3162 | P15: 3062 | Q15: 2912 | R15: 3071 | S15: 2637 | T15: 2546 | U15: 2732 | V15: 2955 | W15: 3243 | X15: 2736 | Y15: 2480 | Z15: 3056 | AA15: 3125
A16: European Union (EU), France | B16: LGHX | C16: 22101 | D16: 24161 | E16: 25997 | F16: 25747 | G16: 26380 | H16: 26369 | I16: 28288 | J16: 38538 | K16: 27111 | L16: 28084 | M16: 27019 | N16: 29037 | O16: 32778 | P16: 32223 | Q16: 32675 | R16: 30215 | S16: 30136 | T16: 33196 | U16: 38687 | V16: 40056 | W16: 40279 | X16: 31789 | Y16: 32662 | Z16: 44259 | AA16: 44647
A17: European Union (EU), Germany | B17: LGHY | C17: 26254 | D17: 29321 | E17: 30059 | F17: 28604 | G17: 27925 | H17: 29718 | I17: 31934 | J17: 37300 | K17: 34997 | L17: 40002 | M17: 35898 | N17: 39684 | O17: 46594 | P17: 45509 | Q17: 44069 | R17: 45068 | S17: 44919 | T17: 49453 | U17: 56889 | V17: 56430 | W17: 56518 | X17: 50275 | Y17: 49589 | Z17: 57491 | AA17: 62982
A18: European Union (EU), Greece | B18: LGHZ | C18: 2868 | D18: 3045 | E18: 2910 | F18: 3022 | G18: 3041 | H18: 3074 | I18: 3037 | J18: 3052 | K18: 3108 | L18: 3403 | M18: 3202 | N18: 2937 | O18: 2702 | P18: 2428 | Q18: 2846 | R18: 3652 | S18: 2649 | T18: 2782 | U18: 3197 | V18: 3773 | W18: 3274 | X18: 2473 | Y18: 2460 | Z18: 3235 | AA18: 3822
... A94: World total | B94: KTMW | C94: 253565 | D94: 282451 | E94: 292805 | F94: 292026 | G94: 302711 | H94: 318389 | I94: 353485 | J94: 404989 | K94: 394061 | L94: 438335 | M94: 416342 | N94: 464176 | O94: 521847 | P94: 524715 | Q94: 539564 | R94: 532236 | S94: 533654 | T94: 575632 | U94: 643286 | V94: 679700 | W94: 706696 | X94: 624100 | Y94: 666886 | Z94: 848051 | AA94: 861234
A96: Table 9.3.2: Imports (Debits), (£ million)
A97: Country | B97: CDID | C97: 1999 | D97: 2000 | E97: 2001 | F97: 2002 | G97: 2003 | H97: 2004 | I97: 2005 | J97: 2006 | K97: 2007 | L97: 2008 | M97: 2009 | N97: 2010 | O97: 2011 | P97: 2012 | Q97: 2013 | R97: 2014 | S97: 2015 | T97: 2016 | U97: 2017 | V97: 2018 | W97: 2019 | X97: 2020 | Y97: 2021 | Z97: 2022 | AA97: 2023
A98: European Union (EU), Austria | B98: LGJY | C98: 1987 | D98: 1971 | E98: 2798 | F98: 3978 | G98: 4044 | H98: 3301 | I98: 3144 | J98: 3541 | K98: 3334 | L98: 3280 | M98: 3320 | N98: 3734 | O98: 3802 | P98: 3472 | Q98: 3841 | R98: 4007 | S98: 3997 | T98: 4526 | U98: 4401 | V98: 5611 | W98: 6018 | X98: 4797 | Y98: 4807 | Z98: 5710 | AA98: 6277
A99: European Union (EU), Belgium | B99: A8EO | C99: 11259 | D99: 11867 | E99: 13592 | F99: 14315 | G99: 14688 | H99: 14973 | I99: 15514 | J99: 16598 | K99: 17013 | L99: 18445 | M99: 17027 | N99: 18887 | O99: 20865 | P99: 20299 | Q99: 22959 | R99: 23370 | S99: 23357 | T99: 25969 | U99: 27935 | V99: 28634 | W99: 28172 | X99: 24893 | Y99: 26141 | Z99: 32441 | AA99: 31713
A100: European Union (EU), Bulgaria | B100: ZWNX | C100: 124 | D100: 147 | E100: 165 | F100: 208 | G100: 228 | H100: 366 | I100: 501 | J100: 498 | K100: 524 | L100: 585 | M100: 453 | N100: 524 | O100: 721 | P100: 656 | Q100: 798 | R100: 814 | S100: 821 | T100: 1039 | U100: 1238 | V100: 1491 | W100: 1634 | X100: 1144 | Y100: 1350 | Z100: 1955 | AA100: 2137
A101: European Union (EU), Croatia | B101: ZWOI | C101: 53 | D101: 75 | E101: 95 | F101: 93 | G101: 138 | H101: 138 | I101: 179 | J101: 293 | K101: 231 | L101: 476 | M101: 304 | N101: 363 | O101: 412 | P101: 362 | Q101: 534 | R101: 423 | S101: 555 | T101: 615 | U101: 918 | V101: 964 | W101: 1227 | X101: 567 | Y101: 676 | Z101: 1286 | AA101: 1313
A102: European Union (EU), Cyprus | B102: A8EP | C102: 1110 | D102: 1262 | E102: 1485 | F102: 1403 | G102: 1570 | H102: 1504 | I102: 1646 | J102: 4021 | K102: 1533 | L102: 1316 | M102: 1126 | N102: 1144 | O102: 1313 | P102: 1298 | Q102: 1189 | R102: 1007 | S102: 1167 | T102: 1242 | U102: 1393 | V102: 1326 | W102: 1923 | X102: 1141 | Y102: 1268 | Z102: 1373 | AA102: 1545
A103: European Union (EU), Czech Republic | B103: LGKS | C103: 801 | D103: 1128 | E103: 1502 | F103: 1804 | G103: 2042 | H103: 1912 | I103: 2590 | J103: 3135 | K103: 3614 | L103: 4127 | M103: 3963 | N103: 4675 | O103: 5056 | P103: 5182 | Q103: 5218 | R103: 5248 | S103: 5444 | T103: 6073 | U103: 6463 | V103: 6885 | W103: 7271 | X103: 5336 | Y103: 5576 | Z103: 6140 | AA103: 6075
A104: European Union (EU), Denmark | B104: LGKA | C104: 2975 | D104: 3168 | E104: 3608 | F104: 3747 | G104: 3822 | H104: 3936 | I104: 5445 | J104: 7443 | K104: 4344 | L104: 4955 | M104: 4886 | N104: 5281 | O104: 7262 | P104: 7042 | Q104: 6906 | R104: 5891 | S104: 4764 | T104: 5394 | U104: 6523 | V104: 8341 | W104: 8277 | X104: 6483 | Y104: 7423 | Z104: 7635 | AA104: 8603
A105: European Union (EU), Estonia | B105: ZWOD | C105: 210 | D105: 371 | E105: 314 | F105: 409 | G105: 320 | H105: 456 | I105: 448 | J105: 649 | K105: 300 | L105: 209 | M105: 152 | N105: 193 | O105: 292 | P105: 264 | Q105: 216 | R105: 216 | S105: 250 | T105: 298 | U105: 296 | V105: 296 | W105: 344 | X105: 274 | Y105: 469 | Z105: 615 | AA105: 522
A106: European Union (EU), Finland | B106: LGKB | C106: 2665 | D106: 3238 | E106: 4357 | F106: 4997 | G106: 3688 | H106: 3065 | I106: 3428 | J106: 3869 | K106: 3017 | L106: 3083 | M106: 2518 | N106: 2611 | O106: 3000 | P106: 2791 | Q106: 3065 | R106: 2920 | S106: 2563 | T106: 2695 | U106: 2856 | V106: 3098 | W106: 3048 | X106: 3242 | Y106: 2806 | Z106: 4227 | AA106: 3135
A107: European Union (EU), France | B107: LGKC | C107: 26339 | D107: 27191 | E107: 29019 | F107: 29976 | G107: 30918 | H107: 30480 | I107: 31045 | J107: 33472 | K107: 33159 | L107: 34085 | M107: 31293 | N107: 32084 | O107: 33729 | P107: 33997 | Q107: 34751 | R107: 35423 | S107: 34824 | T107: 36708 | U107: 39990 | V107: 43714 | W107: 44919 | X107: 34502 | Y107: 33201 | Z107: 50831 | AA107: 60230
A108: European Union (EU), Germany | B108: LGKD | C108: 31155 | D108: 32253 | E108: 35868 | F108: 38869 | G108: 39547 | H108: 41368 | I108: 46068 | J108: 50753 | K108: 53024 | L108: 55509 | M108: 50131 | N108: 56084 | O108: 60041 | P108: 62378 | Q108: 65588 | R108: 69958 | S108: 70324 | T108: 74643 | U108: 80837 | V108: 80874 | W108: 78095 | X108: 67188 | Y108: 68084 | Z108: 79878 | AA108: 87621
A109: European Union (EU), Greece | B109: LGKE | C109: 2170 | D109: 2352 | E109: 2722 | F109: 2925 | G109: 3094 | H109: 3093 | I109: 3040 | J109: 3087 | K109: 2786 | L109: 2766 | M109: 2731 | N109: 2713 | O109: 2909 | P109: 2816 | Q109: 2884 | R109: 3000 | S109: 3271 | T109: 3785 | U109: 3940 | V109: 4377 | W109: 4629 | X109: 2443 | Y109: 3424 | Z109: 6566 | AA109: 7333
... A185: World total | B185: KTMX | C185: 264214 | D185: 295683 | E185: 312602 | F185: 320131 | G185: 329470 | H185: 348904 | I185: 383386 | J185: 432813 | K185: 424046 | L185: 465214 | M185: 435567 | N185: 489258 | O185: 534985 | P185: 541661 | Q185: 564864 | R185: 568413 | S185: 562624 | T185: 613388 | U185: 671211 | V185: 709454 | W185: 737872 | X185: 612353 | Y185: 672005 | Z185: 892166 | AA185: 876290
A187: Table 9.3.3: Balances (£ million)
A188: Country | B188: CDID | C188: 1999 | D188: 2000 | E188: 2001 | F188: 2002 | G188: 2003 | H188: 2004 | I188: 2005 | J188: 2006 | K188: 2007 | L188: 2008 | M188: 2009 | N188: 2010 | O188: 2011 | P188: 2012 | Q188: 2013 | R188: 2014 | S188: 2015 | T188: 2016 | U188: 2017 | V188: 2018 | W188: 2019 | X188: 2020 | Y188: 2021 | Z188: 2022 | AA188: 2023
A189: European Union (EU), Austria | B189: LGMD | C189: -369 | D189: -363 | E189: -1074 | F189: -2182 | G189: -2222 | H189: -1620 | I189: -1201 | J189: -1198 | K189: -1033 | L189: -909 | M189: -1324 | N189: -1612 | O189: -1290 | P189: -1049 | Q189: -1311 | R189: -1489 | S189: -1512 | T189: -1650 | U189: -1303 | V189: -2162 | W189: -2503 | X189: -1805 | Y189: -2101 | Z189: -2370 | AA189: -2840
A190: European Union (EU), Belgium | B190: A8HC | C190: -571 | D190: -156 | E190: -2129 | F190: -2025 | G190: -1417 | H190: -1930 | I190: -1509 | J190: -727 | K190: -2021 | L190: -1968 | M190: -2482 | N190: -2123 | O190: -1478 | P190: -1918 | Q190: -5347 | R190: -7608 | S190: -7770 | T190: -9760 | U190: -8384 | V190: -8875 | W190: -9627 | X190: -9053 | Y190: -4415 | Z190: 2862 | AA190: -6032
A191: European Union (EU), Bulgaria | B191: ZWSK | C191: 42 | D191: 38 | E191: 12 | F191: 19 | G191: 32 | H191: -78 | I191: -144 | J191: -106 | K191: -50 | L191: -42 | M191: 58 | N191: 40 | O191: -105 | P191: 35 | Q191: 36 | R191: 58 | S191: 40 | T191: -46 | U191: -211 | V191: -400 | W191: -457 | X191: -290 | Y191: -606 | Z191: -1002 | AA191: -1219
A192: European Union (EU), Croatia | B192: ZWSV | C192: 40 | D192: 19 | E192: 14 | F192: 63 | G192: 88 | H192: 8 | I192: -40 | J192: -45 | K192: 24 | L192: -187 | M192: 62 | N192: -61 | O192: -163 | P192: -93 | Q192: -258 | R192: -113 | S192: -238 | T192: -275 | U192: -459 | V192: -392 | W192: -747 | X192: -131 | Y192: -337 | Z192: -853 | AA192: -715
A193: European Union (EU), Cyprus | B193: A8HD | C193: -551 | D193: -608 | E193: -828 | F193: -720 | G193: -873 | H193: -687 | I193: -712 | J193: -2289 | K193: -244 | L193: 114 | M193: 296 | N193: 230 | O193: 380 | P193: 180 | Q193: 637 | R193: 461 | S193: 209 | T193: 363 | U193: 266 | V193: 228 | W193: -111 | X193: 396 | Y193: 158 | Z193: 293 | AA193: 370
A194: European Union (EU), Czech Republic | B194: LGMX | C194: 118 | D194: 37 | E194: -183 | F194: -567 | G194: -765 | H194: -542 | I194: -1041 | J194: -1058 | K194: -1598 | L194: -2086 | M194: -2009 | N194: -2358 | O194: -2518 | P194: -2793 | Q194: -2536 | R194: -2404 | S194: -2660 | T194: -3012 | U194: -3220 | V194: -3571 | W194: -3774 | X194: -2396 | Y194: -2885 | Z194: -2865 | AA194: -2442
A195: European Union (EU), Denmark | B195: LGMF | C195: 224 | D195: 482 | E195: 449 | F195: 701 | G195: 229 | H195: -141 | I195: -1340 | J195: -973 | K195: -39 | L195: -29 | M195: 273 | N195: 362 | O195: -958 | P195: -922 | Q195: -653 | R195: -49 | S195: 452 | T195: 487 | U195: -80 | V195: -1585 | W195: -1562 | X195: -30 | Y195: -423 | Z195: 622 | AA195: -319
A196: European Union (EU), Estonia | B196: ZWSQ | C196: -151 | D196: -295 | E196: -226 | F196: -308 | G196: -219 | H196: -347 | I196: -325 | J196: -150 | K196: -29 | L196: 71 | M196: 22 | N196: 54 | O196: 81 | P196: 151 | Q196: 243 | R196: 181 | S196: 106 | T196: 59 | U196: 102 | V196: 87 | W196: 61 | X196: 146 | Y196: -95 | Z196: -167 | AA196: -19
A197: European Union (EU), Finland | B197: LGMG | C197: -662 | D197: -935 | E197: -1965 | F197: -2820 | G197: -1394 | H197: -838 | I197: -1039 | J197: -951 | K197: 307 | L197: 111 | M197: 158 | N197: 281 | O197: 162 | P197: 271 | Q197: -153 | R197: 151 | S197: 74 | T197: -149 | U197: -124 | V197: -143 | W197: 195 | X197: -506 | Y197: -326 | Z197: -1171 | AA197: -10
A198: European Union (EU), France | B198: LGMH | C198: -4238 | D198: -3030 | E198: -3022 | F198: -4229 | G198: -4538 | H198: -4111 | I198: -2757 | J198: 5066 | K198: -6048 | L198: -6001 | M198: -4274 | N198: -3047 | O198: -951 | P198: -1774 | Q198: -2076 | R198: -5208 | S198: -4688 | T198: -3512 | U198: -1303 | V198: -3658 | W198: -4640 | X198: -2713 | Y198: -539 | Z198: -6572 | AA198: -15583
A199: European Union (EU), Germany | B199: LGMI | C199: -4901 | D199: -2932 | E199: -5809 | F199: -10265 | G199: -11622 | H199: -11650 | I199: -14134 | J199: -13453 | K199: -18027 | L199: -15507 | M199: -14233 | N199: -16400 | O199: -13447 | P199: -16869 | Q199: -21519 | R199: -24890 | S199: -25405 | T199: -25190 | U199: -23948 | V199: -24444 | W199: -21577 | X199: -16913 | Y199: -18495 | Z199: -22387 | AA199: -24639
A200: European Union (EU), Greece | B200: LGMJ | C200: 698 | D200: 693 | E200: 188 | F200: 97 | G200: -53 | H200: -19 | I200: -3 | J200: -35 | K200: 322 | L200: 637 | M200: 471 | N200: 224 | O200: -207 | P200: -388 | Q200: -38 | R200: 652 | S200: -622 | T200: -1003 | U200: -743 | V200: -604 | W200: -1355 | X200: 30 | Y200: -964 | Z200: -3331 | AA200: -3511
... A276: World total | B276: KTMY | C276: -10649 | D276: -13232 | E276: -19797 | F276: -28105 | G276: -26759 | H276: -30515 | I276: -29901 | J276: -27824 | K276: -29985 | L276: -26879 | M276: -19225 | N276: -25082 | O276: -13138 | P276: -16946 | Q276: -25300 | R276: -36177 | S276: -28970 | T276: -37756 | U276: -27925 | V276: -29754 | W276: -31176 | X276: 11747 | Y276: -5119 | Z276: -44115 | AA276: -15056

Sheet ONS Pink Book - 9.4
A1: 9.4: Trade in goods
A2: All tables in this worksheet are in pounds million.
A3: This worksheet is divided into 3 sections: credits, debits and balance.
A4: These tables refer to CDIDs which stands for Central Database Identifier, the codes used to identify specific datasets.
A5: Table 9.4.1: Exports (Credits), (£ million)
A6: Country | B6: CDID | C6: 1999 | D6: 2000 | E6: 2001 | F6: 2002 | G6: 2003 | H6: 2004 | I6: 2005 | J6: 2006 | K6: 2007 | L6: 2008 | M6: 2009 | N6: 2010 | O6: 2011 | P6: 2012 | Q6: 2013 | R6: 2014 | S6: 2015 | T6: 2016 | U6: 2017 | V6: 2018 | W6: 2019 | X6: 2020 | Y6: 2021 | Z6: 2022 | AA6: 2023
A7: European Union (EU), Austria | B7: QBRY | C7: 1160 | D7: 1118 | E7: 1255 | F7: 1282 | G7: 1281 | H7: 1110 | I7: 1342 | J7: 1702 | K7: 1410 | L7: 1479 | M7: 1297 | N7: 1478 | O7: 1705 | P7: 1563 | Q7: 1657 | R7: 1661 | S7: 1569 | T7: 1808 | U7: 1875 | V7: 2069 | W7: 1939 | X7: 1783 | Y7: 1614 | Z7: 1837 | AA7: 1722
A8: European Union (EU), Belgium | B8: QDOH | C8: 8732 | D8: 9598 | E8: 9460 | F8: 9995 | G8: 10815 | H8: 10283 | I8: 11197 | J8: 13270 | K8: 12036 | L8: 13388 | M8: 10828 | N8: 13262 | O8: 15798 | P8: 14378 | Q8: 13823 | R8: 12179 | S8: 11719 | T8: 11768 | U8: 14162 | V8: 14562 | W8: 13194 | X8: 11057 | Y8: 16398 | Z8: 29133 | AA8: 17637
A9: European Union (EU), Bulgaria | B9: QAMF | C9: 76 | D9: 89 | E9: 123 | F9: 134 | G9: 156 | H9: 155 | I9: 220 | J9: 219 | K9: 207 | L9: 257 | M9: 206 | N9: 254 | O9: 335 | P9: 321 | Q9: 419 | R9: 461 | S9: 347 | T9: 501 | U9: 460 | V9: 463 | W9: 398 | X9: 390 | Y9: 291 | Z9: 389 | AA9: 396
A10: European Union (EU), Croatia | B10: QAMM | C10: 80 | D10: 78 | E10: 89 | F10: 93 | G10: 160 | H10: 129 | I10: 117 | J10: 145 | K10: 164 | L10: 206 | M10: 213 | N10: 175 | O10: 152 | P10: 153 | Q10: 120 | R10: 153 | S10: 147 | T10: 174 | U10: 205 | V10: 277 | W10: 230 | X10: 231 | Y10: 153 | Z10: 180 | AA10: 182
A11: European Union (EU), Cyprus | B11: QDNZ | C11: 258 | D11: 321 | E11: 293 | F11: 276 | G11: 317 | H11: 329 | I11: 366 | J11: 1060 | K11: 409 | L11: 536 | M11: 623 | N11: 562 | O11: 683 | P11: 470 | Q11: 445 | R11: 453 | S11: 369 | T11: 321 | U11: 383 | V11: 398 | W11: 450 | X11: 471 | Y11: 315 | Z11: 356 | AA11: 446
A12: European Union (EU), Czech Republic | B12: QDLF | C12: 736 | D12: 950 | E12: 1071 | F12: 1032 | G12: 1012 | H12: 987 | I12: 1087 | J12: 1610 | K12: 1441 | L12: 1567 | M12: 1466 | N12: 1847 | O12: 1957 | P12: 1786 | Q12: 1999 | R12: 2136 | S12: 2006 | T12: 2192 | U12: 2212 | V12: 2373 | W12: 2372 | X12: 2156 | Y12: 1930 | Z12: 2268 | AA12: 2350
A13: European Union (EU), Denmark | B13: QBSE | C13: 2062 | D13: 2300 | E13: 2334 | F13: 2810 | G13: 2233 | H13: 2056 | I13: 2326 | J13: 3886 | K13: 2198 | L13: 2597 | M13: 2486 | N13: 2755 | O13: 3013 | P13: 2832 | Q13: 3008 | R13: 2898 | S13: 2294 | T13: 2459 | U13: 2833 | V13: 2799 | W13: 2737 | X13: 2397 | Y13: 2596 | Z13: 3128 | AA13: 2752
A14: European Union (EU), Estonia | B14: QAMN | C14: 52 | D14: 68 | E14: 78 | F14: 93 | G14: 85 | H14: 98 | I14: 110 | J14: 472 | K14: 233 | L14: 221 | M14: 140 | N14: 194 | O14: 280 | P14: 291 | Q14: 345 | R14: 276 | S14: 221 | T14: 236 | U14: 260 | V14: 274 | W14: 259 | X14: 232 | Y14: 256 | Z14: 320 | AA14: 333
A15: European Union (EU), Finland | B15: QBSH | C15: 1348 | D15: 1423 | E15: 1603 | F15: 1434 | G15: 1454 | H15: 1373 | I15: 1522 | J15: 1845 | K15: 1992 | L15: 1998 | M15: 1326 | N15: 1495 | O15: 1659 | P15: 1551 | Q15: 1561 | R15: 1620 | S15: 1318 | T15: 1308 | U15: 1362 | V15: 1433 | W15: 1358 | X15: 1263 | Y15: 1019 | Z15: 1535 | AA15: 1435
A16: European Union (EU), France | B16: QDJA | C16: 16635 | D16: 18085 | E16: 19336 | F16: 19185 | G16: 19288 | H16: 18629 | I16: 20420 | J16: 29606 | K16: 17505 | L16: 18057 | M16: 17275 | N16: 19147 | O16: 21937 | P16: 20919 | Q16: 21038 | R16: 18712 | S16: 17626 | T16: 19669 | U16: 23659 | V16: 24088 | W16: 24767 | X16: 18728 | Y16: 19694 | Z16: 25954 | AA16: 24802
A17: European Union (EU), Germany | B17: QDJD | C17: 20261 | D17: 22513 | E17: 22748 | F17: 21105 | G17: 19770 | H17: 21090 | I17: 22365 | J17: 27048 | K17: 24275 | L17: 28101 | M17: 24641 | N17: 28087 | O17: 34148 | P17: 32545 | Q17: 29785 | R17: 31111 | S17: 30541 | T17: 32434 | U17: 36655 | V17: 36469 | W17: 37065 | X17: 32916 | Y17: 30111 | Z17: 33879 | AA17: 33775
A18: European Union (EU), Greece | B18: QDJG | C18: 1159 | D18: 1248 | E18: 1192 | F18: 1353 | G18: 1412 | H18: 1550 | I18: 1370 | J18: 1527 | K18: 1599 | L18: 1763 | M18: 1680 | N18: 1421 | O18: 1175 | P18: 931 | Q18: 1215 | R18: 1975 | S18: 972 | T18: 969 | U18: 1212 | V18: 1695 | W18: 1135 | X18: 1046 | Y18: 838 | Z18: 1039 | AA18: 1266
... A57: Americas, Mexico | B57: QDLX | C57: 597 | D57: 585 | E57: 689 | F57: 726 | G57: 736 | H57: 663 | I57: 672 | J57: 788 | K57: 819 | L57: 918 | M57: 744 | N57: 951 | O57: 973 | P57: 1119 | Q57: 1118 | R57: 1047 | S57: 1304 | T57: 1301 | U57: 1633 | V57: 1728 | W57: 1437 | X57: 1095 | Y57: 1153 | Z57: 1465 | AA57: 1750
A58: Americas, United States of America | B58: J8V9 | C58: 25385 | D58: 29869 | E58: 30157 | F58: 28366 | G58: 28105 | H58: 27773 | I58: 30993 | J58: 31742 | K58: 31689 | L58: 34620 | M58: 33309 | N58: 37023 | O58: 39323 | P58: 40222 | Q58: 38634 | R58: 37898 | S58: 45434 | T58: 47364 | U58: 48623 | V58: 52715 | W58: 58893 | X58: 47423 | Y58: 49720 | Z58: 59940 | AA58: 60432 | AC58: Share of total exports | AD58: =100*(Table_9.4.1_credits[[#This Row],[2023]]/AA94) -> 15.356936
A59: Americas, Uruguay | B59: QAMU | C59: 65 | D59: 62 | E59: 49 | F59: 30 | G59: 33 | H59: 31 | I59: 39 | J59: 42 | K59: 37 | L59: 62 | M59: 56 | N59: 76 | O59: 117 | P59: 110 | Q59: 163 | R59: 116 | S59: 246 | T59: 152 | U59: 191 | V59: 143 | W59: 139 | X59: 87 | Y59: 99 | Z59: 130 | AA59: 145 | AC59: GDP! | AD59: 2711185
A60: Americas, Venezuela | B60: QAMV | C60: 209 | D60: 232 | E60: 318 | F60: 239 | G60: 149 | H60: 199 | I60: 239 | J60: 237 | K60: 254 | L60: 268 | M60: 284 | N60: 263 | O60: 308 | P60: 378 | Q60: 298 | R60: 204 | S60: 219 | T60: 110 | U60: 75 | V60: 83 | W60: 24 | X60: 10 | Y60: 15 | Z60: 26 | AA60: 19 | AC60: Share of GDP | AD60: =100*(AA58/AD59) -> 2.2289884
A61: Americas, Other Central American Countries | B61: BOQQ | C61: 928 | D61: 972 | E61: 683 | F61: 714 | G61: 701 | H61: 615 | I61: 702 | J61: 847 | K61: 817 | L61: 1059 | M61: 714 | N61: 856 | O61: 917 | P61: 1121 | Q61: 830 | R61: 767 | S61: 972 | T61: 1177 | U61: 1048 | V61: 1005 | W61: 935 | X61: 1025 | Y61: 1133 | Z61: 2155 | AA61: 1152
A62: Americas, Other | B62: BOQT | C62: 161 | D62: 165 | E62: 163 | F62: 163 | G62: 170 | H62: 150 | I62: 157 | J62: 169 | K62: 188 | L62: 238 | M62: 229 | N62: 355 | O62: 463 | P62: 614 | Q62: 559 | R62: 432 | S62: 480 | T62: 345 | U62: 438 | V62: 457 | W62: 455 | X62: 372 | Y62: 428 | Z62: 614 | AA62: 654
A63: Total Americas | B63: EPLO | C63: 31029 | D63: 36292 | E63: 36166 | F63: 34348 | G63: 34092 | H63: 33708 | I63: 37223 | J63: 38968 | K63: 38644 | L63: 42965 | M63: 41434 | N63: 47051 | O63: 51249 | P63: 51730 | Q63: 50135 | R63: 47872 | S63: 55969 | T63: 58291 | U63: 60662 | V63: 65547 | W63: 71557 | X63: 59286 | Y63: 61897 | Z63: 74746 | AA63: 75417
A64: Asia, China | B64: QDMA | C64: 1386 | D64: 1706 | E64: 1854 | F64: 1575 | G64: 2055 | H64: 2845 | I64: 3053 | J64: 3688 | K64: 4820 | L64: 6106 | M64: 5616 | N64: 8090 | O64: 10336 | P64: 11232 | Q64: 12141 | R64: 14125 | S64: 12376 | T64: 13606 | U64: 18031 | V64: 18735 | W64: 26679 | X64: 17986 | Y64: 18959 | Z64: 29369 | AA64: 21881
A65: Asia, Hong Kong | B65: QDMD | C65: 2504 | D65: 2935 | E65: 2971 | F65: 2686 | G65: 2819 | H65: 2846 | I65: 3327 | J65: 3105 | K65: 2955 | L65: 3872 | M65: 3839 | N65: 4531 | O65: 5594 | P65: 5502 | Q65: 5965 | R65: 5167 | S65: 5506 | T65: 6277 | U65: 7258 | V65: 7766 | W65: 8105 | X65: 7982 | Y65: 7324 | Z65: 12874 | AA65: 9781
A66: Asia, India | B66: QDMG | C66: 1537 | D66: 2155 | E66: 1765 | F66: 1674 | G66: 2232 | H66: 2456 | I66: 2802 | J66: 2894 | K66: 3722 | L66: 4812 | M66: 2997 | N66: 4467 | O66: 6375 | P66: 5252 | Q66: 4951 | R66: 4008 | S66: 3933 | T66: 3367 | U66: 4229 | V66: 5207 | W66: 4636 | X66: 3229 | Y66: 4780 | Z66: 6249 | AA66: 5991
A67: Asia, Indonesia | B67: QDMJ | C67: 277 | D67: 324 | E67: 325 | F67: 317 | G67: 461 | H67: 405 | I67: 370 | J67: 308 | K67: 276 | L67: 377 | M67: 362 | N67: 513 | O67: 635 | P67: 637 | Q67: 704 | R67: 525 | S67: 467 | T67: 549 | U67: 840 | V67: 773 | W67: 688 | X67: 584 | Y67: 754 | Z67: 868 | AA67: 913
A68: Asia, Iran | B68: QAON | C68: 251 | D68: 306 | E68: 440 | F68: 416 | G68: 496 | H68: 460 | I68: 478 | J68: 448 | K68: 411 | L68: 422 | M68: 386 | N68: 288 | O68: 183 | P68: 100 | Q68: 79 | R68: 95 | S68: 92 | T68: 148 | U68: 236 | V68: 173 | W68: 83 | X68: 62 | Y68: 70 | Z68: 64 | AA68: 68
A69: Asia, Israel | B69: QDMM | C69: 1290 | D69: 1502 | E69: 1342 | F69: 1408 | G69: 1312 | H69: 1363 | I69: 1330 | J69: 1269 | K69: 1220 | L69: 1243 | M69: 1045 | N69: 1295 | O69: 1514 | P69: 1372 | Q69: 1322 | R69: 1065 | S69: 1010 | T69: 1131 | U69: 1256 | V69: 1240 | W69: 1413 | X69: 1683 | Y69: 1533 | Z69: 1851 | AA69: 1613
A70: Asia, Japan | B70: QAMJ | C70: 3358 | D70: 3796 | E70: 3767 | F70: 3629 | G70: 3732 | H70: 3869 | I70: 3876 | J70: 4033 | K70: 3842 | L70: 3791 | M70: 3571 | N70: 4224 | O70: 4693 | P70: 4963 | Q70: 4996 | R70: 4568 | S70: 4367 | T70: 4871 | U70: 5957 | V70: 6908 | W70: 7046 | X70: 6341 | Y70: 6716 | Z70: 7034 | AA70: 6572
A71: Asia, Malaysia | B71: QDMP | C71: 747 | D71: 927 | E71: 1038 | F71: 880 | G71: 936 | H71: 933 | I71: 849 | J71: 837 | K71: 949 | L71: 1129 | M71: 1024 | N71: 1252 | O71: 1432 | P71: 1497 | Q71: 1626 | R71: 1516 | S71: 1365 | T71: 1494 | U71: 1515 | V71: 1349 | W71: 1393 | X71: 1416 | Y71: 1687 | Z71: 1843 | AA71: 1734
A72: Asia, Pakistan | B72: QDMS | C72: 221 | D72: 212 | E72: 241 | F72: 256 | G72: 293 | H72: 347 | I72: 474 | J72: 474 | K72: 409 | L72: 471 | M72: 465 | N72: 444 | O72: 533 | P72: 564 | Q72: 478 | R72: 523 | S72: 525 | T72: 639 | U72: 720 | V72: 781 | W72: 814 | X72: 602 | Y72: 727 | Z72: 667 | AA72: 486
... A94: World total | B94: LQAD | C94: 166343 | D94: 186824 | E94: 190682 | F94: 187459 | G94: 187883 | H94: 191062 | I94: 212494 | J94: 246418 | K94: 222825 | L94: 252593 | M94: 227951 | N94: 265896 | O94: 302569 | P94: 298431 | Q94: 299730 | R94: 289173 | S94: 280904 | T94: 299398 | U94: 339925 | V94: 354004 | W94: 368203 | X94: 313750 | Y94: 332135 | Z94: 434123 | AA94: 393516
A96: Table 9.4.2: Imports (Debits), (£ million)
A97: Country | B97: CDID | C97: 1999 | D97: 2000 | E97: 2001 | F97: 2002 | G97: 2003 | H97: 2004 | I97: 2005 | J97: 2006 | K97: 2007 | L97: 2008 | M97: 2009 | N97: 2010 | O97: 2011 | P97: 2012 | Q97: 2013 | R97: 2014 | S97: 2015 | T97: 2016 | U97: 2017 | V97: 2018 | W97: 2019 | X97: 2020 | Y97: 2021 | Z97: 2022 | AA97: 2023
A98: European Union (EU), Austria | B98: QBRZ | C98: 1488 | D98: 1438 | E98: 2247 | F98: 3192 | G98: 3320 | H98: 2442 | I98: 2243 | J98: 2636 | K98: 2507 | L98: 2395 | M98: 2409 | N98: 2688 | O98: 2993 | P98: 2677 | Q98: 2890 | R98: 3043 | S98: 3012 | T98: 3199 | U98: 3313 | V98: 4451 | W98: 4728 | X98: 4086 | Y98: 4165 | Z98: 4392 | AA98: 4713
A99: European Union (EU), Belgium | B99: QDOI | C99: 9872 | D99: 10590 | E99: 12151 | F99: 12548 | G99: 12894 | H99: 13164 | I99: 13690 | J99: 14792 | K99: 14918 | L99: 16218 | M99: 14938 | N99: 17005 | O99: 18819 | P99: 18195 | Q99: 20484 | R99: 21093 | S99: 20757 | T99: 23564 | U99: 25229 | V99: 25880 | W99: 25253 | X99: 22685 | Y99: 24256 | Z99: 29860 | AA99: 29199
A100: European Union (EU), Bulgaria | B100: QAMZ | C100: 82 | D100: 99 | E100: 113 | F100: 132 | G100: 135 | H100: 156 | I100: 173 | J100: 210 | K100: 232 | L100: 204 | M100: 175 | N100: 222 | O100: 282 | P100: 293 | Q100: 372 | R100: 353 | S100: 364 | T100: 412 | U100: 451 | V100: 513 | W100: 603 | X100: 471 | Y100: 481 | Z100: 713 | AA100: 696
A101: European Union (EU), Croatia | B101: QANC | C101: 45 | D101: 46 | E101: 57 | F101: 52 | G101: 53 | H101: 56 | I101: 58 | J101: 77 | K101: 79 | L101: 119 | M101: 85 | N101: 104 | O101: 128 | P101: 88 | Q101: 178 | R101: 67 | S101: 95 | T101: 127 | U101: 220 | V101: 202 | W101: 437 | X101: 280 | Y101: 224 | Z101: 289 | AA101: 396
A102: European Union (EU), Cyprus | B102: QDOA | C102: 203 | D102: 224 | E102: 248 | F102: 260 | G102: 254 | H102: 201 | I102: 258 | J102: 2696 | K102: 158 | L102: 190 | M102: 75 | N102: 146 | O102: 123 | P102: 154 | Q102: 136 | R102: 132 | S102: 172 | T102: 171 | U102: 147 | V102: 162 | W102: 486 | X102: 468 | Y102: 572 | Z102: 295 | AA102: 246
A103: European Union (EU), Czech Republic | B103: QDLG | C103: 634 | D103: 887 | E103: 1239 | F103: 1519 | G103: 1665 | H103: 1377 | I103: 2006 | J103: 2482 | K103: 3010 | L103: 3577 | M103: 3367 | N103: 4108 | O103: 4423 | P103: 4671 | Q103: 4611 | R103: 4602 | S103: 4729 | T103: 5266 | U103: 5472 | V103: 5843 | W103: 6028 | X103: 4646 | Y103: 4875 | Z103: 5162 | AA103: 4905
A104: European Union (EU), Denmark | B104: QBSF | C104: 2293 | D104: 2442 | E104: 2856 | F104: 2996 | G104: 3065 | H104: 3104 | I104: 4571 | J104: 6460 | K104: 3457 | L104: 4090 | M104: 3780 | N104: 4089 | O104: 6075 | P104: 5875 | Q104: 5641 | R104: 4456 | S104: 3417 | T104: 3908 | U104: 4997 | V104: 6760 | W104: 6571 | X104: 4847 | Y104: 5199 | Z104: 5109 | AA104: 6002
A105: European Union (EU), Estonia | B105: QAND | C105: 206 | D105: 364 | E105: 307 | F105: 405 | G105: 312 | H105: 431 | I105: 382 | J105: 577 | K105: 243 | L105: 152 | M105: 123 | N105: 160 | O105: 218 | P105: 208 | Q105: 150 | R105: 155 | S105: 183 | T105: 237 | U105: 226 | V105: 213 | W105: 246 | X105: 215 | Y105: 323 | Z105: 466 | AA105: 322
A106: European Union (EU), Finland | B106: QBTG | C106: 2410 | D106: 2966 | E106: 4096 | F106: 4766 | G106: 3420 | H106: 2802 | I106: 3096 | J106: 3512 | K106: 2658 | L106: 2743 | M106: 2086 | N106: 2119 | O106: 2389 | P106: 2267 | Q106: 2492 | R106: 2405 | S106: 2065 | T106: 2192 | U106: 2361 | V106: 2496 | W106: 2454 | X106: 2865 | Y106: 2224 | Z106: 3522 | AA106: 2351
A107: European Union (EU), France | B107: QDJB | C107: 18567 | D107: 18670 | E107: 20377 | F107: 20781 | G107: 21222 | H107: 20522 | I107: 21010 | J107: 22843 | K107: 22442 | L107: 23974 | M107: 21377 | N107: 22345 | O107: 23745 | P107: 23187 | Q107: 24319 | R107: 24470 | S107: 23780 | T107: 24851 | U107: 26929 | V107: 28057 | W107: 30450 | X107: 23334 | Y107: 23512 | Z107: 34398 | AA107: 41280
A108: European Union (EU), Germany | B108: QDJE | C108: 26865 | D108: 27796 | E108: 30918 | F108: 33648 | G108: 34343 | H108: 35808 | I108: 39841 | J108: 44187 | K108: 44462 | L108: 45163 | M108: 40877 | N108: 46352 | O108: 51059 | P108: 52844 | Q108: 56212 | R108: 59737 | S108: 60481 | T108: 63581 | U108: 68354 | V108: 67952 | W108: 65774 | X108: 57404 | Y108: 57870 | Z108: 67906 | AA108: 73750
A109: European Union (EU), Greece | B109: QDJH | C109: 417 | D109: 451 | E109: 504 | F109: 624 | G109: 662 | H109: 777 | I109: 699 | J109: 704 | K109: 697 | L109: 752 | M109: 561 | N109: 668 | O109: 650 | P109: 689 | Q109: 715 | R109: 765 | S109: 696 | T109: 913 | U109: 925 | V109: 1029 | W109: 1005 | X109: 927 | Y109: 997 | Z109: 1606 | AA109: 1693
... A185: World total | B185: LQBL | C185: 199739 | D185: 226639 | E185: 239314 | F185: 242006 | G185: 245178 | H185: 258413 | I185: 286539 | J185: 328679 | K185: 316391 | L185: 348631 | M185: 317207 | N185: 365300 | O185: 406584 | P185: 411034 | Q185: 424693 | R185: 420295 | S185: 406222 | T185: 438729 | U185: 479747 | V185: 495294 | W185: 513200 | X185: 441755 | Y185: 494340 | Z185: 640659 | AA185: 581193
A187: Table 9.4.3: Balances (£ million)
A188: Country | B188: CDID | C188: 1999 | D188: 2000 | E188: 2001 | F188: 2002 | G188: 2003 | H188: 2004 | I188: 2005 | J188: 2006 | K188: 2007 | L188: 2008 | M188: 2009 | N188: 2010 | O188: 2011 | P188: 2012 | Q188: 2013 | R188: 2014 | S188: 2015 | T188: 2016 | U188: 2017 | V188: 2018 | W188: 2019 | X188: 2020 | Y188: 2021 | Z188: 2022 | AA188: 2023
A189: European Union (EU), Austria | B189: QBSA | C189: -328 | D189: -320 | E189: -992 | F189: -1910 | G189: -2039 | H189: -1332 | I189: -901 | J189: -934 | K189: -1097 | L189: -916 | M189: -1112 | N189: -1210 | O189: -1288 | P189: -1114 | Q189: -1233 | R189: -1382 | S189: -1443 | T189: -1391 | U189: -1438 | V189: -2382 | W189: -2789 | X189: -2303 | Y189: -2551 | Z189: -2555 | AA189: -2991
A190: European Union (EU), Belgium | B190: QDOJ | C190: -1140 | D190: -992 | E190: -2691 | F190: -2553 | G190: -2079 | H190: -2881 | I190: -2493 | J190: -1522 | K190: -2882 | L190: -2830 | M190: -4110 | N190: -3743 | O190: -3021 | P190: -3817 | Q190: -6661 | R190: -8914 | S190: -9038 | T190: -11796 | U190: -11067 | V190: -11318 | W190: -12059 | X190: -11628 | Y190: -7858 | Z190: -727 | AA190: -11562
A191: European Union (EU), Bulgaria | B191: QANP | C191: -6 | D191: -10 | E191: 10 | F191: 2 | G191: 21 | H191: -1 | I191: 47 | J191: 9 | K191: -25 | L191: 53 | M191: 31 | N191: 32 | O191: 53 | P191: 28 | Q191: 47 | R191: 108 | S191: -17 | T191: 89 | U191: 9 | V191: -50 | W191: -205 | X191: -81 | Y191: -190 | Z191: -324 | AA191: -300
A192: European Union (EU), Croatia | B192: QANS | C192: 35 | D192: 32 | E192: 32 | F192: 41 | G192: 107 | H192: 73 | I192: 59 | J192: 68 | K192: 85 | L192: 87 | M192: 128 | N192: 71 | O192: 24 | P192: 65 | Q192: -58 | R192: 86 | S192: 52 | T192: 47 | U192: -15 | V192: 75 | W192: -207 | X192: -49 | Y192: -71 | Z192: -109 | AA192: -214
A193: European Union (EU), Cyprus | B193: QDOB | C193: 55 | D193: 97 | E193: 45 | F193: 16 | G193: 63 | H193: 128 | I193: 108 | J193: -1636 | K193: 251 | L193: 346 | M193: 548 | N193: 416 | O193: 560 | P193: 316 | Q193: 309 | R193: 321 | S193: 197 | T193: 150 | U193: 236 | V193: 236 | W193: -36 | X193: 3 | Y193: -257 | Z193: 61 | AA193: 200
A194: European Union (EU), Czech Republic | B194: QDLH | C194: 102 | D194: 63 | E194: -168 | F194: -487 | G194: -653 | H194: -390 | I194: -919 | J194: -872 | K194: -1569 | L194: -2010 | M194: -1901 | N194: -2261 | O194: -2466 | P194: -2885 | Q194: -2612 | R194: -2466 | S194: -2723 | T194: -3074 | U194: -3260 | V194: -3470 | W194: -3656 | X194: -2490 | Y194: -2945 | Z194: -2894 | AA194: -2555
A195: European Union (EU), Denmark | B195: QBSG | C195: -231 | D195: -142 | E195: -522 | F195: -186 | G195: -832 | H195: -1048 | I195: -2245 | J195: -2574 | K195: -1259 | L195: -1493 | M195: -1294 | N195: -1334 | O195: -3062 | P195: -3043 | Q195: -2633 | R195: -1558 | S195: -1123 | T195: -1449 | U195: -2164 | V195: -3961 | W195: -3834 | X195: -2450 | Y195: -2603 | Z195: -1981 | AA195: -3250
A196: European Union (EU), Estonia | B196: QANT | C196: -154 | D196: -296 | E196: -229 | F196: -312 | G196: -227 | H196: -333 | I196: -272 | J196: -105 | K196: -10 | L196: 69 | M196: 17 | N196: 34 | O196: 62 | P196: 83 | Q196: 195 | R196: 121 | S196: 38 | T196: -1 | U196: 34 | V196: 61 | W196: 13 | X196: 17 | Y196: -67 | Z196: -146 | AA196: 11
A197: European Union (EU), Finland | B197: QBTL | C197: -1062 | D197: -1543 | E197: -2493 | F197: -3332 | G197: -1966 | H197: -1429 | I197: -1574 | J197: -1667 | K197: -666 | L197: -745 | M197: -760 | N197: -624 | O197: -730 | P197: -716 | Q197: -931 | R197: -785 | S197: -747 | T197: -884 | U197: -999 | V197: -1063 | W197: -1096 | X197: -1602 | Y197: -1205 | Z197: -1987 | AA197: -916
A198: European Union (EU), France | B198: QDJC | C198: -1932 | D198: -585 | E198: -1041 | F198: -1596 | G198: -1934 | H198: -1893 | I198: -590 | J198: 6763 | K198: -4937 | L198: -5917 | M198: -4102 | N198: -3198 | O198: -1808 | P198: -2268 | Q198: -3281 | R198: -5758 | S198: -6154 | T198: -5182 | U198: -3270 | V198: -3969 | W198: -5683 | X198: -4606 | Y198: -3818 | Z198: -8444 | AA198: -16478
A199: European Union (EU), Germany | B199: QDJF | C199: -6604 | D199: -5283 | E199: -8170 | F199: -12543 | G199: -14573 | H199: -14718 | I199: -17476 | J199: -17139 | K199: -20187 | L199: -17062 | M199: -16236 | N199: -18265 | O199: -16911 | P199: -20299 | Q199: -26427 | R199: -28626 | S199: -29940 | T199: -31147 | U199: -31699 | V199: -31483 | W199: -28709 | X199: -24488 | Y199: -27759 | Z199: -34027 | AA199: -39975
A200: European Union (EU), Greece | B200: QDJI | C200: 742 | D200: 797 | E200: 688 | F200: 729 | G200: 750 | H200: 773 | I200: 671 | J200: 823 | K200: 902 | L200: 1011 | M200: 1119 | N200: 753 | O200: 525 | P200: 242 | Q200: 500 | R200: 1210 | S200: 276 | T200: 56 | U200: 287 | V200: 666 | W200: 130 | X200: 119 | Y200: -159 | Z200: -567 | AA200: -427
... A276: World total | B276: LQCT | C276: -33396 | D276: -39815 | E276: -48632 | F276: -54547 | G276: -57295 | H276: -67351 | I276: -74045 | J276: -82261 | K276: -93566 | L276: -96038 | M276: -89256 | N276: -99404 | O276: -104015 | P276: -112603 | Q276: -124963 | R276: -131122 | S276: -125318 | T276: -139331 | U276: -139822 | V276: -141290 | W276: -144997 | X276: -128005 | Y276: -162205 | Z276: -206536 | AA276: -187677

Sheet ONS Pink Book - 9.5
A1: 9.5: Trade in services
A2: All tables in this worksheet are in pounds million.
A3: This worksheet is divided into 3 sections: credits, debits and balance.
A4: These tables refer to CDIDs which stands for Central Database Identifier, the codes used to identify specific datasets.
A5: Table 9.5.1: Exports (Credits), (£ million)
A6: Country | B6: CDID | C6: 1999 | D6: 2000 | E6: 2001 | F6: 2002 | G6: 2003 | H6: 2004 | I6: 2005 | J6: 2006 | K6: 2007 | L6: 2008 | M6: 2009 | N6: 2010 | O6: 2011 | P6: 2012 | Q6: 2013 | R6: 2014 | S6: 2015 | T6: 2016 | U6: 2017 | V6: 2018 | W6: 2019 | X6: 2020 | Y6: 2021 | Z6: 2022 | AA6: 2023
A7: European Union (EU), Austria | B7: FYVC | C7: 458 | D7: 490 | E7: 469 | F7: 514 | G7: 541 | H7: 571 | I7: 601 | J7: 641 | K7: 891 | L7: 892 | M7: 699 | N7: 644 | O7: 807 | P7: 860 | Q7: 873 | R7: 857 | S7: 916 | T7: 1068 | U7: 1223 | V7: 1380 | W7: 1576 | X7: 1209 | Y7: 1092 | Z7: 1503 | AA7: 1715
A8: European Union (EU), Belgium | B8: A7RX | C8: 1956 | D8: 2113 | E8: 2003 | F8: 2295 | G8: 2456 | H8: 2760 | I8: 2808 | J8: 2601 | K8: 2956 | L8: 3089 | M8: 3717 | N8: 3502 | O8: 3589 | P8: 4003 | Q8: 3789 | R8: 3583 | S8: 3868 | T8: 4441 | U8: 5389 | V8: 5197 | W8: 5351 | X8: 4783 | Y8: 5328 | Z8: 6170 | AA8: 8044
A9: European Union (EU), Bulgaria | B9: ZWKO | C9: 90 | D9: 96 | E9: 54 | F9: 93 | G9: 104 | H9: 133 | I9: 137 | J9: 173 | K9: 267 | L9: 286 | M9: 305 | N9: 310 | O9: 281 | P9: 370 | Q9: 415 | R9: 411 | S9: 514 | T9: 492 | U9: 567 | V9: 628 | W9: 779 | X9: 464 | Y9: 453 | Z9: 564 | AA9: 522
A10: European Union (EU), Croatia | B10: ZWKZ | C10: 13 | D10: 16 | E10: 20 | F10: 63 | G10: 66 | H10: 17 | I10: 22 | J10: 103 | K10: 91 | L10: 83 | M10: 153 | N10: 127 | O10: 97 | P10: 116 | Q10: 156 | R10: 157 | S10: 170 | T10: 166 | U10: 254 | V10: 295 | W10: 250 | X10: 205 | Y10: 186 | Z10: 253 | AA10: 416
A11: European Union (EU), Cyprus | B11: A7RY | C11: 301 | D11: 333 | E11: 364 | F11: 407 | G11: 380 | H11: 488 | I11: 568 | J11: 672 | K11: 880 | L11: 894 | M11: 799 | N11: 812 | O11: 1010 | P11: 1008 | Q11: 1381 | R11: 1015 | S11: 1007 | T11: 1284 | U11: 1276 | V11: 1156 | W11: 1362 | X11: 1066 | Y11: 1111 | Z11: 1310 | AA11: 1469
A12: European Union (EU), Czech Republic | B12: FYVW | C12: 183 | D12: 215 | E12: 248 | F12: 205 | G12: 265 | H12: 383 | I12: 462 | J12: 467 | K12: 575 | L12: 474 | M12: 488 | N12: 470 | O12: 581 | P12: 603 | Q12: 683 | R12: 708 | S12: 778 | T12: 869 | U12: 1031 | V12: 941 | W12: 1125 | X12: 784 | Y12: 761 | Z12: 1007 | AA12: 1283
A13: European Union (EU), Denmark | B13: FYVE | C13: 1137 | D13: 1350 | E13: 1723 | F13: 1638 | G13: 1818 | H13: 1739 | I13: 1779 | J13: 2584 | K13: 2107 | L13: 2329 | M13: 2673 | N13: 2888 | O13: 3291 | P13: 3288 | Q13: 3245 | R13: 2944 | S13: 2922 | T13: 3422 | U13: 3610 | V13: 3957 | W13: 3978 | X13: 4056 | Y13: 4404 | Z13: 5129 | AA13: 5532
A14: European Union (EU), Estonia | B14: ZWKU | C14: 7 | D14: 8 | E14: 10 | F14: 8 | G14: 16 | H14: 11 | I14: 13 | J14: 27 | K14: 38 | L14: 59 | M14: 34 | N14: 53 | O14: 93 | P14: 124 | Q14: 114 | R14: 121 | S14: 135 | T14: 121 | U14: 138 | V14: 109 | W14: 146 | X14: 188 | Y14: 118 | Z14: 128 | AA14: 170
A15: European Union (EU), Finland | B15: FYVF | C15: 655 | D15: 880 | E15: 789 | F15: 743 | G15: 840 | H15: 854 | I15: 867 | J15: 1073 | K15: 1332 | L15: 1196 | M15: 1350 | N15: 1397 | O15: 1503 | P15: 1511 | Q15: 1351 | R15: 1451 | S15: 1319 | T15: 1238 | U15: 1370 | V15: 1522 | W15: 1885 | X15: 1473 | Y15: 1461 | Z15: 1521 | AA15: 1690
A16: European Union (EU), France | B16: FYVG | C16: 5466 | D16: 6076 | E16: 6661 | F16: 6562 | G16: 7092 | H16: 7740 | I16: 7868 | J16: 8932 | K16: 9606 | L16: 10027 | M16: 9744 | N16: 9890 | O16: 10841 | P16: 11304 | Q16: 11637 | R16: 11503 | S16: 12510 | T16: 13527 | U16: 15028 | V16: 15968 | W16: 15512 | X16: 13061 | Y16: 12968 | Z16: 18305 | AA16: 19845
A17: European Union (EU), Germany | B17: FYVH | C17: 5993 | D17: 6808 | E17: 7311 | F17: 7499 | G17: 8155 | H17: 8628 | I17: 9569 | J17: 10252 | K17: 10722 | L17: 11901 | M17: 11257 | N17: 11597 | O17: 12446 | P17: 12964 | Q17: 14284 | R17: 13957 | S17: 14378 | T17: 17019 | U17: 20234 | V17: 19961 | W17: 19453 | X17: 17359 | Y17: 19478 | Z17: 23612 | AA17: 29207
A18: European Union (EU), Greece | B18: FYVI | C18: 1709 | D18: 1797 | E18: 1718 | F18: 1669 | G18: 1629 | H18: 1524 | I18: 1667 | J18: 1525 | K18: 1509 | L18: 1640 | M18: 1522 | N18: 1516 | O18: 1527 | P18: 1497 | Q18: 1631 | R18: 1677 | S18: 1677 | T18: 1813 | U18: 1985 | V18: 2078 | W18: 2139 | X18: 1427 | Y18: 1622 | Z18: 2196 | AA18: 2556
... A94: World total | B94: KTMQ | C94: 87222 | D94: 95627 | E94: 102123 | F94: 104567 | G94: 114828 | H94: 127327 | I94: 140991 | J94: 158571 | K94: 171236 | L94: 185742 | M94: 188391 | N94: 198280 | O94: 219278 | P94: 226284 | Q94: 239834 | R94: 243063 | S94: 252750 | T94: 276234 | U94: 303361 | V94: 325696 | W94: 338493 | X94: 310350 | Y94: 334751 | Z94: 413928 | AA94: 467718
A96: Table 9.5.2: Imports (Debits), (£ million)
A97: Country | B97: CDID | C97: 1999 | D97: 2000 | E97: 2001 | F97: 2002 | G97: 2003 | H97: 2004 | I97: 2005 | J97: 2006 | K97: 2007 | L97: 2008 | M97: 2009 | N97: 2010 | O97: 2011 | P97: 2012 | Q97: 2013 | R97: 2014 | S97: 2015 | T97: 2016 | U97: 2017 | V97: 2018 | W97: 2019 | X97: 2020 | Y97: 2021 | Z97: 2022 | AA97: 2023
A98: European Union (EU), Austria | B98: GGOR | C98: 499 | D98: 533 | E98: 551 | F98: 786 | G98: 724 | H98: 859 | I98: 901 | J98: 905 | K98: 827 | L98: 885 | M98: 911 | N98: 1046 | O98: 809 | P98: 795 | Q98: 951 | R98: 964 | S98: 985 | T98: 1327 | U98: 1088 | V98: 1160 | W98: 1290 | X98: 711 | Y98: 642 | Z98: 1318 | AA98: 1564
A99: European Union (EU), Belgium | B99: A8ET | C99: 1387 | D99: 1277 | E99: 1441 | F99: 1767 | G99: 1794 | H99: 1809 | I99: 1824 | J99: 1806 | K99: 2095 | L99: 2227 | M99: 2089 | N99: 1882 | O99: 2046 | P99: 2104 | Q99: 2475 | R99: 2277 | S99: 2600 | T99: 2405 | U99: 2706 | V99: 2754 | W99: 2919 | X99: 2208 | Y99: 1885 | Z99: 2581 | AA99: 2514
A100: European Union (EU), Bulgaria | B100: ZWMU | C100: 42 | D100: 48 | E100: 52 | F100: 76 | G100: 93 | H100: 210 | I100: 328 | J100: 288 | K100: 292 | L100: 381 | M100: 278 | N100: 302 | O100: 439 | P100: 363 | Q100: 426 | R100: 461 | S100: 457 | T100: 627 | U100: 787 | V100: 978 | W100: 1031 | X100: 673 | Y100: 869 | Z100: 1242 | AA100: 1441
A101: European Union (EU), Croatia | B101: ZWNF | C101: 8 | D101: 29 | E101: 38 | F101: 41 | G101: 85 | H101: 82 | I101: 121 | J101: 216 | K101: 152 | L101: 357 | M101: 219 | N101: 259 | O101: 284 | P101: 274 | Q101: 356 | R101: 356 | S101: 460 | T101: 488 | U101: 698 | V101: 762 | W101: 790 | X101: 287 | Y101: 452 | Z101: 997 | AA101: 917
A102: European Union (EU), Cyprus | B102: A8EU | C102: 907 | D102: 1038 | E102: 1237 | F102: 1143 | G102: 1316 | H102: 1303 | I102: 1388 | J102: 1325 | K102: 1375 | L102: 1126 | M102: 1051 | N102: 998 | O102: 1190 | P102: 1144 | Q102: 1053 | R102: 875 | S102: 995 | T102: 1071 | U102: 1246 | V102: 1164 | W102: 1437 | X102: 673 | Y102: 696 | Z102: 1078 | AA102: 1299
A103: European Union (EU), Czech Republic | B103: GGPL | C103: 167 | D103: 241 | E103: 263 | F103: 285 | G103: 377 | H103: 535 | I103: 584 | J103: 653 | K103: 604 | L103: 550 | M103: 596 | N103: 567 | O103: 633 | P103: 511 | Q103: 607 | R103: 646 | S103: 715 | T103: 807 | U103: 991 | V103: 1042 | W103: 1243 | X103: 690 | Y103: 701 | Z103: 978 | AA103: 1170
A104: European Union (EU), Denmark | B104: GGOT | C104: 682 | D104: 726 | E104: 752 | F104: 751 | G104: 757 | H104: 832 | I104: 874 | J104: 983 | K104: 887 | L104: 865 | M104: 1106 | N104: 1192 | O104: 1187 | P104: 1167 | Q104: 1265 | R104: 1435 | S104: 1347 | T104: 1486 | U104: 1526 | V104: 1581 | W104: 1706 | X104: 1636 | Y104: 2224 | Z104: 2526 | AA104: 2601
A105: European Union (EU), Estonia | B105: ZWNA | C105: 4 | D105: 7 | E105: 7 | F105: 4 | G105: 8 | H105: 25 | I105: 66 | J105: 72 | K105: 57 | L105: 57 | M105: 29 | N105: 33 | O105: 74 | P105: 56 | Q105: 66 | R105: 61 | S105: 67 | T105: 61 | U105: 70 | V105: 83 | W105: 98 | X105: 59 | Y105: 146 | Z105: 149 | AA105: 200
A106: European Union (EU), Finland | B106: GGOU | C106: 255 | D106: 272 | E106: 261 | F106: 231 | G106: 268 | H106: 263 | I106: 332 | J106: 357 | K106: 359 | L106: 340 | M106: 432 | N106: 492 | O106: 611 | P106: 524 | Q106: 573 | R106: 515 | S106: 498 | T106: 503 | U106: 495 | V106: 602 | W106: 594 | X106: 377 | Y106: 582 | Z106: 705 | AA106: 784
A107: European Union (EU), France | B107: GGOV | C107: 7772 | D107: 8521 | E107: 8642 | F107: 9195 | G107: 9696 | H107: 9958 | I107: 10035 | J107: 10629 | K107: 10717 | L107: 10111 | M107: 9916 | N107: 9739 | O107: 9984 | P107: 10810 | Q107: 10432 | R107: 10953 | S107: 11044 | T107: 11857 | U107: 13061 | V107: 15657 | W107: 14469 | X107: 11168 | Y107: 9689 | Z107: 16433 | AA107: 18950
A108: European Union (EU), Germany | B108: GGOW | C108: 4290 | D108: 4457 | E108: 4950 | F108: 5221 | G108: 5204 | H108: 5560 | I108: 6227 | J108: 6566 | K108: 8562 | L108: 10346 | M108: 9254 | N108: 9732 | O108: 8982 | P108: 9534 | Q108: 9376 | R108: 10221 | S108: 9843 | T108: 11062 | U108: 12483 | V108: 12922 | W108: 12321 | X108: 9784 | Y108: 10214 | Z108: 11972 | AA108: 13871
A109: European Union (EU), Greece | B109: GGOX | C109: 1753 | D109: 1901 | E109: 2218 | F109: 2301 | G109: 2432 | H109: 2316 | I109: 2341 | J109: 2383 | K109: 2089 | L109: 2014 | M109: 2170 | N109: 2045 | O109: 2259 | P109: 2127 | Q109: 2169 | R109: 2235 | S109: 2575 | T109: 2872 | U109: 3015 | V109: 3348 | W109: 3624 | X109: 1516 | Y109: 2427 | Z109: 4960 | AA109: 5640
... A185: World total | B185: KTMR | C185: 64475 | D185: 69044 | E185: 73288 | F185: 78125 | G185: 84292 | H185: 90491 | I185: 96847 | J185: 104134 | K185: 107655 | L185: 116583 | M185: 118360 | N185: 123958 | O185: 128401 | P185: 130627 | Q185: 140171 | R185: 148118 | S185: 156402 | T185: 174659 | U185: 191464 | V185: 214160 | W185: 224672 | X185: 170598 | Y185: 177665 | Z185: 251507 | AA185: 295097
A187: Table 9.5.3: Balances
A188: Country | B188: CDID | C188: 1999 | D188: 2000 | E188: 2001 | F188: 2002 | G188: 2003 | H188: 2004 | I188: 2005 | J188: 2006 | K188: 2007 | L188: 2008 | M188: 2009 | N188: 2010 | O188: 2011 | P188: 2012 | Q188: 2013 | R188: 2014 | S188: 2015 | T188: 2016 | U188: 2017 | V188: 2018 | W188: 2019 | X188: 2020 | Y188: 2021 | Z188: 2022 | AA188: 2023
A189: European Union (EU), Austria | B189: GGQW | C189: -41 | D189: -43 | E189: -82 | F189: -272 | G189: -183 | H189: -288 | I189: -300 | J189: -264 | K189: 64 | L189: 7 | M189: -212 | N189: -402 | O189: -2 | P189: 65 | Q189: -78 | R189: -107 | S189: -69 | T189: -259 | U189: 135 | V189: 220 | W189: 286 | X189: 498 | Y189: 450 | Z189: 185 | AA189: 151
A190: European Union (EU), Belgium | B190: A8HH | C190: 569 | D190: 836 | E190: 562 | F190: 528 | G190: 662 | H190: 951 | I190: 984 | J190: 795 | K190: 861 | L190: 862 | M190: 1628 | N190: 1620 | O190: 1543 | P190: 1899 | Q190: 1314 | R190: 1306 | S190: 1268 | T190: 2036 | U190: 2683 | V190: 2443 | W190: 2432 | X190: 2575 | Y190: 3443 | Z190: 3589 | AA190: 5530
A191: European Union (EU), Bulgaria | B191: ZWTO | C191: 48 | D191: 48 | E191: 2 | F191: 17 | G191: 11 | H191: -77 | I191: -191 | J191: -115 | K191: -25 | L191: -95 | M191: 27 | N191: 8 | O191: -158 | P191: 7 | Q191: -11 | R191: -50 | S191: 57 | T191: -135 | U191: -220 | V191: -350 | W191: -252 | X191: -209 | Y191: -416 | Z191: -678 | AA191: -919
A192: European Union (EU), Croatia | B192: ZWTZ | C192: 5 | D192: -13 | E192: -18 | F192: 22 | G192: -19 | H192: -65 | I192: -99 | J192: -113 | K192: -61 | L192: -274 | M192: -66 | N192: -132 | O192: -187 | P192: -158 | Q192: -200 | R192: -199 | S192: -290 | T192: -322 | U192: -444 | V192: -467 | W192: -540 | X192: -82 | Y192: -266 | Z192: -744 | AA192: -501
A193: European Union (EU), Cyprus | B193: A8HI | C193: -606 | D193: -705 | E193: -873 | F193: -736 | G193: -936 | H193: -815 | I193: -820 | J193: -653 | K193: -495 | L193: -232 | M193: -252 | N193: -186 | O193: -180 | P193: -136 | Q193: 328 | R193: 140 | S193: 12 | T193: 213 | U193: 30 | V193: -8 | W193: -75 | X193: 393 | Y193: 415 | Z193: 232 | AA193: 170
A194: European Union (EU), Czech Republic | B194: GGRQ | C194: 16 | D194: -26 | E194: -15 | F194: -80 | G194: -112 | H194: -152 | I194: -122 | J194: -186 | K194: -29 | L194: -76 | M194: -108 | N194: -97 | O194: -52 | P194: 92 | Q194: 76 | R194: 62 | S194: 63 | T194: 62 | U194: 40 | V194: -101 | W194: -118 | X194: 94 | Y194: 60 | Z194: 29 | AA194: 113
A195: European Union (EU), Denmark | B195: GGQY | C195: 455 | D195: 624 | E195: 971 | F195: 887 | G195: 1061 | H195: 907 | I195: 905 | J195: 1601 | K195: 1220 | L195: 1464 | M195: 1567 | N195: 1696 | O195: 2104 | P195: 2121 | Q195: 1980 | R195: 1509 | S195: 1575 | T195: 1936 | U195: 2084 | V195: 2376 | W195: 2272 | X195: 2420 | Y195: 2180 | Z195: 2603 | AA195: 2931
A196: European Union (EU), Estonia | B196: ZWTU | C196: 3 | D196: 1 | E196: 3 | F196: 4 | G196: 8 | H196: -14 | I196: -53 | J196: -45 | K196: -19 | L196: 2 | M196: 5 | N196: 20 | O196: 19 | P196: 68 | Q196: 48 | R196: 60 | S196: 68 | T196: 60 | U196: 68 | V196: 26 | W196: 48 | X196: 129 | Y196: -28 | Z196: -21 | AA196: -30
A197: European Union (EU), Finland | B197: GGQZ | C197: 400 | D197: 608 | E197: 528 | F197: 512 | G197: 572 | H197: 591 | I197: 535 | J197: 716 | K197: 973 | L197: 856 | M197: 918 | N197: 905 | O197: 892 | P197: 987 | Q197: 778 | R197: 936 | S197: 821 | T197: 735 | U197: 875 | V197: 920 | W197: 1291 | X197: 1096 | Y197: 879 | Z197: 816 | AA197: 906
A198: European Union (EU), France | B198: GGRA | C198: -2306 | D198: -2445 | E198: -1981 | F198: -2633 | G198: -2604 | H198: -2218 | I198: -2167 | J198: -1697 | K198: -1111 | L198: -84 | M198: -172 | N198: 151 | O198: 857 | P198: 494 | Q198: 1205 | R198: 550 | S198: 1466 | T198: 1670 | U198: 1967 | V198: 311 | W198: 1043 | X198: 1893 | Y198: 3279 | Z198: 1872 | AA198: 895
A199: European Union (EU), Germany | B199: GGRB | C199: 1703 | D199: 2351 | E199: 2361 | F199: 2278 | G199: 2951 | H199: 3068 | I199: 3342 | J199: 3686 | K199: 2160 | L199: 1555 | M199: 2003 | N199: 1865 | O199: 3464 | P199: 3430 | Q199: 4908 | R199: 3736 | S199: 4535 | T199: 5957 | U199: 7751 | V199: 7039 | W199: 7132 | X199: 7575 | Y199: 9264 | Z199: 11640 | AA199: 15336
A200: European Union (EU), Greece | B200: GGRC | C200: -44 | D200: -104 | E200: -500 | F200: -632 | G200: -803 | H200: -792 | I200: -674 | J200: -858 | K200: -580 | L200: -374 | M200: -648 | N200: -529 | O200: -732 | P200: -630 | Q200: -538 | R200: -558 | S200: -898 | T200: -1059 | U200: -1030 | V200: -1270 | W200: -1485 | X200: -89 | Y200: -805 | Z200: -2764 | AA200: -3084
... A276: World total | B276: KTMS | C276: 22747 | D276: 26583 | E276: 28835 | F276: 26442 | G276: 30536 | H276: 36836 | I276: 44144 | J276: 54437 | K276: 63581 | L276: 69159 | M276: 70031 | N276: 74322 | O276: 90877 | P276: 95657 | Q276: 99663 | R276: 94945 | S276: 96348 | T276: 101575 | U276: 111897 | V276: 111536 | W276: 113821 | X276: 139752 | Y276: 157086 | Z276: 162421 | AA276: 172621

Sheet ONS Pink Book - 9.11
A1: 9.11: Trade in goods countries by commodity 2023
A2: This worksheet contains two tables presented next to each other vertically with one blank row between. Any notes mentioned in this worksheet can be found in the Notes tab
A3: Table 1: Exports of goods by country
A4: Country Code | B4: Country | C4: Total | D4: SITC 0: Food & live animals | E4: SITC 1: Beverages & tobacco | F4: SITC 2: Crude materials | G4: SITC 3: Fuels | H4: SITC 4: Animal & vegetable oils & fats | I4: SITC 5: Chemicals | J4: SITC 6: Material manufactures | K4: SITC 7: Machinery & transport equipment | L4: SITC 8: Miscellaneous manufactures | M4: SITC 9: Unspecified goods
A5: AT | B5: Austria | C5: 1722 | D5: 29 | E5: 36 | F5: 17 | G5: 2 | H5: C | I5: 200 | J5: 213 | K5: 961 | L5: 252 | M5: 14
A6: BE | B6: Belgium | C6: 17637 | D6: 579 | E6: 360 | F6: 504 | G6: 3800 | H6: 63 | I6: 4696 | J6: 1637 | K6: 4727 | L6: 1231 | M6: 41
A7: BG | B7: Bulgaria | C7: 396 | D7: 18 | E7: 45 | F7: 16 | G7: 2 | H7: C | I7: 51 | J7: 25 | K7: 205 | L7: 33 | M7: 2
A8: HR | B8: Croatia | C8: 182 | D8: 11 | E8: 20 | F8: 1 | G8: 1 | H8: 1 | I8: 28 | J8: 13 | K8: 86 | L8: 19 | M8: 2
A9: CY | B9: Cyprus | C9: 446 | D9: 44 | E9: 23 | F9: 1 | G9: 1 | H9: 1 | I9: 29 | J9: 20 | K9: 278 | L9: 46 | M9: 3
A10: CZ | B10: Czechia | C10: 2350 | D10: 83 | E10: 124 | F10: 18 | G10: 4 | H10: 1 | I10: 421 | J10: 353 | K10: 1067 | L10: 259 | M10: 22
A11: DK | B11: Denmark | C11: 2752 | D11: 189 | E11: 69 | F11: 30 | G11: 374 | H11: 7 | I11: 403 | J11: 365 | K11: 961 | L11: 318 | M11: 36
A12: EE | B12: Estonia | C12: 333 | D12: 8 | E12: 19 | F12: 3 | G12: 8 | H12: C | I12: 26 | J12: 28 | K12: 208 | L12: 33 | M12: 1
A13: FI | B13: Finland | C13: 1435 | D13: 38 | E13: 22 | F13: 20 | G13: 441 | H13: C | I13: 142 | J13: 147 | K13: 486 | L13: 129 | M13: 9
A14: FR | B14: France | C14: 24802 | D14: 2188 | E14: 747 | F14: 184 | G14: 1938 | H14: 16 | I14: 3568 | J14: 1945 | K14: 10785 | L14: 3093 | M14: 338
A15: DE | B15: Germany | C15: 33775 | D15: 692 | E15: 605 | F15: 574 | G15: 2191 | H15: 28 | I15: 4118 | J15: 3965 | K15: 17451 | L15: 3869 | M15: 282
A16: GR | B16: Greece | C16: 1266 | D16: 44 | E16: 110 | F16: 56 | G16: 18 | H16: C | I16: 142 | J16: 118 | K16: 661 | L16: 112 | M16: 4
A17: HU | B17: Hungary | C17: 1509 | D17: 44 | E17: 116 | F17: 31 | G17: 6 | H17: 1 | I17: 260 | J17: 123 | K17: 787 | L17: 129 | M17: 11
A18: IE | B18: Irish Republic | C18: 28092 | D18: 3620 | E18: 538 | F18: 354 | G18: 4033 | H18: 109 | I18: 6946 | J18: 3372 | K18: 5857 | L18: 3083 | M18: 180
A19: IT | B19: Italy | C19: 10385 | D19: 306 | E19: 240 | F19: 315 | G19: 592 | H19: 3 | I19: 1127 | J19: 1312 | K19: 5025 | L19: 1317 | M19: 147
A20: LV | B20: Latvia | C20: 376 | D20: 14 | E20: 135 | F20: 20 | G20: 1 | H20: C | I20: 21 | J20: 22 | K20: 134 | L20: 27 | M20: 2
A21: LT | B21: Lithuania | C21: 805 | D21: 46 | E21: 75 | F21: 26 | G21: 235 | H21: C | I21: 81 | J21: 44 | K21: 230 | L21: 65 | M21: 4
A22: LU | B22: Luxembourg | C22: 602 | D22: 12 | E22: 45 | F22: 5 | G22: C | H22: C | I22: 73 | J22: 25 | K22: 400 | L22: 36 | M22: 5
A23: MT | B23: Malta | C23: 386 | D23: 37 | E23: 14 | F23: 1 | G23: 53 | H23: C | I23: 57 | J23: 27 | K23: 151 | L23: 42 | M23: 3
A24: NL | B24: Netherlands | C24: 30943 | D24: 1522 | E24: 363 | F24: 346 | G24: 11381 | H24: 258 | I24: 4373 | J24: 2059 | K24: 7350 | L24: 3211 | M24: 78
A25: PL | B25: Poland | C25: 7157 | D25: 328 | E25: 462 | F25: 147 | G25: 1807 | H25: 8 | I25: 813 | J25: 912 | K25: 2218 | L25: 424 | M25: 38
A26: PT | B26: Portugal | C26: 1426 | D26: 104 | E26: 103 | F26: 128 | G26: 13 | H26: C | I26: 125 | J26: 183 | K26: 659 | L26: 102 | M26: 9
A27: RO | B27: Romania | C27: 1316 | D27: 36 | E27: 207 | F27: 7 | G27: 3 | H27: C | I27: 135 | J27: 204 | K27: 590 | L27: 127 | M27: 7
A28: SK | B28: Slovakia | C28: 937 | D28: 14 | E28: 17 | F28: 2 | G28: 1 | H28: C | I28: 66 | J28: 162 | K28: 583 | L28: 80 | M28: 12
A29: SI | B29: Slovenia | C29: 254 | D29: 10 | E29: 10 | F29: 3 | G29: 1 | H29: C | I29: 85 | J29: 29 | K29: 91 | L29: 22 | M29: 3
A30: ES | B30: Spain | C30: 10110 | D30: 622 | E30: 403 | F30: 362 | G30: 462 | H30: 6 | I30: 1543 | J30: 1006 | K30: 3960 | L30: 757 | M30: 988
A31: SE | B31: Sweden | C31: 4969 | D31: 164 | E31: 89 | F31: 88 | G31: 978 | H31: 5 | I31: 633 | J31: 821 | K31: 1760 | L31: 407 | M31: 24
A32: B5 | B32: Total EU27 | C32: 186363 | D32: 10802 | E32: 5000 | F32: 3260 | G32: 28346 | H32: 509 | I32: 30161 | J32: 19129 | K32: 67671 | L32: 19221 | M32: 2264
A33: AF | B33: Afghanistan | C33: 1 | D33: C | E33: C | F33: C | G33: C | H33: C | I33: 1 | J33: C | K33: 1 | L33: C | M33: C
A34: AL | B34: Albania | C34: 45 | D34: 3 | E34: 3 | F34: 1 | G34: C | H34: C | I34: 5 | J34: 2 | K34: 22 | L34: 11 | M34: C
A35: DZ | B35: Algeria | C35: 337 | D35: 22 | E35: 101 | F35: 3 | G35: 1 | H35: 10 | I35: 66 | J35: 14 | K35: 89 | L35: 31 | M35: 1
A36: AS | B36: American Samoa | C36: C | D36: C | E36: C | F36: C | G36: C | H36: C | I36: C | J36: C | K36: C | L36: C | M36: C
A37: AD | B37: Andorra | C37: 10 | D37: C | E37: 4 | F37: C | G37: C | H37: C | I37: C | J37: C | K37: 6 | L37: 1 | M37: C
A38: AO | B38: Angola | C38: 319 | D38: 5 | E38: 6 | F38: C | G38: 1 | H38: C | I38: 24 | J38: 50 | K38: 193 | L38: 35 | M38: 4
A39: AI | B39: Anguilla | C39: C | D39: C | E39: C | F39: C | G39: C | H39: C | I39: C | J39: C | K39: C | L39: C | M39: C
A40: AQ | B40: Antarctica | C40: 11 | D40: 1 | E40: C | F40: C | G40: C | H40: C | I40: C | J40: C | K40: 1 | L40: 10 | M40: C
A41: AG | B41: Antigua and Barbuda | C41: 25 | D41: 3 | E41: C | F41: 2 | G41: C | H41: C | I41: 2 | J41: 6 | K41: 8 | L41: 2 | M41: 1
A42: AR | B42: Argentina | C42: 404 | D42: 10 | E42: 17 | F42: 5 | G42: 16 | H42: C | I42: 108 | J42: 48 | K42: 172 | L42: 28 | M42: 1
A43: AM | B43: Armenia | C43: 52 | D43: 1 | E43: 8 | F43: C | G43: 1 | H43: C | I43: 5 | J43: 1 | K43: 28 | L43: 7 | M43: C
A44: AW | B44: Aruba | C44: 8 | D44: C | E44: 4 | F44: C | G44: C | H44: C | I44: 1 | J44: C | K44: 2 | L44: 1 | M44: C
A45: AU | B45: Australia | C45: 5150 | D45: 352 | E45: 183 | F45: 24 | G45: 5 | H45: 4 | I45: 683 | J45: 297 | K45: 2720 | L45: 835 | M45: 47
A46: AZ | B46: Azerbaijan | C46: 510 | D46: 1 | E46: 26 | F46: C | G46: C | H46: C | I46: 11 | J46: 32 | K46: 410 | L46: 27 | M46: 2
A47: BH | B47: Bahrain | C47: 334 | D47: 32 | E47: 8 | F47: 1 | G47: 1 | H47: C | I47: 17 | J47: 15 | K47: 149 | L47: 110 | M47: 1
A48: BD | B48: Bangladesh | C48: 471 | D48: 23 | E48: C | F48: 177 | G48: C | H48: C | I48: 13 | J48: 14 | K48: 217 | L48: 23 | M48: 2
A49: BB | B49: Barbados | C49: 103 | D49: 15 | E49: 2 | F49: C | G49: C | H49: C | I49: 6 | J49: 6 | K49: 62 | L49: 12 | M49: 1
A50: BY | B50: Belarus | C50: 15 | D50: 3 | E50: C | F50: C | G50: C | H50: C | I50: 5 | J50: 1 | K50: 1 | L50: 3 | M50: C
A51: BZ | B51: Belize | C51: 9 | D51: 1 | E51: C | F51: C | G51: C | H51: C | I51: 1 | J51: C | K51: 5 | L51: 2 | M51: C
A52: BJ | B52: Benin | C52: 47 | D52: 12 | E52: C | F52: 23 | G52: C | H52: C | I52: C | J52: C | K52: 8 | L52: 2 | M52: C
A53: BM | B53: Bermuda | C53: 66 | D53: 6 | E53: 2 | F53: C | G53: C | H53: C | I53: 17 | J53: 1 | K53: 10 | L53: 29 | M53: C
A54: BT | B54: Bhutan | C54: C | D54: C | E54: 2 | F54: C | G54: C | H54: C | I54: C | J54: C | K54: C | L54: C | M54: C
A55: BO | B55: Bolivia | C55: 19 | D55: 1 | E55: 4 | F55: C | G55: C | H55: C | I55: 3 | J55: C | K55: 9 | L55: 2 | M55: C
A56: BQ | B56: Bonaire, Sint Eustatius and Saba | C56: C | D56: C | E56: C | F56: C | G56: C | H56: C | I56: C | J56: C | K56: C | L56: C | M56: C
A57: BA | B57: Bosnia and Herzegovina | C57: 31 | D57: 2 | E57: 1 | F57: C | G57: C | H57: C | I57: 4 | J57: 6 | K57: 14 | L57: 3 | M57: C
A58: BW | B58: Botswana | C58: 10 | D58: C | E58: C | F58: C | G58: C | H58: C | I58: 1 | J58: C | K58: 5 | L58: 2 | M58: C
A59: BV | B59: Bouvet Island | C59: 4 | D59: C | E59: C | F59: C | G59: C | H59: C | I59: C | J59: C | K59: 4 | L59: C | M59: C
A60: BR | B60: Brazil | C60: 2706 | D60: 41 | E60: 109 | F60: 14 | G60: 17 | H60: 1 | I60: 668 | J60: 268 | K60: 1380 | L60: 189 | M60: 20
A61: IO | B61: British Indian Ocean Territory | C61: C | D61: C | E61: C | F61: C | G61: C | H61: C | I61: C | J61: C | K61: C | L61: C | M61: C
A62: VG | B62: British Virgin Islands | C62: 14 | D62: 1 | E62: 1 | F62: C | G62: C | H62: C | I62: 1 | J62: C | K62: 11 | L62: 1 | M62: C
A63: BN | B63: Brunei | C63: 32 | D63: 3 | E63: 1 | F63: C | G63: C | H63: C | I63: 3 | J63: 4 | K63: 14 | L63: 7 | M63: C
A64: BF | B64: Burkina Faso | C64: 12 | D64: C | E64: C | F64: C | G64: C | H64: C | I64: 1 | J64: 1 | K64: 7 | L64: 2 | M64: C
A65: BI | B65: Burundi | C65: 2 | D65: C | E65: C | F65: C | G65: C | H65: C | I65: C | J65: C | K65: 3 | L65: C | M65: C
A66: KH | B66: Cambodia | C66: 67 | D66: 12 | E66: 5 | F66: C | G66: C | H66: C | I66: 3 | J66: 6 | K66: 33 | L66: 8 | M66: C
A67: CM | B67: Cameroon | C67: 50 | D67: 5 | E67: 9 | F67: 2 | G67: C | H67: C | I67: 7 | J67: 1 | K67: 17 | L67: 9 | M67: C
A68: CA | B68: Canada | C68: 7109 | D68: 308 | E68: 190 | F68: 67 | G68: 1356 | H68: 4 | I68: 795 | J68: 845 | K68: 2776 | L68: 419 | M68: 346
A69: CV | B69: Cape Verde | C69: 1 | D69: C | E69: C | F69: C | G69: C | H69: C | I69: C | J69: C | K69: 2 | L69: C | M69: C
A70: KY | B70: Cayman Islands | C70: 36 | D70: 4 | E70: 2 | F70: C | G70: C | H70: C | I70: 13 | J70: 1 | K70: 11 | L70: 4 | M70: C
A71: CF | B71: Central African Republic | C71: 1 | D71: C | E71: C | F71: C | G71: C | H71: C | I71: C | J71: C | K71: 1 | L71: 1 | M71: C
A72: TD | B72: Chad | C72: 20 | D72: C | E72: C | F72: C | G72: C | H72: C | I72: 17 | J72: C | K72: 1 | L72: C | M72: C
A73: CL | B73: Chile | C73: 492 | D73: 45 | E73: 42 | F73: 2 | G73: 1 | H73: C | I73: 91 | J73: 22 | K73: 241 | L73: 46 | M73: 2
A74: CN | B74: China | C74: 21881 | D74: 535 | E74: 285 | F74: 754 | G74: 1996 | H74: 4 | I74: 1866 | J74: 914 | K74: 8916 | L74: 1243 | M74: 5366
A75: CX | B75: Christmas Island | C75: C | D75: C | E75: C | F75: C | G75: C | H75: C | I75: C | J75: C | K75: C | L75: C | M75: C
A76: CC | B76: Cocos Islands | C76: C | D76: C | E76: C | F76: C | G76: C | H76: C | I76: C | J76: C | K76: C | L76: C | M76: C
A77: CO | B77: Colombia | C77: 554 | D77: 11 | E77: 50 | F77: 2 | G77: 161 | H77: C | I77: 132 | J77: 12 | K77: 144 | L77: 43 | M77: 1
A78: KM | B78: Comoros | C78: C | D78: C | E78: C | F78: C | G78: C | H78: C | I78: C | J78: C | K78: C | L78: C | M78: C
A79: CG | B79: Congo | C79: 49 | D79: 6 | E79: 1 | F79: C | G79: C | H79: C | I79: 3 | J79: 15 | K79: 19 | L79: 5 | M79: 1
A80: CD | B80: Congo (Democratic Republic) | C80: 38 | D80: 2 | E80: 7 | F80: C | G80: C | H80: C | I80: 8 | J80: 1 | K80: 17 | L80: 4 | M80: C
A81: CK | B81: Cook Islands | C81: C | D81: C | E81: C | F81: 1 | G81: C | H81: C | I81: C | J81: C | K81: C | L81: C | M81: C
A82: CR | B82: Costa Rica | C82: 125 | D82: 4 | E82: 3 | F82: 1 | G82: C | H82: C | I82: 20 | J82: 8 | K82: 70 | L82: 21 | M82: 1
A83: CU | B83: Cuba | C83: 7 | D83: C | E83: 2 | F83: C | G83: C | H83: C | I83: C | J83: 1 | K83: 2 | L83: 1 | M83: C
A84: CW | B84: Curacao | C84: 8 | D84: 1 | E84: C | F84: C | G84: C | H84: C | I84: C | J84: 1 | K84: 5 | L84: 1 | M84: C
A85: DJ | B85: Djibouti | C85: 29 | D85: 1 | E85: 14 | F85: 1 | G85: C | H85: C | I85: 2 | J85: 1 | K85: 6 | L85: 3 | M85: C
A86: DM | B86: Dominica | C86: 7 | D86: 2 | E86: C | F86: C | G86: C | H86: C | I86: 1 | J86: 1 | K86: 3 | L86: 1 | M86: C
A87: DO | B87: Dominican Republic | C87: 161 | D87: 11 | E87: 59 | F87: C | G87: C | H87: C | I87: 24 | J87: 15 | K87: 41 | L87: 10 | M87: C
A88: TL | B88: East Timor | C88: C | D88: C | E88: C | F88: C | G88: C | H88: C | I88: C | J88: C | K88: C | L88: C | M88: C
A89: EC | B89: Ecuador | C89: 100 | D89: 4 | E89: 20 | F89: 1 | G89: C | H89: C | I89: 16 | J89: 3 | K89: 42 | L89: 15 | M89: C
A90: EG | B90: Egypt | C90: 1715 | D90: 126 | E90: 46 | F90: 474 | G90: 16 | H90: C | I90: 227 | J90: 72 | K90: 646 | L90: 100 | M90: 8
A91: SV | B91: El Salvador | C91: 28 | D91: 1 | E91: C | F91: C | G91: C | H91: C | I91: 4 | J91: 1 | K91: 18 | L91: 2 | M91: C
A92: GQ | B92: Equatorial Guinea | C92: 43 | D92: 7 | E92: 1 | F92: 1 | G92: C | H92: C | I92: 5 | J92: 5 | K92: 20 | L92: 3 | M92: C
A93: ER | B93: Eritrea | C93: 3 | D93: C | E93: C | F93: C | G93: C | H93: C | I93: C | J93: C | K93: 3 | L93: C | M93: C
A94: SZ | B94: Eswatini | C94: 1 | D94: C | E94: 1 | F94: C | G94: C | H94: C | I94: C | J94: C | K94: 1 | L94: 1 | M94: C
A95: ET | B95: Ethiopia | C95: 164 | D95: 2 | E95: 8 | F95: C | G95: C | H95: C | I95: 6 | J95: 5 | K95: 129 | L95: 13 | M95: 1
A96: FK | B96: Falkland Islands | C96: 105 | D96: 8 | E96: 3 | F96: 3 | G96: 2 | H96: C | I96: 5 | J96: 13 | K96: 51 | L96: 18 | M96: 2
A97: FO | B97: Faroe Islands | C97: 25 | D97: 5 | E97: C | F97: C | G97: C | H97: 9 | I97: 1 | J97: 4 | K97: 5 | L97: 1 | M97: 1
A98: FJ | B98: Fiji | C98: 4 | D98: C | E98: C | F98: C | G98: C | H98: C | I98: 1 | J98: C | K98: 2 | L98: 1 | M98: C
A99: PF | B99: French Polynesia | C99: 3 | D99: C | E99: C | F99: C | G99: C | H99: C | I99: C | J99: C | K99: 4 | L99: C | M99: C
A100: TF | B100: French Southern Territories | C100: C | D100: C | E100: C | F100: C | G100: C | H100: C | I100: C | J100: C | K100: C | L100: C | M100: C
...

Sheet ONS Pink Book - 9.13
A1: 9.13: Trade in services by type of service 2023
A2: All tables in this worksheet are in pounds million.
A3: This worksheet contains two tables presented next to each other vertically with one blank row between. Any notes mentioned in this worksheet can be found in the Notes tab.
A4: The Standard International Trade Classification (SITC) is an identifier code for the classification for goods used in statistics on imports and exports.
A5: Table 9.13.1: Exports by service type and partner country 2023 (£ million)
A6: Country Code | B6: Country Name | C6: 0: Total Services | D6: 1: Manufacturing | E6: 2: Maintenance and Repair | F6: 3: Transportation | G6: 4: Travel | H6: 5: Construction | I6: 6: Insurance and Pension | J6: 7: Financial | K6: 8: Intellectual property | L6: 9: Telecommunications, computer and information services | M6: 10: Other Business Services | N6: 11: Personal, Cultural and Recreational | O6: 12: Government
A7: AT | B7: Austria | C7: 1715 | D7: C | E7: 61 | F7: 159 | G7: 317 | H7: C | I7: 132 | J7: 148 | K7: 91 | L7: 223 | M7: 535 | N7: 27 | O7: C
A8: BE | B8: Belgium | C8: 8044 | D8: 465 | E8: 26 | F8: 499 | G8: 572 | H8: 58 | I8: 130 | J8: 808 | K8: 958 | L8: 475 | M8: 3981 | N8: 28 | O8: 44
A9: BG | B9: Bulgaria | C9: 522 | D9: 0 | E9: 0 | F9: 99 | G9: 229 | H9: 0 | I9: 24 | J9: 32 | K9: 23 | L9: 42 | M9: 66 | N9: C | O9: C
A10: HR | B10: Croatia | C10: 416 | D10: C | E10: 9 | F10: 132 | G10: 50 | H10: 0 | I10: 53 | J10: 46 | K10: 57 | L10: 30 | M10: C | N10: 0 | O10: C
A11: CY | B11: Cyprus | C11: 1469 | D11: 0 | E11: 0 | F11: 252 | G11: 283 | H11: 0 | I11: 56 | J11: 244 | K11: C | L11: 399 | M11: 189 | N11: 26 | O11: C
A12: CZ | B12: Czechia | C12: 1283 | D12: 38 | E12: 7 | F12: 139 | G12: 179 | H12: C | I12: 25 | J12: 182 | K12: 88 | L12: 201 | M12: 410 | N12: C | O12: 8
A13: DK | B13: Denmark | C13: 5532 | D13: 112 | E13: 295 | F13: 506 | G13: 376 | H13: 67 | I13: 201 | J13: 310 | K13: 226 | L13: 764 | M13: 2628 | N13: 43 | O13: 4
A14: EE | B14: Estonia | C14: 170 | D14: 0 | E14: 0 | F14: 18 | G14: 44 | H14: 0 | I14: 0 | J14: 0 | K14: C | L14: 26 | M14: 71 | N14: 0 | O14: C
A15: FI | B15: Finland | C15: 1690 | D15: 174 | E15: 19 | F15: 140 | G15: 166 | H15: C | I15: 32 | J15: 228 | K15: 64 | L15: 421 | M15: 413 | N15: 16 | O15: C
A16: FR | B16: France | C16: 19845 | D16: 243 | E16: 158 | F16: 1575 | G16: 2301 | H16: 76 | I16: 996 | J16: 4213 | K16: 1444 | L16: 2801 | M16: 5761 | N16: 228 | O16: 49
A17: DE | B17: Germany | C17: 29207 | D17: 61 | E17: 470 | F17: 1764 | G17: 2189 | H17: 307 | I17: 1055 | J17: 5479 | K17: 2651 | L17: 4132 | M17: 10674 | N17: 353 | O17: 72
A18: GR | B18: Greece | C18: 2556 | D18: 14 | E18: 9 | F18: 864 | G18: 431 | H18: 144 | I18: 235 | J18: 254 | K18: 73 | L18: 254 | M18: 223 | N18: 46 | O18: 9
A19: HU | B19: Hungary | C19: 1870 | D19: 0 | E19: 15 | F19: 107 | G19: 148 | H19: C | I19: C | J19: 93 | K19: 1126 | L19: 202 | M19: 161 | N19: C | O19: 9
A20: IE | B20: Ireland | C20: 29640 | D20: 95 | E20: 115 | F20: 1197 | G20: 1682 | H20: 102 | I20: 577 | J20: 5907 | K20: 362 | L20: 1125 | M20: 18348 | N20: 115 | O20: 15
A21: IT | B21: Italy | C21: 8481 | D21: 23 | E21: 154 | F21: 1151 | G21: 1365 | H21: 31 | I21: 561 | J21: 1579 | K21: 717 | L21: 805 | M21: 1840 | N21: 233 | O21: 22
A22: LV | B22: Latvia | C22: 198 | D22: 0 | E22: 0 | F22: 33 | G22: 103 | H22: 0 | I22: 0 | J22: 23 | K22: 8 | L22: C | M22: C | N22: 0 | O22: C
A23: LT | B23: Lithuania | C23: 401 | D23: C | E23: 2 | F23: 95 | G23: 177 | H23: 0 | I23: 1 | J23: 37 | K23: 19 | L23: 24 | M23: 38 | N23: 0 | O23: C
A24: LU | B24: Luxembourg | C24: 11061 | D24: C | E24: 22 | F24: 55 | G24: 83 | H24: 128 | I24: 156 | J24: 6120 | K24: 75 | L24: 571 | M24: 3823 | N24: 23 | O24: C
A25: MT | B25: Malta | C25: 1133 | D25: 0 | E25: C | F25: 106 | G25: 83 | H25: 0 | I25: 50 | J25: 150 | K25: 49 | L25: 113 | M25: 557 | N25: 13 | O25: C
A26: NL | B26: Netherlands | C26: 21598 | D26: 1942 | E26: 175 | F26: 1573 | G26: 1341 | H26: 143 | I26: 448 | J26: 2966 | K26: 826 | L26: 2357 | M26: 9741 | N26: 77 | O26: 9
A27: PL | B27: Poland | C27: 3330 | D27: C | E27: C | F27: 399 | G27: 722 | H27: 26 | I27: 38 | J27: 388 | K27: 159 | L27: 372 | M27: 1163 | N27: 23 | O27: 28
A28: PT | B28: Portugal | C28: 1923 | D28: 0 | E28: 86 | F28: 622 | G28: 504 | H28: 48 | I28: 44 | J28: 122 | K28: 37 | L28: 228 | M28: 213 | N28: C | O28: C
A29: RO | B29: Romania | C29: 1202 | D29: 0 | E29: C | F29: 180 | G29: 546 | H29: 10 | I29: 20 | J29: 102 | K29: 56 | L29: 119 | M29: 155 | N29: 0 | O29: C
A30: SK | B30: Slovak Republic | C30: 399 | D30: 0 | E30: 3 | F30: 36 | G30: 99 | H30: 0 | I30: 4 | J30: 46 | K30: 24 | L30: 53 | M30: 129 | N30: 0 | O30: 5
A31: SI | B31: Slovenia | C31: 206 | D31: C | E31: 0 | F31: 15 | G31: 42 | H31: 0 | I31: C | J31: 22 | K31: 47 | L31: 33 | M31: 35 | N31: 0 | O31: 1
A32: ES | B32: Spain | C32: 9613 | D32: 42 | E32: 119 | F32: 2989 | G32: 1490 | H32: 9 | I32: 333 | J32: 1274 | K32: 644 | L32: 832 | M32: 1793 | N32: 68 | O32: 20
A33: SE | B33: Sweden | C33: 6271 | D33: 61 | E33: C | F33: 271 | G33: 477 | H33: 52 | I33: 256 | J33: 854 | K33: 1012 | L33: 849 | M33: 2180 | N33: 228 | O33: C
A34: 4F | B34: European Central Bank | C34: 0 | D34: 0 | E34: 0 | F34: 0 | G34: 0 | H34: 0 | I34: 0 | J34: 0 | K34: 0 | L34: 0 | M34: 0 | N34: 0 | O34: 0
A35: 4A | B35: EU Institutions | C35: 128 | D35: 0 | E35: C | F35: 0 | G35: 0 | H35: 0 | I35: 0 | J35: 21 | K35: C | L35: C | M35: 93 | N35: 0 | O35: 0
A36: B5 | B36: Total EU27 | C36: 169903 | D36: 3289 | E36: 1795 | F36: 14976 | G36: 15999 | H36: 1227 | I36: 5432 | J36: 31648 | K36: 10866 | L36: 17477 | M36: 65261 | N36: 1558 | O36: 375
A37: IS | B37: Iceland | C37: 308 | D37: C | E37: C | F37: 93 | G37: 80 | H37: C | I37: C | J37: 33 | K37: 38 | L37: 20 | M37: 31 | N37: 0 | O37: 4
A38: LI | B38: Liechtenstein | C38: 113 | D38: 0 | E38: 0 | F38: 0 | G38: 0 | H38: 0 | I38: C | J38: 11 | K38: 0 | L38: C | M38: 90 | N38: 0 | O38: 0
A39: NO | B39: Norway | C39: 5316 | D39: 45 | E39: 95 | F39: 355 | G39: 538 | H39: C | I39: 369 | J39: 234 | K39: 201 | L39: 790 | M39: 2582 | N39: 68 | O39: C
A40: CH | B40: Switzerland | C40: 17401 | D40: 864 | E40: 23 | F40: 1122 | G40: 880 | H40: C | I40: 460 | J40: 2850 | K40: 888 | L40: 1449 | M40: 8491 | N40: 357 | O40: C
A41: AL | B41: Albania | C41: 146 | D41: 0 | E41: 0 | F41: 69 | G41: 44 | H41: 0 | I41: 0 | J41: 0 | K41: 15 | L41: C | M41: C | N41: 0 | O41: C
A42: BY | B42: Belarus | C42: 17 | D42: C | E42: C | F42: 0 | G42: C | H42: 0 | I42: 0 | J42: 0 | K42: C | L42: C | M42: 0 | N42: 0 | O42: C
A43: RU | B43: Russia | C43: 819 | D43: 0 | E43: 1 | F43: 39 | G43: 133 | H43: 0 | I43: 118 | J43: 176 | K43: 25 | L43: 114 | M43: 172 | N43: 5 | O43: 36
A44: TR | B44: Turkey | C44: 2854 | D44: 0 | E44: 47 | F44: 739 | G44: 561 | H44: 1 | I44: 120 | J44: 374 | K44: 188 | L44: 236 | M44: 537 | N44: 21 | O44: 30
A45: UA | B45: Ukraine | C45: 236 | D45: 27 | E45: C | F45: C | G45: 74 | H45: 0 | I45: 0 | J45: 10 | K45: C | L45: 11 | M45: 43 | N45: 10 | O45: 9
A46: CS | B46: Serbia and Montenegro | C46: 231 | D46: 0 | E46: C | F46: 0 | G46: 27 | H46: 0 | I46: C | J46: 3 | K46: 110 | L46: 36 | M46: 47 | N46: 0 | O46: C
A47: RS | B47: Serbia | C47: 190 | D47: 0 | E47: C | F47: 0 | G47: 27 | H47: 0 | I47: C | J47: 3 | K47: C | L47: C | M47: 46 | N47: 0 | O47: C
A48: ME | B48: Montenegro | C48: 41 | D48: 0 | E48: 0 | F48: 0 | G48: 0 | H48: 0 | I48: 0 | J48: 0 | K48: C | L48: C | M48: 1 | N48: 0 | O48: 0
A49: PB1 | B49: Other Europe | C49: 12764 | D49: C | E49: 163 | F49: 218 | G49: 586 | H49: C | I49: 282 | J49: 3533 | K49: 1179 | L49: 1317 | M49: 5411 | N49: 53 | O49: C
A50: AR | B50: Argentina | C50: 406 | D50: 2 | E50: 34 | F50: 38 | G50: 129 | H50: C | I50: 44 | J50: 25 | K50: C | L50: 89 | M50: 28 | N50: C | O50: 5
A51: BR | B51: Brazil | C51: 3479 | D51: 1 | E51: 37 | F51: 255 | G51: 469 | H51: 76 | I51: 207 | J51: 824 | K51: 38 | L51: 252 | M51: 1267 | N51: 20 | O51: 33
A52: CA | B52: Canada | C52: 8673 | D52: 173 | E52: 313 | F52: 287 | G52: 1246 | H52: 6 | I52: 1813 | J52: 1611 | K52: 219 | L52: 599 | M52: 2326 | N52: 54 | O52: 26
A53: CL | B53: Chile | C53: 622 | D53: 0 | E53: C | F53: 84 | G53: 79 | H53: 0 | I53: 115 | J53: 51 | K53: 55 | L53: 62 | M53: 139 | N53: C | O53: 23
A54: CO | B54: Colombia | C54: 431 | D54: 0 | E54: C | F54: C | G54: 136 | H54: 0 | I54: 72 | J54: 34 | K54: 28 | L54: 84 | M54: 58 | N54: 0 | O54: C
A55: MX | B55: Mexico | C55: 1422 | D55: 0 | E55: 13 | F55: 118 | G55: 226 | H55: C | I55: 300 | J55: 190 | K55: 101 | L55: 221 | M55: 224 | N55: C | O55: 15
A56: US | B56: United States incl. Puerto Rico | C56: 126303 | D56: 682 | E56: 823 | F56: 4103 | G56: 7276 | H56: 1172 | I56: 11127 | J56: 28639 | K56: 4204 | L56: 8719 | M56: 56854 | N56: 1799 | O56: 905
A57: UY | B57: Uruguay | C57: 52 | D57: C | E57: C | F57: C | G57: C | H57: 0 | I57: 0 | J57: C | K57: 0 | L57: 16 | M57: 18 | N57: 0 | O57: C
A58: VE | B58: Venezuela | C58: 91 | D58: 0 | E58: 0 | F58: 0 | G58: C | H58: 0 | I58: 80 | J58: 0 | K58: 0 | L58: C | M58: 0 | N58: 0 | O58: 5
A59: PB2 | B59: Other Central American Countries | C59: 8640 | D59: C | E59: 44 | F59: 432 | G59: 224 | H59: C | I59: 1419 | J59: 4162 | K59: 34 | L59: 397 | M59: 1790 | N59: 81 | O59: 44
A60: PB3 | B60: Other American Countries | C60: 1071 | D60: 0 | E60: 16 | F60: 19 | G60: 87 | H60: 648 | I60: 113 | J60: 9 | K60: 17 | L60: 29 | M60: 111 | N60: 1 | O60: 21
A61: CN | B61: China | C61: 11419 | D61: 6 | E61: 110 | F61: 786 | G61: 5895 | H61: 29 | I61: 213 | J61: 1725 | K61: 474 | L61: 482 | M61: 1456 | N61: 183 | O61: 60
A62: HK | B62: Hong Kong | C62: 7142 | D62: 0 | E62: 15 | F62: 349 | G62: 1046 | H62: C | I62: 134 | J62: 3221 | K62: 88 | L62: 353 | M62: 1859 | N62: 67 | O62: C
A63: IN | B63: India | C63: 10150 | D63: 14 | E63: 113 | F63: 666 | G63: 6651 | H63: C | I63: 157 | J63: 451 | K63: 424 | L63: 283 | M63: 1284 | N63: C | O63: 30
A64: ID | B64: Indonesia | C64: 833 | D64: 1 | E64: 14 | F64: 47 | G64: 221 | H64: 4 | I64: 100 | J64: 167 | K64: 26 | L64: 57 | M64: 182 | N64: 1 | O64: 13
A65: IR | B65: Iran | C65: 149 | D65: 0 | E65: 0 | F65: 0 | G65: 129 | H65: 0 | I65: 0 | J65: 0 | K65: C | L65: C | M65: C | N65: 0 | O65: C
A66: IL | B66: Israel | C66: 1633 | D66: C | E66: 12 | F66: 121 | G66: 314 | H66: C | I66: 211 | J66: 315 | K66: 65 | L66: 171 | M66: 402 | N66: C | O66: 9
A67: JP | B67: Japan | C67: 7609 | D67: 13 | E67: 110 | F67: 326 | G67: 332 | H67: 8 | I67: 661 | J67: 2369 | K67: 283 | L67: 996 | M67: 2413 | N67: 60 | O67: 38
A68: MY | B68: Malaysia | C68: 1587 | D68: 0 | E68: 20 | F68: 52 | G68: 618 | H68: 1 | I68: 95 | J68: 150 | K68: 62 | L68: 97 | M68: 377 | N68: 102 | O68: 13
A69: PK | B69: Pakistan | C69: 1477 | D69: C | E69: C | F69: 22 | G69: 1267 | H69: 0 | I69: 23 | J69: C | K69: 16 | L69: 25 | M69: 75 | N69: 22 | O69: 19
A70: PH | B70: Philippines | C70: 537 | D70: 0 | E70: C | F70: 30 | G70: 144 | H70: C | I70: 31 | J70: 63 | K70: 22 | L70: 87 | M70: 139 | N70: 0 | O70: 12
A71: SA | B71: Saudi Arabia | C71: 7956 | D71: 1 | E71: 129 | F71: 148 | G71: 1100 | H71: 49 | I71: 107 | J71: 565 | K71: 73 | L71: 345 | M71: 5206 | N71: 164 | O71: 69
A72: SG | B72: Singapore | C72: 8210 | D72: 23 | E72: 69 | F72: 1774 | G72: 431 | H72: C | I72: 298 | J72: 1705 | K72: 550 | L72: 485 | M72: 2765 | N72: 82 | O72: C
A73: KR | B73: South Korea | C73: 4308 | D73: 88 | E73: 14 | F73: 1083 | G73: 388 | H73: 0 | I73: 171 | J73: 1099 | K73: 223 | L73: 165 | M73: 1044 | N73: 20 | O73: 13
A74: TW | B74: Taiwan | C74: 2501 | D74: C | E74: C | F74: 185 | G74: 207 | H74: C | I74: 51 | J74: 1395 | K74: 65 | L74: 169 | M74: 411 | N74: 2 | O74: C
A75: TH | B75: Thailand | C75: 911 | D75: 0 | E75: 7 | F75: 25 | G75: 365 | H75: 0 | I75: 84 | J75: 142 | K75: 17 | L75: 43 | M75: 210 | N75: 9 | O75: 9
A76: PB4 | B76: Residual Gulf Arabian Countries | C76: 10471 | D76: C | E76: 551 | F76: 805 | G76: 2795 | H76: 94 | I76: 448 | J76: 1089 | K76: C | L76: 710 | M76: 3223 | N76: 177 | O76: C
A77: PB5 | B77: Other Near & Middle Eastern Countries | C77: 1708 | D77: 0 | E77: 22 | F77: 34 | G77: 243 | H77: 11 | I77: 767 | J77: 26 | K77: 35 | L77: 91 | M77: 428 | N77: 12 | O77: 39
A78: PB6 | B78: Other Asia | C78: 3109 | D78: C | E78: 82 | F78: 84 | G78: 1506 | H78: C | I78: 102 | J78: 163 | K78: 91 | L78: 267 | M78: 434 | N78: 181 | O78: 180
A79: AU | B79: Australia | C79: 9747 | D79: 6 | E79: 92 | F79: 223 | G79: 1800 | H79: 35 | I79: 1824 | J79: 1526 | K79: 352 | L79: 908 | M79: 2712 | N79: 208 | O79: 61
A80: NZ | B80: New Zealand | C80: 1013 | D80: C | E80: 16 | F80: 24 | G80: 387 | H80: 1 | I80: 207 | J80: 60 | K80: 38 | L80: 142 | M80: 121 | N80: 9 | O80: C
A81: PB7 | B81: Other Australasia & Oceania | C81: 413 | D81: 0 | E81: 18 | F81: 134 | G81: C | H81: 0 | I81: 42 | J81: 14 | K81: 20 | L81: 37 | M81: 130 | N81: 0 | O81: C
A82: EG | B82: Egypt | C82: 955 | D82: C | E82: 39 | F82: 167 | G82: 206 | H82: C | I82: 58 | J82: 61 | K82: 24 | L82: 103 | M82: 220 | N82: 50 | O82: C
A83: MA | B83: Morocco incl. Western Sahara | C83: 437 | D83: C | E83: 1 | F83: 241 | G83: 112 | H83: C | I83: 4 | J83: 0 | K83: 0 | L83: 23 | M83: 40 | N83: 2 | O83: 9
A84: ZA | B84: South Africa | C84: 2571 | D84: C | E84: 30 | F84: 210 | G84: 356 | H84: C | I84: 319 | J84: 402 | K84: 192 | L84: 298 | M84: 703 | N84: 23 | O84: 17
A85: PB8 | B85: Other North Africa | C85: 532 | D85: C | E85: 71 | F85: 72 | G85: 84 | H85: 11 | I85: 29 | J85: C | K85: C | L85: 14 | M85: 214 | N85: C | O85: 25
A86: PB9 | B86: Other Africa | C86: 8764 | D86: 0 | E86: 149 | F86: 458 | G86: 3608 | H86: 383 | I86: 290 | J86: 423 | K86: 186 | L86: 328 | M86: 2699 | N86: 78 | O86: 162
A87: 9A | B87: International Organisations | C87: 278 | D87: 0 | E87: 0 | F87: 0 | G87: 0 | H87: 0 | I87: 0 | J87: 278 | K87: 0 | L87: 0 | M87: 0 | N87: 0 | O87: 0
A88: D5 | B88: Rest of World | C88: 297815 | D88: 1982 | E88: 3324 | F88: 16056 | G88: 43026 | H88: 2692 | I88: 23075 | J88: 60187 | K88: 11233 | L88: 21145 | M88: 108981 | N88: 4010 | O88: 2104
A89: W1 | B89: World total | C89: 467718 | D89: 5271 | E89: 5119 | F89: 31032 | G89: 59025 | H89: 3919 | I89: 28507 | J89: 91835 | K89: 22099 | L89: 38622 | M89: 174242 | N89: 5568 | O89: 2479
A91: Table 9.13.2: Imports by service type and partner country 2023 (£ million)
A92: Country Code | B92: Country Name | C92: 0: Total Services | D92: 1: Manufacturing | E92: 2: Maintenance and Repair | F92: 3: Transportation | G92: 4: Travel | H92: 5: Construction | I92: 6: Insurance and Pension | J92: 7: Financial | K92: 8: Intellectual property | L92: 9: Telecommunications, computer and information services | M92: 10: Other Business Services | N92: 11: Personal, Cultural and Recreational | O92: 12: Government
A93: AT | B93: Austria | C93: 1564 | D93: 22 | E93: 41 | F93: 215 | G93: 764 | H93: 67 | I93: 74 | J93: 29 | K93: 34 | L93: 38 | M93: 273 | N93: C | O93: C
A94: BE | B94: Belgium | C94: 2514 | D94: C | E94: C | F94: 318 | G94: 603 | H94: 40 | I94: 214 | J94: 102 | K94: 42 | L94: 106 | M94: 1008 | N94: 18 | O94: 51
A95: BG | B95: Bulgaria | C95: 1441 | D95: C | E95: 0 | F95: 306 | G95: 439 | H95: 0 | I95: 16 | J95: 87 | K95: 0 | L95: 92 | M95: 365 | N95: C | O95: 128
A96: HR | B96: Croatia | C96: 917 | D96: 67 | E96: 0 | F96: 140 | G96: 634 | H96: 0 | I96: 15 | J96: 0 | K96: 0 | L96: C | M96: 47 | N96: 0 | O96: C
A97: CY | B97: Cyprus | C97: 1299 | D97: C | E97: 0 | F97: 168 | G97: 763 | H97: C | I97: 88 | J97: 18 | K97: C | L97: 74 | M97: 101 | N97: 0 | O97: 77
A98: CZ | B98: Czechia | C98: 1170 | D98: C | E98: 9 | F98: 217 | G98: 321 | H98: C | I98: 45 | J98: 10 | K98: 51 | L98: 76 | M98: 415 | N98: C | O98: 7
A99: DK | B99: Denmark | C99: 2601 | D99: 112 | E99: 158 | F99: 661 | G99: 316 | H99: 246 | I99: 84 | J99: 73 | K99: 153 | L99: 43 | M99: 700 | N99: 46 | O99: 9
A100: EE | B100: Estonia | C100: 200 | D100: C | E100: 0 | F100: 27 | G100: 32 | H100: 0 | I100: C | J100: C | K100: C | L100: 0 | M100: 121 | N100: 1 | O100: 7
A101: FI | B101: Finland | C101: 784 | D101: C | E101: 3 | F101: 144 | G101: 245 | H101: 53 | I101: 32 | J101: 19 | K101: 41 | L101: 46 | M101: 195 | N101: 1 | O101: C
...

Sheet CPI Import Intensity by Class
A1: CPI Import Intensity of Household purchases, COICOP class level categories | C1: https://www.ons.gov.uk/economy/inflationandpriceindices/datasets/contributionstothe12monthrateofcpibyimportintensity
A3: COICOP CSDB_Index | B3: COICOP Class level item | C3: Direct Import Penetration | D3: Total | E3: Group | G3: CPI weight | H3: Goods? | I3: Goods direct import penetration | J3: Goods total import penetration | L3: Goods weight check
A4: D7D5 | B4: 01.1.1 : BREAD & CEREALS | C4: 0.224 | D4: 0.346 | E4: 25-40% | G4: ='ONS - CPI weights'!AB25 -> 20.081 | H4: G | I4: =IF(H4="G",C4*(G4/1000),"") -> 0.004498144 | J4: =IF(H4="G",D4*(G4/1000),"") -> 0.006948026 | L4: =IF(H4="G",G4,"") -> 20.081
A5: D7D6 | B5: 01.1.2 : MEAT | C5: 0.302 | D5: 0.417 | E5: 40% plus | G5: ='ONS - CPI weights'!AB33 -> 20.0618 | H5: G | I5: =IF(H5="G",C5*(G5/1000),"") -> 0.0060586636 | J5: =IF(H5="G",D5*(G5/1000),"") -> 0.0083657706 | L5: =IF(H5="G",G5,"") -> 20.0618
A6: D7D7 | B6: 01.1.3 : FISH | C6: 0.322 | D6: 0.39 | E6: 25-40% | G6: ='ONS - CPI weights'!AB41 -> 4.0117 | H6: G | I6: =IF(H6="G",C6*(G6/1000),"") -> 0.0012917674 | J6: =IF(H6="G",D6*(G6/1000),"") -> 0.001564563 | L6: =IF(H6="G",G6,"") -> 4.0117
A7: D7D8 | B7: 01.1.4 : MILK, CHEESE & EGGS | C7: 0.215 | D7: 0.311 | E7: 25-40% | G7: ='ONS - CPI weights'!AB45 -> 12.9864 | H7: G | I7: =IF(H7="G",C7*(G7/1000),"") -> 0.002792076 | J7: =IF(H7="G",D7*(G7/1000),"") -> 0.0040387704 | L7: =IF(H7="G",G7,"") -> 12.9864
A8: D7D9 | B8: 01.1.5 : OILS & FATS | C8: 0.325 | D8: 0.38 | E8: 25-40% | G8: ='ONS - CPI weights'!AB52 -> 3.2403 | H8: G | I8: =IF(H8="G",C8*(G8/1000),"") -> 0.0010530975 | J8: =IF(H8="G",D8*(G8/1000),"") -> 0.001231314 | L8: =IF(H8="G",G8,"") -> 3.2403
A9: D7DA | B9: 01.1.6 : FRUIT | C9: 0.376 | D9: 0.476 | E9: 40% plus | G9: ='ONS - CPI weights'!AB56 -> 9.5811 | H9: G | I9: =IF(H9="G",C9*(G9/1000),"") -> 0.0036024936 | J9: =IF(H9="G",D9*(G9/1000),"") -> 0.0045606036 | L9: =IF(H9="G",G9,"") -> 9.5811
A10: D7DB | B10: 01.1.7 : VEGETABLES INCLUDING POTATOES AND OTHER TUBERS | C10: 0.382 | D10: 0.449 | E10: 40% plus | G10: ='ONS - CPI weights'!AB60 -> 14.7858 | H10: G | I10: =IF(H10="G",C10*(G10/1000),"") -> 0.0056481756 | J10: =IF(H10="G",D10*(G10/1000),"") -> 0.0066388242 | L10: =IF(H10="G",G10,"") -> 14.7858
A11: D7DC | B11: 01.1.8 : SUGAR, JAM, HONEY, SYRUPS, CHOCOLATE & CONFECTIONERY | C11: 0.291 | D11: 0.341 | E11: 25-40% | G11: ='ONS - CPI weights'!AB67 -> 11.7476 | H11: G | I11: =IF(H11="G",C11*(G11/1000),"") -> 0.0034185516 | J11: =IF(H11="G",D11*(G11/1000),"") -> 0.0040059316 | L11: =IF(H11="G",G11,"") -> 11.7476
A12: D7DD | B12: 01.1.9 : FOOD PRODUCTS | C12: 0.317 | D12: 0.378 | E12: 25-40% | G12: ='ONS - CPI weights'!AB73 -> 4.9253 | H12: G | I12: =IF(H12="G",C12*(G12/1000),"") -> 0.0015613201 | J12: =IF(H12="G",D12*(G12/1000),"") -> 0.0018617634 | L12: =IF(H12="G",G12,"") -> 4.9253
A13: D7DE | B13: 01.2.1 : COFFEE, TEA, COCOA | C13: 0.298 | D13: 0.343 | E13: 25-40% | G13: ='ONS - CPI weights'!AB79 -> 2.5899 | H13: G | I13: =IF(H13="G",C13*(G13/1000),"") -> 0.0007717902 | J13: =IF(H13="G",D13*(G13/1000),"") -> 0.0008883357 | L13: =IF(H13="G",G13,"") -> 2.5899
A14: D7DF | B14: 01.2.2 : MINERAL WATERS, SOFT DRINKS AND JUICES | C14: 0.202 | D14: 0.291 | E14: 25-40% | G14: ='ONS - CPI weights'!AB83 -> 9.1354 | H14: G | I14: =IF(H14="G",C14*(G14/1000),"") -> 0.0018453508 | J14: =IF(H14="G",D14*(G14/1000),"") -> 0.0026584014 | L14: =IF(H14="G",G14,"") -> 9.1354
A15: D7DG | B15: 02.1.1 : SPIRITS | C15: 0.08 | D15: 0.093 | E15: 0-10% | G15: ='ONS - CPI weights'!AB89 -> 6.0627 | H15: G | I15: =IF(H15="G",C15*(G15/1000),"") -> 0.000485016 | J15: =IF(H15="G",D15*(G15/1000),"") -> 0.0005638311 | L15: =IF(H15="G",G15,"") -> 6.0627
A16: D7DH | B16: 02.1.2 : WINE (INC PERRY) | C16: 0.08 | D16: 0.093 | E16: 0-10% | G16: ='ONS - CPI weights'!AB90 -> 9.4115 | H16: G | I16: =IF(H16="G",C16*(G16/1000),"") -> 0.00075292 | J16: =IF(H16="G",D16*(G16/1000),"") -> 0.0008752695 | L16: =IF(H16="G",G16,"") -> 9.4115
A17: D7DI | B17: 02.1.3 : BEER | C17: 0.08 | D17: 0.093 | E17: 0-10% | G17: ='ONS - CPI weights'!AB94 -> 5.4568 | H17: G | I17: =IF(H17="G",C17*(G17/1000),"") -> 0.000436544 | J17: =IF(H17="G",D17*(G17/1000),"") -> 0.0005074824 | L17: =IF(H17="G",G17,"") -> 5.4568
A18: D7CB | B18: 02.2 : TOBACCO | C18: 0.08 | D18: 0.093 | E18: 0-10% | G18: ='ONS - CPI weights'!AB98 -> 18.2186 | H18: G | I18: =IF(H18="G",C18*(G18/1000),"") -> 0.001457488 | J18: =IF(H18="G",D18*(G18/1000),"") -> 0.0016943298 | L18: =IF(H18="G",G18,"") -> 18.2186
A19: D7DK | B19: 03.1.2 : GARMENTS | C19: 0.392 | D19: 0.398 | E19: 25-40% | G19: ='ONS - CPI weights'!AB104 -> 43.4202 | H19: G | I19: =IF(H19="G",C19*(G19/1000),"") -> 0.017020718 | J19: =IF(H19="G",D19*(G19/1000),"") -> 0.01728124 | L19: =IF(H19="G",G19,"") -> 43.4202
A20: D7DL | B20: 03.1.3 :OTHER ARTICLES OF CLOTHING & ACCESSORIES | C20: 0.286 | D20: 0.305 | E20: 25-40% | G20: ='ONS - CPI weights'!AB108 -> 6.0996 | H20: G | I20: =IF(H20="G",C20*(G20/1000),"") -> 0.0017444856 | J20: =IF(H20="G",D20*(G20/1000),"") -> 0.001860378 | L20: =IF(H20="G",G20,"") -> 6.0996
A21: D7DM | B21: 03.1.4 : DRY-CLEANING, REPAIR AND HIRE OF CLOTHING | C21: 0.005 | D21: 0.103 | E21: 10-25% | G21: ='ONS - CPI weights'!AB111 -> 0.5912 | I21: =IF(H21="G",C21*(G21/1000),"") | J21: =IF(H21="G",D21*(G21/1000),"") | L21: =IF(H21="G",G21,"")
A22: D7CD | B22: 03.2 : FOOTWEAR INCLUDING REPAIRS | C22: 0.46 | D22: 0.464 | E22: 40% plus | G22: ='ONS - CPI weights'!AB115 -> 8.4964 | H22: G | I22: =IF(H22="G",C22*(G22/1000),"") -> 0.003908344 | J22: =IF(H22="G",D22*(G22/1000),"") -> 0.0039423296 | L22: =IF(H22="G",G22,"") -> 8.4964
A23: D7CE | B23: 04.1 : ACTUAL RENTS FOR HOUSING | C23: 0 | D23: 0.068 | E23: 0-10% | G23: ='ONS - CPI weights'!AB120 -> 78.2846 | I23: =IF(H23="G",C23*(G23/1000),"") | J23: =IF(H23="G",D23*(G23/1000),"") | L23: =IF(H23="G",G23,"")
A24: D7DN | B24: 04.3.1 : PRODUCTS FOR THE REGULAR REPAIR OF DWELLING | C24: 0.135 | D24: 0.226 | E24: 10-25% | G24: ='ONS - CPI weights'!AB123 -> 1.0629 | H24: G | I24: =IF(H24="G",C24*(G24/1000),"") -> 0.0001434915 | J24: =IF(H24="G",D24*(G24/1000),"") -> 0.0002402154 | L24: =IF(H24="G",G24,"") -> 1.0629
A25: D7DO | B25: 04.3.2 : SERVICES FOR THE REGULAR REPAIR OF DWELLING | C25: 0 | D25: 0.131 | E25: 10-25% | G25: ='ONS - CPI weights'!AB124 -> 1.8024 | I25: =IF(H25="G",C25*(G25/1000),"") | J25: =IF(H25="G",D25*(G25/1000),"") | L25: =IF(H25="G",G25,"")
A26: D7DR | B26: 04.4.1 : WATER SUPPLY | C26: 0 | D26: 0.09 | E26: 0-10% | G26: ='ONS - CPI weights'!AB131 -> 4.4205 | H26: G | I26: =IF(H26="G",C26*(G26/1000),"") -> 0 | J26: =IF(H26="G",D26*(G26/1000),"") -> 0.000397845 | L26: =IF(H26="G",G26,"") -> 4.4205
A27: D7DQ | B27: 04.4.3 : SEWERAGE COLLECTION | C27: 0 | D27: 0.1 | E27: 0-10% | G27: ='ONS - CPI weights'!AB132 -> 4.8811 | I27: =IF(H27="G",C27*(G27/1000),"") | J27: =IF(H27="G",D27*(G27/1000),"") | L27: =IF(H27="G",G27,"")
A28: D7DT | B28: 04.5.1 : ELECTRICITY | C28: 0.001 | D28: 0.232 | E28: Energy | G28: ='ONS - CPI weights'!AB135 -> 23.3142 | H28: G | I28: =IF(H28="G",C28*(G28/1000),"") -> 2.33142e-05 | J28: =IF(H28="G",D28*(G28/1000),"") -> 0.0054088944 | L28: =IF(H28="G",G28,"") -> 23.3142
A29: D7DU | B29: 04.5.2 : GAS | C29: 0.005 | D29: 0.25 | E29: Energy | G29: ='ONS - CPI weights'!AB136 -> 16.1597 | H29: G | I29: =IF(H29="G",C29*(G29/1000),"") -> 8.07985e-05 | J29: =IF(H29="G",D29*(G29/1000),"") -> 0.004039925 | L29: =IF(H29="G",G29,"") -> 16.1597
A30: D7DV | B30: 04.5.3 : LIQUID FUELS | C30: 0.203 | D30: 0.305 | E30: Energy | G30: ='ONS - CPI weights'!AB139 -> 0.9871 | H30: G | I30: =IF(H30="G",C30*(G30/1000),"") -> 0.0002003813 | J30: =IF(H30="G",D30*(G30/1000),"") -> 0.0003010655 | L30: =IF(H30="G",G30,"") -> 0.9871
A31: D7DW | B31: 04.5.4 : SOLID FUELS | C31: 0 | D31: 0.211 | E31: Energy | G31: ='ONS - CPI weights'!AB140 -> 0.4271 | H31: G | I31: =IF(H31="G",C31*(G31/1000),"") -> 0 | J31: =IF(H31="G",D31*(G31/1000),"") -> 9.01181e-05 | L31: =IF(H31="G",G31,"") -> 0.4271
A32: D7DY | B32: 05.1.1 : FURNITURE, FURNISHINGS | C32: 0.251 | D32: 0.301 | E32: 25-40% | G32: ='ONS - CPI weights'!AB143 -> 19.8363 | H32: G | I32: =IF(H32="G",C32*(G32/1000),"") -> 0.0049789113 | J32: =IF(H32="G",D32*(G32/1000),"") -> 0.0059707263 | L32: =IF(H32="G",G32,"") -> 19.8363
A33: D7DZ | B33: 05.1.2 : CARPETS & OTHER FLOOR COVERINGS | C33: 0.188 | D33: 0.226 | E33: 10-25% | G33: ='ONS - CPI weights'!AB148 -> 5.5174 | H33: G | I33: =IF(H33="G",C33*(G33/1000),"") -> 0.0010372712 | J33: =IF(H33="G",D33*(G33/1000),"") -> 0.0012469324 | L33: =IF(H33="G",G33,"") -> 5.5174
A34: D7CJ | B34: 05.2 : HOUSEHOLD TEXTILES | C34: 0.188 | D34: 0.226 | E34: 10-25% | G34: ='ONS - CPI weights'!AB152 -> 5.938 | H34: G | I34: =IF(H34="G",C34*(G34/1000),"") -> 0.001116344 | J34: =IF(H34="G",D34*(G34/1000),"") -> 0.001341988 | L34: =IF(H34="G",G34,"") -> 5.938
A35: D7E3 | B35: 05.3.1 : MAJOR HH APPLIANCES & SMALL ELECTRICAL HH APPLIANCES | C35: 0.379 | D35: 0.38 | E35: 25-40% | G35: ='ONS - CPI weights'!AB158 -> 9.0184 | H35: G | I35: =IF(H35="G",C35*(G35/1000),"") -> 0.0034179736 | J35: =IF(H35="G",D35*(G35/1000),"") -> 0.003426992 | L35: =IF(H35="G",G35,"") -> 9.0184
A36: D7E4 | B36: 05.3.3 : REPAIR OF HOUSEHOLD APPLIANCES | C36: 0.001 | D36: 0.146 | E36: 10-25% | G36: ='ONS - CPI weights'!AB167 -> 0.4991 | I36: =IF(H36="G",C36*(G36/1000),"") | J36: =IF(H36="G",D36*(G36/1000),"") | L36: =IF(H36="G",G36,"")
A37: D7CL | B37: 05.4 : GLASSWARE, TABLEWARE AND HOUSEHOLD UTENSILS | C37: 0.214 | D37: 0.232 | E37: 10-25% | G37: ='ONS - CPI weights'!AB169 -> 5.8458 | H37: G | I37: =IF(H37="G",C37*(G37/1000),"") -> 0.0012510012 | J37: =IF(H37="G",D37*(G37/1000),"") -> 0.0013562256 | L37: =IF(H37="G",G37,"") -> 5.8458
A38: D7CM | B38: 05.5 : TOOLS AND EQUIPMENT FOR HOUSE AND GARDEN | C38: 0.305 | D38: 0.306 | E38: 25-40% | G38: ='ONS - CPI weights'!AB174 -> 6.1295 | H38: G | I38: =IF(H38="G",C38*(G38/1000),"") -> 0.0018694975 | J38: =IF(H38="G",D38*(G38/1000),"") -> 0.001875627 | L38: =IF(H38="G",G38,"") -> 6.1295
A39: D7E5 | B39: 05.6.1 : NON-DURABLE HOUSEHOLD GOODS | C39: 0.251 | D39: 0.263 | E39: 25-40% | G39: ='ONS - CPI weights'!AB181 -> 6.5318 | H39: G | I39: =IF(H39="G",C39*(G39/1000),"") -> 0.0016394818 | J39: =IF(H39="G",D39*(G39/1000),"") -> 0.0017178634 | L39: =IF(H39="G",G39,"") -> 6.5318
A40: D7E6 | B40: 05.6.2 : DOMESTIC SERVICES AND HOME CARE SERVICES | C40: 0.005 | D40: 0.008 | E40: 0-10% | G40: ='ONS - CPI weights'!AB184 -> 3.1576 | I40: =IF(H40="G",C40*(G40/1000),"") | J40: =IF(H40="G",D40*(G40/1000),"") | L40: =IF(H40="G",G40,"")
A41: D7F7 | B41: 06.1.1 : PHARMACEUTICAL PRODUCTS | C41: 0.37 | D41: 0.467 | E41: 40% plus | G41: ='ONS - CPI weights'!AB189 -> 7.2188 | H41: G | I41: =IF(H41="G",C41*(G41/1000),"") -> 0.002670956 | J41: =IF(H41="G",D41*(G41/1000),"") -> 0.0033711796 | L41: =IF(H41="G",G41,"") -> 7.2188
A42: D7F8 | B42: 06.1.2 : OTHER MEDICAL AND THERAPEUTIC EQUIPMENT | C42: 0.493 | D42: 0.494 | E42: 40% plus | G42: ='ONS - CPI weights'!AB190 -> 3.6661 | H42: G | I42: =IF(H42="G",C42*(G42/1000),"") -> 0.0018073873 | J42: =IF(H42="G",D42*(G42/1000),"") -> 0.0018110534 | L42: =IF(H42="G",G42,"") -> 3.6661
A43: D7FA | B43: 06.2.1 : MEDICAL SERVICES AND PARAMEDICAL SERVICES: | C43: 0.134 | D43: 0.149 | E43: 10-25% | G43: ='ONS - CPI weights'!AB196 -> 4.0776 | I43: =IF(H43="G",C43*(G43/1000),"") | J43: =IF(H43="G",D43*(G43/1000),"") | L43: =IF(H43="G",G43,"")
A44: D7FB | B44: 06.2.2 : DENTAL SERVICES: | C44: 0.134 | D44: 0.149 | E44: 10-25% | G44: ='ONS - CPI weights'!AB197 -> 3.1296 | I44: =IF(H44="G",C44*(G44/1000),"") | J44: =IF(H44="G",D44*(G44/1000),"") | L44: =IF(H44="G",G44,"")
A45: D7FC | B45: 06.3 : HOSPITAL SERVICES | C45: 0.134 | D45: 0.149 | E45: 10-25% | G45: ='ONS - CPI weights'!AB199 -> 8.1188 | I45: =IF(H45="G",C45*(G45/1000),"") | J45: =IF(H45="G",D45*(G45/1000),"") | L45: =IF(H45="G",G45,"")
A46: D7E8 | B46: 07.1.1A : NEW CARS | C46: 0.548 | D46: 0.601 | E46: 40% plus | G46: ='ONS - CPI weights'!AB202 -> 16.6727 | H46: G | I46: =IF(H46="G",C46*(G46/1000),"") -> 0.0091366396 | J46: =IF(H46="G",D46*(G46/1000),"") -> 0.010020293 | L46: =IF(H46="G",G46,"") -> 16.6727
A47: D7E9 | B47: 07.1.1B : SECOND-HAND CARS | C47: 0.548 | D47: 0.601 | E47: 40% plus | G47: ='ONS - CPI weights'!AB203 -> 23.7757 | H47: G | I47: =IF(H47="G",C47*(G47/1000),"") -> 0.013029084 | J47: =IF(H47="G",D47*(G47/1000),"") -> 0.014289196 | L47: =IF(H47="G",G47,"") -> 23.7757
A48: D7EA | B48: 07.1.2 : MOTOR CYCLES AND BICYCLES | C48: 0.386 | D48: 0.524 | E48: 40% plus | G48: ='ONS - CPI weights'!AB204 -> 2.13 | H48: G | I48: =IF(H48="G",C48*(G48/1000),"") -> 0.00082218 | J48: =IF(H48="G",D48*(G48/1000),"") -> 0.00111612 | L48: =IF(H48="G",G48,"") -> 2.13
A49: D7EB | B49: 07.2.1 : SPARE PARTS & ACCESSORIES | C49: 0.618 | D49: 0.651 | E49: 40% plus | G49: ='ONS - CPI weights'!AB209 -> 4.1481 | H49: G | I49: =IF(H49="G",C49*(G49/1000),"") -> 0.0025635258 | J49: =IF(H49="G",D49*(G49/1000),"") -> 0.0027004131 | L49: =IF(H49="G",G49,"") -> 4.1481
A50: D7EC | B50: 07.2.2 : FUELS & LUBRICANTS | C50: 0.205 | D50: 0.307 | E50: Energy | G50: ='ONS - CPI weights'!AB212 -> 30.8627 | H50: G | I50: =IF(H50="G",C50*(G50/1000),"") -> 0.0063268535 | J50: =IF(H50="G",D50*(G50/1000),"") -> 0.0094748489 | L50: =IF(H50="G",G50,"") -> 30.8627
A51: D7ED | B51: 07.2.3 : MAINTENANCE & REPAIRS | C51: 0 | D51: 0.025 | E51: 0-10% | G51: ='ONS - CPI weights'!AB216 -> 15.6273 | I51: =IF(H51="G",C51*(G51/1000),"") | J51: =IF(H51="G",D51*(G51/1000),"") | L51: =IF(H51="G",G51,"")
A52: D7EE | B52: 07.2.4 : OTHER SERVICES FOR PERSONAL TRANSPORT EQUIPMENT | C52: 0.002 | D52: 0.081 | E52: 0-10% | G52: ='ONS - CPI weights'!AB217 -> 16.8095 | I52: =IF(H52="G",C52*(G52/1000),"") | J52: =IF(H52="G",D52*(G52/1000),"") | L52: =IF(H52="G",G52,"")
A53: D7EF | B53: 07.3.1 : PASSENGER TRANSPORT BY RAILWAY | C53: 0.009 | D53: 0.14 | E53: 10-25% | G53: ='ONS - CPI weights'!AB223 -> 8.438 | I53: =IF(H53="G",C53*(G53/1000),"") | J53: =IF(H53="G",D53*(G53/1000),"") | L53: =IF(H53="G",G53,"")
A54: D7EG | B54: 07.3.2 : PASSENGER TRANSPORT BY ROAD | C54: 0 | D54: 0.136 | E54: 10-25% | G54: ='ONS - CPI weights'!AB226 -> 9.8858 | I54: =IF(H54="G",C54*(G54/1000),"") | J54: =IF(H54="G",D54*(G54/1000),"") | L54: =IF(H54="G",G54,"")
A55: D7EH | B55: 07.3.3 : PASSENGER TRANSPORT BY AIR | C55: 0.084 | D55: 0.286 | E55: 25-40% | G55: ='ONS - CPI weights'!AB230 -> 5.8362 | I55: =IF(H55="G",C55*(G55/1000),"") | J55: =IF(H55="G",D55*(G55/1000),"") | L55: =IF(H55="G",G55,"")
A56: D7EI | B56: 07.3.4 : PASSENGER TRANSPORT BY SEA AND INLAND WATERWAY | C56: 0.001 | D56: 0.191 | E56: 10-25% | G56: ='ONS - CPI weights'!AB231 -> 1.2701 | I56: =IF(H56="G",C56*(G56/1000),"") | J56: =IF(H56="G",D56*(G56/1000),"") | L56: =IF(H56="G",G56,"")
A57: D7CR | B57: 08.1 : POSTAL SERVICES | C57: 0.012 | D57: 0.154 | E57: 10-25% | G57: ='ONS - CPI weights'!AB233 -> 0.9947 | I57: =IF(H57="G",C57*(G57/1000),"") | J57: =IF(H57="G",D57*(G57/1000),"") | L57: =IF(H57="G",G57,"")
A58: D7EM | B58: 08.2 : TELEPHONE AND TELEFAX EQUIPMENT AND SERVICES | C58: 0.252 | D58: 0.263 | E58: 25-40% | G58: ='ONS - CPI weights'!AB235 -> 22.0927 | H58: G | I58: =IF(H58="G",C58*(G58/1000),"") -> 0.0055673604 | J58: =IF(H58="G",D58*(G58/1000),"") -> 0.0058103801 | L58: =IF(H58="G",G58,"") -> 22.0927
A59: D7EN | B59: 09.1.1 : EQUIPMENT FOR SOUND & PICTUR | C59: 0.252 | D59: 0.263 | E59: 25-40% | G59: ='ONS - CPI weights'!AB244 -> 3.0491 | H59: G | I59: =IF(H59="G",C59*(G59/1000),"") -> 0.0007683732 | J59: =IF(H59="G",D59*(G59/1000),"") -> 0.0008019133 | L59: =IF(H59="G",G59,"") -> 3.0491
A60: D7EO | B60: 09.1.2 : PHOTOGRAPHIC, CINEMATOGRAPHIC & OPTICAL EQUIPMENT | C60: 0.252 | D60: 0.263 | E60: 25-40% | G60: ='ONS - CPI weights'!AB249 -> 0.7916 | H60: G | I60: =IF(H60="G",C60*(G60/1000),"") -> 0.0001994832 | J60: =IF(H60="G",D60*(G60/1000),"") -> 0.0002081908 | L60: =IF(H60="G",G60,"") -> 0.7916
A61: D7EP | B61: 09.1.3 : INFORMATION PROCESSING EQUIPMENT | C61: 0.235 | D61: 0.246 | E61: 10-25% | G61: ='ONS - CPI weights'!AB250 -> 5.7869 | H61: G | I61: =IF(H61="G",C61*(G61/1000),"") -> 0.0013599215 | J61: =IF(H61="G",D61*(G61/1000),"") -> 0.0014235774 | L61: =IF(H61="G",G61,"") -> 5.7869
A62: D7ES | B62: 09.1.4 : RECORDING MEDIA | C62: 0.095 | D62: 0.193 | E62: 10-25% | G62: ='ONS - CPI weights'!AB254 -> 4.738 | H62: G | I62: =IF(H62="G",C62*(G62/1000),"") -> 0.00045011 | J62: =IF(H62="G",D62*(G62/1000),"") -> 0.000914434 | L62: =IF(H62="G",G62,"") -> 4.738
