Workbook
Name Data: [1]sheet0!$C$2

Sheet CHARTS>>

Sheet DATA>>

Sheet Chart Data
B1: Contributions to GDP growth | M1: G7 GDP growth | V1: Contributions to GDP growth | AF1: 2026 forecast vs consensus (HMT survey) | AI1: High | AJ1: Low | AL1: 2026 forecast vs consensus (Focus) | AO1: High | AP1: Low | AR1: Contributions to CPI inflation | AZ1: WFJ forecast - public sector, private sector by pay level | BE1: WFJ forecast - public sector, private sector by pay level | BK1: WFJ forecast - public sector, private sector by pay level | BS1: AE debt dynamics (2026-2030) | CO1: GDIP/GGDBT
B2: Consumer spending | C2: Private investment | D2: Government | E2: Net trade | F2: Other | G2: GDP growth | I2: Private investment | J2: Government | K2: Net trade | N2: ='Annual Data'!AJ2 -> UK | O2: ='Annual Data'!AK2 -> US | P2: ='Annual Data'!AL2 -> Japan | Q2: ='Annual Data'!AM2 -> Germany | R2: ='Annual Data'!AN2 -> France | S2: ='Annual Data'!AO2 -> Italy | T2: ='Annual Data'!AP2 -> Canada | X2: Government consumption & investment | Y2: Other | Z2: GDP growth | AC2: Government consumption & investment | AD2: Other | AG2: OE | AH2: Consensus forecast | AI2: Consensus range* | AJ2: Consensus low | AM2: OE | AN2: Consensus forecast | AO2: Consensus range* | AP2: Consensus low | AS2: Food | AT2: Petrol | AU2: Energy | AV2: Other | AW2: CPI | AX2: 2% LINE | BA2: Government & other services | BB2: Private sector - higher paid* | BC2: Private sector - lower paid* | BF2: Government & other services | BG2: Private sector - higher paid* | BH2: Private sector - lower paid* | BI2: Total | BL2: Government & other services | BM2: Private sector - higher paid* | BN2: Private sector - lower paid* | BO2: Check | BQ2: Private sector | BT2: ='Annual Data'!AQ2 -> UK | BU2: ='Annual Data'!AR2 -> US | BV2: ='Annual Data'!AS2 -> Japan | BW2: ='Annual Data'!AT2 -> Canada | BX2: ='Annual Data'!AU2 -> Australia | BY2: ='Annual Data'!AV2 -> Denmark | BZ2: ='Annual Data'!AW2 -> Sweden | CA2: ='Annual Data'!AX2 -> Switzerland | ... CM2: ='Annual Data'!BJ2 -> Portugal | CP2: ='Annual Data'!AQ2 -> UK | CQ2: ='Annual Data'!BM2 -> Japan | CR2: ='Annual Data'!BN2 -> Canada | CS2: ='Annual Data'!BO2 -> Australia | CT2: ='Annual Data'!BP2 -> Denmark | CU2: ='Annual Data'!BQ2 -> Sweden | CV2: ='Annual Data'!BR2 -> Switzerland | CW2: ='Annual Data'!BS2 -> S Korea | CX2: ='Annual Data'!BT2 -> Germany | ... DI2: ='Annual Data'!CE2 -> UK
A3: 2000- 2009 | B3: =AVERAGE(B22:B31) -> 1.1768592 | C3: =AVERAGE(C22:C31) -> 0.083159375 | D3: =AVERAGE(D22:D31) -> 0.7700912 | E3: =AVERAGE(E22:E31) -> -0.1076214 | F3: =AVERAGE(F22:F31) -> -0.17813516 | G3: =AVERAGE(G22:G31) -> 1.7443533 | M3: 2025 | N3: =100*(('Annual Data'!AJ59/'Annual Data'!AJ58)-1) -> 1.4175184 | O3: =100*(('Annual Data'!AK59/'Annual Data'!AK58)-1) -> 2.0417858 | P3: =100*(('Annual Data'!AL59/'Annual Data'!AL58)-1) -> 1.2519868 | Q3: =100*(('Annual Data'!AM59/'Annual Data'!AM58)-1) -> 0.24336057 | R3: =100*(('Annual Data'!AN59/'Annual Data'!AN58)-1) -> 0.89005196 | S3: =100*(('Annual Data'!AO59/'Annual Data'!AO58)-1) -> 0.55983715 | T3: =100*(('Annual Data'!AP59/'Annual Data'!AP58)-1) -> 1.6286911 | V3: 44562 | W3: Q1 22 | X3: =100*((AC3-AC$6)/'Quarterly Data'!$G$206) -> 0.42406038 | Y3: =100*((AD3-AD$6)/'Quarterly Data'!$G$206) -> -1.3372202 | Z3: =100*(('Quarterly Data'!G203/'Quarterly Data'!$G$206)-1) -> -0.91315981 | AB3: 44562 | AC3: ='Quarterly Data'!J203+'Quarterly Data'!N203 -> 162821 | AD3: ='Quarterly Data'!G203-'Chart Data'!AC3 -> 519706 | AF3: GDP | AG3: =100*(('Annual Data'!B60/'Annual Data'!B59)-1) -> 0.96143326 | AH3: 1.2 | AI3: 1.4 | AJ3: =AG3 -> 0.96143326 | AL3: GDP | AM3: =100*(('Annual Data'!B$60/'Annual Data'!B$59)-1) -> 0.96143326 | AN3: 1.1 | AO3: 1.5 | AP3: 0.9 | AR3: =[2]Contributions!B291 -> 44562 | AS3: =[2]Contributions!C291 -> 0.63444514 | AT3: =[2]Contributions!D291 -> 0.61451004 | AU3: =[2]Contributions!E291 -> 0.75582035 | AV3: =AW3-AS3-AT3-AU3 -> 3.4507378 | AW3: =[2]Contributions!G291 -> 5.4555133 | AX3: 2 | AZ3: 43466 | BE3: 43466 | BF3: =BL3-AVERAGE(BL$23:BL$26) -> -1049.75 | BG3: =BM3-AVERAGE(BM$23:BM$26) -> -352.25 | BH3: =BN3-AVERAGE(BN$23:BN$26) -> 47.75 | BI3: =SUM(BF3:BH3) -> -1354.25 | BK3: 43466 | BL3: ='Quarterly Data'!AH191+'Quarterly Data'!AI191+'Quarterly Data'!AJ191+'Quarterly Data'!AK191+'Quarterly Data'!AL191 -> 10881 | BM3: ='Quarterly Data'!W191+'Quarterly Data'!AD191+'Quarterly Data'!U191+'Quarterly Data'!AC191+'Quarterly Data'!AF191+'Quarterly Data'!X191+'Quarterly Data'!Y191 -> 8593 | BN3: ='Quarterly Data'!AA191+'Quarterly Data'!V191+'Quarterly Data'!AE191+'Quarterly Data'!T191+'Quarterly Data'!AG191+'Quarterly Data'!Z191+'Quarterly Data'!AB191 -> 15966 | BO3: ='Quarterly Data'!S191-'Chart Data'!BL3-'Chart Data'!BM3-'Chart Data'!BN3 -> -2 | BQ3: =BM3+BN3 -> 24559 | BS3: Expected effective interest rates on government debt (r) | BT3: =AVERAGE(CP4:CP8) -> 4.0835467 | BU3: =AVERAGE(CQ4:CQ8) -> 3.6723736 | BV3: =AVERAGE(CR4:CR8) -> 1.3884507 | BW3: =AVERAGE(CS4:CS8) -> 3.2244087 | BX3: =AVERAGE(CT4:CT8) -> 2.4758953 | BY3: =AVERAGE(CU4:CU8) -> 2.0233731 | BZ3: =AVERAGE(CV4:CV8) -> 1.6343447 | CA3: =AVERAGE(CW4:CW8) -> 1.2277289 | ... CM3: =AVERAGE(DI4:DI8) -> 2.2590555 | CO3: 2025 | CP3: =100*('Annual Data'!AQ59/'Annual Data'!BK59) -> 4.5351829 | CQ3: =100*('Annual Data'!AR59/'Annual Data'!BL59) -> 3.5211869 | CR3: =100*('Annual Data'!AS59/'Annual Data'!BM59) -> 0.63596444 | CS3: =100*('Annual Data'!AT59/'Annual Data'!BN59) -> 3.1973737 | CT3: =100*('Annual Data'!AU59/'Annual Data'!BO59) -> 1.6137146 | CU3: =100*('Annual Data'!AV59/'Annual Data'!BP59) -> 2.0153289 | CV3: =100*('Annual Data'!AW59/'Annual Data'!BQ59) -> 1.3512695 | CW3: =100*('Annual Data'!AX59/'Annual Data'!BR59) -> 1.1661427 | ... DI3: =100*('Annual Data'!BJ59/'Annual Data'!CD59) -> 2.0533644
A4: 2010- 2019 | B4: =AVERAGE(B32:B41) -> 1.3065392 | C4: =AVERAGE(C32:C41) -> 0.57229441 | D4: =AVERAGE(D32:D41) -> 0.20639226 | E4: =AVERAGE(E32:E41) -> -0.21890157 | F4: =AVERAGE(F32:F41) -> 0.10334206 | G4: =AVERAGE(G32:G41) -> 1.9696664 | V4: 44652 | W4: Q2 22 | X4: =100*((AC4-AC$6)/'Quarterly Data'!$G$206) -> -0.33332511 | Y4: =100*((AD4-AD$6)/'Quarterly Data'!$G$206) -> -0.027002818 | Z4: =100*(('Quarterly Data'!G204/'Quarterly Data'!$G$206)-1) -> -0.36032792 | AB4: 44652 | AC4: ='Quarterly Data'!J204+'Quarterly Data'!N204 -> 157604 | AD4: ='Quarterly Data'!G204-'Chart Data'!AC4 -> 528731 | AF4: Consumer spending | AG4: =100*(('Annual Data'!C60/'Annual Data'!C59)-1) -> 1.009535 | AH4: 1.1 | AI4: 1.7 | AJ4: 0.7 | AL4: Consumer spending | AM4: =100*(('Annual Data'!C$60/'Annual Data'!C$59)-1) -> 1.009535 | AN4: 1.1 | AO4: 1.5 | AP4: 0.6 | AR4: =[2]Contributions!B292 -> 44593 | AS4: =[2]Contributions!C292 -> 0.74294251 | AT4: =[2]Contributions!D292 -> 0.61728816 | AU4: =[2]Contributions!E292 -> 0.76192273 | AV4: =AW4-AS4-AT4-AU4 -> 4.0544547 | AW4: =[2]Contributions!G292 -> 6.1766081 | AX4: 2 | AZ4: 43556 | BE4: 43556 | BF4: =BL4-AVERAGE(BL$23:BL$26) -> -1030.75 | BG4: =BM4-AVERAGE(BM$23:BM$26) -> -337.25 | BH4: =BN4-AVERAGE(BN$23:BN$26) -> 118.75 | BI4: =SUM(BF4:BH4) -> -1249.25 | BK4: 43556 | BL4: ='Quarterly Data'!AH192+'Quarterly Data'!AI192+'Quarterly Data'!AJ192+'Quarterly Data'!AK192+'Quarterly Data'!AL192 -> 10900 | BM4: ='Quarterly Data'!W192+'Quarterly Data'!AD192+'Quarterly Data'!U192+'Quarterly Data'!AC192+'Quarterly Data'!AF192+'Quarterly Data'!X192+'Quarterly Data'!Y192 -> 8608 | BN4: ='Quarterly Data'!AA192+'Quarterly Data'!V192+'Quarterly Data'!AE192+'Quarterly Data'!T192+'Quarterly Data'!AG192+'Quarterly Data'!Z192+'Quarterly Data'!AB192 -> 16037 | BO4: ='Quarterly Data'!S192-'Chart Data'!BL4-'Chart Data'!BM4-'Chart Data'!BN4 -> 1 | BQ4: =BM4+BN4 -> 24645 | BS4: Expected annual average nominal GDP growth (g) | BT4: =100*(('Annual Data'!CE64/'Annual Data'!CE59)^(1/5)-1) -> 3.7091669 | BU4: =100*(('Annual Data'!CF64/'Annual Data'!CF59)^(1/5)-1) -> 4.1857812 | BV4: =100*(('Annual Data'!CG64/'Annual Data'!CG59)^(1/5)-1) -> 1.3615849 | BW4: =100*(('Annual Data'!CH64/'Annual Data'!CH59)^(1/5)-1) -> 3.5042386 | BX4: =100*(('Annual Data'!CI64/'Annual Data'!CI59)^(1/5)-1) -> 4.6471878 | BY4: =100*(('Annual Data'!CJ64/'Annual Data'!CJ59)^(1/5)-1) -> 4.1015374 | BZ4: =100*(('Annual Data'!CK64/'Annual Data'!CK59)^(1/5)-1) -> 4.014006 | CA4: =100*(('Annual Data'!CL64/'Annual Data'!CL59)^(1/5)-1) -> 2.3464219 | ... CM4: =100*(('Annual Data'!CX64/'Annual Data'!CX59)^(1/5)-1) -> 2.9984881 | CO4: 2026 | CP4: =100*('Annual Data'!AQ60/'Annual Data'!BK60) -> 4.0409321 | CQ4: =100*('Annual Data'!AR60/'Annual Data'!BL60) -> 3.6149732 | CR4: =100*('Annual Data'!AS60/'Annual Data'!BM60) -> 0.83901696 | CS4: =100*('Annual Data'!AT60/'Annual Data'!BN60) -> 3.1886173 | CT4: =100*('Annual Data'!AU60/'Annual Data'!BO60) -> 2.2993875 | CU4: =100*('Annual Data'!AV60/'Annual Data'!BP60) -> 2.00407 | CV4: =100*('Annual Data'!AW60/'Annual Data'!BQ60) -> 1.5709356 | CW4: =100*('Annual Data'!AX60/'Annual Data'!BR60) -> 1.1778994 | ... DI4: =100*('Annual Data'!BJ60/'Annual Data'!CD60) -> 2.1069456
V5: 44743 | W5: Q3 22 | X5: =100*((AC5-AC$6)/'Quarterly Data'!$G$206) -> -0.0078395278 | Y5: =100*((AD5-AD$6)/'Quarterly Data'!$G$206) -> -0.25173595 | Z5: =100*(('Quarterly Data'!G205/'Quarterly Data'!$G$206)-1) -> -0.25957548 | AB5: 44743 | AC5: ='Quarterly Data'!J205+'Quarterly Data'!N205 -> 159846 | AD5: ='Quarterly Data'!G205-'Chart Data'!AC5 -> 527183 | AF5: Fixed investment | AG5: =100*(('Annual Data'!D60/'Annual Data'!D59)-1) -> 0.93629904 | AH5: 1.7 | AI5: 2.9 | AJ5: =AG5 -> 0.93629904 | AL5: Fixed investment | AM5: =100*(('Annual Data'!D$60/'Annual Data'!D$59)-1) -> 0.93629904 | AN5: 1.7 | AO5: 2.9 | AP5: -0.1 | AR5: =[2]Contributions!B293 -> 44621 | AS5: =[2]Contributions!C293 -> 0.88985377 | AT5: =[2]Contributions!D293 -> 0.86461908 | AU5: =[2]Contributions!E293 -> 0.81185819 | AV5: =AW5-AS5-AT5-AU5 -> 4.456793 | AW5: =[2]Contributions!G293 -> 7.023124 | AX5: 2 | AZ5: 43647 | BE5: 43647 | BF5: =BL5-AVERAGE(BL$23:BL$26) -> -968.75 | BG5: =BM5-AVERAGE(BM$23:BM$26) -> -364.25 | BH5: =BN5-AVERAGE(BN$23:BN$26) -> 154.75 | BI5: =SUM(BF5:BH5) -> -1178.25 | BK5: 43647 | BL5: ='Quarterly Data'!AH193+'Quarterly Data'!AI193+'Quarterly Data'!AJ193+'Quarterly Data'!AK193+'Quarterly Data'!AL193 -> 10962 | BM5: ='Quarterly Data'!W193+'Quarterly Data'!AD193+'Quarterly Data'!U193+'Quarterly Data'!AC193+'Quarterly Data'!AF193+'Quarterly Data'!X193+'Quarterly Data'!Y193 -> 8581 | BN5: ='Quarterly Data'!AA193+'Quarterly Data'!V193+'Quarterly Data'!AE193+'Quarterly Data'!T193+'Quarterly Data'!AG193+'Quarterly Data'!Z193+'Quarterly Data'!AB193 -> 16073 | BO5: ='Quarterly Data'!S193-'Chart Data'!BL5-'Chart Data'!BM5-'Chart Data'!BN5 -> -1 | BQ5: =BM5+BN5 -> 24654 | CO5: 2027 | CP5: =100*('Annual Data'!AQ61/'Annual Data'!BK61) -> 4.0897531 | CQ5: =100*('Annual Data'!AR61/'Annual Data'!BL61) -> 3.6703991 | CR5: =100*('Annual Data'!AS61/'Annual Data'!BM61) -> 1.1113602 | CS5: =100*('Annual Data'!AT61/'Annual Data'!BN61) -> 3.2086801 | CT5: =100*('Annual Data'!AU61/'Annual Data'!BO61) -> 2.527882 | CU5: =100*('Annual Data'!AV61/'Annual Data'!BP61) -> 2.0189826 | CV5: =100*('Annual Data'!AW61/'Annual Data'!BQ61) -> 1.6092971 | CW5: =100*('Annual Data'!AX61/'Annual Data'!BR61) -> 1.2040547 | ... DI5: =100*('Annual Data'!BJ61/'Annual Data'!CD61) -> 2.1857001
A6: 2023 | B6: =B45 -> -0.19444691 | C6: =C45 -> -0.051918091 | D6: =D45 -> 0.56220917 | E6: =E45 -> -0.2284396 | F6: =F45 -> 0.18424546 | G6: =G45 -> 0.27165003 | V6: 44835 | W6: Q4 22 | X6: =100*((AC6-AC$6)/'Quarterly Data'!$G$206) -> 0 | Y6: =100*((AD6-AD$6)/'Quarterly Data'!$G$206) -> 0 | Z6: =100*(('Quarterly Data'!G206/'Quarterly Data'!$G$206)-1) -> 0 | AB6: 44835 | AC6: ='Quarterly Data'!J206+'Quarterly Data'!N206 -> 159900 | AD6: ='Quarterly Data'!G206-'Chart Data'!AC6 -> 528917 | AF6: Govt consumption | AG6: =100*(('Annual Data'!E60/'Annual Data'!E59)-1) -> 2.0010144 | AH6: 1.7 | AI6: 2.2 | AJ6: 1.2 | AR6: =[2]Contributions!B294 -> 44652 | AS6: =[2]Contributions!C294 -> 0.96773224 | AT6: =[2]Contributions!D294 -> 0.89042504 | AU6: =[2]Contributions!E294 -> 2.344496 | AV6: =AW6-AS6-AT6-AU6 -> 4.8080084 | AW6: =[2]Contributions!G294 -> 9.0106617 | AX6: 2 | AZ6: 43739 | BE6: 43739 | BF6: =BL6-AVERAGE(BL$23:BL$26) -> -912.75 | BG6: =BM6-AVERAGE(BM$23:BM$26) -> -350.25 | BH6: =BN6-AVERAGE(BN$23:BN$26) -> 128.75 | BI6: =SUM(BF6:BH6) -> -1134.25 | BK6: 43739 | BL6: ='Quarterly Data'!AH194+'Quarterly Data'!AI194+'Quarterly Data'!AJ194+'Quarterly Data'!AK194+'Quarterly Data'!AL194 -> 11018 | BM6: ='Quarterly Data'!W194+'Quarterly Data'!AD194+'Quarterly Data'!U194+'Quarterly Data'!AC194+'Quarterly Data'!AF194+'Quarterly Data'!X194+'Quarterly Data'!Y194 -> 8595 | BN6: ='Quarterly Data'!AA194+'Quarterly Data'!V194+'Quarterly Data'!AE194+'Quarterly Data'!T194+'Quarterly Data'!AG194+'Quarterly Data'!Z194+'Quarterly Data'!AB194 -> 16047 | BO6: ='Quarterly Data'!S194-'Chart Data'!BL6-'Chart Data'!BM6-'Chart Data'!BN6 -> 1 | BQ6: =BM6+BN6 -> 24642 | CO6: 2028 | CP6: =100*('Annual Data'!AQ62/'Annual Data'!BK62) -> 4.0698033 | CQ6: =100*('Annual Data'!AR62/'Annual Data'!BL62) -> 3.6830863 | CR6: =100*('Annual Data'!AS62/'Annual Data'!BM62) -> 1.4228995 | CS6: =100*('Annual Data'!AT62/'Annual Data'!BN62) -> 3.226594 | CT6: =100*('Annual Data'!AU62/'Annual Data'!BO62) -> 2.5506286 | CU6: =100*('Annual Data'!AV62/'Annual Data'!BP62) -> 2.0317969 | CV6: =100*('Annual Data'!AW62/'Annual Data'!BQ62) -> 1.6391828 | CW6: =100*('Annual Data'!AX62/'Annual Data'!BR62) -> 1.2316285 | ... DI6: =100*('Annual Data'!BJ62/'Annual Data'!CD62) -> 2.2623814
A7: 2024 | B7: =B46 -> -0.10726105 | C7: =C46 -> 0.19875269 | D7: =D46 -> 0.82436948 | E7: =E46 -> -0.65879068 | F7: =F46 -> 0.86608211 | G7: =G46 -> 1.1231525 | V7: 44927 | W7: Q1 23 | X7: =100*((AC7-AC$6)/'Quarterly Data'!$G$206) -> 0.16985644 | Y7: =100*((AD7-AD$6)/'Quarterly Data'!$G$206) -> -0.1133828 | Z7: =100*(('Quarterly Data'!G207/'Quarterly Data'!$G$206)-1) -> 0.056473635 | AB7: 44927 | AC7: ='Quarterly Data'!J207+'Quarterly Data'!N207 -> 161070 | AD7: ='Quarterly Data'!G207-'Chart Data'!AC7 -> 528136 | AF7: Exports | AG7: =100*(('Annual Data'!F60/'Annual Data'!F59)-1) -> -0.36591598 | AH7: 1.2 | AI7: 3.3 | AJ7: -0.4 | AR7: =[2]Contributions!B295 -> 44682 | AS7: =[2]Contributions!C295 -> 1.2132102 | AT7: =[2]Contributions!D295 -> 0.93372095 | AU7: =[2]Contributions!E295 -> 2.3435002 | AV7: =AW7-AS7-AT7-AU7 -> 4.59227 | AW7: =[2]Contributions!G295 -> 9.0827013 | AX7: 2 | AZ7: 43831 | BA7: =100*((BL7/BL3)-1) -> 0.86389119 | BB7: =100*((BM7/BM3)-1) -> 0.52368207 | BC7: =100*((BN7/BN3)-1) -> 0.1941626 | BE7: 43831 | BF7: =BL7-AVERAGE(BL$23:BL$26) -> -955.75 | BG7: =BM7-AVERAGE(BM$23:BM$26) -> -307.25 | BH7: =BN7-AVERAGE(BN$23:BN$26) -> 78.75 | BI7: =SUM(BF7:BH7) -> -1184.25 | BK7: 43831 | BL7: ='Quarterly Data'!AH195+'Quarterly Data'!AI195+'Quarterly Data'!AJ195+'Quarterly Data'!AK195+'Quarterly Data'!AL195 -> 10975 | BM7: ='Quarterly Data'!W195+'Quarterly Data'!AD195+'Quarterly Data'!U195+'Quarterly Data'!AC195+'Quarterly Data'!AF195+'Quarterly Data'!X195+'Quarterly Data'!Y195 -> 8638 | BN7: ='Quarterly Data'!AA195+'Quarterly Data'!V195+'Quarterly Data'!AE195+'Quarterly Data'!T195+'Quarterly Data'!AG195+'Quarterly Data'!Z195+'Quarterly Data'!AB195 -> 15997 | BO7: ='Quarterly Data'!S195-'Chart Data'!BL7-'Chart Data'!BM7-'Chart Data'!BN7 -> -1 | BQ7: =BM7+BN7 -> 24635 | CO7: 2029 | CP7: =100*('Annual Data'!AQ63/'Annual Data'!BK63) -> 4.1358825 | CQ7: =100*('Annual Data'!AR63/'Annual Data'!BL63) -> 3.6933855 | CR7: =100*('Annual Data'!AS63/'Annual Data'!BM63) -> 1.6834901 | CS7: =100*('Annual Data'!AT63/'Annual Data'!BN63) -> 3.241977 | CT7: =100*('Annual Data'!AU63/'Annual Data'!BO63) -> 2.5161783 | CU7: =100*('Annual Data'!AV63/'Annual Data'!BP63) -> 2.0408062 | CV7: =100*('Annual Data'!AW63/'Annual Data'!BQ63) -> 1.6659256 | CW7: =100*('Annual Data'!AX63/'Annual Data'!BR63) -> 1.253381 | ... DI7: =100*('Annual Data'!BJ63/'Annual Data'!CD63) -> 2.3353486
A8: 2025 | B8: =B47 -> 0.51482982 | C8: =C47 -> 0.46433244 | D8: =D47 -> 0.52687693 | E8: =E47 -> -0.31060248 | F8: =F47 -> 0.22208169 | G8: =G47 -> 1.4175184 | V8: 45017 | W8: Q2 23 | X8: =100*((AC8-AC$6)/'Quarterly Data'!$G$206) -> 0.41404321 | Y8: =100*((AD8-AD$6)/'Quarterly Data'!$G$206) -> -0.31619429 | Z8: =100*(('Quarterly Data'!G208/'Quarterly Data'!$G$206)-1) -> 0.097848921 | AB8: 45017 | AC8: ='Quarterly Data'!J208+'Quarterly Data'!N208 -> 162752 | AD8: ='Quarterly Data'!G208-'Chart Data'!AC8 -> 526739 | AF8: Imports | AG8: =100*(('Annual Data'!G60/'Annual Data'!G59)-1) -> -0.43116331 | AH8: 1.2 | AI8: 2.3 | AJ8: -0.9 | AR8: =[2]Contributions!B296 -> 44713 | AS8: =[2]Contributions!C296 -> 1.3259122 | AT8: =[2]Contributions!D296 -> 1.220663 | AU8: =[2]Contributions!E296 -> 2.3445813 | AV8: =AW8-AS8-AT8-AU8 -> 4.5209569 | AW8: =[2]Contributions!G296 -> 9.4121135 | AX8: 2 | AZ8: 43922 | BA8: =100*((BL8/BL4)-1) -> 0.70642202 | BB8: =100*((BM8/BM4)-1) -> -1.4521375 | BC8: =100*((BN8/BN4)-1) -> -2.2635156 | BE8: 43922 | BF8: =BL8-AVERAGE(BL$23:BL$26) -> -953.75 | BG8: =BM8-AVERAGE(BM$23:BM$26) -> -462.25 | BH8: =BN8-AVERAGE(BN$23:BN$26) -> -244.25 | BI8: =SUM(BF8:BH8) -> -1660.25 | BK8: 43922 | BL8: ='Quarterly Data'!AH196+'Quarterly Data'!AI196+'Quarterly Data'!AJ196+'Quarterly Data'!AK196+'Quarterly Data'!AL196 -> 10977 | BM8: ='Quarterly Data'!W196+'Quarterly Data'!AD196+'Quarterly Data'!U196+'Quarterly Data'!AC196+'Quarterly Data'!AF196+'Quarterly Data'!X196+'Quarterly Data'!Y196 -> 8483 | BN8: ='Quarterly Data'!AA196+'Quarterly Data'!V196+'Quarterly Data'!AE196+'Quarterly Data'!T196+'Quarterly Data'!AG196+'Quarterly Data'!Z196+'Quarterly Data'!AB196 -> 15674 | BO8: ='Quarterly Data'!S196-'Chart Data'!BL8-'Chart Data'!BM8-'Chart Data'!BN8 -> 1 | BQ8: =BM8+BN8 -> 24157 | CO8: 2030 | CP8: =100*('Annual Data'!AQ64/'Annual Data'!BK64) -> 4.0813627 | CQ8: =100*('Annual Data'!AR64/'Annual Data'!BL64) -> 3.7000238 | CR8: =100*('Annual Data'!AS64/'Annual Data'!BM64) -> 1.8854865 | CS8: =100*('Annual Data'!AT64/'Annual Data'!BN64) -> 3.2561751 | CT8: =100*('Annual Data'!AU64/'Annual Data'!BO64) -> 2.4854001 | CU8: =100*('Annual Data'!AV64/'Annual Data'!BP64) -> 2.0212095 | CV8: =100*('Annual Data'!AW64/'Annual Data'!BQ64) -> 1.6863823 | CW8: =100*('Annual Data'!AX64/'Annual Data'!BR64) -> 1.2716807 | ... DI8: =100*('Annual Data'!BJ64/'Annual Data'!CD64) -> 2.4049019
A9: 2026 | B9: =B48 -> 0.59504155 | C9: =C48 -> -0.056271943 | D9: =D48 -> 0.6611522 | E9: =E48 -> 0.029997956 | F9: =F48 -> -0.26848649 | G9: =G48 -> 0.96143326 | V9: 45108 | W9: Q3 23 | X9: =100*((AC9-AC$6)/'Quarterly Data'!$G$206) -> 0.80761654 | Y9: =100*((AD9-AD$6)/'Quarterly Data'!$G$206) -> -0.9495991 | Z9: =100*(('Quarterly Data'!G209/'Quarterly Data'!$G$206)-1) -> -0.14198256 | AB9: 45108 | AC9: ='Quarterly Data'!J209+'Quarterly Data'!N209 -> 165463 | AD9: ='Quarterly Data'!G209-'Chart Data'!AC9 -> 522376 | AR9: =[2]Contributions!B297 -> 44743 | AS9: =[2]Contributions!C297 -> 1.6820304 | AT9: =[2]Contributions!D297 -> 1.2826645 | AU9: =[2]Contributions!E297 -> 2.3502743 | AV9: =AW9-AS9-AT9-AU9 -> 4.785932 | AW9: =[2]Contributions!G297 -> 10.100901 | AX9: 2 | AZ9: 44013 | BA9: =100*((BL9/BL5)-1) -> -1.0855683 | BB9: =100*((BM9/BM5)-1) -> -3.1464864 | BC9: =100*((BN9/BN5)-1) -> -3.9382816 | BE9: 44013 | BF9: =BL9-AVERAGE(BL$23:BL$26) -> -1087.75 | BG9: =BM9-AVERAGE(BM$23:BM$26) -> -634.25 | BH9: =BN9-AVERAGE(BN$23:BN$26) -> -478.25 | BI9: =SUM(BF9:BH9) -> -2200.25 | BK9: 44013 | BL9: ='Quarterly Data'!AH197+'Quarterly Data'!AI197+'Quarterly Data'!AJ197+'Quarterly Data'!AK197+'Quarterly Data'!AL197 -> 10843 | BM9: ='Quarterly Data'!W197+'Quarterly Data'!AD197+'Quarterly Data'!U197+'Quarterly Data'!AC197+'Quarterly Data'!AF197+'Quarterly Data'!X197+'Quarterly Data'!Y197 -> 8311 | BN9: ='Quarterly Data'!AA197+'Quarterly Data'!V197+'Quarterly Data'!AE197+'Quarterly Data'!T197+'Quarterly Data'!AG197+'Quarterly Data'!Z197+'Quarterly Data'!AB197 -> 15440 | BO9: ='Quarterly Data'!S197-'Chart Data'!BL9-'Chart Data'!BM9-'Chart Data'!BN9 -> 0 | BQ9: =BM9+BN9 -> 23751
V10: 45200 | W10: Q4 23 | X10: =100*((AC10-AC$6)/'Quarterly Data'!$G$206) -> 0.93159722 | Y10: =100*((AD10-AD$6)/'Quarterly Data'!$G$206) -> -1.3945649 | Z10: =100*(('Quarterly Data'!G210/'Quarterly Data'!$G$206)-1) -> -0.46296767 | AB10: 45200 | AC10: ='Quarterly Data'!J210+'Quarterly Data'!N210 -> 166317 | AD10: ='Quarterly Data'!G210-'Chart Data'!AC10 -> 519311 | AR10: =[2]Contributions!B298 -> 44774 | AS10: =[2]Contributions!C298 -> 1.7481531 | AT10: =[2]Contributions!D298 -> 0.94983699 | AU10: =[2]Contributions!E298 -> 2.3137985 | AV10: =AW10-AS10-AT10-AU10 -> 4.8583992 | AW10: =[2]Contributions!G298 -> 9.8701878 | AX10: 2 | AZ10: 44105 | BA10: =100*((BL10/BL6)-1) -> -1.3069523 | BB10: =100*((BM10/BM6)-1) -> -2.6294357 | BC10: =100*((BN10/BN6)-1) -> -4.7734779 | BE10: 44105 | BF10: =BL10-AVERAGE(BL$23:BL$26) -> -1056.75 | BG10: =BM10-AVERAGE(BM$23:BM$26) -> -576.25 | BH10: =BN10-AVERAGE(BN$23:BN$26) -> -637.25 | BI10: =SUM(BF10:BH10) -> -2270.25 | BK10: 44105 | BL10: ='Quarterly Data'!AH198+'Quarterly Data'!AI198+'Quarterly Data'!AJ198+'Quarterly Data'!AK198+'Quarterly Data'!AL198 -> 10874 | BM10: ='Quarterly Data'!W198+'Quarterly Data'!AD198+'Quarterly Data'!U198+'Quarterly Data'!AC198+'Quarterly Data'!AF198+'Quarterly Data'!X198+'Quarterly Data'!Y198 -> 8369 | BN10: ='Quarterly Data'!AA198+'Quarterly Data'!V198+'Quarterly Data'!AE198+'Quarterly Data'!T198+'Quarterly Data'!AG198+'Quarterly Data'!Z198+'Quarterly Data'!AB198 -> 15281 | BO10: ='Quarterly Data'!S198-'Chart Data'!BL10-'Chart Data'!BM10-'Chart Data'!BN10 -> -2 | BQ10: =BM10+BN10 -> 23650
A11: 1989 | I11: ='Annual Data'!D23-'Annual Data'!I23 -> 278440.92 | J11: ='Annual Data'!E23+'Annual Data'!I23 -> 323786.08 | K11: ='Annual Data'!F23-'Annual Data'!G23 -> -4159 | V11: 45292 | W11: Q1 24 | X11: =100*((AC11-AC$6)/'Quarterly Data'!$G$206) -> 1.1773809 | Y11: =100*((AD11-AD$6)/'Quarterly Data'!$G$206) -> -0.8115363 | Z11: =100*(('Quarterly Data'!G211/'Quarterly Data'!$G$206)-1) -> 0.36584463 | AB11: 45292 | AC11: ='Quarterly Data'!J211+'Quarterly Data'!N211 -> 168010 | AD11: ='Quarterly Data'!G211-'Chart Data'!AC11 -> 523327 | AR11: =[2]Contributions!B299 -> 44805 | AS11: =[2]Contributions!C299 -> 1.9149772 | AT11: =[2]Contributions!D299 -> 0.78413565 | AU11: =[2]Contributions!E299 -> 2.3238543 | AV11: =AW11-AS11-AT11-AU11 -> 5.0726606 | AW11: =[2]Contributions!G299 -> 10.095628 | AX11: 2 | AZ11: 44197 | BA11: =100*((BL11/BL7)-1) -> -0.10022779 | BB11: =100*((BM11/BM7)-1) -> -2.5468859 | BC11: =100*((BN11/BN7)-1) -> -4.0257548 | BE11: 44197 | BF11: =BL11-AVERAGE(BL$23:BL$26) -> -966.75 | BG11: =BM11-AVERAGE(BM$23:BM$26) -> -527.25 | BH11: =BN11-AVERAGE(BN$23:BN$26) -> -565.25 | BI11: =SUM(BF11:BH11) -> -2059.25 | BK11: 44197 | BL11: ='Quarterly Data'!AH199+'Quarterly Data'!AI199+'Quarterly Data'!AJ199+'Quarterly Data'!AK199+'Quarterly Data'!AL199 -> 10964 | BM11: ='Quarterly Data'!W199+'Quarterly Data'!AD199+'Quarterly Data'!U199+'Quarterly Data'!AC199+'Quarterly Data'!AF199+'Quarterly Data'!X199+'Quarterly Data'!Y199 -> 8418 | BN11: ='Quarterly Data'!AA199+'Quarterly Data'!V199+'Quarterly Data'!AE199+'Quarterly Data'!T199+'Quarterly Data'!AG199+'Quarterly Data'!Z199+'Quarterly Data'!AB199 -> 15353 | BO11: ='Quarterly Data'!S199-'Chart Data'!BL11-'Chart Data'!BM11-'Chart Data'!BN11 -> -1 | BQ11: =BM11+BN11 -> 23771
A12: 1990 | B12: =100*(('Annual Data'!C24-'Annual Data'!C23)/'Annual Data'!$B23) -> 0.79640579 | C12: =100*((I12-I11)/'Annual Data'!$B23) -> -0.74265839 | D12: =100*((J12-J11)/'Annual Data'!$B23) -> 0.72168462 | E12: =100*((K12-K11)/'Annual Data'!$B23) -> 0.83105233 | F12: =G12-B12-C12-D12-E12 -> -1.038467 | G12: =100*(('Annual Data'!B24/'Annual Data'!B23)-1) -> 0.56801739 | I12: ='Annual Data'!D24-'Annual Data'!I24 -> 267251.71 | J12: ='Annual Data'!E24+'Annual Data'!I24 -> 334659.29 | K12: ='Annual Data'!F24-'Annual Data'!G24 -> 8362 | V12: 45383 | W12: Q2 24 | X12: =100*((AC12-AC$6)/'Quarterly Data'!$G$206) -> 1.2540341 | Y12: =100*((AD12-AD$6)/'Quarterly Data'!$G$206) -> -0.27249618 | Z12: =100*(('Quarterly Data'!G212/'Quarterly Data'!$G$206)-1) -> 0.98153791 | AB12: 45383 | AC12: ='Quarterly Data'!J212+'Quarterly Data'!N212 -> 168538 | AD12: ='Quarterly Data'!G212-'Chart Data'!AC12 -> 527040 | AR12: =[2]Contributions!B300 -> 44835 | AS12: =[2]Contributions!C300 -> 2.1203898 | AT12: =[2]Contributions!D300 -> 0.66663702 | AU12: =[2]Contributions!E300 -> 3.2501679 | AV12: =AW12-AS12-AT12-AU12 -> 5.0143716 | AW12: =[2]Contributions!G300 -> 11.051566 | AX12: 2 | AZ12: 44287 | BA12: =100*((BL12/BL8)-1) -> 0.92010568 | BB12: =100*((BM12/BM8)-1) -> 0.14145939 | BC12: =100*((BN12/BN8)-1) -> -1.1164987 | BE12: 44287 | BF12: =BL12-AVERAGE(BL$23:BL$26) -> -852.75 | BG12: =BM12-AVERAGE(BM$23:BM$26) -> -450.25 | BH12: =BN12-AVERAGE(BN$23:BN$26) -> -419.25 | BI12: =SUM(BF12:BH12) -> -1722.25 | BK12: 44287 | BL12: ='Quarterly Data'!AH200+'Quarterly Data'!AI200+'Quarterly Data'!AJ200+'Quarterly Data'!AK200+'Quarterly Data'!AL200 -> 11078 | BM12: ='Quarterly Data'!W200+'Quarterly Data'!AD200+'Quarterly Data'!U200+'Quarterly Data'!AC200+'Quarterly Data'!AF200+'Quarterly Data'!X200+'Quarterly Data'!Y200 -> 8495 | BN12: ='Quarterly Data'!AA200+'Quarterly Data'!V200+'Quarterly Data'!AE200+'Quarterly Data'!T200+'Quarterly Data'!AG200+'Quarterly Data'!Z200+'Quarterly Data'!AB200 -> 15499 | BO12: ='Quarterly Data'!S200-'Chart Data'!BL12-'Chart Data'!BM12-'Chart Data'!BN12 -> 0 | BQ12: =BM12+BN12 -> 23994
A13: 1991 | B13: =100*(('Annual Data'!C25-'Annual Data'!C24)/'Annual Data'!$B24) -> -0.49366355 | C13: =100*((I13-I12)/'Annual Data'!$B24) -> -1.53306 | D13: =100*((J13-J12)/'Annual Data'!$B24) -> 0.62757019 | E13: =100*((K13-K12)/'Annual Data'!$B24) -> 0.76115264 | F13: =G13-B13-C13-D13-E13 -> -0.76768642 | G13: =100*(('Annual Data'!B25/'Annual Data'!B24)-1) -> -1.4056872 | I13: ='Annual Data'!D25-'Annual Data'!I25 -> 244022.75 | J13: ='Annual Data'!E25+'Annual Data'!I25 -> 344168.25 | K13: ='Annual Data'!F25-'Annual Data'!G25 -> 19895 | V13: 45474 | W13: Q3 24 | X13: =100*((AC13-AC$6)/'Quarterly Data'!$G$206) -> 1.5278369 | Y13: =100*((AD13-AD$6)/'Quarterly Data'!$G$206) -> -0.30385429 | Z13: =100*(('Quarterly Data'!G213/'Quarterly Data'!$G$206)-1) -> 1.2239826 | AB13: 45474 | AC13: ='Quarterly Data'!J213+'Quarterly Data'!N213 -> 170424 | AD13: ='Quarterly Data'!G213-'Chart Data'!AC13 -> 526824 | AR13: =[2]Contributions!B301 -> 44866 | AS13: =[2]Contributions!C301 -> 2.0673238 | AT13: =[2]Contributions!D301 -> 0.53644982 | AU13: =[2]Contributions!E301 -> 3.2074822 | AV13: =AW13-AS13-AT13-AU13 -> 4.860757 | AW13: =[2]Contributions!G301 -> 10.672013 | AX13: 2 | AZ13: 44378 | BA13: =100*((BL13/BL9)-1) -> 2.5177534 | BB13: =100*((BM13/BM9)-1) -> 2.7192877 | BC13: =100*((BN13/BN9)-1) -> 1.2435233 | BE13: 44378 | BF13: =BL13-AVERAGE(BL$23:BL$26) -> -814.75 | BG13: =BM13-AVERAGE(BM$23:BM$26) -> -408.25 | BH13: =BN13-AVERAGE(BN$23:BN$26) -> -286.25 | BI13: =SUM(BF13:BH13) -> -1509.25 | BK13: 44378 | BL13: ='Quarterly Data'!AH201+'Quarterly Data'!AI201+'Quarterly Data'!AJ201+'Quarterly Data'!AK201+'Quarterly Data'!AL201 -> 11116 | BM13: ='Quarterly Data'!W201+'Quarterly Data'!AD201+'Quarterly Data'!U201+'Quarterly Data'!AC201+'Quarterly Data'!AF201+'Quarterly Data'!X201+'Quarterly Data'!Y201 -> 8537 | BN13: ='Quarterly Data'!AA201+'Quarterly Data'!V201+'Quarterly Data'!AE201+'Quarterly Data'!T201+'Quarterly Data'!AG201+'Quarterly Data'!Z201+'Quarterly Data'!AB201 -> 15632 | BO13: ='Quarterly Data'!S201-'Chart Data'!BL13-'Chart Data'!BM13-'Chart Data'!BN13 -> 1 | BQ13: =BM13+BN13 -> 24169
A14: 1992 | B14: =100*(('Annual Data'!C26-'Annual Data'!C25)/'Annual Data'!$B25) -> 0.56067897 | C14: =100*((I14-I13)/'Annual Data'!$B25) -> -0.46008395 | D14: =100*((J14-J13)/'Annual Data'!$B25) -> 0.38377378 | E14: =100*((K14-K13)/'Annual Data'!$B25) -> -0.32525539 | F14: =G14-B14-C14-D14-E14 -> 0.11667424 | G14: =100*(('Annual Data'!B26/'Annual Data'!B25)-1) -> 0.27578765 | I14: ='Annual Data'!D26-'Annual Data'!I26 -> 237149.54 | J14: ='Annual Data'!E26+'Annual Data'!I26 -> 349901.46 | K14: ='Annual Data'!F26-'Annual Data'!G26 -> 15036 | V14: 45566 | W14: Q4 24 | X14: =100*((AC14-AC$6)/'Quarterly Data'!$G$206) -> 1.6576246 | Y14: =100*((AD14-AD$6)/'Quarterly Data'!$G$206) -> -0.19206843 | Z14: =100*(('Quarterly Data'!G214/'Quarterly Data'!$G$206)-1) -> 1.4655562 | AB14: 45566 | AC14: ='Quarterly Data'!J214+'Quarterly Data'!N214 -> 171318 | AD14: ='Quarterly Data'!G214-'Chart Data'!AC14 -> 527594 | AR14: =[2]Contributions!B302 -> 44896 | AS14: =[2]Contributions!C302 -> 2.1053691 | AT14: =[2]Contributions!D302 -> 0.3565041 | AU14: =[2]Contributions!E302 -> 3.1787972 | AV14: =AW14-AS14-AT14-AU14 -> 4.887704 | AW14: =[2]Contributions!G302 -> 10.528374 | AX14: 2 | AZ14: 44470 | BA14: =100*((BL14/BL10)-1) -> 2.4737907 | BB14: =100*((BM14/BM10)-1) -> 2.282232 | BC14: =100*((BN14/BN10)-1) -> 2.2511616 | BE14: 44470 | BF14: =BL14-AVERAGE(BL$23:BL$26) -> -787.75 | BG14: =BM14-AVERAGE(BM$23:BM$26) -> -385.25 | BH14: =BN14-AVERAGE(BN$23:BN$26) -> -293.25 | BI14: =SUM(BF14:BH14) -> -1466.25 | BK14: 44470 | BL14: ='Quarterly Data'!AH202+'Quarterly Data'!AI202+'Quarterly Data'!AJ202+'Quarterly Data'!AK202+'Quarterly Data'!AL202 -> 11143 | BM14: ='Quarterly Data'!W202+'Quarterly Data'!AD202+'Quarterly Data'!U202+'Quarterly Data'!AC202+'Quarterly Data'!AF202+'Quarterly Data'!X202+'Quarterly Data'!Y202 -> 8560 | BN14: ='Quarterly Data'!AA202+'Quarterly Data'!V202+'Quarterly Data'!AE202+'Quarterly Data'!T202+'Quarterly Data'!AG202+'Quarterly Data'!Z202+'Quarterly Data'!AB202 -> 15625 | BO14: ='Quarterly Data'!S202-'Chart Data'!BL14-'Chart Data'!BM14-'Chart Data'!BN14 -> 0 | BQ14: =BM14+BN14 -> 24185
A15: 1993 | B15: =100*(('Annual Data'!C27-'Annual Data'!C26)/'Annual Data'!$B26) -> 1.6377586 | C15: =100*((I15-I14)/'Annual Data'!$B26) -> 0.021772897 | D15: =100*((J15-J14)/'Annual Data'!$B26) -> 0.011137145 | E15: =100*((K15-K14)/'Annual Data'!$B26) -> 0.25907479 | F15: =G15-B15-C15-D15-E15 -> 0.3438532 | G15: =100*(('Annual Data'!B27/'Annual Data'!B26)-1) -> 2.2735966 | I15: ='Annual Data'!D27-'Annual Data'!I27 -> 237475.71 | J15: ='Annual Data'!E27+'Annual Data'!I27 -> 350068.29 | K15: ='Annual Data'!F27-'Annual Data'!G27 -> 18917 | V15: 45658 | W15: Q1 25 | X15: =100*((AC15-AC$6)/'Quarterly Data'!$G$206) -> 1.5099802 | Y15: =100*((AD15-AD$6)/'Quarterly Data'!$G$206) -> 0.62629116 | Z15: =100*(('Quarterly Data'!G215/'Quarterly Data'!$G$206)-1) -> 2.1362713 | AB15: 45658 | AC15: ='Quarterly Data'!J215+'Quarterly Data'!N215 -> 170301 | AD15: ='Quarterly Data'!G215-'Chart Data'!AC15 -> 533231 | AR15: =[2]Contributions!B303 -> 44927 | AS15: =[2]Contributions!C303 -> 2.1442356 | AT15: =[2]Contributions!D303 -> 0.23985336 | AU15: =[2]Contributions!E303 -> 3.2214337 | AV15: =AW15-AS15-AT15-AU15 -> 4.4460012 | AW15: =[2]Contributions!G303 -> 10.051524 | AX15: 2 | AZ15: 44562 | BA15: =100*((BL15/BL11)-1) -> 2.4990879 | BB15: =100*((BM15/BM11)-1) -> 2.6134474 | BC15: =100*((BN15/BN11)-1) -> 3.1394516 | BE15: 44562 | BF15: =BL15-AVERAGE(BL$23:BL$26) -> -692.75 | BG15: =BM15-AVERAGE(BM$23:BM$26) -> -307.25 | BH15: =BN15-AVERAGE(BN$23:BN$26) -> -83.25 | BI15: =SUM(BF15:BH15) -> -1083.25 | BK15: 44562 | BL15: ='Quarterly Data'!AH203+'Quarterly Data'!AI203+'Quarterly Data'!AJ203+'Quarterly Data'!AK203+'Quarterly Data'!AL203 -> 11238 | BM15: ='Quarterly Data'!W203+'Quarterly Data'!AD203+'Quarterly Data'!U203+'Quarterly Data'!AC203+'Quarterly Data'!AF203+'Quarterly Data'!X203+'Quarterly Data'!Y203 -> 8638 | BN15: ='Quarterly Data'!AA203+'Quarterly Data'!V203+'Quarterly Data'!AE203+'Quarterly Data'!T203+'Quarterly Data'!AG203+'Quarterly Data'!Z203+'Quarterly Data'!AB203 -> 15835 | BO15: ='Quarterly Data'!S203-'Chart Data'!BL15-'Chart Data'!BM15-'Chart Data'!BN15 -> 1 | BQ15: =BM15+BN15 -> 24473
A16: 1994 | B16: =100*(('Annual Data'!C28-'Annual Data'!C27)/'Annual Data'!$B27) -> 1.8941545 | C16: =100*((I16-I15)/'Annual Data'!$B27) -> 0.14839989 | D16: =100*((J16-J15)/'Annual Data'!$B27) -> 0.39621848 | E16: =100*((K16-K15)/'Annual Data'!$B27) -> 0.69930983 | F16: =G16-B16-C16-D16-E16 -> 0.28059856 | G16: =100*(('Annual Data'!B28/'Annual Data'!B27)-1) -> 3.4186812 | I16: ='Annual Data'!D28-'Annual Data'!I28 -> 239749.31 | J16: ='Annual Data'!E28+'Annual Data'!I28 -> 356138.69 | K16: ='Annual Data'!F28-'Annual Data'!G28 -> 29631 | V16: 45748 | W16: Q2 25 | X16: =100*((AC16-AC$6)/'Quarterly Data'!$G$206) -> 1.9232975 | Y16: =100*((AD16-AD$6)/'Quarterly Data'!$G$206) -> 0.4966486 | Z16: =100*(('Quarterly Data'!G216/'Quarterly Data'!$G$206)-1) -> 2.4199461 | AB16: 45748 | AC16: ='Quarterly Data'!J216+'Quarterly Data'!N216 -> 173148 | AD16: ='Quarterly Data'!G216-'Chart Data'!AC16 -> 532338 | AR16: =[2]Contributions!B304 -> 44958 | AS16: =[2]Contributions!C304 -> 2.3586634 | AT16: =[2]Contributions!D304 -> 0.14412908 | AU16: =[2]Contributions!E304 -> 3.1778898 | AV16: =AW16-AS16-AT16-AU16 -> 4.7357145 | AW16: =[2]Contributions!G304 -> 10.416397 | AX16: 2 | AZ16: 44652 | BA16: =100*((BL16/BL12)-1) -> 2.2838057 | BB16: =100*((BM16/BM12)-1) -> 1.624485 | BC16: =100*((BN16/BN12)-1) -> 2.9550294 | BE16: 44652 | BF16: =BL16-AVERAGE(BL$23:BL$26) -> -599.75 | BG16: =BM16-AVERAGE(BM$23:BM$26) -> -312.25 | BH16: =BN16-AVERAGE(BN$23:BN$26) -> 38.75 | BI16: =SUM(BF16:BH16) -> -873.25 | BK16: 44652 | BL16: ='Quarterly Data'!AH204+'Quarterly Data'!AI204+'Quarterly Data'!AJ204+'Quarterly Data'!AK204+'Quarterly Data'!AL204 -> 11331 | BM16: ='Quarterly Data'!W204+'Quarterly Data'!AD204+'Quarterly Data'!U204+'Quarterly Data'!AC204+'Quarterly Data'!AF204+'Quarterly Data'!X204+'Quarterly Data'!Y204 -> 8633 | BN16: ='Quarterly Data'!AA204+'Quarterly Data'!V204+'Quarterly Data'!AE204+'Quarterly Data'!T204+'Quarterly Data'!AG204+'Quarterly Data'!Z204+'Quarterly Data'!AB204 -> 15957 | BO16: ='Quarterly Data'!S204-'Chart Data'!BL16-'Chart Data'!BM16-'Chart Data'!BN16 -> -1 | BQ16: =BM16+BN16 -> 24590
A17: 1995 | B17: =100*(('Annual Data'!C29-'Annual Data'!C28)/'Annual Data'!$B28) -> 1.2249607 | C17: =100*((I17-I16)/'Annual Data'!$B28) -> 0.05222445 | D17: =100*((J17-J16)/'Annual Data'!$B28) -> 0.16103446 | E17: =100*((K17-K16)/'Annual Data'!$B28) -> 0.86117722 | F17: =G17-B17-C17-D17-E17 -> 0.10628233 | G17: =100*(('Annual Data'!B29/'Annual Data'!B28)-1) -> 2.4056792 | I17: ='Annual Data'!D29-'Annual Data'!I29 -> 240576.79 | J17: ='Annual Data'!E29+'Annual Data'!I29 -> 358690.21 | K17: ='Annual Data'!F29-'Annual Data'!G29 -> 43276 | V17: 45839 | W17: Q3 25 | X17: =100*((AC17-AC$6)/'Quarterly Data'!$G$206) -> 2.1205923 | Y17: =100*((AD17-AD$6)/'Quarterly Data'!$G$206) -> 0.38297545 | Z17: =100*(('Quarterly Data'!G217/'Quarterly Data'!$G$206)-1) -> 2.5035677 | AB17: 45839 | AC17: ='Quarterly Data'!J217+'Quarterly Data'!N217 -> 174507 | AD17: ='Quarterly Data'!G217-'Chart Data'!AC17 -> 531555 | AR17: =[2]Contributions!B305 -> 44986 | AS17: =[2]Contributions!C305 -> 2.4389848 | AT17: =[2]Contributions!D305 -> -0.20308559 | AU17: =[2]Contributions!E305 -> 3.0831151 | AV17: =AW17-AS17-AT17-AU17 -> 4.7378631 | AW17: =[2]Contributions!G305 -> 10.056877 | AX17: 2 | AZ17: 44743 | BA17: =100*((BL17/BL13)-1) -> 1.7992083 | BB17: =100*((BM17/BM13)-1) -> 0.77310531 | BC17: =100*((BN17/BN13)-1) -> 2.7699591 | BE17: 44743 | BF17: =BL17-AVERAGE(BL$23:BL$26) -> -614.75 | BG17: =BM17-AVERAGE(BM$23:BM$26) -> -342.25 | BH17: =BN17-AVERAGE(BN$23:BN$26) -> 146.75 | BI17: =SUM(BF17:BH17) -> -810.25 | BK17: 44743 | BL17: ='Quarterly Data'!AH205+'Quarterly Data'!AI205+'Quarterly Data'!AJ205+'Quarterly Data'!AK205+'Quarterly Data'!AL205 -> 11316 | BM17: ='Quarterly Data'!W205+'Quarterly Data'!AD205+'Quarterly Data'!U205+'Quarterly Data'!AC205+'Quarterly Data'!AF205+'Quarterly Data'!X205+'Quarterly Data'!Y205 -> 8603 | BN17: ='Quarterly Data'!AA205+'Quarterly Data'!V205+'Quarterly Data'!AE205+'Quarterly Data'!T205+'Quarterly Data'!AG205+'Quarterly Data'!Z205+'Quarterly Data'!AB205 -> 16065 | BO17: ='Quarterly Data'!S205-'Chart Data'!BL17-'Chart Data'!BM17-'Chart Data'!BN17 -> 1 | BQ17: =BM17+BN17 -> 24668
A18: 1996 | B18: =100*(('Annual Data'!C30-'Annual Data'!C29)/'Annual Data'!$B29) -> 2.1586046 | C18: =100*((I18-I17)/'Annual Data'!$B29) -> 1.084603 | D18: =100*((J18-J17)/'Annual Data'!$B29) -> -0.1581749 | E18: =100*((K18-K17)/'Annual Data'!$B29) -> -0.21644595 | F18: =G18-B18-C18-D18-E18 -> -0.25367071 | G18: =100*(('Annual Data'!B30/'Annual Data'!B29)-1) -> 2.614916 | I18: ='Annual Data'!D30-'Annual Data'!I30 -> 258175.3 | J18: ='Annual Data'!E30+'Annual Data'!I30 -> 356123.7 | K18: ='Annual Data'!F30-'Annual Data'!G30 -> 39764 | V18: 45931 | W18: Q4 25 | X18: =100*((AC18-AC$6)/'Quarterly Data'!$G$206) -> 2.1917839 | Y18: =100*((AD18-AD$6)/'Quarterly Data'!$G$206) -> 0.51264995 | Z18: =100*(('Quarterly Data'!G218/'Quarterly Data'!$G$206)-1) -> 2.7044338 | AB18: 45931 | AC18: ='Quarterly Data'!J218+'Quarterly Data'!N218 -> 174997.38 | AD18: ='Quarterly Data'!G218-'Chart Data'!AC18 -> 532448.22 | AR18: =[2]Contributions!B306 -> 45017 | AS18: =[2]Contributions!C306 -> 2.5552057 | AT18: =[2]Contributions!D306 -> -0.30234716 | AU18: =[2]Contributions!E306 -> 1.2789752 | AV18: =AW18-AS18-AT18-AU18 -> 5.1264022 | AW18: =[2]Contributions!G306 -> 8.6582359 | AX18: 2 | AZ18: 44835 | BA18: =100*((BL18/BL14)-1) -> 1.8307458 | BB18: =100*((BM18/BM14)-1) -> 2.0560748 | BC18: =100*((BN18/BN14)-1) -> 3.0272 | BE18: 44835 | BF18: =BL18-AVERAGE(BL$23:BL$26) -> -583.75 | BG18: =BM18-AVERAGE(BM$23:BM$26) -> -209.25 | BH18: =BN18-AVERAGE(BN$23:BN$26) -> 179.75 | BI18: =SUM(BF18:BH18) -> -613.25 | BK18: 44835 | BL18: ='Quarterly Data'!AH206+'Quarterly Data'!AI206+'Quarterly Data'!AJ206+'Quarterly Data'!AK206+'Quarterly Data'!AL206 -> 11347 | BM18: ='Quarterly Data'!W206+'Quarterly Data'!AD206+'Quarterly Data'!U206+'Quarterly Data'!AC206+'Quarterly Data'!AF206+'Quarterly Data'!X206+'Quarterly Data'!Y206 -> 8736 | BN18: ='Quarterly Data'!AA206+'Quarterly Data'!V206+'Quarterly Data'!AE206+'Quarterly Data'!T206+'Quarterly Data'!AG206+'Quarterly Data'!Z206+'Quarterly Data'!AB206 -> 16098 | BO18: ='Quarterly Data'!S206-'Chart Data'!BL18-'Chart Data'!BM18-'Chart Data'!BN18 -> 0 | BQ18: =BM18+BN18 -> 24834
A19: 1997 | B19: =100*(('Annual Data'!C31-'Annual Data'!C30)/'Annual Data'!$B30) -> 2.7819736 | C19: =100*((I19-I18)/'Annual Data'!$B30) -> -0.38025694 | D19: =100*((J19-J18)/'Annual Data'!$B30) -> 0.15761496 | E19: =100*((K19-K18)/'Annual Data'!$B30) -> 0.77537305 | F19: =G19-B19-C19-D19-E19 -> 1.5452806 | G19: =100*(('Annual Data'!B31/'Annual Data'!B30)-1) -> 4.8799853 | I19: ='Annual Data'!D31-'Annual Data'!I31 -> 251844 | J19: ='Annual Data'!E31+'Annual Data'!I31 -> 358748 | K19: ='Annual Data'!F31-'Annual Data'!G31 -> 52674 | V19: 46023 | W19: Q1 26 | X19: =100*((AC19-AC$6)/'Quarterly Data'!$G$206) -> 2.3661001 | Y19: =100*((AD19-AD$6)/'Quarterly Data'!$G$206) -> 0.62055669 | Z19: =100*(('Quarterly Data'!G219/'Quarterly Data'!$G$206)-1) -> 2.9866568 | AB19: 46023 | AC19: ='Quarterly Data'!J219+'Quarterly Data'!N219 -> 176198.1 | AD19: ='Quarterly Data'!G219-'Chart Data'!AC19 -> 533191.5 | AR19: =[2]Contributions!B307 -> 45047 | AS19: =[2]Contributions!C307 -> 2.4891086 | AT19: =[2]Contributions!D307 -> -0.45580316 | AU19: =[2]Contributions!E307 -> 1.2467361 | AV19: =AW19-AS19-AT19-AU19 -> 5.4006406 | AW19: =[2]Contributions!G307 -> 8.680682 | AX19: 2 | AZ19: 44927 | BA19: =100*((BL19/BL15)-1) -> 2.1445097 | BB19: =100*((BM19/BM15)-1) -> 3.056263 | BC19: =100*((BN19/BN15)-1) -> 2.027155 | BE19: 44927 | BF19: =BL19-AVERAGE(BL$23:BL$26) -> -451.75 | BG19: =BM19-AVERAGE(BM$23:BM$26) -> -43.25 | BH19: =BN19-AVERAGE(BN$23:BN$26) -> 237.75 | BI19: =SUM(BF19:BH19) -> -257.25 | BK19: 44927 | BL19: ='Quarterly Data'!AH207+'Quarterly Data'!AI207+'Quarterly Data'!AJ207+'Quarterly Data'!AK207+'Quarterly Data'!AL207 -> 11479 | BM19: ='Quarterly Data'!W207+'Quarterly Data'!AD207+'Quarterly Data'!U207+'Quarterly Data'!AC207+'Quarterly Data'!AF207+'Quarterly Data'!X207+'Quarterly Data'!Y207 -> 8902 | BN19: ='Quarterly Data'!AA207+'Quarterly Data'!V207+'Quarterly Data'!AE207+'Quarterly Data'!T207+'Quarterly Data'!AG207+'Quarterly Data'!Z207+'Quarterly Data'!AB207 -> 16156 | BO19: ='Quarterly Data'!S207-'Chart Data'!BL19-'Chart Data'!BM19-'Chart Data'!BN19 -> 0 | BQ19: =BM19+BN19 -> 25058
A20: 1998 | B20: =100*(('Annual Data'!C32-'Annual Data'!C31)/'Annual Data'!$B31) -> 2.3707851 | C20: =100*((I20-I19)/'Annual Data'!$B31) -> 0.78579499 | D20: =100*((J20-J19)/'Annual Data'!$B31) -> 0.87713321 | E20: =100*((K20-K19)/'Annual Data'!$B31) -> -0.89156407 | F20: =G20-B20-C20-D20-E20 -> 0.10416565 | G20: =100*(('Annual Data'!B32/'Annual Data'!B31)-1) -> 3.2463148 | I20: ='Annual Data'!D32-'Annual Data'!I32 -> 265566 | J20: ='Annual Data'!E32+'Annual Data'!I32 -> 374065 | K20: ='Annual Data'!F32-'Annual Data'!G32 -> 37105 | V20: 46113 | W20: Q2 26 | X20: =100*((AC20-AC$6)/'Quarterly Data'!$G$206) -> 2.5335786 | Y20: =100*((AD20-AD$6)/'Quarterly Data'!$G$206) -> 0.71712516 | Z20: =100*(('Quarterly Data'!G220/'Quarterly Data'!$G$206)-1) -> 3.2507037 | AB20: 46113 | AC20: ='Quarterly Data'!J220+'Quarterly Data'!N220 -> 177351.72 | AD20: ='Quarterly Data'!G220-'Chart Data'!AC20 -> 533856.68 | AR20: =[2]Contributions!B308 -> 45078 | AS20: =[2]Contributions!C308 -> 2.3774168 | AT20: =[2]Contributions!D308 -> -0.85163887 | AU20: =[2]Contributions!E308 -> 1.2177235 | AV20: =AW20-AS20-AT20-AU20 -> 5.2061829 | AW20: =[2]Contributions!G308 -> 7.9496843 | AX20: 2 | AZ20: 45017 | BA20: =100*((BL20/BL16)-1) -> 1.4120554 | BB20: =100*((BM20/BM16)-1) -> 2.4672767 | BC20: =100*((BN20/BN16)-1) -> 0.22560632 | BE20: 45017 | BF20: =BL20-AVERAGE(BL$23:BL$26) -> -439.75 | BG20: =BM20-AVERAGE(BM$23:BM$26) -> -99.25 | BH20: =BN20-AVERAGE(BN$23:BN$26) -> 74.75 | BI20: =SUM(BF20:BH20) -> -464.25 | BK20: 45017 | BL20: ='Quarterly Data'!AH208+'Quarterly Data'!AI208+'Quarterly Data'!AJ208+'Quarterly Data'!AK208+'Quarterly Data'!AL208 -> 11491 | BM20: ='Quarterly Data'!W208+'Quarterly Data'!AD208+'Quarterly Data'!U208+'Quarterly Data'!AC208+'Quarterly Data'!AF208+'Quarterly Data'!X208+'Quarterly Data'!Y208 -> 8846 | BN20: ='Quarterly Data'!AA208+'Quarterly Data'!V208+'Quarterly Data'!AE208+'Quarterly Data'!T208+'Quarterly Data'!AG208+'Quarterly Data'!Z208+'Quarterly Data'!AB208 -> 15993 | BO20: ='Quarterly Data'!S208-'Chart Data'!BL20-'Chart Data'!BM20-'Chart Data'!BN20 -> 0 | BQ20: =BM20+BN20 -> 24839
A21: 1999 | B21: =100*(('Annual Data'!C33-'Annual Data'!C32)/'Annual Data'!$B32) -> 2.5122217 | C21: =100*((I21-I20)/'Annual Data'!$B32) -> 0.36712137 | D21: =100*((J21-J20)/'Annual Data'!$B32) -> 0.55686637 | E21: =100*((K21-K20)/'Annual Data'!$B32) -> -0.81666339 | F21: =G21-B21-C21-D21-E21 -> 0.32491267 | G21: =100*(('Annual Data'!B33/'Annual Data'!B32)-1) -> 2.9444587 | I21: ='Annual Data'!D33-'Annual Data'!I33 -> 272185 | J21: ='Annual Data'!E33+'Annual Data'!I33 -> 384105 | K21: ='Annual Data'!F33-'Annual Data'!G33 -> 22381 | V21: 46204 | W21: Q3 26 | X21: =100*((AC21-AC$6)/'Quarterly Data'!$G$206) -> 2.6981129 | Y21: =100*((AD21-AD$6)/'Quarterly Data'!$G$206) -> 0.86717372 | Z21: =100*(('Quarterly Data'!G221/'Quarterly Data'!$G$206)-1) -> 3.5652866 | AB21: 46204 | AC21: ='Quarterly Data'!J221+'Quarterly Data'!N221 -> 178485.06 | AD21: ='Quarterly Data'!G221-'Chart Data'!AC21 -> 534890.24 | AR21: =[2]Contributions!B309 -> 45108 | AS21: =[2]Contributions!C309 -> 2.1219679 | AT21: =[2]Contributions!D309 -> -0.95626278 | AU21: =[2]Contributions!E309 -> 0.45317659 | AV21: =AW21-AS21-AT21-AU21 -> 5.2083325 | AW21: =[2]Contributions!G309 -> 6.8272142 | AX21: 2 | AZ21: 45108 | BA21: =100*((BL21/BL17)-1) -> 2.2357724 | BB21: =100*((BM21/BM17)-1) -> 2.6037429 | BC21: =100*((BN21/BN17)-1) -> -0.29256147 | BE21: 45108 | BF21: =BL21-AVERAGE(BL$23:BL$26) -> -361.75 | BG21: =BM21-AVERAGE(BM$23:BM$26) -> -118.25 | BH21: =BN21-AVERAGE(BN$23:BN$26) -> 99.75 | BI21: =SUM(BF21:BH21) -> -380.25 | BK21: 45108 | BL21: ='Quarterly Data'!AH209+'Quarterly Data'!AI209+'Quarterly Data'!AJ209+'Quarterly Data'!AK209+'Quarterly Data'!AL209 -> 11569 | BM21: ='Quarterly Data'!W209+'Quarterly Data'!AD209+'Quarterly Data'!U209+'Quarterly Data'!AC209+'Quarterly Data'!AF209+'Quarterly Data'!X209+'Quarterly Data'!Y209 -> 8827 | BN21: ='Quarterly Data'!AA209+'Quarterly Data'!V209+'Quarterly Data'!AE209+'Quarterly Data'!T209+'Quarterly Data'!AG209+'Quarterly Data'!Z209+'Quarterly Data'!AB209 -> 16018 | BO21: ='Quarterly Data'!S209-'Chart Data'!BL21-'Chart Data'!BM21-'Chart Data'!BN21 -> 1 | BQ21: =BM21+BN21 -> 24845
A22: 2000 | B22: =100*(('Annual Data'!C34-'Annual Data'!C33)/'Annual Data'!$B33) -> 2.7657375 | C22: =100*((I22-I21)/'Annual Data'!$B33) -> 0.952246 | D22: =100*((J22-J21)/'Annual Data'!$B33) -> 0.68775717 | E22: =100*((K22-K21)/'Annual Data'!$B33) -> 0.27090036 | F22: =G22-B22-C22-D22-E22 -> -0.15226022 | G22: =100*(('Annual Data'!B34/'Annual Data'!B33)-1) -> 4.5243808 | I22: ='Annual Data'!D34-'Annual Data'!I34 -> 289859 | J22: ='Annual Data'!E34+'Annual Data'!I34 -> 396870 | K22: ='Annual Data'!F34-'Annual Data'!G34 -> 27409 | V22: 46296 | W22: Q4 26 | X22: =100*((AC22-AC$6)/'Quarterly Data'!$G$206) -> 2.8570273 | Y22: =100*((AD22-AD$6)/'Quarterly Data'!$G$206) -> 1.044154 | Z22: =100*(('Quarterly Data'!G222/'Quarterly Data'!$G$206)-1) -> 3.9011813 | AB22: 46296 | AC22: ='Quarterly Data'!J222+'Quarterly Data'!N222 -> 179579.69 | AD22: ='Quarterly Data'!G222-'Chart Data'!AC22 -> 536109.31 | AR22: =[2]Contributions!B310 -> 45139 | AS22: =[2]Contributions!C310 -> 2.0333022 | AT22: =[2]Contributions!D310 -> -0.58279347 | AU22: =[2]Contributions!E310 -> 0.48414516 | AV22: =AW22-AS22-AT22-AU22 -> 4.7223767 | AW22: =[2]Contributions!G310 -> 6.6570306 | AX22: 2 | AZ22: 45200 | BA22: =100*((BL22/BL18)-1) -> 2.8553803 | BB22: =100*((BM22/BM18)-1) -> 0.8470696 | BC22: =100*((BN22/BN18)-1) -> -0.45347248 | BE22: 45200 | BF22: =BL22-AVERAGE(BL$23:BL$26) -> -259.75 | BG22: =BM22-AVERAGE(BM$23:BM$26) -> -135.25 | BH22: =BN22-AVERAGE(BN$23:BN$26) -> 106.75 | BI22: =SUM(BF22:BH22) -> -288.25 | BK22: 45200 | BL22: ='Quarterly Data'!AH210+'Quarterly Data'!AI210+'Quarterly Data'!AJ210+'Quarterly Data'!AK210+'Quarterly Data'!AL210 -> 11671 | BM22: ='Quarterly Data'!W210+'Quarterly Data'!AD210+'Quarterly Data'!U210+'Quarterly Data'!AC210+'Quarterly Data'!AF210+'Quarterly Data'!X210+'Quarterly Data'!Y210 -> 8810 | BN22: ='Quarterly Data'!AA210+'Quarterly Data'!V210+'Quarterly Data'!AE210+'Quarterly Data'!T210+'Quarterly Data'!AG210+'Quarterly Data'!Z210+'Quarterly Data'!AB210 -> 16025 | BO22: ='Quarterly Data'!S210-'Chart Data'!BL22-'Chart Data'!BM22-'Chart Data'!BN22 -> -3 | BQ22: =BM22+BN22 -> 24835
A23: 2001 | B23: =100*(('Annual Data'!C35-'Annual Data'!C34)/'Annual Data'!$B34) -> 1.9862815 | C23: =100*((I23-I22)/'Annual Data'!$B34) -> 0.091133692 | D23: =100*((J23-J22)/'Annual Data'!$B34) -> 1.2701501 | E23: =100*((K23-K22)/'Annual Data'!$B34) -> -0.88927514 | F23: =G23-B23-C23-D23-E23 -> -0.067267799 | G23: =100*(('Annual Data'!B35/'Annual Data'!B34)-1) -> 2.3910223 | I23: ='Annual Data'!D35-'Annual Data'!I35 -> 291627 | J23: ='Annual Data'!E35+'Annual Data'!I35 -> 421511 | K23: ='Annual Data'!F35-'Annual Data'!G35 -> 10157 | AR23: =[2]Contributions!B311 -> 45170 | AS23: =[2]Contributions!C311 -> 1.8973456 | AT23: =[2]Contributions!D311 -> -0.32853829 | AU23: =[2]Contributions!E311 -> 0.46832106 | AV23: =AW23-AS23-AT23-AU23 -> 4.6150483 | AW23: =[2]Contributions!G311 -> 6.6521767 | AX23: 2 | AZ23: 45292 | BA23: =100*((BL23/BL19)-1) -> 3.7895287 | BB23: =100*((BM23/BM19)-1) -> 0.033700292 | BC23: =100*((BN23/BN19)-1) -> -1.1450854 | BE23: 45292 | BF23: =BL23-AVERAGE(BL$23:BL$26) -> -16.75 | BG23: =BM23-AVERAGE(BM$23:BM$26) -> -40.25 | BH23: =BN23-AVERAGE(BN$23:BN$26) -> 52.75 | BI23: =SUM(BF23:BH23) -> -4.25 | BK23: 45292 | BL23: ='Quarterly Data'!AH211+'Quarterly Data'!AI211+'Quarterly Data'!AJ211+'Quarterly Data'!AK211+'Quarterly Data'!AL211 -> 11914 | BM23: ='Quarterly Data'!W211+'Quarterly Data'!AD211+'Quarterly Data'!U211+'Quarterly Data'!AC211+'Quarterly Data'!AF211+'Quarterly Data'!X211+'Quarterly Data'!Y211 -> 8905 | BN23: ='Quarterly Data'!AA211+'Quarterly Data'!V211+'Quarterly Data'!AE211+'Quarterly Data'!T211+'Quarterly Data'!AG211+'Quarterly Data'!Z211+'Quarterly Data'!AB211 -> 15971 | BO23: ='Quarterly Data'!S211-'Chart Data'!BL23-'Chart Data'!BM23-'Chart Data'!BN23 -> -1 | BQ23: =BM23+BN23 -> 24876
A24: 2002 | B24: =100*(('Annual Data'!C36-'Annual Data'!C35)/'Annual Data'!$B35) -> 1.6153903 | C24: =100*((I24-I23)/'Annual Data'!$B35) -> 0.14387888 | D24: =100*((J24-J23)/'Annual Data'!$B35) -> 0.84691197 | E24: =100*((K24-K23)/'Annual Data'!$B35) -> -0.92665449 | F24: =G24-B24-C24-D24-E24 -> 0.029500708 | G24: =100*(('Annual Data'!B36/'Annual Data'!B35)-1) -> 1.7090274 | I24: ='Annual Data'!D36-'Annual Data'!I36 -> 294485 | J24: ='Annual Data'!E36+'Annual Data'!I36 -> 438334 | K24: ='Annual Data'!F36-'Annual Data'!G36 -> -8250 | AC24: =AC17/'Quarterly Data'!G217 -> 0.24715535 | AR24: =[2]Contributions!B312 -> 45200 | AS24: =[2]Contributions!C312 -> 1.639459 | AT24: =[2]Contributions!D312 -> -0.25121814 | AU24: =[2]Contributions!E312 -> -1.0539877 | AV24: =AW24-AS24-AT24-AU24 -> 4.2656248 | AW24: =[2]Contributions!G312 -> 4.599878 | AX24: 2 | AZ24: 45383 | BA24: =100*((BL24/BL20)-1) -> 3.8812984 | BB24: =100*((BM24/BM20)-1) -> 0.1017409 | BC24: =100*((BN24/BN20)-1) -> -0.46270243 | BE24: 45383 | BF24: =BL24-AVERAGE(BL$23:BL$26) -> 6.25 | BG24: =BM24-AVERAGE(BM$23:BM$26) -> -90.25 | BH24: =BN24-AVERAGE(BN$23:BN$26) -> 0.75 | BI24: =SUM(BF24:BH24) -> -83.25 | BK24: 45383 | BL24: ='Quarterly Data'!AH212+'Quarterly Data'!AI212+'Quarterly Data'!AJ212+'Quarterly Data'!AK212+'Quarterly Data'!AL212 -> 11937 | BM24: ='Quarterly Data'!W212+'Quarterly Data'!AD212+'Quarterly Data'!U212+'Quarterly Data'!AC212+'Quarterly Data'!AF212+'Quarterly Data'!X212+'Quarterly Data'!Y212 -> 8855 | BN24: ='Quarterly Data'!AA212+'Quarterly Data'!V212+'Quarterly Data'!AE212+'Quarterly Data'!T212+'Quarterly Data'!AG212+'Quarterly Data'!Z212+'Quarterly Data'!AB212 -> 15919 | BO24: ='Quarterly Data'!S212-'Chart Data'!BL24-'Chart Data'!BM24-'Chart Data'!BN24 -> -1 | BQ24: =BM24+BN24 -> 24774
A25: 2003 | B25: =100*(('Annual Data'!C37-'Annual Data'!C36)/'Annual Data'!$B36) -> 2.0667303 | C25: =100*((I25-I24)/'Annual Data'!$B36) -> 0.15532031 | D25: =100*((J25-J24)/'Annual Data'!$B36) -> 1.0731852 | E25: =100*((K25-K24)/'Annual Data'!$B36) -> -0.01628438 | F25: =G25-B25-C25-D25-E25 -> -0.060435342 | G25: =100*(('Annual Data'!B37/'Annual Data'!B36)-1) -> 3.2185161 | I25: ='Annual Data'!D37-'Annual Data'!I37 -> 297623 | J25: ='Annual Data'!E37+'Annual Data'!I37 -> 460016 | K25: ='Annual Data'!F37-'Annual Data'!G37 -> -8579 | AR25: =[2]Contributions!B313 -> 45231 | AS25: =[2]Contributions!C313 -> 1.5053144 | AT25: =[2]Contributions!D313 -> -0.35236691 | AU25: =[2]Contributions!E313 -> -1.0437809 | AV25: =AW25-AS25-AT25-AU25 -> 3.8318251 | AW25: =[2]Contributions!G313 -> 3.9409917 | AX25: 2 | AZ25: 45474 | BA25: =100*((BL25/BL21)-1) -> 2.9043133 | BB25: =100*((BM25/BM21)-1) -> 1.8805936 | BC25: =100*((BN25/BN21)-1) -> -0.92396054 | BE25: 45474 | BF25: =BL25-AVERAGE(BL$23:BL$26) -> -25.75 | BG25: =BM25-AVERAGE(BM$23:BM$26) -> 47.75 | BH25: =BN25-AVERAGE(BN$23:BN$26) -> -48.25 | BI25: =SUM(BF25:BH25) -> -26.25 | BK25: 45474 | BL25: ='Quarterly Data'!AH213+'Quarterly Data'!AI213+'Quarterly Data'!AJ213+'Quarterly Data'!AK213+'Quarterly Data'!AL213 -> 11905 | BM25: ='Quarterly Data'!W213+'Quarterly Data'!AD213+'Quarterly Data'!U213+'Quarterly Data'!AC213+'Quarterly Data'!AF213+'Quarterly Data'!X213+'Quarterly Data'!Y213 -> 8993 | BN25: ='Quarterly Data'!AA213+'Quarterly Data'!V213+'Quarterly Data'!AE213+'Quarterly Data'!T213+'Quarterly Data'!AG213+'Quarterly Data'!Z213+'Quarterly Data'!AB213 -> 15870 | BO25: ='Quarterly Data'!S213-'Chart Data'!BL25-'Chart Data'!BM25-'Chart Data'!BN25 -> -2 | BQ25: =BM25+BN25 -> 24863
A26: 2004 | B26: =100*(('Annual Data'!C38-'Annual Data'!C37)/'Annual Data'!$B37) -> 1.6888163 | C26: =100*((I26-I25)/'Annual Data'!$B37) -> -0.050878359 | D26: =100*((J26-J25)/'Annual Data'!$B37) -> 1.3038958 | E26: =100*((K26-K25)/'Annual Data'!$B37) -> -0.59030405 | F26: =G26-B26-C26-D26-E26 -> -0.025511109 | G26: =100*(('Annual Data'!B38/'Annual Data'!B37)-1) -> 2.3260186 | I26: ='Annual Data'!D38-'Annual Data'!I38 -> 296562 | J26: ='Annual Data'!E38+'Annual Data'!I38 -> 487207 | K26: ='Annual Data'!F38-'Annual Data'!G38 -> -20889 | AR26: =[2]Contributions!B314 -> 45261 | AS26: =[2]Contributions!C314 -> 1.4800743 | AT26: =[2]Contributions!D314 -> -0.34448789 | AU26: =[2]Contributions!E314 -> -1.030636 | AV26: =AW26-AS26-AT26-AU26 -> 3.8883181 | AW26: =[2]Contributions!G314 -> 3.9932685 | AX26: 2 | AZ26: 45566 | BA26: =100*((BL26/BL22)-1) -> 2.5362008 | BB26: =100*((BM26/BM22)-1) -> 2.4744608 | BC26: =100*((BN26/BN22)-1) -> -0.69890796 | BE26: 45566 | BF26: =BL26-AVERAGE(BL$23:BL$26) -> 36.25 | BG26: =BM26-AVERAGE(BM$23:BM$26) -> 82.75 | BH26: =BN26-AVERAGE(BN$23:BN$26) -> -5.25 | BI26: =SUM(BF26:BH26) -> 113.75 | BK26: 45566 | BL26: ='Quarterly Data'!AH214+'Quarterly Data'!AI214+'Quarterly Data'!AJ214+'Quarterly Data'!AK214+'Quarterly Data'!AL214 -> 11967 | BM26: ='Quarterly Data'!W214+'Quarterly Data'!AD214+'Quarterly Data'!U214+'Quarterly Data'!AC214+'Quarterly Data'!AF214+'Quarterly Data'!X214+'Quarterly Data'!Y214 -> 9028 | BN26: ='Quarterly Data'!AA214+'Quarterly Data'!V214+'Quarterly Data'!AE214+'Quarterly Data'!T214+'Quarterly Data'!AG214+'Quarterly Data'!Z214+'Quarterly Data'!AB214 -> 15913 | BO26: ='Quarterly Data'!S214-'Chart Data'!BL26-'Chart Data'!BM26-'Chart Data'!BN26 -> -2 | BQ26: =BM26+BN26 -> 24941
A27: 2005 | B27: =100*(('Annual Data'!C39-'Annual Data'!C38)/'Annual Data'!$B38) -> 1.6400234 | C27: =100*((I27-I26)/'Annual Data'!$B38) -> 1.1316752 | D27: =100*((J27-J26)/'Annual Data'!$B38) -> 0.61355601 | E27: =100*((K27-K26)/'Annual Data'!$B38) -> -0.027789858 | F27: =G27-B27-C27-D27-E27 -> -0.56681001 | G27: =100*(('Annual Data'!B39/'Annual Data'!B38)-1) -> 2.7906547 | I27: ='Annual Data'!D39-'Annual Data'!I39 -> 320710.5 | J27: ='Annual Data'!E39+'Annual Data'!I39 -> 500299.5 | K27: ='Annual Data'!F39-'Annual Data'!G39 -> -21482 | AR27: =[2]Contributions!B315 -> 45292 | AS27: =[2]Contributions!C315 -> 1.3226708 | AT27: =[2]Contributions!D315 -> -0.29421019 | AU27: =[2]Contributions!E315 -> -0.88012568 | AV27: =AW27-AS27-AT27-AU27 -> 3.8327797 | AW27: =[2]Contributions!G315 -> 3.9811146 | AX27: 2 | AZ27: 45658 | BA27: =100*((BL27/BL23)-1) -> 2.1487326 | BB27: =100*((BM27/BM23)-1) -> 0.68500842 | BC27: =100*((BN27/BN23)-1) -> -0.48212385 | BE27: 45658 | BF27: =BL27-AVERAGE(BL$23:BL$26) -> 239.25 | BG27: =BM27-AVERAGE(BM$23:BM$26) -> 20.75 | BH27: =BN27-AVERAGE(BN$23:BN$26) -> -24.25 | BI27: =SUM(BF27:BH27) -> 235.75 | BK27: 45658 | BL27: ='Quarterly Data'!AH215+'Quarterly Data'!AI215+'Quarterly Data'!AJ215+'Quarterly Data'!AK215+'Quarterly Data'!AL215 -> 12170 | BM27: ='Quarterly Data'!W215+'Quarterly Data'!AD215+'Quarterly Data'!U215+'Quarterly Data'!AC215+'Quarterly Data'!AF215+'Quarterly Data'!X215+'Quarterly Data'!Y215 -> 8966 | BN27: ='Quarterly Data'!AA215+'Quarterly Data'!V215+'Quarterly Data'!AE215+'Quarterly Data'!T215+'Quarterly Data'!AG215+'Quarterly Data'!Z215+'Quarterly Data'!AB215 -> 15894 | BO27: ='Quarterly Data'!S215-'Chart Data'!BL27-'Chart Data'!BM27-'Chart Data'!BN27 -> 0 | BQ27: =BM27+BN27 -> 24860
A28: 2006 | B28: =100*(('Annual Data'!C40-'Annual Data'!C39)/'Annual Data'!$B39) -> 0.4870474 | C28: =100*((I28-I27)/'Annual Data'!$B39) -> 0.61650271 | D28: =100*((J28-J27)/'Annual Data'!$B39) -> 0.1555333 | E28: =100*((K28-K27)/'Annual Data'!$B39) -> 0.35401321 | F28: =G28-B28-C28-D28-E28 -> 0.57672467 | G28: =100*(('Annual Data'!B40/'Annual Data'!B39)-1) -> 2.1898213 | I28: ='Annual Data'!D40-'Annual Data'!I40 -> 334233 | J28: ='Annual Data'!E40+'Annual Data'!I40 -> 503711 | K28: ='Annual Data'!F40-'Annual Data'!G40 -> -13717 | AR28: =[2]Contributions!B316 -> 45323 | AS28: =[2]Contributions!C316 -> 1.0836049 | AT28: =[2]Contributions!D316 -> -0.18987115 | AU28: =[2]Contributions!E316 -> -0.87917176 | AV28: =AW28-AS28-AT28-AU28 -> 3.3969102 | AW28: =[2]Contributions!G316 -> 3.4114722 | AX28: 2 | AZ28: 45748 | BA28: =100*((BL28/BL24)-1) -> 1.5330485 | BB28: =100*((BM28/BM24)-1) -> 0.32749859 | BC28: =100*((BN28/BN24)-1) -> -0.47113512 | BE28: 45748 | BF28: =BL28-AVERAGE(BL$23:BL$26) -> 189.25 | BG28: =BM28-AVERAGE(BM$23:BM$26) -> -61.25 | BH28: =BN28-AVERAGE(BN$23:BN$26) -> -74.25 | BI28: =SUM(BF28:BH28) -> 53.75 | BK28: 45748 | BL28: ='Quarterly Data'!AH216+'Quarterly Data'!AI216+'Quarterly Data'!AJ216+'Quarterly Data'!AK216+'Quarterly Data'!AL216 -> 12120 | BM28: ='Quarterly Data'!W216+'Quarterly Data'!AD216+'Quarterly Data'!U216+'Quarterly Data'!AC216+'Quarterly Data'!AF216+'Quarterly Data'!X216+'Quarterly Data'!Y216 -> 8884 | BN28: ='Quarterly Data'!AA216+'Quarterly Data'!V216+'Quarterly Data'!AE216+'Quarterly Data'!T216+'Quarterly Data'!AG216+'Quarterly Data'!Z216+'Quarterly Data'!AB216 -> 15844 | BO28: ='Quarterly Data'!S216-'Chart Data'!BL28-'Chart Data'!BM28-'Chart Data'!BN28 -> 0 | BQ28: =BM28+BN28 -> 24728
A29: 2007 | B29: =100*(('Annual Data'!C41-'Annual Data'!C40)/'Annual Data'!$B40) -> 2.1543615 | C29: =100*((I29-I28)/'Annual Data'!$B40) -> 0.82482211 | D29: =100*((J29-J28)/'Annual Data'!$B40) -> 0.40143603 | E29: =100*((K29-K28)/'Annual Data'!$B40) -> -0.13352946 | F29: =G29-B29-C29-D29-E29 -> -0.31617884 | G29: =100*(('Annual Data'!B41/'Annual Data'!B40)-1) -> 2.9309113 | I29: ='Annual Data'!D41-'Annual Data'!I41 -> 352721 | J29: ='Annual Data'!E41+'Annual Data'!I41 -> 512709 | K29: ='Annual Data'!F41-'Annual Data'!G41 -> -16710 | AR29: =[2]Contributions!B317 -> 45352 | AS29: =[2]Contributions!C317 -> 0.97087291 | AT29: =[2]Contributions!D317 -> -0.094867963 | AU29: =[2]Contributions!E317 -> -0.87097105 | AV29: =AW29-AS29-AT29-AU29 -> 3.2230254 | AW29: =[2]Contributions!G317 -> 3.2280593 | AX29: 2 | AZ29: 45839 | BA29: =100*((BL29/BL25)-1) -> 2.2435111 | BB29: =100*((BM29/BM25)-1) -> -0.73713333 | BC29: =100*((BN29/BN25)-1) -> -0.28030057 | BE29: 45839 | BF29: =BL29-AVERAGE(BL$23:BL$26) -> 241.34 | BG29: =BM29-AVERAGE(BM$23:BM$26) -> -18.5404 | BH29: =BN29-AVERAGE(BN$23:BN$26) -> -92.7337 | BI29: =SUM(BF29:BH29) -> 130.0659 | BK29: 45839 | BL29: ='Quarterly Data'!AH217+'Quarterly Data'!AI217+'Quarterly Data'!AJ217+'Quarterly Data'!AK217+'Quarterly Data'!AL217 -> 12172.09 | BM29: ='Quarterly Data'!W217+'Quarterly Data'!AD217+'Quarterly Data'!U217+'Quarterly Data'!AC217+'Quarterly Data'!AF217+'Quarterly Data'!X217+'Quarterly Data'!Y217 -> 8926.7096 | BN29: ='Quarterly Data'!AA217+'Quarterly Data'!V217+'Quarterly Data'!AE217+'Quarterly Data'!T217+'Quarterly Data'!AG217+'Quarterly Data'!Z217+'Quarterly Data'!AB217 -> 15825.516 | BO29: ='Quarterly Data'!S217-'Chart Data'!BL29-'Chart Data'!BM29-'Chart Data'!BN29 -> 0.0041 | BQ29: =BM29+BN29 -> 24752.226
A30: 2008 | B30: =100*(('Annual Data'!C42-'Annual Data'!C41)/'Annual Data'!$B41) -> -0.55609783 | C30: =100*((I30-I29)/'Annual Data'!$B41) -> -0.81706939 | D30: =100*((J30-J29)/'Annual Data'!$B41) -> 0.85906929 | E30: =100*((K30-K29)/'Annual Data'!$B41) -> 1.1088149 | F30: =G30-B30-C30-D30-E30 -> -0.6441286 | G30: =100*(('Annual Data'!B42/'Annual Data'!B41)-1) -> -0.049411655 | I30: ='Annual Data'!D42-'Annual Data'!I42 -> 333870 | J30: ='Annual Data'!E42+'Annual Data'!I42 -> 532529 | K30: ='Annual Data'!F42-'Annual Data'!G42 -> 8872 | AR30: =[2]Contributions!B318 -> 45383 | AS30: =[2]Contributions!C318 -> 0.67586846 | AT30: =[2]Contributions!D318 -> 0.013111374 | AU30: =[2]Contributions!E318 -> -1.298924 | AV30: =AW30-AS30-AT30-AU30 -> 2.9430143 | AW30: =[2]Contributions!G318 -> 2.3330701 | AX30: 2 | AZ30: 45931 | BA30: =100*((BL30/BL26)-1) -> 1.9181666 | BB30: =100*((BM30/BM26)-1) -> -1.3274274 | BC30: =100*((BN30/BN26)-1) -> -0.8412317 | BE30: 45931 | BF30: =BL30-AVERAGE(BL$23:BL$26) -> 265.797 | BG30: =BM30-AVERAGE(BM$23:BM$26) -> -37.09015 | BH30: =BN30-AVERAGE(BN$23:BN$26) -> -139.1152 | BI30: =SUM(BF30:BH30) -> 89.59165 | BK30: 45931 | BL30: ='Quarterly Data'!AH218+'Quarterly Data'!AI218+'Quarterly Data'!AJ218+'Quarterly Data'!AK218+'Quarterly Data'!AL218 -> 12196.547 | BM30: ='Quarterly Data'!W218+'Quarterly Data'!AD218+'Quarterly Data'!U218+'Quarterly Data'!AC218+'Quarterly Data'!AF218+'Quarterly Data'!X218+'Quarterly Data'!Y218 -> 8908.1599 | BN30: ='Quarterly Data'!AA218+'Quarterly Data'!V218+'Quarterly Data'!AE218+'Quarterly Data'!T218+'Quarterly Data'!AG218+'Quarterly Data'!Z218+'Quarterly Data'!AB218 -> 15779.135 | BO30: ='Quarterly Data'!S218-'Chart Data'!BL30-'Chart Data'!BM30-'Chart Data'!BN30 -> -0.00165 | BQ30: =BM30+BN30 -> 24687.295
A31: 2009 | B31: =100*(('Annual Data'!C43-'Annual Data'!C42)/'Annual Data'!$B42) -> -2.0796979 | C31: =100*((I31-I30)/'Annual Data'!$B42) -> -2.2160374 | D31: =100*((J31-J30)/'Annual Data'!$B42) -> 0.48941721 | E31: =100*((K31-K30)/'Annual Data'!$B42) -> -0.22610503 | F31: =G31-B31-C31-D31-E31 -> -0.55498507 | G31: =100*(('Annual Data'!B43/'Annual Data'!B42)-1) -> -4.5874082 | I31: ='Annual Data'!D43-'Annual Data'!I43 -> 282768 | J31: ='Annual Data'!E43+'Annual Data'!I43 -> 543815 | K31: ='Annual Data'!F43-'Annual Data'!G43 -> 3658 | AR31: =[2]Contributions!B319 -> 45413 | AS31: =[2]Contributions!C319 -> 0.52129566 | AT31: =[2]Contributions!D319 -> 0.08808913 | AU31: =[2]Contributions!E319 -> -1.288964 | AV31: =AW31-AS31-AT31-AU31 -> 2.6695569 | AW31: =[2]Contributions!G319 -> 1.9899778 | AX31: 2 | AZ31: 46023 | BA31: =100*((BL31/BL27)-1) -> 0.50743632 | BB31: =100*((BM31/BM27)-1) -> -0.39448059 | BC31: =100*((BN31/BN27)-1) -> -0.62612495 | BE31: 46023 | BF31: =BL31-AVERAGE(BL$23:BL$26) -> 301.005 | BG31: =BM31-AVERAGE(BM$23:BM$26) -> -14.61913 | BH31: =BN31-AVERAGE(BN$23:BN$26) -> -123.7663 | BI31: =SUM(BF31:BH31) -> 162.61957 | BK31: 46023 | BL31: ='Quarterly Data'!AH219+'Quarterly Data'!AI219+'Quarterly Data'!AJ219+'Quarterly Data'!AK219+'Quarterly Data'!AL219 -> 12231.755 | BM31: ='Quarterly Data'!W219+'Quarterly Data'!AD219+'Quarterly Data'!U219+'Quarterly Data'!AC219+'Quarterly Data'!AF219+'Quarterly Data'!X219+'Quarterly Data'!Y219 -> 8930.6309 | BN31: ='Quarterly Data'!AA219+'Quarterly Data'!V219+'Quarterly Data'!AE219+'Quarterly Data'!T219+'Quarterly Data'!AG219+'Quarterly Data'!Z219+'Quarterly Data'!AB219 -> 15794.484 | BO31: ='Quarterly Data'!S219-'Chart Data'!BL31-'Chart Data'!BM31-'Chart Data'!BN31 -> 0.00043 | BQ31: =BM31+BN31 -> 24725.115
A32: 2010 | B32: =100*(('Annual Data'!C44-'Annual Data'!C43)/'Annual Data'!$B43) -> 1.6476065 | C32: =100*((I32-I31)/'Annual Data'!$B43) -> 0.31687712 | D32: =100*((J32-J31)/'Annual Data'!$B43) -> 0.058494097 | E32: =100*((K32-K31)/'Annual Data'!$B43) -> -0.68329469 | F32: =G32-B32-C32-D32-E32 -> 0.92086162 | G32: =100*(('Annual Data'!B44/'Annual Data'!B43)-1) -> 2.2605446 | I32: ='Annual Data'!D44-'Annual Data'!I44 -> 289740 | J32: ='Annual Data'!E44+'Annual Data'!I44 -> 545102 | K32: ='Annual Data'!F44-'Annual Data'!G44 -> -11376 | AR32: =[2]Contributions!B320 -> 45444 | AS32: =[2]Contributions!C320 -> 0.47927689 | AT32: =[2]Contributions!D320 -> 0.084469556 | AU32: =[2]Contributions!E320 -> -1.2887757 | AV32: =AW32-AS32-AT32-AU32 -> 2.7003398 | AW32: =[2]Contributions!G320 -> 1.9753105 | AX32: 2 | AZ32: 46113 | BA32: =100*((BL32/BL28)-1) -> 1.207038 | BB32: =100*((BM32/BM28)-1) -> 0.75587382 | BC32: =100*((BN32/BN28)-1) -> -0.24572015 | BE32: 46113 | BF32: =BL32-AVERAGE(BL$23:BL$26) -> 335.543 | BG32: =BM32-AVERAGE(BM$23:BM$26) -> 5.90183 | BH32: =BN32-AVERAGE(BN$23:BN$26) -> -113.1819 | BI32: =SUM(BF32:BH32) -> 228.26293 | BK32: 46113 | BL32: ='Quarterly Data'!AH220+'Quarterly Data'!AI220+'Quarterly Data'!AJ220+'Quarterly Data'!AK220+'Quarterly Data'!AL220 -> 12266.293 | BM32: ='Quarterly Data'!W220+'Quarterly Data'!AD220+'Quarterly Data'!U220+'Quarterly Data'!AC220+'Quarterly Data'!AF220+'Quarterly Data'!X220+'Quarterly Data'!Y220 -> 8951.1518 | BN32: ='Quarterly Data'!AA220+'Quarterly Data'!V220+'Quarterly Data'!AE220+'Quarterly Data'!T220+'Quarterly Data'!AG220+'Quarterly Data'!Z220+'Quarterly Data'!AB220 -> 15805.068 | BO32: ='Quarterly Data'!S220-'Chart Data'!BL32-'Chart Data'!BM32-'Chart Data'!BN32 -> -0.00293 | BQ32: =BM32+BN32 -> 24756.22
A33: 2011 | B33: =100*(('Annual Data'!C45-'Annual Data'!C44)/'Annual Data'!$B44) -> -0.3882293 | C33: =100*((I33-I32)/'Annual Data'!$B44) -> 0.19364797 | D33: =100*((J33-J32)/'Annual Data'!$B44) -> -0.28827192 | E33: =100*((K33-K32)/'Annual Data'!$B44) -> 1.1601545 | F33: =G33-B33-C33-D33-E33 -> 0.17413651 | G33: =100*(('Annual Data'!B45/'Annual Data'!B44)-1) -> 0.85143774 | I33: ='Annual Data'!D45-'Annual Data'!I45 -> 294097 | J33: ='Annual Data'!E45+'Annual Data'!I45 -> 538616 | K33: ='Annual Data'!F45-'Annual Data'!G45 -> 14727 | AR33: =[2]Contributions!B321 -> 45474 | AS33: =[2]Contributions!C321 -> 0.47154098 | AT33: =[2]Contributions!D321 -> 0.058641613 | AU33: =[2]Contributions!E321 -> -0.83789829 | AV33: =AW33-AS33-AT33-AU33 -> 2.5421605 | AW33: =[2]Contributions!G321 -> 2.2344448 | AX33: 2 | AZ33: 46204 | BA33: =100*((BL33/BL29)-1) -> 1.065651 | BB33: =100*((BM33/BM29)-1) -> 0.52381395 | BC33: =100*((BN33/BN29)-1) -> -0.036800063 | BE33: 46204 | BF33: =BL33-AVERAGE(BL$23:BL$26) -> 371.052 | BG33: =BM33-AVERAGE(BM$23:BM$26) -> 28.21895 | BH33: =BN33-AVERAGE(BN$23:BN$26) -> -98.5575 | BI33: =SUM(BF33:BH33) -> 300.71345 | BK33: 46204 | BL33: ='Quarterly Data'!AH221+'Quarterly Data'!AI221+'Quarterly Data'!AJ221+'Quarterly Data'!AK221+'Quarterly Data'!AL221 -> 12301.802 | BM33: ='Quarterly Data'!W221+'Quarterly Data'!AD221+'Quarterly Data'!U221+'Quarterly Data'!AC221+'Quarterly Data'!AF221+'Quarterly Data'!X221+'Quarterly Data'!Y221 -> 8973.469 | BN33: ='Quarterly Data'!AA221+'Quarterly Data'!V221+'Quarterly Data'!AE221+'Quarterly Data'!T221+'Quarterly Data'!AG221+'Quarterly Data'!Z221+'Quarterly Data'!AB221 -> 15819.693 | BO33: ='Quarterly Data'!S221-'Chart Data'!BL33-'Chart Data'!BM33-'Chart Data'!BN33 -> -0.00345 | BQ33: =BM33+BN33 -> 24793.161
A34: 2012 | B34: =100*(('Annual Data'!C46-'Annual Data'!C45)/'Annual Data'!$B45) -> 1.2422899 | C34: =100*((I34-I33)/'Annual Data'!$B45) -> 0.52694529 | D34: =100*((J34-J33)/'Annual Data'!$B45) -> 0.10285944 | E34: =100*((K34-K33)/'Annual Data'!$B45) -> -0.51407685 | F34: =G34-B34-C34-D34-E34 -> 0.17024251 | G34: =100*(('Annual Data'!B46/'Annual Data'!B45)-1) -> 1.5282603 | I34: ='Annual Data'!D46-'Annual Data'!I46 -> 306054 | J34: ='Annual Data'!E46+'Annual Data'!I46 -> 540950 | K34: ='Annual Data'!F46-'Annual Data'!G46 -> 3062 | AR34: =[2]Contributions!B322 -> 45505 | AS34: =[2]Contributions!C322 -> 0.39118637 | AT34: =[2]Contributions!D322 -> -0.093170298 | AU34: =[2]Contributions!E322 -> -0.8548782 | AV34: =AW34-AS34-AT34-AU34 -> 2.7731458 | AW34: =[2]Contributions!G322 -> 2.2162837 | AX34: 2 | AZ34: 46296 | BA34: =100*((BL34/BL30)-1) -> 1.1592789 | BB34: =100*((BM34/BM30)-1) -> 1.0013572 | BC34: =100*((BN34/BN30)-1) -> 0.36496361 | BE34: 46296 | BF34: =BL34-AVERAGE(BL$23:BL$26) -> 407.189 | BG34: =BM34-AVERAGE(BM$23:BM$26) -> 52.11235 | BH34: =BN34-AVERAGE(BN$23:BN$26) -> -81.5271 | BI34: =SUM(BF34:BH34) -> 377.77425 | BK34: 46296 | BL34: ='Quarterly Data'!AH222+'Quarterly Data'!AI222+'Quarterly Data'!AJ222+'Quarterly Data'!AK222+'Quarterly Data'!AL222 -> 12337.939 | BM34: ='Quarterly Data'!W222+'Quarterly Data'!AD222+'Quarterly Data'!U222+'Quarterly Data'!AC222+'Quarterly Data'!AF222+'Quarterly Data'!X222+'Quarterly Data'!Y222 -> 8997.3623 | BN34: ='Quarterly Data'!AA222+'Quarterly Data'!V222+'Quarterly Data'!AE222+'Quarterly Data'!T222+'Quarterly Data'!AG222+'Quarterly Data'!Z222+'Quarterly Data'!AB222 -> 15836.723 | BO34: ='Quarterly Data'!S222-'Chart Data'!BL34-'Chart Data'!BM34-'Chart Data'!BN34 -> -0.00425 | BQ34: =BM34+BN34 -> 24834.085
A35: 2013 | B35: =100*(('Annual Data'!C47-'Annual Data'!C46)/'Annual Data'!$B46) -> 1.5204918 | C35: =100*((I35-I34)/'Annual Data'!$B46) -> 0.82759136 | D35: =100*((J35-J34)/'Annual Data'!$B46) -> -0.15044748 | E35: =100*((K35-K34)/'Annual Data'!$B46) -> -0.83158477 | F35: =G35-B35-C35-D35-E35 -> 0.35241866 | G35: =100*(('Annual Data'!B47/'Annual Data'!B46)-1) -> 1.7184696 | I35: ='Annual Data'!D47-'Annual Data'!I47 -> 325120 | J35: ='Annual Data'!E47+'Annual Data'!I47 -> 537484 | K35: ='Annual Data'!F47-'Annual Data'!G47 -> -16096 | AR35: =[2]Contributions!B323 -> 45536 | AS35: =[2]Contributions!C323 -> 0.41192945 | AT35: =[2]Contributions!D323 -> -0.31587462 | AU35: =[2]Contributions!E323 -> -0.86055027 | AV35: =AW35-AS35-AT35-AU35 -> 2.4448367 | AW35: =[2]Contributions!G323 -> 1.6803412 | AX35: 2
A36: 2014 | B36: =100*(('Annual Data'!C48-'Annual Data'!C47)/'Annual Data'!$B47) -> 1.8859052 | C36: =100*((I36-I35)/'Annual Data'!$B47) -> 0.89430499 | D36: =100*((J36-J35)/'Annual Data'!$B47) -> 0.78006848 | E36: =100*((K36-K35)/'Annual Data'!$B47) -> -1.1489794 | F36: =G36-B36-C36-D36-E36 -> 0.74887428 | G36: =100*(('Annual Data'!B48/'Annual Data'!B47)-1) -> 3.1601735 | I36: ='Annual Data'!D48-'Annual Data'!I48 -> 346077 | J36: ='Annual Data'!E48+'Annual Data'!I48 -> 555764 | K36: ='Annual Data'!F48-'Annual Data'!G48 -> -43021 | AR36: =[2]Contributions!B324 -> 45566 | AS36: =[2]Contributions!C324 -> 0.4273738 | AT36: =[2]Contributions!D324 -> -0.42631874 | AU36: =[2]Contributions!E324 -> -0.28714739 | AV36: =AW36-AS36-AT36-AU36 -> 2.5670838 | AW36: =[2]Contributions!G324 -> 2.2809915 | AX36: 2
A37: 2015 | B37: =100*(('Annual Data'!C49-'Annual Data'!C48)/'Annual Data'!$B48) -> 1.8465409 | C37: =100*((I37-I36)/'Annual Data'!$B48) -> 1.1075357 | D37: =100*((J37-J36)/'Annual Data'!$B48) -> 0.24625234 | E37: =100*((K37-K36)/'Annual Data'!$B48) -> -0.4644171 | F37: =G37-B37-C37-D37-E37 -> -0.59550624 | G37: =100*(('Annual Data'!B49/'Annual Data'!B48)-1) -> 2.1404056 | I37: ='Annual Data'!D49-'Annual Data'!I49 -> 372851 | J37: ='Annual Data'!E49+'Annual Data'!I49 -> 561717 | K37: ='Annual Data'!F49-'Annual Data'!G49 -> -54248 | AR37: =[2]Contributions!B325 -> 45597 | AS37: =[2]Contributions!C325 -> 0.50320077 | AT37: =[2]Contributions!D325 -> -0.33427859 | AU37: =[2]Contributions!E325 -> -0.2849168 | AV37: =AW37-AS37-AT37-AU37 -> 2.7381213 | AW37: =[2]Contributions!G325 -> 2.6221267 | AX37: 2
A38: 2016 | B38: =100*(('Annual Data'!C50-'Annual Data'!C49)/'Annual Data'!$B49) -> 2.295983 | C38: =100*((I38-I37)/'Annual Data'!$B49) -> 1.1534994 | D38: =100*((J38-J37)/'Annual Data'!$B49) -> 0.11416736 | E38: =100*((K38-K37)/'Annual Data'!$B49) -> -0.31706857 | F38: =G38-B38-C38-D38-E38 -> -1.040061 | G38: =100*(('Annual Data'!B50/'Annual Data'!B49)-1) -> 2.2065202 | I38: ='Annual Data'!D50-'Annual Data'!I50 -> 401333 | J38: ='Annual Data'!E50+'Annual Data'!I50 -> 564536 | K38: ='Annual Data'!F50-'Annual Data'!G50 -> -62077 | AR38: =[2]Contributions!B326 -> 45627 | AS38: =[2]Contributions!C326 -> 0.43064023 | AT38: =[2]Contributions!D326 -> -0.14811417 | AU38: =[2]Contributions!E326 -> -0.27647837 | AV38: =AW38-AS38-AT38-AU38 -> 2.4969393 | AW38: =[2]Contributions!G326 -> 2.5029869 | AX38: 2
A39: 2017 | B39: =100*(('Annual Data'!C51-'Annual Data'!C50)/'Annual Data'!$B50) -> 1.2208039 | C39: =100*((I39-I38)/'Annual Data'!$B50) -> 0.47363656 | D39: =100*((J39-J38)/'Annual Data'!$B50) -> 0.44122338 | E39: =100*((K39-K38)/'Annual Data'!$B50) -> 0.94877886 | F39: =G39-B39-C39-D39-E39 -> -0.061220487 | G39: =100*(('Annual Data'!B51/'Annual Data'!B50)-1) -> 3.0232222 | I39: ='Annual Data'!D51-'Annual Data'!I51 -> 413286 | J39: ='Annual Data'!E51+'Annual Data'!I51 -> 575671 | K39: ='Annual Data'!F51-'Annual Data'!G51 -> -38133 | AR39: =[2]Contributions!B327 -> 45658 | AS39: =[2]Contributions!C327 -> 0.55997145 | AT39: =[2]Contributions!D327 -> -0.070329915 | AU39: =[2]Contributions!E327 -> -0.38432663 | AV39: =AW39-AS39-AT39-AU39 -> 2.8776256 | AW39: =[2]Contributions!G327 -> 2.9829405 | AX39: 2
A40: 2018 | B40: =100*(('Annual Data'!C52-'Annual Data'!C51)/'Annual Data'!$B51) -> 1.0584005 | C40: =100*((I40-I39)/'Annual Data'!$B51) -> -0.017884884 | D40: =100*((J40-J39)/'Annual Data'!$B51) -> 0.10430926 | E40: =100*((K40-K39)/'Annual Data'!$B51) -> 0.081501223 | F40: =G40-B40-C40-D40-E40 -> 0.32500488 | G40: =100*(('Annual Data'!B52/'Annual Data'!B51)-1) -> 1.551331 | I40: ='Annual Data'!D52-'Annual Data'!I52 -> 412821 | J40: ='Annual Data'!E52+'Annual Data'!I52 -> 578383 | K40: ='Annual Data'!F52-'Annual Data'!G52 -> -36014 | AR40: =[2]Contributions!B328 -> 45689 | AS40: =[2]Contributions!C328 -> 0.59227492 | AT40: =[2]Contributions!D328 -> -0.081385013 | AU40: =[2]Contributions!E328 -> -0.40839064 | AV40: =AW40-AS40-AT40-AU40 -> 2.7336884 | AW40: =[2]Contributions!G328 -> 2.8361877 | AX40: 2
A41: 2019 | B41: =100*(('Annual Data'!C53-'Annual Data'!C52)/'Annual Data'!$B52) -> 0.73559962 | C41: =100*((I41-I40)/'Annual Data'!$B52) -> 0.2467906 | D41: =100*((J41-J40)/'Annual Data'!$B52) -> 0.65526769 | E41: =100*((K41-K40)/'Annual Data'!$B52) -> -0.42002882 | F41: =G41-B41-C41-D41-E41 -> 0.038669921 | G41: =100*(('Annual Data'!B53/'Annual Data'!B52)-1) -> 1.256299 | I41: ='Annual Data'!D53-'Annual Data'!I53 -> 419337 | J41: ='Annual Data'!E53+'Annual Data'!I53 -> 595684 | K41: ='Annual Data'!F53-'Annual Data'!G53 -> -47104 | AR41: =[2]Contributions!B329 -> 45717 | AS41: =[2]Contributions!C329 -> 0.54635618 | AT41: =[2]Contributions!D329 -> -0.16916156 | AU41: =[2]Contributions!E329 -> -0.40761112 | AV41: =AW41-AS41-AT41-AU41 -> 2.6245682 | AW41: =[2]Contributions!G329 -> 2.5941517 | AX41: 2
A42: 2020 | B42: =100*(('Annual Data'!C54-'Annual Data'!C53)/'Annual Data'!$B53) -> -7.8336915 | C42: =100*((I42-I41)/'Annual Data'!$B53) -> -1.9438818 | D42: =100*((J42-J41)/'Annual Data'!$B53) -> -1.0418689 | E42: =100*((K42-K41)/'Annual Data'!$B53) -> 1.2897494 | F42: =G42-B42-C42-D42-E42 -> -0.5182039 | G42: =100*(('Annual Data'!B54/'Annual Data'!B53)-1) -> -10.047897 | I42: ='Annual Data'!D54-'Annual Data'!I54 -> 367368 | J42: ='Annual Data'!E54+'Annual Data'!I54 -> 567830 | K42: ='Annual Data'!F54-'Annual Data'!G54 -> -12623 | AR42: =[2]Contributions!B330 -> 45748 | AS42: =[2]Contributions!C330 -> 0.60350951 | AT42: =[2]Contributions!D330 -> -0.29529559 | AU42: =[2]Contributions!E330 -> 0.22712404 | AV42: =AW42-AS42-AT42-AU42 -> 2.9919936 | AW42: =[2]Contributions!G330 -> 3.5273316 | AX42: 2
A43: 2021 | B43: =100*(('Annual Data'!C55-'Annual Data'!C54)/'Annual Data'!$B54) -> 4.1916337 | C43: =100*((I43-I42)/'Annual Data'!$B54) -> 1.4791017 | D43: =100*((J43-J42)/'Annual Data'!$B54) -> 2.8851008 | E43: =100*((K43-K42)/'Annual Data'!$B54) -> -0.78978293 | F43: =G43-B43-C43-D43-E43 -> 0.77705858 | G43: =100*(('Annual Data'!B55/'Annual Data'!B54)-1) -> 8.5431118 | I43: ='Annual Data'!D55-'Annual Data'!I55 -> 402938 | J43: ='Annual Data'!E55+'Annual Data'!I55 -> 637212 | K43: ='Annual Data'!F55-'Annual Data'!G55 -> -31616 | AR43: =[2]Contributions!B331 -> 45778 | AS43: =[2]Contributions!C331 -> 0.7008172 | AT43: =[2]Contributions!D331 -> -0.34389686 | AU43: =[2]Contributions!E331 -> 0.22859944 | AV43: =AW43-AS43-AT43-AU43 -> 2.7724301 | AW43: =[2]Contributions!G331 -> 3.3579498 | AX43: 2
A44: 2022 | B44: =100*(('Annual Data'!C56-'Annual Data'!C55)/'Annual Data'!$B55) -> 4.4279822 | C44: =100*((I44-I43)/'Annual Data'!$B55) -> 1.1625163 | D44: =100*((J44-J43)/'Annual Data'!$B55) -> 0.11335923 | E44: =100*((K44-K43)/'Annual Data'!$B55) -> 0.22009083 | F44: =G44-B44-C44-D44-E44 -> -0.77424466 | G44: =100*(('Annual Data'!B56/'Annual Data'!B55)-1) -> 5.1497039 | I44: ='Annual Data'!D56-'Annual Data'!I56 -> 433283 | J44: ='Annual Data'!E56+'Annual Data'!I56 -> 640171 | K44: ='Annual Data'!F56-'Annual Data'!G56 -> -25871 | AR44: =[2]Contributions!B332 -> 45809 | AS44: =[2]Contributions!C332 -> 0.74996165 | AT44: =[2]Contributions!D332 -> -0.27686223 | AU44: =[2]Contributions!E332 -> 0.23127766 | AV44: =AW44-AS44-AT44-AU44 -> 2.8721128 | AW44: =[2]Contributions!G332 -> 3.5764899 | AX44: 2
A45: 2023 | B45: =100*(('Annual Data'!C57-'Annual Data'!C56)/'Annual Data'!$B56) -> -0.19444691 | C45: =100*((I45-I44)/'Annual Data'!$B56) -> -0.051918091 | D45: =100*((J45-J44)/'Annual Data'!$B56) -> 0.56220917 | E45: =100*((K45-K44)/'Annual Data'!$B56) -> -0.2284396 | F45: =G45-B45-C45-D45-E45 -> 0.18424546 | G45: =100*(('Annual Data'!B57/'Annual Data'!B56)-1) -> 0.27165003 | I45: ='Annual Data'!D57-'Annual Data'!I57 -> 431858 | J45: ='Annual Data'!E57+'Annual Data'!I57 -> 655602 | K45: ='Annual Data'!F57-'Annual Data'!G57 -> -32141 | AR45: =[2]Contributions!B333 -> 45839 | AS45: =[2]Contributions!C333 -> 0.77005926 | AT45: =[2]Contributions!D333 -> -0.20455678 | AU45: =[2]Contributions!E333 -> 0.3024595 | AV45: =AW45-AS45-AT45-AU45 -> 2.9615232 | AW45: =[2]Contributions!G333 -> 3.8294852 | AX45: 2
A46: 2024 | B46: =100*(('Annual Data'!C58-'Annual Data'!C57)/'Annual Data'!$B57) -> -0.10726105 | C46: =100*((I46-I45)/'Annual Data'!$B57) -> 0.19875269 | D46: =100*((J46-J45)/'Annual Data'!$B57) -> 0.82436948 | E46: =100*((K46-K45)/'Annual Data'!$B57) -> -0.65879068 | F46: =G46-B46-C46-D46-E46 -> 0.86608211 | G46: =100*(('Annual Data'!B58/'Annual Data'!B57)-1) -> 1.1231525 | I46: ='Annual Data'!D58-'Annual Data'!I58 -> 437328 | J46: ='Annual Data'!E58+'Annual Data'!I58 -> 678290 | K46: ='Annual Data'!F58-'Annual Data'!G58 -> -50272 | AR46: =[2]Contributions!B334 -> 45870 | AS46: =[2]Contributions!C334 -> 0.79683505 | AT46: =[2]Contributions!D334 -> -0.14601686 | AU46: =[2]Contributions!E334 -> 0.30675271 | AV46: =AW46-AS46-AT46-AU46 -> 2.8306859 | AW46: =[2]Contributions!G334 -> 3.7882569 | AX46: 2
... A48: 2026 | B48: =100*(('Annual Data'!C60-'Annual Data'!C59)/'Annual Data'!$B59) -> 0.59504155 | C48: =100*((I48-I47)/'Annual Data'!$B59) -> -0.056271943 | D48: =100*((J48-J47)/'Annual Data'!$B59) -> 0.6611522 | E48: =100*((K48-K47)/'Annual Data'!$B59) -> 0.029997956 | F48: =G48-B48-C48-D48-E48 -> -0.26848649 | G48: =100*(('Annual Data'!B60/'Annual Data'!B59)-1) -> 0.96143326 | I48: ='Annual Data'!D60-'Annual Data'!I60 -> 448662.43 | J48: ='Annual Data'!E60+'Annual Data'!I60 -> 711614.57 | K48: ='Annual Data'!F60-'Annual Data'!G60 -> -58069.6 | AR48: =[2]Contributions!B336 -> 45931 | AS48: =[2]Contributions!C336 -> 0.77052282 | AT48: =[2]Contributions!D336 -> 0.041778546 | AU48: =[2]Contributions!E336 -> 0.07667325 | AV48: =AW48-AS48-AT48-AU48 -> 2.6698892 | AW48: =[2]Contributions!G336 -> 3.5588638 | AX48: 2
AR49: =[2]Contributions!B337 -> 45962 | AS49: =[2]Contributions!C337 -> 0.7340826 | AT49: =[2]Contributions!D337 -> 0.034951373 | AU49: =[2]Contributions!E337 -> 0.079394233 | AV49: =AW49-AS49-AT49-AU49 -> 2.7627481 | AW49: =[2]Contributions!G337 -> 3.6111763 | AX49: 2
AR50: =[2]Contributions!B338 -> 45992 | AS50: =[2]Contributions!C338 -> 0.75387307 | AT50: =[2]Contributions!D338 -> -0.005379126 | AU50: =[2]Contributions!E338 -> 0.075650138 | AV50: =AW50-AS50-AT50-AU50 -> 2.9418441 | AW50: =[2]Contributions!G338 -> 3.7659882 | AX50: 2
AR51: =[2]Contributions!B339 -> 46023 | AS51: =[2]Contributions!C339 -> 0.66624035 | AT51: =[2]Contributions!D339 -> -0.034940554 | AU51: =[2]Contributions!E339 -> 0.033450141 | AV51: =AW51-AS51-AT51-AU51 -> 2.8359892 | AW51: =[2]Contributions!G339 -> 3.5007391 | AX51: 2
AR52: =[2]Contributions!B340 -> 46054 | AS52: =[2]Contributions!C340 -> 0.67156357 | AT52: =[2]Contributions!D340 -> -0.090549041 | AU52: =[2]Contributions!E340 -> 0.033598888 | AV52: =AW52-AS52-AT52-AU52 -> 2.814147 | AW52: =[2]Contributions!G340 -> 3.4287604 | AX52: 2
AR53: =[2]Contributions!B341 -> 46082 | AS53: =[2]Contributions!C341 -> 0.65741666 | AT53: =[2]Contributions!D341 -> -0.074124578 | AU53: =[2]Contributions!E341 -> 0.040964904 | AV53: =AW53-AS53-AT53-AU53 -> 2.7110742 | AW53: =[2]Contributions!G341 -> 3.3353312 | AX53: 2
AR54: =[2]Contributions!B342 -> 46113 | AS54: =[2]Contributions!C342 -> 0.61295707 | AT54: =[2]Contributions!D342 -> -0.024905558 | AU54: =[2]Contributions!E342 -> -0.29639063 | AV54: =AW54-AS54-AT54-AU54 -> 2.1173068 | AW54: =[2]Contributions!G342 -> 2.4089677 | AX54: 2
AR55: =[2]Contributions!B343 -> 46143 | AS55: =[2]Contributions!C343 -> 0.56722136 | AT55: =[2]Contributions!D343 -> 0.0090234007 | AU55: =[2]Contributions!E343 -> -0.292287 | AV55: =AW55-AS55-AT55-AU55 -> 2.2233825 | AW55: =[2]Contributions!G343 -> 2.5073403 | AX55: 2
AR56: =[2]Contributions!B344 -> 46174 | AS56: =[2]Contributions!C344 -> 0.51353164 | AT56: =[2]Contributions!D344 -> 0.0091960939 | AU56: =[2]Contributions!E344 -> -0.28917116 | AV56: =AW56-AS56-AT56-AU56 -> 2.1009675 | AW56: =[2]Contributions!G344 -> 2.334524 | AX56: 2
AR57: =[2]Contributions!B345 -> 46204 | AS57: =[2]Contributions!C345 -> 0.4854481 | AT57: =[2]Contributions!D345 -> -0.04439221 | AU57: =[2]Contributions!E345 -> -0.13418245 | AV57: =AW57-AS57-AT57-AU57 -> 2.070322 | AW57: =[2]Contributions!G345 -> 2.3771954 | AX57: 2
AR58: =[2]Contributions!B346 -> 46235 | AS58: =[2]Contributions!C346 -> 0.46802164 | AT58: =[2]Contributions!D346 -> -0.06373956 | AU58: =[2]Contributions!E346 -> -0.13235791 | AV58: =AW58-AS58-AT58-AU58 -> 2.235645 | AW58: =[2]Contributions!G346 -> 2.5075691 | AX58: 2
AR59: =[2]Contributions!B347 -> 46266 | AS59: =[2]Contributions!C347 -> 0.50470755 | AT59: =[2]Contributions!D347 -> -0.042193702 | AU59: =[2]Contributions!E347 -> -0.12974567 | AV59: =AW59-AS59-AT59-AU59 -> 2.3222325 | AW59: =[2]Contributions!G347 -> 2.6550007 | AX59: 2
AR60: =[2]Contributions!B348 -> 46296 | AS60: =[2]Contributions!C348 -> 0.45781506 | AT60: =[2]Contributions!D348 -> -0.06748126 | AU60: =[2]Contributions!E348 -> -0.1976456 | AV60: =AW60-AS60-AT60-AU60 -> 2.2835748 | AW60: =[2]Contributions!G348 -> 2.476263 | AX60: 2
... AR62: =[2]Contributions!B350 -> 46357 | AS62: =[2]Contributions!C350 -> 0.44143756 | AT62: =[2]Contributions!D350 -> -0.094652088 | AU62: =[2]Contributions!E350 -> -0.19643961 | AV62: =AW62-AS62-AT62-AU62 -> 2.2959737 | AW62: =[2]Contributions!G350 -> 2.4463195 | AX62: 2
AR64: 2025 | AS64: =AVERAGE(AS39:AS50) -> 0.69228355 | AT64: =AVERAGE(AT39:AT50) -> -0.12911062 | AU64: =AVERAGE(AU39:AU50) -> 0.05292504 | AV64: =AVERAGE(AV39:AV50) -> 2.8181985 | AW64: =AVERAGE(AW39:AW50) -> 3.4342965
AR65: 2026 | AS65: =AVERAGE(AS51:AS62) -> 0.54162578 | AT65: =AVERAGE(AT51:AT62) -> -0.050754434 | AU65: =AVERAGE(AU51:AU62) -> -0.14645275 | AV65: =AVERAGE(AV51:AV62) -> 2.3575668 | AW65: =AVERAGE(AW51:AW62) -> 2.7019854
AS66: =AS65-AS64 -> -0.15065777 | AT66: =AT65-AT64 -> 0.078356182 | AU66: =AU65-AU64 -> -0.19937779 | AV66: =AV65-AV64 -> -0.4606317 | AW66: =AW65-AW64 -> -0.73231108

Sheet Annual Data
B1: ='Quarterly Data'!G1 -> DEC003B | C1: ='Quarterly Data'!H1 -> DEC003B | D1: ='Quarterly Data'!I1 -> DEC003B | E1: ='Quarterly Data'!J1 -> DEC003B | F1: ='Quarterly Data'!K1 -> DEC003B | G1: ='Quarterly Data'!L1 -> DEC003B | H1: ='Quarterly Data'!M1 -> DEC003B | I1: ='Quarterly Data'!N1 -> DEC003B | ... CX1: ='Quarterly Data'!DC1 -> DEC003B
B2: ='Quarterly Data'!G2 -> UK | C2: ='Quarterly Data'!H2 -> UK | D2: ='Quarterly Data'!I2 -> UK | E2: ='Quarterly Data'!J2 -> UK | F2: ='Quarterly Data'!K2 -> UK | G2: ='Quarterly Data'!L2 -> UK | H2: ='Quarterly Data'!M2 -> UK | I2: ='Quarterly Data'!N2 -> UK | ... CX2: ='Quarterly Data'!DC2 -> Portugal
B3: ='Quarterly Data'!G3 -> GDP | C3: ='Quarterly Data'!H3 -> C | D3: ='Quarterly Data'!I3 -> IF | E3: ='Quarterly Data'!J3 -> GC | F3: ='Quarterly Data'!K3 -> X | G3: ='Quarterly Data'!L3 -> M | H3: ='Quarterly Data'!M3 -> IPNR | I3: ='Quarterly Data'!N3 -> GI | ... CX3: ='Quarterly Data'!DC3 -> GDP!
B4: ='Quarterly Data'!G4 -> GBR | C4: ='Quarterly Data'!H4 -> GBR | D4: ='Quarterly Data'!I4 -> GBR | E4: ='Quarterly Data'!J4 -> GBR | F4: ='Quarterly Data'!K4 -> GBR | G4: ='Quarterly Data'!L4 -> GBR | H4: ='Quarterly Data'!M4 -> GBR | I4: ='Quarterly Data'!N4 -> GBR | ... CX4: ='Quarterly Data'!DC4 -> PRT
B5: ='Quarterly Data'!G5 -> L | C5: ='Quarterly Data'!H5 -> L | D5: ='Quarterly Data'!I5 -> L | E5: ='Quarterly Data'!J5 -> L | F5: ='Quarterly Data'!K5 -> L | G5: ='Quarterly Data'!L5 -> L | H5: ='Quarterly Data'!M5 -> L | I5: ='Quarterly Data'!N5 -> L | ... CX5: ='Quarterly Data'!DC5 -> L
B6: ='Quarterly Data'!G6 -> 202503 | C6: ='Quarterly Data'!H6 -> 202503 | D6: ='Quarterly Data'!I6 -> 202503 | E6: ='Quarterly Data'!J6 -> 202503 | F6: ='Quarterly Data'!K6 -> 202503 | G6: ='Quarterly Data'!L6 -> 202503 | H6: ='Quarterly Data'!M6 -> 202503 | I6: ='Quarterly Data'!N6 -> 202503 | ... CX6: ='Quarterly Data'!DC6 -> 202503
A7: 1973 | B7: =SUMIF('Quarterly Data'!$B:$B,'Annual Data'!$A7,'Quarterly Data'!G:G) -> 1063550 | C7: =SUMIF('Quarterly Data'!$B:$B,'Annual Data'!$A7,'Quarterly Data'!H:H) -> 551375 | D7: =SUMIF('Quarterly Data'!$B:$B,'Annual Data'!$A7,'Quarterly Data'!I:I) -> 197099 | E7: =SUMIF('Quarterly Data'!$B:$B,'Annual Data'!$A7,'Quarterly Data'!J:J) -> 256299 | F7: =SUMIF('Quarterly Data'!$B:$B,'Annual Data'!$A7,'Quarterly Data'!K:K) -> 155631 | G7: =SUMIF('Quarterly Data'!$B:$B,'Annual Data'!$A7,'Quarterly Data'!L:L) -> 145946 | H7: =SUMIF('Quarterly Data'!$B:$B,'Annual Data'!$A7,'Quarterly Data'!M:M) -> 68404.22 | I7: =SUMIF('Quarterly Data'!$B:$B,'Annual Data'!$A7,'Quarterly Data'!N:N) -> 27306.99 | J7: =AVERAGEIF('Quarterly Data'!$B:$B,'Annual Data'!$A7,'Quarterly Data'!O:O) -> 12.428425 | K7: =SUMIF('Quarterly Data'!$E:$E,'Annual Data'!$A7,'Quarterly Data'!P:P) -> 13 | L7: =SUMIF('Quarterly Data'!$E:$E,'Annual Data'!$A7,'Quarterly Data'!Q:Q) -> 0.001 | M7: =AVERAGEIF('Quarterly Data'!$B:$B,'Annual Data'!$A7,'Quarterly Data'!R:R) -> 12.428425 | N7: =AVERAGEIF('Quarterly Data'!$B:$B,'Annual Data'!$A7,'Quarterly Data'!S:S) -> 27049 | O7: =AVERAGEIF('Quarterly Data'!$B:$B,'Annual Data'!$A7,'Quarterly Data'!T:T) -> 0.001 | P7: =AVERAGEIF('Quarterly Data'!$B:$B,'Annual Data'!$A7,'Quarterly Data'!U:U) -> 0.001 | Q7: =AVERAGEIF('Quarterly Data'!$B:$B,'Annual Data'!$A7,'Quarterly Data'!V:V) -> 0.001 | R7: =AVERAGEIF('Quarterly Data'!$B:$B,'Annual Data'!$A7,'Quarterly Data'!W:W) -> 0.001 | S7: =AVERAGEIF('Quarterly Data'!$B:$B,'Annual Data'!$A7,'Quarterly Data'!X:X) -> 0.001 | T7: =AVERAGEIF('Quarterly Data'!$B:$B,'Annual Data'!$A7,'Quarterly Data'!Y:Y) -> 0.001 | U7: =AVERAGEIF('Quarterly Data'!$B:$B,'Annual Data'!$A7,'Quarterly Data'!Z:Z) -> 0.001 | V7: =AVERAGEIF('Quarterly Data'!$B:$B,'Annual Data'!$A7,'Quarterly Data'!AA:AA) -> 0.001 | W7: =AVERAGEIF('Quarterly Data'!$B:$B,'Annual Data'!$A7,'Quarterly Data'!AB:AB) -> 0.001 | X7: =AVERAGEIF('Quarterly Data'!$B:$B,'Annual Data'!$A7,'Quarterly Data'!AC:AC) -> 0.001 | Y7: =AVERAGEIF('Quarterly Data'!$B:$B,'Annual Data'!$A7,'Quarterly Data'!AD:AD) -> 0.001 | Z7: =AVERAGEIF('Quarterly Data'!$B:$B,'Annual Data'!$A7,'Quarterly Data'!AE:AE) -> 0.001 | AA7: =AVERAGEIF('Quarterly Data'!$B:$B,'Annual Data'!$A7,'Quarterly Data'!AF:AF) -> 0.001 | AB7: =AVERAGEIF('Quarterly Data'!$B:$B,'Annual Data'!$A7,'Quarterly Data'!AG:AG) -> 0.001 | AC7: =AVERAGEIF('Quarterly Data'!$B:$B,'Annual Data'!$A7,'Quarterly Data'!AH:AH) -> 0.001 | AD7: =AVERAGEIF('Quarterly Data'!$B:$B,'Annual Data'!$A7,'Quarterly Data'!AI:AI) -> 0.001 | AE7: =AVERAGEIF('Quarterly Data'!$B:$B,'Annual Data'!$A7,'Quarterly Data'!AJ:AJ) -> 0.001 | AF7: =AVERAGEIF('Quarterly Data'!$B:$B,'Annual Data'!$A7,'Quarterly Data'!AK:AK) -> 0.001 | AG7: =AVERAGEIF('Quarterly Data'!$B:$B,'Annual Data'!$A7,'Quarterly Data'!AL:AL) -> 0.001 | AH7: =AVERAGEIF('Quarterly Data'!$B:$B,'Annual Data'!$A7,'Quarterly Data'!AM:AM) -> 24965 | AI7: =AVERAGEIF('Quarterly Data'!$B:$B,'Annual Data'!$A7,'Quarterly Data'!AN:AN) -> 4943.299 | AJ7: =SUMIF('Quarterly Data'!$B:$B,'Annual Data'!$A7,'Quarterly Data'!AO:AO) -> 1063550 | AK7: =SUMIF('Quarterly Data'!$B:$B,'Annual Data'!$A7,'Quarterly Data'!AP:AP) -> 6106.35 | AL7: =SUMIF('Quarterly Data'!$B:$B,'Annual Data'!$A7,'Quarterly Data'!AQ:AQ) -> 211380.51 | AM7: =SUMIF('Quarterly Data'!$B:$B,'Annual Data'!$A7,'Quarterly Data'!AR:AR) -> 1556.14 | AN7: =SUMIF('Quarterly Data'!$B:$B,'Annual Data'!$A7,'Quarterly Data'!AS:AS) -> 999.15 | AO7: =SUMIF('Quarterly Data'!$B:$B,'Annual Data'!$A7,'Quarterly Data'!AT:AT) -> 932.5699 | AP7: =SUMIF('Quarterly Data'!$B:$B,'Annual Data'!$A7,'Quarterly Data'!AU:AU) -> 707164.6 | AQ7: =SUMIF('Quarterly Data'!$B:$B,'Annual Data'!$A7,'Quarterly Data'!AV:AV) -> 3087 | AR7: =SUMIF('Quarterly Data'!$B:$B,'Annual Data'!$A7,'Quarterly Data'!AW:AW) -> 61.95 | AS7: =SUMIF('Quarterly Data'!$B:$B,'Annual Data'!$A7,'Quarterly Data'!AX:AX) -> 922.9716 | AT7: =SUMIF('Quarterly Data'!$B:$B,'Annual Data'!$A7,'Quarterly Data'!AY:AY) -> 4910 | AU7: =SUMIF('Quarterly Data'!$B:$B,'Annual Data'!$A7,'Quarterly Data'!AZ:AZ) -> 738.1701 | AV7: =SUMIF('Quarterly Data'!$B:$B,'Annual Data'!$A7,'Quarterly Data'!BA:BA) -> 1.9869172 | AW7: =SUMIF('Quarterly Data'!$B:$B,'Annual Data'!$A7,'Quarterly Data'!BB:BB) -> 3553.0365 | AX7: =SUMIF('Quarterly Data'!$B:$B,'Annual Data'!$A7,'Quarterly Data'!BC:BC) -> 1.9153085 | AY7: =SUMIF('Quarterly Data'!$B:$B,'Annual Data'!$A7,'Quarterly Data'!BD:BD) -> 0.004 | AZ7: =SUMIF('Quarterly Data'!$B:$B,'Annual Data'!$A7,'Quarterly Data'!BE:BE) -> 5.47 | BA7: =SUMIF('Quarterly Data'!$B:$B,'Annual Data'!$A7,'Quarterly Data'!BF:BF) -> 1.054 | BB7: =SUMIF('Quarterly Data'!$B:$B,'Annual Data'!$A7,'Quarterly Data'!BG:BG) -> 0.9538121 | BC7: =SUMIF('Quarterly Data'!$B:$B,'Annual Data'!$A7,'Quarterly Data'!BH:BH) -> 0.53253765 | BD7: =SUMIF('Quarterly Data'!$B:$B,'Annual Data'!$A7,'Quarterly Data'!BI:BI) -> 2.3333999 | BE7: =SUMIF('Quarterly Data'!$B:$B,'Annual Data'!$A7,'Quarterly Data'!BJ:BJ) -> 1.5787534 | BF7: =SUMIF('Quarterly Data'!$B:$B,'Annual Data'!$A7,'Quarterly Data'!BK:BK) -> 0.32929355 | BG7: =SUMIF('Quarterly Data'!$B:$B,'Annual Data'!$A7,'Quarterly Data'!BL:BL) -> 0.08021 | BH7: =SUMIF('Quarterly Data'!$B:$B,'Annual Data'!$A7,'Quarterly Data'!BM:BM) -> 0.12189001 | BI7: =SUMIF('Quarterly Data'!$B:$B,'Annual Data'!$A7,'Quarterly Data'!BN:BN) -> -0.00015918688 | BJ7: =SUMIF('Quarterly Data'!$B:$B,'Annual Data'!$A7,'Quarterly Data'!BO:BO) -> 0.004 | BK7: =AVERAGEIF('Quarterly Data'!$B:$B,'Annual Data'!$A7,'Quarterly Data'!BP:BP) -> 32464.552 | BL7: =AVERAGEIF('Quarterly Data'!$B:$B,'Annual Data'!$A7,'Quarterly Data'!BQ:BQ) -> 1135.7315 | BM7: =AVERAGEIF('Quarterly Data'!$B:$B,'Annual Data'!$A7,'Quarterly Data'!BR:BR) -> 16774 | BN7: =AVERAGEIF('Quarterly Data'!$B:$B,'Annual Data'!$A7,'Quarterly Data'!BS:BS) -> 63700 | BO7: =AVERAGEIF('Quarterly Data'!$B:$B,'Annual Data'!$A7,'Quarterly Data'!BT:BT) -> 0.001 | BP7: =AVERAGEIF('Quarterly Data'!$B:$B,'Annual Data'!$A7,'Quarterly Data'!BU:BU) -> 167 | BQ7: =AVERAGEIF('Quarterly Data'!$B:$B,'Annual Data'!$A7,'Quarterly Data'!BV:BV) -> 66450.688 | BR7: =AVERAGEIF('Quarterly Data'!$B:$B,'Annual Data'!$A7,'Quarterly Data'!BW:BW) -> 99.3709 | BS7: =AVERAGEIF('Quarterly Data'!$B:$B,'Annual Data'!$A7,'Quarterly Data'!BX:BX) -> 1193.4997 | BT7: =AVERAGEIF('Quarterly Data'!$B:$B,'Annual Data'!$A7,'Quarterly Data'!BY:BY) -> 85.12329 | BU7: =AVERAGEIF('Quarterly Data'!$B:$B,'Annual Data'!$A7,'Quarterly Data'!BZ:BZ) -> 55.416967 | BV7: =AVERAGEIF('Quarterly Data'!$B:$B,'Annual Data'!$A7,'Quarterly Data'!CA:CA) -> 32.800415 | BW7: =AVERAGEIF('Quarterly Data'!$B:$B,'Annual Data'!$A7,'Quarterly Data'!CB:CB) -> 0.001 | BX7: =AVERAGEIF('Quarterly Data'!$B:$B,'Annual Data'!$A7,'Quarterly Data'!CC:CC) -> 47.450867 | BY7: =AVERAGEIF('Quarterly Data'!$B:$B,'Annual Data'!$A7,'Quarterly Data'!CD:CD) -> 20.499335 | BZ7: =AVERAGEIF('Quarterly Data'!$B:$B,'Annual Data'!$A7,'Quarterly Data'!CE:CE) -> 9.1194122 | CA7: =AVERAGEIF('Quarterly Data'!$B:$B,'Annual Data'!$A7,'Quarterly Data'!CF:CF) -> 0.001 | CB7: =AVERAGEIF('Quarterly Data'!$B:$B,'Annual Data'!$A7,'Quarterly Data'!CG:CG) -> 0.001 | CC7: =AVERAGEIF('Quarterly Data'!$B:$B,'Annual Data'!$A7,'Quarterly Data'!CH:CH) -> 0.32980747 | CD7: =AVERAGEIF('Quarterly Data'!$B:$B,'Annual Data'!$A7,'Quarterly Data'!CI:CI) -> 0.33631423 | CE7: =SUMIF('Quarterly Data'!$B:$B,'Annual Data'!$A7,'Quarterly Data'!CJ:CJ) -> 81809 | CF7: =SUMIF('Quarterly Data'!$B:$B,'Annual Data'!$A7,'Quarterly Data'!CK:CK) -> 1425.375 | CG7: =SUMIF('Quarterly Data'!$B:$B,'Annual Data'!$A7,'Quarterly Data'!CL:CL) -> 115345.45 | CH7: =SUMIF('Quarterly Data'!$B:$B,'Annual Data'!$A7,'Quarterly Data'!CM:CM) -> 132966 | CI7: =SUMIF('Quarterly Data'!$B:$B,'Annual Data'!$A7,'Quarterly Data'!CN:CN) -> 54996 | CJ7: =SUMIF('Quarterly Data'!$B:$B,'Annual Data'!$A7,'Quarterly Data'!CO:CO) -> 0.004 | CK7: =SUMIF('Quarterly Data'!$B:$B,'Annual Data'!$A7,'Quarterly Data'!CP:CP) -> 238126.57 | CL7: =SUMIF('Quarterly Data'!$B:$B,'Annual Data'!$A7,'Quarterly Data'!CQ:CQ) -> 153.06247 | CM7: =SUMIF('Quarterly Data'!$B:$B,'Annual Data'!$A7,'Quarterly Data'!CR:CR) -> 5603.5 | CN7: =SUMIF('Quarterly Data'!$B:$B,'Annual Data'!$A7,'Quarterly Data'!CS:CS) -> 553.1868 | CO7: =SUMIF('Quarterly Data'!$B:$B,'Annual Data'!$A7,'Quarterly Data'!CT:CT) -> 177.825 | CP7: =SUMIF('Quarterly Data'!$B:$B,'Annual Data'!$A7,'Quarterly Data'!CU:CU) -> 53.293 | CQ7: =SUMIF('Quarterly Data'!$B:$B,'Annual Data'!$A7,'Quarterly Data'!CV:CV) -> 27.217473 | CR7: =SUMIF('Quarterly Data'!$B:$B,'Annual Data'!$A7,'Quarterly Data'!CW:CW) -> 138.72 | CS7: =SUMIF('Quarterly Data'!$B:$B,'Annual Data'!$A7,'Quarterly Data'!CX:CX) -> 45.52564 | CT7: =SUMIF('Quarterly Data'!$B:$B,'Annual Data'!$A7,'Quarterly Data'!CY:CY) -> 34.690403 | CU7: =SUMIF('Quarterly Data'!$B:$B,'Annual Data'!$A7,'Quarterly Data'!CZ:CZ) -> 13.895841 | CV7: =SUMIF('Quarterly Data'!$B:$B,'Annual Data'!$A7,'Quarterly Data'!DA:DA) -> 3.8767493 | CW7: =SUMIF('Quarterly Data'!$B:$B,'Annual Data'!$A7,'Quarterly Data'!DB:DB) -> 1.9428507 | CX7: =SUMIF('Quarterly Data'!$B:$B,'Annual Data'!$A7,'Quarterly Data'!DC:DC) -> 23.336028
A8: 1974 | B8: =SUMIF('Quarterly Data'!$B:$B,'Annual Data'!$A8,'Quarterly Data'!G:G) -> 1036973 | C8: =SUMIF('Quarterly Data'!$B:$B,'Annual Data'!$A8,'Quarterly Data'!H:H) -> 544335 | D8: =SUMIF('Quarterly Data'!$B:$B,'Annual Data'!$A8,'Quarterly Data'!I:I) -> 182389 | E8: =SUMIF('Quarterly Data'!$B:$B,'Annual Data'!$A8,'Quarterly Data'!J:J) -> 260615 | F8: =SUMIF('Quarterly Data'!$B:$B,'Annual Data'!$A8,'Quarterly Data'!K:K) -> 166915 | G8: =SUMIF('Quarterly Data'!$B:$B,'Annual Data'!$A8,'Quarterly Data'!L:L) -> 147336 | H8: =SUMIF('Quarterly Data'!$B:$B,'Annual Data'!$A8,'Quarterly Data'!M:M) -> 72445.86 | I8: =SUMIF('Quarterly Data'!$B:$B,'Annual Data'!$A8,'Quarterly Data'!N:N) -> 25511.273 | J8: =AVERAGEIF('Quarterly Data'!$B:$B,'Annual Data'!$A8,'Quarterly Data'!O:O) -> 14.383608 | K8: =SUMIF('Quarterly Data'!$E:$E,'Annual Data'!$A8,'Quarterly Data'!P:P) -> 11.5 | L8: =SUMIF('Quarterly Data'!$E:$E,'Annual Data'!$A8,'Quarterly Data'!Q:Q) -> 0.001 | M8: =AVERAGEIF('Quarterly Data'!$B:$B,'Annual Data'!$A8,'Quarterly Data'!R:R) -> 14.383608 | N8: =AVERAGEIF('Quarterly Data'!$B:$B,'Annual Data'!$A8,'Quarterly Data'!S:S) -> 27133.25 | O8: =AVERAGEIF('Quarterly Data'!$B:$B,'Annual Data'!$A8,'Quarterly Data'!T:T) -> 0.001 | P8: =AVERAGEIF('Quarterly Data'!$B:$B,'Annual Data'!$A8,'Quarterly Data'!U:U) -> 0.001 | Q8: =AVERAGEIF('Quarterly Data'!$B:$B,'Annual Data'!$A8,'Quarterly Data'!V:V) -> 0.001 | R8: =AVERAGEIF('Quarterly Data'!$B:$B,'Annual Data'!$A8,'Quarterly Data'!W:W) -> 0.001 | S8: =AVERAGEIF('Quarterly Data'!$B:$B,'Annual Data'!$A8,'Quarterly Data'!X:X) -> 0.001 | T8: =AVERAGEIF('Quarterly Data'!$B:$B,'Annual Data'!$A8,'Quarterly Data'!Y:Y) -> 0.001 | U8: =AVERAGEIF('Quarterly Data'!$B:$B,'Annual Data'!$A8,'Quarterly Data'!Z:Z) -> 0.001 | V8: =AVERAGEIF('Quarterly Data'!$B:$B,'Annual Data'!$A8,'Quarterly Data'!AA:AA) -> 0.001 | W8: =AVERAGEIF('Quarterly Data'!$B:$B,'Annual Data'!$A8,'Quarterly Data'!AB:AB) -> 0.001 | X8: =AVERAGEIF('Quarterly Data'!$B:$B,'Annual Data'!$A8,'Quarterly Data'!AC:AC) -> 0.001 | Y8: =AVERAGEIF('Quarterly Data'!$B:$B,'Annual Data'!$A8,'Quarterly Data'!AD:AD) -> 0.001 | Z8: =AVERAGEIF('Quarterly Data'!$B:$B,'Annual Data'!$A8,'Quarterly Data'!AE:AE) -> 0.001 | AA8: =AVERAGEIF('Quarterly Data'!$B:$B,'Annual Data'!$A8,'Quarterly Data'!AF:AF) -> 0.001 | AB8: =AVERAGEIF('Quarterly Data'!$B:$B,'Annual Data'!$A8,'Quarterly Data'!AG:AG) -> 0.001 | AC8: =AVERAGEIF('Quarterly Data'!$B:$B,'Annual Data'!$A8,'Quarterly Data'!AH:AH) -> 0.001 | AD8: =AVERAGEIF('Quarterly Data'!$B:$B,'Annual Data'!$A8,'Quarterly Data'!AI:AI) -> 0.001 | AE8: =AVERAGEIF('Quarterly Data'!$B:$B,'Annual Data'!$A8,'Quarterly Data'!AJ:AJ) -> 0.001 | AF8: =AVERAGEIF('Quarterly Data'!$B:$B,'Annual Data'!$A8,'Quarterly Data'!AK:AK) -> 0.001 | AG8: =AVERAGEIF('Quarterly Data'!$B:$B,'Annual Data'!$A8,'Quarterly Data'!AL:AL) -> 0.001 | AH8: =AVERAGEIF('Quarterly Data'!$B:$B,'Annual Data'!$A8,'Quarterly Data'!AM:AM) -> 25029.25 | AI8: =AVERAGEIF('Quarterly Data'!$B:$B,'Annual Data'!$A8,'Quarterly Data'!AN:AN) -> 5129.1028 | AJ8: =SUMIF('Quarterly Data'!$B:$B,'Annual Data'!$A8,'Quarterly Data'!AO:AO) -> 1036973 | AK8: =SUMIF('Quarterly Data'!$B:$B,'Annual Data'!$A8,'Quarterly Data'!AP:AP) -> 6073.4 | AL8: =SUMIF('Quarterly Data'!$B:$B,'Annual Data'!$A8,'Quarterly Data'!AQ:AQ) -> 209230.97 | AM8: =SUMIF('Quarterly Data'!$B:$B,'Annual Data'!$A8,'Quarterly Data'!AR:AR) -> 1571.34 | AN8: =SUMIF('Quarterly Data'!$B:$B,'Annual Data'!$A8,'Quarterly Data'!AS:AS) -> 1043.039 | AO8: =SUMIF('Quarterly Data'!$B:$B,'Annual Data'!$A8,'Quarterly Data'!AT:AT) -> 981.7783 | AP8: =SUMIF('Quarterly Data'!$B:$B,'Annual Data'!$A8,'Quarterly Data'!AU:AU) -> 730909.6 | AQ8: =SUMIF('Quarterly Data'!$B:$B,'Annual Data'!$A8,'Quarterly Data'!AV:AV) -> 4131 | AR8: =SUMIF('Quarterly Data'!$B:$B,'Annual Data'!$A8,'Quarterly Data'!AW:AW) -> 69.55 | AS8: =SUMIF('Quarterly Data'!$B:$B,'Annual Data'!$A8,'Quarterly Data'!AX:AX) -> 1196.62 | AT8: =SUMIF('Quarterly Data'!$B:$B,'Annual Data'!$A8,'Quarterly Data'!AY:AY) -> 5488 | AU8: =SUMIF('Quarterly Data'!$B:$B,'Annual Data'!$A8,'Quarterly Data'!AZ:AZ) -> 807 | AV8: =SUMIF('Quarterly Data'!$B:$B,'Annual Data'!$A8,'Quarterly Data'!BA:BA) -> 2.1632707 | AW8: =SUMIF('Quarterly Data'!$B:$B,'Annual Data'!$A8,'Quarterly Data'!BB:BB) -> 4397.595 | AX8: =SUMIF('Quarterly Data'!$B:$B,'Annual Data'!$A8,'Quarterly Data'!BC:BC) -> 2.2639957 | AY8: =SUMIF('Quarterly Data'!$B:$B,'Annual Data'!$A8,'Quarterly Data'!BD:BD) -> 0.004 | AZ8: =SUMIF('Quarterly Data'!$B:$B,'Annual Data'!$A8,'Quarterly Data'!BE:BE) -> 6.6 | BA8: =SUMIF('Quarterly Data'!$B:$B,'Annual Data'!$A8,'Quarterly Data'!BF:BF) -> 1.354 | BB8: =SUMIF('Quarterly Data'!$B:$B,'Annual Data'!$A8,'Quarterly Data'!BG:BG) -> 1.4292356 | BC8: =SUMIF('Quarterly Data'!$B:$B,'Annual Data'!$A8,'Quarterly Data'!BH:BH) -> 0.9415167 | BD8: =SUMIF('Quarterly Data'!$B:$B,'Annual Data'!$A8,'Quarterly Data'!BI:BI) -> 2.845 | BE8: =SUMIF('Quarterly Data'!$B:$B,'Annual Data'!$A8,'Quarterly Data'!BJ:BJ) -> 1.9021206 | BF8: =SUMIF('Quarterly Data'!$B:$B,'Annual Data'!$A8,'Quarterly Data'!BK:BK) -> 0.39653667 | BG8: =SUMIF('Quarterly Data'!$B:$B,'Annual Data'!$A8,'Quarterly Data'!BL:BL) -> 0.08739 | BH8: =SUMIF('Quarterly Data'!$B:$B,'Annual Data'!$A8,'Quarterly Data'!BM:BM) -> 0.14221 | BI8: =SUMIF('Quarterly Data'!$B:$B,'Annual Data'!$A8,'Quarterly Data'!BN:BN) -> 0.0027016863 | BJ8: =SUMIF('Quarterly Data'!$B:$B,'Annual Data'!$A8,'Quarterly Data'!BO:BO) -> 0.004 | BK8: =AVERAGEIF('Quarterly Data'!$B:$B,'Annual Data'!$A8,'Quarterly Data'!BP:BP) -> 42892.497 | BL8: =AVERAGEIF('Quarterly Data'!$B:$B,'Annual Data'!$A8,'Quarterly Data'!BQ:BQ) -> 1212.9317 | BM8: =AVERAGEIF('Quarterly Data'!$B:$B,'Annual Data'!$A8,'Quarterly Data'!BR:BR) -> 17009.5 | BN8: =AVERAGEIF('Quarterly Data'!$B:$B,'Annual Data'!$A8,'Quarterly Data'!BS:BS) -> 70618.5 | BO8: =AVERAGEIF('Quarterly Data'!$B:$B,'Annual Data'!$A8,'Quarterly Data'!BT:BT) -> 0.001 | BP8: =AVERAGEIF('Quarterly Data'!$B:$B,'Annual Data'!$A8,'Quarterly Data'!BU:BU) -> 167 | BQ8: =AVERAGEIF('Quarterly Data'!$B:$B,'Annual Data'!$A8,'Quarterly Data'!BV:BV) -> 74659.448 | BR8: =AVERAGEIF('Quarterly Data'!$B:$B,'Annual Data'!$A8,'Quarterly Data'!BW:BW) -> 102.613 | BS8: =AVERAGEIF('Quarterly Data'!$B:$B,'Annual Data'!$A8,'Quarterly Data'!BX:BX) -> 1704.7795 | BT8: =AVERAGEIF('Quarterly Data'!$B:$B,'Annual Data'!$A8,'Quarterly Data'!BY:BY) -> 95.906725 | BU8: =AVERAGEIF('Quarterly Data'!$B:$B,'Annual Data'!$A8,'Quarterly Data'!BZ:BZ) -> 59.972025 | BV8: =AVERAGEIF('Quarterly Data'!$B:$B,'Annual Data'!$A8,'Quarterly Data'!CA:CA) -> 42.277125 | BW8: =AVERAGEIF('Quarterly Data'!$B:$B,'Annual Data'!$A8,'Quarterly Data'!CB:CB) -> 0.001 | BX8: =AVERAGEIF('Quarterly Data'!$B:$B,'Annual Data'!$A8,'Quarterly Data'!CC:CC) -> 50.69699 | BY8: =AVERAGEIF('Quarterly Data'!$B:$B,'Annual Data'!$A8,'Quarterly Data'!CD:CD) -> 34.658835 | BZ8: =AVERAGEIF('Quarterly Data'!$B:$B,'Annual Data'!$A8,'Quarterly Data'!CE:CE) -> 10.41547 | CA8: =AVERAGEIF('Quarterly Data'!$B:$B,'Annual Data'!$A8,'Quarterly Data'!CF:CF) -> 0.001 | CB8: =AVERAGEIF('Quarterly Data'!$B:$B,'Annual Data'!$A8,'Quarterly Data'!CG:CG) -> 0.001 | CC8: =AVERAGEIF('Quarterly Data'!$B:$B,'Annual Data'!$A8,'Quarterly Data'!CH:CH) -> 0.39994603 | CD8: =AVERAGEIF('Quarterly Data'!$B:$B,'Annual Data'!$A8,'Quarterly Data'!CI:CI) -> 0.38959338 | CE8: =SUMIF('Quarterly Data'!$B:$B,'Annual Data'!$A8,'Quarterly Data'!CJ:CJ) -> 92686 | CF8: =SUMIF('Quarterly Data'!$B:$B,'Annual Data'!$A8,'Quarterly Data'!CK:CK) -> 1545.25 | CG8: =SUMIF('Quarterly Data'!$B:$B,'Annual Data'!$A8,'Quarterly Data'!CL:CL) -> 137675.47 | CH8: =SUMIF('Quarterly Data'!$B:$B,'Annual Data'!$A8,'Quarterly Data'!CM:CM) -> 158176 | CI8: =SUMIF('Quarterly Data'!$B:$B,'Annual Data'!$A8,'Quarterly Data'!CN:CN) -> 65666 | CJ8: =SUMIF('Quarterly Data'!$B:$B,'Annual Data'!$A8,'Quarterly Data'!CO:CO) -> 0.004 | CK8: =SUMIF('Quarterly Data'!$B:$B,'Annual Data'!$A8,'Quarterly Data'!CP:CP) -> 268984.64 | CL8: =SUMIF('Quarterly Data'!$B:$B,'Annual Data'!$A8,'Quarterly Data'!CQ:CQ) -> 166.05505 | CM8: =SUMIF('Quarterly Data'!$B:$B,'Annual Data'!$A8,'Quarterly Data'!CR:CR) -> 8033.2 | CN8: =SUMIF('Quarterly Data'!$B:$B,'Annual Data'!$A8,'Quarterly Data'!CS:CS) -> 599.3288 | CO8: =SUMIF('Quarterly Data'!$B:$B,'Annual Data'!$A8,'Quarterly Data'!CT:CT) -> 207.305 | CP8: =SUMIF('Quarterly Data'!$B:$B,'Annual Data'!$A8,'Quarterly Data'!CU:CU) -> 67.409 | CQ8: =SUMIF('Quarterly Data'!$B:$B,'Annual Data'!$A8,'Quarterly Data'!CV:CV) -> 33.33162 | CR8: =SUMIF('Quarterly Data'!$B:$B,'Annual Data'!$A8,'Quarterly Data'!CW:CW) -> 138.72 | CS8: =SUMIF('Quarterly Data'!$B:$B,'Annual Data'!$A8,'Quarterly Data'!CX:CX) -> 53.37438 | CT8: =SUMIF('Quarterly Data'!$B:$B,'Annual Data'!$A8,'Quarterly Data'!CY:CY) -> 38.609374 | CU8: =SUMIF('Quarterly Data'!$B:$B,'Annual Data'!$A8,'Quarterly Data'!CZ:CZ) -> 17.537828 | CV8: =SUMIF('Quarterly Data'!$B:$B,'Annual Data'!$A8,'Quarterly Data'!DA:DA) -> 4.307784 | CW8: =SUMIF('Quarterly Data'!$B:$B,'Annual Data'!$A8,'Quarterly Data'!DB:DB) -> 2.2320826 | CX8: =SUMIF('Quarterly Data'!$B:$B,'Annual Data'!$A8,'Quarterly Data'!DC:DC) -> 23.336028
A9: 1975 | B9: =SUMIF('Quarterly Data'!$B:$B,'Annual Data'!$A9,'Quarterly Data'!G:G) -> 1021204 | C9: =SUMIF('Quarterly Data'!$B:$B,'Annual Data'!$A9,'Quarterly Data'!H:H) -> 543607 | D9: =SUMIF('Quarterly Data'!$B:$B,'Annual Data'!$A9,'Quarterly Data'!I:I) -> 171485 | E9: =SUMIF('Quarterly Data'!$B:$B,'Annual Data'!$A9,'Quarterly Data'!J:J) -> 275721 | F9: =SUMIF('Quarterly Data'!$B:$B,'Annual Data'!$A9,'Quarterly Data'!K:K) -> 161983 | G9: =SUMIF('Quarterly Data'!$B:$B,'Annual Data'!$A9,'Quarterly Data'!L:L) -> 137577 | H9: =SUMIF('Quarterly Data'!$B:$B,'Annual Data'!$A9,'Quarterly Data'!M:M) -> 71584.32 | I9: =SUMIF('Quarterly Data'!$B:$B,'Annual Data'!$A9,'Quarterly Data'!N:N) -> 23484.652 | J9: =AVERAGEIF('Quarterly Data'!$B:$B,'Annual Data'!$A9,'Quarterly Data'!O:O) -> 17.648755 | K9: =SUMIF('Quarterly Data'!$E:$E,'Annual Data'!$A9,'Quarterly Data'!P:P) -> 11.25 | L9: =SUMIF('Quarterly Data'!$E:$E,'Annual Data'!$A9,'Quarterly Data'!Q:Q) -> 0.001 | M9: =AVERAGEIF('Quarterly Data'!$B:$B,'Annual Data'!$A9,'Quarterly Data'!R:R) -> 17.648755 | N9: =AVERAGEIF('Quarterly Data'!$B:$B,'Annual Data'!$A9,'Quarterly Data'!S:S) -> 26981 | O9: =AVERAGEIF('Quarterly Data'!$B:$B,'Annual Data'!$A9,'Quarterly Data'!T:T) -> 0.001 | P9: =AVERAGEIF('Quarterly Data'!$B:$B,'Annual Data'!$A9,'Quarterly Data'!U:U) -> 0.001 | Q9: =AVERAGEIF('Quarterly Data'!$B:$B,'Annual Data'!$A9,'Quarterly Data'!V:V) -> 0.001 | R9: =AVERAGEIF('Quarterly Data'!$B:$B,'Annual Data'!$A9,'Quarterly Data'!W:W) -> 0.001 | S9: =AVERAGEIF('Quarterly Data'!$B:$B,'Annual Data'!$A9,'Quarterly Data'!X:X) -> 0.001 | T9: =AVERAGEIF('Quarterly Data'!$B:$B,'Annual Data'!$A9,'Quarterly Data'!Y:Y) -> 0.001 | U9: =AVERAGEIF('Quarterly Data'!$B:$B,'Annual Data'!$A9,'Quarterly Data'!Z:Z) -> 0.001 | V9: =AVERAGEIF('Quarterly Data'!$B:$B,'Annual Data'!$A9,'Quarterly Data'!AA:AA) -> 0.001 | W9: =AVERAGEIF('Quarterly Data'!$B:$B,'Annual Data'!$A9,'Quarterly Data'!AB:AB) -> 0.001 | X9: =AVERAGEIF('Quarterly Data'!$B:$B,'Annual Data'!$A9,'Quarterly Data'!AC:AC) -> 0.001 | Y9: =AVERAGEIF('Quarterly Data'!$B:$B,'Annual Data'!$A9,'Quarterly Data'!AD:AD) -> 0.001 | Z9: =AVERAGEIF('Quarterly Data'!$B:$B,'Annual Data'!$A9,'Quarterly Data'!AE:AE) -> 0.001 | AA9: =AVERAGEIF('Quarterly Data'!$B:$B,'Annual Data'!$A9,'Quarterly Data'!AF:AF) -> 0.001 | AB9: =AVERAGEIF('Quarterly Data'!$B:$B,'Annual Data'!$A9,'Quarterly Data'!AG:AG) -> 0.001 | AC9: =AVERAGEIF('Quarterly Data'!$B:$B,'Annual Data'!$A9,'Quarterly Data'!AH:AH) -> 0.001 | AD9: =AVERAGEIF('Quarterly Data'!$B:$B,'Annual Data'!$A9,'Quarterly Data'!AI:AI) -> 0.001 | AE9: =AVERAGEIF('Quarterly Data'!$B:$B,'Annual Data'!$A9,'Quarterly Data'!AJ:AJ) -> 0.001 | AF9: =AVERAGEIF('Quarterly Data'!$B:$B,'Annual Data'!$A9,'Quarterly Data'!AK:AK) -> 0.001 | AG9: =AVERAGEIF('Quarterly Data'!$B:$B,'Annual Data'!$A9,'Quarterly Data'!AL:AL) -> 0.001 | AH9: =AVERAGEIF('Quarterly Data'!$B:$B,'Annual Data'!$A9,'Quarterly Data'!AM:AM) -> 24933.25 | AI9: =AVERAGEIF('Quarterly Data'!$B:$B,'Annual Data'!$A9,'Quarterly Data'!AN:AN) -> 5356.6968 | AJ9: =SUMIF('Quarterly Data'!$B:$B,'Annual Data'!$A9,'Quarterly Data'!AO:AO) -> 1021204 | AK9: =SUMIF('Quarterly Data'!$B:$B,'Annual Data'!$A9,'Quarterly Data'!AP:AP) -> 6060.85 | AL9: =SUMIF('Quarterly Data'!$B:$B,'Annual Data'!$A9,'Quarterly Data'!AQ:AQ) -> 215781.13 | AM9: =SUMIF('Quarterly Data'!$B:$B,'Annual Data'!$A9,'Quarterly Data'!AR:AR) -> 1557.62 | AN9: =SUMIF('Quarterly Data'!$B:$B,'Annual Data'!$A9,'Quarterly Data'!AS:AS) -> 1033.444 | AO9: =SUMIF('Quarterly Data'!$B:$B,'Annual Data'!$A9,'Quarterly Data'!AT:AT) -> 961.6561 | AP9: =SUMIF('Quarterly Data'!$B:$B,'Annual Data'!$A9,'Quarterly Data'!AU:AU) -> 742205.1 | AQ9: =SUMIF('Quarterly Data'!$B:$B,'Annual Data'!$A9,'Quarterly Data'!AV:AV) -> 4939 | AR9: =SUMIF('Quarterly Data'!$B:$B,'Annual Data'!$A9,'Quarterly Data'!AW:AW) -> 77.425 | AS9: =SUMIF('Quarterly Data'!$B:$B,'Annual Data'!$A9,'Quarterly Data'!AX:AX) -> 1681.8696 | AT9: =SUMIF('Quarterly Data'!$B:$B,'Annual Data'!$A9,'Quarterly Data'!AY:AY) -> 6639 | AU9: =SUMIF('Quarterly Data'!$B:$B,'Annual Data'!$A9,'Quarterly Data'!AZ:AZ) -> 916 | AV9: =SUMIF('Quarterly Data'!$B:$B,'Annual Data'!$A9,'Quarterly Data'!BA:BA) -> 2.3748951 | AW9: =SUMIF('Quarterly Data'!$B:$B,'Annual Data'!$A9,'Quarterly Data'!BB:BB) -> 5346.4 | AX9: =SUMIF('Quarterly Data'!$B:$B,'Annual Data'!$A9,'Quarterly Data'!BC:BC) -> 2.6863469 | AY9: =SUMIF('Quarterly Data'!$B:$B,'Annual Data'!$A9,'Quarterly Data'!BD:BD) -> 30.704407 | AZ9: =SUMIF('Quarterly Data'!$B:$B,'Annual Data'!$A9,'Quarterly Data'!BE:BE) -> 7.75025 | BA9: =SUMIF('Quarterly Data'!$B:$B,'Annual Data'!$A9,'Quarterly Data'!BF:BF) -> 2.294 | BB9: =SUMIF('Quarterly Data'!$B:$B,'Annual Data'!$A9,'Quarterly Data'!BG:BG) -> 2.0944331 | BC9: =SUMIF('Quarterly Data'!$B:$B,'Annual Data'!$A9,'Quarterly Data'!BH:BH) -> 1.227948 | BD9: =SUMIF('Quarterly Data'!$B:$B,'Annual Data'!$A9,'Quarterly Data'!BI:BI) -> 3.2018 | BE9: =SUMIF('Quarterly Data'!$B:$B,'Annual Data'!$A9,'Quarterly Data'!BJ:BJ) -> 2.2591435 | BF9: =SUMIF('Quarterly Data'!$B:$B,'Annual Data'!$A9,'Quarterly Data'!BK:BK) -> 0.5280563 | BG9: =SUMIF('Quarterly Data'!$B:$B,'Annual Data'!$A9,'Quarterly Data'!BL:BL) -> 0.10399999 | BH9: =SUMIF('Quarterly Data'!$B:$B,'Annual Data'!$A9,'Quarterly Data'!BM:BM) -> 0.20696999 | BI9: =SUMIF('Quarterly Data'!$B:$B,'Annual Data'!$A9,'Quarterly Data'!BN:BN) -> 0.016202872 | BJ9: =SUMIF('Quarterly Data'!$B:$B,'Annual Data'!$A9,'Quarterly Data'!BO:BO) -> 0.004 | BK9: =AVERAGEIF('Quarterly Data'!$B:$B,'Annual Data'!$A9,'Quarterly Data'!BP:BP) -> 58158 | BL9: =AVERAGEIF('Quarterly Data'!$B:$B,'Annual Data'!$A9,'Quarterly Data'!BQ:BQ) -> 1348.1227 | BM9: =AVERAGEIF('Quarterly Data'!$B:$B,'Annual Data'!$A9,'Quarterly Data'!BR:BR) -> 24464.75 | BN9: =AVERAGEIF('Quarterly Data'!$B:$B,'Annual Data'!$A9,'Quarterly Data'!BS:BS) -> 79200.25 | BO9: =AVERAGEIF('Quarterly Data'!$B:$B,'Annual Data'!$A9,'Quarterly Data'!BT:BT) -> 0.001 | BP9: =AVERAGEIF('Quarterly Data'!$B:$B,'Annual Data'!$A9,'Quarterly Data'!BU:BU) -> 167 | BQ9: =AVERAGEIF('Quarterly Data'!$B:$B,'Annual Data'!$A9,'Quarterly Data'!BV:BV) -> 85285.515 | BR9: =AVERAGEIF('Quarterly Data'!$B:$B,'Annual Data'!$A9,'Quarterly Data'!BW:BW) -> 105.507 | BS9: =AVERAGEIF('Quarterly Data'!$B:$B,'Annual Data'!$A9,'Quarterly Data'!BX:BX) -> 2317.699 | BT9: =AVERAGEIF('Quarterly Data'!$B:$B,'Annual Data'!$A9,'Quarterly Data'!BY:BY) -> 128.0561 | BU9: =AVERAGEIF('Quarterly Data'!$B:$B,'Annual Data'!$A9,'Quarterly Data'!BZ:BZ) -> 67.140758 | BV9: =AVERAGEIF('Quarterly Data'!$B:$B,'Annual Data'!$A9,'Quarterly Data'!CA:CA) -> 55.573125 | BW9: =AVERAGEIF('Quarterly Data'!$B:$B,'Annual Data'!$A9,'Quarterly Data'!CB:CB) -> 0.001 | BX9: =AVERAGEIF('Quarterly Data'!$B:$B,'Annual Data'!$A9,'Quarterly Data'!CC:CC) -> 55.68485 | BY9: =AVERAGEIF('Quarterly Data'!$B:$B,'Annual Data'!$A9,'Quarterly Data'!CD:CD) -> 38.927225 | BZ9: =AVERAGEIF('Quarterly Data'!$B:$B,'Annual Data'!$A9,'Quarterly Data'!CE:CE) -> 13.95658 | CA9: =AVERAGEIF('Quarterly Data'!$B:$B,'Annual Data'!$A9,'Quarterly Data'!CF:CF) -> 1.457462 | CB9: =AVERAGEIF('Quarterly Data'!$B:$B,'Annual Data'!$A9,'Quarterly Data'!CG:CG) -> 0.001 | CC9: =AVERAGEIF('Quarterly Data'!$B:$B,'Annual Data'!$A9,'Quarterly Data'!CH:CH) -> 0.5275062 | CD9: =AVERAGEIF('Quarterly Data'!$B:$B,'Annual Data'!$A9,'Quarterly Data'!CI:CI) -> 0.57077615 | CE9: =SUMIF('Quarterly Data'!$B:$B,'Annual Data'!$A9,'Quarterly Data'!CJ:CJ) -> 115095 | CF9: =SUMIF('Quarterly Data'!$B:$B,'Annual Data'!$A9,'Quarterly Data'!CK:CK) -> 1684.9 | CG9: =SUMIF('Quarterly Data'!$B:$B,'Annual Data'!$A9,'Quarterly Data'!CL:CL) -> 152524.06 | CH9: =SUMIF('Quarterly Data'!$B:$B,'Annual Data'!$A9,'Quarterly Data'!CM:CM) -> 177928 | CI9: =SUMIF('Quarterly Data'!$B:$B,'Annual Data'!$A9,'Quarterly Data'!CN:CN) -> 76569 | CJ9: =SUMIF('Quarterly Data'!$B:$B,'Annual Data'!$A9,'Quarterly Data'!CO:CO) -> 0.004 | CK9: =SUMIF('Quarterly Data'!$B:$B,'Annual Data'!$A9,'Quarterly Data'!CP:CP) -> 315883.91 | CL9: =SUMIF('Quarterly Data'!$B:$B,'Annual Data'!$A9,'Quarterly Data'!CQ:CQ) -> 164.94286 | CM9: =SUMIF('Quarterly Data'!$B:$B,'Annual Data'!$A9,'Quarterly Data'!CR:CR) -> 10709 | CN9: =SUMIF('Quarterly Data'!$B:$B,'Annual Data'!$A9,'Quarterly Data'!CS:CS) -> 627.6409 | CO9: =SUMIF('Quarterly Data'!$B:$B,'Annual Data'!$A9,'Quarterly Data'!CT:CT) -> 233.583 | CP9: =SUMIF('Quarterly Data'!$B:$B,'Annual Data'!$A9,'Quarterly Data'!CU:CU) -> 76.902 | CQ9: =SUMIF('Quarterly Data'!$B:$B,'Annual Data'!$A9,'Quarterly Data'!CV:CV) -> 39.132731 | CR9: =SUMIF('Quarterly Data'!$B:$B,'Annual Data'!$A9,'Quarterly Data'!CW:CW) -> 138.72 | CS9: =SUMIF('Quarterly Data'!$B:$B,'Annual Data'!$A9,'Quarterly Data'!CX:CX) -> 59.00858 | CT9: =SUMIF('Quarterly Data'!$B:$B,'Annual Data'!$A9,'Quarterly Data'!CY:CY) -> 40.952593 | CU9: =SUMIF('Quarterly Data'!$B:$B,'Annual Data'!$A9,'Quarterly Data'!CZ:CZ) -> 18.378 | CV9: =SUMIF('Quarterly Data'!$B:$B,'Annual Data'!$A9,'Quarterly Data'!DA:DA) -> 5.416479 | CW9: =SUMIF('Quarterly Data'!$B:$B,'Annual Data'!$A9,'Quarterly Data'!DB:DB) -> 2.6855581 | CX9: =SUMIF('Quarterly Data'!$B:$B,'Annual Data'!$A9,'Quarterly Data'!DC:DC) -> 23.336028
A10: 1976 | B10: =SUMIF('Quarterly Data'!$B:$B,'Annual Data'!$A10,'Quarterly Data'!G:G) -> 1051973 | C10: =SUMIF('Quarterly Data'!$B:$B,'Annual Data'!$A10,'Quarterly Data'!H:H) -> 546626 | D10: =SUMIF('Quarterly Data'!$B:$B,'Annual Data'!$A10,'Quarterly Data'!I:I) -> 172649 | E10: =SUMIF('Quarterly Data'!$B:$B,'Annual Data'!$A10,'Quarterly Data'!J:J) -> 279970 | F10: =SUMIF('Quarterly Data'!$B:$B,'Annual Data'!$A10,'Quarterly Data'!K:K) -> 176297 | G10: =SUMIF('Quarterly Data'!$B:$B,'Annual Data'!$A10,'Quarterly Data'!L:L) -> 144319 | H10: =SUMIF('Quarterly Data'!$B:$B,'Annual Data'!$A10,'Quarterly Data'!M:M) -> 73225.01 | I10: =SUMIF('Quarterly Data'!$B:$B,'Annual Data'!$A10,'Quarterly Data'!N:N) -> 22758.194 | J10: =AVERAGEIF('Quarterly Data'!$B:$B,'Annual Data'!$A10,'Quarterly Data'!O:O) -> 20.412077 | K10: =SUMIF('Quarterly Data'!$E:$E,'Annual Data'!$A10,'Quarterly Data'!P:P) -> 14.25 | L10: =SUMIF('Quarterly Data'!$E:$E,'Annual Data'!$A10,'Quarterly Data'!Q:Q) -> 0.001 | M10: =AVERAGEIF('Quarterly Data'!$B:$B,'Annual Data'!$A10,'Quarterly Data'!R:R) -> 20.412077 | N10: =AVERAGEIF('Quarterly Data'!$B:$B,'Annual Data'!$A10,'Quarterly Data'!S:S) -> 26794.75 | O10: =AVERAGEIF('Quarterly Data'!$B:$B,'Annual Data'!$A10,'Quarterly Data'!T:T) -> 0.001 | P10: =AVERAGEIF('Quarterly Data'!$B:$B,'Annual Data'!$A10,'Quarterly Data'!U:U) -> 0.001 | Q10: =AVERAGEIF('Quarterly Data'!$B:$B,'Annual Data'!$A10,'Quarterly Data'!V:V) -> 0.001 | R10: =AVERAGEIF('Quarterly Data'!$B:$B,'Annual Data'!$A10,'Quarterly Data'!W:W) -> 0.001 | S10: =AVERAGEIF('Quarterly Data'!$B:$B,'Annual Data'!$A10,'Quarterly Data'!X:X) -> 0.001 | T10: =AVERAGEIF('Quarterly Data'!$B:$B,'Annual Data'!$A10,'Quarterly Data'!Y:Y) -> 0.001 | U10: =AVERAGEIF('Quarterly Data'!$B:$B,'Annual Data'!$A10,'Quarterly Data'!Z:Z) -> 0.001 | V10: =AVERAGEIF('Quarterly Data'!$B:$B,'Annual Data'!$A10,'Quarterly Data'!AA:AA) -> 0.001 | W10: =AVERAGEIF('Quarterly Data'!$B:$B,'Annual Data'!$A10,'Quarterly Data'!AB:AB) -> 0.001 | X10: =AVERAGEIF('Quarterly Data'!$B:$B,'Annual Data'!$A10,'Quarterly Data'!AC:AC) -> 0.001 | Y10: =AVERAGEIF('Quarterly Data'!$B:$B,'Annual Data'!$A10,'Quarterly Data'!AD:AD) -> 0.001 | Z10: =AVERAGEIF('Quarterly Data'!$B:$B,'Annual Data'!$A10,'Quarterly Data'!AE:AE) -> 0.001 | AA10: =AVERAGEIF('Quarterly Data'!$B:$B,'Annual Data'!$A10,'Quarterly Data'!AF:AF) -> 0.001 | AB10: =AVERAGEIF('Quarterly Data'!$B:$B,'Annual Data'!$A10,'Quarterly Data'!AG:AG) -> 0.001 | AC10: =AVERAGEIF('Quarterly Data'!$B:$B,'Annual Data'!$A10,'Quarterly Data'!AH:AH) -> 0.001 | AD10: =AVERAGEIF('Quarterly Data'!$B:$B,'Annual Data'!$A10,'Quarterly Data'!AI:AI) -> 0.001 | AE10: =AVERAGEIF('Quarterly Data'!$B:$B,'Annual Data'!$A10,'Quarterly Data'!AJ:AJ) -> 0.001 | AF10: =AVERAGEIF('Quarterly Data'!$B:$B,'Annual Data'!$A10,'Quarterly Data'!AK:AK) -> 0.001 | AG10: =AVERAGEIF('Quarterly Data'!$B:$B,'Annual Data'!$A10,'Quarterly Data'!AL:AL) -> 0.001 | AH10: =AVERAGEIF('Quarterly Data'!$B:$B,'Annual Data'!$A10,'Quarterly Data'!AM:AM) -> 24786 | AI10: =AVERAGEIF('Quarterly Data'!$B:$B,'Annual Data'!$A10,'Quarterly Data'!AN:AN) -> 5456.5453 | AJ10: =SUMIF('Quarterly Data'!$B:$B,'Annual Data'!$A10,'Quarterly Data'!AO:AO) -> 1051973 | AK10: =SUMIF('Quarterly Data'!$B:$B,'Annual Data'!$A10,'Quarterly Data'!AP:AP) -> 6387.425 | AL10: =SUMIF('Quarterly Data'!$B:$B,'Annual Data'!$A10,'Quarterly Data'!AQ:AQ) -> 224484.6 | AM10: =SUMIF('Quarterly Data'!$B:$B,'Annual Data'!$A10,'Quarterly Data'!AR:AR) -> 1626.82 | AN10: =SUMIF('Quarterly Data'!$B:$B,'Annual Data'!$A10,'Quarterly Data'!AS:AS) -> 1078.312 | AO10: =SUMIF('Quarterly Data'!$B:$B,'Annual Data'!$A10,'Quarterly Data'!AT:AT) -> 1024.4384 | AP10: =SUMIF('Quarterly Data'!$B:$B,'Annual Data'!$A10,'Quarterly Data'!AU:AU) -> 785915.6 | AQ10: =SUMIF('Quarterly Data'!$B:$B,'Annual Data'!$A10,'Quarterly Data'!AV:AV) -> 6380 | AR10: =SUMIF('Quarterly Data'!$B:$B,'Annual Data'!$A10,'Quarterly Data'!AW:AW) -> 86.725 | AS10: =SUMIF('Quarterly Data'!$B:$B,'Annual Data'!$A10,'Quarterly Data'!AX:AX) -> 2416.8589 | AT10: =SUMIF('Quarterly Data'!$B:$B,'Annual Data'!$A10,'Quarterly Data'!AY:AY) -> 8242 | AU10: =SUMIF('Quarterly Data'!$B:$B,'Annual Data'!$A10,'Quarterly Data'!AZ:AZ) -> 1191 | AV10: =SUMIF('Quarterly Data'!$B:$B,'Annual Data'!$A10,'Quarterly Data'!BA:BA) -> 3.0832487 | AW10: =SUMIF('Quarterly Data'!$B:$B,'Annual Data'!$A10,'Quarterly Data'!BB:BB) -> 5906.224 | AX10: =SUMIF('Quarterly Data'!$B:$B,'Annual Data'!$A10,'Quarterly Data'!BC:BC) -> 2.8778708 | AY10: =SUMIF('Quarterly Data'!$B:$B,'Annual Data'!$A10,'Quarterly Data'!BD:BD) -> 45.524406 | AZ10: =SUMIF('Quarterly Data'!$B:$B,'Annual Data'!$A10,'Quarterly Data'!BE:BE) -> 9.69025 | BA10: =SUMIF('Quarterly Data'!$B:$B,'Annual Data'!$A10,'Quarterly Data'!BF:BF) -> 2.405 | BB10: =SUMIF('Quarterly Data'!$B:$B,'Annual Data'!$A10,'Quarterly Data'!BG:BG) -> 2.9760915 | BC10: =SUMIF('Quarterly Data'!$B:$B,'Annual Data'!$A10,'Quarterly Data'!BH:BH) -> 1.2381697 | BD10: =SUMIF('Quarterly Data'!$B:$B,'Annual Data'!$A10,'Quarterly Data'!BI:BI) -> 3.6652 | BE10: =SUMIF('Quarterly Data'!$B:$B,'Annual Data'!$A10,'Quarterly Data'!BJ:BJ) -> 2.6084906 | BF10: =SUMIF('Quarterly Data'!$B:$B,'Annual Data'!$A10,'Quarterly Data'!BK:BK) -> 0.7505519 | BG10: =SUMIF('Quarterly Data'!$B:$B,'Annual Data'!$A10,'Quarterly Data'!BL:BL) -> 0.123 | BH10: =SUMIF('Quarterly Data'!$B:$B,'Annual Data'!$A10,'Quarterly Data'!BM:BM) -> 0.29331001 | BI10: =SUMIF('Quarterly Data'!$B:$B,'Annual Data'!$A10,'Quarterly Data'!BN:BN) -> 0.034875378 | BJ10: =SUMIF('Quarterly Data'!$B:$B,'Annual Data'!$A10,'Quarterly Data'!BO:BO) -> 0.004 | BK10: =AVERAGEIF('Quarterly Data'!$B:$B,'Annual Data'!$A10,'Quarterly Data'!BP:BP) -> 69520.375 | BL10: =AVERAGEIF('Quarterly Data'!$B:$B,'Annual Data'!$A10,'Quarterly Data'!BQ:BQ) -> 1484.422 | BM10: =AVERAGEIF('Quarterly Data'!$B:$B,'Annual Data'!$A10,'Quarterly Data'!BR:BR) -> 38512.75 | BN10: =AVERAGEIF('Quarterly Data'!$B:$B,'Annual Data'!$A10,'Quarterly Data'!BS:BS) -> 88010 | BO10: =AVERAGEIF('Quarterly Data'!$B:$B,'Annual Data'!$A10,'Quarterly Data'!BT:BT) -> 0.001 | BP10: =AVERAGEIF('Quarterly Data'!$B:$B,'Annual Data'!$A10,'Quarterly Data'!BU:BU) -> 167 | BQ10: =AVERAGEIF('Quarterly Data'!$B:$B,'Annual Data'!$A10,'Quarterly Data'!BV:BV) -> 92524.835 | BR10: =AVERAGEIF('Quarterly Data'!$B:$B,'Annual Data'!$A10,'Quarterly Data'!BW:BW) -> 107.74 | BS10: =AVERAGEIF('Quarterly Data'!$B:$B,'Annual Data'!$A10,'Quarterly Data'!BX:BX) -> 2875.1795 | BT10: =AVERAGEIF('Quarterly Data'!$B:$B,'Annual Data'!$A10,'Quarterly Data'!BY:BY) -> 148.6384 | BU10: =AVERAGEIF('Quarterly Data'!$B:$B,'Annual Data'!$A10,'Quarterly Data'!BZ:BZ) -> 74.513445 | BV10: =AVERAGEIF('Quarterly Data'!$B:$B,'Annual Data'!$A10,'Quarterly Data'!CA:CA) -> 71.13125 | BW10: =AVERAGEIF('Quarterly Data'!$B:$B,'Annual Data'!$A10,'Quarterly Data'!CB:CB) -> 1.504977 | BX10: =AVERAGEIF('Quarterly Data'!$B:$B,'Annual Data'!$A10,'Quarterly Data'!CC:CC) -> 62.134495 | BY10: =AVERAGEIF('Quarterly Data'!$B:$B,'Annual Data'!$A10,'Quarterly Data'!CD:CD) -> 44.578918 | BZ10: =AVERAGEIF('Quarterly Data'!$B:$B,'Annual Data'!$A10,'Quarterly Data'!CE:CE) -> 18.389345 | CA10: =AVERAGEIF('Quarterly Data'!$B:$B,'Annual Data'!$A10,'Quarterly Data'!CF:CF) -> 1.499999 | CB10: =AVERAGEIF('Quarterly Data'!$B:$B,'Annual Data'!$A10,'Quarterly Data'!CG:CG) -> 0.001 | CC10: =AVERAGEIF('Quarterly Data'!$B:$B,'Annual Data'!$A10,'Quarterly Data'!CH:CH) -> 0.63883545 | CD10: =AVERAGEIF('Quarterly Data'!$B:$B,'Annual Data'!$A10,'Quarterly Data'!CI:CI) -> 0.8798624 | CE10: =SUMIF('Quarterly Data'!$B:$B,'Annual Data'!$A10,'Quarterly Data'!CJ:CJ) -> 136995 | CF10: =SUMIF('Quarterly Data'!$B:$B,'Annual Data'!$A10,'Quarterly Data'!CK:CK) -> 1873.425 | CG10: =SUMIF('Quarterly Data'!$B:$B,'Annual Data'!$A10,'Quarterly Data'!CL:CL) -> 171384.16 | CH10: =SUMIF('Quarterly Data'!$B:$B,'Annual Data'!$A10,'Quarterly Data'!CM:CM) -> 205986 | CI10: =SUMIF('Quarterly Data'!$B:$B,'Annual Data'!$A10,'Quarterly Data'!CN:CN) -> 90309 | CJ10: =SUMIF('Quarterly Data'!$B:$B,'Annual Data'!$A10,'Quarterly Data'!CO:CO) -> 0.004 | CK10: =SUMIF('Quarterly Data'!$B:$B,'Annual Data'!$A10,'Quarterly Data'!CP:CP) -> 357275.66 | CL10: =SUMIF('Quarterly Data'!$B:$B,'Annual Data'!$A10,'Quarterly Data'!CQ:CQ) -> 167.06712 | CM10: =SUMIF('Quarterly Data'!$B:$B,'Annual Data'!$A10,'Quarterly Data'!CR:CR) -> 14699.6 | CN10: =SUMIF('Quarterly Data'!$B:$B,'Annual Data'!$A10,'Quarterly Data'!CS:CS) -> 677.2367 | CO10: =SUMIF('Quarterly Data'!$B:$B,'Annual Data'!$A10,'Quarterly Data'!CT:CT) -> 269.714 | CP10: =SUMIF('Quarterly Data'!$B:$B,'Annual Data'!$A10,'Quarterly Data'!CU:CU) -> 96.562 | CQ10: =SUMIF('Quarterly Data'!$B:$B,'Annual Data'!$A10,'Quarterly Data'!CV:CV) -> 47.09136 | CR10: =SUMIF('Quarterly Data'!$B:$B,'Annual Data'!$A10,'Quarterly Data'!CW:CW) -> 138.72 | CS10: =SUMIF('Quarterly Data'!$B:$B,'Annual Data'!$A10,'Quarterly Data'!CX:CX) -> 67.02714 | CT10: =SUMIF('Quarterly Data'!$B:$B,'Annual Data'!$A10,'Quarterly Data'!CY:CY) -> 45.15624 | CU10: =SUMIF('Quarterly Data'!$B:$B,'Annual Data'!$A10,'Quarterly Data'!CZ:CZ) -> 20.789 | CV10: =SUMIF('Quarterly Data'!$B:$B,'Annual Data'!$A10,'Quarterly Data'!DA:DA) -> 6.671923 | CW10: =SUMIF('Quarterly Data'!$B:$B,'Annual Data'!$A10,'Quarterly Data'!DB:DB) -> 3.3405523 | CX10: =SUMIF('Quarterly Data'!$B:$B,'Annual Data'!$A10,'Quarterly Data'!DC:DC) -> 23.336028
A11: 1977 | B11: =SUMIF('Quarterly Data'!$B:$B,'Annual Data'!$A11,'Quarterly Data'!G:G) -> 1077816 | C11: =SUMIF('Quarterly Data'!$B:$B,'Annual Data'!$A11,'Quarterly Data'!H:H) -> 545408 | D11: =SUMIF('Quarterly Data'!$B:$B,'Annual Data'!$A11,'Quarterly Data'!I:I) -> 175324 | E11: =SUMIF('Quarterly Data'!$B:$B,'Annual Data'!$A11,'Quarterly Data'!J:J) -> 276373 | F11: =SUMIF('Quarterly Data'!$B:$B,'Annual Data'!$A11,'Quarterly Data'!K:K) -> 187922 | G11: =SUMIF('Quarterly Data'!$B:$B,'Annual Data'!$A11,'Quarterly Data'!L:L) -> 146817 | H11: =SUMIF('Quarterly Data'!$B:$B,'Annual Data'!$A11,'Quarterly Data'!M:M) -> 74259.88 | I11: =SUMIF('Quarterly Data'!$B:$B,'Annual Data'!$A11,'Quarterly Data'!N:N) -> 18855.926 | J11: =AVERAGEIF('Quarterly Data'!$B:$B,'Annual Data'!$A11,'Quarterly Data'!O:O) -> 23.462157 | K11: =SUMIF('Quarterly Data'!$E:$E,'Annual Data'!$A11,'Quarterly Data'!P:P) -> 7 | L11: =SUMIF('Quarterly Data'!$E:$E,'Annual Data'!$A11,'Quarterly Data'!Q:Q) -> 0.001 | M11: =AVERAGEIF('Quarterly Data'!$B:$B,'Annual Data'!$A11,'Quarterly Data'!R:R) -> 23.462157 | N11: =AVERAGEIF('Quarterly Data'!$B:$B,'Annual Data'!$A11,'Quarterly Data'!S:S) -> 26841 | O11: =AVERAGEIF('Quarterly Data'!$B:$B,'Annual Data'!$A11,'Quarterly Data'!T:T) -> 0.001 | P11: =AVERAGEIF('Quarterly Data'!$B:$B,'Annual Data'!$A11,'Quarterly Data'!U:U) -> 0.001 | Q11: =AVERAGEIF('Quarterly Data'!$B:$B,'Annual Data'!$A11,'Quarterly Data'!V:V) -> 0.001 | R11: =AVERAGEIF('Quarterly Data'!$B:$B,'Annual Data'!$A11,'Quarterly Data'!W:W) -> 0.001 | S11: =AVERAGEIF('Quarterly Data'!$B:$B,'Annual Data'!$A11,'Quarterly Data'!X:X) -> 0.001 | T11: =AVERAGEIF('Quarterly Data'!$B:$B,'Annual Data'!$A11,'Quarterly Data'!Y:Y) -> 0.001 | U11: =AVERAGEIF('Quarterly Data'!$B:$B,'Annual Data'!$A11,'Quarterly Data'!Z:Z) -> 0.001 | V11: =AVERAGEIF('Quarterly Data'!$B:$B,'Annual Data'!$A11,'Quarterly Data'!AA:AA) -> 0.001 | W11: =AVERAGEIF('Quarterly Data'!$B:$B,'Annual Data'!$A11,'Quarterly Data'!AB:AB) -> 0.001 | X11: =AVERAGEIF('Quarterly Data'!$B:$B,'Annual Data'!$A11,'Quarterly Data'!AC:AC) -> 0.001 | Y11: =AVERAGEIF('Quarterly Data'!$B:$B,'Annual Data'!$A11,'Quarterly Data'!AD:AD) -> 0.001 | Z11: =AVERAGEIF('Quarterly Data'!$B:$B,'Annual Data'!$A11,'Quarterly Data'!AE:AE) -> 0.001 | AA11: =AVERAGEIF('Quarterly Data'!$B:$B,'Annual Data'!$A11,'Quarterly Data'!AF:AF) -> 0.001 | AB11: =AVERAGEIF('Quarterly Data'!$B:$B,'Annual Data'!$A11,'Quarterly Data'!AG:AG) -> 0.001 | AC11: =AVERAGEIF('Quarterly Data'!$B:$B,'Annual Data'!$A11,'Quarterly Data'!AH:AH) -> 0.001 | AD11: =AVERAGEIF('Quarterly Data'!$B:$B,'Annual Data'!$A11,'Quarterly Data'!AI:AI) -> 0.001 | AE11: =AVERAGEIF('Quarterly Data'!$B:$B,'Annual Data'!$A11,'Quarterly Data'!AJ:AJ) -> 0.001 | AF11: =AVERAGEIF('Quarterly Data'!$B:$B,'Annual Data'!$A11,'Quarterly Data'!AK:AK) -> 0.001 | AG11: =AVERAGEIF('Quarterly Data'!$B:$B,'Annual Data'!$A11,'Quarterly Data'!AL:AL) -> 0.001 | AH11: =AVERAGEIF('Quarterly Data'!$B:$B,'Annual Data'!$A11,'Quarterly Data'!AM:AM) -> 24809 | AI11: =AVERAGEIF('Quarterly Data'!$B:$B,'Annual Data'!$A11,'Quarterly Data'!AN:AN) -> 5423.299 | AJ11: =SUMIF('Quarterly Data'!$B:$B,'Annual Data'!$A11,'Quarterly Data'!AO:AO) -> 1077816 | AK11: =SUMIF('Quarterly Data'!$B:$B,'Annual Data'!$A11,'Quarterly Data'!AP:AP) -> 6682.825 | AL11: =SUMIF('Quarterly Data'!$B:$B,'Annual Data'!$A11,'Quarterly Data'!AQ:AQ) -> 234520.75 | AM11: =SUMIF('Quarterly Data'!$B:$B,'Annual Data'!$A11,'Quarterly Data'!AR:AR) -> 1683.93 | AN11: =SUMIF('Quarterly Data'!$B:$B,'Annual Data'!$A11,'Quarterly Data'!AS:AS) -> 1116.289 | AO11: =SUMIF('Quarterly Data'!$B:$B,'Annual Data'!$A11,'Quarterly Data'!AT:AT) -> 1048.6038 | AP11: =SUMIF('Quarterly Data'!$B:$B,'Annual Data'!$A11,'Quarterly Data'!AU:AU) -> 813696.4 | AQ11: =SUMIF('Quarterly Data'!$B:$B,'Annual Data'!$A11,'Quarterly Data'!AV:AV) -> 7333 | AR11: =SUMIF('Quarterly Data'!$B:$B,'Annual Data'!$A11,'Quarterly Data'!AW:AW) -> 95.75 | AS11: =SUMIF('Quarterly Data'!$B:$B,'Annual Data'!$A11,'Quarterly Data'!AX:AX) -> 3374.968 | AT11: =SUMIF('Quarterly Data'!$B:$B,'Annual Data'!$A11,'Quarterly Data'!AY:AY) -> 9432 | AU11: =SUMIF('Quarterly Data'!$B:$B,'Annual Data'!$A11,'Quarterly Data'!AZ:AZ) -> 1532 | AV11: =SUMIF('Quarterly Data'!$B:$B,'Annual Data'!$A11,'Quarterly Data'!BA:BA) -> 4.659654 | AW11: =SUMIF('Quarterly Data'!$B:$B,'Annual Data'!$A11,'Quarterly Data'!BB:BB) -> 7658.689 | AX11: =SUMIF('Quarterly Data'!$B:$B,'Annual Data'!$A11,'Quarterly Data'!BC:BC) -> 3.1135911 | AY11: =SUMIF('Quarterly Data'!$B:$B,'Annual Data'!$A11,'Quarterly Data'!BD:BD) -> 64.8477 | AZ11: =SUMIF('Quarterly Data'!$B:$B,'Annual Data'!$A11,'Quarterly Data'!BE:BE) -> 10.62 | BA11: =SUMIF('Quarterly Data'!$B:$B,'Annual Data'!$A11,'Quarterly Data'!BF:BF) -> 3.053 | BB11: =SUMIF('Quarterly Data'!$B:$B,'Annual Data'!$A11,'Quarterly Data'!BG:BG) -> 3.9318799 | BC11: =SUMIF('Quarterly Data'!$B:$B,'Annual Data'!$A11,'Quarterly Data'!BH:BH) -> 1.9685134 | BD11: =SUMIF('Quarterly Data'!$B:$B,'Annual Data'!$A11,'Quarterly Data'!BI:BI) -> 4.0424997 | BE11: =SUMIF('Quarterly Data'!$B:$B,'Annual Data'!$A11,'Quarterly Data'!BJ:BJ) -> 3.1951967 | BF11: =SUMIF('Quarterly Data'!$B:$B,'Annual Data'!$A11,'Quarterly Data'!BK:BK) -> 0.9137154 | BG11: =SUMIF('Quarterly Data'!$B:$B,'Annual Data'!$A11,'Quarterly Data'!BL:BL) -> 0.163 | BH11: =SUMIF('Quarterly Data'!$B:$B,'Annual Data'!$A11,'Quarterly Data'!BM:BM) -> 0.37583997 | BI11: =SUMIF('Quarterly Data'!$B:$B,'Annual Data'!$A11,'Quarterly Data'!BN:BN) -> 0.05319042 | BJ11: =SUMIF('Quarterly Data'!$B:$B,'Annual Data'!$A11,'Quarterly Data'!BO:BO) -> 0.004 | BK11: =AVERAGEIF('Quarterly Data'!$B:$B,'Annual Data'!$A11,'Quarterly Data'!BP:BP) -> 79878.25 | BL11: =AVERAGEIF('Quarterly Data'!$B:$B,'Annual Data'!$A11,'Quarterly Data'!BQ:BQ) -> 1603.6862 | BM11: =AVERAGEIF('Quarterly Data'!$B:$B,'Annual Data'!$A11,'Quarterly Data'!BR:BR) -> 53361 | BN11: =AVERAGEIF('Quarterly Data'!$B:$B,'Annual Data'!$A11,'Quarterly Data'!BS:BS) -> 99603.75 | BO11: =AVERAGEIF('Quarterly Data'!$B:$B,'Annual Data'!$A11,'Quarterly Data'!BT:BT) -> 0.001 | BP11: =AVERAGEIF('Quarterly Data'!$B:$B,'Annual Data'!$A11,'Quarterly Data'!BU:BU) -> 167 | BQ11: =AVERAGEIF('Quarterly Data'!$B:$B,'Annual Data'!$A11,'Quarterly Data'!BV:BV) -> 105014.24 | BR11: =AVERAGEIF('Quarterly Data'!$B:$B,'Annual Data'!$A11,'Quarterly Data'!BW:BW) -> 109.891 | BS11: =AVERAGEIF('Quarterly Data'!$B:$B,'Annual Data'!$A11,'Quarterly Data'!BX:BX) -> 3614.379 | BT11: =AVERAGEIF('Quarterly Data'!$B:$B,'Annual Data'!$A11,'Quarterly Data'!BY:BY) -> 164.6101 | BU11: =AVERAGEIF('Quarterly Data'!$B:$B,'Annual Data'!$A11,'Quarterly Data'!BZ:BZ) -> 82.36663 | BV11: =AVERAGEIF('Quarterly Data'!$B:$B,'Annual Data'!$A11,'Quarterly Data'!CA:CA) -> 89.8235 | BW11: =AVERAGEIF('Quarterly Data'!$B:$B,'Annual Data'!$A11,'Quarterly Data'!CB:CB) -> 7.3837535 | BX11: =AVERAGEIF('Quarterly Data'!$B:$B,'Annual Data'!$A11,'Quarterly Data'!CC:CC) -> 68.041407 | BY11: =AVERAGEIF('Quarterly Data'!$B:$B,'Annual Data'!$A11,'Quarterly Data'!CD:CD) -> 51.0837 | BZ11: =AVERAGEIF('Quarterly Data'!$B:$B,'Annual Data'!$A11,'Quarterly Data'!CE:CE) -> 22.501385 | CA11: =AVERAGEIF('Quarterly Data'!$B:$B,'Annual Data'!$A11,'Quarterly Data'!CF:CF) -> 1.8802573 | CB11: =AVERAGEIF('Quarterly Data'!$B:$B,'Annual Data'!$A11,'Quarterly Data'!CG:CG) -> 0.001 | CC11: =AVERAGEIF('Quarterly Data'!$B:$B,'Annual Data'!$A11,'Quarterly Data'!CH:CH) -> 0.75472987 | CD11: =AVERAGEIF('Quarterly Data'!$B:$B,'Annual Data'!$A11,'Quarterly Data'!CI:CI) -> 1.258027 | CE11: =SUMIF('Quarterly Data'!$B:$B,'Annual Data'!$A11,'Quarterly Data'!CJ:CJ) -> 159775 | CF11: =SUMIF('Quarterly Data'!$B:$B,'Annual Data'!$A11,'Quarterly Data'!CK:CK) -> 2081.825 | CG11: =SUMIF('Quarterly Data'!$B:$B,'Annual Data'!$A11,'Quarterly Data'!CL:CL) -> 191055.77 | CH11: =SUMIF('Quarterly Data'!$B:$B,'Annual Data'!$A11,'Quarterly Data'!CM:CM) -> 227601 | CI11: =SUMIF('Quarterly Data'!$B:$B,'Annual Data'!$A11,'Quarterly Data'!CN:CN) -> 100554 | CJ11: =SUMIF('Quarterly Data'!$B:$B,'Annual Data'!$A11,'Quarterly Data'!CO:CO) -> 285.73514 | CK11: =SUMIF('Quarterly Data'!$B:$B,'Annual Data'!$A11,'Quarterly Data'!CP:CP) -> 388592.02 | CL11: =SUMIF('Quarterly Data'!$B:$B,'Annual Data'!$A11,'Quarterly Data'!CQ:CQ) -> 171.57459 | CM11: =SUMIF('Quarterly Data'!$B:$B,'Annual Data'!$A11,'Quarterly Data'!CR:CR) -> 18907.3 | CN11: =SUMIF('Quarterly Data'!$B:$B,'Annual Data'!$A11,'Quarterly Data'!CS:CS) -> 722.7076 | CO11: =SUMIF('Quarterly Data'!$B:$B,'Annual Data'!$A11,'Quarterly Data'!CT:CT) -> 303.907 | CP11: =SUMIF('Quarterly Data'!$B:$B,'Annual Data'!$A11,'Quarterly Data'!CU:CU) -> 117.316 | CQ11: =SUMIF('Quarterly Data'!$B:$B,'Annual Data'!$A11,'Quarterly Data'!CV:CV) -> 59.74479 | CR11: =SUMIF('Quarterly Data'!$B:$B,'Annual Data'!$A11,'Quarterly Data'!CW:CW) -> 142.446 | CS11: =SUMIF('Quarterly Data'!$B:$B,'Annual Data'!$A11,'Quarterly Data'!CX:CX) -> 72.41644 | CT11: =SUMIF('Quarterly Data'!$B:$B,'Annual Data'!$A11,'Quarterly Data'!CY:CY) -> 49.99079 | CU11: =SUMIF('Quarterly Data'!$B:$B,'Annual Data'!$A11,'Quarterly Data'!CZ:CZ) -> 22.945 | CV11: =SUMIF('Quarterly Data'!$B:$B,'Annual Data'!$A11,'Quarterly Data'!DA:DA) -> 8.120984 | CW11: =SUMIF('Quarterly Data'!$B:$B,'Annual Data'!$A11,'Quarterly Data'!DB:DB) -> 3.9126089 | CX11: =SUMIF('Quarterly Data'!$B:$B,'Annual Data'!$A11,'Quarterly Data'!DC:DC) -> 23.336028
A12: 1978 | B12: =SUMIF('Quarterly Data'!$B:$B,'Annual Data'!$A12,'Quarterly Data'!G:G) -> 1122953 | C12: =SUMIF('Quarterly Data'!$B:$B,'Annual Data'!$A12,'Quarterly Data'!H:H) -> 574834 | D12: =SUMIF('Quarterly Data'!$B:$B,'Annual Data'!$A12,'Quarterly Data'!I:I) -> 188242 | E12: =SUMIF('Quarterly Data'!$B:$B,'Annual Data'!$A12,'Quarterly Data'!J:J) -> 280986 | F12: =SUMIF('Quarterly Data'!$B:$B,'Annual Data'!$A12,'Quarterly Data'!K:K) -> 191023 | G12: =SUMIF('Quarterly Data'!$B:$B,'Annual Data'!$A12,'Quarterly Data'!L:L) -> 151951 | H12: =SUMIF('Quarterly Data'!$B:$B,'Annual Data'!$A12,'Quarterly Data'!M:M) -> 76856.49 | I12: =SUMIF('Quarterly Data'!$B:$B,'Annual Data'!$A12,'Quarterly Data'!N:N) -> 16887.92 | J12: =AVERAGEIF('Quarterly Data'!$B:$B,'Annual Data'!$A12,'Quarterly Data'!O:O) -> 25.215303 | K12: =SUMIF('Quarterly Data'!$E:$E,'Annual Data'!$A12,'Quarterly Data'!P:P) -> 12.5 | L12: =SUMIF('Quarterly Data'!$E:$E,'Annual Data'!$A12,'Quarterly Data'!Q:Q) -> 0.001 | M12: =AVERAGEIF('Quarterly Data'!$B:$B,'Annual Data'!$A12,'Quarterly Data'!R:R) -> 25.215303 | N12: =AVERAGEIF('Quarterly Data'!$B:$B,'Annual Data'!$A12,'Quarterly Data'!S:S) -> 27074.25 | O12: =AVERAGEIF('Quarterly Data'!$B:$B,'Annual Data'!$A12,'Quarterly Data'!T:T) -> 386.00025 | P12: =AVERAGEIF('Quarterly Data'!$B:$B,'Annual Data'!$A12,'Quarterly Data'!U:U) -> 283.00025 | Q12: =AVERAGEIF('Quarterly Data'!$B:$B,'Annual Data'!$A12,'Quarterly Data'!V:V) -> 5045.7503 | R12: =AVERAGEIF('Quarterly Data'!$B:$B,'Annual Data'!$A12,'Quarterly Data'!W:W) -> 190.50025 | S12: =AVERAGEIF('Quarterly Data'!$B:$B,'Annual Data'!$A12,'Quarterly Data'!X:X) -> 116.00025 | T12: =AVERAGEIF('Quarterly Data'!$B:$B,'Annual Data'!$A12,'Quarterly Data'!Y:Y) -> 1423.5003 | U12: =AVERAGEIF('Quarterly Data'!$B:$B,'Annual Data'!$A12,'Quarterly Data'!Z:Z) -> 3009.2503 | V12: =AVERAGEIF('Quarterly Data'!$B:$B,'Annual Data'!$A12,'Quarterly Data'!AA:AA) -> 1043.2503 | W12: =AVERAGEIF('Quarterly Data'!$B:$B,'Annual Data'!$A12,'Quarterly Data'!AB:AB) -> 889.25025 | X12: =AVERAGEIF('Quarterly Data'!$B:$B,'Annual Data'!$A12,'Quarterly Data'!AC:AC) -> 587.75025 | Y12: =AVERAGEIF('Quarterly Data'!$B:$B,'Annual Data'!$A12,'Quarterly Data'!AD:AD) -> 606.25025 | Z12: =AVERAGEIF('Quarterly Data'!$B:$B,'Annual Data'!$A12,'Quarterly Data'!AE:AE) -> 125.50025 | AA12: =AVERAGEIF('Quarterly Data'!$B:$B,'Annual Data'!$A12,'Quarterly Data'!AF:AF) -> 730.00025 | AB12: =AVERAGEIF('Quarterly Data'!$B:$B,'Annual Data'!$A12,'Quarterly Data'!AG:AG) -> 806.50025 | AC12: =AVERAGEIF('Quarterly Data'!$B:$B,'Annual Data'!$A12,'Quarterly Data'!AH:AH) -> 1523.5003 | AD12: =AVERAGEIF('Quarterly Data'!$B:$B,'Annual Data'!$A12,'Quarterly Data'!AI:AI) -> 1300.7503 | AE12: =AVERAGEIF('Quarterly Data'!$B:$B,'Annual Data'!$A12,'Quarterly Data'!AJ:AJ) -> 1455.5003 | AF12: =AVERAGEIF('Quarterly Data'!$B:$B,'Annual Data'!$A12,'Quarterly Data'!AK:AK) -> 371.75025 | AG12: =AVERAGEIF('Quarterly Data'!$B:$B,'Annual Data'!$A12,'Quarterly Data'!AL:AL) -> 444.50025 | AH12: =AVERAGEIF('Quarterly Data'!$B:$B,'Annual Data'!$A12,'Quarterly Data'!AM:AM) -> 24939.75 | AI12: =AVERAGEIF('Quarterly Data'!$B:$B,'Annual Data'!$A12,'Quarterly Data'!AN:AN) -> 5400.5885 | AJ12: =SUMIF('Quarterly Data'!$B:$B,'Annual Data'!$A12,'Quarterly Data'!AO:AO) -> 1122953 | AK12: =SUMIF('Quarterly Data'!$B:$B,'Annual Data'!$A12,'Quarterly Data'!AP:AP) -> 7052.725 | AL12: =SUMIF('Quarterly Data'!$B:$B,'Annual Data'!$A12,'Quarterly Data'!AQ:AQ) -> 247036.86 | AM12: =SUMIF('Quarterly Data'!$B:$B,'Annual Data'!$A12,'Quarterly Data'!AR:AR) -> 1736.22 | AN12: =SUMIF('Quarterly Data'!$B:$B,'Annual Data'!$A12,'Quarterly Data'!AS:AS) -> 1160.514 | AO12: =SUMIF('Quarterly Data'!$B:$B,'Annual Data'!$A12,'Quarterly Data'!AT:AT) -> 1086.8867 | AP12: =SUMIF('Quarterly Data'!$B:$B,'Annual Data'!$A12,'Quarterly Data'!AU:AU) -> 844095.8 | AQ12: =SUMIF('Quarterly Data'!$B:$B,'Annual Data'!$A12,'Quarterly Data'!AV:AV) -> 8160 | AR12: =SUMIF('Quarterly Data'!$B:$B,'Annual Data'!$A12,'Quarterly Data'!AW:AW) -> 112.45 | AS12: =SUMIF('Quarterly Data'!$B:$B,'Annual Data'!$A12,'Quarterly Data'!AX:AX) -> 4369.6682 | AT12: =SUMIF('Quarterly Data'!$B:$B,'Annual Data'!$A12,'Quarterly Data'!AY:AY) -> 11741 | AU12: =SUMIF('Quarterly Data'!$B:$B,'Annual Data'!$A12,'Quarterly Data'!AZ:AZ) -> 1796 | AV12: =SUMIF('Quarterly Data'!$B:$B,'Annual Data'!$A12,'Quarterly Data'!BA:BA) -> 6.209607 | AW12: =SUMIF('Quarterly Data'!$B:$B,'Annual Data'!$A12,'Quarterly Data'!BB:BB) -> 9006.922 | AX12: =SUMIF('Quarterly Data'!$B:$B,'Annual Data'!$A12,'Quarterly Data'!BC:BC) -> 3.0644919 | AY12: =SUMIF('Quarterly Data'!$B:$B,'Annual Data'!$A12,'Quarterly Data'!BD:BD) -> 97.43532 | AZ12: =SUMIF('Quarterly Data'!$B:$B,'Annual Data'!$A12,'Quarterly Data'!BE:BE) -> 11.47025 | BA12: =SUMIF('Quarterly Data'!$B:$B,'Annual Data'!$A12,'Quarterly Data'!BF:BF) -> 3.602 | BB12: =SUMIF('Quarterly Data'!$B:$B,'Annual Data'!$A12,'Quarterly Data'!BG:BG) -> 5.478737 | BC12: =SUMIF('Quarterly Data'!$B:$B,'Annual Data'!$A12,'Quarterly Data'!BH:BH) -> 1.5524579 | BD12: =SUMIF('Quarterly Data'!$B:$B,'Annual Data'!$A12,'Quarterly Data'!BI:BI) -> 4.586899 | BE12: =SUMIF('Quarterly Data'!$B:$B,'Annual Data'!$A12,'Quarterly Data'!BJ:BJ) -> 3.6531857 | BF12: =SUMIF('Quarterly Data'!$B:$B,'Annual Data'!$A12,'Quarterly Data'!BK:BK) -> 1.1747771 | BG12: =SUMIF('Quarterly Data'!$B:$B,'Annual Data'!$A12,'Quarterly Data'!BL:BL) -> 0.193 | BH12: =SUMIF('Quarterly Data'!$B:$B,'Annual Data'!$A12,'Quarterly Data'!BM:BM) -> 0.4850401 | BI12: =SUMIF('Quarterly Data'!$B:$B,'Annual Data'!$A12,'Quarterly Data'!BN:BN) -> 0.08356642 | BJ12: =SUMIF('Quarterly Data'!$B:$B,'Annual Data'!$A12,'Quarterly Data'!BO:BO) -> 0.004 | BK12: =AVERAGEIF('Quarterly Data'!$B:$B,'Annual Data'!$A12,'Quarterly Data'!BP:BP) -> 90247.25 | BL12: =AVERAGEIF('Quarterly Data'!$B:$B,'Annual Data'!$A12,'Quarterly Data'!BQ:BQ) -> 1744.6247 | BM12: =AVERAGEIF('Quarterly Data'!$B:$B,'Annual Data'!$A12,'Quarterly Data'!BR:BR) -> 73448.5 | BN12: =AVERAGEIF('Quarterly Data'!$B:$B,'Annual Data'!$A12,'Quarterly Data'!BS:BS) -> 116244 | BO12: =AVERAGEIF('Quarterly Data'!$B:$B,'Annual Data'!$A12,'Quarterly Data'!BT:BT) -> 0.001 | BP12: =AVERAGEIF('Quarterly Data'!$B:$B,'Annual Data'!$A12,'Quarterly Data'!BU:BU) -> 167 | BQ12: =AVERAGEIF('Quarterly Data'!$B:$B,'Annual Data'!$A12,'Quarterly Data'!BV:BV) -> 131415.75 | BR12: =AVERAGEIF('Quarterly Data'!$B:$B,'Annual Data'!$A12,'Quarterly Data'!BW:BW) -> 112.16403 | BS12: =AVERAGEIF('Quarterly Data'!$B:$B,'Annual Data'!$A12,'Quarterly Data'!BX:BX) -> 4589.1987 | BT12: =AVERAGEIF('Quarterly Data'!$B:$B,'Annual Data'!$A12,'Quarterly Data'!BY:BY) -> 185.74837 | BU12: =AVERAGEIF('Quarterly Data'!$B:$B,'Annual Data'!$A12,'Quarterly Data'!BZ:BZ) -> 95.08794 | BV12: =AVERAGEIF('Quarterly Data'!$B:$B,'Annual Data'!$A12,'Quarterly Data'!CA:CA) -> 112.6275 | BW12: =AVERAGEIF('Quarterly Data'!$B:$B,'Annual Data'!$A12,'Quarterly Data'!CB:CB) -> 9.2636572 | BX12: =AVERAGEIF('Quarterly Data'!$B:$B,'Annual Data'!$A12,'Quarterly Data'!CC:CC) -> 75.231385 | BY12: =AVERAGEIF('Quarterly Data'!$B:$B,'Annual Data'!$A12,'Quarterly Data'!CD:CD) -> 58.169622 | BZ12: =AVERAGEIF('Quarterly Data'!$B:$B,'Annual Data'!$A12,'Quarterly Data'!CE:CE) -> 26.90087 | CA12: =AVERAGEIF('Quarterly Data'!$B:$B,'Annual Data'!$A12,'Quarterly Data'!CF:CF) -> 2.708318 | CB12: =AVERAGEIF('Quarterly Data'!$B:$B,'Annual Data'!$A12,'Quarterly Data'!CG:CG) -> 0.001 | CC12: =AVERAGEIF('Quarterly Data'!$B:$B,'Annual Data'!$A12,'Quarterly Data'!CH:CH) -> 1.1943337 | CD12: =AVERAGEIF('Quarterly Data'!$B:$B,'Annual Data'!$A12,'Quarterly Data'!CI:CI) -> 1.7699775 | CE12: =SUMIF('Quarterly Data'!$B:$B,'Annual Data'!$A12,'Quarterly Data'!CJ:CJ) -> 186141 | CF12: =SUMIF('Quarterly Data'!$B:$B,'Annual Data'!$A12,'Quarterly Data'!CK:CK) -> 2351.6 | CG12: =SUMIF('Quarterly Data'!$B:$B,'Annual Data'!$A12,'Quarterly Data'!CL:CL) -> 210468.72 | CH12: =SUMIF('Quarterly Data'!$B:$B,'Annual Data'!$A12,'Quarterly Data'!CM:CM) -> 252075 | CI12: =SUMIF('Quarterly Data'!$B:$B,'Annual Data'!$A12,'Quarterly Data'!CN:CN) -> 111274 | CJ12: =SUMIF('Quarterly Data'!$B:$B,'Annual Data'!$A12,'Quarterly Data'!CO:CO) -> 318.53979 | CK12: =SUMIF('Quarterly Data'!$B:$B,'Annual Data'!$A12,'Quarterly Data'!CP:CP) -> 433156.2 | CL12: =SUMIF('Quarterly Data'!$B:$B,'Annual Data'!$A12,'Quarterly Data'!CQ:CQ) -> 178.50032 | CM12: =SUMIF('Quarterly Data'!$B:$B,'Annual Data'!$A12,'Quarterly Data'!CR:CR) -> 25567.2 | CN12: =SUMIF('Quarterly Data'!$B:$B,'Annual Data'!$A12,'Quarterly Data'!CS:CS) -> 771.5664 | CO12: =SUMIF('Quarterly Data'!$B:$B,'Annual Data'!$A12,'Quarterly Data'!CT:CT) -> 345.187 | CP12: =SUMIF('Quarterly Data'!$B:$B,'Annual Data'!$A12,'Quarterly Data'!CU:CU) -> 138.022 | CQ12: =SUMIF('Quarterly Data'!$B:$B,'Annual Data'!$A12,'Quarterly Data'!CV:CV) -> 73.13707 | CR12: =SUMIF('Quarterly Data'!$B:$B,'Annual Data'!$A12,'Quarterly Data'!CW:CW) -> 153.722 | CS12: =SUMIF('Quarterly Data'!$B:$B,'Annual Data'!$A12,'Quarterly Data'!CX:CX) -> 77.72558 | CT12: =SUMIF('Quarterly Data'!$B:$B,'Annual Data'!$A12,'Quarterly Data'!CY:CY) -> 52.79484 | CU12: =SUMIF('Quarterly Data'!$B:$B,'Annual Data'!$A12,'Quarterly Data'!CZ:CZ) -> 25.397 | CV12: =SUMIF('Quarterly Data'!$B:$B,'Annual Data'!$A12,'Quarterly Data'!DA:DA) -> 9.598186 | CW12: =SUMIF('Quarterly Data'!$B:$B,'Annual Data'!$A12,'Quarterly Data'!DB:DB) -> 4.773899 | CX12: =SUMIF('Quarterly Data'!$B:$B,'Annual Data'!$A12,'Quarterly Data'!DC:DC) -> 23.336028
A13: 1979 | B13: =SUMIF('Quarterly Data'!$B:$B,'Annual Data'!$A13,'Quarterly Data'!G:G) -> 1164860 | C13: =SUMIF('Quarterly Data'!$B:$B,'Annual Data'!$A13,'Quarterly Data'!H:H) -> 602077 | D13: =SUMIF('Quarterly Data'!$B:$B,'Annual Data'!$A13,'Quarterly Data'!I:I) -> 204441 | E13: =SUMIF('Quarterly Data'!$B:$B,'Annual Data'!$A13,'Quarterly Data'!J:J) -> 285273 | F13: =SUMIF('Quarterly Data'!$B:$B,'Annual Data'!$A13,'Quarterly Data'!K:K) -> 197826 | G13: =SUMIF('Quarterly Data'!$B:$B,'Annual Data'!$A13,'Quarterly Data'!L:L) -> 166088 | H13: =SUMIF('Quarterly Data'!$B:$B,'Annual Data'!$A13,'Quarterly Data'!M:M) -> 79458.24 | I13: =SUMIF('Quarterly Data'!$B:$B,'Annual Data'!$A13,'Quarterly Data'!N:N) -> 16246.718 | J13: =AVERAGEIF('Quarterly Data'!$B:$B,'Annual Data'!$A13,'Quarterly Data'!O:O) -> 28.082898 | K13: =SUMIF('Quarterly Data'!$E:$E,'Annual Data'!$A13,'Quarterly Data'!P:P) -> 17 | L13: =SUMIF('Quarterly Data'!$E:$E,'Annual Data'!$A13,'Quarterly Data'!Q:Q) -> 0.001 | M13: =AVERAGEIF('Quarterly Data'!$B:$B,'Annual Data'!$A13,'Quarterly Data'!R:R) -> 28.082898 | N13: =AVERAGEIF('Quarterly Data'!$B:$B,'Annual Data'!$A13,'Quarterly Data'!S:S) -> 27437.75 | O13: =AVERAGEIF('Quarterly Data'!$B:$B,'Annual Data'!$A13,'Quarterly Data'!T:T) -> 509.25 | P13: =AVERAGEIF('Quarterly Data'!$B:$B,'Annual Data'!$A13,'Quarterly Data'!U:U) -> 373.75 | Q13: =AVERAGEIF('Quarterly Data'!$B:$B,'Annual Data'!$A13,'Quarterly Data'!V:V) -> 6681 | R13: =AVERAGEIF('Quarterly Data'!$B:$B,'Annual Data'!$A13,'Quarterly Data'!W:W) -> 258.25 | S13: =AVERAGEIF('Quarterly Data'!$B:$B,'Annual Data'!$A13,'Quarterly Data'!X:X) -> 156.75 | T13: =AVERAGEIF('Quarterly Data'!$B:$B,'Annual Data'!$A13,'Quarterly Data'!Y:Y) -> 1938.75 | U13: =AVERAGEIF('Quarterly Data'!$B:$B,'Annual Data'!$A13,'Quarterly Data'!Z:Z) -> 4114.25 | V13: =AVERAGEIF('Quarterly Data'!$B:$B,'Annual Data'!$A13,'Quarterly Data'!AA:AA) -> 1400.75 | W13: =AVERAGEIF('Quarterly Data'!$B:$B,'Annual Data'!$A13,'Quarterly Data'!AB:AB) -> 1231.75 | X13: =AVERAGEIF('Quarterly Data'!$B:$B,'Annual Data'!$A13,'Quarterly Data'!AC:AC) -> 791.75 | Y13: =AVERAGEIF('Quarterly Data'!$B:$B,'Annual Data'!$A13,'Quarterly Data'!AD:AD) -> 831.25 | Z13: =AVERAGEIF('Quarterly Data'!$B:$B,'Annual Data'!$A13,'Quarterly Data'!AE:AE) -> 172.5 | AA13: =AVERAGEIF('Quarterly Data'!$B:$B,'Annual Data'!$A13,'Quarterly Data'!AF:AF) -> 1004.25 | AB13: =AVERAGEIF('Quarterly Data'!$B:$B,'Annual Data'!$A13,'Quarterly Data'!AG:AG) -> 1106 | AC13: =AVERAGEIF('Quarterly Data'!$B:$B,'Annual Data'!$A13,'Quarterly Data'!AH:AH) -> 2013.25 | AD13: =AVERAGEIF('Quarterly Data'!$B:$B,'Annual Data'!$A13,'Quarterly Data'!AI:AI) -> 1755.75 | AE13: =AVERAGEIF('Quarterly Data'!$B:$B,'Annual Data'!$A13,'Quarterly Data'!AJ:AJ) -> 1986.25 | AF13: =AVERAGEIF('Quarterly Data'!$B:$B,'Annual Data'!$A13,'Quarterly Data'!AK:AK) -> 506.5 | AG13: =AVERAGEIF('Quarterly Data'!$B:$B,'Annual Data'!$A13,'Quarterly Data'!AL:AL) -> 605.25 | AH13: =AVERAGEIF('Quarterly Data'!$B:$B,'Annual Data'!$A13,'Quarterly Data'!AM:AM) -> 25195.25 | AI13: =AVERAGEIF('Quarterly Data'!$B:$B,'Annual Data'!$A13,'Quarterly Data'!AN:AN) -> 5459.8205 | AJ13: =SUMIF('Quarterly Data'!$B:$B,'Annual Data'!$A13,'Quarterly Data'!AO:AO) -> 1164860 | AK13: =SUMIF('Quarterly Data'!$B:$B,'Annual Data'!$A13,'Quarterly Data'!AP:AP) -> 7276 | AL13: =SUMIF('Quarterly Data'!$B:$B,'Annual Data'!$A13,'Quarterly Data'!AQ:AQ) -> 261577.77 | AM13: =SUMIF('Quarterly Data'!$B:$B,'Annual Data'!$A13,'Quarterly Data'!AR:AR) -> 1810.62 | AN13: =SUMIF('Quarterly Data'!$B:$B,'Annual Data'!$A13,'Quarterly Data'!AS:AS) -> 1203.514 | AO13: =SUMIF('Quarterly Data'!$B:$B,'Annual Data'!$A13,'Quarterly Data'!AT:AT) -> 1147.0066 | AP13: =SUMIF('Quarterly Data'!$B:$B,'Annual Data'!$A13,'Quarterly Data'!AU:AU) -> 875540.1 | AQ13: =SUMIF('Quarterly Data'!$B:$B,'Annual Data'!$A13,'Quarterly Data'!AV:AV) -> 9791 | AR13: =SUMIF('Quarterly Data'!$B:$B,'Annual Data'!$A13,'Quarterly Data'!AW:AW) -> 128.475 | AS13: =SUMIF('Quarterly Data'!$B:$B,'Annual Data'!$A13,'Quarterly Data'!AX:AX) -> 5571.224 | AT13: =SUMIF('Quarterly Data'!$B:$B,'Annual Data'!$A13,'Quarterly Data'!AY:AY) -> 14057 | AU13: =SUMIF('Quarterly Data'!$B:$B,'Annual Data'!$A13,'Quarterly Data'!AZ:AZ) -> 2136 | AV13: =SUMIF('Quarterly Data'!$B:$B,'Annual Data'!$A13,'Quarterly Data'!BA:BA) -> 11.05835 | AW13: =SUMIF('Quarterly Data'!$B:$B,'Annual Data'!$A13,'Quarterly Data'!BB:BB) -> 11487.632 | AX13: =SUMIF('Quarterly Data'!$B:$B,'Annual Data'!$A13,'Quarterly Data'!BC:BC) -> 2.9711764 | AY13: =SUMIF('Quarterly Data'!$B:$B,'Annual Data'!$A13,'Quarterly Data'!BD:BD) -> 116.51299 | AZ13: =SUMIF('Quarterly Data'!$B:$B,'Annual Data'!$A13,'Quarterly Data'!BE:BE) -> 13.17 | BA13: =SUMIF('Quarterly Data'!$B:$B,'Annual Data'!$A13,'Quarterly Data'!BF:BF) -> 4.516 | BB13: =SUMIF('Quarterly Data'!$B:$B,'Annual Data'!$A13,'Quarterly Data'!BG:BG) -> 6.615404 | BC13: =SUMIF('Quarterly Data'!$B:$B,'Annual Data'!$A13,'Quarterly Data'!BH:BH) -> 1.2236236 | BD13: =SUMIF('Quarterly Data'!$B:$B,'Annual Data'!$A13,'Quarterly Data'!BI:BI) -> 5.1364 | BE13: =SUMIF('Quarterly Data'!$B:$B,'Annual Data'!$A13,'Quarterly Data'!BJ:BJ) -> 4.450091 | BF13: =SUMIF('Quarterly Data'!$B:$B,'Annual Data'!$A13,'Quarterly Data'!BK:BK) -> 1.3517846 | BG13: =SUMIF('Quarterly Data'!$B:$B,'Annual Data'!$A13,'Quarterly Data'!BL:BL) -> 0.258 | BH13: =SUMIF('Quarterly Data'!$B:$B,'Annual Data'!$A13,'Quarterly Data'!BM:BM) -> 0.60186 | BI13: =SUMIF('Quarterly Data'!$B:$B,'Annual Data'!$A13,'Quarterly Data'!BN:BN) -> 0.12055573 | BJ13: =SUMIF('Quarterly Data'!$B:$B,'Annual Data'!$A13,'Quarterly Data'!BO:BO) -> 0.004 | BK13: =AVERAGEIF('Quarterly Data'!$B:$B,'Annual Data'!$A13,'Quarterly Data'!BP:BP) -> 100769 | BL13: =AVERAGEIF('Quarterly Data'!$B:$B,'Annual Data'!$A13,'Quarterly Data'!BQ:BQ) -> 1884.0862 | BM13: =AVERAGEIF('Quarterly Data'!$B:$B,'Annual Data'!$A13,'Quarterly Data'!BR:BR) -> 92658.5 | BN13: =AVERAGEIF('Quarterly Data'!$B:$B,'Annual Data'!$A13,'Quarterly Data'!BS:BS) -> 129158 | BO13: =AVERAGEIF('Quarterly Data'!$B:$B,'Annual Data'!$A13,'Quarterly Data'!BT:BT) -> 0.001 | BP13: =AVERAGEIF('Quarterly Data'!$B:$B,'Annual Data'!$A13,'Quarterly Data'!BU:BU) -> 167 | BQ13: =AVERAGEIF('Quarterly Data'!$B:$B,'Annual Data'!$A13,'Quarterly Data'!BV:BV) -> 168921.7 | BR13: =AVERAGEIF('Quarterly Data'!$B:$B,'Annual Data'!$A13,'Quarterly Data'!BW:BW) -> 115.348 | BS13: =AVERAGEIF('Quarterly Data'!$B:$B,'Annual Data'!$A13,'Quarterly Data'!BX:BX) -> 5436.1985 | BT13: =AVERAGEIF('Quarterly Data'!$B:$B,'Annual Data'!$A13,'Quarterly Data'!BY:BY) -> 207.78315 | BU13: =AVERAGEIF('Quarterly Data'!$B:$B,'Annual Data'!$A13,'Quarterly Data'!BZ:BZ) -> 110.13255 | BV13: =AVERAGEIF('Quarterly Data'!$B:$B,'Annual Data'!$A13,'Quarterly Data'!CA:CA) -> 137.25962 | BW13: =AVERAGEIF('Quarterly Data'!$B:$B,'Annual Data'!$A13,'Quarterly Data'!CB:CB) -> 12.01153 | BX13: =AVERAGEIF('Quarterly Data'!$B:$B,'Annual Data'!$A13,'Quarterly Data'!CC:CC) -> 84.241727 | BY13: =AVERAGEIF('Quarterly Data'!$B:$B,'Annual Data'!$A13,'Quarterly Data'!CD:CD) -> 65.3848 | BZ13: =AVERAGEIF('Quarterly Data'!$B:$B,'Annual Data'!$A13,'Quarterly Data'!CE:CE) -> 31.460223 | CA13: =AVERAGEIF('Quarterly Data'!$B:$B,'Annual Data'!$A13,'Quarterly Data'!CF:CF) -> 3.534977 | CB13: =AVERAGEIF('Quarterly Data'!$B:$B,'Annual Data'!$A13,'Quarterly Data'!CG:CG) -> 0.001 | CC13: =AVERAGEIF('Quarterly Data'!$B:$B,'Annual Data'!$A13,'Quarterly Data'!CH:CH) -> 1.3802763 | CD13: =AVERAGEIF('Quarterly Data'!$B:$B,'Annual Data'!$A13,'Quarterly Data'!CI:CI) -> 1.814181 | CE13: =SUMIF('Quarterly Data'!$B:$B,'Annual Data'!$A13,'Quarterly Data'!CJ:CJ) -> 220966 | CF13: =SUMIF('Quarterly Data'!$B:$B,'Annual Data'!$A13,'Quarterly Data'!CK:CK) -> 2627.325 | CG13: =SUMIF('Quarterly Data'!$B:$B,'Annual Data'!$A13,'Quarterly Data'!CL:CL) -> 227860.58 | CH13: =SUMIF('Quarterly Data'!$B:$B,'Annual Data'!$A13,'Quarterly Data'!CM:CM) -> 287608 | CI13: =SUMIF('Quarterly Data'!$B:$B,'Annual Data'!$A13,'Quarterly Data'!CN:CN) -> 126793 | CJ13: =SUMIF('Quarterly Data'!$B:$B,'Annual Data'!$A13,'Quarterly Data'!CO:CO) -> 354.87279 | CK13: =SUMIF('Quarterly Data'!$B:$B,'Annual Data'!$A13,'Quarterly Data'!CP:CP) -> 485518.4 | CL13: =SUMIF('Quarterly Data'!$B:$B,'Annual Data'!$A13,'Quarterly Data'!CQ:CQ) -> 186.58537 | CM13: =SUMIF('Quarterly Data'!$B:$B,'Annual Data'!$A13,'Quarterly Data'!CR:CR) -> 32952.6 | CN13: =SUMIF('Quarterly Data'!$B:$B,'Annual Data'!$A13,'Quarterly Data'!CS:CS) -> 839.0251 | CO13: =SUMIF('Quarterly Data'!$B:$B,'Annual Data'!$A13,'Quarterly Data'!CT:CT) -> 394.491 | CP13: =SUMIF('Quarterly Data'!$B:$B,'Annual Data'!$A13,'Quarterly Data'!CU:CU) -> 168.884 | CQ13: =SUMIF('Quarterly Data'!$B:$B,'Annual Data'!$A13,'Quarterly Data'!CV:CV) -> 85.64545 | CR13: =SUMIF('Quarterly Data'!$B:$B,'Annual Data'!$A13,'Quarterly Data'!CW:CW) -> 162.967 | CS13: =SUMIF('Quarterly Data'!$B:$B,'Annual Data'!$A13,'Quarterly Data'!CX:CX) -> 83.00248 | CT13: =SUMIF('Quarterly Data'!$B:$B,'Annual Data'!$A13,'Quarterly Data'!CY:CY) -> 57.62086 | CU13: =SUMIF('Quarterly Data'!$B:$B,'Annual Data'!$A13,'Quarterly Data'!CZ:CZ) -> 29.405 | CV13: =SUMIF('Quarterly Data'!$B:$B,'Annual Data'!$A13,'Quarterly Data'!DA:DA) -> 11.370012 | CW13: =SUMIF('Quarterly Data'!$B:$B,'Annual Data'!$A13,'Quarterly Data'!DB:DB) -> 5.924302 | CX13: =SUMIF('Quarterly Data'!$B:$B,'Annual Data'!$A13,'Quarterly Data'!DC:DC) -> 23.336028
A14: 1980 | B14: =SUMIF('Quarterly Data'!$B:$B,'Annual Data'!$A14,'Quarterly Data'!G:G) -> 1140989 | C14: =SUMIF('Quarterly Data'!$B:$B,'Annual Data'!$A14,'Quarterly Data'!H:H) -> 602808 | D14: =SUMIF('Quarterly Data'!$B:$B,'Annual Data'!$A14,'Quarterly Data'!I:I) -> 191286 | E14: =SUMIF('Quarterly Data'!$B:$B,'Annual Data'!$A14,'Quarterly Data'!J:J) -> 288533 | F14: =SUMIF('Quarterly Data'!$B:$B,'Annual Data'!$A14,'Quarterly Data'!K:K) -> 196809 | G14: =SUMIF('Quarterly Data'!$B:$B,'Annual Data'!$A14,'Quarterly Data'!L:L) -> 160180 | H14: =SUMIF('Quarterly Data'!$B:$B,'Annual Data'!$A14,'Quarterly Data'!M:M) -> 76034.43 | I14: =SUMIF('Quarterly Data'!$B:$B,'Annual Data'!$A14,'Quarterly Data'!N:N) -> 14104.645 | J14: =AVERAGEIF('Quarterly Data'!$B:$B,'Annual Data'!$A14,'Quarterly Data'!O:O) -> 32.338673 | K14: =SUMIF('Quarterly Data'!$E:$E,'Annual Data'!$A14,'Quarterly Data'!P:P) -> 14 | L14: =SUMIF('Quarterly Data'!$E:$E,'Annual Data'!$A14,'Quarterly Data'!Q:Q) -> 0.001 | M14: =AVERAGEIF('Quarterly Data'!$B:$B,'Annual Data'!$A14,'Quarterly Data'!R:R) -> 32.338673 | N14: =AVERAGEIF('Quarterly Data'!$B:$B,'Annual Data'!$A14,'Quarterly Data'!S:S) -> 27188.75 | O14: =AVERAGEIF('Quarterly Data'!$B:$B,'Annual Data'!$A14,'Quarterly Data'!T:T) -> 508.75 | P14: =AVERAGEIF('Quarterly Data'!$B:$B,'Annual Data'!$A14,'Quarterly Data'!U:U) -> 366.25 | Q14: =AVERAGEIF('Quarterly Data'!$B:$B,'Annual Data'!$A14,'Quarterly Data'!V:V) -> 6309.25 | R14: =AVERAGEIF('Quarterly Data'!$B:$B,'Annual Data'!$A14,'Quarterly Data'!W:W) -> 260.5 | S14: =AVERAGEIF('Quarterly Data'!$B:$B,'Annual Data'!$A14,'Quarterly Data'!X:X) -> 155 | T14: =AVERAGEIF('Quarterly Data'!$B:$B,'Annual Data'!$A14,'Quarterly Data'!Y:Y) -> 1949 | U14: =AVERAGEIF('Quarterly Data'!$B:$B,'Annual Data'!$A14,'Quarterly Data'!Z:Z) -> 4113.75 | V14: =AVERAGEIF('Quarterly Data'!$B:$B,'Annual Data'!$A14,'Quarterly Data'!AA:AA) -> 1399 | W14: =AVERAGEIF('Quarterly Data'!$B:$B,'Annual Data'!$A14,'Quarterly Data'!AB:AB) -> 1260.25 | X14: =AVERAGEIF('Quarterly Data'!$B:$B,'Annual Data'!$A14,'Quarterly Data'!AC:AC) -> 780.5 | Y14: =AVERAGEIF('Quarterly Data'!$B:$B,'Annual Data'!$A14,'Quarterly Data'!AD:AD) -> 865.75 | Z14: =AVERAGEIF('Quarterly Data'!$B:$B,'Annual Data'!$A14,'Quarterly Data'!AE:AE) -> 176.75 | AA14: =AVERAGEIF('Quarterly Data'!$B:$B,'Annual Data'!$A14,'Quarterly Data'!AF:AF) -> 1027.5 | AB14: =AVERAGEIF('Quarterly Data'!$B:$B,'Annual Data'!$A14,'Quarterly Data'!AG:AG) -> 1120.5 | AC14: =AVERAGEIF('Quarterly Data'!$B:$B,'Annual Data'!$A14,'Quarterly Data'!AH:AH) -> 1984.5 | AD14: =AVERAGEIF('Quarterly Data'!$B:$B,'Annual Data'!$A14,'Quarterly Data'!AI:AI) -> 1737.5 | AE14: =AVERAGEIF('Quarterly Data'!$B:$B,'Annual Data'!$A14,'Quarterly Data'!AJ:AJ) -> 2051 | AF14: =AVERAGEIF('Quarterly Data'!$B:$B,'Annual Data'!$A14,'Quarterly Data'!AK:AK) -> 511 | AG14: =AVERAGEIF('Quarterly Data'!$B:$B,'Annual Data'!$A14,'Quarterly Data'!AL:AL) -> 611.75 | AH14: =AVERAGEIF('Quarterly Data'!$B:$B,'Annual Data'!$A14,'Quarterly Data'!AM:AM) -> 25086.25 | AI14: =AVERAGEIF('Quarterly Data'!$B:$B,'Annual Data'!$A14,'Quarterly Data'!AN:AN) -> 5454.0342 | AJ14: =SUMIF('Quarterly Data'!$B:$B,'Annual Data'!$A14,'Quarterly Data'!AO:AO) -> 1140989 | AK14: =SUMIF('Quarterly Data'!$B:$B,'Annual Data'!$A14,'Quarterly Data'!AP:AP) -> 7257.325 | AL14: =SUMIF('Quarterly Data'!$B:$B,'Annual Data'!$A14,'Quarterly Data'!AQ:AQ) -> 272992.43 | AM14: =SUMIF('Quarterly Data'!$B:$B,'Annual Data'!$A14,'Quarterly Data'!AR:AR) -> 1833.95 | AN14: =SUMIF('Quarterly Data'!$B:$B,'Annual Data'!$A14,'Quarterly Data'!AS:AS) -> 1223.307 | AO14: =SUMIF('Quarterly Data'!$B:$B,'Annual Data'!$A14,'Quarterly Data'!AT:AT) -> 1186.9547 | AP14: =SUMIF('Quarterly Data'!$B:$B,'Annual Data'!$A14,'Quarterly Data'!AU:AU) -> 894602.4 | AQ14: =SUMIF('Quarterly Data'!$B:$B,'Annual Data'!$A14,'Quarterly Data'!AV:AV) -> 11972 | AR14: =SUMIF('Quarterly Data'!$B:$B,'Annual Data'!$A14,'Quarterly Data'!AW:AW) -> 148.775 | AS14: =SUMIF('Quarterly Data'!$B:$B,'Annual Data'!$A14,'Quarterly Data'!AX:AX) -> 7259.869 | AT14: =SUMIF('Quarterly Data'!$B:$B,'Annual Data'!$A14,'Quarterly Data'!AY:AY) -> 17033 | AU14: =SUMIF('Quarterly Data'!$B:$B,'Annual Data'!$A14,'Quarterly Data'!AZ:AZ) -> 2396 | AV14: =SUMIF('Quarterly Data'!$B:$B,'Annual Data'!$A14,'Quarterly Data'!BA:BA) -> 13.371521 | AW14: =SUMIF('Quarterly Data'!$B:$B,'Annual Data'!$A14,'Quarterly Data'!BB:BB) -> 16780.388 | AX14: =SUMIF('Quarterly Data'!$B:$B,'Annual Data'!$A14,'Quarterly Data'!BC:BC) -> 3.154236 | AY14: =SUMIF('Quarterly Data'!$B:$B,'Annual Data'!$A14,'Quarterly Data'!BD:BD) -> 177.92179 | AZ14: =SUMIF('Quarterly Data'!$B:$B,'Annual Data'!$A14,'Quarterly Data'!BE:BE) -> 16.739999 | BA14: =SUMIF('Quarterly Data'!$B:$B,'Annual Data'!$A14,'Quarterly Data'!BF:BF) -> 5.516 | BB14: =SUMIF('Quarterly Data'!$B:$B,'Annual Data'!$A14,'Quarterly Data'!BG:BG) -> 8.897634 | BC14: =SUMIF('Quarterly Data'!$B:$B,'Annual Data'!$A14,'Quarterly Data'!BH:BH) -> 2.7622091 | BD14: =SUMIF('Quarterly Data'!$B:$B,'Annual Data'!$A14,'Quarterly Data'!BI:BI) -> 6.1832 | BE14: =SUMIF('Quarterly Data'!$B:$B,'Annual Data'!$A14,'Quarterly Data'!BJ:BJ) -> 5.521848 | BF14: =SUMIF('Quarterly Data'!$B:$B,'Annual Data'!$A14,'Quarterly Data'!BK:BK) -> 1.5851578 | BG14: =SUMIF('Quarterly Data'!$B:$B,'Annual Data'!$A14,'Quarterly Data'!BL:BL) -> 0.322 | BH14: =SUMIF('Quarterly Data'!$B:$B,'Annual Data'!$A14,'Quarterly Data'!BM:BM) -> 0.76311 | BI14: =SUMIF('Quarterly Data'!$B:$B,'Annual Data'!$A14,'Quarterly Data'!BN:BN) -> 0.15690816 | BJ14: =SUMIF('Quarterly Data'!$B:$B,'Annual Data'!$A14,'Quarterly Data'!BO:BO) -> 0.004 | BK14: =AVERAGEIF('Quarterly Data'!$B:$B,'Annual Data'!$A14,'Quarterly Data'!BP:BP) -> 114520.15 | BL14: =AVERAGEIF('Quarterly Data'!$B:$B,'Annual Data'!$A14,'Quarterly Data'!BQ:BQ) -> 2033.236 | BM14: =AVERAGEIF('Quarterly Data'!$B:$B,'Annual Data'!$A14,'Quarterly Data'!BR:BR) -> 110458.5 | BN14: =AVERAGEIF('Quarterly Data'!$B:$B,'Annual Data'!$A14,'Quarterly Data'!BS:BS) -> 143750.5 | BO14: =AVERAGEIF('Quarterly Data'!$B:$B,'Annual Data'!$A14,'Quarterly Data'!BT:BT) -> 0.001 | BP14: =AVERAGEIF('Quarterly Data'!$B:$B,'Annual Data'!$A14,'Quarterly Data'!BU:BU) -> 169.644 | BQ14: =AVERAGEIF('Quarterly Data'!$B:$B,'Annual Data'!$A14,'Quarterly Data'!BV:BV) -> 232544.5 | BR14: =AVERAGEIF('Quarterly Data'!$B:$B,'Annual Data'!$A14,'Quarterly Data'!BW:BW) -> 118.344 | BS14: =AVERAGEIF('Quarterly Data'!$B:$B,'Annual Data'!$A14,'Quarterly Data'!BX:BX) -> 8205.118 | BT14: =AVERAGEIF('Quarterly Data'!$B:$B,'Annual Data'!$A14,'Quarterly Data'!BY:BY) -> 235.3103 | BU14: =AVERAGEIF('Quarterly Data'!$B:$B,'Annual Data'!$A14,'Quarterly Data'!BZ:BZ) -> 124.10612 | BV14: =AVERAGEIF('Quarterly Data'!$B:$B,'Annual Data'!$A14,'Quarterly Data'!CA:CA) -> 166.63163 | BW14: =AVERAGEIF('Quarterly Data'!$B:$B,'Annual Data'!$A14,'Quarterly Data'!CB:CB) -> 21.800147 | BX14: =AVERAGEIF('Quarterly Data'!$B:$B,'Annual Data'!$A14,'Quarterly Data'!CC:CC) -> 94.747028 | BY14: =AVERAGEIF('Quarterly Data'!$B:$B,'Annual Data'!$A14,'Quarterly Data'!CD:CD) -> 77.260018 | BZ14: =AVERAGEIF('Quarterly Data'!$B:$B,'Annual Data'!$A14,'Quarterly Data'!CE:CE) -> 35.7402 | CA14: =AVERAGEIF('Quarterly Data'!$B:$B,'Annual Data'!$A14,'Quarterly Data'!CF:CF) -> 4.0790713 | CB14: =AVERAGEIF('Quarterly Data'!$B:$B,'Annual Data'!$A14,'Quarterly Data'!CG:CG) -> 7.245103 | CC14: =AVERAGEIF('Quarterly Data'!$B:$B,'Annual Data'!$A14,'Quarterly Data'!CH:CH) -> 1.6575215 | CD14: =AVERAGEIF('Quarterly Data'!$B:$B,'Annual Data'!$A14,'Quarterly Data'!CI:CI) -> 2.6170658 | CE14: =SUMIF('Quarterly Data'!$B:$B,'Annual Data'!$A14,'Quarterly Data'!CJ:CJ) -> 259956 | CF14: =SUMIF('Quarterly Data'!$B:$B,'Annual Data'!$A14,'Quarterly Data'!CK:CK) -> 2857.325 | CG14: =SUMIF('Quarterly Data'!$B:$B,'Annual Data'!$A14,'Quarterly Data'!CL:CL) -> 255596.35 | CH14: =SUMIF('Quarterly Data'!$B:$B,'Annual Data'!$A14,'Quarterly Data'!CM:CM) -> 322782 | CI14: =SUMIF('Quarterly Data'!$B:$B,'Annual Data'!$A14,'Quarterly Data'!CN:CN) -> 143163 | CJ14: =SUMIF('Quarterly Data'!$B:$B,'Annual Data'!$A14,'Quarterly Data'!CO:CO) -> 382.38443 | CK14: =SUMIF('Quarterly Data'!$B:$B,'Annual Data'!$A14,'Quarterly Data'!CP:CP) -> 593060.9 | CL14: =SUMIF('Quarterly Data'!$B:$B,'Annual Data'!$A14,'Quarterly Data'!CQ:CQ) -> 205.21645 | CM14: =SUMIF('Quarterly Data'!$B:$B,'Annual Data'!$A14,'Quarterly Data'!CR:CR) -> 40423.4 | CN14: =SUMIF('Quarterly Data'!$B:$B,'Annual Data'!$A14,'Quarterly Data'!CS:CS) -> 896.4522 | CO14: =SUMIF('Quarterly Data'!$B:$B,'Annual Data'!$A14,'Quarterly Data'!CT:CT) -> 447.345 | CP14: =SUMIF('Quarterly Data'!$B:$B,'Annual Data'!$A14,'Quarterly Data'!CU:CU) -> 217.501 | CQ14: =SUMIF('Quarterly Data'!$B:$B,'Annual Data'!$A14,'Quarterly Data'!CV:CV) -> 100.07811 | CR14: =SUMIF('Quarterly Data'!$B:$B,'Annual Data'!$A14,'Quarterly Data'!CW:CW) -> 174.826 | CS14: =SUMIF('Quarterly Data'!$B:$B,'Annual Data'!$A14,'Quarterly Data'!CX:CX) -> 89.06 | CT14: =SUMIF('Quarterly Data'!$B:$B,'Annual Data'!$A14,'Quarterly Data'!CY:CY) -> 61.74276 | CU14: =SUMIF('Quarterly Data'!$B:$B,'Annual Data'!$A14,'Quarterly Data'!CZ:CZ) -> 33.936 | CV14: =SUMIF('Quarterly Data'!$B:$B,'Annual Data'!$A14,'Quarterly Data'!DA:DA) -> 13.492743 | CW14: =SUMIF('Quarterly Data'!$B:$B,'Annual Data'!$A14,'Quarterly Data'!DB:DB) -> 7.112914 | CX14: =SUMIF('Quarterly Data'!$B:$B,'Annual Data'!$A14,'Quarterly Data'!DC:DC) -> 23.336028
A15: 1981 | B15: =SUMIF('Quarterly Data'!$B:$B,'Annual Data'!$A15,'Quarterly Data'!G:G) -> 1134663 | C15: =SUMIF('Quarterly Data'!$B:$B,'Annual Data'!$A15,'Quarterly Data'!H:H) -> 604520 | D15: =SUMIF('Quarterly Data'!$B:$B,'Annual Data'!$A15,'Quarterly Data'!I:I) -> 179837 | E15: =SUMIF('Quarterly Data'!$B:$B,'Annual Data'!$A15,'Quarterly Data'!J:J) -> 288235 | F15: =SUMIF('Quarterly Data'!$B:$B,'Annual Data'!$A15,'Quarterly Data'!K:K) -> 195618 | G15: =SUMIF('Quarterly Data'!$B:$B,'Annual Data'!$A15,'Quarterly Data'!L:L) -> 155614 | H15: =SUMIF('Quarterly Data'!$B:$B,'Annual Data'!$A15,'Quarterly Data'!M:M) -> 70554.62 | I15: =SUMIF('Quarterly Data'!$B:$B,'Annual Data'!$A15,'Quarterly Data'!N:N) -> 10317.83 | J15: =AVERAGEIF('Quarterly Data'!$B:$B,'Annual Data'!$A15,'Quarterly Data'!O:O) -> 36.157795 | K15: =SUMIF('Quarterly Data'!$E:$E,'Annual Data'!$A15,'Quarterly Data'!P:P) -> 14.375 | L15: =SUMIF('Quarterly Data'!$E:$E,'Annual Data'!$A15,'Quarterly Data'!Q:Q) -> 0.001 | M15: =AVERAGEIF('Quarterly Data'!$B:$B,'Annual Data'!$A15,'Quarterly Data'!R:R) -> 36.157795 | N15: =AVERAGEIF('Quarterly Data'!$B:$B,'Annual Data'!$A15,'Quarterly Data'!S:S) -> 26296.25 | O15: =AVERAGEIF('Quarterly Data'!$B:$B,'Annual Data'!$A15,'Quarterly Data'!T:T) -> 491 | P15: =AVERAGEIF('Quarterly Data'!$B:$B,'Annual Data'!$A15,'Quarterly Data'!U:U) -> 344.25 | Q15: =AVERAGEIF('Quarterly Data'!$B:$B,'Annual Data'!$A15,'Quarterly Data'!V:V) -> 5758 | R15: =AVERAGEIF('Quarterly Data'!$B:$B,'Annual Data'!$A15,'Quarterly Data'!W:W) -> 256.75 | S15: =AVERAGEIF('Quarterly Data'!$B:$B,'Annual Data'!$A15,'Quarterly Data'!X:X) -> 149.75 | T15: =AVERAGEIF('Quarterly Data'!$B:$B,'Annual Data'!$A15,'Quarterly Data'!Y:Y) -> 1846.5 | U15: =AVERAGEIF('Quarterly Data'!$B:$B,'Annual Data'!$A15,'Quarterly Data'!Z:Z) -> 4026.5 | V15: =AVERAGEIF('Quarterly Data'!$B:$B,'Annual Data'!$A15,'Quarterly Data'!AA:AA) -> 1354.75 | W15: =AVERAGEIF('Quarterly Data'!$B:$B,'Annual Data'!$A15,'Quarterly Data'!AB:AB) -> 1247 | X15: =AVERAGEIF('Quarterly Data'!$B:$B,'Annual Data'!$A15,'Quarterly Data'!AC:AC) -> 748.75 | Y15: =AVERAGEIF('Quarterly Data'!$B:$B,'Annual Data'!$A15,'Quarterly Data'!AD:AD) -> 876.5 | Z15: =AVERAGEIF('Quarterly Data'!$B:$B,'Annual Data'!$A15,'Quarterly Data'!AE:AE) -> 177.5 | AA15: =AVERAGEIF('Quarterly Data'!$B:$B,'Annual Data'!$A15,'Quarterly Data'!AF:AF) -> 1028.25 | AB15: =AVERAGEIF('Quarterly Data'!$B:$B,'Annual Data'!$A15,'Quarterly Data'!AG:AG) -> 1105 | AC15: =AVERAGEIF('Quarterly Data'!$B:$B,'Annual Data'!$A15,'Quarterly Data'!AH:AH) -> 1952.75 | AD15: =AVERAGEIF('Quarterly Data'!$B:$B,'Annual Data'!$A15,'Quarterly Data'!AI:AI) -> 1712.5 | AE15: =AVERAGEIF('Quarterly Data'!$B:$B,'Annual Data'!$A15,'Quarterly Data'!AJ:AJ) -> 2100.5 | AF15: =AVERAGEIF('Quarterly Data'!$B:$B,'Annual Data'!$A15,'Quarterly Data'!AK:AK) -> 509.25 | AG15: =AVERAGEIF('Quarterly Data'!$B:$B,'Annual Data'!$A15,'Quarterly Data'!AL:AL) -> 611.5 | AH15: =AVERAGEIF('Quarterly Data'!$B:$B,'Annual Data'!$A15,'Quarterly Data'!AM:AM) -> 24430 | AI15: =AVERAGEIF('Quarterly Data'!$B:$B,'Annual Data'!$A15,'Quarterly Data'!AN:AN) -> 5432.0065 | AJ15: =SUMIF('Quarterly Data'!$B:$B,'Annual Data'!$A15,'Quarterly Data'!AO:AO) -> 1134663 | AK15: =SUMIF('Quarterly Data'!$B:$B,'Annual Data'!$A15,'Quarterly Data'!AP:AP) -> 7441.475 | AL15: =SUMIF('Quarterly Data'!$B:$B,'Annual Data'!$A15,'Quarterly Data'!AQ:AQ) -> 284947.89 | AM15: =SUMIF('Quarterly Data'!$B:$B,'Annual Data'!$A15,'Quarterly Data'!AR:AR) -> 1845.86 | AN15: =SUMIF('Quarterly Data'!$B:$B,'Annual Data'!$A15,'Quarterly Data'!AS:AS) -> 1237.82 | AO15: =SUMIF('Quarterly Data'!$B:$B,'Annual Data'!$A15,'Quarterly Data'!AT:AT) -> 1197.887 | AP15: =SUMIF('Quarterly Data'!$B:$B,'Annual Data'!$A15,'Quarterly Data'!AU:AU) -> 925153.7 | AQ15: =SUMIF('Quarterly Data'!$B:$B,'Annual Data'!$A15,'Quarterly Data'!AV:AV) -> 14207 | AR15: =SUMIF('Quarterly Data'!$B:$B,'Annual Data'!$A15,'Quarterly Data'!AW:AW) -> 180.075 | AS15: =SUMIF('Quarterly Data'!$B:$B,'Annual Data'!$A15,'Quarterly Data'!AX:AX) -> 8747.427 | AT15: =SUMIF('Quarterly Data'!$B:$B,'Annual Data'!$A15,'Quarterly Data'!AY:AY) -> 22530 | AU15: =SUMIF('Quarterly Data'!$B:$B,'Annual Data'!$A15,'Quarterly Data'!AZ:AZ) -> 2661 | AV15: =SUMIF('Quarterly Data'!$B:$B,'Annual Data'!$A15,'Quarterly Data'!BA:BA) -> 19.545856 | AW15: =SUMIF('Quarterly Data'!$B:$B,'Annual Data'!$A15,'Quarterly Data'!BB:BB) -> 24984.475 | AX15: =SUMIF('Quarterly Data'!$B:$B,'Annual Data'!$A15,'Quarterly Data'!BC:BC) -> 3.4021693 | AY15: =SUMIF('Quarterly Data'!$B:$B,'Annual Data'!$A15,'Quarterly Data'!BD:BD) -> 251.44862 | AZ15: =SUMIF('Quarterly Data'!$B:$B,'Annual Data'!$A15,'Quarterly Data'!BE:BE) -> 20.750001 | BA15: =SUMIF('Quarterly Data'!$B:$B,'Annual Data'!$A15,'Quarterly Data'!BF:BF) -> 8.674 | BB15: =SUMIF('Quarterly Data'!$B:$B,'Annual Data'!$A15,'Quarterly Data'!BG:BG) -> 12.263617 | BC15: =SUMIF('Quarterly Data'!$B:$B,'Annual Data'!$A15,'Quarterly Data'!BH:BH) -> 5.470951 | BD15: =SUMIF('Quarterly Data'!$B:$B,'Annual Data'!$A15,'Quarterly Data'!BI:BI) -> 7.6944 | BE15: =SUMIF('Quarterly Data'!$B:$B,'Annual Data'!$A15,'Quarterly Data'!BJ:BJ) -> 7.348981 | BF15: =SUMIF('Quarterly Data'!$B:$B,'Annual Data'!$A15,'Quarterly Data'!BK:BK) -> 1.8887409 | BG15: =SUMIF('Quarterly Data'!$B:$B,'Annual Data'!$A15,'Quarterly Data'!BL:BL) -> 0.393 | BH15: =SUMIF('Quarterly Data'!$B:$B,'Annual Data'!$A15,'Quarterly Data'!BM:BM) -> 1.05007 | BI15: =SUMIF('Quarterly Data'!$B:$B,'Annual Data'!$A15,'Quarterly Data'!BN:BN) -> 0.26075251 | BJ15: =SUMIF('Quarterly Data'!$B:$B,'Annual Data'!$A15,'Quarterly Data'!BO:BO) -> 0.004 | BK15: =AVERAGEIF('Quarterly Data'!$B:$B,'Annual Data'!$A15,'Quarterly Data'!BP:BP) -> 129006.75 | BL15: =AVERAGEIF('Quarterly Data'!$B:$B,'Annual Data'!$A15,'Quarterly Data'!BQ:BQ) -> 2203.7288 | BM15: =AVERAGEIF('Quarterly Data'!$B:$B,'Annual Data'!$A15,'Quarterly Data'!BR:BR) -> 132429 | BN15: =AVERAGEIF('Quarterly Data'!$B:$B,'Annual Data'!$A15,'Quarterly Data'!BS:BS) -> 167243 | BO15: =AVERAGEIF('Quarterly Data'!$B:$B,'Annual Data'!$A15,'Quarterly Data'!BT:BT) -> 0.001 | BP15: =AVERAGEIF('Quarterly Data'!$B:$B,'Annual Data'!$A15,'Quarterly Data'!BU:BU) -> 215.45725 | BQ15: =AVERAGEIF('Quarterly Data'!$B:$B,'Annual Data'!$A15,'Quarterly Data'!BV:BV) -> 308835.38 | BR15: =AVERAGEIF('Quarterly Data'!$B:$B,'Annual Data'!$A15,'Quarterly Data'!BW:BW) -> 118.435 | BS15: =AVERAGEIF('Quarterly Data'!$B:$B,'Annual Data'!$A15,'Quarterly Data'!BX:BX) -> 11312.837 | BT15: =AVERAGEIF('Quarterly Data'!$B:$B,'Annual Data'!$A15,'Quarterly Data'!BY:BY) -> 274.04448 | BU15: =AVERAGEIF('Quarterly Data'!$B:$B,'Annual Data'!$A15,'Quarterly Data'!BZ:BZ) -> 136.86905 | BV15: =AVERAGEIF('Quarterly Data'!$B:$B,'Annual Data'!$A15,'Quarterly Data'!CA:CA) -> 207.21963 | BW15: =AVERAGEIF('Quarterly Data'!$B:$B,'Annual Data'!$A15,'Quarterly Data'!CB:CB) -> 30.656125 | BX15: =AVERAGEIF('Quarterly Data'!$B:$B,'Annual Data'!$A15,'Quarterly Data'!CC:CC) -> 107.86365 | BY15: =AVERAGEIF('Quarterly Data'!$B:$B,'Annual Data'!$A15,'Quarterly Data'!CD:CD) -> 94.316015 | BZ15: =AVERAGEIF('Quarterly Data'!$B:$B,'Annual Data'!$A15,'Quarterly Data'!CE:CE) -> 40.011823 | CA15: =AVERAGEIF('Quarterly Data'!$B:$B,'Annual Data'!$A15,'Quarterly Data'!CF:CF) -> 4.6673383 | CB15: =AVERAGEIF('Quarterly Data'!$B:$B,'Annual Data'!$A15,'Quarterly Data'!CG:CG) -> 9.360267 | CC15: =AVERAGEIF('Quarterly Data'!$B:$B,'Annual Data'!$A15,'Quarterly Data'!CH:CH) -> 2.3502447 | CD15: =AVERAGEIF('Quarterly Data'!$B:$B,'Annual Data'!$A15,'Quarterly Data'!CI:CI) -> 4.158632 | CE15: =SUMIF('Quarterly Data'!$B:$B,'Annual Data'!$A15,'Quarterly Data'!CJ:CJ) -> 290550 | CF15: =SUMIF('Quarterly Data'!$B:$B,'Annual Data'!$A15,'Quarterly Data'!CK:CK) -> 3207.025 | CG15: =SUMIF('Quarterly Data'!$B:$B,'Annual Data'!$A15,'Quarterly Data'!CL:CL) -> 274362.5 | CH15: =SUMIF('Quarterly Data'!$B:$B,'Annual Data'!$A15,'Quarterly Data'!CM:CM) -> 368358 | CI15: =SUMIF('Quarterly Data'!$B:$B,'Annual Data'!$A15,'Quarterly Data'!CN:CN) -> 164060 | CJ15: =SUMIF('Quarterly Data'!$B:$B,'Annual Data'!$A15,'Quarterly Data'!CO:CO) -> 417.17177 | CK15: =SUMIF('Quarterly Data'!$B:$B,'Annual Data'!$A15,'Quarterly Data'!CP:CP) -> 647783.2 | CL15: =SUMIF('Quarterly Data'!$B:$B,'Annual Data'!$A15,'Quarterly Data'!CQ:CQ) -> 220.24741 | CM15: =SUMIF('Quarterly Data'!$B:$B,'Annual Data'!$A15,'Quarterly Data'!CR:CR) -> 50591.7 | CN15: =SUMIF('Quarterly Data'!$B:$B,'Annual Data'!$A15,'Quarterly Data'!CS:CS) -> 939.7564 | CO15: =SUMIF('Quarterly Data'!$B:$B,'Annual Data'!$A15,'Quarterly Data'!CT:CT) -> 504.566 | CP15: =SUMIF('Quarterly Data'!$B:$B,'Annual Data'!$A15,'Quarterly Data'!CU:CU) -> 260.06 | CQ15: =SUMIF('Quarterly Data'!$B:$B,'Annual Data'!$A15,'Quarterly Data'!CV:CV) -> 112.29093 | CR15: =SUMIF('Quarterly Data'!$B:$B,'Annual Data'!$A15,'Quarterly Data'!CW:CW) -> 183.319 | CS15: =SUMIF('Quarterly Data'!$B:$B,'Annual Data'!$A15,'Quarterly Data'!CX:CX) -> 93.774 | CT15: =SUMIF('Quarterly Data'!$B:$B,'Annual Data'!$A15,'Quarterly Data'!CY:CY) -> 66.63783 | CU15: =SUMIF('Quarterly Data'!$B:$B,'Annual Data'!$A15,'Quarterly Data'!CZ:CZ) -> 38.364 | CV15: =SUMIF('Quarterly Data'!$B:$B,'Annual Data'!$A15,'Quarterly Data'!DA:DA) -> 16.372137 | CW15: =SUMIF('Quarterly Data'!$B:$B,'Annual Data'!$A15,'Quarterly Data'!DB:DB) -> 8.514692 | CX15: =SUMIF('Quarterly Data'!$B:$B,'Annual Data'!$A15,'Quarterly Data'!DC:DC) -> 23.336028
A16: 1982 | B16: =SUMIF('Quarterly Data'!$B:$B,'Annual Data'!$A16,'Quarterly Data'!G:G) -> 1157191 | C16: =SUMIF('Quarterly Data'!$B:$B,'Annual Data'!$A16,'Quarterly Data'!H:H) -> 611514 | D16: =SUMIF('Quarterly Data'!$B:$B,'Annual Data'!$A16,'Quarterly Data'!I:I) -> 189191 | E16: =SUMIF('Quarterly Data'!$B:$B,'Annual Data'!$A16,'Quarterly Data'!J:J) -> 290011 | F16: =SUMIF('Quarterly Data'!$B:$B,'Annual Data'!$A16,'Quarterly Data'!K:K) -> 197315 | G16: =SUMIF('Quarterly Data'!$B:$B,'Annual Data'!$A16,'Quarterly Data'!L:L) -> 162666 | H16: =SUMIF('Quarterly Data'!$B:$B,'Annual Data'!$A16,'Quarterly Data'!M:M) -> 73360.59 | I16: =SUMIF('Quarterly Data'!$B:$B,'Annual Data'!$A16,'Quarterly Data'!N:N) -> 9685.509 | J16: =AVERAGEIF('Quarterly Data'!$B:$B,'Annual Data'!$A16,'Quarterly Data'!O:O) -> 39.09056 | K16: =SUMIF('Quarterly Data'!$E:$E,'Annual Data'!$A16,'Quarterly Data'!P:P) -> 10 | L16: =SUMIF('Quarterly Data'!$E:$E,'Annual Data'!$A16,'Quarterly Data'!Q:Q) -> 0.001 | M16: =AVERAGEIF('Quarterly Data'!$B:$B,'Annual Data'!$A16,'Quarterly Data'!R:R) -> 39.09056 | N16: =AVERAGEIF('Quarterly Data'!$B:$B,'Annual Data'!$A16,'Quarterly Data'!S:S) -> 25816 | O16: =AVERAGEIF('Quarterly Data'!$B:$B,'Annual Data'!$A16,'Quarterly Data'!T:T) -> 487.5 | P16: =AVERAGEIF('Quarterly Data'!$B:$B,'Annual Data'!$A16,'Quarterly Data'!U:U) -> 327 | Q16: =AVERAGEIF('Quarterly Data'!$B:$B,'Annual Data'!$A16,'Quarterly Data'!V:V) -> 5427.5 | R16: =AVERAGEIF('Quarterly Data'!$B:$B,'Annual Data'!$A16,'Quarterly Data'!W:W) -> 246.75 | S16: =AVERAGEIF('Quarterly Data'!$B:$B,'Annual Data'!$A16,'Quarterly Data'!X:X) -> 145.75 | T16: =AVERAGEIF('Quarterly Data'!$B:$B,'Annual Data'!$A16,'Quarterly Data'!Y:Y) -> 1803 | U16: =AVERAGEIF('Quarterly Data'!$B:$B,'Annual Data'!$A16,'Quarterly Data'!Z:Z) -> 3957.5 | V16: =AVERAGEIF('Quarterly Data'!$B:$B,'Annual Data'!$A16,'Quarterly Data'!AA:AA) -> 1319.25 | W16: =AVERAGEIF('Quarterly Data'!$B:$B,'Annual Data'!$A16,'Quarterly Data'!AB:AB) -> 1256.5 | X16: =AVERAGEIF('Quarterly Data'!$B:$B,'Annual Data'!$A16,'Quarterly Data'!AC:AC) -> 734.5 | Y16: =AVERAGEIF('Quarterly Data'!$B:$B,'Annual Data'!$A16,'Quarterly Data'!AD:AD) -> 879.75 | Z16: =AVERAGEIF('Quarterly Data'!$B:$B,'Annual Data'!$A16,'Quarterly Data'!AE:AE) -> 180.5 | AA16: =AVERAGEIF('Quarterly Data'!$B:$B,'Annual Data'!$A16,'Quarterly Data'!AF:AF) -> 1045 | AB16: =AVERAGEIF('Quarterly Data'!$B:$B,'Annual Data'!$A16,'Quarterly Data'!AG:AG) -> 1117 | AC16: =AVERAGEIF('Quarterly Data'!$B:$B,'Annual Data'!$A16,'Quarterly Data'!AH:AH) -> 1913.5 | AD16: =AVERAGEIF('Quarterly Data'!$B:$B,'Annual Data'!$A16,'Quarterly Data'!AI:AI) -> 1707.25 | AE16: =AVERAGEIF('Quarterly Data'!$B:$B,'Annual Data'!$A16,'Quarterly Data'!AJ:AJ) -> 2138.75 | AF16: =AVERAGEIF('Quarterly Data'!$B:$B,'Annual Data'!$A16,'Quarterly Data'!AK:AK) -> 514 | AG16: =AVERAGEIF('Quarterly Data'!$B:$B,'Annual Data'!$A16,'Quarterly Data'!AL:AL) -> 616 | AH16: =AVERAGEIF('Quarterly Data'!$B:$B,'Annual Data'!$A16,'Quarterly Data'!AM:AM) -> 23950.75 | AI16: =AVERAGEIF('Quarterly Data'!$B:$B,'Annual Data'!$A16,'Quarterly Data'!AN:AN) -> 5394.2015 | AJ16: =SUMIF('Quarterly Data'!$B:$B,'Annual Data'!$A16,'Quarterly Data'!AO:AO) -> 1157191 | AK16: =SUMIF('Quarterly Data'!$B:$B,'Annual Data'!$A16,'Quarterly Data'!AP:AP) -> 7307.3 | AL16: =SUMIF('Quarterly Data'!$B:$B,'Annual Data'!$A16,'Quarterly Data'!AQ:AQ) -> 294351.01 | AM16: =SUMIF('Quarterly Data'!$B:$B,'Annual Data'!$A16,'Quarterly Data'!AR:AR) -> 1836.61 | AN16: =SUMIF('Quarterly Data'!$B:$B,'Annual Data'!$A16,'Quarterly Data'!AS:AS) -> 1267.574 | AO16: =SUMIF('Quarterly Data'!$B:$B,'Annual Data'!$A16,'Quarterly Data'!AT:AT) -> 1201.783 | AP16: =SUMIF('Quarterly Data'!$B:$B,'Annual Data'!$A16,'Quarterly Data'!AU:AU) -> 895861.9 | AQ16: =SUMIF('Quarterly Data'!$B:$B,'Annual Data'!$A16,'Quarterly Data'!AV:AV) -> 15540 | AR16: =SUMIF('Quarterly Data'!$B:$B,'Annual Data'!$A16,'Quarterly Data'!AW:AW) -> 206.175 | AS16: =SUMIF('Quarterly Data'!$B:$B,'Annual Data'!$A16,'Quarterly Data'!AX:AX) -> 10090.229 | AT16: =SUMIF('Quarterly Data'!$B:$B,'Annual Data'!$A16,'Quarterly Data'!AY:AY) -> 27419 | AU16: =SUMIF('Quarterly Data'!$B:$B,'Annual Data'!$A16,'Quarterly Data'!AZ:AZ) -> 3141 | AV16: =SUMIF('Quarterly Data'!$B:$B,'Annual Data'!$A16,'Quarterly Data'!BA:BA) -> 25.321437 | AW16: =SUMIF('Quarterly Data'!$B:$B,'Annual Data'!$A16,'Quarterly Data'!BB:BB) -> 36744.298 | AX16: =SUMIF('Quarterly Data'!$B:$B,'Annual Data'!$A16,'Quarterly Data'!BC:BC) -> 3.5594016 | AY16: =SUMIF('Quarterly Data'!$B:$B,'Annual Data'!$A16,'Quarterly Data'!BD:BD) -> 411.35718 | AZ16: =SUMIF('Quarterly Data'!$B:$B,'Annual Data'!$A16,'Quarterly Data'!BE:BE) -> 24.62 | BA16: =SUMIF('Quarterly Data'!$B:$B,'Annual Data'!$A16,'Quarterly Data'!BF:BF) -> 10.256 | BB16: =SUMIF('Quarterly Data'!$B:$B,'Annual Data'!$A16,'Quarterly Data'!BG:BG) -> 18.669709 | BC16: =SUMIF('Quarterly Data'!$B:$B,'Annual Data'!$A16,'Quarterly Data'!BH:BH) -> 5.91256 | BD16: =SUMIF('Quarterly Data'!$B:$B,'Annual Data'!$A16,'Quarterly Data'!BI:BI) -> 9.2497 | BE16: =SUMIF('Quarterly Data'!$B:$B,'Annual Data'!$A16,'Quarterly Data'!BJ:BJ) -> 9.040706 | BF16: =SUMIF('Quarterly Data'!$B:$B,'Annual Data'!$A16,'Quarterly Data'!BK:BK) -> 2.288244 | BG16: =SUMIF('Quarterly Data'!$B:$B,'Annual Data'!$A16,'Quarterly Data'!BL:BL) -> 0.503 | BH16: =SUMIF('Quarterly Data'!$B:$B,'Annual Data'!$A16,'Quarterly Data'!BM:BM) -> 1.5021 | BI16: =SUMIF('Quarterly Data'!$B:$B,'Annual Data'!$A16,'Quarterly Data'!BN:BN) -> 0.46370225 | BJ16: =SUMIF('Quarterly Data'!$B:$B,'Annual Data'!$A16,'Quarterly Data'!BO:BO) -> 0.004 | BK16: =AVERAGEIF('Quarterly Data'!$B:$B,'Annual Data'!$A16,'Quarterly Data'!BP:BP) -> 137113.4 | BL16: =AVERAGEIF('Quarterly Data'!$B:$B,'Annual Data'!$A16,'Quarterly Data'!BQ:BQ) -> 2436.3063 | BM16: =AVERAGEIF('Quarterly Data'!$B:$B,'Annual Data'!$A16,'Quarterly Data'!BR:BR) -> 156299 | BN16: =AVERAGEIF('Quarterly Data'!$B:$B,'Annual Data'!$A16,'Quarterly Data'!BS:BS) -> 197590 | BO16: =AVERAGEIF('Quarterly Data'!$B:$B,'Annual Data'!$A16,'Quarterly Data'!BT:BT) -> 0.001 | BP16: =AVERAGEIF('Quarterly Data'!$B:$B,'Annual Data'!$A16,'Quarterly Data'!BU:BU) -> 296.00475 | BQ16: =AVERAGEIF('Quarterly Data'!$B:$B,'Annual Data'!$A16,'Quarterly Data'!BV:BV) -> 399448.42 | BR16: =AVERAGEIF('Quarterly Data'!$B:$B,'Annual Data'!$A16,'Quarterly Data'!BW:BW) -> 117.253 | BS16: =AVERAGEIF('Quarterly Data'!$B:$B,'Annual Data'!$A16,'Quarterly Data'!BX:BX) -> 14388.218 | BT16: =AVERAGEIF('Quarterly Data'!$B:$B,'Annual Data'!$A16,'Quarterly Data'!BY:BY) -> 309.02368 | BU16: =AVERAGEIF('Quarterly Data'!$B:$B,'Annual Data'!$A16,'Quarterly Data'!BZ:BZ) -> 168.2892 | BV16: =AVERAGEIF('Quarterly Data'!$B:$B,'Annual Data'!$A16,'Quarterly Data'!CA:CA) -> 256.4331 | BW16: =AVERAGEIF('Quarterly Data'!$B:$B,'Annual Data'!$A16,'Quarterly Data'!CB:CB) -> 39.37575 | BX16: =AVERAGEIF('Quarterly Data'!$B:$B,'Annual Data'!$A16,'Quarterly Data'!CC:CC) -> 124.27428 | BY16: =AVERAGEIF('Quarterly Data'!$B:$B,'Annual Data'!$A16,'Quarterly Data'!CD:CD) -> 114.0518 | BZ16: =AVERAGEIF('Quarterly Data'!$B:$B,'Annual Data'!$A16,'Quarterly Data'!CE:CE) -> 45.31627 | CA16: =AVERAGEIF('Quarterly Data'!$B:$B,'Annual Data'!$A16,'Quarterly Data'!CF:CF) -> 5.884071 | CB16: =AVERAGEIF('Quarterly Data'!$B:$B,'Annual Data'!$A16,'Quarterly Data'!CG:CG) -> 11.8583 | CC16: =AVERAGEIF('Quarterly Data'!$B:$B,'Annual Data'!$A16,'Quarterly Data'!CH:CH) -> 3.2475925 | CD16: =AVERAGEIF('Quarterly Data'!$B:$B,'Annual Data'!$A16,'Quarterly Data'!CI:CI) -> 5.7143165 | CE16: =SUMIF('Quarterly Data'!$B:$B,'Annual Data'!$A16,'Quarterly Data'!CJ:CJ) -> 320013 | CF16: =SUMIF('Quarterly Data'!$B:$B,'Annual Data'!$A16,'Quarterly Data'!CK:CK) -> 3343.8 | CG16: =SUMIF('Quarterly Data'!$B:$B,'Annual Data'!$A16,'Quarterly Data'!CL:CL) -> 288540.02 | CH16: =SUMIF('Quarterly Data'!$B:$B,'Annual Data'!$A16,'Quarterly Data'!CM:CM) -> 388181 | CI16: =SUMIF('Quarterly Data'!$B:$B,'Annual Data'!$A16,'Quarterly Data'!CN:CN) -> 184102 | CJ16: =SUMIF('Quarterly Data'!$B:$B,'Annual Data'!$A16,'Quarterly Data'!CO:CO) -> 475.1505 | CK16: =SUMIF('Quarterly Data'!$B:$B,'Annual Data'!$A16,'Quarterly Data'!CP:CP) -> 708991.2 | CL16: =SUMIF('Quarterly Data'!$B:$B,'Annual Data'!$A16,'Quarterly Data'!CQ:CQ) -> 233.25969 | CM16: =SUMIF('Quarterly Data'!$B:$B,'Annual Data'!$A16,'Quarterly Data'!CR:CR) -> 58429.2 | CN16: =SUMIF('Quarterly Data'!$B:$B,'Annual Data'!$A16,'Quarterly Data'!CS:CS) -> 977.803 | CO16: =SUMIF('Quarterly Data'!$B:$B,'Annual Data'!$A16,'Quarterly Data'!CT:CT) -> 578.925 | CP16: =SUMIF('Quarterly Data'!$B:$B,'Annual Data'!$A16,'Quarterly Data'!CU:CU) -> 306.689 | CQ16: =SUMIF('Quarterly Data'!$B:$B,'Annual Data'!$A16,'Quarterly Data'!CV:CV) -> 129.13314 | CR16: =SUMIF('Quarterly Data'!$B:$B,'Annual Data'!$A16,'Quarterly Data'!CW:CW) -> 190.741 | CS16: =SUMIF('Quarterly Data'!$B:$B,'Annual Data'!$A16,'Quarterly Data'!CX:CX) -> 101.468 | CT16: =SUMIF('Quarterly Data'!$B:$B,'Annual Data'!$A16,'Quarterly Data'!CY:CY) -> 75.82165 | CU16: =SUMIF('Quarterly Data'!$B:$B,'Annual Data'!$A16,'Quarterly Data'!CZ:CZ) -> 43.12 | CV16: =SUMIF('Quarterly Data'!$B:$B,'Annual Data'!$A16,'Quarterly Data'!DA:DA) -> 19.422329 | CW16: =SUMIF('Quarterly Data'!$B:$B,'Annual Data'!$A16,'Quarterly Data'!DB:DB) -> 10.7095 | CX16: =SUMIF('Quarterly Data'!$B:$B,'Annual Data'!$A16,'Quarterly Data'!DC:DC) -> 23.336028
A17: 1983 | B17: =SUMIF('Quarterly Data'!$B:$B,'Annual Data'!$A17,'Quarterly Data'!G:G) -> 1205632 | C17: =SUMIF('Quarterly Data'!$B:$B,'Annual Data'!$A17,'Quarterly Data'!H:H) -> 638005 | D17: =SUMIF('Quarterly Data'!$B:$B,'Annual Data'!$A17,'Quarterly Data'!I:I) -> 203032 | E17: =SUMIF('Quarterly Data'!$B:$B,'Annual Data'!$A17,'Quarterly Data'!J:J) -> 294538 | F17: =SUMIF('Quarterly Data'!$B:$B,'Annual Data'!$A17,'Quarterly Data'!K:K) -> 200808 | G17: =SUMIF('Quarterly Data'!$B:$B,'Annual Data'!$A17,'Quarterly Data'!L:L) -> 172698 | H17: =SUMIF('Quarterly Data'!$B:$B,'Annual Data'!$A17,'Quarterly Data'!M:M) -> 74392.02 | I17: =SUMIF('Quarterly Data'!$B:$B,'Annual Data'!$A17,'Quarterly Data'!N:N) -> 13239.646 | J17: =AVERAGEIF('Quarterly Data'!$B:$B,'Annual Data'!$A17,'Quarterly Data'!O:O) -> 41.019672 | K17: =SUMIF('Quarterly Data'!$E:$E,'Annual Data'!$A17,'Quarterly Data'!P:P) -> 9.0625 | L17: =SUMIF('Quarterly Data'!$E:$E,'Annual Data'!$A17,'Quarterly Data'!Q:Q) -> 0.001 | M17: =AVERAGEIF('Quarterly Data'!$B:$B,'Annual Data'!$A17,'Quarterly Data'!R:R) -> 41.019672 | N17: =AVERAGEIF('Quarterly Data'!$B:$B,'Annual Data'!$A17,'Quarterly Data'!S:S) -> 25758.5 | O17: =AVERAGEIF('Quarterly Data'!$B:$B,'Annual Data'!$A17,'Quarterly Data'!T:T) -> 488.75 | P17: =AVERAGEIF('Quarterly Data'!$B:$B,'Annual Data'!$A17,'Quarterly Data'!U:U) -> 304.5 | Q17: =AVERAGEIF('Quarterly Data'!$B:$B,'Annual Data'!$A17,'Quarterly Data'!V:V) -> 5173.5 | R17: =AVERAGEIF('Quarterly Data'!$B:$B,'Annual Data'!$A17,'Quarterly Data'!W:W) -> 237.5 | S17: =AVERAGEIF('Quarterly Data'!$B:$B,'Annual Data'!$A17,'Quarterly Data'!X:X) -> 143.25 | T17: =AVERAGEIF('Quarterly Data'!$B:$B,'Annual Data'!$A17,'Quarterly Data'!Y:Y) -> 1822.25 | U17: =AVERAGEIF('Quarterly Data'!$B:$B,'Annual Data'!$A17,'Quarterly Data'!Z:Z) -> 3983.25 | V17: =AVERAGEIF('Quarterly Data'!$B:$B,'Annual Data'!$A17,'Quarterly Data'!AA:AA) -> 1299.75 | W17: =AVERAGEIF('Quarterly Data'!$B:$B,'Annual Data'!$A17,'Quarterly Data'!AB:AB) -> 1265.75 | X17: =AVERAGEIF('Quarterly Data'!$B:$B,'Annual Data'!$A17,'Quarterly Data'!AC:AC) -> 732.5 | Y17: =AVERAGEIF('Quarterly Data'!$B:$B,'Annual Data'!$A17,'Quarterly Data'!AD:AD) -> 906 | Z17: =AVERAGEIF('Quarterly Data'!$B:$B,'Annual Data'!$A17,'Quarterly Data'!AE:AE) -> 188.75 | AA17: =AVERAGEIF('Quarterly Data'!$B:$B,'Annual Data'!$A17,'Quarterly Data'!AF:AF) -> 1089 | AB17: =AVERAGEIF('Quarterly Data'!$B:$B,'Annual Data'!$A17,'Quarterly Data'!AG:AG) -> 1159.75 | AC17: =AVERAGEIF('Quarterly Data'!$B:$B,'Annual Data'!$A17,'Quarterly Data'!AH:AH) -> 1912.5 | AD17: =AVERAGEIF('Quarterly Data'!$B:$B,'Annual Data'!$A17,'Quarterly Data'!AI:AI) -> 1723.25 | AE17: =AVERAGEIF('Quarterly Data'!$B:$B,'Annual Data'!$A17,'Quarterly Data'!AJ:AJ) -> 2173.75 | AF17: =AVERAGEIF('Quarterly Data'!$B:$B,'Annual Data'!$A17,'Quarterly Data'!AK:AK) -> 524 | AG17: =AVERAGEIF('Quarterly Data'!$B:$B,'Annual Data'!$A17,'Quarterly Data'!AL:AL) -> 631 | AH17: =AVERAGEIF('Quarterly Data'!$B:$B,'Annual Data'!$A17,'Quarterly Data'!AM:AM) -> 23775.25 | AI17: =AVERAGEIF('Quarterly Data'!$B:$B,'Annual Data'!$A17,'Quarterly Data'!AN:AN) -> 5396.1393 | AJ17: =SUMIF('Quarterly Data'!$B:$B,'Annual Data'!$A17,'Quarterly Data'!AO:AO) -> 1205632 | AK17: =SUMIF('Quarterly Data'!$B:$B,'Annual Data'!$A17,'Quarterly Data'!AP:AP) -> 7642.275 | AL17: =SUMIF('Quarterly Data'!$B:$B,'Annual Data'!$A17,'Quarterly Data'!AQ:AQ) -> 304984.68 | AM17: =SUMIF('Quarterly Data'!$B:$B,'Annual Data'!$A17,'Quarterly Data'!AR:AR) -> 1863.58 | AN17: =SUMIF('Quarterly Data'!$B:$B,'Annual Data'!$A17,'Quarterly Data'!AS:AS) -> 1283.577 | AO17: =SUMIF('Quarterly Data'!$B:$B,'Annual Data'!$A17,'Quarterly Data'!AT:AT) -> 1218.202 | AP17: =SUMIF('Quarterly Data'!$B:$B,'Annual Data'!$A17,'Quarterly Data'!AU:AU) -> 918816.2 | AQ17: =SUMIF('Quarterly Data'!$B:$B,'Annual Data'!$A17,'Quarterly Data'!AV:AV) -> 15996 | AR17: =SUMIF('Quarterly Data'!$B:$B,'Annual Data'!$A17,'Quarterly Data'!AW:AW) -> 227.975 | AS17: =SUMIF('Quarterly Data'!$B:$B,'Annual Data'!$A17,'Quarterly Data'!AX:AX) -> 11534.896 | AT17: =SUMIF('Quarterly Data'!$B:$B,'Annual Data'!$A17,'Quarterly Data'!AY:AY) -> 29858 | AU17: =SUMIF('Quarterly Data'!$B:$B,'Annual Data'!$A17,'Quarterly Data'!AZ:AZ) -> 3764 | AV17: =SUMIF('Quarterly Data'!$B:$B,'Annual Data'!$A17,'Quarterly Data'!BA:BA) -> 37.507473 | AW17: =SUMIF('Quarterly Data'!$B:$B,'Annual Data'!$A17,'Quarterly Data'!BB:BB) -> 43218.67 | AX17: =SUMIF('Quarterly Data'!$B:$B,'Annual Data'!$A17,'Quarterly Data'!BC:BC) -> 3.6574426 | AY17: =SUMIF('Quarterly Data'!$B:$B,'Annual Data'!$A17,'Quarterly Data'!BD:BD) -> 483.6559 | AZ17: =SUMIF('Quarterly Data'!$B:$B,'Annual Data'!$A17,'Quarterly Data'!BE:BE) -> 26.819999 | BA17: =SUMIF('Quarterly Data'!$B:$B,'Annual Data'!$A17,'Quarterly Data'!BF:BF) -> 14.372 | BB17: =SUMIF('Quarterly Data'!$B:$B,'Annual Data'!$A17,'Quarterly Data'!BG:BG) -> 25.846044 | BC17: =SUMIF('Quarterly Data'!$B:$B,'Annual Data'!$A17,'Quarterly Data'!BH:BH) -> 5.0096838 | BD17: =SUMIF('Quarterly Data'!$B:$B,'Annual Data'!$A17,'Quarterly Data'!BI:BI) -> 10.484001 | BE17: =SUMIF('Quarterly Data'!$B:$B,'Annual Data'!$A17,'Quarterly Data'!BJ:BJ) -> 9.992407 | BF17: =SUMIF('Quarterly Data'!$B:$B,'Annual Data'!$A17,'Quarterly Data'!BK:BK) -> 2.3802089 | BG17: =SUMIF('Quarterly Data'!$B:$B,'Annual Data'!$A17,'Quarterly Data'!BL:BL) -> 0.6790001 | BH17: =SUMIF('Quarterly Data'!$B:$B,'Annual Data'!$A17,'Quarterly Data'!BM:BM) -> 1.71288 | BI17: =SUMIF('Quarterly Data'!$B:$B,'Annual Data'!$A17,'Quarterly Data'!BN:BN) -> 0.6847577 | BJ17: =SUMIF('Quarterly Data'!$B:$B,'Annual Data'!$A17,'Quarterly Data'!BO:BO) -> 0.004 | BK17: =AVERAGEIF('Quarterly Data'!$B:$B,'Annual Data'!$A17,'Quarterly Data'!BP:BP) -> 147486.15 | BL17: =AVERAGEIF('Quarterly Data'!$B:$B,'Annual Data'!$A17,'Quarterly Data'!BQ:BQ) -> 2741.4662 | BM17: =AVERAGEIF('Quarterly Data'!$B:$B,'Annual Data'!$A17,'Quarterly Data'!BR:BR) -> 180626 | BN17: =AVERAGEIF('Quarterly Data'!$B:$B,'Annual Data'!$A17,'Quarterly Data'!BS:BS) -> 236067 | BO17: =AVERAGEIF('Quarterly Data'!$B:$B,'Annual Data'!$A17,'Quarterly Data'!BT:BT) -> 0.001 | BP17: =AVERAGEIF('Quarterly Data'!$B:$B,'Annual Data'!$A17,'Quarterly Data'!BU:BU) -> 389.17915 | BQ17: =AVERAGEIF('Quarterly Data'!$B:$B,'Annual Data'!$A17,'Quarterly Data'!BV:BV) -> 488881.4 | BR17: =AVERAGEIF('Quarterly Data'!$B:$B,'Annual Data'!$A17,'Quarterly Data'!BW:BW) -> 116.881 | BS17: =AVERAGEIF('Quarterly Data'!$B:$B,'Annual Data'!$A17,'Quarterly Data'!BX:BX) -> 16501.095 | BT17: =AVERAGEIF('Quarterly Data'!$B:$B,'Annual Data'!$A17,'Quarterly Data'!BY:BY) -> 338.12615 | BU17: =AVERAGEIF('Quarterly Data'!$B:$B,'Annual Data'!$A17,'Quarterly Data'!BZ:BZ) -> 200.80455 | BV17: =AVERAGEIF('Quarterly Data'!$B:$B,'Annual Data'!$A17,'Quarterly Data'!CA:CA) -> 271.58275 | BW17: =AVERAGEIF('Quarterly Data'!$B:$B,'Annual Data'!$A17,'Quarterly Data'!CB:CB) -> 52.028125 | BX17: =AVERAGEIF('Quarterly Data'!$B:$B,'Annual Data'!$A17,'Quarterly Data'!CC:CC) -> 142.38592 | BY17: =AVERAGEIF('Quarterly Data'!$B:$B,'Annual Data'!$A17,'Quarterly Data'!CD:CD) -> 134.8038 | BZ17: =AVERAGEIF('Quarterly Data'!$B:$B,'Annual Data'!$A17,'Quarterly Data'!CE:CE) -> 52.83901 | CA17: =AVERAGEIF('Quarterly Data'!$B:$B,'Annual Data'!$A17,'Quarterly Data'!CF:CF) -> 7.350882 | CB17: =AVERAGEIF('Quarterly Data'!$B:$B,'Annual Data'!$A17,'Quarterly Data'!CG:CG) -> 15.32913 | CC17: =AVERAGEIF('Quarterly Data'!$B:$B,'Annual Data'!$A17,'Quarterly Data'!CH:CH) -> 4.4402918 | CD17: =AVERAGEIF('Quarterly Data'!$B:$B,'Annual Data'!$A17,'Quarterly Data'!CI:CI) -> 7.8130445 | CE17: =SUMIF('Quarterly Data'!$B:$B,'Annual Data'!$A17,'Quarterly Data'!CJ:CJ) -> 351900 | CF17: =SUMIF('Quarterly Data'!$B:$B,'Annual Data'!$A17,'Quarterly Data'!CK:CK) -> 3634.025 | CG17: =SUMIF('Quarterly Data'!$B:$B,'Annual Data'!$A17,'Quarterly Data'!CL:CL) -> 301733.15 | CH17: =SUMIF('Quarterly Data'!$B:$B,'Annual Data'!$A17,'Quarterly Data'!CM:CM) -> 421316 | CI17: =SUMIF('Quarterly Data'!$B:$B,'Annual Data'!$A17,'Quarterly Data'!CN:CN) -> 199312 | CJ17: =SUMIF('Quarterly Data'!$B:$B,'Annual Data'!$A17,'Quarterly Data'!CO:CO) -> 524.3302 | CK17: =SUMIF('Quarterly Data'!$B:$B,'Annual Data'!$A17,'Quarterly Data'!CP:CP) -> 794435.1 | CL17: =SUMIF('Quarterly Data'!$B:$B,'Annual Data'!$A17,'Quarterly Data'!CQ:CQ) -> 240.38774 | CM17: =SUMIF('Quarterly Data'!$B:$B,'Annual Data'!$A17,'Quarterly Data'!CR:CR) -> 69523.4 | CN17: =SUMIF('Quarterly Data'!$B:$B,'Annual Data'!$A17,'Quarterly Data'!CS:CS) -> 1020.0841 | CO17: =SUMIF('Quarterly Data'!$B:$B,'Annual Data'!$A17,'Quarterly Data'!CT:CT) -> 642.54 | CP17: =SUMIF('Quarterly Data'!$B:$B,'Annual Data'!$A17,'Quarterly Data'!CU:CU) -> 357.802 | CQ17: =SUMIF('Quarterly Data'!$B:$B,'Annual Data'!$A17,'Quarterly Data'!CV:CV) -> 147.03457 | CR17: =SUMIF('Quarterly Data'!$B:$B,'Annual Data'!$A17,'Quarterly Data'!CW:CW) -> 198.167 | CS17: =SUMIF('Quarterly Data'!$B:$B,'Annual Data'!$A17,'Quarterly Data'!CX:CX) -> 107.576 | CT17: =SUMIF('Quarterly Data'!$B:$B,'Annual Data'!$A17,'Quarterly Data'!CY:CY) -> 84.48169 | CU17: =SUMIF('Quarterly Data'!$B:$B,'Annual Data'!$A17,'Quarterly Data'!CZ:CZ) -> 48.133 | CV17: =SUMIF('Quarterly Data'!$B:$B,'Annual Data'!$A17,'Quarterly Data'!DA:DA) -> 21.407623 | CW17: =SUMIF('Quarterly Data'!$B:$B,'Annual Data'!$A17,'Quarterly Data'!DB:DB) -> 12.778039 | CX17: =SUMIF('Quarterly Data'!$B:$B,'Annual Data'!$A17,'Quarterly Data'!DC:DC) -> 23.336028
A18: 1984 | B18: =SUMIF('Quarterly Data'!$B:$B,'Annual Data'!$A18,'Quarterly Data'!G:G) -> 1232675 | C18: =SUMIF('Quarterly Data'!$B:$B,'Annual Data'!$A18,'Quarterly Data'!H:H) -> 653525 | D18: =SUMIF('Quarterly Data'!$B:$B,'Annual Data'!$A18,'Quarterly Data'!I:I) -> 216248 | E18: =SUMIF('Quarterly Data'!$B:$B,'Annual Data'!$A18,'Quarterly Data'!J:J) -> 298041 | F18: =SUMIF('Quarterly Data'!$B:$B,'Annual Data'!$A18,'Quarterly Data'!K:K) -> 213734 | G18: =SUMIF('Quarterly Data'!$B:$B,'Annual Data'!$A18,'Quarterly Data'!L:L) -> 189030 | H18: =SUMIF('Quarterly Data'!$B:$B,'Annual Data'!$A18,'Quarterly Data'!M:M) -> 82787.65 | I18: =SUMIF('Quarterly Data'!$B:$B,'Annual Data'!$A18,'Quarterly Data'!N:N) -> 14928.792 | J18: =AVERAGEIF('Quarterly Data'!$B:$B,'Annual Data'!$A18,'Quarterly Data'!O:O) -> 42.766303 | K18: =SUMIF('Quarterly Data'!$E:$E,'Annual Data'!$A18,'Quarterly Data'!P:P) -> 9.5 | L18: =SUMIF('Quarterly Data'!$E:$E,'Annual Data'!$A18,'Quarterly Data'!Q:Q) -> 11.07 | M18: =AVERAGEIF('Quarterly Data'!$B:$B,'Annual Data'!$A18,'Quarterly Data'!R:R) -> 42.766303 | N18: =AVERAGEIF('Quarterly Data'!$B:$B,'Annual Data'!$A18,'Quarterly Data'!S:S) -> 26347.5 | O18: =AVERAGEIF('Quarterly Data'!$B:$B,'Annual Data'!$A18,'Quarterly Data'!T:T) -> 499.5 | P18: =AVERAGEIF('Quarterly Data'!$B:$B,'Annual Data'!$A18,'Quarterly Data'!U:U) -> 284.5 | Q18: =AVERAGEIF('Quarterly Data'!$B:$B,'Annual Data'!$A18,'Quarterly Data'!V:V) -> 5115.25 | R18: =AVERAGEIF('Quarterly Data'!$B:$B,'Annual Data'!$A18,'Quarterly Data'!W:W) -> 230.25 | S18: =AVERAGEIF('Quarterly Data'!$B:$B,'Annual Data'!$A18,'Quarterly Data'!X:X) -> 143.25 | T18: =AVERAGEIF('Quarterly Data'!$B:$B,'Annual Data'!$A18,'Quarterly Data'!Y:Y) -> 1891 | U18: =AVERAGEIF('Quarterly Data'!$B:$B,'Annual Data'!$A18,'Quarterly Data'!Z:Z) -> 4124.75 | V18: =AVERAGEIF('Quarterly Data'!$B:$B,'Annual Data'!$A18,'Quarterly Data'!AA:AA) -> 1309 | W18: =AVERAGEIF('Quarterly Data'!$B:$B,'Annual Data'!$A18,'Quarterly Data'!AB:AB) -> 1332.5 | X18: =AVERAGEIF('Quarterly Data'!$B:$B,'Annual Data'!$A18,'Quarterly Data'!AC:AC) -> 751.25 | Y18: =AVERAGEIF('Quarterly Data'!$B:$B,'Annual Data'!$A18,'Quarterly Data'!AD:AD) -> 940 | Z18: =AVERAGEIF('Quarterly Data'!$B:$B,'Annual Data'!$A18,'Quarterly Data'!AE:AE) -> 202.25 | AA18: =AVERAGEIF('Quarterly Data'!$B:$B,'Annual Data'!$A18,'Quarterly Data'!AF:AF) -> 1162.75 | AB18: =AVERAGEIF('Quarterly Data'!$B:$B,'Annual Data'!$A18,'Quarterly Data'!AG:AG) -> 1225.75 | AC18: =AVERAGEIF('Quarterly Data'!$B:$B,'Annual Data'!$A18,'Quarterly Data'!AH:AH) -> 1903.25 | AD18: =AVERAGEIF('Quarterly Data'!$B:$B,'Annual Data'!$A18,'Quarterly Data'!AI:AI) -> 1759.75 | AE18: =AVERAGEIF('Quarterly Data'!$B:$B,'Annual Data'!$A18,'Quarterly Data'!AJ:AJ) -> 2251.25 | AF18: =AVERAGEIF('Quarterly Data'!$B:$B,'Annual Data'!$A18,'Quarterly Data'!AK:AK) -> 550.5 | AG18: =AVERAGEIF('Quarterly Data'!$B:$B,'Annual Data'!$A18,'Quarterly Data'!AL:AL) -> 670.25 | AH18: =AVERAGEIF('Quarterly Data'!$B:$B,'Annual Data'!$A18,'Quarterly Data'!AM:AM) -> 24285 | AI18: =AVERAGEIF('Quarterly Data'!$B:$B,'Annual Data'!$A18,'Quarterly Data'!AN:AN) -> 5388.8242 | AJ18: =SUMIF('Quarterly Data'!$B:$B,'Annual Data'!$A18,'Quarterly Data'!AO:AO) -> 1232675 | AK18: =SUMIF('Quarterly Data'!$B:$B,'Annual Data'!$A18,'Quarterly Data'!AP:AP) -> 8195.3 | AL18: =SUMIF('Quarterly Data'!$B:$B,'Annual Data'!$A18,'Quarterly Data'!AQ:AQ) -> 318480.11 | AM18: =SUMIF('Quarterly Data'!$B:$B,'Annual Data'!$A18,'Quarterly Data'!AR:AR) -> 1917.61 | AN18: =SUMIF('Quarterly Data'!$B:$B,'Annual Data'!$A18,'Quarterly Data'!AS:AS) -> 1305.053 | AO18: =SUMIF('Quarterly Data'!$B:$B,'Annual Data'!$A18,'Quarterly Data'!AT:AT) -> 1257.309 | AP18: =SUMIF('Quarterly Data'!$B:$B,'Annual Data'!$A18,'Quarterly Data'!AU:AU) -> 973013.1 | AQ18: =SUMIF('Quarterly Data'!$B:$B,'Annual Data'!$A18,'Quarterly Data'!AV:AV) -> 17461 | AR18: =SUMIF('Quarterly Data'!$B:$B,'Annual Data'!$A18,'Quarterly Data'!AW:AW) -> 260.05 | AS18: =SUMIF('Quarterly Data'!$B:$B,'Annual Data'!$A18,'Quarterly Data'!AX:AX) -> 12792.811 | AT18: =SUMIF('Quarterly Data'!$B:$B,'Annual Data'!$A18,'Quarterly Data'!AY:AY) -> 35147 | AU18: =SUMIF('Quarterly Data'!$B:$B,'Annual Data'!$A18,'Quarterly Data'!AZ:AZ) -> 4951 | AV18: =SUMIF('Quarterly Data'!$B:$B,'Annual Data'!$A18,'Quarterly Data'!BA:BA) -> 49.15562 | AW18: =SUMIF('Quarterly Data'!$B:$B,'Annual Data'!$A18,'Quarterly Data'!BB:BB) -> 51442.58 | AX18: =SUMIF('Quarterly Data'!$B:$B,'Annual Data'!$A18,'Quarterly Data'!BC:BC) -> 3.6314575 | AY18: =SUMIF('Quarterly Data'!$B:$B,'Annual Data'!$A18,'Quarterly Data'!BD:BD) -> 583.7112 | AZ18: =SUMIF('Quarterly Data'!$B:$B,'Annual Data'!$A18,'Quarterly Data'!BE:BE) -> 28.230001 | BA18: =SUMIF('Quarterly Data'!$B:$B,'Annual Data'!$A18,'Quarterly Data'!BF:BF) -> 16.479 | BB18: =SUMIF('Quarterly Data'!$B:$B,'Annual Data'!$A18,'Quarterly Data'!BG:BG) -> 31.71889 | BC18: =SUMIF('Quarterly Data'!$B:$B,'Annual Data'!$A18,'Quarterly Data'!BH:BH) -> -0.2330765 | BD18: =SUMIF('Quarterly Data'!$B:$B,'Annual Data'!$A18,'Quarterly Data'!BI:BI) -> 11.7379 | BE18: =SUMIF('Quarterly Data'!$B:$B,'Annual Data'!$A18,'Quarterly Data'!BJ:BJ) -> 10.981798 | BF18: =SUMIF('Quarterly Data'!$B:$B,'Annual Data'!$A18,'Quarterly Data'!BK:BK) -> 2.8380556 | BG18: =SUMIF('Quarterly Data'!$B:$B,'Annual Data'!$A18,'Quarterly Data'!BL:BL) -> 0.8419999 | BH18: =SUMIF('Quarterly Data'!$B:$B,'Annual Data'!$A18,'Quarterly Data'!BM:BM) -> 1.9274599 | BI18: =SUMIF('Quarterly Data'!$B:$B,'Annual Data'!$A18,'Quarterly Data'!BN:BN) -> 0.9909625 | BJ18: =SUMIF('Quarterly Data'!$B:$B,'Annual Data'!$A18,'Quarterly Data'!BO:BO) -> 0.004 | BK18: =AVERAGEIF('Quarterly Data'!$B:$B,'Annual Data'!$A18,'Quarterly Data'!BP:BP) -> 159398.25 | BL18: =AVERAGEIF('Quarterly Data'!$B:$B,'Annual Data'!$A18,'Quarterly Data'!BQ:BQ) -> 3073.6665 | BM18: =AVERAGEIF('Quarterly Data'!$B:$B,'Annual Data'!$A18,'Quarterly Data'!BR:BR) -> 201410.5 | BN18: =AVERAGEIF('Quarterly Data'!$B:$B,'Annual Data'!$A18,'Quarterly Data'!BS:BS) -> 276120.25 | BO18: =AVERAGEIF('Quarterly Data'!$B:$B,'Annual Data'!$A18,'Quarterly Data'!BT:BT) -> 0.001 | BP18: =AVERAGEIF('Quarterly Data'!$B:$B,'Annual Data'!$A18,'Quarterly Data'!BU:BU) -> 456.83337 | BQ18: =AVERAGEIF('Quarterly Data'!$B:$B,'Annual Data'!$A18,'Quarterly Data'!BV:BV) -> 566486.35 | BR18: =AVERAGEIF('Quarterly Data'!$B:$B,'Annual Data'!$A18,'Quarterly Data'!BW:BW) -> 116.25498 | BS18: =AVERAGEIF('Quarterly Data'!$B:$B,'Annual Data'!$A18,'Quarterly Data'!BX:BX) -> 17885.557 | BT18: =AVERAGEIF('Quarterly Data'!$B:$B,'Annual Data'!$A18,'Quarterly Data'!BY:BY) -> 361.17717 | BU18: =AVERAGEIF('Quarterly Data'!$B:$B,'Annual Data'!$A18,'Quarterly Data'!BZ:BZ) -> 229.51145 | BV18: =AVERAGEIF('Quarterly Data'!$B:$B,'Annual Data'!$A18,'Quarterly Data'!CA:CA) -> 300.12735 | BW18: =AVERAGEIF('Quarterly Data'!$B:$B,'Annual Data'!$A18,'Quarterly Data'!CB:CB) -> 68.20275 | BX18: =AVERAGEIF('Quarterly Data'!$B:$B,'Annual Data'!$A18,'Quarterly Data'!CC:CC) -> 159.8594 | BY18: =AVERAGEIF('Quarterly Data'!$B:$B,'Annual Data'!$A18,'Quarterly Data'!CD:CD) -> 153.33463 | BZ18: =AVERAGEIF('Quarterly Data'!$B:$B,'Annual Data'!$A18,'Quarterly Data'!CE:CE) -> 59.79436 | CA18: =AVERAGEIF('Quarterly Data'!$B:$B,'Annual Data'!$A18,'Quarterly Data'!CF:CF) -> 8.2789742 | CB18: =AVERAGEIF('Quarterly Data'!$B:$B,'Annual Data'!$A18,'Quarterly Data'!CG:CG) -> 17.78165 | CC18: =AVERAGEIF('Quarterly Data'!$B:$B,'Annual Data'!$A18,'Quarterly Data'!CH:CH) -> 6.5864847 | CD18: =AVERAGEIF('Quarterly Data'!$B:$B,'Annual Data'!$A18,'Quarterly Data'!CI:CI) -> 10.701716 | CE18: =SUMIF('Quarterly Data'!$B:$B,'Annual Data'!$A18,'Quarterly Data'!CJ:CJ) -> 378608 | CF18: =SUMIF('Quarterly Data'!$B:$B,'Annual Data'!$A18,'Quarterly Data'!CK:CK) -> 4037.65 | CG18: =SUMIF('Quarterly Data'!$B:$B,'Annual Data'!$A18,'Quarterly Data'!CL:CL) -> 319635.48 | CH18: =SUMIF('Quarterly Data'!$B:$B,'Annual Data'!$A18,'Quarterly Data'!CM:CM) -> 461986 | CI18: =SUMIF('Quarterly Data'!$B:$B,'Annual Data'!$A18,'Quarterly Data'!CN:CN) -> 224299 | CJ18: =SUMIF('Quarterly Data'!$B:$B,'Annual Data'!$A18,'Quarterly Data'!CO:CO) -> 578.2886 | CK18: =SUMIF('Quarterly Data'!$B:$B,'Annual Data'!$A18,'Quarterly Data'!CP:CP) -> 892680.1 | CL18: =SUMIF('Quarterly Data'!$B:$B,'Annual Data'!$A18,'Quarterly Data'!CQ:CQ) -> 257.05651 | CM18: =SUMIF('Quarterly Data'!$B:$B,'Annual Data'!$A18,'Quarterly Data'!CR:CR) -> 80395.8 | CN18: =SUMIF('Quarterly Data'!$B:$B,'Annual Data'!$A18,'Quarterly Data'!CS:CS) -> 1070.7138 | CO18: =SUMIF('Quarterly Data'!$B:$B,'Annual Data'!$A18,'Quarterly Data'!CT:CT) -> 699.5 | CP18: =SUMIF('Quarterly Data'!$B:$B,'Annual Data'!$A18,'Quarterly Data'!CU:CU) -> 409.026 | CQ18: =SUMIF('Quarterly Data'!$B:$B,'Annual Data'!$A18,'Quarterly Data'!CV:CV) -> 165.91856 | CR18: =SUMIF('Quarterly Data'!$B:$B,'Annual Data'!$A18,'Quarterly Data'!CW:CW) -> 207.209 | CS18: =SUMIF('Quarterly Data'!$B:$B,'Annual Data'!$A18,'Quarterly Data'!CX:CX) -> 115.854 | CT18: =SUMIF('Quarterly Data'!$B:$B,'Annual Data'!$A18,'Quarterly Data'!CY:CY) -> 90.06417 | CU18: =SUMIF('Quarterly Data'!$B:$B,'Annual Data'!$A18,'Quarterly Data'!CZ:CZ) -> 53.775 | CV18: =SUMIF('Quarterly Data'!$B:$B,'Annual Data'!$A18,'Quarterly Data'!DA:DA) -> 23.708313 | CW18: =SUMIF('Quarterly Data'!$B:$B,'Annual Data'!$A18,'Quarterly Data'!DB:DB) -> 15.89191 | CX18: =SUMIF('Quarterly Data'!$B:$B,'Annual Data'!$A18,'Quarterly Data'!DC:DC) -> 23.336028
