Workbook
Name _DLX1.INC: HAVERM!$A$4:$AC$9

Sheet Chart Data
B1: Dove-hawk scale | C1: Jun vote | D1: Aug vote | H1: Dove-hawk scale | K1: Private sector pay growth | Q1: Underlying services inflation | V1: GDP level
A2: Swati Dhingra | B2: -2 | C2: Cut | D2: Cut | E2: 8 | F2: =17-E2 -> 9 | G2: Pill | H2: 1 | L2: Outturn | M2: BoE forecast | N2: Zeroline | R2: Headline services inflation | S2: BoE's measure of underlying services inflation* | V2: a | W2: OE | X2: BoE (mkt) | Z2: OE q/q | AA2: BoE q/q
A3: Alan Taylor | B3: -1.75 | C3: Cut | D3: Cut | E3: 14 | F3: =17-E3 -> 3 | G3: Mann | H3: 1 | K3: 43466 | L3: =HAVERM!B118 -> 3.6 | M3: =NA() -> #N/A | N3: 0 | Q3: 44562 | R3: =((HAVERM!C154/HAVERM!C142)-1)*100 -> 3.2685512 | S3: =[1]Monthly!QH406 -> 3.4144346 | V3: 2020Q1 | W3: 604719 | X3: ='MPR GDP level'!E11*1000 -> 604719
A4: Sarah Breeden | B4: -1 | C4: Hold | D4: Cut | E4: 12 | F4: =17-E4 -> 5 | G4: Greene | H4: 0.5 | K4: 43497 | L4: =HAVERM!B119 -> 3.6 | M4: =NA() -> #N/A | N4: 0 | Q4: 44593 | R4: =((HAVERM!C155/HAVERM!C143)-1)*100 -> 3.4391534 | S4: =[1]Monthly!QH407 -> 3.6825479 | V4: 2020Q2 | W4: 481769 | X4: ='MPR GDP level'!E12*1000 -> 481769 | Z4: =((W4/W3)-1)*100 -> -20.331757 | AA4: =((X4/X3)-1)*100 -> -20.331757
A5: Dave Ramsden | B5: -0.5 | C5: Hold | D5: Cut | E5: 13 | F5: =17-E5 -> 4 | G5: Bailey | H5: 0.25 | K5: 43525 | L5: =HAVERM!B120 -> 3.6 | M5: =NA() -> #N/A | N5: 0 | Q5: 44621 | R5: =((HAVERM!C156/HAVERM!C144)-1)*100 -> 3.9612676 | S5: =[1]Monthly!QH408 -> 4.3041571 | V5: 2020Q3 | W5: 562648 | X5: ='MPR GDP level'!E13*1000 -> 562648 | Z5: =((W5/W4)-1)*100 -> 16.787921 | AA5: =((X5/X4)-1)*100 -> 16.787921
A6: Andrew Bailey | B6: -0.5 | C6: Hold | D6: Cut | E6: 17 | F6: =17-E6 -> 0 | G6: Lombardelli | H6: 0.25 | K6: 43556 | L6: =HAVERM!B121 -> 3.6 | M6: =NA() -> #N/A | N6: 0 | Q6: 44652 | R6: =((HAVERM!C157/HAVERM!C145)-1)*100 -> 4.7244094 | S6: =[1]Monthly!QH409 -> 5.1902566 | V6: 2020Q4 | W6: 570338 | X6: ='MPR GDP level'!E14*1000 -> 570338 | Z6: =((W6/W5)-1)*100 -> 1.3667515 | AA6: =((X6/X5)-1)*100 -> 1.3667515
A7: Clare Lombardelli | B7: -0.5 | C7: Hold | D7: Cut | E7: 12 | F7: =17-E7 -> 5 | G7: Ramsden | H7: 0 | K7: 43586 | L7: =HAVERM!B122 -> 3.7 | M7: =NA() -> #N/A | N7: 0 | Q7: 44682 | R7: =((HAVERM!C158/HAVERM!C146)-1)*100 -> 4.886562 | S7: =[1]Monthly!QH410 -> 5.2311233 | V7: 2021Q1 | W7: 564411 | X7: ='MPR GDP level'!E15*1000 -> 564411 | Z7: =((W7/W6)-1)*100 -> -1.0392083 | AA7: =((X7/X6)-1)*100 -> -1.0392083
A8: Megan Greene | B8: 0.5 | C8: Hold | D8: Hold | E8: 13 | F8: =17-E8 -> 4 | G8: Breeden | H8: -0.5 | K8: 43617 | L8: =HAVERM!B123 -> 3.9 | M8: =NA() -> #N/A | N8: 0 | Q8: 44713 | R8: =((HAVERM!C159/HAVERM!C147)-1)*100 -> 5.2173913 | S8: =[1]Monthly!QH411 -> 5.3913728 | V8: 2021Q2 | W8: 605353 | X8: ='MPR GDP level'!E16*1000 -> 605353 | Z8: =((W8/W7)-1)*100 -> 7.2539337 | AA8: =((X8/X7)-1)*100 -> 7.2539337
A9: Catherine Mann | B9: 1.5 | C9: Hold | D9: Hold | E9: 11 | F9: =17-E9 -> 6 | G9: Taylor | H9: -1.4 | K9: 43647 | L9: =HAVERM!B124 -> 3.9 | M9: =NA() -> #N/A | N9: 0 | Q9: 44743 | R9: =((HAVERM!C160/HAVERM!C148)-1)*100 -> 5.7241977 | S9: =[1]Monthly!QH412 -> 5.6563704 | V9: 2021Q3 | W9: 615459 | X9: ='MPR GDP level'!E17*1000 -> 615459 | Z9: =((W9/W8)-1)*100 -> 1.6694392 | AA9: =((X9/X8)-1)*100 -> 1.6694392
A10: Huw Pill | B10: 2 | C10: Hold | D10: Hold | E10: 13 | F10: =17-E10 -> 4 | G10: Dhingra | H10: -2 | K10: 43678 | L10: =HAVERM!B125 -> 3.9 | M10: =NA() -> #N/A | N10: 0 | Q10: 44774 | R10: =((HAVERM!C161/HAVERM!C149)-1)*100 -> 5.9585492 | S10: =[1]Monthly!QH413 -> 6.0002874 | V10: 2021Q4 | W10: 624592 | X10: ='MPR GDP level'!E18*1000 -> 624592 | Z10: =((W10/W9)-1)*100 -> 1.4839331 | AA10: =((X10/X9)-1)*100 -> 1.4839331
K11: 43709 | L11: =HAVERM!B126 -> 3.7 | M11: =NA() -> #N/A | N11: 0 | Q11: 44805 | R11: =((HAVERM!C162/HAVERM!C150)-1)*100 -> 6.1312608 | S11: =[1]Monthly!QH414 -> 5.9818641 | V11: 2022Q1 | W11: 629149 | X11: ='MPR GDP level'!E19*1000 -> 629149 | Z11: =((W11/W10)-1)*100 -> 0.72959628 | AA11: =((X11/X10)-1)*100 -> 0.72959628
K12: 43739 | L12: =HAVERM!B127 -> 3.5 | M12: =NA() -> #N/A | N12: 0 | Q12: 44835 | R12: =((HAVERM!C163/HAVERM!C151)-1)*100 -> 6.2660944 | S12: =[1]Monthly!QH415 -> 6.2279616 | V12: 2022Q2 | W12: 631258 | X12: ='MPR GDP level'!E20*1000 -> 631258 | Z12: =((W12/W11)-1)*100 -> 0.33521471 | AA12: =((X12/X11)-1)*100 -> 0.33521471
K13: 43770 | L13: =HAVERM!B128 -> 3.3 | M13: =NA() -> #N/A | N13: 0 | Q13: 44866 | R13: =((HAVERM!C164/HAVERM!C152)-1)*100 -> 6.3464837 | S13: =[1]Monthly!QH416 -> 6.6721767 | V13: 2022Q3 | W13: 631977 | X13: ='MPR GDP level'!E21*1000 -> 631977 | Z13: =((W13/W12)-1)*100 -> 0.11389955 | AA13: =((X13/X12)-1)*100 -> 0.11389955
K14: 43800 | L14: =HAVERM!B129 -> 3.2 | M14: =NA() -> #N/A | N14: 0 | Q14: 44896 | R14: =((HAVERM!C165/HAVERM!C153)-1)*100 -> 6.8376068 | S14: =[1]Monthly!QH417 -> 6.9554919 | V14: 2022Q4 | W14: 634044 | X14: ='MPR GDP level'!E22*1000 -> 634044 | Z14: =((W14/W13)-1)*100 -> 0.32706886 | AA14: =((X14/X13)-1)*100 -> 0.32706886
G15: =LEFT(G2,8) -> Pill | K15: 43831 | L15: =HAVERM!B130 -> 3 | M15: =NA() -> #N/A | N15: 0 | Q15: 44927 | R15: =((HAVERM!C166/HAVERM!C154)-1)*100 -> 5.9024808 | S15: =[1]Monthly!QH418 -> 6.388886 | V15: 2023Q1 | W15: 634428 | X15: ='MPR GDP level'!E23*1000 -> 634428 | Z15: =((W15/W14)-1)*100 -> 0.06056362 | AA15: =((X15/X14)-1)*100 -> 0.06056362
G16: =LEFT(G3,14) -> Mann | K16: 43862 | L16: =HAVERM!B131 -> 2.9 | M16: =NA() -> #N/A | N16: 0 | Q16: 44958 | R16: =((HAVERM!C167/HAVERM!C155)-1)*100 -> 6.6496164 | S16: =[1]Monthly!QH419 -> 7.4140324 | V16: 2023Q2 | W16: 634694 | X16: ='MPR GDP level'!E24*1000 -> 634694 | Z16: =((W16/W15)-1)*100 -> 0.041927532 | AA16: =((X16/X15)-1)*100 -> 0.041927532
G17: =LEFT(G4,12) -> Greene | K17: 43891 | L17: =HAVERM!B132 -> 2.5 | M17: =NA() -> #N/A | N17: 0 | Q17: 44986 | R17: =((HAVERM!C168/HAVERM!C156)-1)*100 -> 6.6892464 | S17: =[1]Monthly!QH420 -> 7.0935122 | V17: 2023Q3 | W17: 634327 | X17: ='MPR GDP level'!E25*1000 -> 634327 | Z17: =((W17/W16)-1)*100 -> -0.05782314 | AA17: =((X17/X16)-1)*100 -> -0.05782314
G18: =LEFT(G5,13) -> Bailey | K18: 43922 | L18: =HAVERM!B133 -> 1.3 | M18: =NA() -> #N/A | N18: 0 | Q18: 45017 | R18: =((HAVERM!C169/HAVERM!C157)-1)*100 -> 6.9340017 | S18: =[1]Monthly!QH421 -> 6.758211 | V18: 2023Q4 | W18: 633011 | X18: ='MPR GDP level'!E26*1000 -> 633011 | Z18: =((W18/W17)-1)*100 -> -0.20746397 | AA18: =((X18/X17)-1)*100 -> -0.20746397
G19: =LEFT(G6,17) -> Lombardelli | K19: 43952 | L19: =HAVERM!B134 -> -0.1 | M19: =NA() -> #N/A | N19: 0 | Q19: 45047 | R19: =((HAVERM!C170/HAVERM!C158)-1)*100 -> 7.3211314 | S19: =[1]Monthly!QH422 -> 6.972619 | V19: 2024Q1 | W19: 638746 | X19: ='MPR GDP level'!E27*1000 -> 638746 | Z19: =((W19/W18)-1)*100 -> 0.90598742 | AA19: =((X19/X18)-1)*100 -> 0.90598742
G20: =LEFT(G7,12) -> Ramsden | K20: 43983 | L20: =HAVERM!B135 -> -1.2 | M20: =NA() -> #N/A | N20: 0 | Q20: 45078 | R20: =((HAVERM!C171/HAVERM!C159)-1)*100 -> 7.1900826 | S20: =[1]Monthly!QH423 -> 6.8272077 | V20: 2024Q2 | W20: 641670 | X20: ='MPR GDP level'!E28*1000 -> 641670 | Z20: =((W20/W19)-1)*100 -> 0.45777195 | AA20: =((X20/X19)-1)*100 -> 0.45777195
G21: =LEFT(G8,13) -> Breeden | K21: 44013 | L21: =HAVERM!B136 -> -0.8 | M21: =NA() -> #N/A | N21: 0 | Q21: 45108 | R21: =((HAVERM!C172/HAVERM!C160)-1)*100 -> 7.4651354 | S21: =[1]Monthly!QH424 -> 6.5465999 | V21: 2024Q3 | W21: 641675 | X21: ='MPR GDP level'!E29*1000 -> 641675 | Z21: =((W21/W20)-1)*100 -> 0.00077921673 | AA21: =((X21/X20)-1)*100 -> 0.00077921673
G22: =LEFT(G9,11) -> Taylor | K22: 44044 | L22: =HAVERM!B137 -> 0.1 | M22: =NA() -> #N/A | N22: 0 | Q22: 45139 | R22: =((HAVERM!C173/HAVERM!C161)-1)*100 -> 6.7644662 | S22: =[1]Monthly!QH425 -> 6.3022688 | V22: 2024Q4 | W22: 642287 | X22: ='MPR GDP level'!E30*1000 -> 642287 | Z22: =((W22/W21)-1)*100 -> 0.095375385 | AA22: =((X22/X21)-1)*100 -> 0.095375385
G23: =LEFT(G10,13) -> Dhingra | K23: 44075 | L23: =HAVERM!B138 -> 1.4 | M23: =NA() -> #N/A | N23: 0 | Q23: 45170 | R23: =((HAVERM!C174/HAVERM!C162)-1)*100 -> 6.916192 | S23: =[1]Monthly!QH426 -> 6.422589 | V23: 2025Q1 | W23: 646833 | X23: ='MPR GDP level'!E31*1000 -> 646140.72 | Z23: =((W23/W22)-1)*100 -> 0.70778328 | AA23: =((X23/X22)-1)*100 -> 0.6
K24: 44105 | L24: =HAVERM!B139 -> 2.4 | M24: =NA() -> #N/A | N24: 0 | Q24: 45200 | R24: =((HAVERM!C175/HAVERM!C163)-1)*100 -> 6.542811 | S24: =[1]Monthly!QH427 -> 6.325407 | V24: 2025Q2 | W24: 648085.3 | X24: ='MPR GDP level'!E32*1000 -> 646786.86 | Z24: =((W24/W23)-1)*100 -> 0.19360484 | AA24: =((X24/X23)-1)*100 -> 0.1
K25: 44136 | L25: =HAVERM!B140 -> 3.3 | M25: =NA() -> #N/A | N25: 0 | Q25: 45231 | R25: =((HAVERM!C176/HAVERM!C164)-1)*100 -> 6.2096774 | S25: =[1]Monthly!QH428 -> 5.7115575 | V25: 2025Q3 | W25: 649052.3 | X25: ='MPR GDP level'!E33*1000 -> 648584.93 | Z25: =((W25/W24)-1)*100 -> 0.14920875 | AA25: =((X25/X24)-1)*100 -> 0.278
K26: 44166 | L26: =HAVERM!B141 -> 3.9 | M26: =NA() -> #N/A | N26: 0 | Q26: 45261 | R26: =((HAVERM!C177/HAVERM!C165)-1)*100 -> 6.4 | S26: =[1]Monthly!QH429 -> 5.696703 | V26: 2025Q4 | W26: 650132.4 | X26: ='MPR GDP level'!E34*1000 -> 650831.63 | Z26: =((W26/W25)-1)*100 -> 0.16641186 | AA26: =((X26/X25)-1)*100 -> 0.3464
K27: 44197 | L27: =HAVERM!B142 -> 4.1 | M27: =NA() -> #N/A | N27: 0 | Q27: 45292 | R27: =((HAVERM!C178/HAVERM!C166)-1)*100 -> 6.542811 | S27: =[1]Monthly!QH430 -> 6.3623904 | V27: 2026Q1 | W27: 651660.6 | X27: ='MPR GDP level'!E35*1000 -> 652945.81 | Z27: =((W27/W26)-1)*100 -> 0.23505981 | AA27: =((X27/X26)-1)*100 -> 0.32484367
K28: 44228 | L28: =HAVERM!B143 -> 4.1 | M28: =NA() -> #N/A | N28: 0 | Q28: 45323 | R28: =((HAVERM!C179/HAVERM!C167)-1)*100 -> 6.0751399 | S28: =[1]Monthly!QH431 -> 5.2837116 | V28: 2026Q2 | W28: 653192.8 | X28: ='MPR GDP level'!E36*1000 -> 655104.7 | Z28: =((W28/W27)-1)*100 -> 0.23512239 | AA28: =((X28/X27)-1)*100 -> 0.33063804
K29: 44256 | L29: =HAVERM!B144 -> 4.3 | M29: =NA() -> #N/A | N29: 0 | Q29: 45352 | R29: =((HAVERM!C180/HAVERM!C168)-1)*100 -> 5.952381 | S29: =[1]Monthly!QH432 -> 5.1433799 | V29: 2026Q3 | W29: 654825.8 | X29: ='MPR GDP level'!E37*1000 -> 657209.45 | Z29: =((W29/W28)-1)*100 -> 0.25000276 | AA29: =((X29/X28)-1)*100 -> 0.32128429
K30: 44287 | L30: =HAVERM!B145 -> 5.7 | M30: =NA() -> #N/A | N30: 0 | Q30: 45383 | R30: =((HAVERM!C181/HAVERM!C169)-1)*100 -> 5.859375 | S30: =[1]Monthly!QH433 -> 5.1603245 | V30: 2026Q4 | W30: 656757.1 | X30: ='MPR GDP level'!E38*1000 -> 659478.3 | Z30: =((W30/W29)-1)*100 -> 0.2949334 | AA30: =((X30/X29)-1)*100 -> 0.34522559
K31: 44317 | L31: =HAVERM!B146 -> 7.2 | M31: =NA() -> #N/A | N31: 0 | Q31: 45413 | R31: =((HAVERM!C182/HAVERM!C170)-1)*100 -> 5.7364341 | S31: =[1]Monthly!QH434 -> 4.8937544 | V31: 2027Q1 | W31: 658891.6 | X31: ='MPR GDP level'!E39*1000 -> 662004.23 | Z31: =((W31/W30)-1)*100 -> 0.325006 | AA31: =((X31/X30)-1)*100 -> 0.38301826
K32: 44348 | L32: =HAVERM!B147 -> 8.4 | M32: =NA() -> #N/A | N32: 0 | Q32: 45444 | R32: =((HAVERM!C183/HAVERM!C171)-1)*100 -> 5.7054742 | S32: =[1]Monthly!QH435 -> 4.7659306 | V32: 2027Q2 | W32: 661313.6 | X32: ='MPR GDP level'!E40*1000 -> 664909.16 | Z32: =((W32/W31)-1)*100 -> 0.36758702 | AA32: =((X32/X31)-1)*100 -> 0.43880932
K33: 44378 | L33: =HAVERM!B148 -> 7.8 | M33: =NA() -> #N/A | N33: 0 | Q33: 45474 | R33: =((HAVERM!C184/HAVERM!C172)-1)*100 -> 5.1908397 | S33: =[1]Monthly!QH436 -> 4.8290599 | V33: 2027Q3 | W33: 664090.8 | X33: ='MPR GDP level'!E41*1000 -> 668049.37 | Z33: =((W33/W32)-1)*100 -> 0.41995205 | AA33: =((X33/X32)-1)*100 -> 0.47227661
K34: 44409 | L34: =HAVERM!B149 -> 6.8 | M34: =NA() -> #N/A | N34: 0 | Q34: 45505 | R34: =((HAVERM!C185/HAVERM!C173)-1)*100 -> 5.5725191 | S34: =[1]Monthly!QH437 -> 4.8032612 | V34: 2027Q4 | W34: 667145.4 | X34: ='MPR GDP level'!E42*1000 -> 671265.36 | Z34: =((W34/W33)-1)*100 -> 0.45996722 | AA34: =((X34/X33)-1)*100 -> 0.4814
K35: 44440 | L35: =HAVERM!B150 -> 5.6 | M35: =NA() -> #N/A | N35: 0 | Q35: 45536 | R35: =((HAVERM!C186/HAVERM!C174)-1)*100 -> 4.9467275 | S35: =[1]Monthly!QH438 -> 4.6551381 | V35: 2028Q1 | W35: 670214.5 | X35: ='MPR GDP level'!E43*1000 -> 674436.26 | Z35: =((W35/W34)-1)*100 -> 0.46003465 | AA35: =((X35/X34)-1)*100 -> 0.4723757
K36: 44470 | L36: =HAVERM!B151 -> 4.8 | M36: =NA() -> #N/A | N36: 0 | Q36: 45566 | R36: =((HAVERM!C187/HAVERM!C175)-1)*100 -> 5.0037908 | S36: =[1]Monthly!QH439 -> 4.2953301 | V36: 2028Q2 | W36: 673230.3 | X36: ='MPR GDP level'!E44*1000 -> 677557.55 | Z36: =((W36/W35)-1)*100 -> 0.44997534 | AA36: =((X36/X35)-1)*100 -> 0.4628
K37: 44501 | L37: =HAVERM!B152 -> 4.3 | M37: =NA() -> #N/A | N37: 0 | Q37: 45597 | R37: =((HAVERM!C188/HAVERM!C176)-1)*100 -> 5.0113895 | S37: =[1]Monthly!QH440 -> 4.5956959 | V37: 2028Q3 | W37: 676293.3 | Z37: =((W37/W36)-1)*100 -> 0.45497061
K38: 44531 | L38: =HAVERM!B153 -> 4.2 | M38: =NA() -> #N/A | N38: 0 | Q38: 45627 | R38: =((HAVERM!C189/HAVERM!C177)-1)*100 -> 4.3609023 | S38: =[1]Monthly!QH441 -> 4.4212682 | V38: 2028Q4 | W38: 679201.6 | Z38: =((W38/W37)-1)*100 -> 0.43003531
K39: 44562 | L39: =HAVERM!B154 -> 4.5 | M39: =NA() -> #N/A | N39: 0 | Q39: 45658 | R39: =((HAVERM!C190/HAVERM!C178)-1)*100 -> 5.0037908 | S39: =[1]Monthly!QH442 -> 4.2345706
K40: 44593 | L40: =HAVERM!B155 -> 4.9 | M40: =NA() -> #N/A | N40: 0 | Q40: 45689 | R40: =((HAVERM!C191/HAVERM!C179)-1)*100 -> 4.9736247 | S40: =[1]Monthly!QH443 -> 4.5106231
K41: 44621 | L41: =HAVERM!B156 -> 5.3 | M41: =NA() -> #N/A | N41: 0 | Q41: 45717 | R41: =((HAVERM!C192/HAVERM!C180)-1)*100 -> 4.7191011 | S41: =[1]Monthly!QH444 -> 4.4763402 | W41: OE | X41: BoE
K42: 44652 | L42: =HAVERM!B157 -> 5.2 | M42: =NA() -> #N/A | N42: 0 | Q42: 45748 | R42: =((HAVERM!C193/HAVERM!C181)-1)*100 -> 5.4612546 | S42: =[1]Monthly!QH445 -> 4.279452 | V42: 2024 | W42: =SUM(W19:W22) -> 2564378 | X42: =SUM(X19:X22) -> 2564378
K43: 44682 | L43: =HAVERM!B158 -> 5.4 | M43: =NA() -> #N/A | N43: 0 | Q43: 45778 | V43: 2025 | W43: =SUM(W23:W26) -> 2594103 | X43: =SUM(X23:X26) -> 2592344.1 | Z43: =((W43/W42)-1)*100 -> 1.1591505 | AA43: =((X43/X42)-1)*100 -> 1.0905624
K44: 44713 | L44: =HAVERM!B159 -> 5.7 | M44: =NA() -> #N/A | N44: 0 | Q44: 45809 | V44: 2026 | W44: =SUM(W27:W30) -> 2616436.3 | X44: =SUM(X27:X30) -> 2624738.3 | Z44: =((W44/W43)-1)*100 -> 0.86092572 | AA44: =((X44/X43)-1)*100 -> 1.2496074
K45: 44743 | L45: =HAVERM!B160 -> 6.1 | M45: =NA() -> #N/A | N45: 0 | Q45: 45839
K46: 44774 | L46: =HAVERM!B161 -> 6.4 | M46: =NA() -> #N/A | N46: 0 | Q46: 45870
K47: 44805 | L47: =HAVERM!B162 -> 6.7 | M47: =NA() -> #N/A | N47: 0 | Q47: 45901
K48: 44835 | L48: =HAVERM!B163 -> 7 | M48: =NA() -> #N/A | N48: 0 | Q48: 45931
K49: 44866 | L49: =HAVERM!B164 -> 7.3 | M49: =NA() -> #N/A | N49: 0 | Q49: 45962
K50: 44896 | L50: =HAVERM!B165 -> 7.3 | M50: =NA() -> #N/A | N50: 0 | Q50: 45992
K51: 44927 | L51: =HAVERM!B166 -> 7.1 | M51: =NA() -> #N/A | N51: 0
K52: 44958 | L52: =HAVERM!B167 -> 7.1 | M52: =NA() -> #N/A | N52: 0
K53: 44986 | L53: =HAVERM!B168 -> 7.2 | M53: =NA() -> #N/A | N53: 0
K54: 45017 | L54: =HAVERM!B169 -> 7.7 | M54: =NA() -> #N/A | N54: 0
K55: 45047 | L55: =HAVERM!B170 -> 7.9 | M55: =NA() -> #N/A | N55: 0
K56: 45078 | L56: =HAVERM!B171 -> 8.2 | M56: =NA() -> #N/A | N56: 0
K57: 45108 | L57: =HAVERM!B172 -> 8.1 | M57: =NA() -> #N/A | N57: 0
K58: 45139 | L58: =HAVERM!B173 -> 8.1 | M58: =NA() -> #N/A | N58: 0
K59: 45170 | L59: =HAVERM!B174 -> 7.8 | M59: =NA() -> #N/A | N59: 0
K60: 45200 | L60: =HAVERM!B175 -> 7.2 | M60: =NA() -> #N/A | N60: 0
K61: 45231 | L61: =HAVERM!B176 -> 6.6 | M61: =NA() -> #N/A | N61: 0
K62: 45261 | L62: =HAVERM!B177 -> 6.2 | M62: =NA() -> #N/A | N62: 0
... K76: 45689 | L76: =HAVERM!B191 -> 5.9 | M76: =NA() -> #N/A | N76: 0
K77: 45717 | L77: =HAVERM!B192 -> 5.6 | M77: ='MPR Chart 2.16'!B91 -> 5.759 | N77: 0
K78: 45748 | M78: =NA() -> #N/A | N78: 0
K79: 45778 | M79: =NA() -> #N/A | N79: 0
K80: 45809 | M80: ='MPR Chart 2.16'!B94 -> 5.202 | N80: 0
K81: 45839 | M81: =NA() -> #N/A | N81: 0
K82: 45870 | M82: =NA() -> #N/A | N82: 0
K83: 45901 | M83: ='MPR Chart 2.16'!B97 -> 4.711 | N83: 0
K84: 45931 | M84: =NA() -> #N/A | N84: 0
K85: 45962 | M85: =NA() -> #N/A | N85: 0
K86: 45992 | M86: ='MPR Chart 2.16'!B100 -> 3.841 | N86: 0

Sheet MPR Chart 2.16
A1: Section 2: Current economic conditions
A2: Chart 2.16 - Measures of private sector wage growth
A4: Date | B4: Private sector regular pay | C4: Indicator-based model | D4: Agents' Pay survey | E4: DMP expected wage growth | G4: Indeed wage tracker | H4: KPMG/REC (advanced 12 months) | I4: HMRC RTI median (private sector proxy) | J4: DMP (realised)
A5: 43131 | B5: 2.7 | C5: n.a | D5: =$C$5 -> n.a | E5: =$C$5 -> n.a | G5: n.a | H5: No permissions | I5: 3.1 | J5: n.a
A6: 43159 | B6: 2.9 | C6: n.a | D6: =$C$5 -> n.a | E6: =$C$5 -> n.a | G6: n.a | I6: 3.3 | J6: n.a
A7: 43190 | B7: 3 | C7: 2.9 | D7: =$C$5 -> n.a | E7: =$C$5 -> n.a | G7: n.a | I7: 3.2 | J7: n.a
A8: 43220 | B8: 3 | C8: n.a | D8: =$C$5 -> n.a | E8: =$C$5 -> n.a | G8: n.a | I8: 3 | J8: n.a
A9: 43251 | B9: 2.9 | C9: n.a | D9: =$C$5 -> n.a | E9: =$C$5 -> n.a | G9: n.a | I9: 3.2 | J9: n.a
A10: 43281 | B10: 2.8 | C10: 3.1 | D10: =$C$5 -> n.a | E10: =$C$5 -> n.a | G10: n.a | I10: 3.4 | J10: n.a
A11: 43312 | B11: 3 | C11: n.a | D11: =$C$5 -> n.a | E11: =$C$5 -> n.a | G11: n.a | I11: 3.8 | J11: n.a
A12: 43343 | B12: 3.2 | C12: n.a | D12: =$C$5 -> n.a | E12: =$C$5 -> n.a | G12: n.a | I12: 3.9 | J12: n.a
A13: 43373 | B13: 3.3 | C13: 3.3 | D13: =$C$5 -> n.a | E13: =$C$5 -> n.a | G13: n.a | I13: 3.8 | J13: n.a
A14: 43404 | B14: 3.4 | C14: n.a | D14: =$C$5 -> n.a | E14: =$C$5 -> n.a | G14: n.a | I14: 3.8 | J14: n.a
A15: 43434 | B15: 3.4 | C15: n.a | D15: =$C$5 -> n.a | E15: =$C$5 -> n.a | G15: n.a | I15: 3.7 | J15: n.a
A16: 43465 | B16: 3.5 | C16: 3.5 | D16: =$C$5 -> n.a | E16: =$C$5 -> n.a | G16: n.a | I16: 3.7 | J16: n.a
A17: 43496 | B17: 3.6 | C17: n.a | D17: =$C$5 -> n.a | E17: =$C$5 -> n.a | G17: n.a | I17: 3.6 | J17: n.a
A18: 43524 | B18: 3.6 | C18: n.a | D18: =$C$5 -> n.a | E18: =$C$5 -> n.a | G18: n.a | I18: 3.6 | J18: n.a
A19: 43555 | B19: 3.6 | C19: 3.5 | D19: =$C$5 -> n.a | E19: =$C$5 -> n.a | G19: 4.4 | I19: 3.7 | J19: n.a
A20: 43585 | B20: 3.6 | C20: n.a | D20: =$C$5 -> n.a | E20: =$C$5 -> n.a | G20: 4.3 | I20: 3.7 | J20: n.a
A21: 43616 | B21: 3.7 | C21: n.a | D21: =$C$5 -> n.a | E21: =$C$5 -> n.a | G21: 4 | I21: 3.7 | J21: n.a
A22: 43646 | B22: 3.9 | C22: 3.5 | D22: =$C$5 -> n.a | E22: =$C$5 -> n.a | G22: 3.7 | I22: 3.4 | J22: n.a
A23: 43677 | B23: 4 | C23: n.a | D23: =$C$5 -> n.a | E23: =$C$5 -> n.a | G23: 3.6 | I23: 3.4 | J23: n.a
A24: 43708 | B24: 3.9 | C24: n.a | D24: =$C$5 -> n.a | E24: =$C$5 -> n.a | G24: 3.5 | I24: 3.2 | J24: n.a
A25: 43738 | B25: 3.7 | C25: 3.4 | D25: =$C$5 -> n.a | E25: =$C$5 -> n.a | G25: 3.5 | I25: 3.4 | J25: n.a
A26: 43769 | B26: 3.5 | C26: n.a | D26: =$C$5 -> n.a | E26: =$C$5 -> n.a | G26: 3.4 | I26: 3.2 | J26: n.a
A27: 43799 | B27: 3.3 | C27: n.a | D27: =$C$5 -> n.a | E27: =$C$5 -> n.a | G27: 3.3 | I27: 3.1 | J27: n.a
A28: 43830 | B28: 3.2 | C28: 3.3 | D28: =$C$5 -> n.a | E28: =$C$5 -> n.a | G28: 3.3 | I28: 3.1 | J28: n.a
A29: 43861 | B29: 3 | C29: n.a | D29: =$C$5 -> n.a | E29: =$C$5 -> n.a | G29: 2.8 | I29: 3.4 | J29: n.a
A30: 43890 | B30: 2.9 | C30: n.a | D30: =$C$5 -> n.a | E30: =$C$5 -> n.a | G30: 2.3 | I30: 3.7 | J30: n.a
A31: 43921 | B31: 2.5 | C31: 3.1 | D31: =$C$5 -> n.a | E31: =$C$5 -> n.a | G31: 1.9 | I31: 3.3 | J31: n.a
A32: 43951 | B32: 1.3 | C32: n.a | D32: =$C$5 -> n.a | E32: =$C$5 -> n.a | G32: 3.2 | I32: 1.3 | J32: n.a
A33: 43982 | B33: -0.1 | C33: n.a | D33: =$C$5 -> n.a | E33: =$C$5 -> n.a | G33: 4.1 | I33: -1 | J33: n.a
A34: 44012 | B34: -1.2 | C34: 2 | D34: =$C$5 -> n.a | E34: =$C$5 -> n.a | G34: 4.5 | I34: -1.9 | J34: n.a
A35: 44043 | B35: -0.8 | C35: n.a | D35: =$C$5 -> n.a | E35: =$C$5 -> n.a | G35: 3.9 | I35: -0.6 | J35: n.a
A36: 44074 | B36: 0.1 | C36: n.a | D36: =$C$5 -> n.a | E36: =$C$5 -> n.a | G36: 3.5 | I36: 1.2 | J36: n.a
A37: 44104 | B37: 1.4 | C37: 1.3 | D37: =$C$5 -> n.a | E37: =$C$5 -> n.a | G37: 3.3 | I37: 2.7 | J37: n.a
A38: 44135 | B38: 2.4 | C38: n.a | D38: =$C$5 -> n.a | E38: =$C$5 -> n.a | G38: 3.3 | I38: 3.7 | J38: n.a
A39: 44165 | B39: 3.3 | C39: n.a | D39: =$C$5 -> n.a | E39: =$C$5 -> n.a | G39: 3.3 | I39: 4.2 | J39: n.a
A40: 44196 | B40: 3.9 | C40: 1.2 | D40: =$C$5 -> n.a | E40: =$C$5 -> n.a | G40: 3.4 | I40: 4.5 | J40: n.a
A41: 44227 | B41: 4.1 | C41: n.a | D41: =$C$5 -> n.a | E41: =$C$5 -> n.a | G41: 3.6 | I41: 4.2 | J41: n.a
A42: 44255 | B42: 4.2 | C42: n.a | D42: =$C$5 -> n.a | E42: =$C$5 -> n.a | G42: 3.7 | I42: 4 | J42: n.a
A43: 44286 | B43: 4.3 | C43: 0.9 | D43: =$C$5 -> n.a | E43: =$C$5 -> n.a | G43: 3.5 | I43: 4.4 | J43: n.a
A44: 44316 | B44: 5.7 | C44: n.a | D44: =$C$5 -> n.a | E44: =$C$5 -> n.a | G44: 2.3 | I44: 7 | J44: n.a
A45: 44347 | B45: 7.2 | C45: n.a | D45: =$C$5 -> n.a | E45: =$C$5 -> n.a | G45: 1.6 | I45: 9.5 | J45: n.a
A46: 44377 | B46: 8.4 | C46: 1.7 | D46: =$C$5 -> n.a | E46: =$C$5 -> n.a | G46: 1.4 | I46: 11 | J46: n.a
A47: 44408 | B47: 7.8 | C47: n.a | D47: =$C$5 -> n.a | E47: =$C$5 -> n.a | G47: 2.3 | I47: 9.6 | J47: n.a
A48: 44439 | B48: 6.8 | C48: n.a | D48: =$C$5 -> n.a | E48: =$C$5 -> n.a | G48: 3.1 | I48: 7.9 | J48: n.a
A49: 44469 | B49: 5.6 | C49: 2.7 | D49: =$C$5 -> n.a | E49: =$C$5 -> n.a | G49: 3.5 | I49: 6.5 | J49: n.a
A50: 44500 | B50: 4.8 | C50: n.a | D50: =$C$5 -> n.a | E50: =$C$5 -> n.a | G50: 3.8 | I50: 6 | J50: n.a
A51: 44530 | B51: 4.3 | C51: n.a | D51: =$C$5 -> n.a | E51: =$C$5 -> n.a | G51: 3.9 | I51: 6.1 | J51: n.a
A52: 44561 | B52: 4.2 | C52: 3.3 | D52: =$C$5 -> n.a | E52: =$C$5 -> n.a | G52: 4 | I52: 6.3 | J52: n.a
A53: 44592 | B53: 4.5 | C53: n.a | D53: =$C$5 -> n.a | E53: =$C$5 -> n.a | G53: 4 | I53: 6.5 | J53: n.a
A54: 44620 | B54: 4.9 | C54: n.a | D54: =$C$5 -> n.a | E54: =$C$5 -> n.a | G54: 4.2 | I54: 6.6 | J54: n.a
A55: 44651 | B55: 5.3 | C55: 4.5 | D55: =$C$5 -> n.a | E55: =$C$5 -> n.a | G55: 4.7 | I55: 6.8 | J55: n.a
A56: 44681 | B56: 5.2 | C56: n.a | D56: =$C$5 -> n.a | E56: =$C$5 -> n.a | G56: 5.5 | I56: 6.7 | J56: n.a
A57: 44712 | B57: 5.4 | C57: n.a | D57: =$C$5 -> n.a | E57: =$C$5 -> n.a | G57: 6.3 | I57: 6.8 | J57: 5.5
A58: 44742 | B58: 5.7 | C58: 5.4 | D58: =$C$5 -> n.a | E58: =$C$5 -> n.a | G58: 6.6 | I58: 6.8 | J58: 5.6
A59: 44773 | B59: 6.1 | C59: n.a | D59: =$C$5 -> n.a | E59: =$C$5 -> n.a | G59: 6.5 | I59: 7.1 | J59: 5.5
A60: 44804 | B60: 6.4 | C60: n.a | D60: =$C$5 -> n.a | E60: =$C$5 -> n.a | G60: 6.5 | I60: 7.1 | J60: 5.8
A61: 44834 | B61: 6.7 | C61: 6.1 | D61: =$C$5 -> n.a | E61: =$C$5 -> n.a | G61: 6.4 | I61: 7.1 | J61: 6.1
A62: 44865 | B62: 7 | C62: n.a | D62: =$C$5 -> n.a | E62: =$C$5 -> n.a | G62: 6.4 | I62: 7 | J62: 6.3
A63: 44895 | B63: 7.3 | C63: n.a | D63: =$C$5 -> n.a | E63: =$C$5 -> n.a | G63: 6.3 | I63: 6.9 | J63: 6.2
A64: 44926 | B64: 7.3 | C64: 6.5 | D64: =$C$5 -> n.a | E64: =$C$5 -> n.a | G64: 6.4 | I64: 6.9 | J64: 6.3
A65: 44957 | B65: 7.1 | C65: n.a | D65: =$C$5 -> n.a | E65: =$C$5 -> n.a | G65: 6.4 | I65: 7.1 | J65: 6.3
A66: 44985 | B66: 7.1 | C66: n.a | D66: =$C$5 -> n.a | E66: =$C$5 -> n.a | G66: 6.5 | I66: 7.3 | J66: 6.5
A67: 45016 | B67: 7.2 | C67: 6.6 | D67: =$C$5 -> n.a | E67: =$C$5 -> n.a | G67: 6.7 | I67: 7.4 | J67: 6.5
A68: 45046 | B68: 7.7 | C68: n.a | D68: =$C$5 -> n.a | E68: =$C$5 -> n.a | G68: 7 | I68: 7.3 | J68: 6.6
A69: 45077 | B69: 7.9 | C69: n.a | D69: =$C$5 -> n.a | E69: =$C$5 -> n.a | G69: 7.2 | I69: 7.2 | J69: 6.6
A70: 45107 | B70: 8.2 | C70: 6.6 | D70: =$C$5 -> n.a | E70: =$C$5 -> n.a | G70: 7.3 | I70: 7 | J70: 6.8
A71: 45138 | B71: 8.1 | C71: n.a | D71: =$C$5 -> n.a | E71: =$C$5 -> n.a | G71: 7.3 | I71: 6.9 | J71: 6.8
A72: 45169 | B72: 8.1 | C72: n.a | D72: =$C$5 -> n.a | E72: =$C$5 -> n.a | G72: 7.2 | I72: 6.9 | J72: 6.9
A73: 45199 | B73: 7.8 | C73: 6.3 | D73: =$C$5 -> n.a | E73: =$C$5 -> n.a | G73: 7.1 | I73: 7 | J73: 6.9
A74: 45230 | B74: 7.2 | C74: n.a | D74: =$C$5 -> n.a | E74: =$C$5 -> n.a | G74: 6.8 | I74: 6.7 | J74: 6.9
A75: 45260 | B75: 6.6 | C75: n.a | D75: =$C$5 -> n.a | E75: =$C$5 -> n.a | G75: 6.7 | I75: 6.3 | J75: 7
A76: 45291 | B76: 6.2 | C76: 5.8 | D76: =$C$5 -> n.a | E76: =$C$5 -> n.a | G76: 6.6 | I76: 6 | J76: 6.9
A77: 45322 | B77: 6.1 | C77: n.a | D77: =$C$5 -> n.a | E77: =$C$5 -> n.a | G77: 6.5 | I77: 6 | J77: 6.9
A78: 45351 | B78: 5.9 | C78: n.a | D78: =$C$5 -> n.a | E78: =$C$5 -> n.a | G78: 6.4 | I78: 6 | J78: 6.7
A79: 45382 | B79: 5.8 | C79: 5.6 | D79: =$C$5 -> n.a | E79: =$C$5 -> n.a | G79: 6.4 | I79: 6 | J79: 6.4
A80: 45412 | B80: 5.7 | C80: n.a | D80: =$C$5 -> n.a | E80: =$C$5 -> n.a | G80: 6.6 | I80: 6.2 | J80: 6.2
A81: 45443 | B81: 5.6 | C81: n.a | D81: =$C$5 -> n.a | E81: =$C$5 -> n.a | G81: 6.7 | I81: 6.2 | J81: 6
A82: 45473 | B82: 5.4 | C82: 5.5 | D82: =$C$5 -> n.a | E82: =$C$5 -> n.a | G82: 6.8 | I82: 6.2 | J82: 6
A83: 45504 | B83: 5.2 | C83: n.a | D83: =$C$5 -> n.a | E83: =$C$5 -> n.a | G83: 6.6 | I83: 6.2 | J83: 5.9
A84: 45535 | B84: 5.1 | C84: n.a | D84: =$C$5 -> n.a | E84: =$C$5 -> n.a | G84: 6.6 | I84: 6.1 | J84: 5.8
A85: 45565 | B85: 5.1 | C85: 5.4 | D85: =$C$5 -> n.a | E85: =$C$5 -> n.a | G85: 6.6 | I85: 5.9 | J85: 5.7
A86: 45596 | B86: 5.6 | C86: n.a | D86: =$C$5 -> n.a | E86: =$C$5 -> n.a | G86: 6.7 | I86: 6 | J86: 5.6
A87: 45626 | B87: 5.9 | C87: n.a | D87: =$C$5 -> n.a | E87: =$C$5 -> n.a | G87: 6.5 | I87: 6.2 | J87: 5.5
A88: 45657 | B88: 6.2 | C88: 5.6 | D88: =$C$5 -> n.a | E88: =$C$5 -> n.a | G88: 6.4 | I88: 6.2 | J88: 5.4
A89: 45688 | B89: 5.9 | C89: n.a | D89: =$C$5 -> n.a | E89: =$C$5 -> n.a | G89: 6.2 | I89: 6.1 | J89: 5.3
A90: 45716 | B90: 5.9 | C90: n.a | D90: =$C$5 -> n.a | E90: =$C$5 -> n.a | G90: 6.1 | I90: 5.8 | J90: 5.2
A91: Mar 2025 (Bank staff projections) | B91: 5.759 | C91: 5.4 | D91: =$C$5 -> n.a | E91: =$C$5 -> n.a | G91: 5.8 | I91: 5.4 | J91: 5
A92: 45777 | B92: =$C$92 -> n.a | C92: =$C$90 -> n.a | D92: =$C$5 -> n.a | E92: =$C$5 -> n.a | G92: n.a | I92: n.a | J92: 4.8
A93: 45808 | B93: =$C$92 -> n.a | C93: =$C$90 -> n.a | D93: =$C$5 -> n.a | E93: =$C$5 -> n.a | G93: n.a | I93: n.a | J93: n.a
A94: June 2025 (Bank staff projections) | B94: 5.202 | C94: =$C$90 -> n.a | D94: =$C$5 -> n.a | E94: =$C$5 -> n.a | G94: n.a | I94: n.a | J94: n.a
A95: 45869 | B95: =$C$92 -> n.a | C95: =$C$90 -> n.a | D95: =$C$5 -> n.a | E95: =$C$5 -> n.a | G95: n.a | I95: n.a | J95: n.a
A96: 45900 | B96: =$C$92 -> n.a | C96: =$C$90 -> n.a | D96: =$C$5 -> n.a | E96: =$C$5 -> n.a | G96: n.a | I96: n.a | J96: n.a
A97: September 2025 (Bank staff projections) | B97: 4.711 | C97: =$C$90 -> n.a | D97: =$C$5 -> n.a | E97: =$C$5 -> n.a | G97: n.a | I97: n.a | J97: n.a
A98: 45961 | B98: =$C$92 -> n.a | C98: =$C$90 -> n.a | D98: =$C$5 -> n.a | E98: =$C$5 -> n.a | G98: n.a | I98: n.a | J98: n.a
A99: 45991 | B99: =$C$92 -> n.a | C99: =$C$90 -> n.a | D99: =$C$5 -> n.a | E99: =$C$5 -> n.a | G99: n.a | I99: n.a | J99: n.a
A100: December 2025 (Bank staff projections) | B100: 3.841 | C100: =$C$90 -> n.a | D100: =$C$5 -> n.a | E100: =$C$5 -> n.a | G100: n.a | I100: n.a | J100: n.a
A101: 46053 | B101: =$C$92 -> n.a | C101: =$C$90 -> n.a | D101: 3.7 | E101: =$C$5 -> n.a | G101: n.a | I101: n.a | J101: n.a
...

Sheet Not used >>>

Sheet HAVERM
A4: 201001 !M | B4: KAJ4@UK | C4: D7F5@UK
A5: .DESC | B5: Great Britain: AWE, Regular Pay: Private Sector [3Mo Mvg Avg vs Yr Ago] (SA, %) | C5: UK: Consumer Price Index: All Services (NSA, 2015=100)
A6: .T1 | B6: Mar-2001 | C6: Jan-1988
A7: .TN | B7: Mar-2025 | C7: Apr-2025
A8: .LSOURCE | B8: Office for National Statistics | C8: Office for National Statistics
A9: .DTLM | B9: May-13-2025 07:03 | C9: May-21-2025 07:02
A10: 201001 | B10: 0.5 | C10: 83.9
A11: 201002 | B11: 0.7 | C11: 84.1
A12: 201003 | B12: 1 | C12: 84.4
A13: 201004 | B13: 0.9 | C13: 84.9
A14: 201005 | B14: 0.8 | C14: 85.2
A15: 201006 | B15: 0.6 | C15: 85.7
A16: 201007 | B16: 1 | C16: 86.1
A17: 201008 | B17: 1.6 | C17: 86.7
A18: 201009 | B18: 2 | C18: 85.9
A19: 201010 | B19: 2 | C19: 86.3
A20: 201011 | B20: 2 | C20: 86.1
A21: 201012 | B21: 1.9 | C21: 87.2
... A192: 202503 | B192: 5.6 | C192: 139.8
A193: 202504 | C193: 142.9

Sheet MPR GDP level
D4: GDP, £ billion chained-volume measure (reference year 2022)
E6: GDP projections based on market interest rate expectations, other policy measures as announced | F6: GDP projections based on interest rates constant at 4.25%, other policy measures as announced
D10: DATE
D11: 2020Q1 | E11: 604.719 | F11: 604.719
D12: 2020Q2 | E12: 481.769 | F12: 481.769
D13: 2020Q3 | E13: 562.648 | F13: 562.648
D14: 2020Q4 | E14: 570.338 | F14: 570.338
D15: 2021Q1 | E15: 564.411 | F15: 564.411
D16: 2021Q2 | E16: 605.353 | F16: 605.353
D17: 2021Q3 | E17: 615.459 | F17: 615.459
D18: 2021Q4 | E18: 624.592 | F18: 624.592
D19: 2022Q1 | E19: 629.149 | F19: 629.149
D20: 2022Q2 | E20: 631.258 | F20: 631.258
D21: 2022Q3 | E21: 631.977 | F21: 631.977
D22: 2022Q4 | E22: 634.044 | F22: 634.044
... D44: 2028Q2 | E44: 677.55755 | F44: 671.62146
