Workbook
Name _DLX1.INC: HAVERM!$B$2:$AH$7
Name _DLX2.INC: HAVERD!$G$3:$GV$8
Name _DLX3.INC: HAVERQ!$B$2:$H$7
Name Data: [1]sheet0!$C$2

Sheet >> MARKET PRICING CHARTS

Sheet >> DATA

Sheet Chart Data
A1: Services inflation | G1: Private sector pay growth | K1: Inflation forecasts | R1: BoE DMP | X1: BoE DMP | AD1: Trade policy uncertainty
B2: Outturn | C2: BoE staff forecast (May) | D2: BoE staff forecast (Aug) | E2: BoE staff forecast (Nov)
B3: Outturn | E3: BoE forecast | H3: Outturn | I3: BoE forecast | L3: CPI inflation | M3: BoE market expectations (Aug) | N3: OE (Oct) | O3: HMT consensus (Oct) | P3: 2% LINE | S3: Prices - past year | T3: Prices - next year | U3: Wages - past year | V3: Wages - next year | Y3: Prices - past year | Z3: Prices - next year | AA3: Wages - past year | AB3: Wages - next year | AE3: UK economic policy uncertainty (LHS) | AF3: US trade policy uncertainty (RHS)
A4: 44562 | B4: =100*((HAVERM!D152/HAVERM!D140)-1) -> 3.2685512 | G4: 44562 | H4: =HAVERM!E152 -> 4.5 | K4: 44927 | L4: =100*((HAVERQ!F40/HAVERQ!F36)-1) -> 10.178263 | P4: 2 | R4: 43466 | S4: =HAVERM!F116 -> 2.79 | T4: =HAVERM!G116 -> 2.531 | U4: =HAVERM!H116 -> #N/A | V4: =HAVERM!I116 -> #N/A | X4: 43466 | Y4: =HAVERM!J116 -> 2.525 | Z4: =HAVERM!K116 -> 2.471 | AA4: =HAVERM!L116 -> #N/A | AB4: =HAVERM!M116 -> #N/A | AD4: 42005 | AE4: =HAVERM!P68 -> 135.73044 | AF4: ='Bloom - Monthly US data'!M362 -> 33.807758
A5: 44593 | B5: =100*((HAVERM!D153/HAVERM!D141)-1) -> 3.4391534 | G5: 44593 | H5: =HAVERM!E153 -> 4.9 | K5: 45017 | L5: =100*((HAVERQ!F41/HAVERQ!F37)-1) -> 8.4390513 | P5: 2 | R5: 43497 | S5: =HAVERM!F117 -> 2.23 | T5: =HAVERM!G117 -> 2.56 | U5: =HAVERM!H117 -> #N/A | V5: =HAVERM!I117 -> #N/A | X5: 43497 | Y5: =HAVERM!J117 -> 2.415 | Z5: =HAVERM!K117 -> 2.424 | AA5: =HAVERM!L117 -> #N/A | AB5: =HAVERM!M117 -> #N/A | AD5: 42036 | AE5: =HAVERM!P69 -> 119.08362 | AF5: ='Bloom - Monthly US data'!M363 -> 15.410779
A6: 44621 | B6: =100*((HAVERM!D154/HAVERM!D142)-1) -> 3.9612676 | G6: 44621 | H6: =HAVERM!E154 -> 5.3 | K6: 45108 | L6: =100*((HAVERQ!F42/HAVERQ!F38)-1) -> 6.7135896 | P6: 2 | R6: 43525 | S6: =HAVERM!F118 -> 2.4 | T6: =HAVERM!G118 -> 2.066 | U6: =HAVERM!H118 -> #N/A | V6: =HAVERM!I118 -> #N/A | X6: 43525 | Y6: =HAVERM!J118 -> 2.474 | Z6: =HAVERM!K118 -> 2.386 | AA6: =HAVERM!L118 -> #N/A | AB6: =HAVERM!M118 -> #N/A | AD6: 42064 | AE6: =HAVERM!P70 -> 131.49865 | AF6: ='Bloom - Monthly US data'!M364 -> 27.907613
A7: 44652 | B7: =100*((HAVERM!D155/HAVERM!D143)-1) -> 4.7244094 | G7: 44652 | H7: =HAVERM!E155 -> 5.2 | K7: 45200 | L7: =100*((HAVERQ!F43/HAVERQ!F39)-1) -> 4.1568008 | P7: 2 | R7: 43556 | S7: =HAVERM!F119 -> 2.87 | T7: =HAVERM!G119 -> 2.705 | U7: =HAVERM!H119 -> #N/A | V7: =HAVERM!I119 -> #N/A | X7: 43556 | Y7: =HAVERM!J119 -> 2.501 | Z7: =HAVERM!K119 -> 2.444 | AA7: =HAVERM!L119 -> #N/A | AB7: =HAVERM!M119 -> #N/A | AD7: 42095 | AE7: =HAVERM!P71 -> 170.47333 | AF7: ='Bloom - Monthly US data'!M365 -> 41.600503
A8: 44682 | B8: =100*((HAVERM!D156/HAVERM!D144)-1) -> 4.886562 | G8: 44682 | H8: =HAVERM!E156 -> 5.4 | K8: 45292 | L8: =100*((HAVERQ!F44/HAVERQ!F40)-1) -> 3.5490605 | N8: =100*((GMW!B211/GMW!B207)-1) -> 3.5491137 | P8: 2 | R8: 43586 | S8: =HAVERM!F120 -> 1.78 | T8: =HAVERM!G120 -> 2.318 | U8: =HAVERM!H120 -> #N/A | V8: =HAVERM!I120 -> #N/A | X8: 43586 | Y8: =HAVERM!J120 -> 2.348 | Z8: =HAVERM!K120 -> 2.363 | AA8: =HAVERM!L120 -> #N/A | AB8: =HAVERM!M120 -> #N/A | AD8: 42125 | AE8: =HAVERM!P72 -> 140.91246 | AF8: ='Bloom - Monthly US data'!M366 -> 88.91986
A9: 44713 | B9: =100*((HAVERM!D157/HAVERM!D145)-1) -> 5.2173913 | G9: 44713 | H9: =HAVERM!E157 -> 5.7 | K9: 45383 | L9: =100*((HAVERQ!F45/HAVERQ!F41)-1) -> 2.110885 | N9: =100*((GMW!B212/GMW!B208)-1) -> 2.1108336 | P9: 2 | R9: 43617 | S9: =HAVERM!F121 -> 2.7 | T9: =HAVERM!G121 -> 2.158 | U9: =HAVERM!H121 -> #N/A | V9: =HAVERM!I121 -> #N/A | X9: 43617 | Y9: =HAVERM!J121 -> 2.449 | Z9: =HAVERM!K121 -> 2.394 | AA9: =HAVERM!L121 -> #N/A | AB9: =HAVERM!M121 -> #N/A | AD9: 42156 | AE9: =HAVERM!P73 -> 148.81656 | AF9: ='Bloom - Monthly US data'!M367 -> 100.80304
A10: 44743 | B10: =100*((HAVERM!D158/HAVERM!D146)-1) -> 5.7241977 | G10: 44743 | H10: =HAVERM!E158 -> 6.1 | K10: 45474 | L10: =100*((HAVERQ!F46/HAVERQ!F42)-1) -> 2.0547945 | M10: =HAVERQ!C46 -> #N/A | N10: =100*((GMW!B213/GMW!B209)-1) -> 2.0547945 | P10: 2 | R10: 43647 | S10: =HAVERM!F122 -> 2.26 | T10: =HAVERM!G122 -> 2.099 | U10: =HAVERM!H122 -> #N/A | V10: =HAVERM!I122 -> #N/A | X10: 43647 | Y10: =HAVERM!J122 -> 2.246 | Z10: =HAVERM!K122 -> 2.192 | AA10: =HAVERM!L122 -> #N/A | AB10: =HAVERM!M122 -> #N/A | AD10: 42186 | AE10: =HAVERM!P74 -> 136.10011 | AF10: ='Bloom - Monthly US data'!M368 -> 51.49282
A11: 44774 | B11: =100*((HAVERM!D159/HAVERM!D147)-1) -> 5.9585492 | G11: 44774 | H11: =HAVERM!E159 -> 6.4 | K11: 45566 | M11: =HAVERQ!C47 -> #N/A | N11: =100*((GMW!B214/GMW!B210)-1) -> 2.4753214 | O11: 2.6 | P11: 2 | R11: 43678 | S11: =HAVERM!F123 -> 1.91 | T11: =HAVERM!G123 -> 2.281 | U11: =HAVERM!H123 -> #N/A | V11: =HAVERM!I123 -> #N/A | X11: 43678 | Y11: =HAVERM!J123 -> 2.291 | Z11: =HAVERM!K123 -> 2.179 | AA11: =HAVERM!L123 -> #N/A | AB11: =HAVERM!M123 -> #N/A | AD11: 42217 | AE11: =HAVERM!P75 -> 86.14368 | AF11: ='Bloom - Monthly US data'!M369 -> 20.829576
A12: 44805 | B12: =100*((HAVERM!D160/HAVERM!D148)-1) -> 6.1312608 | G12: 44805 | H12: =HAVERM!E160 -> 6.7 | K12: 45658 | M12: =HAVERQ!C48 -> 2.8 | N12: =100*((GMW!B215/GMW!B211)-1) -> 2.6789056 | P12: 2 | R12: 43709 | S12: =HAVERM!F124 -> 2.26 | T12: =HAVERM!G124 -> 2.345 | U12: =HAVERM!H124 -> #N/A | V12: =HAVERM!I124 -> #N/A | X12: 43709 | Y12: =HAVERM!J124 -> 2.142 | Z12: =HAVERM!K124 -> 2.241 | AA12: =HAVERM!L124 -> #N/A | AB12: =HAVERM!M124 -> #N/A | AD12: 42248 | AE12: =HAVERM!P76 -> 135.07501 | AF12: ='Bloom - Monthly US data'!M370 -> 19.60964
A13: 44835 | B13: =100*((HAVERM!D161/HAVERM!D149)-1) -> 6.2660944 | G13: 44835 | H13: =HAVERM!E161 -> 7 | K13: 45748 | M13: =HAVERQ!C49 -> 3.5 | N13: =100*((GMW!B216/GMW!B212)-1) -> 2.8477965 | P13: 2 | R13: 43739 | S13: =HAVERM!F125 -> 1.99 | T13: =HAVERM!G125 -> 2.214 | U13: =HAVERM!H125 -> #N/A | V13: =HAVERM!I125 -> #N/A | X13: 43739 | Y13: =HAVERM!J125 -> 2.053 | Z13: =HAVERM!K125 -> 2.28 | AA13: =HAVERM!L125 -> #N/A | AB13: =HAVERM!M125 -> #N/A | AD13: 42278 | AE13: =HAVERM!P77 -> 89.91453 | AF13: ='Bloom - Monthly US data'!M371 -> 68.608963
A14: 44866 | B14: =100*((HAVERM!D162/HAVERM!D150)-1) -> 6.3464837 | G14: 44866 | H14: =HAVERM!E162 -> 7.3 | K14: 45839 | M14: =HAVERQ!C50 -> 3.7 | N14: =100*((GMW!B217/GMW!B213)-1) -> 3.2950783 | P14: 2 | R14: 43770 | S14: =HAVERM!F126 -> 1.86 | T14: =HAVERM!G126 -> 2.152 | U14: =HAVERM!H126 -> #N/A | V14: =HAVERM!I126 -> #N/A | X14: 43770 | Y14: =HAVERM!J126 -> 2.037 | Z14: =HAVERM!K126 -> 2.237 | AA14: =HAVERM!L126 -> #N/A | AB14: =HAVERM!M126 -> #N/A | AD14: 42309 | AE14: =HAVERM!P78 -> 120.86215 | AF14: ='Bloom - Monthly US data'!M372 -> 20.503122
A15: 44896 | B15: =100*((HAVERM!D163/HAVERM!D151)-1) -> 6.8376068 | G15: 44896 | H15: =HAVERM!E163 -> 7.3 | K15: 45931 | M15: =HAVERQ!C51 -> 3.5 | N15: =100*((GMW!B218/GMW!B214)-1) -> 3.1315512 | O15: 2.2 | P15: 2 | R15: 43800 | S15: =HAVERM!F127 -> 1.99 | T15: =HAVERM!G127 -> 2.372 | U15: =HAVERM!H127 -> #N/A | V15: =HAVERM!I127 -> #N/A | X15: 43800 | Y15: =HAVERM!J127 -> 1.948 | Z15: =HAVERM!K127 -> 2.246 | AA15: =HAVERM!L127 -> #N/A | AB15: =HAVERM!M127 -> #N/A | AD15: 42339 | AE15: =HAVERM!P79 -> 82.87279 | AF15: ='Bloom - Monthly US data'!M373 -> 20.475546
A16: 44927 | B16: =100*((HAVERM!D164/HAVERM!D152)-1) -> 5.9024808 | G16: 44927 | H16: =HAVERM!E164 -> 7.1 | K16: 46023 | M16: =HAVERQ!C52 -> 3 | N16: =100*((GMW!B219/GMW!B215)-1) -> 2.9609749 | P16: 2 | R16: 43831 | S16: =HAVERM!F128 -> 2.06 | T16: =HAVERM!G128 -> 2.117 | U16: =HAVERM!H128 -> #N/A | V16: =HAVERM!I128 -> #N/A | X16: 43831 | Y16: =HAVERM!J128 -> 1.971 | Z16: =HAVERM!K128 -> 2.214 | AA16: =HAVERM!L128 -> #N/A | AB16: =HAVERM!M128 -> #N/A | AD16: 42370 | AE16: =HAVERM!P80 -> 135.63232 | AF16: ='Bloom - Monthly US data'!M374 -> 42.781123
A17: 44958 | B17: =100*((HAVERM!D165/HAVERM!D153)-1) -> 6.6496164 | G17: 44958 | H17: =HAVERM!E165 -> 7.1 | K17: 46113 | M17: =HAVERQ!C53 -> 2.6 | N17: =100*((GMW!B220/GMW!B216)-1) -> 2.5644304 | P17: 2 | R17: 43862 | S17: =HAVERM!F129 -> 1.74 | T17: =HAVERM!G129 -> 2.094 | U17: =HAVERM!H129 -> #N/A | V17: =HAVERM!I129 -> #N/A | X17: 43862 | Y17: =HAVERM!J129 -> 1.931 | Z17: =HAVERM!K129 -> 2.195 | AA17: =HAVERM!L129 -> #N/A | AB17: =HAVERM!M129 -> #N/A | AD17: 42401 | AE17: =HAVERM!P81 -> 190.81671 | AF17: ='Bloom - Monthly US data'!M375 -> 26.272142
A18: 44986 | B18: =100*((HAVERM!D166/HAVERM!D154)-1) -> 6.6892464 | G18: 44986 | H18: =HAVERM!E166 -> 7.2 | K18: 46204 | M18: =HAVERQ!C54 -> 2.6 | N18: =100*((GMW!B221/GMW!B217)-1) -> 2.3642295 | P18: 2 | R18: 43891 | S18: =HAVERM!F130 -> 1.69 | T18: =HAVERM!G130 -> 1.598 | U18: =HAVERM!H130 -> #N/A | V18: =HAVERM!I130 -> #N/A | X18: 43891 | Y18: =HAVERM!J130 -> 1.83 | Z18: =HAVERM!K130 -> 1.937 | AA18: =HAVERM!L130 -> #N/A | AB18: =HAVERM!M130 -> #N/A | AD18: 42430 | AE18: =HAVERM!P82 -> 290.92952 | AF18: ='Bloom - Monthly US data'!M376 -> 49.187943
A19: 45017 | B19: =100*((HAVERM!D167/HAVERM!D155)-1) -> 6.9340017 | G19: 45017 | H19: =HAVERM!E167 -> 7.7 | K19: 46296 | M19: =HAVERQ!C55 -> 2.4 | N19: =100*((GMW!B222/GMW!B218)-1) -> 2.2010035 | P19: 2 | R19: 43922 | S19: =HAVERM!F131 -> 1.87 | T19: =HAVERM!G131 -> 1.213 | U19: =HAVERM!H131 -> #N/A | V19: =HAVERM!I131 -> #N/A | X19: 43922 | Y19: =HAVERM!J131 -> 1.765 | Z19: =HAVERM!K131 -> 1.635 | AA19: =HAVERM!L131 -> #N/A | AB19: =HAVERM!M131 -> #N/A | AD19: 42461 | AE19: =HAVERM!P83 -> 197.1708 | AF19: ='Bloom - Monthly US data'!M377 -> 42.923388
A20: 45047 | B20: =100*((HAVERM!D168/HAVERM!D156)-1) -> 7.3211314 | G20: 45047 | H20: =HAVERM!E168 -> 7.9 | K20: 46388 | M20: =HAVERQ!C56 -> 2.3 | N20: =100*((GMW!B223/GMW!B219)-1) -> 2.1744059 | P20: 2 | R20: 43952 | S20: =HAVERM!F132 -> 1.72 | T20: =HAVERM!G132 -> 1.389 | U20: =HAVERM!H132 -> #N/A | V20: =HAVERM!I132 -> #N/A | X20: 43952 | Y20: =HAVERM!J132 -> 1.759 | Z20: =HAVERM!K132 -> 1.4 | AA20: =HAVERM!L132 -> #N/A | AB20: =HAVERM!M132 -> #N/A | AD20: 42491 | AE20: =HAVERM!P84 -> 246.75491 | AF20: ='Bloom - Monthly US data'!M378 -> 76.848017
A21: 45078 | B21: =100*((HAVERM!D169/HAVERM!D157)-1) -> 7.1900826 | G21: 45078 | H21: =HAVERM!E169 -> 8.2 | K21: 46478 | M21: =HAVERQ!C57 -> 2.2 | N21: =100*((GMW!B224/GMW!B220)-1) -> 2.128077 | P21: 2 | R21: 43983 | S21: =HAVERM!F133 -> 1.18 | T21: =HAVERM!G133 -> 1.431 | U21: =HAVERM!H133 -> #N/A | V21: =HAVERM!I133 -> #N/A | X21: 43983 | Y21: =HAVERM!J133 -> 1.59 | Z21: =HAVERM!K133 -> 1.344 | AA21: =HAVERM!L133 -> #N/A | AB21: =HAVERM!M133 -> #N/A | AD21: 42522 | AE21: =HAVERM!P85 -> 503.94249 | AF21: ='Bloom - Monthly US data'!M379 -> 271.07246
A22: 45108 | B22: =100*((HAVERM!D170/HAVERM!D158)-1) -> 7.4651354 | G22: 45108 | H22: =HAVERM!E170 -> 8.1 | K22: 46569 | M22: =HAVERQ!C58 -> 2.1 | N22: =100*((GMW!B225/GMW!B221)-1) -> 2.1274585 | P22: 2 | R22: 44013 | S22: =HAVERM!F134 -> 1.34 | T22: =HAVERM!G134 -> 1.661 | U22: =HAVERM!H134 -> #N/A | V22: =HAVERM!I134 -> #N/A | X22: 44013 | Y22: =HAVERM!J134 -> 1.414 | Z22: =HAVERM!K134 -> 1.494 | AA22: =HAVERM!L134 -> #N/A | AB22: =HAVERM!M134 -> #N/A | AD22: 42552 | AE22: =HAVERM!P86 -> 558.22364 | AF22: ='Bloom - Monthly US data'!M380 -> 116.30264
A23: 45139 | B23: =100*((HAVERM!D171/HAVERM!D159)-1) -> 6.7644662 | G23: 45139 | H23: =HAVERM!E171 -> 8.1 | K23: 46661 | N23: =100*((GMW!B226/GMW!B222)-1) -> 2.1133327 | P23: 2 | R23: 44044 | S23: =HAVERM!F135 -> 1.04 | T23: =HAVERM!G135 -> 2.16 | U23: =HAVERM!H135 -> #N/A | V23: =HAVERM!I135 -> #N/A | X23: 44044 | Y23: =HAVERM!J135 -> 1.187 | Z23: =HAVERM!K135 -> 1.751 | AA23: =HAVERM!L135 -> #N/A | AB23: =HAVERM!M135 -> #N/A | AD23: 42583 | AE23: =HAVERM!P87 -> 311.36483 | AF23: ='Bloom - Monthly US data'!M381 -> 155.27431
A24: 45170 | B24: =100*((HAVERM!D172/HAVERM!D160)-1) -> 6.916192 | G24: 45170 | H24: =HAVERM!E172 -> 7.8 | R24: 44075 | S24: =HAVERM!F136 -> 1.57 | T24: =HAVERM!G136 -> 1.853 | U24: =HAVERM!H136 -> #N/A | V24: =HAVERM!I136 -> #N/A | X24: 44075 | Y24: =HAVERM!J136 -> 1.317 | Z24: =HAVERM!K136 -> 1.891 | AA24: =HAVERM!L136 -> #N/A | AB24: =HAVERM!M136 -> #N/A | AD24: 42614 | AE24: =HAVERM!P88 -> 209.63794 | AF24: ='Bloom - Monthly US data'!M382 -> 93.079444
A25: 45200 | B25: =100*((HAVERM!D173/HAVERM!D161)-1) -> 6.542811 | G25: 45200 | H25: =HAVERM!E173 -> 7.2 | R25: 44105 | S25: =HAVERM!F137 -> 2.21 | T25: =HAVERM!G137 -> 2.354 | U25: =HAVERM!H137 -> #N/A | V25: =HAVERM!I137 -> #N/A | X25: 44105 | Y25: =HAVERM!J137 -> 1.606 | Z25: =HAVERM!K137 -> 2.122 | AA25: =HAVERM!L137 -> #N/A | AB25: =HAVERM!M137 -> #N/A | AD25: 42644 | AE25: =HAVERM!P89 -> 270.02349 | AF25: ='Bloom - Monthly US data'!M383 -> 83.538371
A26: 45231 | B26: =100*((HAVERM!D174/HAVERM!D162)-1) -> 6.2096774 | G26: 45231 | H26: =HAVERM!E174 -> 6.6 | R26: 44136 | S26: =HAVERM!F138 -> 1.69 | T26: =HAVERM!G138 -> 2.092 | U26: =HAVERM!H138 -> #N/A | V26: =HAVERM!I138 -> #N/A | X26: 44136 | Y26: =HAVERM!J138 -> 1.823 | Z26: =HAVERM!K138 -> 2.099 | AA26: =HAVERM!L138 -> #N/A | AB26: =HAVERM!M138 -> #N/A | AD26: 42675 | AE26: =HAVERM!P90 -> 358.82841 | AF26: ='Bloom - Monthly US data'!M384 -> 540.4187
A27: 45261 | B27: =100*((HAVERM!D175/HAVERM!D163)-1) -> 6.4 | G27: 45261 | H27: =HAVERM!E175 -> 6.2 | R27: 44166 | S27: =HAVERM!F139 -> 0.88 | T27: =HAVERM!G139 -> 2.705 | U27: =HAVERM!H139 -> #N/A | V27: =HAVERM!I139 -> #N/A | X27: 44166 | Y27: =HAVERM!J139 -> 1.591 | Z27: =HAVERM!K139 -> 2.383 | AA27: =HAVERM!L139 -> #N/A | AB27: =HAVERM!M139 -> #N/A | AD27: 42705 | AE27: =HAVERM!P91 -> 196.34369 | AF27: ='Bloom - Monthly US data'!M385 -> 275.12017
A28: 45292 | B28: =100*((HAVERM!D176/HAVERM!D164)-1) -> 6.542811 | G28: 45292 | H28: =HAVERM!E176 -> 6.1 | R28: 44197 | S28: =HAVERM!F140 -> 1.83 | T28: =HAVERM!G140 -> 2.517 | U28: =HAVERM!H140 -> #N/A | V28: =HAVERM!I140 -> #N/A | X28: 44197 | Y28: =HAVERM!J140 -> 1.467 | Z28: =HAVERM!K140 -> 2.438 | AA28: =HAVERM!L140 -> #N/A | AB28: =HAVERM!M140 -> #N/A | AD28: 42736 | AE28: =HAVERM!P92 -> 257.8484 | AF28: ='Bloom - Monthly US data'!M386 -> 474.80271
A29: 45323 | B29: =100*((HAVERM!D177/HAVERM!D165)-1) -> 6.0751399 | G29: 45323 | H29: =HAVERM!E177 -> 5.9 | R29: 44228 | S29: =HAVERM!F141 -> 2.05 | T29: =HAVERM!G141 -> 2.719 | U29: =HAVERM!H141 -> #N/A | V29: =HAVERM!I141 -> #N/A | X29: 44228 | Y29: =HAVERM!J141 -> 1.589 | Z29: =HAVERM!K141 -> 2.647 | AA29: =HAVERM!L141 -> #N/A | AB29: =HAVERM!M141 -> #N/A | AD29: 42767 | AE29: =HAVERM!P93 -> 194.0447 | AF29: ='Bloom - Monthly US data'!M387 -> 250.13309
A30: 45352 | B30: =100*((HAVERM!D178/HAVERM!D166)-1) -> 5.952381 | G30: 45352 | H30: =HAVERM!E178 -> 5.8 | R30: 44256 | S30: =HAVERM!F142 -> 1.65 | T30: =HAVERM!G142 -> 2.973 | U30: =HAVERM!H142 -> #N/A | V30: =HAVERM!I142 -> #N/A | X30: 44256 | Y30: =HAVERM!J142 -> 1.847 | Z30: =HAVERM!K142 -> 2.736 | AA30: =HAVERM!L142 -> #N/A | AB30: =HAVERM!M142 -> #N/A | AD30: 42795 | AE30: =HAVERM!P94 -> 232.45973 | AF30: ='Bloom - Monthly US data'!M388 -> 151.94312
A31: 45383 | B31: =100*((HAVERM!D179/HAVERM!D167)-1) -> 5.859375 | C31: ='MPR Chart 2.16 (May)'!L70 -> 5.52 | G31: 45383 | H31: =HAVERM!E179 -> 5.7 | R31: 44287 | S31: =HAVERM!F143 -> 2.79 | T31: =HAVERM!G143 -> 3.139 | U31: =HAVERM!H143 -> #N/A | V31: =HAVERM!I143 -> #N/A | X31: 44287 | Y31: =HAVERM!J143 -> 2.165 | Z31: =HAVERM!K143 -> 2.944 | AA31: =HAVERM!L143 -> #N/A | AB31: =HAVERM!M143 -> #N/A | AD31: 42826 | AE31: =HAVERM!P95 -> 169.17604 | AF31: ='Bloom - Monthly US data'!M389 -> 153.35011
A32: 45413 | B32: =100*((HAVERM!D180/HAVERM!D168)-1) -> 5.7364341 | C32: ='MPR Chart 2.16 (May)'!L71 -> 5.258 | G32: 45413 | H32: =HAVERM!E180 -> 5.6 | R32: 44317 | S32: =HAVERM!F144 -> 2.83 | T32: =HAVERM!G144 -> 3.442 | U32: =HAVERM!H144 -> #N/A | V32: =HAVERM!I144 -> #N/A | X32: 44317 | Y32: =HAVERM!J144 -> 2.424 | Z32: =HAVERM!K144 -> 3.185 | AA32: =HAVERM!L144 -> #N/A | AB32: =HAVERM!M144 -> #N/A | AD32: 42856 | AE32: =HAVERM!P96 -> 159.40145 | AF32: ='Bloom - Monthly US data'!M390 -> 87.267511
A33: 45444 | B33: =100*((HAVERM!D181/HAVERM!D169)-1) -> 5.7054742 | C33: ='MPR Chart 2.16 (May)'!L72 -> 5.134 | G33: 45444 | H33: =HAVERM!E181 -> 5.4 | R33: 44348 | S33: =HAVERM!F145 -> 3.13 | T33: =HAVERM!G145 -> 3.258 | U33: =HAVERM!H145 -> #N/A | V33: =HAVERM!I145 -> #N/A | X33: 44348 | Y33: =HAVERM!J145 -> 2.915 | Z33: =HAVERM!K145 -> 3.28 | AA33: =HAVERM!L145 -> #N/A | AB33: =HAVERM!M145 -> #N/A | AD33: 42887 | AE33: =HAVERM!P97 -> 318.99116 | AF33: ='Bloom - Monthly US data'!M391 -> 86.858279
A34: 45474 | B34: =100*((HAVERM!D182/HAVERM!D170)-1) -> 5.1908397 | C34: ='MPR Chart 2.16 (May)'!L73 -> 4.949 | D34: ='MPR Chart 2.16 (Aug)'!L49 -> 5.563 | G34: 45474 | H34: =HAVERM!E182 -> 5.2 | R34: 44378 | S34: =HAVERM!F146 -> 3.77 | T34: =HAVERM!G146 -> 2.931 | U34: =HAVERM!H146 -> #N/A | V34: =HAVERM!I146 -> #N/A | X34: 44378 | Y34: =HAVERM!J146 -> 3.24 | Z34: =HAVERM!K146 -> 3.21 | AA34: =HAVERM!L146 -> #N/A | AB34: =HAVERM!M146 -> #N/A | AD34: 42917 | AE34: =HAVERM!P98 -> 183.65895 | AF34: ='Bloom - Monthly US data'!M392 -> 92.143455
A35: 45505 | B35: =100*((HAVERM!D183/HAVERM!D171)-1) -> 5.5725191 | C35: ='MPR Chart 2.16 (May)'!L74 -> 5.001 | D35: ='MPR Chart 2.16 (Aug)'!L50 -> 5.84 | G35: 45505 | H35: =HAVERM!E183 -> 5.1 | R35: 44409 | S35: =HAVERM!F147 -> 3.45 | T35: =HAVERM!G147 -> 3.23 | U35: =HAVERM!H147 -> #N/A | V35: =HAVERM!I147 -> #N/A | X35: 44409 | Y35: =HAVERM!J147 -> 3.445 | Z35: =HAVERM!K147 -> 3.14 | AA35: =HAVERM!L147 -> #N/A | AB35: =HAVERM!M147 -> #N/A | AD35: 42948 | AE35: =HAVERM!P99 -> 151.2043 | AF35: ='Bloom - Monthly US data'!M393 -> 91.351067
A36: 45536 | B36: =100*((HAVERM!D184/HAVERM!D172)-1) -> 4.9467275 | C36: ='MPR Chart 2.16 (May)'!L75 -> 4.728 | D36: ='MPR Chart 2.16 (Aug)'!L51 -> 5.52 | G36: 45536 | H36: =HAVERM!E184 -> 5.1 | I36: ='MPR Chart 2.29 (Nov)'!B32 -> 4.753 | R36: 44440 | S36: =HAVERM!F148 -> 4.53 | T36: =HAVERM!G148 -> 4.098 | U36: =HAVERM!H148 -> #N/A | V36: =HAVERM!I148 -> #N/A | X36: 44440 | Y36: =HAVERM!J148 -> 3.913 | Z36: =HAVERM!K148 -> 3.42 | AA36: =HAVERM!L148 -> #N/A | AB36: =HAVERM!M148 -> #N/A | AD36: 42979 | AE36: =HAVERM!P100 -> 140.77882 | AF36: ='Bloom - Monthly US data'!M394 -> 76.291078
A37: 45566 | B37: =100*((HAVERM!D185/HAVERM!D173)-1) -> 5.0037908 | D37: ='MPR Chart 2.16 (Aug)'!L52 -> 5.502 | E37: ='MPR Chart 2.22 (Nov)'!L52 -> 4.972 | G37: 45566 | R37: 44470 | S37: =HAVERM!F149 -> 5.41 | T37: =HAVERM!G149 -> 4.724 | U37: =HAVERM!H149 -> #N/A | V37: =HAVERM!I149 -> #N/A | X37: 44470 | Y37: =HAVERM!J149 -> 4.461 | Z37: =HAVERM!K149 -> 4.017 | AA37: =HAVERM!L149 -> #N/A | AB37: =HAVERM!M149 -> #N/A | AD37: 43009 | AE37: =HAVERM!P101 -> 184.03005 | AF37: ='Bloom - Monthly US data'!M395 -> 96.872971
A38: 45597 | B38: =100*((HAVERM!D186/HAVERM!D174)-1) -> 5.0113895 | D38: ='MPR Chart 2.16 (Aug)'!L53 -> 5.395 | E38: ='MPR Chart 2.22 (Nov)'!L53 -> 4.913 | G38: 45597 | R38: 44501 | S38: =HAVERM!F150 -> 4.81 | T38: =HAVERM!G150 -> 4.411 | U38: =HAVERM!H150 -> #N/A | V38: =HAVERM!I150 -> #N/A | X38: 44501 | Y38: =HAVERM!J150 -> 4.916 | Z38: =HAVERM!K150 -> 4.411 | AA38: =HAVERM!L150 -> #N/A | AB38: =HAVERM!M150 -> #N/A | AD38: 43040 | AE38: =HAVERM!P102 -> 214.97008 | AF38: ='Bloom - Monthly US data'!M396 -> 49.481161
A39: 45627 | B39: =100*((HAVERM!D187/HAVERM!D175)-1) -> 4.3609023 | D39: ='MPR Chart 2.16 (Aug)'!L54 -> 5.286 | E39: ='MPR Chart 2.22 (Nov)'!L54 -> 4.739 | G39: 45627 | I39: ='MPR Chart 2.29 (Nov)'!B33 -> 5.065 | R39: 44531 | S39: =HAVERM!F151 -> 5.48 | T39: =HAVERM!G151 -> 5.094 | U39: =HAVERM!H151 -> #N/A | V39: =HAVERM!I151 -> #N/A | X39: 44531 | Y39: =HAVERM!J151 -> 5.233 | Z39: =HAVERM!K151 -> 4.743 | AA39: =HAVERM!L151 -> #N/A | AB39: =HAVERM!M151 -> #N/A | AD39: 43070 | AE39: =HAVERM!P103 -> 160.7223 | AF39: ='Bloom - Monthly US data'!M397 -> 182.29972
A40: 45658 | E40: ='MPR Chart 2.22 (Nov)'!L55 -> 5.112 | G40: 45658 | R40: 44562 | S40: =HAVERM!F152 -> 5.41 | T40: =HAVERM!G152 -> 4.542 | U40: =HAVERM!H152 -> #N/A | V40: =HAVERM!I152 -> #N/A | X40: 44562 | Y40: =HAVERM!J152 -> 5.235 | Z40: =HAVERM!K152 -> 4.682 | AA40: =HAVERM!L152 -> #N/A | AB40: =HAVERM!M152 -> #N/A | AD40: 43101 | AE40: =HAVERM!P104 -> 123.16 | AF40: ='Bloom - Monthly US data'!M398 -> 247.78682
A41: 45689 | E41: ='MPR Chart 2.22 (Nov)'!L56 -> 4.965 | G41: 45689 | R41: 44593 | S41: =HAVERM!F153 -> 5.24 | T41: =HAVERM!G153 -> 4.863 | U41: =HAVERM!H153 -> #N/A | V41: =HAVERM!I153 -> #N/A | X41: 44593 | Y41: =HAVERM!J153 -> 5.378 | Z41: =HAVERM!K153 -> 4.833 | AA41: =HAVERM!L153 -> #N/A | AB41: =HAVERM!M153 -> #N/A | AD41: 43132 | AE41: =HAVERM!P105 -> 109.74873 | AF41: ='Bloom - Monthly US data'!M399 -> 69.094742
A42: 45717 | E42: ='MPR Chart 2.22 (Nov)'!L57 -> 4.894 | G42: 45717 | I42: ='MPR Chart 2.29 (Nov)'!B34 -> 4.76 | R42: 44621 | S42: =HAVERM!F154 -> 6.82 | T42: =HAVERM!G154 -> 5.857 | U42: =HAVERM!H154 -> #N/A | V42: =HAVERM!I154 -> #N/A | X42: 44621 | Y42: =HAVERM!J154 -> 5.825 | Z42: =HAVERM!K154 -> 5.087 | AA42: =HAVERM!L154 -> #N/A | AB42: =HAVERM!M154 -> #N/A | AD42: 43160 | AE42: =HAVERM!P106 -> 116.6054 | AF42: ='Bloom - Monthly US data'!M400 -> 524.65186
R43: 44652 | S43: =HAVERM!F155 -> 6.5 | T43: =HAVERM!G155 -> 5.999 | U43: =HAVERM!H155 -> #N/A | V43: =HAVERM!I155 -> #N/A | X43: 44652 | Y43: =HAVERM!J155 -> 6.187 | Z43: =HAVERM!K155 -> 5.573 | AA43: =HAVERM!L155 -> #N/A | AB43: =HAVERM!M155 -> #N/A | AD43: 43191 | AE43: =HAVERM!P107 -> 102.28703 | AF43: ='Bloom - Monthly US data'!M401 -> 463.18065
R44: 44682 | S44: =HAVERM!F156 -> 7.27 | T44: =HAVERM!G156 -> 5.842 | U44: =HAVERM!H156 -> 5.5 | V44: =HAVERM!I156 -> 4.8 | X44: 44682 | Y44: =HAVERM!J156 -> 6.863 | Z44: =HAVERM!K156 -> 5.899 | AA44: =HAVERM!L156 -> 5.465 | AB44: =HAVERM!M156 -> 4.787 | AD44: 43221 | AE44: =HAVERM!P108 -> 121.5437 | AF44: ='Bloom - Monthly US data'!M402 -> 283.08382
R45: 44713 | S45: =HAVERM!F157 -> 7.46 | T45: =HAVERM!G157 -> 6.298 | U45: =HAVERM!H157 -> 5.7 | V45: =HAVERM!I157 -> 5.1 | X45: 44713 | Y45: =HAVERM!J157 -> 7.077 | Z45: =HAVERM!K157 -> 6.046 | AA45: =HAVERM!L157 -> 5.578 | AB45: =HAVERM!M157 -> 4.931 | AD45: 43252 | AE45: =HAVERM!P109 -> 105.48677 | AF45: ='Bloom - Monthly US data'!M403 -> 688.39964
R46: 44743 | S46: =HAVERM!F158 -> 7.98 | T46: =HAVERM!G158 -> 6.678 | U46: =HAVERM!H158 -> 5.5 | V46: =HAVERM!I158 -> 5.2 | X46: 44743 | Y46: =HAVERM!J158 -> 7.568 | Z46: =HAVERM!K158 -> 6.272 | AA46: =HAVERM!L158 -> 5.541 | AB46: =HAVERM!M158 -> 5.014 | AD46: 43282 | AE46: =HAVERM!P110 -> 129.62264 | AF46: ='Bloom - Monthly US data'!M404 -> 904.71914
R47: 44774 | S47: =HAVERM!F159 -> 7.65 | T47: =HAVERM!G159 -> 6.416 | U47: =HAVERM!H159 -> 6.4 | V47: =HAVERM!I159 -> 5.5 | X47: 44774 | Y47: =HAVERM!J159 -> 7.695 | Z47: =HAVERM!K159 -> 6.464 | AA47: =HAVERM!L159 -> 5.844 | AB47: =HAVERM!M159 -> 5.244 | AD47: 43313 | AE47: =HAVERM!P111 -> 121.62975 | AF47: ='Bloom - Monthly US data'!M405 -> 469.29295
R48: 44805 | S48: =HAVERM!F160 -> 7.41 | T48: =HAVERM!G160 -> 6.629 | U48: =HAVERM!H160 -> 6.5 | V48: =HAVERM!I160 -> 5.8 | X48: 44805 | Y48: =HAVERM!J160 -> 7.677 | Z48: =HAVERM!K160 -> 6.574 | AA48: =HAVERM!L160 -> 6.098 | AB48: =HAVERM!M160 -> 5.501 | AD48: 43344 | AE48: =HAVERM!P112 -> 157.31582 | AF48: ='Bloom - Monthly US data'!M406 -> 323.39119
R49: 44835 | S49: =HAVERM!F161 -> 7.76 | T49: =HAVERM!G161 -> 6.221 | U49: =HAVERM!H161 -> 6.1 | V49: =HAVERM!I161 -> 5.9 | X49: 44835 | Y49: =HAVERM!J161 -> 7.604 | Z49: =HAVERM!K161 -> 6.422 | AA49: =HAVERM!L161 -> 6.306 | AB49: =HAVERM!M161 -> 5.729 | AD49: 43374 | AE49: =HAVERM!P113 -> 183.25267 | AF49: ='Bloom - Monthly US data'!M407 -> 443.2303
R50: 44866 | S50: =HAVERM!F162 -> 7.17 | T50: =HAVERM!G162 -> 5.708 | U50: =HAVERM!H162 -> 6.1 | V50: =HAVERM!I162 -> 5.8 | X50: 44866 | Y50: =HAVERM!J162 -> 7.445 | Z50: =HAVERM!K162 -> 6.186 | AA50: =HAVERM!L162 -> 6.219 | AB50: =HAVERM!M162 -> 5.833 | AD50: 43405 | AE50: =HAVERM!P114 -> 191.96646 | AF50: ='Bloom - Monthly US data'!M408 -> 403.07749
R51: 44896 | S51: =HAVERM!F163 -> 8.6 | T51: =HAVERM!G163 -> 5.785 | U51: =HAVERM!H163 -> 6.6 | V51: =HAVERM!I163 -> 6.3 | X51: 44896 | Y51: =HAVERM!J163 -> 7.843 | Z51: =HAVERM!K163 -> 5.904 | AA51: =HAVERM!L163 -> 6.26 | AB51: =HAVERM!M163 -> 5.982 | AD51: 43435 | AE51: =HAVERM!P115 -> 239.69103 | AF51: ='Bloom - Monthly US data'!M409 -> 681.87189
R52: 44927 | S52: =HAVERM!F164 -> 7.9 | T52: =HAVERM!G164 -> 5.8 | U52: =HAVERM!H164 -> 6.3 | V52: =HAVERM!I164 -> 5.7 | X52: 44927 | Y52: =HAVERM!J164 -> 7.892 | Z52: =HAVERM!K164 -> 5.764 | AA52: =HAVERM!L164 -> 6.339 | AB52: =HAVERM!M164 -> 5.94 | AD52: 43466 | AE52: =HAVERM!P116 -> 309.97245 | AF52: ='Bloom - Monthly US data'!M410 -> 715.62023
R53: 44958 | S53: =HAVERM!F165 -> 7.76 | T53: =HAVERM!G165 -> 5.364 | U53: =HAVERM!H165 -> 6.6 | V53: =HAVERM!I165 -> 5.8 | X53: 44958 | Y53: =HAVERM!J165 -> 8.089 | Z53: =HAVERM!K165 -> 5.65 | AA53: =HAVERM!L165 -> 6.51 | AB53: =HAVERM!M165 -> 5.928 | AD53: 43497 | AE53: =HAVERM!P117 -> 196.95946 | AF53: ='Bloom - Monthly US data'!M411 -> 307.09272
R54: 44986 | S54: =HAVERM!F166 -> 7.82 | T54: =HAVERM!G166 -> 5.314 | U54: =HAVERM!H166 -> 6.5 | V54: =HAVERM!I166 -> 5.6 | X54: 44986 | Y54: =HAVERM!J166 -> 7.83 | Z54: =HAVERM!K166 -> 5.492 | AA54: =HAVERM!L166 -> 6.478 | AB54: =HAVERM!M166 -> 5.682 | AD54: 43525 | AE54: =HAVERM!P118 -> 212.78254 | AF54: ='Bloom - Monthly US data'!M412 -> 287.66535
... R74: 45597 | S74: =HAVERM!F186 -> 3.67 | T74: =HAVERM!G186 -> 3.781 | U74: =HAVERM!H186 -> 5.5 | V74: =HAVERM!I186 -> 3.8 | X74: 45597 | Y74: =HAVERM!J186 -> 3.907 | Z74: =HAVERM!K186 -> 3.666 | AA74: =HAVERM!L186 -> 5.509 | AB74: =HAVERM!M186 -> 4.008 | AD74: 44136 | AE74: =HAVERM!P138 -> 214.46165 | AF74: ='Bloom - Monthly US data'!M432 -> 204.60834
R75: 45627 | X75: 45627 | AD75: 44166 | AE75: =HAVERM!P139 -> 207.60651 | AF75: ='Bloom - Monthly US data'!M433 -> 123.58402
AD76: 44197 | AE76: =HAVERM!P140 -> 112.63906 | AF76: ='Bloom - Monthly US data'!M434 -> 72.345173
AD77: 44228 | AE77: =HAVERM!P141 -> 138.00995 | AF77: ='Bloom - Monthly US data'!M435 -> 52.348352
AD78: 44256 | AE78: =HAVERM!P142 -> 142.40594 | AF78: ='Bloom - Monthly US data'!M436 -> 47.673848
AD79: 44287 | AE79: =HAVERM!P143 -> 95.28068 | AF79: ='Bloom - Monthly US data'!M437 -> 72.419087
AD80: 44317 | AE80: =HAVERM!P144 -> 98.11193 | AF80: ='Bloom - Monthly US data'!M438 -> 42.693271
AD81: 44348 | AE81: =HAVERM!P145 -> 90.33494 | AF81: ='Bloom - Monthly US data'!M439 -> 40.750573
AD82: 44378 | AE82: =HAVERM!P146 -> 88.28377 | AF82: ='Bloom - Monthly US data'!M440 -> 20.807926
AD83: 44409 | AE83: =HAVERM!P147 -> 79.1091 | AF83: ='Bloom - Monthly US data'!M441 -> 31.874577
AD84: 44440 | AE84: =HAVERM!P148 -> 78.70093 | AF84: ='Bloom - Monthly US data'!M442 -> 7.6726184
AD85: 44470 | AE85: =HAVERM!P149 -> 103.98979 | AF85: ='Bloom - Monthly US data'!M443 -> 40.942715
AD86: 44501 | AE86: =HAVERM!P150 -> 75.3175 | AF86: ='Bloom - Monthly US data'!M444 -> 53.022959
AD87: 44531 | AE87: =HAVERM!P151 -> 174.83134 | AF87: ='Bloom - Monthly US data'!M445 -> 24.930457
... AD126: 45717 | AE126: =HAVERM!P190 -> 472.9471 | AF126: ='Bloom - Monthly US data'!M484 -> 5735.9528

Sheet Market pricing dates
A2: February 2025 MPR | B2: 45688 | D2: May 2025 MPR | E2: 45776
A4: Last 5 working days | D4: Last 5 working days
A5: =TEXT(B5,"dddd") -> Monday | B5: =IF(A6="Monday",B6-3,B6-1) -> 45684 | D5: =TEXT(E5,"dddd") -> Wednesday | E5: =IF(D6="Monday",E6-3,E6-1) -> 45770
A6: =TEXT(B6,"dddd") -> Tuesday | B6: =IF(A7="Monday",B7-3,B7-1) -> 45685 | D6: =TEXT(E6,"dddd") -> Thursday | E6: =IF(D7="Monday",E7-3,E7-1) -> 45771
A7: =TEXT(B7,"dddd") -> Wednesday | B7: =IF(A8="Monday",B8-3,B8-1) -> 45686 | D7: =TEXT(E7,"dddd") -> Friday | E7: =IF(D8="Monday",E8-3,E8-1) -> 45772
A8: =TEXT(B8,"dddd") -> Thursday | B8: =IF(A9="Monday",B9-3,B9-1) -> 45687 | D8: =TEXT(E8,"dddd") -> Monday | E8: =IF(D9="Monday",E9-3,E9-1) -> 45775
A9: =TEXT(B9,"dddd") -> Friday | B9: =B2 -> 45688 | D9: =TEXT(E9,"dddd") -> Tuesday | E9: =E2 -> 45776
B11: =TEXT(B9,"dd mmm yyyy") -> 31 Jan 2025 | E11: =TEXT(E9,"dd mmm yyyy") -> 29 Apr 2025
A12: ="15 working days to "&B11 -> 15 working days to 31 Jan 2025 | D12: ="15 working days to "&E11 -> 15 working days to 29 Apr 2025

Sheet Bloom - Monthly US data
A1: Year | B1: Month | C1: 1. Economic Policy Uncertainty | D1: 2. Monetary policy | E1: Fiscal Policy (Taxes OR Spending) | F1: 3. Taxes | G1: 4. Government spending | H1: 5. Health care | I1: 6. National security | J1: 7. Entitlement programs | K1: 8. Regulation | L1: Financial Regulation | M1: 9. Trade policy | N1: 10. Sovereign debt, currency crises
A2: 1985 | B2: 1 | C2: 213.67883 | D2: 270.46923 | E2: 292.61456 | F2: 295.79079 | G2: 394.09975 | H2: 107.84824 | I2: 179.69985 | J2: 258.34622 | K2: 129.63282 | L2: 113.24718 | M2: 122.61396 | N2: 0
A3: 1985 | B3: 2 | C3: 155.42602 | D3: 219.83568 | E3: 164.23554 | F3: 139.1256 | G3: 225.03278 | H3: 36.73303 | I3: 124.8595 | J3: 82.492997 | K3: 55.191052 | L3: 0 | M3: 41.762223 | N3: 128.389
A4: 1985 | B4: 3 | C4: 121.13737 | D4: 119.03452 | E4: 108.82881 | F4: 115.71434 | G4: 102.02634 | H4: 31.642944 | I4: 63.269264 | J4: 113.69914 | K4: 85.577836 | L4: 149.52152 | M4: 107.92573 | N4: 110.59817
A5: 1985 | B5: 4 | C5: 104.98235 | D5: 122.04476 | E5: 104.73733 | F5: 85.760217 | G5: 138.08053 | H5: 38.066636 | I5: 85.627432 | J5: 51.29276 | K5: 60.054521 | L5: 44.968804 | M5: 194.75287 | N5: 0
A6: 1985 | B6: 5 | C6: 115.73678 | D6: 107.57358 | E6: 134.83997 | F6: 132.17777 | G6: 167.56891 | H6: 54.705931 | I6: 109.38312 | J6: 98.284429 | K6: 65.75614 | L6: 129.25021 | M6: 124.39166 | N6: 95.603868
A7: 1985 | B7: 6 | C7: 139.79243 | D7: 156.64302 | E7: 197.6899 | F7: 190.02239 | G7: 182.43723 | H7: 26.943794 | I7: 161.6203 | J7: 108.91597 | K7: 89.062184 | L7: 42.43892 | M7: 153.16361 | N7: 0
A8: 1985 | B8: 7 | C8: 120.50515 | D8: 173.40758 | E8: 134.14929 | F8: 122.26014 | G8: 201.22261 | H8: 26.003398 | I8: 155.97941 | J8: 116.79397 | K8: 39.069875 | L8: 0 | M8: 59.127152 | N8: 181.77374
A9: 1985 | B9: 8 | C9: 122.68383 | D9: 111.33082 | E9: 118.87554 | F9: 122.82737 | G9: 217.70667 | H9: 56.267169 | I9: 106.07593 | J9: 151.63401 | K9: 57.970918 | L9: 37.982527 | M9: 109.66426 | N9: 168.56963
A10: 1985 | B10: 9 | C10: 91.711134 | D10: 113.58992 | E10: 81.798704 | F10: 67.479869 | G10: 126.92818 | H10: 24.603827 | I10: 83.631037 | J10: 11.050781 | K10: 51.753844 | L10: 77.506519 | M10: 279.72386 | N10: 85.9951
A11: 1985 | B11: 10 | C11: 86.338619 | D11: 69.607238 | E11: 108.07516 | F11: 89.542597 | G11: 103.62251 | H11: 7.1417751 | I11: 42.839395 | J11: 67.362126 | K11: 64.382722 | L11: 33.746831 | M11: 121.79355 | N11: 74.885628
A12: 1985 | B12: 11 | C12: 115.88343 | D12: 70.245579 | E12: 96.548438 | F12: 83.162896 | G12: 99.344154 | H12: 34.234531 | I12: 114.99781 | J12: 36.903362 | K12: 117.27654 | L12: 32.353495 | M12: 93.411958 | N12: 287.17503
A13: 1985 | B13: 12 | C13: 126.42213 | D13: 112.56385 | E13: 150.93895 | F13: 137.02444 | G13: 225.52253 | H13: 6.8573188 | I13: 119.28601 | J13: 55.439227 | K13: 98.909382 | L13: 64.805396 | M13: 70.165513 | N13: 0
... A481: 2024 | B481: 12 | C481: 178.71316 | D481: 155.29582 | E481: 182.71297 | F481: 184.80943 | G481: 144.52786 | H481: 310.54932 | I481: 154.64808 | J481: 277.64988 | K481: 258.82961 | L481: 46.145599 | M481: 1319.0059 | N481: 51.199505
A482: 2025 | B482: 1 | C482: 236.44342 | D482: 222.12527 | E482: 291.74046 | F482: 293.14729 | G482: 208.06876 | H482: 415.24587 | I482: 159.32277 | J482: 448.62547 | K482: 345.67612 | L482: 97.223638 | M482: 1725.7097 | N482: 9.8065141
A483: 2025 | B483: 2 | C483: 313.488 | D483: 229.40616 | E483: 363.177 | F483: 384.39439 | G483: 318.74367 | H483: 500.7028 | I483: 299.05925 | J483: 503.11952 | K483: 335.64221 | L483: 252.77319 | M483: 2481.3681 | N483: 123.40114
A484: 2025 | B484: 3 | C484: 485.18364 | D484: 431.34234 | E484: 630.57542 | F484: 649.70766 | G484: 522.94972 | H484: 613.28823 | I484: 619.74976 | J484: 742.87203 | K484: 351.56754 | L484: 242.3376 | M484: 5735.9528 | N484: 78.422933
A485: Source: “Measuring Economic Policy Uncertainty” by Scott Baker, Nicholas Bloom and Steven J. Davis at www.PolicyUncertainty.com. These data can be used freely with attribution to the authors, the paper, and the website.

Sheet Market expectations - RCB
A1: ='Market pricing dates'!A2 -> February 2025 MPR | C1: ='Market pricing dates'!A12 -> 15 working days to 31 Jan 2025 | BA1: ='Market pricing dates'!D2 -> May 2025 MPR | BC1: ='Market pricing dates'!D12 -> 15 working days to 29 Apr 2025
A2: Column # | B2: =HAVERD!I$1 -> 9 | C2: =+B2+1 -> 10 | D2: =+C2+1 -> 11 | E2: =+D2+1 -> 12 | F2: =+E2+1 -> 13 | G2: =+F2+1 -> 14 | H2: =+G2+1 -> 15 | I2: =+H2+1 -> 16 | J2: =+I2+1 -> 17 | ... AX2: =+AW2+1 -> 57 | BA2: Column # | BB2: =HAVERD!I$1 -> 9 | BC2: =+BB2+1 -> 10 | BD2: =+BC2+1 -> 11 | BE2: =+BD2+1 -> 12 | BF2: =+BE2+1 -> 13 | BG2: =+BF2+1 -> 14 | BH2: =+BG2+1 -> 15 | BI2: =+BH2+1 -> 16 | BJ2: =+BI2+1 -> 17 | ... CX2: =+CW2+1 -> 57
A3: Months | B3: =HAVERD!I$2 -> Overnight | C3: =HAVERD!J$2 -> 1 | D3: =HAVERD!K$2 -> 2 | E3: =HAVERD!L$2 -> 3 | F3: =HAVERD!M$2 -> 4 | G3: =HAVERD!N$2 -> 5 | H3: =HAVERD!O$2 -> 6 | I3: =HAVERD!P$2 -> 7 | ... AX3: =HAVERD!BE$2 -> 48 | BA3: Months | BB3: =HAVERD!I$2 -> Overnight | BC3: =HAVERD!J$2 -> 1 | BD3: =HAVERD!K$2 -> 2 | BE3: =HAVERD!L$2 -> 3 | BF3: =HAVERD!M$2 -> 4 | BG3: =HAVERD!N$2 -> 5 | BH3: =HAVERD!O$2 -> 6 | BI3: =HAVERD!P$2 -> 7 | ... CX3: =HAVERD!BE$2 -> 48
A4: Days | C4: 30.416667 | D4: =+C4+30.4166667 -> 60.833333 | E4: =+D4+30.4166667 -> 91.25 | F4: =+E4+30.4166667 -> 121.66667 | G4: =+F4+30.4166667 -> 152.08333 | H4: =+G4+30.4166667 -> 182.5 | I4: =+H4+30.4166667 -> 212.91667 | J4: =+I4+30.4166667 -> 243.33333 | K4: =+J4+30.4166667 -> 273.75 | ... AX4: =+AW4+30.4166667 -> 1460 | BA4: Days | BC4: 30.416667 | BD4: =+BC4+30.4166667 -> 60.833333 | BE4: =+BD4+30.4166667 -> 91.25 | BF4: =+BE4+30.4166667 -> 121.66667 | BG4: =+BF4+30.4166667 -> 152.08333 | BH4: =+BG4+30.4166667 -> 182.5 | BI4: =+BH4+30.4166667 -> 212.91667 | BJ4: =+BI4+30.4166667 -> 243.33333 | BK4: =+BJ4+30.4166667 -> 273.75 | ... CX4: =+CW4+30.4166667 -> 1460
A5: Dates | BA5: Dates
A6: =A11-7 -> 45670 | B6: =A6 -> 45670 | C6: =$B6+C$4 -> 45700.417 | D6: =$B6+D$4 -> 45730.833 | E6: =$B6+E$4 -> 45761.25 | F6: =$B6+F$4 -> 45791.667 | G6: =$B6+G$4 -> 45822.083 | H6: =$B6+H$4 -> 45852.5 | I6: =$B6+I$4 -> 45882.917 | J6: =$B6+J$4 -> 45913.333 | ... AX6: =$B6+AX$4 -> 47130 | BA6: =BA11-7 -> 45756 | BB6: =BA6 -> 45756 | BC6: =$BA6+BC$4 -> 45786.417 | BD6: =$BA6+BD$4 -> 45816.833 | BE6: =$BA6+BE$4 -> 45847.25 | BF6: =$BA6+BF$4 -> 45877.667 | BG6: =$BA6+BG$4 -> 45908.083 | BH6: =$BA6+BH$4 -> 45938.5 | BI6: =$BA6+BI$4 -> 45968.917 | BJ6: =$BA6+BJ$4 -> 45999.333 | ... CX6: =$BA6+CX$4 -> 47216
A7: =A12-7 -> 45671 | B7: =A7 -> 45671 | C7: =$B7+C$4 -> 45701.417 | D7: =$B7+D$4 -> 45731.833 | E7: =$B7+E$4 -> 45762.25 | F7: =$B7+F$4 -> 45792.667 | G7: =$B7+G$4 -> 45823.083 | H7: =$B7+H$4 -> 45853.5 | I7: =$B7+I$4 -> 45883.917 | J7: =$B7+J$4 -> 45914.333 | ... AX7: =$B7+AX$4 -> 47131 | BA7: =BA12-7 -> 45757 | BB7: =BA7 -> 45757 | BC7: =$BA7+BC$4 -> 45787.417 | BD7: =$BA7+BD$4 -> 45817.833 | BE7: =$BA7+BE$4 -> 45848.25 | BF7: =$BA7+BF$4 -> 45878.667 | BG7: =$BA7+BG$4 -> 45909.083 | BH7: =$BA7+BH$4 -> 45939.5 | BI7: =$BA7+BI$4 -> 45969.917 | BJ7: =$BA7+BJ$4 -> 46000.333 | ... CX7: =$BA7+CX$4 -> 47217
A8: =A13-7 -> 45672 | B8: =A8 -> 45672 | C8: =$B8+C$4 -> 45702.417 | D8: =$B8+D$4 -> 45732.833 | E8: =$B8+E$4 -> 45763.25 | F8: =$B8+F$4 -> 45793.667 | G8: =$B8+G$4 -> 45824.083 | H8: =$B8+H$4 -> 45854.5 | I8: =$B8+I$4 -> 45884.917 | J8: =$B8+J$4 -> 45915.333 | ... AX8: =$B8+AX$4 -> 47132 | BA8: =BA13-7 -> 45758 | BB8: =BA8 -> 45758 | BC8: =$BA8+BC$4 -> 45788.417 | BD8: =$BA8+BD$4 -> 45818.833 | BE8: =$BA8+BE$4 -> 45849.25 | BF8: =$BA8+BF$4 -> 45879.667 | BG8: =$BA8+BG$4 -> 45910.083 | BH8: =$BA8+BH$4 -> 45940.5 | BI8: =$BA8+BI$4 -> 45970.917 | BJ8: =$BA8+BJ$4 -> 46001.333 | ... CX8: =$BA8+CX$4 -> 47218
A9: =A14-7 -> 45673 | B9: =A9 -> 45673 | C9: =$B9+C$4 -> 45703.417 | D9: =$B9+D$4 -> 45733.833 | E9: =$B9+E$4 -> 45764.25 | F9: =$B9+F$4 -> 45794.667 | G9: =$B9+G$4 -> 45825.083 | H9: =$B9+H$4 -> 45855.5 | I9: =$B9+I$4 -> 45885.917 | J9: =$B9+J$4 -> 45916.333 | ... AX9: =$B9+AX$4 -> 47133 | BA9: =BA14-7 -> 45761 | BB9: =BA9 -> 45761 | BC9: =$BA9+BC$4 -> 45791.417 | BD9: =$BA9+BD$4 -> 45821.833 | BE9: =$BA9+BE$4 -> 45852.25 | BF9: =$BA9+BF$4 -> 45882.667 | BG9: =$BA9+BG$4 -> 45913.083 | BH9: =$BA9+BH$4 -> 45943.5 | BI9: =$BA9+BI$4 -> 45973.917 | BJ9: =$BA9+BJ$4 -> 46004.333 | ... CX9: =$BA9+CX$4 -> 47221
A10: =A15-7 -> 45674 | B10: =A10 -> 45674 | C10: =$B10+C$4 -> 45704.417 | D10: =$B10+D$4 -> 45734.833 | E10: =$B10+E$4 -> 45765.25 | F10: =$B10+F$4 -> 45795.667 | G10: =$B10+G$4 -> 45826.083 | H10: =$B10+H$4 -> 45856.5 | I10: =$B10+I$4 -> 45886.917 | J10: =$B10+J$4 -> 45917.333 | ... AX10: =$B10+AX$4 -> 47134 | BA10: =BA15-7 -> 45762 | BB10: =BA10 -> 45762 | BC10: =$BA10+BC$4 -> 45792.417 | BD10: =$BA10+BD$4 -> 45822.833 | BE10: =$BA10+BE$4 -> 45853.25 | BF10: =$BA10+BF$4 -> 45883.667 | BG10: =$BA10+BG$4 -> 45914.083 | BH10: =$BA10+BH$4 -> 45944.5 | BI10: =$BA10+BI$4 -> 45974.917 | BJ10: =$BA10+BJ$4 -> 46005.333 | ... CX10: =$BA10+CX$4 -> 47222
A11: =A16-7 -> 45677 | B11: =A11 -> 45677 | C11: =$B11+C$4 -> 45707.417 | D11: =$B11+D$4 -> 45737.833 | E11: =$B11+E$4 -> 45768.25 | F11: =$B11+F$4 -> 45798.667 | G11: =$B11+G$4 -> 45829.083 | H11: =$B11+H$4 -> 45859.5 | I11: =$B11+I$4 -> 45889.917 | J11: =$B11+J$4 -> 45920.333 | ... AX11: =$B11+AX$4 -> 47137 | BA11: =BA16-7 -> 45763 | BB11: =BA11 -> 45763 | BC11: =$BA11+BC$4 -> 45793.417 | BD11: =$BA11+BD$4 -> 45823.833 | BE11: =$BA11+BE$4 -> 45854.25 | BF11: =$BA11+BF$4 -> 45884.667 | BG11: =$BA11+BG$4 -> 45915.083 | BH11: =$BA11+BH$4 -> 45945.5 | BI11: =$BA11+BI$4 -> 45975.917 | BJ11: =$BA11+BJ$4 -> 46006.333 | ... CX11: =$BA11+CX$4 -> 47223
A12: =A17-7 -> 45678 | B12: =A12 -> 45678 | C12: =$B12+C$4 -> 45708.417 | D12: =$B12+D$4 -> 45738.833 | E12: =$B12+E$4 -> 45769.25 | F12: =$B12+F$4 -> 45799.667 | G12: =$B12+G$4 -> 45830.083 | H12: =$B12+H$4 -> 45860.5 | I12: =$B12+I$4 -> 45890.917 | J12: =$B12+J$4 -> 45921.333 | ... AX12: =$B12+AX$4 -> 47138 | BA12: =BA17-7 -> 45764 | BB12: =BA12 -> 45764 | BC12: =$BA12+BC$4 -> 45794.417 | BD12: =$BA12+BD$4 -> 45824.833 | BE12: =$BA12+BE$4 -> 45855.25 | BF12: =$BA12+BF$4 -> 45885.667 | BG12: =$BA12+BG$4 -> 45916.083 | BH12: =$BA12+BH$4 -> 45946.5 | BI12: =$BA12+BI$4 -> 45976.917 | BJ12: =$BA12+BJ$4 -> 46007.333 | ... CX12: =$BA12+CX$4 -> 47224
A13: =A18-7 -> 45679 | B13: =A13 -> 45679 | C13: =$B13+C$4 -> 45709.417 | D13: =$B13+D$4 -> 45739.833 | E13: =$B13+E$4 -> 45770.25 | F13: =$B13+F$4 -> 45800.667 | G13: =$B13+G$4 -> 45831.083 | H13: =$B13+H$4 -> 45861.5 | I13: =$B13+I$4 -> 45891.917 | J13: =$B13+J$4 -> 45922.333 | ... AX13: =$B13+AX$4 -> 47139 | BA13: =BA18-7 -> 45765 | BB13: =BA13 -> 45765 | BC13: =$BA13+BC$4 -> 45795.417 | BD13: =$BA13+BD$4 -> 45825.833 | BE13: =$BA13+BE$4 -> 45856.25 | BF13: =$BA13+BF$4 -> 45886.667 | BG13: =$BA13+BG$4 -> 45917.083 | BH13: =$BA13+BH$4 -> 45947.5 | BI13: =$BA13+BI$4 -> 45977.917 | BJ13: =$BA13+BJ$4 -> 46008.333 | ... CX13: =$BA13+CX$4 -> 47225
A14: =A19-7 -> 45680 | B14: =A14 -> 45680 | C14: =$B14+C$4 -> 45710.417 | D14: =$B14+D$4 -> 45740.833 | E14: =$B14+E$4 -> 45771.25 | F14: =$B14+F$4 -> 45801.667 | G14: =$B14+G$4 -> 45832.083 | H14: =$B14+H$4 -> 45862.5 | I14: =$B14+I$4 -> 45892.917 | J14: =$B14+J$4 -> 45923.333 | ... AX14: =$B14+AX$4 -> 47140 | BA14: =BA19-7 -> 45768 | BB14: =BA14 -> 45768 | BC14: =$BA14+BC$4 -> 45798.417 | BD14: =$BA14+BD$4 -> 45828.833 | BE14: =$BA14+BE$4 -> 45859.25 | BF14: =$BA14+BF$4 -> 45889.667 | BG14: =$BA14+BG$4 -> 45920.083 | BH14: =$BA14+BH$4 -> 45950.5 | BI14: =$BA14+BI$4 -> 45980.917 | BJ14: =$BA14+BJ$4 -> 46011.333 | ... CX14: =$BA14+CX$4 -> 47228
A15: =A20-7 -> 45681 | B15: =A15 -> 45681 | C15: =$B15+C$4 -> 45711.417 | D15: =$B15+D$4 -> 45741.833 | E15: =$B15+E$4 -> 45772.25 | F15: =$B15+F$4 -> 45802.667 | G15: =$B15+G$4 -> 45833.083 | H15: =$B15+H$4 -> 45863.5 | I15: =$B15+I$4 -> 45893.917 | J15: =$B15+J$4 -> 45924.333 | ... AX15: =$B15+AX$4 -> 47141 | BA15: =BA20-7 -> 45769 | BB15: =BA15 -> 45769 | BC15: =$BA15+BC$4 -> 45799.417 | BD15: =$BA15+BD$4 -> 45829.833 | BE15: =$BA15+BE$4 -> 45860.25 | BF15: =$BA15+BF$4 -> 45890.667 | BG15: =$BA15+BG$4 -> 45921.083 | BH15: =$BA15+BH$4 -> 45951.5 | BI15: =$BA15+BI$4 -> 45981.917 | BJ15: =$BA15+BJ$4 -> 46012.333 | ... CX15: =$BA15+CX$4 -> 47229
A16: ='Market pricing dates'!B5 -> 45684 | B16: =A16 -> 45684 | C16: =$B16+C$4 -> 45714.417 | D16: =$B16+D$4 -> 45744.833 | E16: =$B16+E$4 -> 45775.25 | F16: =$B16+F$4 -> 45805.667 | G16: =$B16+G$4 -> 45836.083 | H16: =$B16+H$4 -> 45866.5 | I16: =$B16+I$4 -> 45896.917 | J16: =$B16+J$4 -> 45927.333 | ... AX16: =$B16+AX$4 -> 47144 | BA16: ='Market pricing dates'!E5 -> 45770 | BB16: =BA16 -> 45770 | BC16: =$BA16+BC$4 -> 45800.417 | BD16: =$BA16+BD$4 -> 45830.833 | BE16: =$BA16+BE$4 -> 45861.25 | BF16: =$BA16+BF$4 -> 45891.667 | BG16: =$BA16+BG$4 -> 45922.083 | BH16: =$BA16+BH$4 -> 45952.5 | BI16: =$BA16+BI$4 -> 45982.917 | BJ16: =$BA16+BJ$4 -> 46013.333 | ... CX16: =$BA16+CX$4 -> 47230
A17: ='Market pricing dates'!B6 -> 45685 | B17: =A17 -> 45685 | C17: =$B17+C$4 -> 45715.417 | D17: =$B17+D$4 -> 45745.833 | E17: =$B17+E$4 -> 45776.25 | F17: =$B17+F$4 -> 45806.667 | G17: =$B17+G$4 -> 45837.083 | H17: =$B17+H$4 -> 45867.5 | I17: =$B17+I$4 -> 45897.917 | J17: =$B17+J$4 -> 45928.333 | ... AX17: =$B17+AX$4 -> 47145 | BA17: ='Market pricing dates'!E6 -> 45771 | BB17: =BA17 -> 45771 | BC17: =$BA17+BC$4 -> 45801.417 | BD17: =$BA17+BD$4 -> 45831.833 | BE17: =$BA17+BE$4 -> 45862.25 | BF17: =$BA17+BF$4 -> 45892.667 | BG17: =$BA17+BG$4 -> 45923.083 | BH17: =$BA17+BH$4 -> 45953.5 | BI17: =$BA17+BI$4 -> 45983.917 | BJ17: =$BA17+BJ$4 -> 46014.333 | ... CX17: =$BA17+CX$4 -> 47231
A18: ='Market pricing dates'!B7 -> 45686 | B18: =A18 -> 45686 | C18: =$B18+C$4 -> 45716.417 | D18: =$B18+D$4 -> 45746.833 | E18: =$B18+E$4 -> 45777.25 | F18: =$B18+F$4 -> 45807.667 | G18: =$B18+G$4 -> 45838.083 | H18: =$B18+H$4 -> 45868.5 | I18: =$B18+I$4 -> 45898.917 | J18: =$B18+J$4 -> 45929.333 | ... AX18: =$B18+AX$4 -> 47146 | BA18: ='Market pricing dates'!E7 -> 45772 | BB18: =BA18 -> 45772 | BC18: =$BA18+BC$4 -> 45802.417 | BD18: =$BA18+BD$4 -> 45832.833 | BE18: =$BA18+BE$4 -> 45863.25 | BF18: =$BA18+BF$4 -> 45893.667 | BG18: =$BA18+BG$4 -> 45924.083 | BH18: =$BA18+BH$4 -> 45954.5 | BI18: =$BA18+BI$4 -> 45984.917 | BJ18: =$BA18+BJ$4 -> 46015.333 | ... CX18: =$BA18+CX$4 -> 47232
A19: ='Market pricing dates'!B8 -> 45687 | B19: =A19 -> 45687 | C19: =$B19+C$4 -> 45717.417 | D19: =$B19+D$4 -> 45747.833 | E19: =$B19+E$4 -> 45778.25 | F19: =$B19+F$4 -> 45808.667 | G19: =$B19+G$4 -> 45839.083 | H19: =$B19+H$4 -> 45869.5 | I19: =$B19+I$4 -> 45899.917 | J19: =$B19+J$4 -> 45930.333 | ... AX19: =$B19+AX$4 -> 47147 | BA19: ='Market pricing dates'!E8 -> 45775 | BB19: =BA19 -> 45775 | BC19: =$BA19+BC$4 -> 45805.417 | BD19: =$BA19+BD$4 -> 45835.833 | BE19: =$BA19+BE$4 -> 45866.25 | BF19: =$BA19+BF$4 -> 45896.667 | BG19: =$BA19+BG$4 -> 45927.083 | BH19: =$BA19+BH$4 -> 45957.5 | BI19: =$BA19+BI$4 -> 45987.917 | BJ19: =$BA19+BJ$4 -> 46018.333 | ... CX19: =$BA19+CX$4 -> 47235
A20: ='Market pricing dates'!B9 -> 45688 | B20: =A20 -> 45688 | C20: =$B20+C$4 -> 45718.417 | D20: =$B20+D$4 -> 45748.833 | E20: =$B20+E$4 -> 45779.25 | F20: =$B20+F$4 -> 45809.667 | G20: =$B20+G$4 -> 45840.083 | H20: =$B20+H$4 -> 45870.5 | I20: =$B20+I$4 -> 45900.917 | J20: =$B20+J$4 -> 45931.333 | ... AX20: =$B20+AX$4 -> 47148 | BA20: ='Market pricing dates'!E9 -> 45776 | BB20: =BA20 -> 45776 | BC20: =$BA20+BC$4 -> 45806.417 | BD20: =$BA20+BD$4 -> 45836.833 | BE20: =$BA20+BE$4 -> 45867.25 | BF20: =$BA20+BF$4 -> 45897.667 | BG20: =$BA20+BG$4 -> 45928.083 | BH20: =$BA20+BH$4 -> 45958.5 | BI20: =$BA20+BI$4 -> 45988.917 | BJ20: =$BA20+BJ$4 -> 46019.333 | ... CX20: =$BA20+CX$4 -> 47236
A22: Market expectations | BA22: Market expectations
A23: =A6 -> 45670 | B23: =VLOOKUP($A23,HAVERD!$A:$BS,B$2,FALSE) -> 4.7 | C23: =VLOOKUP($A23,HAVERD!$A:$BS,C$2,FALSE) -> 4.583527 | D23: =VLOOKUP($A23,HAVERD!$A:$BS,D$2,FALSE) -> 4.5112586 | E23: =VLOOKUP($A23,HAVERD!$A:$BS,E$2,FALSE) -> 4.4690879 | F23: =VLOOKUP($A23,HAVERD!$A:$BS,F$2,FALSE) -> 4.438039 | G23: =VLOOKUP($A23,HAVERD!$A:$BS,G$2,FALSE) -> 4.4093316 | H23: =VLOOKUP($A23,HAVERD!$A:$BS,H$2,FALSE) -> 4.3818388 | I23: =VLOOKUP($A23,HAVERD!$A:$BS,I$2,FALSE) -> 4.3565668 | ... AX23: =VLOOKUP($A23,HAVERD!$A:$BS,AX$2,FALSE) -> 4.0874707 | BA23: =BA6 -> 45756 | BB23: =_xlfn.IFNA(VLOOKUP($BA23,HAVERD!$A:$BS,BB$2,FALSE),"") -> 4.4565 | BC23: =_xlfn.IFNA(VLOOKUP($BA23,HAVERD!$A:$BS,BC$2,FALSE),"") -> 4.3106983 | BD23: =_xlfn.IFNA(VLOOKUP($BA23,HAVERD!$A:$BS,BD$2,FALSE),"") -> 4.1417456 | BE23: =_xlfn.IFNA(VLOOKUP($BA23,HAVERD!$A:$BS,BE$2,FALSE),"") -> 4.0256197 | BF23: =_xlfn.IFNA(VLOOKUP($BA23,HAVERD!$A:$BS,BF$2,FALSE),"") -> 3.9364484 | BG23: =_xlfn.IFNA(VLOOKUP($BA23,HAVERD!$A:$BS,BG$2,FALSE),"") -> 3.8589194 | BH23: =_xlfn.IFNA(VLOOKUP($BA23,HAVERD!$A:$BS,BH$2,FALSE),"") -> 3.7904365 | BI23: =_xlfn.IFNA(VLOOKUP($BA23,HAVERD!$A:$BS,BI$2,FALSE),"") -> 3.7327137 | ... CX23: =_xlfn.IFNA(VLOOKUP($BA23,HAVERD!$A:$BS,CX$2,FALSE),"") -> 4.0012642
A24: =A7 -> 45671 | B24: =VLOOKUP($A24,HAVERD!$A:$BS,B$2,FALSE) -> 4.7 | C24: =VLOOKUP($A24,HAVERD!$A:$BS,C$2,FALSE) -> 4.5928108 | D24: =VLOOKUP($A24,HAVERD!$A:$BS,D$2,FALSE) -> 4.5365359 | E24: =VLOOKUP($A24,HAVERD!$A:$BS,E$2,FALSE) -> 4.5032957 | F24: =VLOOKUP($A24,HAVERD!$A:$BS,F$2,FALSE) -> 4.4752949 | G24: =VLOOKUP($A24,HAVERD!$A:$BS,G$2,FALSE) -> 4.446087 | H24: =VLOOKUP($A24,HAVERD!$A:$BS,H$2,FALSE) -> 4.4172097 | I24: =VLOOKUP($A24,HAVERD!$A:$BS,I$2,FALSE) -> 4.3922553 | ... AX24: =VLOOKUP($A24,HAVERD!$A:$BS,AX$2,FALSE) -> 4.1407446 | BA24: =BA7 -> 45757 | BB24: =_xlfn.IFNA(VLOOKUP($BA24,HAVERD!$A:$BS,BB$2,FALSE),"") -> 4.4579 | BC24: =_xlfn.IFNA(VLOOKUP($BA24,HAVERD!$A:$BS,BC$2,FALSE),"") -> 4.3190332 | BD24: =_xlfn.IFNA(VLOOKUP($BA24,HAVERD!$A:$BS,BD$2,FALSE),"") -> 4.1664726 | BE24: =_xlfn.IFNA(VLOOKUP($BA24,HAVERD!$A:$BS,BE$2,FALSE),"") -> 4.0489946 | BF24: =_xlfn.IFNA(VLOOKUP($BA24,HAVERD!$A:$BS,BF$2,FALSE),"") -> 3.9435279 | BG24: =_xlfn.IFNA(VLOOKUP($BA24,HAVERD!$A:$BS,BG$2,FALSE),"") -> 3.8419045 | BH24: =_xlfn.IFNA(VLOOKUP($BA24,HAVERD!$A:$BS,BH$2,FALSE),"") -> 3.7480781 | BI24: =_xlfn.IFNA(VLOOKUP($BA24,HAVERD!$A:$BS,BI$2,FALSE),"") -> 3.6674148 | ... CX24: =_xlfn.IFNA(VLOOKUP($BA24,HAVERD!$A:$BS,CX$2,FALSE),"") -> 3.7975574
A25: =A8 -> 45672 | B25: =VLOOKUP($A25,HAVERD!$A:$BS,B$2,FALSE) -> 4.7001 | C25: =VLOOKUP($A25,HAVERD!$A:$BS,C$2,FALSE) -> 4.5407893 | D25: =VLOOKUP($A25,HAVERD!$A:$BS,D$2,FALSE) -> 4.4591869 | E25: =VLOOKUP($A25,HAVERD!$A:$BS,E$2,FALSE) -> 4.406464 | F25: =VLOOKUP($A25,HAVERD!$A:$BS,F$2,FALSE) -> 4.3616584 | G25: =VLOOKUP($A25,HAVERD!$A:$BS,G$2,FALSE) -> 4.3170663 | H25: =VLOOKUP($A25,HAVERD!$A:$BS,H$2,FALSE) -> 4.2738664 | I25: =VLOOKUP($A25,HAVERD!$A:$BS,I$2,FALSE) -> 4.2354391 | ... AX25: =VLOOKUP($A25,HAVERD!$A:$BS,AX$2,FALSE) -> 3.9786814 | BA25: =BA8 -> 45758 | BB25: =_xlfn.IFNA(VLOOKUP($BA25,HAVERD!$A:$BS,BB$2,FALSE),"") -> 4.4584 | BC25: =_xlfn.IFNA(VLOOKUP($BA25,HAVERD!$A:$BS,BC$2,FALSE),"") -> 4.3184361 | BD25: =_xlfn.IFNA(VLOOKUP($BA25,HAVERD!$A:$BS,BD$2,FALSE),"") -> 4.1965726 | BE25: =_xlfn.IFNA(VLOOKUP($BA25,HAVERD!$A:$BS,BE$2,FALSE),"") -> 4.1021144 | BF25: =_xlfn.IFNA(VLOOKUP($BA25,HAVERD!$A:$BS,BF$2,FALSE),"") -> 4.0153237 | BG25: =_xlfn.IFNA(VLOOKUP($BA25,HAVERD!$A:$BS,BG$2,FALSE),"") -> 3.931199 | BH25: =_xlfn.IFNA(VLOOKUP($BA25,HAVERD!$A:$BS,BH$2,FALSE),"") -> 3.8543074 | BI25: =_xlfn.IFNA(VLOOKUP($BA25,HAVERD!$A:$BS,BI$2,FALSE),"") -> 3.7891968 | ... CX25: =_xlfn.IFNA(VLOOKUP($BA25,HAVERD!$A:$BS,CX$2,FALSE),"") -> 3.8924818
A26: =A9 -> 45673 | B26: =VLOOKUP($A26,HAVERD!$A:$BS,B$2,FALSE) -> 4.7 | C26: =VLOOKUP($A26,HAVERD!$A:$BS,C$2,FALSE) -> 4.5365792 | D26: =VLOOKUP($A26,HAVERD!$A:$BS,D$2,FALSE) -> 4.4591431 | E26: =VLOOKUP($A26,HAVERD!$A:$BS,E$2,FALSE) -> 4.4049873 | F26: =VLOOKUP($A26,HAVERD!$A:$BS,F$2,FALSE) -> 4.3545297 | G26: =VLOOKUP($A26,HAVERD!$A:$BS,G$2,FALSE) -> 4.3030819 | H26: =VLOOKUP($A26,HAVERD!$A:$BS,H$2,FALSE) -> 4.2536483 | I26: =VLOOKUP($A26,HAVERD!$A:$BS,I$2,FALSE) -> 4.2099764 | ... AX26: =VLOOKUP($A26,HAVERD!$A:$BS,AX$2,FALSE) -> 3.9412115 | BA26: =BA9 -> 45761 | BB26: =_xlfn.IFNA(VLOOKUP($BA26,HAVERD!$A:$BS,BB$2,FALSE),"") -> 4.4582 | BC26: =_xlfn.IFNA(VLOOKUP($BA26,HAVERD!$A:$BS,BC$2,FALSE),"") -> 4.3126921 | BD26: =_xlfn.IFNA(VLOOKUP($BA26,HAVERD!$A:$BS,BD$2,FALSE),"") -> 4.1913674 | BE26: =_xlfn.IFNA(VLOOKUP($BA26,HAVERD!$A:$BS,BE$2,FALSE),"") -> 4.0990096 | BF26: =_xlfn.IFNA(VLOOKUP($BA26,HAVERD!$A:$BS,BF$2,FALSE),"") -> 4.0149637 | BG26: =_xlfn.IFNA(VLOOKUP($BA26,HAVERD!$A:$BS,BG$2,FALSE),"") -> 3.931502 | BH26: =_xlfn.IFNA(VLOOKUP($BA26,HAVERD!$A:$BS,BH$2,FALSE),"") -> 3.85251 | BI26: =_xlfn.IFNA(VLOOKUP($BA26,HAVERD!$A:$BS,BI$2,FALSE),"") -> 3.7838345 | ... CX26: =_xlfn.IFNA(VLOOKUP($BA26,HAVERD!$A:$BS,CX$2,FALSE),"") -> 3.8345921
A27: =A10 -> 45674 | B27: =VLOOKUP($A27,HAVERD!$A:$BS,B$2,FALSE) -> 4.7 | C27: =VLOOKUP($A27,HAVERD!$A:$BS,C$2,FALSE) -> 4.5219514 | D27: =VLOOKUP($A27,HAVERD!$A:$BS,D$2,FALSE) -> 4.4415724 | E27: =VLOOKUP($A27,HAVERD!$A:$BS,E$2,FALSE) -> 4.3810211 | F27: =VLOOKUP($A27,HAVERD!$A:$BS,F$2,FALSE) -> 4.3255362 | G27: =VLOOKUP($A27,HAVERD!$A:$BS,G$2,FALSE) -> 4.2715314 | H27: =VLOOKUP($A27,HAVERD!$A:$BS,H$2,FALSE) -> 4.2216815 | I27: =VLOOKUP($A27,HAVERD!$A:$BS,I$2,FALSE) -> 4.1788801 | ... AX27: =VLOOKUP($A27,HAVERD!$A:$BS,AX$2,FALSE) -> 3.9200765 | BA27: =BA10 -> 45762 | BB27: =_xlfn.IFNA(VLOOKUP($BA27,HAVERD!$A:$BS,BB$2,FALSE),"") -> 4.4585 | BC27: =_xlfn.IFNA(VLOOKUP($BA27,HAVERD!$A:$BS,BC$2,FALSE),"") -> 4.3003244 | BD27: =_xlfn.IFNA(VLOOKUP($BA27,HAVERD!$A:$BS,BD$2,FALSE),"") -> 4.1800162 | BE27: =_xlfn.IFNA(VLOOKUP($BA27,HAVERD!$A:$BS,BE$2,FALSE),"") -> 4.0813777 | BF27: =_xlfn.IFNA(VLOOKUP($BA27,HAVERD!$A:$BS,BF$2,FALSE),"") -> 3.9874367 | BG27: =_xlfn.IFNA(VLOOKUP($BA27,HAVERD!$A:$BS,BG$2,FALSE),"") -> 3.8945333 | BH27: =_xlfn.IFNA(VLOOKUP($BA27,HAVERD!$A:$BS,BH$2,FALSE),"") -> 3.807839 | BI27: =_xlfn.IFNA(VLOOKUP($BA27,HAVERD!$A:$BS,BI$2,FALSE),"") -> 3.7329429 | ... CX27: =_xlfn.IFNA(VLOOKUP($BA27,HAVERD!$A:$BS,CX$2,FALSE),"") -> 3.8253301
A28: =A11 -> 45677 | B28: =VLOOKUP($A28,HAVERD!$A:$BS,B$2,FALSE) -> 4.7 | C28: =VLOOKUP($A28,HAVERD!$A:$BS,C$2,FALSE) -> 4.5000267 | D28: =VLOOKUP($A28,HAVERD!$A:$BS,D$2,FALSE) -> 4.4463263 | E28: =VLOOKUP($A28,HAVERD!$A:$BS,E$2,FALSE) -> 4.3909734 | F28: =VLOOKUP($A28,HAVERD!$A:$BS,F$2,FALSE) -> 4.332188 | G28: =VLOOKUP($A28,HAVERD!$A:$BS,G$2,FALSE) -> 4.2745293 | H28: =VLOOKUP($A28,HAVERD!$A:$BS,H$2,FALSE) -> 4.2228441 | I28: =VLOOKUP($A28,HAVERD!$A:$BS,I$2,FALSE) -> 4.1799756 | ... AX28: =VLOOKUP($A28,HAVERD!$A:$BS,AX$2,FALSE) -> 3.9254038 | BA28: =BA11 -> 45763 | BB28: =_xlfn.IFNA(VLOOKUP($BA28,HAVERD!$A:$BS,BB$2,FALSE),"") -> 4.4585 | BC28: =_xlfn.IFNA(VLOOKUP($BA28,HAVERD!$A:$BS,BC$2,FALSE),"") -> 4.2759184 | BD28: =_xlfn.IFNA(VLOOKUP($BA28,HAVERD!$A:$BS,BD$2,FALSE),"") -> 4.1526541 | BE28: =_xlfn.IFNA(VLOOKUP($BA28,HAVERD!$A:$BS,BE$2,FALSE),"") -> 4.057955 | BF28: =_xlfn.IFNA(VLOOKUP($BA28,HAVERD!$A:$BS,BF$2,FALSE),"") -> 3.971095 | BG28: =_xlfn.IFNA(VLOOKUP($BA28,HAVERD!$A:$BS,BG$2,FALSE),"") -> 3.8852689 | BH28: =_xlfn.IFNA(VLOOKUP($BA28,HAVERD!$A:$BS,BH$2,FALSE),"") -> 3.8044936 | BI28: =_xlfn.IFNA(VLOOKUP($BA28,HAVERD!$A:$BS,BI$2,FALSE),"") -> 3.7344911 | ... CX28: =_xlfn.IFNA(VLOOKUP($BA28,HAVERD!$A:$BS,CX$2,FALSE),"") -> 3.8199038
A29: =A12 -> 45678 | B29: =VLOOKUP($A29,HAVERD!$A:$BS,B$2,FALSE) -> 4.7 | C29: =VLOOKUP($A29,HAVERD!$A:$BS,C$2,FALSE) -> 4.484872 | D29: =VLOOKUP($A29,HAVERD!$A:$BS,D$2,FALSE) -> 4.4384666 | E29: =VLOOKUP($A29,HAVERD!$A:$BS,E$2,FALSE) -> 4.3841836 | F29: =VLOOKUP($A29,HAVERD!$A:$BS,F$2,FALSE) -> 4.3240279 | G29: =VLOOKUP($A29,HAVERD!$A:$BS,G$2,FALSE) -> 4.2650434 | H29: =VLOOKUP($A29,HAVERD!$A:$BS,H$2,FALSE) -> 4.212658 | I29: =VLOOKUP($A29,HAVERD!$A:$BS,I$2,FALSE) -> 4.1700255 | ... AX29: =VLOOKUP($A29,HAVERD!$A:$BS,AX$2,FALSE) -> 3.8604511 | BA29: =BA12 -> 45764 | BB29: =_xlfn.IFNA(VLOOKUP($BA29,HAVERD!$A:$BS,BB$2,FALSE),"") -> 4.459 | BC29: =_xlfn.IFNA(VLOOKUP($BA29,HAVERD!$A:$BS,BC$2,FALSE),"") -> 4.2648654 | BD29: =_xlfn.IFNA(VLOOKUP($BA29,HAVERD!$A:$BS,BD$2,FALSE),"") -> 4.1419825 | BE29: =_xlfn.IFNA(VLOOKUP($BA29,HAVERD!$A:$BS,BE$2,FALSE),"") -> 4.0391454 | BF29: =_xlfn.IFNA(VLOOKUP($BA29,HAVERD!$A:$BS,BF$2,FALSE),"") -> 3.9411515 | BG29: =_xlfn.IFNA(VLOOKUP($BA29,HAVERD!$A:$BS,BG$2,FALSE),"") -> 3.8458918 | BH29: =_xlfn.IFNA(VLOOKUP($BA29,HAVERD!$A:$BS,BH$2,FALSE),"") -> 3.7584655 | BI29: =_xlfn.IFNA(VLOOKUP($BA29,HAVERD!$A:$BS,BI$2,FALSE),"") -> 3.683865 | ... CX29: =_xlfn.IFNA(VLOOKUP($BA29,HAVERD!$A:$BS,CX$2,FALSE),"") -> 3.7772999
A30: =A13 -> 45679 | B30: =VLOOKUP($A30,HAVERD!$A:$BS,B$2,FALSE) -> 4.7 | C30: =VLOOKUP($A30,HAVERD!$A:$BS,C$2,FALSE) -> 4.4757356 | D30: =VLOOKUP($A30,HAVERD!$A:$BS,D$2,FALSE) -> 4.4383779 | E30: =VLOOKUP($A30,HAVERD!$A:$BS,E$2,FALSE) -> 4.3856464 | F30: =VLOOKUP($A30,HAVERD!$A:$BS,F$2,FALSE) -> 4.3229666 | G30: =VLOOKUP($A30,HAVERD!$A:$BS,G$2,FALSE) -> 4.2598599 | H30: =VLOOKUP($A30,HAVERD!$A:$BS,H$2,FALSE) -> 4.2032262 | I30: =VLOOKUP($A30,HAVERD!$A:$BS,I$2,FALSE) -> 4.1570015 | ... AX30: =VLOOKUP($A30,HAVERD!$A:$BS,AX$2,FALSE) -> 3.8686946 | BA30: =BA13 -> 45765 | BB30: =_xlfn.IFNA(VLOOKUP($BA30,HAVERD!$A:$BS,BB$2,FALSE),"") | BC30: =_xlfn.IFNA(VLOOKUP($BA30,HAVERD!$A:$BS,BC$2,FALSE),"") | BD30: =_xlfn.IFNA(VLOOKUP($BA30,HAVERD!$A:$BS,BD$2,FALSE),"") | BE30: =_xlfn.IFNA(VLOOKUP($BA30,HAVERD!$A:$BS,BE$2,FALSE),"") | BF30: =_xlfn.IFNA(VLOOKUP($BA30,HAVERD!$A:$BS,BF$2,FALSE),"") | BG30: =_xlfn.IFNA(VLOOKUP($BA30,HAVERD!$A:$BS,BG$2,FALSE),"") | BH30: =_xlfn.IFNA(VLOOKUP($BA30,HAVERD!$A:$BS,BH$2,FALSE),"") | BI30: =_xlfn.IFNA(VLOOKUP($BA30,HAVERD!$A:$BS,BI$2,FALSE),"") | ... CX30: =_xlfn.IFNA(VLOOKUP($BA30,HAVERD!$A:$BS,CX$2,FALSE),"")
A31: =A14 -> 45680 | B31: =VLOOKUP($A31,HAVERD!$A:$BS,B$2,FALSE) -> 4.7001 | C31: =VLOOKUP($A31,HAVERD!$A:$BS,C$2,FALSE) -> 4.4650853 | D31: =VLOOKUP($A31,HAVERD!$A:$BS,D$2,FALSE) -> 4.4336144 | E31: =VLOOKUP($A31,HAVERD!$A:$BS,E$2,FALSE) -> 4.3790128 | F31: =VLOOKUP($A31,HAVERD!$A:$BS,F$2,FALSE) -> 4.3105457 | G31: =VLOOKUP($A31,HAVERD!$A:$BS,G$2,FALSE) -> 4.2407452 | H31: =VLOOKUP($A31,HAVERD!$A:$BS,H$2,FALSE) -> 4.178016 | I31: =VLOOKUP($A31,HAVERD!$A:$BS,I$2,FALSE) -> 4.1267057 | ... AX31: =VLOOKUP($A31,HAVERD!$A:$BS,AX$2,FALSE) -> 3.8872239 | BA31: =BA14 -> 45768 | BB31: =_xlfn.IFNA(VLOOKUP($BA31,HAVERD!$A:$BS,BB$2,FALSE),"") | BC31: =_xlfn.IFNA(VLOOKUP($BA31,HAVERD!$A:$BS,BC$2,FALSE),"") | BD31: =_xlfn.IFNA(VLOOKUP($BA31,HAVERD!$A:$BS,BD$2,FALSE),"") | BE31: =_xlfn.IFNA(VLOOKUP($BA31,HAVERD!$A:$BS,BE$2,FALSE),"") | BF31: =_xlfn.IFNA(VLOOKUP($BA31,HAVERD!$A:$BS,BF$2,FALSE),"") | BG31: =_xlfn.IFNA(VLOOKUP($BA31,HAVERD!$A:$BS,BG$2,FALSE),"") | BH31: =_xlfn.IFNA(VLOOKUP($BA31,HAVERD!$A:$BS,BH$2,FALSE),"") | BI31: =_xlfn.IFNA(VLOOKUP($BA31,HAVERD!$A:$BS,BI$2,FALSE),"") | ... CX31: =_xlfn.IFNA(VLOOKUP($BA31,HAVERD!$A:$BS,CX$2,FALSE),"")
A32: =A15 -> 45681 | B32: =VLOOKUP($A32,HAVERD!$A:$BS,B$2,FALSE) -> 4.7 | C32: =VLOOKUP($A32,HAVERD!$A:$BS,C$2,FALSE) -> 4.4660198 | D32: =VLOOKUP($A32,HAVERD!$A:$BS,D$2,FALSE) -> 4.4361991 | E32: =VLOOKUP($A32,HAVERD!$A:$BS,E$2,FALSE) -> 4.3843893 | F32: =VLOOKUP($A32,HAVERD!$A:$BS,F$2,FALSE) -> 4.319762 | G32: =VLOOKUP($A32,HAVERD!$A:$BS,G$2,FALSE) -> 4.2545703 | H32: =VLOOKUP($A32,HAVERD!$A:$BS,H$2,FALSE) -> 4.1964227 | I32: =VLOOKUP($A32,HAVERD!$A:$BS,I$2,FALSE) -> 4.1491561 | ... AX32: =VLOOKUP($A32,HAVERD!$A:$BS,AX$2,FALSE) -> 3.9040089 | BA32: =BA15 -> 45769 | BB32: =_xlfn.IFNA(VLOOKUP($BA32,HAVERD!$A:$BS,BB$2,FALSE),"") -> 4.4593 | BC32: =_xlfn.IFNA(VLOOKUP($BA32,HAVERD!$A:$BS,BC$2,FALSE),"") -> 4.213294 | BD32: =_xlfn.IFNA(VLOOKUP($BA32,HAVERD!$A:$BS,BD$2,FALSE),"") -> 4.1262615 | BE32: =_xlfn.IFNA(VLOOKUP($BA32,HAVERD!$A:$BS,BE$2,FALSE),"") -> 4.0235652 | BF32: =_xlfn.IFNA(VLOOKUP($BA32,HAVERD!$A:$BS,BF$2,FALSE),"") -> 3.9125732 | BG32: =_xlfn.IFNA(VLOOKUP($BA32,HAVERD!$A:$BS,BG$2,FALSE),"") -> 3.8043488 | BH32: =_xlfn.IFNA(VLOOKUP($BA32,HAVERD!$A:$BS,BH$2,FALSE),"") -> 3.7071044 | BI32: =_xlfn.IFNA(VLOOKUP($BA32,HAVERD!$A:$BS,BI$2,FALSE),"") -> 3.6256913 | ... CX32: =_xlfn.IFNA(VLOOKUP($BA32,HAVERD!$A:$BS,CX$2,FALSE),"") -> 3.7741399
A33: =A16 -> 45684 | B33: =VLOOKUP($A33,HAVERD!$A:$BS,B$2,FALSE) -> 4.7 | C33: =VLOOKUP($A33,HAVERD!$A:$BS,C$2,FALSE) -> 4.4608224 | D33: =VLOOKUP($A33,HAVERD!$A:$BS,D$2,FALSE) -> 4.4241921 | E33: =VLOOKUP($A33,HAVERD!$A:$BS,E$2,FALSE) -> 4.3661033 | F33: =VLOOKUP($A33,HAVERD!$A:$BS,F$2,FALSE) -> 4.2945824 | G33: =VLOOKUP($A33,HAVERD!$A:$BS,G$2,FALSE) -> 4.2222341 | H33: =VLOOKUP($A33,HAVERD!$A:$BS,H$2,FALSE) -> 4.1569599 | I33: =VLOOKUP($A33,HAVERD!$A:$BS,I$2,FALSE) -> 4.10271 | ... AX33: =VLOOKUP($A33,HAVERD!$A:$BS,AX$2,FALSE) -> 3.8439485 | BA33: =BA16 -> 45770 | BB33: =_xlfn.IFNA(VLOOKUP($BA33,HAVERD!$A:$BS,BB$2,FALSE),"") -> 4.459 | BC33: =_xlfn.IFNA(VLOOKUP($BA33,HAVERD!$A:$BS,BC$2,FALSE),"") -> 4.2000461 | BD33: =_xlfn.IFNA(VLOOKUP($BA33,HAVERD!$A:$BS,BD$2,FALSE),"") -> 4.1260767 | BE33: =_xlfn.IFNA(VLOOKUP($BA33,HAVERD!$A:$BS,BE$2,FALSE),"") -> 4.0314754 | BF33: =_xlfn.IFNA(VLOOKUP($BA33,HAVERD!$A:$BS,BF$2,FALSE),"") -> 3.9271294 | BG33: =_xlfn.IFNA(VLOOKUP($BA33,HAVERD!$A:$BS,BG$2,FALSE),"") -> 3.8258409 | BH33: =_xlfn.IFNA(VLOOKUP($BA33,HAVERD!$A:$BS,BH$2,FALSE),"") -> 3.7369131 | BI33: =_xlfn.IFNA(VLOOKUP($BA33,HAVERD!$A:$BS,BI$2,FALSE),"") -> 3.6661292 | ... CX33: =_xlfn.IFNA(VLOOKUP($BA33,HAVERD!$A:$BS,CX$2,FALSE),"") -> 3.8038986
A34: =A17 -> 45685 | B34: =VLOOKUP($A34,HAVERD!$A:$BS,B$2,FALSE) -> 4.7 | C34: =VLOOKUP($A34,HAVERD!$A:$BS,C$2,FALSE) -> 4.4598169 | D34: =VLOOKUP($A34,HAVERD!$A:$BS,D$2,FALSE) -> 4.4206843 | E34: =VLOOKUP($A34,HAVERD!$A:$BS,E$2,FALSE) -> 4.362708 | F34: =VLOOKUP($A34,HAVERD!$A:$BS,F$2,FALSE) -> 4.2944473 | G34: =VLOOKUP($A34,HAVERD!$A:$BS,G$2,FALSE) -> 4.2275019 | H34: =VLOOKUP($A34,HAVERD!$A:$BS,H$2,FALSE) -> 4.1682824 | I34: =VLOOKUP($A34,HAVERD!$A:$BS,I$2,FALSE) -> 4.1201531 | ... AX34: =VLOOKUP($A34,HAVERD!$A:$BS,AX$2,FALSE) -> 3.8577803 | BA34: =BA17 -> 45771 | BB34: =_xlfn.IFNA(VLOOKUP($BA34,HAVERD!$A:$BS,BB$2,FALSE),"") -> 4.4592 | BC34: =_xlfn.IFNA(VLOOKUP($BA34,HAVERD!$A:$BS,BC$2,FALSE),"") -> 4.1778004 | BD34: =_xlfn.IFNA(VLOOKUP($BA34,HAVERD!$A:$BS,BD$2,FALSE),"") -> 4.1039997 | BE34: =_xlfn.IFNA(VLOOKUP($BA34,HAVERD!$A:$BS,BE$2,FALSE),"") -> 4.0037581 | BF34: =_xlfn.IFNA(VLOOKUP($BA34,HAVERD!$A:$BS,BF$2,FALSE),"") -> 3.8936118 | BG34: =_xlfn.IFNA(VLOOKUP($BA34,HAVERD!$A:$BS,BG$2,FALSE),"") -> 3.7891444 | BH34: =_xlfn.IFNA(VLOOKUP($BA34,HAVERD!$A:$BS,BH$2,FALSE),"") -> 3.698212 | BI34: =_xlfn.IFNA(VLOOKUP($BA34,HAVERD!$A:$BS,BI$2,FALSE),"") -> 3.6246667 | ... CX34: =_xlfn.IFNA(VLOOKUP($BA34,HAVERD!$A:$BS,CX$2,FALSE),"") -> 3.7314689
... A37: =A20 -> 45688 | B37: =VLOOKUP($A37,HAVERD!$A:$BS,B$2,FALSE) -> 4.7037 | C37: =VLOOKUP($A37,HAVERD!$A:$BS,C$2,FALSE) -> 4.4560191 | D37: =VLOOKUP($A37,HAVERD!$A:$BS,D$2,FALSE) -> 4.4072557 | E37: =VLOOKUP($A37,HAVERD!$A:$BS,E$2,FALSE) -> 4.3383168 | F37: =VLOOKUP($A37,HAVERD!$A:$BS,F$2,FALSE) -> 4.2592031 | G37: =VLOOKUP($A37,HAVERD!$A:$BS,G$2,FALSE) -> 4.1834049 | H37: =VLOOKUP($A37,HAVERD!$A:$BS,H$2,FALSE) -> 4.1181155 | I37: =VLOOKUP($A37,HAVERD!$A:$BS,I$2,FALSE) -> 4.0656131 | ... AX37: =VLOOKUP($A37,HAVERD!$A:$BS,AX$2,FALSE) -> 3.7897023 | BA37: =BA20 -> 45776 | BB37: =_xlfn.IFNA(VLOOKUP($BA37,HAVERD!$A:$BS,BB$2,FALSE),"") -> 4.459 | BC37: =_xlfn.IFNA(VLOOKUP($BA37,HAVERD!$A:$BS,BC$2,FALSE),"") -> 4.1829059 | BD37: =_xlfn.IFNA(VLOOKUP($BA37,HAVERD!$A:$BS,BD$2,FALSE),"") -> 4.0985573 | BE37: =_xlfn.IFNA(VLOOKUP($BA37,HAVERD!$A:$BS,BE$2,FALSE),"") -> 3.992871 | BF37: =_xlfn.IFNA(VLOOKUP($BA37,HAVERD!$A:$BS,BF$2,FALSE),"") -> 3.8789074 | BG37: =_xlfn.IFNA(VLOOKUP($BA37,HAVERD!$A:$BS,BG$2,FALSE),"") -> 3.7713581 | BH37: =_xlfn.IFNA(VLOOKUP($BA37,HAVERD!$A:$BS,BH$2,FALSE),"") -> 3.6771273 | BI37: =_xlfn.IFNA(VLOOKUP($BA37,HAVERD!$A:$BS,BI$2,FALSE),"") -> 3.5993768 | ... CX37: =_xlfn.IFNA(VLOOKUP($BA37,HAVERD!$A:$BS,CX$2,FALSE),"") -> 3.6985572
A39: Average | BA39: Average
A40: Month | B40: =MONTH(B20) -> 1 | C40: =MONTH(C20) -> 3 | D40: =MONTH(D20) -> 4 | E40: =MONTH(E20) -> 5 | F40: =MONTH(F20) -> 6 | G40: =MONTH(G20) -> 7 | H40: =MONTH(H20) -> 8 | I40: =MONTH(I20) -> 8 | ... AX40: =MONTH(AX20) -> 1 | BA40: Month | BB40: =MONTH(BB18) -> 4 | BC40: =MONTH(BC18) -> 5 | BD40: =MONTH(BD18) -> 6 | BE40: =MONTH(BE18) -> 7 | BF40: =MONTH(BF18) -> 8 | BG40: =MONTH(BG18) -> 9 | BH40: =MONTH(BH18) -> 10 | BI40: =MONTH(BI18) -> 11 | ... CX40: =MONTH(CX18) -> 4
A41: Year | B41: =YEAR(B20) -> 2025 | C41: =YEAR(C20) -> 2025 | D41: =YEAR(D20) -> 2025 | E41: =YEAR(E20) -> 2025 | F41: =YEAR(F20) -> 2025 | G41: =YEAR(G20) -> 2025 | H41: =YEAR(H20) -> 2025 | I41: =YEAR(I20) -> 2025 | ... AX41: =YEAR(AX20) -> 2029 | BA41: Year | BB41: =YEAR(BB20) -> 2025 | BC41: =YEAR(BC20) -> 2025 | BD41: =YEAR(BD20) -> 2025 | BE41: =YEAR(BE20) -> 2025 | BF41: =YEAR(BF20) -> 2025 | BG41: =YEAR(BG20) -> 2025 | BH41: =YEAR(BH20) -> 2025 | BI41: =YEAR(BI20) -> 2025 | ... CX41: =YEAR(CX20) -> 2029
A42: YYYYMM | B42: =B41*100+B40 -> 202501 | C42: =C41*100+C40 -> 202503 | D42: =D41*100+D40 -> 202504 | E42: =E41*100+E40 -> 202505 | F42: =F41*100+F40 -> 202506 | G42: =G41*100+G40 -> 202507 | H42: =H41*100+H40 -> 202508 | I42: =I41*100+I40 -> 202508 | ... AX42: =AX41*100+AX40 -> 202901 | BA42: YYYYMM | BB42: =BB41*100+BB40 -> 202504 | BC42: =BC41*100+BC40 -> 202505 | BD42: =BD41*100+BD40 -> 202506 | BE42: =BE41*100+BE40 -> 202507 | BF42: =BF41*100+BF40 -> 202508 | BG42: =BG41*100+BG40 -> 202509 | BH42: =BH41*100+BH40 -> 202510 | BI42: =BI41*100+BI40 -> 202511 | ... CX42: =CX41*100+CX40 -> 202904
A43: Quarter | B43: =IF(B40<4,1,IF(B40<7,2,IF(B40<10,3,4))) -> 1 | C43: =IF(C40<4,1,IF(C40<7,2,IF(C40<10,3,4))) -> 1 | D43: =IF(D40<4,1,IF(D40<7,2,IF(D40<10,3,4))) -> 2 | E43: =IF(E40<4,1,IF(E40<7,2,IF(E40<10,3,4))) -> 2 | F43: =IF(F40<4,1,IF(F40<7,2,IF(F40<10,3,4))) -> 2 | G43: =IF(G40<4,1,IF(G40<7,2,IF(G40<10,3,4))) -> 3 | H43: =IF(H40<4,1,IF(H40<7,2,IF(H40<10,3,4))) -> 3 | I43: =IF(I40<4,1,IF(I40<7,2,IF(I40<10,3,4))) -> 3 | ... AX43: =IF(AX40<4,1,IF(AX40<7,2,IF(AX40<10,3,4))) -> 1 | BA43: Quarter | BB43: =IF(BB40<4,1,IF(BB40<7,2,IF(BB40<10,3,4))) -> 2 | BC43: =IF(BC40<4,1,IF(BC40<7,2,IF(BC40<10,3,4))) -> 2 | BD43: =IF(BD40<4,1,IF(BD40<7,2,IF(BD40<10,3,4))) -> 2 | BE43: =IF(BE40<4,1,IF(BE40<7,2,IF(BE40<10,3,4))) -> 3 | BF43: =IF(BF40<4,1,IF(BF40<7,2,IF(BF40<10,3,4))) -> 3 | BG43: =IF(BG40<4,1,IF(BG40<7,2,IF(BG40<10,3,4))) -> 3 | BH43: =IF(BH40<4,1,IF(BH40<7,2,IF(BH40<10,3,4))) -> 4 | BI43: =IF(BI40<4,1,IF(BI40<7,2,IF(BI40<10,3,4))) -> 4 | ... CX43: =IF(CX40<4,1,IF(CX40<7,2,IF(CX40<10,3,4))) -> 2
A44: YYYYQQ | B44: =B41*100+B43 -> 202501 | C44: =C41*100+C43 -> 202501 | D44: =D41*100+D43 -> 202502 | E44: =E41*100+E43 -> 202502 | F44: =F41*100+F43 -> 202502 | G44: =G41*100+G43 -> 202503 | H44: =H41*100+H43 -> 202503 | I44: =I41*100+I43 -> 202503 | ... AX44: =AX41*100+AX43 -> 202901 | BA44: YYYYQQ | BB44: =BB41*100+BB43 -> 202502 | BC44: =BC41*100+BC43 -> 202502 | BD44: =BD41*100+BD43 -> 202502 | BE44: =BE41*100+BE43 -> 202503 | BF44: =BF41*100+BF43 -> 202503 | BG44: =BG41*100+BG43 -> 202503 | BH44: =BH41*100+BH43 -> 202504 | BI44: =BI41*100+BI43 -> 202504 | ... CX44: =CX41*100+CX43 -> 202902
A45: Average | B45: =AVERAGE(B23:B37) -> 4.7003533 | C45: =AVERAGE(C23:C37) -> 4.4978641 | D45: =AVERAGE(D23:D37) -> 4.4456125 | E45: =AVERAGE(E23:E37) -> 4.3910125 | F45: =AVERAGE(F23:F37) -> 4.3322282 | G45: =AVERAGE(G23:G37) -> 4.2741196 | H45: =AVERAGE(H23:H37) -> 4.221536 | I45: =AVERAGE(I23:I37) -> 4.1776239 | ... AX45: =AVERAGE(AX23:AX37) -> 3.9111985 | BA45: Average | BB45: =AVERAGE(BB23:BB37) -> 4.4585846 | BC45: =AVERAGE(BC23:BC37) -> 4.2497151 | BD45: =AVERAGE(BD23:BD37) -> 4.141556 | BE45: =AVERAGE(BE23:BE37) -> 4.0399312 | BF45: =AVERAGE(BF23:BF37) -> 3.9396641 | BG45: =AVERAGE(BG23:BG37) -> 3.8433018 | BH45: =AVERAGE(BH23:BH37) -> 3.7563932 | BI45: =AVERAGE(BI23:BI37) -> 3.6835955 | ... CX45: =AVERAGE(CX23:CX37) -> 3.799509
BA46: Latest | BB46: =BB35 -> 4.4591 | BC46: =BC35 -> 4.1852128 | BD46: =BD35 -> 4.1105568 | BE46: =BE35 -> 4.0107009 | BF46: =BF35 -> 3.9014817 | BG46: =BG35 -> 3.7980535 | BH46: =BH35 -> 3.7078487 | BI46: =BI35 -> 3.6335726 | ... CX46: =CX35 -> 3.7146607
A48: Quarterly series | BA48: Quarterly series
B49: =B44 -> 202501 | C49: =IF(RIGHT(B49)="4",B49+97,B49+1) -> 202502 | D49: =IF(RIGHT(C49)="4",C49+97,C49+1) -> 202503 | E49: =IF(RIGHT(D49)="4",D49+97,D49+1) -> 202504 | F49: =IF(RIGHT(E49)="4",E49+97,E49+1) -> 202601 | G49: =IF(RIGHT(F49)="4",F49+97,F49+1) -> 202602 | H49: =IF(RIGHT(G49)="4",G49+97,G49+1) -> 202603 | I49: =IF(RIGHT(H49)="4",H49+97,H49+1) -> 202604 | J49: =IF(RIGHT(I49)="4",I49+97,I49+1) -> 202701 | ... R49: =IF(RIGHT(Q49)="4",Q49+97,Q49+1) -> 202901 | BB49: =BB44 -> 202502 | BC49: =IF(RIGHT(BB49)="4",BB49+97,BB49+1) -> 202503 | BD49: =IF(RIGHT(BC49)="4",BC49+97,BC49+1) -> 202504 | BE49: =IF(RIGHT(BD49)="4",BD49+97,BD49+1) -> 202601 | BF49: =IF(RIGHT(BE49)="4",BE49+97,BE49+1) -> 202602 | BG49: =IF(RIGHT(BF49)="4",BF49+97,BF49+1) -> 202603 | BH49: =IF(RIGHT(BG49)="4",BG49+97,BG49+1) -> 202604 | BI49: =IF(RIGHT(BH49)="4",BH49+97,BH49+1) -> 202701 | BJ49: =IF(RIGHT(BI49)="4",BI49+97,BI49+1) -> 202702 | ... BQ49: =IF(RIGHT(BP49)="4",BP49+97,BP49+1) -> 202901
A50: =A1 -> February 2025 MPR | B50: =AVERAGEIF($B$44:$AX$44,B49,$B$45:$AX$45) -> 4.5991087 | C50: =AVERAGEIF($B$44:$AX$44,C49,$B$45:$AX$45) -> 4.3896177 | D50: =AVERAGEIF($B$44:$AX$44,D49,$B$45:$AX$45) -> 4.2244265 | E50: =AVERAGEIF($B$44:$AX$44,E49,$B$45:$AX$45) -> 4.1169167 | F50: =AVERAGEIF($B$44:$AX$44,F49,$B$45:$AX$45) -> 4.0936293 | G50: =AVERAGEIF($B$44:$AX$44,G49,$B$45:$AX$45) -> 4.0876992 | H50: =AVERAGEIF($B$44:$AX$44,H49,$B$45:$AX$45) -> 4.0756176 | I50: =AVERAGEIF($B$44:$AX$44,I49,$B$45:$AX$45) -> 4.0500662 | ... R50: =AVERAGEIF($B$44:$AX$44,R49,$B$45:$AX$45) -> 3.9111985 | BA50: =BA1 -> May 2025 MPR | BB50: =AVERAGEIF($BB$44:$CW$44,BB49,$BB$45:$CW$45) -> 4.2832852 | BC50: =AVERAGEIF($BB$44:$CW$44,BC49,$BB$45:$CW$45) -> 3.9409657 | BD50: =AVERAGEIF($BB$44:$CW$44,BD49,$BB$45:$CW$45) -> 3.6889385 | BE50: =AVERAGEIF($BB$44:$CW$44,BE49,$BB$45:$CW$45) -> 3.5615933 | BF50: =AVERAGEIF($BB$44:$CW$44,BF49,$BB$45:$CW$45) -> 3.5286707 | BG50: =AVERAGEIF($BB$44:$CW$44,BG49,$BB$45:$CW$45) -> 3.528984 | BH50: =AVERAGEIF($BB$44:$CW$44,BH49,$BB$45:$CW$45) -> 3.5378558 | BI50: =AVERAGEIF($BB$44:$CW$44,BI49,$BB$45:$CW$45) -> 3.5463125 | ... BQ50: =AVERAGEIF($BB$44:$CW$44,BQ49,$BB$45:$CW$45) -> 3.7716414
BA52: Comparison - monthly
BB53: 44927 | BC53: 44958 | BD53: 44986 | BE53: 45017 | BF53: 45047 | BG53: 45078 | BH53: 45108 | BI53: 45139 | BJ53: 45170 | BK53: 45200 | BL53: 45231 | BM53: 45261 | BN53: 45292 | BO53: 45323 | BP53: 45352 | BQ53: 45383 | BR53: 45413 | BS53: 45444 | BT53: 45474 | BU53: 45505 | BV53: 45536 | BW53: 45566 | BX53: 45597 | BY53: 45627 | BZ53: 45658 | CA53: 45689 | CB53: 45717 | CC53: 45748 | CD53: 45778 | CE53: 45809 | CF53: 45839 | CG53: 45870 | CH53: 45901 | CI53: 45931 | CJ53: 45962 | CK53: 45992 | CL53: 46023 | CM53: 46054 | CN53: 46082 | CO53: 46113 | CP53: 46143 | CQ53: 46174 | CR53: 46204 | CS53: 46235 | CT53: 46266 | CU53: 46296 | CV53: 46327 | CW53: 46357 | CX53: 46388 | CY53: 46419 | CZ53: 46447 | DA53: 46478 | DB53: 46508 | DC53: 46539 | DD53: 46569 | DE53: 46600 | DF53: 46631 | DG53: 46661 | DH53: 46692 | DI53: 46722
BB54: =MONTH(BB53) -> 1 | BC54: =MONTH(BC53) -> 2 | BD54: =MONTH(BD53) -> 3 | BE54: =MONTH(BE53) -> 4 | BF54: =MONTH(BF53) -> 5 | BG54: =MONTH(BG53) -> 6 | BH54: =MONTH(BH53) -> 7 | BI54: =MONTH(BI53) -> 8 | ... DI54: =MONTH(DI53) -> 12
BB55: 202301 | BC55: =IF(BC54=1,BB55+89,BB55+1) -> 202302 | BD55: =IF(BD54=1,BC55+89,BC55+1) -> 202303 | BE55: =IF(BE54=1,BD55+89,BD55+1) -> 202304 | BF55: =IF(BF54=1,BE55+89,BE55+1) -> 202305 | BG55: =IF(BG54=1,BF55+89,BF55+1) -> 202306 | BH55: =IF(BH54=1,BG55+89,BG55+1) -> 202307 | BI55: =IF(BI54=1,BH55+89,BH55+1) -> 202308 | BJ55: =IF(BJ54=1,BI55+89,BI55+1) -> 202309 | ... DI55: =IF(DI54=1,DH55+89,DH55+1) -> 202712
BA56: Bank Rate | BB56: =VLOOKUP(BB53,HAVERM!$A:$N,14,FALSE) -> 3.5 | BC56: =VLOOKUP(BC53,HAVERM!$A:$N,14,FALSE) -> 4 | BD56: =VLOOKUP(BD53,HAVERM!$A:$N,14,FALSE) -> 4.25 | BE56: =VLOOKUP(BE53,HAVERM!$A:$N,14,FALSE) -> 4.25 | BF56: =VLOOKUP(BF53,HAVERM!$A:$N,14,FALSE) -> 4.5 | BG56: =VLOOKUP(BG53,HAVERM!$A:$N,14,FALSE) -> 5 | BH56: =VLOOKUP(BH53,HAVERM!$A:$N,14,FALSE) -> 5 | BI56: =VLOOKUP(BI53,HAVERM!$A:$N,14,FALSE) -> 5.25 | ... DI56: =VLOOKUP(DI53,HAVERM!$A:$N,14,FALSE) -> #N/A
BA57: =A50 -> February 2025 MPR | BB57: =HLOOKUP(BB$55,$B$42:$AX$45,4,FALSE) -> #N/A | BC57: =HLOOKUP(BC$55,$B$42:$AX$45,4,FALSE) -> #N/A | BD57: =HLOOKUP(BD$55,$B$42:$AX$45,4,FALSE) -> #N/A | BE57: =HLOOKUP(BE$55,$B$42:$AX$45,4,FALSE) -> #N/A | BF57: =HLOOKUP(BF$55,$B$42:$AX$45,4,FALSE) -> #N/A | BG57: =HLOOKUP(BG$55,$B$42:$AX$45,4,FALSE) -> #N/A | BH57: =HLOOKUP(BH$55,$B$42:$AX$45,4,FALSE) -> #N/A | BI57: =HLOOKUP(BI$55,$B$42:$AX$45,4,FALSE) -> #N/A | ... CG57: =HLOOKUP(CG$55,$B$42:$AX$45,4,FALSE) -> 4.221536 | CH57: =J45 -> 4.1438796 | CI57: =HLOOKUP(CI$55,$B$42:$AX$45,4,FALSE) -> 4.1438796 | CJ57: =L45 -> 4.105616 | CK57: =HLOOKUP(CK$55,$B$42:$AX$45,4,FALSE) -> 4.105616 | CL57: =HLOOKUP(CL$55,$B$42:$AX$45,4,FALSE) -> 4.0947015 | CM57: =O45 -> 4.0925571 | CN57: =HLOOKUP(CN$55,$B$42:$AX$45,4,FALSE) -> 4.0925571 | CO57: =HLOOKUP(CO$55,$B$42:$AX$45,4,FALSE) -> 4.0903717 | CP57: =HLOOKUP(CP$55,$B$42:$AX$45,4,FALSE) -> 4.0878859 | CQ57: =HLOOKUP(CQ$55,$B$42:$AX$45,4,FALSE) -> 4.08484 | CR57: =HLOOKUP(CR$55,$B$42:$AX$45,4,FALSE) -> 4.0809747 | CS57: =HLOOKUP(CS$55,$B$42:$AX$45,4,FALSE) -> 4.0760306 | CT57: =V45 -> 4.0626075 | CU57: =HLOOKUP(CU$55,$B$42:$AX$45,4,FALSE) -> 4.0626075 | CV57: =X45 -> 4.0459819 | CW57: =HLOOKUP(CW$55,$B$42:$AX$45,4,FALSE) -> 4.0459819 | CX57: =HLOOKUP(CX$55,$B$42:$AX$45,4,FALSE) -> 4.0282027 | CY57: =AA45 -> 4.0194834 | CZ57: =HLOOKUP(CZ$55,$B$42:$AX$45,4,FALSE) -> 4.0194834 | DA57: =HLOOKUP(DA$55,$B$42:$AX$45,4,FALSE) -> 4.0110084 | DB57: =HLOOKUP(DB$55,$B$42:$AX$45,4,FALSE) -> 4.0027926 | DC57: =HLOOKUP(DC$55,$B$42:$AX$45,4,FALSE) -> 3.9948508 | DD57: =HLOOKUP(DD$55,$B$42:$AX$45,4,FALSE) -> 3.9871975 | DE57: =HLOOKUP(DE$55,$B$42:$AX$45,4,FALSE) -> 3.9798477 | DF57: =AH45 -> 3.9661172 | DG57: =HLOOKUP(DG$55,$B$42:$AX$45,4,FALSE) -> 3.9661172 | DH57: =AJ45 -> 3.9537772 | DI57: =HLOOKUP(DI$55,$B$42:$AX$45,4,FALSE) -> 3.9537772
BA58: =BA50 -> May 2025 MPR | BB58: =HLOOKUP(BB$55,$BB$42:$CW$45,4,FALSE) -> #N/A | BC58: =HLOOKUP(BC$55,$BB$42:$CW$45,4,FALSE) -> #N/A | BD58: =HLOOKUP(BD$55,$BB$42:$CW$45,4,FALSE) -> #N/A | BE58: =HLOOKUP(BE$55,$BB$42:$CW$45,4,FALSE) -> #N/A | BF58: =HLOOKUP(BF$55,$BB$42:$CW$45,4,FALSE) -> #N/A | BG58: =HLOOKUP(BG$55,$BB$42:$CW$45,4,FALSE) -> #N/A | BH58: =HLOOKUP(BH$55,$BB$42:$CW$45,4,FALSE) -> #N/A | BI58: =HLOOKUP(BI$55,$BB$42:$CW$45,4,FALSE) -> #N/A | ... CA58: =HLOOKUP(CA$55,$BB$42:$CW$45,4,FALSE) -> #N/A | CB58: =CB56 -> 4.5 | CC58: =HLOOKUP(CC$55,$BB$42:$CW$45,4,FALSE) -> 4.4585846 | CD58: =HLOOKUP(CD$55,$BB$42:$CW$45,4,FALSE) -> 4.2497151 | CE58: =HLOOKUP(CE$55,$BB$42:$CW$45,4,FALSE) -> 4.141556 | CF58: =HLOOKUP(CF$55,$BB$42:$CW$45,4,FALSE) -> 4.0399312 | CG58: =HLOOKUP(CG$55,$BB$42:$CW$45,4,FALSE) -> 3.9396641 | CH58: =HLOOKUP(CH$55,$BB$42:$CW$45,4,FALSE) -> 3.8433018 | CI58: =HLOOKUP(CI$55,$BB$42:$CW$45,4,FALSE) -> 3.7563932 | CJ58: =HLOOKUP(CJ$55,$BB$42:$CW$45,4,FALSE) -> 3.6835955 | ... DI58: =HLOOKUP(DI$55,$BB$42:$CW$45,4,FALSE) -> 3.6062385
BA59: Latest | BB59: =HLOOKUP(BB$55,$BB$42:$CW$46,5,FALSE) -> #N/A | BC59: =HLOOKUP(BC$55,$BB$42:$CW$46,5,FALSE) -> #N/A | BD59: =HLOOKUP(BD$55,$BB$42:$CW$46,5,FALSE) -> #N/A | BE59: =HLOOKUP(BE$55,$BB$42:$CW$46,5,FALSE) -> #N/A | BF59: =HLOOKUP(BF$55,$BB$42:$CW$46,5,FALSE) -> #N/A | BG59: =HLOOKUP(BG$55,$BB$42:$CW$46,5,FALSE) -> #N/A | BH59: =HLOOKUP(BH$55,$BB$42:$CW$46,5,FALSE) -> #N/A | BI59: =HLOOKUP(BI$55,$BB$42:$CW$46,5,FALSE) -> #N/A | ... DI59: =HLOOKUP(DI$55,$BB$42:$CW$46,5,FALSE) -> 3.5176591
BA60: Difference | BQ60: =BQ58-BQ57 -> #N/A | BR60: =BR58-BR57 -> #N/A | BS60: =BS58-BS57 -> #N/A | BT60: =BT58-BT57 -> #N/A | BU60: =BU58-BU57 -> #N/A | BV60: =BV58-BV57 -> #N/A | BW60: =BW58-BW57 -> #N/A | BX60: =BX58-BX57 -> #N/A | ... DI60: =DI58-DI57 -> -0.34753862
BA61: Next 3 years | DC61: =AVERAGE(BW60:DC60) -> #N/A
BA63: Comparison - quarterly
BB64: 44927 | BC64: 45017 | BD64: 45108 | BE64: 45200 | BF64: 45292 | BG64: 45383 | BH64: 45474 | BI64: 45566 | BJ64: 45658 | BK64: 45748 | BL64: 45839 | BM64: 45931 | BN64: 46023 | BO64: 46113 | BP64: 46204 | BQ64: 46296 | BR64: 46388 | BS64: 46478 | BT64: 46569 | BU64: 46661
BB65: 202301 | BC65: =IF(RIGHT(BB65)="4",BB65+97,BB65+1) -> 202302 | BD65: =IF(RIGHT(BC65)="4",BC65+97,BC65+1) -> 202303 | BE65: =IF(RIGHT(BD65)="4",BD65+97,BD65+1) -> 202304 | BF65: =IF(RIGHT(BE65)="4",BE65+97,BE65+1) -> 202401 | BG65: =IF(RIGHT(BF65)="4",BF65+97,BF65+1) -> 202402 | BH65: =IF(RIGHT(BG65)="4",BG65+97,BG65+1) -> 202403 | BI65: =IF(RIGHT(BH65)="4",BH65+97,BH65+1) -> 202404 | BJ65: =IF(RIGHT(BI65)="4",BI65+97,BI65+1) -> 202501 | ... BU65: =IF(RIGHT(BT65)="4",BT65+97,BT65+1) -> 202704
BA66: Bank Rate | BB66: =VLOOKUP(BB64,HAVERQ!$A:$G,7,FALSE) -> 4.25 | BC66: =VLOOKUP(BC64,HAVERQ!$A:$G,7,FALSE) -> 5 | BD66: =VLOOKUP(BD64,HAVERQ!$A:$G,7,FALSE) -> 5.25 | BE66: =VLOOKUP(BE64,HAVERQ!$A:$G,7,FALSE) -> 5.25 | BF66: =VLOOKUP(BF64,HAVERQ!$A:$G,7,FALSE) -> 5.25 | BG66: =VLOOKUP(BG64,HAVERQ!$A:$G,7,FALSE) -> 5.25 | BH66: =VLOOKUP(BH64,HAVERQ!$A:$G,7,FALSE) -> 5 | BI66: =VLOOKUP(BI64,HAVERQ!$A:$G,7,FALSE) -> 4.75
BA67: =A50 -> February 2025 MPR | BB67: =HLOOKUP(BB$65,$B$49:$R$50,2,FALSE) -> #N/A | BC67: =HLOOKUP(BC$65,$B$49:$R$50,2,FALSE) -> #N/A | BD67: =HLOOKUP(BD$65,$B$49:$R$50,2,FALSE) -> #N/A | BE67: =HLOOKUP(BE$65,$B$49:$R$50,2,FALSE) -> #N/A | BF67: =HLOOKUP(BF$65,$B$49:$R$50,2,FALSE) -> #N/A | BG67: =HLOOKUP(BG$65,$B$49:$R$50,2,FALSE) -> #N/A | BH67: =HLOOKUP(BH$65,$B$49:$R$50,2,FALSE) -> #N/A | BI67: =HLOOKUP(BI$65,$B$49:$R$50,2,FALSE) -> #N/A | ... BU67: =HLOOKUP(BU$65,$B$49:$R$50,2,FALSE) -> 3.9569564
BA68: =BA50 -> May 2025 MPR | BB68: =HLOOKUP(BB$65,$BB$49:$BR$50,2,FALSE) -> #N/A | BC68: =HLOOKUP(BC$65,$BB$49:$BR$50,2,FALSE) -> #N/A | BD68: =HLOOKUP(BD$65,$BB$49:$BR$50,2,FALSE) -> #N/A | BE68: =HLOOKUP(BE$65,$BB$49:$BR$50,2,FALSE) -> #N/A | BF68: =HLOOKUP(BF$65,$BB$49:$BR$50,2,FALSE) -> #N/A | BG68: =HLOOKUP(BG$65,$BB$49:$BR$50,2,FALSE) -> #N/A | BH68: =HLOOKUP(BH$65,$BB$49:$BR$50,2,FALSE) -> #N/A | BI68: =BI66 -> 4.75 | BJ68: =HLOOKUP(BJ$65,$BB$49:$BR$50,2,FALSE) -> #N/A | BK68: =HLOOKUP(BK$65,$BB$49:$BR$50,2,FALSE) -> 4.2832852 | BL68: =HLOOKUP(BL$65,$BB$49:$BR$50,2,FALSE) -> 3.9409657 | BM68: =HLOOKUP(BM$65,$BB$49:$BR$50,2,FALSE) -> 3.6889385 | BN68: =HLOOKUP(BN$65,$BB$49:$BR$50,2,FALSE) -> 3.5615933 | BO68: =HLOOKUP(BO$65,$BB$49:$BR$50,2,FALSE) -> 3.5286707 | BP68: =HLOOKUP(BP$65,$BB$49:$BR$50,2,FALSE) -> 3.528984 | BQ68: =HLOOKUP(BQ$65,$BB$49:$BR$50,2,FALSE) -> 3.5378558 | ... BU68: =HLOOKUP(BU$65,$BB$49:$BR$50,2,FALSE) -> 3.5976845
BA69: Difference | BH69: =BH68-BH67 -> #N/A | BI69: =BI68-BI67 -> #N/A | BJ69: =BJ68-BJ67 -> #N/A | BK69: =BK68-BK67 -> -0.10633249 | BL69: =BL68-BL67 -> -0.28346081 | BM69: =BM68-BM67 -> -0.42797819 | BN69: =BN68-BN67 -> -0.53203602 | BO69: =BO68-BO67 -> -0.55902848 | ... BU69: =BU68-BU67 -> -0.35927197
BA70: Next 3 years | BS70: =AVERAGE(BH69:BS69) -> #N/A

Sheet Market expectations - Gas
A1: ='Market pricing dates'!A2 -> February 2025 MPR | C1: ='Market pricing dates'!A12 -> 15 working days to 31 Jan 2025 | AZ1: ='Market pricing dates'!D2 -> May 2025 MPR | BB1: ='Market pricing dates'!D12 -> 15 working days to 29 Apr 2025
A2: Column # | B2: =HAVERD!BU$1 -> 73 | C2: =+B2+1 -> 74 | D2: =+C2+1 -> 75 | E2: =+D2+1 -> 76 | F2: =+E2+1 -> 77 | G2: =+F2+1 -> 78 | H2: =+G2+1 -> 79 | I2: =+H2+1 -> 80 | J2: =+I2+1 -> 81 | ... AW2: =+AV2+1 -> 120 | AZ2: Column # | BA2: =HAVERD!BU$1 -> 73 | BB2: =+BA2+1 -> 74 | BC2: =+BB2+1 -> 75 | BD2: =+BC2+1 -> 76 | BE2: =+BD2+1 -> 77 | BF2: =+BE2+1 -> 78 | BG2: =+BF2+1 -> 79 | BH2: =+BG2+1 -> 80 | BI2: =+BH2+1 -> 81 | ... CV2: =+CU2+1 -> 120
A3: Months | B3: =HAVERD!BU$2 -> Gas - 1 | C3: =HAVERD!BV$2 -> Gas - 2 | D3: =HAVERD!BW$2 -> Gas - 3 | E3: =HAVERD!BX$2 -> Gas - 4 | F3: =HAVERD!BY$2 -> Gas - 5 | G3: =HAVERD!BZ$2 -> Gas - 6 | H3: =HAVERD!CA$2 -> Gas - 7 | I3: =HAVERD!CB$2 -> Gas - 8 | ... AW3: =HAVERD!DP$2 -> Gas - 48 | AZ3: Months | BA3: =HAVERD!BU$2 -> Gas - 1 | BB3: =HAVERD!BV$2 -> Gas - 2 | BC3: =HAVERD!BW$2 -> Gas - 3 | BD3: =HAVERD!BX$2 -> Gas - 4 | BE3: =HAVERD!BY$2 -> Gas - 5 | BF3: =HAVERD!BZ$2 -> Gas - 6 | BG3: =HAVERD!CA$2 -> Gas - 7 | BH3: =HAVERD!CB$2 -> Gas - 8 | ... CV3: =HAVERD!DP$2 -> Gas - 48
A4: Days | C4: 30.416667 | D4: =+C4+30.4166667 -> 60.833333 | E4: =+D4+30.4166667 -> 91.25 | F4: =+E4+30.4166667 -> 121.66667 | G4: =+F4+30.4166667 -> 152.08333 | H4: =+G4+30.4166667 -> 182.5 | I4: =+H4+30.4166667 -> 212.91667 | J4: =+I4+30.4166667 -> 243.33333 | K4: =+J4+30.4166667 -> 273.75 | ... AW4: =+AV4+30.4166667 -> 1429.5833 | AZ4: Days | BB4: 30.416667 | BC4: =+BB4+30.4166667 -> 60.833333 | BD4: =+BC4+30.4166667 -> 91.25 | BE4: =+BD4+30.4166667 -> 121.66667 | BF4: =+BE4+30.4166667 -> 152.08333 | BG4: =+BF4+30.4166667 -> 182.5 | BH4: =+BG4+30.4166667 -> 212.91667 | BI4: =+BH4+30.4166667 -> 243.33333 | BJ4: =+BI4+30.4166667 -> 273.75 | ... CV4: =+CU4+30.4166667 -> 1429.5833
A5: Dates | AZ5: Dates
A6: =A11-7 -> 45670 | B6: =A6 -> 45670 | C6: =$B6+C$4 -> 45700.417 | D6: =$B6+D$4 -> 45730.833 | E6: =$B6+E$4 -> 45761.25 | F6: =$B6+F$4 -> 45791.667 | G6: =$B6+G$4 -> 45822.083 | H6: =$B6+H$4 -> 45852.5 | I6: =$B6+I$4 -> 45882.917 | J6: =$B6+J$4 -> 45913.333 | ... AW6: =$B6+AW$4 -> 47099.583 | AZ6: =AZ11-7 -> 45756 | BA6: =AZ6 -> 45756 | BB6: =$AZ6+BB$4 -> 45786.417 | BC6: =$AZ6+BC$4 -> 45816.833 | BD6: =$AZ6+BD$4 -> 45847.25 | BE6: =$AZ6+BE$4 -> 45877.667 | BF6: =$AZ6+BF$4 -> 45908.083 | BG6: =$AZ6+BG$4 -> 45938.5 | BH6: =$AZ6+BH$4 -> 45968.917 | BI6: =$AZ6+BI$4 -> 45999.333 | ... CV6: =$AZ6+CV$4 -> 47185.583
A7: =A12-7 -> 45671 | B7: =A7 -> 45671 | C7: =$B7+C$4 -> 45701.417 | D7: =$B7+D$4 -> 45731.833 | E7: =$B7+E$4 -> 45762.25 | F7: =$B7+F$4 -> 45792.667 | G7: =$B7+G$4 -> 45823.083 | H7: =$B7+H$4 -> 45853.5 | I7: =$B7+I$4 -> 45883.917 | J7: =$B7+J$4 -> 45914.333 | ... AW7: =$B7+AW$4 -> 47100.583 | AZ7: =AZ12-7 -> 45757 | BA7: =AZ7 -> 45757 | BB7: =$AZ7+BB$4 -> 45787.417 | BC7: =$AZ7+BC$4 -> 45817.833 | BD7: =$AZ7+BD$4 -> 45848.25 | BE7: =$AZ7+BE$4 -> 45878.667 | BF7: =$AZ7+BF$4 -> 45909.083 | BG7: =$AZ7+BG$4 -> 45939.5 | BH7: =$AZ7+BH$4 -> 45969.917 | BI7: =$AZ7+BI$4 -> 46000.333 | ... CV7: =$AZ7+CV$4 -> 47186.583
A8: =A13-7 -> 45672 | B8: =A8 -> 45672 | C8: =$B8+C$4 -> 45702.417 | D8: =$B8+D$4 -> 45732.833 | E8: =$B8+E$4 -> 45763.25 | F8: =$B8+F$4 -> 45793.667 | G8: =$B8+G$4 -> 45824.083 | H8: =$B8+H$4 -> 45854.5 | I8: =$B8+I$4 -> 45884.917 | J8: =$B8+J$4 -> 45915.333 | ... AW8: =$B8+AW$4 -> 47101.583 | AZ8: =AZ13-7 -> 45758 | BA8: =AZ8 -> 45758 | BB8: =$AZ8+BB$4 -> 45788.417 | BC8: =$AZ8+BC$4 -> 45818.833 | BD8: =$AZ8+BD$4 -> 45849.25 | BE8: =$AZ8+BE$4 -> 45879.667 | BF8: =$AZ8+BF$4 -> 45910.083 | BG8: =$AZ8+BG$4 -> 45940.5 | BH8: =$AZ8+BH$4 -> 45970.917 | BI8: =$AZ8+BI$4 -> 46001.333 | ... CV8: =$AZ8+CV$4 -> 47187.583
A9: =A14-7 -> 45673 | B9: =A9 -> 45673 | C9: =$B9+C$4 -> 45703.417 | D9: =$B9+D$4 -> 45733.833 | E9: =$B9+E$4 -> 45764.25 | F9: =$B9+F$4 -> 45794.667 | G9: =$B9+G$4 -> 45825.083 | H9: =$B9+H$4 -> 45855.5 | I9: =$B9+I$4 -> 45885.917 | J9: =$B9+J$4 -> 45916.333 | ... AW9: =$B9+AW$4 -> 47102.583 | AZ9: =AZ14-7 -> 45761 | BA9: =AZ9 -> 45761 | BB9: =$AZ9+BB$4 -> 45791.417 | BC9: =$AZ9+BC$4 -> 45821.833 | BD9: =$AZ9+BD$4 -> 45852.25 | BE9: =$AZ9+BE$4 -> 45882.667 | BF9: =$AZ9+BF$4 -> 45913.083 | BG9: =$AZ9+BG$4 -> 45943.5 | BH9: =$AZ9+BH$4 -> 45973.917 | BI9: =$AZ9+BI$4 -> 46004.333 | ... CV9: =$AZ9+CV$4 -> 47190.583
A10: =A15-7 -> 45674 | B10: =A10 -> 45674 | C10: =$B10+C$4 -> 45704.417 | D10: =$B10+D$4 -> 45734.833 | E10: =$B10+E$4 -> 45765.25 | F10: =$B10+F$4 -> 45795.667 | G10: =$B10+G$4 -> 45826.083 | H10: =$B10+H$4 -> 45856.5 | I10: =$B10+I$4 -> 45886.917 | J10: =$B10+J$4 -> 45917.333 | ... AW10: =$B10+AW$4 -> 47103.583 | AZ10: =AZ15-7 -> 45762 | BA10: =AZ10 -> 45762 | BB10: =$AZ10+BB$4 -> 45792.417 | BC10: =$AZ10+BC$4 -> 45822.833 | BD10: =$AZ10+BD$4 -> 45853.25 | BE10: =$AZ10+BE$4 -> 45883.667 | BF10: =$AZ10+BF$4 -> 45914.083 | BG10: =$AZ10+BG$4 -> 45944.5 | BH10: =$AZ10+BH$4 -> 45974.917 | BI10: =$AZ10+BI$4 -> 46005.333 | ... CV10: =$AZ10+CV$4 -> 47191.583
A11: =A16-7 -> 45677 | B11: =A11 -> 45677 | C11: =$B11+C$4 -> 45707.417 | D11: =$B11+D$4 -> 45737.833 | E11: =$B11+E$4 -> 45768.25 | F11: =$B11+F$4 -> 45798.667 | G11: =$B11+G$4 -> 45829.083 | H11: =$B11+H$4 -> 45859.5 | I11: =$B11+I$4 -> 45889.917 | J11: =$B11+J$4 -> 45920.333 | ... AW11: =$B11+AW$4 -> 47106.583 | AZ11: =AZ16-7 -> 45763 | BA11: =AZ11 -> 45763 | BB11: =$AZ11+BB$4 -> 45793.417 | BC11: =$AZ11+BC$4 -> 45823.833 | BD11: =$AZ11+BD$4 -> 45854.25 | BE11: =$AZ11+BE$4 -> 45884.667 | BF11: =$AZ11+BF$4 -> 45915.083 | BG11: =$AZ11+BG$4 -> 45945.5 | BH11: =$AZ11+BH$4 -> 45975.917 | BI11: =$AZ11+BI$4 -> 46006.333 | ... CV11: =$AZ11+CV$4 -> 47192.583
A12: =A17-7 -> 45678 | B12: =A12 -> 45678 | C12: =$B12+C$4 -> 45708.417 | D12: =$B12+D$4 -> 45738.833 | E12: =$B12+E$4 -> 45769.25 | F12: =$B12+F$4 -> 45799.667 | G12: =$B12+G$4 -> 45830.083 | H12: =$B12+H$4 -> 45860.5 | I12: =$B12+I$4 -> 45890.917 | J12: =$B12+J$4 -> 45921.333 | ... AW12: =$B12+AW$4 -> 47107.583 | AZ12: =AZ17-7 -> 45764 | BA12: =AZ12 -> 45764 | BB12: =$AZ12+BB$4 -> 45794.417 | BC12: =$AZ12+BC$4 -> 45824.833 | BD12: =$AZ12+BD$4 -> 45855.25 | BE12: =$AZ12+BE$4 -> 45885.667 | BF12: =$AZ12+BF$4 -> 45916.083 | BG12: =$AZ12+BG$4 -> 45946.5 | BH12: =$AZ12+BH$4 -> 45976.917 | BI12: =$AZ12+BI$4 -> 46007.333 | ... CV12: =$AZ12+CV$4 -> 47193.583
A13: =A18-7 -> 45679 | B13: =A13 -> 45679 | C13: =$B13+C$4 -> 45709.417 | D13: =$B13+D$4 -> 45739.833 | E13: =$B13+E$4 -> 45770.25 | F13: =$B13+F$4 -> 45800.667 | G13: =$B13+G$4 -> 45831.083 | H13: =$B13+H$4 -> 45861.5 | I13: =$B13+I$4 -> 45891.917 | J13: =$B13+J$4 -> 45922.333 | ... AW13: =$B13+AW$4 -> 47108.583 | AZ13: =AZ18-7 -> 45765 | BA13: =AZ13 -> 45765 | BB13: =$AZ13+BB$4 -> 45795.417 | BC13: =$AZ13+BC$4 -> 45825.833 | BD13: =$AZ13+BD$4 -> 45856.25 | BE13: =$AZ13+BE$4 -> 45886.667 | BF13: =$AZ13+BF$4 -> 45917.083 | BG13: =$AZ13+BG$4 -> 45947.5 | BH13: =$AZ13+BH$4 -> 45977.917 | BI13: =$AZ13+BI$4 -> 46008.333 | ... CV13: =$AZ13+CV$4 -> 47194.583
A14: =A19-7 -> 45680 | B14: =A14 -> 45680 | C14: =$B14+C$4 -> 45710.417 | D14: =$B14+D$4 -> 45740.833 | E14: =$B14+E$4 -> 45771.25 | F14: =$B14+F$4 -> 45801.667 | G14: =$B14+G$4 -> 45832.083 | H14: =$B14+H$4 -> 45862.5 | I14: =$B14+I$4 -> 45892.917 | J14: =$B14+J$4 -> 45923.333 | ... AW14: =$B14+AW$4 -> 47109.583 | AZ14: =AZ19-7 -> 45768 | BA14: =AZ14 -> 45768 | BB14: =$AZ14+BB$4 -> 45798.417 | BC14: =$AZ14+BC$4 -> 45828.833 | BD14: =$AZ14+BD$4 -> 45859.25 | BE14: =$AZ14+BE$4 -> 45889.667 | BF14: =$AZ14+BF$4 -> 45920.083 | BG14: =$AZ14+BG$4 -> 45950.5 | BH14: =$AZ14+BH$4 -> 45980.917 | BI14: =$AZ14+BI$4 -> 46011.333 | ... CV14: =$AZ14+CV$4 -> 47197.583
A15: =A20-7 -> 45681 | B15: =A15 -> 45681 | C15: =$B15+C$4 -> 45711.417 | D15: =$B15+D$4 -> 45741.833 | E15: =$B15+E$4 -> 45772.25 | F15: =$B15+F$4 -> 45802.667 | G15: =$B15+G$4 -> 45833.083 | H15: =$B15+H$4 -> 45863.5 | I15: =$B15+I$4 -> 45893.917 | J15: =$B15+J$4 -> 45924.333 | ... AW15: =$B15+AW$4 -> 47110.583 | AZ15: =AZ20-7 -> 45769 | BA15: =AZ15 -> 45769 | BB15: =$AZ15+BB$4 -> 45799.417 | BC15: =$AZ15+BC$4 -> 45829.833 | BD15: =$AZ15+BD$4 -> 45860.25 | BE15: =$AZ15+BE$4 -> 45890.667 | BF15: =$AZ15+BF$4 -> 45921.083 | BG15: =$AZ15+BG$4 -> 45951.5 | BH15: =$AZ15+BH$4 -> 45981.917 | BI15: =$AZ15+BI$4 -> 46012.333 | ... CV15: =$AZ15+CV$4 -> 47198.583
A16: ='Market pricing dates'!B5 -> 45684 | B16: =A16 -> 45684 | C16: =$B16+C$4 -> 45714.417 | D16: =$B16+D$4 -> 45744.833 | E16: =$B16+E$4 -> 45775.25 | F16: =$B16+F$4 -> 45805.667 | G16: =$B16+G$4 -> 45836.083 | H16: =$B16+H$4 -> 45866.5 | I16: =$B16+I$4 -> 45896.917 | J16: =$B16+J$4 -> 45927.333 | ... AW16: =$B16+AW$4 -> 47113.583 | AZ16: ='Market pricing dates'!E5 -> 45770 | BA16: =AZ16 -> 45770 | BB16: =$AZ16+BB$4 -> 45800.417 | BC16: =$AZ16+BC$4 -> 45830.833 | BD16: =$AZ16+BD$4 -> 45861.25 | BE16: =$AZ16+BE$4 -> 45891.667 | BF16: =$AZ16+BF$4 -> 45922.083 | BG16: =$AZ16+BG$4 -> 45952.5 | BH16: =$AZ16+BH$4 -> 45982.917 | BI16: =$AZ16+BI$4 -> 46013.333 | ... CV16: =$AZ16+CV$4 -> 47199.583
A17: ='Market pricing dates'!B6 -> 45685 | B17: =A17 -> 45685 | C17: =$B17+C$4 -> 45715.417 | D17: =$B17+D$4 -> 45745.833 | E17: =$B17+E$4 -> 45776.25 | F17: =$B17+F$4 -> 45806.667 | G17: =$B17+G$4 -> 45837.083 | H17: =$B17+H$4 -> 45867.5 | I17: =$B17+I$4 -> 45897.917 | J17: =$B17+J$4 -> 45928.333 | ... AW17: =$B17+AW$4 -> 47114.583 | AZ17: ='Market pricing dates'!E6 -> 45771 | BA17: =AZ17 -> 45771 | BB17: =$AZ17+BB$4 -> 45801.417 | BC17: =$AZ17+BC$4 -> 45831.833 | BD17: =$AZ17+BD$4 -> 45862.25 | BE17: =$AZ17+BE$4 -> 45892.667 | BF17: =$AZ17+BF$4 -> 45923.083 | BG17: =$AZ17+BG$4 -> 45953.5 | BH17: =$AZ17+BH$4 -> 45983.917 | BI17: =$AZ17+BI$4 -> 46014.333 | ... CV17: =$AZ17+CV$4 -> 47200.583
A18: ='Market pricing dates'!B7 -> 45686 | B18: =A18 -> 45686 | C18: =$B18+C$4 -> 45716.417 | D18: =$B18+D$4 -> 45746.833 | E18: =$B18+E$4 -> 45777.25 | F18: =$B18+F$4 -> 45807.667 | G18: =$B18+G$4 -> 45838.083 | H18: =$B18+H$4 -> 45868.5 | I18: =$B18+I$4 -> 45898.917 | J18: =$B18+J$4 -> 45929.333 | ... AW18: =$B18+AW$4 -> 47115.583 | AZ18: ='Market pricing dates'!E7 -> 45772 | BA18: =AZ18 -> 45772 | BB18: =$AZ18+BB$4 -> 45802.417 | BC18: =$AZ18+BC$4 -> 45832.833 | BD18: =$AZ18+BD$4 -> 45863.25 | BE18: =$AZ18+BE$4 -> 45893.667 | BF18: =$AZ18+BF$4 -> 45924.083 | BG18: =$AZ18+BG$4 -> 45954.5 | BH18: =$AZ18+BH$4 -> 45984.917 | BI18: =$AZ18+BI$4 -> 46015.333 | ... CV18: =$AZ18+CV$4 -> 47201.583
A19: ='Market pricing dates'!B8 -> 45687 | B19: =A19 -> 45687 | C19: =$B19+C$4 -> 45717.417 | D19: =$B19+D$4 -> 45747.833 | E19: =$B19+E$4 -> 45778.25 | F19: =$B19+F$4 -> 45808.667 | G19: =$B19+G$4 -> 45839.083 | H19: =$B19+H$4 -> 45869.5 | I19: =$B19+I$4 -> 45899.917 | J19: =$B19+J$4 -> 45930.333 | ... AW19: =$B19+AW$4 -> 47116.583 | AZ19: ='Market pricing dates'!E8 -> 45775 | BA19: =AZ19 -> 45775 | BB19: =$AZ19+BB$4 -> 45805.417 | BC19: =$AZ19+BC$4 -> 45835.833 | BD19: =$AZ19+BD$4 -> 45866.25 | BE19: =$AZ19+BE$4 -> 45896.667 | BF19: =$AZ19+BF$4 -> 45927.083 | BG19: =$AZ19+BG$4 -> 45957.5 | BH19: =$AZ19+BH$4 -> 45987.917 | BI19: =$AZ19+BI$4 -> 46018.333 | ... CV19: =$AZ19+CV$4 -> 47204.583
A20: ='Market pricing dates'!B9 -> 45688 | B20: =A20 -> 45688 | C20: =$B20+C$4 -> 45718.417 | D20: =$B20+D$4 -> 45748.833 | E20: =$B20+E$4 -> 45779.25 | F20: =$B20+F$4 -> 45809.667 | G20: =$B20+G$4 -> 45840.083 | H20: =$B20+H$4 -> 45870.5 | I20: =$B20+I$4 -> 45900.917 | J20: =$B20+J$4 -> 45931.333 | ... AW20: =$B20+AW$4 -> 47117.583 | AZ20: ='Market pricing dates'!E9 -> 45776 | BA20: =AZ20 -> 45776 | BB20: =$AZ20+BB$4 -> 45806.417 | BC20: =$AZ20+BC$4 -> 45836.833 | BD20: =$AZ20+BD$4 -> 45867.25 | BE20: =$AZ20+BE$4 -> 45897.667 | BF20: =$AZ20+BF$4 -> 45928.083 | BG20: =$AZ20+BG$4 -> 45958.5 | BH20: =$AZ20+BH$4 -> 45988.917 | BI20: =$AZ20+BI$4 -> 46019.333 | ... CV20: =$AZ20+CV$4 -> 47205.583
A22: Gas futures | AZ22: Gas futures
A23: =A6 -> 45670 | B23: =VLOOKUP($A23,HAVERD!$A:$DP,B$2,FALSE) -> 121.5 | C23: =VLOOKUP($A23,HAVERD!$A:$DP,C$2,FALSE) -> 119.7 | D23: =VLOOKUP($A23,HAVERD!$A:$DP,D$2,FALSE) -> 119.48 | E23: =VLOOKUP($A23,HAVERD!$A:$DP,E$2,FALSE) -> 119.2 | F23: =VLOOKUP($A23,HAVERD!$A:$DP,F$2,FALSE) -> 118.97 | G23: =VLOOKUP($A23,HAVERD!$A:$DP,G$2,FALSE) -> 117.3 | H23: =VLOOKUP($A23,HAVERD!$A:$DP,H$2,FALSE) -> 117.7 | I23: =VLOOKUP($A23,HAVERD!$A:$DP,I$2,FALSE) -> 119.06 | ... AW23: =VLOOKUP($A23,HAVERD!$A:$DP,AW$2,FALSE) -> 79.09 | AZ23: =AZ6 -> 45756 | BA23: =_xlfn.IFNA(VLOOKUP($AZ23,HAVERD!$A:$DP,BA$2,FALSE),"") -> 83.21 | BB23: =_xlfn.IFNA(VLOOKUP($AZ23,HAVERD!$A:$DP,BB$2,FALSE),"") -> 83.74 | BC23: =_xlfn.IFNA(VLOOKUP($AZ23,HAVERD!$A:$DP,BC$2,FALSE),"") -> 83.37 | BD23: =_xlfn.IFNA(VLOOKUP($AZ23,HAVERD!$A:$DP,BD$2,FALSE),"") -> 84.36 | BE23: =_xlfn.IFNA(VLOOKUP($AZ23,HAVERD!$A:$DP,BE$2,FALSE),"") -> 86.41 | BF23: =_xlfn.IFNA(VLOOKUP($AZ23,HAVERD!$A:$DP,BF$2,FALSE),"") -> 86.3 | BG23: =_xlfn.IFNA(VLOOKUP($AZ23,HAVERD!$A:$DP,BG$2,FALSE),"") -> 92.5 | BH23: =_xlfn.IFNA(VLOOKUP($AZ23,HAVERD!$A:$DP,BH$2,FALSE),"") -> 93.95 | ... CV23: =_xlfn.IFNA(VLOOKUP($AZ23,HAVERD!$A:$DP,CV$2,FALSE),"") -> 69.97
A24: =A7 -> 45671 | B24: =VLOOKUP($A24,HAVERD!$A:$DP,B$2,FALSE) -> 118.62 | C24: =VLOOKUP($A24,HAVERD!$A:$DP,C$2,FALSE) -> 117.01 | D24: =VLOOKUP($A24,HAVERD!$A:$DP,D$2,FALSE) -> 116.69 | E24: =VLOOKUP($A24,HAVERD!$A:$DP,E$2,FALSE) -> 116.44 | F24: =VLOOKUP($A24,HAVERD!$A:$DP,F$2,FALSE) -> 115.98 | G24: =VLOOKUP($A24,HAVERD!$A:$DP,G$2,FALSE) -> 114.51 | H24: =VLOOKUP($A24,HAVERD!$A:$DP,H$2,FALSE) -> 114.95 | I24: =VLOOKUP($A24,HAVERD!$A:$DP,I$2,FALSE) -> 116.35 | ... AW24: =VLOOKUP($A24,HAVERD!$A:$DP,AW$2,FALSE) -> 78.65 | AZ24: =AZ7 -> 45757 | BA24: =_xlfn.IFNA(VLOOKUP($AZ24,HAVERD!$A:$DP,BA$2,FALSE),"") -> 82.18 | BB24: =_xlfn.IFNA(VLOOKUP($AZ24,HAVERD!$A:$DP,BB$2,FALSE),"") -> 82.62 | BC24: =_xlfn.IFNA(VLOOKUP($AZ24,HAVERD!$A:$DP,BC$2,FALSE),"") -> 82.26 | BD24: =_xlfn.IFNA(VLOOKUP($AZ24,HAVERD!$A:$DP,BD$2,FALSE),"") -> 83.26 | BE24: =_xlfn.IFNA(VLOOKUP($AZ24,HAVERD!$A:$DP,BE$2,FALSE),"") -> 85.18 | BF24: =_xlfn.IFNA(VLOOKUP($AZ24,HAVERD!$A:$DP,BF$2,FALSE),"") -> 84.98 | BG24: =_xlfn.IFNA(VLOOKUP($AZ24,HAVERD!$A:$DP,BG$2,FALSE),"") -> 91.66 | BH24: =_xlfn.IFNA(VLOOKUP($AZ24,HAVERD!$A:$DP,BH$2,FALSE),"") -> 93.16 | ... CV24: =_xlfn.IFNA(VLOOKUP($AZ24,HAVERD!$A:$DP,CV$2,FALSE),"") -> 70.16
A25: =A8 -> 45672 | B25: =VLOOKUP($A25,HAVERD!$A:$DP,B$2,FALSE) -> 118.45 | C25: =VLOOKUP($A25,HAVERD!$A:$DP,C$2,FALSE) -> 116.93 | D25: =VLOOKUP($A25,HAVERD!$A:$DP,D$2,FALSE) -> 116.39 | E25: =VLOOKUP($A25,HAVERD!$A:$DP,E$2,FALSE) -> 116.05 | F25: =VLOOKUP($A25,HAVERD!$A:$DP,F$2,FALSE) -> 115.64 | G25: =VLOOKUP($A25,HAVERD!$A:$DP,G$2,FALSE) -> 114.26 | H25: =VLOOKUP($A25,HAVERD!$A:$DP,H$2,FALSE) -> 114.74 | I25: =VLOOKUP($A25,HAVERD!$A:$DP,I$2,FALSE) -> 116.12 | ... AW25: =VLOOKUP($A25,HAVERD!$A:$DP,AW$2,FALSE) -> 78.62 | AZ25: =AZ8 -> 45758 | BA25: =_xlfn.IFNA(VLOOKUP($AZ25,HAVERD!$A:$DP,BA$2,FALSE),"") -> 83.1 | BB25: =_xlfn.IFNA(VLOOKUP($AZ25,HAVERD!$A:$DP,BB$2,FALSE),"") -> 83.37 | BC25: =_xlfn.IFNA(VLOOKUP($AZ25,HAVERD!$A:$DP,BC$2,FALSE),"") -> 83.05 | BD25: =_xlfn.IFNA(VLOOKUP($AZ25,HAVERD!$A:$DP,BD$2,FALSE),"") -> 84.3 | BE25: =_xlfn.IFNA(VLOOKUP($AZ25,HAVERD!$A:$DP,BE$2,FALSE),"") -> 86.3 | BF25: =_xlfn.IFNA(VLOOKUP($AZ25,HAVERD!$A:$DP,BF$2,FALSE),"") -> 86.1 | BG25: =_xlfn.IFNA(VLOOKUP($AZ25,HAVERD!$A:$DP,BG$2,FALSE),"") -> 92.81 | BH25: =_xlfn.IFNA(VLOOKUP($AZ25,HAVERD!$A:$DP,BH$2,FALSE),"") -> 94.18 | ... CV25: =_xlfn.IFNA(VLOOKUP($AZ25,HAVERD!$A:$DP,CV$2,FALSE),"") -> 68.83
A26: =A9 -> 45673 | B26: =VLOOKUP($A26,HAVERD!$A:$DP,B$2,FALSE) -> 116.39 | C26: =VLOOKUP($A26,HAVERD!$A:$DP,C$2,FALSE) -> 115.25 | D26: =VLOOKUP($A26,HAVERD!$A:$DP,D$2,FALSE) -> 114.8 | E26: =VLOOKUP($A26,HAVERD!$A:$DP,E$2,FALSE) -> 114.45 | F26: =VLOOKUP($A26,HAVERD!$A:$DP,F$2,FALSE) -> 114.2 | G26: =VLOOKUP($A26,HAVERD!$A:$DP,G$2,FALSE) -> 112.9 | H26: =VLOOKUP($A26,HAVERD!$A:$DP,H$2,FALSE) -> 113.46 | I26: =VLOOKUP($A26,HAVERD!$A:$DP,I$2,FALSE) -> 115 | ... AW26: =VLOOKUP($A26,HAVERD!$A:$DP,AW$2,FALSE) -> 78.19 | AZ26: =AZ9 -> 45761 | BA26: =_xlfn.IFNA(VLOOKUP($AZ26,HAVERD!$A:$DP,BA$2,FALSE),"") -> 85.37 | BB26: =_xlfn.IFNA(VLOOKUP($AZ26,HAVERD!$A:$DP,BB$2,FALSE),"") -> 85.37 | BC26: =_xlfn.IFNA(VLOOKUP($AZ26,HAVERD!$A:$DP,BC$2,FALSE),"") -> 84.99 | BD26: =_xlfn.IFNA(VLOOKUP($AZ26,HAVERD!$A:$DP,BD$2,FALSE),"") -> 86.2 | BE26: =_xlfn.IFNA(VLOOKUP($AZ26,HAVERD!$A:$DP,BE$2,FALSE),"") -> 88.2 | BF26: =_xlfn.IFNA(VLOOKUP($AZ26,HAVERD!$A:$DP,BF$2,FALSE),"") -> 87.92 | BG26: =_xlfn.IFNA(VLOOKUP($AZ26,HAVERD!$A:$DP,BG$2,FALSE),"") -> 94.42 | BH26: =_xlfn.IFNA(VLOOKUP($AZ26,HAVERD!$A:$DP,BH$2,FALSE),"") -> 95.97 | ... CV26: =_xlfn.IFNA(VLOOKUP($AZ26,HAVERD!$A:$DP,CV$2,FALSE),"") -> 68.23
A27: =A10 -> 45674 | B27: =VLOOKUP($A27,HAVERD!$A:$DP,B$2,FALSE) -> 118.31 | C27: =VLOOKUP($A27,HAVERD!$A:$DP,C$2,FALSE) -> 117.13 | D27: =VLOOKUP($A27,HAVERD!$A:$DP,D$2,FALSE) -> 116.59 | E27: =VLOOKUP($A27,HAVERD!$A:$DP,E$2,FALSE) -> 116.3 | F27: =VLOOKUP($A27,HAVERD!$A:$DP,F$2,FALSE) -> 115.99 | G27: =VLOOKUP($A27,HAVERD!$A:$DP,G$2,FALSE) -> 114.74 | H27: =VLOOKUP($A27,HAVERD!$A:$DP,H$2,FALSE) -> 115.44 | I27: =VLOOKUP($A27,HAVERD!$A:$DP,I$2,FALSE) -> 116.81 | ... AW27: =VLOOKUP($A27,HAVERD!$A:$DP,AW$2,FALSE) -> 78.92 | AZ27: =AZ10 -> 45762 | BA27: =_xlfn.IFNA(VLOOKUP($AZ27,HAVERD!$A:$DP,BA$2,FALSE),"") -> 84.32 | BB27: =_xlfn.IFNA(VLOOKUP($AZ27,HAVERD!$A:$DP,BB$2,FALSE),"") -> 84.3 | BC27: =_xlfn.IFNA(VLOOKUP($AZ27,HAVERD!$A:$DP,BC$2,FALSE),"") -> 83.99 | BD27: =_xlfn.IFNA(VLOOKUP($AZ27,HAVERD!$A:$DP,BD$2,FALSE),"") -> 85.32 | BE27: =_xlfn.IFNA(VLOOKUP($AZ27,HAVERD!$A:$DP,BE$2,FALSE),"") -> 87.31 | BF27: =_xlfn.IFNA(VLOOKUP($AZ27,HAVERD!$A:$DP,BF$2,FALSE),"") -> 87.23 | BG27: =_xlfn.IFNA(VLOOKUP($AZ27,HAVERD!$A:$DP,BG$2,FALSE),"") -> 93.91 | BH27: =_xlfn.IFNA(VLOOKUP($AZ27,HAVERD!$A:$DP,BH$2,FALSE),"") -> 95.52 | ... CV27: =_xlfn.IFNA(VLOOKUP($AZ27,HAVERD!$A:$DP,CV$2,FALSE),"") -> 68.38
A28: =A11 -> 45677 | B28: =VLOOKUP($A28,HAVERD!$A:$DP,B$2,FALSE) -> 121.35 | C28: =VLOOKUP($A28,HAVERD!$A:$DP,C$2,FALSE) -> 119.75 | D28: =VLOOKUP($A28,HAVERD!$A:$DP,D$2,FALSE) -> 118.85 | E28: =VLOOKUP($A28,HAVERD!$A:$DP,E$2,FALSE) -> 118.35 | F28: =VLOOKUP($A28,HAVERD!$A:$DP,F$2,FALSE) -> 118 | G28: =VLOOKUP($A28,HAVERD!$A:$DP,G$2,FALSE) -> 116.68 | H28: =VLOOKUP($A28,HAVERD!$A:$DP,H$2,FALSE) -> 117.38 | I28: =VLOOKUP($A28,HAVERD!$A:$DP,I$2,FALSE) -> 118.79 | ... AW28: =VLOOKUP($A28,HAVERD!$A:$DP,AW$2,FALSE) -> 79.16 | AZ28: =AZ11 -> 45763 | BA28: =_xlfn.IFNA(VLOOKUP($AZ28,HAVERD!$A:$DP,BA$2,FALSE),"") -> 86.88 | BB28: =_xlfn.IFNA(VLOOKUP($AZ28,HAVERD!$A:$DP,BB$2,FALSE),"") -> 86.8 | BC28: =_xlfn.IFNA(VLOOKUP($AZ28,HAVERD!$A:$DP,BC$2,FALSE),"") -> 86.39 | BD28: =_xlfn.IFNA(VLOOKUP($AZ28,HAVERD!$A:$DP,BD$2,FALSE),"") -> 87.51 | BE28: =_xlfn.IFNA(VLOOKUP($AZ28,HAVERD!$A:$DP,BE$2,FALSE),"") -> 89.36 | BF28: =_xlfn.IFNA(VLOOKUP($AZ28,HAVERD!$A:$DP,BF$2,FALSE),"") -> 89.36 | BG28: =_xlfn.IFNA(VLOOKUP($AZ28,HAVERD!$A:$DP,BG$2,FALSE),"") -> 95.9 | BH28: =_xlfn.IFNA(VLOOKUP($AZ28,HAVERD!$A:$DP,BH$2,FALSE),"") -> 97.52 | ... CV28: =_xlfn.IFNA(VLOOKUP($AZ28,HAVERD!$A:$DP,CV$2,FALSE),"") -> 68.58
A29: =A12 -> 45678 | B29: =VLOOKUP($A29,HAVERD!$A:$DP,B$2,FALSE) -> 126.61 | C29: =VLOOKUP($A29,HAVERD!$A:$DP,C$2,FALSE) -> 125.1 | D29: =VLOOKUP($A29,HAVERD!$A:$DP,D$2,FALSE) -> 124.1 | E29: =VLOOKUP($A29,HAVERD!$A:$DP,E$2,FALSE) -> 123.45 | F29: =VLOOKUP($A29,HAVERD!$A:$DP,F$2,FALSE) -> 122.88 | G29: =VLOOKUP($A29,HAVERD!$A:$DP,G$2,FALSE) -> 121.45 | H29: =VLOOKUP($A29,HAVERD!$A:$DP,H$2,FALSE) -> 121.75 | I29: =VLOOKUP($A29,HAVERD!$A:$DP,I$2,FALSE) -> 123.13 | ... AW29: =VLOOKUP($A29,HAVERD!$A:$DP,AW$2,FALSE) -> 79.32 | AZ29: =AZ12 -> 45764 | BA29: =_xlfn.IFNA(VLOOKUP($AZ29,HAVERD!$A:$DP,BA$2,FALSE),"") -> 87.27 | BB29: =_xlfn.IFNA(VLOOKUP($AZ29,HAVERD!$A:$DP,BB$2,FALSE),"") -> 87.24 | BC29: =_xlfn.IFNA(VLOOKUP($AZ29,HAVERD!$A:$DP,BC$2,FALSE),"") -> 86.87 | BD29: =_xlfn.IFNA(VLOOKUP($AZ29,HAVERD!$A:$DP,BD$2,FALSE),"") -> 88.14 | BE29: =_xlfn.IFNA(VLOOKUP($AZ29,HAVERD!$A:$DP,BE$2,FALSE),"") -> 90.25 | BF29: =_xlfn.IFNA(VLOOKUP($AZ29,HAVERD!$A:$DP,BF$2,FALSE),"") -> 90.25 | BG29: =_xlfn.IFNA(VLOOKUP($AZ29,HAVERD!$A:$DP,BG$2,FALSE),"") -> 96.73 | BH29: =_xlfn.IFNA(VLOOKUP($AZ29,HAVERD!$A:$DP,BH$2,FALSE),"") -> 98.39 | ... CV29: =_xlfn.IFNA(VLOOKUP($AZ29,HAVERD!$A:$DP,CV$2,FALSE),"") -> 68.95
A30: =A13 -> 45679 | B30: =VLOOKUP($A30,HAVERD!$A:$DP,B$2,FALSE) -> 122.87 | C30: =VLOOKUP($A30,HAVERD!$A:$DP,C$2,FALSE) -> 121.79 | D30: =VLOOKUP($A30,HAVERD!$A:$DP,D$2,FALSE) -> 120.85 | E30: =VLOOKUP($A30,HAVERD!$A:$DP,E$2,FALSE) -> 120.4 | F30: =VLOOKUP($A30,HAVERD!$A:$DP,F$2,FALSE) -> 119.99 | G30: =VLOOKUP($A30,HAVERD!$A:$DP,G$2,FALSE) -> 118.35 | H30: =VLOOKUP($A30,HAVERD!$A:$DP,H$2,FALSE) -> 118.66 | I30: =VLOOKUP($A30,HAVERD!$A:$DP,I$2,FALSE) -> 119.96 | ... AW30: =VLOOKUP($A30,HAVERD!$A:$DP,AW$2,FALSE) -> 77.55 | AZ30: =AZ13 -> 45765 | BA30: =_xlfn.IFNA(VLOOKUP($AZ30,HAVERD!$A:$DP,BA$2,FALSE),"") | BB30: =_xlfn.IFNA(VLOOKUP($AZ30,HAVERD!$A:$DP,BB$2,FALSE),"") | BC30: =_xlfn.IFNA(VLOOKUP($AZ30,HAVERD!$A:$DP,BC$2,FALSE),"") | BD30: =_xlfn.IFNA(VLOOKUP($AZ30,HAVERD!$A:$DP,BD$2,FALSE),"") | BE30: =_xlfn.IFNA(VLOOKUP($AZ30,HAVERD!$A:$DP,BE$2,FALSE),"") | BF30: =_xlfn.IFNA(VLOOKUP($AZ30,HAVERD!$A:$DP,BF$2,FALSE),"") | BG30: =_xlfn.IFNA(VLOOKUP($AZ30,HAVERD!$A:$DP,BG$2,FALSE),"") | BH30: =_xlfn.IFNA(VLOOKUP($AZ30,HAVERD!$A:$DP,BH$2,FALSE),"") | ... CV30: =_xlfn.IFNA(VLOOKUP($AZ30,HAVERD!$A:$DP,CV$2,FALSE),"")
A31: =A14 -> 45680 | B31: =VLOOKUP($A31,HAVERD!$A:$DP,B$2,FALSE) -> 123.5 | C31: =VLOOKUP($A31,HAVERD!$A:$DP,C$2,FALSE) -> 122.24 | D31: =VLOOKUP($A31,HAVERD!$A:$DP,D$2,FALSE) -> 121.52 | E31: =VLOOKUP($A31,HAVERD!$A:$DP,E$2,FALSE) -> 121.4 | F31: =VLOOKUP($A31,HAVERD!$A:$DP,F$2,FALSE) -> 120.97 | G31: =VLOOKUP($A31,HAVERD!$A:$DP,G$2,FALSE) -> 119.9 | H31: =VLOOKUP($A31,HAVERD!$A:$DP,H$2,FALSE) -> 120.22 | I31: =VLOOKUP($A31,HAVERD!$A:$DP,I$2,FALSE) -> 121.41 | ... AW31: =VLOOKUP($A31,HAVERD!$A:$DP,AW$2,FALSE) -> 77.81 | AZ31: =AZ14 -> 45768 | BA31: =_xlfn.IFNA(VLOOKUP($AZ31,HAVERD!$A:$DP,BA$2,FALSE),"") -> 87.27 | BB31: =_xlfn.IFNA(VLOOKUP($AZ31,HAVERD!$A:$DP,BB$2,FALSE),"") -> 87.24 | BC31: =_xlfn.IFNA(VLOOKUP($AZ31,HAVERD!$A:$DP,BC$2,FALSE),"") -> 86.87 | BD31: =_xlfn.IFNA(VLOOKUP($AZ31,HAVERD!$A:$DP,BD$2,FALSE),"") -> 88.14 | BE31: =_xlfn.IFNA(VLOOKUP($AZ31,HAVERD!$A:$DP,BE$2,FALSE),"") -> 90.25 | BF31: =_xlfn.IFNA(VLOOKUP($AZ31,HAVERD!$A:$DP,BF$2,FALSE),"") -> 90.25 | BG31: =_xlfn.IFNA(VLOOKUP($AZ31,HAVERD!$A:$DP,BG$2,FALSE),"") -> 96.73 | BH31: =_xlfn.IFNA(VLOOKUP($AZ31,HAVERD!$A:$DP,BH$2,FALSE),"") -> 98.39 | ... CV31: =_xlfn.IFNA(VLOOKUP($AZ31,HAVERD!$A:$DP,CV$2,FALSE),"") -> 68.95
A32: =A15 -> 45681 | B32: =VLOOKUP($A32,HAVERD!$A:$DP,B$2,FALSE) -> 124.73 | C32: =VLOOKUP($A32,HAVERD!$A:$DP,C$2,FALSE) -> 123.12 | D32: =VLOOKUP($A32,HAVERD!$A:$DP,D$2,FALSE) -> 122.44 | E32: =VLOOKUP($A32,HAVERD!$A:$DP,E$2,FALSE) -> 122.11 | F32: =VLOOKUP($A32,HAVERD!$A:$DP,F$2,FALSE) -> 121.78 | G32: =VLOOKUP($A32,HAVERD!$A:$DP,G$2,FALSE) -> 120.81 | H32: =VLOOKUP($A32,HAVERD!$A:$DP,H$2,FALSE) -> 121.09 | I32: =VLOOKUP($A32,HAVERD!$A:$DP,I$2,FALSE) -> 122.39 | ... AW32: =VLOOKUP($A32,HAVERD!$A:$DP,AW$2,FALSE) -> 77.61 | AZ32: =AZ15 -> 45769 | BA32: =_xlfn.IFNA(VLOOKUP($AZ32,HAVERD!$A:$DP,BA$2,FALSE),"") -> 83.99 | BB32: =_xlfn.IFNA(VLOOKUP($AZ32,HAVERD!$A:$DP,BB$2,FALSE),"") -> 84 | BC32: =_xlfn.IFNA(VLOOKUP($AZ32,HAVERD!$A:$DP,BC$2,FALSE),"") -> 83.58 | BD32: =_xlfn.IFNA(VLOOKUP($AZ32,HAVERD!$A:$DP,BD$2,FALSE),"") -> 84.69 | BE32: =_xlfn.IFNA(VLOOKUP($AZ32,HAVERD!$A:$DP,BE$2,FALSE),"") -> 86.48 | BF32: =_xlfn.IFNA(VLOOKUP($AZ32,HAVERD!$A:$DP,BF$2,FALSE),"") -> 86.52 | BG32: =_xlfn.IFNA(VLOOKUP($AZ32,HAVERD!$A:$DP,BG$2,FALSE),"") -> 92.92 | BH32: =_xlfn.IFNA(VLOOKUP($AZ32,HAVERD!$A:$DP,BH$2,FALSE),"") -> 94.36 | ... CV32: =_xlfn.IFNA(VLOOKUP($AZ32,HAVERD!$A:$DP,CV$2,FALSE),"") -> 68.83
A33: =A16 -> 45684 | B33: =VLOOKUP($A33,HAVERD!$A:$DP,B$2,FALSE) -> 120.15 | C33: =VLOOKUP($A33,HAVERD!$A:$DP,C$2,FALSE) -> 118.58 | D33: =VLOOKUP($A33,HAVERD!$A:$DP,D$2,FALSE) -> 118.24 | E33: =VLOOKUP($A33,HAVERD!$A:$DP,E$2,FALSE) -> 118.05 | F33: =VLOOKUP($A33,HAVERD!$A:$DP,F$2,FALSE) -> 117.97 | G33: =VLOOKUP($A33,HAVERD!$A:$DP,G$2,FALSE) -> 117.12 | H33: =VLOOKUP($A33,HAVERD!$A:$DP,H$2,FALSE) -> 117.42 | I33: =VLOOKUP($A33,HAVERD!$A:$DP,I$2,FALSE) -> 118.42 | ... AW33: =VLOOKUP($A33,HAVERD!$A:$DP,AW$2,FALSE) -> 76.77 | AZ33: =AZ16 -> 45770 | BA33: =_xlfn.IFNA(VLOOKUP($AZ33,HAVERD!$A:$DP,BA$2,FALSE),"") -> 83.61 | BB33: =_xlfn.IFNA(VLOOKUP($AZ33,HAVERD!$A:$DP,BB$2,FALSE),"") -> 83.76 | BC33: =_xlfn.IFNA(VLOOKUP($AZ33,HAVERD!$A:$DP,BC$2,FALSE),"") -> 83.02 | BD33: =_xlfn.IFNA(VLOOKUP($AZ33,HAVERD!$A:$DP,BD$2,FALSE),"") -> 83.98 | BE33: =_xlfn.IFNA(VLOOKUP($AZ33,HAVERD!$A:$DP,BE$2,FALSE),"") -> 85.95 | BF33: =_xlfn.IFNA(VLOOKUP($AZ33,HAVERD!$A:$DP,BF$2,FALSE),"") -> 85.94 | BG33: =_xlfn.IFNA(VLOOKUP($AZ33,HAVERD!$A:$DP,BG$2,FALSE),"") -> 92.34 | BH33: =_xlfn.IFNA(VLOOKUP($AZ33,HAVERD!$A:$DP,BH$2,FALSE),"") -> 94.2 | ... CV33: =_xlfn.IFNA(VLOOKUP($AZ33,HAVERD!$A:$DP,CV$2,FALSE),"") -> 68.58
A34: =A17 -> 45685 | B34: =VLOOKUP($A34,HAVERD!$A:$DP,B$2,FALSE) -> 121.2 | C34: =VLOOKUP($A34,HAVERD!$A:$DP,C$2,FALSE) -> 118.7 | D34: =VLOOKUP($A34,HAVERD!$A:$DP,D$2,FALSE) -> 118.25 | E34: =VLOOKUP($A34,HAVERD!$A:$DP,E$2,FALSE) -> 117.9 | F34: =VLOOKUP($A34,HAVERD!$A:$DP,F$2,FALSE) -> 117.92 | G34: =VLOOKUP($A34,HAVERD!$A:$DP,G$2,FALSE) -> 116.79 | H34: =VLOOKUP($A34,HAVERD!$A:$DP,H$2,FALSE) -> 117.23 | I34: =VLOOKUP($A34,HAVERD!$A:$DP,I$2,FALSE) -> 118.58 | ... AW34: =VLOOKUP($A34,HAVERD!$A:$DP,AW$2,FALSE) -> 76.08 | AZ34: =AZ17 -> 45771 | BA34: =_xlfn.IFNA(VLOOKUP($AZ34,HAVERD!$A:$DP,BA$2,FALSE),"") -> 81.25 | BB34: =_xlfn.IFNA(VLOOKUP($AZ34,HAVERD!$A:$DP,BB$2,FALSE),"") -> 81.69 | BC34: =_xlfn.IFNA(VLOOKUP($AZ34,HAVERD!$A:$DP,BC$2,FALSE),"") -> 80.83 | BD34: =_xlfn.IFNA(VLOOKUP($AZ34,HAVERD!$A:$DP,BD$2,FALSE),"") -> 82.02 | BE34: =_xlfn.IFNA(VLOOKUP($AZ34,HAVERD!$A:$DP,BE$2,FALSE),"") -> 83.93 | BF34: =_xlfn.IFNA(VLOOKUP($AZ34,HAVERD!$A:$DP,BF$2,FALSE),"") -> 84.15 | BG34: =_xlfn.IFNA(VLOOKUP($AZ34,HAVERD!$A:$DP,BG$2,FALSE),"") -> 91.1 | BH34: =_xlfn.IFNA(VLOOKUP($AZ34,HAVERD!$A:$DP,BH$2,FALSE),"") -> 92.84 | ... CV34: =_xlfn.IFNA(VLOOKUP($AZ34,HAVERD!$A:$DP,CV$2,FALSE),"") -> 68.34
... A37: =A20 -> 45688 | B37: =VLOOKUP($A37,HAVERD!$A:$DP,B$2,FALSE) -> 130.54 | C37: =VLOOKUP($A37,HAVERD!$A:$DP,C$2,FALSE) -> 128.91 | D37: =VLOOKUP($A37,HAVERD!$A:$DP,D$2,FALSE) -> 128.29 | E37: =VLOOKUP($A37,HAVERD!$A:$DP,E$2,FALSE) -> 128.28 | F37: =VLOOKUP($A37,HAVERD!$A:$DP,F$2,FALSE) -> 126.79 | G37: =VLOOKUP($A37,HAVERD!$A:$DP,G$2,FALSE) -> 127.14 | H37: =VLOOKUP($A37,HAVERD!$A:$DP,H$2,FALSE) -> 128.54 | I37: =VLOOKUP($A37,HAVERD!$A:$DP,I$2,FALSE) -> 123.62 | ... AW37: =VLOOKUP($A37,HAVERD!$A:$DP,AW$2,FALSE) -> 76.16 | AZ37: =AZ20 -> 45776 | BA37: =_xlfn.IFNA(VLOOKUP($AZ37,HAVERD!$A:$DP,BA$2,FALSE),"") -> 76.67 | BB37: =_xlfn.IFNA(VLOOKUP($AZ37,HAVERD!$A:$DP,BB$2,FALSE),"") -> 77.11 | BC37: =_xlfn.IFNA(VLOOKUP($AZ37,HAVERD!$A:$DP,BC$2,FALSE),"") -> 76.12 | BD37: =_xlfn.IFNA(VLOOKUP($AZ37,HAVERD!$A:$DP,BD$2,FALSE),"") -> 77.25 | BE37: =_xlfn.IFNA(VLOOKUP($AZ37,HAVERD!$A:$DP,BE$2,FALSE),"") -> 79.64 | BF37: =_xlfn.IFNA(VLOOKUP($AZ37,HAVERD!$A:$DP,BF$2,FALSE),"") -> 79.81 | BG37: =_xlfn.IFNA(VLOOKUP($AZ37,HAVERD!$A:$DP,BG$2,FALSE),"") -> 86.44 | BH37: =_xlfn.IFNA(VLOOKUP($AZ37,HAVERD!$A:$DP,BH$2,FALSE),"") -> 88.14 | ... CV37: =_xlfn.IFNA(VLOOKUP($AZ37,HAVERD!$A:$DP,CV$2,FALSE),"") -> 67.93
A39: Average | AZ39: Average
A40: Month | B40: =MONTH(B20) -> 1 | C40: =MONTH(C20) -> 3 | D40: =MONTH(D20) -> 4 | E40: =MONTH(E20) -> 5 | F40: =MONTH(F20) -> 6 | G40: =MONTH(G20) -> 7 | H40: =MONTH(H20) -> 8 | I40: =MONTH(I20) -> 8 | ... AW40: =MONTH(AW20) -> 12 | AZ40: Month | BA40: =MONTH(BA18) -> 4 | BB40: =MONTH(BB18) -> 5 | BC40: =MONTH(BC18) -> 6 | BD40: =MONTH(BD18) -> 7 | BE40: =MONTH(BE18) -> 8 | BF40: =MONTH(BF18) -> 9 | BG40: =MONTH(BG18) -> 10 | BH40: =MONTH(BH18) -> 11 | ... CV40: =MONTH(CV18) -> 3
A41: Year | B41: =YEAR(B20) -> 2025 | C41: =YEAR(C20) -> 2025 | D41: =YEAR(D20) -> 2025 | E41: =YEAR(E20) -> 2025 | F41: =YEAR(F20) -> 2025 | G41: =YEAR(G20) -> 2025 | H41: =YEAR(H20) -> 2025 | I41: =YEAR(I20) -> 2025 | ... AW41: =YEAR(AW20) -> 2028 | AZ41: Year | BA41: =YEAR(BA20) -> 2025 | BB41: =YEAR(BB20) -> 2025 | BC41: =YEAR(BC20) -> 2025 | BD41: =YEAR(BD20) -> 2025 | BE41: =YEAR(BE20) -> 2025 | BF41: =YEAR(BF20) -> 2025 | BG41: =YEAR(BG20) -> 2025 | BH41: =YEAR(BH20) -> 2025 | ... CV41: =YEAR(CV20) -> 2029
A42: YYYYMM | B42: =B41*100+B40 -> 202501 | C42: =C41*100+C40 -> 202503 | D42: =D41*100+D40 -> 202504 | E42: =E41*100+E40 -> 202505 | F42: =F41*100+F40 -> 202506 | G42: =G41*100+G40 -> 202507 | H42: =H41*100+H40 -> 202508 | I42: =I41*100+I40 -> 202508 | ... AW42: =AW41*100+AW40 -> 202812 | AZ42: YYYYMM | BA42: =BA41*100+BA40 -> 202504 | BB42: =BB41*100+BB40 -> 202505 | BC42: =BC41*100+BC40 -> 202506 | BD42: =BD41*100+BD40 -> 202507 | BE42: =BE41*100+BE40 -> 202508 | BF42: =BF41*100+BF40 -> 202509 | BG42: =BG41*100+BG40 -> 202510 | BH42: =BH41*100+BH40 -> 202511 | ... CV42: =CV41*100+CV40 -> 202903
A43: Quarter | B43: =IF(B40<4,1,IF(B40<7,2,IF(B40<10,3,4))) -> 1 | C43: =IF(C40<4,1,IF(C40<7,2,IF(C40<10,3,4))) -> 1 | D43: =IF(D40<4,1,IF(D40<7,2,IF(D40<10,3,4))) -> 2 | E43: =IF(E40<4,1,IF(E40<7,2,IF(E40<10,3,4))) -> 2 | F43: =IF(F40<4,1,IF(F40<7,2,IF(F40<10,3,4))) -> 2 | G43: =IF(G40<4,1,IF(G40<7,2,IF(G40<10,3,4))) -> 3 | H43: =IF(H40<4,1,IF(H40<7,2,IF(H40<10,3,4))) -> 3 | I43: =IF(I40<4,1,IF(I40<7,2,IF(I40<10,3,4))) -> 3 | ... AW43: =IF(AW40<4,1,IF(AW40<7,2,IF(AW40<10,3,4))) -> 4 | AZ43: Quarter | BA43: =IF(BA40<4,1,IF(BA40<7,2,IF(BA40<10,3,4))) -> 2 | BB43: =IF(BB40<4,1,IF(BB40<7,2,IF(BB40<10,3,4))) -> 2 | BC43: =IF(BC40<4,1,IF(BC40<7,2,IF(BC40<10,3,4))) -> 2 | BD43: =IF(BD40<4,1,IF(BD40<7,2,IF(BD40<10,3,4))) -> 3 | BE43: =IF(BE40<4,1,IF(BE40<7,2,IF(BE40<10,3,4))) -> 3 | BF43: =IF(BF40<4,1,IF(BF40<7,2,IF(BF40<10,3,4))) -> 3 | BG43: =IF(BG40<4,1,IF(BG40<7,2,IF(BG40<10,3,4))) -> 4 | BH43: =IF(BH40<4,1,IF(BH40<7,2,IF(BH40<10,3,4))) -> 4 | ... CV43: =IF(CV40<4,1,IF(CV40<7,2,IF(CV40<10,3,4))) -> 1
A44: YYYYQQ | B44: =B41*100+B43 -> 202501 | C44: =C41*100+C43 -> 202501 | D44: =D41*100+D43 -> 202502 | E44: =E41*100+E43 -> 202502 | F44: =F41*100+F43 -> 202502 | G44: =G41*100+G43 -> 202503 | H44: =H41*100+H43 -> 202503 | I44: =I41*100+I43 -> 202503 | ... AW44: =AW41*100+AW43 -> 202804 | AZ44: YYYYQQ | BA44: =BA41*100+BA43 -> 202502 | BB44: =BB41*100+BB43 -> 202502 | BC44: =BC41*100+BC43 -> 202502 | BD44: =BD41*100+BD43 -> 202503 | BE44: =BE41*100+BE43 -> 202503 | BF44: =BF41*100+BF43 -> 202503 | BG44: =BG41*100+BG43 -> 202504 | BH44: =BH41*100+BH43 -> 202504 | ... CV44: =CV41*100+CV43 -> 202901
A45: Average | B45: =AVERAGE(B23:B37) -> 122.81333 | C45: =AVERAGE(C23:C37) -> 121.08933 | D45: =AVERAGE(D23:D37) -> 120.40267 | E45: =AVERAGE(E23:E37) -> 120.06733 | F45: =AVERAGE(F23:F37) -> 119.73133 | G45: =AVERAGE(G23:G37) -> 118.54333 | H45: =AVERAGE(H23:H37) -> 119.02533 | I45: =AVERAGE(I23:I37) -> 119.948 | ... AW45: =AVERAGE(AW23:AW37) -> 77.906 | AZ45: Average | BA45: =AVERAGE(BA23:BA37) -> 82.997143 | BB45: =AVERAGE(BB23:BB37) -> 83.213571 | BC45: =AVERAGE(BC23:BC37) -> 82.666429 | BD45: =AVERAGE(BD23:BD37) -> 83.804286 | BE45: =AVERAGE(BE23:BE37) -> 85.810714 | BF45: =AVERAGE(BF23:BF37) -> 85.808571 | BG45: =AVERAGE(BG23:BG37) -> 92.352857 | BH45: =AVERAGE(BH23:BH37) -> 93.985 | ... CV45: =AVERAGE(CV23:CV37) -> 68.700714
A47: Quarterly series | AZ47: Quarterly series
B48: =B44 -> 202501 | C48: =IF(RIGHT(B48)="4",B48+97,B48+1) -> 202502 | D48: =IF(RIGHT(C48)="4",C48+97,C48+1) -> 202503 | E48: =IF(RIGHT(D48)="4",D48+97,D48+1) -> 202504 | F48: =IF(RIGHT(E48)="4",E48+97,E48+1) -> 202601 | G48: =IF(RIGHT(F48)="4",F48+97,F48+1) -> 202602 | H48: =IF(RIGHT(G48)="4",G48+97,G48+1) -> 202603 | I48: =IF(RIGHT(H48)="4",H48+97,H48+1) -> 202604 | J48: =IF(RIGHT(I48)="4",I48+97,I48+1) -> 202701 | ... R48: =IF(RIGHT(Q48)="4",Q48+97,Q48+1) -> 202901 | BA48: =BA44 -> 202502 | BB48: =IF(RIGHT(BA48)="4",BA48+97,BA48+1) -> 202503 | BC48: =IF(RIGHT(BB48)="4",BB48+97,BB48+1) -> 202504 | BD48: =IF(RIGHT(BC48)="4",BC48+97,BC48+1) -> 202601 | BE48: =IF(RIGHT(BD48)="4",BD48+97,BD48+1) -> 202602 | BF48: =IF(RIGHT(BE48)="4",BE48+97,BE48+1) -> 202603 | BG48: =IF(RIGHT(BF48)="4",BF48+97,BF48+1) -> 202604 | BH48: =IF(RIGHT(BG48)="4",BG48+97,BG48+1) -> 202701 | BI48: =IF(RIGHT(BH48)="4",BH48+97,BH48+1) -> 202702 | ... BP48: =IF(RIGHT(BO48)="4",BO48+97,BO48+1) -> 202901
A49: =A1 -> February 2025 MPR | B49: =AVERAGEIF($B$44:$AW$44,B48,$B$45:$AW$45) -> 121.95133 | C49: =AVERAGEIF($B$44:$AW$44,C48,$B$45:$AW$45) -> 120.06711 | D49: =AVERAGEIF($B$44:$AW$44,D48,$B$45:$AW$45) -> 119.17222 | E49: =AVERAGEIF($B$44:$AW$44,E48,$B$45:$AW$45) -> 116.63567 | F49: =AVERAGEIF($B$44:$AW$44,F48,$B$45:$AW$45) -> 113.56567 | G49: =AVERAGEIF($B$44:$AW$44,G48,$B$45:$AW$45) -> 96.710444 | H49: =AVERAGEIF($B$44:$AW$44,H48,$B$45:$AW$45) -> 94.540667 | I49: =AVERAGEIF($B$44:$AW$44,I48,$B$45:$AW$45) -> 97.897 | ... R49: =AVERAGEIF($B$44:$AW$44,R48,$B$45:$AW$45) -> #DIV/0! | AZ49: =AZ1 -> May 2025 MPR | BA49: =AVERAGEIF($BA$44:$CV$44,BA48,$BA$45:$CV$45) -> 82.959048 | BB49: =AVERAGEIF($BA$44:$CV$44,BB48,$BA$45:$CV$45) -> 85.14119 | BC49: =AVERAGEIF($BA$44:$CV$44,BC48,$BA$45:$CV$45) -> 93.626667 | BD49: =AVERAGEIF($BA$44:$CV$44,BD48,$BA$45:$CV$45) -> 89.813095 | BE49: =AVERAGEIF($BA$44:$CV$44,BE48,$BA$45:$CV$45) -> 78.033571 | BF49: =AVERAGEIF($BA$44:$CV$44,BF48,$BA$45:$CV$45) -> 79.332143 | BG49: =AVERAGEIF($BA$44:$CV$44,BG48,$BA$45:$CV$45) -> 86.203571 | BH49: =AVERAGEIF($BA$44:$CV$44,BH48,$BA$45:$CV$45) -> 81.069286 | ... BP49: =AVERAGEIF($BA$44:$CV$44,BP48,$BA$45:$CV$45) -> 71.446429
AZ51: Comparison - monthly
BA52: 44927 | BB52: 44958 | BC52: 44986 | BD52: 45017 | BE52: 45047 | BF52: 45078 | BG52: 45108 | BH52: 45139 | BI52: 45170 | BJ52: 45200 | BK52: 45231 | BL52: 45261 | BM52: 45292 | BN52: 45323 | BO52: 45352 | BP52: 45383 | BQ52: 45413 | BR52: 45444 | BS52: 45474 | BT52: 45505 | BU52: 45536 | BV52: 45566 | BW52: 45597 | BX52: 45627 | BY52: 45658 | BZ52: 45689 | CA52: 45717 | CB52: 45748 | CC52: 45778 | CD52: 45809 | CE52: 45839 | CF52: 45870 | CG52: 45901 | CH52: 45931 | CI52: 45962 | CJ52: 45992 | CK52: 46023 | CL52: 46054 | CM52: 46082 | CN52: 46113 | CO52: 46143 | CP52: 46174 | CQ52: 46204 | CR52: 46235 | CS52: 46266 | CT52: 46296 | CU52: 46327 | CV52: 46357 | CW52: 46388 | CX52: 46419 | CY52: 46447 | CZ52: 46478 | DA52: 46508 | DB52: 46539 | DC52: 46569 | DD52: 46600 | DE52: 46631 | DF52: 46661 | DG52: 46692 | DH52: 46722
BA53: =MONTH(BA52) -> 1 | BB53: =MONTH(BB52) -> 2 | BC53: =MONTH(BC52) -> 3 | BD53: =MONTH(BD52) -> 4 | BE53: =MONTH(BE52) -> 5 | BF53: =MONTH(BF52) -> 6 | BG53: =MONTH(BG52) -> 7 | BH53: =MONTH(BH52) -> 8 | ... DH53: =MONTH(DH52) -> 12
BA54: 202301 | BB54: =IF(BB53=1,BA54+89,BA54+1) -> 202302 | BC54: =IF(BC53=1,BB54+89,BB54+1) -> 202303 | BD54: =IF(BD53=1,BC54+89,BC54+1) -> 202304 | BE54: =IF(BE53=1,BD54+89,BD54+1) -> 202305 | BF54: =IF(BF53=1,BE54+89,BE54+1) -> 202306 | BG54: =IF(BG53=1,BF54+89,BF54+1) -> 202307 | BH54: =IF(BH53=1,BG54+89,BG54+1) -> 202308 | BI54: =IF(BI53=1,BH54+89,BH54+1) -> 202309 | ... DH54: =IF(DH53=1,DG54+89,DG54+1) -> 202712
AZ55: =A49 -> February 2025 MPR | BA55: =HLOOKUP(BA$54,$B$42:$AW$45,4,FALSE) -> #N/A | BB55: =HLOOKUP(BB$54,$B$42:$AW$45,4,FALSE) -> #N/A | BC55: =HLOOKUP(BC$54,$B$42:$AW$45,4,FALSE) -> #N/A | BD55: =HLOOKUP(BD$54,$B$42:$AW$45,4,FALSE) -> #N/A | BE55: =HLOOKUP(BE$54,$B$42:$AW$45,4,FALSE) -> #N/A | BF55: =HLOOKUP(BF$54,$B$42:$AW$45,4,FALSE) -> #N/A | BG55: =HLOOKUP(BG$54,$B$42:$AW$45,4,FALSE) -> #N/A | BH55: =HLOOKUP(BH$54,$B$42:$AW$45,4,FALSE) -> #N/A | ... DH55: =HLOOKUP(DH$54,$B$42:$AW$45,4,FALSE) -> 84.492667
AZ56: =AZ49 -> May 2025 MPR | BA56: =HLOOKUP(BA$54,$BA$42:$CV$45,4,FALSE) -> #N/A | BB56: =HLOOKUP(BB$54,$BA$42:$CV$45,4,FALSE) -> #N/A | BC56: =HLOOKUP(BC$54,$BA$42:$CV$45,4,FALSE) -> #N/A | BD56: =HLOOKUP(BD$54,$BA$42:$CV$45,4,FALSE) -> #N/A | BE56: =HLOOKUP(BE$54,$BA$42:$CV$45,4,FALSE) -> #N/A | BF56: =HLOOKUP(BF$54,$BA$42:$CV$45,4,FALSE) -> #N/A | BG56: =HLOOKUP(BG$54,$BA$42:$CV$45,4,FALSE) -> #N/A | BH56: =HLOOKUP(BH$54,$BA$42:$CV$45,4,FALSE) -> #N/A | ... DH56: =HLOOKUP(DH$54,$BA$42:$CV$45,4,FALSE) -> 80.452143
AZ57: Difference | BP57: =BP56-BP55 -> #N/A | BQ57: =BQ56-BQ55 -> #N/A | BR57: =BR56-BR55 -> #N/A | BS57: =BS56-BS55 -> #N/A | BT57: =BT56-BT55 -> #N/A | BU57: =BU56-BU55 -> #N/A | BV57: =BV56-BV55 -> #N/A | BW57: =BW56-BW55 -> #N/A | ... DH57: =DH56-DH55 -> -4.0405238
AZ58: Next 3 years | DB58: =AVERAGE(BV57:DB57) -> #N/A
AZ60: Comparison - quarterly
BA61: 44927 | BB61: 45017 | BC61: 45108 | BD61: 45200 | BE61: 45292 | BF61: 45383 | BG61: 45474 | BH61: 45566 | BI61: 45658 | BJ61: 45748 | BK61: 45839 | BL61: 45931 | BM61: 46023 | BN61: 46113 | BO61: 46204 | BP61: 46296 | BQ61: 46388 | BR61: 46478 | BS61: 46569 | BT61: 46661
BA62: 202301 | BB62: =IF(RIGHT(BA62)="4",BA62+97,BA62+1) -> 202302 | BC62: =IF(RIGHT(BB62)="4",BB62+97,BB62+1) -> 202303 | BD62: =IF(RIGHT(BC62)="4",BC62+97,BC62+1) -> 202304 | BE62: =IF(RIGHT(BD62)="4",BD62+97,BD62+1) -> 202401 | BF62: =IF(RIGHT(BE62)="4",BE62+97,BE62+1) -> 202402 | BG62: =IF(RIGHT(BF62)="4",BF62+97,BF62+1) -> 202403 | BH62: =IF(RIGHT(BG62)="4",BG62+97,BG62+1) -> 202404 | BI62: =IF(RIGHT(BH62)="4",BH62+97,BH62+1) -> 202501 | ... BT62: =IF(RIGHT(BS62)="4",BS62+97,BS62+1) -> 202704
AZ63: =A49 -> February 2025 MPR | BA63: =HLOOKUP(BA$62,$B$48:$R$49,2,FALSE) -> #N/A | BB63: =HLOOKUP(BB$62,$B$48:$R$49,2,FALSE) -> #N/A | BC63: =HLOOKUP(BC$62,$B$48:$R$49,2,FALSE) -> #N/A | BD63: =HLOOKUP(BD$62,$B$48:$R$49,2,FALSE) -> #N/A | BE63: =HLOOKUP(BE$62,$B$48:$R$49,2,FALSE) -> #N/A | BF63: =HLOOKUP(BF$62,$B$48:$R$49,2,FALSE) -> #N/A | BG63: =HLOOKUP(BG$62,$B$48:$R$49,2,FALSE) -> #N/A | BH63: =HLOOKUP(BH$62,$B$48:$R$49,2,FALSE) -> #N/A | ... BT63: =HLOOKUP(BT$62,$B$48:$R$49,2,FALSE) -> 83.2125
AZ64: =AZ49 -> May 2025 MPR | BA64: =HLOOKUP(BA$62,$BA$48:$BQ$49,2,FALSE) -> #N/A | BB64: =HLOOKUP(BB$62,$BA$48:$BQ$49,2,FALSE) -> #N/A | BC64: =HLOOKUP(BC$62,$BA$48:$BQ$49,2,FALSE) -> #N/A | BD64: =HLOOKUP(BD$62,$BA$48:$BQ$49,2,FALSE) -> #N/A | BE64: =HLOOKUP(BE$62,$BA$48:$BQ$49,2,FALSE) -> #N/A | BF64: =HLOOKUP(BF$62,$BA$48:$BQ$49,2,FALSE) -> #N/A | BG64: =HLOOKUP(BG$62,$BA$48:$BQ$49,2,FALSE) -> #N/A | BH64: =HLOOKUP(BH$62,$BA$48:$BQ$49,2,FALSE) -> #N/A | ... BT64: =HLOOKUP(BT$62,$BA$48:$BQ$49,2,FALSE) -> 78.912143
AZ65: Difference | BG65: =BG64-BG63 -> #N/A | BH65: =BH64-BH63 -> #N/A | BI65: =BI64-BI63 -> #N/A | BJ65: =BJ64-BJ63 -> -37.108063 | BK65: =BK64-BK63 -> -34.031032 | BL65: =BL64-BL63 -> -23.009 | BM65: =BM64-BM63 -> -23.752571 | BN65: =BN64-BN63 -> -18.676873 | ... BT65: =BT64-BT63 -> -4.3003571
AZ66: Next 3 years | BR66: =AVERAGE(BG65:BR65) -> #N/A

Sheet Market expectations - Electrici
A1: ='Market pricing dates'!A2 -> February 2025 MPR | C1: ='Market pricing dates'!A12 -> 15 working days to 31 Jan 2025 | AZ1: ='Market pricing dates'!D2 -> May 2025 MPR | BB1: ='Market pricing dates'!D12 -> 15 working days to 29 Apr 2025
A2: Column # | B2: =HAVERD!DR$1 -> 122 | C2: =+B2+1 -> 123 | D2: =+C2+1 -> 124 | E2: =+D2+1 -> 125 | F2: =+E2+1 -> 126 | G2: =+F2+1 -> 127 | H2: =+G2+1 -> 128 | I2: =+H2+1 -> 129 | J2: =+I2+1 -> 130 | ... AW2: =+AV2+1 -> 169 | AZ2: Column # | BA2: =HAVERD!DR$1 -> 122 | BB2: =+BA2+1 -> 123 | BC2: =+BB2+1 -> 124 | BD2: =+BC2+1 -> 125 | BE2: =+BD2+1 -> 126 | BF2: =+BE2+1 -> 127 | BG2: =+BF2+1 -> 128 | BH2: =+BG2+1 -> 129 | BI2: =+BH2+1 -> 130 | ... CV2: =+CU2+1 -> 169
A3: Months | B3: =HAVERD!DR$2 -> Electricity - 1 | C3: =HAVERD!DS$2 -> Electricity - 2 | D3: =HAVERD!DT$2 -> Electricity - 3 | E3: =HAVERD!DU$2 -> Electricity - 4 | F3: =HAVERD!DV$2 -> Electricity - 5 | G3: =HAVERD!DW$2 -> Electricity - 6 | H3: =HAVERD!DX$2 -> Electricity - 7 | I3: =HAVERD!DY$2 -> Electricity - 8 | ... AW3: =HAVERD!FM$2 -> Electricity - 48 | AZ3: Months | BA3: =HAVERD!DR$2 -> Electricity - 1 | BB3: =HAVERD!DS$2 -> Electricity - 2 | BC3: =HAVERD!DT$2 -> Electricity - 3 | BD3: =HAVERD!DU$2 -> Electricity - 4 | BE3: =HAVERD!DV$2 -> Electricity - 5 | BF3: =HAVERD!DW$2 -> Electricity - 6 | BG3: =HAVERD!DX$2 -> Electricity - 7 | BH3: =HAVERD!DY$2 -> Electricity - 8 | ... CV3: =HAVERD!FM$2 -> Electricity - 48
A4: Days | C4: 30.416667 | D4: =+C4+30.4166667 -> 60.833333 | E4: =+D4+30.4166667 -> 91.25 | F4: =+E4+30.4166667 -> 121.66667 | G4: =+F4+30.4166667 -> 152.08333 | H4: =+G4+30.4166667 -> 182.5 | I4: =+H4+30.4166667 -> 212.91667 | J4: =+I4+30.4166667 -> 243.33333 | K4: =+J4+30.4166667 -> 273.75 | ... AW4: =+AV4+30.4166667 -> 1429.5833 | AZ4: Days | BB4: 30.416667 | BC4: =+BB4+30.4166667 -> 60.833333 | BD4: =+BC4+30.4166667 -> 91.25 | BE4: =+BD4+30.4166667 -> 121.66667 | BF4: =+BE4+30.4166667 -> 152.08333 | BG4: =+BF4+30.4166667 -> 182.5 | BH4: =+BG4+30.4166667 -> 212.91667 | BI4: =+BH4+30.4166667 -> 243.33333 | BJ4: =+BI4+30.4166667 -> 273.75 | ... CV4: =+CU4+30.4166667 -> 1429.5833
A5: Dates | AZ5: Dates
A6: =A11-7 -> 45670 | B6: =A6 -> 45670 | C6: =$B6+C$4 -> 45700.417 | D6: =$B6+D$4 -> 45730.833 | E6: =$B6+E$4 -> 45761.25 | F6: =$B6+F$4 -> 45791.667 | G6: =$B6+G$4 -> 45822.083 | H6: =$B6+H$4 -> 45852.5 | I6: =$B6+I$4 -> 45882.917 | J6: =$B6+J$4 -> 45913.333 | ... AW6: =$B6+AW$4 -> 47099.583 | AZ6: =AZ11-7 -> 45756 | BA6: =AZ6 -> 45756 | BB6: =$AZ6+BB$4 -> 45786.417 | BC6: =$AZ6+BC$4 -> 45816.833 | BD6: =$AZ6+BD$4 -> 45847.25 | BE6: =$AZ6+BE$4 -> 45877.667 | BF6: =$AZ6+BF$4 -> 45908.083 | BG6: =$AZ6+BG$4 -> 45938.5 | BH6: =$AZ6+BH$4 -> 45968.917 | BI6: =$AZ6+BI$4 -> 45999.333 | ... CV6: =$AZ6+CV$4 -> 47185.583
A7: =A12-7 -> 45671 | B7: =A7 -> 45671 | C7: =$B7+C$4 -> 45701.417 | D7: =$B7+D$4 -> 45731.833 | E7: =$B7+E$4 -> 45762.25 | F7: =$B7+F$4 -> 45792.667 | G7: =$B7+G$4 -> 45823.083 | H7: =$B7+H$4 -> 45853.5 | I7: =$B7+I$4 -> 45883.917 | J7: =$B7+J$4 -> 45914.333 | ... AW7: =$B7+AW$4 -> 47100.583 | AZ7: =AZ12-7 -> 45757 | BA7: =AZ7 -> 45757 | BB7: =$AZ7+BB$4 -> 45787.417 | BC7: =$AZ7+BC$4 -> 45817.833 | BD7: =$AZ7+BD$4 -> 45848.25 | BE7: =$AZ7+BE$4 -> 45878.667 | BF7: =$AZ7+BF$4 -> 45909.083 | BG7: =$AZ7+BG$4 -> 45939.5 | BH7: =$AZ7+BH$4 -> 45969.917 | BI7: =$AZ7+BI$4 -> 46000.333 | ... CV7: =$AZ7+CV$4 -> 47186.583
A8: =A13-7 -> 45672 | B8: =A8 -> 45672 | C8: =$B8+C$4 -> 45702.417 | D8: =$B8+D$4 -> 45732.833 | E8: =$B8+E$4 -> 45763.25 | F8: =$B8+F$4 -> 45793.667 | G8: =$B8+G$4 -> 45824.083 | H8: =$B8+H$4 -> 45854.5 | I8: =$B8+I$4 -> 45884.917 | J8: =$B8+J$4 -> 45915.333 | ... AW8: =$B8+AW$4 -> 47101.583 | AZ8: =AZ13-7 -> 45758 | BA8: =AZ8 -> 45758 | BB8: =$AZ8+BB$4 -> 45788.417 | BC8: =$AZ8+BC$4 -> 45818.833 | BD8: =$AZ8+BD$4 -> 45849.25 | BE8: =$AZ8+BE$4 -> 45879.667 | BF8: =$AZ8+BF$4 -> 45910.083 | BG8: =$AZ8+BG$4 -> 45940.5 | BH8: =$AZ8+BH$4 -> 45970.917 | BI8: =$AZ8+BI$4 -> 46001.333 | ... CV8: =$AZ8+CV$4 -> 47187.583
A9: =A14-7 -> 45673 | B9: =A9 -> 45673 | C9: =$B9+C$4 -> 45703.417 | D9: =$B9+D$4 -> 45733.833 | E9: =$B9+E$4 -> 45764.25 | F9: =$B9+F$4 -> 45794.667 | G9: =$B9+G$4 -> 45825.083 | H9: =$B9+H$4 -> 45855.5 | I9: =$B9+I$4 -> 45885.917 | J9: =$B9+J$4 -> 45916.333 | ... AW9: =$B9+AW$4 -> 47102.583 | AZ9: =AZ14-7 -> 45761 | BA9: =AZ9 -> 45761 | BB9: =$AZ9+BB$4 -> 45791.417 | BC9: =$AZ9+BC$4 -> 45821.833 | BD9: =$AZ9+BD$4 -> 45852.25 | BE9: =$AZ9+BE$4 -> 45882.667 | BF9: =$AZ9+BF$4 -> 45913.083 | BG9: =$AZ9+BG$4 -> 45943.5 | BH9: =$AZ9+BH$4 -> 45973.917 | BI9: =$AZ9+BI$4 -> 46004.333 | ... CV9: =$AZ9+CV$4 -> 47190.583
A10: =A15-7 -> 45674 | B10: =A10 -> 45674 | C10: =$B10+C$4 -> 45704.417 | D10: =$B10+D$4 -> 45734.833 | E10: =$B10+E$4 -> 45765.25 | F10: =$B10+F$4 -> 45795.667 | G10: =$B10+G$4 -> 45826.083 | H10: =$B10+H$4 -> 45856.5 | I10: =$B10+I$4 -> 45886.917 | J10: =$B10+J$4 -> 45917.333 | ... AW10: =$B10+AW$4 -> 47103.583 | AZ10: =AZ15-7 -> 45762 | BA10: =AZ10 -> 45762 | BB10: =$AZ10+BB$4 -> 45792.417 | BC10: =$AZ10+BC$4 -> 45822.833 | BD10: =$AZ10+BD$4 -> 45853.25 | BE10: =$AZ10+BE$4 -> 45883.667 | BF10: =$AZ10+BF$4 -> 45914.083 | BG10: =$AZ10+BG$4 -> 45944.5 | BH10: =$AZ10+BH$4 -> 45974.917 | BI10: =$AZ10+BI$4 -> 46005.333 | ... CV10: =$AZ10+CV$4 -> 47191.583
A11: =A16-7 -> 45677 | B11: =A11 -> 45677 | C11: =$B11+C$4 -> 45707.417 | D11: =$B11+D$4 -> 45737.833 | E11: =$B11+E$4 -> 45768.25 | F11: =$B11+F$4 -> 45798.667 | G11: =$B11+G$4 -> 45829.083 | H11: =$B11+H$4 -> 45859.5 | I11: =$B11+I$4 -> 45889.917 | J11: =$B11+J$4 -> 45920.333 | ... AW11: =$B11+AW$4 -> 47106.583 | AZ11: =AZ16-7 -> 45763 | BA11: =AZ11 -> 45763 | BB11: =$AZ11+BB$4 -> 45793.417 | BC11: =$AZ11+BC$4 -> 45823.833 | BD11: =$AZ11+BD$4 -> 45854.25 | BE11: =$AZ11+BE$4 -> 45884.667 | BF11: =$AZ11+BF$4 -> 45915.083 | BG11: =$AZ11+BG$4 -> 45945.5 | BH11: =$AZ11+BH$4 -> 45975.917 | BI11: =$AZ11+BI$4 -> 46006.333 | ... CV11: =$AZ11+CV$4 -> 47192.583
A12: =A17-7 -> 45678 | B12: =A12 -> 45678 | C12: =$B12+C$4 -> 45708.417 | D12: =$B12+D$4 -> 45738.833 | E12: =$B12+E$4 -> 45769.25 | F12: =$B12+F$4 -> 45799.667 | G12: =$B12+G$4 -> 45830.083 | H12: =$B12+H$4 -> 45860.5 | I12: =$B12+I$4 -> 45890.917 | J12: =$B12+J$4 -> 45921.333 | ... AW12: =$B12+AW$4 -> 47107.583 | AZ12: =AZ17-7 -> 45764 | BA12: =AZ12 -> 45764 | BB12: =$AZ12+BB$4 -> 45794.417 | BC12: =$AZ12+BC$4 -> 45824.833 | BD12: =$AZ12+BD$4 -> 45855.25 | BE12: =$AZ12+BE$4 -> 45885.667 | BF12: =$AZ12+BF$4 -> 45916.083 | BG12: =$AZ12+BG$4 -> 45946.5 | BH12: =$AZ12+BH$4 -> 45976.917 | BI12: =$AZ12+BI$4 -> 46007.333 | ... CV12: =$AZ12+CV$4 -> 47193.583
A13: =A18-7 -> 45679 | B13: =A13 -> 45679 | C13: =$B13+C$4 -> 45709.417 | D13: =$B13+D$4 -> 45739.833 | E13: =$B13+E$4 -> 45770.25 | F13: =$B13+F$4 -> 45800.667 | G13: =$B13+G$4 -> 45831.083 | H13: =$B13+H$4 -> 45861.5 | I13: =$B13+I$4 -> 45891.917 | J13: =$B13+J$4 -> 45922.333 | ... AW13: =$B13+AW$4 -> 47108.583 | AZ13: =AZ18-7 -> 45765 | BA13: =AZ13 -> 45765 | BB13: =$AZ13+BB$4 -> 45795.417 | BC13: =$AZ13+BC$4 -> 45825.833 | BD13: =$AZ13+BD$4 -> 45856.25 | BE13: =$AZ13+BE$4 -> 45886.667 | BF13: =$AZ13+BF$4 -> 45917.083 | BG13: =$AZ13+BG$4 -> 45947.5 | BH13: =$AZ13+BH$4 -> 45977.917 | BI13: =$AZ13+BI$4 -> 46008.333 | ... CV13: =$AZ13+CV$4 -> 47194.583
A14: =A19-7 -> 45680 | B14: =A14 -> 45680 | C14: =$B14+C$4 -> 45710.417 | D14: =$B14+D$4 -> 45740.833 | E14: =$B14+E$4 -> 45771.25 | F14: =$B14+F$4 -> 45801.667 | G14: =$B14+G$4 -> 45832.083 | H14: =$B14+H$4 -> 45862.5 | I14: =$B14+I$4 -> 45892.917 | J14: =$B14+J$4 -> 45923.333 | ... AW14: =$B14+AW$4 -> 47109.583 | AZ14: =AZ19-7 -> 45768 | BA14: =AZ14 -> 45768 | BB14: =$AZ14+BB$4 -> 45798.417 | BC14: =$AZ14+BC$4 -> 45828.833 | BD14: =$AZ14+BD$4 -> 45859.25 | BE14: =$AZ14+BE$4 -> 45889.667 | BF14: =$AZ14+BF$4 -> 45920.083 | BG14: =$AZ14+BG$4 -> 45950.5 | BH14: =$AZ14+BH$4 -> 45980.917 | BI14: =$AZ14+BI$4 -> 46011.333 | ... CV14: =$AZ14+CV$4 -> 47197.583
A15: =A20-7 -> 45681 | B15: =A15 -> 45681 | C15: =$B15+C$4 -> 45711.417 | D15: =$B15+D$4 -> 45741.833 | E15: =$B15+E$4 -> 45772.25 | F15: =$B15+F$4 -> 45802.667 | G15: =$B15+G$4 -> 45833.083 | H15: =$B15+H$4 -> 45863.5 | I15: =$B15+I$4 -> 45893.917 | J15: =$B15+J$4 -> 45924.333 | ... AW15: =$B15+AW$4 -> 47110.583 | AZ15: =AZ20-7 -> 45769 | BA15: =AZ15 -> 45769 | BB15: =$AZ15+BB$4 -> 45799.417 | BC15: =$AZ15+BC$4 -> 45829.833 | BD15: =$AZ15+BD$4 -> 45860.25 | BE15: =$AZ15+BE$4 -> 45890.667 | BF15: =$AZ15+BF$4 -> 45921.083 | BG15: =$AZ15+BG$4 -> 45951.5 | BH15: =$AZ15+BH$4 -> 45981.917 | BI15: =$AZ15+BI$4 -> 46012.333 | ... CV15: =$AZ15+CV$4 -> 47198.583
A16: ='Market pricing dates'!B5 -> 45684 | B16: =A16 -> 45684 | C16: =$B16+C$4 -> 45714.417 | D16: =$B16+D$4 -> 45744.833 | E16: =$B16+E$4 -> 45775.25 | F16: =$B16+F$4 -> 45805.667 | G16: =$B16+G$4 -> 45836.083 | H16: =$B16+H$4 -> 45866.5 | I16: =$B16+I$4 -> 45896.917 | J16: =$B16+J$4 -> 45927.333 | ... AW16: =$B16+AW$4 -> 47113.583 | AZ16: ='Market pricing dates'!E5 -> 45770 | BA16: =AZ16 -> 45770 | BB16: =$AZ16+BB$4 -> 45800.417 | BC16: =$AZ16+BC$4 -> 45830.833 | BD16: =$AZ16+BD$4 -> 45861.25 | BE16: =$AZ16+BE$4 -> 45891.667 | BF16: =$AZ16+BF$4 -> 45922.083 | BG16: =$AZ16+BG$4 -> 45952.5 | BH16: =$AZ16+BH$4 -> 45982.917 | BI16: =$AZ16+BI$4 -> 46013.333 | ... CV16: =$AZ16+CV$4 -> 47199.583
A17: ='Market pricing dates'!B6 -> 45685 | B17: =A17 -> 45685 | C17: =$B17+C$4 -> 45715.417 | D17: =$B17+D$4 -> 45745.833 | E17: =$B17+E$4 -> 45776.25 | F17: =$B17+F$4 -> 45806.667 | G17: =$B17+G$4 -> 45837.083 | H17: =$B17+H$4 -> 45867.5 | I17: =$B17+I$4 -> 45897.917 | J17: =$B17+J$4 -> 45928.333 | ... AW17: =$B17+AW$4 -> 47114.583 | AZ17: ='Market pricing dates'!E6 -> 45771 | BA17: =AZ17 -> 45771 | BB17: =$AZ17+BB$4 -> 45801.417 | BC17: =$AZ17+BC$4 -> 45831.833 | BD17: =$AZ17+BD$4 -> 45862.25 | BE17: =$AZ17+BE$4 -> 45892.667 | BF17: =$AZ17+BF$4 -> 45923.083 | BG17: =$AZ17+BG$4 -> 45953.5 | BH17: =$AZ17+BH$4 -> 45983.917 | BI17: =$AZ17+BI$4 -> 46014.333 | ... CV17: =$AZ17+CV$4 -> 47200.583
A18: ='Market pricing dates'!B7 -> 45686 | B18: =A18 -> 45686 | C18: =$B18+C$4 -> 45716.417 | D18: =$B18+D$4 -> 45746.833 | E18: =$B18+E$4 -> 45777.25 | F18: =$B18+F$4 -> 45807.667 | G18: =$B18+G$4 -> 45838.083 | H18: =$B18+H$4 -> 45868.5 | I18: =$B18+I$4 -> 45898.917 | J18: =$B18+J$4 -> 45929.333 | ... AW18: =$B18+AW$4 -> 47115.583 | AZ18: ='Market pricing dates'!E7 -> 45772 | BA18: =AZ18 -> 45772 | BB18: =$AZ18+BB$4 -> 45802.417 | BC18: =$AZ18+BC$4 -> 45832.833 | BD18: =$AZ18+BD$4 -> 45863.25 | BE18: =$AZ18+BE$4 -> 45893.667 | BF18: =$AZ18+BF$4 -> 45924.083 | BG18: =$AZ18+BG$4 -> 45954.5 | BH18: =$AZ18+BH$4 -> 45984.917 | BI18: =$AZ18+BI$4 -> 46015.333 | ... CV18: =$AZ18+CV$4 -> 47201.583
A19: ='Market pricing dates'!B8 -> 45687 | B19: =A19 -> 45687 | C19: =$B19+C$4 -> 45717.417 | D19: =$B19+D$4 -> 45747.833 | E19: =$B19+E$4 -> 45778.25 | F19: =$B19+F$4 -> 45808.667 | G19: =$B19+G$4 -> 45839.083 | H19: =$B19+H$4 -> 45869.5 | I19: =$B19+I$4 -> 45899.917 | J19: =$B19+J$4 -> 45930.333 | ... AW19: =$B19+AW$4 -> 47116.583 | AZ19: ='Market pricing dates'!E8 -> 45775 | BA19: =AZ19 -> 45775 | BB19: =$AZ19+BB$4 -> 45805.417 | BC19: =$AZ19+BC$4 -> 45835.833 | BD19: =$AZ19+BD$4 -> 45866.25 | BE19: =$AZ19+BE$4 -> 45896.667 | BF19: =$AZ19+BF$4 -> 45927.083 | BG19: =$AZ19+BG$4 -> 45957.5 | BH19: =$AZ19+BH$4 -> 45987.917 | BI19: =$AZ19+BI$4 -> 46018.333 | ... CV19: =$AZ19+CV$4 -> 47204.583
A20: ='Market pricing dates'!B9 -> 45688 | B20: =A20 -> 45688 | C20: =$B20+C$4 -> 45718.417 | D20: =$B20+D$4 -> 45748.833 | E20: =$B20+E$4 -> 45779.25 | F20: =$B20+F$4 -> 45809.667 | G20: =$B20+G$4 -> 45840.083 | H20: =$B20+H$4 -> 45870.5 | I20: =$B20+I$4 -> 45900.917 | J20: =$B20+J$4 -> 45931.333 | ... AW20: =$B20+AW$4 -> 47117.583 | AZ20: ='Market pricing dates'!E9 -> 45776 | BA20: =AZ20 -> 45776 | BB20: =$AZ20+BB$4 -> 45806.417 | BC20: =$AZ20+BC$4 -> 45836.833 | BD20: =$AZ20+BD$4 -> 45867.25 | BE20: =$AZ20+BE$4 -> 45897.667 | BF20: =$AZ20+BF$4 -> 45928.083 | BG20: =$AZ20+BG$4 -> 45958.5 | BH20: =$AZ20+BH$4 -> 45988.917 | BI20: =$AZ20+BI$4 -> 46019.333 | ... CV20: =$AZ20+CV$4 -> 47205.583
A22: Electricity futures | AZ22: Electricity futures
A23: =A6 -> 45670 | B23: =VLOOKUP($A23,HAVERD!$A:$FM,B$2,FALSE) -> 99.65 | C23: =VLOOKUP($A23,HAVERD!$A:$FM,C$2,FALSE) -> 95 | D23: =VLOOKUP($A23,HAVERD!$A:$FM,D$2,FALSE) -> 91.8 | E23: =VLOOKUP($A23,HAVERD!$A:$FM,E$2,FALSE) -> 89.35 | F23: =VLOOKUP($A23,HAVERD!$A:$FM,F$2,FALSE) -> 88.05 | G23: =VLOOKUP($A23,HAVERD!$A:$FM,G$2,FALSE) -> 88.1 | H23: =VLOOKUP($A23,HAVERD!$A:$FM,H$2,FALSE) -> 88.05 | I23: =VLOOKUP($A23,HAVERD!$A:$FM,I$2,FALSE) -> 90.75 | ... AW23: =VLOOKUP($A23,HAVERD!$A:$FM,AW$2,FALSE) -> 72.05 | AZ23: =AZ6 -> 45756 | BA23: =_xlfn.IFNA(VLOOKUP($AZ23,HAVERD!$A:$FM,BA$2,FALSE),"") -> 69.55 | BB23: =_xlfn.IFNA(VLOOKUP($AZ23,HAVERD!$A:$FM,BB$2,FALSE),"") -> 69.65 | BC23: =_xlfn.IFNA(VLOOKUP($AZ23,HAVERD!$A:$FM,BC$2,FALSE),"") -> 71.6 | BD23: =_xlfn.IFNA(VLOOKUP($AZ23,HAVERD!$A:$FM,BD$2,FALSE),"") -> 69.1 | BE23: =_xlfn.IFNA(VLOOKUP($AZ23,HAVERD!$A:$FM,BE$2,FALSE),"") -> 77.5 | BF23: =_xlfn.IFNA(VLOOKUP($AZ23,HAVERD!$A:$FM,BF$2,FALSE),"") -> 79.1 | BG23: =_xlfn.IFNA(VLOOKUP($AZ23,HAVERD!$A:$FM,BG$2,FALSE),"") -> 80.65 | BH23: =_xlfn.IFNA(VLOOKUP($AZ23,HAVERD!$A:$FM,BH$2,FALSE),"") -> 81.25 | ... CV23: =_xlfn.IFNA(VLOOKUP($AZ23,HAVERD!$A:$FM,CV$2,FALSE),"") -> 63.3
A24: =A7 -> 45671 | B24: =VLOOKUP($A24,HAVERD!$A:$FM,B$2,FALSE) -> 97.5 | C24: =VLOOKUP($A24,HAVERD!$A:$FM,C$2,FALSE) -> 92.85 | D24: =VLOOKUP($A24,HAVERD!$A:$FM,D$2,FALSE) -> 89.7 | E24: =VLOOKUP($A24,HAVERD!$A:$FM,E$2,FALSE) -> 87.3 | F24: =VLOOKUP($A24,HAVERD!$A:$FM,F$2,FALSE) -> 85.05 | G24: =VLOOKUP($A24,HAVERD!$A:$FM,G$2,FALSE) -> 86 | H24: =VLOOKUP($A24,HAVERD!$A:$FM,H$2,FALSE) -> 85.95 | I24: =VLOOKUP($A24,HAVERD!$A:$FM,I$2,FALSE) -> 88.65 | ... AW24: =VLOOKUP($A24,HAVERD!$A:$FM,AW$2,FALSE) -> 72.05 | AZ24: =AZ7 -> 45757 | BA24: =_xlfn.IFNA(VLOOKUP($AZ24,HAVERD!$A:$FM,BA$2,FALSE),"") -> 70.1 | BB24: =_xlfn.IFNA(VLOOKUP($AZ24,HAVERD!$A:$FM,BB$2,FALSE),"") -> 69.95 | BC24: =_xlfn.IFNA(VLOOKUP($AZ24,HAVERD!$A:$FM,BC$2,FALSE),"") -> 70.4 | BD24: =_xlfn.IFNA(VLOOKUP($AZ24,HAVERD!$A:$FM,BD$2,FALSE),"") -> 69.8 | BE24: =_xlfn.IFNA(VLOOKUP($AZ24,HAVERD!$A:$FM,BE$2,FALSE),"") -> 76.8 | BF24: =_xlfn.IFNA(VLOOKUP($AZ24,HAVERD!$A:$FM,BF$2,FALSE),"") -> 78.6 | BG24: =_xlfn.IFNA(VLOOKUP($AZ24,HAVERD!$A:$FM,BG$2,FALSE),"") -> 80.15 | BH24: =_xlfn.IFNA(VLOOKUP($AZ24,HAVERD!$A:$FM,BH$2,FALSE),"") -> 80.75 | ... CV24: =_xlfn.IFNA(VLOOKUP($AZ24,HAVERD!$A:$FM,CV$2,FALSE),"") -> 63.3
A25: =A8 -> 45672 | B25: =VLOOKUP($A25,HAVERD!$A:$FM,B$2,FALSE) -> 98.3 | C25: =VLOOKUP($A25,HAVERD!$A:$FM,C$2,FALSE) -> 93.15 | D25: =VLOOKUP($A25,HAVERD!$A:$FM,D$2,FALSE) -> 88.65 | E25: =VLOOKUP($A25,HAVERD!$A:$FM,E$2,FALSE) -> 86.25 | F25: =VLOOKUP($A25,HAVERD!$A:$FM,F$2,FALSE) -> 85.35 | G25: =VLOOKUP($A25,HAVERD!$A:$FM,G$2,FALSE) -> 85.25 | H25: =VLOOKUP($A25,HAVERD!$A:$FM,H$2,FALSE) -> 85.2 | I25: =VLOOKUP($A25,HAVERD!$A:$FM,I$2,FALSE) -> 87.9 | ... AW25: =VLOOKUP($A25,HAVERD!$A:$FM,AW$2,FALSE) -> 72.2 | AZ25: =AZ8 -> 45758 | BA25: =_xlfn.IFNA(VLOOKUP($AZ25,HAVERD!$A:$FM,BA$2,FALSE),"") -> 71.6 | BB25: =_xlfn.IFNA(VLOOKUP($AZ25,HAVERD!$A:$FM,BB$2,FALSE),"") -> 71.75 | BC25: =_xlfn.IFNA(VLOOKUP($AZ25,HAVERD!$A:$FM,BC$2,FALSE),"") -> 73.5 | BD25: =_xlfn.IFNA(VLOOKUP($AZ25,HAVERD!$A:$FM,BD$2,FALSE),"") -> 72 | BE25: =_xlfn.IFNA(VLOOKUP($AZ25,HAVERD!$A:$FM,BE$2,FALSE),"") -> 80.1 | BF25: =_xlfn.IFNA(VLOOKUP($AZ25,HAVERD!$A:$FM,BF$2,FALSE),"") -> 81.3 | BG25: =_xlfn.IFNA(VLOOKUP($AZ25,HAVERD!$A:$FM,BG$2,FALSE),"") -> 82.85 | BH25: =_xlfn.IFNA(VLOOKUP($AZ25,HAVERD!$A:$FM,BH$2,FALSE),"") -> 83.45 | ... CV25: =_xlfn.IFNA(VLOOKUP($AZ25,HAVERD!$A:$FM,CV$2,FALSE),"") -> 66.55
A26: =A9 -> 45673 | B26: =VLOOKUP($A26,HAVERD!$A:$FM,B$2,FALSE) -> 95.7 | C26: =VLOOKUP($A26,HAVERD!$A:$FM,C$2,FALSE) -> 91.65 | D26: =VLOOKUP($A26,HAVERD!$A:$FM,D$2,FALSE) -> 87.35 | E26: =VLOOKUP($A26,HAVERD!$A:$FM,E$2,FALSE) -> 84.95 | F26: =VLOOKUP($A26,HAVERD!$A:$FM,F$2,FALSE) -> 84.1 | G26: =VLOOKUP($A26,HAVERD!$A:$FM,G$2,FALSE) -> 83.7 | H26: =VLOOKUP($A26,HAVERD!$A:$FM,H$2,FALSE) -> 83.65 | I26: =VLOOKUP($A26,HAVERD!$A:$FM,I$2,FALSE) -> 86.35 | ... AW26: =VLOOKUP($A26,HAVERD!$A:$FM,AW$2,FALSE) -> 72.45 | AZ26: =AZ9 -> 45761 | BA26: =_xlfn.IFNA(VLOOKUP($AZ26,HAVERD!$A:$FM,BA$2,FALSE),"") -> 73.25 | BB26: =_xlfn.IFNA(VLOOKUP($AZ26,HAVERD!$A:$FM,BB$2,FALSE),"") -> 73.8 | BC26: =_xlfn.IFNA(VLOOKUP($AZ26,HAVERD!$A:$FM,BC$2,FALSE),"") -> 75.2 | BD26: =_xlfn.IFNA(VLOOKUP($AZ26,HAVERD!$A:$FM,BD$2,FALSE),"") -> 73.65 | BE26: =_xlfn.IFNA(VLOOKUP($AZ26,HAVERD!$A:$FM,BE$2,FALSE),"") -> 82.2 | BF26: =_xlfn.IFNA(VLOOKUP($AZ26,HAVERD!$A:$FM,BF$2,FALSE),"") -> 82.75 | BG26: =_xlfn.IFNA(VLOOKUP($AZ26,HAVERD!$A:$FM,BG$2,FALSE),"") -> 84.3 | BH26: =_xlfn.IFNA(VLOOKUP($AZ26,HAVERD!$A:$FM,BH$2,FALSE),"") -> 84.9 | ... CV26: =_xlfn.IFNA(VLOOKUP($AZ26,HAVERD!$A:$FM,CV$2,FALSE),"") -> 63.7
A27: =A10 -> 45674 | B27: =VLOOKUP($A27,HAVERD!$A:$FM,B$2,FALSE) -> 96.5 | C27: =VLOOKUP($A27,HAVERD!$A:$FM,C$2,FALSE) -> 92.7 | D27: =VLOOKUP($A27,HAVERD!$A:$FM,D$2,FALSE) -> 88.5 | E27: =VLOOKUP($A27,HAVERD!$A:$FM,E$2,FALSE) -> 86.1 | F27: =VLOOKUP($A27,HAVERD!$A:$FM,F$2,FALSE) -> 85.35 | G27: =VLOOKUP($A27,HAVERD!$A:$FM,G$2,FALSE) -> 85.1 | H27: =VLOOKUP($A27,HAVERD!$A:$FM,H$2,FALSE) -> 85.05 | I27: =VLOOKUP($A27,HAVERD!$A:$FM,I$2,FALSE) -> 87.75 | ... AW27: =VLOOKUP($A27,HAVERD!$A:$FM,AW$2,FALSE) -> 72.05 | AZ27: =AZ10 -> 45762 | BA27: =_xlfn.IFNA(VLOOKUP($AZ27,HAVERD!$A:$FM,BA$2,FALSE),"") -> 72.35 | BB27: =_xlfn.IFNA(VLOOKUP($AZ27,HAVERD!$A:$FM,BB$2,FALSE),"") -> 73.2 | BC27: =_xlfn.IFNA(VLOOKUP($AZ27,HAVERD!$A:$FM,BC$2,FALSE),"") -> 74 | BD27: =_xlfn.IFNA(VLOOKUP($AZ27,HAVERD!$A:$FM,BD$2,FALSE),"") -> 72.05 | BE27: =_xlfn.IFNA(VLOOKUP($AZ27,HAVERD!$A:$FM,BE$2,FALSE),"") -> 81.2 | BF27: =_xlfn.IFNA(VLOOKUP($AZ27,HAVERD!$A:$FM,BF$2,FALSE),"") -> 82.05 | BG27: =_xlfn.IFNA(VLOOKUP($AZ27,HAVERD!$A:$FM,BG$2,FALSE),"") -> 83.6 | BH27: =_xlfn.IFNA(VLOOKUP($AZ27,HAVERD!$A:$FM,BH$2,FALSE),"") -> 84.2 | ... CV27: =_xlfn.IFNA(VLOOKUP($AZ27,HAVERD!$A:$FM,CV$2,FALSE),"") -> 63.3
A28: =A11 -> 45677 | B28: =VLOOKUP($A28,HAVERD!$A:$FM,B$2,FALSE) -> 98.85 | C28: =VLOOKUP($A28,HAVERD!$A:$FM,C$2,FALSE) -> 94.5 | D28: =VLOOKUP($A28,HAVERD!$A:$FM,D$2,FALSE) -> 88.45 | E28: =VLOOKUP($A28,HAVERD!$A:$FM,E$2,FALSE) -> 88.1 | F28: =VLOOKUP($A28,HAVERD!$A:$FM,F$2,FALSE) -> 87.85 | G28: =VLOOKUP($A28,HAVERD!$A:$FM,G$2,FALSE) -> 87 | H28: =VLOOKUP($A28,HAVERD!$A:$FM,H$2,FALSE) -> 86.95 | I28: =VLOOKUP($A28,HAVERD!$A:$FM,I$2,FALSE) -> 89.65 | ... AW28: =VLOOKUP($A28,HAVERD!$A:$FM,AW$2,FALSE) -> 72.1 | AZ28: =AZ11 -> 45763 | BA28: =_xlfn.IFNA(VLOOKUP($AZ28,HAVERD!$A:$FM,BA$2,FALSE),"") -> 74.8 | BB28: =_xlfn.IFNA(VLOOKUP($AZ28,HAVERD!$A:$FM,BB$2,FALSE),"") -> 74.75 | BC28: =_xlfn.IFNA(VLOOKUP($AZ28,HAVERD!$A:$FM,BC$2,FALSE),"") -> 76.4 | BD28: =_xlfn.IFNA(VLOOKUP($AZ28,HAVERD!$A:$FM,BD$2,FALSE),"") -> 75 | BE28: =_xlfn.IFNA(VLOOKUP($AZ28,HAVERD!$A:$FM,BE$2,FALSE),"") -> 81.65 | BF28: =_xlfn.IFNA(VLOOKUP($AZ28,HAVERD!$A:$FM,BF$2,FALSE),"") -> 83.6 | BG28: =_xlfn.IFNA(VLOOKUP($AZ28,HAVERD!$A:$FM,BG$2,FALSE),"") -> 85.15 | BH28: =_xlfn.IFNA(VLOOKUP($AZ28,HAVERD!$A:$FM,BH$2,FALSE),"") -> 85.75 | ... CV28: =_xlfn.IFNA(VLOOKUP($AZ28,HAVERD!$A:$FM,CV$2,FALSE),"") -> 64.1
A29: =A12 -> 45678 | B29: =VLOOKUP($A29,HAVERD!$A:$FM,B$2,FALSE) -> 102.45 | C29: =VLOOKUP($A29,HAVERD!$A:$FM,C$2,FALSE) -> 98 | D29: =VLOOKUP($A29,HAVERD!$A:$FM,D$2,FALSE) -> 91.8 | E29: =VLOOKUP($A29,HAVERD!$A:$FM,E$2,FALSE) -> 91.25 | F29: =VLOOKUP($A29,HAVERD!$A:$FM,F$2,FALSE) -> 90.8 | G29: =VLOOKUP($A29,HAVERD!$A:$FM,G$2,FALSE) -> 89.4 | H29: =VLOOKUP($A29,HAVERD!$A:$FM,H$2,FALSE) -> 89.35 | I29: =VLOOKUP($A29,HAVERD!$A:$FM,I$2,FALSE) -> 92.05 | ... AW29: =VLOOKUP($A29,HAVERD!$A:$FM,AW$2,FALSE) -> 72.25 | AZ29: =AZ12 -> 45764 | BA29: =_xlfn.IFNA(VLOOKUP($AZ29,HAVERD!$A:$FM,BA$2,FALSE),"") -> 75.4 | BB29: =_xlfn.IFNA(VLOOKUP($AZ29,HAVERD!$A:$FM,BB$2,FALSE),"") -> 75.8 | BC29: =_xlfn.IFNA(VLOOKUP($AZ29,HAVERD!$A:$FM,BC$2,FALSE),"") -> 76.45 | BD29: =_xlfn.IFNA(VLOOKUP($AZ29,HAVERD!$A:$FM,BD$2,FALSE),"") -> 75.05 | BE29: =_xlfn.IFNA(VLOOKUP($AZ29,HAVERD!$A:$FM,BE$2,FALSE),"") -> 81.7 | BF29: =_xlfn.IFNA(VLOOKUP($AZ29,HAVERD!$A:$FM,BF$2,FALSE),"") -> 83.95 | BG29: =_xlfn.IFNA(VLOOKUP($AZ29,HAVERD!$A:$FM,BG$2,FALSE),"") -> 85.5 | BH29: =_xlfn.IFNA(VLOOKUP($AZ29,HAVERD!$A:$FM,BH$2,FALSE),"") -> 86.1 | ... CV29: =_xlfn.IFNA(VLOOKUP($AZ29,HAVERD!$A:$FM,CV$2,FALSE),"") -> 63.95
A30: =A13 -> 45679 | B30: =VLOOKUP($A30,HAVERD!$A:$FM,B$2,FALSE) -> 100.9 | C30: =VLOOKUP($A30,HAVERD!$A:$FM,C$2,FALSE) -> 95.55 | D30: =VLOOKUP($A30,HAVERD!$A:$FM,D$2,FALSE) -> 89.6 | E30: =VLOOKUP($A30,HAVERD!$A:$FM,E$2,FALSE) -> 89.25 | F30: =VLOOKUP($A30,HAVERD!$A:$FM,F$2,FALSE) -> 88.95 | G30: =VLOOKUP($A30,HAVERD!$A:$FM,G$2,FALSE) -> 87.7 | H30: =VLOOKUP($A30,HAVERD!$A:$FM,H$2,FALSE) -> 87.65 | I30: =VLOOKUP($A30,HAVERD!$A:$FM,I$2,FALSE) -> 90.35 | ... AW30: =VLOOKUP($A30,HAVERD!$A:$FM,AW$2,FALSE) -> 70.6 | AZ30: =AZ13 -> 45765 | BA30: =_xlfn.IFNA(VLOOKUP($AZ30,HAVERD!$A:$FM,BA$2,FALSE),"") | BB30: =_xlfn.IFNA(VLOOKUP($AZ30,HAVERD!$A:$FM,BB$2,FALSE),"") | BC30: =_xlfn.IFNA(VLOOKUP($AZ30,HAVERD!$A:$FM,BC$2,FALSE),"") | BD30: =_xlfn.IFNA(VLOOKUP($AZ30,HAVERD!$A:$FM,BD$2,FALSE),"") | BE30: =_xlfn.IFNA(VLOOKUP($AZ30,HAVERD!$A:$FM,BE$2,FALSE),"") | BF30: =_xlfn.IFNA(VLOOKUP($AZ30,HAVERD!$A:$FM,BF$2,FALSE),"") | BG30: =_xlfn.IFNA(VLOOKUP($AZ30,HAVERD!$A:$FM,BG$2,FALSE),"") | BH30: =_xlfn.IFNA(VLOOKUP($AZ30,HAVERD!$A:$FM,BH$2,FALSE),"") | ... CV30: =_xlfn.IFNA(VLOOKUP($AZ30,HAVERD!$A:$FM,CV$2,FALSE),"")
A31: =A14 -> 45680 | B31: =VLOOKUP($A31,HAVERD!$A:$FM,B$2,FALSE) -> 102.75 | C31: =VLOOKUP($A31,HAVERD!$A:$FM,C$2,FALSE) -> 97.05 | D31: =VLOOKUP($A31,HAVERD!$A:$FM,D$2,FALSE) -> 91.55 | E31: =VLOOKUP($A31,HAVERD!$A:$FM,E$2,FALSE) -> 91.45 | F31: =VLOOKUP($A31,HAVERD!$A:$FM,F$2,FALSE) -> 91.15 | G31: =VLOOKUP($A31,HAVERD!$A:$FM,G$2,FALSE) -> 89.6 | H31: =VLOOKUP($A31,HAVERD!$A:$FM,H$2,FALSE) -> 89.55 | I31: =VLOOKUP($A31,HAVERD!$A:$FM,I$2,FALSE) -> 92.25 | ... AW31: =VLOOKUP($A31,HAVERD!$A:$FM,AW$2,FALSE) -> 70.85 | AZ31: =AZ14 -> 45768 | BA31: =_xlfn.IFNA(VLOOKUP($AZ31,HAVERD!$A:$FM,BA$2,FALSE),"") -> 75.4 | BB31: =_xlfn.IFNA(VLOOKUP($AZ31,HAVERD!$A:$FM,BB$2,FALSE),"") -> 75.8 | BC31: =_xlfn.IFNA(VLOOKUP($AZ31,HAVERD!$A:$FM,BC$2,FALSE),"") -> 76.45 | BD31: =_xlfn.IFNA(VLOOKUP($AZ31,HAVERD!$A:$FM,BD$2,FALSE),"") -> 75.05 | BE31: =_xlfn.IFNA(VLOOKUP($AZ31,HAVERD!$A:$FM,BE$2,FALSE),"") -> 81.7 | BF31: =_xlfn.IFNA(VLOOKUP($AZ31,HAVERD!$A:$FM,BF$2,FALSE),"") -> 83.95 | BG31: =_xlfn.IFNA(VLOOKUP($AZ31,HAVERD!$A:$FM,BG$2,FALSE),"") -> 85.5 | BH31: =_xlfn.IFNA(VLOOKUP($AZ31,HAVERD!$A:$FM,BH$2,FALSE),"") -> 86.1 | ... CV31: =_xlfn.IFNA(VLOOKUP($AZ31,HAVERD!$A:$FM,CV$2,FALSE),"") -> 63.95
A32: =A15 -> 45681 | B32: =VLOOKUP($A32,HAVERD!$A:$FM,B$2,FALSE) -> 106.2 | C32: =VLOOKUP($A32,HAVERD!$A:$FM,C$2,FALSE) -> 98.25 | D32: =VLOOKUP($A32,HAVERD!$A:$FM,D$2,FALSE) -> 92.95 | E32: =VLOOKUP($A32,HAVERD!$A:$FM,E$2,FALSE) -> 92.75 | F32: =VLOOKUP($A32,HAVERD!$A:$FM,F$2,FALSE) -> 92.5 | G32: =VLOOKUP($A32,HAVERD!$A:$FM,G$2,FALSE) -> 90.6 | H32: =VLOOKUP($A32,HAVERD!$A:$FM,H$2,FALSE) -> 90.55 | I32: =VLOOKUP($A32,HAVERD!$A:$FM,I$2,FALSE) -> 91.25 | ... AW32: =VLOOKUP($A32,HAVERD!$A:$FM,AW$2,FALSE) -> 72.65 | AZ32: =AZ15 -> 45769 | BA32: =_xlfn.IFNA(VLOOKUP($AZ32,HAVERD!$A:$FM,BA$2,FALSE),"") -> 73.9 | BB32: =_xlfn.IFNA(VLOOKUP($AZ32,HAVERD!$A:$FM,BB$2,FALSE),"") -> 73.7 | BC32: =_xlfn.IFNA(VLOOKUP($AZ32,HAVERD!$A:$FM,BC$2,FALSE),"") -> 73.95 | BD32: =_xlfn.IFNA(VLOOKUP($AZ32,HAVERD!$A:$FM,BD$2,FALSE),"") -> 72.85 | BE32: =_xlfn.IFNA(VLOOKUP($AZ32,HAVERD!$A:$FM,BE$2,FALSE),"") -> 80.2 | BF32: =_xlfn.IFNA(VLOOKUP($AZ32,HAVERD!$A:$FM,BF$2,FALSE),"") -> 81.4 | BG32: =_xlfn.IFNA(VLOOKUP($AZ32,HAVERD!$A:$FM,BG$2,FALSE),"") -> 82.95 | BH32: =_xlfn.IFNA(VLOOKUP($AZ32,HAVERD!$A:$FM,BH$2,FALSE),"") -> 83.55 | ... CV32: =_xlfn.IFNA(VLOOKUP($AZ32,HAVERD!$A:$FM,CV$2,FALSE),"") -> 62.8
A33: =A16 -> 45684 | B33: =VLOOKUP($A33,HAVERD!$A:$FM,B$2,FALSE) -> 102.9 | C33: =VLOOKUP($A33,HAVERD!$A:$FM,C$2,FALSE) -> 94.9 | D33: =VLOOKUP($A33,HAVERD!$A:$FM,D$2,FALSE) -> 89.9 | E33: =VLOOKUP($A33,HAVERD!$A:$FM,E$2,FALSE) -> 89.75 | F33: =VLOOKUP($A33,HAVERD!$A:$FM,F$2,FALSE) -> 89.7 | G33: =VLOOKUP($A33,HAVERD!$A:$FM,G$2,FALSE) -> 88.75 | H33: =VLOOKUP($A33,HAVERD!$A:$FM,H$2,FALSE) -> 88.7 | I33: =VLOOKUP($A33,HAVERD!$A:$FM,I$2,FALSE) -> 89.4 | ... AW33: =VLOOKUP($A33,HAVERD!$A:$FM,AW$2,FALSE) -> 71.25 | AZ33: =AZ16 -> 45770 | BA33: =_xlfn.IFNA(VLOOKUP($AZ33,HAVERD!$A:$FM,BA$2,FALSE),"") -> 74.7 | BB33: =_xlfn.IFNA(VLOOKUP($AZ33,HAVERD!$A:$FM,BB$2,FALSE),"") -> 74.4 | BC33: =_xlfn.IFNA(VLOOKUP($AZ33,HAVERD!$A:$FM,BC$2,FALSE),"") -> 74.7 | BD33: =_xlfn.IFNA(VLOOKUP($AZ33,HAVERD!$A:$FM,BD$2,FALSE),"") -> 73.65 | BE33: =_xlfn.IFNA(VLOOKUP($AZ33,HAVERD!$A:$FM,BE$2,FALSE),"") -> 80.75 | BF33: =_xlfn.IFNA(VLOOKUP($AZ33,HAVERD!$A:$FM,BF$2,FALSE),"") -> 81.75 | BG33: =_xlfn.IFNA(VLOOKUP($AZ33,HAVERD!$A:$FM,BG$2,FALSE),"") -> 83.3 | BH33: =_xlfn.IFNA(VLOOKUP($AZ33,HAVERD!$A:$FM,BH$2,FALSE),"") -> 83.9 | ... CV33: =_xlfn.IFNA(VLOOKUP($AZ33,HAVERD!$A:$FM,CV$2,FALSE),"") -> 63.55
A34: =A17 -> 45685 | B34: =VLOOKUP($A34,HAVERD!$A:$FM,B$2,FALSE) -> 104.3 | C34: =VLOOKUP($A34,HAVERD!$A:$FM,C$2,FALSE) -> 97.15 | D34: =VLOOKUP($A34,HAVERD!$A:$FM,D$2,FALSE) -> 91.05 | E34: =VLOOKUP($A34,HAVERD!$A:$FM,E$2,FALSE) -> 90.85 | F34: =VLOOKUP($A34,HAVERD!$A:$FM,F$2,FALSE) -> 90.8 | G34: =VLOOKUP($A34,HAVERD!$A:$FM,G$2,FALSE) -> 90.1 | H34: =VLOOKUP($A34,HAVERD!$A:$FM,H$2,FALSE) -> 90.05 | I34: =VLOOKUP($A34,HAVERD!$A:$FM,I$2,FALSE) -> 90.75 | ... AW34: =VLOOKUP($A34,HAVERD!$A:$FM,AW$2,FALSE) -> 69.05 | AZ34: =AZ17 -> 45771 | BA34: =_xlfn.IFNA(VLOOKUP($AZ34,HAVERD!$A:$FM,BA$2,FALSE),"") -> 73.75 | BB34: =_xlfn.IFNA(VLOOKUP($AZ34,HAVERD!$A:$FM,BB$2,FALSE),"") -> 73.6 | BC34: =_xlfn.IFNA(VLOOKUP($AZ34,HAVERD!$A:$FM,BC$2,FALSE),"") -> 73.35 | BD34: =_xlfn.IFNA(VLOOKUP($AZ34,HAVERD!$A:$FM,BD$2,FALSE),"") -> 73.15 | BE34: =_xlfn.IFNA(VLOOKUP($AZ34,HAVERD!$A:$FM,BE$2,FALSE),"") -> 79.7 | BF34: =_xlfn.IFNA(VLOOKUP($AZ34,HAVERD!$A:$FM,BF$2,FALSE),"") -> 80.85 | BG34: =_xlfn.IFNA(VLOOKUP($AZ34,HAVERD!$A:$FM,BG$2,FALSE),"") -> 82.4 | BH34: =_xlfn.IFNA(VLOOKUP($AZ34,HAVERD!$A:$FM,BH$2,FALSE),"") -> 83 | ... CV34: =_xlfn.IFNA(VLOOKUP($AZ34,HAVERD!$A:$FM,CV$2,FALSE),"") -> 63.2
... A37: =A20 -> 45688 | B37: =VLOOKUP($A37,HAVERD!$A:$FM,B$2,FALSE) -> 107.15 | C37: =VLOOKUP($A37,HAVERD!$A:$FM,C$2,FALSE) -> 100.05 | D37: =VLOOKUP($A37,HAVERD!$A:$FM,D$2,FALSE) -> 99.6 | E37: =VLOOKUP($A37,HAVERD!$A:$FM,E$2,FALSE) -> 99.6 | F37: =VLOOKUP($A37,HAVERD!$A:$FM,F$2,FALSE) -> 98.6 | G37: =VLOOKUP($A37,HAVERD!$A:$FM,G$2,FALSE) -> 98.55 | H37: =VLOOKUP($A37,HAVERD!$A:$FM,H$2,FALSE) -> 99.25 | I37: =VLOOKUP($A37,HAVERD!$A:$FM,I$2,FALSE) -> 97.7 | ... AW37: =VLOOKUP($A37,HAVERD!$A:$FM,AW$2,FALSE) -> 71.6 | AZ37: =AZ20 -> 45776 | BA37: =_xlfn.IFNA(VLOOKUP($AZ37,HAVERD!$A:$FM,BA$2,FALSE),"") -> 71.1 | BB37: =_xlfn.IFNA(VLOOKUP($AZ37,HAVERD!$A:$FM,BB$2,FALSE),"") -> 71.05 | BC37: =_xlfn.IFNA(VLOOKUP($AZ37,HAVERD!$A:$FM,BC$2,FALSE),"") -> 70.7 | BD37: =_xlfn.IFNA(VLOOKUP($AZ37,HAVERD!$A:$FM,BD$2,FALSE),"") -> 70.85 | BE37: =_xlfn.IFNA(VLOOKUP($AZ37,HAVERD!$A:$FM,BE$2,FALSE),"") -> 75.8 | BF37: =_xlfn.IFNA(VLOOKUP($AZ37,HAVERD!$A:$FM,BF$2,FALSE),"") -> 78.3 | BG37: =_xlfn.IFNA(VLOOKUP($AZ37,HAVERD!$A:$FM,BG$2,FALSE),"") -> 79 | BH37: =_xlfn.IFNA(VLOOKUP($AZ37,HAVERD!$A:$FM,BH$2,FALSE),"") -> 79.75 | ... CV37: =_xlfn.IFNA(VLOOKUP($AZ37,HAVERD!$A:$FM,CV$2,FALSE),"") -> 63.7
A39: Average | AZ39: Average
A40: Month | B40: =MONTH(B20) -> 1 | C40: =MONTH(C20) -> 3 | D40: =MONTH(D20) -> 4 | E40: =MONTH(E20) -> 5 | F40: =MONTH(F20) -> 6 | G40: =MONTH(G20) -> 7 | H40: =MONTH(H20) -> 8 | I40: =MONTH(I20) -> 8 | ... AW40: =MONTH(AW20) -> 12 | AZ40: Month | BA40: =MONTH(BA20) -> 4 | BB40: =MONTH(BB20) -> 5 | BC40: =MONTH(BC20) -> 6 | BD40: =MONTH(BD20) -> 7 | BE40: =MONTH(BE20) -> 8 | BF40: =MONTH(BF20) -> 9 | BG40: =MONTH(BG20) -> 10 | BH40: =MONTH(BH20) -> 11 | ... CV40: =MONTH(CV20) -> 3
A41: Year | B41: =YEAR(B20) -> 2025 | C41: =YEAR(C20) -> 2025 | D41: =YEAR(D20) -> 2025 | E41: =YEAR(E20) -> 2025 | F41: =YEAR(F20) -> 2025 | G41: =YEAR(G20) -> 2025 | H41: =YEAR(H20) -> 2025 | I41: =YEAR(I20) -> 2025 | ... AW41: =YEAR(AW20) -> 2028 | AZ41: Year | BA41: =YEAR(BA20) -> 2025 | BB41: =YEAR(BB20) -> 2025 | BC41: =YEAR(BC20) -> 2025 | BD41: =YEAR(BD20) -> 2025 | BE41: =YEAR(BE20) -> 2025 | BF41: =YEAR(BF20) -> 2025 | BG41: =YEAR(BG20) -> 2025 | BH41: =YEAR(BH20) -> 2025 | ... CV41: =YEAR(CV20) -> 2029
A42: YYYYMM | B42: =B41*100+B40 -> 202501 | C42: =C41*100+C40 -> 202503 | D42: =D41*100+D40 -> 202504 | E42: =E41*100+E40 -> 202505 | F42: =F41*100+F40 -> 202506 | G42: =G41*100+G40 -> 202507 | H42: =H41*100+H40 -> 202508 | I42: =I41*100+I40 -> 202508 | ... AW42: =AW41*100+AW40 -> 202812 | AZ42: YYYYMM | BA42: =BA41*100+BA40 -> 202504 | BB42: =BB41*100+BB40 -> 202505 | BC42: =BC41*100+BC40 -> 202506 | BD42: =BD41*100+BD40 -> 202507 | BE42: =BE41*100+BE40 -> 202508 | BF42: =BF41*100+BF40 -> 202509 | BG42: =BG41*100+BG40 -> 202510 | BH42: =BH41*100+BH40 -> 202511 | ... CV42: =CV41*100+CV40 -> 202903
A43: Quarter | B43: =IF(B40<4,1,IF(B40<7,2,IF(B40<10,3,4))) -> 1 | C43: =IF(C40<4,1,IF(C40<7,2,IF(C40<10,3,4))) -> 1 | D43: =IF(D40<4,1,IF(D40<7,2,IF(D40<10,3,4))) -> 2 | E43: =IF(E40<4,1,IF(E40<7,2,IF(E40<10,3,4))) -> 2 | F43: =IF(F40<4,1,IF(F40<7,2,IF(F40<10,3,4))) -> 2 | G43: =IF(G40<4,1,IF(G40<7,2,IF(G40<10,3,4))) -> 3 | H43: =IF(H40<4,1,IF(H40<7,2,IF(H40<10,3,4))) -> 3 | I43: =IF(I40<4,1,IF(I40<7,2,IF(I40<10,3,4))) -> 3 | ... AW43: =IF(AW40<4,1,IF(AW40<7,2,IF(AW40<10,3,4))) -> 4 | AZ43: Quarter | BA43: =IF(BA40<4,1,IF(BA40<7,2,IF(BA40<10,3,4))) -> 2 | BB43: =IF(BB40<4,1,IF(BB40<7,2,IF(BB40<10,3,4))) -> 2 | BC43: =IF(BC40<4,1,IF(BC40<7,2,IF(BC40<10,3,4))) -> 2 | BD43: =IF(BD40<4,1,IF(BD40<7,2,IF(BD40<10,3,4))) -> 3 | BE43: =IF(BE40<4,1,IF(BE40<7,2,IF(BE40<10,3,4))) -> 3 | BF43: =IF(BF40<4,1,IF(BF40<7,2,IF(BF40<10,3,4))) -> 3 | BG43: =IF(BG40<4,1,IF(BG40<7,2,IF(BG40<10,3,4))) -> 4 | BH43: =IF(BH40<4,1,IF(BH40<7,2,IF(BH40<10,3,4))) -> 4 | ... CV43: =IF(CV40<4,1,IF(CV40<7,2,IF(CV40<10,3,4))) -> 1
A44: YYYYQQ | B44: =B41*100+B43 -> 202501 | C44: =C41*100+C43 -> 202501 | D44: =D41*100+D43 -> 202502 | E44: =E41*100+E43 -> 202502 | F44: =F41*100+F43 -> 202502 | G44: =G41*100+G43 -> 202503 | H44: =H41*100+H43 -> 202503 | I44: =I41*100+I43 -> 202503 | ... AW44: =AW41*100+AW43 -> 202804 | AZ44: YYYYQQ | BA44: =BA41*100+BA43 -> 202502 | BB44: =BB41*100+BB43 -> 202502 | BC44: =BC41*100+BC43 -> 202502 | BD44: =BD41*100+BD43 -> 202503 | BE44: =BE41*100+BE43 -> 202503 | BF44: =BF41*100+BF43 -> 202503 | BG44: =BG41*100+BG43 -> 202504 | BH44: =BH41*100+BH43 -> 202504 | ... CV44: =CV41*100+CV43 -> 202901
A45: Average | B45: =AVERAGE(B23:B37) -> 103.08333 | C45: =AVERAGE(C23:C37) -> 96.483333 | D45: =AVERAGE(D23:D37) -> 91.54 | E45: =AVERAGE(E23:E37) -> 90.566667 | F45: =AVERAGE(F23:F37) -> 90.003333 | G45: =AVERAGE(G23:G37) -> 89.346667 | H45: =AVERAGE(H23:H37) -> 89.346667 | I45: =AVERAGE(I23:I37) -> 91.096667 | ... AW45: =AVERAGE(AW23:AW37) -> 71.39 | AZ45: Average | BA45: =AVERAGE(BA23:BA37) -> 72.867857 | BB45: =AVERAGE(BB23:BB37) -> 72.964286 | BC45: =AVERAGE(BC23:BC37) -> 73.532143 | BD45: =AVERAGE(BD23:BD37) -> 72.55 | BE45: =AVERAGE(BE23:BE37) -> 79.575 | BF45: =AVERAGE(BF23:BF37) -> 81.125 | BG45: =AVERAGE(BG23:BG37) -> 82.55 | BH45: =AVERAGE(BH23:BH37) -> 83.164286 | ... CV45: =AVERAGE(CV23:CV37) -> 63.671429
A47: Quarterly series | AZ47: Quarterly series
B48: =B44 -> 202501 | C48: =IF(RIGHT(B48)="4",B48+97,B48+1) -> 202502 | D48: =IF(RIGHT(C48)="4",C48+97,C48+1) -> 202503 | E48: =IF(RIGHT(D48)="4",D48+97,D48+1) -> 202504 | F48: =IF(RIGHT(E48)="4",E48+97,E48+1) -> 202601 | G48: =IF(RIGHT(F48)="4",F48+97,F48+1) -> 202602 | H48: =IF(RIGHT(G48)="4",G48+97,G48+1) -> 202603 | I48: =IF(RIGHT(H48)="4",H48+97,H48+1) -> 202604 | J48: =IF(RIGHT(I48)="4",I48+97,I48+1) -> 202701 | ... R48: =IF(RIGHT(Q48)="4",Q48+97,Q48+1) -> 202901 | BA48: =BA44 -> 202502 | BB48: =IF(RIGHT(BA48)="4",BA48+97,BA48+1) -> 202503 | BC48: =IF(RIGHT(BB48)="4",BB48+97,BB48+1) -> 202504 | BD48: =IF(RIGHT(BC48)="4",BC48+97,BC48+1) -> 202601 | BE48: =IF(RIGHT(BD48)="4",BD48+97,BD48+1) -> 202602 | BF48: =IF(RIGHT(BE48)="4",BE48+97,BE48+1) -> 202603 | BG48: =IF(RIGHT(BF48)="4",BF48+97,BF48+1) -> 202604 | BH48: =IF(RIGHT(BG48)="4",BG48+97,BG48+1) -> 202701 | BI48: =IF(RIGHT(BH48)="4",BH48+97,BH48+1) -> 202702 | ... BP48: =IF(RIGHT(BO48)="4",BO48+97,BO48+1) -> 202901
A49: =A1 -> February 2025 MPR | B49: =AVERAGEIF($B$44:$AW$44,B48,$B$45:$AW$45) -> 99.783333 | C49: =AVERAGEIF($B$44:$AW$44,C48,$B$45:$AW$45) -> 90.703333 | D49: =AVERAGEIF($B$44:$AW$44,D48,$B$45:$AW$45) -> 89.93 | E49: =AVERAGEIF($B$44:$AW$44,E48,$B$45:$AW$45) -> 93.234167 | F49: =AVERAGEIF($B$44:$AW$44,F48,$B$45:$AW$45) -> 93.181667 | G49: =AVERAGEIF($B$44:$AW$44,G48,$B$45:$AW$45) -> 72.727778 | H49: =AVERAGEIF($B$44:$AW$44,H48,$B$45:$AW$45) -> 71.925556 | I49: =AVERAGEIF($B$44:$AW$44,I48,$B$45:$AW$45) -> 80.829167 | ... R49: =AVERAGEIF($B$44:$AW$44,R48,$B$45:$AW$45) -> #DIV/0! | AZ49: =AZ1 -> May 2025 MPR | BA49: =AVERAGEIF($BA$44:$CV$44,BA48,$BA$45:$CV$45) -> 73.121429 | BB49: =AVERAGEIF($BA$44:$CV$44,BB48,$BA$45:$CV$45) -> 77.75 | BC49: =AVERAGEIF($BA$44:$CV$44,BC48,$BA$45:$CV$45) -> 83.453571 | BD49: =AVERAGEIF($BA$44:$CV$44,BD48,$BA$45:$CV$45) -> 78.884524 | BE49: =AVERAGEIF($BA$44:$CV$44,BE48,$BA$45:$CV$45) -> 68.545238 | BF49: =AVERAGEIF($BA$44:$CV$44,BF48,$BA$45:$CV$45) -> 71.313095 | BG49: =AVERAGEIF($BA$44:$CV$44,BG48,$BA$45:$CV$45) -> 78.695238 | BH49: =AVERAGEIF($BA$44:$CV$44,BH48,$BA$45:$CV$45) -> 72.603571 | ... BP49: =AVERAGEIF($BA$44:$CV$44,BP48,$BA$45:$CV$45) -> 68.414286
AZ51: Comparison - monthly
BA52: 44927 | BB52: 44958 | BC52: 44986 | BD52: 45017 | BE52: 45047 | BF52: 45078 | BG52: 45108 | BH52: 45139 | BI52: 45170 | BJ52: 45200 | BK52: 45231 | BL52: 45261 | BM52: 45292 | BN52: 45323 | BO52: 45352 | BP52: 45383 | BQ52: 45413 | BR52: 45444 | BS52: 45474 | BT52: 45505 | BU52: 45536 | BV52: 45566 | BW52: 45597 | BX52: 45627 | BY52: 45658 | BZ52: 45689 | CA52: 45717 | CB52: 45748 | CC52: 45778 | CD52: 45809 | CE52: 45839 | CF52: 45870 | CG52: 45901 | CH52: 45931 | CI52: 45962 | CJ52: 45992 | CK52: 46023 | CL52: 46054 | CM52: 46082 | CN52: 46113 | CO52: 46143 | CP52: 46174 | CQ52: 46204 | CR52: 46235 | CS52: 46266 | CT52: 46296 | CU52: 46327 | CV52: 46357 | CW52: 46388 | CX52: 46419 | CY52: 46447 | CZ52: 46478 | DA52: 46508 | DB52: 46539 | DC52: 46569 | DD52: 46600 | DE52: 46631 | DF52: 46661 | DG52: 46692 | DH52: 46722
BA53: =MONTH(BA52) -> 1 | BB53: =MONTH(BB52) -> 2 | BC53: =MONTH(BC52) -> 3 | BD53: =MONTH(BD52) -> 4 | BE53: =MONTH(BE52) -> 5 | BF53: =MONTH(BF52) -> 6 | BG53: =MONTH(BG52) -> 7 | BH53: =MONTH(BH52) -> 8 | ... DH53: =MONTH(DH52) -> 12
BA54: 202301 | BB54: =IF(BB53=1,BA54+89,BA54+1) -> 202302 | BC54: =IF(BC53=1,BB54+89,BB54+1) -> 202303 | BD54: =IF(BD53=1,BC54+89,BC54+1) -> 202304 | BE54: =IF(BE53=1,BD54+89,BD54+1) -> 202305 | BF54: =IF(BF53=1,BE54+89,BE54+1) -> 202306 | BG54: =IF(BG53=1,BF54+89,BF54+1) -> 202307 | BH54: =IF(BH53=1,BG54+89,BG54+1) -> 202308 | BI54: =IF(BI53=1,BH54+89,BH54+1) -> 202309 | ... DH54: =IF(DH53=1,DG54+89,DG54+1) -> 202712
AZ55: =A49 -> February 2025 MPR | BA55: =HLOOKUP(BA$54,$B$42:$AW$45,4,FALSE) -> #N/A | BB55: =HLOOKUP(BB$54,$B$42:$AW$45,4,FALSE) -> #N/A | BC55: =HLOOKUP(BC$54,$B$42:$AW$45,4,FALSE) -> #N/A | BD55: =HLOOKUP(BD$54,$B$42:$AW$45,4,FALSE) -> #N/A | BE55: =HLOOKUP(BE$54,$B$42:$AW$45,4,FALSE) -> #N/A | BF55: =HLOOKUP(BF$54,$B$42:$AW$45,4,FALSE) -> #N/A | BG55: =HLOOKUP(BG$54,$B$42:$AW$45,4,FALSE) -> #N/A | BH55: =HLOOKUP(BH$54,$B$42:$AW$45,4,FALSE) -> #N/A | ... DH55: =HLOOKUP(DH$54,$B$42:$AW$45,4,FALSE) -> 73.62
AZ56: =AZ49 -> May 2025 MPR | BA56: =HLOOKUP(BA$54,$BA$42:$CV$45,4,FALSE) -> #N/A | BB56: =HLOOKUP(BB$54,$BA$42:$CV$45,4,FALSE) -> #N/A | BC56: =HLOOKUP(BC$54,$BA$42:$CV$45,4,FALSE) -> #N/A | BD56: =HLOOKUP(BD$54,$BA$42:$CV$45,4,FALSE) -> #N/A | BE56: =HLOOKUP(BE$54,$BA$42:$CV$45,4,FALSE) -> #N/A | BF56: =HLOOKUP(BF$54,$BA$42:$CV$45,4,FALSE) -> #N/A | BG56: =HLOOKUP(BG$54,$BA$42:$CV$45,4,FALSE) -> #N/A | BH56: =HLOOKUP(BH$54,$BA$42:$CV$45,4,FALSE) -> #N/A | ... DH56: =HLOOKUP(DH$54,$BA$42:$CV$45,4,FALSE) -> 73.696429
AZ57: Difference | BP57: =BP56-BP55 -> #N/A | BQ57: =BQ56-BQ55 -> #N/A | BR57: =BR56-BR55 -> #N/A | BS57: =BS56-BS55 -> #N/A | BT57: =BT56-BT55 -> #N/A | BU57: =BU56-BU55 -> #N/A | BV57: =BV56-BV55 -> #N/A | BW57: =BW56-BW55 -> #N/A | ... DH57: =DH56-DH55 -> 0.076428571
AZ58: Next 3 years | DB58: =AVERAGE(BV57:DB57) -> #N/A
AZ60: Comparison - quarterly
BA61: 44927 | BB61: 45017 | BC61: 45108 | BD61: 45200 | BE61: 45292 | BF61: 45383 | BG61: 45474 | BH61: 45566 | BI61: 45658 | BJ61: 45748 | BK61: 45839 | BL61: 45931 | BM61: 46023 | BN61: 46113 | BO61: 46204 | BP61: 46296 | BQ61: 46388 | BR61: 46478 | BS61: 46569 | BT61: 46661
BA62: 202301 | BB62: =IF(RIGHT(BA62)="4",BA62+97,BA62+1) -> 202302 | BC62: =IF(RIGHT(BB62)="4",BB62+97,BB62+1) -> 202303 | BD62: =IF(RIGHT(BC62)="4",BC62+97,BC62+1) -> 202304 | BE62: =IF(RIGHT(BD62)="4",BD62+97,BD62+1) -> 202401 | BF62: =IF(RIGHT(BE62)="4",BE62+97,BE62+1) -> 202402 | BG62: =IF(RIGHT(BF62)="4",BF62+97,BF62+1) -> 202403 | BH62: =IF(RIGHT(BG62)="4",BG62+97,BG62+1) -> 202404 | BI62: =IF(RIGHT(BH62)="4",BH62+97,BH62+1) -> 202501 | ... BT62: =IF(RIGHT(BS62)="4",BS62+97,BS62+1) -> 202704
AZ63: =A49 -> February 2025 MPR | BA63: =HLOOKUP(BA$62,$B$48:$R$49,2,FALSE) -> #N/A | BB63: =HLOOKUP(BB$62,$B$48:$R$49,2,FALSE) -> #N/A | BC63: =HLOOKUP(BC$62,$B$48:$R$49,2,FALSE) -> #N/A | BD63: =HLOOKUP(BD$62,$B$48:$R$49,2,FALSE) -> #N/A | BE63: =HLOOKUP(BE$62,$B$48:$R$49,2,FALSE) -> #N/A | BF63: =HLOOKUP(BF$62,$B$48:$R$49,2,FALSE) -> #N/A | BG63: =HLOOKUP(BG$62,$B$48:$R$49,2,FALSE) -> #N/A | BH63: =HLOOKUP(BH$62,$B$48:$R$49,2,FALSE) -> #N/A | ... BT63: =HLOOKUP(BT$62,$B$48:$R$49,2,FALSE) -> 72.9775
AZ64: =AZ49 -> May 2025 MPR | BA64: =HLOOKUP(BA$62,$BA$48:$BQ$49,2,FALSE) -> #N/A | BB64: =HLOOKUP(BB$62,$BA$48:$BQ$49,2,FALSE) -> #N/A | BC64: =HLOOKUP(BC$62,$BA$48:$BQ$49,2,FALSE) -> #N/A | BD64: =HLOOKUP(BD$62,$BA$48:$BQ$49,2,FALSE) -> #N/A | BE64: =HLOOKUP(BE$62,$BA$48:$BQ$49,2,FALSE) -> #N/A | BF64: =HLOOKUP(BF$62,$BA$48:$BQ$49,2,FALSE) -> #N/A | BG64: =HLOOKUP(BG$62,$BA$48:$BQ$49,2,FALSE) -> #N/A | BH64: =HLOOKUP(BH$62,$BA$48:$BQ$49,2,FALSE) -> #N/A | ... BT64: =HLOOKUP(BT$62,$BA$48:$BQ$49,2,FALSE) -> 73.667857
AZ65: Difference | BG65: =BG64-BG63 -> #N/A | BH65: =BH64-BH63 -> #N/A | BI65: =BI64-BI63 -> #N/A | BJ65: =BJ64-BJ63 -> -17.581905 | BK65: =BK64-BK63 -> -12.18 | BL65: =BL64-BL63 -> -9.7805952 | BM65: =BM64-BM63 -> -14.297143 | BN65: =BN64-BN63 -> -4.1825397 | ... BT65: =BT64-BT63 -> 0.69035714
AZ66: Next 3 years | BR66: =AVERAGE(BG65:BR65) -> #N/A

Sheet Market expectations - Oil
A1: ='Market pricing dates'!A2 -> February 2025 MPR | C1: ='Market pricing dates'!A12 -> 15 working days to 31 Jan 2025 | N1: ='Market pricing dates'!D2 -> May 2025 MPR | P1: ='Market pricing dates'!D12 -> 15 working days to 29 Apr 2025
A2: Column # | B2: =HAVERD!FX$1 -> 180 | C2: =+B2+1 -> 181 | D2: =+C2+1 -> 182 | E2: =+D2+1 -> 183 | F2: =+E2+1 -> 184 | N2: Column # | O2: =HAVERD!FX$1 -> 180 | P2: =HAVERD!FY$1 -> 181 | Q2: =HAVERD!FZ$1 -> 182 | R2: =HAVERD!GA$1 -> 183 | S2: =HAVERD!GB$1 -> 184
A3: Months | B3: =HAVERD!FX$2 -> Oil - 1 | C3: =HAVERD!FY$2 -> Oil - 3 | D3: =HAVERD!FZ$2 -> Oil - 6 | E3: =HAVERD!GA$2 -> Oil - 12 | F3: =HAVERD!GB$2 -> Oil - 24 | N3: Months | O3: =HAVERD!FX$2 -> Oil - 1 | P3: =HAVERD!FY$2 -> Oil - 3 | Q3: =HAVERD!FZ$2 -> Oil - 6 | R3: =HAVERD!GA$2 -> Oil - 12 | S3: =HAVERD!GB$2 -> Oil - 24
A4: Days | C4: =365/4 -> 91.25 | D4: =365/2 -> 182.5 | E4: 365 | F4: =365*2 -> 730 | N4: Days | P4: =365/4 -> 91.25 | Q4: =365/2 -> 182.5 | R4: 365 | S4: =365*2 -> 730
A5: Dates | N5: Dates
A6: =A11-7 -> 45670 | B6: =A6 -> 45670 | C6: =$B6+C$4 -> 45761.25 | D6: =$B6+D$4 -> 45852.5 | E6: =$B6+E$4 -> 46035 | F6: =$B6+F$4 -> 46400 | N6: =N11-7 -> 45756 | O6: =N6 -> 45756 | P6: =$N6+P$4 -> 45847.25 | Q6: =$N6+Q$4 -> 45938.5 | R6: =$N6+R$4 -> 46121 | S6: =$N6+S$4 -> 46486
A7: =A12-7 -> 45671 | B7: =A7 -> 45671 | C7: =$B7+C$4 -> 45762.25 | D7: =$B7+D$4 -> 45853.5 | E7: =$B7+E$4 -> 46036 | F7: =$B7+F$4 -> 46401 | N7: =N12-7 -> 45757 | O7: =N7 -> 45757 | P7: =$N7+P$4 -> 45848.25 | Q7: =$N7+Q$4 -> 45939.5 | R7: =$N7+R$4 -> 46122 | S7: =$N7+S$4 -> 46487
A8: =A13-7 -> 45672 | B8: =A8 -> 45672 | C8: =$B8+C$4 -> 45763.25 | D8: =$B8+D$4 -> 45854.5 | E8: =$B8+E$4 -> 46037 | F8: =$B8+F$4 -> 46402 | N8: =N13-7 -> 45758 | O8: =N8 -> 45758 | P8: =$N8+P$4 -> 45849.25 | Q8: =$N8+Q$4 -> 45940.5 | R8: =$N8+R$4 -> 46123 | S8: =$N8+S$4 -> 46488
A9: =A14-7 -> 45673 | B9: =A9 -> 45673 | C9: =$B9+C$4 -> 45764.25 | D9: =$B9+D$4 -> 45855.5 | E9: =$B9+E$4 -> 46038 | F9: =$B9+F$4 -> 46403 | N9: =N14-7 -> 45761 | O9: =N9 -> 45761 | P9: =$N9+P$4 -> 45852.25 | Q9: =$N9+Q$4 -> 45943.5 | R9: =$N9+R$4 -> 46126 | S9: =$N9+S$4 -> 46491
A10: =A15-7 -> 45674 | B10: =A10 -> 45674 | C10: =$B10+C$4 -> 45765.25 | D10: =$B10+D$4 -> 45856.5 | E10: =$B10+E$4 -> 46039 | F10: =$B10+F$4 -> 46404 | N10: =N15-7 -> 45762 | O10: =N10 -> 45762 | P10: =$N10+P$4 -> 45853.25 | Q10: =$N10+Q$4 -> 45944.5 | R10: =$N10+R$4 -> 46127 | S10: =$N10+S$4 -> 46492
A11: =A16-7 -> 45677 | B11: =A11 -> 45677 | C11: =$B11+C$4 -> 45768.25 | D11: =$B11+D$4 -> 45859.5 | E11: =$B11+E$4 -> 46042 | F11: =$B11+F$4 -> 46407 | N11: =N16-7 -> 45763 | O11: =N11 -> 45763 | P11: =$N11+P$4 -> 45854.25 | Q11: =$N11+Q$4 -> 45945.5 | R11: =$N11+R$4 -> 46128 | S11: =$N11+S$4 -> 46493
A12: =A17-7 -> 45678 | B12: =A12 -> 45678 | C12: =$B12+C$4 -> 45769.25 | D12: =$B12+D$4 -> 45860.5 | E12: =$B12+E$4 -> 46043 | F12: =$B12+F$4 -> 46408 | N12: =N17-7 -> 45764 | O12: =N12 -> 45764 | P12: =$N12+P$4 -> 45855.25 | Q12: =$N12+Q$4 -> 45946.5 | R12: =$N12+R$4 -> 46129 | S12: =$N12+S$4 -> 46494
A13: =A18-7 -> 45679 | B13: =A13 -> 45679 | C13: =$B13+C$4 -> 45770.25 | D13: =$B13+D$4 -> 45861.5 | E13: =$B13+E$4 -> 46044 | F13: =$B13+F$4 -> 46409 | N13: =N18-7 -> 45765 | O13: =N13 -> 45765 | P13: =$N13+P$4 -> 45856.25 | Q13: =$N13+Q$4 -> 45947.5 | R13: =$N13+R$4 -> 46130 | S13: =$N13+S$4 -> 46495
A14: =A19-7 -> 45680 | B14: =A14 -> 45680 | C14: =$B14+C$4 -> 45771.25 | D14: =$B14+D$4 -> 45862.5 | E14: =$B14+E$4 -> 46045 | F14: =$B14+F$4 -> 46410 | N14: =N19-7 -> 45768 | O14: =N14 -> 45768 | P14: =$N14+P$4 -> 45859.25 | Q14: =$N14+Q$4 -> 45950.5 | R14: =$N14+R$4 -> 46133 | S14: =$N14+S$4 -> 46498
A15: =A20-7 -> 45681 | B15: =A15 -> 45681 | C15: =$B15+C$4 -> 45772.25 | D15: =$B15+D$4 -> 45863.5 | E15: =$B15+E$4 -> 46046 | F15: =$B15+F$4 -> 46411 | N15: =N20-7 -> 45769 | O15: =N15 -> 45769 | P15: =$N15+P$4 -> 45860.25 | Q15: =$N15+Q$4 -> 45951.5 | R15: =$N15+R$4 -> 46134 | S15: =$N15+S$4 -> 46499
A16: ='Market pricing dates'!B5 -> 45684 | B16: =A16 -> 45684 | C16: =$B16+C$4 -> 45775.25 | D16: =$B16+D$4 -> 45866.5 | E16: =$B16+E$4 -> 46049 | F16: =$B16+F$4 -> 46414 | N16: ='Market pricing dates'!E5 -> 45770 | O16: =N16 -> 45770 | P16: =$N16+P$4 -> 45861.25 | Q16: =$N16+Q$4 -> 45952.5 | R16: =$N16+R$4 -> 46135 | S16: =$N16+S$4 -> 46500
A17: ='Market pricing dates'!B6 -> 45685 | B17: =A17 -> 45685 | C17: =$B17+C$4 -> 45776.25 | D17: =$B17+D$4 -> 45867.5 | E17: =$B17+E$4 -> 46050 | F17: =$B17+F$4 -> 46415 | N17: ='Market pricing dates'!E6 -> 45771 | O17: =N17 -> 45771 | P17: =$N17+P$4 -> 45862.25 | Q17: =$N17+Q$4 -> 45953.5 | R17: =$N17+R$4 -> 46136 | S17: =$N17+S$4 -> 46501
A18: ='Market pricing dates'!B7 -> 45686 | B18: =A18 -> 45686 | C18: =$B18+C$4 -> 45777.25 | D18: =$B18+D$4 -> 45868.5 | E18: =$B18+E$4 -> 46051 | F18: =$B18+F$4 -> 46416 | N18: ='Market pricing dates'!E7 -> 45772 | O18: =N18 -> 45772 | P18: =$N18+P$4 -> 45863.25 | Q18: =$N18+Q$4 -> 45954.5 | R18: =$N18+R$4 -> 46137 | S18: =$N18+S$4 -> 46502
A19: ='Market pricing dates'!B8 -> 45687 | B19: =A19 -> 45687 | C19: =$B19+C$4 -> 45778.25 | D19: =$B19+D$4 -> 45869.5 | E19: =$B19+E$4 -> 46052 | F19: =$B19+F$4 -> 46417 | N19: ='Market pricing dates'!E8 -> 45775 | O19: =N19 -> 45775 | P19: =$N19+P$4 -> 45866.25 | Q19: =$N19+Q$4 -> 45957.5 | R19: =$N19+R$4 -> 46140 | S19: =$N19+S$4 -> 46505
A20: ='Market pricing dates'!B9 -> 45688 | B20: =A20 -> 45688 | C20: =$B20+C$4 -> 45779.25 | D20: =$B20+D$4 -> 45870.5 | E20: =$B20+E$4 -> 46053 | F20: =$B20+F$4 -> 46418 | N20: ='Market pricing dates'!E9 -> 45776 | O20: =N20 -> 45776 | P20: =$N20+P$4 -> 45867.25 | Q20: =$N20+Q$4 -> 45958.5 | R20: =$N20+R$4 -> 46141 | S20: =$N20+S$4 -> 46506
A22: Oil futures | N22: Oil futures
A23: =A6 -> 45670 | B23: =VLOOKUP($A23,HAVERD!$A:$GB,B$2,FALSE) -> 81.01 | C23: =VLOOKUP($A23,HAVERD!$A:$GB,C$2,FALSE) -> 78.52 | D23: =VLOOKUP($A23,HAVERD!$A:$GB,D$2,FALSE) -> 76.11 | E23: =VLOOKUP($A23,HAVERD!$A:$GB,E$2,FALSE) -> 73.13 | F23: =VLOOKUP($A23,HAVERD!$A:$GB,F$2,FALSE) -> 70.38 | N23: =N6 -> 45756 | O23: =_xlfn.IFNA(VLOOKUP($N23,HAVERD!$A:$GB,O$2,FALSE),"") -> 65.48 | P23: =_xlfn.IFNA(VLOOKUP($N23,HAVERD!$A:$GB,P$2,FALSE),"") -> 64.39 | Q23: =_xlfn.IFNA(VLOOKUP($N23,HAVERD!$A:$GB,Q$2,FALSE),"") -> 63.52 | R23: =_xlfn.IFNA(VLOOKUP($N23,HAVERD!$A:$GB,R$2,FALSE),"") -> 63.19 | S23: =_xlfn.IFNA(VLOOKUP($N23,HAVERD!$A:$GB,S$2,FALSE),"") -> 64.01
A24: =A7 -> 45671 | B24: =VLOOKUP($A24,HAVERD!$A:$GB,B$2,FALSE) -> 79.92 | C24: =VLOOKUP($A24,HAVERD!$A:$GB,C$2,FALSE) -> 77.93 | D24: =VLOOKUP($A24,HAVERD!$A:$GB,D$2,FALSE) -> 75.88 | E24: =VLOOKUP($A24,HAVERD!$A:$GB,E$2,FALSE) -> 73.26 | F24: =VLOOKUP($A24,HAVERD!$A:$GB,F$2,FALSE) -> 70.78 | N24: =N7 -> 45757 | O24: =_xlfn.IFNA(VLOOKUP($N24,HAVERD!$A:$GB,O$2,FALSE),"") -> 63.33 | P24: =_xlfn.IFNA(VLOOKUP($N24,HAVERD!$A:$GB,P$2,FALSE),"") -> 62.36 | Q24: =_xlfn.IFNA(VLOOKUP($N24,HAVERD!$A:$GB,Q$2,FALSE),"") -> 61.85 | R24: =_xlfn.IFNA(VLOOKUP($N24,HAVERD!$A:$GB,R$2,FALSE),"") -> 61.97 | S24: =_xlfn.IFNA(VLOOKUP($N24,HAVERD!$A:$GB,S$2,FALSE),"") -> 63.13
A25: =A8 -> 45672 | B25: =VLOOKUP($A25,HAVERD!$A:$GB,B$2,FALSE) -> 82.03 | C25: =VLOOKUP($A25,HAVERD!$A:$GB,C$2,FALSE) -> 79.48 | D25: =VLOOKUP($A25,HAVERD!$A:$GB,D$2,FALSE) -> 76.98 | E25: =VLOOKUP($A25,HAVERD!$A:$GB,E$2,FALSE) -> 73.93 | F25: =VLOOKUP($A25,HAVERD!$A:$GB,F$2,FALSE) -> 71.2 | N25: =N8 -> 45758 | O25: =_xlfn.IFNA(VLOOKUP($N25,HAVERD!$A:$GB,O$2,FALSE),"") -> 64.76 | P25: =_xlfn.IFNA(VLOOKUP($N25,HAVERD!$A:$GB,P$2,FALSE),"") -> 63.42 | Q25: =_xlfn.IFNA(VLOOKUP($N25,HAVERD!$A:$GB,Q$2,FALSE),"") -> 62.61 | R25: =_xlfn.IFNA(VLOOKUP($N25,HAVERD!$A:$GB,R$2,FALSE),"") -> 62.52 | S25: =_xlfn.IFNA(VLOOKUP($N25,HAVERD!$A:$GB,S$2,FALSE),"") -> 63.42
A26: =A9 -> 45673 | B26: =VLOOKUP($A26,HAVERD!$A:$GB,B$2,FALSE) -> 81.29 | C26: =VLOOKUP($A26,HAVERD!$A:$GB,C$2,FALSE) -> 78.72 | D26: =VLOOKUP($A26,HAVERD!$A:$GB,D$2,FALSE) -> 76.24 | E26: =VLOOKUP($A26,HAVERD!$A:$GB,E$2,FALSE) -> 73.23 | F26: =VLOOKUP($A26,HAVERD!$A:$GB,F$2,FALSE) -> 70.66 | N26: =N9 -> 45761 | O26: =_xlfn.IFNA(VLOOKUP($N26,HAVERD!$A:$GB,O$2,FALSE),"") -> 64.88 | P26: =_xlfn.IFNA(VLOOKUP($N26,HAVERD!$A:$GB,P$2,FALSE),"") -> 63.7 | Q26: =_xlfn.IFNA(VLOOKUP($N26,HAVERD!$A:$GB,Q$2,FALSE),"") -> 63 | R26: =_xlfn.IFNA(VLOOKUP($N26,HAVERD!$A:$GB,R$2,FALSE),"") -> 63.01 | S26: =_xlfn.IFNA(VLOOKUP($N26,HAVERD!$A:$GB,S$2,FALSE),"") -> 63.99
A27: =A10 -> 45674 | B27: =VLOOKUP($A27,HAVERD!$A:$GB,B$2,FALSE) -> 80.79 | C27: =VLOOKUP($A27,HAVERD!$A:$GB,C$2,FALSE) -> 78.43 | D27: =VLOOKUP($A27,HAVERD!$A:$GB,D$2,FALSE) -> 75.98 | E27: =VLOOKUP($A27,HAVERD!$A:$GB,E$2,FALSE) -> 73 | F27: =VLOOKUP($A27,HAVERD!$A:$GB,F$2,FALSE) -> 70.53 | N27: =N10 -> 45762 | O27: =_xlfn.IFNA(VLOOKUP($N27,HAVERD!$A:$GB,O$2,FALSE),"") -> 64.67 | P27: =_xlfn.IFNA(VLOOKUP($N27,HAVERD!$A:$GB,P$2,FALSE),"") -> 63.31 | Q27: =_xlfn.IFNA(VLOOKUP($N27,HAVERD!$A:$GB,Q$2,FALSE),"") -> 62.55 | R27: =_xlfn.IFNA(VLOOKUP($N27,HAVERD!$A:$GB,R$2,FALSE),"") -> 62.56 | S27: =_xlfn.IFNA(VLOOKUP($N27,HAVERD!$A:$GB,S$2,FALSE),"") -> 63.63
A28: =A11 -> 45677 | B28: =VLOOKUP($A28,HAVERD!$A:$GB,B$2,FALSE) -> 80.15 | C28: =VLOOKUP($A28,HAVERD!$A:$GB,C$2,FALSE) -> 78.13 | D28: =VLOOKUP($A28,HAVERD!$A:$GB,D$2,FALSE) -> 75.91 | E28: =VLOOKUP($A28,HAVERD!$A:$GB,E$2,FALSE) -> 73.16 | F28: =VLOOKUP($A28,HAVERD!$A:$GB,F$2,FALSE) -> 70.89 | N28: =N11 -> 45763 | O28: =_xlfn.IFNA(VLOOKUP($N28,HAVERD!$A:$GB,O$2,FALSE),"") -> 65.85 | P28: =_xlfn.IFNA(VLOOKUP($N28,HAVERD!$A:$GB,P$2,FALSE),"") -> 64.32 | Q28: =_xlfn.IFNA(VLOOKUP($N28,HAVERD!$A:$GB,Q$2,FALSE),"") -> 63.35 | R28: =_xlfn.IFNA(VLOOKUP($N28,HAVERD!$A:$GB,R$2,FALSE),"") -> 63.18 | S28: =_xlfn.IFNA(VLOOKUP($N28,HAVERD!$A:$GB,S$2,FALSE),"") -> 64
A29: =A12 -> 45678 | B29: =VLOOKUP($A29,HAVERD!$A:$GB,B$2,FALSE) -> 79.29 | C29: =VLOOKUP($A29,HAVERD!$A:$GB,C$2,FALSE) -> 77.58 | D29: =VLOOKUP($A29,HAVERD!$A:$GB,D$2,FALSE) -> 75.58 | E29: =VLOOKUP($A29,HAVERD!$A:$GB,E$2,FALSE) -> 72.91 | F29: =VLOOKUP($A29,HAVERD!$A:$GB,F$2,FALSE) -> 70.61 | N29: =N12 -> 45764 | O29: =_xlfn.IFNA(VLOOKUP($N29,HAVERD!$A:$GB,O$2,FALSE),"") -> 67.96 | P29: =_xlfn.IFNA(VLOOKUP($N29,HAVERD!$A:$GB,P$2,FALSE),"") -> 66.33 | Q29: =_xlfn.IFNA(VLOOKUP($N29,HAVERD!$A:$GB,Q$2,FALSE),"") -> 65.28 | R29: =_xlfn.IFNA(VLOOKUP($N29,HAVERD!$A:$GB,R$2,FALSE),"") -> 64.89 | S29: =_xlfn.IFNA(VLOOKUP($N29,HAVERD!$A:$GB,S$2,FALSE),"") -> 65.39
A30: =A13 -> 45679 | B30: =VLOOKUP($A30,HAVERD!$A:$GB,B$2,FALSE) -> 79 | C30: =VLOOKUP($A30,HAVERD!$A:$GB,C$2,FALSE) -> 77.37 | D30: =VLOOKUP($A30,HAVERD!$A:$GB,D$2,FALSE) -> 75.53 | E30: =VLOOKUP($A30,HAVERD!$A:$GB,E$2,FALSE) -> 72.98 | F30: =VLOOKUP($A30,HAVERD!$A:$GB,F$2,FALSE) -> 70.59 | N30: =N13 -> 45765 | O30: =_xlfn.IFNA(VLOOKUP($N30,HAVERD!$A:$GB,O$2,FALSE),"") | P30: =_xlfn.IFNA(VLOOKUP($N30,HAVERD!$A:$GB,P$2,FALSE),"") | Q30: =_xlfn.IFNA(VLOOKUP($N30,HAVERD!$A:$GB,Q$2,FALSE),"") | R30: =_xlfn.IFNA(VLOOKUP($N30,HAVERD!$A:$GB,R$2,FALSE),"") | S30: =_xlfn.IFNA(VLOOKUP($N30,HAVERD!$A:$GB,S$2,FALSE),"")
A31: =A14 -> 45680 | B31: =VLOOKUP($A31,HAVERD!$A:$GB,B$2,FALSE) -> 78.29 | C31: =VLOOKUP($A31,HAVERD!$A:$GB,C$2,FALSE) -> 76.91 | D31: =VLOOKUP($A31,HAVERD!$A:$GB,D$2,FALSE) -> 75.26 | E31: =VLOOKUP($A31,HAVERD!$A:$GB,E$2,FALSE) -> 72.86 | F31: =VLOOKUP($A31,HAVERD!$A:$GB,F$2,FALSE) -> 70.6 | N31: =N14 -> 45768 | O31: =_xlfn.IFNA(VLOOKUP($N31,HAVERD!$A:$GB,O$2,FALSE),"") -> 66.26 | P31: =_xlfn.IFNA(VLOOKUP($N31,HAVERD!$A:$GB,P$2,FALSE),"") -> 64.63 | Q31: =_xlfn.IFNA(VLOOKUP($N31,HAVERD!$A:$GB,Q$2,FALSE),"") -> 63.65 | R31: =_xlfn.IFNA(VLOOKUP($N31,HAVERD!$A:$GB,R$2,FALSE),"") -> 63.44 | S31: =_xlfn.IFNA(VLOOKUP($N31,HAVERD!$A:$GB,S$2,FALSE),"") -> 64.23
A32: =A15 -> 45681 | B32: =VLOOKUP($A32,HAVERD!$A:$GB,B$2,FALSE) -> 78.5 | C32: =VLOOKUP($A32,HAVERD!$A:$GB,C$2,FALSE) -> 76.79 | D32: =VLOOKUP($A32,HAVERD!$A:$GB,D$2,FALSE) -> 75.05 | E32: =VLOOKUP($A32,HAVERD!$A:$GB,E$2,FALSE) -> 72.61 | F32: =VLOOKUP($A32,HAVERD!$A:$GB,F$2,FALSE) -> 70.33 | N32: =N15 -> 45769 | O32: =_xlfn.IFNA(VLOOKUP($N32,HAVERD!$A:$GB,O$2,FALSE),"") -> 67.44 | P32: =_xlfn.IFNA(VLOOKUP($N32,HAVERD!$A:$GB,P$2,FALSE),"") -> 65.79 | Q32: =_xlfn.IFNA(VLOOKUP($N32,HAVERD!$A:$GB,Q$2,FALSE),"") -> 64.72 | R32: =_xlfn.IFNA(VLOOKUP($N32,HAVERD!$A:$GB,R$2,FALSE),"") -> 64.43 | S32: =_xlfn.IFNA(VLOOKUP($N32,HAVERD!$A:$GB,S$2,FALSE),"") -> 65.13
A33: =A16 -> 45684 | B33: =VLOOKUP($A33,HAVERD!$A:$GB,B$2,FALSE) -> 77.08 | C33: =VLOOKUP($A33,HAVERD!$A:$GB,C$2,FALSE) -> 75.42 | D33: =VLOOKUP($A33,HAVERD!$A:$GB,D$2,FALSE) -> 73.73 | E33: =VLOOKUP($A33,HAVERD!$A:$GB,E$2,FALSE) -> 71.49 | F33: =VLOOKUP($A33,HAVERD!$A:$GB,F$2,FALSE) -> 69.43 | N33: =N16 -> 45770 | O33: =_xlfn.IFNA(VLOOKUP($N33,HAVERD!$A:$GB,O$2,FALSE),"") -> 66.12 | P33: =_xlfn.IFNA(VLOOKUP($N33,HAVERD!$A:$GB,P$2,FALSE),"") -> 64.57 | Q33: =_xlfn.IFNA(VLOOKUP($N33,HAVERD!$A:$GB,Q$2,FALSE),"") -> 63.67 | R33: =_xlfn.IFNA(VLOOKUP($N33,HAVERD!$A:$GB,R$2,FALSE),"") -> 63.65 | S33: =_xlfn.IFNA(VLOOKUP($N33,HAVERD!$A:$GB,S$2,FALSE),"") -> 64.68
A34: =A17 -> 45685 | B34: =VLOOKUP($A34,HAVERD!$A:$GB,B$2,FALSE) -> 77.49 | C34: =VLOOKUP($A34,HAVERD!$A:$GB,C$2,FALSE) -> 75.6 | D34: =VLOOKUP($A34,HAVERD!$A:$GB,D$2,FALSE) -> 73.65 | E34: =VLOOKUP($A34,HAVERD!$A:$GB,E$2,FALSE) -> 71.26 | F34: =VLOOKUP($A34,HAVERD!$A:$GB,F$2,FALSE) -> 69.14 | N34: =N17 -> 45771 | O34: =_xlfn.IFNA(VLOOKUP($N34,HAVERD!$A:$GB,O$2,FALSE),"") -> 66.55 | P34: =_xlfn.IFNA(VLOOKUP($N34,HAVERD!$A:$GB,P$2,FALSE),"") -> 65.1 | Q34: =_xlfn.IFNA(VLOOKUP($N34,HAVERD!$A:$GB,Q$2,FALSE),"") -> 64.29 | R34: =_xlfn.IFNA(VLOOKUP($N34,HAVERD!$A:$GB,R$2,FALSE),"") -> 64.27 | S34: =_xlfn.IFNA(VLOOKUP($N34,HAVERD!$A:$GB,S$2,FALSE),"") -> 65.28
... A37: =A20 -> 45688 | B37: =VLOOKUP($A37,HAVERD!$A:$GB,B$2,FALSE) -> 76.76 | C37: =VLOOKUP($A37,HAVERD!$A:$GB,C$2,FALSE) -> 74.92 | D37: =VLOOKUP($A37,HAVERD!$A:$GB,D$2,FALSE) -> 73.17 | E37: =VLOOKUP($A37,HAVERD!$A:$GB,E$2,FALSE) -> 70.82 | F37: =VLOOKUP($A37,HAVERD!$A:$GB,F$2,FALSE) -> 68.8 | N37: =N20 -> 45776 | O37: =_xlfn.IFNA(VLOOKUP($N37,HAVERD!$A:$GB,O$2,FALSE),"") -> 64.25 | P37: =_xlfn.IFNA(VLOOKUP($N37,HAVERD!$A:$GB,P$2,FALSE),"") -> 62.91 | Q37: =_xlfn.IFNA(VLOOKUP($N37,HAVERD!$A:$GB,Q$2,FALSE),"") -> 62.56 | R37: =_xlfn.IFNA(VLOOKUP($N37,HAVERD!$A:$GB,R$2,FALSE),"") -> 63.02 | S37: =_xlfn.IFNA(VLOOKUP($N37,HAVERD!$A:$GB,S$2,FALSE),"") -> 64.36
A39: Average | N39: Average
A40: Month | B40: =MONTH(B20) -> 1 | C40: =MONTH(C20) -> 5 | D40: =MONTH(D20) -> 8 | E40: =MONTH(E20) -> 1 | F40: =MONTH(F20) -> 1 | N40: Month | O40: =MONTH(O20) -> 4 | P40: =MONTH(P20) -> 7 | Q40: =MONTH(Q20) -> 10 | R40: =MONTH(R20) -> 4 | S40: =MONTH(S20) -> 4
A41: Year | B41: =YEAR(B20) -> 2025 | C41: =YEAR(C20) -> 2025 | D41: =YEAR(D20) -> 2025 | E41: =YEAR(E20) -> 2026 | F41: =YEAR(F20) -> 2027 | N41: Year | O41: =YEAR(O20) -> 2025 | P41: =YEAR(P20) -> 2025 | Q41: =YEAR(Q20) -> 2025 | R41: =YEAR(R20) -> 2026 | S41: =YEAR(S20) -> 2027
A42: YYYYMM | B42: =B41*100+B40 -> 202501 | C42: =C41*100+C40 -> 202505 | D42: =D41*100+D40 -> 202508 | E42: =E41*100+E40 -> 202601 | F42: =F41*100+F40 -> 202701 | N42: YYYYMM | O42: =O41*100+O40 -> 202504 | P42: =P41*100+P40 -> 202507 | Q42: =Q41*100+Q40 -> 202510 | R42: =R41*100+R40 -> 202604 | S42: =S41*100+S40 -> 202704
A43: Quarter | B43: =IF(B40<4,1,IF(B40<7,2,IF(B40<10,3,4))) -> 1 | C43: =IF(C40<4,1,IF(C40<7,2,IF(C40<10,3,4))) -> 2 | D43: =IF(D40<4,1,IF(D40<7,2,IF(D40<10,3,4))) -> 3 | E43: =IF(E40<4,1,IF(E40<7,2,IF(E40<10,3,4))) -> 1 | F43: =IF(F40<4,1,IF(F40<7,2,IF(F40<10,3,4))) -> 1 | N43: Quarter | O43: =IF(O40<4,1,IF(O40<7,2,IF(O40<10,3,4))) -> 2 | P43: =IF(P40<4,1,IF(P40<7,2,IF(P40<10,3,4))) -> 3 | Q43: =IF(Q40<4,1,IF(Q40<7,2,IF(Q40<10,3,4))) -> 4 | R43: =IF(R40<4,1,IF(R40<7,2,IF(R40<10,3,4))) -> 2 | S43: =IF(S40<4,1,IF(S40<7,2,IF(S40<10,3,4))) -> 2
A44: YYYYQQ | B44: =B41*100+B43 -> 202501 | C44: =C41*100+C43 -> 202502 | D44: =D41*100+D43 -> 202503 | E44: =E41*100+E43 -> 202601 | F44: =F41*100+F43 -> 202701 | N44: YYYYQQ | O44: =O41*100+O43 -> 202502 | P44: =P41*100+P43 -> 202503 | Q44: =Q41*100+Q43 -> 202504 | R44: =R41*100+R43 -> 202602 | S44: =S41*100+S43 -> 202702
A45: Average | B45: =AVERAGE(B23:B37) -> 79.003333 | C45: =AVERAGE(C23:C37) -> 77.048 | D45: =AVERAGE(D23:D37) -> 75.032667 | E45: =AVERAGE(E23:E37) -> 72.43 | F45: =AVERAGE(F23:F37) -> 70.112667 | N45: Average | O45: =AVERAGE(O23:O37) -> 65.734286 | P45: =AVERAGE(P23:P37) -> 64.312857 | Q45: =AVERAGE(Q23:Q37) -> 63.521429 | R45: =AVERAGE(R23:R37) -> 63.47 | S45: =AVERAGE(S23:S37) -> 64.408571
A47: Quarterly series | N47: Quarterly series
B48: =B44 -> 202501 | C48: =IF(RIGHT(B48)="4",B48+97,B48+1) -> 202502 | D48: =IF(RIGHT(C48)="4",C48+97,C48+1) -> 202503 | E48: =IF(RIGHT(D48)="4",D48+97,D48+1) -> 202504 | F48: =IF(RIGHT(E48)="4",E48+97,E48+1) -> 202601 | G48: =IF(RIGHT(F48)="4",F48+97,F48+1) -> 202602 | H48: =IF(RIGHT(G48)="4",G48+97,G48+1) -> 202603 | I48: =IF(RIGHT(H48)="4",H48+97,H48+1) -> 202604 | J48: =IF(RIGHT(I48)="4",I48+97,I48+1) -> 202701 | ... L48: =IF(RIGHT(K48)="4",K48+97,K48+1) -> 202703 | O48: =O44 -> 202502 | P48: =IF(RIGHT(O48)="4",O48+97,O48+1) -> 202503 | Q48: =IF(RIGHT(P48)="4",P48+97,P48+1) -> 202504 | R48: =IF(RIGHT(Q48)="4",Q48+97,Q48+1) -> 202601 | S48: =IF(RIGHT(R48)="4",R48+97,R48+1) -> 202602 | T48: =IF(RIGHT(S48)="4",S48+97,S48+1) -> 202603 | U48: =IF(RIGHT(T48)="4",T48+97,T48+1) -> 202604 | V48: =IF(RIGHT(U48)="4",U48+97,U48+1) -> 202701 | W48: =IF(RIGHT(V48)="4",V48+97,V48+1) -> 202702
A49: =A1 -> February 2025 MPR | B49: =AVERAGEIF($B$44:$F$44,B48,$B$45:$F$45) -> 79.003333 | C49: =AVERAGEIF($B$44:$F$44,C48,$B$45:$F$45) -> 77.048 | D49: =AVERAGEIF($B$44:$F$44,D48,$B$45:$F$45) -> 75.032667 | E49: =AVERAGE(D49,F49) -> 73.731333 | F49: =AVERAGEIF($B$44:$F$44,F48,$B$45:$F$45) -> 72.43 | G49: =F49+(J49-F49)*1/4 -> 71.850667 | H49: =G49+(J49-F49)*1/4 -> 71.271333 | I49: =H49+(J49-F49)*1/4 -> 70.692 | J49: =AVERAGEIF($B$44:$F$44,J48,$B$45:$F$45) -> 70.112667 | K49: =AVERAGEIF($B$44:$F$44,K48,$B$45:$F$45) -> #DIV/0! | L49: =AVERAGEIF($B$44:$F$44,L48,$B$45:$F$45) -> #DIV/0! | N49: =N1 -> May 2025 MPR | O49: =AVERAGEIF($O$44:$BJ$44,O48,$O$45:$BJ$45) -> 65.734286 | P49: =AVERAGEIF($O$44:$BJ$44,P48,$O$45:$BJ$45) -> 64.312857 | Q49: =AVERAGEIF($O$44:$BJ$44,Q48,$O$45:$BJ$45) -> 63.521429 | R49: =AVERAGE(Q49,S49) -> 63.495714 | S49: =AVERAGEIF($O$44:$BJ$44,S48,$O$45:$BJ$45) -> 63.47 | T49: =S49+(W49-S49)*1/4 -> 63.704643 | U49: =T49+(W49-S49)*1/4 -> 63.939286 | V49: =U49+(W49-S49)*1/4 -> 64.173929 | W49: =AVERAGEIF($O$44:$BJ$44,W48,$O$45:$BJ$45) -> 64.408571
N52: Comparison - quarterly
O53: 44927 | P53: 45017 | Q53: 45108 | R53: 45200 | S53: 45292 | T53: 45383 | U53: 45474 | V53: 45566 | W53: 45658 | X53: 45748 | Y53: 45839 | Z53: 45931 | AA53: 46023 | AB53: 46113 | AC53: 46204 | AD53: 46296 | AE53: 46388 | AF53: 46478 | AG53: 46569 | AH53: 46661
O54: 202301 | P54: =IF(RIGHT(O54)="4",O54+97,O54+1) -> 202302 | Q54: =IF(RIGHT(P54)="4",P54+97,P54+1) -> 202303 | R54: =IF(RIGHT(Q54)="4",Q54+97,Q54+1) -> 202304 | S54: =IF(RIGHT(R54)="4",R54+97,R54+1) -> 202401 | T54: =IF(RIGHT(S54)="4",S54+97,S54+1) -> 202402 | U54: =IF(RIGHT(T54)="4",T54+97,T54+1) -> 202403 | V54: =IF(RIGHT(U54)="4",U54+97,U54+1) -> 202404 | W54: =IF(RIGHT(V54)="4",V54+97,V54+1) -> 202501 | ... AH54: =IF(RIGHT(AG54)="4",AG54+97,AG54+1) -> 202704
N55: =A49 -> February 2025 MPR | O55: =HLOOKUP(O$54,$B$48:$J$49,2,FALSE) -> #N/A | P55: =HLOOKUP(P$54,$B$48:$J$49,2,FALSE) -> #N/A | Q55: =HLOOKUP(Q$54,$B$48:$J$49,2,FALSE) -> #N/A | R55: =HLOOKUP(R$54,$B$48:$J$49,2,FALSE) -> #N/A | S55: =HLOOKUP(S$54,$B$48:$J$49,2,FALSE) -> #N/A | T55: =HLOOKUP(T$54,$B$48:$J$49,2,FALSE) -> #N/A | U55: =HLOOKUP(U$54,$B$48:$J$49,2,FALSE) -> #N/A | V55: =HLOOKUP(V$54,$B$48:$J$49,2,FALSE) -> #N/A | ... AH55: =HLOOKUP(AH$54,$B$48:$J$49,2,FALSE) -> #N/A
N56: =N49 -> May 2025 MPR | O56: =HLOOKUP(O$54,$O$48:$AE$49,2,FALSE) -> #N/A | P56: =HLOOKUP(P$54,$O$48:$AE$49,2,FALSE) -> #N/A | Q56: =HLOOKUP(Q$54,$O$48:$AE$49,2,FALSE) -> #N/A | R56: =HLOOKUP(R$54,$O$48:$AE$49,2,FALSE) -> #N/A | S56: =HLOOKUP(S$54,$O$48:$AE$49,2,FALSE) -> #N/A | T56: =HLOOKUP(T$54,$O$48:$AE$49,2,FALSE) -> #N/A | U56: =HLOOKUP(U$54,$O$48:$AE$49,2,FALSE) -> #N/A | V56: =HLOOKUP(V$54,$O$48:$AE$49,2,FALSE) -> #N/A | ... AH56: =HLOOKUP(AH$54,$O$48:$AE$49,2,FALSE) -> #N/A
N57: Difference | U57: =U56-U55 -> #N/A | V57: =V56-V55 -> #N/A | W57: =W56-W55 -> #N/A | X57: =X56-X55 -> -11.313714 | Y57: =Y56-Y55 -> -10.71981 | Z57: =Z56-Z55 -> -10.209905 | AA57: =AA56-AA55 -> -8.9342857 | AB57: =AB56-AB55 -> -8.3806667 | ... AH57: =AH56-AH55 -> #N/A
N58: Difference % | U58: =100*((U56/U55)-1) -> #N/A | V58: =100*((V56/V55)-1) -> #N/A | W58: =100*((W56/W55)-1) -> #N/A | X58: =100*((X56/X55)-1) -> -14.683982 | Y58: =100*((Y56/Y55)-1) -> -14.286857 | Z58: =100*((Z56/Z55)-1) -> -13.847444 | AA58: =100*((AA56/AA55)-1) -> -12.335062 | AB58: =100*((AB56/AB55)-1) -> -11.664007 | ... AH58: =100*((AH56/AH55)-1) -> #N/A

Sheet Market expectations - Other
A1: ='Market pricing dates'!A2 -> February 2025 MPR | C1: ='Market pricing dates'!A12 -> 15 working days to 31 Jan 2025 | G1: ='Market pricing dates'!D2 -> May 2025 MPR | I1: ='Market pricing dates'!D12 -> 15 working days to 29 Apr 2025
A2: Column # | B2: =HAVERD!FO$1 -> 171 | C2: =+B2+1 -> 172 | D2: =+C2+1 -> 173 | E2: =+D2+1 -> 174 | G2: Column # | H2: =HAVERD!FO$1 -> 171 | I2: =+H2+1 -> 172 | J2: =+I2+1 -> 173 | K2: =+J2+1 -> 174
A3: Months | B3: =HAVERD!FO$2 -> £EER broad | C3: =HAVERD!FP$2 -> Oil price | D3: =HAVERD!FQ$2 -> RXD | E3: =HAVERD!FR$2 -> £ oil price | G3: Months | H3: =HAVERD!FO$2 -> £EER broad | I3: =HAVERD!FP$2 -> Oil price | J3: =HAVERD!FQ$2 -> RXD | K3: =HAVERD!FR$2 -> £ oil price
A4: Days | C4: 30.416667 | D4: =+C4+30.4166667 -> 60.833333 | E4: =+D4+30.4166667 -> 91.25 | G4: Days | I4: 30.416667 | J4: =+I4+30.4166667 -> 60.833333 | K4: =+J4+30.4166667 -> 91.25
A5: Dates | G5: Dates
A6: =A11-7 -> 45670 | B6: =A6 -> 45670 | C6: =$B6+C$4 -> 45700.417 | D6: =$B6+D$4 -> 45730.833 | E6: =$B6+E$4 -> 45761.25 | G6: =G11-7 -> 45756 | H6: =G6 -> 45756 | I6: =$G6+I$4 -> 45786.417 | J6: =$G6+J$4 -> 45816.833 | K6: =$G6+K$4 -> 45847.25
A7: =A12-7 -> 45671 | B7: =A7 -> 45671 | C7: =$B7+C$4 -> 45701.417 | D7: =$B7+D$4 -> 45731.833 | E7: =$B7+E$4 -> 45762.25 | G7: =G12-7 -> 45757 | H7: =G7 -> 45757 | I7: =$G7+I$4 -> 45787.417 | J7: =$G7+J$4 -> 45817.833 | K7: =$G7+K$4 -> 45848.25
A8: =A13-7 -> 45672 | B8: =A8 -> 45672 | C8: =$B8+C$4 -> 45702.417 | D8: =$B8+D$4 -> 45732.833 | E8: =$B8+E$4 -> 45763.25 | G8: =G13-7 -> 45758 | H8: =G8 -> 45758 | I8: =$G8+I$4 -> 45788.417 | J8: =$G8+J$4 -> 45818.833 | K8: =$G8+K$4 -> 45849.25
A9: =A14-7 -> 45673 | B9: =A9 -> 45673 | C9: =$B9+C$4 -> 45703.417 | D9: =$B9+D$4 -> 45733.833 | E9: =$B9+E$4 -> 45764.25 | G9: =G14-7 -> 45761 | H9: =G9 -> 45761 | I9: =$G9+I$4 -> 45791.417 | J9: =$G9+J$4 -> 45821.833 | K9: =$G9+K$4 -> 45852.25
A10: =A15-7 -> 45674 | B10: =A10 -> 45674 | C10: =$B10+C$4 -> 45704.417 | D10: =$B10+D$4 -> 45734.833 | E10: =$B10+E$4 -> 45765.25 | G10: =G15-7 -> 45762 | H10: =G10 -> 45762 | I10: =$G10+I$4 -> 45792.417 | J10: =$G10+J$4 -> 45822.833 | K10: =$G10+K$4 -> 45853.25
A11: =A16-7 -> 45677 | B11: =A11 -> 45677 | C11: =$B11+C$4 -> 45707.417 | D11: =$B11+D$4 -> 45737.833 | E11: =$B11+E$4 -> 45768.25 | G11: =G16-7 -> 45763 | H11: =G11 -> 45763 | I11: =$G11+I$4 -> 45793.417 | J11: =$G11+J$4 -> 45823.833 | K11: =$G11+K$4 -> 45854.25
A12: =A17-7 -> 45678 | B12: =A12 -> 45678 | C12: =$B12+C$4 -> 45708.417 | D12: =$B12+D$4 -> 45738.833 | E12: =$B12+E$4 -> 45769.25 | G12: =G17-7 -> 45764 | H12: =G12 -> 45764 | I12: =$G12+I$4 -> 45794.417 | J12: =$G12+J$4 -> 45824.833 | K12: =$G12+K$4 -> 45855.25
A13: =A18-7 -> 45679 | B13: =A13 -> 45679 | C13: =$B13+C$4 -> 45709.417 | D13: =$B13+D$4 -> 45739.833 | E13: =$B13+E$4 -> 45770.25 | G13: =G18-7 -> 45765 | H13: =G13 -> 45765 | I13: =$G13+I$4 -> 45795.417 | J13: =$G13+J$4 -> 45825.833 | K13: =$G13+K$4 -> 45856.25
A14: =A19-7 -> 45680 | B14: =A14 -> 45680 | C14: =$B14+C$4 -> 45710.417 | D14: =$B14+D$4 -> 45740.833 | E14: =$B14+E$4 -> 45771.25 | G14: =G19-7 -> 45768 | H14: =G14 -> 45768 | I14: =$G14+I$4 -> 45798.417 | J14: =$G14+J$4 -> 45828.833 | K14: =$G14+K$4 -> 45859.25
A15: =A20-7 -> 45681 | B15: =A15 -> 45681 | C15: =$B15+C$4 -> 45711.417 | D15: =$B15+D$4 -> 45741.833 | E15: =$B15+E$4 -> 45772.25 | G15: =G20-7 -> 45769 | H15: =G15 -> 45769 | I15: =$G15+I$4 -> 45799.417 | J15: =$G15+J$4 -> 45829.833 | K15: =$G15+K$4 -> 45860.25
A16: ='Market pricing dates'!B5 -> 45684 | B16: =A16 -> 45684 | C16: =$B16+C$4 -> 45714.417 | D16: =$B16+D$4 -> 45744.833 | E16: =$B16+E$4 -> 45775.25 | G16: ='Market pricing dates'!E5 -> 45770 | H16: =G16 -> 45770 | I16: =$G16+I$4 -> 45800.417 | J16: =$G16+J$4 -> 45830.833 | K16: =$G16+K$4 -> 45861.25
A17: ='Market pricing dates'!B6 -> 45685 | B17: =A17 -> 45685 | C17: =$B17+C$4 -> 45715.417 | D17: =$B17+D$4 -> 45745.833 | E17: =$B17+E$4 -> 45776.25 | G17: ='Market pricing dates'!E6 -> 45771 | H17: =G17 -> 45771 | I17: =$G17+I$4 -> 45801.417 | J17: =$G17+J$4 -> 45831.833 | K17: =$G17+K$4 -> 45862.25
A18: ='Market pricing dates'!B7 -> 45686 | B18: =A18 -> 45686 | C18: =$B18+C$4 -> 45716.417 | D18: =$B18+D$4 -> 45746.833 | E18: =$B18+E$4 -> 45777.25 | G18: ='Market pricing dates'!E7 -> 45772 | H18: =G18 -> 45772 | I18: =$G18+I$4 -> 45802.417 | J18: =$G18+J$4 -> 45832.833 | K18: =$G18+K$4 -> 45863.25
A19: ='Market pricing dates'!B8 -> 45687 | B19: =A19 -> 45687 | C19: =$B19+C$4 -> 45717.417 | D19: =$B19+D$4 -> 45747.833 | E19: =$B19+E$4 -> 45778.25 | G19: ='Market pricing dates'!E8 -> 45775 | H19: =G19 -> 45775 | I19: =$G19+I$4 -> 45805.417 | J19: =$G19+J$4 -> 45835.833 | K19: =$G19+K$4 -> 45866.25
A20: ='Market pricing dates'!B9 -> 45688 | B20: =A20 -> 45688 | C20: =$B20+C$4 -> 45718.417 | D20: =$B20+D$4 -> 45748.833 | E20: =$B20+E$4 -> 45779.25 | G20: ='Market pricing dates'!E9 -> 45776 | H20: =G20 -> 45776 | I20: =$G20+I$4 -> 45806.417 | J20: =$G20+J$4 -> 45836.833 | K20: =$G20+K$4 -> 45867.25
A22: Average levels | G22: Average levels
A23: =A6 -> 45670 | B23: =VLOOKUP($A23,HAVERD!$A:$FV,B$2,FALSE) -> 82.7349 | C23: =VLOOKUP($A23,HAVERD!$A:$FV,C$2,FALSE) -> 82.69 | D23: =VLOOKUP($A23,HAVERD!$A:$FV,D$2,FALSE) -> 1.2152 | E23: =VLOOKUP($A23,HAVERD!$A:$FV,E$2,FALSE) -> 68.046412 | G23: =G6 -> 45756 | H23: =_xlfn.IFNA(VLOOKUP($G23,HAVERD!$A:$FV,H$2,FALSE),"") -> 83.3356 | I23: =_xlfn.IFNA(VLOOKUP($G23,HAVERD!$A:$FV,I$2,FALSE),"") -> 67.3 | J23: =_xlfn.IFNA(VLOOKUP($G23,HAVERD!$A:$FV,J$2,FALSE),"") -> 1.2757 | K23: =_xlfn.IFNA(VLOOKUP($G23,HAVERD!$A:$FV,K$2,FALSE),"") -> 0
A24: =A7 -> 45671 | B24: =VLOOKUP($A24,HAVERD!$A:$FV,B$2,FALSE) -> 82.6172 | C24: =VLOOKUP($A24,HAVERD!$A:$FV,C$2,FALSE) -> 82.39 | D24: =VLOOKUP($A24,HAVERD!$A:$FV,D$2,FALSE) -> 1.2201 | E24: =VLOOKUP($A24,HAVERD!$A:$FV,E$2,FALSE) -> 67.527252 | G24: =G7 -> 45757 | H24: =_xlfn.IFNA(VLOOKUP($G24,HAVERD!$A:$FV,H$2,FALSE),"") -> 83.8394 | I24: =_xlfn.IFNA(VLOOKUP($G24,HAVERD!$A:$FV,I$2,FALSE),"") -> 65.37 | J24: =_xlfn.IFNA(VLOOKUP($G24,HAVERD!$A:$FV,J$2,FALSE),"") -> 1.296 | K24: =_xlfn.IFNA(VLOOKUP($G24,HAVERD!$A:$FV,K$2,FALSE),"") -> 0
A25: =A8 -> 45672 | B25: =VLOOKUP($A25,HAVERD!$A:$FV,B$2,FALSE) -> 82.8952 | C25: =VLOOKUP($A25,HAVERD!$A:$FV,C$2,FALSE) -> 83.48 | D25: =VLOOKUP($A25,HAVERD!$A:$FV,D$2,FALSE) -> 1.2258 | E25: =VLOOKUP($A25,HAVERD!$A:$FV,E$2,FALSE) -> 68.102464 | G25: =G8 -> 45758 | H25: =_xlfn.IFNA(VLOOKUP($G25,HAVERD!$A:$FV,H$2,FALSE),"") -> 83.8206 | I25: =_xlfn.IFNA(VLOOKUP($G25,HAVERD!$A:$FV,I$2,FALSE),"") -> 66.83 | J25: =_xlfn.IFNA(VLOOKUP($G25,HAVERD!$A:$FV,J$2,FALSE),"") -> 1.3059 | K25: =_xlfn.IFNA(VLOOKUP($G25,HAVERD!$A:$FV,K$2,FALSE),"") -> 0
A26: =A9 -> 45673 | B26: =VLOOKUP($A26,HAVERD!$A:$FV,B$2,FALSE) -> 82.7714 | C26: =VLOOKUP($A26,HAVERD!$A:$FV,C$2,FALSE) -> 82.39 | D26: =VLOOKUP($A26,HAVERD!$A:$FV,D$2,FALSE) -> 1.2235 | E26: =VLOOKUP($A26,HAVERD!$A:$FV,E$2,FALSE) -> 67.3396 | G26: =G9 -> 45761 | H26: =_xlfn.IFNA(VLOOKUP($G26,HAVERD!$A:$FV,H$2,FALSE),"") -> 84.473 | I26: =_xlfn.IFNA(VLOOKUP($G26,HAVERD!$A:$FV,I$2,FALSE),"") -> 67.18 | J26: =_xlfn.IFNA(VLOOKUP($G26,HAVERD!$A:$FV,J$2,FALSE),"") -> 1.3187 | K26: =_xlfn.IFNA(VLOOKUP($G26,HAVERD!$A:$FV,K$2,FALSE),"") -> 0
A27: =A10 -> 45674 | B27: =VLOOKUP($A27,HAVERD!$A:$FV,B$2,FALSE) -> 82.5346 | C27: =VLOOKUP($A27,HAVERD!$A:$FV,C$2,FALSE) -> 83.02 | D27: =VLOOKUP($A27,HAVERD!$A:$FV,D$2,FALSE) -> 1.2198 | E27: =VLOOKUP($A27,HAVERD!$A:$FV,E$2,FALSE) -> 68.060338 | G27: =G10 -> 45762 | H27: =_xlfn.IFNA(VLOOKUP($G27,HAVERD!$A:$FV,H$2,FALSE),"") -> 84.9871 | I27: =_xlfn.IFNA(VLOOKUP($G27,HAVERD!$A:$FV,I$2,FALSE),"") -> 66.58 | J27: =_xlfn.IFNA(VLOOKUP($G27,HAVERD!$A:$FV,J$2,FALSE),"") -> 1.3245 | K27: =_xlfn.IFNA(VLOOKUP($G27,HAVERD!$A:$FV,K$2,FALSE),"") -> 0
A28: =A11 -> 45677 | B28: =VLOOKUP($A28,HAVERD!$A:$FV,B$2,FALSE) -> 82.6366 | C28: =VLOOKUP($A28,HAVERD!$A:$FV,C$2,FALSE) -> 81.68 | D28: =VLOOKUP($A28,HAVERD!$A:$FV,D$2,FALSE) -> 1.2293 | E28: =VLOOKUP($A28,HAVERD!$A:$FV,E$2,FALSE) -> 66.444318 | G28: =G11 -> 45763 | H28: =_xlfn.IFNA(VLOOKUP($G28,HAVERD!$A:$FV,H$2,FALSE),"") -> 84.82 | I28: =_xlfn.IFNA(VLOOKUP($G28,HAVERD!$A:$FV,I$2,FALSE),"") -> 67.94 | J28: =_xlfn.IFNA(VLOOKUP($G28,HAVERD!$A:$FV,J$2,FALSE),"") -> 1.3257 | K28: =_xlfn.IFNA(VLOOKUP($G28,HAVERD!$A:$FV,K$2,FALSE),"") -> 0
A29: =A12 -> 45678 | B29: =VLOOKUP($A29,HAVERD!$A:$FV,B$2,FALSE) -> 82.6727 | C29: =VLOOKUP($A29,HAVERD!$A:$FV,C$2,FALSE) -> 80.57 | D29: =VLOOKUP($A29,HAVERD!$A:$FV,D$2,FALSE) -> 1.2299 | E29: =VLOOKUP($A29,HAVERD!$A:$FV,E$2,FALSE) -> 65.509391 | G29: =G12 -> 45764 | H29: =_xlfn.IFNA(VLOOKUP($G29,HAVERD!$A:$FV,H$2,FALSE),"") -> 84.7578 | I29: =_xlfn.IFNA(VLOOKUP($G29,HAVERD!$A:$FV,I$2,FALSE),"") -> 69.33 | J29: =_xlfn.IFNA(VLOOKUP($G29,HAVERD!$A:$FV,J$2,FALSE),"") -> 1.3233 | K29: =_xlfn.IFNA(VLOOKUP($G29,HAVERD!$A:$FV,K$2,FALSE),"") -> 0
A30: =A13 -> 45679 | B30: =VLOOKUP($A30,HAVERD!$A:$FV,B$2,FALSE) -> 82.721 | C30: =VLOOKUP($A30,HAVERD!$A:$FV,C$2,FALSE) -> 80 | D30: =VLOOKUP($A30,HAVERD!$A:$FV,D$2,FALSE) -> 1.2318 | E30: =VLOOKUP($A30,HAVERD!$A:$FV,E$2,FALSE) -> 64.945608 | G30: =G13 -> 45765 | H30: =_xlfn.IFNA(VLOOKUP($G30,HAVERD!$A:$FV,H$2,FALSE),"") | I30: =_xlfn.IFNA(VLOOKUP($G30,HAVERD!$A:$FV,I$2,FALSE),"") | J30: =_xlfn.IFNA(VLOOKUP($G30,HAVERD!$A:$FV,J$2,FALSE),"") | K30: =_xlfn.IFNA(VLOOKUP($G30,HAVERD!$A:$FV,K$2,FALSE),"") -> 0
A31: =A14 -> 45680 | B31: =VLOOKUP($A31,HAVERD!$A:$FV,B$2,FALSE) -> 82.8549 | C31: =VLOOKUP($A31,HAVERD!$A:$FV,C$2,FALSE) -> 78.62 | D31: =VLOOKUP($A31,HAVERD!$A:$FV,D$2,FALSE) -> 1.2324 | E31: =VLOOKUP($A31,HAVERD!$A:$FV,E$2,FALSE) -> 63.794223 | G31: =G14 -> 45768 | H31: =_xlfn.IFNA(VLOOKUP($G31,HAVERD!$A:$FV,H$2,FALSE),"") | I31: =_xlfn.IFNA(VLOOKUP($G31,HAVERD!$A:$FV,I$2,FALSE),"") | J31: =_xlfn.IFNA(VLOOKUP($G31,HAVERD!$A:$FV,J$2,FALSE),"") | K31: =_xlfn.IFNA(VLOOKUP($G31,HAVERD!$A:$FV,K$2,FALSE),"") -> 0
A32: =A15 -> 45681 | B32: =VLOOKUP($A32,HAVERD!$A:$FV,B$2,FALSE) -> 83.3326 | C32: =VLOOKUP($A32,HAVERD!$A:$FV,C$2,FALSE) -> 78.71 | D32: =VLOOKUP($A32,HAVERD!$A:$FV,D$2,FALSE) -> 1.2484 | E32: =VLOOKUP($A32,HAVERD!$A:$FV,E$2,FALSE) -> 63.048702 | G32: =G15 -> 45769 | H32: =_xlfn.IFNA(VLOOKUP($G32,HAVERD!$A:$FV,H$2,FALSE),"") -> 85.1739 | I32: =_xlfn.IFNA(VLOOKUP($G32,HAVERD!$A:$FV,I$2,FALSE),"") -> 68.93 | J32: =_xlfn.IFNA(VLOOKUP($G32,HAVERD!$A:$FV,J$2,FALSE),"") -> 1.3379 | K32: =_xlfn.IFNA(VLOOKUP($G32,HAVERD!$A:$FV,K$2,FALSE),"") -> 0
A33: =A16 -> 45684 | B33: =VLOOKUP($A33,HAVERD!$A:$FV,B$2,FALSE) -> 83.3664 | C33: =VLOOKUP($A33,HAVERD!$A:$FV,C$2,FALSE) -> 77.3 | D33: =VLOOKUP($A33,HAVERD!$A:$FV,D$2,FALSE) -> 1.2473 | E33: =VLOOKUP($A33,HAVERD!$A:$FV,E$2,FALSE) -> 61.973864 | G33: =G16 -> 45770 | H33: =_xlfn.IFNA(VLOOKUP($G33,HAVERD!$A:$FV,H$2,FALSE),"") -> 84.9844 | I33: =_xlfn.IFNA(VLOOKUP($G33,HAVERD!$A:$FV,I$2,FALSE),"") -> 68.26 | J33: =_xlfn.IFNA(VLOOKUP($G33,HAVERD!$A:$FV,J$2,FALSE),"") -> 1.3275 | K33: =_xlfn.IFNA(VLOOKUP($G33,HAVERD!$A:$FV,K$2,FALSE),"") -> 0
A34: =A17 -> 45685 | B34: =VLOOKUP($A34,HAVERD!$A:$FV,B$2,FALSE) -> 83.4659 | C34: =VLOOKUP($A34,HAVERD!$A:$FV,C$2,FALSE) -> 78.01 | D34: =VLOOKUP($A34,HAVERD!$A:$FV,D$2,FALSE) -> 1.2432 | E34: =VLOOKUP($A34,HAVERD!$A:$FV,E$2,FALSE) -> 0 | G34: =G17 -> 45771 | H34: =_xlfn.IFNA(VLOOKUP($G34,HAVERD!$A:$FV,H$2,FALSE),"") -> 85.1643 | I34: =_xlfn.IFNA(VLOOKUP($G34,HAVERD!$A:$FV,I$2,FALSE),"") -> 67.5 | J34: =_xlfn.IFNA(VLOOKUP($G34,HAVERD!$A:$FV,J$2,FALSE),"") -> 1.3315 | K34: =_xlfn.IFNA(VLOOKUP($G34,HAVERD!$A:$FV,K$2,FALSE),"") -> 0
... A37: =A20 -> 45688 | B37: =VLOOKUP($A37,HAVERD!$A:$FV,B$2,FALSE) -> 83.5562 | C37: =VLOOKUP($A37,HAVERD!$A:$FV,C$2,FALSE) -> 77.11 | D37: =VLOOKUP($A37,HAVERD!$A:$FV,D$2,FALSE) -> 1.2426 | E37: =VLOOKUP($A37,HAVERD!$A:$FV,E$2,FALSE) -> 0 | G37: =G20 -> 45776 | H37: =_xlfn.IFNA(VLOOKUP($G37,HAVERD!$A:$FV,H$2,FALSE),"") -> 85.5652 | I37: =_xlfn.IFNA(VLOOKUP($G37,HAVERD!$A:$FV,I$2,FALSE),"") -> 64.04 | J37: =_xlfn.IFNA(VLOOKUP($G37,HAVERD!$A:$FV,J$2,FALSE),"") -> 1.3389 | K37: =_xlfn.IFNA(VLOOKUP($G37,HAVERD!$A:$FV,K$2,FALSE),"") -> 0
A38: Average | B38: =AVERAGE(B23:B37) -> 83.016773 | C38: =AVERAGE(C23:C37) -> 80.027333 | D38: =AVERAGE(D23:D37) -> 1.2332933 | E38: =AVERAGE(E23:E37) -> 48.319478 | G38: Average | H38: =AVERAGE(H23:H37) -> 84.750615 | I38: =AVERAGE(I23:I37) -> 67.106154 | J38: =AVERAGE(J23:J37) -> 1.3212154 | K38: =AVERAGE(K23:K37) -> 0
G40: % diff | H40: =100*((H38/B38)-1) -> 2.0885443 | I40: =100*((I38/C38)-1) -> -16.145958 | J40: =100*((J38/D38)-1) -> 7.1290462 | K40: =100*((K38/E38)-1) -> -100

Sheet MPR Chart 2.16 (Aug)
A1: Section 2: Current economic conditions
A3: Chart 2.16 - Contributions to CPI inflation
B5: Contributions | H5: Inflation rates
A6: Date | B6: Food | C6: Electricity and gas | D6: Fuels and lubricants | E6: Other goods | F6: Services | H6: Food | I6: Electricity and gas | J6: Fuels and lubricants | K6: Other goods | L6: Services | M6: Total CPI
A7: 44227 | B7: -0.1 | C7: -0.3 | D7: -0.3 | E7: 0.4 | F7: 0.8 | H7: -0.7 | I7: -8.4 | J7: -8.2 | K7: 1.4 | L7: 1.7 | M7: 0.7
A8: 44255 | B8: 0 | C8: -0.3 | D8: -0.1 | E8: 0.1 | F8: 0.7 | H8: -0.6 | I8: -7.9 | J8: -3.5 | K8: 0.5 | L8: 1.5 | M8: 0.4
A9: 44286 | B9: -0.1 | C9: -0.2 | D9: 0.1 | E9: 0.3 | F9: 0.7 | H9: -1.4 | I9: -7.3 | J9: 3.5 | K9: 0.9 | L9: 1.5 | M9: 0.7
A10: 44316 | B10: 0 | C10: 0.1 | D10: 0.4 | E10: 0.4 | F10: 0.7 | H10: -0.4 | I10: 2.4 | J10: 13.6 | K10: 1.2 | L10: 1.6 | M10: 1.5
A11: 44347 | B11: -0.1 | C11: 0.1 | D11: 0.5 | E11: 0.8 | F11: 0.9 | H11: -1.3 | I11: 2.6 | J11: 17.9 | K11: 2.2 | L11: 1.9 | M11: 2.1
A12: 44377 | B12: 0 | C12: 0.1 | D12: 0.5 | E12: 1 | F12: 0.9 | H12: -0.6 | I12: 2.5 | J12: 20.3 | K12: 2.7 | L12: 2.1 | M12: 2.5
A13: 44408 | B13: -0.1 | C13: 0.1 | D13: 0.5 | E13: 0.8 | F13: 0.7 | H13: -0.6 | I13: 2.6 | J13: 17.7 | K13: 2.3 | L13: 1.6 | M13: 2
A14: 44439 | B14: 0.1 | C14: 0.1 | D14: 0.5 | E14: 1.2 | F14: 1.4 | H14: 0.3 | I14: 2.6 | J14: 17.7 | K14: 3.2 | L14: 3 | M14: 3.2
A15: 44469 | B15: 0.1 | C15: 0.1 | D15: 0.5 | E15: 1.3 | F15: 1.1 | H15: 0.8 | I15: 2.8 | J15: 17.8 | K15: 3.3 | L15: 2.6 | M15: 3.1
A16: 44500 | B16: 0.2 | C16: 0.8 | D16: 0.6 | E16: 1.3 | F16: 1.4 | H16: 1.2 | I16: 22.9 | J16: 21.5 | K16: 3.4 | L16: 3.2 | M16: 4.2
A17: 44530 | B17: 0.3 | C17: 0.8 | D17: 0.7 | E17: 1.9 | F17: 1.5 | H17: 2.5 | I17: 23.2 | J17: 28.5 | K17: 4.8 | L17: 3.3 | M17: 5.1
A18: 44561 | B18: 0.5 | C18: 0.7 | D18: 0.7 | E18: 2 | F18: 1.5 | H18: 4.2 | I18: 22.7 | J18: 26.8 | K18: 5 | L18: 3.4 | M18: 5.4
... A48: 45444 | B48: 0.2 | C48: -1.3 | D48: 0.1 | E48: 0.3 | F48: 2.7 | H48: 1.5 | I48: -27.2 | J48: 2.6 | K48: 0.8 | L48: 5.7 | M48: 2
A49: July 2024 (Bank staff projections) | B49: 0.159 | C49: -0.828 | D49: 0.054 | E49: 0.281 | F49: 2.7 | H49: 1.31 | I49: -20.122 | J49: 1.894 | K49: 0.831 | L49: 5.563 | M49: 2.366
A50: August 2024 (Bank staff projections) | B50: 0.156 | C50: -0.838 | D50: -0.024 | E50: 0.245 | F50: 2.827 | H50: 1.313 | I50: -20.372 | J50: -1.018 | K50: 0.735 | L50: 5.84 | M50: 2.367
A51: September 2024 (Bank staff projections) | B51: 0.142 | C51: -0.84 | D51: -0.086 | E51: 0.21 | F51: 2.67 | H51: 1.191 | I51: -20.502 | J51: -3.285 | K51: 0.647 | L51: 5.52 | M51: 2.097
A52: October 2024 (Bank staff projections) | B52: 0.112 | C52: -0.329 | D52: -0.109 | E52: 0.249 | F52: 2.675 | H52: 0.928 | I52: -8.466 | J52: -4.125 | K52: 0.768 | L52: 5.502 | M52: 2.6
A53: November 2024 (Bank staff projections) | B53: 0.091 | C53: -0.324 | D53: -0.025 | E53: 0.396 | F53: 2.625 | H53: 0.764 | I53: -8.329 | J53: -1.368 | K53: 1.207 | L53: 5.395 | M53: 2.763
A54: December 2024 (Bank staff projections) | B54: 0.081 | C54: -0.32 | D54: 0.132 | E54: 0.31 | F54: 2.596 | H54: 0.719 | I54: -8.249 | J54: 4.225 | K54: 0.953 | L54: 5.286 | M54: 2.8
A56: 2025 Q1 (Bank staff projection) | B56: n.a. | C56: n.a. | D56: n.a. | E56: n.a. | F56: n.a. | H56: n.a. | I56: n.a. | J56: n.a. | K56: n.a. | L56: n.a. | M56: 2.67

Sheet MPR Chart 2.16 (May)
A1: Section 2: Current economic conditions
A3: Chart 2.16 - Contributions to CPI inflation
B5: Contributions | H5: Inflation rates
A6: Date | B6: Food | C6: Electricity and gas | D6: Fuels and lubricants | E6: Other goods | F6: Services | H6: Food | I6: Electricity and gas | J6: Fuels and lubricants | K6: Other goods | L6: Services | M6: CPI
A7: 43496 | B7: 0.1 | C7: 0.1 | D7: 0 | E7: 0.5 | F7: 1.2 | H7: 0.9 | I7: 1.4 | J7: 0.7 | K7: 1.4 | L7: 2.5 | M7: 1.8
A8: 43524 | B8: 0.1 | C8: 0.1 | D8: 0 | E8: 0.5 | F8: 1.2 | H8: 1.1 | I8: 1.6 | J8: 0.5 | K8: 1.4 | L8: 2.5 | M8: 1.9
A9: 43555 | B9: 0.1 | C9: 0.1 | D9: 0.1 | E9: 0.5 | F9: 1.2 | H9: 0.8 | I9: 1.5 | J9: 2.9 | K9: 1.3 | L9: 2.5 | M9: 1.9
A10: 43585 | B10: 0.1 | C10: 0.3 | D10: 0.1 | E10: 0.2 | F10: 1.4 | H10: 0.7 | I10: 10.5 | J10: 4.3 | K10: 0.5 | L10: 2.9 | M10: 2.1
A11: 43616 | B11: 0.1 | C11: 0.3 | D11: 0.1 | E11: 0.2 | F11: 1.2 | H11: 1 | I11: 10.4 | J11: 3.4 | K11: 0.7 | L11: 2.6 | M11: 2
A12: 43646 | B12: 0.2 | C12: 0.3 | D12: 0 | E12: 0.3 | F12: 1.2 | H12: 1.6 | I12: 7.9 | J12: 0.7 | K12: 1 | L12: 2.5 | M12: 2
A13: 43677 | B13: 0.1 | C13: 0.2 | D13: 0 | E13: 0.5 | F13: 1.2 | H13: 1.4 | I13: 6.5 | J13: 0.2 | K13: 1.5 | L13: 2.5 | M13: 2.1
A14: 43708 | B14: 0.2 | C14: 0.2 | D14: 0 | E14: 0.3 | F14: 1.1 | H14: 1.8 | I14: 6.5 | J14: -0.1 | K14: 0.8 | L14: 2.2 | M14: 1.7
A15: 43738 | B15: 0.2 | C15: 0.2 | D15: -0.1 | E15: 0.2 | F15: 1.2 | H15: 1.8 | I15: 4.9 | J15: -2.1 | K15: 0.7 | L15: 2.5 | M15: 1.7
A16: 43769 | B16: 0.1 | C16: -0.1 | D16: -0.1 | E16: 0.3 | F16: 1.2 | H16: 1.3 | I16: -1.9 | J16: -3.3 | K16: 0.8 | L16: 2.6 | M16: 1.5
A17: 43799 | B17: 0.2 | C17: -0.1 | D17: -0.1 | E17: 0.2 | F17: 1.2 | H17: 2.1 | I17: -1.7 | J17: -2.9 | K17: 0.7 | L17: 2.5 | M17: 1.5
A18: 43830 | B18: 0.2 | C18: -0.1 | D18: 0 | E18: 0.2 | F18: 1 | H18: 1.7 | I18: -1.6 | J18: 1 | K18: 0.4 | L18: 2.1 | M18: 1.3
... A69: 45352 | B69: 0.5 | C69: -0.9 | D69: -0.1 | E69: 0.9 | F69: 2.8 | H69: 4 | I69: -18.2 | J69: -3.7 | K69: 2.7 | L69: 6 | M69: 3.2
A70: Apr 2024 (Bank staff projections) | B70: 0.306 | C70: -1.262 | D70: 0.007 | E70: 0.416 | F70: 2.598 | H70: 2.529 | I70: -26.609 | J70: -0.274 | K70: 1.24 | L70: 5.52 | M70: 2.064
A71: May 2024 (Bank staff projections) | B71: 0.164 | C71: -1.245 | D71: 0.127 | E71: 0.405 | F71: 2.486 | H71: 1.334 | I71: -26.457 | J71: 3.782 | K71: 1.229 | L71: 5.258 | M71: 1.938
A72: Jun 2024 (Bank staff projections) | B72: 0.171 | C72: -1.239 | D72: 0.235 | E72: 0.377 | F72: 2.442 | H72: 1.423 | I72: -26.397 | J72: 7.722 | K72: 1.143 | L72: 5.134 | M72: 1.987
A73: Jul 2024 (Bank staff projections) | B73: 0.142 | C73: -0.814 | D73: 0.26 | E73: 0.406 | F73: 2.4 | H73: 1.166 | I73: -19.79 | J73: 8.5 | K73: 1.215 | L73: 4.949 | M73: 2.394
A74: Aug 2024 (Bank staff projections) | B74: 0.137 | C74: -0.825 | D74: 0.167 | E74: 0.359 | F74: 2.418 | H74: 1.145 | I74: -20.067 | J74: 4.878 | K74: 1.084 | L74: 5.001 | M74: 2.256
A75: Sep 2024 (Bank staff projections) | B75: 0.125 | C75: -0.828 | D75: 0.068 | E75: 0.334 | F75: 2.285 | H75: 1.033 | I75: -20.207 | J75: 1.339 | K75: 1.024 | L75: 4.728 | M75: 1.984

Sheet MPR Chart 2.21 (Aug)
A1: Section 2: Current economic conditions
A3: Chart 2.21 - Measures of annual pay growth
B5: Quarterly frequency | F5: Monthly frequency
A6: Date | B6: AWE private sector regular pay | C6: Indicator-based model | E6: Date | F6: AWE private sector regular pay | G6: KPMG/REC survey (advanced 12 months) | H6: HMRC RTI private sector median | I6: Indeed Wage Tracker
A7: 2018 Q1 | B7: 3 | C7: 2.9 | E7: 43131 | F7: 2.7 | G7: No permissions | H7: 3.1 | I7: n.a.
A8: 2018 Q2 | B8: 2.8 | C8: 3 | E8: 43159 | F8: 2.9 | H8: 3.2 | I8: n.a.
A9: 2018 Q3 | B9: 3.3 | C9: 3.2 | E9: 43190 | F9: 3 | H9: 3.2 | I9: n.a.
A10: 2018 Q4 | B10: 3.5 | C10: 3.4 | E10: 43220 | F10: 3 | H10: 3 | I10: n.a.
A11: 2019 Q1 | B11: 3.6 | C11: 3.4 | E11: 43251 | F11: 2.9 | H11: 3.2 | I11: n.a.
A12: 2019 Q2 | B12: 3.9 | C12: 3.5 | E12: 43281 | F12: 2.8 | H12: 3.4 | I12: n.a.
A13: 2019 Q3 | B13: 3.7 | C13: 3.4 | E13: 43312 | F13: 3 | H13: 3.7 | I13: n.a.
A14: 2019 Q4 | B14: 3.2 | C14: 3.2 | E14: 43343 | F14: 3.2 | H14: 3.9 | I14: n.a.
A15: 2020 Q1 | B15: 2.5 | C15: 3 | E15: 43373 | F15: 3.3 | H15: 3.8 | I15: n.a.
A16: 2020 Q2 | B16: -1.2 | C16: 2.2 | E16: 43404 | F16: 3.4 | H16: 3.8 | I16: n.a.
A17: 2020 Q3 | B17: 1.4 | C17: 1.4 | E17: 43434 | F17: 3.4 | H17: 3.7 | I17: n.a.
A18: 2020 Q4 | B18: 4 | C18: 1.3 | E18: 43465 | F18: 3.5 | H18: 3.7 | I18: n.a.
A19: 2021 Q1 | B19: 4.3 | C19: 1.1 | E19: 43496 | F19: 3.6 | H19: 3.7 | I19: n.a.
... A31: 2024 Q1 | B31: 5.9 | C31: 5.6 | E31: 43861 | F31: 3 | H31: 3.3 | I31: n.a.
A32: 2024 Q2 (Bank Staff Projection) | B32: 5.141 | C32: n.a. | E32: 43890 | F32: 2.9 | H32: 3.7 | I32: n.a.
A33: 2024 Q3 (Bank Staff Projection) | B33: 4.83 | C33: n.a. | E33: 43921 | F33: 2.5 | H33: 3.2 | I33: n.a.
E34: 43951 | F34: 1.3 | H34: 1.2 | I34: 5.5
E35: 43982 | F35: -0.1 | H35: -1 | I35: 4.6
E36: 44012 | F36: -1.2 | H36: -1.8 | I36: 3.8
E37: 44043 | F37: -0.8 | H37: -0.6 | I37: 3.5
E38: 44074 | F38: 0.1 | H38: 1.2 | I38: 3.2
E39: 44104 | F39: 1.4 | H39: 2.7 | I39: 3.2
E40: 44135 | F40: 2.5 | H40: 3.7 | I40: 3.2
E41: 44165 | F41: 3.3 | H41: 4.3 | I41: 3.2
E42: 44196 | F42: 4 | H42: 4.5 | I42: 3.4
E43: 44227 | F43: 4.1 | H43: 4.3 | I43: 3.6
E44: 44255 | F44: 4.2 | H44: 4 | I44: 3.3
E45: 44286 | F45: 4.3 | H45: 4.5 | I45: 2.8
... E83: 45443 | F83: 5.6 | H83: 6.3 | I83: 6.9
E84: 45473 | F84: n.a. | H84: 6.2 | I84: 6.8

Sheet MPR Chart 2.22 (Nov)
A1: Section 2: Current economic conditions
A3: Chart 2.22 - Contributions to CPI inflation
B5: Contributions | H5: Inflation rates
A6: Date | B6: Food | C6: Electricity and gas | D6: Fuels and lubricants | E6: Other goods | F6: Services | H6: Food | I6: Electricity and gas | J6: Fuels and lubricants | K6: Other goods | L6: Services | M6: Total CPI
A7: 44227 | B7: -0.1 | C7: -0.3 | D7: -0.3 | E7: 0.4 | F7: 0.8 | H7: -0.7 | I7: -8.4 | J7: -8.2 | K7: 1.4 | L7: 1.7 | M7: 0.7
A8: 44255 | B8: 0 | C8: -0.3 | D8: -0.1 | E8: 0.1 | F8: 0.7 | H8: -0.6 | I8: -7.9 | J8: -3.5 | K8: 0.5 | L8: 1.5 | M8: 0.4
A9: 44286 | B9: -0.1 | C9: -0.2 | D9: 0.1 | E9: 0.3 | F9: 0.7 | H9: -1.4 | I9: -7.3 | J9: 3.5 | K9: 0.9 | L9: 1.5 | M9: 0.7
A10: 44316 | B10: 0 | C10: 0.1 | D10: 0.4 | E10: 0.4 | F10: 0.7 | H10: -0.4 | I10: 2.4 | J10: 13.6 | K10: 1.2 | L10: 1.6 | M10: 1.5
A11: 44347 | B11: -0.1 | C11: 0.1 | D11: 0.5 | E11: 0.8 | F11: 0.9 | H11: -1.3 | I11: 2.6 | J11: 17.9 | K11: 2.2 | L11: 1.9 | M11: 2.1
A12: 44377 | B12: 0 | C12: 0.1 | D12: 0.5 | E12: 1 | F12: 0.9 | H12: -0.6 | I12: 2.5 | J12: 20.3 | K12: 2.7 | L12: 2.1 | M12: 2.5
A13: 44408 | B13: -0.1 | C13: 0.1 | D13: 0.5 | E13: 0.8 | F13: 0.7 | H13: -0.6 | I13: 2.6 | J13: 17.7 | K13: 2.3 | L13: 1.6 | M13: 2
A14: 44439 | B14: 0.1 | C14: 0.1 | D14: 0.5 | E14: 1.2 | F14: 1.4 | H14: 0.3 | I14: 2.6 | J14: 17.7 | K14: 3.2 | L14: 3 | M14: 3.2
A15: 44469 | B15: 0.1 | C15: 0.1 | D15: 0.5 | E15: 1.3 | F15: 1.1 | H15: 0.8 | I15: 2.8 | J15: 17.8 | K15: 3.3 | L15: 2.6 | M15: 3.1
A16: 44500 | B16: 0.2 | C16: 0.8 | D16: 0.6 | E16: 1.3 | F16: 1.4 | H16: 1.2 | I16: 22.9 | J16: 21.5 | K16: 3.4 | L16: 3.2 | M16: 4.2
A17: 44530 | B17: 0.3 | C17: 0.8 | D17: 0.7 | E17: 1.9 | F17: 1.5 | H17: 2.5 | I17: 23.2 | J17: 28.5 | K17: 4.8 | L17: 3.3 | M17: 5.1
A18: 44561 | B18: 0.5 | C18: 0.7 | D18: 0.7 | E18: 2 | F18: 1.5 | H18: 4.2 | I18: 22.7 | J18: 26.8 | K18: 5 | L18: 3.4 | M18: 5.4
... A51: 45536 | B51: 0.2 | C51: -0.8 | D51: -0.3 | E51: 0.2 | F51: 2.4 | H51: 1.9 | I51: -20.7 | J51: -10.4 | K51: 0.8 | L51: 4.9 | M51: 1.7
A52: October 2024 (Bank staff projections) | B52: 0.156 | C52: -0.275 | D52: -0.435 | E52: 0.319 | F52: 2.416 | H52: 1.319 | I52: -7.075 | J52: -13.738 | K52: 0.982 | L52: 4.972 | M52: 2.182
A53: November 2024 (Bank staff projections) | B53: 0.131 | C53: -0.269 | D53: -0.319 | E53: 0.49 | F53: 2.389 | H53: 1.121 | I53: -6.902 | J53: -10.245 | K53: 1.496 | L53: 4.913 | M53: 2.423
A54: December 2024 (Bank staff projections) | B54: 0.125 | C54: -0.264 | D54: -0.116 | E54: 0.391 | F54: 2.327 | H54: 1.105 | I54: -6.809 | J54: -3.718 | K54: 1.2 | L54: 4.739 | M54: 2.463
A55: January 2025 (Bank staff projections) | B55: 0.117 | C55: -0.443 | D55: -0.012 | E55: 0.326 | F55: 2.51 | H55: 1.038 | I55: -10.859 | J55: -0.477 | K55: 1.017 | L55: 5.112 | M55: 2.498
A56: February 2025 (Bank staff projections) | B56: 0.118 | C56: -0.445 | D56: -0.043 | E56: 0.38 | F56: 2.432 | H56: 1.048 | I56: -10.973 | J56: -1.475 | K56: 1.172 | L56: 4.965 | M56: 2.443
A57: March 2025 (Bank staff projections) | B57: 0.116 | C57: -0.437 | D57: -0.081 | E57: 0.384 | F57: 2.391 | H57: 1.031 | I57: -10.841 | J57: -2.668 | K57: 1.17 | L57: 4.894 | M57: 2.373

Sheet MPR Chart 2.29 (Nov)
A1: Section 2: Current economic conditions
A3: Chart 2.29 - Measures of annual private sector wage growth
A5: Date | B5: AWE private sector regular pay | C5: Indicator-based model | E5: Date | F5: AWE private sector regular pay | G5: KPMG/REC survey (advanced 12 months) | H5: HMRC RTI private sector median | I5: Indeed Wage Tracker
A6: 2018 Q1 | B6: 3 | C6: 2.8 | E6: 43131 | F6: 2.7 | G6: No permission | H6: 3.1 | I6: n.a.
A7: 2018 Q2 | B7: 2.8 | C7: 3 | E7: 43159 | F7: 2.9 | H7: 3.3 | I7: n.a.
A8: 2018 Q3 | B8: 3.3 | C8: 3.2 | E8: 43190 | F8: 3 | H8: 3.2 | I8: n.a.
A9: 2018 Q4 | B9: 3.5 | C9: 3.4 | E9: 43220 | F9: 3 | H9: 2.9 | I9: n.a.
