Workbook
Name _DLX1.INC: HAVERQ!$A$1:$E$6
Name _DLX2.INC: HAVERD!$B$1:$FZ$6
Name _DLX3.INC: HAVERW!$B$1:$F$6
Name _DLX4.INC: HAVERM!$A$1:$AF$6

Sheet Chart Data
A1: Inflation forecasts | H1: Oil and petrol prices | P1: FX pass through | U1: Food commodities | AZ1: Food and core goods contributions | BI1: OE vs BoE forecast >>> | BP1: CPI Services vs Pay growth >>>
B2: OE (February) | C2: OE (February) | D2: BoE (February) | E2: BoE (Nov) | F2: 2% LINE | I2: Unleaded pump price (LHS) | J2: Diesel pump price (LHS) | M2: Brent crude oil price (RHS) | O2: Period | P2: Date | Q2: Passthrough to annual inflation (LHS) | R2: Passthrough to price level (LHS) | U2: Date | V2: UN global food price inflation in £ terms (adv. 12m, LHS) | W2: ONS UK food price inflation (RHS) | X2: PPI food output | Y2: Zeroline | Z2: FX adj | AA2: Rebase | AD2: Date | AE2: MPC's measure of underlying CPI services inflation* (LHS) | AF2: BoE DMP measure of one-year inflation expectations (adv. 6m, RHS) | AJ2: Date | AL2: Pence per therm | AO2: Jul-23 cap | AP2: Oct-23 cap | AQ2: Jan-24 cap | AR2: Apr-24 cap | AS2: Jul-24 cap | AT2: Oct-24 cap | AU2: Jan-25 cap | AV2: Apr-25 cap | AW2: Jul-25 cap | AZ2: Date | BA2: Food | BB2: Core goods | BC2: Food avg | BD2: Core goods avg | BE2: 2010-2019 average | BF2: Zeroline | BJ2: OE (latest) | BK2: OE (Nov) | BL2: BoE* (Feb) | BM2: 2% LINE | BQ2: Date | BR2: CPI services | BS2: AWE total pay growth | BT2: Zeroline | BX2: Lower profit margins | BY2: Higher prices | BZ2: Lower number of employees | CA2: Lower employee wages | CB2: Other | CC2: None of the above
A3: 43831 | B3: ='[24]CPI Forecast'!D294 -> 1.7692706 | C3: =NA() -> #N/A | D3: =NA() -> #N/A | E3: =NA() -> #N/A | F3: 2 | H3: 43836 | I3: =HAVERW!C8 -> 126.09 | J3: =HAVERW!D8 -> 131.56 | L3: 43831 | M3: =HAVERD!BA7/HAVERD!BB7 -> #N/A | O3: 1 | P3: t | Q3: ='[25]Impulse responses'!DK9 -> 0.26727528 | R3: ='[25]Impulse responses'!EN9 -> 0.095902362 | U3: 40179 | V3: =NA() -> #N/A | W3: =((HAVERM!J139/HAVERM!J127)-1)*100 -> 1.8327606 | X3: =((HAVERM!K136/HAVERM!K124)-1)*100 -> 0 | Y3: 0 | Z3: =HAVERM!H139/HAVERM!I139 -> 62.987254 | AA3: =(Z3/AVERAGE($Z$63:$Z$74))*100 -> 103.42422 | AD3: 44197 | AE3: ='BoE MPR - Chart 2.21'!D7 -> 1.4 | AF3: =HAVERM!L265 -> 1.494 | AJ3: 43831 | AL3: =IF(HAVERD!H7="",HAVERD!D7,AVERAGE(HAVERD!H7:Q7)) -> #N/A | AZ3: 45292 | BA3: ='[26]CPI Forecast'!V342 -> 1.9632648 | BB3: ='[26]CPI Forecast'!AN342 -> 8.3186845 | BC3: 0.85340364 | BD3: 2.5013809 | BF3: 0 | BI3: 43831 | BJ3: ='[27]CPI Forecast'!D294 -> 1.7692706 | BK3: =NA() -> #N/A | BL3: =NA() -> #N/A | BM3: 2 | BP3: 20191 | BQ3: =LEFT(BP3,4) -> 2019 | BR3: ='[28]CPI Forecast'!AA581 -> 2.4880644 | BS3: 3.2552148 | BT3: 0 | BW3: 45597 | BX3: =HAVERM!M317 -> 59 | BY3: =HAVERM!N317 -> 54 | BZ3: =HAVERM!O317 -> 54 | CA3: =HAVERM!P317 -> 38 | CB3: =HAVERM!Q317 -> 8 | CC3: =HAVERM!R317 -> 3
A4: 43862 | B4: ='[24]CPI Forecast'!D295 -> 1.7095297 | C4: =NA() -> #N/A | D4: =NA() -> #N/A | E4: =NA() -> #N/A | F4: 2 | H4: =+H3+7 -> 43843 | I4: =HAVERW!C9 -> 127.17 | J4: =HAVERW!D9 -> 132.69 | L4: 43832 | M4: =HAVERD!BA8/HAVERD!BB8 -> 50.837819 | O4: 2 | Q4: ='[25]Impulse responses'!DK10 -> 0.42339588 | R4: ='[25]Impulse responses'!EN10 -> 0.20175133 | U4: 40210 | V4: =NA() -> #N/A | W4: =((HAVERM!J140/HAVERM!J128)-1)*100 -> 1.3528749 | X4: =((HAVERM!K137/HAVERM!K125)-1)*100 -> 0.56369786 | Y4: 0 | Z4: =HAVERM!H140/HAVERM!I140 -> 63.592699 | AA4: =(Z4/AVERAGE($Z$63:$Z$74))*100 -> 104.41835 | AD4: 44228 | AE4: ='BoE MPR - Chart 2.21'!D8 -> 1.2 | AF4: =HAVERM!L266 -> 1.751 | AJ4: 43832 | AL4: =IF(HAVERD!H8="",AL3,AVERAGE(HAVERD!H8:Q8)) -> 37.246 | AZ4: 45323 | BA4: ='[26]CPI Forecast'!V343 -> 1.2718872 | BB4: ='[26]CPI Forecast'!AN343 -> 6.7134168 | BC4: 0.85340364 | BD4: 2.5013809 | BF4: 0 | BI4: 43862 | BJ4: ='[27]CPI Forecast'!D295 -> 1.7095297 | BK4: =NA() -> #N/A | BL4: =NA() -> #N/A | BM4: 2 | BP4: 20192 | BQ4: =LEFT(BP4,4) -> 2019 | BR4: ='[28]CPI Forecast'!AA582 -> 2.6615757 | BS4: 3.9354772 | BT4: 0 | BW4: 45627 | BX4: =HAVERM!M318 -> 64 | BY4: =HAVERM!N318 -> 54 | BZ4: =HAVERM!O318 -> 53 | CA4: =HAVERM!P318 -> 41 | CB4: =HAVERM!Q318 -> 7 | CC4: =HAVERM!R318 -> 4
A5: 43891 | B5: ='[24]CPI Forecast'!D296 -> 1.5233075 | C5: =NA() -> #N/A | D5: =NA() -> #N/A | E5: =NA() -> #N/A | F5: 2 | H5: =+H4+7 -> 43850 | I5: =HAVERW!C10 -> 127.18 | J5: =HAVERW!D10 -> 132.74 | L5: 43833 | M5: =HAVERD!BA9/HAVERD!BB9 -> 52.845777 | O5: 3 | Q5: ='[25]Impulse responses'!DK11 -> 0.57439711 | R5: ='[25]Impulse responses'!EN11 -> 0.34535061 | U5: 40238 | V5: =NA() -> #N/A | W5: =((HAVERM!J141/HAVERM!J129)-1)*100 -> 2.0385051 | X5: =((HAVERM!K138/HAVERM!K126)-1)*100 -> 0.78651685 | Y5: 0 | Z5: =HAVERM!H141/HAVERM!I141 -> 64.106823 | AA5: =(Z5/AVERAGE($Z$63:$Z$74))*100 -> 105.26253 | AD5: 44256 | AE5: ='BoE MPR - Chart 2.21'!D9 -> 1.2 | AF5: =HAVERM!L267 -> 1.891 | AJ5: 43833 | AL5: =IF(HAVERD!H9="",AL4,AVERAGE(HAVERD!H9:Q9)) -> 39.732 | AZ5: 45352 | BA5: ='[26]CPI Forecast'!V344 -> 0.80433786 | BB5: ='[26]CPI Forecast'!AN344 -> 6.0383119 | BC5: 0.85340364 | BD5: 2.5013809 | BF5: 0 | BI5: 43891 | BJ5: ='[27]CPI Forecast'!D296 -> 1.5233075 | BK5: =NA() -> #N/A | BL5: =NA() -> #N/A | BM5: 2 | BP5: 20193 | BQ5: =LEFT(BP5,4) -> 2019 | BR5: ='[28]CPI Forecast'!AA583 -> 2.4026482 | BS5: 3.8289728 | BT5: 0 | BW5: 45658 | BX5: =HAVERM!M319 -> 63 | BY5: =HAVERM!N319 -> 61 | BZ5: =HAVERM!O319 -> 54 | CA5: =HAVERM!P319 -> 37 | CB5: =HAVERM!Q319 -> 12 | CC5: =HAVERM!R319 -> 3
A6: 43922 | B6: ='[24]CPI Forecast'!D297 -> 0.76742263 | C6: =NA() -> #N/A | D6: =NA() -> #N/A | E6: =NA() -> #N/A | F6: 2 | H6: =+H5+7 -> 43857 | I6: =HAVERW!C11 -> 127.33 | J6: =HAVERW!D11 -> 132.88 | L6: 43836 | M6: =HAVERD!BA10/HAVERD!BB10 -> 53.385516 | O6: 4 | Q6: ='[25]Impulse responses'!DK12 -> 0.60063748 | R6: ='[25]Impulse responses'!EN12 -> 0.49550998 | U6: 40269 | V6: =NA() -> #N/A | W6: =((HAVERM!J142/HAVERM!J130)-1)*100 -> 2.8441411 | X6: =((HAVERM!K139/HAVERM!K127)-1)*100 -> -0.22396417 | Y6: 0 | Z6: =HAVERM!H142/HAVERM!I142 -> 63.298566 | AA6: =(Z6/AVERAGE($Z$63:$Z$74))*100 -> 103.93539 | AD6: 44287 | AE6: ='BoE MPR - Chart 2.21'!D10 -> 1.3 | AF6: =HAVERM!L268 -> 2.122 | AJ6: 43836 | AL6: =IF(HAVERD!H10="",AL5,AVERAGE(HAVERD!H10:Q10)) -> 38.667 | AZ6: 45383 | BA6: ='[26]CPI Forecast'!V345 -> -0.11452749 | BB6: ='[26]CPI Forecast'!AN345 -> 4.2109142 | BC6: 0.85340364 | BD6: 2.5013809 | BF6: 0 | BI6: 43922 | BJ6: ='[27]CPI Forecast'!D297 -> 0.76742263 | BK6: =NA() -> #N/A | BL6: =NA() -> #N/A | BM6: 2 | BP6: 20194 | BQ6: =LEFT(BP6,4) -> 2019 | BR6: ='[28]CPI Forecast'!AA584 -> 2.3727847 | BS6: 2.7146402 | BT6: 0
A7: 43952 | B7: ='[24]CPI Forecast'!D298 -> 0.47986067 | C7: =NA() -> #N/A | D7: =NA() -> #N/A | E7: =NA() -> #N/A | F7: 2 | H7: =+H6+7 -> 43864 | I7: =HAVERW!C12 -> 125.85 | J7: =HAVERW!D12 -> 131.48 | L7: 43837 | M7: =HAVERD!BA11/HAVERD!BB11 -> 52.385307 | O7: 5 | P7: t+1 | Q7: ='[25]Impulse responses'!DK13 -> 0.58307829 | R7: ='[25]Impulse responses'!EN13 -> 0.64127955 | U7: 40299 | V7: =NA() -> #N/A | W7: =((HAVERM!J143/HAVERM!J131)-1)*100 -> 1.8038331 | X7: =((HAVERM!K140/HAVERM!K128)-1)*100 -> -0.77864294 | Y7: 0 | Z7: =HAVERM!H143/HAVERM!I143 -> 65.905517 | AA7: =(Z7/AVERAGE($Z$63:$Z$74))*100 -> 108.21597 | AD7: 44317 | AE7: ='BoE MPR - Chart 2.21'!D11 -> 1.8 | AF7: =HAVERM!L269 -> 2.099 | AJ7: 43837 | AL7: =IF(HAVERD!H11="",AL6,AVERAGE(HAVERD!H11:Q11)) -> 37.814 | AZ7: 45413 | BA7: ='[26]CPI Forecast'!V346 -> -0.81732485 | BB7: ='[26]CPI Forecast'!AN346 -> 3.2502555 | BC7: 0.85340364 | BD7: 2.5013809 | BF7: 0 | BI7: 43952 | BJ7: ='[27]CPI Forecast'!D298 -> 0.47986067 | BK7: =NA() -> #N/A | BL7: =NA() -> #N/A | BM7: 2 | BP7: 20201 | BQ7: =LEFT(BP7,4) -> 2020 | BR7: ='[28]CPI Forecast'!AA585 -> 2.4420383 | BS7: 2.2067968 | BT7: 0
A8: 43983 | B8: ='[24]CPI Forecast'!D299 -> 0.60315196 | C8: =NA() -> #N/A | D8: =NA() -> #N/A | E8: =NA() -> #N/A | F8: 2 | H8: =+H7+7 -> 43871 | I8: =HAVERW!C13 -> 124.73 | J8: =HAVERW!D13 -> 129.7 | L8: =+L3+7 -> 43838 | M8: =HAVERD!BA12/HAVERD!BB12 -> 51.385602 | O8: 6 | Q8: ='[25]Impulse responses'!DK14 -> 0.55128787 | R8: ='[25]Impulse responses'!EN14 -> 0.77910152 | U8: 40330 | V8: =NA() -> #N/A | W8: =((HAVERM!J144/HAVERM!J132)-1)*100 -> 1.920904 | X8: =((HAVERM!K141/HAVERM!K129)-1)*100 -> -0.78037904 | Y8: 0 | Z8: =HAVERM!H144/HAVERM!I144 -> 64.968498 | AA8: =(Z8/AVERAGE($Z$63:$Z$74))*100 -> 106.67739 | AD8: 44348 | AE8: ='BoE MPR - Chart 2.21'!D12 -> 2.3 | AF8: =HAVERM!L270 -> 2.383 | AJ8: =+AJ3+7 -> 43838 | AL8: =IF(HAVERD!H12="",AL7,AVERAGE(HAVERD!H12:Q12)) -> 37.963 | AZ8: 45444 | BA8: ='[26]CPI Forecast'!V347 -> -0.90777218 | BB8: ='[26]CPI Forecast'!AN347 -> 2.9929787 | BC8: 0.85340364 | BD8: 2.5013809 | BF8: 0 | BI8: 43983 | BJ8: ='[27]CPI Forecast'!D299 -> 0.60315196 | BK8: =NA() -> #N/A | BL8: =NA() -> #N/A | BM8: 2 | BP8: 20202 | BQ8: =LEFT(BP8,4) -> 2020 | BR8: ='[28]CPI Forecast'!AA586 -> 1.9124297 | BS8: -1.1173184 | BT8: 0
A9: 44013 | B9: ='[24]CPI Forecast'!D300 -> 1.0403061 | C9: =NA() -> #N/A | D9: =NA() -> #N/A | E9: =NA() -> #N/A | F9: 2 | H9: =+H8+7 -> 43878 | I9: =HAVERW!C14 -> 123.8 | J9: =HAVERW!D14 -> 128.2 | L9: =+L4+7 -> 43839 | M9: =HAVERD!BA13/HAVERD!BB13 -> 51.023067 | O9: 7 | Q9: ='[25]Impulse responses'!DK15 -> 0.5160122 | R9: ='[25]Impulse responses'!EN15 -> 0.90810457 | U9: 40360 | V9: =NA() -> #N/A | W9: =((HAVERM!J145/HAVERM!J133)-1)*100 -> 3.2879819 | X9: =((HAVERM!K142/HAVERM!K130)-1)*100 -> -0.44493882 | Y9: 0 | Z9: =HAVERM!H145/HAVERM!I145 -> 65.363749 | AA9: =(Z9/AVERAGE($Z$63:$Z$74))*100 -> 107.32639 | AD9: 44378 | AE9: ='BoE MPR - Chart 2.21'!D13 -> 1.9 | AF9: =HAVERM!L271 -> 2.438 | AJ9: =+AJ4+7 -> 43839 | AL9: =IF(HAVERD!H13="",AL8,AVERAGE(HAVERD!H13:Q13)) -> 38.255 | AZ9: 45474 | BA9: ='[26]CPI Forecast'!V348 -> -0.69584436 | BB9: ='[26]CPI Forecast'!AN348 -> 2.9391016 | BC9: 0.85340364 | BD9: 2.5013809 | BF9: 0 | BI9: 44013 | BJ9: ='[27]CPI Forecast'!D300 -> 1.0403061 | BK9: =NA() -> #N/A | BL9: =NA() -> #N/A | BM9: 2 | BP9: 20203 | BQ9: =LEFT(BP9,4) -> 2020 | BR9: ='[28]CPI Forecast'!AA587 -> 1.3977684 | BS9: 1.4751077 | BT9: 0
A10: 44044 | B10: ='[24]CPI Forecast'!D301 -> 0.21960784 | C10: =NA() -> #N/A | D10: =NA() -> #N/A | E10: =NA() -> #N/A | F10: 2 | H10: =+H9+7 -> 43885 | I10: =HAVERW!C15 -> 123.45 | J10: =HAVERW!D15 -> 127.67 | L10: =+L5+7 -> 43840 | M10: =HAVERD!BA14/HAVERD!BB14 -> 51.117746 | O10: 8 | Q10: ='[25]Impulse responses'!DK16 -> 0.48109182 | R10: ='[25]Impulse responses'!EN16 -> 1.0283775 | U10: 40391 | V10: =NA() -> #N/A | W10: =((HAVERM!J146/HAVERM!J134)-1)*100 -> 4.109589 | X10: =((HAVERM!K143/HAVERM!K131)-1)*100 -> 0.11148272 | Y10: 0 | Z10: =HAVERM!H146/HAVERM!I146 -> 68.837803 | AA10: =(Z10/AVERAGE($Z$63:$Z$74))*100 -> 113.03074 | AD10: 44409 | AE10: ='BoE MPR - Chart 2.21'!D14 -> 4.5 | AF10: =HAVERM!L272 -> 2.647 | AJ10: =+AJ5+7 -> 43840 | AL10: =IF(HAVERD!H14="",AL9,AVERAGE(HAVERD!H14:Q14)) -> 37.688 | AZ10: 45505 | BA10: ='[26]CPI Forecast'!V349 -> -0.52653144 | BB10: ='[26]CPI Forecast'!AN349 -> 2.4618949 | BC10: 0.85340364 | BD10: 2.5013809 | BF10: 0 | BI10: 44044 | BJ10: ='[27]CPI Forecast'!D301 -> 0.21960784 | BK10: =NA() -> #N/A | BL10: =NA() -> #N/A | BM10: 2 | BP10: 20204 | BQ10: =LEFT(BP10,4) -> 2020 | BR10: ='[28]CPI Forecast'!AA588 -> 1.4487676 | BS10: 4.5482547 | BT10: 0
A11: 44075 | B11: ='[24]CPI Forecast'!D302 -> 0.53190018 | C11: =NA() -> #N/A | D11: =NA() -> #N/A | E11: =NA() -> #N/A | F11: 2 | H11: =+H10+7 -> 43892 | I11: =HAVERW!C16 -> 122.43 | J11: =HAVERW!D16 -> 126.62 | L11: =+L6+7 -> 43843 | M11: =HAVERD!BA15/HAVERD!BB15 -> 49.418291 | O11: 9 | P11: t+2 | Q11: ='[25]Impulse responses'!DK17 -> 0.44783231 | R11: ='[25]Impulse responses'!EN17 -> 1.1403356 | U11: 40422 | V11: =NA() -> #N/A | W11: =((HAVERM!J147/HAVERM!J135)-1)*100 -> 5.1843318 | X11: =((HAVERM!K144/HAVERM!K132)-1)*100 -> -0.33444816 | Y11: 0 | Z11: =HAVERM!H147/HAVERM!I147 -> 73.244319 | AA11: =(Z11/AVERAGE($Z$63:$Z$74))*100 -> 120.26618 | AD11: 44440 | AE11: ='BoE MPR - Chart 2.21'!D15 -> 3 | AF11: =HAVERM!L273 -> 2.736 | AJ11: =+AJ6+7 -> 43843 | AL11: =IF(HAVERD!H15="",AL10,AVERAGE(HAVERD!H15:Q15)) -> 38.188 | AZ11: 45536 | BA11: ='[26]CPI Forecast'!V350 -> -0.56232676 | BB11: ='[26]CPI Forecast'!AN350 -> 2.623591 | BC11: 0.85340364 | BD11: 2.5013809 | BF11: 0 | BI11: 44075 | BJ11: ='[27]CPI Forecast'!D302 -> 0.53190018 | BK11: =NA() -> #N/A | BL11: =NA() -> #N/A | BM11: 2 | BP11: 20211 | BQ11: =LEFT(BP11,4) -> 2021 | BR11: ='[28]CPI Forecast'!AA589 -> 1.5594583 | BS11: 4.1949478 | BT11: 0
A12: 44105 | B12: ='[24]CPI Forecast'!D303 -> 0.69715046 | C12: =NA() -> #N/A | D12: =NA() -> #N/A | E12: =NA() -> #N/A | F12: 2 | H12: =+H11+7 -> 43899 | I12: =HAVERW!C17 -> 122.24 | J12: =HAVERW!D17 -> 126.25 | L12: =+L7+7 -> 43844 | M12: =HAVERD!BA16/HAVERD!BB16 -> 49.538816 | O12: 10 | Q12: ='[25]Impulse responses'!DK18 -> 0.41661096 | R12: ='[25]Impulse responses'!EN18 -> 1.2444883 | U12: 40452 | V12: =NA() -> #N/A | W12: =((HAVERM!J148/HAVERM!J136)-1)*100 -> 4.5610034 | X12: =((HAVERM!K145/HAVERM!K133)-1)*100 -> 0.44792833 | Y12: 0 | Z12: =HAVERM!H148/HAVERM!I148 -> 75.715547 | AA12: =(Z12/AVERAGE($Z$63:$Z$74))*100 -> 124.3239 | AD12: 44470 | AE12: ='BoE MPR - Chart 2.21'!D16 -> 3.3 | AF12: =HAVERM!L274 -> 2.944 | AJ12: =+AJ7+7 -> 43844 | AL12: =IF(HAVERD!H16="",AL11,AVERAGE(HAVERD!H16:Q16)) -> 36.646 | AZ12: 45566 | BA12: ='[26]CPI Forecast'!V351 -> -0.29943167 | BB12: ='[26]CPI Forecast'!AN351 -> 2.7310615 | BC12: 0.85340364 | BD12: 2.5013809 | BF12: 0 | BI12: 44105 | BJ12: ='[27]CPI Forecast'!D303 -> 0.69715046 | BK12: =NA() -> #N/A | BL12: =NA() -> #N/A | BM12: 2 | BP12: 20212 | BQ12: =LEFT(BP12,4) -> 2021 | BR12: ='[28]CPI Forecast'!AA590 -> 1.8670632 | BS12: 8.8512241 | BT12: 0
A13: 44136 | B13: ='[24]CPI Forecast'!D304 -> 0.31506509 | C13: =NA() -> #N/A | D13: =NA() -> #N/A | E13: =NA() -> #N/A | F13: 2 | H13: =+H12+7 -> 43906 | I13: =HAVERW!C18 -> 120.33 | J13: =HAVERW!D18 -> 124.36 | L13: =+L8+7 -> 43845 | M13: =HAVERD!BA17/HAVERD!BB17 -> 48.598633 | O13: 11 | Q13: ='[25]Impulse responses'!DK19 -> 0.38746865 | R13: ='[25]Impulse responses'!EN19 -> 1.3413555 | U13: 40483 | V13: =NA() -> #N/A | W13: =((HAVERM!J149/HAVERM!J137)-1)*100 -> 5.5555556 | X13: =((HAVERM!K146/HAVERM!K134)-1)*100 -> 1.3513514 | Y13: 0 | Z13: =HAVERM!H149/HAVERM!I149 -> 77.814673 | AA13: =(Z13/AVERAGE($Z$63:$Z$74))*100 -> 127.77064 | AD13: 44501 | AE13: ='BoE MPR - Chart 2.21'!D17 -> 3.7 | AF13: =HAVERM!L275 -> 3.185 | AJ13: =+AJ8+7 -> 43845 | AL13: =IF(HAVERD!H17="",AL12,AVERAGE(HAVERD!H17:Q17)) -> 36.35 | AZ13: 45597 | BA13: ='[26]CPI Forecast'!V352 -> 0.32758672 | BB13: ='[26]CPI Forecast'!AN352 -> 3.2433227 | BC13: 0.85340364 | BD13: 2.5013809 | BF13: 0 | BI13: 44136 | BJ13: ='[27]CPI Forecast'!D304 -> 0.31506509 | BK13: =NA() -> #N/A | BL13: =NA() -> #N/A | BM13: 2 | BP13: 20213 | BQ13: =LEFT(BP13,4) -> 2021 | BR13: ='[28]CPI Forecast'!AA591 -> 2.4101613 | BS13: 6.0569477 | BT13: 0
A14: 44166 | B14: ='[24]CPI Forecast'!D305 -> 0.58876645 | C14: =NA() -> #N/A | D14: =NA() -> #N/A | E14: =NA() -> #N/A | F14: 2 | H14: =+H13+7 -> 43913 | I14: =HAVERW!C19 -> 119.64 | J14: =HAVERW!D19 -> 123.41 | L14: =+L9+7 -> 43846 | M14: =HAVERD!BA18/HAVERD!BB18 -> 49.460473 | O14: 12 | Q14: ='[25]Impulse responses'!DK20 -> 0.36032826 | R14: ='[25]Impulse responses'!EN20 -> 1.4314376 | U14: 40513 | V14: =NA() -> #N/A | W14: =((HAVERM!J150/HAVERM!J138)-1)*100 -> 6.1728395 | X14: =((HAVERM!K147/HAVERM!K135)-1)*100 -> 0.8988764 | Y14: 0 | Z14: =HAVERM!H150/HAVERM!I150 -> 82.932769 | AA14: =(Z14/AVERAGE($Z$63:$Z$74))*100 -> 136.17448 | AD14: 44531 | AE14: ='BoE MPR - Chart 2.21'!D18 -> 3.4 | AF14: =HAVERM!L276 -> 3.28 | AJ14: =+AJ9+7 -> 43846 | AL14: =IF(HAVERD!H18="",AL13,AVERAGE(HAVERD!H18:Q18)) -> 35.639 | AZ14: 45627 | BA14: ='[26]CPI Forecast'!V353 -> 0.53109473 | BB14: ='[26]CPI Forecast'!AN353 -> 2.825646 | BC14: 0.85340364 | BD14: 2.5013809 | BF14: 0 | BI14: 44166 | BJ14: ='[27]CPI Forecast'!D305 -> 0.58876645 | BK14: =NA() -> #N/A | BL14: =NA() -> #N/A | BM14: 2 | BP14: 20214 | BQ14: =LEFT(BP14,4) -> 2021 | BR14: ='[28]CPI Forecast'!AA592 -> 3.3237203 | BS14: 4.5267549 | BT14: 0
A15: 44197 | B15: ='[24]CPI Forecast'!D306 -> 0.70058043 | C15: =NA() -> #N/A | D15: =NA() -> #N/A | E15: =NA() -> #N/A | F15: 2 | H15: =+H14+7 -> 43920 | I15: =HAVERW!C20 -> 112.45 | J15: =HAVERW!D20 -> 118.6 | L15: =+L10+7 -> 43847 | M15: =HAVERD!BA19/HAVERD!BB19 -> 49.159567 | O15: 13 | P15: t+3 | Q15: ='[25]Impulse responses'!DK21 -> 0.33507514 | R15: ='[25]Impulse responses'!EN21 -> 1.5152064 | U15: 40544 | V15: =NA() -> #N/A | W15: =((HAVERM!J151/HAVERM!J139)-1)*100 -> 6.2992126 | X15: =((HAVERM!K148/HAVERM!K136)-1)*100 -> 2.027027 | Y15: 0 | Z15: =HAVERM!H151/HAVERM!I151 -> 84.710351 | AA15: =(Z15/AVERAGE($Z$63:$Z$74))*100 -> 139.09325 | AD15: 44562 | AE15: ='BoE MPR - Chart 2.21'!D19 -> 3.5 | AF15: =HAVERM!L277 -> 3.21 | AJ15: =+AJ10+7 -> 43847 | AL15: =IF(HAVERD!H19="",AL14,AVERAGE(HAVERD!H19:Q19)) -> 34.806 | AZ15: 45658 | BA15: ='[26]CPI Forecast'!V354 -> 0.67591702 | BB15: ='[26]CPI Forecast'!AN354 -> 3.1140094 | BC15: 0.85340364 | BD15: 2.5013809 | BF15: 0 | BI15: 44197 | BJ15: ='[27]CPI Forecast'!D306 -> 0.70058043 | BK15: =NA() -> #N/A | BL15: =NA() -> #N/A | BM15: 2 | BP15: 20221 | BQ15: =LEFT(BP15,4) -> 2022 | BR15: ='[28]CPI Forecast'!AA593 -> 3.574043 | BS15: 6.9863766 | BT15: 0
A16: 44228 | B16: ='[24]CPI Forecast'!D307 -> 0.41421589 | C16: =NA() -> #N/A | D16: =NA() -> #N/A | E16: =NA() -> #N/A | F16: 2 | H16: =+H15+7 -> 43927 | I16: =HAVERW!C21 -> 110.23 | J16: =HAVERW!D21 -> 116.83 | L16: =+L11+7 -> 43850 | M16: =HAVERD!BA20/HAVERD!BB20 -> 49.723034 | O16: 14 | Q16: ='[25]Impulse responses'!DK22 -> 0.31158664 | R16: ='[25]Impulse responses'!EN22 -> 1.593103 | U16: 40575 | V16: =NA() -> #N/A | W16: =((HAVERM!J152/HAVERM!J140)-1)*100 -> 6.2291435 | X16: =((HAVERM!K149/HAVERM!K137)-1)*100 -> 2.4663677 | Y16: 0 | Z16: =HAVERM!H152/HAVERM!I152 -> 85.368878 | AA16: =(Z16/AVERAGE($Z$63:$Z$74))*100 -> 140.17454 | AD16: 44593 | AE16: ='BoE MPR - Chart 2.21'!D20 -> 3.7 | AF16: =HAVERM!L278 -> 3.14 | AJ16: =+AJ11+7 -> 43850 | AL16: =IF(HAVERD!H20="",AL15,AVERAGE(HAVERD!H20:Q20)) -> 33.852 | AZ16: 45689 | BA16: ='[26]CPI Forecast'!V355 -> 0.7313925 | BB16: ='[26]CPI Forecast'!AN355 -> 3.3016893 | BC16: 0.85340364 | BD16: 2.5013809 | BF16: 0 | BI16: 44228 | BJ16: ='[27]CPI Forecast'!D307 -> 0.41421589 | BK16: =NA() -> #N/A | BL16: =NA() -> #N/A | BM16: 2 | BP16: 20222 | BQ16: =LEFT(BP16,4) -> 2022 | BR16: ='[28]CPI Forecast'!AA594 -> 4.939923 | BS16: 5.1326471 | BT16: 0
A17: 44256 | B17: ='[24]CPI Forecast'!D308 -> 0.71432517 | C17: =NA() -> #N/A | D17: =NA() -> #N/A | E17: =NA() -> #N/A | F17: 2 | H17: =+H16+7 -> 43934 | I17: =HAVERW!C22 -> 109.27 | J17: =HAVERW!D22 -> 116.15 | L17: =+L12+7 -> 43851 | M17: =HAVERD!BA21/HAVERD!BB21 -> 48.751723 | O17: 15 | Q17: ='[25]Impulse responses'!DK23 -> 0.28974269 | R17: ='[25]Impulse responses'!EN23 -> 1.6655387 | U17: 40603 | V17: =NA() -> #N/A | W17: =((HAVERM!J153/HAVERM!J141)-1)*100 -> 4.5504994 | X17: =((HAVERM!K150/HAVERM!K138)-1)*100 -> 2.8985507 | Y17: 0 | Z17: =HAVERM!H153/HAVERM!I153 -> 83.111579 | AA17: =(Z17/AVERAGE($Z$63:$Z$74))*100 -> 136.46809 | AD17: 44621 | AE17: ='BoE MPR - Chart 2.21'!D21 -> 4.4 | AF17: =HAVERM!L279 -> 3.42 | AJ17: =+AJ12+7 -> 43851 | AL17: =IF(HAVERD!H21="",AL16,AVERAGE(HAVERD!H21:Q21)) -> 33.969 | AZ17: 45717 | BA17: ='[26]CPI Forecast'!V356 -> 0.74696704 | BB17: ='[26]CPI Forecast'!AN356 -> 2.8692497 | BC17: 0.85340364 | BD17: 2.5013809 | BF17: 0 | BI17: 44256 | BJ17: ='[27]CPI Forecast'!D308 -> 0.71432517 | BK17: =NA() -> #N/A | BL17: =NA() -> #N/A | BM17: 2 | BP17: 20223 | BQ17: =LEFT(BP17,4) -> 2022 | BR17: ='[28]CPI Forecast'!AA595 -> 5.9272668 | BS17: 5.8823469 | BT17: 0
A18: 44287 | B18: ='[24]CPI Forecast'!D309 -> 1.5259222 | C18: =NA() -> #N/A | D18: =NA() -> #N/A | E18: =NA() -> #N/A | F18: 2 | H18: =+H17+7 -> 43941 | I18: =HAVERW!C23 -> 108.63 | J18: =HAVERW!D23 -> 115.73 | L18: =+L13+7 -> 43852 | M18: =HAVERD!BA22/HAVERD!BB22 -> 47.264287 | O18: 16 | Q18: ='[25]Impulse responses'!DK24 -> 0.26942937 | R18: ='[25]Impulse responses'!EN24 -> 1.732896 | U18: 40634 | V18: =NA() -> #N/A | W18: =((HAVERM!J154/HAVERM!J142)-1)*100 -> 4.3141593 | X18: =((HAVERM!K151/HAVERM!K139)-1)*100 -> 5.0505051 | Y18: 0 | Z18: =HAVERM!H154/HAVERM!I154 -> 83.389416 | AA18: =(Z18/AVERAGE($Z$63:$Z$74))*100 -> 136.92429 | AD18: 44652 | AE18: ='BoE MPR - Chart 2.21'!D22 -> 5.3 | AF18: =HAVERM!L280 -> 4.017 | AJ18: =+AJ13+7 -> 43852 | AL18: =IF(HAVERD!H22="",AL17,AVERAGE(HAVERD!H22:Q22)) -> 33.108 | AZ18: 45748 | BA18: ='[26]CPI Forecast'!V357 -> 0.94314358 | BB18: ='[26]CPI Forecast'!AN357 -> 3.0382419 | BC18: 0.85340364 | BD18: 2.5013809 | BF18: 0 | BI18: 44287 | BJ18: ='[27]CPI Forecast'!D309 -> 1.5259222 | BK18: =NA() -> #N/A | BL18: =NA() -> #N/A | BM18: 2 | BP18: 20224 | BQ18: =LEFT(BP18,4) -> 2022 | BR18: ='[28]CPI Forecast'!AA596 -> 6.4758868 | BS18: 6.355444 | BT18: 0
A19: 44317 | B19: ='[24]CPI Forecast'!D310 -> 2.1149485 | C19: =NA() -> #N/A | D19: =NA() -> #N/A | E19: =NA() -> #N/A | F19: 2 | H19: =+H18+7 -> 43948 | I19: =HAVERW!C24 -> 107.88 | J19: =HAVERW!D24 -> 115.22 | L19: =+L14+7 -> 43853 | M19: =HAVERD!BA23/HAVERD!BB23 -> 46.699192 | O19: 17 | P19: t+4 | Q19: ='[25]Impulse responses'!DK25 -> 0.2505399 | R19: ='[25]Impulse responses'!EN25 -> 1.795531 | U19: 40664 | V19: =NA() -> #N/A | W19: =((HAVERM!J155/HAVERM!J143)-1)*100 -> 5.7585825 | X19: =((HAVERM!K152/HAVERM!K140)-1)*100 -> 5.8295964 | Y19: 0 | Z19: =HAVERM!H155/HAVERM!I155 -> 82.822462 | AA19: =(Z19/AVERAGE($Z$63:$Z$74))*100 -> 135.99336 | AD19: 44682 | AE19: ='BoE MPR - Chart 2.21'!D23 -> 5.4 | AF19: =HAVERM!L281 -> 4.411 | AJ19: =+AJ14+7 -> 43853 | AL19: =IF(HAVERD!H23="",AL18,AVERAGE(HAVERD!H23:Q23)) -> 32.613 | AZ19: 45778 | BA19: ='[26]CPI Forecast'!V358 -> 1.1539396 | BB19: ='[26]CPI Forecast'!AN358 -> 3.4199924 | BC19: 0.85340364 | BD19: 2.5013809 | BF19: 0 | BI19: 44317 | BJ19: ='[27]CPI Forecast'!D310 -> 2.1149485 | BK19: =NA() -> #N/A | BL19: =NA() -> #N/A | BM19: 2 | BP19: 20231 | BQ19: =LEFT(BP19,4) -> 2023 | BR19: ='[28]CPI Forecast'!AA597 -> 6.3958967 | BS19: 6.3087995 | BT19: 0
A20: 44348 | B20: ='[24]CPI Forecast'!D311 -> 2.5141826 | C20: =NA() -> #N/A | D20: =NA() -> #N/A | E20: =NA() -> #N/A | F20: 2 | H20: =+H19+7 -> 43955 | I20: =HAVERW!C25 -> 107.56 | J20: =HAVERW!D25 -> 114.94 | L20: =+L15+7 -> 43854 | M20: =HAVERD!BA24/HAVERD!BB24 -> 45.412107 | O20: 18 | Q20: ='[25]Impulse responses'!DK26 -> 0.23297464 | R20: ='[25]Impulse responses'!EN26 -> 1.8537747 | U20: 40695 | V20: =NA() -> #N/A | W20: =((HAVERM!J156/HAVERM!J144)-1)*100 -> 6.9844789 | X20: =((HAVERM!K153/HAVERM!K141)-1)*100 -> 6.741573 | Y20: 0 | Z20: =HAVERM!H156/HAVERM!I156 -> 83.138029 | AA20: =(Z20/AVERAGE($Z$63:$Z$74))*100 -> 136.51152 | AD20: 44713 | AE20: ='BoE MPR - Chart 2.21'!D24 -> 5.5 | AF20: =HAVERM!L282 -> 4.743 | AJ20: =+AJ15+7 -> 43854 | AL20: =IF(HAVERD!H24="",AL19,AVERAGE(HAVERD!H24:Q24)) -> 32.742 | AZ20: 45809 | BA20: ='[26]CPI Forecast'!V359 -> 1.5126528 | BB20: ='[26]CPI Forecast'!AN359 -> 3.4488504 | BC20: 0.85340364 | BD20: 2.5013809 | BF20: 0 | BI20: 44348 | BJ20: ='[27]CPI Forecast'!D311 -> 2.5141826 | BK20: =NA() -> #N/A | BL20: =NA() -> #N/A | BM20: 2 | BP20: 20232 | BQ20: =LEFT(BP20,4) -> 2023 | BR20: ='[28]CPI Forecast'!AA598 -> 7.1599978 | BS20: 8.1733292 | BT20: 0
A21: 44378 | B21: ='[24]CPI Forecast'!D312 -> 2.0399369 | C21: =NA() -> #N/A | D21: =NA() -> #N/A | E21: =NA() -> #N/A | F21: 2 | H21: =+H20+7 -> 43962 | I21: =HAVERW!C26 -> 107.45 | J21: =HAVERW!D26 -> 114.83 | L21: =+L16+7 -> 43857 | M21: =HAVERD!BA25/HAVERD!BB25 -> 44.837623 | O21: 19 | Q21: ='[25]Impulse responses'!DK27 -> 0.21664083 | R21: ='[25]Impulse responses'!EN27 -> 1.9079349 | U21: 40725 | V21: =NA() -> #N/A | W21: =((HAVERM!J157/HAVERM!J145)-1)*100 -> 6.1470911 | X21: =((HAVERM!K154/HAVERM!K142)-1)*100 -> 6.8156425 | Y21: 0 | Z21: =HAVERM!H157/HAVERM!I157 -> 82.378445 | AA21: =(Z21/AVERAGE($Z$63:$Z$74))*100 -> 135.26429 | AD21: 44743 | AE21: ='BoE MPR - Chart 2.21'!D25 -> 5.7 | AF21: =HAVERM!L283 -> 4.682 | AJ21: =+AJ16+7 -> 43857 | AL21: =IF(HAVERD!H25="",AL20,AVERAGE(HAVERD!H25:Q25)) -> 32.896 | AZ21: 45839 | BA21: ='[26]CPI Forecast'!V360 -> 1.1535605 | BB21: ='[26]CPI Forecast'!AN360 -> 3.4288316 | BC21: 0.85340364 | BD21: 2.5013809 | BF21: 0 | BI21: 44378 | BJ21: ='[27]CPI Forecast'!D312 -> 2.0399369 | BK21: =NA() -> #N/A | BL21: =NA() -> #N/A | BM21: 2 | BP21: 20233 | BQ21: =LEFT(BP21,4) -> 2023 | BR21: ='[28]CPI Forecast'!AA599 -> 7.0600784 | BS21: 7.7130583 | BT21: 0
A22: 44409 | B22: ='[24]CPI Forecast'!D313 -> 3.1966707 | C22: =NA() -> #N/A | D22: =NA() -> #N/A | E22: =NA() -> #N/A | F22: 2 | H22: =+H21+7 -> 43969 | I22: =HAVERW!C27 -> 105.09 | J22: =HAVERW!D27 -> 112.22 | L22: =+L17+7 -> 43858 | M22: =HAVERD!BA26/HAVERD!BB26 -> 45.72903 | O22: 20 | Q22: ='[25]Impulse responses'!DK28 -> 0.20145217 | R22: ='[25]Impulse responses'!EN28 -> 1.9582979 | U22: 40756 | V22: =NA() -> #N/A | W22: =((HAVERM!J158/HAVERM!J146)-1)*100 -> 6.25 | X22: =((HAVERM!K155/HAVERM!K143)-1)*100 -> 7.0155902 | Y22: 0 | Z22: =HAVERM!H158/HAVERM!I158 -> 81.172009 | AA22: =(Z22/AVERAGE($Z$63:$Z$74))*100 -> 133.28334 | AD22: 44774 | AE22: ='BoE MPR - Chart 2.21'!D26 -> 6 | AF22: =HAVERM!L284 -> 4.833 | AJ22: =+AJ17+7 -> 43858 | AL22: =IF(HAVERD!H26="",AL21,AVERAGE(HAVERD!H26:Q26)) -> 33.714 | AZ22: 45870 | BA22: ='[26]CPI Forecast'!V361 -> 1.2150545 | BB22: ='[26]CPI Forecast'!AN361 -> 3.5305889 | BC22: 0.85340364 | BD22: 2.5013809 | BF22: 0 | BI22: 44409 | BJ22: ='[27]CPI Forecast'!D313 -> 3.1966707 | BK22: =NA() -> #N/A | BL22: =NA() -> #N/A | BM22: 2 | BP22: 20234 | BQ22: =LEFT(BP22,4) -> 2023 | BR22: ='[28]CPI Forecast'!AA600 -> 6.4104318 | BS22: 5.9228031 | BT22: 0
A23: 44440 | B23: ='[24]CPI Forecast'!D314 -> 3.080069 | C23: =NA() -> #N/A | D23: =NA() -> #N/A | E23: =NA() -> #N/A | F23: 2 | H23: =+H22+7 -> 43976 | I23: =HAVERW!C28 -> 104.87 | J23: =HAVERW!D28 -> 111.7 | L23: =+L18+7 -> 43859 | M23: =HAVERD!BA27/HAVERD!BB27 -> 45.738462 | O23: 21 | P23: t+5 | Q23: ='[25]Impulse responses'!DK29 -> 0.18732838 | R23: ='[25]Impulse responses'!EN29 -> 2.00513 | U23: 40787 | V23: =NA() -> #N/A | W23: =((HAVERM!J159/HAVERM!J147)-1)*100 -> 6.3526835 | X23: =((HAVERM!K156/HAVERM!K144)-1)*100 -> 7.9418345 | Y23: 0 | Z23: =HAVERM!H159/HAVERM!I159 -> 82.430463 | AA23: =(Z23/AVERAGE($Z$63:$Z$74))*100 -> 135.3497 | AD23: 44805 | AE23: ='BoE MPR - Chart 2.21'!D27 -> 5.9 | AF23: =HAVERM!L285 -> 5.087 | AJ23: =+AJ18+7 -> 43859 | AL23: =IF(HAVERD!H27="",AL22,AVERAGE(HAVERD!H27:Q27)) -> 32.498 | AZ23: 45901 | BA23: ='[26]CPI Forecast'!V362 -> 1.3320921 | BB23: ='[26]CPI Forecast'!AN362 -> 3.3390454 | BC23: 0.85340364 | BD23: 2.5013809 | BF23: 0 | BI23: 44440 | BJ23: ='[27]CPI Forecast'!D314 -> 3.080069 | BK23: =NA() -> #N/A | BL23: =NA() -> #N/A | BM23: 2 | BP23: 20241 | BQ23: =LEFT(BP23,4) -> 2024 | BR23: ='[28]CPI Forecast'!AA601 -> 6.2048304 | BS23: 5.9344095 | BT23: 0
A24: 44470 | B24: ='[24]CPI Forecast'!D315 -> 4.2062117 | C24: =NA() -> #N/A | D24: =NA() -> #N/A | E24: =NA() -> #N/A | F24: 2 | H24: =+H23+7 -> 43983 | I24: =HAVERW!C29 -> 105.17 | J24: =HAVERW!D29 -> 111.76 | L24: =+L19+7 -> 43860 | M24: =HAVERD!BA28/HAVERD!BB28 -> 44.061069 | O24: 22 | Q24: ='[25]Impulse responses'!DK30 -> 0.1741948 | R24: ='[25]Impulse responses'!EN30 -> 2.0486787 | U24: 40817 | V24: =NA() -> #N/A | W24: =((HAVERM!J160/HAVERM!J148)-1)*100 -> 4.9073064 | X24: =((HAVERM!K157/HAVERM!K145)-1)*100 -> 8.0267559 | Y24: 0 | Z24: =HAVERM!H160/HAVERM!I160 -> 79.695431 | AA24: =(Z24/AVERAGE($Z$63:$Z$74))*100 -> 130.85882 | AD24: 44835 | AE24: ='BoE MPR - Chart 2.21'!D28 -> 6.2 | AF24: =HAVERM!L286 -> 5.573 | AJ24: =+AJ19+7 -> 43860 | AL24: =IF(HAVERD!H28="",AL23,AVERAGE(HAVERD!H28:Q28)) -> 31.61 | AZ24: 45931 | BA24: ='[26]CPI Forecast'!V363 -> 0.96235044 | BB24: ='[26]CPI Forecast'!AN363 -> 3.3689461 | BC24: 0.85340364 | BD24: 2.5013809 | BF24: 0 | BI24: 44470 | BJ24: ='[27]CPI Forecast'!D315 -> 4.2062117 | BK24: =NA() -> #N/A | BL24: =NA() -> #N/A | BM24: 2 | BP24: 20242 | BQ24: =LEFT(BP24,4) -> 2024 | BR24: ='[28]CPI Forecast'!AA602 -> 5.7581862 | BS24: 4.5638948 | BT24: 0
A25: 44501 | B25: ='[24]CPI Forecast'!D316 -> 5.1299005 | C25: =NA() -> #N/A | D25: =NA() -> #N/A | E25: =NA() -> #N/A | F25: 2 | H25: =+H24+7 -> 43990 | I25: =HAVERW!C30 -> 105.74 | J25: =HAVERW!D30 -> 111.98 | L25: =+L20+7 -> 43861 | M25: =HAVERD!BA29/HAVERD!BB29 -> 43.834889 | O25: 23 | Q25: ='[25]Impulse responses'!DK31 -> 0.16198201 | R25: ='[25]Impulse responses'!EN31 -> 2.0891742 | U25: 40848 | V25: =NA() -> #N/A | W25: =((HAVERM!J161/HAVERM!J149)-1)*100 -> 3.9742213 | X25: =((HAVERM!K158/HAVERM!K146)-1)*100 -> 7.5555556 | Y25: 0 | Z25: =HAVERM!H161/HAVERM!I161 -> 79.663376 | AA25: =(Z25/AVERAGE($Z$63:$Z$74))*100 -> 130.80618 | AD25: 44866 | AE25: ='BoE MPR - Chart 2.21'!D29 -> 6.7 | AF25: =HAVERM!L287 -> 5.899 | AJ25: =+AJ20+7 -> 43861 | AL25: =IF(HAVERD!H29="",AL24,AVERAGE(HAVERD!H29:Q29)) -> 32.048 | AZ25: 45962 | BA25: ='[26]CPI Forecast'!V364 -> 1.155022 | BB25: ='[26]CPI Forecast'!AN364 -> 3.0784852 | BC25: 0.85340364 | BD25: 2.5013809 | BF25: 0 | BI25: 44501 | BJ25: ='[27]CPI Forecast'!D316 -> 5.1299005 | BK25: =NA() -> #N/A | BL25: =NA() -> #N/A | BM25: 2 | BP25: 20243 | BQ25: =LEFT(BP25,4) -> 2024 | BR25: ='[28]CPI Forecast'!AA603 -> 5.2248195 | BS25: 4.4066047 | BT25: 0
A26: 44531 | B26: ='[24]CPI Forecast'!D317 -> 5.3860457 | C26: =NA() -> #N/A | D26: =NA() -> #N/A | E26: =NA() -> #N/A | F26: 2 | H26: =+H25+7 -> 43997 | I26: =HAVERW!C31 -> 106.37 | J26: =HAVERW!D31 -> 112.53 | L26: =+L21+7 -> 43864 | M26: =HAVERD!BA30/HAVERD!BB30 -> 41.496965 | O26: 24 | Q26: ='[25]Impulse responses'!DK32 -> 0.15062546 | R26: ='[25]Impulse responses'!EN32 -> 2.1268306 | U26: 40878 | V26: =NA() -> #N/A | W26: =((HAVERM!J162/HAVERM!J150)-1)*100 -> 3.6997886 | X26: =((HAVERM!K159/HAVERM!K147)-1)*100 -> 8.1291759 | Y26: 0 | Z26: =HAVERM!H162/HAVERM!I162 -> 78.216234 | AA26: =(Z26/AVERAGE($Z$63:$Z$74))*100 -> 128.43 | AD26: 44896 | AE26: ='BoE MPR - Chart 2.21'!D30 -> 6.8 | AF26: =HAVERM!L288 -> 6.046 | AJ26: =+AJ21+7 -> 43864 | AL26: =IF(HAVERD!H30="",AL25,AVERAGE(HAVERD!H30:Q30)) -> 31.264 | AZ26: 45992 | BA26: ='[26]CPI Forecast'!V365 -> 1.1539155 | BB26: ='[26]CPI Forecast'!AN365 -> 3.1671163 | BC26: 0.85340364 | BD26: 2.5013809 | BF26: 0 | BI26: 44531 | BJ26: ='[27]CPI Forecast'!D317 -> 5.3860457 | BK26: =NA() -> #N/A | BL26: =NA() -> #N/A | BM26: 2 | BP26: 20244 | BQ26: =LEFT(BP26,4) -> 2024 | BR26: ='[28]CPI Forecast'!AA604 -> 4.795296 | BS26: 5.9910132 | BT26: 0
A27: 44562 | B27: ='[24]CPI Forecast'!D318 -> 5.4555133 | C27: =NA() -> #N/A | D27: =NA() -> #N/A | E27: =NA() -> #N/A | F27: 2 | H27: =+H26+7 -> 44004 | I27: =HAVERW!C32 -> 107.13 | J27: =HAVERW!D32 -> 112.98 | L27: =+L22+7 -> 43865 | M27: =HAVERD!BA31/HAVERD!BB31 -> 41.381958 | O27: 25 | P27: 2031 | Q27: ='[25]Impulse responses'!DK33 -> 0.14006512 | R27: ='[25]Impulse responses'!EN33 -> 2.1618469 | U27: 40909 | V27: =((AA15/AA3)-1)*100 -> 34.488084 | W27: =((HAVERM!J163/HAVERM!J151)-1)*100 -> 3.4920635 | X27: =((HAVERM!K160/HAVERM!K148)-1)*100 -> 7.3951435 | Y27: 0 | Z27: =HAVERM!H163/HAVERM!I163 -> 78.787879 | AA27: =(Z27/AVERAGE($Z$63:$Z$74))*100 -> 129.36863 | AD27: 44927 | AE27: ='BoE MPR - Chart 2.21'!D31 -> 6.4 | AF27: =HAVERM!L289 -> 6.272 | AJ27: =+AJ22+7 -> 43865 | AL27: =IF(HAVERD!H31="",AL26,AVERAGE(HAVERD!H31:Q31)) -> 31.947 | AZ27: 46023 | BA27: ='[26]CPI Forecast'!V366 -> 1.1718623 | BB27: ='[26]CPI Forecast'!AN366 -> 3.2384129 | BC27: 0.85340364 | BD27: 2.5013809 | BF27: 0 | BI27: 44562 | BJ27: ='[27]CPI Forecast'!D318 -> 5.4555133 | BK27: =NA() -> #N/A | BL27: =NA() -> #N/A | BM27: 2 | BP27: 20251 | BQ27: =LEFT(BP27,4) -> 2025 | BR27: ='[28]CPI Forecast'!AA605 -> 4.7054626 | BS27: 5.6993959 | BT27: 0
A28: 44593 | B28: ='[24]CPI Forecast'!D319 -> 6.1766081 | C28: =NA() -> #N/A | D28: =NA() -> #N/A | E28: =NA() -> #N/A | F28: 2 | H28: =+H27+7 -> 44011 | I28: =HAVERW!C33 -> 108.31 | J28: =HAVERW!D33 -> 114.1 | L28: =+L23+7 -> 43866 | M28: =HAVERD!BA32/HAVERD!BB32 -> 42.637092 | O28: 26 | Q28: ='[25]Impulse responses'!DK34 -> 0.13024516 | R28: ='[25]Impulse responses'!EN34 -> 2.1944081 | U28: 40940 | V28: =((AA16/AA4)-1)*100 -> 34.243205 | W28: =((HAVERM!J164/HAVERM!J152)-1)*100 -> 3.6649215 | X28: =((HAVERM!K161/HAVERM!K149)-1)*100 -> 6.7833698 | Y28: 0 | Z28: =HAVERM!H164/HAVERM!I164 -> 79.29376 | AA28: =(Z28/AVERAGE($Z$63:$Z$74))*100 -> 130.19928 | AD28: 44958 | AE28: ='BoE MPR - Chart 2.21'!D32 -> 7.5 | AF28: =HAVERM!L290 -> 6.464 | AJ28: =+AJ23+7 -> 43866 | AL28: =IF(HAVERD!H32="",AL27,AVERAGE(HAVERD!H32:Q32)) -> 32.545 | AZ28: 46054 | BA28: ='[26]CPI Forecast'!V367 -> 1.1652859 | BB28: ='[26]CPI Forecast'!AN367 -> 3.246811 | BC28: 0.85340364 | BD28: 2.5013809 | BF28: 0 | BI28: 44593 | BJ28: ='[27]CPI Forecast'!D319 -> 6.1766081 | BK28: =NA() -> #N/A | BL28: =NA() -> #N/A | BM28: 2 | BP28: 20252 | BQ28: =LEFT(BP28,4) -> 2025 | BR28: ='[28]CPI Forecast'!AA606 -> 3.5468013 | BS28: 5.5549469 | BT28: 0
A29: 44621 | B29: ='[24]CPI Forecast'!D320 -> 7.023124 | C29: =NA() -> #N/A | D29: =NA() -> #N/A | E29: =NA() -> #N/A | F29: 2 | H29: =+H28+7 -> 44018 | I29: =HAVERW!C34 -> 109.43 | J29: =HAVERW!D34 -> 115.05 | L29: =+L24+7 -> 43867 | M29: =HAVERD!BA33/HAVERD!BB33 -> 42.679248 | O29: 27 | Q29: ='[25]Impulse responses'!DK35 -> 0.12111368 | R29: ='[25]Impulse responses'!EN35 -> 2.2246866 | U29: 40969 | V29: =((AA17/AA5)-1)*100 -> 29.64545 | W29: =((HAVERM!J165/HAVERM!J153)-1)*100 -> 4.5647558 | X29: =((HAVERM!K162/HAVERM!K150)-1)*100 -> 5.8504875 | Y29: 0 | Z29: =HAVERM!H165/HAVERM!I165 -> 79.44132 | AA29: =(Z29/AVERAGE($Z$63:$Z$74))*100 -> 130.44157 | AD29: 44986 | AE29: ='BoE MPR - Chart 2.21'!D33 -> 7.2 | AF29: =HAVERM!L291 -> 6.574 | AJ29: =+AJ24+7 -> 43867 | AL29: =IF(HAVERD!H33="",AL28,AVERAGE(HAVERD!H33:Q33)) -> 32.332 | AZ29: 46082 | BA29: ='[26]CPI Forecast'!V368 -> 1.1586351 | BB29: ='[26]CPI Forecast'!AN368 -> 3.2706631 | BC29: 0.85340364 | BD29: 2.5013809 | BF29: 0 | BI29: 44621 | BJ29: ='[27]CPI Forecast'!D320 -> 7.023124 | BK29: =NA() -> #N/A | BL29: =NA() -> #N/A | BM29: 2 | BP29: 20253 | BQ29: =LEFT(BP29,4) -> 2025 | BR29: ='[28]CPI Forecast'!AA607 -> 3.6082961 | BS29: 5.225741 | BT29: 0
A30: 44652 | B30: ='[24]CPI Forecast'!D321 -> 9.0106617 | C30: =NA() -> #N/A | D30: =NA() -> #N/A | E30: =NA() -> #N/A | F30: 2 | H30: =+H29+7 -> 44025 | I30: =HAVERW!C35 -> 111.24 | J30: =HAVERW!D35 -> 116.75 | L30: =+L25+7 -> 43868 | M30: =HAVERD!BA34/HAVERD!BB34 -> 42.143906 | O30: 28 | Q30: ='[25]Impulse responses'!DK36 -> 0.11262241 | R30: ='[25]Impulse responses'!EN36 -> 2.2528422 | U30: 41000 | V30: =((AA18/AA6)-1)*100 -> 31.739818 | W30: =((HAVERM!J166/HAVERM!J154)-1)*100 -> 4.3478261 | X30: =((HAVERM!K163/HAVERM!K151)-1)*100 -> 4.9145299 | Y30: 0 | Z30: =HAVERM!H166/HAVERM!I166 -> 77.682028 | AA30: =(Z30/AVERAGE($Z$63:$Z$74))*100 -> 127.55284 | AD30: 45017 | AE30: ='BoE MPR - Chart 2.21'!D34 -> 7.1 | AF30: =HAVERM!L292 -> 6.422 | AJ30: =+AJ25+7 -> 43868 | AL30: =IF(HAVERD!H34="",AL29,AVERAGE(HAVERD!H34:Q34)) -> 32.474 | AZ30: 46113 | BA30: ='[26]CPI Forecast'!V369 -> 1.1595054 | BB30: ='[26]CPI Forecast'!AN369 -> 3.1441456 | BC30: 0.85340364 | BD30: 2.5013809 | BF30: 0 | BI30: 44652 | BJ30: ='[27]CPI Forecast'!D321 -> 9.0106617 | BK30: =NA() -> #N/A | BL30: =NA() -> #N/A | BM30: 2 | BP30: 20254 | BQ30: =LEFT(BP30,4) -> 2025 | BR30: ='[28]CPI Forecast'!AA608 -> 3.8236673 | BS30: 4.0656286 | BT30: 0
A31: 44682 | B31: ='[24]CPI Forecast'!D322 -> 9.0827013 | C31: =NA() -> #N/A | D31: =NA() -> #N/A | E31: =NA() -> #N/A | F31: 2 | H31: =+H30+7 -> 44032 | I31: =HAVERW!C36 -> 112.23 | J31: =HAVERW!D36 -> 117.35 | L31: =+L26+7 -> 43871 | M31: =HAVERD!BA35/HAVERD!BB35 -> 41.313936 | O31: 29 | P31: 2032 | Q31: ='[25]Impulse responses'!DK37 -> 0.10472646 | R31: ='[25]Impulse responses'!EN37 -> 2.2790238 | U31: 41030 | V31: =((AA19/AA7)-1)*100 -> 25.66848 | W31: =((HAVERM!J167/HAVERM!J155)-1)*100 -> 3.3507853 | X31: =((HAVERM!K164/HAVERM!K152)-1)*100 -> 4.2372881 | Y31: 0 | Z31: =HAVERM!H167/HAVERM!I167 -> 74.819239 | AA31: =(Z31/AVERAGE($Z$63:$Z$74))*100 -> 122.85218 | AD31: 45047 | AE31: ='BoE MPR - Chart 2.21'!D35 -> 7.2 | AF31: =HAVERM!L293 -> 6.186 | AJ31: =+AJ26+7 -> 43871 | AL31: =IF(HAVERD!H35="",AL30,AVERAGE(HAVERD!H35:Q35)) -> 31.623 | AZ31: 46143 | BA31: ='[26]CPI Forecast'!V370 -> 1.1537379 | BB31: ='[26]CPI Forecast'!AN370 -> 2.9827404 | BC31: 0.85340364 | BD31: 2.5013809 | BF31: 0 | BI31: 44682 | BJ31: ='[27]CPI Forecast'!D322 -> 9.0827013 | BK31: =NA() -> #N/A | BL31: =NA() -> #N/A | BM31: 2 | BP31: 20261 | BQ31: =LEFT(BP31,4) -> 2026 | BR31: ='[28]CPI Forecast'!AA609 -> 4.1016154 | BS31: 3.4308593 | BT31: 0
A32: 44713 | B32: ='[24]CPI Forecast'!D323 -> 9.4121135 | C32: =NA() -> #N/A | D32: =NA() -> #N/A | E32: =NA() -> #N/A | F32: 2 | H32: =+H31+7 -> 44039 | I32: =HAVERW!C37 -> 112.66 | J32: =HAVERW!D37 -> 117.76 | L32: =+L27+7 -> 43872 | M32: =HAVERD!BA36/HAVERD!BB36 -> 41.714948 | O32: 30 | Q32: ='[25]Impulse responses'!DK38 -> 0.097384096 | R32: ='[25]Impulse responses'!EN38 -> 2.3033698 | U32: 41061 | V32: =((AA20/AA8)-1)*100 -> 27.966678 | W32: =((HAVERM!J168/HAVERM!J156)-1)*100 -> 2.1761658 | X32: =((HAVERM!K165/HAVERM!K153)-1)*100 -> 4.2105263 | Y32: 0 | Z32: =HAVERM!H168/HAVERM!I168 -> 74.369019 | AA32: =(Z32/AVERAGE($Z$63:$Z$74))*100 -> 122.11292 | AD32: 45078 | AE32: ='BoE MPR - Chart 2.21'!D36 -> 7.1 | AF32: =HAVERM!L294 -> 5.904 | AJ32: =+AJ27+7 -> 43872 | AL32: =IF(HAVERD!H36="",AL31,AVERAGE(HAVERD!H36:Q36)) -> 31.567 | AZ32: 46174 | BA32: ='[26]CPI Forecast'!V371 -> 1.1555319 | BB32: ='[26]CPI Forecast'!AN371 -> 2.8290204 | BC32: 0.85340364 | BD32: 2.5013809 | BF32: 0 | BI32: 44713 | BJ32: ='[27]CPI Forecast'!D323 -> 9.4121135 | BK32: =NA() -> #N/A | BL32: =NA() -> #N/A | BM32: 2 | BP32: 20262 | BQ32: =LEFT(BP32,4) -> 2026 | BR32: ='[28]CPI Forecast'!AA610 -> 3.9247882 | BS32: 2.911259 | BT32: 0
A33: 44743 | B33: ='[24]CPI Forecast'!D324 -> 10.100901 | C33: =NA() -> #N/A | D33: =NA() -> #N/A | E33: =NA() -> #N/A | F33: 2 | H33: =+H32+7 -> 44046 | I33: =HAVERW!C38 -> 112.91 | J33: =HAVERW!D38 -> 117.97 | L33: =+L28+7 -> 43873 | M33: =HAVERD!BA37/HAVERD!BB37 -> 42.805395 | O33: 31 | Q33: ='[25]Impulse responses'!DK39 -> 0.090556503 | R33: ='[25]Impulse responses'!EN39 -> 2.3260089 | U33: 41091 | V33: =((AA21/AA9)-1)*100 -> 26.030784 | W33: =((HAVERM!J169/HAVERM!J157)-1)*100 -> 2.1716649 | X33: =((HAVERM!K166/HAVERM!K154)-1)*100 -> 3.7656904 | Y33: 0 | Z33: =HAVERM!H169/HAVERM!I169 -> 78.260312 | AA33: =(Z33/AVERAGE($Z$63:$Z$74))*100 -> 128.50237 | AD33: 45108 | AE33: ='BoE MPR - Chart 2.21'!D37 -> 6.7 | AF33: =HAVERM!L295 -> 5.764 | AJ33: =+AJ28+7 -> 43873 | AL33: =IF(HAVERD!H37="",AL32,AVERAGE(HAVERD!H37:Q37)) -> 32.284 | AZ33: 46204 | BA33: ='[26]CPI Forecast'!V372 -> 1.1825363 | BB33: ='[26]CPI Forecast'!AN372 -> 2.6459875 | BC33: 0.85340364 | BD33: 2.5013809 | BF33: 0 | BI33: 44743 | BJ33: ='[27]CPI Forecast'!D324 -> 10.100901 | BK33: =NA() -> #N/A | BL33: =NA() -> #N/A | BM33: 2 | BP33: 20263 | BQ33: =LEFT(BP33,4) -> 2026 | BR33: ='[28]CPI Forecast'!AA611 -> 3.7535341 | BS33: 2.788756 | BT33: 0
A34: 44774 | B34: ='[24]CPI Forecast'!D325 -> 9.8701878 | C34: =NA() -> #N/A | D34: =NA() -> #N/A | E34: =NA() -> #N/A | F34: 2 | H34: =+H33+7 -> 44053 | I34: =HAVERW!C39 -> 113.02 | J34: =HAVERW!D39 -> 118.01 | L34: =+L29+7 -> 43874 | M34: =HAVERD!BA38/HAVERD!BB38 -> 43.155879 | O34: 32 | Q34: ='[25]Impulse responses'!DK40 -> 0.084207593 | R34: ='[25]Impulse responses'!EN40 -> 2.3470608 | U34: 41122 | V34: =((AA22/AA10)-1)*100 -> 17.917779 | W34: =((HAVERM!J170/HAVERM!J158)-1)*100 -> 2.1671827 | X34: =((HAVERM!K167/HAVERM!K155)-1)*100 -> 3.5379813 | Y34: 0 | Z34: =HAVERM!H170/HAVERM!I170 -> 78.376487 | AA34: =(Z34/AVERAGE($Z$63:$Z$74))*100 -> 128.69313 | AD34: 45139 | AE34: ='BoE MPR - Chart 2.21'!D38 -> 6.5 | AF34: =HAVERM!L296 -> 5.65 | AJ34: =+AJ29+7 -> 43874 | AL34: =IF(HAVERD!H38="",AL33,AVERAGE(HAVERD!H38:Q38)) -> 32.695 | AZ34: 46235 | BA34: ='[26]CPI Forecast'!V373 -> 1.1625584 | BB34: ='[26]CPI Forecast'!AN373 -> 2.5042719 | BC34: 0.85340364 | BD34: 2.5013809 | BF34: 0 | BI34: 44774 | BJ34: ='[27]CPI Forecast'!D325 -> 9.8701878 | BK34: =NA() -> #N/A | BL34: =NA() -> #N/A | BM34: 2 | BP34: 20264 | BQ34: =LEFT(BP34,4) -> 2026 | BR34: ='[28]CPI Forecast'!AA612 -> 3.677327 | BS34: 2.7377058 | BT34: 0
A35: 44805 | B35: ='[24]CPI Forecast'!D326 -> 10.095628 | C35: =NA() -> #N/A | D35: =NA() -> #N/A | E35: =NA() -> #N/A | F35: 2 | H35: =+H34+7 -> 44060 | I35: =HAVERW!C40 -> 113.04 | J35: =HAVERW!D40 -> 118 | L35: =+L30+7 -> 43875 | M35: =HAVERD!BA39/HAVERD!BB39 -> 44.076521 | O35: 33 | P35: 2033 | Q35: ='[25]Impulse responses'!DK41 -> 0.078303804 | R35: ='[25]Impulse responses'!EN41 -> 2.3666368 | U35: 41153 | V35: =((AA23/AA11)-1)*100 -> 12.541784 | W35: =((HAVERM!J171/HAVERM!J159)-1)*100 -> 1.9567456 | X35: =((HAVERM!K168/HAVERM!K156)-1)*100 -> 2.9015544 | Y35: 0 | Z35: =HAVERM!H171/HAVERM!I171 -> 77.624721 | AA35: =(Z35/AVERAGE($Z$63:$Z$74))*100 -> 127.45874 | AD35: 45170 | AE35: ='BoE MPR - Chart 2.21'!D39 -> 6.6 | AF35: =HAVERM!L297 -> 5.492 | AJ35: =+AJ30+7 -> 43875 | AL35: =IF(HAVERD!H39="",AL34,AVERAGE(HAVERD!H39:Q39)) -> 33.108 | AZ35: 46266 | BA35: ='[26]CPI Forecast'!V374 -> 1.1374184 | BB35: ='[26]CPI Forecast'!AN374 -> 2.3710297 | BC35: 0.85340364 | BD35: 2.5013809 | BF35: 0 | BI35: 44805 | BJ35: ='[27]CPI Forecast'!D326 -> 10.095628 | BK35: =NA() -> #N/A | BL35: =NA() -> #N/A | BM35: 2 | BP35: 20271 | BQ35: =LEFT(BP35,4) -> 2027 | BR35: ='[28]CPI Forecast'!AA613 -> 3.6428281 | BS35: 2.6525913 | BT35: 0
A36: 44835 | B36: ='[24]CPI Forecast'!D327 -> 11.051566 | C36: =NA() -> #N/A | D36: =NA() -> #N/A | E36: =NA() -> #N/A | F36: 2 | H36: =+H35+7 -> 44067 | I36: =HAVERW!C41 -> 113.22 | J36: =HAVERW!D41 -> 118.14 | L36: =+L31+7 -> 43878 | M36: =HAVERD!BA40/HAVERD!BB40 -> 44.464093 | O36: 34 | Q36: ='[25]Impulse responses'!DK42 -> 0.072813929 | R36: ='[25]Impulse responses'!EN42 -> 2.3848403 | U36: 41183 | V36: =((AA24/AA12)-1)*100 -> 5.2563642 | W36: =((HAVERM!J172/HAVERM!J160)-1)*100 -> 3.4303534 | X36: =((HAVERM!K169/HAVERM!K157)-1)*100 -> 2.6831785 | Y36: 0 | Z36: =HAVERM!H172/HAVERM!I172 -> 77.119224 | AA36: =(Z36/AVERAGE($Z$63:$Z$74))*100 -> 126.62872 | AD36: 45200 | AE36: ='BoE MPR - Chart 2.21'!D40 -> 6.4 | AF36: =HAVERM!L298 -> 5.545 | AJ36: =+AJ31+7 -> 43878 | AL36: =IF(HAVERD!H40="",AL35,AVERAGE(HAVERD!H40:Q40)) -> 34.343 | AZ36: 46296 | BA36: ='[26]CPI Forecast'!V375 -> 1.1367631 | BB36: ='[26]CPI Forecast'!AN375 -> 2.2152762 | BC36: 0.85340364 | BD36: 2.5013809 | BF36: 0 | BI36: 44835 | BJ36: ='[27]CPI Forecast'!D327 -> 11.051566 | BK36: =NA() -> #N/A | BL36: =NA() -> #N/A | BM36: 2 | BP36: 20272 | BQ36: =LEFT(BP36,4) -> 2027 | BR36: ='[28]CPI Forecast'!AA614 -> 3.5743155 | BS36: 2.5922215 | BT36: 0
A37: 44866 | B37: ='[24]CPI Forecast'!D328 -> 10.672013 | C37: =NA() -> #N/A | D37: =NA() -> #N/A | E37: =NA() -> #N/A | F37: 2 | H37: =+H36+7 -> 44074 | I37: =HAVERW!C42 -> 113.29 | J37: =HAVERW!D42 -> 118.18 | L37: =+L32+7 -> 43879 | M37: =HAVERD!BA41/HAVERD!BB41 -> 43.990182 | O37: 35 | Q37: ='[25]Impulse responses'!DK43 -> 0.067708949 | R37: ='[25]Impulse responses'!EN43 -> 2.4017675 | U37: 41214 | V37: =((AA25/AA13)-1)*100 -> 2.375777 | W37: =((HAVERM!J173/HAVERM!J161)-1)*100 -> 3.9256198 | X37: =((HAVERM!K170/HAVERM!K158)-1)*100 -> 3.0991736 | Y37: 0 | Z37: =HAVERM!H173/HAVERM!I173 -> 77.376104 | AA37: =(Z37/AVERAGE($Z$63:$Z$74))*100 -> 127.05051 | AD37: 45231 | AE37: ='BoE MPR - Chart 2.21'!D41 -> 5.7 | AF37: =HAVERM!L299 -> 5.444 | AJ37: =+AJ32+7 -> 43879 | AL37: =IF(HAVERD!H41="",AL36,AVERAGE(HAVERD!H41:Q41)) -> 33.835 | AZ37: 46327 | BA37: ='[26]CPI Forecast'!V376 -> 1.1225308 | BB37: ='[26]CPI Forecast'!AN376 -> 2.0715836 | BC37: 0.85340364 | BD37: 2.5013809 | BF37: 0 | BI37: 44866 | BJ37: ='[27]CPI Forecast'!D328 -> 10.672013 | BK37: =NA() -> #N/A | BL37: =NA() -> #N/A | BM37: 2 | BP37: 20273 | BQ37: =LEFT(BP37,4) -> 2027 | BR37: ='[28]CPI Forecast'!AA615 -> 3.52096 | BS37: 2.5478114 | BT37: 0
A38: 44896 | B38: ='[24]CPI Forecast'!D329 -> 10.528374 | C38: =NA() -> #N/A | D38: =NA() -> #N/A | E38: =NA() -> #N/A | F38: 2 | H38: =+H37+7 -> 44081 | I38: =HAVERW!C43 -> 113.37 | J38: =HAVERW!D43 -> 118.22 | L38: =+L33+7 -> 43880 | M38: =HAVERD!BA42/HAVERD!BB42 -> 46.112269 | O38: 36 | Q38: ='[25]Impulse responses'!DK44 -> 0.062961879 | R38: ='[25]Impulse responses'!EN44 -> 2.417508 | U38: 41244 | V38: =((AA26/AA14)-1)*100 -> -5.6871799 | W38: =((HAVERM!J174/HAVERM!J162)-1)*100 -> 3.7716616 | X38: =((HAVERM!K171/HAVERM!K159)-1)*100 -> 2.9866117 | Y38: 0 | Z38: =HAVERM!H174/HAVERM!I174 -> 76.065411 | AA38: =(Z38/AVERAGE($Z$63:$Z$74))*100 -> 124.89837 | AD38: 45261 | AE38: ='BoE MPR - Chart 2.21'!D42 -> 5.8 | AF38: =HAVERM!L300 -> 5.297 | AJ38: =+AJ33+7 -> 43880 | AL38: =IF(HAVERD!H42="",AL37,AVERAGE(HAVERD!H42:Q42)) -> 33.529 | AZ38: 46357 | BA38: ='[26]CPI Forecast'!V377 -> 1.1124769 | BB38: ='[26]CPI Forecast'!AN377 -> 1.9244644 | BC38: 0.85340364 | BD38: 2.5013809 | BF38: 0 | BI38: 44896 | BJ38: ='[27]CPI Forecast'!D329 -> 10.528374 | BK38: =NA() -> #N/A | BL38: =NA() -> #N/A | BM38: 2 | BP38: 20274 | BQ38: =LEFT(BP38,4) -> 2027 | BR38: ='[28]CPI Forecast'!AA616 -> 3.4518878 | BS38: 2.5453632 | BT38: 0
A39: 44927 | B39: ='[24]CPI Forecast'!D330 -> 10.051524 | C39: =NA() -> #N/A | D39: =NA() -> #N/A | E39: =NA() -> #N/A | F39: 2 | H39: =+H38+7 -> 44088 | I39: =HAVERW!C44 -> 113.32 | J39: =HAVERW!D44 -> 118.18 | L39: =+L34+7 -> 43881 | M39: =HAVERD!BA43/HAVERD!BB43 -> 46.36286 | O39: 37 | P39: 2034 | Q39: ='[25]Impulse responses'!DK45 -> 0.058547626 | R39: ='[25]Impulse responses'!EN45 -> 2.4321449 | U39: 41275 | V39: =((AA27/AA15)-1)*100 -> -6.9914391 | W39: =((HAVERM!J175/HAVERM!J163)-1)*100 -> 4.192229 | X39: =((HAVERM!K172/HAVERM!K160)-1)*100 -> 3.1860226 | Y39: 0 | Z39: =HAVERM!H175/HAVERM!I175 -> 77.332832 | AA39: =(Z39/AVERAGE($Z$63:$Z$74))*100 -> 126.97946 | AD39: 45292 | AE39: ='BoE MPR - Chart 2.21'!D43 -> 6.3 | AF39: =HAVERM!L301 -> 5.175 | AJ39: =+AJ34+7 -> 43881 | AL39: =IF(HAVERD!H43="",AL38,AVERAGE(HAVERD!H43:Q43)) -> 33.237 | BI39: 44927 | BJ39: ='[27]CPI Forecast'!D330 -> 10.051524 | BK39: =NA() -> #N/A | BL39: =NA() -> #N/A | BM39: 2
A40: 44958 | B40: ='[24]CPI Forecast'!D331 -> 10.416397 | C40: =NA() -> #N/A | D40: =NA() -> #N/A | E40: =NA() -> #N/A | F40: 2 | H40: =+H39+7 -> 44095 | I40: =HAVERW!C45 -> 113.31 | J40: =HAVERW!D45 -> 118.16 | L40: =+L35+7 -> 43882 | M40: =HAVERD!BA44/HAVERD!BB44 -> 45.209073 | O40: 38 | Q40: ='[25]Impulse responses'!DK46 -> 0.054442855 | R40: ='[25]Impulse responses'!EN46 -> 2.4457556 | U40: 41306 | V40: =((AA28/AA16)-1)*100 -> -7.1163142 | W40: =((HAVERM!J176/HAVERM!J164)-1)*100 -> 3.6363636 | X40: =((HAVERM!K173/HAVERM!K161)-1)*100 -> 3.2786885 | Y40: 0 | Z40: =HAVERM!H176/HAVERM!I176 -> 79.661455 | AA40: =(Z40/AVERAGE($Z$63:$Z$74))*100 -> 130.80303 | AD40: 45323 | AE40: ='BoE MPR - Chart 2.21'!D44 -> 5.2 | AF40: =HAVERM!L302 -> 4.977 | AJ40: =+AJ35+7 -> 43882 | AL40: =IF(HAVERD!H44="",AL39,AVERAGE(HAVERD!H44:Q44)) -> 32.786 | BI40: 44958 | BJ40: ='[27]CPI Forecast'!D331 -> 10.416397 | BK40: =NA() -> #N/A | BL40: =NA() -> #N/A | BM40: 2
A41: 44986 | B41: ='[24]CPI Forecast'!D332 -> 10.056877 | C41: =NA() -> #N/A | D41: =NA() -> #N/A | E41: =NA() -> #N/A | F41: 2 | H41: =+H40+7 -> 44102 | I41: =HAVERW!C46 -> 113.3 | J41: =HAVERW!D46 -> 118.14 | L41: =+L36+7 -> 43885 | M41: =HAVERD!BA45/HAVERD!BB45 -> 43.361188 | O41: 39 | Q41: ='[25]Impulse responses'!DK47 -> 0.05062587 | R41: ='[25]Impulse responses'!EN47 -> 2.4584121 | U41: 41334 | V41: =((AA29/AA17)-1)*100 -> -4.4160623 | W41: =((HAVERM!J177/HAVERM!J165)-1)*100 -> 3.7563452 | X41: =((HAVERM!K174/HAVERM!K162)-1)*100 -> 3.3776868 | Y41: 0 | Z41: =HAVERM!H177/HAVERM!I177 -> 81.520297 | AA41: =(Z41/AVERAGE($Z$63:$Z$74))*100 -> 133.85522 | AD41: 45352 | AE41: ='BoE MPR - Chart 2.21'!D45 -> 5.1 | AF41: =HAVERM!L303 -> 4.817 | AJ41: =+AJ36+7 -> 43885 | AL41: =IF(HAVERD!H45="",AL40,AVERAGE(HAVERD!H45:Q45)) -> 31.309 | BI41: 44986 | BJ41: ='[27]CPI Forecast'!D332 -> 10.056877 | BK41: =NA() -> #N/A | BL41: =NA() -> #N/A | BM41: 2
A42: 45017 | B42: ='[24]CPI Forecast'!D333 -> 8.6582359 | C42: =NA() -> #N/A | D42: =NA() -> #N/A | E42: =NA() -> #N/A | F42: 2 | H42: =+H41+7 -> 44109 | I42: =HAVERW!C47 -> 113.26 | J42: =HAVERW!D47 -> 118.11 | L42: =+L37+7 -> 43886 | M42: =HAVERD!BA46/HAVERD!BB46 -> 43.569453 | O42: 40 | Q42: ='[25]Impulse responses'!DK48 -> 0.047076494 | R42: ='[25]Impulse responses'!EN48 -> 2.4701812 | U42: 41365 | V42: =((AA30/AA18)-1)*100 -> -6.8442589 | W42: =((HAVERM!J178/HAVERM!J166)-1)*100 -> 4.5731707 | X42: =((HAVERM!K175/HAVERM!K163)-1)*100 -> 3.4623218 | Y42: 0 | Z42: =HAVERM!H178/HAVERM!I178 -> 80.242883 | AA42: =(Z42/AVERAGE($Z$63:$Z$74))*100 -> 131.75773 | AD42: 45383 | AE42: ='BoE MPR - Chart 2.21'!D46 -> 5.1 | AF42: =HAVERM!L304 -> 4.52 | AJ42: =+AJ37+7 -> 43886 | AL42: =IF(HAVERD!H46="",AL41,AVERAGE(HAVERD!H46:Q46)) -> 30.931 | BI42: 45017 | BJ42: ='[27]CPI Forecast'!D333 -> 8.6582359 | BK42: =NA() -> #N/A | BL42: =NA() -> #N/A | BM42: 2
A43: 45047 | B43: ='[24]CPI Forecast'!D334 -> 8.680682 | C43: =NA() -> #N/A | D43: =NA() -> #N/A | E43: =NA() -> #N/A | F43: 2 | H43: =+H42+7 -> 44116 | I43: =HAVERW!C48 -> 113.19 | J43: =HAVERW!D48 -> 118.05 | L43: =+L38+7 -> 43887 | M43: =HAVERD!BA47/HAVERD!BB47 -> 42.548579 | U43: 41395 | V43: =((AA31/AA19)-1)*100 -> -9.6631066 | W43: =((HAVERM!J179/HAVERM!J167)-1)*100 -> 4.2553191 | X43: =((HAVERM!K176/HAVERM!K164)-1)*100 -> 3.4552846 | Y43: 0 | Z43: =HAVERM!H179/HAVERM!I179 -> 79.947661 | AA43: =(Z43/AVERAGE($Z$63:$Z$74))*100 -> 131.27298 | AD43: 45413 | AE43: ='BoE MPR - Chart 2.21'!D47 -> 4.8 | AF43: =HAVERM!L305 -> 4.444 | AJ43: =+AJ38+7 -> 43887 | AL43: =IF(HAVERD!H47="",AL42,AVERAGE(HAVERD!H47:Q47)) -> 31.204 | BI43: 45047 | BJ43: ='[27]CPI Forecast'!D334 -> 8.680682 | BK43: =NA() -> #N/A | BL43: =NA() -> #N/A | BM43: 2
A44: 45078 | B44: ='[24]CPI Forecast'!D335 -> 7.9496843 | C44: =NA() -> #N/A | D44: =NA() -> #N/A | E44: =NA() -> #N/A | F44: 2 | H44: =+H43+7 -> 44123 | I44: =HAVERW!C49 -> 113.18 | J44: =HAVERW!D49 -> 118.08 | L44: =+L39+7 -> 43888 | M44: =HAVERD!BA48/HAVERD!BB48 -> 40.54222 | U44: 41426 | V44: =((AA32/AA20)-1)*100 -> -10.547531 | W44: =((HAVERM!J180/HAVERM!J168)-1)*100 -> 3.8539554 | X44: =((HAVERM!K177/HAVERM!K165)-1)*100 -> 3.3333333 | Y44: 0 | Z44: =HAVERM!H180/HAVERM!I180 -> 78.110867 | AA44: =(Z44/AVERAGE($Z$63:$Z$74))*100 -> 128.25698 | AD44: 45444 | AE44: ='BoE MPR - Chart 2.21'!D48 -> 4.6 | AF44: =HAVERM!L306 -> 4.364 | AJ44: =+AJ39+7 -> 43888 | AL44: =IF(HAVERD!H48="",AL43,AVERAGE(HAVERD!H48:Q48)) -> 30.917 | BI44: 45078 | BJ44: ='[27]CPI Forecast'!D335 -> 7.9496843 | BK44: =NA() -> #N/A | BL44: =NA() -> #N/A | BM44: 2
A45: 45108 | B45: ='[24]CPI Forecast'!D336 -> 6.8272142 | C45: =NA() -> #N/A | D45: =NA() -> #N/A | E45: =NA() -> #N/A | F45: 2 | H45: =+H44+7 -> 44130 | I45: =HAVERW!C50 -> 113.14 | J45: =HAVERW!D50 -> 118.08 | L45: =+L40+7 -> 43889 | M45: =HAVERD!BA49/HAVERD!BB49 -> 40.16124 | U45: 41456 | V45: =((AA33/AA21)-1)*100 -> -4.9990426 | W45: =((HAVERM!J181/HAVERM!J169)-1)*100 -> 3.8461538 | X45: =((HAVERM!K178/HAVERM!K166)-1)*100 -> 3.7298387 | Y45: 0 | Z45: =HAVERM!H181/HAVERM!I181 -> 77.774848 | AA45: =(Z45/AVERAGE($Z$63:$Z$74))*100 -> 127.70525 | AD45: 45474 | AE45: ='BoE MPR - Chart 2.21'!D49 -> 4.8 | AF45: =HAVERM!L307 -> 4.307 | AJ45: =+AJ40+7 -> 43889 | AL45: =IF(HAVERD!H49="",AL44,AVERAGE(HAVERD!H49:Q49)) -> 32.133 | BI45: 45108 | BJ45: ='[27]CPI Forecast'!D336 -> 6.8272142 | BK45: =NA() -> #N/A | BL45: =NA() -> #N/A | BM45: 2
A46: 45139 | B46: ='[24]CPI Forecast'!D337 -> 6.6570306 | C46: =NA() -> #N/A | D46: =NA() -> #N/A | E46: =NA() -> #N/A | F46: 2 | H46: =+H45+7 -> 44137 | I46: =HAVERW!C51 -> 113.11 | J46: =HAVERW!D51 -> 118.06 | L46: =+L41+7 -> 43892 | M46: =HAVERD!BA50/HAVERD!BB50 -> 41.198619 | U46: 41487 | V46: =((AA34/AA22)-1)*100 -> -3.443948 | W46: =((HAVERM!J182/HAVERM!J170)-1)*100 -> 4.1414141 | X46: =((HAVERM!K179/HAVERM!K167)-1)*100 -> 3.718593 | Y46: 0 | Z46: =HAVERM!H182/HAVERM!I182 -> 74.933901 | AA46: =(Z46/AVERAGE($Z$63:$Z$74))*100 -> 123.04045 | AD46: 45505 | AE46: ='BoE MPR - Chart 2.21'!D50 -> 4.8 | AF46: =HAVERM!L308 -> 4.264 | AJ46: =+AJ41+7 -> 43892 | AL46: =IF(HAVERD!H50="",AL45,AVERAGE(HAVERD!H50:Q50)) -> 32.871 | BI46: 45139 | BJ46: ='[27]CPI Forecast'!D337 -> 6.6570306 | BK46: =NA() -> #N/A | BL46: =NA() -> #N/A | BM46: 2
A47: 45170 | B47: ='[24]CPI Forecast'!D338 -> 6.6521767 | C47: =NA() -> #N/A | D47: =NA() -> #N/A | E47: =NA() -> #N/A | F47: 2 | H47: =+H46+7 -> 44144 | I47: =HAVERW!C52 -> 112.5 | J47: =HAVERW!D52 -> 117.28 | L47: =+L42+7 -> 43893 | M47: =HAVERD!BA51/HAVERD!BB51 -> 40.752009 | U47: 41518 | V47: =((AA35/AA23)-1)*100 -> -5.8300563 | W47: =((HAVERM!J183/HAVERM!J171)-1)*100 -> 4.2424242 | X47: =((HAVERM!K180/HAVERM!K168)-1)*100 -> 4.2296073 | Y47: 0 | Z47: =HAVERM!H183/HAVERM!I183 -> 73.369051 | AA47: =(Z47/AVERAGE($Z$63:$Z$74))*100 -> 120.47099 | AD47: 45536 | AE47: ='BoE MPR - Chart 2.21'!D51 -> 4.6 | AF47: =HAVERM!L309 -> 4.103 | AJ47: =+AJ42+7 -> 43893 | AL47: =IF(HAVERD!H51="",AL46,AVERAGE(HAVERD!H51:Q51)) -> 34.092 | BI47: 45170 | BJ47: ='[27]CPI Forecast'!D338 -> 6.6521767 | BK47: =NA() -> #N/A | BL47: =NA() -> #N/A | BM47: 2
A48: 45200 | B48: ='[24]CPI Forecast'!D339 -> 4.599878 | C48: =NA() -> #N/A | D48: =NA() -> #N/A | E48: =NA() -> #N/A | F48: 2 | H48: =+H47+7 -> 44151 | I48: =HAVERW!C53 -> 112.35 | J48: =HAVERW!D53 -> 117.07 | L48: =+L43+7 -> 43894 | M48: =HAVERD!BA52/HAVERD!BB52 -> 40.449263 | U48: 41548 | V48: =((AA36/AA24)-1)*100 -> -3.2325663 | W48: =((HAVERM!J184/HAVERM!J172)-1)*100 -> 3.919598 | X48: =((HAVERM!K181/HAVERM!K169)-1)*100 -> 4.2211055 | Y48: 0 | Z48: =HAVERM!H184/HAVERM!I184 -> 73.754194 | AA48: =(Z48/AVERAGE($Z$63:$Z$74))*100 -> 121.10339 | AD48: 45566 | AE48: ='BoE MPR - Chart 2.21'!D52 -> 4.2 | AF48: =HAVERM!L310 -> 4 | AJ48: =+AJ43+7 -> 43894 | AL48: =IF(HAVERD!H52="",AL47,AVERAGE(HAVERD!H52:Q52)) -> 33.781 | BI48: 45200 | BJ48: ='[27]CPI Forecast'!D339 -> 4.599878 | BK48: =NA() -> #N/A | BL48: =NA() -> #N/A | BM48: 2
A49: 45231 | B49: ='[24]CPI Forecast'!D340 -> 3.9409917 | C49: =NA() -> #N/A | D49: =NA() -> #N/A | E49: =NA() -> #N/A | F49: 2 | H49: =+H48+7 -> 44158 | I49: =HAVERW!C54 -> 112.42 | J49: =HAVERW!D54 -> 117.13 | L49: =+L44+7 -> 43895 | M49: =HAVERD!BA53/HAVERD!BB53 -> 39.691998 | U49: 41579 | V49: =((AA37/AA25)-1)*100 -> -2.8711714 | W49: =((HAVERM!J185/HAVERM!J173)-1)*100 -> 2.7833002 | X49: =((HAVERM!K182/HAVERM!K170)-1)*100 -> 3.7074148 | Y49: 0 | Z49: =HAVERM!H185/HAVERM!I185 -> 73.646299 | AA49: =(Z49/AVERAGE($Z$63:$Z$74))*100 -> 120.92622 | AD49: 45597 | AE49: ='BoE MPR - Chart 2.21'!D53 -> 4.6 | AF49: =HAVERM!L311 -> 3.902 | AJ49: =+AJ44+7 -> 43895 | AL49: =IF(HAVERD!H53="",AL48,AVERAGE(HAVERD!H53:Q53)) -> 33.383 | BI49: 45231 | BJ49: ='[27]CPI Forecast'!D340 -> 3.9409917 | BK49: =NA() -> #N/A | BL49: =NA() -> #N/A | BM49: 2
A50: 45261 | B50: ='[24]CPI Forecast'!D341 -> 3.9932685 | C50: =NA() -> #N/A | D50: =NA() -> #N/A | E50: =NA() -> #N/A | F50: 2 | H50: =+H49+7 -> 44165 | I50: =HAVERW!C55 -> 112.61 | J50: =HAVERW!D55 -> 117.41 | L50: =+L45+7 -> 43896 | M50: =HAVERD!BA54/HAVERD!BB54 -> 34.998849 | U50: 41609 | V50: =((AA38/AA26)-1)*100 -> -2.7498413 | W50: =((HAVERM!J186/HAVERM!J174)-1)*100 -> 1.9646365 | X50: =((HAVERM!K183/HAVERM!K171)-1)*100 -> 3.6 | Y50: 0 | Z50: =HAVERM!H186/HAVERM!I186 -> 72.183206 | AA50: =(Z50/AVERAGE($Z$63:$Z$74))*100 -> 118.52385 | AD50: 45627 | AE50: ='BoE MPR - Chart 2.21'!D54 -> 4.4 | AF50: =HAVERM!L312 -> 3.867 | AJ50: =+AJ45+7 -> 43896 | AL50: =IF(HAVERD!H54="",AL49,AVERAGE(HAVERD!H54:Q54)) -> 32.557 | BI50: 45261 | BJ50: ='[27]CPI Forecast'!D341 -> 3.9932685 | BK50: =NA() -> #N/A | BL50: =NA() -> #N/A | BM50: 2
A51: 45292 | B51: ='[24]CPI Forecast'!D342 -> 3.9811146 | C51: =NA() -> #N/A | D51: =NA() -> #N/A | E51: =NA() -> #N/A | F51: 2 | H51: =+H50+7 -> 44172 | I51: =HAVERW!C56 -> 113.17 | J51: =HAVERW!D56 -> 117.99 | L51: =+L46+7 -> 43899 | M51: =HAVERD!BA55/HAVERD!BB55 -> 26.948894 | U51: 41640 | V51: =((AA39/AA27)-1)*100 -> -1.8467902 | W51: =((HAVERM!J187/HAVERM!J175)-1)*100 -> 1.9627085 | X51: =((HAVERM!K184/HAVERM!K172)-1)*100 -> 3.0876494 | Y51: 0 | Z51: =HAVERM!H187/HAVERM!I187 -> 70.55252 | AA51: =(Z51/AVERAGE($Z$63:$Z$74))*100 -> 115.84628 | AD51: 45658 | AF51: =HAVERM!L313 -> 3.69 | AJ51: =+AJ46+7 -> 43899 | AL51: =IF(HAVERD!H55="",AL50,AVERAGE(HAVERD!H55:Q55)) -> 31.41 | BI51: 45292 | BJ51: ='[27]CPI Forecast'!D342 -> 3.9811146 | BK51: =NA() -> #N/A | BL51: =NA() -> #N/A | BM51: 2
A52: 45323 | B52: ='[24]CPI Forecast'!D343 -> 3.4114722 | C52: =NA() -> #N/A | D52: =NA() -> #N/A | E52: =NA() -> #N/A | F52: 2 | H52: =+H51+7 -> 44179 | I52: =HAVERW!C57 -> 113.82 | J52: =HAVERW!D57 -> 118.57 | L52: =+L47+7 -> 43900 | M52: =HAVERD!BA56/HAVERD!BB56 -> 27.505413 | U52: 41671 | V52: =((AA40/AA28)-1)*100 -> 0.463712 | W52: =((HAVERM!J188/HAVERM!J176)-1)*100 -> 1.8518519 | X52: =((HAVERM!K185/HAVERM!K173)-1)*100 -> 2.7777778 | Y52: 0 | Z52: =HAVERM!H188/HAVERM!I188 -> 71.588097 | AA52: =(Z52/AVERAGE($Z$63:$Z$74))*100 -> 117.54668 | AD52: 45689 | AF52: =HAVERM!L314 -> 3.525 | AJ52: =+AJ47+7 -> 43900 | AL52: =IF(HAVERD!H56="",AL51,AVERAGE(HAVERD!H56:Q56)) -> 32.733 | BI52: 45323 | BJ52: ='[27]CPI Forecast'!D343 -> 3.4114722 | BK52: =NA() -> #N/A | BL52: =NA() -> #N/A | BM52: 2
A53: 45352 | B53: ='[24]CPI Forecast'!D344 -> 3.2280593 | C53: =NA() -> #N/A | D53: =NA() -> #N/A | E53: =NA() -> #N/A | F53: 2 | H53: =+H52+7 -> 44186 | I53: =HAVERW!C58 -> 114.43 | J53: =HAVERW!D58 -> 119.17 | L53: =+L48+7 -> 43901 | M53: =HAVERD!BA57/HAVERD!BB57 -> 26.732366 | U53: 41699 | V53: =((AA41/AA29)-1)*100 -> 2.6169978 | W53: =((HAVERM!J189/HAVERM!J177)-1)*100 -> 1.6634051 | X53: =((HAVERM!K186/HAVERM!K174)-1)*100 -> 2.1782178 | Y53: 0 | Z53: =HAVERM!H189/HAVERM!I189 -> 73.456864 | AA53: =(Z53/AVERAGE($Z$63:$Z$74))*100 -> 120.61518 | AD53: 45717 | AF53: =HAVERM!L315 -> 3.543 | AJ53: =+AJ48+7 -> 43901 | AL53: =IF(HAVERD!H57="",AL52,AVERAGE(HAVERD!H57:Q57)) -> 33.003 | BI53: 45352 | BJ53: ='[27]CPI Forecast'!D344 -> 3.2280593 | BK53: =NA() -> #N/A | BL53: =NA() -> #N/A | BM53: 2
A54: 45383 | B54: ='[24]CPI Forecast'!D345 -> 2.3330701 | C54: =NA() -> #N/A | D54: =NA() -> #N/A | E54: =NA() -> #N/A | F54: 2 | H54: =+H53+7 -> 44193 | I54: =HAVERW!C59 -> 114.91 | J54: =HAVERW!D59 -> 119.65 | L54: =+L49+7 -> 43902 | M54: =HAVERD!BA58/HAVERD!BB58 -> 24.736842 | U54: 41730 | V54: =((AA42/AA30)-1)*100 -> 3.2965862 | W54: =((HAVERM!J190/HAVERM!J178)-1)*100 -> 0.48590865 | X54: =((HAVERM!K187/HAVERM!K175)-1)*100 -> 1.476378 | Y54: 0 | Z54: =HAVERM!H190/HAVERM!I190 -> 72.56764 | AA54: =(Z54/AVERAGE($Z$63:$Z$74))*100 -> 119.15508 | AD54: 45748 | AF54: =HAVERM!L316 -> 3.511 | AJ54: =+AJ49+7 -> 43902 | AL54: =IF(HAVERD!H58="",AL53,AVERAGE(HAVERD!H58:Q58)) -> 32.441 | BI54: 45383 | BJ54: ='[27]CPI Forecast'!D345 -> 2.3330701 | BK54: =NA() -> #N/A | BL54: =NA() -> #N/A | BM54: 2
A55: 45413 | B55: ='[24]CPI Forecast'!D346 -> 1.9899778 | C55: =NA() -> #N/A | D55: =NA() -> #N/A | E55: =NA() -> #N/A | F55: 2 | H55: =+H54+7 -> 44200 | I55: =HAVERW!C60 -> 115.39 | J55: =HAVERW!D60 -> 119.97 | L55: =+L50+7 -> 43903 | M55: =HAVERD!BA59/HAVERD!BB59 -> 25.995486 | U55: 41760 | V55: =((AA43/AA31)-1)*100 -> 6.854416 | W55: =((HAVERM!J191/HAVERM!J179)-1)*100 -> -0.58309038 | X55: =((HAVERM!K188/HAVERM!K176)-1)*100 -> 1.3752456 | Y55: 0 | Z55: =HAVERM!H191/HAVERM!I191 -> 71.954405 | AA55: =(Z55/AVERAGE($Z$63:$Z$74))*100 -> 118.14816 | AD55: 45778 | AF55: =HAVERM!L317 -> 3.666 | AJ55: =+AJ50+7 -> 43903 | AL55: =IF(HAVERD!H59="",AL54,AVERAGE(HAVERD!H59:Q59)) -> 33.012 | BI55: 45413 | BJ55: ='[27]CPI Forecast'!D346 -> 1.9899778 | BK55: =NA() -> #N/A | BL55: =NA() -> #N/A | BM55: 2
A56: 45444 | B56: ='[24]CPI Forecast'!D347 -> 1.9753105 | C56: =NA() -> #N/A | D56: =NA() -> #N/A | E56: =NA() -> #N/A | F56: 2 | H56: =+H55+7 -> 44207 | I56: =HAVERW!C61 -> 116.14 | J56: =HAVERW!D61 -> 120.61 | L56: =+L51+7 -> 43906 | M56: =HAVERD!BA60/HAVERD!BB60 -> 22.790584 | U56: 41791 | V56: =((AA44/AA32)-1)*100 -> 5.0314603 | W56: =((HAVERM!J192/HAVERM!J180)-1)*100 -> 0 | X56: =((HAVERM!K189/HAVERM!K177)-1)*100 -> 1.1730205 | Y56: 0 | Z56: =HAVERM!H192/HAVERM!I192 -> 70.507512 | AA56: =(Z56/AVERAGE($Z$63:$Z$74))*100 -> 115.77238 | AD56: 45809 | AF56: =HAVERM!L318 -> 3.793 | AJ56: =+AJ51+7 -> 43906 | AL56: =IF(HAVERD!H60="",AL55,AVERAGE(HAVERD!H60:Q60)) -> 32.593 | BI56: 45444 | BJ56: ='[27]CPI Forecast'!D347 -> 1.9753105 | BK56: =NA() -> #N/A | BL56: =NA() -> #N/A | BM56: 2
A57: 45474 | B57: ='[24]CPI Forecast'!D348 -> 2.2344448 | C57: =NA() -> #N/A | D57: =NA() -> #N/A | E57: =NA() -> #N/A | F57: 2 | H57: =+H56+7 -> 44214 | I57: =HAVERW!C62 -> 116.93 | J57: =HAVERW!D62 -> 121.52 | L57: =+L52+7 -> 43907 | M57: =HAVERD!BA61/HAVERD!BB61 -> 23.277297 | U57: 41821 | V57: =((AA45/AA33)-1)*100 -> -0.62031871 | W57: =((HAVERM!J193/HAVERM!J181)-1)*100 -> -0.38986355 | X57: =((HAVERM!K190/HAVERM!K178)-1)*100 -> 0.58309038 | Y57: 0 | Z57: =HAVERM!H193/HAVERM!I193 -> 68.135216 | AA57: =(Z57/AVERAGE($Z$63:$Z$74))*100 -> 111.8771 | AD57: 45839 | AF57: =HAVERM!L319 -> 3.902 | AJ57: =+AJ52+7 -> 43907 | AL57: =IF(HAVERD!H61="",AL56,AVERAGE(HAVERD!H61:Q61)) -> 31.95 | BI57: 45474 | BJ57: ='[27]CPI Forecast'!D348 -> 2.2344448 | BK57: =NA() -> #N/A | BL57: =NA() -> #N/A | BM57: 2
A58: 45505 | B58: ='[24]CPI Forecast'!D349 -> 2.2162837 | C58: =NA() -> #N/A | D58: =NA() -> #N/A | E58: =NA() -> #N/A | F58: 2 | H58: =+H57+7 -> 44221 | I58: =HAVERW!C63 -> 118.1 | J58: =HAVERW!D63 -> 122.7 | L58: =+L53+7 -> 43908 | M58: =HAVERD!BA62/HAVERD!BB62 -> 19.374309 | U58: 41852 | V58: =((AA46/AA34)-1)*100 -> -4.3923712 | W58: =((HAVERM!J194/HAVERM!J182)-1)*100 -> -1.0669253 | X58: =((HAVERM!K191/HAVERM!K179)-1)*100 -> -0.19379845 | Y58: 0 | Z58: =HAVERM!H194/HAVERM!I194 -> 67.508528 | AA58: =(Z58/AVERAGE($Z$63:$Z$74))*100 -> 110.84809 | AD58: 45870 | AJ58: =+AJ53+7 -> 43908 | AL58: =IF(HAVERD!H62="",AL57,AVERAGE(HAVERD!H62:Q62)) -> 31.286 | BI58: 45505 | BJ58: ='[27]CPI Forecast'!D349 -> 2.2162837 | BK58: =NA() -> #N/A | BL58: =NA() -> #N/A | BM58: 2
A59: 45536 | B59: ='[24]CPI Forecast'!D350 -> 1.6803412 | C59: =NA() -> #N/A | D59: =NA() -> #N/A | E59: =NA() -> #N/A | F59: 2 | H59: =+H58+7 -> 44228 | I59: =HAVERW!C64 -> 119.14 | J59: =HAVERW!D64 -> 123.7 | L59: =+L54+7 -> 43909 | M59: =HAVERD!BA63/HAVERD!BB63 -> 20.569566 | U59: 41883 | V59: =((AA47/AA35)-1)*100 -> -5.4823636 | W59: =((HAVERM!J195/HAVERM!J183)-1)*100 -> -1.3565891 | X59: =((HAVERM!K192/HAVERM!K180)-1)*100 -> -1.1594203 | Y59: 0 | Z59: =HAVERM!H195/HAVERM!I195 -> 66.973321 | AA59: =(Z59/AVERAGE($Z$63:$Z$74))*100 -> 109.96929 | AD59: 45901 | AJ59: =+AJ54+7 -> 43909 | AL59: =IF(HAVERD!H63="",AL58,AVERAGE(HAVERD!H63:Q63)) -> 31.449 | BI59: 45536 | BJ59: ='[27]CPI Forecast'!D350 -> 1.6803412 | BK59: =NA() -> #N/A | BL59: =NA() -> #N/A | BM59: 2
A60: 45566 | B60: ='[24]CPI Forecast'!D351 -> 2.2809915 | C60: ='[29]CPI Forecast'!$F351 -> 2.1724579 | D60: =NA() -> #N/A | E60: 2.182 | F60: 2 | H60: =+H59+7 -> 44235 | I60: =HAVERW!C65 -> 119.67 | J60: =HAVERW!D65 -> 124.09 | L60: =+L55+7 -> 43910 | M60: =HAVERD!BA64/HAVERD!BB64 -> 21.761349 | U60: 41913 | V60: =((AA48/AA36)-1)*100 -> -4.3634123 | W60: =((HAVERM!J196/HAVERM!J184)-1)*100 -> -1.450677 | X60: =((HAVERM!K193/HAVERM!K181)-1)*100 -> -1.3500482 | Y60: 0 | Z60: =HAVERM!H196/HAVERM!I196 -> 68.023401 | AA60: =(Z60/AVERAGE($Z$63:$Z$74))*100 -> 111.6935 | AD60: 45931 | AJ60: =+AJ55+7 -> 43910 | AL60: =IF(HAVERD!H64="",AL59,AVERAGE(HAVERD!H64:Q64)) -> 31.031 | BI60: 45566 | BJ60: ='[27]CPI Forecast'!D351 -> 2.2809915 | BK60: =C60 -> 2.1724579 | BL60: =NA() -> #N/A | BM60: 2
A61: 45597 | B61: ='[24]CPI Forecast'!D352 -> 2.6221267 | C61: ='[29]CPI Forecast'!$F352 -> 2.5270521 | D61: =NA() -> #N/A | E61: 2.423 | F61: 2 | H61: =+H60+7 -> 44242 | I61: =HAVERW!C66 -> 120.53 | J61: =HAVERW!D66 -> 125.01 | L61: =+L56+7 -> 43913 | M61: =HAVERD!BA65/HAVERD!BB65 -> 20.666551 | U61: 41944 | V61: =((AA49/AA37)-1)*100 -> -4.820358 | W61: =((HAVERM!J197/HAVERM!J185)-1)*100 -> -1.6441006 | X61: =((HAVERM!K194/HAVERM!K182)-1)*100 -> -1.5458937 | Y61: 0 | Z61: =HAVERM!H197/HAVERM!I197 -> 68.504436 | AA61: =(Z61/AVERAGE($Z$63:$Z$74))*100 -> 112.48336 | AD61: 45962 | AJ61: =+AJ56+7 -> 43913 | AL61: =IF(HAVERD!H65="",AL60,AVERAGE(HAVERD!H65:Q65)) -> 30.941 | BI61: 45597 | BJ61: ='[27]CPI Forecast'!D352 -> 2.6221267 | BK61: =C61 -> 2.5270521 | BL61: =NA() -> #N/A | BM61: 2
A62: 45627 | B62: ='[24]CPI Forecast'!D353 -> 2.5029869 | C62: ='[29]CPI Forecast'!$F353 -> 2.5354946 | D62: =NA() -> #N/A | E62: 2.463 | F62: 2 | H62: =+H61+7 -> 44249 | I62: =HAVERW!C67 -> 121.27 | J62: =HAVERW!D67 -> 125.71 | L62: =+L57+7 -> 43914 | M62: =HAVERD!BA66/HAVERD!BB66 -> 20.812097 | U62: 41974 | V62: =((AA50/AA38)-1)*100 -> -5.103772 | W62: =((HAVERM!J198/HAVERM!J186)-1)*100 -> -1.734104 | X62: =((HAVERM!K195/HAVERM!K183)-1)*100 -> -1.9305019 | Y62: 0 | Z62: =HAVERM!H198/HAVERM!I198 -> 67.263427 | AA62: =(Z62/AVERAGE($Z$63:$Z$74))*100 -> 110.44564 | AD62: 45992 | AJ62: =+AJ57+7 -> 43914 | AL62: =IF(HAVERD!H66="",AL61,AVERAGE(HAVERD!H66:Q66)) -> 31.066 | BI62: 45627 | BJ62: ='[27]CPI Forecast'!D353 -> 2.5029869 | BK62: =C62 -> 2.5354946 | BL62: =NA() -> #N/A | BM62: 2
A63: 45658 | B63: ='[24]CPI Forecast'!D354 -> 2.9299359 | C63: ='[29]CPI Forecast'!$F354 -> 2.7277893 | D63: ='BoE MPR - Chart 2.16'!M55 -> 2.816 | E63: 2.498 | F63: 2 | H63: =+H62+7 -> 44256 | I63: =HAVERW!C68 -> 122.17 | J63: =HAVERW!D68 -> 126.62 | L63: =+L58+7 -> 43915 | M63: =HAVERD!BA67/HAVERD!BB67 -> 21.783862 | U63: 42005 | V63: =((AA51/AA39)-1)*100 -> -8.767702 | W63: =((HAVERM!J199/HAVERM!J187)-1)*100 -> -2.5024062 | X63: =((HAVERM!K196/HAVERM!K184)-1)*100 -> -2.6086957 | Y63: 0 | Z63: =HAVERM!H199/HAVERM!I199 -> 66.697484 | AA63: =(Z63/AVERAGE($Z$63:$Z$74))*100 -> 109.51636 | AJ63: =+AJ58+7 -> 43915 | AL63: =IF(HAVERD!H67="",AL62,AVERAGE(HAVERD!H67:Q67)) -> 31.334 | BI63: 45658 | BJ63: ='[27]CPI Forecast'!D354 -> 2.9829405 | BK63: =C63 -> 2.7277893 | BL63: =D63 -> 2.816 | BM63: 2
A64: 45689 | B64: ='[24]CPI Forecast'!D355 -> 2.7893521 | C64: ='[29]CPI Forecast'!$F355 -> 2.5098802 | D64: ='BoE MPR - Chart 2.16'!M56 -> 2.848 | E64: 2.443 | F64: 2 | H64: =+H63+7 -> 44263 | I64: =HAVERW!C69 -> 122.94 | J64: =HAVERW!D69 -> 127.4 | L64: =+L59+7 -> 43916 | M64: =HAVERD!BA68/HAVERD!BB68 -> 19.406675 | U64: 42036 | V64: =((AA52/AA40)-1)*100 -> -10.134585 | W64: =((HAVERM!J200/HAVERM!J188)-1)*100 -> -3.3492823 | X64: =((HAVERM!K197/HAVERM!K185)-1)*100 -> -2.992278 | Y64: 0 | Z64: =HAVERM!H200/HAVERM!I200 -> 64.366767 | AA64: =(Z64/AVERAGE($Z$63:$Z$74))*100 -> 105.68936 | AJ64: =+AJ59+7 -> 43916 | AL64: =IF(HAVERD!H68="",AL63,AVERAGE(HAVERD!H68:Q68)) -> 30.874 | BI64: 45689 | BJ64: ='[27]CPI Forecast'!D355 -> 2.8572398 | BK64: =C64 -> 2.5098802 | BL64: =D64 -> 2.848 | BM64: 2
A65: 45717 | B65: ='[24]CPI Forecast'!D356 -> 2.4927348 | C65: ='[29]CPI Forecast'!$F356 -> 2.1565432 | D65: ='BoE MPR - Chart 2.16'!M57 -> 2.709 | E65: 2.373 | F65: 2 | H65: =+H64+7 -> 44270 | I65: =HAVERW!C70 -> 123.9 | J65: =HAVERW!D70 -> 128.24 | L65: =+L60+7 -> 43917 | M65: =HAVERD!BA69/HAVERD!BB69 -> 18.116352 | U65: 42064 | V65: =((AA53/AA41)-1)*100 -> -9.8913192 | W65: =((HAVERM!J201/HAVERM!J189)-1)*100 -> -2.8873917 | X65: =((HAVERM!K198/HAVERM!K186)-1)*100 -> -2.5193798 | Y65: 0 | Z65: =HAVERM!H201/HAVERM!I201 -> 63.983419 | AA65: =(Z65/AVERAGE($Z$63:$Z$74))*100 -> 105.05991 | AJ65: =+AJ60+7 -> 43917 | AL65: =IF(HAVERD!H69="",AL64,AVERAGE(HAVERD!H69:Q69)) -> 29.686 | BI65: 45717 | BJ65: ='[27]CPI Forecast'!D356 -> 2.571471 | BK65: =C65 -> 2.1565432 | BL65: =D65 -> 2.709 | BM65: 2
A66: 45748 | B66: ='[24]CPI Forecast'!D357 -> 2.9477402 | C66: ='[29]CPI Forecast'!$F357 -> 2.3019737 | D66: ='BoE MPR - Chart 2.16'!M58 -> 3.554 | E66: =NA() -> #N/A | F66: 2 | H66: =+H65+7 -> 44277 | I66: =HAVERW!C71 -> 124.57 | J66: =HAVERW!D71 -> 129.02 | L66: =+L61+7 -> 43920 | M66: =HAVERD!BA70/HAVERD!BB70 -> 15.455863 | U66: 42095 | V66: =((AA54/AA42)-1)*100 -> -9.565014 | W66: =((HAVERM!J202/HAVERM!J190)-1)*100 -> -2.8046422 | X66: =((HAVERM!K199/HAVERM!K187)-1)*100 -> -2.3278371 | Y66: 0 | Z66: =HAVERM!H202/HAVERM!I202 -> 63.205719 | AA66: =(Z66/AVERAGE($Z$63:$Z$74))*100 -> 103.78293 | AJ66: =+AJ61+7 -> 43920 | AL66: =IF(HAVERD!H70="",AL65,AVERAGE(HAVERD!H70:Q70)) -> 28.51 | BI66: 45748 | BJ66: ='[27]CPI Forecast'!D357 -> 3.1595639 | BK66: =C66 -> 2.3019737 | BL66: =D66 -> 3.554 | BM66: 2
A67: 45778 | B67: ='[24]CPI Forecast'!D358 -> 2.9369169 | C67: ='[29]CPI Forecast'!$F358 -> 2.2437681 | D67: ='BoE MPR - Chart 2.16'!M59 -> 3.53 | E67: =NA() -> #N/A | F67: 2 | H67: =+H66+7 -> 44284 | I67: =HAVERW!C72 -> 125.13 | J67: =HAVERW!D72 -> 129.32 | L67: =+L62+7 -> 43921 | M67: =HAVERD!BA71/HAVERD!BB71 -> 11.97291 | U67: 42125 | V67: =((AA55/AA43)-1)*100 -> -9.9981111 | W67: =((HAVERM!J203/HAVERM!J191)-1)*100 -> -1.8572825 | X67: =((HAVERM!K200/HAVERM!K188)-1)*100 -> -2.4224806 | Y67: 0 | Z67: =HAVERM!H203/HAVERM!I203 -> 61.409179 | AA67: =(Z67/AVERAGE($Z$63:$Z$74))*100 -> 100.83304 | AJ67: =+AJ62+7 -> 43921 | AL67: =IF(HAVERD!H71="",AL66,AVERAGE(HAVERD!H71:Q71)) -> 29.71 | BI67: 45778 | BJ67: ='[27]CPI Forecast'!D358 -> 3.1485108 | BK67: =C67 -> 2.2437681 | BL67: =D67 -> 3.53 | BM67: 2
A68: 45809 | B68: ='[24]CPI Forecast'!D359 -> 3.0157487 | C68: ='[29]CPI Forecast'!$F359 -> 2.2458628 | D68: ='BoE MPR - Chart 2.16'!M60 -> 3.549 | E68: =HAVERQ!C28 -> 2.6 | F68: 2 | H68: =+H67+7 -> 44291 | I68: =HAVERW!C73 -> 125.24 | J68: =HAVERW!D73 -> 129.35 | L68: =+L63+7 -> 43922 | M68: =HAVERD!BA72/HAVERD!BB72 -> 12.049259 | U68: 42156 | V68: =((AA56/AA44)-1)*100 -> -9.7340552 | W68: =((HAVERM!J204/HAVERM!J192)-1)*100 -> -2.1484375 | X68: =((HAVERM!K201/HAVERM!K189)-1)*100 -> -2.4154589 | Y68: 0 | Z68: =HAVERM!H204/HAVERM!I204 -> 60.765673 | AA68: =(Z68/AVERAGE($Z$63:$Z$74))*100 -> 99.776411 | AJ68: =+AJ63+7 -> 43922 | AL68: =IF(HAVERD!H72="",AL67,AVERAGE(HAVERD!H72:Q72)) -> 29.592 | BI68: 45809 | BJ68: ='[27]CPI Forecast'!D359 -> 3.2267937 | BK68: =C68 -> 2.2458628 | BL68: =D68 -> 3.549 | BM68: 2
A69: 45839 | B69: ='[24]CPI Forecast'!D360 -> 3.3318502 | C69: ='[29]CPI Forecast'!$F360 -> 2.5231968 | D69: =NA() -> #N/A | E69: =NA() -> #N/A | F69: 2 | H69: =+H68+7 -> 44298 | I69: =HAVERW!C74 -> 125.4 | J69: =HAVERW!D74 -> 129.39 | L69: =+L64+7 -> 43923 | M69: =HAVERD!BA73/HAVERD!BB73 -> 16.352913 | U69: 42186 | V69: =((AA57/AA45)-1)*100 -> -12.39428 | W69: =((HAVERM!J205/HAVERM!J193)-1)*100 -> -2.6418787 | X69: =((HAVERM!K202/HAVERM!K190)-1)*100 -> -2.5120773 | Y69: 0 | Z69: =HAVERM!H205/HAVERM!I205 -> 60.282776 | AA69: =(Z69/AVERAGE($Z$63:$Z$74))*100 -> 98.983501 | AJ69: =+AJ64+7 -> 43923 | AL69: =IF(HAVERD!H73="",AL68,AVERAGE(HAVERD!H73:Q73)) -> 30.146 | BI69: 45839 | BJ69: ='[27]CPI Forecast'!D360 -> 3.3248185 | BK69: =C69 -> 2.5231968 | BL69: =BL68+(BL71-BL68)/3 -> 3.5993333 | BM69: 2
A70: 45870 | B70: ='[24]CPI Forecast'!D361 -> 3.4275244 | C70: ='[29]CPI Forecast'!$F361 -> 2.5867226 | D70: =NA() -> #N/A | E70: =NA() -> #N/A | F70: 2 | H70: =+H69+7 -> 44305 | I70: =HAVERW!C75 -> 125.48 | J70: =HAVERW!D75 -> 129.49 | L70: =+L65+7 -> 43924 | M70: =HAVERD!BA74/HAVERD!BB74 -> 19.848262 | U70: 42217 | V70: =((AA58/AA46)-1)*100 -> -9.9092299 | W70: =((HAVERM!J206/HAVERM!J194)-1)*100 -> -2.4509804 | X70: =((HAVERM!K203/HAVERM!K191)-1)*100 -> -2.038835 | Y70: 0 | Z70: =HAVERM!H206/HAVERM!I206 -> 57.434384 | AA70: =(Z70/AVERAGE($Z$63:$Z$74))*100 -> 94.306479 | AJ70: =+AJ65+7 -> 43924 | AL70: =IF(HAVERD!H74="",AL69,AVERAGE(HAVERD!H74:Q74)) -> 30.786 | BI70: 45870 | BJ70: ='[27]CPI Forecast'!D361 -> 3.4238931 | BK70: =C70 -> 2.5867226 | BL70: =BL68+(BL71-BL68)*2/3 -> 3.6496667 | BM70: 2
A71: 45901 | B71: ='[24]CPI Forecast'!D362 -> 3.6316394 | C71: ='[29]CPI Forecast'!$F362 -> 2.7292136 | D71: 3.7 | E71: =HAVERQ!C29 -> 2.8 | F71: 2 | H71: =+H70+7 -> 44312 | I71: =HAVERW!C76 -> 125.8 | J71: =HAVERW!D76 -> 129.77 | L71: =+L66+7 -> 43927 | M71: =HAVERD!BA75/HAVERD!BB75 -> 18.425133 | U71: 42248 | V71: =((AA59/AA47)-1)*100 -> -8.7172046 | W71: =((HAVERM!J207/HAVERM!J195)-1)*100 -> -2.259332 | X71: =((HAVERM!K204/HAVERM!K192)-1)*100 -> -1.6617791 | Y71: 0 | Z71: =HAVERM!H207/HAVERM!I207 -> 58.006003 | AA71: =(Z71/AVERAGE($Z$63:$Z$74))*100 -> 95.24507 | AJ71: =+AJ66+7 -> 43927 | AL71: =IF(HAVERD!H75="",AL70,AVERAGE(HAVERD!H75:Q75)) -> 32.04 | BI71: 45901 | BJ71: ='[27]CPI Forecast'!D362 -> 3.6342978 | BK71: =C71 -> 2.7292136 | BL71: =HAVERQ!B29 -> 3.7 | BM71: 2
A72: 45931 | B72: ='[24]CPI Forecast'!D363 -> 3.2787192 | C72: ='[29]CPI Forecast'!$F363 -> 2.4715662 | D72: =NA() -> #N/A | E72: =NA() -> #N/A | F72: 2 | H72: =+H71+7 -> 44319 | I72: =HAVERW!C77 -> 126.09 | J72: =HAVERW!D77 -> 130 | L72: =+L67+7 -> 43928 | M72: =HAVERD!BA76/HAVERD!BB76 -> 17.961638 | U72: 42278 | V72: =((AA60/AA48)-1)*100 -> -7.7701257 | W72: =((HAVERM!J208/HAVERM!J196)-1)*100 -> -2.747792 | X72: =((HAVERM!K205/HAVERM!K193)-1)*100 -> -2.1505376 | Y72: 0 | Z72: =HAVERM!H208/HAVERM!I208 -> 58.869548 | AA72: =(Z72/AVERAGE($Z$63:$Z$74))*100 -> 96.663 | AJ72: =+AJ67+7 -> 43928 | AL72: =IF(HAVERD!H76="",AL71,AVERAGE(HAVERD!H76:Q76)) -> 32.215 | BI72: 45931 | BJ72: ='[27]CPI Forecast'!D363 -> 3.0912884 | BK72: =C72 -> 2.4715662 | BL72: =BL71+(BL74-BL71)/3 -> 3.6333333 | BM72: 2
A73: 45962 | B73: ='[24]CPI Forecast'!D364 -> 3.3443887 | C73: ='[29]CPI Forecast'!$F364 -> 2.4910902 | D73: =NA() -> #N/A | E73: =NA() -> #N/A | F73: 2 | H73: =+H72+7 -> 44326 | I73: =HAVERW!C78 -> 126.53 | J73: =HAVERW!D78 -> 130.43 | L73: =+L68+7 -> 43929 | M73: =HAVERD!BA77/HAVERD!BB77 -> 20.373213 | U73: 42309 | V73: =((AA61/AA49)-1)*100 -> -6.981835 | W73: =((HAVERM!J209/HAVERM!J197)-1)*100 -> -2.4582104 | X73: =((HAVERM!K206/HAVERM!K194)-1)*100 -> -2.2571148 | Y73: 0 | Z73: =HAVERM!H209/HAVERM!I209 -> 57.735352 | AA73: =(Z73/AVERAGE($Z$63:$Z$74))*100 -> 94.800666 | AJ73: =+AJ68+7 -> 43929 | AL73: =IF(HAVERD!H77="",AL72,AVERAGE(HAVERD!H77:Q77)) -> 31.61 | BI73: 45962 | BJ73: ='[27]CPI Forecast'!D364 -> 3.1509898 | BK73: =C73 -> 2.4910902 | BL73: =BL71+(BL74-BL71)*2/3 -> 3.5666667 | BM73: 2
A74: 45992 | B74: ='[24]CPI Forecast'!D365 -> 3.4876175 | C74: ='[29]CPI Forecast'!$F365 -> 2.529148 | D74: 3.5 | E74: =HAVERQ!C30 -> 2.7 | F74: 2 | H74: =+H73+7 -> 44333 | I74: =HAVERW!C79 -> 127.19 | J74: =HAVERW!D79 -> 131.03 | L74: =+L69+7 -> 43930 | M74: =HAVERD!BA78/HAVERD!BB78 -> 16.222935 | U74: 42339 | V74: =((AA62/AA50)-1)*100 -> -6.8156837 | W74: =((HAVERM!J210/HAVERM!J198)-1)*100 -> -2.9411765 | X74: =((HAVERM!K207/HAVERM!K195)-1)*100 -> -2.3622047 | Y74: 0 | Z74: =HAVERM!H210/HAVERM!I210 -> 58.065808 | AA74: =(Z74/AVERAGE($Z$63:$Z$74))*100 -> 95.343269 | AJ74: =+AJ69+7 -> 43930 | AL74: =IF(HAVERD!H78="",AL73,AVERAGE(HAVERD!H78:Q78)) -> 31.883 | BI74: 45992 | BJ74: ='[27]CPI Forecast'!D365 -> 3.2925634 | BK74: =C74 -> 2.529148 | BL74: =HAVERQ!B30 -> 3.5 | BM74: 2
A75: 46023 | B75: ='[24]CPI Forecast'!D366 -> 3.1644425 | C75: ='[29]CPI Forecast'!$F366 -> 2.4333862 | D75: =NA() -> #N/A | E75: =NA() -> #N/A | F75: 2 | H75: =+H74+7 -> 44340 | I75: =HAVERW!C80 -> 127.89 | J75: =HAVERW!D80 -> 131.52 | L75: =+L70+7 -> 43931 | M75: =HAVERD!BA79/HAVERD!BB79 -> #N/A | U75: 42370 | V75: =((AA63/AA51)-1)*100 -> -5.4640653 | W75: =((HAVERM!J211/HAVERM!J199)-1)*100 -> -2.6653504 | X75: =((HAVERM!K208/HAVERM!K196)-1)*100 -> -1.7857143 | Y75: 0 | Z75: =HAVERM!H211/HAVERM!I211 -> 59.04444 | AA75: =(Z75/AVERAGE($Z$63:$Z$74))*100 -> 96.95017 | AJ75: =+AJ70+7 -> 43931 | AL75: =IF(HAVERD!H79="",AL74,AVERAGE(HAVERD!H79:Q79)) -> #N/A | BI75: 46023 | BJ75: ='[27]CPI Forecast'!D366 -> 3.1821506 | BK75: =C75 -> 2.4333862 | BL75: =BL74+(BL77-BL74)/3 -> 3.3333333 | BM75: 2
A76: 46054 | B76: ='[24]CPI Forecast'!D367 -> 3.0952067 | C76: ='[29]CPI Forecast'!$F367 -> 2.4335496 | D76: =NA() -> #N/A | E76: =NA() -> #N/A | F76: 2 | H76: =+H75+7 -> 44347 | I76: =HAVERW!C81 -> 128.15 | J76: =HAVERW!D81 -> 131.82 | L76: =+L71+7 -> 43934 | M76: =HAVERD!BA80/HAVERD!BB80 -> #N/A | U76: 42401 | V76: =((AA64/AA52)-1)*100 -> -10.087334 | W76: =((HAVERM!J212/HAVERM!J200)-1)*100 -> -2.1782178 | X76: =((HAVERM!K209/HAVERM!K197)-1)*100 -> -1.6915423 | Y76: 0 | Z76: =HAVERM!H212/HAVERM!I212 -> 60.226637 | AA76: =(Z76/AVERAGE($Z$63:$Z$74))*100 -> 98.891321 | AJ76: =+AJ71+7 -> 43934 | AL76: =IF(HAVERD!H80="",AL75,AVERAGE(HAVERD!H80:Q80)) -> 31.883 | BI76: 46054 | BJ76: ='[27]CPI Forecast'!D367 -> 3.1074819 | BK76: =C76 -> 2.4335496 | BL76: =BL74+(BL77-BL74)*2/3 -> 3.1666667 | BM76: 2
A77: 46082 | B77: ='[24]CPI Forecast'!D368 -> 3.0577654 | C77: ='[29]CPI Forecast'!$F368 -> 2.4283663 | D77: 3 | E77: =HAVERQ!C31 -> 2.6 | F77: 2 | H77: =+H76+7 -> 44354 | I77: =HAVERW!C82 -> 128.69 | J77: =HAVERW!D82 -> 132.38 | L77: =+L72+7 -> 43935 | M77: =HAVERD!BA81/HAVERD!BB81 -> 17.262188 | U77: 42430 | V77: =((AA65/AA53)-1)*100 -> -12.89661 | W77: =((HAVERM!J213/HAVERM!J201)-1)*100 -> -2.7750248 | X77: =((HAVERM!K210/HAVERM!K198)-1)*100 -> -1.9880716 | Y77: 0 | Z77: =HAVERM!H213/HAVERM!I213 -> 61.333333 | AA77: =(Z77/AVERAGE($Z$63:$Z$74))*100 -> 100.7085 | AJ77: =+AJ72+7 -> 43935 | AL77: =IF(HAVERD!H81="",AL76,AVERAGE(HAVERD!H81:Q81)) -> 30.763 | BI77: 46082 | BJ77: ='[27]CPI Forecast'!D368 -> 3.0666556 | BK77: =C77 -> 2.4283663 | BL77: =HAVERQ!B31 -> 3 | BM77: 2
A78: 46113 | B78: ='[24]CPI Forecast'!D369 -> 2.6569961 | C78: ='[29]CPI Forecast'!$F369 -> 2.3493849 | D78: =NA() -> #N/A | E78: =NA() -> #N/A | F78: 2 | H78: =+H77+7 -> 44361 | I78: =HAVERW!C83 -> 129.47 | J78: =HAVERW!D83 -> 133.17 | L78: =+L73+7 -> 43936 | M78: =HAVERD!BA82/HAVERD!BB82 -> 15.842535 | U78: 42461 | V78: =((AA66/AA54)-1)*100 -> -12.900958 | W78: =((HAVERM!J214/HAVERM!J202)-1)*100 -> -2.4875622 | X78: =((HAVERM!K211/HAVERM!K199)-1)*100 -> -1.9860973 | Y78: 0 | Z78: =HAVERM!H214/HAVERM!I214 -> 62.25545 | AA78: =(Z78/AVERAGE($Z$63:$Z$74))*100 -> 102.2226 | AJ78: =+AJ73+7 -> 43936 | AL78: =IF(HAVERD!H82="",AL77,AVERAGE(HAVERD!H82:Q82)) -> 30.023 | BI78: 46113 | BJ78: ='[27]CPI Forecast'!D369 -> 2.5570557 | BK78: =C78 -> 2.3493849 | BL78: =BL77+(BL80-BL77)/3 -> 2.8666667 | BM78: 2
A79: 46143 | B79: ='[24]CPI Forecast'!D370 -> 2.5961733 | C79: ='[29]CPI Forecast'!$F370 -> 2.3548918 | D79: =NA() -> #N/A | E79: =NA() -> #N/A | F79: 2 | H79: =+H78+7 -> 44368 | I79: =HAVERW!C84 -> 130.1 | J79: =HAVERW!D84 -> 133.69 | L79: =+L74+7 -> 43937 | M79: =HAVERD!BA83/HAVERD!BB83 -> 15.010843 | U79: 42491 | V79: =((AA67/AA55)-1)*100 -> -14.655428 | W79: =((HAVERM!J215/HAVERM!J203)-1)*100 -> -2.7888446 | X79: =((HAVERM!K212/HAVERM!K200)-1)*100 -> -1.8867925 | Y79: 0 | Z79: =HAVERM!H215/HAVERM!I215 -> 62.40529 | AA79: =(Z79/AVERAGE($Z$63:$Z$74))*100 -> 102.46864 | AJ79: =+AJ74+7 -> 43937 | AL79: =IF(HAVERD!H83="",AL78,AVERAGE(HAVERD!H83:Q83)) -> 31.091 | BI79: 46143 | BJ79: ='[27]CPI Forecast'!D370 -> 2.5027802 | BK79: =C79 -> 2.3548918 | BL79: =BL77+(BL80-BL77)*2/3 -> 2.7333333 | BM79: 2
A80: 46174 | B80: ='[24]CPI Forecast'!D371 -> 2.544607 | C80: ='[29]CPI Forecast'!$F371 -> 2.3739627 | D80: 2.6 | E80: =HAVERQ!C32 -> 2.4 | F80: 2 | H80: =+H79+7 -> 44375 | I80: =HAVERW!C85 -> 130.73 | J80: =HAVERW!D85 -> 134.27 | L80: =+L75+7 -> 43938 | M80: =HAVERD!BA84/HAVERD!BB84 -> 15.794946 | U80: 42522 | V80: =((AA68/AA56)-1)*100 -> -13.816739 | W80: =((HAVERM!J216/HAVERM!J204)-1)*100 -> -2.994012 | X80: =((HAVERM!K213/HAVERM!K201)-1)*100 -> -1.8811881 | Y80: 0 | Z80: =HAVERM!H216/HAVERM!I216 -> 66.014498 | AA80: =(Z80/AVERAGE($Z$63:$Z$74))*100 -> 108.39491 | AJ80: =+AJ75+7 -> 43938 | AL80: =IF(HAVERD!H84="",AL79,AVERAGE(HAVERD!H84:Q84)) -> 31.938 | BI80: 46174 | BJ80: ='[27]CPI Forecast'!D371 -> 2.4591563 | BK80: =C80 -> 2.3739627 | BL80: =HAVERQ!B32 -> 2.6 | BM80: 2
A81: 46204 | B81: ='[24]CPI Forecast'!D372 -> 2.3487161 | C81: ='[29]CPI Forecast'!$F372 -> 2.3063834 | D81: =NA() -> #N/A | E81: =NA() -> #N/A | F81: 2 | H81: =+H80+7 -> 44382 | I81: =HAVERW!C86 -> 131.7 | J81: =HAVERW!D86 -> 134.13 | L81: =+L76+7 -> 43941 | M81: =HAVERD!BA85/HAVERD!BB85 -> 13.918063 | U81: 42552 | V81: =((AA69/AA57)-1)*100 -> -11.524789 | W81: =((HAVERM!J217/HAVERM!J205)-1)*100 -> -2.6130653 | X81: =((HAVERM!K214/HAVERM!K202)-1)*100 -> -1.9821606 | Y81: 0 | Z81: =HAVERM!H217/HAVERM!I217 -> 70.77087 | AA81: =(Z81/AVERAGE($Z$63:$Z$74))*100 -> 116.20481 | AJ81: =+AJ76+7 -> 43941 | AL81: =IF(HAVERD!H85="",AL80,AVERAGE(HAVERD!H85:Q85)) -> 31.748 | BI81: 46204 | BJ81: ='[27]CPI Forecast'!D372 -> 2.490762 | BK81: =C81 -> 2.3063834 | BL81: =BL80+(BL83-BL80)/3 -> 2.6 | BM81: 2
A82: 46235 | B82: ='[24]CPI Forecast'!D373 -> 2.3112168 | C82: ='[29]CPI Forecast'!$F373 -> 2.3137371 | D82: =NA() -> #N/A | E82: =NA() -> #N/A | F82: 2 | H82: =+H81+7 -> 44389 | I82: =HAVERW!C87 -> 132.47 | J82: =HAVERW!D87 -> 135.29 | L82: =+L77+7 -> 43942 | M82: =HAVERD!BA86/HAVERD!BB86 -> 7.430946 | U82: 42583 | V82: =((AA70/AA58)-1)*100 -> -14.922773 | W82: =((HAVERM!J218/HAVERM!J206)-1)*100 -> -2.2110553 | X82: =((HAVERM!K215/HAVERM!K203)-1)*100 -> -2.5768087 | Y82: 0 | Z82: =HAVERM!H218/HAVERM!I218 -> 72.748092 | AA82: =(Z82/AVERAGE($Z$63:$Z$74))*100 -> 119.45138 | AJ82: =+AJ77+7 -> 43942 | AL82: =IF(HAVERD!H86="",AL81,AVERAGE(HAVERD!H86:Q86)) -> 31.25 | BI82: 46235 | BJ82: ='[27]CPI Forecast'!D373 -> 2.4624707 | BK82: =C82 -> 2.3137371 | BL82: =BL80+(BL83-BL80)*2/3 -> 2.6 | BM82: 2
A83: 46266 | B83: ='[24]CPI Forecast'!D374 -> 2.2308696 | C83: ='[29]CPI Forecast'!$F374 -> 2.2596957 | D83: 2.6 | E83: =HAVERQ!C33 -> 2.3 | F83: 2 | H83: =+H82+7 -> 44396 | I83: =HAVERW!C88 -> 133.2 | J83: =HAVERW!D88 -> 135.95 | L83: =+L78+7 -> 43943 | M83: =HAVERD!BA87/HAVERD!BB87 -> 11.168789 | U83: 42614 | V83: =((AA71/AA59)-1)*100 -> -13.389389 | W83: =((HAVERM!J219/HAVERM!J207)-1)*100 -> -2.2110553 | X83: =((HAVERM!K216/HAVERM!K204)-1)*100 -> -2.4850895 | Y83: 0 | Z83: =HAVERM!H219/HAVERM!I219 -> 73.124334 | AA83: =(Z83/AVERAGE($Z$63:$Z$74))*100 -> 120.06917 | AJ83: =+AJ78+7 -> 43943 | AL83: =IF(HAVERD!H87="",AL82,AVERAGE(HAVERD!H87:Q87)) -> 30.684 | BI83: 46266 | BJ83: ='[27]CPI Forecast'!D374 -> 2.3816083 | BK83: =C83 -> 2.2596957 | BL83: =HAVERQ!B33 -> 2.6 | BM83: 2
A84: 46296 | B84: ='[24]CPI Forecast'!D375 -> 2.0481071 | C84: ='[29]CPI Forecast'!$F375 -> 2.1786506 | D84: =NA() -> #N/A | E84: =NA() -> #N/A | F84: 2 | H84: =+H83+7 -> 44403 | I84: =HAVERW!C89 -> 133.48 | J84: =HAVERW!D89 -> 136.2 | L84: =+L79+7 -> 43944 | M84: =HAVERD!BA88/HAVERD!BB88 -> 12.158889 | U84: 42644 | V84: =((AA72/AA60)-1)*100 -> -13.456917 | W84: =((HAVERM!J220/HAVERM!J208)-1)*100 -> -2.320888 | X84: =((HAVERM!K217/HAVERM!K205)-1)*100 -> -1.998002 | Y84: 0 | Z84: =HAVERM!H220/HAVERM!I220 -> 77.784086 | AA84: =(Z84/AVERAGE($Z$63:$Z$74))*100 -> 127.72042 | AJ84: =+AJ79+7 -> 43944 | AL84: =IF(HAVERD!H88="",AL83,AVERAGE(HAVERD!H88:Q88)) -> 30.258 | BI84: 46296 | BJ84: ='[27]CPI Forecast'!D375 -> 2.3972491 | BK84: =C84 -> 2.1786506 | BL84: =BL83+(BL86-BL83)/3 -> 2.5333333 | BM84: 2
A85: 46327 | B85: ='[24]CPI Forecast'!D376 -> 2.0124744 | C85: ='[29]CPI Forecast'!$F376 -> 2.164415 | D85: =NA() -> #N/A | E85: =NA() -> #N/A | F85: 2 | H85: =+H84+7 -> 44410 | I85: =HAVERW!C90 -> 134.21 | J85: =HAVERW!D90 -> 136.89 | L85: =+L80+7 -> 43945 | M85: =HAVERD!BA89/HAVERD!BB89 -> 12.862701 | U85: 42675 | V85: =((AA73/AA61)-1)*100 -> -15.720272 | W85: =((HAVERM!J221/HAVERM!J209)-1)*100 -> -2.016129 | X85: =((HAVERM!K218/HAVERM!K206)-1)*100 -> -1.3052209 | Y85: 0 | Z85: =HAVERM!H221/HAVERM!I221 -> 77.226289 | AA85: =(Z85/AVERAGE($Z$63:$Z$74))*100 -> 126.80452 | AJ85: =+AJ80+7 -> 43945 | AL85: =IF(HAVERD!H89="",AL84,AVERAGE(HAVERD!H89:Q89)) -> 29.883 | BI85: 46327 | BJ85: ='[27]CPI Forecast'!D376 -> 2.3674136 | BK85: =C85 -> 2.164415 | BL85: =BL83+(BL86-BL83)*2/3 -> 2.4666667 | BM85: 2
A86: 46357 | B86: ='[24]CPI Forecast'!D377 -> 1.9993263 | C86: ='[29]CPI Forecast'!$F377 -> 2.1760162 | D86: 2.4 | E86: =HAVERQ!C34 -> 2.2 | F86: 2 | H86: =+H85+7 -> 44417 | I86: =HAVERW!C91 -> 134.7 | J86: =HAVERW!D91 -> 137.31 | L86: =+L81+7 -> 43948 | M86: =HAVERD!BA90/HAVERD!BB90 -> 12.224998 | U86: 42705 | V86: =((AA74/AA62)-1)*100 -> -13.674027 | W86: =((HAVERM!J222/HAVERM!J210)-1)*100 -> -1.1111111 | X86: =((HAVERM!K219/HAVERM!K207)-1)*100 -> -0.40322581 | Y86: 0 | Z86: =HAVERM!H222/HAVERM!I222 -> 76.313261 | AA86: =(Z86/AVERAGE($Z$63:$Z$74))*100 -> 125.30534 | AJ86: =+AJ81+7 -> 43948 | AL86: =IF(HAVERD!H90="",AL85,AVERAGE(HAVERD!H90:Q90)) -> 29.628 | BI86: 46357 | BJ86: ='[27]CPI Forecast'!D377 -> 2.3588975 | BK86: =C86 -> 2.1760162 | BL86: =HAVERQ!B34 -> 2.4 | BM86: 2
H87: =+H86+7 -> 44424 | I87: =HAVERW!C92 -> 134.7 | J87: =HAVERW!D92 -> 136.77 | L87: =+L82+7 -> 43949 | M87: =HAVERD!BA91/HAVERD!BB91 -> 12.544226 | U87: 42736 | V87: =((AA75/AA63)-1)*100 -> -11.474262 | W87: =((HAVERM!J223/HAVERM!J211)-1)*100 -> -0.50709939 | X87: =((HAVERM!K220/HAVERM!K208)-1)*100 -> 0.3030303 | Y87: 0 | Z87: =HAVERM!H223/HAVERM!I223 -> 79.183872 | AA87: =(Z87/AVERAGE($Z$63:$Z$74))*100 -> 130.01884 | AJ87: =+AJ82+7 -> 43949 | AL87: =IF(HAVERD!H91="",AL86,AVERAGE(HAVERD!H91:Q91)) -> 29.568
H88: =+H87+7 -> 44431 | I88: =HAVERW!C93 -> 134.68 | J88: =HAVERW!D93 -> 137.15 | L88: =+L83+7 -> 43950 | M88: =HAVERD!BA92/HAVERD!BB92 -> 14.361531 | U88: 42767 | V88: =((AA76/AA64)-1)*100 -> -6.4320923 | W88: =((HAVERM!J224/HAVERM!J212)-1)*100 -> 0.10121457 | X88: =((HAVERM!K221/HAVERM!K209)-1)*100 -> 0.70850202 | Y88: 0 | Z88: =HAVERM!H224/HAVERM!I224 -> 78.542834 | AA88: =(Z88/AVERAGE($Z$63:$Z$74))*100 -> 128.96627 | AJ88: =+AJ83+7 -> 43950 | AL88: =IF(HAVERD!H92="",AL87,AVERAGE(HAVERD!H92:Q92)) -> 29.421
H89: =+H88+7 -> 44438 | I89: =HAVERW!C94 -> 134.66 | J89: =HAVERW!D94 -> 137.11 | L89: =+L84+7 -> 43951 | M89: =HAVERD!BA93/HAVERD!BB93 -> 14.358202 | U89: 42795 | V89: =((AA77/AA65)-1)*100 -> -4.1418321 | W89: =((HAVERM!J225/HAVERM!J213)-1)*100 -> 1.2232416 | X89: =((HAVERM!K222/HAVERM!K210)-1)*100 -> 1.1156187 | Y89: 0 | Z89: =HAVERM!H225/HAVERM!I225 -> 77.907353 | AA89: =(Z89/AVERAGE($Z$63:$Z$74))*100 -> 127.92282 | AJ89: =+AJ84+7 -> 43951 | AL89: =IF(HAVERD!H93="",AL88,AVERAGE(HAVERD!H93:Q93)) -> 30.305
H90: =+H89+7 -> 44445 | I90: =HAVERW!C95 -> 134.76 | J90: =HAVERW!D95 -> 137.19 | L90: =+L85+7 -> 43952 | M90: =HAVERD!BA94/HAVERD!BB94 -> 14.73659 | U90: 42826 | V90: =((AA78/AA66)-1)*100 -> -1.5034546 | W90: =((HAVERM!J226/HAVERM!J214)-1)*100 -> 1.5306122 | X90: =((HAVERM!K223/HAVERM!K211)-1)*100 -> 1.2158055 | Y90: 0 | Z90: =HAVERM!H226/HAVERM!I226 -> 75.086943 | AA90: =(Z90/AVERAGE($Z$63:$Z$74))*100 -> 123.29174 | AJ90: =+AJ85+7 -> 43952 | AL90: =IF(HAVERD!H94="",AL89,AVERAGE(HAVERD!H94:Q94)) -> 30.063
H91: =+H90+7 -> 44452 | I91: =HAVERW!C96 -> 134.75 | J91: =HAVERW!D96 -> 137.19 | L91: =+L86+7 -> 43955 | M91: =HAVERD!BA95/HAVERD!BB95 -> 16.423798 | U91: 42856 | V91: =((AA79/AA67)-1)*100 -> 1.622088 | W91: =((HAVERM!J227/HAVERM!J215)-1)*100 -> 2.0491803 | X91: =((HAVERM!K224/HAVERM!K212)-1)*100 -> 1.5182186 | Y91: 0 | Z91: =HAVERM!H227/HAVERM!I227 -> 75.233898 | AA91: =(Z91/AVERAGE($Z$63:$Z$74))*100 -> 123.53304 | AJ91: =+AJ86+7 -> 43955 | AL91: =IF(HAVERD!H95="",AL90,AVERAGE(HAVERD!H95:Q95)) -> 30.143
A92: 2024 | B92: ='[30]CPI Forecasts'!D656 -> 2.1317788 | C92: ='[31]CPI Forecasts'!D656 -> 3.11194 | H92: =+H91+7 -> 44459 | I92: =HAVERW!C97 -> 134.86 | J92: =HAVERW!D97 -> 137.35 | L92: =+L87+7 -> 43956 | M92: =HAVERD!BA96/HAVERD!BB96 -> 20.443231 | U92: 42887 | V92: =((AA80/AA68)-1)*100 -> 8.6378121 | W92: =((HAVERM!J228/HAVERM!J216)-1)*100 -> 2.2633745 | X92: =((HAVERM!K225/HAVERM!K213)-1)*100 -> 2.1190716 | Y92: 0 | Z92: =HAVERM!H228/HAVERM!I228 -> 76.328729 | AA92: =(Z92/AVERAGE($Z$63:$Z$74))*100 -> 125.33074 | AJ92: =+AJ87+7 -> 43956 | AL92: =IF(HAVERD!H96="",AL91,AVERAGE(HAVERD!H96:Q96)) -> 30.146
A93: 2025 | B93: ='[30]CPI Forecasts'!D657 -> 1.5974637 | C93: ='[31]CPI Forecasts'!D657 -> 1.3861131 | H93: =+H92+7 -> 44466 | I93: =HAVERW!C98 -> 135.19 | J93: =HAVERW!D98 -> 137.95 | L93: =+L88+7 -> 43957 | M93: =HAVERD!BA97/HAVERD!BB97 -> 19.57612 | U93: 42917 | V93: =((AA81/AA69)-1)*100 -> 17.398159 | W93: =((HAVERM!J229/HAVERM!J217)-1)*100 -> 2.5799794 | X93: =((HAVERM!K226/HAVERM!K214)-1)*100 -> 2.5278059 | Y93: 0 | Z93: =HAVERM!H229/HAVERM!I229 -> 76.958596 | AA93: =(Z93/AVERAGE($Z$63:$Z$74))*100 -> 126.36497 | AJ93: =+AJ88+7 -> 43957 | AL93: =IF(HAVERD!H97="",AL92,AVERAGE(HAVERD!H97:Q97)) -> 30.542
H94: =+H93+7 -> 44473 | I94: =HAVERW!C99 -> 136.1 | J94: =HAVERW!D99 -> 139.2 | L94: =+L89+7 -> 43958 | M94: =HAVERD!BA98/HAVERD!BB98 -> 19.720029 | U94: 42948 | V94: =((AA82/AA70)-1)*100 -> 26.662962 | W94: =((HAVERM!J230/HAVERM!J218)-1)*100 -> 2.1582734 | X94: =((HAVERM!K227/HAVERM!K215)-1)*100 -> 4.069176 | Y94: 0 | Z94: =HAVERM!H230/HAVERM!I230 -> 76.572752 | AA94: =(Z94/AVERAGE($Z$63:$Z$74))*100 -> 125.73142 | AJ94: =+AJ89+7 -> 43958 | AL94: =IF(HAVERD!H98="",AL93,AVERAGE(HAVERD!H98:Q98)) -> 31.113
A95: Q2 2024 | B95: =AVERAGE(B54:B56) -> 2.0994528 | E95: =E55 -> #N/A | H95: =+H94+7 -> 44480 | I95: =HAVERW!C100 -> 137.17 | J95: =HAVERW!D100 -> 140.66 | L95: =+L90+7 -> 43959 | M95: =HAVERD!BA99/HAVERD!BB99 -> #N/A | U95: 42979 | V95: =((AA83/AA71)-1)*100 -> 26.063391 | W95: =((HAVERM!J231/HAVERM!J219)-1)*100 -> 2.9804728 | X95: =((HAVERM!K228/HAVERM!K216)-1)*100 -> 4.3832824 | Y95: 0 | Z95: =HAVERM!H231/HAVERM!I231 -> 74.827379 | AA95: =(Z95/AVERAGE($Z$63:$Z$74))*100 -> 122.86554 | AJ95: =+AJ90+7 -> 43959 | AL95: =IF(HAVERD!H99="",AL94,AVERAGE(HAVERD!H99:Q99)) -> 31.113
A96: Q3 2024 | B96: =AVERAGE(B57:B59) -> 2.0436899 | E96: =E58 -> #N/A | H96: =+H95+7 -> 44487 | I96: =HAVERW!C101 -> 139.46 | J96: =HAVERW!D101 -> 143.19 | L96: =+L91+7 -> 43962 | M96: =HAVERD!BA100/HAVERD!BB100 -> 20.658683 | U96: 43009 | V96: =((AA84/AA72)-1)*100 -> 32.129579 | W96: =((HAVERM!J232/HAVERM!J220)-1)*100 -> 3.9256198 | X96: =((HAVERM!K229/HAVERM!K217)-1)*100 -> 4.7910296 | Y96: 0 | Z96: =HAVERM!H232/HAVERM!I232 -> 74.8655 | AA96: =(Z96/AVERAGE($Z$63:$Z$74))*100 -> 122.92814 | AJ96: =+AJ91+7 -> 43962 | AL96: =IF(HAVERD!H100="",AL95,AVERAGE(HAVERD!H100:Q100)) -> 31.265
A97: Q4 2024 | B97: =AVERAGE(B60:B62) -> 2.4687017 | E97: =E61 -> 2.423 | H97: =+H96+7 -> 44494 | I97: =HAVERW!C102 -> 141.81 | J97: =HAVERW!D102 -> 145.9 | L97: =+L92+7 -> 43963 | M97: =HAVERD!BA101/HAVERD!BB101 -> 21.63017 | U97: 43040 | V97: =((AA85/AA73)-1)*100 -> 33.759103 | W97: =((HAVERM!J233/HAVERM!J221)-1)*100 -> 4.0123457 | X97: =((HAVERM!K230/HAVERM!K218)-1)*100 -> 5.08647 | Y97: 0 | Z97: =HAVERM!H233/HAVERM!I233 -> 74.740903 | AA97: =(Z97/AVERAGE($Z$63:$Z$74))*100 -> 122.72355 | AJ97: =+AJ92+7 -> 43963 | AL97: =IF(HAVERD!H101="",AL96,AVERAGE(HAVERD!H101:Q101)) -> 30.685
H98: =+H97+7 -> 44501 | I98: =HAVERW!C103 -> 143.7 | J98: =HAVERW!D103 -> 147.48 | L98: =+L93+7 -> 43964 | M98: =HAVERD!BA102/HAVERD!BB102 -> 22.81204 | U98: 43070 | V98: =((AA86/AA74)-1)*100 -> 31.42547 | W98: =((HAVERM!J234/HAVERM!J222)-1)*100 -> 3.9836568 | X98: =((HAVERM!K231/HAVERM!K219)-1)*100 -> 5.1619433 | Y98: 0 | Z98: =HAVERM!H234/HAVERM!I234 -> 71.929563 | AA98: =(Z98/AVERAGE($Z$63:$Z$74))*100 -> 118.10737 | AJ98: =+AJ93+7 -> 43964 | AL98: =IF(HAVERD!H102="",AL97,AVERAGE(HAVERD!H102:Q102)) -> 30.477
H99: =+H98+7 -> 44508 | I99: =HAVERW!C104 -> 144.9 | J99: =HAVERW!D104 -> 148.84 | L99: =+L94+7 -> 43965 | M99: =HAVERD!BA103/HAVERD!BB103 -> 24.485614 | U99: 43101 | V99: =((AA87/AA75)-1)*100 -> 34.108939 | W99: =((HAVERM!J235/HAVERM!J223)-1)*100 -> 3.6697248 | X99: =((HAVERM!K232/HAVERM!K220)-1)*100 -> 4.9345418 | Y99: 0 | Z99: =HAVERM!H235/HAVERM!I235 -> 69.910353 | AA99: =(Z99/AVERAGE($Z$63:$Z$74))*100 -> 114.79185 | AJ99: =+AJ94+7 -> 43965 | AL99: =IF(HAVERD!H103="",AL98,AVERAGE(HAVERD!H103:Q103)) -> 31.038
H100: =+H99+7 -> 44515 | I100: =HAVERW!C105 -> 145.87 | J100: =HAVERW!D105 -> 149.76 | L100: =+L95+7 -> 43966 | M100: =HAVERD!BA104/HAVERD!BB104 -> 25.523668 | U100: 43132 | V100: =((AA88/AA76)-1)*100 -> 30.412121 | W100: =((HAVERM!J236/HAVERM!J224)-1)*100 -> 3.033367 | X100: =((HAVERM!K233/HAVERM!K221)-1)*100 -> 4.9246231 | Y100: 0 | Z100: =HAVERM!H236/HAVERM!I236 -> 70.052289 | AA100: =(Z100/AVERAGE($Z$63:$Z$74))*100 -> 115.02491 | AJ100: =+AJ95+7 -> 43966 | AL100: =IF(HAVERD!H104="",AL99,AVERAGE(HAVERD!H104:Q104)) -> 31.438
...

Sheet Data >>>

Sheet HAVERW
B1: 20200101W !W | C1: P112GPU@INTWKLY | D1: P112GPD@INTWKLY
B2: .DESC | C2: United Kingdom: Pump Price: Ultra Low Sulfur Unleaded Petrol (Pence/Liter) | D2: United Kingdom: Pump Price: Ultra Low Sulfur Diesel (Pence/Liter)
B3: .T1 | C3: 09-Jun-2003W | D3: 09-Jun-2003W
B4: .TN | C4: 03-Mar-2025W | D4: 03-Mar-2025W
B5: .LSOURCE | C5: UK Department of Energy & Climate Change | D5: UK Department of Energy & Climate Change
B6: .DTLM | C6: Mar-04-2025 10:01 | D6: Mar-04-2025 10:01
A7: 43829 | B7: 20191230W | C7: 124.96 | D7: 130.54
A8: =+A7+7 -> 43836 | B8: 20200106W | C8: 126.09 | D8: 131.56
A9: =+A8+7 -> 43843 | B9: 20200113W | C9: 127.17 | D9: 132.69
A10: =+A9+7 -> 43850 | B10: 20200120W | C10: 127.18 | D10: 132.74
A11: =+A10+7 -> 43857 | B11: 20200127W | C11: 127.33 | D11: 132.88
A12: =+A11+7 -> 43864 | B12: 20200203W | C12: 125.85 | D12: 131.48
A13: =+A12+7 -> 43871 | B13: 20200210W | C13: 124.73 | D13: 129.7
A14: =+A13+7 -> 43878 | B14: 20200217W | C14: 123.8 | D14: 128.2
A15: =+A14+7 -> 43885 | B15: 20200224W | C15: 123.45 | D15: 127.67
A16: =+A15+7 -> 43892 | B16: 20200302W | C16: 122.43 | D16: 126.62
A17: =+A16+7 -> 43899 | B17: 20200309W | C17: 122.24 | D17: 126.25
A18: =+A17+7 -> 43906 | B18: 20200316W | C18: 120.33 | D18: 124.36
A19: =+A18+7 -> 43913 | B19: 20200323W | C19: 119.64 | D19: 123.41
... A277: =+A276+7 -> 45719 | B277: 20250303W | C277: 139.61 | D277: 146.88

Sheet HAVERD
B1: 20200101 !D | D1: IFNG01C@CMDTY | E1: IFNG02C@CMDTY | F1: IFNG03C@CMDTY | G1: IFNG04C@CMDTY | H1: IFNG05C@CMDTY | I1: IFNG06C@CMDTY | J1: IFNG07C@CMDTY | K1: IFNG08C@CMDTY | L1: IFNG09C@CMDTY | M1: IFNG10C@CMDTY | N1: IFNG11C@CMDTY | O1: IFNG12C@CMDTY | P1: IFNG13C@CMDTY | Q1: IFNG14C@CMDTY | R1: IFNG15C@CMDTY | S1: IFNG16C@CMDTY | T1: IFNG17C@CMDTY | U1: IFNG18C@CMDTY | V1: IFNG19C@CMDTY | W1: IFNG20C@CMDTY | X1: IFNG21C@CMDTY | Y1: IFNG22C@CMDTY | Z1: IFNG23C@CMDTY | AA1: IFNG24C@CMDTY | AB1: IFNG25C@CMDTY | AC1: IFNG26C@CMDTY | AD1: IFNG27C@CMDTY | AE1: IFNG28C@CMDTY | AF1: IFNG29C@CMDTY | AG1: IFNG30C@CMDTY | AH1: IFNG31C@CMDTY | AI1: IFNG32C@CMDTY | AJ1: IFNG33C@CMDTY | AK1: IFNG34C@CMDTY | AL1: IFNG35C@CMDTY | AM1: IFNG36C@CMDTY | AN1: IFNG37C@CMDTY | AO1: IFNG38C@CMDTY | AP1: IFNG39C@CMDTY | AQ1: IFNG40C@CMDTY | AR1: IFNG41C@CMDTY | AS1: IFNG42C@CMDTY | AT1: IFNG43C@CMDTY | AU1: IFNG44C@CMDTY | AV1: IFNG45C@CMDTY | AW1: IFNG46C@CMDTY | AX1: IFNG47C@CMDTY | AY1: IFNG48C@CMDTY | BA1: PEBRT@DAILY | BB1: X112USB@INTDAILY
B2: .DESC | D2: ICE UK Natural Gas Futures: 1st Position: Settlement Price (Sterling/Therm) | E2: ICE UK Natural Gas Futures: 2nd Position: Settlement Price (Sterling/Therm) | F2: ICE UK Natural Gas Futures: 3rd Position: Settlement Price (Sterling/Therm) | G2: ICE UK Natural Gas Futures: 4th Position: Settlement Price (Sterling/Therm) | H2: ICE UK Natural Gas Futures: 5th Position: Settlement Price (Sterling/Therm) | I2: ICE UK Natural Gas Futures: 6th Position: Settlement Price (Sterling/Therm) | J2: ICE UK Natural Gas Futures: 7th Position: Settlement Price (Sterling/Therm) | K2: ICE UK Natural Gas Futures: 8th Position: Settlement Price (Sterling/Therm) | L2: ICE UK Natural Gas Futures: 9th Position: Settlement Price (Sterling/Therm) | M2: ICE UK Natural Gas Futures: 10th Position: Settlement Price (Sterling/Therm) | N2: ICE UK Natural Gas Futures: 11th Position: Settlement Price (Sterling/Therm) | O2: ICE UK Natural Gas Futures: 12th Position: Settlement Price (Sterling/Therm) | P2: ICE UK Natural Gas Futures: 13th Position: Settlement Price (Sterling/Therm) | Q2: ICE UK Natural Gas Futures: 14th Position: Settlement Price (Sterling/Therm) | R2: ICE UK Natural Gas Futures: 15th Position: Settlement Price (Sterling/Therm) | S2: ICE UK Natural Gas Futures: 16th Position: Settlement Price (Sterling/Therm) | T2: ICE UK Natural Gas Futures: 17th Position: Settlement Price (Sterling/Therm) | U2: ICE UK Natural Gas Futures: 18th Position: Settlement Price (Sterling/Therm) | V2: ICE UK Natural Gas Future: 19th Position: Settlement Price (Sterling/Therm) | W2: ICE UK Natural Gas Future: 20th Position: Settlement Price (Sterling/Therm) | X2: ICE UK Natural Gas Future: 21st Position: Settlement Price (Sterling/Therm) | Y2: ICE UK Natural Gas Future: 22nd Position: Settlement Price (Sterling/Therm) | Z2: ICE UK Natural Gas Future: 23rd Position: Settlement Price (Sterling/Therm) | AA2: ICE UK Natural Gas Future: 24th Position: Settlement Price (Sterling/Therm) | AB2: ICE UK Natural Gas Future: 25th Position: Settlement Price (Sterling/Therm) | AC2: ICE UK Natural Gas Future: 26th Position: Settlement Price (Sterling/Therm) | AD2: ICE UK Natural Gas Future: 27th Position: Settlement Price (Sterling/Therm) | AE2: ICE UK Natural Gas Future: 28th Position: Settlement Price (Sterling/Therm) | AF2: ICE UK Natural Gas Future: 29th Position: Settlement Price (Sterling/Therm) | AG2: ICE UK Natural Gas Future: 30th Position: Settlement Price (Sterling/Therm) | AH2: ICE UK Natural Gas Future: 31st Position: Settlement Price (Sterling/Therm) | AI2: ICE UK Natural Gas Future: 32nd Position: Settlement Price (Sterling/Therm) | AJ2: ICE UK Natural Gas Future: 33rd Position: Settlement Price (Sterling/Therm) | AK2: ICE UK Natural Gas Future: 34th Position: Settlement Price (Sterling/Therm) | AL2: ICE UK Natural Gas Future: 35th Position: Settlement Price (Sterling/Therm) | AM2: ICE UK Natural Gas Future: 36th Position: Settlement Price (Sterling/Therm) | AN2: ICE UK Natural Gas Future: 37th Position: Settlement Price (Sterling/Therm) | AO2: ICE UK Natural Gas Future: 38th Position: Settlement Price (Sterling/Therm) | AP2: ICE UK Natural Gas Future: 39th Position: Settlement Price (Sterling/Therm) | AQ2: ICE UK Natural Gas Future: 40th Position: Settlement Price (Sterling/Therm) | AR2: ICE UK Natural Gas Future: 41st Position: Settlement Price (Sterling/Therm) | AS2: ICE UK Natural Gas Future: 42nd Position: Settlement Price (Sterling/Therm) | AT2: ICE UK Natural Gas Future: 43rd Position: Settlement Price (Sterling/Therm) | AU2: ICE UK Natural Gas Future: 44th Position: Settlement Price (Sterling/Therm) | AV2: ICE UK Natural Gas Future: 45th Position: Settlement Price (Sterling/Therm) | AW2: ICE UK Natural Gas Future: 46th Position: Settlement Price (Sterling/Therm) | AX2: ICE UK Natural Gas Future: 47th Position: Settlement Price (Sterling/Therm) | AY2: ICE UK Natural Gas Future: 48th Position: Settlement Price (Sterling/Therm) | BA2: Europe Brent Spot Price FOB (US$ per Barrel) | BB2: UK: Spot Exchange Rate: US Dollar (US$/GBP)
B3: .T1 | D3: 31-Jan-1997 | E3: 31-Jan-1997 | F3: 31-Jan-1997 | G3: 31-Jan-1997 | H3: 31-Jan-1997 | I3: 31-Jan-1997 | J3: 31-Jan-1997 | K3: 31-Jan-1997 | L3: 31-Jan-1997 | M3: 31-Jan-1997 | N3: 31-Jan-1997 | O3: 29-Jun-2004 | P3: 28-Feb-2007 | Q3: 11-Apr-2008 | R3: 11-Apr-2008 | S3: 11-Apr-2008 | T3: 11-Apr-2008 | U3: 30-May-2008 | V3: 16-Aug-2010 | W3: 16-Aug-2010 | X3: 16-Aug-2010 | Y3: 16-Aug-2010 | Z3: 16-Aug-2010 | AA3: 16-Aug-2010 | AB3: 16-Aug-2010 | AC3: 16-Aug-2010 | AD3: 16-Aug-2010 | AE3: 16-Aug-2010 | AF3: 16-Aug-2010 | AG3: 16-Aug-2010 | AH3: 16-Aug-2010 | AI3: 16-Aug-2010 | AJ3: 16-Aug-2010 | AK3: 16-Aug-2010 | AL3: 16-Aug-2010 | AM3: 16-Aug-2010 | AN3: 16-Aug-2010 | AO3: 16-Aug-2010 | AP3: 16-Aug-2010 | AQ3: 16-Aug-2010 | AR3: 16-Aug-2010 | AS3: 16-Aug-2010 | AT3: 16-Aug-2010 | AU3: 16-Aug-2010 | AV3: 16-Aug-2010 | AW3: 16-Aug-2010 | AX3: 16-Aug-2010 | AY3: 16-Aug-2010 | BA3: 21-May-1986 | BB3: 02-Jan-1975
B4: .TN | D4: 06-Mar-2025 | E4: 06-Mar-2025 | F4: 06-Mar-2025 | G4: 06-Mar-2025 | H4: 06-Mar-2025 | I4: 06-Mar-2025 | J4: 06-Mar-2025 | K4: 06-Mar-2025 | L4: 06-Mar-2025 | M4: 06-Mar-2025 | N4: 06-Mar-2025 | O4: 06-Mar-2025 | P4: 06-Mar-2025 | Q4: 06-Mar-2025 | R4: 06-Mar-2025 | S4: 06-Mar-2025 | T4: 06-Mar-2025 | U4: 06-Mar-2025 | V4: 06-Mar-2025 | W4: 06-Mar-2025 | X4: 06-Mar-2025 | Y4: 06-Mar-2025 | Z4: 06-Mar-2025 | AA4: 06-Mar-2025 | AB4: 06-Mar-2025 | AC4: 06-Mar-2025 | AD4: 06-Mar-2025 | AE4: 06-Mar-2025 | AF4: 06-Mar-2025 | AG4: 06-Mar-2025 | AH4: 06-Mar-2025 | AI4: 06-Mar-2025 | AJ4: 06-Mar-2025 | AK4: 06-Mar-2025 | AL4: 06-Mar-2025 | AM4: 06-Mar-2025 | AN4: 06-Mar-2025 | AO4: 06-Mar-2025 | AP4: 06-Mar-2025 | AQ4: 06-Mar-2025 | AR4: 06-Mar-2025 | AS4: 06-Mar-2025 | AT4: 06-Mar-2025 | AU4: 06-Mar-2025 | AV4: 06-Mar-2025 | AW4: 06-Mar-2025 | AX4: 06-Mar-2025 | AY4: 06-Mar-2025 | BA4: 05-Mar-2025 | BB4: 06-Mar-2025
B5: .LSOURCE | D5: IntercontinentalExchange | E5: IntercontinentalExchange | F5: IntercontinentalExchange | G5: IntercontinentalExchange | H5: IntercontinentalExchange | I5: IntercontinentalExchange | J5: IntercontinentalExchange | K5: IntercontinentalExchange | L5: IntercontinentalExchange | M5: IntercontinentalExchange | N5: IntercontinentalExchange | O5: IntercontinentalExchange | P5: IntercontinentalExchange | Q5: IntercontinentalExchange | R5: IntercontinentalExchange | S5: IntercontinentalExchange | T5: IntercontinentalExchange | U5: IntercontinentalExchange | V5: IntercontinentalExchange | W5: IntercontinentalExchange | X5: IntercontinentalExchange | Y5: IntercontinentalExchange | Z5: IntercontinentalExchange | AA5: IntercontinentalExchange | AB5: IntercontinentalExchange | AC5: IntercontinentalExchange | AD5: IntercontinentalExchange | AE5: IntercontinentalExchange | AF5: IntercontinentalExchange | AG5: IntercontinentalExchange | AH5: IntercontinentalExchange | AI5: IntercontinentalExchange | AJ5: IntercontinentalExchange | AK5: IntercontinentalExchange | AL5: IntercontinentalExchange | AM5: IntercontinentalExchange | AN5: IntercontinentalExchange | AO5: IntercontinentalExchange | AP5: IntercontinentalExchange | AQ5: IntercontinentalExchange | AR5: IntercontinentalExchange | AS5: IntercontinentalExchange | AT5: IntercontinentalExchange | AU5: IntercontinentalExchange | AV5: IntercontinentalExchange | AW5: IntercontinentalExchange | AX5: IntercontinentalExchange | AY5: IntercontinentalExchange | BA5: Energy Information Administration | BB5: Bank of England
B6: .DTLM | D6: Mar-07-2025 03:19 | E6: Mar-07-2025 03:19 | F6: Mar-07-2025 03:19 | G6: Mar-07-2025 03:19 | H6: Mar-07-2025 03:19 | I6: Mar-07-2025 03:19 | J6: Mar-07-2025 03:19 | K6: Mar-07-2025 03:19 | L6: Mar-07-2025 03:19 | M6: Mar-07-2025 03:19 | N6: Mar-07-2025 03:19 | O6: Mar-07-2025 03:19 | P6: Mar-07-2025 03:19 | Q6: Mar-07-2025 03:19 | R6: Mar-07-2025 03:19 | S6: Mar-07-2025 03:19 | T6: Mar-07-2025 03:19 | U6: Mar-07-2025 03:19 | V6: Mar-07-2025 03:19 | W6: Mar-07-2025 03:19 | X6: Mar-07-2025 03:19 | Y6: Mar-07-2025 03:19 | Z6: Mar-07-2025 03:19 | AA6: Mar-07-2025 03:19 | AB6: Mar-07-2025 03:19 | AC6: Mar-07-2025 03:19 | AD6: Mar-07-2025 03:19 | AE6: Mar-07-2025 03:19 | AF6: Mar-07-2025 03:19 | AG6: Mar-07-2025 03:19 | AH6: Mar-07-2025 03:19 | AI6: Mar-07-2025 03:19 | AJ6: Mar-07-2025 03:19 | AK6: Mar-07-2025 03:19 | AL6: Mar-07-2025 03:19 | AM6: Mar-07-2025 03:19 | AN6: Mar-07-2025 03:19 | AO6: Mar-07-2025 03:19 | AP6: Mar-07-2025 03:19 | AQ6: Mar-07-2025 03:19 | AR6: Mar-07-2025 03:19 | AS6: Mar-07-2025 03:19 | AT6: Mar-07-2025 03:19 | AU6: Mar-07-2025 03:19 | AV6: Mar-07-2025 03:19 | AW6: Mar-07-2025 03:19 | AX6: Mar-07-2025 03:19 | AY6: Mar-07-2025 03:19 | BA6: Mar-06-2025 13:02 | BB6: Mar-07-2025 09:31
A7: 43831 | B7: 20200101 | C7: 43831 | D7: #N/A | E7: #N/A | F7: #N/A | G7: #N/A | H7: #N/A | I7: #N/A | J7: #N/A | K7: #N/A | L7: #N/A | M7: #N/A | N7: #N/A | O7: #N/A | P7: #N/A | Q7: #N/A | R7: #N/A | S7: #N/A | T7: #N/A | U7: #N/A | V7: #N/A | W7: #N/A | X7: #N/A | Y7: #N/A | Z7: #N/A | AA7: #N/A | AB7: #N/A | AC7: #N/A | AD7: #N/A | AE7: #N/A | AF7: #N/A | AG7: #N/A | AH7: #N/A | AI7: #N/A | AJ7: #N/A | AK7: #N/A | AL7: #N/A | AM7: #N/A | AN7: #N/A | AO7: #N/A | AP7: #N/A | AQ7: #N/A | AR7: #N/A | AS7: #N/A | AT7: #N/A | AU7: #N/A | AV7: #N/A | AW7: #N/A | AX7: #N/A | AY7: #N/A | BA7: #N/A | BB7: #N/A
A8: 43832 | B8: 20200102 | C8: 43832 | D8: 31.03 | E8: 30.63 | F8: 29.5 | G8: 28.72 | H8: 27.58 | I8: 28.3 | J8: 29.31 | K8: 30.22 | L8: 33.15 | M8: 40.85 | N8: 45.48 | O8: 46.39 | P8: 47 | Q8: 44.18 | R8: 40.47 | S8: 37.83 | T8: 37 | U8: 36.06 | V8: 36.51 | W8: 38.13 | X8: 42.19 | Y8: 45.31 | Z8: 47.77 | AA8: 51.39 | AB8: 50.66 | AC8: 46.76 | AD8: 40.78 | AE8: 39 | AF8: 38.6 | AG8: 39.19 | AH8: 40.2 | AI8: 41.96 | AJ8: 46.51 | AK8: 48.99 | AL8: 50.33 | AM8: 50.87 | AN8: 49.48 | AO8: 46.4 | AP8: 40.95 | AQ8: 39.43 | AR8: 38.9 | AS8: 39.14 | AT8: 40.21 | AU8: 43.18 | AV8: 47.78 | AW8: 50.08 | AX8: 50.61 | AY8: 50.66 | BA8: 67.05 | BB8: 1.3189
A9: 43833 | B9: 20200103 | C9: 43833 | D9: 33.07 | E9: 32.74 | F9: 31.77 | G9: 31.17 | H9: 30.27 | I9: 31.01 | J9: 31.86 | K9: 33.16 | L9: 35.76 | M9: 43.96 | N9: 47.05 | O9: 48.61 | P9: 49.23 | Q9: 46.41 | R9: 42.61 | S9: 39.83 | T9: 38.96 | U9: 38.02 | V9: 38.47 | W9: 40.09 | X9: 44.13 | Y9: 47.21 | Z9: 49.64 | AA9: 53.26 | AB9: 52.53 | AC9: 48.5 | AD9: 42.45 | AE9: 40.6 | AF9: 40.13 | AG9: 40.72 | AH9: 41.73 | AI9: 43.49 | AJ9: 47.99 | AK9: 50.47 | AL9: 51.81 | AM9: 52.35 | AN9: 50.96 | AO9: 47.88 | AP9: 42.48 | AQ9: 41.01 | AR9: 40.48 | AS9: 40.72 | AT9: 41.79 | AU9: 44.76 | AV9: 49.36 | AW9: 51.66 | AX9: 52.19 | AY9: 52.24 | BA9: 69.08 | BB9: 1.3072
A10: 43836 | B10: 20200106 | C10: 43836 | D10: 31.18 | E10: 31.16 | F10: 30.65 | G10: 29.98 | H10: 29.05 | I10: 29.68 | J10: 30.54 | K10: 31.95 | L10: 34.69 | M10: 42.96 | N10: 46.05 | O10: 47.75 | P10: 48.41 | Q10: 45.59 | R10: 41.56 | S10: 38.68 | T10: 37.77 | U10: 36.83 | V10: 37.28 | W10: 38.9 | X10: 43.02 | Y10: 46.18 | Z10: 48.64 | AA10: 52.29 | AB10: 51.59 | AC10: 47.59 | AD10: 41.54 | AE10: 39.69 | AF10: 39.22 | AG10: 39.81 | AH10: 40.82 | AI10: 42.58 | AJ10: 47.08 | AK10: 49.56 | AL10: 50.9 | AM10: 51.44 | AN10: 50.05 | AO10: 46.97 | AP10: 41.57 | AQ10: 40.1 | AR10: 39.57 | AS10: 39.81 | AT10: 40.88 | AU10: 43.85 | AV10: 48.53 | AW10: 50.91 | AX10: 51.47 | AY10: 51.55 | BA10: 70.25 | BB10: 1.3159
A11: 43837 | B11: 20200107 | C11: 43837 | D11: 30.24 | E11: 30.09 | F11: 29.52 | G11: 29.11 | H11: 28.3 | I11: 28.83 | J11: 29.67 | K11: 31.08 | L11: 33.68 | M11: 42.08 | N11: 45.03 | O11: 47 | P11: 47.67 | Q11: 44.8 | R11: 40.68 | S11: 37.8 | T11: 36.96 | U11: 36.3 | V11: 36.83 | W11: 38.45 | X11: 42.51 | Y11: 45.67 | Z11: 48.07 | AA11: 51.63 | AB11: 50.93 | AC11: 47.02 | AD11: 41.17 | AE11: 39.35 | AF11: 38.9 | AG11: 39.5 | AH11: 40.51 | AI11: 42.27 | AJ11: 46.92 | AK11: 49.44 | AL11: 50.78 | AM11: 51.32 | AN11: 49.93 | AO11: 46.85 | AP11: 41.33 | AQ11: 39.86 | AR11: 39.33 | AS11: 39.57 | AT11: 40.64 | AU11: 43.43 | AV11: 48.27 | AW11: 50.65 | AX11: 51.21 | AY11: 51.29 | BA11: 68.74 | BB11: 1.3122
A12: =+A7+7 -> 43838 | B12: 20200108 | C12: 43838 | D12: 30.46 | E12: 30.28 | F12: 29.59 | G12: 29.09 | H12: 28.4 | I12: 28.97 | J12: 29.77 | K12: 31.13 | L12: 33.73 | M12: 42.13 | N12: 45.33 | O12: 47.24 | P12: 47.89 | Q12: 45.04 | R12: 40.8 | S12: 37.91 | T12: 37.12 | U12: 36.7 | V12: 37.29 | W12: 38.91 | X12: 42.94 | Y12: 46.1 | Z12: 48.5 | AA12: 52.06 | AB12: 51.36 | AC12: 47.45 | AD12: 41.6 | AE12: 39.78 | AF12: 39.33 | AG12: 39.93 | AH12: 40.94 | AI12: 42.7 | AJ12: 47.32 | AK12: 49.81 | AL12: 51.12 | AM12: 51.66 | AN12: 50.27 | AO12: 47.19 | AP12: 41.72 | AQ12: 40.25 | AR12: 39.72 | AS12: 39.96 | AT12: 41.03 | AU12: 43.82 | AV12: 48.52 | AW12: 50.78 | AX12: 51.26 | AY12: 51.34 | BA12: 67.31 | BB12: 1.3099
A13: =+A8+7 -> 43839 | B13: 20200109 | C13: 43839 | D13: 31.03 | E13: 30.54 | F13: 30.01 | G13: 29.51 | H13: 28.81 | I13: 29.32 | J13: 29.99 | K13: 31.55 | L13: 34.15 | M13: 42.28 | N13: 45.57 | O13: 47.55 | P13: 48.02 | Q13: 45.31 | R13: 41.16 | S13: 38.42 | T13: 37.68 | U13: 37.26 | V13: 37.85 | W13: 39.38 | X13: 43.43 | Y13: 46.59 | Z13: 48.99 | AA13: 52.55 | AB13: 51.8 | AC13: 47.85 | AD13: 41.95 | AE13: 40.08 | AF13: 39.63 | AG13: 40.23 | AH13: 41.24 | AI13: 43 | AJ13: 47.62 | AK13: 50.11 | AL13: 51.42 | AM13: 51.96 | AN13: 50.57 | AO13: 47.49 | AP13: 42.02 | AQ13: 40.55 | AR13: 40.02 | AS13: 40.26 | AT13: 41.29 | AU13: 44.04 | AV13: 48.7 | AW13: 50.91 | AX13: 51.39 | AY13: 51.47 | BA13: 66.58 | BB13: 1.3049
A14: =+A9+7 -> 43840 | B14: 20200110 | C14: 43840 | D14: 30.45 | E14: 30.02 | F14: 29.48 | G14: 28.87 | H14: 28.21 | I14: 28.77 | J14: 29.47 | K14: 30.97 | L14: 33.64 | M14: 42.01 | N14: 44.79 | O14: 46.89 | P14: 47.42 | Q14: 44.71 | R14: 40.64 | S14: 37.93 | T14: 37.19 | U14: 36.77 | V14: 37.36 | W14: 38.89 | X14: 43.06 | Y14: 46.22 | Z14: 48.62 | AA14: 52.09 | AB14: 51.34 | AC14: 47.39 | AD14: 41.38 | AE14: 39.41 | AF14: 38.96 | AG14: 39.56 | AH14: 40.57 | AI14: 42.33 | AJ14: 47.02 | AK14: 49.58 | AL14: 50.93 | AM14: 51.47 | AN14: 50.09 | AO14: 47.02 | AP14: 41.54 | AQ14: 40.08 | AR14: 39.58 | AS14: 39.82 | AT14: 40.85 | AU14: 43.6 | AV14: 48.26 | AW14: 50.47 | AX14: 50.95 | AY14: 51.03 | BA14: 66.77 | BB14: 1.3062
A15: =+A10+7 -> 43843 | B15: 20200113 | C15: 43843 | D15: 31.34 | E15: 30.65 | F15: 30.05 | G15: 29.45 | H15: 28.76 | I15: 29.33 | J15: 30.06 | K15: 31.57 | L15: 34.12 | M15: 42.29 | N15: 45.53 | O15: 47.29 | P15: 47.82 | Q15: 45.11 | R15: 41.06 | S15: 38.37 | T15: 37.63 | U15: 37.21 | V15: 37.8 | W15: 39.29 | X15: 43.39 | Y15: 46.51 | Z15: 48.88 | AA15: 52.35 | AB15: 51.6 | AC15: 47.65 | AD15: 41.67 | AE15: 39.7 | AF15: 39.25 | AG15: 39.85 | AH15: 40.86 | AI15: 42.62 | AJ15: 47.29 | AK15: 49.83 | AL15: 51.18 | AM15: 51.72 | AN15: 50.34 | AO15: 47.27 | AP15: 41.83 | AQ15: 40.4 | AR15: 39.9 | AS15: 40.14 | AT15: 41.17 | AU15: 43.92 | AV15: 48.58 | AW15: 50.79 | AX15: 51.27 | AY15: 51.35 | BA15: 64.14 | BB15: 1.2979
A16: =+A11+7 -> 43844 | B16: 20200114 | C16: 43844 | D16: 29.18 | E16: 28.59 | F16: 28.03 | G16: 27.63 | H16: 27.22 | I16: 27.76 | J16: 28.44 | K16: 29.95 | L16: 32.48 | M16: 40.78 | N16: 43.8 | O16: 45.68 | P16: 46.48 | Q16: 43.87 | R16: 39.78 | S16: 37.09 | T16: 36.35 | U16: 35.93 | V16: 36.5 | W16: 37.94 | X16: 42.04 | Y16: 45.11 | Z16: 47.48 | AA16: 51 | AB16: 50.29 | AC16: 46.48 | AD16: 40.62 | AE16: 38.72 | AF16: 38.27 | AG16: 38.87 | AH16: 39.86 | AI16: 41.57 | AJ16: 46.19 | AK16: 48.73 | AL16: 50.08 | AM16: 50.62 | AN16: 49.24 | AO16: 46.22 | AP16: 40.83 | AQ16: 39.4 | AR16: 38.9 | AS16: 39.14 | AT16: 40.17 | AU16: 42.92 | AV16: 47.58 | AW16: 49.79 | AX16: 50.27 | AY16: 50.35 | BA16: 64.45 | BB16: 1.301
A17: =+A12+7 -> 43845 | B17: 20200115 | C17: 43845 | D17: 29.05 | E17: 28.51 | F17: 27.87 | G17: 27.5 | H17: 27 | I17: 27.5 | J17: 28.19 | K17: 29.66 | L17: 32.19 | M17: 40.27 | N17: 43.47 | O17: 45.41 | P17: 46.21 | Q17: 43.6 | R17: 39.55 | S17: 36.88 | T17: 36.14 | U17: 35.72 | V17: 36.29 | W17: 37.73 | X17: 41.76 | Y17: 44.83 | Z17: 47.2 | AA17: 50.72 | AB17: 50.01 | AC17: 46.2 | AD17: 40.44 | AE17: 38.54 | AF17: 38.09 | AG17: 38.69 | AH17: 39.68 | AI17: 41.35 | AJ17: 45.9 | AK17: 48.44 | AL17: 49.79 | AM17: 50.33 | AN17: 48.95 | AO17: 45.93 | AP17: 40.54 | AQ17: 39.11 | AR17: 38.61 | AS17: 38.85 | AT17: 39.88 | AU17: 42.63 | AV17: 47.29 | AW17: 49.5 | AX17: 49.98 | AY17: 50.06 | BA17: 63.29 | BB17: 1.3023
A18: =+A13+7 -> 43846 | B18: 20200116 | C18: 43846 | D18: 28.83 | E18: 28.15 | F18: 27.47 | G18: 27.09 | H18: 26.72 | I18: 27.22 | J18: 27.74 | K18: 29.19 | L18: 31.54 | M18: 39.31 | N18: 42.37 | O18: 44.41 | P18: 45.25 | Q18: 42.64 | R18: 38.91 | S18: 36.37 | T18: 35.63 | U18: 35.21 | V18: 35.78 | W18: 37.22 | X18: 41.1 | Y18: 44.17 | Z18: 46.54 | AA18: 50.11 | AB18: 49.4 | AC18: 45.59 | AD18: 39.95 | AE18: 38.1 | AF18: 37.65 | AG18: 38.25 | AH18: 39.21 | AI18: 40.24 | AJ18: 43.33 | AK18: 45.85 | AL18: 48.4 | AM18: 50.14 | AN18: 49.96 | AO18: 46.88 | AP18: 40.99 | AQ18: 39.06 | AR18: 38.11 | AS18: 38.15 | AT18: 39.18 | AU18: 41.93 | AV18: 46.59 | AW18: 48.8 | AX18: 49.28 | AY18: 49.36 | BA18: 64.63 | BB18: 1.3067
A19: =+A14+7 -> 43847 | B19: 20200117 | C19: 43847 | D19: 28.31 | E19: 27.48 | F19: 26.76 | G19: 26.55 | H19: 26.12 | I19: 26.67 | J19: 27.22 | K19: 28.48 | L19: 30.59 | M19: 38.42 | N19: 41.59 | O19: 43.36 | P19: 44.13 | Q19: 41.48 | R19: 37.95 | S19: 35.59 | T19: 34.98 | U19: 34.66 | V19: 35.27 | W19: 36.71 | X19: 40.44 | Y19: 43.51 | Z19: 45.88 | AA19: 49.45 | AB19: 48.74 | AC19: 44.93 | AD19: 39.49 | AE19: 37.79 | AF19: 37.44 | AG19: 38.04 | AH19: 38.91 | AI19: 39.78 | AJ19: 42.67 | AK19: 45.16 | AL19: 47.71 | AM19: 49.5 | AN19: 49.47 | AO19: 46.49 | AP19: 40.7 | AQ19: 38.77 | AR19: 37.82 | AS19: 37.86 | AT19: 38.89 | AU19: 41.64 | AV19: 46.15 | AW19: 48.26 | AX19: 48.69 | AY19: 48.77 | BA19: 64.05 | BB19: 1.3029
A20: =+A15+7 -> 43850 | B20: 20200120 | C20: 43850 | D20: 27.35 | E20: 26.57 | F20: 25.85 | G20: 25.9 | H20: 25.74 | I20: 26.14 | J20: 26.59 | K20: 27.94 | L20: 30.04 | M20: 37.04 | N20: 40.09 | O20: 41.99 | P20: 42.75 | Q20: 40.2 | R20: 36.93 | S20: 34.78 | T20: 34.26 | U20: 33.99 | V20: 34.6 | W20: 36.04 | X20: 39.79 | Y20: 42.88 | Z20: 45.27 | AA20: 48.84 | AB20: 48.13 | AC20: 44.37 | AD20: 39.05 | AE20: 37.4 | AF20: 37.05 | AG20: 37.67 | AH20: 38.61 | AI20: 39.53 | AJ20: 42.61 | AK20: 45.1 | AL20: 47.65 | AM20: 49.44 | AN20: 49.41 | AO20: 46.43 | AP20: 40.64 | AQ20: 38.71 | AR20: 37.76 | AS20: 37.8 | AT20: 38.83 | AU20: 41.58 | AV20: 46.09 | AW20: 48.2 | AX20: 48.63 | AY20: 48.71 | BA20: 64.63 | BB20: 1.2998
A21: =+A16+7 -> 43851 | B21: 20200121 | C21: 43851 | D21: 27.85 | E21: 26.96 | F21: 26.26 | G21: 26.05 | H21: 26.01 | I21: 26.44 | J21: 26.92 | K21: 28.14 | L21: 30.23 | M21: 37.18 | N21: 40.15 | O21: 41.94 | P21: 42.66 | Q21: 40.02 | R21: 36.66 | S21: 34.48 | T21: 33.95 | U21: 33.68 | V21: 34.29 | W21: 35.73 | X21: 39.53 | Y21: 42.69 | Z21: 45.11 | AA21: 48.71 | AB21: 48.02 | AC21: 44.29 | AD21: 38.98 | AE21: 37.34 | AF21: 37 | AG21: 37.63 | AH21: 38.58 | AI21: 39.5 | AJ21: 42.55 | AK21: 45.02 | AL21: 47.54 | AM21: 49.27 | AN21: 49.18 | AO21: 46.12 | AP21: 40.32 | AQ21: 38.39 | AR21: 37.44 | AS21: 37.48 | AT21: 38.51 | AU21: 41.26 | AV21: 45.77 | AW21: 47.88 | AX21: 48.32 | AY21: 48.42 | BA21: 63.66 | BB21: 1.3058
A22: =+A17+7 -> 43852 | B22: 20200122 | C22: 43852 | D22: 26.81 | E22: 25.92 | F22: 25.3 | G22: 25.15 | H22: 25.1 | I22: 25.54 | J22: 26.06 | K22: 27.29 | L22: 29.29 | M22: 36.21 | N22: 39.29 | O22: 41.4 | P22: 41.77 | Q22: 39.13 | R22: 35.91 | S22: 33.73 | T22: 33.2 | U22: 32.93 | V22: 33.54 | W22: 34.98 | X22: 38.68 | Y22: 41.8 | Z22: 44.22 | AA22: 47.82 | AB22: 47.13 | AC22: 43.43 | AD22: 38.16 | AE22: 36.59 | AF22: 36.27 | AG22: 36.9 | AH22: 37.85 | AI22: 38.77 | AJ22: 41.77 | AK22: 44.24 | AL22: 46.76 | AM22: 48.49 | AN22: 48.4 | AO22: 45.34 | AP22: 39.46 | AQ22: 37.48 | AR22: 36.49 | AS22: 36.54 | AT22: 37.58 | AU22: 40.34 | AV22: 44.86 | AW22: 46.97 | AX22: 47.41 | AY22: 47.51 | BA22: 62.11 | BB22: 1.3141
A23: =+A18+7 -> 43853 | B23: 20200123 | C23: 43853 | D23: 26.77 | E23: 25.69 | F23: 25.05 | G23: 24.96 | H23: 24.89 | I23: 25.24 | J23: 25.79 | K23: 27.01 | L23: 28.94 | M23: 35.44 | N23: 38.56 | O23: 41.07 | P23: 40.96 | Q23: 38.23 | R23: 35.47 | S23: 33.46 | T23: 32.96 | U23: 32.66 | V23: 33.27 | W23: 34.76 | X23: 38.46 | Y23: 41.58 | Z23: 44 | AA23: 47.6 | AB23: 46.91 | AC23: 43.18 | AD23: 38.16 | AE23: 36.69 | AF23: 36.37 | AG23: 37 | AH23: 37.95 | AI23: 38.82 | AJ23: 41.71 | AK23: 44.13 | AL23: 46.65 | AM23: 48.38 | AN23: 48.29 | AO23: 45.23 | AP23: 39.35 | AQ23: 37.37 | AR23: 36.38 | AS23: 36.43 | AT23: 37.47 | AU23: 40.23 | AV23: 44.75 | AW23: 46.86 | AX23: 47.3 | AY23: 47.4 | BA23: 61.26 | BB23: 1.3118
... A78: =+A73+7 -> 43930 | B78: 20200409 | C78: 43930 | D78: 16.86 | E78: 17.71 | F78: 18.67 | G78: 20.08 | H78: 22.26 | I78: 25.22 | J78: 32.48 | K78: 35.73 | L78: 37.19 | M78: 37.65 | N78: 35.18 | O78: 32.63 | P78: 30.65 | Q78: 29.84 | R78: 29.62 | S78: 30.42 | T78: 32.3 | U78: 35.74 | V78: 38.37 | W78: 40.68 | X78: 44.18 | Y78: 43.8 | Z78: 40.18 | AA78: 36.06 | AB78: 34.98 | AC78: 34.66 | AD78: 33.97 | AE78: 34.4 | AF78: 35.61 | AG78: 39.07 | AH78: 42.2 | AI78: 45.07 | AJ78: 47.17 | AK78: 47.27 | AL78: 44.97 | AM78: 39.92 | AN78: 38.17 | AO78: 37.23 | AP78: 37.39 | AQ78: 38.25 | AR78: 40.93 | AS78: 45.39 | AT78: 47.35 | AU78: 47.68 | AV78: 47.81 | AW78: 45.36 | AX78: 42.82 | AY78: 38.91 | BA78: 20.23 | BB78: 1.247
A79: =+A74+7 -> 43931 | B79: 20200410 | C79: 43931 | D79: #N/A | E79: #N/A | F79: #N/A | G79: #N/A | H79: #N/A | I79: #N/A | J79: #N/A | K79: #N/A | L79: #N/A | M79: #N/A | N79: #N/A | O79: #N/A | P79: #N/A | Q79: #N/A | R79: #N/A | S79: #N/A | T79: #N/A | U79: #N/A | V79: #N/A | W79: #N/A | X79: #N/A | Y79: #N/A | Z79: #N/A | AA79: #N/A | AB79: #N/A | AC79: #N/A | AD79: #N/A | AE79: #N/A | AF79: #N/A | AG79: #N/A | AH79: #N/A | AI79: #N/A | AJ79: #N/A | AK79: #N/A | AL79: #N/A | AM79: #N/A | AN79: #N/A | AO79: #N/A | AP79: #N/A | AQ79: #N/A | AR79: #N/A | AS79: #N/A | AT79: #N/A | AU79: #N/A | AV79: #N/A | AW79: #N/A | AX79: #N/A | AY79: #N/A | BA79: #N/A | BB79: #N/A
A80: =+A75+7 -> 43934 | B80: 20200413 | C80: 43934 | D80: 16.86 | E80: 17.71 | F80: 18.67 | G80: 20.08 | H80: 22.26 | I80: 25.22 | J80: 32.48 | K80: 35.73 | L80: 37.19 | M80: 37.65 | N80: 35.18 | O80: 32.63 | P80: 30.65 | Q80: 29.84 | R80: 29.62 | S80: 30.42 | T80: 32.3 | U80: 35.74 | V80: 38.37 | W80: 40.68 | X80: 44.18 | Y80: 43.8 | Z80: 40.18 | AA80: 36.06 | AB80: 34.98 | AC80: 34.66 | AD80: 33.97 | AE80: 34.4 | AF80: 35.61 | AG80: 39.07 | AH80: 42.2 | AI80: 45.07 | AJ80: 47.17 | AK80: 47.27 | AL80: 44.97 | AM80: 39.92 | AN80: 38.17 | AO80: 37.23 | AP80: 37.39 | AQ80: 38.25 | AR80: 40.93 | AS80: 45.39 | AT80: 47.35 | AU80: 47.68 | AV80: 47.81 | AW80: 45.36 | AX80: 42.82 | AY80: 38.91 | BA80: #N/A | BB80: #N/A
A81: =+A76+7 -> 43935 | B81: 20200414 | C81: 43935 | D81: 15.52 | E81: 16.41 | F81: 17.34 | G81: 18.74 | H81: 20.9 | I81: 23.81 | J81: 31.34 | K81: 34.66 | L81: 36.34 | M81: 36.77 | N81: 33.77 | O81: 31.52 | P81: 29.63 | Q81: 28.89 | R81: 28.72 | S81: 29.52 | T81: 31.39 | U81: 34.82 | V81: 37.45 | W81: 39.76 | X81: 43.26 | Y81: 42.88 | Z81: 39.3 | AA81: 35.22 | AB81: 34.14 | AC81: 33.82 | AD81: 33.13 | AE81: 33.56 | AF81: 34.77 | AG81: 38.24 | AH81: 41.37 | AI81: 44.24 | AJ81: 46.34 | AK81: 46.44 | AL81: 44.14 | AM81: 39.09 | AN81: 37.34 | AO81: 36.4 | AP81: 36.56 | AQ81: 37.42 | AR81: 40.1 | AS81: 44.56 | AT81: 46.52 | AU81: 46.85 | AV81: 46.98 | AW81: 44.53 | AX81: 41.99 | AY81: 38.08 | BA81: 21.74 | BB81: 1.2594
A82: =+A77+7 -> 43936 | B82: 20200415 | C82: 43936 | D82: 14.68 | E82: 15.39 | F82: 16.37 | G82: 17.87 | H82: 20.06 | I82: 22.87 | J82: 30.43 | K82: 33.82 | L82: 35.39 | M82: 35.79 | N82: 33.37 | O82: 31.07 | P82: 29.1 | Q82: 28.33 | R82: 28.13 | S82: 28.9 | T82: 30.74 | U82: 34.22 | V82: 36.91 | W82: 39.24 | X82: 42.77 | Y82: 42.42 | Z82: 38.87 | AA82: 34.82 | AB82: 33.74 | AC82: 33.42 | AD82: 32.69 | AE82: 33.12 | AF82: 34.33 | AG82: 37.83 | AH82: 40.99 | AI82: 43.86 | AJ82: 45.96 | AK82: 46.06 | AL82: 43.76 | AM82: 38.71 | AN82: 36.96 | AO82: 36.02 | AP82: 36.18 | AQ82: 37.04 | AR82: 39.72 | AS82: 44.18 | AT82: 46.14 | AU82: 46.47 | AV82: 46.6 | AW82: 44.15 | AX82: 41.65 | AY82: 37.8 | BA82: 19.8 | BB82: 1.2498
A83: =+A78+7 -> 43937 | B83: 20200416 | C83: 43937 | D83: 15.2 | E83: 15.98 | F83: 17.01 | G83: 18.44 | H83: 20.72 | I83: 23.77 | J83: 31.65 | K83: 35.14 | L83: 36.66 | M83: 37.05 | N83: 34.57 | O83: 32.12 | P83: 30.05 | Q83: 29.18 | R83: 28.91 | S83: 29.66 | T83: 31.45 | U83: 34.93 | V83: 37.57 | W83: 39.89 | X83: 43.42 | Y83: 43.07 | Z83: 39.42 | AA83: 35.44 | AB83: 34.26 | AC83: 33.87 | AD83: 33.14 | AE83: 33.57 | AF83: 34.77 | AG83: 38.38 | AH83: 41.53 | AI83: 44.4 | AJ83: 46.46 | AK83: 46.52 | AL83: 44.06 | AM83: 38.95 | AN83: 37 | AO83: 36.06 | AP83: 36.24 | AQ83: 37.18 | AR83: 39.94 | AS83: 44.53 | AT83: 46.62 | AU83: 46.98 | AV83: 47.08 | AW83: 44.6 | AX83: 42.06 | AY83: 38.16 | BA83: 18.69 | BB83: 1.2451
A84: =+A79+7 -> 43938 | B84: 20200417 | C84: 43938 | D84: 15.36 | E84: 16.34 | F84: 17.53 | G84: 18.94 | H84: 21.06 | I84: 24.63 | J84: 32.66 | K84: 36.07 | L84: 37.57 | M84: 37.83 | N84: 35.81 | O84: 33.07 | P84: 30.81 | Q84: 29.87 | R84: 29.55 | S84: 30.3 | T84: 32.09 | U84: 35.67 | V84: 38.42 | W84: 40.85 | X84: 44.38 | Y84: 43.97 | Z84: 40.1 | AA84: 35.97 | AB84: 34.63 | AC84: 34.08 | AD84: 33.35 | AE84: 33.8 | AF84: 35.02 | AG84: 38.89 | AH84: 42.04 | AI84: 44.91 | AJ84: 46.97 | AK84: 47.03 | AL84: 44.53 | AM84: 39.38 | AN84: 37.38 | AO84: 36.4 | AP84: 36.58 | AQ84: 37.52 | AR84: 40.28 | AS84: 44.87 | AT84: 46.96 | AU84: 47.32 | AV84: 47.42 | AW84: 44.94 | AX84: 42.4 | AY84: 38.4 | BA84: 19.75 | BB84: 1.2504
A85: =+A80+7 -> 43941 | B85: 20200420 | C85: 43941 | D85: 13.8 | E85: 15.81 | F85: 17.18 | G85: 18.66 | H85: 20.81 | I85: 24.28 | J85: 32.53 | K85: 36.09 | L85: 37.22 | M85: 37.58 | N85: 35.56 | O85: 32.94 | P85: 30.7 | Q85: 29.77 | R85: 29.4 | S85: 30.09 | T85: 31.83 | U85: 35.22 | V85: 37.97 | W85: 40.4 | X85: 44.03 | Y85: 43.68 | Z85: 39.92 | AA85: 35.9 | AB85: 34.6 | AC85: 34.05 | AD85: 33.32 | AE85: 33.77 | AF85: 34.99 | AG85: 38.86 | AH85: 42.01 | AI85: 44.88 | AJ85: 46.94 | AK85: 47 | AL85: 44.5 | AM85: 39.35 | AN85: 37.35 | AO85: 36.37 | AP85: 36.55 | AQ85: 37.49 | AR85: 40.25 | AS85: 44.84 | AT85: 46.93 | AU85: 47.29 | AV85: 47.39 | AW85: 44.91 | AX85: 42.37 | AY85: 38.37 | BA85: 17.36 | BB85: 1.2473
A86: =+A81+7 -> 43942 | B86: 20200421 | C86: 43942 | D86: 13.99 | E86: 15.7 | F86: 17.15 | G86: 18.48 | H86: 20.58 | I86: 23.66 | J86: 32.16 | K86: 35.66 | L86: 36.8 | M86: 37.1 | N86: 35.07 | O86: 32.31 | P86: 30.01 | Q86: 29.15 | R86: 28.85 | S86: 29.59 | T86: 31.33 | U86: 34.72 | V86: 37.41 | W86: 39.79 | X86: 43.31 | Y86: 42.96 | Z86: 39.2 | AA86: 35.18 | AB86: 33.88 | AC86: 33.33 | AD86: 32.6 | AE86: 33.04 | AF86: 34.25 | AG86: 38.1 | AH86: 41.23 | AI86: 44.1 | AJ86: 46.16 | AK86: 46.22 | AL86: 43.64 | AM86: 38.4 | AN86: 36.33 | AO86: 35.35 | AP86: 35.55 | AQ86: 36.64 | AR86: 39.59 | AS86: 44.28 | AT86: 46.46 | AU86: 46.82 | AV86: 46.92 | AW86: 44.44 | AX86: 41.9 | AY86: 37.9 | BA86: 9.12 | BB86: 1.2273
A87: =+A82+7 -> 43943 | B87: 20200422 | C87: 43943 | D87: 14.43 | E87: 15.3 | F87: 16.8 | G87: 18.16 | H87: 20.18 | I87: 23.22 | J87: 31.62 | K87: 35 | L87: 36.3 | M87: 36.45 | N87: 34.46 | O87: 31.69 | P87: 29.39 | Q87: 28.53 | R87: 28.23 | S87: 28.91 | T87: 30.63 | U87: 34.02 | V87: 36.71 | W87: 39.09 | X87: 42.57 | Y87: 42.22 | Z87: 38.46 | AA87: 34.44 | AB87: 33.14 | AC87: 32.59 | AD87: 31.86 | AE87: 32.23 | AF87: 33.35 | AG87: 37.14 | AH87: 40.19 | AI87: 42.95 | AJ87: 44.96 | AK87: 45.02 | AL87: 42.54 | AM87: 37.45 | AN87: 35.44 | AO87: 34.46 | AP87: 34.66 | AQ87: 35.75 | AR87: 38.7 | AS87: 43.39 | AT87: 45.57 | AU87: 45.93 | AV87: 46.03 | AW87: 43.55 | AX87: 41.01 | AY87: 37.01 | BA87: 13.77 | BB87: 1.2329
A88: =+A83+7 -> 43944 | B88: 20200423 | C88: 43944 | D88: 13.82 | E88: 14.54 | F88: 16.07 | G88: 17.45 | H88: 19.43 | I88: 22.54 | J88: 31.22 | K88: 34.6 | L88: 36.01 | M88: 36.17 | N88: 34.19 | O88: 31.29 | P88: 29 | Q88: 28.13 | R88: 27.83 | S88: 28.56 | T88: 30.34 | U88: 33.77 | V88: 36.5 | W88: 38.88 | X88: 42.39 | Y88: 42.05 | Z88: 38.29 | AA88: 34.27 | AB88: 32.97 | AC88: 32.42 | AD88: 31.69 | AE88: 32.16 | AF88: 33.42 | AG88: 37.21 | AH88: 40.26 | AI88: 43.02 | AJ88: 45.03 | AK88: 45.09 | AL88: 42.61 | AM88: 37.52 | AN88: 35.51 | AO88: 34.53 | AP88: 34.73 | AQ88: 35.82 | AR88: 38.77 | AS88: 43.46 | AT88: 45.64 | AU88: 46 | AV88: 46.1 | AW88: 43.62 | AX88: 41.08 | AY88: 37.08 | BA88: 15.06 | BB88: 1.2386
A89: =+A84+7 -> 43945 | B89: 20200424 | C89: 43945 | D89: 12.76 | E89: 13.74 | F89: 15.29 | G89: 16.79 | H89: 18.99 | I89: 22.09 | J89: 30.77 | K89: 34.29 | L89: 35.83 | M89: 35.92 | N89: 33.77 | O89: 30.81 | P89: 28.6 | Q89: 27.76 | R89: 27.53 | S89: 28.34 | T89: 30.26 | U89: 33.76 | V89: 36.45 | W89: 38.68 | X89: 42.08 | Y89: 41.82 | Z89: 38.17 | AA89: 34.16 | AB89: 32.86 | AC89: 32.31 | AD89: 31.58 | AE89: 32.05 | AF89: 33.31 | AG89: 37.15 | AH89: 40.2 | AI89: 42.96 | AJ89: 44.92 | AK89: 44.98 | AL89: 42.5 | AM89: 37.41 | AN89: 35.4 | AO89: 34.42 | AP89: 34.62 | AQ89: 35.71 | AR89: 38.66 | AS89: 43.35 | AT89: 45.53 | AU89: 45.89 | AV89: 45.99 | AW89: 43.51 | AX89: 40.97 | AY89: 36.97 | BA89: 15.87 | BB89: 1.2338
A90: =+A85+7 -> 43948 | B90: 20200427 | C90: 43948 | D90: 13.14 | E90: 13.95 | F90: 15.48 | G90: 16.99 | H90: 19.1 | I90: 22.01 | J90: 30.59 | K90: 34.04 | L90: 35.5 | M90: 35.49 | N90: 33.25 | O90: 30.38 | P90: 28.34 | Q90: 27.58 | R90: 27.35 | S90: 28.16 | T90: 30 | U90: 33.51 | V90: 36.11 | W90: 38.32 | X90: 41.72 | Y90: 41.46 | Z90: 37.74 | AA90: 33.66 | AB90: 32.31 | AC90: 31.76 | AD90: 31.03 | AE90: 31.5 | AF90: 32.76 | AG90: 36.68 | AH90: 39.79 | AI90: 42.55 | AJ90: 44.51 | AK90: 44.57 | AL90: 42.09 | AM90: 37 | AN90: 34.99 | AO90: 34.01 | AP90: 34.21 | AQ90: 35.3 | AR90: 38.25 | AS90: 42.94 | AT90: 45.12 | AU90: 45.48 | AV90: 45.58 | AW90: 43.1 | AX90: 40.56 | AY90: 36.56 | BA90: 15.17 | BB90: 1.2409
A91: =+A86+7 -> 43949 | B91: 20200428 | C91: 43949 | D91: 13.83 | E91: 14.42 | F91: 15.82 | G91: 17.33 | H91: 19.36 | I91: 22.11 | J91: 30.37 | K91: 33.86 | L91: 35.43 | M91: 35.46 | N91: 33.18 | O91: 30.26 | P91: 28.22 | Q91: 27.43 | R91: 27.17 | S91: 27.98 | T91: 29.82 | U91: 33.31 | V91: 35.91 | W91: 38.12 | X91: 41.57 | Y91: 41.36 | Z91: 37.73 | AA91: 33.67 | AB91: 32.41 | AC91: 31.91 | AD91: 31.23 | AE91: 31.7 | AF91: 32.96 | AG91: 36.93 | AH91: 40.04 | AI91: 42.8 | AJ91: 44.76 | AK91: 44.82 | AL91: 42.34 | AM91: 37.25 | AN91: 35.24 | AO91: 34.26 | AP91: 34.46 | AQ91: 35.55 | AR91: 38.5 | AS91: 43.19 | AT91: 45.37 | AU91: 45.73 | AV91: 45.83 | AW91: 43.35 | AX91: 40.81 | AY91: 36.81 | BA91: 15.6 | BB91: 1.2436
A92: =+A87+7 -> 43950 | B92: 20200429 | C92: 43950 | D92: 13.24 | E92: 13.98 | F92: 15.43 | G92: 16.92 | H92: 19.08 | I92: 21.84 | J92: 30.44 | K92: 33.67 | L92: 35.64 | M92: 35.49 | N92: 32.77 | O92: 29.95 | P92: 28.02 | Q92: 27.31 | R92: 27 | S92: 27.78 | T92: 29.56 | U92: 33.04 | V92: 35.64 | W92: 37.82 | X92: 41.24 | Y92: 41 | Z92: 37.34 | AA92: 33.22 | AB92: 31.93 | AC92: 31.43 | AD92: 30.75 | AE92: 31.22 | AF92: 32.48 | AG92: 36.45 | AH92: 39.55 | AI92: 42.26 | AJ92: 44.16 | AK92: 44.22 | AL92: 41.74 | AM92: 36.65 | AN92: 34.64 | AO92: 33.66 | AP92: 33.86 | AQ92: 34.95 | AR92: 37.91 | AS92: 42.6 | AT92: 44.86 | AU92: 45.21 | AV92: 45.31 | AW92: 42.77 | AX92: 40.16 | AY92: 36.09 | BA92: 17.86 | BB92: 1.2436
... A98: =+A93+7 -> 43958 | B98: 20200507 | C98: 43958 | D98: 13.98 | E98: 15.07 | F98: 16.59 | G98: 19.2 | H98: 22.25 | I98: 31.2 | J98: 34.81 | K98: 36.17 | L98: 36.59 | M98: 34.1 | N98: 30.99 | O98: 29 | P98: 28.18 | Q98: 27.84 | R98: 28.52 | S98: 30.22 | T98: 33.66 | U98: 36.24 | V98: 38.37 | W98: 41.72 | X98: 41.43 | Y98: 37.69 | Z98: 33.63 | AA98: 32.3 | AB98: 31.78 | AC98: 31.08 | AD98: 31.52 | AE98: 32.66 | AF98: 36.29 | AG98: 39.33 | AH98: 42.04 | AI98: 43.87 | AJ98: 43.87 | AK98: 41.37 | AL98: 36.38 | AM98: 34.4 | AN98: 33.42 | AO98: 33.59 | AP98: 34.65 | AQ98: 37.58 | AR98: 42.24 | AS98: 44.49 | AT98: 44.84 | AU98: 44.88 | AV98: 42.3 | AW98: 39.65 | AX98: 35.58 | AY98: 35.26 | BA98: 24.23 | BB98: 1.2287
A99: =+A94+7 -> 43959 | B99: 20200508 | C99: 43959 | D99: 13.98 | E99: 15.07 | F99: 16.59 | G99: 19.2 | H99: 22.25 | I99: 31.2 | J99: 34.81 | K99: 36.17 | L99: 36.59 | M99: 34.1 | N99: 30.99 | O99: 29 | P99: 28.18 | Q99: 27.84 | R99: 28.52 | S99: 30.22 | T99: 33.66 | U99: 36.24 | V99: 38.37 | W99: 41.72 | X99: 41.43 | Y99: 37.69 | Z99: 33.63 | AA99: 32.3 | AB99: 31.78 | AC99: 31.08 | AD99: 31.52 | AE99: 32.66 | AF99: 36.29 | AG99: 39.33 | AH99: 42.04 | AI99: 43.87 | AJ99: 43.87 | AK99: 41.37 | AL99: 36.38 | AM99: 34.4 | AN99: 33.42 | AO99: 33.59 | AP99: 34.65 | AQ99: 37.58 | AR99: 42.24 | AS99: 44.49 | AT99: 44.84 | AU99: 44.88 | AV99: 42.3 | AW99: 39.65 | AX99: 35.58 | AY99: 35.26 | BA99: #N/A | BB99: #N/A
A100: =+A95+7 -> 43962 | B100: 20200511 | C100: 43962 | D100: 13.29 | E100: 14.44 | F100: 16.06 | G100: 18.79 | H100: 22.26 | I100: 31.33 | J100: 34.96 | K100: 36.3 | L100: 36.81 | M100: 34.29 | N100: 31.13 | O100: 29.14 | P100: 28.32 | Q100: 28.11 | R100: 28.88 | S100: 30.48 | T100: 33.92 | U100: 36.41 | V100: 38.54 | W100: 41.89 | X100: 41.6 | Y100: 37.92 | Z100: 33.85 | AA100: 32.52 | AB100: 32.05 | AC100: 31.35 | AD100: 31.79 | AE100: 32.96 | AF100: 36.63 | AG100: 39.67 | AH100: 42.38 | AI100: 44.21 | AJ100: 44.21 | AK100: 41.71 | AL100: 36.67 | AM100: 34.64 | AN100: 33.66 | AO100: 33.79 | AP100: 34.85 | AQ100: 37.73 | AR100: 42.35 | AS100: 44.54 | AT100: 44.89 | AU100: 44.93 | AV100: 42.35 | AW100: 39.7 | AX100: 35.63 | AY100: 35.31 | BA100: 25.53 | BB100: 1.2358
A101: =+A96+7 -> 43963 | B101: 20200512 | C101: 43963 | D101: 12.2 | E101: 13.21 | F101: 15.11 | G101: 18.06 | H101: 21.56 | I101: 30.71 | J101: 34.49 | K101: 35.83 | L101: 36.22 | M101: 33.86 | N101: 30.56 | O101: 28.5 | P101: 27.68 | Q101: 27.44 | R101: 28.21 | S101: 29.86 | T101: 33.46 | U101: 35.98 | V101: 38.12 | W101: 41.47 | X101: 41.18 | Y101: 37.5 | Z101: 33.49 | AA101: 32.22 | AB101: 31.77 | AC101: 31.07 | AD101: 31.51 | AE101: 32.68 | AF101: 36.39 | AG101: 39.47 | AH101: 42.21 | AI101: 44.04 | AJ101: 44.04 | AK101: 41.54 | AL101: 36.5 | AM101: 34.47 | AN101: 33.49 | AO101: 33.62 | AP101: 34.68 | AQ101: 37.56 | AR101: 42.23 | AS101: 44.48 | AT101: 44.88 | AU101: 44.92 | AV101: 42.34 | AW101: 39.69 | AX101: 35.62 | AY101: 35.3 | BA101: 26.67 | BB101: 1.233
A102: =+A97+7 -> 43964 | B102: 20200513 | C102: 43964 | D102: 12.01 | E102: 12.53 | F102: 14.49 | G102: 17.51 | H102: 21.07 | I102: 30.28 | J102: 34.07 | K102: 35.55 | L102: 35.92 | M102: 33.61 | N102: 30.51 | O102: 28.59 | P102: 27.71 | Q102: 27.46 | R102: 28.23 | S102: 29.92 | T102: 33.47 | U102: 36.03 | V102: 38.17 | W102: 41.52 | X102: 41.23 | Y102: 37.55 | Z102: 33.44 | AA102: 32.17 | AB102: 31.72 | AC102: 31 | AD102: 31.33 | AE102: 32.4 | AF102: 36.01 | AG102: 39.09 | AH102: 41.83 | AI102: 43.66 | AJ102: 43.66 | AK102: 41.2 | AL102: 36.2 | AM102: 34.21 | AN102: 33.27 | AO102: 33.44 | AP102: 34.54 | AQ102: 37.46 | AR102: 42.17 | AS102: 44.42 | AT102: 44.82 | AU102: 44.86 | AV102: 42.28 | AW102: 39.63 | AX102: 35.56 | AY102: 35.24 | BA102: 27.89 | BB102: 1.2226
A103: =+A98+7 -> 43965 | B103: 20200514 | C103: 43965 | D103: 12.53 | E103: 12.91 | F103: 14.88 | G103: 17.94 | H103: 21.51 | I103: 30.75 | J103: 34.65 | K103: 36.17 | L103: 36.55 | M103: 34.24 | N103: 31.1 | O103: 29.14 | P103: 28.26 | Q103: 28.01 | R103: 28.78 | S103: 30.42 | T103: 33.93 | U103: 36.49 | V103: 38.69 | W103: 42.12 | X103: 41.91 | Y103: 38.23 | Z103: 34.09 | AA103: 32.8 | AB103: 32.3 | AC103: 31.53 | AD103: 31.81 | AE103: 32.82 | AF103: 36.41 | AG103: 39.44 | AH103: 42.13 | AI103: 43.96 | AJ103: 43.96 | AK103: 41.5 | AL103: 36.5 | AM103: 34.51 | AN103: 33.57 | AO103: 33.74 | AP103: 34.84 | AQ103: 37.76 | AR103: 42.47 | AS103: 44.72 | AT103: 45.12 | AU103: 45.16 | AV103: 42.58 | AW103: 39.93 | AX103: 35.86 | AY103: 35.54 | BA103: 29.87 | BB103: 1.2199
A104: =+A99+7 -> 43966 | B104: 20200515 | C104: 43966 | D104: 12.59 | E104: 12.92 | F104: 14.76 | G104: 17.91 | H104: 21.57 | I104: 30.94 | J104: 34.94 | K104: 36.52 | L104: 36.9 | M104: 34.39 | N104: 31.61 | O104: 29.82 | P104: 28.98 | Q104: 28.71 | R104: 29.46 | S104: 31.16 | T104: 34.76 | U104: 37.37 | V104: 39.59 | W104: 43.04 | X104: 42.87 | Y104: 39.24 | Z104: 35.06 | AA104: 33.8 | AB104: 33.34 | AC104: 32.53 | AD104: 32.81 | AE104: 33.8 | AF104: 37.41 | AG104: 40.44 | AH104: 43.13 | AI104: 44.96 | AJ104: 44.96 | AK104: 42.5 | AL104: 37.48 | AM104: 35.42 | AN104: 34.4 | AO104: 34.54 | AP104: 35.64 | AQ104: 38.56 | AR104: 43.29 | AS104: 45.55 | AT104: 45.96 | AU104: 46.01 | AV104: 43.43 | AW104: 40.78 | AX104: 36.71 | AY104: 36.39 | BA104: 30.95 | BB104: 1.2126
A105: =+A100+7 -> 43969 | B105: 20200518 | C105: 43969 | D105: 11.53 | E105: 11.95 | F105: 13.87 | G105: 17.31 | H105: 21.3 | I105: 31.03 | J105: 35.2 | K105: 36.78 | L105: 37.14 | M105: 34.64 | N105: 31.8 | O105: 29.91 | P105: 29.07 | Q105: 28.8 | R105: 29.55 | S105: 31.25 | T105: 34.92 | U105: 37.53 | V105: 39.75 | W105: 43.2 | X105: 43.03 | Y105: 39.4 | Z105: 35.32 | AA105: 34.06 | AB105: 33.6 | AC105: 32.78 | AD105: 33.05 | AE105: 34 | AF105: 37.47 | AG105: 40.44 | AH105: 43.08 | AI105: 44.83 | AJ105: 44.83 | AK105: 42.37 | AL105: 37.35 | AM105: 35.29 | AN105: 34.27 | AO105: 34.41 | AP105: 35.51 | AQ105: 38.43 | AR105: 43.16 | AS105: 45.42 | AT105: 45.83 | AU105: 45.88 | AV105: 43.3 | AW105: 40.65 | AX105: 36.58 | AY105: 36.26 | BA105: 33.3 | BB105: 1.2192
A106: =+A101+7 -> 43970 | B106: 20200519 | C106: 43970 | D106: 11.17 | E106: 11.46 | F106: 13.22 | G106: 16.7 | H106: 20.8 | I106: 30.77 | J106: 35.05 | K106: 36.84 | L106: 37.21 | M106: 34.71 | N106: 31.86 | O106: 29.97 | P106: 29.13 | Q106: 28.86 | R106: 29.64 | S106: 31.37 | T106: 35 | U106: 37.63 | V106: 39.86 | W106: 43.31 | X106: 43.14 | Y106: 39.45 | Z106: 35.32 | AA106: 34.08 | AB106: 33.62 | AC106: 32.8 | AD106: 33.07 | AE106: 34.02 | AF106: 37.54 | AG106: 40.56 | AH106: 43.26 | AI106: 45.04 | AJ106: 45.04 | AK106: 42.58 | AL106: 37.55 | AM106: 35.48 | AN106: 34.46 | AO106: 34.6 | AP106: 35.7 | AQ106: 38.62 | AR106: 43.35 | AS106: 45.61 | AT106: 46.02 | AU106: 46.07 | AV106: 43.49 | AW106: 40.84 | AX106: 36.77 | AY106: 36.45 | BA106: 33.06 | BB106: 1.2251
A107: =+A102+7 -> 43971 | B107: 20200520 | C107: 43971 | D107: 10.78 | E107: 10.98 | F107: 12.74 | G107: 16.23 | H107: 20.56 | I107: 30.58 | J107: 34.9 | K107: 36.88 | L107: 37.22 | M107: 34.82 | N107: 32.02 | O107: 30.17 | P107: 29.36 | Q107: 29.11 | R107: 29.89 | S107: 31.6 | T107: 35.2 | U107: 37.79 | V107: 40.02 | W107: 43.47 | X107: 43.3 | Y107: 39.61 | Z107: 35.39 | AA107: 34.13 | AB107: 33.67 | AC107: 32.87 | AD107: 33.14 | AE107: 34.09 | AF107: 37.71 | AG107: 40.78 | AH107: 43.48 | AI107: 45.26 | AJ107: 45.26 | AK107: 42.8 | AL107: 37.81 | AM107: 35.74 | AN107: 34.72 | AO107: 34.86 | AP107: 35.96 | AQ107: 38.88 | AR107: 43.69 | AS107: 46.02 | AT107: 46.43 | AU107: 46.48 | AV107: 43.9 | AW107: 41.25 | AX107: 37.18 | AY107: 36.86 | BA107: 34.76 | BB107: 1.227
A108: =+A103+7 -> 43972 | B108: 20200521 | C108: 43972 | D108: 9.27 | E108: 9.49 | F108: 11.36 | G108: 14.81 | H108: 19.12 | I108: 29.35 | J108: 33.8 | K108: 35.53 | L108: 35.92 | M108: 33.93 | N108: 31.63 | O108: 29.78 | P108: 28.87 | Q108: 28.62 | R108: 29.5 | S108: 31.36 | T108: 35.15 | U108: 37.94 | V108: 40.36 | W108: 43.91 | X108: 43.74 | Y108: 40.05 | Z108: 35.7 | AA108: 34.34 | AB108: 33.83 | AC108: 33.03 | AD108: 33.3 | AE108: 34.25 | AF108: 37.87 | AG108: 40.94 | AH108: 43.64 | AI108: 45.42 | AJ108: 45.42 | AK108: 42.96 | AL108: 37.87 | AM108: 35.78 | AN108: 34.76 | AO108: 34.9 | AP108: 36 | AQ108: 38.92 | AR108: 43.73 | AS108: 46.06 | AT108: 46.47 | AU108: 46.52 | AV108: 43.94 | AW108: 41.29 | AX108: 37.22 | AY108: 36.9 | BA108: 34.78 | BB108: 1.2212
A109: =+A104+7 -> 43973 | B109: 20200522 | C109: 43973 | D109: 9.46 | E109: 9.93 | F109: 11.65 | G109: 14.85 | H109: 18.62 | I109: 28.68 | J109: 33.07 | K109: 35.07 | L109: 35.46 | M109: 33.31 | N109: 30.97 | O109: 29.11 | P109: 28.08 | Q109: 27.8 | R109: 28.68 | S109: 30.6 | T109: 34.54 | U109: 37.43 | V109: 39.92 | W109: 43.53 | X109: 43.41 | Y109: 39.75 | Z109: 35.38 | AA109: 34 | AB109: 33.47 | AC109: 32.67 | AD109: 32.94 | AE109: 33.95 | AF109: 37.68 | AG109: 40.81 | AH109: 43.51 | AI109: 45.29 | AJ109: 45.29 | AK109: 42.83 | AL109: 37.59 | AM109: 35.4 | AN109: 34.35 | AO109: 34.49 | AP109: 35.59 | AQ109: 38.51 | AR109: 43.32 | AS109: 45.65 | AT109: 46.06 | AU109: 46.11 | AV109: 43.53 | AW109: 40.88 | AX109: 36.81 | AY109: 36.49 | BA109: 33.8 | BB109: 1.219
A110: =+A105+7 -> 43976 | B110: 20200525 | C110: 43976 | D110: 9.46 | E110: 9.93 | F110: 11.65 | G110: 14.85 | H110: 18.62 | I110: 28.68 | J110: 33.07 | K110: 35.07 | L110: 35.46 | M110: 33.31 | N110: 30.97 | O110: 29.11 | P110: 28.08 | Q110: 27.8 | R110: 28.68 | S110: 30.6 | T110: 34.54 | U110: 37.43 | V110: 39.92 | W110: 43.53 | X110: 43.41 | Y110: 39.75 | Z110: 35.38 | AA110: 34 | AB110: 33.47 | AC110: 32.67 | AD110: 32.94 | AE110: 33.95 | AF110: 37.68 | AG110: 40.81 | AH110: 43.51 | AI110: 45.29 | AJ110: 45.29 | AK110: 42.83 | AL110: 37.59 | AM110: 35.4 | AN110: 34.35 | AO110: 34.49 | AP110: 35.59 | AQ110: 38.51 | AR110: 43.32 | AS110: 45.65 | AT110: 46.06 | AU110: 46.11 | AV110: 43.53 | AW110: 40.88 | AX110: 36.81 | AY110: 36.49 | BA110: #N/A | BB110: #N/A
A111: =+A106+7 -> 43977 | B111: 20200526 | C111: 43977 | D111: 9.82 | E111: 10.05 | F111: 11.88 | G111: 14.97 | H111: 19.26 | I111: 29.54 | J111: 33.65 | K111: 35.6 | L111: 35.97 | M111: 33.74 | N111: 31.33 | O111: 29.45 | P111: 28.37 | Q111: 28.09 | R111: 28.97 | S111: 30.89 | T111: 34.83 | U111: 37.72 | V111: 40.21 | W111: 43.82 | X111: 43.7 | Y111: 40.04 | Z111: 35.64 | AA111: 34.23 | AB111: 33.67 | AC111: 32.87 | AD111: 33.13 | AE111: 34.05 | AF111: 37.69 | AG111: 40.74 | AH111: 43.41 | AI111: 45.19 | AJ111: 45.19 | AK111: 42.73 | AL111: 37.52 | AM111: 35.36 | AN111: 34.34 | AO111: 34.51 | AP111: 35.64 | AQ111: 38.59 | AR111: 43.43 | AS111: 45.79 | AT111: 46.23 | AU111: 46.28 | AV111: 43.7 | AW111: 41.05 | AX111: 36.98 | AY111: 36.66 | BA111: 33.95 | BB111: 1.2363
A112: =+A107+7 -> 43978 | B112: 20200527 | C112: 43978 | D112: 8.88 | E112: 9.23 | F112: 11.13 | G112: 14.33 | H112: 18.66 | I112: 28.98 | J112: 33.23 | K112: 35.21 | L112: 35.57 | M112: 33.34 | N112: 30.89 | O112: 28.98 | P112: 27.96 | Q112: 27.83 | R112: 28.75 | S112: 30.72 | T112: 34.71 | U112: 37.63 | V112: 40.12 | W112: 43.73 | X112: 43.61 | Y112: 39.95 | Z112: 35.52 | AA112: 34.09 | AB112: 33.53 | AC112: 32.77 | AD112: 33.05 | AE112: 33.99 | AF112: 37.65 | AG112: 40.7 | AH112: 43.37 | AI112: 45.15 | AJ112: 45.15 | AK112: 42.65 | AL112: 37.4 | AM112: 35.2 | AN112: 34.14 | AO112: 34.29 | AP112: 35.42 | AQ112: 38.37 | AR112: 43.23 | AS112: 45.61 | AT112: 46.07 | AU112: 46.12 | AV112: 43.54 | AW112: 40.89 | AX112: 36.82 | AY112: 36.5 | BA112: 32.73 | BB112: 1.2217
A113: =+A108+7 -> 43979 | B113: 20200528 | C113: 43979 | D113: 8.34 | E113: 8.77 | F113: 10.69 | G113: 14.08 | H113: 18.4 | I113: 28.67 | J113: 32.95 | K113: 34.9 | L113: 35.23 | M113: 33 | N113: 30.36 | O113: 28.35 | P113: 27.28 | Q113: 27.15 | R113: 28.07 | S113: 30.04 | T113: 34.1 | U113: 37.09 | V113: 39.65 | W113: 43.31 | X113: 43.23 | Y113: 39.61 | Z113: 35.23 | AA113: 33.84 | AB113: 33.28 | AC113: 32.52 | AD113: 32.8 | AE113: 33.74 | AF113: 37.4 | AG113: 40.45 | AH113: 43.12 | AI113: 44.9 | AJ113: 44.9 | AK113: 42.4 | AL113: 37.15 | AM113: 34.95 | AN113: 33.89 | AO113: 34.04 | AP113: 35.17 | AQ113: 38.05 | AR113: 42.86 | AS113: 45.19 | AT113: 45.61 | AU113: 45.66 | AV113: 43.08 | AW113: 40.43 | AX113: 36.36 | AY113: 36.04 | BA113: 33.98 | BB113: 1.2323
A114: =+A109+7 -> 43980 | B114: 20200529 | C114: 43980 | D114: 9.63 | E114: 11.3 | F114: 14.63 | G114: 18.76 | H114: 28.82 | I114: 33.03 | J114: 34.93 | K114: 35.57 | L114: 33.23 | M114: 30.53 | N114: 28.5 | O114: 27.39 | P114: 27.17 | Q114: 28.09 | R114: 30.06 | S114: 34.11 | T114: 37.07 | U114: 39.61 | V114: 43.27 | W114: 43.19 | X114: 39.52 | Y114: 35.06 | Z114: 33.64 | AA114: 33.05 | AB114: 32.29 | AC114: 32.57 | AD114: 33.51 | AE114: 37.23 | AF114: 40.32 | AG114: 43.02 | AH114: 44.8 | AI114: 44.8 | AJ114: 42.3 | AK114: 37.05 | AL114: 34.85 | AM114: 33.79 | AN114: 33.94 | AO114: 35.07 | AP114: 37.95 | AQ114: 42.76 | AR114: 45.09 | AS114: 45.51 | AT114: 45.56 | AU114: 42.98 | AV114: 40.33 | AW114: 36.26 | AX114: 35.94 | AY114: 35.78 | BA114: 34.15 | BB114: 1.2368
A115: =+A110+7 -> 43983 | B115: 20200601 | C115: 43983 | D115: 8.79 | E115: 10.55 | F115: 13.69 | G115: 17.92 | H115: 28.04 | I115: 32.4 | J115: 34.62 | K115: 35 | L115: 32.55 | M115: 29.83 | N115: 27.88 | O115: 26.79 | P115: 26.62 | Q115: 27.59 | R115: 29.61 | S115: 33.7 | T115: 36.69 | U115: 39.23 | V115: 42.89 | W115: 42.81 | X115: 39.19 | Y115: 34.78 | Z115: 33.36 | AA115: 32.77 | AB115: 32.01 | AC115: 32.29 | AD115: 33.23 | AE115: 36.95 | AF115: 40.04 | AG115: 42.74 | AH115: 44.52 | AI115: 44.52 | AJ115: 42.02 | AK115: 36.77 | AL115: 34.57 | AM115: 33.51 | AN115: 33.66 | AO115: 34.79 | AP115: 37.67 | AQ115: 42.48 | AR115: 44.81 | AS115: 45.23 | AT115: 45.28 | AU115: 42.7 | AV115: 40.05 | AW115: 35.98 | AX115: 35.66 | AY115: 35.5 | BA115: 36.74 | BB115: 1.2481
A116: =+A111+7 -> 43984 | B116: 20200602 | C116: 43984 | D116: 10.91 | E116: 12.46 | F116: 15.26 | G116: 19.19 | H116: 29.06 | I116: 32.95 | J116: 35 | K116: 35.47 | L116: 32.84 | M116: 30.27 | N116: 28.43 | O116: 27.34 | P116: 27.13 | Q116: 28.1 | R116: 30.17 | S116: 34.23 | T116: 37.17 | U116: 39.64 | V116: 43.24 | W116: 43.16 | X116: 39.54 | Y116: 35.13 | Z116: 33.71 | AA116: 33.12 | AB116: 32.36 | AC116: 32.7 | AD116: 33.75 | AE116: 37.54 | AF116: 40.63 | AG116: 43.33 | AH116: 45.11 | AI116: 45.11 | AJ116: 42.56 | AK116: 37.26 | AL116: 35.01 | AM116: 33.95 | AN116: 34.1 | AO116: 35.23 | AP116: 38.11 | AQ116: 42.92 | AR116: 45.25 | AS116: 45.67 | AT116: 45.72 | AU116: 43.14 | AV116: 40.49 | AW116: 36.42 | AX116: 36.1 | AY116: 35.94 | BA116: 37.72 | BB116: 1.2557
A117: =+A112+7 -> 43985 | B117: 20200603 | C117: 43985 | D117: 12.15 | E117: 13.61 | F117: 16.42 | G117: 19.95 | H117: 29.44 | I117: 32.95 | J117: 34.85 | K117: 35.3 | L117: 32.92 | M117: 30.02 | N117: 28.82 | O117: 27.87 | P117: 27.28 | Q117: 28.25 | R117: 30.32 | S117: 34.5 | T117: 37.44 | U117: 39.9 | V117: 43.5 | W117: 43.42 | X117: 39.79 | Y117: 35.37 | Z117: 33.95 | AA117: 33.36 | AB117: 32.53 | AC117: 32.87 | AD117: 33.91 | AE117: 37.68 | AF117: 40.77 | AG117: 43.47 | AH117: 45.25 | AI117: 45.25 | AJ117: 42.7 | AK117: 37.45 | AL117: 35.2 | AM117: 34.14 | AN117: 34.29 | AO117: 35.42 | AP117: 38.41 | AQ117: 43.28 | AR117: 45.61 | AS117: 46.03 | AT117: 46.08 | AU117: 43.5 | AV117: 40.85 | AW117: 36.78 | AX117: 36.46 | AY117: 36.3 | BA117: 37.98 | BB117: 1.2597
A118: =+A113+7 -> 43986 | B118: 20200604 | C118: 43986 | D118: 12.79 | E118: 14.05 | F118: 16.89 | G118: 20.34 | H118: 29.63 | I118: 33.69 | J118: 35.31 | K118: 35.68 | L118: 33.34 | M118: 30.39 | N118: 29.44 | O118: 28.4 | P118: 27.76 | Q118: 28.73 | R118: 30.8 | S118: 34.91 | T118: 37.79 | U118: 40.25 | V118: 43.85 | W118: 43.77 | X118: 40.14 | Y118: 35.72 | Z118: 34.3 | AA118: 33.71 | AB118: 32.88 | AC118: 33.22 | AD118: 34.26 | AE118: 37.81 | AF118: 40.9 | AG118: 43.6 | AH118: 45.38 | AI118: 45.38 | AJ118: 42.83 | AK118: 37.8 | AL118: 35.55 | AM118: 34.49 | AN118: 34.64 | AO118: 35.77 | AP118: 38.76 | AQ118: 43.63 | AR118: 45.96 | AS118: 46.38 | AT118: 46.43 | AU118: 43.85 | AV118: 41.2 | AW118: 37.13 | AX118: 36.81 | AY118: 36.65 | BA118: 38.41 | BB118: 1.2607
A119: =+A114+7 -> 43987 | B119: 20200605 | C119: 43987 | D119: 13.89 | E119: 15.13 | F119: 17.75 | G119: 21.13 | H119: 30.49 | I119: 34.49 | J119: 36.19 | K119: 36.53 | L119: 34.21 | M119: 31.21 | N119: 30.2 | O119: 29.08 | P119: 28.35 | Q119: 29.24 | R119: 31.11 | S119: 35.08 | T119: 37.86 | U119: 40.32 | V119: 43.92 | W119: 43.84 | X119: 40.21 | Y119: 35.9 | Z119: 34.48 | AA119: 33.94 | AB119: 33.18 | AC119: 33.58 | AD119: 34.68 | AE119: 38.29 | AF119: 41.38 | AG119: 44.06 | AH119: 45.79 | AI119: 45.74 | AJ119: 43.19 | AK119: 38.14 | AL119: 35.89 | AM119: 34.83 | AN119: 34.98 | AO119: 36.11 | AP119: 39.1 | AQ119: 43.99 | AR119: 46.32 | AS119: 46.69 | AT119: 46.69 | AU119: 44.06 | AV119: 41.36 | AW119: 37.24 | AX119: 36.87 | AY119: 36.66 | BA119: 41 | BB119: 1.2725
A120: =+A115+7 -> 43990 | B120: 20200608 | C120: 43990 | D120: 12.76 | E120: 14.23 | F120: 16.99 | G120: 20.5 | H120: 29.62 | I120: 33.8 | J120: 35.8 | K120: 35.67 | L120: 33.19 | M120: 30.39 | N120: 29.73 | O120: 28.67 | P120: 27.94 | Q120: 28.79 | R120: 30.64 | S120: 34.71 | T120: 37.63 | U120: 40.19 | V120: 43.79 | W120: 43.71 | X120: 40.08 | Y120: 35.68 | Z120: 34.26 | AA120: 33.72 | AB120: 32.96 | AC120: 33.36 | AD120: 34.48 | AE120: 38.09 | AF120: 41.18 | AG120: 43.86 | AH120: 45.59 | AI120: 45.54 | AJ120: 42.99 | AK120: 37.94 | AL120: 35.69 | AM120: 34.63 | AN120: 34.78 | AO120: 35.91 | AP120: 38.9 | AQ120: 43.79 | AR120: 46.12 | AS120: 46.49 | AT120: 46.49 | AU120: 43.86 | AV120: 41.16 | AW120: 37.04 | AX120: 36.67 | AY120: 36.46 | BA120: 39.66 | BB120: 1.2698
A121: =+A116+7 -> 43991 | B121: 20200609 | C121: 43991 | D121: 11.64 | E121: 13.12 | F121: 15.98 | G121: 19.61 | H121: 29.21 | I121: 33.12 | J121: 35.16 | K121: 35.18 | L121: 32.85 | M121: 30.18 | N121: 28.96 | O121: 28.14 | P121: 27.42 | Q121: 28.19 | R121: 29.97 | S121: 33.95 | T121: 36.82 | U121: 39.38 | V121: 42.98 | W121: 42.9 | X121: 39.28 | Y121: 34.94 | Z121: 33.59 | AA121: 33.12 | AB121: 32.43 | AC121: 32.93 | AD121: 34.14 | AE121: 37.83 | AF121: 40.95 | AG121: 43.63 | AH121: 45.36 | AI121: 45.31 | AJ121: 42.76 | AK121: 37.71 | AL121: 35.46 | AM121: 34.4 | AN121: 34.55 | AO121: 35.68 | AP121: 38.67 | AQ121: 43.56 | AR121: 45.89 | AS121: 46.26 | AT121: 46.26 | AU121: 43.63 | AV121: 40.93 | AW121: 36.83 | AX121: 36.46 | AY121: 36.25 | BA121: 40.45 | BB121: 1.2722
A122: =+A117+7 -> 43992 | B122: 20200610 | C122: 43992 | D122: 11.86 | E122: 13.02 | F122: 15.94 | G122: 19.56 | H122: 29.39 | I122: 33.39 | J122: 35.27 | K122: 35.43 | L122: 33.03 | M122: 30.36 | N122: 29.16 | O122: 28.44 | P122: 27.77 | Q122: 28.54 | R122: 30.32 | S122: 34.1 | T122: 36.86 | U122: 39.42 | V122: 43.02 | W122: 42.94 | X122: 39.32 | Y122: 35.15 | Z122: 33.8 | AA122: 33.33 | AB122: 32.64 | AC122: 33.14 | AD122: 34.35 | AE122: 37.87 | AF122: 40.99 | AG122: 43.67 | AH122: 45.4 | AI122: 45.35 | AJ122: 42.8 | AK122: 37.5 | AL122: 35.25 | AM122: 34.19 | AN122: 34.34 | AO122: 35.47 | AP122: 38.46 | AQ122: 43.73 | AR122: 46.15 | AS122: 46.52 | AT122: 46.52 | AU122: 43.89 | AV122: 41.19 | AW122: 37.09 | AX122: 36.72 | AY122: 36.51 | BA122: 41.18 | BB122: 1.2755
... A179: =+A174+7 -> 44071 | B179: 20200828 | C179: 44071 | D179: 28.95 | E179: 36.44 | F179: 40.15 | G179: 41.99 | H179: 42.24 | I179: 39.9 | J179: 36.79 | K179: 34.7 | L179: 32.97 | M179: 32.94 | N179: 33.1 | O179: 35.06 | P179: 39.43 | Q179: 42.29 | R179: 44.73 | S179: 48.35 | T179: 48.18 | U179: 44.3 | V179: 39.68 | W179: 37.41 | X179: 36.72 | Y179: 35.9 | Z179: 36.45 | AA179: 37.46 | AB179: 41.18 | AC179: 44.6 | AD179: 47.24 | AE179: 48.9 | AF179: 48.81 | AG179: 46.2 | AH179: 39.99 | AI179: 37.41 | AJ179: 36.33 | AK179: 36.54 | AL179: 37.74 | AM179: 40.68 | AN179: 46.01 | AO179: 48.35 | AP179: 48.51 | AQ179: 48.35 | AR179: 45.67 | AS179: 43.17 | AT179: 38.83 | AU179: 38.28 | AV179: 37.98 | AW179: 38.07 | AX179: 38.07 | AY179: 39.81 | BA179: 45.22 | BB179: 1.333
A180: =+A175+7 -> 44074 | B180: 20200831 | C180: 44074 | D180: 28.95 | E180: 36.44 | F180: 40.15 | G180: 41.99 | H180: 42.24 | I180: 39.9 | J180: 36.79 | K180: 34.7 | L180: 32.97 | M180: 32.94 | N180: 33.1 | O180: 35.06 | P180: 39.43 | Q180: 42.29 | R180: 44.73 | S180: 48.35 | T180: 48.18 | U180: 44.3 | V180: 39.68 | W180: 37.41 | X180: 36.72 | Y180: 35.9 | Z180: 36.45 | AA180: 37.46 | AB180: 41.18 | AC180: 44.6 | AD180: 47.24 | AE180: 48.9 | AF180: 48.81 | AG180: 46.2 | AH180: 39.99 | AI180: 37.41 | AJ180: 36.33 | AK180: 36.54 | AL180: 37.74 | AM180: 40.68 | AN180: 46.01 | AO180: 48.35 | AP180: 48.51 | AQ180: 48.35 | AR180: 45.67 | AS180: 43.17 | AT180: 38.83 | AU180: 38.28 | AV180: 37.98 | AW180: 38.07 | AX180: 38.07 | AY180: 39.81 | BA180: #N/A | BB180: #N/A
A181: =+A176+7 -> 44075 | B181: 20200901 | C181: 44075 | D181: 29.11 | E181: 36.7 | F181: 40.63 | G181: 42.53 | H181: 42.99 | I181: 40.36 | J181: 36.85 | K181: 34.63 | L181: 32.76 | M181: 32.88 | N181: 33.04 | O181: 34.9 | P181: 39.19 | Q181: 42.05 | R181: 44.56 | S181: 48.27 | T181: 48.09 | U181: 44.04 | V181: 39.2 | W181: 36.68 | X181: 35.99 | Y181: 35.17 | Z181: 35.72 | AA181: 36.81 | AB181: 40.62 | AC181: 44.12 | AD181: 46.76 | AE181: 48.42 | AF181: 48.33 | AG181: 45.72 | AH181: 39.51 | AI181: 36.93 | AJ181: 35.85 | AK181: 36.06 | AL181: 37.26 | AM181: 40.2 | AN181: 45.53 | AO181: 47.87 | AP181: 48.03 | AQ181: 47.87 | AR181: 45.19 | AS181: 42.69 | AT181: 38.35 | AU181: 37.8 | AV181: 37.5 | AW181: 37.59 | AX181: 37.59 | AY181: 39.33 | BA181: 45.72 | BB181: 1.345
A182: =+A177+7 -> 44076 | B182: 20200902 | C182: 44076 | D182: 28.5 | E182: 35.91 | F182: 39.94 | G182: 41.78 | H182: 42.33 | I182: 39.64 | J182: 36.02 | K182: 33.76 | L182: 31.85 | M182: 32.02 | N182: 32.26 | O182: 34.16 | P182: 38.52 | Q182: 41.47 | R182: 43.98 | S182: 47.69 | T182: 47.51 | U182: 43.52 | V182: 38.79 | W182: 36.39 | X182: 35.7 | Y182: 34.88 | Z182: 35.43 | AA182: 36.43 | AB182: 40.16 | AC182: 43.58 | AD182: 46.22 | AE182: 47.88 | AF182: 47.79 | AG182: 45.18 | AH182: 38.97 | AI182: 36.39 | AJ182: 35.31 | AK182: 35.52 | AL182: 36.72 | AM182: 39.66 | AN182: 44.99 | AO182: 47.33 | AP182: 47.49 | AQ182: 47.33 | AR182: 44.65 | AS182: 42.15 | AT182: 37.81 | AU182: 37.26 | AV182: 36.96 | AW182: 37.05 | AX182: 37.05 | AY182: 38.79 | BA182: 42.7 | BB182: 1.3303
A183: =+A178+7 -> 44077 | B183: 20200903 | C183: 44077 | D183: 30.19 | E183: 37 | F183: 40.8 | G183: 42.46 | H183: 42.76 | I183: 40.19 | J183: 36.54 | K183: 34.28 | L183: 32.37 | M183: 32.54 | N183: 32.78 | O183: 34.64 | P183: 38.94 | Q183: 41.84 | R183: 44.35 | S183: 48.06 | T183: 47.88 | U183: 43.89 | V183: 38.99 | W183: 36.59 | X183: 35.9 | Y183: 35.08 | Z183: 35.63 | AA183: 36.58 | AB183: 40.34 | AC183: 43.71 | AD183: 46.35 | AE183: 48.01 | AF183: 47.92 | AG183: 45.31 | AH183: 39.1 | AI183: 36.52 | AJ183: 35.44 | AK183: 35.65 | AL183: 36.85 | AM183: 39.83 | AN183: 45.32 | AO183: 47.7 | AP183: 47.86 | AQ183: 47.7 | AR183: 45.02 | AS183: 42.52 | AT183: 38.18 | AU183: 37.63 | AV183: 37.33 | AW183: 37.42 | AX183: 37.42 | AY183: 39.16 | BA183: 42.72 | BB183: 1.3271
A184: =+A179+7 -> 44078 | B184: 20200904 | C184: 44078 | D184: 30.31 | E184: 36.66 | F184: 40.49 | G184: 42.27 | H184: 42.56 | I184: 39.99 | J184: 36.29 | K184: 33.8 | L184: 31.89 | M184: 32.13 | N184: 32.37 | O184: 34.12 | P184: 38.32 | Q184: 41.16 | R184: 43.67 | S184: 47.38 | T184: 47.2 | U184: 43.21 | V184: 38.4 | W184: 36 | X184: 35.31 | Y184: 34.49 | Z184: 35.04 | AA184: 36.06 | AB184: 39.81 | AC184: 43.25 | AD184: 45.89 | AE184: 47.55 | AF184: 47.46 | AG184: 44.85 | AH184: 38.8 | AI184: 36.22 | AJ184: 35.14 | AK184: 35.35 | AL184: 36.55 | AM184: 39.54 | AN184: 45.03 | AO184: 47.41 | AP184: 47.57 | AQ184: 47.41 | AR184: 44.73 | AS184: 42.23 | AT184: 37.89 | AU184: 37.34 | AV184: 37.04 | AW184: 37.13 | AX184: 37.13 | AY184: 38.87 | BA184: 41.1 | BB184: 1.3199
A185: =+A180+7 -> 44081 | B185: 20200907 | C185: 44081 | D185: 29.27 | E185: 35.29 | F185: 39.36 | G185: 40.82 | H185: 41.34 | I185: 38.69 | J185: 35.4 | K185: 33.13 | L185: 31.27 | M185: 31.38 | N185: 31.65 | O185: 33.45 | P185: 37.72 | Q185: 40.59 | R185: 43.13 | S185: 46.84 | T185: 46.66 | U185: 42.74 | V185: 37.99 | W185: 35.66 | X185: 34.97 | Y185: 34.15 | Z185: 34.7 | AA185: 35.72 | AB185: 39.53 | AC185: 43.03 | AD185: 45.71 | AE185: 47.39 | AF185: 47.32 | AG185: 44.73 | AH185: 38.7 | AI185: 36.12 | AJ185: 35.03 | AK185: 35.24 | AL185: 36.45 | AM185: 39.44 | AN185: 44.93 | AO185: 47.31 | AP185: 47.47 | AQ185: 47.31 | AR185: 44.63 | AS185: 42.13 | AT185: 37.78 | AU185: 37.24 | AV185: 36.94 | AW185: 37.03 | AX185: 37.03 | AY185: 38.77 | BA185: 40.67 | BB185: 1.3177
A186: =+A181+7 -> 44082 | B186: 20200908 | C186: 44082 | D186: 28.13 | E186: 34.72 | F186: 38.81 | G186: 40.21 | H186: 40.74 | I186: 38.05 | J186: 34.59 | K186: 32.45 | L186: 30.5 | M186: 30.64 | N186: 31.04 | O186: 32.84 | P186: 37.03 | Q186: 39.85 | R186: 42.37 | S186: 46.06 | T186: 45.86 | U186: 41.94 | V186: 37.19 | W186: 34.86 | X186: 34.17 | Y186: 33.35 | Z186: 33.9 | AA186: 34.92 | AB186: 38.73 | AC186: 42.23 | AD186: 44.91 | AE186: 46.59 | AF186: 46.52 | AG186: 43.93 | AH186: 37.9 | AI186: 35.32 | AJ186: 34.23 | AK186: 34.44 | AL186: 35.65 | AM186: 38.64 | AN186: 44 | AO186: 46.38 | AP186: 46.54 | AQ186: 46.38 | AR186: 43.7 | AS186: 41.2 | AT186: 36.85 | AU186: 36.31 | AV186: 36.01 | AW186: 36.1 | AX186: 36.1 | AY186: 37.83 | BA186: 38.53 | BB186: 1.3023
A187: =+A182+7 -> 44083 | B187: 20200909 | C187: 44083 | D187: 28.03 | E187: 34.64 | F187: 38.64 | G187: 40.11 | H187: 40.65 | I187: 38.09 | J187: 34.62 | K187: 32.48 | L187: 30.41 | M187: 30.55 | N187: 30.95 | O187: 32.75 | P187: 37.09 | Q187: 40.01 | R187: 42.53 | S187: 46.22 | T187: 46.02 | U187: 42.1 | V187: 37.35 | W187: 35.02 | X187: 34.33 | Y187: 33.51 | Z187: 34.06 | AA187: 35.08 | AB187: 38.84 | AC187: 42.32 | AD187: 45 | AE187: 46.68 | AF187: 46.61 | AG187: 44.02 | AH187: 37.99 | AI187: 35.41 | AJ187: 34.32 | AK187: 34.53 | AL187: 35.74 | AM187: 38.73 | AN187: 44.09 | AO187: 46.47 | AP187: 46.63 | AQ187: 46.47 | AR187: 43.79 | AS187: 41.29 | AT187: 36.94 | AU187: 36.4 | AV187: 36.1 | AW187: 36.19 | AX187: 36.19 | AY187: 38.01 | BA187: 39.98 | BB187: 1.2996
A188: =+A183+7 -> 44084 | B188: 20200910 | C188: 44084 | D188: 27.7 | E188: 34.76 | F188: 38.81 | G188: 40.7 | H188: 40.75 | I188: 38.35 | J188: 35.04 | K188: 32.94 | L188: 30.87 | M188: 31.01 | N188: 31.41 | O188: 33.18 | P188: 37.38 | Q188: 40.16 | R188: 42.68 | S188: 46.37 | T188: 46.17 | U188: 42.25 | V188: 37.5 | W188: 35.17 | X188: 34.48 | Y188: 33.66 | Z188: 34.21 | AA188: 35.3 | AB188: 39.16 | AC188: 42.7 | AD188: 45.38 | AE188: 47.06 | AF188: 46.99 | AG188: 44.4 | AH188: 38.37 | AI188: 35.79 | AJ188: 34.7 | AK188: 34.91 | AL188: 36.12 | AM188: 39.11 | AN188: 44.47 | AO188: 46.85 | AP188: 47.01 | AQ188: 46.85 | AR188: 44.17 | AS188: 41.67 | AT188: 37.32 | AU188: 36.78 | AV188: 36.48 | AW188: 36.57 | AX188: 36.57 | AY188: 38.37 | BA188: 39.27 | BB188: 1.2867
A189: =+A184+7 -> 44085 | B189: 20200911 | C189: 44085 | D189: 27.78 | E189: 35.07 | F189: 39.01 | G189: 40.88 | H189: 41.08 | I189: 38.48 | J189: 35.29 | K189: 33.26 | L189: 31.19 | M189: 31.33 | N189: 31.73 | O189: 33.5 | P189: 37.7 | Q189: 40.48 | R189: 43 | S189: 46.69 | T189: 46.49 | U189: 42.57 | V189: 37.71 | W189: 35.29 | X189: 34.6 | Y189: 33.78 | Z189: 34.33 | AA189: 35.42 | AB189: 39.28 | AC189: 42.82 | AD189: 45.5 | AE189: 47.18 | AF189: 47.11 | AG189: 44.52 | AH189: 38.49 | AI189: 35.91 | AJ189: 34.82 | AK189: 35.03 | AL189: 36.23 | AM189: 39.22 | AN189: 44.58 | AO189: 46.96 | AP189: 47.12 | AQ189: 46.96 | AR189: 44.28 | AS189: 41.78 | AT189: 37.38 | AU189: 36.79 | AV189: 36.45 | AW189: 36.5 | AX189: 36.43 | AY189: 38.15 | BA189: 38.8 | BB189: 1.2782
A190: =+A185+7 -> 44088 | B190: 20200914 | C190: 44088 | D190: 28.38 | E190: 35.63 | F190: 39.47 | G190: 41.53 | H190: 41.83 | I190: 39.2 | J190: 35.9 | K190: 33.76 | L190: 31.69 | M190: 31.83 | N190: 32.23 | O190: 34 | P190: 38.2 | Q190: 40.98 | R190: 43.5 | S190: 47.19 | T190: 46.99 | U190: 43.07 | V190: 38.24 | W190: 35.82 | X190: 35.13 | Y190: 34.31 | Z190: 34.86 | AA190: 35.95 | AB190: 39.91 | AC190: 43.45 | AD190: 46.13 | AE190: 47.81 | AF190: 47.74 | AG190: 45.15 | AH190: 39.12 | AI190: 36.54 | AJ190: 35.45 | AK190: 35.66 | AL190: 36.86 | AM190: 39.85 | AN190: 45.21 | AO190: 47.59 | AP190: 47.75 | AQ190: 47.59 | AR190: 44.91 | AS190: 42.41 | AT190: 38.01 | AU190: 37.42 | AV190: 37.08 | AW190: 37.13 | AX190: 37.06 | AY190: 38.78 | BA190: 38.57 | BB190: 1.2883
A191: =+A186+7 -> 44089 | B191: 20200915 | C191: 44089 | D191: 28.97 | E191: 35.91 | F191: 39.78 | G191: 41.78 | H191: 41.98 | I191: 39.37 | J191: 36.12 | K191: 34 | L191: 31.89 | M191: 31.89 | N191: 32.24 | O191: 34.01 | P191: 38.19 | Q191: 40.97 | R191: 43.5 | S191: 47.17 | T191: 46.97 | U191: 43.07 | V191: 38.26 | W191: 35.92 | X191: 35.23 | Y191: 34.48 | Z191: 35.03 | AA191: 36.16 | AB191: 40.14 | AC191: 43.68 | AD191: 46.36 | AE191: 48.04 | AF191: 47.97 | AG191: 45.38 | AH191: 39.35 | AI191: 36.77 | AJ191: 35.68 | AK191: 35.89 | AL191: 37.09 | AM191: 40.08 | AN191: 45.44 | AO191: 47.82 | AP191: 47.98 | AQ191: 47.82 | AR191: 45.14 | AS191: 42.64 | AT191: 38.24 | AU191: 37.65 | AV191: 37.31 | AW191: 37.36 | AX191: 37.29 | AY191: 38.97 | BA191: 39.54 | BB191: 1.2854
A192: =+A187+7 -> 44090 | B192: 20200916 | C192: 44090 | D192: 29.74 | E192: 36.31 | F192: 39.82 | G192: 41.94 | H192: 42.11 | I192: 39.54 | J192: 36.37 | K192: 34.25 | L192: 32.14 | M192: 32.14 | N192: 32.49 | O192: 34.3 | P192: 38.49 | Q192: 41.31 | R192: 43.84 | S192: 47.52 | T192: 47.33 | U192: 43.43 | V192: 38.62 | W192: 36.28 | X192: 35.59 | Y192: 34.84 | Z192: 35.39 | AA192: 36.52 | AB192: 40.45 | AC192: 43.94 | AD192: 46.56 | AE192: 48.22 | AF192: 48.11 | AG192: 45.5 | AH192: 39.47 | AI192: 36.89 | AJ192: 35.8 | AK192: 36.01 | AL192: 37.21 | AM192: 40.2 | AN192: 45.55 | AO192: 47.91 | AP192: 48.07 | AQ192: 47.91 | AR192: 45.23 | AS192: 42.73 | AT192: 38.33 | AU192: 37.74 | AV192: 37.4 | AW192: 37.45 | AX192: 37.38 | AY192: 39.06 | BA192: 41.23 | BB192: 1.3006
... A263: =+A258+7 -> 44189 | B263: 20201224 | C263: 44189 | D263: 51.07 | E263: 51.77 | F263: 48.07 | G263: 43.87 | H263: 40.4 | I263: 38.85 | J263: 38.33 | K263: 38.71 | L263: 39.5 | M263: 42.92 | N263: 47.06 | O263: 49.81 | P263: 51.29 | Q263: 51.28 | R263: 47.01 | S263: 41.75 | T263: 39.05 | U263: 37.45 | V263: 36.64 | W263: 36.61 | X263: 37.18 | Y263: 41.4 | Z263: 44.32 | AA263: 46.72 | AB263: 48.06 | AC263: 47.81 | AD263: 44.97 | AE263: 39.58 | AF263: 36.45 | AG263: 34.53 | AH263: 34.3 | AI263: 35.22 | AJ263: 37.7 | AK263: 43.17 | AL263: 45.5 | AM263: 46.53 | AN263: 46.57 | AO263: 44.07 | AP263: 41.47 | AQ263: 37.03 | AR263: 35.69 | AS263: 35.16 | AT263: 35.15 | AU263: 35.21 | AV263: 36.7 | AW263: 41.87 | AX263: 44.88 | AY263: 45.99 | BA263: 50.88 | BB263: 1.3588
A264: =+A259+7 -> 44190 | B264: 20201225 | C264: 44190 | D264: #N/A | E264: #N/A | F264: #N/A | G264: #N/A | H264: #N/A | I264: #N/A | J264: #N/A | K264: #N/A | L264: #N/A | M264: #N/A | N264: #N/A | O264: #N/A | P264: #N/A | Q264: #N/A | R264: #N/A | S264: #N/A | T264: #N/A | U264: #N/A | V264: #N/A | W264: #N/A | X264: #N/A | Y264: #N/A | Z264: #N/A | AA264: #N/A | AB264: #N/A | AC264: #N/A | AD264: #N/A | AE264: #N/A | AF264: #N/A | AG264: #N/A | AH264: #N/A | AI264: #N/A | AJ264: #N/A | AK264: #N/A | AL264: #N/A | AM264: #N/A | AN264: #N/A | AO264: #N/A | AP264: #N/A | AQ264: #N/A | AR264: #N/A | AS264: #N/A | AT264: #N/A | AU264: #N/A | AV264: #N/A | AW264: #N/A | AX264: #N/A | AY264: #N/A | BA264: #N/A | BB264: #N/A
A265: =+A260+7 -> 44193 | B265: 20201228 | C265: 44193 | D265: 51.07 | E265: 51.77 | F265: 48.07 | G265: 43.87 | H265: 40.4 | I265: 38.85 | J265: 38.33 | K265: 38.71 | L265: 39.5 | M265: 42.92 | N265: 47.06 | O265: 49.81 | P265: 51.29 | Q265: 51.28 | R265: 47.01 | S265: 41.75 | T265: 39.05 | U265: 37.45 | V265: 36.64 | W265: 36.61 | X265: 37.18 | Y265: 41.4 | Z265: 44.32 | AA265: 46.72 | AB265: 48.06 | AC265: 47.81 | AD265: 44.97 | AE265: 39.58 | AF265: 36.45 | AG265: 34.53 | AH265: 34.3 | AI265: 35.22 | AJ265: 37.7 | AK265: 43.17 | AL265: 45.5 | AM265: 46.53 | AN265: 46.57 | AO265: 44.07 | AP265: 41.47 | AQ265: 37.03 | AR265: 35.69 | AS265: 35.16 | AT265: 35.15 | AU265: 35.21 | AV265: 36.7 | AW265: 41.87 | AX265: 44.88 | AY265: 45.99 | BA265: #N/A | BB265: #N/A
A266: =+A261+7 -> 44194 | B266: 20201229 | C266: 44194 | D266: 55.51 | E266: 55.68 | F266: 51.3 | G266: 46.37 | H266: 42.58 | I266: 40.91 | J266: 40.21 | K266: 40.52 | L266: 41.27 | M266: 44.74 | N266: 48.92 | O266: 51.51 | P266: 53.17 | Q266: 53.04 | R266: 48.34 | S266: 42.83 | T266: 39.66 | U266: 37.56 | V266: 36.68 | W266: 36.65 | X266: 37.22 | Y266: 41.85 | Z266: 45.15 | AA266: 47.78 | AB266: 49.12 | AC266: 48.87 | AD266: 46.03 | AE266: 40.64 | AF266: 37.39 | AG266: 35.36 | AH266: 35.13 | AI266: 36.05 | AJ266: 38.53 | AK266: 43.97 | AL266: 46.52 | AM266: 47.78 | AN266: 47.82 | AO266: 45.32 | AP266: 42.72 | AQ266: 38.28 | AR266: 36.94 | AS266: 36.41 | AT266: 36.4 | AU266: 36.46 | AV266: 37.95 | AW266: 43.12 | AX266: 46.13 | AY266: 47.24 | BA266: 50.44 | BB266: 1.3494
A267: =+A262+7 -> 44195 | B267: 20201230 | C267: 44195 | D267: 55.82 | E267: 55.88 | F267: 51.69 | G267: 46.38 | H267: 42.58 | I267: 40.96 | J267: 40.25 | K267: 40.68 | L267: 41.46 | M267: 44.66 | N267: 48.62 | O267: 51.13 | P267: 53.43 | Q267: 53.36 | R267: 48.71 | S267: 43 | T267: 39.58 | U267: 37.41 | V267: 36.5 | W267: 36.44 | X267: 36.95 | Y267: 41.54 | Z267: 44.78 | AA267: 47.41 | AB267: 48.67 | AC267: 48.5 | AD267: 45.8 | AE267: 40.61 | AF267: 37.48 | AG267: 35.47 | AH267: 35.19 | AI267: 36.06 | AJ267: 38.49 | AK267: 43.57 | AL267: 45.94 | AM267: 47.13 | AN267: 47.17 | AO267: 44.67 | AP267: 42.07 | AQ267: 37.67 | AR267: 36.33 | AS267: 35.8 | AT267: 35.79 | AU267: 35.85 | AV267: 37.34 | AW267: 42.51 | AX267: 45.52 | AY267: 46.63 | BA267: 50.74 | BB267: 1.3608
A268: =+A263+7 -> 44196 | B268: 20201231 | C268: 44196 | D268: 56.4 | E268: 52.31 | F268: 46.85 | G268: 42.85 | H268: 41.05 | I268: 40.35 | J268: 41.04 | K268: 41.9 | L268: 44.85 | M268: 48.81 | N268: 51.24 | O268: 53.3 | P268: 53.23 | Q268: 48.58 | R268: 43.32 | S268: 39.9 | T268: 37.73 | U268: 37.08 | V268: 37.02 | W268: 37.53 | X268: 41.72 | Y268: 44.96 | Z268: 47.59 | AA268: 48.85 | AB268: 48.69 | AC268: 46 | AD268: 40.38 | AE268: 37.25 | AF268: 35.24 | AG268: 34.96 | AH268: 35.83 | AI268: 38.26 | AJ268: 43.34 | AK268: 45.71 | AL268: 46.9 | AM268: 46.94 | AN268: 44.44 | AO268: 41.76 | AP268: 37.28 | AQ268: 35.94 | AR268: 35.41 | AS268: 35.4 | AT268: 35.46 | AU268: 36.95 | AV268: 42.12 | AW268: 45.13 | AX268: 46.24 | AY268: 46.84 | BA268: 51.22 | BB268: 1.3649
A269: =+A264+7 -> 44197 | B269: 20210101 | C269: 44197 | D269: #N/A | E269: #N/A | F269: #N/A | G269: #N/A | H269: #N/A | I269: #N/A | J269: #N/A | K269: #N/A | L269: #N/A | M269: #N/A | N269: #N/A | O269: #N/A | P269: #N/A | Q269: #N/A | R269: #N/A | S269: #N/A | T269: #N/A | U269: #N/A | V269: #N/A | W269: #N/A | X269: #N/A | Y269: #N/A | Z269: #N/A | AA269: #N/A | AB269: #N/A | AC269: #N/A | AD269: #N/A | AE269: #N/A | AF269: #N/A | AG269: #N/A | AH269: #N/A | AI269: #N/A | AJ269: #N/A | AK269: #N/A | AL269: #N/A | AM269: #N/A | AN269: #N/A | AO269: #N/A | AP269: #N/A | AQ269: #N/A | AR269: #N/A | AS269: #N/A | AT269: #N/A | AU269: #N/A | AV269: #N/A | AW269: #N/A | AX269: #N/A | AY269: #N/A | BA269: #N/A | BB269: #N/A
A270: =+A265+7 -> 44200 | B270: 20210104 | C270: 44200 | D270: 59.45 | E270: 54.77 | F270: 48.21 | G270: 43.8 | H270: 42.05 | I270: 41.25 | J270: 41.79 | K270: 42.72 | L270: 45.76 | M270: 49.78 | N270: 52.16 | O270: 54.19 | P270: 54.04 | Q270: 49.27 | R270: 43.79 | S270: 40.3 | T270: 38.09 | U270: 37.42 | V270: 37.36 | W270: 37.87 | X270: 42.15 | Y270: 45.39 | Z270: 48.02 | AA270: 49.28 | AB270: 49.12 | AC270: 46.43 | AD270: 40.7 | AE270: 37.5 | AF270: 35.42 | AG270: 35.08 | AH270: 35.9 | AI270: 38.24 | AJ270: 43.27 | AK270: 45.62 | AL270: 46.79 | AM270: 46.82 | AN270: 44.32 | AO270: 41.64 | AP270: 37.16 | AQ270: 35.82 | AR270: 35.29 | AS270: 35.28 | AT270: 35.34 | AU270: 36.83 | AV270: 42.02 | AW270: 45.05 | AX270: 46.18 | AY270: 46.79 | BA270: 50.37 | BB270: 1.3579
A271: =+A266+7 -> 44201 | B271: 20210105 | C271: 44201 | D271: 54.02 | E271: 50.15 | F271: 45.53 | G271: 41.74 | H271: 40.22 | I271: 39.58 | J271: 40.05 | K271: 40.81 | L271: 44.04 | M271: 48.25 | N271: 50.7 | O271: 52.72 | P271: 52.57 | Q271: 47.8 | R271: 42.43 | S271: 39.01 | T271: 36.83 | U271: 36.23 | V271: 36.19 | W271: 36.72 | X271: 40.97 | Y271: 44.19 | Z271: 46.8 | AA271: 48.06 | AB271: 47.9 | AC271: 45.19 | AD271: 39.53 | AE271: 36.34 | AF271: 34.26 | AG271: 33.92 | AH271: 34.74 | AI271: 37.08 | AJ271: 42.16 | AK271: 44.53 | AL271: 45.7 | AM271: 45.73 | AN271: 43.23 | AO271: 40.55 | AP271: 36.14 | AQ271: 34.96 | AR271: 34.51 | AS271: 34.56 | AT271: 34.65 | AU271: 36.17 | AV271: 41.42 | AW271: 44.51 | AX271: 45.72 | AY271: 46.4 | BA271: 53.16 | BB271: 1.3593
A272: =+A267+7 -> 44202 | B272: 20210106 | C272: 44202 | D272: 52.95 | E272: 49.26 | F272: 44.95 | G272: 41.32 | H272: 39.75 | I272: 39.08 | J272: 39.83 | K272: 40.59 | L272: 43.69 | M272: 47.77 | N272: 50.22 | O272: 52.24 | P272: 52.1 | Q272: 47.5 | R272: 42.3 | S272: 39.07 | T272: 36.89 | U272: 36.29 | V272: 36.25 | W272: 36.84 | X272: 41.17 | Y272: 44.45 | Z272: 47.06 | AA272: 48.32 | AB272: 48.16 | AC272: 45.2 | AD272: 39.23 | AE272: 35.7 | AF272: 33.62 | AG272: 33.28 | AH272: 34.1 | AI272: 36.65 | AJ272: 41.92 | AK272: 44.5 | AL272: 45.67 | AM272: 45.7 | AN272: 43.2 | AO272: 40.52 | AP272: 36.11 | AQ272: 34.93 | AR272: 34.48 | AS272: 34.53 | AT272: 34.62 | AU272: 36.14 | AV272: 41.39 | AW272: 44.48 | AX272: 45.69 | AY272: 46.37 | BA272: 53.8 | BB272: 1.355
A273: =+A268+7 -> 44203 | B273: 20210107 | C273: 44203 | D273: 58.08 | E273: 53.38 | F273: 47.93 | G273: 43.48 | H273: 41.98 | I273: 41.26 | J273: 41.96 | K273: 42.67 | L273: 45.91 | M273: 50.06 | N273: 52.58 | O273: 54.55 | P273: 54.36 | Q273: 49.73 | R273: 43.99 | S273: 40.32 | T273: 37.74 | U273: 36.84 | V273: 36.6 | W273: 37.12 | X273: 41.67 | Y273: 45.03 | Z273: 47.68 | AA273: 48.97 | AB273: 48.84 | AC273: 45.91 | AD273: 39.98 | AE273: 36.47 | AF273: 34.42 | AG273: 34.1 | AH273: 34.94 | AI273: 37.5 | AJ273: 42.78 | AK273: 45.37 | AL273: 46.54 | AM273: 46.57 | AN273: 44.07 | AO273: 41.39 | AP273: 36.94 | AQ273: 35.73 | AR273: 35.26 | AS273: 35.3 | AT273: 35.39 | AU273: 36.91 | AV273: 42.07 | AW273: 45.06 | AX273: 46.2 | AY273: 46.82 | BA273: 53.7 | BB273: 1.3544
A274: =+A269+7 -> 44204 | B274: 20210108 | C274: 44204 | D274: 60.69 | E274: 55.26 | F274: 48.39 | G274: 43.5 | H274: 41.95 | I274: 41.35 | J274: 42.17 | K274: 42.96 | L274: 46.08 | M274: 50.23 | N274: 52.76 | O274: 54.73 | P274: 54.54 | Q274: 49.9 | R274: 44.02 | S274: 40.2 | T274: 37.52 | U274: 37.07 | V274: 37.09 | W274: 37.73 | X274: 42.26 | Y274: 45.59 | Z274: 48.22 | AA274: 49.49 | AB274: 49.34 | AC274: 46.4 | AD274: 40.34 | AE274: 36.69 | AF274: 34.55 | AG274: 34.23 | AH274: 35.07 | AI274: 37.63 | AJ274: 42.95 | AK274: 45.56 | AL274: 46.73 | AM274: 46.72 | AN274: 44.22 | AO274: 41.54 | AP274: 37.09 | AQ274: 35.88 | AR274: 35.41 | AS274: 35.45 | AT274: 35.54 | AU274: 37.06 | AV274: 42.22 | AW274: 45.21 | AX274: 46.35 | AY274: 46.97 | BA274: 55.51 | BB274: 1.359
A275: =+A270+7 -> 44207 | B275: 20210111 | C275: 44207 | D275: 66.3 | E275: 59.32 | F275: 50.82 | G275: 44.72 | H275: 43.18 | I275: 42.58 | J275: 43.36 | K275: 44.26 | L275: 47.17 | M275: 51.51 | N275: 54.19 | O275: 56.18 | P275: 56.01 | Q275: 51.39 | R275: 45.12 | S275: 40.95 | T275: 37.92 | U275: 37.27 | V275: 37.15 | W275: 37.72 | X275: 42.33 | Y275: 45.74 | Z275: 48.44 | AA275: 49.75 | AB275: 49.63 | AC275: 46.71 | AD275: 40.51 | AE275: 36.75 | AF275: 34.54 | AG275: 34.2 | AH275: 35.03 | AI275: 37.64 | AJ275: 43.11 | AK275: 45.89 | AL275: 47.21 | AM275: 47.3 | AN275: 44.87 | AO275: 42.24 | AP275: 37.79 | AQ275: 36.58 | AR275: 36.11 | AS275: 36.15 | AT275: 36.24 | AU275: 37.76 | AV275: 42.92 | AW275: 45.91 | AX275: 47.05 | AY275: 47.67 | BA275: 54.84 | BB275: 1.3492
A276: =+A271+7 -> 44208 | B276: 20210112 | C276: 44208 | D276: 77.43 | E276: 68.06 | F276: 52.75 | G276: 46.37 | H276: 44.75 | I276: 43.55 | J276: 44.1 | K276: 44.34 | L276: 47.34 | M276: 52.93 | N276: 55.91 | O276: 57.72 | P276: 57.24 | Q276: 52.26 | R276: 45.45 | S276: 41.01 | T276: 38.1 | U276: 37.67 | V276: 37.74 | W276: 38.33 | X276: 42.98 | Y276: 46.35 | Z276: 49.02 | AA276: 50.27 | AB276: 50.09 | AC276: 47.1 | AD276: 40.84 | AE276: 37.01 | AF276: 34.73 | AG276: 34.32 | AH276: 35.08 | AI276: 37.63 | AJ276: 42.96 | AK276: 45.74 | AL276: 47.06 | AM276: 47.15 | AN276: 44.72 | AO276: 42.09 | AP276: 37.64 | AQ276: 36.43 | AR276: 35.96 | AS276: 36 | AT276: 36.09 | AU276: 37.61 | AV276: 42.77 | AW276: 45.76 | AX276: 46.9 | AY276: 47.52 | BA276: 55.98 | BB276: 1.3624
A277: =+A272+7 -> 44209 | B277: 20210113 | C277: 44209 | D277: 65.16 | E277: 57.01 | F277: 48.54 | G277: 43.23 | H277: 41.93 | I277: 41.08 | J277: 41.53 | K277: 42.92 | L277: 45 | M277: 50.45 | N277: 53.26 | O277: 54.81 | P277: 54.42 | Q277: 49.52 | R277: 43.05 | S277: 38.85 | T277: 36.18 | U277: 35.95 | V277: 36.13 | W277: 37.01 | X277: 41.65 | Y277: 45.02 | Z277: 47.69 | AA277: 48.94 | AB277: 48.85 | AC277: 46.01 | AD277: 40.03 | AE277: 36.23 | AF277: 34.01 | AG277: 33.66 | AH277: 34.48 | AI277: 37.09 | AJ277: 42.59 | AK277: 45.46 | AL277: 46.85 | AM277: 46.99 | AN277: 44.56 | AO277: 41.76 | AP277: 36.96 | AQ277: 35.75 | AR277: 35.28 | AS277: 35.32 | AT277: 35.41 | AU277: 37.01 | AV277: 42.26 | AW277: 45.25 | AX277: 46.39 | AY277: 47.01 | BA277: 55.52 | BB277: 1.3634
A278: =+A273+7 -> 44210 | B278: 20210114 | C278: 44210 | D278: 63.15 | E278: 56.35 | F278: 47.5 | G278: 43 | H278: 41.5 | I278: 40.01 | J278: 41.29 | K278: 43.62 | L278: 45.27 | M278: 50.39 | N278: 52.17 | O278: 53.94 | P278: 53.76 | Q278: 49.83 | R278: 43.73 | S278: 39.64 | T278: 37.08 | U278: 36.95 | V278: 37.17 | W278: 38 | X278: 42.58 | Y278: 45.87 | Z278: 48.46 | AA278: 49.62 | AB278: 49.47 | AC278: 46.63 | AD278: 40.65 | AE278: 36.75 | AF278: 34.46 | AG278: 34.07 | AH278: 34.89 | AI278: 37.4 | AJ278: 42.77 | AK278: 45.54 | AL278: 46.83 | AM278: 46.89 | AN278: 44.46 | AO278: 41.66 | AP278: 36.86 | AQ278: 35.65 | AR278: 35.18 | AS278: 35.22 | AT278: 35.31 | AU278: 36.91 | AV278: 42.16 | AW278: 45.15 | AX278: 46.29 | AY278: 46.91 | BA278: 55.76 | BB278: 1.3691
A279: =+A274+7 -> 44211 | B279: 20210115 | C279: 44211 | D279: 59.35 | E279: 53.45 | F279: 45.92 | G279: 41.58 | H279: 40.28 | I279: 38.96 | J279: 39.91 | K279: 42.21 | L279: 44.07 | M279: 49.27 | N279: 51.1 | O279: 52.75 | P279: 52.54 | Q279: 48.81 | R279: 42.91 | S279: 39.02 | T279: 36.62 | U279: 36.49 | V279: 36.71 | W279: 37.54 | X279: 42.01 | Y279: 45.2 | Z279: 47.73 | AA279: 48.85 | AB279: 48.7 | AC279: 45.86 | AD279: 40.13 | AE279: 36.48 | AF279: 34.29 | AG279: 34 | AH279: 34.92 | AI279: 37.53 | AJ279: 42.75 | AK279: 45.34 | AL279: 46.53 | AM279: 46.59 | AN279: 44.16 | AO279: 41.36 | AP279: 36.56 | AQ279: 35.35 | AR279: 34.88 | AS279: 34.92 | AT279: 35.01 | AU279: 36.61 | AV279: 41.86 | AW279: 44.85 | AX279: 45.99 | AY279: 46.61 | BA279: 54.8 | BB279: 1.3585
A280: =+A275+7 -> 44214 | B280: 20210118 | C280: 44214 | D280: 54.86 | E280: 50.35 | F280: 44.48 | G280: 40.66 | H280: 39.92 | I280: 38.64 | J280: 39.31 | K280: 41.51 | L280: 43.48 | M280: 48.72 | N280: 50.57 | O280: 52.28 | P280: 52.07 | Q280: 48.36 | R280: 42.41 | S280: 38.54 | T280: 36.14 | U280: 36.01 | V280: 36.27 | W280: 37.19 | X280: 41.9 | Y280: 45.21 | Z280: 47.89 | AA280: 49.01 | AB280: 48.86 | AC280: 46.02 | AD280: 40.28 | AE280: 36.55 | AF280: 34.32 | AG280: 34.03 | AH280: 34.95 | AI280: 37.56 | AJ280: 42.87 | AK280: 45.55 | AL280: 46.74 | AM280: 46.8 | AN280: 44.37 | AO280: 41.57 | AP280: 36.77 | AQ280: 35.56 | AR280: 35.09 | AS280: 35.13 | AT280: 35.22 | AU280: 36.82 | AV280: 42.07 | AW280: 45.06 | AX280: 46.2 | AY280: 46.82 | BA280: 54.21 | BB280: 1.3575
A281: =+A276+7 -> 44215 | B281: 20210119 | C281: 44215 | D281: 57.77 | E281: 53.41 | F281: 46.84 | G281: 42.97 | H281: 41.88 | I281: 40.72 | J281: 41.33 | K281: 43.49 | L281: 45.62 | M281: 50.9 | N281: 52.82 | O281: 54.71 | P281: 54.14 | Q281: 50.16 | R281: 44.09 | S281: 39.96 | T281: 37.36 | U281: 37.27 | V281: 37.54 | W281: 38.58 | X281: 43.29 | Y281: 46.61 | Z281: 49.3 | AA281: 50.24 | AB281: 50.01 | AC281: 46.94 | AD281: 41.06 | AE281: 36.88 | AF281: 34.47 | AG281: 34.18 | AH281: 35.19 | AI281: 37.94 | AJ281: 43.35 | AK281: 46.04 | AL281: 47.23 | AM281: 47.29 | AN281: 44.95 | AO281: 42.35 | AP281: 37.55 | AQ281: 36.33 | AR281: 35.86 | AS281: 35.9 | AT281: 35.99 | AU281: 37.59 | AV281: 42.61 | AW281: 45.36 | AX281: 46.37 | AY281: 46.99 | BA281: 55.38 | BB281: 1.3618
... A333: =+A328+7 -> 44287 | B333: 20210401 | C333: 44287 | D333: 47.21 | E333: 47.16 | F333: 45.93 | G333: 46.03 | H333: 47.49 | I333: 49.21 | J333: 54.38 | K333: 57.46 | L333: 58.71 | M333: 58.85 | N333: 53.56 | O333: 46.38 | P333: 42.16 | Q333: 39.44 | R333: 39.32 | S333: 39.75 | T333: 41.17 | U333: 45.37 | V333: 48.48 | W333: 51.31 | X333: 52.95 | Y333: 52.74 | Z333: 49.09 | AA333: 43.57 | AB333: 39.35 | AC333: 36.48 | AD333: 35.97 | AE333: 36.2 | AF333: 38.64 | AG333: 43.76 | AH333: 47.05 | AI333: 48.97 | AJ333: 49.87 | AK333: 48.68 | AL333: 45.39 | AM333: 39.6 | AN333: 37.12 | AO333: 35.61 | AP333: 35.3 | AQ333: 35.53 | AR333: 36.56 | AS333: 42 | AT333: 45.28 | AU333: 47.14 | AV333: 48.55 | AW333: 47.57 | AX333: 44.47 | AY333: 39.14 | BA333: 63.85 | BB333: 1.3819
A334: =+A329+7 -> 44288 | B334: 20210402 | C334: 44288 | D334: #N/A | E334: #N/A | F334: #N/A | G334: #N/A | H334: #N/A | I334: #N/A | J334: #N/A | K334: #N/A | L334: #N/A | M334: #N/A | N334: #N/A | O334: #N/A | P334: #N/A | Q334: #N/A | R334: #N/A | S334: #N/A | T334: #N/A | U334: #N/A | V334: #N/A | W334: #N/A | X334: #N/A | Y334: #N/A | Z334: #N/A | AA334: #N/A | AB334: #N/A | AC334: #N/A | AD334: #N/A | AE334: #N/A | AF334: #N/A | AG334: #N/A | AH334: #N/A | AI334: #N/A | AJ334: #N/A | AK334: #N/A | AL334: #N/A | AM334: #N/A | AN334: #N/A | AO334: #N/A | AP334: #N/A | AQ334: #N/A | AR334: #N/A | AS334: #N/A | AT334: #N/A | AU334: #N/A | AV334: #N/A | AW334: #N/A | AX334: #N/A | AY334: #N/A | BA334: #N/A | BB334: #N/A
A335: =+A330+7 -> 44291 | B335: 20210405 | C335: 44291 | D335: 47.21 | E335: 47.16 | F335: 45.93 | G335: 46.03 | H335: 47.49 | I335: 49.21 | J335: 54.38 | K335: 57.46 | L335: 58.71 | M335: 58.85 | N335: 53.56 | O335: 46.38 | P335: 42.16 | Q335: 39.44 | R335: 39.32 | S335: 39.75 | T335: 41.17 | U335: 45.37 | V335: 48.48 | W335: 51.31 | X335: 52.95 | Y335: 52.74 | Z335: 49.09 | AA335: 43.57 | AB335: 39.35 | AC335: 36.48 | AD335: 35.97 | AE335: 36.2 | AF335: 38.64 | AG335: 43.76 | AH335: 47.05 | AI335: 48.97 | AJ335: 49.87 | AK335: 48.68 | AL335: 45.39 | AM335: 39.6 | AN335: 37.12 | AO335: 35.61 | AP335: 35.3 | AQ335: 35.53 | AR335: 36.56 | AS335: 42 | AT335: 45.28 | AU335: 47.14 | AV335: 48.55 | AW335: 47.57 | AX335: 44.47 | AY335: 39.14 | BA335: #N/A | BB335: #N/A
A336: =+A331+7 -> 44292 | B336: 20210406 | C336: 44292 | D336: 48.97 | E336: 48.78 | F336: 47.56 | G336: 47.58 | H336: 48.88 | I336: 50.8 | J336: 56.12 | K336: 58.84 | L336: 60.07 | M336: 60.19 | N336: 55.15 | O336: 46.65 | P336: 42.56 | Q336: 39.97 | R336: 39.96 | S336: 40.45 | T336: 41.9 | U336: 46.05 | V336: 49.11 | W336: 51.9 | X336: 53.5 | Y336: 53.28 | Z336: 49.64 | AA336: 44.13 | AB336: 39.91 | AC336: 37.04 | AD336: 36.53 | AE336: 36.76 | AF336: 39.2 | AG336: 44.32 | AH336: 47.61 | AI336: 49.53 | AJ336: 50.43 | AK336: 49.24 | AL336: 45.95 | AM336: 40.16 | AN336: 37.68 | AO336: 36.17 | AP336: 35.86 | AQ336: 36.09 | AR336: 37.12 | AS336: 42.56 | AT336: 45.84 | AU336: 47.7 | AV336: 49.11 | AW336: 48.13 | AX336: 45.03 | AY336: 39.7 | BA336: 61.47 | BB336: 1.3858
...

Sheet HAVERM
A1: 199901 !M | B1: K5BZ@UK | C1: KAB9@UK | D1: K5C3@UK | E1: KAC3@UK | F1: sa(D7F5@UK) | G1: D7F5@UK | H1: PUNFPI@CMDTY | I1: UNAUSS@UK | J1: D7BU@UK | K1: GBA6@UK | L1: UNVDPE3@UK | M1: UNVDNPM@UK | N1: UNVDNHP@UK | O1: UNVDNNE@UK | P1: UNVDNEW@UK | Q1: UNVDNO@UK | R1: UNVDNOA@UK
A2: .DESC | B2: Great Britain: AWE, Total Pay: Services (SA, GBP) | C2: Great Britain: AWE, Total Pay: Whole Economy (SA, GBP) | D2: Great Britain: AWE, Total Pay: Services [3Mo Mvg Avg vs Yr Ago] (SA, %) | E2: Great Britain: AWE: Total Pay: Whole Economy [3Mo Mvg Avg vs Yr Ago] (SA, %) | F2: UK: Consumer Price Index: All Services (NSA, 2015=100) - Seasonal Adjustment, All | G2: UK: Consumer Price Index: All Services (NSA, 2015=100) | H2: Food and Agriculture Organization of the UN: Food Price Index (2014-16=100) | I2: UK: Exchange Rate: United States, Average (US$/GBP) | J2: UK: Consumer Price Index: Food & Non-Alcoholic Beverages (NSA, 2015=100) | K2: UK: PPI: Gross Sector Output: Food, Beverages & Tobacco Excl Duty(NSA, 2015=100) | L2: UK: BoE DMP: Expected Price Growth Over the Next Year: 3 Month Average (%) | M2: UK: BoE DMP: Reaction to Chg in NICs After Nov24 Budget: Lower Profit Margins(%) | N2: UK: BoE DMP: Reaction to Change in NICs After Nov24 Budget: Higher Prices (%) | O2: UK: BoE DMP: Reaction to Change in NICs After Nov24 Budget: Less Employees (%) | P2: UK: BoE DMP: Reaction to Chg in NICs After Nov24 Budget: Lower Employee Wages(%) | Q2: UK: BoE DMP: Reaction to Change in NICs After Nov24 Budget: Other (%) | R2: UK: BoE DMP: Reaction to Change in NICs After Nov24 Budget: None of the Above(%)
A3: .T1 | B3: Jan-2000 | C3: Jan-2000 | D3: Mar-2001 | E3: Mar-2001 | F3: Jan-1988 | G3: Jan-1988 | H3: Jan-1990 | I3: Jan-1921 | J3: Jan-1988 | K3: Jan-1996 | L3: Jan-2017 | M3: Nov-2024 | N3: Nov-2024 | O3: Nov-2024 | P3: Nov-2024 | Q3: Nov-2024 | R3: Nov-2024
A4: .TN | B4: Dec-2024 | C4: Dec-2024 | D4: Dec-2024 | E4: Dec-2024 | F4: Jan-2025 | G4: Jan-2025 | H4: Jan-2025 | I4: Feb-2025 | J4: Jan-2025 | K4: Jan-2025 | L4: Feb-2025 | M4: Jan-2025 | N4: Jan-2025 | O4: Jan-2025 | P4: Jan-2025 | Q4: Jan-2025 | R4: Jan-2025
A5: .LSOURCE | B5: Office for National Statistics | C5: Office for National Statistics | D5: Office for National Statistics | E5: Office for National Statistics | F5: Office for National Statistics | G5: Office for National Statistics | H5: Food and Agriculture Organization of the UN | I5: Bank of England | J5: Office for National Statistics | K5: Office for National Statistics | L5: Bank of England | M5: Bank of England | N5: Bank of England | O5: Bank of England | P5: Bank of England | Q5: Bank of England | R5: Bank of England
A6: .DTLM | B6: Feb-18-2025 07:06 | C6: Feb-18-2025 07:06 | D6: Feb-18-2025 07:06 | E6: Feb-18-2025 07:06 | F6: Feb-19-2025 07:02 | G6: Feb-19-2025 07:02 | H6: Feb-07-2025 11:28 | I6: Mar-03-2025 11:29 | J6: Feb-19-2025 07:02 | K6: Feb-19-2025 07:06 | L6: Mar-06-2025 09:31 | M6: Feb-06-2025 14:01 | N6: Feb-06-2025 14:01 | O6: Feb-06-2025 14:01 | P6: Feb-06-2025 14:01 | Q6: Feb-06-2025 14:01 | R6: Feb-06-2025 14:01
A7: 199901 | B7: #N/A | C7: #N/A | D7: #N/A | E7: #N/A | F7: 56.679939 | G7: 56.6 | H7: 61.2 | I7: 1.6509 | J7: 67.3 | K7: 69.5 | L7: #N/A | M7: #N/A | N7: #N/A | O7: #N/A | P7: #N/A | Q7: #N/A | R7: #N/A
A8: 199902 | B8: #N/A | C8: #N/A | D8: #N/A | E8: #N/A | F8: 56.870492 | G8: 56.7 | H8: 58.6 | I8: 1.6276 | J8: 67.4 | K8: 69.8 | L8: #N/A | M8: #N/A | N8: #N/A | O8: #N/A | P8: #N/A | Q8: #N/A | R8: #N/A
A9: 199903 | B9: #N/A | C9: #N/A | D9: #N/A | E9: #N/A | F9: 56.976867 | G9: 56.7 | H9: 57.2 | I9: 1.622 | J9: 67 | K9: 70.1 | L9: #N/A | M9: #N/A | N9: #N/A | O9: #N/A | P9: #N/A | Q9: #N/A | R9: #N/A
A10: 199904 | B10: #N/A | C10: #N/A | D10: #N/A | E10: #N/A | F10: 57.179409 | G10: 57.3 | H10: 56 | I10: 1.6105 | J10: 66.6 | K10: 70 | L10: #N/A | M10: #N/A | N10: #N/A | O10: #N/A | P10: #N/A | Q10: #N/A | R10: #N/A
A11: 199905 | B11: #N/A | C11: #N/A | D11: #N/A | E11: #N/A | F11: 57.302793 | G11: 57.4 | H11: 55.6 | I11: 1.6154 | J11: 67 | K11: 70 | L11: #N/A | M11: #N/A | N11: #N/A | O11: #N/A | P11: #N/A | Q11: #N/A | R11: #N/A
A12: 199906 | B12: #N/A | C12: #N/A | D12: #N/A | E12: #N/A | F12: 57.418938 | G12: 57.5 | H12: 54.8 | I12: 1.595 | J12: 66.6 | K12: 69.9 | L12: #N/A | M12: #N/A | N12: #N/A | O12: #N/A | P12: #N/A | Q12: #N/A | R12: #N/A
A13: 199907 | B13: #N/A | C13: #N/A | D13: #N/A | E13: #N/A | F13: 57.579925 | G13: 57.7 | H13: 52.8 | I13: 1.5747 | J13: 66 | K13: 70.1 | L13: #N/A | M13: #N/A | N13: #N/A | O13: #N/A | P13: #N/A | Q13: #N/A | R13: #N/A
A14: 199908 | B14: #N/A | C14: #N/A | D14: #N/A | E14: #N/A | F14: 57.708304 | G14: 57.8 | H14: 54.6 | I14: 1.6073 | J14: 65.9 | K14: 70 | L14: #N/A | M14: #N/A | N14: #N/A | O14: #N/A | P14: #N/A | Q14: #N/A | R14: #N/A
A15: 199909 | B15: #N/A | C15: #N/A | D15: #N/A | E15: #N/A | F15: 57.896085 | G15: 58 | H15: 54.8 | I15: 1.6243 | J15: 65.8 | K15: 69.8 | L15: #N/A | M15: #N/A | N15: #N/A | O15: #N/A | P15: #N/A | Q15: #N/A | R15: #N/A
A16: 199910 | B16: #N/A | C16: #N/A | D16: #N/A | E16: #N/A | F16: 58.088969 | G16: 58.2 | H16: 53.5 | I16: 1.6572 | J16: 65.7 | K16: 69.6 | L16: #N/A | M16: #N/A | N16: #N/A | O16: #N/A | P16: #N/A | Q16: #N/A | R16: #N/A
A17: 199911 | B17: #N/A | C17: #N/A | D17: #N/A | E17: #N/A | F17: 58.272428 | G17: 58.2 | H17: 53.5 | I17: 1.6214 | J17: 65.9 | K17: 69.2 | L17: #N/A | M17: #N/A | N17: #N/A | O17: #N/A | P17: #N/A | Q17: #N/A | R17: #N/A
A18: 199912 | B18: #N/A | C18: #N/A | D18: #N/A | E18: #N/A | F18: 58.401385 | G18: 58.3 | H18: 52.1 | I18: 1.6132 | J18: 66 | K18: 69.1 | L18: #N/A | M18: #N/A | N18: #N/A | O18: #N/A | P18: #N/A | Q18: #N/A | R18: #N/A
A19: 200001 | B19: 290 | C19: 305 | D19: #N/A | E19: #N/A | F19: 58.589632 | G19: 58.5 | H19: 52.8 | I19: 1.6402 | J19: 66 | K19: 69.3 | L19: #N/A | M19: #N/A | N19: #N/A | O19: #N/A | P19: #N/A | Q19: #N/A | R19: #N/A
A20: 200002 | B20: 283 | C20: 300 | D20: #N/A | E20: #N/A | F20: 58.792068 | G20: 58.6 | H20: 52.5 | I20: 1.5998 | J20: 65.9 | K20: 69.3 | L20: #N/A | M20: #N/A | N20: #N/A | O20: #N/A | P20: #N/A | Q20: #N/A | R20: #N/A
A21: 200003 | B21: 297 | C21: 311 | D21: #N/A | E21: #N/A | F21: 59.003408 | G21: 58.7 | H21: 53.1 | I21: 1.5802 | J21: 65.4 | K21: 69.4 | L21: #N/A | M21: #N/A | N21: #N/A | O21: #N/A | P21: #N/A | Q21: #N/A | R21: #N/A
A22: 200004 | B22: 291 | C22: 309 | D22: #N/A | E22: #N/A | F22: 58.781237 | G22: 58.9 | H22: 53.7 | I22: 1.5837 | J22: 65.2 | K22: 69.4 | L22: #N/A | M22: #N/A | N22: #N/A | O22: #N/A | P22: #N/A | Q22: #N/A | R22: #N/A
A23: 200005 | B23: 296 | C23: 311 | D23: #N/A | E23: #N/A | F23: 59.000569 | G23: 59.1 | H23: 54 | I23: 1.5075 | J23: 65.9 | K23: 69.6 | L23: #N/A | M23: #N/A | N23: #N/A | O23: #N/A | P23: #N/A | Q23: #N/A | R23: #N/A
A24: 200006 | B24: 295 | C24: 311 | D24: #N/A | E24: #N/A | F24: 59.219397 | G24: 59.3 | H24: 54.2 | I24: 1.5089 | J24: 66.1 | K24: 69.6 | L24: #N/A | M24: #N/A | N24: #N/A | O24: #N/A | P24: #N/A | Q24: #N/A | R24: #N/A
A25: 200007 | B25: 298 | C25: 313 | D25: #N/A | E25: #N/A | F25: 59.34379 | G25: 59.5 | H25: 54.4 | I25: 1.5088 | J25: 66.6 | K25: 69.6 | L25: #N/A | M25: #N/A | N25: #N/A | O25: #N/A | P25: #N/A | Q25: #N/A | R25: #N/A
A26: 200008 | B26: 300 | C26: 315 | D26: #N/A | E26: #N/A | F26: 59.579376 | G26: 59.7 | H26: 53.5 | I26: 1.491 | J26: 66.1 | K26: 69.3 | L26: #N/A | M26: #N/A | N26: #N/A | O26: #N/A | P26: #N/A | Q26: #N/A | R26: #N/A
A27: 200009 | B27: 302 | C27: 317 | D27: #N/A | E27: #N/A | F27: 59.895035 | G27: 60 | H27: 52.9 | I27: 1.4355 | J27: 66.3 | K27: 69.4 | L27: #N/A | M27: #N/A | N27: #N/A | O27: #N/A | P27: #N/A | Q27: #N/A | R27: #N/A
A28: 200010 | B28: 302 | C28: 318 | D28: #N/A | E28: #N/A | F28: 60.091084 | G28: 60.2 | H28: 53.7 | I28: 1.4511 | J28: 66.3 | K28: 69.4 | L28: #N/A | M28: #N/A | N28: #N/A | O28: #N/A | P28: #N/A | Q28: #N/A | R28: #N/A
A29: 200011 | B29: 304 | C29: 320 | D29: #N/A | E29: #N/A | F29: 60.304473 | G29: 60.2 | H29: 54.2 | I29: 1.4256 | J29: 66.7 | K29: 69.5 | L29: #N/A | M29: #N/A | N29: #N/A | O29: #N/A | P29: #N/A | Q29: #N/A | R29: #N/A
A30: 200012 | B30: 310 | C30: 323 | D30: #N/A | E30: #N/A | F30: 60.380855 | G30: 60.3 | H30: 54.8 | I30: 1.4625 | J30: 66.8 | K30: 69.7 | L30: #N/A | M30: #N/A | N30: #N/A | O30: #N/A | P30: #N/A | Q30: #N/A | R30: #N/A
... A32: 200102 | B32: 310 | C32: 325 | D32: #N/A | E32: #N/A | F32: 60.712551 | G32: 60.5 | H32: 54.6 | I32: 1.4529 | J32: 67.1 | K32: 70 | L32: #N/A | M32: #N/A | N32: #N/A | O32: #N/A | P32: #N/A | Q32: #N/A | R32: #N/A
A33: 200103 | B33: 311 | C33: 326 | D33: 6.9 | E33: 6.1 | F33: 60.917522 | G33: 60.6 | H33: 55.5 | I33: 1.4454 | J33: 67.9 | K33: 70.5 | L33: #N/A | M33: #N/A | N33: #N/A | O33: #N/A | P33: #N/A | Q33: #N/A | R33: #N/A
A34: 200104 | B34: 312 | C34: 326 | D34: 7.1 | E34: 6.2 | F34: 61.285092 | G34: 61.4 | H34: 55 | I34: 1.435 | J34: 68.1 | K34: 70.6 | L34: #N/A | M34: #N/A | N34: #N/A | O34: #N/A | P34: #N/A | Q34: #N/A | R34: #N/A
A35: 200105 | B35: 311 | C35: 327 | D35: 5.7 | E35: 5.1 | F35: 61.603586 | G35: 61.7 | H35: 55.8 | I35: 1.4259 | J35: 70 | K35: 71 | L35: #N/A | M35: #N/A | N35: #N/A | O35: #N/A | P35: #N/A | Q35: #N/A | R35: #N/A
A36: 200106 | B36: 313 | C36: 328 | D36: 6.2 | E36: 5.5 | F36: 61.711169 | G36: 61.8 | H36: 55.2 | I36: 1.4014 | J36: 70.4 | K36: 70.8 | L36: #N/A | M36: #N/A | N36: #N/A | O36: #N/A | P36: #N/A | Q36: #N/A | R36: #N/A
A37: 200107 | B37: 313 | C37: 328 | D37: 5.5 | E37: 5.2 | F37: 61.996588 | G37: 62.2 | H37: 56.9 | I37: 1.4139 | J37: 69 | K37: 70.8 | L37: #N/A | M37: #N/A | N37: #N/A | O37: #N/A | P37: #N/A | Q37: #N/A | R37: #N/A
A38: 200108 | B38: 315 | C38: 331 | D38: 5.4 | E38: 5.3 | F38: 62.332026 | G38: 62.5 | H38: 57 | I38: 1.4365 | J38: 68.8 | K38: 70.8 | L38: #N/A | M38: #N/A | N38: #N/A | O38: #N/A | P38: #N/A | Q38: #N/A | R38: #N/A
A39: 200109 | B39: 315 | C39: 331 | D39: 4.8 | E39: 4.8 | F39: 62.31114 | G39: 62.4 | H39: 55.8 | I39: 1.4635 | J39: 68.7 | K39: 71 | L39: #N/A | M39: #N/A | N39: #N/A | O39: #N/A | P39: #N/A | Q39: #N/A | R39: #N/A
A40: 200110 | B40: 317 | C40: 333 | D40: 4.7 | E40: 4.8 | F40: 62.409867 | G40: 62.5 | H40: 54.5 | I40: 1.4517 | J40: 68.8 | K40: 71.1 | L40: #N/A | M40: #N/A | N40: #N/A | O40: #N/A | P40: #N/A | Q40: #N/A | R40: #N/A
A41: 200111 | B41: 318 | C41: 334 | D41: 4.6 | E41: 4.6 | F41: 62.540701 | G41: 62.4 | H41: 55.1 | I41: 1.4358 | J41: 68.7 | K41: 71.3 | L41: #N/A | M41: #N/A | N41: #N/A | O41: #N/A | P41: #N/A | Q41: #N/A | R41: #N/A
A42: 200112 | B42: 320 | C42: 334 | D42: 4.3 | E42: 4.2 | F42: 62.748321 | G42: 62.7 | H42: 54.6 | I42: 1.4409 | J42: 69.1 | K42: 71.5 | L42: #N/A | M42: #N/A | N42: #N/A | O42: #N/A | P42: #N/A | Q42: #N/A | R42: #N/A
A43: 200201 | B43: 321 | C43: 333 | D43: 4 | E43: 3.8 | F43: 63.02793 | G43: 62.9 | H43: 53.8 | I43: 1.4323 | J43: 69.7 | K43: 71.7 | L43: #N/A | M43: #N/A | N43: #N/A | O43: #N/A | P43: #N/A | Q43: #N/A | R43: #N/A
A44: 200202 | B44: 319 | C44: 334 | D44: 3.4 | E44: 3.2 | F44: 63.232449 | G44: 63 | H44: 52 | I44: 1.4231 | J44: 69.6 | K44: 71.7 | L44: #N/A | M44: #N/A | N44: #N/A | O44: #N/A | P44: #N/A | Q44: #N/A | R44: #N/A
... A222: 201612 | B222: 480 | C222: 496 | D222: 2.3 | E222: 2.5 | F222: 103.88398 | G222: 104 | H222: 95.3 | I222: 1.2488 | J222: 97.9 | K222: 99.7 | L222: #N/A | M222: #N/A | N222: #N/A | O222: #N/A | P222: #N/A | Q222: #N/A | R222: #N/A
A223: 201701 | B223: 482 | C223: 497 | D223: 2 | E223: 2.1 | F223: 103.86895 | G223: 103.3 | H223: 97.8 | I223: 1.2351 | J223: 98.1 | K223: 99.9 | L223: 2.992 | M223: #N/A | N223: #N/A | O223: #N/A | P223: #N/A | Q223: #N/A | R223: #N/A
A224: 201702 | B224: 484 | C224: 499 | D224: 2 | E224: 2.1 | F224: 104.33702 | G224: 103.9 | H224: 98.1 | I224: 1.249 | J224: 98.9 | K224: 100.3 | L224: 2.863 | M224: #N/A | N224: #N/A | O224: #N/A | P224: #N/A | Q224: #N/A | R224: #N/A
A225: 201703 | B225: 487 | C225: 501 | D225: 2.3 | E225: 2.3 | F225: 104.29704 | G225: 103.8 | H225: 96.2 | I225: 1.2348 | J225: 99.3 | K225: 101.2 | L225: 2.82 | M225: #N/A | N225: #N/A | O225: #N/A | P225: #N/A | Q225: #N/A | R225: #N/A
A226: 201704 | B226: 487 | C226: 502 | D226: 2.4 | E226: 2.2 | F226: 104.89087 | G226: 105 | H226: 95 | I226: 1.2652 | J226: 99.5 | K226: 101.4 | L226: 2.766 | M226: #N/A | N226: #N/A | O226: #N/A | P226: #N/A | Q226: #N/A | R226: #N/A
A227: 201705 | B227: 489 | C227: 503 | D227: 2.2 | E227: 1.9 | F227: 105.06057 | G227: 105.1 | H227: 97.3 | I227: 1.2933 | J227: 99.6 | K227: 102.3 | L227: 2.681 | M227: #N/A | N227: #N/A | O227: #N/A | P227: #N/A | Q227: #N/A | R227: #N/A
A228: 201706 | B228: 493 | C228: 508 | D228: 2.5 | E228: 2.2 | F228: 105.32895 | G228: 105.5 | H228: 97.8 | I228: 1.2813 | J228: 99.4 | K228: 102.4 | L228: 2.615 | M228: #N/A | N228: #N/A | O228: #N/A | P228: #N/A | Q228: #N/A | R228: #N/A
A229: 201707 | B229: 489 | C229: 504 | D229: 2.4 | E229: 2.2 | F229: 105.46332 | G229: 106 | H229: 100 | I229: 1.2994 | J229: 99.4 | K229: 102.8 | L229: 2.468 | M229: #N/A | N229: #N/A | O229: #N/A | P229: #N/A | Q229: #N/A | R229: #N/A
A230: 201708 | B230: 491 | C230: 507 | D230: 2.5 | E230: 2.4 | F230: 105.69424 | G230: 106.5 | H230: 99.2 | I230: 1.2955 | J230: 99.4 | K230: 103.3 | L230: 2.467 | M230: #N/A | N230: #N/A | O230: #N/A | P230: #N/A | Q230: #N/A | R230: #N/A
A231: 201709 | B231: 493 | C231: 509 | D231: 2.3 | E231: 2.3 | F231: 105.93057 | G231: 106.1 | H231: 99.7 | I231: 1.3324 | J231: 100.2 | K231: 103.9 | L231: 2.527 | M231: #N/A | N231: #N/A | O231: #N/A | P231: #N/A | Q231: #N/A | R231: #N/A
A232: 201710 | B232: 492 | C232: 509 | D232: 2.6 | E232: 2.6 | F232: 106.00045 | G232: 105.9 | H232: 98.8 | I232: 1.3197 | J232: 100.6 | K232: 104.2 | L232: 2.444 | M232: #N/A | N232: #N/A | O232: #N/A | P232: #N/A | Q232: #N/A | R232: #N/A
A233: 201711 | B233: 494 | C233: 510 | D233: 2.5 | E233: 2.5 | F233: 106.22933 | G233: 105.9 | H233: 98.8 | I233: 1.3219 | J233: 101.1 | K233: 104.4 | L233: 2.423 | M233: #N/A | N233: #N/A | O233: #N/A | P233: #N/A | Q233: #N/A | R233: #N/A
A234: 201712 | B234: 496 | C234: 512 | D234: 2.6 | E234: 2.6 | F234: 106.52174 | G234: 106.6 | H234: 96.4 | I234: 1.3402 | J234: 101.8 | K234: 105.1 | L234: 2.471 | M234: #N/A | N234: #N/A | O234: #N/A | P234: #N/A | Q234: #N/A | R234: #N/A
... A316: 202410 | B316: 692 | C316: 708 | D316: 5.1 | E316: 5.3 | F316: 138.12689 | G316: 138.5 | H316: 126.9 | I316: 1.3045 | J316: 136.5 | K316: 134.8 | L316: 3.511 | M316: #N/A | N316: #N/A | O316: #N/A | P316: #N/A | Q316: #N/A | R316: #N/A
A317: 202411 | B317: 693 | C317: 705 | D317: 5.4 | E317: 5.5 | F317: 138.5593 | G317: 138.3 | H317: 127.7 | I317: 1.275 | J317: 137.1 | K317: 135.5 | L317: 3.666 | M317: 59 | N317: 54 | O317: 54 | P317: 38 | Q317: 8 | R317: 3
A318: 202412 | B318: 699 | C318: 710 | D318: 6.1 | E318: 6 | F318: 138.97722 | G318: 138.8 | H318: 127 | I318: 1.2647 | J318: 137.8 | K318: 135.4 | L318: 3.793 | M318: 64 | N318: 54 | O318: 53 | P318: 41 | Q318: 7 | R318: 4
A319: 202501 | F319: 139.52036 | G319: 138.5 | H319: 124.9 | I319: 1.2348 | J319: 139 | K319: 135.9 | L319: 3.902 | M319: 63 | N319: 61 | O319: 54 | P319: 37 | Q319: 12 | R319: 3
A320: 202502 | I320: 1.2545 | L320: 3.96

Sheet HAVERQ
A1: 20201 !Q | B1: UNQMPCPI@UK | C1: UNPM244@UK
A2: .DESC | B2: UK: BoE MPR Bank Staff Projections: CPI (Y/Y % Change) | C2: UK: BoE CPI Proj Based on Expected Interest Rate: Median [Q4-24] (Y/Y % Chg)
A3: .T1 | B3: Q1-2017 | C3: Q4-2024
A4: .TN | B4: Q1-2028 | C4: Q4-2027
A5: .LSOURCE | B5: Bank of England | C5: Discontinued
A6: .DTLM | B6: Feb-06-2025 12:42 | C6: Nov-07-2024 12:46
A7: 20201 | B7: 1.7 | C7: #N/A
A8: 20202 | B8: 0.6 | C8: #N/A
A9: 20203 | B9: 0.6 | C9: #N/A
A10: 20204 | B10: 0.5 | C10: #N/A
A11: 20211 | B11: 0.6 | C11: #N/A
A12: 20212 | B12: 2.1 | C12: #N/A
A13: 20213 | B13: 2.8 | C13: #N/A
A14: 20214 | B14: 4.9 | C14: #N/A
A15: 20221 | B15: 6.2 | C15: #N/A
A16: 20222 | B16: 9.2 | C16: #N/A
A17: 20223 | B17: 10 | C17: #N/A
A18: 20224 | B18: 10.7 | C18: #N/A
... A25: 20243 | B25: 2 | C25: #N/A
A26: 20244 | B26: 2.5 | C26: 2.4
A27: 20251 | B27: 2.8 | C27: 2.4
A28: 20252 | B28: 3.5 | C28: 2.6
A29: 20253 | B29: 3.7 | C29: 2.8
A30: 20254 | B30: 3.5 | C30: 2.7
A31: 20261 | B31: 3 | C31: 2.6
A32: 20262 | B32: 2.6 | C32: 2.4
A33: 20263 | B33: 2.6 | C33: 2.3
A34: 20264 | B34: 2.4 | C34: 2.2
A35: 20271 | B35: 2.3 | C35: 2.1
A36: 20272 | B36: 2.2 | C36: 1.9
A37: 20273 | B37: 2.1 | C37: 1.9
A38: 20274 | B38: 2 | C38: 1.8
A39: 20281 | B39: 1.9

Sheet BoE MPR - Chart 2.16
A1: Section 2: Current economic conditions
A3: Chart 2.18 - Contributions to CPI inflation
B5: Contributions, percentage points | H5: Inflation rates, per cent
A6: Date | B6: Food | C6: Electricity and gas | D6: Fuels and lubricants | E6: Other goods | F6: Services | H6: Food | I6: Electricity and gas | J6: Fuels and lubricants | K6: Other goods | L6: Services | M6: Total CPI
A7: 44227 | B7: -0.1 | C7: -0.3 | D7: -0.3 | E7: 0.4 | F7: 0.8 | H7: -0.7 | I7: -8.4 | J7: -8.2 | K7: 1.4 | L7: 1.7 | M7: 0.7
A8: 44255 | B8: 0 | C8: -0.3 | D8: -0.1 | E8: 0.1 | F8: 0.7 | H8: -0.6 | I8: -7.9 | J8: -3.5 | K8: 0.5 | L8: 1.5 | M8: 0.4
A9: 44286 | B9: -0.1 | C9: -0.2 | D9: 0.1 | E9: 0.3 | F9: 0.7 | H9: -1.4 | I9: -7.3 | J9: 3.5 | K9: 0.9 | L9: 1.5 | M9: 0.7
A10: 44316 | B10: 0 | C10: 0.1 | D10: 0.4 | E10: 0.4 | F10: 0.7 | H10: -0.4 | I10: 2.4 | J10: 13.6 | K10: 1.2 | L10: 1.6 | M10: 1.5
A11: 44347 | B11: -0.1 | C11: 0.1 | D11: 0.5 | E11: 0.8 | F11: 0.9 | H11: -1.3 | I11: 2.6 | J11: 17.9 | K11: 2.2 | L11: 1.9 | M11: 2.1
A12: 44377 | B12: 0 | C12: 0.1 | D12: 0.5 | E12: 1 | F12: 0.9 | H12: -0.6 | I12: 2.5 | J12: 20.3 | K12: 2.7 | L12: 2.1 | M12: 2.5
A13: 44408 | B13: -0.1 | C13: 0.1 | D13: 0.5 | E13: 0.8 | F13: 0.7 | H13: -0.6 | I13: 2.6 | J13: 17.7 | K13: 2.3 | L13: 1.6 | M13: 2
A14: 44439 | B14: 0.1 | C14: 0.1 | D14: 0.5 | E14: 1.2 | F14: 1.4 | H14: 0.3 | I14: 2.6 | J14: 17.7 | K14: 3.2 | L14: 3 | M14: 3.2
A15: 44469 | B15: 0.1 | C15: 0.1 | D15: 0.5 | E15: 1.3 | F15: 1.1 | H15: 0.8 | I15: 2.8 | J15: 17.8 | K15: 3.3 | L15: 2.6 | M15: 3.1
A16: 44500 | B16: 0.2 | C16: 0.8 | D16: 0.6 | E16: 1.3 | F16: 1.4 | H16: 1.2 | I16: 22.9 | J16: 21.5 | K16: 3.4 | L16: 3.2 | M16: 4.2
A17: 44530 | B17: 0.3 | C17: 0.8 | D17: 0.7 | E17: 1.9 | F17: 1.5 | H17: 2.5 | I17: 23.2 | J17: 28.5 | K17: 4.8 | L17: 3.3 | M17: 5.1
A18: 44561 | B18: 0.5 | C18: 0.7 | D18: 0.7 | E18: 2 | F18: 1.5 | H18: 4.2 | I18: 22.7 | J18: 26.8 | K18: 5 | L18: 3.4 | M18: 5.4
... A54: 45627 | B54: 0.2 | C54: -0.3 | D54: -0.2 | E54: 0.6 | F54: 2.1 | H54: 2 | I54: -6.8 | J54: -5 | K54: 1.7 | L54: 4.4 | M54: 2.5
A55: January 2025 (Bank staff projections) | B55: 0.27 | C55: -0.407 | D55: -0.07 | E55: 0.493 | F55: 2.529 | H55: 2.389 | I55: -9.862 | J55: -2.245 | K55: 1.523 | L55: 5.161 | M55: 2.816
A56: February 2025 (Bank staff projections) | B56: 0.307 | C56: -0.407 | D56: -0.069 | E56: 0.532 | F56: 2.483 | H56: 2.732 | I56: -9.911 | J56: -2.082 | K56: 1.639 | L56: 5.066 | M56: 2.848
A57: March 2025 (Bank staff projections) | B57: 0.287 | C57: -0.398 | D57: -0.108 | E57: 0.51 | F57: 2.417 | H57: 2.564 | I57: -9.772 | J57: -3.261 | K57: 1.566 | L57: 4.926 | M57: 2.709
A58: April 2025 (Bank staff projections) | B58: 0.306 | C58: 0.251 | D58: -0.161 | E58: 0.631 | F58: 2.525 | H58: 2.738 | I58: 7.508 | J58: -4.825 | K58: 1.943 | L58: 5.077 | M58: 3.554
A59: May 2025 (Bank staff projections) | B59: 0.354 | C59: 0.256 | D59: -0.161 | E59: 0.694 | F59: 2.387 | H59: 3.183 | I59: 7.672 | J59: -4.849 | K59: 2.141 | L59: 4.782 | M59: 3.53
A60: June 2025 (Bank staff projections) | B60: 0.342 | C60: 0.26 | D60: -0.084 | E60: 0.697 | F60: 2.333 | H60: 3.076 | I60: 7.821 | J60: -2.505 | K60: 2.159 | L60: 4.651 | M60: 3.549

Sheet BoE MPR - Chart 2.21
A1: Section 2: Current economic conditions
A3: Chart 2.21 - Measures of annual services price inflation, per cent
B5: Annual inflation
A6: Date | B6: Services | C6: Services low variance weighted | D6: Services excluding indexed and volatile components, rents and foreign holidays | E6: Services trimmed mean
A7: 44197 | B7: 2.1 | C7: 2.2 | D7: 1.4 | E7: 1.8
A8: 44228 | B8: 1.8 | C8: 2.1 | D8: 1.2 | E8: 1.7
A9: 44256 | B9: 1.8 | C9: 2.1 | D9: 1.2 | E9: 1.7
A10: 44287 | B10: 1.9 | C10: 2.1 | D10: 1.3 | E10: 1.7
A11: 44317 | B11: 2.2 | C11: 2.5 | D11: 1.8 | E11: 2
A12: 44348 | B12: 2.4 | C12: 2.7 | D12: 2.3 | E12: 2.3
A13: 44378 | B13: 1.9 | C13: 2.4 | D13: 1.9 | E13: 1.8
A14: 44409 | B14: 3 | C14: 3.6 | D14: 4.5 | E14: 2.8
A15: 44440 | B15: 2.5 | C15: 2.6 | D15: 3 | E15: 2.4
A16: 44470 | B16: 3 | C16: 2.9 | D16: 3.3 | E16: 2.9
A17: 44501 | B17: 3.2 | C17: 3.1 | D17: 3.7 | E17: 3.1
A18: 44531 | B18: 3.2 | C18: 3.2 | D18: 3.4 | E18: 3
... A54: 45627 | B54: 4.4 | C54: 5.5 | D54: 4.4 | E54: 5.1

Sheet Charts not used >>>
