Workbook
Name _DLX1.INC: HAVERD!$B$3:$AU$8
Name _DLX2.INC: 'HAVER BoE'!$B$2:$BP$7
Name _DLX3.INC: HAVERM!$B$1:$AF$6
Name Data: [1]sheet0!$C$2

Sheet CHARTS>>

Sheet DATA>>

Sheet Chart Data
A1: Vote share | E1: Term premium forecast | K1: RLG forecasts | S1: Impact of tighter FC on economy | X1: Quoted mortgage rates | AB1: Margins | AI1: Diff vs expiring deal
K2: Feb | M2: May | O2: Diff | X2: End-date: | Y2: =HAVERM!D4 -> Apr-2026 | Z2: =HAVERM!E4 -> Apr-2026 | AI2: 2 year fix, 75% LTV ** | AJ2: 5 year fix, 75% LTV **
B3: 2024 general election | C3: 2026 local elections | F3: UK | G3: US | H3: Japan | I3: Germany | K3: 2026 | L3: 2027 | M3: 2026 | N3: 2027 | O3: 2026 | P3: 2027 | T3: GDP | U3: C | V3: IPNR | Y3: 2 year fix, 75% LTV | Z3: 5 year fix, 75% LTV | AB3: 2 year fix, 75% LTV | AC3: 5 year fix, 75% LTV | AE3: 2 year swap | AF3: 5 year swap | AI3: 2 year fix, 75% LTV | AJ3: 5 year fix, 75% LTV
A4: Labour | B4: 33.7 | C4: 17 | E4: 2020 | F4: =Data!C194 -> -1.400203 | G4: =Data!D194 -> -1.270818 | H4: =Data!E194 -> -0.4589267 | I4: =Data!F194 -> -1.554241 | K4: 4.501 | L4: 4.318 | M4: 4.549 | N4: 4.792 | O4: =M4-K4 -> 0.048 | P4: =N4-L4 -> 0.474 | S4: 2026 | T4: =100*(('Data - Scen'!C218/'Data - Base'!C218)-1) -> 0 | U4: =100*(('Data - Scen'!D218/'Data - Base'!D218)-1) -> 0 | V4: =100*(('Data - Scen'!E218/'Data - Base'!E218)-1) -> 0 | X4: 41640 | Y4: =HAVERM!D175 -> 2.37 | Z4: =HAVERM!E175 -> 3.34 | AB4: =Y4-AE4 -> #N/A | AC4: =Z4-AF4 -> #N/A | AE4: =HAVERM!F175 -> #N/A | AF4: =HAVERM!G175 -> #N/A | AH4: 41640
A5: Conserv. | B5: 23.7 | C5: 17 | F5: =Data!C195 -> -0.4742025 | G5: =Data!D195 -> -1.328421 | H5: =Data!E195 -> -0.3453717 | I5: =Data!F195 -> -1.170631 | K5: 4.492 | L5: 4.196 | M5: 4.97 | N5: 4.682 | O5: =M5-K5 -> 0.478 | P5: =N5-L5 -> 0.486 | T5: =100*(('Data - Scen'!C219/'Data - Base'!C219)-1) -> 0.024372929 | U5: =100*(('Data - Scen'!D219/'Data - Base'!D219)-1) -> 0.026024031 | V5: =100*(('Data - Scen'!E219/'Data - Base'!E219)-1) -> 0.03558939 | X5: 41671 | Y5: =HAVERM!D176 -> 2.38 | Z5: =HAVERM!E176 -> 3.45 | AB5: =Y5-AE5 -> #N/A | AC5: =Z5-AF5 -> #N/A | AE5: =HAVERM!F176 -> #N/A | AF5: =HAVERM!G176 -> #N/A | AH5: 41671
A6: Reform | B6: 14.3 | C6: 26 | F6: =Data!C196 -> 0.2480247 | G6: =Data!D196 -> -1.259258 | H6: =Data!E196 -> -0.205531 | I6: =Data!F196 -> -1.146578 | K6: 4.467 | L6: 4.07 | M6: 4.961 | N6: 4.54 | O6: =M6-K6 -> 0.494 | P6: =N6-L6 -> 0.47 | T6: =100*(('Data - Scen'!C220/'Data - Base'!C220)-1) -> 0.058185233 | U6: =100*(('Data - Scen'!D220/'Data - Base'!D220)-1) -> 0.066199594 | V6: =100*(('Data - Scen'!E220/'Data - Base'!E220)-1) -> 0.10267494 | X6: 41699 | Y6: =HAVERM!D177 -> 2.37 | Z6: =HAVERM!E177 -> 3.48 | AB6: =Y6-AE6 -> #N/A | AC6: =Z6-AF6 -> #N/A | AE6: =HAVERM!F177 -> #N/A | AF6: =HAVERM!G177 -> #N/A | AH6: 41699
A7: Lib. Dem. | B7: 12.2 | C7: 16 | F7: =Data!C197 -> 0.7901152 | G7: =Data!D197 -> -0.9656042 | H7: =Data!E197 -> -0.06359368 | I7: =Data!F197 -> -1.126168 | K7: 4.412 | L7: 3.956 | M7: 4.88 | N7: 4.372 | O7: =M7-K7 -> 0.468 | P7: =N7-L7 -> 0.416 | Q7: =AVERAGE(O5:O7,P4:P7) -> 0.46942857 | T7: =100*(('Data - Scen'!C221/'Data - Base'!C221)-1) -> 0.10765458 | U7: =100*(('Data - Scen'!D221/'Data - Base'!D221)-1) -> 0.12617001 | V7: =100*(('Data - Scen'!E221/'Data - Base'!E221)-1) -> 0.2094553 | X7: 41730 | Y7: =HAVERM!D178 -> 2.54 | Z7: =HAVERM!E178 -> 3.69 | AB7: =Y7-AE7 -> #N/A | AC7: =Z7-AF7 -> #N/A | AE7: =HAVERM!F178 -> #N/A | AF7: =HAVERM!G178 -> #N/A | AH7: 41730
A8: Green | B8: 6.4 | C8: 18 | E8: 2021 | F8: =Data!C198 -> 1.541162 | G8: =Data!D198 -> -0.4946406 | H8: =Data!E198 -> -0.0002151728 | I8: =Data!F198 -> -0.8528938 | S8: 2027 | T8: =100*(('Data - Scen'!C222/'Data - Base'!C222)-1) -> 0.15659114 | U8: =100*(('Data - Scen'!D222/'Data - Base'!D222)-1) -> 0.19033725 | V8: =100*(('Data - Scen'!E222/'Data - Base'!E222)-1) -> 0.32678249 | X8: 41760 | Y8: =HAVERM!D179 -> 2.56 | Z8: =HAVERM!E179 -> 3.72 | AB8: =Y8-AE8 -> #N/A | AC8: =Z8-AF8 -> #N/A | AE8: =HAVERM!F179 -> #N/A | AF8: =HAVERM!G179 -> #N/A | AH8: 41760
A9: Other | B9: =100-SUM(B4:B8) -> 9.7 | C9: 6 | F9: =Data!C199 -> 1.185967 | G9: =Data!D199 -> -0.3768889 | H9: =Data!E199 -> 0.02403095 | I9: =Data!F199 -> -1.156042 | K9: RCB forecasts | T9: =100*(('Data - Scen'!C223/'Data - Base'!C223)-1) -> 0.18874361 | U9: =100*(('Data - Scen'!D223/'Data - Base'!D223)-1) -> 0.2458776 | V9: =100*(('Data - Scen'!E223/'Data - Base'!E223)-1) -> 0.42328042 | X9: 41791 | Y9: =HAVERM!D180 -> 2.6 | Z9: =HAVERM!E180 -> 3.69 | AB9: =Y9-AE9 -> #N/A | AC9: =Z9-AF9 -> #N/A | AE9: =HAVERM!F180 -> #N/A | AF9: =HAVERM!G180 -> #N/A | AH9: 41791
F10: =Data!C200 -> 0.5780302 | G10: =Data!D200 -> -0.8651952 | H10: =Data!E200 -> -0.07522835 | I10: =Data!F200 -> -1.259767 | K10: Feb | M10: May | O10: Diff | T10: =100*(('Data - Scen'!C224/'Data - Base'!C224)-1) -> 0.20621222 | U10: =100*(('Data - Scen'!D224/'Data - Base'!D224)-1) -> 0.29101465 | V10: =100*(('Data - Scen'!E224/'Data - Base'!E224)-1) -> 0.48333277 | X10: 41821 | Y10: =HAVERM!D181 -> 2.54 | Z10: =HAVERM!E181 -> 3.78 | AB10: =Y10-AE10 -> #N/A | AC10: =Z10-AF10 -> #N/A | AE10: =HAVERM!F181 -> #N/A | AF10: =HAVERM!G181 -> #N/A | AH10: 41821
F11: =Data!C201 -> 0.4362244 | G11: =Data!D201 -> -0.9455727 | H11: =Data!E201 -> -0.1353906 | I11: =Data!F201 -> -1.106633 | K11: 2026 | L11: 2027 | M11: 2026 | N11: 2027 | O11: 2026 | P11: 2027 | T11: =100*(('Data - Scen'!C225/'Data - Base'!C225)-1) -> 0.21144683 | U11: =100*(('Data - Scen'!D225/'Data - Base'!D225)-1) -> 0.32735412 | V11: =100*(('Data - Scen'!E225/'Data - Base'!E225)-1) -> 0.50517386 | X11: 41852 | Y11: =HAVERM!D182 -> 2.54 | Z11: =HAVERM!E182 -> 3.76 | AB11: =Y11-AE11 -> 1.5588 | AC11: =Z11-AF11 -> 2.15 | AE11: =HAVERM!F182 -> 0.9812 | AF11: =HAVERM!G182 -> 1.61 | AH11: 41852
E12: 2022 | F12: =Data!C202 -> -0.005793571 | G12: =Data!D202 -> -1.035532 | H12: =Data!E202 -> -0.1517915 | I12: =Data!F202 -> -0.9248759 | K12: 3.75 | L12: 3.25 | M12: 3.75 | N12: 3.75 | O12: =M12-K12 -> 0 | P12: =N12-L12 -> 0.5 | X12: 41883 | Y12: =HAVERM!D183 -> 2.46 | Z12: =HAVERM!E183 -> 3.61 | AB12: =Y12-AE12 -> 1.4812727 | AC12: =Z12-AF12 -> 1.9375955 | AE12: =HAVERM!F183 -> 0.97872727 | AF12: =HAVERM!G183 -> 1.6724045 | AH12: 41883
F13: =Data!C203 -> -1.116444 | G13: =Data!D203 -> -0.9544389 | H13: =Data!E203 -> -0.3281502 | I13: =Data!F203 -> -0.7541516 | K13: 3.581 | L13: 3.077 | M13: 3.75 | N13: 3.75 | O13: =M13-K13 -> 0.169 | P13: =N13-L13 -> 0.673 | X13: 41913 | Y13: =HAVERM!D184 -> 2.21 | Z13: =HAVERM!E184 -> 3.27 | AB13: =Y13-AE13 -> 1.3656522 | AC13: =Z13-AF13 -> 1.8341696 | AE13: =HAVERM!F184 -> 0.84434783 | AF13: =HAVERM!G184 -> 1.4358304 | AH13: 41913
F14: =Data!C204 -> -2.262011 | G14: =Data!D204 -> -2.050474 | H14: =Data!E204 -> -0.6069162 | I14: =Data!F204 -> -1.08056 | K14: 3.5 | L14: 3 | M14: 3.75 | N14: 3.75 | O14: =M14-K14 -> 0.25 | P14: =N14-L14 -> 0.75 | X14: 41944 | Y14: =HAVERM!D185 -> 2.17 | Z14: =HAVERM!E185 -> 3.21 | AB14: =Y14-AE14 -> 1.4026833 | AC14: =Z14-AF14 -> 1.8787167 | AE14: =HAVERM!F185 -> 0.76731667 | AF14: =HAVERM!G185 -> 1.3312833 | AH14: 41944
F15: =Data!C205 -> -2.748286 | G15: =Data!D205 -> -2.42089 | H15: =Data!E205 -> -0.8705126 | I15: =Data!F205 -> -1.370171 | K15: 3.345 | L15: 3 | M15: 3.75 | N15: 3.591 | O15: =M15-K15 -> 0.405 | P15: =N15-L15 -> 0.591 | Q15: =AVERAGE(O13:O15,P12:P15) -> 0.47685714 | X15: 41974 | Y15: =HAVERM!D186 -> 2.08 | Z15: =HAVERM!E186 -> 3.21 | AB15: =Y15-AE15 -> 1.3790636 | AC15: =Z15-AF15 -> 2.0094227 | AE15: =HAVERM!F186 -> 0.70093636 | AF15: =HAVERM!G186 -> 1.2005773 | AH15: 41974
E16: 2023 | F16: =Data!C206 -> -4.198305 | G16: =Data!D206 -> -3.155869 | H16: =Data!E206 -> -0.8742595 | I16: =Data!F206 -> -2.290555 | X16: 42005 | Y16: =HAVERM!D187 -> 2.01 | Z16: =HAVERM!E187 -> 3.09 | AB16: =Y16-AE16 -> 1.4174286 | AC16: =Z16-AF16 -> 2.1329952 | AE16: =HAVERM!F187 -> 0.59257143 | AF16: =HAVERM!G187 -> 0.95700476 | AH16: 42005
F17: =Data!C207 -> -3.759159 | G17: =Data!D207 -> -3.433098 | H17: =Data!E207 -> -1.02899 | I17: =Data!F207 -> -2.461839 | X17: 42036 | Y17: =HAVERM!D188 -> 1.96 | Z17: =HAVERM!E188 -> 3.05 | AB17: =Y17-AE17 -> 1.280755 | AC17: =Z17-AF17 -> 1.92882 | AE17: =HAVERM!F188 -> 0.679245 | AF17: =HAVERM!G188 -> 1.12118 | AH17: 42036
F18: =Data!C208 -> -3.51581 | G18: =Data!D208 -> -2.936102 | H18: =Data!E208 -> -0.9281871 | I18: =Data!F208 -> -2.727603 | X18: 42064 | Y18: =HAVERM!D189 -> 1.99 | Z18: =HAVERM!E189 -> 2.98 | AB18: =Y18-AE18 -> 1.3028524 | AC18: =Z18-AF18 -> 1.8285952 | AE18: =HAVERM!F189 -> 0.68714762 | AF18: =HAVERM!G189 -> 1.1514048 | AH18: 42064
F19: =Data!C209 -> -3.460574 | G19: =Data!D209 -> -2.457488 | H19: =Data!E209 -> -0.7505955 | I19: =Data!F209 -> -2.915811 | X19: 42095 | Y19: =HAVERM!D190 -> 1.95 | Z19: =HAVERM!E190 -> 2.92 | AB19: =Y19-AE19 -> 1.3036476 | AC19: =Z19-AF19 -> 1.8594333 | AE19: =HAVERM!F190 -> 0.64635238 | AF19: =HAVERM!G190 -> 1.0605667 | AH19: 42095
E20: 2024 | F20: =Data!C210 -> -3.233632 | G20: =Data!D210 -> -2.455854 | H20: =Data!E210 -> -0.8963838 | I20: =Data!F210 -> -2.96869 | X20: 42125 | Y20: =HAVERM!D191 -> 1.9 | Z20: =HAVERM!E191 -> 2.86 | AB20: =Y20-AE20 -> 1.1638524 | AC20: =Z20-AF20 -> 1.5970476 | AE20: =HAVERM!F191 -> 0.73614762 | AF20: =HAVERM!G191 -> 1.2629524 | AH20: 42125
F21: =Data!C211 -> -2.550798 | G21: =Data!D211 -> -1.896409 | H21: =Data!E211 -> -0.728087 | I21: =Data!F211 -> -2.469674 | X21: 42156 | Y21: =HAVERM!D192 -> 1.83 | Z21: =HAVERM!E192 -> 2.82 | AB21: =Y21-AE21 -> 1.0497955 | AC21: =Z21-AF21 -> 1.4679636 | AE21: =HAVERM!F192 -> 0.78020455 | AF21: =HAVERM!G192 -> 1.3520364 | AH21: 42156
F22: =Data!C212 -> -2.304361 | G22: =Data!D212 -> -1.963248 | H22: =Data!E212 -> -0.7111451 | I22: =Data!F212 -> -2.171902 | X22: 42186 | Y22: =HAVERM!D193 -> 1.87 | Z22: =HAVERM!E193 -> 2.83 | AB22: =Y22-AE22 -> 1.0242609 | AC22: =Z22-AF22 -> 1.422013 | AE22: =HAVERM!F193 -> 0.84573913 | AF22: =HAVERM!G193 -> 1.407987 | AH22: 42186
F23: =Data!C213 -> -1.380183 | G23: =Data!D213 -> -1.07173 | H23: =Data!E213 -> -0.5910925 | I23: =Data!F213 -> -1.608057 | X23: 42217 | Y23: =HAVERM!D194 -> 1.95 | Z23: =HAVERM!E194 -> 2.92 | AB23: =Y23-AE23 -> 1.1439048 | AC23: =Z23-AF23 -> 1.5978381 | AE23: =HAVERM!F194 -> 0.80609524 | AF23: =HAVERM!G194 -> 1.3221619 | AH23: 42217
E24: 2025 | F24: =Data!C214 -> -0.552002 | G24: =Data!D214 -> -0.6183422 | H24: =Data!E214 -> -0.3766288 | I24: =Data!F214 -> -0.7403606 | X24: 42248 | Y24: =HAVERM!D195 -> 1.91 | Z24: =HAVERM!E195 -> 2.84 | AB24: =Y24-AE24 -> 1.1834227 | AC24: =Z24-AF24 -> 1.6508136 | AE24: =HAVERM!F195 -> 0.72657727 | AF24: =HAVERM!G195 -> 1.1891864 | AH24: 42248
F25: =Data!C215 -> -0.2427194 | G25: =Data!D215 -> -0.6384518 | H25: =Data!E215 -> -0.3859788 | I25: =Data!F215 -> -0.2694005 | X25: 42278 | Y25: =HAVERM!D196 -> 1.87 | Z25: =HAVERM!E196 -> 2.78 | AB25: =Y25-AE25 -> 1.2124818 | AC25: =Z25-AF25 -> 1.6863545 | AE25: =HAVERM!F196 -> 0.65751818 | AF25: =HAVERM!G196 -> 1.0936455 | AH25: 42278
F26: =Data!C216 -> 0.07717013 | G26: =Data!D216 -> -0.6522727 | H26: =Data!E216 -> -0.2569222 | I26: =Data!F216 -> 0.1669607 | X26: 42309 | Y26: =HAVERM!D197 -> 1.92 | Z26: =HAVERM!E197 -> 2.77 | AB26: =Y26-AE26 -> 1.1974619 | AC26: =Z26-AF26 -> 1.5989381 | AE26: =HAVERM!F197 -> 0.7225381 | AF26: =HAVERM!G197 -> 1.1710619 | AH26: 42309
F27: =Data!C217 -> 0.007980824 | G27: =Data!D217 -> -0.5917101 | H27: =Data!E217 -> -0.08502853 | I27: =Data!F217 -> 0.2965423 | X27: 42339 | Y27: =HAVERM!D198 -> 1.9 | Z27: =HAVERM!E198 -> 2.75 | AB27: =Y27-AE27 -> 1.1574739 | AC27: =Z27-AF27 -> 1.5918435 | AE27: =HAVERM!F198 -> 0.74252609 | AF27: =HAVERM!G198 -> 1.1581565 | AH27: 42339
E28: 2026 | F28: =Data!C218 -> 0.1418591 | G28: =Data!D218 -> -0.369029 | H28: =Data!E218 -> 0.2529943 | I28: =Data!F218 -> 0.458383 | X28: 42370 | Y28: =HAVERM!D199 -> 1.93 | Z28: =HAVERM!E199 -> 2.68 | AB28: =Y28-AE28 -> 1.3224 | AC28: =Z28-AF28 -> 1.6969905 | AE28: =HAVERM!F199 -> 0.6076 | AF28: =HAVERM!G199 -> 0.98300952 | AH28: 42370 | AI28: =Y28-Y4 -> -0.44
F29: =Data!C219 -> 0.5102613 | G29: =Data!D219 -> -0.2961555 | H29: =Data!E219 -> 0.3214837 | I29: =Data!F219 -> 0.4592803 | X29: 42401 | Y29: =HAVERM!D200 -> 1.95 | Z29: =HAVERM!E200 -> 2.73 | AB29: =Y29-AE29 -> 1.5433238 | AC29: =Z29-AF29 -> 2.1155333 | AE29: =HAVERM!F200 -> 0.40667619 | AF29: =HAVERM!G200 -> 0.61446667 | AH29: 42401 | AI29: =Y29-Y5 -> -0.43
F30: =Data!C220 -> 0.4649615 | G30: =Data!D220 -> -0.3544827 | H30: =Data!E220 -> 0.4101481 | I30: =Data!F220 -> 0.2457602 | X30: 42430 | Y30: =HAVERM!D201 -> 1.9 | Z30: =HAVERM!E201 -> 2.7 | AB30: =Y30-AE30 -> 1.4501435 | AC30: =Z30-AF30 -> 2.0500696 | AE30: =HAVERM!F201 -> 0.44985652 | AF30: =HAVERM!G201 -> 0.64993043 | AH30: 42430 | AI30: =Y30-Y6 -> -0.47
F31: =Data!C221 -> 0.3446136 | G31: =Data!D221 -> -0.3542929 | H31: =Data!E221 -> 0.3521092 | I31: =Data!F221 -> 0.1769397 | X31: 42461 | Y31: =HAVERM!D202 -> 1.84 | Z31: =HAVERM!E202 -> 2.71 | AB31: =Y31-AE31 -> 1.3879619 | AC31: =Z31-AF31 -> 2.0608476 | AE31: =HAVERM!F202 -> 0.4520381 | AF31: =HAVERM!G202 -> 0.64915238 | AH31: 42461 | AI31: =Y31-Y7 -> -0.7
E32: 2027 | F32: =Data!C222 -> 0.2126694 | G32: =Data!D222 -> -0.2746601 | H32: =Data!E222 -> 0.2867934 | I32: =Data!F222 -> 0.2104251 | X32: 42491 | Y32: =HAVERM!D203 -> 1.91 | Z32: =HAVERM!E203 -> 2.64 | AB32: =Y32-AE32 -> 1.4411136 | AC32: =Z32-AF32 -> 1.9507182 | AE32: =HAVERM!F203 -> 0.46888636 | AF32: =HAVERM!G203 -> 0.68928182 | AH32: 42491 | AI32: =Y32-Y8 -> -0.65
F33: =Data!C223 -> 0.2192936 | G33: =Data!D223 -> -0.1621642 | H33: =Data!E223 -> 0.2386544 | I33: =Data!F223 -> 0.2725015 | X33: 42522 | Y33: =HAVERM!D204 -> 1.75 | Z33: =HAVERM!E204 -> 2.54 | AB33: =Y33-AE33 -> 1.3929045 | AC33: =Z33-AF33 -> 2.0278727 | AE33: =HAVERM!F204 -> 0.35709545 | AF33: =HAVERM!G204 -> 0.51212727 | AH33: 42522 | AI33: =Y33-Y9 -> -0.85
F34: =Data!C224 -> 0.24489 | G34: =Data!D224 -> -0.1229942 | H34: =Data!E224 -> 0.2211438 | I34: =Data!F224 -> 0.2912043 | X34: 42552 | Y34: =HAVERM!D205 -> 1.72 | Z34: =HAVERM!E205 -> 2.51 | AB34: =Y34-AE34 -> 1.5872619 | AC34: =Z34-AF34 -> 2.2893238 | AE34: =HAVERM!F205 -> 0.1327381 | AF34: =HAVERM!G205 -> 0.22067619 | AH34: 42552 | AI34: =Y34-Y10 -> -0.82
F35: =Data!C225 -> 0.3653541 | G35: =Data!D225 -> -0.07734013 | H35: =Data!E225 -> 0.2099167 | I35: =Data!F225 -> 0.2674395 | X35: 42583 | Y35: =HAVERM!D206 -> 1.69 | Z35: =HAVERM!E206 -> 2.39 | AB35: =Y35-AE35 -> 1.5824 | AC35: =Z35-AF35 -> 2.2147217 | AE35: =HAVERM!F206 -> 0.1076 | AF35: =HAVERM!G206 -> 0.17527826 | AH35: 42583 | AI35: =Y35-Y11 -> -0.85
E36: 2028 | F36: =Data!C226 -> 0.4382534 | G36: =Data!D226 -> -0.02301836 | H36: =Data!E226 -> 0.1942207 | I36: =Data!F226 -> 0.257955 | X36: 42614 | Y36: =HAVERM!D207 -> 1.59 | Z36: =HAVERM!E207 -> 2.34 | AB36: =Y36-AE36 -> 1.4666318 | AC36: =Z36-AF36 -> 2.1336091 | AE36: =HAVERM!F207 -> 0.12336818 | AF36: =HAVERM!G207 -> 0.20639091 | AH36: 42614 | AI36: =Y36-Y12 -> -0.87
F37: =Data!C227 -> 0.5065141 | G37: =Data!D227 -> 0.09917021 | H37: =Data!E227 -> 0.2446561 | I37: =Data!F227 -> 0.2833562 | X37: 42644 | Y37: =HAVERM!D208 -> 1.52 | Z37: =HAVERM!E208 -> 2.27 | AB37: =Y37-AE37 -> 1.3240381 | AC37: =Z37-AF37 -> 1.9146571 | AE37: =HAVERM!F208 -> 0.1959619 | AF37: =HAVERM!G208 -> 0.35534286 | AH37: 42644 | AI37: =Y37-Y13 -> -0.69
F38: =Data!C228 -> 0.5948478 | G38: =Data!D228 -> 0.2112072 | H38: =Data!E228 -> 0.3469173 | I38: =Data!F228 -> 0.325026 | X38: 42675 | Y38: =HAVERM!D209 -> 1.43 | Z38: =HAVERM!E209 -> 2.25 | AB38: =Y38-AE38 -> 1.1526455 | AC38: =Z38-AF38 -> 1.6863136 | AE38: =HAVERM!F209 -> 0.27735455 | AF38: =HAVERM!G209 -> 0.56368636 | AH38: 42675 | AI38: =Y38-Y14 -> -0.74
F39: =Data!C229 -> 0.6895179 | G39: =Data!D229 -> 0.3133483 | H39: =Data!E229 -> 0.4395704 | I39: =Data!F229 -> 0.3521523 | X39: 42705 | Y39: =HAVERM!D210 -> 1.45 | Z39: =HAVERM!E210 -> 2.26 | AB39: =Y39-AE39 -> 1.1509364 | AC39: =Z39-AF39 -> 1.6513864 | AE39: =HAVERM!F210 -> 0.29906364 | AF39: =HAVERM!G210 -> 0.60861364 | AH39: 42705 | AI39: =Y39-Y15 -> -0.63
E40: 2029 | F40: =Data!C230 -> 0.7829341 | G40: =Data!D230 -> 0.3990054 | H40: =Data!E230 -> 0.5587473 | I40: =Data!F230 -> 0.3748323 | X40: 42736 | Y40: =HAVERM!D211 -> 1.45 | Z40: =HAVERM!E211 -> 2.22 | AB40: =Y40-AE40 -> 1.1252182 | AC40: =Z40-AF40 -> 1.61045 | AE40: =HAVERM!F211 -> 0.32478182 | AF40: =HAVERM!G211 -> 0.60955 | AH40: 42736 | AI40: =Y40-Y16 -> -0.56
F41: =Data!C231 -> 0.8230639 | G41: =Data!D231 -> 0.4140043 | H41: =Data!E231 -> 0.6299802 | I41: =Data!F231 -> 0.3634992 | X41: 42767 | Y41: =HAVERM!D212 -> 1.42 | Z41: =HAVERM!E212 -> 2.2 | AB41: =Y41-AE41 -> 1.12247 | AC41: =Z41-AF41 -> 1.648535 | AE41: =HAVERM!F212 -> 0.29753 | AF41: =HAVERM!G212 -> 0.551465 | AH41: 42767 | AI41: =Y41-Y17 -> -0.54
F42: =Data!C232 -> 0.8 | G42: =Data!D232 -> 0.4158251 | H42: =Data!E232 -> 0.6503463 | I42: =Data!F232 -> 0.3256664 | X42: 42795 | Y42: =HAVERM!D213 -> 1.37 | Z42: =HAVERM!E213 -> 2.15 | AB42: =Y42-AE42 -> 1.0473304 | AC42: =Z42-AF42 -> 1.591987 | AE42: =HAVERM!F213 -> 0.32266957 | AF42: =HAVERM!G213 -> 0.55801304 | AH42: 42795 | AI42: =Y42-Y18 -> -0.62
F43: =Data!C233 -> 0.7640756 | G43: =Data!D233 -> 0.4070799 | H43: =Data!E233 -> 0.6597865 | I43: =Data!F233 -> 0.2892472 | X43: 42826 | Y43: =HAVERM!D214 -> 1.35 | Z43: =HAVERM!E214 -> 2.09 | AB43: =Y43-AE43 -> 1.07341 | AC43: =Z43-AF43 -> 1.624545 | AE43: =HAVERM!F214 -> 0.27659 | AF43: =HAVERM!G214 -> 0.465455 | AH43: 42826 | AI43: =Y43-Y19 -> -0.6
E44: 2030 | F44: =Data!C234 -> 0.7434697 | G44: =Data!D234 -> 0.3861387 | H44: =Data!E234 -> 0.6662557 | I44: =Data!F234 -> 0.2527082 | X44: 42856 | Y44: =HAVERM!D215 -> 1.49 | Z44: =HAVERM!E215 -> 2.03 | AB44: =Y44-AE44 -> 1.1840478 | AC44: =Z44-AF44 -> 1.5019739 | AE44: =HAVERM!F215 -> 0.30595217 | AF44: =HAVERM!G215 -> 0.52802609 | AH44: 42856 | AI44: =Y44-Y20 -> -0.41
F45: =Data!C235 -> 0.7310648 | G45: =Data!D235 -> 0.3650539 | H45: =Data!E235 -> 0.6790503 | I45: =Data!F235 -> 0.2225187 | X45: 42887 | Y45: =HAVERM!D216 -> 1.48 | Z45: =HAVERM!E216 -> 1.99 | AB45: =Y45-AE45 -> 1.1347682 | AC45: =Z45-AF45 -> 1.4356773 | AE45: =HAVERM!F216 -> 0.34523182 | AF45: =HAVERM!G216 -> 0.55432273 | AH45: 42887 | AI45: =Y45-Y21 -> -0.35
F46: =Data!C236 -> 0.7110219 | G46: =Data!D236 -> 0.343538 | H46: =Data!E236 -> 0.6880352 | I46: =Data!F236 -> 0.205555 | X46: 42917 | Y46: =HAVERM!D217 -> 1.41 | Z46: =HAVERM!E217 -> 1.97 | AB46: =Y46-AE46 -> 0.97240952 | AC46: =Z46-AF46 -> 1.2782571 | AE46: =HAVERM!F217 -> 0.43759048 | AF46: =HAVERM!G217 -> 0.69174286 | AH46: 42917 | AI46: =Y46-Y22 -> -0.46
F47: =Data!C237 -> 0.6946571 | G47: =Data!D237 -> 0.3229084 | H47: =Data!E237 -> 0.6979308 | I47: =Data!F237 -> 0.201362 | X47: 42948 | Y47: =HAVERM!D218 -> 1.43 | Z47: =HAVERM!E218 -> 1.96 | AB47: =Y47-AE47 -> 1.0583739 | AC47: =Z47-AF47 -> 1.3781739 | AE47: =HAVERM!F218 -> 0.37162609 | AF47: =HAVERM!G218 -> 0.58182609 | AH47: 42948 | AI47: =Y47-Y23 -> -0.52
X48: 42979 | Y48: =HAVERM!D219 -> 1.4 | Z48: =HAVERM!E219 -> 1.9 | AB48: =Y48-AE48 -> 0.86071429 | AC48: =Z48-AF48 -> 1.1466619 | AE48: =HAVERM!F219 -> 0.53928571 | AF48: =HAVERM!G219 -> 0.7533381 | AH48: 42979 | AI48: =Y48-Y24 -> -0.51
X49: 43009 | Y49: =HAVERM!D220 -> 1.55 | Z49: =HAVERM!E220 -> 2.04 | AB49: =Y49-AE49 -> 0.87478182 | AC49: =Z49-AF49 -> 1.1439545 | AE49: =HAVERM!F220 -> 0.67521818 | AF49: =HAVERM!G220 -> 0.89604545 | AH49: 43009 | AI49: =Y49-Y25 -> -0.32
X50: 43040 | Y50: =HAVERM!D221 -> 1.61 | Z50: =HAVERM!E221 -> 2.04 | AB50: =Y50-AE50 -> 0.93155238 | AC50: =Z50-AF50 -> 1.1523905 | AE50: =HAVERM!F221 -> 0.67844762 | AF50: =HAVERM!G221 -> 0.88760952 | AH50: 43040 | AI50: =Y50-Y26 -> -0.31
X51: 43070 | Y51: =HAVERM!D222 -> 1.57 | Z51: =HAVERM!E222 -> 2.07 | AB51: =Y51-AE51 -> 0.88347143 | AC51: =Z51-AF51 -> 1.1779048 | AE51: =HAVERM!F222 -> 0.68652857 | AF51: =HAVERM!G222 -> 0.89209524 | AH51: 43070 | AI51: =Y51-Y27 -> -0.33
X52: 43101 | Y52: =HAVERM!D223 -> 1.54 | Z52: =HAVERM!E223 -> 1.98 | AB52: =Y52-AE52 -> 0.79875455 | AC52: =Z52-AF52 -> 0.99838636 | AE52: =HAVERM!F223 -> 0.74124545 | AF52: =HAVERM!G223 -> 0.98161364 | AH52: 43101 | AI52: =Y52-Y28 -> -0.39
X53: 43132 | Y53: =HAVERM!D224 -> 1.49 | Z53: =HAVERM!E224 -> 1.99 | AB53: =Y53-AE53 -> 0.62635 | AC53: =Z53-AF53 -> 0.81268 | AE53: =HAVERM!F224 -> 0.86365 | AF53: =HAVERM!G224 -> 1.17732 | AH53: 43132 | AI53: =Y53-Y29 -> -0.46
X54: 43160 | Y54: =HAVERM!D225 -> 1.53 | Z54: =HAVERM!E225 -> 2.02 | AB54: =Y54-AE54 -> 0.63301818 | AC54: =Z54-AF54 -> 0.89234545 | AE54: =HAVERM!F225 -> 0.89698182 | AF54: =HAVERM!G225 -> 1.1276545 | AH54: 43160 | AI54: =Y54-Y30 -> -0.37
X55: 43191 | Y55: =HAVERM!D226 -> 1.72 | Z55: =HAVERM!E226 -> 2.01 | AB55: =Y55-AE55 -> 0.8357 | AC55: =Z55-AF55 -> 0.90777143 | AE55: =HAVERM!F226 -> 0.8843 | AF55: =HAVERM!G226 -> 1.1022286 | AH55: 43191 | AI55: =Y55-Y31 -> -0.12
X56: 43221 | Y56: =HAVERM!D227 -> 1.74 | Z56: =HAVERM!E227 -> 2.06 | AB56: =Y56-AE56 -> 0.95797826 | AC56: =Z56-AF56 -> 1.0067348 | AE56: =HAVERM!F227 -> 0.78202174 | AF56: =HAVERM!G227 -> 1.0532652 | AH56: 43221 | AI56: =Y56-Y32 -> -0.17
X57: 43252 | Y57: =HAVERM!D228 -> 1.74 | Z57: =HAVERM!E228 -> 2.03 | AB57: =Y57-AE57 -> 0.94799524 | AC57: =Z57-AF57 -> 0.99781905 | AE57: =HAVERM!F228 -> 0.79200476 | AF57: =HAVERM!G228 -> 1.032181 | AH57: 43252 | AI57: =Y57-Y33 -> -0.01
X58: 43282 | Y58: =HAVERM!D229 -> 1.75 | Z58: =HAVERM!E229 -> 2.04 | AB58: =Y58-AE58 -> 0.91528636 | AC58: =Z58-AF58 -> 1.0096955 | AE58: =HAVERM!F229 -> 0.83471364 | AF58: =HAVERM!G229 -> 1.0303045 | AH58: 43282 | AI58: =Y58-Y34 -> 0.03
X59: 43313 | Y59: =HAVERM!D230 -> 1.75 | Z59: =HAVERM!E230 -> 2.03 | AB59: =Y59-AE59 -> 0.88283478 | AC59: =Z59-AF59 -> 0.9683913 | AE59: =HAVERM!F230 -> 0.86716522 | AF59: =HAVERM!G230 -> 1.0616087 | AH59: 43313 | AI59: =Y59-Y35 -> 0.06
... X63: 43435 | Y63: =HAVERM!D234 -> 1.73 | Z63: =HAVERM!E234 -> 2.01 | AB63: =Y63-AE63 -> 0.8571 | AC63: =Z63-AF63 -> 0.98364286 | AE63: =HAVERM!F234 -> 0.8729 | AF63: =HAVERM!G234 -> 1.0263571 | AH63: 43435 | AI63: =Y63-Y39 -> 0.28
X64: 43466 | Y64: =HAVERM!D235 -> 1.72 | Z64: =HAVERM!E235 -> 2.05 | AB64: =Y64-AE64 -> 0.85026087 | AC64: =Z64-AF64 -> 1.0260217 | AE64: =HAVERM!F235 -> 0.86973913 | AF64: =HAVERM!G235 -> 1.0239783 | AH64: 43466 | AI64: =Y64-Y40 -> 0.27 | AJ64: =Z64-Z4 -> -1.29
X65: 43497 | Y65: =HAVERM!D236 -> 1.7 | Z65: =HAVERM!E236 -> 2.05 | AB65: =Y65-AE65 -> 0.873395 | AC65: =Z65-AF65 -> 1.07894 | AE65: =HAVERM!F236 -> 0.826605 | AF65: =HAVERM!G236 -> 0.97106 | AH65: 43497 | AI65: =Y65-Y41 -> 0.28 | AJ65: =Z65-Z5 -> -1.4
X66: 43525 | Y66: =HAVERM!D237 -> 1.7 | Z66: =HAVERM!E237 -> 2.03 | AB66: =Y66-AE66 -> 0.90167619 | AC66: =Z66-AF66 -> 1.0868 | AE66: =HAVERM!F237 -> 0.79832381 | AF66: =HAVERM!G237 -> 0.9432 | AH66: 43525 | AI66: =Y66-Y42 -> 0.33 | AJ66: =Z66-Z6 -> -1.45
X67: 43556 | Y67: =HAVERM!D238 -> 1.66 | Z67: =HAVERM!E238 -> 2 | AB67: =Y67-AE67 -> 0.86787273 | AC67: =Z67-AF67 -> 1.0611364 | AE67: =HAVERM!F238 -> 0.79212727 | AF67: =HAVERM!G238 -> 0.93886364 | AH67: 43556 | AI67: =Y67-Y43 -> 0.31 | AJ67: =Z67-Z7 -> -1.69
X68: 43586 | Y68: =HAVERM!D239 -> 1.65 | Z68: =HAVERM!E239 -> 1.99 | AB68: =Y68-AE68 -> 0.88321304 | AC68: =Z68-AF68 -> 1.1189522 | AE68: =HAVERM!F239 -> 0.76678696 | AF68: =HAVERM!G239 -> 0.87104783 | AH68: 43586 | AI68: =Y68-Y44 -> 0.16 | AJ68: =Z68-Z8 -> -1.73
X69: 43617 | Y69: =HAVERM!D240 -> 1.64 | Z69: =HAVERM!E240 -> 1.97 | AB69: =Y69-AE69 -> 0.998995 | AC69: =Z69-AF69 -> 1.290385 | AE69: =HAVERM!F240 -> 0.641005 | AF69: =HAVERM!G240 -> 0.679615 | AH69: 43617 | AI69: =Y69-Y45 -> 0.16 | AJ69: =Z69-Z9 -> -1.72
X70: 43647 | Y70: =HAVERM!D241 -> 1.61 | Z70: =HAVERM!E241 -> 1.93 | AB70: =Y70-AE70 -> 1.074087 | AC70: =Z70-AF70 -> 1.3573087 | AE70: =HAVERM!F241 -> 0.53591304 | AF70: =HAVERM!G241 -> 0.5726913 | AH70: 43647 | AI70: =Y70-Y46 -> 0.2 | AJ70: =Z70-Z10 -> -1.85
X71: 43678 | Y71: =HAVERM!D242 -> 1.59 | Z71: =HAVERM!E242 -> 1.89 | AB71: =Y71-AE71 -> 1.1301773 | AC71: =Z71-AF71 -> 1.4921818 | AE71: =HAVERM!F242 -> 0.45982273 | AF71: =HAVERM!G242 -> 0.39781818 | AH71: 43678 | AI71: =Y71-Y47 -> 0.16 | AJ71: =Z71-Z11 -> -1.87
X72: 43709 | Y72: =HAVERM!D243 -> 1.55 | Z72: =HAVERM!E243 -> 1.79 | AB72: =Y72-AE72 -> 1.0178952 | AC72: =Z72-AF72 -> 1.3218286 | AE72: =HAVERM!F243 -> 0.53210476 | AF72: =HAVERM!G243 -> 0.46817143 | AH72: 43709 | AI72: =Y72-Y48 -> 0.15 | AJ72: =Z72-Z12 -> -1.82
X73: 43739 | Y73: =HAVERM!D244 -> 1.47 | Z73: =HAVERM!E244 -> 1.71 | AB73: =Y73-AE73 -> 0.9451087 | AC73: =Z73-AF73 -> 1.2177696 | AE73: =HAVERM!F244 -> 0.5248913 | AF73: =HAVERM!G244 -> 0.49223043 | AH73: 43739 | AI73: =Y73-Y49 -> -0.08 | AJ73: =Z73-Z13 -> -1.56
X74: 43770 | Y74: =HAVERM!D245 -> 1.41 | Z74: =HAVERM!E245 -> 1.67 | AB74: =Y74-AE74 -> 0.82919524 | AC74: =Z74-AF74 -> 1.0745143 | AE74: =HAVERM!F245 -> 0.58080476 | AF74: =HAVERM!G245 -> 0.59548571 | AH74: 43770 | AI74: =Y74-Y50 -> -0.2 | AJ74: =Z74-Z14 -> -1.54
X75: 43800 | Y75: =HAVERM!D246 -> 1.42 | Z75: =HAVERM!E246 -> 1.67 | AB75: =Y75-AE75 -> 0.81618182 | AC75: =Z75-AF75 -> 1.0191955 | AE75: =HAVERM!F246 -> 0.60381818 | AF75: =HAVERM!G246 -> 0.65080455 | AH75: 43800 | AI75: =Y75-Y51 -> -0.15 | AJ75: =Z75-Z15 -> -1.54
... X151: 46113 | Y151: =HAVERM!D322 -> 5.14 | Z151: =HAVERM!E322 -> 5 | AB151: =Y151-AE151 -> 0.97142727 | AC151: =Z151-AF151 -> 0.84685909 | AE151: =HAVERM!F322 -> 4.1685727 | AF151: =HAVERM!G322 -> 4.1531409 | AH151: 46113 | AI151: =Y151-Y127 -> 0.16 | AJ151: =Z151-Z91 -> 3.29
X152: 46143 | Y152: =AB152+AE152 -> 4.957061 | Z152: =AC152+AF152 -> 4.895758 | AB152: 0.7 | AC152: 0.65 | AE152: =Data!H219 -> 4.257061 | AF152: =Data!I219 -> 4.245758 | AH152: 46143 | AI152: =Y152-Y128 -> -0.232939 | AJ152: =Z152-Z92 -> 3.215758
X153: 46174 | Y153: =AB153+AE153 -> 4.8971857 | Z153: =AC153+AF153 -> 4.8525077 | AB153: =AB152+(AB155-AB152)*1/3 -> 0.66666667 | AC153: =AC152+(AC155-AC152)*1/3 -> 0.61666667 | AE153: =AE152+(AE155-AE152)*1/3 -> 4.230519 | AF153: =AF152+(AF155-AF152)*1/3 -> 4.235841 | AH153: 46174 | AI153: =Y153-Y129 -> -0.26281433 | AJ153: =Z153-Z93 -> 3.2525077
X154: 46204 | Y154: =AB154+AE154 -> 4.8373103 | Z154: =AC154+AF154 -> 4.8092573 | AB154: =AB153+(AB155-AB152)*1/3 -> 0.63333333 | AC154: =AC153+(AC155-AC152)*1/3 -> 0.58333333 | AE154: =AE153+(AE155-AE152)*1/3 -> 4.203977 | AF154: =AF153+(AF155-AF152)*1/3 -> 4.225924 | AH154: 46204 | AI154: =Y154-Y130 -> -0.15268967 | AJ154: =Z154-Z94 -> 3.3592573
X155: 46235 | Y155: =AB155+AE155 -> 4.777435 | Z155: =AC155+AF155 -> 4.766007 | AB155: 0.6 | AC155: 0.55 | AE155: =Data!H220 -> 4.177435 | AF155: =Data!I220 -> 4.216007 | AH155: 46235 | AI155: =Y155-Y131 -> -0.022565 | AJ155: =Z155-Z95 -> 3.376007
X156: 46266 | Y156: =AB156+AE156 -> 4.7271657 | Z156: =AC156+AF156 -> 4.724596 | AB156: =AB155+(AB158-AB155)*1/3 -> 0.6 | AC156: =AC155+(AC158-AC155)*1/3 -> 0.53333333 | AE156: =AE155+(AE158-AE155)*1/3 -> 4.1271657 | AF156: =AF155+(AF158-AF155)*1/3 -> 4.1912627 | AH156: 46266 | AI156: =Y156-Y132 -> 0.14716567 | AJ156: =Z156-Z96 -> 3.444596
X157: 46296 | Y157: =AB157+AE157 -> 4.6768963 | Z157: =AC157+AF157 -> 4.683185 | AB157: =AB156+(AB158-AB155)*1/3 -> 0.6 | AC157: =AC156+(AC158-AC155)*1/3 -> 0.51666667 | AE157: =AE156+(AE158-AE155)*1/3 -> 4.0768963 | AF157: =AF156+(AF158-AF155)*1/3 -> 4.1665183 | AH157: 46296 | AI157: =Y157-Y133 -> 0.27689633 | AJ157: =Z157-Z97 -> 3.383185
X158: 46327 | Y158: =AB158+AE158 -> 4.626627 | Z158: =AC158+AF158 -> 4.641774 | AB158: 0.6 | AC158: 0.5 | AE158: =Data!H221 -> 4.026627 | AF158: =Data!I221 -> 4.141774 | AH158: 46327 | AI158: =Y158-Y134 -> 0.096627 | AJ158: =Z158-Z98 -> 3.121774
X159: 46357 | Y159: =AB159+AE159 -> 4.6051763 | Z159: =AC159+AF159 -> 4.6299547 | AB159: =AB158+(AB161-AB158)*1/3 -> 0.6 | AC159: =AC158+(AC161-AC158)*1/3 -> 0.5 | AE159: =AE158+(AE161-AE158)*1/3 -> 4.0051763 | AF159: =AF158+(AF161-AF158)*1/3 -> 4.1299547 | AH159: 46357 | AI159: =Y159-Y135 -> 0.0051763333 | AJ159: =Z159-Z99 -> 3.0399547
X160: 46388 | Y160: =AB160+AE160 -> 4.5837257 | Z160: =AC160+AF160 -> 4.6181353 | AB160: =AB159+(AB161-AB158)*1/3 -> 0.6 | AC160: =AC159+(AC161-AC158)*1/3 -> 0.5 | AE160: =AE159+(AE161-AE158)*1/3 -> 3.9837257 | AF160: =AF159+(AF161-AF158)*1/3 -> 4.1181353 | AH160: 46388 | AI160: =Y160-Y136 -> -0.046274333 | AJ160: =Z160-Z100 -> 2.9881353
X161: 46419 | Y161: =AB161+AE161 -> 4.562275 | Z161: =AC161+AF161 -> 4.606316 | AB161: ='[2]Mortgage & deposit rates'!Z119 -> 0.6 | AC161: 0.5 | AE161: =Data!H222 -> 3.962275 | AF161: =Data!I222 -> 4.106316 | AH161: 46419 | AI161: =Y161-Y137 -> -0.087725 | AJ161: =Z161-Z101 -> 2.816316
X162: 46447 | Y162: =AB162+AE162 -> 4.5535047 | Z162: =AC162+AF162 -> 4.582105 | AB162: =AB161+(AB164-AB161)*1/3 -> 0.63333333 | AC162: =AC161+(AC164-AC161)*1/3 -> 0.5 | AE162: =AE161+(AE164-AE161)*1/3 -> 3.9201713 | AF162: =AF161+(AF164-AF161)*1/3 -> 4.082105 | AH162: 46447 | AI162: =Y162-Y138 -> 0.013504667 | AJ162: =Z162-Z102 -> 2.472105
X163: 46478 | Y163: =AB163+AE163 -> 4.5447343 | Z163: =AC163+AF163 -> 4.557894 | AB163: =AB162+(AB164-AB161)*1/3 -> 0.66666667 | AC163: =AC162+(AC164-AC161)*1/3 -> 0.5 | AE163: =AE162+(AE164-AE161)*1/3 -> 3.8780677 | AF163: =AF162+(AF164-AF161)*1/3 -> 4.057894 | AH163: 46478 | AI163: =Y163-Y139 -> 0.12473433 | AJ163: =Z163-Z103 -> 2.207894
X164: 46508 | Y164: =AB164+AE164 -> 4.535964 | Z164: =AC164+AF164 -> 4.533683 | AB164: ='[2]Mortgage & deposit rates'!Z120 -> 0.7 | AC164: ='[2]Mortgage & deposit rates'!AA120 -> 0.5 | AE164: =Data!H223 -> 3.835964 | AF164: =Data!I223 -> 4.033683 | AH164: 46508 | AI164: =Y164-Y140 -> 0.355964 | AJ164: =Z164-Z104 -> 1.913683
X165: 46539 | Y165: =AB165+AE165 -> 4.520069 | Z165: =AC165+AF165 -> 4.5197463 | AB165: =AB164+(AB167-AB164)*1/3 -> 0.71666667 | AC165: =AC164+(AC167-AC164)*1/3 -> 0.51666667 | AE165: =AE164+(AE167-AE164)*1/3 -> 3.8034023 | AF165: =AF164+(AF167-AF164)*1/3 -> 4.0030797 | AH165: 46539 | AI165: =Y165-Y141 -> 0.240069 | AJ165: =Z165-Z105 -> 1.6197463
X166: 46569 | Y166: =AB166+AE166 -> 4.504174 | Z166: =AC166+AF166 -> 4.5058097 | AB166: =AB165+(AB167-AB164)*1/3 -> 0.73333333 | AC166: =AC165+(AC167-AC164)*1/3 -> 0.53333333 | AE166: =AE165+(AE167-AE164)*1/3 -> 3.7708407 | AF166: =AF165+(AF167-AF164)*1/3 -> 3.9724763 | AH166: 46569 | AI166: =Y166-Y142 -> 0.294174 | AJ166: =Z166-Z106 -> 1.0758097
X167: 46600 | Y167: =AB167+AE167 -> 4.488279 | Z167: =AC167+AF167 -> 4.491873 | AB167: ='[2]Mortgage & deposit rates'!Z121 -> 0.75 | AC167: ='[2]Mortgage & deposit rates'!AA121 -> 0.55 | AE167: =Data!H224 -> 3.738279 | AF167: =Data!I224 -> 3.941873 | AH167: 46600 | AI167: =Y167-Y143 -> 0.388279 | AJ167: =Z167-Z107 -> 0.881873
X168: 46631 | Y168: =AB168+AE168 -> 4.4544497 | Z168: =AC168+AF168 -> 4.4599207 | AB168: =AB167+(AB170-AB167)*1/3 -> 0.76666667 | AC168: =AC167+(AC170-AC167)*1/3 -> 0.56666667 | AE168: =AE167+(AE170-AE167)*1/3 -> 3.687783 | AF168: =AF167+(AF170-AF167)*1/3 -> 3.893254 | AH168: 46631 | AI168: =Y168-Y144 -> 0.26444967 | AJ168: =Z168-Z108 -> 0.48992067
X169: 46661 | Y169: =AB169+AE169 -> 4.4206203 | Z169: =AC169+AF169 -> 4.4279683 | AB169: =AB168+(AB170-AB167)*1/3 -> 0.78333333 | AC169: =AC168+(AC170-AC167)*1/3 -> 0.58333333 | AE169: =AE168+(AE170-AE167)*1/3 -> 3.637287 | AF169: =AF168+(AF170-AF167)*1/3 -> 3.844635 | AH169: 46661 | AI169: =Y169-Y145 -> 0.22062033 | AJ169: =Z169-Z109 -> -1.1820317
X170: 46692 | Y170: =AB170+AE170 -> 4.386791 | Z170: =AC170+AF170 -> 4.396016 | AB170: ='[2]Mortgage & deposit rates'!Z122 -> 0.8 | AC170: ='[2]Mortgage & deposit rates'!AA122 -> 0.6 | AE170: =Data!H225 -> 3.586791 | AF170: =Data!I225 -> 3.796016 | AH170: 46692 | AI170: =Y170-Y146 -> 0.326791 | AJ170: =Z170-Z110 -> -1.103984
X171: 46722 | Y171: =AB171+AE171 -> 4.3151237 | Z171: =AC171+AF171 -> 4.357012 | AB171: =AB170+(AB173-AB170)*1/3 -> 0.8 | AC171: =AC170+(AC173-AC170)*1/3 -> 0.61666667 | AE171: =AE170+(AE173-AE170)*1/3 -> 3.5151237 | AF171: =AF170+(AF173-AF170)*1/3 -> 3.7403453 | AH171: 46722 | AI171: =Y171-Y147 -> 0.34512367 | AJ171: =Z171-Z111 -> -0.692988
AB172: =AB171+(AB173-AB170)*1/3 -> 0.8 | AC172: =AC171+(AC173-AC170)*1/3 -> 0.63333333 | AE172: =AE171+(AE173-AE170)*1/3 -> 3.4434563 | AF172: =AF171+(AF173-AF170)*1/3 -> 3.6846747
AB173: ='[2]Mortgage & deposit rates'!Z123 -> 0.8 | AC173: ='[2]Mortgage & deposit rates'!AA123 -> 0.65 | AE173: =Data!H226 -> 3.371789 | AF173: =Data!I226 -> 3.629004
Y174: =Y151-Y149 -> 1.17 | Z174: =Z151-Z149 -> 0.99

Sheet HAVERD
C1: UK | D1: US | E1: Germany | F1: Italy | G1: Japan | H1: New Zealand | I1: Sweden | J1: Canada | K1: France | L1: Spain | M1: Australia | O1: UK | P1: US | R1: UK | S1: UK | T1: US | U1: US | V1: Eurozone | W1: Eurozone | AS1: CALCULATIONS >> | AT1: UK | AU1: US | AV1: Eurozone | BA1: UK | BB1: US | BD1: =C1 -> UK | BE1: =D1 -> US | BF1: =E1 -> Germany | BG1: =F1 -> Italy | BH1: =G1 -> Japan | BI1: =H1 -> New Zealand | BJ1: =I1 -> Sweden | BK1: =J1 -> Canada | ... BN1: =M1 -> Australia | BQ1: RLG since 27/2 | CC1: =AT1 -> UK | CD1: =AU1 -> US | CE1: =AV1 -> Eurozone | CG1: Yield curve
C2: 10-year | D2: 10-year | E2: 10-year | O2: 2-year | P2: 2-year | R2: 1yr | S2: 2yr | T2: 1yr | U2: 2yr | V2: 1yr | W2: 2yr | Y2: 1Y | Z2: 2Y | AA2: 3Y | AB2: 4Y | AC2: 5Y | AD2: 6Y | AE2: 7Y | AF2: 8Y | AG2: 9Y | AH2: 10Y | AI2: 15Y | AJ2: 20Y | AK2: 30Y | AT2: 1y1y fwd | AU2: 1y1y fwd | AV2: 1y1y fwd | AX2: 10-year Gilt-US Treasury spread | AY2: Spread in policy rate expectations (1y1y OIS GBP-USD) | BA2: 2s10s | BB2: 2s10s | BD2: RLG since 27/2 | BE2: RLG since 27/2 | BF2: RLG since 27/2 | BG2: RLG since 27/2 | BH2: RLG since 27/2 | BI2: RLG since 27/2 | BJ2: RLG since 27/2 | BK2: RLG since 27/2 | BL2: RLG since 27/2 | BM2: RLG since 27/2 | BN2: RLG since 27/2 | BQ2: =RANK(BQ4,$BQ$4:$CA$4) -> 1 | BR2: =RANK(BR4,$BQ$4:$CA$4) -> 4 | BS2: =RANK(BS4,$BQ$4:$CA$4) -> 7 | BT2: =RANK(BT4,$BQ$4:$CA$4) -> 2 | BU2: =RANK(BU4,$BQ$4:$CA$4) -> 8 | BV2: =RANK(BV4,$BQ$4:$CA$4) -> 10 | BW2: =RANK(BW4,$BQ$4:$CA$4) -> 11 | BX2: =RANK(BX4,$BQ$4:$CA$4) -> 6 | ... CA2: =RANK(CA4,$BQ$4:$CA$4) -> 9 | CC2: 1yr1yr forward rate since 27/2 | CD2: 1yr1yr forward rate since 27/2 | CE2: 1yr1yr forward rate since 27/2 | CI2: 1Y | CJ2: 2Y | CK2: 3Y | CL2: 4Y | CM2: 5Y | CN2: 6Y | CO2: 7Y | CP2: 8Y | CQ2: 9Y | CR2: 10Y | CS2: 15Y | CT2: 20Y | CU2: 30Y
B3: 1240101 !D | C3: T112GA@INTDAILY | D3: R111GA@INTDAILY | E3: T134GA@INTDAILY | F3: T136GA@INTDAILY | G3: T158GA@INTDAILY | H3: T196GA@INTDAILY | I3: T144GA@INTDAILY | J3: T156GA@INTDAILY | K3: T132GA@INTDAILY | L3: T184GA@INTDAILY | M3: R193MA@INTDAILY | O3: T112G2@INTDAILY | P3: T111G2@INTDAILY | R3: M112I1Y@INTDAILY | S3: M112IHH@INTDAILY | T3: MUSAU1Y@INTDAILY | U3: MUSAU2Y@INTDAILY | V3: M02321M@INTDAILY | W3: M02341M@INTDAILY | Y3: T112G1@INTDAILY | Z3: T112G2@INTDAILY | AA3: T112G3@INTDAILY | AB3: T112G4@INTDAILY | AC3: T112G5@INTDAILY | AD3: T112G6@INTDAILY | AE3: T112G7@INTDAILY | AF3: T112G8@INTDAILY | AG3: T112G9@INTDAILY | AH3: T112GA@INTDAILY | AI3: T112GF@INTDAILY | AJ3: T112GK@INTDAILY | AK3: T112GT@INTDAILY | AL3: R11212F@INTDAILY | AM3: R11224F@INTDAILY | AN3: R11236F@INTDAILY | AO3: R11248F@INTDAILY | AP3: R11260F@INTDAILY | AQ3: R112I6A@INTDAILY | BQ3: =BD1 -> UK | BR3: =BE1 -> US | BS3: =BF1 -> Germany | BT3: =BG1 -> Italy | BU3: =BH1 -> Japan | BV3: =BI1 -> New Zealand | BW3: =BJ1 -> Sweden | BX3: =BK1 -> Canada | ... CA3: =BN1 -> Australia | CG3: 46080 | CH3: Pre-conflict | CI3: =INDEX($Y$9:$AK$723,MATCH($CG3,$A$9:$A$723,0),MATCH(CI$2,$Y$2:$AK$2,0)) -> 3.52 | CJ3: =INDEX($Y$9:$AK$723,MATCH($CG3,$A$9:$A$723,0),MATCH(CJ$2,$Y$2:$AK$2,0)) -> 3.69 | CK3: =INDEX($Y$9:$AK$723,MATCH($CG3,$A$9:$A$723,0),MATCH(CK$2,$Y$2:$AK$2,0)) -> 3.76 | CL3: =INDEX($Y$9:$AK$723,MATCH($CG3,$A$9:$A$723,0),MATCH(CL$2,$Y$2:$AK$2,0)) -> 3.68 | CM3: =INDEX($Y$9:$AK$723,MATCH($CG3,$A$9:$A$723,0),MATCH(CM$2,$Y$2:$AK$2,0)) -> 3.8 | CN3: =INDEX($Y$9:$AK$723,MATCH($CG3,$A$9:$A$723,0),MATCH(CN$2,$Y$2:$AK$2,0)) -> 3.85 | CO3: =INDEX($Y$9:$AK$723,MATCH($CG3,$A$9:$A$723,0),MATCH(CO$2,$Y$2:$AK$2,0)) -> 4.02 | CP3: =INDEX($Y$9:$AK$723,MATCH($CG3,$A$9:$A$723,0),MATCH(CP$2,$Y$2:$AK$2,0)) -> 4.17 | ... CU3: =INDEX($Y$9:$AK$723,MATCH($CG3,$A$9:$A$723,0),MATCH(CU$2,$Y$2:$AK$2,0)) -> 4.99
B4: .DESC | C4: UK: 10-Yr Government Bond Yield (%) | D4: U.S.: 10-Year Treasury Note Yield at Constant Maturity ( % p.a.) | E4: Germany: 10-Yr Government Bond Yield (%) | F4: Italy: 10-Yr Government Bond Yield (%) | G4: Japan: 10-Yr Government Bond Yield (%) | H4: New Zealand: 10-Yr Government Bond Yield (%) | I4: Sweden: 10-Yr Government Bond Yield (%) | J4: Canada: 10-Yr Government Bond Yield (%) | K4: France: 10-Yr Government Bond Yield (%) | L4: Spain: 10-Yr Government Bond Yield (%) | M4: Australia: 10 Year Treasury Bond Mid Yield (% p.a.) | O4: UK: 2-Yr Government Bond Yield (%) | P4: US: 2-Yr Treasury Note Yield (%) | R4: UK: 12 Month Overnight Index Swap[Ann,Act/365]v SONIA:Mid Rate[2PM ET](%p.a) | S4: UK: 24 Month Overnight Index Swap[Ann,Act/365]v SONIA:Mid Rate[2PM ET](%p.a) | T4: U.S: OIS [Act/360 Ann] vs SOFR: 1 Year Mid [NYK/LCH, 7AM ET] (% p.a) | U4: U.S: OIS [Act/360 Ann] vs SOFR: 2 Year Mid [NYK/LCH, 7AM ET] (% p.a) | V4: Euro Area: 1 Yr Int Rt Swp[Ann,Act/360]v 3 M EURIBOR[IMM Dt 1]:Mid Rt[2PM ET](%) | W4: Euro Area: 2 Yr Int Rt Swp[Ann,Act/360]v 3 M EURIBOR[IMM Dt 1]:Mid Rt[2PM ET](%) | Y4: UK: 1-Yr Government Bond Yield (%) | Z4: UK: 2-Yr Government Bond Yield (%) | AA4: UK: 3-Yr Government Bond Yield (%) | AB4: UK: 4-Yr Government Bond Yield (%) | AC4: UK: 5-Yr Government Bond Yield (%) | AD4: UK: 6-Yr Government Bond Yield (%) | AE4: UK: 7-Yr Government Bond Yield (%) | AF4: UK: 8-Yr Government Bond Yield (%) | AG4: UK: 9-Yr Government Bond Yield (%) | AH4: UK: 10-Yr Government Bond Yield (%) | AI4: UK: 15-Yr Government Bond Yield (%) | AJ4: UK: 20-Yr Government Bond Yield (%) | AK4: UK: 30-Yr Government Bond Yield (%) | AL4: UK: Overnight Index Swap: Forward Yields, 12-Month (% p.a.) | AM4: UK: Overnight Index Swap: Forward Yields, 24-Month (% p.a.) | AN4: UK: Overnight Index Swap: Forward Yields, 36-Month (% p.a.) | AO4: UK: Overnight Index Swap: Forward Yields, 48-Month (% p.a.) | AP4: UK: Overnight Index Swap: Forward Yields, 60-Month (% p.a.) | AQ4: UK: Overnight Index Swap: Forward Yields, 6-Year (% p.a.) | BP4: 46153 | BQ4: =INDEX($BD$9:$BN$723,MATCH($BP4,$A$9:$A$723,0),MATCH(BQ$3,$BD$1:$BN$1,0))+BQ5 -> 71.00001 | BR4: =INDEX($BD$9:$BN$723,MATCH($BP4,$A$9:$A$723,0),MATCH(BR$3,$BD$1:$BN$1,0))+BR5 -> 45.00002 | BS4: =INDEX($BD$9:$BN$723,MATCH($BP4,$A$9:$A$723,0),MATCH(BS$3,$BD$1:$BN$1,0))+BS5 -> 41.00003 | BT4: =INDEX($BD$9:$BN$723,MATCH($BP4,$A$9:$A$723,0),MATCH(BT$3,$BD$1:$BN$1,0))+BT5 -> 51.00004 | BU4: =INDEX($BD$9:$BN$723,MATCH($BP4,$A$9:$A$723,0),MATCH(BU$3,$BD$1:$BN$1,0))+BU5 -> 40.10005 | BV4: =INDEX($BD$9:$BN$723,MATCH($BP4,$A$9:$A$723,0),MATCH(BV$3,$BD$1:$BN$1,0))+BV5 -> 34.00006 | BW4: =INDEX($BD$9:$BN$723,MATCH($BP4,$A$9:$A$723,0),MATCH(BW$3,$BD$1:$BN$1,0))+BW5 -> 20.00007 | BX4: =INDEX($BD$9:$BN$723,MATCH($BP4,$A$9:$A$723,0),MATCH(BX$3,$BD$1:$BN$1,0))+BX5 -> 41.00008 | ... CA4: =INDEX($BD$9:$BN$723,MATCH($BP4,$A$9:$A$723,0),MATCH(CA$3,$BD$1:$BN$1,0))+CA5 -> 34.06011 | CG4: 46153 | CH4: Latest | CI4: =INDEX($Y$9:$AK$723,MATCH($CG4,$A$9:$A$723,0),MATCH(CI$2,$Y$2:$AK$2,0)) -> 4.39 | CJ4: =INDEX($Y$9:$AK$723,MATCH($CG4,$A$9:$A$723,0),MATCH(CJ$2,$Y$2:$AK$2,0)) -> 4.48 | CK4: =INDEX($Y$9:$AK$723,MATCH($CG4,$A$9:$A$723,0),MATCH(CK$2,$Y$2:$AK$2,0)) -> 4.51 | CL4: =INDEX($Y$9:$AK$723,MATCH($CG4,$A$9:$A$723,0),MATCH(CL$2,$Y$2:$AK$2,0)) -> 4.53 | CM4: =INDEX($Y$9:$AK$723,MATCH($CG4,$A$9:$A$723,0),MATCH(CM$2,$Y$2:$AK$2,0)) -> 4.59 | CN4: =INDEX($Y$9:$AK$723,MATCH($CG4,$A$9:$A$723,0),MATCH(CN$2,$Y$2:$AK$2,0)) -> 4.63 | CO4: =INDEX($Y$9:$AK$723,MATCH($CG4,$A$9:$A$723,0),MATCH(CO$2,$Y$2:$AK$2,0)) -> 4.75 | CP4: =INDEX($Y$9:$AK$723,MATCH($CG4,$A$9:$A$723,0),MATCH(CP$2,$Y$2:$AK$2,0)) -> 4.89 | ... CU4: =INDEX($Y$9:$AK$723,MATCH($CG4,$A$9:$A$723,0),MATCH(CU$2,$Y$2:$AK$2,0)) -> 5.69
B5: .T1 | C5: 26-Jan-1994 | D5: 02-Jan-1962 | E5: 10-Jan-1994 | F5: 02-Jan-1995 | G5: 13-Sep-1985 | H5: 14-Jul-1994 | I5: 02-Jan-1992 | J5: 03-Jan-1989 | K5: 02-Feb-1994 | L5: 18-Mar-1994 | M5: 01-Mar-2006 | O5: 26-Jan-1994 | P5: 29-Sep-1986 | R5: 26-Aug-2014 | S5: 26-Aug-2014 | T5: 01-Mar-2021 | U5: 01-Mar-2021 | V5: 25-Aug-2014 | W5: 25-Aug-2014 | Y5: 16-Jul-1999 | Z5: 26-Jan-1994 | AA5: 03-Jan-1995 | AB5: 06-Mar-1995 | AC5: 03-Jan-1995 | AD5: 06-Mar-1995 | AE5: 18-Jul-1995 | AF5: 06-Mar-1995 | AG5: 06-Mar-1995 | AH5: 26-Jan-1994 | AI5: 03-Jan-1995 | AJ5: 03-Jan-1995 | AK5: 03-Jan-1995 | AL5: 02-Jan-2009 | AM5: 02-Jan-2009 | AN5: 02-Jan-2009 | AO5: 02-Jan-2009 | AP5: 02-Jan-2009 | AQ5: 02-Jan-2018 | BQ5: 1e-05 | BR5: =+BQ5+0.00001 -> 2e-05 | BS5: =+BR5+0.00001 -> 3e-05 | BT5: =+BS5+0.00001 -> 4e-05 | BU5: =+BT5+0.00001 -> 5e-05 | BV5: =+BU5+0.00001 -> 6e-05 | BW5: =+BV5+0.00001 -> 7e-05 | BX5: =+BW5+0.00001 -> 8e-05 | BY5: =+BX5+0.00001 -> 9e-05 | ... CA5: =+BZ5+0.00001 -> 0.00011
B6: .TN | C6: 11-May-2026 | D6: 11-May-2026 | E6: 11-May-2026 | F6: 11-May-2026 | G6: 11-May-2026 | H6: 11-May-2026 | I6: 11-May-2026 | J6: 11-May-2026 | K6: 11-May-2026 | L6: 11-May-2026 | M6: 11-May-2026 | O6: 11-May-2026 | P6: 11-May-2026 | R6: 11-May-2026 | S6: 11-May-2026 | T6: 11-May-2026 | U6: 11-May-2026 | V6: 11-May-2026 | W6: 11-May-2026 | Y6: 11-May-2026 | Z6: 11-May-2026 | AA6: 11-May-2026 | AB6: 11-May-2026 | AC6: 11-May-2026 | AD6: 11-May-2026 | AE6: 11-May-2026 | AF6: 11-May-2026 | AG6: 11-May-2026 | AH6: 11-May-2026 | AI6: 11-May-2026 | AJ6: 11-May-2026 | AK6: 11-May-2026 | AL6: 11-May-2026 | AM6: 11-May-2026 | AN6: 11-May-2026 | AO6: 11-May-2026 | AP6: 11-May-2026 | AQ6: 11-May-2026 | BQ6: 1 | BR6: 2 | BS6: 3 | BT6: 4 | BU6: 5 | BV6: 6 | BW6: 7 | BX6: 8 | BY6: 9 | BZ6: 10 | CA6: 11 | CH6: Diff | CI6: =CI4-CI3 -> 0.87 | CJ6: =CJ4-CJ3 -> 0.79 | CK6: =CK4-CK3 -> 0.75 | CL6: =CL4-CL3 -> 0.85 | CM6: =CM4-CM3 -> 0.79 | CN6: =CN4-CN3 -> 0.78 | CO6: =CO4-CO3 -> 0.73 | CP6: =CP4-CP3 -> 0.72 | ... CU6: =CU4-CU3 -> 0.7
B7: .LSOURCE | C7: London Stock Exchange Group | D7: U.S. Treasury | E7: London Stock Exchange Group | F7: London Stock Exchange Group | G7: London Stock Exchange Group | H7: London Stock Exchange Group | I7: London Stock Exchange Group | J7: London Stock Exchange Group | K7: London Stock Exchange Group | L7: London Stock Exchange Group | M7: Tullett Prebon Information/Haver Analytics | O7: London Stock Exchange Group | P7: London Stock Exchange Group | R7: Tullett Prebon Information/Haver Analytics | S7: Tullett Prebon Information/Haver Analytics | T7: Tullett Prebon Information | U7: Tullett Prebon Information | V7: Tullett Prebon Information/Haver Analytics | W7: Tullett Prebon Information/Haver Analytics | Y7: London Stock Exchange Group | Z7: London Stock Exchange Group | AA7: London Stock Exchange Group | AB7: London Stock Exchange Group | AC7: London Stock Exchange Group | AD7: London Stock Exchange Group | AE7: London Stock Exchange Group | AF7: London Stock Exchange Group | AG7: London Stock Exchange Group | AH7: London Stock Exchange Group | AI7: London Stock Exchange Group | AJ7: London Stock Exchange Group | AK7: London Stock Exchange Group | AL7: Bank of England | AM7: Bank of England | AN7: Bank of England | AO7: Bank of England | AP7: Bank of England | AQ7: Bank of England | BQ7: =HLOOKUP(BQ$6,$BQ$2:$CA$4,2,FALSE) -> UK | BR7: =HLOOKUP(BR$6,$BQ$2:$CA$4,2,FALSE) -> Italy | BS7: =HLOOKUP(BS$6,$BQ$2:$CA$4,2,FALSE) -> France | BT7: =HLOOKUP(BT$6,$BQ$2:$CA$4,2,FALSE) -> US | BU7: =HLOOKUP(BU$6,$BQ$2:$CA$4,2,FALSE) -> Spain | BV7: =HLOOKUP(BV$6,$BQ$2:$CA$4,2,FALSE) -> Canada | BW7: =HLOOKUP(BW$6,$BQ$2:$CA$4,2,FALSE) -> Germany | BX7: =HLOOKUP(BX$6,$BQ$2:$CA$4,2,FALSE) -> Japan | ... CA7: =HLOOKUP(CA$6,$BQ$2:$CA$4,2,FALSE) -> Sweden
B8: .DTLM | C8: May-11-2026 20:55 | D8: May-11-2026 21:02 | E8: May-11-2026 20:55 | F8: May-11-2026 20:55 | G8: May-11-2026 19:01 | H8: May-11-2026 19:01 | I8: May-11-2026 20:55 | J8: May-12-2026 01:49 | K8: May-11-2026 20:55 | L8: May-11-2026 20:55 | M8: May-11-2026 12:04 | O8: May-11-2026 20:55 | P8: May-12-2026 01:49 | R8: May-11-2026 19:04 | S8: May-11-2026 19:04 | T8: May-11-2026 12:04 | U8: May-11-2026 12:04 | V8: May-11-2026 19:04 | W8: May-11-2026 19:04 | Y8: May-11-2026 20:55 | Z8: May-11-2026 20:55 | AA8: May-11-2026 20:55 | AB8: May-11-2026 20:55 | AC8: May-11-2026 20:55 | AD8: May-11-2026 20:55 | AE8: May-11-2026 20:55 | AF8: May-11-2026 20:55 | AG8: May-11-2026 20:55 | AH8: May-11-2026 20:55 | AI8: May-11-2026 20:55 | AJ8: May-11-2026 20:55 | AK8: May-11-2026 20:55 | AL8: May-12-2026 10:28 | AM8: May-12-2026 10:28 | AN8: May-12-2026 10:28 | AO8: May-12-2026 10:28 | AP8: May-12-2026 10:28 | AQ8: May-12-2026 10:28 | BQ8: =HLOOKUP(BQ$6,$BQ$2:$CA$4,3,FALSE) -> 71.00001 | BR8: =HLOOKUP(BR$6,$BQ$2:$CA$4,3,FALSE) -> 51.00004 | BS8: =HLOOKUP(BS$6,$BQ$2:$CA$4,3,FALSE) -> 46.00009 | BT8: =HLOOKUP(BT$6,$BQ$2:$CA$4,3,FALSE) -> 45.00002 | BU8: =HLOOKUP(BU$6,$BQ$2:$CA$4,3,FALSE) -> 41.0001 | BV8: =HLOOKUP(BV$6,$BQ$2:$CA$4,3,FALSE) -> 41.00008 | BW8: =HLOOKUP(BW$6,$BQ$2:$CA$4,3,FALSE) -> 41.00003 | BX8: =HLOOKUP(BX$6,$BQ$2:$CA$4,3,FALSE) -> 40.10005 | ... CA8: =HLOOKUP(CA$6,$BQ$2:$CA$4,3,FALSE) -> 20.00007
A9: 45292 | B9: 240101 | C9: #N/A | D9: #N/A | E9: 2.02 | F9: 3.7 | G9: 0.619 | H9: #N/A | I9: 2.03 | J9: #N/A | K9: 2.56 | L9: 2.99 | M9: 3.9545 | O9: #N/A | P9: #N/A | R9: 4.7307 | S9: 4.0314 | T9: 4.766 | U9: 4.08 | V9: 2.94 | W9: 2.442 | Y9: 4.73 | Z9: #N/A | AA9: 3.59 | AB9: 3.41 | AC9: 3.46 | AD9: 3.35 | AE9: 3.37 | AF9: 3.45 | AG9: 3.44 | AH9: #N/A | AI9: 3.92 | AJ9: 4.09 | AK9: #N/A | AL9: #N/A | AM9: #N/A | AN9: #N/A | AO9: #N/A | AP9: #N/A | AQ9: #N/A | AT9: =(2*S9)-R9 -> 3.3321 | AU9: =(2*U9)-T9 -> 3.394 | AV9: =(2*W9)-V9 -> 1.944 | AX9: =(C9-D9)*100 -> #N/A | AY9: =(AT9-AU9)*100 -> -6.19 | BA9: =C9-O9 -> #N/A | BB9: =D9-P9 -> #N/A
A10: 45293 | B10: 240102 | C10: 3.65 | D10: 3.95 | E10: 2.07 | F10: 3.72 | G10: 0.625 | H10: 4.41 | I10: 2.06 | J10: 3.18 | K10: 2.6 | L10: 3.03 | M10: 4.0058 | O10: 4.06 | P10: 4.33 | R10: 4.7456 | S10: 4.0735 | T10: 4.793 | U10: 4.128 | V10: 2.975 | W10: 2.486 | Y10: 4.79 | Z10: 4.06 | AA10: 3.69 | AB10: 3.5 | AC10: 3.55 | AD10: 3.46 | AE10: 3.47 | AF10: 3.56 | AG10: 3.55 | AH10: 3.65 | AI10: 4.04 | AJ10: 4.22 | AK10: 4.28 | AL10: 3.8133507 | AM10: 3.122496 | AN10: 2.9397965 | AO10: 2.9139373 | AP10: 2.976615 | AQ10: 3.0953136 | AT10: =(2*S10)-R10 -> 3.4014 | AU10: =(2*U10)-T10 -> 3.463 | AV10: =(2*W10)-V10 -> 1.997 | AX10: =(C10-D10)*100 -> -30 | AY10: =(AT10-AU10)*100 -> -6.16 | BA10: =C10-O10 -> -0.41 | BB10: =D10-P10 -> -0.38
A11: 45294 | B11: 240103 | C11: 3.61 | D11: 3.91 | E11: 2 | F11: 3.69 | G11: 0.625 | H11: 4.53 | I11: 2.06 | J11: 3.16 | K11: 2.55 | L11: 2.99 | M11: 4.0489 | O11: 4.07 | P11: 4.32 | R11: 4.7514 | S11: 4.0626 | T11: 4.822 | U11: 4.166 | V11: 2.94 | W11: 2.428 | Y11: 4.82 | Z11: 4.07 | AA11: 3.68 | AB11: 3.51 | AC11: 3.55 | AD11: 3.47 | AE11: 3.45 | AF11: 3.54 | AG11: 3.52 | AH11: 3.61 | AI11: 3.99 | AJ11: 4.19 | AK11: 4.26 | AL11: 3.8103909 | AM11: 3.0582151 | AN11: 2.9010166 | AO11: 2.8980372 | AP11: 2.9573435 | AQ11: 3.066086 | AT11: =(2*S11)-R11 -> 3.3738 | AU11: =(2*U11)-T11 -> 3.51 | AV11: =(2*W11)-V11 -> 1.916 | AX11: =(C11-D11)*100 -> -30 | AY11: =(AT11-AU11)*100 -> -13.62 | BA11: =C11-O11 -> -0.46 | BB11: =D11-P11 -> -0.41
A12: 45295 | B12: 240104 | C12: 3.74 | D12: 3.99 | E12: 2.13 | F12: 3.82 | G12: 0.622 | H12: 4.57 | I12: 2.12 | J12: 3.24 | K12: 2.68 | L12: 3.12 | M12: 4.048 | O12: 4.22 | P12: 4.38 | R12: 4.811 | S12: 4.1761 | T12: 4.839 | U12: 4.172 | V12: 3.062 | W12: 2.579 | Y12: 4.96 | Z12: 4.22 | AA12: 3.82 | AB12: 3.66 | AC12: 3.7 | AD12: 3.61 | AE12: 3.59 | AF12: 3.67 | AG12: 3.65 | AH12: 3.74 | AI12: 4.12 | AJ12: 4.3 | AK12: 4.38 | AL12: 3.9458216 | AM12: 3.2268182 | AN12: 3.0787962 | AO12: 3.071935 | AP12: 3.1227582 | AQ12: 3.2155848 | AT12: =(2*S12)-R12 -> 3.5412 | AU12: =(2*U12)-T12 -> 3.505 | AV12: =(2*W12)-V12 -> 2.096 | AX12: =(C12-D12)*100 -> -25 | AY12: =(AT12-AU12)*100 -> 3.62 | BA12: =C12-O12 -> -0.48 | BB12: =D12-P12 -> -0.39
A13: 45296 | B13: 240105 | C13: 3.81 | D13: 4.05 | E13: 2.18 | F13: 3.86 | G13: 0.605 | H13: 4.63 | I13: 2.21 | J13: 3.26 | K13: 2.72 | L13: 3.17 | M13: 4.1283 | O13: 4.24 | P13: 4.39 | R13: 4.8442 | S13: 4.2399 | T13: 4.883 | U13: 4.258 | V13: 3.099 | W13: 2.632 | Y13: 4.93 | Z13: 4.24 | AA13: 3.9 | AB13: 3.74 | AC13: 3.78 | AD13: 3.69 | AE13: 3.66 | AF13: 3.74 | AG13: 3.73 | AH13: 3.81 | AI13: 4.17 | AJ13: 4.35 | AK13: 4.42 | AL13: 4.0318583 | AM13: 3.3301963 | AN13: 3.1663868 | AO13: 3.1551932 | AP13: 3.1965007 | AQ13: 3.2772656 | AT13: =(2*S13)-R13 -> 3.6356 | AU13: =(2*U13)-T13 -> 3.633 | AV13: =(2*W13)-V13 -> 2.165 | AX13: =(C13-D13)*100 -> -24 | AY13: =(AT13-AU13)*100 -> 0.26 | BA13: =C13-O13 -> -0.43 | BB13: =D13-P13 -> -0.34
A14: =+A9+7 -> 45299 | B14: 240108 | C14: 3.77 | D14: 4.01 | E14: 2.14 | F14: 3.82 | G14: 0.603 | H14: 4.68 | I14: 2.21 | J14: 3.25 | K14: 2.67 | L14: 3.14 | M14: 4.1613 | O14: 4.19 | P14: 4.35 | R14: 4.8303 | S14: 4.2074 | T14: 4.86 | U14: 4.23 | V14: 3.082 | W14: 2.6 | Y14: 4.83 | Z14: 4.19 | AA14: 3.86 | AB14: 3.7 | AC14: 3.72 | AD14: 3.64 | AE14: 3.62 | AF14: 3.7 | AG14: 3.69 | AH14: 3.77 | AI14: 4.12 | AJ14: 4.31 | AK14: 4.38 | AL14: 3.9915985 | AM14: 3.3028128 | AN14: 3.1397409 | AO14: 3.1224812 | AP14: 3.1630678 | AQ14: 3.2511539 | AT14: =(2*S14)-R14 -> 3.5845 | AU14: =(2*U14)-T14 -> 3.6 | AV14: =(2*W14)-V14 -> 2.118 | AX14: =(C14-D14)*100 -> -24 | AY14: =(AT14-AU14)*100 -> -1.55 | BA14: =C14-O14 -> -0.42 | BB14: =D14-P14 -> -0.34
A15: =+A10+7 -> 45300 | B15: 240109 | C15: 3.79 | D15: 4.02 | E15: 2.19 | F15: 3.85 | G15: 0.588 | H15: 4.65 | I15: 2.27 | J15: 3.22 | K15: 2.72 | L15: 3.16 | M15: 4.1051 | O15: 4.21 | P15: 4.37 | R15: 4.8374 | S15: 4.2219 | T15: 4.854 | U15: 4.222 | V15: 3.136 | W15: 2.668 | Y15: 4.8 | Z15: 4.21 | AA15: 3.87 | AB15: 3.72 | AC15: 3.73 | AD15: 3.66 | AE15: 3.64 | AF15: 3.72 | AG15: 3.7 | AH15: 3.79 | AI15: 4.15 | AJ15: 4.32 | AK15: 4.4 | AL15: 4.0132622 | AM15: 3.3161053 | AN15: 3.1342282 | AO15: 3.1158539 | AP15: 3.1673712 | AQ15: 3.2636287 | AT15: =(2*S15)-R15 -> 3.6064 | AU15: =(2*U15)-T15 -> 3.59 | AV15: =(2*W15)-V15 -> 2.2 | AX15: =(C15-D15)*100 -> -23 | AY15: =(AT15-AU15)*100 -> 1.64 | BA15: =C15-O15 -> -0.42 | BB15: =D15-P15 -> -0.35
A16: =+A11+7 -> 45301 | B16: 240110 | C16: 3.82 | D16: 4.04 | E16: 2.23 | F16: 3.85 | G16: 0.584 | H16: 4.74 | I16: 2.25 | J16: 3.28 | K16: 2.76 | L16: 3.19 | M16: 4.121 | O16: 4.22 | P16: 4.37 | R16: 4.8524 | S16: 4.2558 | T16: 4.821 | U16: 4.187 | V16: 3.165 | W16: 2.702 | Y16: 4.86 | Z16: 4.22 | AA16: 3.88 | AB16: 3.74 | AC16: 3.75 | AD16: 3.68 | AE16: 3.67 | AF16: 3.76 | AG16: 3.74 | AH16: 3.82 | AI16: 4.18 | AJ16: 4.34 | AK16: 4.42 | AL16: 4.0516976 | AM16: 3.367845 | AN16: 3.1564854 | AO16: 3.1247781 | AP16: 3.1751377 | AQ16: 3.2731349 | AT16: =(2*S16)-R16 -> 3.6592 | AU16: =(2*U16)-T16 -> 3.553 | AV16: =(2*W16)-V16 -> 2.239 | AX16: =(C16-D16)*100 -> -22 | AY16: =(AT16-AU16)*100 -> 10.62 | BA16: =C16-O16 -> -0.4 | BB16: =D16-P16 -> -0.33
A17: =+A12+7 -> 45302 | B17: 240111 | C17: 3.85 | D17: 3.98 | E17: 2.19 | F17: 3.81 | G17: 0.594 | H17: 4.72 | I17: 2.23 | J17: 3.25 | K17: 2.73 | L17: 3.11 | M17: 4.1101 | O17: 4.25 | P17: 4.26 | R17: 4.8273 | S17: 4.2359 | T17: 4.804 | U17: 4.162 | V17: 3.138 | W17: 2.67 | Y17: 4.93 | Z17: 4.25 | AA17: 3.88 | AB17: 3.74 | AC17: 3.76 | AD17: 3.7 | AE17: 3.7 | AF17: 3.79 | AG17: 3.77 | AH17: 3.85 | AI17: 4.2 | AJ17: 4.36 | AK17: 4.44 | AL17: 4.0309256 | AM17: 3.3363711 | AN17: 3.180615 | AO17: 3.1794607 | AP17: 3.2379589 | AQ17: 3.3335096 | AT17: =(2*S17)-R17 -> 3.6445 | AU17: =(2*U17)-T17 -> 3.52 | AV17: =(2*W17)-V17 -> 2.202 | AX17: =(C17-D17)*100 -> -13 | AY17: =(AT17-AU17)*100 -> 12.45 | BA17: =C17-O17 -> -0.4 | BB17: =D17-P17 -> -0.28
A18: =+A13+7 -> 45303 | B18: 240112 | C18: 3.8 | D18: 3.96 | E18: 2.16 | F18: 3.75 | G18: 0.58 | H18: 4.64 | I18: 2.15 | J18: 3.22 | K18: 2.68 | L18: 3.1 | M18: 4.0743 | O18: 4.18 | P18: 4.14 | R18: 4.7549 | S18: 4.139 | T18: 4.737 | U18: 4.094 | V18: 3.04 | W18: 2.566 | Y18: 4.89 | Z18: 4.18 | AA18: 3.78 | AB18: 3.64 | AC18: 3.67 | AD18: 3.62 | AE18: 3.63 | AF18: 3.73 | AG18: 3.71 | AH18: 3.8 | AI18: 4.16 | AJ18: 4.34 | AK18: 4.43 | AL18: 3.906338 | AM18: 3.2413816 | AN18: 3.0985542 | AO18: 3.1066479 | AP18: 3.1735852 | AQ18: 3.2788019 | AT18: =(2*S18)-R18 -> 3.5231 | AU18: =(2*U18)-T18 -> 3.451 | AV18: =(2*W18)-V18 -> 2.092 | AX18: =(C18-D18)*100 -> -16 | AY18: =(AT18-AU18)*100 -> 7.21 | BA18: =C18-O18 -> -0.38 | BB18: =D18-P18 -> -0.18
A19: =+A14+7 -> 45306 | B19: 240115 | C19: 3.8 | D19: #N/A | E19: 2.2 | F19: 3.81 | G19: 0.558 | H19: 4.62 | I19: 2.16 | J19: 3.23 | K19: 2.73 | L19: 3.15 | M19: 4.078 | O19: 4.16 | P19: #N/A | R19: 4.7449 | S19: 4.1148 | T19: #N/A | U19: #N/A | V19: 3.103 | W19: 2.621 | Y19: 4.92 | Z19: 4.16 | AA19: 3.78 | AB19: 3.64 | AC19: 3.68 | AD19: 3.63 | AE19: 3.63 | AF19: 3.74 | AG19: 3.71 | AH19: 3.8 | AI19: 4.18 | AJ19: 4.36 | AK19: 4.46 | AL19: 3.882187 | AM19: 3.2212368 | AN19: 3.0832033 | AO19: 3.0955378 | AP19: 3.1690068 | AQ19: 3.2852854 | AT19: =(2*S19)-R19 -> 3.4847 | AU19: =(2*U19)-T19 -> #N/A | AV19: =(2*W19)-V19 -> 2.139 | AX19: =(C19-D19)*100 -> #N/A | AY19: =(AT19-AU19)*100 -> #N/A | BA19: =C19-O19 -> -0.36 | BB19: =D19-P19 -> #N/A
A20: =+A15+7 -> 45307 | B20: 240116 | C20: 3.83 | D20: 4.07 | E20: 2.25 | F20: 3.85 | G20: 0.591 | H20: 4.66 | I20: 2.2 | J20: 3.36 | K20: 2.78 | L20: 3.19 | M20: 4.1566 | O20: 4.19 | P20: 4.23 | R20: 4.7622 | S20: 4.1407 | T20: 4.683 | U20: 4.041 | V20: 3.124 | W20: 2.637 | Y20: 4.98 | Z20: 4.19 | AA20: 3.8 | AB20: 3.66 | AC20: 3.7 | AD20: 3.65 | AE20: 3.65 | AF20: 3.76 | AG20: 3.74 | AH20: 3.83 | AI20: 4.22 | AJ20: 4.41 | AK20: 4.51 | AL20: 3.8892679 | AM20: 3.2276975 | AN20: 3.1136786 | AO20: 3.1338846 | AP20: 3.2156826 | AQ20: 3.3398985 | AT20: =(2*S20)-R20 -> 3.5192 | AU20: =(2*U20)-T20 -> 3.399 | AV20: =(2*W20)-V20 -> 2.15 | AX20: =(C20-D20)*100 -> -24 | AY20: =(AT20-AU20)*100 -> 12.02 | BA20: =C20-O20 -> -0.36 | BB20: =D20-P20 -> -0.16
A21: =+A16+7 -> 45308 | B21: 240117 | C21: 3.98 | D21: 4.1 | E21: 2.28 | F21: 3.92 | G21: 0.609 | H21: 4.67 | I21: 2.25 | J21: 3.44 | K21: 2.82 | L21: 3.25 | M21: 4.2117 | O21: 4.38 | P21: 4.35 | R21: 4.9161 | S21: 4.3635 | T21: 4.758 | U21: 4.119 | V21: 3.221 | W21: 2.739 | Y21: 5.06 | Z21: 4.38 | AA21: 4 | AB21: 3.86 | AC21: 3.91 | AD21: 3.83 | AE21: 3.82 | AF21: 3.92 | AG21: 3.9 | AH21: 3.98 | AI21: 4.37 | AJ21: 4.54 | AK21: 4.64 | AL21: 4.1724997 | AM21: 3.5121132 | AN21: 3.3242844 | AO21: 3.3045953 | AP21: 3.3656448 | AQ21: 3.4747675 | AT21: =(2*S21)-R21 -> 3.8109 | AU21: =(2*U21)-T21 -> 3.48 | AV21: =(2*W21)-V21 -> 2.257 | AX21: =(C21-D21)*100 -> -12 | AY21: =(AT21-AU21)*100 -> 33.09 | BA21: =C21-O21 -> -0.4 | BB21: =D21-P21 -> -0.25
A22: =+A17+7 -> 45309 | B22: 240118 | C22: 3.94 | D22: 4.14 | E22: 2.32 | F22: 3.94 | G22: 0.643 | H22: 4.73 | I22: 2.26 | J22: 3.49 | K22: 2.85 | L22: 3.27 | M22: 4.2636 | O22: 4.31 | P22: 4.36 | R22: 4.8737 | S22: 4.2944 | T22: 4.783 | U22: 4.158 | V22: 3.197 | W22: 2.722 | Y22: 4.97 | Z22: 4.31 | AA22: 3.95 | AB22: 3.81 | AC22: 3.84 | AD22: 3.77 | AE22: 3.77 | AF22: 3.87 | AG22: 3.85 | AH22: 3.94 | AI22: 4.33 | AJ22: 4.51 | AK22: 4.61 | AL22: 4.1179306 | AM22: 3.4239054 | AN22: 3.2622235 | AO22: 3.2576652 | AP22: 3.3228304 | AQ22: 3.4345602 | AT22: =(2*S22)-R22 -> 3.7151 | AU22: =(2*U22)-T22 -> 3.533 | AV22: =(2*W22)-V22 -> 2.247 | AX22: =(C22-D22)*100 -> -20 | AY22: =(AT22-AU22)*100 -> 18.21 | BA22: =C22-O22 -> -0.37 | BB22: =D22-P22 -> -0.22
A23: =+A18+7 -> 45310 | B23: 240119 | C23: 3.92 | D23: 4.15 | E23: 2.3 | F23: 3.88 | G23: 0.664 | H23: 4.79 | I23: 2.3 | J23: 3.49 | K23: 2.83 | L23: 3.23 | M23: 4.2964 | O23: 4.29 | P23: 4.41 | R23: 4.8871 | S23: 4.3261 | T23: 4.803 | U23: 4.195 | V23: 3.265 | W23: 2.792 | Y23: 4.95 | Z23: 4.29 | AA23: 3.95 | AB23: 3.8 | AC23: 3.84 | AD23: 3.75 | AE23: 3.75 | AF23: 3.85 | AG23: 3.83 | AH23: 3.92 | AI23: 4.29 | AJ23: 4.46 | AK23: 4.56 | AL23: 4.1495841 | AM23: 3.4724444 | AN23: 3.2869698 | AO23: 3.2554136 | AP23: 3.2984134 | AQ23: 3.3935567 | AT23: =(2*S23)-R23 -> 3.7651 | AU23: =(2*U23)-T23 -> 3.587 | AV23: =(2*W23)-V23 -> 2.319 | AX23: =(C23-D23)*100 -> -23 | AY23: =(AT23-AU23)*100 -> 17.81 | BA23: =C23-O23 -> -0.37 | BB23: =D23-P23 -> -0.26
A24: =+A19+7 -> 45313 | B24: 240122 | C24: 3.91 | D24: 4.11 | E24: 2.26 | F24: 3.85 | G24: 0.653 | H24: 4.72 | I24: 2.29 | J24: 3.46 | K24: 2.79 | L24: 3.2 | M24: 4.23 | O24: 4.31 | P24: 4.38 | R24: 4.8696 | S24: 4.3097 | T24: 4.836 | U24: 4.221 | V24: 3.242 | W24: 2.751 | Y24: 4.95 | Z24: 4.31 | AA24: 3.97 | AB24: 3.82 | AC24: 3.85 | AD24: 3.77 | AE24: 3.75 | AF24: 3.84 | AG24: 3.82 | AH24: 3.91 | AI24: 4.27 | AJ24: 4.44 | AK24: 4.54 | AL24: 4.1228926 | AM24: 3.4913458 | AN24: 3.2940466 | AO24: 3.2473597 | AP24: 3.2848664 | AQ24: 3.3810345 | AT24: =(2*S24)-R24 -> 3.7498 | AU24: =(2*U24)-T24 -> 3.606 | AV24: =(2*W24)-V24 -> 2.26 | AX24: =(C24-D24)*100 -> -20 | AY24: =(AT24-AU24)*100 -> 14.38 | BA24: =C24-O24 -> -0.4 | BB24: =D24-P24 -> -0.27
A25: =+A20+7 -> 45314 | B25: 240123 | C25: 4 | D25: 4.14 | E25: 2.35 | F25: 3.93 | G25: 0.673 | H25: 4.7 | I25: 2.34 | J25: 3.47 | K25: 2.84 | L25: 3.27 | M25: 4.193 | O25: 4.38 | P25: 4.39 | R25: 4.9142 | S25: 4.3742 | T25: 4.849 | U25: 4.241 | V25: 3.259 | W25: 2.772 | Y25: 5.1 | Z25: 4.38 | AA25: 4.06 | AB25: 3.91 | AC25: 3.94 | AD25: 3.86 | AE25: 3.84 | AF25: 3.93 | AG25: 3.9 | AH25: 4 | AI25: 4.34 | AJ25: 4.51 | AK25: 4.59 | AL25: 4.2025817 | AM25: 3.5704832 | AN25: 3.3760902 | AO25: 3.3337293 | AP25: 3.3717084 | AQ25: 3.4630552 | AT25: =(2*S25)-R25 -> 3.8342 | AU25: =(2*U25)-T25 -> 3.633 | AV25: =(2*W25)-V25 -> 2.285 | AX25: =(C25-D25)*100 -> -14 | AY25: =(AT25-AU25)*100 -> 20.12 | BA25: =C25-O25 -> -0.38 | BB25: =D25-P25 -> -0.25
A26: =+A21+7 -> 45315 | B26: 240124 | C26: 4 | D26: 4.18 | E26: 2.35 | F26: 3.9 | G26: 0.719 | H26: 4.76 | I26: 2.35 | J26: 3.5 | K26: 2.85 | L26: 3.28 | M26: 4.2311 | O26: 4.38 | P26: 4.38 | R26: 4.9356 | S26: 4.3973 | T26: 4.814 | U26: 4.196 | V26: 3.251 | W26: 2.776 | Y26: 4.95 | Z26: 4.38 | AA26: 4.08 | AB26: 3.92 | AC26: 3.95 | AD26: 3.87 | AE26: 3.84 | AF26: 3.93 | AG26: 3.91 | AH26: 4 | AI26: 4.34 | AJ26: 4.51 | AK26: 4.59 | AL26: 4.2413794 | AM26: 3.5977218 | AN26: 3.3956214 | AO26: 3.3450975 | AP26: 3.3736588 | AQ26: 3.4577191 | AT26: =(2*S26)-R26 -> 3.859 | AU26: =(2*U26)-T26 -> 3.578 | AV26: =(2*W26)-V26 -> 2.301 | AX26: =(C26-D26)*100 -> -18 | AY26: =(AT26-AU26)*100 -> 28.1 | BA26: =C26-O26 -> -0.38 | BB26: =D26-P26 -> -0.2
A27: =+A22+7 -> 45316 | B27: 240125 | C27: 3.99 | D27: 4.14 | E27: 2.29 | F27: 3.83 | G27: 0.745 | H27: 4.76 | I27: 2.33 | J27: 3.48 | K27: 2.78 | L27: 3.18 | M27: 4.239 | O27: 4.37 | P27: 4.31 | R27: 4.9043 | S27: 4.359 | T27: 4.828 | U27: 4.228 | V27: 3.153 | W27: 2.664 | Y27: 4.93 | Z27: 4.37 | AA27: 4.04 | AB27: 3.89 | AC27: 3.92 | AD27: 3.85 | AE27: 3.83 | AF27: 3.92 | AG27: 3.9 | AH27: 3.99 | AI27: 4.34 | AJ27: 4.51 | AK27: 4.6 | AL27: 4.1762114 | AM27: 3.5261338 | AN27: 3.372546 | AO27: 3.3486961 | AP27: 3.3895437 | AQ27: 3.4778425 | AT27: =(2*S27)-R27 -> 3.8137 | AU27: =(2*U27)-T27 -> 3.628 | AV27: =(2*W27)-V27 -> 2.175 | AX27: =(C27-D27)*100 -> -15 | AY27: =(AT27-AU27)*100 -> 18.57 | BA27: =C27-O27 -> -0.38 | BB27: =D27-P27 -> -0.17
A28: =+A23+7 -> 45317 | B28: 240126 | C28: 3.97 | D28: 4.15 | E28: 2.3 | F28: 3.83 | G28: 0.716 | H28: 4.72 | I28: 2.36 | J28: 3.52 | K28: 2.79 | L28: 3.21 | M28: 4.239 | O28: 4.34 | P28: 4.37 | R28: 4.8807 | S28: 4.3207 | T28: 4.782 | U28: 4.168 | V28: 3.167 | W28: 2.689 | Y28: 4.89 | Z28: 4.34 | AA28: 4.01 | AB28: 3.85 | AC28: 3.89 | AD28: 3.82 | AE28: 3.81 | AF28: 3.91 | AG28: 3.88 | AH28: 3.97 | AI28: 4.33 | AJ28: 4.5 | AK28: 4.59 | AL28: 4.1361011 | AM28: 3.4827399 | AN28: 3.3349198 | AO28: 3.3284474 | AP28: 3.3763003 | AQ28: 3.4670205 | AT28: =(2*S28)-R28 -> 3.7607 | AU28: =(2*U28)-T28 -> 3.554 | AV28: =(2*W28)-V28 -> 2.211 | AX28: =(C28-D28)*100 -> -18 | AY28: =(AT28-AU28)*100 -> 20.67 | BA28: =C28-O28 -> -0.37 | BB28: =D28-P28 -> -0.22
A29: =+A24+7 -> 45320 | B29: 240129 | C29: 3.88 | D29: 4.08 | E29: 2.23 | F29: 3.74 | G29: 0.712 | H29: 4.75 | I29: 2.35 | J29: 3.45 | K29: 2.72 | L29: 3.12 | M29: 4.2193 | O29: 4.27 | P29: 4.32 | R29: 4.8403 | S29: #N/A | T29: 4.788 | U29: 4.181 | V29: 3.123 | W29: 2.632 | Y29: 4.87 | Z29: 4.27 | AA29: 3.94 | AB29: 3.78 | AC29: 3.81 | AD29: 3.74 | AE29: 3.73 | AF29: 3.82 | AG29: 3.8 | AH29: 3.88 | AI29: 4.25 | AJ29: 4.43 | AK29: 4.51 | AL29: 4.0609841 | AM29: 3.4125505 | AN29: 3.2642552 | AO29: 3.2506235 | AP29: 3.2913976 | AQ29: 3.3833081 | AT29: =(2*S29)-R29 -> #N/A | AU29: =(2*U29)-T29 -> 3.574 | AV29: =(2*W29)-V29 -> 2.141 | AX29: =(C29-D29)*100 -> -20 | AY29: =(AT29-AU29)*100 -> #N/A | BA29: =C29-O29 -> -0.39 | BB29: =D29-P29 -> -0.24
A30: =+A25+7 -> 45321 | B30: 240130 | C30: 3.9 | D30: 4.06 | E30: 2.27 | F30: 3.81 | G30: 0.702 | H30: 4.71 | I30: 2.34 | J30: 3.41 | K30: 2.76 | L30: 3.16 | M30: 4.1426 | O30: 4.33 | P30: 4.36 | R30: 4.8761 | S30: 4.318 | T30: 4.79 | U30: 4.173 | V30: 3.167 | W30: 2.68 | Y30: 4.93 | Z30: 4.33 | AA30: 4 | AB30: 3.84 | AC30: 3.86 | AD30: 3.77 | AE30: 3.76 | AF30: 3.85 | AG30: 3.82 | AH30: 3.9 | AI30: 4.27 | AJ30: 4.45 | AK30: 4.53 | AL30: 4.1444715 | AM30: 3.4983825 | AN30: 3.2994999 | AO30: 3.2551629 | AP30: 3.2980624 | AQ30: 3.3986548 | AT30: =(2*S30)-R30 -> 3.7599 | AU30: =(2*U30)-T30 -> 3.556 | AV30: =(2*W30)-V30 -> 2.193 | AX30: =(C30-D30)*100 -> -16 | AY30: =(AT30-AU30)*100 -> 20.39 | BA30: =C30-O30 -> -0.43 | BB30: =D30-P30 -> -0.3
A31: =+A26+7 -> 45322 | B31: 240131 | C31: 3.79 | D31: 3.99 | E31: 2.17 | F31: 3.72 | G31: 0.724 | H31: 4.63 | I31: 2.19 | J31: 3.32 | K31: 2.67 | L31: 3.12 | M31: 4.0135 | O31: 4.22 | P31: 4.23 | R31: 4.7962 | S31: 4.213 | T31: 4.805 | U31: 4.188 | V31: 3.108 | W31: 2.604 | Y31: 4.81 | Z31: 4.22 | AA31: 3.87 | AB31: 3.71 | AC31: 3.74 | AD31: 3.65 | AE31: 3.63 | AF31: 3.73 | AG31: 3.7 | AH31: 3.79 | AI31: 4.16 | AJ31: 4.35 | AK31: 4.45 | AL31: 4.0272195 | AM31: 3.3484123 | AN31: 3.1736842 | AO31: 3.1499939 | AP31: 3.1941967 | AQ31: 3.2908242 | AT31: =(2*S31)-R31 -> 3.6298 | AU31: =(2*U31)-T31 -> 3.571 | AV31: =(2*W31)-V31 -> 2.1 | AX31: =(C31-D31)*100 -> -20 | AY31: =(AT31-AU31)*100 -> 5.88 | BA31: =C31-O31 -> -0.43 | BB31: =D31-P31 -> -0.24
A32: =+A27+7 -> 45323 | B32: 240201 | C32: 3.76 | D32: 3.87 | E32: 2.16 | F32: 3.72 | G32: 0.686 | H32: 4.61 | I32: 2.16 | J32: 3.27 | K32: 2.66 | L32: 3.1 | M32: 4.0154 | O32: 4.24 | P32: 4.19 | R32: 4.8297 | S32: 4.2253 | T32: 4.73 | U32: 4.079 | V32: 3.156 | W32: 2.643 | Y32: 4.81 | Z32: 4.24 | AA32: 3.85 | AB32: 3.69 | AC32: 3.71 | AD32: 3.62 | AE32: 3.6 | AF32: 3.7 | AG32: 3.67 | AH32: 3.76 | AI32: 4.14 | AJ32: 4.33 | AK32: 4.43 | AL32: 4.0357457 | AM32: 3.290833 | AN32: 3.1267148 | AO32: 3.1156765 | AP32: 3.1671779 | AQ32: 3.2647526 | AT32: =(2*S32)-R32 -> 3.6209 | AU32: =(2*U32)-T32 -> 3.428 | AV32: =(2*W32)-V32 -> 2.13 | AX32: =(C32-D32)*100 -> -11 | AY32: =(AT32-AU32)*100 -> 19.29 | BA32: =C32-O32 -> -0.48 | BB32: =D32-P32 -> -0.32
A33: =+A28+7 -> 45324 | B33: 240202 | C33: 3.92 | D33: 4.03 | E33: 2.23 | F33: 3.82 | G33: 0.651 | H33: 4.6 | I33: 2.25 | J33: 3.38 | K33: 2.74 | L33: 3.16 | M33: 3.9823 | O33: 4.43 | P33: 4.37 | R33: 4.9085 | S33: 4.3523 | T33: 4.734 | U33: 4.084 | V33: 3.253 | W33: 2.745 | Y33: 4.96 | Z33: 4.43 | AA33: 4.05 | AB33: 3.89 | AC33: 3.91 | AD33: 3.81 | AE33: 3.78 | AF33: 3.86 | AG33: 3.83 | AH33: 3.92 | AI33: 4.28 | AJ33: 4.46 | AK33: 4.55 | AL33: 4.2314125 | AM33: 3.5046886 | AN33: 3.3004236 | AO33: 3.2740175 | AP33: 3.3153328 | AQ33: 3.4043849 | AT33: =(2*S33)-R33 -> 3.7961 | AU33: =(2*U33)-T33 -> 3.434 | AV33: =(2*W33)-V33 -> 2.237 | AX33: =(C33-D33)*100 -> -11 | AY33: =(AT33-AU33)*100 -> 36.21 | BA33: =C33-O33 -> -0.51 | BB33: =D33-P33 -> -0.34
A34: =+A29+7 -> 45327 | B34: 240205 | C34: 4 | D34: 4.17 | E34: 2.32 | F34: 3.87 | G34: 0.714 | H34: 4.71 | I34: 2.27 | J34: 3.51 | K34: 2.82 | L34: 3.23 | M34: 4.0996 | O34: 4.49 | P34: 4.47 | R34: 4.9633 | S34: 4.451 | T34: 4.911 | U34: 4.302 | V34: 3.281 | W34: 2.791 | Y34: 4.92 | Z34: 4.49 | AA34: 4.12 | AB34: 3.96 | AC34: 3.98 | AD34: 3.89 | AE34: 3.86 | AF34: 3.94 | AG34: 3.91 | AH34: 4 | AI34: 4.35 | AJ34: 4.52 | AK34: 4.61 | AL34: 4.2995466 | AM34: 3.6350742 | AN34: 3.4230267 | AO34: 3.3576259 | AP34: 3.3761608 | AQ34: 3.4611283 | AT34: =(2*S34)-R34 -> 3.9387 | AU34: =(2*U34)-T34 -> 3.693 | AV34: =(2*W34)-V34 -> 2.301 | AX34: =(C34-D34)*100 -> -17 | AY34: =(AT34-AU34)*100 -> 24.57 | BA34: =C34-O34 -> -0.49 | BB34: =D34-P34 -> -0.3
A35: =+A30+7 -> 45328 | B35: 240206 | C35: 3.94 | D35: 4.09 | E35: 2.28 | F35: 3.84 | G35: 0.726 | H35: 4.7 | I35: 2.28 | J35: 3.43 | K35: 2.79 | L35: 3.19 | M35: 4.1337 | O35: 4.43 | P35: 4.41 | R35: 4.9409 | S35: 4.419 | T35: 4.908 | U35: 4.322 | V35: 3.256 | W35: 2.764 | Y35: 4.76 | Z35: 4.43 | AA35: 4.08 | AB35: 3.92 | AC35: 3.94 | AD35: 3.84 | AE35: 3.81 | AF35: 3.89 | AG35: 3.85 | AH35: 3.94 | AI35: 4.29 | AJ35: 4.45 | AK35: 4.54 | AL35: 4.2673702 | AM35: 3.5957926 | AN35: 3.3766193 | AO35: 3.3052161 | AP35: 3.3236646 | AQ35: 3.4014301 | AT35: =(2*S35)-R35 -> 3.8971 | AU35: =(2*U35)-T35 -> 3.736 | AV35: =(2*W35)-V35 -> 2.272 | AX35: =(C35-D35)*100 -> -15 | AY35: =(AT35-AU35)*100 -> 16.11 | BA35: =C35-O35 -> -0.49 | BB35: =D35-P35 -> -0.32
A36: =+A31+7 -> 45329 | B36: 240207 | C36: 4 | D36: 4.09 | E36: 2.32 | F36: 3.89 | G36: 0.715 | H36: 4.79 | I36: 2.31 | J36: 3.48 | K36: 2.83 | L36: 3.24 | M36: 4.092 | O36: 4.48 | P36: 4.42 | R36: 4.9504 | S36: 4.4349 | T36: 4.868 | U36: 4.276 | V36: 3.301 | W36: 2.817 | Y36: 4.8 | Z36: 4.48 | AA36: 4.13 | AB36: 3.97 | AC36: 3.98 | AD36: 3.89 | AE36: 3.86 | AF36: 3.94 | AG36: 3.91 | AH36: 4 | AI36: 4.33 | AJ36: 4.49 | AK36: 4.58 | AL36: 4.2922424 | AM36: 3.6234413 | AN36: 3.3971393 | AO36: 3.3400918 | AP36: 3.3722969 | AQ36: 3.459763 | AT36: =(2*S36)-R36 -> 3.9194 | AU36: =(2*U36)-T36 -> 3.684 | AV36: =(2*W36)-V36 -> 2.333 | AX36: =(C36-D36)*100 -> -9 | AY36: =(AT36-AU36)*100 -> 23.54 | BA36: =C36-O36 -> -0.48 | BB36: =D36-P36 -> -0.33
A37: =+A32+7 -> 45330 | B37: 240208 | C37: 4.06 | D37: 4.15 | E37: 2.36 | F37: 3.94 | G37: 0.704 | H37: 4.79 | I37: 2.38 | J37: 3.55 | K37: 2.87 | L37: 3.31 | M37: 4.104 | O37: 4.55 | P37: 4.46 | R37: 4.9731 | S37: 4.4835 | T37: 4.869 | U37: 4.287 | V37: 3.338 | W37: 2.864 | Y37: 4.87 | Z37: 4.55 | AA37: 4.19 | AB37: 4.04 | AC37: 4.06 | AD37: 3.97 | AE37: 3.93 | AF37: 4.01 | AG37: 3.97 | AH37: 4.06 | AI37: 4.38 | AJ37: 4.54 | AK37: 4.62 | AL37: 4.3165857 | AM37: 3.7049529 | AN37: 3.492197 | AO37: 3.4251139 | AP37: 3.4407334 | AQ37: 3.5096235 | AT37: =(2*S37)-R37 -> 3.9939 | AU37: =(2*U37)-T37 -> 3.705 | AV37: =(2*W37)-V37 -> 2.39 | AX37: =(C37-D37)*100 -> -9 | AY37: =(AT37-AU37)*100 -> 28.89 | BA37: =C37-O37 -> -0.49 | BB37: =D37-P37 -> -0.31
A38: =+A33+7 -> 45331 | B38: 240209 | C38: 4.06 | D38: 4.17 | E38: 2.38 | F38: 3.96 | G38: 0.725 | H38: 4.88 | I38: 2.43 | J38: 3.55 | K38: 2.89 | L38: 3.36 | M38: 4.1276 | O38: 4.57 | P38: 4.49 | R38: 4.9961 | S38: 4.5318 | T38: 4.905 | U38: 4.334 | V38: 3.368 | W38: 2.897 | Y38: 4.88 | Z38: 4.57 | AA38: 4.22 | AB38: 4.06 | AC38: 4.08 | AD38: 3.99 | AE38: 3.94 | AF38: 4.02 | AG38: 3.98 | AH38: 4.06 | AI38: 4.38 | AJ38: 4.52 | AK38: 4.59 | AL38: 4.4001298 | AM38: 3.7510339 | AN38: 3.5239403 | AO38: 3.4549601 | AP38: 3.4555105 | AQ38: 3.5079092 | AT38: =(2*S38)-R38 -> 4.0675 | AU38: =(2*U38)-T38 -> 3.763 | AV38: =(2*W38)-V38 -> 2.426 | AX38: =(C38-D38)*100 -> -11 | AY38: =(AT38-AU38)*100 -> 30.45 | BA38: =C38-O38 -> -0.51 | BB38: =D38-P38 -> -0.32
A39: =+A34+7 -> 45334 | B39: 240212 | C39: 4.06 | D39: 4.17 | E39: 2.36 | F39: 3.9 | G39: 0.721 | H39: 4.91 | I39: 2.42 | J39: 3.58 | K39: 2.86 | L39: 3.32 | M39: 4.1613 | O39: 4.55 | P39: 4.47 | R39: 4.9594 | S39: 4.4775 | T39: 4.9 | U39: 4.323 | V39: 3.335 | W39: 2.862 | Y39: 4.83 | Z39: 4.55 | AA39: 4.2 | AB39: 4.05 | AC39: 4.06 | AD39: 3.97 | AE39: 3.93 | AF39: 4.01 | AG39: 3.98 | AH39: 4.06 | AI39: 4.37 | AJ39: 4.52 | AK39: 4.59 | AL39: 4.3545467 | AM39: 3.7385228 | AN39: 3.5187691 | AO39: 3.4426787 | AP39: 3.4487837 | AQ39: 3.5164127 | AT39: =(2*S39)-R39 -> 3.9956 | AU39: =(2*U39)-T39 -> 3.746 | AV39: =(2*W39)-V39 -> 2.389 | AX39: =(C39-D39)*100 -> -11 | AY39: =(AT39-AU39)*100 -> 24.96 | BA39: =C39-O39 -> -0.49 | BB39: =D39-P39 -> -0.3
A40: =+A35+7 -> 45335 | B40: 240213 | C40: 4.16 | D40: 4.31 | E40: 2.4 | F40: 3.96 | G40: 0.725 | H40: 4.9 | I40: 2.44 | J40: 3.65 | K40: 2.9 | L40: 3.37 | M40: 4.1747 | O40: 4.68 | P40: 4.66 | R40: 5.0727 | S40: 4.6386 | T40: 4.902 | U40: 4.331 | V40: 3.422 | W40: 2.954 | Y40: 4.95 | Z40: 4.68 | AA40: 4.34 | AB40: 4.19 | AC40: 4.2 | AD40: 4.1 | AE40: 4.04 | AF40: 4.11 | AG40: 4.08 | AH40: 4.16 | AI40: 4.47 | AJ40: 4.6 | AK40: 4.67 | AL40: 4.5397856 | AM40: 3.912166 | AN40: 3.6341962 | AO40: 3.5295794 | AP40: 3.5237192 | AQ40: 3.5806898 | AT40: =(2*S40)-R40 -> 4.2045 | AU40: =(2*U40)-T40 -> 3.76 | AV40: =(2*W40)-V40 -> 2.486 | AX40: =(C40-D40)*100 -> -15 | AY40: =(AT40-AU40)*100 -> 44.45 | BA40: =C40-O40 -> -0.52 | BB40: =D40-P40 -> -0.35
A41: =+A36+7 -> 45336 | B41: 240214 | C41: 4.03 | D41: 4.27 | E41: 2.32 | F41: 3.84 | G41: 0.755 | H41: 4.96 | I41: 2.4 | J41: 3.56 | K41: 2.83 | L41: 3.26 | M41: 4.2669 | O41: 4.54 | P41: 4.58 | R41: 4.9834 | S41: 4.5035 | T41: 5.027 | U41: 4.494 | V41: 3.372 | W41: 2.889 | Y41: 4.86 | Z41: 4.54 | AA41: 4.18 | AB41: 4.03 | AC41: 4.04 | AD41: 3.96 | AE41: 3.9 | AF41: 3.99 | AG41: 3.95 | AH41: 4.03 | AI41: 4.34 | AJ41: 4.49 | AK41: 4.56 | AL41: 4.3721217 | AM41: 3.698171 | AN41: 3.452018 | AO41: 3.3878629 | AP41: 3.4121463 | AQ41: 3.491881 | AT41: =(2*S41)-R41 -> 4.0236 | AU41: =(2*U41)-T41 -> 3.961 | AV41: =(2*W41)-V41 -> 2.406 | AX41: =(C41-D41)*100 -> -24 | AY41: =(AT41-AU41)*100 -> 6.26 | BA41: =C41-O41 -> -0.51 | BB41: =D41-P41 -> -0.31
... A43: =+A38+7 -> 45338 | B43: 240216 | C43: 4.11 | D43: 4.3 | E43: 2.4 | F43: 3.88 | G43: 0.732 | H43: 4.88 | I43: 2.48 | J43: 3.59 | K43: 2.87 | L43: 3.29 | M43: 4.1949 | O43: 4.63 | P43: 4.66 | R43: 5.0384 | S43: 4.5961 | T43: 5.018 | U43: 4.48 | V43: 3.436 | W43: 2.976 | Y43: 4.86 | Z43: 4.63 | AA43: 4.27 | AB43: 4.12 | AC43: 4.13 | AD43: 4.04 | AE43: 3.98 | AF43: 4.07 | AG43: 4.04 | AH43: 4.11 | AI43: 4.43 | AJ43: 4.58 | AK43: 4.65 | AL43: 4.4997817 | AM43: 3.8341098 | AN43: 3.5549935 | AO43: 3.4750358 | AP43: 3.4889631 | AQ43: 3.5572596 | AT43: =(2*S43)-R43 -> 4.1538 | AU43: =(2*U43)-T43 -> 3.942 | AV43: =(2*W43)-V43 -> 2.516 | AX43: =(C43-D43)*100 -> -19 | AY43: =(AT43-AU43)*100 -> 21.18 | BA43: =C43-O43 -> -0.52 | BB43: =D43-P43 -> -0.36
A44: =+A39+7 -> 45341 | B44: 240219 | C44: 4.12 | D44: #N/A | E44: 2.42 | F44: 3.91 | G44: 0.729 | H44: 4.91 | I44: 2.49 | J44: #N/A | K44: 2.89 | L44: 3.32 | M44: 4.1724 | O44: 4.63 | P44: #N/A | R44: 5.0137 | S44: 4.5645 | T44: 5.036 | U44: 4.51 | V44: 3.447 | W44: 2.984 | Y44: 4.87 | Z44: 4.63 | AA44: 4.28 | AB44: 4.13 | AC44: 4.15 | AD44: 4.05 | AE44: 4 | AF44: 4.07 | AG44: 4.05 | AH44: 4.12 | AI44: 4.44 | AJ44: 4.59 | AK44: 4.66 | AL44: 4.4448221 | AM44: 3.8216572 | AN44: 3.5799148 | AO44: 3.4777495 | AP44: 3.4772801 | AQ44: 3.5581922 | AT44: =(2*S44)-R44 -> 4.1153 | AU44: =(2*U44)-T44 -> 3.984 | AV44: =(2*W44)-V44 -> 2.521 | AX44: =(C44-D44)*100 -> #N/A | AY44: =(AT44-AU44)*100 -> 13.13 | BA44: =C44-O44 -> -0.51 | BB44: =D44-P44 -> #N/A
A45: =+A40+7 -> 45342 | B45: 240220 | C45: 4.05 | D45: 4.27 | E45: 2.38 | F45: 3.87 | G45: 0.728 | H45: 4.88 | I45: 2.41 | J45: 3.52 | K45: 2.86 | L45: 3.3 | M45: 4.1814 | O45: 4.55 | P45: 4.61 | R45: 4.9636 | S45: 4.4954 | T45: 5.013 | U45: 4.481 | V45: 3.417 | W45: 2.945 | Y45: 4.8 | Z45: 4.55 | AA45: 4.21 | AB45: 4.06 | AC45: 4.07 | AD45: 3.97 | AE45: 3.93 | AF45: 4 | AG45: 3.97 | AH45: 4.05 | AI45: 4.37 | AJ45: 4.53 | AK45: 4.6 | AL45: 4.3330006 | AM45: 3.7488513 | AN45: 3.5051998 | AO45: 3.4277604 | AP45: 3.4364615 | AQ45: 3.5029268 | AT45: =(2*S45)-R45 -> 4.0272 | AU45: =(2*U45)-T45 -> 3.949 | AV45: =(2*W45)-V45 -> 2.473 | AX45: =(C45-D45)*100 -> -22 | AY45: =(AT45-AU45)*100 -> 7.82 | BA45: =C45-O45 -> -0.5 | BB45: =D45-P45 -> -0.34
A46: =+A41+7 -> 45343 | B46: 240221 | C46: 4.1 | D46: 4.32 | E46: 2.45 | F46: 3.96 | G46: 0.721 | H46: 4.87 | I46: 2.44 | J46: 3.55 | K46: 2.93 | L46: 3.38 | M46: 4.1732 | O46: 4.61 | P46: 4.65 | R46: 5.0152 | S46: 4.5815 | T46: 5.008 | U46: 4.471 | V46: 3.46 | W46: 3.002 | Y46: 4.85 | Z46: 4.61 | AA46: 4.28 | AB46: 4.13 | AC46: 4.14 | AD46: 4.03 | AE46: 3.98 | AF46: 4.05 | AG46: 4.03 | AH46: 4.1 | AI46: 4.42 | AJ46: 4.57 | AK46: 4.63 | AL46: 4.4481289 | AM46: 3.856475 | AN46: 3.5894549 | AO46: 3.4903112 | AP46: 3.4828828 | AQ46: 3.5351891 | AT46: =(2*S46)-R46 -> 4.1478 | AU46: =(2*U46)-T46 -> 3.934 | AV46: =(2*W46)-V46 -> 2.544 | AX46: =(C46-D46)*100 -> -22 | AY46: =(AT46-AU46)*100 -> 21.38 | BA46: =C46-O46 -> -0.51 | BB46: =D46-P46 -> -0.33
A47: =+A42+7 -> 45344 | B47: 240222 | C47: 4.11 | D47: 4.33 | E47: 2.44 | F47: 3.92 | G47: 0.716 | H47: 4.88 | I47: 2.46 | J47: 3.54 | K47: 2.92 | L47: 3.35 | M47: 4.1597 | O47: 4.61 | P47: 4.71 | R47: 5.0294 | S47: 4.6146 | T47: 5.052 | U47: 4.537 | V47: 3.523 | W47: 3.077 | Y47: 4.84 | Z47: 4.61 | AA47: 4.3 | AB47: 4.14 | AC47: 4.16 | AD47: 4.06 | AE47: 3.99 | AF47: 4.07 | AG47: 4.04 | AH47: 4.11 | AI47: 4.43 | AJ47: 4.58 | AK47: 4.64 | AL47: 4.4865227 | AM47: 3.9099208 | AN47: 3.6383454 | AO47: 3.5170996 | AP47: 3.4939846 | AQ47: 3.5372711 | AT47: =(2*S47)-R47 -> 4.1998 | AU47: =(2*U47)-T47 -> 4.022 | AV47: =(2*W47)-V47 -> 2.631 | AX47: =(C47-D47)*100 -> -22 | AY47: =(AT47-AU47)*100 -> 17.78 | BA47: =C47-O47 -> -0.5 | BB47: =D47-P47 -> -0.38
A48: =+A43+7 -> 45345 | B48: 240223 | C48: 4.11 | D48: 4.26 | E48: 2.37 | F48: 3.8 | G48: 0.713 | H48: 4.89 | I48: 2.45 | J48: 3.46 | K48: 2.83 | L48: 3.25 | M48: 4.1973 | O48: 4.25 | P48: 4.69 | R48: 4.9931 | S48: 4.5499 | T48: 5.094 | U48: 4.591 | V48: 3.469 | W48: 2.996 | Y48: 4.53 | Z48: 4.25 | AA48: 4.07 | AB48: 4.09 | AC48: 3.99 | AD48: 3.92 | AE48: 3.95 | AF48: 3.97 | AG48: 4.04 | AH48: 4.11 | AI48: 4.41 | AJ48: 4.57 | AK48: 4.62 | AL48: 4.4239811 | AM48: 3.8130501 | AN48: 3.5576301 | AO48: 3.4571179 | AP48: 3.4340229 | AQ48: 3.4690291 | AT48: =(2*S48)-R48 -> 4.1067 | AU48: =(2*U48)-T48 -> 4.088 | AV48: =(2*W48)-V48 -> 2.523 | AX48: =(C48-D48)*100 -> -15 | AY48: =(AT48-AU48)*100 -> 1.87 | BA48: =C48-O48 -> -0.14 | BB48: =D48-P48 -> -0.43
A49: =+A44+7 -> 45348 | B49: 240226 | C49: 4.15 | D49: 4.28 | E49: 2.43 | F49: 3.9 | G49: 0.689 | H49: 4.85 | I49: 2.49 | J49: 3.5 | K49: 2.9 | L49: 3.32 | M49: 4.103 | O49: 4.3 | P49: 4.74 | R49: 5.0179 | S49: 4.5963 | T49: 5.078 | U49: 4.555 | V49: 3.532 | W49: 3.082 | Y49: 4.6 | Z49: 4.3 | AA49: 4.13 | AB49: 4.16 | AC49: 4.04 | AD49: 3.99 | AE49: 4.02 | AF49: 4.03 | AG49: 4.1 | AH49: 4.15 | AI49: 4.46 | AJ49: 4.62 | AK49: 4.63 | AL49: 4.4559274 | AM49: 3.9090228 | AN49: 3.6443957 | AO49: 3.5121666 | AP49: 3.4776123 | AQ49: 3.522342 | AT49: =(2*S49)-R49 -> 4.1747 | AU49: =(2*U49)-T49 -> 4.032 | AV49: =(2*W49)-V49 -> 2.632 | AX49: =(C49-D49)*100 -> -13 | AY49: =(AT49-AU49)*100 -> 14.27 | BA49: =C49-O49 -> -0.15 | BB49: =D49-P49 -> -0.46
A50: =+A45+7 -> 45349 | B50: 240227 | C50: 4.19 | D50: 4.31 | E50: 2.47 | F50: 3.91 | G50: 0.687 | H50: 4.88 | I50: 2.56 | J50: 3.56 | K50: 2.94 | L50: 3.36 | M50: 4.133 | O50: 4.35 | P50: 4.71 | R50: 5.0317 | S50: 4.6239 | T50: 5.096 | U50: 4.575 | V50: 3.534 | W50: 3.083 | Y50: 4.63 | Z50: 4.35 | AA50: 4.17 | AB50: 4.2 | AC50: 4.09 | AD50: 4.02 | AE50: 4.05 | AF50: 4.06 | AG50: 4.13 | AH50: 4.19 | AI50: 4.49 | AJ50: 4.63 | AK50: 4.66 | AL50: 4.5037869 | AM50: 3.9527734 | AN50: 3.6714602 | AO50: 3.5417123 | AP50: 3.5102113 | AQ50: 3.5494533 | AT50: =(2*S50)-R50 -> 4.2161 | AU50: =(2*U50)-T50 -> 4.054 | AV50: =(2*W50)-V50 -> 2.632 | AX50: =(C50-D50)*100 -> -12 | AY50: =(AT50-AU50)*100 -> 16.21 | BA50: =C50-O50 -> -0.16 | BB50: =D50-P50 -> -0.4
A51: =+A46+7 -> 45350 | B51: 240228 | C51: 4.18 | D51: 4.27 | E51: 2.46 | F51: 3.89 | G51: 0.693 | H51: 4.79 | I51: 2.57 | J51: 3.52 | K51: 2.93 | L51: 3.34 | M51: 4.1687 | O51: 4.35 | P51: 4.65 | R51: 5.0258 | S51: 4.618 | T51: 5.091 | U51: 4.575 | V51: 3.516 | W51: 3.07 | Y51: 4.64 | Z51: 4.35 | AA51: 4.17 | AB51: 4.21 | AC51: 4.09 | AD51: 4.03 | AE51: 4.05 | AF51: 4.05 | AG51: 4.12 | AH51: 4.18 | AI51: 4.47 | AJ51: 4.62 | AK51: 4.65 | AL51: 4.5059494 | AM51: 3.9338182 | AN51: 3.6442803 | AO51: 3.5241174 | AP51: 3.4957626 | AQ51: 3.5308213 | AT51: =(2*S51)-R51 -> 4.2102 | AU51: =(2*U51)-T51 -> 4.059 | AV51: =(2*W51)-V51 -> 2.624 | AX51: =(C51-D51)*100 -> -9 | AY51: =(AT51-AU51)*100 -> 15.12 | BA51: =C51-O51 -> -0.17 | BB51: =D51-P51 -> -0.38
A52: =+A47+7 -> 45351 | B52: 240229 | C52: 4.12 | D52: 4.25 | E52: 2.42 | F52: 3.85 | G52: 0.709 | H52: 4.77 | I52: 2.48 | J52: 3.49 | K52: 2.89 | L52: 3.3 | M52: 4.136 | O52: 4.3 | P52: 4.65 | R52: 5.0152 | S52: 4.5966 | T52: 5.084 | U52: 4.57 | V52: 3.533 | W52: 3.08 | Y52: 4.59 | Z52: 4.3 | AA52: 4.13 | AB52: 4.16 | AC52: 4.05 | AD52: 3.99 | AE52: 4.01 | AF52: 4 | AG52: 4.07 | AH52: 4.12 | AI52: 4.41 | AJ52: 4.55 | AK52: 4.58 | AL52: 4.4344145 | AM52: 3.9079271 | AN52: 3.6051999 | AO52: 3.4731127 | AP52: 3.4398101 | AQ52: 3.4682755 | AT52: =(2*S52)-R52 -> 4.178 | AU52: =(2*U52)-T52 -> 4.056 | AV52: =(2*W52)-V52 -> 2.627 | AX52: =(C52-D52)*100 -> -13 | AY52: =(AT52-AU52)*100 -> 12.2 | BA52: =C52-O52 -> -0.18 | BB52: =D52-P52 -> -0.4
A53: =+A48+7 -> 45352 | B53: 240301 | C53: 4.1 | D53: 4.19 | E53: 2.41 | F53: 3.88 | G53: 0.711 | H53: 4.79 | I53: 2.48 | J53: 3.43 | K53: 2.9 | L53: 3.29 | M53: 4.1424 | O53: 4.28 | P53: 4.53 | R53: 5.0001 | S53: 4.567 | T53: 5.023 | U53: 4.492 | V53: 3.519 | W53: 3.055 | Y53: 4.56 | Z53: 4.28 | AA53: 4.1 | AB53: 4.13 | AC53: 4.04 | AD53: 3.96 | AE53: 3.99 | AF53: 3.97 | AG53: 4.06 | AH53: 4.1 | AI53: 4.38 | AJ53: 4.52 | AK53: 4.54 | AL53: 4.4272611 | AM53: 3.855362 | AN53: 3.5793939 | AO53: 3.4601096 | AP53: 3.4210924 | AQ53: 3.4431278 | AT53: =(2*S53)-R53 -> 4.1339 | AU53: =(2*U53)-T53 -> 3.961 | AV53: =(2*W53)-V53 -> 2.591 | AX53: =(C53-D53)*100 -> -9 | AY53: =(AT53-AU53)*100 -> 17.29 | BA53: =C53-O53 -> -0.18 | BB53: =D53-P53 -> -0.34
A54: =+A49+7 -> 45355 | B54: 240304 | C54: 4.13 | D54: 4.22 | E54: 2.4 | F54: 3.82 | G54: 0.709 | H54: 4.78 | I54: 2.41 | J54: 3.45 | K54: 2.87 | L54: 3.27 | M54: 4.1046 | O54: 4.3 | P54: 4.61 | R54: 5.0332 | S54: 4.6111 | T54: 5.012 | U54: 4.471 | V54: 3.544 | W54: 3.081 | Y54: 4.64 | Z54: 4.3 | AA54: 4.15 | AB54: 4.17 | AC54: 4.07 | AD54: 3.98 | AE54: 4.04 | AF54: 4 | AG54: 4.07 | AH54: 4.13 | AI54: 4.4 | AJ54: 4.53 | AK54: 4.56 | AL54: 4.4975999 | AM54: 3.9305434 | AN54: 3.6091027 | AO54: 3.467159 | AP54: 3.4261419 | AQ54: 3.4572742 | AT54: =(2*S54)-R54 -> 4.189 | AU54: =(2*U54)-T54 -> 3.93 | AV54: =(2*W54)-V54 -> 2.618 | AX54: =(C54-D54)*100 -> -9 | AY54: =(AT54-AU54)*100 -> 25.9 | BA54: =C54-O54 -> -0.17 | BB54: =D54-P54 -> -0.39
A55: =+A50+7 -> 45356 | B55: 240305 | C55: 4.01 | D55: 4.13 | E55: 2.32 | F55: 3.71 | G55: 0.697 | H55: 4.78 | I55: 2.33 | J55: 3.36 | K55: 2.79 | L55: 3.17 | M55: 4.0924 | O55: 4.23 | P55: 4.55 | R55: 5.0022 | S55: 4.5557 | T55: 5.035 | U55: 4.49 | V55: 3.502 | W55: 3.021 | Y55: 4.59 | Z55: 4.23 | AA55: 4.07 | AB55: 4.08 | AC55: 3.98 | AD55: 3.89 | AE55: 3.9 | AF55: 3.89 | AG55: 3.95 | AH55: 4.01 | AI55: 4.28 | AJ55: 4.42 | AK55: 4.45 | AL55: 4.4289855 | AM55: 3.8478194 | AN55: 3.5041245 | AO55: 3.3467159 | AP55: 3.3066967 | AQ55: 3.3392197 | AT55: =(2*S55)-R55 -> 4.1092 | AU55: =(2*U55)-T55 -> 3.945 | AV55: =(2*W55)-V55 -> 2.54 | AX55: =(C55-D55)*100 -> -12 | AY55: =(AT55-AU55)*100 -> 16.42 | BA55: =C55-O55 -> -0.22 | BB55: =D55-P55 -> -0.42
A56: =+A51+7 -> 45357 | B56: 240306 | C56: 4 | D56: 4.11 | E56: 2.33 | F56: 3.66 | G56: 0.723 | H56: 4.71 | I56: 2.36 | J56: 3.35 | K56: 2.79 | L56: 3.16 | M56: 4.0101 | O56: 4.3 | P56: 4.56 | R56: 5.0004 | S56: 4.5462 | T56: 5.016 | U56: 4.469 | V56: 3.514 | W56: 3.031 | Y56: 4.58 | Z56: 4.3 | AA56: 4.04 | AB56: 4.05 | AC56: 3.94 | AD56: 3.86 | AE56: 3.92 | AF56: 3.87 | AG56: 3.94 | AH56: 4 | AI56: 4.27 | AJ56: 4.4 | AK56: 4.44 | AL56: 4.4302308 | AM56: 3.8024889 | AN56: 3.4519409 | AO56: 3.3185527 | AP56: 3.2922575 | AQ56: 3.3246405 | AT56: =(2*S56)-R56 -> 4.092 | AU56: =(2*U56)-T56 -> 3.922 | AV56: =(2*W56)-V56 -> 2.548 | AX56: =(C56-D56)*100 -> -11 | AY56: =(AT56-AU56)*100 -> 17 | BA56: =C56-O56 -> -0.3 | BB56: =D56-P56 -> -0.45
... A72: =+A67+7 -> 45379 | B72: 240328 | C72: 3.95 | D72: 4.2 | E72: 2.31 | F72: 3.69 | G72: 0.711 | H72: 4.61 | I72: 2.33 | J72: 3.47 | K72: 2.82 | L72: 3.17 | M72: 3.9656 | O72: 4.16 | P72: 4.62 | R72: 4.8763 | S72: 4.4009 | T72: 5.037 | U72: 4.545 | V72: 3.235 | W72: 2.849 | Y72: 4.5 | Z72: 4.16 | AA72: 3.94 | AB72: 3.94 | AC72: 3.84 | AD72: 3.77 | AE72: 3.81 | AF72: 3.81 | AG72: 3.89 | AH72: 3.95 | AI72: 4.24 | AJ72: 4.4 | AK72: 4.45 | AL72: 4.2335021 | AM72: 3.6363153 | AN72: 3.3529125 | AO72: 3.2620468 | AP72: 3.2621838 | AQ72: 3.3153029 | AT72: =(2*S72)-R72 -> 3.9255 | AU72: =(2*U72)-T72 -> 4.053 | AV72: =(2*W72)-V72 -> 2.463 | AX72: =(C72-D72)*100 -> -25 | AY72: =(AT72-AU72)*100 -> -12.75 | BA72: =C72-O72 -> -0.21 | BB72: =D72-P72 -> -0.42
A73: =+A68+7 -> 45380 | B73: 240329 | C73: 3.95 | D73: #N/A | E73: 2.29 | F73: 3.68 | G73: 0.736 | H73: #N/A | I73: #N/A | J73: #N/A | K73: 2.8 | L73: 3.16 | M73: 3.9656 | O73: 4.17 | P73: #N/A | R73: 4.8763 | S73: 4.4009 | T73: 5.036 | U73: 4.541 | V73: 3.237 | W73: 2.853 | Y73: 4.5 | Z73: 4.17 | AA73: 3.94 | AB73: 3.94 | AC73: 3.84 | AD73: 3.77 | AE73: 3.81 | AF73: #N/A | AG73: #N/A | AH73: 3.95 | AI73: 4.25 | AJ73: 4.4 | AK73: #N/A | AL73: #N/A | AM73: #N/A | AN73: #N/A | AO73: #N/A | AP73: #N/A | AQ73: #N/A | AT73: =(2*S73)-R73 -> 3.9255 | AU73: =(2*U73)-T73 -> 4.046 | AV73: =(2*W73)-V73 -> 2.469 | AX73: =(C73-D73)*100 -> #N/A | AY73: =(AT73-AU73)*100 -> -12.05 | BA73: =C73-O73 -> -0.22 | BB73: =D73-P73 -> #N/A
A74: =+A69+7 -> 45383 | B74: 240401 | C74: #N/A | D74: 4.33 | E74: #N/A | F74: #N/A | G74: 0.743 | H74: 4.62 | I74: #N/A | J74: 3.59 | K74: #N/A | L74: #N/A | M74: 3.9656 | O74: #N/A | P74: 4.72 | R74: 4.8763 | S74: 4.4009 | T74: 5.021 | U74: 4.525 | V74: 3.237 | W74: 2.853 | Y74: #N/A | Z74: #N/A | AA74: #N/A | AB74: #N/A | AC74: #N/A | AD74: #N/A | AE74: #N/A | AF74: #N/A | AG74: #N/A | AH74: #N/A | AI74: #N/A | AJ74: #N/A | AK74: #N/A | AL74: #N/A | AM74: #N/A | AN74: #N/A | AO74: #N/A | AP74: #N/A | AQ74: #N/A | AT74: =(2*S74)-R74 -> 3.9255 | AU74: =(2*U74)-T74 -> 4.029 | AV74: =(2*W74)-V74 -> 2.469 | AX74: =(C74-D74)*100 -> #N/A | AY74: =(AT74-AU74)*100 -> -10.35 | BA74: =C74-O74 -> #N/A | BB74: =D74-P74 -> -0.39
A75: =+A70+7 -> 45384 | B75: 240402 | C75: 4.08 | D75: 4.36 | E75: 2.4 | F75: 3.8 | G75: 0.743 | H75: 4.68 | I75: 2.48 | J75: 3.61 | K75: 2.92 | L75: 3.25 | M75: 4.062 | O75: 4.25 | P75: 4.7 | R75: 4.8839 | S75: 4.45 | T75: 5.08 | U75: 4.624 | V75: 3.218 | W75: 2.851 | Y75: 4.56 | Z75: 4.25 | AA75: 4.03 | AB75: 4.04 | AC75: 3.94 | AD75: 3.88 | AE75: 3.94 | AF75: 3.94 | AG75: 4.02 | AH75: 4.08 | AI75: 4.38 | AJ75: 4.54 | AK75: 4.57 | AL75: 4.3040203 | AM75: 3.751573 | AN75: 3.4779442 | AO75: 3.3796573 | AP75: 3.3832782 | AQ75: 3.4537561 | AT75: =(2*S75)-R75 -> 4.0161 | AU75: =(2*U75)-T75 -> 4.168 | AV75: =(2*W75)-V75 -> 2.484 | AX75: =(C75-D75)*100 -> -28 | AY75: =(AT75-AU75)*100 -> -15.19 | BA75: =C75-O75 -> -0.17 | BB75: =D75-P75 -> -0.34
A76: =+A71+7 -> 45385 | B76: 240403 | C76: 4.04 | D76: 4.36 | E76: 2.38 | F76: 3.81 | G76: 0.768 | H76: 4.67 | I76: 2.51 | J76: 3.6 | K76: 2.89 | L76: 3.23 | M76: 4.1287 | O76: 4.2 | P76: 4.68 | R76: 4.8728 | S76: 4.4285 | T76: 5.065 | U76: 4.61 | V76: 3.234 | W76: 2.86 | Y76: 4.52 | Z76: 4.2 | AA76: 3.98 | AB76: 3.99 | AC76: 3.89 | AD76: 3.84 | AE76: 3.88 | AF76: 3.89 | AG76: 3.98 | AH76: 4.04 | AI76: 4.35 | AJ76: 4.51 | AK76: 4.55 | AL76: 4.2873411 | AM76: 3.7189756 | AN76: 3.4130603 | AO76: 3.3268925 | AP76: 3.3433996 | AQ76: 3.4107635 | AT76: =(2*S76)-R76 -> 3.9842 | AU76: =(2*U76)-T76 -> 4.155 | AV76: =(2*W76)-V76 -> 2.486 | AX76: =(C76-D76)*100 -> -32 | AY76: =(AT76-AU76)*100 -> -17.08 | BA76: =C76-O76 -> -0.16 | BB76: =D76-P76 -> -0.32
A77: =+A72+7 -> 45386 | B77: 240404 | C77: 4.02 | D77: 4.31 | E77: 2.36 | F77: 3.71 | G77: 0.768 | H77: 4.69 | I77: 2.47 | J77: 3.55 | K77: 2.86 | L77: 3.18 | M77: 4.1796 | O77: 4.2 | P77: 4.64 | R77: 4.8609 | S77: 4.42 | T77: 5.047 | U77: 4.591 | V77: 3.251 | W77: 2.875 | Y77: 4.52 | Z77: 4.2 | AA77: 3.98 | AB77: 4 | AC77: 3.89 | AD77: 3.83 | AE77: 3.87 | AF77: 3.88 | AG77: 3.97 | AH77: 4.02 | AI77: 4.34 | AJ77: 4.51 | AK77: 4.54 | AL77: 4.285214 | AM77: 3.6788126 | AN77: 3.3991694 | AO77: 3.3357089 | AP77: 3.3517351 | AQ77: 3.4153988 | AT77: =(2*S77)-R77 -> 3.9791 | AU77: =(2*U77)-T77 -> 4.135 | AV77: =(2*W77)-V77 -> 2.499 | AX77: =(C77-D77)*100 -> -29 | AY77: =(AT77-AU77)*100 -> -15.59 | BA77: =C77-O77 -> -0.18 | BB77: =D77-P77 -> -0.33
A78: =+A73+7 -> 45387 | B78: 240405 | C78: 4.06 | D78: 4.39 | E78: 2.41 | F78: 3.78 | G78: 0.768 | H78: 4.67 | I78: 2.48 | J78: 3.59 | K78: 2.92 | L78: 3.25 | M78: 4.1003 | O78: 4.22 | P78: 4.73 | R78: 4.8622 | S78: 4.4399 | T78: 5.022 | U78: 4.568 | V78: 3.264 | W78: 2.899 | Y78: 4.55 | Z78: 4.22 | AA78: 4.01 | AB78: 4.03 | AC78: 3.92 | AD78: 3.87 | AE78: 3.92 | AF78: 3.92 | AG78: 4 | AH78: 4.06 | AI78: 4.38 | AJ78: 4.53 | AK78: 4.57 | AL78: 4.2781786 | AM78: 3.7136829 | AN78: 3.4693622 | AO78: 3.3959459 | AP78: 3.4017517 | AQ78: 3.4598017 | AT78: =(2*S78)-R78 -> 4.0176 | AU78: =(2*U78)-T78 -> 4.114 | AV78: =(2*W78)-V78 -> 2.534 | AX78: =(C78-D78)*100 -> -33 | AY78: =(AT78-AU78)*100 -> -9.64 | BA78: =C78-O78 -> -0.16 | BB78: =D78-P78 -> -0.34
A79: =+A74+7 -> 45390 | B79: 240408 | C79: 4.09 | D79: 4.42 | E79: 2.43 | F79: 3.79 | G79: 0.785 | H79: 4.77 | I79: 2.56 | J79: 3.63 | K79: 2.92 | L79: 3.25 | M79: 4.1991 | O79: 4.23 | P79: 4.79 | R79: 4.8732 | S79: 4.4667 | T79: 5.089 | U79: 4.68 | V79: 3.302 | W79: 2.952 | Y79: 4.56 | Z79: 4.23 | AA79: 4.04 | AB79: 4.06 | AC79: 3.96 | AD79: 3.9 | AE79: 3.94 | AF79: 3.95 | AG79: 4.03 | AH79: 4.09 | AI79: 4.41 | AJ79: 4.56 | AK79: 4.6 | AL79: 4.3140391 | AM79: 3.802481 | AN79: 3.5296285 | AO79: 3.417446 | AP79: 3.4075096 | AQ79: 3.4688325 | AT79: =(2*S79)-R79 -> 4.0602 | AU79: =(2*U79)-T79 -> 4.271 | AV79: =(2*W79)-V79 -> 2.602 | AX79: =(C79-D79)*100 -> -33 | AY79: =(AT79-AU79)*100 -> -21.08 | BA79: =C79-O79 -> -0.14 | BB79: =D79-P79 -> -0.37
A80: =+A75+7 -> 45391 | B80: 240409 | C80: 4.01 | D80: 4.36 | E80: 2.37 | F80: 3.71 | G80: 0.781 | H80: 4.8 | I80: 2.48 | J80: 3.56 | K80: 2.86 | L80: 3.19 | M80: 4.1754 | O80: 4.2 | P80: 4.75 | R80: 4.8595 | S80: 4.4353 | T80: 5.086 | U80: 4.666 | V80: 3.281 | W80: 2.916 | Y80: 4.52 | Z80: 4.2 | AA80: 4.01 | AB80: 4.02 | AC80: 3.92 | AD80: 3.84 | AE80: 3.88 | AF80: 3.88 | AG80: 3.96 | AH80: 4.01 | AI80: 4.33 | AJ80: 4.48 | AK80: 4.52 | AL80: 4.2831506 | AM80: 3.7421137 | AN80: 3.448614 | AO80: 3.3356935 | AP80: 3.3325652 | AQ80: 3.395766 | AT80: =(2*S80)-R80 -> 4.0111 | AU80: =(2*U80)-T80 -> 4.246 | AV80: =(2*W80)-V80 -> 2.551 | AX80: =(C80-D80)*100 -> -35 | AY80: =(AT80-AU80)*100 -> -23.49 | BA80: =C80-O80 -> -0.19 | BB80: =D80-P80 -> -0.39
A81: =+A76+7 -> 45392 | B81: 240410 | C81: 4.15 | D81: 4.55 | E81: 2.45 | F81: 3.78 | G81: 0.791 | H81: 4.72 | I81: 2.5 | J81: 3.7 | K81: 2.93 | L81: 3.26 | M81: 4.1182 | O81: 4.34 | P81: 4.97 | R81: 4.958 | S81: 4.5857 | T81: 5.056 | U81: 4.637 | V81: 3.37 | W81: 3.032 | Y81: 4.67 | Z81: 4.34 | AA81: 4.16 | AB81: 4.17 | AC81: 4.07 | AD81: 3.99 | AE81: 4.02 | AF81: 4.02 | AG81: 4.09 | AH81: 4.15 | AI81: 4.45 | AJ81: 4.6 | AK81: 4.63 | AL81: 4.4683502 | AM81: 3.9554252 | AN81: 3.6118631 | AO81: 3.4744691 | AP81: 3.4569729 | AQ81: 3.5049891 | AT81: =(2*S81)-R81 -> 4.2134 | AU81: =(2*U81)-T81 -> 4.218 | AV81: =(2*W81)-V81 -> 2.694 | AX81: =(C81-D81)*100 -> -40 | AY81: =(AT81-AU81)*100 -> -0.46 | BA81: =C81-O81 -> -0.19 | BB81: =D81-P81 -> -0.42
A82: =+A77+7 -> 45393 | B82: 240411 | C82: 4.19 | D82: 4.56 | E82: 2.46 | F82: 3.84 | G82: 0.863 | H82: 4.84 | I82: 2.53 | J82: 3.73 | K82: 2.94 | L82: 3.28 | M82: 4.2551 | O82: 4.37 | P82: 4.96 | R82: 5.0183 | S82: 4.6759 | T82: 5.223 | U82: 4.869 | V82: 3.361 | W82: 3.023 | Y82: 4.68 | Z82: 4.37 | AA82: 4.2 | AB82: 4.22 | AC82: 4.1 | AD82: 4.03 | AE82: 4.08 | AF82: 4.07 | AG82: 4.14 | AH82: 4.19 | AI82: 4.49 | AJ82: 4.64 | AK82: 4.68 | AL82: 4.5618678 | AM82: 4.0126218 | AN82: 3.6412548 | AO82: 3.5148063 | AP82: 3.4988029 | AQ82: 3.5392484 | AT82: =(2*S82)-R82 -> 4.3335 | AU82: =(2*U82)-T82 -> 4.515 | AV82: =(2*W82)-V82 -> 2.685 | AX82: =(C82-D82)*100 -> -37 | AY82: =(AT82-AU82)*100 -> -18.15 | BA82: =C82-O82 -> -0.18 | BB82: =D82-P82 -> -0.4
A83: =+A78+7 -> 45394 | B83: 240412 | C83: 4.13 | D83: 4.5 | E83: 2.36 | F83: 3.74 | G83: 0.853 | H83: 4.91 | I83: 2.39 | J83: 3.66 | K83: 2.87 | L83: 3.2 | M83: 4.2698 | O83: 4.35 | P83: 4.88 | R83: 4.9654 | S83: 4.6015 | T83: 5.198 | U83: 4.838 | V83: 3.281 | W83: 2.923 | Y83: 4.63 | Z83: 4.35 | AA83: 4.15 | AB83: 4.16 | AC83: 4.04 | AD83: 3.98 | AE83: 4.02 | AF83: 4 | AG83: 4.08 | AH83: 4.13 | AI83: 4.43 | AJ83: 4.58 | AK83: 4.62 | AL83: 4.4687694 | AM83: 3.9231054 | AN83: 3.6057768 | AO83: 3.4718949 | AP83: 3.4430327 | AQ83: 3.4819572 | AT83: =(2*S83)-R83 -> 4.2376 | AU83: =(2*U83)-T83 -> 4.478 | AV83: =(2*W83)-V83 -> 2.565 | AX83: =(C83-D83)*100 -> -37 | AY83: =(AT83-AU83)*100 -> -24.04 | BA83: =C83-O83 -> -0.22 | BB83: =D83-P83 -> -0.38
A84: =+A79+7 -> 45397 | B84: 240415 | C84: 4.22 | D84: 4.63 | E84: 2.44 | F84: 3.84 | G84: 0.871 | H84: 4.85 | I84: 2.51 | J84: 3.74 | K84: 2.96 | L84: 3.26 | M84: 4.2647 | O84: 4.42 | P84: 4.94 | R84: 4.9837 | S84: 4.6458 | T84: 5.206 | U84: 4.857 | V84: 3.315 | W84: 2.971 | Y84: 4.67 | Z84: 4.42 | AA84: 4.24 | AB84: 4.25 | AC84: 4.14 | AD84: 4.08 | AE84: 4.11 | AF84: 4.11 | AG84: 4.19 | AH84: 4.22 | AI84: 4.51 | AJ84: 4.69 | AK84: 4.72 | AL84: 4.5418212 | AM84: 4.0551691 | AN84: 3.7140923 | AO84: 3.5656648 | AP84: 3.541911 | AQ84: 3.5947629 | AT84: =(2*S84)-R84 -> 4.3079 | AU84: =(2*U84)-T84 -> 4.508 | AV84: =(2*W84)-V84 -> 2.627 | AX84: =(C84-D84)*100 -> -41 | AY84: =(AT84-AU84)*100 -> -20.01 | BA84: =C84-O84 -> -0.2 | BB84: =D84-P84 -> -0.31
A85: =+A80+7 -> 45398 | B85: 240416 | C85: 4.3 | D85: 4.67 | E85: 2.49 | F85: 3.91 | G85: 0.867 | H85: 4.92 | I85: 2.55 | J85: 3.74 | K85: 3.01 | L85: 3.34 | M85: 4.3304 | O85: 4.48 | P85: 4.96 | R85: 5.0461 | S85: 4.7405 | T85: 5.21 | U85: 4.865 | V85: 3.371 | W85: 3.057 | Y85: 4.74 | Z85: 4.48 | AA85: 4.31 | AB85: 4.32 | AC85: 4.21 | AD85: 4.15 | AE85: 4.17 | AF85: 4.17 | AG85: 4.25 | AH85: 4.3 | AI85: 4.58 | AJ85: 4.72 | AK85: 4.75 | AL85: 4.6441791 | AM85: 4.1753595 | AN85: 3.8044475 | AO85: 3.6321907 | AP85: 3.5952757 | AQ85: 3.6383558 | AT85: =(2*S85)-R85 -> 4.4349 | AU85: =(2*U85)-T85 -> 4.52 | AV85: =(2*W85)-V85 -> 2.743 | AX85: =(C85-D85)*100 -> -37 | AY85: =(AT85-AU85)*100 -> -8.51 | BA85: =C85-O85 -> -0.18 | BB85: =D85-P85 -> -0.29
A86: =+A81+7 -> 45399 | B86: 240417 | C86: 4.25 | D86: 4.59 | E86: 2.47 | F86: 3.87 | G86: 0.88 | H86: 4.99 | I86: 2.51 | J86: 3.7 | K86: 2.98 | L86: 3.3 | M86: 4.3804 | O86: 4.45 | P86: 4.93 | R86: #N/A | S86: #N/A | T86: 5.214 | U86: 4.877 | V86: #N/A | W86: #N/A | Y86: 4.71 | Z86: 4.45 | AA86: 4.28 | AB86: 4.29 | AC86: 4.18 | AD86: 4.1 | AE86: 4.12 | AF86: 4.12 | AG86: 4.2 | AH86: 4.25 | AI86: 4.52 | AJ86: 4.65 | AK86: 4.68 | AL86: 4.5975445 | AM86: 4.1071989 | AN86: 3.7244121 | AO86: 3.5634393 | AP86: 3.544147 | AQ86: 3.5959834 | AT86: =(2*S86)-R86 -> #N/A | AU86: =(2*U86)-T86 -> 4.54 | AV86: =(2*W86)-V86 -> #N/A | AX86: =(C86-D86)*100 -> -34 | AY86: =(AT86-AU86)*100 -> #N/A | BA86: =C86-O86 -> -0.2 | BB86: =D86-P86 -> -0.34
A87: =+A82+7 -> 45400 | B87: 240418 | C87: 4.27 | D87: 4.64 | E87: 2.49 | F87: 3.9 | G87: 0.868 | H87: 4.93 | I87: 2.48 | J87: 3.75 | K87: 3 | L87: 3.31 | M87: 4.2802 | O87: 4.48 | P87: 4.99 | R87: 5.0393 | S87: 4.7265 | T87: 5.193 | U87: 4.838 | V87: 3.391 | W87: 3.081 | Y87: 4.74 | Z87: 4.48 | AA87: 4.3 | AB87: 4.31 | AC87: 4.2 | AD87: 4.13 | AE87: 4.18 | AF87: 4.15 | AG87: 4.23 | AH87: 4.27 | AI87: 4.56 | AJ87: 4.7 | AK87: 4.73 | AL87: 4.6365605 | AM87: 4.1014642 | AN87: 3.7591169 | AO87: 3.6168007 | AP87: 3.588842 | AQ87: 3.626961 | AT87: =(2*S87)-R87 -> 4.4137 | AU87: =(2*U87)-T87 -> 4.483 | AV87: =(2*W87)-V87 -> 2.771 | AX87: =(C87-D87)*100 -> -37 | AY87: =(AT87-AU87)*100 -> -6.93 | BA87: =C87-O87 -> -0.21 | BB87: =D87-P87 -> -0.35
A88: =+A83+7 -> 45401 | B88: 240419 | C88: 4.23 | D88: 4.62 | E88: 2.5 | F88: 3.91 | G88: 0.841 | H88: 4.89 | I88: 2.55 | J88: 3.74 | K88: 3.02 | L88: 3.32 | M88: 4.2571 | O88: 4.39 | P88: 4.97 | R88: 4.9679 | S88: 4.6475 | T88: 5.201 | U88: 4.86 | V88: 3.404 | W88: 3.097 | Y88: 4.68 | Z88: 4.39 | AA88: 4.21 | AB88: 4.24 | AC88: 4.14 | AD88: 4.07 | AE88: 4.1 | AF88: 4.11 | AG88: 4.18 | AH88: 4.23 | AI88: 4.52 | AJ88: 4.67 | AK88: 4.71 | AL88: 4.5149809 | AM88: 4.0189512 | AN88: 3.7221197 | AO88: 3.5930194 | AP88: 3.5583257 | AQ88: 3.58897 | AT88: =(2*S88)-R88 -> 4.3271 | AU88: =(2*U88)-T88 -> 4.519 | AV88: =(2*W88)-V88 -> 2.79 | AX88: =(C88-D88)*100 -> -39 | AY88: =(AT88-AU88)*100 -> -19.19 | BA88: =C88-O88 -> -0.16 | BB88: =D88-P88 -> -0.35
A89: =+A84+7 -> 45404 | B89: 240422 | C89: 4.2 | D89: 4.62 | E89: 2.49 | F89: 3.81 | G89: 0.891 | H89: 4.95 | I89: 2.47 | J89: 3.75 | K89: 2.98 | L89: 3.26 | M89: 4.3196 | O89: 4.33 | P89: 4.97 | R89: 4.9127 | S89: 4.5819 | T89: 5.223 | U89: 4.902 | V89: 3.367 | W89: 3.057 | Y89: 4.61 | Z89: 4.33 | AA89: 4.15 | AB89: 4.19 | AC89: 4.09 | AD89: 4.04 | AE89: 4.07 | AF89: 4.07 | AG89: 4.15 | AH89: 4.2 | AI89: 4.5 | AJ89: 4.65 | AK89: 4.69 | AL89: 4.4631532 | AM89: 4.024273 | AN89: 3.7018565 | AO89: 3.551556 | AP89: 3.5225063 | AQ89: 3.5736335 | AT89: =(2*S89)-R89 -> 4.2511 | AU89: =(2*U89)-T89 -> 4.581 | AV89: =(2*W89)-V89 -> 2.747 | AX89: =(C89-D89)*100 -> -42 | AY89: =(AT89-AU89)*100 -> -32.99 | BA89: =C89-O89 -> -0.13 | BB89: =D89-P89 -> -0.35
A90: =+A85+7 -> 45405 | B90: 240423 | C90: 4.23 | D90: 4.61 | E90: 2.51 | F90: 3.81 | G90: 0.885 | H90: 4.91 | I90: 2.45 | J90: 3.76 | K90: 3.01 | L90: 3.29 | M90: 4.2681 | O90: 4.35 | P90: 4.93 | R90: 4.9508 | S90: 4.624 | T90: 5.221 | U90: 4.89 | V90: 3.381 | W90: 3.069 | Y90: 4.64 | Z90: 4.35 | AA90: 4.19 | AB90: 4.23 | AC90: 4.13 | AD90: 4.07 | AE90: 4.1 | AF90: 4.1 | AG90: 4.18 | AH90: 4.23 | AI90: 4.52 | AJ90: 4.67 | AK90: 4.72 | AL90: 4.5031148 | AM90: 4.0641847 | AN90: 3.7295495 | AO90: 3.5749908 | AP90: 3.5475003 | AQ90: 3.598513 | AT90: =(2*S90)-R90 -> 4.2972 | AU90: =(2*U90)-T90 -> 4.559 | AV90: =(2*W90)-V90 -> 2.757 | AX90: =(C90-D90)*100 -> -38 | AY90: =(AT90-AU90)*100 -> -26.18 | BA90: =C90-O90 -> -0.12 | BB90: =D90-P90 -> -0.32
A91: =+A86+7 -> 45406 | B91: 240424 | C91: 4.33 | D91: 4.65 | E91: 2.59 | F91: 3.95 | G91: 0.884 | H91: 4.95 | I91: 2.51 | J91: 3.81 | K91: 3.09 | L91: 3.39 | M91: 4.4098 | O91: 4.45 | P91: 4.94 | R91: 4.996 | S91: 4.6955 | T91: 5.202 | U91: 4.865 | V91: 3.419 | W91: 3.124 | Y91: 4.74 | Z91: 4.45 | AA91: 4.3 | AB91: 4.33 | AC91: 4.22 | AD91: 4.17 | AE91: 4.2 | AF91: 4.21 | AG91: 4.29 | AH91: 4.33 | AI91: 4.62 | AJ91: 4.76 | AK91: 4.81 | AL91: 4.585914 | AM91: 4.1608696 | AN91: 3.8148468 | AO91: 3.6718085 | AP91: 3.6623326 | AQ91: 3.7206555 | AT91: =(2*S91)-R91 -> 4.395 | AU91: =(2*U91)-T91 -> 4.528 | AV91: =(2*W91)-V91 -> 2.829 | AX91: =(C91-D91)*100 -> -32 | AY91: =(AT91-AU91)*100 -> -13.3 | BA91: =C91-O91 -> -0.12 | BB91: =D91-P91 -> -0.29
A92: =+A87+7 -> 45407 | B92: 240425 | C92: 4.36 | D92: 4.7 | E92: 2.63 | F92: 3.99 | G92: 0.896 | H92: #N/A | I92: 2.56 | J92: 3.87 | K92: 3.13 | L92: 3.44 | M92: 4.4098 | O92: 4.5 | P92: 5 | R92: 5.026 | S92: 4.7385 | T92: 5.188 | U92: 4.848 | V92: 3.46 | W92: 3.173 | Y92: 4.78 | Z92: 4.5 | AA92: 4.34 | AB92: 4.37 | AC92: 4.26 | AD92: 4.2 | AE92: 4.22 | AF92: 4.23 | AG92: 4.31 | AH92: 4.36 | AI92: 4.64 | AJ92: 4.79 | AK92: 4.83 | AL92: 4.6421697 | AM92: 4.1840556 | AN92: 3.8431144 | AO92: 3.7149131 | AP92: 3.6988822 | AQ92: 3.7448667 | AT92: =(2*S92)-R92 -> 4.451 | AU92: =(2*U92)-T92 -> 4.508 | AV92: =(2*W92)-V92 -> 2.886 | AX92: =(C92-D92)*100 -> -34 | AY92: =(AT92-AU92)*100 -> -5.7 | BA92: =C92-O92 -> -0.14 | BB92: =D92-P92 -> -0.3
A93: =+A88+7 -> 45408 | B93: 240426 | C93: 4.33 | D93: 4.67 | E93: 2.58 | F93: 3.89 | G93: 0.896 | H93: 5.04 | I93: 2.49 | J93: 3.83 | K93: 3.07 | L93: 3.37 | M93: 4.5226 | O93: 4.48 | P93: 5 | R93: 5.0188 | S93: 4.7288 | T93: 5.245 | U93: 4.926 | V93: 3.444 | W93: 3.143 | Y93: 4.76 | Z93: 4.48 | AA93: 4.33 | AB93: 4.36 | AC93: 4.25 | AD93: 4.17 | AE93: 4.19 | AF93: 4.2 | AG93: 4.28 | AH93: 4.33 | AI93: 4.6 | AJ93: 4.74 | AK93: 4.78 | AL93: 4.6180653 | AM93: 4.1455133 | AN93: 3.8348361 | AO93: 3.6999131 | AP93: 3.6647859 | AQ93: 3.6957686 | AT93: =(2*S93)-R93 -> 4.4388 | AU93: =(2*U93)-T93 -> 4.607 | AV93: =(2*W93)-V93 -> 2.842 | AX93: =(C93-D93)*100 -> -34 | AY93: =(AT93-AU93)*100 -> -16.82 | BA93: =C93-O93 -> -0.15 | BB93: =D93-P93 -> -0.33
A94: =+A89+7 -> 45411 | B94: 240429 | C94: 4.28 | D94: 4.63 | E94: 2.53 | F94: 3.82 | G94: 0.928 | H94: 4.98 | I94: 2.51 | J94: 3.76 | K94: 3.02 | L94: 3.3 | M94: 4.4886 | O94: 4.45 | P94: 4.97 | R94: 4.9951 | S94: 4.6854 | T94: 5.226 | U94: 4.898 | V94: 3.415 | W94: 3.106 | Y94: 4.73 | Z94: 4.45 | AA94: 4.28 | AB94: 4.32 | AC94: 4.21 | AD94: 4.13 | AE94: 4.16 | AF94: 4.16 | AG94: 4.24 | AH94: 4.28 | AI94: 4.56 | AJ94: 4.71 | AK94: 4.75 | AL94: 4.5901511 | AM94: 4.1344014 | AN94: 3.7928362 | AO94: 3.6357626 | AP94: 3.6041305 | AQ94: 3.6525416 | AT94: =(2*S94)-R94 -> 4.3757 | AU94: =(2*U94)-T94 -> 4.57 | AV94: =(2*W94)-V94 -> 2.797 | AX94: =(C94-D94)*100 -> -35 | AY94: =(AT94-AU94)*100 -> -19.43 | BA94: =C94-O94 -> -0.17 | BB94: =D94-P94 -> -0.34
A95: =+A90+7 -> 45412 | B95: 240430 | C95: 4.36 | D95: 4.69 | E95: 2.59 | F95: 3.89 | G95: 0.869 | H95: 4.94 | I95: 2.49 | J95: 3.82 | K95: 3.08 | L95: 3.37 | M95: 4.4222 | O95: 4.52 | P95: 5.05 | R95: 5.0394 | S95: 4.755 | T95: 5.238 | U95: 4.908 | V95: 3.483 | W95: 3.2 | Y95: 4.79 | Z95: 4.52 | AA95: 4.35 | AB95: 4.38 | AC95: 4.27 | AD95: 4.2 | AE95: 4.23 | AF95: 4.23 | AG95: 4.31 | AH95: 4.36 | AI95: 4.63 | AJ95: 4.76 | AK95: 4.8 | AL95: 4.6642637 | AM95: 4.2393928 | AN95: 3.863759 | AO95: 3.6953248 | AP95: 3.6622123 | AQ95: 3.707335 | AT95: =(2*S95)-R95 -> 4.4706 | AU95: =(2*U95)-T95 -> 4.578 | AV95: =(2*W95)-V95 -> 2.917 | AX95: =(C95-D95)*100 -> -33 | AY95: =(AT95-AU95)*100 -> -10.74 | BA95: =C95-O95 -> -0.16 | BB95: =D95-P95 -> -0.36
A96: =+A91+7 -> 45413 | B96: 240501 | C96: 4.36 | D96: 4.63 | E96: 2.58 | F96: 3.88 | G96: 0.886 | H96: 4.96 | I96: 2.48 | J96: 3.76 | K96: 3.08 | L96: 3.36 | M96: 4.5125 | O96: 4.52 | P96: 4.94 | R96: 5.0462 | S96: 4.7751 | T96: 5.282 | U96: 4.965 | V96: 3.467 | W96: 3.186 | Y96: 4.78 | Z96: 4.52 | AA96: 4.36 | AB96: 4.39 | AC96: 4.27 | AD96: 4.21 | AE96: 4.24 | AF96: 4.24 | AG96: 4.31 | AH96: 4.36 | AI96: 4.64 | AJ96: 4.77 | AK96: 4.81 | AL96: 4.7086454 | AM96: 4.2495301 | AN96: 3.8406074 | AO96: 3.693288 | AP96: 3.677319 | AQ96: 3.7200887 | AT96: =(2*S96)-R96 -> 4.504 | AU96: =(2*U96)-T96 -> 4.648 | AV96: =(2*W96)-V96 -> 2.905 | AX96: =(C96-D96)*100 -> -27 | AY96: =(AT96-AU96)*100 -> -14.4 | BA96: =C96-O96 -> -0.16 | BB96: =D96-P96 -> -0.31
A97: =+A92+7 -> 45414 | B97: 240502 | C97: 4.28 | D97: 4.58 | E97: 2.54 | F97: 3.86 | G97: 0.896 | H97: 4.89 | I97: 2.5 | J97: 3.74 | K97: 3.04 | L97: 3.31 | M97: 4.4458 | O97: 4.42 | P97: 4.88 | R97: 4.9894 | S97: 4.6806 | T97: 5.225 | U97: 4.87 | V97: 3.431 | W97: 3.131 | Y97: 4.7 | Z97: 4.42 | AA97: 4.27 | AB97: 4.29 | AC97: 4.18 | AD97: 4.13 | AE97: 4.21 | AF97: 4.16 | AG97: 4.23 | AH97: 4.28 | AI97: 4.57 | AJ97: 4.72 | AK97: 4.75 | AL97: 4.5729799 | AM97: 4.1046626 | AN97: 3.7569042 | AO97: 3.6277461 | AP97: 3.6101204 | AQ97: 3.6531242 | AT97: =(2*S97)-R97 -> 4.3718 | AU97: =(2*U97)-T97 -> 4.515 | AV97: =(2*W97)-V97 -> 2.831 | AX97: =(C97-D97)*100 -> -30 | AY97: =(AT97-AU97)*100 -> -14.32 | BA97: =C97-O97 -> -0.14 | BB97: =D97-P97 -> -0.3
A98: =+A93+7 -> 45415 | B98: 240503 | C98: 4.22 | D98: 4.5 | E98: 2.49 | F98: 3.8 | G98: 0.9 | H98: 4.86 | I98: 2.41 | J98: 3.66 | K98: 3 | L98: 3.26 | M98: 4.4194 | O98: 4.36 | P98: 4.81 | R98: 4.9414 | S98: 4.6053 | T98: 5.19 | U98: 4.815 | V98: 3.395 | W98: 3.072 | Y98: 4.65 | Z98: 4.36 | AA98: 4.19 | AB98: 4.21 | AC98: 4.1 | AD98: 4.05 | AE98: 4.08 | AF98: 4.08 | AG98: 4.16 | AH98: 4.22 | AI98: 4.5 | AJ98: 4.66 | AK98: 4.7 | AL98: 4.4832177 | AM98: 3.9802119 | AN98: 3.6845594 | AO98: 3.5618538 | AP98: 3.5384056 | AQ98: 3.5799985 | AT98: =(2*S98)-R98 -> 4.2692 | AU98: =(2*U98)-T98 -> 4.44 | AV98: =(2*W98)-V98 -> 2.749 | AX98: =(C98-D98)*100 -> -28 | AY98: =(AT98-AU98)*100 -> -17.08 | BA98: =C98-O98 -> -0.14 | BB98: =D98-P98 -> -0.31
A99: =+A94+7 -> 45418 | B99: 240506 | C99: #N/A | D99: 4.49 | E99: 2.47 | F99: 3.79 | G99: 0.897 | H99: 4.79 | I99: 2.36 | J99: 3.61 | K99: 2.98 | L99: 3.24 | M99: 4.3826 | O99: 4.37 | P99: 4.82 | R99: 4.9414 | S99: 4.6053 | T99: 5.133 | U99: 4.713 | V99: 3.387 | W99: 3.055 | Y99: 4.65 | Z99: 4.37 | AA99: 4.2 | AB99: #N/A | AC99: #N/A | AD99: 4.07 | AE99: 4.21 | AF99: 4.09 | AG99: 4.17 | AH99: #N/A | AI99: #N/A | AJ99: 4.68 | AK99: 4.72 | AL99: #N/A | AM99: #N/A | AN99: #N/A | AO99: #N/A | AP99: #N/A | AQ99: #N/A | AT99: =(2*S99)-R99 -> 4.2692 | AU99: =(2*U99)-T99 -> 4.293 | AV99: =(2*W99)-V99 -> 2.723 | AX99: =(C99-D99)*100 -> #N/A | AY99: =(AT99-AU99)*100 -> -2.38 | BA99: =C99-O99 -> #N/A | BB99: =D99-P99 -> -0.33
A100: =+A95+7 -> 45419 | B100: 240507 | C100: 4.13 | D100: 4.47 | E100: 2.43 | F100: 3.76 | G100: 0.87 | H100: 4.74 | I100: 2.29 | J100: 3.59 | K100: 2.93 | L100: 3.22 | M100: 4.3078 | O100: 4.3 | P100: 4.83 | R100: 4.9185 | S100: 4.5541 | T100: 5.145 | U100: 4.729 | V100: 3.39 | W100: 3.053 | Y100: 4.62 | Z100: 4.3 | AA100: 4.13 | AB100: 4.14 | AC100: 4.03 | AD100: 3.97 | AE100: 3.99 | AF100: 4 | AG100: 4.07 | AH100: 4.13 | AI100: 4.41 | AJ100: 4.57 | AK100: 4.61 | AL100: 4.4268952 | AM100: 3.9496039 | AN100: 3.5873863 | AO100: 3.4376648 | AP100: 3.426485 | AQ100: 3.489822 | AT100: =(2*S100)-R100 -> 4.1897 | AU100: =(2*U100)-T100 -> 4.313 | AV100: =(2*W100)-V100 -> 2.716 | AX100: =(C100-D100)*100 -> -34 | AY100: =(AT100-AU100)*100 -> -12.33 | BA100: =C100-O100 -> -0.17 | BB100: =D100-P100 -> -0.36
A101: =+A96+7 -> 45420 | B101: 240508 | C101: 4.13 | D101: 4.48 | E101: 2.47 | F101: 3.8 | G101: 0.875 | H101: 4.7 | I101: 2.35 | J101: 3.63 | K101: 2.96 | L101: 3.26 | M101: 4.292 | O101: 4.31 | P101: 4.84 | R101: 4.9062 | S101: 4.5515 | T101: 5.16 | U101: 4.752 | V101: 3.41 | W101: 3.083 | Y101: 4.64 | Z101: 4.31 | AA101: 4.12 | AB101: 4.14 | AC101: 4.02 | AD101: 3.97 | AE101: 3.99 | AF101: 4 | AG101: 4.08 | AH101: 4.13 | AI101: 4.43 | AJ101: 4.57 | AK101: 4.61 | AL101: 4.4436754 | AM101: 3.9313985 | AN101: 3.5656394 | AO101: 3.4373864 | AP101: 3.4343059 | AQ101: 3.492279 | AT101: =(2*S101)-R101 -> 4.1968 | AU101: =(2*U101)-T101 -> 4.344 | AV101: =(2*W101)-V101 -> 2.756 | AX101: =(C101-D101)*100 -> -35 | AY101: =(AT101-AU101)*100 -> -14.72 | BA101: =C101-O101 -> -0.18 | BB101: =D101-P101 -> -0.36
A102: =+A97+7 -> 45421 | B102: 240509 | C102: 4.14 | D102: 4.45 | E102: 2.49 | F102: 3.82 | G102: 0.914 | H102: 4.76 | I102: 2.34 | J102: 3.63 | K102: 3 | L102: 3.27 | M102: 4.3509 | O102: 4.27 | P102: 4.81 | R102: 4.8725 | S102: 4.501 | T102: 5.156 | U102: 4.763 | V102: 3.404 | W102: 3.074 | Y102: 4.62 | Z102: 4.27 | AA102: 4.09 | AB102: 4.13 | AC102: 4 | AD102: 3.96 | AE102: 3.98 | AF102: 4 | AG102: 4.08 | AH102: 4.14 | AI102: 4.42 | AJ102: 4.58 | AK102: 4.62 | AL102: 4.3419605 | AM102: 3.850773 | AN102: 3.5379177 | AO102: 3.4433861 | AP102: 3.4562358 | AQ102: 3.5220022 | AT102: =(2*S102)-R102 -> 4.1295 | AU102: =(2*U102)-T102 -> 4.37 | AV102: =(2*W102)-V102 -> 2.744 | AX102: =(C102-D102)*100 -> -31 | AY102: =(AT102-AU102)*100 -> -24.05 | BA102: =C102-O102 -> -0.13 | BB102: =D102-P102 -> -0.36
A103: =+A98+7 -> 45422 | B103: 240510 | C103: 4.17 | D103: 4.5 | E103: 2.52 | F103: 3.86 | G103: 0.905 | H103: 4.77 | I103: 2.42 | J103: 3.7 | K103: 3.03 | L103: 3.31 | M103: 4.3225 | O103: 4.32 | P103: 4.87 | R103: 4.8947 | S103: 4.5413 | T103: 5.137 | U103: 4.734 | V103: 3.433 | W103: 3.115 | Y103: 4.65 | Z103: 4.32 | AA103: 4.14 | AB103: 4.17 | AC103: 4.05 | AD103: 4 | AE103: 4.02 | AF103: 4.03 | AG103: 4.11 | AH103: 4.17 | AI103: 4.45 | AJ103: 4.61 | AK103: 4.66 | AL103: 4.4136821 | AM103: 3.9114576 | AN103: 3.5986249 | AO103: 3.4802124 | AP103: 3.4721393 | AQ103: 3.5292218 | AT103: =(2*S103)-R103 -> 4.1879 | AU103: =(2*U103)-T103 -> 4.331 | AV103: =(2*W103)-V103 -> 2.797 | AX103: =(C103-D103)*100 -> -33 | AY103: =(AT103-AU103)*100 -> -14.31 | BA103: =C103-O103 -> -0.15 | BB103: =D103-P103 -> -0.37
A104: =+A99+7 -> 45425 | B104: 240513 | C104: 4.17 | D104: 4.48 | E104: 2.51 | F104: 3.85 | G104: 0.933 | H104: 4.76 | I104: 2.32 | J104: 3.7 | K104: 3.01 | L104: 3.3 | M104: 4.3281 | O104: 4.32 | P104: 4.86 | R104: 4.9086 | S104: 4.5615 | T104: 5.158 | U104: 4.764 | V104: 3.424 | W104: 3.101 | Y104: 4.65 | Z104: 4.32 | AA104: 4.15 | AB104: 4.18 | AC104: 4.06 | AD104: 4 | AE104: 4.03 | AF104: 4.04 | AG104: 4.11 | AH104: 4.17 | AI104: 4.43 | AJ104: 4.61 | AK104: 4.65 | AL104: 4.4502711 | AM104: 3.9658206 | AN104: 3.609809 | AO104: 3.4651596 | AP104: 3.4542919 | AQ104: 3.5200075 | AT104: =(2*S104)-R104 -> 4.2144 | AU104: =(2*U104)-T104 -> 4.37 | AV104: =(2*W104)-V104 -> 2.778 | AX104: =(C104-D104)*100 -> -31 | AY104: =(AT104-AU104)*100 -> -15.56 | BA104: =C104-O104 -> -0.15 | BB104: =D104-P104 -> -0.38
A105: =+A100+7 -> 45426 | B105: 240514 | C105: 4.16 | D105: 4.45 | E105: 2.54 | F105: 3.88 | G105: 0.955 | H105: 4.72 | I105: 2.41 | J105: 3.69 | K105: 3.05 | L105: 3.33 | M105: 4.3313 | O105: 4.31 | P105: 4.82 | R105: 4.8964 | S105: 4.5449 | T105: 5.156 | U105: 4.751 | V105: 3.447 | W105: 3.128 | Y105: 4.63 | Z105: 4.31 | AA105: 4.14 | AB105: 4.17 | AC105: 4.05 | AD105: 3.98 | AE105: 4 | AF105: 4.02 | AG105: 4.11 | AH105: 4.16 | AI105: 4.43 | AJ105: 4.59 | AK105: 4.64 | AL105: 4.4361707 | AM105: 3.9383014 | AN105: 3.58787 | AO105: 3.4590717 | AP105: 3.4555721 | AQ105: 3.5176793 | AT105: =(2*S105)-R105 -> 4.1934 | AU105: =(2*U105)-T105 -> 4.346 | AV105: =(2*W105)-V105 -> 2.809 | AX105: =(C105-D105)*100 -> -29 | AY105: =(AT105-AU105)*100 -> -15.26 | BA105: =C105-O105 -> -0.15 | BB105: =D105-P105 -> -0.37
A106: =+A101+7 -> 45427 | B106: 240515 | C106: 4.06 | D106: 4.36 | E106: 2.42 | F106: 3.71 | G106: 0.947 | H106: 4.69 | I106: 2.27 | J106: 3.57 | K106: 2.92 | L106: 3.19 | M106: 4.3168 | O106: 4.23 | P106: 4.74 | R106: 4.8593 | S106: 4.476 | T106: 5.141 | U106: 4.721 | V106: 3.384 | W106: 3.025 | Y106: 4.56 | Z106: 4.23 | AA106: 4.04 | AB106: 4.07 | AC106: 3.94 | AD106: 3.88 | AE106: 3.94 | AF106: 3.92 | AG106: 4 | AH106: 4.06 | AI106: 4.32 | AJ106: 4.49 | AK106: 4.51 | AL106: 4.3502609 | AM106: 3.8053352 | AN106: 3.467255 | AO106: 3.361525 | AP106: 3.3656233 | AQ106: 3.4229422 | AT106: =(2*S106)-R106 -> 4.0927 | AU106: =(2*U106)-T106 -> 4.301 | AV106: =(2*W106)-V106 -> 2.666 | AX106: =(C106-D106)*100 -> -30 | AY106: =(AT106-AU106)*100 -> -20.83 | BA106: =C106-O106 -> -0.17 | BB106: =D106-P106 -> -0.38
A107: =+A102+7 -> 45428 | B107: 240516 | C107: 4.07 | D107: 4.38 | E107: 2.46 | F107: 3.76 | G107: 0.924 | H107: 4.61 | I107: 2.3 | J107: 3.57 | K107: 2.96 | L107: 3.23 | M107: 4.1919 | O107: 4.26 | P107: 4.79 | R107: 4.8684 | S107: 4.4945 | T107: 5.106 | U107: 4.652 | V107: 3.422 | W107: 3.081 | Y107: 4.59 | Z107: 4.26 | AA107: 4.07 | AB107: 4.1 | AC107: 3.97 | AD107: 3.91 | AE107: 3.95 | AF107: 3.94 | AG107: 4.02 | AH107: 4.07 | AI107: 4.36 | AJ107: 4.52 | AK107: 4.56 | AL107: 4.3538116 | AM107: 3.8278236 | AN107: 3.5047163 | AO107: 3.3950757 | AP107: 3.3943738 | AQ107: 3.4519508 | AT107: =(2*S107)-R107 -> 4.1206 | AU107: =(2*U107)-T107 -> 4.198 | AV107: =(2*W107)-V107 -> 2.74 | AX107: =(C107-D107)*100 -> -31 | AY107: =(AT107-AU107)*100 -> -7.74 | BA107: =C107-O107 -> -0.19 | BB107: =D107-P107 -> -0.41
A108: =+A103+7 -> 45429 | B108: 240517 | C108: 4.12 | D108: 4.42 | E108: 2.52 | F108: 3.83 | G108: 0.952 | H108: 4.64 | I108: 2.41 | J108: 3.63 | K108: 3.01 | L108: 3.28 | M108: 4.2134 | O108: 4.32 | P108: 4.83 | R108: 4.8837 | S108: 4.5242 | T108: 5.134 | U108: 4.702 | V108: 3.466 | W108: 3.147 | Y108: 4.65 | Z108: 4.32 | AA108: 4.12 | AB108: 4.15 | AC108: 4.02 | AD108: 3.96 | AE108: 4.22 | AF108: 4 | AG108: 4.07 | AH108: 4.12 | AI108: 4.41 | AJ108: 4.56 | AK108: 4.61 | AL108: 4.4029029 | AM108: 3.887147 | AN108: 3.5822574 | AO108: 3.4657414 | AP108: 3.4518116 | AQ108: 3.5009502 | AT108: =(2*S108)-R108 -> 4.1647 | AU108: =(2*U108)-T108 -> 4.27 | AV108: =(2*W108)-V108 -> 2.828 | AX108: =(C108-D108)*100 -> -30 | AY108: =(AT108-AU108)*100 -> -10.53 | BA108: =C108-O108 -> -0.2 | BB108: =D108-P108 -> -0.41
A109: =+A104+7 -> 45432 | B109: 240520 | C109: 4.17 | D109: 4.44 | E109: 2.53 | F109: 3.82 | G109: 0.976 | H109: 4.65 | I109: 2.37 | J109: #N/A | K109: 3.02 | L109: 3.29 | M109: 4.237 | O109: 4.35 | P109: 4.84 | R109: 4.8974 | S109: 4.5501 | T109: 5.147 | U109: 4.724 | V109: 3.468 | W109: 3.155 | Y109: 4.68 | Z109: 4.35 | AA109: 4.16 | AB109: 4.19 | AC109: 4.06 | AD109: 4 | AE109: 4.03 | AF109: 4.04 | AG109: 4.12 | AH109: 4.17 | AI109: 4.45 | AJ109: 4.61 | AK109: 4.66 | AL109: 4.4466964 | AM109: 3.9537193 | AN109: 3.6200981 | AO109: 3.4916913 | AP109: 3.4839397 | AQ109: 3.5474531 | AT109: =(2*S109)-R109 -> 4.2028 | AU109: =(2*U109)-T109 -> 4.301 | AV109: =(2*W109)-V109 -> 2.842 | AX109: =(C109-D109)*100 -> -27 | AY109: =(AT109-AU109)*100 -> -9.82 | BA109: =C109-O109 -> -0.18 | BB109: =D109-P109 -> -0.4
A110: =+A105+7 -> 45433 | B110: 240521 | C110: 4.13 | D110: 4.41 | E110: 2.51 | F110: 3.8 | G110: 0.975 | H110: 4.67 | I110: 2.33 | J110: 3.58 | K110: 3 | L110: 3.28 | M110: 4.2526 | O110: 4.3 | P110: 4.83 | R110: 4.8885 | S110: 4.5252 | T110: 5.155 | U110: 4.731 | V110: 3.453 | W110: 3.13 | Y110: 4.62 | Z110: 4.3 | AA110: 4.11 | AB110: 4.14 | AC110: 4.01 | AD110: 3.95 | AE110: 4 | AF110: 3.99 | AG110: 4.07 | AH110: 4.13 | AI110: 4.4 | AJ110: 4.56 | AK110: 4.61 | AL110: 4.4113217 | AM110: 3.8964215 | AN110: 3.5642754 | AO110: 3.4488243 | AP110: 3.4436568 | AQ110: 3.5022427 | AT110: =(2*S110)-R110 -> 4.1619 | AU110: =(2*U110)-T110 -> 4.307 | AV110: =(2*W110)-V110 -> 2.807 | AX110: =(C110-D110)*100 -> -28 | AY110: =(AT110-AU110)*100 -> -14.51 | BA110: =C110-O110 -> -0.17 | BB110: =D110-P110 -> -0.42
A111: =+A106+7 -> 45434 | B111: 240522 | C111: 4.23 | D111: 4.43 | E111: 2.54 | F111: 3.83 | G111: 1.002 | H111: 4.72 | I111: 2.41 | J111: 3.6 | K111: 3.03 | L111: 3.3 | M111: 4.2848 | O111: 4.45 | P111: 4.88 | R111: 5.0381 | S111: 4.6954 | T111: 5.169 | U111: 4.727 | V111: 3.494 | W111: 3.182 | Y111: 4.79 | Z111: 4.45 | AA111: 4.26 | AB111: 4.28 | AC111: 4.14 | AD111: 4.07 | AE111: 4.09 | AF111: 4.1 | AG111: 4.18 | AH111: 4.23 | AI111: 4.49 | AJ111: 4.64 | AK111: 4.7 | AL111: 4.5755412 | AM111: 4.0943236 | AN111: 3.6384224 | AO111: 3.5114404 | AP111: 3.51755 | AQ111: 3.5754235 | AT111: =(2*S111)-R111 -> 4.3527 | AU111: =(2*U111)-T111 -> 4.285 | AV111: =(2*W111)-V111 -> 2.87 | AX111: =(C111-D111)*100 -> -20 | AY111: =(AT111-AU111)*100 -> 6.77 | BA111: =C111-O111 -> -0.22 | BB111: =D111-P111 -> -0.45
A112: =+A107+7 -> 45435 | B112: 240523 | C112: 4.26 | D112: 4.47 | E112: 2.59 | F112: 3.89 | G112: 0.995 | H112: 4.77 | I112: 2.44 | J112: 3.62 | K112: 3.08 | L112: 3.34 | M112: 4.2563 | O112: 4.5 | P112: 4.93 | R112: 5.0726 | S112: 4.7391 | T112: 5.164 | U112: 4.756 | V112: 3.524 | W112: 3.238 | Y112: 4.85 | Z112: 4.5 | AA112: 4.31 | AB112: 4.32 | AC112: 4.18 | AD112: 4.11 | AE112: 4.12 | AF112: 4.13 | AG112: 4.2 | AH112: 4.26 | AI112: 4.51 | AJ112: 4.65 | AK112: 4.7 | AL112: 4.644142 | AM112: 4.0730422 | AN112: 3.6752541 | AO112: 3.5320195 | AP112: 3.5136186 | AQ112: 3.561849 | AT112: =(2*S112)-R112 -> 4.4056 | AU112: =(2*U112)-T112 -> 4.348 | AV112: =(2*W112)-V112 -> 2.952 | AX112: =(C112-D112)*100 -> -21 | AY112: =(AT112-AU112)*100 -> 5.76 | BA112: =C112-O112 -> -0.24 | BB112: =D112-P112 -> -0.46
A113: =+A108+7 -> 45436 | B113: 240524 | C113: 4.26 | D113: 4.46 | E113: 2.58 | F113: 3.89 | G113: 1.001 | H113: 4.81 | I113: 2.43 | J113: 3.61 | K113: 3.07 | L113: 3.34 | M113: 4.312 | O113: 4.51 | P113: 4.95 | R113: 5.0676 | S113: 4.7395 | T113: 5.204 | U113: 4.822 | V113: 3.547 | W113: 3.261 | Y113: 4.85 | Z113: 4.51 | AA113: 4.31 | AB113: 4.33 | AC113: 4.18 | AD113: 4.11 | AE113: 4.15 | AF113: 4.13 | AG113: 4.21 | AH113: 4.26 | AI113: 4.52 | AJ113: 4.67 | AK113: 4.71 | AL113: 4.6575197 | AM113: 4.0769844 | AN113: 3.6985719 | AO113: 3.5500656 | AP113: 3.5227144 | AQ113: 3.5657763 | AT113: =(2*S113)-R113 -> 4.4114 | AU113: =(2*U113)-T113 -> 4.44 | AV113: =(2*W113)-V113 -> 2.975 | AX113: =(C113-D113)*100 -> -20 | AY113: =(AT113-AU113)*100 -> -2.86 | BA113: =C113-O113 -> -0.25 | BB113: =D113-P113 -> -0.49
A114: =+A109+7 -> 45439 | B114: 240527 | C114: 4.26 | D114: #N/A | E114: 2.55 | F114: 3.84 | G114: 1.024 | H114: 4.81 | I114: 2.38 | J114: 3.63 | K114: 3.03 | L114: 3.3 | M114: 4.2774 | O114: 4.5 | P114: #N/A | R114: 5.0676 | S114: 4.7395 | T114: #N/A | U114: #N/A | V114: 3.51 | W114: 3.214 | Y114: 4.84 | Z114: 4.5 | AA114: 4.31 | AB114: 4.32 | AC114: 4.18 | AD114: 4.1 | AE114: 4.24 | AF114: 4.13 | AG114: 4.2 | AH114: 4.26 | AI114: 4.52 | AJ114: 4.66 | AK114: 4.71 | AL114: #N/A | AM114: #N/A | AN114: #N/A | AO114: #N/A | AP114: #N/A | AQ114: #N/A | AT114: =(2*S114)-R114 -> 4.4114 | AU114: =(2*U114)-T114 -> #N/A | AV114: =(2*W114)-V114 -> 2.918 | AX114: =(C114-D114)*100 -> #N/A | AY114: =(AT114-AU114)*100 -> #N/A | BA114: =C114-O114 -> -0.24 | BB114: =D114-P114 -> #N/A
A115: =+A110+7 -> 45440 | B115: 240528 | C115: 4.27 | D115: 4.54 | E115: 2.6 | F115: 3.91 | G115: 1.035 | H115: 4.84 | I115: 2.36 | J115: 3.7 | K115: 3.09 | L115: 3.37 | M115: 4.2627 | O115: 4.51 | P115: 4.98 | R115: 5.0689 | S115: 4.7459 | T115: 5.205 | U115: 4.819 | V115: 3.527 | W115: 3.248 | Y115: 4.85 | Z115: 4.51 | AA115: 4.31 | AB115: 4.34 | AC115: 4.19 | AD115: 4.12 | AE115: 4.14 | AF115: 4.15 | AG115: 4.23 | AH115: 4.27 | AI115: 4.54 | AJ115: 4.69 | AK115: 4.74 | AL115: 4.6661869 | AM115: 4.1380999 | AN115: 3.7131421 | AO115: 3.5403989 | AP115: 3.5198739 | AQ115: 3.5791635 | AT115: =(2*S115)-R115 -> 4.4229 | AU115: =(2*U115)-T115 -> 4.433 | AV115: =(2*W115)-V115 -> 2.969 | AX115: =(C115-D115)*100 -> -27 | AY115: =(AT115-AU115)*100 -> -1.01 | BA115: =C115-O115 -> -0.24 | BB115: =D115-P115 -> -0.44
A116: =+A111+7 -> 45441 | B116: 240529 | C116: 4.41 | D116: 4.61 | E116: 2.69 | F116: 4.03 | G116: 1.084 | H116: 4.91 | I116: 2.43 | J116: 3.76 | K116: 3.19 | L116: 3.44 | M116: 4.3978 | O116: 4.58 | P116: 4.99 | R116: 5.0951 | S116: 4.7982 | T116: 5.23 | U116: 4.867 | V116: 3.537 | W116: 3.273 | Y116: 4.91 | Z116: 4.58 | AA116: 4.42 | AB116: 4.45 | AC116: 4.31 | AD116: 4.25 | AE116: 4.27 | AF116: 4.28 | AG116: 4.36 | AH116: 4.41 | AI116: 4.67 | AJ116: 4.83 | AK116: 4.87 | AL116: 4.7297872 | AM116: 4.2215273 | AN116: 3.827656 | AO116: 3.6795389 | AP116: 3.6680118 | AQ116: 3.724459 | AT116: =(2*S116)-R116 -> 4.5013 | AU116: =(2*U116)-T116 -> 4.504 | AV116: =(2*W116)-V116 -> 3.009 | AX116: =(C116-D116)*100 -> -20 | AY116: =(AT116-AU116)*100 -> -0.27 | BA116: =C116-O116 -> -0.17 | BB116: =D116-P116 -> -0.38
...

Sheet BoE market pricing
A1: Interest rates - OE forecast & market expectations - monthly
D2: 45292 | E2: 45323 | F2: 45352 | G2: 45383 | H2: 45413 | I2: 45444 | J2: 45474 | K2: 45505 | L2: 45536 | M2: 45566 | N2: 45597 | O2: 45627 | P2: 45658 | Q2: 45689 | R2: 45717 | S2: 45748 | T2: 45778 | U2: 45809 | V2: 45839 | W2: 45870 | X2: 45901 | Y2: 45931 | Z2: 45962 | AA2: 45992 | AB2: 46023 | AC2: 46054 | AD2: 46082 | AE2: 46113 | AF2: 46143 | AG2: 46174 | AH2: 46204 | AI2: 46235 | AJ2: 46266 | AK2: 46296 | AL2: 46327 | AM2: 46357 | AN2: 46388 | AO2: 46419 | AP2: 46447 | AQ2: 46478 | AR2: 46508 | AS2: 46539 | AT2: 46569 | AU2: 46600 | AV2: 46631 | AW2: 46661 | AX2: 46692 | AY2: 46722
D3: =EOMONTH(D2,0) -> 45322 | E3: =EOMONTH(E2,0) -> 45351 | F3: =EOMONTH(F2,0) -> 45382 | G3: =EOMONTH(G2,0) -> 45412 | H3: =EOMONTH(H2,0) -> 45443 | I3: =EOMONTH(I2,0) -> 45473 | J3: =EOMONTH(J2,0) -> 45504 | K3: =EOMONTH(K2,0) -> 45535 | ... AY3: =EOMONTH(AY2,0) -> 46752
A4: =C4 -> Bank Rate | B4: =C4 -> Bank Rate | C4: Bank Rate | D4: =VLOOKUP(D2,HAVERM!$A:$C,3,FALSE) -> 5.25 | E4: =VLOOKUP(E2,HAVERM!$A:$C,3,FALSE) -> 5.25 | F4: =VLOOKUP(F2,HAVERM!$A:$C,3,FALSE) -> 5.25 | G4: =VLOOKUP(G2,HAVERM!$A:$C,3,FALSE) -> 5.25 | H4: =VLOOKUP(H2,HAVERM!$A:$C,3,FALSE) -> 5.25 | I4: =VLOOKUP(I2,HAVERM!$A:$C,3,FALSE) -> 5.25 | J4: =VLOOKUP(J2,HAVERM!$A:$C,3,FALSE) -> 5.25 | K4: =VLOOKUP(K2,HAVERM!$A:$C,3,FALSE) -> 5 | ... AY4: =VLOOKUP(AY2,HAVERM!$A:$C,3,FALSE) -> #N/A
A5: Market expectations - Pre-conflict | B5: =C5 -> 46080 | C5: =C14 -> 46080 | D5: =HLOOKUP(D$3,$D$13:$AN$14,2,FALSE) -> #N/A | E5: =HLOOKUP(E$3,$D$13:$AN$14,2,FALSE) -> #N/A | F5: =HLOOKUP(F$3,$D$13:$AN$14,2,FALSE) -> #N/A | G5: =HLOOKUP(G$3,$D$13:$AN$14,2,FALSE) -> #N/A | H5: =HLOOKUP(H$3,$D$13:$AN$14,2,FALSE) -> #N/A | I5: =HLOOKUP(I$3,$D$13:$AN$14,2,FALSE) -> #N/A | J5: =HLOOKUP(J$3,$D$13:$AN$14,2,FALSE) -> #N/A | K5: =HLOOKUP(K$3,$D$13:$AN$14,2,FALSE) -> #N/A | ... AY5: =HLOOKUP(AY$3,$D$13:$AN$14,2,FALSE) -> 3.3130203
A6: Market expectations - Current | B6: =C6 -> 46153 | C6: =C22 -> 46153 | D6: =HLOOKUP(D$3,$D$21:$AN$22,2,FALSE) -> #N/A | E6: =HLOOKUP(E$3,$D$21:$AN$22,2,FALSE) -> #N/A | F6: =HLOOKUP(F$3,$D$21:$AN$22,2,FALSE) -> #N/A | G6: =HLOOKUP(G$3,$D$21:$AN$22,2,FALSE) -> #N/A | H6: =HLOOKUP(H$3,$D$21:$AN$22,2,FALSE) -> #N/A | I6: =HLOOKUP(I$3,$D$21:$AN$22,2,FALSE) -> #N/A | J6: =HLOOKUP(J$3,$D$21:$AN$22,2,FALSE) -> #N/A | K6: =HLOOKUP(K$3,$D$21:$AN$22,2,FALSE) -> #N/A | ... AY6: =HLOOKUP(AY$3,$D$21:$AN$22,2,FALSE) -> 4.442842
A7: =C7 -> OE forecast | C7: OE forecast | D7: =IF(D3>$E$1,HLOOKUP(D$3,$AK$34:$EN$35,2,FALSE),NA()) -> #N/A | E7: =IF(E3>$E$1,HLOOKUP(E$3,$AK$34:$EN$35,2,FALSE),NA()) -> #N/A | F7: =IF(F3>$E$1,HLOOKUP(F$3,$AK$34:$EN$35,2,FALSE),NA()) -> #N/A | G7: =IF(G3>$E$1,HLOOKUP(G$3,$AK$34:$EN$35,2,FALSE),NA()) -> #N/A | H7: =IF(H3>$E$1,HLOOKUP(H$3,$AK$34:$EN$35,2,FALSE),NA()) -> #N/A | I7: =IF(I3>$E$1,HLOOKUP(I$3,$AK$34:$EN$35,2,FALSE),NA()) -> #N/A | J7: =IF(J3>$E$1,HLOOKUP(J$3,$AK$34:$EN$35,2,FALSE),NA()) -> #N/A | K7: =IF(K3>$E$1,HLOOKUP(K$3,$AK$34:$EN$35,2,FALSE),NA()) -> #N/A | ... AD7: =IF(AD3>$E$1,HLOOKUP(AD$3,$AK$34:$EN$35,2,FALSE),NA()) -> #N/A | AE7: =AE4 -> 3.75 | AF7: =AE7 -> 3.75 | AG7: =AF7 -> 3.75 | AH7: =AG7 -> 3.75 | AI7: =AH7 -> 3.75 | AJ7: =AI7 -> 3.75 | AK7: =AJ7 -> 3.75 | AL7: =AK7 -> 3.75 | AM7: =AL7 -> 3.75 | ... AW7: =AV7 -> 3.75 | AX7: =AW7-0.25 -> 3.5 | AY7: =AX7 -> 3.5
C9: Column # | D9: 4 | E9: =+D9+1 -> 5 | F9: =+E9+1 -> 6 | G9: =+F9+1 -> 7 | H9: =+G9+1 -> 8 | I9: =+H9+1 -> 9 | J9: =+I9+1 -> 10 | K9: =+J9+1 -> 11 | L9: =+K9+1 -> 12 | ... BL9: =+BK9+1 -> 64
C10: Months | D10: ='HAVER BoE'!D1 -> Overnight | E10: ='HAVER BoE'!E1 -> 1 | F10: ='HAVER BoE'!F1 -> 2 | G10: ='HAVER BoE'!G1 -> 3 | H10: ='HAVER BoE'!H1 -> 4 | I10: ='HAVER BoE'!I1 -> 5 | J10: ='HAVER BoE'!J1 -> 6 | K10: ='HAVER BoE'!K1 -> 7 | ... BL10: ='HAVER BoE'!BL1 -> 60
C11: Days | E11: 30.416667 | F11: =+E11+30.4166667 -> 60.833333 | G11: =+F11+30.4166667 -> 91.25 | H11: =+G11+30.4166667 -> 121.66667 | I11: =+H11+30.4166667 -> 152.08333 | J11: =+I11+30.4166667 -> 182.5 | K11: =+J11+30.4166667 -> 212.91667 | L11: =+K11+30.4166667 -> 243.33333 | M11: =+L11+30.4166667 -> 273.75 | ... BL11: =+BK11+30.4166667 -> 1825
D12: =C14 -> 46080 | E12: =$D12+E11 -> 46110.417 | F12: =$D12+F11 -> 46140.833 | G12: =$D12+G11 -> 46171.25 | H12: =$D12+H11 -> 46201.667 | I12: =$D12+I11 -> 46232.083 | J12: =$D12+J11 -> 46262.5 | K12: =$D12+K11 -> 46292.917 | L12: =$D12+L11 -> 46323.333 | ... BL12: =$D12+BL11 -> 47905
D13: =EOMONTH(D12,0) -> 46081 | E13: =EOMONTH(E12,0) -> 46112 | F13: =EOMONTH(F12,0) -> 46142 | G13: =EOMONTH(G12,0) -> 46173 | H13: =EOMONTH(H12,0) -> 46203 | I13: =EOMONTH(I12,0) -> 46234 | J13: =EOMONTH(J12,0) -> 46265 | K13: =EOMONTH(K12,0) -> 46295 | ... BL13: =EOMONTH(BL12,0) -> 47907
C14: 46080 | D14: =VLOOKUP($C14,'HAVER BoE'!$A:$BL,D9,FALSE) -> 3.7267 | E14: =VLOOKUP($C14,'HAVER BoE'!$A:$BL,E9,FALSE) -> 3.5178962 | F14: =VLOOKUP($C14,'HAVER BoE'!$A:$BL,F9,FALSE) -> 3.4951976 | G14: =VLOOKUP($C14,'HAVER BoE'!$A:$BL,G9,FALSE) -> 3.4552224 | H14: =VLOOKUP($C14,'HAVER BoE'!$A:$BL,H9,FALSE) -> 3.4041663 | I14: =VLOOKUP($C14,'HAVER BoE'!$A:$BL,I9,FALSE) -> 3.3509989 | J14: =VLOOKUP($C14,'HAVER BoE'!$A:$BL,J9,FALSE) -> 3.3038578 | K14: =VLOOKUP($C14,'HAVER BoE'!$A:$BL,K9,FALSE) -> 3.265964 | ... BL14: =VLOOKUP($C14,'HAVER BoE'!$A:$BL,BL9,FALSE) -> 3.865903
C15: Diff vs overnight | E15: =E14-$D$14 -> -0.2088038 | F15: =F14-$D$14 -> -0.2315024 | G15: =G14-$D$14 -> -0.2714776 | H15: =H14-$D$14 -> -0.3225337 | I15: =I14-$D$14 -> -0.3757011 | J15: =J14-$D$14 -> -0.4228422 | K15: =K14-$D$14 -> -0.460736 | L15: =L14-$D$14 -> -0.4875258 | ... BL15: =BL14-$D$14 -> 0.139203
C17: Column # | D17: 4 | E17: =+D17+1 -> 5 | F17: =+E17+1 -> 6 | G17: =+F17+1 -> 7 | H17: =+G17+1 -> 8 | I17: =+H17+1 -> 9 | J17: =+I17+1 -> 10 | K17: =+J17+1 -> 11 | L17: =+K17+1 -> 12 | ... BL17: =+BK17+1 -> 64
C18: Months | D18: ='HAVER BoE'!D9 -> 5.1863 | E18: ='HAVER BoE'!E9 -> 5.1869458 | F18: ='HAVER BoE'!F9 -> 5.1737152 | G18: ='HAVER BoE'!G9 -> 5.1274641 | H18: ='HAVER BoE'!H9 -> 5.0330693 | I18: ='HAVER BoE'!I9 -> 4.8948084 | J18: ='HAVER BoE'!J9 -> 4.7267552 | K18: ='HAVER BoE'!K9 -> 4.5455904 | ... BL18: ='HAVER BoE'!BL9 -> 2.976615
C19: Days | E19: 30.416667 | F19: =+E19+30.4166667 -> 60.833333 | G19: =+F19+30.4166667 -> 91.25 | H19: =+G19+30.4166667 -> 121.66667 | I19: =+H19+30.4166667 -> 152.08333 | J19: =+I19+30.4166667 -> 182.5 | K19: =+J19+30.4166667 -> 212.91667 | L19: =+K19+30.4166667 -> 243.33333 | M19: =+L19+30.4166667 -> 273.75 | ... BL19: =+BK19+30.4166667 -> 1825
D20: =C22 -> 46153 | E20: =$D20+E19 -> 46183.417 | F20: =$D20+F19 -> 46213.833 | G20: =$D20+G19 -> 46244.25 | H20: =$D20+H19 -> 46274.667 | I20: =$D20+I19 -> 46305.083 | J20: =$D20+J19 -> 46335.5 | K20: =$D20+K19 -> 46365.917 | L20: =$D20+L19 -> 46396.333 | ... BL20: =$D20+BL19 -> 47978
D21: =EOMONTH(D20,0) -> 46173 | E21: =EOMONTH(E20,0) -> 46203 | F21: =EOMONTH(F20,0) -> 46234 | G21: =EOMONTH(G20,0) -> 46265 | H21: =EOMONTH(H20,0) -> 46295 | I21: =EOMONTH(I20,0) -> 46326 | J21: =EOMONTH(J20,0) -> 46356 | K21: =EOMONTH(K20,0) -> 46387 | ... BL21: =EOMONTH(BL20,0) -> 47999
C22: 46153 | D22: =VLOOKUP($C22,'HAVER BoE'!$A:$BL,D17,FALSE) -> 3.7294 | E22: =VLOOKUP($C22,'HAVER BoE'!$A:$BL,E17,FALSE) -> 3.7472358 | F22: =VLOOKUP($C22,'HAVER BoE'!$A:$BL,F17,FALSE) -> 3.8679606 | G22: =VLOOKUP($C22,'HAVER BoE'!$A:$BL,G17,FALSE) -> 3.9873898 | H22: =VLOOKUP($C22,'HAVER BoE'!$A:$BL,H17,FALSE) -> 4.1010276 | I22: =VLOOKUP($C22,'HAVER BoE'!$A:$BL,I17,FALSE) -> 4.2014623 | J22: =VLOOKUP($C22,'HAVER BoE'!$A:$BL,J17,FALSE) -> 4.2831312 | K22: =VLOOKUP($C22,'HAVER BoE'!$A:$BL,K17,FALSE) -> 4.3481314 | ... BL22: =VLOOKUP($C22,'HAVER BoE'!$A:$BL,BL17,FALSE) -> 4.4100254
C23: Diff vs overnight | E23: =E22-$D$14 -> 0.0205358 | F23: =F22-$D$14 -> 0.1412606 | G23: =G22-$D$14 -> 0.2606898 | H23: =H22-$D$14 -> 0.3743276 | I23: =I22-$D$14 -> 0.4747623 | J23: =J22-$D$14 -> 0.5564312 | K23: =K22-$D$14 -> 0.6214314 | L23: =L22-$D$14 -> 0.6713586 | ... BL23: =BL22-$D$14 -> 0.6833254

Sheet HAVER BoE
C1: Bank Rate | D1: Overnight | E1: 1 | F1: 2 | G1: 3 | H1: 4 | I1: 5 | J1: 6 | K1: 7 | L1: 8 | M1: 9 | N1: 10 | O1: 11 | P1: 12 | Q1: 13 | R1: 14 | S1: 15 | T1: 16 | U1: 17 | V1: 18 | W1: 19 | X1: 20 | Y1: 21 | Z1: 22 | AA1: 23 | AB1: 24 | AC1: 25 | AD1: 26 | AE1: 27 | AF1: 28 | AG1: 29 | AH1: 30 | AI1: 31 | AJ1: 32 | AK1: 33 | AL1: 34 | AM1: 35 | AN1: 36 | AO1: 37 | AP1: 38 | AQ1: 39 | AR1: 40 | AS1: 41 | AT1: 42 | AU1: 43 | AV1: 44 | AW1: 45 | AX1: 46 | AY1: 47 | AZ1: 48 | BA1: 49 | BB1: 50 | BC1: 51 | BD1: 52 | BE1: 53 | BF1: 54 | BG1: 55 | BH1: 56 | BI1: 57 | BJ1: 58 | BK1: 59 | BL1: 60 | BM1: 5.5yrs | BN1: 6yrs
B2: 20240101 !D | C2: R112RD@INTDAILY | D2: R112LOS@INTDAILY | E2: R11201F@INTDAILY | F2: R11202F@INTDAILY | G2: R11203F@INTDAILY | H2: R11204F@INTDAILY | I2: R11205F@INTDAILY | J2: R11206F@INTDAILY | K2: R11207F@INTDAILY | L2: R11208F@INTDAILY | M2: R11209F@INTDAILY | N2: R11210F@INTDAILY | O2: R11211F@INTDAILY | P2: R11212F@INTDAILY | Q2: R11213F@INTDAILY | R2: R11214F@INTDAILY | S2: R11215F@INTDAILY | T2: R11216F@INTDAILY | U2: R11217F@INTDAILY | V2: R11218F@INTDAILY | W2: R11219F@INTDAILY | X2: R11220F@INTDAILY | Y2: R11221F@INTDAILY | Z2: R11222F@INTDAILY | AA2: R11223F@INTDAILY | AB2: R11224F@INTDAILY | AC2: R11225F@INTDAILY | AD2: R11226F@INTDAILY | AE2: R11227F@INTDAILY | AF2: R11228F@INTDAILY | AG2: R11229F@INTDAILY | AH2: R11230F@INTDAILY | AI2: R11231F@INTDAILY | AJ2: R11232F@INTDAILY | AK2: R11233F@INTDAILY | AL2: R11234F@INTDAILY | AM2: R11235F@INTDAILY | AN2: R11236F@INTDAILY | AO2: R11237F@INTDAILY | AP2: R11238F@INTDAILY | AQ2: R11239F@INTDAILY | AR2: R11240F@INTDAILY | AS2: R11241F@INTDAILY | AT2: R11242F@INTDAILY | AU2: R11243F@INTDAILY | AV2: R11244F@INTDAILY | AW2: R11245F@INTDAILY | AX2: R11246F@INTDAILY | AY2: R11247F@INTDAILY | AZ2: R11248F@INTDAILY | BA2: R11249F@INTDAILY | BB2: R11250F@INTDAILY | BC2: R11251F@INTDAILY | BD2: R11252F@INTDAILY | BE2: R11253F@INTDAILY | BF2: R11254F@INTDAILY | BG2: R11255F@INTDAILY | BH2: R11256F@INTDAILY | BI2: R11257F@INTDAILY | BJ2: R11258F@INTDAILY | BK2: R11259F@INTDAILY | BL2: R11260F@INTDAILY | BM2: R112I5B@INTDAILY | BN2: R112I6A@INTDAILY
B3: .DESC | C3: United Kingdom: Official Bank Rate (%) | D3: UK:Lending Rate: Sterling Overnight Interbank Average [SONIA] (% pa) | E3: UK: Overnight Index Swap: Forward Yields, 1-Month (% p.a.) | F3: UK: Overnight Index Swap: Forward Yields, 2-Month (% p.a.) | G3: UK: Overnight Index Swap: Forward Yields, 3-Month (% p.a.) | H3: UK: Overnight Index Swap: Forward Yields, 4-Month (% p.a.) | I3: UK: Overnight Index Swap: Forward Yields, 5-Month (% p.a.) | J3: UK: Overnight Index Swap: Forward Yields, 6-Month (% p.a.) | K3: UK: Overnight Index Swap: Forward Yields, 7-Month (% p.a.) | L3: UK: Overnight Index Swap: Forward Yields, 8-Month (% p.a.) | M3: UK: Overnight Index Swap: Forward Yields, 9-Month (% p.a.) | N3: UK: Overnight Index Swap: Forward Yields, 10-Month (% p.a.) | O3: UK: Overnight Index Swap: Forward Yields, 11-Month (% p.a.) | P3: UK: Overnight Index Swap: Forward Yields, 12-Month (% p.a.) | Q3: UK: Overnight Index Swap: Forward Yields, 13-Month (% p.a.) | R3: UK: Overnight Index Swap: Forward Yields, 14-Month (% p.a.) | S3: UK: Overnight Index Swap: Forward Yields, 15-Month (% p.a.) | T3: UK: Overnight Index Swap: Forward Yields, 16-Month (% p.a.) | U3: UK: Overnight Index Swap: Forward Yields, 17-Month (% p.a.) | V3: UK: Overnight Index Swap: Forward Yields, 18-Month (% p.a.) | W3: UK: Overnight Index Swap: Forward Yields, 19-Month (% p.a.) | X3: UK: Overnight Index Swap: Forward Yields, 20-Month (% p.a.) | Y3: UK: Overnight Index Swap: Forward Yields, 21-Month (% p.a.) | Z3: UK: Overnight Index Swap: Forward Yields, 22-Month (% p.a.) | AA3: UK: Overnight Index Swap: Forward Yields, 23-Month (% p.a.) | AB3: UK: Overnight Index Swap: Forward Yields, 24-Month (% p.a.) | AC3: UK: Overnight Index Swap: Forward Yields, 25-Month (% p.a.) | AD3: UK: Overnight Index Swap: Forward Yields, 26-Month (% p.a.) | AE3: UK: Overnight Index Swap: Forward Yields, 27-Month (% p.a.) | AF3: UK: Overnight Index Swap: Forward Yields, 28-Month (% p.a.) | AG3: UK: Overnight Index Swap: Forward Yields, 29-Month (% p.a.) | AH3: UK: Overnight Index Swap: Forward Yields, 30-Month (% p.a.) | AI3: UK: Overnight Index Swap: Forward Yields, 31-Month (% p.a.) | AJ3: UK: Overnight Index Swap: Forward Yields, 32-Month (% p.a.) | AK3: UK: Overnight Index Swap: Forward Yields, 33-Month (% p.a.) | AL3: UK: Overnight Index Swap: Forward Yields, 34-Month (% p.a.) | AM3: UK: Overnight Index Swap: Forward Yields, 35-Month (% p.a.) | AN3: UK: Overnight Index Swap: Forward Yields, 36-Month (% p.a.) | AO3: UK: Overnight Index Swap: Forward Yields, 37-Month (% p.a.) | AP3: UK: Overnight Index Swap: Forward Yields, 38-Month (% p.a.) | AQ3: UK: Overnight Index Swap: Forward Yields, 39-Month (% p.a.) | AR3: UK: Overnight Index Swap: Forward Yields, 40-Month (% p.a.) | AS3: UK: Overnight Index Swap: Forward Yields, 41-Month (% p.a.) | AT3: UK: Overnight Index Swap: Forward Yields, 42-Month (% p.a.) | AU3: UK: Overnight Index Swap: Forward Yields, 43-Month (% p.a.) | AV3: UK: Overnight Index Swap: Forward Yields, 44-Month (% p.a.) | AW3: UK: Overnight Index Swap: Forward Yields, 45-Month (% p.a.) | AX3: UK: Overnight Index Swap: Forward Yields, 46-Month (% p.a.) | AY3: UK: Overnight Index Swap: Forward Yields, 47-Month (% p.a.) | AZ3: UK: Overnight Index Swap: Forward Yields, 48-Month (% p.a.) | BA3: UK: Overnight Index Swap: Forward Yields, 49-Month (% p.a.) | BB3: UK: Overnight Index Swap: Forward Yields, 50-Month (% p.a.) | BC3: UK: Overnight Index Swap: Forward Yields, 51-Month (% p.a.) | BD3: UK: Overnight Index Swap: Forward Yields, 52-Month (% p.a.) | BE3: UK: Overnight Index Swap: Forward Yields, 53-Month (% p.a.) | BF3: UK: Overnight Index Swap: Forward Yields, 54-Month (% p.a.) | BG3: UK: Overnight Index Swap: Forward Yields, 55-Month (% p.a.) | BH3: UK: Overnight Index Swap: Forward Yields, 56-Month (% p.a.) | BI3: UK: Overnight Index Swap: Forward Yields, 57-Month (% p.a.) | BJ3: UK: Overnight Index Swap: Forward Yields, 58-Month (% p.a.) | BK3: UK: Overnight Index Swap: Forward Yields, 59-Month (% p.a.) | BL3: UK: Overnight Index Swap: Forward Yields, 60-Month (% p.a.) | BM3: UK: Overnight Index Swap: Forward Yields, 5.5-Year (% p.a.) | BN3: UK: Overnight Index Swap: Forward Yields, 6-Year (% p.a.)
B4: .T1 | C4: 03-Jan-1955 | D4: 02-Jan-1997 | E4: 02-Jan-2009 | F4: 02-Jan-2009 | G4: 02-Jan-2009 | H4: 02-Jan-2009 | I4: 02-Jan-2009 | J4: 02-Jan-2009 | K4: 02-Jan-2009 | L4: 02-Jan-2009 | M4: 02-Jan-2009 | N4: 02-Jan-2009 | O4: 02-Jan-2009 | P4: 02-Jan-2009 | Q4: 02-Jan-2009 | R4: 02-Jan-2009 | S4: 02-Jan-2009 | T4: 02-Jan-2009 | U4: 02-Jan-2009 | V4: 02-Jan-2009 | W4: 02-Jan-2009 | X4: 02-Jan-2009 | Y4: 02-Jan-2009 | Z4: 02-Jan-2009 | AA4: 02-Jan-2009 | AB4: 02-Jan-2009 | AC4: 02-Jan-2009 | AD4: 02-Jan-2009 | AE4: 02-Jan-2009 | AF4: 02-Jan-2009 | AG4: 02-Jan-2009 | AH4: 02-Jan-2009 | AI4: 02-Jan-2009 | AJ4: 02-Jan-2009 | AK4: 02-Jan-2009 | AL4: 02-Jan-2009 | AM4: 02-Jan-2009 | AN4: 02-Jan-2009 | AO4: 02-Jan-2009 | AP4: 02-Jan-2009 | AQ4: 02-Jan-2009 | AR4: 02-Jan-2009 | AS4: 02-Jan-2009 | AT4: 02-Jan-2009 | AU4: 02-Jan-2009 | AV4: 02-Jan-2009 | AW4: 02-Jan-2009 | AX4: 02-Jan-2009 | AY4: 02-Jan-2009 | AZ4: 02-Jan-2009 | BA4: 02-Jan-2009 | BB4: 02-Jan-2009 | BC4: 02-Jan-2009 | BD4: 02-Jan-2009 | BE4: 02-Jan-2009 | BF4: 02-Jan-2009 | BG4: 02-Jan-2009 | BH4: 02-Jan-2009 | BI4: 02-Jan-2009 | BJ4: 02-Jan-2009 | BK4: 02-Jan-2009 | BL4: 02-Jan-2009 | BM4: 02-Jan-2018 | BN4: 02-Jan-2018
B5: .TN | C5: 11-May-2026 | D5: 08-May-2026 | E5: 11-May-2026 | F5: 11-May-2026 | G5: 11-May-2026 | H5: 11-May-2026 | I5: 11-May-2026 | J5: 11-May-2026 | K5: 11-May-2026 | L5: 11-May-2026 | M5: 11-May-2026 | N5: 11-May-2026 | O5: 11-May-2026 | P5: 11-May-2026 | Q5: 11-May-2026 | R5: 11-May-2026 | S5: 11-May-2026 | T5: 11-May-2026 | U5: 11-May-2026 | V5: 11-May-2026 | W5: 11-May-2026 | X5: 11-May-2026 | Y5: 11-May-2026 | Z5: 11-May-2026 | AA5: 11-May-2026 | AB5: 11-May-2026 | AC5: 11-May-2026 | AD5: 11-May-2026 | AE5: 11-May-2026 | AF5: 11-May-2026 | AG5: 11-May-2026 | AH5: 11-May-2026 | AI5: 11-May-2026 | AJ5: 11-May-2026 | AK5: 11-May-2026 | AL5: 11-May-2026 | AM5: 11-May-2026 | AN5: 11-May-2026 | AO5: 11-May-2026 | AP5: 11-May-2026 | AQ5: 11-May-2026 | AR5: 11-May-2026 | AS5: 11-May-2026 | AT5: 11-May-2026 | AU5: 11-May-2026 | AV5: 11-May-2026 | AW5: 11-May-2026 | AX5: 11-May-2026 | AY5: 11-May-2026 | AZ5: 11-May-2026 | BA5: 11-May-2026 | BB5: 11-May-2026 | BC5: 11-May-2026 | BD5: 11-May-2026 | BE5: 11-May-2026 | BF5: 11-May-2026 | BG5: 11-May-2026 | BH5: 11-May-2026 | BI5: 11-May-2026 | BJ5: 11-May-2026 | BK5: 11-May-2026 | BL5: 11-May-2026 | BM5: 11-May-2026 | BN5: 11-May-2026
B6: .LSOURCE | C6: Bank of England | D6: Bank of England | E6: Bank of England | F6: Bank of England | G6: Bank of England | H6: Bank of England | I6: Bank of England | J6: Bank of England | K6: Bank of England | L6: Bank of England | M6: Bank of England | N6: Bank of England | O6: Bank of England | P6: Bank of England | Q6: Bank of England | R6: Bank of England | S6: Bank of England | T6: Bank of England | U6: Bank of England | V6: Bank of England | W6: Bank of England | X6: Bank of England | Y6: Bank of England | Z6: Bank of England | AA6: Bank of England | AB6: Bank of England | AC6: Bank of England | AD6: Bank of England | AE6: Bank of England | AF6: Bank of England | AG6: Bank of England | AH6: Bank of England | AI6: Bank of England | AJ6: Bank of England | AK6: Bank of England | AL6: Bank of England | AM6: Bank of England | AN6: Bank of England | AO6: Bank of England | AP6: Bank of England | AQ6: Bank of England | AR6: Bank of England | AS6: Bank of England | AT6: Bank of England | AU6: Bank of England | AV6: Bank of England | AW6: Bank of England | AX6: Bank of England | AY6: Bank of England | AZ6: Bank of England | BA6: Bank of England | BB6: Bank of England | BC6: Bank of England | BD6: Bank of England | BE6: Bank of England | BF6: Bank of England | BG6: Bank of England | BH6: Bank of England | BI6: Bank of England | BJ6: Bank of England | BK6: Bank of England | BL6: Bank of England | BM6: Bank of England | BN6: Bank of England
B7: .DTLM | C7: May-11-2026 14:25 | D7: May-12-2026 09:32 | E7: May-12-2026 10:28 | F7: May-12-2026 10:28 | G7: May-12-2026 10:28 | H7: May-12-2026 10:28 | I7: May-12-2026 10:28 | J7: May-12-2026 10:28 | K7: May-12-2026 10:28 | L7: May-12-2026 10:28 | M7: May-12-2026 10:28 | N7: May-12-2026 10:28 | O7: May-12-2026 10:28 | P7: May-12-2026 10:28 | Q7: May-12-2026 10:28 | R7: May-12-2026 10:28 | S7: May-12-2026 10:28 | T7: May-12-2026 10:28 | U7: May-12-2026 10:28 | V7: May-12-2026 10:28 | W7: May-12-2026 10:28 | X7: May-12-2026 10:28 | Y7: May-12-2026 10:28 | Z7: May-12-2026 10:28 | AA7: May-12-2026 10:28 | AB7: May-12-2026 10:28 | AC7: May-12-2026 10:28 | AD7: May-12-2026 10:28 | AE7: May-12-2026 10:28 | AF7: May-12-2026 10:28 | AG7: May-12-2026 10:28 | AH7: May-12-2026 10:28 | AI7: May-12-2026 10:28 | AJ7: May-12-2026 10:28 | AK7: May-12-2026 10:28 | AL7: May-12-2026 10:28 | AM7: May-12-2026 10:28 | AN7: May-12-2026 10:28 | AO7: May-12-2026 10:28 | AP7: May-12-2026 10:28 | AQ7: May-12-2026 10:28 | AR7: May-12-2026 10:28 | AS7: May-12-2026 10:28 | AT7: May-12-2026 10:28 | AU7: May-12-2026 10:28 | AV7: May-12-2026 10:28 | AW7: May-12-2026 10:28 | AX7: May-12-2026 10:28 | AY7: May-12-2026 10:28 | AZ7: May-12-2026 10:28 | BA7: May-12-2026 10:28 | BB7: May-12-2026 10:28 | BC7: May-12-2026 10:28 | BD7: May-12-2026 10:28 | BE7: May-12-2026 10:28 | BF7: May-12-2026 10:28 | BG7: May-12-2026 10:28 | BH7: May-12-2026 10:28 | BI7: May-12-2026 10:28 | BJ7: May-12-2026 10:28 | BK7: May-12-2026 10:28 | BL7: May-12-2026 10:28 | BM7: May-12-2026 10:28 | BN7: May-12-2026 10:28
A8: 45292 | B8: 20240101 | C8: 5.25 | D8: #N/A | E8: #N/A | F8: #N/A | G8: #N/A | H8: #N/A | I8: #N/A | J8: #N/A | K8: #N/A | L8: #N/A | M8: #N/A | N8: #N/A | O8: #N/A | P8: #N/A | Q8: #N/A | R8: #N/A | S8: #N/A | T8: #N/A | U8: #N/A | V8: #N/A | W8: #N/A | X8: #N/A | Y8: #N/A | Z8: #N/A | AA8: #N/A | AB8: #N/A | AC8: #N/A | AD8: #N/A | AE8: #N/A | AF8: #N/A | AG8: #N/A | AH8: #N/A | AI8: #N/A | AJ8: #N/A | AK8: #N/A | AL8: #N/A | AM8: #N/A | AN8: #N/A | AO8: #N/A | AP8: #N/A | AQ8: #N/A | AR8: #N/A | AS8: #N/A | AT8: #N/A | AU8: #N/A | AV8: #N/A | AW8: #N/A | AX8: #N/A | AY8: #N/A | AZ8: #N/A | BA8: #N/A | BB8: #N/A | BC8: #N/A | BD8: #N/A | BE8: #N/A | BF8: #N/A | BG8: #N/A | BH8: #N/A | BI8: #N/A | BJ8: #N/A | BK8: #N/A | BL8: #N/A | BM8: #N/A | BN8: #N/A
A9: 45293 | B9: 20240102 | C9: 5.25 | D9: 5.1863 | E9: 5.1869458 | F9: 5.1737152 | G9: 5.1274641 | H9: 5.0330693 | I9: 4.8948084 | J9: 4.7267552 | K9: 4.5455904 | L9: 4.3673209 | M9: 4.2024467 | N9: 4.0550731 | O9: 3.9257072 | P9: 3.8133507 | Q9: 3.7135649 | R9: 3.6243989 | S9: 3.5449015 | T9: 3.4741183 | U9: 3.4110951 | V9: 3.3548802 | W9: 3.3045933 | X9: 3.2596362 | Y9: 3.2194791 | Z9: 3.1835906 | AA9: 3.1514396 | AB9: 3.122496 | AC9: 3.0962854 | AD9: 3.0725845 | AE9: 3.0512401 | AF9: 3.0320982 | AG9: 3.0150048 | AH9: 2.9998064 | AI9: 2.9863491 | AJ9: 2.974479 | AK9: 2.9640426 | AL9: 2.9548859 | AM9: 2.9468551 | AN9: 2.9397965 | AO9: 2.9335733 | AP9: 2.9281397 | AQ9: 2.9234809 | AR9: 2.9195818 | AS9: 2.9164273 | AT9: 2.9140026 | AU9: 2.9122925 | AV9: 2.9112821 | AW9: 2.9109564 | AX9: 2.9113003 | AY9: 2.912299 | AZ9: 2.9139373 | BA9: 2.9161996 | BB9: 2.919067 | BC9: 2.9225195 | BD9: 2.9265371 | BE9: 2.9310997 | BF9: 2.9361872 | BG9: 2.9417797 | BH9: 2.9478571 | BI9: 2.9543994 | BJ9: 2.9613864 | BK9: 2.9687984 | BL9: 2.976615 | BM9: 3.030969 | BN9: 3.0953136
A10: 45294 | B10: 20240103 | C10: 5.25 | D10: 5.1863 | E10: 5.1879346 | F10: 5.1698623 | G10: 5.1217679 | H10: 5.0292524 | I10: 4.8955915 | J10: 4.7327474 | K10: 4.5561573 | L10: 4.3801251 | M10: 4.2145866 | N10: 4.0638514 | O10: 3.9292761 | P10: 3.8103909 | Q10: 3.7037411 | R10: 3.6077142 | S10: 3.521457 | T10: 3.4441131 | U10: 3.3748263 | V10: 3.3127429 | W10: 3.2570771 | X10: 3.2073119 | Y10: 3.1629961 | Z10: 3.1236764 | AA10: 3.0889 | AB10: 3.0582151 | AC10: 3.0311935 | AD10: 3.0075393 | AE10: 2.9870022 | AF10: 2.969331 | AG10: 2.9542745 | AH10: 2.9415821 | AI10: 2.9310026 | AJ10: 2.9222851 | AK10: 2.9151788 | AL10: 2.9094326 | AM10: 2.9047955 | AN10: 2.9010166 | AO10: 2.8978771 | AP10: 2.895314 | AQ10: 2.8933122 | AR10: 2.8918564 | AS10: 2.8909314 | AT10: 2.8905219 | AU10: 2.8906127 | AV10: 2.8911885 | AW10: 2.8922341 | AX10: 2.8937342 | AY10: 2.8956737 | AZ10: 2.8980372 | BA10: 2.9008111 | BB10: 2.9039899 | BC10: 2.9075703 | BD10: 2.9115491 | BE10: 2.9159234 | BF10: 2.9206896 | BG10: 2.9258448 | BH10: 2.9313858 | BI10: 2.9373093 | BJ10: 2.9436122 | BK10: 2.9502914 | BL10: 2.9573435 | BM10: 3.0068421 | BN10: 3.066086
A11: 45295 | B11: 20240104 | C11: 5.25 | D11: 5.187 | E11: 5.1847631 | F11: 5.1706678 | G11: 5.1289199 | H11: 5.0490298 | I11: 4.9325416 | J11: 4.7903404 | K11: 4.6344699 | L11: 4.4767792 | M11: 4.325913 | N11: 4.1861158 | O11: 4.0594066 | P11: 3.9458216 | Q11: 3.8430555 | R11: 3.7499596 | S11: 3.6659829 | T11: 3.5905712 | U11: 3.5231711 | V11: 3.4632312 | W11: 3.4101861 | X11: 3.3634253 | Y11: 3.3223291 | Z11: 3.2862764 | AA11: 3.2546461 | AB11: 3.2268182 | AC11: 3.202227 | AD11: 3.1805764 | AE11: 3.1616533 | AF11: 3.1452434 | AG11: 3.1311331 | AH11: 3.1191088 | AI11: 3.1089566 | AJ11: 3.1004627 | AK11: 3.0934135 | AL11: 3.0875952 | AM11: 3.082794 | AN11: 3.0787962 | AO11: 3.0754178 | AP11: 3.0726057 | AQ11: 3.0703431 | AR11: 3.0686133 | AS11: 3.0673993 | AT11: 3.0666845 | AU11: 3.066452 | AV11: 3.0666849 | AW11: 3.0673665 | AX11: 3.0684799 | AY11: 3.0700083 | AZ11: 3.071935 | BA11: 3.0742445 | BB11: 3.0769279 | BC11: 3.0799781 | BD11: 3.083388 | BE11: 3.0871505 | BF11: 3.0912583 | BG11: 3.0957043 | BH11: 3.1004814 | BI11: 3.1055825 | BJ11: 3.1110004 | BK11: 3.1167281 | BL11: 3.1227582 | BM11: 3.164827 | BN11: 3.2155848
A12: 45296 | B12: 20240105 | C12: 5.25 | D12: 5.1869 | E12: 5.1873271 | F12: 5.1720792 | G12: 5.1334347 | H12: 5.0598045 | I12: 4.9517376 | J12: 4.818767 | K12: 4.6723585 | L12: 4.5243145 | M12: 4.3831627 | N12: 4.2534108 | O12: 4.1364167 | P12: 4.0318583 | Q12: 3.9368302 | R12: 3.85008 | S12: 3.7711019 | T12: 3.6993871 | U12: 3.6344272 | V12: 3.5757159 | W12: 3.5227608 | X12: 3.4751452 | Y12: 3.4324758 | Z12: 3.3943576 | AA12: 3.3603956 | AB12: 3.3301963 | AC12: 3.3033905 | AD12: 3.2797228 | AE12: 3.2589696 | AF12: 3.2409068 | AG12: 3.2253104 | AH12: 3.2119566 | AI12: 3.2006214 | AJ12: 3.1910808 | AK12: 3.1831111 | AL12: 3.1764881 | AM12: 3.1709879 | AN12: 3.1663868 | AO12: 3.1624898 | AP12: 3.1592315 | AQ12: 3.156582 | AR12: 3.1545114 | AS12: 3.1529896 | AT12: 3.1519869 | AU12: 3.1514732 | AV12: 3.1514186 | AW12: 3.1517933 | AX12: 3.1525672 | AY12: 3.1537105 | AZ12: 3.1551932 | BA12: 3.1569896 | BB12: 3.1590924 | BC12: 3.1614995 | BD12: 3.1642087 | BE12: 3.1672179 | BF12: 3.170525 | BG12: 3.1741276 | BH12: 3.1780239 | BI12: 3.1822114 | BJ12: 3.1866882 | BK12: 3.191452 | BL12: 3.1965007 | BM12: 3.2325006 | BN12: 3.2772656
A13: =+A8+7 -> 45299 | B13: 20240108 | C13: 5.25 | D13: 5.1869 | E13: 5.1875371 | F13: 5.1723518 | G13: 5.1318123 | H13: 5.0538828 | I13: 4.940707 | J13: 4.8022983 | K13: 4.6506226 | L13: 4.4975445 | M13: 4.3519114 | N13: 4.2180825 | O13: 4.0980801 | P13: 3.9915985 | Q13: 3.8957127 | R13: 3.8090536 | S13: 3.7309025 | T13: 3.6605376 | U13: 3.5972375 | V13: 3.5402832 | W13: 3.489008 | X13: 3.4429542 | Y13: 3.4017156 | Z13: 3.3648842 | AA13: 3.3320521 | AB13: 3.3028128 | AC13: 3.2767879 | AD13: 3.2537295 | AE13: 3.2334264 | AF13: 3.2156666 | AG13: 3.2002382 | AH13: 3.1869299 | AI13: 3.1755298 | AJ13: 3.1658259 | AK13: 3.1576069 | AL13: 3.1506609 | AM13: 3.1447761 | AN13: 3.1397409 | AO13: 3.135372 | AP13: 3.1316118 | AQ13: 3.1284378 | AR13: 3.1258269 | AS13: 3.1237565 | AT13: 3.1222038 | AU13: 3.1211458 | AV13: 3.12056 | AW13: 3.1204234 | AX13: 3.1207133 | AY13: 3.1214068 | AZ13: 3.1224812 | BA13: 3.1239165 | BB13: 3.1257072 | BC13: 3.1278529 | BD13: 3.1303531 | BE13: 3.1332076 | BF13: 3.1364157 | BG13: 3.139977 | BH13: 3.1438913 | BI13: 3.1481579 | BJ13: 3.1527765 | BK13: 3.1577466 | BL13: 3.1630678 | BM13: 3.2019754 | BN13: 3.2511539
A14: =+A9+7 -> 45300 | B14: 20240109 | C14: 5.25 | D14: 5.1867 | E14: 5.1852612 | F14: 5.1702463 | G14: 5.1298316 | H14: 5.0519415 | I14: 4.9396491 | J14: 4.8037639 | K14: 4.656196 | L14: 4.5079649 | M14: 4.3668257 | N14: 4.2366576 | O14: 4.1187677 | P14: 4.0132622 | Q14: 3.9177742 | R14: 3.8311198 | S14: 3.7526542 | T14: 3.6817291 | U14: 3.6176969 | V14: 3.5599118 | W14: 3.5077647 | X14: 3.4607923 | Y14: 3.4185682 | Z14: 3.3806642 | AA14: 3.3466522 | AB14: 3.3161053 | AC14: 3.2886325 | AD14: 3.2640061 | AE14: 3.2420446 | AF14: 3.2225655 | AG14: 3.2053862 | AH14: 3.190325 | AI14: 3.1771994 | AJ14: 3.1658272 | AK14: 3.1560262 | AL14: 3.1476142 | AM14: 3.1404089 | AN14: 3.1342282 | AO14: 3.1289081 | AP14: 3.1243834 | AQ14: 3.1206224 | AR14: 3.1175928 | AS14: 3.1152628 | AT14: 3.1136004 | AU14: 3.1125735 | AV14: 3.1121503 | AW14: 3.1122987 | AX14: 3.1129868 | AY14: 3.1141825 | AZ14: 3.1158539 | BA14: 3.117972 | BB14: 3.1205215 | BC14: 3.1234918 | BD14: 3.1268719 | BE14: 3.1306511 | BF14: 3.1348186 | BG14: 3.1393635 | BH14: 3.1442751 | BI14: 3.1495424 | BJ14: 3.1551547 | BK14: 3.1611013 | BL14: 3.1673712 | BM14: 3.2111431 | BN14: 3.2636287
A15: =+A10+7 -> 45301 | B15: 20240110 | C15: 5.25 | D15: 5.1872 | E15: 5.1850912 | F15: 5.1708219 | G15: 5.1309503 | H15: 5.0544508 | I15: 4.9451799 | J15: 4.8134886 | K15: 4.6711024 | L15: 4.5282674 | M15: 4.3923388 | N15: 4.2669033 | O15: 4.1533587 | P15: 4.0516976 | Q15: 3.9600377 | R15: 3.8771955 | S15: 3.8023256 | T15: 3.7345796 | U15: 3.6731095 | V15: 3.6170693 | W15: 3.5657097 | X15: 3.5186568 | Y15: 3.4756281 | Z15: 3.4363392 | AA15: 3.4005058 | AB15: 3.367845 | AC15: 3.3380884 | AD15: 3.311053 | AE15: 3.2865854 | AF15: 3.2645311 | AG15: 3.2447358 | AH15: 3.2270459 | AI15: 3.2113071 | AJ15: 3.1973651 | AK15: 3.1850661 | AL15: 3.1742559 | AM15: 3.1647803 | AN15: 3.1564854 | AO15: 3.1492323 | AP15: 3.1429566 | AQ15: 3.1376166 | AR15: 3.1331706 | AS15: 3.1295768 | AT15: 3.1267935 | AU15: 3.124779 | AV15: 3.1234916 | AW15: 3.1228895 | AX15: 3.122931 | AY15: 3.1235745 | AZ15: 3.1247781 | BA15: 3.126504 | BB15: 3.1287318 | BC15: 3.1314456 | BD15: 3.1346296 | BE15: 3.1382682 | BF15: 3.1423454 | BG15: 3.1468455 | BH15: 3.1517528 | BI15: 3.1570515 | BJ15: 3.1627257 | BK15: 3.1687597 | BL15: 3.1751377 | BM15: 3.2197924 | BN15: 3.2731349
A16: =+A11+7 -> 45302 | B16: 20240111 | C16: 5.25 | D16: 5.1876 | E16: 5.1883039 | F16: 5.1673171 | G16: 5.1189594 | H16: 5.0346508 | I16: 4.9187015 | J16: 4.782997 | K16: 4.639412 | L16: 4.4977175 | M16: 4.3643034 | N16: 4.2417532 | O16: 4.1308656 | P16: 4.0309256 | Q16: 3.9389315 | R16: 3.8538379 | S16: 3.7754857 | T16: 3.7037131 | U16: 3.6383589 | V16: 3.579264 | W16: 3.5262153 | X16: 3.478802 | Y16: 3.4365684 | Z16: 3.3990568 | AA16: 3.3658098 | AB16: 3.3363711 | AC16: 3.3103155 | AD16: 3.287374 | AE16: 3.267326 | AF16: 3.2499503 | AG16: 3.2350255 | AH16: 3.222331 | AI16: 3.2116455 | AJ16: 3.2027477 | AK16: 3.195417 | AL16: 3.189432 | AM16: 3.1845717 | AN16: 3.180615 | AO16: 3.1773707 | AP16: 3.1747784 | AQ16: 3.1728145 | AR16: 3.1714548 | AS16: 3.1706755 | AT16: 3.1704526 | AU16: 3.1707622 | AV16: 3.1715805 | AW16: 3.1728834 | AX16: 3.174647 | AY16: 3.1768474 | AZ16: 3.1794607 | BA16: 3.1824649 | BB16: 3.1858464 | BC16: 3.1895941 | BD16: 3.1936968 | BE16: 3.1981434 | BF16: 3.2029227 | BG16: 3.2080234 | BH16: 3.2134345 | BI16: 3.2191448 | BJ16: 3.225143 | BK16: 3.2314182 | BL16: 3.2379589 | BM16: 3.2822065 | BN16: 3.3335096
A17: =+A12+7 -> 45303 | B17: 20240112 | C17: 5.25 | D17: 5.1884 | E17: 5.188735 | F17: 5.1604989 | G17: 5.0990229 | H17: 4.995414 | I17: 4.8574653 | J17: 4.7009555 | K17: 4.5407209 | L17: 4.3873025 | M17: 4.2463179 | N17: 4.1196492 | O17: 4.0067672 | P17: 3.906338 | Q17: 3.8150971 | R17: 3.7317978 | S17: 3.656016 | T17: 3.5873251 | U17: 3.5252985 | V17: 3.4695121 | W17: 3.4195369 | X17: 3.374933 | Y17: 3.3352586 | Z17: 3.3000704 | AA17: 3.2689254 | AB17: 3.2413816 | AC17: 3.2170317 | AD17: 3.1956271 | AE17: 3.1769635 | AF17: 3.1608361 | AG17: 3.14704 | AH17: 3.1353707 | AI17: 3.1256236 | AJ17: 3.1175937 | AK17: 3.1110766 | AL17: 3.1058674 | AM17: 3.1017615 | AN17: 3.0985542 | AO17: 3.0960678 | AP17: 3.0942432 | AQ17: 3.0930544 | AR17: 3.0924751 | AS17: 3.0924793 | AT17: 3.0930407 | AU17: 3.0941333 | AV17: 3.0957309 | AW17: 3.0978072 | AX17: 3.1003363 | AY17: 3.1032919 | AZ17: 3.1066479 | BA17: 3.1103807 | BB17: 3.1144784 | BC17: 3.1189321 | BD17: 3.123733 | BE17: 3.1288724 | BF17: 3.1343415 | BG17: 3.1401313 | BH17: 3.1462333 | BI17: 3.1526384 | BJ17: 3.1593379 | BK17: 3.1663232 | BL17: 3.1735852 | BM17: 3.2224388 | BN17: 3.2788019
A18: =+A13+7 -> 45306 | B18: 20240115 | C18: 5.25 | D18: 5.1874 | E18: 5.1864987 | F18: 5.1613939 | G18: 5.1015345 | H18: 4.9956199 | I18: 4.8521908 | J18: 4.688973 | K18: 4.5229898 | L18: 4.3655985 | M18: 4.2226677 | N18: 4.0950554 | O18: 3.9821699 | P18: 3.882187 | Q18: 3.7914806 | R18: 3.7087614 | S18: 3.6335691 | T18: 3.5654407 | U18: 3.5039133 | V18: 3.4485262 | W18: 3.3988263 | X18: 3.3543966 | Y18: 3.3148308 | Z18: 3.2797206 | AA18: 3.2486582 | AB18: 3.2212368 | AC18: 3.1970775 | AD18: 3.1759309 | AE18: 3.1575841 | AF18: 3.1418233 | AG18: 3.1284346 | AH18: 3.117205 | AI18: 3.1079206 | AJ18: 3.1003678 | AK18: 3.0943333 | AL18: 3.0896034 | AM18: 3.0859646 | AN18: 3.0832033 | AO18: 3.0811348 | AP18: 3.0797022 | AQ18: 3.0788836 | AR18: 3.078657 | AS18: 3.0790008 | AT18: 3.0798929 | AU18: 3.0813115 | AV18: 3.0832348 | AW18: 3.0856409 | AX18: 3.088508 | AY18: 3.0918143 | AZ18: 3.0955378 | BA18: 3.0996584 | BB18: 3.1041662 | BC18: 3.109054 | BD18: 3.1143149 | BE18: 3.1199422 | BF18: 3.1259288 | BG18: 3.1322677 | BH18: 3.1389522 | BI18: 3.1459753 | BJ18: 3.15333 | BK18: 3.1610095 | BL18: 3.1690068 | BM18: 3.2230363 | BN18: 3.2852854
A19: =+A14+7 -> 45307 | B19: 20240116 | C19: 5.25 | D19: 5.1876 | E19: 5.1912832 | F19: 5.1664072 | G19: 5.1080097 | H19: 5.0063493 | I19: 4.867976 | J19: 4.7086042 | K19: 4.5445595 | L19: 4.38725 | M19: 4.2424888 | N19: 4.1116753 | O19: 3.9942376 | P19: 3.8892679 | Q19: 3.7938851 | R19: 3.707063 | S19: 3.6284902 | T19: 3.557852 | U19: 3.4948342 | V19: 3.4391248 | W19: 3.3903464 | X19: 3.3478821 | Y19: 3.3110591 | Z19: 3.2792031 | AA19: 3.2516403 | AB19: 3.2276975 | AC19: 3.2067727 | AD19: 3.188581 | AE19: 3.1729261 | AF19: 3.1596107 | AG19: 3.1484378 | AH19: 3.1392107 | AI19: 3.1317324 | AJ19: 3.1258057 | AK19: 3.121234 | AL19: 3.1178202 | AM19: 3.1153674 | AN19: 3.1136786 | AO19: 3.1125798 | AP19: 3.1120197 | AQ19: 3.1119887 | AR19: 3.1124767 | AS19: 3.1134739 | AT19: 3.1149705 | AU19: 3.1169565 | AV19: 3.1194223 | AW19: 3.1223578 | AX19: 3.1257533 | AY19: 3.1295988 | AZ19: 3.1338846 | BA19: 3.1386005 | BB19: 3.1437357 | BC19: 3.1492789 | BD19: 3.155219 | BE19: 3.1615448 | BF19: 3.168245 | BG19: 3.1753084 | BH19: 3.182724 | BI19: 3.1904803 | BJ19: 3.1985663 | BK19: 3.2069709 | BL19: 3.2156826 | BM19: 3.2737519 | BN19: 3.3398985
A20: =+A15+7 -> 45308 | B20: 20240117 | C20: 5.25 | D20: 5.188 | E20: 5.1870648 | F20: 5.1803458 | G20: 5.1485105 | H20: 5.0809502 | I20: 4.98113 | J20: 4.8598482 | K20: 4.7298052 | L20: 4.6007117 | M20: 4.4787319 | N20: 4.3664604 | O20: 4.2645357 | P20: 4.1724997 | Q20: 4.0877527 | R20: 4.0093645 | S20: 3.9370579 | T20: 3.8705529 | U20: 3.8095699 | V20: 3.7538311 | W20: 3.7030483 | X20: 3.6569008 | Y20: 3.6150618 | Z20: 3.5772029 | AA20: 3.5429957 | AB20: 3.5121132 | AC20: 3.4842457 | AD20: 3.4591839 | AE20: 3.4367527 | AF20: 3.4167765 | AG20: 3.3990794 | AH20: 3.3834865 | AI20: 3.3698221 | AJ20: 3.3579105 | AK20: 3.3475765 | AL20: 3.3386445 | AM20: 3.3309389 | AN20: 3.3242844 | AO20: 3.3185256 | AP20: 3.3136055 | AQ20: 3.3094973 | AR20: 3.3061737 | AS20: 3.3036079 | AT20: 3.3017729 | AU20: 3.3006415 | AV20: 3.3001869 | AW20: 3.3003819 | AX20: 3.3011997 | AY20: 3.3026131 | AZ20: 3.3045953 | BA20: 3.3071205 | BB20: 3.3101696 | BC20: 3.3137253 | BD20: 3.31777 | BE20: 3.3222865 | BF20: 3.3272571 | BG20: 3.3326646 | BH20: 3.3384916 | BI20: 3.3447204 | BJ20: 3.3513339 | BK20: 3.3583145 | BL20: 3.3656448 | BM20: 3.4160227 | BN20: 3.4747675
A21: =+A16+7 -> 45309 | B21: 20240118 | C21: 5.25 | D21: 5.1883 | E21: 5.1869164 | F21: 5.1776901 | G21: 5.1408352 | H21: 5.0663889 | I21: 4.9579612 | J21: 4.8290191 | K21: 4.6930677 | L21: 4.5596575 | M21: 4.4343029 | N21: 4.3189017 | O21: 4.2137297 | P21: 4.1179306 | Q21: 4.0287191 | R21: 3.9452892 | S21: 3.8677035 | T21: 3.7960222 | U21: 3.7303058 | V21: 3.670617 | W21: 3.6169267 | X21: 3.5688652 | Y21: 3.5259831 | Z21: 3.4878294 | AA21: 3.4539534 | AB21: 3.4239054 | AC21: 3.3972655 | AD21: 3.3737641 | AE21: 3.3531784 | AF21: 3.3352845 | AG21: 3.3198589 | AH21: 3.3066783 | AI21: 3.2955192 | AJ21: 3.2861579 | AK21: 3.2783713 | AL21: 3.2719357 | AM21: 3.2666275 | AN21: 3.2622235 | AO21: 3.2585313 | AP21: 3.2554963 | AQ21: 3.2531022 | AR21: 3.2513323 | AS21: 3.2501701 | AT21: 3.2495992 | AU21: 3.249603 | AV21: 3.250165 | AW21: 3.2512688 | AX21: 3.2528977 | AY21: 3.2550354 | AZ21: 3.2576652 | BA21: 3.2607713 | BB21: 3.2643408 | BC21: 3.2683613 | BD21: 3.2728207 | BE21: 3.2777068 | BF21: 3.2830074 | BG21: 3.2887101 | BH21: 3.294803 | BI21: 3.3012737 | BJ21: 3.3081099 | BK21: 3.3152996 | BL21: 3.3228304 | BM21: 3.374397 | BN21: 3.4345602
A22: =+A17+7 -> 45310 | B22: 20240119 | C22: 5.25 | D22: 5.1876 | E22: 5.1887528 | F22: 5.1780003 | G22: 5.1399208 | H22: 5.0660792 | I22: 4.9607851 | J22: 4.8358842 | K22: 4.7040655 | L22: 4.5747957 | M22: 4.4535067 | N22: 4.342442 | O22: 4.2414709 | P22: 4.1495841 | Q22: 4.0640079 | R22: 3.9839484 | S22: 3.9094062 | T22: 3.8403786 | U22: 3.7768635 | V22: 3.718861 | W22: 3.6663115 | X22: 3.6188895 | Y22: 3.5761943 | Z22: 3.5378231 | AA22: 3.5033735 | AB22: 3.4724444 | AC22: 3.4446637 | AD22: 3.4197932 | AE22: 3.3976326 | AF22: 3.3779807 | AG22: 3.3606364 | AH22: 3.3453992 | AI22: 3.332068 | AJ22: 3.3204417 | AK22: 3.3103197 | AL22: 3.3015011 | AM22: 3.2937847 | AN22: 3.2869698 | AO22: 3.2808836 | AP22: 3.2754765 | AQ22: 3.2707334 | AR22: 3.2666391 | AS22: 3.2631784 | AT22: 3.260336 | AU22: 3.2580967 | AV22: 3.2564452 | AW22: 3.2553664 | AX22: 3.2548451 | AY22: 3.2548659 | AZ22: 3.2554136 | BA22: 3.2564736 | BB22: 3.258033 | BC22: 3.2600796 | BD22: 3.2626013 | BE22: 3.2655858 | BF22: 3.269021 | BG22: 3.2728947 | BH22: 3.2771947 | BI22: 3.2819087 | BJ22: 3.2870246 | BK22: 3.2925303 | BL22: 3.2984134 | BM22: 3.3409003 | BN22: 3.3935567
A23: =+A18+7 -> 45313 | B23: 20240122 | C23: 5.25 | D23: 5.1879 | E23: 5.1876758 | F23: 5.1735163 | G23: 5.1304359 | H23: 5.0506997 | I23: 4.9406132 | J23: 4.8124133 | K23: 4.6785996 | L23: 4.548289 | M23: 4.4266204 | N23: 4.3151828 | O23: 4.2142326 | P23: 4.1228926 | Q23: 4.0394159 | R23: 3.9630131 | S23: 3.8932351 | T23: 3.8296297 | U23: 3.7717453 | V23: 3.7191321 | W23: 3.6713504 | X23: 3.6280058 | Y23: 3.5887163 | Z23: 3.5530986 | AA23: 3.5207691 | AB23: 3.4913458 | AC23: 3.4644814 | AD23: 3.4399885 | AE23: 3.4177248 | AF23: 3.3975468 | AG23: 3.3793113 | AH23: 3.3628758 | AI23: 3.3480969 | AJ23: 3.3348316 | AK23: 3.322937 | AL23: 3.31227 | AM23: 3.3026875 | AN23: 3.2940466 | AO23: 3.2862231 | AP23: 3.2791755 | AQ23: 3.2728859 | AR23: 3.2673357 | AS23: 3.2625067 | AT23: 3.2583806 | AU23: 3.2549391 | AV23: 3.2521639 | AW23: 3.2500366 | AX23: 3.2485391 | AY23: 3.2476529 | AZ23: 3.2473597 | BA23: 3.247642 | BB23: 3.2484853 | BC23: 3.2498763 | BD23: 3.251802 | BE23: 3.2542491 | BF23: 3.2572043 | BG23: 3.2606544 | BH23: 3.2645863 | BI23: 3.2689867 | BJ23: 3.2738422 | BK23: 3.2791399 | BL23: 3.2848664 | BM23: 3.3273444 | BN23: 3.3810345
A24: =+A19+7 -> 45314 | B24: 20240123 | C24: 5.25 | D24: 5.1873 | E24: 5.1859941 | F24: 5.174959 | G24: 5.1400496 | H24: 5.0725396 | I24: 4.9760912 | J24: 4.8604414 | K24: 4.7365585 | L24: 4.6134216 | M24: 4.496681 | N24: 4.3890212 | O24: 4.2910856 | P24: 4.2025817 | Q24: 4.1210901 | R24: 4.0457403 | S24: 3.9762845 | T24: 3.912472 | U24: 3.8540524 | V24: 3.8007774 | W24: 3.752374 | X24: 3.7084834 | Y24: 3.668728 | Z24: 3.6327287 | AA24: 3.6001064 | AB24: 3.5704832 | AC24: 3.5435145 | AD24: 3.519007 | AE24: 3.4968103 | AF24: 3.4767731 | AG24: 3.4587441 | AH24: 3.4425727 | AI24: 3.4281076 | AJ24: 3.4151976 | AK24: 3.403692 | AL24: 3.3934397 | AM24: 3.3842894 | AN24: 3.3760902 | AO24: 3.3687072 | AP24: 3.3620912 | AQ24: 3.3562225 | AR24: 3.3510809 | AS24: 3.3466465 | AT24: 3.3428994 | AU24: 3.3398195 | AV24: 3.3373869 | AW24: 3.3355815 | AX24: 3.3343835 | AY24: 3.3337727 | AZ24: 3.3337293 | BA24: 3.334234 | BB24: 3.3352711 | BC24: 3.3368259 | BD24: 3.3388839 | BE24: 3.3414304 | BF24: 3.3444509 | BG24: 3.3479307 | BH24: 3.3518553 | BI24: 3.3562099 | BJ24: 3.36098 | BK24: 3.3661511 | BL24: 3.3717084 | BM24: 3.4123271 | BN24: 3.4630552
... A71: =+A66+7 -> 45379 | B71: 20240328 | C71: 5.25 | D71: 5.1911 | E71: 5.1827949 | F71: 5.1285197 | G71: 5.0548387 | H71: 4.9650427 | I71: 4.8685886 | J71: 4.7708037 | K71: 4.6732194 | L71: 4.5769532 | M71: 4.4834965 | N71: 4.3944428 | O71: 4.3108747 | P71: 4.2335021 | Q71: 4.162811 | R71: 4.0982378 | S71: 4.0389508 | T71: 3.9841158 | U71: 3.9328986 | V71: 3.8844672 | W71: 3.8381017 | X71: 3.7936677 | Y71: 3.7512193 | Z71: 3.7108091 | AA71: 3.6724898 | AB71: 3.6363153 | AC71: 3.6023211 | AD71: 3.5704587 | AE71: 3.5406553 | AF71: 3.5128369 | AG71: 3.4869296 | AH71: 3.4628602 | AI71: 3.440555 | AJ71: 3.4199399 | AK71: 3.400942 | AL71: 3.3834872 | AM71: 3.3675018 | AN71: 3.3529125 | AO71: 3.3396465 | AP71: 3.3276361 | AQ71: 3.3168154 | AR71: 3.307118 | AS71: 3.2984779 | AT71: 3.2908291 | AU71: 3.2841052 | AV71: 3.2782402 | AW71: 3.273168 | AX71: 3.2688225 | AY71: 3.2651374 | AZ71: 3.2620468 | BA71: 3.2594922 | BB71: 3.2574503 | BC71: 3.2559073 | BD71: 3.2548493 | BE71: 3.2542624 | BF71: 3.2541328 | BG71: 3.2544467 | BH71: 3.2551903 | BI71: 3.2563496 | BJ71: 3.2579108 | BK71: 3.2598602 | BL71: 3.2621838 | BM71: 3.2833438 | BN71: 3.3153029
A72: =+A67+7 -> 45380 | B72: 20240329 | C72: 5.25 | D72: #N/A | E72: #N/A | F72: #N/A | G72: #N/A | H72: #N/A | I72: #N/A | J72: #N/A | K72: #N/A | L72: #N/A | M72: #N/A | N72: #N/A | O72: #N/A | P72: #N/A | Q72: #N/A | R72: #N/A | S72: #N/A | T72: #N/A | U72: #N/A | V72: #N/A | W72: #N/A | X72: #N/A | Y72: #N/A | Z72: #N/A | AA72: #N/A | AB72: #N/A | AC72: #N/A | AD72: #N/A | AE72: #N/A | AF72: #N/A | AG72: #N/A | AH72: #N/A | AI72: #N/A | AJ72: #N/A | AK72: #N/A | AL72: #N/A | AM72: #N/A | AN72: #N/A | AO72: #N/A | AP72: #N/A | AQ72: #N/A | AR72: #N/A | AS72: #N/A | AT72: #N/A | AU72: #N/A | AV72: #N/A | AW72: #N/A | AX72: #N/A | AY72: #N/A | AZ72: #N/A | BA72: #N/A | BB72: #N/A | BC72: #N/A | BD72: #N/A | BE72: #N/A | BF72: #N/A | BG72: #N/A | BH72: #N/A | BI72: #N/A | BJ72: #N/A | BK72: #N/A | BL72: #N/A | BM72: #N/A | BN72: #N/A
A73: =+A68+7 -> 45383 | B73: 20240401 | C73: 5.25 | D73: #N/A | E73: #N/A | F73: #N/A | G73: #N/A | H73: #N/A | I73: #N/A | J73: #N/A | K73: #N/A | L73: #N/A | M73: #N/A | N73: #N/A | O73: #N/A | P73: #N/A | Q73: #N/A | R73: #N/A | S73: #N/A | T73: #N/A | U73: #N/A | V73: #N/A | W73: #N/A | X73: #N/A | Y73: #N/A | Z73: #N/A | AA73: #N/A | AB73: #N/A | AC73: #N/A | AD73: #N/A | AE73: #N/A | AF73: #N/A | AG73: #N/A | AH73: #N/A | AI73: #N/A | AJ73: #N/A | AK73: #N/A | AL73: #N/A | AM73: #N/A | AN73: #N/A | AO73: #N/A | AP73: #N/A | AQ73: #N/A | AR73: #N/A | AS73: #N/A | AT73: #N/A | AU73: #N/A | AV73: #N/A | AW73: #N/A | AX73: #N/A | AY73: #N/A | AZ73: #N/A | BA73: #N/A | BB73: #N/A | BC73: #N/A | BD73: #N/A | BE73: #N/A | BF73: #N/A | BG73: #N/A | BH73: #N/A | BI73: #N/A | BJ73: #N/A | BK73: #N/A | BL73: #N/A | BM73: #N/A | BN73: #N/A
A74: =+A69+7 -> 45384 | B74: 20240402 | C74: 5.25 | D74: 5.1956 | E74: 5.1807489 | F74: 5.1199562 | G74: 5.0432068 | H74: 4.9538124 | I74: 4.8601742 | J74: 4.7672807 | K74: 4.6768675 | L74: 4.5904147 | M74: 4.5095263 | N74: 4.4349691 | O74: 4.3666138 | P74: 4.3040203 | Q74: 4.245397 | R74: 4.1899963 | S74: 4.1374546 | T74: 4.0874062 | U74: 4.0394856 | V74: 3.993329 | W74: 3.9486534 | X74: 3.9055228 | Y74: 3.8640941 | Z74: 3.8245225 | AA74: 3.7869632 | AB74: 3.751573 | AC74: 3.7184638 | AD74: 3.6875746 | AE74: 3.6588023 | AF74: 3.6320425 | AG74: 3.6071911 | AH74: 3.5841446 | AI74: 3.5627989 | AJ74: 3.5430499 | AK74: 3.5247939 | AL74: 3.507927 | AM74: 3.4923449 | AN74: 3.4779442 | AO74: 3.4646324 | AP74: 3.4523639 | AQ74: 3.4411054 | AR74: 3.430823 | AS74: 3.4214829 | AT74: 3.4130515 | AU74: 3.4054951 | AV74: 3.3987798 | AW74: 3.3928722 | AX74: 3.3877384 | AY74: 3.3833446 | AZ74: 3.3796573 | BA74: 3.3766452 | BB74: 3.3742886 | BC74: 3.3725717 | BD74: 3.3714786 | BE74: 3.3709933 | BF74: 3.3710999 | BG74: 3.3717825 | BH74: 3.3730252 | BI74: 3.3748121 | BJ74: 3.3771271 | BK74: 3.3799545 | BL74: 3.3832782 | BM74: 3.4124666 | BN74: 3.4537561
A75: =+A70+7 -> 45385 | B75: 20240403 | C75: 5.25 | D75: 5.1952 | E75: 5.1797674 | F75: 5.1131197 | G75: 5.0320872 | H75: 4.9409016 | I75: 4.8471024 | J75: 4.7546427 | K75: 4.6646348 | L75: 4.5782068 | M75: 4.4967782 | N75: 4.4211358 | O75: 4.3513992 | P75: 4.2873411 | Q75: 4.2279176 | R75: 4.1723537 | S75: 4.1200009 | T75: 4.0702083 | U75: 4.0223254 | V75: 3.9757031 | W75: 3.9298374 | X75: 3.8848387 | Y75: 3.8409809 | Z75: 3.7985361 | AA75: 3.7577764 | AB75: 3.7189756 | AC75: 3.6823697 | AD75: 3.6479792 | AE75: 3.6157465 | AF75: 3.5856125 | AG75: 3.5575183 | AH75: 3.531406 | AI75: 3.5072165 | AJ75: 3.4848911 | AK75: 3.4643715 | AL75: 3.445599 | AM75: 3.4285146 | AN75: 3.4130603 | AO75: 3.399174 | AP75: 3.3867787 | AQ75: 3.375793 | AR75: 3.3661353 | AS75: 3.3577239 | AT75: 3.3504775 | AU75: 3.3443143 | AV75: 3.3391528 | AW75: 3.3349114 | AX75: 3.3315087 | AY75: 3.3288628 | AZ75: 3.3268925 | BA75: 3.3255251 | BB75: 3.324728 | BC75: 3.3244799 | BD75: 3.3247592 | BE75: 3.3255443 | BF75: 3.3268139 | BG75: 3.3285463 | BH75: 3.3307202 | BI75: 3.3333139 | BJ75: 3.3363061 | BK75: 3.3396751 | BL75: 3.3433996 | BM75: 3.3723498 | BN75: 3.4107635
A76: =+A71+7 -> 45386 | B76: 20240404 | C76: 5.25 | D76: 5.1949 | E76: 5.1769496 | F76: 5.1016997 | G76: 5.0170889 | H76: 4.9251208 | I76: 4.8317243 | J76: 4.740301 | K76: 4.6518337 | L76: 4.5674583 | M76: 4.488418 | N76: 4.415362 | O76: 4.3478637 | P76: 4.285214 | Q76: 4.2255322 | R76: 4.1681248 | S76: 4.1126996 | T76: 4.0589627 | U76: 4.0066199 | V76: 3.9553792 | W76: 3.9050367 | X76: 3.8558508 | Y76: 3.8082292 | Z76: 3.762578 | AA76: 3.7193033 | AB76: 3.6788126 | AC76: 3.6414432 | AD76: 3.6071603 | AE76: 3.5758061 | AF76: 3.5472212 | AG76: 3.5212464 | AH76: 3.4977234 | AI76: 3.4764931 | AJ76: 3.4573963 | AK76: 3.4402745 | AL76: 3.4249688 | AM76: 3.4113199 | AN76: 3.3991694 | AO76: 3.3883705 | AP76: 3.3788308 | AQ76: 3.3704734 | AR76: 3.3632209 | AS76: 3.356996 | AT76: 3.3517216 | AU76: 3.3473204 | AV76: 3.3437151 | AW76: 3.3408285 | AX76: 3.3385835 | AY76: 3.3369027 | AZ76: 3.3357089 | BA76: 3.3349356 | BB76: 3.3345643 | BC76: 3.3345893 | BD76: 3.3350051 | BE76: 3.3358062 | BF76: 3.3369869 | BG76: 3.3385418 | BH76: 3.3404654 | BI76: 3.3427521 | BJ76: 3.3453962 | BK76: 3.3483924 | BL76: 3.3517351 | BM76: 3.3785759 | BN76: 3.4153988
A77: =+A72+7 -> 45387 | B77: 20240405 | C77: 5.25 | D77: 5.1949 | E77: 5.1743507 | F77: 5.0990626 | G77: 5.0156411 | H77: 4.9256211 | I77: 4.8342136 | J77: 4.7444207 | K77: 4.6568399 | L77: 4.5722358 | M77: 4.4916264 | N77: 4.4156849 | O77: 4.3445416 | P77: 4.2781786 | Q77: 4.2157358 | R77: 4.1567632 | S77: 4.1010152 | T77: 4.0482438 | U77: 3.9982015 | V77: 3.9506425 | W77: 3.9053601 | X77: 3.862339 | Y77: 3.8216207 | Z77: 3.783245 | AA77: 3.747252 | AB77: 3.7136829 | AC77: 3.682556 | AD77: 3.6537839 | AE77: 3.6272481 | AF77: 3.6028289 | AG77: 3.5804068 | AH77: 3.5598631 | AI77: 3.5410783 | AJ77: 3.5239328 | AK77: 3.5083079 | AL77: 3.494084 | AM77: 3.4811418 | AN77: 3.4693622 | AO77: 3.4586379 | AP77: 3.4489092 | AQ77: 3.440129 | AR77: 3.4322496 | AS77: 3.4252234 | AT77: 3.4190032 | AU77: 3.4135414 | AV77: 3.4087904 | AW77: 3.4047029 | AX77: 3.4012313 | AY77: 3.3983281 | AZ77: 3.3959459 | BA77: 3.394043 | BB77: 3.3926035 | BC77: 3.3916186 | BD77: 3.3910794 | BE77: 3.390977 | BF77: 3.3913028 | BG77: 3.3920477 | BH77: 3.3932031 | BI77: 3.39476 | BJ77: 3.3967096 | BK77: 3.3990431 | BL77: 3.4017517 | BM77: 3.4253239 | BN77: 3.4598017
A78: =+A73+7 -> 45390 | B78: 20240408 | C78: 5.25 | D78: 5.1949 | E78: 5.1730522 | F78: 5.0963888 | G78: 5.0139903 | H78: 4.927098 | I78: 4.8391915 | J78: 4.7523231 | K78: 4.6673225 | L78: 4.5856252 | M78: 4.5090046 | N78: 4.438254 | O78: 4.3734106 | P78: 4.3140391 | Q78: 4.2587921 | R78: 4.2069901 | S78: 4.1582037 | T78: 4.1120019 | U78: 4.0679533 | V78: 4.0256285 | W78: 3.9846795 | X78: 3.945108 | Y78: 3.9070088 | Z78: 3.8704753 | AA78: 3.8356012 | AB78: 3.802481 | AC78: 3.7711816 | AD78: 3.7416622 | AE78: 3.7138564 | AF78: 3.6876969 | AG78: 3.6631161 | AH78: 3.6400476 | AI78: 3.6184239 | AJ78: 3.5981777 | AK78: 3.5792423 | AL78: 3.5615504 | AM78: 3.5450348 | AN78: 3.5296285 | AO78: 3.5152706 | AP78: 3.5019243 | AQ78: 3.4895598 | AR78: 3.4781464 | AS78: 3.4676539 | AT78: 3.458052 | AU78: 3.4493105 | AV78: 3.4413988 | AW78: 3.4342869 | AX78: 3.4279443 | AY78: 3.4223407 | AZ78: 3.417446 | BA78: 3.4132316 | BB78: 3.4096799 | BC78: 3.4067769 | BD78: 3.4045083 | BE78: 3.4028602 | BF78: 3.4018183 | BG78: 3.4013687 | BH78: 3.4014971 | BI78: 3.4021895 | BJ78: 3.4034318 | BK78: 3.4052099 | BL78: 3.4075096 | BM78: 3.431248 | BN78: 3.4688325
A79: =+A74+7 -> 45391 | B79: 20240409 | C79: 5.25 | D79: 5.1976 | E79: 5.1735725 | F79: 5.0952865 | G79: 5.0105427 | H79: 4.9211557 | I79: 4.8305117 | J79: 4.7405381 | K79: 4.6521592 | L79: 4.5669255 | M79: 4.4867711 | N79: 4.4127683 | O79: 4.3449946 | P79: 4.2831506 | Q79: 4.225535 | R79: 4.1713594 | S79: 4.1201866 | T79: 4.0715771 | U79: 4.025092 | V79: 3.9802938 | W79: 3.936831 | X79: 3.8947212 | Y79: 3.8540801 | Z79: 3.815022 | AA79: 3.7776613 | AB79: 3.7421137 | AC79: 3.7084644 | AD79: 3.676683 | AE79: 3.6467111 | AF79: 3.6184892 | AG79: 3.5919577 | AH79: 3.5670583 | AI79: 3.5437313 | AJ79: 3.5219175 | AK79: 3.5015582 | AL79: 3.482594 | AM79: 3.4649655 | AN79: 3.448614 | AO79: 3.4334831 | AP79: 3.4195288 | AQ79: 3.4067104 | AR79: 3.3949868 | AS79: 3.3843168 | AT79: 3.3746598 | AU79: 3.3659747 | AV79: 3.3582204 | AW79: 3.3513561 | AX79: 3.3453409 | AY79: 3.3401336 | AZ79: 3.3356935 | BA79: 3.331982 | BB79: 3.3289729 | BC79: 3.3266437 | BD79: 3.324972 | BE79: 3.3239351 | BF79: 3.3235107 | BG79: 3.3236762 | BH79: 3.3244091 | BI79: 3.325687 | BJ79: 3.3274873 | BK79: 3.3297875 | BL79: 3.3325652 | BM79: 3.3580989 | BN79: 3.395766
A80: =+A75+7 -> 45392 | B80: 20240410 | C80: 5.25 | D80: 5.1978 | E80: 5.1829638 | F80: 5.1267104 | G80: 5.0605244 | H80: 4.9882833 | I80: 4.9138514 | J80: 4.8392415 | K80: 4.765667 | L80: 4.6950966 | M80: 4.629687 | N80: 4.570391 | O80: 4.5169311 | P80: 4.4683502 | Q80: 4.4221688 | R80: 4.3774853 | S80: 4.3339173 | T80: 4.2910808 | U80: 4.248592 | V80: 4.2060685 | W80: 4.163245 | X80: 4.1203548 | Y80: 4.0777634 | Z80: 4.035835 | AA80: 3.9949337 | AB80: 3.9554252 | AC80: 3.9176095 | AD80: 3.8815302 | AE80: 3.8471681 | AF80: 3.8145029 | AG80: 3.7835141 | AH80: 3.7541825 | AI80: 3.7264876 | AJ80: 3.7004092 | AK80: 3.6759277 | AL80: 3.653023 | AM80: 3.6316746 | AN80: 3.6118631 | AO80: 3.5935624 | AP80: 3.5767178 | AQ80: 3.5612664 | AR80: 3.547145 | AS80: 3.5342902 | AT80: 3.5226391 | AU80: 3.5121283 | AV80: 3.5026947 | AW80: 3.4942752 | AX80: 3.4868066 | AY80: 3.4802256 | AZ80: 3.4744691 | BA80: 3.4694794 | BB80: 3.4652226 | BC80: 3.4616714 | BD80: 3.4587988 | BE80: 3.4565772 | BF80: 3.4549797 | BG80: 3.453979 | BH80: 3.4535477 | BI80: 3.4536587 | BJ80: 3.4542847 | BK80: 3.4553985 | BL80: 3.4569729 | BM80: 3.4749519 | BN80: 3.5049891
A81: =+A76+7 -> 45393 | B81: 20240411 | C81: 5.25 | D81: 5.198 | E81: 5.1842682 | F81: 5.1430865 | G81: 5.0913354 | H81: 5.0313446 | I81: 4.9668834 | J81: 4.9006882 | K81: 4.8343025 | L81: 4.7698293 | M81: 4.70966 | N81: 4.6552127 | O81: 4.6062733 | P81: 4.5618678 | Q81: 4.5187788 | R81: 4.4759072 | S81: 4.4328707 | T81: 4.3892856 | U81: 4.3447682 | V81: 4.2989362 | W81: 4.2515468 | X81: 4.2030786 | Y81: 4.1542425 | Z81: 4.1057479 | AA81: 4.058304 | AB81: 4.0126218 | AC81: 3.9693057 | AD81: 3.9284478 | AE81: 3.8899863 | AF81: 3.8538578 | AG81: 3.8199987 | AH81: 3.788347 | AI81: 3.7588392 | AJ81: 3.7314121 | AK81: 3.7060033 | AL81: 3.6825495 | AM81: 3.6609875 | AN81: 3.6412548 | AO81: 3.6232832 | AP81: 3.6069827 | AQ81: 3.5922578 | AR81: 3.5790124 | AS81: 3.5671505 | AT81: 3.5565765 | AU81: 3.5471944 | AV81: 3.5389083 | AW81: 3.5316223 | AX81: 3.5252406 | AY81: 3.5196672 | AZ81: 3.5148063 | BA81: 3.5105735 | BB81: 3.5069347 | BC81: 3.5038699 | BD81: 3.501359 | BE81: 3.4993819 | BF81: 3.4979186 | BG81: 3.4969489 | BH81: 3.4964528 | BI81: 3.4964103 | BJ81: 3.4968011 | BK81: 3.4976054 | BL81: 3.4988029 | BM81: 3.5134585 | BN81: 3.5392484
A82: =+A77+7 -> 45394 | B82: 20240412 | C82: 5.25 | D82: 5.198 | E82: 5.1777519 | F82: 5.1243654 | G82: 5.0619834 | H82: 4.99353 | I82: 4.922471 | J82: 4.8506936 | K82: 4.7792744 | L82: 4.7097298 | M82: 4.6435819 | N82: 4.5815523 | O82: 4.5234462 | P82: 4.4687694 | Q82: 4.4162013 | R82: 4.3652519 | S82: 4.3157671 | T82: 4.2675908 | U82: 4.2205672 | V82: 4.174542 | W82: 4.1294101 | X82: 4.0853022 | Y82: 4.0424186 | Z82: 4.0009584 | AA82: 3.9611205 | AB82: 3.9231054 | AC82: 3.8870719 | AD82: 3.8530021 | AE82: 3.8208309 | AF82: 3.7904914 | AG82: 3.7619172 | AH82: 3.7350428 | AI82: 3.7098016 | AJ82: 3.6861272 | AK82: 3.6639539 | AL82: 3.6432152 | AM82: 3.6238448 | AN82: 3.6057768 | AO82: 3.588948 | AP82: 3.5733078 | AQ82: 3.5588093 | AR82: 3.5454051 | AS82: 3.5330478 | AT82: 3.5216904 | AU82: 3.5112855 | AV82: 3.5017858 | AW82: 3.4931442 | AX82: 3.4853134 | AY82: 3.4782459 | AZ82: 3.4718949 | BA82: 3.4662174 | BB82: 3.4611909 | BC82: 3.4567989 | BD82: 3.4530242 | BE82: 3.4498502 | BF82: 3.4472599 | BG82: 3.4452364 | BH82: 3.443763 | BI82: 3.4428228 | BJ82: 3.4423989 | BK82: 3.4424745 | BL82: 3.4430327 | BM82: 3.4556619 | BN82: 3.4819572
A83: =+A78+7 -> 45397 | B83: 20240415 | C83: 5.25 | D83: 5.1984 | E83: 5.1768825 | F83: 5.1245399 | G83: 5.0626385 | H83: 4.9957348 | I83: 4.9274829 | J83: 4.8597546 | K83: 4.794103 | L83: 4.7324453 | M83: 4.6765649 | N83: 4.6268466 | O83: 4.5824389 | P83: 4.5418212 | Q83: 4.5020418 | R83: 4.4622795 | S83: 4.4224011 | T83: 4.3822716 | U83: 4.3417564 | V83: 4.300722 | W83: 4.2591184 | X83: 4.2172519 | Y83: 4.1755238 | Z83: 4.1343338 | AA83: 4.0940818 | AB83: 4.0551691 | AC83: 4.0179235 | AD83: 3.9823854 | AE83: 3.9485244 | AF83: 3.9163092 | AG83: 3.885708 | AH83: 3.8566906 | AI83: 3.8292254 | AJ83: 3.803281 | AK83: 3.7788268 | AL83: 3.7558314 | AM83: 3.7342635 | AN83: 3.7140923 | AO83: 3.6952842 | AP83: 3.6777964 | AQ83: 3.6615844 | AR83: 3.646603 | AS83: 3.6328071 | AT83: 3.6201523 | AU83: 3.6085933 | AV83: 3.5980852 | AW83: 3.5885833 | AX83: 3.5800426 | AY83: 3.572418 | AZ83: 3.5656648 | BA83: 3.5597402 | BB83: 3.5546147 | BC83: 3.550264 | BD83: 3.5466632 | BE83: 3.5437879 | BF83: 3.5416135 | BG83: 3.5401155 | BH83: 3.5392693 | BI83: 3.5390503 | BJ83: 3.539434 | BK83: 3.5403957 | BL83: 3.541911 | BM83: 3.5613048 | BN83: 3.5947629
A84: =+A79+7 -> 45398 | B84: 20240416 | C84: 5.25 | D84: 5.1984 | E84: 5.1825747 | F84: 5.1409117 | G84: 5.0900899 | H84: 5.034852 | I84: 4.9785409 | J84: 4.9223758 | K84: 4.8672673 | L84: 4.8146038 | M84: 4.7658647 | N84: 4.7216218 | O84: 4.6813829 | P84: 4.6441791 | Q84: 4.6078024 | R84: 4.5714875 | S84: 4.5349473 | T84: 4.4978936 | U84: 4.4600379 | V84: 4.4210934 | W84: 4.3808913 | X84: 4.3397655 | Y84: 4.2981834 | Z84: 4.2566108 | AA84: 4.2155137 | AB84: 4.1753595 | AC84: 4.1365375 | AD84: 4.0991307 | AE84: 4.0631469 | AF84: 4.0285926 | AG84: 3.9954743 | AH84: 3.9637998 | AI84: 3.9335754 | AJ84: 3.9048077 | AK84: 3.8775045 | AL84: 3.8516721 | AM84: 3.8273173 | AN84: 3.8044475 | AO84: 3.78306 | AP84: 3.7631148 | AQ84: 3.7445632 | AR84: 3.7273558 | AS84: 3.7114432 | AT84: 3.6967768 | AU84: 3.6833072 | AV84: 3.6709851 | AW84: 3.6597616 | AX84: 3.6495875 | AY84: 3.6404135 | AZ84: 3.6321907 | BA84: 3.6248722 | BB84: 3.6184239 | BC84: 3.6128164 | BD84: 3.6080198 | BE84: 3.6040043 | BF84: 3.6007404 | BG84: 3.5981984 | BH84: 3.5963484 | BI84: 3.5951608 | BJ84: 3.594606 | BK84: 3.5946542 | BL84: 3.5952757 | BM84: 3.6095937 | BN84: 3.6383558
A85: =+A80+7 -> 45399 | B85: 20240417 | C85: 5.25 | D85: 5.1984 | E85: 5.1864649 | F85: 5.1406635 | G85: 5.082378 | H85: 5.0182776 | I85: 4.9533389 | J85: 4.8893764 | K85: 4.8279117 | L85: 4.7707196 | M85: 4.7193814 | N85: 4.674208 | O85: 4.634165 | P85: 4.5975445 | Q85: 4.5610471 | R85: 4.5238099 | S85: 4.4857238 | T85: 4.4466787 | U85: 4.4065642 | V85: 4.3652716 | W85: 4.3227819 | X85: 4.2794604 | Y85: 4.235775 | Z85: 4.1921919 | AA85: 4.1491773 | AB85: 4.1071989 | AC85: 4.0666479 | AD85: 4.0276152 | AE85: 3.9901181 | AF85: 3.9541724 | AG85: 3.9197939 | AH85: 3.8869999 | AI85: 3.8558062 | AJ85: 3.8262287 | AK85: 3.7982845 | AL85: 3.7719895 | AM85: 3.7473598 | AN85: 3.7244121 | AO85: 3.7031517 | AP85: 3.6835306 | AQ85: 3.6654853 | AR85: 3.6489518 | AS85: 3.6338659 | AT85: 3.6201642 | AU85: 3.6077825 | AV85: 3.596657 | AW85: 3.5867238 | AX85: 3.5779191 | AY85: 3.5701788 | AZ85: 3.5634393 | BA85: 3.5576398 | BB85: 3.5527354 | BC85: 3.5486865 | BD85: 3.5454529 | BE85: 3.5429948 | BF85: 3.5412723 | BG85: 3.5402453 | BH85: 3.539874 | BI85: 3.5401185 | BJ85: 3.5409387 | BK85: 3.5422949 | BL85: 3.544147 | BM85: 3.5641156 | BN85: 3.5959834
... A97: =+A92+7 -> 45415 | B97: 20240503 | C97: 5.25 | D97: 5.2001 | E97: 5.1712702 | F97: 5.1003635 | G97: 5.0239676 | H97: 4.9492633 | I97: 4.8792355 | J97: 4.8124831 | K97: 4.7483961 | L97: 4.6876538 | M97: 4.6308991 | N97: 4.578289 | O97: 4.5293833 | P97: 4.4832177 | Q97: 4.4378251 | R97: 4.392694 | S97: 4.3479186 | T97: 4.3035917 | U97: 4.2598065 | V97: 4.2166574 | W97: 4.1742532 | X97: 4.1327758 | Y97: 4.0924297 | Z97: 4.0534181 | AA97: 4.015944 | AB97: 3.9802119 | AC97: 3.9463882 | AD97: 3.9144595 | AE97: 3.8843591 | AF97: 3.856019 | AG97: 3.8293713 | AH97: 3.804349 | AI97: 3.7808843 | AJ97: 3.7589094 | AK97: 3.7383572 | AL97: 3.7191599 | AM97: 3.7012497 | AN97: 3.6845594 | AO97: 3.669025 | AP97: 3.6545989 | AQ97: 3.6412384 | AR97: 3.6289004 | AS97: 3.6175419 | AT97: 3.6071201 | AU97: 3.597592 | AV97: 3.5889146 | AW97: 3.5810451 | AX97: 3.5739404 | AY97: 3.5675576 | AZ97: 3.5618538 | BA97: 3.5567901 | BB97: 3.5523454 | BC97: 3.5485037 | BD97: 3.5452489 | BE97: 3.5425648 | BF97: 3.5404353 | BG97: 3.5388445 | BH97: 3.5377761 | BI97: 3.5372141 | BJ97: 3.5371425 | BK97: 3.537545 | BL97: 3.5384056 | BM97: 3.5524607 | BN97: 3.5799985
A98: =+A93+7 -> 45418 | B98: 20240506 | C98: 5.25 | D98: #N/A | E98: #N/A | F98: #N/A | G98: #N/A | H98: #N/A | I98: #N/A | J98: #N/A | K98: #N/A | L98: #N/A | M98: #N/A | N98: #N/A | O98: #N/A | P98: #N/A | Q98: #N/A | R98: #N/A | S98: #N/A | T98: #N/A | U98: #N/A | V98: #N/A | W98: #N/A | X98: #N/A | Y98: #N/A | Z98: #N/A | AA98: #N/A | AB98: #N/A | AC98: #N/A | AD98: #N/A | AE98: #N/A | AF98: #N/A | AG98: #N/A | AH98: #N/A | AI98: #N/A | AJ98: #N/A | AK98: #N/A | AL98: #N/A | AM98: #N/A | AN98: #N/A | AO98: #N/A | AP98: #N/A | AQ98: #N/A | AR98: #N/A | AS98: #N/A | AT98: #N/A | AU98: #N/A | AV98: #N/A | AW98: #N/A | AX98: #N/A | AY98: #N/A | AZ98: #N/A | BA98: #N/A | BB98: #N/A | BC98: #N/A | BD98: #N/A | BE98: #N/A | BF98: #N/A | BG98: #N/A | BH98: #N/A | BI98: #N/A | BJ98: #N/A | BK98: #N/A | BL98: #N/A | BM98: #N/A | BN98: #N/A
A99: =+A94+7 -> 45419 | B99: 20240507 | C99: 5.25 | D99: 5.2 | E99: 5.1658608 | F99: 5.0926656 | G99: 5.0167812 | H99: 4.9418598 | I99: 4.868704 | J99: 4.7956925 | K99: 4.7232078 | L99: 4.6533796 | M99: 4.5881558 | N99: 4.5286464 | O99: 4.4751233 | P99: 4.4268952 | Q99: 4.3825152 | R99: 4.3410095 | S99: 4.3015751 | T99: 4.2634071 | U99: 4.2257011 | V99: 4.1876536 | W99: 4.1486331 | X99: 4.1088111 | Y99: 4.068593 | Z99: 4.0283828 | AA99: 3.9885846 | AB99: 3.9496039 | AC99: 3.9117837 | AD99: 3.8752231 | AE99: 3.8399614 | AF99: 3.8060366 | AG99: 3.773487 | AH99: 3.7423516 | AI99: 3.7126687 | AJ99: 3.6844763 | AK99: 3.6578136 | AL99: 3.6327188 | AM99: 3.60923 | AN99: 3.5873863 | AO99: 3.5672085 | AP99: 3.5486485 | AQ99: 3.5316413 | AR99: 3.5161215 | AS99: 3.5020234 | AT99: 3.4892821 | AU99: 3.4778321 | AV99: 3.4676079 | AW99: 3.4585445 | AX99: 3.4505764 | AY99: 3.4436383 | AZ99: 3.4376648 | BA99: 3.432595 | BB99: 3.4283889 | BC99: 3.4250133 | BD99: 3.4224346 | BE99: 3.4206194 | BF99: 3.4195344 | BG99: 3.4191461 | BH99: 3.419421 | BI99: 3.4203258 | BJ99: 3.421827 | BK99: 3.4238912 | BL99: 3.426485 | BM99: 3.4516748 | BN99: 3.489822
A100: =+A95+7 -> 45420 | B100: 20240508 | C100: 5.25 | D100: 5.2 | E100: 5.1566669 | F100: 5.0761636 | G100: 4.997842 | H100: 4.9231594 | I100: 4.8509448 | J100: 4.7793498 | K100: 4.7094935 | L100: 4.6441852 | M100: 4.5851155 | N100: 4.5327786 | O100: 4.4861275 | P100: 4.4436754 | Q100: 4.4026643 | R100: 4.3621283 | S100: 4.3216844 | T100: 4.280948 | U100: 4.2395345 | V100: 4.1970609 | W100: 4.1532546 | X100: 4.1084779 | Y100: 4.063318 | Z100: 4.0183606 | AA100: 3.9741917 | AB100: 3.9313985 | AC100: 3.8904668 | AD100: 3.851482 | AE100: 3.8144311 | AF100: 3.7792993 | AG100: 3.7460722 | AH100: 3.7147364 | AI100: 3.6852775 | AJ100: 3.6576808 | AK100: 3.631933 | AL100: 3.6080197 | AM100: 3.5859263 | AN100: 3.5656394 | AO100: 3.5471347 | AP100: 3.5303398 | AQ100: 3.5151687 | AR100: 3.5015344 | AS100: 3.4893501 | AT100: 3.4785295 | AU100: 3.4689857 | AV100: 3.460632 | AW100: 3.4533819 | AX100: 3.4471488 | AY100: 3.4418457 | AZ100: 3.4373864 | BA100: 3.4336924 | BB100: 3.4307235 | BC100: 3.4284496 | BD100: 3.4268407 | BE100: 3.4258667 | BF100: 3.4254977 | BG100: 3.4257035 | BH100: 3.4264543 | BI100: 3.42772 | BJ100: 3.4294705 | BK100: 3.4316758 | BL100: 3.4343059 | BM100: 3.4578475 | BN100: 3.492279
A101: =+A96+7 -> 45421 | B101: 20240509 | C101: 5.25 | D101: 5.2 | E101: 5.1626161 | F101: 5.0646919 | G101: 4.9759418 | H101: 4.8958561 | I101: 4.8203431 | J101: 4.7453182 | K101: 4.6697515 | L101: 4.5951484 | M101: 4.5236859 | N101: 4.4571984 | O101: 4.396587 | P101: 4.3419605 | Q101: 4.2924698 | R101: 4.2470985 | S101: 4.2048483 | T101: 4.1647193 | U101: 4.1257118 | V101: 4.0868272 | W101: 4.0472549 | X101: 4.0071517 | Y101: 3.9669854 | Z101: 3.9272224 | AA101: 3.888329 | AB101: 3.850773 | AC101: 3.8149553 | AD101: 3.7809581 | AE101: 3.7487675 | AF101: 3.7183684 | AG101: 3.689746 | AH101: 3.6628863 | AI101: 3.6377742 | AJ101: 3.614395 | AK101: 3.5927346 | AL101: 3.572778 | AM101: 3.5545104 | AN101: 3.5379177 | AO101: 3.522974 | AP101: 3.5096053 | AQ101: 3.497725 | AR101: 3.4872455 | AS101: 3.4780798 | AT101: 3.4701408 | AU101: 3.4633413 | AV101: 3.4575941 | AW101: 3.4528121 | AX101: 3.4489083 | AY101: 3.4457953 | AZ101: 3.4433861 | BA101: 3.4416034 | BB101: 3.4404131 | BC101: 3.4397932 | BD101: 3.4397215 | BE101: 3.4401759 | BF101: 3.4411345 | BG101: 3.4425751 | BH101: 3.4444757 | BI101: 3.4468141 | BJ101: 3.4495683 | BK101: 3.4527163 | BL101: 3.4562358 | BM101: 3.4842411 | BN101: 3.5220022
A102: =+A97+7 -> 45422 | B102: 20240510 | C102: 5.25 | D102: 5.2 | E102: 5.1592683 | F102: 5.0635548 | G102: 4.979909 | H102: 4.9063664 | I102: 4.8371351 | J102: 4.7684671 | K102: 4.7001132 | L102: 4.6339371 | M102: 4.5717753 | N102: 4.5145216 | O102: 4.4621251 | P102: 4.4136821 | Q102: 4.3673676 | R102: 4.3224751 | S102: 4.278729 | T102: 4.2358525 | U102: 4.1935683 | V102: 4.151601 | W102: 4.1097573 | X102: 4.0682314 | Y102: 4.0273316 | Z102: 3.9873646 | AA102: 3.9486372 | AB102: 3.9114576 | AC102: 3.8760802 | AD102: 3.8425284 | AE102: 3.8107628 | AF102: 3.780743 | AG102: 3.7524285 | AH102: 3.7257801 | AI102: 3.7007573 | AJ102: 3.6773198 | AK102: 3.6554281 | AL102: 3.6350417 | AM102: 3.6161206 | AN102: 3.5986249 | AO102: 3.5825116 | AP102: 3.5677257 | AQ102: 3.55421 | AR102: 3.5419067 | AS102: 3.530758 | AT102: 3.5207067 | AU102: 3.5116948 | AV102: 3.5036649 | AW102: 3.4965593 | AX102: 3.4903205 | AY102: 3.4848906 | AZ102: 3.4802124 | BA102: 3.4762334 | BB102: 3.472926 | BC102: 3.470269 | BD102: 3.4682413 | BE102: 3.4668218 | BF102: 3.4659893 | BG102: 3.4657227 | BH102: 3.4660009 | BI102: 3.4668028 | BJ102: 3.4681073 | BK102: 3.4698931 | BL102: 3.4721393 | BM102: 3.4943368 | BN102: 3.5292218
A103: =+A98+7 -> 45425 | B103: 20240513 | C103: 5.25 | D103: 5.2 | E103: 5.1597455 | F103: 5.063519 | G103: 4.9821352 | H103: 4.9109913 | I103: 4.8429709 | J103: 4.7749746 | K103: 4.70779 | L103: 4.6442508 | M103: 4.5867096 | N103: 4.5358374 | O103: 4.4909189 | P103: 4.4502711 | Q103: 4.4110852 | R103: 4.372419 | S103: 4.3339156 | T103: 4.2952165 | U103: 4.2559635 | V103: 4.2157994 | W103: 4.1744892 | X103: 4.1323685 | Y103: 4.0899399 | Z103: 4.0477047 | AA103: 4.006164 | AB103: 3.9658206 | AC103: 3.92709 | AD103: 3.8900458 | AE103: 3.854677 | AF103: 3.8209717 | AG103: 3.7889177 | AH103: 3.7585041 | AI103: 3.7297189 | AJ103: 3.70255 | AK103: 3.6769865 | AL103: 3.6530163 | AM103: 3.6306275 | AN103: 3.609809 | AO103: 3.5905412 | AP103: 3.5727746 | AQ103: 3.5564526 | AR103: 3.5415182 | AS103: 3.5279141 | AT103: 3.5155838 | AU103: 3.5044702 | AV103: 3.4945162 | AW103: 3.4856652 | AX103: 3.47786 | AY103: 3.4710438 | AZ103: 3.4651596 | BA103: 3.4601538 | BB103: 3.4559911 | BC103: 3.4526422 | BD103: 3.4500778 | BE103: 3.4482686 | BF103: 3.4471855 | BG103: 3.446799 | BH103: 3.4470799 | BI103: 3.4479989 | BJ103: 3.4495267 | BK103: 3.4516342 | BL103: 3.4542919 | BM103: 3.4803464 | BN103: 3.5200075
A104: =+A99+7 -> 45426 | B104: 20240514 | C104: 5.25 | D104: 5.2 | E104: 5.1570657 | F104: 5.0577854 | G104: 4.9745817 | H104: 4.9018868 | I104: 4.8328847 | J104: 4.7645375 | K104: 4.6973956 | L104: 4.633822 | M104: 4.5758667 | N104: 4.5241403 | O104: 4.4780785 | P104: 4.4361707 | Q104: 4.3956175 | R104: 4.3555107 | S104: 4.315535 | T104: 4.2753733 | U104: 4.2347087 | V104: 4.1932258 | W104: 4.1507255 | X104: 4.107555 | Y104: 4.0642215 | Z104: 4.0212307 | AA104: 3.9790883 | AB104: 3.9383014 | AC104: 3.8992883 | AD104: 3.8621181 | AE104: 3.8267738 | AF104: 3.793237 | AG104: 3.7614896 | AH104: 3.7315144 | AI104: 3.7032931 | AJ104: 3.6768076 | AK104: 3.6520406 | AL104: 3.628974 | AM104: 3.6075896 | AN104: 3.58787 | AO104: 3.5697882 | AP104: 3.5532813 | AQ104: 3.5382779 | AR104: 3.5247062 | AS104: 3.5124944 | AT104: 3.501571 | AU104: 3.4918643 | AV104: 3.4833025 | AW104: 3.4758141 | AX104: 3.4693273 | AY104: 3.4637703 | AZ104: 3.4590717 | BA104: 3.4551654 | BB104: 3.4520137 | BC104: 3.4495874 | BD104: 3.4478572 | BE104: 3.446794 | BF104: 3.4463685 | BG104: 3.4465515 | BH104: 3.4473139 | BI104: 3.4486263 | BJ104: 3.4504596 | BK104: 3.4527846 | BL104: 3.4555721 | BM104: 3.4807717 | BN104: 3.5176793
A105: =+A100+7 -> 45427 | B105: 20240515 | C105: 5.25 | D105: 5.2 | E105: 5.1536761 | F105: 5.0425642 | G105: 4.9530835 | H105: 4.8765879 | I105: 4.8037872 | J105: 4.7307557 | K105: 4.6574133 | L105: 4.5859727 | M105: 4.5187779 | N105: 4.4572718 | O105: 4.4013475 | P105: 4.3502609 | Q105: 4.3016155 | R105: 4.2544778 | S105: 4.2084324 | T105: 4.1630623 | U105: 4.1179505 | V105: 4.0726816 | W105: 4.0269436 | X105: 3.9810199 | Y105: 3.9354043 | Z105: 3.8905896 | AA105: 3.8470685 | AB105: 3.8053352 | AC105: 3.765792 | AD105: 3.7284797 | AE105: 3.69335 | AF105: 3.6603531 | AG105: 3.6294394 | AH105: 3.6005607 | AI105: 3.5736671 | AJ105: 3.5487093 | AK105: 3.5256386 | AL105: 3.5044055 | AM105: 3.4849605 | AN105: 3.467255 | AO105: 3.4512341 | AP105: 3.4368176 | AQ105: 3.4239176 | AR105: 3.4124459 | AS105: 3.4023144 | AT105: 3.3934352 | AU105: 3.3857201 | AV105: 3.3790811 | AW105: 3.3734302 | AX105: 3.3686792 | AY105: 3.3647402 | AZ105: 3.361525 | BA105: 3.3589552 | BB105: 3.356995 | BC105: 3.3556204 | BD105: 3.3548072 | BE105: 3.3545314 | BF105: 3.3547688 | BG105: 3.3554954 | BH105: 3.3566871 | BI105: 3.3583198 | BJ105: 3.3603695 | BK105: 3.362812 | BL105: 3.3656233 | BM105: 3.389331 | BN105: 3.4229422
A106: =+A101+7 -> 45428 | B106: 20240516 | C106: 5.25 | D106: 5.2 | E106: 5.1477799 | F106: 5.036401 | G106: 4.9501748 | H106: 4.8789412 | I106: 4.811774 | J106: 4.7436211 | K106: 4.673774 | L106: 4.6038292 | M106: 4.5358026 | N106: 4.4711083 | O106: 4.4103961 | P106: 4.3538116 | Q106: 4.3012296 | R106: 4.2520515 | S106: 4.2055673 | T106: 4.1610654 | U106: 4.1178342 | V106: 4.0751638 | W106: 4.0324795 | X106: 3.9899091 | Y106: 3.9478061 | Z106: 3.9065225 | AA106: 3.8664105 | AB106: 3.8278236 | AC106: 3.7910624 | AD106: 3.7561766 | AE106: 3.7231409 | AF106: 3.6919285 | AG106: 3.6625128 | AH106: 3.6348683 | AI106: 3.6089683 | AJ106: 3.5847863 | AK106: 3.5622965 | AL106: 3.5414725 | AM106: 3.5222877 | AN106: 3.5047163 | AO106: 3.4887239 | AP106: 3.4742411 | AQ106: 3.4611891 | AR106: 3.4494889 | AS106: 3.4390614 | AT106: 3.4298279 | AU106: 3.4217093 | AV106: 3.4146265 | AW106: 3.4085007 | AX106: 3.403253 | AY106: 3.3988043 | AZ106: 3.3950757 | BA106: 3.3919969 | BB106: 3.3895366 | BC106: 3.387674 | BD106: 3.3863882 | BE106: 3.3856584 | BF106: 3.3854639 | BG106: 3.3857839 | BH106: 3.3865977 | BI106: 3.3878843 | BJ106: 3.389623 | BK106: 3.3917931 | BL106: 3.3943738 | BM106: 3.417582 | BN106: 3.4519508
A107: =+A102+7 -> 45429 | B107: 20240517 | C107: 5.25 | D107: 5.2 | E107: 5.1480381 | F107: 5.0431696 | G107: 4.9609866 | H107: 4.8918344 | I107: 4.8259089 | J107: 4.7593501 | K107: 4.6921448 | L107: 4.62633 | M107: 4.563981 | N107: 4.5060875 | O107: 4.4526572 | P107: 4.4029029 | Q107: 4.3549837 | R107: 4.3082671 | S107: 4.2625933 | T107: 4.2178012 | U107: 4.1737297 | V107: 4.130219 | W107: 4.0871701 | X107: 4.0447718 | Y107: 4.003298 | Z107: 3.9630207 | AA107: 3.9242125 | AB107: 3.887147 | AC107: 3.8520461 | AD107: 3.8189101 | AE107: 3.7876787 | AF107: 3.7582909 | AG107: 3.7306855 | AH107: 3.7048023 | AI107: 3.6805802 | AJ107: 3.6579582 | AK107: 3.6368759 | AL107: 3.6172722 | AM107: 3.5990862 | AN107: 3.5822574 | AO107: 3.5667258 | AP107: 3.5524355 | AQ107: 3.5393318 | AR107: 3.5273598 | AS107: 3.5164645 | AT107: 3.5065913 | AU107: 3.4976852 | AV107: 3.4896912 | AW107: 3.4825548 | AX107: 3.4762209 | AY107: 3.4706347 | AZ107: 3.4657414 | BA107: 3.4614917 | BB107: 3.4578614 | BC107: 3.4548332 | BD107: 3.4523898 | BE107: 3.4505137 | BF107: 3.4491877 | BG107: 3.4483945 | BH107: 3.4481165 | BI107: 3.4483366 | BJ107: 3.4490374 | BK107: 3.4502015 | BL107: 3.4518116 | BM107: 3.4700334 | BN107: 3.5009502
A108: =+A103+7 -> 45432 | B108: 20240520 | C108: 5.25 | D108: 5.2 | E108: 5.1458317 | F108: 5.0407189 | G108: 4.9615556 | H108: 4.8962773 | I108: 4.8333933 | J108: 4.7694833 | K108: 4.7053932 | L108: 4.6437869 | M108: 4.58688 | N108: 4.5354488 | O108: 4.4891519 | P108: 4.4466964 | Q108: 4.4056142 | R108: 4.3650799 | S108: 4.3248078 | T108: 4.2845108 | U108: 4.2439017 | V108: 4.2026948 | W108: 4.1607125 | X108: 4.1182859 | Y108: 4.0758948 | Z108: 4.0340175 | AA108: 3.9931324 | AB108: 3.9537193 | AC108: 3.9161698 | AD108: 3.8805293 | AE108: 3.8467573 | AF108: 3.8148124 | AG108: 3.7846532 | AH108: 3.7562393 | AI108: 3.7295293 | AJ108: 3.7044817 | AK108: 3.681056 | AL108: 3.659211 | AM108: 3.6389052 | AN108: 3.6200981 | AO108: 3.6027457 | AP108: 3.5867932 | AQ108: 3.5721838 | AR108: 3.5588601 | AS108: 3.5467648 | AT108: 3.5358409 | AU108: 3.5260312 | AV108: 3.5172782 | AW108: 3.509525 | AX108: 3.5027143 | AY108: 3.4967887 | AZ108: 3.4916913 | BA108: 3.487369 | BB108: 3.4837912 | BC108: 3.4809352 | BD108: 3.4787781 | BE108: 3.4772971 | BF108: 3.4764692 | BG108: 3.4762718 | BH108: 3.4766818 | BI108: 3.4776764 | BJ108: 3.4792329 | BK108: 3.4813283 | BL108: 3.4839397 | BM108: 3.5091961 | BN108: 3.5474531
A109: =+A104+7 -> 45433 | B109: 20240521 | C109: 5.25 | D109: 5.2 | E109: 5.1435703 | F109: 5.0432979 | G109: 4.9648542 | H109: 4.8972071 | I109: 4.830589 | J109: 4.7622113 | K109: 4.6931747 | L109: 4.6262303 | M109: 4.5639472 | N109: 4.5075423 | O109: 4.4570337 | P109: 4.4113217 | Q109: 4.3676578 | R109: 4.3250259 | S109: 4.2829982 | T109: 4.2411453 | U109: 4.1990379 | V109: 4.156248 | W109: 4.1124902 | X109: 4.0681461 | Y109: 4.0237921 | Z109: 3.9800031 | AA109: 3.9373541 | AB109: 3.8964215 | AC109: 3.8576737 | AD109: 3.8211525 | AE109: 3.7867943 | AF109: 3.7545346 | AG109: 3.7243084 | AH109: 3.6960524 | AI109: 3.6697016 | AJ109: 3.6451915 | AK109: 3.6224584 | AL109: 3.6014376 | AM109: 3.5820646 | AN109: 3.5642754 | AO109: 3.5480043 | AP109: 3.5331808 | AQ109: 3.5197336 | AR109: 3.5075909 | AS109: 3.4966811 | AT109: 3.4869329 | AU109: 3.4782744 | AV109: 3.4706342 | AW109: 3.4639407 | AX109: 3.4581222 | AY109: 3.4531073 | AZ109: 3.4488243 | BA109: 3.445209 | BB109: 3.4422325 | BC109: 3.439877 | BD109: 3.4381244 | BE109: 3.4369569 | BF109: 3.4363564 | BG109: 3.4363051 | BH109: 3.4367849 | BI109: 3.4377779 | BJ109: 3.4392662 | BK109: 3.4412319 | BL109: 3.4436568 | BM109: 3.4668715 | BN109: 3.5022427
A110: =+A105+7 -> 45434 | B110: 20240522 | C110: 5.25 | D110: 5.2 | E110: 5.1884426 | F110: 5.1484831 | G110: 5.0960044 | H110: 5.0258805 | I110: 4.940567 | J110: 4.8514404 | K110: 4.7719343 | L110: 4.7101938 | M110: 4.6608673 | N110: 4.6198459 | O110: 4.590465 | P110: 4.5755412 | Q110: 4.5617168 | R110: 4.5445679 | S110: 4.5232344 | T110: 4.4968556 | U110: 4.4645703 | V110: 4.4255188 | W110: 4.3791576 | X110: 4.3267421 | Y110: 4.2701621 | Z110: 4.2113063 | AA110: 4.1520633 | AB110: 4.0943236 | AC110: 4.0396473 | AD110: 3.9882797 | AE110: 3.9401392 | AF110: 3.8951427 | AG110: 3.8532067 | AH110: 3.8142498 | AI110: 3.7781885 | AJ110: 3.7449398 | AK110: 3.7144219 | AL110: 3.6865515 | AM110: 3.6612457 | AN110: 3.6384224 | AO110: 3.6179905 | AP110: 3.5998204 | AQ110: 3.5837712 | AR110: 3.5697013 | AS110: 3.5574693 | AT110: 3.5469342 | AU110: 3.5379545 | AV110: 3.5303887 | AW110: 3.5240958 | AX110: 3.5189344 | AY110: 3.514763 | AZ110: 3.5114404 | BA110: 3.5088419 | BB110: 3.5069151 | BC110: 3.5056282 | BD110: 3.504949 | BE110: 3.5048456 | BF110: 3.5052858 | BG110: 3.5062377 | BH110: 3.5076692 | BI110: 3.5095482 | BJ110: 3.5118427 | BK110: 3.5145207 | BL110: 3.51755 | BM110: 3.5420274 | BN110: 3.5754235
... A112: =+A107+7 -> 45436 | B112: 20240524 | C112: 5.25 | D112: 5.2 | E112: 5.1918997 | F112: 5.1544352 | G112: 5.110974 | H112: 5.0623055 | I112: 5.0089365 | J112: 4.9529316 | K112: 4.8968827 | L112: 4.8430324 | M112: 4.7925632 | N112: 4.7454649 | O112: 4.7008909 | P112: 4.6575197 | Q112: 4.6130578 | R112: 4.5670033 | S112: 4.5195777 | T112: 4.4710013 | U112: 4.4214946 | V112: 4.3712795 | W112: 4.3206152 | X112: 4.2699407 | Y112: 4.2197491 | Z112: 4.1705314 | AA112: 4.1227788 | AB112: 4.0769844 | AC112: 4.0335622 | AD112: 3.992551 | AE112: 3.9538769 | AF112: 3.9174641 | AG112: 3.8832375 | AH112: 3.8511226 | AI112: 3.8210442 | AJ112: 3.7929269 | AK112: 3.7666962 | AL112: 3.7422769 | AM112: 3.7195936 | AN112: 3.6985719 | AO112: 3.6791373 | AP112: 3.6612188 | AQ112: 3.6447472 | AR112: 3.6296521 | AS112: 3.6158637 | AT112: 3.6033123 | AU112: 3.5919279 | AV112: 3.5816406 | AW112: 3.5723807 | AX112: 3.5640781 | AY112: 3.556663 | AZ112: 3.5500656 | BA112: 3.544223 | BB112: 3.539104 | BC112: 3.5346858 | BD112: 3.5309457 | BE112: 3.5278611 | BF112: 3.5254092 | BG112: 3.5235673 | BH112: 3.5223128 | BI112: 3.521623 | BJ112: 3.5214751 | BK112: 3.5218465 | BL112: 3.5227144 | BM112: 3.5373486 | BN112: 3.5657763
A113: =+A108+7 -> 45439 | B113: 20240527 | C113: 5.25 | D113: #N/A | E113: #N/A | F113: #N/A | G113: #N/A | H113: #N/A | I113: #N/A | J113: #N/A | K113: #N/A | L113: #N/A | M113: #N/A | N113: #N/A | O113: #N/A | P113: #N/A | Q113: #N/A | R113: #N/A | S113: #N/A | T113: #N/A | U113: #N/A | V113: #N/A | W113: #N/A | X113: #N/A | Y113: #N/A | Z113: #N/A | AA113: #N/A | AB113: #N/A | AC113: #N/A | AD113: #N/A | AE113: #N/A | AF113: #N/A | AG113: #N/A | AH113: #N/A | AI113: #N/A | AJ113: #N/A | AK113: #N/A | AL113: #N/A | AM113: #N/A | AN113: #N/A | AO113: #N/A | AP113: #N/A | AQ113: #N/A | AR113: #N/A | AS113: #N/A | AT113: #N/A | AU113: #N/A | AV113: #N/A | AW113: #N/A | AX113: #N/A | AY113: #N/A | AZ113: #N/A | BA113: #N/A | BB113: #N/A | BC113: #N/A | BD113: #N/A | BE113: #N/A | BF113: #N/A | BG113: #N/A | BH113: #N/A | BI113: #N/A | BJ113: #N/A | BK113: #N/A | BL113: #N/A | BM113: #N/A | BN113: #N/A
A114: =+A109+7 -> 45440 | B114: 20240528 | C114: 5.25 | D114: 5.2 | E114: 5.1907866 | F114: 5.1537904 | G114: 5.1111076 | H114: 5.0630185 | I114: 5.0089531 | J114: 4.9513151 | K114: 4.8936897 | L114: 4.8390533 | M114: 4.7892072 | N114: 4.7444465 | O114: 4.703955 | P114: 4.6661869 | Q114: 4.6285819 | R114: 4.590306 | S114: 4.5510569 | T114: 4.510531 | U114: 4.4684244 | V114: 4.4244351 | W114: 4.3783986 | X114: 4.3307957 | Y114: 4.2822962 | Z114: 4.2335681 | AA114: 4.1852795 | AB114: 4.1380999 | AC114: 4.0925884 | AD114: 4.0488672 | AE114: 4.0069508 | AF114: 3.9668524 | AG114: 3.9285851 | AH114: 3.8921634 | AI114: 3.8576005 | AJ114: 3.8249095 | AK114: 3.7941048 | AL114: 3.7651997 | AM114: 3.7382074 | AN114: 3.7131421 | AO114: 3.6900014 | AP114: 3.6687199 | AQ114: 3.6492174 | AR114: 3.6314127 | AS114: 3.6152249 | AT114: 3.6005735 | AU114: 3.5873774 | AV114: 3.5755558 | AW114: 3.5650281 | AX114: 3.5557132 | AY114: 3.5475304 | AZ114: 3.5403989 | BA114: 3.5342434 | BB114: 3.5290174 | BC114: 3.5246847 | BD114: 3.5212087 | BE114: 3.5185531 | BF114: 3.5166815 | BG114: 3.5155573 | BH114: 3.5151442 | BI114: 3.5154058 | BJ114: 3.5163055 | BK114: 3.5178071 | BL114: 3.5198739 | BM114: 3.5425562 | BN114: 3.5791635
A115: =+A110+7 -> 45441 | B115: 20240529 | C115: 5.25 | D115: 5.2 | E115: 5.1930598 | F115: 5.1596666 | G115: 5.1192513 | H115: 5.073743 | I115: 5.0236947 | J115: 4.9718467 | K115: 4.9214158 | L115: 4.8746751 | M115: 4.8326907 | N115: 4.7954835 | O115: 4.7617536 | P115: 4.7297872 | Q115: 4.6964982 | R115: 4.6611643 | S115: 4.6238048 | T115: 4.5844381 | U115: 4.5430824 | V115: 4.4997573 | W115: 4.4545562 | X115: 4.4079963 | Y115: 4.3607464 | Z115: 4.3134733 | AA115: 4.2668441 | AB115: 4.2215273 | AC115: 4.178077 | AD115: 4.1365947 | AE115: 4.0970707 | AF115: 4.0594935 | AG115: 4.0238518 | AH115: 3.9901357 | AI115: 3.9583338 | AJ115: 3.9284348 | AK115: 3.9004287 | AL115: 3.8743041 | AM115: 3.85005 | AN115: 3.827656 | AO115: 3.8071021 | AP115: 3.7883202 | AQ115: 3.7712271 | AR115: 3.7557386 | AS115: 3.7417708 | AT115: 3.7292402 | AU115: 3.7180627 | AV115: 3.7081545 | AW115: 3.6994319 | AX115: 3.691811 | AY115: 3.6852079 | AZ115: 3.6795389 | BA115: 3.6747269 | BB115: 3.6707279 | BC115: 3.6675082 | BD115: 3.6650338 | BE115: 3.663271 | BF115: 3.6621859 | BG115: 3.6617447 | BH115: 3.6619134 | BI115: 3.6626584 | BJ115: 3.6639456 | BK115: 3.6657414 | BL115: 3.6680118 | BM115: 3.6902643 | BN115: 3.724459
A116: =+A111+7 -> 45442 | B116: 20240530 | C116: 5.25 | D116: 5.2 | E116: 5.1906704 | F116: 5.1519018 | G116: 5.1072776 | H116: 5.0587532 | I116: 5.0059869 | J116: 4.9506031 | K116: 4.8952542 | L116: 4.8420042 | M116: 4.7917629 | N116: 4.7446814 | O116: 4.7001742 | P116: 4.6573225 | Q116: 4.6144859 | R116: 4.5712955 | S116: 4.5277779 | T116: 4.4839581 | U116: 4.4398613 | V116: 4.395514 | W116: 4.3509874 | X116: 4.3065884 | Y116: 4.2627013 | Z116: 4.2197084 | AA116: 4.1779924 | AB116: 4.1379372 | AC116: 4.099866 | AD116: 4.0638124 | AE116: 4.0297232 | AF116: 3.9975438 | AG116: 3.9672197 | AH116: 3.9386976 | AI116: 3.9119231 | AJ116: 3.8868416 | AK116: 3.8633997 | AL116: 3.8415431 | AM116: 3.8212173 | AN116: 3.8023687 | AO116: 3.7849412 | AP116: 3.7688698 | AQ116: 3.7540873 | AR116: 3.7405262 | AS116: 3.7281186 | AT116: 3.7167975 | AU116: 3.7064952 | AV116: 3.697144 | AW116: 3.6886768 | AX116: 3.6810258 | AY116: 3.6741236 | AZ116: 3.6679027 | BA116: 3.6623037 | BB116: 3.6573026 | BC116: 3.6528854 | BD116: 3.649038 | BE116: 3.6457461 | BF116: 3.6429959 | BG116: 3.6407731 | BH116: 3.6390637 | BI116: 3.6378536 | BJ116: 3.6371286 | BK116: 3.6368747 | BL116: 3.6370778 | BM116: 3.6472413 | BN116: 3.6711414
A117: =+A112+7 -> 45443 | B117: 20240531 | C117: 5.25 | D117: 5.2 | E117: 5.1914862 | F117: 5.1532652 | G117: 5.1085288 | H117: 5.0601905 | I117: 5.0075459 | J117: 4.9512707 | K117: 4.8933999 | L117: 4.8355564 | M117: 4.7787506 | N117: 4.723548 | O117: 4.6702708 | P117: 4.6189747 | Q117: 4.5698104 | R117: 4.522524 | S117: 4.476721 | T117: 4.4320052 | U117: 4.3879804 | V117: 4.3442521 | W117: 4.3005318 | X117: 4.2570309 | Y117: 4.214107 | Z117: 4.1721163 | AA117: 4.1314151 | AB117: 4.0923609 | AC117: 4.055249 | AD117: 4.0201054 | AE117: 3.9868831 | AF117: 3.9555339 | AG117: 3.9260095 | AH117: 3.898263 | AI117: 3.872246 | AJ117: 3.8479105 | AK117: 3.8252092 | AL117: 3.804094 | AM117: 3.7845168 | AN117: 3.7664304 | AO117: 3.7497829 | AP117: 3.7345068 | AQ117: 3.7205307 | AR117: 3.7077824 | AS117: 3.6961902 | AT117: 3.6856824 | AU117: 3.676187 | AV117: 3.6676321 | AW117: 3.6599461 | AX117: 3.6530571 | AY117: 3.6468931 | AZ117: 3.6413826 | BA117: 3.6364624 | BB117: 3.632109 | BC117: 3.6283096 | BD117: 3.6250515 | BE117: 3.6223218 | BF117: 3.6201079 | BG117: 3.618397 | BH117: 3.6171762 | BI117: 3.6164329 | BJ117: 3.6161542 | BK117: 3.6163275 | BL117: 3.6169398 | BM117: 3.6291925 | BN117: 3.6544702
A118: =+A113+7 -> 45446 | B118: 20240603 | C118: 5.25 | D118: 5.2 | E118: 5.1837953 | F118: 5.1408526 | G118: 5.0905588 | H118: 5.0343781 | I118: 4.9724934 | J118: 4.907684 | K118: 4.8437055 | L118: 4.7831394 | M118: 4.7273848 | N118: 4.6764946 | O118: 4.6297622 | P118: 4.5858413 | Q118: 4.5426647 | R118: 4.4996039 | S118: 4.4564777 | T118: 4.4131032 | U118: 4.3692976 | V118: 4.3248795 | W118: 4.2797657 | X118: 4.2342904 | Y118: 4.1888995 | Z118: 4.144037 | AA118: 4.1001472 | AB118: 4.0576759 | AC118: 4.0169887 | AD118: 3.9781387 | AE118: 3.9411018 | AF118: 3.9058526 | AG118: 3.8723656 | AH118: 3.8406168 | AI118: 3.8105808 | AJ118: 3.7822323 | AK118: 3.7555469 | AL118: 3.7304995 | AM118: 3.7070647 | AN118: 3.6852182 | AO118: 3.6649289 | AP118: 3.6461432 | AQ118: 3.6288022 | AR118: 3.6128464 | AS118: 3.5982165 | AT118: 3.5848533 | AU118: 3.5726976 | AV118: 3.56169 | AW118: 3.5517713 | AX118: 3.5428823 | AY118: 3.5349636 | AZ118: 3.5279561 | BA118: 3.5218044 | BB118: 3.5164752 | BC118: 3.5119423 | BD118: 3.5081796 | BE118: 3.5051609 | BF118: 3.5028601 | BG118: 3.5012511 | BH118: 3.5003077 | BI118: 3.5000038 | BJ118: 3.5003132 | BK118: 3.5012099 | BL118: 3.5026677 | BM118: 3.521895 | BN118: 3.5557243
A119: =+A114+7 -> 45447 | B119: 20240604 | C119: 5.25 | D119: 5.2 | E119: 5.1849217 | F119: 5.1420211 | G119: 5.0904666 | H119: 5.0323024 | I119: 4.9680967 | J119: 4.9008148 | K119: 4.834459 | L119: 4.7717549 | M119: 4.7142725 | N119: 4.6620265 | O119: 4.6141403 | P119: 4.5690585 | Q119: 4.5241912 | R119: 4.4788812 | S119: 4.43307 | T119: 4.386697 | U119: 4.3397021 | V119: 4.2920264 | W119: 4.243697 | X119: 4.1951077 | Y119: 4.1467503 | Z119: 4.0991149 | AA119: 4.0526918 | AB119: 4.0079726 | AC119: 3.9653577 | AD119: 3.9248872 | AE119: 3.886513 | AF119: 3.8501852 | AG119: 3.8158542 | AH119: 3.7834717 | AI119: 3.7529879 | AJ119: 3.7243533 | AK119: 3.6975193 | AL119: 3.6724364 | AM119: 3.6490549 | AN119: 3.6273264 | AO119: 3.6071987 | AP119: 3.5886107 | AQ119: 3.5714992 | AR119: 3.5558004 | AS119: 3.5414508 | AT119: 3.528387 | AU119: 3.5165455 | AV119: 3.5058626 | AW119: 3.496275 | AX119: 3.4877191 | AY119: 3.4801313 | AZ119: 3.4734482 | BA119: 3.4676111 | BB119: 3.4625854 | BC119: 3.4583438 | BD119: 3.4548589 | BE119: 3.4521033 | BF119: 3.4500497 | BG119: 3.4486708 | BH119: 3.4479391 | BI119: 3.4478273 | BJ119: 3.4483081 | BK119: 3.4493542 | BL119: 3.450938 | BM119: 3.4704155 | BN119: 3.5036427
A120: =+A115+7 -> 45448 | B120: 20240605 | C120: 5.25 | D120: 5.2 | E120: 5.1868982 | F120: 5.1455249 | G120: 5.0955964 | H120: 5.038482 | I120: 4.9747153 | J120: 4.9076476 | K120: 4.8412077 | L120: 4.7779631 | M120: 4.7194609 | N120: 4.6660153 | O120: 4.6169117 | P120: 4.5709155 | Q120: 4.525484 | R120: 4.4798959 | S120: 4.4340134 | T120: 4.387697 | U120: 4.340807 | V120: 4.2932055 | W120: 4.2448501 | X120: 4.1961061 | Y120: 4.1474478 | Z120: 4.0993478 | AA120: 4.0522786 | AB120: 4.0067145 | AC120: 3.9630473 | AD120: 3.9213461 | AE120: 3.8816008 | AF120: 3.8437997 | AG120: 3.8079312 | AH120: 3.7739851 | AI120: 3.7419499 | AJ120: 3.711814 | AK120: 3.6835669 | AL120: 3.6571973 | AM120: 3.6326937 | AN120: 3.6100455 | AO120: 3.5892318 | AP120: 3.5701857 | AQ120: 3.5528265 | AR120: 3.5370733 | AS120: 3.522845 | AT120: 3.5100611 | AU120: 3.4986404 | AV120: 3.4885021 | AW120: 3.4795654 | AX120: 3.4717494 | AY120: 3.464973 | AZ120: 3.4591557 | BA120: 3.4542229 | BB120: 3.4501292 | BC120: 3.4468374 | BD120: 3.4443101 | BE120: 3.4425098 | BF120: 3.4413992 | BG120: 3.4409409 | BH120: 3.4410976 | BI120: 3.4418317 | BJ120: 3.4431061 | BK120: 3.4448832 | BL120: 3.4471257 | BM120: 3.4689866 | BN120: 3.5025835
A121: =+A116+7 -> 45449 | B121: 20240606 | C121: 5.25 | D121: 5.2 | E121: 5.1779003 | F121: 5.135123 | G121: 5.0821582 | H121: 5.0203309 | I121: 4.9509381 | J121: 4.8782304 | K121: 4.8069992 | L121: 4.7402836 | M121: 4.6796515 | N121: 4.6251147 | O121: 4.5756481 | P121: 4.5295635 | Q121: 4.4839205 | R121: 4.437919 | S121: 4.3914083 | T121: 4.3442362 | U121: 4.2962503 | V121: 4.2472998 | W121: 4.1973344 | X121: 4.1468254 | Y121: 4.0964127 | Z121: 4.0467343 | AA121: 3.9984284 | AB121: 3.952135 | AC121: 3.9083945 | AD121: 3.8672721 | AE121: 3.8286896 | AF121: 3.7925674 | AG121: 3.7588258 | AH121: 3.7273865 | AI121: 3.6981699 | AJ121: 3.6710965 | AK121: 3.6460878 | AL121: 3.6230642 | AM121: 3.6019464 | AN121: 3.5826557 | AO121: 3.5651108 | AP121: 3.5492216 | AQ121: 3.5348967 | AR121: 3.5220439 | AS121: 3.5105709 | AT121: 3.5003861 | AU121: 3.4913972 | AV121: 3.4835122 | AW121: 3.4766393 | AX121: 3.4706863 | AY121: 3.4655612 | AZ121: 3.461172 | BA121: 3.4574375 | BB121: 3.4543239 | BC121: 3.4518104 | BD121: 3.4498765 | BE121: 3.4485014 | BF121: 3.4476644 | BG121: 3.4473449 | BH121: 3.4475221 | BI121: 3.4481755 | BJ121: 3.4492842 | BK121: 3.4508276 | BL121: 3.4527851 | BM121: 3.4723554 | BN121: 3.5033721
