Workbook
Name _DLX1.INC: HAVERQ!$4:$10

Sheet Data >>
A3: Chains of reasoning:
A4: 1 | B4: Headline GDP appears to be stronger in Q1 since the pandemic
A5: 2 | B5: NSA data suggests that this is due to a shift in actual output more towards Q1, rather than being a function of the ONS' adjustments. But it does suggest the ONS isn't squeezing this underlying seasonality change out of the system.
A6: 3 | B6: This regime shift in output comes from XYZ (e.g. need to take a look at the expenditure components)
A7: 4 | B7: Implications - creates difficulty for policymakers. Users should take care to not overemphasise individual monthly/quarterly GDP outturns, and instead look at a broader sweep of indicators
B10: Question is whether we've now seen a long enough time series (a few years after pandemic distortions) to judge whether the shift in seasonality towards Q1 is a sustained shift (the implication being that the ONS should be adjusting for a sustained shift)
A13: ONS data link:
A14: https://www.ons.gov.uk/economy/grossdomesticproductgdp/datasets/uksecondestimateofgdpdatatables
A16: Investment has been running very hot in Q1 and very soft in Q3 and Q4 since the pandemic/energy crisis
A18: Look at what's driving those investment gains in Q1. Looks to be business investment - ICT investment, other buildings investment, and intellectual property investment
A20: Do the same but on the output side of GDP, particularly for IoS. Not sure this is possible
A26: Conclusions
A28: 1. | B28: The headline GDP data has been showing signs of residual seasonality for some time now
A30: 2. | B30: The ONS is now making downwards adjustments to the Q1 NSA data when forming its seasonally adjusted GDP series. However, these downward adjustments need to be bigger.
A32: 3. | B32: We can also see that the non-seasonally adjusted data in Q1 is now much stronger than is used to be (i.e. there has been a regime shift in underlying activity towards Q1). This suggests the ONS should be squeezing this shift in underlying activity towards Q1 out of the system
A34: 4. | B34: Where is this coming from? Our analysis suggests the change in pattern of activity towards Q1 is coming from investments, specifically business investment. Within this, there are some signs it results from ICT, building, and IP investment. No signs this is coming from deflators
A36: 5. | B36: The ONS' downward adjustments to Q1 are now increasingly geared towards lowering investment - so they have correctly identified the source of the issues, but they clearly need to go further in brining Q1 investment lower
A38: 6. | B38: The key question for the ONS is whether we've now seen a long enough period to judge whether the shift in output towards Q1 is a sustained shift. If so, further downward adjustments to Q1 would be warranted.
A40: 7. | B40: Last year's note suggests the ONS is watching this closely, given the scrutiny from us and other economists. The takeaway is that, for the timing being at least, we're likely to continue seeing stronger Q1's and weaker H2's, which clients and policymakers need to be aware of. Broader sweep of indicators is better

Sheet ONS A2 AGG
A1: Worksheet A2: National accounts aggregates [note 1, 5]
A2: This worksheet contains five tables with one blank row between them. Some cells refer to notes which can be found on the notes worksheet.
A3: Some cells in this table are empty because data was not collected for these variables at these time points.
A4: Reference year 2023 = 100
A5: Figures are in £ million
A7: Table 1: Annual
A8: Time period and dataset code row | B8: Gross national income at market prices: Current prices | C8: Net income from abroad: Current prices [note 2] | D8: Gross domestic product at market prices: Current prices | E8: less Basic price adjustment: Current prices [note 3] | F8: Gross value added at basic prices: Current prices | G8: Gross domestic product at market prices: Chained volume measure | H8: less Basic price adjustment: Chained volume measure [note 3] | I8: Gross value added at basic prices: Chained volume measure | J8: Gross domestic product at market prices: Chained volume measure: Non-seasonally adjusted | K8: Gross value added excluding oil & gas: Chained volume measure [note 4]
A9: Dataset identifier | B9: ABMZ | C9: CAES | D9: YBHA | E9: NTAP | F9: ABML | G9: ABMI | H9: NTAO | I9: ABMM | J9: BKVT | K9: KLS2
A10: 1948 | B10: 11632 | D10: 11429 | E10: 1049 | F10: 10380 | G10: 455134 | H10: 53600 | I10: 403688 | J10: 455134
A11: 1949 | B11: 12358 | D11: 12172 | E11: 1045 | F11: 11127 | G11: 470210 | H11: 53600 | I11: 418450 | J11: 470210
A12: 1950 | B12: 13099 | D12: 12742 | E12: 1160 | F12: 11582 | G12: 485925 | H12: 56267 | I12: 431768 | J12: 485925
A13: 1951 | B13: 14606 | D13: 14305 | E13: 1345 | F13: 12960 | G13: 503980 | H13: 59808 | I13: 446669 | J13: 503980
A14: 1952 | B14: 15745 | D14: 15536 | E14: 1386 | F14: 14150 | G14: 511536 | H14: 58207 | I14: 455294 | J14: 511536
A15: 1953 | B15: 16862 | D15: 16682 | E15: 1476 | F15: 15206 | G15: 539917 | H15: 60475 | I15: 481238 | J15: 539917
A16: 1954 | B16: 17796 | D16: 17598 | E16: 1493 | F16: 16105 | G16: 563461 | H16: 61909 | I16: 503188 | J16: 563461
A17: 1955 | B17: 19291 | D17: 19170 | E17: 1678 | F17: 17492 | G17: 586122 | H17: 65724 | I17: 522421 | J17: 586122
A18: 1956 | B18: 21019 | D18: 20846 | E18: 1789 | F18: 19057 | G18: 596062 | H18: 64980 | I18: 532656 | J18: 596062
A19: 1957 | B19: 22298 | D19: 22107 | E19: 1799 | F19: 20308 | G19: 607813 | H19: 64653 | I19: 544373 | J19: 607813
A20: 1958 | B20: 23450 | D20: 23223 | E20: 1858 | F20: 21365 | G20: 615967 | H20: 67312 | I20: 550345 | J20: 615967
A21: 1959 | B21: 24587 | D21: 24392 | E21: 1969 | F21: 22423 | G21: 642287 | H21: 72638 | I21: 572136 | J21: 642287
... A58: 1996 | B58: 912967 | D58: 913609 | E58: 83316 | F58: 830293 | G58: 1665005 | H58: 161059 | I58: 1503264 | J58: 1665005
A59: 1997 | B59: 957920 | C59: -619 | D59: 958539 | E59: 91510 | F59: 867029 | G59: 1746257 | H59: 180523 | I59: 1565755 | J59: 1746257 | K59: 1499012
A60: 1998 | B60: 1013611 | C60: 10807 | D60: 1002804 | E60: 98710 | F60: 904094 | G60: 1802946 | H60: 185366 | I60: 1617515 | J60: 1802946 | K60: 1548754
A61: 1999 | B61: 1043174 | C61: -3556 | D61: 1046727 | E61: 107063 | F61: 939664 | G61: 1856033 | H61: 189603 | I61: 1666306 | J61: 1856033 | K61: 1595763
A62: 2000 | B62: 1107797 | C62: 3038 | D62: 1104759 | E62: 113237 | F62: 991522 | G62: 1940007 | H62: 197096 | I62: 1742783 | J62: 1940007 | K62: 1671783
A63: 2001 | B63: 1156730 | C63: 6191 | D63: 1150542 | E63: 115018 | F63: 1035524 | G63: 1986393 | H63: 201320 | I63: 1784946 | J63: 1986393 | K63: 1715551
A64: 2002 | B64: 1208435 | C64: 13788 | D64: 1194646 | E64: 119282 | F64: 1075364 | G64: 2020341 | H64: 208136 | I64: 1812127 | J64: 2020341 | K64: 1743698
A65: 2003 | B65: 1276902 | C65: 14396 | D65: 1262502 | E65: 125442 | F65: 1137060 | G65: 2085366 | H65: 215723 | I65: 1869594 | J65: 2085366 | K65: 1801377
A66: 2004 | B66: 1338028 | C66: 10885 | D66: 1327143 | E66: 133224 | F66: 1193919 | G66: 2133872 | H66: 225408 | I66: 1908618 | J66: 2133872 | K66: 1841379
A67: 2005 | B67: 1417765 | C67: 14515 | D67: 1403249 | E67: 138843 | F67: 1264406 | G67: 2193421 | H67: 226520 | I67: 1966774 | J67: 2193421 | K67: 1901664
A68: 2006 | B68: 1472303 | C68: -5780 | D68: 1478080 | E68: 146111 | F68: 1331969 | G68: 2241453 | H68: 228207 | I68: 2012964 | J68: 2241453 | K68: 1952689
A69: 2007 | B69: 1537626 | C69: -14105 | D69: 1551729 | E69: 154479 | F69: 1397250 | G69: 2307148 | H69: 234884 | I69: 2071973 | J69: 2307148 | K69: 2013717
A70: 2008 | B70: 1581186 | C70: -21031 | D70: 1602217 | E70: 151577 | F70: 1450640 | G70: 2306008 | H70: 229852 | I70: 2075743 | J70: 2306008 | K70: 2020533
... A87: 2025 | B87: 3021037 | C87: -18824 | D87: 3039861 | E87: 297086 | F87: 2742775 | G87: 2820520 | H87: 258843 | I87: 2561677 | J87: 2820520 | K87: 2538746
A89: Table 2: Quarterly
A90: Time period and dataset code row | B90: Gross national income at market prices: Current prices | C90: Net income from abroad: Current prices [note 2] | D90: Gross domestic product at market prices: Current prices | E90: less Basic price adjustment: Current prices [note 3] | F90: Gross value added at basic prices: Current prices | G90: Gross domestic product at market prices: Chained volume measure | H90: less Basic price adjustment: Chained volume measure [note 3] | I90: Gross value added at basic prices: Chained volume measure | J90: Gross domestic product at market prices: Chained volume measure: Non-seasonally adjusted | K90: Gross value added excluding oil & gas: Chained volume measure [note 4]
A91: Dataset identifier | B91: ABMZ | C91: CAES | D91: YBHA | E91: NTAP | F91: ABML | G91: ABMI | H91: NTAO | I91: ABMM | J91: BKVT | K91: KLS2
A92: 1955 Q1 | B92: 4694 | D92: 4666 | E92: 394 | F92: 4272 | G92: 145457 | H92: 15759 | I92: 130040 | J92: 142178
A93: 1955 Q2 | B93: 4725 | D93: 4688 | E93: 417 | F93: 4271 | G93: 145551 | H93: 16295 | I93: 129812 | J93: 144515
A94: 1955 Q3 | B94: 4911 | D94: 4862 | E94: 440 | F94: 4422 | G94: 147995 | H94: 17110 | I94: 131515 | J94: 149341
A95: 1955 Q4 | B95: 4961 | D95: 4954 | E95: 427 | F95: 4527 | G95: 147119 | H95: 16560 | I95: 131054 | J95: 150088
A96: 1956 Q1 | B96: 5110 | D96: 5086 | E96: 435 | F96: 4651 | G96: 148955 | H96: 16629 | I96: 132807 | J96: 143984
A97: 1956 Q2 | B97: 5192 | D97: 5155 | E97: 447 | F97: 4708 | G97: 148835 | H97: 16021 | I97: 133157 | J97: 150105
A98: 1956 Q3 | B98: 5287 | D98: 5235 | E98: 451 | F98: 4784 | G98: 148665 | H98: 15872 | I98: 133118 | J98: 148483
A99: 1956 Q4 | B99: 5430 | D99: 5370 | E99: 456 | F99: 4914 | G99: 149607 | H99: 16458 | I99: 133574 | J99: 153490
A100: 1957 Q1 | B100: 5404 | D100: 5380 | E100: 447 | F100: 4933 | G100: 152331 | H100: 16308 | I100: 136329 | J100: 148510
A101: 1957 Q2 | B101: 5503 | D101: 5461 | E101: 453 | F101: 5008 | G101: 152285 | H101: 16053 | I101: 136512 | J101: 153733
A102: 1957 Q3 | B102: 5637 | D102: 5578 | E102: 449 | F102: 5129 | G102: 151340 | H102: 16235 | I102: 135441 | J102: 151117
A103: 1957 Q4 | B103: 5754 | D103: 5688 | E103: 450 | F103: 5238 | G103: 151857 | H103: 16057 | I103: 136091 | J103: 154453
... A259: 1996 Q4 | B259: 232693 | D259: 233368 | E259: 21213 | F259: 212155 | G259: 422639 | H259: 41414 | I259: 381090 | J259: 437703
A260: 1997 Q1 | B260: 233575 | C260: 231 | D260: 233344 | E260: 21485 | F260: 211859 | G260: 429418 | H260: 43561 | I260: 385815 | J260: 423715 | K260: 369229
A261: 1997 Q2 | B261: 237436 | C261: 186 | D261: 237250 | E261: 23089 | F261: 214161 | G261: 434199 | H261: 44648 | I261: 389540 | J261: 432165 | K261: 373183
A262: 1997 Q3 | B262: 245261 | C262: -92 | D262: 245353 | E262: 23042 | F262: 222311 | G262: 438100 | H262: 45607 | I262: 392511 | J262: 440937 | K262: 375758
A263: 1997 Q4 | B263: 241648 | C263: -944 | D263: 242592 | E263: 23894 | F263: 218698 | G263: 444540 | H263: 46707 | I263: 397889 | J263: 449440 | K263: 380842
A264: 1998 Q1 | B264: 246581 | C264: -594 | D264: 247175 | E264: 23724 | F264: 223451 | G264: 447712 | H264: 46614 | I264: 401139 | J264: 443596 | K264: 384030
A265: 1998 Q2 | B265: 250296 | C265: 1062 | D265: 249234 | E265: 24610 | F265: 224624 | G265: 450292 | H265: 46587 | I265: 403715 | J265: 442790 | K265: 386484
A266: 1998 Q3 | B266: 257117 | C266: 5625 | D266: 251492 | E266: 25347 | F266: 226145 | G266: 451005 | H266: 46198 | I266: 404770 | J266: 450046 | K266: 387621
A267: 1998 Q4 | B267: 259617 | C267: 4714 | D267: 254903 | E267: 25029 | F267: 229874 | G267: 453937 | H267: 45967 | I267: 407891 | J267: 466514 | K267: 390619
A268: 1999 Q1 | B268: 256026 | C268: -1089 | D268: 257115 | E268: 26029 | F268: 231086 | G268: 457044 | H268: 46852 | I268: 410160 | J268: 456503 | K268: 392765
A269: 1999 Q2 | B269: 257908 | C269: -930 | D269: 258836 | E269: 26161 | F269: 232675 | G269: 458710 | H269: 47204 | I269: 411490 | J269: 449667 | K269: 394064
A270: 1999 Q3 | B270: 260672 | C270: -1657 | D270: 262328 | E270: 27235 | F270: 235093 | G270: 466387 | H270: 47493 | I270: 418859 | J270: 468640 | K270: 401095
A271: 1999 Q4 | B271: 268568 | C271: 120 | D271: 268448 | E271: 27638 | F271: 240810 | G271: 473892 | H271: 48054 | I271: 425797 | J271: 481223 | K271: 407839
... A375: 2025 Q4 | B375: 766587 | C375: -2674 | D375: 769261 | E375: 75293 | F375: 693968 | G375: 706067 | H375: 64739 | I375: 641328 | J375: 716608 | K375: 635602
A377: Table 3: Percentage change, latest year on previous year
A378: Time period and dataset code row | B378: Gross national income at market prices: Current prices | C378: Gross domestic product at market prices: Current prices | D378: Gross value added at basic prices: Current prices | E378: Gross domestic product at market prices: Chained volume measure | F378: Gross value added at basic prices: Chained volume measure | G378: Gross value added excluding oil & gas: Chained volume measure [note 4]
A379: Dataset identifier | B379: KH74 | C379: IHYM | D379: KGL6 | E379: IHYP | F379: KGM7 | G379: KLH8
A380: 1949 | B380: 6.2 | C380: 6.5 | D380: 7.2 | E380: 3.3 | F380: 3.7
A381: 1950 | B381: 6 | C381: 4.7 | D381: 4.1 | E381: 3.3 | F381: 3.2
A382: 1951 | B382: 11.5 | C382: 12.3 | D382: 11.9 | E382: 3.7 | F382: 3.5
A383: 1952 | B383: 7.8 | C383: 8.6 | D383: 9.2 | E383: 1.5 | F383: 1.9
A384: 1953 | B384: 7.1 | C384: 7.4 | D384: 7.5 | E384: 5.5 | F384: 5.7
A385: 1954 | B385: 5.5 | C385: 5.5 | D385: 5.9 | E385: 4.4 | F385: 4.6
A386: 1955 | B386: 8.4 | C386: 8.9 | D386: 8.6 | E386: 4 | F386: 3.8
A387: 1956 | B387: 9 | C387: 8.7 | D387: 8.9 | E387: 1.7 | F387: 2
A388: 1957 | B388: 6.1 | C388: 6 | D388: 6.6 | E388: 2 | F388: 2.2
A389: 1958 | B389: 5.2 | C389: 5 | D389: 5.2 | E389: 1.3 | F389: 1.1
A390: 1959 | B390: 4.8 | C390: 5 | D390: 5 | E390: 4.3 | F390: 4
A391: 1960 | B391: 7.3 | C391: 7.4 | D391: 8.1 | E391: 6.3 | F391: 6.7
... A428: 1997 | B428: 4.9 | C428: 4.9 | D428: 4.4 | E428: 4.9 | F428: 4.2
A429: 1998 | B429: 5.8 | C429: 4.6 | D429: 4.3 | E429: 3.2 | F429: 3.3 | G429: 3.3
A430: 1999 | B430: 2.9 | C430: 4.4 | D430: 3.9 | E430: 2.9 | F430: 3 | G430: 3
A431: 2000 | B431: 6.2 | C431: 5.5 | D431: 5.5 | E431: 4.5 | F431: 4.6 | G431: 4.8
A432: 2001 | B432: 4.4 | C432: 4.1 | D432: 4.4 | E432: 2.4 | F432: 2.4 | G432: 2.6
A433: 2002 | B433: 4.5 | C433: 3.8 | D433: 3.8 | E433: 1.7 | F433: 1.5 | G433: 1.6
A434: 2003 | B434: 5.7 | C434: 5.7 | D434: 5.7 | E434: 3.2 | F434: 3.2 | G434: 3.3
A435: 2004 | B435: 4.8 | C435: 5.1 | D435: 5 | E435: 2.3 | F435: 2.1 | G435: 2.2
A436: 2005 | B436: 6 | C436: 5.7 | D436: 5.9 | E436: 2.8 | F436: 3 | G436: 3.3
A437: 2006 | B437: 3.8 | C437: 5.3 | D437: 5.3 | E437: 2.2 | F437: 2.3 | G437: 2.7
A438: 2007 | B438: 4.4 | C438: 5 | D438: 4.9 | E438: 2.9 | F438: 2.9 | G438: 3.1
A439: 2008 | B439: 2.8 | C439: 3.3 | D439: 3.8 | E439: 0 | F439: 0.2 | G439: 0.3
A440: 2009 | B440: -2.2 | C440: -2.7 | D440: -2.1 | E440: -4.6 | F440: -4.5 | G440: -4.5
... A456: 2025 | B456: 6.2 | C456: 5.1 | D456: 5.1 | E456: 1.4 | F456: 1.4 | G456: 1.4
A458: Table 4: Percentage change, latest quarter on previous quarter
A459: Time period and dataset code row | B459: Gross national income at market prices: Current prices | C459: Gross domestic product at market prices: Current prices | D459: Gross value added at basic prices: Current prices | E459: Gross domestic product at market prices: Chained volume measure | F459: Gross value added at basic prices: Chained volume measure | G459: Gross domestic product at market prices: Chained volume measure: Non-seasonally adjusted | H459: Gross value added excluding oil & gas: Chained volume measure [note 4]
A460: Dataset identifier | B460: KH75 | C460: IHYN | D460: KGL8 | E460: IHYQ | F460: KGM9 | G460: BFDW | H460: KLH8
A461: 1955 Q2 | B461: 0.7 | C461: 0.5 | D461: 0 | E461: 0.1 | F461: -0.2 | G461: 1.6
A462: 1955 Q3 | B462: 3.9 | C462: 3.7 | D462: 3.5 | E462: 1.7 | F462: 1.3 | G462: 3.3
A463: 1955 Q4 | B463: 1 | C463: 1.9 | D463: 2.4 | E463: -0.6 | F463: -0.4 | G463: 0.5
A464: 1956 Q1 | B464: 3 | C464: 2.7 | D464: 2.7 | E464: 1.2 | F464: 1.3 | G464: -4.1
A465: 1956 Q2 | B465: 1.6 | C465: 1.4 | D465: 1.2 | E465: -0.1 | F465: 0.3 | G465: 4.3
...

Sheet HAVERQ
B1: Seasonally adjusted >> | L1: Non seasonally adjusted >> | U1: Investment detail >> | AK1: Nominal GDP and components
AK2: SA >> | AT2: NSA >>
B3: GDP | C3: Consumer spending | D3: NPISH | E3: Government consumption | F3: Investment | G3: Inventories | H3: Acquisitions | I3: Exports | J3: Imports | K3: Statistical discrepancy | L3: GDP | M3: Consumer spending | N3: NPISH | O3: Government consumption | P3: Investment | Q3: Inventories | R3: Acquisitions | S3: Exports | T3: Imports | U3: IPNR SA | V3: GI SA | W3: IPNR NSA | X3: GI NSA | Y3: Transport SA | Z3: ICT SA | AA3: Dwellings SA | AB3: Other buildings SA | AC3: IP SA | AD3: Transport NSA | AE3: ICT NSA | AF3: Dwellings NSA | AG3: Other buildings NSA | AH3: IP NSA | AK3: GDP | AL3: Consumer spending | AM3: NPISH | AN3: Government consumption | AO3: Investment | AP3: Inventories | AQ3: Acquisitions | AR3: Exports | AS3: Imports | AT3: GDP | AU3: Consumer spending | AV3: NPISH | AW3: Government consumption | AX3: Investment | AY3: Inventories | AZ3: Acquisitions | BA3: Exports | BB3: Imports
A4: 19901 !Q | B4: ABMIQ@UK | C4: ABJRQ@UK | D4: HAYOQ@UK | E4: NMRYQ@UK | F4: NPQTQ@UK | G4: CAFUQ@UK | H4: NPJRQ@UK | I4: IKBKQ@UK | J4: IKBLQ@UK | K4: GIXSQ@UK | L4: BKVTQ@UK | M4: ABPFQ@UK | N4: ABNUQ@UK | O4: NMRUQ@UK | P4: NPQRQ@UK | Q4: ABMQQ@UK | R4: NPJPQ@UK | S4: KTMZQ@UK | T4: KTNBQ@UK | U4: NPELQ@UK | V4: DLWFQ@UK | W4: NPENQ@UK | X4: EQDNQ@UK | Y4: DLWLQ@UK | Z4: DLWOQ@UK | AA4: DFEGQ@UK | AB4: DLWTQ@UK | AC4: EQDOQ@UK | AD4: DLWJQ@UK | AE4: DLWMQ@UK | AF4: DFDVQ@UK | AG4: DLWQQ@UK | AH4: EQDTQ@UK | AK4: YBHAQ@UK | AL4: ABJQQ@UK | AM4: HAYEQ@UK | AN4: NMRPQ@UK | AO4: NPQSQ@UK | AP4: CAEXQ@UK | AQ4: NPJQQ@UK | AR4: IKBHQ@UK | AS4: IKBIQ@UK | AT4: BKTLQ@UK | AU4: ABPBQ@UK | AV4: ABNVQ@UK | AW4: NMRKQ@UK | AX4: NPQXQ@UK | AY4: ABMPQ@UK | AZ4: NPJOQ@UK | BA4: KTMWQ@UK | BB4: KTMXQ@UK
A5: .DESC | B5: UK: Real Gross Domestic Product (SA, Mil.Chn.2023.GBP) | C5: UK: Household Final Consumption Expenditure (SA, Mil.Chn.2023.GBP) | D5: UK: Nonprofit Inst Final Consumption Expenditure (SA, Mil.Chn.2023.GBP) | E5: UK: General Govt Final Consumption Expenditure (SA, Mil.Chn.2023.GBP) | F5: UK: Gross Fixed Capital Formation (SA, Mil.Chn.2023.GBP) | G5: UK: Change in Inventories/Stocks: All Industries (SA, Mil.Chn.2023.GBP) | H5: UK: Acquisitions less Disposals of Valuables (SA, Mil.Chn.2023.GBP) | I5: UK: Exports of Goods & Services (SA, Mil.Chn.2023.Pounds) | J5: UK: Imports of Goods & Services (SA, Mil.Chn.2023.Pounds) | K5: UK: Statistical Discrepancy (SA, Mil.Chn.2023.GBP) | L5: U.K.: Gross Domestic Product (NSA, Mil.Chn.2023.GBP) | M5: UK: HH Final Consumption Expenditure: National Concept (NSA, Mil.Chn.2023.GBP) | N5: U.K.: Nonprofit Inst Final Consumption Expenditure (NSA, Mil.Chn.2023.GBP) | O5: UK: General Government Final Consumption Expenditure (NSA, Mil.Chn.2023.GBP) | P5: UK: Gross Fixed Capital Formation (NSA, Mil.Chn.2023.GBP) | Q5: U.K.: Changes in Inventories (NSA, Mil.Chn.2023.GBP) | R5: UK: Acquisitions less Disposals of Valuables (NSA, Mil.Chn.2023.GBP) | S5: UK: Exports: Goods & Services (NSA, Mil.Chn.2023.Pounds) | T5: UK: Imports: Goods & Services (NSA, Mil.Chn.2023.Pounds) | U5: UK: Gross Fixed Capital Formation: Business Investment (SA, Mil.Chn.2023.GBP) | V5: UK: Gross Fixed Capital Formation: General Government (SA, Mil.Chn.2023.GBP) | W5: UK: GFCF: Total Business Investment (NSA, Mil.Chn.2023.GBP) | X5: UK: GFCF: General Government (NSA, Mil.Chn.2023.GBP) | Y5: UK: Gross Fixed Capital Formation: Transport Equipment (SA, Mil.Chn.2023.GBP) | Z5: UK: GDP: GFCF: Plant & Machinery (SA, Mil.Chained.2023.Pounds) | AA5: UK: Gross Fixed Capital Formation: Dwellings (SA, Mil.Chn.2023.GBP) | AB5: UK: GFCF: Other Buildings & Structures (SA, Mil.Chn.2023.GBP) | AC5: UK: GDP: GFCF: All Intangible Fixed Assets (SA, Mil.Chained.2023.Pounds) | AD5: U.K.: GDP: GFCF: Vehicles, Ships & Aircraft (NSA, Mil.Chained.2023.Pounds) | AE5: U.K.: GDP: GFCF: Plant & Machinery (NSA, Mil.Chained.2023.Pounds) | AF5: UK: GFCF: Asset: Dwellings (NSA, Mil.Chn.2023.GBP) | AG5: UK: GFCF: Asset: Other New Buildings & Structures (NSA, Mil.Chn.2023.GBP) | AH5: U.K.: GDP: GFCF: All Intangible Fixed Assets (NSA, Mil.Chained.2023.Pounds) | AK5: UK: Gross Domestic Product [GDP] (SA, Mil.Pounds) | AL5: UK: GDP: Household Final Consumption Expenditure (SA, Mil.Pounds) | AM5: UK: GDP: Nonprofit Institutions Final Consumption Expenditure (SA,Mil.Pounds) | AN5: UK: GDP: General Government Final Consumption Expenditure (SA, Mil.Pounds) | AO5: UK: GDP: Gross Fixed Capital Formation (SA, Mil.Pounds) | AP5: UK: GDP: Changes in Inventories and Stocks (SA, Mil.Pounds) | AQ5: UK: GDP: Acquisitions Less Disposals of Valuables (SA, Mil.Pounds) | AR5: UK: GDP: Exports of Goods and Services (SA, Mil.Pounds) | AS5: UK: GDP: Imports of Goods and Services (SA, Mil.Pounds) | AT5: UK: Gross Domestic Product [GDP] (NSA, Mil.Pounds) | AU5: UK: GDP: Household Final Consumption Expenditure (NSA, Mil.Pounds) | AV5: UK: GDP: Nonprofit Institutions Final Consumption Expenditure (NSA, Mil.Pounds) | AW5: UK: GDP: General Government Final Consumption Expenditure (NSA, Mil.Pounds) | AX5: UK: GDP: Gross Fixed Capital Formation (NSA, Mil.Pounds) | AY5: UK: GDP: Changes in Inventories and Stocks (NSA, Mil.Pounds) | AZ5: UK: GDP: Acquisitions Less Disposals of Valuables (NSA, Mil.Pounds) | BA5: UK: GDP: Exports of Goods and Services (NSA, Mil.Pounds) | BB5: UK: GDP: Imports of Goods and Services (NSA, Mil.Pounds)
A6: .T1 | B6: Q1-1955 | C6: Q1-1955 | D6: Q1-1955 | E6: Q1-1955 | F6: Q1-1955 | G6: Q1-1955 | H6: Q1-1955 | I6: Q1-1955 | J6: Q1-1955 | K6: Q1-1955 | L6: Q1-1955 | M6: Q1-1955 | N6: Q1-1955 | O6: Q1-1955 | P6: Q1-1955 | Q6: Q1-1955 | R6: Q1-1955 | S6: Q1-1955 | T6: Q1-1955 | U6: Q1-1997 | V6: Q1-1997 | W6: Q1-1997 | X6: Q1-1997 | Y6: Q1-1997 | Z6: Q1-1997 | AA6: Q1-1997 | AB6: Q1-1997 | AC6: Q1-1997 | AD6: Q1-1997 | AE6: Q1-1997 | AF6: Q1-1997 | AG6: Q1-1997 | AH6: Q1-1997 | AK6: Q1-1955 | AL6: Q1-1955 | AM6: Q1-1955 | AN6: Q1-1955 | AO6: Q1-1955 | AP6: Q1-1955 | AQ6: Q1-1986 | AR6: Q1-1955 | AS6: Q1-1955 | AT6: Q1-1955 | AU6: Q1-1955 | AV6: Q1-1955 | AW6: Q1-1955 | AX6: Q1-1955 | AY6: Q1-1955 | AZ6: Q1-1986 | BA6: Q1-1955 | BB6: Q1-1955
A7: .TN | B7: Q4-2025 | C7: Q4-2025 | D7: Q4-2025 | E7: Q4-2025 | F7: Q4-2025 | G7: Q4-2025 | H7: Q4-2025 | I7: Q4-2025 | J7: Q4-2025 | K7: Q4-2025 | L7: Q4-2025 | M7: Q4-2025 | N7: Q4-2025 | O7: Q4-2025 | P7: Q4-2025 | Q7: Q4-2025 | R7: Q4-2025 | S7: Q4-2025 | T7: Q4-2025 | U7: Q4-2025 | V7: Q4-2025 | W7: Q4-2025 | X7: Q4-2025 | Y7: Q4-2025 | Z7: Q4-2025 | AA7: Q4-2025 | AB7: Q4-2025 | AC7: Q4-2025 | AD7: Q4-2025 | AE7: Q4-2025 | AF7: Q4-2025 | AG7: Q4-2025 | AH7: Q4-2025 | AK7: Q4-2025 | AL7: Q4-2025 | AM7: Q4-2025 | AN7: Q4-2025 | AO7: Q4-2025 | AP7: Q4-2025 | AQ7: Q4-2025 | AR7: Q4-2025 | AS7: Q4-2025 | AT7: Q4-2025 | AU7: Q4-2025 | AV7: Q4-2025 | AW7: Q4-2025 | AX7: Q4-2025 | AY7: Q4-2025 | AZ7: Q4-2025 | BA7: Q4-2025 | BB7: Q4-2025
A8: .LSOURCE | B8: Office for National Statistics | C8: Office for National Statistics | D8: Office for National Statistics | E8: Office for National Statistics | F8: Office for National Statistics | G8: Office for National Statistics | H8: Office for National Statistics | I8: Office for National Statistics | J8: Office for National Statistics | K8: Office for National Statistics | L8: Office for National Statistics | M8: Office for National Statistics | N8: Office for National Statistics | O8: Office for National Statistics | P8: Office for National Statistics | Q8: Office for National Statistics | R8: Office for National Statistics | S8: Office for National Statistics | T8: Office for National Statistics | U8: Office for National Statistics | V8: Office for National Statistics | W8: Office for National Statistics | X8: Office for National Statistics | Y8: Office for National Statistics | Z8: Office for National Statistics | AA8: Office for National Statistics | AB8: Office for National Statistics | AC8: Office for National Statistics | AD8: Office for National Statistics | AE8: Office for National Statistics | AF8: Office for National Statistics | AG8: Office for National Statistics | AH8: Office for National Statistics | AK8: Office for National Statistics | AL8: Office for National Statistics | AM8: Office for National Statistics | AN8: Office for National Statistics | AO8: Office for National Statistics | AP8: Office for National Statistics | AQ8: Office for National Statistics | AR8: Office for National Statistics | AS8: Office for National Statistics | AT8: Office for National Statistics | AU8: Office for National Statistics | AV8: Office for National Statistics | AW8: Office for National Statistics | AX8: Office for National Statistics | AY8: Office for National Statistics | AZ8: Office for National Statistics | BA8: Office for National Statistics | BB8: Office for National Statistics
A9: .DTLM | B9: Mar-31-2026 07:04 | C9: Mar-31-2026 07:04 | D9: Mar-31-2026 07:04 | E9: Mar-31-2026 07:04 | F9: Mar-31-2026 07:04 | G9: Mar-31-2026 07:04 | H9: Mar-31-2026 07:04 | I9: Apr-16-2026 07:03 | J9: Apr-16-2026 07:03 | K9: Mar-31-2026 07:04 | L9: Mar-31-2026 07:46 | M9: Mar-31-2026 07:46 | N9: Mar-31-2026 07:46 | O9: Mar-31-2026 07:46 | P9: Mar-31-2026 07:46 | Q9: Mar-31-2026 07:46 | R9: Mar-31-2026 07:46 | S9: Mar-31-2026 07:46 | T9: Mar-31-2026 07:46 | U9: Mar-31-2026 10:14 | V9: Mar-31-2026 07:04 | W9: Mar-31-2026 10:14 | X9: Mar-31-2026 07:46 | Y9: Mar-31-2026 10:14 | Z9: Mar-31-2026 10:14 | AA9: Mar-31-2026 10:14 | AB9: Mar-31-2026 10:14 | AC9: Mar-31-2026 10:14 | AD9: Mar-31-2026 07:46 | AE9: Mar-31-2026 07:46 | AF9: Mar-31-2026 07:46 | AG9: Mar-31-2026 07:46 | AH9: Mar-31-2026 07:46 | AK9: Mar-31-2026 07:04 | AL9: Mar-31-2026 07:04 | AM9: Mar-31-2026 07:04 | AN9: Mar-31-2026 07:04 | AO9: Mar-31-2026 07:04 | AP9: Mar-31-2026 07:04 | AQ9: Mar-31-2026 07:04 | AR9: Mar-31-2026 07:02 | AS9: Mar-31-2026 07:02 | AT9: Mar-31-2026 07:04 | AU9: Mar-31-2026 07:46 | AV9: Mar-31-2026 07:46 | AW9: Mar-31-2026 07:46 | AX9: Mar-31-2026 07:46 | AY9: Mar-31-2026 07:46 | AZ9: Mar-31-2026 07:46 | BA9: Mar-31-2026 07:46 | BB9: Mar-31-2026 07:46
A10: .FRQ | B10: Quarterly | C10: Quarterly | D10: Quarterly | E10: Quarterly | F10: Quarterly | G10: Quarterly | H10: Quarterly | I10: Quarterly | J10: Quarterly | K10: Quarterly | L10: Quarterly | M10: Quarterly | N10: Quarterly | O10: Quarterly | P10: Quarterly | Q10: Quarterly | R10: Quarterly | S10: Quarterly | T10: Quarterly | U10: Quarterly | V10: Quarterly | W10: Quarterly | X10: Quarterly | Y10: Quarterly | Z10: Quarterly | AA10: Quarterly | AB10: Quarterly | AC10: Quarterly | AD10: Quarterly | AE10: Quarterly | AF10: Quarterly | AG10: Quarterly | AH10: Quarterly | AK10: Quarterly | AL10: Quarterly | AM10: Quarterly | AN10: Quarterly | AO10: Quarterly | AP10: Quarterly | AQ10: Quarterly | AR10: Quarterly | AS10: Quarterly | AT10: Quarterly | AU10: Quarterly | AV10: Quarterly | AW10: Quarterly | AX10: Quarterly | AY10: Quarterly | AZ10: Quarterly | BA10: Quarterly | BB10: Quarterly
A11: 19901 | B11: 379458 | C11: 215861 | D11: 6862 | E11: 77235 | F11: 73856 | G11: 348 | H11: -336 | I11: 69304 | J11: 68197 | K11: 1 | L11: 364170 | M11: 201610 | N11: 6759 | O11: 78352 | P11: 73861 | Q11: 179 | R11: -303 | S11: 66749 | T11: 66340 | U11: #N/A | V11: #N/A | W11: #N/A | X11: #N/A | Y11: #N/A | Z11: #N/A | AA11: #N/A | AB11: #N/A | AC11: #N/A | AD11: #N/A | AE11: #N/A | AF11: #N/A | AG11: #N/A | AH11: #N/A | AK11: 163591 | AL11: 98144 | AM11: 2139 | AN11: 26492 | AO11: 39711 | AP11: 413 | AQ11: 146 | AR11: 35672 | AS11: 39126 | AT11: 161953 | AU11: 94443 | AV11: 2123 | AW11: 26821 | AX11: 41923 | AY11: 148 | AZ11: 138 | BA11: 34459 | BB11: 38102
A12: 19902 | B12: 381997 | C12: 216571 | D12: 6568 | E12: 77520 | F12: 72815 | G12: 1826 | H12: 1143 | I12: 69149 | J12: 68012 | K12: 1 | L12: 372155 | M12: 208672 | N12: 6684 | O12: 76427 | P12: 72814 | Q12: 1288 | R12: 1047 | S12: 69030 | T12: 69254 | U12: #N/A | V12: #N/A | W12: #N/A | X12: #N/A | Y12: #N/A | Z12: #N/A | AA12: #N/A | AB12: #N/A | AC12: #N/A | AD12: #N/A | AE12: #N/A | AF12: #N/A | AG12: #N/A | AH12: #N/A | AK12: 167263 | AL12: 100606 | AM12: 2042 | AN12: 27463 | AO12: 39742 | AP12: 467 | AQ12: 128 | AR12: 36108 | AS12: 39293 | AT12: 162310 | AU12: 98783 | AV12: 2068 | AW12: 27283 | AX12: 37043 | AY12: 732 | AZ12: 136 | BA12: 35966 | BB12: 39701
A13: 19903 | B13: 377831 | C13: 215211 | D13: 6734 | E13: 78145 | F13: 72153 | G13: -1895 | H13: -3101 | I13: 69065 | J13: 66865 | K13: 0 | L13: 386781 | M13: 222850 | N13: 6746 | O13: 77933 | P13: 72151 | Q13: 249 | R13: -2987 | S13: 68723 | T13: 68804 | U13: #N/A | V13: #N/A | W13: #N/A | X13: #N/A | Y13: #N/A | Z13: #N/A | AA13: #N/A | AB13: #N/A | AC13: #N/A | AD13: #N/A | AE13: #N/A | AF13: #N/A | AG13: #N/A | AH13: #N/A | AK13: 170618 | AL13: 102143 | AM13: 2093 | AN13: 28389 | AO13: 39970 | AP13: -382 | AQ13: 141 | AR13: 35662 | AS13: 37398 | AT13: 170916 | AU13: 103826 | AV13: 2107 | AW13: 28183 | AX13: 39644 | AY13: -41 | AZ13: 141 | BA13: 35580 | BB13: 38524
A14: 19904 | B14: 375916 | C14: 215007 | D14: 6832 | E14: 78838 | F14: 71349 | G14: -6060 | H14: 1053 | I14: 69632 | J14: 65714 | K14: 0 | L14: 392096 | M14: 229518 | N14: 6807 | O14: 79026 | P14: 71347 | Q14: -7497 | R14: 1002 | S14: 72648 | T14: 64390 | U14: #N/A | V14: #N/A | W14: #N/A | X14: #N/A | Y14: #N/A | Z14: #N/A | AA14: #N/A | AB14: #N/A | AC14: #N/A | AD14: #N/A | AE14: #N/A | AF14: #N/A | AG14: #N/A | AH14: #N/A | AK14: 171505 | AL14: 103680 | AM14: 2122 | AN14: 28924 | AO14: 40066 | AP14: -2298 | AQ14: 143 | AR14: 36072 | AS14: 37204 | AT14: 177798 | AU14: 107521 | AV14: 2098 | AW14: 28981 | AX14: 40879 | AY14: -2639 | AZ14: 143 | BA14: 37509 | BB14: 36694
A15: 19911 | B15: 374060 | C15: 214735 | D15: 6531 | E15: 79041 | F15: 68137 | G15: -1893 | H15: -2024 | I15: 66995 | J15: 63535 | K15: 0 | L15: 357751 | M15: 200541 | N15: 6475 | O15: 79913 | P15: 68143 | Q15: -4244 | R15: -1987 | S15: 64001 | T15: 61158 | U15: #N/A | V15: #N/A | W15: #N/A | X15: #N/A | Y15: #N/A | Z15: #N/A | AA15: #N/A | AB15: #N/A | AC15: #N/A | AD15: #N/A | AE15: #N/A | AF15: #N/A | AG15: #N/A | AH15: #N/A | AK15: 173745 | AL15: 105632 | AM15: 1868 | AN15: 29365 | AO15: 38516 | AP15: -852 | AQ15: 123 | AR15: 34859 | AS15: 35766 | AT15: 170440 | AU15: 101439 | AV15: 1869 | AW15: 29510 | AX15: 40396 | AY15: -1457 | AZ15: 150 | BA15: 33002 | BB15: 34469
A16: 19912 | B16: 373608 | C16: 213315 | D16: 6485 | E16: 81070 | F16: 67111 | G16: -4769 | H16: 4205 | I16: 69215 | J16: 63812 | K16: 0 | L16: 363951 | M16: 205225 | N16: 6520 | O16: 80148 | P16: 67112 | Q16: -1711 | R16: 4101 | S16: 69165 | T16: 65393 | U16: #N/A | V16: #N/A | W16: #N/A | X16: #N/A | Y16: #N/A | Z16: #N/A | AA16: #N/A | AB16: #N/A | AC16: #N/A | AD16: #N/A | AE16: #N/A | AF16: #N/A | AG16: #N/A | AH16: #N/A | AK16: 176366 | AL16: 107349 | AM16: 1946 | AN16: 30346 | AO16: 38045 | AP16: -1569 | AQ16: 184 | AR16: 36588 | AS16: 36523 | AT16: 172098 | AU16: 105384 | AV16: 1948 | AW16: 30634 | AX16: 35322 | AY16: -808 | AZ16: 157 | BA16: 36763 | BB16: 37302
A17: 19913 | B17: 372878 | C17: 213544 | D17: 6558 | E17: 80462 | F17: 65897 | G17: -3885 | H17: -2001 | I17: 70286 | J17: 64199 | K17: 1 | L17: 381218 | M17: 221618 | N17: 6596 | O17: 80288 | P17: 65896 | Q17: -297 | R17: -1894 | S17: 70172 | T17: 66165 | U17: #N/A | V17: #N/A | W17: #N/A | X17: #N/A | Y17: #N/A | Z17: #N/A | AA17: #N/A | AB17: #N/A | AC17: #N/A | AD17: #N/A | AE17: #N/A | AF17: #N/A | AG17: #N/A | AH17: #N/A | AK17: 177818 | AL17: 108833 | AM17: 1924 | AN17: 31240 | AO17: 37007 | AP17: -1401 | AQ17: 163 | AR17: 37516 | AS17: 37464 | AT17: 179802 | AU17: 110810 | AV17: 1951 | AW17: 31110 | AX17: 36897 | AY17: -339 | AZ17: 163 | BA17: 37724 | BB17: 38514
A18: 19914 | B18: 373357 | C18: 213576 | D18: 6678 | E18: 80327 | F18: 66146 | G18: -2274 | H18: -1022 | I18: 70075 | J18: 65130 | K18: 1 | L18: 390983 | M18: 227786 | N18: 6661 | O18: 80551 | P18: 66140 | Q18: -6569 | R18: -1062 | S18: 73233 | T18: 63960 | U18: #N/A | V18: #N/A | W18: #N/A | X18: #N/A | Y18: #N/A | Z18: #N/A | AA18: #N/A | AB18: #N/A | AC18: #N/A | AD18: #N/A | AE18: #N/A | AF18: #N/A | AG18: #N/A | AH18: #N/A | AK18: 180143 | AL18: 110093 | AM18: 2044 | AN18: 31673 | AO18: 37414 | AP18: -1105 | AQ18: 169 | AR18: 37339 | AS18: 37484 | AT18: 185732 | AU18: 114274 | AV18: 2014 | AW18: 31370 | AX18: 38367 | AY18: -2323 | AZ18: 169 | BA18: 38813 | BB18: 36952
A19: 19921 | B19: 373317 | C19: 213040 | D19: 6583 | E19: 80646 | F19: 66335 | G19: -1362 | H19: -837 | I19: 70839 | J19: 66269 | K19: 1 | L19: 362126 | M19: 203115 | N19: 6486 | O19: 81269 | P19: 66348 | Q19: -2575 | R19: -841 | S19: 68493 | T19: 64588 | U19: #N/A | V19: #N/A | W19: #N/A | X19: #N/A | Y19: #N/A | Z19: #N/A | AA19: #N/A | AB19: #N/A | AC19: #N/A | AD19: #N/A | AE19: #N/A | AF19: #N/A | AG19: #N/A | AH19: #N/A | AK19: 182024 | AL19: 111080 | AM19: 1933 | AN19: 32247 | AO19: 37102 | AP19: -698 | AQ19: 178 | AR19: 37905 | AS19: 37723 | AT19: 178952 | AU19: 107064 | AV19: 1913 | AW19: 32245 | AX19: 38855 | AY19: -872 | AZ19: 172 | BA19: 36389 | BB19: 36814
A20: 19922 | B20: 372751 | C20: 215855 | D20: 6339 | E20: 80966 | F20: 65950 | G20: -3117 | H20: 223 | I20: 72581 | J20: 69297 | K20: 0 | L20: 366762 | M20: 210292 | N20: 6407 | O20: 80314 | P20: 65948 | Q20: 31 | R20: 225 | S20: 71971 | T20: 70236 | U20: #N/A | V20: #N/A | W20: #N/A | X20: #N/A | Y20: #N/A | Z20: #N/A | AA20: #N/A | AB20: #N/A | AC20: #N/A | AD20: #N/A | AE20: #N/A | AF20: #N/A | AG20: #N/A | AH20: #N/A | AK20: 182472 | AL20: 113093 | AM20: 1856 | AN20: 32598 | AO20: 36307 | AP20: -971 | AQ20: 167 | AR20: 38579 | AS20: 39157 | AT20: 177930 | AU20: 110941 | AV20: 1870 | AW20: 32632 | AX20: 33634 | AY20: -106 | AZ20: 173 | BA20: 38486 | BB20: 39700
A21: 19923 | B21: 374537 | C21: 217123 | D21: 6366 | E21: 80958 | F21: 66215 | G21: -1381 | H21: -319 | I21: 71131 | J21: 68557 | K21: 0 | L21: 380547 | M21: 224008 | N21: 6431 | O21: 80783 | P21: 66209 | Q21: 939 | R21: -320 | S21: 71413 | T21: 70670 | U21: #N/A | V21: #N/A | W21: #N/A | X21: #N/A | Y21: #N/A | Z21: #N/A | AA21: #N/A | AB21: #N/A | AC21: #N/A | AD21: #N/A | AE21: #N/A | AF21: #N/A | AG21: #N/A | AH21: #N/A | AK21: 183139 | AL21: 114392 | AM21: 1791 | AN21: 33110 | AO21: 35600 | AP21: -260 | AQ21: 165 | AR21: 37103 | AS21: 38762 | AT21: 184996 | AU21: 116536 | AV21: 1836 | AW21: 32979 | AX21: 35724 | AY21: 278 | AZ21: 165 | BA21: 37431 | BB21: 39953
A22: 19924 | B22: 377418 | C22: 217528 | D22: 6454 | E22: 81332 | F22: 64649 | G22: 327 | H22: 1245 | I22: 73975 | J22: 69367 | K22: 1 | L22: 388588 | M22: 226131 | N22: 6418 | O22: 81536 | P22: 64644 | Q22: -3928 | R22: 1248 | S22: 76649 | T22: 67996 | U22: #N/A | V22: #N/A | W22: #N/A | X22: #N/A | Y22: #N/A | Z22: #N/A | AA22: #N/A | AB22: #N/A | AC22: #N/A | AD22: #N/A | AE22: #N/A | AF22: #N/A | AG22: #N/A | AH22: #N/A | AK22: 185586 | AL22: 115536 | AM22: 1897 | AN22: 33428 | AO22: 35624 | AP22: -8 | AQ22: 156 | AR22: 40518 | AS22: 41565 | AT22: 191343 | AU22: 119560 | AV22: 1858 | AW22: 33527 | AX22: 36420 | AY22: -1237 | AZ22: 156 | BA22: 41799 | BB22: 40740
... A38: 19964 | B38: 422639 | C38: 246780 | D38: 8445 | E38: 83484 | F38: 68837 | G38: 1941 | H38: -220 | I38: 98508 | J38: 88403 | K38: 1 | L38: 437703 | M38: 256947 | N38: 8425 | O38: 83983 | P38: 68376 | Q38: 3579 | R38: -220 | S38: 100908 | T38: 88182 | U38: #N/A | V38: #N/A | W38: #N/A | X38: #N/A | Y38: #N/A | Z38: #N/A | AA38: #N/A | AB38: #N/A | AC38: #N/A | AD38: #N/A | AE38: #N/A | AF38: #N/A | AG38: #N/A | AH38: #N/A | AK38: 233368 | AL38: 146261 | AM38: 3349 | AN38: 37882 | AO38: 42260 | AP38: 1439 | AQ38: 208 | AR38: 61441 | AS38: 59472 | AT38: 242422 | AU38: 150871 | AV38: 3341 | AW38: 38082 | AX38: 43354 | AY38: 2876 | AZ38: 192 | BA38: 62477 | BB38: 58771
A39: 19971 | B39: 429418 | C39: 249328 | D39: 10272 | E39: 82772 | F39: 66734 | G39: -2841 | H39: 602 | I39: 105733 | J39: 90862 | K39: 0 | L39: 423715 | M39: 242507 | N39: 10272 | O39: 82517 | P39: 69063 | Q39: -3676 | R39: 563 | S39: 102511 | T39: 87296 | U39: 37825 | V39: 6170 | W39: 37189 | X39: 9179 | Y39: 3547 | Z39: 9079 | AA39: 20290 | AB39: 24335 | AC39: 12217 | AD39: 3890 | AE39: 9669 | AF39: 20570 | AG39: 25442 | AH39: 12184 | AK39: 233344 | AL39: 148217 | AM39: 3731 | AN39: 38420 | AO39: 40184 | AP39: 366 | AQ39: 286 | AR39: 61079 | AS39: 58939 | AT39: 232219 | AU39: 144345 | AV39: 3731 | AW39: 37943 | AX39: 42365 | AY39: 1014 | AZ39: 245 | BA39: 59332 | BB39: 56756
A40: 19972 | B40: 434199 | C40: 253090 | D40: 10160 | E40: 81353 | F40: 67734 | G40: -972 | H40: 642 | I40: 107210 | J40: 95127 | K40: 0 | L40: 432165 | M40: 250043 | N40: 10160 | O40: 82169 | P40: 65642 | Q40: 2139 | R40: 745 | S40: 107155 | T40: 95773 | U40: 38040 | V40: 6934 | W40: 37998 | X40: 5250 | Y40: 3730 | Z40: 9397 | AA40: 19619 | AB40: 25029 | AC40: 12530 | AD40: 3987 | AE40: 8583 | AF40: 19392 | AG40: 23798 | AH40: 12486 | AK40: 237250 | AL40: 151927 | AM40: 3792 | AN40: 37377 | AO40: 40498 | AP40: 3084 | AQ40: 347 | AR40: 60994 | AS40: 60769 | AT40: 235358 | AU40: 150478 | AV40: 3792 | AW40: 37834 | AX40: 39334 | AY40: 3829 | AZ40: 390 | BA40: 61062 | BB40: 61361
A41: 19973 | B41: 438100 | C41: 256735 | D41: 10263 | E41: 82427 | F41: 71812 | G41: 3796 | H41: 613 | I41: 106575 | J41: 94199 | K41: 0 | L41: 440937 | M41: 259576 | N41: 10263 | O41: 81848 | P41: 70444 | Q41: 3192 | R41: 512 | S41: 107459 | T41: 97448 | U41: 40957 | V41: 7403 | W41: 40158 | X41: 6711 | Y41: 3954 | Z41: 10301 | AA41: 20015 | AB41: 26487 | AC41: 12904 | AD41: 3884 | AE41: 9719 | AF41: 20212 | AG41: 26061 | AH41: 12885 | AK41: 245353 | AL41: 154724 | AM41: 3870 | AN41: 37964 | AO41: 43161 | AP41: 3917 | AQ41: 272 | AR41: 61133 | AS41: 59688 | AT41: 244272 | AU41: 156277 | AV41: 3870 | AW41: 37939 | AX41: 41932 | AY41: 3670 | AZ41: 256 | BA41: 61888 | BB41: 61560
A42: 19974 | B42: 444540 | C42: 258701 | D42: 10337 | E42: 84058 | F42: 73702 | G42: 3235 | H42: 590 | I42: 110005 | J42: 96661 | K42: 0 | L42: 449440 | M42: 265728 | N42: 10337 | O42: 84076 | P42: 74833 | Q42: 1563 | R42: 627 | S42: 112398 | T42: 96332 | U42: 41619 | V42: 7631 | W42: 43095 | X42: 6998 | Y42: 3838 | Z42: 10462 | AA42: 21434 | AB42: 27305 | AC42: 13228 | AD42: 3307 | AE42: 11268 | AF42: 21184 | AG42: 27856 | AH42: 13325 | AK42: 242592 | AL42: 155080 | AM42: 3920 | AN42: 39014 | AO42: 44347 | AP42: -1375 | AQ42: 303 | AR42: 62362 | AS42: 61059 | AT42: 246690 | AU42: 158848 | AV42: 3920 | AW42: 39059 | AX42: 44559 | AY42: -2521 | AZ42: 317 | BA42: 63286 | BB42: 60778
A43: 19981 | B43: 447712 | C43: 260797 | D43: 10445 | E43: 84775 | F43: 74393 | G43: 3707 | H43: 844 | I43: 110615 | J43: 98715 | K43: 0 | L43: 443596 | M43: 254184 | N43: 10445 | O43: 84655 | P43: 78694 | Q43: 1790 | R43: 789 | S43: 108241 | T43: 96135 | U43: 42028 | V43: 8473 | W43: 42952 | X43: 11854 | Y43: 4489 | Z43: 10318 | AA43: 20045 | AB43: 27821 | AC43: 13651 | AD43: 4794 | AE43: 10889 | AF43: 20331 | AG43: 30829 | AH43: 13756 | AK43: 247175 | AL43: 157183 | AM43: 3949 | AN43: 39473 | AO43: 44749 | AP43: 1658 | AQ43: 461 | AR43: 61446 | AS43: 61744 | AT43: 244068 | AU43: 152694 | AV43: 3949 | AW43: 39005 | AX43: 46813 | AY43: 1080 | AZ43: 420 | BA43: 59996 | BB43: 59889
A44: 19982 | B44: 450292 | C44: 263411 | D44: 10482 | E44: 85124 | F44: 74474 | G44: 2303 | H44: 718 | I44: 110558 | J44: 101342 | K44: 0 | L44: 442790 | M44: 260527 | N44: 10482 | O44: 85695 | P44: 70490 | Q44: 2944 | R44: 815 | S44: 110010 | T44: 101708 | U44: 42503 | V44: 7895 | W44: 40997 | X44: 5767 | Y44: 3991 | Z44: 10328 | AA44: 20520 | AB44: 27940 | AC44: 13986 | AD44: 4333 | AE44: 9514 | AF44: 20297 | AG44: 24549 | AH44: 13933 | AK44: 249234 | AL44: 159647 | AM44: 3951 | AN44: 39359 | AO44: 44776 | AP44: 2495 | AQ44: 391 | AR44: 61016 | AS44: 62401 | AT44: 246263 | AU44: 158388 | AV44: 3951 | AW44: 39814 | AX44: 43089 | AY44: 2528 | AZ44: 433 | BA44: 60874 | BB44: 62814
A45: 19983 | B45: 451005 | C45: 267649 | D45: 10328 | E45: 85950 | F45: 73749 | G45: 2199 | H45: 967 | I45: 110034 | J45: 101742 | K45: 0 | L45: 450046 | M45: 270292 | N45: 10328 | O45: 85429 | P45: 72124 | Q45: 626 | R45: 881 | S45: 110606 | T45: 104415 | U45: 41933 | V45: 7804 | W45: 41014 | X45: 7026 | Y45: 3911 | Z45: 10188 | AA45: 20052 | AB45: 27676 | AC45: 14039 | AD45: 3844 | AE45: 9605 | AF45: 20250 | AG45: 27103 | AH45: 13946 | AK45: 251492 | AL45: 163345 | AM45: 3985 | AN45: 40204 | AO45: 44339 | AP45: 1047 | AQ45: 502 | AR45: 60327 | AS45: 62257 | AT45: 251429 | AU45: 165192 | AV45: 3985 | AW45: 40187 | AX45: 43684 | AY45: 966 | AZ45: 485 | BA45: 61009 | BB45: 64079
A46: 19984 | B46: 453937 | C46: 267397 | D46: 10214 | E46: 85893 | F46: 75273 | G46: -3081 | H46: 829 | I46: 109183 | J46: 101486 | K46: 0 | L46: 466514 | M46: 274251 | N46: 10214 | O46: 85963 | P46: 76581 | Q46: -232 | R46: 873 | S46: 111533 | T46: 101027 | U46: 42520 | V46: 8151 | W46: 44021 | X46: 7675 | Y46: 4386 | Z46: 10518 | AA46: 20264 | AB46: 27687 | AC46: 14037 | AD46: 3806 | AE46: 11344 | AF46: 20004 | AG46: 28643 | AH46: 14079 | AK46: 254903 | AL46: 163595 | AM46: 4015 | AN46: 40579 | AO46: 46163 | AP46: 1475 | AQ46: 458 | AR46: 61107 | AS46: 62489 | AT46: 261044 | AU46: 167496 | AV46: 4015 | AW46: 40609 | AX46: 46441 | AY46: 2101 | AZ46: 474 | BA46: 62017 | BB46: 62109
A47: 19991 | B47: 457044 | C47: 270159 | D47: 10146 | E47: 85762 | F47: 75322 | G47: 1452 | H47: 803 | I47: 109716 | J47: 104893 | K47: 0 | L47: 456503 | M47: 263344 | N47: 10146 | O47: 85541 | P47: 77359 | Q47: 2349 | R47: 741 | S47: 107024 | T47: 102160 | U47: 43428 | V47: 7429 | W47: 42777 | X47: 10242 | Y47: 4471 | Z47: 10547 | AA47: 20149 | AB47: 27724 | AC47: 13937 | AD47: 4695 | AE47: 11128 | AF47: 20446 | AG47: 28455 | AH47: 14015 | AK47: 257115 | AL47: 165881 | AM47: 4035 | AN47: 41798 | AO47: 46564 | AP47: 2462 | AQ47: 457 | AR47: 60130 | AS47: 64212 | AT47: 255362 | AU47: 161207 | AV47: 4035 | AW47: 41339 | AX47: 48442 | AY47: 3503 | AZ47: 416 | BA47: 58708 | BB47: 62288
A48: 19992 | B48: 458710 | C48: 275407 | D48: 10538 | E48: 88720 | F48: 75306 | G48: 312 | H48: 516 | I48: 110243 | J48: 106418 | K48: 0 | L48: 449667 | M48: 272027 | N48: 10538 | O48: 89218 | P48: 71534 | Q48: -862 | R48: 600 | S48: 109814 | T48: 106508 | U48: 43043 | V48: 7559 | W48: 41082 | X48: 6048 | Y48: 3987 | Z48: 10570 | AA48: 21262 | AB48: 27772 | AC48: 13892 | AD48: 4417 | AE48: 9753 | AF48: 21049 | AG48: 24629 | AH48: 13850 | AK48: 258836 | AL48: 168797 | AM48: 4127 | AN48: 42423 | AO48: 46044 | AP48: -115 | AQ48: 276 | AR48: 61928 | AS48: 64644 | AT48: 255719 | AU48: 167296 | AV48: 4127 | AW48: 42899 | AX48: 44391 | AY48: -285 | AZ48: 317 | BA48: 61899 | BB48: 64925
A49: 19993 | B49: 466387 | C49: 278331 | D49: 10548 | E49: 89707 | F49: 76109 | G49: -251 | H49: 665 | I49: 116888 | J49: 109856 | K49: 0 | L49: 468640 | M49: 281591 | N49: 10548 | O49: 89307 | P49: 75581 | Q49: 2008 | R49: 595 | S49: 117414 | T49: 112640 | U49: 42939 | V49: 7620 | W49: 43192 | X49: 6693 | Y49: 4283 | Z49: 11283 | AA49: 21615 | AB49: 26676 | AC49: 14084 | AD49: 4183 | AE49: 10658 | AF49: 21796 | AG49: 27278 | AH49: 14001 | AK49: 262328 | AL49: 169584 | AM49: 4205 | AN49: 43319 | AO49: 47459 | AP49: 26 | AQ49: 356 | AR49: 64440 | AS49: 67061 | AT49: 263487 | AU49: 171727 | AV49: 4205 | AW49: 43313 | AX49: 46461 | AY49: 1390 | AZ49: 334 | BA49: 64996 | BB49: 68939
A50: 19994 | B50: 473892 | C50: 280651 | D50: 10704 | E50: 89800 | F50: 75564 | G50: 5435 | H50: 1052 | I50: 118826 | J50: 112125 | K50: 0 | L50: 481223 | M50: 287586 | N50: 10704 | O50: 89923 | P50: 77827 | Q50: 3453 | R50: 1100 | S50: 121421 | T50: 111984 | U50: 42381 | V50: 7508 | W50: 44739 | X50: 7132 | Y50: 4479 | Z50: 10425 | AA50: 21806 | AB50: 27091 | AC50: 14274 | AD50: 3927 | AE50: 11286 | AF50: 21542 | AG50: 28901 | AH50: 14322 | AK50: 268448 | AL50: 171557 | AM50: 4327 | AN50: 43587 | AO50: 47388 | AP50: 2487 | AQ50: 646 | AR50: 66920 | AS50: 68464 | AT50: 272159 | AU50: 175589 | AV50: 4327 | AW50: 43576 | AX50: 48161 | AY50: 252 | AZ50: 668 | BA50: 67815 | BB50: 68229
... A154: 20254 | B154: 706067 | C154: 416308 | D154: 14870 | E154: 149250 | F154: 138849 | G154: -992 | H154: 5891 | I154: 227206 | J154: 244706 | K154: -609 | L154: 716608 | M154: 425640 | N154: 14870 | O154: 149877 | P154: 140714 | Q154: -6017 | R154: 5911 | S154: 234329 | T154: 248107 | U154: 76573 | V154: 25855 | W154: 79298 | X154: 24206 | Y154: 4867 | Z154: 20288 | AA154: 27560 | AB154: 47128 | AC154: 39005 | AD154: 6063 | AE154: 20794 | AF154: 27785 | AG154: 47464 | AH154: 38607 | AK154: 769261 | AL154: 448516 | AM154: 15339 | AN154: 164036 | AO154: 145928 | AP154: -2015 | AQ154: 10281 | AR154: 233723 | AS154: 245884 | AT154: 774633 | AU154: 457895 | AV154: 15339 | AW154: 163797 | AX154: 147694 | AY154: -6495 | AZ154: 10239 | BA154: 241689 | BB154: 249595

Sheet Real calculations >>

Sheet GDP calculations
D1: Levels >> | H1: Quarterly ratios of levels >> | P1: Seven-quarter rolling window >> | W1: 2x4 MA >>
A4: Date | B4: Year | C4: Quarter | D4: GDP SA | E4: GDP NSA | F4: Ratio | H4: Year | I4: Q1 | J4: Q2 | K4: Q3 | L4: Q4 | M4: One line | P4: Q1 | Q4: Q2 | R4: Q3 | S4: Q4 | T4: One line | W4: Q1 | X4: Q2 | Y4: Q3 | Z4: Q4 | AA4: One line
A5: 1990 Q1 | B5: =LEFT(A5,4) -> 1990 | C5: =RIGHT(A5,2) -> Q1 | D5: ='ONS A2 AGG'!G232 -> 379458 | E5: ='ONS A2 AGG'!J232 -> 364170 | F5: =D5/E5 -> 1.0419804 | H5: 1990 | I5: =INDEX($F5:$F$148,MATCH(I$4,$C5:$C$148,0)) -> 1.0419804 | J5: =INDEX($F5:$F$148,MATCH(J$4,$C5:$C$148,0)) -> 1.026446 | K5: =INDEX($F5:$F$148,MATCH(K$4,$C5:$C$148,0)) -> 0.97686029 | L5: =INDEX($F5:$F$148,MATCH(L$4,$C5:$C$148,0)) -> 0.9587346 | M5: 1 | S5: =E8/AVERAGE(E5:E11) -> 1.0483362 | T5: 1 | AA5: 1
A6: 1990 Q2 | B6: =LEFT(A6,4) -> 1990 | C6: =RIGHT(A6,2) -> Q2 | D6: ='ONS A2 AGG'!G233 -> 381997 | E6: ='ONS A2 AGG'!J233 -> 372155 | F6: =D6/E6 -> 1.026446 | H6: 1991 | I6: =F9 -> 1.0455876 | J6: =F10 -> 1.0265338 | K6: =F11 -> 0.97812275 | L6: =F12 -> 0.95491876 | M6: 1 | P6: =E9/AVERAGE(E6:E12) -> 0.9468123 | Q6: =E10/AVERAGE(E7:E13) -> 0.96688724 | R6: =E11/AVERAGE(E8:E14) -> 1.0205129 | S6: =E12/AVERAGE(E9:E15) -> 1.0512968 | T6: 1 | AA6: 1
A7: 1990 Q3 | B7: =LEFT(A7,4) -> 1990 | C7: =RIGHT(A7,2) -> Q3 | D7: ='ONS A2 AGG'!G234 -> 377831 | E7: ='ONS A2 AGG'!J234 -> 386781 | F7: =D7/E7 -> 0.97686029 | H7: 1992 | I7: =INDEX($F13:$F$148,MATCH(I$4,$C13:$C$148,0)) -> 1.0309036 | J7: =INDEX($F13:$F$148,MATCH(J$4,$C13:$C$148,0)) -> 1.0163294 | K7: =INDEX($F13:$F$148,MATCH(K$4,$C13:$C$148,0)) -> 0.98420694 | L7: =INDEX($F13:$F$148,MATCH(L$4,$C13:$C$148,0)) -> 0.9712549 | M7: 1 | P7: =E13/AVERAGE(E10:E16) -> 0.96230585 | Q7: =E14/AVERAGE(E11:E17) -> 0.97310199 | R7: =E15/AVERAGE(E12:E18) -> 1.0128339 | S7: =E16/AVERAGE(E13:E19) -> 1.0340987 | T7: 1 | AA7: 1
A8: 1990 Q4 | B8: =LEFT(A8,4) -> 1990 | C8: =RIGHT(A8,2) -> Q4 | D8: ='ONS A2 AGG'!G235 -> 375916 | E8: ='ONS A2 AGG'!J235 -> 392096 | F8: =D8/E8 -> 0.9587346 | H8: 1993 | I8: =INDEX($F17:$F$148,MATCH(I$4,$C17:$C$148,0)) -> 1.0306867 | J8: =INDEX($F17:$F$148,MATCH(J$4,$C17:$C$148,0)) -> 1.0215848 | K8: =INDEX($F17:$F$148,MATCH(K$4,$C17:$C$148,0)) -> 0.98260803 | L8: =INDEX($F17:$F$148,MATCH(L$4,$C17:$C$148,0)) -> 0.96862514 | M8: 1 | P8: =E17/AVERAGE(E14:E20) -> 0.96572162 | Q8: =E18/AVERAGE(E15:E21) -> 0.97331595 | R8: =E19/AVERAGE(E16:E22) -> 1.01868 | S8: =E20/AVERAGE(E17:E23) -> 1.0342096 | T8: 1 | AA8: 1
A9: 1991 Q1 | B9: =LEFT(A9,4) -> 1991 | C9: =RIGHT(A9,2) -> Q1 | D9: ='ONS A2 AGG'!G236 -> 374060 | E9: ='ONS A2 AGG'!J236 -> 357751 | F9: =D9/E9 -> 1.0455876 | H9: 1994 | I9: =INDEX($F21:$F$148,MATCH(I$4,$C21:$C$148,0)) -> 1.0254483 | J9: =INDEX($F21:$F$148,MATCH(J$4,$C21:$C$148,0)) -> 1.0193807 | K9: =INDEX($F21:$F$148,MATCH(K$4,$C21:$C$148,0)) -> 0.98473116 | L9: =INDEX($F21:$F$148,MATCH(L$4,$C21:$C$148,0)) -> 0.97319264 | M9: 1 | P9: =E21/AVERAGE(E18:E24) -> 0.97117956 | Q9: =E22/AVERAGE(E19:E25) -> 0.97883421 | R9: =E23/AVERAGE(E20:E26) -> 1.0229956 | S9: =E24/AVERAGE(E21:E27) -> 1.0344043 | T9: 1 | AA9: 1
A10: 1991 Q2 | B10: =LEFT(A10,4) -> 1991 | C10: =RIGHT(A10,2) -> Q2 | D10: ='ONS A2 AGG'!G237 -> 373608 | E10: ='ONS A2 AGG'!J237 -> 363951 | F10: =D10/E10 -> 1.0265338 | H10: 1995 | I10: =INDEX($F25:$F$148,MATCH(I$4,$C25:$C$148,0)) -> 1.0246205 | J10: =INDEX($F25:$F$148,MATCH(J$4,$C25:$C$148,0)) -> 1.0269614 | K10: =INDEX($F25:$F$148,MATCH(K$4,$C25:$C$148,0)) -> 0.98614829 | L10: =INDEX($F25:$F$148,MATCH(L$4,$C25:$C$148,0)) -> 0.96570835 | M10: 1 | P10: =E25/AVERAGE(E22:E28) -> 0.97286844 | Q10: =E26/AVERAGE(E23:E29) -> 0.96823229 | R10: =E27/AVERAGE(E24:E30) -> 1.0204124 | S10: =E28/AVERAGE(E25:E31) -> 1.040613 | T10: 1 | AA10: 1
A11: 1991 Q3 | B11: =LEFT(A11,4) -> 1991 | C11: =RIGHT(A11,2) -> Q3 | D11: ='ONS A2 AGG'!G238 -> 372878 | E11: ='ONS A2 AGG'!J238 -> 381218 | F11: =D11/E11 -> 0.97812275 | H11: 1996 | I11: =INDEX($F29:$F$148,MATCH(I$4,$C29:$C$148,0)) -> 1.0293808 | J11: =INDEX($F29:$F$148,MATCH(J$4,$C29:$C$148,0)) -> 1.0266062 | K11: =INDEX($F29:$F$148,MATCH(K$4,$C29:$C$148,0)) -> 0.98254588 | L11: =INDEX($F29:$F$148,MATCH(L$4,$C29:$C$148,0)) -> 0.96558397 | M11: 1 | P11: =E29/AVERAGE(E26:E32) -> 0.96786511 | Q11: =E30/AVERAGE(E27:E33) -> 0.96322093 | R11: =E31/AVERAGE(E28:E34) -> 1.0089807 | S11: =E32/AVERAGE(E29:E35) -> 1.0344717 | T11: 1 | AA11: 1
A12: 1991 Q4 | B12: =LEFT(A12,4) -> 1991 | C12: =RIGHT(A12,2) -> Q4 | D12: ='ONS A2 AGG'!G239 -> 373357 | E12: ='ONS A2 AGG'!J239 -> 390983 | F12: =D12/E12 -> 0.95491876 | H12: 1997 | I12: =INDEX($F33:$F$148,MATCH(I$4,$C33:$C$148,0)) -> 1.0134595 | J12: =INDEX($F33:$F$148,MATCH(J$4,$C33:$C$148,0)) -> 1.0047065 | K12: =INDEX($F33:$F$148,MATCH(K$4,$C33:$C$148,0)) -> 0.99356597 | L12: =INDEX($F33:$F$148,MATCH(L$4,$C33:$C$148,0)) -> 0.98909754 | M12: 1 | P12: =E33/AVERAGE(E30:E36) -> 0.98505646 | Q12: =E34/AVERAGE(E31:E37) -> 0.99120965 | R12: =E35/AVERAGE(E32:E38) -> 1.0052805 | S12: =E36/AVERAGE(E33:E39) -> 1.0205635 | T12: 1 | AA12: 1
A13: 1992 Q1 | B13: =LEFT(A13,4) -> 1992 | C13: =RIGHT(A13,2) -> Q1 | D13: ='ONS A2 AGG'!G240 -> 373317 | E13: ='ONS A2 AGG'!J240 -> 362126 | F13: =D13/E13 -> 1.0309036 | H13: 1998 | I13: =INDEX($F37:$F$148,MATCH(I$4,$C37:$C$148,0)) -> 1.0092787 | J13: =INDEX($F37:$F$148,MATCH(J$4,$C37:$C$148,0)) -> 1.0169426 | K13: =INDEX($F37:$F$148,MATCH(K$4,$C37:$C$148,0)) -> 1.0021309 | L13: =INDEX($F37:$F$148,MATCH(L$4,$C37:$C$148,0)) -> 0.97304047 | M13: 1 | P13: =E37/AVERAGE(E34:E40) -> 0.9934999 | Q13: =E38/AVERAGE(E35:E41) -> 0.98403213 | R13: =E39/AVERAGE(E36:E42) -> 0.99739311 | S13: =E40/AVERAGE(E37:E43) -> 1.0276428 | T13: 1 | AA13: 1
A14: 1992 Q2 | B14: =LEFT(A14,4) -> 1992 | C14: =RIGHT(A14,2) -> Q2 | D14: ='ONS A2 AGG'!G241 -> 372751 | E14: ='ONS A2 AGG'!J241 -> 366762 | F14: =D14/E14 -> 1.0163294 | H14: 1999 | I14: =INDEX($F41:$F$148,MATCH(I$4,$C41:$C$148,0)) -> 1.0011851 | J14: =INDEX($F41:$F$148,MATCH(J$4,$C41:$C$148,0)) -> 1.0201104 | K14: =INDEX($F41:$F$148,MATCH(K$4,$C41:$C$148,0)) -> 0.99519247 | L14: =INDEX($F41:$F$148,MATCH(L$4,$C41:$C$148,0)) -> 0.9847659 | M14: 1 | P14: =E41/AVERAGE(E38:E44) -> 0.99382282 | Q14: =E42/AVERAGE(E39:E45) -> 0.96969567 | R14: =E43/AVERAGE(E40:E46) -> 1.0020166 | S14: =E44/AVERAGE(E41:E47) -> 1.0218236 | T14: 1 | AA14: 1
A15: 1992 Q3 | B15: =LEFT(A15,4) -> 1992 | C15: =RIGHT(A15,2) -> Q3 | D15: ='ONS A2 AGG'!G242 -> 374537 | E15: ='ONS A2 AGG'!J242 -> 380547 | F15: =D15/E15 -> 0.98420694 | H15: 2000 | I15: =INDEX($F45:$F$148,MATCH(I$4,$C45:$C$148,0)) -> 1.0142931 | J15: =INDEX($F45:$F$148,MATCH(J$4,$C45:$C$148,0)) -> 1.0121075 | K15: =INDEX($F45:$F$148,MATCH(K$4,$C45:$C$148,0)) -> 0.99461219 | L15: =INDEX($F45:$F$148,MATCH(L$4,$C45:$C$148,0)) -> 0.98014309 | M15: 1 | P15: =E45/AVERAGE(E42:E48) -> 0.99238757 | Q15: =E46/AVERAGE(E43:E49) -> 0.98894547 | R15: =E47/AVERAGE(E44:E50) -> 1.0075484 | S15: =E48/AVERAGE(E45:E51) -> 1.0223211 | T15: 1 | AA15: 1
A16: 1992 Q4 | B16: =LEFT(A16,4) -> 1992 | C16: =RIGHT(A16,2) -> Q4 | D16: ='ONS A2 AGG'!G243 -> 377418 | E16: ='ONS A2 AGG'!J243 -> 388588 | F16: =D16/E16 -> 0.9712549 | H16: 2001 | I16: =INDEX($F49:$F$148,MATCH(I$4,$C49:$C$148,0)) -> 1.0017251 | J16: =INDEX($F49:$F$148,MATCH(J$4,$C49:$C$148,0)) -> 1.021527 | K16: =INDEX($F49:$F$148,MATCH(K$4,$C49:$C$148,0)) -> 0.99242039 | L16: =INDEX($F49:$F$148,MATCH(L$4,$C49:$C$148,0)) -> 0.98521812 | M16: 1 | P16: =E49/AVERAGE(E46:E52) -> 0.99887632 | Q16: =E50/AVERAGE(E47:E53) -> 0.9773746 | R16: =E51/AVERAGE(E48:E54) -> 1.0097084 | S16: =E52/AVERAGE(E49:E55) -> 1.0157177 | T16: 1 | AA16: 1
A17: 1993 Q1 | B17: =LEFT(A17,4) -> 1993 | C17: =RIGHT(A17,2) -> Q1 | D17: ='ONS A2 AGG'!G244 -> 379370 | E17: ='ONS A2 AGG'!J244 -> 368075 | F17: =D17/E17 -> 1.0306867 | H17: 2002 | I17: =INDEX($F53:$F$148,MATCH(I$4,$C53:$C$148,0)) -> 1.0022816 | J17: =INDEX($F53:$F$148,MATCH(J$4,$C53:$C$148,0)) -> 1.0212721 | K17: =INDEX($F53:$F$148,MATCH(K$4,$C53:$C$148,0)) -> 0.98615566 | L17: =INDEX($F53:$F$148,MATCH(L$4,$C53:$C$148,0)) -> 0.99121625 | M17: 1 | P17: =E53/AVERAGE(E50:E56) -> 0.99532414 | Q17: =E54/AVERAGE(E51:E57) -> 0.97366257 | R17: =E55/AVERAGE(E52:E58) -> 1.0125698 | S17: =E56/AVERAGE(E53:E59) -> 1.0082405 | T17: 1 | AA17: 1
A18: 1993 Q2 | B18: =LEFT(A18,4) -> 1993 | C18: =RIGHT(A18,2) -> Q2 | D18: ='ONS A2 AGG'!G245 -> 381045 | E18: ='ONS A2 AGG'!J245 -> 372994 | F18: =D18/E18 -> 1.0215848 | H18: 2003 | I18: =INDEX($F57:$F$148,MATCH(I$4,$C57:$C$148,0)) -> 0.99789174 | J18: =INDEX($F57:$F$148,MATCH(J$4,$C57:$C$148,0)) -> 1.0220343 | K18: =INDEX($F57:$F$148,MATCH(K$4,$C57:$C$148,0)) -> 0.99429838 | L18: =INDEX($F57:$F$148,MATCH(L$4,$C57:$C$148,0)) -> 0.98675228 | M18: 1 | P18: =E57/AVERAGE(E54:E60) -> 0.99993511 | Q18: =E58/AVERAGE(E55:E61) -> 0.97631931 | R18: =E59/AVERAGE(E56:E62) -> 1.0122325 | S18: =E60/AVERAGE(E57:E63) -> 1.0196112 | T18: 1 | AA18: 1
A19: 1993 Q3 | B19: =LEFT(A19,4) -> 1993 | C19: =RIGHT(A19,2) -> Q3 | D19: ='ONS A2 AGG'!G246 -> 384524 | E19: ='ONS A2 AGG'!J246 -> 391330 | F19: =D19/E19 -> 0.98260803 | H19: 2004 | I19: =INDEX($F61:$F$148,MATCH(I$4,$C61:$C$148,0)) -> 1.0068332 | J19: =INDEX($F61:$F$148,MATCH(J$4,$C61:$C$148,0)) -> 1.0242709 | K19: =INDEX($F61:$F$148,MATCH(K$4,$C61:$C$148,0)) -> 0.9822317 | L19: =INDEX($F61:$F$148,MATCH(L$4,$C61:$C$148,0)) -> 0.9879507 | M19: 1 | P19: =E61/AVERAGE(E58:E64) -> 0.99478203 | Q19: =E62/AVERAGE(E59:E65) -> 0.97390386 | R19: =E63/AVERAGE(E60:E66) -> 1.0176956 | S19: =E64/AVERAGE(E61:E67) -> 1.0109809 | T19: 1 | AA19: 1
A20: 1993 Q4 | B20: =LEFT(A20,4) -> 1993 | C20: =RIGHT(A20,2) -> Q4 | D20: ='ONS A2 AGG'!G247 -> 387143 | E20: ='ONS A2 AGG'!J247 -> 399683 | F20: =D20/E20 -> 0.96862514 | H20: 2005 | I20: =INDEX($F65:$F$148,MATCH(I$4,$C65:$C$148,0)) -> 1.0010047 | J20: =INDEX($F65:$F$148,MATCH(J$4,$C65:$C$148,0)) -> 1.0238773 | K20: =INDEX($F65:$F$148,MATCH(K$4,$C65:$C$148,0)) -> 0.99099459 | L20: =INDEX($F65:$F$148,MATCH(L$4,$C65:$C$148,0)) -> 0.98536593 | M20: 1 | P20: =E65/AVERAGE(E62:E68) -> 0.99539608 | Q20: =E66/AVERAGE(E63:E69) -> 0.97165628 | R20: =E67/AVERAGE(E64:E70) -> 1.0122573 | S20: =E68/AVERAGE(E65:E71) -> 1.0230282 | T20: 1 | AA20: 1
A21: 1994 Q1 | B21: =LEFT(A21,4) -> 1994 | C21: =RIGHT(A21,2) -> Q1 | D21: ='ONS A2 AGG'!G248 -> 391026 | E21: ='ONS A2 AGG'!J248 -> 381322 | F21: =D21/E21 -> 1.0254483 | H21: 2006 | I21: =INDEX($F69:$F$148,MATCH(I$4,$C69:$C$148,0)) -> 1.0014924 | J21: =INDEX($F69:$F$148,MATCH(J$4,$C69:$C$148,0)) -> 1.0225351 | K21: =INDEX($F69:$F$148,MATCH(K$4,$C69:$C$148,0)) -> 0.99288815 | L21: =INDEX($F69:$F$148,MATCH(L$4,$C69:$C$148,0)) -> 0.98399327 | M21: 1 | P21: =E69/AVERAGE(E66:E72) -> 1.0020504 | Q21: =E70/AVERAGE(E67:E73) -> 0.97603992 | R21: =E71/AVERAGE(E68:E74) -> 1.0058946 | S21: =E72/AVERAGE(E69:E75) -> 1.0125731 | T21: 1 | AA21: 1
A22: 1994 Q2 | B22: =LEFT(A22,4) -> 1994 | C22: =RIGHT(A22,2) -> Q2 | D22: ='ONS A2 AGG'!G249 -> 394588 | E22: ='ONS A2 AGG'!J249 -> 387086 | F22: =D22/E22 -> 1.0193807 | H22: 2007 | I22: =INDEX($F73:$F$148,MATCH(I$4,$C73:$C$148,0)) -> 1.007342 | J22: =INDEX($F73:$F$148,MATCH(J$4,$C73:$C$148,0)) -> 1.0272762 | K22: =INDEX($F73:$F$148,MATCH(K$4,$C73:$C$148,0)) -> 0.98580326 | L22: =INDEX($F73:$F$148,MATCH(L$4,$C73:$C$148,0)) -> 0.98145409 | M22: 1 | P22: =E73/AVERAGE(E70:E76) -> 0.99042223 | Q22: =E74/AVERAGE(E71:E77) -> 0.97171386 | R22: =E75/AVERAGE(E72:E78) -> 1.0200176 | S22: =E76/AVERAGE(E73:E79) -> 1.0311307 | T22: 1 | AA22: 1
A23: 1994 Q3 | B23: =LEFT(A23,4) -> 1994 | C23: =RIGHT(A23,2) -> Q3 | D23: ='ONS A2 AGG'!G250 -> 398566 | E23: ='ONS A2 AGG'!J250 -> 404746 | F23: =D23/E23 -> 0.98473116 | H23: 2008 | I23: =INDEX($F77:$F$148,MATCH(I$4,$C77:$C$148,0)) -> 1.0065538 | J23: =INDEX($F77:$F$148,MATCH(J$4,$C77:$C$148,0)) -> 1.0182984 | K23: =INDEX($F77:$F$148,MATCH(K$4,$C77:$C$148,0)) -> 0.98974322 | L23: =INDEX($F77:$F$148,MATCH(L$4,$C77:$C$148,0)) -> 0.98534132 | M23: 1 | P23: =E77/AVERAGE(E74:E80) -> 1.0078136 | Q23: =E78/AVERAGE(E75:E81) -> 0.99385435 | R23: =E79/AVERAGE(E76:E82) -> 1.0189182 | S23: =E80/AVERAGE(E77:E83) -> 1.0118849 | T23: 1 | AA23: 1
A24: 1994 Q4 | B24: =LEFT(A24,4) -> 1994 | C24: =RIGHT(A24,2) -> Q4 | D24: ='ONS A2 AGG'!G251 -> 400279 | E24: ='ONS A2 AGG'!J251 -> 411305 | F24: =D24/E24 -> 0.97319264 | H24: 2009 | I24: =INDEX($F81:$F$148,MATCH(I$4,$C81:$C$148,0)) -> 1.0068962 | J24: =INDEX($F81:$F$148,MATCH(J$4,$C81:$C$148,0)) -> 1.0244589 | K24: =INDEX($F81:$F$148,MATCH(K$4,$C81:$C$148,0)) -> 0.98856621 | L24: =INDEX($F81:$F$148,MATCH(L$4,$C81:$C$148,0)) -> 0.98128103 | M24: 1 | P24: =E81/AVERAGE(E78:E84) -> 0.97538003 | Q24: =E82/AVERAGE(E79:E85) -> 0.96100537 | R24: =E83/AVERAGE(E80:E86) -> 1.0050401 | S24: =E84/AVERAGE(E81:E87) -> 1.0155806 | T24: 1 | AA24: 1
A25: 1995 Q1 | B25: =LEFT(A25,4) -> 1995 | C25: =RIGHT(A25,2) -> Q1 | D25: ='ONS A2 AGG'!G252 -> 402390 | E25: ='ONS A2 AGG'!J252 -> 392721 | F25: =D25/E25 -> 1.0246205 | H25: 2010 | I25: =INDEX($F85:$F$148,MATCH(I$4,$C85:$C$148,0)) -> 1.0069672 | J25: =INDEX($F85:$F$148,MATCH(J$4,$C85:$C$148,0)) -> 1.0239363 | K25: =INDEX($F85:$F$148,MATCH(K$4,$C85:$C$148,0)) -> 0.9901191 | L25: =INDEX($F85:$F$148,MATCH(L$4,$C85:$C$148,0)) -> 0.98034274 | M25: 1 | P25: =E85/AVERAGE(E82:E88) -> 0.99015883 | Q25: =E86/AVERAGE(E83:E89) -> 0.97848949 | R25: =E87/AVERAGE(E84:E90) -> 1.0179234 | S25: =E88/AVERAGE(E85:E91) -> 1.0260243 | T25: 1 | W25: =$E85/(($E83/8)+($E84/4)+($E85/4)+($E86/4)+($E87/8)) -> 0.99181266 | X25: =$E86/(($E84/8)+($E85/4)+($E86/4)+($E87/4)+($E88/8)) -> 0.97973939 | Y25: =$E87/(($E85/8)+($E86/4)+($E87/4)+($E88/4)+($E89/8)) -> 1.0136286 | Z25: =$E88/(($E86/8)+($E87/4)+($E88/4)+($E89/4)+($E90/8)) -> 1.0207454 | AA25: 1
A26: 1995 Q2 | B26: =LEFT(A26,4) -> 1995 | C26: =RIGHT(A26,2) -> Q2 | D26: ='ONS A2 AGG'!G253 -> 403259 | E26: ='ONS A2 AGG'!J253 -> 392672 | F26: =D26/E26 -> 1.0269614 | H26: 2011 | I26: =INDEX($F89:$F$148,MATCH(I$4,$C89:$C$148,0)) -> 1.0100763 | J26: =INDEX($F89:$F$148,MATCH(J$4,$C89:$C$148,0)) -> 1.0197176 | K26: =INDEX($F89:$F$148,MATCH(K$4,$C89:$C$148,0)) -> 0.99275009 | L26: =INDEX($F89:$F$148,MATCH(L$4,$C89:$C$148,0)) -> 0.97852622 | M26: 1 | P26: =E89/AVERAGE(E86:E92) -> 0.99032146 | Q26: =E90/AVERAGE(E87:E93) -> 0.9757884 | R26: =E91/AVERAGE(E88:E94) -> 1.0062612 | S26: =E92/AVERAGE(E89:E95) -> 1.0209506 | T26: 1 | W26: =$E89/(($E87/8)+($E88/4)+($E89/4)+($E90/4)+($E91/8)) -> 0.99081884 | X26: =$E90/(($E88/8)+($E89/4)+($E90/4)+($E91/4)+($E92/8)) -> 0.98018899 | Y26: =$E91/(($E89/8)+($E90/4)+($E91/4)+($E92/4)+($E93/8)) -> 1.0062755 | Z26: =$E92/(($E90/8)+($E91/4)+($E92/4)+($E93/4)+($E94/8)) -> 1.0186234 | AA26: 1
A27: 1995 Q3 | B27: =LEFT(A27,4) -> 1995 | C27: =RIGHT(A27,2) -> Q3 | D27: ='ONS A2 AGG'!G254 -> 407795 | E27: ='ONS A2 AGG'!J254 -> 413523 | F27: =D27/E27 -> 0.98614829 | H27: 2012 | I27: =INDEX($F93:$F$148,MATCH(I$4,$C93:$C$148,0)) -> 1.0089845 | J27: =INDEX($F93:$F$148,MATCH(J$4,$C93:$C$148,0)) -> 1.018873 | K27: =INDEX($F93:$F$148,MATCH(K$4,$C93:$C$148,0)) -> 0.99777373 | L27: =INDEX($F93:$F$148,MATCH(L$4,$C93:$C$148,0)) -> 0.97565153 | M27: 1 | P27: =E93/AVERAGE(E90:E96) -> 0.99164392 | Q27: =E94/AVERAGE(E91:E97) -> 0.97718472 | R27: =E95/AVERAGE(E92:E98) -> 1.0072646 | S27: =E96/AVERAGE(E93:E99) -> 1.0263475 | T27: 1 | W27: =$E93/(($E91/8)+($E92/4)+($E93/4)+($E94/4)+($E95/8)) -> 0.99382477 | X27: =$E94/(($E92/8)+($E93/4)+($E94/4)+($E95/4)+($E96/8)) -> 0.9792193 | Y27: =$E95/(($E93/8)+($E94/4)+($E95/4)+($E96/4)+($E97/8)) -> 1.0065275 | Z27: =$E96/(($E94/8)+($E95/4)+($E96/4)+($E97/4)+($E98/8)) -> 1.0238726 | AA27: 1
A28: 1995 Q4 | B28: =LEFT(A28,4) -> 1995 | C28: =RIGHT(A28,2) -> Q4 | D28: ='ONS A2 AGG'!G255 -> 409132 | E28: ='ONS A2 AGG'!J255 -> 423660 | F28: =D28/E28 -> 0.96570835 | H28: 2013 | I28: =INDEX($F97:$F$148,MATCH(I$4,$C97:$C$148,0)) -> 1.0111484 | J28: =INDEX($F97:$F$148,MATCH(J$4,$C97:$C$148,0)) -> 1.0142085 | K28: =INDEX($F97:$F$148,MATCH(K$4,$C97:$C$148,0)) -> 0.99768932 | L28: =INDEX($F97:$F$148,MATCH(L$4,$C97:$C$148,0)) -> 0.97817767 | M28: 1 | P28: =E97/AVERAGE(E94:E100) -> 0.98397374 | Q28: =E98/AVERAGE(E95:E101) -> 0.9802025 | R28: =E99/AVERAGE(E96:E102) -> 0.9999571 | S28: =E100/AVERAGE(E97:E103) -> 1.0233971 | T28: 1 | W28: =$E97/(($E95/8)+($E96/4)+($E97/4)+($E98/4)+($E99/8)) -> 0.98586029 | X28: =$E98/(($E96/8)+($E97/4)+($E98/4)+($E99/4)+($E100/8)) -> 0.9848487 | Y28: =$E99/(($E97/8)+($E98/4)+($E99/4)+($E100/4)+($E101/8)) -> 1.001935 | Z28: =$E100/(($E98/8)+($E99/4)+($E100/4)+($E101/4)+($E102/8)) -> 1.0196837 | AA28: 1
A29: 1996 Q1 | B29: =LEFT(A29,4) -> 1996 | C29: =RIGHT(A29,2) -> Q1 | D29: ='ONS A2 AGG'!G256 -> 412022 | E29: ='ONS A2 AGG'!J256 -> 400262 | F29: =D29/E29 -> 1.0293808 | H29: 2014 | I29: =INDEX($F101:$F$148,MATCH(I$4,$C101:$C$148,0)) -> 1.0062565 | J29: =INDEX($F101:$F$148,MATCH(J$4,$C101:$C$148,0)) -> 1.0085093 | K29: =INDEX($F101:$F$148,MATCH(K$4,$C101:$C$148,0)) -> 1.0025393 | L29: =INDEX($F101:$F$148,MATCH(L$4,$C101:$C$148,0)) -> 0.98338026 | M29: 1 | P29: =E101/AVERAGE(E98:E104) -> 0.99126823 | Q29: =E102/AVERAGE(E99:E105) -> 0.99115062 | R29: =E103/AVERAGE(E100:E106) -> 1.0002383 | S29: =E104/AVERAGE(E101:E107) -> 1.0231271 | T29: 1 | W29: =$E101/(($E99/8)+($E100/4)+($E101/4)+($E102/4)+($E103/8)) -> 0.99122979 | X29: =$E102/(($E100/8)+($E101/4)+($E102/4)+($E103/4)+($E104/8)) -> 0.99156084 | Y29: =$E103/(($E101/8)+($E102/4)+($E103/4)+($E104/4)+($E105/8)) -> 0.99950967 | Z29: =$E104/(($E102/8)+($E103/4)+($E104/4)+($E105/4)+($E106/8)) -> 1.020256 | AA29: 1
A30: 1996 Q2 | B30: =LEFT(A30,4) -> 1996 | C30: =RIGHT(A30,2) -> Q2 | D30: ='ONS A2 AGG'!G257 -> 413325 | E30: ='ONS A2 AGG'!J257 -> 402613 | F30: =D30/E30 -> 1.0266062 | H30: 2015 | I30: =INDEX($F105:$F$148,MATCH(I$4,$C105:$C$148,0)) -> 1.0118686 | J30: =INDEX($F105:$F$148,MATCH(J$4,$C105:$C$148,0)) -> 1.009249 | K30: =INDEX($F105:$F$148,MATCH(K$4,$C105:$C$148,0)) -> 0.9988949 | L30: =INDEX($F105:$F$148,MATCH(L$4,$C105:$C$148,0)) -> 0.98083798 | M30: 1 | P30: =E105/AVERAGE(E102:E108) -> 0.98778657 | Q30: =E106/AVERAGE(E103:E109) -> 0.9900348 | R30: =E107/AVERAGE(E104:E110) -> 0.99981424 | S30: =E108/AVERAGE(E105:E111) -> 1.022447 | T30: 1 | W30: =$E105/(($E103/8)+($E104/4)+($E105/4)+($E106/4)+($E107/8)) -> 0.98920929 | X30: =$E106/(($E104/8)+($E105/4)+($E106/4)+($E107/4)+($E108/8)) -> 0.99107819 | Y30: =$E107/(($E105/8)+($E106/4)+($E107/4)+($E108/4)+($E109/8)) -> 1.00018 | Z30: =$E108/(($E106/8)+($E107/4)+($E108/4)+($E109/4)+($E110/8)) -> 1.0192236 | AA30: 1
A31: 1996 Q3 | B31: =LEFT(A31,4) -> 1996 | C31: =RIGHT(A31,2) -> Q3 | D31: ='ONS A2 AGG'!G258 -> 417019 | E31: ='ONS A2 AGG'!J258 -> 424427 | F31: =D31/E31 -> 0.98254588 | H31: 2016 | I31: =INDEX($F109:$F$148,MATCH(I$4,$C109:$C$148,0)) -> 1.01115 | J31: =INDEX($F109:$F$148,MATCH(J$4,$C109:$C$148,0)) -> 1.0083283 | K31: =INDEX($F109:$F$148,MATCH(K$4,$C109:$C$148,0)) -> 1.0047323 | L31: =INDEX($F109:$F$148,MATCH(L$4,$C109:$C$148,0)) -> 0.97686292 | M31: 1 | P31: =E109/AVERAGE(E106:E112) -> 0.98643252 | Q31: =E110/AVERAGE(E107:E113) -> 0.99090039 | R31: =E111/AVERAGE(E108:E114) -> 0.99401357 | S31: =E112/AVERAGE(E109:E115) -> 1.0247734 | T31: 1 | W31: =$E109/(($E107/8)+($E108/4)+($E109/4)+($E110/4)+($E111/8)) -> 0.98871691 | X31: =$E110/(($E108/8)+($E109/4)+($E110/4)+($E111/4)+($E112/8)) -> 0.99323735 | Y31: =$E111/(($E109/8)+($E110/4)+($E111/4)+($E112/4)+($E113/8)) -> 0.99446585 | Z31: =$E112/(($E110/8)+($E111/4)+($E112/4)+($E113/4)+($E114/8)) -> 1.0225982 | AA31: 1
A32: 1996 Q4 | B32: =LEFT(A32,4) -> 1996 | C32: =RIGHT(A32,2) -> Q4 | D32: ='ONS A2 AGG'!G259 -> 422639 | E32: ='ONS A2 AGG'!J259 -> 437703 | F32: =D32/E32 -> 0.96558397 | H32: 2017 | I32: =INDEX($F113:$F$148,MATCH(I$4,$C113:$C$148,0)) -> 1.011936 | J32: =INDEX($F113:$F$148,MATCH(J$4,$C113:$C$148,0)) -> 1.0118512 | K32: =INDEX($F113:$F$148,MATCH(K$4,$C113:$C$148,0)) -> 1.0018753 | L32: =INDEX($F113:$F$148,MATCH(L$4,$C113:$C$148,0)) -> 0.97567149 | M32: 1 | P32: =E113/AVERAGE(E110:E116) -> 0.98641081 | Q32: =E114/AVERAGE(E111:E117) -> 0.98925182 | R32: =E115/AVERAGE(E112:E118) -> 1.0010389 | S32: =E116/AVERAGE(E113:E119) -> 1.0338793 | T32: 1 | W32: =$E113/(($E111/8)+($E112/4)+($E113/4)+($E114/4)+($E115/8)) -> 0.9892996 | X32: =$E114/(($E112/8)+($E113/4)+($E114/4)+($E115/4)+($E116/8)) -> 0.98939042 | Y32: =$E115/(($E113/8)+($E114/4)+($E115/4)+($E116/4)+($E117/8)) -> 0.99876594 | Z32: =$E116/(($E114/8)+($E115/4)+($E116/4)+($E117/4)+($E118/8)) -> 1.0280911 | AA32: 1
A33: 1997 Q1 | B33: =LEFT(A33,4) -> 1997 | C33: =RIGHT(A33,2) -> Q1 | D33: ='ONS A2 AGG'!G260 -> 429418 | E33: ='ONS A2 AGG'!J260 -> 423715 | F33: =D33/E33 -> 1.0134595 | H33: 2018 | I33: =INDEX($F117:$F$148,MATCH(I$4,$C117:$C$148,0)) -> 1.0115 | J33: =INDEX($F117:$F$148,MATCH(J$4,$C117:$C$148,0)) -> 1.0120291 | K33: =INDEX($F117:$F$148,MATCH(K$4,$C117:$C$148,0)) -> 1.0031067 | L33: =INDEX($F117:$F$148,MATCH(L$4,$C117:$C$148,0)) -> 0.97444962 | M33: 1 | P33: =E117/AVERAGE(E114:E120) -> 0.98837662 | Q33: =E118/AVERAGE(E115:E121) -> 0.98661435 | R33: =E119/AVERAGE(E116:E122) -> 0.99600605 | S33: =E120/AVERAGE(E117:E123) -> 1.0283803 | T33: 1 | W33: =$E117/(($E115/8)+($E116/4)+($E117/4)+($E118/4)+($E119/8)) -> 0.98885254 | X33: =$E118/(($E116/8)+($E117/4)+($E118/4)+($E119/4)+($E120/8)) -> 0.98786173 | Y33: =$E119/(($E117/8)+($E118/4)+($E119/4)+($E120/4)+($E121/8)) -> 0.99757572 | Z33: =$E120/(($E118/8)+($E119/4)+($E120/4)+($E121/4)+($E122/8)) -> 1.024854 | AA33: 1
A34: 1997 Q2 | B34: =LEFT(A34,4) -> 1997 | C34: =RIGHT(A34,2) -> Q2 | D34: ='ONS A2 AGG'!G261 -> 434199 | E34: ='ONS A2 AGG'!J261 -> 432165 | F34: =D34/E34 -> 1.0047065 | H34: 2019 | I34: =INDEX($F121:$F$148,MATCH(I$4,$C121:$C$148,0)) -> 1.0141039 | J34: =INDEX($F121:$F$148,MATCH(J$4,$C121:$C$148,0)) -> 1.006007 | K34: =INDEX($F121:$F$148,MATCH(K$4,$C121:$C$148,0)) -> 1.0072568 | L34: =INDEX($F121:$F$148,MATCH(L$4,$C121:$C$148,0)) -> 0.97376335 | M34: 1 | P34: =E121/AVERAGE(E118:E124) -> 0.98497051 | Q34: =E122/AVERAGE(E119:E125) -> 0.99512522 | R34: =E123/AVERAGE(E120:E126) -> 1.0297862 | S34: =E124/AVERAGE(E121:E127) -> 1.0848045 | T34: 1 | W34: =$E121/(($E119/8)+($E120/4)+($E121/4)+($E122/4)+($E123/8)) -> 0.98638277 | X34: =$E122/(($E120/8)+($E121/4)+($E122/4)+($E123/4)+($E124/8)) -> 0.99351563 | Y34: =$E123/(($E121/8)+($E122/4)+($E123/4)+($E124/4)+($E125/8)) -> 0.99703775 | Z34: =$E124/(($E122/8)+($E123/4)+($E124/4)+($E125/4)+($E126/8)) -> 1.0605432 | AA34: 1
A35: 1997 Q3 | B35: =LEFT(A35,4) -> 1997 | C35: =RIGHT(A35,2) -> Q3 | D35: ='ONS A2 AGG'!G262 -> 438100 | E35: ='ONS A2 AGG'!J262 -> 440937 | F35: =D35/E35 -> 0.99356597 | H35: 2020 | I35: =INDEX($F125:$F$148,MATCH(I$4,$C125:$C$148,0)) -> 1.0020866 | J35: =INDEX($F125:$F$148,MATCH(J$4,$C125:$C$148,0)) -> 1.0017279 | K35: =INDEX($F125:$F$148,MATCH(K$4,$C125:$C$148,0)) -> 1.0217026 | L35: =INDEX($F125:$F$148,MATCH(L$4,$C125:$C$148,0)) -> 0.97598835 | M35: 1 | P35: =E125/AVERAGE(E122:E128) -> 1.0302236 | Q35: =E126/AVERAGE(E123:E129) -> 0.83424791 | R35: =E127/AVERAGE(E124:E130) -> 0.9620426 | S35: =E128/AVERAGE(E125:E131) -> 1.0275747 | T35: 1 | W35: =$E125/(($E123/8)+($E124/4)+($E125/4)+($E126/4)+($E127/8)) -> 1.0443283 | X35: =$E126/(($E124/8)+($E125/4)+($E126/4)+($E127/4)+($E128/8)) -> 0.85769787 | Y35: =$E127/(($E125/8)+($E126/4)+($E127/4)+($E128/4)+($E129/8)) -> 1.0018611 | Z35: =$E128/(($E126/8)+($E127/4)+($E128/4)+($E129/4)+($E130/8)) -> 1.0444666 | AA35: 1
A36: 1997 Q4 | B36: =LEFT(A36,4) -> 1997 | C36: =RIGHT(A36,2) -> Q4 | D36: ='ONS A2 AGG'!G263 -> 444540 | E36: ='ONS A2 AGG'!J263 -> 449440 | F36: =D36/E36 -> 0.98909754 | H36: 2021 | I36: =INDEX($F129:$F$148,MATCH(I$4,$C129:$C$148,0)) -> 0.99424548 | J36: =INDEX($F129:$F$148,MATCH(J$4,$C129:$C$148,0)) -> 1.0218768 | K36: =INDEX($F129:$F$148,MATCH(K$4,$C129:$C$148,0)) -> 1.0093714 | L36: =INDEX($F129:$F$148,MATCH(L$4,$C129:$C$148,0)) -> 0.97591694 | M36: 1 | P36: =E129/AVERAGE(E126:E132) -> 0.98835438 | Q36: =E130/AVERAGE(E127:E133) -> 0.99266228 | R36: =E131/AVERAGE(E128:E134) -> 1.005837 | S36: =E132/AVERAGE(E129:E135) -> 1.0416957 | T36: 1 | W36: =$E130/(($E128/8)+($E129/4)+($E130/4)+($E131/4)+($E132/8)) -> 0.99389922 | X36: =$E131/(($E129/8)+($E130/4)+($E131/4)+($E132/4)+($E133/8)) -> 0.99960262 | Y36: =$E132/(($E130/8)+($E131/4)+($E132/4)+($E133/4)+($E134/8)) -> 1.0300105 | Z36: =$E133/(($E131/8)+($E132/4)+($E133/4)+($E134/4)+($E135/8)) -> 1.0007424 | AA36: 1
A37: 1998 Q1 | B37: =LEFT(A37,4) -> 1998 | C37: =RIGHT(A37,2) -> Q1 | D37: ='ONS A2 AGG'!G264 -> 447712 | E37: ='ONS A2 AGG'!J264 -> 443596 | F37: =D37/E37 -> 1.0092787 | H37: 2022 | I37: =INDEX($F133:$F$148,MATCH(I$4,$C133:$C$148,0)) -> 1.003393 | J37: =INDEX($F133:$F$148,MATCH(J$4,$C133:$C$148,0)) -> 1.0239603 | K37: =INDEX($F133:$F$148,MATCH(K$4,$C133:$C$148,0)) -> 0.99323415 | L37: =INDEX($F133:$F$148,MATCH(L$4,$C133:$C$148,0)) -> 0.98051544 | M37: 1 | P37: =E133/AVERAGE(E130:E136) -> 1.0048008 | Q37: =E134/AVERAGE(E131:E137) -> 0.98171968 | R37: =E135/AVERAGE(E132:E138) -> 1.0089165 | S37: =E136/AVERAGE(E133:E139) -> 1.0255738 | T37: 1 | W37: =$E134/(($E132/8)+($E133/4)+($E134/4)+($E135/4)+($E136/8)) -> 0.97863491 | X37: =$E135/(($E133/8)+($E134/4)+($E135/4)+($E136/4)+($E137/8)) -> 1.0077498 | Y37: =$E136/(($E134/8)+($E135/4)+($E136/4)+($E137/4)+($E138/8)) -> 1.0213181 | Z37: =$E137/(($E135/8)+($E136/4)+($E137/4)+($E138/4)+($E139/8)) -> 0.99025763 | AA37: 1
A38: 1998 Q2 | B38: =LEFT(A38,4) -> 1998 | C38: =RIGHT(A38,2) -> Q2 | D38: ='ONS A2 AGG'!G265 -> 450292 | E38: ='ONS A2 AGG'!J265 -> 442790 | F38: =D38/E38 -> 1.0169426 | H38: 2023 | I38: =INDEX($F137:$F$148,MATCH(I$4,$C137:$C$148,0)) -> 1.0106845 | J38: =INDEX($F137:$F$148,MATCH(J$4,$C137:$C$148,0)) -> 1.0136756 | K38: =INDEX($F137:$F$148,MATCH(K$4,$C137:$C$148,0)) -> 0.99962941 | L38: =INDEX($F137:$F$148,MATCH(L$4,$C137:$C$148,0)) -> 0.97673233 | M38: 1 | P38: =E137/AVERAGE(E134:E140) -> 0.99102842 | Q38: =E138/AVERAGE(E135:E141) -> 0.98408885 | R38: =E139/AVERAGE(E136:E142) -> 0.99755967 | S38: =E140/AVERAGE(E137:E143) -> 1.0186635 | T38: 1 | W38: =$E138/(($E136/8)+($E137/4)+($E138/4)+($E139/4)+($E140/8)) -> 0.9884902 | X38: =$E139/(($E137/8)+($E138/4)+($E139/4)+($E140/4)+($E141/8)) -> 0.99826198 | Y38: =$E140/(($E138/8)+($E139/4)+($E140/4)+($E141/4)+($E142/8)) -> 1.0162304 | Z38: =$E141/(($E139/8)+($E140/4)+($E141/4)+($E142/4)+($E143/8)) -> 0.99965687 | AA38: 1
A39: 1998 Q3 | B39: =LEFT(A39,4) -> 1998 | C39: =RIGHT(A39,2) -> Q3 | D39: ='ONS A2 AGG'!G266 -> 451005 | E39: ='ONS A2 AGG'!J266 -> 450046 | F39: =D39/E39 -> 1.0021309 | H39: 2024 | I39: =INDEX($F141:$F$148,MATCH(I$4,$C141:$C$148,0)) -> 0.99852008 | J39: =INDEX($F141:$F$148,MATCH(J$4,$C141:$C$148,0)) -> 1.0195074 | K39: =INDEX($F141:$F$148,MATCH(K$4,$C141:$C$148,0)) -> 0.99854965 | L39: =INDEX($F141:$F$148,MATCH(L$4,$C141:$C$148,0)) -> 0.98414182 | M39: 1 | P39: =E141/AVERAGE(E138:E144) -> 0.99821872 | Q39: =E142/AVERAGE(E139:E145) -> 0.97805732 | R39: =E143/AVERAGE(E140:E146) -> 1.0004029 | S39: =E144/AVERAGE(E141:E147) -> 1.0177465 | T39: 1 | W39: =$E142/(($E140/8)+($E141/4)+($E142/4)+($E143/4)+($E144/8)) -> 0.98188427 | X39: =$E143/(($E141/8)+($E142/4)+($E143/4)+($E144/4)+($E145/8)) -> 1.0003964 | Y39: =$E144/(($E142/8)+($E143/4)+($E144/4)+($E145/4)+($E146/8)) -> 1.0139561 | Z39: =$E145/(($E143/8)+($E144/4)+($E145/4)+($E146/4)+($E147/8)) -> 1.0077185 | AA39: 1
A40: 1998 Q4 | B40: =LEFT(A40,4) -> 1998 | C40: =RIGHT(A40,2) -> Q4 | D40: ='ONS A2 AGG'!G267 -> 453937 | E40: ='ONS A2 AGG'!J267 -> 466514 | F40: =D40/E40 -> 0.97304047 | H40: 2025 | I40: =INDEX($F145:$F$148,MATCH(I$4,$C145:$C$148,0)) -> 0.99380965 | J40: =INDEX($F145:$F$148,MATCH(J$4,$C145:$C$148,0)) -> 1.0211879 | K40: =INDEX($F145:$F$148,MATCH(K$4,$C145:$C$148,0)) -> 1.0004168 | L40: =INDEX($F145:$F$148,MATCH(L$4,$C145:$C$148,0)) -> 0.98529042 | M40: 1 | P40: =E145/AVERAGE(E142:E148) -> 1.0093227 | T40: 1 | W40: =$E146/(($E144/8)+($E145/4)+($E146/4)+($E147/4)+($E148/8)) -> 0.98031959 | AA40: 1
A41: 1999 Q1 | B41: =LEFT(A41,4) -> 1999 | C41: =RIGHT(A41,2) -> Q1 | D41: ='ONS A2 AGG'!G268 -> 457044 | E41: ='ONS A2 AGG'!J268 -> 456503 | F41: =D41/E41 -> 1.0011851
A42: 1999 Q2 | B42: =LEFT(A42,4) -> 1999 | C42: =RIGHT(A42,2) -> Q2 | D42: ='ONS A2 AGG'!G269 -> 458710 | E42: ='ONS A2 AGG'!J269 -> 449667 | F42: =D42/E42 -> 1.0201104
A43: 1999 Q3 | B43: =LEFT(A43,4) -> 1999 | C43: =RIGHT(A43,2) -> Q3 | D43: ='ONS A2 AGG'!G270 -> 466387 | E43: ='ONS A2 AGG'!J270 -> 468640 | F43: =D43/E43 -> 0.99519247
A44: 1999 Q4 | B44: =LEFT(A44,4) -> 1999 | C44: =RIGHT(A44,2) -> Q4 | D44: ='ONS A2 AGG'!G271 -> 473892 | E44: ='ONS A2 AGG'!J271 -> 481223 | F44: =D44/E44 -> 0.9847659
A45: 2000 Q1 | B45: =LEFT(A45,4) -> 2000 | C45: =RIGHT(A45,2) -> Q1 | D45: ='ONS A2 AGG'!G272 -> 480212 | E45: ='ONS A2 AGG'!J272 -> 473445 | F45: =D45/E45 -> 1.0142931
A46: 2000 Q2 | B46: =LEFT(A46,4) -> 2000 | C46: =RIGHT(A46,2) -> Q2 | D46: ='ONS A2 AGG'!G273 -> 483672 | E46: ='ONS A2 AGG'!J273 -> 477886 | F46: =D46/E46 -> 1.0121075
A47: 2000 Q3 | B47: =LEFT(A47,4) -> 2000 | C47: =RIGHT(A47,2) -> Q3 | D47: ='ONS A2 AGG'!G274 -> 486617 | E47: ='ONS A2 AGG'!J274 -> 489253 | F47: =D47/E47 -> 0.99461219
A48: 2000 Q4 | B48: =LEFT(A48,4) -> 2000 | C48: =RIGHT(A48,2) -> Q4 | D48: ='ONS A2 AGG'!G275 -> 489506 | E48: ='ONS A2 AGG'!J275 -> 499423 | F48: =D48/E48 -> 0.98014309
A49: 2001 Q1 | B49: =LEFT(A49,4) -> 2001 | C49: =RIGHT(A49,2) -> Q1 | D49: ='ONS A2 AGG'!G276 -> 493575 | E49: ='ONS A2 AGG'!J276 -> 492725 | F49: =D49/E49 -> 1.0017251
A50: 2001 Q2 | B50: =LEFT(A50,4) -> 2001 | C50: =RIGHT(A50,2) -> Q2 | D50: ='ONS A2 AGG'!G277 -> 495602 | E50: ='ONS A2 AGG'!J277 -> 485158 | F50: =D50/E50 -> 1.021527
A51: 2001 Q3 | B51: =LEFT(A51,4) -> 2001 | C51: =RIGHT(A51,2) -> Q3 | D51: ='ONS A2 AGG'!G278 -> 497938 | E51: ='ONS A2 AGG'!J278 -> 501741 | F51: =D51/E51 -> 0.99242039
A52: 2001 Q4 | B52: =LEFT(A52,4) -> 2001 | C52: =RIGHT(A52,2) -> Q4 | D52: ='ONS A2 AGG'!G279 -> 499278 | E52: ='ONS A2 AGG'!J279 -> 506769 | F52: =D52/E52 -> 0.98521812
... A68: 2005 Q4 | B68: =LEFT(A68,4) -> 2005 | C68: =RIGHT(A68,2) -> Q4 | D68: ='ONS A2 AGG'!G295 -> 556311 | E68: ='ONS A2 AGG'!J295 -> 564573 | F68: =D68/E68 -> 0.98536593
A69: 2006 Q1 | B69: =LEFT(A69,4) -> 2006 | C69: =RIGHT(A69,2) -> Q1 | D69: ='ONS A2 AGG'!G296 -> 558314 | E69: ='ONS A2 AGG'!J296 -> 557482 | F69: =D69/E69 -> 1.0014924 | I69: 1. | J69: The ONS is now making downwards adjustments to the Q1 NSA data when forming its seasonally adjusted GDP series
A70: 2006 Q2 | B70: =LEFT(A70,4) -> 2006 | C70: =RIGHT(A70,2) -> Q2 | D70: ='ONS A2 AGG'!G297 -> 559795 | E70: ='ONS A2 AGG'!J297 -> 547458 | F70: =D70/E70 -> 1.0225351
A71: 2006 Q3 | B71: =LEFT(A71,4) -> 2006 | C71: =RIGHT(A71,2) -> Q3 | D71: ='ONS A2 AGG'!G298 -> 560675 | E71: ='ONS A2 AGG'!J298 -> 564691 | F71: =D71/E71 -> 0.99288815 | I71: 2. | J71: We can also see that the non-seasonally adjusted data in Q1 is now much stronger than is used to be. In other words, there has been a clear regime shift in underlying activity towards Q1
A72: 2006 Q4 | B72: =LEFT(A72,4) -> 2006 | C72: =RIGHT(A72,2) -> Q4 | D72: ='ONS A2 AGG'!G299 -> 562669 | E72: ='ONS A2 AGG'!J299 -> 571822 | F72: =D72/E72 -> 0.98399327
A73: 2007 Q1 | B73: =LEFT(A73,4) -> 2007 | C73: =RIGHT(A73,2) -> Q1 | D73: ='ONS A2 AGG'!G300 -> 568845 | E73: ='ONS A2 AGG'!J300 -> 564699 | F73: =D73/E73 -> 1.007342
A74: 2007 Q2 | B74: =LEFT(A74,4) -> 2007 | C74: =RIGHT(A74,2) -> Q2 | D74: ='ONS A2 AGG'!G301 -> 574194 | E74: ='ONS A2 AGG'!J301 -> 558948 | F74: =D74/E74 -> 1.0272762
A75: 2007 Q3 | B75: =LEFT(A75,4) -> 2007 | C75: =RIGHT(A75,2) -> Q3 | D75: ='ONS A2 AGG'!G302 -> 579605 | E75: ='ONS A2 AGG'!J302 -> 587952 | F75: =D75/E75 -> 0.98580326
A76: 2007 Q4 | B76: =LEFT(A76,4) -> 2007 | C76: =RIGHT(A76,2) -> Q4 | D76: ='ONS A2 AGG'!G303 -> 584504 | E76: ='ONS A2 AGG'!J303 -> 595549 | F76: =D76/E76 -> 0.98145409
A77: 2008 Q1 | B77: =LEFT(A77,4) -> 2008 | C77: =RIGHT(A77,2) -> Q1 | D77: ='ONS A2 AGG'!G304 -> 586690 | E77: ='ONS A2 AGG'!J304 -> 582870 | F77: =D77/E77 -> 1.0065538
A78: 2008 Q2 | B78: =LEFT(A78,4) -> 2008 | C78: =RIGHT(A78,2) -> Q2 | D78: ='ONS A2 AGG'!G305 -> 583541 | E78: ='ONS A2 AGG'!J305 -> 573055 | F78: =D78/E78 -> 1.0182984
A79: 2008 Q3 | B79: =LEFT(A79,4) -> 2008 | C79: =RIGHT(A79,2) -> Q3 | D79: ='ONS A2 AGG'!G306 -> 573961 | E79: ='ONS A2 AGG'!J306 -> 579909 | F79: =D79/E79 -> 0.98974322
A80: 2008 Q4 | B80: =LEFT(A80,4) -> 2008 | C80: =RIGHT(A80,2) -> Q4 | D80: ='ONS A2 AGG'!G307 -> 561816 | E80: ='ONS A2 AGG'!J307 -> 570174 | F80: =D80/E80 -> 0.98534132
A81: 2009 Q1 | B81: =LEFT(A81,4) -> 2009 | C81: =RIGHT(A81,2) -> Q1 | D81: ='ONS A2 AGG'!G308 -> 550451 | E81: ='ONS A2 AGG'!J308 -> 546681 | F81: =D81/E81 -> 1.0068962
A82: 2009 Q2 | B82: =LEFT(A82,4) -> 2009 | C82: =RIGHT(A82,2) -> Q2 | D82: ='ONS A2 AGG'!G309 -> 548859 | E82: ='ONS A2 AGG'!J309 -> 535755 | F82: =D82/E82 -> 1.0244589
A83: 2009 Q3 | B83: =LEFT(A83,4) -> 2009 | C83: =RIGHT(A83,2) -> Q3 | D83: ='ONS A2 AGG'!G310 -> 549540 | E83: ='ONS A2 AGG'!J310 -> 555896 | F83: =D83/E83 -> 0.98856621
... A148: 2025 Q4 | B148: =LEFT(A148,4) -> 2025 | C148: =RIGHT(A148,2) -> Q4 | D148: ='ONS A2 AGG'!G375 -> 706067 | E148: ='ONS A2 AGG'!J375 -> 716608 | F148: =D148/E148 -> 0.98529042

Sheet Component calculations
D1: Seasonally adjusted >> | U1: Non-seasonally adjusted >> | AL1: Ratios >> | BD1: Rolling windows - consumer spending >> | BL1: NPISH >> | BT1: Government consumption >> | CB1: Investments >> | CJ1: Inventories >> | CR1: Exports >> | CZ1: Imports >> | DH1: Business investment >> | DP1: Government investment >> | DX1: Transport investment >> | EF1: ICT equipment investment >> | EN1: Dwellings investment >> | EV1: Other buildings investment >> | FD1: Intellectual property investment >>
AM3: =AVERAGE(AM25:AM34) -> 1.0298179 | AN3: =AVERAGE(AN25:AN34) -> 1 | AO3: =AVERAGE(AO25:AO34) -> 0.9852982 | AP3: =AVERAGE(AP25:AP34) -> 0.97911196 | AQ3: =AVERAGE(AQ25:AQ34) -> 4.2579344 | AR3: =AVERAGE(AR25:AR34) -> 1.823068 | AS3: =AVERAGE(AS25:AS34) -> 1.0227094 | AT3: =AVERAGE(AT25:AT34) -> 1.0172456 | ... BA3: =AVERAGE(BA25:BA34) -> 0.97859795 | BE3: =AVERAGE(BE25:BE34) -> 0.96544619 | BF3: =AVERAGE(BF25:BF34) -> 0.98738442 | BG3: =AVERAGE(BG25:BG34) -> 1.0202674 | BH3: =AVERAGE(BH25:BH34) -> 1.039431 | BM3: =AVERAGE(BM25:BM34) -> 0.99156498 | BN3: =AVERAGE(BN25:BN34) -> 1.0070972 | BO3: =AVERAGE(BO25:BO34) -> 1.0146557 | BP3: =AVERAGE(BP25:BP34) -> 1.0004571 | BU3: =AVERAGE(BU25:BU34) -> 1.0180952 | BV3: =AVERAGE(BV25:BV34) -> 0.99122486 | BW3: =AVERAGE(BW25:BW34) -> 0.99031558 | BX3: =AVERAGE(BX25:BX34) -> 1.0067218 | CC3: =AVERAGE(CC25:CC34) -> 1.0315866 | CD3: =AVERAGE(CD25:CD34) -> 0.93907304 | CE3: =AVERAGE(CE25:CE34) -> 0.99483702 | CF3: =AVERAGE(CF25:CF34) -> 1.0474074 | CK3: =AVERAGE(CK25:CK34) -> -1.0820984 | CL3: =AVERAGE(CL25:CL34) -> -25.681223 | CM3: =AVERAGE(CM25:CM34) -> -1.2226416 | CN3: =AVERAGE(CN25:CN34) -> 3.8609962 | CS3: =AVERAGE(CS25:CS34) -> 0.97870783 | CT3: =AVERAGE(CT25:CT34) -> 1.0067443 | CU3: =AVERAGE(CU25:CU34) -> 0.9963911 | CV3: =AVERAGE(CV25:CV34) -> 1.0325935 | CZ3: 2010-19 | DA3: =AVERAGE(DA25:DA34) -> 0.98477206 | DB3: =AVERAGE(DB25:DB34) -> 0.99131497 | DC3: =AVERAGE(DC25:DC34) -> 1.0296615 | DD3: =AVERAGE(DD25:DD34) -> 1.0102396 | DH3: 2010-19 | DI3: =AVERAGE(DI25:DI34) -> 0.956545 | DJ3: =AVERAGE(DJ25:DJ34) -> 0.97271383 | DK3: =AVERAGE(DK25:DK34) -> 1.0012045 | DL3: =AVERAGE(DL25:DL34) -> 1.080966 | DP3: 2010-19 | DQ3: =AVERAGE(DQ25:DQ34) -> 1.4559705 | DR3: =AVERAGE(DR25:DR34) -> 0.74676709 | DS3: =AVERAGE(DS25:DS34) -> 0.90537141 | DT3: =AVERAGE(DT25:DT34) -> 0.92459677 | DX3: 2010-19 | DY3: =AVERAGE(DY25:DY34) -> 1.0250894 | DZ3: =AVERAGE(DZ25:DZ34) -> 0.95940065 | EA3: =AVERAGE(EA25:EA34) -> 0.87301823 | EB3: =AVERAGE(EB25:EB34) -> 1.1630328 | EF3: 2010-19 | EG3: =AVERAGE(EG25:EG34) -> 1.0794565 | EH3: =AVERAGE(EH25:EH34) -> 0.89774565 | EI3: =AVERAGE(EI25:EI34) -> 0.96574793 | EJ3: =AVERAGE(EJ25:EJ34) -> 1.0710461 | EN3: 2010-19 | EO3: =AVERAGE(EO25:EO34) -> 0.96129051 | EP3: =AVERAGE(EP25:EP34) -> 0.98468935 | EQ3: =AVERAGE(EQ25:EQ34) -> 1.030079 | ER3: =AVERAGE(ER25:ER34) -> 1.0417622 | EV3: 2010-19 | EW3: =AVERAGE(EW25:EW34) -> 1.0553609 | EX3: =AVERAGE(EX25:EX34) -> 0.89887368 | EY3: =AVERAGE(EY25:EY34) -> 1.0141664 | EZ3: =AVERAGE(EZ25:EZ34) -> 1.0473061 | FD3: 2010-19 | FE3: =AVERAGE(FE25:FE34) -> 1.0209403 | FF3: =AVERAGE(FF25:FF34) -> 0.97790074 | FG3: =AVERAGE(FG25:FG34) -> 0.99332701 | FH3: =AVERAGE(FH25:FH34) -> 1.0122268
A4: Date | B4: Year | C4: Quarter | D4: Consumer spending | E4: NPISH | F4: Government consumption | G4: Investment | H4: Inventories | I4: Acquisitions | J4: Exports | K4: Imports | L4: Business investment | M4: Government investment | N4: Transport SA | O4: ICT SA | P4: Dwellings SA | Q4: Other buildings SA | R4: IP SA | U4: Consumer spending | V4: NPISH | W4: Government consumption | X4: Investment | Y4: Inventories | Z4: Acquisitions | AA4: Exports | AB4: Imports | AC4: Business investment | AD4: Government investment | AE4: Transport SA | AF4: ICT SA | AG4: Dwellings SA | AH4: Other buildings SA | AI4: IP SA | AL4: Year | AM4: Consumer spending | AN4: NPISH | AO4: Government consumption | AP4: Investment | AQ4: Inventories | AR4: Acquisitions | AS4: Exports | AT4: Imports | AU4: Business investment | AV4: Government investment | AW4: Transport SA | AX4: ICT SA | AY4: Dwellings SA | AZ4: Other buildings SA | BA4: IP SA | BD4: Year | BE4: Q1 | BF4: Q2 | BG4: Q3 | BH4: Q4 | BI4: One line | BL4: Year | BM4: Q1 | BN4: Q2 | BO4: Q3 | BP4: Q4 | BQ4: One line | BT4: Year | BU4: Q1 | BV4: Q2 | BW4: Q3 | BX4: Q4 | BY4: One line | CB4: Year | CC4: Q1 | CD4: Q2 | CE4: Q3 | CF4: Q4 | CG4: One line | CJ4: Year | CK4: Q1 | CL4: Q2 | CM4: Q3 | CN4: Q4 | CO4: One line | CR4: Year | CS4: Q1 | CT4: Q2 | CU4: Q3 | CV4: Q4 | CW4: One line | CZ4: Year | DA4: Q1 | DB4: Q2 | DC4: Q3 | DD4: Q4 | DE4: One line | DH4: Year | DI4: Q1 | DJ4: Q2 | DK4: Q3 | DL4: Q4 | DM4: One line | DP4: Year | DQ4: Q1 | DR4: Q2 | DS4: Q3 | DT4: Q4 | DU4: One line | DX4: Year | DY4: Q1 | DZ4: Q2 | EA4: Q3 | EB4: Q4 | EC4: One line | EF4: Year | EG4: Q1 | EH4: Q2 | EI4: Q3 | EJ4: Q4 | EK4: One line | EN4: Year | EO4: Q1 | EP4: Q2 | EQ4: Q3 | ER4: Q4 | ES4: One line | EV4: Year | EW4: Q1 | EX4: Q2 | EY4: Q3 | EZ4: Q4 | FA4: One line | FD4: Year | FE4: Q1 | FF4: Q2 | FG4: Q3 | FH4: Q4 | FI4: One line
A5: 1990 Q1 | B5: =LEFT(A5,4) -> 1990 | C5: =RIGHT(A5,2) -> Q1 | D5: =HAVERQ!C11 -> 215861 | E5: =HAVERQ!D11 -> 6862 | F5: =HAVERQ!E11 -> 77235 | G5: =HAVERQ!F11 -> 73856 | H5: =HAVERQ!G11 -> 348 | I5: =HAVERQ!H11 -> -336 | J5: =HAVERQ!I11 -> 69304 | K5: =HAVERQ!J11 -> 68197 | L5: =HAVERQ!U11 -> #N/A | M5: =HAVERQ!V11 -> #N/A | N5: =HAVERQ!Y11 -> #N/A | O5: =HAVERQ!Z11 -> #N/A | P5: =HAVERQ!AA11 -> #N/A | Q5: =HAVERQ!AB11 -> #N/A | R5: =HAVERQ!AC11 -> #N/A | U5: =HAVERQ!M11 -> 201610 | V5: =HAVERQ!N11 -> 6759 | W5: =HAVERQ!O11 -> 78352 | X5: =HAVERQ!P11 -> 73861 | Y5: =HAVERQ!Q11 -> 179 | Z5: =HAVERQ!R11 -> -303 | AA5: =HAVERQ!S11 -> 66749 | AB5: =HAVERQ!T11 -> 66340 | AC5: =HAVERQ!W11 -> #N/A | AD5: =HAVERQ!X11 -> #N/A | AE5: =HAVERQ!AD11 -> #N/A | AF5: =HAVERQ!AE11 -> #N/A | AG5: =HAVERQ!AF11 -> #N/A | AH5: =HAVERQ!AG11 -> #N/A | AI5: =HAVERQ!AH11 -> #N/A | AL5: 1990 | AM5: =D5/U5 -> 1.070686 | AN5: =E5/V5 -> 1.0152389 | AO5: =F5/W5 -> 0.98574382 | AP5: =G5/X5 -> 0.99993231 | AQ5: =H5/Y5 -> 1.9441341 | AR5: =I5/Z5 -> 1.1089109 | AS5: =J5/AA5 -> 1.0382777 | AT5: =K5/AB5 -> 1.0279922 | ... BA5: =R5/AI5 -> #N/A | BD5: 1990 | BL5: 1990 | BT5: 1990 | CB5: 1990 | CJ5: 1990 | CR5: 1990 | CZ5: 1990 | DH5: 1990 | DP5: 1990 | DX5: 1990 | EF5: 1990 | EN5: 1990 | EV5: 1990 | FD5: 1990
A6: 1990 Q2 | B6: =LEFT(A6,4) -> 1990 | C6: =RIGHT(A6,2) -> Q2 | D6: =HAVERQ!C12 -> 216571 | E6: =HAVERQ!D12 -> 6568 | F6: =HAVERQ!E12 -> 77520 | G6: =HAVERQ!F12 -> 72815 | H6: =HAVERQ!G12 -> 1826 | I6: =HAVERQ!H12 -> 1143 | J6: =HAVERQ!I12 -> 69149 | K6: =HAVERQ!J12 -> 68012 | L6: =HAVERQ!U12 -> #N/A | M6: =HAVERQ!V12 -> #N/A | N6: =HAVERQ!Y12 -> #N/A | O6: =HAVERQ!Z12 -> #N/A | P6: =HAVERQ!AA12 -> #N/A | Q6: =HAVERQ!AB12 -> #N/A | R6: =HAVERQ!AC12 -> #N/A | U6: =HAVERQ!M12 -> 208672 | V6: =HAVERQ!N12 -> 6684 | W6: =HAVERQ!O12 -> 76427 | X6: =HAVERQ!P12 -> 72814 | Y6: =HAVERQ!Q12 -> 1288 | Z6: =HAVERQ!R12 -> 1047 | AA6: =HAVERQ!S12 -> 69030 | AB6: =HAVERQ!T12 -> 69254 | AC6: =HAVERQ!W12 -> #N/A | AD6: =HAVERQ!X12 -> #N/A | AE6: =HAVERQ!AD12 -> #N/A | AF6: =HAVERQ!AE12 -> #N/A | AG6: =HAVERQ!AF12 -> #N/A | AH6: =HAVERQ!AG12 -> #N/A | AI6: =HAVERQ!AH12 -> #N/A | AL6: 1991 | AM6: =D9/U9 -> 1.0707785 | AN6: =E9/V9 -> 1.0086486 | AO6: =F9/W9 -> 0.98908813 | AP6: =G9/X9 -> 0.99991195 | AQ6: =H9/Y9 -> 0.44604147 | AR6: =I9/Z9 -> 1.018621 | AS6: =J9/AA9 -> 1.0467805 | AT6: =K9/AB9 -> 1.0388665 | ... BA6: =R9/AI9 -> #N/A | BD6: 1991 | BE6: =U9/AVERAGE(U6:U12) -> 0.92585262 | BF6: =U10/AVERAGE(U7:U13) -> 0.95096293 | BG6: =U11/AVERAGE(U8:U14) -> 1.0355325 | BH6: =U12/AVERAGE(U9:U15) -> 1.0682822 | BI6: 1 | BL6: 1991 | BM6: =V9/AVERAGE(V6:V12) -> 0.97496182 | BN6: =V10/AVERAGE(V7:V13) -> 0.98593679 | BO6: =V11/AVERAGE(V8:V14) -> 1.0047876 | BP6: =V12/AVERAGE(V9:V15) -> 1.0230604 | BQ6: 1 | BT6: 1991 | BU6: =W9/AVERAGE(W6:W12) -> 1.00921 | BV6: =W10/AVERAGE(W7:W13) -> 1.0034125 | BW6: =W11/AVERAGE(W8:W14) -> 1.0009029 | BX6: =W12/AVERAGE(W9:W15) -> 1.0010492 | BY6: 1 | CB6: 1991 | CC6: =X9/AVERAGE(X6:X12) -> 0.98634831 | CD6: =X10/AVERAGE(X7:X13) -> 0.98458933 | CE6: =X11/AVERAGE(X8:X14) -> 0.97948332 | CF6: =X12/AVERAGE(X9:X15) -> 0.99395443 | CG6: 1 | CJ6: 1991 | CK6: =Y9/AVERAGE(Y6:Y12) -> 1.5818114 | CL6: =Y10/AVERAGE(Y7:Y13) -> 0.52892598 | CM6: =Y11/AVERAGE(Y8:Y14) -> 0.090936926 | CN6: =Y12/AVERAGE(Y9:Y15) -> 3.1875087 | CO6: 1 | CR6: 1991 | CS6: =AA9/AVERAGE(AA6:AA12) -> 0.91998513 | CT6: =AA10/AVERAGE(AA7:AA13) -> 0.99531284 | CU6: =AA11/AVERAGE(AA8:AA14) -> 1.0031061 | CV6: =AA12/AVERAGE(AA9:AA15) -> 1.0495099 | CW6: 1 | CZ6: 1991 | DA6: =AB9/AVERAGE(AB6:AB12) -> 0.93244091 | DB6: =AB10/AVERAGE(AB7:AB13) -> 1.007246 | DC6: =AB11/AVERAGE(AB8:AB14) -> 1.0159359 | DD6: =AB12/AVERAGE(AB9:AB15) -> 0.96873445 | DE6: 1 | DH6: 1991 | DI6: =AC9/AVERAGE(AC6:AC12) -> #N/A | DJ6: =AC10/AVERAGE(AC7:AC13) -> #N/A | DK6: =AC11/AVERAGE(AC8:AC14) -> #N/A | DL6: =AC12/AVERAGE(AC9:AC15) -> #N/A | DM6: 1 | DP6: 1991 | DQ6: =AD9/AVERAGE(AD6:AD12) -> #N/A | DR6: =AD10/AVERAGE(AD7:AD13) -> #N/A | DS6: =AD11/AVERAGE(AD8:AD14) -> #N/A | DT6: =AD12/AVERAGE(AD9:AD15) -> #N/A | DU6: 1 | DX6: 1991 | DY6: =AE9/AVERAGE(AE6:AE12) -> #N/A | DZ6: =AE10/AVERAGE(AE7:AE13) -> #N/A | EA6: =AE11/AVERAGE(AE8:AE14) -> #N/A | EB6: =AE12/AVERAGE(AE9:AE15) -> #N/A | EC6: 1 | EF6: 1991 | EG6: =AF9/AVERAGE(AF6:AF12) -> #N/A | EH6: =AF10/AVERAGE(AF7:AF13) -> #N/A | EI6: =AF11/AVERAGE(AF8:AF14) -> #N/A | EJ6: =AF12/AVERAGE(AF9:AF15) -> #N/A | EK6: 1 | EN6: 1991 | EO6: =AG9/AVERAGE(AG6:AG12) -> #N/A | EP6: =AG10/AVERAGE(AG7:AG13) -> #N/A | EQ6: =AG11/AVERAGE(AG8:AG14) -> #N/A | ER6: =AG12/AVERAGE(AG9:AG15) -> #N/A | ES6: 1 | EV6: 1991 | EW6: =AH9/AVERAGE(AH6:AH12) -> #N/A | EX6: =AH10/AVERAGE(AH7:AH13) -> #N/A | EY6: =AH11/AVERAGE(AH8:AH14) -> #N/A | EZ6: =AH12/AVERAGE(AH9:AH15) -> #N/A | FA6: 1 | FD6: 1991 | FE6: =AI9/AVERAGE(AI6:AI12) -> #N/A | FF6: =AI10/AVERAGE(AI7:AI13) -> #N/A | FG6: =AI11/AVERAGE(AI8:AI14) -> #N/A | FH6: =AI12/AVERAGE(AI9:AI15) -> #N/A | FI6: 1
A7: 1990 Q3 | B7: =LEFT(A7,4) -> 1990 | C7: =RIGHT(A7,2) -> Q3 | D7: =HAVERQ!C13 -> 215211 | E7: =HAVERQ!D13 -> 6734 | F7: =HAVERQ!E13 -> 78145 | G7: =HAVERQ!F13 -> 72153 | H7: =HAVERQ!G13 -> -1895 | I7: =HAVERQ!H13 -> -3101 | J7: =HAVERQ!I13 -> 69065 | K7: =HAVERQ!J13 -> 66865 | L7: =HAVERQ!U13 -> #N/A | M7: =HAVERQ!V13 -> #N/A | N7: =HAVERQ!Y13 -> #N/A | O7: =HAVERQ!Z13 -> #N/A | P7: =HAVERQ!AA13 -> #N/A | Q7: =HAVERQ!AB13 -> #N/A | R7: =HAVERQ!AC13 -> #N/A | U7: =HAVERQ!M13 -> 222850 | V7: =HAVERQ!N13 -> 6746 | W7: =HAVERQ!O13 -> 77933 | X7: =HAVERQ!P13 -> 72151 | Y7: =HAVERQ!Q13 -> 249 | Z7: =HAVERQ!R13 -> -2987 | AA7: =HAVERQ!S13 -> 68723 | AB7: =HAVERQ!T13 -> 68804 | AC7: =HAVERQ!W13 -> #N/A | AD7: =HAVERQ!X13 -> #N/A | AE7: =HAVERQ!AD13 -> #N/A | AF7: =HAVERQ!AE13 -> #N/A | AG7: =HAVERQ!AF13 -> #N/A | AH7: =HAVERQ!AG13 -> #N/A | AI7: =HAVERQ!AH13 -> #N/A | AL7: 1992 | AM7: =D13/U13 -> 1.0488639 | AN7: =E13/V13 -> 1.0149553 | AO7: =F13/W13 -> 0.9923341 | AP7: =G13/X13 -> 0.99980406 | AQ7: =H13/Y13 -> 0.52893204 | AR7: =I13/Z13 -> 0.99524376 | AS7: =J13/AA13 -> 1.0342517 | AT7: =K13/AB13 -> 1.0260265 | ... BA7: =R13/AI13 -> #N/A | BD7: 1992 | BE7: =U13/AVERAGE(U10:U16) -> 0.93652247 | BF7: =U14/AVERAGE(U11:U17) -> 0.96648651 | BG7: =U15/AVERAGE(U12:U18) -> 1.035192 | BH7: =U16/AVERAGE(U13:U19) -> 1.0429854 | BI7: 1 | BL7: 1992 | BM7: =V13/AVERAGE(V10:V16) -> 0.99742964 | BN7: =V14/AVERAGE(V11:V17) -> 0.9816578 | BO7: =V15/AVERAGE(V12:V18) -> 0.96931657 | BP7: =V16/AVERAGE(V13:V19) -> 0.95283139 | BQ7: 1 | BT7: 1992 | BU7: =W13/AVERAGE(W10:W16) -> 1.0070704 | BV7: =W14/AVERAGE(W11:W17) -> 0.99367419 | BW7: =W15/AVERAGE(W12:W18) -> 1.000807 | BX7: =W16/AVERAGE(W13:W19) -> 1.0100018 | BY7: 1 | CB7: 1992 | CC7: =X13/AVERAGE(X10:X16) -> 1.0046269 | CD7: =X14/AVERAGE(X11:X17) -> 1.000479 | CE7: =X15/AVERAGE(X12:X18) -> 1.0045278 | CF7: =X16/AVERAGE(X13:X19) -> 0.98122372 | CG7: 1 | CJ7: 1992 | CK7: =Y13/AVERAGE(Y10:Y16) -> 1.2774628 | CL7: =Y14/AVERAGE(Y11:Y17) -> -0.012564414 | CM7: =Y15/AVERAGE(Y12:Y18) -> -0.48491332 | CN7: =Y16/AVERAGE(Y13:Y19) -> 4.4738041 | CO7: 1 | CR7: 1992 | CS7: =AA13/AVERAGE(AA10:AA16) -> 0.95680468 | CT7: =AA14/AVERAGE(AA11:AA17) -> 0.99809414 | CU7: =AA15/AVERAGE(AA12:AA18) -> 0.98500496 | CV7: =AA16/AVERAGE(AA13:AA19) -> 1.0508109 | CW7: 1 | CZ7: 1992 | DA7: =AB13/AVERAGE(AB10:AB16) -> 0.96398356 | DB7: =AB14/AVERAGE(AB11:AB17) -> 1.0436499 | DC7: =AB15/AVERAGE(AB12:AB18) -> 1.0399813 | DD7: =AB16/AVERAGE(AB13:AB19) -> 0.98187549 | DE7: 1 | DH7: 1992 | DI7: =AC13/AVERAGE(AC10:AC16) -> #N/A | DJ7: =AC14/AVERAGE(AC11:AC17) -> #N/A | DK7: =AC15/AVERAGE(AC12:AC18) -> #N/A | DL7: =AC16/AVERAGE(AC13:AC19) -> #N/A | DM7: 1 | DP7: 1992 | DQ7: =AD13/AVERAGE(AD10:AD16) -> #N/A | DR7: =AD14/AVERAGE(AD11:AD17) -> #N/A | DS7: =AD15/AVERAGE(AD12:AD18) -> #N/A | DT7: =AD16/AVERAGE(AD13:AD19) -> #N/A | DU7: 1 | DX7: 1992 | DY7: =AE13/AVERAGE(AE10:AE16) -> #N/A | DZ7: =AE14/AVERAGE(AE11:AE17) -> #N/A | EA7: =AE15/AVERAGE(AE12:AE18) -> #N/A | EB7: =AE16/AVERAGE(AE13:AE19) -> #N/A | EC7: 1 | EF7: 1992 | EG7: =AF13/AVERAGE(AF10:AF16) -> #N/A | EH7: =AF14/AVERAGE(AF11:AF17) -> #N/A | EI7: =AF15/AVERAGE(AF12:AF18) -> #N/A | EJ7: =AF16/AVERAGE(AF13:AF19) -> #N/A | EK7: 1 | EN7: 1992 | EO7: =AG13/AVERAGE(AG10:AG16) -> #N/A | EP7: =AG14/AVERAGE(AG11:AG17) -> #N/A | EQ7: =AG15/AVERAGE(AG12:AG18) -> #N/A | ER7: =AG16/AVERAGE(AG13:AG19) -> #N/A | ES7: 1 | EV7: 1992 | EW7: =AH13/AVERAGE(AH10:AH16) -> #N/A | EX7: =AH14/AVERAGE(AH11:AH17) -> #N/A | EY7: =AH15/AVERAGE(AH12:AH18) -> #N/A | EZ7: =AH16/AVERAGE(AH13:AH19) -> #N/A | FA7: 1 | FD7: 1992 | FE7: =AI13/AVERAGE(AI10:AI16) -> #N/A | FF7: =AI14/AVERAGE(AI11:AI17) -> #N/A | FG7: =AI15/AVERAGE(AI12:AI18) -> #N/A | FH7: =AI16/AVERAGE(AI13:AI19) -> #N/A | FI7: 1
A8: 1990 Q4 | B8: =LEFT(A8,4) -> 1990 | C8: =RIGHT(A8,2) -> Q4 | D8: =HAVERQ!C14 -> 215007 | E8: =HAVERQ!D14 -> 6832 | F8: =HAVERQ!E14 -> 78838 | G8: =HAVERQ!F14 -> 71349 | H8: =HAVERQ!G14 -> -6060 | I8: =HAVERQ!H14 -> 1053 | J8: =HAVERQ!I14 -> 69632 | K8: =HAVERQ!J14 -> 65714 | L8: =HAVERQ!U14 -> #N/A | M8: =HAVERQ!V14 -> #N/A | N8: =HAVERQ!Y14 -> #N/A | O8: =HAVERQ!Z14 -> #N/A | P8: =HAVERQ!AA14 -> #N/A | Q8: =HAVERQ!AB14 -> #N/A | R8: =HAVERQ!AC14 -> #N/A | U8: =HAVERQ!M14 -> 229518 | V8: =HAVERQ!N14 -> 6807 | W8: =HAVERQ!O14 -> 79026 | X8: =HAVERQ!P14 -> 71347 | Y8: =HAVERQ!Q14 -> -7497 | Z8: =HAVERQ!R14 -> 1002 | AA8: =HAVERQ!S14 -> 72648 | AB8: =HAVERQ!T14 -> 64390 | AC8: =HAVERQ!W14 -> #N/A | AD8: =HAVERQ!X14 -> #N/A | AE8: =HAVERQ!AD14 -> #N/A | AF8: =HAVERQ!AE14 -> #N/A | AG8: =HAVERQ!AF14 -> #N/A | AH8: =HAVERQ!AG14 -> #N/A | AI8: =HAVERQ!AH14 -> #N/A | AL8: 1993 | AM8: =D17/U17 -> 1.0438045 | AN8: =E17/V17 -> 1.0097189 | AO8: =F17/W17 -> 0.99475542 | AP8: =G17/X17 -> 0.99990941 | AQ8: =H17/Y17 -> 0.11576355 | AR8: =I17/Z17 -> 0.99557522 | AS8: =J17/AA17 -> 1.0276267 | AT8: =K17/AB17 -> 1.0364288 | ... BA8: =R17/AI17 -> #N/A | BD8: 1993 | BE8: =U17/AVERAGE(U14:U20) -> 0.94992286 | BF8: =U18/AVERAGE(U15:U21) -> 0.95844284 | BG8: =U19/AVERAGE(U16:U22) -> 1.0385275 | BH8: =U20/AVERAGE(U17:U23) -> 1.0457648 | BI8: 1 | BL8: 1993 | BM8: =V17/AVERAGE(V14:V20) -> 0.97387252 | BN8: =V18/AVERAGE(V15:V21) -> 1.0505073 | BO8: =V19/AVERAGE(V16:V22) -> 1.0325067 | BP8: =V20/AVERAGE(V17:V23) -> 1.0152316 | BQ8: 1 | BT8: 1993 | BU8: =W17/AVERAGE(W14:W20) -> 1.0042631 | BV8: =W18/AVERAGE(W15:W21) -> 0.98445217 | BW8: =W19/AVERAGE(W16:W22) -> 0.99634392 | BX8: =W20/AVERAGE(W17:W23) -> 1.0010609 | BY8: 1 | CB8: 1993 | CC8: =X17/AVERAGE(X14:X20) -> 1.0031939 | CD8: =X18/AVERAGE(X15:X21) -> 0.9927469 | CE8: =X19/AVERAGE(X16:X22) -> 0.99263371 | CF8: =X20/AVERAGE(X17:X23) -> 1.0077742 | CG8: 1 | CJ8: 1993 | CK8: =Y17/AVERAGE(Y14:Y20) -> 9.7467848 | CL8: =Y18/AVERAGE(Y15:Y21) -> -3.9597948 | CM8: =Y19/AVERAGE(Y16:Y22) -> 4.5300462 | CN8: =Y20/AVERAGE(Y17:Y23) -> 0.056105978 | CO8: 1 | CR8: 1993 | CS8: =AA17/AVERAGE(AA14:AA20) -> 0.97857221 | CT8: =AA18/AVERAGE(AA15:AA21) -> 0.96808384 | CU8: =AA19/AVERAGE(AA16:AA22) -> 0.99793994 | CV8: =AA20/AVERAGE(AA17:AA23) -> 1.0173662 | CW8: 1 | CZ8: 1993 | DA8: =AB17/AVERAGE(AB14:AB20) -> 0.96212552 | DB8: =AB18/AVERAGE(AB15:AB21) -> 1.0068883 | DC8: =AB19/AVERAGE(AB16:AB22) -> 1.0289328 | DD8: =AB20/AVERAGE(AB17:AB23) -> 0.98148178 | DE8: 1 | DH8: 1993 | DI8: =AC17/AVERAGE(AC14:AC20) -> #N/A | DJ8: =AC18/AVERAGE(AC15:AC21) -> #N/A | DK8: =AC19/AVERAGE(AC16:AC22) -> #N/A | DL8: =AC20/AVERAGE(AC17:AC23) -> #N/A | DM8: 1 | DP8: 1993 | DQ8: =AD17/AVERAGE(AD14:AD20) -> #N/A | DR8: =AD18/AVERAGE(AD15:AD21) -> #N/A | DS8: =AD19/AVERAGE(AD16:AD22) -> #N/A | DT8: =AD20/AVERAGE(AD17:AD23) -> #N/A | DU8: 1 | DX8: 1993 | DY8: =AE17/AVERAGE(AE14:AE20) -> #N/A | DZ8: =AE18/AVERAGE(AE15:AE21) -> #N/A | EA8: =AE19/AVERAGE(AE16:AE22) -> #N/A | EB8: =AE20/AVERAGE(AE17:AE23) -> #N/A | EC8: 1 | EF8: 1993 | EG8: =AF17/AVERAGE(AF14:AF20) -> #N/A | EH8: =AF18/AVERAGE(AF15:AF21) -> #N/A | EI8: =AF19/AVERAGE(AF16:AF22) -> #N/A | EJ8: =AF20/AVERAGE(AF17:AF23) -> #N/A | EK8: 1 | EN8: 1993 | EO8: =AG17/AVERAGE(AG14:AG20) -> #N/A | EP8: =AG18/AVERAGE(AG15:AG21) -> #N/A | EQ8: =AG19/AVERAGE(AG16:AG22) -> #N/A | ER8: =AG20/AVERAGE(AG17:AG23) -> #N/A | ES8: 1 | EV8: 1993 | EW8: =AH17/AVERAGE(AH14:AH20) -> #N/A | EX8: =AH18/AVERAGE(AH15:AH21) -> #N/A | EY8: =AH19/AVERAGE(AH16:AH22) -> #N/A | EZ8: =AH20/AVERAGE(AH17:AH23) -> #N/A | FA8: 1 | FD8: 1993 | FE8: =AI17/AVERAGE(AI14:AI20) -> #N/A | FF8: =AI18/AVERAGE(AI15:AI21) -> #N/A | FG8: =AI19/AVERAGE(AI16:AI22) -> #N/A | FH8: =AI20/AVERAGE(AI17:AI23) -> #N/A | FI8: 1
A9: 1991 Q1 | B9: =LEFT(A9,4) -> 1991 | C9: =RIGHT(A9,2) -> Q1 | D9: =HAVERQ!C15 -> 214735 | E9: =HAVERQ!D15 -> 6531 | F9: =HAVERQ!E15 -> 79041 | G9: =HAVERQ!F15 -> 68137 | H9: =HAVERQ!G15 -> -1893 | I9: =HAVERQ!H15 -> -2024 | J9: =HAVERQ!I15 -> 66995 | K9: =HAVERQ!J15 -> 63535 | L9: =HAVERQ!U15 -> #N/A | M9: =HAVERQ!V15 -> #N/A | N9: =HAVERQ!Y15 -> #N/A | O9: =HAVERQ!Z15 -> #N/A | P9: =HAVERQ!AA15 -> #N/A | Q9: =HAVERQ!AB15 -> #N/A | R9: =HAVERQ!AC15 -> #N/A | U9: =HAVERQ!M15 -> 200541 | V9: =HAVERQ!N15 -> 6475 | W9: =HAVERQ!O15 -> 79913 | X9: =HAVERQ!P15 -> 68143 | Y9: =HAVERQ!Q15 -> -4244 | Z9: =HAVERQ!R15 -> -1987 | AA9: =HAVERQ!S15 -> 64001 | AB9: =HAVERQ!T15 -> 61158 | AC9: =HAVERQ!W15 -> #N/A | AD9: =HAVERQ!X15 -> #N/A | AE9: =HAVERQ!AD15 -> #N/A | AF9: =HAVERQ!AE15 -> #N/A | AG9: =HAVERQ!AF15 -> #N/A | AH9: =HAVERQ!AG15 -> #N/A | AI9: =HAVERQ!AH15 -> #N/A | AL9: 1994 | AM9: =OFFSET($D$5, (ROW(D5)-1)*4,0)/OFFSET($U$5, (ROW(U5)-1)*4,0) -> 1.0369942 | AN9: =OFFSET(E$5, (ROW(E5)-1)*4,0)/OFFSET(V$5, (ROW(V5)-1)*4,0) -> 1.0009565 | AO9: =OFFSET(F$5, (ROW(F5)-1)*4,0)/OFFSET(W$5, (ROW(W5)-1)*4,0) -> 0.99602543 | AP9: =OFFSET(G$5, (ROW(G5)-1)*4,0)/OFFSET(X$5, (ROW(X5)-1)*4,0) -> 0.99982396 | AQ9: =OFFSET(H$5, (ROW(H5)-1)*4,0)/OFFSET(Y$5, (ROW(Y5)-1)*4,0) -> 0.71479714 | AR9: =OFFSET(I$5, (ROW(I5)-1)*4,0)/OFFSET(Z$5, (ROW(Z5)-1)*4,0) -> 0.99717514 | AS9: =OFFSET(J$5, (ROW(J5)-1)*4,0)/OFFSET(AA$5, (ROW(AA5)-1)*4,0) -> 1.023186 | AT9: =OFFSET(K$5, (ROW(K5)-1)*4,0)/OFFSET(AB$5, (ROW(AB5)-1)*4,0) -> 1.0324983 | AU9: =OFFSET(L$5, (ROW(L5)-1)*4,0)/OFFSET(AC$5, (ROW(AC5)-1)*4,0) -> #N/A | ... BA9: =OFFSET(R$5, (ROW(R5)-1)*4,0)/OFFSET(AI$5, (ROW(AI5)-1)*4,0) -> #N/A | BD9: 1994 | BE9: =U21/AVERAGE(U18:U24) -> 0.96315269 | BF9: =U22/AVERAGE(U19:U25) -> 0.9672441 | BG9: =U23/AVERAGE(U20:U26) -> 1.0379032 | BH9: =U24/AVERAGE(U21:U27) -> 1.04258 | BI9: 1 | BL9: 1994 | BM9: =V21/AVERAGE(V18:V24) -> 0.98450953 | BN9: =V22/AVERAGE(V19:V25) -> 0.98534778 | BO9: =V23/AVERAGE(V20:V26) -> 0.99096544 | BP9: =V24/AVERAGE(V21:V27) -> 0.99237548 | BQ9: 1 | BT9: 1994 | BU9: =W21/AVERAGE(W18:W24) -> 0.99980783 | BV9: =W22/AVERAGE(W19:W25) -> 1.0030873 | BW9: =W23/AVERAGE(W20:W26) -> 0.99836698 | BX9: =W24/AVERAGE(W21:W27) -> 0.99892309 | BY9: 1 | CB9: 1994 | CC9: =X21/AVERAGE(X18:X24) -> 1.017522 | CD9: =X22/AVERAGE(X19:X25) -> 0.995479 | CE9: =X23/AVERAGE(X20:X26) -> 1.0001869 | CF9: =X24/AVERAGE(X21:X27) -> 1.005353 | CG9: 1 | CJ9: 1994 | CK9: =Y21/AVERAGE(Y18:Y24) -> -1.0120191 | CL9: =Y22/AVERAGE(Y19:Y25) -> 5.2870303 | CM9: =Y23/AVERAGE(Y20:Y26) -> 1.4480233 | CN9: =Y24/AVERAGE(Y21:Y27) -> 1.1066476 | CO9: 1 | CR9: 1994 | CS9: =AA21/AVERAGE(AA18:AA24) -> 0.98511337 | CT9: =AA22/AVERAGE(AA19:AA25) -> 0.97710041 | CU9: =AA23/AVERAGE(AA20:AA26) -> 1.0099402 | CV9: =AA24/AVERAGE(AA21:AA27) -> 1.0183987 | CW9: 1 | CZ9: 1994 | DA9: =AB21/AVERAGE(AB18:AB24) -> 0.97166211 | DB9: =AB22/AVERAGE(AB19:AB25) -> 1.0296372 | DC9: =AB23/AVERAGE(AB20:AB26) -> 1.0135809 | DD9: =AB24/AVERAGE(AB21:AB27) -> 0.99458772 | DE9: 1 | DH9: 1994 | DI9: =AC21/AVERAGE(AC18:AC24) -> #N/A | DJ9: =AC22/AVERAGE(AC19:AC25) -> #N/A | DK9: =AC23/AVERAGE(AC20:AC26) -> #N/A | DL9: =AC24/AVERAGE(AC21:AC27) -> #N/A | DM9: 1 | DP9: 1994 | DQ9: =AD21/AVERAGE(AD18:AD24) -> #N/A | DR9: =AD22/AVERAGE(AD19:AD25) -> #N/A | DS9: =AD23/AVERAGE(AD20:AD26) -> #N/A | DT9: =AD24/AVERAGE(AD21:AD27) -> #N/A | DU9: 1 | DX9: 1994 | DY9: =AE21/AVERAGE(AE18:AE24) -> #N/A | DZ9: =AE22/AVERAGE(AE19:AE25) -> #N/A | EA9: =AE23/AVERAGE(AE20:AE26) -> #N/A | EB9: =AE24/AVERAGE(AE21:AE27) -> #N/A | EC9: 1 | EF9: 1994 | EG9: =AF21/AVERAGE(AF18:AF24) -> #N/A | EH9: =AF22/AVERAGE(AF19:AF25) -> #N/A | EI9: =AF23/AVERAGE(AF20:AF26) -> #N/A | EJ9: =AF24/AVERAGE(AF21:AF27) -> #N/A | EK9: 1 | EN9: 1994 | EO9: =AG21/AVERAGE(AG18:AG24) -> #N/A | EP9: =AG22/AVERAGE(AG19:AG25) -> #N/A | EQ9: =AG23/AVERAGE(AG20:AG26) -> #N/A | ER9: =AG24/AVERAGE(AG21:AG27) -> #N/A | ES9: 1 | EV9: 1994 | EW9: =AH21/AVERAGE(AH18:AH24) -> #N/A | EX9: =AH22/AVERAGE(AH19:AH25) -> #N/A | EY9: =AH23/AVERAGE(AH20:AH26) -> #N/A | EZ9: =AH24/AVERAGE(AH21:AH27) -> #N/A | FA9: 1 | FD9: 1994 | FE9: =AI21/AVERAGE(AI18:AI24) -> #N/A | FF9: =AI22/AVERAGE(AI19:AI25) -> #N/A | FG9: =AI23/AVERAGE(AI20:AI26) -> #N/A | FH9: =AI24/AVERAGE(AI21:AI27) -> #N/A | FI9: 1
A10: 1991 Q2 | B10: =LEFT(A10,4) -> 1991 | C10: =RIGHT(A10,2) -> Q2 | D10: =HAVERQ!C16 -> 213315 | E10: =HAVERQ!D16 -> 6485 | F10: =HAVERQ!E16 -> 81070 | G10: =HAVERQ!F16 -> 67111 | H10: =HAVERQ!G16 -> -4769 | I10: =HAVERQ!H16 -> 4205 | J10: =HAVERQ!I16 -> 69215 | K10: =HAVERQ!J16 -> 63812 | L10: =HAVERQ!U16 -> #N/A | M10: =HAVERQ!V16 -> #N/A | N10: =HAVERQ!Y16 -> #N/A | O10: =HAVERQ!Z16 -> #N/A | P10: =HAVERQ!AA16 -> #N/A | Q10: =HAVERQ!AB16 -> #N/A | R10: =HAVERQ!AC16 -> #N/A | U10: =HAVERQ!M16 -> 205225 | V10: =HAVERQ!N16 -> 6520 | W10: =HAVERQ!O16 -> 80148 | X10: =HAVERQ!P16 -> 67112 | Y10: =HAVERQ!Q16 -> -1711 | Z10: =HAVERQ!R16 -> 4101 | AA10: =HAVERQ!S16 -> 69165 | AB10: =HAVERQ!T16 -> 65393 | AC10: =HAVERQ!W16 -> #N/A | AD10: =HAVERQ!X16 -> #N/A | AE10: =HAVERQ!AD16 -> #N/A | AF10: =HAVERQ!AE16 -> #N/A | AG10: =HAVERQ!AF16 -> #N/A | AH10: =HAVERQ!AG16 -> #N/A | AI10: =HAVERQ!AH16 -> #N/A | AL10: 1995 | AM10: =OFFSET($D$5, (ROW(D6)-1)*4,0)/OFFSET($U$5, (ROW(U6)-1)*4,0) -> 1.0498853 | AN10: =OFFSET($E$5, (ROW(E6)-1)*4,0)/OFFSET($V$5, (ROW(V6)-1)*4,0) -> 1.0085653 | AO10: =OFFSET(F$5, (ROW(F6)-1)*4,0)/OFFSET(W$5, (ROW(W6)-1)*4,0) -> 1.0002549 | AP10: =OFFSET(G$5, (ROW(G6)-1)*4,0)/OFFSET(X$5, (ROW(X6)-1)*4,0) -> 1.0006296 | AQ10: =OFFSET(H$5, (ROW(H6)-1)*4,0)/OFFSET(Y$5, (ROW(Y6)-1)*4,0) -> 0.55954757 | AR10: =OFFSET(I$5, (ROW(I6)-1)*4,0)/OFFSET(Z$5, (ROW(Z6)-1)*4,0) -> 1 | AS10: =OFFSET(J$5, (ROW(J6)-1)*4,0)/OFFSET(AA$5, (ROW(AA6)-1)*4,0) -> 1.0132081 | AT10: =OFFSET(K$5, (ROW(K6)-1)*4,0)/OFFSET(AB$5, (ROW(AB6)-1)*4,0) -> 1.0325158 | AU10: =OFFSET(L$5, (ROW(L6)-1)*4,0)/OFFSET(AC$5, (ROW(AC6)-1)*4,0) -> #N/A | AV10: =OFFSET(M$5, (ROW(M6)-1)*4,0)/OFFSET(AD$5, (ROW(AD6)-1)*4,0) -> #N/A | ... BA10: =OFFSET(R$5, (ROW(R6)-1)*4,0)/OFFSET(AI$5, (ROW(AI6)-1)*4,0) -> #N/A | BD10: 1995 | BE10: =U25/AVERAGE(U22:U28) -> 0.94524344 | BF10: =U26/AVERAGE(U23:U29) -> 0.9669946 | BG10: =U27/AVERAGE(U24:U30) -> 1.0323296 | BH10: =U28/AVERAGE(U25:U31) -> 1.049214 | BI10: 1 | BL10: 1995 | BM10: =V25/AVERAGE(V22:V28) -> 1.0151061 | BN10: =V26/AVERAGE(V23:V29) -> 0.99256327 | BO10: =V27/AVERAGE(V24:V30) -> 0.99370483 | BP10: =V28/AVERAGE(V25:V31) -> 0.99656255 | BQ10: 1 | BT10: 1995 | BU10: =W25/AVERAGE(W22:W28) -> 1.0020865 | BV10: =W26/AVERAGE(W23:W29) -> 1.0000589 | BW10: =W27/AVERAGE(W24:W30) -> 0.99243616 | BX10: =W28/AVERAGE(W25:W31) -> 1.0107706 | BY10: 1 | CB10: 1995 | CC10: =X25/AVERAGE(X22:X28) -> 0.99276331 | CD10: =X26/AVERAGE(X23:X29) -> 0.98845711 | CE10: =X27/AVERAGE(X24:X30) -> 0.98621883 | CF10: =X28/AVERAGE(X25:X31) -> 0.98490944 | CG10: 1 | CJ10: 1995 | CK10: =Y25/AVERAGE(Y22:Y28) -> -0.76288884 | CL10: =Y26/AVERAGE(Y23:Y29) -> 3.4252146 | CM10: =Y27/AVERAGE(Y24:Y30) -> 1.9616193 | CN10: =Y28/AVERAGE(Y25:Y31) -> 1.5565752 | CO10: 1 | CR10: 1995 | CS10: =AA25/AVERAGE(AA22:AA28) -> 1.0067201 | CT10: =AA26/AVERAGE(AA23:AA29) -> 0.98013952 | CU10: =AA27/AVERAGE(AA24:AA30) -> 1.009892 | CV10: =AA28/AVERAGE(AA25:AA31) -> 1.0142963 | CW10: 1 | CZ10: 1995 | DA10: =AB25/AVERAGE(AB22:AB28) -> 0.9456299 | DB10: =AB26/AVERAGE(AB23:AB29) -> 1.0234263 | DC10: =AB27/AVERAGE(AB24:AB30) -> 1.0232293 | DD10: =AB28/AVERAGE(AB25:AB31) -> 0.9798275 | DE10: 1 | DH10: 1995 | DI10: =AC25/AVERAGE(AC22:AC28) -> #N/A | DJ10: =AC26/AVERAGE(AC23:AC29) -> #N/A | DK10: =AC27/AVERAGE(AC24:AC30) -> #N/A | DL10: =AC28/AVERAGE(AC25:AC31) -> #N/A | DM10: 1 | DP10: 1995 | DQ10: =AD25/AVERAGE(AD22:AD28) -> #N/A | DR10: =AD26/AVERAGE(AD23:AD29) -> #N/A | DS10: =AD27/AVERAGE(AD24:AD30) -> #N/A | DT10: =AD28/AVERAGE(AD25:AD31) -> #N/A | DU10: 1 | DX10: 1995 | DY10: =AE25/AVERAGE(AE22:AE28) -> #N/A | DZ10: =AE26/AVERAGE(AE23:AE29) -> #N/A | EA10: =AE27/AVERAGE(AE24:AE30) -> #N/A | EB10: =AE28/AVERAGE(AE25:AE31) -> #N/A | EC10: 1 | EF10: 1995 | EG10: =AF25/AVERAGE(AF22:AF28) -> #N/A | EH10: =AF26/AVERAGE(AF23:AF29) -> #N/A | EI10: =AF27/AVERAGE(AF24:AF30) -> #N/A | EJ10: =AF28/AVERAGE(AF25:AF31) -> #N/A | EK10: 1 | EN10: 1995 | EO10: =AG25/AVERAGE(AG22:AG28) -> #N/A | EP10: =AG26/AVERAGE(AG23:AG29) -> #N/A | EQ10: =AG27/AVERAGE(AG24:AG30) -> #N/A | ER10: =AG28/AVERAGE(AG25:AG31) -> #N/A | ES10: 1 | EV10: 1995 | EW10: =AH25/AVERAGE(AH22:AH28) -> #N/A | EX10: =AH26/AVERAGE(AH23:AH29) -> #N/A | EY10: =AH27/AVERAGE(AH24:AH30) -> #N/A | EZ10: =AH28/AVERAGE(AH25:AH31) -> #N/A | FA10: 1 | FD10: 1995 | FE10: =AI25/AVERAGE(AI22:AI28) -> #N/A | FF10: =AI26/AVERAGE(AI23:AI29) -> #N/A | FG10: =AI27/AVERAGE(AI24:AI30) -> #N/A | FH10: =AI28/AVERAGE(AI25:AI31) -> #N/A | FI10: 1
A11: 1991 Q3 | B11: =LEFT(A11,4) -> 1991 | C11: =RIGHT(A11,2) -> Q3 | D11: =HAVERQ!C17 -> 213544 | E11: =HAVERQ!D17 -> 6558 | F11: =HAVERQ!E17 -> 80462 | G11: =HAVERQ!F17 -> 65897 | H11: =HAVERQ!G17 -> -3885 | I11: =HAVERQ!H17 -> -2001 | J11: =HAVERQ!I17 -> 70286 | K11: =HAVERQ!J17 -> 64199 | L11: =HAVERQ!U17 -> #N/A | M11: =HAVERQ!V17 -> #N/A | N11: =HAVERQ!Y17 -> #N/A | O11: =HAVERQ!Z17 -> #N/A | P11: =HAVERQ!AA17 -> #N/A | Q11: =HAVERQ!AB17 -> #N/A | R11: =HAVERQ!AC17 -> #N/A | U11: =HAVERQ!M17 -> 221618 | V11: =HAVERQ!N17 -> 6596 | W11: =HAVERQ!O17 -> 80288 | X11: =HAVERQ!P17 -> 65896 | Y11: =HAVERQ!Q17 -> -297 | Z11: =HAVERQ!R17 -> -1894 | AA11: =HAVERQ!S17 -> 70172 | AB11: =HAVERQ!T17 -> 66165 | AC11: =HAVERQ!W17 -> #N/A | AD11: =HAVERQ!X17 -> #N/A | AE11: =HAVERQ!AD17 -> #N/A | AF11: =HAVERQ!AE17 -> #N/A | AG11: =HAVERQ!AF17 -> #N/A | AH11: =HAVERQ!AG17 -> #N/A | AI11: =HAVERQ!AH17 -> #N/A | AL11: 1996 | AM11: =OFFSET($D$5, (ROW(D7)-1)*4,0)/OFFSET($U$5, (ROW(U7)-1)*4,0) -> 1.0499428 | AN11: =OFFSET($E$5, (ROW(E7)-1)*4,0)/OFFSET($V$5, (ROW(V7)-1)*4,0) -> 0.99544596 | AO11: =OFFSET(F$5, (ROW(F7)-1)*4,0)/OFFSET(W$5, (ROW(W7)-1)*4,0) -> 0.99803647 | AP11: =OFFSET(G$5, (ROW(G7)-1)*4,0)/OFFSET(X$5, (ROW(X7)-1)*4,0) -> 0.9955155 | AQ11: =OFFSET(H$5, (ROW(H7)-1)*4,0)/OFFSET(Y$5, (ROW(Y7)-1)*4,0) -> -1.0090466 | AR11: =OFFSET(I$5, (ROW(I7)-1)*4,0)/OFFSET(Z$5, (ROW(Z7)-1)*4,0) -> 0.99796748 | AS11: =OFFSET(J$5, (ROW(J7)-1)*4,0)/OFFSET(AA$5, (ROW(AA7)-1)*4,0) -> 1.0182034 | AT11: =OFFSET(K$5, (ROW(K7)-1)*4,0)/OFFSET(AB$5, (ROW(AB7)-1)*4,0) -> 1.0277901 | AU11: =OFFSET(L$5, (ROW(L7)-1)*4,0)/OFFSET(AC$5, (ROW(AC7)-1)*4,0) -> #N/A | AV11: =OFFSET(M$5, (ROW(M7)-1)*4,0)/OFFSET(AD$5, (ROW(AD7)-1)*4,0) -> #N/A | ... BA11: =OFFSET(R$5, (ROW(R7)-1)*4,0)/OFFSET(AI$5, (ROW(AI7)-1)*4,0) -> #N/A | BD11: 1996 | BE11: =U29/AVERAGE(U26:U32) -> 0.94651462 | BF11: =U30/AVERAGE(U27:U33) -> 0.96563076 | BG11: =U31/AVERAGE(U28:U34) -> 1.0284816 | BH11: =U32/AVERAGE(U29:U35) -> 1.0434941 | BI11: 1 | BL11: 1996 | BM11: =V29/AVERAGE(V26:V32) -> 1.0904042 | BN11: =V30/AVERAGE(V27:V33) -> 0.93956291 | BO11: =V31/AVERAGE(V28:V34) -> 0.91015989 | BP11: =V32/AVERAGE(V29:V35) -> 0.91761319 | BQ11: 1 | BT11: 1996 | BU11: =W29/AVERAGE(W26:W32) -> 1.0062441 | BV11: =W30/AVERAGE(W27:W33) -> 0.99459088 | BW11: =W31/AVERAGE(W28:W34) -> 0.99720072 | BX11: =W32/AVERAGE(W29:W35) -> 1.0146411 | BY11: 1 | CB11: 1996 | CC11: =X29/AVERAGE(X26:X32) -> 1.0106511 | CD11: =X30/AVERAGE(X27:X33) -> 1.0379291 | CE11: =X31/AVERAGE(X28:X34) -> 1.0306949 | CF11: =X32/AVERAGE(X29:X35) -> 0.9836575 | CG11: 1 | CJ11: 1996 | CK11: =Y29/AVERAGE(Y26:Y32) -> -1.0706759 | CL11: =Y30/AVERAGE(Y27:Y33) -> 2.5186546 | CM11: =Y31/AVERAGE(Y28:Y34) -> 0.73944658 | CN11: =Y32/AVERAGE(Y29:Y35) -> 4.614662 | CO11: 1 | CR11: 1996 | CS11: =AA29/AVERAGE(AA26:AA32) -> 0.98363686 | CT11: =AA30/AVERAGE(AA27:AA33) -> 0.98247175 | CU11: =AA31/AVERAGE(AA28:AA34) -> 0.98374772 | CV11: =AA32/AVERAGE(AA29:AA35) -> 1.0092184 | CW11: 1 | CZ11: 1996 | DA11: =AB29/AVERAGE(AB26:AB32) -> 0.97516874 | DB11: =AB30/AVERAGE(AB27:AB33) -> 1.0172663 | DC11: =AB31/AVERAGE(AB28:AB34) -> 1.0115482 | DD11: =AB32/AVERAGE(AB29:AB35) -> 0.98996363 | DE11: 1 | DH11: 1996 | DI11: =AC29/AVERAGE(AC26:AC32) -> #N/A | DJ11: =AC30/AVERAGE(AC27:AC33) -> #N/A | DK11: =AC31/AVERAGE(AC28:AC34) -> #N/A | DL11: =AC32/AVERAGE(AC29:AC35) -> #N/A | DM11: 1 | DP11: 1996 | DQ11: =AD29/AVERAGE(AD26:AD32) -> #N/A | DR11: =AD30/AVERAGE(AD27:AD33) -> #N/A | DS11: =AD31/AVERAGE(AD28:AD34) -> #N/A | DT11: =AD32/AVERAGE(AD29:AD35) -> #N/A | DU11: 1 | DX11: 1996 | DY11: =AE29/AVERAGE(AE26:AE32) -> #N/A | DZ11: =AE30/AVERAGE(AE27:AE33) -> #N/A | EA11: =AE31/AVERAGE(AE28:AE34) -> #N/A | EB11: =AE32/AVERAGE(AE29:AE35) -> #N/A | EC11: 1 | EF11: 1996 | EG11: =AF29/AVERAGE(AF26:AF32) -> #N/A | EH11: =AF30/AVERAGE(AF27:AF33) -> #N/A | EI11: =AF31/AVERAGE(AF28:AF34) -> #N/A | EJ11: =AF32/AVERAGE(AF29:AF35) -> #N/A | EK11: 1 | EN11: 1996 | EO11: =AG29/AVERAGE(AG26:AG32) -> #N/A | EP11: =AG30/AVERAGE(AG27:AG33) -> #N/A | EQ11: =AG31/AVERAGE(AG28:AG34) -> #N/A | ER11: =AG32/AVERAGE(AG29:AG35) -> #N/A | ES11: 1 | EV11: 1996 | EW11: =AH29/AVERAGE(AH26:AH32) -> #N/A | EX11: =AH30/AVERAGE(AH27:AH33) -> #N/A | EY11: =AH31/AVERAGE(AH28:AH34) -> #N/A | EZ11: =AH32/AVERAGE(AH29:AH35) -> #N/A | FA11: 1 | FD11: 1996 | FE11: =AI29/AVERAGE(AI26:AI32) -> #N/A | FF11: =AI30/AVERAGE(AI27:AI33) -> #N/A | FG11: =AI31/AVERAGE(AI28:AI34) -> #N/A | FH11: =AI32/AVERAGE(AI29:AI35) -> #N/A | FI11: 1
A12: 1991 Q4 | B12: =LEFT(A12,4) -> 1991 | C12: =RIGHT(A12,2) -> Q4 | D12: =HAVERQ!C18 -> 213576 | E12: =HAVERQ!D18 -> 6678 | F12: =HAVERQ!E18 -> 80327 | G12: =HAVERQ!F18 -> 66146 | H12: =HAVERQ!G18 -> -2274 | I12: =HAVERQ!H18 -> -1022 | J12: =HAVERQ!I18 -> 70075 | K12: =HAVERQ!J18 -> 65130 | L12: =HAVERQ!U18 -> #N/A | M12: =HAVERQ!V18 -> #N/A | N12: =HAVERQ!Y18 -> #N/A | O12: =HAVERQ!Z18 -> #N/A | P12: =HAVERQ!AA18 -> #N/A | Q12: =HAVERQ!AB18 -> #N/A | R12: =HAVERQ!AC18 -> #N/A | U12: =HAVERQ!M18 -> 227786 | V12: =HAVERQ!N18 -> 6661 | W12: =HAVERQ!O18 -> 80551 | X12: =HAVERQ!P18 -> 66140 | Y12: =HAVERQ!Q18 -> -6569 | Z12: =HAVERQ!R18 -> -1062 | AA12: =HAVERQ!S18 -> 73233 | AB12: =HAVERQ!T18 -> 63960 | AC12: =HAVERQ!W18 -> #N/A | AD12: =HAVERQ!X18 -> #N/A | AE12: =HAVERQ!AD18 -> #N/A | AF12: =HAVERQ!AE18 -> #N/A | AG12: =HAVERQ!AF18 -> #N/A | AH12: =HAVERQ!AG18 -> #N/A | AI12: =HAVERQ!AH18 -> #N/A | AL12: 1997 | AM12: =OFFSET($D$5, (ROW(D8)-1)*4,0)/OFFSET($U$5, (ROW(U8)-1)*4,0) -> 1.028127 | AN12: =OFFSET($E$5, (ROW(E8)-1)*4,0)/OFFSET($V$5, (ROW(V8)-1)*4,0) -> 1 | AO12: =OFFSET(F$5, (ROW(F8)-1)*4,0)/OFFSET(W$5, (ROW(W8)-1)*4,0) -> 1.0030903 | AP12: =OFFSET(G$5, (ROW(G8)-1)*4,0)/OFFSET(X$5, (ROW(X8)-1)*4,0) -> 0.96627717 | AQ12: =OFFSET(H$5, (ROW(H8)-1)*4,0)/OFFSET(Y$5, (ROW(Y8)-1)*4,0) -> 0.77285092 | AR12: =OFFSET(I$5, (ROW(I8)-1)*4,0)/OFFSET(Z$5, (ROW(Z8)-1)*4,0) -> 1.0692718 | AS12: =OFFSET(J$5, (ROW(J8)-1)*4,0)/OFFSET(AA$5, (ROW(AA8)-1)*4,0) -> 1.0314308 | AT12: =OFFSET(K$5, (ROW(K8)-1)*4,0)/OFFSET(AB$5, (ROW(AB8)-1)*4,0) -> 1.0408495 | AU12: =OFFSET(L$5, (ROW(L8)-1)*4,0)/OFFSET(AC$5, (ROW(AC8)-1)*4,0) -> 1.0171018 | AV12: =OFFSET(M$5, (ROW(M8)-1)*4,0)/OFFSET(AD$5, (ROW(AD8)-1)*4,0) -> 0.67218651 | ... BA12: =OFFSET(R$5, (ROW(R8)-1)*4,0)/OFFSET(AI$5, (ROW(AI8)-1)*4,0) -> 1.0027085 | BD12: 1997 | BE12: =U33/AVERAGE(U30:U36) -> 0.96384452 | BF12: =U34/AVERAGE(U31:U37) -> 0.98306222 | BG12: =U35/AVERAGE(U32:U38) -> 1.0153785 | BH12: =U36/AVERAGE(U33:U39) -> 1.0317491 | BI12: 1 | BL12: 1997 | BM12: =V33/AVERAGE(V30:V36) -> 1.0960307 | BN12: =V34/AVERAGE(V31:V37) -> 1.0461131 | BO12: =V35/AVERAGE(V32:V38) -> 1.0207007 | BP12: =V36/AVERAGE(V33:V39) -> 1.000996 | BQ12: 1 | BT12: 1997 | BU12: =W33/AVERAGE(W30:W36) -> 0.99597897 | BV12: =W34/AVERAGE(W31:W37) -> 0.98820714 | BW12: =W35/AVERAGE(W32:W38) -> 0.97947321 | BX12: =W36/AVERAGE(W33:W39) -> 1.0036546 | BY12: 1 | CB12: 1997 | CC12: =X33/AVERAGE(X30:X36) -> 0.98336117 | CD12: =X34/AVERAGE(X31:X37) -> 0.92211212 | CE12: =X35/AVERAGE(X32:X38) -> 0.99108819 | CF12: =X36/AVERAGE(X33:X39) -> 1.044966 | CG12: 1 | CJ12: 1997 | CK12: =Y33/AVERAGE(Y30:Y36) -> -2.6081492 | CL12: =Y34/AVERAGE(Y31:Y37) -> 1.6435785 | CM12: =Y35/AVERAGE(Y32:Y38) -> 1.9377331 | CN12: =Y36/AVERAGE(Y33:Y39) -> 1.2754721 | CO12: 1 | CR12: 1997 | CS12: =AA33/AVERAGE(AA30:AA36) -> 0.99585878 | CT12: =AA34/AVERAGE(AA31:AA37) -> 1.0205946 | CU12: =AA35/AVERAGE(AA32:AA38) -> 1.0047163 | CV12: =AA36/AVERAGE(AA33:AA39) -> 1.0374562 | CW12: 1 | CZ12: 1997 | DA12: =AB33/AVERAGE(AB30:AB36) -> 0.95703707 | DB12: =AB34/AVERAGE(AB31:AB37) -> 1.0334733 | DC12: =AB35/AVERAGE(AB32:AB38) -> 1.0290583 | DD12: =AB36/AVERAGE(AB33:AB39) -> 0.99295693 | DE12: 1 | DH12: 1997 | DI12: =AC33/AVERAGE(AC30:AC36) -> #N/A | DJ12: =AC34/AVERAGE(AC31:AC37) -> #N/A | DK12: =AC35/AVERAGE(AC32:AC38) -> #N/A | DL12: =AC36/AVERAGE(AC33:AC39) -> 1.0644383 | DM12: 1 | DP12: 1997 | DQ12: =AD33/AVERAGE(AD30:AD36) -> #N/A | DR12: =AD34/AVERAGE(AD31:AD37) -> #N/A | DS12: =AD35/AVERAGE(AD32:AD38) -> #N/A | DT12: =AD36/AVERAGE(AD33:AD39) -> 0.9280288 | DU12: 1 | DX12: 1997 | DY12: =AE33/AVERAGE(AE30:AE36) -> #N/A | DZ12: =AE34/AVERAGE(AE31:AE37) -> #N/A | EA12: =AE35/AVERAGE(AE32:AE38) -> #N/A | EB12: =AE36/AVERAGE(AE33:AE39) -> 0.82560006 | EC12: 1 | EF12: 1997 | EG12: =AF33/AVERAGE(AF30:AF36) -> #N/A | EH12: =AF34/AVERAGE(AF31:AF37) -> #N/A | EI12: =AF35/AVERAGE(AF32:AF38) -> #N/A | EJ12: =AF36/AVERAGE(AF33:AF39) -> 1.139053 | EK12: 1 | EN12: 1997 | EO12: =AG33/AVERAGE(AG30:AG36) -> #N/A | EP12: =AG34/AVERAGE(AG31:AG37) -> #N/A | EQ12: =AG35/AVERAGE(AG32:AG38) -> #N/A | ER12: =AG36/AVERAGE(AG33:AG39) -> 1.042549 | ES12: 1 | EV12: 1997 | EW12: =AH33/AVERAGE(AH30:AH36) -> #N/A | EX12: =AH34/AVERAGE(AH31:AH37) -> #N/A | EY12: =AH35/AVERAGE(AH32:AH38) -> #N/A | EZ12: =AH36/AVERAGE(AH33:AH39) -> 1.0503884 | FA12: 1 | FD12: 1997 | FE12: =AI33/AVERAGE(AI30:AI36) -> #N/A | FF12: =AI34/AVERAGE(AI31:AI37) -> #N/A | FG12: =AI35/AVERAGE(AI32:AI38) -> #N/A | FH12: =AI36/AVERAGE(AI33:AI39) -> 1.0082149 | FI12: 1
A13: 1992 Q1 | B13: =LEFT(A13,4) -> 1992 | C13: =RIGHT(A13,2) -> Q1 | D13: =HAVERQ!C19 -> 213040 | E13: =HAVERQ!D19 -> 6583 | F13: =HAVERQ!E19 -> 80646 | G13: =HAVERQ!F19 -> 66335 | H13: =HAVERQ!G19 -> -1362 | I13: =HAVERQ!H19 -> -837 | J13: =HAVERQ!I19 -> 70839 | K13: =HAVERQ!J19 -> 66269 | L13: =HAVERQ!U19 -> #N/A | M13: =HAVERQ!V19 -> #N/A | N13: =HAVERQ!Y19 -> #N/A | O13: =HAVERQ!Z19 -> #N/A | P13: =HAVERQ!AA19 -> #N/A | Q13: =HAVERQ!AB19 -> #N/A | R13: =HAVERQ!AC19 -> #N/A | U13: =HAVERQ!M19 -> 203115 | V13: =HAVERQ!N19 -> 6486 | W13: =HAVERQ!O19 -> 81269 | X13: =HAVERQ!P19 -> 66348 | Y13: =HAVERQ!Q19 -> -2575 | Z13: =HAVERQ!R19 -> -841 | AA13: =HAVERQ!S19 -> 68493 | AB13: =HAVERQ!T19 -> 64588 | AC13: =HAVERQ!W19 -> #N/A | AD13: =HAVERQ!X19 -> #N/A | AE13: =HAVERQ!AD19 -> #N/A | AF13: =HAVERQ!AE19 -> #N/A | AG13: =HAVERQ!AF19 -> #N/A | AH13: =HAVERQ!AG19 -> #N/A | AI13: =HAVERQ!AH19 -> #N/A | AL13: 1998 | AM13: =OFFSET($D$5, (ROW(D9)-1)*4,0)/OFFSET($U$5, (ROW(U9)-1)*4,0) -> 1.0260166 | AN13: =OFFSET($E$5, (ROW(E9)-1)*4,0)/OFFSET($V$5, (ROW(V9)-1)*4,0) -> 1 | AO13: =OFFSET(F$5, (ROW(F9)-1)*4,0)/OFFSET(W$5, (ROW(W9)-1)*4,0) -> 1.0014175 | AP13: =OFFSET(G$5, (ROW(G9)-1)*4,0)/OFFSET(X$5, (ROW(X9)-1)*4,0) -> 0.94534526 | AQ13: =OFFSET(H$5, (ROW(H9)-1)*4,0)/OFFSET(Y$5, (ROW(Y9)-1)*4,0) -> 2.0709497 | AR13: =OFFSET(I$5, (ROW(I9)-1)*4,0)/OFFSET(Z$5, (ROW(Z9)-1)*4,0) -> 1.0697085 | AS13: =OFFSET(J$5, (ROW(J9)-1)*4,0)/OFFSET(AA$5, (ROW(AA9)-1)*4,0) -> 1.0219325 | AT13: =OFFSET(K$5, (ROW(K9)-1)*4,0)/OFFSET(AB$5, (ROW(AB9)-1)*4,0) -> 1.0268373 | AU13: =OFFSET(L$5, (ROW(L9)-1)*4,0)/OFFSET(AC$5, (ROW(AC9)-1)*4,0) -> 0.97848761 | AV13: =OFFSET(M$5, (ROW(M9)-1)*4,0)/OFFSET(AD$5, (ROW(AD9)-1)*4,0) -> 0.71477982 | ... BA13: =OFFSET(R$5, (ROW(R9)-1)*4,0)/OFFSET(AI$5, (ROW(AI9)-1)*4,0) -> 0.99236697 | BD13: 1998 | BE13: =U37/AVERAGE(U34:U40) -> 0.96985012 | BF13: =U38/AVERAGE(U35:U41) -> 0.98689703 | BG13: =U39/AVERAGE(U36:U42) -> 1.0170349 | BH13: =U40/AVERAGE(U37:U43) -> 1.0232068 | BI13: 1 | BL13: 1998 | BM13: =V37/AVERAGE(V34:V40) -> 1.0122665 | BN13: =V38/AVERAGE(V35:V41) -> 1.0160493 | BO13: =V39/AVERAGE(V36:V42) -> 0.99732377 | BP13: =V40/AVERAGE(V37:V43) -> 0.98345277 | BQ13: 1 | BT13: 1998 | BU13: =W37/AVERAGE(W34:W40) -> 1.0046623 | BV13: =W38/AVERAGE(W35:W41) -> 1.0112237 | BW13: =W39/AVERAGE(W36:W42) -> 0.99571412 | BX13: =W40/AVERAGE(W37:W43) -> 0.99328665 | BY13: 1 | CB13: 1998 | CC13: =X37/AVERAGE(X34:X40) -> 1.0826441 | CD13: =X38/AVERAGE(X35:X41) -> 0.94794678 | CE13: =X39/AVERAGE(X36:X42) -> 0.96789394 | CF13: =X40/AVERAGE(X37:X43) -> 1.0262346 | CG13: 1 | CJ13: 1998 | CK13: =Y37/AVERAGE(Y34:Y40) -> 1.0422559 | CL13: =Y38/AVERAGE(Y35:Y41) -> 1.6847613 | CM13: =Y39/AVERAGE(Y36:Y42) -> 0.53582783 | CN13: =Y40/AVERAGE(Y37:Y43) -> -0.18833353 | CO13: 1 | CR13: 1998 | CS13: =AA37/AVERAGE(AA34:AA40) -> 0.9873404 | CT13: =AA38/AVERAGE(AA35:AA41) -> 1.003648 | CU13: =AA39/AVERAGE(AA36:AA42) -> 1.0059977 | CV13: =AA40/AVERAGE(AA37:AA43) -> 1.0078604 | CW13: 1 | CZ13: 1998 | DA13: =AB37/AVERAGE(AB34:AB40) -> 0.97128766 | DB13: =AB38/AVERAGE(AB35:AB41) -> 1.0182073 | DC13: =AB39/AVERAGE(AB36:AB42) -> 1.0319363 | DD13: =AB40/AVERAGE(AB37:AB43) -> 0.975981 | DE13: 1 | DH13: 1998 | DI13: =AC37/AVERAGE(AC34:AC40) -> 1.035933 | DJ13: =AC38/AVERAGE(AC35:AC41) -> 0.972764 | DK13: =AC39/AVERAGE(AC36:AC42) -> 0.97012888 | DL13: =AC40/AVERAGE(AC37:AC43) -> 1.0409141 | DM13: 1 | DP13: 1998 | DQ13: =AD37/AVERAGE(AD34:AD40) -> 1.6181042 | DR13: =AD38/AVERAGE(AD35:AD41) -> 0.71737778 | DS13: =AD39/AVERAGE(AD36:AD42) -> 0.88440928 | DT13: =AD40/AVERAGE(AD37:AD43) -> 0.97143115 | DU13: 1 | DX13: 1998 | DY13: =AE37/AVERAGE(AE34:AE40) -> 1.2004293 | DZ13: =AE38/AVERAGE(AE35:AE41) -> 1.0581935 | EA13: =AE39/AVERAGE(AE36:AE42) -> 0.9216331 | EB13: =AE40/AVERAGE(AE37:AE43) -> 0.88594041 | EC13: 1 | EF13: 1998 | EG13: =AF37/AVERAGE(AF34:AF40) -> 1.0747441 | EH13: =AF38/AVERAGE(AF35:AF41) -> 0.90650224 | EI13: =AF39/AVERAGE(AF36:AF42) -> 0.91474946 | EJ13: =AF40/AVERAGE(AF37:AF43) -> 1.0894075 | EK13: 1 | EN13: 1998 | EO13: =AG37/AVERAGE(AG34:AG40) -> 1.004567 | EP13: =AG38/AVERAGE(AG35:AG41) -> 0.99548079 | EQ13: =AG39/AVERAGE(AG36:AG42) -> 0.98738515 | ER13: =AG40/AVERAGE(AG37:AG43) -> 0.97124982 | ES13: 1 | EV13: 1998 | EW13: =AH37/AVERAGE(AH34:AH40) -> 1.1427883 | EX13: =AH38/AVERAGE(AH35:AH41) -> 0.88809588 | EY13: =AH39/AVERAGE(AH36:AH42) -> 0.98780094 | EZ13: =AH40/AVERAGE(AH37:AH43) -> 1.0470792 | FA13: 1 | FD13: 1998 | FE13: =AI37/AVERAGE(AI34:AI40) -> 1.0199343 | FF13: =AI38/AVERAGE(AI35:AI41) -> 1.0165939 | FG13: =AI39/AVERAGE(AI36:AI42) -> 1.0074094 | FH13: =AI40/AVERAGE(AI37:AI43) -> 1.0099713 | FI13: 1
A14: 1992 Q2 | B14: =LEFT(A14,4) -> 1992 | C14: =RIGHT(A14,2) -> Q2 | D14: =HAVERQ!C20 -> 215855 | E14: =HAVERQ!D20 -> 6339 | F14: =HAVERQ!E20 -> 80966 | G14: =HAVERQ!F20 -> 65950 | H14: =HAVERQ!G20 -> -3117 | I14: =HAVERQ!H20 -> 223 | J14: =HAVERQ!I20 -> 72581 | K14: =HAVERQ!J20 -> 69297 | L14: =HAVERQ!U20 -> #N/A | M14: =HAVERQ!V20 -> #N/A | N14: =HAVERQ!Y20 -> #N/A | O14: =HAVERQ!Z20 -> #N/A | P14: =HAVERQ!AA20 -> #N/A | Q14: =HAVERQ!AB20 -> #N/A | R14: =HAVERQ!AC20 -> #N/A | U14: =HAVERQ!M20 -> 210292 | V14: =HAVERQ!N20 -> 6407 | W14: =HAVERQ!O20 -> 80314 | X14: =HAVERQ!P20 -> 65948 | Y14: =HAVERQ!Q20 -> 31 | Z14: =HAVERQ!R20 -> 225 | AA14: =HAVERQ!S20 -> 71971 | AB14: =HAVERQ!T20 -> 70236 | AC14: =HAVERQ!W20 -> #N/A | AD14: =HAVERQ!X20 -> #N/A | AE14: =HAVERQ!AD20 -> #N/A | AF14: =HAVERQ!AE20 -> #N/A | AG14: =HAVERQ!AF20 -> #N/A | AH14: =HAVERQ!AG20 -> #N/A | AI14: =HAVERQ!AH20 -> #N/A | AL14: 1999 | AM14: =OFFSET($D$5, (ROW(D10)-1)*4,0)/OFFSET($U$5, (ROW(U10)-1)*4,0) -> 1.0258787 | AN14: =OFFSET($E$5, (ROW(E10)-1)*4,0)/OFFSET($V$5, (ROW(V10)-1)*4,0) -> 1 | AO14: =OFFSET(F$5, (ROW(F10)-1)*4,0)/OFFSET(W$5, (ROW(W10)-1)*4,0) -> 1.0025836 | AP14: =OFFSET(G$5, (ROW(G10)-1)*4,0)/OFFSET(X$5, (ROW(X10)-1)*4,0) -> 0.97366822 | AQ14: =OFFSET(H$5, (ROW(H10)-1)*4,0)/OFFSET(Y$5, (ROW(Y10)-1)*4,0) -> 0.61813538 | AR14: =OFFSET(I$5, (ROW(I10)-1)*4,0)/OFFSET(Z$5, (ROW(Z10)-1)*4,0) -> 1.0836707 | AS14: =OFFSET(J$5, (ROW(J10)-1)*4,0)/OFFSET(AA$5, (ROW(AA10)-1)*4,0) -> 1.0251532 | AT14: =OFFSET(K$5, (ROW(K10)-1)*4,0)/OFFSET(AB$5, (ROW(AB10)-1)*4,0) -> 1.0267522 | AU14: =OFFSET(L$5, (ROW(L10)-1)*4,0)/OFFSET(AC$5, (ROW(AC10)-1)*4,0) -> 1.0152185 | AV14: =OFFSET(M$5, (ROW(M10)-1)*4,0)/OFFSET(AD$5, (ROW(AD10)-1)*4,0) -> 0.72534661 | ... BA14: =OFFSET(R$5, (ROW(R10)-1)*4,0)/OFFSET(AI$5, (ROW(AI10)-1)*4,0) -> 0.99443453 | BD14: 1999 | BE14: =U41/AVERAGE(U38:U44) -> 0.96532814 | BF14: =U42/AVERAGE(U39:U45) -> 0.98868576 | BG14: =U43/AVERAGE(U40:U46) -> 1.0161883 | BH14: =U44/AVERAGE(U41:U47) -> 1.0273282 | BI14: 1 | BL14: 1999 | BM14: =V41/AVERAGE(V38:V44) -> 0.9734375 | BN14: =V42/AVERAGE(V39:V45) -> 1.0079112 | BO14: =V43/AVERAGE(V40:V46) -> 1.0012611 | BP14: =V44/AVERAGE(V41:V47) -> 1.0049221 | BQ14: 1 | BT14: 1999 | BU14: =W41/AVERAGE(W38:W44) -> 0.97988957 | BV14: =W42/AVERAGE(W39:W45) -> 1.0166102 | BW14: =W43/AVERAGE(W40:W46) -> 1.0062129 | BX14: =W44/AVERAGE(W41:W47) -> 1.0026441 | BY14: 1 | CB14: 1999 | CC14: =X41/AVERAGE(X38:X44) -> 1.0383838 | CD14: =X42/AVERAGE(X39:X45) -> 0.94074702 | CE14: =X43/AVERAGE(X40:X46) -> 0.97898683 | CF14: =X44/AVERAGE(X41:X47) -> 1.0081516 | CG14: 1 | CJ14: 1999 | CK14: =Y41/AVERAGE(Y38:Y44) -> 1.5985806 | CL14: =Y42/AVERAGE(Y39:Y45) -> -0.57957929 | CM14: =Y43/AVERAGE(Y40:Y46) -> 1.7181274 | CN14: =Y44/AVERAGE(Y41:Y47) -> 1.7033827 | CO14: 1 | CR14: 1999 | CS14: =AA41/AVERAGE(AA38:AA44) -> 0.95093562 | CT14: =AA42/AVERAGE(AA39:AA45) -> 0.96447844 | CU14: =AA43/AVERAGE(AA40:AA46) -> 1.0131854 | CV14: =AA44/AVERAGE(AA41:AA47) -> 1.0294988 | CW14: 1 | CZ14: 1999 | DA14: =AB41/AVERAGE(AB38:AB44) -> 0.96580151 | DB14: =AB42/AVERAGE(AB39:AB45) -> 0.99417541 | DC14: =AB43/AVERAGE(AB40:AB46) -> 1.0342186 | DD14: =AB44/AVERAGE(AB41:AB47) -> 1.0009666 | DE14: 1 | DH14: 1999 | DI14: =AC41/AVERAGE(AC38:AC44) -> 1.0054294 | DJ14: =AC42/AVERAGE(AC39:AC45) -> 0.95383309 | DK14: =AC43/AVERAGE(AC40:AC46) -> 0.98401974 | DL14: =AC44/AVERAGE(AC41:AC47) -> 1.0226992 | DM14: 1 | DP14: 1999 | DQ14: =AD41/AVERAGE(AD38:AD44) -> 1.4173537 | DR14: =AD42/AVERAGE(AD39:AD45) -> 0.77282269 | DS14: =AD43/AVERAGE(AD40:AD46) -> 0.87135471 | DT14: =AD44/AVERAGE(AD41:AD47) -> 0.9418201 | DU14: 1 | DX14: 1999 | DY14: =AE41/AVERAGE(AE38:AE44) -> 1.125321 | DZ14: =AE42/AVERAGE(AE39:AE45) -> 1.0732037 | EA14: =AE43/AVERAGE(AE40:AE46) -> 0.99935154 | EB14: =AE44/AVERAGE(AE41:AE47) -> 0.94626506 | EC14: 1 | EF14: 1999 | EG14: =AF41/AVERAGE(AF38:AF44) -> 1.0628752 | EH14: =AF42/AVERAGE(AF39:AF45) -> 0.89774745 | EI14: =AF43/AVERAGE(AF40:AF46) -> 0.93327496 | EJ14: =AF44/AVERAGE(AF41:AF47) -> 0.99098105 | EK14: 1 | EN14: 1999 | EO14: =AG41/AVERAGE(AG38:AG44) -> 0.9844412 | EP14: =AG42/AVERAGE(AG39:AG45) -> 0.99373449 | EQ14: =AG43/AVERAGE(AG40:AG46) -> 1.0103838 | ER14: =AG44/AVERAGE(AG41:AG47) -> 0.97928992 | ES14: 1 | EV14: 1999 | EW14: =AH41/AVERAGE(AH38:AH44) -> 1.0507866 | EX14: =AH42/AVERAGE(AH39:AH45) -> 0.88720725 | EY14: =AH43/AVERAGE(AH40:AH46) -> 0.99484203 | EZ14: =AH44/AVERAGE(AH41:AH47) -> 1.0674254 | FA14: 1 | FD14: 1999 | FE14: =AI41/AVERAGE(AI38:AI44) -> 0.99958226 | FF14: =AI42/AVERAGE(AI39:AI45) -> 0.97952049 | FG14: =AI43/AVERAGE(AI40:AI46) -> 0.97869005 | FH14: =AI44/AVERAGE(AI41:AI47) -> 0.99313501 | FI14: 1
A15: 1992 Q3 | B15: =LEFT(A15,4) -> 1992 | C15: =RIGHT(A15,2) -> Q3 | D15: =HAVERQ!C21 -> 217123 | E15: =HAVERQ!D21 -> 6366 | F15: =HAVERQ!E21 -> 80958 | G15: =HAVERQ!F21 -> 66215 | H15: =HAVERQ!G21 -> -1381 | I15: =HAVERQ!H21 -> -319 | J15: =HAVERQ!I21 -> 71131 | K15: =HAVERQ!J21 -> 68557 | L15: =HAVERQ!U21 -> #N/A | M15: =HAVERQ!V21 -> #N/A | N15: =HAVERQ!Y21 -> #N/A | O15: =HAVERQ!Z21 -> #N/A | P15: =HAVERQ!AA21 -> #N/A | Q15: =HAVERQ!AB21 -> #N/A | R15: =HAVERQ!AC21 -> #N/A | U15: =HAVERQ!M21 -> 224008 | V15: =HAVERQ!N21 -> 6431 | W15: =HAVERQ!O21 -> 80783 | X15: =HAVERQ!P21 -> 66209 | Y15: =HAVERQ!Q21 -> 939 | Z15: =HAVERQ!R21 -> -320 | AA15: =HAVERQ!S21 -> 71413 | AB15: =HAVERQ!T21 -> 70670 | AC15: =HAVERQ!W21 -> #N/A | AD15: =HAVERQ!X21 -> #N/A | AE15: =HAVERQ!AD21 -> #N/A | AF15: =HAVERQ!AE21 -> #N/A | AG15: =HAVERQ!AF21 -> #N/A | AH15: =HAVERQ!AG21 -> #N/A | AI15: =HAVERQ!AH21 -> #N/A | AL15: 2000 | AM15: =OFFSET($D$5, (ROW(D11)-1)*4,0)/OFFSET($U$5, (ROW(U11)-1)*4,0) -> 1.0266713 | AN15: =OFFSET($E$5, (ROW(E11)-1)*4,0)/OFFSET($V$5, (ROW(V11)-1)*4,0) -> 1 | AO15: =OFFSET(F$5, (ROW(F11)-1)*4,0)/OFFSET(W$5, (ROW(W11)-1)*4,0) -> 1.003879 | AP15: =OFFSET(G$5, (ROW(G11)-1)*4,0)/OFFSET(X$5, (ROW(X11)-1)*4,0) -> 0.96838971 | AQ15: =OFFSET(H$5, (ROW(H11)-1)*4,0)/OFFSET(Y$5, (ROW(Y11)-1)*4,0) -> 1.2623004 | AR15: =OFFSET(I$5, (ROW(I11)-1)*4,0)/OFFSET(Z$5, (ROW(Z11)-1)*4,0) -> 1.1594533 | AS15: =OFFSET(J$5, (ROW(J11)-1)*4,0)/OFFSET(AA$5, (ROW(AA11)-1)*4,0) -> 1.0157722 | AT15: =OFFSET(K$5, (ROW(K11)-1)*4,0)/OFFSET(AB$5, (ROW(AB11)-1)*4,0) -> 1.0189855 | AU15: =OFFSET(L$5, (ROW(L11)-1)*4,0)/OFFSET(AC$5, (ROW(AC11)-1)*4,0) -> 0.99834333 | AV15: =OFFSET(M$5, (ROW(M11)-1)*4,0)/OFFSET(AD$5, (ROW(AD11)-1)*4,0) -> 0.73667837 | ... BA15: =OFFSET(R$5, (ROW(R11)-1)*4,0)/OFFSET(AI$5, (ROW(AI11)-1)*4,0) -> 0.99552967 | BD15: 2000 | BE15: =U45/AVERAGE(U42:U48) -> 0.97052604 | BF15: =U46/AVERAGE(U43:U49) -> 0.98861102 | BG15: =U47/AVERAGE(U44:U50) -> 1.0176109 | BH15: =U48/AVERAGE(U45:U51) -> 1.0329035 | BI15: 1 | BL15: 2000 | BM15: =V45/AVERAGE(V42:V48) -> 0.99362441 | BN15: =V46/AVERAGE(V43:V49) -> 1.0032393 | BO15: =V47/AVERAGE(V44:V50) -> 1.0073572 | BP15: =V48/AVERAGE(V45:V51) -> 0.99755789 | BQ15: 1 | BT15: 2000 | BU15: =W45/AVERAGE(W42:W48) -> 0.98061566 | BV15: =W46/AVERAGE(W43:W49) -> 1.0091306 | BW15: =W47/AVERAGE(W44:W50) -> 1.0023956 | BX15: =W48/AVERAGE(W45:W51) -> 0.99437515 | BY15: 1 | CB15: 2000 | CC15: =X45/AVERAGE(X42:X48) -> 1.0434169 | CD15: =X46/AVERAGE(X43:X49) -> 1.0041317 | CE15: =X47/AVERAGE(X44:X50) -> 0.94946581 | CF15: =X48/AVERAGE(X45:X51) -> 1.0134546 | CG15: 1 | CJ15: 2000 | CK15: =Y45/AVERAGE(Y42:Y48) -> 2.8255952 | CL15: =Y46/AVERAGE(Y43:Y49) -> -1.5087342 | CM15: =Y47/AVERAGE(Y44:Y50) -> 5.0675439 | CN15: =Y48/AVERAGE(Y45:Y51) -> -2.6435573 | CO15: 1 | CR15: 2000 | CS15: =AA45/AVERAGE(AA42:AA48) -> 0.9829476 | CT15: =AA46/AVERAGE(AA43:AA49) -> 1.003898 | CU15: =AA47/AVERAGE(AA44:AA50) -> 1.0010846 | CV15: =AA48/AVERAGE(AA45:AA51) -> 1.0321064 | CW15: 1 | CZ15: 2000 | DA15: =AB45/AVERAGE(AB42:AB48) -> 0.96815884 | DB15: =AB46/AVERAGE(AB43:AB49) -> 0.99608108 | DC15: =AB47/AVERAGE(AB44:AB50) -> 1.020011 | DD15: =AB48/AVERAGE(AB45:AB51) -> 1.0121643 | DE15: 1 | DH15: 2000 | DI15: =AC45/AVERAGE(AC42:AC48) -> 1.0052792 | DJ15: =AC46/AVERAGE(AC43:AC49) -> 1.0359158 | DK15: =AC47/AVERAGE(AC44:AC50) -> 0.94363106 | DL15: =AC48/AVERAGE(AC45:AC51) -> 1.0432393 | DM15: 1 | DP15: 2000 | DQ15: =AD45/AVERAGE(AD42:AD48) -> 1.3868069 | DR15: =AD46/AVERAGE(AD43:AD49) -> 0.74542202 | DS15: =AD47/AVERAGE(AD44:AD50) -> 0.84529547 | DT15: =AD48/AVERAGE(AD45:AD51) -> 0.89635888 | DU15: 1 | DX15: 2000 | DY15: =AE45/AVERAGE(AE42:AE48) -> 0.97967162 | DZ15: =AE46/AVERAGE(AE43:AE49) -> 1.1024383 | EA15: =AE47/AVERAGE(AE44:AE50) -> 0.84810903 | EB15: =AE48/AVERAGE(AE45:AE51) -> 0.88003057 | EC15: 1 | EF15: 2000 | EG15: =AF45/AVERAGE(AF42:AF48) -> 1.05198 | EH15: =AF46/AVERAGE(AF43:AF49) -> 1.1105417 | EI15: =AF47/AVERAGE(AF44:AF50) -> 0.90731679 | EJ15: =AF48/AVERAGE(AF45:AF51) -> 1.0539949 | EK15: 1 | EN15: 2000 | EO15: =AG45/AVERAGE(AG42:AG48) -> 1.0408329 | EP15: =AG46/AVERAGE(AG43:AG49) -> 1.018938 | EQ15: =AG47/AVERAGE(AG44:AG50) -> 1.0191953 | ER15: =AG48/AVERAGE(AG45:AG51) -> 0.98425686 | ES15: 1 | EV15: 2000 | EW15: =AH45/AVERAGE(AH42:AH48) -> 1.0798817 | EX15: =AH46/AVERAGE(AH43:AH49) -> 0.88217809 | EY15: =AH47/AVERAGE(AH44:AH50) -> 0.93635279 | EZ15: =AH48/AVERAGE(AH45:AH51) -> 1.0376308 | FA15: 1 | FD15: 2000 | FE15: =AI45/AVERAGE(AI42:AI48) -> 1.010946 | FF15: =AI46/AVERAGE(AI43:AI49) -> 1.0257977 | FG15: =AI47/AVERAGE(AI44:AI50) -> 1.0031289 | FH15: =AI48/AVERAGE(AI45:AI51) -> 1.0245716 | FI15: 1
A16: 1992 Q4 | B16: =LEFT(A16,4) -> 1992 | C16: =RIGHT(A16,2) -> Q4 | D16: =HAVERQ!C22 -> 217528 | E16: =HAVERQ!D22 -> 6454 | F16: =HAVERQ!E22 -> 81332 | G16: =HAVERQ!F22 -> 64649 | H16: =HAVERQ!G22 -> 327 | I16: =HAVERQ!H22 -> 1245 | J16: =HAVERQ!I22 -> 73975 | K16: =HAVERQ!J22 -> 69367 | L16: =HAVERQ!U22 -> #N/A | M16: =HAVERQ!V22 -> #N/A | N16: =HAVERQ!Y22 -> #N/A | O16: =HAVERQ!Z22 -> #N/A | P16: =HAVERQ!AA22 -> #N/A | Q16: =HAVERQ!AB22 -> #N/A | R16: =HAVERQ!AC22 -> #N/A | U16: =HAVERQ!M22 -> 226131 | V16: =HAVERQ!N22 -> 6418 | W16: =HAVERQ!O22 -> 81536 | X16: =HAVERQ!P22 -> 64644 | Y16: =HAVERQ!Q22 -> -3928 | Z16: =HAVERQ!R22 -> 1248 | AA16: =HAVERQ!S22 -> 76649 | AB16: =HAVERQ!T22 -> 67996 | AC16: =HAVERQ!W22 -> #N/A | AD16: =HAVERQ!X22 -> #N/A | AE16: =HAVERQ!AD22 -> #N/A | AF16: =HAVERQ!AE22 -> #N/A | AG16: =HAVERQ!AF22 -> #N/A | AH16: =HAVERQ!AG22 -> #N/A | AI16: =HAVERQ!AH22 -> #N/A | AL16: 2001 | AM16: =OFFSET($D$5, (ROW(D12)-1)*4,0)/OFFSET($U$5, (ROW(U12)-1)*4,0) -> 1.0278527 | AN16: =OFFSET($E$5, (ROW(E12)-1)*4,0)/OFFSET($V$5, (ROW(V12)-1)*4,0) -> 1 | AO16: =OFFSET(F$5, (ROW(F12)-1)*4,0)/OFFSET(W$5, (ROW(W12)-1)*4,0) -> 1.0034438 | AP16: =OFFSET(G$5, (ROW(G12)-1)*4,0)/OFFSET(X$5, (ROW(X12)-1)*4,0) -> 0.93909439 | AQ16: =OFFSET(H$5, (ROW(H12)-1)*4,0)/OFFSET(Y$5, (ROW(Y12)-1)*4,0) -> 2.8211144 | AR16: =OFFSET(I$5, (ROW(I12)-1)*4,0)/OFFSET(Z$5, (ROW(Z12)-1)*4,0) -> 1.2517986 | AS16: =OFFSET(J$5, (ROW(J12)-1)*4,0)/OFFSET(AA$5, (ROW(AA12)-1)*4,0) -> 1.0172993 | AT16: =OFFSET(K$5, (ROW(K12)-1)*4,0)/OFFSET(AB$5, (ROW(AB12)-1)*4,0) -> 1.0158251 | AU16: =OFFSET(L$5, (ROW(L12)-1)*4,0)/OFFSET(AC$5, (ROW(AC12)-1)*4,0) -> 0.93475857 | AV16: =OFFSET(M$5, (ROW(M12)-1)*4,0)/OFFSET(AD$5, (ROW(AD12)-1)*4,0) -> 0.83503889 | ... BA16: =OFFSET(R$5, (ROW(R12)-1)*4,0)/OFFSET(AI$5, (ROW(AI12)-1)*4,0) -> 0.99436562 | BD16: 2001 | BE16: =U49/AVERAGE(U46:U52) -> 0.96618175 | BF16: =U50/AVERAGE(U47:U53) -> 0.98473176 | BG16: =U51/AVERAGE(U48:U54) -> 1.0164701 | BH16: =U52/AVERAGE(U49:U55) -> 1.0362511 | BI16: 1 | BL16: 2001 | BM16: =V49/AVERAGE(V46:V52) -> 0.98819316 | BN16: =V50/AVERAGE(V47:V53) -> 1.0017784 | BO16: =V51/AVERAGE(V48:V54) -> 1.0104259 | BP16: =V52/AVERAGE(V49:V55) -> 1.0059272 | BQ16: 1 | BT16: 2001 | BU16: =W49/AVERAGE(W46:W52) -> 1.0078425 | BV16: =W50/AVERAGE(W47:W53) -> 0.98862227 | BW16: =W51/AVERAGE(W48:W54) -> 0.99941408 | BX16: =W52/AVERAGE(W49:W55) -> 1.0090383 | BY16: 1 | CB16: 2001 | CC16: =X49/AVERAGE(X46:X52) -> 1.058215 | CD16: =X50/AVERAGE(X47:X53) -> 0.98563098 | CE16: =X51/AVERAGE(X48:X54) -> 0.99097403 | CF16: =X52/AVERAGE(X49:X55) -> 0.99585984 | CG16: 1 | CJ16: 2001 | CK16: =Y49/AVERAGE(Y46:Y52) -> -1.0831947 | CL16: =Y50/AVERAGE(Y47:Y53) -> 1.8435916 | CM16: =Y51/AVERAGE(Y48:Y54) -> 11.201004 | CN16: =Y52/AVERAGE(Y49:Y55) -> -1.0679727 | CO16: 1 | CR16: 2001 | CS16: =AA49/AVERAGE(AA46:AA52) -> 1.0292419 | CT16: =AA50/AVERAGE(AA47:AA53) -> 1.0037576 | CU16: =AA51/AVERAGE(AA48:AA54) -> 0.97199522 | CV16: =AA52/AVERAGE(AA49:AA55) -> 0.99504426 | CW16: 1 | CZ16: 2001 | DA16: =AB49/AVERAGE(AB46:AB52) -> 1.0062343 | DB16: =AB50/AVERAGE(AB47:AB53) -> 1.0214547 | DC16: =AB51/AVERAGE(AB48:AB54) -> 1.0060826 | DD16: =AB52/AVERAGE(AB49:AB55) -> 0.96699306 | DE16: 1 | DH16: 2001 | DI16: =AC49/AVERAGE(AC46:AC52) -> 1.0076782 | DJ16: =AC50/AVERAGE(AC47:AC53) -> 1.0157474 | DK16: =AC51/AVERAGE(AC48:AC54) -> 0.99278244 | DL16: =AC52/AVERAGE(AC49:AC55) -> 1.0169775 | DM16: 1 | DP16: 2001 | DQ16: =AD49/AVERAGE(AD46:AD52) -> 1.4753434 | DR16: =AD50/AVERAGE(AD47:AD53) -> 0.82723859 | DS16: =AD51/AVERAGE(AD48:AD54) -> 0.93926676 | DT16: =AD52/AVERAGE(AD49:AD55) -> 0.9564244 | DU16: 1 | DX16: 2001 | DY16: =AE49/AVERAGE(AE46:AE52) -> 0.89038481 | DZ16: =AE50/AVERAGE(AE47:AE53) -> 1.4187786 | EA16: =AE51/AVERAGE(AE48:AE54) -> 1.0244545 | EB16: =AE52/AVERAGE(AE49:AE55) -> 0.78702749 | EC16: 1 | EF16: 2001 | EG16: =AF49/AVERAGE(AF46:AF52) -> 1.0414779 | EH16: =AF50/AVERAGE(AF47:AF53) -> 0.90195303 | EI16: =AF51/AVERAGE(AF48:AF54) -> 0.9574589 | EJ16: =AF52/AVERAGE(AF49:AF55) -> 1.0937867 | EK16: 1 | EN16: 2001 | EO16: =AG49/AVERAGE(AG46:AG52) -> 1.0168277 | EP16: =AG50/AVERAGE(AG47:AG53) -> 0.95521181 | EQ16: =AG51/AVERAGE(AG48:AG54) -> 1.0031053 | ER16: =AG52/AVERAGE(AG49:AG55) -> 0.96223799 | ES16: 1 | EV16: 2001 | EW16: =AH49/AVERAGE(AH46:AH52) -> 1.1182926 | EX16: =AH50/AVERAGE(AH47:AH53) -> 0.98204612 | EY16: =AH51/AVERAGE(AH48:AH54) -> 1.0184792 | EZ16: =AH52/AVERAGE(AH49:AH55) -> 0.98477444 | FA16: 1 | FD16: 2001 | FE16: =AI49/AVERAGE(AI46:AI52) -> 0.98119761 | FF16: =AI50/AVERAGE(AI47:AI53) -> 0.98204646 | FG16: =AI51/AVERAGE(AI48:AI54) -> 0.995741 | FH16: =AI52/AVERAGE(AI49:AI55) -> 1.0210731 | FI16: 1
A17: 1993 Q1 | B17: =LEFT(A17,4) -> 1993 | C17: =RIGHT(A17,2) -> Q1 | D17: =HAVERQ!C23 -> 219343 | E17: =HAVERQ!D23 -> 6753 | F17: =HAVERQ!E23 -> 80611 | G17: =HAVERQ!F23 -> 66224 | H17: =HAVERQ!G23 -> -564 | I17: =HAVERQ!H23 -> 450 | J17: =HAVERQ!I23 -> 74840 | K17: =HAVERQ!J23 -> 69932 | L17: =HAVERQ!U23 -> #N/A | M17: =HAVERQ!V23 -> #N/A | N17: =HAVERQ!Y23 -> #N/A | O17: =HAVERQ!Z23 -> #N/A | P17: =HAVERQ!AA23 -> #N/A | Q17: =HAVERQ!AB23 -> #N/A | R17: =HAVERQ!AC23 -> #N/A | U17: =HAVERQ!M23 -> 210138 | V17: =HAVERQ!N23 -> 6688 | W17: =HAVERQ!O23 -> 81036 | X17: =HAVERQ!P23 -> 66230 | Y17: =HAVERQ!Q23 -> -4872 | Z17: =HAVERQ!R23 -> 452 | AA17: =HAVERQ!S23 -> 72828 | AB17: =HAVERQ!T23 -> 67474 | AC17: =HAVERQ!W23 -> #N/A | AD17: =HAVERQ!X23 -> #N/A | AE17: =HAVERQ!AD23 -> #N/A | AF17: =HAVERQ!AE23 -> #N/A | AG17: =HAVERQ!AF23 -> #N/A | AH17: =HAVERQ!AG23 -> #N/A | AI17: =HAVERQ!AH23 -> #N/A | AL17: 2002 | AM17: =OFFSET($D$5, (ROW(D13)-1)*4,0)/OFFSET($U$5, (ROW(U13)-1)*4,0) -> 1.0294432 | AN17: =OFFSET($E$5, (ROW(E13)-1)*4,0)/OFFSET($V$5, (ROW(V13)-1)*4,0) -> 1 | AO17: =OFFSET(F$5, (ROW(F13)-1)*4,0)/OFFSET(W$5, (ROW(W13)-1)*4,0) -> 1.0038825 | AP17: =OFFSET(G$5, (ROW(G13)-1)*4,0)/OFFSET(X$5, (ROW(X13)-1)*4,0) -> 0.97685662 | AQ17: =OFFSET(H$5, (ROW(H13)-1)*4,0)/OFFSET(Y$5, (ROW(Y13)-1)*4,0) -> -0.22796143 | AR17: =OFFSET(I$5, (ROW(I13)-1)*4,0)/OFFSET(Z$5, (ROW(Z13)-1)*4,0) -> 1.0876979 | AS17: =OFFSET(J$5, (ROW(J13)-1)*4,0)/OFFSET(AA$5, (ROW(AA13)-1)*4,0) -> 1.0328199 | AT17: =OFFSET(K$5, (ROW(K13)-1)*4,0)/OFFSET(AB$5, (ROW(AB13)-1)*4,0) -> 1.0319196 | AU17: =OFFSET(L$5, (ROW(L13)-1)*4,0)/OFFSET(AC$5, (ROW(AC13)-1)*4,0) -> 1.0046415 | AV17: =OFFSET(M$5, (ROW(M13)-1)*4,0)/OFFSET(AD$5, (ROW(AD13)-1)*4,0) -> 0.81039755 | ... BA17: =OFFSET(R$5, (ROW(R13)-1)*4,0)/OFFSET(AI$5, (ROW(AI13)-1)*4,0) -> 0.99159719 | BD17: 2002 | BE17: =U53/AVERAGE(U50:U56) -> 0.96658272 | BF17: =U54/AVERAGE(U51:U57) -> 0.98603833 | BG17: =U55/AVERAGE(U52:U58) -> 1.0110011 | BH17: =U56/AVERAGE(U53:U59) -> 1.0293556 | BI17: 1 | BL17: 2002 | BM17: =V53/AVERAGE(V50:V56) -> 0.99016235 | BN17: =V54/AVERAGE(V51:V57) -> 0.99171037 | BO17: =V55/AVERAGE(V52:V58) -> 1.0048651 | BP17: =V56/AVERAGE(V53:V59) -> 1.0042515 | BQ17: 1 | BT17: 2002 | BU17: =W53/AVERAGE(W50:W56) -> 0.993049 | BV17: =W54/AVERAGE(W51:W57) -> 1.005651 | BW17: =W55/AVERAGE(W52:W58) -> 1.0045 | BX17: =W56/AVERAGE(W53:W59) -> 0.99779755 | BY17: 1 | CB17: 2002 | CC17: =X53/AVERAGE(X50:X56) -> 1.0016975 | CD17: =X54/AVERAGE(X51:X57) -> 0.95698137 | CE17: =X55/AVERAGE(X52:X58) -> 0.97630488 | CF17: =X56/AVERAGE(X53:X59) -> 1.0548146 | CG17: 1 | CJ17: 2002 | CK17: =Y53/AVERAGE(Y50:Y56) -> 1.075328 | CL17: =Y54/AVERAGE(Y51:Y57) -> 0.36226017 | CM17: =Y55/AVERAGE(Y52:Y58) -> -12.601496 | CN17: =Y56/AVERAGE(Y53:Y59) -> -3.6569116 | CO17: 1 | CR17: 2002 | CS17: =AA53/AVERAGE(AA50:AA56) -> 0.96671792 | CT17: =AA54/AVERAGE(AA51:AA57) -> 1.0326307 | CU17: =AA55/AVERAGE(AA52:AA58) -> 1.0194816 | CV17: =AA56/AVERAGE(AA53:AA59) -> 0.9885239 | CW17: 1 | CZ17: 2002 | DA17: =AB53/AVERAGE(AB50:AB56) -> 0.96426376 | DB17: =AB54/AVERAGE(AB51:AB57) -> 1.0392465 | DC17: =AB55/AVERAGE(AB52:AB58) -> 1.0363739 | DD17: =AB56/AVERAGE(AB53:AB59) -> 0.9959753 | DE17: 1 | DH17: 2002 | DI17: =AC53/AVERAGE(AC50:AC56) -> 0.96160706 | DJ17: =AC54/AVERAGE(AC51:AC57) -> 0.97522647 | DK17: =AC55/AVERAGE(AC52:AC58) -> 0.97450143 | DL17: =AC56/AVERAGE(AC53:AC59) -> 1.0737084 | DM17: 1 | DP17: 2002 | DQ17: =AD53/AVERAGE(AD50:AD56) -> 1.2463053 | DR17: =AD54/AVERAGE(AD51:AD57) -> 0.82275714 | DS17: =AD55/AVERAGE(AD52:AD58) -> 0.90680818 | DT17: =AD56/AVERAGE(AD53:AD59) -> 0.96084682 | DU17: 1 | DX17: 2002 | DY17: =AE53/AVERAGE(AE50:AE56) -> 0.86270023 | DZ17: =AE54/AVERAGE(AE51:AE57) -> 1.2607503 | EA17: =AE55/AVERAGE(AE52:AE58) -> 1.0550807 | EB17: =AE56/AVERAGE(AE53:AE59) -> 0.94677322 | EC17: 1 | EF17: 2002 | EG17: =AF53/AVERAGE(AF50:AF56) -> 1.0456579 | EH17: =AF54/AVERAGE(AF51:AF57) -> 0.92689821 | EI17: =AF55/AVERAGE(AF52:AF58) -> 0.95636911 | EJ17: =AF56/AVERAGE(AF53:AF59) -> 1.1187552 | EK17: 1 | EN17: 2002 | EO17: =AG53/AVERAGE(AG50:AG56) -> 1.0153746 | EP17: =AG54/AVERAGE(AG51:AG57) -> 0.96677302 | EQ17: =AG55/AVERAGE(AG52:AG58) -> 0.99874392 | ER17: =AG56/AVERAGE(AG53:AG59) -> 1.0611289 | ES17: 1 | EV17: 2002 | EW17: =AH53/AVERAGE(AH50:AH56) -> 0.98862133 | EX17: =AH54/AVERAGE(AH51:AH57) -> 0.8743809 | EY17: =AH55/AVERAGE(AH52:AH58) -> 0.96757465 | EZ17: =AH56/AVERAGE(AH53:AH59) -> 1.0896268 | FA17: 1 | FD17: 2002 | FE17: =AI53/AVERAGE(AI50:AI56) -> 1.0056492 | FF17: =AI54/AVERAGE(AI51:AI57) -> 0.96816413 | FG17: =AI55/AVERAGE(AI52:AI58) -> 0.98414403 | FH17: =AI56/AVERAGE(AI53:AI59) -> 0.9907661 | FI17: 1
A18: 1993 Q2 | B18: =LEFT(A18,4) -> 1993 | C18: =RIGHT(A18,2) -> Q2 | D18: =HAVERQ!C24 -> 219780 | E18: =HAVERQ!D24 -> 7329 | F18: =HAVERQ!E24 -> 79936 | G18: =HAVERQ!F24 -> 65856 | H18: =HAVERQ!G24 -> 1920 | I18: =HAVERQ!H24 -> 3309 | J18: =HAVERQ!I24 -> 73811 | K18: =HAVERQ!J24 -> 69387 | L18: =HAVERQ!U24 -> #N/A | M18: =HAVERQ!V24 -> #N/A | N18: =HAVERQ!Y24 -> #N/A | O18: =HAVERQ!Z24 -> #N/A | P18: =HAVERQ!AA24 -> #N/A | Q18: =HAVERQ!AB24 -> #N/A | R18: =HAVERQ!AC24 -> #N/A | U18: =HAVERQ!M24 -> 213279 | V18: =HAVERQ!N24 -> 7351 | W18: =HAVERQ!O24 -> 79536 | X18: =HAVERQ!P24 -> 65855 | Y18: =HAVERQ!Q24 -> 3419 | Z18: =HAVERQ!R24 -> 3318 | AA18: =HAVERQ!S24 -> 72914 | AB18: =HAVERQ!T24 -> 70748 | AC18: =HAVERQ!W24 -> #N/A | AD18: =HAVERQ!X24 -> #N/A | AE18: =HAVERQ!AD24 -> #N/A | AF18: =HAVERQ!AE24 -> #N/A | AG18: =HAVERQ!AF24 -> #N/A | AH18: =HAVERQ!AG24 -> #N/A | AI18: =HAVERQ!AH24 -> #N/A | AL18: 2003 | AM18: =OFFSET($D$5, (ROW(D14)-1)*4,0)/OFFSET($U$5, (ROW(U14)-1)*4,0) -> 1.0313986 | AN18: =OFFSET($E$5, (ROW(E14)-1)*4,0)/OFFSET($V$5, (ROW(V14)-1)*4,0) -> 1 | AO18: =OFFSET(F$5, (ROW(F14)-1)*4,0)/OFFSET(W$5, (ROW(W14)-1)*4,0) -> 0.9986678 | AP18: =OFFSET(G$5, (ROW(G14)-1)*4,0)/OFFSET(X$5, (ROW(X14)-1)*4,0) -> 0.97821031 | AQ18: =OFFSET(H$5, (ROW(H14)-1)*4,0)/OFFSET(Y$5, (ROW(Y14)-1)*4,0) -> 3.8612245 | AR18: =OFFSET(I$5, (ROW(I14)-1)*4,0)/OFFSET(Z$5, (ROW(Z14)-1)*4,0) -> 1.0795031 | AS18: =OFFSET(J$5, (ROW(J14)-1)*4,0)/OFFSET(AA$5, (ROW(AA14)-1)*4,0) -> 1.0292221 | AT18: =OFFSET(K$5, (ROW(K14)-1)*4,0)/OFFSET(AB$5, (ROW(AB14)-1)*4,0) -> 1.0279677 | AU18: =OFFSET(L$5, (ROW(L14)-1)*4,0)/OFFSET(AC$5, (ROW(AC14)-1)*4,0) -> 1.0127745 | AV18: =OFFSET(M$5, (ROW(M14)-1)*4,0)/OFFSET(AD$5, (ROW(AD14)-1)*4,0) -> 0.81675281 | ... BA18: =OFFSET(R$5, (ROW(R14)-1)*4,0)/OFFSET(AI$5, (ROW(AI14)-1)*4,0) -> 0.98941504 | BD18: 2003 | BE18: =U57/AVERAGE(U54:U60) -> 0.96421938 | BF18: =U58/AVERAGE(U55:U61) -> 0.99413968 | BG18: =U59/AVERAGE(U56:U62) -> 1.0148727 | BH18: =U60/AVERAGE(U57:U63) -> 1.0316222 | BI18: 1 | BL18: 2003 | BM18: =V57/AVERAGE(V54:V60) -> 0.99235157 | BN18: =V58/AVERAGE(V55:V61) -> 0.99159793 | BO18: =V59/AVERAGE(V56:V62) -> 1.0049712 | BP18: =V60/AVERAGE(V57:V63) -> 1.0099704 | BQ18: 1 | BT18: 2003 | BU18: =W57/AVERAGE(W54:W60) -> 0.98809305 | BV18: =W58/AVERAGE(W55:W61) -> 0.99794461 | BW18: =W59/AVERAGE(W56:W62) -> 1.0004506 | BX18: =W60/AVERAGE(W57:W63) -> 1.0100966 | BY18: 1 | CB18: 2003 | CC18: =X57/AVERAGE(X54:X60) -> 1.0720867 | CD18: =X58/AVERAGE(X55:X61) -> 0.95140869 | CE18: =X59/AVERAGE(X56:X62) -> 0.95959526 | CF18: =X60/AVERAGE(X57:X63) -> 1.0033616 | CG18: 1 | CJ18: 2003 | CK18: =Y57/AVERAGE(Y54:Y60) -> 76.5625 | CL18: =Y58/AVERAGE(Y55:Y61) -> 1.0282486 | CM18: =Y59/AVERAGE(Y56:Y62) -> -4.0154083 | CN18: =Y60/AVERAGE(Y57:Y63) -> -8.1089109 | CO18: 1 | CR18: 2003 | CS18: =AA57/AVERAGE(AA54:AA60) -> 0.98365976 | CT18: =AA58/AVERAGE(AA55:AA61) -> 0.99808624 | CU18: =AA59/AVERAGE(AA56:AA62) -> 0.99517328 | CV18: =AA60/AVERAGE(AA57:AA63) -> 1.0148709 | CW18: 1 | CZ18: 2003 | DA18: =AB57/AVERAGE(AB54:AB60) -> 0.96639662 | DB18: =AB58/AVERAGE(AB55:AB61) -> 0.98644759 | DC18: =AB59/AVERAGE(AB56:AB62) -> 1.0177996 | DD18: =AB60/AVERAGE(AB57:AB63) -> 0.99647787 | DE18: 1 | DH18: 2003 | DI18: =AC57/AVERAGE(AC54:AC60) -> 1.0392373 | DJ18: =AC58/AVERAGE(AC55:AC61) -> 0.97287729 | DK18: =AC59/AVERAGE(AC56:AC62) -> 0.96955754 | DL18: =AC60/AVERAGE(AC57:AC63) -> 1.0413067 | DM18: 1 | DP18: 2003 | DQ18: =AD57/AVERAGE(AD54:AD60) -> 1.3848406 | DR18: =AD58/AVERAGE(AD55:AD61) -> 0.83559902 | DS18: =AD59/AVERAGE(AD56:AD62) -> 0.85590835 | DT18: =AD60/AVERAGE(AD57:AD63) -> 0.86174038 | DU18: 1 | DX18: 2003 | DY18: =AE57/AVERAGE(AE54:AE60) -> 0.94559617 | DZ18: =AE58/AVERAGE(AE55:AE61) -> 1.06326 | EA18: =AE59/AVERAGE(AE56:AE62) -> 1.0501006 | EB18: =AE60/AVERAGE(AE57:AE63) -> 0.89650624 | EC18: 1 | EF18: 2003 | EG18: =AF57/AVERAGE(AF54:AF60) -> 1.1256907 | EH18: =AF58/AVERAGE(AF55:AF61) -> 0.8704421 | EI18: =AF59/AVERAGE(AF56:AF62) -> 0.91814277 | EJ18: =AF60/AVERAGE(AF57:AF63) -> 1.0046731 | EK18: 1 | EN18: 2003 | EO18: =AG57/AVERAGE(AG54:AG60) -> 1.0156308 | EP18: =AG58/AVERAGE(AG55:AG61) -> 0.95652433 | EQ18: =AG59/AVERAGE(AG56:AG62) -> 0.99613792 | ER18: =AG60/AVERAGE(AG57:AG63) -> 1.026428 | ES18: 1 | EV18: 2003 | EW18: =AH57/AVERAGE(AH54:AH60) -> 1.1478041 | EX18: =AH58/AVERAGE(AH55:AH61) -> 0.90802079 | EY18: =AH59/AVERAGE(AH56:AH62) -> 0.91149956 | EZ18: =AH60/AVERAGE(AH57:AH63) -> 1.0125871 | FA18: 1 | FD18: 2003 | FE18: =AI57/AVERAGE(AI54:AI60) -> 1.0162934 | FF18: =AI58/AVERAGE(AI55:AI61) -> 1.0197785 | FG18: =AI59/AVERAGE(AI56:AI62) -> 1.0039828 | FH18: =AI60/AVERAGE(AI57:AI63) -> 1.0062496 | FI18: 1
A19: 1993 Q3 | B19: =LEFT(A19,4) -> 1993 | C19: =RIGHT(A19,2) -> Q3 | D19: =HAVERQ!C25 -> 223611 | E19: =HAVERQ!D25 -> 7289 | F19: =HAVERQ!E25 -> 80863 | G19: =HAVERQ!F25 -> 65937 | H19: =HAVERQ!G25 -> 305 | I19: =HAVERQ!H25 -> -2681 | J19: =HAVERQ!I25 -> 75100 | K19: =HAVERQ!J25 -> 70897 | L19: =HAVERQ!U25 -> #N/A | M19: =HAVERQ!V25 -> #N/A | N19: =HAVERQ!Y25 -> #N/A | O19: =HAVERQ!Z25 -> #N/A | P19: =HAVERQ!AA25 -> #N/A | Q19: =HAVERQ!AB25 -> #N/A | R19: =HAVERQ!AC25 -> #N/A | U19: =HAVERQ!M25 -> 230716 | V19: =HAVERQ!N25 -> 7369 | W19: =HAVERQ!O25 -> 80626 | X19: =HAVERQ!P25 -> 65933 | Y19: =HAVERQ!Q25 -> 840 | Z19: =HAVERQ!R25 -> -2689 | AA19: =HAVERQ!S25 -> 76331 | AB19: =HAVERQ!T25 -> 73046 | AC19: =HAVERQ!W25 -> #N/A | AD19: =HAVERQ!X25 -> #N/A | AE19: =HAVERQ!AD25 -> #N/A | AF19: =HAVERQ!AE25 -> #N/A | AG19: =HAVERQ!AF25 -> #N/A | AH19: =HAVERQ!AG25 -> #N/A | AI19: =HAVERQ!AH25 -> #N/A | AL19: 2004 | AM19: =OFFSET($D$5, (ROW(D15)-1)*4,0)/OFFSET($U$5, (ROW(U15)-1)*4,0) -> 1.031243 | AN19: =OFFSET($E$5, (ROW(E15)-1)*4,0)/OFFSET($V$5, (ROW(V15)-1)*4,0) -> 1 | AO19: =OFFSET(F$5, (ROW(F15)-1)*4,0)/OFFSET(W$5, (ROW(W15)-1)*4,0) -> 0.99598682 | AP19: =OFFSET(G$5, (ROW(G15)-1)*4,0)/OFFSET(X$5, (ROW(X15)-1)*4,0) -> 0.96807424 | AQ19: =OFFSET(H$5, (ROW(H15)-1)*4,0)/OFFSET(Y$5, (ROW(Y15)-1)*4,0) -> -1.5453575 | AR19: =OFFSET(I$5, (ROW(I15)-1)*4,0)/OFFSET(Z$5, (ROW(Z15)-1)*4,0) -> 1.0704522 | AS19: =OFFSET(J$5, (ROW(J15)-1)*4,0)/OFFSET(AA$5, (ROW(AA15)-1)*4,0) -> 1.0258615 | AT19: =OFFSET(K$5, (ROW(K15)-1)*4,0)/OFFSET(AB$5, (ROW(AB15)-1)*4,0) -> 1.0198833 | AU19: =OFFSET(L$5, (ROW(L15)-1)*4,0)/OFFSET(AC$5, (ROW(AC15)-1)*4,0) -> 0.99712468 | AV19: =OFFSET(M$5, (ROW(M15)-1)*4,0)/OFFSET(AD$5, (ROW(AD15)-1)*4,0) -> 0.81686345 | ... BA19: =OFFSET(R$5, (ROW(R15)-1)*4,0)/OFFSET(AI$5, (ROW(AI15)-1)*4,0) -> 0.98675697 | BD19: 2004 | BE19: =U61/AVERAGE(U58:U64) -> 0.9638713 | BF19: =U62/AVERAGE(U59:U65) -> 0.99080517 | BG19: =U63/AVERAGE(U60:U66) -> 1.0135888 | BH19: =U64/AVERAGE(U61:U67) -> 1.0292323 | BI19: 1 | BL19: 2004 | BM19: =V61/AVERAGE(V58:V64) -> 1.0122458 | BN19: =V62/AVERAGE(V59:V65) -> 0.99127914 | BO19: =V63/AVERAGE(V60:V66) -> 1.0068733 | BP19: =V64/AVERAGE(V61:V67) -> 1.0099824 | BQ19: 1 | BT19: 2004 | BU19: =W61/AVERAGE(W58:W64) -> 1.0047459 | BV19: =W62/AVERAGE(W59:W65) -> 1.0000093 | BW19: =W63/AVERAGE(W60:W66) -> 0.99854979 | BX19: =W64/AVERAGE(W61:W67) -> 1.0037683 | BY19: 1 | CB19: 2004 | CC19: =X61/AVERAGE(X58:X64) -> 1.0490218 | CD19: =X62/AVERAGE(X59:X65) -> 0.94801388 | CE19: =X63/AVERAGE(X60:X66) -> 0.97593999 | CF19: =X64/AVERAGE(X61:X67) -> 1.0071372 | CG19: 1 | CJ19: 2004 | CK19: =Y61/AVERAGE(Y58:Y64) -> 14.320961 | CL19: =Y62/AVERAGE(Y59:Y65) -> -4.5603614 | CM19: =Y63/AVERAGE(Y60:Y66) -> 6.0263208 | CN19: =Y64/AVERAGE(Y61:Y67) -> -3.1045971 | CO19: 1 | CR19: 2004 | CS19: =AA61/AVERAGE(AA58:AA64) -> 0.9664005 | CT19: =AA62/AVERAGE(AA59:AA65) -> 1.0044863 | CU19: =AA63/AVERAGE(AA60:AA66) -> 1.000556 | CV19: =AA64/AVERAGE(AA61:AA67) -> 1.0304249 | CW19: 1 | CZ19: 2004 | DA19: =AB61/AVERAGE(AB58:AB64) -> 0.96831873 | DB19: =AB62/AVERAGE(AB59:AB65) -> 0.9990809 | DC19: =AB63/AVERAGE(AB60:AB66) -> 1.0355341 | DD19: =AB64/AVERAGE(AB61:AB67) -> 1.0027099 | DE19: 1 | DH19: 2004 | DI19: =AC61/AVERAGE(AC58:AC64) -> 1.020972 | DJ19: =AC62/AVERAGE(AC59:AC65) -> 0.91683269 | DK19: =AC63/AVERAGE(AC60:AC66) -> 0.8936362 | DL19: =AC64/AVERAGE(AC61:AC67) -> 0.96268564 | DM19: 1 | DP19: 2004 | DQ19: =AD61/AVERAGE(AD58:AD64) -> 1.3057551 | DR19: =AD62/AVERAGE(AD59:AD65) -> 0.89662098 | DS19: =AD63/AVERAGE(AD60:AD66) -> 1.2477379 | DT19: =AD64/AVERAGE(AD61:AD67) -> 1.254444 | DU19: 1 | DX19: 2004 | DY19: =AE61/AVERAGE(AE58:AE64) -> 0.93179496 | DZ19: =AE62/AVERAGE(AE59:AE65) -> 1.1710135 | EA19: =AE63/AVERAGE(AE60:AE66) -> 1.0123565 | EB19: =AE64/AVERAGE(AE61:AE67) -> 0.87223604 | EC19: 1 | EF19: 2004 | EG19: =AF61/AVERAGE(AF58:AF64) -> 1.0924638 | EH19: =AF62/AVERAGE(AF59:AF65) -> 0.91224378 | EI19: =AF63/AVERAGE(AF60:AF66) -> 0.96003389 | EJ19: =AF64/AVERAGE(AF61:AF67) -> 1.0320538 | EK19: 1 | EN19: 2004 | EO19: =AG61/AVERAGE(AG58:AG64) -> 1.0351418 | EP19: =AG62/AVERAGE(AG59:AG65) -> 0.95716917 | EQ19: =AG63/AVERAGE(AG60:AG66) -> 0.9993022 | ER19: =AG64/AVERAGE(AG61:AG67) -> 1.0068789 | ES19: 1 | EV19: 2004 | EW19: =AH61/AVERAGE(AH58:AH64) -> 1.1003349 | EX19: =AH62/AVERAGE(AH59:AH65) -> 0.9018344 | EY19: =AH63/AVERAGE(AH60:AH66) -> 0.97052564 | EZ19: =AH64/AVERAGE(AH61:AH67) -> 1.0350871 | FA19: 1 | FD19: 2004 | FE19: =AI61/AVERAGE(AI58:AI64) -> 0.99218315 | FF19: =AI62/AVERAGE(AI59:AI65) -> 0.96869393 | FG19: =AI63/AVERAGE(AI60:AI66) -> 0.99347194 | FH19: =AI64/AVERAGE(AI61:AI67) -> 1.0117892 | FI19: 1
A20: 1993 Q4 | B20: =LEFT(A20,4) -> 1993 | C20: =RIGHT(A20,2) -> Q4 | D20: =HAVERQ!C26 -> 225346 | E20: =HAVERQ!D26 -> 7445 | F20: =HAVERQ!E26 -> 80801 | G20: =HAVERQ!F26 -> 67316 | H20: =HAVERQ!G26 -> -2202 | I20: =HAVERQ!H26 -> -1253 | J20: =HAVERQ!I26 -> 77175 | K20: =HAVERQ!J26 -> 71793 | L20: =HAVERQ!U26 -> #N/A | M20: =HAVERQ!V26 -> #N/A | N20: =HAVERQ!Y26 -> #N/A | O20: =HAVERQ!Z26 -> #N/A | P20: =HAVERQ!AA26 -> #N/A | Q20: =HAVERQ!AB26 -> #N/A | R20: =HAVERQ!AC26 -> #N/A | U20: =HAVERQ!M26 -> 233947 | V20: =HAVERQ!N26 -> 7408 | W20: =HAVERQ!O26 -> 81013 | X20: =HAVERQ!P26 -> 67315 | Y20: =HAVERQ!Q26 -> 72 | Z20: =HAVERQ!R26 -> -1256 | AA20: =HAVERQ!S26 -> 78853 | AB20: =HAVERQ!T26 -> 70741 | AC20: =HAVERQ!W26 -> #N/A | AD20: =HAVERQ!X26 -> #N/A | AE20: =HAVERQ!AD26 -> #N/A | AF20: =HAVERQ!AE26 -> #N/A | AG20: =HAVERQ!AF26 -> #N/A | AH20: =HAVERQ!AG26 -> #N/A | AI20: =HAVERQ!AH26 -> #N/A | AL20: 2005 | AM20: =OFFSET($D$5, (ROW(D16)-1)*4,0)/OFFSET($U$5, (ROW(U16)-1)*4,0) -> 1.0300603 | AN20: =OFFSET($E$5, (ROW(E16)-1)*4,0)/OFFSET($V$5, (ROW(V16)-1)*4,0) -> 1 | AO20: =OFFSET(F$5, (ROW(F16)-1)*4,0)/OFFSET(W$5, (ROW(W16)-1)*4,0) -> 0.99672403 | AP20: =OFFSET(G$5, (ROW(G16)-1)*4,0)/OFFSET(X$5, (ROW(X16)-1)*4,0) -> 0.97370363 | AQ20: =OFFSET(H$5, (ROW(H16)-1)*4,0)/OFFSET(Y$5, (ROW(Y16)-1)*4,0) -> 0.23828287 | AR20: =OFFSET(I$5, (ROW(I16)-1)*4,0)/OFFSET(Z$5, (ROW(Z16)-1)*4,0) -> 1.0778032 | AS20: =OFFSET(J$5, (ROW(J16)-1)*4,0)/OFFSET(AA$5, (ROW(AA16)-1)*4,0) -> 1.038579 | AT20: =OFFSET(K$5, (ROW(K16)-1)*4,0)/OFFSET(AB$5, (ROW(AB16)-1)*4,0) -> 1.0325979 | AU20: =OFFSET(L$5, (ROW(L16)-1)*4,0)/OFFSET(AC$5, (ROW(AC16)-1)*4,0) -> 1.0515043 | AV20: =OFFSET(M$5, (ROW(M16)-1)*4,0)/OFFSET(AD$5, (ROW(AD16)-1)*4,0) -> 0.74622108 | ... BA20: =OFFSET(R$5, (ROW(R16)-1)*4,0)/OFFSET(AI$5, (ROW(AI16)-1)*4,0) -> 0.98361204 | BD20: 2005 | BE20: =U65/AVERAGE(U62:U68) -> 0.96962385 | BF20: =U66/AVERAGE(U63:U69) -> 0.99292208 | BG20: =U67/AVERAGE(U64:U70) -> 1.0177551 | BH20: =U68/AVERAGE(U65:U71) -> 1.0333609 | BI20: 1 | BL20: 2005 | BM20: =V65/AVERAGE(V62:V68) -> 0.99849158 | BN20: =V66/AVERAGE(V63:V69) -> 0.99373034 | BO20: =V67/AVERAGE(V64:V70) -> 0.98855357 | BP20: =V68/AVERAGE(V65:V71) -> 1.0308449 | BQ20: 1 | BT20: 2005 | BU20: =W65/AVERAGE(W62:W68) -> 0.99677747 | BV20: =W66/AVERAGE(W63:W69) -> 1.0006563 | BW20: =W67/AVERAGE(W64:W70) -> 0.99998331 | BX20: =W68/AVERAGE(W65:W71) -> 1.0015649 | BY20: 1 | CB20: 2005 | CC20: =X65/AVERAGE(X62:X68) -> 1.0264381 | CD20: =X66/AVERAGE(X63:X69) -> 0.98109733 | CE20: =X67/AVERAGE(X64:X70) -> 1.0069231 | CF20: =X68/AVERAGE(X65:X71) -> 1.0299589 | CG20: 1 | CJ20: 2005 | CK20: =Y65/AVERAGE(Y62:Y68) -> -14.081769 | CL20: =Y66/AVERAGE(Y63:Y69) -> 13.578439 | CM20: =Y67/AVERAGE(Y64:Y70) -> 2.5717982 | CN20: =Y68/AVERAGE(Y65:Y71) -> -18.546336 | CO20: 1 | CR20: 2005 | CS20: =AA65/AVERAGE(AA62:AA68) -> 0.93112943 | CT20: =AA66/AVERAGE(AA63:AA69) -> 1.0010485 | CU20: =AA67/AVERAGE(AA64:AA70) -> 0.97161827 | CV20: =AA68/AVERAGE(AA65:AA71) -> 1.0059156 | CW20: 1 | CZ20: 2005 | DA20: =AB65/AVERAGE(AB62:AB68) -> 0.95148433 | DB20: =AB66/AVERAGE(AB63:AB69) -> 0.99542546 | DC20: =AB67/AVERAGE(AB64:AB70) -> 0.99786277 | DD20: =AB68/AVERAGE(AB65:AB71) -> 0.9804684 | DE20: 1 | DH20: 2005 | DI20: =AC65/AVERAGE(AC62:AC68) -> 0.89841733 | DJ20: =AC66/AVERAGE(AC63:AC69) -> 1.3566896 | DK20: =AC67/AVERAGE(AC64:AC70) -> 0.96111249 | DL20: =AC68/AVERAGE(AC65:AC71) -> 0.98910738 | DM20: 1 | DP20: 2005 | DQ20: =AD65/AVERAGE(AD62:AD68) -> 1.8902109 | DR20: =AD66/AVERAGE(AD63:AD69) -> -1.0469887 | DS20: =AD67/AVERAGE(AD64:AD70) -> 1.2301104 | DT20: =AD68/AVERAGE(AD65:AD71) -> 1.2398517 | DU20: 1 | DX20: 2005 | DY20: =AE65/AVERAGE(AE62:AE68) -> 0.86241769 | DZ20: =AE66/AVERAGE(AE63:AE69) -> 1.186041 | EA20: =AE67/AVERAGE(AE64:AE70) -> 0.97518907 | EB20: =AE68/AVERAGE(AE65:AE71) -> 0.89147824 | EC20: 1 | EF20: 2005 | EG20: =AF65/AVERAGE(AF62:AF68) -> 1.015048 | EH20: =AF66/AVERAGE(AF63:AF69) -> 0.87768812 | EI20: =AF67/AVERAGE(AF64:AF70) -> 1.033769 | EJ20: =AF68/AVERAGE(AF65:AF71) -> 1.1012075 | EK20: 1 | EN20: 2005 | EO20: =AG65/AVERAGE(AG62:AG68) -> 1.025842 | EP20: =AG66/AVERAGE(AG63:AG69) -> 0.98274597 | EQ20: =AG67/AVERAGE(AG64:AG70) -> 1.0152846 | ER20: =AG68/AVERAGE(AG65:AG71) -> 1.0086821 | ES20: 1 | EV20: 2005 | EW20: =AH65/AVERAGE(AH62:AH68) -> 1.0881892 | EX20: =AH66/AVERAGE(AH63:AH69) -> 0.89369153 | EY20: =AH67/AVERAGE(AH64:AH70) -> 1.0032254 | EZ20: =AH68/AVERAGE(AH65:AH71) -> 1.0602424 | FA20: 1 | FD20: 2005 | FE20: =AI65/AVERAGE(AI62:AI68) -> 1.0261481 | FF20: =AI66/AVERAGE(AI63:AI69) -> 0.98242073 | FG20: =AI67/AVERAGE(AI64:AI70) -> 1.0042302 | FH20: =AI68/AVERAGE(AI65:AI71) -> 1.0063045 | FI20: 1
A21: 1994 Q1 | B21: =LEFT(A21,4) -> 1994 | C21: =RIGHT(A21,2) -> Q1 | D21: =HAVERQ!C27 -> 227586 | E21: =HAVERQ!D27 -> 7325 | F21: =HAVERQ!E27 -> 80693 | G21: =HAVERQ!F27 -> 68155 | H21: =HAVERQ!G27 -> -1797 | I21: =HAVERQ!H27 -> -353 | J21: =HAVERQ!I27 -> 80051 | K21: =HAVERQ!J27 -> 73486 | L21: =HAVERQ!U27 -> #N/A | M21: =HAVERQ!V27 -> #N/A | N21: =HAVERQ!Y27 -> #N/A | O21: =HAVERQ!Z27 -> #N/A | P21: =HAVERQ!AA27 -> #N/A | Q21: =HAVERQ!AB27 -> #N/A | R21: =HAVERQ!AC27 -> #N/A | U21: =HAVERQ!M27 -> 219467 | V21: =HAVERQ!N27 -> 7318 | W21: =HAVERQ!O27 -> 81015 | X21: =HAVERQ!P27 -> 68167 | Y21: =HAVERQ!Q27 -> -2514 | Z21: =HAVERQ!R27 -> -354 | AA21: =HAVERQ!S27 -> 78237 | AB21: =HAVERQ!T27 -> 71173 | AC21: =HAVERQ!W27 -> #N/A | AD21: =HAVERQ!X27 -> #N/A | AE21: =HAVERQ!AD27 -> #N/A | AF21: =HAVERQ!AE27 -> #N/A | AG21: =HAVERQ!AF27 -> #N/A | AH21: =HAVERQ!AG27 -> #N/A | AI21: =HAVERQ!AH27 -> #N/A | AL21: 2006 | AM21: =OFFSET($D$5, (ROW(D17)-1)*4,0)/OFFSET($U$5, (ROW(U17)-1)*4,0) -> 1.0301242 | AN21: =OFFSET($E$5, (ROW(E17)-1)*4,0)/OFFSET($V$5, (ROW(V17)-1)*4,0) -> 1 | AO21: =OFFSET(F$5, (ROW(F17)-1)*4,0)/OFFSET(W$5, (ROW(W17)-1)*4,0) -> 0.99242098 | AP21: =OFFSET(G$5, (ROW(G17)-1)*4,0)/OFFSET(X$5, (ROW(X17)-1)*4,0) -> 0.98045001 | AQ21: =OFFSET(H$5, (ROW(H17)-1)*4,0)/OFFSET(Y$5, (ROW(Y17)-1)*4,0) -> -5.4589235 | AR21: =OFFSET(I$5, (ROW(I17)-1)*4,0)/OFFSET(Z$5, (ROW(Z17)-1)*4,0) -> 1.0506781 | AS21: =OFFSET(J$5, (ROW(J17)-1)*4,0)/OFFSET(AA$5, (ROW(AA17)-1)*4,0) -> 1.022685 | AT21: =OFFSET(K$5, (ROW(K17)-1)*4,0)/OFFSET(AB$5, (ROW(AB17)-1)*4,0) -> 1.016307 | AU21: =OFFSET(L$5, (ROW(L17)-1)*4,0)/OFFSET(AC$5, (ROW(AC17)-1)*4,0) -> 1.0437917 | AV21: =OFFSET(M$5, (ROW(M17)-1)*4,0)/OFFSET(AD$5, (ROW(AD17)-1)*4,0) -> 0.74702168 | ... BA21: =OFFSET(R$5, (ROW(R17)-1)*4,0)/OFFSET(AI$5, (ROW(AI17)-1)*4,0) -> 0.97562918 | BD21: 2006 | BE21: =U69/AVERAGE(U66:U72) -> 0.96360249 | BF21: =U70/AVERAGE(U67:U73) -> 0.98602331 | BG21: =U71/AVERAGE(U68:U74) -> 1.0096253 | BH21: =U72/AVERAGE(U69:U75) -> 1.022162 | BI21: 1 | BL21: 2006 | BM21: =V69/AVERAGE(V66:V72) -> 1.0116921 | BN21: =V70/AVERAGE(V67:V73) -> 0.9916869 | BO21: =V71/AVERAGE(V68:V74) -> 1.0058723 | BP21: =V72/AVERAGE(V69:V75) -> 0.99767916 | BQ21: 1 | BT21: 2006 | BU21: =W69/AVERAGE(W66:W72) -> 1.0130167 | BV21: =W70/AVERAGE(W67:W73) -> 0.98907681 | BW21: =W71/AVERAGE(W68:W74) -> 0.9990968 | BX21: =W72/AVERAGE(W69:W75) -> 0.99721845 | BY21: 1 | CB21: 2006 | CC21: =X69/AVERAGE(X66:X72) -> 1.030437 | CD21: =X70/AVERAGE(X67:X73) -> 0.93442342 | CE21: =X71/AVERAGE(X68:X74) -> 0.9956878 | CF21: =X72/AVERAGE(X69:X75) -> 1.014549 | CG21: 1 | CJ21: 2006 | CK21: =Y69/AVERAGE(Y66:Y72) -> 1.984739 | CL21: =Y70/AVERAGE(Y67:Y73) -> -2.2336945 | CM21: =Y71/AVERAGE(Y68:Y74) -> 9.0042576 | CN21: =Y72/AVERAGE(Y69:Y75) -> 1.8218176 | CO21: 1 | CR21: 2006 | CS21: =AA69/AVERAGE(AA66:AA72) -> 1.0550851 | CT21: =AA70/AVERAGE(AA67:AA73) -> 1.1147979 | CU21: =AA71/AVERAGE(AA68:AA74) -> 0.96295309 | CV21: =AA72/AVERAGE(AA69:AA75) -> 0.96568869 | CW21: 1 | CZ21: 2006 | DA21: =AB69/AVERAGE(AB66:AB72) -> 1.0571342 | DB21: =AB70/AVERAGE(AB67:AB73) -> 1.0873088 | DC21: =AB71/AVERAGE(AB68:AB74) -> 0.98605219 | DD21: =AB72/AVERAGE(AB69:AB75) -> 0.9487273 | DE21: 1 | DH21: 2006 | DI21: =AC69/AVERAGE(AC66:AC72) -> 0.94185038 | DJ21: =AC70/AVERAGE(AC67:AC73) -> 0.96484051 | DK21: =AC71/AVERAGE(AC68:AC74) -> 1.0089534 | DL21: =AC72/AVERAGE(AC69:AC75) -> 1.0123152 | DM21: 1 | DP21: 2006 | DQ21: =AD69/AVERAGE(AD66:AD72) -> 1.7766422 | DR21: =AD70/AVERAGE(AD67:AD73) -> 0.72197803 | DS21: =AD71/AVERAGE(AD68:AD74) -> 0.91928285 | DT21: =AD72/AVERAGE(AD69:AD75) -> 0.99970443 | DU21: 1 | DX21: 2006 | DY21: =AE69/AVERAGE(AE66:AE72) -> 0.95490107 | DZ21: =AE70/AVERAGE(AE67:AE73) -> 1.068725 | EA21: =AE71/AVERAGE(AE68:AE74) -> 1.0686317 | EB21: =AE72/AVERAGE(AE69:AE75) -> 0.98273788 | EC21: 1 | EF21: 2006 | EG21: =AF69/AVERAGE(AF66:AF72) -> 1.052618 | EH21: =AF70/AVERAGE(AF67:AF73) -> 0.87110522 | EI21: =AF71/AVERAGE(AF68:AF74) -> 0.96239968 | EJ21: =AF72/AVERAGE(AF69:AF75) -> 1.0562259 | EK21: 1 | EN21: 2006 | EO21: =AG69/AVERAGE(AG66:AG72) -> 1.0462056 | EP21: =AG70/AVERAGE(AG67:AG73) -> 0.96372048 | EQ21: =AG71/AVERAGE(AG68:AG74) -> 0.9831164 | ER21: =AG72/AVERAGE(AG69:AG75) -> 0.9956543 | ES21: 1 | EV21: 2006 | EW21: =AH69/AVERAGE(AH66:AH72) -> 1.0295948 | EX21: =AH70/AVERAGE(AH67:AH73) -> 0.90375657 | EY21: =AH71/AVERAGE(AH68:AH74) -> 1.0269461 | EZ21: =AH72/AVERAGE(AH69:AH75) -> 1.0264265 | FA21: 1 | FD21: 2006 | FE21: =AI69/AVERAGE(AI66:AI72) -> 1.0445013 | FF21: =AI70/AVERAGE(AI67:AI73) -> 0.98018356 | FG21: =AI71/AVERAGE(AI68:AI74) -> 0.97408152 | FH21: =AI72/AVERAGE(AI69:AI75) -> 0.98561572 | FI21: 1
A22: 1994 Q2 | B22: =LEFT(A22,4) -> 1994 | C22: =RIGHT(A22,2) -> Q2 | D22: =HAVERQ!C28 -> 227983 | E22: =HAVERQ!D28 -> 7454 | F22: =HAVERQ!E28 -> 81916 | G22: =HAVERQ!F28 -> 66804 | H22: =HAVERQ!G28 -> 5712 | I22: =HAVERQ!H28 -> 531 | J22: =HAVERQ!I28 -> 80308 | K22: =HAVERQ!J28 -> 74141 | L22: =HAVERQ!U28 -> #N/A | M22: =HAVERQ!V28 -> #N/A | N22: =HAVERQ!Y28 -> #N/A | O22: =HAVERQ!Z28 -> #N/A | P22: =HAVERQ!AA28 -> #N/A | Q22: =HAVERQ!AB28 -> #N/A | R22: =HAVERQ!AC28 -> #N/A | U22: =HAVERQ!M28 -> 221420 | V22: =HAVERQ!N28 -> 7407 | W22: =HAVERQ!O28 -> 81691 | X22: =HAVERQ!P28 -> 66812 | Y22: =HAVERQ!Q28 -> 8281 | Z22: =HAVERQ!R28 -> 532 | AA22: =HAVERQ!S28 -> 79608 | AB22: =HAVERQ!T28 -> 75766 | AC22: =HAVERQ!W28 -> #N/A | AD22: =HAVERQ!X28 -> #N/A | AE22: =HAVERQ!AD28 -> #N/A | AF22: =HAVERQ!AE28 -> #N/A | AG22: =HAVERQ!AF28 -> #N/A | AH22: =HAVERQ!AG28 -> #N/A | AI22: =HAVERQ!AH28 -> #N/A | AL22: 2007 | AM22: =OFFSET($D$5, (ROW(D18)-1)*4,0)/OFFSET($U$5, (ROW(U18)-1)*4,0) -> 1.0295482 | AN22: =OFFSET($E$5, (ROW(E18)-1)*4,0)/OFFSET($V$5, (ROW(V18)-1)*4,0) -> 1 | AO22: =OFFSET(F$5, (ROW(F18)-1)*4,0)/OFFSET(W$5, (ROW(W18)-1)*4,0) -> 0.99198522 | AP22: =OFFSET(G$5, (ROW(G18)-1)*4,0)/OFFSET(X$5, (ROW(X18)-1)*4,0) -> 0.95590687 | AQ22: =OFFSET(H$5, (ROW(H18)-1)*4,0)/OFFSET(Y$5, (ROW(Y18)-1)*4,0) -> 0.8730028 | AR22: =OFFSET(I$5, (ROW(I18)-1)*4,0)/OFFSET(Z$5, (ROW(Z18)-1)*4,0) -> 1.0990385 | AS22: =OFFSET(J$5, (ROW(J18)-1)*4,0)/OFFSET(AA$5, (ROW(AA18)-1)*4,0) -> 1.0233107 | AT22: =OFFSET(K$5, (ROW(K18)-1)*4,0)/OFFSET(AB$5, (ROW(AB18)-1)*4,0) -> 1.0139516 | AU22: =OFFSET(L$5, (ROW(L18)-1)*4,0)/OFFSET(AC$5, (ROW(AC18)-1)*4,0) -> 0.99601196 | AV22: =OFFSET(M$5, (ROW(M18)-1)*4,0)/OFFSET(AD$5, (ROW(AD18)-1)*4,0) -> 0.74942061 | ... BA22: =OFFSET(R$5, (ROW(R18)-1)*4,0)/OFFSET(AI$5, (ROW(AI18)-1)*4,0) -> 0.97466795 | BD22: 2007 | BE22: =U73/AVERAGE(U70:U76) -> 0.96373181 | BF22: =U74/AVERAGE(U71:U77) -> 0.98988542 | BG22: =U75/AVERAGE(U72:U78) -> 1.0247563 | BH22: =U76/AVERAGE(U73:U79) -> 1.0431738 | BI22: 1 | BL22: 2007 | BM22: =V73/AVERAGE(V70:V76) -> 0.98878849 | BN22: =V74/AVERAGE(V71:V77) -> 0.98485519 | BO22: =V75/AVERAGE(V72:V78) -> 1.0050899 | BP22: =V76/AVERAGE(V73:V79) -> 0.99066327 | BQ22: 1 | BT22: 2007 | BU22: =W73/AVERAGE(W70:W76) -> 1.0138864 | BV22: =W74/AVERAGE(W71:W77) -> 0.993285 | BW22: =W75/AVERAGE(W72:W78) -> 1.0006963 | BX22: =W76/AVERAGE(W73:W79) -> 0.99037204 | BY22: 1 | CB22: 2007 | CC22: =X73/AVERAGE(X70:X76) -> 1.0390065 | CD22: =X74/AVERAGE(X71:X77) -> 0.94492874 | CE22: =X75/AVERAGE(X72:X78) -> 0.98264082 | CF22: =X76/AVERAGE(X73:X79) -> 1.0698543 | CG22: 1 | CJ22: 2007 | CK22: =Y73/AVERAGE(Y70:Y76) -> 6.4204563 | CL22: =Y74/AVERAGE(Y71:Y77) -> -1.9701888 | CM22: =Y75/AVERAGE(Y72:Y78) -> 4.6705436 | CN22: =Y76/AVERAGE(Y73:Y79) -> -11.648551 | CO22: 1 | CR22: 2007 | CS22: =AA73/AVERAGE(AA70:AA76) -> 0.94043217 | CT22: =AA74/AVERAGE(AA71:AA77) -> 1.0142792 | CU22: =AA75/AVERAGE(AA72:AA78) -> 0.99405774 | CV22: =AA76/AVERAGE(AA73:AA79) -> 1.0429507 | CW22: 1 | CZ22: 2007 | DA22: =AB73/AVERAGE(AB70:AB76) -> 0.97103396 | DB22: =AB74/AVERAGE(AB71:AB77) -> 0.99303446 | DC22: =AB75/AVERAGE(AB72:AB78) -> 1.0432934 | DD22: =AB76/AVERAGE(AB73:AB79) -> 1.008881 | DE22: 1 | DH22: 2007 | DI22: =AC73/AVERAGE(AC70:AC76) -> 0.98105298 | DJ22: =AC74/AVERAGE(AC71:AC77) -> 0.98450452 | DK22: =AC75/AVERAGE(AC72:AC78) -> 1.0145722 | DL22: =AC76/AVERAGE(AC73:AC79) -> 1.0763673 | DM22: 1 | DP22: 2007 | DQ22: =AD73/AVERAGE(AD70:AD76) -> 1.376854 | DR22: =AD74/AVERAGE(AD71:AD77) -> 0.70261738 | DS22: =AD75/AVERAGE(AD72:AD78) -> 0.80540871 | DT22: =AD76/AVERAGE(AD73:AD79) -> 1.0441955 | DU22: 1 | DX22: 2007 | DY22: =AE73/AVERAGE(AE70:AE76) -> 0.9443501 | DZ22: =AE74/AVERAGE(AE71:AE77) -> 1.2155267 | EA22: =AE75/AVERAGE(AE72:AE78) -> 0.97164208 | EB22: =AE76/AVERAGE(AE73:AE79) -> 0.92748469 | EC22: 1 | EF22: 2007 | EG22: =AF73/AVERAGE(AF70:AF76) -> 1.1039224 | EH22: =AF74/AVERAGE(AF71:AF77) -> 0.85855976 | EI22: =AF75/AVERAGE(AF72:AF78) -> 0.91217065 | EJ22: =AF76/AVERAGE(AF73:AF79) -> 1.1652519 | EK22: 1 | EN22: 2007 | EO22: =AG73/AVERAGE(AG70:AG76) -> 1.0323129 | EP22: =AG74/AVERAGE(AG71:AG77) -> 0.98444451 | EQ22: =AG75/AVERAGE(AG72:AG78) -> 0.98541572 | ER22: =AG76/AVERAGE(AG73:AG79) -> 1.0418012 | ES22: 1 | EV22: 2007 | EW22: =AH73/AVERAGE(AH70:AH76) -> 1.0354646 | EX22: =AH74/AVERAGE(AH71:AH77) -> 0.89136719 | EY22: =AH75/AVERAGE(AH72:AH78) -> 1.0323044 | EZ22: =AH76/AVERAGE(AH73:AH79) -> 1.0782239 | FA22: 1 | FD22: 2007 | FE22: =AI73/AVERAGE(AI70:AI76) -> 1.011821 | FF22: =AI74/AVERAGE(AI71:AI77) -> 0.99200403 | FG22: =AI75/AVERAGE(AI72:AI78) -> 0.97671471 | FH22: =AI76/AVERAGE(AI73:AI79) -> 1.0310612 | FI22: 1
A23: 1994 Q3 | B23: =LEFT(A23,4) -> 1994 | C23: =RIGHT(A23,2) -> Q3 | D23: =HAVERQ!C29 -> 229961 | E23: =HAVERQ!D29 -> 7478 | F23: =HAVERQ!E29 -> 81861 | G23: =HAVERQ!F29 -> 67262 | H23: =HAVERQ!G29 -> 3711 | I23: =HAVERQ!H29 -> -453 | J23: =HAVERQ!I29 -> 82678 | K23: =HAVERQ!J29 -> 73776 | L23: =HAVERQ!U29 -> #N/A | M23: =HAVERQ!V29 -> #N/A | N23: =HAVERQ!Y29 -> #N/A | O23: =HAVERQ!Z29 -> #N/A | P23: =HAVERQ!AA29 -> #N/A | Q23: =HAVERQ!AB29 -> #N/A | R23: =HAVERQ!AC29 -> #N/A | U23: =HAVERQ!M29 -> 236996 | V23: =HAVERQ!N29 -> 7537 | W23: =HAVERQ!O29 -> 81573 | X23: =HAVERQ!P29 -> 67258 | Y23: =HAVERQ!Q29 -> 3757 | Z23: =HAVERQ!R29 -> -452 | AA23: =HAVERQ!S29 -> 83778 | AB23: =HAVERQ!T29 -> 75582 | AC23: =HAVERQ!W29 -> #N/A | AD23: =HAVERQ!X29 -> #N/A | AE23: =HAVERQ!AD29 -> #N/A | AF23: =HAVERQ!AE29 -> #N/A | AG23: =HAVERQ!AF29 -> #N/A | AH23: =HAVERQ!AG29 -> #N/A | AI23: =HAVERQ!AH29 -> #N/A | AL23: 2008 | AM23: =OFFSET($D$5, (ROW(D19)-1)*4,0)/OFFSET($U$5, (ROW(U19)-1)*4,0) -> 1.0284232 | AN23: =OFFSET($E$5, (ROW(E19)-1)*4,0)/OFFSET($V$5, (ROW(V19)-1)*4,0) -> 1 | AO23: =OFFSET(F$5, (ROW(F19)-1)*4,0)/OFFSET(W$5, (ROW(W19)-1)*4,0) -> 0.99471739 | AP23: =OFFSET(G$5, (ROW(G19)-1)*4,0)/OFFSET(X$5, (ROW(X19)-1)*4,0) -> 0.94892568 | AQ23: =OFFSET(H$5, (ROW(H19)-1)*4,0)/OFFSET(Y$5, (ROW(Y19)-1)*4,0) -> -3.5800766 | AR23: =OFFSET(I$5, (ROW(I19)-1)*4,0)/OFFSET(Z$5, (ROW(Z19)-1)*4,0) -> 1.2849873 | AS23: =OFFSET(J$5, (ROW(J19)-1)*4,0)/OFFSET(AA$5, (ROW(AA19)-1)*4,0) -> 1.0298164 | AT23: =OFFSET(K$5, (ROW(K19)-1)*4,0)/OFFSET(AB$5, (ROW(AB19)-1)*4,0) -> 1.0224994 | AU23: =OFFSET(L$5, (ROW(L19)-1)*4,0)/OFFSET(AC$5, (ROW(AC19)-1)*4,0) -> 0.97743049 | AV23: =OFFSET(M$5, (ROW(M19)-1)*4,0)/OFFSET(AD$5, (ROW(AD19)-1)*4,0) -> 0.78937462 | ... BA23: =OFFSET(R$5, (ROW(R19)-1)*4,0)/OFFSET(AI$5, (ROW(AI19)-1)*4,0) -> 0.97591766 | BD23: 2008 | BE23: =U77/AVERAGE(U74:U80) -> 0.98692551 | BF23: =U78/AVERAGE(U75:U81) -> 1.0000514 | BG23: =U79/AVERAGE(U76:U82) -> 1.0115318 | BH23: =U80/AVERAGE(U77:U83) -> 1.0161406 | BI23: 1 | BL23: 2008 | BM23: =V77/AVERAGE(V74:V80) -> 0.9753063 | BN23: =V78/AVERAGE(V75:V81) -> 0.98899565 | BO23: =V79/AVERAGE(V76:V82) -> 1.0006953 | BP23: =V80/AVERAGE(V77:V83) -> 1.0008871 | BQ23: 1 | BT23: 2008 | BU23: =W77/AVERAGE(W74:W80) -> 1.0080594 | BV23: =W78/AVERAGE(W75:W81) -> 0.98859135 | BW23: =W79/AVERAGE(W76:W82) -> 1.0012936 | BX23: =W80/AVERAGE(W77:W83) -> 1.0111827 | BY23: 1 | CB23: 2008 | CC23: =X77/AVERAGE(X74:X80) -> 1.0658422 | CD23: =X78/AVERAGE(X75:X81) -> 0.97698898 | CE23: =X79/AVERAGE(X76:X82) -> 0.99086399 | CF23: =X80/AVERAGE(X77:X83) -> 1.0230602 | CG23: 1 | CJ23: 2008 | CK23: =Y77/AVERAGE(Y74:Y80) -> -0.61511009 | CL23: =Y78/AVERAGE(Y75:Y81) -> 0.14121467 | CM23: =Y79/AVERAGE(Y76:Y82) -> -0.75732405 | CN23: =Y80/AVERAGE(Y77:Y83) -> 3.0932793 | CO23: 1 | CR23: 2008 | CS23: =AA77/AVERAGE(AA74:AA80) -> 0.98288755 | CT23: =AA78/AVERAGE(AA75:AA81) -> 1.0339518 | CU23: =AA79/AVERAGE(AA76:AA82) -> 1.0419875 | CV23: =AA80/AVERAGE(AA77:AA83) -> 1.0272647 | CW23: 1 | CZ23: 2008 | DA23: =AB77/AVERAGE(AB74:AB80) -> 0.99599469 | DB23: =AB78/AVERAGE(AB75:AB81) -> 1.0276614 | DC23: =AB79/AVERAGE(AB76:AB82) -> 1.0513065 | DD23: =AB80/AVERAGE(AB77:AB83) -> 0.98234767 | DE23: 1 | DH23: 2008 | DI23: =AC77/AVERAGE(AC74:AC80) -> 0.97274538 | DJ23: =AC78/AVERAGE(AC75:AC81) -> 1.031599 | DK23: =AC79/AVERAGE(AC76:AC82) -> 1.0347654 | DL23: =AC80/AVERAGE(AC77:AC83) -> 1.0428276 | DM23: 1 | DP23: 2008 | DQ23: =AD77/AVERAGE(AD74:AD80) -> 1.4509481 | DR23: =AD78/AVERAGE(AD75:AD81) -> 0.73769301 | DS23: =AD79/AVERAGE(AD76:AD82) -> 0.88786179 | DT23: =AD80/AVERAGE(AD77:AD83) -> 1.0154779 | DU23: 1 | DX23: 2008 | DY23: =AE77/AVERAGE(AE74:AE80) -> 0.76922859 | DZ23: =AE78/AVERAGE(AE75:AE81) -> 1.3537965 | EA23: =AE79/AVERAGE(AE76:AE82) -> 0.95555026 | EB23: =AE80/AVERAGE(AE77:AE83) -> 0.99320342 | EC23: 1 | EF23: 2008 | EG23: =AF77/AVERAGE(AF74:AF80) -> 1.1724761 | EH23: =AF78/AVERAGE(AF75:AF81) -> 0.90648485 | EI23: =AF79/AVERAGE(AF76:AF82) -> 0.96157653 | EJ23: =AF80/AVERAGE(AF77:AF83) -> 1.0731192 | EK23: 1 | EN23: 2008 | EO23: =AG77/AVERAGE(AG74:AG80) -> 1.0460018 | EP23: =AG78/AVERAGE(AG75:AG81) -> 1.0036541 | EQ23: =AG79/AVERAGE(AG76:AG82) -> 0.99454533 | ER23: =AG80/AVERAGE(AG77:AG83) -> 1.0201627 | ES23: 1 | EV23: 2008 | EW23: =AH77/AVERAGE(AH74:AH80) -> 1.0916493 | EX23: =AH78/AVERAGE(AH75:AH81) -> 0.93907925 | EY23: =AH79/AVERAGE(AH76:AH82) -> 1.0119086 | EZ23: =AH80/AVERAGE(AH77:AH83) -> 1.0071526 | FA23: 1 | FD23: 2008 | FE23: =AI77/AVERAGE(AI74:AI80) -> 1.020315 | FF23: =AI78/AVERAGE(AI75:AI81) -> 0.9833715 | FG23: =AI79/AVERAGE(AI76:AI82) -> 0.99401198 | FH23: =AI80/AVERAGE(AI77:AI83) -> 1.0108159 | FI23: 1
A24: 1994 Q4 | B24: =LEFT(A24,4) -> 1994 | C24: =RIGHT(A24,2) -> Q4 | D24: =HAVERQ!C30 -> 231570 | E24: =HAVERQ!D30 -> 7647 | F24: =HAVERQ!E30 -> 81569 | G24: =HAVERQ!F30 -> 67628 | H24: =HAVERQ!G30 -> 5432 | I24: =HAVERQ!H30 -> 2569 | J24: =HAVERQ!I30 -> 84800 | K24: =HAVERQ!J30 -> 76803 | L24: =HAVERQ!U30 -> #N/A | M24: =HAVERQ!V30 -> #N/A | N24: =HAVERQ!Y30 -> #N/A | O24: =HAVERQ!Z30 -> #N/A | P24: =HAVERQ!AA30 -> #N/A | Q24: =HAVERQ!AB30 -> #N/A | R24: =HAVERQ!AC30 -> #N/A | U24: =HAVERQ!M30 -> 239217 | V24: =HAVERQ!N30 -> 7642 | W24: =HAVERQ!O30 -> 81760 | X24: =HAVERQ!P30 -> 67612 | Y24: =HAVERQ!Q30 -> 3534 | Z24: =HAVERQ!R30 -> 2568 | AA24: =HAVERQ!S30 -> 86214 | AB24: =HAVERQ!T30 -> 75685 | AC24: =HAVERQ!W30 -> #N/A | AD24: =HAVERQ!X30 -> #N/A | AE24: =HAVERQ!AD30 -> #N/A | AF24: =HAVERQ!AE30 -> #N/A | AG24: =HAVERQ!AF30 -> #N/A | AH24: =HAVERQ!AG30 -> #N/A | AI24: =HAVERQ!AH30 -> #N/A | AL24: 2009 | AM24: =OFFSET($D$5, (ROW(D20)-1)*4,0)/OFFSET($U$5, (ROW(U20)-1)*4,0) -> 1.0248104 | AN24: =OFFSET($E$5, (ROW(E20)-1)*4,0)/OFFSET($V$5, (ROW(V20)-1)*4,0) -> 1 | AO24: =OFFSET(F$5, (ROW(F20)-1)*4,0)/OFFSET(W$5, (ROW(W20)-1)*4,0) -> 0.99048668 | AP24: =OFFSET(G$5, (ROW(G20)-1)*4,0)/OFFSET(X$5, (ROW(X20)-1)*4,0) -> 0.95277822 | AQ24: =OFFSET(H$5, (ROW(H20)-1)*4,0)/OFFSET(Y$5, (ROW(Y20)-1)*4,0) -> 1.1540446 | AR24: =OFFSET(I$5, (ROW(I20)-1)*4,0)/OFFSET(Z$5, (ROW(Z20)-1)*4,0) -> 1.0961689 | AS24: =OFFSET(J$5, (ROW(J20)-1)*4,0)/OFFSET(AA$5, (ROW(AA20)-1)*4,0) -> 1.0323846 | AT24: =OFFSET(K$5, (ROW(K20)-1)*4,0)/OFFSET(AB$5, (ROW(AB20)-1)*4,0) -> 1.0207754 | AU24: =OFFSET(L$5, (ROW(L20)-1)*4,0)/OFFSET(AC$5, (ROW(AC20)-1)*4,0) -> 1.0198043 | AV24: =OFFSET(M$5, (ROW(M20)-1)*4,0)/OFFSET(AD$5, (ROW(AD20)-1)*4,0) -> 0.75342937 | ... BA24: =OFFSET(R$5, (ROW(R20)-1)*4,0)/OFFSET(AI$5, (ROW(AI20)-1)*4,0) -> 0.97776032 | BD24: 2009 | BE24: =U81/AVERAGE(U78:U84) -> 0.95921716 | BF24: =U82/AVERAGE(U79:U85) -> 0.97948812 | BG24: =U83/AVERAGE(U80:U86) -> 1.0012618 | BH24: =U84/AVERAGE(U81:U87) -> 1.0266032 | BI24: 1 | BL24: 2009 | BM24: =V81/AVERAGE(V78:V84) -> 0.99612144 | BN24: =V82/AVERAGE(V79:V85) -> 0.99889253 | BO24: =V83/AVERAGE(V80:V86) -> 1.019205 | BP24: =V84/AVERAGE(V81:V87) -> 1.0131215 | BQ24: 1 | BT24: 2009 | BU24: =W81/AVERAGE(W78:W84) -> 1.0104142 | BV24: =W82/AVERAGE(W79:W85) -> 0.98661794 | BW24: =W83/AVERAGE(W80:W86) -> 0.99723384 | BX24: =W84/AVERAGE(W81:W87) -> 1.0121485 | BY24: 1 | CB24: 2009 | CC24: =X81/AVERAGE(X78:X84) -> 1.0343969 | CD24: =X82/AVERAGE(X79:X85) -> 0.89265697 | CE24: =X83/AVERAGE(X80:X86) -> 0.97992976 | CF24: =X84/AVERAGE(X81:X87) -> 0.99763375 | CG24: 1 | CJ24: 2009 | CK24: =Y81/AVERAGE(Y78:Y84) -> 1.1859556 | CL24: =Y82/AVERAGE(Y79:Y85) -> 1.2362355 | CM24: =Y83/AVERAGE(Y80:Y86) -> 0.85545466 | CN24: =Y84/AVERAGE(Y81:Y87) -> 1.9119966 | CO24: 1 | CR24: 2009 | CS24: =AA81/AVERAGE(AA78:AA84) -> 0.9263885 | CT24: =AA82/AVERAGE(AA79:AA85) -> 0.96910303 | CU24: =AA83/AVERAGE(AA80:AA86) -> 0.97461359 | CV24: =AA84/AVERAGE(AA81:AA87) -> 1.0311116 | CW24: 1 | CZ24: 2009 | DA24: =AB81/AVERAGE(AB78:AB84) -> 0.92941188 | DB24: =AB82/AVERAGE(AB79:AB85) -> 0.9555475 | DC24: =AB83/AVERAGE(AB80:AB86) -> 1.0166355 | DD24: =AB84/AVERAGE(AB81:AB87) -> 1.0015173 | DE24: 1 | DH24: 2009 | DI24: =AC81/AVERAGE(AC78:AC84) -> 0.95170308 | DJ24: =AC82/AVERAGE(AC79:AC85) -> 0.94422036 | DK24: =AC83/AVERAGE(AC80:AC86) -> 0.97935551 | DL24: =AC84/AVERAGE(AC81:AC87) -> 1.0064738 | DM24: 1 | DP24: 2009 | DQ24: =AD81/AVERAGE(AD78:AD84) -> 1.4262871 | DR24: =AD82/AVERAGE(AD79:AD85) -> 0.69027893 | DS24: =AD83/AVERAGE(AD80:AD86) -> 0.94621091 | DT24: =AD84/AVERAGE(AD81:AD87) -> 0.98158982 | DU24: 1 | DX24: 2009 | DY24: =AE81/AVERAGE(AE78:AE84) -> 0.81635164 | DZ24: =AE82/AVERAGE(AE79:AE85) -> 1.2184223 | EA24: =AE83/AVERAGE(AE80:AE86) -> 0.99432463 | EB24: =AE84/AVERAGE(AE81:AE87) -> 0.89823913 | EC24: 1 | EF24: 2009 | EG24: =AF81/AVERAGE(AF78:AF84) -> 1.1841664 | EH24: =AF82/AVERAGE(AF79:AF85) -> 0.75422656 | EI24: =AF83/AVERAGE(AF80:AF86) -> 0.90526199 | EJ24: =AF84/AVERAGE(AF81:AF87) -> 1.0324148 | EK24: 1 | EN24: 2009 | EO24: =AG81/AVERAGE(AG78:AG84) -> 0.98431697 | EP24: =AG82/AVERAGE(AG79:AG85) -> 0.91509211 | EQ24: =AG83/AVERAGE(AG80:AG86) -> 0.99253612 | ER24: =AG84/AVERAGE(AG81:AG87) -> 0.96861448 | ES24: 1 | EV24: 2009 | EW24: =AH81/AVERAGE(AH78:AH84) -> 1.0219554 | EX24: =AH82/AVERAGE(AH79:AH85) -> 0.85477197 | EY24: =AH83/AVERAGE(AH80:AH86) -> 1.0145319 | EZ24: =AH84/AVERAGE(AH81:AH87) -> 1.0217968 | FA24: 1 | FD24: 2009 | FE24: =AI81/AVERAGE(AI78:AI84) -> 1.0300007 | FF24: =AI82/AVERAGE(AI79:AI85) -> 0.96124185 | FG24: =AI83/AVERAGE(AI80:AI86) -> 0.97787885 | FH24: =AI84/AVERAGE(AI81:AI87) -> 0.9825624 | FI24: 1
A25: 1995 Q1 | B25: =LEFT(A25,4) -> 1995 | C25: =RIGHT(A25,2) -> Q1 | D25: =HAVERQ!C31 -> 231674 | E25: =HAVERQ!D31 -> 8007 | F25: =HAVERQ!E31 -> 82420 | G25: =HAVERQ!F31 -> 66753 | H25: =HAVERQ!G31 -> -1682 | I25: =HAVERQ!H31 -> 358 | J25: =HAVERQ!I31 -> 88448 | K25: =HAVERQ!J31 -> 75480 | L25: =HAVERQ!U31 -> #N/A | M25: =HAVERQ!V31 -> #N/A | N25: =HAVERQ!Y31 -> #N/A | O25: =HAVERQ!Z31 -> #N/A | P25: =HAVERQ!AA31 -> #N/A | Q25: =HAVERQ!AB31 -> #N/A | R25: =HAVERQ!AC31 -> #N/A | U25: =HAVERQ!M31 -> 220666 | V25: =HAVERQ!N31 -> 7939 | W25: =HAVERQ!O31 -> 82399 | X25: =HAVERQ!P31 -> 66711 | Y25: =HAVERQ!Q31 -> -3006 | Z25: =HAVERQ!R31 -> 358 | AA25: =HAVERQ!S31 -> 87295 | AB25: =HAVERQ!T31 -> 73103 | AC25: =HAVERQ!W31 -> #N/A | AD25: =HAVERQ!X31 -> #N/A | AE25: =HAVERQ!AD31 -> #N/A | AF25: =HAVERQ!AE31 -> #N/A | AG25: =HAVERQ!AF31 -> #N/A | AH25: =HAVERQ!AG31 -> #N/A | AI25: =HAVERQ!AH31 -> #N/A | AL25: 2010 | AM25: =OFFSET($D$5, (ROW(D21)-1)*4,0)/OFFSET($U$5, (ROW(U21)-1)*4,0) -> 1.0261414 | AN25: =OFFSET($E$5, (ROW(E21)-1)*4,0)/OFFSET($V$5, (ROW(V21)-1)*4,0) -> 1 | AO25: =OFFSET(F$5, (ROW(F21)-1)*4,0)/OFFSET(W$5, (ROW(W21)-1)*4,0) -> 0.98653351 | AP25: =OFFSET(G$5, (ROW(G21)-1)*4,0)/OFFSET(X$5, (ROW(X21)-1)*4,0) -> 0.95826546 | AQ25: =OFFSET(H$5, (ROW(H21)-1)*4,0)/OFFSET(Y$5, (ROW(Y21)-1)*4,0) -> 0.69137931 | AR25: =OFFSET(I$5, (ROW(I21)-1)*4,0)/OFFSET(Z$5, (ROW(Z21)-1)*4,0) -> 0.76923077 | AS25: =OFFSET(J$5, (ROW(J21)-1)*4,0)/OFFSET(AA$5, (ROW(AA21)-1)*4,0) -> 1.0307114 | AT25: =OFFSET(K$5, (ROW(K21)-1)*4,0)/OFFSET(AB$5, (ROW(AB21)-1)*4,0) -> 1.0256769 | AU25: =OFFSET(L$5, (ROW(L21)-1)*4,0)/OFFSET(AC$5, (ROW(AC21)-1)*4,0) -> 1.0274964 | AV25: =OFFSET(M$5, (ROW(M21)-1)*4,0)/OFFSET(AD$5, (ROW(AD21)-1)*4,0) -> 0.76463604 | ... BA25: =OFFSET(R$5, (ROW(R21)-1)*4,0)/OFFSET(AI$5, (ROW(AI21)-1)*4,0) -> 0.9670151 | BD25: 2010 | BE25: =U85/AVERAGE(U82:U88) -> 0.96125964 | BF25: =U86/AVERAGE(U83:U89) -> 0.99952823 | BG25: =U87/AVERAGE(U84:U90) -> 1.0246003 | BH25: =U88/AVERAGE(U85:U91) -> 1.0423385 | BI25: 1 | BL25: 2010 | BM25: =V85/AVERAGE(V82:V88) -> 1.0042877 | BN25: =V86/AVERAGE(V83:V89) -> 1.0051567 | BO25: =V87/AVERAGE(V84:V90) -> 1.0096196 | BP25: =V88/AVERAGE(V85:V91) -> 0.99485455 | BQ25: 1 | BT25: 2010 | BU25: =W85/AVERAGE(W82:W88) -> 1.0102889 | BV25: =W86/AVERAGE(W83:W89) -> 0.98713723 | BW25: =W87/AVERAGE(W84:W90) -> 0.991648 | BX25: =W88/AVERAGE(W85:W91) -> 1.0061169 | BY25: 1 | CB25: 2010 | CC25: =X85/AVERAGE(X82:X88) -> 1.0625741 | CD25: =X86/AVERAGE(X83:X89) -> 0.91141761 | CE25: =X87/AVERAGE(X84:X90) -> 1.0109478 | CF25: =X88/AVERAGE(X85:X91) -> 1.060861 | CG25: 1 | CJ25: 2010 | CK25: =Y85/AVERAGE(Y82:Y88) -> 0.82736134 | CL25: =Y86/AVERAGE(Y83:Y89) -> 1.2295637 | CM25: =Y87/AVERAGE(Y84:Y90) -> -1.7068725 | CN25: =Y88/AVERAGE(Y85:Y91) -> 5.9921959 | CO25: 1 | CR25: 2010 | CS25: =AA85/AVERAGE(AA82:AA88) -> 0.9596049 | CT25: =AA86/AVERAGE(AA83:AA89) -> 1.0037687 | CU25: =AA87/AVERAGE(AA84:AA90) -> 0.99618144 | CV25: =AA88/AVERAGE(AA85:AA91) -> 1.0223928 | CW25: 1 | CZ25: 2010 | DA25: =AB85/AVERAGE(AB82:AB88) -> 0.96375641 | DB25: =AB86/AVERAGE(AB83:AB89) -> 0.99777807 | DC25: =AB87/AVERAGE(AB84:AB90) -> 1.0524066 | DD25: =AB88/AVERAGE(AB85:AB91) -> 1.0233435 | DE25: 1 | DH25: 2010 | DI25: =AC85/AVERAGE(AC82:AC88) -> 0.97426357 | DJ25: =AC86/AVERAGE(AC83:AC89) -> 0.95159236 | DK25: =AC87/AVERAGE(AC84:AC90) -> 1.0122899 | DL25: =AC88/AVERAGE(AC85:AC91) -> 1.0943696 | DM25: 1 | DP25: 2010 | DQ25: =AD85/AVERAGE(AD82:AD88) -> 1.4453132 | DR25: =AD86/AVERAGE(AD83:AD89) -> 0.71516646 | DS25: =AD87/AVERAGE(AD84:AD90) -> 0.93669057 | DT25: =AD88/AVERAGE(AD85:AD91) -> 0.96713642 | DU25: 1 | DX25: 2010 | DY25: =AE85/AVERAGE(AE82:AE88) -> 0.82783033 | DZ25: =AE86/AVERAGE(AE83:AE89) -> 0.96032017 | EA25: =AE87/AVERAGE(AE84:AE90) -> 1.0226253 | EB25: =AE88/AVERAGE(AE85:AE91) -> 1.6526984 | EC25: 1 | EF25: 2010 | EG25: =AF85/AVERAGE(AF82:AF88) -> 1.2418748 | EH25: =AF86/AVERAGE(AF83:AF89) -> 0.82217156 | EI25: =AF87/AVERAGE(AF84:AF90) -> 0.9064053 | EJ25: =AF88/AVERAGE(AF85:AF91) -> 1.0028935 | EK25: 1 | EN25: 2010 | EO25: =AG85/AVERAGE(AG82:AG88) -> 0.95538429 | EP25: =AG86/AVERAGE(AG83:AG89) -> 0.98334678 | EQ25: =AG87/AVERAGE(AG84:AG90) -> 1.0589916 | ER25: =AG88/AVERAGE(AG85:AG91) -> 1.0529662 | ES25: 1 | EV25: 2010 | EW25: =AH85/AVERAGE(AH82:AH88) -> 1.0864739 | EX25: =AH86/AVERAGE(AH83:AH89) -> 0.8455999 | EY25: =AH87/AVERAGE(AH84:AH90) -> 1.0454949 | EZ25: =AH88/AVERAGE(AH85:AH91) -> 1.039405 | FA25: 1 | FD25: 2010 | FE25: =AI85/AVERAGE(AI82:AI88) -> 1.0453741 | FF25: =AI86/AVERAGE(AI83:AI89) -> 0.99952929 | FG25: =AI87/AVERAGE(AI84:AI90) -> 1.0073897 | FH25: =AI88/AVERAGE(AI85:AI91) -> 0.99627282 | FI25: 1
A26: 1995 Q2 | B26: =LEFT(A26,4) -> 1995 | C26: =RIGHT(A26,2) -> Q2 | D26: =HAVERQ!C32 -> 233343 | E26: =HAVERQ!D32 -> 8008 | F26: =HAVERQ!E32 -> 82730 | G26: =HAVERQ!F32 -> 66884 | H26: =HAVERQ!G32 -> 4292 | I26: =HAVERQ!H32 -> 1834 | J26: =HAVERQ!I32 -> 87297 | K26: =HAVERQ!J32 -> 78210 | L26: =HAVERQ!U32 -> #N/A | M26: =HAVERQ!V32 -> #N/A | N26: =HAVERQ!Y32 -> #N/A | O26: =HAVERQ!Z32 -> #N/A | P26: =HAVERQ!AA32 -> #N/A | Q26: =HAVERQ!AB32 -> #N/A | R26: =HAVERQ!AC32 -> #N/A | U26: =HAVERQ!M32 -> 226675 | V26: =HAVERQ!N32 -> 7989 | W26: =HAVERQ!O32 -> 82494 | X26: =HAVERQ!P32 -> 66843 | Y26: =HAVERQ!Q32 -> 8038 | Z26: =HAVERQ!R32 -> 1836 | AA26: =HAVERQ!S32 -> 86689 | AB26: =HAVERQ!T32 -> 79935 | AC26: =HAVERQ!W32 -> #N/A | AD26: =HAVERQ!X32 -> #N/A | AE26: =HAVERQ!AD32 -> #N/A | AF26: =HAVERQ!AE32 -> #N/A | AG26: =HAVERQ!AF32 -> #N/A | AH26: =HAVERQ!AG32 -> #N/A | AI26: =HAVERQ!AH32 -> #N/A | AL26: 2011 | AM26: =OFFSET($D$5, (ROW(D22)-1)*4,0)/OFFSET($U$5, (ROW(U22)-1)*4,0) -> 1.0286542 | AN26: =OFFSET($E$5, (ROW(E22)-1)*4,0)/OFFSET($V$5, (ROW(V22)-1)*4,0) -> 1 | AO26: =OFFSET(F$5, (ROW(F22)-1)*4,0)/OFFSET(W$5, (ROW(W22)-1)*4,0) -> 0.98592528 | AP26: =OFFSET(G$5, (ROW(G22)-1)*4,0)/OFFSET(X$5, (ROW(X22)-1)*4,0) -> 0.9587151 | AQ26: =OFFSET(H$5, (ROW(H22)-1)*4,0)/OFFSET(Y$5, (ROW(Y22)-1)*4,0) -> 0.035244608 | AR26: =OFFSET(I$5, (ROW(I22)-1)*4,0)/OFFSET(Z$5, (ROW(Z22)-1)*4,0) -> 0.95136986 | AS26: =OFFSET(J$5, (ROW(J22)-1)*4,0)/OFFSET(AA$5, (ROW(AA22)-1)*4,0) -> 1.0250377 | AT26: =OFFSET(K$5, (ROW(K22)-1)*4,0)/OFFSET(AB$5, (ROW(AB22)-1)*4,0) -> 1.0202983 | AU26: =OFFSET(L$5, (ROW(L22)-1)*4,0)/OFFSET(AC$5, (ROW(AC22)-1)*4,0) -> 1.0286339 | AV26: =OFFSET(M$5, (ROW(M22)-1)*4,0)/OFFSET(AD$5, (ROW(AD22)-1)*4,0) -> 0.74603752 | ... BA26: =OFFSET(R$5, (ROW(R22)-1)*4,0)/OFFSET(AI$5, (ROW(AI22)-1)*4,0) -> 0.98125947 | BD26: 2011 | BE26: =U89/AVERAGE(U86:U92) -> 0.96583358 | BF26: =U90/AVERAGE(U87:U93) -> 0.98142647 | BG26: =U91/AVERAGE(U88:U94) -> 1.0068031 | BH26: =U92/AVERAGE(U89:U95) -> 1.0278502 | BI26: 1 | BL26: 2011 | BM26: =V89/AVERAGE(V86:V92) -> 0.97793357 | BN26: =V90/AVERAGE(V87:V93) -> 1.0176976 | BO26: =V91/AVERAGE(V88:V94) -> 1.0138125 | BP26: =V92/AVERAGE(V89:V95) -> 0.98879735 | BQ26: 1 | BT26: 2011 | BU26: =W89/AVERAGE(W86:W92) -> 1.0245733 | BV26: =W90/AVERAGE(W87:W93) -> 0.98187217 | BW26: =W91/AVERAGE(W88:W94) -> 0.97864496 | BX26: =W92/AVERAGE(W89:W95) -> 0.99619044 | BY26: 1 | CB26: 2011 | CC26: =X89/AVERAGE(X86:X92) -> 1.0390991 | CD26: =X90/AVERAGE(X87:X93) -> 0.90077138 | CE26: =X91/AVERAGE(X88:X94) -> 0.98534454 | CF26: =X92/AVERAGE(X89:X95) -> 1.0578167 | CG26: 1 | CJ26: 2011 | CK26: =Y89/AVERAGE(Y86:Y92) -> 4.2719101 | CL26: =Y90/AVERAGE(Y87:Y93) -> -24.608483 | CM26: =Y91/AVERAGE(Y88:Y94) -> 3.3847737 | CN26: =Y92/AVERAGE(Y89:Y95) -> -1.6264224 | CO26: 1 | CR26: 2011 | CS26: =AA89/AVERAGE(AA86:AA92) -> 1.0027192 | CT26: =AA90/AVERAGE(AA87:AA93) -> 1.0005514 | CU26: =AA91/AVERAGE(AA88:AA94) -> 1.0013531 | CV26: =AA92/AVERAGE(AA89:AA95) -> 1.0189588 | CW26: 1 | CZ26: 2011 | DA26: =AB89/AVERAGE(AB86:AB92) -> 0.96567577 | DB26: =AB90/AVERAGE(AB87:AB93) -> 0.99566759 | DC26: =AB91/AVERAGE(AB88:AB94) -> 1.023193 | DD26: =AB92/AVERAGE(AB89:AB95) -> 0.99659838 | DE26: 1 | DH26: 2011 | DI26: =AC89/AVERAGE(AC86:AC92) -> 0.92933836 | DJ26: =AC90/AVERAGE(AC87:AC93) -> 0.95668732 | DK26: =AC91/AVERAGE(AC88:AC94) -> 1.0053861 | DL26: =AC92/AVERAGE(AC89:AC95) -> 1.0926291 | DM26: 1 | DP26: 2011 | DQ26: =AD89/AVERAGE(AD86:AD92) -> 1.5245962 | DR26: =AD90/AVERAGE(AD87:AD93) -> 0.65864457 | DS26: =AD91/AVERAGE(AD88:AD94) -> 0.8837292 | DT26: =AD92/AVERAGE(AD89:AD95) -> 0.93566265 | DU26: 1 | DX26: 2011 | DY26: =AE89/AVERAGE(AE86:AE92) -> 0.66456494 | DZ26: =AE90/AVERAGE(AE87:AE93) -> 0.84084537 | EA26: =AE91/AVERAGE(AE88:AE94) -> 0.68610837 | EB26: =AE92/AVERAGE(AE89:AE95) -> 1.3165192 | EC26: 1 | EF26: 2011 | EG26: =AF89/AVERAGE(AF86:AF92) -> 1.0986275 | EH26: =AF90/AVERAGE(AF87:AF93) -> 0.88704386 | EI26: =AF91/AVERAGE(AF88:AF94) -> 0.99502464 | EJ26: =AF92/AVERAGE(AF89:AF95) -> 1.0923494 | EK26: 1 | EN26: 2011 | EO26: =AG89/AVERAGE(AG86:AG92) -> 0.97377934 | EP26: =AG90/AVERAGE(AG87:AG93) -> 0.97056512 | EQ26: =AG91/AVERAGE(AG88:AG94) -> 1.0141604 | ER26: =AG92/AVERAGE(AG89:AG95) -> 1.0551613 | ES26: 1 | EV26: 2011 | EW26: =AH89/AVERAGE(AH86:AH92) -> 1.1324856 | EX26: =AH90/AVERAGE(AH87:AH93) -> 0.82674474 | EY26: =AH91/AVERAGE(AH88:AH94) -> 1.0041978 | EZ26: =AH92/AVERAGE(AH89:AH95) -> 1.0310162 | FA26: 1 | FD26: 2011 | FE26: =AI89/AVERAGE(AI86:AI92) -> 1.021147 | FF26: =AI90/AVERAGE(AI87:AI93) -> 0.96937323 | FG26: =AI91/AVERAGE(AI88:AI94) -> 1.0142246 | FH26: =AI92/AVERAGE(AI89:AI95) -> 1.0131292 | FI26: 1
A27: 1995 Q3 | B27: =LEFT(A27,4) -> 1995 | C27: =RIGHT(A27,2) -> Q3 | D27: =HAVERQ!C33 -> 234345 | E27: =HAVERQ!D33 -> 7959 | F27: =HAVERQ!E33 -> 82532 | G27: =HAVERQ!F33 -> 67357 | H27: =HAVERQ!G33 -> 6523 | I27: =HAVERQ!H33 -> -1866 | J27: =HAVERQ!I33 -> 90195 | K27: =HAVERQ!J33 -> 79909 | L27: =HAVERQ!U33 -> #N/A | M27: =HAVERQ!V33 -> #N/A | N27: =HAVERQ!Y33 -> #N/A | O27: =HAVERQ!Z33 -> #N/A | P27: =HAVERQ!AA33 -> #N/A | Q27: =HAVERQ!AB33 -> #N/A | R27: =HAVERQ!AC33 -> #N/A | U27: =HAVERQ!M33 -> 241689 | V27: =HAVERQ!N33 -> 8073 | W27: =HAVERQ!O33 -> 82005 | X27: =HAVERQ!P33 -> 67361 | Y27: =HAVERQ!Q33 -> 4264 | Z27: =HAVERQ!R33 -> -1867 | AA27: =HAVERQ!S33 -> 90774 | AB27: =HAVERQ!T33 -> 81434 | AC27: =HAVERQ!W33 -> #N/A | AD27: =HAVERQ!X33 -> #N/A | AE27: =HAVERQ!AD33 -> #N/A | AF27: =HAVERQ!AE33 -> #N/A | AG27: =HAVERQ!AF33 -> #N/A | AH27: =HAVERQ!AG33 -> #N/A | AI27: =HAVERQ!AH33 -> #N/A | AL27: 2012 | AM27: =OFFSET($D$5, (ROW(D23)-1)*4,0)/OFFSET($U$5, (ROW(U23)-1)*4,0) -> 1.0289372 | AN27: =OFFSET($E$5, (ROW(E23)-1)*4,0)/OFFSET($V$5, (ROW(V23)-1)*4,0) -> 1 | AO27: =OFFSET(F$5, (ROW(F23)-1)*4,0)/OFFSET(W$5, (ROW(W23)-1)*4,0) -> 0.98467924 | AP27: =OFFSET(G$5, (ROW(G23)-1)*4,0)/OFFSET(X$5, (ROW(X23)-1)*4,0) -> 0.97879781 | AQ27: =OFFSET(H$5, (ROW(H23)-1)*4,0)/OFFSET(Y$5, (ROW(Y23)-1)*4,0) -> 3.2539683 | AR27: =OFFSET(I$5, (ROW(I23)-1)*4,0)/OFFSET(Z$5, (ROW(Z23)-1)*4,0) -> 0.93062827 | AS27: =OFFSET(J$5, (ROW(J23)-1)*4,0)/OFFSET(AA$5, (ROW(AA23)-1)*4,0) -> 1.016244 | AT27: =OFFSET(K$5, (ROW(K23)-1)*4,0)/OFFSET(AB$5, (ROW(AB23)-1)*4,0) -> 1.0126588 | AU27: =OFFSET(L$5, (ROW(L23)-1)*4,0)/OFFSET(AC$5, (ROW(AC23)-1)*4,0) -> 1.0647793 | AV27: =OFFSET(M$5, (ROW(M23)-1)*4,0)/OFFSET(AD$5, (ROW(AD23)-1)*4,0) -> 0.73016994 | ... BA27: =OFFSET(R$5, (ROW(R23)-1)*4,0)/OFFSET(AI$5, (ROW(AI23)-1)*4,0) -> 1.0037842 | BD27: 2012 | BE27: =U93/AVERAGE(U90:U96) -> 0.9590087 | BF27: =U94/AVERAGE(U91:U97) -> 0.98012023 | BG27: =U95/AVERAGE(U92:U98) -> 1.0162878 | BH27: =U96/AVERAGE(U93:U99) -> 1.045778 | BI27: 1 | BL27: 2012 | BM27: =V93/AVERAGE(V90:V96) -> 0.97758748 | BN27: =V94/AVERAGE(V91:V97) -> 1.0242499 | BO27: =V95/AVERAGE(V92:V98) -> 1.0466874 | BP27: =V96/AVERAGE(V93:V99) -> 0.98957892 | BQ27: 1 | BT27: 2012 | BU27: =W93/AVERAGE(W90:W96) -> 1.0401455 | BV27: =W94/AVERAGE(W91:W97) -> 0.98370139 | BW27: =W95/AVERAGE(W92:W98) -> 0.98642453 | BX27: =W96/AVERAGE(W93:W99) -> 1.0091878 | BY27: 1 | CB27: 2012 | CC27: =X93/AVERAGE(X90:X96) -> 1.0491076 | CD27: =X94/AVERAGE(X91:X97) -> 0.92270507 | CE27: =X95/AVERAGE(X92:X98) -> 0.9697975 | CF27: =X96/AVERAGE(X93:X99) -> 1.0499645 | CG27: 1 | CJ27: 2012 | CK27: =Y93/AVERAGE(Y90:Y96) -> -1.7316754 | CL27: =Y94/AVERAGE(Y91:Y97) -> -236.33229 | CM27: =Y95/AVERAGE(Y92:Y98) -> -9.1477632 | CN27: =Y96/AVERAGE(Y93:Y99) -> -10.705713 | CO27: 1 | CR27: 2012 | CS27: =AA93/AVERAGE(AA90:AA96) -> 1.0183799 | CT27: =AA94/AVERAGE(AA91:AA97) -> 0.98589759 | CU27: =AA95/AVERAGE(AA92:AA98) -> 1.0017514 | CV27: =AA96/AVERAGE(AA93:AA99) -> 0.99245828 | CW27: 1 | CZ27: 2012 | DA27: =AB93/AVERAGE(AB90:AB96) -> 0.98809004 | DB27: =AB94/AVERAGE(AB91:AB97) -> 1.0073698 | DC27: =AB95/AVERAGE(AB92:AB98) -> 1.0250574 | DD27: =AB96/AVERAGE(AB93:AB99) -> 0.97978233 | DE27: 1 | DH27: 2012 | DI27: =AC93/AVERAGE(AC90:AC96) -> 0.96762982 | DJ27: =AC94/AVERAGE(AC91:AC97) -> 0.95970389 | DK27: =AC95/AVERAGE(AC92:AC98) -> 0.9892834 | DL27: =AC96/AVERAGE(AC93:AC99) -> 1.0895408 | DM27: 1 | DP27: 2012 | DQ27: =AD93/AVERAGE(AD90:AD96) -> 1.5292671 | DR27: =AD94/AVERAGE(AD91:AD97) -> 0.75267007 | DS27: =AD95/AVERAGE(AD92:AD98) -> 0.85297438 | DT27: =AD96/AVERAGE(AD93:AD99) -> 0.92693581 | DU27: 1 | DX27: 2012 | DY27: =AE93/AVERAGE(AE90:AE96) -> 1.9100213 | DZ27: =AE94/AVERAGE(AE91:AE97) -> 0.78607089 | EA27: =AE95/AVERAGE(AE92:AE98) -> 0.37528785 | EB27: =AE96/AVERAGE(AE93:AE99) -> 0.9800365 | EC27: 1 | EF27: 2012 | EG27: =AF93/AVERAGE(AF90:AF96) -> 1.0231704 | EH27: =AF94/AVERAGE(AF91:AF97) -> 0.90506368 | EI27: =AF95/AVERAGE(AF92:AF98) -> 0.99354118 | EJ27: =AF96/AVERAGE(AF93:AF99) -> 1.1068967 | EK27: 1 | EN27: 2012 | EO27: =AG93/AVERAGE(AG90:AG96) -> 0.94326995 | EP27: =AG94/AVERAGE(AG91:AG97) -> 0.9523133 | EQ27: =AG95/AVERAGE(AG92:AG98) -> 1.0045174 | ER27: =AG96/AVERAGE(AG93:AG99) -> 1.0193901 | ES27: 1 | EV27: 2012 | EW27: =AH93/AVERAGE(AH90:AH96) -> 1.0467674 | EX27: =AH94/AVERAGE(AH91:AH97) -> 0.89669307 | EY27: =AH95/AVERAGE(AH92:AH98) -> 0.99677877 | EZ27: =AH96/AVERAGE(AH93:AH99) -> 1.0798138 | FA27: 1 | FD27: 2012 | FE27: =AI93/AVERAGE(AI90:AI96) -> 0.94751635 | FF27: =AI94/AVERAGE(AI91:AI97) -> 0.97615017 | FG27: =AI95/AVERAGE(AI92:AI98) -> 1.012128 | FH27: =AI96/AVERAGE(AI93:AI99) -> 1.0115747 | FI27: 1
A28: 1995 Q4 | B28: =LEFT(A28,4) -> 1995 | C28: =RIGHT(A28,2) -> Q4 | D28: =HAVERQ!C34 -> 237147 | E28: =HAVERQ!D34 -> 8186 | F28: =HAVERQ!E34 -> 82886 | G28: =HAVERQ!F34 -> 67705 | H28: =HAVERQ!G34 -> 2877 | I28: =HAVERQ!H34 -> -1092 | J28: =HAVERQ!I34 -> 91446 | K28: =HAVERQ!J34 -> 80511 | L28: =HAVERQ!U34 -> #N/A | M28: =HAVERQ!V34 -> #N/A | N28: =HAVERQ!Y34 -> #N/A | O28: =HAVERQ!Z34 -> #N/A | P28: =HAVERQ!AA34 -> #N/A | Q28: =HAVERQ!AB34 -> #N/A | R28: =HAVERQ!AC34 -> #N/A | U28: =HAVERQ!M34 -> 247479 | V28: =HAVERQ!N34 -> 8159 | W28: =HAVERQ!O34 -> 83670 | X28: =HAVERQ!P34 -> 67784 | Y28: =HAVERQ!Q34 -> 2714 | Z28: =HAVERQ!R34 -> -1093 | AA28: =HAVERQ!S34 -> 92628 | AB28: =HAVERQ!T34 -> 79638 | AC28: =HAVERQ!W34 -> #N/A | AD28: =HAVERQ!X34 -> #N/A | AE28: =HAVERQ!AD34 -> #N/A | AF28: =HAVERQ!AE34 -> #N/A | AG28: =HAVERQ!AF34 -> #N/A | AH28: =HAVERQ!AG34 -> #N/A | AI28: =HAVERQ!AH34 -> #N/A | AL28: 2013 | AM28: =OFFSET($D$5, (ROW(D24)-1)*4,0)/OFFSET($U$5, (ROW(U24)-1)*4,0) -> 1.0258967 | AN28: =OFFSET($E$5, (ROW(E24)-1)*4,0)/OFFSET($V$5, (ROW(V24)-1)*4,0) -> 1 | AO28: =OFFSET(F$5, (ROW(F24)-1)*4,0)/OFFSET(W$5, (ROW(W24)-1)*4,0) -> 0.98722334 | AP28: =OFFSET(G$5, (ROW(G24)-1)*4,0)/OFFSET(X$5, (ROW(X24)-1)*4,0) -> 0.97896624 | AQ28: =OFFSET(H$5, (ROW(H24)-1)*4,0)/OFFSET(Y$5, (ROW(Y24)-1)*4,0) -> 0.14603175 | AR28: =OFFSET(I$5, (ROW(I24)-1)*4,0)/OFFSET(Z$5, (ROW(Z24)-1)*4,0) -> 1.4527938 | AS28: =OFFSET(J$5, (ROW(J24)-1)*4,0)/OFFSET(AA$5, (ROW(AA24)-1)*4,0) -> 1.02773 | AT28: =OFFSET(K$5, (ROW(K24)-1)*4,0)/OFFSET(AB$5, (ROW(AB24)-1)*4,0) -> 1.0221401 | AU28: =OFFSET(L$5, (ROW(L24)-1)*4,0)/OFFSET(AC$5, (ROW(AC24)-1)*4,0) -> 1.0454713 | AV28: =OFFSET(M$5, (ROW(M24)-1)*4,0)/OFFSET(AD$5, (ROW(AD24)-1)*4,0) -> 0.72599881 | ... BA28: =OFFSET(R$5, (ROW(R24)-1)*4,0)/OFFSET(AI$5, (ROW(AI24)-1)*4,0) -> 0.96890573 | BD28: 2013 | BE28: =U97/AVERAGE(U94:U100) -> 0.96782308 | BF28: =U98/AVERAGE(U95:U101) -> 0.98108521 | BG28: =U99/AVERAGE(U96:U102) -> 1.014928 | BH28: =U100/AVERAGE(U97:U103) -> 1.0301195 | BI28: 1 | BL28: 2013 | BM28: =V97/AVERAGE(V94:V100) -> 0.98083354 | BN28: =V98/AVERAGE(V95:V101) -> 0.99869478 | BO28: =V99/AVERAGE(V96:V102) -> 1.018516 | BP28: =V100/AVERAGE(V97:V103) -> 0.99616725 | BQ28: 1 | BT28: 2013 | BU28: =W97/AVERAGE(W94:W100) -> 1.0099779 | BV28: =W98/AVERAGE(W95:W101) -> 0.98811448 | BW28: =W99/AVERAGE(W96:W102) -> 0.97749533 | BX28: =W100/AVERAGE(W97:W103) -> 1.0065153 | BY28: 1 | CB28: 2013 | CC28: =X97/AVERAGE(X94:X100) -> 1.0113202 | CD28: =X98/AVERAGE(X95:X101) -> 0.93662725 | CE28: =X99/AVERAGE(X96:X102) -> 1.0016483 | CF28: =X100/AVERAGE(X97:X103) -> 1.0320172 | CG28: 1 | CJ28: 2013 | CK28: =Y97/AVERAGE(Y94:Y100) -> -5.1174935 | CL28: =Y98/AVERAGE(Y95:Y101) -> -0.92038505 | CM28: =Y99/AVERAGE(Y96:Y102) -> -10.241693 | CN28: =Y100/AVERAGE(Y97:Y103) -> 0.22828972 | CO28: 1 | CR28: 2013 | CS28: =AA97/AVERAGE(AA94:AA100) -> 0.97736171 | CT28: =AA98/AVERAGE(AA95:AA101) -> 1.017881 | CU28: =AA99/AVERAGE(AA96:AA102) -> 1.0129856 | CV28: =AA100/AVERAGE(AA97:AA103) -> 1.0036508 | CW28: 1 | CZ28: 2013 | DA28: =AB97/AVERAGE(AB94:AB100) -> 0.95478024 | DB28: =AB98/AVERAGE(AB95:AB101) -> 1.0106011 | DC28: =AB99/AVERAGE(AB96:AB102) -> 1.0307084 | DD28: =AB100/AVERAGE(AB97:AB103) -> 1.013531 | DE28: 1 | DH28: 2013 | DI28: =AC97/AVERAGE(AC94:AC100) -> 0.94062849 | DJ28: =AC98/AVERAGE(AC95:AC101) -> 0.96673829 | DK28: =AC99/AVERAGE(AC96:AC102) -> 1.0188906 | DL28: =AC100/AVERAGE(AC97:AC103) -> 1.0634745 | DM28: 1 | DP28: 2013 | DQ28: =AD97/AVERAGE(AD94:AD100) -> 1.4438078 | DR28: =AD98/AVERAGE(AD95:AD101) -> 0.68995308 | DS28: =AD99/AVERAGE(AD96:AD102) -> 0.86357191 | DT28: =AD100/AVERAGE(AD97:AD103) -> 0.92247509 | DU28: 1 | DX28: 2013 | DY28: =AE97/AVERAGE(AE94:AE100) -> 0.71768824 | DZ28: =AE98/AVERAGE(AE95:AE101) -> 0.91554368 | EA28: =AE99/AVERAGE(AE96:AE102) -> 1.122936 | EB28: =AE100/AVERAGE(AE97:AE103) -> 1.1260451 | EC28: 1 | EF28: 2013 | EG28: =AF97/AVERAGE(AF94:AF100) -> 1.0928811 | EH28: =AF98/AVERAGE(AF95:AF101) -> 0.8479207 | EI28: =AF99/AVERAGE(AF96:AF102) -> 0.94040177 | EJ28: =AF100/AVERAGE(AF97:AF103) -> 1.0424858 | EK28: 1 | EN28: 2013 | EO28: =AG97/AVERAGE(AG94:AG100) -> 0.9361382 | EP28: =AG98/AVERAGE(AG95:AG101) -> 1.0078619 | EQ28: =AG99/AVERAGE(AG96:AG102) -> 1.0499103 | ER28: =AG100/AVERAGE(AG97:AG103) -> 1.0411284 | ES28: 1 | EV28: 2013 | EW28: =AH97/AVERAGE(AH94:AH100) -> 1.0190198 | EX28: =AH98/AVERAGE(AH95:AH101) -> 0.91703892 | EY28: =AH99/AVERAGE(AH96:AH102) -> 1.0037368 | EZ28: =AH100/AVERAGE(AH97:AH103) -> 1.0291491 | FA28: 1 | FD28: 2013 | FE28: =AI97/AVERAGE(AI94:AI100) -> 1.0439528 | FF28: =AI98/AVERAGE(AI95:AI101) -> 0.97514361 | FG28: =AI99/AVERAGE(AI96:AI102) -> 0.9864041 | FH28: =AI100/AVERAGE(AI97:AI103) -> 1.0024206 | FI28: 1
A29: 1996 Q1 | B29: =LEFT(A29,4) -> 1996 | C29: =RIGHT(A29,2) -> Q1 | D29: =HAVERQ!C35 -> 239556 | E29: =HAVERQ!D35 -> 8962 | F29: =HAVERQ!E35 -> 83359 | G29: =HAVERQ!F35 -> 69483 | H29: =HAVERQ!G35 -> 2900 | I29: =HAVERQ!H35 -> -491 | J29: =HAVERQ!I35 -> 93411 | K29: =HAVERQ!J35 -> 83621 | L29: =HAVERQ!U35 -> #N/A | M29: =HAVERQ!V35 -> #N/A | N29: =HAVERQ!Y35 -> #N/A | O29: =HAVERQ!Z35 -> #N/A | P29: =HAVERQ!AA35 -> #N/A | Q29: =HAVERQ!AB35 -> #N/A | R29: =HAVERQ!AC35 -> #N/A | U29: =HAVERQ!M35 -> 228161 | V29: =HAVERQ!N35 -> 9003 | W29: =HAVERQ!O35 -> 83523 | X29: =HAVERQ!P35 -> 69796 | Y29: =HAVERQ!Q35 -> -2874 | Z29: =HAVERQ!R35 -> -492 | AA29: =HAVERQ!S35 -> 91741 | AB29: =HAVERQ!T35 -> 81360 | AC29: =HAVERQ!W35 -> #N/A | AD29: =HAVERQ!X35 -> #N/A | AE29: =HAVERQ!AD35 -> #N/A | AF29: =HAVERQ!AE35 -> #N/A | AG29: =HAVERQ!AF35 -> #N/A | AH29: =HAVERQ!AG35 -> #N/A | AI29: =HAVERQ!AH35 -> #N/A | AL29: 2014 | AM29: =OFFSET($D$5, (ROW(D25)-1)*4,0)/OFFSET($U$5, (ROW(U25)-1)*4,0) -> 1.0309429 | AN29: =OFFSET($E$5, (ROW(E25)-1)*4,0)/OFFSET($V$5, (ROW(V25)-1)*4,0) -> 1 | AO29: =OFFSET(F$5, (ROW(F25)-1)*4,0)/OFFSET(W$5, (ROW(W25)-1)*4,0) -> 0.98360827 | AP29: =OFFSET(G$5, (ROW(G25)-1)*4,0)/OFFSET(X$5, (ROW(X25)-1)*4,0) -> 0.97631386 | AQ29: =OFFSET(H$5, (ROW(H25)-1)*4,0)/OFFSET(Y$5, (ROW(Y25)-1)*4,0) -> -0.018772709 | AR29: =OFFSET(I$5, (ROW(I25)-1)*4,0)/OFFSET(Z$5, (ROW(Z25)-1)*4,0) -> 1.3795424 | AS29: =OFFSET(J$5, (ROW(J25)-1)*4,0)/OFFSET(AA$5, (ROW(AA25)-1)*4,0) -> 1.0234379 | AT29: =OFFSET(K$5, (ROW(K25)-1)*4,0)/OFFSET(AB$5, (ROW(AB25)-1)*4,0) -> 1.0192311 | AU29: =OFFSET(L$5, (ROW(L25)-1)*4,0)/OFFSET(AC$5, (ROW(AC25)-1)*4,0) -> 1.0442291 | AV29: =OFFSET(M$5, (ROW(M25)-1)*4,0)/OFFSET(AD$5, (ROW(AD25)-1)*4,0) -> 0.73398293 | ... BA29: =OFFSET(R$5, (ROW(R25)-1)*4,0)/OFFSET(AI$5, (ROW(AI25)-1)*4,0) -> 0.97407074 | BD29: 2014 | BE29: =U101/AVERAGE(U98:U104) -> 0.96057502 | BF29: =U102/AVERAGE(U99:U105) -> 0.98283385 | BG29: =U103/AVERAGE(U100:U106) -> 1.0220614 | BH29: =U104/AVERAGE(U101:U107) -> 1.0335646 | BI29: 1 | BL29: 2014 | BM29: =V101/AVERAGE(V98:V104) -> 0.99812105 | BN29: =V102/AVERAGE(V99:V105) -> 0.98732713 | BO29: =V103/AVERAGE(V100:V106) -> 0.99028777 | BP29: =V104/AVERAGE(V101:V107) -> 0.97473046 | BQ29: 1 | BT29: 2014 | BU29: =W101/AVERAGE(W98:W104) -> 1.0240192 | BV29: =W102/AVERAGE(W99:W105) -> 0.99840617 | BW29: =W103/AVERAGE(W100:W106) -> 0.99090522 | BX29: =W104/AVERAGE(W101:W107) -> 0.99652078 | BY29: 1 | CB29: 2014 | CC29: =X101/AVERAGE(X98:X104) -> 1.0341798 | CD29: =X102/AVERAGE(X99:X105) -> 0.93445898 | CE29: =X103/AVERAGE(X100:X106) -> 0.97831395 | CF29: =X104/AVERAGE(X101:X107) -> 1.0456867 | CG29: 1 | CJ29: 2014 | CK29: =Y101/AVERAGE(Y98:Y104) -> -1.3030474 | CL29: =Y102/AVERAGE(Y99:Y105) -> 1.729848 | CM29: =Y103/AVERAGE(Y100:Y106) -> 1.7508037 | CN29: =Y104/AVERAGE(Y101:Y107) -> 3.89694 | CO29: 1 | CR29: 2014 | CS29: =AA101/AVERAGE(AA98:AA104) -> 0.96684915 | CT29: =AA102/AVERAGE(AA99:AA105) -> 1.0035148 | CU29: =AA103/AVERAGE(AA100:AA106) -> 0.98647977 | CV29: =AA104/AVERAGE(AA101:AA107) -> 1.0304223 | CW29: 1 | CZ29: 2014 | DA29: =AB101/AVERAGE(AB98:AB104) -> 0.96390886 | DB29: =AB102/AVERAGE(AB99:AB105) -> 0.9628451 | DC29: =AB103/AVERAGE(AB100:AB106) -> 1.0198235 | DD29: =AB104/AVERAGE(AB101:AB107) -> 1.0434993 | DE29: 1 | DH29: 2014 | DI29: =AC101/AVERAGE(AC98:AC104) -> 0.93847652 | DJ29: =AC102/AVERAGE(AC99:AC105) -> 0.97757858 | DK29: =AC103/AVERAGE(AC100:AC106) -> 0.97820974 | DL29: =AC104/AVERAGE(AC101:AC107) -> 1.0805274 | DM29: 1 | DP29: 2014 | DQ29: =AD101/AVERAGE(AD98:AD104) -> 1.567147 | DR29: =AD102/AVERAGE(AD99:AD105) -> 0.70247422 | DS29: =AD103/AVERAGE(AD100:AD106) -> 0.89111534 | DT29: =AD104/AVERAGE(AD101:AD107) -> 0.93849513 | DU29: 1 | DX29: 2014 | DY29: =AE101/AVERAGE(AE98:AE104) -> 0.93728097 | DZ29: =AE102/AVERAGE(AE99:AE105) -> 0.99065975 | EA29: =AE103/AVERAGE(AE100:AE106) -> 0.85162264 | EB29: =AE104/AVERAGE(AE101:AE107) -> 1.0042646 | EC29: 1 | EF29: 2014 | EG29: =AF101/AVERAGE(AF98:AF104) -> 1.0881428 | EH29: =AF102/AVERAGE(AF99:AF105) -> 0.91081468 | EI29: =AF103/AVERAGE(AF100:AF106) -> 1.0099216 | EJ29: =AF104/AVERAGE(AF101:AF107) -> 1.0882978 | EK29: 1 | EN29: 2014 | EO29: =AG101/AVERAGE(AG98:AG104) -> 0.96689861 | EP29: =AG102/AVERAGE(AG99:AG105) -> 0.9523129 | EQ29: =AG103/AVERAGE(AG100:AG106) -> 1.0208199 | ER29: =AG104/AVERAGE(AG101:AG107) -> 1.0265343 | ES29: 1 | EV29: 2014 | EW29: =AH101/AVERAGE(AH98:AH104) -> 1.0532409 | EX29: =AH102/AVERAGE(AH99:AH105) -> 0.91099631 | EY29: =AH103/AVERAGE(AH100:AH106) -> 0.96550013 | EZ29: =AH104/AVERAGE(AH101:AH107) -> 1.046164 | FA29: 1 | FD29: 2014 | FE29: =AI101/AVERAGE(AI98:AI104) -> 1.0446338 | FF29: =AI102/AVERAGE(AI99:AI105) -> 0.95309837 | FG29: =AI103/AVERAGE(AI100:AI106) -> 0.97270866 | FH29: =AI104/AVERAGE(AI101:AI107) -> 1.0388925 | FI29: 1
A30: 1996 Q2 | B30: =LEFT(A30,4) -> 1996 | C30: =RIGHT(A30,2) -> Q2 | D30: =HAVERQ!C36 -> 241559 | E30: =HAVERQ!D36 -> 8068 | F30: =HAVERQ!E36 -> 82760 | G30: =HAVERQ!F36 -> 71846 | H30: =HAVERQ!G36 -> -718 | I30: =HAVERQ!H36 -> 67 | J30: =HAVERQ!I36 -> 94853 | K30: =HAVERQ!J36 -> 84635 | L30: =HAVERQ!U36 -> #N/A | M30: =HAVERQ!V36 -> #N/A | N30: =HAVERQ!Y36 -> #N/A | O30: =HAVERQ!Z36 -> #N/A | P30: =HAVERQ!AA36 -> #N/A | Q30: =HAVERQ!AB36 -> #N/A | R30: =HAVERQ!AC36 -> #N/A | U30: =HAVERQ!M36 -> 234953 | V30: =HAVERQ!N36 -> 8064 | W30: =HAVERQ!O36 -> 82559 | X30: =HAVERQ!P36 -> 72009 | Y30: =HAVERQ!Q36 -> 2546 | Z30: =HAVERQ!R36 -> 66 | AA30: =HAVERQ!S36 -> 93853 | AB30: =HAVERQ!T36 -> 85942 | AC30: =HAVERQ!W36 -> #N/A | AD30: =HAVERQ!X36 -> #N/A | AE30: =HAVERQ!AD36 -> #N/A | AF30: =HAVERQ!AE36 -> #N/A | AG30: =HAVERQ!AF36 -> #N/A | AH30: =HAVERQ!AG36 -> #N/A | AI30: =HAVERQ!AH36 -> #N/A | AL30: 2015 | AM30: =OFFSET($D$5, (ROW(D26)-1)*4,0)/OFFSET($U$5, (ROW(U26)-1)*4,0) -> 1.0294747 | AN30: =OFFSET($E$5, (ROW(E26)-1)*4,0)/OFFSET($V$5, (ROW(V26)-1)*4,0) -> 1 | AO30: =OFFSET(F$5, (ROW(F26)-1)*4,0)/OFFSET(W$5, (ROW(W26)-1)*4,0) -> 0.9842894 | AP30: =OFFSET(G$5, (ROW(G26)-1)*4,0)/OFFSET(X$5, (ROW(X26)-1)*4,0) -> 0.98706239 | AQ30: =OFFSET(H$5, (ROW(H26)-1)*4,0)/OFFSET(Y$5, (ROW(Y26)-1)*4,0) -> 0.49102084 | AR30: =OFFSET(I$5, (ROW(I26)-1)*4,0)/OFFSET(Z$5, (ROW(Z26)-1)*4,0) -> 1.1742028 | AS30: =OFFSET(J$5, (ROW(J26)-1)*4,0)/OFFSET(AA$5, (ROW(AA26)-1)*4,0) -> 1.0221692 | AT30: =OFFSET(K$5, (ROW(K26)-1)*4,0)/OFFSET(AB$5, (ROW(AB26)-1)*4,0) -> 1.0194637 | AU30: =OFFSET(L$5, (ROW(L26)-1)*4,0)/OFFSET(AC$5, (ROW(AC26)-1)*4,0) -> 1.0495392 | AV30: =OFFSET(M$5, (ROW(M26)-1)*4,0)/OFFSET(AD$5, (ROW(AD26)-1)*4,0) -> 0.75315292 | ... BA30: =OFFSET(R$5, (ROW(R26)-1)*4,0)/OFFSET(AI$5, (ROW(AI26)-1)*4,0) -> 0.97735279 | BD30: 2015 | BE30: =U105/AVERAGE(U102:U108) -> 0.96944099 | BF30: =U106/AVERAGE(U103:U109) -> 0.98328322 | BG30: =U107/AVERAGE(U104:U110) -> 1.0167846 | BH30: =U108/AVERAGE(U105:U111) -> 1.0204222 | BI30: 1 | BL30: 2015 | BM30: =V105/AVERAGE(V102:V108) -> 0.9722574 | BN30: =V106/AVERAGE(V103:V109) -> 1.0281488 | BO30: =V107/AVERAGE(V104:V110) -> 1.0232246 | BP30: =V108/AVERAGE(V105:V111) -> 1.0090646 | BQ30: 1 | BT30: 2015 | BU30: =W105/AVERAGE(W102:W108) -> 1.0102901 | BV30: =W106/AVERAGE(W103:W109) -> 0.99426742 | BW30: =W107/AVERAGE(W104:W110) -> 0.99541029 | BX30: =W108/AVERAGE(W105:W111) -> 1.0012681 | BY30: 1 | CB30: 2015 | CC30: =X105/AVERAGE(X102:X108) -> 1.0438237 | CD30: =X106/AVERAGE(X103:X109) -> 0.95786355 | CE30: =X107/AVERAGE(X104:X110) -> 0.96868541 | CF30: =X108/AVERAGE(X105:X111) -> 1.0283427 | CG30: 1 | CJ30: 2015 | CK30: =Y105/AVERAGE(Y102:Y108) -> 2.0934861 | CL30: =Y106/AVERAGE(Y103:Y109) -> -2.0979913 | CM30: =Y107/AVERAGE(Y104:Y110) -> -1.7228331 | CN30: =Y108/AVERAGE(Y105:Y111) -> 20.791261 | CO30: 1 | CR30: 2015 | CS30: =AA105/AVERAGE(AA102:AA108) -> 0.97079237 | CT30: =AA106/AVERAGE(AA103:AA109) -> 1.0305147 | CU30: =AA107/AVERAGE(AA104:AA110) -> 0.96761268 | CV30: =AA108/AVERAGE(AA105:AA111) -> 1.0287156 | CW30: 1 | CZ30: 2015 | DA30: =AB105/AVERAGE(AB102:AB108) -> 0.99897299 | DB30: =AB106/AVERAGE(AB103:AB109) -> 0.98110164 | DC30: =AB107/AVERAGE(AB104:AB110) -> 1.0011199 | DD30: =AB108/AVERAGE(AB105:AB111) -> 1.0038457 | DE30: 1 | DH30: 2015 | DI30: =AC105/AVERAGE(AC102:AC108) -> 0.97509908 | DJ30: =AC106/AVERAGE(AC103:AC109) -> 0.98105882 | DK30: =AC107/AVERAGE(AC104:AC110) -> 0.96280448 | DL30: =AC108/AVERAGE(AC105:AC111) -> 1.0674673 | DM30: 1 | DP30: 2015 | DQ30: =AD105/AVERAGE(AD102:AD108) -> 1.5054338 | DR30: =AD106/AVERAGE(AD103:AD109) -> 0.79806973 | DS30: =AD107/AVERAGE(AD104:AD110) -> 0.88966414 | DT30: =AD108/AVERAGE(AD105:AD111) -> 0.88365682 | DU30: 1 | DX30: 2015 | DY30: =AE105/AVERAGE(AE102:AE108) -> 1.4697421 | DZ30: =AE106/AVERAGE(AE103:AE109) -> 0.87384876 | EA30: =AE107/AVERAGE(AE104:AE110) -> 0.70875831 | EB30: =AE108/AVERAGE(AE105:AE111) -> 0.95310867 | EC30: 1 | EF30: 2015 | EG30: =AF105/AVERAGE(AF102:AF108) -> 1.0379402 | EH30: =AF106/AVERAGE(AF103:AF109) -> 0.87962636 | EI30: =AF107/AVERAGE(AF104:AF110) -> 0.93148606 | EJ30: =AF108/AVERAGE(AF105:AF111) -> 1.096451 | EK30: 1 | EN30: 2015 | EO30: =AG105/AVERAGE(AG102:AG108) -> 0.95259902 | EP30: =AG106/AVERAGE(AG103:AG109) -> 1.007048 | EQ30: =AG107/AVERAGE(AG104:AG110) -> 1.013895 | ER30: =AG108/AVERAGE(AG105:AG111) -> 1.025464 | ES30: 1 | EV30: 2015 | EW30: =AH105/AVERAGE(AH102:AH108) -> 1.0447115 | EX30: =AH106/AVERAGE(AH103:AH109) -> 0.95161963 | EY30: =AH107/AVERAGE(AH104:AH110) -> 1.0110175 | EZ30: =AH108/AVERAGE(AH105:AH111) -> 1.0333694 | FA30: 1 | FD30: 2015 | FE30: =AI105/AVERAGE(AI102:AI108) -> 1.0105912 | FF30: =AI106/AVERAGE(AI103:AI109) -> 1.0029006 | FG30: =AI107/AVERAGE(AI104:AI110) -> 0.97670191 | FH30: =AI108/AVERAGE(AI105:AI111) -> 0.99936078 | FI30: 1
