Workbook
Name Data: [1]sheet0!$C$2

Sheet CHARTS>>

Sheet SCENARIO CHECKS>>

Sheet DATA>>

Sheet Chart Data
A1: GDP | F1: Migration assumptions | L1: POPW (%y/y) | Q1: PSCB (% of GDP) | V1: PSNFL (% of GDP) | AB1: Employment by sector & nationality | AF1: Employment by sector & nationality | AJ1: TOT | AK1: UK | AP1: Old age dependency ratio | AU1: Old age dependency ratio | BD1: SCENARIO RESULTS >> | BE1: GDP (%y/y) | BJ1: YHAT (%y/y) | BO1: Unemployment | BT1: ETILO (%y/y) | BY1: CUMOD | CD1: Bank Rate | CI1: CPI (%y/y) | CN1: GEXP per head | CS1: GREV per head | CX1: GDP per head | DC1: Potential output - baseline | DV1: Potential output - upside | EO1: Potential output - zero net migration
B2: Baseline | C2: Upside | D2: Zero net migration | G2: Baseline | H2: Upside | I2: Zero net migration | M2: =$B$2 -> Baseline | N2: =$C$2 -> Upside | O2: =$D$2 -> Zero net migration | R2: =$B$2 -> Baseline | S2: =$C$2 -> Upside | T2: =$D$2 -> Zero net migration | W2: =$B$2 -> Baseline | X2: =$C$2 -> Upside | Y2: =$D$2 -> Zero net migration | AC2: Non-UK share | AG2: Non-UK share | AJ2: Total | AK2: UK | AL2: Non-UK | AQ2: =$B$2 -> Baseline | AR2: =$C$2 -> Upside | AS2: =$D$2 -> Zero net migration | AV2: UK | AW2: US | AX2: Japan | AY2: Germany | AZ2: France | BA2: Italy | BB2: Canada | BF2: =$B$2 -> Baseline | BG2: =$C$2 -> Upside | BH2: =$D$2 -> Zero net migration | BK2: =$B$2 -> Baseline | BL2: =$C$2 -> Upside | BM2: =$D$2 -> Zero net migration | BP2: Baseline | BQ2: Upside | BR2: Zero net migration | BU2: =$B$2 -> Baseline | BV2: =$C$2 -> Upside | BW2: =$D$2 -> Zero net migration | BZ2: Baseline | CA2: Upside | CB2: Zero net migration | CE2: Baseline | CF2: Upside | CG2: Zero net migration | CJ2: =$B$2 -> Baseline | CK2: =$C$2 -> Upside | CL2: =$D$2 -> Zero net migration | CO2: =$B$2 -> Baseline | CP2: =$C$2 -> Upside | CQ2: =$D$2 -> Zero net migration | CT2: =$B$2 -> Baseline | CU2: =$C$2 -> Upside | CV2: =$D$2 -> Zero net migration | CY2: =$B$2 -> Baseline | CZ2: =$C$2 -> Upside | DA2: =$D$2 -> Zero net migration | DD2: YHAT | DE2: ESTAR | DF2: AVHR | DG2: EDUC | DH2: POP15_64 | DI2: K | DJ2: TREND | DL2: ESTAR * AVHR | DM2: EDUC / POP15_64 | DN2: K | DO2: TREND | DP2: YHAT | DQ2: GDP | DS2: Potential output | DT2: GDP | DW2: YHAT | DX2: ESTAR | DY2: AVHR | DZ2: EDUC | EA2: POP15_64 | EB2: K | EC2: TREND | EE2: ESTAR * AVHR | EF2: EDUC / POP15_64 | EG2: K | EH2: TREND | EI2: YHAT | EJ2: GDP | EL2: Potential output | EM2: GDP | EP2: YHAT | EQ2: ESTAR | ER2: AVHR | ES2: EDUC | ET2: POP15_64 | EU2: K | EV2: TREND | EX2: ESTAR * AVHR | EY2: EDUC / POP15_64 | EZ2: K | FA2: TREND | FB2: YHAT | FC2: GDP | FE2: Potential output | FF2: GDP
A3: 2020 | B3: ='GEM data - Baseline'!$F167 -> 652180 | C3: ='GEM data - Upside'!$F167 -> 652180 | D3: ='GEM data - Zero_net'!$F167 -> 652180 | F3: 2000 | G3: ='[2]Chart Data'!M4 -> 139.3 | L3: 2020 | M3: =100*(('GEM data - Baseline'!$P167/'GEM data - Baseline'!$P163)-1) -> 0.98561726 | N3: =100*(('GEM data - Upside'!$P167/'GEM data - Upside'!$P163)-1) -> 0.98561726 | O3: =100*(('GEM data - Zero_net'!$P167/'GEM data - Zero_net'!$P163)-1) -> 0.98561726 | Q3: 2020 | R3: =100*(SUMIF('GEM data - Baseline'!$C:$C,'Chart Data'!$Q3,'GEM data - Baseline'!$Q:$Q)/SUMIF('GEM data - Baseline'!$C:$C,'Chart Data'!$Q3,'GEM data - Baseline'!$S:$S)) -> -11.329793 | S3: =100*(SUMIF('GEM data - Upside'!$C:$C,'Chart Data'!$Q3,'GEM data - Upside'!$Q:$Q)/SUMIF('GEM data - Upside'!$C:$C,'Chart Data'!$Q3,'GEM data - Upside'!$S:$S)) -> -11.329793 | T3: =100*(SUMIF('GEM data - Zero_net'!$C:$C,'Chart Data'!$Q3,'GEM data - Zero_net'!$Q:$Q)/SUMIF('GEM data - Zero_net'!$C:$C,'Chart Data'!$Q3,'GEM data - Zero_net'!$S:$S)) -> -11.329793 | V3: 2020 | W3: =100*(SUMIF('GEM data - Baseline'!$D:$D,'Chart Data'!$Q3,'GEM data - Baseline'!$R:$R)/SUMIF('GEM data - Baseline'!$C:$C,'Chart Data'!$Q3,'GEM data - Baseline'!$S:$S)) -> 87.638115 | X3: =100*(SUMIF('GEM data - Upside'!$D:$D,'Chart Data'!$Q3,'GEM data - Upside'!$R:$R)/SUMIF('GEM data - Upside'!$C:$C,'Chart Data'!$Q3,'GEM data - Upside'!$S:$S)) -> 87.638115 | Y3: =100*(SUMIF('GEM data - Zero_net'!$D:$D,'Chart Data'!$Q3,'GEM data - Zero_net'!$R:$R)/SUMIF('GEM data - Zero_net'!$C:$C,'Chart Data'!$Q3,'GEM data - Zero_net'!$S:$S)) -> 87.638115 | AA3: 1 | AB3: =VLOOKUP($AA3,$AE$3:$AG$21,2,FALSE) -> Administrative services | AC3: =VLOOKUP($AA3,$AE$3:$AG$21,3,FALSE) -> 33.584697 | AE3: =RANK(AG3,$AG$3:$AG$21) -> 8 | AF3: Agriculture | AG3: =100*(AL3/AJ3) -> 18.872631 | AI3: AGR | AJ3: {=INDEX('HMRC emp by ind and nat'!$A$149:$C$233,MATCH(1,('HMRC emp by ind and nat'!$A$145:$CG$145=AJ$1)*('HMRC emp by ind and nat'!$A$146:$CG$146=$AI3),0),3)} -> 200466.67 | AK3: {=INDEX('HMRC emp by ind and nat'!$A$149:$C$233,MATCH(1,('HMRC emp by ind and nat'!$A$145:$CG$145=AK$1)*('HMRC emp by ind and nat'!$A$146:$CG$146=$AI3),0),3)} -> 162633.33 | AL3: =AJ3-AK3 -> 37833.333 | AP3: 2000 | AQ3: =AVERAGEIF('GEM data - Baseline'!$B:$B,'Chart Data'!$AP3,'GEM data - Baseline'!$AE:$AE) -> 25.758363 | AR3: =AVERAGEIF('GEM data - Upside'!$B:$B,'Chart Data'!$AP3,'GEM data - Upside'!$AE:$AE) -> 25.758363 | AS3: =AVERAGEIF('GEM data - Zero_net'!$B:$B,'Chart Data'!$AP3,'GEM data - Zero_net'!$AE:$AE) -> 25.758363 | AU3: 2000 | AV3: =AVERAGEIF('GEM data - Baseline'!$B:$B,'Chart Data'!$AP3,'GEM data - Baseline'!AE:AE) -> 25.758363 | AW3: =AVERAGEIF('GEM data - Baseline'!$B:$B,'Chart Data'!$AP3,'GEM data - Baseline'!AF:AF) -> 16.497422 | AX3: =AVERAGEIF('GEM data - Baseline'!$B:$B,'Chart Data'!$AP3,'GEM data - Baseline'!AG:AG) -> 25.58323 | AY3: =AVERAGEIF('GEM data - Baseline'!$B:$B,'Chart Data'!$AP3,'GEM data - Baseline'!AH:AH) -> 24.29539 | AZ3: =AVERAGEIF('GEM data - Baseline'!$B:$B,'Chart Data'!$AP3,'GEM data - Baseline'!AI:AI) -> 24.42167 | BA3: =AVERAGEIF('GEM data - Baseline'!$B:$B,'Chart Data'!$AP3,'GEM data - Baseline'!AJ:AJ) -> 28.48933 | BB3: =AVERAGEIF('GEM data - Baseline'!$B:$B,'Chart Data'!$AP3,'GEM data - Baseline'!AK:AK) -> 15.987073 | BE3: 2020 | BF3: =100*(('GEM data - Baseline'!$F167/'GEM data - Baseline'!$F163)-1) -> -1.995023 | BG3: =100*(('GEM data - Upside'!$F167/'GEM data - Upside'!$F163)-1) -> -1.995023 | BH3: =100*(('GEM data - Zero_net'!$F167/'GEM data - Zero_net'!$F163)-1) -> -1.995023 | BJ3: 2020 | BK3: =100*(('GEM data - Baseline'!$U167/'GEM data - Baseline'!$U163)-1) -> -0.88167579 | BL3: =100*(('GEM data - Upside'!$U167/'GEM data - Upside'!$U163)-1) -> -0.88167579 | BM3: =100*(('GEM data - Zero_net'!$U167/'GEM data - Zero_net'!$U163)-1) -> -0.88167579 | BO3: 2020 | BP3: ='GEM data - Baseline'!$O167 -> 4.1 | BQ3: ='GEM data - Upside'!$O167 -> 4.1 | BR3: ='GEM data - Zero_net'!$O167 -> 4.1 | BT3: 2020 | BU3: =100*(('GEM data - Baseline'!$L167/'GEM data - Baseline'!$L163)-1) -> 0.61020259 | BV3: =100*(('GEM data - Upside'!$L167/'GEM data - Upside'!$L163)-1) -> 0.61020259 | BW3: =100*(('GEM data - Zero_net'!$L167/'GEM data - Zero_net'!$L163)-1) -> 0.61020259 | BY3: 2020 | BZ3: ='GEM data - Baseline'!$T167 -> -0.9545326 | CA3: ='GEM data - Upside'!$T167 -> -0.9545326 | CB3: ='GEM data - Zero_net'!$T167 -> -0.9545326 | CD3: 2020 | CE3: ='GEM data - Baseline'!$J167 -> 0.6138462 | CF3: ='GEM data - Upside'!$J167 -> 0.6138462 | CG3: ='GEM data - Zero_net'!$J167 -> 0.6138462 | CI3: 2020 | CJ3: =100*(('GEM data - Baseline'!$I167/'GEM data - Baseline'!$I163)-1) -> 1.6557638 | CK3: =100*(('GEM data - Upside'!$I167/'GEM data - Upside'!$I163)-1) -> 1.6557638 | CL3: =100*(('GEM data - Zero_net'!$I167/'GEM data - Zero_net'!$I163)-1) -> 1.6557638 | CN3: 2020 | CO3: =100*('GEM data - Baseline'!$AB167/'GEM data - Baseline'!$AD167) -> 343.17064 | CP3: =100*('GEM data - Upside'!$AB167/'GEM data - Upside'!$AD167) -> 343.17064 | CQ3: =100*('GEM data - Zero_net'!$AB167/'GEM data - Zero_net'!$AD167) -> 343.17064 | CS3: 2020 | CT3: =100*('GEM data - Baseline'!$AC167/'GEM data - Baseline'!$AD167) -> 342.29224 | CU3: =100*('GEM data - Upside'!$AC167/'GEM data - Upside'!$AD167) -> 342.29224 | CV3: =100*('GEM data - Zero_net'!$AC167/'GEM data - Zero_net'!$AD167) -> 342.29224 | CX3: 2020 | CY3: =100*('GEM data - Baseline'!$F167/'GEM data - Baseline'!$AD167) -> 977.60523 | CZ3: =100*('GEM data - Upside'!$F167/'GEM data - Upside'!$AD167) -> 977.60523 | DA3: =100*('GEM data - Zero_net'!$F167/'GEM data - Zero_net'!$AD167) -> 977.60523 | DC3: 1980 | DD3: =SUMIF('GEM data - Baseline'!$B:$B,'Chart Data'!$DC3,'GEM data - Baseline'!$U:$U) -> 1164663.3 | DE3: =AVERAGEIF('GEM data - Baseline'!$B:$B,'Chart Data'!$DC3,'GEM data - Baseline'!$V:$V) -> 24765.53 | DF3: =AVERAGEIF('GEM data - Baseline'!$B:$B,'Chart Data'!$DC3,'GEM data - Baseline'!$W:$W) -> 0.001 | DG3: =AVERAGEIF('GEM data - Baseline'!$B:$B,'Chart Data'!$DC3,'GEM data - Baseline'!$X:$X) -> 306731.33 | DH3: =AVERAGEIF('GEM data - Baseline'!$B:$B,'Chart Data'!$DC3,'GEM data - Baseline'!$Y:$Y) -> 36102.315 | DI3: =AVERAGEIF('GEM data - Baseline'!$B:$B,'Chart Data'!$DC3,'GEM data - Baseline'!$Z:$Z) -> 1231755.5 | DJ3: =AVERAGEIF('GEM data - Baseline'!$B:$B,'Chart Data'!$DC3,'GEM data - Baseline'!$AA:$AA) -> -1.8272072 | DL3: =DE3*DF3 -> 24.76553 | DM3: =DG3/DH3 -> 8.4961678 | DN3: =DI3 -> 1231755.5 | DO3: =DJ3 -> -1.8272072 | DP3: =DD3 -> 1164663.3 | DQ3: =SUMIF('GEM data - Baseline'!$B:$B,'Chart Data'!$DC3,'GEM data - Baseline'!$F:$F) -> 1140989 | DV3: 1980 | DW3: =SUMIF('GEM data - Upside'!$B:$B,'Chart Data'!$DC3,'GEM data - Upside'!$U:$U) -> 1164663.3 | DX3: =AVERAGEIF('GEM data - Upside'!$B:$B,'Chart Data'!$DC3,'GEM data - Upside'!$V:$V) -> 24765.53 | DY3: =AVERAGEIF('GEM data - Upside'!$B:$B,'Chart Data'!$DC3,'GEM data - Upside'!$W:$W) -> 0.001 | DZ3: =AVERAGEIF('GEM data - Upside'!$B:$B,'Chart Data'!$DC3,'GEM data - Upside'!$X:$X) -> 306731.33 | EA3: =AVERAGEIF('GEM data - Upside'!$B:$B,'Chart Data'!$DC3,'GEM data - Upside'!$Y:$Y) -> 36102.315 | EB3: =AVERAGEIF('GEM data - Upside'!$B:$B,'Chart Data'!$DC3,'GEM data - Upside'!$Z:$Z) -> 1231755.5 | EC3: =AVERAGEIF('GEM data - Upside'!$B:$B,'Chart Data'!$DC3,'GEM data - Upside'!$AA:$AA) -> -1.8272072 | EE3: =DX3*DY3 -> 24.76553 | EF3: =DZ3/EA3 -> 8.4961678 | EG3: =EB3 -> 1231755.5 | EH3: =EC3 -> -1.8272072 | EI3: =DW3 -> 1164663.3 | EJ3: =SUMIF('GEM data - Upside'!$B:$B,'Chart Data'!$DC3,'GEM data - Upside'!$F:$F) -> 1140989 | EO3: 1980 | EP3: =SUMIF('GEM data - Zero_net'!$B:$B,'Chart Data'!$DC3,'GEM data - Zero_net'!$U:$U) -> 1164663.3 | EQ3: =AVERAGEIF('GEM data - Zero_net'!$B:$B,'Chart Data'!$DC3,'GEM data - Zero_net'!$V:$V) -> 24765.53 | ER3: =AVERAGEIF('GEM data - Zero_net'!$B:$B,'Chart Data'!$DC3,'GEM data - Zero_net'!$W:$W) -> 0.001 | ES3: =AVERAGEIF('GEM data - Zero_net'!$B:$B,'Chart Data'!$DC3,'GEM data - Zero_net'!$X:$X) -> 306731.33 | ET3: =AVERAGEIF('GEM data - Zero_net'!$B:$B,'Chart Data'!$DC3,'GEM data - Zero_net'!$Y:$Y) -> 36102.315 | EU3: =AVERAGEIF('GEM data - Zero_net'!$B:$B,'Chart Data'!$DC3,'GEM data - Zero_net'!$Z:$Z) -> 1231755.5 | EV3: =AVERAGEIF('GEM data - Zero_net'!$B:$B,'Chart Data'!$DC3,'GEM data - Zero_net'!$AA:$AA) -> -1.8272072 | EX3: =EQ3*ER3 -> 24.76553 | EY3: =ES3/ET3 -> 8.4961678 | EZ3: =EU3 -> 1231755.5 | FA3: =EV3 -> -1.8272072 | FB3: =EP3 -> 1164663.3 | FC3: =SUMIF('GEM data - Zero_net'!$B:$B,'Chart Data'!$DC3,'GEM data - Zero_net'!$F:$F) -> 1140989
B4: ='GEM data - Baseline'!$F168 -> 522356 | C4: ='GEM data - Upside'!$F168 -> 522356 | D4: ='GEM data - Zero_net'!$F168 -> 522356 | F4: 2001 | G4: ='[2]Chart Data'!M5 -> 153.2 | M4: =100*(('GEM data - Baseline'!$P168/'GEM data - Baseline'!$P164)-1) -> 0.91787615 | N4: =100*(('GEM data - Upside'!$P168/'GEM data - Upside'!$P164)-1) -> 0.91787615 | O4: =100*(('GEM data - Zero_net'!$P168/'GEM data - Zero_net'!$P164)-1) -> 0.91787615 | Q4: 2021 | R4: =100*(SUMIF('GEM data - Baseline'!$C:$C,'Chart Data'!$Q4,'GEM data - Baseline'!$Q:$Q)/SUMIF('GEM data - Baseline'!$C:$C,'Chart Data'!$Q4,'GEM data - Baseline'!$S:$S)) -> -2.8065235 | S4: =100*(SUMIF('GEM data - Upside'!$C:$C,'Chart Data'!$Q4,'GEM data - Upside'!$Q:$Q)/SUMIF('GEM data - Upside'!$C:$C,'Chart Data'!$Q4,'GEM data - Upside'!$S:$S)) -> -2.8065235 | T4: =100*(SUMIF('GEM data - Zero_net'!$C:$C,'Chart Data'!$Q4,'GEM data - Zero_net'!$Q:$Q)/SUMIF('GEM data - Zero_net'!$C:$C,'Chart Data'!$Q4,'GEM data - Zero_net'!$S:$S)) -> -2.8065235 | V4: 2021 | W4: =100*(SUMIF('GEM data - Baseline'!$D:$D,'Chart Data'!$Q4,'GEM data - Baseline'!$R:$R)/SUMIF('GEM data - Baseline'!$C:$C,'Chart Data'!$Q4,'GEM data - Baseline'!$S:$S)) -> 82.591698 | X4: =100*(SUMIF('GEM data - Upside'!$D:$D,'Chart Data'!$Q4,'GEM data - Upside'!$R:$R)/SUMIF('GEM data - Upside'!$C:$C,'Chart Data'!$Q4,'GEM data - Upside'!$S:$S)) -> 82.591698 | Y4: =100*(SUMIF('GEM data - Zero_net'!$D:$D,'Chart Data'!$Q4,'GEM data - Zero_net'!$R:$R)/SUMIF('GEM data - Zero_net'!$C:$C,'Chart Data'!$Q4,'GEM data - Zero_net'!$S:$S)) -> 82.591698 | AA4: 2 | AB4: =VLOOKUP($AA4,$AE$3:$AG$21,2,FALSE) -> Accommodation & food | AC4: =VLOOKUP($AA4,$AE$3:$AG$21,3,FALSE) -> 30.691508 | AE4: =RANK(AG4,$AG$3:$AG$21) -> 17 | AF4: Extraction | AG4: =100*(AL4/AJ4) -> 9.6848578 | AI4: MIN | AJ4: {=INDEX('HMRC emp by ind and nat'!$A$149:$C$233,MATCH(1,('HMRC emp by ind and nat'!$A$145:$CG$145=AJ$1)*('HMRC emp by ind and nat'!$A$146:$CG$146=$AI4),0),3)} -> 43366.667 | AK4: {=INDEX('HMRC emp by ind and nat'!$A$149:$C$233,MATCH(1,('HMRC emp by ind and nat'!$A$145:$CG$145=AK$1)*('HMRC emp by ind and nat'!$A$146:$CG$146=$AI4),0),3)} -> 39166.667 | AL4: =AJ4-AK4 -> 4200 | AP4: 2001 | AQ4: =AVERAGEIF('GEM data - Baseline'!$B:$B,'Chart Data'!$AP4,'GEM data - Baseline'!$AE:$AE) -> 25.742498 | AR4: =AVERAGEIF('GEM data - Upside'!$B:$B,'Chart Data'!$AP4,'GEM data - Upside'!$AE:$AE) -> 25.742498 | AS4: =AVERAGEIF('GEM data - Zero_net'!$B:$B,'Chart Data'!$AP4,'GEM data - Zero_net'!$AE:$AE) -> 25.742498 | AU4: 2001 | AV4: =AVERAGEIF('GEM data - Baseline'!$B:$B,'Chart Data'!$AP4,'GEM data - Baseline'!AE:AE) -> 25.742498 | AW4: =AVERAGEIF('GEM data - Baseline'!$B:$B,'Chart Data'!$AP4,'GEM data - Baseline'!AF:AF) -> 16.409743 | AX4: =AVERAGEIF('GEM data - Baseline'!$B:$B,'Chart Data'!$AP4,'GEM data - Baseline'!AG:AG) -> 26.620055 | AY4: =AVERAGEIF('GEM data - Baseline'!$B:$B,'Chart Data'!$AP4,'GEM data - Baseline'!AH:AH) -> 24.97196 | AZ4: =AVERAGEIF('GEM data - Baseline'!$B:$B,'Chart Data'!$AP4,'GEM data - Baseline'!AI:AI) -> 24.609677 | BA4: =AVERAGEIF('GEM data - Baseline'!$B:$B,'Chart Data'!$AP4,'GEM data - Baseline'!AJ:AJ) -> 29.065067 | BB4: =AVERAGEIF('GEM data - Baseline'!$B:$B,'Chart Data'!$AP4,'GEM data - Baseline'!AK:AK) -> 16.060247 | BF4: =100*(('GEM data - Baseline'!$F168/'GEM data - Baseline'!$F164)-1) -> -21.671078 | BG4: =100*(('GEM data - Upside'!$F168/'GEM data - Upside'!$F164)-1) -> -21.671078 | BH4: =100*(('GEM data - Zero_net'!$F168/'GEM data - Zero_net'!$F164)-1) -> -21.671078 | BK4: =100*(('GEM data - Baseline'!$U168/'GEM data - Baseline'!$U164)-1) -> -13.133792 | BL4: =100*(('GEM data - Upside'!$U168/'GEM data - Upside'!$U164)-1) -> -13.133792 | BM4: =100*(('GEM data - Zero_net'!$U168/'GEM data - Zero_net'!$U164)-1) -> -13.133792 | BP4: ='GEM data - Baseline'!$O168 -> 4.1 | BQ4: ='GEM data - Upside'!$O168 -> 4.1 | BR4: ='GEM data - Zero_net'!$O168 -> 4.1 | BU4: =100*(('GEM data - Baseline'!$L168/'GEM data - Baseline'!$L164)-1) -> -0.99808877 | BV4: =100*(('GEM data - Upside'!$L168/'GEM data - Upside'!$L164)-1) -> -0.99808877 | BW4: =100*(('GEM data - Zero_net'!$L168/'GEM data - Zero_net'!$L164)-1) -> -0.99808877 | BZ4: ='GEM data - Baseline'!$T168 -> -10.17914 | CA4: ='GEM data - Upside'!$T168 -> -10.17914 | CB4: ='GEM data - Zero_net'!$T168 -> -10.17914 | CE4: ='GEM data - Baseline'!$J168 -> 0.1 | CF4: ='GEM data - Upside'!$J168 -> 0.1 | CG4: ='GEM data - Zero_net'!$J168 -> 0.1 | CJ4: =100*(('GEM data - Baseline'!$I168/'GEM data - Baseline'!$I164)-1) -> 0.68024119 | CK4: =100*(('GEM data - Upside'!$I168/'GEM data - Upside'!$I164)-1) -> 0.68024119 | CL4: =100*(('GEM data - Zero_net'!$I168/'GEM data - Zero_net'!$I164)-1) -> 0.68024119 | CO4: =100*('GEM data - Baseline'!$AB168/'GEM data - Baseline'!$AD168) -> 450.69973 | CP4: =100*('GEM data - Upside'!$AB168/'GEM data - Upside'!$AD168) -> 450.69973 | CQ4: =100*('GEM data - Zero_net'!$AB168/'GEM data - Zero_net'!$AD168) -> 450.69973 | CT4: =100*('GEM data - Baseline'!$AC168/'GEM data - Baseline'!$AD168) -> 252.47228 | CU4: =100*('GEM data - Upside'!$AC168/'GEM data - Upside'!$AD168) -> 252.47228 | CV4: =100*('GEM data - Zero_net'!$AC168/'GEM data - Zero_net'!$AD168) -> 252.47228 | CY4: =100*('GEM data - Baseline'!$F168/'GEM data - Baseline'!$AD168) -> 782.67306 | CZ4: =100*('GEM data - Upside'!$F168/'GEM data - Upside'!$AD168) -> 782.67306 | DA4: =100*('GEM data - Zero_net'!$F168/'GEM data - Zero_net'!$AD168) -> 782.67306 | DC4: 1981 | DD4: =SUMIF('GEM data - Baseline'!$B:$B,'Chart Data'!$DC4,'GEM data - Baseline'!$U:$U) -> 1182107.9 | DE4: =AVERAGEIF('GEM data - Baseline'!$B:$B,'Chart Data'!$DC4,'GEM data - Baseline'!$V:$V) -> 24659.65 | DF4: =AVERAGEIF('GEM data - Baseline'!$B:$B,'Chart Data'!$DC4,'GEM data - Baseline'!$W:$W) -> 0.001 | DG4: =AVERAGEIF('GEM data - Baseline'!$B:$B,'Chart Data'!$DC4,'GEM data - Baseline'!$X:$X) -> 309382.7 | DH4: =AVERAGEIF('GEM data - Baseline'!$B:$B,'Chart Data'!$DC4,'GEM data - Baseline'!$Y:$Y) -> 36300.177 | DI4: =AVERAGEIF('GEM data - Baseline'!$B:$B,'Chart Data'!$DC4,'GEM data - Baseline'!$Z:$Z) -> 1243839.2 | DJ4: =AVERAGEIF('GEM data - Baseline'!$B:$B,'Chart Data'!$DC4,'GEM data - Baseline'!$AA:$AA) -> -1.8145853 | DL4: =DE4*DF4 -> 24.65965 | DM4: =DG4/DH4 -> 8.5228977 | DN4: =DI4 -> 1243839.2 | DO4: =DJ4 -> -1.8145853 | DP4: =DD4 -> 1182107.9 | DQ4: =SUMIF('GEM data - Baseline'!$B:$B,'Chart Data'!$DC4,'GEM data - Baseline'!$F:$F) -> 1134663 | DS4: =100*((DP4/DP3)-1) -> 1.4978234 | DT4: =100*((DQ4/DQ3)-1) -> -0.55443129 | DV4: 1981 | DW4: =SUMIF('GEM data - Upside'!$B:$B,'Chart Data'!$DC4,'GEM data - Upside'!$U:$U) -> 1182107.9 | DX4: =AVERAGEIF('GEM data - Upside'!$B:$B,'Chart Data'!$DC4,'GEM data - Upside'!$V:$V) -> 24659.65 | DY4: =AVERAGEIF('GEM data - Upside'!$B:$B,'Chart Data'!$DC4,'GEM data - Upside'!$W:$W) -> 0.001 | DZ4: =AVERAGEIF('GEM data - Upside'!$B:$B,'Chart Data'!$DC4,'GEM data - Upside'!$X:$X) -> 309382.7 | EA4: =AVERAGEIF('GEM data - Upside'!$B:$B,'Chart Data'!$DC4,'GEM data - Upside'!$Y:$Y) -> 36300.177 | EB4: =AVERAGEIF('GEM data - Upside'!$B:$B,'Chart Data'!$DC4,'GEM data - Upside'!$Z:$Z) -> 1243839.2 | EC4: =AVERAGEIF('GEM data - Upside'!$B:$B,'Chart Data'!$DC4,'GEM data - Upside'!$AA:$AA) -> -1.8145853 | EE4: =DX4*DY4 -> 24.65965 | EF4: =DZ4/EA4 -> 8.5228977 | EG4: =EB4 -> 1243839.2 | EH4: =EC4 -> -1.8145853 | EI4: =DW4 -> 1182107.9 | EJ4: =SUMIF('GEM data - Upside'!$B:$B,'Chart Data'!$DC4,'GEM data - Upside'!$F:$F) -> 1134663 | EL4: =100*((EI4/EI3)-1) -> 1.4978234 | EM4: =100*((EJ4/EJ3)-1) -> -0.55443129 | EO4: 1981 | EP4: =SUMIF('GEM data - Zero_net'!$B:$B,'Chart Data'!$DC4,'GEM data - Zero_net'!$U:$U) -> 1182107.9 | EQ4: =AVERAGEIF('GEM data - Zero_net'!$B:$B,'Chart Data'!$DC4,'GEM data - Zero_net'!$V:$V) -> 24659.65 | ER4: =AVERAGEIF('GEM data - Zero_net'!$B:$B,'Chart Data'!$DC4,'GEM data - Zero_net'!$W:$W) -> 0.001 | ES4: =AVERAGEIF('GEM data - Zero_net'!$B:$B,'Chart Data'!$DC4,'GEM data - Zero_net'!$X:$X) -> 309382.7 | ET4: =AVERAGEIF('GEM data - Zero_net'!$B:$B,'Chart Data'!$DC4,'GEM data - Zero_net'!$Y:$Y) -> 36300.177 | EU4: =AVERAGEIF('GEM data - Zero_net'!$B:$B,'Chart Data'!$DC4,'GEM data - Zero_net'!$Z:$Z) -> 1243839.2 | EV4: =AVERAGEIF('GEM data - Zero_net'!$B:$B,'Chart Data'!$DC4,'GEM data - Zero_net'!$AA:$AA) -> -1.8145853 | EX4: =EQ4*ER4 -> 24.65965 | EY4: =ES4/ET4 -> 8.5228977 | EZ4: =EU4 -> 1243839.2 | FA4: =EV4 -> -1.8145853 | FB4: =EP4 -> 1182107.9 | FC4: =SUMIF('GEM data - Zero_net'!$B:$B,'Chart Data'!$DC4,'GEM data - Zero_net'!$F:$F) -> 1134663 | FE4: =100*((FB4/FB3)-1) -> 1.4978234 | FF4: =100*((FC4/FC3)-1) -> -0.55443129
B5: ='GEM data - Baseline'!$F169 -> 610972 | C5: ='GEM data - Upside'!$F169 -> 610972 | D5: ='GEM data - Zero_net'!$F169 -> 610972 | F5: 2002 | G5: ='[2]Chart Data'!M6 -> 190.9 | M5: =100*(('GEM data - Baseline'!$P169/'GEM data - Baseline'!$P165)-1) -> 0.82324975 | N5: =100*(('GEM data - Upside'!$P169/'GEM data - Upside'!$P165)-1) -> 0.82324975 | O5: =100*(('GEM data - Zero_net'!$P169/'GEM data - Zero_net'!$P165)-1) -> 0.82324975 | Q5: 2022 | R5: =100*(SUMIF('GEM data - Baseline'!$C:$C,'Chart Data'!$Q5,'GEM data - Baseline'!$Q:$Q)/SUMIF('GEM data - Baseline'!$C:$C,'Chart Data'!$Q5,'GEM data - Baseline'!$S:$S)) -> -3.0590843 | S5: =100*(SUMIF('GEM data - Upside'!$C:$C,'Chart Data'!$Q5,'GEM data - Upside'!$Q:$Q)/SUMIF('GEM data - Upside'!$C:$C,'Chart Data'!$Q5,'GEM data - Upside'!$S:$S)) -> -3.0590843 | T5: =100*(SUMIF('GEM data - Zero_net'!$C:$C,'Chart Data'!$Q5,'GEM data - Zero_net'!$Q:$Q)/SUMIF('GEM data - Zero_net'!$C:$C,'Chart Data'!$Q5,'GEM data - Zero_net'!$S:$S)) -> -3.0590843 | V5: 2022 | W5: =100*(SUMIF('GEM data - Baseline'!$D:$D,'Chart Data'!$Q5,'GEM data - Baseline'!$R:$R)/SUMIF('GEM data - Baseline'!$C:$C,'Chart Data'!$Q5,'GEM data - Baseline'!$S:$S)) -> 81.818978 | X5: =100*(SUMIF('GEM data - Upside'!$D:$D,'Chart Data'!$Q5,'GEM data - Upside'!$R:$R)/SUMIF('GEM data - Upside'!$C:$C,'Chart Data'!$Q5,'GEM data - Upside'!$S:$S)) -> 81.818978 | Y5: =100*(SUMIF('GEM data - Zero_net'!$D:$D,'Chart Data'!$Q5,'GEM data - Zero_net'!$R:$R)/SUMIF('GEM data - Zero_net'!$C:$C,'Chart Data'!$Q5,'GEM data - Zero_net'!$S:$S)) -> 81.818978 | AA5: 3 | AB5: =VLOOKUP($AA5,$AE$3:$AG$21,2,FALSE) -> Health | AC5: =VLOOKUP($AA5,$AE$3:$AG$21,3,FALSE) -> 26.033779 | AE5: =RANK(AG5,$AG$3:$AG$21) -> 7 | AF5: Manufacturing | AG5: =100*(AL5/AJ5) -> 19.09214 | AI5: MAN | AJ5: {=INDEX('HMRC emp by ind and nat'!$A$149:$C$233,MATCH(1,('HMRC emp by ind and nat'!$A$145:$CG$145=AJ$1)*('HMRC emp by ind and nat'!$A$146:$CG$146=$AI5),0),3)} -> 2338833.3 | AK5: {=INDEX('HMRC emp by ind and nat'!$A$149:$C$233,MATCH(1,('HMRC emp by ind and nat'!$A$145:$CG$145=AK$1)*('HMRC emp by ind and nat'!$A$146:$CG$146=$AI5),0),3)} -> 1892300 | AL5: =AJ5-AK5 -> 446533.33 | AP5: 2002 | AQ5: =AVERAGEIF('GEM data - Baseline'!$B:$B,'Chart Data'!$AP5,'GEM data - Baseline'!$AE:$AE) -> 25.72545 | AR5: =AVERAGEIF('GEM data - Upside'!$B:$B,'Chart Data'!$AP5,'GEM data - Upside'!$AE:$AE) -> 25.72545 | AS5: =AVERAGEIF('GEM data - Zero_net'!$B:$B,'Chart Data'!$AP5,'GEM data - Zero_net'!$AE:$AE) -> 25.72545 | AU5: 2002 | AV5: =AVERAGEIF('GEM data - Baseline'!$B:$B,'Chart Data'!$AP5,'GEM data - Baseline'!AE:AE) -> 25.72545 | AW5: =AVERAGEIF('GEM data - Baseline'!$B:$B,'Chart Data'!$AP5,'GEM data - Baseline'!AF:AF) -> 16.331443 | AX5: =AVERAGEIF('GEM data - Baseline'!$B:$B,'Chart Data'!$AP5,'GEM data - Baseline'!AG:AG) -> 27.62727 | AY5: =AVERAGEIF('GEM data - Baseline'!$B:$B,'Chart Data'!$AP5,'GEM data - Baseline'!AH:AH) -> 25.666835 | AZ5: =AVERAGEIF('GEM data - Baseline'!$B:$B,'Chart Data'!$AP5,'GEM data - Baseline'!AI:AI) -> 24.764575 | BA5: =AVERAGEIF('GEM data - Baseline'!$B:$B,'Chart Data'!$AP5,'GEM data - Baseline'!AJ:AJ) -> 29.608413 | BB5: =AVERAGEIF('GEM data - Baseline'!$B:$B,'Chart Data'!$AP5,'GEM data - Baseline'!AK:AK) -> 16.10583 | BF5: =100*(('GEM data - Baseline'!$F169/'GEM data - Baseline'!$F165)-1) -> -8.8845375 | BG5: =100*(('GEM data - Upside'!$F169/'GEM data - Upside'!$F165)-1) -> -8.8845375 | BH5: =100*(('GEM data - Zero_net'!$F169/'GEM data - Zero_net'!$F165)-1) -> -8.8845375 | BK5: =100*(('GEM data - Baseline'!$U169/'GEM data - Baseline'!$U165)-1) -> -8.0989333 | BL5: =100*(('GEM data - Upside'!$U169/'GEM data - Upside'!$U165)-1) -> -8.0989333 | BM5: =100*(('GEM data - Zero_net'!$U169/'GEM data - Zero_net'!$U165)-1) -> -8.0989333 | BP5: ='GEM data - Baseline'!$O169 -> 5 | BQ5: ='GEM data - Upside'!$O169 -> 5 | BR5: ='GEM data - Zero_net'!$O169 -> 5 | BU5: =100*(('GEM data - Baseline'!$L169/'GEM data - Baseline'!$L165)-1) -> -1.6384971 | BV5: =100*(('GEM data - Upside'!$L169/'GEM data - Upside'!$L165)-1) -> -1.6384971 | BW5: =100*(('GEM data - Zero_net'!$L169/'GEM data - Zero_net'!$L165)-1) -> -1.6384971 | BZ5: ='GEM data - Baseline'!$T169 -> -0.01592636 | CA5: ='GEM data - Upside'!$T169 -> -0.01592636 | CB5: ='GEM data - Zero_net'!$T169 -> -0.01592636 | CE5: ='GEM data - Baseline'!$J169 -> 0.1 | CF5: ='GEM data - Upside'!$J169 -> 0.1 | CG5: ='GEM data - Zero_net'!$J169 -> 0.1 | CJ5: =100*(('GEM data - Baseline'!$I169/'GEM data - Baseline'!$I165)-1) -> 0.61570178 | CK5: =100*(('GEM data - Upside'!$I169/'GEM data - Upside'!$I165)-1) -> 0.61570178 | CL5: =100*(('GEM data - Zero_net'!$I169/'GEM data - Zero_net'!$I165)-1) -> 0.61570178 | CO5: =100*('GEM data - Baseline'!$AB169/'GEM data - Baseline'!$AD169) -> 395.60176 | CP5: =100*('GEM data - Upside'!$AB169/'GEM data - Upside'!$AD169) -> 395.60176 | CQ5: =100*('GEM data - Zero_net'!$AB169/'GEM data - Zero_net'!$AD169) -> 395.60176 | CT5: =100*('GEM data - Baseline'!$AC169/'GEM data - Baseline'!$AD169) -> 285.05004 | CU5: =100*('GEM data - Upside'!$AC169/'GEM data - Upside'!$AD169) -> 285.05004 | CV5: =100*('GEM data - Zero_net'!$AC169/'GEM data - Zero_net'!$AD169) -> 285.05004 | CY5: =100*('GEM data - Baseline'!$F169/'GEM data - Baseline'!$AD169) -> 914.63559 | CZ5: =100*('GEM data - Upside'!$F169/'GEM data - Upside'!$AD169) -> 914.63559 | DA5: =100*('GEM data - Zero_net'!$F169/'GEM data - Zero_net'!$AD169) -> 914.63559 | DC5: 1982 | DD5: =SUMIF('GEM data - Baseline'!$B:$B,'Chart Data'!$DC5,'GEM data - Baseline'!$U:$U) -> 1189450.8 | DE5: =AVERAGEIF('GEM data - Baseline'!$B:$B,'Chart Data'!$DC5,'GEM data - Baseline'!$V:$V) -> 24297.707 | DF5: =AVERAGEIF('GEM data - Baseline'!$B:$B,'Chart Data'!$DC5,'GEM data - Baseline'!$W:$W) -> 0.001 | DG5: =AVERAGEIF('GEM data - Baseline'!$B:$B,'Chart Data'!$DC5,'GEM data - Baseline'!$X:$X) -> 311708.92 | DH5: =AVERAGEIF('GEM data - Baseline'!$B:$B,'Chart Data'!$DC5,'GEM data - Baseline'!$Y:$Y) -> 36500.68 | DI5: =AVERAGEIF('GEM data - Baseline'!$B:$B,'Chart Data'!$DC5,'GEM data - Baseline'!$Z:$Z) -> 1254045.5 | DJ5: =AVERAGEIF('GEM data - Baseline'!$B:$B,'Chart Data'!$DC5,'GEM data - Baseline'!$AA:$AA) -> -1.8020507 | DL5: =DE5*DF5 -> 24.297707 | DM5: =DG5/DH5 -> 8.5398115 | DN5: =DI5 -> 1254045.5 | DO5: =DJ5 -> -1.8020507 | DP5: =DD5 -> 1189450.8 | DQ5: =SUMIF('GEM data - Baseline'!$B:$B,'Chart Data'!$DC5,'GEM data - Baseline'!$F:$F) -> 1157191 | DS5: =100*((DP5/DP4)-1) -> 0.62117003 | DT5: =100*((DQ5/DQ4)-1) -> 1.9854353 | DV5: 1982 | DW5: =SUMIF('GEM data - Upside'!$B:$B,'Chart Data'!$DC5,'GEM data - Upside'!$U:$U) -> 1189450.8 | DX5: =AVERAGEIF('GEM data - Upside'!$B:$B,'Chart Data'!$DC5,'GEM data - Upside'!$V:$V) -> 24297.707 | DY5: =AVERAGEIF('GEM data - Upside'!$B:$B,'Chart Data'!$DC5,'GEM data - Upside'!$W:$W) -> 0.001 | DZ5: =AVERAGEIF('GEM data - Upside'!$B:$B,'Chart Data'!$DC5,'GEM data - Upside'!$X:$X) -> 311708.92 | EA5: =AVERAGEIF('GEM data - Upside'!$B:$B,'Chart Data'!$DC5,'GEM data - Upside'!$Y:$Y) -> 36500.68 | EB5: =AVERAGEIF('GEM data - Upside'!$B:$B,'Chart Data'!$DC5,'GEM data - Upside'!$Z:$Z) -> 1254045.5 | EC5: =AVERAGEIF('GEM data - Upside'!$B:$B,'Chart Data'!$DC5,'GEM data - Upside'!$AA:$AA) -> -1.8020507 | EE5: =DX5*DY5 -> 24.297707 | EF5: =DZ5/EA5 -> 8.5398115 | EG5: =EB5 -> 1254045.5 | EH5: =EC5 -> -1.8020507 | EI5: =DW5 -> 1189450.8 | EJ5: =SUMIF('GEM data - Upside'!$B:$B,'Chart Data'!$DC5,'GEM data - Upside'!$F:$F) -> 1157191 | EL5: =100*((EI5/EI4)-1) -> 0.62117003 | EM5: =100*((EJ5/EJ4)-1) -> 1.9854353 | EO5: 1982 | EP5: =SUMIF('GEM data - Zero_net'!$B:$B,'Chart Data'!$DC5,'GEM data - Zero_net'!$U:$U) -> 1189450.8 | EQ5: =AVERAGEIF('GEM data - Zero_net'!$B:$B,'Chart Data'!$DC5,'GEM data - Zero_net'!$V:$V) -> 24297.707 | ER5: =AVERAGEIF('GEM data - Zero_net'!$B:$B,'Chart Data'!$DC5,'GEM data - Zero_net'!$W:$W) -> 0.001 | ES5: =AVERAGEIF('GEM data - Zero_net'!$B:$B,'Chart Data'!$DC5,'GEM data - Zero_net'!$X:$X) -> 311708.92 | ET5: =AVERAGEIF('GEM data - Zero_net'!$B:$B,'Chart Data'!$DC5,'GEM data - Zero_net'!$Y:$Y) -> 36500.68 | EU5: =AVERAGEIF('GEM data - Zero_net'!$B:$B,'Chart Data'!$DC5,'GEM data - Zero_net'!$Z:$Z) -> 1254045.5 | EV5: =AVERAGEIF('GEM data - Zero_net'!$B:$B,'Chart Data'!$DC5,'GEM data - Zero_net'!$AA:$AA) -> -1.8020507 | EX5: =EQ5*ER5 -> 24.297707 | EY5: =ES5/ET5 -> 8.5398115 | EZ5: =EU5 -> 1254045.5 | FA5: =EV5 -> -1.8020507 | FB5: =EP5 -> 1189450.8 | FC5: =SUMIF('GEM data - Zero_net'!$B:$B,'Chart Data'!$DC5,'GEM data - Zero_net'!$F:$F) -> 1157191 | FE5: =100*((FB5/FB4)-1) -> 0.62117003 | FF5: =100*((FC5/FC4)-1) -> 1.9854353
B6: ='GEM data - Baseline'!$F170 -> 619330 | C6: ='GEM data - Upside'!$F170 -> 619330 | D6: ='GEM data - Zero_net'!$F170 -> 619330 | F6: 2003 | G6: ='[2]Chart Data'!M7 -> 194.3 | M6: =100*(('GEM data - Baseline'!$P170/'GEM data - Baseline'!$P166)-1) -> 0.72907922 | N6: =100*(('GEM data - Upside'!$P170/'GEM data - Upside'!$P166)-1) -> 0.72907922 | O6: =100*(('GEM data - Zero_net'!$P170/'GEM data - Zero_net'!$P166)-1) -> 0.72907922 | Q6: 2023 | R6: =100*(SUMIF('GEM data - Baseline'!$C:$C,'Chart Data'!$Q6,'GEM data - Baseline'!$Q:$Q)/SUMIF('GEM data - Baseline'!$C:$C,'Chart Data'!$Q6,'GEM data - Baseline'!$S:$S)) -> -2.4070169 | S6: =100*(SUMIF('GEM data - Upside'!$C:$C,'Chart Data'!$Q6,'GEM data - Upside'!$Q:$Q)/SUMIF('GEM data - Upside'!$C:$C,'Chart Data'!$Q6,'GEM data - Upside'!$S:$S)) -> -2.4070169 | T6: =100*(SUMIF('GEM data - Zero_net'!$C:$C,'Chart Data'!$Q6,'GEM data - Zero_net'!$Q:$Q)/SUMIF('GEM data - Zero_net'!$C:$C,'Chart Data'!$Q6,'GEM data - Zero_net'!$S:$S)) -> -2.4070169 | V6: 2023 | W6: =100*(SUMIF('GEM data - Baseline'!$D:$D,'Chart Data'!$Q6,'GEM data - Baseline'!$R:$R)/SUMIF('GEM data - Baseline'!$C:$C,'Chart Data'!$Q6,'GEM data - Baseline'!$S:$S)) -> 81.627529 | X6: =100*(SUMIF('GEM data - Upside'!$D:$D,'Chart Data'!$Q6,'GEM data - Upside'!$R:$R)/SUMIF('GEM data - Upside'!$C:$C,'Chart Data'!$Q6,'GEM data - Upside'!$S:$S)) -> 81.627529 | Y6: =100*(SUMIF('GEM data - Zero_net'!$D:$D,'Chart Data'!$Q6,'GEM data - Zero_net'!$R:$R)/SUMIF('GEM data - Zero_net'!$C:$C,'Chart Data'!$Q6,'GEM data - Zero_net'!$S:$S)) -> 81.627529 | AA6: 4 | AB6: =VLOOKUP($AA6,$AE$3:$AG$21,2,FALSE) -> Transport | AC6: =VLOOKUP($AA6,$AE$3:$AG$21,3,FALSE) -> 24.217837 | AE6: =RANK(AG6,$AG$3:$AG$21) -> 16 | AF6: Utilities | AG6: =100*(AL6/AJ6) -> 10.590137 | AI6: UEGAS | AJ6: {=INDEX('HMRC emp by ind and nat'!$A$149:$C$233,MATCH(1,('HMRC emp by ind and nat'!$A$145:$CG$145=AJ$1)*('HMRC emp by ind and nat'!$A$146:$CG$146=$AI6),0),3)} -> 123700 | AK6: {=INDEX('HMRC emp by ind and nat'!$A$149:$C$233,MATCH(1,('HMRC emp by ind and nat'!$A$145:$CG$145=AK$1)*('HMRC emp by ind and nat'!$A$146:$CG$146=$AI6),0),3)} -> 110600 | AL6: =AJ6-AK6 -> 13100 | AP6: 2003 | AQ6: =AVERAGEIF('GEM data - Baseline'!$B:$B,'Chart Data'!$AP6,'GEM data - Baseline'!$AE:$AE) -> 25.725755 | AR6: =AVERAGEIF('GEM data - Upside'!$B:$B,'Chart Data'!$AP6,'GEM data - Upside'!$AE:$AE) -> 25.725755 | AS6: =AVERAGEIF('GEM data - Zero_net'!$B:$B,'Chart Data'!$AP6,'GEM data - Zero_net'!$AE:$AE) -> 25.725755 | AU6: 2003 | AV6: =AVERAGEIF('GEM data - Baseline'!$B:$B,'Chart Data'!$AP6,'GEM data - Baseline'!AE:AE) -> 25.725755 | AW6: =AVERAGEIF('GEM data - Baseline'!$B:$B,'Chart Data'!$AP6,'GEM data - Baseline'!AF:AF) -> 16.210363 | AX6: =AVERAGEIF('GEM data - Baseline'!$B:$B,'Chart Data'!$AP6,'GEM data - Baseline'!AG:AG) -> 28.517777 | AY6: =AVERAGEIF('GEM data - Baseline'!$B:$B,'Chart Data'!$AP6,'GEM data - Baseline'!AH:AH) -> 26.454957 | AZ6: =AVERAGEIF('GEM data - Baseline'!$B:$B,'Chart Data'!$AP6,'GEM data - Baseline'!AI:AI) -> 24.865965 | BA6: =AVERAGEIF('GEM data - Baseline'!$B:$B,'Chart Data'!$AP6,'GEM data - Baseline'!AJ:AJ) -> 30.04239 | BB6: =AVERAGEIF('GEM data - Baseline'!$B:$B,'Chart Data'!$AP6,'GEM data - Baseline'!AK:AK) -> 16.18965 | BF6: =100*(('GEM data - Baseline'!$F170/'GEM data - Baseline'!$F166)-1) -> -7.6436018 | BG6: =100*(('GEM data - Upside'!$F170/'GEM data - Upside'!$F166)-1) -> -7.6436018 | BH6: =100*(('GEM data - Zero_net'!$F170/'GEM data - Zero_net'!$F166)-1) -> -7.6436018 | BK6: =100*(('GEM data - Baseline'!$U170/'GEM data - Baseline'!$U166)-1) -> -3.9425066 | BL6: =100*(('GEM data - Upside'!$U170/'GEM data - Upside'!$U166)-1) -> -3.9425066 | BM6: =100*(('GEM data - Zero_net'!$U170/'GEM data - Zero_net'!$U166)-1) -> -3.9425066 | BP6: ='GEM data - Baseline'!$O170 -> 5.3 | BQ6: ='GEM data - Upside'!$O170 -> 5.3 | BR6: ='GEM data - Zero_net'!$O170 -> 5.3 | BU6: =100*(('GEM data - Baseline'!$L170/'GEM data - Baseline'!$L166)-1) -> -2.3867865 | BV6: =100*(('GEM data - Upside'!$L170/'GEM data - Upside'!$L166)-1) -> -2.3867865 | BW6: =100*(('GEM data - Zero_net'!$L170/'GEM data - Zero_net'!$L166)-1) -> -2.3867865 | BZ6: ='GEM data - Baseline'!$T170 -> -3.113651 | CA6: ='GEM data - Upside'!$T170 -> -3.113651 | CB6: ='GEM data - Zero_net'!$T170 -> -3.113651 | CE6: ='GEM data - Baseline'!$J170 -> 0.1 | CF6: ='GEM data - Upside'!$J170 -> 0.1 | CG6: ='GEM data - Zero_net'!$J170 -> 0.1 | CJ6: =100*(('GEM data - Baseline'!$I170/'GEM data - Baseline'!$I166)-1) -> 0.5841379 | CK6: =100*(('GEM data - Upside'!$I170/'GEM data - Upside'!$I166)-1) -> 0.5841379 | CL6: =100*(('GEM data - Zero_net'!$I170/'GEM data - Zero_net'!$I166)-1) -> 0.5841379 | CO6: =100*('GEM data - Baseline'!$AB170/'GEM data - Baseline'!$AD170) -> 391.39981 | CP6: =100*('GEM data - Upside'!$AB170/'GEM data - Upside'!$AD170) -> 391.39981 | CQ6: =100*('GEM data - Zero_net'!$AB170/'GEM data - Zero_net'!$AD170) -> 391.39981 | CT6: =100*('GEM data - Baseline'!$AC170/'GEM data - Baseline'!$AD170) -> 296.78278 | CU6: =100*('GEM data - Upside'!$AC170/'GEM data - Upside'!$AD170) -> 296.78278 | CV6: =100*('GEM data - Zero_net'!$AC170/'GEM data - Zero_net'!$AD170) -> 296.78278 | CY6: =100*('GEM data - Baseline'!$F170/'GEM data - Baseline'!$AD170) -> 926.32256 | CZ6: =100*('GEM data - Upside'!$F170/'GEM data - Upside'!$AD170) -> 926.32256 | DA6: =100*('GEM data - Zero_net'!$F170/'GEM data - Zero_net'!$AD170) -> 926.32256 | DC6: 1983 | DD6: =SUMIF('GEM data - Baseline'!$B:$B,'Chart Data'!$DC6,'GEM data - Baseline'!$U:$U) -> 1209349.6 | DE6: =AVERAGEIF('GEM data - Baseline'!$B:$B,'Chart Data'!$DC6,'GEM data - Baseline'!$V:$V) -> 24304.682 | DF6: =AVERAGEIF('GEM data - Baseline'!$B:$B,'Chart Data'!$DC6,'GEM data - Baseline'!$W:$W) -> 0.001 | DG6: =AVERAGEIF('GEM data - Baseline'!$B:$B,'Chart Data'!$DC6,'GEM data - Baseline'!$X:$X) -> 314668.83 | DH6: =AVERAGEIF('GEM data - Baseline'!$B:$B,'Chart Data'!$DC6,'GEM data - Baseline'!$Y:$Y) -> 36776.192 | DI6: =AVERAGEIF('GEM data - Baseline'!$B:$B,'Chart Data'!$DC6,'GEM data - Baseline'!$Z:$Z) -> 1266603.5 | DJ6: =AVERAGEIF('GEM data - Baseline'!$B:$B,'Chart Data'!$DC6,'GEM data - Baseline'!$AA:$AA) -> -1.7896025 | DL6: =DE6*DF6 -> 24.304682 | DM6: =DG6/DH6 -> 8.5563187 | DN6: =DI6 -> 1266603.5 | DO6: =DJ6 -> -1.7896025 | DP6: =DD6 -> 1209349.6 | DQ6: =SUMIF('GEM data - Baseline'!$B:$B,'Chart Data'!$DC6,'GEM data - Baseline'!$F:$F) -> 1205632 | DS6: =100*((DP6/DP5)-1) -> 1.6729402 | DT6: =100*((DQ6/DQ5)-1) -> 4.1860851 | DV6: 1983 | DW6: =SUMIF('GEM data - Upside'!$B:$B,'Chart Data'!$DC6,'GEM data - Upside'!$U:$U) -> 1209349.6 | DX6: =AVERAGEIF('GEM data - Upside'!$B:$B,'Chart Data'!$DC6,'GEM data - Upside'!$V:$V) -> 24304.682 | DY6: =AVERAGEIF('GEM data - Upside'!$B:$B,'Chart Data'!$DC6,'GEM data - Upside'!$W:$W) -> 0.001 | DZ6: =AVERAGEIF('GEM data - Upside'!$B:$B,'Chart Data'!$DC6,'GEM data - Upside'!$X:$X) -> 314668.83 | EA6: =AVERAGEIF('GEM data - Upside'!$B:$B,'Chart Data'!$DC6,'GEM data - Upside'!$Y:$Y) -> 36776.192 | EB6: =AVERAGEIF('GEM data - Upside'!$B:$B,'Chart Data'!$DC6,'GEM data - Upside'!$Z:$Z) -> 1266603.5 | EC6: =AVERAGEIF('GEM data - Upside'!$B:$B,'Chart Data'!$DC6,'GEM data - Upside'!$AA:$AA) -> -1.7896025 | EE6: =DX6*DY6 -> 24.304682 | EF6: =DZ6/EA6 -> 8.5563187 | EG6: =EB6 -> 1266603.5 | EH6: =EC6 -> -1.7896025 | EI6: =DW6 -> 1209349.6 | EJ6: =SUMIF('GEM data - Upside'!$B:$B,'Chart Data'!$DC6,'GEM data - Upside'!$F:$F) -> 1205632 | EL6: =100*((EI6/EI5)-1) -> 1.6729402 | EM6: =100*((EJ6/EJ5)-1) -> 4.1860851 | EO6: 1983 | EP6: =SUMIF('GEM data - Zero_net'!$B:$B,'Chart Data'!$DC6,'GEM data - Zero_net'!$U:$U) -> 1209349.6 | EQ6: =AVERAGEIF('GEM data - Zero_net'!$B:$B,'Chart Data'!$DC6,'GEM data - Zero_net'!$V:$V) -> 24304.682 | ER6: =AVERAGEIF('GEM data - Zero_net'!$B:$B,'Chart Data'!$DC6,'GEM data - Zero_net'!$W:$W) -> 0.001 | ES6: =AVERAGEIF('GEM data - Zero_net'!$B:$B,'Chart Data'!$DC6,'GEM data - Zero_net'!$X:$X) -> 314668.83 | ET6: =AVERAGEIF('GEM data - Zero_net'!$B:$B,'Chart Data'!$DC6,'GEM data - Zero_net'!$Y:$Y) -> 36776.192 | EU6: =AVERAGEIF('GEM data - Zero_net'!$B:$B,'Chart Data'!$DC6,'GEM data - Zero_net'!$Z:$Z) -> 1266603.5 | EV6: =AVERAGEIF('GEM data - Zero_net'!$B:$B,'Chart Data'!$DC6,'GEM data - Zero_net'!$AA:$AA) -> -1.7896025 | EX6: =EQ6*ER6 -> 24.304682 | EY6: =ES6/ET6 -> 8.5563187 | EZ6: =EU6 -> 1266603.5 | FA6: =EV6 -> -1.7896025 | FB6: =EP6 -> 1209349.6 | FC6: =SUMIF('GEM data - Zero_net'!$B:$B,'Chart Data'!$DC6,'GEM data - Zero_net'!$F:$F) -> 1205632 | FE6: =100*((FB6/FB5)-1) -> 1.6729402 | FF6: =100*((FC6/FC5)-1) -> 4.1860851
A7: 2021 | B7: ='GEM data - Baseline'!$F171 -> 612665 | C7: ='GEM data - Upside'!$F171 -> 612665 | D7: ='GEM data - Zero_net'!$F171 -> 612665 | F7: 2004 | G7: ='[2]Chart Data'!M8 -> 209.5 | L7: 2021 | M7: =100*(('GEM data - Baseline'!$P171/'GEM data - Baseline'!$P167)-1) -> 0.63536161 | N7: =100*(('GEM data - Upside'!$P171/'GEM data - Upside'!$P167)-1) -> 0.63536161 | O7: =100*(('GEM data - Zero_net'!$P171/'GEM data - Zero_net'!$P167)-1) -> 0.63536161 | Q7: 2024 | R7: =100*(SUMIF('GEM data - Baseline'!$C:$C,'Chart Data'!$Q7,'GEM data - Baseline'!$Q:$Q)/SUMIF('GEM data - Baseline'!$C:$C,'Chart Data'!$Q7,'GEM data - Baseline'!$S:$S)) -> -2.5903661 | S7: =100*(SUMIF('GEM data - Upside'!$C:$C,'Chart Data'!$Q7,'GEM data - Upside'!$Q:$Q)/SUMIF('GEM data - Upside'!$C:$C,'Chart Data'!$Q7,'GEM data - Upside'!$S:$S)) -> -2.5903661 | T7: =100*(SUMIF('GEM data - Zero_net'!$C:$C,'Chart Data'!$Q7,'GEM data - Zero_net'!$Q:$Q)/SUMIF('GEM data - Zero_net'!$C:$C,'Chart Data'!$Q7,'GEM data - Zero_net'!$S:$S)) -> -2.5903661 | V7: 2024 | W7: =100*(SUMIF('GEM data - Baseline'!$D:$D,'Chart Data'!$Q7,'GEM data - Baseline'!$R:$R)/SUMIF('GEM data - Baseline'!$C:$C,'Chart Data'!$Q7,'GEM data - Baseline'!$S:$S)) -> 83.085282 | X7: =100*(SUMIF('GEM data - Upside'!$D:$D,'Chart Data'!$Q7,'GEM data - Upside'!$R:$R)/SUMIF('GEM data - Upside'!$C:$C,'Chart Data'!$Q7,'GEM data - Upside'!$S:$S)) -> 83.085282 | Y7: =100*(SUMIF('GEM data - Zero_net'!$D:$D,'Chart Data'!$Q7,'GEM data - Zero_net'!$R:$R)/SUMIF('GEM data - Zero_net'!$C:$C,'Chart Data'!$Q7,'GEM data - Zero_net'!$S:$S)) -> 83.085282 | AA7: 5 | AB7: =VLOOKUP($AA7,$AE$3:$AG$21,2,FALSE) -> Communications | AC7: =VLOOKUP($AA7,$AE$3:$AG$21,3,FALSE) -> 22.034733 | AE7: =RANK(AG7,$AG$3:$AG$21) -> 15 | AF7: Water | AG7: =100*(AL7/AJ7) -> 10.725356 | AI7: UWSWM | AJ7: {=INDEX('HMRC emp by ind and nat'!$A$149:$C$233,MATCH(1,('HMRC emp by ind and nat'!$A$145:$CG$145=AJ$1)*('HMRC emp by ind and nat'!$A$146:$CG$146=$AI7),0),3)} -> 215066.67 | AK7: {=INDEX('HMRC emp by ind and nat'!$A$149:$C$233,MATCH(1,('HMRC emp by ind and nat'!$A$145:$CG$145=AK$1)*('HMRC emp by ind and nat'!$A$146:$CG$146=$AI7),0),3)} -> 192000 | AL7: =AJ7-AK7 -> 23066.667 | AP7: 2004 | AQ7: =AVERAGEIF('GEM data - Baseline'!$B:$B,'Chart Data'!$AP7,'GEM data - Baseline'!$AE:$AE) -> 25.696 | AR7: =AVERAGEIF('GEM data - Upside'!$B:$B,'Chart Data'!$AP7,'GEM data - Upside'!$AE:$AE) -> 25.696 | AS7: =AVERAGEIF('GEM data - Zero_net'!$B:$B,'Chart Data'!$AP7,'GEM data - Zero_net'!$AE:$AE) -> 25.696 | AU7: 2004 | AV7: =AVERAGEIF('GEM data - Baseline'!$B:$B,'Chart Data'!$AP7,'GEM data - Baseline'!AE:AE) -> 25.696 | AW7: =AVERAGEIF('GEM data - Baseline'!$B:$B,'Chart Data'!$AP7,'GEM data - Baseline'!AF:AF) -> 16.207178 | AX7: =AVERAGEIF('GEM data - Baseline'!$B:$B,'Chart Data'!$AP7,'GEM data - Baseline'!AG:AG) -> 29.490485 | AY7: =AVERAGEIF('GEM data - Baseline'!$B:$B,'Chart Data'!$AP7,'GEM data - Baseline'!AH:AH) -> 26.54218 | AZ7: =AVERAGEIF('GEM data - Baseline'!$B:$B,'Chart Data'!$AP7,'GEM data - Baseline'!AI:AI) -> 25.00869 | BA7: =AVERAGEIF('GEM data - Baseline'!$B:$B,'Chart Data'!$AP7,'GEM data - Baseline'!AJ:AJ) -> 30.534055 | BB7: =AVERAGEIF('GEM data - Baseline'!$B:$B,'Chart Data'!$AP7,'GEM data - Baseline'!AK:AK) -> 16.277442 | BE7: 2021 | BF7: =100*(('GEM data - Baseline'!$F171/'GEM data - Baseline'!$F167)-1) -> -6.0589101 | BG7: =100*(('GEM data - Upside'!$F171/'GEM data - Upside'!$F167)-1) -> -6.0589101 | BH7: =100*(('GEM data - Zero_net'!$F171/'GEM data - Zero_net'!$F167)-1) -> -6.0589101 | BJ7: 2021 | BK7: =100*(('GEM data - Baseline'!$U171/'GEM data - Baseline'!$U167)-1) -> -4.5221023 | BL7: =100*(('GEM data - Upside'!$U171/'GEM data - Upside'!$U167)-1) -> -4.5221023 | BM7: =100*(('GEM data - Zero_net'!$U171/'GEM data - Zero_net'!$U167)-1) -> -4.5221023 | BO7: 2021 | BP7: ='GEM data - Baseline'!$O171 -> 4.9 | BQ7: ='GEM data - Upside'!$O171 -> 4.9 | BR7: ='GEM data - Zero_net'!$O171 -> 4.9 | BT7: 2021 | BU7: =100*(('GEM data - Baseline'!$L171/'GEM data - Baseline'!$L167)-1) -> -2.0075206 | BV7: =100*(('GEM data - Upside'!$L171/'GEM data - Upside'!$L167)-1) -> -2.0075206 | BW7: =100*(('GEM data - Zero_net'!$L171/'GEM data - Zero_net'!$L167)-1) -> -2.0075206 | BY7: 2021 | BZ7: ='GEM data - Baseline'!$T171 -> -2.577209 | CA7: ='GEM data - Upside'!$T171 -> -2.577209 | CB7: ='GEM data - Zero_net'!$T171 -> -2.577209 | CD7: 2021 | CE7: ='GEM data - Baseline'!$J171 -> 0.1 | CF7: ='GEM data - Upside'!$J171 -> 0.1 | CG7: ='GEM data - Zero_net'!$J171 -> 0.1 | CI7: 2021 | CJ7: =100*(('GEM data - Baseline'!$I171/'GEM data - Baseline'!$I167)-1) -> 0.64535936 | CK7: =100*(('GEM data - Upside'!$I171/'GEM data - Upside'!$I167)-1) -> 0.64535936 | CL7: =100*(('GEM data - Zero_net'!$I171/'GEM data - Zero_net'!$I167)-1) -> 0.64535936 | CN7: 2021 | CO7: =100*('GEM data - Baseline'!$AB171/'GEM data - Baseline'!$AD171) -> 412.61833 | CP7: =100*('GEM data - Upside'!$AB171/'GEM data - Upside'!$AD171) -> 412.61833 | CQ7: =100*('GEM data - Zero_net'!$AB171/'GEM data - Zero_net'!$AD171) -> 412.61833 | CS7: 2021 | CT7: =100*('GEM data - Baseline'!$AC171/'GEM data - Baseline'!$AD171) -> 350.49949 | CU7: =100*('GEM data - Upside'!$AC171/'GEM data - Upside'!$AD171) -> 350.49949 | CV7: =100*('GEM data - Zero_net'!$AC171/'GEM data - Zero_net'!$AD171) -> 350.49949 | CX7: 2021 | CY7: =100*('GEM data - Baseline'!$F171/'GEM data - Baseline'!$AD171) -> 915.53905 | CZ7: =100*('GEM data - Upside'!$F171/'GEM data - Upside'!$AD171) -> 915.53905 | DA7: =100*('GEM data - Zero_net'!$F171/'GEM data - Zero_net'!$AD171) -> 915.53905 | DC7: 1984 | DD7: =SUMIF('GEM data - Baseline'!$B:$B,'Chart Data'!$DC7,'GEM data - Baseline'!$U:$U) -> 1251974.1 | DE7: =AVERAGEIF('GEM data - Baseline'!$B:$B,'Chart Data'!$DC7,'GEM data - Baseline'!$V:$V) -> 24910.802 | DF7: =AVERAGEIF('GEM data - Baseline'!$B:$B,'Chart Data'!$DC7,'GEM data - Baseline'!$W:$W) -> 0.001 | DG7: =AVERAGEIF('GEM data - Baseline'!$B:$B,'Chart Data'!$DC7,'GEM data - Baseline'!$X:$X) -> 318382.53 | DH7: =AVERAGEIF('GEM data - Baseline'!$B:$B,'Chart Data'!$DC7,'GEM data - Baseline'!$Y:$Y) -> 37029.132 | DI7: =AVERAGEIF('GEM data - Baseline'!$B:$B,'Chart Data'!$DC7,'GEM data - Baseline'!$Z:$Z) -> 1286788 | DJ7: =AVERAGEIF('GEM data - Baseline'!$B:$B,'Chart Data'!$DC7,'GEM data - Baseline'!$AA:$AA) -> -1.7772407 | DL7: =DE7*DF7 -> 24.910802 | DM7: =DG7/DH7 -> 8.5981632 | DN7: =DI7 -> 1286788 | DO7: =DJ7 -> -1.7772407 | DP7: =DD7 -> 1251974.1 | DQ7: =SUMIF('GEM data - Baseline'!$B:$B,'Chart Data'!$DC7,'GEM data - Baseline'!$F:$F) -> 1232675 | DS7: =100*((DP7/DP6)-1) -> 3.5245805 | DT7: =100*((DQ7/DQ6)-1) -> 2.2430559 | DV7: 1984 | DW7: =SUMIF('GEM data - Upside'!$B:$B,'Chart Data'!$DC7,'GEM data - Upside'!$U:$U) -> 1251974.1 | DX7: =AVERAGEIF('GEM data - Upside'!$B:$B,'Chart Data'!$DC7,'GEM data - Upside'!$V:$V) -> 24910.802 | DY7: =AVERAGEIF('GEM data - Upside'!$B:$B,'Chart Data'!$DC7,'GEM data - Upside'!$W:$W) -> 0.001 | DZ7: =AVERAGEIF('GEM data - Upside'!$B:$B,'Chart Data'!$DC7,'GEM data - Upside'!$X:$X) -> 318382.53 | EA7: =AVERAGEIF('GEM data - Upside'!$B:$B,'Chart Data'!$DC7,'GEM data - Upside'!$Y:$Y) -> 37029.132 | EB7: =AVERAGEIF('GEM data - Upside'!$B:$B,'Chart Data'!$DC7,'GEM data - Upside'!$Z:$Z) -> 1286788 | EC7: =AVERAGEIF('GEM data - Upside'!$B:$B,'Chart Data'!$DC7,'GEM data - Upside'!$AA:$AA) -> -1.7772407 | EE7: =DX7*DY7 -> 24.910802 | EF7: =DZ7/EA7 -> 8.5981632 | EG7: =EB7 -> 1286788 | EH7: =EC7 -> -1.7772407 | EI7: =DW7 -> 1251974.1 | EJ7: =SUMIF('GEM data - Upside'!$B:$B,'Chart Data'!$DC7,'GEM data - Upside'!$F:$F) -> 1232675 | EL7: =100*((EI7/EI6)-1) -> 3.5245805 | EM7: =100*((EJ7/EJ6)-1) -> 2.2430559 | EO7: 1984 | EP7: =SUMIF('GEM data - Zero_net'!$B:$B,'Chart Data'!$DC7,'GEM data - Zero_net'!$U:$U) -> 1251974.1 | EQ7: =AVERAGEIF('GEM data - Zero_net'!$B:$B,'Chart Data'!$DC7,'GEM data - Zero_net'!$V:$V) -> 24910.802 | ER7: =AVERAGEIF('GEM data - Zero_net'!$B:$B,'Chart Data'!$DC7,'GEM data - Zero_net'!$W:$W) -> 0.001 | ES7: =AVERAGEIF('GEM data - Zero_net'!$B:$B,'Chart Data'!$DC7,'GEM data - Zero_net'!$X:$X) -> 318382.53 | ET7: =AVERAGEIF('GEM data - Zero_net'!$B:$B,'Chart Data'!$DC7,'GEM data - Zero_net'!$Y:$Y) -> 37029.132 | EU7: =AVERAGEIF('GEM data - Zero_net'!$B:$B,'Chart Data'!$DC7,'GEM data - Zero_net'!$Z:$Z) -> 1286788 | EV7: =AVERAGEIF('GEM data - Zero_net'!$B:$B,'Chart Data'!$DC7,'GEM data - Zero_net'!$AA:$AA) -> -1.7772407 | EX7: =EQ7*ER7 -> 24.910802 | EY7: =ES7/ET7 -> 8.5981632 | EZ7: =EU7 -> 1286788 | FA7: =EV7 -> -1.7772407 | FB7: =EP7 -> 1251974.1 | FC7: =SUMIF('GEM data - Zero_net'!$B:$B,'Chart Data'!$DC7,'GEM data - Zero_net'!$F:$F) -> 1232675 | FE7: =100*((FB7/FB6)-1) -> 3.5245805 | FF7: =100*((FC7/FC6)-1) -> 2.2430559
B8: ='GEM data - Baseline'!$F172 -> 655443 | C8: ='GEM data - Upside'!$F172 -> 655443 | D8: ='GEM data - Zero_net'!$F172 -> 655443 | F8: 2005 | G8: ='[2]Chart Data'!M9 -> 335.6 | M8: =100*(('GEM data - Baseline'!$P172/'GEM data - Baseline'!$P168)-1) -> 0.54204657 | N8: =100*(('GEM data - Upside'!$P172/'GEM data - Upside'!$P168)-1) -> 0.54204657 | O8: =100*(('GEM data - Zero_net'!$P172/'GEM data - Zero_net'!$P168)-1) -> 0.54204657 | Q8: 2025 | R8: =100*(SUMIF('GEM data - Baseline'!$C:$C,'Chart Data'!$Q8,'GEM data - Baseline'!$Q:$Q)/SUMIF('GEM data - Baseline'!$C:$C,'Chart Data'!$Q8,'GEM data - Baseline'!$S:$S)) -> -1.8835895 | S8: =100*(SUMIF('GEM data - Upside'!$C:$C,'Chart Data'!$Q8,'GEM data - Upside'!$Q:$Q)/SUMIF('GEM data - Upside'!$C:$C,'Chart Data'!$Q8,'GEM data - Upside'!$S:$S)) -> -1.9093813 | T8: =100*(SUMIF('GEM data - Zero_net'!$C:$C,'Chart Data'!$Q8,'GEM data - Zero_net'!$Q:$Q)/SUMIF('GEM data - Zero_net'!$C:$C,'Chart Data'!$Q8,'GEM data - Zero_net'!$S:$S)) -> -1.9302828 | V8: 2025 | W8: =100*(SUMIF('GEM data - Baseline'!$D:$D,'Chart Data'!$Q8,'GEM data - Baseline'!$R:$R)/SUMIF('GEM data - Baseline'!$C:$C,'Chart Data'!$Q8,'GEM data - Baseline'!$S:$S)) -> 83.419912 | X8: =100*(SUMIF('GEM data - Upside'!$D:$D,'Chart Data'!$Q8,'GEM data - Upside'!$R:$R)/SUMIF('GEM data - Upside'!$C:$C,'Chart Data'!$Q8,'GEM data - Upside'!$S:$S)) -> 83.453237 | Y8: =100*(SUMIF('GEM data - Zero_net'!$D:$D,'Chart Data'!$Q8,'GEM data - Zero_net'!$R:$R)/SUMIF('GEM data - Zero_net'!$C:$C,'Chart Data'!$Q8,'GEM data - Zero_net'!$S:$S)) -> 83.523154 | AA8: 6 | AB8: =VLOOKUP($AA8,$AE$3:$AG$21,2,FALSE) -> Other services | AC8: =VLOOKUP($AA8,$AE$3:$AG$21,3,FALSE) -> 20.636898 | AE8: =RANK(AG8,$AG$3:$AG$21) -> 14 | AF8: Construction | AG8: =100*(AL8/AJ8) -> 12.079649 | AI8: CON | AJ8: {=INDEX('HMRC emp by ind and nat'!$A$149:$C$233,MATCH(1,('HMRC emp by ind and nat'!$A$145:$CG$145=AJ$1)*('HMRC emp by ind and nat'!$A$146:$CG$146=$AI8),0),3)} -> 1360966.7 | AK8: {=INDEX('HMRC emp by ind and nat'!$A$149:$C$233,MATCH(1,('HMRC emp by ind and nat'!$A$145:$CG$145=AK$1)*('HMRC emp by ind and nat'!$A$146:$CG$146=$AI8),0),3)} -> 1196566.7 | AL8: =AJ8-AK8 -> 164400 | AP8: 2005 | AQ8: =AVERAGEIF('GEM data - Baseline'!$B:$B,'Chart Data'!$AP8,'GEM data - Baseline'!$AE:$AE) -> 25.608593 | AR8: =AVERAGEIF('GEM data - Upside'!$B:$B,'Chart Data'!$AP8,'GEM data - Upside'!$AE:$AE) -> 25.608593 | AS8: =AVERAGEIF('GEM data - Zero_net'!$B:$B,'Chart Data'!$AP8,'GEM data - Zero_net'!$AE:$AE) -> 25.608593 | AU8: 2005 | AV8: =AVERAGEIF('GEM data - Baseline'!$B:$B,'Chart Data'!$AP8,'GEM data - Baseline'!AE:AE) -> 25.608593 | AW8: =AVERAGEIF('GEM data - Baseline'!$B:$B,'Chart Data'!$AP8,'GEM data - Baseline'!AF:AF) -> 16.201367 | AX8: =AVERAGEIF('GEM data - Baseline'!$B:$B,'Chart Data'!$AP8,'GEM data - Baseline'!AG:AG) -> 30.746955 | AY8: =AVERAGEIF('GEM data - Baseline'!$B:$B,'Chart Data'!$AP8,'GEM data - Baseline'!AH:AH) -> 27.96087 | AZ8: =AVERAGEIF('GEM data - Baseline'!$B:$B,'Chart Data'!$AP8,'GEM data - Baseline'!AI:AI) -> 25.104933 | BA8: =AVERAGEIF('GEM data - Baseline'!$B:$B,'Chart Data'!$AP8,'GEM data - Baseline'!AJ:AJ) -> 31.127795 | BB8: =AVERAGEIF('GEM data - Baseline'!$B:$B,'Chart Data'!$AP8,'GEM data - Baseline'!AK:AK) -> 16.360055 | BF8: =100*(('GEM data - Baseline'!$F172/'GEM data - Baseline'!$F168)-1) -> 25.478218 | BG8: =100*(('GEM data - Upside'!$F172/'GEM data - Upside'!$F168)-1) -> 25.478218 | BH8: =100*(('GEM data - Zero_net'!$F172/'GEM data - Zero_net'!$F168)-1) -> 25.478218 | BK8: =100*(('GEM data - Baseline'!$U172/'GEM data - Baseline'!$U168)-1) -> 12.597205 | BL8: =100*(('GEM data - Upside'!$U172/'GEM data - Upside'!$U168)-1) -> 12.597205 | BM8: =100*(('GEM data - Zero_net'!$U172/'GEM data - Zero_net'!$U168)-1) -> 12.597205 | BP8: ='GEM data - Baseline'!$O172 -> 4.7 | BQ8: ='GEM data - Upside'!$O172 -> 4.7 | BR8: ='GEM data - Zero_net'!$O172 -> 4.7 | BU8: =100*(('GEM data - Baseline'!$L172/'GEM data - Baseline'!$L168)-1) -> -0.56382914 | BV8: =100*(('GEM data - Upside'!$L172/'GEM data - Upside'!$L168)-1) -> -0.56382914 | BW8: =100*(('GEM data - Zero_net'!$L172/'GEM data - Zero_net'!$L168)-1) -> -0.56382914 | BZ8: ='GEM data - Baseline'!$T172 -> 0.6524086 | CA8: ='GEM data - Upside'!$T172 -> 0.6524086 | CB8: ='GEM data - Zero_net'!$T172 -> 0.6524086 | CE8: ='GEM data - Baseline'!$J172 -> 0.1 | CF8: ='GEM data - Upside'!$J172 -> 0.1 | CG8: ='GEM data - Zero_net'!$J172 -> 0.1 | CJ8: =100*(('GEM data - Baseline'!$I172/'GEM data - Baseline'!$I168)-1) -> 2.0270276 | CK8: =100*(('GEM data - Upside'!$I172/'GEM data - Upside'!$I168)-1) -> 2.0270276 | CL8: =100*(('GEM data - Zero_net'!$I172/'GEM data - Zero_net'!$I168)-1) -> 2.0270276 | CO8: =100*('GEM data - Baseline'!$AB172/'GEM data - Baseline'!$AD172) -> 393.9189 | CP8: =100*('GEM data - Upside'!$AB172/'GEM data - Upside'!$AD172) -> 393.9189 | CQ8: =100*('GEM data - Zero_net'!$AB172/'GEM data - Zero_net'!$AD172) -> 393.9189 | CT8: =100*('GEM data - Baseline'!$AC172/'GEM data - Baseline'!$AD172) -> 305.28084 | CU8: =100*('GEM data - Upside'!$AC172/'GEM data - Upside'!$AD172) -> 305.28084 | CV8: =100*('GEM data - Zero_net'!$AC172/'GEM data - Zero_net'!$AD172) -> 305.28084 | CY8: =100*('GEM data - Baseline'!$F172/'GEM data - Baseline'!$AD172) -> 978.59446 | CZ8: =100*('GEM data - Upside'!$F172/'GEM data - Upside'!$AD172) -> 978.59446 | DA8: =100*('GEM data - Zero_net'!$F172/'GEM data - Zero_net'!$AD172) -> 978.59446 | DC8: 1985 | DD8: =SUMIF('GEM data - Baseline'!$B:$B,'Chart Data'!$DC8,'GEM data - Baseline'!$U:$U) -> 1287059.7 | DE8: =AVERAGEIF('GEM data - Baseline'!$B:$B,'Chart Data'!$DC8,'GEM data - Baseline'!$V:$V) -> 25107.865 | DF8: =AVERAGEIF('GEM data - Baseline'!$B:$B,'Chart Data'!$DC8,'GEM data - Baseline'!$W:$W) -> 0.001 | DG8: =AVERAGEIF('GEM data - Baseline'!$B:$B,'Chart Data'!$DC8,'GEM data - Baseline'!$X:$X) -> 322872.05 | DH8: =AVERAGEIF('GEM data - Baseline'!$B:$B,'Chart Data'!$DC8,'GEM data - Baseline'!$Y:$Y) -> 37116.963 | DI8: =AVERAGEIF('GEM data - Baseline'!$B:$B,'Chart Data'!$DC8,'GEM data - Baseline'!$Z:$Z) -> 1312207.8 | DJ8: =AVERAGEIF('GEM data - Baseline'!$B:$B,'Chart Data'!$DC8,'GEM data - Baseline'!$AA:$AA) -> -1.764964 | DL8: =DE8*DF8 -> 25.107865 | DM8: =DG8/DH8 -> 8.6987735 | DN8: =DI8 -> 1312207.8 | DO8: =DJ8 -> -1.764964 | DP8: =DD8 -> 1287059.7 | DQ8: =SUMIF('GEM data - Baseline'!$B:$B,'Chart Data'!$DC8,'GEM data - Baseline'!$F:$F) -> 1283200 | DS8: =100*((DP8/DP7)-1) -> 2.8024222 | DT8: =100*((DQ8/DQ7)-1) -> 4.0988095 | DV8: 1985 | DW8: =SUMIF('GEM data - Upside'!$B:$B,'Chart Data'!$DC8,'GEM data - Upside'!$U:$U) -> 1287059.7 | DX8: =AVERAGEIF('GEM data - Upside'!$B:$B,'Chart Data'!$DC8,'GEM data - Upside'!$V:$V) -> 25107.865 | DY8: =AVERAGEIF('GEM data - Upside'!$B:$B,'Chart Data'!$DC8,'GEM data - Upside'!$W:$W) -> 0.001 | DZ8: =AVERAGEIF('GEM data - Upside'!$B:$B,'Chart Data'!$DC8,'GEM data - Upside'!$X:$X) -> 322872.05 | EA8: =AVERAGEIF('GEM data - Upside'!$B:$B,'Chart Data'!$DC8,'GEM data - Upside'!$Y:$Y) -> 37116.963 | EB8: =AVERAGEIF('GEM data - Upside'!$B:$B,'Chart Data'!$DC8,'GEM data - Upside'!$Z:$Z) -> 1312207.8 | EC8: =AVERAGEIF('GEM data - Upside'!$B:$B,'Chart Data'!$DC8,'GEM data - Upside'!$AA:$AA) -> -1.764964 | EE8: =DX8*DY8 -> 25.107865 | EF8: =DZ8/EA8 -> 8.6987735 | EG8: =EB8 -> 1312207.8 | EH8: =EC8 -> -1.764964 | EI8: =DW8 -> 1287059.7 | EJ8: =SUMIF('GEM data - Upside'!$B:$B,'Chart Data'!$DC8,'GEM data - Upside'!$F:$F) -> 1283200 | EL8: =100*((EI8/EI7)-1) -> 2.8024222 | EM8: =100*((EJ8/EJ7)-1) -> 4.0988095 | EO8: 1985 | EP8: =SUMIF('GEM data - Zero_net'!$B:$B,'Chart Data'!$DC8,'GEM data - Zero_net'!$U:$U) -> 1287059.7 | EQ8: =AVERAGEIF('GEM data - Zero_net'!$B:$B,'Chart Data'!$DC8,'GEM data - Zero_net'!$V:$V) -> 25107.865 | ER8: =AVERAGEIF('GEM data - Zero_net'!$B:$B,'Chart Data'!$DC8,'GEM data - Zero_net'!$W:$W) -> 0.001 | ES8: =AVERAGEIF('GEM data - Zero_net'!$B:$B,'Chart Data'!$DC8,'GEM data - Zero_net'!$X:$X) -> 322872.05 | ET8: =AVERAGEIF('GEM data - Zero_net'!$B:$B,'Chart Data'!$DC8,'GEM data - Zero_net'!$Y:$Y) -> 37116.963 | EU8: =AVERAGEIF('GEM data - Zero_net'!$B:$B,'Chart Data'!$DC8,'GEM data - Zero_net'!$Z:$Z) -> 1312207.8 | EV8: =AVERAGEIF('GEM data - Zero_net'!$B:$B,'Chart Data'!$DC8,'GEM data - Zero_net'!$AA:$AA) -> -1.764964 | EX8: =EQ8*ER8 -> 25.107865 | EY8: =ES8/ET8 -> 8.6987735 | EZ8: =EU8 -> 1312207.8 | FA8: =EV8 -> -1.764964 | FB8: =EP8 -> 1287059.7 | FC8: =SUMIF('GEM data - Zero_net'!$B:$B,'Chart Data'!$DC8,'GEM data - Zero_net'!$F:$F) -> 1283200 | FE8: =100*((FB8/FB7)-1) -> 2.8024222 | FF8: =100*((FC8/FC7)-1) -> 4.0988095
B9: ='GEM data - Baseline'!$F173 -> 666498 | C9: ='GEM data - Upside'!$F173 -> 666498 | D9: ='GEM data - Zero_net'!$F173 -> 666498 | F9: 2006 | G9: ='[2]Chart Data'!M10 -> 254.5 | M9: =100*(('GEM data - Baseline'!$P173/'GEM data - Baseline'!$P169)-1) -> 0.62382593 | N9: =100*(('GEM data - Upside'!$P173/'GEM data - Upside'!$P169)-1) -> 0.62382593 | O9: =100*(('GEM data - Zero_net'!$P173/'GEM data - Zero_net'!$P169)-1) -> 0.62382593 | Q9: 2026 | R9: =100*(SUMIF('GEM data - Baseline'!$C:$C,'Chart Data'!$Q9,'GEM data - Baseline'!$Q:$Q)/SUMIF('GEM data - Baseline'!$C:$C,'Chart Data'!$Q9,'GEM data - Baseline'!$S:$S)) -> -1.8779703 | S9: =100*(SUMIF('GEM data - Upside'!$C:$C,'Chart Data'!$Q9,'GEM data - Upside'!$Q:$Q)/SUMIF('GEM data - Upside'!$C:$C,'Chart Data'!$Q9,'GEM data - Upside'!$S:$S)) -> -1.9786354 | T9: =100*(SUMIF('GEM data - Zero_net'!$C:$C,'Chart Data'!$Q9,'GEM data - Zero_net'!$Q:$Q)/SUMIF('GEM data - Zero_net'!$C:$C,'Chart Data'!$Q9,'GEM data - Zero_net'!$S:$S)) -> -2.1787484 | V9: 2026 | W9: =100*(SUMIF('GEM data - Baseline'!$D:$D,'Chart Data'!$Q9,'GEM data - Baseline'!$R:$R)/SUMIF('GEM data - Baseline'!$C:$C,'Chart Data'!$Q9,'GEM data - Baseline'!$S:$S)) -> 85.185693 | X9: =100*(SUMIF('GEM data - Upside'!$D:$D,'Chart Data'!$Q9,'GEM data - Upside'!$R:$R)/SUMIF('GEM data - Upside'!$C:$C,'Chart Data'!$Q9,'GEM data - Upside'!$S:$S)) -> 85.186566 | Y9: =100*(SUMIF('GEM data - Zero_net'!$D:$D,'Chart Data'!$Q9,'GEM data - Zero_net'!$R:$R)/SUMIF('GEM data - Zero_net'!$C:$C,'Chart Data'!$Q9,'GEM data - Zero_net'!$S:$S)) -> 86.123304 | AA9: 7 | AB9: =VLOOKUP($AA9,$AE$3:$AG$21,2,FALSE) -> Manufacturing | AC9: =VLOOKUP($AA9,$AE$3:$AG$21,3,FALSE) -> 19.09214 | AE9: =RANK(AG9,$AG$3:$AG$21) -> 11 | AF9: Wholesale & retail | AG9: =100*(AL9/AJ9) -> 16.953289 | AI9: DISTR | AJ9: {=INDEX('HMRC emp by ind and nat'!$A$149:$C$233,MATCH(1,('HMRC emp by ind and nat'!$A$145:$CG$145=AJ$1)*('HMRC emp by ind and nat'!$A$146:$CG$146=$AI9),0),3)} -> 4452233.3 | AK9: {=INDEX('HMRC emp by ind and nat'!$A$149:$C$233,MATCH(1,('HMRC emp by ind and nat'!$A$145:$CG$145=AK$1)*('HMRC emp by ind and nat'!$A$146:$CG$146=$AI9),0),3)} -> 3697433.3 | AL9: =AJ9-AK9 -> 754800 | AP9: 2006 | AQ9: =AVERAGEIF('GEM data - Baseline'!$B:$B,'Chart Data'!$AP9,'GEM data - Baseline'!$AE:$AE) -> 25.525467 | AR9: =AVERAGEIF('GEM data - Upside'!$B:$B,'Chart Data'!$AP9,'GEM data - Upside'!$AE:$AE) -> 25.525467 | AS9: =AVERAGEIF('GEM data - Zero_net'!$B:$B,'Chart Data'!$AP9,'GEM data - Zero_net'!$AE:$AE) -> 25.525467 | AU9: 2006 | AV9: =AVERAGEIF('GEM data - Baseline'!$B:$B,'Chart Data'!$AP9,'GEM data - Baseline'!AE:AE) -> 25.525467 | AW9: =AVERAGEIF('GEM data - Baseline'!$B:$B,'Chart Data'!$AP9,'GEM data - Baseline'!AF:AF) -> 16.23223 | AX9: =AVERAGEIF('GEM data - Baseline'!$B:$B,'Chart Data'!$AP9,'GEM data - Baseline'!AG:AG) -> 32.100983 | AY9: =AVERAGEIF('GEM data - Baseline'!$B:$B,'Chart Data'!$AP9,'GEM data - Baseline'!AH:AH) -> 29.502115 | AZ9: =AVERAGEIF('GEM data - Baseline'!$B:$B,'Chart Data'!$AP9,'GEM data - Baseline'!AI:AI) -> 25.079438 | BA9: =AVERAGEIF('GEM data - Baseline'!$B:$B,'Chart Data'!$AP9,'GEM data - Baseline'!AJ:AJ) -> 31.682987 | BB9: =AVERAGEIF('GEM data - Baseline'!$B:$B,'Chart Data'!$AP9,'GEM data - Baseline'!AK:AK) -> 16.533375 | BF9: =100*(('GEM data - Baseline'!$F173/'GEM data - Baseline'!$F169)-1) -> 9.0881415 | BG9: =100*(('GEM data - Upside'!$F173/'GEM data - Upside'!$F169)-1) -> 9.0881415 | BH9: =100*(('GEM data - Zero_net'!$F173/'GEM data - Zero_net'!$F169)-1) -> 9.0881415 | BK9: =100*(('GEM data - Baseline'!$U173/'GEM data - Baseline'!$U169)-1) -> 8.4831445 | BL9: =100*(('GEM data - Upside'!$U173/'GEM data - Upside'!$U169)-1) -> 8.4831445 | BM9: =100*(('GEM data - Zero_net'!$U173/'GEM data - Zero_net'!$U169)-1) -> 8.4831445 | BP9: ='GEM data - Baseline'!$O173 -> 4.4 | BQ9: ='GEM data - Upside'!$O173 -> 4.4 | BR9: ='GEM data - Zero_net'!$O173 -> 4.4 | BU9: =100*(('GEM data - Baseline'!$L173/'GEM data - Baseline'!$L169)-1) -> 1.1342213 | BV9: =100*(('GEM data - Upside'!$L173/'GEM data - Upside'!$L169)-1) -> 1.1342213 | BW9: =100*(('GEM data - Zero_net'!$L173/'GEM data - Zero_net'!$L169)-1) -> 1.1342213 | BZ9: ='GEM data - Baseline'!$T173 -> 0.5401611 | CA9: ='GEM data - Upside'!$T173 -> 0.5401611 | CB9: ='GEM data - Zero_net'!$T173 -> 0.5401611 | CE9: ='GEM data - Baseline'!$J173 -> 0.1 | CF9: ='GEM data - Upside'!$J173 -> 0.1 | CG9: ='GEM data - Zero_net'!$J173 -> 0.1 | CJ9: =100*(('GEM data - Baseline'!$I173/'GEM data - Baseline'!$I169)-1) -> 2.7539788 | CK9: =100*(('GEM data - Upside'!$I173/'GEM data - Upside'!$I169)-1) -> 2.7539788 | CL9: =100*(('GEM data - Zero_net'!$I173/'GEM data - Zero_net'!$I169)-1) -> 2.7539788 | CO9: =100*('GEM data - Baseline'!$AB173/'GEM data - Baseline'!$AD173) -> 381.57054 | CP9: =100*('GEM data - Upside'!$AB173/'GEM data - Upside'!$AD173) -> 381.57054 | CQ9: =100*('GEM data - Zero_net'!$AB173/'GEM data - Zero_net'!$AD173) -> 381.57054 | CT9: =100*('GEM data - Baseline'!$AC173/'GEM data - Baseline'!$AD173) -> 329.47686 | CU9: =100*('GEM data - Upside'!$AC173/'GEM data - Upside'!$AD173) -> 329.47686 | CV9: =100*('GEM data - Zero_net'!$AC173/'GEM data - Zero_net'!$AD173) -> 329.47686 | CY9: =100*('GEM data - Baseline'!$F173/'GEM data - Baseline'!$AD173) -> 992.66188 | CZ9: =100*('GEM data - Upside'!$F173/'GEM data - Upside'!$AD173) -> 992.66188 | DA9: =100*('GEM data - Zero_net'!$F173/'GEM data - Zero_net'!$AD173) -> 992.66188 | DC9: 1986 | DD9: =SUMIF('GEM data - Baseline'!$B:$B,'Chart Data'!$DC9,'GEM data - Baseline'!$U:$U) -> 1320242.4 | DE9: =AVERAGEIF('GEM data - Baseline'!$B:$B,'Chart Data'!$DC9,'GEM data - Baseline'!$V:$V) -> 25255.61 | DF9: =AVERAGEIF('GEM data - Baseline'!$B:$B,'Chart Data'!$DC9,'GEM data - Baseline'!$W:$W) -> 33.524138 | DG9: =AVERAGEIF('GEM data - Baseline'!$B:$B,'Chart Data'!$DC9,'GEM data - Baseline'!$X:$X) -> 327826.4 | DH9: =AVERAGEIF('GEM data - Baseline'!$B:$B,'Chart Data'!$DC9,'GEM data - Baseline'!$Y:$Y) -> 37205.482 | DI9: =AVERAGEIF('GEM data - Baseline'!$B:$B,'Chart Data'!$DC9,'GEM data - Baseline'!$Z:$Z) -> 1335181 | DJ9: =AVERAGEIF('GEM data - Baseline'!$B:$B,'Chart Data'!$DC9,'GEM data - Baseline'!$AA:$AA) -> -1.7529055 | DL9: =DE9*DF9 -> 846672.54 | DM9: =DG9/DH9 -> 8.811239 | DN9: =DI9 -> 1335181 | DO9: =DJ9 -> -1.7529055 | DP9: =DD9 -> 1320242.4 | DQ9: =SUMIF('GEM data - Baseline'!$B:$B,'Chart Data'!$DC9,'GEM data - Baseline'!$F:$F) -> 1323173 | DS9: =100*((DP9/DP8)-1) -> 2.5781788 | DT9: =100*((DQ9/DQ8)-1) -> 3.1151029 | DV9: 1986 | DW9: =SUMIF('GEM data - Upside'!$B:$B,'Chart Data'!$DC9,'GEM data - Upside'!$U:$U) -> 1320242.4 | DX9: =AVERAGEIF('GEM data - Upside'!$B:$B,'Chart Data'!$DC9,'GEM data - Upside'!$V:$V) -> 25255.61 | DY9: =AVERAGEIF('GEM data - Upside'!$B:$B,'Chart Data'!$DC9,'GEM data - Upside'!$W:$W) -> 33.524138 | DZ9: =AVERAGEIF('GEM data - Upside'!$B:$B,'Chart Data'!$DC9,'GEM data - Upside'!$X:$X) -> 327826.4 | EA9: =AVERAGEIF('GEM data - Upside'!$B:$B,'Chart Data'!$DC9,'GEM data - Upside'!$Y:$Y) -> 37205.482 | EB9: =AVERAGEIF('GEM data - Upside'!$B:$B,'Chart Data'!$DC9,'GEM data - Upside'!$Z:$Z) -> 1335181 | EC9: =AVERAGEIF('GEM data - Upside'!$B:$B,'Chart Data'!$DC9,'GEM data - Upside'!$AA:$AA) -> -1.7529055 | EE9: =DX9*DY9 -> 846672.54 | EF9: =DZ9/EA9 -> 8.811239 | EG9: =EB9 -> 1335181 | EH9: =EC9 -> -1.7529055 | EI9: =DW9 -> 1320242.4 | EJ9: =SUMIF('GEM data - Upside'!$B:$B,'Chart Data'!$DC9,'GEM data - Upside'!$F:$F) -> 1323173 | EL9: =100*((EI9/EI8)-1) -> 2.5781788 | EM9: =100*((EJ9/EJ8)-1) -> 3.1151029 | EO9: 1986 | EP9: =SUMIF('GEM data - Zero_net'!$B:$B,'Chart Data'!$DC9,'GEM data - Zero_net'!$U:$U) -> 1320242.4 | EQ9: =AVERAGEIF('GEM data - Zero_net'!$B:$B,'Chart Data'!$DC9,'GEM data - Zero_net'!$V:$V) -> 25255.61 | ER9: =AVERAGEIF('GEM data - Zero_net'!$B:$B,'Chart Data'!$DC9,'GEM data - Zero_net'!$W:$W) -> 33.524138 | ES9: =AVERAGEIF('GEM data - Zero_net'!$B:$B,'Chart Data'!$DC9,'GEM data - Zero_net'!$X:$X) -> 327826.4 | ET9: =AVERAGEIF('GEM data - Zero_net'!$B:$B,'Chart Data'!$DC9,'GEM data - Zero_net'!$Y:$Y) -> 37205.482 | EU9: =AVERAGEIF('GEM data - Zero_net'!$B:$B,'Chart Data'!$DC9,'GEM data - Zero_net'!$Z:$Z) -> 1335181 | EV9: =AVERAGEIF('GEM data - Zero_net'!$B:$B,'Chart Data'!$DC9,'GEM data - Zero_net'!$AA:$AA) -> -1.7529055 | EX9: =EQ9*ER9 -> 846672.54 | EY9: =ES9/ET9 -> 8.811239 | EZ9: =EU9 -> 1335181 | FA9: =EV9 -> -1.7529055 | FB9: =EP9 -> 1320242.4 | FC9: =SUMIF('GEM data - Zero_net'!$B:$B,'Chart Data'!$DC9,'GEM data - Zero_net'!$F:$F) -> 1323173 | FE9: =100*((FB9/FB8)-1) -> 2.5781788 | FF9: =100*((FC9/FC8)-1) -> 3.1151029
B10: ='GEM data - Baseline'!$F174 -> 675680 | C10: ='GEM data - Upside'!$F174 -> 675680 | D10: ='GEM data - Zero_net'!$F174 -> 675680 | F10: 2007 | G10: ='[2]Chart Data'!M11 -> 304.6 | M10: =100*(('GEM data - Baseline'!$P174/'GEM data - Baseline'!$P170)-1) -> 0.70533732 | N10: =100*(('GEM data - Upside'!$P174/'GEM data - Upside'!$P170)-1) -> 0.70533732 | O10: =100*(('GEM data - Zero_net'!$P174/'GEM data - Zero_net'!$P170)-1) -> 0.70533732 | Q10: 2027 | R10: =100*(SUMIF('GEM data - Baseline'!$C:$C,'Chart Data'!$Q10,'GEM data - Baseline'!$Q:$Q)/SUMIF('GEM data - Baseline'!$C:$C,'Chart Data'!$Q10,'GEM data - Baseline'!$S:$S)) -> -0.55742427 | S10: =100*(SUMIF('GEM data - Upside'!$C:$C,'Chart Data'!$Q10,'GEM data - Upside'!$Q:$Q)/SUMIF('GEM data - Upside'!$C:$C,'Chart Data'!$Q10,'GEM data - Upside'!$S:$S)) -> -0.56577133 | T10: =100*(SUMIF('GEM data - Zero_net'!$C:$C,'Chart Data'!$Q10,'GEM data - Zero_net'!$Q:$Q)/SUMIF('GEM data - Zero_net'!$C:$C,'Chart Data'!$Q10,'GEM data - Zero_net'!$S:$S)) -> -0.69627703 | V10: 2027 | W10: =100*(SUMIF('GEM data - Baseline'!$D:$D,'Chart Data'!$Q10,'GEM data - Baseline'!$R:$R)/SUMIF('GEM data - Baseline'!$C:$C,'Chart Data'!$Q10,'GEM data - Baseline'!$S:$S)) -> 85.553188 | X10: =100*(SUMIF('GEM data - Upside'!$D:$D,'Chart Data'!$Q10,'GEM data - Upside'!$R:$R)/SUMIF('GEM data - Upside'!$C:$C,'Chart Data'!$Q10,'GEM data - Upside'!$S:$S)) -> 85.234087 | Y10: =100*(SUMIF('GEM data - Zero_net'!$D:$D,'Chart Data'!$Q10,'GEM data - Zero_net'!$R:$R)/SUMIF('GEM data - Zero_net'!$C:$C,'Chart Data'!$Q10,'GEM data - Zero_net'!$S:$S)) -> 86.778071 | AA10: 8 | AB10: =VLOOKUP($AA10,$AE$3:$AG$21,2,FALSE) -> Agriculture | AC10: =VLOOKUP($AA10,$AE$3:$AG$21,3,FALSE) -> 18.872631 | AE10: =RANK(AG10,$AG$3:$AG$21) -> 4 | AF10: Transport | AG10: =100*(AL10/AJ10) -> 24.217837 | AI10: TRA | AJ10: {=INDEX('HMRC emp by ind and nat'!$A$149:$C$233,MATCH(1,('HMRC emp by ind and nat'!$A$145:$CG$145=AJ$1)*('HMRC emp by ind and nat'!$A$146:$CG$146=$AI10),0),3)} -> 1454300 | AK10: {=INDEX('HMRC emp by ind and nat'!$A$149:$C$233,MATCH(1,('HMRC emp by ind and nat'!$A$145:$CG$145=AK$1)*('HMRC emp by ind and nat'!$A$146:$CG$146=$AI10),0),3)} -> 1102100 | AL10: =AJ10-AK10 -> 352200 | AP10: 2007 | AQ10: =AVERAGEIF('GEM data - Baseline'!$B:$B,'Chart Data'!$AP10,'GEM data - Baseline'!$AE:$AE) -> 25.603512 | AR10: =AVERAGEIF('GEM data - Upside'!$B:$B,'Chart Data'!$AP10,'GEM data - Upside'!$AE:$AE) -> 25.603512 | AS10: =AVERAGEIF('GEM data - Zero_net'!$B:$B,'Chart Data'!$AP10,'GEM data - Zero_net'!$AE:$AE) -> 25.603512 | AU10: 2007 | AV10: =AVERAGEIF('GEM data - Baseline'!$B:$B,'Chart Data'!$AP10,'GEM data - Baseline'!AE:AE) -> 25.603512 | AW10: =AVERAGEIF('GEM data - Baseline'!$B:$B,'Chart Data'!$AP10,'GEM data - Baseline'!AF:AF) -> 16.300623 | AX10: =AVERAGEIF('GEM data - Baseline'!$B:$B,'Chart Data'!$AP10,'GEM data - Baseline'!AG:AG) -> 33.386003 | AY10: =AVERAGEIF('GEM data - Baseline'!$B:$B,'Chart Data'!$AP10,'GEM data - Baseline'!AH:AH) -> 30.171895 | AZ10: =AVERAGEIF('GEM data - Baseline'!$B:$B,'Chart Data'!$AP10,'GEM data - Baseline'!AI:AI) -> 25.122045 | BA10: =AVERAGEIF('GEM data - Baseline'!$B:$B,'Chart Data'!$AP10,'GEM data - Baseline'!AJ:AJ) -> 32.020135 | BB10: =AVERAGEIF('GEM data - Baseline'!$B:$B,'Chart Data'!$AP10,'GEM data - Baseline'!AK:AK) -> 16.702047 | BF10: =100*(('GEM data - Baseline'!$F174/'GEM data - Baseline'!$F170)-1) -> 9.098542 | BG10: =100*(('GEM data - Upside'!$F174/'GEM data - Upside'!$F170)-1) -> 9.098542 | BH10: =100*(('GEM data - Zero_net'!$F174/'GEM data - Zero_net'!$F170)-1) -> 9.098542 | BK10: =100*(('GEM data - Baseline'!$U174/'GEM data - Baseline'!$U170)-1) -> 4.0591495 | BL10: =100*(('GEM data - Upside'!$U174/'GEM data - Upside'!$U170)-1) -> 4.0591495 | BM10: =100*(('GEM data - Zero_net'!$U174/'GEM data - Zero_net'!$U170)-1) -> 4.0591495 | BP10: ='GEM data - Baseline'!$O174 -> 4.2 | BQ10: ='GEM data - Upside'!$O174 -> 4.2 | BR10: ='GEM data - Zero_net'!$O174 -> 4.2 | BU10: =100*(('GEM data - Baseline'!$L174/'GEM data - Baseline'!$L170)-1) -> 1.4379571 | BV10: =100*(('GEM data - Upside'!$L174/'GEM data - Upside'!$L170)-1) -> 1.4379571 | BW10: =100*(('GEM data - Zero_net'!$L174/'GEM data - Zero_net'!$L170)-1) -> 1.4379571 | BZ10: ='GEM data - Baseline'!$T174 -> 1.61562 | CA10: ='GEM data - Upside'!$T174 -> 1.61562 | CB10: ='GEM data - Zero_net'!$T174 -> 1.61562 | CE10: ='GEM data - Baseline'!$J174 -> 0.1272727 | CF10: ='GEM data - Upside'!$J174 -> 0.1272727 | CG10: ='GEM data - Zero_net'!$J174 -> 0.1272727 | CJ10: =100*(('GEM data - Baseline'!$I174/'GEM data - Baseline'!$I170)-1) -> 4.8899435 | CK10: =100*(('GEM data - Upside'!$I174/'GEM data - Upside'!$I170)-1) -> 4.8899435 | CL10: =100*(('GEM data - Zero_net'!$I174/'GEM data - Zero_net'!$I170)-1) -> 4.8899435 | CO10: =100*('GEM data - Baseline'!$AB174/'GEM data - Baseline'!$AD174) -> 373.52281 | CP10: =100*('GEM data - Upside'!$AB174/'GEM data - Upside'!$AD174) -> 373.52281 | CQ10: =100*('GEM data - Zero_net'!$AB174/'GEM data - Zero_net'!$AD174) -> 373.52281 | CT10: =100*('GEM data - Baseline'!$AC174/'GEM data - Baseline'!$AD174) -> 336.07946 | CU10: =100*('GEM data - Upside'!$AC174/'GEM data - Upside'!$AD174) -> 336.07946 | CV10: =100*('GEM data - Zero_net'!$AC174/'GEM data - Zero_net'!$AD174) -> 336.07946 | CY10: =100*('GEM data - Baseline'!$F174/'GEM data - Baseline'!$AD174) -> 1003.8778 | CZ10: =100*('GEM data - Upside'!$F174/'GEM data - Upside'!$AD174) -> 1003.8778 | DA10: =100*('GEM data - Zero_net'!$F174/'GEM data - Zero_net'!$AD174) -> 1003.8778 | DC10: 1987 | DD10: =SUMIF('GEM data - Baseline'!$B:$B,'Chart Data'!$DC10,'GEM data - Baseline'!$U:$U) -> 1357334.8 | DE10: =AVERAGEIF('GEM data - Baseline'!$B:$B,'Chart Data'!$DC10,'GEM data - Baseline'!$V:$V) -> 25501.767 | DF10: =AVERAGEIF('GEM data - Baseline'!$B:$B,'Chart Data'!$DC10,'GEM data - Baseline'!$W:$W) -> 33.524137 | DG10: =AVERAGEIF('GEM data - Baseline'!$B:$B,'Chart Data'!$DC10,'GEM data - Baseline'!$X:$X) -> 332272.33 | DH10: =AVERAGEIF('GEM data - Baseline'!$B:$B,'Chart Data'!$DC10,'GEM data - Baseline'!$Y:$Y) -> 37265.827 | DI10: =AVERAGEIF('GEM data - Baseline'!$B:$B,'Chart Data'!$DC10,'GEM data - Baseline'!$Z:$Z) -> 1361967 | DJ10: =AVERAGEIF('GEM data - Baseline'!$B:$B,'Chart Data'!$DC10,'GEM data - Baseline'!$AA:$AA) -> -1.7414617 | DL10: =DE10*DF10 -> 854924.76 | DM10: =DG10/DH10 -> 8.9162739 | DN10: =DI10 -> 1361967 | DO10: =DJ10 -> -1.7414617 | DP10: =DD10 -> 1357334.8 | DQ10: =SUMIF('GEM data - Baseline'!$B:$B,'Chart Data'!$DC10,'GEM data - Baseline'!$F:$F) -> 1395353 | DS10: =100*((DP10/DP9)-1) -> 2.8095144 | DT10: =100*((DQ10/DQ9)-1) -> 5.455069 | DV10: 1987 | DW10: =SUMIF('GEM data - Upside'!$B:$B,'Chart Data'!$DC10,'GEM data - Upside'!$U:$U) -> 1357334.8 | DX10: =AVERAGEIF('GEM data - Upside'!$B:$B,'Chart Data'!$DC10,'GEM data - Upside'!$V:$V) -> 25501.767 | DY10: =AVERAGEIF('GEM data - Upside'!$B:$B,'Chart Data'!$DC10,'GEM data - Upside'!$W:$W) -> 33.524137 | DZ10: =AVERAGEIF('GEM data - Upside'!$B:$B,'Chart Data'!$DC10,'GEM data - Upside'!$X:$X) -> 332272.33 | EA10: =AVERAGEIF('GEM data - Upside'!$B:$B,'Chart Data'!$DC10,'GEM data - Upside'!$Y:$Y) -> 37265.827 | EB10: =AVERAGEIF('GEM data - Upside'!$B:$B,'Chart Data'!$DC10,'GEM data - Upside'!$Z:$Z) -> 1361967 | EC10: =AVERAGEIF('GEM data - Upside'!$B:$B,'Chart Data'!$DC10,'GEM data - Upside'!$AA:$AA) -> -1.7414617 | EE10: =DX10*DY10 -> 854924.76 | EF10: =DZ10/EA10 -> 8.9162739 | EG10: =EB10 -> 1361967 | EH10: =EC10 -> -1.7414617 | EI10: =DW10 -> 1357334.8 | EJ10: =SUMIF('GEM data - Upside'!$B:$B,'Chart Data'!$DC10,'GEM data - Upside'!$F:$F) -> 1395353 | EL10: =100*((EI10/EI9)-1) -> 2.8095144 | EM10: =100*((EJ10/EJ9)-1) -> 5.455069 | EO10: 1987 | EP10: =SUMIF('GEM data - Zero_net'!$B:$B,'Chart Data'!$DC10,'GEM data - Zero_net'!$U:$U) -> 1357334.8 | EQ10: =AVERAGEIF('GEM data - Zero_net'!$B:$B,'Chart Data'!$DC10,'GEM data - Zero_net'!$V:$V) -> 25501.767 | ER10: =AVERAGEIF('GEM data - Zero_net'!$B:$B,'Chart Data'!$DC10,'GEM data - Zero_net'!$W:$W) -> 33.524137 | ES10: =AVERAGEIF('GEM data - Zero_net'!$B:$B,'Chart Data'!$DC10,'GEM data - Zero_net'!$X:$X) -> 332272.33 | ET10: =AVERAGEIF('GEM data - Zero_net'!$B:$B,'Chart Data'!$DC10,'GEM data - Zero_net'!$Y:$Y) -> 37265.827 | EU10: =AVERAGEIF('GEM data - Zero_net'!$B:$B,'Chart Data'!$DC10,'GEM data - Zero_net'!$Z:$Z) -> 1361967 | EV10: =AVERAGEIF('GEM data - Zero_net'!$B:$B,'Chart Data'!$DC10,'GEM data - Zero_net'!$AA:$AA) -> -1.7414617 | EX10: =EQ10*ER10 -> 854924.76 | EY10: =ES10/ET10 -> 8.9162739 | EZ10: =EU10 -> 1361967 | FA10: =EV10 -> -1.7414617 | FB10: =EP10 -> 1357334.8 | FC10: =SUMIF('GEM data - Zero_net'!$B:$B,'Chart Data'!$DC10,'GEM data - Zero_net'!$F:$F) -> 1395353 | FE10: =100*((FB10/FB9)-1) -> 2.8095144 | FF10: =100*((FC10/FC9)-1) -> 5.455069
A11: 2022 | B11: ='GEM data - Baseline'!$F175 -> 682527 | C11: ='GEM data - Upside'!$F175 -> 682527 | D11: ='GEM data - Zero_net'!$F175 -> 682527 | F11: 2008 | G11: ='[2]Chart Data'!M12 -> 283.6 | L11: 2022 | M11: =100*(('GEM data - Baseline'!$P175/'GEM data - Baseline'!$P171)-1) -> 0.78665204 | N11: =100*(('GEM data - Upside'!$P175/'GEM data - Upside'!$P171)-1) -> 0.78665204 | O11: =100*(('GEM data - Zero_net'!$P175/'GEM data - Zero_net'!$P171)-1) -> 0.78665204 | Q11: 2028 | R11: =100*(SUMIF('GEM data - Baseline'!$C:$C,'Chart Data'!$Q11,'GEM data - Baseline'!$Q:$Q)/SUMIF('GEM data - Baseline'!$C:$C,'Chart Data'!$Q11,'GEM data - Baseline'!$S:$S)) -> -0.06721703 | S11: =100*(SUMIF('GEM data - Upside'!$C:$C,'Chart Data'!$Q11,'GEM data - Upside'!$Q:$Q)/SUMIF('GEM data - Upside'!$C:$C,'Chart Data'!$Q11,'GEM data - Upside'!$S:$S)) -> -0.06175871 | T11: =100*(SUMIF('GEM data - Zero_net'!$C:$C,'Chart Data'!$Q11,'GEM data - Zero_net'!$Q:$Q)/SUMIF('GEM data - Zero_net'!$C:$C,'Chart Data'!$Q11,'GEM data - Zero_net'!$S:$S)) -> -0.05453206 | V11: 2028 | W11: =100*(SUMIF('GEM data - Baseline'!$D:$D,'Chart Data'!$Q11,'GEM data - Baseline'!$R:$R)/SUMIF('GEM data - Baseline'!$C:$C,'Chart Data'!$Q11,'GEM data - Baseline'!$S:$S)) -> 85.25083 | X11: =100*(SUMIF('GEM data - Upside'!$D:$D,'Chart Data'!$Q11,'GEM data - Upside'!$R:$R)/SUMIF('GEM data - Upside'!$C:$C,'Chart Data'!$Q11,'GEM data - Upside'!$S:$S)) -> 84.784094 | Y11: =100*(SUMIF('GEM data - Zero_net'!$D:$D,'Chart Data'!$Q11,'GEM data - Zero_net'!$R:$R)/SUMIF('GEM data - Zero_net'!$C:$C,'Chart Data'!$Q11,'GEM data - Zero_net'!$S:$S)) -> 86.481022 | AA11: 9 | AB11: =VLOOKUP($AA11,$AE$3:$AG$21,2,FALSE) -> Professional services | AC11: =VLOOKUP($AA11,$AE$3:$AG$21,3,FALSE) -> 18.441099 | AE11: =RANK(AG11,$AG$3:$AG$21) -> 2 | AF11: Accommodation & food | AG11: =100*(AL11/AJ11) -> 30.691508 | AI11: HOTL | AJ11: {=INDEX('HMRC emp by ind and nat'!$A$149:$C$233,MATCH(1,('HMRC emp by ind and nat'!$A$145:$CG$145=AJ$1)*('HMRC emp by ind and nat'!$A$146:$CG$146=$AI11),0),3)} -> 2345600 | AK11: {=INDEX('HMRC emp by ind and nat'!$A$149:$C$233,MATCH(1,('HMRC emp by ind and nat'!$A$145:$CG$145=AK$1)*('HMRC emp by ind and nat'!$A$146:$CG$146=$AI11),0),3)} -> 1625700 | AL11: =AJ11-AK11 -> 719900 | AP11: 2008 | AQ11: =AVERAGEIF('GEM data - Baseline'!$B:$B,'Chart Data'!$AP11,'GEM data - Baseline'!$AE:$AE) -> 25.845307 | AR11: =AVERAGEIF('GEM data - Upside'!$B:$B,'Chart Data'!$AP11,'GEM data - Upside'!$AE:$AE) -> 25.845307 | AS11: =AVERAGEIF('GEM data - Zero_net'!$B:$B,'Chart Data'!$AP11,'GEM data - Zero_net'!$AE:$AE) -> 25.845307 | AU11: 2008 | AV11: =AVERAGEIF('GEM data - Baseline'!$B:$B,'Chart Data'!$AP11,'GEM data - Baseline'!AE:AE) -> 25.845307 | AW11: =AVERAGEIF('GEM data - Baseline'!$B:$B,'Chart Data'!$AP11,'GEM data - Baseline'!AF:AF) -> 16.548075 | AX11: =AVERAGEIF('GEM data - Baseline'!$B:$B,'Chart Data'!$AP11,'GEM data - Baseline'!AG:AG) -> 34.655637 | AY11: =AVERAGEIF('GEM data - Baseline'!$B:$B,'Chart Data'!$AP11,'GEM data - Baseline'!AH:AH) -> 30.697187 | AZ11: =AVERAGEIF('GEM data - Baseline'!$B:$B,'Chart Data'!$AP11,'GEM data - Baseline'!AI:AI) -> 25.304662 | BA11: =AVERAGEIF('GEM data - Baseline'!$B:$B,'Chart Data'!$AP11,'GEM data - Baseline'!AJ:AJ) -> 32.268567 | BB11: =AVERAGEIF('GEM data - Baseline'!$B:$B,'Chart Data'!$AP11,'GEM data - Baseline'!AK:AK) -> 16.922238 | BE11: 2022 | BF11: =100*(('GEM data - Baseline'!$F175/'GEM data - Baseline'!$F171)-1) -> 11.402969 | BG11: =100*(('GEM data - Upside'!$F175/'GEM data - Upside'!$F171)-1) -> 11.402969 | BH11: =100*(('GEM data - Zero_net'!$F175/'GEM data - Zero_net'!$F171)-1) -> 11.402969 | BJ11: 2022 | BK11: =100*(('GEM data - Baseline'!$U175/'GEM data - Baseline'!$U171)-1) -> 6.0031992 | BL11: =100*(('GEM data - Upside'!$U175/'GEM data - Upside'!$U171)-1) -> 6.0031992 | BM11: =100*(('GEM data - Zero_net'!$U175/'GEM data - Zero_net'!$U171)-1) -> 6.0031992 | BO11: 2022 | BP11: ='GEM data - Baseline'!$O175 -> 3.8 | BQ11: ='GEM data - Upside'!$O175 -> 3.8 | BR11: ='GEM data - Zero_net'!$O175 -> 3.8 | BT11: 2022 | BU11: =100*(('GEM data - Baseline'!$L175/'GEM data - Baseline'!$L171)-1) -> 1.4730457 | BV11: =100*(('GEM data - Upside'!$L175/'GEM data - Upside'!$L171)-1) -> 1.4730457 | BW11: =100*(('GEM data - Zero_net'!$L175/'GEM data - Zero_net'!$L171)-1) -> 1.4730457 | BY11: 2022 | BZ11: ='GEM data - Baseline'!$T175 -> 2.391243 | CA11: ='GEM data - Upside'!$T175 -> 2.391243 | CB11: ='GEM data - Zero_net'!$T175 -> 2.391243 | CD11: 2022 | CE11: ='GEM data - Baseline'!$J175 -> 0.453125 | CF11: ='GEM data - Upside'!$J175 -> 0.453125 | CG11: ='GEM data - Zero_net'!$J175 -> 0.453125 | CI11: 2022 | CJ11: =100*(('GEM data - Baseline'!$I175/'GEM data - Baseline'!$I171)-1) -> 6.1984103 | CK11: =100*(('GEM data - Upside'!$I175/'GEM data - Upside'!$I171)-1) -> 6.1984103 | CL11: =100*(('GEM data - Zero_net'!$I175/'GEM data - Zero_net'!$I171)-1) -> 6.1984103 | CN11: 2022 | CO11: =100*('GEM data - Baseline'!$AB175/'GEM data - Baseline'!$AD175) -> 399.31971 | CP11: =100*('GEM data - Upside'!$AB175/'GEM data - Upside'!$AD175) -> 399.31971 | CQ11: =100*('GEM data - Zero_net'!$AB175/'GEM data - Zero_net'!$AD175) -> 399.31971 | CS11: 2022 | CT11: =100*('GEM data - Baseline'!$AC175/'GEM data - Baseline'!$AD175) -> 398.32225 | CU11: =100*('GEM data - Upside'!$AC175/'GEM data - Upside'!$AD175) -> 398.32225 | CV11: =100*('GEM data - Zero_net'!$AC175/'GEM data - Zero_net'!$AD175) -> 398.32225 | CX11: 2022 | CY11: =100*('GEM data - Baseline'!$F175/'GEM data - Baseline'!$AD175) -> 1011.5782 | CZ11: =100*('GEM data - Upside'!$F175/'GEM data - Upside'!$AD175) -> 1011.5782 | DA11: =100*('GEM data - Zero_net'!$F175/'GEM data - Zero_net'!$AD175) -> 1011.5782 | DC11: 1988 | DD11: =SUMIF('GEM data - Baseline'!$B:$B,'Chart Data'!$DC11,'GEM data - Baseline'!$U:$U) -> 1405882.9 | DE11: =AVERAGEIF('GEM data - Baseline'!$B:$B,'Chart Data'!$DC11,'GEM data - Baseline'!$V:$V) -> 25806.3 | DF11: =AVERAGEIF('GEM data - Baseline'!$B:$B,'Chart Data'!$DC11,'GEM data - Baseline'!$W:$W) -> 33.690102 | DG11: =AVERAGEIF('GEM data - Baseline'!$B:$B,'Chart Data'!$DC11,'GEM data - Baseline'!$X:$X) -> 336945.48 | DH11: =AVERAGEIF('GEM data - Baseline'!$B:$B,'Chart Data'!$DC11,'GEM data - Baseline'!$Y:$Y) -> 37299.198 | DI11: =AVERAGEIF('GEM data - Baseline'!$B:$B,'Chart Data'!$DC11,'GEM data - Baseline'!$Z:$Z) -> 1400419.5 | DJ11: =AVERAGEIF('GEM data - Baseline'!$B:$B,'Chart Data'!$DC11,'GEM data - Baseline'!$AA:$AA) -> -1.7301365 | DL11: =DE11*DF11 -> 869416.89 | DM11: =DG11/DH11 -> 9.0335851 | DN11: =DI11 -> 1400419.5 | DO11: =DJ11 -> -1.7301365 | DP11: =DD11 -> 1405882.9 | DQ11: =SUMIF('GEM data - Baseline'!$B:$B,'Chart Data'!$DC11,'GEM data - Baseline'!$F:$F) -> 1471002 | DS11: =100*((DP11/DP10)-1) -> 3.5767226 | DT11: =100*((DQ11/DQ10)-1) -> 5.4214955 | DV11: 1988 | DW11: =SUMIF('GEM data - Upside'!$B:$B,'Chart Data'!$DC11,'GEM data - Upside'!$U:$U) -> 1405882.9 | DX11: =AVERAGEIF('GEM data - Upside'!$B:$B,'Chart Data'!$DC11,'GEM data - Upside'!$V:$V) -> 25806.3 | DY11: =AVERAGEIF('GEM data - Upside'!$B:$B,'Chart Data'!$DC11,'GEM data - Upside'!$W:$W) -> 33.690102 | DZ11: =AVERAGEIF('GEM data - Upside'!$B:$B,'Chart Data'!$DC11,'GEM data - Upside'!$X:$X) -> 336945.48 | EA11: =AVERAGEIF('GEM data - Upside'!$B:$B,'Chart Data'!$DC11,'GEM data - Upside'!$Y:$Y) -> 37299.198 | EB11: =AVERAGEIF('GEM data - Upside'!$B:$B,'Chart Data'!$DC11,'GEM data - Upside'!$Z:$Z) -> 1400419.5 | EC11: =AVERAGEIF('GEM data - Upside'!$B:$B,'Chart Data'!$DC11,'GEM data - Upside'!$AA:$AA) -> -1.7301365 | EE11: =DX11*DY11 -> 869416.89 | EF11: =DZ11/EA11 -> 9.0335851 | EG11: =EB11 -> 1400419.5 | EH11: =EC11 -> -1.7301365 | EI11: =DW11 -> 1405882.9 | EJ11: =SUMIF('GEM data - Upside'!$B:$B,'Chart Data'!$DC11,'GEM data - Upside'!$F:$F) -> 1471002 | EL11: =100*((EI11/EI10)-1) -> 3.5767226 | EM11: =100*((EJ11/EJ10)-1) -> 5.4214955 | EO11: 1988 | EP11: =SUMIF('GEM data - Zero_net'!$B:$B,'Chart Data'!$DC11,'GEM data - Zero_net'!$U:$U) -> 1405882.9 | EQ11: =AVERAGEIF('GEM data - Zero_net'!$B:$B,'Chart Data'!$DC11,'GEM data - Zero_net'!$V:$V) -> 25806.3 | ER11: =AVERAGEIF('GEM data - Zero_net'!$B:$B,'Chart Data'!$DC11,'GEM data - Zero_net'!$W:$W) -> 33.690102 | ES11: =AVERAGEIF('GEM data - Zero_net'!$B:$B,'Chart Data'!$DC11,'GEM data - Zero_net'!$X:$X) -> 336945.48 | ET11: =AVERAGEIF('GEM data - Zero_net'!$B:$B,'Chart Data'!$DC11,'GEM data - Zero_net'!$Y:$Y) -> 37299.198 | EU11: =AVERAGEIF('GEM data - Zero_net'!$B:$B,'Chart Data'!$DC11,'GEM data - Zero_net'!$Z:$Z) -> 1400419.5 | EV11: =AVERAGEIF('GEM data - Zero_net'!$B:$B,'Chart Data'!$DC11,'GEM data - Zero_net'!$AA:$AA) -> -1.7301365 | EX11: =EQ11*ER11 -> 869416.89 | EY11: =ES11/ET11 -> 9.0335851 | EZ11: =EU11 -> 1400419.5 | FA11: =EV11 -> -1.7301365 | FB11: =EP11 -> 1405882.9 | FC11: =SUMIF('GEM data - Zero_net'!$B:$B,'Chart Data'!$DC11,'GEM data - Zero_net'!$F:$F) -> 1471002 | FE11: =100*((FB11/FB10)-1) -> 3.5767226 | FF11: =100*((FC11/FC10)-1) -> 5.4214955
B12: ='GEM data - Baseline'!$F176 -> 686335 | C12: ='GEM data - Upside'!$F176 -> 686335 | D12: ='GEM data - Zero_net'!$F176 -> 686335 | F12: 2009 | G12: ='[2]Chart Data'!M13 -> 219.8 | M12: =100*(('GEM data - Baseline'!$P176/'GEM data - Baseline'!$P172)-1) -> 0.86774756 | N12: =100*(('GEM data - Upside'!$P176/'GEM data - Upside'!$P172)-1) -> 0.86774756 | O12: =100*(('GEM data - Zero_net'!$P176/'GEM data - Zero_net'!$P172)-1) -> 0.86774756 | Q12: 2029 | R12: =100*(SUMIF('GEM data - Baseline'!$C:$C,'Chart Data'!$Q12,'GEM data - Baseline'!$Q:$Q)/SUMIF('GEM data - Baseline'!$C:$C,'Chart Data'!$Q12,'GEM data - Baseline'!$S:$S)) -> -0.077177242 | S12: =100*(SUMIF('GEM data - Upside'!$C:$C,'Chart Data'!$Q12,'GEM data - Upside'!$Q:$Q)/SUMIF('GEM data - Upside'!$C:$C,'Chart Data'!$Q12,'GEM data - Upside'!$S:$S)) -> -0.072489122 | T12: =100*(SUMIF('GEM data - Zero_net'!$C:$C,'Chart Data'!$Q12,'GEM data - Zero_net'!$Q:$Q)/SUMIF('GEM data - Zero_net'!$C:$C,'Chart Data'!$Q12,'GEM data - Zero_net'!$S:$S)) -> -0.040584525 | V12: 2029 | W12: =100*(SUMIF('GEM data - Baseline'!$D:$D,'Chart Data'!$Q12,'GEM data - Baseline'!$R:$R)/SUMIF('GEM data - Baseline'!$C:$C,'Chart Data'!$Q12,'GEM data - Baseline'!$S:$S)) -> 85.146404 | X12: =100*(SUMIF('GEM data - Upside'!$D:$D,'Chart Data'!$Q12,'GEM data - Upside'!$R:$R)/SUMIF('GEM data - Upside'!$C:$C,'Chart Data'!$Q12,'GEM data - Upside'!$S:$S)) -> 84.576065 | Y12: =100*(SUMIF('GEM data - Zero_net'!$D:$D,'Chart Data'!$Q12,'GEM data - Zero_net'!$R:$R)/SUMIF('GEM data - Zero_net'!$C:$C,'Chart Data'!$Q12,'GEM data - Zero_net'!$S:$S)) -> 86.362173 | AA12: 10 | AB12: =VLOOKUP($AA12,$AE$3:$AG$21,2,FALSE) -> Financial services | AC12: =VLOOKUP($AA12,$AE$3:$AG$21,3,FALSE) -> 17.065334 | AE12: =RANK(AG12,$AG$3:$AG$21) -> 5 | AF12: Communications | AG12: =100*(AL12/AJ12) -> 22.034733 | AI12: COM | AJ12: {=INDEX('HMRC emp by ind and nat'!$A$149:$C$233,MATCH(1,('HMRC emp by ind and nat'!$A$145:$CG$145=AJ$1)*('HMRC emp by ind and nat'!$A$146:$CG$146=$AI12),0),3)} -> 1286000 | AK12: {=INDEX('HMRC emp by ind and nat'!$A$149:$C$233,MATCH(1,('HMRC emp by ind and nat'!$A$145:$CG$145=AK$1)*('HMRC emp by ind and nat'!$A$146:$CG$146=$AI12),0),3)} -> 1002633.3 | AL12: =AJ12-AK12 -> 283366.67 | AP12: 2009 | AQ12: =AVERAGEIF('GEM data - Baseline'!$B:$B,'Chart Data'!$AP12,'GEM data - Baseline'!$AE:$AE) -> 26.175472 | AR12: =AVERAGEIF('GEM data - Upside'!$B:$B,'Chart Data'!$AP12,'GEM data - Upside'!$AE:$AE) -> 26.175472 | AS12: =AVERAGEIF('GEM data - Zero_net'!$B:$B,'Chart Data'!$AP12,'GEM data - Zero_net'!$AE:$AE) -> 26.175472 | AU12: 2009 | AV12: =AVERAGEIF('GEM data - Baseline'!$B:$B,'Chart Data'!$AP12,'GEM data - Baseline'!AE:AE) -> 26.175472 | AW12: =AVERAGEIF('GEM data - Baseline'!$B:$B,'Chart Data'!$AP12,'GEM data - Baseline'!AF:AF) -> 16.773772 | AX12: =AVERAGEIF('GEM data - Baseline'!$B:$B,'Chart Data'!$AP12,'GEM data - Baseline'!AG:AG) -> 35.68888 | AY12: =AVERAGEIF('GEM data - Baseline'!$B:$B,'Chart Data'!$AP12,'GEM data - Baseline'!AH:AH) -> 31.19476 | AZ12: =AVERAGEIF('GEM data - Baseline'!$B:$B,'Chart Data'!$AP12,'GEM data - Baseline'!AI:AI) -> 25.53587 | BA12: =AVERAGEIF('GEM data - Baseline'!$B:$B,'Chart Data'!$AP12,'GEM data - Baseline'!AJ:AJ) -> 32.54833 | BB12: =AVERAGEIF('GEM data - Baseline'!$B:$B,'Chart Data'!$AP12,'GEM data - Baseline'!AK:AK) -> 17.158935 | BF12: =100*(('GEM data - Baseline'!$F176/'GEM data - Baseline'!$F172)-1) -> 4.7131482 | BG12: =100*(('GEM data - Upside'!$F176/'GEM data - Upside'!$F172)-1) -> 4.7131482 | BH12: =100*(('GEM data - Zero_net'!$F176/'GEM data - Zero_net'!$F172)-1) -> 4.7131482 | BK12: =100*(('GEM data - Baseline'!$U176/'GEM data - Baseline'!$U172)-1) -> 2.7705524 | BL12: =100*(('GEM data - Upside'!$U176/'GEM data - Upside'!$U172)-1) -> 2.7705524 | BM12: =100*(('GEM data - Zero_net'!$U176/'GEM data - Zero_net'!$U172)-1) -> 2.7705524 | BP12: ='GEM data - Baseline'!$O176 -> 3.8 | BQ12: ='GEM data - Upside'!$O176 -> 3.8 | BR12: ='GEM data - Zero_net'!$O176 -> 3.8 | BU12: =100*(('GEM data - Baseline'!$L176/'GEM data - Baseline'!$L172)-1) -> 1.7010786 | BV12: =100*(('GEM data - Upside'!$L176/'GEM data - Upside'!$L172)-1) -> 1.7010786 | BW12: =100*(('GEM data - Zero_net'!$L176/'GEM data - Zero_net'!$L172)-1) -> 1.7010786 | BZ12: ='GEM data - Baseline'!$T176 -> 2.525043 | CA12: ='GEM data - Upside'!$T176 -> 2.525043 | CB12: ='GEM data - Zero_net'!$T176 -> 2.525043 | CE12: ='GEM data - Baseline'!$J176 -> 0.95 | CF12: ='GEM data - Upside'!$J176 -> 0.95 | CG12: ='GEM data - Zero_net'!$J176 -> 0.95 | CJ12: =100*(('GEM data - Baseline'!$I176/'GEM data - Baseline'!$I172)-1) -> 9.1511767 | CK12: =100*(('GEM data - Upside'!$I176/'GEM data - Upside'!$I172)-1) -> 9.1511767 | CL12: =100*(('GEM data - Zero_net'!$I176/'GEM data - Zero_net'!$I172)-1) -> 9.1511767 | CO12: =100*('GEM data - Baseline'!$AB176/'GEM data - Baseline'!$AD176) -> 406.62813 | CP12: =100*('GEM data - Upside'!$AB176/'GEM data - Upside'!$AD176) -> 406.62813 | CQ12: =100*('GEM data - Zero_net'!$AB176/'GEM data - Zero_net'!$AD176) -> 406.62813 | CT12: =100*('GEM data - Baseline'!$AC176/'GEM data - Baseline'!$AD176) -> 345.9696 | CU12: =100*('GEM data - Upside'!$AC176/'GEM data - Upside'!$AD176) -> 345.9696 | CV12: =100*('GEM data - Zero_net'!$AC176/'GEM data - Zero_net'!$AD176) -> 345.9696 | CY12: =100*('GEM data - Baseline'!$F176/'GEM data - Baseline'!$AD176) -> 1014.7481 | CZ12: =100*('GEM data - Upside'!$F176/'GEM data - Upside'!$AD176) -> 1014.7481 | DA12: =100*('GEM data - Zero_net'!$F176/'GEM data - Zero_net'!$AD176) -> 1014.7481 | DC12: 1989 | DD12: =SUMIF('GEM data - Baseline'!$B:$B,'Chart Data'!$DC12,'GEM data - Baseline'!$U:$U) -> 1456760.7 | DE12: =AVERAGEIF('GEM data - Baseline'!$B:$B,'Chart Data'!$DC12,'GEM data - Baseline'!$V:$V) -> 26091.83 | DF12: =AVERAGEIF('GEM data - Baseline'!$B:$B,'Chart Data'!$DC12,'GEM data - Baseline'!$W:$W) -> 33.77308 | DG12: =AVERAGEIF('GEM data - Baseline'!$B:$B,'Chart Data'!$DC12,'GEM data - Baseline'!$X:$X) -> 341767.78 | DH12: =AVERAGEIF('GEM data - Baseline'!$B:$B,'Chart Data'!$DC12,'GEM data - Baseline'!$Y:$Y) -> 37327.732 | DI12: =AVERAGEIF('GEM data - Baseline'!$B:$B,'Chart Data'!$DC12,'GEM data - Baseline'!$Z:$Z) -> 1449040.2 | DJ12: =AVERAGEIF('GEM data - Baseline'!$B:$B,'Chart Data'!$DC12,'GEM data - Baseline'!$AA:$AA) -> -1.7188853 | DL12: =DE12*DF12 -> 881201.46 | DM12: =DG12/DH12 -> 9.1558676 | DN12: =DI12 -> 1449040.2 | DO12: =DJ12 -> -1.7188853 | DP12: =DD12 -> 1456760.7 | DQ12: =SUMIF('GEM data - Baseline'!$B:$B,'Chart Data'!$DC12,'GEM data - Baseline'!$F:$F) -> 1506644 | DS12: =100*((DP12/DP11)-1) -> 3.6189216 | DT12: =100*((DQ12/DQ11)-1) -> 2.4229743 | DV12: 1989 | DW12: =SUMIF('GEM data - Upside'!$B:$B,'Chart Data'!$DC12,'GEM data - Upside'!$U:$U) -> 1456760.7 | DX12: =AVERAGEIF('GEM data - Upside'!$B:$B,'Chart Data'!$DC12,'GEM data - Upside'!$V:$V) -> 26091.83 | DY12: =AVERAGEIF('GEM data - Upside'!$B:$B,'Chart Data'!$DC12,'GEM data - Upside'!$W:$W) -> 33.77308 | DZ12: =AVERAGEIF('GEM data - Upside'!$B:$B,'Chart Data'!$DC12,'GEM data - Upside'!$X:$X) -> 341767.78 | EA12: =AVERAGEIF('GEM data - Upside'!$B:$B,'Chart Data'!$DC12,'GEM data - Upside'!$Y:$Y) -> 37327.732 | EB12: =AVERAGEIF('GEM data - Upside'!$B:$B,'Chart Data'!$DC12,'GEM data - Upside'!$Z:$Z) -> 1449040.2 | EC12: =AVERAGEIF('GEM data - Upside'!$B:$B,'Chart Data'!$DC12,'GEM data - Upside'!$AA:$AA) -> -1.7188853 | EE12: =DX12*DY12 -> 881201.46 | EF12: =DZ12/EA12 -> 9.1558676 | EG12: =EB12 -> 1449040.2 | EH12: =EC12 -> -1.7188853 | EI12: =DW12 -> 1456760.7 | EJ12: =SUMIF('GEM data - Upside'!$B:$B,'Chart Data'!$DC12,'GEM data - Upside'!$F:$F) -> 1506644 | EL12: =100*((EI12/EI11)-1) -> 3.6189216 | EM12: =100*((EJ12/EJ11)-1) -> 2.4229743 | EO12: 1989 | EP12: =SUMIF('GEM data - Zero_net'!$B:$B,'Chart Data'!$DC12,'GEM data - Zero_net'!$U:$U) -> 1456760.7 | EQ12: =AVERAGEIF('GEM data - Zero_net'!$B:$B,'Chart Data'!$DC12,'GEM data - Zero_net'!$V:$V) -> 26091.83 | ER12: =AVERAGEIF('GEM data - Zero_net'!$B:$B,'Chart Data'!$DC12,'GEM data - Zero_net'!$W:$W) -> 33.77308 | ES12: =AVERAGEIF('GEM data - Zero_net'!$B:$B,'Chart Data'!$DC12,'GEM data - Zero_net'!$X:$X) -> 341767.78 | ET12: =AVERAGEIF('GEM data - Zero_net'!$B:$B,'Chart Data'!$DC12,'GEM data - Zero_net'!$Y:$Y) -> 37327.732 | EU12: =AVERAGEIF('GEM data - Zero_net'!$B:$B,'Chart Data'!$DC12,'GEM data - Zero_net'!$Z:$Z) -> 1449040.2 | EV12: =AVERAGEIF('GEM data - Zero_net'!$B:$B,'Chart Data'!$DC12,'GEM data - Zero_net'!$AA:$AA) -> -1.7188853 | EX12: =EQ12*ER12 -> 881201.46 | EY12: =ES12/ET12 -> 9.1558676 | EZ12: =EU12 -> 1449040.2 | FA12: =EV12 -> -1.7188853 | FB12: =EP12 -> 1456760.7 | FC12: =SUMIF('GEM data - Zero_net'!$B:$B,'Chart Data'!$DC12,'GEM data - Zero_net'!$F:$F) -> 1506644 | FE12: =100*((FB12/FB11)-1) -> 3.6189216 | FF12: =100*((FC12/FC11)-1) -> 2.4229743
B13: ='GEM data - Baseline'!$F177 -> 687029 | C13: ='GEM data - Upside'!$F177 -> 687029 | D13: ='GEM data - Zero_net'!$F177 -> 687029 | F13: 2010 | G13: ='[2]Chart Data'!M14 -> 255.4 | M13: =100*(('GEM data - Baseline'!$P177/'GEM data - Baseline'!$P173)-1) -> 0.99731336 | N13: =100*(('GEM data - Upside'!$P177/'GEM data - Upside'!$P173)-1) -> 0.99731336 | O13: =100*(('GEM data - Zero_net'!$P177/'GEM data - Zero_net'!$P173)-1) -> 0.99731336 | Q13: 2030 | R13: =100*(SUMIF('GEM data - Baseline'!$C:$C,'Chart Data'!$Q13,'GEM data - Baseline'!$Q:$Q)/SUMIF('GEM data - Baseline'!$C:$C,'Chart Data'!$Q13,'GEM data - Baseline'!$S:$S)) -> 0.21616183 | S13: =100*(SUMIF('GEM data - Upside'!$C:$C,'Chart Data'!$Q13,'GEM data - Upside'!$Q:$Q)/SUMIF('GEM data - Upside'!$C:$C,'Chart Data'!$Q13,'GEM data - Upside'!$S:$S)) -> 0.23563519 | T13: =100*(SUMIF('GEM data - Zero_net'!$C:$C,'Chart Data'!$Q13,'GEM data - Zero_net'!$Q:$Q)/SUMIF('GEM data - Zero_net'!$C:$C,'Chart Data'!$Q13,'GEM data - Zero_net'!$S:$S)) -> 0.20701149 | V13: 2030 | W13: =100*(SUMIF('GEM data - Baseline'!$D:$D,'Chart Data'!$Q13,'GEM data - Baseline'!$R:$R)/SUMIF('GEM data - Baseline'!$C:$C,'Chart Data'!$Q13,'GEM data - Baseline'!$S:$S)) -> 84.699773 | X13: =100*(SUMIF('GEM data - Upside'!$D:$D,'Chart Data'!$Q13,'GEM data - Upside'!$R:$R)/SUMIF('GEM data - Upside'!$C:$C,'Chart Data'!$Q13,'GEM data - Upside'!$S:$S)) -> 84.028324 | Y13: =100*(SUMIF('GEM data - Zero_net'!$D:$D,'Chart Data'!$Q13,'GEM data - Zero_net'!$R:$R)/SUMIF('GEM data - Zero_net'!$C:$C,'Chart Data'!$Q13,'GEM data - Zero_net'!$S:$S)) -> 86.014588 | AA13: 11 | AB13: =VLOOKUP($AA13,$AE$3:$AG$21,2,FALSE) -> Wholesale & retail | AC13: =VLOOKUP($AA13,$AE$3:$AG$21,3,FALSE) -> 16.953289 | AE13: =RANK(AG13,$AG$3:$AG$21) -> 10 | AF13: Financial services | AG13: =100*(AL13/AJ13) -> 17.065334 | AI13: FIN | AJ13: {=INDEX('HMRC emp by ind and nat'!$A$149:$C$233,MATCH(1,('HMRC emp by ind and nat'!$A$145:$CG$145=AJ$1)*('HMRC emp by ind and nat'!$A$146:$CG$146=$AI13),0),3)} -> 1120400 | AK13: {=INDEX('HMRC emp by ind and nat'!$A$149:$C$233,MATCH(1,('HMRC emp by ind and nat'!$A$145:$CG$145=AK$1)*('HMRC emp by ind and nat'!$A$146:$CG$146=$AI13),0),3)} -> 929200 | AL13: =AJ13-AK13 -> 191200 | AP13: 2010 | AQ13: =AVERAGEIF('GEM data - Baseline'!$B:$B,'Chart Data'!$AP13,'GEM data - Baseline'!$AE:$AE) -> 26.453032 | AR13: =AVERAGEIF('GEM data - Upside'!$B:$B,'Chart Data'!$AP13,'GEM data - Upside'!$AE:$AE) -> 26.453032 | AS13: =AVERAGEIF('GEM data - Zero_net'!$B:$B,'Chart Data'!$AP13,'GEM data - Zero_net'!$AE:$AE) -> 26.453032 | AU13: 2010 | AV13: =AVERAGEIF('GEM data - Baseline'!$B:$B,'Chart Data'!$AP13,'GEM data - Baseline'!AE:AE) -> 26.453032 | AW13: =AVERAGEIF('GEM data - Baseline'!$B:$B,'Chart Data'!$AP13,'GEM data - Baseline'!AF:AF) -> 16.988437 | AX13: =AVERAGEIF('GEM data - Baseline'!$B:$B,'Chart Data'!$AP13,'GEM data - Baseline'!AG:AG) -> 36.357518 | AY13: =AVERAGEIF('GEM data - Baseline'!$B:$B,'Chart Data'!$AP13,'GEM data - Baseline'!AH:AH) -> 31.39973 | AZ13: =AVERAGEIF('GEM data - Baseline'!$B:$B,'Chart Data'!$AP13,'GEM data - Baseline'!AI:AI) -> 25.749962 | BA13: =AVERAGEIF('GEM data - Baseline'!$B:$B,'Chart Data'!$AP13,'GEM data - Baseline'!AJ:AJ) -> 32.792255 | BB13: =AVERAGEIF('GEM data - Baseline'!$B:$B,'Chart Data'!$AP13,'GEM data - Baseline'!AK:AK) -> 17.41872 | BF13: =100*(('GEM data - Baseline'!$F177/'GEM data - Baseline'!$F173)-1) -> 3.0804293 | BG13: =100*(('GEM data - Upside'!$F177/'GEM data - Upside'!$F173)-1) -> 3.0804293 | BH13: =100*(('GEM data - Zero_net'!$F177/'GEM data - Zero_net'!$F173)-1) -> 3.0804293 | BK13: =100*(('GEM data - Baseline'!$U177/'GEM data - Baseline'!$U173)-1) -> 1.173965 | BL13: =100*(('GEM data - Upside'!$U177/'GEM data - Upside'!$U173)-1) -> 1.173965 | BM13: =100*(('GEM data - Zero_net'!$U177/'GEM data - Zero_net'!$U173)-1) -> 1.173965 | BP13: ='GEM data - Baseline'!$O177 -> 3.7 | BQ13: ='GEM data - Upside'!$O177 -> 3.7 | BR13: ='GEM data - Zero_net'!$O177 -> 3.7 | BU13: =100*(('GEM data - Baseline'!$L177/'GEM data - Baseline'!$L173)-1) -> 0.60200464 | BV13: =100*(('GEM data - Upside'!$L177/'GEM data - Upside'!$L173)-1) -> 0.60200464 | BW13: =100*(('GEM data - Zero_net'!$L177/'GEM data - Zero_net'!$L173)-1) -> 0.60200464 | BZ13: ='GEM data - Baseline'!$T177 -> 2.407074 | CA13: ='GEM data - Upside'!$T177 -> 2.407074 | CB13: ='GEM data - Zero_net'!$T177 -> 2.407074 | CE13: ='GEM data - Baseline'!$J177 -> 1.621212 | CF13: ='GEM data - Upside'!$J177 -> 1.621212 | CG13: ='GEM data - Zero_net'!$J177 -> 1.621212 | CJ13: =100*(('GEM data - Baseline'!$I177/'GEM data - Baseline'!$I173)-1) -> 10.005959 | CK13: =100*(('GEM data - Upside'!$I177/'GEM data - Upside'!$I173)-1) -> 10.005959 | CL13: =100*(('GEM data - Zero_net'!$I177/'GEM data - Zero_net'!$I173)-1) -> 10.005959 | CO13: =100*('GEM data - Baseline'!$AB177/'GEM data - Baseline'!$AD177) -> 406.9306 | CP13: =100*('GEM data - Upside'!$AB177/'GEM data - Upside'!$AD177) -> 406.9306 | CQ13: =100*('GEM data - Zero_net'!$AB177/'GEM data - Zero_net'!$AD177) -> 406.9306 | CT13: =100*('GEM data - Baseline'!$AC177/'GEM data - Baseline'!$AD177) -> 371.82667 | CU13: =100*('GEM data - Upside'!$AC177/'GEM data - Upside'!$AD177) -> 371.82667 | CV13: =100*('GEM data - Zero_net'!$AC177/'GEM data - Zero_net'!$AD177) -> 371.82667 | CY13: =100*('GEM data - Baseline'!$F177/'GEM data - Baseline'!$AD177) -> 1012.4435 | CZ13: =100*('GEM data - Upside'!$F177/'GEM data - Upside'!$AD177) -> 1012.4435 | DA13: =100*('GEM data - Zero_net'!$F177/'GEM data - Zero_net'!$AD177) -> 1012.4435 | DC13: 1990 | DD13: =SUMIF('GEM data - Baseline'!$B:$B,'Chart Data'!$DC13,'GEM data - Baseline'!$U:$U) -> 1496083.5 | DE13: =AVERAGEIF('GEM data - Baseline'!$B:$B,'Chart Data'!$DC13,'GEM data - Baseline'!$V:$V) -> 26176.673 | DF13: =AVERAGEIF('GEM data - Baseline'!$B:$B,'Chart Data'!$DC13,'GEM data - Baseline'!$W:$W) -> 33.607123 | DG13: =AVERAGEIF('GEM data - Baseline'!$B:$B,'Chart Data'!$DC13,'GEM data - Baseline'!$X:$X) -> 346213.43 | DH13: =AVERAGEIF('GEM data - Baseline'!$B:$B,'Chart Data'!$DC13,'GEM data - Baseline'!$Y:$Y) -> 37358.555 | DI13: =AVERAGEIF('GEM data - Baseline'!$B:$B,'Chart Data'!$DC13,'GEM data - Baseline'!$Z:$Z) -> 1504679.8 | DJ13: =AVERAGEIF('GEM data - Baseline'!$B:$B,'Chart Data'!$DC13,'GEM data - Baseline'!$AA:$AA) -> -1.7077067 | DL13: =DE13*DF13 -> 879722.64 | DM13: =DG13/DH13 -> 9.2673131 | DN13: =DI13 -> 1504679.8 | DO13: =DJ13 -> -1.7077067 | DP13: =DD13 -> 1496083.5 | DQ13: =SUMIF('GEM data - Baseline'!$B:$B,'Chart Data'!$DC13,'GEM data - Baseline'!$F:$F) -> 1515202 | DS13: =100*((DP13/DP12)-1) -> 2.6993315 | DT13: =100*((DQ13/DQ12)-1) -> 0.56801739 | DV13: 1990 | DW13: =SUMIF('GEM data - Upside'!$B:$B,'Chart Data'!$DC13,'GEM data - Upside'!$U:$U) -> 1496083.5 | DX13: =AVERAGEIF('GEM data - Upside'!$B:$B,'Chart Data'!$DC13,'GEM data - Upside'!$V:$V) -> 26176.673 | DY13: =AVERAGEIF('GEM data - Upside'!$B:$B,'Chart Data'!$DC13,'GEM data - Upside'!$W:$W) -> 33.607123 | DZ13: =AVERAGEIF('GEM data - Upside'!$B:$B,'Chart Data'!$DC13,'GEM data - Upside'!$X:$X) -> 346213.43 | EA13: =AVERAGEIF('GEM data - Upside'!$B:$B,'Chart Data'!$DC13,'GEM data - Upside'!$Y:$Y) -> 37358.555 | EB13: =AVERAGEIF('GEM data - Upside'!$B:$B,'Chart Data'!$DC13,'GEM data - Upside'!$Z:$Z) -> 1504679.8 | EC13: =AVERAGEIF('GEM data - Upside'!$B:$B,'Chart Data'!$DC13,'GEM data - Upside'!$AA:$AA) -> -1.7077067 | EE13: =DX13*DY13 -> 879722.64 | EF13: =DZ13/EA13 -> 9.2673131 | EG13: =EB13 -> 1504679.8 | EH13: =EC13 -> -1.7077067 | EI13: =DW13 -> 1496083.5 | EJ13: =SUMIF('GEM data - Upside'!$B:$B,'Chart Data'!$DC13,'GEM data - Upside'!$F:$F) -> 1515202 | EL13: =100*((EI13/EI12)-1) -> 2.6993315 | EM13: =100*((EJ13/EJ12)-1) -> 0.56801739 | EO13: 1990 | EP13: =SUMIF('GEM data - Zero_net'!$B:$B,'Chart Data'!$DC13,'GEM data - Zero_net'!$U:$U) -> 1496083.5 | EQ13: =AVERAGEIF('GEM data - Zero_net'!$B:$B,'Chart Data'!$DC13,'GEM data - Zero_net'!$V:$V) -> 26176.673 | ER13: =AVERAGEIF('GEM data - Zero_net'!$B:$B,'Chart Data'!$DC13,'GEM data - Zero_net'!$W:$W) -> 33.607123 | ES13: =AVERAGEIF('GEM data - Zero_net'!$B:$B,'Chart Data'!$DC13,'GEM data - Zero_net'!$X:$X) -> 346213.43 | ET13: =AVERAGEIF('GEM data - Zero_net'!$B:$B,'Chart Data'!$DC13,'GEM data - Zero_net'!$Y:$Y) -> 37358.555 | EU13: =AVERAGEIF('GEM data - Zero_net'!$B:$B,'Chart Data'!$DC13,'GEM data - Zero_net'!$Z:$Z) -> 1504679.8 | EV13: =AVERAGEIF('GEM data - Zero_net'!$B:$B,'Chart Data'!$DC13,'GEM data - Zero_net'!$AA:$AA) -> -1.7077067 | EX13: =EQ13*ER13 -> 879722.64 | EY13: =ES13/ET13 -> 9.2673131 | EZ13: =EU13 -> 1504679.8 | FA13: =EV13 -> -1.7077067 | FB13: =EP13 -> 1496083.5 | FC13: =SUMIF('GEM data - Zero_net'!$B:$B,'Chart Data'!$DC13,'GEM data - Zero_net'!$F:$F) -> 1515202 | FE13: =100*((FB13/FB12)-1) -> 2.6993315 | FF13: =100*((FC13/FC12)-1) -> 0.56801739
B14: ='GEM data - Baseline'!$F178 -> 688817 | C14: ='GEM data - Upside'!$F178 -> 688817 | D14: ='GEM data - Zero_net'!$F178 -> 688817 | F14: 2011 | G14: ='[2]Chart Data'!M15 -> 270.3 | M14: =100*(('GEM data - Baseline'!$P178/'GEM data - Baseline'!$P174)-1) -> 1.1263197 | N14: =100*(('GEM data - Upside'!$P178/'GEM data - Upside'!$P174)-1) -> 1.1263197 | O14: =100*(('GEM data - Zero_net'!$P178/'GEM data - Zero_net'!$P174)-1) -> 1.1263197 | Q14: 2031 | R14: =100*(SUMIF('GEM data - Baseline'!$C:$C,'Chart Data'!$Q14,'GEM data - Baseline'!$Q:$Q)/SUMIF('GEM data - Baseline'!$C:$C,'Chart Data'!$Q14,'GEM data - Baseline'!$S:$S)) -> 0.016351715 | S14: =100*(SUMIF('GEM data - Upside'!$C:$C,'Chart Data'!$Q14,'GEM data - Upside'!$Q:$Q)/SUMIF('GEM data - Upside'!$C:$C,'Chart Data'!$Q14,'GEM data - Upside'!$S:$S)) -> 0.075822063 | T14: =100*(SUMIF('GEM data - Zero_net'!$C:$C,'Chart Data'!$Q14,'GEM data - Zero_net'!$Q:$Q)/SUMIF('GEM data - Zero_net'!$C:$C,'Chart Data'!$Q14,'GEM data - Zero_net'!$S:$S)) -> -0.017115125 | V14: 2031 | W14: =100*(SUMIF('GEM data - Baseline'!$D:$D,'Chart Data'!$Q14,'GEM data - Baseline'!$R:$R)/SUMIF('GEM data - Baseline'!$C:$C,'Chart Data'!$Q14,'GEM data - Baseline'!$S:$S)) -> 84.339065 | X14: =100*(SUMIF('GEM data - Upside'!$D:$D,'Chart Data'!$Q14,'GEM data - Upside'!$R:$R)/SUMIF('GEM data - Upside'!$C:$C,'Chart Data'!$Q14,'GEM data - Upside'!$S:$S)) -> 83.534543 | Y14: =100*(SUMIF('GEM data - Zero_net'!$D:$D,'Chart Data'!$Q14,'GEM data - Zero_net'!$R:$R)/SUMIF('GEM data - Zero_net'!$C:$C,'Chart Data'!$Q14,'GEM data - Zero_net'!$S:$S)) -> 85.794666 | AA14: 12 | AB14: =VLOOKUP($AA14,$AE$3:$AG$21,2,FALSE) -> Real estate | AC14: =VLOOKUP($AA14,$AE$3:$AG$21,3,FALSE) -> 13.085794 | AE14: =RANK(AG14,$AG$3:$AG$21) -> 12 | AF14: Real estate | AG14: =100*(AL14/AJ14) -> 13.085794 | AI14: REAL | AJ14: {=INDEX('HMRC emp by ind and nat'!$A$149:$C$233,MATCH(1,('HMRC emp by ind and nat'!$A$145:$CG$145=AJ$1)*('HMRC emp by ind and nat'!$A$146:$CG$146=$AI14),0),3)} -> 500033.33 | AK14: {=INDEX('HMRC emp by ind and nat'!$A$149:$C$233,MATCH(1,('HMRC emp by ind and nat'!$A$145:$CG$145=AK$1)*('HMRC emp by ind and nat'!$A$146:$CG$146=$AI14),0),3)} -> 434600 | AL14: =AJ14-AK14 -> 65433.333 | AP14: 2011 | AQ14: =AVERAGEIF('GEM data - Baseline'!$B:$B,'Chart Data'!$AP14,'GEM data - Baseline'!$AE:$AE) -> 26.74501 | AR14: =AVERAGEIF('GEM data - Upside'!$B:$B,'Chart Data'!$AP14,'GEM data - Upside'!$AE:$AE) -> 26.74501 | AS14: =AVERAGEIF('GEM data - Zero_net'!$B:$B,'Chart Data'!$AP14,'GEM data - Zero_net'!$AE:$AE) -> 26.74501 | AU14: 2011 | AV14: =AVERAGEIF('GEM data - Baseline'!$B:$B,'Chart Data'!$AP14,'GEM data - Baseline'!AE:AE) -> 26.74501 | AW14: =AVERAGEIF('GEM data - Baseline'!$B:$B,'Chart Data'!$AP14,'GEM data - Baseline'!AF:AF) -> 17.223195 | AX14: =AVERAGEIF('GEM data - Baseline'!$B:$B,'Chart Data'!$AP14,'GEM data - Baseline'!AG:AG) -> 37.510938 | AY14: =AVERAGEIF('GEM data - Baseline'!$B:$B,'Chart Data'!$AP14,'GEM data - Baseline'!AH:AH) -> 31.357408 | AZ14: =AVERAGEIF('GEM data - Baseline'!$B:$B,'Chart Data'!$AP14,'GEM data - Baseline'!AI:AI) -> 26.27397 | BA14: =AVERAGEIF('GEM data - Baseline'!$B:$B,'Chart Data'!$AP14,'GEM data - Baseline'!AJ:AJ) -> 33.355265 | BB14: =AVERAGEIF('GEM data - Baseline'!$B:$B,'Chart Data'!$AP14,'GEM data - Baseline'!AK:AK) -> 17.758223 | BF14: =100*(('GEM data - Baseline'!$F178/'GEM data - Baseline'!$F174)-1) -> 1.9442636 | BG14: =100*(('GEM data - Upside'!$F178/'GEM data - Upside'!$F174)-1) -> 1.9442636 | BH14: =100*(('GEM data - Zero_net'!$F178/'GEM data - Zero_net'!$F174)-1) -> 1.9442636 | BK14: =100*(('GEM data - Baseline'!$U178/'GEM data - Baseline'!$U174)-1) -> 1.4010192 | BL14: =100*(('GEM data - Upside'!$U178/'GEM data - Upside'!$U174)-1) -> 1.4010192 | BM14: =100*(('GEM data - Zero_net'!$U178/'GEM data - Zero_net'!$U174)-1) -> 1.4010192 | BP14: ='GEM data - Baseline'!$O178 -> 3.9 | BQ14: ='GEM data - Upside'!$O178 -> 3.9 | BR14: ='GEM data - Zero_net'!$O178 -> 3.9 | BU14: =100*(('GEM data - Baseline'!$L178/'GEM data - Baseline'!$L174)-1) -> 1.1731639 | BV14: =100*(('GEM data - Upside'!$L178/'GEM data - Upside'!$L174)-1) -> 1.1731639 | BW14: =100*(('GEM data - Zero_net'!$L178/'GEM data - Zero_net'!$L174)-1) -> 1.1731639 | BZ14: ='GEM data - Baseline'!$T178 -> 2.149868 | CA14: ='GEM data - Upside'!$T178 -> 2.149868 | CB14: ='GEM data - Zero_net'!$T178 -> 2.149868 | CE14: ='GEM data - Baseline'!$J178 -> 2.826923 | CF14: ='GEM data - Upside'!$J178 -> 2.826923 | CG14: ='GEM data - Zero_net'!$J178 -> 2.826923 | CJ14: =100*(('GEM data - Baseline'!$I178/'GEM data - Baseline'!$I174)-1) -> 10.751748 | CK14: =100*(('GEM data - Upside'!$I178/'GEM data - Upside'!$I174)-1) -> 10.751748 | CL14: =100*(('GEM data - Zero_net'!$I178/'GEM data - Zero_net'!$I174)-1) -> 10.751748 | CO14: =100*('GEM data - Baseline'!$AB178/'GEM data - Baseline'!$AD178) -> 429.88205 | CP14: =100*('GEM data - Upside'!$AB178/'GEM data - Upside'!$AD178) -> 429.88205 | CQ14: =100*('GEM data - Zero_net'!$AB178/'GEM data - Zero_net'!$AD178) -> 429.88205 | CT14: =100*('GEM data - Baseline'!$AC178/'GEM data - Baseline'!$AD178) -> 367.31393 | CU14: =100*('GEM data - Upside'!$AC178/'GEM data - Upside'!$AD178) -> 367.31393 | CV14: =100*('GEM data - Zero_net'!$AC178/'GEM data - Zero_net'!$AD178) -> 367.31393 | CY14: =100*('GEM data - Baseline'!$F178/'GEM data - Baseline'!$AD178) -> 1011.761 | CZ14: =100*('GEM data - Upside'!$F178/'GEM data - Upside'!$AD178) -> 1011.761 | DA14: =100*('GEM data - Zero_net'!$F178/'GEM data - Zero_net'!$AD178) -> 1011.761 | DC14: 1991 | DD14: =SUMIF('GEM data - Baseline'!$B:$B,'Chart Data'!$DC14,'GEM data - Baseline'!$U:$U) -> 1517014.6 | DE14: =AVERAGEIF('GEM data - Baseline'!$B:$B,'Chart Data'!$DC14,'GEM data - Baseline'!$V:$V) -> 25966.485 | DF14: =AVERAGEIF('GEM data - Baseline'!$B:$B,'Chart Data'!$DC14,'GEM data - Baseline'!$W:$W) -> 33.192217 | DG14: =AVERAGEIF('GEM data - Baseline'!$B:$B,'Chart Data'!$DC14,'GEM data - Baseline'!$X:$X) -> 350307.55 | DH14: =AVERAGEIF('GEM data - Baseline'!$B:$B,'Chart Data'!$DC14,'GEM data - Baseline'!$Y:$Y) -> 37364.492 | DI14: =AVERAGEIF('GEM data - Baseline'!$B:$B,'Chart Data'!$DC14,'GEM data - Baseline'!$Z:$Z) -> 1557341 | DJ14: =AVERAGEIF('GEM data - Baseline'!$B:$B,'Chart Data'!$DC14,'GEM data - Baseline'!$AA:$AA) -> -1.696601 | DL14: =DE14*DF14 -> 861885.22 | DM14: =DG14/DH14 -> 9.375413 | DN14: =DI14 -> 1557341 | DO14: =DJ14 -> -1.696601 | DP14: =DD14 -> 1517014.6 | DQ14: =SUMIF('GEM data - Baseline'!$B:$B,'Chart Data'!$DC14,'GEM data - Baseline'!$F:$F) -> 1493903 | DS14: =100*((DP14/DP13)-1) -> 1.3990596 | DT14: =100*((DQ14/DQ13)-1) -> -1.4056872 | DV14: 1991 | DW14: =SUMIF('GEM data - Upside'!$B:$B,'Chart Data'!$DC14,'GEM data - Upside'!$U:$U) -> 1517014.6 | DX14: =AVERAGEIF('GEM data - Upside'!$B:$B,'Chart Data'!$DC14,'GEM data - Upside'!$V:$V) -> 25966.485 | DY14: =AVERAGEIF('GEM data - Upside'!$B:$B,'Chart Data'!$DC14,'GEM data - Upside'!$W:$W) -> 33.192217 | DZ14: =AVERAGEIF('GEM data - Upside'!$B:$B,'Chart Data'!$DC14,'GEM data - Upside'!$X:$X) -> 350307.55 | EA14: =AVERAGEIF('GEM data - Upside'!$B:$B,'Chart Data'!$DC14,'GEM data - Upside'!$Y:$Y) -> 37364.492 | EB14: =AVERAGEIF('GEM data - Upside'!$B:$B,'Chart Data'!$DC14,'GEM data - Upside'!$Z:$Z) -> 1557341 | EC14: =AVERAGEIF('GEM data - Upside'!$B:$B,'Chart Data'!$DC14,'GEM data - Upside'!$AA:$AA) -> -1.696601 | EE14: =DX14*DY14 -> 861885.22 | EF14: =DZ14/EA14 -> 9.375413 | EG14: =EB14 -> 1557341 | EH14: =EC14 -> -1.696601 | EI14: =DW14 -> 1517014.6 | EJ14: =SUMIF('GEM data - Upside'!$B:$B,'Chart Data'!$DC14,'GEM data - Upside'!$F:$F) -> 1493903 | EL14: =100*((EI14/EI13)-1) -> 1.3990596 | EM14: =100*((EJ14/EJ13)-1) -> -1.4056872 | EO14: 1991 | EP14: =SUMIF('GEM data - Zero_net'!$B:$B,'Chart Data'!$DC14,'GEM data - Zero_net'!$U:$U) -> 1517014.6 | EQ14: =AVERAGEIF('GEM data - Zero_net'!$B:$B,'Chart Data'!$DC14,'GEM data - Zero_net'!$V:$V) -> 25966.485 | ER14: =AVERAGEIF('GEM data - Zero_net'!$B:$B,'Chart Data'!$DC14,'GEM data - Zero_net'!$W:$W) -> 33.192217 | ES14: =AVERAGEIF('GEM data - Zero_net'!$B:$B,'Chart Data'!$DC14,'GEM data - Zero_net'!$X:$X) -> 350307.55 | ET14: =AVERAGEIF('GEM data - Zero_net'!$B:$B,'Chart Data'!$DC14,'GEM data - Zero_net'!$Y:$Y) -> 37364.492 | EU14: =AVERAGEIF('GEM data - Zero_net'!$B:$B,'Chart Data'!$DC14,'GEM data - Zero_net'!$Z:$Z) -> 1557341 | EV14: =AVERAGEIF('GEM data - Zero_net'!$B:$B,'Chart Data'!$DC14,'GEM data - Zero_net'!$AA:$AA) -> -1.696601 | EX14: =EQ14*ER14 -> 861885.22 | EY14: =ES14/ET14 -> 9.375413 | EZ14: =EU14 -> 1557341 | FA14: =EV14 -> -1.696601 | FB14: =EP14 -> 1517014.6 | FC14: =SUMIF('GEM data - Zero_net'!$B:$B,'Chart Data'!$DC14,'GEM data - Zero_net'!$F:$F) -> 1493903 | FE14: =100*((FB14/FB13)-1) -> 1.3990596 | FF14: =100*((FC14/FC13)-1) -> -1.4056872
A15: 2023 | B15: ='GEM data - Baseline'!$F179 -> 689206 | C15: ='GEM data - Upside'!$F179 -> 689206 | D15: ='GEM data - Zero_net'!$F179 -> 689206 | F15: 2012 | G15: ='[2]Chart Data'!M16 -> 162 | L15: 2023 | M15: =100*(('GEM data - Baseline'!$P179/'GEM data - Baseline'!$P175)-1) -> 1.2547696 | N15: =100*(('GEM data - Upside'!$P179/'GEM data - Upside'!$P175)-1) -> 1.2547696 | O15: =100*(('GEM data - Zero_net'!$P179/'GEM data - Zero_net'!$P175)-1) -> 1.2547696 | Q15: 2032 | R15: =100*(SUMIF('GEM data - Baseline'!$C:$C,'Chart Data'!$Q15,'GEM data - Baseline'!$Q:$Q)/SUMIF('GEM data - Baseline'!$C:$C,'Chart Data'!$Q15,'GEM data - Baseline'!$S:$S)) -> -0.18565621 | S15: =100*(SUMIF('GEM data - Upside'!$C:$C,'Chart Data'!$Q15,'GEM data - Upside'!$Q:$Q)/SUMIF('GEM data - Upside'!$C:$C,'Chart Data'!$Q15,'GEM data - Upside'!$S:$S)) -> -0.082709442 | T15: =100*(SUMIF('GEM data - Zero_net'!$C:$C,'Chart Data'!$Q15,'GEM data - Zero_net'!$Q:$Q)/SUMIF('GEM data - Zero_net'!$C:$C,'Chart Data'!$Q15,'GEM data - Zero_net'!$S:$S)) -> -0.26302892 | V15: 2032 | W15: =100*(SUMIF('GEM data - Baseline'!$D:$D,'Chart Data'!$Q15,'GEM data - Baseline'!$R:$R)/SUMIF('GEM data - Baseline'!$C:$C,'Chart Data'!$Q15,'GEM data - Baseline'!$S:$S)) -> 84.205048 | X15: =100*(SUMIF('GEM data - Upside'!$D:$D,'Chart Data'!$Q15,'GEM data - Upside'!$R:$R)/SUMIF('GEM data - Upside'!$C:$C,'Chart Data'!$Q15,'GEM data - Upside'!$S:$S)) -> 83.229542 | Y15: =100*(SUMIF('GEM data - Zero_net'!$D:$D,'Chart Data'!$Q15,'GEM data - Zero_net'!$R:$R)/SUMIF('GEM data - Zero_net'!$C:$C,'Chart Data'!$Q15,'GEM data - Zero_net'!$S:$S)) -> 85.888522 | AA15: 13 | AB15: =VLOOKUP($AA15,$AE$3:$AG$21,2,FALSE) -> Education | AC15: =VLOOKUP($AA15,$AE$3:$AG$21,3,FALSE) -> 12.084882 | AE15: =RANK(AG15,$AG$3:$AG$21) -> 9 | AF15: Professional services | AG15: =100*(AL15/AJ15) -> 18.441099 | AI15: PROF | AJ15: {=INDEX('HMRC emp by ind and nat'!$A$149:$C$233,MATCH(1,('HMRC emp by ind and nat'!$A$145:$CG$145=AJ$1)*('HMRC emp by ind and nat'!$A$146:$CG$146=$AI15),0),3)} -> 2581733.3 | AK15: {=INDEX('HMRC emp by ind and nat'!$A$149:$C$233,MATCH(1,('HMRC emp by ind and nat'!$A$145:$CG$145=AK$1)*('HMRC emp by ind and nat'!$A$146:$CG$146=$AI15),0),3)} -> 2105633.3 | AL15: =AJ15-AK15 -> 476100 | AP15: 2012 | AQ15: =AVERAGEIF('GEM data - Baseline'!$B:$B,'Chart Data'!$AP15,'GEM data - Baseline'!$AE:$AE) -> 27.439737 | AR15: =AVERAGEIF('GEM data - Upside'!$B:$B,'Chart Data'!$AP15,'GEM data - Upside'!$AE:$AE) -> 27.439737 | AS15: =AVERAGEIF('GEM data - Zero_net'!$B:$B,'Chart Data'!$AP15,'GEM data - Zero_net'!$AE:$AE) -> 27.439737 | AU15: 2012 | AV15: =AVERAGEIF('GEM data - Baseline'!$B:$B,'Chart Data'!$AP15,'GEM data - Baseline'!AE:AE) -> 27.439737 | AW15: =AVERAGEIF('GEM data - Baseline'!$B:$B,'Chart Data'!$AP15,'GEM data - Baseline'!AF:AF) -> 17.59113 | AX15: =AVERAGEIF('GEM data - Baseline'!$B:$B,'Chart Data'!$AP15,'GEM data - Baseline'!AG:AG) -> 39.353817 | AY15: =AVERAGEIF('GEM data - Baseline'!$B:$B,'Chart Data'!$AP15,'GEM data - Baseline'!AH:AH) -> 31.361685 | AZ15: =AVERAGEIF('GEM data - Baseline'!$B:$B,'Chart Data'!$AP15,'GEM data - Baseline'!AI:AI) -> 27.015032 | BA15: =AVERAGEIF('GEM data - Baseline'!$B:$B,'Chart Data'!$AP15,'GEM data - Baseline'!AJ:AJ) -> 33.4105 | BB15: =AVERAGEIF('GEM data - Baseline'!$B:$B,'Chart Data'!$AP15,'GEM data - Baseline'!AK:AK) -> 18.260435 | BE15: 2023 | BF15: =100*(('GEM data - Baseline'!$F179/'GEM data - Baseline'!$F175)-1) -> 0.97856935 | BG15: =100*(('GEM data - Upside'!$F179/'GEM data - Upside'!$F175)-1) -> 0.97856935 | BH15: =100*(('GEM data - Zero_net'!$F179/'GEM data - Zero_net'!$F175)-1) -> 0.97856935 | BJ15: 2023 | BK15: =100*(('GEM data - Baseline'!$U179/'GEM data - Baseline'!$U175)-1) -> 1.8511418 | BL15: =100*(('GEM data - Upside'!$U179/'GEM data - Upside'!$U175)-1) -> 1.8511418 | BM15: =100*(('GEM data - Zero_net'!$U179/'GEM data - Zero_net'!$U175)-1) -> 1.8511418 | BO15: 2023 | BP15: ='GEM data - Baseline'!$O179 -> 4 | BQ15: ='GEM data - Upside'!$O179 -> 4 | BR15: ='GEM data - Zero_net'!$O179 -> 4 | BT15: 2023 | BU15: =100*(('GEM data - Baseline'!$L179/'GEM data - Baseline'!$L175)-1) -> 1.631595 | BV15: =100*(('GEM data - Upside'!$L179/'GEM data - Upside'!$L175)-1) -> 1.631595 | BW15: =100*(('GEM data - Zero_net'!$L179/'GEM data - Zero_net'!$L175)-1) -> 1.631595 | BY15: 2023 | BZ15: ='GEM data - Baseline'!$T179 -> 1.530838 | CA15: ='GEM data - Upside'!$T179 -> 1.530838 | CB15: ='GEM data - Zero_net'!$T179 -> 1.530838 | CD15: 2023 | CE15: ='GEM data - Baseline'!$J179 -> 3.85 | CF15: ='GEM data - Upside'!$J179 -> 3.85 | CG15: ='GEM data - Zero_net'!$J179 -> 3.85 | CI15: 2023 | CJ15: =100*(('GEM data - Baseline'!$I179/'GEM data - Baseline'!$I175)-1) -> 10.178266 | CK15: =100*(('GEM data - Upside'!$I179/'GEM data - Upside'!$I175)-1) -> 10.178266 | CL15: =100*(('GEM data - Zero_net'!$I179/'GEM data - Zero_net'!$I175)-1) -> 10.178266 | CN15: 2023 | CO15: =100*('GEM data - Baseline'!$AB179/'GEM data - Baseline'!$AD179) -> 463.87374 | CP15: =100*('GEM data - Upside'!$AB179/'GEM data - Upside'!$AD179) -> 463.87374 | CQ15: =100*('GEM data - Zero_net'!$AB179/'GEM data - Zero_net'!$AD179) -> 463.87374 | CS15: 2023 | CT15: =100*('GEM data - Baseline'!$AC179/'GEM data - Baseline'!$AD179) -> 434.71711 | CU15: =100*('GEM data - Upside'!$AC179/'GEM data - Upside'!$AD179) -> 434.71711 | CV15: =100*('GEM data - Zero_net'!$AC179/'GEM data - Zero_net'!$AD179) -> 434.71711 | CX15: 2023 | CY15: =100*('GEM data - Baseline'!$F179/'GEM data - Baseline'!$AD179) -> 1009.0347 | CZ15: =100*('GEM data - Upside'!$F179/'GEM data - Upside'!$AD179) -> 1009.0347 | DA15: =100*('GEM data - Zero_net'!$F179/'GEM data - Zero_net'!$AD179) -> 1009.0347 | DC15: 1992 | DD15: =SUMIF('GEM data - Baseline'!$B:$B,'Chart Data'!$DC15,'GEM data - Baseline'!$U:$U) -> 1538269.7 | DE15: =AVERAGEIF('GEM data - Baseline'!$B:$B,'Chart Data'!$DC15,'GEM data - Baseline'!$V:$V) -> 25667.158 | DF15: =AVERAGEIF('GEM data - Baseline'!$B:$B,'Chart Data'!$DC15,'GEM data - Baseline'!$W:$W) -> 33.076295 | DG15: =AVERAGEIF('GEM data - Baseline'!$B:$B,'Chart Data'!$DC15,'GEM data - Baseline'!$X:$X) -> 353919.65 | DH15: =AVERAGEIF('GEM data - Baseline'!$B:$B,'Chart Data'!$DC15,'GEM data - Baseline'!$Y:$Y) -> 37339.07 | DI15: =AVERAGEIF('GEM data - Baseline'!$B:$B,'Chart Data'!$DC15,'GEM data - Baseline'!$Z:$Z) -> 1594484.8 | DJ15: =AVERAGEIF('GEM data - Baseline'!$B:$B,'Chart Data'!$DC15,'GEM data - Baseline'!$AA:$AA) -> -1.6855678 | DL15: =DE15*DF15 -> 848974.47 | DM15: =DG15/DH15 -> 9.4785341 | DN15: =DI15 -> 1594484.8 | DO15: =DJ15 -> -1.6855678 | DP15: =DD15 -> 1538269.7 | DQ15: =SUMIF('GEM data - Baseline'!$B:$B,'Chart Data'!$DC15,'GEM data - Baseline'!$F:$F) -> 1498023 | DS15: =100*((DP15/DP14)-1) -> 1.4011137 | DT15: =100*((DQ15/DQ14)-1) -> 0.27578765 | DV15: 1992 | DW15: =SUMIF('GEM data - Upside'!$B:$B,'Chart Data'!$DC15,'GEM data - Upside'!$U:$U) -> 1538269.7 | DX15: =AVERAGEIF('GEM data - Upside'!$B:$B,'Chart Data'!$DC15,'GEM data - Upside'!$V:$V) -> 25667.158 | DY15: =AVERAGEIF('GEM data - Upside'!$B:$B,'Chart Data'!$DC15,'GEM data - Upside'!$W:$W) -> 33.076295 | DZ15: =AVERAGEIF('GEM data - Upside'!$B:$B,'Chart Data'!$DC15,'GEM data - Upside'!$X:$X) -> 353919.65 | EA15: =AVERAGEIF('GEM data - Upside'!$B:$B,'Chart Data'!$DC15,'GEM data - Upside'!$Y:$Y) -> 37339.07 | EB15: =AVERAGEIF('GEM data - Upside'!$B:$B,'Chart Data'!$DC15,'GEM data - Upside'!$Z:$Z) -> 1594484.8 | EC15: =AVERAGEIF('GEM data - Upside'!$B:$B,'Chart Data'!$DC15,'GEM data - Upside'!$AA:$AA) -> -1.6855678 | EE15: =DX15*DY15 -> 848974.47 | EF15: =DZ15/EA15 -> 9.4785341 | EG15: =EB15 -> 1594484.8 | EH15: =EC15 -> -1.6855678 | EI15: =DW15 -> 1538269.7 | EJ15: =SUMIF('GEM data - Upside'!$B:$B,'Chart Data'!$DC15,'GEM data - Upside'!$F:$F) -> 1498023 | EL15: =100*((EI15/EI14)-1) -> 1.4011137 | EM15: =100*((EJ15/EJ14)-1) -> 0.27578765 | EO15: 1992 | EP15: =SUMIF('GEM data - Zero_net'!$B:$B,'Chart Data'!$DC15,'GEM data - Zero_net'!$U:$U) -> 1538269.7 | EQ15: =AVERAGEIF('GEM data - Zero_net'!$B:$B,'Chart Data'!$DC15,'GEM data - Zero_net'!$V:$V) -> 25667.158 | ER15: =AVERAGEIF('GEM data - Zero_net'!$B:$B,'Chart Data'!$DC15,'GEM data - Zero_net'!$W:$W) -> 33.076295 | ES15: =AVERAGEIF('GEM data - Zero_net'!$B:$B,'Chart Data'!$DC15,'GEM data - Zero_net'!$X:$X) -> 353919.65 | ET15: =AVERAGEIF('GEM data - Zero_net'!$B:$B,'Chart Data'!$DC15,'GEM data - Zero_net'!$Y:$Y) -> 37339.07 | EU15: =AVERAGEIF('GEM data - Zero_net'!$B:$B,'Chart Data'!$DC15,'GEM data - Zero_net'!$Z:$Z) -> 1594484.8 | EV15: =AVERAGEIF('GEM data - Zero_net'!$B:$B,'Chart Data'!$DC15,'GEM data - Zero_net'!$AA:$AA) -> -1.6855678 | EX15: =EQ15*ER15 -> 848974.47 | EY15: =ES15/ET15 -> 9.4785341 | EZ15: =EU15 -> 1594484.8 | FA15: =EV15 -> -1.6855678 | FB15: =EP15 -> 1538269.7 | FC15: =SUMIF('GEM data - Zero_net'!$B:$B,'Chart Data'!$DC15,'GEM data - Zero_net'!$F:$F) -> 1498023 | FE15: =100*((FB15/FB14)-1) -> 1.4011137 | FF15: =100*((FC15/FC14)-1) -> 0.27578765
B16: ='GEM data - Baseline'!$F180 -> 689491 | C16: ='GEM data - Upside'!$F180 -> 689491 | D16: ='GEM data - Zero_net'!$F180 -> 689491 | F16: 2013 | G16: ='[2]Chart Data'!M17 -> 215 | M16: =100*(('GEM data - Baseline'!$P180/'GEM data - Baseline'!$P176)-1) -> 1.3826671 | N16: =100*(('GEM data - Upside'!$P180/'GEM data - Upside'!$P176)-1) -> 1.3826671 | O16: =100*(('GEM data - Zero_net'!$P180/'GEM data - Zero_net'!$P176)-1) -> 1.3826671 | Q16: 2033 | R16: =100*(SUMIF('GEM data - Baseline'!$C:$C,'Chart Data'!$Q16,'GEM data - Baseline'!$Q:$Q)/SUMIF('GEM data - Baseline'!$C:$C,'Chart Data'!$Q16,'GEM data - Baseline'!$S:$S)) -> -0.38739912 | S16: =100*(SUMIF('GEM data - Upside'!$C:$C,'Chart Data'!$Q16,'GEM data - Upside'!$Q:$Q)/SUMIF('GEM data - Upside'!$C:$C,'Chart Data'!$Q16,'GEM data - Upside'!$S:$S)) -> -0.27028884 | T16: =100*(SUMIF('GEM data - Zero_net'!$C:$C,'Chart Data'!$Q16,'GEM data - Zero_net'!$Q:$Q)/SUMIF('GEM data - Zero_net'!$C:$C,'Chart Data'!$Q16,'GEM data - Zero_net'!$S:$S)) -> -0.56318929 | V16: 2033 | W16: =100*(SUMIF('GEM data - Baseline'!$D:$D,'Chart Data'!$Q16,'GEM data - Baseline'!$R:$R)/SUMIF('GEM data - Baseline'!$C:$C,'Chart Data'!$Q16,'GEM data - Baseline'!$S:$S)) -> 84.074075 | X16: =100*(SUMIF('GEM data - Upside'!$D:$D,'Chart Data'!$Q16,'GEM data - Upside'!$R:$R)/SUMIF('GEM data - Upside'!$C:$C,'Chart Data'!$Q16,'GEM data - Upside'!$S:$S)) -> 82.946853 | Y16: =100*(SUMIF('GEM data - Zero_net'!$D:$D,'Chart Data'!$Q16,'GEM data - Zero_net'!$R:$R)/SUMIF('GEM data - Zero_net'!$C:$C,'Chart Data'!$Q16,'GEM data - Zero_net'!$S:$S)) -> 86.163267 | AA16: 14 | AB16: =VLOOKUP($AA16,$AE$3:$AG$21,2,FALSE) -> Construction | AC16: =VLOOKUP($AA16,$AE$3:$AG$21,3,FALSE) -> 12.079649 | AE16: =RANK(AG16,$AG$3:$AG$21) -> 1 | AF16: Administrative services | AG16: =100*(AL16/AJ16) -> 33.584697 | AI16: ADMIN | AJ16: {=INDEX('HMRC emp by ind and nat'!$A$149:$C$233,MATCH(1,('HMRC emp by ind and nat'!$A$145:$CG$145=AJ$1)*('HMRC emp by ind and nat'!$A$146:$CG$146=$AI16),0),3)} -> 2709666.7 | AK16: {=INDEX('HMRC emp by ind and nat'!$A$149:$C$233,MATCH(1,('HMRC emp by ind and nat'!$A$145:$CG$145=AK$1)*('HMRC emp by ind and nat'!$A$146:$CG$146=$AI16),0),3)} -> 1799633.3 | AL16: =AJ16-AK16 -> 910033.33 | AP16: 2013 | AQ16: =AVERAGEIF('GEM data - Baseline'!$B:$B,'Chart Data'!$AP16,'GEM data - Baseline'!$AE:$AE) -> 27.93509 | AR16: =AVERAGEIF('GEM data - Upside'!$B:$B,'Chart Data'!$AP16,'GEM data - Upside'!$AE:$AE) -> 27.93509 | AS16: =AVERAGEIF('GEM data - Zero_net'!$B:$B,'Chart Data'!$AP16,'GEM data - Zero_net'!$AE:$AE) -> 27.93509 | AU16: 2013 | AV16: =AVERAGEIF('GEM data - Baseline'!$B:$B,'Chart Data'!$AP16,'GEM data - Baseline'!AE:AE) -> 27.93509 | AW16: =AVERAGEIF('GEM data - Baseline'!$B:$B,'Chart Data'!$AP16,'GEM data - Baseline'!AF:AF) -> 18.022983 | AX16: =AVERAGEIF('GEM data - Baseline'!$B:$B,'Chart Data'!$AP16,'GEM data - Baseline'!AG:AG) -> 41.32392 | AY16: =AVERAGEIF('GEM data - Baseline'!$B:$B,'Chart Data'!$AP16,'GEM data - Baseline'!AH:AH) -> 31.462042 | AZ16: =AVERAGEIF('GEM data - Baseline'!$B:$B,'Chart Data'!$AP16,'GEM data - Baseline'!AI:AI) -> 27.751485 | BA16: =AVERAGEIF('GEM data - Baseline'!$B:$B,'Chart Data'!$AP16,'GEM data - Baseline'!AJ:AJ) -> 33.572385 | BB16: =AVERAGEIF('GEM data - Baseline'!$B:$B,'Chart Data'!$AP16,'GEM data - Baseline'!AK:AK) -> 18.752803 | BF16: =100*(('GEM data - Baseline'!$F180/'GEM data - Baseline'!$F176)-1) -> 0.45983375 | BG16: =100*(('GEM data - Upside'!$F180/'GEM data - Upside'!$F176)-1) -> 0.45983375 | BH16: =100*(('GEM data - Zero_net'!$F180/'GEM data - Zero_net'!$F176)-1) -> 0.45983375 | BK16: =100*(('GEM data - Baseline'!$U180/'GEM data - Baseline'!$U176)-1) -> 1.6470621 | BL16: =100*(('GEM data - Upside'!$U180/'GEM data - Upside'!$U176)-1) -> 1.6470621 | BM16: =100*(('GEM data - Zero_net'!$U180/'GEM data - Zero_net'!$U176)-1) -> 1.6470621 | BP16: ='GEM data - Baseline'!$O180 -> 4.2 | BQ16: ='GEM data - Upside'!$O180 -> 4.2 | BR16: ='GEM data - Zero_net'!$O180 -> 4.2 | BU16: =100*(('GEM data - Baseline'!$L180/'GEM data - Baseline'!$L176)-1) -> 1.0544815 | BV16: =100*(('GEM data - Upside'!$L180/'GEM data - Upside'!$L176)-1) -> 1.0544815 | BW16: =100*(('GEM data - Zero_net'!$L180/'GEM data - Zero_net'!$L176)-1) -> 1.0544815 | BZ16: ='GEM data - Baseline'!$T180 -> 1.350212 | CA16: ='GEM data - Upside'!$T180 -> 1.350212 | CB16: ='GEM data - Zero_net'!$T180 -> 1.350212 | CE16: ='GEM data - Baseline'!$J180 -> 4.446154 | CF16: ='GEM data - Upside'!$J180 -> 4.446154 | CG16: ='GEM data - Zero_net'!$J180 -> 4.446154 | CJ16: =100*(('GEM data - Baseline'!$I180/'GEM data - Baseline'!$I176)-1) -> 8.439049 | CK16: =100*(('GEM data - Upside'!$I180/'GEM data - Upside'!$I176)-1) -> 8.439049 | CL16: =100*(('GEM data - Zero_net'!$I180/'GEM data - Zero_net'!$I176)-1) -> 8.439049 | CO16: =100*('GEM data - Baseline'!$AB180/'GEM data - Baseline'!$AD180) -> 450.12842 | CP16: =100*('GEM data - Upside'!$AB180/'GEM data - Upside'!$AD180) -> 450.12842 | CQ16: =100*('GEM data - Zero_net'!$AB180/'GEM data - Zero_net'!$AD180) -> 450.12842 | CT16: =100*('GEM data - Baseline'!$AC180/'GEM data - Baseline'!$AD180) -> 370.68704 | CU16: =100*('GEM data - Upside'!$AC180/'GEM data - Upside'!$AD180) -> 370.68704 | CV16: =100*('GEM data - Zero_net'!$AC180/'GEM data - Zero_net'!$AD180) -> 370.68704 | CY16: =100*('GEM data - Baseline'!$F180/'GEM data - Baseline'!$AD180) -> 1006.1743 | CZ16: =100*('GEM data - Upside'!$F180/'GEM data - Upside'!$AD180) -> 1006.1743 | DA16: =100*('GEM data - Zero_net'!$F180/'GEM data - Zero_net'!$AD180) -> 1006.1743 | DC16: 1993 | DD16: =SUMIF('GEM data - Baseline'!$B:$B,'Chart Data'!$DC16,'GEM data - Baseline'!$U:$U) -> 1563590.1 | DE16: =AVERAGEIF('GEM data - Baseline'!$B:$B,'Chart Data'!$DC16,'GEM data - Baseline'!$V:$V) -> 25571.118 | DF16: =AVERAGEIF('GEM data - Baseline'!$B:$B,'Chart Data'!$DC16,'GEM data - Baseline'!$W:$W) -> 33 | DG16: =AVERAGEIF('GEM data - Baseline'!$B:$B,'Chart Data'!$DC16,'GEM data - Baseline'!$X:$X) -> 357272.07 | DH16: =AVERAGEIF('GEM data - Baseline'!$B:$B,'Chart Data'!$DC16,'GEM data - Baseline'!$Y:$Y) -> 37349.41 | DI16: =AVERAGEIF('GEM data - Baseline'!$B:$B,'Chart Data'!$DC16,'GEM data - Baseline'!$Z:$Z) -> 1624514.8 | DJ16: =AVERAGEIF('GEM data - Baseline'!$B:$B,'Chart Data'!$DC16,'GEM data - Baseline'!$AA:$AA) -> -1.6746063 | DL16: =DE16*DF16 -> 843846.88 | DM16: =DG16/DH16 -> 9.5656685 | DN16: =DI16 -> 1624514.8 | DO16: =DJ16 -> -1.6746063 | DP16: =DD16 -> 1563590.1 | DQ16: =SUMIF('GEM data - Baseline'!$B:$B,'Chart Data'!$DC16,'GEM data - Baseline'!$F:$F) -> 1532082 | DS16: =100*((DP16/DP15)-1) -> 1.6460313 | DT16: =100*((DQ16/DQ15)-1) -> 2.2735966 | DV16: 1993 | DW16: =SUMIF('GEM data - Upside'!$B:$B,'Chart Data'!$DC16,'GEM data - Upside'!$U:$U) -> 1563590.1 | DX16: =AVERAGEIF('GEM data - Upside'!$B:$B,'Chart Data'!$DC16,'GEM data - Upside'!$V:$V) -> 25571.118 | DY16: =AVERAGEIF('GEM data - Upside'!$B:$B,'Chart Data'!$DC16,'GEM data - Upside'!$W:$W) -> 33 | DZ16: =AVERAGEIF('GEM data - Upside'!$B:$B,'Chart Data'!$DC16,'GEM data - Upside'!$X:$X) -> 357272.07 | EA16: =AVERAGEIF('GEM data - Upside'!$B:$B,'Chart Data'!$DC16,'GEM data - Upside'!$Y:$Y) -> 37349.41 | EB16: =AVERAGEIF('GEM data - Upside'!$B:$B,'Chart Data'!$DC16,'GEM data - Upside'!$Z:$Z) -> 1624514.8 | EC16: =AVERAGEIF('GEM data - Upside'!$B:$B,'Chart Data'!$DC16,'GEM data - Upside'!$AA:$AA) -> -1.6746063 | EE16: =DX16*DY16 -> 843846.88 | EF16: =DZ16/EA16 -> 9.5656685 | EG16: =EB16 -> 1624514.8 | EH16: =EC16 -> -1.6746063 | EI16: =DW16 -> 1563590.1 | EJ16: =SUMIF('GEM data - Upside'!$B:$B,'Chart Data'!$DC16,'GEM data - Upside'!$F:$F) -> 1532082 | EL16: =100*((EI16/EI15)-1) -> 1.6460313 | EM16: =100*((EJ16/EJ15)-1) -> 2.2735966 | EO16: 1993 | EP16: =SUMIF('GEM data - Zero_net'!$B:$B,'Chart Data'!$DC16,'GEM data - Zero_net'!$U:$U) -> 1563590.1 | EQ16: =AVERAGEIF('GEM data - Zero_net'!$B:$B,'Chart Data'!$DC16,'GEM data - Zero_net'!$V:$V) -> 25571.118 | ER16: =AVERAGEIF('GEM data - Zero_net'!$B:$B,'Chart Data'!$DC16,'GEM data - Zero_net'!$W:$W) -> 33 | ES16: =AVERAGEIF('GEM data - Zero_net'!$B:$B,'Chart Data'!$DC16,'GEM data - Zero_net'!$X:$X) -> 357272.07 | ET16: =AVERAGEIF('GEM data - Zero_net'!$B:$B,'Chart Data'!$DC16,'GEM data - Zero_net'!$Y:$Y) -> 37349.41 | EU16: =AVERAGEIF('GEM data - Zero_net'!$B:$B,'Chart Data'!$DC16,'GEM data - Zero_net'!$Z:$Z) -> 1624514.8 | EV16: =AVERAGEIF('GEM data - Zero_net'!$B:$B,'Chart Data'!$DC16,'GEM data - Zero_net'!$AA:$AA) -> -1.6746063 | EX16: =EQ16*ER16 -> 843846.88 | EY16: =ES16/ET16 -> 9.5656685 | EZ16: =EU16 -> 1624514.8 | FA16: =EV16 -> -1.6746063 | FB16: =EP16 -> 1563590.1 | FC16: =SUMIF('GEM data - Zero_net'!$B:$B,'Chart Data'!$DC16,'GEM data - Zero_net'!$F:$F) -> 1532082 | FE16: =100*((FB16/FB15)-1) -> 1.6460313 | FF16: =100*((FC16/FC15)-1) -> 2.2735966
B17: ='GEM data - Baseline'!$F181 -> 687839 | C17: ='GEM data - Upside'!$F181 -> 687839 | D17: ='GEM data - Zero_net'!$F181 -> 687839 | F17: 2014 | G17: ='[2]Chart Data'!M18 -> 248 | M17: =100*(('GEM data - Baseline'!$P181/'GEM data - Baseline'!$P177)-1) -> 1.3110784 | N17: =100*(('GEM data - Upside'!$P181/'GEM data - Upside'!$P177)-1) -> 1.3110784 | O17: =100*(('GEM data - Zero_net'!$P181/'GEM data - Zero_net'!$P177)-1) -> 1.3110784 | Q17: 2034 | R17: =100*(SUMIF('GEM data - Baseline'!$C:$C,'Chart Data'!$Q17,'GEM data - Baseline'!$Q:$Q)/SUMIF('GEM data - Baseline'!$C:$C,'Chart Data'!$Q17,'GEM data - Baseline'!$S:$S)) -> -0.58967563 | S17: =100*(SUMIF('GEM data - Upside'!$C:$C,'Chart Data'!$Q17,'GEM data - Upside'!$Q:$Q)/SUMIF('GEM data - Upside'!$C:$C,'Chart Data'!$Q17,'GEM data - Upside'!$S:$S)) -> -0.46906095 | T17: =100*(SUMIF('GEM data - Zero_net'!$C:$C,'Chart Data'!$Q17,'GEM data - Zero_net'!$Q:$Q)/SUMIF('GEM data - Zero_net'!$C:$C,'Chart Data'!$Q17,'GEM data - Zero_net'!$S:$S)) -> -0.87726379 | V17: 2034 | W17: =100*(SUMIF('GEM data - Baseline'!$D:$D,'Chart Data'!$Q17,'GEM data - Baseline'!$R:$R)/SUMIF('GEM data - Baseline'!$C:$C,'Chart Data'!$Q17,'GEM data - Baseline'!$S:$S)) -> 84.128657 | X17: =100*(SUMIF('GEM data - Upside'!$D:$D,'Chart Data'!$Q17,'GEM data - Upside'!$R:$R)/SUMIF('GEM data - Upside'!$C:$C,'Chart Data'!$Q17,'GEM data - Upside'!$S:$S)) -> 82.86911 | Y17: =100*(SUMIF('GEM data - Zero_net'!$D:$D,'Chart Data'!$Q17,'GEM data - Zero_net'!$R:$R)/SUMIF('GEM data - Zero_net'!$C:$C,'Chart Data'!$Q17,'GEM data - Zero_net'!$S:$S)) -> 86.774703 | AA17: 15 | AB17: =VLOOKUP($AA17,$AE$3:$AG$21,2,FALSE) -> Water | AC17: =VLOOKUP($AA17,$AE$3:$AG$21,3,FALSE) -> 10.725356 | AE17: =RANK(AG17,$AG$3:$AG$21) -> 19 | AF17: Public administration | AG17: =100*(AL17/AJ17) -> 6.4230613 | AI17: PUB | AJ17: {=INDEX('HMRC emp by ind and nat'!$A$149:$C$233,MATCH(1,('HMRC emp by ind and nat'!$A$145:$CG$145=AJ$1)*('HMRC emp by ind and nat'!$A$146:$CG$146=$AI17),0),3)} -> 1642000 | AK17: {=INDEX('HMRC emp by ind and nat'!$A$149:$C$233,MATCH(1,('HMRC emp by ind and nat'!$A$145:$CG$145=AK$1)*('HMRC emp by ind and nat'!$A$146:$CG$146=$AI17),0),3)} -> 1536533.3 | AL17: =AJ17-AK17 -> 105466.67 | AP17: 2014 | AQ17: =AVERAGEIF('GEM data - Baseline'!$B:$B,'Chart Data'!$AP17,'GEM data - Baseline'!$AE:$AE) -> 28.314323 | AR17: =AVERAGEIF('GEM data - Upside'!$B:$B,'Chart Data'!$AP17,'GEM data - Upside'!$AE:$AE) -> 28.314323 | AS17: =AVERAGEIF('GEM data - Zero_net'!$B:$B,'Chart Data'!$AP17,'GEM data - Zero_net'!$AE:$AE) -> 28.314323 | AU17: 2014 | AV17: =AVERAGEIF('GEM data - Baseline'!$B:$B,'Chart Data'!$AP17,'GEM data - Baseline'!AE:AE) -> 28.314323 | AW17: =AVERAGEIF('GEM data - Baseline'!$B:$B,'Chart Data'!$AP17,'GEM data - Baseline'!AF:AF) -> 18.443395 | AX17: =AVERAGEIF('GEM data - Baseline'!$B:$B,'Chart Data'!$AP17,'GEM data - Baseline'!AG:AG) -> 43.134605 | AY17: =AVERAGEIF('GEM data - Baseline'!$B:$B,'Chart Data'!$AP17,'GEM data - Baseline'!AH:AH) -> 31.69355 | AZ17: =AVERAGEIF('GEM data - Baseline'!$B:$B,'Chart Data'!$AP17,'GEM data - Baseline'!AI:AI) -> 28.519118 | BA17: =AVERAGEIF('GEM data - Baseline'!$B:$B,'Chart Data'!$AP17,'GEM data - Baseline'!AJ:AJ) -> 34.046193 | BB17: =AVERAGEIF('GEM data - Baseline'!$B:$B,'Chart Data'!$AP17,'GEM data - Baseline'!AK:AK) -> 19.221222 | BF17: =100*(('GEM data - Baseline'!$F181/'GEM data - Baseline'!$F177)-1) -> 0.11789895 | BG17: =100*(('GEM data - Upside'!$F181/'GEM data - Upside'!$F177)-1) -> 0.11789895 | BH17: =100*(('GEM data - Zero_net'!$F181/'GEM data - Zero_net'!$F177)-1) -> 0.11789895 | BK17: =100*(('GEM data - Baseline'!$U181/'GEM data - Baseline'!$U177)-1) -> 1.3678161 | BL17: =100*(('GEM data - Upside'!$U181/'GEM data - Upside'!$U177)-1) -> 1.3678161 | BM17: =100*(('GEM data - Zero_net'!$U181/'GEM data - Zero_net'!$U177)-1) -> 1.3678161 | BP17: ='GEM data - Baseline'!$O181 -> 4.1 | BQ17: ='GEM data - Upside'!$O181 -> 4.1 | BR17: ='GEM data - Zero_net'!$O181 -> 4.1 | BU17: =100*(('GEM data - Baseline'!$L181/'GEM data - Baseline'!$L177)-1) -> 1.3031196 | BV17: =100*(('GEM data - Upside'!$L181/'GEM data - Upside'!$L177)-1) -> 1.3031196 | BW17: =100*(('GEM data - Zero_net'!$L181/'GEM data - Zero_net'!$L177)-1) -> 1.3031196 | BZ17: ='GEM data - Baseline'!$T181 -> 1.166248 | CA17: ='GEM data - Upside'!$T181 -> 1.166248 | CB17: ='GEM data - Zero_net'!$T181 -> 1.166248 | CE17: ='GEM data - Baseline'!$J181 -> 5.161539 | CF17: ='GEM data - Upside'!$J181 -> 5.161539 | CG17: ='GEM data - Zero_net'!$J181 -> 5.161539 | CJ17: =100*(('GEM data - Baseline'!$I181/'GEM data - Baseline'!$I177)-1) -> 6.7136185 | CK17: =100*(('GEM data - Upside'!$I181/'GEM data - Upside'!$I177)-1) -> 6.7136185 | CL17: =100*(('GEM data - Zero_net'!$I181/'GEM data - Zero_net'!$I177)-1) -> 6.7136185 | CO17: =100*('GEM data - Baseline'!$AB181/'GEM data - Baseline'!$AD181) -> 432.59708 | CP17: =100*('GEM data - Upside'!$AB181/'GEM data - Upside'!$AD181) -> 432.59708 | CQ17: =100*('GEM data - Zero_net'!$AB181/'GEM data - Zero_net'!$AD181) -> 432.59708 | CT17: =100*('GEM data - Baseline'!$AC181/'GEM data - Baseline'!$AD181) -> 389.50298 | CU17: =100*('GEM data - Upside'!$AC181/'GEM data - Upside'!$AD181) -> 389.50298 | CV17: =100*('GEM data - Zero_net'!$AC181/'GEM data - Zero_net'!$AD181) -> 389.50298 | CY17: =100*('GEM data - Baseline'!$F181/'GEM data - Baseline'!$AD181) -> 1001.0063 | CZ17: =100*('GEM data - Upside'!$F181/'GEM data - Upside'!$AD181) -> 1001.0063 | DA17: =100*('GEM data - Zero_net'!$F181/'GEM data - Zero_net'!$AD181) -> 1001.0063 | DC17: 1994 | DD17: =SUMIF('GEM data - Baseline'!$B:$B,'Chart Data'!$DC17,'GEM data - Baseline'!$U:$U) -> 1604511.8 | DE17: =AVERAGEIF('GEM data - Baseline'!$B:$B,'Chart Data'!$DC17,'GEM data - Baseline'!$V:$V) -> 25629.675 | DF17: =AVERAGEIF('GEM data - Baseline'!$B:$B,'Chart Data'!$DC17,'GEM data - Baseline'!$W:$W) -> 33.225 | DG17: =AVERAGEIF('GEM data - Baseline'!$B:$B,'Chart Data'!$DC17,'GEM data - Baseline'!$X:$X) -> 360583.75 | DH17: =AVERAGEIF('GEM data - Baseline'!$B:$B,'Chart Data'!$DC17,'GEM data - Baseline'!$Y:$Y) -> 37433.702 | DI17: =AVERAGEIF('GEM data - Baseline'!$B:$B,'Chart Data'!$DC17,'GEM data - Baseline'!$Z:$Z) -> 1658319.8 | DJ17: =AVERAGEIF('GEM data - Baseline'!$B:$B,'Chart Data'!$DC17,'GEM data - Baseline'!$AA:$AA) -> -1.6637158 | DL17: =DE17*DF17 -> 851545.95 | DM17: =DG17/DH17 -> 9.6325965 | DN17: =DI17 -> 1658319.8 | DO17: =DJ17 -> -1.6637158 | DP17: =DD17 -> 1604511.8 | DQ17: =SUMIF('GEM data - Baseline'!$B:$B,'Chart Data'!$DC17,'GEM data - Baseline'!$F:$F) -> 1584459 | DS17: =100*((DP17/DP16)-1) -> 2.6171629 | DT17: =100*((DQ17/DQ16)-1) -> 3.4186812 | DV17: 1994 | DW17: =SUMIF('GEM data - Upside'!$B:$B,'Chart Data'!$DC17,'GEM data - Upside'!$U:$U) -> 1604511.8 | DX17: =AVERAGEIF('GEM data - Upside'!$B:$B,'Chart Data'!$DC17,'GEM data - Upside'!$V:$V) -> 25629.675 | DY17: =AVERAGEIF('GEM data - Upside'!$B:$B,'Chart Data'!$DC17,'GEM data - Upside'!$W:$W) -> 33.225 | DZ17: =AVERAGEIF('GEM data - Upside'!$B:$B,'Chart Data'!$DC17,'GEM data - Upside'!$X:$X) -> 360583.75 | EA17: =AVERAGEIF('GEM data - Upside'!$B:$B,'Chart Data'!$DC17,'GEM data - Upside'!$Y:$Y) -> 37433.702 | EB17: =AVERAGEIF('GEM data - Upside'!$B:$B,'Chart Data'!$DC17,'GEM data - Upside'!$Z:$Z) -> 1658319.8 | EC17: =AVERAGEIF('GEM data - Upside'!$B:$B,'Chart Data'!$DC17,'GEM data - Upside'!$AA:$AA) -> -1.6637158 | EE17: =DX17*DY17 -> 851545.95 | EF17: =DZ17/EA17 -> 9.6325965 | EG17: =EB17 -> 1658319.8 | EH17: =EC17 -> -1.6637158 | EI17: =DW17 -> 1604511.8 | EJ17: =SUMIF('GEM data - Upside'!$B:$B,'Chart Data'!$DC17,'GEM data - Upside'!$F:$F) -> 1584459 | EL17: =100*((EI17/EI16)-1) -> 2.6171629 | EM17: =100*((EJ17/EJ16)-1) -> 3.4186812 | EO17: 1994 | EP17: =SUMIF('GEM data - Zero_net'!$B:$B,'Chart Data'!$DC17,'GEM data - Zero_net'!$U:$U) -> 1604511.8 | EQ17: =AVERAGEIF('GEM data - Zero_net'!$B:$B,'Chart Data'!$DC17,'GEM data - Zero_net'!$V:$V) -> 25629.675 | ER17: =AVERAGEIF('GEM data - Zero_net'!$B:$B,'Chart Data'!$DC17,'GEM data - Zero_net'!$W:$W) -> 33.225 | ES17: =AVERAGEIF('GEM data - Zero_net'!$B:$B,'Chart Data'!$DC17,'GEM data - Zero_net'!$X:$X) -> 360583.75 | ET17: =AVERAGEIF('GEM data - Zero_net'!$B:$B,'Chart Data'!$DC17,'GEM data - Zero_net'!$Y:$Y) -> 37433.702 | EU17: =AVERAGEIF('GEM data - Zero_net'!$B:$B,'Chart Data'!$DC17,'GEM data - Zero_net'!$Z:$Z) -> 1658319.8 | EV17: =AVERAGEIF('GEM data - Zero_net'!$B:$B,'Chart Data'!$DC17,'GEM data - Zero_net'!$AA:$AA) -> -1.6637158 | EX17: =EQ17*ER17 -> 851545.95 | EY17: =ES17/ET17 -> 9.6325965 | EZ17: =EU17 -> 1658319.8 | FA17: =EV17 -> -1.6637158 | FB17: =EP17 -> 1604511.8 | FC17: =SUMIF('GEM data - Zero_net'!$B:$B,'Chart Data'!$DC17,'GEM data - Zero_net'!$F:$F) -> 1584459 | FE17: =100*((FB17/FB16)-1) -> 2.6171629 | FF17: =100*((FC17/FC16)-1) -> 3.4186812
B18: ='GEM data - Baseline'!$F182 -> 685628 | C18: ='GEM data - Upside'!$F182 -> 685628 | D18: ='GEM data - Zero_net'!$F182 -> 685628 | F18: 2015 | G18: ='[2]Chart Data'!M19 -> 296 | M18: =100*(('GEM data - Baseline'!$P182/'GEM data - Baseline'!$P178)-1) -> 1.2400045 | N18: =100*(('GEM data - Upside'!$P182/'GEM data - Upside'!$P178)-1) -> 1.2400045 | O18: =100*(('GEM data - Zero_net'!$P182/'GEM data - Zero_net'!$P178)-1) -> 1.2400045 | Q18: 2035 | R18: =100*(SUMIF('GEM data - Baseline'!$C:$C,'Chart Data'!$Q18,'GEM data - Baseline'!$Q:$Q)/SUMIF('GEM data - Baseline'!$C:$C,'Chart Data'!$Q18,'GEM data - Baseline'!$S:$S)) -> -0.77550552 | S18: =100*(SUMIF('GEM data - Upside'!$C:$C,'Chart Data'!$Q18,'GEM data - Upside'!$Q:$Q)/SUMIF('GEM data - Upside'!$C:$C,'Chart Data'!$Q18,'GEM data - Upside'!$S:$S)) -> -0.62393741 | T18: =100*(SUMIF('GEM data - Zero_net'!$C:$C,'Chart Data'!$Q18,'GEM data - Zero_net'!$Q:$Q)/SUMIF('GEM data - Zero_net'!$C:$C,'Chart Data'!$Q18,'GEM data - Zero_net'!$S:$S)) -> -1.149483 | V18: 2035 | W18: =100*(SUMIF('GEM data - Baseline'!$D:$D,'Chart Data'!$Q18,'GEM data - Baseline'!$R:$R)/SUMIF('GEM data - Baseline'!$C:$C,'Chart Data'!$Q18,'GEM data - Baseline'!$S:$S)) -> 84.373244 | X18: =100*(SUMIF('GEM data - Upside'!$D:$D,'Chart Data'!$Q18,'GEM data - Upside'!$R:$R)/SUMIF('GEM data - Upside'!$C:$C,'Chart Data'!$Q18,'GEM data - Upside'!$S:$S)) -> 82.924875 | Y18: =100*(SUMIF('GEM data - Zero_net'!$D:$D,'Chart Data'!$Q18,'GEM data - Zero_net'!$R:$R)/SUMIF('GEM data - Zero_net'!$C:$C,'Chart Data'!$Q18,'GEM data - Zero_net'!$S:$S)) -> 87.627145 | AA18: 16 | AB18: =VLOOKUP($AA18,$AE$3:$AG$21,2,FALSE) -> Utilities | AC18: =VLOOKUP($AA18,$AE$3:$AG$21,3,FALSE) -> 10.590137 | AE18: =RANK(AG18,$AG$3:$AG$21) -> 13 | AF18: Education | AG18: =100*(AL18/AJ18) -> 12.084882 | AI18: EDUC | AJ18: {=INDEX('HMRC emp by ind and nat'!$A$149:$C$233,MATCH(1,('HMRC emp by ind and nat'!$A$145:$CG$145=AJ$1)*('HMRC emp by ind and nat'!$A$146:$CG$146=$AI18),0),3)} -> 3336400 | AK18: {=INDEX('HMRC emp by ind and nat'!$A$149:$C$233,MATCH(1,('HMRC emp by ind and nat'!$A$145:$CG$145=AK$1)*('HMRC emp by ind and nat'!$A$146:$CG$146=$AI18),0),3)} -> 2933200 | AL18: =AJ18-AK18 -> 403200 | AP18: 2015 | AQ18: =AVERAGEIF('GEM data - Baseline'!$B:$B,'Chart Data'!$AP18,'GEM data - Baseline'!$AE:$AE) -> 28.513655 | AR18: =AVERAGEIF('GEM data - Upside'!$B:$B,'Chart Data'!$AP18,'GEM data - Upside'!$AE:$AE) -> 28.513655 | AS18: =AVERAGEIF('GEM data - Zero_net'!$B:$B,'Chart Data'!$AP18,'GEM data - Zero_net'!$AE:$AE) -> 28.513655 | AU18: 2015 | AV18: =AVERAGEIF('GEM data - Baseline'!$B:$B,'Chart Data'!$AP18,'GEM data - Baseline'!AE:AE) -> 28.513655 | AW18: =AVERAGEIF('GEM data - Baseline'!$B:$B,'Chart Data'!$AP18,'GEM data - Baseline'!AF:AF) -> 18.803197 | AX18: =AVERAGEIF('GEM data - Baseline'!$B:$B,'Chart Data'!$AP18,'GEM data - Baseline'!AG:AG) -> 44.69951 | AY18: =AVERAGEIF('GEM data - Baseline'!$B:$B,'Chart Data'!$AP18,'GEM data - Baseline'!AH:AH) -> 31.802692 | AZ18: =AVERAGEIF('GEM data - Baseline'!$B:$B,'Chart Data'!$AP18,'GEM data - Baseline'!AI:AI) -> 29.293598 | BA18: =AVERAGEIF('GEM data - Baseline'!$B:$B,'Chart Data'!$AP18,'GEM data - Baseline'!AJ:AJ) -> 34.401403 | BB18: =AVERAGEIF('GEM data - Baseline'!$B:$B,'Chart Data'!$AP18,'GEM data - Baseline'!AK:AK) -> 19.684775 | BF18: =100*(('GEM data - Baseline'!$F182/'GEM data - Baseline'!$F178)-1) -> -0.46296767 | BG18: =100*(('GEM data - Upside'!$F182/'GEM data - Upside'!$F178)-1) -> -0.46296767 | BH18: =100*(('GEM data - Zero_net'!$F182/'GEM data - Zero_net'!$F178)-1) -> -0.46296767 | BK18: =100*(('GEM data - Baseline'!$U182/'GEM data - Baseline'!$U178)-1) -> 1.381024 | BL18: =100*(('GEM data - Upside'!$U182/'GEM data - Upside'!$U178)-1) -> 1.381024 | BM18: =100*(('GEM data - Zero_net'!$U182/'GEM data - Zero_net'!$U178)-1) -> 1.381024 | BP18: ='GEM data - Baseline'!$O182 -> 3.9 | BQ18: ='GEM data - Upside'!$O182 -> 3.9 | BR18: ='GEM data - Zero_net'!$O182 -> 3.9 | BU18: =100*(('GEM data - Baseline'!$L182/'GEM data - Baseline'!$L178)-1) -> 0.79417804 | BV18: =100*(('GEM data - Upside'!$L182/'GEM data - Upside'!$L178)-1) -> 0.79417804 | BW18: =100*(('GEM data - Zero_net'!$L182/'GEM data - Zero_net'!$L178)-1) -> 0.79417804 | BZ18: ='GEM data - Baseline'!$T182 -> 0.3142357 | CA18: ='GEM data - Upside'!$T182 -> 0.3142357 | CB18: ='GEM data - Zero_net'!$T182 -> 0.3142357 | CE18: ='GEM data - Baseline'!$J182 -> 5.25 | CF18: ='GEM data - Upside'!$J182 -> 5.25 | CG18: ='GEM data - Zero_net'!$J182 -> 5.25 | CJ18: =100*(('GEM data - Baseline'!$I182/'GEM data - Baseline'!$I178)-1) -> 4.1568272 | CK18: =100*(('GEM data - Upside'!$I182/'GEM data - Upside'!$I178)-1) -> 4.1568272 | CL18: =100*(('GEM data - Zero_net'!$I182/'GEM data - Zero_net'!$I178)-1) -> 4.1568272 | CO18: =100*('GEM data - Baseline'!$AB182/'GEM data - Baseline'!$AD182) -> 441.29979 | CP18: =100*('GEM data - Upside'!$AB182/'GEM data - Upside'!$AD182) -> 441.29979 | CQ18: =100*('GEM data - Zero_net'!$AB182/'GEM data - Zero_net'!$AD182) -> 441.29979 | CT18: =100*('GEM data - Baseline'!$AC182/'GEM data - Baseline'!$AD182) -> 383.85278 | CU18: =100*('GEM data - Upside'!$AC182/'GEM data - Upside'!$AD182) -> 383.85278 | CV18: =100*('GEM data - Zero_net'!$AC182/'GEM data - Zero_net'!$AD182) -> 383.85278 | CY18: =100*('GEM data - Baseline'!$F182/'GEM data - Baseline'!$AD182) -> 995.0554 | CZ18: =100*('GEM data - Upside'!$F182/'GEM data - Upside'!$AD182) -> 995.0554 | DA18: =100*('GEM data - Zero_net'!$F182/'GEM data - Zero_net'!$AD182) -> 995.0554 | DC18: 1995 | DD18: =SUMIF('GEM data - Baseline'!$B:$B,'Chart Data'!$DC18,'GEM data - Baseline'!$U:$U) -> 1646030.5 | DE18: =AVERAGEIF('GEM data - Baseline'!$B:$B,'Chart Data'!$DC18,'GEM data - Baseline'!$V:$V) -> 25810.103 | DF18: =AVERAGEIF('GEM data - Baseline'!$B:$B,'Chart Data'!$DC18,'GEM data - Baseline'!$W:$W) -> 33.25 | DG18: =AVERAGEIF('GEM data - Baseline'!$B:$B,'Chart Data'!$DC18,'GEM data - Baseline'!$X:$X) -> 363847.53 | DH18: =AVERAGEIF('GEM data - Baseline'!$B:$B,'Chart Data'!$DC18,'GEM data - Baseline'!$Y:$Y) -> 37552.995 | DI18: =AVERAGEIF('GEM data - Baseline'!$B:$B,'Chart Data'!$DC18,'GEM data - Baseline'!$Z:$Z) -> 1697417 | DJ18: =AVERAGEIF('GEM data - Baseline'!$B:$B,'Chart Data'!$DC18,'GEM data - Baseline'!$AA:$AA) -> -1.652896 | DL18: =DE18*DF18 -> 858185.91 | DM18: =DG18/DH18 -> 9.6889083 | DN18: =DI18 -> 1697417 | DO18: =DJ18 -> -1.652896 | DP18: =DD18 -> 1646030.5 | DQ18: =SUMIF('GEM data - Baseline'!$B:$B,'Chart Data'!$DC18,'GEM data - Baseline'!$F:$F) -> 1622576 | DS18: =100*((DP18/DP17)-1) -> 2.587622 | DT18: =100*((DQ18/DQ17)-1) -> 2.4056792 | DV18: 1995 | DW18: =SUMIF('GEM data - Upside'!$B:$B,'Chart Data'!$DC18,'GEM data - Upside'!$U:$U) -> 1646030.5 | DX18: =AVERAGEIF('GEM data - Upside'!$B:$B,'Chart Data'!$DC18,'GEM data - Upside'!$V:$V) -> 25810.103 | DY18: =AVERAGEIF('GEM data - Upside'!$B:$B,'Chart Data'!$DC18,'GEM data - Upside'!$W:$W) -> 33.25 | DZ18: =AVERAGEIF('GEM data - Upside'!$B:$B,'Chart Data'!$DC18,'GEM data - Upside'!$X:$X) -> 363847.53 | EA18: =AVERAGEIF('GEM data - Upside'!$B:$B,'Chart Data'!$DC18,'GEM data - Upside'!$Y:$Y) -> 37552.995 | EB18: =AVERAGEIF('GEM data - Upside'!$B:$B,'Chart Data'!$DC18,'GEM data - Upside'!$Z:$Z) -> 1697417 | EC18: =AVERAGEIF('GEM data - Upside'!$B:$B,'Chart Data'!$DC18,'GEM data - Upside'!$AA:$AA) -> -1.652896 | EE18: =DX18*DY18 -> 858185.91 | EF18: =DZ18/EA18 -> 9.6889083 | EG18: =EB18 -> 1697417 | EH18: =EC18 -> -1.652896 | EI18: =DW18 -> 1646030.5 | EJ18: =SUMIF('GEM data - Upside'!$B:$B,'Chart Data'!$DC18,'GEM data - Upside'!$F:$F) -> 1622576 | EL18: =100*((EI18/EI17)-1) -> 2.587622 | EM18: =100*((EJ18/EJ17)-1) -> 2.4056792 | EO18: 1995 | EP18: =SUMIF('GEM data - Zero_net'!$B:$B,'Chart Data'!$DC18,'GEM data - Zero_net'!$U:$U) -> 1646030.5 | EQ18: =AVERAGEIF('GEM data - Zero_net'!$B:$B,'Chart Data'!$DC18,'GEM data - Zero_net'!$V:$V) -> 25810.103 | ER18: =AVERAGEIF('GEM data - Zero_net'!$B:$B,'Chart Data'!$DC18,'GEM data - Zero_net'!$W:$W) -> 33.25 | ES18: =AVERAGEIF('GEM data - Zero_net'!$B:$B,'Chart Data'!$DC18,'GEM data - Zero_net'!$X:$X) -> 363847.53 | ET18: =AVERAGEIF('GEM data - Zero_net'!$B:$B,'Chart Data'!$DC18,'GEM data - Zero_net'!$Y:$Y) -> 37552.995 | EU18: =AVERAGEIF('GEM data - Zero_net'!$B:$B,'Chart Data'!$DC18,'GEM data - Zero_net'!$Z:$Z) -> 1697417 | EV18: =AVERAGEIF('GEM data - Zero_net'!$B:$B,'Chart Data'!$DC18,'GEM data - Zero_net'!$AA:$AA) -> -1.652896 | EX18: =EQ18*ER18 -> 858185.91 | EY18: =ES18/ET18 -> 9.6889083 | EZ18: =EU18 -> 1697417 | FA18: =EV18 -> -1.652896 | FB18: =EP18 -> 1646030.5 | FC18: =SUMIF('GEM data - Zero_net'!$B:$B,'Chart Data'!$DC18,'GEM data - Zero_net'!$F:$F) -> 1622576 | FE18: =100*((FB18/FB17)-1) -> 2.587622 | FF18: =100*((FC18/FC17)-1) -> 2.4056792
A19: 2024 | B19: ='GEM data - Baseline'!$F183 -> 690904 | C19: ='GEM data - Upside'!$F183 -> 690904 | D19: ='GEM data - Zero_net'!$F183 -> 690904 | F19: 2016 | G19: ='[2]Chart Data'!M20 -> 321 | L19: 2024 | M19: =100*(('GEM data - Baseline'!$P183/'GEM data - Baseline'!$P179)-1) -> 1.1694167 | N19: =100*(('GEM data - Upside'!$P183/'GEM data - Upside'!$P179)-1) -> 1.1694167 | O19: =100*(('GEM data - Zero_net'!$P183/'GEM data - Zero_net'!$P179)-1) -> 1.1694167 | Q19: 2036 | R19: =100*(SUMIF('GEM data - Baseline'!$C:$C,'Chart Data'!$Q19,'GEM data - Baseline'!$Q:$Q)/SUMIF('GEM data - Baseline'!$C:$C,'Chart Data'!$Q19,'GEM data - Baseline'!$S:$S)) -> -0.91839571 | S19: =100*(SUMIF('GEM data - Upside'!$C:$C,'Chart Data'!$Q19,'GEM data - Upside'!$Q:$Q)/SUMIF('GEM data - Upside'!$C:$C,'Chart Data'!$Q19,'GEM data - Upside'!$S:$S)) -> -0.75859127 | T19: =100*(SUMIF('GEM data - Zero_net'!$C:$C,'Chart Data'!$Q19,'GEM data - Zero_net'!$Q:$Q)/SUMIF('GEM data - Zero_net'!$C:$C,'Chart Data'!$Q19,'GEM data - Zero_net'!$S:$S)) -> -1.4037035 | V19: 2036 | W19: =100*(SUMIF('GEM data - Baseline'!$D:$D,'Chart Data'!$Q19,'GEM data - Baseline'!$R:$R)/SUMIF('GEM data - Baseline'!$C:$C,'Chart Data'!$Q19,'GEM data - Baseline'!$S:$S)) -> 84.763742 | X19: =100*(SUMIF('GEM data - Upside'!$D:$D,'Chart Data'!$Q19,'GEM data - Upside'!$R:$R)/SUMIF('GEM data - Upside'!$C:$C,'Chart Data'!$Q19,'GEM data - Upside'!$S:$S)) -> 83.154679 | Y19: =100*(SUMIF('GEM data - Zero_net'!$D:$D,'Chart Data'!$Q19,'GEM data - Zero_net'!$R:$R)/SUMIF('GEM data - Zero_net'!$C:$C,'Chart Data'!$Q19,'GEM data - Zero_net'!$S:$S)) -> 88.758678 | AA19: 17 | AB19: =VLOOKUP($AA19,$AE$3:$AG$21,2,FALSE) -> Extraction | AC19: =VLOOKUP($AA19,$AE$3:$AG$21,3,FALSE) -> 9.6848578 | AE19: =RANK(AG19,$AG$3:$AG$21) -> 3 | AF19: Health | AG19: =100*(AL19/AJ19) -> 26.033779 | AI19: HEAL | AJ19: {=INDEX('HMRC emp by ind and nat'!$A$149:$C$233,MATCH(1,('HMRC emp by ind and nat'!$A$145:$CG$145=AJ$1)*('HMRC emp by ind and nat'!$A$146:$CG$146=$AI19),0),3)} -> 4886600 | AK19: {=INDEX('HMRC emp by ind and nat'!$A$149:$C$233,MATCH(1,('HMRC emp by ind and nat'!$A$145:$CG$145=AK$1)*('HMRC emp by ind and nat'!$A$146:$CG$146=$AI19),0),3)} -> 3614433.3 | AL19: =AJ19-AK19 -> 1272166.7 | AP19: 2016 | AQ19: =AVERAGEIF('GEM data - Baseline'!$B:$B,'Chart Data'!$AP19,'GEM data - Baseline'!$AE:$AE) -> 28.66643 | AR19: =AVERAGEIF('GEM data - Upside'!$B:$B,'Chart Data'!$AP19,'GEM data - Upside'!$AE:$AE) -> 28.66643 | AS19: =AVERAGEIF('GEM data - Zero_net'!$B:$B,'Chart Data'!$AP19,'GEM data - Zero_net'!$AE:$AE) -> 28.66643 | AU19: 2016 | AV19: =AVERAGEIF('GEM data - Baseline'!$B:$B,'Chart Data'!$AP19,'GEM data - Baseline'!AE:AE) -> 28.66643 | AW19: =AVERAGEIF('GEM data - Baseline'!$B:$B,'Chart Data'!$AP19,'GEM data - Baseline'!AF:AF) -> 19.176578 | AX19: =AVERAGEIF('GEM data - Baseline'!$B:$B,'Chart Data'!$AP19,'GEM data - Baseline'!AG:AG) -> 46.03462 | AY19: =AVERAGEIF('GEM data - Baseline'!$B:$B,'Chart Data'!$AP19,'GEM data - Baseline'!AH:AH) -> 32.022122 | AZ19: =AVERAGEIF('GEM data - Baseline'!$B:$B,'Chart Data'!$AP19,'GEM data - Baseline'!AI:AI) -> 30.04563 | BA19: =AVERAGEIF('GEM data - Baseline'!$B:$B,'Chart Data'!$AP19,'GEM data - Baseline'!AJ:AJ) -> 34.68176 | BB19: =AVERAGEIF('GEM data - Baseline'!$B:$B,'Chart Data'!$AP19,'GEM data - Baseline'!AK:AK) -> 20.146113 | BE19: 2024 | BF19: =100*(('GEM data - Baseline'!$F183/'GEM data - Baseline'!$F179)-1) -> 0.24637046 | BG19: =100*(('GEM data - Upside'!$F183/'GEM data - Upside'!$F179)-1) -> 0.24637046 | BH19: =100*(('GEM data - Zero_net'!$F183/'GEM data - Zero_net'!$F179)-1) -> 0.24637046 | BJ19: 2024 | BK19: =100*(('GEM data - Baseline'!$U183/'GEM data - Baseline'!$U179)-1) -> 1.7968855 | BL19: =100*(('GEM data - Upside'!$U183/'GEM data - Upside'!$U179)-1) -> 1.7968855 | BM19: =100*(('GEM data - Zero_net'!$U183/'GEM data - Zero_net'!$U179)-1) -> 1.7968855 | BO19: 2024 | BP19: ='GEM data - Baseline'!$O183 -> 4.3 | BQ19: ='GEM data - Upside'!$O183 -> 4.3 | BR19: ='GEM data - Zero_net'!$O183 -> 4.3 | BT19: 2024 | BU19: =100*(('GEM data - Baseline'!$L183/'GEM data - Baseline'!$L179)-1) -> 0.030007502 | BV19: =100*(('GEM data - Upside'!$L183/'GEM data - Upside'!$L179)-1) -> 0.030007502 | BW19: =100*(('GEM data - Zero_net'!$L183/'GEM data - Zero_net'!$L179)-1) -> 0.030007502 | BY19: 2024 | BZ19: ='GEM data - Baseline'!$T183 -> -0.004005432 | CA19: ='GEM data - Upside'!$T183 -> -0.004005432 | CB19: ='GEM data - Zero_net'!$T183 -> -0.004005432 | CD19: 2024 | CE19: ='GEM data - Baseline'!$J183 -> 5.25 | CF19: ='GEM data - Upside'!$J183 -> 5.25 | CG19: ='GEM data - Zero_net'!$J183 -> 5.25 | CI19: 2024 | CJ19: =100*(('GEM data - Baseline'!$I183/'GEM data - Baseline'!$I179)-1) -> 3.5491137 | CK19: =100*(('GEM data - Upside'!$I183/'GEM data - Upside'!$I179)-1) -> 3.5491137 | CL19: =100*(('GEM data - Zero_net'!$I183/'GEM data - Zero_net'!$I179)-1) -> 3.5491137 | CN19: 2024 | CO19: =100*('GEM data - Baseline'!$AB183/'GEM data - Baseline'!$AD183) -> 464.54125 | CP19: =100*('GEM data - Upside'!$AB183/'GEM data - Upside'!$AD183) -> 464.54125 | CQ19: =100*('GEM data - Zero_net'!$AB183/'GEM data - Zero_net'!$AD183) -> 464.54125 | CS19: 2024 | CT19: =100*('GEM data - Baseline'!$AC183/'GEM data - Baseline'!$AD183) -> 448.15012 | CU19: =100*('GEM data - Upside'!$AC183/'GEM data - Upside'!$AD183) -> 448.15012 | CV19: =100*('GEM data - Zero_net'!$AC183/'GEM data - Zero_net'!$AD183) -> 448.15012 | CX19: 2024 | CY19: =100*('GEM data - Baseline'!$F183/'GEM data - Baseline'!$AD183) -> 999.97322 | CZ19: =100*('GEM data - Upside'!$F183/'GEM data - Upside'!$AD183) -> 999.97322 | DA19: =100*('GEM data - Zero_net'!$F183/'GEM data - Zero_net'!$AD183) -> 999.97322 | DC19: 1996 | DD19: =SUMIF('GEM data - Baseline'!$B:$B,'Chart Data'!$DC19,'GEM data - Baseline'!$U:$U) -> 1690511.7 | DE19: =AVERAGEIF('GEM data - Baseline'!$B:$B,'Chart Data'!$DC19,'GEM data - Baseline'!$V:$V) -> 26087.385 | DF19: =AVERAGEIF('GEM data - Baseline'!$B:$B,'Chart Data'!$DC19,'GEM data - Baseline'!$W:$W) -> 33.225 | DG19: =AVERAGEIF('GEM data - Baseline'!$B:$B,'Chart Data'!$DC19,'GEM data - Baseline'!$X:$X) -> 366199.2 | DH19: =AVERAGEIF('GEM data - Baseline'!$B:$B,'Chart Data'!$DC19,'GEM data - Baseline'!$Y:$Y) -> 37673.28 | DI19: =AVERAGEIF('GEM data - Baseline'!$B:$B,'Chart Data'!$DC19,'GEM data - Baseline'!$Z:$Z) -> 1739056.8 | DJ19: =AVERAGEIF('GEM data - Baseline'!$B:$B,'Chart Data'!$DC19,'GEM data - Baseline'!$AA:$AA) -> -1.642147 | DL19: =DE19*DF19 -> 866753.37 | DM19: =DG19/DH19 -> 9.720396 | DN19: =DI19 -> 1739056.8 | DO19: =DJ19 -> -1.642147 | DP19: =DD19 -> 1690511.7 | DQ19: =SUMIF('GEM data - Baseline'!$B:$B,'Chart Data'!$DC19,'GEM data - Baseline'!$F:$F) -> 1665005 | DS19: =100*((DP19/DP18)-1) -> 2.7023315 | DT19: =100*((DQ19/DQ18)-1) -> 2.614916 | DV19: 1996 | DW19: =SUMIF('GEM data - Upside'!$B:$B,'Chart Data'!$DC19,'GEM data - Upside'!$U:$U) -> 1690511.7 | DX19: =AVERAGEIF('GEM data - Upside'!$B:$B,'Chart Data'!$DC19,'GEM data - Upside'!$V:$V) -> 26087.385 | DY19: =AVERAGEIF('GEM data - Upside'!$B:$B,'Chart Data'!$DC19,'GEM data - Upside'!$W:$W) -> 33.225 | DZ19: =AVERAGEIF('GEM data - Upside'!$B:$B,'Chart Data'!$DC19,'GEM data - Upside'!$X:$X) -> 366199.2 | EA19: =AVERAGEIF('GEM data - Upside'!$B:$B,'Chart Data'!$DC19,'GEM data - Upside'!$Y:$Y) -> 37673.28 | EB19: =AVERAGEIF('GEM data - Upside'!$B:$B,'Chart Data'!$DC19,'GEM data - Upside'!$Z:$Z) -> 1739056.8 | EC19: =AVERAGEIF('GEM data - Upside'!$B:$B,'Chart Data'!$DC19,'GEM data - Upside'!$AA:$AA) -> -1.642147 | EE19: =DX19*DY19 -> 866753.37 | EF19: =DZ19/EA19 -> 9.720396 | EG19: =EB19 -> 1739056.8 | EH19: =EC19 -> -1.642147 | EI19: =DW19 -> 1690511.7 | EJ19: =SUMIF('GEM data - Upside'!$B:$B,'Chart Data'!$DC19,'GEM data - Upside'!$F:$F) -> 1665005 | EL19: =100*((EI19/EI18)-1) -> 2.7023315 | EM19: =100*((EJ19/EJ18)-1) -> 2.614916 | EO19: 1996 | EP19: =SUMIF('GEM data - Zero_net'!$B:$B,'Chart Data'!$DC19,'GEM data - Zero_net'!$U:$U) -> 1690511.7 | EQ19: =AVERAGEIF('GEM data - Zero_net'!$B:$B,'Chart Data'!$DC19,'GEM data - Zero_net'!$V:$V) -> 26087.385 | ER19: =AVERAGEIF('GEM data - Zero_net'!$B:$B,'Chart Data'!$DC19,'GEM data - Zero_net'!$W:$W) -> 33.225 | ES19: =AVERAGEIF('GEM data - Zero_net'!$B:$B,'Chart Data'!$DC19,'GEM data - Zero_net'!$X:$X) -> 366199.2 | ET19: =AVERAGEIF('GEM data - Zero_net'!$B:$B,'Chart Data'!$DC19,'GEM data - Zero_net'!$Y:$Y) -> 37673.28 | EU19: =AVERAGEIF('GEM data - Zero_net'!$B:$B,'Chart Data'!$DC19,'GEM data - Zero_net'!$Z:$Z) -> 1739056.8 | EV19: =AVERAGEIF('GEM data - Zero_net'!$B:$B,'Chart Data'!$DC19,'GEM data - Zero_net'!$AA:$AA) -> -1.642147 | EX19: =EQ19*ER19 -> 866753.37 | EY19: =ES19/ET19 -> 9.720396 | EZ19: =EU19 -> 1739056.8 | FA19: =EV19 -> -1.642147 | FB19: =EP19 -> 1690511.7 | FC19: =SUMIF('GEM data - Zero_net'!$B:$B,'Chart Data'!$DC19,'GEM data - Zero_net'!$F:$F) -> 1665005 | FE19: =100*((FB19/FB18)-1) -> 2.7023315 | FF19: =100*((FC19/FC18)-1) -> 2.614916
B20: ='GEM data - Baseline'!$F184 -> 695145 | C20: ='GEM data - Upside'!$F184 -> 695145 | D20: ='GEM data - Zero_net'!$F184 -> 695145 | F20: 2017 | G20: ='[2]Chart Data'!M21 -> 200 | M20: =100*(('GEM data - Baseline'!$P184/'GEM data - Baseline'!$P180)-1) -> 1.0992873 | N20: =100*(('GEM data - Upside'!$P184/'GEM data - Upside'!$P180)-1) -> 1.0992873 | O20: =100*(('GEM data - Zero_net'!$P184/'GEM data - Zero_net'!$P180)-1) -> 1.0992873 | Q20: 2037 | R20: =100*(SUMIF('GEM data - Baseline'!$C:$C,'Chart Data'!$Q20,'GEM data - Baseline'!$Q:$Q)/SUMIF('GEM data - Baseline'!$C:$C,'Chart Data'!$Q20,'GEM data - Baseline'!$S:$S)) -> -1.0615329 | S20: =100*(SUMIF('GEM data - Upside'!$C:$C,'Chart Data'!$Q20,'GEM data - Upside'!$Q:$Q)/SUMIF('GEM data - Upside'!$C:$C,'Chart Data'!$Q20,'GEM data - Upside'!$S:$S)) -> -0.88762451 | T20: =100*(SUMIF('GEM data - Zero_net'!$C:$C,'Chart Data'!$Q20,'GEM data - Zero_net'!$Q:$Q)/SUMIF('GEM data - Zero_net'!$C:$C,'Chart Data'!$Q20,'GEM data - Zero_net'!$S:$S)) -> -1.6522001 | V20: 2037 | W20: =100*(SUMIF('GEM data - Baseline'!$D:$D,'Chart Data'!$Q20,'GEM data - Baseline'!$R:$R)/SUMIF('GEM data - Baseline'!$C:$C,'Chart Data'!$Q20,'GEM data - Baseline'!$S:$S)) -> 85.288101 | X20: =100*(SUMIF('GEM data - Upside'!$D:$D,'Chart Data'!$Q20,'GEM data - Upside'!$R:$R)/SUMIF('GEM data - Upside'!$C:$C,'Chart Data'!$Q20,'GEM data - Upside'!$S:$S)) -> 83.509303 | Y20: =100*(SUMIF('GEM data - Zero_net'!$D:$D,'Chart Data'!$Q20,'GEM data - Zero_net'!$R:$R)/SUMIF('GEM data - Zero_net'!$C:$C,'Chart Data'!$Q20,'GEM data - Zero_net'!$S:$S)) -> 90.113704 | AA20: 18 | AB20: =VLOOKUP($AA20,$AE$3:$AG$21,2,FALSE) -> Art & recreation | AC20: =VLOOKUP($AA20,$AE$3:$AG$21,3,FALSE) -> 9.4098437 | AE20: =RANK(AG20,$AG$3:$AG$21) -> 18 | AF20: Art & recreation | AG20: =100*(AL20/AJ20) -> 9.4098437 | AI20: ART | AJ20: {=INDEX('HMRC emp by ind and nat'!$A$149:$C$233,MATCH(1,('HMRC emp by ind and nat'!$A$145:$CG$145=AJ$1)*('HMRC emp by ind and nat'!$A$146:$CG$146=$AI20),0),3)} -> 714500 | AK20: {=INDEX('HMRC emp by ind and nat'!$A$149:$C$233,MATCH(1,('HMRC emp by ind and nat'!$A$145:$CG$145=AK$1)*('HMRC emp by ind and nat'!$A$146:$CG$146=$AI20),0),3)} -> 647266.67 | AL20: =AJ20-AK20 -> 67233.333 | AP20: 2017 | AQ20: =AVERAGEIF('GEM data - Baseline'!$B:$B,'Chart Data'!$AP20,'GEM data - Baseline'!$AE:$AE) -> 28.798678 | AR20: =AVERAGEIF('GEM data - Upside'!$B:$B,'Chart Data'!$AP20,'GEM data - Upside'!$AE:$AE) -> 28.798678 | AS20: =AVERAGEIF('GEM data - Zero_net'!$B:$B,'Chart Data'!$AP20,'GEM data - Zero_net'!$AE:$AE) -> 28.798678 | AU20: 2017 | AV20: =AVERAGEIF('GEM data - Baseline'!$B:$B,'Chart Data'!$AP20,'GEM data - Baseline'!AE:AE) -> 28.798678 | AW20: =AVERAGEIF('GEM data - Baseline'!$B:$B,'Chart Data'!$AP20,'GEM data - Baseline'!AF:AF) -> 19.635298 | AX20: =AVERAGEIF('GEM data - Baseline'!$B:$B,'Chart Data'!$AP20,'GEM data - Baseline'!AG:AG) -> 47.089785 | AY20: =AVERAGEIF('GEM data - Baseline'!$B:$B,'Chart Data'!$AP20,'GEM data - Baseline'!AH:AH) -> 32.372285 | AZ20: =AVERAGEIF('GEM data - Baseline'!$B:$B,'Chart Data'!$AP20,'GEM data - Baseline'!AI:AI) -> 30.710395 | BA20: =AVERAGEIF('GEM data - Baseline'!$B:$B,'Chart Data'!$AP20,'GEM data - Baseline'!AJ:AJ) -> 34.884142 | BB20: =AVERAGEIF('GEM data - Baseline'!$B:$B,'Chart Data'!$AP20,'GEM data - Baseline'!AK:AK) -> 20.581557 | BF20: =100*(('GEM data - Baseline'!$F184/'GEM data - Baseline'!$F180)-1) -> 0.82002521 | BG20: =100*(('GEM data - Upside'!$F184/'GEM data - Upside'!$F180)-1) -> 0.82002521 | BH20: =100*(('GEM data - Zero_net'!$F184/'GEM data - Zero_net'!$F180)-1) -> 0.82002521 | BK20: =100*(('GEM data - Baseline'!$U184/'GEM data - Baseline'!$U180)-1) -> 1.9824639 | BL20: =100*(('GEM data - Upside'!$U184/'GEM data - Upside'!$U180)-1) -> 1.9824639 | BM20: =100*(('GEM data - Zero_net'!$U184/'GEM data - Zero_net'!$U180)-1) -> 1.9824639 | BP20: ='GEM data - Baseline'!$O184 -> 4.2 | BQ20: ='GEM data - Upside'!$O184 -> 4.2 | BR20: ='GEM data - Zero_net'!$O184 -> 4.2 | BU20: =100*(('GEM data - Baseline'!$L184/'GEM data - Baseline'!$L180)-1) -> 0.4167916 | BV20: =100*(('GEM data - Upside'!$L184/'GEM data - Upside'!$L180)-1) -> 0.4167916 | BW20: =100*(('GEM data - Zero_net'!$L184/'GEM data - Zero_net'!$L180)-1) -> 0.4167916 | BZ20: ='GEM data - Baseline'!$T184 -> 0.2038002 | CA20: ='GEM data - Upside'!$T184 -> 0.2038002 | CB20: ='GEM data - Zero_net'!$T184 -> 0.2038002 | CE20: ='GEM data - Baseline'!$J184 -> 5.25 | CF20: ='GEM data - Upside'!$J184 -> 5.25 | CG20: ='GEM data - Zero_net'!$J184 -> 5.25 | CJ20: =100*(('GEM data - Baseline'!$I184/'GEM data - Baseline'!$I180)-1) -> 2.1108336 | CK20: =100*(('GEM data - Upside'!$I184/'GEM data - Upside'!$I180)-1) -> 2.1108336 | CL20: =100*(('GEM data - Zero_net'!$I184/'GEM data - Zero_net'!$I180)-1) -> 2.1108336 | CO20: =100*('GEM data - Baseline'!$AB184/'GEM data - Baseline'!$AD184) -> 451.04718 | CP20: =100*('GEM data - Upside'!$AB184/'GEM data - Upside'!$AD184) -> 451.04718 | CQ20: =100*('GEM data - Zero_net'!$AB184/'GEM data - Zero_net'!$AD184) -> 451.04718 | CT20: =100*('GEM data - Baseline'!$AC184/'GEM data - Baseline'!$AD184) -> 376.83492 | CU20: =100*('GEM data - Upside'!$AC184/'GEM data - Upside'!$AD184) -> 376.83492 | CV20: =100*('GEM data - Zero_net'!$AC184/'GEM data - Zero_net'!$AD184) -> 376.83492 | CY20: =100*('GEM data - Baseline'!$F184/'GEM data - Baseline'!$AD184) -> 1003.3703 | CZ20: =100*('GEM data - Upside'!$F184/'GEM data - Upside'!$AD184) -> 1003.3703 | DA20: =100*('GEM data - Zero_net'!$F184/'GEM data - Zero_net'!$AD184) -> 1003.3703 | DC20: 1997 | DD20: =SUMIF('GEM data - Baseline'!$B:$B,'Chart Data'!$DC20,'GEM data - Baseline'!$U:$U) -> 1738402.6 | DE20: =AVERAGEIF('GEM data - Baseline'!$B:$B,'Chart Data'!$DC20,'GEM data - Baseline'!$V:$V) -> 26460.545 | DF20: =AVERAGEIF('GEM data - Baseline'!$B:$B,'Chart Data'!$DC20,'GEM data - Baseline'!$W:$W) -> 33.175 | DG20: =AVERAGEIF('GEM data - Baseline'!$B:$B,'Chart Data'!$DC20,'GEM data - Baseline'!$X:$X) -> 368101.37 | DH20: =AVERAGEIF('GEM data - Baseline'!$B:$B,'Chart Data'!$DC20,'GEM data - Baseline'!$Y:$Y) -> 37794.405 | DI20: =AVERAGEIF('GEM data - Baseline'!$B:$B,'Chart Data'!$DC20,'GEM data - Baseline'!$Z:$Z) -> 1788682.8 | DJ20: =AVERAGEIF('GEM data - Baseline'!$B:$B,'Chart Data'!$DC20,'GEM data - Baseline'!$AA:$AA) -> -1.6323513 | DL20: =DE20*DF20 -> 877828.58 | DM20: =DG20/DH20 -> 9.7395732 | DN20: =DI20 -> 1788682.8 | DO20: =DJ20 -> -1.6323513 | DP20: =DD20 -> 1738402.6 | DQ20: =SUMIF('GEM data - Baseline'!$B:$B,'Chart Data'!$DC20,'GEM data - Baseline'!$F:$F) -> 1746257 | DS20: =100*((DP20/DP19)-1) -> 2.8329233 | DT20: =100*((DQ20/DQ19)-1) -> 4.8799853 | DV20: 1997 | DW20: =SUMIF('GEM data - Upside'!$B:$B,'Chart Data'!$DC20,'GEM data - Upside'!$U:$U) -> 1738402.6 | DX20: =AVERAGEIF('GEM data - Upside'!$B:$B,'Chart Data'!$DC20,'GEM data - Upside'!$V:$V) -> 26460.545 | DY20: =AVERAGEIF('GEM data - Upside'!$B:$B,'Chart Data'!$DC20,'GEM data - Upside'!$W:$W) -> 33.175 | DZ20: =AVERAGEIF('GEM data - Upside'!$B:$B,'Chart Data'!$DC20,'GEM data - Upside'!$X:$X) -> 368101.37 | EA20: =AVERAGEIF('GEM data - Upside'!$B:$B,'Chart Data'!$DC20,'GEM data - Upside'!$Y:$Y) -> 37794.405 | EB20: =AVERAGEIF('GEM data - Upside'!$B:$B,'Chart Data'!$DC20,'GEM data - Upside'!$Z:$Z) -> 1788682.8 | EC20: =AVERAGEIF('GEM data - Upside'!$B:$B,'Chart Data'!$DC20,'GEM data - Upside'!$AA:$AA) -> -1.6323513 | EE20: =DX20*DY20 -> 877828.58 | EF20: =DZ20/EA20 -> 9.7395732 | EG20: =EB20 -> 1788682.8 | EH20: =EC20 -> -1.6323513 | EI20: =DW20 -> 1738402.6 | EJ20: =SUMIF('GEM data - Upside'!$B:$B,'Chart Data'!$DC20,'GEM data - Upside'!$F:$F) -> 1746257 | EL20: =100*((EI20/EI19)-1) -> 2.8329233 | EM20: =100*((EJ20/EJ19)-1) -> 4.8799853 | EO20: 1997 | EP20: =SUMIF('GEM data - Zero_net'!$B:$B,'Chart Data'!$DC20,'GEM data - Zero_net'!$U:$U) -> 1738402.6 | EQ20: =AVERAGEIF('GEM data - Zero_net'!$B:$B,'Chart Data'!$DC20,'GEM data - Zero_net'!$V:$V) -> 26460.545 | ER20: =AVERAGEIF('GEM data - Zero_net'!$B:$B,'Chart Data'!$DC20,'GEM data - Zero_net'!$W:$W) -> 33.175 | ES20: =AVERAGEIF('GEM data - Zero_net'!$B:$B,'Chart Data'!$DC20,'GEM data - Zero_net'!$X:$X) -> 368101.37 | ET20: =AVERAGEIF('GEM data - Zero_net'!$B:$B,'Chart Data'!$DC20,'GEM data - Zero_net'!$Y:$Y) -> 37794.405 | EU20: =AVERAGEIF('GEM data - Zero_net'!$B:$B,'Chart Data'!$DC20,'GEM data - Zero_net'!$Z:$Z) -> 1788682.8 | EV20: =AVERAGEIF('GEM data - Zero_net'!$B:$B,'Chart Data'!$DC20,'GEM data - Zero_net'!$AA:$AA) -> -1.6323513 | EX20: =EQ20*ER20 -> 877828.58 | EY20: =ES20/ET20 -> 9.7395732 | EZ20: =EU20 -> 1788682.8 | FA20: =EV20 -> -1.6323513 | FB20: =EP20 -> 1738402.6 | FC20: =SUMIF('GEM data - Zero_net'!$B:$B,'Chart Data'!$DC20,'GEM data - Zero_net'!$F:$F) -> 1746257 | FE20: =100*((FB20/FB19)-1) -> 2.8329233 | FF20: =100*((FC20/FC19)-1) -> 4.8799853
B21: ='GEM data - Baseline'!$F185 -> 696752 | C21: ='GEM data - Upside'!$F185 -> 696752 | D21: ='GEM data - Zero_net'!$F185 -> 696752 | F21: 2018 | G21: ='[2]Chart Data'!M22 -> 216 | M21: =100*(('GEM data - Baseline'!$P185/'GEM data - Baseline'!$P181)-1) -> 0.84941081 | N21: =100*(('GEM data - Upside'!$P185/'GEM data - Upside'!$P181)-1) -> 0.84941081 | O21: =100*(('GEM data - Zero_net'!$P185/'GEM data - Zero_net'!$P181)-1) -> 0.84941081 | Q21: 2038 | R21: =100*(SUMIF('GEM data - Baseline'!$C:$C,'Chart Data'!$Q21,'GEM data - Baseline'!$Q:$Q)/SUMIF('GEM data - Baseline'!$C:$C,'Chart Data'!$Q21,'GEM data - Baseline'!$S:$S)) -> -1.2047254 | S21: =100*(SUMIF('GEM data - Upside'!$C:$C,'Chart Data'!$Q21,'GEM data - Upside'!$Q:$Q)/SUMIF('GEM data - Upside'!$C:$C,'Chart Data'!$Q21,'GEM data - Upside'!$S:$S)) -> -1.0078419 | T21: =100*(SUMIF('GEM data - Zero_net'!$C:$C,'Chart Data'!$Q21,'GEM data - Zero_net'!$Q:$Q)/SUMIF('GEM data - Zero_net'!$C:$C,'Chart Data'!$Q21,'GEM data - Zero_net'!$S:$S)) -> -1.8927122 | V21: 2038 | W21: =100*(SUMIF('GEM data - Baseline'!$D:$D,'Chart Data'!$Q21,'GEM data - Baseline'!$R:$R)/SUMIF('GEM data - Baseline'!$C:$C,'Chart Data'!$Q21,'GEM data - Baseline'!$S:$S)) -> 85.942591 | X21: =100*(SUMIF('GEM data - Upside'!$D:$D,'Chart Data'!$Q21,'GEM data - Upside'!$R:$R)/SUMIF('GEM data - Upside'!$C:$C,'Chart Data'!$Q21,'GEM data - Upside'!$S:$S)) -> 83.966564 | Y21: =100*(SUMIF('GEM data - Zero_net'!$D:$D,'Chart Data'!$Q21,'GEM data - Zero_net'!$R:$R)/SUMIF('GEM data - Zero_net'!$C:$C,'Chart Data'!$Q21,'GEM data - Zero_net'!$S:$S)) -> 91.662699 | AA21: 19 | AB21: =VLOOKUP($AA21,$AE$3:$AG$21,2,FALSE) -> Public administration | AC21: =VLOOKUP($AA21,$AE$3:$AG$21,3,FALSE) -> 6.4230613 | AE21: =RANK(AG21,$AG$3:$AG$21) -> 6 | AF21: Other services | AG21: =100*(AL21/AJ21) -> 20.636898 | AI21: STU | AJ21: =AJ23-SUM(AJ3:AJ20) -> 856233.33 | AK21: =AK23-SUM(AK3:AK20) -> 679533.33 | AL21: =AJ21-AK21 -> 176700 | AP21: 2018 | AQ21: =AVERAGEIF('GEM data - Baseline'!$B:$B,'Chart Data'!$AP21,'GEM data - Baseline'!$AE:$AE) -> 28.924365 | AR21: =AVERAGEIF('GEM data - Upside'!$B:$B,'Chart Data'!$AP21,'GEM data - Upside'!$AE:$AE) -> 28.924365 | AS21: =AVERAGEIF('GEM data - Zero_net'!$B:$B,'Chart Data'!$AP21,'GEM data - Zero_net'!$AE:$AE) -> 28.924365 | AU21: 2018 | AV21: =AVERAGEIF('GEM data - Baseline'!$B:$B,'Chart Data'!$AP21,'GEM data - Baseline'!AE:AE) -> 28.924365 | AW21: =AVERAGEIF('GEM data - Baseline'!$B:$B,'Chart Data'!$AP21,'GEM data - Baseline'!AF:AF) -> 20.010063 | AX21: =AVERAGEIF('GEM data - Baseline'!$B:$B,'Chart Data'!$AP21,'GEM data - Baseline'!AG:AG) -> 47.910202 | AY21: =AVERAGEIF('GEM data - Baseline'!$B:$B,'Chart Data'!$AP21,'GEM data - Baseline'!AH:AH) -> 32.695325 | AZ21: =AVERAGEIF('GEM data - Baseline'!$B:$B,'Chart Data'!$AP21,'GEM data - Baseline'!AI:AI) -> 31.299115 | BA21: =AVERAGEIF('GEM data - Baseline'!$B:$B,'Chart Data'!$AP21,'GEM data - Baseline'!AJ:AJ) -> 35.076077 | BB21: =AVERAGEIF('GEM data - Baseline'!$B:$B,'Chart Data'!$AP21,'GEM data - Baseline'!AK:AK) -> 20.980675 | BF21: =100*(('GEM data - Baseline'!$F185/'GEM data - Baseline'!$F181)-1) -> 1.2957974 | BG21: =100*(('GEM data - Upside'!$F185/'GEM data - Upside'!$F181)-1) -> 1.2957974 | BH21: =100*(('GEM data - Zero_net'!$F185/'GEM data - Zero_net'!$F181)-1) -> 1.2957974 | BK21: =100*(('GEM data - Baseline'!$U185/'GEM data - Baseline'!$U181)-1) -> 3.0734703 | BL21: =100*(('GEM data - Upside'!$U185/'GEM data - Upside'!$U181)-1) -> 3.0734703 | BM21: =100*(('GEM data - Zero_net'!$U185/'GEM data - Zero_net'!$U181)-1) -> 3.0734703 | BP21: ='GEM data - Baseline'!$O185 -> 4.3 | BQ21: ='GEM data - Upside'!$O185 -> 4.3 | BR21: ='GEM data - Zero_net'!$O185 -> 4.3 | BU21: =100*(('GEM data - Baseline'!$L185/'GEM data - Baseline'!$L181)-1) -> 1.2743628 | BV21: =100*(('GEM data - Upside'!$L185/'GEM data - Upside'!$L181)-1) -> 1.2743628 | BW21: =100*(('GEM data - Zero_net'!$L185/'GEM data - Zero_net'!$L181)-1) -> 1.2743628 | BZ21: ='GEM data - Baseline'!$T185 -> -0.5734444 | CA21: ='GEM data - Upside'!$T185 -> -0.5734444 | CB21: ='GEM data - Zero_net'!$T185 -> -0.5734444 | CE21: ='GEM data - Baseline'!$J185 -> 5.087121 | CF21: ='GEM data - Upside'!$J185 -> 5.087121 | CG21: ='GEM data - Zero_net'!$J185 -> 5.087121 | CJ21: =100*(('GEM data - Baseline'!$I185/'GEM data - Baseline'!$I181)-1) -> 2.0547945 | CK21: =100*(('GEM data - Upside'!$I185/'GEM data - Upside'!$I181)-1) -> 2.0547945 | CL21: =100*(('GEM data - Zero_net'!$I185/'GEM data - Zero_net'!$I181)-1) -> 2.0547945 | CO21: =100*('GEM data - Baseline'!$AB185/'GEM data - Baseline'!$AD185) -> 451.68428 | CP21: =100*('GEM data - Upside'!$AB185/'GEM data - Upside'!$AD185) -> 451.68428 | CQ21: =100*('GEM data - Zero_net'!$AB185/'GEM data - Zero_net'!$AD185) -> 451.68428 | CT21: =100*('GEM data - Baseline'!$AC185/'GEM data - Baseline'!$AD185) -> 397.73699 | CU21: =100*('GEM data - Upside'!$AC185/'GEM data - Upside'!$AD185) -> 397.73699 | CV21: =100*('GEM data - Zero_net'!$AC185/'GEM data - Zero_net'!$AD185) -> 397.73699 | CY21: =100*('GEM data - Baseline'!$F185/'GEM data - Baseline'!$AD185) -> 1004.9428 | CZ21: =100*('GEM data - Upside'!$F185/'GEM data - Upside'!$AD185) -> 1004.9428 | DA21: =100*('GEM data - Zero_net'!$F185/'GEM data - Zero_net'!$AD185) -> 1004.9428 | DC21: 1998 | DD21: =SUMIF('GEM data - Baseline'!$B:$B,'Chart Data'!$DC21,'GEM data - Baseline'!$U:$U) -> 1778836 | DE21: =AVERAGEIF('GEM data - Baseline'!$B:$B,'Chart Data'!$DC21,'GEM data - Baseline'!$V:$V) -> 26754.357 | DF21: =AVERAGEIF('GEM data - Baseline'!$B:$B,'Chart Data'!$DC21,'GEM data - Baseline'!$W:$W) -> 33.075 | DG21: =AVERAGEIF('GEM data - Baseline'!$B:$B,'Chart Data'!$DC21,'GEM data - Baseline'!$X:$X) -> 370531.55 | DH21: =AVERAGEIF('GEM data - Baseline'!$B:$B,'Chart Data'!$DC21,'GEM data - Baseline'!$Y:$Y) -> 37944.26 | DI21: =AVERAGEIF('GEM data - Baseline'!$B:$B,'Chart Data'!$DC21,'GEM data - Baseline'!$Z:$Z) -> 1845250 | DJ21: =AVERAGEIF('GEM data - Baseline'!$B:$B,'Chart Data'!$DC21,'GEM data - Baseline'!$AA:$AA) -> -1.6261382 | DL21: =DE21*DF21 -> 884900.37 | DM21: =DG21/DH21 -> 9.7651542 | DN21: =DI21 -> 1845250 | DO21: =DJ21 -> -1.6261382 | DP21: =DD21 -> 1778836 | DQ21: =SUMIF('GEM data - Baseline'!$B:$B,'Chart Data'!$DC21,'GEM data - Baseline'!$F:$F) -> 1802946 | DS21: =100*((DP21/DP20)-1) -> 2.3258939 | DT21: =100*((DQ21/DQ20)-1) -> 3.2463148 | DV21: 1998 | DW21: =SUMIF('GEM data - Upside'!$B:$B,'Chart Data'!$DC21,'GEM data - Upside'!$U:$U) -> 1778836 | DX21: =AVERAGEIF('GEM data - Upside'!$B:$B,'Chart Data'!$DC21,'GEM data - Upside'!$V:$V) -> 26754.357 | DY21: =AVERAGEIF('GEM data - Upside'!$B:$B,'Chart Data'!$DC21,'GEM data - Upside'!$W:$W) -> 33.075 | DZ21: =AVERAGEIF('GEM data - Upside'!$B:$B,'Chart Data'!$DC21,'GEM data - Upside'!$X:$X) -> 370531.55 | EA21: =AVERAGEIF('GEM data - Upside'!$B:$B,'Chart Data'!$DC21,'GEM data - Upside'!$Y:$Y) -> 37944.26 | EB21: =AVERAGEIF('GEM data - Upside'!$B:$B,'Chart Data'!$DC21,'GEM data - Upside'!$Z:$Z) -> 1845250 | EC21: =AVERAGEIF('GEM data - Upside'!$B:$B,'Chart Data'!$DC21,'GEM data - Upside'!$AA:$AA) -> -1.6261382 | EE21: =DX21*DY21 -> 884900.37 | EF21: =DZ21/EA21 -> 9.7651542 | EG21: =EB21 -> 1845250 | EH21: =EC21 -> -1.6261382 | EI21: =DW21 -> 1778836 | EJ21: =SUMIF('GEM data - Upside'!$B:$B,'Chart Data'!$DC21,'GEM data - Upside'!$F:$F) -> 1802946 | EL21: =100*((EI21/EI20)-1) -> 2.3258939 | EM21: =100*((EJ21/EJ20)-1) -> 3.2463148 | EO21: 1998 | EP21: =SUMIF('GEM data - Zero_net'!$B:$B,'Chart Data'!$DC21,'GEM data - Zero_net'!$U:$U) -> 1778836 | EQ21: =AVERAGEIF('GEM data - Zero_net'!$B:$B,'Chart Data'!$DC21,'GEM data - Zero_net'!$V:$V) -> 26754.357 | ER21: =AVERAGEIF('GEM data - Zero_net'!$B:$B,'Chart Data'!$DC21,'GEM data - Zero_net'!$W:$W) -> 33.075 | ES21: =AVERAGEIF('GEM data - Zero_net'!$B:$B,'Chart Data'!$DC21,'GEM data - Zero_net'!$X:$X) -> 370531.55 | ET21: =AVERAGEIF('GEM data - Zero_net'!$B:$B,'Chart Data'!$DC21,'GEM data - Zero_net'!$Y:$Y) -> 37944.26 | EU21: =AVERAGEIF('GEM data - Zero_net'!$B:$B,'Chart Data'!$DC21,'GEM data - Zero_net'!$Z:$Z) -> 1845250 | EV21: =AVERAGEIF('GEM data - Zero_net'!$B:$B,'Chart Data'!$DC21,'GEM data - Zero_net'!$AA:$AA) -> -1.6261382 | EX21: =EQ21*ER21 -> 884900.37 | EY21: =ES21/ET21 -> 9.7651542 | EZ21: =EU21 -> 1845250 | FA21: =EV21 -> -1.6261382 | FB21: =EP21 -> 1778836 | FC21: =SUMIF('GEM data - Zero_net'!$B:$B,'Chart Data'!$DC21,'GEM data - Zero_net'!$F:$F) -> 1802946 | FE21: =100*((FB21/FB20)-1) -> 2.3258939 | FF21: =100*((FC21/FC20)-1) -> 3.2463148
B22: ='GEM data - Baseline'!$F186 -> 699094 | C22: ='GEM data - Upside'!$F186 -> 699094 | D22: ='GEM data - Zero_net'!$F186 -> 699094 | F22: 2019 | G22: ='[2]Chart Data'!M23 -> 224 | M22: =100*(('GEM data - Baseline'!$P186/'GEM data - Baseline'!$P182)-1) -> 0.60090018 | N22: =100*(('GEM data - Upside'!$P186/'GEM data - Upside'!$P182)-1) -> 0.60090018 | O22: =100*(('GEM data - Zero_net'!$P186/'GEM data - Zero_net'!$P182)-1) -> 0.60090018 | Q22: 2039 | R22: =100*(SUMIF('GEM data - Baseline'!$C:$C,'Chart Data'!$Q22,'GEM data - Baseline'!$Q:$Q)/SUMIF('GEM data - Baseline'!$C:$C,'Chart Data'!$Q22,'GEM data - Baseline'!$S:$S)) -> -1.34804 | S22: =100*(SUMIF('GEM data - Upside'!$C:$C,'Chart Data'!$Q22,'GEM data - Upside'!$Q:$Q)/SUMIF('GEM data - Upside'!$C:$C,'Chart Data'!$Q22,'GEM data - Upside'!$S:$S)) -> -1.1404025 | T22: =100*(SUMIF('GEM data - Zero_net'!$C:$C,'Chart Data'!$Q22,'GEM data - Zero_net'!$Q:$Q)/SUMIF('GEM data - Zero_net'!$C:$C,'Chart Data'!$Q22,'GEM data - Zero_net'!$S:$S)) -> -2.1468328 | V22: 2039 | W22: =100*(SUMIF('GEM data - Baseline'!$D:$D,'Chart Data'!$Q22,'GEM data - Baseline'!$R:$R)/SUMIF('GEM data - Baseline'!$C:$C,'Chart Data'!$Q22,'GEM data - Baseline'!$S:$S)) -> 86.714775 | X22: =100*(SUMIF('GEM data - Upside'!$D:$D,'Chart Data'!$Q22,'GEM data - Upside'!$R:$R)/SUMIF('GEM data - Upside'!$C:$C,'Chart Data'!$Q22,'GEM data - Upside'!$S:$S)) -> 84.557875 | Y22: =100*(SUMIF('GEM data - Zero_net'!$D:$D,'Chart Data'!$Q22,'GEM data - Zero_net'!$R:$R)/SUMIF('GEM data - Zero_net'!$C:$C,'Chart Data'!$Q22,'GEM data - Zero_net'!$S:$S)) -> 93.43618 | AP22: 2019 | AQ22: =AVERAGEIF('GEM data - Baseline'!$B:$B,'Chart Data'!$AP22,'GEM data - Baseline'!$AE:$AE) -> 29.024977 | AR22: =AVERAGEIF('GEM data - Upside'!$B:$B,'Chart Data'!$AP22,'GEM data - Upside'!$AE:$AE) -> 29.024977 | AS22: =AVERAGEIF('GEM data - Zero_net'!$B:$B,'Chart Data'!$AP22,'GEM data - Zero_net'!$AE:$AE) -> 29.024977 | AU22: 2019 | AV22: =AVERAGEIF('GEM data - Baseline'!$B:$B,'Chart Data'!$AP22,'GEM data - Baseline'!AE:AE) -> 29.024977 | AW22: =AVERAGEIF('GEM data - Baseline'!$B:$B,'Chart Data'!$AP22,'GEM data - Baseline'!AF:AF) -> 20.509593 | AX22: =AVERAGEIF('GEM data - Baseline'!$B:$B,'Chart Data'!$AP22,'GEM data - Baseline'!AG:AG) -> 48.519737 | AY22: =AVERAGEIF('GEM data - Baseline'!$B:$B,'Chart Data'!$AP22,'GEM data - Baseline'!AH:AH) -> 33.07467 | AZ22: =AVERAGEIF('GEM data - Baseline'!$B:$B,'Chart Data'!$AP22,'GEM data - Baseline'!AI:AI) -> 31.88594 | BA22: =AVERAGEIF('GEM data - Baseline'!$B:$B,'Chart Data'!$AP22,'GEM data - Baseline'!AJ:AJ) -> 35.476827 | BB22: =AVERAGEIF('GEM data - Baseline'!$B:$B,'Chart Data'!$AP22,'GEM data - Baseline'!AK:AK) -> 21.456747 | BF22: =100*(('GEM data - Baseline'!$F186/'GEM data - Baseline'!$F182)-1) -> 1.9640388 | BG22: =100*(('GEM data - Upside'!$F186/'GEM data - Upside'!$F182)-1) -> 1.9640388 | BH22: =100*(('GEM data - Zero_net'!$F186/'GEM data - Zero_net'!$F182)-1) -> 1.9640388 | BK22: =100*(('GEM data - Baseline'!$U186/'GEM data - Baseline'!$U182)-1) -> 2.3599045 | BL22: =100*(('GEM data - Upside'!$U186/'GEM data - Upside'!$U182)-1) -> 2.3599045 | BM22: =100*(('GEM data - Zero_net'!$U186/'GEM data - Zero_net'!$U182)-1) -> 2.3599045 | BP22: ='GEM data - Baseline'!$O186 -> 4.4 | BQ22: ='GEM data - Upside'!$O186 -> 4.4 | BR22: ='GEM data - Zero_net'!$O186 -> 4.4 | BU22: =100*(('GEM data - Baseline'!$L186/'GEM data - Baseline'!$L182)-1) -> 1.4500135 | BV22: =100*(('GEM data - Upside'!$L186/'GEM data - Upside'!$L182)-1) -> 1.4500135 | BW22: =100*(('GEM data - Zero_net'!$L186/'GEM data - Zero_net'!$L182)-1) -> 1.4500135 | BZ22: ='GEM data - Baseline'!$T186 -> -0.07324219 | CA22: ='GEM data - Upside'!$T186 -> -0.07324219 | CB22: ='GEM data - Zero_net'!$T186 -> -0.07324219 | CE22: ='GEM data - Baseline'!$J186 -> 4.852273 | CF22: ='GEM data - Upside'!$J186 -> 4.852273 | CG22: ='GEM data - Zero_net'!$J186 -> 4.852273 | CJ22: =100*(('GEM data - Baseline'!$I186/'GEM data - Baseline'!$I182)-1) -> 2.4753214 | CK22: =100*(('GEM data - Upside'!$I186/'GEM data - Upside'!$I182)-1) -> 2.4753214 | CL22: =100*(('GEM data - Zero_net'!$I186/'GEM data - Zero_net'!$I182)-1) -> 2.4753214 | CO22: =100*('GEM data - Baseline'!$AB186/'GEM data - Baseline'!$AD186) -> 468.55759 | CP22: =100*('GEM data - Upside'!$AB186/'GEM data - Upside'!$AD186) -> 468.55759 | CQ22: =100*('GEM data - Zero_net'!$AB186/'GEM data - Zero_net'!$AD186) -> 468.55759 | CT22: =100*('GEM data - Baseline'!$AC186/'GEM data - Baseline'!$AD186) -> 394.60394 | CU22: =100*('GEM data - Upside'!$AC186/'GEM data - Upside'!$AD186) -> 394.60394 | CV22: =100*('GEM data - Zero_net'!$AC186/'GEM data - Zero_net'!$AD186) -> 394.60394 | CY22: =100*('GEM data - Baseline'!$F186/'GEM data - Baseline'!$AD186) -> 1007.5724 | CZ22: =100*('GEM data - Upside'!$F186/'GEM data - Upside'!$AD186) -> 1007.5724 | DA22: =100*('GEM data - Zero_net'!$F186/'GEM data - Zero_net'!$AD186) -> 1007.5724 | DC22: 1999 | DD22: =SUMIF('GEM data - Baseline'!$B:$B,'Chart Data'!$DC22,'GEM data - Baseline'!$U:$U) -> 1827269.5 | DE22: =AVERAGEIF('GEM data - Baseline'!$B:$B,'Chart Data'!$DC22,'GEM data - Baseline'!$V:$V) -> 27233.62 | DF22: =AVERAGEIF('GEM data - Baseline'!$B:$B,'Chart Data'!$DC22,'GEM data - Baseline'!$W:$W) -> 32.9 | DG22: =AVERAGEIF('GEM data - Baseline'!$B:$B,'Chart Data'!$DC22,'GEM data - Baseline'!$X:$X) -> 375183.33 | DH22: =AVERAGEIF('GEM data - Baseline'!$B:$B,'Chart Data'!$DC22,'GEM data - Baseline'!$Y:$Y) -> 38156.28 | DI22: =AVERAGEIF('GEM data - Baseline'!$B:$B,'Chart Data'!$DC22,'GEM data - Baseline'!$Z:$Z) -> 1902000 | DJ22: =AVERAGEIF('GEM data - Baseline'!$B:$B,'Chart Data'!$DC22,'GEM data - Baseline'!$AA:$AA) -> -1.620242 | DL22: =DE22*DF22 -> 895986.1 | DM22: =DG22/DH22 -> 9.8328067 | DN22: =DI22 -> 1902000 | DO22: =DJ22 -> -1.620242 | DP22: =DD22 -> 1827269.5 | DQ22: =SUMIF('GEM data - Baseline'!$B:$B,'Chart Data'!$DC22,'GEM data - Baseline'!$F:$F) -> 1856033 | DS22: =100*((DP22/DP21)-1) -> 2.7227636 | DT22: =100*((DQ22/DQ21)-1) -> 2.9444587 | DV22: 1999 | DW22: =SUMIF('GEM data - Upside'!$B:$B,'Chart Data'!$DC22,'GEM data - Upside'!$U:$U) -> 1827269.5 | DX22: =AVERAGEIF('GEM data - Upside'!$B:$B,'Chart Data'!$DC22,'GEM data - Upside'!$V:$V) -> 27233.62 | DY22: =AVERAGEIF('GEM data - Upside'!$B:$B,'Chart Data'!$DC22,'GEM data - Upside'!$W:$W) -> 32.9 | DZ22: =AVERAGEIF('GEM data - Upside'!$B:$B,'Chart Data'!$DC22,'GEM data - Upside'!$X:$X) -> 375183.33 | EA22: =AVERAGEIF('GEM data - Upside'!$B:$B,'Chart Data'!$DC22,'GEM data - Upside'!$Y:$Y) -> 38156.28 | EB22: =AVERAGEIF('GEM data - Upside'!$B:$B,'Chart Data'!$DC22,'GEM data - Upside'!$Z:$Z) -> 1902000 | EC22: =AVERAGEIF('GEM data - Upside'!$B:$B,'Chart Data'!$DC22,'GEM data - Upside'!$AA:$AA) -> -1.620242 | EE22: =DX22*DY22 -> 895986.1 | EF22: =DZ22/EA22 -> 9.8328067 | EG22: =EB22 -> 1902000 | EH22: =EC22 -> -1.620242 | EI22: =DW22 -> 1827269.5 | EJ22: =SUMIF('GEM data - Upside'!$B:$B,'Chart Data'!$DC22,'GEM data - Upside'!$F:$F) -> 1856033 | EL22: =100*((EI22/EI21)-1) -> 2.7227636 | EM22: =100*((EJ22/EJ21)-1) -> 2.9444587 | EO22: 1999 | EP22: =SUMIF('GEM data - Zero_net'!$B:$B,'Chart Data'!$DC22,'GEM data - Zero_net'!$U:$U) -> 1827269.5 | EQ22: =AVERAGEIF('GEM data - Zero_net'!$B:$B,'Chart Data'!$DC22,'GEM data - Zero_net'!$V:$V) -> 27233.62 | ER22: =AVERAGEIF('GEM data - Zero_net'!$B:$B,'Chart Data'!$DC22,'GEM data - Zero_net'!$W:$W) -> 32.9 | ES22: =AVERAGEIF('GEM data - Zero_net'!$B:$B,'Chart Data'!$DC22,'GEM data - Zero_net'!$X:$X) -> 375183.33 | ET22: =AVERAGEIF('GEM data - Zero_net'!$B:$B,'Chart Data'!$DC22,'GEM data - Zero_net'!$Y:$Y) -> 38156.28 | EU22: =AVERAGEIF('GEM data - Zero_net'!$B:$B,'Chart Data'!$DC22,'GEM data - Zero_net'!$Z:$Z) -> 1902000 | EV22: =AVERAGEIF('GEM data - Zero_net'!$B:$B,'Chart Data'!$DC22,'GEM data - Zero_net'!$AA:$AA) -> -1.620242 | EX22: =EQ22*ER22 -> 895986.1 | EY22: =ES22/ET22 -> 9.8328067 | EZ22: =EU22 -> 1902000 | FA22: =EV22 -> -1.620242 | FB22: =EP22 -> 1827269.5 | FC22: =SUMIF('GEM data - Zero_net'!$B:$B,'Chart Data'!$DC22,'GEM data - Zero_net'!$F:$F) -> 1856033 | FE22: =100*((FB22/FB21)-1) -> 2.7227636 | FF22: =100*((FC22/FC21)-1) -> 2.9444587
A23: 2025 | B23: ='GEM data - Baseline'!$F187 -> 703655 | C23: ='GEM data - Upside'!$F187 -> 703655 | D23: ='GEM data - Zero_net'!$F187 -> 703655 | F23: 2020 | G23: ='[2]Chart Data'!M24 -> 111 | L23: 2025 | M23: =100*(('GEM data - Baseline'!$P187/'GEM data - Baseline'!$P183)-1) -> 0.35372156 | N23: =100*(('GEM data - Upside'!$P187/'GEM data - Upside'!$P183)-1) -> 0.35372156 | O23: =100*(('GEM data - Zero_net'!$P187/'GEM data - Zero_net'!$P183)-1) -> 0.35372156 | Q23: 2040 | R23: =100*(SUMIF('GEM data - Baseline'!$C:$C,'Chart Data'!$Q23,'GEM data - Baseline'!$Q:$Q)/SUMIF('GEM data - Baseline'!$C:$C,'Chart Data'!$Q23,'GEM data - Baseline'!$S:$S)) -> -1.4566134 | S23: =100*(SUMIF('GEM data - Upside'!$C:$C,'Chart Data'!$Q23,'GEM data - Upside'!$Q:$Q)/SUMIF('GEM data - Upside'!$C:$C,'Chart Data'!$Q23,'GEM data - Upside'!$S:$S)) -> -1.221374 | T23: =100*(SUMIF('GEM data - Zero_net'!$C:$C,'Chart Data'!$Q23,'GEM data - Zero_net'!$Q:$Q)/SUMIF('GEM data - Zero_net'!$C:$C,'Chart Data'!$Q23,'GEM data - Zero_net'!$S:$S)) -> -2.3504937 | V23: 2040 | W23: =100*(SUMIF('GEM data - Baseline'!$D:$D,'Chart Data'!$Q23,'GEM data - Baseline'!$R:$R)/SUMIF('GEM data - Baseline'!$C:$C,'Chart Data'!$Q23,'GEM data - Baseline'!$S:$S)) -> 87.541393 | X23: =100*(SUMIF('GEM data - Upside'!$D:$D,'Chart Data'!$Q23,'GEM data - Upside'!$R:$R)/SUMIF('GEM data - Upside'!$C:$C,'Chart Data'!$Q23,'GEM data - Upside'!$S:$S)) -> 85.168146 | Y23: =100*(SUMIF('GEM data - Zero_net'!$D:$D,'Chart Data'!$Q23,'GEM data - Zero_net'!$R:$R)/SUMIF('GEM data - Zero_net'!$C:$C,'Chart Data'!$Q23,'GEM data - Zero_net'!$S:$S)) -> 95.312864 | AB23: Total | AC23: =AG23 -> 20.10356 | AF23: Total | AG23: =100*(AL23/AJ23) -> 20.10356 | AI23: TOT | AJ23: {=INDEX('HMRC emp by ind and nat'!$A$149:$C$233,MATCH(1,('HMRC emp by ind and nat'!$A$145:$CG$145=AJ$1)*('HMRC emp by ind and nat'!$A$146:$CG$146=$AI23),0),3)} -> 32168100 | AK23: {=INDEX('HMRC emp by ind and nat'!$A$149:$C$233,MATCH(1,('HMRC emp by ind and nat'!$A$145:$CG$145=AK$1)*('HMRC emp by ind and nat'!$A$146:$CG$146=$AI23),0),3)} -> 25701167 | AL23: =AJ23-AK23 -> 6466933.3 | AP23: 2020 | AQ23: =AVERAGEIF('GEM data - Baseline'!$B:$B,'Chart Data'!$AP23,'GEM data - Baseline'!$AE:$AE) -> 29.084843 | AR23: =AVERAGEIF('GEM data - Upside'!$B:$B,'Chart Data'!$AP23,'GEM data - Upside'!$AE:$AE) -> 29.084843 | AS23: =AVERAGEIF('GEM data - Zero_net'!$B:$B,'Chart Data'!$AP23,'GEM data - Zero_net'!$AE:$AE) -> 29.084843 | AU23: 2020 | AV23: =AVERAGEIF('GEM data - Baseline'!$B:$B,'Chart Data'!$AP23,'GEM data - Baseline'!AE:AE) -> 29.084843 | AW23: =AVERAGEIF('GEM data - Baseline'!$B:$B,'Chart Data'!$AP23,'GEM data - Baseline'!AF:AF) -> 21.000145 | AX23: =AVERAGEIF('GEM data - Baseline'!$B:$B,'Chart Data'!$AP23,'GEM data - Baseline'!AG:AG) -> 49.129845 | AY23: =AVERAGEIF('GEM data - Baseline'!$B:$B,'Chart Data'!$AP23,'GEM data - Baseline'!AH:AH) -> 33.487963 | AZ23: =AVERAGEIF('GEM data - Baseline'!$B:$B,'Chart Data'!$AP23,'GEM data - Baseline'!AI:AI) -> 32.329493 | BA23: =AVERAGEIF('GEM data - Baseline'!$B:$B,'Chart Data'!$AP23,'GEM data - Baseline'!AJ:AJ) -> 35.9874 | BB23: =AVERAGEIF('GEM data - Baseline'!$B:$B,'Chart Data'!$AP23,'GEM data - Baseline'!AK:AK) -> 21.913008 | BE23: 2025 | BF23: =100*(('GEM data - Baseline'!$F187/'GEM data - Baseline'!$F183)-1) -> 1.8455531 | BG23: =100*(('GEM data - Upside'!$F187/'GEM data - Upside'!$F183)-1) -> 1.8455531 | BH23: =100*(('GEM data - Zero_net'!$F187/'GEM data - Zero_net'!$F183)-1) -> 1.8455531 | BJ23: 2025 | BK23: =100*(('GEM data - Baseline'!$U187/'GEM data - Baseline'!$U183)-1) -> 1.7821735 | BL23: =100*(('GEM data - Upside'!$U187/'GEM data - Upside'!$U183)-1) -> 1.7821735 | BM23: =100*(('GEM data - Zero_net'!$U187/'GEM data - Zero_net'!$U183)-1) -> 1.7821735 | BO23: 2025 | BP23: ='GEM data - Baseline'!$O187 -> 4.5 | BQ23: ='GEM data - Upside'!$O187 -> 4.5 | BR23: ='GEM data - Zero_net'!$O187 -> 4.5 | BT23: 2025 | BU23: =100*(('GEM data - Baseline'!$L187/'GEM data - Baseline'!$L183)-1) -> 1.919904 | BV23: =100*(('GEM data - Upside'!$L187/'GEM data - Upside'!$L183)-1) -> 1.919904 | BW23: =100*(('GEM data - Zero_net'!$L187/'GEM data - Zero_net'!$L183)-1) -> 1.919904 | BY23: 2025 | BZ23: ='GEM data - Baseline'!$T187 -> 0.0582695 | CA23: ='GEM data - Upside'!$T187 -> 0.0582695 | CB23: ='GEM data - Zero_net'!$T187 -> 0.0582695 | CD23: 2025 | CE23: ='GEM data - Baseline'!$J187 -> 4.601563 | CF23: ='GEM data - Upside'!$J187 -> 4.601563 | CG23: ='GEM data - Zero_net'!$J187 -> 4.601563 | CI23: 2025 | CJ23: =100*(('GEM data - Baseline'!$I187/'GEM data - Baseline'!$I183)-1) -> 2.7973783 | CK23: =100*(('GEM data - Upside'!$I187/'GEM data - Upside'!$I183)-1) -> 2.7973783 | CL23: =100*(('GEM data - Zero_net'!$I187/'GEM data - Zero_net'!$I183)-1) -> 2.7973783 | CN23: 2025 | CO23: =100*('GEM data - Baseline'!$AB187/'GEM data - Baseline'!$AD187) -> 489.37935 | CP23: =100*('GEM data - Upside'!$AB187/'GEM data - Upside'!$AD187) -> 489.37935 | CQ23: =100*('GEM data - Zero_net'!$AB187/'GEM data - Zero_net'!$AD187) -> 489.37935 | CS23: 2025 | CT23: =100*('GEM data - Baseline'!$AC187/'GEM data - Baseline'!$AD187) -> 472.62423 | CU23: =100*('GEM data - Upside'!$AC187/'GEM data - Upside'!$AD187) -> 472.62423 | CV23: =100*('GEM data - Zero_net'!$AC187/'GEM data - Zero_net'!$AD187) -> 472.62423 | CX23: 2025 | CY23: =100*('GEM data - Baseline'!$F187/'GEM data - Baseline'!$AD187) -> 1013.3937 | CZ23: =100*('GEM data - Upside'!$F187/'GEM data - Upside'!$AD187) -> 1013.3937 | DA23: =100*('GEM data - Zero_net'!$F187/'GEM data - Zero_net'!$AD187) -> 1013.3937 | DC23: 2000 | DD23: =SUMIF('GEM data - Baseline'!$B:$B,'Chart Data'!$DC23,'GEM data - Baseline'!$U:$U) -> 1866820.4 | DE23: =AVERAGEIF('GEM data - Baseline'!$B:$B,'Chart Data'!$DC23,'GEM data - Baseline'!$V:$V) -> 27515.478 | DF23: =AVERAGEIF('GEM data - Baseline'!$B:$B,'Chart Data'!$DC23,'GEM data - Baseline'!$W:$W) -> 32.6 | DG23: =AVERAGEIF('GEM data - Baseline'!$B:$B,'Chart Data'!$DC23,'GEM data - Baseline'!$X:$X) -> 383089.93 | DH23: =AVERAGEIF('GEM data - Baseline'!$B:$B,'Chart Data'!$DC23,'GEM data - Baseline'!$Y:$Y) -> 38407.347 | DI23: =AVERAGEIF('GEM data - Baseline'!$B:$B,'Chart Data'!$DC23,'GEM data - Baseline'!$Z:$Z) -> 1960500 | DJ23: =AVERAGEIF('GEM data - Baseline'!$B:$B,'Chart Data'!$DC23,'GEM data - Baseline'!$AA:$AA) -> -1.614367 | DL23: =DE23*DF23 -> 897004.57 | DM23: =DG23/DH23 -> 9.9743916 | DN23: =DI23 -> 1960500 | DO23: =DJ23 -> -1.614367 | DP23: =DD23 -> 1866820.4 | DQ23: =SUMIF('GEM data - Baseline'!$B:$B,'Chart Data'!$DC23,'GEM data - Baseline'!$F:$F) -> 1940007 | DS23: =100*((DP23/DP22)-1) -> 2.1644809 | DT23: =100*((DQ23/DQ22)-1) -> 4.5243808 | DV23: 2000 | DW23: =SUMIF('GEM data - Upside'!$B:$B,'Chart Data'!$DC23,'GEM data - Upside'!$U:$U) -> 1866820.4 | DX23: =AVERAGEIF('GEM data - Upside'!$B:$B,'Chart Data'!$DC23,'GEM data - Upside'!$V:$V) -> 27515.478 | DY23: =AVERAGEIF('GEM data - Upside'!$B:$B,'Chart Data'!$DC23,'GEM data - Upside'!$W:$W) -> 32.6 | DZ23: =AVERAGEIF('GEM data - Upside'!$B:$B,'Chart Data'!$DC23,'GEM data - Upside'!$X:$X) -> 383089.93 | EA23: =AVERAGEIF('GEM data - Upside'!$B:$B,'Chart Data'!$DC23,'GEM data - Upside'!$Y:$Y) -> 38407.347 | EB23: =AVERAGEIF('GEM data - Upside'!$B:$B,'Chart Data'!$DC23,'GEM data - Upside'!$Z:$Z) -> 1960500 | EC23: =AVERAGEIF('GEM data - Upside'!$B:$B,'Chart Data'!$DC23,'GEM data - Upside'!$AA:$AA) -> -1.614367 | EE23: =DX23*DY23 -> 897004.57 | EF23: =DZ23/EA23 -> 9.9743916 | EG23: =EB23 -> 1960500 | EH23: =EC23 -> -1.614367 | EI23: =DW23 -> 1866820.4 | EJ23: =SUMIF('GEM data - Upside'!$B:$B,'Chart Data'!$DC23,'GEM data - Upside'!$F:$F) -> 1940007 | EL23: =100*((EI23/EI22)-1) -> 2.1644809 | EM23: =100*((EJ23/EJ22)-1) -> 4.5243808 | EO23: 2000 | EP23: =SUMIF('GEM data - Zero_net'!$B:$B,'Chart Data'!$DC23,'GEM data - Zero_net'!$U:$U) -> 1866820.4 | EQ23: =AVERAGEIF('GEM data - Zero_net'!$B:$B,'Chart Data'!$DC23,'GEM data - Zero_net'!$V:$V) -> 27515.478 | ER23: =AVERAGEIF('GEM data - Zero_net'!$B:$B,'Chart Data'!$DC23,'GEM data - Zero_net'!$W:$W) -> 32.6 | ES23: =AVERAGEIF('GEM data - Zero_net'!$B:$B,'Chart Data'!$DC23,'GEM data - Zero_net'!$X:$X) -> 383089.93 | ET23: =AVERAGEIF('GEM data - Zero_net'!$B:$B,'Chart Data'!$DC23,'GEM data - Zero_net'!$Y:$Y) -> 38407.347 | EU23: =AVERAGEIF('GEM data - Zero_net'!$B:$B,'Chart Data'!$DC23,'GEM data - Zero_net'!$Z:$Z) -> 1960500 | EV23: =AVERAGEIF('GEM data - Zero_net'!$B:$B,'Chart Data'!$DC23,'GEM data - Zero_net'!$AA:$AA) -> -1.614367 | EX23: =EQ23*ER23 -> 897004.57 | EY23: =ES23/ET23 -> 9.9743916 | EZ23: =EU23 -> 1960500 | FA23: =EV23 -> -1.614367 | FB23: =EP23 -> 1866820.4 | FC23: =SUMIF('GEM data - Zero_net'!$B:$B,'Chart Data'!$DC23,'GEM data - Zero_net'!$F:$F) -> 1940007 | FE23: =100*((FB23/FB22)-1) -> 2.1644809 | FF23: =100*((FC23/FC22)-1) -> 4.5243808
B24: ='GEM data - Baseline'!$F188 -> 705117 | C24: ='GEM data - Upside'!$F188 -> 705117 | D24: ='GEM data - Zero_net'!$F188 -> 705117 | F24: 2021 | G24: ='[2]Chart Data'!M25 -> 251 | M24: =100*(('GEM data - Baseline'!$P188/'GEM data - Baseline'!$P184)-1) -> 0.10790945 | N24: =100*(('GEM data - Upside'!$P188/'GEM data - Upside'!$P184)-1) -> 0.10790945 | O24: =100*(('GEM data - Zero_net'!$P188/'GEM data - Zero_net'!$P184)-1) -> 0.10790945 | Q24: 2041 | R24: =100*(SUMIF('GEM data - Baseline'!$C:$C,'Chart Data'!$Q24,'GEM data - Baseline'!$Q:$Q)/SUMIF('GEM data - Baseline'!$C:$C,'Chart Data'!$Q24,'GEM data - Baseline'!$S:$S)) -> -1.4546319 | S24: =100*(SUMIF('GEM data - Upside'!$C:$C,'Chart Data'!$Q24,'GEM data - Upside'!$Q:$Q)/SUMIF('GEM data - Upside'!$C:$C,'Chart Data'!$Q24,'GEM data - Upside'!$S:$S)) -> -1.1966833 | T24: =100*(SUMIF('GEM data - Zero_net'!$C:$C,'Chart Data'!$Q24,'GEM data - Zero_net'!$Q:$Q)/SUMIF('GEM data - Zero_net'!$C:$C,'Chart Data'!$Q24,'GEM data - Zero_net'!$S:$S)) -> -2.4442593 | V24: 2041 | W24: =100*(SUMIF('GEM data - Baseline'!$D:$D,'Chart Data'!$Q24,'GEM data - Baseline'!$R:$R)/SUMIF('GEM data - Baseline'!$C:$C,'Chart Data'!$Q24,'GEM data - Baseline'!$S:$S)) -> 88.301755 | X24: =100*(SUMIF('GEM data - Upside'!$D:$D,'Chart Data'!$Q24,'GEM data - Upside'!$R:$R)/SUMIF('GEM data - Upside'!$C:$C,'Chart Data'!$Q24,'GEM data - Upside'!$S:$S)) -> 85.697362 | Y24: =100*(SUMIF('GEM data - Zero_net'!$D:$D,'Chart Data'!$Q24,'GEM data - Zero_net'!$R:$R)/SUMIF('GEM data - Zero_net'!$C:$C,'Chart Data'!$Q24,'GEM data - Zero_net'!$S:$S)) -> 97.17538 | AP24: 2021 | AQ24: =AVERAGEIF('GEM data - Baseline'!$B:$B,'Chart Data'!$AP24,'GEM data - Baseline'!$AE:$AE) -> 29.299085 | AR24: =AVERAGEIF('GEM data - Upside'!$B:$B,'Chart Data'!$AP24,'GEM data - Upside'!$AE:$AE) -> 29.299085 | AS24: =AVERAGEIF('GEM data - Zero_net'!$B:$B,'Chart Data'!$AP24,'GEM data - Zero_net'!$AE:$AE) -> 29.299085 | AU24: 2021 | AV24: =AVERAGEIF('GEM data - Baseline'!$B:$B,'Chart Data'!$AP24,'GEM data - Baseline'!AE:AE) -> 29.299085 | AW24: =AVERAGEIF('GEM data - Baseline'!$B:$B,'Chart Data'!$AP24,'GEM data - Baseline'!AF:AF) -> 21.439053 | AX24: =AVERAGEIF('GEM data - Baseline'!$B:$B,'Chart Data'!$AP24,'GEM data - Baseline'!AG:AG) -> 49.744215 | AY24: =AVERAGEIF('GEM data - Baseline'!$B:$B,'Chart Data'!$AP24,'GEM data - Baseline'!AH:AH) -> 33.850192 | AZ24: =AVERAGEIF('GEM data - Baseline'!$B:$B,'Chart Data'!$AP24,'GEM data - Baseline'!AI:AI) -> 32.652895 | BA24: =AVERAGEIF('GEM data - Baseline'!$B:$B,'Chart Data'!$AP24,'GEM data - Baseline'!AJ:AJ) -> 36.405833 | BB24: =AVERAGEIF('GEM data - Baseline'!$B:$B,'Chart Data'!$AP24,'GEM data - Baseline'!AK:AK) -> 22.489377 | BF24: =100*(('GEM data - Baseline'!$F188/'GEM data - Baseline'!$F184)-1) -> 1.4345209 | BG24: =100*(('GEM data - Upside'!$F188/'GEM data - Upside'!$F184)-1) -> 1.4345209 | BH24: =100*(('GEM data - Zero_net'!$F188/'GEM data - Zero_net'!$F184)-1) -> 1.4345209 | BK24: =100*(('GEM data - Baseline'!$U188/'GEM data - Baseline'!$U184)-1) -> 2.367189 | BL24: =100*(('GEM data - Upside'!$U188/'GEM data - Upside'!$U184)-1) -> 2.367189 | BM24: =100*(('GEM data - Zero_net'!$U188/'GEM data - Zero_net'!$U184)-1) -> 2.367189 | BP24: ='GEM data - Baseline'!$O188 -> 4.7 | BQ24: ='GEM data - Upside'!$O188 -> 4.7 | BR24: ='GEM data - Zero_net'!$O188 -> 4.7 | BU24: =100*(('GEM data - Baseline'!$L188/'GEM data - Baseline'!$L184)-1) -> 2.16489 | BV24: =100*(('GEM data - Upside'!$L188/'GEM data - Upside'!$L184)-1) -> 2.16489 | BW24: =100*(('GEM data - Zero_net'!$L188/'GEM data - Zero_net'!$L184)-1) -> 2.16489 | BZ24: ='GEM data - Baseline'!$T188 -> -0.7115364 | CA24: ='GEM data - Upside'!$T188 -> -0.7115364 | CB24: ='GEM data - Zero_net'!$T188 -> -0.7115364 | CE24: ='GEM data - Baseline'!$J188 -> 4.353846 | CF24: ='GEM data - Upside'!$J188 -> 4.353846 | CG24: ='GEM data - Zero_net'!$J188 -> 4.353846 | CJ24: =100*(('GEM data - Baseline'!$I188/'GEM data - Baseline'!$I184)-1) -> 3.4869498 | CK24: =100*(('GEM data - Upside'!$I188/'GEM data - Upside'!$I184)-1) -> 3.4869498 | CL24: =100*(('GEM data - Zero_net'!$I188/'GEM data - Zero_net'!$I184)-1) -> 3.4869498 | CO24: =100*('GEM data - Baseline'!$AB188/'GEM data - Baseline'!$AD188) -> 489.49444 | CP24: =100*('GEM data - Upside'!$AB188/'GEM data - Upside'!$AD188) -> 489.49444 | CQ24: =100*('GEM data - Zero_net'!$AB188/'GEM data - Zero_net'!$AD188) -> 489.49444 | CT24: =100*('GEM data - Baseline'!$AC188/'GEM data - Baseline'!$AD188) -> 398.97103 | CU24: =100*('GEM data - Upside'!$AC188/'GEM data - Upside'!$AD188) -> 398.97103 | CV24: =100*('GEM data - Zero_net'!$AC188/'GEM data - Zero_net'!$AD188) -> 398.97103 | CY24: =100*('GEM data - Baseline'!$F188/'GEM data - Baseline'!$AD188) -> 1014.7466 | CZ24: =100*('GEM data - Upside'!$F188/'GEM data - Upside'!$AD188) -> 1014.7466 | DA24: =100*('GEM data - Zero_net'!$F188/'GEM data - Zero_net'!$AD188) -> 1014.7466 | DC24: 2001 | DD24: =SUMIF('GEM data - Baseline'!$B:$B,'Chart Data'!$DC24,'GEM data - Baseline'!$U:$U) -> 1923900.1 | DE24: =AVERAGEIF('GEM data - Baseline'!$B:$B,'Chart Data'!$DC24,'GEM data - Baseline'!$V:$V) -> 27733.675 | DF24: =AVERAGEIF('GEM data - Baseline'!$B:$B,'Chart Data'!$DC24,'GEM data - Baseline'!$W:$W) -> 32.675 | DG24: =AVERAGEIF('GEM data - Baseline'!$B:$B,'Chart Data'!$DC24,'GEM data - Baseline'!$X:$X) -> 395262.5 | DH24: =AVERAGEIF('GEM data - Baseline'!$B:$B,'Chart Data'!$DC24,'GEM data - Baseline'!$Y:$Y) -> 38667.287 | DI24: =AVERAGEIF('GEM data - Baseline'!$B:$B,'Chart Data'!$DC24,'GEM data - Baseline'!$Z:$Z) -> 2017375 | DJ24: =AVERAGEIF('GEM data - Baseline'!$B:$B,'Chart Data'!$DC24,'GEM data - Baseline'!$AA:$AA) -> -1.6085132 | DL24: =DE24*DF24 -> 906197.83 | DM24: =DG24/DH24 -> 10.222142 | DN24: =DI24 -> 2017375 | DO24: =DJ24 -> -1.6085132 | DP24: =DD24 -> 1923900.1 | DQ24: =SUMIF('GEM data - Baseline'!$B:$B,'Chart Data'!$DC24,'GEM data - Baseline'!$F:$F) -> 1986393 | DS24: =100*((DP24/DP23)-1) -> 3.0575893 | DT24: =100*((DQ24/DQ23)-1) -> 2.3910223 | DV24: 2001 | DW24: =SUMIF('GEM data - Upside'!$B:$B,'Chart Data'!$DC24,'GEM data - Upside'!$U:$U) -> 1923900.1 | DX24: =AVERAGEIF('GEM data - Upside'!$B:$B,'Chart Data'!$DC24,'GEM data - Upside'!$V:$V) -> 27733.675 | DY24: =AVERAGEIF('GEM data - Upside'!$B:$B,'Chart Data'!$DC24,'GEM data - Upside'!$W:$W) -> 32.675 | DZ24: =AVERAGEIF('GEM data - Upside'!$B:$B,'Chart Data'!$DC24,'GEM data - Upside'!$X:$X) -> 395262.5 | EA24: =AVERAGEIF('GEM data - Upside'!$B:$B,'Chart Data'!$DC24,'GEM data - Upside'!$Y:$Y) -> 38667.287 | EB24: =AVERAGEIF('GEM data - Upside'!$B:$B,'Chart Data'!$DC24,'GEM data - Upside'!$Z:$Z) -> 2017375 | EC24: =AVERAGEIF('GEM data - Upside'!$B:$B,'Chart Data'!$DC24,'GEM data - Upside'!$AA:$AA) -> -1.6085132 | EE24: =DX24*DY24 -> 906197.83 | EF24: =DZ24/EA24 -> 10.222142 | EG24: =EB24 -> 2017375 | EH24: =EC24 -> -1.6085132 | EI24: =DW24 -> 1923900.1 | EJ24: =SUMIF('GEM data - Upside'!$B:$B,'Chart Data'!$DC24,'GEM data - Upside'!$F:$F) -> 1986393 | EL24: =100*((EI24/EI23)-1) -> 3.0575893 | EM24: =100*((EJ24/EJ23)-1) -> 2.3910223 | EO24: 2001 | EP24: =SUMIF('GEM data - Zero_net'!$B:$B,'Chart Data'!$DC24,'GEM data - Zero_net'!$U:$U) -> 1923900.1 | EQ24: =AVERAGEIF('GEM data - Zero_net'!$B:$B,'Chart Data'!$DC24,'GEM data - Zero_net'!$V:$V) -> 27733.675 | ER24: =AVERAGEIF('GEM data - Zero_net'!$B:$B,'Chart Data'!$DC24,'GEM data - Zero_net'!$W:$W) -> 32.675 | ES24: =AVERAGEIF('GEM data - Zero_net'!$B:$B,'Chart Data'!$DC24,'GEM data - Zero_net'!$X:$X) -> 395262.5 | ET24: =AVERAGEIF('GEM data - Zero_net'!$B:$B,'Chart Data'!$DC24,'GEM data - Zero_net'!$Y:$Y) -> 38667.287 | EU24: =AVERAGEIF('GEM data - Zero_net'!$B:$B,'Chart Data'!$DC24,'GEM data - Zero_net'!$Z:$Z) -> 2017375 | EV24: =AVERAGEIF('GEM data - Zero_net'!$B:$B,'Chart Data'!$DC24,'GEM data - Zero_net'!$AA:$AA) -> -1.6085132 | EX24: =EQ24*ER24 -> 906197.83 | EY24: =ES24/ET24 -> 10.222142 | EZ24: =EU24 -> 2017375 | FA24: =EV24 -> -1.6085132 | FB24: =EP24 -> 1923900.1 | FC24: =SUMIF('GEM data - Zero_net'!$B:$B,'Chart Data'!$DC24,'GEM data - Zero_net'!$F:$F) -> 1986393 | FE24: =100*((FB24/FB23)-1) -> 3.0575893 | FF24: =100*((FC24/FC23)-1) -> 2.3910223
