Workbook
Name _DLX1.INC: HAVERM!$A$4:$AC$10
Name _DLX2.INC: HAVERQ!$A$4:$AU$10

Sheet Data >>

Sheet BB consensus
B1: Headline CPI >> | G1: Core CPI >> | L1: Services CPI >>
A3: Date | B3: Outturn | C3: Consensus median | D3: Absolute error | G3: Outturn | H3: Consensus median | I3: Absolute error | L3: Date | M3: Outturn | N3: Consensus median | O3: Absolute error
A4: 43861 | B4: 1.8 | C4: 1.6 | D4: =ABS(B4-C4) -> 0.2 | G4: 1.6 | H4: 1.5 | I4: =ABS(G4-H4) -> 0.1 | L4: 45199 | M4: 6.9 | N4: 6.8 | O4: =ABS(M4-N4) -> 0.1
A5: 43890 | B5: 1.7 | C5: 1.7 | D5: =ABS(B5-C5) -> 0 | G5: 1.7 | H5: 1.5 | I5: =ABS(G5-H5) -> 0.2 | L5: 45230 | M5: 6.6 | N5: 6.7 | O5: =ABS(M5-N5) -> 0.1
A6: 43921 | B6: 1.5 | C6: 1.5 | D6: =ABS(B6-C6) -> 0 | G6: 1.6 | H6: 1.6 | I6: =ABS(G6-H6) -> 0 | L6: 45260 | M6: 6.3 | N6: 6.6 | O6: =ABS(M6-N6) -> 0.3
A7: 43951 | B7: 0.8 | C7: 0.9 | D7: =ABS(B7-C7) -> 0.1 | G7: 1.4 | H7: 1.4 | I7: =ABS(G7-H7) -> 0 | L7: 45291 | M7: 6.4 | N7: 6.1 | O7: =ABS(M7-N7) -> 0.3
A8: 43982 | B8: 0.5 | C8: 0.5 | D8: =ABS(B8-C8) -> 0 | G8: 1.2 | H8: 1.3 | I8: =ABS(G8-H8) -> 0.1 | L8: 45322 | M8: 6.5 | N8: 6.8 | O8: =ABS(M8-N8) -> 0.3
A9: 44012 | B9: 0.6 | C9: 0.4 | D9: =ABS(B9-C9) -> 0.2 | G9: 1.4 | H9: 1.2 | I9: =ABS(G9-H9) -> 0.2 | L9: 45351 | M9: 6.1 | N9: 6 | O9: =ABS(M9-N9) -> 0.1
A10: 44043 | B10: 1 | C10: 0.6 | D10: =ABS(B10-C10) -> 0.4 | G10: 1.8 | H10: 1.2 | I10: =ABS(G10-H10) -> 0.6 | L10: 45382 | M10: 6 | N10: 5.8 | O10: =ABS(M10-N10) -> 0.2
A11: 44074 | B11: 0.2 | C11: 0 | D11: =ABS(B11-C11) -> 0.2 | G11: 0.9 | H11: 0.5 | I11: =ABS(G11-H11) -> 0.4 | L11: 45412 | M11: 5.9 | N11: 5.4 | O11: =ABS(M11-N11) -> 0.5
A12: 44104 | B12: 0.5 | C12: 0.6 | D12: =ABS(B12-C12) -> 0.1 | G12: 1.3 | H12: 1.3 | I12: =ABS(G12-H12) -> 0 | L12: 45443 | M12: 5.7 | N12: 5.5 | O12: =ABS(M12-N12) -> 0.2
A13: 44135 | B13: 0.7 | C13: 0.5 | D13: =ABS(B13-C13) -> 0.2 | G13: 1.5 | H13: 1.3 | I13: =ABS(G13-H13) -> 0.2 | L13: 45473 | M13: 5.7 | N13: 5.6 | O13: =ABS(M13-N13) -> 0.1
A14: 44165 | B14: 0.3 | C14: 0.6 | D14: =ABS(B14-C14) -> 0.3 | G14: 1.1 | H14: 1.4 | I14: =ABS(G14-H14) -> 0.3 | L14: 45504 | M14: 5.2 | N14: 5.5 | O14: =ABS(M14-N14) -> 0.3
A15: 44196 | B15: 0.6 | C15: 0.5 | D15: =ABS(B15-C15) -> 0.1 | G15: 1.4 | H15: 1.3 | I15: =ABS(G15-H15) -> 0.1 | L15: 45535 | M15: 5.6 | N15: 5.6 | O15: =ABS(M15-N15) -> 0
... A32: 44712 | B32: 9.1 | C32: 9.1 | D32: =ABS(B32-C32) -> 0 | G32: 5.9 | H32: 6 | I32: =ABS(G32-H32) -> 0.1 | L32: 46053 | M32: 4.4 | N32: 4.2 | O32: =ABS(M32-N32) -> 0.2
A33: 44742 | B33: 9.4 | C33: 9.3 | D33: =ABS(B33-C33) -> 0.1 | G33: 5.8 | H33: 5.8 | I33: =ABS(G33-H33) -> 0
A34: 44773 | B34: 10.1 | C34: 9.8 | D34: =ABS(B34-C34) -> 0.3 | G34: 6.2 | H34: 5.9 | I34: =ABS(G34-H34) -> 0.3
A35: 44804 | B35: 9.9 | C35: 10 | D35: =ABS(B35-C35) -> 0.1 | G35: 6.3 | H35: 6.2 | I35: =ABS(G35-H35) -> 0.1
A36: 44834 | B36: 10.1 | C36: 10 | D36: =ABS(B36-C36) -> 0.1 | G36: 6.5 | H36: 6.4 | I36: =ABS(G36-H36) -> 0.1
A37: 44865 | B37: 11.1 | C37: 10.7 | D37: =ABS(B37-C37) -> 0.4 | G37: 6.5 | H37: 6.4 | I37: =ABS(G37-H37) -> 0.1
A38: 44895 | B38: 10.7 | C38: 10.9 | D38: =ABS(B38-C38) -> 0.2 | G38: 6.3 | H38: 6.5 | I38: =ABS(G38-H38) -> 0.2
A39: 44926 | B39: 10.5 | C39: 10.5 | D39: =ABS(B39-C39) -> 0 | G39: 6.3 | H39: 6.2 | I39: =ABS(G39-H39) -> 0.1
A40: 44957 | B40: 10.1 | C40: 10.3 | D40: =ABS(B40-C40) -> 0.2 | G40: 5.8 | H40: 6.2 | I40: =ABS(G40-H40) -> 0.4
A41: 44985 | B41: 10.4 | C41: 9.9 | D41: =ABS(B41-C41) -> 0.5 | G41: 6.2 | H41: 5.7 | I41: =ABS(G41-H41) -> 0.5
A42: 45016 | B42: 10.1 | C42: 9.8 | D42: =ABS(B42-C42) -> 0.3 | G42: 6.2 | H42: 6 | I42: =ABS(G42-H42) -> 0.2
A43: 45046 | B43: 8.7 | C43: 8.2 | D43: =ABS(B43-C43) -> 0.5 | G43: 6.8 | H43: 6.2 | I43: =ABS(G43-H43) -> 0.6
A44: 45077 | B44: 8.7 | C44: 8.4 | D44: =ABS(B44-C44) -> 0.3 | G44: 7.1 | H44: 6.8 | I44: =ABS(G44-H44) -> 0.3
... A76: 46053 | B76: 3 | C76: 3 | D76: =ABS(B76-C76) -> 0 | G76: 3.1 | H76: 3 | I76: =ABS(G76-H76) -> 0.1

Sheet HAVERM
A4: 200001 !M | B4: D7BT@UK
A5: .DESC | B5: UK: Consumer Price Index: All Items (NSA, 2015=100)
A6: .T1 | B6: Jan-1988
A7: .TN | B7: Dec-2025
A8: .LSOURCE | B8: Office for National Statistics
A9: .DTLM | B9: Jan-21-2026 07:02
A10: .FRQ | B10: Monthly
A11: 200001 | B11: 71.9
A12: 200002 | B12: 72.2
A13: 200003 | B13: 72.3
A14: 200004 | B14: 72.6
A15: 200005 | B15: 72.8
A16: 200006 | B16: 72.9
A17: 200007 | B17: 72.5
A18: 200008 | B18: 72.5
A19: 200009 | B19: 73.1
A20: 200010 | B20: 73.1
A21: 200011 | B21: 73.2
A22: 200012 | B22: 73.2
... A322: 202512 | B322: 140.1

Sheet HAVERQ
A4: 20001 !Q | B4: UNCPI261@UK
A5: .DESC | B5: UK: BoE MPR Bank Staff Projections: CPI [Feb-26] (Y/Y % Change)
A6: .T1 | B6: Q1-2004
A7: .TN | B7: Q1-2029
A8: .LSOURCE | B8: Discontinued
A9: .DTLM | B9: Feb-05-2026 16:39
A10: .FRQ | B10: Quarterly
A11: 20001 | B11: #N/A
A12: 20002 | B12: #N/A
A13: 20003 | B13: #N/A
A14: 20004 | B14: #N/A
A15: 20011 | B15: #N/A
A16: 20012 | B16: #N/A
A17: 20013 | B17: #N/A
A18: 20014 | B18: #N/A
A19: 20021 | B19: #N/A
A20: 20022 | B20: #N/A
A21: 20023 | B21: #N/A
A22: 20024 | B22: #N/A
... A26: 20034 | B26: #N/A
A27: 20041 | B27: 1.3
A28: 20042 | B28: 1.4
A29: 20043 | B29: 1.3
A30: 20044 | B30: 1.4
A31: 20051 | B31: 1.7
A32: 20052 | B32: 2
A33: 20053 | B33: 2.4
A34: 20054 | B34: 2.1
A35: 20061 | B35: 1.9
A36: 20062 | B36: 2.3
A37: 20063 | B37: 2.4
A38: 20064 | B38: 2.7
... A127: 20291 | B127: 2

Sheet Calculations >>

Sheet Chart data
A1: April forecast errors >> | I1: CPI inflation forecasts >> | P1: Energy price cap >>
A4: Headline | B4: April outturn | C4: April consensus | D4: April absolute error | E4: Average error (excl April) | I4: Date | J4: CPI inflation | K4: Oxford Economics (Feb-26) | L4: Bank of England (Feb-26) | M4: 2% line | Q4: Wholesale gas & electricity | R4: Network costs | S4: Operating costs | T4: Policy | U4: VAT | V4: Other | X4: Check
A5: 2020 | B5: ='BB consensus'!B7 -> 0.8 | C5: ='BB consensus'!C7 -> 0.9 | D5: =ABS(B5-C5) -> 0.1 | E5: =AVERAGE('BB consensus'!D4:D6,'BB consensus'!D8:D15) -> 0.15454545 | F5: =D5/E5 -> 0.64705882 | I5: 45292 | J5: =HAVERQ!B107 -> 3.5 | M5: 2 | P5: 45658 | Q5: ='[1]EPC calculation'!C20 -> 755 | R5: ='[1]EPC calculation'!F20 -> 370 | S5: ='[1]EPC calculation'!G20 -> 276 | T5: ='[1]EPC calculation'!K20 -> 187 | U5: ='[1]EPC calculation'!P20 -> 81.8 | V5: =SUM('[1]EPC calculation'!L20:O20) -> 68 | X5: =SUM(Q5:V5) -> 1737.8
A6: 2021 | B6: ='BB consensus'!B19 -> 1.5 | C6: ='BB consensus'!C19 -> 1.5 | D6: =ABS(B6-C6) -> 0 | E6: =AVERAGE('BB consensus'!D16:D18,'BB consensus'!D20:D27) -> 0.24545455 | F6: =D6/E6 -> 0 | I6: 45383 | J6: =HAVERQ!B108 -> 2.1 | M6: 2 | P6: 45748 | Q6: ='[1]EPC calculation'!C21 -> 841 | R6: ='[1]EPC calculation'!F21 -> 372 | S6: ='[1]EPC calculation'!G21 -> 279 | T6: ='[1]EPC calculation'!K21 -> 198 | U6: ='[1]EPC calculation'!P21 -> 88.05 | V6: =SUM('[1]EPC calculation'!L21:O21) -> 71 | X6: =SUM(Q6:V6) -> 1849.05
A7: 2022 | B7: ='BB consensus'!B31 -> 9 | C7: ='BB consensus'!C31 -> 9.1 | D7: =ABS(B7-C7) -> 0.1 | E7: =AVERAGE('BB consensus'!D28:D30,'BB consensus'!D32:D39) -> 0.16363636 | F7: =D7/E7 -> 0.61111111 | I7: 45474 | J7: =HAVERQ!B109 -> 2 | M7: 2 | P7: 45839 | Q7: ='[1]EPC calculation'!C22 -> 734 | R7: ='[1]EPC calculation'!F22 -> 372 | S7: ='[1]EPC calculation'!G22 -> 264 | T7: ='[1]EPC calculation'!K22 -> 198 | U7: ='[1]EPC calculation'!P22 -> 82.85 | V7: =SUM('[1]EPC calculation'!L22:O22) -> 69 | X7: =SUM(Q7:V7) -> 1719.85
A8: 2023 | B8: ='BB consensus'!B43 -> 8.7 | C8: ='BB consensus'!C43 -> 8.2 | D8: =ABS(B8-C8) -> 0.5 | E8: =AVERAGE('BB consensus'!D40:D42,'BB consensus'!D44:D51) -> 0.25454545 | F8: =D8/E8 -> 1.9642857 | I8: 45566 | J8: =HAVERQ!B110 -> 2.5 | M8: 2 | P8: 45931 | Q8: ='[1]EPC calculation'!C23 -> 720 | R8: ='[1]EPC calculation'!F23 -> 396 | S8: ='[1]EPC calculation'!G23 -> 270 | T8: ='[1]EPC calculation'!K23 -> 215 | U8: ='[1]EPC calculation'!P23 -> 83.55 | V8: =SUM('[1]EPC calculation'!L23:O23) -> 70 | X8: =SUM(Q8:V8) -> 1754.55
A9: 2024 | B9: ='BB consensus'!B67 -> 3.5 | C9: ='BB consensus'!C67 -> 3.3 | D9: =ABS(B9-C9) -> 0.2 | E9: =AVERAGE('BB consensus'!D52:D54,'BB consensus'!D56:D63) -> 0.081818182 | F9: =D9/E9 -> 2.4444444 | I9: 45658 | J9: =HAVERQ!B111 -> 2.8 | M9: 2 | P9: 46023 | Q9: ='[1]EPC calculation'!C24 -> 690 | R9: ='[1]EPC calculation'!F24 -> 397 | S9: ='[1]EPC calculation'!G24 -> 279 | T9: ='[1]EPC calculation'!K24 -> 236 | U9: ='[1]EPC calculation'!P24 -> 83.7 | V9: =SUM('[1]EPC calculation'!L24:O24) -> 72 | X9: =SUM(Q9:V9) -> 1757.7
A10: 2025 | B10: ='BB consensus'!B67 -> 3.5 | C10: ='BB consensus'!C67 -> 3.3 | D10: =ABS(B10-C10) -> 0.2 | E10: =AVERAGE('BB consensus'!D64:D66,'BB consensus'!D68:D76) -> 0.13333333 | F10: =D10/E10 -> 1.5 | I10: 45748 | J10: =HAVERQ!B112 -> 3.5 | M10: 2 | P10: 46113 | Q10: ='[1]EPC calculation'!C25 -> 652 | R10: ='[1]EPC calculation'!F25 -> 463 | S10: ='[1]EPC calculation'!G25 -> 274 | T10: ='[1]EPC calculation'!K25 -> 106 | U10: ='[1]EPC calculation'!P25 -> 79.1 | V10: =SUM('[1]EPC calculation'!L25:O25) -> 67 | X10: =SUM(Q10:V10) -> 1641.1
I11: 45839 | J11: =HAVERQ!B113 -> 3.8 | M11: 2
I12: 45931 | J12: =HAVERQ!B114 -> 3.4 | K12: ='[2]CPI Forecast'!D608 -> 3.3933356 | L12: =HAVERQ!B114 -> 3.4 | M12: 2 | P12: Apr-26 change | Q12: =Q10-Q9 -> -38 | R12: =R10-R9 -> 66 | S12: =S10-S9 -> -5 | T12: =T10-T9 -> -130 | U12: =U10-U9 -> -4.6 | V12: =V10-V9 -> -5 | X12: =X10-X9 -> -116.6
A13: Core | B13: April outturn | C13: April consensus | D13: April absolute error | E13: Average error (excl April) | I13: 46023 | K13: ='[2]CPI Forecast'!D609 -> 2.9787965 | L13: =HAVERQ!B115 -> 3 | M13: 2
A14: 2020 | B14: ='BB consensus'!G7 -> 1.4 | C14: ='BB consensus'!H7 -> 1.4 | D14: =ABS(B14-C14) -> 0 | E14: =AVERAGE('BB consensus'!I4:I6,'BB consensus'!I8:I15) -> 0.2 | F14: =D14/E14 -> 0 | I14: 46113 | K14: ='[2]CPI Forecast'!D610 -> 2.3078119 | L14: =HAVERQ!B116 -> 2.1 | M14: 2
A15: 2021 | B15: ='BB consensus'!G19 -> 1.3 | C15: ='BB consensus'!H19 -> 1.3 | D15: =ABS(B15-C15) -> 0 | E15: =AVERAGE('BB consensus'!I16:I18,'BB consensus'!I20:I27) -> 0.25454545 | F15: =D15/E15 -> 0 | I15: 46204 | K15: ='[2]CPI Forecast'!D611 -> 2.4838163 | L15: =HAVERQ!B117 -> 2 | M15: 2
A16: 2022 | B16: ='BB consensus'!G31 -> 6.2 | C16: ='BB consensus'!H31 -> 6.2 | D16: =ABS(B16-C16) -> 0 | E16: =AVERAGE('BB consensus'!I28:I30,'BB consensus'!I32:I39) -> 0.15454545 | F16: =D16/E16 -> 0 | I16: 46296 | K16: ='[2]CPI Forecast'!D612 -> 2.6488056 | L16: =HAVERQ!B118 -> 2 | M16: 2
A17: 2023 | B17: ='BB consensus'!G43 -> 6.8 | C17: ='BB consensus'!H43 -> 6.2 | D17: =ABS(B17-C17) -> 0.6 | E17: =AVERAGE('BB consensus'!I40:I42,'BB consensus'!I44:I51) -> 0.29090909 | F17: =D17/E17 -> 2.0625 | I17: 46388 | K17: ='[2]CPI Forecast'!D613 -> 2.6396296 | L17: =HAVERQ!B119 -> 1.7 | M17: 2
A18: 2024 | B18: ='BB consensus'!G67 -> 3.8 | C18: ='BB consensus'!H67 -> 3.6 | D18: =ABS(B18-C18) -> 0.2 | E18: =AVERAGE('BB consensus'!I52:I54,'BB consensus'!I56:I63) -> 0.10909091 | F18: =D18/E18 -> 1.8333333 | I18: 46478 | K18: ='[2]CPI Forecast'!D614 -> 2.6822886 | L18: =HAVERQ!B120 -> 2 | M18: 2
A19: 2025 | B19: ='BB consensus'!G67 -> 3.8 | C19: ='BB consensus'!H67 -> 3.6 | D19: =ABS(B19-C19) -> 0.2 | E19: =AVERAGE('BB consensus'!I64:I66,'BB consensus'!I68:I76) -> 0.083333333 | F19: =D19/E19 -> 2.4 | I19: 46569 | K19: ='[2]CPI Forecast'!D615 -> 2.5150682 | L19: =HAVERQ!B121 -> 1.9 | M19: 2
I20: 46661 | K20: ='[2]CPI Forecast'!D616 -> 2.3760329 | L20: =HAVERQ!B122 -> 1.8 | M20: 2
I21: 46753 | K21: ='[2]CPI Forecast'!D617 -> 2.3475678 | L21: =HAVERQ!B123 -> 1.8 | M21: 2
B22: April | C22: Average month (excl. April) | I22: 46844 | K22: ='[2]CPI Forecast'!D618 -> 2.1051675 | L22: =HAVERQ!B124 -> 2 | M22: 2
A23: 2023 | B23: =D8 -> 0.5 | C23: =E8 -> 0.25454545 | I23: 46935 | K23: ='[2]CPI Forecast'!D619 -> 2.1499042 | L23: =HAVERQ!B125 -> 2 | M23: 2
A24: 2024 | B24: =D9 -> 0.2 | C24: =E9 -> 0.081818182 | I24: 47027 | K24: ='[2]CPI Forecast'!D620 -> 2.1824155 | L24: =HAVERQ!B126 -> 2 | M24: 2
A25: 2025 | B25: =D10 -> 0.2 | C25: =E10 -> 0.13333333
B27: April core CPI error | C27: Non-April services CPI error
A28: 2023 | B28: =D17 -> 0.6 | C28: =E17 -> 0.29090909
A29: 2024 | B29: =D18 -> 0.2 | C29: =E18 -> 0.10909091
A30: 2025 | B30: =D19 -> 0.2 | C30: =E19 -> 0.083333333

Sheet Charts >>
