Workbook
Name _DLX1.INC: HAVERM!$A$1:$G$6
Name _DLX2.INC: HAVERQ!$A$1:$E$6
Name Data: [1]sheet0!$C$2

Sheet CHARTS>>

Sheet DATA>>

Sheet Chart Data
A1: Potential output | L1: Net inward migration | R1: Population | Y1: Components of net inflows | AE1: Inflows aggregated | AN1: Inflows | BV1: Outflows aggregated | CE1: Outfflows | DM1: GDP forecast comparison | DT1: Working age population | EA1: Inactivity | EH1: Age profile of population | FW1: Output per worker long-term (5yr ma) | GL1: OBR YHAT calculations | GZ1: GDP forecasts - LT (2023=100)
AO2: Total | BC2: EU+ | BK2: Non-EU+ | CF2: Total | CI2: Total | CT2: EU+ | DB2: Non-EU+ | DU2: Working age population (LHS) | DX2: State pension age - males (RHS) | DY2: State pension age - females (RHS) | EE2: Levels | GM2: Baseline - growth | GP2: Baseline - levels | GT2: New OBR | HF2: growth rates
B3: ESTAR * AVHR | C3: EDUC / POP15_64 | D3: K | E3: TREND | F3: YHAT | G3: GDP | I3: Potential output | J3: GDP | M3: OE (Feb26) | N3: ONS principal projection (Jan25) | O3: ONS migration category variant (Jan25) | P3: OBR (Nov25) | S3: OE (Feb26) | T3: ONS principal projection (Jan25) | U3: ONS migration category variant (Jan25) | V3: OBR (Nov25) | W3: OBR Fys | Z3: Inflows | AA3: Outflows | AB3: Net inflows | AC3: Net inflows check | AF3: Work | AG3: Study | AH3: Dependents | AI3: Family | AJ3: British | AK3: Other | AL3: check | AO3: Brit+EU++Non-eu+ | AP3: Other | AQ3: British | AR3: All reasons | AS3: Work: Main applicant | AT3: Work: Dependant | AU3: Study: Main applicant | AV3: Study: Dependant | AW3: Family | AX3: Humanitarian | AY3: Asylum | AZ3: Other | BA3: check | BC3: All reasons | BD3: Work: Main applicant | BE3: Work: Dependant | BF3: Study: Main applicant | BG3: Study: Dependant | BH3: Family | BI3: check | BK3: All reasons | BL3: Work: Main applicant | BM3: Work: Dependant | BN3: Study: Main applicant | BO3: Study: Dependant | BP3: Family | BQ3: Humanitarian | BR3: Asylum | BS3: Other | BT3: check | BW3: Work | BX3: Study | BY3: Dependents | BZ3: Family | CA3: British | CB3: Other | CC3: check | CF3: Brit+EU++Non-eu+ | CG3: Other | CH3: British | CI3: All reasons | CJ3: Work: Main applicant | CK3: Work: Dependant | CL3: Study: Main applicant | CM3: Study: Dependant | CN3: Family | CO3: Humanitarian | CP3: Asylum | CQ3: Other | CR3: check | CT3: All reasons | CU3: Work: Main applicant | CV3: Work: Dependant | CW3: Study: Main applicant | CX3: Study: Dependant | CY3: Family | CZ3: check | DB3: All reasons | DC3: Work: Main applicant | DD3: Work: Dependant | DE3: Study: Main applicant | DF3: Study: Dependant | DG3: Family | DH3: Humanitarian | DI3: Asylum | DJ3: Other | DK3: check | DN3: OE | DO3: OBR | DP3: Consensus | DQ3: Consensus low | DR3: Consensus range | DU3: Working age population | DV3: Rolling 10 year average | DW3: ZERO LINE | DX3: State pension age - males | DY3: State pension age - females | EB3: % of inactive | EC3: Average 1993-2025 | EE3: LT sick | EF3: Other | EI3: 2022 | EJ3: 2023 | EK3: 2024 | EL3: 2025 | EM3: 2026 | EN3: 2027 | EO3: 2028 | EP3: 2029 | EQ3: 2030 | ER3: 2031 | ES3: 2032 | ET3: 2033 | EU3: 2034 | EV3: 2035 | EW3: 2036 | EX3: 2037 | EY3: 2038 | EZ3: 2039 | FA3: 2040 | FB3: 2041 | FC3: 2042 | FD3: 2043 | FE3: 2044 | FF3: 2045 | FG3: 2046 | FH3: 2047 | FI3: 2048 | FJ3: 2049 | FK3: 2050 | FL3: 2051 | FM3: 2052 | FN3: 2053 | FO3: 2054 | FP3: 2055 | FQ3: 2056 | FR3: 2057 | FS3: 2058 | FT3: 2059 | FU3: 2060 | FX3: 5-year moving average | FY3: 10-year moving average | FZ3: 1970-2007 average | GA3: 2008-2019 average | GD3: Pre-GFC trend calc | GG3: GFC-pandemic | GJ3: Pandemic-now | GM3: Potential pop | GN3: potential output | GP3: Potential pop | GQ3: potential output | GR3: Migrants diff | GS3: 16+ pop diff | GT3: Potential pop | GU3: Potential pop | GV3: potential output | GW3: potential output | GX3: YHAT diff | HA3: OE | HB3: OBR | HD3: Difference | HF3: OBR
A4: 1980 | B4: =Data!F14*Data!G14 -> 24.76553 | C4: =Data!H14/Data!I14 -> 8.4961659 | D4: =Data!E14 -> 1238528 | E4: =Data!J14 -> -1.827207 | F4: =Data!D14 -> 1164663 | G4: =Data!B14 -> 1140989 | L4: 2000 | M4: ='[2]2022-based'!L7 -> 139.3 | R4: 2020 | S4: ='[2]2022-based'!Q27 -> 66739.867 | Y4: 2012 | Z4: =SUMIF('ONS Nov25 T1'!$L:$L,'Chart Data'!$Y4,'ONS Nov25 T1'!$C:$C)/1000 -> 639 | AA4: =SUMIF('ONS Nov25 T1'!$M:$M,'Chart Data'!$Y4,'ONS Nov25 T1'!$C:$C)/1000 -> 477 | AB4: =SUMIF('ONS Nov25 T1'!$N:$N,'Chart Data'!$Y4,'ONS Nov25 T1'!$C:$C)/1000 -> 162 | AC4: =Z4-AA4 -> 162 | AE4: 2021 | AF4: =AS4 -> 59 | AG4: =AU4 -> 115 | AH4: =AT4+AV4 -> 59 | AI4: =AW4 -> 64 | AJ4: =AQ4 -> 74 | AK4: =AP4+AX4+AY4+AZ4 -> 447 | AL4: =AO4-SUM(AF4:AK4) -> 0 | AN4: 2021 | AO4: =+AP4+AQ4+AR4 -> 818 | AP4: =Z13-AQ4-AR4 -> 376 | AQ4: =SUMIF('ONS Nov25 T1'!$L:$L,'Chart Data'!$Y4,'ONS Nov25 T1'!$D:$D)/1000 -> 74 | AR4: =BC4+BK4 -> 368 | AS4: =BD4+BL4 -> 59 | AT4: =BE4+BM4 -> 41 | AU4: =BF4+BN4 -> 115 | AV4: =BG4+BO4 -> 18 | AW4: =BH4+BP4 -> 64 | AX4: =BQ4 -> 10 | AY4: =BR4 -> 36 | AZ4: =BS4 -> 25 | BA4: =AR4-AS4-AT4-AU4-AV4-AW4-AX4-AY4-AZ4 -> 0 | BC4: =SUMIF('ONS Nov25 T4a'!$P:$P,'Chart Data'!$AN4,'ONS Nov25 T4a'!C:C)/1000 -> 5 | BD4: =SUMIF('ONS Nov25 T4a'!$P:$P,'Chart Data'!$AN4,'ONS Nov25 T4a'!E:E)/1000 -> 4 | BE4: =SUMIF('ONS Nov25 T4a'!$P:$P,'Chart Data'!$AN4,'ONS Nov25 T4a'!F:F)/1000 -> 0 | BF4: =SUMIF('ONS Nov25 T4a'!$P:$P,'Chart Data'!$AN4,'ONS Nov25 T4a'!H:H)/1000 -> 0 | BG4: =SUMIF('ONS Nov25 T4a'!$P:$P,'Chart Data'!$AN4,'ONS Nov25 T4a'!I:I)/1000 -> 0 | BH4: =SUMIF('ONS Nov25 T4a'!$P:$P,'Chart Data'!$AN4,'ONS Nov25 T4a'!J:J)/1000 -> 0 | BI4: =BC4-BD4-BE4-BF4-BG4-BH4 -> 1 | BK4: =SUMIF('ONS Nov25 T4b'!$S:$S,'Chart Data'!$AN4,'ONS Nov25 T4b'!C:C)/1000 -> 363 | BL4: =SUMIF('ONS Nov25 T4b'!$S:$S,'Chart Data'!$AN4,'ONS Nov25 T4b'!E:E)/1000 -> 55 | BM4: =SUMIF('ONS Nov25 T4b'!$S:$S,'Chart Data'!$AN4,'ONS Nov25 T4b'!F:F)/1000 -> 41 | BN4: =SUMIF('ONS Nov25 T4b'!$S:$S,'Chart Data'!$AN4,'ONS Nov25 T4b'!H:H)/1000 -> 115 | BO4: =SUMIF('ONS Nov25 T4b'!$S:$S,'Chart Data'!$AN4,'ONS Nov25 T4b'!I:I)/1000 -> 18 | BP4: =SUMIF('ONS Nov25 T4b'!$S:$S,'Chart Data'!$AN4,'ONS Nov25 T4b'!J:J)/1000 -> 64 | BQ4: =SUMIF('ONS Nov25 T4b'!$S:$S,'Chart Data'!$AN4,'ONS Nov25 T4b'!K:K)/1000 -> 10 | BR4: =SUMIF('ONS Nov25 T4b'!$S:$S,'Chart Data'!$AN4,'ONS Nov25 T4b'!O:O)/1000 -> 36 | BS4: =SUMIF('ONS Nov25 T4b'!$S:$S,'Chart Data'!$AN4,'ONS Nov25 T4b'!P:P)/1000 -> 25 | BT4: =BK4-BL4-BM4-BN4-BO4-BP4-BQ4-BR4-BS4 -> -1 | BV4: 2021 | BW4: =CJ4 -> 24 | BX4: =CL4 -> 69 | BY4: =CK4+CM4 -> 16 | BZ4: =CN4 -> 9 | CA4: =CH4 -> 262 | CB4: =CG4+CO4+CP4+CQ4 -> 187 | CC4: =CF4-SUM(BW4:CB4) -> 0 | CE4: 2021 | CF4: =CG4+CH4+CI4 -> 567 | CG4: =AA13-CH4-CI4 -> 185 | CH4: =SUMIF('ONS Nov25 T1'!$M:$M,'Chart Data'!$CE4,'ONS Nov25 T1'!$D:$D)/1000 -> 262 | CI4: =CT4+DB4 -> 120 | CJ4: =CU4+DC4 -> 24 | CK4: =CV4+DD4 -> 12 | CL4: =CW4+DE4 -> 69 | CM4: =CX4+DF4 -> 4 | CN4: =CY4+DG4 -> 9 | CO4: =DH4 -> 0 | CP4: =DI4 -> 0 | CQ4: =DJ4 -> 2 | CR4: =CI4-CJ4-CK4-CL4-CM4-CN4-CO4-CP4-CQ4 -> 0 | CT4: =SUMIF('ONS Nov25 T4a'!$Q:$Q,'Chart Data'!$CE4,'ONS Nov25 T4a'!C:C)/1000 -> 0 | CU4: =SUMIF('ONS Nov25 T4a'!$Q:$Q,'Chart Data'!$CE4,'ONS Nov25 T4a'!E:E)/1000 -> 0 | CV4: =SUMIF('ONS Nov25 T4a'!$Q:$Q,'Chart Data'!$CE4,'ONS Nov25 T4a'!F:F)/1000 -> 0 | CW4: =SUMIF('ONS Nov25 T4a'!$Q:$Q,'Chart Data'!$CE4,'ONS Nov25 T4a'!H:H)/1000 -> 0 | CX4: =SUMIF('ONS Nov25 T4a'!$Q:$Q,'Chart Data'!$CE4,'ONS Nov25 T4a'!I:I)/1000 -> 0 | CY4: =SUMIF('ONS Nov25 T4a'!$Q:$Q,'Chart Data'!$CE4,'ONS Nov25 T4a'!J:J)/1000 -> 0 | CZ4: =CT4-CU4-CV4-CW4-CX4-CY4 -> 0 | DB4: =SUMIF('ONS Nov25 T4b'!$T:$T,'Chart Data'!$CE4,'ONS Nov25 T4b'!C:C)/1000 -> 120 | DC4: =SUMIF('ONS Nov25 T4b'!$T:$T,'Chart Data'!$CE4,'ONS Nov25 T4b'!E:E)/1000 -> 24 | DD4: =SUMIF('ONS Nov25 T4b'!$T:$T,'Chart Data'!$CE4,'ONS Nov25 T4b'!F:F)/1000 -> 12 | DE4: =SUMIF('ONS Nov25 T4b'!$T:$T,'Chart Data'!$AN4,'ONS Nov25 T4b'!H:H)/1000 -> 69 | DF4: =SUMIF('ONS Nov25 T4b'!$T:$T,'Chart Data'!$AN4,'ONS Nov25 T4b'!I:I)/1000 -> 4 | DG4: =SUMIF('ONS Nov25 T4b'!$T:$T,'Chart Data'!$AN4,'ONS Nov25 T4b'!J:J)/1000 -> 9 | DH4: =SUMIF('ONS Nov25 T4b'!$T:$T,'Chart Data'!$AN4,'ONS Nov25 T4b'!K:K)/1000 -> 0 | DI4: =SUMIF('ONS Nov25 T4b'!$T:$T,'Chart Data'!$AN4,'ONS Nov25 T4b'!O:O)/1000 -> 0 | DJ4: =SUMIF('ONS Nov25 T4b'!$T:$T,'Chart Data'!$AN4,'ONS Nov25 T4b'!P:P)/1000 -> 2 | DK4: =DB4-DC4-DD4-DE4-DF4-DG4-DH4-DI4-DJ4 -> 0 | DM4: 2024 | DN4: =100*(Data!B58/Data!$B$58) -> 100 | DO4: =100*('OBR Nov25 ST1.1'!R114/'OBR Nov25 ST1.1'!$R$114) -> 100 | DP4: ='OBR Nov25 C2.25'!M26 -> 100 | DQ4: ='OBR Nov25 C2.25'!N26 -> 100 | DR4: ='OBR Nov25 C2.25'!O26-'Chart Data'!DQ4 -> 0 | DT4: 1974 | DU4: =100*((Data!M8/Data!M7)-1) -> 0.028023783 | DW4: 0 | DX4: 65 | DY4: 60 | EA4: 33970 | EC4: =AVERAGE($EB$7:$EB$399) -> 25.050854 | EH4: 0-15 | EI4: =100*(EI10/EI$13) -> 18.338943 | EJ4: =100*(EJ10/EJ$13) -> 18.100138 | EK4: =100*(EK10/EK$13) -> 17.821261 | EL4: =100*(EL10/EL$13) -> 17.56445 | EM4: =100*(EM10/EM$13) -> 17.309362 | EN4: =100*(EN10/EN$13) -> 17.047745 | EO4: =100*(EO10/EO$13) -> 16.794473 | EP4: =100*(EP10/EP$13) -> 16.572539 | ... FU4: =100*(FU10/FU$13) -> 14.452173 | FW4: 1960 | GC4: 1970 | GD4: =AVERAGE(HAVERQ!B47:B50) -> 44.625 | GF4: 2007 | GG4: =AVERAGE(HAVERQ!B195:B198) -> 94.175 | GI4: 2019 | GJ4: =AVERAGE(HAVERQ!B243:B246) -> 98.075 | GL4: ='OBR Nov25 ST1.15'!B70 -> 2023-24 | GM4: ='OBR Nov25 ST1.15'!O70 -> 1.193242 | GN4: ='OBR Nov25 ST1.15'!M70 -> 1.1188062 | GP4: ='OBR Nov25 ST1.15'!F70 -> 55208.25 | GQ4: ='OBR Nov25 ST1.15'!D70 -> 2753907.4 | GT4: =GP4+GS4 -> 55208.25 | GW4: =GQ4 -> 2753907.4 | GZ4: 2015 | HA4: =100*(Data!B49/Data!$B$57) -> 89.717837 | HB4: =HA4 -> 89.717837 | HD4: =100*((HB4/HA4)-1) -> 0
A5: 1981 | B5: =Data!F15*Data!G15 -> 24.65965 | C5: =Data!H15/Data!I15 -> 8.5228971 | D5: =Data!E15 -> 1247026 | E5: =Data!J15 -> -1.814585 | F5: =Data!D15 -> 1182108 | G5: =Data!B15 -> 1134663 | I5: =100*((F5/F4)-1) -> 1.4978582 | J5: =100*((G5/G4)-1) -> -0.55443129 | L5: 2001 | M5: ='[2]2022-based'!L8 -> 153.2 | R5: 2021 | S5: ='[2]2022-based'!Q28 -> 66977.988 | Y5: 2013 | Z5: =SUMIF('ONS Nov25 T1'!$L:$L,'Chart Data'!$Y5,'ONS Nov25 T1'!$C:$C)/1000 -> 669 | AA5: =SUMIF('ONS Nov25 T1'!$M:$M,'Chart Data'!$Y5,'ONS Nov25 T1'!$C:$C)/1000 -> 454 | AB5: =SUMIF('ONS Nov25 T1'!$N:$N,'Chart Data'!$Y5,'ONS Nov25 T1'!$C:$C)/1000 -> 215 | AC5: =Z5-AA5 -> 215 | AE5: 2022 | AF5: =AS5 -> 134 | AG5: =AU5 -> 269 | AH5: =AT5+AV5 -> 150 | AI5: =AW5 -> 65 | AJ5: =AQ5 -> 75 | AK5: =AP5+AX5+AY5+AZ5 -> 473 | AL5: =AO5-SUM(AF5:AK5) -> 1 | AN5: 2022 | AO5: =+AP5+AQ5+AR5 -> 1167 | AP5: =Z14-AQ5-AR5 -> 224 | AQ5: =SUMIF('ONS Nov25 T1'!$L:$L,'Chart Data'!$Y5,'ONS Nov25 T1'!$D:$D)/1000 -> 75 | AR5: =BC5+BK5 -> 868 | AS5: =BD5+BL5 -> 134 | AT5: =BE5+BM5 -> 93 | AU5: =BF5+BN5 -> 269 | AV5: =BG5+BO5 -> 57 | AW5: =BH5+BP5 -> 65 | AX5: =BQ5 -> 151 | AY5: =BR5 -> 70 | AZ5: =BS5 -> 28 | BA5: =AR5-AS5-AT5-AU5-AV5-AW5-AX5-AY5-AZ5 -> 1 | BC5: =SUMIF('ONS Nov25 T4a'!$P:$P,'Chart Data'!$AN5,'ONS Nov25 T4a'!C:C)/1000 -> 30 | BD5: =SUMIF('ONS Nov25 T4a'!$P:$P,'Chart Data'!$AN5,'ONS Nov25 T4a'!E:E)/1000 -> 15 | BE5: =SUMIF('ONS Nov25 T4a'!$P:$P,'Chart Data'!$AN5,'ONS Nov25 T4a'!F:F)/1000 -> 3 | BF5: =SUMIF('ONS Nov25 T4a'!$P:$P,'Chart Data'!$AN5,'ONS Nov25 T4a'!H:H)/1000 -> 11 | BG5: =SUMIF('ONS Nov25 T4a'!$P:$P,'Chart Data'!$AN5,'ONS Nov25 T4a'!I:I)/1000 -> 0 | BH5: =SUMIF('ONS Nov25 T4a'!$P:$P,'Chart Data'!$AN5,'ONS Nov25 T4a'!J:J)/1000 -> 1 | BI5: =BC5-BD5-BE5-BF5-BG5-BH5 -> 0 | BK5: =SUMIF('ONS Nov25 T4b'!$S:$S,'Chart Data'!$AN5,'ONS Nov25 T4b'!C:C)/1000 -> 838 | BL5: =SUMIF('ONS Nov25 T4b'!$S:$S,'Chart Data'!$AN5,'ONS Nov25 T4b'!E:E)/1000 -> 119 | BM5: =SUMIF('ONS Nov25 T4b'!$S:$S,'Chart Data'!$AN5,'ONS Nov25 T4b'!F:F)/1000 -> 90 | BN5: =SUMIF('ONS Nov25 T4b'!$S:$S,'Chart Data'!$AN5,'ONS Nov25 T4b'!H:H)/1000 -> 258 | BO5: =SUMIF('ONS Nov25 T4b'!$S:$S,'Chart Data'!$AN5,'ONS Nov25 T4b'!I:I)/1000 -> 57 | BP5: =SUMIF('ONS Nov25 T4b'!$S:$S,'Chart Data'!$AN5,'ONS Nov25 T4b'!J:J)/1000 -> 64 | BQ5: =SUMIF('ONS Nov25 T4b'!$S:$S,'Chart Data'!$AN5,'ONS Nov25 T4b'!K:K)/1000 -> 151 | BR5: =SUMIF('ONS Nov25 T4b'!$S:$S,'Chart Data'!$AN5,'ONS Nov25 T4b'!O:O)/1000 -> 70 | BS5: =SUMIF('ONS Nov25 T4b'!$S:$S,'Chart Data'!$AN5,'ONS Nov25 T4b'!P:P)/1000 -> 28 | BT5: =BK5-BL5-BM5-BN5-BO5-BP5-BQ5-BR5-BS5 -> 1 | BV5: 2022 | BW5: =CJ5 -> 17 | BX5: =CL5 -> 45 | BY5: =CK5+CM5 -> 14 | BZ5: =CN5 -> 10 | CA5: =CH5 -> 240 | CB5: =CG5+CO5+CP5+CQ5 -> 160 | CC5: =CF5-SUM(BW5:CB5) -> 0 | CE5: 2022 | CF5: =CG5+CH5+CI5 -> 486 | CG5: =AA14-CH5-CI5 -> 158 | CH5: =SUMIF('ONS Nov25 T1'!$M:$M,'Chart Data'!$CE5,'ONS Nov25 T1'!$D:$D)/1000 -> 240 | CI5: =CT5+DB5 -> 88 | CJ5: =CU5+DC5 -> 17 | CK5: =CV5+DD5 -> 9 | CL5: =CW5+DE5 -> 45 | CM5: =CX5+DF5 -> 5 | CN5: =CY5+DG5 -> 10 | CO5: =DH5 -> 0 | CP5: =DI5 -> 0 | CQ5: =DJ5 -> 2 | CR5: =CI5-CJ5-CK5-CL5-CM5-CN5-CO5-CP5-CQ5 -> 0 | CT5: =SUMIF('ONS Nov25 T4a'!$Q:$Q,'Chart Data'!$CE5,'ONS Nov25 T4a'!C:C)/1000 -> 0 | CU5: =SUMIF('ONS Nov25 T4a'!$Q:$Q,'Chart Data'!$CE5,'ONS Nov25 T4a'!E:E)/1000 -> 0 | CV5: =SUMIF('ONS Nov25 T4a'!$Q:$Q,'Chart Data'!$CE5,'ONS Nov25 T4a'!F:F)/1000 -> 0 | CW5: =SUMIF('ONS Nov25 T4a'!$Q:$Q,'Chart Data'!$CE5,'ONS Nov25 T4a'!H:H)/1000 -> 0 | CX5: =SUMIF('ONS Nov25 T4a'!$Q:$Q,'Chart Data'!$CE5,'ONS Nov25 T4a'!I:I)/1000 -> 0 | CY5: =SUMIF('ONS Nov25 T4a'!$Q:$Q,'Chart Data'!$CE5,'ONS Nov25 T4a'!J:J)/1000 -> 0 | CZ5: =CT5-CU5-CV5-CW5-CX5-CY5 -> 0 | DB5: =SUMIF('ONS Nov25 T4b'!$T:$T,'Chart Data'!$CE5,'ONS Nov25 T4b'!C:C)/1000 -> 88 | DC5: =SUMIF('ONS Nov25 T4b'!$T:$T,'Chart Data'!$CE5,'ONS Nov25 T4b'!E:E)/1000 -> 17 | DD5: =SUMIF('ONS Nov25 T4b'!$T:$T,'Chart Data'!$CE5,'ONS Nov25 T4b'!F:F)/1000 -> 9 | DE5: =SUMIF('ONS Nov25 T4b'!$T:$T,'Chart Data'!$AN5,'ONS Nov25 T4b'!H:H)/1000 -> 45 | DF5: =SUMIF('ONS Nov25 T4b'!$T:$T,'Chart Data'!$AN5,'ONS Nov25 T4b'!I:I)/1000 -> 5 | DG5: =SUMIF('ONS Nov25 T4b'!$T:$T,'Chart Data'!$AN5,'ONS Nov25 T4b'!J:J)/1000 -> 10 | DH5: =SUMIF('ONS Nov25 T4b'!$T:$T,'Chart Data'!$AN5,'ONS Nov25 T4b'!K:K)/1000 -> 0 | DI5: =SUMIF('ONS Nov25 T4b'!$T:$T,'Chart Data'!$AN5,'ONS Nov25 T4b'!O:O)/1000 -> 0 | DJ5: =SUMIF('ONS Nov25 T4b'!$T:$T,'Chart Data'!$AN5,'ONS Nov25 T4b'!P:P)/1000 -> 2 | DK5: =DB5-DC5-DD5-DE5-DF5-DG5-DH5-DI5-DJ5 -> 0 | DM5: 2025 | DN5: =100*(Data!B59/Data!$B$58) -> 101.38115 | DO5: =100*('OBR Nov25 ST1.1'!R115/'OBR Nov25 ST1.1'!$R$114) -> 101.48334 | DP5: ='OBR Nov25 C2.25'!M27 -> 101.45766 | DQ5: ='OBR Nov25 C2.25'!N27 -> 101.3 | DR5: ='OBR Nov25 C2.25'!O27-'Chart Data'!DQ5 -> 0.3 | DT5: 1975 | DU5: =100*((Data!M9/Data!M8)-1) -> -0.015228704 | DW5: 0 | DX5: 65 | DY5: 60 | EA5: 34001 | EC5: =AVERAGE($EB$7:$EB$399) -> 25.050854 | EH5: 16-64 | EI5: =100*(EI11/EI$13) -> 62.821174 | EJ5: =100*(EJ11/EJ$13) -> 63.014647 | EK5: =100*(EK11/EK$13) -> 63.163697 | EL5: =100*(EL11/EL$13) -> 63.249701 | EM5: =100*(EM11/EM$13) -> 63.277552 | EN5: =100*(EN11/EN$13) -> 63.259142 | EO5: =100*(EO11/EO$13) -> 63.194181 | EP5: =100*(EP11/EP$13) -> 63.086963 | ... FU5: =100*(FU11/FU$13) -> 60.298516 | GC5: 2007 | GD5: =AVERAGE(HAVERQ!B195:B198) -> 94.175 | GF5: 2019 | GG5: =AVERAGE(HAVERQ!B243:B246) -> 98.075 | GI5: 2025 | GJ5: =AVERAGE(HAVERQ!B265:B268) -> 100.15 | GL5: ='OBR Nov25 ST1.15'!B71 -> 2024-25 | GM5: ='OBR Nov25 ST1.15'!O71 -> 1.1492848 | GN5: ='OBR Nov25 ST1.15'!M71 -> 1.8882217 | GP5: ='OBR Nov25 ST1.15'!F71 -> 55842.75 | GQ5: ='OBR Nov25 ST1.15'!D71 -> 2805907.3 | GR5: =M29-P29 -> -86.772929 | GS5: =GR5*$GR$12 -> -72.859817 | GT5: =GP5+GS5 -> 55769.89 | GU5: =100*((GT5/GT4)-1) -> 1.0173121 | GV5: =GN5-GM5+GU5 -> 1.756249 | GW5: =GW4*(1+GV5/100) -> 2802272.9 | GX5: =100*((GW5/GQ5)-1) -> -0.12952694 | GZ5: 2016 | HA5: =100*(Data!B50/Data!$B$57) -> 91.697479 | HB5: =HA5 -> 91.697479 | HD5: =100*((HB5/HA5)-1) -> 0
A6: 1982 | B6: =Data!F16*Data!G16 -> 24.29771 | C6: =Data!H16/Data!I16 -> 8.5398108 | D6: =Data!E16 -> 1258257 | E6: =Data!J16 -> -1.802051 | F6: =Data!D16 -> 1189451 | G6: =Data!B16 -> 1157191 | I6: =100*((F6/F5)-1) -> 0.62117844 | J6: =100*((G6/G5)-1) -> 1.9854353 | L6: 2002 | M6: ='[2]2022-based'!L9 -> 190.9 | R6: 2022 | S6: ='[2]2022-based'!Q29 -> 67636.134 | T6: {=TRANSPOSE('ONS popproj Jan25 pp'!C8:AO8)} -> 67602.761 | U6: {=TRANSPOSE('ONS popproj Jan25 migcv'!C8:AO8)} -> 67602.761 | V6: =S6 -> 67636.134 | W6: {=TRANSPOSE('OBR Nov25 ST4.3'!T34:AB34)} -> 67970 | Y6: 2014 | Z6: =SUMIF('ONS Nov25 T1'!$L:$L,'Chart Data'!$Y6,'ONS Nov25 T1'!$C:$C)/1000 -> 737 | AA6: =SUMIF('ONS Nov25 T1'!$M:$M,'Chart Data'!$Y6,'ONS Nov25 T1'!$C:$C)/1000 -> 489 | AB6: =SUMIF('ONS Nov25 T1'!$N:$N,'Chart Data'!$Y6,'ONS Nov25 T1'!$C:$C)/1000 -> 248 | AC6: =Z6-AA6 -> 248 | AE6: 2023 | AF6: =AS6 -> 220 | AG6: =AU6 -> 352 | AH6: =AT6+AV6 -> 318 | AI6: =AW6 -> 90 | AJ6: =AQ6 -> 82 | AK6: =AP6+AX6+AY6+AZ6 -> 402 | AL6: =AO6-SUM(AF6:AK6) -> 2 | AN6: 2023 | AO6: =+AP6+AQ6+AR6 -> 1466 | AP6: =Z15-AQ6-AR6 -> 170 | AQ6: =SUMIF('ONS Nov25 T1'!$L:$L,'Chart Data'!$Y6,'ONS Nov25 T1'!$D:$D)/1000 -> 82 | AR6: =BC6+BK6 -> 1214 | AS6: =BD6+BL6 -> 220 | AT6: =BE6+BM6 -> 187 | AU6: =BF6+BN6 -> 352 | AV6: =BG6+BO6 -> 131 | AW6: =BH6+BP6 -> 90 | AX6: =BQ6 -> 126 | AY6: =BR6 -> 85 | AZ6: =BS6 -> 21 | BA6: =AR6-AS6-AT6-AU6-AV6-AW6-AX6-AY6-AZ6 -> 2 | BC6: =SUMIF('ONS Nov25 T4a'!$P:$P,'Chart Data'!$AN6,'ONS Nov25 T4a'!C:C)/1000 -> 32 | BD6: =SUMIF('ONS Nov25 T4a'!$P:$P,'Chart Data'!$AN6,'ONS Nov25 T4a'!E:E)/1000 -> 14 | BE6: =SUMIF('ONS Nov25 T4a'!$P:$P,'Chart Data'!$AN6,'ONS Nov25 T4a'!F:F)/1000 -> 4 | BF6: =SUMIF('ONS Nov25 T4a'!$P:$P,'Chart Data'!$AN6,'ONS Nov25 T4a'!H:H)/1000 -> 11 | BG6: =SUMIF('ONS Nov25 T4a'!$P:$P,'Chart Data'!$AN6,'ONS Nov25 T4a'!I:I)/1000 -> 0 | BH6: =SUMIF('ONS Nov25 T4a'!$P:$P,'Chart Data'!$AN6,'ONS Nov25 T4a'!J:J)/1000 -> 2 | BI6: =BC6-BD6-BE6-BF6-BG6-BH6 -> 1 | BK6: =SUMIF('ONS Nov25 T4b'!$S:$S,'Chart Data'!$AN6,'ONS Nov25 T4b'!C:C)/1000 -> 1182 | BL6: =SUMIF('ONS Nov25 T4b'!$S:$S,'Chart Data'!$AN6,'ONS Nov25 T4b'!E:E)/1000 -> 206 | BM6: =SUMIF('ONS Nov25 T4b'!$S:$S,'Chart Data'!$AN6,'ONS Nov25 T4b'!F:F)/1000 -> 183 | BN6: =SUMIF('ONS Nov25 T4b'!$S:$S,'Chart Data'!$AN6,'ONS Nov25 T4b'!H:H)/1000 -> 341 | BO6: =SUMIF('ONS Nov25 T4b'!$S:$S,'Chart Data'!$AN6,'ONS Nov25 T4b'!I:I)/1000 -> 131 | BP6: =SUMIF('ONS Nov25 T4b'!$S:$S,'Chart Data'!$AN6,'ONS Nov25 T4b'!J:J)/1000 -> 88 | BQ6: =SUMIF('ONS Nov25 T4b'!$S:$S,'Chart Data'!$AN6,'ONS Nov25 T4b'!K:K)/1000 -> 126 | BR6: =SUMIF('ONS Nov25 T4b'!$S:$S,'Chart Data'!$AN6,'ONS Nov25 T4b'!O:O)/1000 -> 85 | BS6: =SUMIF('ONS Nov25 T4b'!$S:$S,'Chart Data'!$AN6,'ONS Nov25 T4b'!P:P)/1000 -> 21 | BT6: =BK6-BL6-BM6-BN6-BO6-BP6-BQ6-BR6-BS6 -> 1 | BV6: 2023 | BW6: =CJ6 -> 21 | BX6: =CL6 -> 85 | BY6: =CK6+CM6 -> 19 | BZ6: =CN6 -> 11 | CA6: =CH6 -> 252 | CB6: =CG6+CO6+CP6+CQ6 -> 153 | CC6: =CF6-SUM(BW6:CB6) -> 2 | CE6: 2023 | CF6: =CG6+CH6+CI6 -> 543 | CG6: =AA15-CH6-CI6 -> 149 | CH6: =SUMIF('ONS Nov25 T1'!$M:$M,'Chart Data'!$CE6,'ONS Nov25 T1'!$D:$D)/1000 -> 252 | CI6: =CT6+DB6 -> 142 | CJ6: =CU6+DC6 -> 21 | CK6: =CV6+DD6 -> 11 | CL6: =CW6+DE6 -> 85 | CM6: =CX6+DF6 -> 8 | CN6: =CY6+DG6 -> 11 | CO6: =DH6 -> 1 | CP6: =DI6 -> 1 | CQ6: =DJ6 -> 2 | CR6: =CI6-CJ6-CK6-CL6-CM6-CN6-CO6-CP6-CQ6 -> 2 | CT6: =SUMIF('ONS Nov25 T4a'!$Q:$Q,'Chart Data'!$CE6,'ONS Nov25 T4a'!C:C)/1000 -> 5 | CU6: =SUMIF('ONS Nov25 T4a'!$Q:$Q,'Chart Data'!$CE6,'ONS Nov25 T4a'!E:E)/1000 -> 2 | CV6: =SUMIF('ONS Nov25 T4a'!$Q:$Q,'Chart Data'!$CE6,'ONS Nov25 T4a'!F:F)/1000 -> 0 | CW6: =SUMIF('ONS Nov25 T4a'!$Q:$Q,'Chart Data'!$CE6,'ONS Nov25 T4a'!H:H)/1000 -> 2 | CX6: =SUMIF('ONS Nov25 T4a'!$Q:$Q,'Chart Data'!$CE6,'ONS Nov25 T4a'!I:I)/1000 -> 0 | CY6: =SUMIF('ONS Nov25 T4a'!$Q:$Q,'Chart Data'!$CE6,'ONS Nov25 T4a'!J:J)/1000 -> 0 | CZ6: =CT6-CU6-CV6-CW6-CX6-CY6 -> 1 | DB6: =SUMIF('ONS Nov25 T4b'!$T:$T,'Chart Data'!$CE6,'ONS Nov25 T4b'!C:C)/1000 -> 137 | DC6: =SUMIF('ONS Nov25 T4b'!$T:$T,'Chart Data'!$CE6,'ONS Nov25 T4b'!E:E)/1000 -> 19 | DD6: =SUMIF('ONS Nov25 T4b'!$T:$T,'Chart Data'!$CE6,'ONS Nov25 T4b'!F:F)/1000 -> 11 | DE6: =SUMIF('ONS Nov25 T4b'!$T:$T,'Chart Data'!$AN6,'ONS Nov25 T4b'!H:H)/1000 -> 83 | DF6: =SUMIF('ONS Nov25 T4b'!$T:$T,'Chart Data'!$AN6,'ONS Nov25 T4b'!I:I)/1000 -> 8 | DG6: =SUMIF('ONS Nov25 T4b'!$T:$T,'Chart Data'!$AN6,'ONS Nov25 T4b'!J:J)/1000 -> 11 | DH6: =SUMIF('ONS Nov25 T4b'!$T:$T,'Chart Data'!$AN6,'ONS Nov25 T4b'!K:K)/1000 -> 1 | DI6: =SUMIF('ONS Nov25 T4b'!$T:$T,'Chart Data'!$AN6,'ONS Nov25 T4b'!O:O)/1000 -> 1 | DJ6: =SUMIF('ONS Nov25 T4b'!$T:$T,'Chart Data'!$AN6,'ONS Nov25 T4b'!P:P)/1000 -> 2 | DK6: =DB6-DC6-DD6-DE6-DF6-DG6-DH6-DI6-DJ6 -> 1 | DM6: 2026 | DN6: =100*(Data!B60/Data!$B$58) -> 102.26486 | DO6: =100*('OBR Nov25 ST1.1'!R116/'OBR Nov25 ST1.1'!$R$114) -> 102.87515 | DP6: ='OBR Nov25 C2.25'!M28 -> 102.63936 | DQ6: =DN6 -> 102.26486 | DR6: ='OBR Nov25 C2.25'!O28-'Chart Data'!DQ6 -> 0.7575371 | DT6: 1976 | DU6: =100*((Data!M10/Data!M9)-1) -> 0.10264916 | DW6: 0 | DX6: 65 | DY6: 60 | EA6: 34029 | EC6: =AVERAGE($EB$7:$EB$399) -> 25.050854 | EH6: 65+ | EI6: =100*(EI12/EI$13) -> 18.839883 | EJ6: =100*(EJ12/EJ$13) -> 18.885215 | EK6: =100*(EK12/EK$13) -> 19.015042 | EL6: =100*(EL12/EL$13) -> 19.185849 | EM6: =100*(EM12/EM$13) -> 19.413087 | EN6: =100*(EN12/EN$13) -> 19.693114 | EO6: =100*(EO12/EO$13) -> 20.011347 | EP6: =100*(EP12/EP$13) -> 20.340498 | ... FU6: =100*(FU12/FU$13) -> 25.24931 | GC6: y/y | GD6: =100*((GD5/GD4)^(1/37)-1) -> 2.0390523 | GF6: y/y | GG6: =100*((GG5/GG4)^(1/12)-1) -> 0.33872019 | GI6: y/y | GJ6: =100*((GJ5/GJ4)^(4/23)-1) -> 0.36477796 | GL6: ='OBR Nov25 ST1.15'!B72 -> 2025-26 | GM6: ='OBR Nov25 ST1.15'!O72 -> 0.92630512 | GN6: ='OBR Nov25 ST1.15'!M72 -> 1.5356702 | GP6: ='OBR Nov25 ST1.15'!F72 -> 56360.024 | GQ6: ='OBR Nov25 ST1.15'!D72 -> 2848996.8 | GR6: =GR5+M30-P30 -> -255.24158 | GS6: =GR6*$GR$12 -> -214.31632 | GT6: =GP6+GS6 -> 56145.708 | GU6: =100*((GT6/GT5)-1) -> 0.67387212 | GV6: =GN6-GM6+GU6 -> 1.2832372 | GW6: =GW5*(1+GV6/100) -> 2838232.7 | GX6: =100*((GW6/GQ6)-1) -> -0.37782 | GZ6: 2017 | HA6: =100*(Data!B51/Data!$B$57) -> 94.469697 | HB6: =HA6 -> 94.469697 | HD6: =100*((HB6/HA6)-1) -> 0
A7: 1983 | B7: =Data!F17*Data!G17 -> 24.30468 | C7: =Data!H17/Data!I17 -> 8.5563186 | D7: =Data!E17 -> 1271612 | E7: =Data!J17 -> -1.789603 | F7: =Data!D17 -> 1209350 | G7: =Data!B17 -> 1205632 | I7: =100*((F7/F6)-1) -> 1.6729567 | J7: =100*((G7/G6)-1) -> 4.1860851 | L7: 2003 | M7: ='[2]2022-based'!L10 -> 194.3 | R7: 2023 | S7: ='[2]2022-based'!Q30 -> 68526.183 | T7: 68492.495 | U7: 68492.495 | V7: =S7 -> 68526.183 | W7: 68809.5 | Y7: 2015 | Z7: =SUMIF('ONS Nov25 T1'!$L:$L,'Chart Data'!$Y7,'ONS Nov25 T1'!$C:$C)/1000 -> 778 | AA7: =SUMIF('ONS Nov25 T1'!$M:$M,'Chart Data'!$Y7,'ONS Nov25 T1'!$C:$C)/1000 -> 482 | AB7: =SUMIF('ONS Nov25 T1'!$N:$N,'Chart Data'!$Y7,'ONS Nov25 T1'!$C:$C)/1000 -> 296 | AC7: =Z7-AA7 -> 296 | AE7: 2024 | AF7: =AS7 -> 202 | AG7: =AU7 -> 310 | AH7: =AT7+AV7 -> 336 | AI7: =AW7 -> 87 | AJ7: =AQ7 -> 83 | AK7: =AP7+AX7+AY7+AZ7 -> 280 | AL7: =AO7-SUM(AF7:AK7) -> 1 | AN7: 2024 | AO7: =+AP7+AQ7+AR7 -> 1299 | AP7: =Z16-AQ7-AR7 -> 122 | AQ7: =SUMIF('ONS Nov25 T1'!$L:$L,'Chart Data'!$Y7,'ONS Nov25 T1'!$D:$D)/1000 -> 83 | AR7: =BC7+BK7 -> 1094 | AS7: =BD7+BL7 -> 202 | AT7: =BE7+BM7 -> 249 | AU7: =BF7+BN7 -> 310 | AV7: =BG7+BO7 -> 87 | AW7: =BH7+BP7 -> 87 | AX7: =BQ7 -> 62 | AY7: =BR7 -> 81 | AZ7: =BS7 -> 15 | BA7: =AR7-AS7-AT7-AU7-AV7-AW7-AX7-AY7-AZ7 -> 1 | BC7: =SUMIF('ONS Nov25 T4a'!$P:$P,'Chart Data'!$AN7,'ONS Nov25 T4a'!C:C)/1000 -> 31 | BD7: =SUMIF('ONS Nov25 T4a'!$P:$P,'Chart Data'!$AN7,'ONS Nov25 T4a'!E:E)/1000 -> 12 | BE7: =SUMIF('ONS Nov25 T4a'!$P:$P,'Chart Data'!$AN7,'ONS Nov25 T4a'!F:F)/1000 -> 4 | BF7: =SUMIF('ONS Nov25 T4a'!$P:$P,'Chart Data'!$AN7,'ONS Nov25 T4a'!H:H)/1000 -> 11 | BG7: =SUMIF('ONS Nov25 T4a'!$P:$P,'Chart Data'!$AN7,'ONS Nov25 T4a'!I:I)/1000 -> 0 | BH7: =SUMIF('ONS Nov25 T4a'!$P:$P,'Chart Data'!$AN7,'ONS Nov25 T4a'!J:J)/1000 -> 3 | BI7: =BC7-BD7-BE7-BF7-BG7-BH7 -> 1 | BK7: =SUMIF('ONS Nov25 T4b'!$S:$S,'Chart Data'!$AN7,'ONS Nov25 T4b'!C:C)/1000 -> 1063 | BL7: =SUMIF('ONS Nov25 T4b'!$S:$S,'Chart Data'!$AN7,'ONS Nov25 T4b'!E:E)/1000 -> 190 | BM7: =SUMIF('ONS Nov25 T4b'!$S:$S,'Chart Data'!$AN7,'ONS Nov25 T4b'!F:F)/1000 -> 245 | BN7: =SUMIF('ONS Nov25 T4b'!$S:$S,'Chart Data'!$AN7,'ONS Nov25 T4b'!H:H)/1000 -> 299 | BO7: =SUMIF('ONS Nov25 T4b'!$S:$S,'Chart Data'!$AN7,'ONS Nov25 T4b'!I:I)/1000 -> 87 | BP7: =SUMIF('ONS Nov25 T4b'!$S:$S,'Chart Data'!$AN7,'ONS Nov25 T4b'!J:J)/1000 -> 84 | BQ7: =SUMIF('ONS Nov25 T4b'!$S:$S,'Chart Data'!$AN7,'ONS Nov25 T4b'!K:K)/1000 -> 62 | BR7: =SUMIF('ONS Nov25 T4b'!$S:$S,'Chart Data'!$AN7,'ONS Nov25 T4b'!O:O)/1000 -> 81 | BS7: =SUMIF('ONS Nov25 T4b'!$S:$S,'Chart Data'!$AN7,'ONS Nov25 T4b'!P:P)/1000 -> 15 | BT7: =BK7-BL7-BM7-BN7-BO7-BP7-BQ7-BR7-BS7 -> 0 | BV7: 2024 | BW7: =CJ7 -> 38 | BX7: =CL7 -> 128 | BY7: =CK7+CM7 -> 40 | BZ7: =CN7 -> 23 | CA7: =CH7 -> 257 | CB7: =CG7+CO7+CP7+CQ7 -> 164 | CC7: =CF7-SUM(BW7:CB7) -> 0 | CE7: 2024 | CF7: =CG7+CH7+CI7 -> 650 | CG7: =AA16-CH7-CI7 -> 145 | CH7: =SUMIF('ONS Nov25 T1'!$M:$M,'Chart Data'!$CE7,'ONS Nov25 T1'!$D:$D)/1000 -> 257 | CI7: =CT7+DB7 -> 248 | CJ7: =CU7+DC7 -> 38 | CK7: =CV7+DD7 -> 22 | CL7: =CW7+DE7 -> 128 | CM7: =CX7+DF7 -> 18 | CN7: =CY7+DG7 -> 23 | CO7: =DH7 -> 10 | CP7: =DI7 -> 4 | CQ7: =DJ7 -> 5 | CR7: =CI7-CJ7-CK7-CL7-CM7-CN7-CO7-CP7-CQ7 -> 0 | CT7: =SUMIF('ONS Nov25 T4a'!$Q:$Q,'Chart Data'!$CE7,'ONS Nov25 T4a'!C:C)/1000 -> 10 | CU7: =SUMIF('ONS Nov25 T4a'!$Q:$Q,'Chart Data'!$CE7,'ONS Nov25 T4a'!E:E)/1000 -> 4 | CV7: =SUMIF('ONS Nov25 T4a'!$Q:$Q,'Chart Data'!$CE7,'ONS Nov25 T4a'!F:F)/1000 -> 1 | CW7: =SUMIF('ONS Nov25 T4a'!$Q:$Q,'Chart Data'!$CE7,'ONS Nov25 T4a'!H:H)/1000 -> 4 | CX7: =SUMIF('ONS Nov25 T4a'!$Q:$Q,'Chart Data'!$CE7,'ONS Nov25 T4a'!I:I)/1000 -> 0 | CY7: =SUMIF('ONS Nov25 T4a'!$Q:$Q,'Chart Data'!$CE7,'ONS Nov25 T4a'!J:J)/1000 -> 0 | CZ7: =CT7-CU7-CV7-CW7-CX7-CY7 -> 1 | DB7: =SUMIF('ONS Nov25 T4b'!$T:$T,'Chart Data'!$CE7,'ONS Nov25 T4b'!C:C)/1000 -> 238 | DC7: =SUMIF('ONS Nov25 T4b'!$T:$T,'Chart Data'!$CE7,'ONS Nov25 T4b'!E:E)/1000 -> 34 | DD7: =SUMIF('ONS Nov25 T4b'!$T:$T,'Chart Data'!$CE7,'ONS Nov25 T4b'!F:F)/1000 -> 21 | DE7: =SUMIF('ONS Nov25 T4b'!$T:$T,'Chart Data'!$AN7,'ONS Nov25 T4b'!H:H)/1000 -> 124 | DF7: =SUMIF('ONS Nov25 T4b'!$T:$T,'Chart Data'!$AN7,'ONS Nov25 T4b'!I:I)/1000 -> 18 | DG7: =SUMIF('ONS Nov25 T4b'!$T:$T,'Chart Data'!$AN7,'ONS Nov25 T4b'!J:J)/1000 -> 23 | DH7: =SUMIF('ONS Nov25 T4b'!$T:$T,'Chart Data'!$AN7,'ONS Nov25 T4b'!K:K)/1000 -> 10 | DI7: =SUMIF('ONS Nov25 T4b'!$T:$T,'Chart Data'!$AN7,'ONS Nov25 T4b'!O:O)/1000 -> 4 | DJ7: =SUMIF('ONS Nov25 T4b'!$T:$T,'Chart Data'!$AN7,'ONS Nov25 T4b'!P:P)/1000 -> 5 | DK7: =DB7-DC7-DD7-DE7-DF7-DG7-DH7-DI7-DJ7 -> -1 | DM7: 2027 | DN7: =100*(Data!B61/Data!$B$58) -> 103.63217 | DO7: =100*('OBR Nov25 ST1.1'!R117/'OBR Nov25 ST1.1'!$R$114) -> 104.46214 | DP7: ='OBR Nov25 C2.25'!M29 -> 104.03723 | DQ7: =DN7 -> 103.63217 | DR7: ='OBR Nov25 C2.25'!O29-'Chart Data'!DQ7 -> 0.63202207 | DT7: 1977 | DU7: =100*((Data!M11/Data!M10)-1) -> 0.58379587 | DW7: 0 | DX7: 65 | DY7: 60 | EA7: 34060 | EB7: =100*(HAVERM!C46/HAVERM!B46) -> 21.187332 | EC7: =AVERAGE($EB$7:$EB$399) -> 25.050854 | EE7: =HAVERM!C46 -> 1813 | EF7: =HAVERM!B46-HAVERM!C46 -> 6744 | EH7: Total | EI7: =SUM(EI4:EI6) -> 100 | EJ7: =SUM(EJ4:EJ6) -> 100 | EK7: =SUM(EK4:EK6) -> 100 | EL7: =SUM(EL4:EL6) -> 100 | EM7: =SUM(EM4:EM6) -> 100 | EN7: =SUM(EN4:EN6) -> 100 | EO7: =SUM(EO4:EO6) -> 100 | EP7: =SUM(EP4:EP6) -> 100 | ... FU7: =SUM(FU4:FU6) -> 100 | GC7: q/q | GD7: =100*((GD5/GD4)^(1/144)-1) -> 0.52000047 | GF7: q/q | GG7: =100*((GG5/GG4)^(1/48)-1) -> 0.084572698 | GI7: q/q | GJ7: =100*((GJ5/GJ4)^(1/23)-1) -> 0.091070009 | GL7: ='OBR Nov25 ST1.15'!B73 -> 2026-27 | GM7: ='OBR Nov25 ST1.15'!O73 -> 0.69881766 | GN7: ='OBR Nov25 ST1.15'!M73 -> 1.2938669 | GP7: ='OBR Nov25 ST1.15'!F73 -> 56753.878 | GQ7: ='OBR Nov25 ST1.15'!D73 -> 2885859 | GR7: =GR6+M31-P31 -> -374.64021 | GS7: =GR7*$GR$12 -> -314.57065 | GT7: =GP7+GS7 -> 56439.307 | GU7: =100*((GT7/GT6)-1) -> 0.52292416 | GV7: =GN7-GM7+GU7 -> 1.1179734 | GW7: =GW6*(1+GV7/100) -> 2869963.4 | GX7: =100*((GW7/GQ7)-1) -> -0.55081067 | GZ7: 2018 | HA7: =100*(Data!B52/Data!$B$57) -> 95.935235 | HB7: =HA7 -> 95.935235 | HD7: =100*((HB7/HA7)-1) -> 0
A8: 1984 | B8: =Data!F18*Data!G18 -> 24.9108 | C8: =Data!H18/Data!I18 -> 8.5981658 | D8: =Data!E18 -> 1295894 | E8: =Data!J18 -> -1.777241 | F8: =Data!D18 -> 1251974 | G8: =Data!B18 -> 1232675 | I8: =100*((F8/F7)-1) -> 3.524538 | J8: =100*((G8/G7)-1) -> 2.2430559 | L8: 2004 | M8: ='[2]2022-based'!L11 -> 209.5 | R8: 2024 | S8: ='[2]2022-based'!Q31 -> 69281.437 | T8: 69226.231 | U8: 69226.231 | V8: =S8 -> 69281.437 | W8: 69395 | Y8: 2016 | Z8: =SUMIF('ONS Nov25 T1'!$L:$L,'Chart Data'!$Y8,'ONS Nov25 T1'!$C:$C)/1000 -> 832 | AA8: =SUMIF('ONS Nov25 T1'!$M:$M,'Chart Data'!$Y8,'ONS Nov25 T1'!$C:$C)/1000 -> 511 | AB8: =SUMIF('ONS Nov25 T1'!$N:$N,'Chart Data'!$Y8,'ONS Nov25 T1'!$C:$C)/1000 -> 321 | AC8: =Z8-AA8 -> 321 | AE8: 2025 | AF8: =AS8 -> 98 | AG8: =AU8 -> 288 | AH8: =AT8+AV8 -> 102 | AI8: =AW8 -> 63 | AJ8: =AQ8 -> 74 | AK8: =AP8+AX8+AY8+AZ8 -> 272 | AL8: =AO8-SUM(AF8:AK8) -> 1 | AN8: 2025 | AO8: =+AP8+AQ8+AR8 -> 898 | AP8: =Z17-AQ8-AR8 -> 122 | AQ8: =SUMIF('ONS Nov25 T1'!$L:$L,'Chart Data'!$Y8,'ONS Nov25 T1'!$D:$D)/1000 -> 74 | AR8: =BC8+BK8 -> 702 | AS8: =BD8+BL8 -> 98 | AT8: =BE8+BM8 -> 89 | AU8: =BF8+BN8 -> 288 | AV8: =BG8+BO8 -> 13 | AW8: =BH8+BP8 -> 63 | AX8: =BQ8 -> 41 | AY8: =BR8 -> 96 | AZ8: =BS8 -> 13 | BA8: =AR8-AS8-AT8-AU8-AV8-AW8-AX8-AY8-AZ8 -> 1 | BC8: =SUMIF('ONS Nov25 T4a'!$P:$P,'Chart Data'!$AN8,'ONS Nov25 T4a'!C:C)/1000 -> 32 | BD8: =SUMIF('ONS Nov25 T4a'!$P:$P,'Chart Data'!$AN8,'ONS Nov25 T4a'!E:E)/1000 -> 12 | BE8: =SUMIF('ONS Nov25 T4a'!$P:$P,'Chart Data'!$AN8,'ONS Nov25 T4a'!F:F)/1000 -> 4 | BF8: =SUMIF('ONS Nov25 T4a'!$P:$P,'Chart Data'!$AN8,'ONS Nov25 T4a'!H:H)/1000 -> 13 | BG8: =SUMIF('ONS Nov25 T4a'!$P:$P,'Chart Data'!$AN8,'ONS Nov25 T4a'!I:I)/1000 -> 0 | BH8: =SUMIF('ONS Nov25 T4a'!$P:$P,'Chart Data'!$AN8,'ONS Nov25 T4a'!J:J)/1000 -> 3 | BI8: =BC8-BD8-BE8-BF8-BG8-BH8 -> 0 | BK8: =SUMIF('ONS Nov25 T4b'!$S:$S,'Chart Data'!$AN8,'ONS Nov25 T4b'!C:C)/1000 -> 670 | BL8: =SUMIF('ONS Nov25 T4b'!$S:$S,'Chart Data'!$AN8,'ONS Nov25 T4b'!E:E)/1000 -> 86 | BM8: =SUMIF('ONS Nov25 T4b'!$S:$S,'Chart Data'!$AN8,'ONS Nov25 T4b'!F:F)/1000 -> 85 | BN8: =SUMIF('ONS Nov25 T4b'!$S:$S,'Chart Data'!$AN8,'ONS Nov25 T4b'!H:H)/1000 -> 275 | BO8: =SUMIF('ONS Nov25 T4b'!$S:$S,'Chart Data'!$AN8,'ONS Nov25 T4b'!I:I)/1000 -> 13 | BP8: =SUMIF('ONS Nov25 T4b'!$S:$S,'Chart Data'!$AN8,'ONS Nov25 T4b'!J:J)/1000 -> 60 | BQ8: =SUMIF('ONS Nov25 T4b'!$S:$S,'Chart Data'!$AN8,'ONS Nov25 T4b'!K:K)/1000 -> 41 | BR8: =SUMIF('ONS Nov25 T4b'!$S:$S,'Chart Data'!$AN8,'ONS Nov25 T4b'!O:O)/1000 -> 96 | BS8: =SUMIF('ONS Nov25 T4b'!$S:$S,'Chart Data'!$AN8,'ONS Nov25 T4b'!P:P)/1000 -> 13 | BT8: =BK8-BL8-BM8-BN8-BO8-BP8-BQ8-BR8-BS8 -> 1 | BV8: 2025 | BW8: =CJ8 -> 45 | BX8: =CL8 -> 122 | BY8: =CK8+CM8 -> 51 | BZ8: =CN8 -> 47 | CA8: =CH8 -> 252 | CB8: =CG8+CO8+CP8+CQ8 -> 178 | CC8: =CF8-SUM(BW8:CB8) -> -2 | CE8: 2025 | CF8: =CG8+CH8+CI8 -> 693 | CG8: =AA17-CH8-CI8 -> 145 | CH8: =SUMIF('ONS Nov25 T1'!$M:$M,'Chart Data'!$CE8,'ONS Nov25 T1'!$D:$D)/1000 -> 252 | CI8: =CT8+DB8 -> 296 | CJ8: =CU8+DC8 -> 45 | CK8: =CV8+DD8 -> 24 | CL8: =CW8+DE8 -> 122 | CM8: =CX8+DF8 -> 27 | CN8: =CY8+DG8 -> 47 | CO8: =DH8 -> 20 | CP8: =DI8 -> 6 | CQ8: =DJ8 -> 7 | CR8: =CI8-CJ8-CK8-CL8-CM8-CN8-CO8-CP8-CQ8 -> -2 | CT8: =SUMIF('ONS Nov25 T4a'!$Q:$Q,'Chart Data'!$CE8,'ONS Nov25 T4a'!C:C)/1000 -> 10 | CU8: =SUMIF('ONS Nov25 T4a'!$Q:$Q,'Chart Data'!$CE8,'ONS Nov25 T4a'!E:E)/1000 -> 4 | CV8: =SUMIF('ONS Nov25 T4a'!$Q:$Q,'Chart Data'!$CE8,'ONS Nov25 T4a'!F:F)/1000 -> 1 | CW8: =SUMIF('ONS Nov25 T4a'!$Q:$Q,'Chart Data'!$CE8,'ONS Nov25 T4a'!H:H)/1000 -> 4 | CX8: =SUMIF('ONS Nov25 T4a'!$Q:$Q,'Chart Data'!$CE8,'ONS Nov25 T4a'!I:I)/1000 -> 0 | CY8: =SUMIF('ONS Nov25 T4a'!$Q:$Q,'Chart Data'!$CE8,'ONS Nov25 T4a'!J:J)/1000 -> 1 | CZ8: =CT8-CU8-CV8-CW8-CX8-CY8 -> 0 | DB8: =SUMIF('ONS Nov25 T4b'!$T:$T,'Chart Data'!$CE8,'ONS Nov25 T4b'!C:C)/1000 -> 286 | DC8: =SUMIF('ONS Nov25 T4b'!$T:$T,'Chart Data'!$CE8,'ONS Nov25 T4b'!E:E)/1000 -> 41 | DD8: =SUMIF('ONS Nov25 T4b'!$T:$T,'Chart Data'!$CE8,'ONS Nov25 T4b'!F:F)/1000 -> 23 | DE8: =SUMIF('ONS Nov25 T4b'!$T:$T,'Chart Data'!$AN8,'ONS Nov25 T4b'!H:H)/1000 -> 118 | DF8: =SUMIF('ONS Nov25 T4b'!$T:$T,'Chart Data'!$AN8,'ONS Nov25 T4b'!I:I)/1000 -> 27 | DG8: =SUMIF('ONS Nov25 T4b'!$T:$T,'Chart Data'!$AN8,'ONS Nov25 T4b'!J:J)/1000 -> 46 | DH8: =SUMIF('ONS Nov25 T4b'!$T:$T,'Chart Data'!$AN8,'ONS Nov25 T4b'!K:K)/1000 -> 20 | DI8: =SUMIF('ONS Nov25 T4b'!$T:$T,'Chart Data'!$AN8,'ONS Nov25 T4b'!O:O)/1000 -> 6 | DJ8: =SUMIF('ONS Nov25 T4b'!$T:$T,'Chart Data'!$AN8,'ONS Nov25 T4b'!P:P)/1000 -> 7 | DK8: =DB8-DC8-DD8-DE8-DF8-DG8-DH8-DI8-DJ8 -> -2 | DM8: 2028 | DN8: =100*(Data!B62/Data!$B$58) -> 105.12535 | DO8: =100*('OBR Nov25 ST1.1'!R118/'OBR Nov25 ST1.1'!$R$114) -> 105.99506 | DP8: ='OBR Nov25 C2.25'!M30 -> 105.48614 | DQ8: ='OBR Nov25 C2.25'!N30 -> 104.98848 | DR8: ='OBR Nov25 C2.25'!O30-'Chart Data'!DQ8 -> 0.98981322 | DT8: 1978 | DU8: =100*((Data!M12/Data!M11)-1) -> 0.62030177 | DW8: 0 | DX8: 65 | DY8: 60 | EA8: 34090 | EB8: =100*(HAVERM!C47/HAVERM!B47) -> 21.412726 | EC8: =AVERAGE($EB$7:$EB$399) -> 25.050854 | EE8: =HAVERM!C47 -> 1834 | EF8: =HAVERM!B47-HAVERM!C47 -> 6731 | FW8: 1961 | GL8: ='OBR Nov25 ST1.15'!B74 -> 2027-28 | GM8: ='OBR Nov25 ST1.15'!O74 -> 0.71395504 | GN8: ='OBR Nov25 ST1.15'!M74 -> 1.2834508 | GP8: ='OBR Nov25 ST1.15'!F74 -> 57159.075 | GQ8: ='OBR Nov25 ST1.15'!D74 -> 2922897.6 | GR8: =GR7+M32-P32 -> -487.46056 | GS8: =GR8*$GR$12 -> -409.30147 | GT8: =GP8+GS8 -> 56749.774 | GU8: =100*((GT8/GT7)-1) -> 0.55008889 | GV8: =GN8-GM8+GU8 -> 1.1195846 | GW8: =GW7*(1+GV8/100) -> 2902095.1 | GX8: =100*((GW8/GQ8)-1) -> -0.71170918 | GZ8: 2019 | HA8: =100*(Data!B53/Data!$B$57) -> 97.140468 | HB8: =HA8 -> 97.140468 | HD8: =100*((HB8/HA8)-1) -> 0
A9: 1985 | B9: =Data!F19*Data!G19 -> 25.10787 | C9: =Data!H19/Data!I19 -> 8.6987754 | D9: =Data!E19 -> 1321996 | E9: =Data!J19 -> -1.764964 | F9: =Data!D19 -> 1287060 | G9: =Data!B19 -> 1283200 | I9: =100*((F9/F8)-1) -> 2.8024544 | J9: =100*((G9/G8)-1) -> 4.0988095 | L9: 2005 | M9: ='[2]2022-based'!L12 -> 335.6 | R9: 2025 | S9: ='[2]2022-based'!Q32 -> 69487 | T9: 69867.979 | U9: 69584.497 | V9: =V8*W9/W8 -> 69569.69 | W9: 69683.726 | Y9: 2017 | Z9: =SUMIF('ONS Nov25 T1'!$L:$L,'Chart Data'!$Y9,'ONS Nov25 T1'!$C:$C)/1000 -> 718 | AA9: =SUMIF('ONS Nov25 T1'!$M:$M,'Chart Data'!$Y9,'ONS Nov25 T1'!$C:$C)/1000 -> 518 | AB9: =SUMIF('ONS Nov25 T1'!$N:$N,'Chart Data'!$Y9,'ONS Nov25 T1'!$C:$C)/1000 -> 200 | AC9: =Z9-AA9 -> 200 | AE9: 2026 | AF9: =AS9 -> 39.2 | AG9: =AU9 -> 288 | AH9: =AT9+AV9 -> 57.5 | AI9: =AW9 -> 63 | AJ9: =AQ9 -> 75 | AK9: =AP9+AX9+AY9+AZ9 -> 246.5018 | AL9: =AO9-SUM(AF9:AK9) -> 0 | AN9: 2026 | AO9: ='[2]Migration calculations'!L17 -> 769.2018 | AP9: =AO9-AQ9-AR9 -> 104.5018 | AQ9: ='[2]Migration calculations'!U17 -> 75 | AR9: =SUM(AS9:AZ9) -> 589.7 | AS9: ='[2]Migration calculations'!W17 -> 39.2 | AT9: ='[2]Migration calculations'!X17 -> 44.5 | AU9: ='[2]Migration calculations'!Y17 -> 288 | AV9: ='[2]Migration calculations'!Z17 -> 13 | AW9: ='[2]Migration calculations'!AA17 -> 63 | AX9: ='[2]Migration calculations'!AB17 -> 32 | AY9: ='[2]Migration calculations'!AC17 -> 90 | AZ9: ='[2]Migration calculations'!AD17 -> 20 | BV9: 2026 | BW9: =CJ9 -> 45 | BX9: =CL9 -> 120 | BY9: =CK9+CM9 -> 43.4 | BZ9: =CN9 -> 45 | CA9: =CH9 -> 250 | CB9: =CG9+CO9+CP9+CQ9 -> 172.40146 | CC9: =CF9-SUM(BW9:CB9) -> 0 | CE9: 2026 | CF9: ='[2]Migration calculations'!M17 -> 675.80146 | CG9: =CF9-CH9-CI9 -> 141.40146 | CH9: ='[2]Migration calculations'!AL17 -> 250 | CI9: =SUM(CJ9:CQ9) -> 284.4 | CJ9: ='[2]Migration calculations'!AN17 -> 45 | CK9: ='[2]Migration calculations'!AO17 -> 23.4 | CL9: ='[2]Migration calculations'!AP17 -> 120 | CM9: ='[2]Migration calculations'!AQ17 -> 20 | CN9: ='[2]Migration calculations'!AR17 -> 45 | CO9: ='[2]Migration calculations'!AS17 -> 20 | CP9: ='[2]Migration calculations'!AT17 -> 6 | CQ9: ='[2]Migration calculations'!AU17 -> 5 | DM9: 2029 | DN9: =100*(Data!B63/Data!$B$58) -> 106.64783 | DO9: =100*('OBR Nov25 ST1.1'!R119/'OBR Nov25 ST1.1'!$R$114) -> 107.60945 | DP9: ='OBR Nov25 C2.25'!M31 -> 106.96116 | DQ9: ='OBR Nov25 C2.25'!N31 -> 105.82839 | DR9: ='OBR Nov25 C2.25'!O31-'Chart Data'!DQ9 -> 1.9043356 | DT9: 1979 | DU9: =100*((Data!M13/Data!M12)-1) -> 0.61644762 | DW9: 0 | DX9: 65 | DY9: 60 | EA9: 34121 | EB9: =100*(HAVERM!C48/HAVERM!B48) -> 21.681261 | EC9: =AVERAGE($EB$7:$EB$399) -> 25.050854 | EE9: =HAVERM!C48 -> 1857 | EF9: =HAVERM!B48-HAVERM!C48 -> 6708 | EI9: 2022 | EJ9: 2023 | EK9: 2024 | EL9: 2025 | EM9: 2026 | EN9: 2027 | EO9: 2028 | EP9: 2029 | EQ9: 2030 | ER9: 2031 | ES9: 2032 | ET9: 2033 | EU9: 2034 | EV9: 2035 | EW9: 2036 | EX9: 2037 | EY9: 2038 | EZ9: 2039 | FA9: 2040 | FB9: 2041 | FC9: 2042 | FD9: 2043 | FE9: 2044 | FF9: 2045 | FG9: 2046 | FH9: 2047 | FI9: 2048 | FJ9: 2049 | FK9: 2050 | FL9: 2051 | FM9: 2052 | FN9: 2053 | FO9: 2054 | FP9: 2055 | FQ9: 2056 | FR9: 2057 | FS9: 2058 | FT9: 2059 | FU9: 2060 | GL9: ='OBR Nov25 ST1.15'!B75 -> 2028-29 | GM9: ='OBR Nov25 ST1.15'!O75 -> 0.7367156 | GN9: ='OBR Nov25 ST1.15'!M75 -> 1.3662466 | GP9: ='OBR Nov25 ST1.15'!F75 -> 57580.175 | GQ9: ='OBR Nov25 ST1.15'!D75 -> 2962831.6 | GR9: =GR8+M33-P33 -> -610.19557 | GS9: =GR9*$GR$12 -> -512.35723 | GT9: =GP9+GS9 -> 57067.818 | GU9: =100*((GT9/GT8)-1) -> 0.56043231 | GV9: =GN9-GM9+GU9 -> 1.1899633 | GW9: =GW8*(1+GV9/100) -> 2936629 | GX9: =100*((GW9/GQ9)-1) -> -0.88437876 | GZ9: 2020 | HA9: =100*(Data!B54/Data!$B$57) -> 87.379895 | HB9: =HA9 -> 87.379895 | HD9: =100*((HB9/HA9)-1) -> 0
A10: 1986 | B10: =Data!F20*Data!G20 -> 846672.61 | C10: =Data!H20/Data!I20 -> 8.8112396 | D10: =Data!E20 -> 1343092 | E10: =Data!J20 -> -1.752906 | F10: =Data!D20 -> 1320242 | G10: =Data!B20 -> 1323173 | I10: =100*((F10/F9)-1) -> 2.5781238 | J10: =100*((G10/G9)-1) -> 3.1151029 | L10: 2006 | M10: ='[2]2022-based'!L13 -> 254.5 | R10: 2026 | S10: ='[2]2022-based'!Q33 -> 69592.921 | T10: 70414.3 | U10: 69850.426 | V10: =V9*W10/W9 -> 69831.52 | W10: 69945.985 | Y10: 2018 | Z10: =SUMIF('ONS Nov25 T1'!$L:$L,'Chart Data'!$Y10,'ONS Nov25 T1'!$C:$C)/1000 -> 757 | AA10: =SUMIF('ONS Nov25 T1'!$M:$M,'Chart Data'!$Y10,'ONS Nov25 T1'!$C:$C)/1000 -> 541 | AB10: =SUMIF('ONS Nov25 T1'!$N:$N,'Chart Data'!$Y10,'ONS Nov25 T1'!$C:$C)/1000 -> 216 | AC10: =Z10-AA10 -> 216 | AE10: 2027 | AF10: =AS10 -> 70 | AG10: =AU10 -> 288 | AH10: =AT10+AV10 -> 48 | AI10: =AW10 -> 60 | AJ10: =AQ10 -> 80 | AK10: =AP10+AX10+AY10+AZ10 -> 233.96392 | AL10: =AO10-SUM(AF10:AK10) -> 0 | AN10: 2027 | AO10: ='[2]Migration calculations'!L18 -> 779.96392 | AP10: =AO10-AQ10-AR10 -> 105.96392 | AQ10: ='[2]Migration calculations'!U18 -> 80 | AR10: =SUM(AS10:AZ10) -> 594 | AS10: ='[2]Migration calculations'!W18 -> 70 | AT10: ='[2]Migration calculations'!X18 -> 35 | AU10: ='[2]Migration calculations'!Y18 -> 288 | AV10: ='[2]Migration calculations'!Z18 -> 13 | AW10: ='[2]Migration calculations'!AA18 -> 60 | AX10: ='[2]Migration calculations'!AB18 -> 23 | AY10: ='[2]Migration calculations'!AC18 -> 85 | AZ10: ='[2]Migration calculations'!AD18 -> 20 | BV10: 2027 | BW10: =CJ10 -> 40 | BX10: =CL10 -> 120 | BY10: =CK10+CM10 -> 40.8 | BZ10: =CN10 -> 40 | CA10: =CH10 -> 250 | CB10: =CG10+CO10+CP10+CQ10 -> 150.09854 | CC10: =CF10-SUM(BW10:CB10) -> 0 | CE10: 2027 | CF10: ='[2]Migration calculations'!M18 -> 640.89854 | CG10: =CF10-CH10-CI10 -> 134.09854 | CH10: ='[2]Migration calculations'!AL18 -> 250 | CI10: =SUM(CJ10:CQ10) -> 256.8 | CJ10: ='[2]Migration calculations'!AN18 -> 40 | CK10: ='[2]Migration calculations'!AO18 -> 20.8 | CL10: ='[2]Migration calculations'!AP18 -> 120 | CM10: ='[2]Migration calculations'!AQ18 -> 20 | CN10: ='[2]Migration calculations'!AR18 -> 40 | CO10: ='[2]Migration calculations'!AS18 -> 10 | CP10: ='[2]Migration calculations'!AT18 -> 4 | CQ10: ='[2]Migration calculations'!AU18 -> 2 | DM10: 2030 | DN10: =100*(Data!B64/Data!$B$58) -> 108.2189 | DO10: =100*('OBR Nov25 ST1.1'!R120/'OBR Nov25 ST1.1'!$R$114) -> 109.27672 | DT10: 1980 | DU10: =100*((Data!M14/Data!M13)-1) -> 0.61267083 | DW10: 0 | DX10: 65 | DY10: 60 | EA10: 34151 | EB10: =100*(HAVERM!C49/HAVERM!B49) -> 21.949802 | EC10: =AVERAGE($EB$7:$EB$399) -> 25.050854 | EE10: =HAVERM!C49 -> 1889 | EF10: =HAVERM!B49-HAVERM!C49 -> 6717 | EH10: 0-15 | EI10: =SUM('ONS popproj by year Jan25'!C2:C17,'ONS popproj by year Jan25'!C109:C124) -> 12397632 | EJ10: =SUM('ONS popproj by year Jan25'!D2:D17,'ONS popproj by year Jan25'!D109:D124) -> 12397236 | EK10: =SUM('ONS popproj by year Jan25'!E2:E17,'ONS popproj by year Jan25'!E109:E124) -> 12336987 | EL10: =SUM('ONS popproj by year Jan25'!F2:F17,'ONS popproj by year Jan25'!F109:F124) -> 12271926 | EM10: =SUM('ONS popproj by year Jan25'!G2:G17,'ONS popproj by year Jan25'!G109:G124) -> 12188266 | EN10: =SUM('ONS popproj by year Jan25'!H2:H17,'ONS popproj by year Jan25'!H109:H124) -> 12080358 | EO10: =SUM('ONS popproj by year Jan25'!I2:I17,'ONS popproj by year Jan25'!I109:I124) -> 11959025 | EP10: =SUM('ONS popproj by year Jan25'!J2:J17,'ONS popproj by year Jan25'!J109:J124) -> 11857264 | ... FU10: =SUM('ONS popproj by year Jan25'!AO2:AO17,'ONS popproj by year Jan25'!AO109:AO124) -> 11389081 | GL10: ='OBR Nov25 ST1.15'!B76 -> 2029-30 | GM10: ='OBR Nov25 ST1.15'!O76 -> 0.72803113 | GN10: ='OBR Nov25 ST1.15'!M76 -> 1.4860266 | GP10: ='OBR Nov25 ST1.15'!F76 -> 57999.377 | GQ10: ='OBR Nov25 ST1.15'!D76 -> 3006860.1 | GR10: =GR9+M34-P34 -> -721.23904 | GS10: =GR10*$GR$12 -> -605.59607 | GT10: =GP10+GS10 -> 57393.781 | GU10: =100*((GT10/GT9)-1) -> 0.5711849 | GV10: =GN10-GM10+GU10 -> 1.3291803 | GW10: =GW9*(1+GV10/100) -> 2975662 | GX10: =100*((GW10/GQ10)-1) -> -1.0375615 | GZ10: 2021 | HA10: =100*(Data!B55/Data!$B$57) -> 94.844857 | HB10: =HA10 -> 94.844857 | HD10: =100*((HB10/HA10)-1) -> 0
A11: 1987 | B11: =Data!F21*Data!G21 -> 854924.91 | C11: =Data!H21/Data!I21 -> 8.9162753 | D11: =Data!E21 -> 1373292 | E11: =Data!J21 -> -1.741462 | F11: =Data!D21 -> 1357335 | G11: =Data!B21 -> 1395353 | I11: =100*((F11/F10)-1) -> 2.8095607 | J11: =100*((G11/G10)-1) -> 5.455069 | L11: 2007 | M11: ='[2]2022-based'!L14 -> 304.6 | R11: 2027 | S11: ='[2]2022-based'!Q34 -> 69742.9 | T11: 70861.913 | U11: 70106.549 | V11: =V10*W11/W10 -> 70096.392 | W11: 70211.29 | Y11: 2019 | Z11: =SUMIF('ONS Nov25 T1'!$L:$L,'Chart Data'!$Y11,'ONS Nov25 T1'!$C:$C)/1000 -> 821 | AA11: =SUMIF('ONS Nov25 T1'!$M:$M,'Chart Data'!$Y11,'ONS Nov25 T1'!$C:$C)/1000 -> 597 | AB11: =SUMIF('ONS Nov25 T1'!$N:$N,'Chart Data'!$Y11,'ONS Nov25 T1'!$C:$C)/1000 -> 224 | AC11: =Z11-AA11 -> 224 | AE11: 2028 | AF11: =AS11 -> 85 | AG11: =AU11 -> 288 | AH11: =AT11+AV11 -> 55.5 | AI11: =AW11 -> 60 | AJ11: =AQ11 -> 80 | AK11: =AP11+AX11+AY11+AZ11 -> 221.30026 | AL11: =AO11-SUM(AF11:AK11) -> 0 | AN11: 2028 | AO11: ='[2]Migration calculations'!L19 -> 789.80026 | AP11: =AO11-AQ11-AR11 -> 107.30026 | AQ11: ='[2]Migration calculations'!U19 -> 80 | AR11: =SUM(AS11:AZ11) -> 602.5 | AS11: ='[2]Migration calculations'!W19 -> 85 | AT11: ='[2]Migration calculations'!X19 -> 42.5 | AU11: ='[2]Migration calculations'!Y19 -> 288 | AV11: ='[2]Migration calculations'!Z19 -> 13 | AW11: ='[2]Migration calculations'!AA19 -> 60 | AX11: ='[2]Migration calculations'!AB19 -> 14 | AY11: ='[2]Migration calculations'!AC19 -> 80 | AZ11: ='[2]Migration calculations'!AD19 -> 20 | BV11: 2028 | BW11: =CJ11 -> 35 | BX11: =CL11 -> 120 | BY11: =CK11+CM11 -> 38.2 | BZ11: =CN11 -> 37 | CA11: =CH11 -> 250 | CB11: =CG11+CO11+CP11+CQ11 -> 132.11861 | CC11: =CF11-SUM(BW11:CB11) -> 0 | CE11: 2028 | CF11: ='[2]Migration calculations'!M19 -> 612.31861 | CG11: =CF11-CH11-CI11 -> 128.11861 | CH11: ='[2]Migration calculations'!AL19 -> 250 | CI11: =SUM(CJ11:CQ11) -> 234.2 | CJ11: ='[2]Migration calculations'!AN19 -> 35 | CK11: ='[2]Migration calculations'!AO19 -> 18.2 | CL11: ='[2]Migration calculations'!AP19 -> 120 | CM11: ='[2]Migration calculations'!AQ19 -> 20 | CN11: ='[2]Migration calculations'!AR19 -> 37 | CO11: ='[2]Migration calculations'!AS19 -> 0 | CP11: ='[2]Migration calculations'!AT19 -> 2 | CQ11: ='[2]Migration calculations'!AU19 -> 2 | DT11: 1981 | DU11: =100*((Data!M15/Data!M14)-1) -> 0.57075665 | DW11: 0 | DX11: 65 | DY11: 60 | EA11: 34182 | EB11: =100*(HAVERM!C50/HAVERM!B50) -> 21.950367 | EC11: =AVERAGE($EB$7:$EB$399) -> 25.050854 | EE11: =HAVERM!C50 -> 1884 | EF11: =HAVERM!B50-HAVERM!C50 -> 6699 | EH11: 16-64 | EI11: =SUM('ONS popproj by year Jan25'!C18:C66,'ONS popproj by year Jan25'!C125:C173) -> 42468848 | EJ11: =SUM('ONS popproj by year Jan25'!D18:D66,'ONS popproj by year Jan25'!D125:D173) -> 43160304 | EK11: =SUM('ONS popproj by year Jan25'!E18:E66,'ONS popproj by year Jan25'!E125:E173) -> 43725847 | EL11: =SUM('ONS popproj by year Jan25'!F18:F66,'ONS popproj by year Jan25'!F125:F173) -> 44191288 | EM11: =SUM('ONS popproj by year Jan25'!G18:G66,'ONS popproj by year Jan25'!G125:G173) -> 44556445 | EN11: =SUM('ONS popproj by year Jan25'!H18:H66,'ONS popproj by year Jan25'!H125:H173) -> 44826638 | EO11: =SUM('ONS popproj by year Jan25'!I18:I66,'ONS popproj by year Jan25'!I125:I173) -> 44999376 | EP11: =SUM('ONS popproj by year Jan25'!J18:J66,'ONS popproj by year Jan25'!J125:J173) -> 45137247 | ... FU11: =SUM('ONS popproj by year Jan25'!AO18:AO66,'ONS popproj by year Jan25'!AO125:AO173) -> 47518437 | GZ11: 2022 | HA11: =100*(Data!B56/Data!$B$57) -> 99.729086 | HB11: =HA11 -> 99.729086 | HD11: =100*((HB11/HA11)-1) -> 0
A12: 1988 | B12: =Data!F22*Data!G22 -> 869416.83 | C12: =Data!H22/Data!I22 -> 9.0335852 | D12: =Data!E22 -> 1416696 | E12: =Data!J22 -> -1.730137 | F12: =Data!D22 -> 1405883 | G12: =Data!B22 -> 1471002 | I12: =100*((F12/F11)-1) -> 3.5767147 | J12: =100*((G12/G11)-1) -> 5.4214955 | L12: 2008 | M12: ='[2]2022-based'!L15 -> 283.6 | R12: 2028 | S12: ='[2]2022-based'!Q35 -> 69926.569 | T12: 71208.101 | U12: 70387.142 | V12: =V11*W12/W11 -> 70387.343 | W12: 70502.718 | Y12: 2020 | Z12: =SUMIF('ONS Nov25 T1'!$L:$L,'Chart Data'!$Y12,'ONS Nov25 T1'!$C:$C)/1000 -> 736 | AA12: =SUMIF('ONS Nov25 T1'!$M:$M,'Chart Data'!$Y12,'ONS Nov25 T1'!$C:$C)/1000 -> 625 | AB12: =SUMIF('ONS Nov25 T1'!$N:$N,'Chart Data'!$Y12,'ONS Nov25 T1'!$C:$C)/1000 -> 111 | AC12: =Z12-AA12 -> 111 | AE12: 2029 | AF12: =AS12 -> 100 | AG12: =AU12 -> 292 | AH12: =AT12+AV12 -> 63 | AI12: =AW12 -> 60 | AJ12: =AQ12 -> 80 | AK12: =AP12+AX12+AY12+AZ12 -> 209.26546 | AL12: =AO12-SUM(AF12:AK12) -> 0 | AN12: 2029 | AO12: ='[2]Migration calculations'!L20 -> 804.26546 | AP12: =AO12-AQ12-AR12 -> 109.26546 | AQ12: ='[2]Migration calculations'!U20 -> 80 | AR12: =SUM(AS12:AZ12) -> 615 | AS12: ='[2]Migration calculations'!W20 -> 100 | AT12: ='[2]Migration calculations'!X20 -> 50 | AU12: ='[2]Migration calculations'!Y20 -> 292 | AV12: ='[2]Migration calculations'!Z20 -> 13 | AW12: ='[2]Migration calculations'!AA20 -> 60 | AX12: ='[2]Migration calculations'!AB20 -> 5 | AY12: ='[2]Migration calculations'!AC20 -> 75 | AZ12: ='[2]Migration calculations'!AD20 -> 20 | BV12: 2029 | BW12: =CJ12 -> 30 | BX12: =CL12 -> 120 | BY12: =CK12+CM12 -> 35.6 | BZ12: =CN12 -> 37 | CA12: =CH12 -> 250 | CB12: =CG12+CO12+CP12+CQ12 -> 127.57847 | CC12: =CF12-SUM(BW12:CB12) -> 0 | CE12: 2029 | CF12: ='[2]Migration calculations'!M20 -> 600.17847 | CG12: =CF12-CH12-CI12 -> 125.57847 | CH12: ='[2]Migration calculations'!AL20 -> 250 | CI12: =SUM(CJ12:CQ12) -> 224.6 | CJ12: ='[2]Migration calculations'!AN20 -> 30 | CK12: ='[2]Migration calculations'!AO20 -> 15.6 | CL12: ='[2]Migration calculations'!AP20 -> 120 | CM12: ='[2]Migration calculations'!AQ20 -> 20 | CN12: ='[2]Migration calculations'!AR20 -> 37 | CO12: ='[2]Migration calculations'!AS20 -> 0 | CP12: ='[2]Migration calculations'!AT20 -> 0 | CQ12: ='[2]Migration calculations'!AU20 -> 2 | DO12: =100*((DN10/DO10)-1) -> -0.96801371 | DT12: 1982 | DU12: =100*((Data!M16/Data!M15)-1) -> 0.4752789 | DW12: 0 | DX12: 65 | DY12: 60 | EA12: 34213 | EB12: =100*(HAVERM!C51/HAVERM!B51) -> 22.187282 | EC12: =AVERAGE($EB$7:$EB$399) -> 25.050854 | EE12: =HAVERM!C51 -> 1905 | EF12: =HAVERM!B51-HAVERM!C51 -> 6681 | EH12: 65+ | EI12: =SUM('ONS popproj by year Jan25'!C67:C108,'ONS popproj by year Jan25'!C174:C215) -> 12736281 | EJ12: =SUM('ONS popproj by year Jan25'!D67:D108,'ONS popproj by year Jan25'!D174:D215) -> 12934955 | EK12: =SUM('ONS popproj by year Jan25'!E67:E108,'ONS popproj by year Jan25'!E174:E215) -> 13163397 | EL12: =SUM('ONS popproj by year Jan25'!F67:F108,'ONS popproj by year Jan25'!F174:F215) -> 13404765 | EM12: =SUM('ONS popproj by year Jan25'!G67:G108,'ONS popproj by year Jan25'!G174:G215) -> 13669589 | EN12: =SUM('ONS popproj by year Jan25'!H67:H108,'ONS popproj by year Jan25'!H174:H215) -> 13954917 | EO12: =SUM('ONS popproj by year Jan25'!I67:I108,'ONS popproj by year Jan25'!I174:I215) -> 14249700 | EP12: =SUM('ONS popproj by year Jan25'!J67:J108,'ONS popproj by year Jan25'!J174:J215) -> 14553151 | ... FU12: =SUM('ONS popproj by year Jan25'!AO67:AO108,'ONS popproj by year Jan25'!AO174:AO215) -> 19897799 | FW12: 1962 | GL12: 16+ share of migrants | GR12: ='[2]2022-based'!$I$2+'[2]2022-based'!$I$4 -> 0.83966069 | GZ12: 2023 | HA12: =100*(Data!B57/Data!$B$57) -> 100 | HB12: =HA12 -> 100 | HD12: =100*((HB12/HA12)-1) -> 0
A13: 1989 | B13: =Data!F23*Data!G23 -> 881201.46 | C13: =Data!H23/Data!I23 -> 9.1558688 | D13: =Data!E23 -> 1468447 | E13: =Data!J23 -> -1.718885 | F13: =Data!D23 -> 1456761 | G13: =Data!B23 -> 1506644 | I13: =100*((F13/F12)-1) -> 3.6189356 | J13: =100*((G13/G12)-1) -> 2.4229743 | L13: 2009 | M13: ='[2]2022-based'!L16 -> 219.8 | R13: 2029 | S13: ='[2]2022-based'!Q36 -> 70130.217 | T13: 71547.662 | U13: 70696.611 | V13: =V12*W13/W12 -> 70698.372 | W13: 70814.258 | Y13: 2021 | Z13: =SUMIF('ONS Nov25 T1'!$L:$L,'Chart Data'!$Y13,'ONS Nov25 T1'!$C:$C)/1000 -> 818 | AA13: =SUMIF('ONS Nov25 T1'!$M:$M,'Chart Data'!$Y13,'ONS Nov25 T1'!$C:$C)/1000 -> 567 | AB13: =SUMIF('ONS Nov25 T1'!$N:$N,'Chart Data'!$Y13,'ONS Nov25 T1'!$C:$C)/1000 -> 251 | AC13: =Z13-AA13 -> 251 | AE13: 2030 | AF13: =AS13 -> 110 | AG13: =AU13 -> 297 | AH13: =AT13+AV13 -> 68 | AI13: =AW13 -> 61 | AJ13: =AQ13 -> 80 | AK13: =AP13+AX13+AY13+AZ13 -> 200.99485 | AL13: =AO13-SUM(AF13:AK13) -> 0 | AN13: 2030 | AO13: ='[2]Migration calculations'!L21 -> 816.99485 | AP13: =AO13-AQ13-AR13 -> 110.99485 | AQ13: ='[2]Migration calculations'!U21 -> 80 | AR13: =SUM(AS13:AZ13) -> 626 | AS13: ='[2]Migration calculations'!W21 -> 110 | AT13: ='[2]Migration calculations'!X21 -> 55 | AU13: ='[2]Migration calculations'!Y21 -> 297 | AV13: ='[2]Migration calculations'!Z21 -> 13 | AW13: ='[2]Migration calculations'!AA21 -> 61 | AX13: ='[2]Migration calculations'!AB21 -> 0 | AY13: ='[2]Migration calculations'!AC21 -> 70 | AZ13: ='[2]Migration calculations'!AD21 -> 20 | BV13: 2030 | BW13: =CJ13 -> 25 | BX13: =CL13 -> 120 | BY13: =CK13+CM13 -> 33 | BZ13: =CN13 -> 35 | CA13: =CH13 -> 250 | CB13: =CG13+CO13+CP13+CQ13 -> 125.03832 | CC13: =CF13-SUM(BW13:CB13) -> 0 | CE13: 2030 | CF13: ='[2]Migration calculations'!M21 -> 588.03832 | CG13: =CF13-CH13-CI13 -> 123.03832 | CH13: ='[2]Migration calculations'!AL21 -> 250 | CI13: =SUM(CJ13:CQ13) -> 215 | CJ13: ='[2]Migration calculations'!AN21 -> 25 | CK13: ='[2]Migration calculations'!AO21 -> 13 | CL13: ='[2]Migration calculations'!AP21 -> 120 | CM13: ='[2]Migration calculations'!AQ21 -> 20 | CN13: ='[2]Migration calculations'!AR21 -> 35 | CO13: ='[2]Migration calculations'!AS21 -> 0 | CP13: ='[2]Migration calculations'!AT21 -> 0 | CQ13: ='[2]Migration calculations'!AU21 -> 2 | DT13: 1983 | DU13: =100*((Data!M17/Data!M16)-1) -> 0.70478951 | DV13: =AVERAGE(DU4:DU13) -> 0.42994854 | DW13: 0 | DX13: 65 | DY13: 60 | EA13: 34243 | EB13: =100*(HAVERM!C52/HAVERM!B52) -> 22.563744 | EC13: =AVERAGE($EB$7:$EB$399) -> 25.050854 | EE13: =HAVERM!C52 -> 1938 | EF13: =HAVERM!B52-HAVERM!C52 -> 6651 | EH13: Total | EI13: =SUM('ONS popproj by year Jan25'!C2:C215) -> 67602761 | EJ13: =SUM('ONS popproj by year Jan25'!D2:D215) -> 68492495 | EK13: =SUM('ONS popproj by year Jan25'!E2:E215) -> 69226231 | EL13: =SUM('ONS popproj by year Jan25'!F2:F215) -> 69867979 | EM13: =SUM('ONS popproj by year Jan25'!G2:G215) -> 70414300 | EN13: =SUM('ONS popproj by year Jan25'!H2:H215) -> 70861913 | EO13: =SUM('ONS popproj by year Jan25'!I2:I215) -> 71208101 | EP13: =SUM('ONS popproj by year Jan25'!J2:J215) -> 71547662 | ... FU13: =SUM('ONS popproj by year Jan25'!AO2:AO215) -> 78805317 | GZ13: 2024 | HA13: =100*(Data!B58/Data!$B$57) -> 101.08813 | HB13: =HA13 -> 101.08813 | HD13: =100*((HB13/HA13)-1) -> 0
A14: 1990 | B14: =Data!F24*Data!G24 -> 879722.49 | C14: =Data!H24/Data!I24 -> 9.2673112 | D14: =Data!E24 -> 1526420 | E14: =Data!J24 -> -1.707707 | F14: =Data!D24 -> 1496084 | G14: =Data!B24 -> 1515202 | I14: =100*((F14/F13)-1) -> 2.6993446 | J14: =100*((G14/G13)-1) -> 0.56801739 | L14: 2010 | M14: ='[2]2022-based'!L17 -> 255.4 | R14: 2030 | S14: ='[2]2022-based'!Q37 -> 70351.5 | T14: 71879.988 | U14: 71011.585 | V14: =V13*W14/W13 -> 71009.871 | W14: 71126.267 | Y14: 2022 | Z14: =SUMIF('ONS Nov25 T1'!$L:$L,'Chart Data'!$Y14,'ONS Nov25 T1'!$C:$C)/1000 -> 1167 | AA14: =SUMIF('ONS Nov25 T1'!$M:$M,'Chart Data'!$Y14,'ONS Nov25 T1'!$C:$C)/1000 -> 486 | AB14: =SUMIF('ONS Nov25 T1'!$N:$N,'Chart Data'!$Y14,'ONS Nov25 T1'!$C:$C)/1000 -> 681 | AC14: =Z14-AA14 -> 681 | AE14: 2031 | AF14: =AS14 -> 120 | AG14: =AU14 -> 300 | AH14: =AT14+AV14 -> 73 | AI14: =AW14 -> 62 | AJ14: =AQ14 -> 80 | AK14: =AP14+AX14+AY14+AZ14 -> 198.19588 | AL14: =AO14-SUM(AF14:AK14) -> 0 | AN14: 2031 | AO14: ='[2]Migration calculations'!L22 -> 833.19588 | AP14: =AO14-AQ14-AR14 -> 113.19588 | AQ14: ='[2]Migration calculations'!U22 -> 80 | AR14: =SUM(AS14:AZ14) -> 640 | AS14: ='[2]Migration calculations'!W22 -> 120 | AT14: ='[2]Migration calculations'!X22 -> 60 | AU14: ='[2]Migration calculations'!Y22 -> 300 | AV14: ='[2]Migration calculations'!Z22 -> 13 | AW14: ='[2]Migration calculations'!AA22 -> 62 | AX14: ='[2]Migration calculations'!AB22 -> 0 | AY14: ='[2]Migration calculations'!AC22 -> 65 | AZ14: ='[2]Migration calculations'!AD22 -> 20 | BV14: 2031 | BW14: =CJ14 -> 23.5 | BX14: =CL14 -> 120 | BY14: =CK14+CM14 -> 32.22 | BZ14: =CN14 -> 33 | CA14: =CH14 -> 250 | CB14: =CG14+CO14+CP14+CQ14 -> 123.90584 | CC14: =CF14-SUM(BW14:CB14) -> 0 | CE14: 2031 | CF14: ='[2]Migration calculations'!M22 -> 582.62584 | CG14: =CF14-CH14-CI14 -> 121.90584 | CH14: ='[2]Migration calculations'!AL22 -> 250 | CI14: =SUM(CJ14:CQ14) -> 210.72 | CJ14: ='[2]Migration calculations'!AN22 -> 23.5 | CK14: ='[2]Migration calculations'!AO22 -> 12.22 | CL14: ='[2]Migration calculations'!AP22 -> 120 | CM14: ='[2]Migration calculations'!AQ22 -> 20 | CN14: ='[2]Migration calculations'!AR22 -> 33 | CO14: ='[2]Migration calculations'!AS22 -> 0 | CP14: ='[2]Migration calculations'!AT22 -> 0 | CQ14: ='[2]Migration calculations'!AU22 -> 2 | DT14: 1984 | DU14: =100*((Data!M18/Data!M17)-1) -> 0.697956 | DV14: =AVERAGE(DU5:DU14) -> 0.49694176 | DW14: 0 | DX14: 65 | DY14: 60 | EA14: 34274 | EB14: =100*(HAVERM!C53/HAVERM!B53) -> 22.481072 | EC14: =AVERAGE($EB$7:$EB$399) -> 25.050854 | EE14: =HAVERM!C53 -> 1930 | EF14: =HAVERM!B53-HAVERM!C53 -> 6655 | EH14: check | EI14: =EI13-EI10-EI11-EI12 -> 0 | EJ14: =EJ13-EJ10-EJ11-EJ12 -> 0 | EK14: =EK13-EK10-EK11-EK12 -> 0 | EL14: =EL13-EL10-EL11-EL12 -> 0 | EM14: =EM13-EM10-EM11-EM12 -> 0 | EN14: =EN13-EN10-EN11-EN12 -> 0 | EO14: =EO13-EO10-EO11-EO12 -> 0 | EP14: =EP13-EP10-EP11-EP12 -> 0 | ... FU14: =FU13-FU10-FU11-FU12 -> 0 | GL14: 5yr growth | GP14: =100*((GP10/GP5)^(1/5)-1) -> 0.76073012 | GQ14: =100*((GQ10/GQ5)^(1/5)-1) -> 1.3930014 | GT14: =100*((GT10/GT5)^(1/5)-1) -> 0.57568722 | GW14: =100*((GW10/GW5)^(1/5)-1) -> 1.2079516 | GZ14: 2025 | HA14: =100*(Data!B59/Data!$B$57) -> 102.4843 | HB14: =HB13*(1+HF14/100) -> 102.58761 | HD14: =100*((HB14/HA14)-1) -> 0.10080507 | HF14: =100*(('OBR Nov25 ST1.1'!R115/'OBR Nov25 ST1.1'!R114)-1) -> 1.4833428
A15: 1991 | B15: =Data!F25*Data!G25 -> 861885.45 | C15: =Data!H25/Data!I25 -> 9.3754123 | D15: =Data!E25 -> 1575894 | E15: =Data!J25 -> -1.696601 | F15: =Data!D25 -> 1517014 | G15: =Data!B25 -> 1493903 | I15: =100*((F15/F14)-1) -> 1.3989856 | J15: =100*((G15/G14)-1) -> -1.4056872 | L15: 2011 | M15: ='[2]2022-based'!L18 -> 270.3 | R15: 2031 | S15: ='[2]2022-based'!Q38 -> 70586.656 | T15: 72204.574 | U15: 71318.66 | Y15: 2023 | Z15: =SUMIF('ONS Nov25 T1'!$L:$L,'Chart Data'!$Y15,'ONS Nov25 T1'!$C:$C)/1000 -> 1466 | AA15: =SUMIF('ONS Nov25 T1'!$M:$M,'Chart Data'!$Y15,'ONS Nov25 T1'!$C:$C)/1000 -> 543 | AB15: =SUMIF('ONS Nov25 T1'!$N:$N,'Chart Data'!$Y15,'ONS Nov25 T1'!$C:$C)/1000 -> 924 | AC15: =Z15-AA15 -> 923 | AE15: 2032 | AF15: =AS15 -> 135 | AG15: =AU15 -> 300 | AH15: =AT15+AV15 -> 80.5 | AI15: =AW15 -> 63 | AJ15: =AQ15 -> 80 | AK15: =AP15+AX15+AY15+AZ15 -> 196.10438 | AL15: =AO15-SUM(AF15:AK15) -> 0 | AN15: 2032 | AO15: ='[2]Migration calculations'!L23 -> 854.60438 | AP15: =AO15-AQ15-AR15 -> 116.10438 | AQ15: ='[2]Migration calculations'!U23 -> 80 | AR15: =SUM(AS15:AZ15) -> 658.5 | AS15: ='[2]Migration calculations'!W23 -> 135 | AT15: ='[2]Migration calculations'!X23 -> 67.5 | AU15: ='[2]Migration calculations'!Y23 -> 300 | AV15: ='[2]Migration calculations'!Z23 -> 13 | AW15: ='[2]Migration calculations'!AA23 -> 63 | AX15: ='[2]Migration calculations'!AB23 -> 0 | AY15: ='[2]Migration calculations'!AC23 -> 60 | AZ15: ='[2]Migration calculations'!AD23 -> 20 | BV15: 2032 | BW15: =CJ15 -> 23.5 | BX15: =CL15 -> 120 | BY15: =CK15+CM15 -> 32.22 | BZ15: =CN15 -> 33 | CA15: =CH15 -> 250 | CB15: =CG15+CO15+CP15+CQ15 -> 123.90584 | CC15: =CF15-SUM(BW15:CB15) -> 0 | CE15: 2032 | CF15: ='[2]Migration calculations'!M23 -> 582.62584 | CG15: =CF15-CH15-CI15 -> 121.90584 | CH15: ='[2]Migration calculations'!AL23 -> 250 | CI15: =SUM(CJ15:CQ15) -> 210.72 | CJ15: ='[2]Migration calculations'!AN23 -> 23.5 | CK15: ='[2]Migration calculations'!AO23 -> 12.22 | CL15: ='[2]Migration calculations'!AP23 -> 120 | CM15: ='[2]Migration calculations'!AQ23 -> 20 | CN15: ='[2]Migration calculations'!AR23 -> 33 | CO15: ='[2]Migration calculations'!AS23 -> 0 | CP15: ='[2]Migration calculations'!AT23 -> 0 | CQ15: ='[2]Migration calculations'!AU23 -> 2 | DT15: 1985 | DU15: =100*((Data!M19/Data!M18)-1) -> 0.49341661 | DV15: =AVERAGE(DU6:DU15) -> 0.54780629 | DW15: 0 | DX15: 65 | DY15: 60 | EA15: 34304 | EB15: =100*(HAVERM!C54/HAVERM!B54) -> 22.434479 | EC15: =AVERAGE($EB$7:$EB$399) -> 25.050854 | EE15: =HAVERM!C54 -> 1926 | EF15: =HAVERM!B54-HAVERM!C54 -> 6659 | GW15: =GW14-GQ14 -> -0.18504975 | GZ15: 2026 | HA15: =100*(Data!B60/Data!$B$57) -> 103.37763 | HB15: =HB14*(1+HF15/100) -> 103.99456 | HD15: =100*((HB15/HA15)-1) -> 0.59677386 | HF15: =100*(('OBR Nov25 ST1.1'!R116/'OBR Nov25 ST1.1'!R115)-1) -> 1.3714665
A16: 1992 | B16: =Data!F26*Data!G26 -> 848974.43 | C16: =Data!H26/Data!I26 -> 9.4785328 | D16: =Data!E26 -> 1605639 | E16: =Data!J26 -> -1.685568 | F16: =Data!D26 -> 1538270 | G16: =Data!B26 -> 1498023 | I16: =100*((F16/F15)-1) -> 1.4011736 | J16: =100*((G16/G15)-1) -> 0.27578765 | L16: 2012 | M16: =AB4 -> 162 | R16: 2032 | S16: ='[2]2022-based'!Q39 -> 70835.233 | T16: 72521.173 | U16: 71617.737 | Y16: 2024 | Z16: =SUMIF('ONS Nov25 T1'!$L:$L,'Chart Data'!$Y16,'ONS Nov25 T1'!$C:$C)/1000 -> 1299 | AA16: =SUMIF('ONS Nov25 T1'!$M:$M,'Chart Data'!$Y16,'ONS Nov25 T1'!$C:$C)/1000 -> 650 | AB16: =SUMIF('ONS Nov25 T1'!$N:$N,'Chart Data'!$Y16,'ONS Nov25 T1'!$C:$C)/1000 -> 649 | AC16: =Z16-AA16 -> 649 | DT16: 1986 | DU16: =100*((Data!M20/Data!M19)-1) -> 0.41478282 | DV16: =AVERAGE(DU7:DU16) -> 0.57901966 | DW16: 0 | DX16: 65 | DY16: 60 | EA16: 34335 | EB16: =100*(HAVERM!C55/HAVERM!B55) -> 22.336089 | EC16: =AVERAGE($EB$7:$EB$399) -> 25.050854 | EE16: =HAVERM!C55 -> 1918 | EF16: =HAVERM!B55-HAVERM!C55 -> 6669 | FW16: 1963 | GW16: =100*((GW10/GQ10)-1) -> -1.0375615 | GZ16: 2027 | HA16: =100*(Data!B61/Data!$B$57) -> 104.75982 | HB16: =HB15*(1+HF16/100) -> 105.59882 | HD16: =100*((HB16/HA16)-1) -> 0.80088474 | HF16: =100*(('OBR Nov25 ST1.1'!R117/'OBR Nov25 ST1.1'!R116)-1) -> 1.5426381
A17: 1993 | B17: =Data!F27*Data!G27 -> 843846.96 | C17: =Data!H27/Data!I27 -> 9.5656692 | D17: =Data!E27 -> 1635840 | E17: =Data!J27 -> -1.674606 | F17: =Data!D27 -> 1563590 | G17: =Data!B27 -> 1532082 | I17: =100*((F17/F16)-1) -> 1.6460049 | J17: =100*((G17/G16)-1) -> 2.2735966 | L17: 2013 | M17: =AB5 -> 215 | R17: 2033 | S17: ='[2]2022-based'!Q40 -> 71076.06 | T17: 72830.021 | U17: 71909.247 | Y17: 2025 | Z17: =SUMIF('ONS Nov25 T1'!$L:$L,'Chart Data'!$Y17,'ONS Nov25 T1'!$C:$C)/1000 -> 898 | AA17: =SUMIF('ONS Nov25 T1'!$M:$M,'Chart Data'!$Y17,'ONS Nov25 T1'!$C:$C)/1000 -> 693 | AB17: =SUMIF('ONS Nov25 T1'!$N:$N,'Chart Data'!$Y17,'ONS Nov25 T1'!$C:$C)/1000 -> 204 | AC17: =Z17-AA17 -> 205 | DT17: 1987 | DU17: =100*((Data!M21/Data!M20)-1) -> 0.4090401 | DV17: =AVERAGE(DU8:DU17) -> 0.56154408 | DW17: 0 | DX17: 65 | DY17: 60 | EA17: 34366 | EB17: =100*(HAVERM!C56/HAVERM!B56) -> 22.272727 | EC17: =AVERAGE($EB$7:$EB$399) -> 25.050854 | EE17: =HAVERM!C56 -> 1911 | EF17: =HAVERM!B56-HAVERM!C56 -> 6669 | GZ17: 2028 | HA17: =100*(Data!B62/Data!$B$57) -> 106.26925 | HB17: =HB16*(1+HF17/100) -> 107.14842 | HD17: =100*((HB17/HA17)-1) -> 0.82730453 | HF17: =100*(('OBR Nov25 ST1.1'!R118/'OBR Nov25 ST1.1'!R117)-1) -> 1.4674362
A18: 1994 | B18: =Data!F28*Data!G28 -> 851546.12 | C18: =Data!H28/Data!I28 -> 9.6325984 | D18: =Data!E28 -> 1671807 | E18: =Data!J28 -> -1.663716 | F18: =Data!D28 -> 1604512 | G18: =Data!B28 -> 1584459 | I18: =100*((F18/F17)-1) -> 2.6171823 | J18: =100*((G18/G17)-1) -> 3.4186812 | L18: 2014 | M18: =AB6 -> 248 | R18: 2034 | S18: ='[2]2022-based'!Q41 -> 71309.615 | T18: 73131.597 | U18: 72193.851 | Y18: 2026 | Z18: =AO9 -> 769.2018 | AA18: =CF9 -> 675.80146 | AB18: =Z18-AA18 -> 93.400344 | DT18: 1988 | DU18: =100*((Data!M22/Data!M21)-1) -> 0.30865471 | DV18: =AVERAGE(DU9:DU18) -> 0.53037937 | DW18: 0 | DX18: 65 | DY18: 60 | EA18: 34394 | EB18: =100*(HAVERM!C57/HAVERM!B57) -> 22.571628 | EC18: =AVERAGE($EB$7:$EB$399) -> 25.050854 | EE18: =HAVERM!C57 -> 1938 | EF18: =HAVERM!B57-HAVERM!C57 -> 6648 | GZ18: 2029 | HA18: =100*(Data!B63/Data!$B$57) -> 107.80829 | HB18: =HB17*(1+HF18/100) -> 108.78038 | HD18: =100*((HB18/HA18)-1) -> 0.90168259 | HF18: =100*(('OBR Nov25 ST1.1'!R119/'OBR Nov25 ST1.1'!R118)-1) -> 1.5230852
A19: 1995 | B19: =Data!F29*Data!G29 -> 858185.82 | C19: =Data!H29/Data!I29 -> 9.6889063 | D19: =Data!E29 -> 1712783 | E19: =Data!J29 -> -1.652896 | F19: =Data!D29 -> 1646030 | G19: =Data!B29 -> 1622576 | I19: =100*((F19/F18)-1) -> 2.587578 | J19: =100*((G19/G18)-1) -> 2.4056792 | L19: 2015 | M19: =AB7 -> 296 | R19: 2035 | S19: ='[2]2022-based'!Q42 -> 71536.164 | T19: 73426.168 | U19: 72472.001 | Y19: 2027 | Z19: =AO10 -> 779.96392 | AA19: =CF10 -> 640.89854 | AB19: =Z19-AA19 -> 139.06538 | DT19: 1989 | DU19: =100*((Data!M23/Data!M22)-1) -> 0.26095485 | DV19: =AVERAGE(DU10:DU19) -> 0.4948301 | DW19: 0 | DX19: 65 | DY19: 60 | EA19: 34425 | EB19: =100*(HAVERM!C58/HAVERM!B58) -> 22.539793 | EC19: =AVERAGE($EB$7:$EB$399) -> 25.050854 | EE19: =HAVERM!C58 -> 1940 | EF19: =HAVERM!B58-HAVERM!C58 -> 6667 | GZ19: 2030 | HA19: =100*(Data!B64/Data!$B$57) -> 109.39646 | HB19: =HB18*(1+HF19/100) -> 110.46578 | HD19: =100*((HB19/HA19)-1) -> 0.97747581 | HF19: =100*(('OBR Nov25 ST1.1'!R120/'OBR Nov25 ST1.1'!R119)-1) -> 1.5493637
A20: 1996 | B20: =Data!F30*Data!G30 -> 866753.2 | C20: =Data!H30/Data!I30 -> 9.720396 | D20: =Data!E30 -> 1754821 | E20: =Data!J30 -> -1.642147 | F20: =Data!D30 -> 1690512 | G20: =Data!B30 -> 1665005 | I20: =100*((F20/F19)-1) -> 2.7023809 | J20: =100*((G20/G19)-1) -> 2.614916 | L20: 2016 | M20: =AB8 -> 321 | R20: 2036 | S20: ='[2]2022-based'!Q43 -> 71756.064 | T20: 73714.089 | U20: 72744.274 | Y20: 2028 | Z20: =AO11 -> 789.80026 | AA20: =CF11 -> 612.31861 | AB20: =Z20-AA20 -> 177.48164 | DT20: 1990 | DU20: =100*((Data!M24/Data!M23)-1) -> 0.1888224 | DV20: =AVERAGE(DU11:DU20) -> 0.45244525 | DW20: 0 | DX20: 65 | DY20: 60 | EA20: 34455 | EB20: =100*(HAVERM!C59/HAVERM!B59) -> 22.62926 | EC20: =AVERAGE($EB$7:$EB$399) -> 25.050854 | EE20: =HAVERM!C59 -> 1952 | EF20: =HAVERM!B59-HAVERM!C59 -> 6674 | FW20: 1964 | GZ20: 2031 | HA20: =100*(Data!B65/Data!$B$57) -> 111.05912 | HB20: =HB19*(1+HF20/100) -> 112.65565 | HD20: =100*((HB20/HA20)-1) -> 1.437555 | HF20: {=TRANSPOSE('OBR LT economic determinants'!L7:AO7)} -> 1.9823941
A21: 1997 | B21: =Data!F31*Data!G31 -> 877828.41 | C21: =Data!H31/Data!I31 -> 9.7395726 | D21: =Data!E31 -> 1809000 | E21: =Data!J31 -> -1.632351 | F21: =Data!D31 -> 1738403 | G21: =Data!B31 -> 1746257 | I21: =100*((F21/F20)-1) -> 2.8329287 | J21: =100*((G21/G20)-1) -> 4.8799853 | L21: 2017 | M21: =AB9 -> 200 | R21: 2037 | S21: ='[2]2022-based'!Q44 -> 71969.894 | T21: 73995.941 | U21: 73011.327 | Y21: 2029 | Z21: =AO12 -> 804.26546 | AA21: =CF12 -> 600.17847 | AB21: =Z21-AA21 -> 204.087 | DT21: 1991 | DU21: =100*((Data!M25/Data!M24)-1) -> 0.1228944 | DV21: =AVERAGE(DU12:DU21) -> 0.40765903 | DW21: 0 | DX21: 65 | DY21: 60 | EA21: 34486 | EB21: =100*(HAVERM!C60/HAVERM!B60) -> 22.55814 | EC21: =AVERAGE($EB$7:$EB$399) -> 25.050854 | EE21: =HAVERM!C60 -> 1940 | EF21: =HAVERM!B60-HAVERM!C60 -> 6660 | GZ21: 2032 | HA21: =100*(Data!B66/Data!$B$57) -> 112.70629 | HB21: =HB20*(1+HF21/100) -> 114.92281 | HD21: =100*((HB21/HA21)-1) -> 1.9666274 | HF21: 2.0124631
A22: 1998 | B22: =Data!F32*Data!G32 -> 884900.46 | C22: =Data!H32/Data!I32 -> 9.7651529 | D22: =Data!E32 -> 1867000 | E22: =Data!J32 -> -1.626138 | F22: =Data!D32 -> 1778836 | G22: =Data!B32 -> 1802946 | I22: =100*((F22/F21)-1) -> 2.3258704 | J22: =100*((G22/G21)-1) -> 3.2463148 | L22: 2018 | M22: =AB10 -> 216 | R22: 2038 | S22: ='[2]2022-based'!Q45 -> 72178.266 | T22: 74272.334 | U22: 73273.897 | Y22: 2030 | Z22: =AO13 -> 816.99485 | AA22: =CF13 -> 588.03832 | AB22: =Z22-AA22 -> 228.95652 | DT22: 1992 | DU22: =100*((Data!M26/Data!M25)-1) -> 0.029350485 | DV22: =AVERAGE(DU13:DU22) -> 0.36306619 | DW22: 0 | DX22: 65 | DY22: 60 | EA22: 34516 | EB22: =100*(HAVERM!C61/HAVERM!B61) -> 22.628161 | EC22: =AVERAGE($EB$7:$EB$399) -> 25.050854 | EE22: =HAVERM!C61 -> 1951 | EF22: =HAVERM!B61-HAVERM!C61 -> 6671 | GZ22: 2033 | HA22: =100*(Data!B67/Data!$B$57) -> 114.33621 | HB22: =HB21*(1+HF22/100) -> 117.27771 | HD22: =100*((HB22/HA22)-1) -> 2.5726748 | HF22: 2.0491176
A23: 1999 | B23: =Data!F33*Data!G33 -> 895986.1 | C23: =Data!H33/Data!I33 -> 9.832806 | D23: =Data!E33 -> 1923000 | E23: =Data!J33 -> -1.620242 | F23: =Data!D33 -> 1827270 | G23: =Data!B33 -> 1856033 | I23: =100*((F23/F22)-1) -> 2.7227918 | J23: =100*((G23/G22)-1) -> 2.9444587 | L23: 2019 | M23: =AB11 -> 224 | R23: 2039 | S23: ='[2]2022-based'!Q46 -> 72381.648 | T23: 74543.738 | U23: 73532.487 | Y23: 2031 | Z23: =AO14 -> 833.19588 | AA23: =CF14 -> 582.62584 | AB23: =Z23-AA23 -> 250.57004 | DT23: 1993 | DU23: =100*((Data!M27/Data!M26)-1) -> 0.031557426 | DV23: =AVERAGE(DU14:DU23) -> 0.29574298 | DW23: 0 | DX23: 65 | DY23: 60 | EA23: 34547 | EB23: =100*(HAVERM!C62/HAVERM!B62) -> 22.804582 | EC23: =AVERAGE($EB$7:$EB$399) -> 25.050854 | EE23: =HAVERM!C62 -> 1971 | EF23: =HAVERM!B62-HAVERM!C62 -> 6672 | FX23: =100*((AVERAGE(HAVERQ!B7:B26)/AVERAGE(HAVERQ!B3:B22))-1) -> 1.7880317 | GZ23: 2034 | HA23: =100*(Data!B68/Data!$B$57) -> 116.0219 | HB23: =HB22*(1+HF23/100) -> 119.7076 | HD23: =100*((HB23/HA23)-1) -> 3.1767267 | HF23: 2.0719126
A24: 2000 | B24: =Data!F34*Data!G34 -> 897004.65 | C24: =Data!H34/Data!I34 -> 9.9743903 | D24: =Data!E34 -> 1983000 | E24: =Data!J34 -> -1.614367 | F24: =Data!D34 -> 1866820 | G24: =Data!B34 -> 1940007 | I24: =100*((F24/F23)-1) -> 2.1644311 | J24: =100*((G24/G23)-1) -> 4.5243808 | L24: 2020 | M24: =AB12 -> 111 | R24: 2040 | S24: ='[2]2022-based'!Q47 -> 72580.367 | T24: 74810.478 | U24: 73787.498 | Y24: 2032 | Z24: =AO15 -> 854.60438 | AA24: =CF15 -> 582.62584 | AB24: =Z24-AA24 -> 271.97854 | DT24: 1994 | DU24: =100*((Data!M28/Data!M27)-1) -> 0.16043493 | DV24: =AVERAGE(DU15:DU24) -> 0.24199087 | DW24: 0 | DX24: 65 | DY24: 60 | EA24: 34578 | EB24: =100*(HAVERM!C63/HAVERM!B63) -> 22.978576 | EC24: =AVERAGE($EB$7:$EB$399) -> 25.050854 | EE24: =HAVERM!C63 -> 1995 | EF24: =HAVERM!B63-HAVERM!C63 -> 6687 | FW24: 1965 | FX24: =100*((AVERAGE(HAVERQ!B8:B27)/AVERAGE(HAVERQ!B4:B23))-1) -> 1.9511989 | GZ24: 2035 | HA24: =100*(Data!B69/Data!$B$57) -> 117.74829 | HB24: =HB23*(1+HF24/100) -> 122.1948 | HD24: =100*((HB24/HA24)-1) -> 3.7762846 | HF24: 2.0777282
A25: 2001 | B25: =Data!F35*Data!G35 -> 906197.99 | C25: =Data!H35/Data!I35 -> 10.222141 | D25: =Data!E35 -> 2038000 | E25: =Data!J35 -> -1.608513 | F25: =Data!D35 -> 1923900 | G25: =Data!B35 -> 1986393 | I25: =100*((F25/F24)-1) -> 3.057606 | J25: =100*((G25/G24)-1) -> 2.3910223 | L25: 2021 | M25: =AB13 -> 251 | R25: 2041 | S25: ='[2]2022-based'!Q48 -> 72774.759 | T25: 75072.892 | U25: 74039.147 | DT25: 1995 | DU25: =100*((Data!M29/Data!M28)-1) -> 0.31204932 | DV25: =AVERAGE(DU16:DU25) -> 0.22385414 | DW25: 0 | DX25: 65 | DY25: 60 | EA25: 34608 | EB25: =100*(HAVERM!C64/HAVERM!B64) -> 23.105148 | EC25: =AVERAGE($EB$7:$EB$399) -> 25.050854 | EE25: =HAVERM!C64 -> 2015 | EF25: =HAVERM!B64-HAVERM!C64 -> 6706 | FX25: =100*((AVERAGE(HAVERQ!B9:B28)/AVERAGE(HAVERQ!B5:B24))-1) -> 2.1571429 | GZ25: 2036 | HA25: =100*(Data!B70/Data!$B$57) -> 119.51966 | HB25: =HB24*(1+HF25/100) -> 124.75532 | HD25: =100*((HB25/HA25)-1) -> 4.3805857 | HF25: 2.0954413
A26: 2002 | B26: =Data!F36*Data!G36 -> 905078.99 | C26: =Data!H36/Data!I36 -> 10.553831 | D26: =Data!E36 -> 2081000 | E26: =Data!J36 -> -1.602681 | F26: =Data!D36 -> 1969294 | G26: =Data!B36 -> 2020341 | I26: =100*((F26/F25)-1) -> 2.3594781 | J26: =100*((G26/G25)-1) -> 1.7090274 | L26: 2022 | M26: =AB14 -> 681 | R26: 2042 | S26: ='[2]2022-based'!Q49 -> 72965.055 | T26: 75331.209 | U26: 74287.558 | DT26: 1996 | DU26: =100*((Data!M30/Data!M29)-1) -> 0.36678279 | DV26: =AVERAGE(DU17:DU26) -> 0.21905414 | DW26: 0 | DX26: 65 | DY26: 60 | EA26: 34639 | EB26: =100*(HAVERM!C65/HAVERM!B65) -> 23.182285 | EC26: =AVERAGE($EB$7:$EB$399) -> 25.050854 | EE26: =HAVERM!C65 -> 2031 | EF26: =HAVERM!B65-HAVERM!C65 -> 6730 | FX26: =100*((AVERAGE(HAVERQ!B10:B29)/AVERAGE(HAVERQ!B6:B25))-1) -> 2.3831986 | GZ26: 2037 | HA26: =100*(Data!B71/Data!$B$57) -> 121.32725 | HB26: =HB25*(1+HF26/100) -> 127.44959 | HD26: =100*((HB26/HA26)-1) -> 5.0461379 | HF26: 2.1596476
A27: 2003 | B27: =Data!F37*Data!G37 -> 907433.11 | C27: =Data!H37/Data!I37 -> 10.921335 | D27: =Data!E37 -> 2118000 | E27: =Data!J37 -> -1.59687 | F27: =Data!D37 -> 2018424 | G27: =Data!B37 -> 2085366 | I27: =100*((F27/F26)-1) -> 2.4948027 | J27: =100*((G27/G26)-1) -> 3.2185161 | L27: 2023 | M27: =AB15 -> 924 | N27: {=TRANSPOSE('ONS popproj Jan25 pp'!C16:AN16)} -> 906 | O27: {=TRANSPOSE('ONS popproj Jan25 migcv'!C18:AN18)} -> 906 | P27: ='OBR Nov25 C2.8'!D37 -> 906 | R27: 2043 | S27: ='[2]2022-based'!Q50 -> 73151.06 | T27: 75585.236 | U27: 74532.48 | DT27: 1997 | DU27: =100*((Data!M31/Data!M30)-1) -> 0.35389738 | DV27: =AVERAGE(DU18:DU27) -> 0.21353987 | DW27: 0 | DX27: 65 | DY27: 60 | EA27: 34669 | EB27: =100*(HAVERM!C66/HAVERM!B66) -> 23.554798 | EC27: =AVERAGE($EB$7:$EB$399) -> 25.050854 | EE27: =HAVERM!C66 -> 2074 | EF27: =HAVERM!B66-HAVERM!C66 -> 6731 | FX27: =100*((AVERAGE(HAVERQ!B11:B30)/AVERAGE(HAVERQ!B7:B26))-1) -> 2.6066015 | GZ27: 2038 | HA27: =100*(Data!B72/Data!$B$57) -> 123.17024 | HB27: =HB26*(1+HF27/100) -> 130.11762 | HD27: =100*((HB27/HA27)-1) -> 5.6404713 | HF27: 2.0933983
A28: 2004 | B28: =Data!F38*Data!G38 -> 912728.12 | C28: =Data!H38/Data!I38 -> 11.276552 | D28: =Data!E38 -> 2149000 | E28: =Data!J38 -> -1.59108 | F28: =Data!D38 -> 2069413 | G28: =Data!B38 -> 2133872 | I28: =100*((F28/F27)-1) -> 2.5261788 | J28: =100*((G28/G27)-1) -> 2.3260186 | L28: 2024 | M28: =AB16 -> 649 | N28: 728 | O28: 728 | P28: ='OBR Nov25 C2.8'!D38 -> 739 | R28: 2044 | S28: ='[2]2022-based'!Q51 -> 73332.31 | T28: 75834.507 | U28: 74773.337 | DT28: 1998 | DU28: =100*((Data!M32/Data!M31)-1) -> 0.37481621 | DV28: =AVERAGE(DU19:DU28) -> 0.22015602 | DW28: 0 | DX28: 65 | DY28: 60 | EA28: 34700 | EB28: =100*(HAVERM!C67/HAVERM!B67) -> 23.656895 | EC28: =AVERAGE($EB$7:$EB$399) -> 25.050854 | EE28: =HAVERM!C67 -> 2074 | EF28: =HAVERM!B67-HAVERM!C67 -> 6693 | FW28: 1966 | FX28: =100*((AVERAGE(HAVERQ!B12:B31)/AVERAGE(HAVERQ!B8:B27))-1) -> 2.5482191 | GZ28: 2039 | HA28: =100*(Data!B73/Data!$B$57) -> 125.04833 | HB28: =HB27*(1+HF28/100) -> 132.76745 | HD28: =100*((HB28/HA28)-1) -> 6.1729116 | HF28: 2.0364854
A29: 2005 | B29: =Data!F39*Data!G39 -> 926585.3 | C29: =Data!H39/Data!I39 -> 11.571259 | D29: =Data!E39 -> 2193000 | E29: =Data!J39 -> -1.585311 | F29: =Data!D39 -> 2130628 | G29: =Data!B39 -> 2193421 | I29: =100*((F29/F28)-1) -> 2.9580852 | J29: =100*((G29/G28)-1) -> 2.7906547 | L29: 2025 | M29: =AB17 -> 204 | N29: 630.9 | O29: 350.251 | P29: ='OBR Nov25 C2.8'!D39 -> 290.77293 | R29: 2045 | S29: ='[2]2022-based'!Q52 -> 73508.468 | T29: 76078.686 | U29: 75009.673 | DT29: 1999 | DU29: =100*((Data!M33/Data!M32)-1) -> 0.51355263 | DV29: =AVERAGE(DU20:DU29) -> 0.2454158 | DW29: 0 | DX29: 65 | DY29: 60 | EA29: 34731 | EB29: =100*(HAVERM!C68/HAVERM!B68) -> 23.809524 | EC29: =AVERAGE($EB$7:$EB$399) -> 25.050854 | EE29: =HAVERM!C68 -> 2080 | EF29: =HAVERM!B68-HAVERM!C68 -> 6656 | FX29: =100*((AVERAGE(HAVERQ!B13:B32)/AVERAGE(HAVERQ!B9:B28))-1) -> 2.4472102 | GZ29: 2040 | HA29: =100*(Data!B74/Data!$B$57) -> 126.98662 | HB29: =HB28*(1+HF29/100) -> 135.37975 | HD29: =100*((HB29/HA29)-1) -> 6.6094578 | HF29: 1.9675736
A30: 2006 | B30: =Data!F40*Data!G40 -> 938041.64 | C30: =Data!H40/Data!I40 -> 11.80839 | D30: =Data!E40 -> 2239000 | E30: =Data!J40 -> -1.579563 | F30: =Data!D40 -> 2188892 | G30: =Data!B40 -> 2241453 | I30: =100*((F30/F29)-1) -> 2.7345928 | J30: =100*((G30/G29)-1) -> 2.1898213 | L30: 2026 | M30: ='[2]2022-based'!L33 -> 93.400344 | N30: 533.8 | O30: 261.869 | P30: ='OBR Nov25 C2.8'!D40 -> 261.869 | R30: 2046 | S30: ='[2]2022-based'!Q53 -> 73679.24 | T30: 76317.48 | U30: 75241.097 | DT30: 2000 | DU30: =100*((Data!M34/Data!M33)-1) -> 0.6089928 | DV30: =AVERAGE(DU21:DU30) -> 0.28743284 | DW30: 0 | DX30: 65 | DY30: 60 | EA30: 34759 | EB30: =100*(HAVERM!C69/HAVERM!B69) -> 23.821539 | EC30: =AVERAGE($EB$7:$EB$399) -> 25.050854 | EE30: =HAVERM!C69 -> 2077 | EF30: =HAVERM!B69-HAVERM!C69 -> 6642 | FX30: =100*((AVERAGE(HAVERQ!B14:B33)/AVERAGE(HAVERQ!B10:B29))-1) -> 2.4315687 | GZ30: 2041 | HA30: =100*(Data!B75/Data!$B$57) -> 129.00249 | HB30: =HB29*(1+HF30/100) -> 137.9755 | HD30: =100*((HB30/HA30)-1) -> 6.9556904 | HF30: 1.9173879
A31: 2007 | B31: =Data!F41*Data!G41 -> 945614.3 | C31: =Data!H41/Data!I41 -> 12.020052 | D31: =Data!E41 -> 2304000 | E31: =Data!J41 -> -1.577017 | F31: =Data!D41 -> 2236227 | G31: =Data!B41 -> 2307148 | I31: =100*((F31/F30)-1) -> 2.1625096 | J31: =100*((G31/G30)-1) -> 2.9309113 | L31: 2027 | M31: ='[2]2022-based'!L34 -> 139.06538 | N31: 436.7 | O31: 258.464 | P31: ='OBR Nov25 C2.8'!D41 -> 258.464 | R31: 2047 | S31: ='[2]2022-based'!Q54 -> 73844.274 | T31: 76550.535 | U31: 75467.1 | DT31: 2001 | DU31: =100*((Data!M35/Data!M34)-1) -> 0.72055167 | DV31: =AVERAGE(DU22:DU31) -> 0.34719856 | DW31: 0 | DX31: 65 | DY31: 60 | EA31: 34790 | EB31: =100*(HAVERM!C70/HAVERM!B70) -> 24.216328 | EC31: =AVERAGE($EB$7:$EB$399) -> 25.050854 | EE31: =HAVERM!C70 -> 2109 | EF31: =HAVERM!B70-HAVERM!C70 -> 6600 | FX31: =100*((AVERAGE(HAVERQ!B15:B34)/AVERAGE(HAVERQ!B11:B30))-1) -> 2.4299323 | GZ31: 2042 | HA31: =100*(Data!B76/Data!$B$57) -> 131.0689 | HB31: =HB30*(1+HF31/100) -> 140.5541 | HD31: =100*((HB31/HA31)-1) -> 7.2368088 | HF31: 1.8688841
A32: 2008 | B32: =Data!F42*Data!G42 -> 954262.22 | C32: =Data!H42/Data!I42 -> 12.201911 | D32: =Data!E42 -> 2370000 | E32: =Data!J42 -> -1.577136 | F32: =Data!D42 -> 2282011 | G32: =Data!B42 -> 2306008 | I32: =100*((F32/F31)-1) -> 2.0473771 | J32: =100*((G32/G31)-1) -> -0.049411655 | L32: 2028 | M32: ='[2]2022-based'!L35 -> 177.48164 | N32: 340 | O32: 290.302 | P32: ='OBR Nov25 C2.8'!D42 -> 290.302 | R32: 2048 | S32: ='[2]2022-based'!Q55 -> 74002.177 | T32: 76776.46 | U32: 75686.179 | DT32: 2002 | DU32: =100*((Data!M36/Data!M35)-1) -> 0.68498715 | DV32: =AVERAGE(DU23:DU32) -> 0.41276223 | DW32: 0 | DX32: 65 | DY32: 60 | EA32: 34820 | EB32: =100*(HAVERM!C71/HAVERM!B71) -> 24.320294 | EC32: =AVERAGE($EB$7:$EB$399) -> 25.050854 | EE32: =HAVERM!C71 -> 2120 | EF32: =HAVERM!B71-HAVERM!C71 -> 6597 | FW32: 1967 | FX32: =100*((AVERAGE(HAVERQ!B16:B35)/AVERAGE(HAVERQ!B12:B31))-1) -> 2.5672707 | GZ32: 2043 | HA32: =100*(Data!B77/Data!$B$57) -> 133.12306 | HB32: =HB31*(1+HF32/100) -> 143.13574 | HD32: =100*((HB32/HA32)-1) -> 7.5213708 | HF32: 1.8367582
A33: 2009 | B33: =Data!F43*Data!G43 -> 945894.56 | C33: =Data!H43/Data!I43 -> 12.349721 | D33: =Data!E43 -> 2401000 | E33: =Data!J43 -> -1.577942 | F33: =Data!D43 -> 2293332 | G33: =Data!B43 -> 2200222 | I33: =100*((F33/F32)-1) -> 0.49609752 | J33: =100*((G33/G32)-1) -> -4.5874082 | L33: 2029 | M33: ='[2]2022-based'!L36 -> 204.087 | N33: 340 | O33: 326.822 | P33: ='OBR Nov25 C2.8'!D43 -> 326.822 | R33: 2049 | S33: ='[2]2022-based'!Q56 -> 74151.333 | T33: 76993.637 | U33: 75896.638 | DT33: 2003 | DU33: =100*((Data!M37/Data!M36)-1) -> 0.63017067 | DV33: =AVERAGE(DU24:DU33) -> 0.47262356 | DW33: 0 | DX33: 65 | DY33: 60 | EA33: 34851 | EB33: =100*(HAVERM!C72/HAVERM!B72) -> 24.358532 | EC33: =AVERAGE($EB$7:$EB$399) -> 25.050854 | EE33: =HAVERM!C72 -> 2117 | EF33: =HAVERM!B72-HAVERM!C72 -> 6574 | FX33: =100*((AVERAGE(HAVERQ!B17:B36)/AVERAGE(HAVERQ!B13:B32))-1) -> 2.7300027 | GZ33: 2044 | HA33: =100*(Data!B78/Data!$B$57) -> 135.11949 | HB33: =HB32*(1+HF33/100) -> 145.73202 | HD33: =100*((HB33/HA33)-1) -> 7.8541791 | HF33: 1.8138563
A34: 2010 | B34: =Data!F44*Data!G44 -> 952641.9 | C34: =Data!H44/Data!I44 -> 12.459158 | D34: =Data!E44 -> 2435000 | E34: =Data!J44 -> -1.578457 | F34: =Data!D44 -> 2319739 | G34: =Data!B44 -> 2249959 | I34: =100*((F34/F33)-1) -> 1.1514687 | J34: =100*((G34/G33)-1) -> 2.2605446 | L34: 2030 | M34: ='[2]2022-based'!L37 -> 228.95652 | N34: 340 | O34: 340 | P34: ='OBR Nov25 C2.8'!D44 -> 340 | R34: 2050 | S34: ='[2]2022-based'!Q57 -> 74291.157 | T34: 77201.483 | U34: 76097.809 | DT34: 2004 | DU34: =100*((Data!M38/Data!M37)-1) -> 0.75987743 | DV34: =AVERAGE(DU25:DU34) -> 0.53256781 | DW34: 0 | DX34: 65 | DY34: 60 | EA34: 34881 | EB34: =100*(HAVERM!C73/HAVERM!B73) -> 24.500404 | EC34: =AVERAGE($EB$7:$EB$399) -> 25.050854 | EE34: =HAVERM!C73 -> 2121 | EF34: =HAVERM!B73-HAVERM!C73 -> 6536 | FX34: =100*((AVERAGE(HAVERQ!B18:B37)/AVERAGE(HAVERQ!B14:B33))-1) -> 2.8486164 | GZ34: 2045 | HA34: =100*(Data!B79/Data!$B$57) -> 137.06236 | HB34: =HB33*(1+HF34/100) -> 148.32882 | HD34: =100*((HB34/HA34)-1) -> 8.2199481 | HF34: 1.7819004
A35: 2011 | B35: =Data!F45*Data!G45 -> 956197.41 | C35: =Data!H45/Data!I45 -> 12.568908 | D35: =Data!E45 -> 2465000 | E35: =Data!J45 -> -1.579189 | F35: =Data!D45 -> 2340697 | G35: =Data!B45 -> 2269116 | I35: =100*((F35/F34)-1) -> 0.90346371 | J35: =100*((G35/G34)-1) -> 0.85143774 | L35: 2031 | M35: ='[2]2022-based'!L38 -> 250.57004 | N35: 340 | O35: 340 | R35: 2051 | S35: ='[2]2022-based'!Q58 -> 74421.298 | T35: 77399.645 | U35: 76289.212 | DT35: 2005 | DU35: =100*((Data!M39/Data!M38)-1) -> 0.97276662 | DV35: =AVERAGE(DU26:DU35) -> 0.59863954 | DW35: 0 | DX35: 65 | DY35: 60 | EA35: 34912 | EB35: =100*(HAVERM!C74/HAVERM!B74) -> 24.667515 | EC35: =AVERAGE($EB$7:$EB$399) -> 25.050854 | EE35: =HAVERM!C74 -> 2133 | EF35: =HAVERM!B74-HAVERM!C74 -> 6514 | FX35: =100*((AVERAGE(HAVERQ!B19:B38)/AVERAGE(HAVERQ!B15:B34))-1) -> 2.992317 | GZ35: 2046 | HA35: =100*(Data!B80/Data!$B$57) -> 138.99451 | HB35: =HB34*(1+HF35/100) -> 150.95224 | HD35: =100*((HB35/HA35)-1) -> 8.6030193 | HF35: 1.768653
A36: 2012 | B36: =Data!F46*Data!G46 -> 973247.64 | C36: =Data!H46/Data!I46 -> 12.676275 | D36: =Data!E46 -> 2495000 | E36: =Data!J46 -> -1.579922 | F36: =Data!D46 -> 2382224 | G36: =Data!B46 -> 2303794 | I36: =100*((F36/F35)-1) -> 1.7741297 | J36: =100*((G36/G35)-1) -> 1.5282603 | L36: 2032 | M36: ='[2]2022-based'!L39 -> 271.97854 | N36: 340 | O36: 340 | R36: 2052 | S36: ='[2]2022-based'!Q59 -> 74541.68 | T36: 77588.049 | U36: 76470.677 | DT36: 2006 | DU36: =100*((Data!M40/Data!M39)-1) -> 0.84869501 | DV36: =AVERAGE(DU27:DU36) -> 0.64683076 | DW36: 0 | DX36: 65 | DY36: 60 | EA36: 34943 | EB36: =100*(HAVERM!C75/HAVERM!B75) -> 24.702209 | EC36: =AVERAGE($EB$7:$EB$399) -> 25.050854 | EE36: =HAVERM!C75 -> 2136 | EF36: =HAVERM!B75-HAVERM!C75 -> 6511 | FW36: 1968 | FX36: =100*((AVERAGE(HAVERQ!B20:B39)/AVERAGE(HAVERQ!B16:B35))-1) -> 3.2124214 | GZ36: 2047 | HA36: =100*(Data!B81/Data!$B$57) -> 140.95134 | HB36: =HB35*(1+HF36/100) -> 153.59636 | HD36: =100*((HB36/HA36)-1) -> 8.9711974 | HF36: 1.751628
A37: 2013 | B37: =Data!F47*Data!G47 -> 988566.22 | C37: =Data!H47/Data!I47 -> 12.780853 | D37: =Data!E47 -> 2527000 | E37: =Data!J47 -> -1.580655 | F37: =Data!D47 -> 2421124 | G37: =Data!B47 -> 2343384 | I37: =100*((F37/F36)-1) -> 1.6329279 | J37: =100*((G37/G36)-1) -> 1.7184696 | L37: 2033 | M37: ='[2]2022-based'!L40 -> 271.97854 | N37: 340 | O37: 340 | R37: 2053 | S37: ='[2]2022-based'!Q60 -> 74652.32 | T37: 77766.71 | U37: 76642.198 | DT37: 2007 | DU37: =100*((Data!M41/Data!M40)-1) -> 0.69772108 | DV37: =AVERAGE(DU28:DU37) -> 0.68121313 | DW37: 0 | DX37: 65 | DY37: 60 | EA37: 34973 | EB37: =100*(HAVERM!C76/HAVERM!B76) -> 24.708329 | EC37: =AVERAGE($EB$7:$EB$399) -> 25.050854 | EE37: =HAVERM!C76 -> 2139 | EF37: =HAVERM!B76-HAVERM!C76 -> 6518 | FX37: =100*((AVERAGE(HAVERQ!B21:B40)/AVERAGE(HAVERQ!B17:B36))-1) -> 3.2288068 | GZ37: 2048 | HA37: =100*(Data!B82/Data!$B$57) -> 142.90071 | HB37: =HB36*(1+HF37/100) -> 156.26253 | HD37: =100*((HB37/HA37)-1) -> 9.3504222 | HF37: 1.7358305
A38: 2014 | B38: =Data!F48*Data!G48 -> 1001159.6 | C38: =Data!H48/Data!I48 -> 12.882915 | D38: =Data!E48 -> 2574000 | E38: =Data!J48 -> -1.581388 | F38: =Data!D48 -> 2457942 | G38: =Data!B48 -> 2417439 | I38: =100*((F38/F37)-1) -> 1.5206987 | J38: =100*((G38/G37)-1) -> 3.1601735 | L38: 2034 | M38: ='[2]2022-based'!L41 -> 271.97854 | N38: 340 | O38: 340 | R38: 2054 | S38: ='[2]2022-based'!Q61 -> 74753.422 | T38: 77935.834 | U38: 76803.913 | DT38: 2008 | DU38: =100*((Data!M42/Data!M41)-1) -> 0.60565971 | DV38: =AVERAGE(DU29:DU38) -> 0.70429748 | DW38: 0 | DX38: 65 | DY38: 60 | EA38: 35004 | EB38: =100*(HAVERM!C77/HAVERM!B77) -> 24.898762 | EC38: =AVERAGE($EB$7:$EB$399) -> 25.050854 | EE38: =HAVERM!C77 -> 2152 | EF38: =HAVERM!B77-HAVERM!C77 -> 6491 | FX38: =100*((AVERAGE(HAVERQ!B22:B41)/AVERAGE(HAVERQ!B18:B37))-1) -> 3.3368504 | GZ38: 2049 | HA38: =100*(Data!B83/Data!$B$57) -> 144.84631 | HB38: =HB37*(1+HF38/100) -> 158.94545 | HD38: =100*((HB38/HA38)-1) -> 9.7338639 | HF38: 1.7169304
A39: 2015 | B39: =Data!F49*Data!G49 -> 1010319.9 | C39: =Data!H49/Data!I49 -> 12.982594 | D39: =Data!E49 -> 2635000 | E39: =Data!J49 -> -1.582121 | F39: =Data!D49 -> 2494130 | G39: =Data!B49 -> 2469182 | I39: =100*((F39/F38)-1) -> 1.4722886 | J39: =100*((G39/G38)-1) -> 2.1404056 | L39: 2035 | M39: ='[2]2022-based'!L42 -> 271.97854 | N39: 340 | O39: 340 | R39: 2055 | S39: ='[2]2022-based'!Q62 -> 74845.7 | T39: 78096.133 | U39: 76956.519 | DT39: 2009 | DU39: =100*((Data!M43/Data!M42)-1) -> 0.51906437 | DV39: =AVERAGE(DU30:DU39) -> 0.70484865 | DW39: 0 | DX39: 65 | DY39: 60 | EA39: 35034 | EB39: =100*(HAVERM!C78/HAVERM!B78) -> 24.886878 | EC39: =AVERAGE($EB$7:$EB$399) -> 25.050854 | EE39: =HAVERM!C78 -> 2145 | EF39: =HAVERM!B78-HAVERM!C78 -> 6474 | FX39: =100*((AVERAGE(HAVERQ!B23:B42)/AVERAGE(HAVERQ!B19:B38))-1) -> 3.2979976 | GZ39: 2050 | HA39: =100*(Data!B84/Data!$B$57) -> 146.76872 | HB39: =HB38*(1+HF39/100) -> 161.65228 | HD39: =100*((HB39/HA39)-1) -> 10.140824 | HF39: 1.7029932
A40: 2016 | B40: =Data!F50*Data!G50 -> 1020729.7 | C40: =Data!H50/Data!I50 -> 13.080187 | D40: =Data!E50 -> 2706000 | E40: =Data!J50 -> -1.582855 | F40: =Data!D50 -> 2536360 | G40: =Data!B50 -> 2523665 | I40: =100*((F40/F39)-1) -> 1.6931756 | J40: =100*((G40/G39)-1) -> 2.2065202 | L40: 2036 | M40: ='[2]2022-based'!L43 -> 271.97854 | N40: 340 | O40: 340 | R40: 2056 | S40: ='[2]2022-based'!Q63 -> 74930.303 | T40: 78248.758 | U40: 77101.106 | DT40: 2010 | DU40: =100*((Data!M44/Data!M43)-1) -> 0.82222707 | DV40: =AVERAGE(DU31:DU40) -> 0.72617208 | DW40: 0 | DX40: 65 | DY40: 60 | EA40: 35065 | EB40: =100*(HAVERM!C79/HAVERM!B79) -> 24.979762 | EC40: =AVERAGE($EB$7:$EB$399) -> 25.050854 | EE40: =HAVERM!C79 -> 2160 | EF40: =HAVERM!B79-HAVERM!C79 -> 6487 | FW40: 1969 | FX40: =100*((AVERAGE(HAVERQ!B24:B43)/AVERAGE(HAVERQ!B20:B39))-1) -> 3.0864998 | GZ40: 2051 | HA40: =100*(Data!B85/Data!$B$57) -> 148.68351 | HB40: =HB39*(1+HF40/100) -> 164.39271 | HD40: =100*((HB40/HA40)-1) -> 10.565532 | HF40: 1.6952618
A41: 2017 | B41: =Data!F51*Data!G51 -> 1029431 | C41: =Data!H51/Data!I51 -> 13.176208 | D41: =Data!E51 -> 2780000 | E41: =Data!J51 -> -1.58359 | F41: =Data!D51 -> 2578098 | G41: =Data!B51 -> 2599961 | I41: =100*((F41/F40)-1) -> 1.6455866 | J41: =100*((G41/G40)-1) -> 3.0232222 | L41: 2037 | M41: ='[2]2022-based'!L44 -> 271.97854 | N41: 340 | O41: 340 | R41: 2057 | S41: ='[2]2022-based'!Q64 -> 75008.42 | T41: 78394.896 | U41: 77238.857 | DT41: 2011 | DU41: =100*((Data!M45/Data!M44)-1) -> 1.1039563 | DV41: =AVERAGE(DU32:DU41) -> 0.76451254 | DW41: 0 | DX41: 65 | DY41: =DY40+($AI$48-$AI$40)*1/8 -> 60 | EA41: 35096 | EB41: =100*(HAVERM!C80/HAVERM!B80) -> 24.919429 | EC41: =AVERAGE($EB$7:$EB$399) -> 25.050854 | EE41: =HAVERM!C80 -> 2165 | EF41: =HAVERM!B80-HAVERM!C80 -> 6523 | FX41: =100*((AVERAGE(HAVERQ!B25:B44)/AVERAGE(HAVERQ!B21:B40))-1) -> 3.0119707 | GZ41: 2052 | HA41: =100*(Data!B86/Data!$B$57) -> 150.58216 | HB41: =HB40*(1+HF41/100) -> 167.16224 | HD41: =100*((HB41/HA41)-1) -> 11.010656 | HF41: 1.6847048
A42: 2018 | B42: =Data!F52*Data!G52 -> 1036885.1 | C42: =Data!H52/Data!I52 -> 13.270807 | D42: =Data!E52 -> 2838000 | E42: =Data!J52 -> -1.584324 | F42: =Data!D52 -> 2616327 | G42: =Data!B52 -> 2640295 | I42: =100*((F42/F41)-1) -> 1.4828373 | J42: =100*((G42/G41)-1) -> 1.551331 | L42: 2038 | M42: ='[2]2022-based'!L45 -> 271.97854 | N42: 340 | O42: 340 | R42: 2058 | S42: ='[2]2022-based'!Q65 -> 75081.113 | T42: 78535.61 | U42: 77370.851 | DT42: 2012 | DU42: =100*((Data!M46/Data!M45)-1) -> 0.65879862 | DV42: =AVERAGE(DU33:DU42) -> 0.76189369 | DW42: 0 | DX42: 65 | DY42: =DY41+($AI$48-$AI$40)*1/8 -> 60 | EA42: 35125 | EB42: =100*(HAVERM!C81/HAVERM!B81) -> 24.92219 | EC42: =AVERAGE($EB$7:$EB$399) -> 25.050854 | EE42: =HAVERM!C81 -> 2162 | EF42: =HAVERM!B81-HAVERM!C81 -> 6513 | FX42: =100*((AVERAGE(HAVERQ!B26:B45)/AVERAGE(HAVERQ!B22:B41))-1) -> 2.8589662 | GZ42: 2053 | HA42: =100*(Data!B87/Data!$B$57) -> 152.45316 | HB42: =HB41*(1+HF42/100) -> 169.94777 | HD42: =100*((HB42/HA42)-1) -> 11.475398 | HF42: 1.6663589
A43: 2019 | B43: =Data!F53*Data!G53 -> 1050158 | C43: =Data!H53/Data!I53 -> 13.364048 | D43: =Data!E53 -> 2892000 | E43: =Data!J53 -> -1.585059 | F43: =Data!D53 -> 2660121 | G43: =Data!B53 -> 2673465 | I43: =100*((F43/F42)-1) -> 1.6738733 | J43: =100*((G43/G42)-1) -> 1.256299 | L43: 2039 | M43: ='[2]2022-based'!L46 -> 271.97854 | N43: 340 | O43: 340 | R43: 2059 | S43: ='[2]2022-based'!Q66 -> 75149.517 | T43: 78672.036 | U43: 77498.204 | DT43: 2013 | DU43: =100*((Data!M47/Data!M46)-1) -> 0.77680363 | DV43: =AVERAGE(DU34:DU43) -> 0.77655699 | DW43: 0 | DX43: 65 | DY43: =DY42+($AI$48-$AI$40)*1/8 -> 60 | EA43: 35156 | EB43: =100*(HAVERM!C82/HAVERM!B82) -> 25.349186 | EC43: =AVERAGE($EB$7:$EB$399) -> 25.050854 | EE43: =HAVERM!C82 -> 2196 | EF43: =HAVERM!B82-HAVERM!C82 -> 6467 | FX43: =100*((AVERAGE(HAVERQ!B27:B46)/AVERAGE(HAVERQ!B23:B42))-1) -> 2.8126188 | FY43: =100*((AVERAGE(HAVERQ!B7:B46)/AVERAGE(HAVERQ!B3:B42))-1) -> 1.6040473 | GZ43: 2054 | HA43: =100*(Data!B88/Data!$B$57) -> 154.32431 | HB43: =HB42*(1+HF43/100) -> 172.74909 | HD43: =100*((HB43/HA43)-1) -> 11.939 | HF43: 1.6483409
A44: 2020 | B44: =Data!F54*Data!G54 -> 943585.33 | C44: =Data!H54/Data!I54 -> 13.456149 | D44: =Data!E54 -> 2920000 | E44: =Data!J54 -> -1.589898 | F44: =Data!D54 -> 2486749 | G44: =Data!B54 -> 2404838 | I44: =100*((F44/F43)-1) -> -6.5174479 | J44: =100*((G44/G43)-1) -> -10.047897 | L44: 2040 | M44: ='[2]2022-based'!L47 -> 271.97854 | N44: 340 | O44: 340 | R44: 2060 | S44: ='[2]2022-based'!Q67 -> 75214.777 | T44: 78805.317 | U44: 77622.122 | DT44: 2014 | DU44: =100*((Data!M48/Data!M47)-1) -> 0.86671659 | DV44: =AVERAGE(DU35:DU44) -> 0.7872409 | DW44: 0 | DX44: 65 | DY44: =DY43+($AI$48-$AI$40)*1/8 -> 60 | EA44: 35186 | EB44: =100*(HAVERM!C83/HAVERM!B83) -> 25.288284 | EC44: =AVERAGE($EB$7:$EB$399) -> 25.050854 | EE44: =HAVERM!C83 -> 2193 | EF44: =HAVERM!B83-HAVERM!C83 -> 6479 | FW44: 1970 | FX44: =100*((AVERAGE(HAVERQ!B28:B47)/AVERAGE(HAVERQ!B24:B43))-1) -> 2.7550635 | FY44: =100*((AVERAGE(HAVERQ!B8:B47)/AVERAGE(HAVERQ!B4:B43))-1) -> 1.8360248 | FZ44: =$GD$6 -> 2.0390523 | GZ44: 2055 | HA44: =100*(Data!B89/Data!$B$57) -> 156.18339 | HB44: =HB43*(1+HF44/100) -> 175.56367 | HD44: =100*((HB44/HA44)-1) -> 12.408668 | HF44: 1.6292884
A45: 2021 | B45: =Data!F55*Data!G55 -> 1011326.2 | C45: =Data!H55/Data!I55 -> 13.547247 | D45: =Data!E55 -> 2967000 | E45: =Data!J55 -> -1.594172 | F45: =Data!D55 -> 2607600 | G45: =Data!B55 -> 2610286 | I45: =100*((F45/F44)-1) -> 4.8597989 | J45: =100*((G45/G44)-1) -> 8.5431118 | L45: 2041 | M45: ='[2]2022-based'!L48 -> 271.97854 | N45: 340 | O45: 340 | DT45: 2015 | DU45: =100*((Data!M49/Data!M48)-1) -> 0.96732098 | DV45: =AVERAGE(DU36:DU45) -> 0.78669634 | DW45: 0 | DX45: 65 | DY45: =DY44+($AI$48-$AI$40)*1/8 -> 60 | EA45: 35217 | EB45: =100*(HAVERM!C84/HAVERM!B84) -> 25.490646 | EC45: =AVERAGE($EB$7:$EB$399) -> 25.050854 | EE45: =HAVERM!C84 -> 2221 | EF45: =HAVERM!B84-HAVERM!C84 -> 6492 | FX45: =100*((AVERAGE(HAVERQ!B29:B48)/AVERAGE(HAVERQ!B25:B44))-1) -> 2.8489317 | FY45: =100*((AVERAGE(HAVERQ!B9:B48)/AVERAGE(HAVERQ!B5:B44))-1) -> 2.1666783 | FZ45: =$GD$6 -> 2.0390523 | GZ45: 2056 | HA45: =100*(Data!B90/Data!$B$57) -> 158.03219 | HB45: =HB44*(1+HF45/100) -> 178.38126 | HD45: =100*((HB45/HA45)-1) -> 12.876538 | HF45: 1.6048863
A46: 2022 | B46: =Data!F56*Data!G56 -> 1043187.5 | C46: =Data!H56/Data!I56 -> 13.637271 | D46: =Data!E56 -> 3028000 | E46: =Data!J56 -> -1.594949 | F46: =Data!D56 -> 2680477 | G46: =Data!B56 -> 2744708 | I46: =100*((F46/F45)-1) -> 2.7947921 | J46: =100*((G46/G45)-1) -> 5.1497039 | L46: 2042 | M46: ='[2]2022-based'!L49 -> 271.97854 | N46: 340 | O46: 340 | R46: Diff 2030 | T46: =T14-$S$14 -> 1528.4881 | U46: =U14-$S$14 -> 660.08511 | V46: =V14-$S$14 -> 658.37107 | DT46: 2016 | DU46: =100*((Data!M50/Data!M49)-1) -> 1.0251636 | DV46: =AVERAGE(DU37:DU46) -> 0.80434319 | DW46: 0 | DX46: 65 | DY46: =DY45+($AI$48-$AI$40)*1/8 -> 60 | EA46: 35247 | EB46: =100*(HAVERM!C85/HAVERM!B85) -> 25.680487 | EC46: =AVERAGE($EB$7:$EB$399) -> 25.050854 | EE46: =HAVERM!C85 -> 2236 | EF46: =HAVERM!B85-HAVERM!C85 -> 6471 | FX46: =100*((AVERAGE(HAVERQ!B30:B49)/AVERAGE(HAVERQ!B26:B45))-1) -> 2.9408115 | FY46: =100*((AVERAGE(HAVERQ!B10:B49)/AVERAGE(HAVERQ!B6:B45))-1) -> 2.5016964 | FZ46: =$GD$6 -> 2.0390523 | GZ46: 2057 | HA46: =100*(Data!B91/Data!$B$57) -> 159.88749 | HB46: =HB45*(1+HF46/100) -> 181.20676 | HD46: =100*((HB46/HA46)-1) -> 13.333918 | HF46: 1.5839641
A47: 2023 | B47: =Data!F57*Data!G57 -> 1054153.6 | C47: =Data!H57/Data!I57 -> 13.726025 | D47: =Data!E57 -> 3095000 | E47: =Data!J57 -> -1.595527 | F47: =Data!D57 -> 2722320 | G47: =Data!B57 -> 2752164 | I47: =100*((F47/F46)-1) -> 1.5610281 | J47: =100*((G47/G46)-1) -> 0.27165003 | L47: 2043 | M47: ='[2]2022-based'!L50 -> 271.97854 | N47: 340 | O47: 340 | R47: % diff 2030 | T47: =100*(($S$14/T14)-1) -> -2.1264446 | U47: =100*(($S$14/U14)-1) -> -0.92954567 | DT47: 2017 | DU47: =100*((Data!M51/Data!M50)-1) -> 0.90819636 | DV47: =AVERAGE(DU38:DU47) -> 0.82539072 | DW47: 0 | DX47: 65 | DY47: =DY46+($AI$48-$AI$40)*1/8 -> 60 | EA47: 35278 | EB47: =100*(HAVERM!C86/HAVERM!B86) -> 25.992655 | EC47: =AVERAGE($EB$7:$EB$399) -> 25.050854 | EE47: =HAVERM!C86 -> 2265 | EF47: =HAVERM!B86-HAVERM!C86 -> 6449 | FX47: =100*((AVERAGE(HAVERQ!B31:B50)/AVERAGE(HAVERQ!B27:B46))-1) -> 3.1176833 | FY47: =100*((AVERAGE(HAVERQ!B11:B50)/AVERAGE(HAVERQ!B7:B46))-1) -> 2.8799262 | FZ47: =$GD$6 -> 2.0390523 | GZ47: 2058 | HA47: =100*(Data!B92/Data!$B$57) -> 161.75838 | HB47: =HB46*(1+HF47/100) -> 184.04136 | HD47: =100*((HB47/HA47)-1) -> 13.775468 | HF47: 1.5642902
A48: 2024 | B48: =Data!F58*Data!G58 -> 1077081.4 | C48: =Data!H58/Data!I58 -> 13.813545 | D48: =Data!E58 -> 3153000 | E48: =Data!J58 -> -1.595867 | F48: =Data!D58 -> 2785026 | G48: =Data!B58 -> 2782111 | I48: =100*((F48/F47)-1) -> 2.303403 | J48: =100*((G48/G47)-1) -> 1.0881256 | L48: 2044 | M48: ='[2]2022-based'!L51 -> 271.97854 | N48: 340 | O48: 340 | DT48: 2018 | DU48: =100*((Data!M52/Data!M51)-1) -> 0.9444089 | DV48: =AVERAGE(DU39:DU48) -> 0.85926564 | DW48: 0 | DX48: 65 | DY48: 65 | EA48: 35309 | EB48: =100*(HAVERM!C87/HAVERM!B87) -> 26.176742 | EC48: =AVERAGE($EB$7:$EB$399) -> 25.050854 | EE48: =HAVERM!C87 -> 2269 | EF48: =HAVERM!B87-HAVERM!C87 -> 6399 | FW48: 1971 | FX48: =100*((AVERAGE(HAVERQ!B32:B51)/AVERAGE(HAVERQ!B28:B47))-1) -> 3.3545544 | FY48: =100*((AVERAGE(HAVERQ!B12:B51)/AVERAGE(HAVERQ!B8:B47))-1) -> 2.9795036 | FZ48: =$GD$6 -> 2.0390523 | GZ48: 2059 | HA48: =100*(Data!B93/Data!$B$57) -> 163.63095 | HB48: =HB47*(1+HF48/100) -> 186.90108 | HD48: =100*((HB48/HA48)-1) -> 14.221108 | HF48: 1.5538474
A49: 2025 | B49: =Data!F59*Data!G59 -> 1095641.2 | C49: =Data!H59/Data!I59 -> 13.899707 | D49: =Data!E59 -> 3210988 | E49: =Data!J59 -> -1.596186 | F49: =Data!D59 -> 2839341 | G49: =Data!B59 -> 2820536 | I49: =100*((F49/F48)-1) -> 1.9502511 | J49: =100*((G49/G48)-1) -> 1.3811455 | L49: 2045 | M49: ='[2]2022-based'!L52 -> 271.97854 | N49: 340 | O49: 340 | DT49: 2019 | DU49: =100*((Data!M53/Data!M52)-1) -> 1.1205492 | DV49: =AVERAGE(DU40:DU49) -> 0.91941412 | DW49: 0 | DX49: =DX48+($AH$51-$AH$48)*1/3 -> 65 | DY49: =DY48+($AI$51-$AI$48)*1/3 -> 65 | EA49: 35339 | EB49: =100*(HAVERM!C88/HAVERM!B88) -> 26.235389 | EC49: =AVERAGE($EB$7:$EB$399) -> 25.050854 | EE49: =HAVERM!C88 -> 2267 | EF49: =HAVERM!B88-HAVERM!C88 -> 6374 | FX49: =100*((AVERAGE(HAVERQ!B33:B52)/AVERAGE(HAVERQ!B29:B48))-1) -> 3.5354149 | FY49: =100*((AVERAGE(HAVERQ!B13:B52)/AVERAGE(HAVERQ!B9:B48))-1) -> 3.029515 | FZ49: =$GD$6 -> 2.0390523 | GZ49: 2060 | HA49: =100*(Data!B94/Data!$B$57) -> 165.52146 | HB49: =HB48*(1+HF49/100) -> 189.7673 | HD49: =100*((HB49/HA49)-1) -> 14.648156 | HF49: 1.5335493
A50: 2026 | B50: =Data!F60*Data!G60 -> 1107875.4 | C50: =Data!H60/Data!I60 -> 13.984293 | D50: =Data!E60 -> 3257932 | E50: =Data!J60 -> -1.596306 | F50: =Data!D60 -> 2881111 | G50: =Data!B60 -> 2845122 | I50: =100*((F50/F49)-1) -> 1.471116 | J50: =100*((G50/G49)-1) -> 0.87167829 | L50: 2046 | M50: ='[2]2022-based'!L53 -> 271.97854 | N50: 340 | O50: 340 | DT50: 2020 | DU50: =100*((Data!M54/Data!M53)-1) -> 0.86369425 | DV50: =AVERAGE(DU41:DU50) -> 0.92356084 | DW50: 0 | DX50: =DX49+($AH$51-$AH$48)*1/3 -> 65 | DY50: =DY49+($AI$51-$AI$48)*1/3 -> 65 | EA50: 35370 | EB50: =100*(HAVERM!C89/HAVERM!B89) -> 26.570439 | EC50: =AVERAGE($EB$7:$EB$399) -> 25.050854 | EE50: =HAVERM!C89 -> 2301 | EF50: =HAVERM!B89-HAVERM!C89 -> 6359 | FX50: =100*((AVERAGE(HAVERQ!B34:B53)/AVERAGE(HAVERQ!B30:B49))-1) -> 3.7849566 | FY50: =100*((AVERAGE(HAVERQ!B14:B53)/AVERAGE(HAVERQ!B10:B49))-1) -> 3.1562641 | FZ50: =$GD$6 -> 2.0390523
A51: 2027 | B51: =Data!F61*Data!G61 -> 1116608.1 | C51: =Data!H61/Data!I61 -> 14.067016 | D51: =Data!E61 -> 3305250 | E51: =Data!J61 -> -1.596046 | F51: =Data!D61 -> 2916429 | G51: =Data!B61 -> 2883162 | I51: =100*((F51/F50)-1) -> 1.2258466 | J51: =100*((G51/G50)-1) -> 1.3370253 | L51: 2047 | M51: ='[2]2022-based'!L54 -> 271.97854 | N51: 340 | O51: 340 | DT51: 2021 | DU51: =100*((Data!M55/Data!M54)-1) -> 0.62669028 | DV51: =AVERAGE(DU42:DU51) -> 0.87583423 | DW51: 0 | DX51: 66 | DY51: 66 | EA51: 35400 | EB51: =100*(HAVERM!C90/HAVERM!B90) -> 26.725929 | EC51: =AVERAGE($EB$7:$EB$399) -> 25.050854 | EE51: =HAVERM!C90 -> 2315 | EF51: =HAVERM!B90-HAVERM!C90 -> 6347 | FX51: =100*((AVERAGE(HAVERQ!B35:B54)/AVERAGE(HAVERQ!B31:B50))-1) -> 3.9913958 | FY51: =100*((AVERAGE(HAVERQ!B15:B54)/AVERAGE(HAVERQ!B11:B50))-1) -> 3.2669272 | FZ51: =$GD$6 -> 2.0390523
A52: 2028 | B52: =Data!F62*Data!G62 -> 1122929.3 | C52: =Data!H62/Data!I62 -> 14.147761 | D52: =Data!E62 -> 3353361 | E52: =Data!J62 -> -1.595229 | F52: =Data!D62 -> 2949480 | G52: =Data!B62 -> 2924704 | I52: =100*((F52/F51)-1) -> 1.1332695 | J52: =100*((G52/G51)-1) -> 1.4408486 | L52: 2048 | M52: ='[2]2022-based'!L55 -> 271.97854 | N52: 340 | O52: 340 | DT52: 2022 | DU52: =100*((Data!M56/Data!M55)-1) -> 0.94478689 | DV52: =AVERAGE(DU43:DU52) -> 0.90443306 | DW52: 0 | DX52: {=TRANSPOSE('[2]2022 calcs'!$B$34:$AN$34)} -> 66 | DY52: {=TRANSPOSE('[2]2022 calcs'!B$33:$AN$33)} -> 66 | EA52: 35431 | EB52: =100*(HAVERM!C91/HAVERM!B91) -> 26.81603 | EC52: =AVERAGE($EB$7:$EB$399) -> 25.050854 | EE52: =HAVERM!C91 -> 2322 | EF52: =HAVERM!B91-HAVERM!C91 -> 6337 | FW52: 1972 | FX52: =100*((AVERAGE(HAVERQ!B36:B55)/AVERAGE(HAVERQ!B32:B51))-1) -> 4.0748638 | FY52: =100*((AVERAGE(HAVERQ!B16:B55)/AVERAGE(HAVERQ!B12:B51))-1) -> 3.3765738 | FZ52: =$GD$6 -> 2.0390523
A53: 2029 | B53: =Data!F63*Data!G63 -> 1129430.5 | C53: =Data!H63/Data!I63 -> 14.226344 | D53: =Data!E63 -> 3401949 | E53: =Data!J63 -> -1.594013 | F53: =Data!D63 -> 2984114 | G53: =Data!B63 -> 2967061 | I53: =100*((F53/F52)-1) -> 1.1742409 | J53: =100*((G53/G52)-1) -> 1.4482491 | L53: 2049 | M53: ='[2]2022-based'!L56 -> 271.97854 | N53: 340 | O53: 340 | DT53: 2023 | DU53: =100*((Data!M57/Data!M56)-1) -> 1.297072 | DV53: =AVERAGE(DU44:DU53) -> 0.9564599 | DW53: 0 | DX53: 66 | DY53: 66 | EA53: 35462 | EB53: =100*(HAVERM!C92/HAVERM!B92) -> 26.766744 | EC53: =AVERAGE($EB$7:$EB$399) -> 25.050854 | EE53: =HAVERM!C92 -> 2318 | EF53: =HAVERM!B92-HAVERM!C92 -> 6342 | FX53: =100*((AVERAGE(HAVERQ!B37:B56)/AVERAGE(HAVERQ!B33:B52))-1) -> 4.1539545 | FY53: =100*((AVERAGE(HAVERQ!B17:B56)/AVERAGE(HAVERQ!B13:B52))-1) -> 3.4957092 | FZ53: =$GD$6 -> 2.0390523
A54: 2030 | B54: =Data!F64*Data!G64 -> 1136183.6 | C54: =Data!H64/Data!I64 -> 14.302599 | D54: =Data!E64 -> 3451700 | E54: =Data!J64 -> -1.59218 | F54: =Data!D64 -> 3021213 | G54: =Data!B64 -> 3010770 | I54: =100*((F54/F53)-1) -> 1.2432166 | J54: =100*((G54/G53)-1) -> 1.4731413 | L54: 2050 | M54: ='[2]2022-based'!L57 -> 271.97854 | N54: 340 | O54: 340 | DT54: 2024 | DU54: =100*((Data!M58/Data!M57)-1) -> 1.0422928 | DV54: =AVERAGE(DU45:DU54) -> 0.97401752 | DW54: 0 | DX54: 66 | DY54: 66 | EA54: 35490 | EB54: =100*(HAVERM!C93/HAVERM!B93) -> 26.701329 | EC54: =AVERAGE($EB$7:$EB$399) -> 25.050854 | EE54: =HAVERM!C93 -> 2311 | EF54: =HAVERM!B93-HAVERM!C93 -> 6344 | FX54: =100*((AVERAGE(HAVERQ!B38:B57)/AVERAGE(HAVERQ!B34:B53))-1) -> 4.1347271 | FY54: =100*((AVERAGE(HAVERQ!B18:B57)/AVERAGE(HAVERQ!B14:B53))-1) -> 3.5414842 | FZ54: =$GD$6 -> 2.0390523
A55: 2031 | B55: =Data!F65*Data!G65 -> 1143006.1 | C55: =Data!H65/Data!I65 -> 14.375719 | D55: =Data!E65 -> 3503373 | E55: =Data!J65 -> -1.589714 | F55: =Data!D65 -> 3060781 | G55: =Data!B65 -> 3056529 | I55: =100*((F55/F54)-1) -> 1.3096726 | J55: =100*((G55/G54)-1) -> 1.5198438 | L55: 2051 | M55: ='[2]2022-based'!L58 -> 271.97854 | N55: 340 | O55: 340 | DT55: 2025 | DU55: =100*((Data!M59/Data!M58)-1) -> 0.26452376 | DV55: =AVERAGE(DU46:DU55) -> 0.9037378 | DW55: 0 | DX55: 66 | DY55: 66 | EA55: 35521 | EB55: =100*(HAVERM!C94/HAVERM!B94) -> 26.704414 | EC55: =AVERAGE($EB$7:$EB$399) -> 25.050854 | EE55: =HAVERM!C94 -> 2311 | EF55: =HAVERM!B94-HAVERM!C94 -> 6343 | FX55: =100*((AVERAGE(HAVERQ!B39:B58)/AVERAGE(HAVERQ!B35:B54))-1) -> 4.1025052 | FY55: =100*((AVERAGE(HAVERQ!B19:B58)/AVERAGE(HAVERQ!B15:B54))-1) -> 3.5915886 | FZ55: =$GD$6 -> 2.0390523
A56: 2032 | B56: =Data!F66*Data!G66 -> 1149569.7 | C56: =Data!H66/Data!I66 -> 14.444565 | D56: =Data!E66 -> 3557452 | E56: =Data!J66 -> -1.586593 | F56: =Data!D66 -> 3102499 | G56: =Data!B66 -> 3101862 | I56: =100*((F56/F55)-1) -> 1.3629855 | J56: =100*((G56/G55)-1) -> 1.4831529 | L56: 2052 | M56: ='[2]2022-based'!L59 -> 271.97854 | N56: 340 | O56: 340 | DT56: 2026 | DU56: =100*((Data!M60/Data!M59)-1) -> -0.16626093 | DV56: =AVERAGE(DU47:DU56) -> 0.78459535 | DW56: 0 | DX56: 66.153005 | DY56: 66.153005 | EA56: 35551 | EB56: =100*(HAVERM!C95/HAVERM!B95) -> 26.505464 | EC56: =AVERAGE($EB$7:$EB$399) -> 25.050854 | EE56: =HAVERM!C95 -> 2280 | EF56: =HAVERM!B95-HAVERM!C95 -> 6322 | FW56: 1973 | FX56: =100*((AVERAGE(HAVERQ!B40:B59)/AVERAGE(HAVERQ!B36:B55))-1) -> 4.2112452 | FY56: =100*((AVERAGE(HAVERQ!B20:B59)/AVERAGE(HAVERQ!B16:B55))-1) -> 3.7522298 | FZ56: =$GD$6 -> 2.0390523
A57: 2033 | B57: =Data!F67*Data!G67 -> 1155958.1 | C57: =Data!H67/Data!I67 -> 14.508895 | D57: =Data!E67 -> 3614353 | E57: =Data!J67 -> -1.582805 | F57: =Data!D67 -> 3146720 | G57: =Data!B67 -> 3146720 | I57: =100*((F57/F56)-1) -> 1.4253349 | J57: =100*((G57/G56)-1) -> 1.4461636 | L57: 2053 | M57: ='[2]2022-based'!L60 -> 271.97854 | N57: 340 | O57: 340 | DT57: 2027 | DU57: =100*((Data!M61/Data!M60)-1) -> 0.443312 | DV57: =AVERAGE(DU48:DU57) -> 0.73810692 | DW57: 0 | DX57: 66.649315 | DY57: 66.649315 | EA57: 35582 | EB57: =100*(HAVERM!C96/HAVERM!B96) -> 26.59698 | EC57: =AVERAGE($EB$7:$EB$399) -> 25.050854 | EE57: =HAVERM!C96 -> 2290 | EF57: =HAVERM!B96-HAVERM!C96 -> 6320 | FX57: =100*((AVERAGE(HAVERQ!B41:B60)/AVERAGE(HAVERQ!B37:B56))-1) -> 4.2361424 | FY57: =100*((AVERAGE(HAVERQ!B21:B60)/AVERAGE(HAVERQ!B17:B56))-1) -> 3.77393 | FZ57: =$GD$6 -> 2.0390523
A58: 2034 | B58: =Data!F68*Data!G68 -> 1162167.1 | C58: =Data!H68/Data!I68 -> 14.568488 | D58: =Data!E68 -> 3674380 | E58: =Data!J68 -> -1.578516 | F58: =Data!D68 -> 3193112 | G58: =Data!B68 -> 3193113 | I58: =100*((F58/F57)-1) -> 1.474297 | J58: =100*((G58/G57)-1) -> 1.4743288 | L58: 2054 | M58: ='[2]2022-based'!L61 -> 271.97854 | N58: 340 | O58: 340 | DT58: 2028 | DU58: =100*((Data!M62/Data!M61)-1) -> 0.9401326 | DV58: =AVERAGE(DU49:DU58) -> 0.73767929 | DW58: 0 | DX58: 67 | DY58: 67 | EA58: 35612 | EB58: =100*(HAVERM!C97/HAVERM!B97) -> 26.724337 | EC58: =AVERAGE($EB$7:$EB$399) -> 25.050854 | EE58: =HAVERM!C97 -> 2317 | EF58: =HAVERM!B97-HAVERM!C97 -> 6353 | FX58: =100*((AVERAGE(HAVERQ!B42:B61)/AVERAGE(HAVERQ!B38:B57))-1) -> 4.1267009 | FY58: =100*((AVERAGE(HAVERQ!B22:B61)/AVERAGE(HAVERQ!B18:B57))-1) -> 3.7648054 | FZ58: =$GD$6 -> 2.0390523
A59: 2035 | B59: =Data!F69*Data!G69 -> 1167897.5 | C59: =Data!H69/Data!I69 -> 14.623137 | D59: =Data!E69 -> 3737431 | E59: =Data!J69 -> -1.573904 | F59: =Data!D69 -> 3240625 | G59: =Data!B69 -> 3240626 | I59: =100*((F59/F58)-1) -> 1.4879841 | J59: =100*((G59/G58)-1) -> 1.4879837 | L59: 2055 | M59: ='[2]2022-based'!L62 -> 271.97854 | N59: 340 | O59: 340 | DT59: 2029 | DU59: =100*((Data!M63/Data!M62)-1) -> 0.69800436 | DV59: =AVERAGE(DU50:DU59) -> 0.69542481 | DW59: 0 | DX59: 67 | DY59: 67 | EA59: 35643 | EB59: =100*(HAVERM!C98/HAVERM!B98) -> 26.786331 | EC59: =AVERAGE($EB$7:$EB$399) -> 25.050854 | EE59: =HAVERM!C98 -> 2328 | EF59: =HAVERM!B98-HAVERM!C98 -> 6363 | FX59: =100*((AVERAGE(HAVERQ!B43:B62)/AVERAGE(HAVERQ!B39:B58))-1) -> 3.9518711 | FY59: =100*((AVERAGE(HAVERQ!B23:B62)/AVERAGE(HAVERQ!B19:B58))-1) -> 3.6526946 | FZ59: =$GD$6 -> 2.0390523
A60: 2036 | B60: =Data!F70*Data!G70 -> 1173587.8 | C60: =Data!H70/Data!I70 -> 14.673656 | D60: =Data!E70 -> 3803435 | E60: =Data!J70 -> -1.569188 | F60: =Data!D70 -> 3289375 | G60: =Data!B70 -> 3289377 | I60: =100*((F60/F59)-1) -> 1.5043394 | J60: =100*((G60/G59)-1) -> 1.5043698 | L60: 2056 | M60: ='[2]2022-based'!L63 -> 271.97854 | N60: 340 | O60: 340 | DT60: 2030 | DU60: =100*((Data!M64/Data!M63)-1) -> 0.16762348 | DV60: =AVERAGE(DU51:DU60) -> 0.62581773 | DW60: 0 | DX60: 67 | DY60: 67 | EA60: 35674 | EB60: =100*(HAVERM!C99/HAVERM!B99) -> 26.678912 | EC60: =AVERAGE($EB$7:$EB$399) -> 25.050854 | EE60: =HAVERM!C99 -> 2324 | EF60: =HAVERM!B99-HAVERM!C99 -> 6387 | FW60: 1974 | FX60: =100*((AVERAGE(HAVERQ!B44:B63)/AVERAGE(HAVERQ!B40:B59))-1) -> 3.5823504 | FY60: =100*((AVERAGE(HAVERQ!B24:B63)/AVERAGE(HAVERQ!B20:B59))-1) -> 3.3556649 | FZ60: =$GD$6 -> 2.0390523
A61: 2037 | B61: =Data!F71*Data!G71 -> 1179277.6 | C61: =Data!H71/Data!I71 -> 14.721603 | D61: =Data!E71 -> 3872296 | E61: =Data!J71 -> -1.564486 | F61: =Data!D71 -> 3339124 | G61: =Data!B71 -> 3339125 | I61: =100*((F61/F60)-1) -> 1.512415 | J61: =100*((G61/G60)-1) -> 1.5123837 | L61: 2057 | M61: ='[2]2022-based'!L64 -> 271.97854 | N61: 340 | O61: 340 | DT61: 2031 | DU61: =100*((Data!M65/Data!M64)-1) -> 0.10457558 | DV61: =AVERAGE(DU52:DU61) -> 0.57360626 | DW61: 0 | DX61: 67 | DY61: 67 | EA61: 35704 | EB61: =100*(HAVERM!C100/HAVERM!B100) -> 26.736191 | EC61: =AVERAGE($EB$7:$EB$399) -> 25.050854 | EE61: =HAVERM!C100 -> 2333 | EF61: =HAVERM!B100-HAVERM!C100 -> 6393 | FX61: =100*((AVERAGE(HAVERQ!B45:B64)/AVERAGE(HAVERQ!B41:B60))-1) -> 3.285776 | FY61: =100*((AVERAGE(HAVERQ!B25:B64)/AVERAGE(HAVERQ!B21:B60))-1) -> 3.1608014 | FZ61: =$GD$6 -> 2.0390523
A62: 2038 | B62: =Data!F72*Data!G72 -> 1184966.3 | C62: =Data!H72/Data!I72 -> 14.767194 | D62: =Data!E72 -> 3943931 | E62: =Data!J72 -> -1.559797 | F62: =Data!D72 -> 3389844 | G62: =Data!B72 -> 3389847 | I62: =100*((F62/F61)-1) -> 1.5189613 | J62: =100*((G62/G61)-1) -> 1.5190207 | L62: 2058 | M62: ='[2]2022-based'!L65 -> 271.97854 | N62: 340 | O62: 340 | DT62: 2032 | DU62: =100*((Data!M66/Data!M65)-1) -> 0.11230407 | DV62: =AVERAGE(DU53:DU62) -> 0.49035798 | DW62: 0 | DX62: 67 | DY62: 67 | EA62: 35735 | EB62: =100*(HAVERM!C101/HAVERM!B101) -> 26.839034 | EC62: =AVERAGE($EB$7:$EB$399) -> 25.050854 | EE62: =HAVERM!C101 -> 2346 | EF62: =HAVERM!B101-HAVERM!C101 -> 6395 | FX62: =100*((AVERAGE(HAVERQ!B46:B65)/AVERAGE(HAVERQ!B42:B61))-1) -> 3.138389 | FY62: =100*((AVERAGE(HAVERQ!B26:B65)/AVERAGE(HAVERQ!B22:B61))-1) -> 3.0108905 | FZ62: =$GD$6 -> 2.0390523
A63: 2039 | B63: =Data!F73*Data!G73 -> 1190654.1 | C63: =Data!H73/Data!I73 -> 14.810802 | D63: =Data!E73 -> 4018269 | E63: =Data!J73 -> -1.555124 | F63: =Data!D73 -> 3441533 | G63: =Data!B73 -> 3441535 | I63: =100*((F63/F62)-1) -> 1.5248194 | J63: =100*((G63/G62)-1) -> 1.5247886 | L63: 2059 | M63: ='[2]2022-based'!L66 -> 271.97854 | N63: 340 | O63: 340 | DT63: 2033 | DU63: =100*((Data!M67/Data!M66)-1) -> 0.13988724 | DV63: =AVERAGE(DU54:DU63) -> 0.3746395 | DW63: 0 | DX63: 67 | DY63: 67 | EA63: 35765 | EB63: =100*(HAVERM!C102/HAVERM!B102) -> 26.506024 | EC63: =AVERAGE($EB$7:$EB$399) -> 25.050854 | EE63: =HAVERM!C102 -> 2332 | EF63: =HAVERM!B102-HAVERM!C102 -> 6466 | FX63: =100*((AVERAGE(HAVERQ!B47:B66)/AVERAGE(HAVERQ!B43:B62))-1) -> 2.9096315 | FY63: =100*((AVERAGE(HAVERQ!B27:B66)/AVERAGE(HAVERQ!B23:B62))-1) -> 2.8653957 | FZ63: =$GD$6 -> 2.0390523
A64: 2040 | B64: =Data!F74*Data!G74 -> 1196341.1 | C64: =Data!H74/Data!I74 -> 14.85308 | D64: =Data!E74 -> 4095163 | E64: =Data!J74 -> -1.550269 | F64: =Data!D74 -> 3494877 | G64: =Data!B74 -> 3494880 | I64: =100*((F64/F63)-1) -> 1.5500069 | J64: =100*((G64/G63)-1) -> 1.5500351 | L64: 2060 | M64: ='[2]2022-based'!L67 -> 271.97854 | N64: 340 | O64: 340 | DT64: 2034 | DU64: =100*((Data!M68/Data!M67)-1) -> 0.11836801 | DV64: =AVERAGE(DU55:DU64) -> 0.28224702 | DW64: 0 | DX64: 67 | DY64: 67 | EA64: 35796 | EB64: =100*(HAVERM!C103/HAVERM!B103) -> 26.853434 | EC64: =AVERAGE($EB$7:$EB$399) -> 25.050854 | EE64: =HAVERM!C103 -> 2358 | EF64: =HAVERM!B103-HAVERM!C103 -> 6423 | FW64: 1975 | FX64: =100*((AVERAGE(HAVERQ!B48:B67)/AVERAGE(HAVERQ!B44:B63))-1) -> 2.8785323 | FY64: =100*((AVERAGE(HAVERQ!B28:B67)/AVERAGE(HAVERQ!B24:B63))-1) -> 2.8222337 | FZ64: =$GD$6 -> 2.0390523
A65: 2041 | B65: =Data!F75*Data!G75 -> 1202409.7 | C65: =Data!H75/Data!I75 -> 14.894546 | D65: =Data!E75 -> 4174660 | E65: =Data!J75 -> -1.545314 | F65: =Data!D75 -> 3550358 | G65: =Data!B75 -> 3550360 | I65: =100*((F65/F64)-1) -> 1.5874951 | J65: =100*((G65/G64)-1) -> 1.5874651 | DT65: 2035 | DU65: =100*((Data!M69/Data!M68)-1) -> 0.093880546 | DV65: =AVERAGE(DU56:DU65) -> 0.2651827 | DW65: 0 | DX65: 67 | DY65: 67 | EA65: 35827 | EB65: =100*(HAVERM!C104/HAVERM!B104) -> 27.028259 | EC65: =AVERAGE($EB$7:$EB$399) -> 25.050854 | EE65: =HAVERM!C104 -> 2372 | EF65: =HAVERM!B104-HAVERM!C104 -> 6404 | FX65: =100*((AVERAGE(HAVERQ!B49:B68)/AVERAGE(HAVERQ!B45:B64))-1) -> 2.6161574 | FY65: =100*((AVERAGE(HAVERQ!B29:B68)/AVERAGE(HAVERQ!B25:B64))-1) -> 2.7222507 | FZ65: =$GD$6 -> 2.0390523
A66: 2042 | B66: =Data!F76*Data!G76 -> 1208653.6 | C66: =Data!H76/Data!I76 -> 14.935395 | D66: =Data!E76 -> 4256788 | E66: =Data!J76 -> -1.540375 | F66: =Data!D76 -> 3607228 | G66: =Data!B76 -> 3607231 | I66: =100*((F66/F65)-1) -> 1.6018103 | J66: =100*((G66/G65)-1) -> 1.6018376 | L66: 2025-2030 | M66: =AVERAGE(M29:M34) -> 174.49848 | N66: =AVERAGE(N29:N34) -> 436.9 | O66: =AVERAGE(O29:O34) -> 304.618 | DT66: 2036 | DU66: =100*((Data!M70/Data!M69)-1) -> 0.091557251 | DV66: =AVERAGE(DU57:DU66) -> 0.29096451 | DW66: 0 | DX66: 67 | DY66: 67 | EA66: 35855 | EB66: =100*(HAVERM!C105/HAVERM!B105) -> 27.16921 | EC66: =AVERAGE($EB$7:$EB$399) -> 25.050854 | EE66: =HAVERM!C105 -> 2386 | EF66: =HAVERM!B105-HAVERM!C105 -> 6396 | FX66: =100*((AVERAGE(HAVERQ!B50:B69)/AVERAGE(HAVERQ!B46:B65))-1) -> 2.2847648 | FY66: =100*((AVERAGE(HAVERQ!B30:B69)/AVERAGE(HAVERQ!B26:B65))-1) -> 2.5836725 | FZ66: =$GD$6 -> 2.0390523
A67: 2043 | B67: =Data!F77*Data!G77 -> 1214198 | C67: =Data!H77/Data!I77 -> 14.975707 | D67: =Data!E77 -> 4341282 | E67: =Data!J77 -> -1.535452 | F67: =Data!D77 -> 3663762 | G67: =Data!B77 -> 3663765 | I67: =100*((F67/F66)-1) -> 1.5672422 | J67: =100*((G67/G66)-1) -> 1.5672409 | L67: 2026-2030 | M67: =AVERAGE(M30:M34) -> 168.59818 | N67: =AVERAGE(N30:N34) -> 398.1 | O67: =AVERAGE(O30:O34) -> 295.4914 | DT67: 2037 | DU67: =100*((Data!M71/Data!M70)-1) -> 0.076169533 | DV67: =AVERAGE(DU58:DU67) -> 0.25425027 | DW67: 0 | DX67: 67 | DY67: 67 | EA67: 35886 | EB67: =100*(HAVERM!C106/HAVERM!B106) -> 26.942299 | EC67: =AVERAGE($EB$7:$EB$399) -> 25.050854 | EE67: =HAVERM!C106 -> 2372 | EF67: =HAVERM!B106-HAVERM!C106 -> 6432 | FX67: =100*((AVERAGE(HAVERQ!B51:B70)/AVERAGE(HAVERQ!B47:B66))-1) -> 2.0637705 | FY67: =100*((AVERAGE(HAVERQ!B31:B70)/AVERAGE(HAVERQ!B27:B66))-1) -> 2.5440863 | FZ67: =$GD$6 -> 2.0390523
A68: 2044 | B68: =Data!F78*Data!G78 -> 1218491.5 | C68: =Data!H78/Data!I78 -> 15.015438 | D68: =Data!E78 -> 4427700 | E68: =Data!J78 -> -1.530545 | F68: =Data!D78 -> 3718705 | G68: =Data!B78 -> 3718710 | I68: =100*((F68/F67)-1) -> 1.4996334 | J68: =100*((G68/G67)-1) -> 1.4996868 | DT68: 2038 | DU68: =100*((Data!M72/Data!M71)-1) -> 0.074798914 | DV68: =AVERAGE(DU59:DU68) -> 0.1677169 | DW68: 0 | DX68: 67 | DY68: 67 | EA68: 35916 | EB68: =100*(HAVERM!C107/HAVERM!B107) -> 26.867196 | EC68: =AVERAGE($EB$7:$EB$399) -> 25.050854 | EE68: =HAVERM!C107 -> 2367 | EF68: =HAVERM!B107-HAVERM!C107 -> 6443 | FW68: 1976 | FX68: =100*((AVERAGE(HAVERQ!B52:B71)/AVERAGE(HAVERQ!B48:B67))-1) -> 1.8858256 | FY68: =100*((AVERAGE(HAVERQ!B32:B71)/AVERAGE(HAVERQ!B28:B67))-1) -> 2.5550907 | FZ68: =$GD$6 -> 2.0390523
A69: 2045 | B69: =Data!F79*Data!G79 -> 1221707.7 | C69: =Data!H79/Data!I79 -> 15.054305 | D69: =Data!E79 -> 4515675 | E69: =Data!J79 -> -1.525653 | F69: =Data!D79 -> 3772176 | G69: =Data!B79 -> 3772181 | I69: =100*((F69/F68)-1) -> 1.437893 | J69: =100*((G69/G68)-1) -> 1.4378911 | L69: pop in 2030 | M69: ='[2]2022-based'!$Q$37 -> 70351.5 | N69: ='ONS popproj Jan25 pp'!J20 -> 71879.988 | O69: ='ONS popproj Jan25 migcv'!J20 -> 71011.585 | DT69: 2039 | DU69: =100*((Data!M73/Data!M72)-1) -> 0.057188566 | DV69: =AVERAGE(DU60:DU69) -> 0.10363532 | DW69: 0 | DX69: 67 | DY69: 67 | EA69: 35947 | EB69: =100*(HAVERM!C108/HAVERM!B108) -> 27.210418 | EC69: =AVERAGE($EB$7:$EB$399) -> 25.050854 | EE69: =HAVERM!C108 -> 2382 | EF69: =HAVERM!B108-HAVERM!C108 -> 6372 | FX69: =100*((AVERAGE(HAVERQ!B53:B72)/AVERAGE(HAVERQ!B49:B68))-1) -> 1.8050173 | FY69: =100*((AVERAGE(HAVERQ!B33:B72)/AVERAGE(HAVERQ!B29:B68))-1) -> 2.5946665 | FZ69: =$GD$6 -> 2.0390523
A70: 2046 | B70: =Data!F80*Data!G80 -> 1224514.4 | C70: =Data!H80/Data!I80 -> 15.092185 | D70: =Data!E80 -> 4605080 | E70: =Data!J80 -> -1.520776 | F70: =Data!D80 -> 3825352 | G70: =Data!B80 -> 3825357 | I70: =100*((F70/F69)-1) -> 1.4096903 | J70: =100*((G70/G69)-1) -> 1.4096885 | L70: diff | N70: =N69-$M$69 -> 1528.4881 | O70: =O69-$M$69 -> 660.08511 | DT70: 2040 | DU70: =100*((Data!M74/Data!M73)-1) -> 0.065829764 | DV70: =AVERAGE(DU61:DU70) -> 0.093455947 | DW70: 0 | DX70: 67 | DY70: 67 | EA70: 35977 | EB70: =100*(HAVERM!C109/HAVERM!B109) -> 27.210024 | EC70: =AVERAGE($EB$7:$EB$399) -> 25.050854 | EE70: =HAVERM!C109 -> 2367 | EF70: =HAVERM!B109-HAVERM!C109 -> 6332 | FX70: =100*((AVERAGE(HAVERQ!B54:B73)/AVERAGE(HAVERQ!B50:B69))-1) -> 1.7463702 | FY70: =100*((AVERAGE(HAVERQ!B34:B73)/AVERAGE(HAVERQ!B30:B69))-1) -> 2.6784238 | FZ70: =$GD$6 -> 2.0390523
A71: 2047 | B71: =Data!F81*Data!G81 -> 1227404.4 | C71: =Data!H81/Data!I81 -> 15.129115 | D71: =Data!E81 -> 4695962 | E71: =Data!J81 -> -1.515916 | F71: =Data!D81 -> 3879208 | G71: =Data!B81 -> 3879212 | I71: =100*((F71/F70)-1) -> 1.4078704 | J71: =100*((G71/G70)-1) -> 1.4078425 | DT71: 2041 | DU71: =100*((Data!M75/Data!M74)-1) -> 0.12831962 | DV71: =AVERAGE(DU62:DU71) -> 0.095830351 | DW71: 0 | DX71: 67 | DY71: 67 | EA71: 36008 | EB71: =100*(HAVERM!C110/HAVERM!B110) -> 27.164316 | EC71: =AVERAGE($EB$7:$EB$399) -> 25.050854 | EE71: =HAVERM!C110 -> 2369 | EF71: =HAVERM!B110-HAVERM!C110 -> 6352 | FX71: =100*((AVERAGE(HAVERQ!B55:B74)/AVERAGE(HAVERQ!B51:B70))-1) -> 1.7389546 | FY71: =100*((AVERAGE(HAVERQ!B35:B74)/AVERAGE(HAVERQ!B31:B70))-1) -> 2.7712361 | FZ71: =$GD$6 -> 2.0390523
A72: 2048 | B72: =Data!F82*Data!G82 -> 1229949.3 | C72: =Data!H82/Data!I82 -> 15.165227 | D72: =Data!E82 -> 4788220 | E72: =Data!J82 -> -1.511071 | F72: =Data!D82 -> 3932860 | G72: =Data!B82 -> 3932862 | I72: =100*((F72/F71)-1) -> 1.3830658 | J72: =100*((G72/G71)-1) -> 1.3830128 | DT72: 2042 | DU72: =100*((Data!M76/Data!M75)-1) -> 0.1920256 | DV72: =AVERAGE(DU63:DU72) -> 0.1038025 | DW72: 0 | DX72: 67 | DY72: 67 | EA72: 36039 | EB72: =100*(HAVERM!C111/HAVERM!B111) -> 27.236146 | EC72: =AVERAGE($EB$7:$EB$399) -> 25.050854 | EE72: =HAVERM!C111 -> 2369 | EF72: =HAVERM!B111-HAVERM!C111 -> 6329 | FW72: 1977 | FX72: =100*((AVERAGE(HAVERQ!B56:B75)/AVERAGE(HAVERQ!B52:B71))-1) -> 1.7000302 | FY72: =100*((AVERAGE(HAVERQ!B36:B75)/AVERAGE(HAVERQ!B32:B71))-1) -> 2.7906218 | FZ72: =$GD$6 -> 2.0390523
A73: 2049 | B73: =Data!F83*Data!G83 -> 1232217.1 | C73: =Data!H83/Data!I83 -> 15.200656 | D73: =Data!E83 -> 4881777 | E73: =Data!J83 -> -1.506241 | F73: =Data!D83 -> 3986404 | G73: =Data!B83 -> 3986408 | I73: =100*((F73/F72)-1) -> 1.361452 | J73: =100*((G73/G72)-1) -> 1.3615021 | DT73: 2043 | DU73: =100*((Data!M77/Data!M76)-1) -> 0.22138777 | DV73: =AVERAGE(DU64:DU73) -> 0.11195256 | DW73: 0 | DX73: 67 | DY73: 67 | EA73: 36069 | EB73: =100*(HAVERM!C112/HAVERM!B112) -> 27.096551 | EC73: =AVERAGE($EB$7:$EB$399) -> 25.050854 | EE73: =HAVERM!C112 -> 2349 | EF73: =HAVERM!B112-HAVERM!C112 -> 6320 | FX73: =100*((AVERAGE(HAVERQ!B57:B76)/AVERAGE(HAVERQ!B53:B72))-1) -> 1.5726735 | FY73: =100*((AVERAGE(HAVERQ!B37:B76)/AVERAGE(HAVERQ!B33:B72))-1) -> 2.7614158 | FZ73: =$GD$6 -> 2.0390523
A74: 2050 | B74: =Data!F84*Data!G84 -> 1233990.7 | C74: =Data!H84/Data!I84 -> 15.23541 | D74: =Data!E84 -> 4976234 | E74: =Data!J84 -> -1.501427 | F74: =Data!D84 -> 4039312 | G74: =Data!B84 -> 4039316 | I74: =100*((F74/F73)-1) -> 1.3272112 | J74: =100*((G74/G73)-1) -> 1.3272099 | DT74: 2044 | DU74: =100*((Data!M78/Data!M77)-1) -> 0.29740544 | DV74: =AVERAGE(DU65:DU74) -> 0.1298563 | DW74: 0 | DX74: 67.153425 | DY74: 67.153425 | EA74: 36100 | EB74: =100*(HAVERM!C113/HAVERM!B113) -> 27.014874 | EC74: =AVERAGE($EB$7:$EB$399) -> 25.050854 | EE74: =HAVERM!C113 -> 2343 | EF74: =HAVERM!B113-HAVERM!C113 -> 6330 | FX74: =100*((AVERAGE(HAVERQ!B58:B77)/AVERAGE(HAVERQ!B54:B73))-1) -> 1.4868776 | FY74: =100*((AVERAGE(HAVERQ!B38:B77)/AVERAGE(HAVERQ!B34:B73))-1) -> 2.7105362 | FZ74: =$GD$6 -> 2.0390523
A75: 2051 | B75: =Data!F85*Data!G85 -> 1235530.6 | C75: =Data!H85/Data!I85 -> 15.269632 | D75: =Data!E85 -> 5071464 | E75: =Data!J85 -> -1.496628 | F75: =Data!D85 -> 4092009 | G75: =Data!B85 -> 4092014 | I75: =100*((F75/F74)-1) -> 1.3046034 | J75: =100*((G75/G74)-1) -> 1.3046268 | DT75: 2045 | DU75: =100*((Data!M79/Data!M78)-1) -> 0.604999 | DV75: =AVERAGE(DU66:DU75) -> 0.18096815 | DW75: 0 | DX75: 67.649315 | DY75: 67.649315 | EA75: 36130 | EB75: =100*(HAVERM!C114/HAVERM!B114) -> 27.00603 | EC75: =AVERAGE($EB$7:$EB$399) -> 25.050854 | EE75: =HAVERM!C114 -> 2329 | EF75: =HAVERM!B114-HAVERM!C114 -> 6295 | FX75: =100*((AVERAGE(HAVERQ!B59:B78)/AVERAGE(HAVERQ!B55:B74))-1) -> 1.3812978 | FY75: =100*((AVERAGE(HAVERQ!B39:B78)/AVERAGE(HAVERQ!B35:B74))-1) -> 2.6432188 | FZ75: =$GD$6 -> 2.0390523
A76: 2052 | B76: =Data!F86*Data!G86 -> 1236724.5 | C76: =Data!H86/Data!I86 -> 15.303784 | D76: =Data!E86 -> 5167431 | E76: =Data!J86 -> -1.491845 | F76: =Data!D86 -> 4144264 | G76: =Data!B86 -> 4144268 | I76: =100*((F76/F75)-1) -> 1.2770011 | J76: =100*((G76/G75)-1) -> 1.2769751 | DT76: 2046 | DU76: =100*((Data!M80/Data!M79)-1) -> 0.96923207 | DV76: =AVERAGE(DU67:DU76) -> 0.26873563 | DW76: 0 | DX76: 68 | DY76: 68 | EA76: 36161 | EB76: =100*(HAVERM!C115/HAVERM!B115) -> 26.93958 | EC76: =AVERAGE($EB$7:$EB$399) -> 25.050854 | EE76: =HAVERM!C115 -> 2323 | EF76: =HAVERM!B115-HAVERM!C115 -> 6300 | FW76: 1978 | FX76: =100*((AVERAGE(HAVERQ!B60:B79)/AVERAGE(HAVERQ!B56:B75))-1) -> 1.0781405 | FY76: =100*((AVERAGE(HAVERQ!B40:B79)/AVERAGE(HAVERQ!B36:B75))-1) -> 2.534928 | FZ76: =$GD$6 -> 2.0390523
A77: 2053 | B77: =Data!F87*Data!G87 -> 1237451.8 | C77: =Data!H87/Data!I87 -> 15.337849 | D77: =Data!E87 -> 5264017 | E77: =Data!J87 -> -1.487076 | F77: =Data!D87 -> 4195756 | G77: =Data!B87 -> 4195761 | I77: =100*((F77/F76)-1) -> 1.2424884 | J77: =100*((G77/G76)-1) -> 1.2425113 | DT77: 2047 | DU77: =100*((Data!M81/Data!M80)-1) -> 0.6897372 | DV77: =AVERAGE(DU68:DU77) -> 0.33009239 | DW77: 0 | DX77: 68 | DY77: 68 | EA77: 36192 | EB77: =100*(HAVERM!C116/HAVERM!B116) -> 27.032967 | EC77: =AVERAGE($EB$7:$EB$399) -> 25.050854 | EE77: =HAVERM!C116 -> 2337 | EF77: =HAVERM!B116-HAVERM!C116 -> 6308 | FX77: =100*((AVERAGE(HAVERQ!B61:B80)/AVERAGE(HAVERQ!B57:B76))-1) -> 0.97633136 | FY77: =100*((AVERAGE(HAVERQ!B41:B80)/AVERAGE(HAVERQ!B37:B76))-1) -> 2.4978965 | FZ77: =$GD$6 -> 2.0390523
A78: 2054 | B78: =Data!F88*Data!G88 -> 1238087.3 | C78: =Data!H88/Data!I88 -> 15.371584 | D78: =Data!E88 -> 5361248 | E78: =Data!J88 -> -1.482323 | F78: =Data!D88 -> 4247256 | G78: =Data!B88 -> 4247258 | I78: =100*((F78/F77)-1) -> 1.2274308 | J78: =100*((G78/G77)-1) -> 1.2273578 | DT78: 2048 | DU78: =100*((Data!M82/Data!M81)-1) -> 0.15277773 | DV78: =AVERAGE(DU69:DU78) -> 0.33789028 | DW78: 0 | DX78: 68 | DY78: 68 | EA78: 36220 | EB78: =100*(HAVERM!C117/HAVERM!B117) -> 27.221325 | EC78: =AVERAGE($EB$7:$EB$399) -> 25.050854 | EE78: =HAVERM!C117 -> 2359 | EF78: =HAVERM!B117-HAVERM!C117 -> 6307 | FX78: =100*((AVERAGE(HAVERQ!B62:B81)/AVERAGE(HAVERQ!B58:B77))-1) -> 0.99311701 | FY78: =100*((AVERAGE(HAVERQ!B42:B81)/AVERAGE(HAVERQ!B38:B77))-1) -> 2.4613294 | FZ78: =$GD$6 -> 2.0390523
A79: 2055 | B79: =Data!F89*Data!G89 -> 1238485.8 | C79: =Data!H89/Data!I89 -> 15.404941 | D79: =Data!E89 -> 5459089 | E79: =Data!J89 -> -1.477586 | F79: =Data!D89 -> 4298419 | G79: =Data!B89 -> 4298423 | I79: =100*((F79/F78)-1) -> 1.204613 | J79: =100*((G79/G78)-1) -> 1.2046596 | DT79: 2049 | DU79: =100*((Data!M83/Data!M82)-1) -> 0.055864706 | DV79: =AVERAGE(DU70:DU79) -> 0.33775789 | DW79: 0 | DX79: 68 | DY79: 68 | EA79: 36251 | EB79: =100*(HAVERM!C118/HAVERM!B118) -> 27.108503 | EC79: =AVERAGE($EB$7:$EB$399) -> 25.050854 | EE79: =HAVERM!C118 -> 2356 | EF79: =HAVERM!B118-HAVERM!C118 -> 6335 | FX79: =100*((AVERAGE(HAVERQ!B63:B82)/AVERAGE(HAVERQ!B59:B78))-1) -> 1.039012 | FY79: =100*((AVERAGE(HAVERQ!B43:B82)/AVERAGE(HAVERQ!B39:B78))-1) -> 2.409013 | FZ79: =$GD$6 -> 2.0390523
A80: 2056 | B80: =Data!F90*Data!G90 -> 1238685.9 | C80: =Data!H90/Data!I90 -> 15.437829 | D80: =Data!E90 -> 5557519 | E80: =Data!J90 -> -1.472863 | F80: =Data!D90 -> 4349304 | G80: =Data!B90 -> 4349305 | I80: =100*((F80/F79)-1) -> 1.1838073 | J80: =100*((G80/G79)-1) -> 1.1837365 | DT80: 2050 | DU80: =100*((Data!M84/Data!M83)-1) -> 0.053615384 | DV80: =AVERAGE(DU71:DU80) -> 0.33653645 | DW80: 0 | DX80: 68 | DY80: 68 | EA80: 36281 | EB80: =100*(HAVERM!C119/HAVERM!B119) -> 27.049747 | EC80: =AVERAGE($EB$7:$EB$399) -> 25.050854 | EE80: =HAVERM!C119 -> 2349 | EF80: =HAVERM!B119-HAVERM!C119 -> 6335 | FW80: 1979 | FX80: =100*((AVERAGE(HAVERQ!B64:B83)/AVERAGE(HAVERQ!B60:B79))-1) -> 1.3112829 | FY80: =100*((AVERAGE(HAVERQ!B44:B83)/AVERAGE(HAVERQ!B40:B79))-1) -> 2.3845161 | FZ80: =$GD$6 -> 2.0390523
A81: 2057 | B81: =Data!F91*Data!G91 -> 1238893.6 | C81: =Data!H91/Data!I91 -> 15.470141 | D81: =Data!E91 -> 5656602 | E81: =Data!J91 -> -1.468156 | F81: =Data!D91 -> 4400360 | G81: =Data!B91 -> 4400366 | I81: =100*((F81/F80)-1) -> 1.173889 | J81: =100*((G81/G80)-1) -> 1.1740037 | DT81: 2051 | DU81: =100*((Data!M85/Data!M84)-1) -> 0.060913118 | DV81: =AVERAGE(DU72:DU81) -> 0.3297958 | DW81: 1 | DX81: 68 | DY81: 68 | EA81: 36312 | EB81: =100*(HAVERM!C120/HAVERM!B120) -> 26.93502 | EC81: =AVERAGE($EB$7:$EB$399) -> 25.050854 | EE81: =HAVERM!C120 -> 2342 | EF81: =HAVERM!B120-HAVERM!C120 -> 6353 | FX81: =100*((AVERAGE(HAVERQ!B65:B84)/AVERAGE(HAVERQ!B61:B80))-1) -> 1.6993847 | FY81: =100*((AVERAGE(HAVERQ!B45:B84)/AVERAGE(HAVERQ!B41:B80))-1) -> 2.4524139 | FZ81: =$GD$6 -> 2.0390523
A82: 2058 | B82: =Data!F92*Data!G92 -> 1239204.3 | C82: =Data!H92/Data!I92 -> 15.501956 | D82: =Data!E92 -> 5756439 | E82: =Data!J92 -> -1.463463 | F82: =Data!D92 -> 4451854 | G82: =Data!B92 -> 4451856 | I82: =100*((F82/F81)-1) -> 1.1702224 | J82: =100*((G82/G81)-1) -> 1.1701299 | DT82: 2052 | DU82: =100*((Data!M86/Data!M85)-1) -> 0.049945781 | DV82: =AVERAGE(DU73:DU82) -> 0.31558782 | DW82: 2 | DX82: 68 | DY82: 68 | EA82: 36342 | EB82: =100*(HAVERM!C121/HAVERM!B121) -> 26.837134 | EC82: =AVERAGE($EB$7:$EB$399) -> 25.050854 | EE82: =HAVERM!C121 -> 2330 | EF82: =HAVERM!B121-HAVERM!C121 -> 6352 | FX82: =100*((AVERAGE(HAVERQ!B66:B85)/AVERAGE(HAVERQ!B62:B81))-1) -> 1.8303963 | FY82: =100*((AVERAGE(HAVERQ!B46:B85)/AVERAGE(HAVERQ!B42:B81))-1) -> 2.4532055 | FZ82: =$GD$6 -> 2.0390523
A83: 2059 | B83: =Data!F93*Data!G93 -> 1239441.3 | C83: =Data!H93/Data!I93 -> 15.533361 | D83: =Data!E93 -> 5857050 | E83: =Data!J93 -> -1.458786 | F83: =Data!D93 -> 4503388 | G83: =Data!B93 -> 4503392 | I83: =100*((F83/F82)-1) -> 1.1575851 | J83: =100*((G83/G82)-1) -> 1.1576295 | DT83: 2053 | DU83: =100*((Data!M87/Data!M86)-1) -> 0.033786734 | DV83: =AVERAGE(DU74:DU83) -> 0.29682772 | DW83: 3 | DX83: 68 | DY83: 68 | EA83: 36373 | EB83: =100*(HAVERM!C122/HAVERM!B122) -> 27.015477 | EC83: =AVERAGE($EB$7:$EB$399) -> 25.050854 | EE83: =HAVERM!C122 -> 2339 | EF83: =HAVERM!B122-HAVERM!C122 -> 6319 | FX83: =100*((AVERAGE(HAVERQ!B67:B86)/AVERAGE(HAVERQ!B63:B82))-1) -> 2.008149 | FY83: =100*((AVERAGE(HAVERQ!B47:B86)/AVERAGE(HAVERQ!B43:B82))-1) -> 2.4385298 | FZ83: =$GD$6 -> 2.0390523
A84: 2060 | B84: =Data!F94*Data!G94 -> 1239788.9 | C84: =Data!H94/Data!I94 -> 15.564343 | D84: =Data!E94 -> 5958536 | E84: =Data!J94 -> -1.454123 | F84: =Data!D94 -> 4555414 | G84: =Data!B94 -> 4555422 | I84: =100*((F84/F83)-1) -> 1.1552635 | J84: =100*((G84/G83)-1) -> 1.1553513 | DT84: 2054 | DU84: =100*((Data!M88/Data!M87)-1) -> -0.015201003 | DV84: =AVERAGE(DU75:DU84) -> 0.26556707 | DW84: 4 | DX84: 68 | DY84: 68 | EA84: 36404 | EB84: =100*(HAVERM!C123/HAVERM!B123) -> 26.7288 | EC84: =AVERAGE($EB$7:$EB$399) -> 25.050854 | EE84: =HAVERM!C123 -> 2323 | EF84: =HAVERM!B123-HAVERM!C123 -> 6368 | FW84: 1980 | FX84: =100*((AVERAGE(HAVERQ!B68:B87)/AVERAGE(HAVERQ!B64:B83))-1) -> 2.0380566 | FY84: =100*((AVERAGE(HAVERQ!B48:B87)/AVERAGE(HAVERQ!B44:B83))-1) -> 2.4398851 | FZ84: =$GD$6 -> 2.0390523
DT85: 2055 | DU85: =100*((Data!M89/Data!M88)-1) -> -0.034434136 | DV85: =AVERAGE(DU76:DU85) -> 0.20162376 | DW85: 5 | DX85: 68 | DY85: 68 | EA85: 36434 | EB85: =100*(HAVERM!C124/HAVERM!B124) -> 26.648161 | EC85: =AVERAGE($EB$7:$EB$399) -> 25.050854 | EE85: =HAVERM!C124 -> 2304 | EF85: =HAVERM!B124-HAVERM!C124 -> 6342 | FX85: =100*((AVERAGE(HAVERQ!B69:B88)/AVERAGE(HAVERQ!B65:B84))-1) -> 1.9206761 | FY85: =100*((AVERAGE(HAVERQ!B49:B88)/AVERAGE(HAVERQ!B45:B84))-1) -> 2.2534929 | FZ85: =$GD$6 -> 2.0390523
A86: Contributions to growth | DT86: 2056 | DU86: =100*((Data!M90/Data!M89)-1) -> -0.061973264 | DV86: =AVERAGE(DU77:DU86) -> 0.098503225 | DW86: 6 | DX86: 68 | DY86: 68 | EA86: 36465 | EB86: =100*(HAVERM!C125/HAVERM!B125) -> 26.485923 | EC86: =AVERAGE($EB$7:$EB$399) -> 25.050854 | EE86: =HAVERM!C125 -> 2286 | EF86: =HAVERM!B125-HAVERM!C125 -> 6345 | FX86: =100*((AVERAGE(HAVERQ!B70:B89)/AVERAGE(HAVERQ!B66:B85))-1) -> 1.9791567 | FY86: =100*((AVERAGE(HAVERQ!B50:B89)/AVERAGE(HAVERQ!B46:B85))-1) -> 2.1256472 | FZ86: =$GD$6 -> 2.0390523
B87: Labour supply | C87: Human capital | D87: Capital stock | E87: Total factor productivity | F87: Potential output | G87: GDP | DT87: 2057 | DU87: =100*((Data!M91/Data!M90)-1) -> -0.10184017 | DV87: =AVERAGE(DU78:DU87) -> 0.019345488 | DW87: 7 | DX87: 68 | DY87: 68 | EA87: 36495 | EB87: =100*(HAVERM!C126/HAVERM!B126) -> 26.500868 | EC87: =AVERAGE($EB$7:$EB$399) -> 25.050854 | EE87: =HAVERM!C126 -> 2291 | EF87: =HAVERM!B126-HAVERM!C126 -> 6354 | FX87: =100*((AVERAGE(HAVERQ!B71:B90)/AVERAGE(HAVERQ!B67:B86))-1) -> 1.8449834 | FY87: =100*((AVERAGE(HAVERQ!B51:B90)/AVERAGE(HAVERQ!B47:B86))-1) -> 1.9499159 | FZ87: =$GD$6 -> 2.0390523
A88: 1990s | B88: =0.65*(100*((B23/B13)^(1/10)-1)) -> 0.10824108 | C88: =0.3*(100*((C23/C13)^(1/10)-1)) -> 0.21475281 | D88: =0.35*(100*((D23/D13)^(1/10)-1)) -> 0.95672637 | E88: =F88-B88-C88-D88 -> 1.012226 | F88: =100*((F23/F13)^(1/10)-1) -> 2.2919463 | G88: =100*((G23/G13)^(1/10)-1) -> 2.1074675 | DT88: 2058 | DU88: =100*((Data!M92/Data!M91)-1) -> -0.10376103 | DV88: =AVERAGE(DU79:DU88) -> -0.0063083879 | DW88: 8 | DX88: 68 | DY88: 68 | EA88: 36526 | EB88: =100*(HAVERM!C127/HAVERM!B127) -> 26.437046 | EC88: =AVERAGE($EB$7:$EB$399) -> 25.050854 | EE88: =HAVERM!C127 -> 2295 | EF88: =HAVERM!B127-HAVERM!C127 -> 6386 | FW88: 1981 | FX88: =100*((AVERAGE(HAVERQ!B72:B91)/AVERAGE(HAVERQ!B68:B87))-1) -> 1.7322984 | FY88: =100*((AVERAGE(HAVERQ!B52:B91)/AVERAGE(HAVERQ!B48:B87))-1) -> 1.8060135 | FZ88: =$GD$6 -> 2.0390523
A89: 2000s | B89: =0.65*(100*((B33/B23)^(1/10)-1)) -> 0.35329699 | C89: =0.3*(100*((C33/C23)^(1/10)-1)) -> 0.69157835 | D89: =0.35*(100*((D33/D23)^(1/10)-1)) -> 0.78568477 | E89: =F89-B89-C89-D89 -> 0.46726975 | F89: =100*((F33/F23)^(1/10)-1) -> 2.2978299 | G89: =100*((G33/G23)^(1/10)-1) -> 1.7157208 | DT89: 2059 | DU89: =100*((Data!M93/Data!M92)-1) -> -0.12776857 | DV89: =AVERAGE(DU80:DU89) -> -0.024671715 | DW89: 9 | DX89: 68 | DY89: 68 | EA89: 36557 | EB89: =100*(HAVERM!C128/HAVERM!B128) -> 26.65896 | EC89: =AVERAGE($EB$7:$EB$399) -> 25.050854 | EE89: =HAVERM!C128 -> 2306 | EF89: =HAVERM!B128-HAVERM!C128 -> 6344 | FX89: =100*((AVERAGE(HAVERQ!B73:B92)/AVERAGE(HAVERQ!B69:B88))-1) -> 1.6866108 | FY89: =100*((AVERAGE(HAVERQ!B53:B92)/AVERAGE(HAVERQ!B49:B88))-1) -> 1.7434742 | FZ89: =$GD$6 -> 2.0390523
A90: 2010s | B90: =0.65*(100*((B43/B33)^(1/10)-1)) -> 0.68323711 | C90: =0.3*(100*((C43/C33)^(1/10)-1)) -> 0.23774102 | D90: =0.35*(100*((D43/D33)^(1/10)-1)) -> 0.65731661 | E90: =F90-B90-C90-D90 -> -0.083575605 | F90: =100*((F43/F33)^(1/10)-1) -> 1.4947191 | G90: =100*((G43/G33)^(1/10)-1) -> 1.9672719 | DT90: 2060 | DU90: =100*((Data!M94/Data!M93)-1) -> -0.14896107 | DV90: =AVERAGE(DU81:DU90) -> -0.044929361 | DW90: 10 | DX90: 68 | DY90: 68 | EA90: 36586 | EB90: =100*(HAVERM!C129/HAVERM!B129) -> 26.722145 | EC90: =AVERAGE($EB$7:$EB$399) -> 25.050854 | EE90: =HAVERM!C129 -> 2312 | EF90: =HAVERM!B129-HAVERM!C129 -> 6340 | FX90: =100*((AVERAGE(HAVERQ!B74:B93)/AVERAGE(HAVERQ!B70:B89))-1) -> 1.6407275 | FY90: =100*((AVERAGE(HAVERQ!B54:B93)/AVERAGE(HAVERQ!B50:B89))-1) -> 1.6914453 | FZ90: =$GD$6 -> 2.0390523
A91: 2020s | B91: =0.65*(100*((B53/B43)^(1/10)-1)) -> 0.47474944 | C91: =0.3*(100*((C53/C43)^(1/10)-1)) -> 0.18816966 | D91: =0.35*(100*((D53/D43)^(1/10)-1)) -> 0.5730412 | E91: =F91-B91-C91-D91 -> -0.080017578 | F91: =100*((F53/F43)^(1/10)-1) -> 1.1559427 | G91: =100*((G53/G43)^(1/10)-1) -> 1.0474125 | EA91: 36617 | EB91: =100*(HAVERM!C130/HAVERM!B130) -> 26.646603 | EC91: =AVERAGE($EB$7:$EB$399) -> 25.050854 | EE91: =HAVERM!C130 -> 2302 | EF91: =HAVERM!B130-HAVERM!C130 -> 6337 | FX91: =100*((AVERAGE(HAVERQ!B75:B94)/AVERAGE(HAVERQ!B71:B90))-1) -> 1.6621533 | FY91: =100*((AVERAGE(HAVERQ!B55:B94)/AVERAGE(HAVERQ!B51:B90))-1) -> 1.6990291 | FZ91: =$GD$6 -> 2.0390523
A92: 2030s | B92: =0.65*(100*((B63/B53)^(1/10)-1)) -> 0.34403753 | C92: =0.3*(100*((C63/C53)^(1/10)-1)) -> 0.12102744 | D92: =0.35*(100*((D63/D53)^(1/10)-1)) -> 0.58763808 | E92: =F92-B92-C92-D92 -> 0.38365613 | F92: =100*((F63/F53)^(1/10)-1) -> 1.4363592 | G92: =100*((G63/G53)^(1/10)-1) -> 1.4945148 | DT92: 2015-2025 | DU92: =100*((Data!M59/Data!M49)^(1/10)-1) -> 0.90337738 | EA92: 36647 | EB92: =100*(HAVERM!C131/HAVERM!B131) -> 26.412918 | EC92: =AVERAGE($EB$7:$EB$399) -> 25.050854 | EE92: =HAVERM!C131 -> 2290 | EF92: =HAVERM!B131-HAVERM!C131 -> 6380 | FW92: 1982 | FX92: =100*((AVERAGE(HAVERQ!B76:B95)/AVERAGE(HAVERQ!B72:B91))-1) -> 1.7214106 | FY92: =100*((AVERAGE(HAVERQ!B56:B95)/AVERAGE(HAVERQ!B52:B91))-1) -> 1.7111369 | FZ92: =$GD$6 -> 2.0390523
A93: 2040s | B93: =0.65*(100*((B73/B63)^(1/10)-1)) -> 0.22341267 | C93: =0.3*(100*((C73/C63)^(1/10)-1)) -> 0.078046767 | D93: =0.35*(100*((D73/D63)^(1/10)-1)) -> 0.68797758 | E93: =F93-B93-C93-D93 -> 0.49114216 | F93: =100*((F73/F63)^(1/10)-1) -> 1.4805792 | G93: =100*((G73/G63)^(1/10)-1) -> 1.4805835 | DT93: 2025-2035 | DU93: =100*((Data!M69/Data!M59)^(1/10)-1) -> 0.26469195 | EA93: 36678 | EB93: =100*(HAVERM!C132/HAVERM!B132) -> 26.359447 | EC93: =AVERAGE($EB$7:$EB$399) -> 25.050854 | EE93: =HAVERM!C132 -> 2288 | EF93: =HAVERM!B132-HAVERM!C132 -> 6392 | FX93: =100*((AVERAGE(HAVERQ!B77:B96)/AVERAGE(HAVERQ!B73:B92))-1) -> 1.8532246 | FY93: =100*((AVERAGE(HAVERQ!B57:B96)/AVERAGE(HAVERQ!B53:B92))-1) -> 1.7184116 | FZ93: =$GD$6 -> 2.0390523
A94: 2050s | B94: =0.65*(100*((B83/B73)^(1/10)-1)) -> 0.03800751 | C94: =0.3*(100*((C83/C73)^(1/10)-1)) -> 0.065024596 | D94: =0.35*(100*((D83/D73)^(1/10)-1)) -> 0.64331952 | E94: =F94-B94-C94-D94 -> 0.48051773 | F94: =100*((F83/F73)^(1/10)-1) -> 1.2268694 | G94: =100*((G83/G73)^(1/10)-1) -> 1.2268682 | DT94: 2035-2045 | DU94: =100*((Data!M79/Data!M69)^(1/10)-1) -> 0.18084026 | EA94: 36708 | EB94: =100*(HAVERM!C133/HAVERM!B133) -> 26.535315 | EC94: =AVERAGE($EB$7:$EB$399) -> 25.050854 | EE94: =HAVERM!C133 -> 2303 | EF94: =HAVERM!B133-HAVERM!C133 -> 6376 | FX94: =100*((AVERAGE(HAVERQ!B78:B97)/AVERAGE(HAVERQ!B74:B93))-1) -> 1.9739876 | FY94: =100*((AVERAGE(HAVERQ!B58:B97)/AVERAGE(HAVERQ!B54:B93))-1) -> 1.7400058 | FZ94: =$GD$6 -> 2.0390523
DT95: 2045-2055 | DU95: =100*((Data!M89/Data!M79)^(1/10)-1) -> 0.20110319 | EA95: 36739 | EB95: =100*(HAVERM!C134/HAVERM!B134) -> 26.61597 | EC95: =AVERAGE($EB$7:$EB$399) -> 25.050854 | EE95: =HAVERM!C134 -> 2310 | EF95: =HAVERM!B134-HAVERM!C134 -> 6369 | FX95: =100*((AVERAGE(HAVERQ!B79:B98)/AVERAGE(HAVERQ!B75:B94))-1) -> 2.1126114 | FY95: =100*((AVERAGE(HAVERQ!B59:B98)/AVERAGE(HAVERQ!B55:B94))-1) -> 1.7613365 | FZ95: =$GD$6 -> 2.0390523
A96: diff vs 10-19 | EA96: 36770 | EB96: =100*(HAVERM!C135/HAVERM!B135) -> 26.619201 | EC96: =AVERAGE($EB$7:$EB$399) -> 25.050854 | EE96: =HAVERM!C135 -> 2318 | EF96: =HAVERM!B135-HAVERM!C135 -> 6390 | FW96: 1983 | FX96: =100*((AVERAGE(HAVERQ!B80:B99)/AVERAGE(HAVERQ!B76:B95))-1) -> 2.3600439 | FY96: =100*((AVERAGE(HAVERQ!B60:B99)/AVERAGE(HAVERQ!B56:B95))-1) -> 1.7441308 | FZ96: =$GD$6 -> 2.0390523
A97: 2020-30 | B97: =B91-B$89 -> 0.12145245 | C97: =C91-C$89 -> -0.50340869 | D97: =D91-D$89 -> -0.21264357 | E97: =E91-E$89 -> -0.54728733 | F97: =F91-F$89 -> -1.1418871 | G97: =G91-G$89 -> -0.66830825 | EA97: 36800 | EB97: =100*(HAVERM!C136/HAVERM!B136) -> 26.831491 | EC97: =AVERAGE($EB$7:$EB$399) -> 25.050854 | EE97: =HAVERM!C136 -> 2355 | EF97: =HAVERM!B136-HAVERM!C136 -> 6422 | FX97: =100*((AVERAGE(HAVERQ!B81:B100)/AVERAGE(HAVERQ!B77:B96))-1) -> 2.4563319 | FY97: =100*((AVERAGE(HAVERQ!B61:B100)/AVERAGE(HAVERQ!B57:B96))-1) -> 1.746167 | FZ97: =$GD$6 -> 2.0390523
A98: 2030-40 | B98: =B92-B$89 -> -0.0092594613 | C98: =C92-C$89 -> -0.57055091 | D98: =D92-D$89 -> -0.19804669 | E98: =E92-E$89 -> -0.083613619 | F98: =F92-F$89 -> -0.86147068 | G98: =G92-G$89 -> -0.22120602 | EA98: 36831 | EB98: =100*(HAVERM!C137/HAVERM!B137) -> 26.675023 | EC98: =AVERAGE($EB$7:$EB$399) -> 25.050854 | EE98: =HAVERM!C137 -> 2341 | EF98: =HAVERM!B137-HAVERM!C137 -> 6435 | FX98: =100*((AVERAGE(HAVERQ!B82:B101)/AVERAGE(HAVERQ!B78:B97))-1) -> 2.4875622 | FY98: =100*((AVERAGE(HAVERQ!B62:B101)/AVERAGE(HAVERQ!B58:B97))-1) -> 1.7714959 | FZ98: =$GD$6 -> 2.0390523
A99: 2040-50 | B99: =B93-B$89 -> -0.12988432 | C99: =C93-C$89 -> -0.61353158 | D99: =D93-D$89 -> -0.097707189 | E99: =E93-E$89 -> 0.02387241 | F99: =F93-F$89 -> -0.81725068 | G99: =G93-G$89 -> -0.23513732 | EA99: 36861 | EB99: =100*(HAVERM!C138/HAVERM!B138) -> 26.80436 | EC99: =AVERAGE($EB$7:$EB$399) -> 25.050854 | EE99: =HAVERM!C138 -> 2336 | EF99: =HAVERM!B138-HAVERM!C138 -> 6379 | FX99: =100*((AVERAGE(HAVERQ!B83:B102)/AVERAGE(HAVERQ!B79:B98))-1) -> 2.5006746 | FY99: =100*((AVERAGE(HAVERQ!B63:B102)/AVERAGE(HAVERQ!B59:B98))-1) -> 1.8012102 | FZ99: =$GD$6 -> 2.0390523
A100: 2050-60 | B100: =B94-B$89 -> -0.31528948 | C100: =C94-C$89 -> -0.62655375 | D100: =D94-D$89 -> -0.14236524 | E100: =E94-E$89 -> 0.013247981 | F100: =F94-F$89 -> -1.0709605 | G100: =G94-G$89 -> -0.48885258 | EA100: 36892 | EB100: =100*(HAVERM!C139/HAVERM!B139) -> 26.73913 | EC100: =AVERAGE($EB$7:$EB$399) -> 25.050854 | EE100: =HAVERM!C139 -> 2337 | EF100: =HAVERM!B139-HAVERM!C139 -> 6403 | FW100: 1984 | FX100: =100*((AVERAGE(HAVERQ!B84:B103)/AVERAGE(HAVERQ!B80:B99))-1) -> 2.4754245 | FY100: =100*((AVERAGE(HAVERQ!B64:B103)/AVERAGE(HAVERQ!B60:B99))-1) -> 1.9197534 | FZ100: =$GD$6 -> 2.0390523
...

Sheet OBR Nov25 ST1.15
A1: Back to contents
B2: 1.15 Potential output forecast
C3: Levels | L3: Growth rates
D4: Potential output1 (£m) | F4: Population (16+) | G4: Potential employment rate2 (16+) | H4: of which: potential participation rate | I4: of which: equilibrium unemployment rate | J4: Potential average hours | K4: Potential productivity per hour | M4: Potential output3 | O4: Population (16+) | P4: Potential employment rate | Q4: of which: potential participation rate | R4: of which: equilibrium unemployment rate | S4: Potential average hours | T4: Potential productivity per hour
B5: 2019Q1 | D5: 660703.2 | F5: 53301 | G5: 61.243246 | H5: 63.774381 | I5: 3.9688889 | J5: 31.777531 | K5: 636.93145 | M5: 0.52524372 | O5: 0.57361737 | P5: 0.46377686 | Q5: 0.091576861 | R5: 0.37185946 | S5: -0.71858088 | T5: 0.21058247
B6: 2019Q2 | D6: 661753.04 | F6: 53381 | G6: 61.240665 | H6: 63.776858 | I6: 3.9766667 | J6: 31.727531 | K6: 638.01819 | M6: 0.51372999 | O6: 0.59549609 | P6: 0.23416934 | Q6: 0.069588636 | R6: 0.16446625 | S6: -0.62641861 | T6: 0.31366906
B7: 2019Q3 | D7: 664170.11 | F7: 53435 | G7: 61.23021 | H7: 63.771136 | I7: 3.9844444 | J7: 31.677531 | K7: 640.82055 | M7: 0.78069578 | O7: 0.55324514 | P7: 0.050761412 | Q7: 0.034552109 | R7: 0.016203704 | S7: -0.62740115 | T7: 0.80781819
B8: 2019Q4 | D8: 667414.56 | F8: 53475 | G8: 61.215992 | H8: 63.761492 | I8: 3.9922222 | J8: 31.627531 | K8: 644.63621 | M8: 1.137853 | O8: 0.47725522 | P8: -0.038760342 | Q8: -0.00636812 | R8: -0.032394285 | S8: -0.62838678 | T8: 1.3332551
B9: 2020Q1 | D9: 652180 | F9: 53515 | G9: 61.195265 | H9: 63.745068 | I9: 4 | J9: 31.30912 | K9: 636.0676 | M9: -1.2900193 | O9: 0.40149341 | P9: -0.078345718 | Q9: -0.0459637 | R9: -0.032396908 | S9: -1.4740349 | T9: -0.13562666
B10: 2020Q2 | D10: 522347.25 | F10: 53555 | G10: 60.853309 | H10: 63.720743 | I10: 4.5 | J10: 26.205522 | K10: 611.62084 | M10: -21.066135 | O10: 0.32595867 | P10: -0.63251429 | Q10: -0.087987404 | R10: -0.54500642 | S10: -17.404473 | T10: -4.1373967
B11: 2020Q3 | D11: 616029.42 | F11: 53618 | G11: 60.83121 | H11: 63.697602 | I11: 4.5 | J11: 30.60767 | K11: 617.06955 | M11: -7.2482472 | O11: 0.34247216 | P11: -0.6516393 | Q11: -0.11530842 | R11: -0.53695003 | S11: -3.3773511 | T11: -3.7063421
B12: 2020Q4 | D12: 624312.06 | F12: 53692 | G12: 60.809885 | H12: 63.675272 | I12: 4.5 | J12: 31.123036 | K12: 614.3785 | M12: -6.45813 | O12: 0.4057971 | P12: -0.66340055 | Q12: -0.1352234 | R12: -0.52889234 | S12: -1.5951152 | T12: -4.6937651
B13: 2021Q1 | D13: 609814.64 | F13: 53767 | G13: 60.78923 | H13: 63.653644 | I13: 4.5 | J13: 30.45 | K13: 612.72853 | M13: -6.4959614 | O13: 0.47089601 | P13: -0.66350724 | Q13: -0.14342089 | R13: -0.52083333 | S13: -2.7439915 | T13: -3.6692748
B14: 2021Q2 | D14: 645942.3 | F14: 53842 | G14: 60.899 | H14: 63.635319 | I14: 4.3 | J14: 31.3 | K14: 629.3874 | M14: 23.661472 | O14: 0.53589768 | P14: 0.07508319 | Q14: -0.13406014 | R14: 0.20942408 | S14: 19.440475 | T14: 2.9048321
B15: 2021Q3 | D15: 655412.17 | F15: 53949 | G15: 61.010675 | H15: 63.619056 | I15: 4.1 | J15: 31.39 | K15: 634.35732 | M15: 6.392998 | O15: 0.61733 | P15: 0.29502146 | Q15: -0.12331022 | R15: 0.41884817 | S15: 2.5559933 | T15: 2.8015912
B16: 2021Q4 | D16: 662998.81 | F16: 54073 | G16: 61.036931 | H16: 63.601541 | I16: 4.0323077 | J16: 31.51 | K16: 637.51615 | M16: 6.1967003 | O16: 0.70960292 | P16: 0.37337128 | Q16: -0.11579182 | R16: 0.48973017 | S16: 1.2433365 | T16: 3.7660246
... B53: 2031Q1 | D53: 767764.31 | F53: 58556.245 | G53: 60.703161 | H53: 63.324808 | I53: 4.14 | J53: 31.718334 | K53: 680.97791 | M53: 1.5603032 | O53: 0.69282931 | P53: -0.038461269 | Q53: -0.038461269 | R53: 0 | S53: -0.13843662 | T53: 1.0401893
B54: 2019 | D54: 2654040.9 | F54: 53398 | G54: 61.232528 | H54: 63.770967 | I54: 3.9805556 | J54: 31.702531 | K54: 640.1016 | M54: 0.73971407 | O54: 0.54984371 | P54: 0.17714797 | Q54: 0.04732672 | R54: 0.12980057 | S54: -0.65026573 | T54: 0.66642398
B55: 2020 | D55: 2414868.7 | F55: 53595 | G55: 60.922417 | H55: 63.709671 | I55: 4.375 | J55: 29.811337 | K55: 619.78412 | M55: -9.0116237 | O55: 0.36892768 | P55: -0.50644845 | Q55: -0.096118432 | R55: -0.41079642 | S55: -5.9654372 | T55: -3.1741018
B56: 2021 | D56: 2574167.9 | F56: 53907.75 | G56: 60.933959 | H56: 63.62739 | I56: 4.2330769 | J56: 31.1625 | K56: 628.49735 | M56: 6.596598 | O56: 0.58354324 | P56: 0.018945143 | Q56: -0.12915004 | R56: 0.14841629 | S56: 4.5323802 | T56: 1.4058485
B57: 2022 | D57: 2707503.6 | F57: 54407 | G57: 60.990597 | H57: 63.571093 | I57: 4.0592308 | J57: 31.7248 | K57: 642.95913 | M57: 5.1797571 | O57: 0.92611916 | P57: 0.092949498 | Q57: -0.088479102 | R57: 0.18153048 | S57: 1.8044135 | T57: 2.3010095
B58: 2023 | D58: 2746003.2 | F58: 55044.5 | G58: 60.935345 | H58: 63.542034 | I58: 4.1023077 | J58: 31.8874 | K58: 641.86358 | M58: 1.4219617 | O58: 1.1717242 | P58: -0.090590351 | Q58: -0.04571059 | R58: -0.044899497 | S58: 0.51253012 | T58: -0.17039206
B59: 2024 | D59: 2791243.3 | F59: 55690 | G59: 60.901095 | H59: 63.529506 | I59: 4.1373077 | J59: 31.942845 | K59: 644.10878 | M59: 1.6474894 | O59: 1.1726876 | P59: -0.056207594 | Q59: -0.019716612 | R59: -0.036497229 | S59: 0.1738802 | T59: 0.34979396
B60: 2025 | D60: 2840686.7 | F60: 56249.512 | G60: 60.885728 | H60: 63.51526 | I60: 4.14 | J60: 31.959213 | K60: 648.8321 | M60: 1.7713731 | O60: 1.0046905 | P60: -0.025232635 | Q60: -0.022424587 | R60: -0.0028085042 | S60: 0.051239104 | T60: 0.7333102
B61: 2026 | D61: 2876585 | F61: 56654.967 | G61: 60.835684 | H61: 63.463054 | I61: 4.14 | J61: 31.946438 | K61: 653.1267 | M61: 1.263721 | O61: 0.7208155 | P61: -0.082194011 | Q61: -0.082194011 | R61: 0 | S61: -0.039970991 | T61: 0.66189824
B62: 2027 | D62: 2913476.6 | F62: 57055.686 | G62: 60.783754 | H62: 63.408882 | I62: 4.14 | J62: 31.9065 | K62: 658.24129 | M62: 1.2824765 | O62: 0.70729584 | P62: -0.08535973 | Q62: -0.08535973 | R62: 0 | S62: -0.12501499 | T62: 0.78309264
B63: 2028 | D63: 2952447 | F63: 57474.408 | G63: 60.745555 | H63: 63.369033 | I63: 4.14 | J63: 31.850591 | K63: 663.76546 | M63: 1.337594 | O63: 0.73388449 | P63: -0.062844869 | Q63: -0.062844869 | R63: 0 | S63: -0.17522796 | T63: 0.83923132
B64: 2029 | D64: 2995594.7 | F64: 57895.87 | G64: 60.727318 | H64: 63.350009 | I64: 4.14 | J64: 31.796427 | K64: 669.90278 | M64: 1.4614219 | O64: 0.73330372 | P64: -0.030021425 | Q64: -0.030021425 | R64: 0 | S64: -0.17005809 | T64: 0.92462185
B65: 2030 | D65: 3041433.1 | F65: 58305.39 | G65: 60.719472 | H65: 63.341824 | I65: 4.14 | J65: 31.744929 | K65: 676.55923 | M65: 1.5301934 | O65: 0.70733767 | P65: -0.012919782 | Q65: -0.012919782 | R65: 0 | S65: -0.16195925 | T65: 0.99364425
B66: 2019-20 | D66: 2645517.7 | F66: 53451.5 | G66: 61.220533 | H66: 63.763639 | I66: 3.9883333 | J66: 31.585428 | K66: 639.88564 | M66: 0.28479056 | O66: 0.5067504 | P66: 0.041841372 | Q66: 0.01294146 | R66: 0.028911094 | S66: -0.83856121 | T66: 0.57953225
B67: 2020-21 | D67: 2372503.4 | F67: 53658 | G67: 60.820909 | H67: 63.686815 | I67: 4.5 | J67: 29.596557 | K67: 613.94936 | M67: -10.319883 | O67: 0.38633153 | P67: -0.65276233 | Q67: -0.1204814 | R67: -0.53292135 | S67: -6.2968008 | T67: -4.0532682
B68: 2021-22 | D68: 2633165 | F68: 54015.5 | G68: 60.990323 | H68: 63.610353 | I68: 4.1188462 | J68: 31.454625 | K68: 635.22865 | M68: 10.986774 | O68: 0.66625666 | P68: 0.27854618 | Q68: -0.12005983 | R68: 0.39911398 | S68: 6.2779871 | T68: 3.4659698
B69: 2022-23 | D69: 2723437.5 | F69: 54557.25 | G69: 60.975749 | H69: 63.562752 | I69: 4.07 | J69: 31.782943 | K69: 643.94759 | M69: 3.4282889 | O69: 1.0029529 | P69: -0.02389561 | Q69: -0.07483225 | R69: 0.050944479 | S69: 1.0437827 | T69: 1.3725664
B70: 2023-24 | D70: 2753907.4 | F70: 55208.25 | G70: 60.92402 | H70: 63.53736 | I70: 4.1130769 | J70: 31.907253 | K70: 641.51779 | M70: 1.1188062 | O70: 1.193242 | P70: -0.084835161 | Q70: -0.039947562 | R70: -0.044904538 | S70: 0.39112043 | T70: -0.37732851
B71: 2024-25 | D71: 2805907.3 | F71: 55842.75 | G71: 60.896875 | H71: 63.526888 | I71: 4.14 | J71: 31.949599 | K71: 645.62892 | M71: 1.8882217 | O71: 1.1492848 | P71: -0.044555587 | Q71: -0.016481692 | R71: -0.028077944 | S71: 0.13271869 | T71: 0.64084411
B72: 2025-26 | D72: 2848996.8 | F72: 56360.024 | G72: 60.877629 | H72: 63.506811 | I72: 4.14 | J72: 31.958623 | K72: 649.55212 | M72: 1.5356702 | O72: 0.92630512 | P72: -0.031603745 | Q72: -0.031603745 | R72: 0 | S72: 0.028243603 | T72: 0.60765569
B73: 2026-27 | D73: 2885859 | F73: 56753.878 | G73: 60.820446 | H73: 63.447158 | I73: 4.14 | J73: 31.939034 | K73: 654.40609 | M73: 1.2938669 | O73: 0.69881766 | P73: -0.093931777 | Q73: -0.093931777 | R73: 0 | S73: -0.061296304 | T73: 0.74727974
B74: 2027-28 | D74: 2922897.6 | F74: 57159.075 | G74: 60.773352 | H74: 63.398031 | I74: 4.14 | J74: 31.893234 | K74: 659.56235 | M74: 1.2834508 | O74: 0.71395504 | P74: -0.07743003 | Q74: -0.07743003 | R74: 0 | S74: -0.1433973 | T74: 0.7879289
B75: 2028-29 | D75: 2962831.6 | F75: 57580.175 | G75: 60.738642 | H75: 63.361822 | I75: 4.14 | J75: 31.83657 | K75: 665.24489 | M75: 1.3662466 | O75: 0.7367156 | P75: -0.05711386 | Q75: -0.05711386 | R75: 0 | S75: -0.17766889 | T75: 0.86156314
B76: 2029-30 | D76: 3006860.1 | F76: 57999.377 | G76: 60.726321 | H76: 63.348969 | I76: 4.14 | J76: 31.78291 | K76: 671.51847 | M76: 1.4860266 | O76: 0.72803113 | P76: -0.020285628 | Q76: -0.020285628 | R76: 0 | S76: -0.16854571 | T76: 0.94304704
B77: 2030-31 | D77: 3053228.5 | F77: 58406.115 | G77: 60.713633 | H77: 63.335733 | I77: 4.14 | J77: 31.733937 | K77: 678.31186 | M77: 1.5420896 | O77: 0.70128142 | P77: -0.020893416 | Q77: -0.020893416 | R77: 0 | S77: -0.15408786 | T77: 1.0116471
B78: Definitions:
B79: OBR estimate of potential population, based on LFS household population, all aged 16 and over (ONS identifier: MGSL) and is based on the ‘migration category variant’ of the latest ONS population projections (published in January 2025) for net migration and natural change.
B80: OBR estimate of the potential participation rate, on the same basis as the LFS participation rate, all aged 16 and over (ONS identifier: MGWG)
B81: OBR estimate of the equilibirum unemployment rate, on the same basis as the ILO unemployment rate, all aged 16 and over (ONS identifier: MGSX)
B82: OBR estimate of the potential employment rate, on the same basis as the LFS employment rate, all aged 16 and over (ONS identifier: MGSR)
B83: OBR estimate of potential average hours, on the same basis as LFS average (mean) actual weekly hours worked, all workers (ONS identifier: YBUV)
B84: OBR estimate of potential output per hour, on the same basis as GDP (ONS identifier: ABMI) divided by total weekly hours worked (ONS identifier: YBUS)
B85: Notes:
B86: 1 Potential output can be calculated by multiplying potential population, productivity, average hours and the employment rate divided by 100.
B87: 2 The potential employment rate is determined by multiplying the potential participation rate by 1 minus the equilibrium unemployment rate divided by 100.
B88: 3 Potential output growth is approximately equal to the sum of the growth rates of potential population, the employment rate, average hours and productivity.

Sheet HAVERM
A1: 199001 !M | B1: LF2M@UK | C1: LF69@UK | D1: LF2S@UK
A2: .DESC | B2: UK: LFS: Economically Inactive: Aged 16 to 64 (SA, Thous) | C2: UK: LFS: Economically Inactive: Long Term Sick (SA, Thous) | D2: UK: LFS: Economic Inactivity Rate: Aged 16 to 64 (SA, %)
A3: .T1 | B3: Feb-1971 | C3: Apr-1993 | D3: Feb-1971
A4: .TN | B4: Oct-2025 | C4: Oct-2025 | D4: Oct-2025
A5: .LSOURCE | B5: Office for National Statistics | C5: Office for National Statistics | D5: Office for National Statistics
A6: .DTLM | B6: Jan-20-2026 07:05 | C6: Jan-20-2026 07:05 | D6: Jan-20-2026 07:05
A7: 199001 | B7: 7890 | C7: #N/A | D7: 21.7
A8: 199002 | B8: 7897 | C8: #N/A | D8: 21.8
A9: 199003 | B9: 7892 | C9: #N/A | D9: 21.7
A10: 199004 | B10: 7883 | C10: #N/A | D10: 21.7
A11: 199005 | B11: 7877 | C11: #N/A | D11: 21.7
A12: 199006 | B12: 7875 | C12: #N/A | D12: 21.7
A13: 199007 | B13: 7874 | C13: #N/A | D13: 21.7
A14: 199008 | B14: 7889 | C14: #N/A | D14: 21.7
A15: 199009 | B15: 7906 | C15: #N/A | D15: 21.8
A16: 199010 | B16: 7919 | C16: #N/A | D16: 21.8
A17: 199011 | B17: 7934 | C17: #N/A | D17: 21.8
A18: 199012 | B18: 7965 | C18: #N/A | D18: 21.9
... A45: 199303 | B45: 8557 | C45: #N/A | D45: 23.5
A46: 199304 | B46: 8557 | C46: 1813 | D46: 23.5
A47: 199305 | B47: 8565 | C47: 1834 | D47: 23.6
A48: 199306 | B48: 8565 | C48: 1857 | D48: 23.6
A49: 199307 | B49: 8606 | C49: 1889 | D49: 23.7
A50: 199308 | B50: 8583 | C50: 1884 | D50: 23.6
A51: 199309 | B51: 8586 | C51: 1905 | D51: 23.6
A52: 199310 | B52: 8589 | C52: 1938 | D52: 23.6
A53: 199311 | B53: 8585 | C53: 1930 | D53: 23.6
A54: 199312 | B54: 8585 | C54: 1926 | D54: 23.6
A55: 199401 | B55: 8587 | C55: 1918 | D55: 23.6
A56: 199402 | B56: 8580 | C56: 1911 | D56: 23.6
A57: 199403 | B57: 8586 | C57: 1938 | D57: 23.6
... A436: 202510 | B436: 9021 | C436: 2811 | D436: 20.8

Sheet HAVERQ
A1: 19601 !Q | B1: A4YMQ@UK
A2: .DESC | B2: UK: Output per Worker: Whole Economy (SA, 2023=100)
A3: .T1 | B3: Q3-1959
A4: .TN | B4: Q2-2025
A5: .LSOURCE | B5: Office for National Statistics
A6: .DTLM | B6: Nov-13-2025 11:32
A7: 19601 | B7: 33.7
A8: 19602 | B8: 33.4
A9: 19603 | B9: 33.8
A10: 19604 | B10: 33.9
A11: 19611 | B11: 34.3
A12: 19612 | B12: 34.4
A13: 19613 | B13: 34.2
A14: 19614 | B14: 34.2
A15: 19621 | B15: 34.3
A16: 19622 | B16: 34.5
A17: 19623 | B17: 34.6
A18: 19624 | B18: 34.6
... A268: 20252 | B268: 100

Sheet Data
B1: =GMW!$DB$2 -> Desktop | C1: =$B$1 -> Desktop | D1: =$B$1 -> Desktop | E1: =$B$1 -> Desktop | F1: =$B$1 -> Desktop | G1: =$B$1 -> Desktop | H1: =$B$1 -> Desktop | I1: =$B$1 -> Desktop | J1: =$B$1 -> Desktop | ... P1: =$B$1 -> Desktop
B2: UK | C2: UK | D2: UK | E2: UK | F2: UK | G2: UK | H2: UK | I2: UK | J2: UK | K2: UK | L2: UK | M2: UK | N2: UK | O2: UK | P2: UK
B3: GDP | C3: UPILO | D3: YHAT | E3: K | F3: ESTAR | G3: AVHR | H3: EDUC | I3: POP15_64 | J3: TREND | K3: ETILO | L3: POP | M3: POPW | N3: PSNB | O3: GNDBT | P3: GDP!
B4: GBR | C4: GBR | D4: GBR | E4: GBR | F4: GBR | G4: GBR | H4: GBR | I4: GBR | J4: GBR | K4: GBR | L4: GBR | M4: GBR | N4: GBR | O4: GBR | P4: GBR
B5: L | C5: L | D5: L | E5: L | F5: L | G5: L | H5: L | I5: L | J5: L | K5: L | L5: L | M5: L | N5: L | O5: L | P5: L
A6: =A94+5 -> 2065 | B6: {=_xlfn.CONCAT(INDEX(GMW!$A$2:$DB$60,MATCH(1,(GMW!$DA$2:$DA$60=B$3)*(GMW!$DB$2:$DB$60=B$1),0),$A6-1966),"0",(INDEX(GMW!$A$2:$DB$60,MATCH(1,(GMW!$DA$2:$DA$60=B$3)*(GMW!$DB$2:$DB$60=B$1),0),$A6-1965)))} -> 202503 | C6: {=_xlfn.CONCAT(INDEX(GMW!$A$2:$DB$60,MATCH(1,(GMW!$DA$2:$DA$60=C$3)*(GMW!$DB$2:$DB$60=C$1),0),$A6-1966),"0",(INDEX(GMW!$A$2:$DB$60,MATCH(1,(GMW!$DA$2:$DA$60=C$3)*(GMW!$DB$2:$DB$60=C$1),0),$A6-1965)))} -> 202503 | D6: {=_xlfn.CONCAT(INDEX(GMW!$A$2:$DB$60,MATCH(1,(GMW!$DA$2:$DA$60=D$3)*(GMW!$DB$2:$DB$60=D$1),0),$A6-1966),"0",(INDEX(GMW!$A$2:$DB$60,MATCH(1,(GMW!$DA$2:$DA$60=D$3)*(GMW!$DB$2:$DB$60=D$1),0),$A6-1965)))} -> 202402 | E6: {=_xlfn.CONCAT(INDEX(GMW!$A$2:$DB$60,MATCH(1,(GMW!$DA$2:$DA$60=E$3)*(GMW!$DB$2:$DB$60=E$1),0),$A6-1966),"0",(INDEX(GMW!$A$2:$DB$60,MATCH(1,(GMW!$DA$2:$DA$60=E$3)*(GMW!$DB$2:$DB$60=E$1),0),$A6-1965)))} -> 202404 | F6: {=_xlfn.CONCAT(INDEX(GMW!$A$2:$DB$60,MATCH(1,(GMW!$DA$2:$DA$60=F$3)*(GMW!$DB$2:$DB$60=F$1),0),$A6-1966),"0",(INDEX(GMW!$A$2:$DB$60,MATCH(1,(GMW!$DA$2:$DA$60=F$3)*(GMW!$DB$2:$DB$60=F$1),0),$A6-1965)))} -> 202404 | G6: {=_xlfn.CONCAT(INDEX(GMW!$A$2:$DB$60,MATCH(1,(GMW!$DA$2:$DA$60=G$3)*(GMW!$DB$2:$DB$60=G$1),0),$A6-1966),"0",(INDEX(GMW!$A$2:$DB$60,MATCH(1,(GMW!$DA$2:$DA$60=G$3)*(GMW!$DB$2:$DB$60=G$1),0),$A6-1965)))} -> 202503 | H6: {=_xlfn.CONCAT(INDEX(GMW!$A$2:$DB$60,MATCH(1,(GMW!$DA$2:$DA$60=H$3)*(GMW!$DB$2:$DB$60=H$1),0),$A6-1966),"0",(INDEX(GMW!$A$2:$DB$60,MATCH(1,(GMW!$DA$2:$DA$60=H$3)*(GMW!$DB$2:$DB$60=H$1),0),$A6-1965)))} -> 201004 | I6: {=_xlfn.CONCAT(INDEX(GMW!$A$2:$DB$60,MATCH(1,(GMW!$DA$2:$DA$60=I$3)*(GMW!$DB$2:$DB$60=I$1),0),$A6-1966),"0",(INDEX(GMW!$A$2:$DB$60,MATCH(1,(GMW!$DA$2:$DA$60=I$3)*(GMW!$DB$2:$DB$60=I$1),0),$A6-1965)))} -> 202402 | ... P6: {=_xlfn.CONCAT(INDEX(GMW!$A$2:$DB$60,MATCH(1,(GMW!$DA$2:$DA$60=P$3)*(GMW!$DB$2:$DB$60=P$1),0),$A6-1966),"0",(INDEX(GMW!$A$2:$DB$60,MATCH(1,(GMW!$DA$2:$DA$60=P$3)*(GMW!$DB$2:$DB$60=P$1),0),$A6-1965)))} -> 202503
A7: 1973 | B7: {=INDEX(GMW!$A$2:$DB$60,MATCH(1,(GMW!$DA$2:$DA$60=B$3)*(GMW!$DB$2:$DB$60=B$1),0),$A7-1966)} -> 1063550 | C7: {=INDEX(GMW!$A$2:$DB$60,MATCH(1,(GMW!$DA$2:$DA$60=C$3)*(GMW!$DB$2:$DB$60=C$1),0),$A7-1966)} -> 3.65 | D7: {=INDEX(GMW!$A$2:$DB$60,MATCH(1,(GMW!$DA$2:$DA$60=D$3)*(GMW!$DB$2:$DB$60=D$1),0),$A7-1966)} -> 1072428 | E7: {=INDEX(GMW!$A$2:$DB$60,MATCH(1,(GMW!$DA$2:$DA$60=E$3)*(GMW!$DB$2:$DB$60=E$1),0),$A7-1966)} -> 1059904 | F7: {=INDEX(GMW!$A$2:$DB$60,MATCH(1,(GMW!$DA$2:$DA$60=F$3)*(GMW!$DB$2:$DB$60=F$1),0),$A7-1966)} -> 24874.8 | G7: {=INDEX(GMW!$A$2:$DB$60,MATCH(1,(GMW!$DA$2:$DA$60=G$3)*(GMW!$DB$2:$DB$60=G$1),0),$A7-1966)} -> 0.001 | H7: {=INDEX(GMW!$A$2:$DB$60,MATCH(1,(GMW!$DA$2:$DA$60=H$3)*(GMW!$DB$2:$DB$60=H$1),0),$A7-1966)} -> 286021.4 | I7: {=INDEX(GMW!$A$2:$DB$60,MATCH(1,(GMW!$DA$2:$DA$60=I$3)*(GMW!$DB$2:$DB$60=I$1),0),$A7-1966)} -> 35322.81 | ... P7: {=INDEX(GMW!$A$2:$DB$60,MATCH(1,(GMW!$DA$2:$DA$60=P$3)*(GMW!$DB$2:$DB$60=P$1),0),$A7-1966)} -> 81809
A8: =+A7+1 -> 1974 | B8: {=INDEX(GMW!$A$2:$DB$60,MATCH(1,(GMW!$DA$2:$DA$60=B$3)*(GMW!$DB$2:$DB$60=B$1),0),$A8-1966)} -> 1036973 | C8: {=INDEX(GMW!$A$2:$DB$60,MATCH(1,(GMW!$DA$2:$DA$60=C$3)*(GMW!$DB$2:$DB$60=C$1),0),$A8-1966)} -> 3.65 | D8: {=INDEX(GMW!$A$2:$DB$60,MATCH(1,(GMW!$DA$2:$DA$60=D$3)*(GMW!$DB$2:$DB$60=D$1),0),$A8-1966)} -> 1085376 | E8: {=INDEX(GMW!$A$2:$DB$60,MATCH(1,(GMW!$DA$2:$DA$60=E$3)*(GMW!$DB$2:$DB$60=E$1),0),$A8-1966)} -> 1089042 | F8: {=INDEX(GMW!$A$2:$DB$60,MATCH(1,(GMW!$DA$2:$DA$60=F$3)*(GMW!$DB$2:$DB$60=F$1),0),$A8-1966)} -> 24938.64 | G8: {=INDEX(GMW!$A$2:$DB$60,MATCH(1,(GMW!$DA$2:$DA$60=G$3)*(GMW!$DB$2:$DB$60=G$1),0),$A8-1966)} -> 0.001 | H8: {=INDEX(GMW!$A$2:$DB$60,MATCH(1,(GMW!$DA$2:$DA$60=H$3)*(GMW!$DB$2:$DB$60=H$1),0),$A8-1966)} -> 288869 | I8: {=INDEX(GMW!$A$2:$DB$60,MATCH(1,(GMW!$DA$2:$DA$60=I$3)*(GMW!$DB$2:$DB$60=I$1),0),$A8-1966)} -> 35332.71 | ... P8: {=INDEX(GMW!$A$2:$DB$60,MATCH(1,(GMW!$DA$2:$DA$60=P$3)*(GMW!$DB$2:$DB$60=P$1),0),$A8-1966)} -> 92686
A9: =+A8+1 -> 1975 | B9: {=INDEX(GMW!$A$2:$DB$60,MATCH(1,(GMW!$DA$2:$DA$60=B$3)*(GMW!$DB$2:$DB$60=B$1),0),$A9-1966)} -> 1021204 | C9: {=INDEX(GMW!$A$2:$DB$60,MATCH(1,(GMW!$DA$2:$DA$60=C$3)*(GMW!$DB$2:$DB$60=C$1),0),$A9-1966)} -> 4.5 | D9: {=INDEX(GMW!$A$2:$DB$60,MATCH(1,(GMW!$DA$2:$DA$60=D$3)*(GMW!$DB$2:$DB$60=D$1),0),$A9-1966)} -> 1094012 | E9: {=INDEX(GMW!$A$2:$DB$60,MATCH(1,(GMW!$DA$2:$DA$60=E$3)*(GMW!$DB$2:$DB$60=E$1),0),$A9-1966)} -> 1117422 | F9: {=INDEX(GMW!$A$2:$DB$60,MATCH(1,(GMW!$DA$2:$DA$60=F$3)*(GMW!$DB$2:$DB$60=F$1),0),$A9-1966)} -> 24932.05 | G9: {=INDEX(GMW!$A$2:$DB$60,MATCH(1,(GMW!$DA$2:$DA$60=G$3)*(GMW!$DB$2:$DB$60=G$1),0),$A9-1966)} -> 0.001 | H9: {=INDEX(GMW!$A$2:$DB$60,MATCH(1,(GMW!$DA$2:$DA$60=H$3)*(GMW!$DB$2:$DB$60=H$1),0),$A9-1966)} -> 291532.5 | I9: {=INDEX(GMW!$A$2:$DB$60,MATCH(1,(GMW!$DA$2:$DA$60=I$3)*(GMW!$DB$2:$DB$60=I$1),0),$A9-1966)} -> 35327.33 | ... P9: {=INDEX(GMW!$A$2:$DB$60,MATCH(1,(GMW!$DA$2:$DA$60=P$3)*(GMW!$DB$2:$DB$60=P$1),0),$A9-1966)} -> 115095
A10: =+A9+1 -> 1976 | B10: {=INDEX(GMW!$A$2:$DB$60,MATCH(1,(GMW!$DA$2:$DA$60=B$3)*(GMW!$DB$2:$DB$60=B$1),0),$A10-1966)} -> 1051973 | C10: {=INDEX(GMW!$A$2:$DB$60,MATCH(1,(GMW!$DA$2:$DA$60=C$3)*(GMW!$DB$2:$DB$60=C$1),0),$A10-1966)} -> 5.425 | D10: {=INDEX(GMW!$A$2:$DB$60,MATCH(1,(GMW!$DA$2:$DA$60=D$3)*(GMW!$DB$2:$DB$60=D$1),0),$A10-1966)} -> 1099141 | E10: {=INDEX(GMW!$A$2:$DB$60,MATCH(1,(GMW!$DA$2:$DA$60=E$3)*(GMW!$DB$2:$DB$60=E$1),0),$A10-1966)} -> 1143676 | F10: {=INDEX(GMW!$A$2:$DB$60,MATCH(1,(GMW!$DA$2:$DA$60=F$3)*(GMW!$DB$2:$DB$60=F$1),0),$A10-1966)} -> 24850.21 | G10: {=INDEX(GMW!$A$2:$DB$60,MATCH(1,(GMW!$DA$2:$DA$60=G$3)*(GMW!$DB$2:$DB$60=G$1),0),$A10-1966)} -> 0.001 | H10: {=INDEX(GMW!$A$2:$DB$60,MATCH(1,(GMW!$DA$2:$DA$60=H$3)*(GMW!$DB$2:$DB$60=H$1),0),$A10-1966)} -> 293842.9 | I10: {=INDEX(GMW!$A$2:$DB$60,MATCH(1,(GMW!$DA$2:$DA$60=I$3)*(GMW!$DB$2:$DB$60=I$1),0),$A10-1966)} -> 35352.08 | ... P10: {=INDEX(GMW!$A$2:$DB$60,MATCH(1,(GMW!$DA$2:$DA$60=P$3)*(GMW!$DB$2:$DB$60=P$1),0),$A10-1966)} -> 136995
A11: =+A10+1 -> 1977 | B11: {=INDEX(GMW!$A$2:$DB$60,MATCH(1,(GMW!$DA$2:$DA$60=B$3)*(GMW!$DB$2:$DB$60=B$1),0),$A11-1966)} -> 1077816 | C11: {=INDEX(GMW!$A$2:$DB$60,MATCH(1,(GMW!$DA$2:$DA$60=C$3)*(GMW!$DB$2:$DB$60=C$1),0),$A11-1966)} -> 5.6 | D11: {=INDEX(GMW!$A$2:$DB$60,MATCH(1,(GMW!$DA$2:$DA$60=D$3)*(GMW!$DB$2:$DB$60=D$1),0),$A11-1966)} -> 1102761 | E11: {=INDEX(GMW!$A$2:$DB$60,MATCH(1,(GMW!$DA$2:$DA$60=E$3)*(GMW!$DB$2:$DB$60=E$1),0),$A11-1966)} -> 1167655 | F11: {=INDEX(GMW!$A$2:$DB$60,MATCH(1,(GMW!$DA$2:$DA$60=F$3)*(GMW!$DB$2:$DB$60=F$1),0),$A11-1966)} -> 24800.74 | G11: {=INDEX(GMW!$A$2:$DB$60,MATCH(1,(GMW!$DA$2:$DA$60=G$3)*(GMW!$DB$2:$DB$60=G$1),0),$A11-1966)} -> 0.001 | H11: {=INDEX(GMW!$A$2:$DB$60,MATCH(1,(GMW!$DA$2:$DA$60=H$3)*(GMW!$DB$2:$DB$60=H$1),0),$A11-1966)} -> 295875.2 | I11: {=INDEX(GMW!$A$2:$DB$60,MATCH(1,(GMW!$DA$2:$DA$60=I$3)*(GMW!$DB$2:$DB$60=I$1),0),$A11-1966)} -> 35501.05 | ... P11: {=INDEX(GMW!$A$2:$DB$60,MATCH(1,(GMW!$DA$2:$DA$60=P$3)*(GMW!$DB$2:$DB$60=P$1),0),$A11-1966)} -> 159775
A12: =+A11+1 -> 1978 | B12: {=INDEX(GMW!$A$2:$DB$60,MATCH(1,(GMW!$DA$2:$DA$60=B$3)*(GMW!$DB$2:$DB$60=B$1),0),$A12-1966)} -> 1122953 | C12: {=INDEX(GMW!$A$2:$DB$60,MATCH(1,(GMW!$DA$2:$DA$60=C$3)*(GMW!$DB$2:$DB$60=C$1),0),$A12-1966)} -> 5.525 | D12: {=INDEX(GMW!$A$2:$DB$60,MATCH(1,(GMW!$DA$2:$DA$60=D$3)*(GMW!$DB$2:$DB$60=D$1),0),$A12-1966)} -> 1111856 | E12: {=INDEX(GMW!$A$2:$DB$60,MATCH(1,(GMW!$DA$2:$DA$60=E$3)*(GMW!$DB$2:$DB$60=E$1),0),$A12-1966)} -> 1197400 | F12: {=INDEX(GMW!$A$2:$DB$60,MATCH(1,(GMW!$DA$2:$DA$60=F$3)*(GMW!$DB$2:$DB$60=F$1),0),$A12-1966)} -> 24703.73 | G12: {=INDEX(GMW!$A$2:$DB$60,MATCH(1,(GMW!$DA$2:$DA$60=G$3)*(GMW!$DB$2:$DB$60=G$1),0),$A12-1966)} -> 0.001 | H12: {=INDEX(GMW!$A$2:$DB$60,MATCH(1,(GMW!$DA$2:$DA$60=H$3)*(GMW!$DB$2:$DB$60=H$1),0),$A12-1966)} -> 297883.1 | I12: {=INDEX(GMW!$A$2:$DB$60,MATCH(1,(GMW!$DA$2:$DA$60=I$3)*(GMW!$DB$2:$DB$60=I$1),0),$A12-1966)} -> 35670.84 | ... P12: {=INDEX(GMW!$A$2:$DB$60,MATCH(1,(GMW!$DA$2:$DA$60=P$3)*(GMW!$DB$2:$DB$60=P$1),0),$A12-1966)} -> 186141
A13: =+A12+1 -> 1979 | B13: {=INDEX(GMW!$A$2:$DB$60,MATCH(1,(GMW!$DA$2:$DA$60=B$3)*(GMW!$DB$2:$DB$60=B$1),0),$A13-1966)} -> 1164860 | C13: {=INDEX(GMW!$A$2:$DB$60,MATCH(1,(GMW!$DA$2:$DA$60=C$3)*(GMW!$DB$2:$DB$60=C$1),0),$A13-1966)} -> 5.4 | D13: {=INDEX(GMW!$A$2:$DB$60,MATCH(1,(GMW!$DA$2:$DA$60=D$3)*(GMW!$DB$2:$DB$60=D$1),0),$A13-1966)} -> 1135923 | E13: {=INDEX(GMW!$A$2:$DB$60,MATCH(1,(GMW!$DA$2:$DA$60=E$3)*(GMW!$DB$2:$DB$60=E$1),0),$A13-1966)} -> 1220468 | F13: {=INDEX(GMW!$A$2:$DB$60,MATCH(1,(GMW!$DA$2:$DA$60=F$3)*(GMW!$DB$2:$DB$60=F$1),0),$A13-1966)} -> 24709.44 | G13: {=INDEX(GMW!$A$2:$DB$60,MATCH(1,(GMW!$DA$2:$DA$60=G$3)*(GMW!$DB$2:$DB$60=G$1),0),$A13-1966)} -> 0.001 | H13: {=INDEX(GMW!$A$2:$DB$60,MATCH(1,(GMW!$DA$2:$DA$60=H$3)*(GMW!$DB$2:$DB$60=H$1),0),$A13-1966)} -> 300120.3 | I13: {=INDEX(GMW!$A$2:$DB$60,MATCH(1,(GMW!$DA$2:$DA$60=I$3)*(GMW!$DB$2:$DB$60=I$1),0),$A13-1966)} -> 35882.96 | ... P13: {=INDEX(GMW!$A$2:$DB$60,MATCH(1,(GMW!$DA$2:$DA$60=P$3)*(GMW!$DB$2:$DB$60=P$1),0),$A13-1966)} -> 220966
A14: =+A13+1 -> 1980 | B14: {=INDEX(GMW!$A$2:$DB$60,MATCH(1,(GMW!$DA$2:$DA$60=B$3)*(GMW!$DB$2:$DB$60=B$1),0),$A14-1966)} -> 1140989 | C14: {=INDEX(GMW!$A$2:$DB$60,MATCH(1,(GMW!$DA$2:$DA$60=C$3)*(GMW!$DB$2:$DB$60=C$1),0),$A14-1966)} -> 6.8 | D14: {=INDEX(GMW!$A$2:$DB$60,MATCH(1,(GMW!$DA$2:$DA$60=D$3)*(GMW!$DB$2:$DB$60=D$1),0),$A14-1966)} -> 1164663 | E14: {=INDEX(GMW!$A$2:$DB$60,MATCH(1,(GMW!$DA$2:$DA$60=E$3)*(GMW!$DB$2:$DB$60=E$1),0),$A14-1966)} -> 1238528 | F14: {=INDEX(GMW!$A$2:$DB$60,MATCH(1,(GMW!$DA$2:$DA$60=F$3)*(GMW!$DB$2:$DB$60=F$1),0),$A14-1966)} -> 24765.53 | G14: {=INDEX(GMW!$A$2:$DB$60,MATCH(1,(GMW!$DA$2:$DA$60=G$3)*(GMW!$DB$2:$DB$60=G$1),0),$A14-1966)} -> 0.001 | H14: {=INDEX(GMW!$A$2:$DB$60,MATCH(1,(GMW!$DA$2:$DA$60=H$3)*(GMW!$DB$2:$DB$60=H$1),0),$A14-1966)} -> 306731.3 | I14: {=INDEX(GMW!$A$2:$DB$60,MATCH(1,(GMW!$DA$2:$DA$60=I$3)*(GMW!$DB$2:$DB$60=I$1),0),$A14-1966)} -> 36102.32 | ... P14: {=INDEX(GMW!$A$2:$DB$60,MATCH(1,(GMW!$DA$2:$DA$60=P$3)*(GMW!$DB$2:$DB$60=P$1),0),$A14-1966)} -> 259956
A15: =+A14+1 -> 1981 | B15: {=INDEX(GMW!$A$2:$DB$60,MATCH(1,(GMW!$DA$2:$DA$60=B$3)*(GMW!$DB$2:$DB$60=B$1),0),$A15-1966)} -> 1134663 | C15: {=INDEX(GMW!$A$2:$DB$60,MATCH(1,(GMW!$DA$2:$DA$60=C$3)*(GMW!$DB$2:$DB$60=C$1),0),$A15-1966)} -> 9.65 | D15: {=INDEX(GMW!$A$2:$DB$60,MATCH(1,(GMW!$DA$2:$DA$60=D$3)*(GMW!$DB$2:$DB$60=D$1),0),$A15-1966)} -> 1182108 | E15: {=INDEX(GMW!$A$2:$DB$60,MATCH(1,(GMW!$DA$2:$DA$60=E$3)*(GMW!$DB$2:$DB$60=E$1),0),$A15-1966)} -> 1247026 | F15: {=INDEX(GMW!$A$2:$DB$60,MATCH(1,(GMW!$DA$2:$DA$60=F$3)*(GMW!$DB$2:$DB$60=F$1),0),$A15-1966)} -> 24659.65 | G15: {=INDEX(GMW!$A$2:$DB$60,MATCH(1,(GMW!$DA$2:$DA$60=G$3)*(GMW!$DB$2:$DB$60=G$1),0),$A15-1966)} -> 0.001 | H15: {=INDEX(GMW!$A$2:$DB$60,MATCH(1,(GMW!$DA$2:$DA$60=H$3)*(GMW!$DB$2:$DB$60=H$1),0),$A15-1966)} -> 309382.7 | I15: {=INDEX(GMW!$A$2:$DB$60,MATCH(1,(GMW!$DA$2:$DA$60=I$3)*(GMW!$DB$2:$DB$60=I$1),0),$A15-1966)} -> 36300.18 | ... P15: {=INDEX(GMW!$A$2:$DB$60,MATCH(1,(GMW!$DA$2:$DA$60=P$3)*(GMW!$DB$2:$DB$60=P$1),0),$A15-1966)} -> 290550
A16: =+A15+1 -> 1982 | B16: {=INDEX(GMW!$A$2:$DB$60,MATCH(1,(GMW!$DA$2:$DA$60=B$3)*(GMW!$DB$2:$DB$60=B$1),0),$A16-1966)} -> 1157191 | C16: {=INDEX(GMW!$A$2:$DB$60,MATCH(1,(GMW!$DA$2:$DA$60=C$3)*(GMW!$DB$2:$DB$60=C$1),0),$A16-1966)} -> 10.725 | D16: {=INDEX(GMW!$A$2:$DB$60,MATCH(1,(GMW!$DA$2:$DA$60=D$3)*(GMW!$DB$2:$DB$60=D$1),0),$A16-1966)} -> 1189451 | E16: {=INDEX(GMW!$A$2:$DB$60,MATCH(1,(GMW!$DA$2:$DA$60=E$3)*(GMW!$DB$2:$DB$60=E$1),0),$A16-1966)} -> 1258257 | F16: {=INDEX(GMW!$A$2:$DB$60,MATCH(1,(GMW!$DA$2:$DA$60=F$3)*(GMW!$DB$2:$DB$60=F$1),0),$A16-1966)} -> 24297.71 | G16: {=INDEX(GMW!$A$2:$DB$60,MATCH(1,(GMW!$DA$2:$DA$60=G$3)*(GMW!$DB$2:$DB$60=G$1),0),$A16-1966)} -> 0.001 | H16: {=INDEX(GMW!$A$2:$DB$60,MATCH(1,(GMW!$DA$2:$DA$60=H$3)*(GMW!$DB$2:$DB$60=H$1),0),$A16-1966)} -> 311708.9 | I16: {=INDEX(GMW!$A$2:$DB$60,MATCH(1,(GMW!$DA$2:$DA$60=I$3)*(GMW!$DB$2:$DB$60=I$1),0),$A16-1966)} -> 36500.68 | ... P16: {=INDEX(GMW!$A$2:$DB$60,MATCH(1,(GMW!$DA$2:$DA$60=P$3)*(GMW!$DB$2:$DB$60=P$1),0),$A16-1966)} -> 320013
A17: =+A16+1 -> 1983 | B17: {=INDEX(GMW!$A$2:$DB$60,MATCH(1,(GMW!$DA$2:$DA$60=B$3)*(GMW!$DB$2:$DB$60=B$1),0),$A17-1966)} -> 1205632 | C17: {=INDEX(GMW!$A$2:$DB$60,MATCH(1,(GMW!$DA$2:$DA$60=C$3)*(GMW!$DB$2:$DB$60=C$1),0),$A17-1966)} -> 11.475 | D17: {=INDEX(GMW!$A$2:$DB$60,MATCH(1,(GMW!$DA$2:$DA$60=D$3)*(GMW!$DB$2:$DB$60=D$1),0),$A17-1966)} -> 1209350 | E17: {=INDEX(GMW!$A$2:$DB$60,MATCH(1,(GMW!$DA$2:$DA$60=E$3)*(GMW!$DB$2:$DB$60=E$1),0),$A17-1966)} -> 1271612 | F17: {=INDEX(GMW!$A$2:$DB$60,MATCH(1,(GMW!$DA$2:$DA$60=F$3)*(GMW!$DB$2:$DB$60=F$1),0),$A17-1966)} -> 24304.68 | G17: {=INDEX(GMW!$A$2:$DB$60,MATCH(1,(GMW!$DA$2:$DA$60=G$3)*(GMW!$DB$2:$DB$60=G$1),0),$A17-1966)} -> 0.001 | H17: {=INDEX(GMW!$A$2:$DB$60,MATCH(1,(GMW!$DA$2:$DA$60=H$3)*(GMW!$DB$2:$DB$60=H$1),0),$A17-1966)} -> 314668.8 | I17: {=INDEX(GMW!$A$2:$DB$60,MATCH(1,(GMW!$DA$2:$DA$60=I$3)*(GMW!$DB$2:$DB$60=I$1),0),$A17-1966)} -> 36776.19 | ... P17: {=INDEX(GMW!$A$2:$DB$60,MATCH(1,(GMW!$DA$2:$DA$60=P$3)*(GMW!$DB$2:$DB$60=P$1),0),$A17-1966)} -> 351900
A18: =+A17+1 -> 1984 | B18: {=INDEX(GMW!$A$2:$DB$60,MATCH(1,(GMW!$DA$2:$DA$60=B$3)*(GMW!$DB$2:$DB$60=B$1),0),$A18-1966)} -> 1232675 | C18: {=INDEX(GMW!$A$2:$DB$60,MATCH(1,(GMW!$DA$2:$DA$60=C$3)*(GMW!$DB$2:$DB$60=C$1),0),$A18-1966)} -> 11.75 | D18: {=INDEX(GMW!$A$2:$DB$60,MATCH(1,(GMW!$DA$2:$DA$60=D$3)*(GMW!$DB$2:$DB$60=D$1),0),$A18-1966)} -> 1251974 | E18: {=INDEX(GMW!$A$2:$DB$60,MATCH(1,(GMW!$DA$2:$DA$60=E$3)*(GMW!$DB$2:$DB$60=E$1),0),$A18-1966)} -> 1295894 | F18: {=INDEX(GMW!$A$2:$DB$60,MATCH(1,(GMW!$DA$2:$DA$60=F$3)*(GMW!$DB$2:$DB$60=F$1),0),$A18-1966)} -> 24910.8 | G18: {=INDEX(GMW!$A$2:$DB$60,MATCH(1,(GMW!$DA$2:$DA$60=G$3)*(GMW!$DB$2:$DB$60=G$1),0),$A18-1966)} -> 0.001 | H18: {=INDEX(GMW!$A$2:$DB$60,MATCH(1,(GMW!$DA$2:$DA$60=H$3)*(GMW!$DB$2:$DB$60=H$1),0),$A18-1966)} -> 318382.6 | I18: {=INDEX(GMW!$A$2:$DB$60,MATCH(1,(GMW!$DA$2:$DA$60=I$3)*(GMW!$DB$2:$DB$60=I$1),0),$A18-1966)} -> 37029.13 | ... P18: {=INDEX(GMW!$A$2:$DB$60,MATCH(1,(GMW!$DA$2:$DA$60=P$3)*(GMW!$DB$2:$DB$60=P$1),0),$A18-1966)} -> 378608
A19: =+A18+1 -> 1985 | B19: {=INDEX(GMW!$A$2:$DB$60,MATCH(1,(GMW!$DA$2:$DA$60=B$3)*(GMW!$DB$2:$DB$60=B$1),0),$A19-1966)} -> 1283200 | C19: {=INDEX(GMW!$A$2:$DB$60,MATCH(1,(GMW!$DA$2:$DA$60=C$3)*(GMW!$DB$2:$DB$60=C$1),0),$A19-1966)} -> 11.375 | D19: {=INDEX(GMW!$A$2:$DB$60,MATCH(1,(GMW!$DA$2:$DA$60=D$3)*(GMW!$DB$2:$DB$60=D$1),0),$A19-1966)} -> 1287060 | E19: {=INDEX(GMW!$A$2:$DB$60,MATCH(1,(GMW!$DA$2:$DA$60=E$3)*(GMW!$DB$2:$DB$60=E$1),0),$A19-1966)} -> 1321996 | F19: {=INDEX(GMW!$A$2:$DB$60,MATCH(1,(GMW!$DA$2:$DA$60=F$3)*(GMW!$DB$2:$DB$60=F$1),0),$A19-1966)} -> 25107.87 | G19: {=INDEX(GMW!$A$2:$DB$60,MATCH(1,(GMW!$DA$2:$DA$60=G$3)*(GMW!$DB$2:$DB$60=G$1),0),$A19-1966)} -> 0.001 | H19: {=INDEX(GMW!$A$2:$DB$60,MATCH(1,(GMW!$DA$2:$DA$60=H$3)*(GMW!$DB$2:$DB$60=H$1),0),$A19-1966)} -> 322872.1 | I19: {=INDEX(GMW!$A$2:$DB$60,MATCH(1,(GMW!$DA$2:$DA$60=I$3)*(GMW!$DB$2:$DB$60=I$1),0),$A19-1966)} -> 37116.96 | ... P19: {=INDEX(GMW!$A$2:$DB$60,MATCH(1,(GMW!$DA$2:$DA$60=P$3)*(GMW!$DB$2:$DB$60=P$1),0),$A19-1966)} -> 415455
... A94: =+A93+1 -> 2060 | B94: {=INDEX(GMW!$A$2:$DB$60,MATCH(1,(GMW!$DA$2:$DA$60=B$3)*(GMW!$DB$2:$DB$60=B$1),0),$A94-1966)} -> 4555422 | C94: {=INDEX(GMW!$A$2:$DB$60,MATCH(1,(GMW!$DA$2:$DA$60=C$3)*(GMW!$DB$2:$DB$60=C$1),0),$A94-1966)} -> 3.999998 | D94: {=INDEX(GMW!$A$2:$DB$60,MATCH(1,(GMW!$DA$2:$DA$60=D$3)*(GMW!$DB$2:$DB$60=D$1),0),$A94-1966)} -> 4555414 | E94: {=INDEX(GMW!$A$2:$DB$60,MATCH(1,(GMW!$DA$2:$DA$60=E$3)*(GMW!$DB$2:$DB$60=E$1),0),$A94-1966)} -> 5958536 | F94: {=INDEX(GMW!$A$2:$DB$60,MATCH(1,(GMW!$DA$2:$DA$60=F$3)*(GMW!$DB$2:$DB$60=F$1),0),$A94-1966)} -> 38843.18 | G94: {=INDEX(GMW!$A$2:$DB$60,MATCH(1,(GMW!$DA$2:$DA$60=G$3)*(GMW!$DB$2:$DB$60=G$1),0),$A94-1966)} -> 31.9178 | H94: {=INDEX(GMW!$A$2:$DB$60,MATCH(1,(GMW!$DA$2:$DA$60=H$3)*(GMW!$DB$2:$DB$60=H$1),0),$A94-1966)} -> 703536.3 | I94: {=INDEX(GMW!$A$2:$DB$60,MATCH(1,(GMW!$DA$2:$DA$60=I$3)*(GMW!$DB$2:$DB$60=I$1),0),$A94-1966)} -> 45201.8 | ... P94: {=INDEX(GMW!$A$2:$DB$60,MATCH(1,(GMW!$DA$2:$DA$60=P$3)*(GMW!$DB$2:$DB$60=P$1),0),$A94-1966)} -> 10430610

Sheet GMW
A1: Location | B1: Indicator | C1: Scenario | D1: Units | E1: Scale | F1: Measurement | G1: 1973 | H1: 1974 | I1: 1975 | J1: 1976 | K1: 1977 | L1: 1978 | M1: 1979 | N1: 1980 | O1: 1981 | P1: 1982 | Q1: 1983 | R1: 1984 | S1: 1985 | T1: 1986 | U1: 1987 | V1: 1988 | W1: 1989 | X1: 1990 | Y1: 1991 | Z1: 1992 | AA1: 1993 | AB1: 1994 | AC1: 1995 | AD1: 1996 | AE1: 1997 | AF1: 1998 | AG1: 1999 | AH1: 2000 | AI1: 2001 | AJ1: 2002 | AK1: 2003 | AL1: 2004 | AM1: 2005 | AN1: 2006 | AO1: 2007 | AP1: 2008 | AQ1: 2009 | AR1: 2010 | AS1: 2011 | AT1: 2012 | AU1: 2013 | AV1: 2014 | AW1: 2015 | AX1: 2016 | AY1: 2017 | AZ1: 2018 | BA1: 2019 | BB1: 2020 | BC1: 2021 | BD1: 2022 | BE1: 2023 | BF1: 2024 | BG1: 2025 | BH1: 2026 | BI1: 2027 | BJ1: 2028 | BK1: 2029 | BL1: 2030 | BM1: 2031 | BN1: 2032 | BO1: 2033 | BP1: 2034 | BQ1: 2035 | BR1: 2036 | BS1: 2037 | BT1: 2038 | BU1: 2039 | BV1: 2040 | BW1: 2041 | BX1: 2042 | BY1: 2043 | BZ1: 2044 | CA1: 2045 | CB1: 2046 | CC1: 2047 | CD1: 2048 | CE1: 2049 | CF1: 2050 | CG1: 2051 | CH1: 2052 | CI1: 2053 | CJ1: 2054 | CK1: 2055 | CL1: 2056 | CM1: 2057 | CN1: 2058 | CO1: 2059 | CP1: 2060 | CQ1: Source | CR1: Seasonally adjusted | CS1: Base year price | CT1: Base year index | CU1: Historical end year | CV1: Historical end quarter | CW1: Date of last update | CX1: Source details | CY1: Additional source details | CZ1: Location code | DA1: Indicator code | DB1: Databank code
A2: United Kingdom | B2: Average hours of work per week | C2: FEB004G | D2: Hours per Week | E2: NA | F2: Level | G2: 0.001 | H2: 0.001 | I2: 0.001 | J2: 0.001 | K2: 0.001 | L2: 0.001 | M2: 0.001 | N2: 0.001 | O2: 0.001 | P2: 0.001 | Q2: 0.001 | R2: 0.001 | S2: 0.001 | T2: 33.52414 | U2: 33.52414 | V2: 33.6901 | W2: 33.77308 | X2: 33.60712 | Y2: 33.19222 | Z2: 33.07629 | AA2: 33 | AB2: 33.225 | AC2: 33.25 | AD2: 33.225 | AE2: 33.175 | AF2: 33.075 | AG2: 32.9 | AH2: 32.6 | AI2: 32.675 | AJ2: 32.325 | AK2: 32.15 | AL2: 32.075 | AM2: 32.175 | AN2: 32.05 | AO2: 32.075 | AP2: 31.975 | AQ2: 31.55 | AR2: 31.65 | AS2: 31.575 | AT2: 31.825 | AU2: 32.05 | AV2: 32.175 | AW2: 32.1 | AX2: 32.05 | AY2: 32.1 | AZ2: 32 | BA2: 32.05 | BB2: 28.875 | BC2: 30.95 | BD2: 31.75 | BE2: 31.625 | BF2: 31.975 | BG2: 31.825 | BH2: 31.925 | BI2: 31.99948 | BJ2: 31.99865 | BK2: 31.99781 | BL2: 31.99698 | BM2: 31.99615 | BN2: 31.99531 | BO2: 31.99357 | BP2: 31.99128 | BQ2: 31.98898 | BR2: 31.98669 | BS2: 31.9844 | BT2: 31.98211 | BU2: 31.97982 | BV2: 31.97753 | BW2: 31.97479 | BX2: 31.9718 | BY2: 31.9688 | BZ2: 31.9658 | CA2: 31.9628 | CB2: 31.95979 | CC2: 31.95679 | CD2: 31.95379 | CE2: 31.9508 | CF2: 31.94779 | CG2: 31.9448 | CH2: 31.9418 | CI2: 31.93879 | CJ2: 31.93579 | CK2: 31.93279 | CL2: 31.9298 | CM2: 31.9268 | CN2: 31.92379 | CO2: 31.9208 | CP2: 31.9178 | CQ2: ONS\Haver Analytics | CR2: FALSE | CS2: NA | CT2: NA | CU2: 2025 | CV2: 3 | CW2: 46057 | CX2: YBUVQ@UK | CY2: UK: LFS: Average Actual Weekly Hours Worked: All Workers (SA, Number) | CZ2: GBR | DA2: AVHR | DB2: Desktop
A3: United Kingdom | B3: Capital stock, real, LCU | C3: FEB004G | D3: Pound | E3: Millions: chained 2023 prices | F3: Level | G3: 1059904 | H3: 1089042 | I3: 1117422 | J3: 1143676 | K3: 1167655 | L3: 1197400 | M3: 1220468 | N3: 1238528 | O3: 1247026 | P3: 1258257 | Q3: 1271612 | R3: 1295894 | S3: 1321996 | T3: 1343092 | U3: 1373292 | V3: 1416696 | W3: 1468447 | X3: 1526420 | Y3: 1575894 | Z3: 1605639 | AA3: 1635840 | AB3: 1671807 | AC3: 1712783 | AD3: 1754821 | AE3: 1809000 | AF3: 1867000 | AG3: 1923000 | AH3: 1983000 | AI3: 2038000 | AJ3: 2081000 | AK3: 2118000 | AL3: 2149000 | AM3: 2193000 | AN3: 2239000 | AO3: 2304000 | AP3: 2370000 | AQ3: 2401000 | AR3: 2435000 | AS3: 2465000 | AT3: 2495000 | AU3: 2527000 | AV3: 2574000 | AW3: 2635000 | AX3: 2706000 | AY3: 2780000 | AZ3: 2838000 | BA3: 2892000 | BB3: 2920000 | BC3: 2967000 | BD3: 3028000 | BE3: 3095000 | BF3: 3153000 | BG3: 3210988 | BH3: 3257932 | BI3: 3305250 | BJ3: 3353361 | BK3: 3401949 | BL3: 3451700 | BM3: 3503373 | BN3: 3557452 | BO3: 3614353 | BP3: 3674380 | BQ3: 3737431 | BR3: 3803435 | BS3: 3872296 | BT3: 3943931 | BU3: 4018269 | BV3: 4095163 | BW3: 4174660 | BX3: 4256788 | BY3: 4341282 | BZ3: 4427700 | CA3: 4515675 | CB3: 4605080 | CC3: 4695962 | CD3: 4788220 | CE3: 4881777 | CF3: 4976234 | CG3: 5071464 | CH3: 5167431 | CI3: 5264017 | CJ3: 5361248 | CK3: 5459089 | CL3: 5557519 | CM3: 5656602 | CN3: 5756439 | CO3: 5857050 | CP3: 5958536 | CQ3: Office for National Statistics\Haver Analytics | CR3: FALSE | CS3: chained 2023 | CT3: NA | CU3: 2024 | CV3: 4 | CW3: 46057 | CX3: (MLR3A@UK-MLO9A@UK)*1000, interpolated | CY3: (UK: Net Capital Stock: Assets (Bil.Chn.2023.GBP) - UK: Net Capital Stock: Dwellings excluding Land (Bil.Chn.2023.GBP)) *1000, interpolated | CZ3: GBR | DA3: K | DB3: Desktop
A4: United Kingdom | B4: Employment at the Nairu | C4: FEB004G | D4: Person | E4: Thousands | F4: Level | G4: 24874.8 | H4: 24938.64 | I4: 24932.05 | J4: 24850.21 | K4: 24800.74 | L4: 24703.73 | M4: 24709.44 | N4: 24765.53 | O4: 24659.65 | P4: 24297.71 | Q4: 24304.68 | R4: 24910.8 | S4: 25107.87 | T4: 25255.61 | U4: 25501.77 | V4: 25806.3 | W4: 26091.83 | X4: 26176.67 | Y4: 25966.49 | Z4: 25667.16 | AA4: 25571.12 | AB4: 25629.68 | AC4: 25810.1 | AD4: 26087.38 | AE4: 26460.54 | AF4: 26754.36 | AG4: 27233.62 | AH4: 27515.48 | AI4: 27733.68 | AJ4: 27999.35 | AK4: 28224.98 | AL4: 28456.06 | AM4: 28798.3 | AN4: 29268.07 | AO4: 29481.35 | AP4: 29844.01 | AQ4: 29980.81 | AR4: 30099.27 | AS4: 30283.37 | AT4: 30581.23 | AU4: 30844.5 | AV4: 31116.07 | AW4: 31474.14 | AX4: 31848.04 | AY4: 32069.5 | AZ4: 32402.66 | BA4: 32766.24 | BB4: 32678.28 | BC4: 32676.13 | BD4: 32856.3 | BE4: 33332.92 | BF4: 33685.11 | BG4: 34427.06 | BH4: 34702.44 | BI4: 34894.57 | BJ4: 35093.02 | BK4: 35297.12 | BL4: 35509.09 | BM4: 35723.24 | BN4: 35929.32 | BO4: 36130.95 | BP4: 36327.62 | BQ4: 36509.37 | BR4: 36689.88 | BS4: 36870.4 | BT4: 37050.91 | BU4: 37231.42 | BV4: 37411.93 | BW4: 37604.93 | BX4: 37803.74 | BY4: 37980.72 | BZ4: 38118.6 | CA4: 38222.8 | CB4: 38314.22 | CC4: 38408.25 | CD4: 38491.5 | CE4: 38566.08 | CF4: 38625.23 | CG4: 38677.05 | CH4: 38718.06 | CI4: 38744.48 | CJ4: 38768.02 | CK4: 38784.14 | CL4: 38794.04 | CM4: 38804.19 | CN4: 38817.58 | CO4: 38828.64 | CP4: 38843.18 | CQ4: Oxford Economics estimate | CR4: FALSE | CS4: NA | CT4: NA | CU4: 2024 | CV4: 4 | CW4: 46057 | CX4: Oxford Economics estimate | CY4: NA | CZ4: GBR | DA4: ESTAR | DB4: Desktop
A5: United Kingdom | B5: Employment, aged 16 and over, ILO definition | C5: FEB004G | D5: Person | E5: Thousands | F5: Level | G5: 24965 | H5: 25029.25 | I5: 24933.25 | J5: 24786 | K5: 24809 | L5: 24939.75 | M5: 25195.25 | N5: 25086.25 | O5: 24430 | P5: 23950.75 | Q5: 23775.25 | R5: 24285 | S5: 24592.5 | T5: 24746.25 | U5: 25238.75 | V5: 26070 | W5: 26748.75 | X5: 26871.25 | Y5: 26162.5 | Z5: 25540 | AA5: 25302.75 | AB5: 25504.5 | AC5: 25818.5 | AD5: 26059.75 | AE5: 26525.75 | AF5: 26795 | AG5: 27167.75 | AH5: 27483.5 | AI5: 27712 | AJ5: 27943.75 | AK5: 28221.25 | AL5: 28530 | AM5: 28849.75 | AN5: 29137.75 | AO5: 29378 | AP5: 29628.5 | AQ5: 29156 | AR5: 29228.5 | AS5: 29381 | AT5: 29723 | AU5: 30096.75 | AV5: 30818.25 | AW5: 31345.75 | AX5: 31810.25 | AY5: 32127.75 | AZ5: 32506.75 | BA5: 32923 | BB5: 32558.75 | BC5: 32555 | BD5: 32957.25 | BE5: 33351 | BF5: 33615.5 | BG5: 34170.35 | BH5: 34316.22 | BI5: 34577.91 | BJ5: 34880.04 | BK5: 35157.74 | BL5: 35411.58 | BM5: 35676.31 | BN5: 35917.63 | BO5: 36130.95 | BP5: 36327.62 | BQ5: 36509.37 | BR5: 36689.88 | BS5: 36870.39 | BT5: 37050.91 | BU5: 37231.42 | BV5: 37411.93 | BW5: 37604.94 | BX5: 37803.73 | BY5: 37980.72 | BZ5: 38118.6 | CA5: 38222.8 | CB5: 38314.22 | CC5: 38408.25 | CD5: 38491.5 | CE5: 38566.08 | CF5: 38625.23 | CG5: 38677.05 | CH5: 38718.06 | CI5: 38744.48 | CJ5: 38768.02 | CK5: 38784.15 | CL5: 38794.04 | CM5: 38804.18 | CN5: 38817.58 | CO5: 38828.64 | CP5: 38843.18 | CQ5: Office for National Statistics\Haver Analytics | CR5: TRUE | CS5: NA | CT5: NA | CU5: 2025 | CV5: 3 | CW5: 46057 | CX5: MGRZQ@UK | CY5: UK: LFS: Employment: Aged 16 and Over (SA, Thous) | CZ5: GBR | DA5: ETILO | DB5: Desktop
A6: United Kingdom | B6: GDP, nominal, LCU | C6: FEB004G | D6: Pound | E6: Millions | F6: Level | G6: 81809 | H6: 92686 | I6: 115095 | J6: 136995 | K6: 159775 | L6: 186141 | M6: 220966 | N6: 259956 | O6: 290550 | P6: 320013 | Q6: 351900 | R6: 378608 | S6: 415455 | T6: 447561 | U6: 498040 | V6: 557277 | W6: 616595 | X6: 672977 | Y6: 708072 | Z6: 733221 | AA6: 772390 | AB6: 813527 | AC6: 854921 | AD6: 913609 | AE6: 958539 | AF6: 1002804 | AG6: 1046727 | AH6: 1104759 | AI6: 1150542 | AJ6: 1194646 | AK6: 1262502 | AL6: 1327143 | AM6: 1403249 | AN6: 1478080 | AO6: 1551729 | AP6: 1602217 | AQ6: 1559405 | AR6: 1615839 | AS6: 1669945 | AT6: 1721708 | AU6: 1789072 | AV6: 1875066 | AW6: 1928016 | AX6: 2004755 | AY6: 2097222 | AZ6: 2171559 | BA6: 2252961 | BB6: 2124720 | BC6: 2322652 | BD6: 2580949 | BE6: 2752164 | BF6: 2890664 | BG6: 3036810 | BH6: 3135849 | BI6: 3258126 | BJ6: 3379536 | BK6: 3498528 | BL6: 3622229 | BM6: 3755902 | BN6: 3894588 | BO6: 4036918 | BP6: 4185062 | BQ6: 4338592 | BR6: 4497976 | BS6: 4663265 | BT6: 4834916 | BU6: 5013925 | BV6: 5201316 | BW6: 5397826 | BX6: 5602767 | BY6: 5813881 | BZ6: 6029272 | CA6: 6248932 | CB6: 6474800 | CC6: 6708702 | CD6: 6949354 | CE6: 7197288 | CF6: 7451668 | CG6: 7713513 | CH6: 7982503 | CI6: 8258062 | CJ6: 8541962 | CK6: 8833706 | CL6: 9133532 | CM6: 9442621 | CN6: 9761924 | CO6: 10090850 | CP6: 10430610 | CQ6: Office for National Statistics\Haver Analytics | CR6: TRUE | CS6: NA | CT6: NA | CU6: 2025 | CV6: 3 | CW6: 46057 | CX6: YBHAQ@UK | CY6: U.K.: Gross Domestic Product (SA, Mil.Pounds) | CZ6: GBR | DA6: GDP! | DB6: Desktop
A7: United Kingdom | B7: GDP, real, LCU | C7: FEB004G | D7: Pound | E7: Millions: chained 2023 prices | F7: Level | G7: 1063550 | H7: 1036973 | I7: 1021204 | J7: 1051973 | K7: 1077816 | L7: 1122953 | M7: 1164860 | N7: 1140989 | O7: 1134663 | P7: 1157191 | Q7: 1205632 | R7: 1232675 | S7: 1283200 | T7: 1323173 | U7: 1395353 | V7: 1471002 | W7: 1506644 | X7: 1515202 | Y7: 1493903 | Z7: 1498023 | AA7: 1532082 | AB7: 1584459 | AC7: 1622576 | AD7: 1665005 | AE7: 1746257 | AF7: 1802946 | AG7: 1856033 | AH7: 1940007 | AI7: 1986393 | AJ7: 2020341 | AK7: 2085366 | AL7: 2133872 | AM7: 2193421 | AN7: 2241453 | AO7: 2307148 | AP7: 2306008 | AQ7: 2200222 | AR7: 2249959 | AS7: 2269116 | AT7: 2303794 | AU7: 2343384 | AV7: 2417439 | AW7: 2469182 | AX7: 2523665 | AY7: 2599961 | AZ7: 2640295 | BA7: 2673465 | BB7: 2404838 | BC7: 2610286 | BD7: 2744708 | BE7: 2752164 | BF7: 2782111 | BG7: 2820536 | BH7: 2845122 | BI7: 2883162 | BJ7: 2924704 | BK7: 2967061 | BL7: 3010770 | BM7: 3056529 | BN7: 3101862 | BO7: 3146720 | BP7: 3193113 | BQ7: 3240626 | BR7: 3289377 | BS7: 3339125 | BT7: 3389847 | BU7: 3441535 | BV7: 3494880 | BW7: 3550360 | BX7: 3607231 | BY7: 3663765 | BZ7: 3718710 | CA7: 3772181 | CB7: 3825357 | CC7: 3879212 | CD7: 3932862 | CE7: 3986408 | CF7: 4039316 | CG7: 4092014 | CH7: 4144268 | CI7: 4195761 | CJ7: 4247258 | CK7: 4298423 | CL7: 4349305 | CM7: 4400366 | CN7: 4451856 | CO7: 4503392 | CP7: 4555422 | CQ7: Office for National Statistics\Haver Analytics | CR7: TRUE | CS7: chained 2023 | CT7: NA | CU7: 2025 | CV7: 3 | CW7: 46057 | CX7: ABMIQ@UK | CY7: U.K.: Real Gross Domestic Product (SA, Mil.Chn.2023.GBP) | CZ7: GBR | DA7: GDP | DB7: Desktop
A8: United Kingdom | B8: Government debt, net, LCU | C8: FEB004G | D8: Pound | E8: Millions | F8: Level | G8: 31563.38 | H8: 37800.67 | I8: 46452.6 | J8: 53375.52 | K8: 58825.45 | L8: 64877.93 | M8: 72490.47 | N8: 84954.26 | O8: 95587.21 | P8: 103194.7 | Q8: 105693.5 | R8: 95829.01 | S8: 108612.9 | T8: 116453.6 | U8: 115805.7 | V8: 102356.9 | W8: 94653.84 | X8: 101559.6 | Y8: 119147.9 | Z8: 172439.8 | AA8: 234900 | AB8: 278400 | AC8: 313600 | AD8: 341900 | AE8: 365000 | AF8: 364300 | AG8: 368300 | AH8: 333300 | AI8: 335500 | AJ8: 368700 | AK8: 404600 | AL8: 463800 | AM8: 503500 | AN8: 539000 | AO8: 574700 | AP8: 749900 | AQ8: 958600 | AR8: 1152500 | AS8: 1250600 | AT8: 1354300 | AU8: 1452600 | AV8: 1550800 | AW8: 1602900 | AX8: 1690600 | AY8: 1744600 | AZ8: 1798600 | BA8: 1837500 | BB8: 2152500 | BC8: 2364800 | BD8: 2501300 | BE8: 2695600 | BF8: 2815200 | BG8: 2935800 | BH8: 3062897 | BI8: 3207597 | BJ8: 3345910 | BK8: 3481869 | BL8: 3600212 | BM8: 3720058 | BN8: 3851374 | BO8: 3982372 | BP8: 4122138 | BQ8: 4275630 | BR8: 4441028 | BS8: 4619026 | BT8: 4810366 | BU8: 5015858 | BV8: 5236382 | BW8: 5464936 | BX8: 5701732 | BY8: 5947058 | BZ8: 6201096 | CA8: 6464012 | CB8: 6736048 | CC8: 7017528 | CD8: 7308728 | CE8: 7609944 | CF8: 7921438 | CG8: 8243509 | CH8: 8576451 | CI8: 8920527 | CJ8: 9276071 | CK8: 9643402 | CL8: 10022840 | CM8: 10414770 | CN8: 10819590 | CO8: 11237690 | CP8: 11669510 | CQ8: Office for National Statistics\Haver Analytics | CR8: FALSE | CS8: NA | CT8: NA | CU8: 2025 | CV8: 4 | CW8: 46057 | CX8: HF6WQ@UK * 1000 | CY8: UK: Public Sector: Net Debt excluding Financial Interventions (NSA, Bil.GBP) * 1000 | CZ8: GBR | DA8: GNDBT | DB8: Desktop
A9: United Kingdom | B9: Nairu | C9: FEB004G | D9: % | E9: NA | F9: Level | G9: 4 | H9: 4 | I9: 4.5 | J9: 5.15 | K9: 5.625 | L9: 6.4 | M9: 7.2 | N9: 8 | O9: 8.8 | P9: 9.425 | Q9: 9.5 | R9: 9.5 | S9: 9.5 | T9: 9.5 | U9: 9.5 | V9: 9.5 | W9: 9.5 | X9: 9.5 | Y9: 9.5 | Z9: 9.5 | AA9: 9.425 | AB9: 9.049999 | AC9: 8.65 | AD9: 8 | AE9: 7.2 | AF9: 6.4 | AG9: 5.75 | AH9: 5.35 | AI9: 5.025 | AJ9: 5 | AK9: 5 | AL9: 5 | AM9: 5 | AN9: 5 | AO9: 5 | AP9: 5 | AQ9: 5 | AR9: 5.125 | AS9: 5.2875 | AT9: 5.3 | AU9: 5.3 | AV9: 5.2625 | AW9: 4.9875 | AX9: 4.775 | AY9: 4.575 | AZ9: 4.39375 | BA9: 4.2875 | BB9: 4.25 | BC9: 4.175 | BD9: 4.1 | BE9: 4.1 | BF9: 4.1 | BG9: 4.1 | BH9: 4.1 | BI9: 4.1 | BJ9: 4.1 | BK9: 4.0925 | BL9: 4.055 | BM9: 4.015 | BN9: 4 | BO9: 4 | BP9: 4 | BQ9: 4 | BR9: 4 | BS9: 4 | BT9: 4 | BU9: 4 | BV9: 4 | BW9: 4 | BX9: 4 | BY9: 4 | BZ9: 4 | CA9: 4 | CB9: 4 | CC9: 4 | CD9: 4 | CE9: 4 | CF9: 4 | CG9: 4 | CH9: 4 | CI9: 4 | CJ9: 4 | CK9: 4 | CL9: 4 | CM9: 4 | CN9: 4 | CO9: 4 | CP9: 4 | CQ9: Oxford Economics estimate | CR9: FALSE | CS9: NA | CT9: NA | CU9: 2024 | CV9: 4 | CW9: 46057 | CX9: Oxford Economics estimate | CY9: The NAIRU | CZ9: GBR | DA9: NAIRU | DB9: Desktop
A10: United Kingdom | B10: Output gap | C10: FEB004G | D10: % | E10: NA | F10: Level | G10: -0.8635044 | H10: -4.512739 | I10: -6.779242 | J10: -4.236555 | K10: -2.098274 | L10: 1.005578 | M10: 2.358103 | N10: -2.058458 | O10: -4.09863 | P10: -2.75178 | Q10: -0.3082991 | R10: -1.554108 | S10: -0.3017902 | T10: 0.2162218 | U10: 2.746868 | V10: 4.52776 | W10: 3.37007 | X10: 1.270151 | Y10: -1.534724 | Z10: -2.652216 | AA10: -2.037263 | AB10: -1.257992 | AC10: -1.435089 | AD10: -1.521969 | AE10: 0.4448891 | AF10: 1.34685 | AG10: 1.554561 | AH10: 3.848004 | AI10: 3.198195 | AJ10: 2.559781 | AK10: 3.259182 | AL10: 3.069377 | AM10: 2.902269 | AN10: 2.37515 | AO10: 3.118372 | AP10: 1.032782 | AQ10: -4.144692 | AR10: -3.055406 | AS10: -3.105092 | AT10: -3.346658 | AU10: -3.265452 | AV10: -1.664901 | AW10: -1.00441 | AX10: -0.5028248 | AY10: 0.8413076 | AZ10: 0.9132385 | BA10: 0.4998207 | BB10: -3.565812 | BC10: 0.05774498 | BD10: 2.368307 | BE10: 1.090384 | BF10: -0.1038313 | BG10: -0.662899 | BH10: -1.256728 | BI10: -1.147556 | BJ10: -0.8438826 | BK10: -0.5733013 | BL10: -0.3464937 | BM10: -0.1391888 | BN10: -0.02062321 | BO10: -2.384186e-05 | BP10: 4.768372e-05 | BQ10: 4.768372e-05 | BR10: 7.152557e-05 | BS10: 4.768372e-05 | BT10: 7.152557e-05 | BU10: 7.152557e-05 | BV10: 9.536743e-05 | BW10: 4.768372e-05 | BX10: 7.152557e-05 | BY10: 7.152557e-05 | BZ10: 0.000166893 | CA10: 0.0001192093 | CB10: 0.0001192093 | CC10: 0.0001430511 | CD10: 7.152557e-05 | CE10: 7.152557e-05 | CF10: 9.536743e-05 | CG10: 0.0001192093 | CH10: 7.152557e-05 | CI10: 9.536743e-05 | CJ10: 2.384186e-05 | CK10: 7.152557e-05 | CL10: 2.384186e-05 | CM10: 0.0001192093 | CN10: 4.768372e-05 | CO10: 7.152557e-05 | CP10: 0.000166893 | CQ10: Oxford Economics calculation | CR10: FALSE | CS10: NA | CT10: NA | CU10: 2024 | CV10: 4 | CW10: 46057 | CX10: Oxford Economics calculation | CY10: NA | CZ10: GBR | DA10: CUMOD | DB10: Desktop
A11: United Kingdom | B11: Population of working age | C11: FEB004G | D11: Person | E11: Thousands | F11: Level | G11: 32757.89 | H11: 32767.07 | I11: 32762.08 | J11: 32795.71 | K11: 32987.17 | L11: 33191.79 | M11: 33396.4 | N11: 33601.01 | O11: 33792.79 | P11: 33953.4 | Q11: 34192.7 | R11: 34431.35 | S11: 34601.24 | T11: 34744.76 | U11: 34886.88 | V11: 34994.56 | W11: 35085.88 | X11: 35152.13 | Y11: 35195.33 | Z11: 35205.66 | AA11: 35216.77 | AB11: 35273.27 | AC11: 35383.34 | AD11: 35513.12 | AE11: 35638.8 | AF11: 35772.38 | AG11: 35956.09 | AH11: 36175.06 | AI11: 36435.72 | AJ11: 36685.3 | AK11: 36916.48 | AL11: 37197 | AM11: 37558.84 | AN11: 37877.6 | AO11: 38141.88 | AP11: 38372.89 | AQ11: 38572.07 | AR11: 38889.22 | AS11: 39318.54 | AT11: 39577.57 | AU11: 39885.01 | AV11: 40230.7 | AW11: 40619.86 | AX11: 41036.28 | AY11: 41408.97 | AZ11: 41800.04 | BA11: 42268.43 | BB11: 42633.5 | BC11: 42900.68 | BD11: 43306 | BE11: 43867.71 | BF11: 44324.94 | BG11: 44442.19 | BH11: 44368.3 | BI11: 44564.99 | BJ11: 44983.96 | BK11: 45297.95 | BL11: 45373.88 | BM11: 45421.33 | BN11: 45472.34 | BO11: 45535.95 | BP11: 45589.85 | BQ11: 45632.65 | BR11: 45674.43 | BS11: 45709.22 | BT11: 45743.41 | BU11: 45769.57 | BV11: 45799.7 | BW11: 45858.47 | BX11: 45946.53 | BY11: 46048.25 | BZ11: 46185.2 | CA11: 46464.62 | CB11: 46914.97 | CC11: 47238.56 | CD11: 47310.73 | CE11: 47337.16 | CF11: 47362.54 | CG11: 47391.39 | CH11: 47415.06 | CI11: 47431.08 | CJ11: 47423.87 | CK11: 47407.54 | CL11: 47378.16 | CM11: 47329.91 | CN11: 47280.8 | CO11: 47220.39 | CP11: 47150.05 | CQ11: Office for National Statistics Population Estimates | CR11: FALSE | CS11: NA | CT11: NA | CU11: 2024 | CV11: 2 | CW11: 46057 | CX11: Calculated by Oxford Economics using ONS single-year population estimates. Allows for changing state pension age | CY11: NA | CZ11: GBR | DA11: POPW | DB11: Desktop
A12: United Kingdom | B12: Population, 15-64 | C12: FEB004G | D12: Person | E12: Thousands | F12: Level | G12: 35322.81 | H12: 35332.71 | I12: 35327.33 | J12: 35352.08 | K12: 35501.05 | L12: 35670.84 | M12: 35882.96 | N12: 36102.32 | O12: 36300.18 | P12: 36500.68 | Q12: 36776.19 | R12: 37029.13 | S12: 37116.96 | T12: 37205.48 | U12: 37265.83 | V12: 37299.2 | W12: 37327.73 | X12: 37358.56 | Y12: 37364.49 | Z12: 37339.07 | AA12: 37349.41 | AB12: 37433.7 | AC12: 37553 | AD12: 37673.28 | AE12: 37794.41 | AF12: 37944.26 | AG12: 38156.28 | AH12: 38407.35 | AI12: 38667.29 | AJ12: 38934.07 | AK12: 39208.64 | AL12: 39524.45 | AM12: 39942.1 | AN12: 40350.64 | AO12: 40723.55 | AP12: 41014.32 | AQ12: 41237.87 | AR12: 41479.08 | AS12: 41689.11 | AT12: 41698.6 | AU12: 41772.11 | AV12: 41914.35 | AW12: 42102.28 | AX12: 42299.06 | AY12: 42426.66 | AZ12: 42565.27 | BA12: 42702.21 | BB12: 42780.8 | BC12: 42964.73 | BD12: 43370.1 | BE12: 43941.6 | BF12: 44390.12 | BG12: 44533.42 | BH12: 44547.9 | BI12: 44573.84 | BJ12: 44596.25 | BK12: 44613.64 | BL12: 44624.91 | BM12: 44651.04 | BN12: 44704.37 | BO12: 44757.55 | BP12: 44805.02 | BQ12: 44850.61 | BR12: 44896.95 | BS12: 44923.39 | BT12: 44977.55 | BU12: 45037.79 | BV12: 45122.38 | BW12: 45221.64 | BX12: 45336.43 | BY12: 45461.84 | BZ12: 45566.51 | CA12: 45620.89 | CB12: 45645.4 | CC12: 45668.5 | CD12: 45694.41 | CE12: 45714.5 | CF12: 45726.45 | CG12: 45714.27 | CH12: 45692.26 | CI12: 45656.63 | CJ12: 45601.84 | CK12: 45546.53 | CL12: 45480.28 | CM12: 45404.92 | CN12: 45333.13 | CO12: 45270.12 | CP12: 45201.8 | CQ12: Office for National Statistics Mid-Year Population Estimates | CR12: FALSE | CS12: NA | CT12: NA | CU12: 2024 | CV12: 2 | CW12: 46057 | CX12: Population aged 15-64 aggregated from ONS mid-year population estimates | CY12: NA | CZ12: GBR | DA12: POP15_64 | DB12: Desktop
A13: United Kingdom | B13: Population, total | C13: FEB004G | D13: Person | E13: Thousands | F13: Level | G13: 56217.56 | H13: 56233.31 | I13: 56224.75 | J13: 56211.75 | K13: 56189.38 | L13: 56190.38 | M13: 56253 | N13: 56329.63 | O13: 56343.69 | P13: 56299.88 | Q13: 56331.88 | R13: 56430.38 | S13: 56569.31 | T13: 56698.38 | U13: 56817.5 | V13: 56939.19 | W13: 57097.12 | X13: 57265.62 | Y13: 57453.81 | Z13: 57600.06 | AA13: 57733.69 | AB13: 57883.31 | AC13: 58040.88 | AD13: 58183.44 | AE13: 58334.81 | AF13: 58504.12 | AG13: 58708.81 | AH13: 58915.94 | AI13: 59146.25 | AJ13: 59401 | AK13: 59678.75 | AL13: 60017.25 | AM13: 60461.69 | AN13: 60893.38 | AO13: 61382.94 | AP13: 61874.38 | AQ13: 62327.25 | AR13: 62827.25 | AS13: 63332.06 | AT13: 63764.44 | AU13: 64201.5 | AV13: 64676.69 | AW13: 65155.06 | AX13: 65640.69 | AY13: 66002.19 | AZ13: 66330.75 | BA13: 66627.69 | BB13: 66777.62 | BC13: 67086.5 | BD13: 67761.75 | BE13: 68611.94 | BF13: 69272.44 | BG13: 69493.98 | BH13: 69614.42 | BI13: 69767.96 | BJ13: 69953.27 | BK13: 70158.98 | BL13: 70381.77 | BM13: 70618.57 | BN13: 70864.85 | BO13: 71104.8 | BP13: 71337.5 | BQ13: 71563.23 | BR13: 71782.41 | BS13: 71995.59 | BT13: 72203.38 | BU13: 72406.2 | BV13: 72604.4 | BW13: 72798.29 | BX13: 72988.03 | BY13: 73173.42 | BZ13: 73354.02 | CA13: 73529.48 | CB13: 73699.51 | CC13: 73863.57 | CD13: 74020.27 | CE13: 74168.23 | CF13: 74306.82 | CG13: 74435.73 | CH13: 74554.91 | CI13: 74664.36 | CJ13: 74764.41 | CK13: 74855.8 | CL13: 74939.66 | CM13: 75017.17 | CN13: 75089.39 | CO13: 75157.48 | CP13: 75222.94 | CQ13: Office for National Statistics\Haver Analytics | CR13: FALSE | CS13: NA | CT13: NA | CU13: 2025 | CV13: 2 | CW13: 46057 | CX13: DYAYA@UK | CY13: U.K.: Population: Midyear Estimates (Thous.Persons) | CZ13: GBR | DA13: POP | DB13: Desktop
... A18: United Kingdom | B18: Total Years of Schooling in Population | C18: FEB004G | D18: Years | E18: NA | F18: Level | G18: 286021.4 | H18: 288869 | I18: 291532.5 | J18: 293842.9 | K18: 295875.2 | L18: 297883.1 | M18: 300120.3 | N18: 306731.3 | O18: 309382.7 | P18: 311708.9 | Q18: 314668.8 | R18: 318382.6 | S18: 322872.1 | T18: 327826.4 | U18: 332272.4 | V18: 336945.5 | W18: 341767.8 | X18: 346213.4 | Y18: 350307.5 | Z18: 353919.6 | AA18: 357272.1 | AB18: 360583.8 | AC18: 363847.5 | AD18: 366199.2 | AE18: 368101.4 | AF18: 370531.5 | AG18: 375183.3 | AH18: 383089.9 | AI18: 395262.5 | AJ18: 410903.6 | AK18: 428210.7 | AL18: 445699.5 | AM18: 462180.4 | AN18: 476476.1 | AO18: 489499.2 | AP18: 500453.1 | AQ18: 509276.2 | AR18: 516794.4 | AS18: 523986.6 | AT18: 528582.9 | AU18: 533883.2 | AV18: 539979 | AW18: 546596.8 | AX18: 553279.6 | AY18: 559022.5 | AZ18: 564875.5 | BA18: 570674.4 | BB18: 575664.8 | BC18: 582053.8 | BD18: 591449.8 | BE18: 603143.5 | BF18: 613184.9 | BG18: 619001.5 | BH18: 622970.9 | BI18: 627020.9 | BJ18: 630937.1 | BK18: 634689 | BL18: 638252.2 | BM18: 641890.8 | BN18: 645735.2 | BO18: 649382.6 | BP18: 652741.4 | BQ18: 655856.6 | BR18: 658802.4 | BS18: 661344.3 | BT18: 664192.2 | BU18: 667045.8 | BV18: 670206.3 | BW18: 673555.8 | BX18: 677117.5 | BY18: 680823.2 | BZ18: 684201.1 | CA18: 686790.8 | CB18: 688888.8 | CC18: 690924 | CD18: 692966.1 | CE18: 694890.4 | CF18: 696661.2 | CG18: 698040.1 | CH18: 699264.5 | CI18: 700274.5 | CJ18: 700972.5 | CK18: 701641.6 | CL18: 702116.8 | CM18: 702420.5 | CN18: 702752.2 | CO18: 703197.1 | CP18: 703536.3 | CQ18: Barro R. & J.W. Lee\Office for National Statistics Mid-Year Population Estimates | CR18: FALSE | CS18: NA | CT18: NA | CU18: 2010 | CV18: 4 | CW18: 46057 | CX18: EDUCAVE * POP15_64 | CY18: NA | CZ18: GBR | DA18: EDUC | DB18: Desktop

Sheet ONS popproj Jan25 pp
A1: Persons, thousands - population by broad age group, components of change and summary statistics [note 1]
A2: United Kingdom (UK)
A3: Principal projection
A4: This worksheet contains three tables presented vertically with one blank row between each table. Some cells refer to notes which can be found on the notes worksheet.
A5: Shorthand is used, z = not applicable
A6: Table 1: Projected population, components of change (to mid-year ending), Total Fertility Rate (TFR) and Expectation Of Life At Birth (EOLB) based on the mortality rates for the year
A7: Components | B7: 2022 [note 2] | C7: 2023 | D7: 2024 | E7: 2025 | F7: 2026 | G7: 2027 | H7: 2028 | I7: 2029 | J7: 2030 | K7: 2031 | L7: 2032 | M7: 2033 | N7: 2034 | O7: 2035 | P7: 2036 | Q7: 2037 | R7: 2038 | S7: 2039 | T7: 2040 | U7: 2041 | V7: 2042 | W7: 2043 | X7: 2044 | Y7: 2045 | Z7: 2046 | AA7: 2047 | AB7: 2048 | AC7: 2049 | AD7: 2050 | AE7: 2051 | AF7: 2052 | AG7: 2053 | AH7: 2054 | AI7: 2055 | AJ7: 2056 | AK7: 2057 | AL7: 2058 | AM7: 2059 | AN7: 2060 | AO7: 2061 | AP7: 2062 | AQ7: 2063 | AR7: 2064 | AS7: 2065 | AT7: 2066 | AU7: 2067 | AV7: 2068 | AW7: 2069 | AX7: 2070 | AY7: 2071 | AZ7: 2072 | BA7: 2073 | BB7: 2074 | BC7: 2075 | BD7: 2076 | BE7: 2077 | BF7: 2078 | BG7: 2079 | BH7: 2080 | BI7: 2081 | BJ7: 2082 | BK7: 2083 | BL7: 2084 | BM7: 2085 | BN7: 2086 | BO7: 2087 | BP7: 2088 | BQ7: 2089 | BR7: 2090 | BS7: 2091 | BT7: 2092 | BU7: 2093 | BV7: 2094 | BW7: 2095 | BX7: 2096 | BY7: 2097 | BZ7: 2098 | CA7: 2099 | CB7: 2100 | CC7: 2101 | CD7: 2102 | CE7: 2103 | CF7: 2104 | CG7: 2105 | CH7: 2106 | CI7: 2107 | CJ7: 2108 | CK7: 2109 | CL7: 2110 | CM7: 2111 | CN7: 2112 | CO7: 2113 | CP7: 2114 | CQ7: 2115 | CR7: 2116 | CS7: 2117 | CT7: 2118 | CU7: 2119 | CV7: 2120 | CW7: 2121 | CX7: 2122
A8: Population at start | B8: [z] | C8: 67602.761 | D8: 68492.495 | E8: 69226.231 | F8: 69867.979 | G8: 70414.3 | H8: 70861.913 | I8: 71208.101 | J8: 71547.662 | K8: 71879.988 | L8: 72204.574 | M8: 72521.173 | N8: 72830.021 | O8: 73131.597 | P8: 73426.168 | Q8: 73714.089 | R8: 73995.941 | S8: 74272.334 | T8: 74543.738 | U8: 74810.478 | V8: 75072.892 | W8: 75331.209 | X8: 75585.236 | Y8: 75834.507 | Z8: 76078.686 | AA8: 76317.48 | AB8: 76550.535 | AC8: 76776.46 | AD8: 76993.637 | AE8: 77201.483 | AF8: 77399.645 | AG8: 77588.049 | AH8: 77766.71 | AI8: 77935.834 | AJ8: 78096.133 | AK8: 78248.758 | AL8: 78394.896 | AM8: 78535.61 | AN8: 78672.036 | AO8: 78805.317 | AP8: 78936.487 | AQ8: 79066.48 | AR8: 79195.863 | AS8: 79325.004 | AT8: 79454.27 | AU8: 79583.857 | AV8: 79713.62 | AW8: 79843.214 | AX8: 79972.1 | AY8: 80099.544 | AZ8: 80224.705 | BA8: 80346.626 | BB8: 80464.328 | BC8: 80576.958 | BD8: 80683.666 | BE8: 80783.805 | BF8: 80876.875 | BG8: 80962.574 | BH8: 81040.744 | BI8: 81111.28 | BJ8: 81174.269 | BK8: 81229.882 | BL8: 81278.373 | BM8: 81320.103 | BN8: 81355.442 | BO8: 81384.875 | BP8: 81408.957 | BQ8: 81428.186 | BR8: 81443.111 | BS8: 81454.243 | BT8: 81462.068 | BU8: 81467.091 | BV8: 81469.704 | BW8: 81470.32 | BX8: 81469.232 | BY8: 81466.731 | BZ8: 81463.093 | CA8: 81458.489 | CB8: 81453.12 | CC8: 81447.095 | CD8: 81440.608 | CE8: 81433.781 | CF8: 81426.783 | CG8: 81419.829 | CH8: 81413.183 | CI8: 81407.2 | CJ8: 81402.25 | CK8: 81398.709 | CL8: 81396.967 | CM8: 81397.436 | CN8: 81400.459 | CO8: 81406.276 | CP8: 81415.084 | CQ8: 81426.996 | CR8: 81442.03 | CS8: 81460.095 | CT8: 81480.985 | CU8: 81504.456 | CV8: 81530.145 | CW8: 81557.639 | CX8: 81586.535
A9: Births | B9: [z] | C9: 664.464 | D9: 667.909 | E9: 674.821 | F9: 679.536 | G9: 682.033 | H9: 683.078 | I9: 683.712 | J9: 684.296 | K9: 684.842 | L9: 685.388 | M9: 686.341 | N9: 687.824 | O9: 689.489 | P9: 691.363 | Q9: 693.541 | R9: 696.057 | S9: 698.697 | T9: 701.18 | U9: 703.429 | V9: 705.443 | W9: 706.766 | X9: 707.187 | Y9: 707.052 | Z9: 706.476 | AA9: 705.561 | AB9: 703.392 | AC9: 699.815 | AD9: 695.821 | AE9: 691.576 | AF9: 687.291 | AG9: 682.886 | AH9: 678.412 | AI9: 674.276 | AJ9: 670.711 | AK9: 667.758 | AL9: 665.234 | AM9: 663.165 | AN9: 661.617 | AO9: 660.582 | AP9: 660.03 | AQ9: 659.744 | AR9: 659.66 | AS9: 659.953 | AT9: 660.535 | AU9: 661.282 | AV9: 662.134 | AW9: 662.999 | AX9: 663.833 | AY9: 664.673 | AZ9: 665.418 | BA9: 666.027 | BB9: 666.469 | BC9: 666.715 | BD9: 666.758 | BE9: 666.554 | BF9: 666.115 | BG9: 665.435 | BH9: 664.498 | BI9: 663.336 | BJ9: 661.957 | BK9: 660.421 | BL9: 658.743 | BM9: 656.976 | BN9: 655.182 | BO9: 653.387 | BP9: 651.671 | BQ9: 650.031 | BR9: 648.514 | BS9: 647.138 | BT9: 645.944 | BU9: 644.941 | BV9: 644.117 | BW9: 643.472 | BX9: 642.999 | BY9: 642.684 | BZ9: 642.513 | CA9: 642.452 | CB9: 642.491 | CC9: 642.589 | CD9: 642.723 | CE9: 642.878 | CF9: 643.028 | CG9: 643.138 | CH9: 643.208 | CI9: 643.209 | CJ9: 643.128 | CK9: 642.964 | CL9: 642.707 | CM9: 642.348 | CN9: 641.901 | CO9: 641.359 | CP9: 640.734 | CQ9: 640.034 | CR9: 639.269 | CS9: 638.464 | CT9: 637.628 | CU9: 636.771 | CV9: 635.916 | CW9: 635.074 | CX9: 634.267
A10: Deaths | B10: [z] | C10: 680.727 | D10: 662.165 | E10: 663.972 | F10: 667.017 | G10: 671.141 | H10: 676.893 | I10: 684.146 | J10: 691.966 | K10: 700.251 | L10: 708.775 | M10: 717.48 | N10: 726.238 | O10: 734.928 | P10: 743.43 | Q10: 751.673 | R10: 759.66 | S10: 767.301 | T10: 774.428 | U10: 781.008 | V10: 787.123 | W10: 792.724 | X10: 797.922 | Y10: 802.872 | Z10: 807.661 | AA10: 812.509 | AB10: 817.471 | AC10: 822.642 | AD10: 827.971 | AE10: 833.423 | AF10: 838.875 | AG10: 844.223 | AH10: 849.282 | AI10: 853.967 | AJ10: 858.092 | AK10: 861.619 | AL10: 864.525 | AM10: 866.729 | AN10: 868.334 | AO10: 869.393 | AP10: 870.025 | AQ10: 870.358 | AR10: 870.515 | AS10: 870.672 | AT10: 870.944 | AU10: 871.519 | AV10: 872.533 | AW10: 874.107 | AX10: 876.379 | AY10: 879.509 | AZ10: 883.49 | BA10: 888.312 | BB10: 893.842 | BC10: 900.001 | BD10: 906.602 | BE10: 913.48 | BF10: 920.421 | BG10: 927.267 | BH10: 933.959 | BI10: 940.342 | BJ10: 946.35 | BK10: 951.927 | BL10: 957.03 | BM10: 961.627 | BN10: 965.737 | BO10: 969.312 | BP10: 972.441 | BQ10: 975.097 | BR10: 977.368 | BS10: 979.317 | BT10: 980.928 | BU10: 982.323 | BV10: 983.499 | BW10: 984.564 | BX10: 985.498 | BY10: 986.324 | BZ10: 987.109 | CA10: 987.824 | CB10: 988.499 | CC10: 989.073 | CD10: 989.552 | CE10: 989.875 | CF10: 989.985 | CG10: 989.778 | CH10: 989.183 | CI10: 988.158 | CJ10: 986.672 | CK10: 984.706 | CL10: 982.241 | CM10: 979.329 | CN10: 976.069 | CO10: 972.545 | CP10: 968.82 | CQ10: 964.992 | CR10: 961.212 | CS10: 957.564 | CT10: 954.156 | CU10: 951.083 | CV10: 948.41 | CW10: 946.163 | CX10: 944.429
A11: Natural Change | B11: [z] | C11: -16.263 | D11: 5.744 | E11: 10.849 | F11: 12.519 | G11: 10.892 | H11: 6.185 | I11: -0.434 | J11: -7.67 | K11: -15.409 | L11: -23.387 | M11: -31.139 | N11: -38.414 | O11: -45.439 | P11: -52.067 | Q11: -58.132 | R11: -63.603 | S11: -68.604 | T11: -73.248 | U11: -77.579 | V11: -81.68 | W11: -85.958 | X11: -90.735 | Y11: -95.82 | Z11: -101.185 | AA11: -106.948 | AB11: -114.079 | AC11: -122.827 | AD11: -132.15 | AE11: -141.847 | AF11: -151.584 | AG11: -161.337 | AH11: -170.87 | AI11: -179.691 | AJ11: -187.381 | AK11: -193.861 | AL11: -199.291 | AM11: -203.564 | AN11: -206.717 | AO11: -208.811 | AP11: -209.995 | AQ11: -210.614 | AR11: -210.855 | AS11: -210.719 | AT11: -210.409 | AU11: -210.237 | AV11: -210.399 | AW11: -211.108 | AX11: -212.546 | AY11: -214.836 | AZ11: -218.072 | BA11: -222.285 | BB11: -227.373 | BC11: -233.286 | BD11: -239.844 | BE11: -246.926 | BF11: -254.306 | BG11: -261.832 | BH11: -269.461 | BI11: -277.006 | BJ11: -284.393 | BK11: -291.506 | BL11: -298.287 | BM11: -304.651 | BN11: -310.555 | BO11: -315.925 | BP11: -320.77 | BQ11: -325.066 | BR11: -328.854 | BS11: -332.179 | BT11: -334.984 | BU11: -337.382 | BV11: -339.382 | BW11: -341.092 | BX11: -342.499 | BY11: -343.64 | BZ11: -344.596 | CA11: -345.372 | CB11: -346.008 | CC11: -346.484 | CD11: -346.829 | CE11: -346.997 | CF11: -346.957 | CG11: -346.64 | CH11: -345.975 | CI11: -344.949 | CJ11: -343.544 | CK11: -341.742 | CL11: -339.534 | CM11: -336.981 | CN11: -334.168 | CO11: -331.186 | CP11: -328.086 | CQ11: -324.958 | CR11: -321.943 | CS11: -319.1 | CT11: -316.528 | CU11: -314.312 | CV11: -312.494 | CW11: -311.089 | CX11: -310.162
A12: International migration inflows | B12: [z] | C12: 1319.5 | D12: 1207 | E12: 1119.7 | F12: 1032.4 | G12: 945.1 | H12: 858 | I12: 858 | J12: 858 | K12: 858 | L12: 858 | M12: 858 | N12: 858 | O12: 858 | P12: 858 | Q12: 858 | R12: 858 | S12: 858 | T12: 858 | U12: 858 | V12: 858 | W12: 858 | X12: 858 | Y12: 858 | Z12: 858 | AA12: 858 | AB12: 858 | AC12: 858 | AD12: 858 | AE12: 858 | AF12: 858 | AG12: 858 | AH12: 858 | AI12: 858 | AJ12: 858 | AK12: 858 | AL12: 858 | AM12: 858 | AN12: 858 | AO12: 858 | AP12: 858 | AQ12: 858 | AR12: 858 | AS12: 858 | AT12: 858 | AU12: 858 | AV12: 858 | AW12: 858 | AX12: 858 | AY12: 858 | AZ12: 858 | BA12: 858 | BB12: 858 | BC12: 858 | BD12: 858 | BE12: 858 | BF12: 858 | BG12: 858 | BH12: 858 | BI12: 858 | BJ12: 858 | BK12: 858 | BL12: 858 | BM12: 858 | BN12: 858 | BO12: 858 | BP12: 858 | BQ12: 858 | BR12: 858 | BS12: 858 | BT12: 858 | BU12: 858 | BV12: 858 | BW12: 858 | BX12: 858 | BY12: 858 | BZ12: 858 | CA12: 858 | CB12: 858 | CC12: 858 | CD12: 858 | CE12: 858 | CF12: 858 | CG12: 858 | CH12: 858 | CI12: 858 | CJ12: 858 | CK12: 858 | CL12: 858 | CM12: 858 | CN12: 858 | CO12: 858 | CP12: 858 | CQ12: 858 | CR12: 858 | CS12: 858 | CT12: 858 | CU12: 858 | CV12: 858 | CW12: 858 | CX12: 858
A13: Cross border migration inflows [note 3] | B13: [z] | C13: [z] | D13: [z] | E13: [z] | F13: [z] | G13: [z] | H13: [z] | I13: [z] | J13: [z] | K13: [z] | L13: [z] | M13: [z] | N13: [z] | O13: [z] | P13: [z] | Q13: [z] | R13: [z] | S13: [z] | T13: [z] | U13: [z] | V13: [z] | W13: [z] | X13: [z] | Y13: [z] | Z13: [z] | AA13: [z] | AB13: [z] | AC13: [z] | AD13: [z] | AE13: [z] | AF13: [z] | AG13: [z] | AH13: [z] | AI13: [z] | AJ13: [z] | AK13: [z] | AL13: [z] | AM13: [z] | AN13: [z] | AO13: [z] | AP13: [z] | AQ13: [z] | AR13: [z] | AS13: [z] | AT13: [z] | AU13: [z] | AV13: [z] | AW13: [z] | AX13: [z] | AY13: [z] | AZ13: [z] | BA13: [z] | BB13: [z] | BC13: [z] | BD13: [z] | BE13: [z] | BF13: [z] | BG13: [z] | BH13: [z] | BI13: [z] | BJ13: [z] | BK13: [z] | BL13: [z] | BM13: [z] | BN13: [z] | BO13: [z] | BP13: [z] | BQ13: [z] | BR13: [z] | BS13: [z] | BT13: [z] | BU13: [z] | BV13: [z] | BW13: [z] | BX13: [z] | BY13: [z] | BZ13: [z] | CA13: [z] | CB13: [z] | CC13: [z] | CD13: [z] | CE13: [z] | CF13: [z] | CG13: [z] | CH13: [z] | CI13: [z] | CJ13: [z] | CK13: [z] | CL13: [z] | CM13: [z] | CN13: [z] | CO13: [z] | CP13: [z] | CQ13: [z] | CR13: [z] | CS13: [z] | CT13: [z] | CU13: [z] | CV13: [z] | CW13: [z] | CX13: [z]
