Workbook
Name _DLX1.INC: HAVERQ!$D$1:$AD$6
Name Data: [1]sheet0!$C$2

Sheet CHARTS>>

Sheet DATA>>

Sheet Chart Data
A1: AE debt dynamics (2026-2030) | W1: Budget deficit in 2025 | AF1: Gross government debt in 2025 | AO1: Government net debt in 2025 | AX1: Budget deficit & debt | BG1: GG net debt | BK1: Term premium | BQ1: Inflation | CF1: Debt interest payments | CJ1: OBR forecasts - GNDBT% | DB1: OBR forecasts - PSNBX% | DT1: Output per worker long-term (5yr ma)
B2: =DataA!BK2 -> UK | C2: =DataA!BL2 -> US | D2: =DataA!BM2 -> Japan | E2: =DataA!BN2 -> Canada | F2: =DataA!BO2 -> Australia | G2: =DataA!BP2 -> Denmark | H2: =DataA!BQ2 -> Sweden | I2: =DataA!BR2 -> Switzerland | ... U2: =DataA!CD2 -> Portugal | X2: =RANK(X4,$X$4:$AD$4) -> 5 | Y2: =RANK(Y4,$X$4:$AD$4) -> 7 | Z2: =RANK(Z4,$X$4:$AD$4) -> 2 | AA2: =RANK(AA4,$X$4:$AD$4) -> 3 | AB2: =RANK(AB4,$X$4:$AD$4) -> 6 | AC2: =RANK(AC4,$X$4:$AD$4) -> 4 | AD2: =RANK(AD4,$X$4:$AD$4) -> 1 | AG2: =RANK(AG4,$AG$4:$AM$4) -> 6 | AH2: =RANK(AH4,$AG$4:$AM$4) -> 3 | AI2: =RANK(AI4,$AG$4:$AM$4) -> 1 | AJ2: =RANK(AJ4,$AG$4:$AM$4) -> 7 | AK2: =RANK(AK4,$AG$4:$AM$4) -> 4 | AL2: =RANK(AL4,$AG$4:$AM$4) -> 2 | AM2: =RANK(AM4,$AG$4:$AM$4) -> 5 | AP2: =RANK(AP4,$AP$4:$AV$4) -> 3 | AQ2: =RANK(AQ4,$AP$4:$AV$4) -> 2 | AR2: =RANK(AR4,$AP$4:$AV$4) -> 4 | AS2: =RANK(AS4,$AP$4:$AV$4) -> 6 | AT2: =RANK(AT4,$AP$4:$AV$4) -> 5 | AU2: =RANK(AU4,$AP$4:$AV$4) -> 1 | AV2: =RANK(AV4,$AP$4:$AV$4) -> 7 | AX2: 2026 | AY2: =X3&", "&$AX2 -> UK, 2026 | AZ2: =Y3&", "&$AX2 -> US, 2026 | BA2: =Z3&", "&$AX2 -> Japan, 2026 | BB2: =AA3&", "&$AX2 -> Germany, 2026 | BC2: =AB3&", "&$AX2 -> France, 2026 | BD2: =AC3&", "&$AX2 -> Italy, 2026 | BE2: =AD3&", "&$AX2 -> Canada, 2026 | BH2: GNDBT% | BI2: GNDBT% (from GEM) | BL2: UK | BM2: US | BN2: Germany | BO2: Japan | BR2: UK | BS2: G7 median | BT2: Bottom | BU2: Range of G7 exc. UK | BX2: UK | BY2: US | BZ2: Japan | CA2: Germany | CB2: France | CC2: Italy | CD2: Canada | CG2: % of government revenue | CH2: % of GDP | CK2: 2015 | CL2: 2016 | CM2: 2017 | CN2: 2018 | CO2: 2019 | CP2: 2020 | CQ2: 2021 | CR2: 2022 | CS2: 2023 | CT2: 2024 | CU2: 2025 | CV2: 2026 | CW2: 2027 | CX2: 2028 | CY2: 2029 | CZ2: 2030 | DC2: 2015 | DD2: 2016 | DE2: 2017 | DF2: 2018 | DG2: 2019 | DH2: 2020 | DI2: 2021 | DJ2: 2022 | DK2: 2023 | DL2: 2024 | DM2: 2025 | DN2: 2026 | DO2: 2027 | DP2: 2028 | DQ2: 2029 | DR2: 2030 | DU2: 5-year moving average | DV2: 10-year moving average | DW2: 1980-2007 average | DX2: 2008-2019 average | EA2: Pre-GFC trend calc | ED2: GFC-pandemic | EG2: Pandemic-now
A3: Expected effective interest rates on government debt (r) | B3: =AVERAGE(DataA!BK60:BK64) -> 4.3075818 | C3: =AVERAGE(DataA!BL60:BL64) -> 3.5375515 | D3: =AVERAGE(DataA!BM60:BM64) -> 1.0687388 | E3: =AVERAGE(DataA!BN60:BN64) -> 3.0697351 | F3: =AVERAGE(DataA!BO60:BO64) -> 2.7182818 | G3: =AVERAGE(DataA!BP60:BP64) -> 2.7025818 | H3: =AVERAGE(DataA!BQ60:BQ64) -> 1.4191454 | I3: =AVERAGE(DataA!BR60:BR64) -> 1.1865096 | ... U3: =AVERAGE(DataA!CD60:CD64) -> 2.2694908 | X3: UK | Y3: US | Z3: Japan | AA3: Germany | AB3: France | AC3: Italy | AD3: Canada | AG3: UK | AH3: US | AI3: Japan | AJ3: Germany | AK3: France | AL3: Italy | AM3: Canada | AP3: UK | AQ3: US | AR3: Japan | AS3: Germany | AT3: France | AU3: Italy | AV3: Canada | AY3: =X3 -> UK | AZ3: =Y3 -> US | BA3: =Z3 -> Japan | BB3: =AA3 -> Germany | BC3: =AB3 -> France | BD3: =AC3 -> Italy | BE3: =AD3 -> Canada | BG3: 1980 | BH3: =100*(SUMIF(HAVERQ!$B:$B,'Chart Data'!$BG3,HAVERQ!L:L)/SUMIF(HAVERQ!$A:$A,'Chart Data'!$BG3,HAVERQ!G:G)) -> 42.727615 | BI3: =100*('Data Q to A'!AK15/'Data Q to A'!AL15) -> 32.060879 | BK3: 43831 | BL3: =DataQ!AQ195 -> -1.400203 | BM3: =DataQ!AR195 -> -1.270818 | BN3: =DataQ!AS195 -> -1.554241 | BO3: =DataQ!AT195 -> -0.4589267 | BQ3: 2020 | BR3: =BX3 -> 1.6557638 | BS3: =MEDIAN(BX3:CD3) -> 1.5192134 | BT3: =MIN(BY3:CD3) -> 0.2790036 | BU3: =MAX(BY3:CD3)-BT3 -> 1.8647638 | BW3: 2020 | BX3: =100*((DataQ!AU195/DataQ!AU191)-1) -> 1.6557638 | BY3: =100*((DataQ!AV195/DataQ!AV191)-1) -> 2.1437674 | BZ3: =100*((DataQ!AW195/DataQ!AW191)-1) -> 0.66870612 | CA3: =100*((DataQ!AX195/DataQ!AX191)-1) -> 1.5192134 | CB3: =100*((DataQ!AY195/DataQ!AY191)-1) -> 1.1940649 | CC3: =100*((DataQ!AZ195/DataQ!AZ191)-1) -> 0.2790036 | CD3: =100*((DataQ!BA195/DataQ!BA191)-1) -> 1.8060865 | CF3: 1960 | CG3: =OBR_MAR26_C4.6!C30 -> 9.9517559 | CH3: =OBR_MAR26_C4.6!D30 -> 3.3290797 | CJ3: History | CK3: {=TRANSPOSE('OBR Agg (per cent of GDP)'!X72:X82)} -> 80.586366 | CL3: 82.708697 | CM3: 81.606768 | CN3: 79.644006 | CO3: 84.499793 | CP3: 95.381028 | CQ3: 94.313911 | CR3: 93.21417 | CS3: 94.1 | CT3: 93.2 | CU3: 93.8 | DB3: History | DC3: {=TRANSPOSE('OBR Agg (per cent of GDP)'!O72:O82)} -> 4.1512226 | DD3: 2.8199641 | DE3: 2.8034391 | DF3: 2.0233908 | DG3: 2.5789127 | DH3: 14.738132 | DI3: 5.0083361 | DJ3: 4.8346149 | DK3: 4.8376726 | DL3: 5.1732984 | DM3: 4.3221745 | DT3: 1960 | DZ3: 1980 | EA3: =AVERAGE(HAVERQ!J87:J90) -> 50.2 | EC3: 2007 | ED3: =AVERAGE(HAVERQ!J195:J198) -> 92.975 | EF3: 2019 | EG3: =AVERAGE(HAVERQ!J243:J246) -> 96.725
A4: Expected annual average nominal GDP growth (g) | B4: =100*((DataA!AP64/DataA!AP59)^(1/5)-1) -> 3.6166959 | C4: =100*((DataA!AQ64/DataA!AQ59)^(1/5)-1) -> 4.6423722 | D4: =100*((DataA!AR64/DataA!AR59)^(1/5)-1) -> 1.9108873 | E4: =100*((DataA!AS64/DataA!AS59)^(1/5)-1) -> 3.6692556 | F4: =100*((DataA!AT64/DataA!AT59)^(1/5)-1) -> 4.7650898 | G4: =100*((DataA!AU64/DataA!AU59)^(1/5)-1) -> 3.5404453 | H4: =100*((DataA!AV64/DataA!AV59)^(1/5)-1) -> 4.0334553 | I4: =100*((DataA!AW64/DataA!AW59)^(1/5)-1) -> 2.2351676 | ... U4: =100*((DataA!BI64/DataA!BI59)^(1/5)-1) -> 3.6953333 | W4: 2025 | X4: =100*('Data Q to A'!I60/'Data Q to A'!AD60) -> -4.9571948 | Y4: =100*('Data Q to A'!J60/'Data Q to A'!AE60) -> -7.4069828 | Z4: =100*('Data Q to A'!K60/'Data Q to A'!AF60) -> -1.842392 | AA4: =100*('Data Q to A'!L60/'Data Q to A'!AG60) -> -2.7607817 | AB4: =100*('Data Q to A'!M60/'Data Q to A'!AH60) -> -5.110621 | AC4: =100*('Data Q to A'!N60/'Data Q to A'!AI60) -> -3.0729095 | AD4: =100*('Data Q to A'!O60/'Data Q to A'!AJ60) -> -0.76203518 | AF4: 2025 | AG4: =100*(HAVERQ!K270/SUM(HAVERQ!$G$267:$G$270)) -> 102.3143 | AH4: =100*('Data Q to A'!Q60/'Data Q to A'!AE60) -> 137.36076 | AI4: =100*('Data Q to A'!R60/'Data Q to A'!AF60) -> 205.18095 | AJ4: =100*('Data Q to A'!S60/'Data Q to A'!AG60) -> 59.442747 | AK4: =100*('Data Q to A'!T60/'Data Q to A'!AH60) -> 124.09208 | AL4: =100*('Data Q to A'!U60/'Data Q to A'!AI60) -> 149.35996 | AM4: =100*('Data Q to A'!V60/'Data Q to A'!AJ60) -> 107.47438 | AO4: 2025 | AP4: =100*(HAVERQ!L270/SUM(HAVERQ!$G$267:$G$270)) -> 93.846256 | AQ4: =100*('Data Q to A'!X60/'Data Q to A'!AE60) -> 101.74622 | AR4: =100*('Data Q to A'!Y60/'Data Q to A'!AF60) -> 87.280865 | AS4: =100*('Data Q to A'!Z60/'Data Q to A'!AG60) -> 21.998883 | AT4: =100*('Data Q to A'!AA60/'Data Q to A'!AH60) -> 76.159851 | AU4: =100*('Data Q to A'!AB60/'Data Q to A'!AI60) -> 124.67013 | AV4: =100*('Data Q to A'!AC60/'Data Q to A'!AJ60) -> 8.3304342 | AX4: Budget deficit | AY4: =X4 -> -4.9571948 | AZ4: =Y4 -> -7.4069828 | BA4: =Z4 -> -1.842392 | BB4: =AA4 -> -2.7607817 | BC4: =AB4 -> -5.110621 | BD4: =AC4 -> -3.0729095 | BE4: =AD4 -> -0.76203518 | BG4: 1981 | BH4: =100*(SUMIF(HAVERQ!$B:$B,'Chart Data'!$BG4,HAVERQ!L:L)/SUMIF(HAVERQ!$A:$A,'Chart Data'!$BG4,HAVERQ!G:G)) -> 41.888487 | BI4: =100*('Data Q to A'!AK16/'Data Q to A'!AL16) -> 31.659426 | BK4: 43922 | BL4: =DataQ!AQ196 -> -0.4742025 | BM4: =DataQ!AR196 -> -1.328421 | BN4: =DataQ!AS196 -> -1.170631 | BO4: =DataQ!AT196 -> -0.3453717 | BR4: =BX4 -> 0.68024119 | BS4: =MEDIAN(BX4:CD4) -> 0.2935571 | BT4: =MIN(BY4:CD4) -> -0.15866324 | BU4: =MAX(BY4:CD4)-BT4 -> 0.99678261 | BX4: =100*((DataQ!AU196/DataQ!AU192)-1) -> 0.68024119 | BY4: =100*((DataQ!AV196/DataQ!AV192)-1) -> 0.40928934 | BZ4: =100*((DataQ!AW196/DataQ!AW192)-1) -> 0.13345898 | CA4: =100*((DataQ!AX196/DataQ!AX192)-1) -> 0.83811937 | CB4: =100*((DataQ!AY196/DataQ!AY192)-1) -> 0.2935571 | CC4: =100*((DataQ!AZ196/DataQ!AZ192)-1) -> -0.15866324 | CD4: =100*((DataQ!BA196/DataQ!BA192)-1) -> 0 | CF4: 1961 | CG4: =OBR_MAR26_C4.6!C31 -> 9.509018 | CH4: =OBR_MAR26_C4.6!D31 -> 3.3715849 | CJ4: Latest | CT4: =[2]TA.9!C26 -> 93.161363 | CU4: =[2]TA.9!D26 -> 94.309904 | CV4: =[2]TA.9!E26 -> 94.814987 | CW4: =[2]TA.9!F26 -> 95.738708 | CX4: =[2]TA.9!G26 -> 96.281069 | CY4: =[2]TA.9!H26 -> 96.065091 | CZ4: =[2]TA.9!I26 -> 95.050964 | DB4: Latest | DL4: =[2]TA.9!C17 -> 5.2058932 | DM4: =[2]TA.9!D17 -> 4.3453219 | DN4: =[2]TA.9!E17 -> 3.6491378 | DO4: =[2]TA.9!F17 -> 2.9437631 | DP4: =[2]TA.9!G17 -> 2.5367168 | DQ4: =[2]TA.9!H17 -> 1.8080768 | DR4: =[2]TA.9!I17 -> 1.625073 | DZ4: 2007 | EA4: =AVERAGE(HAVERQ!J195:J198) -> 92.975 | EC4: 2019 | ED4: =AVERAGE(HAVERQ!J243:J246) -> 96.725 | EF4: 2025 | EG4: =AVERAGE(HAVERQ!J265:J268) -> 99.25
AX5: Government debt | AY5: =AG4 -> 102.3143 | AZ5: =AH4 -> 137.36076 | BA5: =AI4 -> 205.18095 | BB5: =AJ4 -> 59.442747 | BC5: =AK4 -> 124.09208 | BD5: =AL4 -> 149.35996 | BE5: =AM4 -> 107.47438 | BG5: 1982 | BH5: =100*(SUMIF(HAVERQ!$B:$B,'Chart Data'!$BG5,HAVERQ!L:L)/SUMIF(HAVERQ!$A:$A,'Chart Data'!$BG5,HAVERQ!G:G)) -> 40.429295 | BI5: =100*('Data Q to A'!AK17/'Data Q to A'!AL17) -> 32.149926 | BK5: 44013 | BL5: =DataQ!AQ197 -> 0.2480247 | BM5: =DataQ!AR197 -> -1.259258 | BN5: =DataQ!AS197 -> -1.146578 | BO5: =DataQ!AT197 -> -0.205531 | BR5: =BX5 -> 0.61570178 | BS5: =MEDIAN(BX5:CD5) -> 0.31774619 | BT5: =MIN(BY5:CD5) -> -0.47543584 | BU5: =MAX(BY5:CD5)-BT5 -> 1.6986029 | BX5: =100*((DataQ!AU197/DataQ!AU193)-1) -> 0.61570178 | BY5: =100*((DataQ!AV197/DataQ!AV193)-1) -> 1.2231671 | BZ5: =100*((DataQ!AW197/DataQ!AW193)-1) -> 0.033341113 | CA5: =100*((DataQ!AX197/DataQ!AX193)-1) -> -0.033441474 | CB5: =100*((DataQ!AY197/DataQ!AY193)-1) -> 0.3469545 | CC5: =100*((DataQ!AZ197/DataQ!AZ193)-1) -> -0.47543584 | CD5: =100*((DataQ!BA197/DataQ!BA193)-1) -> 0.31774619 | CF5: 1962 | CG5: =OBR_MAR26_C4.6!C32 -> 8.9482247 | CH5: =OBR_MAR26_C4.6!D32 -> 3.1741182 | CJ5: 45931 | CT5: =[3]TA.9!C26 -> 93.621758 | CU5: =[3]TA.9!D26 -> 95.026166 | CV5: =[3]TA.9!E26 -> 95.296185 | CW5: =[3]TA.9!F26 -> 96.346622 | CX5: =[3]TA.9!G26 -> 96.987821 | CY5: =[3]TA.9!H26 -> 96.835817 | CZ5: =[3]TA.9!I26 -> 96.06548 | DB5: 45931 | DL5: =[3]TA.9!C17 -> 5.106433 | DM5: =[3]TA.9!D17 -> 4.5440104 | DN5: =[3]TA.9!E17 -> 3.5417875 | DO5: =[3]TA.9!F17 -> 3.0043702 | DP5: =[3]TA.9!G17 -> 2.5657879 | DQ5: =[3]TA.9!H17 -> 1.9368629 | DR5: =[3]TA.9!I17 -> 1.8510844 | DZ5: y/y | EA5: =100*((EA4/EA3)^(1/27)-1) -> 2.3089022 | EC5: y/y | ED5: =100*((ED4/ED3)^(1/12)-1) -> 0.33005399 | EF5: y/y | EG5: =100*((EG4/EG3)^(4/23)-1) -> 0.44918005
X6: 1 | Y6: 2 | Z6: 3 | AA6: 4 | AB6: 5 | AC6: 6 | AD6: 7 | AG6: 1 | AH6: 2 | AI6: 3 | AJ6: 4 | AK6: 5 | AL6: 6 | AM6: 7 | AP6: 1 | AQ6: 2 | AR6: 3 | AS6: 4 | AT6: 5 | AU6: 6 | AV6: 7 | BG6: 1983 | BH6: =100*(SUMIF(HAVERQ!$B:$B,'Chart Data'!$BG6,HAVERQ!L:L)/SUMIF(HAVERQ!$A:$A,'Chart Data'!$BG6,HAVERQ!G:G)) -> 40.028701 | BI6: =100*('Data Q to A'!AK18/'Data Q to A'!AL18) -> 26.707127 | BK6: 44105 | BL6: =DataQ!AQ198 -> 0.7901152 | BM6: =DataQ!AR198 -> -0.9656042 | BN6: =DataQ!AS198 -> -1.126168 | BO6: =DataQ!AT198 -> -0.06359368 | BR6: =BX6 -> 0.5841379 | BS6: =MEDIAN(BX6:CD6) -> 0.08475497 | BT6: =MIN(BY6:CD6) -> -0.9290342 | BU6: =MAX(BY6:CD6)-BT6 -> 2.1713177 | BX6: =100*((DataQ!AU198/DataQ!AU194)-1) -> 0.5841379 | BY6: =100*((DataQ!AV198/DataQ!AV194)-1) -> 1.2422835 | BZ6: =100*((DataQ!AW198/DataQ!AW194)-1) -> -0.9290342 | CA6: =100*((DataQ!AX198/DataQ!AX194)-1) -> -0.1 | CB6: =100*((DataQ!AY198/DataQ!AY194)-1) -> 0.08475497 | CC6: =100*((DataQ!AZ198/DataQ!AZ194)-1) -> -0.19896935 | CD6: =100*((DataQ!BA198/DataQ!BA194)-1) -> 0.7789924 | CF6: 1963 | CG6: =OBR_MAR26_C4.6!C33 -> 8.9001447 | CH6: =OBR_MAR26_C4.6!D33 -> 3.0818378 | CJ6: 45717 | CS6: =[4]TA.9!C27 -> 95.482908 | CT6: =[4]TA.9!D27 -> 95.860994 | CU6: =[4]TA.9!E27 -> 95.118117 | CV6: =[4]TA.9!F27 -> 95.765323 | CW6: =[4]TA.9!G27 -> 96.138698 | CX6: =[4]TA.9!H27 -> 96.261883 | CY6: =[4]TA.9!I27 -> 96.114047 | DB6: 45717 | DK6: =[4]TA.9!C18 -> 4.7735122 | DL6: =[4]TA.9!D18 -> 4.7741675 | DM6: =[4]TA.9!E18 -> 3.930973 | DN6: =[4]TA.9!F18 -> 3.1329234 | DO6: =[4]TA.9!G18 -> 2.4897772 | DP6: =[4]TA.9!H18 -> 2.3184554 | DQ6: =[4]TA.9!I18 -> 2.1374759 | DZ6: q/q | EA6: =100*((EA4/EA3)^(1/108)-1) -> 0.57229399 | EC6: q/q | ED6: =100*((ED4/ED3)^(1/48)-1) -> 0.082411566 | EF6: q/q | EG6: =100*((EG4/EG3)^(1/23)-1) -> 0.11210635
X7: =HLOOKUP(X$6,$X$2:$AD$4,2,FALSE) -> Canada | Y7: =HLOOKUP(Y$6,$X$2:$AD$4,2,FALSE) -> Japan | Z7: =HLOOKUP(Z$6,$X$2:$AD$4,2,FALSE) -> Germany | AA7: =HLOOKUP(AA$6,$X$2:$AD$4,2,FALSE) -> Italy | AB7: =HLOOKUP(AB$6,$X$2:$AD$4,2,FALSE) -> UK | AC7: =HLOOKUP(AC$6,$X$2:$AD$4,2,FALSE) -> France | AD7: =HLOOKUP(AD$6,$X$2:$AD$4,2,FALSE) -> US | AG7: =HLOOKUP(AG$6,$AF$2:$AM$4,2,FALSE) -> Japan | AH7: =HLOOKUP(AH$6,$AF$2:$AM$4,2,FALSE) -> Italy | AI7: =HLOOKUP(AI$6,$AF$2:$AM$4,2,FALSE) -> US | AJ7: =HLOOKUP(AJ$6,$AF$2:$AM$4,2,FALSE) -> France | AK7: =HLOOKUP(AK$6,$AF$2:$AM$4,2,FALSE) -> Canada | AL7: =HLOOKUP(AL$6,$AF$2:$AM$4,2,FALSE) -> UK | AM7: =HLOOKUP(AM$6,$AF$2:$AM$4,2,FALSE) -> Germany | AP7: =HLOOKUP(AP$6,$AO$2:$AV$4,2,FALSE) -> Italy | AQ7: =HLOOKUP(AQ$6,$AO$2:$AV$4,2,FALSE) -> US | AR7: =HLOOKUP(AR$6,$AO$2:$AV$4,2,FALSE) -> UK | AS7: =HLOOKUP(AS$6,$AO$2:$AV$4,2,FALSE) -> Japan | AT7: =HLOOKUP(AT$6,$AO$2:$AV$4,2,FALSE) -> France | AU7: =HLOOKUP(AU$6,$AO$2:$AV$4,2,FALSE) -> Germany | AV7: =HLOOKUP(AV$6,$AO$2:$AV$4,2,FALSE) -> Canada | AX7: 2030 | AY7: =X13&", "&$AX7 -> UK, 2030 | AZ7: =Y13&", "&$AX7 -> US, 2030 | BA7: =Z13&", "&$AX7 -> Japan, 2030 | BB7: =AA13&", "&$AX7 -> Germany, 2030 | BC7: =AB13&", "&$AX7 -> France, 2030 | BD7: =AC13&", "&$AX7 -> Italy, 2030 | BE7: =AD13&", "&$AX7 -> Canada, 2030 | BG7: 1984 | BH7: =100*(SUMIF(HAVERQ!$B:$B,'Chart Data'!$BG7,HAVERQ!L:L)/SUMIF(HAVERQ!$A:$A,'Chart Data'!$BG7,HAVERQ!G:G)) -> 40.50205 | BI7: =100*('Data Q to A'!AK19/'Data Q to A'!AL19) -> 25.47886 | BK7: 44197 | BL7: =DataQ!AQ199 -> 1.541162 | BM7: =DataQ!AR199 -> -0.4946406 | BN7: =DataQ!AS199 -> -0.8528938 | BO7: =DataQ!AT199 -> -0.0002151728 | BQ7: 2021 | BR7: =BX7 -> 0.64535936 | BS7: =MEDIAN(BX7:CD7) -> 0.74036936 | BT7: =MIN(BY7:CD7) -> -0.53141131 | BU7: =MAX(BY7:CD7)-BT7 -> 2.4341405 | BW7: 2021 | BX7: =100*((DataQ!AU199/DataQ!AU195)-1) -> 0.64535936 | BY7: =100*((DataQ!AV199/DataQ!AV195)-1) -> 1.9027292 | BZ7: =100*((DataQ!AW199/DataQ!AW195)-1) -> -0.53141131 | CA7: =100*((DataQ!AX199/DataQ!AX195)-1) -> 1.5298309 | CB7: =100*((DataQ!AY199/DataQ!AY195)-1) -> 0.74036936 | CC7: =100*((DataQ!AZ199/DataQ!AZ195)-1) -> 0.63592605 | CD7: =100*((DataQ!BA199/DataQ!BA195)-1) -> 1.5795379 | CF7: 1964 | CG7: =OBR_MAR26_C4.6!C34 -> 8.0443828 | CH7: =OBR_MAR26_C4.6!D34 -> 2.8281322 | CJ7: 45597 | CS7: =[5]TA.9!C27 -> 97.810368 | CT7: =[5]TA.9!D27 -> 98.395587 | CU7: =[5]TA.9!E27 -> 96.921744 | CV7: =[5]TA.9!F27 -> 96.966301 | CW7: =[5]TA.9!G27 -> 97.245969 | CX7: =[5]TA.9!H27 -> 97.339932 | CY7: =[5]TA.9!I27 -> 97.147985 | DB7: 9072 | DK7: =[5]TA.9!C18 -> 4.4802137 | DL7: =[5]TA.9!D18 -> 4.5295378 | DM7: =[5]TA.9!E18 -> 3.578844 | DN7: =[5]TA.9!F18 -> 2.8914094 | DO7: =[5]TA.9!G18 -> 2.2785057 | DP7: =[5]TA.9!H18 -> 2.1929134 | DQ7: =[5]TA.9!I18 -> 2.077655 | DT7: 1961
W8: =W4 -> 2025 | X8: =HLOOKUP(X$6,$X$2:$AD$4,3,FALSE) -> -0.76203518 | Y8: =HLOOKUP(Y$6,$X$2:$AD$4,3,FALSE) -> -1.842392 | Z8: =HLOOKUP(Z$6,$X$2:$AD$4,3,FALSE) -> -2.7607817 | AA8: =HLOOKUP(AA$6,$X$2:$AD$4,3,FALSE) -> -3.0729095 | AB8: =HLOOKUP(AB$6,$X$2:$AD$4,3,FALSE) -> -4.9571948 | AC8: =HLOOKUP(AC$6,$X$2:$AD$4,3,FALSE) -> -5.110621 | AD8: =HLOOKUP(AD$6,$X$2:$AD$4,3,FALSE) -> -7.4069828 | AF8: =AF4 -> 2025 | AG8: =HLOOKUP(AG$6,$AF$2:$AM$4,3,FALSE) -> 205.18095 | AH8: =HLOOKUP(AH$6,$AF$2:$AM$4,3,FALSE) -> 149.35996 | AI8: =HLOOKUP(AI$6,$AF$2:$AM$4,3,FALSE) -> 137.36076 | AJ8: =HLOOKUP(AJ$6,$AF$2:$AM$4,3,FALSE) -> 124.09208 | AK8: =HLOOKUP(AK$6,$AF$2:$AM$4,3,FALSE) -> 107.47438 | AL8: =HLOOKUP(AL$6,$AF$2:$AM$4,3,FALSE) -> 102.3143 | AM8: =HLOOKUP(AM$6,$AF$2:$AM$4,3,FALSE) -> 59.442747 | AO8: =AO4 -> 2025 | AP8: =HLOOKUP(AP$6,$AO$2:$AV$4,3,FALSE) -> 124.67013 | AQ8: =HLOOKUP(AQ$6,$AO$2:$AV$4,3,FALSE) -> 101.74622 | AR8: =HLOOKUP(AR$6,$AO$2:$AV$4,3,FALSE) -> 93.846256 | AS8: =HLOOKUP(AS$6,$AO$2:$AV$4,3,FALSE) -> 87.280865 | AT8: =HLOOKUP(AT$6,$AO$2:$AV$4,3,FALSE) -> 76.159851 | AU8: =HLOOKUP(AU$6,$AO$2:$AV$4,3,FALSE) -> 21.998883 | AV8: =HLOOKUP(AV$6,$AO$2:$AV$4,3,FALSE) -> 8.3304342 | AY8: =X13 -> UK | AZ8: =Y13 -> US | BA8: =Z13 -> Japan | BB8: =AA13 -> Germany | BC8: =AB13 -> France | BD8: =AC13 -> Italy | BE8: =AD13 -> Canada | BG8: 1985 | BH8: =100*(SUMIF(HAVERQ!$B:$B,'Chart Data'!$BG8,HAVERQ!L:L)/SUMIF(HAVERQ!$A:$A,'Chart Data'!$BG8,HAVERQ!G:G)) -> 38.740658 | BI8: =100*('Data Q to A'!AK20/'Data Q to A'!AL20) -> 25.767186 | BK8: 44287 | BL8: =DataQ!AQ200 -> 1.185967 | BM8: =DataQ!AR200 -> -0.3768889 | BN8: =DataQ!AS200 -> -1.156042 | BO8: =DataQ!AT200 -> 0.02403095 | BR8: =BX8 -> 2.0270276 | BS8: =MEDIAN(BX8:CD8) -> 2.0270276 | BT8: =MIN(BY8:CD8) -> -0.73287117 | BU8: =MAX(BY8:CD8)-BT8 -> 5.5158141 | BX8: =100*((DataQ!AU200/DataQ!AU196)-1) -> 2.0270276 | BY8: =100*((DataQ!AV200/DataQ!AV196)-1) -> 4.7829429 | BZ8: =100*((DataQ!AW200/DataQ!AW196)-1) -> -0.73287117 | CA8: =100*((DataQ!AX200/DataQ!AX196)-1) -> 2.1941482 | CB8: =100*((DataQ!AY200/DataQ!AY196)-1) -> 1.3826343 | CC8: =100*((DataQ!AZ200/DataQ!AZ196)-1) -> 1.231621 | CD8: =100*((DataQ!BA200/DataQ!BA196)-1) -> 3.2883689 | CF8: 1965 | CG8: =OBR_MAR26_C4.6!C35 -> 7.3234147 | CH8: =OBR_MAR26_C4.6!D35 -> 2.7059483 | CJ8: 45352 | CR8: =[6]TA.9!C27 -> 95.726818 | CS8: =[6]TA.9!D27 -> 97.589333 | CT8: =[6]TA.9!E27 -> 98.777579 | CU8: =[6]TA.9!F27 -> 96.357307 | CV8: =[6]TA.9!G27 -> 95.479822 | CW8: =[6]TA.9!H27 -> 95.061625 | CX8: =[6]TA.9!I27 -> 94.29872 | DB8: 45352 | DJ8: =[6]TA.9!C16 -> 5.040891 | DK8: =[6]TA.9!D16 -> 4.1766481 | DL8: =[6]TA.9!E16 -> 3.1313233 | DM8: =[6]TA.9!F16 -> 2.6949793 | DN8: =[6]TA.9!G16 -> 2.3003184 | DO8: =[6]TA.9!H16 -> 1.6339411 | DP8: =[6]TA.9!I16 -> 1.2294641
AX9: Budget deficit | AY9: =X14 -> -2.3446715 | AZ9: =Y14 -> -7.5133161 | BA9: =Z14 -> -2.8347063 | BB9: =AA14 -> -3.5461105 | BC9: =AB14 -> -4.5319327 | BD9: =AC14 -> -2.5705903 | BE9: =AD14 -> -2.2744649 | BG9: 1986 | BH9: =100*(SUMIF(HAVERQ!$B:$B,'Chart Data'!$BG9,HAVERQ!L:L)/SUMIF(HAVERQ!$A:$A,'Chart Data'!$BG9,HAVERQ!G:G)) -> 37.434227 | BI9: =100*('Data Q to A'!AK21/'Data Q to A'!AL21) -> 25.29025 | BK9: 44378 | BL9: =DataQ!AQ201 -> 0.5780302 | BM9: =DataQ!AR201 -> -0.8651952 | BN9: =DataQ!AS201 -> -1.259767 | BO9: =DataQ!AT201 -> -0.07522835 | BR9: =BX9 -> 2.7539788 | BS9: =MEDIAN(BX9:CD9) -> 2.7539788 | BT9: =MIN(BY9:CD9) -> -0.16666 | BU9: =MAX(BY9:CD9)-BT9 -> 5.4162205 | BX9: =100*((DataQ!AU201/DataQ!AU197)-1) -> 2.7539788 | BY9: =100*((DataQ!AV201/DataQ!AV197)-1) -> 5.2495605 | BZ9: =100*((DataQ!AW201/DataQ!AW197)-1) -> -0.16666 | CA9: =100*((DataQ!AX201/DataQ!AX197)-1) -> 3.8474775 | CB9: =100*((DataQ!AY201/DataQ!AY197)-1) -> 1.7210871 | CC9: =100*((DataQ!AZ201/DataQ!AZ197)-1) -> 2.1894985 | CD9: =100*((DataQ!BA201/DataQ!BA197)-1) -> 3.9961257 | CF9: 1966 | CG9: =OBR_MAR26_C4.6!C36 -> 7.4150429 | CH9: =OBR_MAR26_C4.6!D36 -> 2.7901506 | CJ9: 45231 | CR9: =[7]TA.9!C27 -> 95.789462 | CS9: =[7]TA.9!D27 -> 97.869671 | CT9: =[7]TA.9!E27 -> 98.626745 | CU9: =[7]TA.9!F27 -> 96.281813 | CV9: =[7]TA.9!G27 -> 95.509908 | CW9: =[7]TA.9!H27 -> 95.000759 | CX9: =[7]TA.9!I27 -> 94.105503 | DB9: 45231 | DJ9: =[7]TA.9!C16 -> 5.0256521 | DK9: =[7]TA.9!D16 -> 4.5446593 | DL9: =[7]TA.9!E16 -> 3.0226263 | DM9: =[7]TA.9!F16 -> 2.6614041 | DN9: =[7]TA.9!G16 -> 2.2839522 | DO9: =[7]TA.9!H16 -> 1.5795786 | DP9: =[7]TA.9!I16 -> 1.0877049
AX10: Government debt | AY10: =AG14 -> 100.18769 | AZ10: =AH14 -> 145.37042 | BA10: =AI14 -> 202.07445 | BB10: =AJ14 -> 64.967518 | BC10: =AK14 -> 128.1406 | BD10: =AL14 -> 149.40588 | BE10: =AM14 -> 103.37566 | BG10: 1987 | BH10: =100*(SUMIF(HAVERQ!$B:$B,'Chart Data'!$BG10,HAVERQ!L:L)/SUMIF(HAVERQ!$A:$A,'Chart Data'!$BG10,HAVERQ!G:G)) -> 33.857321 | BI10: =100*('Data Q to A'!AK22/'Data Q to A'!AL22) -> 21.118881 | BK10: 44470 | BL10: =DataQ!AQ202 -> 0.4362244 | BM10: =DataQ!AR202 -> -0.9455727 | BN10: =DataQ!AS202 -> -1.106633 | BO10: =DataQ!AT202 -> -0.1353906 | BR10: =BX10 -> 4.8899435 | BS10: =MEDIAN(BX10:CD10) -> 4.7047047 | BT10: =MIN(BY10:CD10) -> 0.50231415 | BU10: =MAX(BY10:CD10)-BT10 -> 6.2690999 | BX10: =100*((DataQ!AU202/DataQ!AU198)-1) -> 4.8899435 | BY10: =100*((DataQ!AV202/DataQ!AV198)-1) -> 6.771414 | BZ10: =100*((DataQ!AW202/DataQ!AW198)-1) -> 0.50231415 | CA10: =100*((DataQ!AX202/DataQ!AX198)-1) -> 4.7047047 | CB10: =100*((DataQ!AY202/DataQ!AY198)-1) -> 2.7176804 | CC10: =100*((DataQ!AZ202/DataQ!AZ198)-1) -> 3.5087679 | CD10: =100*((DataQ!BA202/DataQ!BA198)-1) -> 4.7342754 | CF10: 1967 | CG10: =OBR_MAR26_C4.6!C37 -> 7.3668372 | CH10: =OBR_MAR26_C4.6!D37 -> 2.8786453 | CJ10: 44986 | CQ10: =[8]TA.9!C27 -> 96.901805 | CR10: =[8]TA.9!D27 -> 100.61452 | CS10: =[8]TA.9!E27 -> 103.07297 | CT10: =[8]TA.9!F27 -> 102.41794 | CU10: =[8]TA.9!G27 -> 99.099826 | CV10: =[8]TA.9!H27 -> 97.602946 | CW10: =[8]TA.9!I27 -> 96.932318 | DB10: 44986 | DI10: =[8]TA.9!C16 -> 5.2345344 | DJ10: =[8]TA.9!D16 -> 6.0841634 | DK10: =[8]TA.9!E16 -> 5.1128597 | DL10: =[8]TA.9!F16 -> 3.1999641 | DM10: =[8]TA.9!G16 -> 2.7791586 | DN10: =[8]TA.9!H16 -> 2.2269114 | DO10: =[8]TA.9!I16 -> 1.6698882
W11: Budget deficit in 2030 | AF11: Gross government debt in 2030 | AO11: Government net debt in 2030 | BG11: 1988 | BH11: =100*(SUMIF(HAVERQ!$B:$B,'Chart Data'!$BG11,HAVERQ!L:L)/SUMIF(HAVERQ!$A:$A,'Chart Data'!$BG11,HAVERQ!G:G)) -> 28.259914 | BI11: =100*('Data Q to A'!AK23/'Data Q to A'!AL23) -> 16.615076 | BK11: 44562 | BL11: =DataQ!AQ203 -> -0.005793571 | BM11: =DataQ!AR203 -> -1.035532 | BN11: =DataQ!AS203 -> -0.9248759 | BO11: =DataQ!AT203 -> -0.1517915 | BQ11: 2022 | BR11: =BX11 -> 6.1984103 | BS11: =MEDIAN(BX11:CD11) -> 5.6477014 | BT11: =MIN(BY11:CD11) -> 0.86810679 | BU11: =MAX(BY11:CD11)-BT11 -> 7.1561654 | BW11: 2022 | BX11: =100*((DataQ!AU203/DataQ!AU199)-1) -> 6.1984103 | BY11: =100*((DataQ!AV203/DataQ!AV199)-1) -> 8.0242722 | BZ11: =100*((DataQ!AW203/DataQ!AW199)-1) -> 0.86810679 | CA11: =100*((DataQ!AX203/DataQ!AX199)-1) -> 4.7821144 | CB11: =100*((DataQ!AY203/DataQ!AY199)-1) -> 3.6593222 | CC11: =100*((DataQ!AZ203/DataQ!AZ199)-1) -> 5.6477014 | CD11: =100*((DataQ!BA203/DataQ!BA199)-1) -> 5.8612693 | CF11: 1968 | CG11: =OBR_MAR26_C4.6!C38 -> 6.8228266 | CH11: =OBR_MAR26_C4.6!D38 -> 2.7833002 | CJ11: 44866 | CQ11: =[9]TA.5!C27 -> 97.423344 | CR11: =[9]TA.5!D27 -> 101.86249 | CS11: =[9]TA.5!E27 -> 106.70332 | CT11: =[9]TA.5!F27 -> 105.78743 | CU11: =[9]TA.5!G27 -> 101.69865 | CV11: =[9]TA.5!H27 -> 99.985432 | CW11: =[9]TA.5!I27 -> 99.272594 | DB11: 44866 | DI11: =[9]TA.5!C17 -> 5.6891509 | DJ11: =[9]TA.5!D17 -> 7.0896394 | DK11: =[9]TA.5!E17 -> 5.5085268 | DL11: =[9]TA.5!F17 -> 3.2087565 | DM11: =[9]TA.5!G17 -> 2.8347858 | DN11: =[9]TA.5!H17 -> 2.8525034 | DO11: =[9]TA.5!I17 -> 2.3637925 | DT11: 1962
X12: =RANK(X14,$X$14:$AD$14) -> 2 | Y12: =RANK(Y14,$X$14:$AD$14) -> 7 | Z12: =RANK(Z14,$X$14:$AD$14) -> 4 | AA12: =RANK(AA14,$X$14:$AD$14) -> 5 | AB12: =RANK(AB14,$X$14:$AD$14) -> 6 | AC12: =RANK(AC14,$X$14:$AD$14) -> 3 | AD12: =RANK(AD14,$X$14:$AD$14) -> 1 | AG12: =RANK(AG14,$AG$14:$AM$14) -> 6 | AH12: =RANK(AH14,$AG$14:$AM$14) -> 3 | AI12: =RANK(AI14,$AG$14:$AM$14) -> 1 | AJ12: =RANK(AJ14,$AG$14:$AM$14) -> 7 | AK12: =RANK(AK14,$AG$14:$AM$14) -> 4 | AL12: =RANK(AL14,$AG$14:$AM$14) -> 2 | AM12: =RANK(AM14,$AG$14:$AM$14) -> 5 | AP12: =RANK(AP14,$AP$14:$AV$14) -> 3 | AQ12: =RANK(AQ14,$AP$14:$AV$14) -> 2 | AR12: =RANK(AR14,$AP$14:$AV$14) -> 4 | AS12: =RANK(AS14,$AP$14:$AV$14) -> 6 | AT12: =RANK(AT14,$AP$14:$AV$14) -> 5 | AU12: =RANK(AU14,$AP$14:$AV$14) -> 1 | AV12: =RANK(AV14,$AP$14:$AV$14) -> 7 | AX12: 2026 | AY12: =X19&", "&$AX12 -> UK, 2026 | AZ12: =Y19&", "&$AX12 -> US, 2026 | BA12: =Z19&", "&$AX12 -> Japan, 2026 | BB12: =AA19&", "&$AX12 -> Germany, 2026 | BC12: =AB19&", "&$AX12 -> France, 2026 | BD12: =AC19&", "&$AX12 -> Italy, 2026 | BE12: =AD19&", "&$AX12 -> Canada, 2026 | BG12: 1989 | BH12: =100*(SUMIF(HAVERQ!$B:$B,'Chart Data'!$BG12,HAVERQ!L:L)/SUMIF(HAVERQ!$A:$A,'Chart Data'!$BG12,HAVERQ!G:G)) -> 24.82894 | BI12: =100*('Data Q to A'!AK24/'Data Q to A'!AL24) -> 15.033128 | BK12: 44652 | BL12: =DataQ!AQ204 -> -1.116444 | BM12: =DataQ!AR204 -> -0.9544389 | BN12: =DataQ!AS204 -> -0.7541516 | BO12: =DataQ!AT204 -> -0.3281502 | BR12: =BX12 -> 9.1511767 | BS12: =MEDIAN(BX12:CD12) -> 6.9466369 | BT12: =MIN(BY12:CD12) -> 2.3825435 | BU12: =MAX(BY12:CD12)-BT12 -> 6.2024404 | BX12: =100*((DataQ!AU204/DataQ!AU200)-1) -> 9.1511767 | BY12: =100*((DataQ!AV204/DataQ!AV200)-1) -> 8.5849839 | BZ12: =100*((DataQ!AW204/DataQ!AW200)-1) -> 2.3825435 | CA12: =100*((DataQ!AX204/DataQ!AX200)-1) -> 6.6363023 | CB12: =100*((DataQ!AY204/DataQ!AY200)-1) -> 5.291745 | CC12: =100*((DataQ!AZ204/DataQ!AZ200)-1) -> 6.9466369 | CD12: =100*((DataQ!BA204/DataQ!BA200)-1) -> 7.5552388 | CF12: 1969 | CG12: =OBR_MAR26_C4.6!C39 -> 6.1751022 | CH12: =OBR_MAR26_C4.6!D39 -> 2.5837659 | CJ12: 44621 | CO12: ='[10]T3.38'!C16 -> 82.729735 | CP12: ='[10]T3.38'!D16 -> 93.977911 | CQ12: ='[10]T3.38'!E16 -> 95.551157 | CR12: ='[10]T3.38'!F16 -> 95.471541 | CS12: ='[10]T3.38'!G16 -> 94.08063 | CT12: ='[10]T3.38'!H16 -> 91.237255 | CU12: ='[10]T3.38'!I16 -> 85.813581 | CV12: ='[10]T3.38'!J16 -> 83.121441 | DB12: 44621 | DG12: ='[10]T3.38'!C21 -> 2.435919 | DH12: ='[10]T3.38'!D21 -> 15.029808 | DI12: ='[10]T3.38'!E21 -> 5.4064361 | DJ12: ='[10]T3.38'!F21 -> 3.9448448 | DK12: ='[10]T3.38'!G21 -> 1.9147022 | DL12: ='[10]T3.38'!H21 -> 1.3397308 | DM12: ='[10]T3.38'!I21 -> 1.2323035 | DN12: ='[10]T3.38'!J21 -> 1.0763712
X13: UK | Y13: US | Z13: Japan | AA13: Germany | AB13: France | AC13: Italy | AD13: Canada | AG13: UK | AH13: US | AI13: Japan | AJ13: Germany | AK13: France | AL13: Italy | AM13: Canada | AP13: UK | AQ13: US | AR13: Japan | AS13: Germany | AT13: France | AU13: Italy | AV13: Canada | AY13: =X18 -> 5 | AZ13: =Y18 -> 7 | BA13: =Z18 -> 2 | BB13: =AA18 -> 4 | BC13: =AB18 -> 6 | BD13: =AC18 -> 3 | BE13: =AD18 -> 1 | BG13: 1990 | BH13: =100*(SUMIF(HAVERQ!$B:$B,'Chart Data'!$BG13,HAVERQ!L:L)/SUMIF(HAVERQ!$A:$A,'Chart Data'!$BG13,HAVERQ!G:G)) -> 23.116243 | BI13: =100*('Data Q to A'!AK25/'Data Q to A'!AL25) -> 14.488901 | BK13: 44743 | BL13: =DataQ!AQ205 -> -2.262011 | BM13: =DataQ!AR205 -> -2.050474 | BN13: =DataQ!AS205 -> -1.08056 | BO13: =DataQ!AT205 -> -0.6069162 | BR13: =BX13 -> 10.005959 | BS13: =MEDIAN(BX13:CD13) -> 7.3775427 | BT13: =MIN(BY13:CD13) -> 2.8714456 | BU13: =MAX(BY13:CD13)-BT13 -> 5.504082 | BX13: =100*((DataQ!AU205/DataQ!AU201)-1) -> 10.005959 | BY13: =100*((DataQ!AV205/DataQ!AV201)-1) -> 8.2920958 | BZ13: =100*((DataQ!AW205/DataQ!AW201)-1) -> 2.8714456 | CA13: =100*((DataQ!AX205/DataQ!AX201)-1) -> 7.3775427 | CB13: =100*((DataQ!AY205/DataQ!AY201)-1) -> 5.850136 | CC13: =100*((DataQ!AZ205/DataQ!AZ201)-1) -> 8.3755275 | CD13: =100*((DataQ!BA205/DataQ!BA201)-1) -> 7.0993423 | CF13: 1970 | CG13: =OBR_MAR26_C4.6!C40 -> 5.8139032 | CH13: =OBR_MAR26_C4.6!D40 -> 2.3277161 | CJ13: 44470 | CO13: ='[11]T3.38'!C16 -> 84.150466 | CP13: ='[11]T3.38'!D16 -> 96.605899 | CQ13: ='[11]T3.38'!E16 -> 98.202523 | CR13: ='[11]T3.38'!F16 -> 97.898319 | CS13: ='[11]T3.38'!G16 -> 97.805409 | CT13: ='[11]T3.38'!H16 -> 94.671932 | CU13: ='[11]T3.38'!I16 -> 90.546261 | CV13: ='[11]T3.38'!J16 -> 87.956174 | DB13: 44470 | DG13: ='[11]T3.38'!C21 -> 2.5581097 | DH13: ='[11]T3.38'!D21 -> 15.244423 | DI13: ='[11]T3.38'!E21 -> 7.8965664 | DJ13: ='[11]T3.38'!F21 -> 3.3460556 | DK13: ='[11]T3.38'!G21 -> 2.3888791 | DL13: ='[11]T3.38'!H21 -> 1.7392579 | DM13: ='[11]T3.38'!I21 -> 1.6794935 | DN13: ='[11]T3.38'!J21 -> 1.5336108
W14: 2030 | X14: =100*('Data Q to A'!I65/'Data Q to A'!AD65) -> -2.3446715 | Y14: =100*('Data Q to A'!J65/'Data Q to A'!AE65) -> -7.5133161 | Z14: =100*('Data Q to A'!K65/'Data Q to A'!AF65) -> -2.8347063 | AA14: =100*('Data Q to A'!L65/'Data Q to A'!AG65) -> -3.5461105 | AB14: =100*('Data Q to A'!M65/'Data Q to A'!AH65) -> -4.5319327 | AC14: =100*('Data Q to A'!N65/'Data Q to A'!AI65) -> -2.5705903 | AD14: =100*('Data Q to A'!O65/'Data Q to A'!AJ65) -> -2.2744649 | AF14: 2030 | AG14: =100*('Data Q to A'!P65/'Data Q to A'!AD65) -> 100.18769 | AH14: =100*('Data Q to A'!Q65/'Data Q to A'!AE65) -> 145.37042 | AI14: =100*('Data Q to A'!R65/'Data Q to A'!AF65) -> 202.07445 | AJ14: =100*('Data Q to A'!S65/'Data Q to A'!AG65) -> 64.967518 | AK14: =100*('Data Q to A'!T65/'Data Q to A'!AH65) -> 128.1406 | AL14: =100*('Data Q to A'!U65/'Data Q to A'!AI65) -> 149.40588 | AM14: =100*('Data Q to A'!V65/'Data Q to A'!AJ65) -> 103.37566 | AO14: 2030 | AP14: =100*('Data Q to A'!W65/'Data Q to A'!AD65) -> 99.453613 | AQ14: =100*('Data Q to A'!X65/'Data Q to A'!AE65) -> 116.26922 | AR14: =100*('Data Q to A'!Y65/'Data Q to A'!AF65) -> 94.821064 | AS14: =100*('Data Q to A'!Z65/'Data Q to A'!AG65) -> 34.379022 | AT14: =100*('Data Q to A'!AA65/'Data Q to A'!AH65) -> 87.433644 | AU14: =100*('Data Q to A'!AB65/'Data Q to A'!AI65) -> 124.35997 | AV14: =100*('Data Q to A'!AC65/'Data Q to A'!AJ65) -> 20.926859 | AX14: Budget deficit | AY14: =X20 -> -4.0001734 | AZ14: =Y20 -> -8.5558702 | BA14: =Z20 -> -2.8506069 | BB14: =AA20 -> -3.2175664 | BC14: =AB20 -> -5.1308615 | BD14: =AC20 -> -2.8984413 | BE14: =AD20 -> -2.6887195 | BG14: 1991 | BH14: =100*(SUMIF(HAVERQ!$B:$B,'Chart Data'!$BG14,HAVERQ!L:L)/SUMIF(HAVERQ!$A:$A,'Chart Data'!$BG14,HAVERQ!G:G)) -> 24.039081 | BI14: =100*('Data Q to A'!AK26/'Data Q to A'!AL26) -> 18.162022 | BK14: 44835 | BL14: =DataQ!AQ206 -> -2.748286 | BM14: =DataQ!AR206 -> -2.42089 | BN14: =DataQ!AS206 -> -1.370171 | BO14: =DataQ!AT206 -> -0.8705126 | BR14: =BX14 -> 10.751748 | BS14: =MEDIAN(BX14:CD14) -> 7.0919783 | BT14: =MIN(BY14:CD14) -> 3.8654128 | BU14: =MAX(BY14:CD14)-BT14 -> 7.9219528 | BX14: =100*((DataQ!AU206/DataQ!AU202)-1) -> 10.751748 | BY14: =100*((DataQ!AV206/DataQ!AV202)-1) -> 7.0919783 | BZ14: =100*((DataQ!AW206/DataQ!AW202)-1) -> 3.8654128 | CA14: =100*((DataQ!AX206/DataQ!AX202)-1) -> 8.6042065 | CB14: =100*((DataQ!AY206/DataQ!AY202)-1) -> 6.0635666 | CC14: =100*((DataQ!AZ206/DataQ!AZ202)-1) -> 11.787366 | CD14: =100*((DataQ!BA206/DataQ!BA202)-1) -> 6.5959886 | CF14: 1971 | CG14: =OBR_MAR26_C4.6!C41 -> 6.2308313 | CH14: =OBR_MAR26_C4.6!D41 -> 2.3904259 | CJ14: 44256 | CO14: ='[12]T3.34'!C16 -> 84.385651 | CP14: ='[12]T3.34'!D16 -> 100.18536 | CQ14: ='[12]T3.34'!E16 -> 107.35822 | CR14: ='[12]T3.34'!F16 -> 108.99736 | CS14: ='[12]T3.34'!G16 -> 109.6843 | CT14: ='[12]T3.34'!H16 -> 106.17704 | CU14: ='[12]T3.34'!I16 -> 103.76446 | DB14: 44256 | DG14: ='[12]T3.34'!C21 -> 2.566323 | DH14: ='[12]T3.34'!D21 -> 16.913985 | DI14: ='[12]T3.34'!E21 -> 10.330701 | DJ14: ='[12]T3.34'!F21 -> 4.5020679 | DK14: ='[12]T3.34'!G21 -> 3.4702553 | DL14: ='[12]T3.34'!H21 -> 2.9172069 | DM14: ='[12]T3.34'!I21 -> 2.7783686
AX15: Government debt | AY15: =AG20 -> 102.90878 | AZ15: =AH20 -> 139.10168 | BA15: =AI20 -> 201.40608 | BB15: =AJ20 -> 60.85768 | BC15: =AK20 -> 126.12567 | BD15: =AL20 -> 151.13582 | BE15: =AM20 -> 106.07867 | BG15: 1992 | BH15: =100*(SUMIF(HAVERQ!$B:$B,'Chart Data'!$BG15,HAVERQ!L:L)/SUMIF(HAVERQ!$A:$A,'Chart Data'!$BG15,HAVERQ!G:G)) -> 28.391576 | BI15: =100*('Data Q to A'!AK27/'Data Q to A'!AL27) -> 26.942452 | BK15: 44927 | BL15: =DataQ!AQ207 -> -4.198305 | BM15: =DataQ!AR207 -> -3.155869 | BN15: =DataQ!AS207 -> -2.290555 | BO15: =DataQ!AT207 -> -0.8742595 | BQ15: 2023 | BR15: =BX15 -> 10.178266 | BS15: =MEDIAN(BX15:CD15) -> 5.9931317 | BT15: =MIN(BY15:CD15) -> 3.6412115 | BU15: =MAX(BY15:CD15)-BT15 -> 5.2559929 | BW15: 2023 | BX15: =100*((DataQ!AU207/DataQ!AU203)-1) -> 10.178266 | BY15: =100*((DataQ!AV207/DataQ!AV203)-1) -> 5.7298257 | BZ15: =100*((DataQ!AW207/DataQ!AW203)-1) -> 3.6412115 | CA15: =100*((DataQ!AX207/DataQ!AX203)-1) -> 8.221353 | CB15: =100*((DataQ!AY207/DataQ!AY203)-1) -> 5.9931317 | CC15: =100*((DataQ!AZ207/DataQ!AZ203)-1) -> 8.8972044 | CD15: =100*((DataQ!BA207/DataQ!BA203)-1) -> 5.1525424 | CF15: 1972 | CG15: =OBR_MAR26_C4.6!C42 -> 6.5073141 | CH15: =OBR_MAR26_C4.6!D42 -> 2.334262 | CJ15: 44136 | CO15: ='[13]T3.30'!C16 -> 85.454671 | CP15: ='[13]T3.30'!D16 -> 105.19319 | CQ15: ='[13]T3.30'!E16 -> 108.03806 | CR15: ='[13]T3.30'!F16 -> 108.57979 | CS15: ='[13]T3.30'!G16 -> 109.41773 | CT15: ='[13]T3.30'!H16 -> 104.97 | CU15: ='[13]T3.30'!I16 -> 104.74934 | DB15: 44136 | DG15: ='[13]T3.30'!C21 -> 2.5274085 | DH15: ='[13]T3.30'!D21 -> 19.016635 | DI15: ='[13]T3.30'!E21 -> 7.400033 | DJ15: ='[13]T3.30'!F21 -> 4.4492529 | DK15: ='[13]T3.30'!G21 -> 4.1130923 | DL15: ='[13]T3.30'!H21 -> 3.9269697 | DM15: ='[13]T3.30'!I21 -> 3.8616613 | DT15: 1963
BG16: 1993 | BH16: =100*(SUMIF(HAVERQ!$B:$B,'Chart Data'!$BG16,HAVERQ!L:L)/SUMIF(HAVERQ!$A:$A,'Chart Data'!$BG16,HAVERQ!G:G)) -> 33.091702 | BI16: =100*('Data Q to A'!AK28/'Data Q to A'!AL28) -> 31.477766 | BK16: 45017 | BL16: =DataQ!AQ208 -> -3.759159 | BM16: =DataQ!AR208 -> -3.433098 | BN16: =DataQ!AS208 -> -2.461839 | BO16: =DataQ!AT208 -> -1.02899 | BR16: =BX16 -> 8.439049 | BS16: =MEDIAN(BX16:CD16) -> 5.1773244 | BT16: =MIN(BY16:CD16) -> 3.3759095 | BU16: =MAX(BY16:CD16)-BT16 -> 3.9635321 | BX16: =100*((DataQ!AU208/DataQ!AU204)-1) -> 8.439049 | BY16: =100*((DataQ!AV208/DataQ!AV204)-1) -> 4.0439594 | BZ16: =100*((DataQ!AW208/DataQ!AW204)-1) -> 3.3759095 | CA16: =100*((DataQ!AX208/DataQ!AX204)-1) -> 6.5588144 | CB16: =100*((DataQ!AY208/DataQ!AY204)-1) -> 5.1773244 | CC16: =100*((DataQ!AZ208/DataQ!AZ204)-1) -> 7.3394417 | CD16: =100*((DataQ!BA208/DataQ!BA204)-1) -> 3.5785288 | CF16: 1973 | CG16: =OBR_MAR26_C4.6!C43 -> 6.7291653 | CH16: =OBR_MAR26_C4.6!D43 -> 2.4339033 | CJ16: 43891 | CN16: ='[14]T3.40'!C16 -> 80.646995 | CO16: ='[14]T3.40'!D16 -> 79.493871 | CP16: ='[14]T3.40'!E16 -> 77.435816 | CQ16: ='[14]T3.40'!F16 -> 74.993508 | CR16: ='[14]T3.40'!G16 -> 75.409295 | CS16: ='[14]T3.40'!H16 -> 75.55736 | CT16: ='[14]T3.40'!I16 -> 75.225038 | DB16: 43891 | DF16: ='[14]T3.40'!C21 -> 1.7721895 | DG16: ='[14]T3.40'!D21 -> 2.1289957 | DH16: ='[14]T3.40'!E21 -> 2.3773683 | DI16: ='[14]T3.40'!F21 -> 2.7843366 | DJ16: ='[14]T3.40'!G21 -> 2.481179 | DK16: ='[14]T3.40'!H21 -> 2.3514082 | DL16: ='[14]T3.40'!I21 -> 2.1823592
W17: Budget deficit in 2026 | AF17: Gross government debt in 2026 | AO17: Government net debt in 2026 | BG17: 1994 | BH17: =100*(SUMIF(HAVERQ!$B:$B,'Chart Data'!$BG17,HAVERQ!L:L)/SUMIF(HAVERQ!$A:$A,'Chart Data'!$BG17,HAVERQ!G:G)) -> 36.609602 | BI17: =100*('Data Q to A'!AK29/'Data Q to A'!AL29) -> 34.831446 | BK17: 45108 | BL17: =DataQ!AQ209 -> -3.51581 | BM17: =DataQ!AR209 -> -2.936102 | BN17: =DataQ!AS209 -> -2.727603 | BO17: =DataQ!AT209 -> -0.9281871 | BR17: =BX17 -> 6.7136185 | BS17: =MEDIAN(BX17:CD17) -> 4.6812076 | BT17: =MIN(BY17:CD17) -> 3.148296 | BU17: =MAX(BY17:CD17)-BT17 -> 2.432262 | BX17: =100*((DataQ!AU209/DataQ!AU205)-1) -> 6.7136185 | BY17: =100*((DataQ!AV209/DataQ!AV205)-1) -> 3.5660494 | BZ17: =100*((DataQ!AW209/DataQ!AW205)-1) -> 3.148296 | CA17: =100*((DataQ!AX209/DataQ!AX205)-1) -> 5.5805581 | CB17: =100*((DataQ!AY209/DataQ!AY205)-1) -> 4.6812076 | CC17: =100*((DataQ!AZ209/DataQ!AZ205)-1) -> 5.5715351 | CD17: =100*((DataQ!BA209/DataQ!BA205)-1) -> 3.7190541 | CF17: 1974 | CG17: =OBR_MAR26_C4.6!C44 -> 6.1927264 | CH17: =OBR_MAR26_C4.6!D44 -> 2.4156754 | CJ17: 43525 | CM17: ='[15]T4.37'!C16 -> 84.704401 | CN17: ='[15]T4.37'!D16 -> 83.31282 | CO17: ='[15]T4.37'!E16 -> 82.228042 | CP17: ='[15]T4.37'!F16 -> 78.981682 | CQ17: ='[15]T4.37'!G16 -> 74.925844 | CR17: ='[15]T4.37'!H16 -> 74.026199 | CS17: ='[15]T4.37'!I16 -> 72.980694 | DB17: 43525 | DE17: ='[15]T4.37'!C18 -> 2.0274272 | DF17: ='[15]T4.37'!D18 -> 1.0711559 | DG17: ='[15]T4.37'!E18 -> 1.3335606 | DH17: ='[15]T4.37'!F18 -> 0.93003908 | DI17: ='[15]T4.37'!G18 -> 0.74865478 | DJ17: ='[15]T4.37'!H18 -> 0.59081155 | DK17: ='[15]T4.37'!I18 -> 0.532105
X18: =RANK(X20,$X$20:$AD$20) -> 5 | Y18: =RANK(Y20,$X$20:$AD$20) -> 7 | Z18: =RANK(Z20,$X$20:$AD$20) -> 2 | AA18: =RANK(AA20,$X$20:$AD$20) -> 4 | AB18: =RANK(AB20,$X$20:$AD$20) -> 6 | AC18: =RANK(AC20,$X$20:$AD$20) -> 3 | AD18: =RANK(AD20,$X$20:$AD$20) -> 1 | AG18: =RANK(AG20,$AG$20:$AM$20) -> 6 | AH18: =RANK(AH20,$AG$20:$AM$20) -> 3 | AI18: =RANK(AI20,$AG$20:$AM$20) -> 1 | AJ18: =RANK(AJ20,$AG$20:$AM$20) -> 7 | AK18: =RANK(AK20,$AG$20:$AM$20) -> 4 | AL18: =RANK(AL20,$AG$20:$AM$20) -> 2 | AM18: =RANK(AM20,$AG$20:$AM$20) -> 5 | AP18: =RANK(AP20,$AP$20:$AV$20) -> 3 | AQ18: =RANK(AQ20,$AP$20:$AV$20) -> 2 | AR18: =RANK(AR20,$AP$20:$AV$20) -> 4 | AS18: =RANK(AS20,$AP$20:$AV$20) -> 6 | AT18: =RANK(AT20,$AP$20:$AV$20) -> 5 | AU18: =RANK(AU20,$AP$20:$AV$20) -> 1 | AV18: =RANK(AV20,$AP$20:$AV$20) -> 7 | BG18: 1995 | BH18: =100*(SUMIF(HAVERQ!$B:$B,'Chart Data'!$BG18,HAVERQ!L:L)/SUMIF(HAVERQ!$A:$A,'Chart Data'!$BG18,HAVERQ!G:G)) -> 38.837507 | BI18: =100*('Data Q to A'!AK30/'Data Q to A'!AL30) -> 36.45979 | BK18: 45200 | BL18: =DataQ!AQ210 -> -3.460574 | BM18: =DataQ!AR210 -> -2.457488 | BN18: =DataQ!AS210 -> -2.915811 | BO18: =DataQ!AT210 -> -0.7505955 | BR18: =BX18 -> 4.1568272 | BS18: =MEDIAN(BX18:CD18) -> 3.2334846 | BT18: =MIN(BY18:CD18) -> 0.9993143 | BU18: =MAX(BY18:CD18)-BT18 -> 2.7212708 | BX18: =100*((DataQ!AU210/DataQ!AU206)-1) -> 4.1568272 | BY18: =100*((DataQ!AV210/DataQ!AV206)-1) -> 3.2334846 | BZ18: =100*((DataQ!AW210/DataQ!AW206)-1) -> 2.9194418 | CA18: =100*((DataQ!AX210/DataQ!AX206)-1) -> 3.5211268 | CB18: =100*((DataQ!AY210/DataQ!AY206)-1) -> 3.7205851 | CC18: =100*((DataQ!AZ210/DataQ!AZ206)-1) -> 0.9993143 | CD18: =100*((DataQ!BA210/DataQ!BA206)-1) -> 3.1804407 | CF18: 1975 | CG18: =OBR_MAR26_C4.6!C45 -> 6.4126892 | CH18: =OBR_MAR26_C4.6!D45 -> 2.5727384 | CJ18: 43374 | CM18: ='[16]T4.45'!C16 -> 85.047161 | CN18: ='[16]T4.45'!D16 -> 83.675146 | CO18: ='[16]T4.45'!E16 -> 82.841229 | CP18: ='[16]T4.45'!F16 -> 79.670328 | CQ18: ='[16]T4.45'!G16 -> 75.687396 | CR18: ='[16]T4.45'!H16 -> 75.038262 | CS18: ='[16]T4.45'!I16 -> 74.050274 | DB18: 43374 | DE18: ='[16]T4.45'!C18 -> 1.9320546 | DF18: ='[16]T4.45'!D18 -> 1.1983087 | DG18: ='[16]T4.45'!E18 -> 1.4446749 | DH18: ='[16]T4.45'!F18 -> 1.1727942 | DI18: ='[16]T4.45'!G18 -> 1.0133467 | DJ18: ='[16]T4.45'!H18 -> 0.85562922 | DK18: ='[16]T4.45'!I18 -> 0.784627
X19: UK | Y19: US | Z19: Japan | AA19: Germany | AB19: France | AC19: Italy | AD19: Canada | AG19: UK | AH19: US | AI19: Japan | AJ19: Germany | AK19: France | AL19: Italy | AM19: Canada | AP19: UK | AQ19: US | AR19: Japan | AS19: Germany | AT19: France | AU19: Italy | AV19: Canada | BG19: 1996 | BH19: =100*(SUMIF(HAVERQ!$B:$B,'Chart Data'!$BG19,HAVERQ!L:L)/SUMIF(HAVERQ!$A:$A,'Chart Data'!$BG19,HAVERQ!G:G)) -> 40.021935 | BI19: =100*('Data Q to A'!AK31/'Data Q to A'!AL31) -> 37.120438 | BK19: 45292 | BL19: =DataQ!AQ211 -> -3.233632 | BM19: =DataQ!AR211 -> -2.455854 | BN19: =DataQ!AS211 -> -2.96869 | BO19: =DataQ!AT211 -> -0.8963838 | BQ19: 2024 | BR19: =BX19 -> 3.5491137 | BS19: =MEDIAN(BX19:CD19) -> 2.7905518 | BT19: =MIN(BY19:CD19) -> 0.92687951 | BU19: =MAX(BY19:CD19)-BT19 -> 2.317482 | BW19: 2024 | BX19: =100*((DataQ!AU211/DataQ!AU207)-1) -> 3.5491137 | BY19: =100*((DataQ!AV211/DataQ!AV207)-1) -> 3.2443615 | BZ19: =100*((DataQ!AW211/DataQ!AW207)-1) -> 2.5231228 | CA19: =100*((DataQ!AX211/DataQ!AX207)-1) -> 2.5418544 | CB19: =100*((DataQ!AY211/DataQ!AY207)-1) -> 2.7905518 | CC19: =100*((DataQ!AZ211/DataQ!AZ207)-1) -> 0.92687951 | CD19: =100*((DataQ!BA211/DataQ!BA207)-1) -> 2.8583495 | CF19: 1976 | CG19: =OBR_MAR26_C4.6!C46 -> 7.1401064 | CH19: =OBR_MAR26_C4.6!D46 -> 2.8710795 | CJ19: 43160 | CL19: ='[17]T4.40'!C16 -> 85.301455 | CM19: ='[17]T4.40'!D16 -> 85.567583 | CN19: ='[17]T4.40'!E16 -> 85.519318 | CO19: ='[17]T4.40'!F16 -> 85.107509 | CP19: ='[17]T4.40'!G16 -> 82.100865 | CQ19: ='[17]T4.40'!H16 -> 78.325555 | CR19: ='[17]T4.40'!I16 -> 77.941182 | DB19: 43160 | DD19: ='[17]T4.40'!C18 -> 2.3028187 | DE19: ='[17]T4.40'!D18 -> 2.198356 | DF19: ='[17]T4.40'!E18 -> 1.7511384 | DG19: ='[17]T4.40'!F18 -> 1.5574026 | DH19: ='[17]T4.40'!G18 -> 1.2820424 | DI19: ='[17]T4.40'!H18 -> 1.1242667 | DJ19: ='[17]T4.40'!I18 -> 0.89528229 | DT19: 1964
W20: 2026 | X20: =100*('Data Q to A'!I61/'Data Q to A'!AD61) -> -4.0001734 | Y20: =100*('Data Q to A'!J61/'Data Q to A'!AE61) -> -8.5558702 | Z20: =100*('Data Q to A'!K61/'Data Q to A'!AF61) -> -2.8506069 | AA20: =100*('Data Q to A'!L61/'Data Q to A'!AG61) -> -3.2175664 | AB20: =100*('Data Q to A'!M61/'Data Q to A'!AH61) -> -5.1308615 | AC20: =100*('Data Q to A'!N61/'Data Q to A'!AI61) -> -2.8984413 | AD20: =100*('Data Q to A'!O61/'Data Q to A'!AJ61) -> -2.6887195 | AF20: 2026 | AG20: =100*('Data Q to A'!P61/'Data Q to A'!AD61) -> 102.90878 | AH20: =100*('Data Q to A'!Q61/'Data Q to A'!AE61) -> 139.10168 | AI20: =100*('Data Q to A'!R61/'Data Q to A'!AF61) -> 201.40608 | AJ20: =100*('Data Q to A'!S61/'Data Q to A'!AG61) -> 60.85768 | AK20: =100*('Data Q to A'!T61/'Data Q to A'!AH61) -> 126.12567 | AL20: =100*('Data Q to A'!U61/'Data Q to A'!AI61) -> 151.13582 | AM20: =100*('Data Q to A'!V61/'Data Q to A'!AJ61) -> 106.07867 | AO20: 2026 | AP20: =100*('Data Q to A'!W61/'Data Q to A'!AD61) -> 97.203557 | AQ20: =100*('Data Q to A'!X61/'Data Q to A'!AE61) -> 105.08329 | AR20: =100*('Data Q to A'!Y61/'Data Q to A'!AF61) -> 87.313062 | AS20: =100*('Data Q to A'!Z61/'Data Q to A'!AG61) -> 24.549321 | AT20: =100*('Data Q to A'!AA61/'Data Q to A'!AH61) -> 79.389783 | AU20: =100*('Data Q to A'!AB61/'Data Q to A'!AI61) -> 125.03976 | AV20: =100*('Data Q to A'!AC61/'Data Q to A'!AJ61) -> 10.891426 | BG20: 1997 | BH20: =100*(SUMIF(HAVERQ!$C:$C,'Chart Data'!$BG20,HAVERQ!L:L)/SUMIF(HAVERQ!$A:$A,'Chart Data'!$BG20,HAVERQ!G:G)) -> 40.05669 | BI20: =100*('Data Q to A'!AK32/'Data Q to A'!AL32) -> 36.612845 | BK20: 45383 | BL20: =DataQ!AQ212 -> -2.550798 | BM20: =DataQ!AR212 -> -1.896409 | BN20: =DataQ!AS212 -> -2.469674 | BO20: =DataQ!AT212 -> -0.728087 | BR20: =BX20 -> 2.1108336 | BS20: =MEDIAN(BX20:CD20) -> 2.2330381 | BT20: =MIN(BY20:CD20) -> 0.85470769 | BU20: =MAX(BY20:CD20)-BT20 -> 2.3368129 | BX20: =100*((DataQ!AU212/DataQ!AU208)-1) -> 2.1108336 | BY20: =100*((DataQ!AV212/DataQ!AV208)-1) -> 3.1915206 | BZ20: =100*((DataQ!AW212/DataQ!AW208)-1) -> 2.7267288 | CA20: =100*((DataQ!AX212/DataQ!AX208)-1) -> 2.2330381 | CB20: =100*((DataQ!AY212/DataQ!AY208)-1) -> 2.2056875 | CC20: =100*((DataQ!AZ212/DataQ!AZ208)-1) -> 0.85470769 | CD20: =100*((DataQ!BA212/DataQ!BA208)-1) -> 2.7511196 | CF20: 1977 | CG20: =OBR_MAR26_C4.6!C47 -> 7.6961684 | CH20: =OBR_MAR26_C4.6!D47 -> 2.9544757 | CJ20: 43040 | CL20: ='[18]T4.43'!C16 -> 85.808696 | CM20: ='[18]T4.43'!D16 -> 86.455763 | CN20: ='[18]T4.43'!E16 -> 86.422084 | CO20: ='[18]T4.43'!F16 -> 86.10845 | CP20: ='[18]T4.43'!G16 -> 83.134737 | CQ20: ='[18]T4.43'!H16 -> 79.288509 | CR20: ='[18]T4.43'!I16 -> 79.054443 | DB20: 43040 | DD20: ='[18]T4.43'!C18 -> 2.3056284 | DE20: ='[18]T4.43'!D18 -> 2.4413815 | DF20: ='[18]T4.43'!E18 -> 1.8804656 | DG20: ='[18]T4.43'!F18 -> 1.6100221 | DH20: ='[18]T4.43'!G18 -> 1.4733212 | DI20: ='[18]T4.43'!H18 -> 1.308081 | DJ20: ='[18]T4.43'!I18 -> 1.0759828
BG21: 1998 | BH21: =100*(SUMIF(HAVERQ!$C:$C,'Chart Data'!$BG21,HAVERQ!L:L)/SUMIF(HAVERQ!$A:$A,'Chart Data'!$BG21,HAVERQ!G:G)) -> 38.146737 | BI21: =100*('Data Q to A'!AK33/'Data Q to A'!AL33) -> 35.516352 | BK21: 45474 | BL21: =DataQ!AQ213 -> -2.304361 | BM21: =DataQ!AR213 -> -1.963248 | BN21: =DataQ!AS213 -> -2.171902 | BO21: =DataQ!AT213 -> -0.7111451 | BR21: =BX21 -> 2.0547945 | BS21: =MEDIAN(BX21:CD21) -> 2.0248897 | BT21: =MIN(BY21:CD21) -> 1.0554954 | BU21: =MAX(BY21:CD21)-BT21 -> 1.7136055 | BX21: =100*((DataQ!AU213/DataQ!AU209)-1) -> 2.0547945 | BY21: =100*((DataQ!AV213/DataQ!AV209)-1) -> 2.6576119 | BZ21: =100*((DataQ!AW213/DataQ!AW209)-1) -> 2.7691009 | CA21: =100*((DataQ!AX213/DataQ!AX209)-1) -> 1.9323956 | CB21: =100*((DataQ!AY213/DataQ!AY209)-1) -> 1.7417055 | CC21: =100*((DataQ!AZ213/DataQ!AZ209)-1) -> 1.0554954 | CD21: =100*((DataQ!BA213/DataQ!BA209)-1) -> 2.0248897 | CF21: 1978 | CG21: =OBR_MAR26_C4.6!C48 -> 8.2497464 | CH21: =OBR_MAR26_C4.6!D48 -> 3.0445927 | CJ21: 42795 | CK21: ='[19]T4.41'!C16 -> 83.611666 | CL21: ='[19]T4.41'!D16 -> 86.571027 | CM21: ='[19]T4.41'!E16 -> 88.795212 | CN21: ='[19]T4.41'!F16 -> 88.496851 | CO21: ='[19]T4.41'!G16 -> 86.904105 | CP21: ='[19]T4.41'!H16 -> 82.976574 | CQ21: ='[19]T4.41'!I16 -> 79.795605 | DB21: 42795 | DC21: ='[19]T4.41'!C18 -> 3.7997915 | DD21: ='[19]T4.41'!D18 -> 2.6344292 | DE21: ='[19]T4.41'!E18 -> 2.8715301 | DF21: ='[19]T4.41'!F18 -> 1.9479472 | DG21: ='[19]T4.41'!G18 -> 0.98537529 | DH21: ='[19]T4.41'!H18 -> 0.91480607 | DI21: ='[19]T4.41'!I18 -> 0.71801817
BG22: 1999 | BH22: =100*(SUMIF(HAVERQ!$C:$C,'Chart Data'!$BG22,HAVERQ!L:L)/SUMIF(HAVERQ!$A:$A,'Chart Data'!$BG22,HAVERQ!G:G)) -> 36.94459 | BI22: =100*('Data Q to A'!AK34/'Data Q to A'!AL34) -> 32.730237 | BK22: 45566 | BL22: =DataQ!AQ214 -> -1.380183 | BM22: =DataQ!AR214 -> -1.07173 | BN22: =DataQ!AS214 -> -1.608057 | BO22: =DataQ!AT214 -> -0.5910925 | BR22: =BX22 -> 2.4753214 | BS22: =MEDIAN(BX22:CD22) -> 2.3242347 | BT22: =MIN(BY22:CD22) -> 1.1941351 | BU22: =MAX(BY22:CD22)-BT22 -> 1.7361027 | BX22: =100*((DataQ!AU214/DataQ!AU210)-1) -> 2.4753214 | BY22: =100*((DataQ!AV214/DataQ!AV210)-1) -> 2.7231785 | BZ22: =100*((DataQ!AW214/DataQ!AW210)-1) -> 2.9302378 | CA22: =100*((DataQ!AX214/DataQ!AX210)-1) -> 2.3242347 | CB22: =100*((DataQ!AY214/DataQ!AY210)-1) -> 1.270649 | CC22: =100*((DataQ!AZ214/DataQ!AZ210)-1) -> 1.1941351 | CD22: =100*((DataQ!BA214/DataQ!BA210)-1) -> 1.9081355 | CF22: 1979 | CG22: =OBR_MAR26_C4.6!C49 -> 8.7531871 | CH22: =OBR_MAR26_C4.6!D49 -> 3.262426 | CJ22: 42675 | CK22: ='[20]T4.40'!C16 -> 84.216421 | CL22: ='[20]T4.40'!D16 -> 87.302195 | CM22: ='[20]T4.40'!E16 -> 90.187612 | CN22: ='[20]T4.40'!F16 -> 89.6727 | CO22: ='[20]T4.40'!G16 -> 88.0211 | CP22: ='[20]T4.40'!H16 -> 84.847846 | CQ22: ='[20]T4.40'!I16 -> 81.563679 | DB22: 42675 | DC22: ='[20]T4.40'!C18 -> 4.0387713 | DD22: ='[20]T4.40'!D18 -> 3.4942744 | DE22: ='[20]T4.40'!E18 -> 2.946441 | DF22: ='[20]T4.40'!F18 -> 2.2327888 | DG22: ='[20]T4.40'!G18 -> 1.0126548 | DH22: ='[20]T4.40'!H18 -> 0.92048966 | DI22: ='[20]T4.40'!I18 -> 0.733998 | DU22: =100*((AVERAGE(HAVERQ!J7:J26)/AVERAGE(HAVERQ!J3:J22))-1) -> #N/A
BG23: 2000 | BH23: =100*(SUMIF(HAVERQ!$C:$C,'Chart Data'!$BG23,HAVERQ!L:L)/SUMIF(HAVERQ!$A:$A,'Chart Data'!$BG23,HAVERQ!G:G)) -> 31.639842 | BI23: =100*('Data Q to A'!AK35/'Data Q to A'!AL35) -> 28.560481 | BK23: 45658 | BL23: =DataQ!AQ215 -> -0.552002 | BM23: =DataQ!AR215 -> -0.6183422 | BN23: =DataQ!AS215 -> -0.7403606 | BO23: =DataQ!AT215 -> -0.3766288 | BQ23: 2025 | BR23: =BX23 -> 2.7973783 | BS23: =MEDIAN(BX23:CD23) -> 2.2775182 | BT23: =MIN(BY23:CD23) -> 1.0710117 | BU23: =MAX(BY23:CD23)-BT23 -> 2.6984276 | BW23: 2025 | BX23: =100*((DataQ!AU215/DataQ!AU211)-1) -> 2.7973783 | BY23: =100*((DataQ!AV215/DataQ!AV211)-1) -> 2.7239904 | BZ23: =100*((DataQ!AW215/DataQ!AW211)-1) -> 3.7694393 | CA23: =100*((DataQ!AX215/DataQ!AX211)-1) -> 2.2535499 | CB23: =100*((DataQ!AY215/DataQ!AY211)-1) -> 1.0710117 | CC23: =100*((DataQ!AZ215/DataQ!AZ211)-1) -> 1.6666633 | CD23: =100*((DataQ!BA215/DataQ!BA211)-1) -> 2.2775182 | CF23: 1980 | CG23: =OBR_MAR26_C4.6!C50 -> 8.8974986 | CH23: =OBR_MAR26_C4.6!D50 -> 3.424806 | DT23: 1965 | DU23: =100*((AVERAGE(HAVERQ!J8:J27)/AVERAGE(HAVERQ!J4:J23))-1) -> #N/A
BG24: 2001 | BH24: =100*(SUMIF(HAVERQ!$C:$C,'Chart Data'!$BG24,HAVERQ!L:L)/SUMIF(HAVERQ!$A:$A,'Chart Data'!$BG24,HAVERQ!G:G)) -> 30.427485 | BI24: =100*('Data Q to A'!AK36/'Data Q to A'!AL36) -> 28.25414 | BK24: 45748 | BL24: =DataQ!AQ216 -> -0.2413776 | BM24: =DataQ!AR216 -> -0.6384518 | BN24: =DataQ!AS216 -> -0.2694005 | BO24: =DataQ!AT216 -> -0.3859788 | BR24: =BX24 -> 3.4869498 | BS24: =MEDIAN(BX24:CD24) -> 2.1002526 | BT24: =MIN(BY24:CD24) -> 0.81892597 | BU24: =MAX(BY24:CD24)-BT24 -> 2.5761666 | BX24: =100*((DataQ!AU216/DataQ!AU212)-1) -> 3.4869498 | BY24: =100*((DataQ!AV216/DataQ!AV212)-1) -> 2.4610268 | BZ24: =100*((DataQ!AW216/DataQ!AW212)-1) -> 3.3950926 | CA24: =100*((DataQ!AX216/DataQ!AX212)-1) -> 2.1002526 | CB24: =100*((DataQ!AY216/DataQ!AY212)-1) -> 0.81892597 | CC24: =100*((DataQ!AZ216/DataQ!AZ212)-1) -> 1.6949084 | CD24: =100*((DataQ!BA216/DataQ!BA212)-1) -> 1.8057285 | CF24: 1981 | CG24: =OBR_MAR26_C4.6!C51 -> 9.2124473 | CH24: =OBR_MAR26_C4.6!D51 -> 3.7598037 | DU24: =100*((AVERAGE(HAVERQ!J9:J28)/AVERAGE(HAVERQ!J5:J24))-1) -> #N/A
BG25: 2002 | BH25: =100*(SUMIF(HAVERQ!$C:$C,'Chart Data'!$BG25,HAVERQ!L:L)/SUMIF(HAVERQ!$A:$A,'Chart Data'!$BG25,HAVERQ!G:G)) -> 31.233269 | BI25: =100*('Data Q to A'!AK37/'Data Q to A'!AL37) -> 30.139612 | BK25: 45839 | BL25: =DataQ!AQ217 -> 0.08038092 | BM25: =DataQ!AR217 -> -0.6522727 | BN25: =DataQ!AS217 -> 0.1669607 | BO25: =DataQ!AT217 -> -0.2569222 | BR25: =BX25 -> 3.803132 | BS25: =MEDIAN(BX25:CD25) -> 2.2302196 | BT25: =MIN(BY25:CD25) -> 1.0083417 | BU25: =MAX(BY25:CD25)-BT25 -> 1.893088 | BX25: =100*((DataQ!AU217/DataQ!AU213)-1) -> 3.803132 | BY25: =100*((DataQ!AV217/DataQ!AV213)-1) -> 2.9014297 | BZ25: =100*((DataQ!AW217/DataQ!AW213)-1) -> 2.8781069 | CA25: =100*((DataQ!AX217/DataQ!AX213)-1) -> 2.2302196 | CB25: =100*((DataQ!AY217/DataQ!AY213)-1) -> 1.0083417 | CC25: =100*((DataQ!AZ217/DataQ!AZ213)-1) -> 1.5835614 | CD25: =100*((DataQ!BA217/DataQ!BA213)-1) -> 1.9847017 | CF25: 1982 | CG25: =OBR_MAR26_C4.6!C52 -> 9.0962455 | CH25: =OBR_MAR26_C4.6!D52 -> 3.6860724 | DU25: =100*((AVERAGE(HAVERQ!J10:J29)/AVERAGE(HAVERQ!J6:J25))-1) -> #N/A
BG26: 2003 | BH26: =100*(SUMIF(HAVERQ!$C:$C,'Chart Data'!$BG26,HAVERQ!L:L)/SUMIF(HAVERQ!$A:$A,'Chart Data'!$BG26,HAVERQ!G:G)) -> 32.852304 | BI26: =100*('Data Q to A'!AK38/'Data Q to A'!AL38) -> 31.195293 | BK26: 45931 | BL26: =DataQ!AQ218 -> 0.013731 | BM26: =DataQ!AR218 -> -0.5917101 | BN26: =DataQ!AS218 -> 0.2965423 | BO26: =DataQ!AT218 -> -0.08502853 | BR26: =BX26 -> 3.3769049 | BS26: =MEDIAN(BX26:CD26) -> 2.2427778 | BT26: =MIN(BY26:CD26) -> 0.8779602 | BU26: =MAX(BY26:CD26)-BT26 -> 1.9519981 | BX26: =100*((DataQ!AU218/DataQ!AU214)-1) -> 3.3769049 | BY26: =100*((DataQ!AV218/DataQ!AV214)-1) -> 2.8299583 | BZ26: =100*((DataQ!AW218/DataQ!AW214)-1) -> 2.6650204 | CA26: =100*((DataQ!AX218/DataQ!AX214)-1) -> 2.1606654 | CB26: =100*((DataQ!AY218/DataQ!AY214)-1) -> 0.8779602 | CC26: =100*((DataQ!AZ218/DataQ!AZ214)-1) -> 1.1126095 | CD26: =100*((DataQ!BA218/DataQ!BA214)-1) -> 2.2427778 | CF26: 1983 | CG26: =OBR_MAR26_C4.6!C53 -> 9.3554799 | CH26: =OBR_MAR26_C4.6!D53 -> 3.6875007 | DU26: =100*((AVERAGE(HAVERQ!J11:J30)/AVERAGE(HAVERQ!J7:J26))-1) -> #N/A
BG27: 2004 | BH27: =100*(SUMIF(HAVERQ!$C:$C,'Chart Data'!$BG27,HAVERQ!L:L)/SUMIF(HAVERQ!$A:$A,'Chart Data'!$BG27,HAVERQ!G:G)) -> 35.780319 | BI27: =100*('Data Q to A'!AK39/'Data Q to A'!AL39) -> 33.809731 | BK27: 46023 | BL27: =DataQ!AQ219 -> 0.1694608 | BM27: =DataQ!AR219 -> -0.369029 | BN27: =DataQ!AS219 -> 0.458383 | BO27: =DataQ!AT219 -> 0.2529943 | BQ27: 2026 | BR27: =BX27 -> 3.1134829 | BS27: =MEDIAN(BX27:CD27) -> 2.1450455 | BT27: =MIN(BY27:CD27) -> 0.95908246 | BU27: =MAX(BY27:CD27)-BT27 -> 1.7449476 | BW27: 2026 | BX27: =100*((DataQ!AU219/DataQ!AU215)-1) -> 3.1134829 | BY27: =100*((DataQ!AV219/DataQ!AV215)-1) -> 2.70403 | BZ27: =100*((DataQ!AW219/DataQ!AW215)-1) -> 1.4110181 | CA27: =100*((DataQ!AX219/DataQ!AX215)-1) -> 2.2865289 | CB27: =100*((DataQ!AY219/DataQ!AY215)-1) -> 0.95908246 | CC27: =100*((DataQ!AZ219/DataQ!AZ215)-1) -> 1.4051222 | CD27: =100*((DataQ!BA219/DataQ!BA215)-1) -> 2.1450455 | CF27: 1984 | CG27: =OBR_MAR26_C4.6!C54 -> 9.7248373 | CH27: =OBR_MAR26_C4.6!D54 -> 3.8063912 | DT27: 1966 | DU27: =100*((AVERAGE(HAVERQ!J12:J31)/AVERAGE(HAVERQ!J8:J27))-1) -> #N/A
BG28: 2005 | BH28: =100*(SUMIF(HAVERQ!$C:$C,'Chart Data'!$BG28,HAVERQ!L:L)/SUMIF(HAVERQ!$A:$A,'Chart Data'!$BG28,HAVERQ!G:G)) -> 36.964145 | BI28: =100*('Data Q to A'!AK40/'Data Q to A'!AL40) -> 34.610253 | BK28: 46113 | BL28: =DataQ!AQ220 -> 0.6252518 | BM28: =DataQ!AR220 -> -0.1839261 | BN28: =DataQ!AS220 -> 0.4592803 | BO28: =DataQ!AT220 -> 0.3214837 | CF28: 1985 | CG28: =OBR_MAR26_C4.6!C55 -> 10.232056 | CH28: =OBR_MAR26_C4.6!D55 -> 3.910175 | DU28: =100*((AVERAGE(HAVERQ!J13:J32)/AVERAGE(HAVERQ!J9:J28))-1) -> #N/A
BG29: 2006 | BH29: =100*(SUMIF(HAVERQ!$C:$C,'Chart Data'!$BG29,HAVERQ!L:L)/SUMIF(HAVERQ!$A:$A,'Chart Data'!$BG29,HAVERQ!G:G)) -> 37.524424 | BI29: =100*('Data Q to A'!AK41/'Data Q to A'!AL41) -> 35.359782 | BK29: 46204 | BL29: =DataQ!AQ221 -> 0.7767475 | BM29: =DataQ!AR221 -> -0.3246279 | BN29: =DataQ!AS221 -> 0.2457361 | BO29: =DataQ!AT221 -> 0.4101481 | CF29: 1986 | CG29: =OBR_MAR26_C4.6!C56 -> 10.198507 | CH29: =OBR_MAR26_C4.6!D56 -> 3.8053068 | DU29: =100*((AVERAGE(HAVERQ!J14:J33)/AVERAGE(HAVERQ!J10:J29))-1) -> #N/A
BG30: 2007 | BH30: =100*(SUMIF(HAVERQ!$C:$C,'Chart Data'!$BG30,HAVERQ!L:L)/SUMIF(HAVERQ!$A:$A,'Chart Data'!$BG30,HAVERQ!G:G)) -> 37.905137 | BI30: =100*('Data Q to A'!AK42/'Data Q to A'!AL42) -> 35.728886 | BK30: 46296 | BL30: =DataQ!AQ222 -> 0.8152063 | BM30: =DataQ!AR222 -> -0.3651996 | BN30: =DataQ!AS222 -> 0.1769158 | BO30: =DataQ!AT222 -> 0.3521092 | CF30: 1987 | CG30: =OBR_MAR26_C4.6!C57 -> 10.061053 | CH30: =OBR_MAR26_C4.6!D57 -> 3.6278937 | DU30: =100*((AVERAGE(HAVERQ!J15:J34)/AVERAGE(HAVERQ!J11:J30))-1) -> #N/A
BG31: 2008 | BH31: =100*(SUMIF(HAVERQ!$C:$C,'Chart Data'!$BG31,HAVERQ!L:L)/SUMIF(HAVERQ!$A:$A,'Chart Data'!$BG31,HAVERQ!G:G)) -> 44.780264 | BI31: =100*('Data Q to A'!AK43/'Data Q to A'!AL43) -> 49.862549 | BK31: 46388 | BL31: =DataQ!AQ223 -> 0.7842233 | BM31: =DataQ!AR223 -> -0.3061402 | BN31: =DataQ!AS223 -> 0.2104012 | BO31: =DataQ!AT223 -> 0.2867934 | CF31: 1988 | CG31: =OBR_MAR26_C4.6!C58 -> 9.4655916 | CH31: =OBR_MAR26_C4.6!D58 -> 3.351217 | DT31: 1967 | DU31: =100*((AVERAGE(HAVERQ!J16:J35)/AVERAGE(HAVERQ!J12:J31))-1) -> #N/A
BG32: 2009 | BH32: =100*(SUMIF(HAVERQ!$C:$C,'Chart Data'!$BG32,HAVERQ!L:L)/SUMIF(HAVERQ!$A:$A,'Chart Data'!$BG32,HAVERQ!G:G)) -> 57.827376 | BI32: =100*('Data Q to A'!AK44/'Data Q to A'!AL44) -> 64.993532 | BK32: 46478 | BL32: =DataQ!AQ224 -> 0.8207624 | BM32: =DataQ!AR224 -> -0.206615 | BN32: =DataQ!AS224 -> 0.2725015 | BO32: =DataQ!AT224 -> 0.2386544 | CF32: 1989 | CG32: =OBR_MAR26_C4.6!C59 -> 9.1654459 | CH32: =OBR_MAR26_C4.6!D59 -> 3.1698509 | DU32: =100*((AVERAGE(HAVERQ!J17:J36)/AVERAGE(HAVERQ!J13:J32))-1) -> #N/A
BG33: 2010 | BH33: =100*(SUMIF(HAVERQ!$C:$C,'Chart Data'!$BG33,HAVERQ!L:L)/SUMIF(HAVERQ!$A:$A,'Chart Data'!$BG33,HAVERQ!G:G)) -> 68.457377 | BI33: =100*('Data Q to A'!AK45/'Data Q to A'!AL45) -> 71.031041 | BK33: 46569 | BL33: =DataQ!AQ225 -> 0.8354957 | BM33: =DataQ!AR225 -> -0.1461685 | BN33: =DataQ!AS225 -> 0.2912283 | BO33: =DataQ!AT225 -> 0.2211438 | CF33: 1990 | CG33: =OBR_MAR26_C4.6!C60 -> 8.5982169 | CH33: =OBR_MAR26_C4.6!D60 -> 2.9040419 | DU33: =100*((AVERAGE(HAVERQ!J18:J37)/AVERAGE(HAVERQ!J14:J33))-1) -> #N/A
BG34: 2011 | BH34: =100*(SUMIF(HAVERQ!$C:$C,'Chart Data'!$BG34,HAVERQ!L:L)/SUMIF(HAVERQ!$A:$A,'Chart Data'!$BG34,HAVERQ!G:G)) -> 72.883059 | BI34: =100*('Data Q to A'!AK46/'Data Q to A'!AL46) -> 74.500734 | BK34: 46661 | BL34: =DataQ!AQ226 -> 0.9301975 | BM34: =DataQ!AR226 -> -0.08266401 | BN34: =DataQ!AS226 -> 0.2674636 | BO34: =DataQ!AT226 -> 0.2099167 | CF34: 1991 | CG34: =OBR_MAR26_C4.6!C61 -> 7.4988932 | CH34: =OBR_MAR26_C4.6!D61 -> 2.5054983 | DU34: =100*((AVERAGE(HAVERQ!J19:J38)/AVERAGE(HAVERQ!J15:J34))-1) -> #N/A
BG35: 2012 | BH35: =100*(SUMIF(HAVERQ!$C:$C,'Chart Data'!$BG35,HAVERQ!L:L)/SUMIF(HAVERQ!$A:$A,'Chart Data'!$BG35,HAVERQ!G:G)) -> 75.67677 | BI35: =100*('Data Q to A'!AK47/'Data Q to A'!AL47) -> 77.978517 | BK35: 46753 | BL35: =DataQ!AQ227 -> 0.9513316 | BM35: =DataQ!AR227 -> -0.01909375 | BN35: =DataQ!AS227 -> 0.2579789 | BO35: =DataQ!AT227 -> 0.1942207 | CF35: 1992 | CG35: =OBR_MAR26_C4.6!C62 -> 7.9763233 | CH35: =OBR_MAR26_C4.6!D62 -> 2.5470652 | DT35: 1968 | DU35: =100*((AVERAGE(HAVERQ!J20:J39)/AVERAGE(HAVERQ!J16:J35))-1) -> #N/A
BG36: 2013 | BH36: =100*(SUMIF(HAVERQ!$C:$C,'Chart Data'!$BG36,HAVERQ!L:L)/SUMIF(HAVERQ!$A:$A,'Chart Data'!$BG36,HAVERQ!G:G)) -> 76.744424 | BI36: =100*('Data Q to A'!AK48/'Data Q to A'!AL48) -> 79.808516 | BK36: 46844 | BL36: =DataQ!AQ228 -> 0.9089571 | BM36: =DataQ!AR228 -> 0.1041012 | BN36: =DataQ!AS228 -> 0.2833322 | BO36: =DataQ!AT228 -> 0.2446561 | CF36: 1993 | CG36: =OBR_MAR26_C4.6!C63 -> 8.4102631 | CH36: =OBR_MAR26_C4.6!D63 -> 2.625316 | DU36: =100*((AVERAGE(HAVERQ!J21:J40)/AVERAGE(HAVERQ!J17:J36))-1) -> #N/A
BG37: 2014 | BH37: =100*(SUMIF(HAVERQ!$C:$C,'Chart Data'!$BG37,HAVERQ!L:L)/SUMIF(HAVERQ!$A:$A,'Chart Data'!$BG37,HAVERQ!G:G)) -> 78.372495 | BI37: =100*('Data Q to A'!AK49/'Data Q to A'!AL49) -> 81.374222 | BK37: 46935 | BL37: =DataQ!AQ229 -> 0.8601605 | BM37: =DataQ!AR229 -> 0.2399063 | BN37: =DataQ!AS229 -> 0.325026 | BO37: =DataQ!AT229 -> 0.3469173 | CF37: 1994 | CG37: =OBR_MAR26_C4.6!C64 -> 8.7682396 | CH37: =OBR_MAR26_C4.6!D64 -> 2.8138696 | DU37: =100*((AVERAGE(HAVERQ!J22:J41)/AVERAGE(HAVERQ!J18:J37))-1) -> #N/A
BG38: 2015 | BH38: =100*(SUMIF(HAVERQ!$C:$C,'Chart Data'!$BG38,HAVERQ!L:L)/SUMIF(HAVERQ!$A:$A,'Chart Data'!$BG38,HAVERQ!G:G)) -> 78.870092 | BI38: =100*('Data Q to A'!AK50/'Data Q to A'!AL50) -> 81.36435 | BK38: 47027 | BL38: =DataQ!AQ230 -> 0.8025382 | BM38: =DataQ!AR230 -> 0.3580289 | BN38: =DataQ!AS230 -> 0.3521523 | BO38: =DataQ!AT230 -> 0.4395704 | CF38: 1995 | CG38: =OBR_MAR26_C4.6!C65 -> 9.2409988 | CH38: =OBR_MAR26_C4.6!D65 -> 3.062618 | DU38: =100*((AVERAGE(HAVERQ!J23:J42)/AVERAGE(HAVERQ!J19:J38))-1) -> #N/A
BG39: 2016 | BH39: =100*(SUMIF(HAVERQ!$C:$C,'Chart Data'!$BG39,HAVERQ!L:L)/SUMIF(HAVERQ!$A:$A,'Chart Data'!$BG39,HAVERQ!G:G)) -> 78.310866 | BI39: =100*('Data Q to A'!AK51/'Data Q to A'!AL51) -> 83.47221 | BK39: 47119 | BL39: =DataQ!AQ231 -> 0.7665976 | BM39: =DataQ!AR231 -> 0.4511135 | BN39: =DataQ!AS231 -> 0.3748323 | BO39: =DataQ!AT231 -> 0.5587473 | CF39: 1996 | CG39: =OBR_MAR26_C4.6!C66 -> 9.3515614 | CH39: =OBR_MAR26_C4.6!D66 -> 3.0209788 | DT39: 1969 | DU39: =100*((AVERAGE(HAVERQ!J24:J43)/AVERAGE(HAVERQ!J20:J39))-1) -> #N/A
BG40: 2017 | BH40: =100*(SUMIF(HAVERQ!$C:$C,'Chart Data'!$BG40,HAVERQ!L:L)/SUMIF(HAVERQ!$A:$A,'Chart Data'!$BG40,HAVERQ!G:G)) -> 76.685587 | BI40: =100*('Data Q to A'!AK52/'Data Q to A'!AL52) -> 82.36411 | BK40: 47209 | BL40: =DataQ!AQ232 -> 0.7271161 | BM40: =DataQ!AR232 -> 0.4757442 | BN40: =DataQ!AS232 -> 0.3635231 | BO40: =DataQ!AT232 -> 0.6299802 | CF40: 1997 | CG40: =OBR_MAR26_C4.6!C67 -> 8.9393045 | CH40: =OBR_MAR26_C4.6!D67 -> 3.0729976 | DU40: =100*((AVERAGE(HAVERQ!J25:J44)/AVERAGE(HAVERQ!J21:J40))-1) -> #N/A
BG41: 2018 | BH41: =100*(SUMIF(HAVERQ!$C:$C,'Chart Data'!$BG41,HAVERQ!L:L)/SUMIF(HAVERQ!$A:$A,'Chart Data'!$BG41,HAVERQ!G:G)) -> 75.88981 | BI41: =100*('Data Q to A'!AK53/'Data Q to A'!AL53) -> 80.338144 | BK41: 47300 | BL41: =DataQ!AQ233 -> 0.6670064 | BM41: =DataQ!AR233 -> 0.4572711 | BN41: =DataQ!AS233 -> 0.3256425 | BO41: =DataQ!AT233 -> 0.6503463 | CF41: 1998 | CG41: =OBR_MAR26_C4.6!C68 -> 8.3006761 | CH41: =OBR_MAR26_C4.6!D68 -> 2.9032697 | DU41: =100*((AVERAGE(HAVERQ!J26:J45)/AVERAGE(HAVERQ!J22:J41))-1) -> #N/A
BG42: 2019 | BH42: =100*(SUMIF(HAVERQ!$C:$C,'Chart Data'!$BG42,HAVERQ!L:L)/SUMIF(HAVERQ!$A:$A,'Chart Data'!$BG42,HAVERQ!G:G)) -> 75.133835 | BI42: =100*('Data Q to A'!AK54/'Data Q to A'!AL54) -> 83.348098 | BK42: 47392 | BL42: =DataQ!AQ234 -> 0.6306264 | BM42: =DataQ!AR234 -> 0.4311786 | BN42: =DataQ!AS234 -> 0.2892233 | BO42: =DataQ!AT234 -> 0.6597865 | CF42: 1999 | CG42: =OBR_MAR26_C4.6!C69 -> 6.8422652 | CH42: =OBR_MAR26_C4.6!D69 -> 2.4410612 | DU42: =100*((AVERAGE(HAVERQ!J27:J46)/AVERAGE(HAVERQ!J23:J42))-1) -> #N/A | DV42: =100*((AVERAGE(HAVERQ!J7:J46)/AVERAGE(HAVERQ!J3:J42))-1) -> #N/A
BG43: 2020 | BH43: =100*(SUMIF(HAVERQ!$C:$C,'Chart Data'!$BG43,HAVERQ!L:L)/SUMIF(HAVERQ!$A:$A,'Chart Data'!$BG43,HAVERQ!G:G)) -> 92.197466 | BI43: =100*('Data Q to A'!AK55/'Data Q to A'!AL55) -> 97.702887 | BK43: 47484 | BL43: =DataQ!AQ235 -> 0.6250288 | BM43: =DataQ!AR235 -> 0.401109 | BN43: =DataQ!AS235 -> 0.2533313 | BO43: =DataQ!AT235 -> 0.6662557 | CF43: 2000 | CG43: =OBR_MAR26_C4.6!C70 -> 6.6166845 | CH43: =OBR_MAR26_C4.6!D70 -> 2.4060671 | DT43: 1970 | DU43: =100*((AVERAGE(HAVERQ!J28:J47)/AVERAGE(HAVERQ!J24:J43))-1) -> #N/A | DV43: =100*((AVERAGE(HAVERQ!J8:J47)/AVERAGE(HAVERQ!J4:J43))-1) -> #N/A | DW43: =$EA$5 -> 2.3089022
BG44: 2021 | BH44: =100*(SUMIF(HAVERQ!$C:$C,'Chart Data'!$BG44,HAVERQ!L:L)/SUMIF(HAVERQ!$A:$A,'Chart Data'!$BG44,HAVERQ!G:G)) -> 90.18187 | BI44: =100*('Data Q to A'!AK56/'Data Q to A'!AL56) -> 96.650128 | BK44: 47574 | BL44: =DataQ!AQ236 -> 0.6386032 | BM44: =DataQ!AR236 -> 0.3738184 | BN44: =DataQ!AS236 -> 0.2243876 | BO44: =DataQ!AT236 -> 0.6790503 | CF44: 2001 | CG44: =OBR_MAR26_C4.6!C71 -> 5.580598 | CH44: =OBR_MAR26_C4.6!D71 -> 1.9847618 | DU44: =100*((AVERAGE(HAVERQ!J29:J48)/AVERAGE(HAVERQ!J25:J44))-1) -> #N/A | DV44: =100*((AVERAGE(HAVERQ!J9:J48)/AVERAGE(HAVERQ!J5:J44))-1) -> #N/A | DW44: =$EA$5 -> 2.3089022
BG45: 2022 | BH45: =100*(SUMIF(HAVERQ!$C:$C,'Chart Data'!$BG45,HAVERQ!L:L)/SUMIF(HAVERQ!$A:$A,'Chart Data'!$BG45,HAVERQ!G:G)) -> 87.89608 | BI45: =100*('Data Q to A'!AK57/'Data Q to A'!AL57) -> 94.7179 | BK45: 47665 | BL45: =DataQ!AQ237 -> 0.6378323 | BM45: =DataQ!AR237 -> 0.3497627 | BN45: =DataQ!AS237 -> 0.2092209 | BO45: =DataQ!AT237 -> 0.6880352 | CF45: 2002 | CG45: =OBR_MAR26_C4.6!C72 -> 5.2055732 | CH45: =OBR_MAR26_C4.6!D72 -> 1.7971385 | DU45: =100*((AVERAGE(HAVERQ!J30:J49)/AVERAGE(HAVERQ!J26:J45))-1) -> #N/A | DV45: =100*((AVERAGE(HAVERQ!J10:J49)/AVERAGE(HAVERQ!J6:J45))-1) -> #N/A | DW45: =$EA$5 -> 2.3089022
BG46: 2023 | BH46: =100*(SUMIF(HAVERQ!$C:$C,'Chart Data'!$BG46,HAVERQ!L:L)/SUMIF(HAVERQ!$A:$A,'Chart Data'!$BG46,HAVERQ!G:G)) -> 90.397593 | BI46: =100*('Data Q to A'!AK58/'Data Q to A'!AL58) -> 95.702339 | BK46: 47757 | BL46: =DataQ!AQ238 -> 0.6296595 | BM46: =DataQ!AR238 -> 0.329133 | BN46: =DataQ!AS238 -> 0.2073281 | BO46: =DataQ!AT238 -> 0.6979308 | CF46: 2003 | CG46: =OBR_MAR26_C4.6!C73 -> 5.1502079 | CH46: =OBR_MAR26_C4.6!D73 -> 1.8175571 | DU46: =100*((AVERAGE(HAVERQ!J31:J50)/AVERAGE(HAVERQ!J27:J46))-1) -> #N/A | DV46: =100*((AVERAGE(HAVERQ!J11:J50)/AVERAGE(HAVERQ!J7:J46))-1) -> #N/A | DW46: =$EA$5 -> 2.3089022
BG47: 2024 | BH47: =100*(SUMIF(HAVERQ!$C:$C,'Chart Data'!$BG47,HAVERQ!L:L)/SUMIF(HAVERQ!$A:$A,'Chart Data'!$BG47,HAVERQ!G:G)) -> 92.41617 | BI47: =100*('Data Q to A'!AK59/'Data Q to A'!AL59) -> 94.389689 | CF47: 2004 | CG47: =OBR_MAR26_C4.6!C74 -> 5.3568287 | CH47: =OBR_MAR26_C4.6!D74 -> 1.9225099 | DT47: 1971 | DU47: =100*((AVERAGE(HAVERQ!J32:J51)/AVERAGE(HAVERQ!J28:J47))-1) -> #N/A | DV47: =100*((AVERAGE(HAVERQ!J12:J51)/AVERAGE(HAVERQ!J8:J47))-1) -> #N/A | DW47: =$EA$5 -> 2.3089022
BG48: 2025 | BH48: =100*(SUMIF(HAVERQ!$C:$C,'Chart Data'!$BG48,HAVERQ!L:L)/SUMIF(HAVERQ!$A:$A,'Chart Data'!$BG48,HAVERQ!G:G)) -> 93.846256 | BI48: =100*('Data Q to A'!AK60/'Data Q to A'!AL60) -> 93.951784 | CF48: 2005 | CG48: =OBR_MAR26_C4.6!C75 -> 5.3483745 | CH48: =OBR_MAR26_C4.6!D75 -> 1.952644 | DU48: =100*((AVERAGE(HAVERQ!J33:J52)/AVERAGE(HAVERQ!J29:J48))-1) -> #N/A | DV48: =100*((AVERAGE(HAVERQ!J13:J52)/AVERAGE(HAVERQ!J9:J48))-1) -> #N/A | DW48: =$EA$5 -> 2.3089022
BG49: 2026 | BH49: =BH48+BI49-BI48 -> 96.12068 | BI49: =100*('Data Q to A'!AK61/'Data Q to A'!AL61) -> 96.226208 | CF49: 2006 | CG49: =OBR_MAR26_C4.6!C76 -> 5.5780497 | CH49: =OBR_MAR26_C4.6!D76 -> 2.0598642 | DU49: =100*((AVERAGE(HAVERQ!J34:J53)/AVERAGE(HAVERQ!J30:J49))-1) -> #N/A | DV49: =100*((AVERAGE(HAVERQ!J14:J53)/AVERAGE(HAVERQ!J10:J49))-1) -> #N/A | DW49: =$EA$5 -> 2.3089022
BG50: 2027 | BH50: =BH49+BI50-BI49 -> 97.225972 | BI50: =100*('Data Q to A'!AK62/'Data Q to A'!AL62) -> 97.331501 | CF50: 2007 | CG50: =OBR_MAR26_C4.6!C77 -> 5.7689345 | CH50: =OBR_MAR26_C4.6!D77 -> 2.1438018 | DU50: =100*((AVERAGE(HAVERQ!J35:J54)/AVERAGE(HAVERQ!J31:J50))-1) -> #N/A | DV50: =100*((AVERAGE(HAVERQ!J15:J54)/AVERAGE(HAVERQ!J11:J50))-1) -> #N/A | DW50: =$EA$5 -> 2.3089022
BG51: 2028 | BH51: =BH50+BI51-BI50 -> 97.408665 | BI51: =100*('Data Q to A'!AK63/'Data Q to A'!AL63) -> 97.514194 | CF51: 2008 | CG51: =OBR_MAR26_C4.6!C78 -> 5.8887055 | CH51: =OBR_MAR26_C4.6!D78 -> 2.1047947 | DT51: 1972 | DU51: =100*((AVERAGE(HAVERQ!J36:J55)/AVERAGE(HAVERQ!J32:J51))-1) -> #N/A | DV51: =100*((AVERAGE(HAVERQ!J16:J55)/AVERAGE(HAVERQ!J12:J51))-1) -> #N/A | DW51: =$EA$5 -> 2.3089022
BG52: 2029 | BH52: =BH51+BI52-BI51 -> 97.863204 | BI52: =100*('Data Q to A'!AK64/'Data Q to A'!AL64) -> 97.968733 | CF52: 2009 | CG52: =OBR_MAR26_C4.6!C79 -> 5.0226682 | CH52: =OBR_MAR26_C4.6!D79 -> 1.7971118 | DU52: =100*((AVERAGE(HAVERQ!J37:J56)/AVERAGE(HAVERQ!J33:J52))-1) -> #N/A | DV52: =100*((AVERAGE(HAVERQ!J17:J56)/AVERAGE(HAVERQ!J13:J52))-1) -> #N/A | DW52: =$EA$5 -> 2.3089022
BG53: 2030 | BH53: =BH52+BI53-BI52 -> 97.421798 | BI53: =100*('Data Q to A'!AK65/'Data Q to A'!AL65) -> 97.527327 | CF53: 2010 | CG53: =OBR_MAR26_C4.6!C80 -> 6.8250374 | CH53: =OBR_MAR26_C4.6!D80 -> 2.5121163 | DU53: =100*((AVERAGE(HAVERQ!J38:J57)/AVERAGE(HAVERQ!J34:J53))-1) -> #N/A | DV53: =100*((AVERAGE(HAVERQ!J18:J57)/AVERAGE(HAVERQ!J14:J53))-1) -> #N/A | DW53: =$EA$5 -> 2.3089022
CF54: 2011 | CG54: =OBR_MAR26_C4.6!C81 -> 6.972641 | CH54: =OBR_MAR26_C4.6!D81 -> 2.5861171 | DU54: =100*((AVERAGE(HAVERQ!J39:J58)/AVERAGE(HAVERQ!J35:J54))-1) -> #N/A | DV54: =100*((AVERAGE(HAVERQ!J19:J58)/AVERAGE(HAVERQ!J15:J54))-1) -> #N/A | DW54: =$EA$5 -> 2.3089022
CF55: 2012 | CG55: =OBR_MAR26_C4.6!C82 -> 6.0806791 | CH55: =OBR_MAR26_C4.6!D82 -> 2.228828 | DT55: 1973 | DU55: =100*((AVERAGE(HAVERQ!J40:J59)/AVERAGE(HAVERQ!J36:J55))-1) -> #N/A | DV55: =100*((AVERAGE(HAVERQ!J20:J59)/AVERAGE(HAVERQ!J16:J55))-1) -> #N/A | DW55: =$EA$5 -> 2.3089022
CF56: 2013 | CG56: =OBR_MAR26_C4.6!C83 -> 5.7106699 | CH56: =OBR_MAR26_C4.6!D83 -> 2.086513 | DU56: =100*((AVERAGE(HAVERQ!J41:J60)/AVERAGE(HAVERQ!J37:J56))-1) -> #N/A | DV56: =100*((AVERAGE(HAVERQ!J21:J60)/AVERAGE(HAVERQ!J17:J56))-1) -> #N/A | DW56: =$EA$5 -> 2.3089022
CF57: 2014 | CG57: =OBR_MAR26_C4.6!C84 -> 4.9659561 | CH57: =OBR_MAR26_C4.6!D84 -> 1.8112783 | DU57: =100*((AVERAGE(HAVERQ!J42:J61)/AVERAGE(HAVERQ!J38:J57))-1) -> #N/A | DV57: =100*((AVERAGE(HAVERQ!J22:J61)/AVERAGE(HAVERQ!J18:J57))-1) -> #N/A | DW57: =$EA$5 -> 2.3089022
CF58: 2015 | CG58: =OBR_MAR26_C4.6!C85 -> 4.8618163 | CH58: =OBR_MAR26_C4.6!D85 -> 1.7832257 | DU58: =100*((AVERAGE(HAVERQ!J43:J62)/AVERAGE(HAVERQ!J39:J58))-1) -> #N/A | DV58: =100*((AVERAGE(HAVERQ!J23:J62)/AVERAGE(HAVERQ!J19:J58))-1) -> #N/A | DW58: =$EA$5 -> 2.3089022
CF59: 2016 | CG59: =OBR_MAR26_C4.6!C86 -> 4.8761732 | CH59: =OBR_MAR26_C4.6!D86 -> 1.8142999 | DT59: 1974 | DU59: =100*((AVERAGE(HAVERQ!J44:J63)/AVERAGE(HAVERQ!J40:J59))-1) -> #N/A | DV59: =100*((AVERAGE(HAVERQ!J24:J63)/AVERAGE(HAVERQ!J20:J59))-1) -> #N/A | DW59: =$EA$5 -> 2.3089022
CF60: 2017 | CG60: =OBR_MAR26_C4.6!C87 -> 5.4698175 | CH60: =OBR_MAR26_C4.6!D87 -> 2.0161571 | DU60: =100*((AVERAGE(HAVERQ!J45:J64)/AVERAGE(HAVERQ!J41:J60))-1) -> #N/A | DV60: =100*((AVERAGE(HAVERQ!J25:J64)/AVERAGE(HAVERQ!J21:J60))-1) -> #N/A | DW60: =$EA$5 -> 2.3089022
CF61: 2018 | CG61: =OBR_MAR26_C4.6!C88 -> 4.7780435 | CH61: =OBR_MAR26_C4.6!D88 -> 1.7710891 | DU61: =100*((AVERAGE(HAVERQ!J46:J65)/AVERAGE(HAVERQ!J42:J61))-1) -> #N/A | DV61: =100*((AVERAGE(HAVERQ!J26:J65)/AVERAGE(HAVERQ!J22:J61))-1) -> #N/A | DW61: =$EA$5 -> 2.3089022
CF62: 2019 | CG62: =OBR_MAR26_C4.6!C89 -> 4.7064731 | CH62: =OBR_MAR26_C4.6!D89 -> 1.7186418 | DU62: =100*((AVERAGE(HAVERQ!J47:J66)/AVERAGE(HAVERQ!J43:J62))-1) -> #N/A | DV62: =100*((AVERAGE(HAVERQ!J27:J66)/AVERAGE(HAVERQ!J23:J62))-1) -> #N/A | DW62: =$EA$5 -> 2.3089022
CF63: 2020 | CG63: =OBR_MAR26_C4.6!C90 -> 3.113517 | CH63: =OBR_MAR26_C4.6!D90 -> 1.1685804 | DT63: 1975 | DU63: =100*((AVERAGE(HAVERQ!J48:J67)/AVERAGE(HAVERQ!J44:J63))-1) -> #N/A | DV63: =100*((AVERAGE(HAVERQ!J28:J67)/AVERAGE(HAVERQ!J24:J63))-1) -> #N/A | DW63: =$EA$5 -> 2.3089022
CF64: 2021 | CG64: =OBR_MAR26_C4.6!C91 -> 5.9485648 | CH64: =OBR_MAR26_C4.6!D91 -> 2.28133 | DU64: =100*((AVERAGE(HAVERQ!J49:J68)/AVERAGE(HAVERQ!J45:J64))-1) -> #N/A | DV64: =100*((AVERAGE(HAVERQ!J29:J68)/AVERAGE(HAVERQ!J25:J64))-1) -> #N/A | DW64: =$EA$5 -> 2.3089022
CF65: 2022 | CG65: =OBR_MAR26_C4.6!C92 -> 10.80109 | CH65: =OBR_MAR26_C4.6!D92 -> 4.2373866 | DU65: =100*((AVERAGE(HAVERQ!J50:J69)/AVERAGE(HAVERQ!J46:J65))-1) -> #N/A | DV65: =100*((AVERAGE(HAVERQ!J30:J69)/AVERAGE(HAVERQ!J26:J65))-1) -> #N/A | DW65: =$EA$5 -> 2.3089022
CF66: 2023 | CG66: =OBR_MAR26_C4.6!C93 -> 9.8133907 | CH66: =OBR_MAR26_C4.6!D93 -> 3.8550287 | DU66: =100*((AVERAGE(HAVERQ!J51:J70)/AVERAGE(HAVERQ!J47:J66))-1) -> #N/A | DV66: =100*((AVERAGE(HAVERQ!J31:J70)/AVERAGE(HAVERQ!J27:J66))-1) -> #N/A | DW66: =$EA$5 -> 2.3089022
CF67: 2024 | CG67: =OBR_MAR26_C4.6!C94 -> 9.2792728 | CH67: =OBR_MAR26_C4.6!D94 -> 3.6022235 | DT67: 1976 | DU67: =100*((AVERAGE(HAVERQ!J52:J71)/AVERAGE(HAVERQ!J48:J67))-1) -> #N/A | DV67: =100*((AVERAGE(HAVERQ!J32:J71)/AVERAGE(HAVERQ!J28:J67))-1) -> #N/A | DW67: =$EA$5 -> 2.3089022
CF68: 2025 | CG68: =OBR_MAR26_C4.6!C95 -> 8.879279 | CH68: =OBR_MAR26_C4.6!D95 -> 3.5906242 | DU68: =100*((AVERAGE(HAVERQ!J53:J72)/AVERAGE(HAVERQ!J49:J68))-1) -> #N/A | DV68: =100*((AVERAGE(HAVERQ!J33:J72)/AVERAGE(HAVERQ!J29:J68))-1) -> #N/A | DW68: =$EA$5 -> 2.3089022
CF69: 2026 | CG69: =OBR_MAR26_C4.6!C96 -> 8.3882946 | CH69: =OBR_MAR26_C4.6!D96 -> 3.4564942 | DU69: =100*((AVERAGE(HAVERQ!J54:J73)/AVERAGE(HAVERQ!J50:J69))-1) -> #N/A | DV69: =100*((AVERAGE(HAVERQ!J34:J73)/AVERAGE(HAVERQ!J30:J69))-1) -> #N/A | DW69: =$EA$5 -> 2.3089022
CF70: 2027 | CG70: =OBR_MAR26_C4.6!C97 -> 8.4854151 | CH70: =OBR_MAR26_C4.6!D97 -> 3.5614507 | DU70: =100*((AVERAGE(HAVERQ!J55:J74)/AVERAGE(HAVERQ!J51:J70))-1) -> 2.0029422 | DV70: =100*((AVERAGE(HAVERQ!J35:J74)/AVERAGE(HAVERQ!J31:J70))-1) -> #N/A | DW70: =$EA$5 -> 2.3089022
CF71: 2028 | CG71: =OBR_MAR26_C4.6!C98 -> 8.8216193 | CH71: =OBR_MAR26_C4.6!D98 -> 3.713642 | DT71: 1977 | DU71: =100*((AVERAGE(HAVERQ!J56:J75)/AVERAGE(HAVERQ!J52:J71))-1) -> 1.980198 | DV71: =100*((AVERAGE(HAVERQ!J36:J75)/AVERAGE(HAVERQ!J32:J71))-1) -> #N/A | DW71: =$EA$5 -> 2.3089022
CF72: 2029 | CG72: =OBR_MAR26_C4.6!C99 -> 9.0287683 | CH72: =OBR_MAR26_C4.6!D99 -> 3.8413616 | DU72: =100*((AVERAGE(HAVERQ!J57:J76)/AVERAGE(HAVERQ!J53:J72))-1) -> 1.8924972 | DV72: =100*((AVERAGE(HAVERQ!J37:J76)/AVERAGE(HAVERQ!J33:J72))-1) -> #N/A | DW72: =$EA$5 -> 2.3089022
CF73: 2030 | CG73: =OBR_MAR26_C4.6!C100 -> 8.8374331 | CH73: =OBR_MAR26_C4.6!D100 -> 3.7752691 | DU73: =100*((AVERAGE(HAVERQ!J58:J77)/AVERAGE(HAVERQ!J54:J73))-1) -> 1.8508195 | DV73: =100*((AVERAGE(HAVERQ!J38:J77)/AVERAGE(HAVERQ!J34:J73))-1) -> #N/A | DW73: =$EA$5 -> 2.3089022
DU74: =100*((AVERAGE(HAVERQ!J59:J78)/AVERAGE(HAVERQ!J55:J74))-1) -> 1.7750166 | DV74: =100*((AVERAGE(HAVERQ!J39:J78)/AVERAGE(HAVERQ!J35:J74))-1) -> #N/A | DW74: =$EA$5 -> 2.3089022
DT75: 1978 | DU75: =100*((AVERAGE(HAVERQ!J60:J79)/AVERAGE(HAVERQ!J56:J75))-1) -> 1.5004413 | DV75: =100*((AVERAGE(HAVERQ!J40:J79)/AVERAGE(HAVERQ!J36:J75))-1) -> #N/A | DW75: =$EA$5 -> 2.3089022
DU76: =100*((AVERAGE(HAVERQ!J61:J80)/AVERAGE(HAVERQ!J57:J76))-1) -> 1.4287284 | DV76: =100*((AVERAGE(HAVERQ!J41:J80)/AVERAGE(HAVERQ!J37:J76))-1) -> #N/A | DW76: =$EA$5 -> 2.3089022
DU77: =100*((AVERAGE(HAVERQ!J62:J81)/AVERAGE(HAVERQ!J58:J77))-1) -> 1.4668856 | DV77: =100*((AVERAGE(HAVERQ!J42:J81)/AVERAGE(HAVERQ!J38:J77))-1) -> #N/A | DW77: =$EA$5 -> 2.3089022
DU78: =100*((AVERAGE(HAVERQ!J63:J82)/AVERAGE(HAVERQ!J59:J78))-1) -> 1.5042511 | DV78: =100*((AVERAGE(HAVERQ!J43:J82)/AVERAGE(HAVERQ!J39:J78))-1) -> #N/A | DW78: =$EA$5 -> 2.3089022
DT79: 1979 | DU79: =100*((AVERAGE(HAVERQ!J64:J83)/AVERAGE(HAVERQ!J60:J79))-1) -> 1.7608696 | DV79: =100*((AVERAGE(HAVERQ!J44:J83)/AVERAGE(HAVERQ!J40:J79))-1) -> #N/A | DW79: =$EA$5 -> 2.3089022
DU80: =100*((AVERAGE(HAVERQ!J65:J84)/AVERAGE(HAVERQ!J61:J80))-1) -> 2.112905 | DV80: =100*((AVERAGE(HAVERQ!J45:J84)/AVERAGE(HAVERQ!J41:J80))-1) -> #N/A | DW80: =$EA$5 -> 2.3089022
DU81: =100*((AVERAGE(HAVERQ!J66:J85)/AVERAGE(HAVERQ!J62:J81))-1) -> 2.190096 | DV81: =100*((AVERAGE(HAVERQ!J46:J85)/AVERAGE(HAVERQ!J42:J81))-1) -> #N/A | DW81: =$EA$5 -> 2.3089022
DU82: =100*((AVERAGE(HAVERQ!J67:J86)/AVERAGE(HAVERQ!J63:J82))-1) -> 2.3303265 | DV82: =100*((AVERAGE(HAVERQ!J47:J86)/AVERAGE(HAVERQ!J43:J82))-1) -> #N/A | DW82: =$EA$5 -> 2.3089022
DT83: 1980 | DU83: =100*((AVERAGE(HAVERQ!J68:J87)/AVERAGE(HAVERQ!J64:J83))-1) -> 2.3178808 | DV83: =100*((AVERAGE(HAVERQ!J48:J87)/AVERAGE(HAVERQ!J44:J83))-1) -> #N/A | DW83: =$EA$5 -> 2.3089022
DU84: =100*((AVERAGE(HAVERQ!J69:J88)/AVERAGE(HAVERQ!J65:J84))-1) -> 2.1859083 | DV84: =100*((AVERAGE(HAVERQ!J49:J88)/AVERAGE(HAVERQ!J45:J84))-1) -> #N/A | DW84: =$EA$5 -> 2.3089022
DU85: =100*((AVERAGE(HAVERQ!J70:J89)/AVERAGE(HAVERQ!J66:J85))-1) -> 2.269848 | DV85: =100*((AVERAGE(HAVERQ!J50:J89)/AVERAGE(HAVERQ!J46:J85))-1) -> #N/A | DW85: =$EA$5 -> 2.3089022
DU86: =100*((AVERAGE(HAVERQ!J71:J90)/AVERAGE(HAVERQ!J67:J86))-1) -> 2.1933046 | DV86: =100*((AVERAGE(HAVERQ!J51:J90)/AVERAGE(HAVERQ!J47:J86))-1) -> #N/A | DW86: =$EA$5 -> 2.3089022
DT87: 1981 | DU87: =100*((AVERAGE(HAVERQ!J72:J91)/AVERAGE(HAVERQ!J68:J87))-1) -> 2.1609771 | DV87: =100*((AVERAGE(HAVERQ!J52:J91)/AVERAGE(HAVERQ!J48:J87))-1) -> #N/A | DW87: =$EA$5 -> 2.3089022
DU88: =100*((AVERAGE(HAVERQ!J73:J92)/AVERAGE(HAVERQ!J69:J88))-1) -> 2.2222222 | DV88: =100*((AVERAGE(HAVERQ!J53:J92)/AVERAGE(HAVERQ!J49:J88))-1) -> #N/A | DW88: =$EA$5 -> 2.3089022
DU89: =100*((AVERAGE(HAVERQ!J74:J93)/AVERAGE(HAVERQ!J70:J89))-1) -> 2.271085 | DV89: =100*((AVERAGE(HAVERQ!J54:J93)/AVERAGE(HAVERQ!J50:J89))-1) -> #N/A | DW89: =$EA$5 -> 2.3089022
DU90: =100*((AVERAGE(HAVERQ!J75:J94)/AVERAGE(HAVERQ!J71:J90))-1) -> 2.3618813 | DV90: =100*((AVERAGE(HAVERQ!J55:J94)/AVERAGE(HAVERQ!J51:J90))-1) -> 2.1911171 | DW90: =$EA$5 -> 2.3089022
DT91: 1982 | DU91: =100*((AVERAGE(HAVERQ!J76:J95)/AVERAGE(HAVERQ!J72:J91))-1) -> 2.4729205 | DV91: =100*((AVERAGE(HAVERQ!J56:J95)/AVERAGE(HAVERQ!J52:J91))-1) -> 2.2384063 | DW91: =$EA$5 -> 2.3089022
DU92: =100*((AVERAGE(HAVERQ!J77:J96)/AVERAGE(HAVERQ!J73:J92))-1) -> 2.6412028 | DV92: =100*((AVERAGE(HAVERQ!J57:J96)/AVERAGE(HAVERQ!J53:J92))-1) -> 2.2850751 | DW92: =$EA$5 -> 2.3089022
DU93: =100*((AVERAGE(HAVERQ!J78:J97)/AVERAGE(HAVERQ!J74:J93))-1) -> 2.785909 | DV93: =100*((AVERAGE(HAVERQ!J58:J97)/AVERAGE(HAVERQ!J54:J93))-1) -> 2.3415978 | DW93: =$EA$5 -> 2.3089022
DU94: =100*((AVERAGE(HAVERQ!J79:J98)/AVERAGE(HAVERQ!J75:J94))-1) -> 2.9394061 | DV94: =100*((AVERAGE(HAVERQ!J59:J98)/AVERAGE(HAVERQ!J55:J94))-1) -> 2.3864714 | DW94: =$EA$5 -> 2.3089022
DT95: 1983 | DU95: =100*((AVERAGE(HAVERQ!J80:J99)/AVERAGE(HAVERQ!J76:J95))-1) -> 3.2209813 | DV95: =100*((AVERAGE(HAVERQ!J60:J99)/AVERAGE(HAVERQ!J56:J95))-1) -> 2.4041483 | DW95: =$EA$5 -> 2.3089022
DU96: =100*((AVERAGE(HAVERQ!J81:J100)/AVERAGE(HAVERQ!J77:J96))-1) -> 3.3353127 | DV96: =100*((AVERAGE(HAVERQ!J61:J100)/AVERAGE(HAVERQ!J57:J96))-1) -> 2.4319117 | DW96: =$EA$5 -> 2.3089022
DU97: =100*((AVERAGE(HAVERQ!J82:J101)/AVERAGE(HAVERQ!J78:J97))-1) -> 3.3781793 | DV97: =100*((AVERAGE(HAVERQ!J62:J101)/AVERAGE(HAVERQ!J58:J97))-1) -> 2.4743762 | DW97: =$EA$5 -> 2.3089022
DU98: =100*((AVERAGE(HAVERQ!J83:J102)/AVERAGE(HAVERQ!J79:J98))-1) -> 3.4109736 | DV98: =100*((AVERAGE(HAVERQ!J63:J102)/AVERAGE(HAVERQ!J59:J98))-1) -> 2.5109339 | DW98: =$EA$5 -> 2.3089022
DT99: 1984 | DU99: =100*((AVERAGE(HAVERQ!J84:J103)/AVERAGE(HAVERQ!J80:J99))-1) -> 3.3813158 | DV99: =100*((AVERAGE(HAVERQ!J64:J103)/AVERAGE(HAVERQ!J60:J99))-1) -> 2.6187919 | DW99: =$EA$5 -> 2.3089022
DU100: =100*((AVERAGE(HAVERQ!J85:J104)/AVERAGE(HAVERQ!J81:J100))-1) -> 3.0552629 | DV100: =100*((AVERAGE(HAVERQ!J65:J104)/AVERAGE(HAVERQ!J61:J100))-1) -> 2.6131164 | DW100: =$EA$5 -> 2.3089022
...

Sheet HAVERQ
D1: 19601 !Q | E1: NMFX@UK | F1: MU74@UK | G1: YBHAQ@UK | H1: JW2QQ@UK | I1: A4YMQ@UK | J1: LZVBQ@UK | K1: BKPXQ@UK | L1: MDK2@UK
D2: .DESC | E2: UK: Central Government: Current Expenditure: Interest (NSA, Mil.GBP) | F2: UK: BoE: Curr Exp: Int & Divs Paid to Priv Sector/Rest of World (NSA, Mil.GBP) | G2: UK: Gross Domestic Product [GDP] (SA, Mil.Pounds) | H2: UK: Public Sector ex Finl Intervention: Total Current Expenditure (NSA, Mil.GBP) | I2: UK: Output per Worker: Whole Economy (SA, 2023=100) | J2: U.K.: Output per Hour Worked: Whole Economy (SA, 2023=100) | K2: UK: General Government Consolidated Gross Debt - Nominal (EOP, NSA, Mil.GBP) | L2: UK: General Government Net Debt (EOP, NSA, Mil.GBP)
D3: .T1 | E3: Q2-1997 <- Apr-1997 | F3: Q1-1997 <- Mar-1997 | G3: Q1-1955 | H3: Q1-1946 | I3: Q3-1959 | J3: Q1-1971 | K3: Q1-1975 | L3: Q1-1975 <- Mar-1975
D4: .TN | E4: Q1-2026 <- Apr-2026 | F4: Q1-2026 <- Apr-2026 | G4: Q1-2026 | H4: Q1-2026 | I4: Q4-2025 | J4: Q4-2025 | K4: Q1-2026 | L4: Q1-2026 <- Apr-2026
D5: .LSOURCE | E5: Office for National Statistics | F5: Office for National Statistics | G5: Office for National Statistics | H5: Office for National Statistics | I5: Office for National Statistics | J5: Office for National Statistics | K5: Office for National Statistics | L5: Office for National Statistics
A6: CY tot | B6: CY end-1 | C6: CY end | D6: .DTLM | E6: May-22-2026 07:10 | F6: May-22-2026 07:10 | G6: May-14-2026 07:16 | H6: May-22-2026 07:10 | I6: May-19-2026 09:32 | J6: May-19-2026 09:32 | K6: May-22-2026 07:06 | L6: May-22-2026 07:06
A7: 1960 | D7: 19601 | E7: #N/A | F7: #N/A | G7: 6427 | H7: 1871 | I7: 33.7 | J7: #N/A | K7: #N/A | L7: #N/A
A8: 1960 | D8: 19602 | E8: #N/A | F8: #N/A | G8: 6486 | H8: 1877 | I8: 33.4 | J8: #N/A | K8: #N/A | L8: #N/A
A9: 1960 | D9: 19603 | E9: #N/A | F9: #N/A | G9: 6580 | H9: 1879 | I9: 33.8 | J9: #N/A | K9: #N/A | L9: #N/A
A10: 1960 | C10: 1960 | D10: 19604 | E10: #N/A | F10: #N/A | G10: 6713 | H10: 1963 | I10: 33.9 | J10: #N/A | K10: #N/A | L10: #N/A
A11: =+A7+1 -> 1961 | B11: 1960 | D11: 19611 | E11: #N/A | F11: #N/A | G11: 6883 | H11: 2048 | I11: 34.3 | J11: #N/A | K11: #N/A | L11: #N/A
A12: =+A8+1 -> 1961 | D12: 19612 | E12: #N/A | F12: #N/A | G12: 6883 | H12: 2024 | I12: 34.4 | J12: #N/A | K12: #N/A | L12: #N/A
A13: =+A9+1 -> 1961 | D13: 19613 | E13: #N/A | F13: #N/A | G13: 7121 | H13: 2102 | I13: 34.2 | J13: #N/A | K13: #N/A | L13: #N/A
A14: =+A10+1 -> 1961 | C14: 1961 | D14: 19614 | E14: #N/A | F14: #N/A | G14: 7037 | H14: 2109 | I14: 34.2 | J14: #N/A | K14: #N/A | L14: #N/A
A15: =+A11+1 -> 1962 | B15: 1961 | D15: 19621 | E15: #N/A | F15: #N/A | G15: 7134 | H15: 2251 | I15: 34.3 | J15: #N/A | K15: #N/A | L15: #N/A
A16: =+A12+1 -> 1962 | D16: 19622 | E16: #N/A | F16: #N/A | G16: 7309 | H16: 2124 | I16: 34.5 | J16: #N/A | K16: #N/A | L16: #N/A
A17: =+A13+1 -> 1962 | D17: 19623 | E17: #N/A | F17: #N/A | G17: 7383 | H17: 2176 | I17: 34.6 | J17: #N/A | K17: #N/A | L17: #N/A
A18: =+A14+1 -> 1962 | C18: 1962 | D18: 19624 | E18: #N/A | F18: #N/A | G18: 7416 | H18: 2259 | I18: 34.6 | J18: #N/A | K18: #N/A | L18: #N/A
A19: =+A15+1 -> 1963 | B19: 1962 | D19: 19631 | E19: #N/A | F19: #N/A | G19: 7367 | H19: 2249 | I19: 35.1 | J19: #N/A | K19: #N/A | L19: #N/A
A20: =+A16+1 -> 1963 | D20: 19632 | E20: #N/A | F20: #N/A | G20: 7752 | H20: 2175 | I20: 36.4 | J20: #N/A | K20: #N/A | L20: #N/A
A21: =+A17+1 -> 1963 | D21: 19633 | E21: #N/A | F21: #N/A | G21: 7871 | H21: 2265 | I21: 36.3 | J21: #N/A | K21: #N/A | L21: #N/A
A22: =+A18+1 -> 1963 | C22: 1963 | D22: 19634 | E22: #N/A | F22: #N/A | G22: 8117 | H22: 2303 | I22: 37.1 | J22: #N/A | K22: #N/A | L22: #N/A
A23: =+A19+1 -> 1964 | B23: 1963 | D23: 19641 | E23: #N/A | F23: #N/A | G23: 8144 | H23: 2407 | I23: 37.4 | J23: #N/A | K23: #N/A | L23: #N/A
A24: =+A20+1 -> 1964 | D24: 19642 | E24: #N/A | F24: #N/A | G24: 8435 | H24: 2299 | I24: 37.8 | J24: #N/A | K24: #N/A | L24: #N/A
A25: =+A21+1 -> 1964 | D25: 19643 | E25: #N/A | F25: #N/A | G25: 8620 | H25: 2391 | I25: 37.8 | J25: #N/A | K25: #N/A | L25: #N/A
A26: =+A22+1 -> 1964 | C26: 1964 | D26: 19644 | E26: #N/A | F26: #N/A | G26: 8857 | H26: 2412 | I26: 38.1 | J26: #N/A | K26: #N/A | L26: #N/A
A27: =+A23+1 -> 1965 | B27: 1964 | D27: 19651 | E27: #N/A | F27: #N/A | G27: 9021 | H27: 2622 | I27: 38.1 | J27: #N/A | K27: #N/A | L27: #N/A
A28: =+A24+1 -> 1965 | D28: 19652 | E28: #N/A | F28: #N/A | G28: 9065 | H28: 2612 | I28: 38.2 | J28: #N/A | K28: #N/A | L28: #N/A
A29: =+A25+1 -> 1965 | D29: 19653 | E29: #N/A | F29: #N/A | G29: 9286 | H29: 2727 | I29: 38.4 | J29: #N/A | K29: #N/A | L29: #N/A
A30: =+A26+1 -> 1965 | C30: 1965 | D30: 19654 | E30: #N/A | F30: #N/A | G30: 9467 | H30: 2746 | I30: 38.5 | J30: #N/A | K30: #N/A | L30: #N/A
A31: =+A27+1 -> 1966 | B31: 1965 | D31: 19661 | E31: #N/A | F31: #N/A | G31: 9609 | H31: 2881 | I31: 38.4 | J31: #N/A | K31: #N/A | L31: #N/A
A32: =+A28+1 -> 1966 | D32: 19662 | E32: #N/A | F32: #N/A | G32: 9775 | H32: 2803 | I32: 38.6 | J32: #N/A | K32: #N/A | L32: #N/A
A33: =+A29+1 -> 1966 | D33: 19663 | E33: #N/A | F33: #N/A | G33: 9959 | H33: 2900 | I33: 38.8 | J33: #N/A | K33: #N/A | L33: #N/A
A34: =+A30+1 -> 1966 | C34: 1966 | D34: 19664 | E34: #N/A | F34: #N/A | G34: 10064 | H34: 2992 | I34: 38.9 | J34: #N/A | K34: #N/A | L34: #N/A
A35: =+A31+1 -> 1967 | B35: 1966 | D35: 19671 | E35: #N/A | F35: #N/A | G35: 10161 | H35: 3263 | I35: 39.5 | J35: #N/A | K35: #N/A | L35: #N/A
A36: =+A32+1 -> 1967 | D36: 19672 | E36: #N/A | F36: #N/A | G36: 10417 | H36: 3090 | I36: 40 | J36: #N/A | K36: #N/A | L36: #N/A
A37: =+A33+1 -> 1967 | D37: 19673 | E37: #N/A | F37: #N/A | G37: 10487 | H37: 3291 | I37: 40.2 | J37: #N/A | K37: #N/A | L37: #N/A
A38: =+A34+1 -> 1967 | C38: 1967 | D38: 19674 | E38: #N/A | F38: #N/A | G38: 10622 | H38: 3356 | I38: 40.5 | J38: #N/A | K38: #N/A | L38: #N/A
A39: =+A35+1 -> 1968 | B39: 1967 | D39: 19681 | E39: #N/A | F39: #N/A | G39: 11102 | H39: 3682 | I39: 42.1 | J39: #N/A | K39: #N/A | L39: #N/A
A40: =+A36+1 -> 1968 | D40: 19682 | E40: #N/A | F40: #N/A | G40: 11235 | H40: 3429 | I40: 42.2 | J40: #N/A | K40: #N/A | L40: #N/A
A41: =+A37+1 -> 1968 | D41: 19683 | E41: #N/A | F41: #N/A | G41: 11591 | H41: 3593 | I41: 42.9 | J41: #N/A | K41: #N/A | L41: #N/A
A42: =+A38+1 -> 1968 | C42: 1968 | D42: 19684 | E42: #N/A | F42: #N/A | G42: 11883 | H42: 3566 | I42: 42.9 | J42: #N/A | K42: #N/A | L42: #N/A
A43: =+A39+1 -> 1969 | B43: 1968 | D43: 19691 | E43: #N/A | F43: #N/A | G43: 12091 | H43: 3877 | I43: 43 | J43: #N/A | K43: #N/A | L43: #N/A
A44: =+A40+1 -> 1969 | D44: 19692 | E44: #N/A | F44: #N/A | G44: 12271 | H44: 3575 | I44: 43.2 | J44: #N/A | K44: #N/A | L44: #N/A
A45: =+A41+1 -> 1969 | D45: 19693 | E45: #N/A | F45: #N/A | G45: 12545 | H45: 3828 | I45: 43.4 | J45: #N/A | K45: #N/A | L45: #N/A
A46: =+A42+1 -> 1969 | C46: 1969 | D46: 19694 | E46: #N/A | F46: #N/A | G46: 12869 | H46: 3884 | I46: 43.7 | J46: #N/A | K46: #N/A | L46: #N/A
A47: =+A43+1 -> 1970 | B47: 1969 | D47: 19701 | E47: #N/A | F47: #N/A | G47: 13223 | H47: 4118 | I47: 43.4 | J47: #N/A | K47: #N/A | L47: #N/A
A48: =+A44+1 -> 1970 | D48: 19702 | E48: #N/A | F48: #N/A | G48: 13806 | H48: 4019 | I48: 44.5 | J48: #N/A | K48: #N/A | L48: #N/A
A49: =+A45+1 -> 1970 | D49: 19703 | E49: #N/A | F49: #N/A | G49: 14256 | H49: 4231 | I49: 44.9 | J49: #N/A | K49: #N/A | L49: #N/A
A50: =+A46+1 -> 1970 | C50: 1970 | D50: 19704 | E50: #N/A | F50: #N/A | G50: 14771 | H50: 4327 | I50: 45.7 | J50: #N/A | K50: #N/A | L50: #N/A
A51: =+A47+1 -> 1971 | B51: 1970 | D51: 19711 | E51: #N/A | F51: #N/A | G51: 14990 | H51: 4473 | I51: 45.8 | J51: 41.2 | K51: #N/A | L51: #N/A
A52: =+A48+1 -> 1971 | D52: 19712 | E52: #N/A | F52: #N/A | G52: 15501 | H52: 4433 | I52: 46.6 | J52: 42 | K52: #N/A | L52: #N/A
A53: =+A49+1 -> 1971 | D53: 19713 | E53: #N/A | F53: #N/A | G53: 15997 | H53: 4716 | I53: 47.6 | J53: 42.8 | K53: #N/A | L53: #N/A
A54: =+A50+1 -> 1971 | C54: 1971 | D54: 19714 | E54: #N/A | F54: #N/A | G54: 16398 | H54: 4977 | I54: 48.1 | J54: 43 | K54: #N/A | L54: #N/A
A55: =+A51+1 -> 1972 | B55: 1971 | D55: 19721 | E55: #N/A | F55: #N/A | G55: 16603 | H55: 5369 | I55: 47.9 | J55: 42.7 | K55: #N/A | L55: #N/A
A56: =+A52+1 -> 1972 | D56: 19722 | E56: #N/A | F56: #N/A | G56: 17392 | H56: 5089 | I56: 49 | J56: 43.5 | K56: #N/A | L56: #N/A
A57: =+A53+1 -> 1972 | D57: 19723 | E57: #N/A | F57: #N/A | G57: 17763 | H57: 5329 | I57: 49.2 | J57: 43.6 | K57: #N/A | L57: #N/A
A58: =+A54+1 -> 1972 | C58: 1972 | D58: 19724 | E58: #N/A | F58: #N/A | G58: 18837 | H58: 5715 | I58: 49.8 | J58: 44.1 | K58: #N/A | L58: #N/A
A59: =+A55+1 -> 1973 | B59: 1972 | D59: 19731 | E59: #N/A | F59: #N/A | G59: 20050 | H59: 5903 | I59: 51.8 | J59: 45.8 | K59: #N/A | L59: #N/A
A60: =+A56+1 -> 1973 | D60: 19732 | E60: #N/A | F60: #N/A | G60: 19879 | H60: 5685 | I60: 51.8 | J60: 45.8 | K60: #N/A | L60: #N/A
A61: =+A57+1 -> 1973 | D61: 19733 | E61: #N/A | F61: #N/A | G61: 20563 | H61: 6117 | I61: 51.3 | J61: 45.3 | K61: #N/A | L61: #N/A
A62: =+A58+1 -> 1973 | C62: 1973 | D62: 19734 | E62: #N/A | F62: #N/A | G62: 21317 | H62: 6558 | I62: 51 | J62: 45.1 | K62: #N/A | L62: #N/A
A63: =+A59+1 -> 1974 | B63: 1973 | D63: 19741 | E63: #N/A | F63: #N/A | G63: 21136 | H63: 7324 | I63: 49.7 | J63: 44 | K63: #N/A | L63: #N/A
A64: =+A60+1 -> 1974 | D64: 19742 | E64: #N/A | F64: #N/A | G64: 22654 | H64: 6969 | I64: 50.4 | J64: 44.8 | K64: #N/A | L64: #N/A
A65: =+A61+1 -> 1974 | D65: 19743 | E65: #N/A | F65: #N/A | G65: 23899 | H65: 8197 | I65: 50.7 | J65: 45.3 | K65: #N/A | L65: #N/A
A66: =+A62+1 -> 1974 | C66: 1974 | D66: 19744 | E66: #N/A | F66: #N/A | G66: 24997 | H66: 9003 | I66: 49.9 | J66: 44.8 | K66: #N/A | L66: #N/A
A67: =+A63+1 -> 1975 | B67: 1974 | D67: 19751 | E67: #N/A | F67: #N/A | G67: 26815 | H67: 9970 | I67: 50 | J67: 45.1 | K67: 53670 | L67: 50196
A68: =+A64+1 -> 1975 | D68: 19752 | E68: #N/A | F68: #N/A | G68: 28130 | H68: 9857 | I68: 49.4 | J68: 44.7 | K68: #N/A | L68: #N/A
A69: =+A65+1 -> 1975 | D69: 19753 | E69: #N/A | F69: #N/A | G69: 29260 | H69: 10748 | I69: 49.2 | J69: 44.7 | K69: #N/A | L69: #N/A
A70: =+A66+1 -> 1975 | C70: 1975 | D70: 19754 | E70: #N/A | F70: #N/A | G70: 30890 | H70: 11248 | I70: 49.9 | J70: 45.4 | K70: #N/A | L70: #N/A
A71: =+A67+1 -> 1976 | B71: 1975 | D71: 19761 | E71: #N/A | F71: #N/A | G71: 32448 | H71: 12067 | I71: 50.8 | J71: 46.3 | K71: 65638 | L71: 61867
A72: =+A68+1 -> 1976 | D72: 19762 | E72: #N/A | F72: #N/A | G72: 33320 | H72: 12029 | I72: 50.8 | J72: 46.2 | K72: #N/A | L72: #N/A
A73: =+A69+1 -> 1976 | D73: 19763 | E73: #N/A | F73: #N/A | G73: 34548 | H73: 12744 | I73: 51.4 | J73: 46.7 | K73: #N/A | L73: #N/A
A74: =+A70+1 -> 1976 | C74: 1976 | D74: 19764 | E74: #N/A | F74: #N/A | G74: 36679 | H74: 12843 | I74: 52.3 | J74: 47.5 | K74: #N/A | L74: #N/A
A75: =+A71+1 -> 1977 | B75: 1976 | D75: 19771 | E75: #N/A | F75: #N/A | G75: 38036 | H75: 13650 | I75: 52.6 | J75: 47.7 | K75: 75991 | L75: 69158
A76: =+A72+1 -> 1977 | D76: 19772 | E76: #N/A | F76: #N/A | G76: 39241 | H76: 13432 | I76: 52 | J76: 47 | K76: #N/A | L76: #N/A
A77: =+A73+1 -> 1977 | D77: 19773 | E77: #N/A | F77: #N/A | G77: 40335 | H77: 14052 | I77: 52.2 | J77: 47.2 | K77: #N/A | L77: #N/A
A78: =+A74+1 -> 1977 | C78: 1977 | D78: 19774 | E78: #N/A | F78: #N/A | G78: 42163 | H78: 14415 | I78: 53 | J78: 48 | K78: #N/A | L78: #N/A
A79: =+A75+1 -> 1978 | B79: 1977 | D79: 19781 | E79: #N/A | F79: #N/A | G79: 44136 | H79: 15656 | I79: 53.5 | J79: 48.4 | K79: 86357 | L79: 74692
A80: =+A76+1 -> 1978 | D80: 19782 | E80: #N/A | F80: #N/A | G80: 45901 | H80: 15424 | I80: 53.8 | J80: 48.7 | K80: #N/A | L80: #N/A
A81: =+A77+1 -> 1978 | D81: 19783 | E81: #N/A | F81: #N/A | G81: 47202 | H81: 16062 | I81: 54.5 | J81: 49.3 | K81: #N/A | L81: #N/A
A82: =+A78+1 -> 1978 | C82: 1978 | D82: 19784 | E82: #N/A | F82: #N/A | G82: 48902 | H82: 16711 | I82: 54.7 | J82: 49.4 | K82: #N/A | L82: #N/A
A83: =+A79+1 -> 1979 | B83: 1978 | D83: 19791 | E83: #N/A | F83: #N/A | G83: 50455 | H83: 17874 | I83: 54.2 | J83: 49 | K83: 96731 | L83: 84240
A84: =+A80+1 -> 1979 | D84: 19792 | E84: #N/A | F84: #N/A | G84: 53962 | H84: 18173 | I84: 56.4 | J84: 51 | K84: #N/A | L84: #N/A
A85: =+A81+1 -> 1979 | D85: 19793 | E85: #N/A | F85: #N/A | G85: 56764 | H85: 19068 | I85: 55.3 | J85: 50.1 | K85: #N/A | L85: #N/A
A86: =+A82+1 -> 1979 | C86: 1979 | D86: 19794 | E86: #N/A | F86: #N/A | G86: 59785 | H86: 20021 | I86: 55.5 | J86: 50.5 | K86: #N/A | L86: #N/A
A87: =+A83+1 -> 1980 | B87: 1979 | D87: 19801 | E87: #N/A | F87: #N/A | G87: 62083 | H87: 22229 | I87: 54.9 | J87: 50.1 | K87: 107499 | L87: 94404
A88: =+A84+1 -> 1980 | D88: 19802 | E88: #N/A | F88: #N/A | G88: 63691 | H88: 22146 | I88: 54.3 | J88: 49.8 | K88: #N/A | L88: #N/A
A89: =+A85+1 -> 1980 | D89: 19803 | E89: #N/A | F89: #N/A | G89: 66013 | H89: 23935 | I89: 54.5 | J89: 50.4 | K89: #N/A | L89: #N/A
A90: =+A86+1 -> 1980 | C90: 1980 | D90: 19804 | E90: #N/A | F90: #N/A | G90: 68169 | H90: 24175 | I90: 54.2 | J90: 50.5 | K90: #N/A | L90: #N/A
A91: =+A87+1 -> 1981 | B91: 1980 | D91: 19811 | E91: #N/A | F91: #N/A | G91: 69957 | H91: 26380 | I91: 54.6 | J91: 51.1 | K91: 126222 | L91: 111073
A92: =+A88+1 -> 1981 | D92: 19812 | E92: #N/A | F92: #N/A | G92: 71408 | H92: 26203 | I92: 55.3 | J92: 52 | K92: #N/A | L92: #N/A
A93: =+A89+1 -> 1981 | D93: 19813 | E93: #N/A | F93: #N/A | G93: 73442 | H93: 27949 | I93: 56.3 | J93: 53 | K93: #N/A | L93: #N/A
A94: =+A90+1 -> 1981 | C94: 1981 | D94: 19814 | E94: #N/A | F94: #N/A | G94: 75743 | H94: 26934 | I94: 56.9 | J94: 53.6 | K94: #N/A | L94: #N/A
A95: =+A91+1 -> 1982 | B95: 1981 | D95: 19821 | E95: #N/A | F95: #N/A | G95: 77593 | H95: 29501 | I95: 57.1 | J95: 53.7 | K95: 133648 | L95: 121707
A96: =+A92+1 -> 1982 | D96: 19822 | E96: #N/A | F96: #N/A | G96: 79106 | H96: 28856 | I96: 58 | J96: 54.6 | K96: #N/A | L96: #N/A
A97: =+A93+1 -> 1982 | D97: 19823 | E97: #N/A | F97: #N/A | G97: 80536 | H97: 30155 | I97: 58.5 | J97: 55.1 | K97: #N/A | L97: #N/A
A98: =+A94+1 -> 1982 | C98: 1982 | D98: 19824 | E98: #N/A | F98: #N/A | G98: 82778 | H98: 30212 | I98: 59.2 | J98: 55.8 | K98: #N/A | L98: #N/A
A99: =+A95+1 -> 1983 | B99: 1982 | D99: 19831 | E99: #N/A | F99: #N/A | G99: 85858 | H99: 32213 | I99: 60.8 | J99: 57.4 | K99: 142889 | L99: 129379
A100: =+A96+1 -> 1983 | D100: 19832 | E100: #N/A | F100: #N/A | G100: 86421 | H100: 31312 | I100: 61 | J100: 57.7 | K100: #N/A | L100: #N/A
...

Sheet OBR Agg (per cent of GDP)
A1: https://obr.uk/data/ | C1: Per cent of GDP1
C3: Receipts and expenditure | K3: Deficit | Q3: Fiscal targets | T3: Financing | X3: Other Debt and Deficit measures | AE3: Economic indicators
C4: Public sector current receipts | D4: Total managed expenditure | E4: Public sector current expenditure | F4: Public sector net investment | G4: Depreciation | H4: Public sector gross investment | I4: National account taxes | K4: Cyclically-adjusted current budget deficit | L4: Primary balance | M4: Cyclically-adjusted primary balance | N4: Cyclically-adjusted net borrowing | O4: Public sector net borrowing | Q4: Current budget deficit | R4: Public sector net financial liabilities | T4: Central government net cash requirement | U4: Public sector net cash requirement | V4: Central government debt interest, net of APF | X4: Public sector net debt2 | Y4: Public sector net debt (ex BOE)2 | Z4: Public sector net worth (inverted) | AA4: General government net borrowing | AB4: Cyclically-adjusted general government net borrowing | AC4: General Government Gross Debt | AE4: Nominal GDP (£ billion) | AF4: Nominal GDP, centred end-March (£ billion) | AG4: Output gap (per cent of GDP) | BS4: Forecast
B5: 1948-49 | C5: 42.940919 | D5: 38.599562 | E5: 33.234136 | F5: 2.6345733 | G5: 2.7308534 | H5: 5.3654267 | I5: 37.207877 | K5: - | L5: 7.6936543 | M5: - | N5: - | O5: -4.3413567 | Q5: -6.97593 | T5: -5.9256018 | U5: -4.3413567 | V5: 4.5514223 | X5: - | AA5: -3.7986871 | AB5: - | AC5: - | AE5: 11.425 | AF5: - | AG5: -
B6: 1949-50 | C6: 43.298545 | D6: 38.474813 | E6: 32.780015 | F6: 2.9912072 | G6: 2.7035911 | H6: 5.6947983 | I6: 36.929904 | K6: - | L6: 7.8724628 | M6: - | N6: - | O6: -4.8237324 | Q6: -7.8149396 | T6: -6.5247761 | U6: -4.8237324 | V6: 4.2649355 | X6: - | AA6: -4.2320651 | AB6: - | AC6: - | AE6: 12.169 | AF6: - | AG6: -
B7: 1950-51 | C7: 42.841444 | D7: 39.183673 | E7: 32.629513 | F7: 3.7598116 | G7: 2.7943485 | H7: 6.5541601 | I7: 36.075353 | K7: - | L7: 6.4678179 | M7: - | N7: - | O7: -3.6577708 | Q7: -7.4175824 | T7: -5.8477237 | U7: -3.6577708 | V7: 4.1679749 | X7: - | AA7: -3.2731554 | AB7: - | AC7: - | AE7: 12.74 | AF7: - | AG7: -
B8: 1951-52 | C8: 41.131231 | D8: 40.648815 | E8: 32.300916 | F8: 5.4394183 | G8: 2.9084807 | H8: 8.347899 | I8: 34.782913 | K8: - | L8: 3.4118716 | M8: - | N8: - | O8: -0.48241628 | Q8: -5.9218346 | T8: -2.6847515 | U8: -0.48241628 | V8: 4.0481018 | X8: - | AA8: -0.0069915402 | AB8: - | AC8: - | AE8: 14.303 | AF8: - | AG8: -
B9: 1952-53 | C9: 39.926622 | D9: 41.271885 | E9: 32.537333 | F9: 5.7736869 | G9: 2.9608651 | H9: 8.734552 | I9: 33.953399 | K9: - | L9: 1.911689 | M9: - | N9: - | O9: 1.3452626 | Q9: -4.4284243 | T9: -1.930999 | U9: 1.3452626 | V9: 4.0808445 | X9: - | AA9: 0.99124614 | AB9: - | AC9: - | AE9: 15.536 | AF9: - | AG9: -
B10: 1953-54 | C10: 37.998202 | D10: 40.503446 | E10: 31.603236 | F10: 6.0593347 | G10: 2.840875 | H10: 8.9002098 | I10: 31.705124 | K10: - | L10: 0.45549895 | M10: - | N10: - | O10: 2.5052442 | Q10: -3.5540905 | T10: -0.94695835 | U10: 2.5052442 | V10: 3.9376686 | X10: - | AA10: 1.7620617 | AB10: - | AC10: - | AE10: 16.685 | AF10: - | AG10: -
B11: 1954-55 | C11: 37.46378 | D11: 38.923925 | E11: 31.123232 | F11: 4.965627 | G11: 2.8350662 | H11: 7.8006931 | I11: 30.913016 | K11: - | L11: 1.0794841 | M11: - | N11: - | O11: 1.4601443 | Q11: -3.5054826 | T11: -1.7442191 | U11: 1.4601443 | V11: 3.727061 | X11: - | AA11: 0.64200898 | AB11: - | AC11: - | AE11: 17.601 | AF11: - | AG11: -
B12: 1955-56 | C12: 35.96424 | D12: 35.770115 | E12: 28.664112 | F12: 4.311622 | G12: 2.7943806 | H12: 7.1060026 | I12: 29.644955 | K12: - | L12: 2.7535121 | M12: - | N12: - | O12: -0.19412516 | Q12: -4.5057471 | T12: -2.8403576 | U12: -0.19412516 | V12: 3.7905492 | X12: - | AA12: -0.55172414 | AB12: - | AC12: - | AE12: 19.575 | AF12: - | AG12: -
B13: 1956-57 | C13: 35.569836 | D13: 35.957286 | E13: 28.883954 | F13: 4.2477792 | G13: 2.8255528 | H13: 7.0733321 | I13: 29.247779 | K13: - | L13: 1.8474768 | M13: - | N13: - | O13: 0.38745039 | Q13: -3.8603289 | T13: -1.7955018 | U13: 0.38745039 | V13: 3.4539785 | X13: - | AA13: 0.15120015 | AB13: - | AC13: - | AE13: 21.164 | AF13: 21.812 | AG13: -
B14: 1957-58 | C14: 35.163468 | D14: 35.190121 | E14: 28.375977 | F14: 3.9623312 | G14: 2.8518124 | H14: 6.8141436 | I14: 28.913468 | K14: - | L14: 2.2254797 | M14: - | N14: - | O14: 0.026652452 | Q14: -3.9356787 | T14: -2.0788913 | U14: 0.026652452 | V14: 3.4159559 | X14: - | AA14: -0.43532338 | AB14: - | AC14: - | AE14: 22.512 | AF14: 23.008 | AG14: -
B15: 1958-59 | C15: 35.644201 | D15: 35.948413 | E15: 28.990102 | F15: 4.0747247 | G15: 2.8835854 | H15: 6.9583101 | I15: 29.529971 | K15: - | L15: 2.3394319 | M15: - | N15: - | O15: 0.30421183 | Q15: -3.7705129 | T15: -2.2280303 | U15: 0.30421183 | V15: 3.3977463 | X15: - | AA15: -0.72839453 | AB15: - | AC15: - | AE15: 23.339 | AF15: 23.962 | AG15: -
B16: 1959-60 | C16: 33.652223 | D16: 35.939384 | E16: 29.069861 | F16: 4.1160865 | G16: 2.7534368 | H16: 6.8695233 | I16: 28.426722 | K16: - | L16: 1.4591205 | M16: - | N16: - | O16: 2.2871613 | Q16: -1.8289252 | T16: -1.1335316 | U16: 2.2871613 | V16: 3.2920653 | X16: - | AA16: 0.2291181 | AB16: - | AC16: - | AE16: 24.878 | AF16: 25.796 | AG16: -
B17: 1960-61 | C17: 33.452184 | D17: 35.936796 | E17: 29.151028 | F17: 4.0009008 | G17: 2.7848671 | H17: 6.7857679 | I17: 27.88245 | K17: - | L17: 1.3774208 | M17: - | N17: - | O17: 2.4846119 | Q17: -1.5162888 | T17: -0.79192313 | U17: 2.4846119 | V17: 3.3290797 | X17: - | AA17: 0.63053596 | AB17: - | AC17: - | AE17: 26.644 | AF17: 27.588 | AG17: -
B18: 1961-62 | C18: 35.456709 | D18: 37.623903 | E18: 30.148861 | F18: 4.4018901 | G18: 3.0731517 | H18: 7.4750417 | I18: 29.843323 | K18: - | L18: 1.8048105 | M18: - | N18: - | O18: 2.1671937 | Q18: -2.2346964 | T18: -1.669805 | U18: 2.1671937 | V18: 3.3715849 | X18: - | AA18: 0.1669805 | AB18: - | AC18: - | AE18: 28.147 | AF18: 28.849 | AG18: -
B19: 1962-63 | C19: 35.472044 | D19: 37.298435 | E19: 29.901212 | F19: 4.2706318 | G19: 3.1265913 | H19: 7.3972231 | I19: 29.639814 | K19: - | L19: 1.8671284 | M19: - | N19: - | O19: 1.826391 | Q19: -2.4442408 | T19: -1.3035951 | U19: 2.1930271 | V19: 3.1741182 | X19: - | AA19: 0.22745018 | AB19: - | AC19: - | AE19: 29.457 | AF19: 30.39 | AG19: -
B20: 1963-64 | C20: 34.626828 | D20: 37.3297 | E20: 28.657333 | F20: 5.5341539 | G20: 3.1382129 | H20: 8.6723668 | I20: 28.688653 | K20: - | L20: 0.90513326 | M20: - | N20: - | O20: 2.702872 | Q20: -2.8312819 | T20: 0.94898055 | U20: 3.0974976 | V20: 3.0818378 | X20: - | AA20: 2.4209966 | AB20: - | AC20: - | AE20: 31.929 | AF20: 33.349 | AG20: -
B21: 1964-65 | C21: 35.156609 | D21: 37.023864 | E21: 27.891235 | F21: 6.0119321 | G21: 3.1206976 | H21: 9.1326296 | I21: 29.075838 | K21: - | L21: 1.5460073 | M21: - | N21: - | O21: 1.8672556 | Q21: -4.1446765 | T21: 0.93506196 | U21: 2.6216154 | V21: 2.8281322 | X21: - | AA21: 0.088916934 | AB21: - | AC21: - | AE21: 34.864 | AF21: 36.173 | AG21: -
B22: 1965-66 | C22: 36.94927 | D22: 38.473034 | E22: 29.263737 | F22: 6.0069917 | G22: 3.2023057 | H22: 9.2092974 | I22: 30.683425 | K22: - | L22: 1.7666053 | M22: - | N22: - | O22: 1.5237638 | Q22: -4.4832279 | T22: 1.2515678 | U22: 2.4604382 | V22: 2.7059483 | X22: - | AA22: 1.2195447 | AB22: - | AC22: - | AE22: 37.473 | AF22: 38.766 | AG22: -
B23: 1966-67 | C23: 37.628247 | D23: 40.023022 | E23: 29.923427 | F23: 6.7489115 | G23: 3.3506831 | H23: 10.099595 | I23: 31.382313 | K23: - | L23: 0.95090336 | M23: - | N23: - | O23: 2.394775 | Q23: -4.3541364 | T23: 1.8592663 | U23: 2.9177719 | V23: 2.7901506 | X23: - | AA23: 0.080076072 | AB23: - | AC23: - | AE23: 39.962 | AF23: 41.161 | AG23: -
B24: 1967-68 | C24: 39.075729 | D24: 42.925682 | E24: 31.559266 | F24: 7.9633114 | G24: 3.4031044 | H24: 11.366416 | I24: 32.598777 | K24: - | L24: -0.18344309 | M24: - | N24: - | O24: 3.849953 | Q24: -4.1133584 | T24: 3.2314205 | U24: 4.7530574 | V24: 2.8786453 | X24: - | AA24: 1.4840075 | AB24: - | AC24: - | AE24: 42.52 | AF24: 44.405 | AG24: -
... B28: 1971-72 | C28: 38.364478 | D28: 39.346039 | E28: 30.182224 | F28: 5.3722655 | G28: 3.7915499 | H28: 9.1638154 | I28: 32.060194 | K28: - | L28: 1.9755074 | M28: - | N28: - | O28: 0.9815609 | Q28: -4.3907046 | T28: 0.75552322 | U28: 1.3159728 | V28: 2.3904259 | X28: - | AA28: -0.63011875 | AB28: - | AC28: - | AE28: 64.591 | AF28: 68.145 | AG28: -
B29: 1972-73 | C29: 35.871359 | D29: 38.458522 | E29: 29.801736 | F29: 4.9146628 | G29: 3.7421222 | H29: 8.656785 | I29: 29.824727 | K29: - | L29: 0.14876525 | M29: - | N29: - | O29: 2.5871629 | Q29: -2.3274999 | T29: 2.5804009 | U29: 3.3120554 | V29: 2.334262 | X29: - | AA29: 1.9650537 | AB29: - | AC29: - | AE29: 73.942 | AF29: 79.237 | AG29: 2.5446864
B30: 1973-74 | C30: 36.169468 | D30: 40.251717 | E30: 30.992748 | F30: 5.2430887 | G30: 4.0158801 | H30: 9.2589688 | I30: 29.79088 | K30: - | L30: -1.0510311 | M30: - | N30: - | O30: 4.0822483 | Q30: -1.1608403 | T30: 2.5762933 | U30: 5.2744627 | V30: 2.4339033 | X30: - | AA30: 3.6611118 | AB30: - | AC30: - | AE30: 82.871 | AF30: 88.839 | AG30: 6.5394316
B31: 1974-75 | C31: 39.00827 | D31: 44.703234 | E31: 34.767598 | F31: 5.5259084 | G31: 4.4097279 | H31: 9.9356363 | I31: 32.489409 | K31: - | L31: -2.2965211 | M31: - | N31: - | O31: 5.694965 | Q31: 0.16905654 | T31: 5.1877953 | U31: 8.1340639 | V31: 2.4156754 | X31: 47.746914 | AA31: 3.4330699 | AB31: - | AC31: 54.658221 | AE31: 98.192 | AF31: 109.117 | AG31: 3.1047807
B32: 1975-76 | C32: 40.119493 | D32: 46.450796 | E32: 36.344378 | F32: 5.5608884 | G32: 4.5455298 | H32: 10.106418 | I32: 33.353745 | K32: 0.52283906 | L32: -2.9972527 | M32: -2.749677 | N32: 6.0837275 | O32: 6.3313032 | Q32: 0.77041475 | T32: 7.2432227 | U32: 8.5076628 | V32: 2.5727384 | X32: 49.330944 | AA32: 4.212042 | AB32: 3.9644663 | AC32: 54.316309 | AE32: 120.844 | AF32: 131.155 | AG32: -1.7370637
B33: 1976-77 | C33: 40.210597 | D33: 45.140492 | E33: 36.084521 | F33: 4.5040543 | G33: 4.5519173 | H33: 9.0559716 | I33: 32.76015 | K33: -0.24139334 | L33: -1.3070837 | M33: -0.63984998 | N33: 4.2626609 | O33: 4.9298947 | Q33: 0.42584042 | T33: 4.1098879 | U33: 5.8040993 | V33: 2.8710795 | X33: 47.792828 | AA33: 3.6178839 | AB33: 2.9506501 | AC33: 53.487668 | AE33: 142.072 | AF33: 153.998 | AG33: -0.63964205
B34: 1977-78 | C34: 38.388917 | D34: 42.256769 | E34: 34.653525 | F34: 3.1507583 | G34: 4.4524857 | H34: 7.6032441 | I34: 31.619573 | K34: 0.35463006 | L34: -0.32272243 | M34: 0.039741564 | N34: 3.5053884 | O34: 3.8678524 | Q34: 0.71709405 | T34: 2.8165961 | U34: 3.3524599 | V34: 2.9544757 | X34: 44.324511 | AA34: 3.2206013 | AB34: 2.8581373 | AC34: 51.995039 | AE34: 166.087 | AF34: 179.359 | AG34: -0.46907117
B35: 1978-79 | C35: 36.905288 | D35: 41.420706 | E35: 34.35097 | F35: 2.7258879 | G35: 4.3438476 | H35: 7.0697355 | I35: 30.379378 | K35: 2.4763795 | L35: -1.0538575 | M35: -1.7407069 | N35: 5.2022674 | O35: 4.5154179 | Q35: 1.7895301 | T35: 4.0319017 | U35: 4.694267 | V35: 3.0445927 | X35: 42.182642 | AA35: 3.764148 | AB35: 4.4509975 | AC35: 50.29141 | AE35: 192.341 | AF35: 210.039 | AG35: 1.5613273
B36: 1979-80 | C36: 37.271293 | D36: 40.946091 | E36: 34.181297 | F36: 2.5266924 | G36: 4.2381008 | H36: 6.7647931 | I36: 31.193643 | K36: 1.4113888 | L36: -0.069660341 | M36: -0.33294351 | N36: 3.9380812 | O36: 3.674798 | Q36: 1.1481056 | T36: 3.467537 | U36: 4.1809105 | V36: 3.262426 | X36: 39.083022 | AA36: 2.6109728 | AB36: 2.874256 | AC36: 46.224797 | AE36: 232.557 | AF36: 251.26 | AG36: -0.097964602
B37: 1980-81 | C37: 38.491785 | D37: 42.803908 | E37: 36.119126 | F37: 2.249316 | G37: 4.4354658 | H37: 6.6847818 | I37: 32.109379 | K37: 0.63491141 | L37: -0.55653565 | M37: 0.87136036 | N37: 2.8842274 | O37: 4.3121234 | Q37: 2.0628074 | T37: 4.6709376 | U37: 4.5849717 | V37: 3.424806 | X37: 40.295738 | AA37: 3.3463154 | AB37: 1.9184194 | AC37: 47.177329 | AE37: 267.548 | AF37: 282.412 | AG37: -2.8166062
B38: 1981-82 | C38: 40.812214 | D38: 42.820321 | E38: 37.017932 | F38: 1.4621459 | G38: 4.3402435 | H38: 5.8023894 | I38: 33.969452 | K38: -1.5988648 | L38: 1.9234181 | M38: 4.0682444 | N38: -0.13671892 | O38: 2.0081074 | Q38: 0.54596152 | T38: 2.5557426 | U38: 2.9028684 | V38: 3.7598037 | X38: 39.957999 | AA38: 2.7843703 | AB38: 0.63954397 | AC38: 44.737379 | AE38: 298.739 | AF38: 313.329 | AG38: -3.1630102
B39: 1982-83 | C39: 40.523009 | D39: 43.127992 | E39: 37.033332 | F39: 1.9325425 | G39: 4.1621177 | H39: 6.0946601 | I39: 33.674179 | K39: -1.3162769 | L39: 1.0265012 | M39: 3.0152187 | N39: 0.61626556 | O39: 2.6049831 | Q39: 0.67244061 | T39: 3.9093044 | U39: 2.7440456 | V39: 3.6860724 | X39: 38.603289 | AA39: 2.6546918 | AB39: 0.66597433 | AC39: 43.575676 | AE39: 327.91 | AF39: 343.235 | AG39: -2.7122309
B40: 1983-84 | C40: 39.415409 | D40: 42.706138 | E40: 36.534 | F40: 2.1832235 | G40: 3.9889138 | H40: 6.1721373 | I40: 32.988144 | K40: -0.17906419 | L40: 0.16199909 | M40: 1.4485682 | N40: 2.0041593 | O40: 3.2907284 | Q40: 1.1075049 | T40: 3.4262388 | U40: 2.7311206 | V40: 3.6875007 | X40: 38.75446 | AA40: 3.2790176 | AB40: 1.9924485 | AC40: 43.259611 | AE40: 358.644 | AF40: 370.538 | AG40: -1.4882459
B41: 1984-85 | C41: 39.140924 | D41: 42.382304 | E41: 36.672459 | F41: 1.9311229 | G41: 3.7787225 | H41: 5.7098454 | I41: 33.550804 | K41: 0.82633749 | L41: 0.36719263 | M41: 0.85111222 | N41: 2.7574604 | O41: 3.24138 | Q41: 1.3102571 | T41: 2.6567163 | U41: 2.6528375 | V41: 3.8063912 | X41: 38.614312 | AA41: 2.8591894 | AB41: 2.3752698 | AC41: 43.049974 | AE41: 386.718 | AF41: 406.585 | AG41: -0.37254084
B42: 1985-86 | C42: 38.214948 | D42: 40.342803 | E42: 35.462916 | F42: 1.4911944 | G42: 3.3886927 | H42: 4.8798871 | I42: 32.640222 | K42: 0.62058835 | L42: 1.3074743 | M42: 1.3235466 | N42: 2.1117827 | O42: 2.127855 | Q42: 0.63666063 | T42: 2.6177752 | U42: 1.3517556 | V42: 3.910175 | X42: 37.005577 | AA42: 2.2727112 | AB42: 2.2566389 | AC42: 42.228053 | AE42: 424.559 | AF42: 439.123 | AG42: 0.11687178
B43: 1986-87 | C43: 37.312392 | D43: 39.228198 | E43: 34.820749 | F43: 0.93883232 | G43: 3.4686161 | H43: 4.4074484 | I43: 32.436953 | K43: 1.1301814 | L43: 1.354435 | M43: 1.2012266 | N43: 2.0690137 | O43: 1.9158054 | Q43: 0.97697307 | T43: 2.2869105 | U43: 0.8081893 | V43: 3.8053068 | X43: 34.78095 | AA43: 2.1293059 | AB43: 2.2825142 | AC43: 41.797876 | AE43: 456.205 | AF43: 482.448 | AG43: 0.25966798
... B55: 1998-99 | C55: 34.976304 | D55: 34.988433 | E55: 32.192747 | F55: 0.6339624 | G55: 2.161724 | H55: 2.7956864 | I55: 31.670115 | K55: 0.081511777 | L55: 2.4560743 | M55: 1.7527291 | N55: 0.71547417 | O55: 0.012129005 | Q55: -0.62183339 | T55: -0.44818154 | U55: -0.75811214 | V55: 2.9032697 | X55: 35.061394 | AA55: -0.12553027 | AB55: 0.5778149 | AC55: 40.934998 | AE55: 1014.098 | AF55: 1035.612 | AG55: 0.92235761
B56: 1999-00 | C56: 35.676214 | D56: 34.601446 | E56: 31.865467 | F56: 0.56269104 | G56: 2.1732881 | H56: 2.7359791 | I56: 32.453512 | K56: -1.0157392 | L56: 3.1587043 | M56: 2.5369843 | N56: -0.45304819 | O56: -1.0747682 | Q56: -1.6374592 | R56: 27.438863 | T56: -0.86119062 | U56: -0.8256572 | V56: 2.4410612 | X56: 32.350606 | Y56: 32.45133 | Z56: 30.581899 | AA56: -1.0636463 | AB56: -0.44192632 | AC56: 38.486088 | AE56: 1060.973 | AF56: 1092.097 | AG56: 0.87449691
B57: 2000-01 | C57: 36.363636 | D57: 34.905734 | E57: 32.25549 | F57: 0.49765889 | G57: 2.152585 | H57: 2.6502439 | I57: 32.970036 | K57: -1.1454678 | L57: 3.3611212 | M57: 2.5510276 | N57: -0.64780895 | O57: -1.4579025 | Q57: -1.9555614 | R57: 26.86782 | T57: -3.1825295 | U57: -3.4025481 | V57: 2.4060671 | X57: 28.208053 | Y57: 28.313176 | Z57: 30.810727 | AA57: -1.3889175 | AB57: -0.57882388 | AC57: 35.643633 | AE57: 1117.633 | AF57: 1141.518 | AG57: 1.2703884
B58: 2001-02 | C58: 35.565396 | D58: 36.051432 | E58: 32.703683 | F58: 1.1589491 | G58: 2.1888003 | H58: 3.3477494 | I58: 32.298538 | K58: -0.069301116 | L58: 1.203534 | M58: 0.59992198 | N58: 1.089648 | O58: 0.48603595 | Q58: -0.67291315 | R58: 28.243999 | T58: 0.2389648 | U58: 0.34451981 | V58: 1.9847618 | X58: 27.978349 | Y58: 28.079903 | Z58: 32.317531 | AA58: 0.42635943 | AB58: 1.0299715 | AC58: 34.292786 | AE58: 1159.585 | AF58: 1181.628 | AG58: 0.69906871
B59: 2002-03 | C59: 34.523355 | D59: 37.416808 | E59: 33.665607 | F59: 1.5253531 | G59: 2.2258471 | H59: 3.7512003 | I59: 31.414722 | K59: 1.5446932 | L59: -1.2443953 | M59: -1.4209891 | N59: 3.0700463 | O59: 2.8934525 | Q59: 1.3680994 | R59: 31.277551 | T59: 1.7973864 | U59: 1.9321636 | V59: 1.7971385 | X59: 29.731083 | Y59: 29.819665 | Z59: 34.975415 | AA59: 2.5143247 | AB59: 2.6909185 | AC59: 34.872239 | AE59: 1210.146 | AF59: 1241.798 | AG59: 0.073560053
B60: 2003-04 | C60: 35.290945 | D60: 38.697583 | E60: 34.823661 | F60: 1.6983486 | G60: 2.1755738 | H60: 3.8739224 | I60: 32.224791 | K60: 1.9149205 | L60: -1.6534987 | M60: -1.86013 | N60: 3.6132691 | O60: 3.4066378 | Q60: 1.7082892 | R60: 31.177818 | T60: 3.0832174 | U60: 3.129711 | V60: 1.8175571 | X60: 30.83373 | Y60: 30.940448 | Z60: 35.080629 | AA60: 2.9360658 | AB60: 3.1426971 | AC60: 36.605917 | AE60: 1277.594 | AF60: 1311.875 | AG60: 0.38383864
B61: 2004-05 | C61: 35.888956 | D61: 39.725954 | E61: 35.507053 | F61: 2.0426064 | G61: 2.1762946 | H61: 4.218901 | I61: 32.840123 | K61: 2.1125805 | L61: -2.0399327 | M61: -2.358121 | N61: 4.1551869 | O61: 3.8369985 | Q61: 1.7943921 | R61: 33.265384 | T61: 3.0533631 | U61: 3.1464249 | V61: 1.9225099 | X61: 33.352582 | Y61: 33.461128 | Z61: 34.612223 | AA61: 3.3078905 | AB61: 3.6260789 | AC61: 39.038277 | AE61: 1346.417 | AF61: 1381.902 | AG61: 0.48284129
B62: 2005-06 | C62: 36.509111 | D62: 39.696408 | E62: 35.629202 | F62: 1.8542285 | G62: 2.2129778 | H62: 4.0672063 | I62: 33.238571 | K62: 1.5886088 | L62: -1.403667 | M62: -1.6592066 | N62: 3.4428373 | O62: 3.1872977 | Q62: 1.3330692 | R62: 32.261952 | T62: 3.0234125 | U62: 3.0234125 | V62: 1.952644 | X62: 34.17671 | Y62: 34.327268 | Z62: 32.206861 | AA62: 2.9476867 | AB62: 3.2032262 | AC62: 40.373796 | AE62: 1423.557 | AF62: 1461.229 | AG62: 0.31794263
B63: 2006-07 | C63: 36.928035 | D63: 39.669208 | E63: 35.6151 | F63: 1.8131197 | G63: 2.2409886 | H63: 4.0541083 | I63: 33.635453 | K63: 0.99556806 | L63: -0.86953145 | M63: -0.93704576 | N63: 2.8086878 | O63: 2.7411734 | Q63: 0.92805374 | R63: 32.284344 | T63: 2.5070843 | U63: 2.3941242 | V63: 2.0598642 | X63: 34.930781 | Y63: 35.061315 | Z63: 31.962774 | AA63: 2.5810741 | AB63: 2.6485885 | AC63: 41.382157 | AE63: 1493.448 | AF63: 1532.173 | AG63: 0.0078515864
B64: 2007-08 | C64: 37.16114 | D64: 40.027304 | E64: 35.959812 | F64: 1.8213314 | G64: 2.2461603 | H64: 4.0674917 | I64: 33.642975 | K64: 1.3883603 | L64: -1.0932442 | M64: -1.4367723 | N64: 3.2096917 | O64: 2.8661636 | Q64: 1.0448322 | R64: 34.069041 | T64: 2.1160652 | U64: 1.8526942 | V64: 2.1438018 | X64: 35.467024 | Y64: 35.598337 | Z64: 35.002114 | AA64: 2.8765967 | AB64: 3.2201248 | AC64: 42.109207 | AE64: 1571.927 | AF64: 1599.232 | AG64: 0.6839156
B65: 2008-09 | C65: 35.742911 | D65: 43.041938 | E65: 37.592444 | F65: 3.0475746 | G65: 2.4019201 | H65: 5.4494947 | I65: 32.022065 | K65: 3.9060075 | L65: -5.3773159 | M65: -5.0318703 | N65: 6.9535821 | O65: 7.2990277 | Q65: 4.2514531 | R65: 47.209227 | T65: 10.282583 | U65: 10.915308 | V65: 2.1037277 | X65: 50.243495 | Y65: 50.275407 | Z65: 46.523165 | AA65: 6.7112417 | AB65: 6.3657961 | AC65: 53.186754 | AE65: 1593.267 | AF65: 1566.77 | AG65: -0.96445749
B66: 2009-10 | C66: 35.780023 | D66: 45.967442 | E66: 40.368395 | F66: 3.0444077 | G66: 2.5546402 | H66: 5.5990479 | I66: 32.152871 | K66: 5.3939189 | L66: -8.1880835 | M66: -6.4389903 | N66: 8.4383266 | O66: 10.18742 | Q66: 7.1430121 | R66: 54.332474 | T66: 12.672823 | U66: 12.812255 | V66: 1.790539 | X66: 64.385479 | Y66: 63.602505 | Z66: 53.366222 | AA66: 9.9660513 | AB66: 8.2169581 | AC66: 70.342742 | AE66: 1567.07 | AF66: 1596.478 | AG66: -3.1124034
B67: 2010-11 | C67: 36.807363 | D67: 45.502246 | E67: 40.497794 | F67: 2.5055024 | G67: 2.4989497 | H67: 5.0044521 | I67: 33.122505 | K67: 4.3738952 | L67: -6.126977 | M67: -4.3114919 | N67: 6.8793976 | O67: 8.6948827 | Q67: 6.1893803 | R67: 58.625818 | T67: 8.2069243 | U67: 7.7188434 | V67: 2.5110752 | X67: 70.622886 | Y67: 70.344914 | Z67: 47.359936 | AA67: 8.7660433 | AB67: 6.9505582 | AC67: 75.976376 | AE67: 1632.926 | AF67: 1654.846 | AG67: -2.3860088
... B76: 2019-20 | C76: 36.516732 | D76: 39.095644 | E76: 34.9142 | F76: 1.8742072 | G76: 2.3072366 | H76: 4.1814438 | I76: 32.851954 | K76: 1.0566881 | L76: -1.2128445 | M76: -1.5648271 | N76: 2.9308953 | O76: 2.5789127 | Q76: 0.70470544 | R76: 73.780819 | T76: 2.4775588 | U76: 1.1509453 | V76: 1.7312779 | X76: 84.499793 | Y76: 76.477013 | Z76: 61.601969 | AA76: 2.847982 | AB76: 3.1999646 | AC76: 83.8998 | AE76: 2263.357 | AF76: 2148.881 | AG76: 0.55236491
B77: 2020-21 | C77: 37.530261 | D77: 52.268393 | E77: 46.335396 | F77: 3.4057884 | G77: 2.5272086 | H77: 5.932997 | I77: 33.716841 | K77: 11.299081 | L77: -13.7396 | M77: -13.706336 | N77: 14.704869 | O77: 14.738132 | Q77: 11.332344 | R77: 81.859105 | T77: 16.018182 | U77: 15.74894 | V77: 1.194552 | X77: 95.381028 | Y77: 85.42734 | Z77: 67.716591 | AA77: 14.986284 | AB77: 14.953021 | AC77: 106.37243 | AE77: 2109.996 | AF77: 2259.464 | AG77: -0.28747247 | BS77: 60
B78: 2021-22 | C78: 38.354015 | D78: 43.362351 | E78: 38.862722 | F78: 2.2016349 | G78: 2.2979939 | H78: 4.4996288 | I78: 34.668251 | K78: 3.639914 | L78: -2.9799642 | M78: -3.813177 | N78: 5.8415489 | O78: 5.0083361 | Q78: 2.8067012 | R78: 78.541644 | T78: 5.3656935 | U78: 3.2630006 | V78: 2.3068674 | X78: 94.313911 | Y78: 81.22532 | Z78: 61.819306 | AA78: 5.6263586 | AB78: 6.4595714 | AC78: 99.373187 | AE78: 2400.398 | AF78: 2524.336 | AG78: 1.7814146 | BS78: 60
B79: 2022-23 | C79: 39.224837 | D79: 44.059452 | E79: 39.981688 | F79: 1.7722872 | G79: 2.3054766 | H79: 4.0777638 | I79: 35.193764 | K79: 3.9328002 | L79: -1.174983 | M79: -2.0454555 | N79: 5.7050874 | O79: 4.8346149 | Q79: 3.0623277 | R79: 79.012219 | T79: 4.2273271 | U79: 1.6546105 | V79: 4.2557973 | X79: 93.21417 | Y79: 82.49573 | Z79: 63.940306 | AA79: 5.2398403 | AB79: 6.1103129 | AC79: 96.336344 | AE79: 2634.336 | AF79: 2730.808 | AG79: 1.0283793 | BS79: 60
B80: 2023-24 | C80: 39.272494 | D80: 44.110167 | E80: 39.330448 | F80: 2.4399283 | G80: 2.3397908 | H80: 4.779719 | I80: 34.915259 | K80: 2.6079329 | L80: -1.8664136 | M80: -2.0766021 | N80: 5.0478612 | O80: 4.8376726 | Q80: 2.3977444 | R80: 79.5 | T80: 5.6412096 | U80: 2.1949247 | V80: 3.8557232 | X80: 94.1 | Y80: 85.7 | Z80: 64.125827 | AA80: 5.7498054 | AB80: 5.9599939 | AC80: 98.050509 | AE80: 2790.164 | AF80: 2853.401 | AG80: 0.0090254017 | BS80: 60
B81: 2024-25 | C81: 38.792992 | D81: 43.966291 | E81: 39.038279 | F81: 2.5811643 | G81: 2.3468475 | H81: 4.9280118 | I81: 34.525926 | K81: 2.3887427 | L81: -2.3739653 | M81: -2.1705739 | N81: 4.969907 | O81: 5.1732984 | Q81: 2.5921341 | R81: 81 | T81: 6.14 | U81: 2.4828793 | V81: 3.6183518 | X81: 93.2 | Y81: 87.7 | Z81: 62.853729 | AA81: 5.8074323 | AB81: 5.604041 | AC81: 99.628255 | AE81: 2935.342 | AF81: 3008.092 | AG81: -0.41039288 | BS81: 60
B82: 2025-26 | C82: 40.291114 | D82: 44.613288 | E82: 39.590743 | F82: 2.6568861 | G82: 2.3656595 | H82: 5.0225457 | I82: 36.137796 | K82: 1.1796826 | L82: -1.4158012 | M82: -0.93019541 | N82: 3.8365687 | O82: 4.3221745 | Q82: 1.6652884 | R82: 83.3 | T82: 4.4066682 | U82: 1.2444568 | V82: 3.5973817 | X82: 93.8 | Y82: 89.90771 | Z82: 64.224238 | AA82: 4.6211597 | AB82: 4.1355539 | AC82: 101.53535 | AE82: 3054.6661 | AF82: 3098.6219 | AG82: -0.80705446 | BS82: 60
B83: 2026-27 | C83: 41.206161 | D83: 44.855299 | E83: 39.830485 | F83: 2.5771801 | G83: 2.4476333 | H83: 5.0248134 | I83: 36.995843 | K83: 0.52131888 | L83: -0.83555771 | M83: -0.28491887 | N83: 3.098499 | O83: 3.6491378 | Q83: 1.0719577 | R83: 82.64445 | T83: 4.3681474 | U83: 3.6272637 | V83: 3.4564942 | X83: 94.814987 | Y83: 92.262918 | Z83: 63.661662 | AA83: 4.1016951 | AB83: 3.5510563 | AC83: 103.27016 | AE83: 3164.0741 | AF83: 3220.0205 | AG83: -0.7784559
B84: 2027-28 | C84: 41.971437 | D84: 44.9152 | E84: 39.645298 | F84: 2.804628 | G84: 2.4652735 | H84: 5.2699015 | I84: 37.722211 | K84: -0.22471223 | L84: -0.046860748 | M84: 0.31698664 | N84: 2.5799158 | O84: 2.9437631 | Q84: 0.13913515 | R84: 82.946466 | T84: 4.2446547 | U84: 4.3232376 | V84: 3.5614507 | X84: 95.738708 | Y84: 93.53426 | Z84: 63.301025 | AA84: 3.5409483 | AB84: 3.1771009 | AC84: 104.17207 | AE84: 3277.0085 | AF84: 3333.452 | AG84: -0.41631241
B85: 2028-29 | C85: 42.097056 | D85: 44.633773 | E85: 39.5219 | F85: 2.6336952 | G85: 2.4781778 | H85: 5.111873 | I85: 37.845834 | K85: -0.25264401 | L85: 0.52042929 | M85: 0.67609489 | N85: 2.3810512 | O85: 2.5367168 | Q85: -0.096978404 | R85: 82.931146 | T85: 4.1208939 | U85: 4.1284497 | V85: 3.713642 | X85: 96.281069 | Y85: 94.466418 | Z85: 62.895701 | AA85: 3.1950264 | AB85: 3.0393608 | AC85: 104.82589 | AE85: 3390.8253 | AF85: 3447.6246 | AG85: -0.14480624
B86: 2029-30 | C86: 42.545799 | D86: 44.353876 | E86: 39.393508 | F86: 2.4800413 | G86: 2.4803264 | H86: 4.9603677 | I86: 38.289421 | K86: -0.72135905 | L86: 1.3662156 | M86: 1.4156102 | N86: 1.7586823 | O86: 1.8080768 | Q86: -0.6719645 | R86: 82.172651 | T86: 2.6955001 | U86: 2.679325 | V86: 3.8413616 | X86: 96.065091 | Y86: 94.536821 | Z86: 61.716741 | AA86: 2.3815303 | AB86: 2.3321358 | AC86: 104.73413 | AE86: 3506.6786 | AF86: 3567.5284 | AG86: -0.04086661
B87: 2030-31 | C87: 42.719068 | D87: 44.344141 | E87: 39.402011 | F87: 2.4591801 | G87: 2.4829498 | H87: 4.94213 | I87: 38.462436 | K87: -0.84476636 | L87: 1.482855 | M87: 1.4935142 | N87: 1.6144138 | O87: 1.625073 | Q87: -0.83410717 | R87: 81.133774 | T87: 2.9294329 | U87: 2.470906 | V87: 3.7752691 | X87: 95.050964 | Y87: 94.298884 | Z87: 59.632673 | AA87: 2.2671985 | AB87: 2.2565393 | AC87: 104.32603 | AE87: 3631.8315 | AF87: 3696.6443 | AG87: -0.0049717367
B88: Notes: | C88: 1 Outturn data presented as a per cent of GDP is consistent with the latest available ONS GDP data (Quarterly National Accounts published 31st March 2026).
C89: 2 Debt at end March; GDP centred on end-March.
C90: Outturn fiscal data consistent with the ONS/HM Treasury Public Sector Finances Statistical Bulletin released on 23 April 2026.
C91: Forecast years from 2026-27 are consistent with the OBR Economic and fiscal outlook forecast published March 2026.
C92: A full list of sources is available in the glossary.
C93: Cyclically adjusted aggregates are OBR estimates based on internal calculations of the size of the output gap. For more information see Working paper No. 3: Cyclically-adjusting the public finances (https://obr.uk/download/working-paper-no-3-cyclically-adjusting-the-public-finances/)

Sheet OBR_MAR26_C4.6
A1: Back to contents
B2: Chart 4.6: Debt interest spending relative to GDP and revenue
B25: Date | C25: March 2026 forecast (per cent of GDP) | D25: March 2026 forecast (per cent of revenue) | E25: November 2025 forecast (per cent of GDP) | F25: November 2025 forecast (per cent of revenue)
B26: 1956-57 | C26: 9.7104145 | D26: 3.4539785
B27: 1957-58 | C27: 9.7145023 | D27: 3.4159559
B28: 1958-59 | C28: 9.5323957 | D28: 3.3977463
B29: 1959-60 | C29: 9.7826087 | D29: 3.2920653
B30: 1960-61 | C30: 9.9517559 | D30: 3.3290797
B31: 1961-62 | C31: 9.509018 | D31: 3.3715849
B32: 1962-63 | C32: 8.9482247 | D32: 3.1741182
B33: 1963-64 | C33: 8.9001447 | D33: 3.0818378
B34: 1964-65 | C34: 8.0443828 | D34: 2.8281322
B35: 1965-66 | C35: 7.3234147 | D35: 2.7059483
B36: 1966-67 | C36: 7.4150429 | D36: 2.7901506
B37: 1967-68 | C37: 7.3668372 | D37: 2.8786453
... B91: 2021-22 | C91: 5.9485648 | D91: 2.28133
B92: 2022-23 | C92: 10.80109 | D92: 4.2373866 | E92: 10.80109 | F92: 4.2373866
B93: 2023-24 | C93: 9.8133907 | D93: 3.8550287 | E93: 9.8133907 | F93: 3.8550287
B94: 2024-25 | C94: 9.2792728 | D94: 3.6022235 | E94: 9.638968 | F94: 3.7497719
B95: 2025-26 | C95: 8.879279 | D95: 3.5906242 | E95: 9.2294927 | F95: 3.7353375
B96: 2026-27 | C96: 8.3882946 | D96: 3.4564942 | E96: 8.6874927 | F96: 3.5786943
B97: 2027-28 | C97: 8.4854151 | D97: 3.5614507 | E97: 8.6602243 | F97: 3.6207294
B98: 2028-29 | C98: 8.8216193 | D98: 3.713642 | E98: 8.9887482 | F98: 3.7688342
B99: 2029-30 | C99: 9.0287683 | D99: 3.8413616 | E99: 9.2080564 | F99: 3.8979093
B100: 2030-31 | C100: 8.8374331 | D100: 3.7752691 | E100: 9.1179543 | F100: 3.8690365

Sheet Foreign Share of Govt Debt (%)
A1: G7 Nations: Foreign Holdings as a Share of Central Government Debt (%)
A2: Sources: US Treasury TIC / FRED (US); UK DMO/ONS (UK); Deutsche Bundesbank / ECB SHS (Germany); Agence France Trésor / ECB SHS (France); Bank of Italy / ECB SHS (Italy); Statistics Canada / Bank of Canada (Canada); Bank of Japan Flow of Funds / MoF (Japan). Data are annual, generally end-year (Q4). See 'Notes & Sources' sheet for full methodology.
A4: Year | B4: United States | C4: United Kingdom | D4: Germany | E4: France | F4: Italy | G4: Canada | H4: Japan
A5: 1970 | B5: 5
A6: 1971 | B6: 5.8
A7: 1972 | B7: 6.9
A8: 1973 | B8: 8.8
A9: 1974 | B9: 10.1
A10: 1975 | B10: 12
A11: 1976 | B11: 13.5
A12: 1977 | B12: 15
A13: 1978 | B13: 17.6
A14: 1979 | B14: 18.8
A15: 1980 | B15: 17.2
A16: 1981 | B16: 14.5
... A34: 1999 | B34: 26.5
A35: 2000 | B35: 29.6 | C35: 19 | D35: 33 | E35: 36 | F35: 38 | G35: 26 | H35: 4.5
A36: 2001 | B36: 30.4 | C36: 19.5 | D36: 37 | E36: 40 | F36: 40 | G36: 24 | H36: 4.8
A37: 2002 | B37: 31.3 | C37: 20.5 | D37: 42 | E37: 44 | F37: 43 | G37: 22 | H37: 4.5
A38: 2003 | B38: 34.2 | C38: 22 | D38: 46 | E38: 49 | F38: 44 | G38: 20 | H38: 3.9
A39: 2004 | B39: 37.4 | C39: 24 | D39: 49 | E39: 52 | F39: 46 | G39: 19 | H39: 4.2
A40: 2005 | B40: 39.2 | C40: 25.8 | D40: 52 | E40: 56 | F40: 47 | G40: 19 | H40: 4.8
A41: 2006 | B41: 43 | C41: 28 | D41: 54 | E41: 59 | F41: 47 | G41: 20 | H41: 5.8
A42: 2007 | B42: 47 | C42: 30.2 | D42: 57 | E42: 63 | F42: 47 | G42: 22 | H42: 6.8
A43: 2008 | B43: 50.2 | C43: 31.5 | D43: 55 | E43: 63 | F43: 43 | G43: 25 | H43: 6.2
A44: 2009 | B44: 46.3 | C44: 30.1 | D44: 52 | E44: 64 | F44: 40 | G44: 26.5 | H44: 5.5
A45: 2010 | B45: 45.9 | C45: 28.8 | D45: 53 | E45: 65 | F45: 40 | G45: 27 | H45: 5.9
A46: 2011 | B46: 46.4 | C46: 28.3 | D46: 54 | E46: 62 | F46: 33 | G46: 27.5 | H46: 6.5
... A59: 2024 | B59: 30.4 | C59: 31 | D59: 51.5 | E59: 49 | F59: 27 | G59: 27.5 | H59: 14.5
A60: 2025 | B60: 31
A62: Notes & Sources
A65: COVERAGE
A66: Series: | B66: Annual, end-year (Q4 where available). Generally refers to outstanding marketable central/general government debt held by non-residents.
A67: Start date: | B67: US: 1970 (FRED). All other G7: 2000 (consistent national source data).
A68: End date: | B68: 2025 (US); 2024 (all others). Data for 2024-2025 may be preliminary.
A70: DATA SOURCES BY COUNTRY
A71: United States | B71: Foreign share of publicly held federal debt. Primary source: US Treasury TIC data (ticdata.treasury.gov) and FRED series FDHBFIN. Supplemented by CRS Report RS22331 (updated April 2026). Long series (1945-2025) confirmed via EveryCRSReport.com. Peak of ~56.5% in 2008 (CRS); 31% Dec 2025. | C71: https://fred.stlouisfed.org/series/FDHBFIN | https://ticdata.treasury.gov | https://www.congress.gov/crs-product/RS22331
A72: United Kingdom | B72: Overseas holdings of gilts as % of total gilt market value. Source: UK Debt Management Office (DMO) Quarterly Reviews and Annual Reviews; data compiled from ONS/Bank of England gilt holder statistics. Published quarterly. | C72: https://www.dmo.gov.uk/data/gilt-market/ownership-of-gilts/
A73: Germany | B73: Foreign ownership of German general government bonds (Bunds). Source: Deutsche Bundesbank portfolio investment statistics; ECB Securities Holdings Statistics (SHS) from 2013. Pre-2013 estimates from Bundesbank annual reports and academic literature. | C73: https://www.bundesbank.de/en/statistics | https://www.ecb.europa.eu/stats/financial_markets_and_interest_rates/securities_holdings/
A74: France | B74: Foreign ownership of OATs and other central government securities. Source: Agence France Trésor (AFT) annual reports; ECB SHS from 2013. France historically had among highest foreign ownership in the euro area (~63% in 2009-10), declining as ECB became major buyer under QE. | C74: https://www.aft.gouv.fr/en/statistics | https://www.ecb.europa.eu/stats/
A75: Italy | B75: Foreign ownership of BTPs and other central government securities. Source: Bank of Italy, Banca d'Italia Supplementi al Bollettino Statistico; ECB SHS from 2013. Sharp decline during 2011-12 sovereign crisis (47% to ~28%); partial recovery thereafter. | C75: https://www.bancaditalia.it/pubblicazioni/supplementi/ | https://www.ecb.europa.eu/stats/
A76: Canada | B76: Foreign holdings of federal government marketable bonds. Source: Statistics Canada National Balance Sheet Accounts (Table 36-10-0580-01); Bank of Canada Financial System Review. | C76: https://www150.statcan.gc.ca/t1/tbl1/en/tv.action?pid=3610058001
A77: Japan | B77: Foreign ownership of Japanese Government Bonds (JGBs), including FILP bonds and T-bills. Source: Bank of Japan Flow of Funds (www.boj.or.jp/en/statistics/sj/). Historically very low (<5% pre-2010) due to domestic institutional demand; rose to ~13-15% by 2020s. Ministry of Finance also publishes holder data. | C77: https://www.boj.or.jp/en/statistics/sj/index.htm
A79: CROSS-COUNTRY SOURCES
A80: IMF QEDS | B80: The IMF/World Bank Quarterly External Debt Statistics (SDDS) database covers general government external debt from 1998Q1. The QEDS database is accessible via World Bank DataBank at databank.worldbank.org. For G7 SDDS subscribers, Table 1 provides gross external debt by sector. Note: QEDS measures EXTERNAL (foreign-held) debt; to convert to a share requires dividing by total marketable government debt from national sources. | C80: https://databank.worldbank.org/source/quarterly-external-debt-statistics-sdds | https://www.worldbank.org/en/programs/debt-statistics/qeds
A81: OECD Global Debt Report 2026 | B81: Chapter 3 (Investor Base) provides cross-country data on foreign holdings. As of 2025: US 34%, Euro area 26%, Japan (BoJ dominant at 39% share). Available: https://doi.org/10.1787/e9d80efd-en | C81: https://www.oecd.org/en/publications/global-debt-report-2026_e9d80efd-en.html
A82: ECB Securities Holdings Statistics (SHS) | B82: Country-level data on euro area government bond holders from 2013. Best source for Germany, France, Italy cross-referenced data. | C82: https://www.ecb.europa.eu/stats/financial_markets_and_interest_rates/securities_holdings/
A84: METHODOLOGICAL NOTES
A85: Concept: | B85: Data represent the share of central/general government MARKETABLE debt (bonds, notes, bills) held by NON-RESIDENTS. Definitions vary slightly: US uses 'publicly held debt' (excludes intragovernmental); UK uses total gilt market; Japan includes FILP bonds and T-bills. Some series are nominal value; others market value.
A86: Comparability: | B86: Cross-country comparisons should be treated with caution. The 'foreign' category in national statistics typically corresponds to BPM6 'non-resident' holders. The ECB/Eurosystem's holdings of euro area sovereign bonds are treated differently across national sources — some include ECB QE holdings in 'domestic' (Eurosystem), others do not.
A87: Estimation: | B87: Where exact data were not available in open sources (primarily pre-2000 non-US, and some interpolated years), values are estimated from: (a) OECD Global Debt Report charts, (b) academic literature (IMF WP/12/158 for pre-2012 G20; Xu 2024 Harvard paper on G7 bond market integration), (c) known anchor points from national sources. Estimated cells are marked with a tilde (~) in a separate column below if applicable.
A88: How to update: | B88: US: Download FRED series FDHBFIN or Treasury TIC data. UK: DMO ownership-of-gilts page. Euro area: ECB SHS portal or national central bank statistics. Japan: BoJ Flow of Funds release. All: IMF QEDS DataBank (quarterly).

Sheet IL Gilt Share
A1: UK Index-Linked Gilts: Share of Gilt Portfolio (Nominal Uplifted Values, End-December)
A2: Source: UK Debt Management Office (DMO) Quarterly Reviews. Values are gross nominal uplifted values (including RPI uplift for IL gilts); gilt portfolio only (excludes Treasury bills). End-December each year except 2025 (end-September). See 'Notes & Sources' sheet for full detail.
A4: Year | B4: IL Gilts (£bn) | C4: Conv. Gilts (£bn) | D4: Total Gilt Stock (£bn) | E4: IL Share (%) | F4: YoY Change (pp) | G4: Approx. Data Quality
A5: 1999 | B5: 68 | C5: 241 | D5: 309 | E5: 22.006472 | G5: ○ Estimated
A6: 2000 | B6: 70.5 | C6: 240 | D6: 310.5 | E6: 22.705314 | F6: 0.69884152 | G6: ○ Estimated
A7: 2001 | B7: 73.5 | C7: 239 | D7: 312.5 | E7: 23.52 | F7: 0.81468599 | G7: ○ Estimated
A8: 2002 | B8: 73 | C8: 213 | D8: 286 | E8: 25.524476 | F8: 2.0044755 | G8: ○ Estimated
A9: 2003 | B9: 79 | C9: 225 | D9: 304 | E9: 25.986842 | F9: 0.46236658 | G9: ○ Estimated
A10: 2004 | B10: 91 | C10: 264 | D10: 355 | E10: 25.633803 | F10: -0.35303929 | G10: ○ Estimated
A11: 2005 | B11: 100 | C11: 298 | D11: 398 | E11: 25.125628 | F11: -0.50817468 | G11: ○ Estimated
A12: 2006 | B12: 115.6 | C12: 322.3 | D12: 437.9 | E12: 26.398721 | F12: 1.273093 | G12: ● Direct
A13: 2007 | B13: 136 | C13: 337.9 | D13: 473.9 | E13: 28.698038 | F13: 2.2993164 | G13: ● Direct
A14: 2008 | B14: 163 | C14: 524 | D14: 687 | E14: 23.726346 | F14: -4.9716911 | G14: ○ Estimated
A15: 2009 | B15: 182.5 | C15: 681.2 | D15: 863.7 | E15: 21.130022 | F15: -2.5963244 | G15: ● Direct
A16: 2010 | B16: 200 | C16: 790 | D16: 990 | E16: 20.20202 | F16: -0.9280018 | G16: ○ Estimated
A17: 2011 | B17: 228 | C17: 863 | D17: 1091 | E17: 20.898258 | F17: 0.69623828 | G17: ○ Estimated
... A31: 2025 | B31: 678.8 | C31: 2093.8 | D31: 2772.6 | E31: 24.482435 | F31: 0.67963448 | G31: ● Direct
A33: Notes & Sources
A35: PRIMARY SOURCE
A36: DMO Quarterly Reviews | B36: The UK Debt Management Office publishes a Quarterly Review every three months. Each edition contains a 'portfolio summary statistics' table showing the nominal uplifted value of conventional and index-linked gilts at end-quarter. End-December values are used here for the annual series. The complete quarterly history is also available via the DMO website data section. | C36: https://www.dmo.gov.uk/publications/quarterly-reviews/ | https://dmo.gov.uk/data/gilt-market/
A37: DMO Annual Reviews | B37: The DMO Annual Review (published each September) contains Annex A with the composition of the central government wholesale debt stock over time, including Chart A.10 (in recent editions) showing the index-linked proportion back to ~2006. Also used to fill gaps. | C37: https://www.dmo.gov.uk/publications/annual-reviews/
A38: DMR 2025-26 (HM Treasury) | B38: The Debt Management Report 2025-26 (published April 2025) confirms the stock of index-linked debt at ~£619bn at end-2024, representing 24.5% of the wholesale debt portfolio. | C38: https://www.gov.uk/government/publications/debt-management-report-2025-26/debt-management-report-2025-26-accessible
A40: SPECIFIC QUARTERLY REVIEW PDFS USED
A41: Q4 2000 (Oct-Dec 2000) | B41: IL=~£70.5bn; IL 25.3% of gilt+T-bill stock per pie chart. Conv=~£240bn | C41: https://www.dmo.gov.uk/media/3cknkyve/oct-dec00.pdf
A42: Q3 2002 (Jul-Sep 2002) | B42: IL 25.3% per pie chart; nominal IL=£70.1bn (Q3 end), Conv = £213bn (Q3 end) | C42: https://www.dmo.gov.uk/media/5cad2vmq/jul-sep02.pdf
A43: Q1 2007 (Jan-Mar 2007) | B43: Dec 2006: IL=£115.64bn, Conv=£322.30bn → IL share = 26.4% | C43: https://www.dmo.gov.uk/media/jsnccfad/jan-mar07.pdf
A44: Q4 2007 (Oct-Dec 2007) | B44: Dec 2007: IL=£135.95bn, Conv=£337.94bn → IL share = 28.7% | C44: https://www.dmo.gov.uk/media/qtgc1wtc/oct-dec07.pdf
A45: Q4 2009 (Oct-Dec 2009) | B45: Dec 2009: IL=£182.53bn, Conv=£681.19bn → IL share = 21.1% | C45: https://www.dmo.gov.uk/media/mlupe1c2/oct-dec09.pdf
A46: Q2 2014 (Apr-Jun 2014) | B46: Jun 2014: IL=£335.25bn, Conv=£1,063.72bn → IL share = 24.0% | C46: https://www.dmo.gov.uk/media/tgll2dww/apr-jun14.pdf
A47: Q4 2016 (Oct-Dec 2016) | B47: Dec 2016: IL=£387.53bn, Conv=£1,124.79bn; IL 26.0% per pie chart | C47: https://www.dmo.gov.uk/media/y2ipfajl/oct-dec16.pdf
A48: Q3 2022 (Jul-Sep 2022) | B48: Dec 2021: IL=£499.49bn, Conv=£1,614.15bn → IL share = 23.6% | C48: https://www.dmo.gov.uk/media/l1zel0pa/jul-sep-2022-v2a.pdf
A49: Q3 2023 (Jul-Sep 2023) | B49: Dec 2022: IL=£556.17bn, Conv=£1,721.70bn → IL share = 24.4% | C49: https://www.dmo.gov.uk/media/xl5bo4as/jul-sep-2023.pdf
A50: Q1/Q2 2024 | B50: Dec 2023: IL=£617.45bn, Conv=£1,834.54bn → IL share = 25.2% | C50: https://www.dmo.gov.uk/media/hmjfikgr/jan-mar-2024.pdf
A51: Q2/Q3 2025 | B51: Dec 2024: IL=£623.81bn, Conv=£1,996.88bn → IL share = 23.8%. Sep 2025: IL=£678.75bn, Conv=£2,093.79bn → 24.5% | C51: https://www.dmo.gov.uk/media/opunj3ps/apr-jun25.pdf | https://www.dmo.gov.uk/media/oykbuhke/jul-sep25.pdf
A53: METHODOLOGY
A54: Definition | B54: Index-linked share = IL nominal uplifted value / (IL + conventional nominal uplifted value). T-bills excluded from the denominator. 'Nominal uplifted' means the nominal face value adjusted upwards for RPI accrual since issuance — this is the standard DMO presentation.
A55: Data quality flags | B55: '● Direct' = value taken directly from a specific DMO Quarterly Review PDF identified above. '○ Estimated' = interpolated or estimated from DMO Annual Review charts and adjacent quarters where the specific end-December PDF was not directly fetched. The estimates are consistent with surrounding known anchor points and the trend shown in DMR 2025-26 Chart A.2.
A56: Timing | B56: Values are end-December (Q4) for each year, consistent with the calendar year. The 2025 observation is end-September 2025 (latest available as of May 2026).
A57: Gross vs net | B57: Gross values include gilts held by the DMO itself. Net values (which exclude DMO-held gilts) are slightly lower; the IL share is broadly similar. The DMO's own Chart A.10 in DMR 2025-26 uses gross values.
A58: RPI uplift caveat | B58: The nominal uplifted value of IL gilts grows mechanically with RPI even without new issuance. The share of IL gilts in the portfolio therefore partly reflects inflation outturns, not just issuance decisions. Between 2021 and 2023, the IL stock rose sharply in nominal terms due to high RPI, which distorts apparent trends in the share.
A59: How to update | B59: Download the most recent DMO Quarterly Review from dmo.gov.uk/publications/quarterly-reviews/ and read the 'Portfolio summary statistics' table on page 1. The 'Uplifted nominal value' rows for 'Index-linked gilts' and 'Conventional gilts' give the numerator and denominator directly. | C59: https://www.dmo.gov.uk/publications/quarterly-reviews/

Sheet DataA
B1: =GMWA!$DB$2 -> Desktop | C1: =$B$1 -> Desktop | D1: =$B$1 -> Desktop | E1: =$B$1 -> Desktop | F1: =$B$1 -> Desktop | G1: =$B$1 -> Desktop | H1: =$B$1 -> Desktop | I1: =$B$1 -> Desktop | J1: =$B$1 -> Desktop | ... BI1: =$B$1 -> Desktop | CF1: FYs | CN1: CYs
B2: UK | C2: US | D2: Japan | E2: Canada | F2: Australia | G2: Denmark | H2: Sweden | I2: Switzerland | J2: S Korea | K2: Germany | L2: France | M2: Italy | N2: Spain | O2: Netherlands | P2: Belgium | Q2: Austria | R2: Finland | S2: Ireland | T2: Greece | U2: Portugal | V2: UK | W2: US | X2: Japan | Y2: Canada | Z2: Australia | AA2: Denmark | AB2: Sweden | AC2: Switzerland | AD2: S Korea | AE2: Germany | AF2: France | AG2: Italy | AH2: Spain | AI2: Netherlands | AJ2: Belgium | AK2: Austria | AL2: Finland | AM2: Ireland | AN2: Greece | AO2: Portugal | AP2: UK | AQ2: US | AR2: Japan | AS2: Canada | AT2: Australia | AU2: Denmark | AV2: Sweden | AW2: Switzerland | AX2: S Korea | AY2: Germany | AZ2: France | BA2: Italy | BB2: Spain | BC2: Netherlands | BD2: Belgium | BE2: Austria | BF2: Finland | BG2: Ireland | BH2: Greece | BI2: Portugal | BK2: =B2 -> UK | BL2: =C2 -> US | BM2: =D2 -> Japan | BN2: =E2 -> Canada | BO2: =F2 -> Australia | BP2: =G2 -> Denmark | BQ2: =H2 -> Sweden | BR2: =I2 -> Switzerland | ... CD2: =U2 -> Portugal
B3: GDIP | C3: GDIP | D3: GDIP | E3: GDIP | F3: GDIP | G3: GDIP | H3: GDIP | I3: GDIP | J3: GDIP | K3: GDIP | L3: GDIP | M3: GDIP | N3: GDIP | O3: GDIP | P3: GDIP | Q3: GDIP | R3: GDIP | S3: GDIP | T3: GDIP | U3: GDIP | V3: GGDBT | W3: GGDBT | X3: GGDBT | Y3: GGDBT | Z3: GGDBT | AA3: GGDBT | AB3: GGDBT | AC3: GGDBT | AD3: GGDBT | AE3: GGDBT | AF3: GGDBT | AG3: GGDBT | AH3: GGDBT | AI3: GGDBT | AJ3: GGDBT | AK3: GGDBT | AL3: GGDBT | AM3: GGDBT | AN3: GGDBT | AO3: GGDBT | AP3: GDP! | AQ3: GDP! | AR3: GDP! | AS3: GDP! | AT3: GDP! | AU3: GDP! | AV3: GDP! | AW3: GDP! | AX3: GDP! | AY3: GDP! | AZ3: GDP! | BA3: GDP! | BB3: GDP! | BC3: GDP! | BD3: GDP! | BE3: GDP! | BF3: GDP! | BG3: GDP! | BH3: GDP! | BI3: GDP! | BK3: GDIP/GGDBT | BL3: GDIP/GGDBT | BM3: GDIP/GGDBT | BN3: GDIP/GGDBT | BO3: GDIP/GGDBT | BP3: GDIP/GGDBT | BQ3: GDIP/GGDBT | BR3: GDIP/GGDBT | BS3: GDIP/GGDBT | BT3: GDIP/GGDBT | BU3: GDIP/GGDBT | BV3: GDIP/GGDBT | BW3: GDIP/GGDBT | BX3: GDIP/GGDBT | BY3: GDIP/GGDBT | BZ3: GDIP/GGDBT | CA3: GDIP/GGDBT | CB3: GDIP/GGDBT | CC3: GDIP/GGDBT | CD3: GDIP/GGDBT | CF3: =DataQ!I3 -> GDP | CG3: =DataQ!J3 -> GDP | CH3: =DataQ!K3 -> GDP | CI3: =DataQ!L3 -> GDP | CJ3: =DataQ!M3 -> GDP | CK3: =DataQ!N3 -> GDP | CL3: =DataQ!O3 -> GB | CN3: =DataQ!P3 -> GB | CO3: =DataQ!Q3 -> GB | CP3: =DataQ!R3 -> GB
B4: GBR | C4: USA | D4: JPN | E4: CAN | F4: AUS | G4: DNK | H4: SWE | I4: CHE | J4: KOR | K4: DEU | L4: FRA | M4: ITA | N4: ESP | O4: NLD | P4: BEL | Q4: AUT | R4: FIN | S4: IRL | T4: GRC | U4: PRT | V4: GBR | W4: USA | X4: JPN | Y4: CAN | Z4: AUS | AA4: DNK | AB4: SWE | AC4: CHE | AD4: KOR | AE4: DEU | AF4: FRA | AG4: ITA | AH4: ESP | AI4: NLD | AJ4: BEL | AK4: AUT | AL4: FIN | AM4: IRL | AN4: GRC | AO4: PRT | AP4: GBR | AQ4: USA | AR4: JPN | AS4: CAN | AT4: AUS | AU4: DNK | AV4: SWE | AW4: CHE | AX4: KOR | AY4: DEU | AZ4: FRA | BA4: ITA | BB4: ESP | BC4: NLD | BD4: BEL | BE4: AUT | BF4: FIN | BG4: IRL | BH4: GRC | BI4: PRT | BK4: =B4 -> GBR | BL4: =C4 -> USA | BM4: =D4 -> JPN | BN4: =E4 -> CAN | BO4: =F4 -> AUS | BP4: =G4 -> DNK | BQ4: =H4 -> SWE | BR4: =I4 -> CHE | ... CD4: =U4 -> PRT
B5: L | C5: L | D5: L | E5: L | F5: L | G5: L | H5: L | I5: L | J5: L | K5: L | L5: L | M5: L | N5: L | O5: L | P5: L | Q5: L | R5: L | S5: L | T5: L | U5: L | V5: L | W5: L | X5: L | Y5: L | Z5: L | AA5: L | AB5: L | AC5: L | AD5: L | AE5: L | AF5: L | AG5: L | AH5: L | AI5: L | AJ5: L | AK5: L | AL5: L | AM5: L | AN5: L | AO5: L | AP5: L | AQ5: L | AR5: L | AS5: L | AT5: L | AU5: L | AV5: L | AW5: L | AX5: L | AY5: L | AZ5: L | BA5: L | BB5: L | BC5: L | BD5: L | BE5: L | BF5: L | BG5: L | BH5: L | BI5: L
A6: =A94+5 -> 2065 | B6: {=_xlfn.CONCAT(INDEX(GMWA!$A$2:$DB$600,MATCH(1,(GMWA!$DA$2:$DA$600=B$3)*(GMWA!$CZ$2:$CZ$600=B$4)*(GMWA!$DB$2:$DB$600=B$1),0),$A6-1966),"0",(INDEX(GMWA!$A$2:$DB$600,MATCH(1,(GMWA!$DA$2:$DA$600=B$3)*(GMWA!$CZ$2:$CZ$600=B$4)*(GMWA!$DB$2:$DB$600=B$1),0),$A6-1965)))} -> 202601 | C6: {=_xlfn.CONCAT(INDEX(GMWA!$A$2:$DB$600,MATCH(1,(GMWA!$DA$2:$DA$600=C$3)*(GMWA!$CZ$2:$CZ$600=C$4)*(GMWA!$DB$2:$DB$600=C$1),0),$A6-1966),"0",(INDEX(GMWA!$A$2:$DB$600,MATCH(1,(GMWA!$DA$2:$DA$600=C$3)*(GMWA!$CZ$2:$CZ$600=C$4)*(GMWA!$DB$2:$DB$600=C$1),0),$A6-1965)))} -> 202601 | D6: {=_xlfn.CONCAT(INDEX(GMWA!$A$2:$DB$600,MATCH(1,(GMWA!$DA$2:$DA$600=D$3)*(GMWA!$CZ$2:$CZ$600=D$4)*(GMWA!$DB$2:$DB$600=D$1),0),$A6-1966),"0",(INDEX(GMWA!$A$2:$DB$600,MATCH(1,(GMWA!$DA$2:$DA$600=D$3)*(GMWA!$CZ$2:$CZ$600=D$4)*(GMWA!$DB$2:$DB$600=D$1),0),$A6-1965)))} -> 202501 | E6: {=_xlfn.CONCAT(INDEX(GMWA!$A$2:$DB$600,MATCH(1,(GMWA!$DA$2:$DA$600=E$3)*(GMWA!$CZ$2:$CZ$600=E$4)*(GMWA!$DB$2:$DB$600=E$1),0),$A6-1966),"0",(INDEX(GMWA!$A$2:$DB$600,MATCH(1,(GMWA!$DA$2:$DA$600=E$3)*(GMWA!$CZ$2:$CZ$600=E$4)*(GMWA!$DB$2:$DB$600=E$1),0),$A6-1965)))} -> 202601 | F6: {=_xlfn.CONCAT(INDEX(GMWA!$A$2:$DB$600,MATCH(1,(GMWA!$DA$2:$DA$600=F$3)*(GMWA!$CZ$2:$CZ$600=F$4)*(GMWA!$DB$2:$DB$600=F$1),0),$A6-1966),"0",(INDEX(GMWA!$A$2:$DB$600,MATCH(1,(GMWA!$DA$2:$DA$600=F$3)*(GMWA!$CZ$2:$CZ$600=F$4)*(GMWA!$DB$2:$DB$600=F$1),0),$A6-1965)))} -> 202601 | G6: {=_xlfn.CONCAT(INDEX(GMWA!$A$2:$DB$600,MATCH(1,(GMWA!$DA$2:$DA$600=G$3)*(GMWA!$CZ$2:$CZ$600=G$4)*(GMWA!$DB$2:$DB$600=G$1),0),$A6-1966),"0",(INDEX(GMWA!$A$2:$DB$600,MATCH(1,(GMWA!$DA$2:$DA$600=G$3)*(GMWA!$CZ$2:$CZ$600=G$4)*(GMWA!$DB$2:$DB$600=G$1),0),$A6-1965)))} -> 202504 | H6: {=_xlfn.CONCAT(INDEX(GMWA!$A$2:$DB$600,MATCH(1,(GMWA!$DA$2:$DA$600=H$3)*(GMWA!$CZ$2:$CZ$600=H$4)*(GMWA!$DB$2:$DB$600=H$1),0),$A6-1966),"0",(INDEX(GMWA!$A$2:$DB$600,MATCH(1,(GMWA!$DA$2:$DA$600=H$3)*(GMWA!$CZ$2:$CZ$600=H$4)*(GMWA!$DB$2:$DB$600=H$1),0),$A6-1965)))} -> 202504 | I6: {=_xlfn.CONCAT(INDEX(GMWA!$A$2:$DB$600,MATCH(1,(GMWA!$DA$2:$DA$600=I$3)*(GMWA!$CZ$2:$CZ$600=I$4)*(GMWA!$DB$2:$DB$600=I$1),0),$A6-1966),"0",(INDEX(GMWA!$A$2:$DB$600,MATCH(1,(GMWA!$DA$2:$DA$600=I$3)*(GMWA!$CZ$2:$CZ$600=I$4)*(GMWA!$DB$2:$DB$600=I$1),0),$A6-1965)))} -> 202004 | ... BI6: {=_xlfn.CONCAT(INDEX(GMWA!$A$2:$DB$600,MATCH(1,(GMWA!$DA$2:$DA$600=BI$3)*(GMWA!$CZ$2:$CZ$600=BI$4)*(GMWA!$DB$2:$DB$600=BI$1),0),$A6-1966),"0",(INDEX(GMWA!$A$2:$DB$600,MATCH(1,(GMWA!$DA$2:$DA$600=BI$3)*(GMWA!$CZ$2:$CZ$600=BI$4)*(GMWA!$DB$2:$DB$600=BI$1),0),$A6-1965)))} -> 202504 | CF6: =DataQ!I6 -> 202601 | CG6: =DataQ!J6 -> 202504 | CH6: =DataQ!K6 -> 202601 | CI6: =DataQ!L6 -> 202601 | CJ6: =DataQ!M6 -> 202601 | CK6: =DataQ!N6 -> 202601 | CL6: =DataQ!O6 -> 202601 | CN6: =DataQ!P6 -> 202504 | CO6: =DataQ!Q6 -> 202501 | CP6: =DataQ!R6 -> 202601
A7: 1973 | B7: {=INDEX(GMWA!$A$2:$DB$600,MATCH(1,(GMWA!$DA$2:$DA$600=B$3)*(GMWA!$CZ$2:$CZ$600=B$4)*(GMWA!$DB$2:$DB$600=B$1),0),$A7-1966)} -> 3087 | C7: {=INDEX(GMWA!$A$2:$DB$600,MATCH(1,(GMWA!$DA$2:$DA$600=C$3)*(GMWA!$CZ$2:$CZ$600=C$4)*(GMWA!$DB$2:$DB$600=C$1),0),$A7-1966)} -> 61.95 | D7: {=INDEX(GMWA!$A$2:$DB$600,MATCH(1,(GMWA!$DA$2:$DA$600=D$3)*(GMWA!$CZ$2:$CZ$600=D$4)*(GMWA!$DB$2:$DB$600=D$1),0),$A7-1966)} -> 922.9716 | E7: {=INDEX(GMWA!$A$2:$DB$600,MATCH(1,(GMWA!$DA$2:$DA$600=E$3)*(GMWA!$CZ$2:$CZ$600=E$4)*(GMWA!$DB$2:$DB$600=E$1),0),$A7-1966)} -> 4910 | F7: {=INDEX(GMWA!$A$2:$DB$600,MATCH(1,(GMWA!$DA$2:$DA$600=F$3)*(GMWA!$CZ$2:$CZ$600=F$4)*(GMWA!$DB$2:$DB$600=F$1),0),$A7-1966)} -> 738.1701 | G7: {=INDEX(GMWA!$A$2:$DB$600,MATCH(1,(GMWA!$DA$2:$DA$600=G$3)*(GMWA!$CZ$2:$CZ$600=G$4)*(GMWA!$DB$2:$DB$600=G$1),0),$A7-1966)} -> 1.986917 | H7: {=INDEX(GMWA!$A$2:$DB$600,MATCH(1,(GMWA!$DA$2:$DA$600=H$3)*(GMWA!$CZ$2:$CZ$600=H$4)*(GMWA!$DB$2:$DB$600=H$1),0),$A7-1966)} -> 3553.037 | I7: {=INDEX(GMWA!$A$2:$DB$600,MATCH(1,(GMWA!$DA$2:$DA$600=I$3)*(GMWA!$CZ$2:$CZ$600=I$4)*(GMWA!$DB$2:$DB$600=I$1),0),$A7-1966)} -> 1.915308 | ... BI7: {=INDEX(GMWA!$A$2:$DB$600,MATCH(1,(GMWA!$DA$2:$DA$600=BI$3)*(GMWA!$CZ$2:$CZ$600=BI$4)*(GMWA!$DB$2:$DB$600=BI$1),0),$A7-1966)} -> 23.33603 | BK7: =100*(B7/V7) -> 8.5822878 | BL7: =100*(C7/W7) -> 5.3458308 | BM7: =100*(D7/X7) -> 5.1843599 | BN7: =100*(E7/Y7) -> 7.5628052 | BO7: =100*(F7/Z7) -> 73817010 | BP7: =100*(G7/AA7) -> 1.1897707 | BQ7: =100*(H7/AB7) -> 5.1876507 | BR7: =100*(I7/AC7) -> 1.8912737 | ... CD7: =100*(U7/AO7) -> 1.139807 | CF7: =SUMIF(DataQ!$C:$C,DataA!$A7,DataQ!I:I) -> 6116.05 | CG7: =SUMIF(DataQ!$C:$C,DataA!$A7,DataQ!J:J) -> 219811.51 | CH7: =SUMIF(DataQ!$C:$C,DataA!$A7,DataQ!K:K) -> 1564.34 | CI7: =SUMIF(DataQ!$C:$C,DataA!$A7,DataQ!L:L) -> 1013.889 | CJ7: =SUMIF(DataQ!$C:$C,DataA!$A7,DataQ!M:M) -> 954.3197 | CK7: =AVERAGEIF(DataQ!$C:$C,DataA!$A7,DataQ!N:N) -> 178599.27 | CL7: =SUMIF(DataQ!$C:$C,DataA!$A7,DataQ!O:O) -> -3383 | CN7: =SUMIF(DataQ!$B:$B,DataA!$A7,DataQ!P:P) -> -44.59125 | CO7: =SUMIF(DataQ!$B:$B,DataA!$A7,DataQ!Q:Q) -> -2130.75 | CP7: =SUMIF(DataQ!$B:$B,DataA!$A7,DataQ!R:R) -> -23.045528
A8: =+A7+1 -> 1974 | B8: {=INDEX(GMWA!$A$2:$DB$600,MATCH(1,(GMWA!$DA$2:$DA$600=B$3)*(GMWA!$CZ$2:$CZ$600=B$4)*(GMWA!$DB$2:$DB$600=B$1),0),$A8-1966)} -> 4131 | C8: {=INDEX(GMWA!$A$2:$DB$600,MATCH(1,(GMWA!$DA$2:$DA$600=C$3)*(GMWA!$CZ$2:$CZ$600=C$4)*(GMWA!$DB$2:$DB$600=C$1),0),$A8-1966)} -> 69.55 | D8: {=INDEX(GMWA!$A$2:$DB$600,MATCH(1,(GMWA!$DA$2:$DA$600=D$3)*(GMWA!$CZ$2:$CZ$600=D$4)*(GMWA!$DB$2:$DB$600=D$1),0),$A8-1966)} -> 1196.62 | E8: {=INDEX(GMWA!$A$2:$DB$600,MATCH(1,(GMWA!$DA$2:$DA$600=E$3)*(GMWA!$CZ$2:$CZ$600=E$4)*(GMWA!$DB$2:$DB$600=E$1),0),$A8-1966)} -> 5488 | F8: {=INDEX(GMWA!$A$2:$DB$600,MATCH(1,(GMWA!$DA$2:$DA$600=F$3)*(GMWA!$CZ$2:$CZ$600=F$4)*(GMWA!$DB$2:$DB$600=F$1),0),$A8-1966)} -> 807 | G8: {=INDEX(GMWA!$A$2:$DB$600,MATCH(1,(GMWA!$DA$2:$DA$600=G$3)*(GMWA!$CZ$2:$CZ$600=G$4)*(GMWA!$DB$2:$DB$600=G$1),0),$A8-1966)} -> 2.163271 | H8: {=INDEX(GMWA!$A$2:$DB$600,MATCH(1,(GMWA!$DA$2:$DA$600=H$3)*(GMWA!$CZ$2:$CZ$600=H$4)*(GMWA!$DB$2:$DB$600=H$1),0),$A8-1966)} -> 4397.595 | I8: {=INDEX(GMWA!$A$2:$DB$600,MATCH(1,(GMWA!$DA$2:$DA$600=I$3)*(GMWA!$CZ$2:$CZ$600=I$4)*(GMWA!$DB$2:$DB$600=I$1),0),$A8-1966)} -> 2.263996 | ... BI8: {=INDEX(GMWA!$A$2:$DB$600,MATCH(1,(GMWA!$DA$2:$DA$600=BI$3)*(GMWA!$CZ$2:$CZ$600=BI$4)*(GMWA!$DB$2:$DB$600=BI$1),0),$A8-1966)} -> 23.33603 | BK8: =100*(B8/V8) -> 8.4599839 | BL8: =100*(C8/W8) -> 5.5564033 | BM8: =100*(D8/X8) -> 7.2373291 | BN8: =100*(E8/Y8) -> 7.4126101 | BO8: =100*(F8/Z8) -> 80700000 | BP8: =100*(G8/AA8) -> 1.2953719 | BQ8: =100*(H8/AB8) -> 5.6119733 | BR8: =100*(I8/AC8) -> 2.1942007 | ... CD8: =100*(U8/AO8) -> 0.96902159 | CF8: =SUMIF(DataQ!$C:$C,DataA!$A8,DataQ!I:I) -> 6038.325 | CG8: =SUMIF(DataQ!$C:$C,DataA!$A8,DataQ!J:J) -> 218946.48 | CH8: =SUMIF(DataQ!$C:$C,DataA!$A8,DataQ!K:K) -> 1563.89 | CI8: =SUMIF(DataQ!$C:$C,DataA!$A8,DataQ!L:L) -> 1041.055 | CJ8: =SUMIF(DataQ!$C:$C,DataA!$A8,DataQ!M:M) -> 975.1377 | CK8: =AVERAGEIF(DataQ!$C:$C,DataA!$A8,DataQ!N:N) -> 182714.27 | CL8: =SUMIF(DataQ!$C:$C,DataA!$A8,DataQ!O:O) -> -5592 | CN8: =SUMIF(DataQ!$B:$B,DataA!$A8,DataQ!P:P) -> -59.765 | CO8: =SUMIF(DataQ!$B:$B,DataA!$A8,DataQ!Q:Q) -> -2482.25 | CP8: =SUMIF(DataQ!$B:$B,DataA!$A8,DataQ!R:R) -> -36.381582
A9: =+A8+1 -> 1975 | B9: {=INDEX(GMWA!$A$2:$DB$600,MATCH(1,(GMWA!$DA$2:$DA$600=B$3)*(GMWA!$CZ$2:$CZ$600=B$4)*(GMWA!$DB$2:$DB$600=B$1),0),$A9-1966)} -> 4939 | C9: {=INDEX(GMWA!$A$2:$DB$600,MATCH(1,(GMWA!$DA$2:$DA$600=C$3)*(GMWA!$CZ$2:$CZ$600=C$4)*(GMWA!$DB$2:$DB$600=C$1),0),$A9-1966)} -> 77.425 | D9: {=INDEX(GMWA!$A$2:$DB$600,MATCH(1,(GMWA!$DA$2:$DA$600=D$3)*(GMWA!$CZ$2:$CZ$600=D$4)*(GMWA!$DB$2:$DB$600=D$1),0),$A9-1966)} -> 1681.87 | E9: {=INDEX(GMWA!$A$2:$DB$600,MATCH(1,(GMWA!$DA$2:$DA$600=E$3)*(GMWA!$CZ$2:$CZ$600=E$4)*(GMWA!$DB$2:$DB$600=E$1),0),$A9-1966)} -> 6639 | F9: {=INDEX(GMWA!$A$2:$DB$600,MATCH(1,(GMWA!$DA$2:$DA$600=F$3)*(GMWA!$CZ$2:$CZ$600=F$4)*(GMWA!$DB$2:$DB$600=F$1),0),$A9-1966)} -> 916 | G9: {=INDEX(GMWA!$A$2:$DB$600,MATCH(1,(GMWA!$DA$2:$DA$600=G$3)*(GMWA!$CZ$2:$CZ$600=G$4)*(GMWA!$DB$2:$DB$600=G$1),0),$A9-1966)} -> 2.374895 | H9: {=INDEX(GMWA!$A$2:$DB$600,MATCH(1,(GMWA!$DA$2:$DA$600=H$3)*(GMWA!$CZ$2:$CZ$600=H$4)*(GMWA!$DB$2:$DB$600=H$1),0),$A9-1966)} -> 5346.4 | I9: {=INDEX(GMWA!$A$2:$DB$600,MATCH(1,(GMWA!$DA$2:$DA$600=I$3)*(GMWA!$CZ$2:$CZ$600=I$4)*(GMWA!$DB$2:$DB$600=I$1),0),$A9-1966)} -> 2.686347 | ... BI9: {=INDEX(GMWA!$A$2:$DB$600,MATCH(1,(GMWA!$DA$2:$DA$600=BI$3)*(GMWA!$CZ$2:$CZ$600=BI$4)*(GMWA!$DB$2:$DB$600=BI$1),0),$A9-1966)} -> 23.33603 | BK9: =100*(B9/V9) -> 7.883983 | BL9: =100*(C9/W9) -> 5.4832482 | BM9: =100*(D9/X9) -> 5.7552955 | BN9: =100*(E9/Y9) -> 8.0669267 | BO9: =100*(F9/Z9) -> 91600000 | BP9: =100*(G9/AA9) -> 1.4220928 | BQ9: =100*(H9/AB9) -> 5.9776213 | BR9: =100*(I9/AC9) -> 2.5110529 | ... CD9: =100*(U9/AO9) -> 0.60098917 | CF9: =SUMIF(DataQ!$C:$C,DataA!$A9,DataQ!I:I) -> 6152.5 | CG9: =SUMIF(DataQ!$C:$C,DataA!$A9,DataQ!J:J) -> 227886.25 | CH9: =SUMIF(DataQ!$C:$C,DataA!$A9,DataQ!K:K) -> 1571.03 | CI9: =SUMIF(DataQ!$C:$C,DataA!$A9,DataQ!L:L) -> 1041.161 | CJ9: =SUMIF(DataQ!$C:$C,DataA!$A9,DataQ!M:M) -> 971.922 | CK9: =AVERAGEIF(DataQ!$C:$C,DataA!$A9,DataQ!N:N) -> 188382.77 | CL9: =SUMIF(DataQ!$C:$C,DataA!$A9,DataQ!O:O) -> -7651 | CN9: =SUMIF(DataQ!$B:$B,DataA!$A9,DataQ!P:P) -> -128.606 | CO9: =SUMIF(DataQ!$B:$B,DataA!$A9,DataQ!Q:Q) -> -7342 | CP9: =SUMIF(DataQ!$B:$B,DataA!$A9,DataQ!R:R) -> -62.44885
A10: =+A9+1 -> 1976 | B10: {=INDEX(GMWA!$A$2:$DB$600,MATCH(1,(GMWA!$DA$2:$DA$600=B$3)*(GMWA!$CZ$2:$CZ$600=B$4)*(GMWA!$DB$2:$DB$600=B$1),0),$A10-1966)} -> 6380 | C10: {=INDEX(GMWA!$A$2:$DB$600,MATCH(1,(GMWA!$DA$2:$DA$600=C$3)*(GMWA!$CZ$2:$CZ$600=C$4)*(GMWA!$DB$2:$DB$600=C$1),0),$A10-1966)} -> 86.725 | D10: {=INDEX(GMWA!$A$2:$DB$600,MATCH(1,(GMWA!$DA$2:$DA$600=D$3)*(GMWA!$CZ$2:$CZ$600=D$4)*(GMWA!$DB$2:$DB$600=D$1),0),$A10-1966)} -> 2416.859 | E10: {=INDEX(GMWA!$A$2:$DB$600,MATCH(1,(GMWA!$DA$2:$DA$600=E$3)*(GMWA!$CZ$2:$CZ$600=E$4)*(GMWA!$DB$2:$DB$600=E$1),0),$A10-1966)} -> 8242 | F10: {=INDEX(GMWA!$A$2:$DB$600,MATCH(1,(GMWA!$DA$2:$DA$600=F$3)*(GMWA!$CZ$2:$CZ$600=F$4)*(GMWA!$DB$2:$DB$600=F$1),0),$A10-1966)} -> 1191 | G10: {=INDEX(GMWA!$A$2:$DB$600,MATCH(1,(GMWA!$DA$2:$DA$600=G$3)*(GMWA!$CZ$2:$CZ$600=G$4)*(GMWA!$DB$2:$DB$600=G$1),0),$A10-1966)} -> 3.083249 | H10: {=INDEX(GMWA!$A$2:$DB$600,MATCH(1,(GMWA!$DA$2:$DA$600=H$3)*(GMWA!$CZ$2:$CZ$600=H$4)*(GMWA!$DB$2:$DB$600=H$1),0),$A10-1966)} -> 5906.224 | I10: {=INDEX(GMWA!$A$2:$DB$600,MATCH(1,(GMWA!$DA$2:$DA$600=I$3)*(GMWA!$CZ$2:$CZ$600=I$4)*(GMWA!$DB$2:$DB$600=I$1),0),$A10-1966)} -> 2.877871 | ... BI10: {=INDEX(GMWA!$A$2:$DB$600,MATCH(1,(GMWA!$DA$2:$DA$600=BI$3)*(GMWA!$CZ$2:$CZ$600=BI$4)*(GMWA!$DB$2:$DB$600=BI$1),0),$A10-1966)} -> 23.33603 | BK10: =100*(B10/V10) -> 8.6917724 | BL10: =100*(C10/W10) -> 5.6833932 | BM10: =100*(D10/X10) -> 5.4821463 | BN10: =100*(E10/Y10) -> 9.0138565 | BO10: =100*(F10/Z10) -> 119100000 | BP10: =100*(G10/AA10) -> 1.8462569 | BQ10: =100*(H10/AB10) -> 6.2582121 | BR10: =100*(I10/AC10) -> 2.6295615 | ... CD10: =100*(U10/AO10) -> 0.39665304 | CF10: =SUMIF(DataQ!$C:$C,DataA!$A10,DataQ!I:I) -> 6438.45 | CG10: =SUMIF(DataQ!$C:$C,DataA!$A10,DataQ!J:J) -> 236541.04 | CH10: =SUMIF(DataQ!$C:$C,DataA!$A10,DataQ!K:K) -> 1644.12 | CI10: =SUMIF(DataQ!$C:$C,DataA!$A10,DataQ!L:L) -> 1090.008 | CJ10: =SUMIF(DataQ!$C:$C,DataA!$A10,DataQ!M:M) -> 1039.9587 | CK10: =AVERAGEIF(DataQ!$C:$C,DataA!$A10,DataQ!N:N) -> 198585.85 | CL10: =SUMIF(DataQ!$C:$C,DataA!$A10,DataQ!O:O) -> -7004 | CN10: =SUMIF(DataQ!$B:$B,DataA!$A10,DataQ!P:P) -> -104.50225 | CO10: =SUMIF(DataQ!$B:$B,DataA!$A10,DataQ!Q:Q) -> -9301 | CP10: =SUMIF(DataQ!$B:$B,DataA!$A10,DataQ!R:R) -> -53.17428
A11: =+A10+1 -> 1977 | B11: {=INDEX(GMWA!$A$2:$DB$600,MATCH(1,(GMWA!$DA$2:$DA$600=B$3)*(GMWA!$CZ$2:$CZ$600=B$4)*(GMWA!$DB$2:$DB$600=B$1),0),$A11-1966)} -> 7333 | C11: {=INDEX(GMWA!$A$2:$DB$600,MATCH(1,(GMWA!$DA$2:$DA$600=C$3)*(GMWA!$CZ$2:$CZ$600=C$4)*(GMWA!$DB$2:$DB$600=C$1),0),$A11-1966)} -> 95.75 | D11: {=INDEX(GMWA!$A$2:$DB$600,MATCH(1,(GMWA!$DA$2:$DA$600=D$3)*(GMWA!$CZ$2:$CZ$600=D$4)*(GMWA!$DB$2:$DB$600=D$1),0),$A11-1966)} -> 3374.968 | E11: {=INDEX(GMWA!$A$2:$DB$600,MATCH(1,(GMWA!$DA$2:$DA$600=E$3)*(GMWA!$CZ$2:$CZ$600=E$4)*(GMWA!$DB$2:$DB$600=E$1),0),$A11-1966)} -> 9432 | F11: {=INDEX(GMWA!$A$2:$DB$600,MATCH(1,(GMWA!$DA$2:$DA$600=F$3)*(GMWA!$CZ$2:$CZ$600=F$4)*(GMWA!$DB$2:$DB$600=F$1),0),$A11-1966)} -> 1532 | G11: {=INDEX(GMWA!$A$2:$DB$600,MATCH(1,(GMWA!$DA$2:$DA$600=G$3)*(GMWA!$CZ$2:$CZ$600=G$4)*(GMWA!$DB$2:$DB$600=G$1),0),$A11-1966)} -> 4.659654 | H11: {=INDEX(GMWA!$A$2:$DB$600,MATCH(1,(GMWA!$DA$2:$DA$600=H$3)*(GMWA!$CZ$2:$CZ$600=H$4)*(GMWA!$DB$2:$DB$600=H$1),0),$A11-1966)} -> 7658.689 | I11: {=INDEX(GMWA!$A$2:$DB$600,MATCH(1,(GMWA!$DA$2:$DA$600=I$3)*(GMWA!$CZ$2:$CZ$600=I$4)*(GMWA!$DB$2:$DB$600=I$1),0),$A11-1966)} -> 3.113591 | ... BI11: {=INDEX(GMWA!$A$2:$DB$600,MATCH(1,(GMWA!$DA$2:$DA$600=BI$3)*(GMWA!$CZ$2:$CZ$600=BI$4)*(GMWA!$DB$2:$DB$600=BI$1),0),$A11-1966)} -> 23.33603 | BK11: =100*(B11/V11) -> 8.7542007 | BL11: =100*(C11/W11) -> 5.7924214 | BM11: =100*(D11/X11) -> 5.7274684 | BN11: =100*(E11/Y11) -> 9.0254918 | BO11: =100*(F11/Z11) -> 153200000 | BP11: =100*(G11/AA11) -> 2.790212 | BQ11: =100*(H11/AB11) -> 6.8751057 | BR11: =100*(I11/AC11) -> 2.8045341 | ... CD11: =100*(U11/AO11) -> 0.28413531 | CF11: =SUMIF(DataQ!$C:$C,DataA!$A11,DataQ!I:I) -> 6749.975 | CG11: =SUMIF(DataQ!$C:$C,DataA!$A11,DataQ!J:J) -> 247315.04 | CH11: =SUMIF(DataQ!$C:$C,DataA!$A11,DataQ!K:K) -> 1695.09 | CI11: =SUMIF(DataQ!$C:$C,DataA!$A11,DataQ!L:L) -> 1125.804 | CJ11: =SUMIF(DataQ!$C:$C,DataA!$A11,DataQ!M:M) -> 1051.1927 | CK11: =AVERAGEIF(DataQ!$C:$C,DataA!$A11,DataQ!N:N) -> 205230.4 | CL11: =SUMIF(DataQ!$C:$C,DataA!$A11,DataQ!O:O) -> -6424 | CN11: =SUMIF(DataQ!$B:$B,DataA!$A11,DataQ!P:P) -> -88.151 | CO11: =SUMIF(DataQ!$B:$B,DataA!$A11,DataQ!Q:Q) -> -10191.75 | CP11: =SUMIF(DataQ!$B:$B,DataA!$A11,DataQ!R:R) -> -44.70044
A12: =+A11+1 -> 1978 | B12: {=INDEX(GMWA!$A$2:$DB$600,MATCH(1,(GMWA!$DA$2:$DA$600=B$3)*(GMWA!$CZ$2:$CZ$600=B$4)*(GMWA!$DB$2:$DB$600=B$1),0),$A12-1966)} -> 8160 | C12: {=INDEX(GMWA!$A$2:$DB$600,MATCH(1,(GMWA!$DA$2:$DA$600=C$3)*(GMWA!$CZ$2:$CZ$600=C$4)*(GMWA!$DB$2:$DB$600=C$1),0),$A12-1966)} -> 112.45 | D12: {=INDEX(GMWA!$A$2:$DB$600,MATCH(1,(GMWA!$DA$2:$DA$600=D$3)*(GMWA!$CZ$2:$CZ$600=D$4)*(GMWA!$DB$2:$DB$600=D$1),0),$A12-1966)} -> 4369.668 | E12: {=INDEX(GMWA!$A$2:$DB$600,MATCH(1,(GMWA!$DA$2:$DA$600=E$3)*(GMWA!$CZ$2:$CZ$600=E$4)*(GMWA!$DB$2:$DB$600=E$1),0),$A12-1966)} -> 11741 | F12: {=INDEX(GMWA!$A$2:$DB$600,MATCH(1,(GMWA!$DA$2:$DA$600=F$3)*(GMWA!$CZ$2:$CZ$600=F$4)*(GMWA!$DB$2:$DB$600=F$1),0),$A12-1966)} -> 1796 | G12: {=INDEX(GMWA!$A$2:$DB$600,MATCH(1,(GMWA!$DA$2:$DA$600=G$3)*(GMWA!$CZ$2:$CZ$600=G$4)*(GMWA!$DB$2:$DB$600=G$1),0),$A12-1966)} -> 6.209607 | H12: {=INDEX(GMWA!$A$2:$DB$600,MATCH(1,(GMWA!$DA$2:$DA$600=H$3)*(GMWA!$CZ$2:$CZ$600=H$4)*(GMWA!$DB$2:$DB$600=H$1),0),$A12-1966)} -> 9006.922 | I12: {=INDEX(GMWA!$A$2:$DB$600,MATCH(1,(GMWA!$DA$2:$DA$600=I$3)*(GMWA!$CZ$2:$CZ$600=I$4)*(GMWA!$DB$2:$DB$600=I$1),0),$A12-1966)} -> 3.064492 | ... BI12: {=INDEX(GMWA!$A$2:$DB$600,MATCH(1,(GMWA!$DA$2:$DA$600=BI$3)*(GMWA!$CZ$2:$CZ$600=BI$4)*(GMWA!$DB$2:$DB$600=BI$1),0),$A12-1966)} -> 23.33603 | BK12: =100*(B12/V12) -> 8.6681716 | BL12: =100*(C12/W12) -> 6.2377478 | BM12: =100*(D12/X12) -> 5.3183564 | BN12: =100*(E12/Y12) -> 9.5232302 | BO12: =100*(F12/Z12) -> 179600000 | BP12: =100*(G12/AA12) -> 3.7183275 | BQ12: =100*(H12/AB12) -> 6.2798084 | BR12: =100*(I12/AC12) -> 2.7169626 | ... CD12: =100*(U12/AO12) -> 0.20127852 | CF12: =SUMIF(DataQ!$C:$C,DataA!$A12,DataQ!I:I) -> 7163.325 | CG12: =SUMIF(DataQ!$C:$C,DataA!$A12,DataQ!J:J) -> 261116.05 | CH12: =SUMIF(DataQ!$C:$C,DataA!$A12,DataQ!K:K) -> 1749.22 | CI12: =SUMIF(DataQ!$C:$C,DataA!$A12,DataQ!L:L) -> 1172.004 | CJ12: =SUMIF(DataQ!$C:$C,DataA!$A12,DataQ!M:M) -> 1101.4476 | CK12: =AVERAGEIF(DataQ!$C:$C,DataA!$A12,DataQ!N:N) -> 212796.95 | CL12: =SUMIF(DataQ!$C:$C,DataA!$A12,DataQ!O:O) -> -8685 | CN12: =SUMIF(DataQ!$B:$B,DataA!$A12,DataQ!P:P) -> -81.16925 | CO12: =SUMIF(DataQ!$B:$B,DataA!$A12,DataQ!Q:Q) -> -13458 | CP12: =SUMIF(DataQ!$B:$B,DataA!$A12,DataQ!R:R) -> -52.05288
A13: =+A12+1 -> 1979 | B13: {=INDEX(GMWA!$A$2:$DB$600,MATCH(1,(GMWA!$DA$2:$DA$600=B$3)*(GMWA!$CZ$2:$CZ$600=B$4)*(GMWA!$DB$2:$DB$600=B$1),0),$A13-1966)} -> 9791 | C13: {=INDEX(GMWA!$A$2:$DB$600,MATCH(1,(GMWA!$DA$2:$DA$600=C$3)*(GMWA!$CZ$2:$CZ$600=C$4)*(GMWA!$DB$2:$DB$600=C$1),0),$A13-1966)} -> 128.475 | D13: {=INDEX(GMWA!$A$2:$DB$600,MATCH(1,(GMWA!$DA$2:$DA$600=D$3)*(GMWA!$CZ$2:$CZ$600=D$4)*(GMWA!$DB$2:$DB$600=D$1),0),$A13-1966)} -> 5571.224 | E13: {=INDEX(GMWA!$A$2:$DB$600,MATCH(1,(GMWA!$DA$2:$DA$600=E$3)*(GMWA!$CZ$2:$CZ$600=E$4)*(GMWA!$DB$2:$DB$600=E$1),0),$A13-1966)} -> 14057 | F13: {=INDEX(GMWA!$A$2:$DB$600,MATCH(1,(GMWA!$DA$2:$DA$600=F$3)*(GMWA!$CZ$2:$CZ$600=F$4)*(GMWA!$DB$2:$DB$600=F$1),0),$A13-1966)} -> 2136 | G13: {=INDEX(GMWA!$A$2:$DB$600,MATCH(1,(GMWA!$DA$2:$DA$600=G$3)*(GMWA!$CZ$2:$CZ$600=G$4)*(GMWA!$DB$2:$DB$600=G$1),0),$A13-1966)} -> 11.05835 | H13: {=INDEX(GMWA!$A$2:$DB$600,MATCH(1,(GMWA!$DA$2:$DA$600=H$3)*(GMWA!$CZ$2:$CZ$600=H$4)*(GMWA!$DB$2:$DB$600=H$1),0),$A13-1966)} -> 11487.63 | I13: {=INDEX(GMWA!$A$2:$DB$600,MATCH(1,(GMWA!$DA$2:$DA$600=I$3)*(GMWA!$CZ$2:$CZ$600=I$4)*(GMWA!$DB$2:$DB$600=I$1),0),$A13-1966)} -> 2.971176 | ... BI13: {=INDEX(GMWA!$A$2:$DB$600,MATCH(1,(GMWA!$DA$2:$DA$600=BI$3)*(GMWA!$CZ$2:$CZ$600=BI$4)*(GMWA!$DB$2:$DB$600=BI$1),0),$A13-1966)} -> 23.33603 | BK13: =100*(B13/V13) -> 9.3419333 | BL13: =100*(C13/W13) -> 6.5985116 | BM13: =100*(D13/X13) -> 5.6300012 | BN13: =100*(E13/Y13) -> 10.594664 | BO13: =100*(F13/Z13) -> 213600000 | BP13: =100*(G13/AA13) -> 6.6217665 | BQ13: =100*(H13/AB13) -> 6.2358653 | BR13: =100*(I13/AC13) -> 2.534986 | ... CD13: =100*(U13/AO13) -> 0.23387546 | CF13: =SUMIF(DataQ!$C:$C,DataA!$A13,DataQ!I:I) -> 7301.725 | CG13: =SUMIF(DataQ!$C:$C,DataA!$A13,DataQ!J:J) -> 276028.03 | CH13: =SUMIF(DataQ!$C:$C,DataA!$A13,DataQ!K:K) -> 1830.73 | CI13: =SUMIF(DataQ!$C:$C,DataA!$A13,DataQ!L:L) -> 1213.536 | CJ13: =SUMIF(DataQ!$C:$C,DataA!$A13,DataQ!M:M) -> 1160.2021 | CK13: =AVERAGEIF(DataQ!$C:$C,DataA!$A13,DataQ!N:N) -> 220753.85 | CL13: =SUMIF(DataQ!$C:$C,DataA!$A13,DataQ!O:O) -> -8546 | CN13: =SUMIF(DataQ!$B:$B,DataA!$A13,DataQ!P:P) -> -78.56225 | CO13: =SUMIF(DataQ!$B:$B,DataA!$A13,DataQ!Q:Q) -> -12426.5 | CP13: =SUMIF(DataQ!$B:$B,DataA!$A13,DataQ!R:R) -> -58.44036
A14: =+A13+1 -> 1980 | B14: {=INDEX(GMWA!$A$2:$DB$600,MATCH(1,(GMWA!$DA$2:$DA$600=B$3)*(GMWA!$CZ$2:$CZ$600=B$4)*(GMWA!$DB$2:$DB$600=B$1),0),$A14-1966)} -> 11972 | C14: {=INDEX(GMWA!$A$2:$DB$600,MATCH(1,(GMWA!$DA$2:$DA$600=C$3)*(GMWA!$CZ$2:$CZ$600=C$4)*(GMWA!$DB$2:$DB$600=C$1),0),$A14-1966)} -> 148.775 | D14: {=INDEX(GMWA!$A$2:$DB$600,MATCH(1,(GMWA!$DA$2:$DA$600=D$3)*(GMWA!$CZ$2:$CZ$600=D$4)*(GMWA!$DB$2:$DB$600=D$1),0),$A14-1966)} -> 7259.869 | E14: {=INDEX(GMWA!$A$2:$DB$600,MATCH(1,(GMWA!$DA$2:$DA$600=E$3)*(GMWA!$CZ$2:$CZ$600=E$4)*(GMWA!$DB$2:$DB$600=E$1),0),$A14-1966)} -> 17033 | F14: {=INDEX(GMWA!$A$2:$DB$600,MATCH(1,(GMWA!$DA$2:$DA$600=F$3)*(GMWA!$CZ$2:$CZ$600=F$4)*(GMWA!$DB$2:$DB$600=F$1),0),$A14-1966)} -> 2396 | G14: {=INDEX(GMWA!$A$2:$DB$600,MATCH(1,(GMWA!$DA$2:$DA$600=G$3)*(GMWA!$CZ$2:$CZ$600=G$4)*(GMWA!$DB$2:$DB$600=G$1),0),$A14-1966)} -> 13.37152 | H14: {=INDEX(GMWA!$A$2:$DB$600,MATCH(1,(GMWA!$DA$2:$DA$600=H$3)*(GMWA!$CZ$2:$CZ$600=H$4)*(GMWA!$DB$2:$DB$600=H$1),0),$A14-1966)} -> 16780.39 | I14: {=INDEX(GMWA!$A$2:$DB$600,MATCH(1,(GMWA!$DA$2:$DA$600=I$3)*(GMWA!$CZ$2:$CZ$600=I$4)*(GMWA!$DB$2:$DB$600=I$1),0),$A14-1966)} -> 3.154236 | ... BI14: {=INDEX(GMWA!$A$2:$DB$600,MATCH(1,(GMWA!$DA$2:$DA$600=BI$3)*(GMWA!$CZ$2:$CZ$600=BI$4)*(GMWA!$DB$2:$DB$600=BI$1),0),$A14-1966)} -> 23.33603 | BK14: =100*(B14/V14) -> 9.8501497 | BL14: =100*(C14/W14) -> 7.129675 | BM14: =100*(D14/X14) -> 6.1859824 | BN14: =100*(E14/Y14) -> 11.32566 | BO14: =100*(F14/Z14) -> 239600000 | BP14: =100*(G14/AA14) -> 7.5300266 | BQ14: =100*(H14/AB14) -> 6.4159937 | BR14: =100*(I14/AC14) -> 2.6306389 | ... CD14: =100*(U14/AO14) -> 0.12653751 | CF14: =SUMIF(DataQ!$C:$C,DataA!$A14,DataQ!I:I) -> 7286.675 | CG14: =SUMIF(DataQ!$C:$C,DataA!$A14,DataQ!J:J) -> 287722.88 | CH14: =SUMIF(DataQ!$C:$C,DataA!$A14,DataQ!K:K) -> 1834.03 | CI14: =SUMIF(DataQ!$C:$C,DataA!$A14,DataQ!L:L) -> 1221.947 | CJ14: =SUMIF(DataQ!$C:$C,DataA!$A14,DataQ!M:M) -> 1191.0443 | CK14: =AVERAGEIF(DataQ!$C:$C,DataA!$A14,DataQ!N:N) -> 225566.85 | CL14: =SUMIF(DataQ!$C:$C,DataA!$A14,DataQ!O:O) -> -11537 | CN14: =SUMIF(DataQ!$B:$B,DataA!$A14,DataQ!P:P) -> -128.273 | CO14: =SUMIF(DataQ!$B:$B,DataA!$A14,DataQ!Q:Q) -> -11822.5 | CP14: =SUMIF(DataQ!$B:$B,DataA!$A14,DataQ!R:R) -> -62.0868
A15: =+A14+1 -> 1981 | B15: {=INDEX(GMWA!$A$2:$DB$600,MATCH(1,(GMWA!$DA$2:$DA$600=B$3)*(GMWA!$CZ$2:$CZ$600=B$4)*(GMWA!$DB$2:$DB$600=B$1),0),$A15-1966)} -> 14207 | C15: {=INDEX(GMWA!$A$2:$DB$600,MATCH(1,(GMWA!$DA$2:$DA$600=C$3)*(GMWA!$CZ$2:$CZ$600=C$4)*(GMWA!$DB$2:$DB$600=C$1),0),$A15-1966)} -> 180.075 | D15: {=INDEX(GMWA!$A$2:$DB$600,MATCH(1,(GMWA!$DA$2:$DA$600=D$3)*(GMWA!$CZ$2:$CZ$600=D$4)*(GMWA!$DB$2:$DB$600=D$1),0),$A15-1966)} -> 8747.427 | E15: {=INDEX(GMWA!$A$2:$DB$600,MATCH(1,(GMWA!$DA$2:$DA$600=E$3)*(GMWA!$CZ$2:$CZ$600=E$4)*(GMWA!$DB$2:$DB$600=E$1),0),$A15-1966)} -> 22530 | F15: {=INDEX(GMWA!$A$2:$DB$600,MATCH(1,(GMWA!$DA$2:$DA$600=F$3)*(GMWA!$CZ$2:$CZ$600=F$4)*(GMWA!$DB$2:$DB$600=F$1),0),$A15-1966)} -> 2661 | G15: {=INDEX(GMWA!$A$2:$DB$600,MATCH(1,(GMWA!$DA$2:$DA$600=G$3)*(GMWA!$CZ$2:$CZ$600=G$4)*(GMWA!$DB$2:$DB$600=G$1),0),$A15-1966)} -> 19.54586 | H15: {=INDEX(GMWA!$A$2:$DB$600,MATCH(1,(GMWA!$DA$2:$DA$600=H$3)*(GMWA!$CZ$2:$CZ$600=H$4)*(GMWA!$DB$2:$DB$600=H$1),0),$A15-1966)} -> 24984.48 | I15: {=INDEX(GMWA!$A$2:$DB$600,MATCH(1,(GMWA!$DA$2:$DA$600=I$3)*(GMWA!$CZ$2:$CZ$600=I$4)*(GMWA!$DB$2:$DB$600=I$1),0),$A15-1966)} -> 3.402169 | ... BI15: {=INDEX(GMWA!$A$2:$DB$600,MATCH(1,(GMWA!$DA$2:$DA$600=BI$3)*(GMWA!$CZ$2:$CZ$600=BI$4)*(GMWA!$DB$2:$DB$600=BI$1),0),$A15-1966)} -> 23.33603 | BK15: =100*(B15/V15) -> 10.779906 | BL15: =100*(C15/W15) -> 7.8990206 | BM15: =100*(D15/X15) -> 6.1832381 | BN15: =100*(E15/Y15) -> 12.703478 | BO15: =100*(F15/Z15) -> 266100000 | BP15: =100*(G15/AA15) -> 8.206133 | BQ15: =100*(H15/AB15) -> 7.4091182 | BR15: =100*(I15/AC15) -> 2.8515348 | ... CD15: =100*(U15/AO15) -> 0.084084135 | CF15: =SUMIF(DataQ!$C:$C,DataA!$A15,DataQ!I:I) -> 7400.625 | CG15: =SUMIF(DataQ!$C:$C,DataA!$A15,DataQ!J:J) -> 299421.32 | CH15: =SUMIF(DataQ!$C:$C,DataA!$A15,DataQ!K:K) -> 1847.27 | CI15: =SUMIF(DataQ!$C:$C,DataA!$A15,DataQ!L:L) -> 1246.444 | CJ15: =SUMIF(DataQ!$C:$C,DataA!$A15,DataQ!M:M) -> 1200.915 | CK15: =AVERAGEIF(DataQ!$C:$C,DataA!$A15,DataQ!N:N) -> 230470.8 | CL15: =SUMIF(DataQ!$C:$C,DataA!$A15,DataQ!O:O) -> -5999 | CN15: =SUMIF(DataQ!$B:$B,DataA!$A15,DataQ!P:P) -> -130.469 | CO15: =SUMIF(DataQ!$B:$B,DataA!$A15,DataQ!Q:Q) -> -10937.75 | CP15: =SUMIF(DataQ!$B:$B,DataA!$A15,DataQ!R:R) -> -75.16716
A16: =+A15+1 -> 1982 | B16: {=INDEX(GMWA!$A$2:$DB$600,MATCH(1,(GMWA!$DA$2:$DA$600=B$3)*(GMWA!$CZ$2:$CZ$600=B$4)*(GMWA!$DB$2:$DB$600=B$1),0),$A16-1966)} -> 15540 | C16: {=INDEX(GMWA!$A$2:$DB$600,MATCH(1,(GMWA!$DA$2:$DA$600=C$3)*(GMWA!$CZ$2:$CZ$600=C$4)*(GMWA!$DB$2:$DB$600=C$1),0),$A16-1966)} -> 206.175 | D16: {=INDEX(GMWA!$A$2:$DB$600,MATCH(1,(GMWA!$DA$2:$DA$600=D$3)*(GMWA!$CZ$2:$CZ$600=D$4)*(GMWA!$DB$2:$DB$600=D$1),0),$A16-1966)} -> 10090.23 | E16: {=INDEX(GMWA!$A$2:$DB$600,MATCH(1,(GMWA!$DA$2:$DA$600=E$3)*(GMWA!$CZ$2:$CZ$600=E$4)*(GMWA!$DB$2:$DB$600=E$1),0),$A16-1966)} -> 27419 | F16: {=INDEX(GMWA!$A$2:$DB$600,MATCH(1,(GMWA!$DA$2:$DA$600=F$3)*(GMWA!$CZ$2:$CZ$600=F$4)*(GMWA!$DB$2:$DB$600=F$1),0),$A16-1966)} -> 3141 | G16: {=INDEX(GMWA!$A$2:$DB$600,MATCH(1,(GMWA!$DA$2:$DA$600=G$3)*(GMWA!$CZ$2:$CZ$600=G$4)*(GMWA!$DB$2:$DB$600=G$1),0),$A16-1966)} -> 25.32144 | H16: {=INDEX(GMWA!$A$2:$DB$600,MATCH(1,(GMWA!$DA$2:$DA$600=H$3)*(GMWA!$CZ$2:$CZ$600=H$4)*(GMWA!$DB$2:$DB$600=H$1),0),$A16-1966)} -> 36744.3 | I16: {=INDEX(GMWA!$A$2:$DB$600,MATCH(1,(GMWA!$DA$2:$DA$600=I$3)*(GMWA!$CZ$2:$CZ$600=I$4)*(GMWA!$DB$2:$DB$600=I$1),0),$A16-1966)} -> 3.559402 | ... BI16: {=INDEX(GMWA!$A$2:$DB$600,MATCH(1,(GMWA!$DA$2:$DA$600=BI$3)*(GMWA!$CZ$2:$CZ$600=BI$4)*(GMWA!$DB$2:$DB$600=BI$1),0),$A16-1966)} -> 23.33603 | BK16: =100*(B16/V16) -> 11.054298 | BL16: =100*(C16/W16) -> 8.0600771 | BM16: =100*(D16/X16) -> 6.1080353 | BN16: =100*(E16/Y16) -> 13.073351 | BO16: =100*(F16/Z16) -> 314100000 | BP16: =100*(G16/AA16) -> 7.6570143 | BQ16: =100*(H16/AB16) -> 8.4123511 | BR16: =100*(I16/AC16) -> 3.0350695 | ... CD16: =100*(U16/AO16) -> 0.06360694 | CF16: =SUMIF(DataQ!$C:$C,DataA!$A16,DataQ!I:I) -> 7333.425 | CG16: =SUMIF(DataQ!$C:$C,DataA!$A16,DataQ!J:J) -> 309237.08 | CH16: =SUMIF(DataQ!$C:$C,DataA!$A16,DataQ!K:K) -> 1834.54 | CI16: =SUMIF(DataQ!$C:$C,DataA!$A16,DataQ!L:L) -> 1272.743 | CJ16: =SUMIF(DataQ!$C:$C,DataA!$A16,DataQ!M:M) -> 1200.73 | CK16: =AVERAGEIF(DataQ!$C:$C,DataA!$A16,DataQ!N:N) -> 223200.35 | CL16: =SUMIF(DataQ!$C:$C,DataA!$A16,DataQ!O:O) -> -8542 | CN16: =SUMIF(DataQ!$B:$B,DataA!$A16,DataQ!P:P) -> -220.126 | CO16: =SUMIF(DataQ!$B:$B,DataA!$A16,DataQ!Q:Q) -> -11134.25 | CP16: =SUMIF(DataQ!$B:$B,DataA!$A16,DataQ!R:R) -> -74.95508
A17: =+A16+1 -> 1983 | B17: {=INDEX(GMWA!$A$2:$DB$600,MATCH(1,(GMWA!$DA$2:$DA$600=B$3)*(GMWA!$CZ$2:$CZ$600=B$4)*(GMWA!$DB$2:$DB$600=B$1),0),$A17-1966)} -> 15996 | C17: {=INDEX(GMWA!$A$2:$DB$600,MATCH(1,(GMWA!$DA$2:$DA$600=C$3)*(GMWA!$CZ$2:$CZ$600=C$4)*(GMWA!$DB$2:$DB$600=C$1),0),$A17-1966)} -> 227.975 | D17: {=INDEX(GMWA!$A$2:$DB$600,MATCH(1,(GMWA!$DA$2:$DA$600=D$3)*(GMWA!$CZ$2:$CZ$600=D$4)*(GMWA!$DB$2:$DB$600=D$1),0),$A17-1966)} -> 11534.9 | E17: {=INDEX(GMWA!$A$2:$DB$600,MATCH(1,(GMWA!$DA$2:$DA$600=E$3)*(GMWA!$CZ$2:$CZ$600=E$4)*(GMWA!$DB$2:$DB$600=E$1),0),$A17-1966)} -> 29858 | F17: {=INDEX(GMWA!$A$2:$DB$600,MATCH(1,(GMWA!$DA$2:$DA$600=F$3)*(GMWA!$CZ$2:$CZ$600=F$4)*(GMWA!$DB$2:$DB$600=F$1),0),$A17-1966)} -> 3764 | G17: {=INDEX(GMWA!$A$2:$DB$600,MATCH(1,(GMWA!$DA$2:$DA$600=G$3)*(GMWA!$CZ$2:$CZ$600=G$4)*(GMWA!$DB$2:$DB$600=G$1),0),$A17-1966)} -> 37.50747 | H17: {=INDEX(GMWA!$A$2:$DB$600,MATCH(1,(GMWA!$DA$2:$DA$600=H$3)*(GMWA!$CZ$2:$CZ$600=H$4)*(GMWA!$DB$2:$DB$600=H$1),0),$A17-1966)} -> 43218.67 | I17: {=INDEX(GMWA!$A$2:$DB$600,MATCH(1,(GMWA!$DA$2:$DA$600=I$3)*(GMWA!$CZ$2:$CZ$600=I$4)*(GMWA!$DB$2:$DB$600=I$1),0),$A17-1966)} -> 3.657443 | ... BI17: {=INDEX(GMWA!$A$2:$DB$600,MATCH(1,(GMWA!$DA$2:$DA$600=BI$3)*(GMWA!$CZ$2:$CZ$600=BI$4)*(GMWA!$DB$2:$DB$600=BI$1),0),$A17-1966)} -> 23.33603 | BK17: =100*(B17/V17) -> 10.51792 | BL17: =100*(C17/W17) -> 8.0021383 | BM17: =100*(D17/X17) -> 6.0747088 | BN17: =100*(E17/Y17) -> 11.854622 | BO17: =100*(F17/Z17) -> 376400000 | BP17: =100*(G17/AA17) -> 8.8404927 | BQ17: =100*(H17/AB17) -> 8.3091047 | BR17: =100*(I17/AC17) -> 3.1187426 | ... CD17: =100*(U17/AO17) -> 0.0458311 | CF17: =SUMIF(DataQ!$C:$C,DataA!$A17,DataQ!I:I) -> 7800.95 | CG17: =SUMIF(DataQ!$C:$C,DataA!$A17,DataQ!J:J) -> 320860.99 | CH17: =SUMIF(DataQ!$C:$C,DataA!$A17,DataQ!K:K) -> 1879.96 | CI17: =SUMIF(DataQ!$C:$C,DataA!$A17,DataQ!L:L) -> 1287.699 | CJ17: =SUMIF(DataQ!$C:$C,DataA!$A17,DataQ!M:M) -> 1229.587 | CK17: =AVERAGEIF(DataQ!$C:$C,DataA!$A17,DataQ!N:N) -> 233186.72 | CL17: =SUMIF(DataQ!$C:$C,DataA!$A17,DataQ!O:O) -> -11802 | CN17: =SUMIF(DataQ!$B:$B,DataA!$A17,DataQ!P:P) -> -265.23725 | CO17: =SUMIF(DataQ!$B:$B,DataA!$A17,DataQ!Q:Q) -> -11809.25 | CP17: =SUMIF(DataQ!$B:$B,DataA!$A17,DataQ!R:R) -> -71.17676
A18: =+A17+1 -> 1984 | B18: {=INDEX(GMWA!$A$2:$DB$600,MATCH(1,(GMWA!$DA$2:$DA$600=B$3)*(GMWA!$CZ$2:$CZ$600=B$4)*(GMWA!$DB$2:$DB$600=B$1),0),$A18-1966)} -> 17461 | C18: {=INDEX(GMWA!$A$2:$DB$600,MATCH(1,(GMWA!$DA$2:$DA$600=C$3)*(GMWA!$CZ$2:$CZ$600=C$4)*(GMWA!$DB$2:$DB$600=C$1),0),$A18-1966)} -> 260.05 | D18: {=INDEX(GMWA!$A$2:$DB$600,MATCH(1,(GMWA!$DA$2:$DA$600=D$3)*(GMWA!$CZ$2:$CZ$600=D$4)*(GMWA!$DB$2:$DB$600=D$1),0),$A18-1966)} -> 12792.81 | E18: {=INDEX(GMWA!$A$2:$DB$600,MATCH(1,(GMWA!$DA$2:$DA$600=E$3)*(GMWA!$CZ$2:$CZ$600=E$4)*(GMWA!$DB$2:$DB$600=E$1),0),$A18-1966)} -> 35147 | F18: {=INDEX(GMWA!$A$2:$DB$600,MATCH(1,(GMWA!$DA$2:$DA$600=F$3)*(GMWA!$CZ$2:$CZ$600=F$4)*(GMWA!$DB$2:$DB$600=F$1),0),$A18-1966)} -> 4951 | G18: {=INDEX(GMWA!$A$2:$DB$600,MATCH(1,(GMWA!$DA$2:$DA$600=G$3)*(GMWA!$CZ$2:$CZ$600=G$4)*(GMWA!$DB$2:$DB$600=G$1),0),$A18-1966)} -> 49.15562 | H18: {=INDEX(GMWA!$A$2:$DB$600,MATCH(1,(GMWA!$DA$2:$DA$600=H$3)*(GMWA!$CZ$2:$CZ$600=H$4)*(GMWA!$DB$2:$DB$600=H$1),0),$A18-1966)} -> 51442.58 | I18: {=INDEX(GMWA!$A$2:$DB$600,MATCH(1,(GMWA!$DA$2:$DA$600=I$3)*(GMWA!$CZ$2:$CZ$600=I$4)*(GMWA!$DB$2:$DB$600=I$1),0),$A18-1966)} -> 3.631457 | ... BI18: {=INDEX(GMWA!$A$2:$DB$600,MATCH(1,(GMWA!$DA$2:$DA$600=BI$3)*(GMWA!$CZ$2:$CZ$600=BI$4)*(GMWA!$DB$2:$DB$600=BI$1),0),$A18-1966)} -> 23.33603 | BK18: =100*(B18/V18) -> 10.66982 | BL18: =100*(C18/W18) -> 8.1117155 | BM18: =100*(D18/X18) -> 6.140765 | BN18: =100*(E18/Y18) -> 12.091678 | BO18: =100*(F18/Z18) -> 495100000 | BP18: =100*(G18/AA18) -> 10.318747 | BQ18: =100*(H18/AB18) -> 8.6560477 | BR18: =100*(I18/AC18) -> 3.110096 | ... CD18: =100*(U18/AO18) -> 0.033652669 | CF18: =SUMIF(DataQ!$C:$C,DataA!$A18,DataQ!I:I) -> 8286.8 | CG18: =SUMIF(DataQ!$C:$C,DataA!$A18,DataQ!J:J) -> 335688.83 | CH18: =SUMIF(DataQ!$C:$C,DataA!$A18,DataQ!K:K) -> 1924.4 | CI18: =SUMIF(DataQ!$C:$C,DataA!$A18,DataQ!L:L) -> 1309.22 | CJ18: =SUMIF(DataQ!$C:$C,DataA!$A18,DataQ!M:M) -> 1263.855 | CK18: =AVERAGEIF(DataQ!$C:$C,DataA!$A18,DataQ!N:N) -> 246574.27 | CL18: =SUMIF(DataQ!$C:$C,DataA!$A18,DataQ!O:O) -> -12535 | CN18: =SUMIF(DataQ!$B:$B,DataA!$A18,DataQ!P:P) -> -249.608 | CO18: =SUMIF(DataQ!$B:$B,DataA!$A18,DataQ!Q:Q) -> -8204.75 | CP18: =SUMIF(DataQ!$B:$B,DataA!$A18,DataQ!R:R) -> -66.7484
A19: =+A18+1 -> 1985 | B19: {=INDEX(GMWA!$A$2:$DB$600,MATCH(1,(GMWA!$DA$2:$DA$600=B$3)*(GMWA!$CZ$2:$CZ$600=B$4)*(GMWA!$DB$2:$DB$600=B$1),0),$A19-1966)} -> 19036 | C19: {=INDEX(GMWA!$A$2:$DB$600,MATCH(1,(GMWA!$DA$2:$DA$600=C$3)*(GMWA!$CZ$2:$CZ$600=C$4)*(GMWA!$DB$2:$DB$600=C$1),0),$A19-1966)} -> 285.75 | D19: {=INDEX(GMWA!$A$2:$DB$600,MATCH(1,(GMWA!$DA$2:$DA$600=D$3)*(GMWA!$CZ$2:$CZ$600=D$4)*(GMWA!$DB$2:$DB$600=D$1),0),$A19-1966)} -> 13766.58 | E19: {=INDEX(GMWA!$A$2:$DB$600,MATCH(1,(GMWA!$DA$2:$DA$600=E$3)*(GMWA!$CZ$2:$CZ$600=E$4)*(GMWA!$DB$2:$DB$600=E$1),0),$A19-1966)} -> 40585 | F19: {=INDEX(GMWA!$A$2:$DB$600,MATCH(1,(GMWA!$DA$2:$DA$600=F$3)*(GMWA!$CZ$2:$CZ$600=F$4)*(GMWA!$DB$2:$DB$600=F$1),0),$A19-1966)} -> 6665 | G19: {=INDEX(GMWA!$A$2:$DB$600,MATCH(1,(GMWA!$DA$2:$DA$600=G$3)*(GMWA!$CZ$2:$CZ$600=G$4)*(GMWA!$DB$2:$DB$600=G$1),0),$A19-1966)} -> 55.07229 | H19: {=INDEX(GMWA!$A$2:$DB$600,MATCH(1,(GMWA!$DA$2:$DA$600=H$3)*(GMWA!$CZ$2:$CZ$600=H$4)*(GMWA!$DB$2:$DB$600=H$1),0),$A19-1966)} -> 62413.66 | I19: {=INDEX(GMWA!$A$2:$DB$600,MATCH(1,(GMWA!$DA$2:$DA$600=I$3)*(GMWA!$CZ$2:$CZ$600=I$4)*(GMWA!$DB$2:$DB$600=I$1),0),$A19-1966)} -> 3.735457 | ... BI19: {=INDEX(GMWA!$A$2:$DB$600,MATCH(1,(GMWA!$DA$2:$DA$600=BI$3)*(GMWA!$CZ$2:$CZ$600=BI$4)*(GMWA!$DB$2:$DB$600=BI$1),0),$A19-1966)} -> 23.33603 | BK19: =100*(B19/V19) -> 10.810823 | BL19: =100*(C19/W19) -> 7.8436895 | BM19: =100*(D19/X19) -> 5.945223 | BN19: =100*(E19/Y19) -> 11.919692 | BO19: =100*(F19/Z19) -> 666500000 | BP19: =100*(G19/AA19) -> 10.996226 | BQ19: =100*(H19/AB19) -> 9.7090807 | BR19: =100*(I19/AC19) -> 3.2611006 | ... CD19: =100*(U19/AO19) -> 0.025463467 | CF19: =SUMIF(DataQ!$C:$C,DataA!$A19,DataQ!I:I) -> 8624.075 | CG19: =SUMIF(DataQ!$C:$C,DataA!$A19,DataQ!J:J) -> 353340.08 | CH19: =SUMIF(DataQ!$C:$C,DataA!$A19,DataQ!K:K) -> 1978.87 | CI19: =SUMIF(DataQ!$C:$C,DataA!$A19,DataQ!L:L) -> 1334.186 | CJ19: =SUMIF(DataQ!$C:$C,DataA!$A19,DataQ!M:M) -> 1304.003 | CK19: =AVERAGEIF(DataQ!$C:$C,DataA!$A19,DataQ!N:N) -> 256722.58 | CL19: =SUMIF(DataQ!$C:$C,DataA!$A19,DataQ!O:O) -> -9034 | CN19: =SUMIF(DataQ!$B:$B,DataA!$A19,DataQ!P:P) -> -270.54324 | CO19: =SUMIF(DataQ!$B:$B,DataA!$A19,DataQ!Q:Q) -> -4308.75 | CP19: =SUMIF(DataQ!$B:$B,DataA!$A19,DataQ!R:R) -> -82.98528
... A94: =+A93+1 -> 2060 | B94: {=INDEX(GMWA!$A$2:$DB$600,MATCH(1,(GMWA!$DA$2:$DA$600=B$3)*(GMWA!$CZ$2:$CZ$600=B$4)*(GMWA!$DB$2:$DB$600=B$1),0),$A94-1966)} -> 242677.3 | C94: {=INDEX(GMWA!$A$2:$DB$600,MATCH(1,(GMWA!$DA$2:$DA$600=C$3)*(GMWA!$CZ$2:$CZ$600=C$4)*(GMWA!$DB$2:$DB$600=C$1),0),$A94-1966)} -> 6563.423 | D94: {=INDEX(GMWA!$A$2:$DB$600,MATCH(1,(GMWA!$DA$2:$DA$600=D$3)*(GMWA!$CZ$2:$CZ$600=D$4)*(GMWA!$DB$2:$DB$600=D$1),0),$A94-1966)} -> 50899.07 | E94: {=INDEX(GMWA!$A$2:$DB$600,MATCH(1,(GMWA!$DA$2:$DA$600=E$3)*(GMWA!$CZ$2:$CZ$600=E$4)*(GMWA!$DB$2:$DB$600=E$1),0),$A94-1966)} -> 251970.7 | F94: {=INDEX(GMWA!$A$2:$DB$600,MATCH(1,(GMWA!$DA$2:$DA$600=F$3)*(GMWA!$CZ$2:$CZ$600=F$4)*(GMWA!$DB$2:$DB$600=F$1),0),$A94-1966)} -> 208572.4 | G94: {=INDEX(GMWA!$A$2:$DB$600,MATCH(1,(GMWA!$DA$2:$DA$600=G$3)*(GMWA!$CZ$2:$CZ$600=G$4)*(GMWA!$DB$2:$DB$600=G$1),0),$A94-1966)} -> 40.88998 | H94: {=INDEX(GMWA!$A$2:$DB$600,MATCH(1,(GMWA!$DA$2:$DA$600=H$3)*(GMWA!$CZ$2:$CZ$600=H$4)*(GMWA!$DB$2:$DB$600=H$1),0),$A94-1966)} -> 121233.9 | I94: {=INDEX(GMWA!$A$2:$DB$600,MATCH(1,(GMWA!$DA$2:$DA$600=I$3)*(GMWA!$CZ$2:$CZ$600=I$4)*(GMWA!$DB$2:$DB$600=I$1),0),$A94-1966)} -> 5.516781 | ... BI94: {=INDEX(GMWA!$A$2:$DB$600,MATCH(1,(GMWA!$DA$2:$DA$600=BI$3)*(GMWA!$CZ$2:$CZ$600=BI$4)*(GMWA!$DB$2:$DB$600=BI$1),0),$A94-1966)} -> 868.6583 | BK94: =100*(B94/V94) -> 2.1777769 | BL94: =100*(C94/W94) -> 3.7110965 | BM94: =100*(D94/X94) -> 2.0881695 | BN94: =100*(E94/Y94) -> 3.3623844 | BO94: =100*(F94/Z94) -> 3.6049571 | BP94: =100*(G94/AA94) -> 3.3011011 | BQ94: =100*(H94/AB94) -> 2.0362684 | BR94: =100*(I94/AC94) -> 0.71743771 | ... CD94: =100*(U94/AO94) -> 3.071568 | CF94: =SUMIF(DataQ!$C:$C,DataA!$A94,DataQ!I:I) -> 34098.66 | CG94: =SUMIF(DataQ!$C:$C,DataA!$A94,DataQ!J:J) -> 487700.4 | CH94: =SUMIF(DataQ!$C:$C,DataA!$A94,DataQ!K:K) -> 3674.604 | CI94: =SUMIF(DataQ!$C:$C,DataA!$A94,DataQ!L:L) -> 2427.3335 | CJ94: =SUMIF(DataQ!$C:$C,DataA!$A94,DataQ!M:M) -> 1644.1354 | CK94: =AVERAGEIF(DataQ!$C:$C,DataA!$A94,DataQ!N:N) -> 1157837.3 | CL94: =SUMIF(DataQ!$C:$C,DataA!$A94,DataQ!O:O) -> -396411.22 | CN94: =SUMIF(DataQ!$B:$B,DataA!$A94,DataQ!P:P) -> -3859.7766 | CO94: =SUMIF(DataQ!$B:$B,DataA!$A94,DataQ!Q:Q) -> -41921.73 | CP94: =SUMIF(DataQ!$B:$B,DataA!$A94,DataQ!R:R) -> -185.78711

Sheet Data Q to A
B1: CY total | P1: CY end | W1: CY end | AD1: CY total | AK1: FY end | AL1: FY end
B2: =DataQ!H1 -> Desktop | C2: =DataQ!I1 -> Desktop | D2: =DataQ!J1 -> Desktop | E2: =DataQ!K1 -> Desktop | F2: =DataQ!L1 -> Desktop | G2: =DataQ!M1 -> Desktop | H2: =DataQ!N1 -> Desktop | I2: =DataQ!O1 -> Desktop | ... AJ2: =DataQ!AP1 -> Desktop | AK2: =DataQ!AC1 -> Desktop | AL2: =DataQ!AJ1 -> Desktop
B3: =DataQ!H2 -> UK | C3: =DataQ!I2 -> US | D3: =DataQ!J2 -> Japan | E3: =DataQ!K2 -> Germany | F3: =DataQ!L2 -> France | G3: =DataQ!M2 -> Italy | H3: =DataQ!N2 -> Canada | I3: =DataQ!O2 -> UK | ... AJ3: =DataQ!AP2 -> Canada | AK3: =DataQ!AC2 -> UK | AL3: =DataQ!AJ2 -> UK
B4: =DataQ!H3 -> GDP | C4: =DataQ!I3 -> GDP | D4: =DataQ!J3 -> GDP | E4: =DataQ!K3 -> GDP | F4: =DataQ!L3 -> GDP | G4: =DataQ!M3 -> GDP | H4: =DataQ!N3 -> GDP | I4: =DataQ!O3 -> GB | ... AJ4: =DataQ!AP3 -> GDP! | AK4: =DataQ!AC3 -> GNDBT | AL4: =DataQ!AJ3 -> GDP!
B5: =DataQ!H4 -> GBR | C5: =DataQ!I4 -> USA | D5: =DataQ!J4 -> JPN | E5: =DataQ!K4 -> DEU | F5: =DataQ!L4 -> FRA | G5: =DataQ!M4 -> ITA | H5: =DataQ!N4 -> CAN | I5: =DataQ!O4 -> GBR | ... AJ5: =DataQ!AP4 -> CAN | AK5: =DataQ!AC4 -> GBR | AL5: =DataQ!AJ4 -> GBR
B6: =DataQ!H5 -> L | C6: =DataQ!I5 -> L | D6: =DataQ!J5 -> L | E6: =DataQ!K5 -> L | F6: =DataQ!L5 -> L | G6: =DataQ!M5 -> L | H6: =DataQ!N5 -> L | I6: =DataQ!O5 -> L | ... AJ6: =DataQ!AP5 -> L | AK6: =DataQ!AC5 -> L | AL6: =DataQ!AJ5 -> L
B7: =DataQ!H6 -> 202601 | C7: =DataQ!I6 -> 202601 | D7: =DataQ!J6 -> 202504 | E7: =DataQ!K6 -> 202601 | F7: =DataQ!L6 -> 202601 | G7: =DataQ!M6 -> 202601 | H7: =DataQ!N6 -> 202601 | I7: =DataQ!O6 -> 202601 | ... AJ7: =DataQ!AP6 -> 202601 | AK7: =DataQ!AC6 -> 202601 | AL7: =DataQ!AJ6 -> 202601
A8: 1973 | B8: =SUMIF(DataQ!$B:$B,'Data Q to A'!$A8,DataQ!H:H) -> 1063550 | C8: =SUMIF(DataQ!$B:$B,'Data Q to A'!$A8,DataQ!I:I) -> 6106.35 | D8: =SUMIF(DataQ!$B:$B,'Data Q to A'!$A8,DataQ!J:J) -> 220315.45 | E8: =SUMIF(DataQ!$B:$B,'Data Q to A'!$A8,DataQ!K:K) -> 1556.14 | F8: =SUMIF(DataQ!$B:$B,'Data Q to A'!$A8,DataQ!L:L) -> 999.15 | G8: =SUMIF(DataQ!$B:$B,'Data Q to A'!$A8,DataQ!M:M) -> 932.5699 | H8: =SUMIF(DataQ!$B:$B,'Data Q to A'!$A8,DataQ!N:N) -> 707164.6 | I8: =SUMIF(DataQ!$B:$B,'Data Q to A'!$A8,DataQ!O:O) -> -2740 | J8: =SUMIF(DataQ!$B:$B,'Data Q to A'!$A8,DataQ!P:P) -> -44.59125 | K8: =SUMIF(DataQ!$B:$B,'Data Q to A'!$A8,DataQ!Q:Q) -> -2130.75 | L8: =SUMIF(DataQ!$B:$B,'Data Q to A'!$A8,DataQ!R:R) -> -23.045528 | M8: =SUMIF(DataQ!$B:$B,'Data Q to A'!$A8,DataQ!S:S) -> 0.8040001 | N8: =SUMIF(DataQ!$B:$B,'Data Q to A'!$A8,DataQ!T:T) -> -3.2833435 | O8: =SUMIF(DataQ!$B:$B,'Data Q to A'!$A8,DataQ!U:U) -> 1605 | P8: =SUMIF(DataQ!$F:$F,'Data Q to A'!$A8,DataQ!V:V) -> 35969.43 | Q8: =SUMIF(DataQ!$F:$F,'Data Q to A'!$A8,DataQ!W:W) -> 1158.847 | R8: =SUMIF(DataQ!$F:$F,'Data Q to A'!$A8,DataQ!X:X) -> 17803 | S8: =SUMIF(DataQ!$F:$F,'Data Q to A'!$A8,DataQ!Y:Y) -> 89.06523 | T8: =SUMIF(DataQ!$F:$F,'Data Q to A'!$A8,DataQ!Z:Z) -> 56.7663 | U8: =SUMIF(DataQ!$F:$F,'Data Q to A'!$A8,DataQ!AA:AA) -> 36.414 | V8: =SUMIF(DataQ!$F:$F,'Data Q to A'!$A8,DataQ!AB:AB) -> 64923 | W8: =SUMIF(DataQ!$F:$F,'Data Q to A'!$A8,DataQ!AC:AC) -> 31563.38 | X8: =SUMIF(DataQ!$F:$F,'Data Q to A'!$A8,DataQ!AD:AD) -> 917.226 | Y8: =SUMIF(DataQ!$F:$F,'Data Q to A'!$A8,DataQ!AE:AE) -> -11201.23 | Z8: =SUMIF(DataQ!$F:$F,'Data Q to A'!$A8,DataQ!AF:AF) -> -15.92239 | AA8: =SUMIF(DataQ!$F:$F,'Data Q to A'!$A8,DataQ!AG:AG) -> 1.675 | AB8: =SUMIF(DataQ!$F:$F,'Data Q to A'!$A8,DataQ!AH:AH) -> 24.066 | AC8: =SUMIF(DataQ!$F:$F,'Data Q to A'!$A8,DataQ!AI:AI) -> 10761 | AD8: =SUMIF(DataQ!$B:$B,'Data Q to A'!$A8,DataQ!AJ:AJ) -> 81809 | AE8: =SUMIF(DataQ!$B:$B,'Data Q to A'!$A8,DataQ!AK:AK) -> 1425.375 | AF8: =SUMIF(DataQ!$B:$B,'Data Q to A'!$A8,DataQ!AL:AL) -> 115345.45 | AG8: =SUMIF(DataQ!$B:$B,'Data Q to A'!$A8,DataQ!AM:AM) -> 553.1868 | AH8: =SUMIF(DataQ!$B:$B,'Data Q to A'!$A8,DataQ!AN:AN) -> 177.825 | AI8: =SUMIF(DataQ!$B:$B,'Data Q to A'!$A8,DataQ!AO:AO) -> 53.293 | AJ8: =SUMIF(DataQ!$B:$B,'Data Q to A'!$A8,DataQ!AP:AP) -> 132966 | AK8: =SUMIF(DataQ!$E:$E,'Data Q to A'!$A8,DataQ!AC:AC) -> 32701.34 | AL8: =SUMIF(DataQ!$D:$D,'Data Q to A'!$A8,DataQ!AJ:AJ) -> 85670
A9: 1974 | B9: =SUMIF(DataQ!$B:$B,'Data Q to A'!$A9,DataQ!H:H) -> 1036973 | C9: =SUMIF(DataQ!$B:$B,'Data Q to A'!$A9,DataQ!I:I) -> 6073.4 | D9: =SUMIF(DataQ!$B:$B,'Data Q to A'!$A9,DataQ!J:J) -> 218075.07 | E9: =SUMIF(DataQ!$B:$B,'Data Q to A'!$A9,DataQ!K:K) -> 1571.34 | F9: =SUMIF(DataQ!$B:$B,'Data Q to A'!$A9,DataQ!L:L) -> 1043.039 | G9: =SUMIF(DataQ!$B:$B,'Data Q to A'!$A9,DataQ!M:M) -> 981.7783 | H9: =SUMIF(DataQ!$B:$B,'Data Q to A'!$A9,DataQ!N:N) -> 730909.6 | I9: =SUMIF(DataQ!$B:$B,'Data Q to A'!$A9,DataQ!O:O) -> -4310 | J9: =SUMIF(DataQ!$B:$B,'Data Q to A'!$A9,DataQ!P:P) -> -59.765 | K9: =SUMIF(DataQ!$B:$B,'Data Q to A'!$A9,DataQ!Q:Q) -> -2482.25 | L9: =SUMIF(DataQ!$B:$B,'Data Q to A'!$A9,DataQ!R:R) -> -36.381582 | M9: =SUMIF(DataQ!$B:$B,'Data Q to A'!$A9,DataQ!S:S) -> 0.4830001 | N9: =SUMIF(DataQ!$B:$B,'Data Q to A'!$A9,DataQ!T:T) -> -4.0740696 | O9: =SUMIF(DataQ!$B:$B,'Data Q to A'!$A9,DataQ!U:U) -> 3052 | P9: =SUMIF(DataQ!$F:$F,'Data Q to A'!$A9,DataQ!V:V) -> 48829.88 | Q9: =SUMIF(DataQ!$F:$F,'Data Q to A'!$A9,DataQ!W:W) -> 1251.709 | R9: =SUMIF(DataQ!$F:$F,'Data Q to A'!$A9,DataQ!X:X) -> 16534 | S9: =SUMIF(DataQ!$F:$F,'Data Q to A'!$A9,DataQ!Y:Y) -> 106.168 | T9: =SUMIF(DataQ!$F:$F,'Data Q to A'!$A9,DataQ!Z:Z) -> 61.89546 | U9: =SUMIF(DataQ!$F:$F,'Data Q to A'!$A9,DataQ!AA:AA) -> 45.795 | V9: =SUMIF(DataQ!$F:$F,'Data Q to A'!$A9,DataQ!AB:AB) -> 74036 | W9: =SUMIF(DataQ!$F:$F,'Data Q to A'!$A9,DataQ!AC:AC) -> 37800.67 | X9: =SUMIF(DataQ!$F:$F,'Data Q to A'!$A9,DataQ!AD:AD) -> 994.256 | Y9: =SUMIF(DataQ!$F:$F,'Data Q to A'!$A9,DataQ!AE:AE) -> -12349.15 | Z9: =SUMIF(DataQ!$F:$F,'Data Q to A'!$A9,DataQ!AF:AF) -> -13.40793 | AA9: =SUMIF(DataQ!$F:$F,'Data Q to A'!$A9,DataQ!AG:AG) -> 0.279 | AB9: =SUMIF(DataQ!$F:$F,'Data Q to A'!$A9,DataQ!AH:AH) -> 29.201 | AC9: =SUMIF(DataQ!$F:$F,'Data Q to A'!$A9,DataQ!AI:AI) -> 9218 | AD9: =SUMIF(DataQ!$B:$B,'Data Q to A'!$A9,DataQ!AJ:AJ) -> 92686 | AE9: =SUMIF(DataQ!$B:$B,'Data Q to A'!$A9,DataQ!AK:AK) -> 1545.25 | AF9: =SUMIF(DataQ!$B:$B,'Data Q to A'!$A9,DataQ!AL:AL) -> 137675.47 | AG9: =SUMIF(DataQ!$B:$B,'Data Q to A'!$A9,DataQ!AM:AM) -> 599.3288 | AH9: =SUMIF(DataQ!$B:$B,'Data Q to A'!$A9,DataQ!AN:AN) -> 207.305 | AI9: =SUMIF(DataQ!$B:$B,'Data Q to A'!$A9,DataQ!AO:AO) -> 67.409 | AJ9: =SUMIF(DataQ!$B:$B,'Data Q to A'!$A9,DataQ!AP:AP) -> 158176 | AK9: =SUMIF(DataQ!$E:$E,'Data Q to A'!$A9,DataQ!AC:AC) -> 40349.93 | AL9: =SUMIF(DataQ!$D:$D,'Data Q to A'!$A9,DataQ!AJ:AJ) -> 103841
A10: 1975 | B10: =SUMIF(DataQ!$B:$B,'Data Q to A'!$A10,DataQ!H:H) -> 1021204 | C10: =SUMIF(DataQ!$B:$B,'Data Q to A'!$A10,DataQ!I:I) -> 6060.85 | D10: =SUMIF(DataQ!$B:$B,'Data Q to A'!$A10,DataQ!J:J) -> 224902.08 | E10: =SUMIF(DataQ!$B:$B,'Data Q to A'!$A10,DataQ!K:K) -> 1557.62 | F10: =SUMIF(DataQ!$B:$B,'Data Q to A'!$A10,DataQ!L:L) -> 1033.444 | G10: =SUMIF(DataQ!$B:$B,'Data Q to A'!$A10,DataQ!M:M) -> 961.6561 | H10: =SUMIF(DataQ!$B:$B,'Data Q to A'!$A10,DataQ!N:N) -> 742205.1 | I10: =SUMIF(DataQ!$B:$B,'Data Q to A'!$A10,DataQ!O:O) -> -7211 | J10: =SUMIF(DataQ!$B:$B,'Data Q to A'!$A10,DataQ!P:P) -> -128.606 | K10: =SUMIF(DataQ!$B:$B,'Data Q to A'!$A10,DataQ!Q:Q) -> -7342 | L10: =SUMIF(DataQ!$B:$B,'Data Q to A'!$A10,DataQ!R:R) -> -62.44885 | M10: =SUMIF(DataQ!$B:$B,'Data Q to A'!$A10,DataQ!S:S) -> -4.3009993 | N10: =SUMIF(DataQ!$B:$B,'Data Q to A'!$A10,DataQ!T:T) -> -7.734278 | O10: =SUMIF(DataQ!$B:$B,'Data Q to A'!$A10,DataQ!U:U) -> -4505 | P10: =SUMIF(DataQ!$F:$F,'Data Q to A'!$A10,DataQ!V:V) -> 62646 | Q10: =SUMIF(DataQ!$F:$F,'Data Q to A'!$A10,DataQ!W:W) -> 1412.028 | R10: =SUMIF(DataQ!$F:$F,'Data Q to A'!$A10,DataQ!X:X) -> 29223 | S10: =SUMIF(DataQ!$F:$F,'Data Q to A'!$A10,DataQ!Y:Y) -> 136.7461 | T10: =SUMIF(DataQ!$F:$F,'Data Q to A'!$A10,DataQ!Z:Z) -> 70.28793 | U10: =SUMIF(DataQ!$F:$F,'Data Q to A'!$A10,DataQ!AA:AA) -> 61.44 | V10: =SUMIF(DataQ!$F:$F,'Data Q to A'!$A10,DataQ!AB:AB) -> 82299 | W10: =SUMIF(DataQ!$F:$F,'Data Q to A'!$A10,DataQ!AC:AC) -> 46452.6 | X10: =SUMIF(DataQ!$F:$F,'Data Q to A'!$A10,DataQ!AD:AD) -> 1128.134 | Y10: =SUMIF(DataQ!$F:$F,'Data Q to A'!$A10,DataQ!AE:AE) -> -8692.456 | Z10: =SUMIF(DataQ!$F:$F,'Data Q to A'!$A10,DataQ!AF:AF) -> -2.992506 | AA10: =SUMIF(DataQ!$F:$F,'Data Q to A'!$A10,DataQ!AG:AG) -> 1.675 | AB10: =SUMIF(DataQ!$F:$F,'Data Q to A'!$A10,DataQ!AH:AH) -> 40.098 | AC10: =SUMIF(DataQ!$F:$F,'Data Q to A'!$A10,DataQ!AI:AI) -> 15920 | AD10: =SUMIF(DataQ!$B:$B,'Data Q to A'!$A10,DataQ!AJ:AJ) -> 115095 | AE10: =SUMIF(DataQ!$B:$B,'Data Q to A'!$A10,DataQ!AK:AK) -> 1684.9 | AF10: =SUMIF(DataQ!$B:$B,'Data Q to A'!$A10,DataQ!AL:AL) -> 152524.06 | AG10: =SUMIF(DataQ!$B:$B,'Data Q to A'!$A10,DataQ!AM:AM) -> 627.6409 | AH10: =SUMIF(DataQ!$B:$B,'Data Q to A'!$A10,DataQ!AN:AN) -> 233.583 | AI10: =SUMIF(DataQ!$B:$B,'Data Q to A'!$A10,DataQ!AO:AO) -> 76.902 | AJ10: =SUMIF(DataQ!$B:$B,'Data Q to A'!$A10,DataQ!AP:AP) -> 177928 | AK10: =SUMIF(DataQ!$E:$E,'Data Q to A'!$A10,DataQ!AC:AC) -> 48463.17 | AL10: =SUMIF(DataQ!$D:$D,'Data Q to A'!$A10,DataQ!AJ:AJ) -> 125918
A11: 1976 | B11: =SUMIF(DataQ!$B:$B,'Data Q to A'!$A11,DataQ!H:H) -> 1051973 | C11: =SUMIF(DataQ!$B:$B,'Data Q to A'!$A11,DataQ!I:I) -> 6387.425 | D11: =SUMIF(DataQ!$B:$B,'Data Q to A'!$A11,DataQ!J:J) -> 233973.44 | E11: =SUMIF(DataQ!$B:$B,'Data Q to A'!$A11,DataQ!K:K) -> 1626.82 | F11: =SUMIF(DataQ!$B:$B,'Data Q to A'!$A11,DataQ!L:L) -> 1078.312 | G11: =SUMIF(DataQ!$B:$B,'Data Q to A'!$A11,DataQ!M:M) -> 1024.4384 | H11: =SUMIF(DataQ!$B:$B,'Data Q to A'!$A11,DataQ!N:N) -> 785915.6 | I11: =SUMIF(DataQ!$B:$B,'Data Q to A'!$A11,DataQ!O:O) -> -7961 | J11: =SUMIF(DataQ!$B:$B,'Data Q to A'!$A11,DataQ!P:P) -> -104.50225 | K11: =SUMIF(DataQ!$B:$B,'Data Q to A'!$A11,DataQ!Q:Q) -> -9301 | L11: =SUMIF(DataQ!$B:$B,'Data Q to A'!$A11,DataQ!R:R) -> -53.17428 | M11: =SUMIF(DataQ!$B:$B,'Data Q to A'!$A11,DataQ!S:S) -> -1.5120001 | N11: =SUMIF(DataQ!$B:$B,'Data Q to A'!$A11,DataQ!T:T) -> -7.402609 | O11: =SUMIF(DataQ!$B:$B,'Data Q to A'!$A11,DataQ!U:U) -> -4501 | P11: =SUMIF(DataQ!$F:$F,'Data Q to A'!$A11,DataQ!V:V) -> 73402.75 | Q11: =SUMIF(DataQ!$F:$F,'Data Q to A'!$A11,DataQ!W:W) -> 1525.937 | R11: =SUMIF(DataQ!$F:$F,'Data Q to A'!$A11,DataQ!X:X) -> 44086 | S11: =SUMIF(DataQ!$F:$F,'Data Q to A'!$A11,DataQ!Y:Y) -> 155.0151 | T11: =SUMIF(DataQ!$F:$F,'Data Q to A'!$A11,DataQ!Z:Z) -> 77.04875 | U11: =SUMIF(DataQ!$F:$F,'Data Q to A'!$A11,DataQ!AA:AA) -> 76.946 | V11: =SUMIF(DataQ!$F:$F,'Data Q to A'!$A11,DataQ!AB:AB) -> 91437 | W11: =SUMIF(DataQ!$F:$F,'Data Q to A'!$A11,DataQ!AC:AC) -> 53375.52 | X11: =SUMIF(DataQ!$F:$F,'Data Q to A'!$A11,DataQ!AD:AD) -> 1175.914 | Y11: =SUMIF(DataQ!$F:$F,'Data Q to A'!$A11,DataQ!AE:AE) -> -2982.051 | Z11: =SUMIF(DataQ!$F:$F,'Data Q to A'!$A11,DataQ!AF:AF) -> 4.283612 | AA11: =SUMIF(DataQ!$F:$F,'Data Q to A'!$A11,DataQ!AG:AG) -> -1.256 | AB11: =SUMIF(DataQ!$F:$F,'Data Q to A'!$A11,DataQ!AH:AH) -> 50.719 | AC11: =SUMIF(DataQ!$F:$F,'Data Q to A'!$A11,DataQ!AI:AI) -> 20333 | AD11: =SUMIF(DataQ!$B:$B,'Data Q to A'!$A11,DataQ!AJ:AJ) -> 136995 | AE11: =SUMIF(DataQ!$B:$B,'Data Q to A'!$A11,DataQ!AK:AK) -> 1873.425 | AF11: =SUMIF(DataQ!$B:$B,'Data Q to A'!$A11,DataQ!AL:AL) -> 171384.16 | AG11: =SUMIF(DataQ!$B:$B,'Data Q to A'!$A11,DataQ!AM:AM) -> 677.2367 | AH11: =SUMIF(DataQ!$B:$B,'Data Q to A'!$A11,DataQ!AN:AN) -> 269.714 | AI11: =SUMIF(DataQ!$B:$B,'Data Q to A'!$A11,DataQ!AO:AO) -> 96.562 | AJ11: =SUMIF(DataQ!$B:$B,'Data Q to A'!$A11,DataQ!AP:AP) -> 205986 | AK11: =SUMIF(DataQ!$E:$E,'Data Q to A'!$A11,DataQ!AC:AC) -> 54506.05 | AL11: =SUMIF(DataQ!$D:$D,'Data Q to A'!$A11,DataQ!AJ:AJ) -> 148504
A12: 1977 | B12: =SUMIF(DataQ!$B:$B,'Data Q to A'!$A12,DataQ!H:H) -> 1077816 | C12: =SUMIF(DataQ!$B:$B,'Data Q to A'!$A12,DataQ!I:I) -> 6682.825 | D12: =SUMIF(DataQ!$B:$B,'Data Q to A'!$A12,DataQ!J:J) -> 244433.81 | E12: =SUMIF(DataQ!$B:$B,'Data Q to A'!$A12,DataQ!K:K) -> 1683.93 | F12: =SUMIF(DataQ!$B:$B,'Data Q to A'!$A12,DataQ!L:L) -> 1116.289 | G12: =SUMIF(DataQ!$B:$B,'Data Q to A'!$A12,DataQ!M:M) -> 1048.6038 | H12: =SUMIF(DataQ!$B:$B,'Data Q to A'!$A12,DataQ!N:N) -> 813696.4 | I12: =SUMIF(DataQ!$B:$B,'Data Q to A'!$A12,DataQ!O:O) -> -5836 | J12: =SUMIF(DataQ!$B:$B,'Data Q to A'!$A12,DataQ!P:P) -> -88.151 | K12: =SUMIF(DataQ!$B:$B,'Data Q to A'!$A12,DataQ!Q:Q) -> -10191.75 | L12: =SUMIF(DataQ!$B:$B,'Data Q to A'!$A12,DataQ!R:R) -> -44.70044 | M12: =SUMIF(DataQ!$B:$B,'Data Q to A'!$A12,DataQ!S:S) -> -1.9469999 | N12: =SUMIF(DataQ!$B:$B,'Data Q to A'!$A12,DataQ!T:T) -> -7.911603 | O12: =SUMIF(DataQ!$B:$B,'Data Q to A'!$A12,DataQ!U:U) -> -7329 | P12: =SUMIF(DataQ!$F:$F,'Data Q to A'!$A12,DataQ!V:V) -> 83765.5 | Q12: =SUMIF(DataQ!$F:$F,'Data Q to A'!$A12,DataQ!W:W) -> 1653.022 | R12: =SUMIF(DataQ!$F:$F,'Data Q to A'!$A12,DataQ!X:X) -> 58926 | S12: =SUMIF(DataQ!$F:$F,'Data Q to A'!$A12,DataQ!Y:Y) -> 172.103 | T12: =SUMIF(DataQ!$F:$F,'Data Q to A'!$A12,DataQ!Z:Z) -> 85.55736 | U12: =SUMIF(DataQ!$F:$F,'Data Q to A'!$A12,DataQ!AA:AA) -> 97.55 | V12: =SUMIF(DataQ!$F:$F,'Data Q to A'!$A12,DataQ!AB:AB) -> 104504 | W12: =SUMIF(DataQ!$F:$F,'Data Q to A'!$A12,DataQ!AC:AC) -> 58825.45 | X12: =SUMIF(DataQ!$F:$F,'Data Q to A'!$A12,DataQ!AD:AD) -> 1243.483 | Y12: =SUMIF(DataQ!$F:$F,'Data Q to A'!$A12,DataQ!AE:AE) -> 3307.912 | Z12: =SUMIF(DataQ!$F:$F,'Data Q to A'!$A12,DataQ!AF:AF) -> 9.602367 | AA12: =SUMIF(DataQ!$F:$F,'Data Q to A'!$A12,DataQ!AG:AG) -> -2.931 | AB12: =SUMIF(DataQ!$F:$F,'Data Q to A'!$A12,DataQ!AH:AH) -> 62.422 | AC12: =SUMIF(DataQ!$F:$F,'Data Q to A'!$A12,DataQ!AI:AI) -> 24434 | AD12: =SUMIF(DataQ!$B:$B,'Data Q to A'!$A12,DataQ!AJ:AJ) -> 159775 | AE12: =SUMIF(DataQ!$B:$B,'Data Q to A'!$A12,DataQ!AK:AK) -> 2081.825 | AF12: =SUMIF(DataQ!$B:$B,'Data Q to A'!$A12,DataQ!AL:AL) -> 191055.77 | AG12: =SUMIF(DataQ!$B:$B,'Data Q to A'!$A12,DataQ!AM:AM) -> 722.7076 | AH12: =SUMIF(DataQ!$B:$B,'Data Q to A'!$A12,DataQ!AN:AN) -> 303.907 | AI12: =SUMIF(DataQ!$B:$B,'Data Q to A'!$A12,DataQ!AO:AO) -> 117.316 | AJ12: =SUMIF(DataQ!$B:$B,'Data Q to A'!$A12,DataQ!AP:AP) -> 227601 | AK12: =SUMIF(DataQ!$E:$E,'Data Q to A'!$A12,DataQ!AC:AC) -> 60407.98 | AL12: =SUMIF(DataQ!$D:$D,'Data Q to A'!$A12,DataQ!AJ:AJ) -> 172535
A13: 1978 | B13: =SUMIF(DataQ!$B:$B,'Data Q to A'!$A13,DataQ!H:H) -> 1122953 | C13: =SUMIF(DataQ!$B:$B,'Data Q to A'!$A13,DataQ!I:I) -> 7052.725 | D13: =SUMIF(DataQ!$B:$B,'Data Q to A'!$A13,DataQ!J:J) -> 257478.99 | E13: =SUMIF(DataQ!$B:$B,'Data Q to A'!$A13,DataQ!K:K) -> 1736.22 | F13: =SUMIF(DataQ!$B:$B,'Data Q to A'!$A13,DataQ!L:L) -> 1160.514 | G13: =SUMIF(DataQ!$B:$B,'Data Q to A'!$A13,DataQ!M:M) -> 1086.8867 | H13: =SUMIF(DataQ!$B:$B,'Data Q to A'!$A13,DataQ!N:N) -> 844095.8 | I13: =SUMIF(DataQ!$B:$B,'Data Q to A'!$A13,DataQ!O:O) -> -8334 | J13: =SUMIF(DataQ!$B:$B,'Data Q to A'!$A13,DataQ!P:P) -> -81.16925 | K13: =SUMIF(DataQ!$B:$B,'Data Q to A'!$A13,DataQ!Q:Q) -> -13458 | L13: =SUMIF(DataQ!$B:$B,'Data Q to A'!$A13,DataQ!R:R) -> -52.05288 | M13: =SUMIF(DataQ!$B:$B,'Data Q to A'!$A13,DataQ!S:S) -> -6.702 | N13: =SUMIF(DataQ!$B:$B,'Data Q to A'!$A13,DataQ!T:T) -> -11.376781 | O13: =SUMIF(DataQ!$B:$B,'Data Q to A'!$A13,DataQ!U:U) -> -10455 | P13: =SUMIF(DataQ!$F:$F,'Data Q to A'!$A13,DataQ!V:V) -> 94137.5 | Q13: =SUMIF(DataQ!$F:$F,'Data Q to A'!$A13,DataQ!W:W) -> 1802.734 | R13: =SUMIF(DataQ!$F:$F,'Data Q to A'!$A13,DataQ!X:X) -> 82162 | S13: =SUMIF(DataQ!$F:$F,'Data Q to A'!$A13,DataQ!Y:Y) -> 193.9361 | T13: =SUMIF(DataQ!$F:$F,'Data Q to A'!$A13,DataQ!Z:Z) -> 100.8063 | U13: =SUMIF(DataQ!$F:$F,'Data Q to A'!$A13,DataQ!AA:AA) -> 121.674 | V13: =SUMIF(DataQ!$F:$F,'Data Q to A'!$A13,DataQ!AB:AB) -> 123288 | W13: =SUMIF(DataQ!$F:$F,'Data Q to A'!$A13,DataQ!AC:AC) -> 64877.93 | X13: =SUMIF(DataQ!$F:$F,'Data Q to A'!$A13,DataQ!AD:AD) -> 1294.937 | Y13: =SUMIF(DataQ!$F:$F,'Data Q to A'!$A13,DataQ!AE:AE) -> 15538.89 | Z13: =SUMIF(DataQ!$F:$F,'Data Q to A'!$A13,DataQ!AF:AF) -> 15.45187 | AA13: =SUMIF(DataQ!$F:$F,'Data Q to A'!$A13,DataQ!AG:AG) -> -0.039 | AB13: =SUMIF(DataQ!$F:$F,'Data Q to A'!$A13,DataQ!AH:AH) -> 77.149 | AC13: =SUMIF(DataQ!$F:$F,'Data Q to A'!$A13,DataQ!AI:AI) -> 31882 | AD13: =SUMIF(DataQ!$B:$B,'Data Q to A'!$A13,DataQ!AJ:AJ) -> 186141 | AE13: =SUMIF(DataQ!$B:$B,'Data Q to A'!$A13,DataQ!AK:AK) -> 2351.6 | AF13: =SUMIF(DataQ!$B:$B,'Data Q to A'!$A13,DataQ!AL:AL) -> 210468.72 | AG13: =SUMIF(DataQ!$B:$B,'Data Q to A'!$A13,DataQ!AM:AM) -> 771.5664 | AH13: =SUMIF(DataQ!$B:$B,'Data Q to A'!$A13,DataQ!AN:AN) -> 345.187 | AI13: =SUMIF(DataQ!$B:$B,'Data Q to A'!$A13,DataQ!AO:AO) -> 138.022 | AJ13: =SUMIF(DataQ!$B:$B,'Data Q to A'!$A13,DataQ!AP:AP) -> 252075 | AK13: =SUMIF(DataQ!$E:$E,'Data Q to A'!$A13,DataQ!AC:AC) -> 65815.09 | AL13: =SUMIF(DataQ!$D:$D,'Data Q to A'!$A13,DataQ!AJ:AJ) -> 200521
A14: 1979 | B14: =SUMIF(DataQ!$B:$B,'Data Q to A'!$A14,DataQ!H:H) -> 1164860 | C14: =SUMIF(DataQ!$B:$B,'Data Q to A'!$A14,DataQ!I:I) -> 7276 | D14: =SUMIF(DataQ!$B:$B,'Data Q to A'!$A14,DataQ!J:J) -> 272634.53 | E14: =SUMIF(DataQ!$B:$B,'Data Q to A'!$A14,DataQ!K:K) -> 1810.62 | F14: =SUMIF(DataQ!$B:$B,'Data Q to A'!$A14,DataQ!L:L) -> 1203.514 | G14: =SUMIF(DataQ!$B:$B,'Data Q to A'!$A14,DataQ!M:M) -> 1147.0066 | H14: =SUMIF(DataQ!$B:$B,'Data Q to A'!$A14,DataQ!N:N) -> 875540.1 | I14: =SUMIF(DataQ!$B:$B,'Data Q to A'!$A14,DataQ!O:O) -> -9364 | J14: =SUMIF(DataQ!$B:$B,'Data Q to A'!$A14,DataQ!P:P) -> -78.56225 | K14: =SUMIF(DataQ!$B:$B,'Data Q to A'!$A14,DataQ!Q:Q) -> -12426.5 | L14: =SUMIF(DataQ!$B:$B,'Data Q to A'!$A14,DataQ!R:R) -> -58.44036 | M14: =SUMIF(DataQ!$B:$B,'Data Q to A'!$A14,DataQ!S:S) -> -1.934 | N14: =SUMIF(DataQ!$B:$B,'Data Q to A'!$A14,DataQ!T:T) -> -13.51795 | O14: =SUMIF(DataQ!$B:$B,'Data Q to A'!$A14,DataQ!U:U) -> -8532 | P14: =SUMIF(DataQ!$F:$F,'Data Q to A'!$A14,DataQ!V:V) -> 104807 | Q14: =SUMIF(DataQ!$F:$F,'Data Q to A'!$A14,DataQ!W:W) -> 1947.03 | R14: =SUMIF(DataQ!$F:$F,'Data Q to A'!$A14,DataQ!X:X) -> 98956 | S14: =SUMIF(DataQ!$F:$F,'Data Q to A'!$A14,DataQ!Y:Y) -> 217.6445 | T14: =SUMIF(DataQ!$F:$F,'Data Q to A'!$A14,DataQ!Z:Z) -> 115.7283 | U14: =SUMIF(DataQ!$F:$F,'Data Q to A'!$A14,DataQ!AA:AA) -> 146.611 | V14: =SUMIF(DataQ!$F:$F,'Data Q to A'!$A14,DataQ!AB:AB) -> 132680 | W14: =SUMIF(DataQ!$F:$F,'Data Q to A'!$A14,DataQ!AC:AC) -> 72490.47 | X14: =SUMIF(DataQ!$F:$F,'Data Q to A'!$A14,DataQ!AD:AD) -> 1298.247 | Y14: =SUMIF(DataQ!$F:$F,'Data Q to A'!$A14,DataQ!AE:AE) -> 24974.84 | Z14: =SUMIF(DataQ!$F:$F,'Data Q to A'!$A14,DataQ!AF:AF) -> 22.56989 | AA14: =SUMIF(DataQ!$F:$F,'Data Q to A'!$A14,DataQ!AG:AG) -> -5.611 | AB14: =SUMIF(DataQ!$F:$F,'Data Q to A'!$A14,DataQ!AH:AH) -> 92.639 | AC14: =SUMIF(DataQ!$F:$F,'Data Q to A'!$A14,DataQ!AI:AI) -> 40451 | AD14: =SUMIF(DataQ!$B:$B,'Data Q to A'!$A14,DataQ!AJ:AJ) -> 220966 | AE14: =SUMIF(DataQ!$B:$B,'Data Q to A'!$A14,DataQ!AK:AK) -> 2627.325 | AF14: =SUMIF(DataQ!$B:$B,'Data Q to A'!$A14,DataQ!AL:AL) -> 227860.58 | AG14: =SUMIF(DataQ!$B:$B,'Data Q to A'!$A14,DataQ!AM:AM) -> 839.0251 | AH14: =SUMIF(DataQ!$B:$B,'Data Q to A'!$A14,DataQ!AN:AN) -> 394.491 | AI14: =SUMIF(DataQ!$B:$B,'Data Q to A'!$A14,DataQ!AO:AO) -> 168.884 | AJ14: =SUMIF(DataQ!$B:$B,'Data Q to A'!$A14,DataQ!AP:AP) -> 287608 | AK14: =SUMIF(DataQ!$E:$E,'Data Q to A'!$A14,DataQ!AC:AC) -> 75983.41 | AL14: =SUMIF(DataQ!$D:$D,'Data Q to A'!$A14,DataQ!AJ:AJ) -> 242323
A15: 1980 | B15: =SUMIF(DataQ!$B:$B,'Data Q to A'!$A15,DataQ!H:H) -> 1140989 | C15: =SUMIF(DataQ!$B:$B,'Data Q to A'!$A15,DataQ!I:I) -> 7257.325 | D15: =SUMIF(DataQ!$B:$B,'Data Q to A'!$A15,DataQ!J:J) -> 284531.66 | E15: =SUMIF(DataQ!$B:$B,'Data Q to A'!$A15,DataQ!K:K) -> 1833.95 | F15: =SUMIF(DataQ!$B:$B,'Data Q to A'!$A15,DataQ!L:L) -> 1223.307 | G15: =SUMIF(DataQ!$B:$B,'Data Q to A'!$A15,DataQ!M:M) -> 1186.9547 | H15: =SUMIF(DataQ!$B:$B,'Data Q to A'!$A15,DataQ!N:N) -> 894602.4 | I15: =SUMIF(DataQ!$B:$B,'Data Q to A'!$A15,DataQ!O:O) -> -10041 | J15: =SUMIF(DataQ!$B:$B,'Data Q to A'!$A15,DataQ!P:P) -> -128.273 | K15: =SUMIF(DataQ!$B:$B,'Data Q to A'!$A15,DataQ!Q:Q) -> -11822.5 | L15: =SUMIF(DataQ!$B:$B,'Data Q to A'!$A15,DataQ!R:R) -> -62.0868 | M15: =SUMIF(DataQ!$B:$B,'Data Q to A'!$A15,DataQ!S:S) -> -1.928 | N15: =SUMIF(DataQ!$B:$B,'Data Q to A'!$A15,DataQ!T:T) -> -14.305154 | O15: =SUMIF(DataQ!$B:$B,'Data Q to A'!$A15,DataQ!U:U) -> -11149 | P15: =SUMIF(DataQ!$F:$F,'Data Q to A'!$A15,DataQ!V:V) -> 121541.3 | Q15: =SUMIF(DataQ!$F:$F,'Data Q to A'!$A15,DataQ!W:W) -> 2086.701 | R15: =SUMIF(DataQ!$F:$F,'Data Q to A'!$A15,DataQ!X:X) -> 117360 | S15: =SUMIF(DataQ!$F:$F,'Data Q to A'!$A15,DataQ!Y:Y) -> 248.8942 | T15: =SUMIF(DataQ!$F:$F,'Data Q to A'!$A15,DataQ!Z:Z) -> 129.1328 | U15: =SUMIF(DataQ!$F:$F,'Data Q to A'!$A15,DataQ!AA:AA) -> 178.644 | V15: =SUMIF(DataQ!$F:$F,'Data Q to A'!$A15,DataQ!AB:AB) -> 150393 | W15: =SUMIF(DataQ!$F:$F,'Data Q to A'!$A15,DataQ!AC:AC) -> 84954.26 | X15: =SUMIF(DataQ!$F:$F,'Data Q to A'!$A15,DataQ!AD:AD) -> 1360.465 | Y15: =SUMIF(DataQ!$F:$F,'Data Q to A'!$A15,DataQ!AE:AE) -> 32330.46 | Z15: =SUMIF(DataQ!$F:$F,'Data Q to A'!$A15,DataQ!AF:AF) -> 30.58755 | AA15: =SUMIF(DataQ!$F:$F,'Data Q to A'!$A15,DataQ!AG:AG) -> -15.68 | AB15: =SUMIF(DataQ!$F:$F,'Data Q to A'!$A15,DataQ!AH:AH) -> 110.03 | AC15: =SUMIF(DataQ!$F:$F,'Data Q to A'!$A15,DataQ!AI:AI) -> 48078 | AD15: =SUMIF(DataQ!$B:$B,'Data Q to A'!$A15,DataQ!AJ:AJ) -> 259956 | AE15: =SUMIF(DataQ!$B:$B,'Data Q to A'!$A15,DataQ!AK:AK) -> 2857.325 | AF15: =SUMIF(DataQ!$B:$B,'Data Q to A'!$A15,DataQ!AL:AL) -> 261521.75 | AG15: =SUMIF(DataQ!$B:$B,'Data Q to A'!$A15,DataQ!AM:AM) -> 896.4522 | AH15: =SUMIF(DataQ!$B:$B,'Data Q to A'!$A15,DataQ!AN:AN) -> 447.345 | AI15: =SUMIF(DataQ!$B:$B,'Data Q to A'!$A15,DataQ!AO:AO) -> 217.501 | AJ15: =SUMIF(DataQ!$B:$B,'Data Q to A'!$A15,DataQ!AP:AP) -> 322782 | AK15: =SUMIF(DataQ!$E:$E,'Data Q to A'!$A15,DataQ!AC:AC) -> 88342.79 | AL15: =SUMIF(DataQ!$D:$D,'Data Q to A'!$A15,DataQ!AJ:AJ) -> 275547
A16: 1981 | B16: =SUMIF(DataQ!$B:$B,'Data Q to A'!$A16,DataQ!H:H) -> 1134663 | C16: =SUMIF(DataQ!$B:$B,'Data Q to A'!$A16,DataQ!I:I) -> 7441.475 | D16: =SUMIF(DataQ!$B:$B,'Data Q to A'!$A16,DataQ!J:J) -> 296992.41 | E16: =SUMIF(DataQ!$B:$B,'Data Q to A'!$A16,DataQ!K:K) -> 1845.86 | F16: =SUMIF(DataQ!$B:$B,'Data Q to A'!$A16,DataQ!L:L) -> 1237.82 | G16: =SUMIF(DataQ!$B:$B,'Data Q to A'!$A16,DataQ!M:M) -> 1197.887 | H16: =SUMIF(DataQ!$B:$B,'Data Q to A'!$A16,DataQ!N:N) -> 925153.7 | I16: =SUMIF(DataQ!$B:$B,'Data Q to A'!$A16,DataQ!O:O) -> -8825 | J16: =SUMIF(DataQ!$B:$B,'Data Q to A'!$A16,DataQ!P:P) -> -130.469 | K16: =SUMIF(DataQ!$B:$B,'Data Q to A'!$A16,DataQ!Q:Q) -> -10937.75 | L16: =SUMIF(DataQ!$B:$B,'Data Q to A'!$A16,DataQ!R:R) -> -75.16716 | M16: =SUMIF(DataQ!$B:$B,'Data Q to A'!$A16,DataQ!S:S) -> -12.242 | N16: =SUMIF(DataQ!$B:$B,'Data Q to A'!$A16,DataQ!T:T) -> -27.037463 | O16: =SUMIF(DataQ!$B:$B,'Data Q to A'!$A16,DataQ!U:U) -> -7830 | P16: =SUMIF(DataQ!$F:$F,'Data Q to A'!$A16,DataQ!V:V) -> 131791.5 | Q16: =SUMIF(DataQ!$F:$F,'Data Q to A'!$A16,DataQ!W:W) -> 2279.713 | R16: =SUMIF(DataQ!$F:$F,'Data Q to A'!$A16,DataQ!X:X) -> 141470 | S16: =SUMIF(DataQ!$F:$F,'Data Q to A'!$A16,DataQ!Y:Y) -> 287.4771 | T16: =SUMIF(DataQ!$F:$F,'Data Q to A'!$A16,DataQ!Z:Z) -> 141.5108 | U16: =SUMIF(DataQ!$F:$F,'Data Q to A'!$A16,DataQ!AA:AA) -> 224.365 | V16: =SUMIF(DataQ!$F:$F,'Data Q to A'!$A16,DataQ!AB:AB) -> 177353 | W16: =SUMIF(DataQ!$F:$F,'Data Q to A'!$A16,DataQ!AC:AC) -> 95587.21 | X16: =SUMIF(DataQ!$F:$F,'Data Q to A'!$A16,DataQ!AD:AD) -> 1557.032 | Y16: =SUMIF(DataQ!$F:$F,'Data Q to A'!$A16,DataQ!AE:AE) -> 44668.72 | Z16: =SUMIF(DataQ!$F:$F,'Data Q to A'!$A16,DataQ!AF:AF) -> 41.89132 | AA16: =SUMIF(DataQ!$F:$F,'Data Q to A'!$A16,DataQ!AG:AG) -> -0.947 | AB16: =SUMIF(DataQ!$F:$F,'Data Q to A'!$A16,DataQ!AH:AH) -> 140.807 | AC16: =SUMIF(DataQ!$F:$F,'Data Q to A'!$A16,DataQ!AI:AI) -> 51408 | AD16: =SUMIF(DataQ!$B:$B,'Data Q to A'!$A16,DataQ!AJ:AJ) -> 290550 | AE16: =SUMIF(DataQ!$B:$B,'Data Q to A'!$A16,DataQ!AK:AK) -> 3207.025 | AF16: =SUMIF(DataQ!$B:$B,'Data Q to A'!$A16,DataQ!AL:AL) -> 280722.94 | AG16: =SUMIF(DataQ!$B:$B,'Data Q to A'!$A16,DataQ!AM:AM) -> 939.7564 | AH16: =SUMIF(DataQ!$B:$B,'Data Q to A'!$A16,DataQ!AN:AN) -> 504.566 | AI16: =SUMIF(DataQ!$B:$B,'Data Q to A'!$A16,DataQ!AO:AO) -> 260.06 | AJ16: =SUMIF(DataQ!$B:$B,'Data Q to A'!$A16,DataQ!AP:AP) -> 368358 | AK16: =SUMIF(DataQ!$E:$E,'Data Q to A'!$A16,DataQ!AC:AC) -> 96841.12 | AL16: =SUMIF(DataQ!$D:$D,'Data Q to A'!$A16,DataQ!AJ:AJ) -> 305884
A17: 1982 | B17: =SUMIF(DataQ!$B:$B,'Data Q to A'!$A17,DataQ!H:H) -> 1157191 | C17: =SUMIF(DataQ!$B:$B,'Data Q to A'!$A17,DataQ!I:I) -> 7307.3 | D17: =SUMIF(DataQ!$B:$B,'Data Q to A'!$A17,DataQ!J:J) -> 306793.03 | E17: =SUMIF(DataQ!$B:$B,'Data Q to A'!$A17,DataQ!K:K) -> 1836.61 | F17: =SUMIF(DataQ!$B:$B,'Data Q to A'!$A17,DataQ!L:L) -> 1267.574 | G17: =SUMIF(DataQ!$B:$B,'Data Q to A'!$A17,DataQ!M:M) -> 1201.783 | H17: =SUMIF(DataQ!$B:$B,'Data Q to A'!$A17,DataQ!N:N) -> 895861.9 | I17: =SUMIF(DataQ!$B:$B,'Data Q to A'!$A17,DataQ!O:O) -> -7359 | J17: =SUMIF(DataQ!$B:$B,'Data Q to A'!$A17,DataQ!P:P) -> -220.126 | K17: =SUMIF(DataQ!$B:$B,'Data Q to A'!$A17,DataQ!Q:Q) -> -11134.25 | L17: =SUMIF(DataQ!$B:$B,'Data Q to A'!$A17,DataQ!R:R) -> -74.95508 | M17: =SUMIF(DataQ!$B:$B,'Data Q to A'!$A17,DataQ!S:S) -> -16.498 | N17: =SUMIF(DataQ!$B:$B,'Data Q to A'!$A17,DataQ!T:T) -> -29.281416 | O17: =SUMIF(DataQ!$B:$B,'Data Q to A'!$A17,DataQ!U:U) -> -23407 | P17: =SUMIF(DataQ!$F:$F,'Data Q to A'!$A17,DataQ!V:V) -> 140578.8 | Q17: =SUMIF(DataQ!$F:$F,'Data Q to A'!$A17,DataQ!W:W) -> 2557.978 | R17: =SUMIF(DataQ!$F:$F,'Data Q to A'!$A17,DataQ!X:X) -> 165196 | S17: =SUMIF(DataQ!$F:$F,'Data Q to A'!$A17,DataQ!Y:Y) -> 320.4308 | T17: =SUMIF(DataQ!$F:$F,'Data Q to A'!$A17,DataQ!Z:Z) -> 184.3563 | U17: =SUMIF(DataQ!$F:$F,'Data Q to A'!$A17,DataQ!AA:AA) -> 275.674 | V17: =SUMIF(DataQ!$F:$F,'Data Q to A'!$A17,DataQ!AB:AB) -> 209732 | W17: =SUMIF(DataQ!$F:$F,'Data Q to A'!$A17,DataQ!AC:AC) -> 103194.7 | X17: =SUMIF(DataQ!$F:$F,'Data Q to A'!$A17,DataQ!AD:AD) -> 1752.067 | Y17: =SUMIF(DataQ!$F:$F,'Data Q to A'!$A17,DataQ!AE:AE) -> 59344.71 | Z17: =SUMIF(DataQ!$F:$F,'Data Q to A'!$A17,DataQ!AF:AF) -> 51.99055 | AA17: =SUMIF(DataQ!$F:$F,'Data Q to A'!$A17,DataQ!AG:AG) -> 7.672 | AB17: =SUMIF(DataQ!$F:$F,'Data Q to A'!$A17,DataQ!AH:AH) -> 176.365 | AC17: =SUMIF(DataQ!$F:$F,'Data Q to A'!$A17,DataQ!AI:AI) -> 76833 | AD17: =SUMIF(DataQ!$B:$B,'Data Q to A'!$A17,DataQ!AJ:AJ) -> 320013 | AE17: =SUMIF(DataQ!$B:$B,'Data Q to A'!$A17,DataQ!AK:AK) -> 3343.8 | AF17: =SUMIF(DataQ!$B:$B,'Data Q to A'!$A17,DataQ!AL:AL) -> 295229.15 | AG17: =SUMIF(DataQ!$B:$B,'Data Q to A'!$A17,DataQ!AM:AM) -> 977.803 | AH17: =SUMIF(DataQ!$B:$B,'Data Q to A'!$A17,DataQ!AN:AN) -> 578.925 | AI17: =SUMIF(DataQ!$B:$B,'Data Q to A'!$A17,DataQ!AO:AO) -> 306.689 | AJ17: =SUMIF(DataQ!$B:$B,'Data Q to A'!$A17,DataQ!AP:AP) -> 388181 | AK17: =SUMIF(DataQ!$E:$E,'Data Q to A'!$A17,DataQ!AC:AC) -> 107892.9 | AL17: =SUMIF(DataQ!$D:$D,'Data Q to A'!$A17,DataQ!AJ:AJ) -> 335593
