Workbook
Name _DLX1.INC: HAVERA!$A$1:$D$4
Name Data: [1]sheet0!$C$2

Sheet Charts >>

Sheet Data >>

Sheet Chart data
A1: Share of household spending by income | M1: Actions taken by households | S1: Household deposits | X1: Distributional inflation
Y2: 0-10 | Z2: 11-20 | AA2: 21-30 | AB2: 31-40 | AC2: 41-50 | AD2: 51-60 | AE2: 61-70 | AF2: 71-80 | AG2: 81-90 | AH2: 91-100 | AI2: CPI
X3: 2010 | Y3: ='CPI by declile'!Q113 -> 2.9813552 | Z3: ='CPI by declile'!R113 -> 3.0382523 | AA3: ='CPI by declile'!S113 -> 3.0878782 | AB3: ='CPI by declile'!T113 -> 3.2147626 | AC3: ='CPI by declile'!U113 -> 3.3017874 | AD3: ='CPI by declile'!V113 -> 3.3501306 | AE3: ='CPI by declile'!W113 -> 3.3844234 | AF3: ='CPI by declile'!X113 -> 3.4118183 | ... AI3: ='CPI by declile'!AA113 -> 3.3015651
A4: Income deciles | B4: Food and non-alcoholic beverages | C4: Energy | D4: Motor fuel | H4: Food and non-alcoholic beverages | I4: Energy | J4: Motor fuel | N4: Buying the same or more | O4: Cutting back on some things | P4: Cutting back completely | T4: March 2022 survey | U4: March 2026 survey | X4: 2011 | Y4: ='CPI by declile'!Q114 -> 4.5767999 | Z4: ='CPI by declile'!R114 -> 4.6167534 | AA4: ='CPI by declile'!S114 -> 4.526999 | AB4: ='CPI by declile'!T114 -> 4.5833306 | AC4: ='CPI by declile'!U114 -> 4.5721223 | AD4: ='CPI by declile'!V114 -> 4.5216134 | AE4: ='CPI by declile'!W114 -> 4.5188635 | AF4: ='CPI by declile'!X114 -> 4.4954366 | ... AI4: ='CPI by declile'!AA114 -> 4.4632913
A5: 1 | B5: ='Apr26 MPR A.1'!B6 -> 14.6 | G5: 1 | H5: ='Apr26 MPR A.1'!B6 -> 14.6 | I5: ='Apr26 MPR A.1'!C6 -> 7.1 | J5: ='Apr26 MPR A.1'!D6 -> 2.4 | M5: 1 | N5: ='Apr26 MPR E.1'!B7 -> 26.99 | O5: ='Apr26 MPR E.1'!C7 -> 26.28 | P5: ='Apr26 MPR E.1'!D7 -> 46.73 | S5: Lowest quintile | T5: ='Apr26 MPR E.1'!G7 -> 43.548 | U5: ='Apr26 MPR E.1'!H7 -> 25.191 | X5: 2012 | Y5: ='CPI by declile'!Q115 -> 3.038899 | Z5: ='CPI by declile'!R115 -> 3.0740112 | AA5: ='CPI by declile'!S115 -> 2.9550293 | AB5: ='CPI by declile'!T115 -> 2.8965588 | AC5: ='CPI by declile'!U115 -> 2.8655041 | AD5: ='CPI by declile'!V115 -> 2.816043 | AE5: ='CPI by declile'!W115 -> 2.7913757 | AF5: ='CPI by declile'!X115 -> 2.7676168 | ... AI5: ='CPI by declile'!AA115 -> 2.8008242
B6: ='Apr26 MPR A.1'!B7 -> 15.4 | G6: 2 | H6: ='Apr26 MPR A.1'!B7 -> 15.4 | I6: ='Apr26 MPR A.1'!C7 -> 7.1 | J6: ='Apr26 MPR A.1'!D7 -> 2.7 | M6: 2 | N6: ='Apr26 MPR E.1'!B8 -> 36.19 | O6: ='Apr26 MPR E.1'!C8 -> 27.53 | P6: ='Apr26 MPR E.1'!D8 -> 36.29 | S6: Highest quintile | T6: ='Apr26 MPR E.1'!G8 -> 54.042 | U6: ='Apr26 MPR E.1'!H8 -> 17.142 | X6: 2013 | Y6: ='CPI by declile'!Q116 -> 2.9739702 | Z6: ='CPI by declile'!R116 -> 2.9389112 | AA6: ='CPI by declile'!S116 -> 2.7226476 | AB6: ='CPI by declile'!T116 -> 2.6749426 | AC6: ='CPI by declile'!U116 -> 2.619984 | AD6: ='CPI by declile'!V116 -> 2.5658926 | AE6: ='CPI by declile'!W116 -> 2.5404892 | AF6: ='CPI by declile'!X116 -> 2.5016419 | ... AI6: ='CPI by declile'!AA116 -> 2.5683227
B7: ='Apr26 MPR A.1'!B8 -> 15.2 | G7: 3 | H7: ='Apr26 MPR A.1'!B8 -> 15.2 | I7: ='Apr26 MPR A.1'!C8 -> 6.2 | J7: ='Apr26 MPR A.1'!D8 -> 2.8 | M7: 3 | N7: ='Apr26 MPR E.1'!B9 -> 38.8 | O7: ='Apr26 MPR E.1'!C9 -> 30.61 | P7: ='Apr26 MPR E.1'!D9 -> 30.59 | X7: 2014 | Y7: ='CPI by declile'!Q117 -> 1.6526726 | Z7: ='CPI by declile'!R117 -> 1.6443428 | AA7: ='CPI by declile'!S117 -> 1.5139332 | AB7: ='CPI by declile'!T117 -> 1.4743028 | AC7: ='CPI by declile'!U117 -> 1.4229924 | AD7: ='CPI by declile'!V117 -> 1.4377905 | AE7: ='CPI by declile'!W117 -> 1.425967 | AF7: ='CPI by declile'!X117 -> 1.4250676 | ... AI7: ='CPI by declile'!AA117 -> 1.4719567
B8: ='Apr26 MPR A.1'!B9 -> 13.8 | G8: 4 | H8: ='Apr26 MPR A.1'!B9 -> 13.8 | I8: ='Apr26 MPR A.1'!C9 -> 5.8 | J8: ='Apr26 MPR A.1'!D9 -> 2.9 | M8: 4 | N8: ='Apr26 MPR E.1'!B10 -> 43.78 | O8: ='Apr26 MPR E.1'!C10 -> 26.41 | P8: ='Apr26 MPR E.1'!D10 -> 29.8 | X8: 2015 | Y8: ='CPI by declile'!Q118 -> -0.11647601 | Z8: ='CPI by declile'!R118 -> -0.056553227 | AA8: ='CPI by declile'!S118 -> -0.11385871 | AB8: ='CPI by declile'!T118 -> -0.046916613 | AC8: ='CPI by declile'!U118 -> -0.027784789 | AD8: ='CPI by declile'!V118 -> 0.046917797 | AE8: ='CPI by declile'!W118 -> 0.015410863 | AF8: ='CPI by declile'!X118 -> -0.013084909 | ... AI8: ='CPI by declile'!AA118 -> 0.049990831
B9: ='Apr26 MPR A.1'!B10 -> 13.2 | G9: 5 | H9: ='Apr26 MPR A.1'!B10 -> 13.2 | I9: ='Apr26 MPR A.1'!C10 -> 5.2 | J9: ='Apr26 MPR A.1'!D10 -> 3.4 | M9: 5 | N9: ='Apr26 MPR E.1'!B11 -> 55.06 | O9: ='Apr26 MPR E.1'!C11 -> 24.83 | P9: ='Apr26 MPR E.1'!D11 -> 20.11 | X9: 2016 | Y9: ='CPI by declile'!Q119 -> 0.41385279 | Z9: ='CPI by declile'!R119 -> 0.43541139 | AA9: ='CPI by declile'!S119 -> 0.50533475 | AB9: ='CPI by declile'!T119 -> 0.56193473 | AC9: ='CPI by declile'!U119 -> 0.59785596 | AD9: ='CPI by declile'!V119 -> 0.6133612 | AE9: ='CPI by declile'!W119 -> 0.64888621 | AF9: ='CPI by declile'!X119 -> 0.65421761 | ... AI9: ='CPI by declile'!AA119 -> 0.64164674
B10: ='Apr26 MPR A.1'!B11 -> 12.4 | G10: 6 | H10: ='Apr26 MPR A.1'!B11 -> 12.4 | I10: ='Apr26 MPR A.1'!C11 -> 4.5 | J10: ='Apr26 MPR A.1'!D11 -> 2.9 | X10: 2017 | Y10: ='CPI by declile'!Q120 -> 2.6775345 | Z10: ='CPI by declile'!R120 -> 2.7010582 | AA10: ='CPI by declile'!S120 -> 2.7186288 | AB10: ='CPI by declile'!T120 -> 2.7228943 | AC10: ='CPI by declile'!U120 -> 2.7084349 | AD10: ='CPI by declile'!V120 -> 2.7026215 | AE10: ='CPI by declile'!W120 -> 2.706421 | AF10: ='CPI by declile'!X120 -> 2.7087024 | ... AI10: ='CPI by declile'!AA120 -> 2.6909091
B11: ='Apr26 MPR A.1'!B12 -> 11.3 | G11: 7 | H11: ='Apr26 MPR A.1'!B12 -> 11.3 | I11: ='Apr26 MPR A.1'!C12 -> 4.3 | J11: ='Apr26 MPR A.1'!D12 -> 3.3 | X11: 2018 | Y11: ='CPI by declile'!Q121 -> 2.6114711 | Z11: ='CPI by declile'!R121 -> 2.6002523 | AA11: ='CPI by declile'!S121 -> 2.568673 | AB11: ='CPI by declile'!T121 -> 2.5423537 | AC11: ='CPI by declile'!U121 -> 2.4970952 | AD11: ='CPI by declile'!V121 -> 2.5055084 | AE11: ='CPI by declile'!W121 -> 2.4830722 | AF11: ='CPI by declile'!X121 -> 2.4700969 | ... AI11: ='CPI by declile'!AA121 -> 2.4751738
B12: ='Apr26 MPR A.1'!B13 -> 10.9 | G12: 8 | H12: ='Apr26 MPR A.1'!B13 -> 10.9 | I12: ='Apr26 MPR A.1'!C13 -> 4.1 | J12: ='Apr26 MPR A.1'!D13 -> 3.1 | X12: 2019 | Y12: ='CPI by declile'!Q122 -> 1.8760809 | Z12: ='CPI by declile'!R122 -> 1.8623673 | AA12: ='CPI by declile'!S122 -> 1.8277129 | AB12: ='CPI by declile'!T122 -> 1.8067401 | AC12: ='CPI by declile'!U122 -> 1.7845732 | AD12: ='CPI by declile'!V122 -> 1.7726978 | AE12: ='CPI by declile'!W122 -> 1.7729592 | AF12: ='CPI by declile'!X122 -> 1.7491977 | ... AI12: ='CPI by declile'!AA122 -> 1.7780954
B13: ='Apr26 MPR A.1'!B14 -> 9.5 | G13: 9 | H13: ='Apr26 MPR A.1'!B14 -> 9.5 | I13: ='Apr26 MPR A.1'!C14 -> 3.4 | J13: ='Apr26 MPR A.1'!D14 -> 3.2 | X13: 2020 | Y13: ='CPI by declile'!Q123 -> 0.73536296 | Z13: ='CPI by declile'!R123 -> 0.71637156 | AA13: ='CPI by declile'!S123 -> 0.78219459 | AB13: ='CPI by declile'!T123 -> 0.76246951 | AC13: ='CPI by declile'!U123 -> 0.84178485 | AD13: ='CPI by declile'!V123 -> 0.83976225 | AE13: ='CPI by declile'!W123 -> 0.85248869 | AF13: ='CPI by declile'!X123 -> 0.91937172 | ... AI13: ='CPI by declile'!AA123 -> 0.8812616
A14: 10 | B14: ='Apr26 MPR A.1'!B15 -> 8.9 | G14: 10 | H14: ='Apr26 MPR A.1'!B15 -> 8.9 | I14: ='Apr26 MPR A.1'!C15 -> 3.3 | J14: ='Apr26 MPR A.1'!D15 -> 2.2 | X14: 2021 | Y14: ='CPI by declile'!Q124 -> 2.5349601 | Z14: ='CPI by declile'!R124 -> 2.5194748 | AA14: ='CPI by declile'!S124 -> 2.5676656 | AB14: ='CPI by declile'!T124 -> 2.5863433 | AC14: ='CPI by declile'!U124 -> 2.6125217 | AD14: ='CPI by declile'!V124 -> 2.6292926 | AE14: ='CPI by declile'!W124 -> 2.6069924 | AF14: ='CPI by declile'!X124 -> 2.6108352 | ... AI14: ='CPI by declile'!AA124 -> 2.5823448
X15: 2022 | Y15: ='CPI by declile'!Q125 -> 11.513326 | Z15: ='CPI by declile'!R125 -> 10.65336 | AA15: ='CPI by declile'!S125 -> 9.928738 | AB15: ='CPI by declile'!T125 -> 9.654986 | AC15: ='CPI by declile'!U125 -> 9.4473332 | AD15: ='CPI by declile'!V125 -> 8.9738745 | AE15: ='CPI by declile'!W125 -> 8.8500634 | AF15: ='CPI by declile'!X125 -> 8.9075284 | ... AI15: ='CPI by declile'!AA125 -> 9.0535621
A16: 1 | C16: ='Apr26 MPR A.1'!C6 -> 7.1 | X16: 2023 | Y16: ='CPI by declile'!Q126 -> 7.9134942 | Z16: ='CPI by declile'!R126 -> 7.9332343 | AA16: ='CPI by declile'!S126 -> 7.6490149 | AB16: ='CPI by declile'!T126 -> 7.4158543 | AC16: ='CPI by declile'!U126 -> 7.3449449 | AD16: ='CPI by declile'!V126 -> 7.2798219 | AE16: ='CPI by declile'!W126 -> 7.1971091 | AF16: ='CPI by declile'!X126 -> 7.1997001 | ... AI16: ='CPI by declile'!AA126 -> 7.3019268
C17: ='Apr26 MPR A.1'!C7 -> 7.1 | X17: 2024 | Y17: ='CPI by declile'!Q127 -> 1.6065477 | Z17: ='CPI by declile'!R127 -> 1.7955065 | AA17: ='CPI by declile'!S127 -> 2.1140166 | AB17: ='CPI by declile'!T127 -> 2.2416325 | AC17: ='CPI by declile'!U127 -> 2.3806101 | AD17: ='CPI by declile'!V127 -> 2.5627345 | AE17: ='CPI by declile'!W127 -> 2.6121776 | AF17: ='CPI by declile'!X127 -> 2.6984426 | ... AI17: ='CPI by declile'!AA127 -> 2.5406441
C18: ='Apr26 MPR A.1'!C8 -> 6.2 | X18: 2025 | Y18: ='CPI by declile'!Q128 -> 3.346226 | Z18: ='CPI by declile'!R128 -> 3.3729236 | AA18: ='CPI by declile'!S128 -> 3.3672608 | AB18: ='CPI by declile'!T128 -> 3.3246415 | AC18: ='CPI by declile'!U128 -> 3.340624 | AD18: ='CPI by declile'!V128 -> 3.3603711 | AE18: ='CPI by declile'!W128 -> 3.3519709 | AF18: ='CPI by declile'!X128 -> 3.3652103 | ... AI18: ='CPI by declile'!AA128 -> 3.3680392
C19: ='Apr26 MPR A.1'!C9 -> 5.8 | X19: 2026 | Y19: ='CPI by declile'!Q129 -> 3.9768501 | Z19: ='CPI by declile'!R129 -> 3.9689382 | AA19: ='CPI by declile'!S129 -> 3.9652023 | AB19: ='CPI by declile'!T129 -> 4.0031998 | AC19: ='CPI by declile'!U129 -> 3.9831629 | AD19: ='CPI by declile'!V129 -> 3.9655499 | AE19: ='CPI by declile'!W129 -> 3.9684312 | AF19: ='CPI by declile'!X129 -> 3.9615185 | ... AI19: ='CPI by declile'!AA129 -> 3.9541306
C20: ='Apr26 MPR A.1'!C10 -> 5.2
C21: ='Apr26 MPR A.1'!C11 -> 4.5
C22: ='Apr26 MPR A.1'!C12 -> 4.3
C23: ='Apr26 MPR A.1'!C13 -> 4.1
C24: ='Apr26 MPR A.1'!C14 -> 3.4
A25: 10 | C25: ='Apr26 MPR A.1'!C15 -> 3.3
A27: 1 | D27: ='Apr26 MPR A.1'!D6 -> 2.4
D28: ='Apr26 MPR A.1'!D7 -> 2.7
D29: ='Apr26 MPR A.1'!D8 -> 2.8
D30: ='Apr26 MPR A.1'!D9 -> 2.9
D31: ='Apr26 MPR A.1'!D10 -> 3.4
D32: ='Apr26 MPR A.1'!D11 -> 2.9
D33: ='Apr26 MPR A.1'!D12 -> 3.3
D34: ='Apr26 MPR A.1'!D13 -> 3.1
D35: ='Apr26 MPR A.1'!D14 -> 3.2
A36: 10 | D36: ='Apr26 MPR A.1'!D15 -> 2.2

Sheet Apr26 MPR A.1
A1: Section 2: Topical policy issues
A3: Chart A.1 - Share of household spending on categories particularly exposed to energy-driven price rises, by income decile
A5: Income decile | B5: Food and non-alcoholic beverages | C5: Electricity, gas and other fuels | D5: Motor fuels
A6: 1 (poorest) | B6: 14.6 | C6: 7.1 | D6: 2.4
A7: 2 | B7: 15.4 | C7: 7.1 | D7: 2.7
A8: 3 | B8: 15.2 | C8: 6.2 | D8: 2.8
A9: 4 | B9: 13.8 | C9: 5.8 | D9: 2.9
A10: 5 | B10: 13.2 | C10: 5.2 | D10: 3.4
A11: 6 | B11: 12.4 | C11: 4.5 | D11: 2.9
A12: 7 | B12: 11.3 | C12: 4.3 | D12: 3.3
A13: 8 | B13: 10.9 | C13: 4.1 | D13: 3.1
A14: 9 | B14: 9.5 | C14: 3.4 | D14: 3.2
A15: 10 (richest) | B15: 8.9 | C15: 3.3 | D15: 2.2

Sheet Apr26 MPR E.1
A1: Section 2: Topical policy issues
A3: Chart E.1 - Actions taken by households in response to higher costs and share of households with deposits worth less than two weeks of income
B5: Actions taken by households in response to higher costs, share of households (per cent) | G5: Share of households with deposits worth less than two weeks of income (per cent)
A6: Income quintile | B6: Buying the same or more | C6: Cutting back on some things | D6: Cutting back completely | F6: Date | G6: Low income | H6: High income
A7: 1 (lowest) | B7: 26.99 | C7: 26.28 | D7: 46.73 | F7: 2022 H1 | G7: 43.548 | H7: 25.191
A8: 2 | B8: 36.19 | C8: 27.53 | D8: 36.29 | F8: 2026 H1 | G8: 54.042 | H8: 17.142
A9: 3 | B9: 38.8 | C9: 30.61 | D9: 30.59
A10: 4 | B10: 43.78 | C10: 26.41 | D10: 29.8
A11: 5 (highest) | B11: 55.06 | C11: 24.83 | D11: 20.11

Sheet Distributional analysis >>

Sheet CPI by declile
A1: CPI data | O1: Weights - food | AC1: Weights - energy | AQ1: Weights - petrol & oil | BE1: Weights - other
B3: CPI | C3: Food | D3: Energy | E3: Petrol | F3: CPI other | G3: Check | P3: CPI food | Q3: EFS total | R3: 0-10 | S3: 11-20 | T3: 21-30 | U3: 31-40 | V3: 41-50 | W3: 51-60 | X3: 61-70 | Y3: 71-80 | Z3: 81-90 | AA3: 91-100 | AD3: CPI energy | AE3: EFS total | AF3: 0-10 | AG3: 11-20 | AH3: 21-30 | AI3: 31-40 | AJ3: 41-50 | AK3: 51-60 | AL3: 61-70 | AM3: 71-80 | AN3: 81-90 | AO3: 91-100 | AR3: CPI petrol | AS3: EFS total | AT3: 0-10 | AU3: 11-20 | AV3: 21-30 | AW3: 31-40 | AX3: 41-50 | AY3: 51-60 | AZ3: 61-70 | BA3: 71-80 | BB3: 81-90 | BC3: 91-100 | BF3: CPI oth | BG3: EFS total | BH3: 0-10 | BI3: 11-20 | BJ3: 21-30 | BK3: 31-40 | BL3: 41-50 | BM3: 51-60 | BN3: 61-70 | BO3: 71-80 | BP3: 81-90 | BQ3: 91-100
A4: 1987 | P4: =HAVERA!B5/1000 -> #N/A | Q4: =Q5 -> 0.10488419 | R4: =R5 -> 0.16946117 | S4: =S5 -> 0.16582996 | T4: =T5 -> 0.1484721 | U4: =U5 -> 0.1299966 | V4: =V5 -> 0.12155375 | W4: =W5 -> 0.10751169 | X4: =X5 -> 0.10524167 | ... AA4: =AA5 -> 0.071317947 | AD4: =HAVERA!C5/1000 -> #N/A | AE4: =AE5 -> 0.029417273 | AF4: =AF5 -> 0.059160641 | AG4: =AG5 -> 0.057823242 | AH4: =AH5 -> 0.046293902 | AI4: =AI5 -> 0.038459694 | AJ4: =AJ5 -> 0.034945783 | AK4: =AK5 -> 0.028826884 | AL4: =AL5 -> 0.027915083 | ... AO4: =AO5 -> 0.018580417 | AR4: =HAVERA!D5/1000 -> #N/A | AS4: =AS5 -> 0.037060748 | AT4: =AT5 -> 0.02434028 | AU4: =AU5 -> 0.02486177 | AV4: =AV5 -> 0.03334324 | AW4: =AW5 -> 0.038079986 | AX4: =AX5 -> 0.042426535 | AY4: =AY5 -> 0.038179695 | AZ4: =AZ5 -> 0.040970915 | ... BC4: =BC5 -> 0.03330738 | BF4: =1-P4-AD4-AR4 -> #N/A | BG4: =BG5 -> 0.82863779 | BH4: =BH5 -> 0.74703791 | BI4: =BI5 -> 0.75148502 | BJ4: =BJ5 -> 0.77189076 | BK4: =BK5 -> 0.79346372 | BL4: =BL5 -> 0.80107393 | BM4: =BM5 -> 0.82548174 | BN4: =BN5 -> 0.82587233 | ... BQ4: =BQ5 -> 0.87679426
A5: 1988 | P5: =HAVERA!B6/1000 -> 0.184 | Q5: =Q6 -> 0.10488419 | R5: =R6 -> 0.16946117 | S5: =S6 -> 0.16582996 | T5: =T6 -> 0.1484721 | U5: =U6 -> 0.1299966 | V5: =V6 -> 0.12155375 | W5: =W6 -> 0.10751169 | X5: =X6 -> 0.10524167 | ... AA5: =AA6 -> 0.071317947 | AD5: =HAVERA!C6/1000 -> 0.062 | AE5: =AE6 -> 0.029417273 | AF5: =AF6 -> 0.059160641 | AG5: =AG6 -> 0.057823242 | AH5: =AH6 -> 0.046293902 | AI5: =AI6 -> 0.038459694 | AJ5: =AJ6 -> 0.034945783 | AK5: =AK6 -> 0.028826884 | AL5: =AL6 -> 0.027915083 | ... AO5: =AO6 -> 0.018580417 | AR5: =HAVERA!D6/1000 -> 0.041 | AS5: =AS6 -> 0.037060748 | AT5: =AT6 -> 0.02434028 | AU5: =AU6 -> 0.02486177 | AV5: =AV6 -> 0.03334324 | AW5: =AW6 -> 0.038079986 | AX5: =AX6 -> 0.042426535 | AY5: =AY6 -> 0.038179695 | AZ5: =AZ6 -> 0.040970915 | ... BC5: =BC6 -> 0.03330738 | BF5: =1-P5-AD5-AR5 -> 0.713 | BG5: =BG6 -> 0.82863779 | BH5: =BH6 -> 0.74703791 | BI5: =BI6 -> 0.75148502 | BJ5: =BJ6 -> 0.77189076 | BK5: =BK6 -> 0.79346372 | BL5: =BL6 -> 0.80107393 | BM5: =BM6 -> 0.82548174 | BN5: =BN6 -> 0.82587233 | ... BQ5: =BQ6 -> 0.87679426
A6: 1989 | P6: =HAVERA!B7/1000 -> 0.177 | Q6: =Q7 -> 0.10488419 | R6: =R7 -> 0.16946117 | S6: =S7 -> 0.16582996 | T6: =T7 -> 0.1484721 | U6: =U7 -> 0.1299966 | V6: =V7 -> 0.12155375 | W6: =W7 -> 0.10751169 | X6: =X7 -> 0.10524167 | ... AA6: =AA7 -> 0.071317947 | AD6: =HAVERA!C7/1000 -> 0.062 | AE6: =AE7 -> 0.029417273 | AF6: =AF7 -> 0.059160641 | AG6: =AG7 -> 0.057823242 | AH6: =AH7 -> 0.046293902 | AI6: =AI7 -> 0.038459694 | AJ6: =AJ7 -> 0.034945783 | AK6: =AK7 -> 0.028826884 | AL6: =AL7 -> 0.027915083 | ... AO6: =AO7 -> 0.018580417 | AR6: =HAVERA!D7/1000 -> 0.039 | AS6: =AS7 -> 0.037060748 | AT6: =AT7 -> 0.02434028 | AU6: =AU7 -> 0.02486177 | AV6: =AV7 -> 0.03334324 | AW6: =AW7 -> 0.038079986 | AX6: =AX7 -> 0.042426535 | AY6: =AY7 -> 0.038179695 | AZ6: =AZ7 -> 0.040970915 | ... BC6: =BC7 -> 0.03330738 | BF6: =1-P6-AD6-AR6 -> 0.722 | BG6: =BG7 -> 0.82863779 | BH6: =BH7 -> 0.74703791 | BI6: =BI7 -> 0.75148502 | BJ6: =BJ7 -> 0.77189076 | BK6: =BK7 -> 0.79346372 | BL6: =BL7 -> 0.80107393 | BM6: =BM7 -> 0.82548174 | BN6: =BN7 -> 0.82587233 | ... BQ6: =BQ7 -> 0.87679426
A7: 1990 | P7: =HAVERA!B8/1000 -> 0.185 | Q7: =Q8 -> 0.10488419 | R7: =R8 -> 0.16946117 | S7: =S8 -> 0.16582996 | T7: =T8 -> 0.1484721 | U7: =U8 -> 0.1299966 | V7: =V8 -> 0.12155375 | W7: =W8 -> 0.10751169 | X7: =X8 -> 0.10524167 | ... AA7: =AA8 -> 0.071317947 | AD7: =HAVERA!C8/1000 -> 0.058 | AE7: =AE8 -> 0.029417273 | AF7: =AF8 -> 0.059160641 | AG7: =AG8 -> 0.057823242 | AH7: =AH8 -> 0.046293902 | AI7: =AI8 -> 0.038459694 | AJ7: =AJ8 -> 0.034945783 | AK7: =AK8 -> 0.028826884 | AL7: =AL8 -> 0.027915083 | ... AO7: =AO8 -> 0.018580417 | AR7: =HAVERA!D8/1000 -> 0.038 | AS7: =AS8 -> 0.037060748 | AT7: =AT8 -> 0.02434028 | AU7: =AU8 -> 0.02486177 | AV7: =AV8 -> 0.03334324 | AW7: =AW8 -> 0.038079986 | AX7: =AX8 -> 0.042426535 | AY7: =AY8 -> 0.038179695 | AZ7: =AZ8 -> 0.040970915 | ... BC7: =BC8 -> 0.03330738 | BF7: =1-P7-AD7-AR7 -> 0.719 | BG7: =BG8 -> 0.82863779 | BH7: =BH8 -> 0.74703791 | BI7: =BI8 -> 0.75148502 | BJ7: =BJ8 -> 0.77189076 | BK7: =BK8 -> 0.79346372 | BL7: =BL8 -> 0.80107393 | BM7: =BM8 -> 0.82548174 | BN7: =BN8 -> 0.82587233 | ... BQ7: =BQ8 -> 0.87679426
A8: 1991 | P8: =HAVERA!B9/1000 -> 0.177 | Q8: =Q9 -> 0.10488419 | R8: =R9 -> 0.16946117 | S8: =S9 -> 0.16582996 | T8: =T9 -> 0.1484721 | U8: =U9 -> 0.1299966 | V8: =V9 -> 0.12155375 | W8: =W9 -> 0.10751169 | X8: =X9 -> 0.10524167 | ... AA8: =AA9 -> 0.071317947 | AD8: =HAVERA!C9/1000 -> 0.054 | AE8: =AE9 -> 0.029417273 | AF8: =AF9 -> 0.059160641 | AG8: =AG9 -> 0.057823242 | AH8: =AH9 -> 0.046293902 | AI8: =AI9 -> 0.038459694 | AJ8: =AJ9 -> 0.034945783 | AK8: =AK9 -> 0.028826884 | AL8: =AL9 -> 0.027915083 | ... AO8: =AO9 -> 0.018580417 | AR8: =HAVERA!D9/1000 -> 0.039 | AS8: =AS9 -> 0.037060748 | AT8: =AT9 -> 0.02434028 | AU8: =AU9 -> 0.02486177 | AV8: =AV9 -> 0.03334324 | AW8: =AW9 -> 0.038079986 | AX8: =AX9 -> 0.042426535 | AY8: =AY9 -> 0.038179695 | AZ8: =AZ9 -> 0.040970915 | ... BC8: =BC9 -> 0.03330738 | BF8: =1-P8-AD8-AR8 -> 0.73 | BG8: =BG9 -> 0.82863779 | BH8: =BH9 -> 0.74703791 | BI8: =BI9 -> 0.75148502 | BJ8: =BJ9 -> 0.77189076 | BK8: =BK9 -> 0.79346372 | BL8: =BL9 -> 0.80107393 | BM8: =BM9 -> 0.82548174 | BN8: =BN9 -> 0.82587233 | ... BQ8: =BQ9 -> 0.87679426
A9: 1992 | P9: =HAVERA!B10/1000 -> 0.172 | Q9: =Q10 -> 0.10488419 | R9: =R10 -> 0.16946117 | S9: =S10 -> 0.16582996 | T9: =T10 -> 0.1484721 | U9: =U10 -> 0.1299966 | V9: =V10 -> 0.12155375 | W9: =W10 -> 0.10751169 | X9: =X10 -> 0.10524167 | ... AA9: =AA10 -> 0.071317947 | AD9: =HAVERA!C10/1000 -> 0.053 | AE9: =AE10 -> 0.029417273 | AF9: =AF10 -> 0.059160641 | AG9: =AG10 -> 0.057823242 | AH9: =AH10 -> 0.046293902 | AI9: =AI10 -> 0.038459694 | AJ9: =AJ10 -> 0.034945783 | AK9: =AK10 -> 0.028826884 | AL9: =AL10 -> 0.027915083 | ... AO9: =AO10 -> 0.018580417 | AR9: =HAVERA!D10/1000 -> 0.038 | AS9: =AS10 -> 0.037060748 | AT9: =AT10 -> 0.02434028 | AU9: =AU10 -> 0.02486177 | AV9: =AV10 -> 0.03334324 | AW9: =AW10 -> 0.038079986 | AX9: =AX10 -> 0.042426535 | AY9: =AY10 -> 0.038179695 | AZ9: =AZ10 -> 0.040970915 | ... BC9: =BC10 -> 0.03330738 | BF9: =1-P9-AD9-AR9 -> 0.737 | BG9: =BG10 -> 0.82863779 | BH9: =BH10 -> 0.74703791 | BI9: =BI10 -> 0.75148502 | BJ9: =BJ10 -> 0.77189076 | BK9: =BK10 -> 0.79346372 | BL9: =BL10 -> 0.80107393 | BM9: =BM10 -> 0.82548174 | BN9: =BN10 -> 0.82587233 | ... BQ9: =BQ10 -> 0.87679426
A10: 1993 | P10: =HAVERA!B11/1000 -> 0.159 | Q10: =Q11 -> 0.10488419 | R10: =R11 -> 0.16946117 | S10: =S11 -> 0.16582996 | T10: =T11 -> 0.1484721 | U10: =U11 -> 0.1299966 | V10: =V11 -> 0.12155375 | W10: =W11 -> 0.10751169 | X10: =X11 -> 0.10524167 | ... AA10: =AA11 -> 0.071317947 | AD10: =HAVERA!C11/1000 -> 0.052 | AE10: =AE11 -> 0.029417273 | AF10: =AF11 -> 0.059160641 | AG10: =AG11 -> 0.057823242 | AH10: =AH11 -> 0.046293902 | AI10: =AI11 -> 0.038459694 | AJ10: =AJ11 -> 0.034945783 | AK10: =AK11 -> 0.028826884 | AL10: =AL11 -> 0.027915083 | ... AO10: =AO11 -> 0.018580417 | AR10: =HAVERA!D11/1000 -> 0.039 | AS10: =AS11 -> 0.037060748 | AT10: =AT11 -> 0.02434028 | AU10: =AU11 -> 0.02486177 | AV10: =AV11 -> 0.03334324 | AW10: =AW11 -> 0.038079986 | AX10: =AX11 -> 0.042426535 | AY10: =AY11 -> 0.038179695 | AZ10: =AZ11 -> 0.040970915 | ... BC10: =BC11 -> 0.03330738 | BF10: =1-P10-AD10-AR10 -> 0.75 | BG10: =BG11 -> 0.82863779 | BH10: =BH11 -> 0.74703791 | BI10: =BI11 -> 0.75148502 | BJ10: =BJ11 -> 0.77189076 | BK10: =BK11 -> 0.79346372 | BL10: =BL11 -> 0.80107393 | BM10: =BM11 -> 0.82548174 | BN10: =BN11 -> 0.82587233 | ... BQ10: =BQ11 -> 0.87679426
A11: 1994 | P11: =HAVERA!B12/1000 -> 0.157 | Q11: =Q12 -> 0.10488419 | R11: =R12 -> 0.16946117 | S11: =S12 -> 0.16582996 | T11: =T12 -> 0.1484721 | U11: =U12 -> 0.1299966 | V11: =V12 -> 0.12155375 | W11: =W12 -> 0.10751169 | X11: =X12 -> 0.10524167 | ... AA11: =AA12 -> 0.071317947 | AD11: =HAVERA!C12/1000 -> 0.049 | AE11: =AE12 -> 0.029417273 | AF11: =AF12 -> 0.059160641 | AG11: =AG12 -> 0.057823242 | AH11: =AH12 -> 0.046293902 | AI11: =AI12 -> 0.038459694 | AJ11: =AJ12 -> 0.034945783 | AK11: =AK12 -> 0.028826884 | AL11: =AL12 -> 0.027915083 | ... AO11: =AO12 -> 0.018580417 | AR11: =HAVERA!D12/1000 -> 0.041 | AS11: =AS12 -> 0.037060748 | AT11: =AT12 -> 0.02434028 | AU11: =AU12 -> 0.02486177 | AV11: =AV12 -> 0.03334324 | AW11: =AW12 -> 0.038079986 | AX11: =AX12 -> 0.042426535 | AY11: =AY12 -> 0.038179695 | AZ11: =AZ12 -> 0.040970915 | ... BC11: =BC12 -> 0.03330738 | BF11: =1-P11-AD11-AR11 -> 0.753 | BG11: =BG12 -> 0.82863779 | BH11: =BH12 -> 0.74703791 | BI11: =BI12 -> 0.75148502 | BJ11: =BJ12 -> 0.77189076 | BK11: =BK12 -> 0.79346372 | BL11: =BL12 -> 0.80107393 | BM11: =BM12 -> 0.82548174 | BN11: =BN12 -> 0.82587233 | ... BQ11: =BQ12 -> 0.87679426
A12: 1995 | P12: =HAVERA!B13/1000 -> 0.158 | Q12: =Q13 -> 0.10488419 | R12: =R13 -> 0.16946117 | S12: =S13 -> 0.16582996 | T12: =T13 -> 0.1484721 | U12: =U13 -> 0.1299966 | V12: =V13 -> 0.12155375 | W12: =W13 -> 0.10751169 | X12: =X13 -> 0.10524167 | ... AA12: =AA13 -> 0.071317947 | AD12: =HAVERA!C13/1000 -> 0.049 | AE12: =AE13 -> 0.029417273 | AF12: =AF13 -> 0.059160641 | AG12: =AG13 -> 0.057823242 | AH12: =AH13 -> 0.046293902 | AI12: =AI13 -> 0.038459694 | AJ12: =AJ13 -> 0.034945783 | AK12: =AK13 -> 0.028826884 | AL12: =AL13 -> 0.027915083 | ... AO12: =AO13 -> 0.018580417 | AR12: =HAVERA!D13/1000 -> 0.041 | AS12: =AS13 -> 0.037060748 | AT12: =AT13 -> 0.02434028 | AU12: =AU13 -> 0.02486177 | AV12: =AV13 -> 0.03334324 | AW12: =AW13 -> 0.038079986 | AX12: =AX13 -> 0.042426535 | AY12: =AY13 -> 0.038179695 | AZ12: =AZ13 -> 0.040970915 | ... BC12: =BC13 -> 0.03330738 | BF12: =1-P12-AD12-AR12 -> 0.752 | BG12: =BG13 -> 0.82863779 | BH12: =BH13 -> 0.74703791 | BI12: =BI13 -> 0.75148502 | BJ12: =BJ13 -> 0.77189076 | BK12: =BK13 -> 0.79346372 | BL12: =BL13 -> 0.80107393 | BM12: =BM13 -> 0.82548174 | BN12: =BN13 -> 0.82587233 | ... BQ12: =BQ13 -> 0.87679426
A13: 1996 | B13: =DataA!N30 -> 68.81667 | C13: =DataA!O30 -> 58.90833 | D13: =DataA!P30 -> 40.2 | E13: =DataA!Q30 -> 50.46667 | F13: =$F$32*(1*B13/$B$32-P13*C13/$C$32-AD13*D13/$D$32-AR13*E13/$E$32)/(1-P13-AD13-AR13) -> 73.509342 | G13: =G14*(P13*C13/C14+AD13*D13/D14+AR13*E13/E14+BF13*F13/F14) -> 69.999737 | H13: =100*((G13/G12)-1) -> #DIV/0! | I13: =100*((B13/B12)-1) -> #DIV/0! | P13: =HAVERA!B14/1000 -> 0.156 | Q13: =Q14 -> 0.10488419 | R13: =R14 -> 0.16946117 | S13: =S14 -> 0.16582996 | T13: =T14 -> 0.1484721 | U13: =U14 -> 0.1299966 | V13: =V14 -> 0.12155375 | W13: =W14 -> 0.10751169 | X13: =X14 -> 0.10524167 | ... AA13: =AA14 -> 0.071317947 | AD13: =HAVERA!C14/1000 -> 0.045 | AE13: =AE14 -> 0.029417273 | AF13: =AF14 -> 0.059160641 | AG13: =AG14 -> 0.057823242 | AH13: =AH14 -> 0.046293902 | AI13: =AI14 -> 0.038459694 | AJ13: =AJ14 -> 0.034945783 | AK13: =AK14 -> 0.028826884 | AL13: =AL14 -> 0.027915083 | ... AO13: =AO14 -> 0.018580417 | AR13: =HAVERA!D14/1000 -> 0.04 | AS13: =AS14 -> 0.037060748 | AT13: =AT14 -> 0.02434028 | AU13: =AU14 -> 0.02486177 | AV13: =AV14 -> 0.03334324 | AW13: =AW14 -> 0.038079986 | AX13: =AX14 -> 0.042426535 | AY13: =AY14 -> 0.038179695 | AZ13: =AZ14 -> 0.040970915 | ... BC13: =BC14 -> 0.03330738 | BF13: =1-P13-AD13-AR13 -> 0.759 | BG13: =BG14 -> 0.82863779 | BH13: =BH14 -> 0.74703791 | BI13: =BI14 -> 0.75148502 | BJ13: =BJ14 -> 0.77189076 | BK13: =BK14 -> 0.79346372 | BL13: =BL14 -> 0.80107393 | BM13: =BM14 -> 0.82548174 | BN13: =BN14 -> 0.82587233 | ... BQ13: =BQ14 -> 0.87679426
A14: 1997 | B14: =DataA!N31 -> 70.06667 | C14: =DataA!O31 -> 59.60833 | D14: =DataA!P31 -> 39.01667 | E14: =DataA!Q31 -> 55.48333 | F14: =$F$32*(1*B14/$B$32-P14*C14/$C$32-AD14*D14/$D$32-AR14*E14/$E$32)/(1-P14-AD14-AR14) -> 74.767241 | G14: =G15*(P14*C14/C15+AD14*D14/D15+AR14*E14/E15+BF14*F14/F15) -> 71.199695 | H14: =100*((G14/G13)-1) -> 1.7142332 | I14: =100*((B14/B13)-1) -> 1.8164204 | P14: =HAVERA!B15/1000 -> 0.152 | Q14: =Q15 -> 0.10488419 | R14: =R15 -> 0.16946117 | S14: =S15 -> 0.16582996 | T14: =T15 -> 0.1484721 | U14: =U15 -> 0.1299966 | V14: =V15 -> 0.12155375 | W14: =W15 -> 0.10751169 | X14: =X15 -> 0.10524167 | ... AA14: =AA15 -> 0.071317947 | AD14: =HAVERA!C15/1000 -> 0.044 | AE14: =AE15 -> 0.029417273 | AF14: =AF15 -> 0.059160641 | AG14: =AG15 -> 0.057823242 | AH14: =AH15 -> 0.046293902 | AI14: =AI15 -> 0.038459694 | AJ14: =AJ15 -> 0.034945783 | AK14: =AK15 -> 0.028826884 | AL14: =AL15 -> 0.027915083 | ... AO14: =AO15 -> 0.018580417 | AR14: =HAVERA!D15/1000 -> 0.043 | AS14: =AS15 -> 0.037060748 | AT14: =AT15 -> 0.02434028 | AU14: =AU15 -> 0.02486177 | AV14: =AV15 -> 0.03334324 | AW14: =AW15 -> 0.038079986 | AX14: =AX15 -> 0.042426535 | AY14: =AY15 -> 0.038179695 | AZ14: =AZ15 -> 0.040970915 | ... BC14: =BC15 -> 0.03330738 | BF14: =1-P14-AD14-AR14 -> 0.761 | BG14: =BG15 -> 0.82863779 | BH14: =BH15 -> 0.74703791 | BI14: =BI15 -> 0.75148502 | BJ14: =BJ15 -> 0.77189076 | BK14: =BK15 -> 0.79346372 | BL14: =BL15 -> 0.80107393 | BM14: =BM15 -> 0.82548174 | BN14: =BN15 -> 0.82587233 | ... BQ14: =BQ15 -> 0.87679426
A15: 1998 | B15: =DataA!N32 -> 71.15833 | C15: =DataA!O32 -> 61.06666 | D15: =DataA!P32 -> 37.38334 | E15: =DataA!Q32 -> 58.25834 | F15: =$F$32*(1*B15/$B$32-P15*C15/$C$32-AD15*D15/$D$32-AR15*E15/$E$32)/(1-P15-AD15-AR15) -> 75.644456 | G15: =G16*(P15*C15/C16+AD15*D15/D16+AR15*E15/E16+BF15*F15/F16) -> 72.106848 | H15: =100*((G15/G14)-1) -> 1.2740967 | I15: =100*((B15/B14)-1) -> 1.5580304 | P15: =HAVERA!B16/1000 -> 0.144 | Q15: =Q16 -> 0.10488419 | R15: =R16 -> 0.16946117 | S15: =S16 -> 0.16582996 | T15: =T16 -> 0.1484721 | U15: =U16 -> 0.1299966 | V15: =V16 -> 0.12155375 | W15: =W16 -> 0.10751169 | X15: =X16 -> 0.10524167 | ... AA15: =AA16 -> 0.071317947 | AD15: =HAVERA!C16/1000 -> 0.043 | AE15: =AE16 -> 0.029417273 | AF15: =AF16 -> 0.059160641 | AG15: =AG16 -> 0.057823242 | AH15: =AH16 -> 0.046293902 | AI15: =AI16 -> 0.038459694 | AJ15: =AJ16 -> 0.034945783 | AK15: =AK16 -> 0.028826884 | AL15: =AL16 -> 0.027915083 | ... AO15: =AO16 -> 0.018580417 | AR15: =HAVERA!D16/1000 -> 0.043 | AS15: =AS16 -> 0.037060748 | AT15: =AT16 -> 0.02434028 | AU15: =AU16 -> 0.02486177 | AV15: =AV16 -> 0.03334324 | AW15: =AW16 -> 0.038079986 | AX15: =AX16 -> 0.042426535 | AY15: =AY16 -> 0.038179695 | AZ15: =AZ16 -> 0.040970915 | ... BC15: =BC16 -> 0.03330738 | BF15: =1-P15-AD15-AR15 -> 0.77 | BG15: =BG16 -> 0.82863779 | BH15: =BH16 -> 0.74703791 | BI15: =BI16 -> 0.75148502 | BJ15: =BJ16 -> 0.77189076 | BK15: =BK16 -> 0.79346372 | BL15: =BL16 -> 0.80107393 | BM15: =BM16 -> 0.82548174 | BN15: =BN16 -> 0.82587233 | ... BQ15: =BQ16 -> 0.87679426
A16: 1999 | B16: =DataA!N33 -> 72.11666 | C16: =DataA!O33 -> 62.375 | D16: =DataA!P33 -> 37.36666 | E16: =DataA!Q33 -> 63.16667 | F16: =$F$32*(1*B16/$B$32-P16*C16/$C$32-AD16*D16/$D$32-AR16*E16/$E$32)/(1-P16-AD16-AR16) -> 76.166192 | G16: =G17*(P16*C16/C17+AD16*D16/D17+AR16*E16/E17+BF16*F16/F17) -> 72.954361 | H16: =100*((G16/G15)-1) -> 1.1753565 | I16: =100*((B16/B15)-1) -> 1.3467573 | P16: =HAVERA!B17/1000 -> 0.141 | Q16: =Q17 -> 0.10488419 | R16: =R17 -> 0.16946117 | S16: =S17 -> 0.16582996 | T16: =T17 -> 0.1484721 | U16: =U17 -> 0.1299966 | V16: =V17 -> 0.12155375 | W16: =W17 -> 0.10751169 | X16: =X17 -> 0.10524167 | ... AA16: =AA17 -> 0.071317947 | AD16: =HAVERA!C17/1000 -> 0.04 | AE16: =AE17 -> 0.029417273 | AF16: =AF17 -> 0.059160641 | AG16: =AG17 -> 0.057823242 | AH16: =AH17 -> 0.046293902 | AI16: =AI17 -> 0.038459694 | AJ16: =AJ17 -> 0.034945783 | AK16: =AK17 -> 0.028826884 | AL16: =AL17 -> 0.027915083 | ... AO16: =AO17 -> 0.018580417 | AR16: =HAVERA!D17/1000 -> 0.043 | AS16: =AS17 -> 0.037060748 | AT16: =AT17 -> 0.02434028 | AU16: =AU17 -> 0.02486177 | AV16: =AV17 -> 0.03334324 | AW16: =AW17 -> 0.038079986 | AX16: =AX17 -> 0.042426535 | AY16: =AY17 -> 0.038179695 | AZ16: =AZ17 -> 0.040970915 | ... BC16: =BC17 -> 0.03330738 | BF16: =1-P16-AD16-AR16 -> 0.776 | BG16: =BG17 -> 0.82863779 | BH16: =BH17 -> 0.74703791 | BI16: =BI17 -> 0.75148502 | BJ16: =BJ17 -> 0.77189076 | BK16: =BK17 -> 0.79346372 | BL16: =BL17 -> 0.80107393 | BM16: =BM17 -> 0.82548174 | BN16: =BN17 -> 0.82587233 | ... BQ16: =BQ17 -> 0.87679426
A17: 2000 | B17: =DataA!N34 -> 72.69167 | C17: =DataA!O34 -> 63.075 | D17: =DataA!P34 -> 37.39167 | E17: =DataA!Q34 -> 71.475 | F17: =$F$32*(1*B17/$B$32-P17*C17/$C$32-AD17*D17/$D$32-AR17*E17/$E$32)/(1-P17-AD17-AR17) -> 75.623249 | G17: =G18*(P17*C17/C18+AD17*D17/D18+AR17*E17/E18+BF17*F17/F18) -> 73.028746 | H17: =100*((G17/G16)-1) -> 0.10196156 | I17: =100*((B17/B16)-1) -> 0.7973331 | P17: =HAVERA!B18/1000 -> 0.121 | Q17: =Q18 -> 0.10488419 | R17: =R18 -> 0.16946117 | S17: =S18 -> 0.16582996 | T17: =T18 -> 0.1484721 | U17: =U18 -> 0.1299966 | V17: =V18 -> 0.12155375 | W17: =W18 -> 0.10751169 | X17: =X18 -> 0.10524167 | ... AA17: =AA18 -> 0.071317947 | AD17: =HAVERA!C18/1000 -> 0.033 | AE17: =AE18 -> 0.029417273 | AF17: =AF18 -> 0.059160641 | AG17: =AG18 -> 0.057823242 | AH17: =AH18 -> 0.046293902 | AI17: =AI18 -> 0.038459694 | AJ17: =AJ18 -> 0.034945783 | AK17: =AK18 -> 0.028826884 | AL17: =AL18 -> 0.027915083 | ... AO17: =AO18 -> 0.018580417 | AR17: =HAVERA!D18/1000 -> 0.038 | AS17: =AS18 -> 0.037060748 | AT17: =AT18 -> 0.02434028 | AU17: =AU18 -> 0.02486177 | AV17: =AV18 -> 0.03334324 | AW17: =AW18 -> 0.038079986 | AX17: =AX18 -> 0.042426535 | AY17: =AY18 -> 0.038179695 | AZ17: =AZ18 -> 0.040970915 | ... BC17: =BC18 -> 0.03330738 | BF17: =1-P17-AD17-AR17 -> 0.808 | BG17: =BG18 -> 0.82863779 | BH17: =BH18 -> 0.74703791 | BI17: =BI18 -> 0.75148502 | BJ17: =BJ18 -> 0.77189076 | BK17: =BK18 -> 0.79346372 | BL17: =BL18 -> 0.80107393 | BM17: =BM18 -> 0.82548174 | BN17: =BN18 -> 0.82587233 | ... BQ17: =BQ18 -> 0.87679426
A18: 2001 | B18: =DataA!N35 -> 73.59167 | C18: =DataA!O35 -> 65.36667 | D18: =DataA!P35 -> 37.58333 | E18: =DataA!Q35 -> 67.80833 | F18: =$F$32*(1*B18/$B$32-P18*C18/$C$32-AD18*D18/$D$32-AR18*E18/$E$32)/(1-P18-AD18-AR18) -> 76.262117 | G18: =G19*(P18*C18/C19+AD18*D18/D19+AR18*E18/E19+BF18*F18/F19) -> 73.701226 | H18: =100*((G18/G17)-1) -> 0.92084212 | I18: =100*((B18/B17)-1) -> 1.2381061 | P18: =HAVERA!B19/1000 -> 0.114 | Q18: ='Family spending workbook 1'!Y8/100 -> 0.10488419 | R18: ='Family spending workbook 1'!O8/100 -> 0.16946117 | S18: ='Family spending workbook 1'!P8/100 -> 0.16582996 | T18: ='Family spending workbook 1'!Q8/100 -> 0.1484721 | U18: ='Family spending workbook 1'!R8/100 -> 0.1299966 | V18: ='Family spending workbook 1'!S8/100 -> 0.12155375 | W18: ='Family spending workbook 1'!T8/100 -> 0.10751169 | X18: ='Family spending workbook 1'!U8/100 -> 0.10524167 | Y18: ='Family spending workbook 1'!V8/100 -> 0.09551406 | ... AA18: ='Family spending workbook 1'!X8/100 -> 0.071317947 | AD18: =HAVERA!C19/1000 -> 0.029 | AE18: ='Family spending workbook 1'!Y39/100 -> 0.029417273 | AF18: ='Family spending workbook 1'!O39/100 -> 0.059160641 | AG18: ='Family spending workbook 1'!P39/100 -> 0.057823242 | AH18: ='Family spending workbook 1'!Q39/100 -> 0.046293902 | AI18: ='Family spending workbook 1'!R39/100 -> 0.038459694 | AJ18: ='Family spending workbook 1'!S39/100 -> 0.034945783 | AK18: ='Family spending workbook 1'!T39/100 -> 0.028826884 | AL18: ='Family spending workbook 1'!U39/100 -> 0.027915083 | AM18: ='Family spending workbook 1'!V39/100 -> 0.024749824 | ... AO18: ='Family spending workbook 1'!X39/100 -> 0.018580417 | AR18: =HAVERA!D19/1000 -> 0.037 | AS18: ='Family spending workbook 1'!Y70/100 -> 0.037060748 | AT18: ='Family spending workbook 1'!O70/100 -> 0.02434028 | AU18: ='Family spending workbook 1'!P70/100 -> 0.02486177 | AV18: ='Family spending workbook 1'!Q70/100 -> 0.03334324 | AW18: ='Family spending workbook 1'!R70/100 -> 0.038079986 | AX18: ='Family spending workbook 1'!S70/100 -> 0.042426535 | AY18: ='Family spending workbook 1'!T70/100 -> 0.038179695 | AZ18: ='Family spending workbook 1'!U70/100 -> 0.040970915 | BA18: ='Family spending workbook 1'!V70/100 -> 0.042121645 | ... BC18: ='Family spending workbook 1'!X70/100 -> 0.03330738 | BF18: =1-P18-AD18-AR18 -> 0.82 | BG18: =1-Q18-AE18-AS18 -> 0.82863779 | BH18: =1-R18-AF18-AT18 -> 0.74703791 | BI18: =1-S18-AG18-AU18 -> 0.75148502 | BJ18: =1-T18-AH18-AV18 -> 0.77189076 | BK18: =1-U18-AI18-AW18 -> 0.79346372 | BL18: =1-V18-AJ18-AX18 -> 0.80107393 | BM18: =1-W18-AK18-AY18 -> 0.82548174 | ... BQ18: =1-AA18-AO18-BC18 -> 0.87679426
A19: 2002 | B19: =DataA!N36 -> 74.5 | C19: =DataA!O36 -> 66.09167 | D19: =DataA!P36 -> 38.425 | E19: =DataA!Q36 -> 65.675 | F19: =$F$32*(1*B19/$B$32-P19*C19/$C$32-AD19*D19/$D$32-AR19*E19/$E$32)/(1-P19-AD19-AR19) -> 77.175481 | G19: =G20*(P19*C19/C20+AD19*D19/D20+AR19*E19/E20+BF19*F19/F20) -> 74.474908 | H19: =100*((G19/G18)-1) -> 1.0497552 | I19: =100*((B19/B18)-1) -> 1.2342837 | P19: =HAVERA!B20/1000 -> 0.115 | Q19: ='Family spending workbook 1'!Y9/100 -> 0.10520183 | R19: ='Family spending workbook 1'!O9/100 -> 0.15704853 | S19: ='Family spending workbook 1'!P9/100 -> 0.16338986 | T19: ='Family spending workbook 1'!Q9/100 -> 0.15702111 | U19: ='Family spending workbook 1'!R9/100 -> 0.12308773 | V19: ='Family spending workbook 1'!S9/100 -> 0.11976307 | W19: ='Family spending workbook 1'!T9/100 -> 0.10687917 | X19: ='Family spending workbook 1'!U9/100 -> 0.10740519 | Y19: ='Family spending workbook 1'!V9/100 -> 0.097301147 | ... AA19: ='Family spending workbook 1'!X9/100 -> 0.075718961 | AD19: =HAVERA!C20/1000 -> 0.028 | AE19: ='Family spending workbook 1'!Y40/100 -> 0.028784334 | AF19: ='Family spending workbook 1'!O40/100 -> 0.056798542 | AG19: ='Family spending workbook 1'!P40/100 -> 0.055393867 | AH19: ='Family spending workbook 1'!Q40/100 -> 0.045530941 | AI19: ='Family spending workbook 1'!R40/100 -> 0.036538901 | AJ19: ='Family spending workbook 1'!S40/100 -> 0.033104209 | AK19: ='Family spending workbook 1'!T40/100 -> 0.029968753 | AL19: ='Family spending workbook 1'!U40/100 -> 0.027078174 | AM19: ='Family spending workbook 1'!V40/100 -> 0.024760157 | ... AO19: ='Family spending workbook 1'!X40/100 -> 0.018750652 | AR19: =HAVERA!D20/1000 -> 0.028 | AS19: ='Family spending workbook 1'!Y71/100 -> 0.036521359 | AT19: ='Family spending workbook 1'!O71/100 -> 0.02195034 | AU19: ='Family spending workbook 1'!P71/100 -> 0.025403737 | AV19: ='Family spending workbook 1'!Q71/100 -> 0.029677211 | AW19: ='Family spending workbook 1'!R71/100 -> 0.036351205 | AX19: ='Family spending workbook 1'!S71/100 -> 0.036855088 | AY19: ='Family spending workbook 1'!T71/100 -> 0.038877889 | AZ19: ='Family spending workbook 1'!U71/100 -> 0.040017961 | BA19: ='Family spending workbook 1'!V71/100 -> 0.04180088 | ... BC19: ='Family spending workbook 1'!X71/100 -> 0.032584176 | BF19: =1-P19-AD19-AR19 -> 0.829 | BG19: =1-Q19-AE19-AS19 -> 0.82949248 | BH19: =1-R19-AF19-AT19 -> 0.76420259 | BI19: =1-S19-AG19-AU19 -> 0.75581254 | BJ19: =1-T19-AH19-AV19 -> 0.76777073 | BK19: =1-U19-AI19-AW19 -> 0.80402217 | BL19: =1-V19-AJ19-AX19 -> 0.81027764 | BM19: =1-W19-AK19-AY19 -> 0.82427419 | ... BQ19: =1-AA19-AO19-BC19 -> 0.87294621
A20: 2003 | B20: =DataA!N37 -> 75.525 | C20: =DataA!O37 -> 67.01667 | D20: =DataA!P37 -> 39.125 | E20: =DataA!Q37 -> 68.05 | F20: =$F$32*(1*B20/$B$32-P20*C20/$C$32-AD20*D20/$D$32-AR20*E20/$E$32)/(1-P20-AD20-AR20) -> 78.07417 | G20: =G21*(P20*C20/C21+AD20*D20/D21+AR20*E20/E21+BF20*F20/F21) -> 75.425866 | H20: =100*((G20/G19)-1) -> 1.276884 | I20: =100*((B20/B19)-1) -> 1.3758389 | P20: =HAVERA!B21/1000 -> 0.108 | Q20: ='Family spending workbook 1'!Y10/100 -> 0.10409083 | R20: ='Family spending workbook 1'!O10/100 -> 0.1532264 | S20: ='Family spending workbook 1'!P10/100 -> 0.16027044 | T20: ='Family spending workbook 1'!Q10/100 -> 0.15265657 | U20: ='Family spending workbook 1'!R10/100 -> 0.12240644 | V20: ='Family spending workbook 1'!S10/100 -> 0.11713357 | W20: ='Family spending workbook 1'!T10/100 -> 0.10866181 | X20: ='Family spending workbook 1'!U10/100 -> 0.10185856 | Y20: ='Family spending workbook 1'!V10/100 -> 0.091684736 | ... AA20: ='Family spending workbook 1'!X10/100 -> 0.074906704 | AD20: =HAVERA!C21/1000 -> 0.028 | AE20: ='Family spending workbook 1'!Y41/100 -> 0.028631137 | AF20: ='Family spending workbook 1'!O41/100 -> 0.056310083 | AG20: ='Family spending workbook 1'!P41/100 -> 0.050813824 | AH20: ='Family spending workbook 1'!Q41/100 -> 0.047442448 | AI20: ='Family spending workbook 1'!R41/100 -> 0.035665035 | AJ20: ='Family spending workbook 1'!S41/100 -> 0.032064158 | AK20: ='Family spending workbook 1'!T41/100 -> 0.029602689 | AL20: ='Family spending workbook 1'!U41/100 -> 0.026501233 | AM20: ='Family spending workbook 1'!V41/100 -> 0.023762872 | ... AO20: ='Family spending workbook 1'!X41/100 -> 0.019226402 | AR20: =HAVERA!D21/1000 -> 0.027 | AS20: ='Family spending workbook 1'!Y72/100 -> 0.035761298 | AT20: ='Family spending workbook 1'!O72/100 -> 0.024327927 | AU20: ='Family spending workbook 1'!P72/100 -> 0.024733822 | AV20: ='Family spending workbook 1'!Q72/100 -> 0.029539023 | AW20: ='Family spending workbook 1'!R72/100 -> 0.033440621 | AX20: ='Family spending workbook 1'!S72/100 -> 0.037471131 | AY20: ='Family spending workbook 1'!T72/100 -> 0.038535195 | AZ20: ='Family spending workbook 1'!U72/100 -> 0.038057991 | BA20: ='Family spending workbook 1'!V72/100 -> 0.038576037 | ... BC20: ='Family spending workbook 1'!X72/100 -> 0.034476651 | BF20: =1-P20-AD20-AR20 -> 0.837 | BG20: =1-Q20-AE20-AS20 -> 0.83151673 | BH20: =1-R20-AF20-AT20 -> 0.76613559 | BI20: =1-S20-AG20-AU20 -> 0.76418192 | BJ20: =1-T20-AH20-AV20 -> 0.77036196 | BK20: =1-U20-AI20-AW20 -> 0.8084879 | BL20: =1-V20-AJ20-AX20 -> 0.81333114 | BM20: =1-W20-AK20-AY20 -> 0.82320031 | ... BQ20: =1-AA20-AO20-BC20 -> 0.87139024
A21: 2004 | B21: =DataA!N38 -> 76.54167 | C21: =DataA!O38 -> 67.73334 | D21: =DataA!P38 -> 41.79166 | E21: =DataA!Q38 -> 71.85 | F21: =$F$32*(1*B21/$B$32-P21*C21/$C$32-AD21*D21/$D$32-AR21*E21/$E$32)/(1-P21-AD21-AR21) -> 78.860925 | G21: =G22*(P21*C21/C22+AD21*D21/D22+AR21*E21/E22+BF21*F21/F22) -> 76.396689 | H21: =100*((G21/G20)-1) -> 1.2871218 | I21: =100*((B21/B20)-1) -> 1.346137 | P21: =HAVERA!B22/1000 -> 0.106 | Q21: ='Family spending workbook 1'!Y11/100 -> 0.10297638 | R21: ='Family spending workbook 1'!O11/100 -> 0.1592675 | S21: ='Family spending workbook 1'!P11/100 -> 0.15891258 | T21: ='Family spending workbook 1'!Q11/100 -> 0.14269955 | U21: ='Family spending workbook 1'!R11/100 -> 0.11884906 | V21: ='Family spending workbook 1'!S11/100 -> 0.1165455 | W21: ='Family spending workbook 1'!T11/100 -> 0.10650418 | X21: ='Family spending workbook 1'!U11/100 -> 0.10268439 | Y21: ='Family spending workbook 1'!V11/100 -> 0.095494142 | ... AA21: ='Family spending workbook 1'!X11/100 -> 0.073741672 | AD21: =HAVERA!C22/1000 -> 0.026 | AE21: ='Family spending workbook 1'!Y42/100 -> 0.028887721 | AF21: ='Family spending workbook 1'!O42/100 -> 0.054691011 | AG21: ='Family spending workbook 1'!P42/100 -> 0.053264522 | AH21: ='Family spending workbook 1'!Q42/100 -> 0.042581598 | AI21: ='Family spending workbook 1'!R42/100 -> 0.035798322 | AJ21: ='Family spending workbook 1'!S42/100 -> 0.032498847 | AK21: ='Family spending workbook 1'!T42/100 -> 0.030185893 | AL21: ='Family spending workbook 1'!U42/100 -> 0.027068736 | AM21: ='Family spending workbook 1'!V42/100 -> 0.025582282 | ... AO21: ='Family spending workbook 1'!X42/100 -> 0.019621298 | AR21: =HAVERA!D22/1000 -> 0.026 | AS21: ='Family spending workbook 1'!Y73/100 -> 0.03725737 | AT21: ='Family spending workbook 1'!O73/100 -> 0.020871716 | AU21: ='Family spending workbook 1'!P73/100 -> 0.02630056 | AV21: ='Family spending workbook 1'!Q73/100 -> 0.032057508 | AW21: ='Family spending workbook 1'!R73/100 -> 0.034915541 | AX21: ='Family spending workbook 1'!S73/100 -> 0.036953302 | AY21: ='Family spending workbook 1'!T73/100 -> 0.039475378 | AZ21: ='Family spending workbook 1'!U73/100 -> 0.041325102 | BA21: ='Family spending workbook 1'!V73/100 -> 0.041574926 | ... BC21: ='Family spending workbook 1'!X73/100 -> 0.036026305 | BF21: =1-P21-AD21-AR21 -> 0.842 | BG21: =1-Q21-AE21-AS21 -> 0.83087853 | BH21: =1-R21-AF21-AT21 -> 0.76516977 | BI21: =1-S21-AG21-AU21 -> 0.76152234 | BJ21: =1-T21-AH21-AV21 -> 0.78266134 | BK21: =1-U21-AI21-AW21 -> 0.81043708 | BL21: =1-V21-AJ21-AX21 -> 0.81400235 | BM21: =1-W21-AK21-AY21 -> 0.82383455 | ... BQ21: =1-AA21-AO21-BC21 -> 0.87061072
A22: 2005 | B22: =DataA!N39 -> 78.1 | C22: =DataA!O39 -> 68.9 | D22: =DataA!P39 -> 47.28334 | E22: =DataA!Q39 -> 78.14166 | F22: =$F$32*(1*B22/$B$32-P22*C22/$C$32-AD22*D22/$D$32-AR22*E22/$E$32)/(1-P22-AD22-AR22) -> 80.281714 | G22: =B22 -> 78.1 | H22: =100*((G22/G21)-1) -> 2.2295613 | I22: =100*((B22/B21)-1) -> 2.0359237 | P22: =HAVERA!B23/1000 -> 0.106 | Q22: ='Family spending workbook 1'!Y12/100 -> 0.10219289 | R22: ='Family spending workbook 1'!O12/100 -> 0.1554441 | S22: ='Family spending workbook 1'!P12/100 -> 0.16474089 | T22: ='Family spending workbook 1'!Q12/100 -> 0.13221753 | U22: ='Family spending workbook 1'!R12/100 -> 0.12330339 | V22: ='Family spending workbook 1'!S12/100 -> 0.1176211 | W22: ='Family spending workbook 1'!T12/100 -> 0.1068728 | X22: ='Family spending workbook 1'!U12/100 -> 0.1047476 | Y22: ='Family spending workbook 1'!V12/100 -> 0.095866251 | ... AA22: ='Family spending workbook 1'!X12/100 -> 0.072158489 | AD22: =HAVERA!C23/1000 -> 0.028 | AE22: ='Family spending workbook 1'!Y43/100 -> 0.031301102 | AF22: ='Family spending workbook 1'!O43/100 -> 0.057790564 | AG22: ='Family spending workbook 1'!P43/100 -> 0.056381669 | AH22: ='Family spending workbook 1'!Q43/100 -> 0.046641105 | AI22: ='Family spending workbook 1'!R43/100 -> 0.041374441 | AJ22: ='Family spending workbook 1'!S43/100 -> 0.036869684 | AK22: ='Family spending workbook 1'!T43/100 -> 0.032708996 | AL22: ='Family spending workbook 1'!U43/100 -> 0.029665669 | AM22: ='Family spending workbook 1'!V43/100 -> 0.026571226 | ... AO22: ='Family spending workbook 1'!X43/100 -> 0.020565009 | AR22: =HAVERA!D23/1000 -> 0.027 | AS22: ='Family spending workbook 1'!Y74/100 -> 0.062920236 | AT22: ='Family spending workbook 1'!O74/100 -> 0.036202842 | AU22: ='Family spending workbook 1'!P74/100 -> 0.046296907 | AV22: ='Family spending workbook 1'!Q74/100 -> 0.04942166 | AW22: ='Family spending workbook 1'!R74/100 -> 0.053748211 | AX22: ='Family spending workbook 1'!S74/100 -> 0.067155425 | AY22: ='Family spending workbook 1'!T74/100 -> 0.068446557 | AZ22: ='Family spending workbook 1'!U74/100 -> 0.064355461 | BA22: ='Family spending workbook 1'!V74/100 -> 0.072610736 | ... BC22: ='Family spending workbook 1'!X74/100 -> 0.062595777 | BF22: =1-P22-AD22-AR22 -> 0.839 | BG22: =1-Q22-AE22-AS22 -> 0.80358578 | BH22: =1-R22-AF22-AT22 -> 0.7505625 | BI22: =1-S22-AG22-AU22 -> 0.73258053 | BJ22: =1-T22-AH22-AV22 -> 0.7717197 | BK22: =1-U22-AI22-AW22 -> 0.78157396 | BL22: =1-V22-AJ22-AX22 -> 0.77835379 | BM22: =1-W22-AK22-AY22 -> 0.79197165 | ... BQ22: =1-AA22-AO22-BC22 -> 0.84468072
A23: 2006 | B23: =DataA!N40 -> 79.93333 | C23: =DataA!O40 -> 70.66666 | D23: =DataA!P40 -> 58.96667 | E23: =DataA!Q40 -> 82.44167 | F23: =$F$32*(1*B23/$B$32-P23*C23/$C$32-AD23*D23/$D$32-AR23*E23/$E$32)/(1-P23-AD23-AR23) -> 81.764505 | G23: =G22*(P23*C23/C22+AD23*D23/D22+AR23*E23/E22+BF23*F23/F22) -> 80.270926 | H23: =100*((G23/G22)-1) -> 2.7796745 | I23: =100*((B23/B22)-1) -> 2.3474136 | P23: =HAVERA!B24/1000 -> 0.102 | Q23: ='Family spending workbook 1'!Y13/100 -> 0.10285063 | R23: ='Family spending workbook 1'!O13/100 -> 0.15729622 | S23: ='Family spending workbook 1'!P13/100 -> 0.15708845 | T23: ='Family spending workbook 1'!Q13/100 -> 0.13487698 | U23: ='Family spending workbook 1'!R13/100 -> 0.12053503 | V23: ='Family spending workbook 1'!S13/100 -> 0.11725278 | W23: ='Family spending workbook 1'!T13/100 -> 0.10812504 | X23: ='Family spending workbook 1'!U13/100 -> 0.10232598 | Y23: ='Family spending workbook 1'!V13/100 -> 0.097304216 | ... AA23: ='Family spending workbook 1'!X13/100 -> 0.074573905 | AD23: =HAVERA!C24/1000 -> 0.032 | AE23: ='Family spending workbook 1'!Y44/100 -> 0.034854812 | AF23: ='Family spending workbook 1'!O44/100 -> 0.065800519 | AG23: ='Family spending workbook 1'!P44/100 -> 0.062331171 | AH23: ='Family spending workbook 1'!Q44/100 -> 0.05140911 | AI23: ='Family spending workbook 1'!R44/100 -> 0.041946446 | AJ23: ='Family spending workbook 1'!S44/100 -> 0.040465447 | AK23: ='Family spending workbook 1'!T44/100 -> 0.036331291 | AL23: ='Family spending workbook 1'!U44/100 -> 0.032306615 | AM23: ='Family spending workbook 1'!V44/100 -> 0.030310467 | ... AO23: ='Family spending workbook 1'!X44/100 -> 0.02378899 | AR23: =HAVERA!D24/1000 -> 0.035 | AS23: ='Family spending workbook 1'!Y75/100 -> 0.062786832 | AT23: ='Family spending workbook 1'!O75/100 -> 0.041190967 | AU23: ='Family spending workbook 1'!P75/100 -> 0.045460325 | AV23: ='Family spending workbook 1'!Q75/100 -> 0.057382364 | AW23: ='Family spending workbook 1'!R75/100 -> 0.056518364 | AX23: ='Family spending workbook 1'!S75/100 -> 0.065682415 | AY23: ='Family spending workbook 1'!T75/100 -> 0.064615519 | AZ23: ='Family spending workbook 1'!U75/100 -> 0.066219308 | BA23: ='Family spending workbook 1'!V75/100 -> 0.068604752 | ... BC23: ='Family spending workbook 1'!X75/100 -> 0.063394792 | BF23: =1-P23-AD23-AR23 -> 0.831 | BG23: =1-Q23-AE23-AS23 -> 0.79950773 | BH23: =1-R23-AF23-AT23 -> 0.73571229 | BI23: =1-S23-AG23-AU23 -> 0.73512005 | BJ23: =1-T23-AH23-AV23 -> 0.75633155 | BK23: =1-U23-AI23-AW23 -> 0.78100016 | BL23: =1-V23-AJ23-AX23 -> 0.77659936 | BM23: =1-W23-AK23-AY23 -> 0.79092815 | ... BQ23: =1-AA23-AO23-BC23 -> 0.83824231
A24: 2007 | B24: =DataA!N41 -> 81.78333 | C24: =DataA!O41 -> 73.65833 | D24: =DataA!P41 -> 63.23333 | E24: =DataA!Q41 -> 84.83334 | F24: =$F$32*(1*B24/$B$32-P24*C24/$C$32-AD24*D24/$D$32-AR24*E24/$E$32)/(1-P24-AD24-AR24) -> 83.539699 | G24: =G23*(P24*C24/C23+AD24*D24/D23+AR24*E24/E23+BF24*F24/F23) -> 82.363854 | H24: =100*((G24/G23)-1) -> 2.6073303 | I24: =100*((B24/B23)-1) -> 2.3144288 | P24: =HAVERA!B25/1000 -> 0.103 | Q24: ='Family spending workbook 1'!Y14/100 -> 0.10480237 | R24: ='Family spending workbook 1'!O14/100 -> 0.14190576 | S24: ='Family spending workbook 1'!P14/100 -> 0.16534494 | T24: ='Family spending workbook 1'!Q14/100 -> 0.14086814 | U24: ='Family spending workbook 1'!R14/100 -> 0.12681719 | V24: ='Family spending workbook 1'!S14/100 -> 0.11953321 | W24: ='Family spending workbook 1'!T14/100 -> 0.10618105 | X24: ='Family spending workbook 1'!U14/100 -> 0.1089597 | Y24: ='Family spending workbook 1'!V14/100 -> 0.099061697 | ... AA24: ='Family spending workbook 1'!X14/100 -> 0.074074847 | AD24: =HAVERA!C25/1000 -> 0.039 | AE24: ='Family spending workbook 1'!Y45/100 -> 0.037356644 | AF24: ='Family spending workbook 1'!O45/100 -> 0.06362175 | AG24: ='Family spending workbook 1'!P45/100 -> 0.067427698 | AH24: ='Family spending workbook 1'!Q45/100 -> 0.053585002 | AI24: ='Family spending workbook 1'!R45/100 -> 0.046932899 | AJ24: ='Family spending workbook 1'!S45/100 -> 0.041630192 | AK24: ='Family spending workbook 1'!T45/100 -> 0.037691418 | AL24: ='Family spending workbook 1'!U45/100 -> 0.03704995 | AM24: ='Family spending workbook 1'!V45/100 -> 0.032595608 | ... AO24: ='Family spending workbook 1'!X45/100 -> 0.025559063 | AR24: =HAVERA!D25/1000 -> 0.036 | AS24: ='Family spending workbook 1'!Y76/100 -> 0.0398612 | AT24: ='Family spending workbook 1'!O76/100 -> 0.026784808 | AU24: ='Family spending workbook 1'!P76/100 -> 0.026966063 | AV24: ='Family spending workbook 1'!Q76/100 -> 0.033473822 | AW24: ='Family spending workbook 1'!R76/100 -> 0.039060926 | AX24: ='Family spending workbook 1'!S76/100 -> 0.042117341 | AY24: ='Family spending workbook 1'!T76/100 -> 0.04489631 | AZ24: ='Family spending workbook 1'!U76/100 -> 0.049051951 | BA24: ='Family spending workbook 1'!V76/100 -> 0.044105874 | ... BC24: ='Family spending workbook 1'!X76/100 -> 0.034214148 | BF24: =1-P24-AD24-AR24 -> 0.822 | BG24: =1-Q24-AE24-AS24 -> 0.81797979 | BH24: =1-R24-AF24-AT24 -> 0.76768768 | BI24: =1-S24-AG24-AU24 -> 0.7402613 | BJ24: =1-T24-AH24-AV24 -> 0.77207304 | BK24: =1-U24-AI24-AW24 -> 0.78718899 | BL24: =1-V24-AJ24-AX24 -> 0.79671925 | BM24: =1-W24-AK24-AY24 -> 0.81123123 | ... BQ24: =1-AA24-AO24-BC24 -> 0.86615194
A25: 2008 | B25: =DataA!N42 -> 84.725 | C25: =DataA!O42 -> 79.225 | D25: =DataA!P42 -> 74.93333 | E25: =DataA!Q42 -> 97.42498 | F25: =$F$32*(1*B25/$B$32-P25*C25/$C$32-AD25*D25/$D$32-AR25*E25/$E$32)/(1-P25-AD25-AR25) -> 85.278271 | G25: =G24*(P25*C25/C24+AD25*D25/D24+AR25*E25/E24+BF25*F25/F24) -> 85.442411 | H25: =100*((G25/G24)-1) -> 3.737753 | I25: =100*((B25/B24)-1) -> 3.5969066 | P25: =HAVERA!B26/1000 -> 0.109 | Q25: ='Family spending workbook 1'!Y15/100 -> 0.10764331 | R25: ='Family spending workbook 1'!O15/100 -> 0.17176318 | S25: ='Family spending workbook 1'!P15/100 -> 0.165 | T25: ='Family spending workbook 1'!Q15/100 -> 0.14741346 | U25: ='Family spending workbook 1'!R15/100 -> 0.13238413 | V25: ='Family spending workbook 1'!S15/100 -> 0.12748092 | W25: ='Family spending workbook 1'!T15/100 -> 0.11345819 | X25: ='Family spending workbook 1'!U15/100 -> 0.10285075 | Y25: ='Family spending workbook 1'!V15/100 -> 0.10132651 | ... AA25: ='Family spending workbook 1'!X15/100 -> 0.075988133 | AD25: =HAVERA!C26/1000 -> 0.035 | AE25: ='Family spending workbook 1'!Y46/100 -> 0.040127389 | AF25: ='Family spending workbook 1'!O46/100 -> 0.083929733 | AG25: ='Family spending workbook 1'!P46/100 -> 0.0735 | AH25: ='Family spending workbook 1'!Q46/100 -> 0.060676779 | AI25: ='Family spending workbook 1'!R46/100 -> 0.052105423 | AJ25: ='Family spending workbook 1'!S46/100 -> 0.044783715 | AK25: ='Family spending workbook 1'!T46/100 -> 0.040940767 | AL25: ='Family spending workbook 1'!U46/100 -> 0.037078442 | AM25: ='Family spending workbook 1'!V46/100 -> 0.03356241 | ... AO25: ='Family spending workbook 1'!X46/100 -> 0.027466743 | AR25: =HAVERA!D26/1000 -> 0.038 | AS25: ='Family spending workbook 1'!Y77/100 -> 0.044585987 | AT25: ='Family spending workbook 1'!O77/100 -> 0.026024723 | AU25: ='Family spending workbook 1'!P77/100 -> 0.0285 | AV25: ='Family spending workbook 1'!Q77/100 -> 0.036172695 | AW25: ='Family spending workbook 1'!R77/100 -> 0.042714329 | AX25: ='Family spending workbook 1'!S77/100 -> 0.047328244 | AY25: ='Family spending workbook 1'!T77/100 -> 0.046385017 | AZ25: ='Family spending workbook 1'!U77/100 -> 0.048071548 | BA25: ='Family spending workbook 1'!V77/100 -> 0.048106121 | ... BC25: ='Family spending workbook 1'!X77/100 -> 0.042970619 | BF25: =1-P25-AD25-AR25 -> 0.818 | BG25: =1-Q25-AE25-AS25 -> 0.80764331 | BH25: =1-R25-AF25-AT25 -> 0.71828237 | BI25: =1-S25-AG25-AU25 -> 0.733 | BJ25: =1-T25-AH25-AV25 -> 0.75573707 | BK25: =1-U25-AI25-AW25 -> 0.77279612 | BL25: =1-V25-AJ25-AX25 -> 0.78040712 | BM25: =1-W25-AK25-AY25 -> 0.79921603 | ... BQ25: =1-AA25-AO25-BC25 -> 0.8535745
A26: 2009 | B26: =DataA!N43 -> 86.575 | C26: =DataA!O43 -> 83.325 | D26: =DataA!P43 -> 80.14167 | E26: =DataA!Q43 -> 89.79167 | F26: =$F$32*(1*B26/$B$32-P26*C26/$C$32-AD26*D26/$D$32-AR26*E26/$E$32)/(1-P26-AD26-AR26) -> 87.276845 | G26: =G25*(P26*C26/C25+AD26*D26/D25+AR26*E26/E25+BF26*F26/F25) -> 87.615692 | H26: =100*((G26/G25)-1) -> 2.5435621 | I26: =100*((B26/B25)-1) -> 2.183535 | P26: =HAVERA!B27/1000 -> 0.118 | Q26: ='Family spending workbook 1'!Y16/100 -> 0.11472527 | R26: ='Family spending workbook 1'!O16/100 -> 0.15918869 | S26: ='Family spending workbook 1'!P16/100 -> 0.16050538 | T26: ='Family spending workbook 1'!Q16/100 -> 0.14926968 | U26: ='Family spending workbook 1'!R16/100 -> 0.13155529 | V26: ='Family spending workbook 1'!S16/100 -> 0.13120291 | W26: ='Family spending workbook 1'!T16/100 -> 0.12042367 | X26: ='Family spending workbook 1'!U16/100 -> 0.11488511 | Y26: ='Family spending workbook 1'!V16/100 -> 0.11149346 | ... AA26: ='Family spending workbook 1'!X16/100 -> 0.082048181 | AD26: =HAVERA!C27/1000 -> 0.046 | AE26: ='Family spending workbook 1'!Y47/100 -> 0.046813187 | AF26: ='Family spending workbook 1'!O47/100 -> 0.085433313 | AG26: ='Family spending workbook 1'!P47/100 -> 0.076275152 | AH26: ='Family spending workbook 1'!Q47/100 -> 0.063769149 | AI26: ='Family spending workbook 1'!R47/100 -> 0.058435721 | AJ26: ='Family spending workbook 1'!S47/100 -> 0.051182125 | AK26: ='Family spending workbook 1'!T47/100 -> 0.048583928 | AL26: ='Family spending workbook 1'!U47/100 -> 0.046753247 | AM26: ='Family spending workbook 1'!V47/100 -> 0.043358568 | ... AO26: ='Family spending workbook 1'!X47/100 -> 0.029936498 | AR26: =HAVERA!D27/1000 -> 0.034 | AS26: ='Family spending workbook 1'!Y78/100 -> 0.042197802 | AT26: ='Family spending workbook 1'!O78/100 -> 0.028887523 | AU26: ='Family spending workbook 1'!P78/100 -> 0.02620496 | AV26: ='Family spending workbook 1'!Q78/100 -> 0.03526897 | AW26: ='Family spending workbook 1'!R78/100 -> 0.040155829 | AX26: ='Family spending workbook 1'!S78/100 -> 0.041829047 | AY26: ='Family spending workbook 1'!T78/100 -> 0.046511628 | AZ26: ='Family spending workbook 1'!U78/100 -> 0.045754246 | BA26: ='Family spending workbook 1'!V78/100 -> 0.051445286 | ... BC26: ='Family spending workbook 1'!X78/100 -> 0.035883479 | BF26: =1-P26-AD26-AR26 -> 0.802 | BG26: =1-Q26-AE26-AS26 -> 0.79626374 | BH26: =1-R26-AF26-AT26 -> 0.72649047 | BI26: =1-S26-AG26-AU26 -> 0.73701451 | BJ26: =1-T26-AH26-AV26 -> 0.7516922 | BK26: =1-U26-AI26-AW26 -> 0.76985316 | BL26: =1-V26-AJ26-AX26 -> 0.77578592 | BM26: =1-W26-AK26-AY26 -> 0.78448077 | ... BQ26: =1-AA26-AO26-BC26 -> 0.85213184
A27: 2010 | B27: =DataA!N44 -> 89.43333 | C27: =DataA!O44 -> 86.625 | D27: =DataA!P44 -> 77.90834 | E27: =DataA!Q44 -> 104.8167 | F27: =$F$32*(1*B27/$B$32-P27*C27/$C$32-AD27*D27/$D$32-AR27*E27/$E$32)/(1-P27-AD27-AR27) -> 89.690583 | G27: =G26*(P27*C27/C26+AD27*D27/D26+AR27*E27/E26+BF27*F27/F26) -> 90.424967 | H27: =100*((G27/G26)-1) -> 3.2063603 | I27: =100*((B27/B26)-1) -> 3.3015651 | P27: =HAVERA!B28/1000 -> 0.108 | Q27: ='Family spending workbook 1'!Y17/100 -> 0.11233108 | R27: ='Family spending workbook 1'!O17/100 -> 0.14655172 | S27: ='Family spending workbook 1'!P17/100 -> 0.16061453 | T27: ='Family spending workbook 1'!Q17/100 -> 0.14668133 | U27: ='Family spending workbook 1'!R17/100 -> 0.13385598 | V27: ='Family spending workbook 1'!S17/100 -> 0.12675 | W27: ='Family spending workbook 1'!T17/100 -> 0.11857018 | X27: ='Family spending workbook 1'!U17/100 -> 0.11462451 | Y27: ='Family spending workbook 1'!V17/100 -> 0.10358835 | ... AA27: ='Family spending workbook 1'!X17/100 -> 0.081885125 | AD27: =HAVERA!C28/1000 -> 0.047 | AE27: ='Family spending workbook 1'!Y48/100 -> 0.045185811 | AF27: ='Family spending workbook 1'!O48/100 -> 0.072737069 | AG27: ='Family spending workbook 1'!P48/100 -> 0.079608939 | AH27: ='Family spending workbook 1'!Q48/100 -> 0.068573524 | AI27: ='Family spending workbook 1'!R48/100 -> 0.055168409 | AJ27: ='Family spending workbook 1'!S48/100 -> 0.05175 | AK27: ='Family spending workbook 1'!T48/100 -> 0.047515257 | AL27: ='Family spending workbook 1'!U48/100 -> 0.04197252 | AM27: ='Family spending workbook 1'!V48/100 -> 0.03943805 | ... AO27: ='Family spending workbook 1'!X48/100 -> 0.030927835 | AR27: =HAVERA!D28/1000 -> 0.041 | AS27: ='Family spending workbook 1'!Y79/100 -> 0.045608108 | AT27: ='Family spending workbook 1'!O79/100 -> 0.030711207 | AU27: ='Family spending workbook 1'!P79/100 -> 0.036312849 | AV27: ='Family spending workbook 1'!Q79/100 -> 0.036670334 | AW27: ='Family spending workbook 1'!R79/100 -> 0.041521487 | AX27: ='Family spending workbook 1'!S79/100 -> 0.047 | AY27: ='Family spending workbook 1'!T79/100 -> 0.049476896 | AZ27: ='Family spending workbook 1'!U79/100 -> 0.050065876 | BA27: ='Family spending workbook 1'!V79/100 -> 0.051963439 | ... BC27: ='Family spending workbook 1'!X79/100 -> 0.041531664 | BF27: =1-P27-AD27-AR27 -> 0.804 | BG27: =1-Q27-AE27-AS27 -> 0.796875 | BH27: =1-R27-AF27-AT27 -> 0.75 | BI27: =1-S27-AG27-AU27 -> 0.72346369 | BJ27: =1-T27-AH27-AV27 -> 0.74807481 | BK27: =1-U27-AI27-AW27 -> 0.76945412 | BL27: =1-V27-AJ27-AX27 -> 0.7745 | BM27: =1-W27-AK27-AY27 -> 0.78443766 | ... BQ27: =1-AA27-AO27-BC27 -> 0.84565538
A28: 2011 | B28: =DataA!N45 -> 93.425 | C28: =DataA!O45 -> 92.10001 | D28: =DataA!P45 -> 85.66666 | E28: =DataA!Q45 -> 120.1917 | F28: =$F$32*(1*B28/$B$32-P28*C28/$C$32-AD28*D28/$D$32-AR28*E28/$E$32)/(1-P28-AD28-AR28) -> 92.593543 | G28: =G27*(P28*C28/C27+AD28*D28/D27+AR28*E28/E27+BF28*F28/F27) -> 94.392667 | H28: =100*((G28/G27)-1) -> 4.3878374 | I28: =100*((B28/B27)-1) -> 4.4632913 | P28: =HAVERA!B29/1000 -> 0.118 | Q28: ='Family spending workbook 1'!Y18/100 -> 0.11331679 | R28: ='Family spending workbook 1'!O18/100 -> 0.1648786 | S28: ='Family spending workbook 1'!P18/100 -> 0.15503876 | T28: ='Family spending workbook 1'!Q18/100 -> 0.14006849 | U28: ='Family spending workbook 1'!R18/100 -> 0.13803767 | V28: ='Family spending workbook 1'!S18/100 -> 0.13193439 | W28: ='Family spending workbook 1'!T18/100 -> 0.11544133 | X28: ='Family spending workbook 1'!U18/100 -> 0.11259755 | Y28: ='Family spending workbook 1'!V18/100 -> 0.108867 | ... AA28: ='Family spending workbook 1'!X18/100 -> 0.083943774 | AD28: =HAVERA!C29/1000 -> 0.044 | AE28: ='Family spending workbook 1'!Y49/100 -> 0.045698925 | AF28: ='Family spending workbook 1'!O49/100 -> 0.078486731 | AG28: ='Family spending workbook 1'!P49/100 -> 0.075695394 | AH28: ='Family spending workbook 1'!Q49/100 -> 0.062328767 | AI28: ='Family spending workbook 1'!R49/100 -> 0.057070565 | AJ28: ='Family spending workbook 1'!S49/100 -> 0.053545586 | AK28: ='Family spending workbook 1'!T49/100 -> 0.047819676 | AL28: ='Family spending workbook 1'!U49/100 -> 0.044221479 | AM28: ='Family spending workbook 1'!V49/100 -> 0.040394089 | ... AO28: ='Family spending workbook 1'!X49/100 -> 0.031379925 | AR28: =HAVERA!D29/1000 -> 0.043 | AS28: ='Family spending workbook 1'!Y80/100 -> 0.051488834 | AT28: ='Family spending workbook 1'!O80/100 -> 0.028232637 | AU28: ='Family spending workbook 1'!P80/100 -> 0.036023712 | AV28: ='Family spending workbook 1'!Q80/100 -> 0.040068493 | AW28: ='Family spending workbook 1'!R80/100 -> 0.048636491 | AX28: ='Family spending workbook 1'!S80/100 -> 0.051374819 | AY28: ='Family spending workbook 1'!T80/100 -> 0.054771435 | AZ28: ='Family spending workbook 1'!U80/100 -> 0.057413601 | BA28: ='Family spending workbook 1'!V80/100 -> 0.05862069 | ... BC28: ='Family spending workbook 1'!X80/100 -> 0.049000198 | BF28: =1-P28-AD28-AR28 -> 0.795 | BG28: =1-Q28-AE28-AS28 -> 0.78949545 | BH28: =1-R28-AF28-AT28 -> 0.72840203 | BI28: =1-S28-AG28-AU28 -> 0.73324213 | BJ28: =1-T28-AH28-AV28 -> 0.75753425 | BK28: =1-U28-AI28-AW28 -> 0.75625527 | BL28: =1-V28-AJ28-AX28 -> 0.7631452 | BM28: =1-W28-AK28-AY28 -> 0.78196756 | ... BQ28: =1-AA28-AO28-BC28 -> 0.8356761
A29: 2012 | B29: =DataA!N46 -> 96.04167 | C29: =DataA!O46 -> 95.8 | D29: =DataA!P46 -> 92.48334 | E29: =DataA!Q46 -> 122.5333 | F29: =$F$32*(1*B29/$B$32-P29*C29/$C$32-AD29*D29/$D$32-AR29*E29/$E$32)/(1-P29-AD29-AR29) -> 94.769082 | G29: =G28*(P29*C29/C28+AD29*D29/D28+AR29*E29/E28+BF29*F29/F28) -> 97.065791 | H29: =100*((G29/G28)-1) -> 2.8319188 | I29: =100*((B29/B28)-1) -> 2.8008242 | P29: =HAVERA!B30/1000 -> 0.112 | Q29: ='Family spending workbook 1'!Y19/100 -> 0.11615542 | R29: ='Family spending workbook 1'!O19/100 -> 0.15018125 | S29: ='Family spending workbook 1'!P19/100 -> 0.16435289 | T29: ='Family spending workbook 1'!Q19/100 -> 0.14996446 | U29: ='Family spending workbook 1'!R19/100 -> 0.13045852 | V29: ='Family spending workbook 1'!S19/100 -> 0.13161729 | W29: ='Family spending workbook 1'!T19/100 -> 0.125 | X29: ='Family spending workbook 1'!U19/100 -> 0.11723749 | Y29: ='Family spending workbook 1'!V19/100 -> 0.11552519 | ... AA29: ='Family spending workbook 1'!X19/100 -> 0.08563327 | AD29: =HAVERA!C30/1000 -> 0.056 | AE29: ='Family spending workbook 1'!Y50/100 -> 0.047443763 | AF29: ='Family spending workbook 1'!O50/100 -> 0.078197825 | AG29: ='Family spending workbook 1'!P50/100 -> 0.080609046 | AH29: ='Family spending workbook 1'!Q50/100 -> 0.064321251 | AI29: ='Family spending workbook 1'!R50/100 -> 0.060043668 | AJ29: ='Family spending workbook 1'!S50/100 -> 0.054395338 | AK29: ='Family spending workbook 1'!T50/100 -> 0.047933884 | AL29: ='Family spending workbook 1'!U50/100 -> 0.045916447 | AM29: ='Family spending workbook 1'!V50/100 -> 0.042428095 | ... AO29: ='Family spending workbook 1'!X50/100 -> 0.031852552 | AR29: =HAVERA!D30/1000 -> 0.046 | AS29: ='Family spending workbook 1'!Y81/100 -> 0.050511247 | AT29: ='Family spending workbook 1'!O81/100 -> 0.028482651 | AU29: ='Family spending workbook 1'!P81/100 -> 0.033587103 | AV29: ='Family spending workbook 1'!Q81/100 -> 0.042643923 | AW29: ='Family spending workbook 1'!R81/100 -> 0.047489083 | AX29: ='Family spending workbook 1'!S81/100 -> 0.050752793 | AY29: ='Family spending workbook 1'!T81/100 -> 0.056198347 | AZ29: ='Family spending workbook 1'!U81/100 -> 0.057207377 | BA29: ='Family spending workbook 1'!V81/100 -> 0.060543461 | ... BC29: ='Family spending workbook 1'!X81/100 -> 0.046219282 | BF29: =1-P29-AD29-AR29 -> 0.786 | BG29: =1-Q29-AE29-AS29 -> 0.78588957 | BH29: =1-R29-AF29-AT29 -> 0.74313827 | BI29: =1-S29-AG29-AU29 -> 0.72145096 | BJ29: =1-T29-AH29-AV29 -> 0.74307036 | BK29: =1-U29-AI29-AW29 -> 0.76200873 | BL29: =1-V29-AJ29-AX29 -> 0.76323458 | BM29: =1-W29-AK29-AY29 -> 0.77086777 | ... BQ29: =1-AA29-AO29-BC29 -> 0.8362949
A30: 2013 | B30: =DataA!N47 -> 98.50833 | C30: =DataA!O47 -> 100.1417 | D30: =DataA!P47 -> 99.12499 | E30: =DataA!Q47 -> 121.2 | F30: =$F$32*(1*B30/$B$32-P30*C30/$C$32-AD30*D30/$D$32-AR30*E30/$E$32)/(1-P30-AD30-AR30) -> 97.120512 | G30: =G29*(P30*C30/C29+AD30*D30/D29+AR30*E30/E29+BF30*F30/F29) -> 99.765624 | H30: =100*((G30/G29)-1) -> 2.7814463 | I30: =100*((B30/B29)-1) -> 2.5683227 | P30: =HAVERA!B31/1000 -> 0.106 | Q30: ='Family spending workbook 1'!Y20/100 -> 0.11366712 | R30: ='Family spending workbook 1'!O20/100 -> 0.15639328 | S30: ='Family spending workbook 1'!P20/100 -> 0.16790231 | T30: ='Family spending workbook 1'!Q20/100 -> 0.13512638 | U30: ='Family spending workbook 1'!R20/100 -> 0.12725824 | V30: ='Family spending workbook 1'!S20/100 -> 0.12604473 | W30: ='Family spending workbook 1'!T20/100 -> 0.11858476 | X30: ='Family spending workbook 1'!U20/100 -> 0.11606363 | Y30: ='Family spending workbook 1'!V20/100 -> 0.11337481 | ... AA30: ='Family spending workbook 1'!X20/100 -> 0.083281208 | AD30: =HAVERA!C31/1000 -> 0.048 | AE30: ='Family spending workbook 1'!Y51/100 -> 0.051227528 | AF30: ='Family spending workbook 1'!O51/100 -> 0.10392257 | AG30: ='Family spending workbook 1'!P51/100 -> 0.097252508 | AH30: ='Family spending workbook 1'!Q51/100 -> 0.072261828 | AI30: ='Family spending workbook 1'!R51/100 -> 0.066418704 | AJ30: ='Family spending workbook 1'!S51/100 -> 0.055793991 | AK30: ='Family spending workbook 1'!T51/100 -> 0.051710731 | AL30: ='Family spending workbook 1'!U51/100 -> 0.048243314 | AM30: ='Family spending workbook 1'!V51/100 -> 0.043856921 | ... AO30: ='Family spending workbook 1'!X51/100 -> 0.033240997 | AR30: =HAVERA!D31/1000 -> 0.04 | AS30: ='Family spending workbook 1'!Y82/100 -> 0.045428185 | AT30: ='Family spending workbook 1'!O82/100 -> 0.025471218 | AU30: ='Family spending workbook 1'!P82/100 -> 0.033144352 | AV30: ='Family spending workbook 1'!Q82/100 -> 0.042125729 | AW30: ='Family spending workbook 1'!R82/100 -> 0.043304995 | AX30: ='Family spending workbook 1'!S82/100 -> 0.044047888 | AY30: ='Family spending workbook 1'!T82/100 -> 0.049572317 | AZ30: ='Family spending workbook 1'!U82/100 -> 0.050690439 | BA30: ='Family spending workbook 1'!V82/100 -> 0.054276827 | ... BC30: ='Family spending workbook 1'!X82/100 -> 0.040478956 | BF30: =1-P30-AD30-AR30 -> 0.806 | BG30: =1-Q30-AE30-AS30 -> 0.78967717 | BH30: =1-R30-AF30-AT30 -> 0.71421294 | BI30: =1-S30-AG30-AU30 -> 0.70170083 | BJ30: =1-T30-AH30-AV30 -> 0.75048607 | BK30: =1-U30-AI30-AW30 -> 0.76301807 | BL30: =1-V30-AJ30-AX30 -> 0.7741134 | BM30: =1-W30-AK30-AY30 -> 0.78013219 | ... BQ30: =1-AA30-AO30-BC30 -> 0.84299884
A31: 2014 | B31: =DataA!N48 -> 99.95833 | C31: =DataA!O48 -> 101.275 | D31: =DataA!P48 -> 103.4417 | E31: =DataA!Q48 -> 115.1416 | F31: =$F$32*(1*B31/$B$32-P31*C31/$C$32-AD31*D31/$D$32-AR31*E31/$E$32)/(1-P31-AD31-AR31) -> 98.913861 | G31: =G30*(P31*C31/C30+AD31*D31/D30+AR31*E31/E30+BF31*F31/F30) -> 101.40153 | H31: =100*((G31/G30)-1) -> 1.6397502 | I31: =100*((B31/B30)-1) -> 1.4719567 | P31: =HAVERA!B32/1000 -> 0.112 | Q31: ='Family spending workbook 1'!Y21/100 -> 0.11067194 | R31: ='Family spending workbook 1'!O21/100 -> 0.15966387 | S31: ='Family spending workbook 1'!P21/100 -> 0.1498998 | T31: ='Family spending workbook 1'!Q21/100 -> 0.14236546 | U31: ='Family spending workbook 1'!R21/100 -> 0.13749001 | V31: ='Family spending workbook 1'!S21/100 -> 0.12789391 | W31: ='Family spending workbook 1'!T21/100 -> 0.11857555 | X31: ='Family spending workbook 1'!U21/100 -> 0.11171019 | Y31: ='Family spending workbook 1'!V21/100 -> 0.1013415 | ... AA31: ='Family spending workbook 1'!X21/100 -> 0.078726533 | AD31: =HAVERA!C32/1000 -> 0.045 | AE31: ='Family spending workbook 1'!Y52/100 -> 0.048560136 | AF31: ='Family spending workbook 1'!O52/100 -> 0.098214286 | AG31: ='Family spending workbook 1'!P52/100 -> 0.086973948 | AH31: ='Family spending workbook 1'!Q52/100 -> 0.069774718 | AI31: ='Family spending workbook 1'!R52/100 -> 0.062616573 | AJ31: ='Family spending workbook 1'!S52/100 -> 0.056866712 | AK31: ='Family spending workbook 1'!T52/100 -> 0.04773821 | AL31: ='Family spending workbook 1'!U52/100 -> 0.046166807 | AM31: ='Family spending workbook 1'!V52/100 -> 0.041557305 | ... AO31: ='Family spending workbook 1'!X52/100 -> 0.031490613 | AR31: =HAVERA!D32/1000 -> 0.035 | AS31: ='Family spending workbook 1'!Y83/100 -> 0.043290043 | AT31: ='Family spending workbook 1'!O83/100 -> 0.029936975 | AU31: ='Family spending workbook 1'!P83/100 -> 0.028056112 | AV31: ='Family spending workbook 1'!Q83/100 -> 0.041614518 | AW31: ='Family spending workbook 1'!R83/100 -> 0.045297096 | AX31: ='Family spending workbook 1'!S83/100 -> 0.051697011 | AY31: ='Family spending workbook 1'!T83/100 -> 0.047160731 | AZ31: ='Family spending workbook 1'!U83/100 -> 0.049031171 | BA31: ='Family spending workbook 1'!V83/100 -> 0.04855643 | ... BC31: ='Family spending workbook 1'!X83/100 -> 0.035037633 | BF31: =1-P31-AD31-AR31 -> 0.808 | BG31: =1-Q31-AE31-AS31 -> 0.79747788 | BH31: =1-R31-AF31-AT31 -> 0.71218487 | BI31: =1-S31-AG31-AU31 -> 0.73507014 | BJ31: =1-T31-AH31-AV31 -> 0.74624531 | BK31: =1-U31-AI31-AW31 -> 0.75459632 | BL31: =1-V31-AJ31-AX31 -> 0.76354237 | BM31: =1-W31-AK31-AY31 -> 0.78652551 | ... BQ31: =1-AA31-AO31-BC31 -> 0.85474522
A32: 2015 | B32: =DataA!N49 -> 100.0083 | C32: =DataA!O49 -> 99.99998 | D32: =DataA!P49 -> 100 | E32: =DataA!Q49 -> 100 | F32: 100 | G32: =G31*(P32*C32/C31+AD32*D32/D31+AR32*E32/E31+BF32*F32/F31) -> 101.57238 | H32: =100*((G32/G31)-1) -> 0.16848309 | I32: =100*((B32/B31)-1) -> 0.049990831 | P32: =HAVERA!B33/1000 -> 0.11 | Q32: ='Family spending workbook 1'!Y22/100 -> 0.1073927 | R32: ='Family spending workbook 1'!O22/100 -> 0.16333333 | S32: ='Family spending workbook 1'!P22/100 -> 0.14209115 | T32: ='Family spending workbook 1'!Q22/100 -> 0.14155844 | U32: ='Family spending workbook 1'!R22/100 -> 0.13290113 | V32: ='Family spending workbook 1'!S22/100 -> 0.11654054 | W32: ='Family spending workbook 1'!T22/100 -> 0.10497238 | X32: ='Family spending workbook 1'!U22/100 -> 0.11326861 | Y32: ='Family spending workbook 1'!V22/100 -> 0.10456331 | ... AA32: ='Family spending workbook 1'!X22/100 -> 0.078155254 | AD32: =HAVERA!C33/1000 -> 0.042 | AE32: ='Family spending workbook 1'!Y53/100 -> 0.044053696 | AF32: ='Family spending workbook 1'!O53/100 -> 0.096666667 | AG32: ='Family spending workbook 1'!P53/100 -> 0.077747989 | AH32: ='Family spending workbook 1'!Q53/100 -> 0.069155844 | AI32: ='Family spending workbook 1'!R53/100 -> 0.059157212 | AJ32: ='Family spending workbook 1'!S53/100 -> 0.048864865 | AK32: ='Family spending workbook 1'!T53/100 -> 0.04198895 | AL32: ='Family spending workbook 1'!U53/100 -> 0.040708568 | AM32: ='Family spending workbook 1'!V53/100 -> 0.037322454 | ... AO32: ='Family spending workbook 1'!X53/100 -> 0.028076043 | AR32: =HAVERA!D33/1000 -> 0.034 | AS32: ='Family spending workbook 1'!Y84/100 -> 0.036679902 | AT32: ='Family spending workbook 1'!O84/100 -> 0.022777778 | AU32: ='Family spending workbook 1'!P84/100 -> 0.027958637 | AV32: ='Family spending workbook 1'!Q84/100 -> 0.03474026 | AW32: ='Family spending workbook 1'!R84/100 -> 0.034575905 | AX32: ='Family spending workbook 1'!S84/100 -> 0.039135135 | AY32: ='Family spending workbook 1'!T84/100 -> 0.037937385 | AZ32: ='Family spending workbook 1'!U84/100 -> 0.039175609 | BA32: ='Family spending workbook 1'!V84/100 -> 0.043668782 | ... BC32: ='Family spending workbook 1'!X84/100 -> 0.033092765 | BF32: =1-P32-AD32-AR32 -> 0.814 | BG32: =1-Q32-AE32-AS32 -> 0.8118737 | BH32: =1-R32-AF32-AT32 -> 0.71722222 | BI32: =1-S32-AG32-AU32 -> 0.75220222 | BJ32: =1-T32-AH32-AV32 -> 0.75454545 | BK32: =1-U32-AI32-AW32 -> 0.77336575 | BL32: =1-V32-AJ32-AX32 -> 0.79545946 | BM32: =1-W32-AK32-AY32 -> 0.81510129 | ... BQ32: =1-AA32-AO32-BC32 -> 0.86067594
A33: 2016 | B33: =DataA!N50 -> 100.65 | C33: =DataA!O50 -> 98.725 | D33: =DataA!P50 -> 97.05 | E33: =DataA!Q50 -> 97.61666 | F33: =F32*(1*B33/B32-P33*C33/C32-AD33*D33/D32-AR33*E33/E32)/BF33 -> 101.14757 | G33: =G32*(P33*C33/C32+AD33*D33/D32+AR33*E33/E32+BF33*F33/F32) -> 102.22411 | H33: =100*((G33/G32)-1) -> 0.64164674 | I33: =100*((B33/B32)-1) -> 0.64164674 | P33: =HAVERA!B34/1000 -> 0.103 | Q33: ='Family spending workbook 1'!Y23/100 -> 0.10465536 | R33: ='Family spending workbook 1'!O23/100 -> 0.13754826 | S33: ='Family spending workbook 1'!P23/100 -> 0.14037736 | T33: ='Family spending workbook 1'!Q23/100 -> 0.13256228 | U33: ='Family spending workbook 1'!R23/100 -> 0.12258369 | V33: ='Family spending workbook 1'!S23/100 -> 0.11321873 | W33: ='Family spending workbook 1'!T23/100 -> 0.11024761 | X33: ='Family spending workbook 1'!U23/100 -> 0.10510806 | Y33: ='Family spending workbook 1'!V23/100 -> 0.10018526 | ... AA33: ='Family spending workbook 1'!X23/100 -> 0.076468481 | AD33: =HAVERA!C34/1000 -> 0.035 | AE33: ='Family spending workbook 1'!Y54/100 -> 0.040057741 | AF33: ='Family spending workbook 1'!O54/100 -> 0.085907336 | AG33: ='Family spending workbook 1'!P54/100 -> 0.07509434 | AH33: ='Family spending workbook 1'!Q54/100 -> 0.059608541 | AI33: ='Family spending workbook 1'!R54/100 -> 0.050212164 | AJ33: ='Family spending workbook 1'!S54/100 -> 0.04346967 | AK33: ='Family spending workbook 1'!T54/100 -> 0.040484367 | AL33: ='Family spending workbook 1'!U54/100 -> 0.035363458 | AM33: ='Family spending workbook 1'!V54/100 -> 0.034487673 | ... AO33: ='Family spending workbook 1'!X54/100 -> 0.025698424 | AR33: =HAVERA!D34/1000 -> 0.032 | AS33: ='Family spending workbook 1'!Y85/100 -> 0.037351137 | AT33: ='Family spending workbook 1'!O85/100 -> 0.026061776 | AU33: ='Family spending workbook 1'!P85/100 -> 0.030566038 | AV33: ='Family spending workbook 1'!Q85/100 -> 0.034104389 | AW33: ='Family spending workbook 1'!R85/100 -> 0.035832155 | AX33: ='Family spending workbook 1'!S85/100 -> 0.039913061 | AY33: ='Family spending workbook 1'!T85/100 -> 0.041026568 | AZ33: ='Family spending workbook 1'!U85/100 -> 0.040438769 | BA33: ='Family spending workbook 1'!V85/100 -> 0.043323358 | ... BC33: ='Family spending workbook 1'!X85/100 -> 0.032682665 | BF33: =1-P33-AD33-AR33 -> 0.83 | BG33: =1-Q33-AE33-AS33 -> 0.81793576 | BH33: =1-R33-AF33-AT33 -> 0.75048263 | BI33: =1-S33-AG33-AU33 -> 0.75396226 | BJ33: =1-T33-AH33-AV33 -> 0.77372479 | BK33: =1-U33-AI33-AW33 -> 0.79137199 | BL33: =1-V33-AJ33-AX33 -> 0.80339854 | BM33: =1-W33-AK33-AY33 -> 0.80824146 | ... BQ33: =1-AA33-AO33-BC33 -> 0.86515043
A34: 2017 | B34: =DataA!N51 -> 103.3584 | C34: =DataA!O51 -> 101.5333 | D34: =DataA!P51 -> 100.7 | E34: =DataA!Q51 -> 105.6 | F34: =F33*(1*B34/B33-P34*C34/C33-AD34*D34/D33-AR34*E34/E33)/BF34 -> 103.58583 | G34: =G33*(P34*C34/C33+AD34*D34/D33+AR34*E34/E33+BF34*F34/F33) -> 104.97487 | H34: =100*((G34/G33)-1) -> 2.6909091 | I34: =100*((B34/B33)-1) -> 2.6909091 | P34: =HAVERA!B35/1000 -> 0.10291667 | Q34: ='Family spending workbook 1'!Y24/100 -> 0.10595796 | R34: ='Family spending workbook 1'!O24/100 -> 0.14379699 | S34: ='Family spending workbook 1'!P24/100 -> 0.15077271 | T34: ='Family spending workbook 1'!Q24/100 -> 0.13568825 | U34: ='Family spending workbook 1'!R24/100 -> 0.12452741 | V34: ='Family spending workbook 1'!S24/100 -> 0.11638906 | W34: ='Family spending workbook 1'!T24/100 -> 0.10971192 | X34: ='Family spending workbook 1'!U24/100 -> 0.1042477 | Y34: ='Family spending workbook 1'!V24/100 -> 0.10278841 | ... AA34: ='Family spending workbook 1'!X24/100 -> 0.075295834 | AD34: =HAVERA!C35/1000 -> 0.033916667 | AE34: ='Family spending workbook 1'!Y55/100 -> 0.039256557 | AF34: ='Family spending workbook 1'!O55/100 -> 0.080357143 | AG34: ='Family spending workbook 1'!P55/100 -> 0.072747833 | AH34: ='Family spending workbook 1'!Q55/100 -> 0.058873003 | AI34: ='Family spending workbook 1'!R55/100 -> 0.051984877 | AJ34: ='Family spending workbook 1'!S55/100 -> 0.04503393 | AK34: ='Family spending workbook 1'!T55/100 -> 0.038985682 | AL34: ='Family spending workbook 1'!U55/100 -> 0.03469737 | AM34: ='Family spending workbook 1'!V55/100 -> 0.031984691 | ... AO34: ='Family spending workbook 1'!X55/100 -> 0.02544983 | AR34: =HAVERA!D35/1000 -> 0.032916667 | AS34: ='Family spending workbook 1'!Y86/100 -> 0.03734584 | AT34: ='Family spending workbook 1'!O86/100 -> 0.022556391 | AU34: ='Family spending workbook 1'!P86/100 -> 0.027892951 | AV34: ='Family spending workbook 1'!Q86/100 -> 0.035323802 | AW34: ='Family spending workbook 1'!R86/100 -> 0.038516068 | AX34: ='Family spending workbook 1'!S86/100 -> 0.038247995 | AY34: ='Family spending workbook 1'!T86/100 -> 0.039158185 | AZ34: ='Family spending workbook 1'!U86/100 -> 0.041232301 | BA34: ='Family spending workbook 1'!V86/100 -> 0.042372881 | ... BC34: ='Family spending workbook 1'!X86/100 -> 0.031852812 | BF34: =1-P34-AD34-AR34 -> 0.83025 | BG34: =1-Q34-AE34-AS34 -> 0.81743964 | BH34: =1-R34-AF34-AT34 -> 0.75328947 | BI34: =1-S34-AG34-AU34 -> 0.74858651 | BJ34: =1-T34-AH34-AV34 -> 0.77011494 | BK34: =1-U34-AI34-AW34 -> 0.78497164 | BL34: =1-V34-AJ34-AX34 -> 0.80032902 | BM34: =1-W34-AK34-AY34 -> 0.81214421 | ... BQ34: =1-AA34-AO34-BC34 -> 0.86740152
A35: 2018 | B35: =DataA!N52 -> 105.9167 | C35: =DataA!O52 -> 104.3083 | D35: =DataA!P52 -> 107.5333 | E35: =DataA!Q52 -> 113.0083 | F35: =F34*(1*B35/B34-P35*C35/C34-AD35*D35/D34-AR35*E35/E34)/BF35 -> 105.76107 | G35: =G34*(P35*C35/C34+AD35*D35/D34+AR35*E35/E34+BF35*F35/F34) -> 107.57318 | H35: =100*((G35/G34)-1) -> 2.4751738 | I35: =100*((B35/B34)-1) -> 2.4751738 | P35: =HAVERA!B36/1000 -> 0.101 | Q35: ='Family spending workbook 1'!Y25/100 -> 0.10456081 | R35: ='Family spending workbook 1'!O25/100 -> 0.13845504 | S35: ='Family spending workbook 1'!P25/100 -> 0.1409465 | T35: ='Family spending workbook 1'!Q25/100 -> 0.12800664 | U35: ='Family spending workbook 1'!R25/100 -> 0.11996316 | V35: ='Family spending workbook 1'!S25/100 -> 0.11033175 | W35: ='Family spending workbook 1'!T25/100 -> 0.11205433 | X35: ='Family spending workbook 1'!U25/100 -> 0.10406959 | Y35: ='Family spending workbook 1'!V25/100 -> 0.097554492 | ... AA35: ='Family spending workbook 1'!X25/100 -> 0.081776087 | AD35: =HAVERA!C36/1000 -> 0.034 | AE35: ='Family spending workbook 1'!Y56/100 -> 0.041554054 | AF35: ='Family spending workbook 1'!O56/100 -> 0.080624736 | AG35: ='Family spending workbook 1'!P56/100 -> 0.070644719 | AH35: ='Family spending workbook 1'!Q56/100 -> 0.059441526 | AI35: ='Family spending workbook 1'!R56/100 -> 0.054110062 | AJ35: ='Family spending workbook 1'!S56/100 -> 0.043412322 | AK35: ='Family spending workbook 1'!T56/100 -> 0.04057725 | AL35: ='Family spending workbook 1'!U56/100 -> 0.039608574 | AM35: ='Family spending workbook 1'!V56/100 -> 0.037214248 | ... AO35: ='Family spending workbook 1'!X56/100 -> 0.027865057 | AR35: =HAVERA!D36/1000 -> 0.030916667 | AS35: ='Family spending workbook 1'!Y87/100 -> 0.039189189 | AT35: ='Family spending workbook 1'!O87/100 -> 0.025327142 | AU35: ='Family spending workbook 1'!P87/100 -> 0.03223594 | AV35: ='Family spending workbook 1'!Q87/100 -> 0.038153166 | AW35: ='Family spending workbook 1'!R87/100 -> 0.038913194 | AX35: ='Family spending workbook 1'!S87/100 -> 0.041137441 | AY35: ='Family spending workbook 1'!T87/100 -> 0.04533107 | AZ35: ='Family spending workbook 1'!U87/100 -> 0.042715129 | BA35: ='Family spending workbook 1'!V87/100 -> 0.043195109 | ... BC35: ='Family spending workbook 1'!X87/100 -> 0.03290888 | BF35: =1-P35-AD35-AR35 -> 0.83408333 | BG35: =1-Q35-AE35-AS35 -> 0.81469595 | BH35: =1-R35-AF35-AT35 -> 0.75559308 | BI35: =1-S35-AG35-AU35 -> 0.75617284 | BJ35: =1-T35-AH35-AV35 -> 0.77439867 | BK35: =1-U35-AI35-AW35 -> 0.78701359 | BL35: =1-V35-AJ35-AX35 -> 0.80511848 | BM35: =1-W35-AK35-AY35 -> 0.80203735 | ... BQ35: =1-AA35-AO35-BC35 -> 0.85744998
A36: 2019 | B36: =DataA!N53 -> 107.8 | C36: =DataA!O53 -> 106.3667 | D36: =DataA!P53 -> 111.6083 | E36: =DataA!Q53 -> 113.4333 | F36: =F35*(1*B36/B35-P36*C36/C35-AD36*D36/D35-AR36*E36/E35)/BF36 -> 107.59097 | G36: =G35*(P36*C36/C35+AD36*D36/D35+AR36*E36/E35+BF36*F36/F35) -> 109.48593 | H36: =100*((G36/G35)-1) -> 1.7780954 | I36: =100*((B36/B35)-1) -> 1.7780954 | P36: =HAVERA!B37/1000 -> 0.1 | Q36: ='Family spending workbook 1'!Y26/100 -> 0.10835176 | R36: ='Family spending workbook 1'!O26/100 -> 0.1404655 | S36: ='Family spending workbook 1'!P26/100 -> 0.14385232 | T36: ='Family spending workbook 1'!Q26/100 -> 0.13353524 | U36: ='Family spending workbook 1'!R26/100 -> 0.12454128 | V36: ='Family spending workbook 1'!S26/100 -> 0.12017084 | W36: ='Family spending workbook 1'!T26/100 -> 0.11023622 | X36: ='Family spending workbook 1'!U26/100 -> 0.11375865 | Y36: ='Family spending workbook 1'!V26/100 -> 0.10093188 | ... AA36: ='Family spending workbook 1'!X26/100 -> 0.082284285 | AD36: =HAVERA!C37/1000 -> 0.031166667 | AE36: ='Family spending workbook 1'!Y57/100 -> 0.041673754 | AF36: ='Family spending workbook 1'!O57/100 -> 0.077174357 | AG36: ='Family spending workbook 1'!P57/100 -> 0.074538488 | AH36: ='Family spending workbook 1'!Q57/100 -> 0.060848018 | AI36: ='Family spending workbook 1'!R57/100 -> 0.055275229 | AJ36: ='Family spending workbook 1'!S57/100 -> 0.044651524 | AK36: ='Family spending workbook 1'!T57/100 -> 0.04022595 | AL36: ='Family spending workbook 1'!U57/100 -> 0.040891622 | AM36: ='Family spending workbook 1'!V57/100 -> 0.034125213 | ... AO36: ='Family spending workbook 1'!X57/100 -> 0.026677782 | AR36: =HAVERA!D37/1000 -> 0.03 | AS36: ='Family spending workbook 1'!Y88/100 -> 0.037931621 | AT36: ='Family spending workbook 1'!O88/100 -> 0.025316456 | AU36: ='Family spending workbook 1'!P88/100 -> 0.032044584 | AV36: ='Family spending workbook 1'!Q88/100 -> 0.03496696 | AW36: ='Family spending workbook 1'!R88/100 -> 0.040366972 | AX36: ='Family spending workbook 1'!S88/100 -> 0.039798097 | AY36: ='Family spending workbook 1'!T88/100 -> 0.040054776 | AZ36: ='Family spending workbook 1'!U88/100 -> 0.041506533 | BA36: ='Family spending workbook 1'!V88/100 -> 0.04646279 | ... BC36: ='Family spending workbook 1'!X88/100 -> 0.030846186 | BF36: =1-P36-AD36-AR36 -> 0.83883333 | BG36: =1-Q36-AE36-AS36 -> 0.81204286 | BH36: =1-R36-AF36-AT36 -> 0.75704369 | BI36: =1-S36-AG36-AU36 -> 0.74956461 | BJ36: =1-T36-AH36-AV36 -> 0.77064978 | BK36: =1-U36-AI36-AW36 -> 0.77981651 | BL36: =1-V36-AJ36-AX36 -> 0.79537954 | BM36: =1-W36-AK36-AY36 -> 0.80948305 | ... BQ36: =1-AA36-AO36-BC36 -> 0.86019175
A37: 2020 | B37: =DataA!N54 -> 108.75 | C37: =DataA!O54 -> 107.5083 | D37: =DataA!P54 -> 106.45 | E37: =DataA!Q54 -> 103.575 | F37: =F36*(1*B37/B36-P37*C37/C36-AD37*D37/D36-AR37*E37/E36)/BF37 -> 109.12891 | G37: =G36*(P37*C37/C36+AD37*D37/D36+AR37*E37/E36+BF37*F37/F36) -> 110.45079 | H37: =100*((G37/G36)-1) -> 0.8812616 | I37: =100*((B37/B36)-1) -> 0.8812616 | P37: =HAVERA!B38/1000 -> 0.099 | Q37: ='Family spending workbook 1'!Y27/100 -> 0.14371755 | R37: ='Family spending workbook 1'!O27/100 -> 0.18118812 | S37: ='Family spending workbook 1'!P27/100 -> 0.17045908 | T37: ='Family spending workbook 1'!Q27/100 -> 0.15932793 | U37: ='Family spending workbook 1'!R27/100 -> 0.16891698 | V37: ='Family spending workbook 1'!S27/100 -> 0.14762014 | W37: ='Family spending workbook 1'!T27/100 -> 0.14471243 | X37: ='Family spending workbook 1'!U27/100 -> 0.14796117 | Y37: ='Family spending workbook 1'!V27/100 -> 0.13862852 | ... AA37: ='Family spending workbook 1'!X27/100 -> 0.11919686 | AD37: =HAVERA!C38/1000 -> 0.032916667 | AE37: ='Family spending workbook 1'!Y58/100 -> 0.048182762 | AF37: ='Family spending workbook 1'!O58/100 -> 0.083663366 | AG37: ='Family spending workbook 1'!P58/100 -> 0.077045908 | AH37: ='Family spending workbook 1'!Q58/100 -> 0.063151796 | AI37: ='Family spending workbook 1'!R58/100 -> 0.063774777 | AJ37: ='Family spending workbook 1'!S58/100 -> 0.053345597 | AK37: ='Family spending workbook 1'!T58/100 -> 0.048031334 | AL37: ='Family spending workbook 1'!U58/100 -> 0.046796117 | AM37: ='Family spending workbook 1'!V58/100 -> 0.03963164 | ... AO37: ='Family spending workbook 1'!X58/100 -> 0.033570594 | AR37: =HAVERA!D38/1000 -> 0.031 | AS37: ='Family spending workbook 1'!Y89/100 -> 0.023468328 | AT37: ='Family spending workbook 1'!O89/100 -> 0.015346535 | AU37: ='Family spending workbook 1'!P89/100 -> 0.021556886 | AV37: ='Family spending workbook 1'!Q89/100 -> 0.023754345 | AW37: ='Family spending workbook 1'!R89/100 -> 0.024992818 | AX37: ='Family spending workbook 1'!S89/100 -> 0.024143481 | AY37: ='Family spending workbook 1'!T89/100 -> 0.02762317 | AZ37: ='Family spending workbook 1'!U89/100 -> 0.026990291 | BA37: ='Family spending workbook 1'!V89/100 -> 0.024995889 | ... BC37: ='Family spending workbook 1'!X89/100 -> 0.019334962 | BF37: =1-P37-AD37-AR37 -> 0.83708333 | BG37: =1-Q37-AE37-AS37 -> 0.78463136 | BH37: =1-R37-AF37-AT37 -> 0.71980198 | BI37: =1-S37-AG37-AU37 -> 0.73093812 | BJ37: =1-T37-AH37-AV37 -> 0.75376593 | BK37: =1-U37-AI37-AW37 -> 0.74231543 | BL37: =1-V37-AJ37-AX37 -> 0.77489078 | BM37: =1-W37-AK37-AY37 -> 0.77963307 | ... BQ37: =1-AA37-AO37-BC37 -> 0.82789759
A38: 2021 | B38: =DataA!N55 -> 111.5583 | C38: =DataA!O55 -> 108.525 | D38: =DataA!P55 -> 111.4583 | E38: =DataA!Q55 -> 118.1 | F38: =F37*(1*B38/B37-P38*C38/C37-AD38*D38/D37-AR38*E38/E37)/BF38 -> 111.69412 | G38: =G37*(P38*C38/C37+AD38*D38/D37+AR38*E38/E37+BF38*F38/F37) -> 113.30301 | H38: =100*((G38/G37)-1) -> 2.5823448 | I38: =100*((B38/B37)-1) -> 2.5823448 | P38: =HAVERA!B39/1000 -> 0.114 | Q38: ='Family spending workbook 1'!Y28/100 -> 0.11762481 | R38: ='Family spending workbook 1'!O28/100 -> 0.14007937 | S38: ='Family spending workbook 1'!P28/100 -> 0.14950635 | T38: ='Family spending workbook 1'!Q28/100 -> 0.13701373 | U38: ='Family spending workbook 1'!R28/100 -> 0.12642011 | V38: ='Family spending workbook 1'!S28/100 -> 0.12351738 | W38: ='Family spending workbook 1'!T28/100 -> 0.13023165 | X38: ='Family spending workbook 1'!U28/100 -> 0.12040602 | Y38: ='Family spending workbook 1'!V28/100 -> 0.11238844 | ... AA38: ='Family spending workbook 1'!X28/100 -> 0.090655231 | AD38: =HAVERA!C39/1000 -> 0.033 | AE38: ='Family spending workbook 1'!Y59/100 -> 0.048600605 | AF38: ='Family spending workbook 1'!O59/100 -> 0.079365079 | AG38: ='Family spending workbook 1'!P59/100 -> 0.072990127 | AH38: ='Family spending workbook 1'!Q59/100 -> 0.063787185 | AI38: ='Family spending workbook 1'!R59/100 -> 0.058979937 | AJ38: ='Family spending workbook 1'!S59/100 -> 0.052556237 | AK38: ='Family spending workbook 1'!T59/100 -> 0.050613198 | AL38: ='Family spending workbook 1'!U59/100 -> 0.044452223 | AM38: ='Family spending workbook 1'!V59/100 -> 0.042807442 | ... AO38: ='Family spending workbook 1'!X59/100 -> 0.034806024 | AR38: =HAVERA!D39/1000 -> 0.026916667 | AS38: ='Family spending workbook 1'!Y90/100 -> 0.035741301 | AT38: ='Family spending workbook 1'!O90/100 -> 0.028174603 | AU38: ='Family spending workbook 1'!P90/100 -> 0.029266573 | AV38: ='Family spending workbook 1'!Q90/100 -> 0.03375286 | AW38: ='Family spending workbook 1'!R90/100 -> 0.035049553 | AX38: ='Family spending workbook 1'!S90/100 -> 0.038241309 | AY38: ='Family spending workbook 1'!T90/100 -> 0.040879891 | AZ38: ='Family spending workbook 1'!U90/100 -> 0.039026951 | BA38: ='Family spending workbook 1'!V90/100 -> 0.03872334 | ... BC38: ='Family spending workbook 1'!X90/100 -> 0.031215718 | BF38: =1-P38-AD38-AR38 -> 0.82608333 | BG38: =1-Q38-AE38-AS38 -> 0.79803328 | BH38: =1-R38-AF38-AT38 -> 0.75238095 | BI38: =1-S38-AG38-AU38 -> 0.74823695 | BJ38: =1-T38-AH38-AV38 -> 0.76544622 | BK38: =1-U38-AI38-AW38 -> 0.7795504 | BL38: =1-V38-AJ38-AX38 -> 0.78568507 | BM38: =1-W38-AK38-AY38 -> 0.77827526 | ... BQ38: =1-AA38-AO38-BC38 -> 0.84332303
A39: 2022 | B39: =DataA!N56 -> 121.6583 | C39: =DataA!O56 -> 118.2917 | D39: =DataA!P56 -> 183.6417 | E39: =DataA!Q56 -> 150.9167 | F39: =F38*(1*B39/B38-P39*C39/C38-AD39*D39/D38-AR39*E39/E38)/BF39 -> 118.27958 | G39: =G38*(P39*C39/C38+AD39*D39/D38+AR39*E39/E38+BF39*F39/F38) -> 123.56097 | H39: =100*((G39/G38)-1) -> 9.0535621 | I39: =100*((B39/B38)-1) -> 9.0535621 | P39: =HAVERA!B40/1000 -> 0.11591667 | Q39: ='Family spending workbook 1'!Y29/100 -> 0.11185485 | R39: ='Family spending workbook 1'!O29/100 -> 0.13516609 | S39: ='Family spending workbook 1'!P29/100 -> 0.14254248 | T39: ='Family spending workbook 1'!Q29/100 -> 0.12419594 | U39: ='Family spending workbook 1'!R29/100 -> 0.12376662 | V39: ='Family spending workbook 1'!S29/100 -> 0.12595795 | W39: ='Family spending workbook 1'!T29/100 -> 0.1220698 | X39: ='Family spending workbook 1'!U29/100 -> 0.11061947 | Y39: ='Family spending workbook 1'!V29/100 -> 0.10634091 | ... AA39: ='Family spending workbook 1'!X29/100 -> 0.086335826 | AD39: =HAVERA!C40/1000 -> 0.036 | AE39: ='Family spending workbook 1'!Y60/100 -> 0.065351418 | AF39: ='Family spending workbook 1'!O60/100 -> 0.11149294 | AG39: ='Family spending workbook 1'!P60/100 -> 0.09314034 | AH39: ='Family spending workbook 1'!Q60/100 -> 0.078921326 | AI39: ='Family spending workbook 1'!R60/100 -> 0.075933076 | AJ39: ='Family spending workbook 1'!S60/100 -> 0.070544311 | AK39: ='Family spending workbook 1'!T60/100 -> 0.062858135 | AL39: ='Family spending workbook 1'!U60/100 -> 0.059816454 | AM39: ='Family spending workbook 1'!V60/100 -> 0.061290778 | ... AO39: ='Family spending workbook 1'!X60/100 -> 0.049140526 | AR39: =HAVERA!D40/1000 -> 0.031 | AS39: ='Family spending workbook 1'!Y91/100 -> 0.037167518 | AT39: ='Family spending workbook 1'!O91/100 -> 0.024054983 | AU39: ='Family spending workbook 1'!P91/100 -> 0.032410321 | AV39: ='Family spending workbook 1'!Q91/100 -> 0.039584364 | AW39: ='Family spending workbook 1'!R91/100 -> 0.034963535 | AX39: ='Family spending workbook 1'!S91/100 -> 0.039496954 | AY39: ='Family spending workbook 1'!T91/100 -> 0.038722 | AZ39: ='Family spending workbook 1'!U91/100 -> 0.042772861 | BA39: ='Family spending workbook 1'!V91/100 -> 0.042084451 | ... BC39: ='Family spending workbook 1'!X91/100 -> 0.032048169 | BF39: =1-P39-AD39-AR39 -> 0.81708333 | BG39: =1-Q39-AE39-AS39 -> 0.78562621 | BH39: =1-R39-AF39-AT39 -> 0.72928599 | BI39: =1-S39-AG39-AU39 -> 0.73190686 | BJ39: =1-T39-AH39-AV39 -> 0.75729837 | BK39: =1-U39-AI39-AW39 -> 0.76533677 | BL39: =1-V39-AJ39-AX39 -> 0.76400079 | BM39: =1-W39-AK39-AY39 -> 0.77635006 | ... BQ39: =1-AA39-AO39-BC39 -> 0.83247548
A40: 2023 | B40: =DataA!N57 -> 130.5417 | C40: =DataA!O57 -> 133.5667 | D40: =DataA!P57 -> 211.9667 | E40: =DataA!Q57 -> 135.0417 | F40: =F39*(1*B40/B39-P40*C40/C39-AD40*D40/D39-AR40*E40/E39)/BF40 -> 126.16311 | G40: =G39*(P40*C40/C39+AD40*D40/D39+AR40*E40/E39+BF40*F40/F39) -> 132.5833 | H40: =100*((G40/G39)-1) -> 7.3019268 | I40: =100*((B40/B39)-1) -> 7.3019268 | P40: =HAVERA!B41/1000 -> 0.11883333 | Q40: ='Family spending workbook 1'!Y30/100 -> 0.11310765 | R40: ='Family spending workbook 1'!O30/100 -> 0.13340336 | S40: ='Family spending workbook 1'!P30/100 -> 0.15145814 | T40: ='Family spending workbook 1'!Q30/100 -> 0.13396005 | U40: ='Family spending workbook 1'!R30/100 -> 0.12662075 | V40: ='Family spending workbook 1'!S30/100 -> 0.1187262 | W40: ='Family spending workbook 1'!T30/100 -> 0.11725045 | X40: ='Family spending workbook 1'!U30/100 -> 0.10983818 | Y40: ='Family spending workbook 1'!V30/100 -> 0.11538962 | ... AA40: ='Family spending workbook 1'!X30/100 -> 0.085923529 | AD40: =HAVERA!C41/1000 -> 0.048916667 | AE40: ='Family spending workbook 1'!Y61/100 -> 0.064976737 | AF40: ='Family spending workbook 1'!O61/100 -> 0.10889356 | AG40: ='Family spending workbook 1'!P61/100 -> 0.10034494 | AH40: ='Family spending workbook 1'!Q61/100 -> 0.085076381 | AI40: ='Family spending workbook 1'!R61/100 -> 0.07678282 | AJ40: ='Family spending workbook 1'!S61/100 -> 0.07113188 | AK40: ='Family spending workbook 1'!T61/100 -> 0.063311955 | AL40: ='Family spending workbook 1'!U61/100 -> 0.060718889 | AM40: ='Family spending workbook 1'!V61/100 -> 0.056979316 | ... AO40: ='Family spending workbook 1'!X61/100 -> 0.046666099 | AR40: =HAVERA!D41/1000 -> 0.031083333 | AS40: ='Family spending workbook 1'!Y92/100 -> 0.031766405 | AT40: ='Family spending workbook 1'!O92/100 -> 0.025910364 | AU40: ='Family spending workbook 1'!P92/100 -> 0.026967701 | AV40: ='Family spending workbook 1'!Q92/100 -> 0.029377203 | AW40: ='Family spending workbook 1'!R92/100 -> 0.036061588 | AX40: ='Family spending workbook 1'!S92/100 -> 0.034440983 | AY40: ='Family spending workbook 1'!T92/100 -> 0.033711561 | AZ40: ='Family spending workbook 1'!U92/100 -> 0.034512387 | BA40: ='Family spending workbook 1'!V92/100 -> 0.034473787 | ... BC40: ='Family spending workbook 1'!X92/100 -> 0.026313548 | BF40: =1-P40-AD40-AR40 -> 0.80116667 | BG40: =1-Q40-AE40-AS40 -> 0.79014921 | BH40: =1-R40-AF40-AT40 -> 0.73179272 | BI40: =1-S40-AG40-AU40 -> 0.72122923 | BJ40: =1-T40-AH40-AV40 -> 0.75158637 | BK40: =1-U40-AI40-AW40 -> 0.76053485 | BL40: =1-V40-AJ40-AX40 -> 0.77570093 | BM40: =1-W40-AK40-AY40 -> 0.78572603 | ... BQ40: =1-AA40-AO40-BC40 -> 0.84109682
A41: 2024 | B41: =DataA!N58 -> 133.8583 | C41: =DataA!O58 -> 138.875 | D41: =DataA!P58 -> 172.2417 | E41: =DataA!Q58 -> 128.5167 | F41: =F40*(1*B41/B40-P41*C41/C40-AD41*D41/D40-AR41*E41/E40)/BF41 -> 130.81076 | G41: =G40*(P41*C41/C40+AD41*D41/D40+AR41*E41/E40+BF41*F41/F40) -> 135.95177 | H41: =100*((G41/G40)-1) -> 2.5406441 | I41: =100*((B41/B40)-1) -> 2.5406441 | P41: =HAVERA!B42/1000 -> 0.11312657 | Q41: =Q40 -> 0.11310765 | R41: =R40 -> 0.13340336 | S41: =S40 -> 0.15145814 | T41: =T40 -> 0.13396005 | U41: =U40 -> 0.12662075 | V41: =V40 -> 0.1187262 | W41: =W40 -> 0.11725045 | X41: =X40 -> 0.10983818 | ... AA41: =AA40 -> 0.085923529 | AD41: =HAVERA!C42/1000 -> 0.040709867 | AE41: =AE40 -> 0.064976737 | AF41: =AF40 -> 0.10889356 | AG41: =AG40 -> 0.10034494 | AH41: =AH40 -> 0.085076381 | AI41: =AI40 -> 0.07678282 | AJ41: =AJ40 -> 0.07113188 | AK41: =AK40 -> 0.063311955 | AL41: =AL40 -> 0.060718889 | ... AO41: =AO40 -> 0.046666099 | AR41: =HAVERA!D42/1000 -> 0.030900175 | AS41: =AS40 -> 0.031766405 | AT41: =AT40 -> 0.025910364 | AU41: =AU40 -> 0.026967701 | AV41: =AV40 -> 0.029377203 | AW41: =AW40 -> 0.036061588 | AX41: =AX40 -> 0.034440983 | AY41: =AY40 -> 0.033711561 | AZ41: =AZ40 -> 0.034512387 | ... BC41: =BC40 -> 0.026313548 | BF41: =1-P41-AD41-AR41 -> 0.81526339 | BG41: =BG40 -> 0.79014921 | BH41: =BH40 -> 0.73179272 | BI41: =BI40 -> 0.72122923 | BJ41: =BJ40 -> 0.75158637 | BK41: =BK40 -> 0.76053485 | BL41: =BL40 -> 0.77570093 | BM41: =BM40 -> 0.78572603 | BN41: =BN40 -> 0.79493055 | ... BQ41: =BQ40 -> 0.84109682
A42: 2025 | B42: =DataA!N59 -> 138.3667 | C42: =DataA!O59 -> 145.1667 | D42: =DataA!P59 -> 174.9167 | E42: =DataA!Q59 -> 123.1083 | F42: =F41*(1*B42/B41-P42*C42/C41-AD42*D42/D41-AR42*E42/E41)/BF42 -> 135.4417 | G42: =G41*(P42*C42/C41+AD42*D42/D41+AR42*E42/E41+BF42*F42/F41) -> 140.53068 | H42: =100*((G42/G41)-1) -> 3.3680392 | I42: =100*((B42/B41)-1) -> 3.3680392 | P42: =HAVERA!B43/1000 -> 0.11247973 | Q42: =Q41 -> 0.11310765 | R42: =R41 -> 0.13340336 | S42: =S41 -> 0.15145814 | T42: =T41 -> 0.13396005 | U42: =U41 -> 0.12662075 | V42: =V41 -> 0.1187262 | W42: =W41 -> 0.11725045 | X42: =X41 -> 0.10983818 | ... AA42: =AA41 -> 0.085923529 | AD42: =HAVERA!C43/1000 -> 0.033621117 | AE42: =AE41 -> 0.064976737 | AF42: =AF41 -> 0.10889356 | AG42: =AG41 -> 0.10034494 | AH42: =AH41 -> 0.085076381 | AI42: =AI41 -> 0.07678282 | AJ42: =AJ41 -> 0.07113188 | AK42: =AK41 -> 0.063311955 | AL42: =AL41 -> 0.060718889 | ... AO42: =AO41 -> 0.046666099 | AR42: =HAVERA!D43/1000 -> 0.027968983 | AS42: =AS41 -> 0.031766405 | AT42: =AT41 -> 0.025910364 | AU42: =AU41 -> 0.026967701 | AV42: =AV41 -> 0.029377203 | AW42: =AW41 -> 0.036061588 | AX42: =AX41 -> 0.034440983 | AY42: =AY41 -> 0.033711561 | AZ42: =AZ41 -> 0.034512387 | ... BC42: =BC41 -> 0.026313548 | BF42: =1-P42-AD42-AR42 -> 0.82593017 | BG42: =BG41 -> 0.79014921 | BH42: =BH41 -> 0.73179272 | BI42: =BI41 -> 0.72122923 | BJ42: =BJ41 -> 0.75158637 | BK42: =BK41 -> 0.76053485 | BL42: =BL41 -> 0.77570093 | BM42: =BM41 -> 0.78572603 | BN42: =BN41 -> 0.79493055 | ... BQ42: =BQ41 -> 0.84109682
A43: 2026 | B43: =DataA!N60 -> 143.8379 | C43: =DataA!O60 -> 150.3771 | D43: =DataA!P60 -> 184.185 | E43: =DataA!Q60 -> 136.9272 | F43: =F42*(1*B43/B42-P43*C43/C42-AD43*D43/D42-AR43*E43/E42)/BF43 -> 140.47986 | G43: =G42*(P43*C43/C42+AD43*D43/D42+AR43*E43/E42+BF43*F43/F42) -> 146.08745 | H43: =100*((G43/G42)-1) -> 3.9541306 | I43: =100*((B43/B42)-1) -> 3.9541306 | P43: =HAVERA!B44/1000 -> 0.10956861 | Q43: =Q42 -> 0.11310765 | R43: =R42 -> 0.13340336 | S43: =S42 -> 0.15145814 | T43: =T42 -> 0.13396005 | U43: =U42 -> 0.12662075 | V43: =V42 -> 0.1187262 | W43: =W42 -> 0.11725045 | X43: =X42 -> 0.10983818 | ... AA43: =AA42 -> 0.085923529 | AD43: =HAVERA!C44/1000 -> 0.0319407 | AE43: =AE42 -> 0.064976737 | AF43: =AF42 -> 0.10889356 | AG43: =AG42 -> 0.10034494 | AH43: =AH42 -> 0.085076381 | AI43: =AI42 -> 0.07678282 | AJ43: =AJ42 -> 0.07113188 | AK43: =AK42 -> 0.063311955 | AL43: =AL42 -> 0.060718889 | ... AO43: =AO42 -> 0.046666099 | AR43: =HAVERA!D44/1000 -> 0.026408625 | AS43: =AS42 -> 0.031766405 | AT43: =AT42 -> 0.025910364 | AU43: =AU42 -> 0.026967701 | AV43: =AV42 -> 0.029377203 | AW43: =AW42 -> 0.036061588 | AX43: =AX42 -> 0.034440983 | AY43: =AY42 -> 0.033711561 | AZ43: =AZ42 -> 0.034512387 | ... BC43: =BC42 -> 0.026313548 | BF43: =1-P43-AD43-AR43 -> 0.83208207 | BG43: =BG42 -> 0.79014921 | BH43: =BH42 -> 0.73179272 | BI43: =BI42 -> 0.72122923 | BJ43: =BJ42 -> 0.75158637 | BK43: =BK42 -> 0.76053485 | BL43: =BL42 -> 0.77570093 | BM43: =BM42 -> 0.78572603 | BN43: =BN42 -> 0.79493055 | ... BQ43: =BQ42 -> 0.84109682
A45: CPI by decile | O45: Constraint
B46: Total | C46: 0-10 | D46: 11-20 | E46: 21-30 | F46: 31-40 | G46: 41-50 | H46: 51-60 | I46: 61-70 | J46: 71-80 | K46: 81-90 | L46: 91-100 | M46: CPI | P46: Total | Q46: 0-10 | R46: 11-20 | S46: 21-30 | T46: 31-40 | U46: 41-50 | V46: 51-60 | W46: 61-70 | X46: 71-80 | Y46: 81-90 | Z46: 91-100 | AA46: CPI | AC46: HCI
A47: 1987 | O47: 1987
A48: 1988 | O48: 1988
A49: 1989 | O49: 1989
A50: 1990 | O50: 1990
A51: 1991 | O51: 1991
A52: 1992 | O52: 1992
A53: 1993 | O53: 1993
A54: 1994 | O54: 1994
A55: 1995 | O55: 1995
A56: 1996 | B56: =B57*(Q13*$C13/$C14+AE13*$D13/$D14+AS13*$E13/$E14+BG13*$F13/$F14) -> 70.020396 | C56: =C57*(R13*$C13/$C14+AF13*$D13/$D14+AT13*$E13/$E14+BH13*$F13/$F14) -> 69.925063 | D56: =D57*(S13*$C13/$C14+AG13*$D13/$D14+AU13*$E13/$E14+BI13*$F13/$F14) -> 69.924488 | E56: =E57*(T13*$C13/$C14+AH13*$D13/$D14+AV13*$E13/$E14+BJ13*$F13/$F14) -> 69.854647 | F56: =F57*(U13*$C13/$C14+AI13*$D13/$D14+AW13*$E13/$E14+BK13*$F13/$F14) -> 69.887627 | G56: =G57*(V13*$C13/$C14+AJ13*$D13/$D14+AX13*$E13/$E14+BL13*$F13/$F14) -> 69.859334 | H56: =H57*(W13*$C13/$C14+AK13*$D13/$D14+AY13*$E13/$E14+BM13*$F13/$F14) -> 69.952731 | I56: =I57*(X13*$C13/$C14+AL13*$D13/$D14+AZ13*$E13/$E14+BN13*$F13/$F14) -> 69.94458 | ... L56: =L57*(AA13*$C13/$C14+AO13*$D13/$D14+BC13*$E13/$E14+BQ13*$F13/$F14) -> 70.280649 | M56: =B13 -> 68.81667 | O56: 1996 | P56: =B56*($M56/$B56) -> 68.81667 | Q56: =C56*($M56/$B56) -> 68.722976 | R56: =D56*($M56/$B56) -> 68.72241 | S56: =E56*($M56/$B56) -> 68.65377 | T56: =F56*($M56/$B56) -> 68.686184 | U56: =G56*($M56/$B56) -> 68.658377 | V56: =H56*($M56/$B56) -> 68.750168 | W56: =I56*($M56/$B56) -> 68.742157 | ... AA56: =M56*($M56/$B56) -> 67.633637
A57: 1997 | B57: =B58*(Q14*$C14/$C15+AE14*$D14/$D15+AS14*$E14/$E15+BG14*$F14/$F15) -> 71.277126 | C57: =C58*(R14*$C14/$C15+AF14*$D14/$D15+AT14*$E14/$E15+BH14*$F14/$F15) -> 70.98738 | D57: =D58*(S14*$C14/$C15+AG14*$D14/$D15+AU14*$E14/$E15+BI14*$F14/$F15) -> 70.995436 | E57: =E58*(T14*$C14/$C15+AH14*$D14/$D15+AV14*$E14/$E15+BJ14*$F14/$F15) -> 71.015088 | F57: =F58*(U14*$C14/$C15+AI14*$D14/$D15+AW14*$E14/$E15+BK14*$F14/$F15) -> 71.107305 | G57: =G58*(V14*$C14/$C15+AJ14*$D14/$D15+AX14*$E14/$E15+BL14*$F14/$F15) -> 71.116757 | H57: =H58*(W14*$C14/$C15+AK14*$D14/$D15+AY14*$E14/$E15+BM14*$F14/$F15) -> 71.215266 | I57: =I58*(X14*$C14/$C15+AL14*$D14/$D15+AZ14*$E14/$E15+BN14*$F14/$F15) -> 71.225817 | ... L57: =L58*(AA14*$C14/$C15+AO14*$D14/$D15+BC14*$E14/$E15+BQ14*$F14/$F15) -> 71.571579 | M57: =B14 -> 70.06667 | O57: 1997 | P57: =B57*($M57/$B57) -> 70.06667 | Q57: =C57*($M57/$B57) -> 69.781844 | R57: =D57*($M57/$B57) -> 69.789764 | S57: =E57*($M57/$B57) -> 69.809082 | T57: =F57*($M57/$B57) -> 69.899733 | U57: =G57*($M57/$B57) -> 69.909024 | V57: =H57*($M57/$B57) -> 70.005861 | W57: =I57*($M57/$B57) -> 70.016232 | ... AA57: =M57*($M57/$B57) -> 68.876771
A58: 1998 | B58: =B59*(Q15*$C15/$C16+AE15*$D15/$D16+AS15*$E15/$E16+BG15*$F15/$F16) -> 72.186247 | C58: =C59*(R15*$C15/$C16+AF15*$D15/$D16+AT15*$E15/$E16+BH15*$F15/$F16) -> 71.797583 | D58: =D59*(S15*$C15/$C16+AG15*$D15/$D16+AU15*$E15/$E16+BI15*$F15/$F16) -> 71.809227 | E58: =E59*(T15*$C15/$C16+AH15*$D15/$D16+AV15*$E15/$E16+BJ15*$F15/$F16) -> 71.882168 | F58: =F59*(U15*$C15/$C16+AI15*$D15/$D16+AW15*$E15/$E16+BK15*$F15/$F16) -> 72.002979 | G58: =G59*(V15*$C15/$C16+AJ15*$D15/$D16+AX15*$E15/$E16+BL15*$F15/$F16) -> 72.030579 | H58: =H59*(W15*$C15/$C16+AK15*$D15/$D16+AY15*$E15/$E16+BM15*$F15/$F16) -> 72.131287 | I58: =I59*(X15*$C15/$C16+AL15*$D15/$D16+AZ15*$E15/$E16+BN15*$F15/$F16) -> 72.15097 | ... L58: =L59*(AA15*$C15/$C16+AO15*$D15/$D16+BC15*$E15/$E16+BQ15*$F15/$F16) -> 72.488241 | M58: =B15 -> 71.15833 | O58: 1998 | P58: =B58*($M58/$B58) -> 71.15833 | Q58: =C58*($M58/$B58) -> 70.7752 | R58: =D58*($M58/$B58) -> 70.786678 | S58: =E58*($M58/$B58) -> 70.858581 | T58: =F58*($M58/$B58) -> 70.977671 | U58: =G58*($M58/$B58) -> 71.004879 | V58: =H58*($M58/$B58) -> 71.104152 | W58: =I58*($M58/$B58) -> 71.123555 | ... AA58: =M58*($M58/$B58) -> 70.14505
A59: 1999 | B59: =B60*(Q16*$C16/$C17+AE16*$D16/$D17+AS16*$E16/$E17+BG16*$F16/$F17) -> 72.970149 | C59: =C60*(R16*$C16/$C17+AF16*$D16/$D17+AT16*$E16/$E17+BH16*$F16/$F17) -> 72.562144 | D59: =D60*(S16*$C16/$C17+AG16*$D16/$D17+AU16*$E16/$E17+BI16*$F16/$F17) -> 72.573576 | E59: =E60*(T16*$C16/$C17+AH16*$D16/$D17+AV16*$E16/$E17+BJ16*$F16/$F17) -> 72.679604 | F59: =F60*(U16*$C16/$C17+AI16*$D16/$D17+AW16*$E16/$E17+BK16*$F16/$F17) -> 72.811458 | G59: =G60*(V16*$C16/$C17+AJ16*$D16/$D17+AX16*$E16/$E17+BL16*$F16/$F17) -> 72.855161 | H59: =H60*(W16*$C16/$C17+AK16*$D16/$D17+AY16*$E16/$E17+BM16*$F16/$F17) -> 72.92349 | I59: =I60*(X16*$C16/$C17+AL16*$D16/$D17+AZ16*$E16/$E17+BN16*$F16/$F17) -> 72.956102 | ... L59: =L60*(AA16*$C16/$C17+AO16*$D16/$D17+BC16*$E16/$E17+BQ16*$F16/$F17) -> 73.226493 | M59: =B16 -> 72.11666 | O59: 1999 | P59: =B59*($M59/$B59) -> 72.11666 | Q59: =C59*($M59/$B59) -> 71.713427 | R59: =D59*($M59/$B59) -> 71.724725 | S59: =E59*($M59/$B59) -> 71.829513 | T59: =F59*($M59/$B59) -> 71.959825 | U59: =G59*($M59/$B59) -> 72.003016 | V59: =H59*($M59/$B59) -> 72.070546 | W59: =I59*($M59/$B59) -> 72.102777 | ... AA59: =M59*($M59/$B59) -> 71.273153
A60: 2000 | B60: =B61*(Q17*$C17/$C18+AE17*$D17/$D18+AS17*$E17/$E18+BG17*$F17/$F18) -> 72.936773 | C60: =C61*(R17*$C17/$C18+AF17*$D17/$D18+AT17*$E17/$E18+BH17*$F17/$F18) -> 72.51763 | D60: =D61*(S17*$C17/$C18+AG17*$D17/$D18+AU17*$E17/$E18+BI17*$F17/$F18) -> 72.528148 | E60: =E61*(T17*$C17/$C18+AH17*$D17/$D18+AV17*$E17/$E18+BJ17*$F17/$F18) -> 72.680527 | F60: =F61*(U17*$C17/$C18+AI17*$D17/$D18+AW17*$E17/$E18+BK17*$F17/$F18) -> 72.825888 | G60: =G61*(V17*$C17/$C18+AJ17*$D17/$D18+AX17*$E17/$E18+BL17*$F17/$F18) -> 72.89545 | H60: =H61*(W17*$C17/$C18+AK17*$D17/$D18+AY17*$E17/$E18+BM17*$F17/$F18) -> 72.903359 | I60: =I61*(X17*$C17/$C18+AL17*$D17/$D18+AZ17*$E17/$E18+BN17*$F17/$F18) -> 72.957541 | ... L60: =L61*(AA17*$C17/$C18+AO17*$D17/$D18+BC17*$E17/$E18+BQ17*$F17/$F18) -> 73.108101 | M60: =B17 -> 72.69167 | O60: 2000 | P60: =B60*($M60/$B60) -> 72.69167 | Q60: =C60*($M60/$B60) -> 72.273936 | R60: =D60*($M60/$B60) -> 72.284419 | S60: =E60*($M60/$B60) -> 72.436286 | T60: =F60*($M60/$B60) -> 72.581158 | U60: =G60*($M60/$B60) -> 72.650487 | V60: =H60*($M60/$B60) -> 72.658369 | W60: =I60*($M60/$B60) -> 72.712369 | ... AA60: =M60*($M60/$B60) -> 72.447391
A61: 2001 | B61: =B62*(Q18*$C18/$C19+AE18*$D18/$D19+AS18*$E18/$E19+BG18*$F18/$F19) -> 73.581702 | C61: =C62*(R18*$C18/$C19+AF18*$D18/$D19+AT18*$E18/$E19+BH18*$F18/$F19) -> 73.337895 | D61: =D62*(S18*$C18/$C19+AG18*$D18/$D19+AU18*$E18/$E19+BI18*$F18/$F19) -> 73.339256 | E61: =E62*(T18*$C18/$C19+AH18*$D18/$D19+AV18*$E18/$E19+BJ18*$F18/$F19) -> 73.422435 | F61: =F62*(U18*$C18/$C19+AI18*$D18/$D19+AW18*$E18/$E19+BK18*$F18/$F19) -> 73.51261 | G61: =G62*(V18*$C18/$C19+AJ18*$D18/$D19+AX18*$E18/$E19+BL18*$F18/$F19) -> 73.546807 | H61: =H62*(W18*$C18/$C19+AK18*$D18/$D19+AY18*$E18/$E19+BM18*$F18/$F19) -> 73.548154 | I61: =I62*(X18*$C18/$C19+AL18*$D18/$D19+AZ18*$E18/$E19+BN18*$F18/$F19) -> 73.5856 | ... L61: =L62*(AA18*$C18/$C19+AO18*$D18/$D19+BC18*$E18/$E19+BQ18*$F18/$F19) -> 73.70802 | M61: =B18 -> 73.59167 | O61: 2001 | P61: =B61*($M61/$B61) -> 73.59167 | Q61: =C61*($M61/$B61) -> 73.34783 | R61: =D61*($M61/$B61) -> 73.349191 | S61: =E61*($M61/$B61) -> 73.432381 | T61: =F61*($M61/$B61) -> 73.522568 | U61: =G61*($M61/$B61) -> 73.55677 | V61: =H61*($M61/$B61) -> 73.558117 | W61: =I61*($M61/$B61) -> 73.595568 | ... AA61: =M61*($M61/$B61) -> 73.601639
A62: 2002 | B62: =B63*(Q19*$C19/$C20+AE19*$D19/$D20+AS19*$E19/$E20+BG19*$F19/$F20) -> 74.354836 | C62: =C63*(R19*$C19/$C20+AF19*$D19/$D20+AT19*$E19/$E20+BH19*$F19/$F20) -> 74.168978 | D62: =D63*(S19*$C19/$C20+AG19*$D19/$D20+AU19*$E19/$E20+BI19*$F19/$F20) -> 74.167846 | E62: =E63*(T19*$C19/$C20+AH19*$D19/$D20+AV19*$E19/$E20+BJ19*$F19/$F20) -> 74.216167 | F62: =F63*(U19*$C19/$C20+AI19*$D19/$D20+AW19*$E19/$E20+BK19*$F19/$F20) -> 74.286831 | G62: =G63*(V19*$C19/$C20+AJ19*$D19/$D20+AX19*$E19/$E20+BL19*$F19/$F20) -> 74.304815 | H62: =H63*(W19*$C19/$C20+AK19*$D19/$D20+AY19*$E19/$E20+BM19*$F19/$F20) -> 74.316594 | I62: =I63*(X19*$C19/$C20+AL19*$D19/$D20+AZ19*$E19/$E20+BN19*$F19/$F20) -> 74.344596 | ... L62: =L63*(AA19*$C19/$C20+AO19*$D19/$D20+BC19*$E19/$E20+BQ19*$F19/$F20) -> 74.488975 | M62: =B19 -> 74.5 | O62: 2002 | P62: =B62*($M62/$B62) -> 74.5 | Q62: =C62*($M62/$B62) -> 74.313779 | R62: =D62*($M62/$B62) -> 74.312645 | S62: =E62*($M62/$B62) -> 74.36106 | T62: =F62*($M62/$B62) -> 74.431862 | U62: =G62*($M62/$B62) -> 74.449882 | V62: =H62*($M62/$B62) -> 74.461683 | W62: =I62*($M62/$B62) -> 74.48974 | ... AA62: =M62*($M62/$B62) -> 74.645448
A63: 2003 | B63: =B64*(Q20*$C20/$C21+AE20*$D20/$D21+AS20*$E20/$E21+BG20*$F20/$F21) -> 75.318133 | C63: =C64*(R20*$C20/$C21+AF20*$D20/$D21+AT20*$E20/$E21+BH20*$F20/$F21) -> 75.126576 | D63: =D64*(S20*$C20/$C21+AG20*$D20/$D21+AU20*$E20/$E21+BI20*$F20/$F21) -> 75.132001 | E63: =E64*(T20*$C20/$C21+AH20*$D20/$D21+AV20*$E20/$E21+BJ20*$F20/$F21) -> 75.182659 | F63: =F64*(U20*$C20/$C21+AI20*$D20/$D21+AW20*$E20/$E21+BK20*$F20/$F21) -> 75.255841 | G63: =G64*(V20*$C20/$C21+AJ20*$D20/$D21+AX20*$E20/$E21+BL20*$F20/$F21) -> 75.272706 | H63: =H64*(W20*$C20/$C21+AK20*$D20/$D21+AY20*$E20/$E21+BM20*$F20/$F21) -> 75.284469 | I63: =I64*(X20*$C20/$C21+AL20*$D20/$D21+AZ20*$E20/$E21+BN20*$F20/$F21) -> 75.313555 | ... L63: =L64*(AA20*$C20/$C21+AO20*$D20/$D21+BC20*$E20/$E21+BQ20*$F20/$F21) -> 75.436918 | M63: =B20 -> 75.525 | O63: 2003 | P63: =B63*($M63/$B63) -> 75.525 | Q63: =C63*($M63/$B63) -> 75.332917 | R63: =D63*($M63/$B63) -> 75.338356 | S63: =E63*($M63/$B63) -> 75.389153 | T63: =F63*($M63/$B63) -> 75.462536 | U63: =G63*($M63/$B63) -> 75.479448 | V63: =H63*($M63/$B63) -> 75.491243 | W63: =I63*($M63/$B63) -> 75.520409 | ... AA63: =M63*($M63/$B63) -> 75.732435
A64: 2004 | B64: =B65*(Q21*$C21/$C22+AE21*$D21/$D22+AS21*$E21/$E22+BG21*$F21/$F22) -> 76.319076 | C64: =C65*(R21*$C21/$C22+AF21*$D21/$D22+AT21*$E21/$E22+BH21*$F21/$F22) -> 76.204435 | D64: =D65*(S21*$C21/$C22+AG21*$D21/$D22+AU21*$E21/$E22+BI21*$F21/$F22) -> 76.188747 | E64: =E65*(T21*$C21/$C22+AH21*$D21/$D22+AV21*$E21/$E22+BJ21*$F21/$F22) -> 76.241672 | F64: =F65*(U21*$C21/$C22+AI21*$D21/$D22+AW21*$E21/$E22+BK21*$F21/$F22) -> 76.27838 | G64: =G65*(V21*$C21/$C22+AJ21*$D21/$D22+AX21*$E21/$E22+BL21*$F21/$F22) -> 76.293613 | H64: =H65*(W21*$C21/$C22+AK21*$D21/$D22+AY21*$E21/$E22+BM21*$F21/$F22) -> 76.298423 | I64: =I65*(X21*$C21/$C22+AL21*$D21/$D22+AZ21*$E21/$E22+BN21*$F21/$F22) -> 76.313087 | ... L64: =L65*(AA21*$C21/$C22+AO21*$D21/$D22+BC21*$E21/$E22+BQ21*$F21/$F22) -> 76.394615 | M64: =B21 -> 76.54167 | O64: 2004 | P64: =B64*($M64/$B64) -> 76.54167 | Q64: =C64*($M64/$B64) -> 76.426695 | R64: =D64*($M64/$B64) -> 76.410962 | S64: =E64*($M64/$B64) -> 76.464041 | T64: =F64*($M64/$B64) -> 76.500855 | U64: =G64*($M64/$B64) -> 76.516133 | V64: =H64*($M64/$B64) -> 76.520957 | W64: =I64*($M64/$B64) -> 76.535664 | ... AA64: =M64*($M64/$B64) -> 76.764914
A65: 2005 | B65: =$B$22 -> 78.1 | C65: =$B$22 -> 78.1 | D65: =$B$22 -> 78.1 | E65: =$B$22 -> 78.1 | F65: =$B$22 -> 78.1 | G65: =$B$22 -> 78.1 | H65: =$B$22 -> 78.1 | I65: =$B$22 -> 78.1 | ... M65: =$B$22 -> 78.1 | O65: 2005 | P65: =B65*($M65/$B65) -> 78.1 | Q65: =C65*($M65/$B65) -> 78.1 | R65: =D65*($M65/$B65) -> 78.1 | S65: =E65*($M65/$B65) -> 78.1 | T65: =F65*($M65/$B65) -> 78.1 | U65: =G65*($M65/$B65) -> 78.1 | V65: =H65*($M65/$B65) -> 78.1 | W65: =I65*($M65/$B65) -> 78.1 | ... AA65: =M65*($M65/$B65) -> 78.1 | AC65: 77.433333
A66: 2006 | B66: =B65*(Q23*$C23/$C22+AE23*$D23/$D22+AS23*$E23/$E22+BG23*$F23/$F22) -> 80.401714 | C66: =C65*(R23*$C23/$C22+AF23*$D23/$D22+AT23*$E23/$E22+BH23*$F23/$F22) -> 80.923093 | D66: =D65*(S23*$C23/$C22+AG23*$D23/$D22+AU23*$E23/$E22+BI23*$F23/$F22) -> 80.87322 | E66: =E65*(T23*$C23/$C22+AH23*$D23/$D22+AV23*$E23/$E22+BJ23*$F23/$F22) -> 80.699803 | F66: =F65*(U23*$C23/$C22+AI23*$D23/$D22+AW23*$E23/$E22+BK23*$F23/$F22) -> 80.520344 | G66: =G65*(V23*$C23/$C22+AJ23*$D23/$D22+AX23*$E23/$E22+BL23*$F23/$F22) -> 80.518227 | H66: =H65*(W23*$C23/$C22+AK23*$D23/$D22+AY23*$E23/$E22+BM23*$F23/$F22) -> 80.436252 | I66: =I65*(X23*$C23/$C22+AL23*$D23/$D22+AZ23*$E23/$E22+BN23*$F23/$F22) -> 80.365721 | ... L66: =L65*(AA23*$C23/$C22+AO23*$D23/$D22+BC23*$E23/$E22+BQ23*$F23/$F22) -> 80.190028 | M66: =B23 -> 79.93333 | O66: 2006 | P66: =B66*($M66/$B66) -> 79.93333 | Q66: =C66*($M66/$B66) -> 80.451672 | R66: =D66*($M66/$B66) -> 80.40209 | S66: =E66*($M66/$B66) -> 80.229683 | T66: =F66*($M66/$B66) -> 80.051269 | U66: =G66*($M66/$B66) -> 80.049165 | V66: =H66*($M66/$B66) -> 79.967667 | W66: =I66*($M66/$B66) -> 79.897547 | ... AA66: =M66*($M66/$B66) -> 79.467675 | AC66: 79.916667
A67: 2007 | B67: =B66*(Q24*$C24/$C23+AE24*$D24/$D23+AS24*$E24/$E23+BG24*$F24/$F23) -> 82.496615 | C67: =C66*(R24*$C24/$C23+AF24*$D24/$D23+AT24*$E24/$E23+BH24*$F24/$F23) -> 83.193424 | D67: =D66*(S24*$C24/$C23+AG24*$D24/$D23+AU24*$E24/$E23+BI24*$F24/$F23) -> 83.196943 | E67: =E66*(T24*$C24/$C23+AH24*$D24/$D23+AV24*$E24/$E23+BJ24*$F24/$F23) -> 82.925061 | F67: =F66*(U24*$C24/$C23+AI24*$D24/$D23+AW24*$E24/$E23+BK24*$F24/$F23) -> 82.693477 | G67: =G66*(V24*$C24/$C23+AJ24*$D24/$D23+AX24*$E24/$E23+BL24*$F24/$F23) -> 82.659379 | H67: =H66*(W24*$C24/$C23+AK24*$D24/$D23+AY24*$E24/$E23+BM24*$F24/$F23) -> 82.53866 | I67: =I66*(X24*$C24/$C23+AL24*$D24/$D23+AZ24*$E24/$E23+BN24*$F24/$F23) -> 82.470718 | ... L67: =L66*(AA24*$C24/$C23+AO24*$D24/$D23+BC24*$E24/$E23+BQ24*$F24/$F23) -> 82.177377 | M67: =B24 -> 81.78333 | O67: 2007 | P67: =B67*($M67/$B67) -> 81.78333 | Q67: =C67*($M67/$B67) -> 82.474115 | R67: =D67*($M67/$B67) -> 82.477603 | S67: =E67*($M67/$B67) -> 82.208072 | T67: =F67*($M67/$B67) -> 81.97849 | U67: =G67*($M67/$B67) -> 81.944687 | V67: =H67*($M67/$B67) -> 81.825012 | W67: =I67*($M67/$B67) -> 81.757657 | ... AA67: =M67*($M67/$B67) -> 81.076213 | AC67: 82.808333
A68: 2008 | B68: =B67*(Q25*$C25/$C24+AE25*$D25/$D24+AS25*$E25/$E24+BG25*$F25/$F24) -> 85.712805 | C68: =C67*(R25*$C25/$C24+AF25*$D25/$D24+AT25*$E25/$E24+BH25*$F25/$F24) -> 87.130262 | D68: =D67*(S25*$C25/$C24+AG25*$D25/$D24+AU25*$E25/$E24+BI25*$F25/$F24) -> 86.986919 | E68: =E67*(T25*$C25/$C24+AH25*$D25/$D24+AV25*$E25/$E24+BJ25*$F25/$F24) -> 86.529362 | F68: =F67*(U25*$C25/$C24+AI25*$D25/$D24+AW25*$E25/$E24+BK25*$F25/$F24) -> 86.172288 | G68: =G67*(V25*$C25/$C24+AJ25*$D25/$D24+AX25*$E25/$E24+BL25*$F25/$F24) -> 86.063846 | H68: =H67*(W25*$C25/$C24+AK25*$D25/$D24+AY25*$E25/$E24+BM25*$F25/$F24) -> 85.812748 | I68: =I67*(X25*$C25/$C24+AL25*$D25/$D24+AZ25*$E25/$E24+BN25*$F25/$F24) -> 85.659646 | ... L68: =L67*(AA25*$C25/$C24+AO25*$D25/$D24+BC25*$E25/$E24+BQ25*$F25/$F24) -> 85.050868 | M68: =B25 -> 84.725 | O68: 2008 | P68: =B68*($M68/$B68) -> 84.725 | Q68: =C68*($M68/$B68) -> 86.126122 | R68: =D68*($M68/$B68) -> 85.98443 | S68: =E68*($M68/$B68) -> 85.532146 | T68: =F68*($M68/$B68) -> 85.179188 | U68: =G68*($M68/$B68) -> 85.071996 | V68: =H68*($M68/$B68) -> 84.823791 | W68: =I68*($M68/$B68) -> 84.672454 | ... AA68: =M68*($M68/$B68) -> 83.748579 | AC68: 86.066667
A69: 2009 | B69: =B68*(Q26*$C26/$C25+AE26*$D26/$D25+AS26*$E26/$E25+BG26*$F26/$F25) -> 87.816706 | C69: =C68*(R26*$C26/$C25+AF26*$D26/$D25+AT26*$E26/$E25+BH26*$F26/$F25) -> 89.651724 | D69: =D68*(S26*$C26/$C25+AG26*$D26/$D25+AU26*$E26/$E25+BI26*$F26/$F25) -> 89.494526 | E69: =E68*(T26*$C26/$C25+AH26*$D26/$D25+AV26*$E26/$E25+BJ26*$F26/$F25) -> 88.866563 | F69: =F68*(U26*$C26/$C25+AI26*$D26/$D25+AW26*$E26/$E25+BK26*$F26/$F25) -> 88.392585 | G69: =G68*(V26*$C26/$C25+AJ26*$D26/$D25+AX26*$E26/$E25+BL26*$F26/$F25) -> 88.237072 | H69: =H68*(W26*$C26/$C25+AK26*$D26/$D25+AY26*$E26/$E25+BM26*$F26/$F25) -> 87.902269 | I69: =I68*(X26*$C26/$C25+AL26*$D26/$D25+AZ26*$E26/$E25+BN26*$F26/$F25) -> 87.731385 | ... L69: =L68*(AA26*$C26/$C25+AO26*$D26/$D25+BC26*$E26/$E25+BQ26*$F26/$F25) -> 87.048362 | M69: =B26 -> 86.575 | O69: 2009 | P69: =B69*($M69/$B69) -> 86.575 | Q69: =C69*($M69/$B69) -> 88.384072 | R69: =D69*($M69/$B69) -> 88.229096 | S69: =E69*($M69/$B69) -> 87.610013 | T69: =F69*($M69/$B69) -> 87.142736 | U69: =G69*($M69/$B69) -> 86.989422 | V69: =H69*($M69/$B69) -> 86.659353 | W69: =I69*($M69/$B69) -> 86.490885 | ... AA69: =M69*($M69/$B69) -> 85.350852 | AC69: 86.308333
A70: 2010 | B70: =B69*(Q27*$C27/$C26+AE27*$D27/$D26+AS27*$E27/$E26+BG27*$F27/$F26) -> 90.702338 | C70: =C69*(R27*$C27/$C26+AF27*$D27/$D26+AT27*$E27/$E26+BH27*$F27/$F26) -> 92.310624 | D70: =D69*(S27*$C27/$C26+AG27*$D27/$D26+AU27*$E27/$E26+BI27*$F27/$F26) -> 92.199676 | E70: =E69*(T27*$C27/$C26+AH27*$D27/$D26+AV27*$E27/$E26+BJ27*$F27/$F26) -> 91.596826 | F70: =F69*(U27*$C27/$C26+AI27*$D27/$D26+AW27*$E27/$E26+BK27*$F27/$F26) -> 91.220425 | G70: =G69*(V27*$C27/$C26+AJ27*$D27/$D26+AX27*$E27/$E26+BL27*$F27/$F26) -> 91.136714 | H70: =H69*(W27*$C27/$C26+AK27*$D27/$D26+AY27*$E27/$E26+BM27*$F27/$F26) -> 90.833397 | I70: =I69*(X27*$C27/$C26+AL27*$D27/$D26+AZ27*$E27/$E26+BN27*$F27/$F26) -> 90.686895 | ... L70: =L69*(AA27*$C27/$C26+AO27*$D27/$D26+BC27*$E27/$E26+BQ27*$F27/$F26) -> 89.89643 | M70: =B27 -> 89.43333 | O70: 2010 | P70: =B70*($M70/$B70) -> 89.43333 | Q70: =C70*($M70/$B70) -> 91.019115 | R70: =D70*($M70/$B70) -> 90.909718 | S70: =E70*($M70/$B70) -> 90.315303 | T70: =F70*($M70/$B70) -> 89.944168 | U70: =G70*($M70/$B70) -> 89.861628 | V70: =H70*($M70/$B70) -> 89.562555 | W70: =I70*($M70/$B70) -> 89.418103 | ... AA70: =M70*($M70/$B70) -> 88.182076 | AC70: 89.333333
A71: 2011 | B71: =B70*(Q28*$C28/$C27+AE28*$D28/$D27+AS28*$E28/$E27+BG28*$F28/$F27) -> 94.767488 | C71: =C70*(R28*$C28/$C27+AF28*$D28/$D27+AT28*$E28/$E27+BH28*$F28/$F27) -> 96.552655 | D71: =D70*(S28*$C28/$C27+AG28*$D28/$D27+AU28*$E28/$E27+BI28*$F28/$F27) -> 96.473451 | E71: =E70*(T28*$C28/$C27+AH28*$D28/$D27+AV28*$E28/$E27+BJ28*$F28/$F27) -> 95.760431 | F71: =F70*(U28*$C28/$C27+AI28*$D28/$D27+AW28*$E28/$E27+BK28*$F28/$F27) -> 95.418315 | G71: =G70*(V28*$C28/$C27+AJ28*$D28/$D27+AX28*$E28/$E27+BL28*$F28/$F27) -> 95.320535 | H71: =H70*(W28*$C28/$C27+AK28*$D28/$D27+AY28*$E28/$E27+BM28*$F28/$F27) -> 94.957406 | I71: =I70*(X28*$C28/$C27+AL28*$D28/$D27+AZ28*$E28/$E27+BN28*$F28/$F27) -> 94.801759 | ... L71: =L70*(AA28*$C28/$C27+AO28*$D28/$D27+BC28*$E28/$E27+BQ28*$F28/$F27) -> 93.731936 | M71: =B28 -> 93.425 | O71: 2011 | P71: =B71*($M71/$B71) -> 93.425 | Q71: =C71*($M71/$B71) -> 95.184877 | R71: =D71*($M71/$B71) -> 95.106796 | S71: =E71*($M71/$B71) -> 94.403876 | T71: =F71*($M71/$B71) -> 94.066607 | U71: =G71*($M71/$B71) -> 93.970212 | V71: =H71*($M71/$B71) -> 93.612227 | W71: =I71*($M71/$B71) -> 93.458785 | ... AA71: =M71*($M71/$B71) -> 92.101529 | AC71: 93.616667
A72: 2012 | B72: =B71*(Q29*$C29/$C28+AE29*$D29/$D28+AS29*$E29/$E28+BG29*$F29/$F28) -> 97.410609 | C72: =C71*(R29*$C29/$C28+AF29*$D29/$D28+AT29*$E29/$E28+BH29*$F29/$F28) -> 99.475406 | D72: =D71*(S29*$C29/$C28+AG29*$D29/$D28+AU29*$E29/$E28+BI29*$F29/$F28) -> 99.427675 | E72: =E71*(T29*$C29/$C28+AH29*$D29/$D28+AV29*$E29/$E28+BJ29*$F29/$F28) -> 98.578896 | F72: =F71*(U29*$C29/$C28+AI29*$D29/$D28+AW29*$E29/$E28+BK29*$F29/$F28) -> 98.170925 | G72: =G71*(V29*$C29/$C28+AJ29*$D29/$D28+AX29*$E29/$E28+BL29*$F29/$F28) -> 98.040726 | H72: =H71*(W29*$C29/$C28+AK29*$D29/$D28+AY29*$E29/$E28+BM29*$F29/$F28) -> 97.620273 | I72: =I71*(X29*$C29/$C28+AL29*$D29/$D28+AZ29*$E29/$E28+BN29*$F29/$F28) -> 97.436879 | ... L72: =L71*(AA29*$C29/$C28+AO29*$D29/$D28+BC29*$E29/$E28+BQ29*$F29/$F28) -> 96.218125 | M72: =B29 -> 96.04167 | O72: 2012 | P72: =B72*($M72/$B72) -> 96.04167 | Q72: =C72*($M72/$B72) -> 98.07745 | R72: =D72*($M72/$B72) -> 98.030389 | S72: =E72*($M72/$B72) -> 97.193538 | T72: =F72*($M72/$B72) -> 96.791301 | U72: =G72*($M72/$B72) -> 96.662932 | V72: =H72*($M72/$B72) -> 96.248388 | W72: =I72*($M72/$B72) -> 96.067571 | ... AA72: =M72*($M72/$B72) -> 94.691969 | AC72: 96.25
A73: 2013 | B73: =B72*(Q30*$C30/$C29+AE30*$D30/$D29+AS30*$E30/$E29+BG30*$F30/$F29) -> 100.13125 | C73: =C72*(R30*$C30/$C29+AF30*$D30/$D29+AT30*$E30/$E29+BH30*$F30/$F29) -> 102.65812 | D73: =D72*(S30*$C30/$C29+AG30*$D30/$D29+AU30*$E30/$E29+BI30*$F30/$F29) -> 102.57393 | E73: =E72*(T30*$C30/$C29+AH30*$D30/$D29+AV30*$E30/$E29+BJ30*$F30/$F29) -> 101.48463 | F73: =F72*(U30*$C30/$C29+AI30*$D30/$D29+AW30*$E30/$E29+BK30*$F30/$F29) -> 101.0177 | G73: =G72*(V30*$C30/$C29+AJ30*$D30/$D29+AX30*$E30/$E29+BL30*$F30/$F29) -> 100.82973 | H73: =H72*(W30*$C30/$C29+AK30*$D30/$D29+AY30*$E30/$E29+BM30*$F30/$F29) -> 100.3444 | I73: =I72*(X30*$C30/$C29+AL30*$D30/$D29+AZ30*$E30/$E29+BN30*$F30/$F29) -> 100.13108 | ... L73: =L72*(AA30*$C30/$C29+AO30*$D30/$D29+BC30*$E30/$E29+BQ30*$F30/$F29) -> 98.781158 | M73: =B30 -> 98.50833 | O73: 2013 | P73: =B73*($M73/$B73) -> 98.50833 | Q73: =C73*($M73/$B73) -> 100.99424 | R73: =D73*($M73/$B73) -> 100.91142 | S73: =E73*($M73/$B73) -> 99.839776 | T73: =F73*($M73/$B73) -> 99.380413 | U73: =G73*($M73/$B73) -> 99.195485 | V73: =H73*($M73/$B73) -> 98.718018 | W73: =I73*($M73/$B73) -> 98.508157 | ... AA73: =M73*($M73/$B73) -> 96.911711 | AC73: 98.675
A74: 2014 | B74: =B73*(Q31*$C31/$C30+AE31*$D31/$D30+AS31*$E31/$E30+BG31*$F31/$F30) -> 101.72623 | C74: =C73*(R31*$C31/$C30+AF31*$D31/$D30+AT31*$E31/$E30+BH31*$F31/$F30) -> 104.47909 | D74: =D73*(S31*$C31/$C30+AG31*$D31/$D30+AU31*$E31/$E30+BI31*$F31/$F30) -> 104.38485 | E74: =E73*(T31*$C31/$C30+AH31*$D31/$D30+AV31*$E31/$E30+BJ31*$F31/$F30) -> 103.14382 | F74: =F73*(U31*$C31/$C30+AI31*$D31/$D30+AW31*$E31/$E30+BK31*$F31/$F30) -> 102.62917 | G74: =G73*(V31*$C31/$C30+AJ31*$D31/$D30+AX31*$E31/$E30+BL31*$F31/$F30) -> 102.3864 | H74: =H73*(W31*$C31/$C30+AK31*$D31/$D30+AY31*$E31/$E30+BM31*$F31/$F30) -> 101.90844 | I74: =I73*(X31*$C31/$C30+AL31*$D31/$D30+AZ31*$E31/$E30+BN31*$F31/$F30) -> 101.67994 | ... L74: =L73*(AA31*$C31/$C30+AO31*$D31/$D30+BC31*$E31/$E30+BQ31*$F31/$F30) -> 100.39069 | M74: =B31 -> 99.95833 | O74: 2014 | P74: =B74*($M74/$B74) -> 99.95833 | Q74: =C74*($M74/$B74) -> 102.66335 | R74: =D74*($M74/$B74) -> 102.57075 | S74: =E74*($M74/$B74) -> 101.35128 | T74: =F74*($M74/$B74) -> 100.84558 | U74: =G74*($M74/$B74) -> 100.60703 | V74: =H74*($M74/$B74) -> 100.13738 | W74: =I74*($M74/$B74) -> 99.912851 | ... AA74: =M74*($M74/$B74) -> 98.221158 | AC74: 100.09167
A75: 2015 | B75: =B74*(Q32*$C32/$C31+AE32*$D32/$D31+AS32*$E32/$E31+BG32*$F32/$F31) -> 101.85578 | C75: =C74*(R32*$C32/$C31+AF32*$D32/$D31+AT32*$E32/$E31+BH32*$F32/$F31) -> 104.43809 | D75: =D74*(S32*$C32/$C31+AG32*$D32/$D31+AU32*$E32/$E31+BI32*$F32/$F31) -> 104.40648 | E75: =E74*(T32*$C32/$C31+AH32*$D32/$D31+AV32*$E32/$E31+BJ32*$F32/$F31) -> 103.10604 | F75: =F74*(U32*$C32/$C31+AI32*$D32/$D31+AW32*$E32/$E31+BK32*$F32/$F31) -> 102.66034 | G75: =G74*(V32*$C32/$C31+AJ32*$D32/$D31+AX32*$E32/$E31+BL32*$F32/$F31) -> 102.4371 | H75: =H74*(W32*$C32/$C31+AK32*$D32/$D31+AY32*$E32/$E31+BM32*$F32/$F31) -> 102.03509 | I75: =I74*(X32*$C32/$C31+AL32*$D32/$D31+AZ32*$E32/$E31+BN32*$F32/$F31) -> 101.77425 | ... L75: =L74*(AA32*$C32/$C31+AO32*$D32/$D31+BC32*$E32/$E31+BQ32*$F32/$F31) -> 100.71002 | M75: =B32 -> 100.0083 | O75: 2015 | P75: =B75*($M75/$B75) -> 100.0083 | Q75: =C75*($M75/$B75) -> 102.54377 | R75: =D75*($M75/$B75) -> 102.51274 | S75: =E75*($M75/$B75) -> 101.23589 | T75: =F75*($M75/$B75) -> 100.79827 | U75: =G75*($M75/$B75) -> 100.57908 | V75: =H75*($M75/$B75) -> 100.18436 | W75: =I75*($M75/$B75) -> 99.928248 | ... AA75: =M75*($M75/$B75) -> 98.194329 | AC75: 99.991667
A76: 2016 | B76: =B75*(Q33*$C33/$C32+AE33*$D33/$D32+AS33*$E33/$E32+BG33*$F33/$F32) -> 102.4649 | C76: =C75*(R33*$C33/$C32+AF33*$D33/$D32+AT33*$E33/$E32+BH33*$F33/$F32) -> 104.82485 | D76: =D75*(S33*$C33/$C32+AG33*$D33/$D32+AU33*$E33/$E32+BI33*$F33/$F32) -> 104.81562 | E76: =E75*(T33*$C33/$C32+AH33*$D33/$D32+AV33*$E33/$E32+BJ33*$F33/$F32) -> 103.58215 | F76: =F75*(U33*$C33/$C32+AI33*$D33/$D32+AW33*$E33/$E32+BK33*$F33/$F32) -> 103.19247 | G76: =G75*(V33*$C33/$C32+AJ33*$D33/$D32+AX33*$E33/$E32+BL33*$F33/$F32) -> 103.00485 | H76: =H75*(W33*$C33/$C32+AK33*$D33/$D32+AY33*$E33/$E32+BM33*$F33/$F32) -> 102.61643 | I76: =I75*(X33*$C33/$C32+AL33*$D33/$D32+AZ33*$E33/$E32+BN33*$F33/$F32) -> 102.39024 | ... L76: =L75*(AA33*$C33/$C32+AO33*$D33/$D32+BC33*$E33/$E32+BQ33*$F33/$F32) -> 101.45691 | M76: =B33 -> 100.65 | O76: 2016 | P76: =B76*($M76/$B76) -> 100.65 | Q76: =C76*($M76/$B76) -> 102.96815 | R76: =D76*($M76/$B76) -> 102.95909 | S76: =E76*($M76/$B76) -> 101.74747 | T76: =F76*($M76/$B76) -> 101.36469 | U76: =G76*($M76/$B76) -> 101.18039 | V76: =H76*($M76/$B76) -> 100.79885 | W76: =I76*($M76/$B76) -> 100.57667 | ... AA76: =M76*($M76/$B76) -> 98.86725 | AC76: 100.725
A77: 2017 | B77: =B76*(Q34*$C34/$C33+AE34*$D34/$D33+AS34*$E34/$E33+BG34*$F34/$F33) -> 105.25705 | C77: =C76*(R34*$C34/$C33+AF34*$D34/$D33+AT34*$E34/$E33+BH34*$F34/$F33) -> 107.66728 | D77: =D76*(S34*$C34/$C33+AG34*$D34/$D33+AU34*$E34/$E33+BI34*$F34/$F33) -> 107.68248 | E77: =E76*(T34*$C34/$C33+AH34*$D34/$D33+AV34*$E34/$E33+BJ34*$F34/$F33) -> 106.43347 | F77: =F76*(U34*$C34/$C33+AI34*$D34/$D33+AW34*$E34/$E33+BK34*$F34/$F33) -> 106.03747 | G77: =G76*(V34*$C34/$C33+AJ34*$D34/$D33+AX34*$E34/$E33+BL34*$F34/$F33) -> 105.82978 | H77: =H76*(W34*$C34/$C33+AK34*$D34/$D33+AY34*$E34/$E33+BM34*$F34/$F33) -> 105.42474 | I77: =I76*(X34*$C34/$C33+AL34*$D34/$D33+AZ34*$E34/$E33+BN34*$F34/$F33) -> 105.19625 | ... L77: =L76*(AA34*$C34/$C33+AO34*$D34/$D33+BC34*$E34/$E33+BQ34*$F34/$F33) -> 104.15703 | M77: =B34 -> 103.3584 | O77: 2017 | P77: =B77*($M77/$B77) -> 103.3584 | Q77: =C77*($M77/$B77) -> 105.72516 | R77: =D77*($M77/$B77) -> 105.74008 | S77: =E77*($M77/$B77) -> 104.5136 | T77: =F77*($M77/$B77) -> 104.12474 | U77: =G77*($M77/$B77) -> 103.9208 | V77: =H77*($M77/$B77) -> 103.52306 | W77: =I77*($M77/$B77) -> 103.2987 | ... AA77: =M77*($M77/$B77) -> 101.494 | AC77: 103.31667
... A85: 2025 | B85: =B84*(Q42*$C42/$C41+AE42*$D42/$D41+AS42*$E42/$E41+BG42*$F42/$F41) -> 142.79518 | C85: =C84*(R42*$C42/$C41+AF42*$D42/$D41+AT42*$E42/$E41+BH42*$F42/$F41) -> 148.86795 | D85: =D84*(S42*$C42/$C41+AG42*$D42/$D41+AU42*$E42/$E41+BI42*$F42/$F41) -> 147.99445 | E85: =E84*(T42*$C42/$C41+AH42*$D42/$D41+AV42*$E42/$E41+BJ42*$F42/$F41) -> 145.45192 | F85: =F84*(U42*$C42/$C41+AI42*$D42/$D41+AW42*$E42/$E41+BK42*$F42/$F41) -> 144.28876 | G85: =G84*(V42*$C42/$C41+AJ42*$D42/$D41+AX42*$E42/$E41+BL42*$F42/$F41) -> 143.91114 | H85: =H84*(W42*$C42/$C41+AK42*$D42/$D41+AY42*$E42/$E41+BM42*$F42/$F41) -> 142.95021 | I85: =I84*(X42*$C42/$C41+AL42*$D42/$D41+AZ42*$E42/$E41+BN42*$F42/$F41) -> 142.38176 | ... L85: =L84*(AA42*$C42/$C41+AO42*$D42/$D41+BC42*$E42/$E41+BQ42*$F42/$F41) -> 140.16063 | M85: =B42 -> 138.3667 | O85: 2025 | P85: =B85*($M85/$B85) -> 138.3667 | Q85: =C85*($M85/$B85) -> 144.25114 | R85: =D85*($M85/$B85) -> 143.40472 | S85: =E85*($M85/$B85) -> 140.94105 | T85: =F85*($M85/$B85) -> 139.81397 | U85: =G85*($M85/$B85) -> 139.44805 | V85: =H85*($M85/$B85) -> 138.51692 | W85: =I85*($M85/$B85) -> 137.9661 | ... AA85: =M85*($M85/$B85) -> 134.07556 | AC85: 142.9
A86: 2026 | B86: =B85*(Q43*$C43/$C42+AE43*$D43/$D42+AS43*$E43/$E42+BG43*$F43/$F42) -> 148.57273 | C86: =C85*(R43*$C43/$C42+AF43*$D43/$D42+AT43*$E43/$E42+BH43*$F43/$F42) -> 154.92506 | D86: =D85*(S43*$C43/$C42+AG43*$D43/$D42+AU43*$E43/$E42+BI43*$F43/$F42) -> 154.00429 | E86: =E85*(T43*$C43/$C42+AH43*$D43/$D42+AV43*$E43/$E42+BJ43*$F43/$F42) -> 151.35308 | F86: =F85*(U43*$C43/$C42+AI43*$D43/$D42+AW43*$E43/$E42+BK43*$F43/$F42) -> 150.19761 | G86: =G85*(V43*$C43/$C42+AJ43*$D43/$D42+AX43*$E43/$E42+BL43*$F43/$F42) -> 149.77566 | H86: =H85*(W43*$C43/$C42+AK43*$D43/$D42+AY43*$E43/$E42+BM43*$F43/$F42) -> 148.75037 | I86: =I85*(X43*$C43/$C42+AL43*$D43/$D42+AZ43*$E43/$E42+BN43*$F43/$F42) -> 148.16296 | ... L86: =L85*(AA43*$C43/$C42+AO43*$D43/$D42+BC43*$E43/$E42+BQ43*$F43/$F42) -> 145.73868 | M86: =B43 -> 143.8379 | O86: 2026 | P86: =B86*($M86/$B86) -> 143.8379 | Q86: =C86*($M86/$B86) -> 149.98779 | R86: =D86*($M86/$B86) -> 149.09637 | S86: =E86*($M86/$B86) -> 146.52964 | T86: =F86*($M86/$B86) -> 145.411 | U86: =G86*($M86/$B86) -> 145.0025 | V86: =H86*($M86/$B86) -> 144.00988 | W86: =I86*($M86/$B86) -> 143.44119 | ... AA86: =M86*($M86/$B86) -> 139.25396
A88: Deflators rebased to 2015=100 by decile | O88: Deflators %/year | AC88: Range
B89: Total | C89: 0-10 | D89: 11-20 | E89: 21-30 | F89: 31-40 | G89: 41-50 | H89: 51-60 | I89: 61-70 | J89: 71-80 | K89: 81-90 | L89: 91-100 | M89: CPI | P89: Total | Q89: 0-10 | R89: 11-20 | S89: 21-30 | T89: 31-40 | U89: 41-50 | V89: 51-60 | W89: 61-70 | X89: 71-80 | Y89: 81-90 | Z89: 91-100 | AA89: CPI | AD89: Max | AE89: Min | AF89: Diff
A90: 1987 | O90: 1987
A91: 1988 | O91: 1988
A92: 1989 | O92: 1989
A93: 1990 | O93: 1990
A94: 1991 | O94: 1991
A95: 1992 | O95: 1992
A96: 1993 | O96: 1993
A97: 1994 | O97: 1994
A98: 1995 | O98: 1995
A99: 1996 | B99: =100*(P56/P$75) -> 68.810959 | C99: =100*(Q56/Q$75) -> 67.018188 | D99: =100*(R56/R$75) -> 67.037923 | E99: =100*(S56/S$75) -> 67.815646 | F99: =100*(T56/T$75) -> 68.142226 | G99: =100*(U56/U$75) -> 68.263082 | H99: =100*(V56/V$75) -> 68.623654 | I99: =100*(W56/W$75) -> 68.791516 | ... L99: =100*(Z56/Z$75) -> 69.852478 | M99: =100*(B13/B$32) -> 68.810959 | O99: 1996
A100: 1997 | B100: =100*(P57/P$75) -> 70.060855 | C100: =100*(Q57/Q$75) -> 68.050789 | D100: =100*(R57/R$75) -> 68.079114 | E100: =100*(S57/S$75) -> 68.956854 | F100: =100*(T57/T$75) -> 69.346165 | G100: =100*(U57/U$75) -> 69.506529 | H100: =100*(V57/V$75) -> 69.877036 | I100: =100*(W57/W$75) -> 70.066506 | ... L100: =100*(Z57/Z$75) -> 71.150648 | M100: =100*(B14/B$32) -> 70.060855 | O100: 1997 | P100: =100*((B100/B99)-1) -> 1.8164204 | Q100: =100*((C100/C99)-1) -> 1.5407777 | R100: =100*((D100/D99)-1) -> 1.5531379 | S100: =100*((E100/E99)-1) -> 1.6828091 | T100: =100*((F100/F99)-1) -> 1.7668031 | U100: =100*((G100/G99)-1) -> 1.8215514 | V100: =100*((H100/H99)-1) -> 1.8264577 | W100: =100*((I100/I99)-1) -> 1.8534117 | ... AA100: =100*((M100/M99)-1) -> 1.8164204
A101: 1998 | B101: =100*(P58/P$75) -> 71.152424 | C101: =100*(Q58/Q$75) -> 69.019503 | D101: =100*(R58/R$75) -> 69.051593 | E101: =100*(S58/S$75) -> 69.99354 | F101: =100*(T58/T$75) -> 70.415566 | G101: =100*(U58/U$75) -> 70.596074 | H101: =100*(V58/V$75) -> 70.973306 | I101: =100*(W58/W$75) -> 71.174624 | ... L101: =100*(Z58/Z$75) -> 72.26297 | M101: =100*(B15/B$32) -> 71.152424 | O101: 1998 | P101: =100*((B101/B100)-1) -> 1.5580304 | Q101: =100*((C101/C100)-1) -> 1.4235162 | R101: =100*((D101/D100)-1) -> 1.4284534 | S101: =100*((E101/E100)-1) -> 1.5033841 | T101: =100*((F101/F100)-1) -> 1.5421197 | U101: =100*((G101/G100)-1) -> 1.567543 | V101: =100*((H101/H100)-1) -> 1.5688559 | W101: =100*((I101/I100)-1) -> 1.5815226 | ... AA101: =100*((M101/M100)-1) -> 1.5580304
A102: 1999 | B102: =100*(P59/P$75) -> 72.110675 | C102: =100*(Q59/Q$75) -> 69.934455 | D102: =100*(R59/R$75) -> 69.966646 | E102: =100*(S59/S$75) -> 70.952619 | F102: =100*(T59/T$75) -> 71.389942 | G102: =100*(U59/U$75) -> 71.588465 | H102: =100*(V59/V$75) -> 71.937922 | I102: =100*(W59/W$75) -> 72.154549 | ... L102: =100*(Z59/Z$75) -> 73.187274 | M102: =100*(B16/B$32) -> 72.110675 | O102: 1999 | P102: =100*((B102/B101)-1) -> 1.3467573 | Q102: =100*((C102/C101)-1) -> 1.3256429 | R102: =100*((D102/D101)-1) -> 1.3251735 | S102: =100*((E102/E101)-1) -> 1.3702394 | T102: =100*((F102/F101)-1) -> 1.3837506 | U102: =100*((G102/G101)-1) -> 1.4057312 | V102: =100*((H102/H101)-1) -> 1.3591247 | W102: =100*((I102/I101)-1) -> 1.3767897 | ... AA102: =100*((M102/M101)-1) -> 1.3467573
A103: 2000 | B103: =100*(P60/P$75) -> 72.685637 | C103: =100*(Q60/Q$75) -> 70.48106 | D103: =100*(R60/R$75) -> 70.512621 | E103: =100*(S60/S$75) -> 71.551985 | F103: =100*(T60/T$75) -> 72.006354 | G103: =100*(U60/U$75) -> 72.232207 | H103: =100*(V60/V$75) -> 72.524664 | I103: =100*(W60/W$75) -> 72.764578 | ... L103: =100*(Z60/Z$75) -> 73.685251 | M103: =100*(B17/B$32) -> 72.685637 | O103: 2000 | P103: =100*((B103/B102)-1) -> 0.7973331 | Q103: =100*((C103/C102)-1) -> 0.78159565 | R103: =100*((D103/D102)-1) -> 0.78033635 | S103: =100*((E103/E102)-1) -> 0.84474016 | T103: =100*((F103/F102)-1) -> 0.86344456 | U103: =100*((G103/G102)-1) -> 0.89922661 | V103: =100*((H103/H102)-1) -> 0.8156219 | W103: =100*((I103/I102)-1) -> 0.84544856 | ... AA103: =100*((M103/M102)-1) -> 0.7973331
A104: 2001 | B104: =100*(P61/P$75) -> 73.585562 | C104: =100*(Q61/Q$75) -> 71.528314 | D104: =100*(R61/R$75) -> 71.551294 | E104: =100*(S61/S$75) -> 72.53592 | F104: =100*(T61/T$75) -> 72.940309 | G104: =100*(U61/U$75) -> 73.133273 | H104: =100*(V61/V$75) -> 73.422756 | I104: =100*(W61/W$75) -> 73.648412 | ... L104: =100*(Z61/Z$75) -> 74.550496 | M104: =100*(B18/B$32) -> 73.585562 | O104: 2001 | P104: =100*((B104/B103)-1) -> 1.2381061 | Q104: =100*((C104/C103)-1) -> 1.4858661 | R104: =100*((D104/D103)-1) -> 1.4730313 | S104: =100*((E104/E103)-1) -> 1.3751331 | T104: =100*((F104/F103)-1) -> 1.2970452 | U104: =100*((G104/G103)-1) -> 1.2474569 | V104: =100*((H104/H103)-1) -> 1.2383268 | W104: =100*((I104/I103)-1) -> 1.2146481 | ... AA104: =100*((M104/M103)-1) -> 1.2381061
A105: 2002 | B105: =100*(P62/P$75) -> 74.493817 | C105: =100*(Q62/Q$75) -> 72.470301 | D105: =100*(R62/R$75) -> 72.491133 | E105: =100*(S62/S$75) -> 73.453262 | F105: =100*(T62/T$75) -> 73.842402 | G105: =100*(U62/U$75) -> 74.021243 | H105: =100*(V62/V$75) -> 74.324659 | I105: =100*(W62/W$75) -> 74.543226 | ... L105: =100*(Z62/Z$75) -> 75.477241 | M105: =100*(B19/B$32) -> 74.493817 | O105: 2002 | P105: =100*((B105/B104)-1) -> 1.2342837 | Q105: =100*((C105/C104)-1) -> 1.3169429 | R105: =100*((D105/D104)-1) -> 1.313517 | S105: =100*((E105/E104)-1) -> 1.2646726 | T105: =100*((F105/F104)-1) -> 1.2367544 | U105: =100*((G105/G104)-1) -> 1.2141804 | V105: =100*((H105/H104)-1) -> 1.2283704 | W105: =100*((I105/I104)-1) -> 1.2149811 | ... AA105: =100*((M105/M104)-1) -> 1.2342837
A106: 2003 | B106: =100*(P63/P$75) -> 75.518732 | C106: =100*(Q63/Q$75) -> 73.464158 | D106: =100*(R63/R$75) -> 73.491702 | E106: =100*(S63/S$75) -> 74.468803 | F106: =100*(T63/T$75) -> 74.864913 | G106: =100*(U63/U$75) -> 75.044881 | H106: =100*(V63/V$75) -> 75.352324 | I106: =100*(W63/W$75) -> 75.574635 | ... L106: =100*(Z63/Z$75) -> 76.498353 | M106: =100*(B20/B$32) -> 75.518732 | O106: 2003 | P106: =100*((B106/B105)-1) -> 1.3758389 | Q106: =100*((C106/C105)-1) -> 1.3713983 | R106: =100*((D106/D105)-1) -> 1.3802651 | S106: =100*((E106/E105)-1) -> 1.3825686 | T106: =100*((F106/F105)-1) -> 1.3847214 | U106: =100*((G106/G105)-1) -> 1.3828984 | V106: =100*((H106/H105)-1) -> 1.3826704 | W106: =100*((I106/I105)-1) -> 1.3836387 | ... AA106: =100*((M106/M105)-1) -> 1.3758389
A107: 2004 | B107: =100*(P64/P$75) -> 76.535318 | C107: =100*(Q64/Q$75) -> 74.530803 | D107: =100*(R64/R$75) -> 74.538016 | E107: =100*(S64/S$75) -> 75.530569 | F107: =100*(T64/T$75) -> 75.89501 | G107: =100*(U64/U$75) -> 76.075598 | H107: =100*(V64/V$75) -> 76.380144 | I107: =100*(W64/W$75) -> 76.590619 | ... L107: =100*(Z64/Z$75) -> 77.482664 | M107: =100*(B21/B$32) -> 76.535318 | O107: 2004 | P107: =100*((B107/B106)-1) -> 1.346137 | Q107: =100*((C107/C106)-1) -> 1.4519266 | R107: =100*((D107/D106)-1) -> 1.4237172 | S107: =100*((E107/E106)-1) -> 1.4257855 | T107: =100*((F107/F106)-1) -> 1.3759403 | U107: =100*((G107/G106)-1) -> 1.3734668 | V107: =100*((H107/H106)-1) -> 1.3640185 | W107: =100*((I107/I106)-1) -> 1.3443449 | ... AA107: =100*((M107/M106)-1) -> 1.346137
A108: 2005 | B108: =100*(P65/P$75) -> 78.093518 | C108: =100*(Q65/Q$75) -> 76.162599 | D108: =100*(R65/R$75) -> 76.185654 | E108: =100*(S65/S$75) -> 77.146556 | F108: =100*(T65/T$75) -> 77.48149 | G108: =100*(U65/U$75) -> 77.650345 | H108: =100*(V65/V$75) -> 77.956281 | I108: =100*(W65/W$75) -> 78.156078 | ... L108: =100*(Z65/Z$75) -> 78.981976 | M108: =100*(B22/B$32) -> 78.093518 | O108: 2005 | P108: =100*((B108/B107)-1) -> 2.0359237 | Q108: =100*((C108/C107)-1) -> 2.1894243 | R108: =100*((D108/D107)-1) -> 2.2104661 | S108: =100*((E108/E107)-1) -> 2.1395147 | T108: =100*((F108/F107)-1) -> 2.0903617 | U108: =100*((G108/G107)-1) -> 2.0699774 | V108: =100*((H108/H107)-1) -> 2.0635426 | W108: =100*((I108/I107)-1) -> 2.043931 | ... AA108: =100*((M108/M107)-1) -> 2.0359237
A109: 2006 | B109: =100*(P66/P$75) -> 79.926696 | C109: =100*(Q66/Q$75) -> 78.455934 | D109: =100*(R66/R$75) -> 78.431316 | E109: =100*(S66/S$75) -> 79.25024 | F109: =100*(T66/T$75) -> 79.417306 | G109: =100*(U66/U$75) -> 79.588288 | H109: =100*(V66/V$75) -> 79.820511 | I109: =100*(W66/W$75) -> 79.954916 | ... L109: =100*(Z66/Z$75) -> 80.623181 | M109: =100*(B23/B$32) -> 79.926696 | O109: 2006 | P109: =100*((B109/B108)-1) -> 2.3474136 | Q109: =100*((C109/C108)-1) -> 3.0111037 | R109: =100*((D109/D108)-1) -> 2.947618 | S109: =100*((E109/E108)-1) -> 2.7268663 | T109: =100*((F109/F108)-1) -> 2.4984241 | U109: =100*((G109/G108)-1) -> 2.4957297 | V109: =100*((H109/H108)-1) -> 2.3913793 | W109: =100*((I109/I108)-1) -> 2.301597 | ... AA109: =100*((M109/M108)-1) -> 2.3474136
A110: 2007 | B110: =100*(P67/P$75) -> 81.776543 | C110: =100*(Q67/Q$75) -> 80.428206 | D110: =100*(R67/R$75) -> 80.455955 | E110: =100*(S67/S$75) -> 81.204477 | F110: =100*(T67/T$75) -> 81.329264 | G110: =100*(U67/U$75) -> 81.472897 | H110: =100*(V67/V$75) -> 81.674438 | I110: =100*(W67/W$75) -> 81.816362 | ... L110: =100*(Z67/Z$75) -> 82.38685 | M110: =100*(B24/B$32) -> 81.776543 | O110: 2007 | P110: =100*((B110/B109)-1) -> 2.3144288 | Q110: =100*((C110/C109)-1) -> 2.5138605 | R110: =100*((D110/D109)-1) -> 2.5814169 | S110: =100*((E110/E109)-1) -> 2.4659073 | T110: =100*((F110/F109)-1) -> 2.407483 | U110: =100*((G110/G109)-1) -> 2.3679479 | V110: =100*((H110/H109)-1) -> 2.3226197 | W110: =100*((I110/I109)-1) -> 2.3281193 | ... AA110: =100*((M110/M109)-1) -> 2.3144288
...

Sheet Family spending workbook 1
A1: Spending on food & non-alcoholic drinks (COICOP 1) | N1: Food & non-alcoholic drinks share (COICOP 1)
B2: Income deciles | O2: Income deciles
B3: 0-10 | C3: 11-20 | D3: 21-30 | E3: 31-40 | F3: 41-50 | G3: 51-60 | H3: 61-70 | I3: 71-80 | J3: 81-90 | K3: 91-100 | L3: Total | O3: 0-10 | P3: 11-20 | Q3: 21-30 | R3: 31-40 | S3: 41-50 | T3: 51-60 | U3: 61-70 | V3: 71-80 | W3: 81-90 | X3: 91-100 | Y3: Total
A4: 1997 | N4: 1997
A5: 1998 | N5: 1998
A6: 1999 | B6: 25.2 | C6: 31.8 | D6: 38.1 | E6: 46.2 | F6: 52.8 | G6: 62.3 | H6: 68.6 | I6: 78.1 | J6: 87 | K6: 106 | L6: 59.6 | N6: 1999 | O6: =100*(B6/B192) -> 21.052632 | P6: =100*(C6/C192) -> 21.662125 | Q6: =100*(D6/D192) -> 21.392476 | R6: =100*(E6/E192) -> 18.872549 | S6: =100*(F6/F192) -> 17.6 | T6: =100*(G6/G192) -> 17.219458 | U6: =100*(H6/H192) -> 16.614192 | V6: =100*(I6/I192) -> 16.210046 | ... Y6: =100*(L6/L192) -> 16.583194
A7: 2000 | B7: 25.8003 | C7: 33.3712 | D7: 42.1325 | E7: 48.4583 | F7: 56.1025 | G7: 62.9453 | H7: 72.1602 | I7: 79.2868 | J7: 87.608 | K7: 111.3694 | L7: 61.9319 | N7: 2000 | O7: =100*(B7/B193) -> 20.370824 | P7: =100*(C7/C193) -> 21.698438 | Q7: =100*(D7/D193) -> 19.585025 | R7: =100*(E7/E193) -> 18.170354 | S7: =100*(F7/F193) -> 17.051525 | T7: =100*(G7/G193) -> 17.003259 | U7: =100*(H7/H193) -> 16.105541 | V7: =100*(I7/I193) -> 15.842139 | ... Y7: =100*(L7/L193) -> 16.056314
A8: 2001 | B8: 21.6983 | C8: 28.4112 | D8: 32.2724 | E8: 36.3243 | F8: 39.1419 | G8: 41.8181 | H8: 47.2981 | I8: 50.6012 | J8: 56.8294 | K8: 63.3587 | L8: 41.7768 | N8: 2001 | O8: =100*(B8/B194) -> 16.946117 | P8: =100*(C8/C194) -> 16.582996 | Q8: =100*(D8/D194) -> 14.84721 | R8: =100*(E8/E194) -> 12.99966 | S8: =100*(F8/F194) -> 12.155375 | T8: =100*(G8/G194) -> 10.751169 | U8: =100*(H8/H194) -> 10.524167 | V8: =100*(I8/I194) -> 9.551406 | ... Y8: =100*(L8/L194) -> 10.488419
A9: 2002 | B9: 21.2903 | C9: 27.677 | D9: 34.4553 | E9: 36.3305 | F9: 40.1224 | G9: 42.7966 | H9: 48.9623 | I9: 51.9654 | J9: 56.8653 | K9: 66.8872 | L9: 42.7319 | N9: 2002 | O9: =100*(B9/B195) -> 15.704853 | P9: =100*(C9/C195) -> 16.338986 | Q9: =100*(D9/D195) -> 15.702111 | R9: =100*(E9/E195) -> 12.308773 | S9: =100*(F9/F195) -> 11.976307 | T9: =100*(G9/G195) -> 10.687917 | U9: =100*(H9/H195) -> 10.740519 | V9: =100*(I9/I195) -> 9.7301147 | ... Y9: =100*(L9/L195) -> 10.520183
A10: 2003 | B10: 21.3918 | C10: 27.7757 | D10: 34.2269 | E10: 36.517 | F10: 42.365 | G10: 44.7055 | H10: 48.7507 | I10: 51.088 | J10: 60.6381 | K10: 67.7902 | L10: 43.523 | N10: 2003 | O10: =100*(B10/B196) -> 15.32264 | P10: =100*(C10/C196) -> 16.027044 | Q10: =100*(D10/D196) -> 15.265657 | R10: =100*(E10/E196) -> 12.240644 | S10: =100*(F10/F196) -> 11.713357 | T10: =100*(G10/G196) -> 10.866181 | U10: =100*(H10/H196) -> 10.185856 | V10: =100*(I10/I196) -> 9.1684736 | ... Y10: =100*(L10/L196) -> 10.409083
A11: 2004 | B11: 23.4616 | C11: 28.3378 | D11: 35.4956 | E11: 37.1849 | F11: 43.5078 | G11: 46.4173 | H11: 50.2828 | I11: 54.2704 | J11: 60.1617 | K11: 68.2599 | L11: 44.7357 | N11: 2004 | O11: =100*(B11/B197) -> 15.92675 | P11: =100*(C11/C197) -> 15.891258 | Q11: =100*(D11/D197) -> 14.269955 | R11: =100*(E11/E197) -> 11.884906 | S11: =100*(F11/F197) -> 11.65455 | T11: =100*(G11/G197) -> 10.650418 | U11: =100*(H11/H197) -> 10.268439 | V11: =100*(I11/I197) -> 9.5494142 | ... Y11: =100*(L11/L197) -> 10.297638
A12: 2005 | B12: 23.8764 | C12: 29.476 | D12: 34.9736 | E12: 38.2423 | F12: 41.9538 | G12: 46.4429 | H12: 50.1792 | I12: 55.9924 | J12: 60.5438 | K12: 71.4174 | L12: 45.3074 | N12: 2005 | O12: =100*(B12/B198) -> 15.54441 | P12: =100*(C12/C198) -> 16.474089 | Q12: =100*(D12/D198) -> 13.221753 | R12: =100*(E12/E198) -> 12.330339 | S12: =100*(F12/F198) -> 11.76211 | T12: =100*(G12/G198) -> 10.68728 | U12: =100*(H12/H198) -> 10.47476 | V12: =100*(I12/I198) -> 9.5866251 | ... Y12: =100*(L12/L198) -> 10.219289
A13: 2006 | B13: 24.4718 | C13: 31.3798 | D13: 36.6092 | E13: 40.1328 | F13: 44.5828 | G13: 47.3653 | H13: 51.8677 | I13: 57.8086 | J13: 62.7418 | K13: 71.9175 | L13: 46.8881 | N13: 2006 | O13: =100*(B13/B199) -> 15.729622 | P13: =100*(C13/C199) -> 15.708845 | Q13: =100*(D13/D199) -> 13.487698 | R13: =100*(E13/E199) -> 12.053503 | S13: =100*(F13/F199) -> 11.725278 | T13: =100*(G13/G199) -> 10.812504 | U13: =100*(H13/H199) -> 10.232598 | V13: =100*(I13/I199) -> 9.7304216 | ... Y13: =100*(L13/L199) -> 10.285063
A14: 2007 | B14: 24.4619 | C14: 32.3043 | D14: 36.6754 | E14: 41.4896 | F14: 46.8908 | G14: 48.7158 | H14: 55.1925 | I14: 59.3186 | J14: 63.1156 | K14: 73.0916 | L14: 48.1214 | N14: 2007 | O14: =100*(B14/B200) -> 14.190576 | P14: =100*(C14/C200) -> 16.534494 | Q14: =100*(D14/D200) -> 14.086814 | R14: =100*(E14/E200) -> 12.681719 | S14: =100*(F14/F200) -> 11.953321 | T14: =100*(G14/G200) -> 10.618105 | U14: =100*(H14/H200) -> 10.89597 | V14: =100*(I14/I200) -> 9.9061697 | ... Y14: =100*(L14/L200) -> 10.480237
A15: 2008 | B15: 26.4 | C15: 33 | D15: 37.9 | E15: 43.7 | F15: 50.1 | G15: 52.1 | H15: 55.2 | I15: 63.4 | J15: 65.9 | K15: 79.4 | L15: 50.7 | N15: 2008 | O15: =100*(B15/B201) -> 17.176318 | P15: =100*(C15/C201) -> 16.5 | Q15: =100*(D15/D201) -> 14.741346 | R15: =100*(E15/E201) -> 13.238413 | S15: =100*(F15/F201) -> 12.748092 | T15: =100*(G15/G201) -> 11.345819 | U15: =100*(H15/H201) -> 10.285075 | V15: =100*(I15/I201) -> 10.132651 | ... Y15: =100*(L15/L201) -> 10.764331
A16: 2009 | B16: 25.9 | C16: 34.3 | D16: 41.9 | E16: 43.9 | F16: 50.5 | G16: 52.3 | H16: 57.5 | I16: 64.8 | J16: 69.3 | K16: 81.4 | L16: 52.2 | N16: 2009 | O16: =100*(B16/B202) -> 15.918869 | P16: =100*(C16/C202) -> 16.050538 | Q16: =100*(D16/D202) -> 14.926968 | R16: =100*(E16/E202) -> 13.155529 | S16: =100*(F16/F202) -> 13.120291 | T16: =100*(G16/G202) -> 12.042367 | U16: =100*(H16/H202) -> 11.488511 | V16: =100*(I16/I202) -> 11.149346 | ... Y16: =100*(L16/L202) -> 11.472527
A17: 2010 | B17: 27.2 | C17: 34.5 | D17: 40 | E17: 46.1 | F17: 50.7 | G17: 54.4 | H17: 60.9 | I17: 61.2 | J17: 73.7 | K17: 83.4 | L17: 53.2 | N17: 2010 | O17: =100*(B17/B203) -> 14.655172 | P17: =100*(C17/C203) -> 16.061453 | Q17: =100*(D17/D203) -> 14.668133 | R17: =100*(E17/E203) -> 13.385598 | S17: =100*(F17/F203) -> 12.675 | T17: =100*(G17/G203) -> 11.857018 | U17: =100*(H17/H203) -> 11.462451 | V17: =100*(I17/I203) -> 10.358835 | ... Y17: =100*(L17/L203) -> 11.233108
... A21: 2014 | B21: 30.4 | C21: 37.4 | D21: 45.5 | E21: 51.6 | F21: 56.9 | G21: 61.6 | H21: 66.3 | I21: 69.5 | J21: 77.5 | K21: 91 | L21: 58.8 | N21: 2014 | O21: =100*(B21/B207) -> 15.966387 | P21: =100*(C21/C207) -> 14.98998 | Q21: =100*(D21/D207) -> 14.236546 | R21: =100*(E21/E207) -> 13.749001 | S21: =100*(F21/F207) -> 12.789391 | T21: =100*(G21/G207) -> 11.857555 | U21: =100*(H21/H207) -> 11.171019 | V21: =100*(I21/I207) -> 10.13415 | ... Y21: =100*(L21/L207) -> 11.067194
A22: 2015-16 | B22: 29.4 | C22: 37.1 | D22: 43.6 | E22: 49.2 | F22: 53.9 | G22: 57 | H22: 66.5 | I22: 69.2 | J22: 73.6 | K22: 88.8 | L22: 56.8 | N22: 2015-16 | O22: =100*(B22/B208) -> 16.333333 | P22: =100*(C22/C208) -> 14.209115 | Q22: =100*(D22/D208) -> 14.155844 | R22: =100*(E22/E208) -> 13.290113 | S22: =100*(F22/F208) -> 11.654054 | T22: =100*(G22/G208) -> 10.497238 | U22: =100*(H22/H208) -> 11.326861 | V22: =100*(I22/I208) -> 10.456331 | ... Y22: =100*(L22/L208) -> 10.73927
A23: 2016-17 | B23: 28.5 | C23: 37.2 | D23: 44.7 | E23: 52 | F23: 57.3 | G23: 61 | H23: 64.2 | I23: 70.3 | J23: 79.3 | K23: 85.4 | L23: 58 | N23: 2016-17 | O23: =100*(B23/B209) -> 13.754826 | P23: =100*(C23/C209) -> 14.037736 | Q23: =100*(D23/D209) -> 13.256228 | R23: =100*(E23/E209) -> 12.258369 | S23: =100*(F23/F209) -> 11.321873 | T23: =100*(G23/G209) -> 11.024761 | U23: =100*(H23/H209) -> 10.510806 | V23: =100*(I23/I209) -> 10.018526 | ... Y23: =100*(L23/L209) -> 10.465536
A24: 2017-18 | B24: 30.6 | C24: 40 | D24: 48.4 | E24: 52.7 | F24: 56.6 | G24: 63.6 | H24: 67 | I24: 75.2 | J24: 83.2 | K24: 92.9 | L24: 61 | N24: 2017-18 | O24: =100*(B24/B210) -> 14.379699 | P24: =100*(C24/C210) -> 15.077271 | Q24: =100*(D24/D210) -> 13.568825 | R24: =100*(E24/E210) -> 12.452741 | S24: =100*(F24/F210) -> 11.638906 | T24: =100*(G24/G210) -> 10.971192 | U24: =100*(H24/H210) -> 10.42477 | V24: =100*(I24/I210) -> 10.278841 | ... Y24: =100*(L24/L210) -> 10.595796
A25: 2018-19 | B25: 32.8 | C25: 41.1 | D25: 46.3 | E25: 52.1 | F25: 58.2 | G25: 66 | H25: 67 | I25: 73.4 | J25: 83.3 | K25: 98.9 | L25: 61.9 | N25: 2018-19 | O25: =100*(B25/B211) -> 13.845504 | P25: =100*(C25/C211) -> 14.09465 | Q25: =100*(D25/D211) -> 12.800664 | R25: =100*(E25/E211) -> 11.996316 | S25: =100*(F25/F211) -> 11.033175 | T25: =100*(G25/G211) -> 11.205433 | U25: =100*(H25/H211) -> 10.406959 | V25: =100*(I25/I211) -> 9.7554492 | ... Y25: =100*(L25/L211) -> 10.456081
A26: 2019-20 | B26: 34.4 | C26: 41.3 | D26: 48.5 | E26: 54.3 | F26: 61.9 | G26: 64.4 | H26: 74 | I26: 76.9 | J26: 82.6 | K26: 98.7 | L26: 63.7 | N26: 2019-20 | O26: =100*(B26/B212) -> 14.04655 | P26: =100*(C26/C212) -> 14.385232 | Q26: =100*(D26/D212) -> 13.353524 | R26: =100*(E26/E212) -> 12.454128 | S26: =100*(F26/F212) -> 12.017084 | T26: =100*(G26/G212) -> 11.023622 | U26: =100*(H26/H212) -> 11.375865 | V26: =100*(I26/I212) -> 10.093188 | ... Y26: =100*(L26/L212) -> 10.835176
A27: 2020-21 | B27: 36.6 | C27: 42.7 | D27: 55 | E27: 58.8 | F27: 64.2 | G27: 70.2 | H27: 76.2 | I27: 84.3 | J27: 92 | K27: 112.2 | L27: 69.2 | N27: 2020-21 | O27: =100*(B27/B213) -> 18.118812 | P27: =100*(C27/C213) -> 17.045908 | Q27: =100*(D27/D213) -> 15.932793 | R27: =100*(E27/E213) -> 16.891698 | S27: =100*(F27/F213) -> 14.762014 | T27: =100*(G27/G213) -> 14.471243 | U27: =100*(H27/H213) -> 14.796117 | V27: =100*(I27/I213) -> 13.862852 | ... Y27: =100*(L27/L213) -> 14.371755
A28: 2021-22 | B28: 35.3 | C28: 42.4 | D28: 47.9 | E28: 52.3 | F28: 60.4 | G28: 66.9 | H28: 68.8 | I28: 74.3 | J28: 82.7 | K28: 90.9 | L28: 62.2 | N28: 2021-22 | O28: =100*(B28/B214) -> 14.007937 | P28: =100*(C28/C214) -> 14.950635 | Q28: =100*(D28/D214) -> 13.701373 | R28: =100*(E28/E214) -> 12.642011 | S28: =100*(F28/F214) -> 12.351738 | T28: =100*(G28/G214) -> 13.023165 | U28: =100*(H28/H214) -> 12.040602 | V28: =100*(I28/I214) -> 11.238844 | ... Y28: =100*(L28/L214) -> 11.762481
A29: 2022-23 | B29: 35.4 | C29: 45.3 | D29: 50.2 | E29: 57.7 | F29: 64.1 | G29: 70.3 | H29: 67.5 | I29: 75.3 | J29: 80.3 | K29: 88.9 | L29: 63.5 | N29: 2022-23 | O29: =100*(B29/B215) -> 13.516609 | P29: =100*(C29/C215) -> 14.254248 | Q29: =100*(D29/D215) -> 12.419594 | R29: =100*(E29/E215) -> 12.376662 | S29: =100*(F29/F215) -> 12.595795 | T29: =100*(G29/G215) -> 12.20698 | U29: =100*(H29/H215) -> 11.061947 | V29: =100*(I29/I215) -> 10.634091 | ... Y29: =100*(L29/L215) -> 11.185485
A30: 2023-24 | B30: 38.1 | C30: 48.3 | D30: 57 | E30: 62.5 | F30: 68.6 | G30: 71.3 | H30: 76.7 | I30: 88.7 | J30: 93.2 | K30: 100.9 | L30: 70.5 | N30: 2023-24 | O30: =100*(B30/B216) -> 13.340336 | P30: =100*(C30/C216) -> 15.145814 | Q30: =100*(D30/D216) -> 13.396005 | R30: =100*(E30/E216) -> 12.662075 | S30: =100*(F30/F216) -> 11.87262 | T30: =100*(G30/G216) -> 11.725045 | U30: =100*(H30/H216) -> 10.983818 | V30: =100*(I30/I216) -> 11.538962 | ... Y30: =100*(L30/L216) -> 11.310765
A32: Spending on electricity, gas and other fuels (COICOP 4.4) | N32: Housing share (COICOP 4)
B33: Income deciles | O33: Income deciles
B34: 0-10 | C34: 11-20 | D34: 21-30 | E34: 31-40 | F34: 41-50 | G34: 51-60 | H34: 61-70 | I34: 71-80 | J34: 81-90 | K34: 91-100 | L34: Total | O34: 0-10 | P34: 11-20 | Q34: 21-30 | R34: 31-40 | S34: 41-50 | T34: 51-60 | U34: 61-70 | V34: 71-80 | W34: 81-90 | X34: 91-100 | Y34: Total
A35: 1997 | N35: 1997
A36: 1998 | N36: 1998
A37: 1999 | B37: 7.8 | C37: 9.8 | D37: 9.8 | E37: 10.3 | F37: 10.8 | G37: 11.4 | H37: 12.1 | I37: 12.3 | J37: 13.4 | K37: 15.9 | L37: 11.3 | N37: 1999 | O37: =100*(B37/B192) -> 6.5162907 | P37: =100*(C37/C192) -> 6.6757493 | Q37: =100*(D37/D192) -> 5.5025267 | R37: =100*(E37/E192) -> 4.2075163 | S37: =100*(F37/F192) -> 3.6 | T37: =100*(G37/G192) -> 3.1509121 | U37: =100*(H37/H192) -> 2.9304916 | V37: =100*(I37/I192) -> 2.5529265 | ... Y37: =100*(L37/L192) -> 3.1441291
A38: 2000 | B38: 8.6447 | C38: 9.3991 | D38: 11.7925 | E38: 10.563 | F38: 11.1523 | G38: 11.4982 | H38: 12.4779 | I38: 13.3051 | J38: 13.3857 | K38: 16.593 | L38: 11.8819 | N38: 2000 | O38: =100*(B38/B193) -> 6.8254888 | P38: =100*(C38/C193) -> 6.1114312 | Q38: =100*(D38/D193) -> 5.4816687 | R38: =100*(E38/E193) -> 3.9607963 | S38: =100*(F38/F193) -> 3.3895765 | T38: =100*(G38/G193) -> 3.1059805 | U38: =100*(H38/H193) -> 2.7849608 | V38: =100*(I38/I193) -> 2.6584657 | ... Y38: =100*(L38/L193) -> 3.0804725
A39: 2001 | B39: 7.5751 | C39: 9.9067 | D39: 10.0626 | E39: 10.7466 | F39: 11.253 | G39: 11.2126 | H39: 12.5457 | I39: 13.1119 | J39: 14.2492 | K39: 16.5068 | L39: 11.7173 | N39: 2001 | O39: =100*(B39/B194) -> 5.9160641 | P39: =100*(C39/C194) -> 5.7823242 | Q39: =100*(D39/D194) -> 4.6293902 | R39: =100*(E39/E194) -> 3.8459694 | S39: =100*(F39/F194) -> 3.4945783 | T39: =100*(G39/G194) -> 2.8826884 | U39: =100*(H39/H194) -> 2.7915083 | V39: =100*(I39/I194) -> 2.4749824 | ... Y39: =100*(L39/L194) -> 2.9417273
A40: 2002 | B40: 7.6999 | C40: 9.3833 | D40: 9.9909 | E40: 10.7848 | F40: 11.0904 | G40: 12.0001 | H40: 12.344 | I40: 13.2236 | J40: 13.8451 | K40: 16.5636 | L40: 11.6919 | N40: 2002 | O40: =100*(B40/B195) -> 5.6798542 | P40: =100*(C40/C195) -> 5.5393867 | Q40: =100*(D40/D195) -> 4.5530941 | R40: =100*(E40/E195) -> 3.6538901 | S40: =100*(F40/F195) -> 3.3104209 | T40: =100*(G40/G195) -> 2.9968753 | U40: =100*(H40/H195) -> 2.7078174 | V40: =100*(I40/I195) -> 2.4760157 | ... Y40: =100*(L40/L195) -> 2.8784334
A41: 2003 | B41: 7.8614 | C41: 8.8063 | D41: 10.637 | E41: 10.6398 | F41: 11.597 | G41: 12.1791 | H41: 12.6838 | I41: 13.241 | J41: 14.6731 | K41: 17.3998 | L41: 11.9714 | N41: 2003 | O41: =100*(B41/B196) -> 5.6310083 | P41: =100*(C41/C196) -> 5.0813824 | Q41: =100*(D41/D196) -> 4.7442448 | R41: =100*(E41/E196) -> 3.5665035 | S41: =100*(F41/F196) -> 3.2064158 | T41: =100*(G41/G196) -> 2.9602689 | U41: =100*(H41/H196) -> 2.6501233 | V41: =100*(I41/I196) -> 2.3762872 | ... Y41: =100*(L41/L196) -> 2.8631137
A42: 2004 | B42: 8.0565 | C42: 9.4983 | D42: 10.5919 | E42: 11.2004 | F42: 12.1322 | G42: 13.1558 | H42: 13.2551 | I42: 14.5387 | J42: 14.9097 | K42: 18.1627 | L42: 12.5496 | N42: 2004 | O42: =100*(B42/B197) -> 5.4691011 | P42: =100*(C42/C197) -> 5.3264522 | Q42: =100*(D42/D197) -> 4.2581598 | R42: =100*(E42/E197) -> 3.5798322 | S42: =100*(F42/F197) -> 3.2498847 | T42: =100*(G42/G197) -> 3.0185893 | U42: =100*(H42/H197) -> 2.7068736 | V42: =100*(I42/I197) -> 2.5582282 | ... Y42: =100*(L42/L197) -> 2.8887721
A43: 2005 | B43: 8.8767 | C43: 10.088 | D43: 12.3373 | E43: 12.8322 | F43: 13.1509 | G43: 14.2141 | H43: 14.2113 | I43: 15.5194 | J43: 17.1958 | K43: 20.3538 | L43: 13.8774 | N43: 2005 | O43: =100*(B43/B198) -> 5.7790564 | P43: =100*(C43/C198) -> 5.6381669 | Q43: =100*(D43/D198) -> 4.6641105 | R43: =100*(E43/E198) -> 4.1374441 | S43: =100*(F43/F198) -> 3.6869684 | T43: =100*(G43/G198) -> 3.2708996 | U43: =100*(H43/H198) -> 2.9665669 | V43: =100*(I43/I198) -> 2.6571226 | ... Y43: =100*(L43/L198) -> 3.1301102
A44: 2006 | B44: 10.2371 | C44: 12.4512 | D44: 13.9538 | E44: 13.9663 | F44: 15.3861 | G44: 15.9153 | H44: 16.3758 | I44: 18.0075 | J44: 19.6613 | K44: 22.9416 | L44: 15.8898 | N44: 2006 | O44: =100*(B44/B199) -> 6.5800519 | P44: =100*(C44/C199) -> 6.2331171 | Q44: =100*(D44/D199) -> 5.140911 | R44: =100*(E44/E199) -> 4.1946446 | S44: =100*(F44/F199) -> 4.0465447 | T44: =100*(G44/G199) -> 3.6331291 | U44: =100*(H44/H199) -> 3.2306615 | V44: =100*(I44/I199) -> 3.0310467 | ... Y44: =100*(L44/L199) -> 3.4854812
A45: 2007 | B45: 10.9672 | C45: 13.1737 | D45: 13.951 | E45: 15.3546 | F45: 16.3308 | G45: 17.2928 | H45: 18.7673 | I45: 19.5184 | J45: 20.965 | K45: 25.2198 | L45: 17.1528 | N45: 2007 | O45: =100*(B45/B200) -> 6.362175 | P45: =100*(C45/C200) -> 6.7427698 | Q45: =100*(D45/D200) -> 5.3585002 | R45: =100*(E45/E200) -> 4.6932899 | S45: =100*(F45/F200) -> 4.1630192 | T45: =100*(G45/G200) -> 3.7691418 | U45: =100*(H45/H200) -> 3.704995 | V45: =100*(I45/I200) -> 3.2595608 | ... Y45: =100*(L45/L200) -> 3.7356644
A46: 2008 | B46: 12.9 | C46: 14.7 | D46: 15.6 | E46: 17.2 | F46: 17.6 | G46: 18.8 | H46: 19.9 | I46: 21 | J46: 23 | K46: 28.7 | L46: 18.9 | N46: 2008 | O46: =100*(B46/B201) -> 8.3929733 | P46: =100*(C46/C201) -> 7.35 | Q46: =100*(D46/D201) -> 6.0676779 | R46: =100*(E46/E201) -> 5.2105423 | S46: =100*(F46/F201) -> 4.4783715 | T46: =100*(G46/G201) -> 4.0940767 | U46: =100*(H46/H201) -> 3.7078442 | V46: =100*(I46/I201) -> 3.356241 | ... Y46: =100*(L46/L201) -> 4.0127389
A47: 2009 | B47: 13.9 | C47: 16.3 | D47: 17.9 | E47: 19.5 | F47: 19.7 | G47: 21.1 | H47: 23.4 | I47: 25.2 | J47: 25.7 | K47: 29.7 | L47: 21.3 | N47: 2009 | O47: =100*(B47/B202) -> 8.5433313 | P47: =100*(C47/C202) -> 7.6275152 | Q47: =100*(D47/D202) -> 6.3769149 | R47: =100*(E47/E202) -> 5.8435721 | S47: =100*(F47/F202) -> 5.1182125 | T47: =100*(G47/G202) -> 4.8583928 | U47: =100*(H47/H202) -> 4.6753247 | V47: =100*(I47/I202) -> 4.3358568 | ... Y47: =100*(L47/L202) -> 4.6813187
A48: 2010 | B48: 13.5 | C48: 17.1 | D48: 18.7 | E48: 19 | F48: 20.7 | G48: 21.8 | H48: 22.3 | I48: 23.3 | J48: 26 | K48: 31.5 | L48: 21.4 | N48: 2010 | O48: =100*(B48/B203) -> 7.2737069 | P48: =100*(C48/C203) -> 7.9608939 | Q48: =100*(D48/D203) -> 6.8573524 | R48: =100*(E48/E203) -> 5.5168409 | S48: =100*(F48/F203) -> 5.175 | T48: =100*(G48/G203) -> 4.7515257 | U48: =100*(H48/H203) -> 4.197252 | V48: =100*(I48/I203) -> 3.943805 | ... Y48: =100*(L48/L203) -> 4.5185811
... A52: 2014 | B52: 18.7 | C52: 21.7 | D52: 22.3 | E52: 23.5 | F52: 25.3 | G52: 24.8 | H52: 27.4 | I52: 28.5 | J52: 29.8 | K52: 36.4 | L52: 25.8 | N52: 2014 | O52: =100*(B52/B207) -> 9.8214286 | P52: =100*(C52/C207) -> 8.6973948 | Q52: =100*(D52/D207) -> 6.9774718 | R52: =100*(E52/E207) -> 6.2616573 | S52: =100*(F52/F207) -> 5.6866712 | T52: =100*(G52/G207) -> 4.773821 | U52: =100*(H52/H207) -> 4.6166807 | V52: =100*(I52/I207) -> 4.1557305 | ... Y52: =100*(L52/L207) -> 4.8560136
A53: 2015-16 | B53: 17.4 | C53: 20.3 | D53: 21.3 | E53: 21.9 | F53: 22.6 | G53: 22.8 | H53: 23.9 | I53: 24.7 | J53: 26.1 | K53: 31.9 | L53: 23.3 | N53: 2015-16 | O53: =100*(B53/B208) -> 9.6666667 | P53: =100*(C53/C208) -> 7.7747989 | Q53: =100*(D53/D208) -> 6.9155844 | R53: =100*(E53/E208) -> 5.9157212 | S53: =100*(F53/F208) -> 4.8864865 | T53: =100*(G53/G208) -> 4.198895 | U53: =100*(H53/H208) -> 4.0708568 | V53: =100*(I53/I208) -> 3.7322454 | ... Y53: =100*(L53/L208) -> 4.4053696
A54: 2016-17 | B54: 17.8 | C54: 19.9 | D54: 20.1 | E54: 21.3 | F54: 22 | G54: 22.4 | H54: 21.6 | I54: 24.2 | J54: 24.3 | K54: 28.7 | L54: 22.2 | N54: 2016-17 | O54: =100*(B54/B209) -> 8.5907336 | P54: =100*(C54/C209) -> 7.509434 | Q54: =100*(D54/D209) -> 5.9608541 | R54: =100*(E54/E209) -> 5.0212164 | S54: =100*(F54/F209) -> 4.346967 | T54: =100*(G54/G209) -> 4.0484367 | U54: =100*(H54/H209) -> 3.5363458 | V54: =100*(I54/I209) -> 3.4487673 | ... Y54: =100*(L54/L209) -> 4.0057741
A55: 2017-18 | B55: 17.1 | C55: 19.3 | D55: 21 | E55: 22 | F55: 21.9 | G55: 22.6 | H55: 22.3 | I55: 23.4 | J55: 24.8 | K55: 31.4 | L55: 22.6 | N55: 2017-18 | O55: =100*(B55/B210) -> 8.0357143 | P55: =100*(C55/C210) -> 7.2747833 | Q55: =100*(D55/D210) -> 5.8873003 | R55: =100*(E55/E210) -> 5.1984877 | S55: =100*(F55/F210) -> 4.503393 | T55: =100*(G55/G210) -> 3.8985682 | U55: =100*(H55/H210) -> 3.469737 | V55: =100*(I55/I210) -> 3.1984691 | ... Y55: =100*(L55/L210) -> 3.9256557
A56: 2018-19 | B56: 19.1 | C56: 20.6 | D56: 21.5 | E56: 23.5 | F56: 22.9 | G56: 23.9 | H56: 25.5 | I56: 28 | J56: 27.9 | K56: 33.7 | L56: 24.6 | N56: 2018-19 | O56: =100*(B56/B211) -> 8.0624736 | P56: =100*(C56/C211) -> 7.0644719 | Q56: =100*(D56/D211) -> 5.9441526 | R56: =100*(E56/E211) -> 5.4110062 | S56: =100*(F56/F211) -> 4.3412322 | T56: =100*(G56/G211) -> 4.057725 | U56: =100*(H56/H211) -> 3.9608574 | V56: =100*(I56/I211) -> 3.7214248 | ... Y56: =100*(L56/L211) -> 4.1554054
A57: 2019-20 | B57: 18.9 | C57: 21.4 | D57: 22.1 | E57: 24.1 | F57: 23 | G57: 23.5 | H57: 26.6 | I57: 26 | J57: 27 | K57: 32 | L57: 24.5 | N57: 2019-20 | O57: =100*(B57/B212) -> 7.7174357 | P57: =100*(C57/C212) -> 7.4538488 | Q57: =100*(D57/D212) -> 6.0848018 | R57: =100*(E57/E212) -> 5.5275229 | S57: =100*(F57/F212) -> 4.4651524 | T57: =100*(G57/G212) -> 4.022595 | U57: =100*(H57/H212) -> 4.0891622 | V57: =100*(I57/I212) -> 3.4125213 | ... Y57: =100*(L57/L212) -> 4.1673754
A58: 2020-21 | B58: 16.9 | C58: 19.3 | D58: 21.8 | E58: 22.2 | F58: 23.2 | G58: 23.3 | H58: 24.1 | I58: 24.1 | J58: 25.4 | K58: 31.6 | L58: 23.2 | N58: 2020-21 | O58: =100*(B58/B213) -> 8.3663366 | P58: =100*(C58/C213) -> 7.7045908 | Q58: =100*(D58/D213) -> 6.3151796 | R58: =100*(E58/E213) -> 6.3774777 | S58: =100*(F58/F213) -> 5.3345597 | T58: =100*(G58/G213) -> 4.8031334 | U58: =100*(H58/H213) -> 4.6796117 | V58: =100*(I58/I213) -> 3.963164 | ... Y58: =100*(L58/L213) -> 4.8182762
A59: 2021-22 | B59: 20 | C59: 20.7 | D59: 22.3 | E59: 24.4 | F59: 25.7 | G59: 26 | H59: 25.4 | I59: 28.3 | J59: 28.9 | K59: 34.9 | L59: 25.7 | N59: 2021-22 | O59: =100*(B59/B214) -> 7.9365079 | P59: =100*(C59/C214) -> 7.2990127 | Q59: =100*(D59/D214) -> 6.3787185 | R59: =100*(E59/E214) -> 5.8979937 | S59: =100*(F59/F214) -> 5.2556237 | T59: =100*(G59/G214) -> 5.0613198 | U59: =100*(H59/H214) -> 4.4452223 | V59: =100*(I59/I214) -> 4.2807442 | ... Y59: =100*(L59/L214) -> 4.8600605
A60: 2022-23 | B60: 29.2 | C60: 29.6 | D60: 31.9 | E60: 35.4 | F60: 35.9 | G60: 36.2 | H60: 36.5 | I60: 43.4 | J60: 42.3 | K60: 50.6 | L60: 37.1 | N60: 2022-23 | O60: =100*(B60/B215) -> 11.149294 | P60: =100*(C60/C215) -> 9.314034 | Q60: =100*(D60/D215) -> 7.8921326 | R60: =100*(E60/E215) -> 7.5933076 | S60: =100*(F60/F215) -> 7.0544311 | T60: =100*(G60/G215) -> 6.2858135 | U60: =100*(H60/H215) -> 5.9816454 | V60: =100*(I60/I215) -> 6.1290778 | ... Y60: =100*(L60/L215) -> 6.5351418
A61: 2023-24 | B61: 31.1 | C61: 32 | D61: 36.2 | E61: 37.9 | F61: 41.1 | G61: 38.5 | H61: 42.4 | I61: 43.8 | J61: 47.1 | K61: 54.8 | L61: 40.5 | N61: 2023-24 | O61: =100*(B61/B216) -> 10.889356 | P61: =100*(C61/C216) -> 10.034494 | Q61: =100*(D61/D216) -> 8.5076381 | R61: =100*(E61/E216) -> 7.678282 | S61: =100*(F61/F216) -> 7.113188 | T61: =100*(G61/G216) -> 6.3311955 | U61: =100*(H61/H216) -> 6.0718889 | V61: =100*(I61/I216) -> 5.6979316 | ... Y61: =100*(L61/L216) -> 6.4976737
A63: Spending on petrol, diesel and other motor oils (COICOP 7.2.2) | N63: Spending on petrol, diesel and other motor oils (COICOP 7.2.2)
B64: Income deciles | O64: Income deciles
B65: 0-10 | C65: 11-20 | D65: 21-30 | E65: 31-40 | F65: 41-50 | G65: 51-60 | H65: 61-70 | I65: 71-80 | J65: 81-90 | K65: 91-100 | L65: Total | O65: 0-10 | P65: 11-20 | Q65: 21-30 | R65: 31-40 | S65: 41-50 | T65: 51-60 | U65: 61-70 | V65: 71-80 | W65: 81-90 | X65: 91-100 | Y65: Total
A66: 1997 | N66: 1997
A67: 1998 | N67: 1998
A68: 1999 | B68: 2.9 | C68: 4.3 | D68: 5.8 | E68: 8.9 | F68: 12.5 | G68: 15.1 | H68: 18.4 | I68: 21.4 | J68: 24.7 | K68: 29.6 | L68: 14.4 | N68: 1999 | O68: =100*(B68/B192) -> 2.4227235 | P68: =100*(C68/C192) -> 2.9291553 | Q68: =100*(D68/D192) -> 3.2565974 | R68: =100*(E68/E192) -> 3.6356209 | S68: =100*(F68/F192) -> 4.1666667 | T68: =100*(G68/G192) -> 4.1735766 | U68: =100*(H68/H192) -> 4.4562848 | V68: =100*(I68/I192) -> 4.441677 | ... Y68: =100*(L68/L192) -> 4.0066778
A69: 2000 | B69: 2.4362 | C69: 4.2607 | D69: 7.6293 | E69: 9.9221 | F69: 14.3012 | G69: 16.7612 | H69: 20.5523 | I69: 22.803 | J69: 27.0116 | K69: 32.6883 | L69: 15.8396 | N69: 2000 | O69: =100*(B69/B193) -> 1.9235203 | P69: =100*(C69/C193) -> 2.7703689 | Q69: =100*(D69/D193) -> 3.5464316 | R69: =100*(E69/E193) -> 3.7204787 | S69: =100*(F69/F193) -> 4.3466381 | T69: =100*(G69/G193) -> 4.5276617 | U69: =100*(H69/H193) -> 4.587098 | V69: =100*(I69/I193) -> 4.5562224 | ... Y69: =100*(L69/L193) -> 4.1065362
A70: 2001 | B70: 3.1166 | C70: 4.2595 | D70: 7.2476 | E70: 10.6405 | F70: 13.6619 | G70: 14.8505 | H70: 18.4133 | I70: 22.3151 | J70: 23.5129 | K70: 29.5902 | L70: 14.7618 | N70: 2001 | O70: =100*(B70/B194) -> 2.434028 | P70: =100*(C70/C194) -> 2.486177 | Q70: =100*(D70/D194) -> 3.334324 | R70: =100*(E70/E194) -> 3.8079986 | S70: =100*(F70/F194) -> 4.2426535 | T70: =100*(G70/G194) -> 3.8179695 | U70: =100*(H70/H194) -> 4.0970915 | V70: =100*(I70/I194) -> 4.2121645 | ... Y70: =100*(L70/L194) -> 3.7060748
A71: 2002 | B71: 2.9757 | C71: 4.3032 | D71: 6.5121 | E71: 10.7294 | F71: 12.347 | G71: 15.5675 | H71: 18.2428 | I71: 22.3245 | J71: 26.5792 | K71: 28.7836 | L71: 14.8346 | N71: 2002 | O71: =100*(B71/B195) -> 2.195034 | P71: =100*(C71/C195) -> 2.5403737 | Q71: =100*(D71/D195) -> 2.9677211 | R71: =100*(E71/E195) -> 3.6351205 | S71: =100*(F71/F195) -> 3.6855088 | T71: =100*(G71/G195) -> 3.8877889 | U71: =100*(H71/H195) -> 4.0017961 | V71: =100*(I71/I195) -> 4.180088 | ... Y71: =100*(L71/L195) -> 3.6521359
A72: 2003 | B72: 3.3964 | C72: 4.2865 | D72: 6.6229 | E72: 9.9762 | F72: 13.5526 | G72: 15.8541 | H72: 18.215 | I72: 21.4951 | J72: 24.94 | K72: 31.2012 | L72: 14.9527 | N72: 2003 | O72: =100*(B72/B196) -> 2.4327927 | P72: =100*(C72/C196) -> 2.4733822 | Q72: =100*(D72/D196) -> 2.9539023 | R72: =100*(E72/E196) -> 3.3440621 | S72: =100*(F72/F196) -> 3.7471131 | T72: =100*(G72/G196) -> 3.8535195 | U72: =100*(H72/H196) -> 3.8057991 | V72: =100*(I72/I196) -> 3.8576037 | ... Y72: =100*(L72/L196) -> 3.5761298
A73: 2004 | B73: 3.0746 | C73: 4.69 | D73: 7.9741 | E73: 10.9242 | F73: 13.7951 | G73: 17.2044 | H73: 20.2362 | I73: 23.6275 | J73: 26.9985 | K73: 33.3482 | L73: 16.1856 | N73: 2004 | O73: =100*(B73/B197) -> 2.0871716 | P73: =100*(C73/C197) -> 2.630056 | Q73: =100*(D73/D197) -> 3.2057508 | R73: =100*(E73/E197) -> 3.4915541 | S73: =100*(F73/F197) -> 3.6953302 | T73: =100*(G73/G197) -> 3.9475378 | U73: =100*(H73/H197) -> 4.1325102 | V73: =100*(I73/I197) -> 4.1574926 | ... Y73: =100*(L73/L197) -> 3.725737
A74: 2005 | B74: 5.5608 | C74: 8.2836 | D74: 13.0728 | E74: 16.6699 | F74: 23.9534 | G74: 29.7443 | H74: 30.8294 | I74: 42.4096 | J74: 46.5071 | K74: 61.9529 | L74: 27.8958 | N74: 2005 | O74: =100*(B74/B198) -> 3.6202842 | P74: =100*(C74/C198) -> 4.6296907 | Q74: =100*(D74/D198) -> 4.942166 | R74: =100*(E74/E198) -> 5.3748211 | S74: =100*(F74/F198) -> 6.7155425 | T74: =100*(G74/G198) -> 6.8446557 | U74: =100*(H74/H198) -> 6.4355461 | V74: =100*(I74/I198) -> 7.2610736 | ... Y74: =100*(L74/L198) -> 6.2920236
A75: 2006 | B75: 6.4084 | C75: 9.0811 | D75: 15.5751 | E75: 18.8181 | F75: 24.9743 | G75: 28.3055 | H75: 33.5657 | I75: 40.7582 | J75: 47.6113 | K75: 61.1366 | L75: 28.6236 | N75: 2006 | O75: =100*(B75/B199) -> 4.1190967 | P75: =100*(C75/C199) -> 4.5460325 | Q75: =100*(D75/D199) -> 5.7382364 | R75: =100*(E75/E199) -> 5.6518364 | S75: =100*(F75/F199) -> 6.5682415 | T75: =100*(G75/G199) -> 6.4615519 | U75: =100*(H75/H199) -> 6.6219308 | V75: =100*(I75/I199) -> 6.8604752 | ... Y75: =100*(L75/L199) -> 6.2786832
A76: 2007 | B76: 4.6172 | C76: 5.2685 | D76: 8.715 | E76: 12.7792 | F76: 16.5219 | G76: 20.5984 | H76: 24.8468 | I76: 26.4108 | J76: 29.5384 | K76: 33.76 | L76: 18.3028 | N76: 2007 | O76: =100*(B76/B200) -> 2.6784808 | P76: =100*(C76/C200) -> 2.6966063 | Q76: =100*(D76/D200) -> 3.3473822 | R76: =100*(E76/E200) -> 3.9060926 | S76: =100*(F76/F200) -> 4.2117341 | T76: =100*(G76/G200) -> 4.489631 | U76: =100*(H76/H200) -> 4.9051951 | V76: =100*(I76/I200) -> 4.4105874 | ... Y76: =100*(L76/L200) -> 3.98612
A77: 2008 | B77: 4 | C77: 5.7 | D77: 9.3 | E77: 14.1 | F77: 18.6 | G77: 21.3 | H77: 25.8 | I77: 30.1 | J77: 36.5 | K77: 44.9 | L77: 21 | N77: 2008 | O77: =100*(B77/B201) -> 2.6024723 | P77: =100*(C77/C201) -> 2.85 | Q77: =100*(D77/D201) -> 3.6172695 | R77: =100*(E77/E201) -> 4.2714329 | S77: =100*(F77/F201) -> 4.7328244 | T77: =100*(G77/G201) -> 4.6385017 | U77: =100*(H77/H201) -> 4.8071548 | V77: =100*(I77/I201) -> 4.8106121 | ... Y77: =100*(L77/L201) -> 4.4585987
A78: 2009 | B78: 4.7 | C78: 5.6 | D78: 9.9 | E78: 13.4 | F78: 16.1 | G78: 20.2 | H78: 22.9 | I78: 29.9 | J78: 34.2 | K78: 35.6 | L78: 19.2 | N78: 2009 | O78: =100*(B78/B202) -> 2.8887523 | P78: =100*(C78/C202) -> 2.620496 | Q78: =100*(D78/D202) -> 3.526897 | R78: =100*(E78/E202) -> 4.0155829 | S78: =100*(F78/F202) -> 4.1829047 | T78: =100*(G78/G202) -> 4.6511628 | U78: =100*(H78/H202) -> 4.5754246 | V78: =100*(I78/I202) -> 5.1445286 | ... Y78: =100*(L78/L202) -> 4.2197802
A79: 2010 | B79: 5.7 | C79: 7.8 | D79: 10 | E79: 14.3 | F79: 18.8 | G79: 22.7 | H79: 26.6 | I79: 30.7 | J79: 37.4 | K79: 42.3 | L79: 21.6 | N79: 2010 | O79: =100*(B79/B203) -> 3.0711207 | P79: =100*(C79/C203) -> 3.6312849 | Q79: =100*(D79/D203) -> 3.6670334 | R79: =100*(E79/E203) -> 4.1521487 | S79: =100*(F79/F203) -> 4.7 | T79: =100*(G79/G203) -> 4.9476896 | U79: =100*(H79/H203) -> 5.0065876 | V79: =100*(I79/I203) -> 5.1963439 | ... Y79: =100*(L79/L203) -> 4.5608108
... A83: 2014 | B83: 5.7 | C83: 7 | D83: 13.3 | E83: 17 | F83: 23 | G83: 24.5 | H83: 29.1 | I83: 33.3 | J83: 36.7 | K83: 40.5 | L83: 23 | N83: 2014 | O83: =100*(B83/B207) -> 2.9936975 | P83: =100*(C83/C207) -> 2.8056112 | Q83: =100*(D83/D207) -> 4.1614518 | R83: =100*(E83/E207) -> 4.5297096 | S83: =100*(F83/F207) -> 5.1697011 | T83: =100*(G83/G207) -> 4.7160731 | U83: =100*(H83/H207) -> 4.9031171 | V83: =100*(I83/I207) -> 4.855643 | ... Y83: =100*(L83/L207) -> 4.3290043
A84: 2015-16 | B84: 4.1 | C84: 7.3 | D84: 10.7 | E84: 12.8 | F84: 18.1 | G84: 20.6 | H84: 23 | I84: 28.9 | J84: 30.8 | K84: 37.6 | L84: 19.4 | N84: 2015-16 | O84: =100*(B84/B208) -> 2.2777778 | P84: =100*(C84/C208) -> 2.7958637 | Q84: =100*(D84/D208) -> 3.474026 | R84: =100*(E84/E208) -> 3.4575905 | S84: =100*(F84/F208) -> 3.9135135 | T84: =100*(G84/G208) -> 3.7937385 | U84: =100*(H84/H208) -> 3.9175609 | V84: =100*(I84/I208) -> 4.3668782 | ... Y84: =100*(L84/L208) -> 3.6679902
A85: 2016-17 | B85: 5.4 | C85: 8.1 | D85: 11.5 | E85: 15.2 | F85: 20.2 | G85: 22.7 | H85: 24.7 | I85: 30.4 | J85: 32.7 | K85: 36.5 | L85: 20.7 | N85: 2016-17 | O85: =100*(B85/B209) -> 2.6061776 | P85: =100*(C85/C209) -> 3.0566038 | Q85: =100*(D85/D209) -> 3.4104389 | R85: =100*(E85/E209) -> 3.5832155 | S85: =100*(F85/F209) -> 3.9913061 | T85: =100*(G85/G209) -> 4.1026568 | U85: =100*(H85/H209) -> 4.0438769 | V85: =100*(I85/I209) -> 4.3323358 | ... Y85: =100*(L85/L209) -> 3.7351137
A86: 2017-18 | B86: 4.8 | C86: 7.4 | D86: 12.6 | E86: 16.3 | F86: 18.6 | G86: 22.7 | H86: 26.5 | I86: 31 | J86: 36.2 | K86: 39.3 | L86: 21.5 | N86: 2017-18 | O86: =100*(B86/B210) -> 2.2556391 | P86: =100*(C86/C210) -> 2.7892951 | Q86: =100*(D86/D210) -> 3.5323802 | R86: =100*(E86/E210) -> 3.8516068 | S86: =100*(F86/F210) -> 3.8247995 | T86: =100*(G86/G210) -> 3.9158185 | U86: =100*(H86/H210) -> 4.1232301 | V86: =100*(I86/I210) -> 4.2372881 | ... Y86: =100*(L86/L210) -> 3.734584
A87: 2018-19 | B87: 6 | C87: 9.4 | D87: 13.8 | E87: 16.9 | F87: 21.7 | G87: 26.7 | H87: 27.5 | I87: 32.5 | J87: 37.5 | K87: 39.8 | L87: 23.2 | N87: 2018-19 | O87: =100*(B87/B211) -> 2.5327142 | P87: =100*(C87/C211) -> 3.223594 | Q87: =100*(D87/D211) -> 3.8153166 | R87: =100*(E87/E211) -> 3.8913194 | S87: =100*(F87/F211) -> 4.1137441 | T87: =100*(G87/G211) -> 4.533107 | U87: =100*(H87/H211) -> 4.2715129 | V87: =100*(I87/I211) -> 4.3195109 | ... Y87: =100*(L87/L211) -> 3.9189189
A88: 2019-20 | B88: 6.2 | C88: 9.2 | D88: 12.7 | E88: 17.6 | F88: 20.5 | G88: 23.4 | H88: 27 | I88: 35.4 | J88: 33.5 | K88: 37 | L88: 22.3 | N88: 2019-20 | O88: =100*(B88/B212) -> 2.5316456 | P88: =100*(C88/C212) -> 3.2044584 | Q88: =100*(D88/D212) -> 3.496696 | R88: =100*(E88/E212) -> 4.0366972 | S88: =100*(F88/F212) -> 3.9798097 | T88: =100*(G88/G212) -> 4.0054776 | U88: =100*(H88/H212) -> 4.1506533 | V88: =100*(I88/I212) -> 4.646279 | ... Y88: =100*(L88/L212) -> 3.7931621
A89: 2020-21 | B89: 3.1 | C89: 5.4 | D89: 8.2 | E89: 8.7 | F89: 10.5 | G89: 13.4 | H89: 13.9 | I89: 15.2 | J89: 16.2 | K89: 18.2 | L89: 11.3 | N89: 2020-21 | O89: =100*(B89/B213) -> 1.5346535 | P89: =100*(C89/C213) -> 2.1556886 | Q89: =100*(D89/D213) -> 2.3754345 | R89: =100*(E89/E213) -> 2.4992818 | S89: =100*(F89/F213) -> 2.4143481 | T89: =100*(G89/G213) -> 2.762317 | U89: =100*(H89/H213) -> 2.6990291 | V89: =100*(I89/I213) -> 2.4995889 | ... Y89: =100*(L89/L213) -> 2.3468328
A90: 2021-22 | B90: 7.1 | C90: 8.3 | D90: 11.8 | E90: 14.5 | F90: 18.7 | G90: 21 | H90: 22.3 | I90: 25.6 | J90: 28.2 | K90: 31.3 | L90: 18.9 | N90: 2021-22 | O90: =100*(B90/B214) -> 2.8174603 | P90: =100*(C90/C214) -> 2.9266573 | Q90: =100*(D90/D214) -> 3.375286 | R90: =100*(E90/E214) -> 3.5049553 | S90: =100*(F90/F214) -> 3.8241309 | T90: =100*(G90/G214) -> 4.0879891 | U90: =100*(H90/H214) -> 3.9026951 | V90: =100*(I90/I214) -> 3.872334 | ... Y90: =100*(L90/L214) -> 3.5741301
A91: 2022-23 | B91: 6.3 | C91: 10.3 | D91: 16 | E91: 16.3 | F91: 20.1 | G91: 22.3 | H91: 26.1 | I91: 29.8 | J91: 30.6 | K91: 33 | L91: 21.1 | N91: 2022-23 | O91: =100*(B91/B215) -> 2.4054983 | P91: =100*(C91/C215) -> 3.2410321 | Q91: =100*(D91/D215) -> 3.9584364 | R91: =100*(E91/E215) -> 3.4963535 | S91: =100*(F91/F215) -> 3.9496954 | T91: =100*(G91/G215) -> 3.8722 | U91: =100*(H91/H215) -> 4.2772861 | V91: =100*(I91/I215) -> 4.2084451 | ... Y91: =100*(L91/L215) -> 3.7167518
A92: 2023-24 | B92: 7.4 | C92: 8.6 | D92: 12.5 | E92: 17.8 | F92: 19.9 | G92: 20.5 | H92: 24.1 | I92: 26.5 | J92: 30.1 | K92: 30.9 | L92: 19.8 | N92: 2023-24 | O92: =100*(B92/B216) -> 2.5910364 | P92: =100*(C92/C216) -> 2.6967701 | Q92: =100*(D92/D216) -> 2.9377203 | R92: =100*(E92/E216) -> 3.6061588 | S92: =100*(F92/F216) -> 3.4440983 | T92: =100*(G92/G216) -> 3.3711561 | U92: =100*(H92/H216) -> 3.4512387 | V92: =100*(I92/I216) -> 3.4473787 | ... Y92: =100*(L92/L216) -> 3.1766405
A94: Spending on housing (COICOP 4) | N94: Housing share (COICOP 4)
B95: Income deciles | O95: Income deciles
B96: 0-10 | C96: 11-20 | D96: 21-30 | E96: 31-40 | F96: 41-50 | G96: 51-60 | H96: 61-70 | I96: 71-80 | J96: 81-90 | K96: 91-100 | L96: Total | O96: 0-10 | P96: 11-20 | Q96: 21-30 | R96: 31-40 | S96: 41-50 | T96: 51-60 | U96: 61-70 | V96: 71-80 | W96: 81-90 | X96: 91-100 | Y96: Total
A97: 1997 | N97: 1997
A98: 1998 | N98: 1998
A99: 1999 | B99: 19.8 | C99: 23.8 | D99: 29.6 | E99: 42.1 | F99: 50.9 | G99: 57.9 | H99: 66 | I99: 72.5 | J99: 86.7 | K99: 120.8 | L99: 57 | N99: 1999 | O99: =100*(B99/B192) -> 16.541353 | P99: =100*(C99/C192) -> 16.212534 | Q99: =100*(D99/D192) -> 16.619876 | R99: =100*(E99/E192) -> 17.197712 | S99: =100*(F99/F192) -> 16.966667 | T99: =100*(G99/G192) -> 16.003317 | U99: =100*(H99/H192) -> 15.9845 | V99: =100*(I99/I192) -> 15.047738 | ... Y99: =100*(L99/L192) -> 15.859766
A100: 2000 | B100: 21.0032 | C100: 27.5747 | D100: 34.6257 | E100: 47.5363 | F100: 54.3939 | G100: 61.6056 | H100: 73.1431 | I100: 85.157 | J100: 92.8871 | K100: 141.1032 | L100: 63.916 | N100: 2000 | O100: =100*(B100/B193) -> 16.583237 | P100: =100*(C100/C193) -> 17.92947 | Q100: =100*(D100/D193) -> 16.095537 | R100: =100*(E100/E193) -> 17.824633 | S100: =100*(F100/F193) -> 16.532221 | T100: =100*(G100/G193) -> 16.641369 | U100: =100*(H100/H193) -> 16.324916 | V100: =100*(I100/I193) -> 17.015052 | ... Y100: =100*(L100/L193) -> 16.570707
A101: 2001 | B101: 20.5563 | C101: 27.472 | D101: 30.6442 | E101: 31.1975 | F101: 34.8589 | G101: 37.5843 | H101: 37.2358 | I101: 37.6375 | J101: 39.5209 | K101: 62.2719 | L101: 35.8991 | N101: 2001 | O101: =100*(B101/B194) -> 16.054229 | P101: =100*(C101/C194) -> 16.034806 | Q101: =100*(D101/D194) -> 14.098142 | R101: =100*(E101/E194) -> 11.164892 | S101: =100*(F101/F194) -> 10.825305 | T101: =100*(G101/G194) -> 9.6626854 | U101: =100*(H101/H194) -> 8.2852328 | V101: =100*(I101/I194) -> 7.1043976 | ... Y101: =100*(L101/L194) -> 9.0127729
A102: 2002 | B102: 20.8553 | C102: 28.3848 | D102: 29.3293 | E102: 34.8222 | F102: 37.5763 | G102: 38.1193 | H102: 37.1256 | I102: 39.728 | J102: 42.8303 | K102: 60.0212 | L102: 36.8761 | N102: 2002 | O102: =100*(B102/B195) -> 15.383974 | P102: =100*(C102/C195) -> 16.756832 | Q102: =100*(D102/D195) -> 13.36607 | R102: =100*(E102/E195) -> 11.797761 | S102: =100*(F102/F195) -> 11.21631 | T102: =100*(G102/G195) -> 9.5198197 | U102: =100*(H102/H195) -> 8.1439846 | V102: =100*(I102/I195) -> 7.4387573 | ... Y102: =100*(L102/L195) -> 9.0785414
A103: 2003 | B103: 22.8424 | C103: 28.2952 | D103: 31.9078 | E103: 34.9287 | F103: 42.0392 | G103: 43.5711 | H103: 41.4751 | I103: 44.0059 | J103: 42.8051 | K103: 57.994 | L103: 38.9846 | N103: 2003 | O103: =100*(B103/B196) -> 16.361684 | P103: =100*(C103/C196) -> 16.326804 | Q103: =100*(D103/D196) -> 14.231307 | R103: =100*(E103/E196) -> 11.70824 | S103: =100*(F103/F196) -> 11.623278 | T103: =100*(G103/G196) -> 10.590452 | U103: =100*(H103/H196) -> 8.6657096 | V103: =100*(I103/I196) -> 7.8974893 | ... Y103: =100*(L103/L196) -> 9.3236667
A104: 2004 | B104: 23.1578 | C104: 28.2736 | D104: 34.0201 | E104: 40.659 | F104: 39.8392 | G104: 43.5432 | H104: 42.5624 | I104: 42.9784 | J104: 46.5995 | K104: 62.8055 | L104: 40.442 | N104: 2004 | O104: =100*(B104/B197) -> 15.720517 | P104: =100*(C104/C197) -> 15.855256 | Q104: =100*(D104/D197) -> 13.676774 | R104: =100*(E104/E197) -> 12.995286 | S104: =100*(F104/F197) -> 10.671833 | T104: =100*(G104/G197) -> 9.9909574 | U104: =100*(H104/H197) -> 8.6918272 | V104: =100*(I104/I197) -> 7.562475 | ... Y104: =100*(L104/L197) -> 9.3092783
A105: 2005 | B105: 33.1436 | C105: 31.1666 | D105: 39.3093 | E105: 41.499 | F105: 45.1042 | G105: 44.0485 | H105: 45.3595 | I105: 50.4898 | J105: 51.2641 | K105: 60.3114 | L105: 44.1679 | N105: 2005 | O105: =100*(B105/B198) -> 21.577696 | P105: =100*(C105/C198) -> 17.418963 | Q105: =100*(D105/D198) -> 14.860863 | R105: =100*(E105/E198) -> 13.380386 | S105: =100*(F105/F198) -> 12.645352 | T105: =100*(G105/G198) -> 10.136289 | U105: =100*(H105/H198) -> 9.4686615 | V105: =100*(I105/I198) -> 8.6445086 | ... Y105: =100*(L105/L198) -> 9.9622692
A106: 2006 | B106: 32.3161 | C106: 35.2499 | D106: 42.4689 | E106: 43.2967 | F106: 45.4415 | G106: 49.9228 | H106: 48.9111 | I106: 52.5954 | J106: 51.0929 | K106: 74.306 | L106: 47.5611 | N106: 2006 | O106: =100*(B106/B199) -> 20.771665 | P106: =100*(C106/C199) -> 17.646231 | Q106: =100*(D106/D199) -> 15.64655 | R106: =100*(E106/E199) -> 13.00375 | S106: =100*(F106/F199) -> 11.951116 | T106: =100*(G106/G199) -> 11.396328 | U106: =100*(H106/H199) -> 9.6493123 | V106: =100*(I106/I199) -> 8.8529287 | ... Y106: =100*(L106/L199) -> 10.432688
A107: 2007 | B107: 37.9568 | C107: 38.2115 | D107: 42.9851 | E107: 49.6378 | F107: 55.5695 | G107: 59.7447 | H107: 53.9556 | I107: 53.404 | J107: 55.3255 | K107: 71.1713 | L107: 51.794 | N107: 2007 | O107: =100*(B107/B200) -> 22.019094 | P107: =100*(C107/C200) -> 19.558009 | Q107: =100*(D107/D200) -> 16.510334 | R107: =100*(E107/E200) -> 15.172299 | S107: =100*(F107/F200) -> 14.165681 | T107: =100*(G107/G200) -> 13.021966 | U107: =100*(H107/H200) -> 10.651784 | V107: =100*(I107/I200) -> 8.9184352 | ... Y107: =100*(L107/L200) -> 11.280083
A108: 2008 | B108: 36.3 | C108: 38.4 | D108: 47.9 | E108: 51.3 | F108: 53.8 | G108: 55.9 | H108: 57.1 | I108: 63 | J108: 54.8 | K108: 72 | L108: 53 | N108: 2008 | O108: =100*(B108/B201) -> 23.617437 | P108: =100*(C108/C201) -> 19.2 | Q108: =100*(D108/D201) -> 18.630883 | R108: =100*(E108/E201) -> 15.540745 | S108: =100*(F108/F201) -> 13.689567 | T108: =100*(G108/G201) -> 12.173345 | U108: =100*(H108/H201) -> 10.639091 | V108: =100*(I108/I201) -> 10.068723 | ... Y108: =100*(L108/L201) -> 11.252654
A109: 2009 | B109: 37.6 | C109: 44.4 | D109: 51.8 | E109: 59.2 | F109: 57.8 | G109: 59.9 | H109: 58.4 | I109: 63.7 | J109: 63 | K109: 77.2 | L109: 57.3 | N109: 2009 | O109: =100*(B109/B202) -> 23.110018 | P109: =100*(C109/C202) -> 20.77679 | Q109: =100*(D109/D202) -> 18.453865 | R109: =100*(E109/E202) -> 17.740485 | S109: =100*(F109/F202) -> 15.016888 | T109: =100*(G109/G202) -> 13.792309 | U109: =100*(H109/H202) -> 11.668332 | V109: =100*(I109/I202) -> 10.960083 | ... Y109: =100*(L109/L202) -> 12.593407
A110: 2010 | B110: 42.5 | C110: 45.1 | D110: 50.3 | E110: 58.1 | F110: 61.2 | G110: 60.7 | H110: 67.9 | I110: 68.7 | J110: 64.7 | K110: 84.7 | L110: 60.4 | N110: 2010 | O110: =100*(B110/B203) -> 22.898707 | P110: =100*(C110/C203) -> 20.996276 | Q110: =100*(D110/D203) -> 18.445178 | R110: =100*(E110/E203) -> 16.869919 | S110: =100*(F110/F203) -> 15.3 | T110: =100*(G110/G203) -> 13.230166 | U110: =100*(H110/H203) -> 12.779974 | V110: =100*(I110/I203) -> 11.628301 | ... Y110: =100*(L110/L203) -> 12.753378
... A114: 2014 | B114: 46.5 | C114: 56.5 | D114: 62.8 | E114: 68.3 | F114: 72.9 | G114: 80.4 | H114: 75 | I114: 77.4 | J114: 80.4 | K114: 106.4 | L114: 72.7 | N114: 2014 | O114: =100*(B114/B207) -> 24.422269 | P114: =100*(C114/C207) -> 22.645291 | Q114: =100*(D114/D207) -> 19.649562 | R114: =100*(E114/E207) -> 18.198774 | S114: =100*(F114/F207) -> 16.385705 | T114: =100*(G114/G207) -> 15.47642 | U114: =100*(H114/H207) -> 12.6369 | V114: =100*(I114/I207) -> 11.286089 | ... Y114: =100*(L114/L207) -> 13.683418
A115: 2015-16 | B115: 45.2 | C115: 59 | D115: 58.8 | E115: 70.6 | F115: 73.9 | G115: 79.9 | H115: 78.1 | I115: 73 | J115: 86 | K115: 100.3 | L115: 72.5 | N115: 2015-16 | O115: =100*(B115/B208) -> 25.111111 | P115: =100*(C115/C208) -> 22.596706 | Q115: =100*(D115/D208) -> 19.090909 | R115: =100*(E115/E208) -> 19.070773 | S115: =100*(F115/F208) -> 15.978378 | T115: =100*(G115/G208) -> 14.714549 | U115: =100*(H115/H208) -> 13.302674 | V115: =100*(I115/I208) -> 11.030523 | ... Y115: =100*(L115/L208) -> 13.707695
...

Sheet GMWA
A1: Location | B1: Indicator | C1: Scenario | D1: Units | E1: Scale | F1: Measurement | G1: 1973 | H1: 1974 | I1: 1975 | J1: 1976 | K1: 1977 | L1: 1978 | M1: 1979 | N1: 1980 | O1: 1981 | P1: 1982 | Q1: 1983 | R1: 1984 | S1: 1985 | T1: 1986 | U1: 1987 | V1: 1988 | W1: 1989 | X1: 1990 | Y1: 1991 | Z1: 1992 | AA1: 1993 | AB1: 1994 | AC1: 1995 | AD1: 1996 | AE1: 1997 | AF1: 1998 | AG1: 1999 | AH1: 2000 | AI1: 2001 | AJ1: 2002 | AK1: 2003 | AL1: 2004 | AM1: 2005 | AN1: 2006 | AO1: 2007 | AP1: 2008 | AQ1: 2009 | AR1: 2010 | AS1: 2011 | AT1: 2012 | AU1: 2013 | AV1: 2014 | AW1: 2015 | AX1: 2016 | AY1: 2017 | AZ1: 2018 | BA1: 2019 | BB1: 2020 | BC1: 2021 | BD1: 2022 | BE1: 2023 | BF1: 2024 | BG1: 2025 | BH1: 2026 | BI1: 2027 | BJ1: 2028 | BK1: 2029 | BL1: 2030 | BM1: 2031 | BN1: 2032 | BO1: 2033 | BP1: 2034 | BQ1: 2035 | BR1: 2036 | BS1: 2037 | BT1: 2038 | BU1: 2039 | BV1: 2040 | BW1: 2041 | BX1: 2042 | BY1: 2043 | BZ1: 2044 | CA1: 2045 | CB1: 2046 | CC1: 2047 | CD1: 2048 | CE1: 2049 | CF1: 2050 | CG1: 2051 | CH1: 2052 | CI1: 2053 | CJ1: 2054 | CK1: 2055 | CL1: 2056 | CM1: 2057 | CN1: 2058 | CO1: 2059 | CP1: 2060 | CQ1: Source | CR1: Seasonally adjusted | CS1: Base year price | CT1: Base year index | CU1: Historical end year | CV1: Historical end quarter | CW1: Date of last update | CX1: Source details | CY1: Additional source details | CZ1: Location code | DA1: Indicator code | DB1: Databank code
A2: United Kingdom | B2: Consumer price index | C2: MAY013E | D2: Index | E2: 2015=100 | F2: Level | G2: 12.42842 | H2: 14.38361 | I2: 17.64876 | J2: 20.41208 | K2: 23.46216 | L2: 25.2153 | M2: 28.0829 | N2: 32.33867 | O2: 36.15779 | P2: 39.09056 | Q2: 41.01967 | R2: 42.7663 | S2: 44.87138 | T2: 46.36383 | U2: 47.84977 | V2: 49.60834 | W2: 52.21667 | X2: 55.85 | Y2: 60.05833 | Z2: 62.6 | AA2: 64.2 | AB2: 65.47501 | AC2: 67.18333 | AD2: 68.81667 | AE2: 70.06667 | AF2: 71.15833 | AG2: 72.11666 | AH2: 72.69167 | AI2: 73.59167 | AJ2: 74.5 | AK2: 75.525 | AL2: 76.54167 | AM2: 78.1 | AN2: 79.93333 | AO2: 81.78333 | AP2: 84.725 | AQ2: 86.575 | AR2: 89.43333 | AS2: 93.425 | AT2: 96.04167 | AU2: 98.50833 | AV2: 99.95833 | AW2: 100.0083 | AX2: 100.65 | AY2: 103.3584 | AZ2: 105.9167 | BA2: 107.8 | BB2: 108.75 | BC2: 111.5583 | BD2: 121.6583 | BE2: 130.5417 | BF2: 133.8583 | BG2: 138.3667 | BH2: 143.8379 | BI2: 147.9919 | BJ2: 150.7546 | BK2: 153.6561 | BL2: 156.5676 | BM2: 159.6106 | BN2: 162.7771 | BO2: 166.0399 | BP2: 169.3696 | BQ2: 172.756 | BR2: 176.2112 | BS2: 179.7353 | BT2: 183.3301 | BU2: 186.9966 | BV2: 190.7366 | BW2: 194.5513 | BX2: 198.4424 | BY2: 202.4112 | BZ2: 206.4594 | CA2: 210.5886 | CB2: 214.8004 | CC2: 219.0964 | CD2: 223.4783 | CE2: 227.9479 | CF2: 232.5068 | CG2: 237.157 | CH2: 241.9001 | CI2: 246.7381 | CJ2: 251.6729 | CK2: 256.7064 | CL2: 261.8405 | CM2: 267.0773 | CN2: 272.4189 | CO2: 277.8672 | CP2: 283.4245 | CQ2: Office for National Statistics\Haver Analytics | CR2: FALSE | CS2: NA | CT2: 2015 | CU2: 2026 | CV2: 1 | CW2: 46155 | CX2: D7BT@UK | CY2: UK: Consumer Price Index: All Items (NSA, 2015=100) | CZ2: GBR | DA2: CPI | DB2: Desktop
A3: United Kingdom | B3: Fuels & lubricants for transport component of CPI | C3: MAY013E | D3: Index | E3: 2015=100 | F3: Level | G3: 0.001 | H3: 0.001 | I3: 0.001 | J3: 0.001 | K3: 0.001 | L3: 0.001 | M3: 0.001 | N3: 0.001 | O3: 0.001 | P3: 0.001 | Q3: 0.001 | R3: 0.001 | S3: 0.001 | T3: 0.001 | U3: 0.001 | V3: 30.675 | W3: 32.89167 | X3: 36.69167 | Y3: 39.425 | Z3: 40.56667 | AA3: 43.77501 | AB3: 45.775 | AC3: 48.15 | AD3: 50.46667 | AE3: 55.48333 | AF3: 58.25834 | AG3: 63.16667 | AH3: 71.475 | AI3: 67.80833 | AJ3: 65.675 | AK3: 68.05 | AL3: 71.85 | AM3: 78.14166 | AN3: 82.44167 | AO3: 84.83334 | AP3: 97.42498 | AQ3: 89.79167 | AR3: 104.8167 | AS3: 120.1917 | AT3: 122.5333 | AU3: 121.2 | AV3: 115.1416 | AW3: 100 | AX3: 97.61666 | AY3: 105.6 | AZ3: 113.0083 | BA3: 113.4333 | BB3: 103.575 | BC3: 118.1 | BD3: 150.9167 | BE3: 135.0417 | BF3: 128.5167 | BG3: 123.1083 | BH3: 136.9272 | BI3: 125.241 | BJ3: 119.1574 | BK3: 118.0845 | BL3: 119.9965 | BM3: 121.0129 | BN3: 121.8405 | BO3: 122.5892 | BP3: 123.1693 | BQ3: 123.6977 | BR3: 124.2002 | BS3: 124.7048 | BT3: 125.2114 | BU3: 125.72 | BV3: 126.2307 | BW3: 126.7435 | BX3: 127.2584 | BY3: 127.7753 | BZ3: 128.2944 | CA3: 128.8156 | CB3: 129.3389 | CC3: 129.8643 | CD3: 130.3918 | CE3: 130.9215 | CF3: 131.4533 | CG3: 131.9873 | CH3: 132.5235 | CI3: 133.0619 | CJ3: 133.6024 | CK3: 134.1451 | CL3: 134.6901 | CM3: 135.2372 | CN3: 135.7865 | CO3: 136.3382 | CP3: 136.892 | CQ3: Office for National Statistics\Haver Analytics | CR3: FALSE | CS3: NA | CT3: 2015 | CU3: 2026 | CV3: 1 | CW3: 46155 | CX3: D7EC@UK | CY3: UK: Consumer Price Index: Transport Equipment: Fuels & Lubricants(NSA, 2015=100) | CZ3: GBR | DA3: CPITRAFU | DB3: Desktop
A4: United Kingdom | B4: CPI ex Energy, Food, Alcoholic Beverages & Tobacco (core CPI) | C4: MAY013E | D4: Index | E4: 2015=100 | F4: Level | G4: 0.001 | H4: 0.001 | I4: 0.001 | J4: 0.001 | K4: 0.001 | L4: 0.001 | M4: 0.001 | N4: 0.001 | O4: 0.001 | P4: 0.001 | Q4: 0.001 | R4: 0.001 | S4: 0.001 | T4: 0.001 | U4: 0.001 | V4: 54.45 | W4: 57.25 | X4: 60.84999 | Y4: 65.475 | Z4: 68.40834 | AA4: 70.05833 | AB4: 71.23334 | AC4: 72.69167 | AD4: 74.15833 | AE4: 75.55 | AF4: 76.64166 | AG4: 77.20834 | AH4: 77.26666 | AI4: 78.09166 | AJ4: 79.25 | AK4: 80.26666 | AL4: 81.125 | AM4: 82.35 | AN4: 83.44167 | AO4: 84.85 | AP4: 86.225 | AQ4: 87.74166 | AR4: 90.26667 | AS4: 93.16666 | AT4: 95.35 | AU4: 97.325 | AV4: 98.925 | AW4: 100.0083 | AX4: 101.3333 | AY4: 103.75 | AZ4: 105.875 | BA4: 107.725 | BB4: 109.225 | BC4: 111.8417 | BD4: 118.4833 | BE4: 125.775 | BF4: 130.4583 | BG4: 135.0667 | BH4: 140.0791 | BI4: 144.4399 | BJ4: 148.0479 | BK4: 151.4656 | BL4: 154.6895 | BM4: 157.8607 | BN4: 161.0998 | BO4: 164.4358 | BP4: 167.8617 | BQ4: 171.3679 | BR4: 174.9534 | BS4: 178.6022 | BT4: 182.3272 | BU4: 186.1299 | BV4: 190.0118 | BW4: 193.9748 | BX4: 198.0204 | BY4: 202.1503 | BZ4: 206.3664 | CA4: 210.6704 | CB4: 215.0641 | CC4: 219.5496 | CD4: 224.1286 | CE4: 228.8031 | CF4: 233.575 | CG4: 238.4466 | CH4: 243.4197 | CI4: 248.4964 | CJ4: 253.6791 | CK4: 258.9698 | CL4: 264.371 | CM4: 269.8848 | CN4: 275.5137 | CO4: 281.2598 | CP4: 287.1258 | CQ4: Office for National Statistics\Haver Analytics | CR4: FALSE | CS4: NA | CT4: 2015 | CU4: 2026 | CV4: 1 | CW4: 46155 | CX4: DKC6@UK | CY4: UK: CPI: All Items ex Energy, Food, Alcoholic Beverages & Tobacco(NSA, 2015=100) | CZ4: GBR | DA4: CPICORE | DB4: Desktop
A5: United Kingdom | B5: Consumption, private deflator | C5: MAY013E | D5: Index | E5: 2023=100 | F5: Level | G5: 8.885191 | H5: 10.51064 | I5: 12.96881 | J5: 15.10153 | K5: 17.37881 | L5: 19.11831 | M5: 21.75542 | N5: 25.4294 | O5: 28.57231 | P5: 31.20906 | Q5: 33.02437 | R5: 34.77971 | S5: 36.21796 | T5: 37.70331 | U5: 39.33882 | V5: 41.31282 | W5: 43.57815 | X5: 46.90096 | Y5: 50.50714 | Z5: 52.58299 | AA5: 54.2424 | AB5: 55.1663 | AC5: 56.78875 | AD5: 58.7155 | AE5: 59.92178 | AF5: 60.77198 | AG5: 61.1871 | AH5: 61.26581 | AI5: 61.70495 | AJ5: 62.13469 | AK5: 62.91361 | AL5: 64.11768 | AM5: 65.27091 | AN5: 67.19907 | AO5: 68.09623 | AP5: 70.81306 | AQ5: 71.34564 | AR5: 71.97644 | AS5: 74.83904 | AT5: 76.04836 | AU5: 77.71761 | AV5: 78.58492 | AW5: 78.29362 | AX5: 79.28234 | AY5: 80.71116 | AZ5: 82.35863 | BA5: 83.44873 | BB5: 83.47016 | BC5: 85.87554 | BD5: 93.46116 | BE5: 100.0031 | BF5: 102.9905 | BG5: 106.8064 | BH5: 111.0258 | BI5: 114.2297 | BJ5: 116.3638 | BK5: 118.6034 | BL5: 120.8507 | BM5: 123.2483 | BN5: 125.7128 | BO5: 128.2266 | BP5: 130.7906 | BQ5: 133.406 | BR5: 136.0735 | BS5: 138.7945 | BT5: 141.5699 | BU5: 144.4007 | BV5: 147.2882 | BW5: 150.2334 | BX5: 153.2375 | BY5: 156.3017 | BZ5: 159.4271 | CA5: 162.6151 | CB5: 165.8667 | CC5: 169.1835 | CD5: 172.5665 | CE5: 176.0172 | CF5: 179.5368 | CG5: 183.1269 | CH5: 186.7888 | CI5: 190.5238 | CJ5: 194.3336 | CK5: 198.2195 | CL5: 202.1831 | CM5: 206.226 | CN5: 210.3498 | CO5: 214.556 | CP5: 218.8463 | CQ5: Office for National Statistics\Haver Analytics | CR5: TRUE | CS5: NA | CT5: 2023 | CU5: 2025 | CV5: 4 | CW5: 46155 | CX5: Consumption, private, nominal/Consumption, private, real * 100 | CY5: NA | CZ5: GBR | DA5: PC | DB5: Desktop
A6: United Kingdom | B6: Consumption, private, nominal, LCU | C6: MAY013E | D6: Pound | E6: Millions | F6: Level | G6: 48988 | H6: 57233 | I6: 70474 | J6: 82570 | K6: 94811 | L6: 109917 | M6: 130985 | N6: 153233 | O6: 172721 | P6: 190883 | Q6: 210722 | R6: 227316 | S6: 248664 | T6: 274186 | U6: 301124 | V6: 338673 | W6: 370725 | X6: 404573 | Y6: 431907 | Z6: 454101 | AA6: 481753 | AB6: 505949 | AC6: 531875 | AD6: 570493 | AE6: 609948 | AF6: 643770 | AG6: 675819 | AH6: 708151 | AI6: 736985 | AJ6: 762109 | AK6: 797938 | AL6: 835800 | AM6: 873660 | AN6: 906653 | AO6: 951695 | AP6: 980317 | AQ6: 953638 | AR6: 988252 | AS6: 1020931 | AT6: 1058894 | AU6: 1109368 | AV6: 1156436 | AW6: 1187125 | AX6: 1247100 | AY6: 1294413 | AZ6: 1343506 | BA6: 1377461 | BB6: 1203098 | BC6: 1325178 | BD6: 1549599 | BE6: 1652281 | BF6: 1700131 | BG6: 1776885 | BH6: 1853570 | BI6: 1914842 | BJ6: 1977583 | BK6: 2052431 | BL6: 2121032 | BM6: 2191978 | BN6: 2265518 | BO6: 2341464 | BP6: 2421115 | BQ6: 2504039 | BR6: 2589915 | BS6: 2678748 | BT6: 2770708 | BU6: 2865915 | BV6: 2965067 | BW6: 3068116 | BX6: 3174784 | BY6: 3283786 | BZ6: 3393880 | CA6: 3505126 | CB6: 3618765 | CC6: 3735824 | CD6: 3855486 | CE6: 3977853 | CF6: 4102794 | CG6: 4230867 | CH6: 4361720 | CI6: 4495058 | CJ6: 4631692 | CK6: 4771308 | CL6: 4914273 | CM6: 5061211 | CN6: 5212478 | CO6: 5367832 | CP6: 5527898 | CQ6: Office for National Statistics\Haver Analytics | CR6: TRUE | CS6: NA | CT6: NA | CU6: 2025 | CV6: 4 | CW6: 46155 | CX6: ABJQQ@UK | CY6: U.K.: Household Final Consumption Expenditure (SA, Mil.Pounds) | CZ6: GBR | DA6: C! | DB6: Desktop
A7: United Kingdom | B7: Consumption, private, real, LCU | C7: MAY013E | D7: Pound | E7: Millions: chained 2023 prices | F7: Level | G7: 551375 | H7: 544335 | I7: 543607 | J7: 546626 | K7: 545408 | L7: 574834 | M7: 602077 | N7: 602808 | O7: 604520 | P7: 611514 | Q7: 638005 | R7: 653525 | S7: 686449 | T7: 727133 | U7: 765263 | V7: 819586 | W7: 850651 | X7: 862650 | Y7: 855170 | Z7: 863546 | AA7: 888080 | AB7: 917100 | AC7: 936509 | AD7: 971534 | AE7: 1017854 | AF7: 1059254 | AG7: 1104548 | AH7: 1155881 | AI7: 1194415 | AJ7: 1226503 | AK7: 1268258 | AL7: 1303476 | AM7: 1338472 | AN7: 1349155 | AO7: 1397444 | AP7: 1384614 | AQ7: 1336656 | AR7: 1372907 | AS7: 1364172 | AT7: 1392361 | AU7: 1427390 | AV7: 1471584 | AW7: 1516223 | AX7: 1572915 | AY7: 1603724 | AZ7: 1631242 | BA7: 1650664 | BB7: 1441233 | BC7: 1542035 | BD7: 1657618 | BE7: 1652281 | BF7: 1650727 | BG7: 1663641 | BH7: 1669498 | BI7: 1676292 | BJ7: 1699433 | BK7: 1730460 | BL7: 1755050 | BM7: 1778468 | BN7: 1802102 | BO7: 1825999 | BP7: 1851099 | BQ7: 1876966 | BR7: 1903280 | BS7: 1929968 | BT7: 1957089 | BU7: 1984653 | BV7: 2013061 | BW7: 2042187 | BX7: 2071760 | BY7: 2100884 | BZ7: 2128756 | CA7: 2155434 | CB7: 2181690 | CC7: 2208109 | CD7: 2234163 | CE7: 2259884 | CF7: 2285171 | CG7: 2310308 | CH7: 2335070 | CI7: 2359278 | CJ7: 2383336 | CK7: 2407047 | CL7: 2430568 | CM7: 2454169 | CN7: 2477968 | CO7: 2501795 | CP7: 2525890 | CQ7: Office for National Statistics\Haver Analytics | CR7: TRUE | CS7: chained 2023 | CT7: NA | CU7: 2025 | CV7: 4 | CW7: 46155 | CX7: ABJRQ@UK | CY7: U.K.: Household Final Consumption Expenditure (SA, Mil.Chn.2023.GBP) | CZ7: GBR | DA7: C | DB7: Desktop
A8: United Kingdom | B8: Earnings, quarterly total, whole economy, Gross, LCU | C8: MAY013E | D8: Pound per Employee | E8: NA | F8: Level | G8: 443.8228 | H8: 522.59 | I8: 680.2156 | J8: 768.136 | K8: 847.3041 | L8: 962.3206 | M8: 1113.615 | N8: 1341.292 | O8: 1499.111 | P8: 1630.398 | Q8: 1765.725 | R8: 1873.078 | S8: 2033.735 | T8: 2196.167 | U8: 2344.097 | V8: 2544.206 | W8: 2783.697 | X8: 3060.33 | Y8: 3325.865 | Z8: 3484.662 | AA8: 3599.443 | AB8: 3712.438 | AC8: 3821.793 | AD8: 3934.536 | AE8: 4171.854 | AF8: 4293.578 | AG8: 4546.107 | AH8: 4765.2 | AI8: 5033.759 | AJ8: 5116.017 | AK8: 5339.896 | AL8: 5605.391 | AM8: 5797.88 | AN8: 6072.096 | AO8: 6454.834 | AP8: 6535.597 | AQ8: 6546.071 | AR8: 6617.797 | AS8: 6742.713 | AT8: 6807.28 | AU8: 7033.879 | AV8: 7175.158 | AW8: 7261.312 | AX8: 7441.245 | AY8: 7653.613 | AZ8: 7840.839 | BA8: 8057.376 | BB8: 8020.547 | BC8: 8417.898 | BD8: 8937.117 | BE8: 9494.5 | BF8: 9965.352 | BG8: 10414.71 | BH8: 10827.94 | BI8: 11219.16 | BJ8: 11544.3 | BK8: 11847.99 | BL8: 12160.08 | BM8: 12490.43 | BN8: 12849.4 | BO8: 13230.62 | BP8: 13633.08 | BQ8: 14050.9 | BR8: 14482.18 | BS8: 14927.37 | BT8: 15386.96 | BU8: 15861.44 | BV8: 16352.97 | BW8: 16863.58 | BX8: 17390.89 | BY8: 17938.14 | BZ8: 18509.37 | CA8: 19105.48 | CB8: 19723.8 | CC8: 20361.04 | CD8: 21018.88 | CE8: 21698.47 | CF8: 22401.29 | CG8: 23126.4 | CH8: 23873.99 | CI8: 24645.97 | CJ8: 25441.33 | CK8: 26260.74 | CL8: 27104.7 | CM8: 27972.49 | CN8: 28863.89 | CO8: 29780.51 | CP8: 30722.25 | CQ8: Oxford Economics calculation using Office for National Statistics data | CR8: TRUE | CS8: NA | CT8: NA | CU8: 2025 | CV8: 4 | CW8: 46155 | CX8: Oxford Economics calculation using Office for National Statistics data | CY8: NA | CZ8: GBR | DA8: ER | DB8: Desktop
A9: United Kingdom | B9: Employees | C9: MAY013E | D9: Person | E9: Thousands | F9: Level | G9: 22200.85 | H9: 22307.42 | I9: 22183.98 | J9: 22056.64 | K9: 22121.9 | L9: 22269.04 | M9: 22553.8 | N9: 22216.92 | O9: 21309.78 | P9: 20835.84 | Q9: 20624.75 | R9: 20831.11 | S9: 20982.34 | T9: 20962.99 | U9: 21258.47 | V9: 21913.11 | W9: 22346.09 | X9: 22485.16 | Y9: 21891.05 | Z9: 21562.48 | AA9: 21402.75 | AB9: 21525.75 | AC9: 21863.25 | AD9: 22196.25 | AE9: 22742.75 | AF9: 23182.25 | AG9: 23604.25 | AH9: 23976.75 | AI9: 24186.25 | AJ9: 24407 | AK9: 24458.75 | AL9: 24686.75 | AM9: 24997 | AN9: 25195.25 | AO9: 25345 | AP9: 25574 | AQ9: 25092 | AR9: 25016.75 | AS9: 25117.5 | AT9: 25213.25 | AU9: 25513.5 | AV9: 25959.5 | AW9: 26503.5 | AX9: 26771 | AY9: 27065 | AZ9: 27494.25 | BA9: 27781.25 | BB9: 27840.75 | BC9: 28196 | BD9: 28563.75 | BE9: 28820.5 | BF9: 29125.25 | BG9: 29584 | BH9: 29645.35 | BI9: 29724.6 | BJ9: 29991.5 | BK9: 30234.42 | BL9: 30420.38 | BM9: 30596.97 | BN9: 30753.09 | BO9: 30887.08 | BP9: 31011.96 | BQ9: 31140.56 | BR9: 31269.69 | BS9: 31398.82 | BT9: 31527.96 | BU9: 31657.1 | BV9: 31786.23 | BW9: 31916.48 | BX9: 32045.81 | BY9: 32153.21 | BZ9: 32222.51 | CA9: 32258.43 | CB9: 32280.93 | CC9: 32303.88 | CD9: 32315.42 | CE9: 32317.06 | CF9: 32303.29 | CG9: 32283.54 | CH9: 32255.34 | CI9: 32215.54 | CJ9: 32173.21 | CK9: 32124.47 | CL9: 32072.88 | CM9: 32023.7 | CN9: 31978.8 | CO9: 31934.46 | CP9: 31895.24 | CQ9: Office for National Statistics\Haver Analytics | CR9: TRUE | CS9: NA | CT9: NA | CU9: 2025 | CV9: 4 | CW9: 46155 | CX9: MGRNQ@UK | CY9: UK: LFS: Employees (SA, Thous) | CZ9: GBR | DA9: EE | DB9: Desktop
A10: United Kingdom | B10: Energy Component of CPI | C10: MAY013E | D10: Index | E10: 2015=100 | F10: Level | G10: 0.001 | H10: 0.001 | I10: 0.001 | J10: 0.001 | K10: 0.001 | L10: 0.001 | M10: 0.001 | N10: 0.001 | O10: 0.001 | P10: 0.001 | Q10: 0.001 | R10: 0.001 | S10: 0.001 | T10: 0.001 | U10: 0.001 | V10: 30.23333 | W10: 31.88333 | X10: 34.5 | Y10: 37.24167 | Z10: 38.08334 | AA10: 37.58333 | AB10: 39.20833 | AC10: 40.04166 | AD10: 40.2 | AE10: 39.01667 | AF10: 37.38334 | AG10: 37.36666 | AH10: 37.39167 | AI10: 37.58333 | AJ10: 38.425 | AK10: 39.125 | AL10: 41.79166 | AM10: 47.28334 | AN10: 58.96667 | AO10: 63.23333 | AP10: 74.93333 | AQ10: 80.14167 | AR10: 77.90834 | AS10: 85.66666 | AT10: 92.48334 | AU10: 99.12499 | AV10: 103.4417 | AW10: 100 | AX10: 97.05 | AY10: 100.7 | AZ10: 107.5333 | BA10: 111.6083 | BB10: 106.45 | BC10: 111.4583 | BD10: 183.6417 | BE10: 211.9667 | BF10: 172.2417 | BG10: 174.9167 | BH10: 184.185 | BI10: 183.0643 | BJ10: 164.0671 | BK10: 159.7159 | BL10: 158.1852 | BM10: 162.7164 | BN10: 169.2467 | BO10: 176.228 | BP10: 183.112 | BQ10: 189.7512 | BR10: 196.5147 | BS10: 203.5193 | BT10: 210.7737 | BU10: 218.2865 | BV10: 226.0672 | BW10: 234.1252 | BX10: 242.4704 | BY10: 251.113 | BZ10: 260.0638 | CA10: 269.3336 | CB10: 278.9337 | CC10: 288.8761 | CD10: 299.1729 | CE10: 309.8367 | CF10: 320.8806 | CG10: 332.3181 | CH10: 344.1634 | CI10: 356.4308 | CJ10: 369.1355 | CK10: 382.2931 | CL10: 395.9196 | CM10: 410.0319 | CN10: 424.6472 | CO10: 439.7834 | CP10: 455.4591 | CQ10: Office for National Statistics / Haver Analytics | CR10: FALSE | CS10: NA | CT10: 2015 | CU10: 2026 | CV10: 1 | CW10: 46155 | CX10: D7CH@UK | CY10: UK: Consumer Price Index: Housing: Electricity, Gas & Other Fuels(NSA, 2015=100) | CZ10: GBR | DA10: CPIEN | DB10: Desktop
A11: United Kingdom | B11: Food component of CPI | C11: MAY013E | D11: Index | E11: 2015=100 | F11: Level | G11: 0.001 | H11: 0.001 | I11: 0.001 | J11: 0.001 | K11: 0.001 | L11: 0.001 | M11: 0.001 | N11: 0.001 | O11: 0.001 | P11: 0.001 | Q11: 0.001 | R11: 0.001 | S11: 0.001 | T11: 0.001 | U11: 0.001 | V11: 41.15833 | W11: 43.24167 | X11: 46.64167 | Y11: 50.05 | Z11: 52.05 | AA11: 53.61667 | AB11: 54.64167 | AC11: 56.875 | AD11: 58.90833 | AE11: 59.60833 | AF11: 61.06666 | AG11: 62.375 | AH11: 63.075 | AI11: 65.36667 | AJ11: 66.09167 | AK11: 67.01667 | AL11: 67.73334 | AM11: 68.9 | AN11: 70.66666 | AO11: 73.65833 | AP11: 79.225 | AQ11: 83.325 | AR11: 86.625 | AS11: 92.10001 | AT11: 95.8 | AU11: 100.1417 | AV11: 101.275 | AW11: 99.99998 | AX11: 98.725 | AY11: 101.5333 | AZ11: 104.3083 | BA11: 106.3667 | BB11: 107.5083 | BC11: 108.525 | BD11: 118.2917 | BE11: 133.5667 | BF11: 138.875 | BG11: 145.1667 | BH11: 150.3771 | BI11: 157.2108 | BJ11: 160.7712 | BK11: 162.8925 | BL11: 165.0051 | BM11: 167.2475 | BN11: 169.6005 | BO11: 172.0312 | BP11: 174.5139 | BQ11: 177.0328 | BR11: 179.5859 | BS11: 182.1758 | BT11: 184.8029 | BU11: 187.468 | BV11: 190.1716 | BW11: 192.9141 | BX11: 195.6962 | BY11: 198.5183 | BZ11: 201.3812 | CA11: 204.2854 | CB11: 207.2314 | CC11: 210.22 | CD11: 213.2516 | CE11: 216.3269 | CF11: 219.4467 | CG11: 222.6114 | CH11: 225.8217 | CI11: 229.0784 | CJ11: 232.382 | CK11: 235.7332 | CL11: 239.1328 | CM11: 242.5813 | CN11: 246.0797 | CO11: 249.6284 | CP11: 253.2284 | CQ11: Office for National Statistics / Haver Analytics | CR11: FALSE | CS11: NA | CT11: 2015 | CU11: 2026 | CV11: 1 | CW11: 46155 | CX11: DK9O@UK | CY11: UK: CPI: Food, Alcoholic Beverages & Tobacco (NSA, 2015=100) | CZ11: GBR | DA11: CPIFD | DB11: Desktop
A12: United Kingdom | B12: GDP, real, LCU | C12: MAY013E | D12: Pound | E12: Millions: chained 2023 prices | F12: Level | G12: 1063550 | H12: 1036973 | I12: 1021204 | J12: 1051973 | K12: 1077816 | L12: 1122953 | M12: 1164860 | N12: 1140989 | O12: 1134663 | P12: 1157191 | Q12: 1205632 | R12: 1232675 | S12: 1283200 | T12: 1323173 | U12: 1395353 | V12: 1471002 | W12: 1506644 | X12: 1515202 | Y12: 1493903 | Z12: 1498023 | AA12: 1532082 | AB12: 1584459 | AC12: 1622576 | AD12: 1665005 | AE12: 1746257 | AF12: 1802946 | AG12: 1856033 | AH12: 1940007 | AI12: 1986393 | AJ12: 2020341 | AK12: 2085366 | AL12: 2133872 | AM12: 2193421 | AN12: 2241453 | AO12: 2307148 | AP12: 2306008 | AQ12: 2200222 | AR12: 2249959 | AS12: 2269116 | AT12: 2303794 | AU12: 2343384 | AV12: 2417439 | AW12: 2469182 | AX12: 2523665 | AY12: 2599961 | AZ12: 2640295 | BA12: 2673465 | BB12: 2404838 | BC12: 2610286 | BD12: 2744708 | BE12: 2752164 | BF12: 2781895 | BG12: 2820520 | BH12: 2838512 | BI12: 2860532 | BJ12: 2909994 | BK12: 2959876 | BL12: 3002989 | BM12: 3046656 | BN12: 3090264 | BO12: 3133231 | BP12: 3177630 | BQ12: 3223384 | BR12: 3270088 | BS12: 3317569 | BT12: 3365837 | BU12: 3414918 | BV12: 3465496 | BW12: 3517360 | BX12: 3570045 | BY12: 3622006 | BZ12: 3671858 | CA12: 3719699 | CB12: 3766856 | CC12: 3814342 | CD12: 3861242 | CE12: 3907611 | CF12: 3952918 | CG12: 3997789 | CH12: 4042041 | CI12: 4085362 | CJ12: 4128453 | CK12: 4170974 | CL12: 4213194 | CM12: 4255581 | CN12: 4298342 | CO12: 4341179 | CP12: 4384511 | CQ12: Office for National Statistics\Haver Analytics | CR12: TRUE | CS12: chained 2023 | CT12: NA | CU12: 2025 | CV12: 4 | CW12: 46155 | CX12: ABMIQ@UK | CY12: U.K.: Real Gross Domestic Product (SA, Mil.Chn.2023.GBP) | CZ12: GBR | DA12: GDP | DB12: Desktop
A13: United Kingdom | B13: Income, personal disposable, nominal, LCU | C13: MAY013E | D13: Pound | E13: Millions | F13: Level | G13: 52440 | H13: 61574 | I13: 76596 | J13: 89178 | K13: 100757 | L13: 118851 | M13: 143308 | N13: 170398 | O13: 191360 | P13: 209806 | Q13: 226997 | R13: 247814 | S13: 269034 | T13: 292095 | U13: 308544 | V13: 341617 | W13: 379456 | X13: 424197 | Y13: 465139 | Z13: 496994 | AA13: 527363 | AB13: 546235 | AC13: 579311 | AD13: 615831 | AE13: 640021 | AF13: 654745 | AG13: 688023 | AH13: 728537 | AI13: 761188 | AJ13: 785771 | AK13: 814318 | AL13: 853679 | AM13: 892146 | AN13: 936606 | AO13: 989024 | AP13: 1024014 | AQ13: 1050092 | AR13: 1070069 | AS13: 1084990 | AT13: 1130017 | AU13: 1175937 | AV13: 1217891 | AW13: 1287116 | AX13: 1312733 | AY13: 1348375 | AZ13: 1402614 | BA13: 1456540 | BB13: 1454341 | BC13: 1519777 | BD13: 1613529 | BE13: 1740150 | BF13: 1863165 | BG13: 1950418 | BH13: 2023422 | BI13: 2087289 | BJ13: 2162079 | BK13: 2242304 | BL13: 2315441 | BM13: 2393350 | BN13: 2476248 | BO13: 2558837 | BP13: 2645641 | BQ13: 2735936 | BR13: 2829028 | BS13: 2926137 | BT13: 3026665 | BU13: 3130740 | BV13: 3238877 | BW13: 3351490 | BX13: 3468218 | BY13: 3587917 | BZ13: 3709050 | CA13: 3831292 | CB13: 3955782 | CC13: 4083997 | CD13: 4215208 | CE13: 4349458 | CF13: 4486396 | CG13: 4626836 | CH13: 4770446 | CI13: 4916729 | CJ13: 5066546 | CK13: 5219690 | CL13: 5376386 | CM13: 5537296 | CN13: 5702985 | CO13: 5873131 | CP13: 6048411 | CQ13: Office for National Statistics\Haver Analytics | CR13: TRUE | CS13: NA | CT13: NA | CU13: 2025 | CV13: 4 | CW13: 46155 | CX13: RPHQQ@UK | CY13: UK: HH & NPISH: Gross Disposable Income (SA, Mil.GBP) | CZ13: GBR | DA13: PEDY! | DB13: Desktop
A14: United Kingdom | B14: Income, personal disposable, real, LCU | C14: MAY013E | D14: Pound | E14: Millions: chained 2023 prices | F14: Level | G14: 600127 | H14: 595007 | I14: 599956 | J14: 599113 | K14: 588180 | L14: 631121 | M14: 668934 | N14: 680140 | O14: 679707 | P14: 682582 | Q14: 697850 | R14: 723364 | S14: 753842 | T14: 784877 | U14: 794123 | V14: 837202 | W14: 880745 | X14: 915377 | Y14: 934194 | Z14: 959658 | AA14: 984991 | AB14: 1003216 | AC14: 1033438 | AD14: 1061145 | AE14: 1082261 | AF14: 1091321 | AG14: 1138283 | AH14: 1202414 | AI14: 1245868 | AJ14: 1275228 | AK14: 1303644 | AL14: 1340203 | AM14: 1373808 | AN14: 1398855 | AO14: 1455734 | AP14: 1448377 | AQ14: 1471733 | AR14: 1486258 | AS14: 1450518 | AT14: 1486025 | AU14: 1512963 | AV14: 1548542 | AW14: 1642001 | AX14: 1653979 | AY14: 1669528 | AZ14: 1702200 | BA14: 1742944 | BB14: 1733465 | BC14: 1762861 | BD14: 1725226 | BE14: 1740150 | BF14: 1808439 | BG14: 1828770 | BH14: 1825287 | BI14: 1829884 | BJ14: 1860584 | BK14: 1893104 | BL14: 1918424 | BM14: 1944303 | BN14: 1972135 | BO14: 1997880 | BP14: 2025079 | BQ14: 2053060 | BR14: 2081221 | BS14: 2110385 | BT14: 2140020 | BU14: 2170138 | BV14: 2201010 | BW14: 2232818 | BX14: 2265219 | BY14: 2297393 | BZ14: 2328336 | CA14: 2357866 | CB14: 2386695 | CC14: 2415689 | CD14: 2444367 | CE14: 2472718 | CF14: 2500515 | CG14: 2528184 | CH14: 2555504 | CI14: 2582185 | CJ14: 2608656 | CK14: 2634774 | CL14: 2660624 | CM14: 2686489 | CN14: 2712590 | CO14: 2738712 | CP14: 2765114 | CQ14: Office for National Statistics\Haver Analytics | CR14: TRUE | CS14: chained 2023 | CT14: NA | CU14: 2025 | CV14: 4 | CW14: 46155 | CX14: NRJRQ@UK | CY14: UK: HH & NPISH: Real Household Disposable Income (SA, Mil.Chn.2023.Pounds) | CZ14: GBR | DA14: PEDY | DB14: Desktop
