Workbook
Name \A: #REF!
Name \B: #REF!
Name \e: #REF!
Name \I: #REF!
Name \l: #REF!
Name \P: #REF!
Name \Q: #REF!
Name \S: #REF!
Name \T: #REF!
Name \UPDATE: #REF!
Name \Z: #REF!
Name ________tab6: !#REF!
Name ________tab8: !#REF!
Name _______tab3: !#REF!
Name _______tab6: !#REF!
Name _______tab8: !#REF!
Name ______tab3: !#REF!
Name ______tab6: !#REF!
Name ______tab8: !#REF!
Name _____PC1: #REF!
Name _____tab3: !#REF!
Name _____tab6: !#REF!
Name _____tab8: !#REF!
Name ____tab3: !#REF!
Name ____tab6: !#REF!
Name ____tab8: !#REF!
Name ___05MAY11: #REF!
Name ___20MAY11: #REF!
Name ___21MAY11: #REF!
Name ___PC1: #REF!
Name ___tab3: !#REF!
Name ___tab6: !#REF!
Name ___tab8: !#REF!
Name __05MAY11: #REF!
Name __20MAY11: #REF!
Name __21MAY11: #REF!
Name __PBR1: #REF!
Name __PBR2: #REF!
Name __PBR3: #REF!
Name __PBR4: #REF!
Name __PBR5: #REF!
Name __PBR6: #REF!
Name __PBR7: #REF!
Name __PBR8: #REF!
Name __PC1: #REF!
Name __pop: #REF!
Name __tab3: !#REF!
Name __tab6: !#REF!
Name __tab8: !#REF!
Name __Territ: #REF!
Name _05MAY11: #REF!
Name _1_: #REF!
Name _1_0: #REF!
Name _1_05MAY11: #REF!
Name _1377_0: #REF!
Name _1395_0: #REF!
Name _1396_0: #REF!
Name _2_: #REF!
Name _2_0: #REF!
Name _2_20MAY11: #REF!

Sheet Chart Data
A1: Inflation forecasts | H1: Bank Rate forecasts
B2: BoE Scenario A | C2: BoE Scenario B | D2: BoE Scenario C | E2: Oxford Economics baseline | F2: Oxford Economics prolonged war | I2: BoE Scenario A | J2: BoE Scenario B | K2: BoE Scenario C | L2: Oxford Economics baseline | M2: Oxford Economics prolonged war
A3: 2025 | B3: =100*((GMW!C215/GMW!C211)-1) -> 2.7973783 | H3: 2025 | I3: =GMW!D215 -> 4.601563
B4: =100*((GMW!C216/GMW!C212)-1) -> 3.4869498 | I4: =GMW!D216 -> 4.353846
B5: =100*((GMW!C217/GMW!C213)-1) -> 3.803132 | I5: =GMW!D217 -> 4.102273
B6: =100*((GMW!C218/GMW!C214)-1) -> 3.3769049 | I6: =GMW!D218 -> 3.962121
A7: 2026 | B7: =100*((GMW!C219/GMW!C215)-1) -> 3.1134829 | C7: =$E7 -> 3.1134829 | D7: =$E7 -> 3.1134829 | E7: =100*((GMW!C219/GMW!C215)-1) -> 3.1134829 | F7: =100*((GMW!F219/GMW!F215)-1) -> 3.1134829 | H7: 2026 | I7: =GMW!D219 -> 3.75 | J7: =$E7 -> 3.1134829 | K7: =$E7 -> 3.1134829 | L7: =GMW!D219 -> 3.75 | M7: =GMW!G219 -> 3.75
B8: ='MPR 2. CPI inflation'!C119 -> 3.1 | C8: ='MPR 2. CPI inflation'!D119 -> 3.1 | D8: ='MPR 2. CPI inflation'!E119 -> 3.6 | E8: =100*((GMW!C220/GMW!C216)-1) -> 3.7575451 | F8: =100*((GMW!F220/GMW!F216)-1) -> 4.2948014 | I8: ='MPR Chart G.1'!E12 -> 4.014 | J8: ='MPR Chart G.1'!I12 -> 4.025 | K8: ='MPR Chart G.1'!M12 -> 4.384 | L8: =GMW!D220 -> 3.75 | M8: =GMW!G220 -> 4.000007
B9: ='MPR 2. CPI inflation'!C120 -> 3.3 | C9: ='MPR 2. CPI inflation'!D120 -> 3.3 | D9: ='MPR 2. CPI inflation'!E120 -> 5.2 | E9: =100*((GMW!C221/GMW!C217)-1) -> 4.498204 | F9: =100*((GMW!F221/GMW!F217)-1) -> 6.510704 | I9: ='MPR Chart G.1'!E13 -> 4.184 | J9: ='MPR Chart G.1'!I13 -> 4.224 | K9: ='MPR Chart G.1'!M13 -> 4.877 | L9: =GMW!D221 -> 3.75 | M9: =GMW!G221 -> 4.500035
B10: ='MPR 2. CPI inflation'!C121 -> 3.6 | C10: ='MPR 2. CPI inflation'!D121 -> 3.7 | D10: ='MPR 2. CPI inflation'!E121 -> 6 | E10: =100*((GMW!C222/GMW!C218)-1) -> 4.4854793 | F10: =100*((GMW!F222/GMW!F218)-1) -> 8.7109442 | I10: ='MPR Chart G.1'!E14 -> 4.248 | J10: ='MPR Chart G.1'!I14 -> 4.336 | K10: ='MPR Chart G.1'!M14 -> 5.183 | L10: =GMW!D222 -> 3.75 | M10: =GMW!G222 -> 4.750074
A11: 2027 | B11: ='MPR 2. CPI inflation'!C122 -> 3.4 | C11: ='MPR 2. CPI inflation'!D122 -> 3.6 | D11: ='MPR 2. CPI inflation'!E122 -> 6.2 | E11: =100*((GMW!C223/GMW!C219)-1) -> 4.2426534 | F11: =100*((GMW!F223/GMW!F219)-1) -> 8.4708274 | H11: 2027 | I11: ='MPR Chart G.1'!E15 -> 4.213 | J11: ='MPR Chart G.1'!I15 -> 4.36 | K11: ='MPR Chart G.1'!M15 -> 5.316 | L11: =GMW!D223 -> 3.75 | M11: =GMW!G223 -> 4.750141
B12: ='MPR 2. CPI inflation'!C123 -> 2.9 | C12: ='MPR 2. CPI inflation'!D123 -> 3.2 | D12: ='MPR 2. CPI inflation'!E123 -> 5.6 | E12: =100*((GMW!C224/GMW!C220)-1) -> 2.847168 | F12: =100*((GMW!F224/GMW!F220)-1) -> 6.16802 | I12: ='MPR Chart G.1'!E16 -> 4.11 | J12: ='MPR Chart G.1'!I16 -> 4.32 | K12: ='MPR Chart G.1'!M16 -> 5.317 | L12: =GMW!D224 -> 3.75 | M12: =GMW!G224 -> 4.750249
B13: ='MPR 2. CPI inflation'!C124 -> 2.3 | C13: ='MPR 2. CPI inflation'!D124 -> 2.8 | D13: ='MPR 2. CPI inflation'!E124 -> 4.1 | E13: =100*((GMW!C225/GMW!C221)-1) -> 2.0318091 | F13: =100*((GMW!F225/GMW!F221)-1) -> 3.7987926 | I13: ='MPR Chart G.1'!E17 -> 3.979 | J13: ='MPR Chart G.1'!I17 -> 4.244 | K13: ='MPR Chart G.1'!M17 -> 5.24 | L13: =GMW!D225 -> 3.75 | M13: =GMW!G225 -> 4.750368
B14: ='MPR 2. CPI inflation'!C125 -> 1.7 | C14: ='MPR 2. CPI inflation'!D125 -> 2.3 | D14: ='MPR 2. CPI inflation'!E125 -> 3.5 | E14: =100*((GMW!C226/GMW!C222)-1) -> 1.975824 | F14: =100*((GMW!F226/GMW!F222)-1) -> 1.6273419 | I14: ='MPR Chart G.1'!E18 -> 3.848 | J14: ='MPR Chart G.1'!I18 -> 4.158 | K14: ='MPR Chart G.1'!M18 -> 5.135 | L14: =GMW!D226 -> 3.590909 | M14: =GMW!G226 -> 4.341372
A15: 2028 | B15: ='MPR 2. CPI inflation'!C126 -> 1.4 | C15: ='MPR 2. CPI inflation'!D126 -> 2 | D15: ='MPR 2. CPI inflation'!E126 -> 3 | E15: =100*((GMW!C227/GMW!C223)-1) -> 2.036905 | F15: =100*((GMW!F227/GMW!F223)-1) -> 1.6396396 | H15: 2028 | I15: ='MPR Chart G.1'!E19 -> 3.736 | J15: ='MPR Chart G.1'!I19 -> 4.077 | K15: ='MPR Chart G.1'!M19 -> 5.021 | L15: =GMW!D227 -> 3.338462 | M15: =GMW!G227 -> 4.088992
B16: ='MPR 2. CPI inflation'!C127 -> 1.5 | C16: ='MPR 2. CPI inflation'!D127 -> 2 | D16: ='MPR 2. CPI inflation'!E127 -> 2.9 | E16: =100*((GMW!C228/GMW!C224)-1) -> 1.7474798 | F16: =100*((GMW!F228/GMW!F224)-1) -> 1.5830942 | I16: ='MPR Chart G.1'!E20 -> 3.646 | J16: ='MPR Chart G.1'!I20 -> 4.006 | K16: ='MPR Chart G.1'!M20 -> 4.908 | L16: =GMW!D228 -> 3.088462 | M16: =GMW!G228 -> 3.83901
B17: ='MPR 2. CPI inflation'!C128 -> 1.6 | C17: ='MPR 2. CPI inflation'!D128 -> 2 | D17: ='MPR 2. CPI inflation'!E128 -> 2.8 | E17: =100*((GMW!C229/GMW!C225)-1) -> 1.795549 | F17: =100*((GMW!F229/GMW!F225)-1) -> 1.6073936 | I17: ='MPR Chart G.1'!E21 -> 3.573 | J17: ='MPR Chart G.1'!I21 -> 3.941 | K17: ='MPR Chart G.1'!M21 -> 4.799 | L17: =GMW!D229 -> 3 | M17: =GMW!G229 -> 3.500527
B18: ='MPR 2. CPI inflation'!C129 -> 1.6 | C18: ='MPR 2. CPI inflation'!D129 -> 2 | D18: ='MPR 2. CPI inflation'!E129 -> 2.7 | E18: =100*((GMW!C230/GMW!C226)-1) -> 1.8753088 | F18: =100*((GMW!F230/GMW!F226)-1) -> 1.5862626 | I18: ='MPR Chart G.1'!E22 -> 3.513 | J18: ='MPR Chart G.1'!I22 -> 3.883 | K18: ='MPR Chart G.1'!M22 -> 4.693 | L18: =GMW!D230 -> 3 | M18: =GMW!G230 -> 3.250471
A19: 2029 | B19: ='MPR 2. CPI inflation'!C130 -> 1.7 | C19: ='MPR 2. CPI inflation'!D130 -> 2 | D19: ='MPR 2. CPI inflation'!E130 -> 2.6 | E19: =100*((GMW!C231/GMW!C227)-1) -> 1.9275092 | F19: =100*((GMW!F231/GMW!F227)-1) -> 1.5843348 | H19: 2029 | I19: ='MPR Chart G.1'!E23 -> 3.466 | J19: ='MPR Chart G.1'!I23 -> 3.83 | K19: ='MPR Chart G.1'!M23 -> 4.593 | L19: =GMW!D231 -> 3 | M19: =GMW!G231 -> 3.000411
B20: ='MPR 2. CPI inflation'!C131 -> 1.7 | C20: ='MPR 2. CPI inflation'!D131 -> 2 | D20: ='MPR 2. CPI inflation'!E131 -> 2.6 | E20: =100*((GMW!C232/GMW!C228)-1) -> 1.9352513 | F20: =100*((GMW!F232/GMW!F228)-1) -> 1.5683725 | I20: ='MPR Chart G.1'!E24 -> 3.428 | J20: ='MPR Chart G.1'!I24 -> 3.782 | K20: ='MPR Chart G.1'!M24 -> 4.497 | L20: =GMW!D232 -> 2.842308 | M20: =GMW!G232 -> 2.842655

Sheet GMW
A1: Location | B1: United Kingdom | C1: United Kingdom | D1: United Kingdom | E1: United Kingdom | F1: United Kingdom | G1: United Kingdom
A2: Indicator | B2: GDP, real, LCU | C2: Consumer price index | D2: Interest rate, central bank policy | E2: GDP, real, LCU | F2: Consumer price index | G2: Interest rate, central bank policy
A3: Scenario | B3: UK290426_BLANK2 | C3: UK290426_BLANK2 | D3: UK290426_BLANK2 | E3: GSS_Prolonged_Iran_War_Apr26_2 | F3: GSS_Prolonged_Iran_War_Apr26_2 | G3: GSS_Prolonged_Iran_War_Apr26_2
A4: Units | B4: Pound | C4: Index | D4: % | E4: Pound | F4: Index | G4: %
A5: Scale | B5: Millions | C5: NA | D5: NA | E5: Millions | F5: NA | G5: NA
A6: Measurement | B6: Level | C6: Level | D6: Level | E6: Level | F6: Level | G6: Level
A7: 1973 Q1 | B7: 267015 | C7: 11.88749 | D7: 8.788462 | E7: 0 | F7: 0 | G7: 0
A8: 1973 Q2 | B8: 267521 | C8: 12.3046 | D8: 7.996154 | E8: 0 | F8: 0 | G8: 0
A9: 1973 Q3 | B9: 265025 | C9: 12.51315 | D9: 10.38461 | E9: 0 | F9: 0 | G9: 0
A10: 1973 Q4 | B10: 263989 | C10: 13.00846 | D10: 12.23485 | E10: 0 | F10: 0 | G10: 0
A11: 1974 Q1 | B11: 256670 | C11: 13.47771 | D11: 12.60938 | E11: 0 | F11: 0 | G11: 0
A12: 1974 Q2 | B12: 260347 | C12: 14.23371 | D12: 11.96923 | E12: 0 | F12: 0 | G12: 0
A13: 1974 Q3 | B13: 261890 | C13: 14.57261 | D13: 11.72727 | E13: 0 | F13: 0 | G13: 0
A14: 1974 Q4 | B14: 258066 | C14: 15.2504 | D14: 11.5 | E14: 0 | F14: 0 | G14: 0
A15: 1975 Q1 | B15: 258116 | C15: 16.05854 | D15: 10.77344 | E15: 0 | F15: 0 | G15: 0
A16: 1975 Q2 | B16: 253935 | C16: 17.46627 | D16: 9.961538 | E16: 0 | F16: 0 | G16: 0
A17: 1975 Q3 | B17: 253168 | C17: 18.22228 | D17: 10.71212 | E17: 0 | F17: 0 | G17: 0
A18: 1975 Q4 | B18: 255985 | C18: 18.84793 | D18: 11.73106 | E18: 0 | F18: 0 | G18: 0
... A358: 2060 Q4 | B358: 1100197 | C358: 285.2462 | D358: 2.5 | E358: 0 | F358: 0 | G358: 0
A359: Source | B359: Office for National Statistics\Haver Analytics | C359: Office for National Statistics\Haver Analytics | D359: Bank of England \Haver Analytics | E359: Office for National Statistics\Haver Analytics | F359: Office for National Statistics\Haver Analytics | G359: Bank of England \Haver Analytics
A360: Seasonally adjusted | B360: TRUE | C360: FALSE | D360: FALSE | E360: TRUE | F360: FALSE | G360: FALSE
A361: Base year price | B361: chained 2023 | C361: NA | D361: NA | E361: chained 2023 | F361: NA | G361: NA
A362: Base year index | B362: NA | C362: 2015 | D362: NA | E362: NA | F362: 2015 | G362: NA
A363: Historical end year | B363: 2025 | C363: 2026 | D363: 2026 | E363: 2025 | F363: 2026 | G363: 2026
A364: Historical end quarter | B364: 4 | C364: 1 | D364: 1 | E364: 4 | F364: 1 | G364: 1
A365: Date of last update | B365: NA | C365: NA | D365: NA | E365: NA | F365: NA | G365: NA
A366: Source details | B366: ABMIQ@UK | C366: D7BT@UK | D366: agg(R112RD@INTDAILY,avg) | E366: ABMIQ@UK | F366: D7BT@UK | G366: agg(R112RD@INTDAILY,avg)
A367: Additional source details | B367: U.K.: Real Gross Domestic Product (SA, Mil.Chn.2023.GBP) | C367: UK: Consumer Price Index: All Items (NSA, 2015=100) | D367: United Kingdom: Official Bank Rate (%) | E367: U.K.: Real Gross Domestic Product (SA, Mil.Chn.2023.GBP) | F367: UK: Consumer Price Index: All Items (NSA, 2015=100) | G367: United Kingdom: Official Bank Rate (%)
A368: Location code | B368: GBR | C368: GBR | D368: GBR | E368: GBR | F368: GBR | G368: GBR
A369: Indicator code | B369: GDP | C369: CPI | D369: RCB | E369: GDP | F369: CPI | G369: RCB
A370: Databank code | B370: UK290426_BLANK2.db | C370: UK290426_BLANK2.db | D370: UK290426_BLANK2.db | E370: GSS_Prolonged_Iran_War_Apr26_2.db | F370: GSS_Prolonged_Iran_War_Apr26_2.db | G370: GSS_Prolonged_Iran_War_Apr26_2.db

Sheet MPR 2. CPI inflation
A1: CPI inflation
A2: Per cent
A3: Four-quarter percentage change in CPI index. Based on ONS series D7G7.
A5: Date | B5: February 2026 central projection | C5: April 2026 Scenario A | D5: April 2026 Scenario B | E5: April 2026 Scenario C
A6: 1998 Q1 | B6: 1.6 | C6: 1.6 | D6: 1.6 | E6: 1.6
A7: 1998 Q2 | B7: 1.8 | C7: 1.8 | D7: 1.8 | E7: 1.8
A8: 1998 Q3 | B8: 1.4 | C8: 1.4 | D8: 1.4 | E8: 1.4
A9: 1998 Q4 | B9: 1.4 | C9: 1.4 | D9: 1.4 | E9: 1.4
A10: 1999 Q1 | B10: 1.6 | C10: 1.6 | D10: 1.6 | E10: 1.6
A11: 1999 Q2 | B11: 1.4 | C11: 1.4 | D11: 1.4 | E11: 1.4
A12: 1999 Q3 | B12: 1.2 | C12: 1.2 | D12: 1.2 | E12: 1.2
A13: 1999 Q4 | B13: 1.1 | C13: 1.1 | D13: 1.1 | E13: 1.1
A14: 2000 Q1 | B14: 0.8 | C14: 0.8 | D14: 0.8 | E14: 0.8
A15: 2000 Q2 | B15: 0.6 | C15: 0.6 | D15: 0.6 | E15: 0.6
A16: 2000 Q3 | B16: 0.8 | C16: 0.8 | D16: 0.8 | E16: 0.8
A17: 2000 Q4 | B17: 1 | C17: 1 | D17: 1 | E17: 1
... A130: 2029 Q1 | B130: 2 | C130: 1.7 | D130: 2 | E130: 2.6
A131: 2029 Q2 | B131: n.a. | C131: 1.7 | D131: 2 | E131: 2.6

Sheet MPR Chart G.1
A1: Section 2: Topical policy issues
A3: Chart G.1 - Illustrative model-based policy projections, per cent
D5: Scenario A | H5: Scenario B | L5: Scenario C
A6: Date | B6: Bank Rate | D6: Illustrative model-based policy projection, lambda = 0 | E6: Illustrative model-based policy projection, lambda = 0.25 | F6: Illustrative model-based policy projection, lambda = 0.5 | H6: Illustrative model-based policy projection, lambda = 0 | I6: Illustrative model-based policy projection, lambda = 0.25 | J6: Illustrative model-based policy projection, lambda = 0.5 | L6: Illustrative model-based policy projection, lambda = 0 | M6: Illustrative model-based policy projection, lambda = 0.25 | N6: Illustrative model-based policy projection, lambda = 0.5
A7: 2025 Q1 | B7: 4.599 | D7: n.a. | E7: n.a. | F7: n.a. | H7: n.a. | I7: n.a. | J7: n.a. | L7: n.a. | M7: n.a. | N7: n.a.
A8: 2025 Q2 | B8: 4.348 | D8: n.a. | E8: n.a. | F8: n.a. | H8: n.a. | I8: n.a. | J8: n.a. | L8: n.a. | M8: n.a. | N8: n.a.
A9: 2025 Q3 | B9: 4.104 | D9: n.a. | E9: n.a. | F9: n.a. | H9: n.a. | I9: n.a. | J9: n.a. | L9: n.a. | M9: n.a. | N9: n.a.
A10: 2025 Q4 | B10: 3.969 | D10: n.a. | E10: n.a. | F10: n.a. | H10: n.a. | I10: n.a. | J10: n.a. | L10: n.a. | M10: n.a. | N10: n.a.
A11: 2026 Q1 | B11: 3.75 | D11: n.a. | E11: n.a. | F11: n.a. | H11: n.a. | I11: n.a. | J11: n.a. | L11: n.a. | M11: n.a. | N11: n.a.
A12: 2026 Q2 | B12: n.a. | D12: 4.134 | E12: 4.014 | F12: 3.924 | H12: 4.144 | I12: 4.025 | J12: 3.935 | L12: 4.551 | M12: 4.384 | N12: 4.256
A13: 2026 Q3 | B13: n.a. | D13: 4.395 | E13: 4.184 | F13: 4.026 | H13: 4.435 | I13: 4.224 | J13: 4.065 | L13: 5.181 | M13: 4.877 | N13: 4.645
A14: 2026 Q4 | B14: n.a. | D14: 4.52 | E14: 4.248 | F14: 4.044 | H14: 4.614 | I14: 4.336 | J14: 4.127 | L14: 5.592 | M14: 5.183 | N14: 4.874
A15: 2027 Q1 | B15: n.a. | D15: 4.52 | E15: 4.213 | F15: 3.984 | H15: 4.684 | I15: 4.36 | J15: 4.119 | L15: 5.802 | M15: 5.316 | N15: 4.952
A16: 2027 Q2 | B16: n.a. | D16: 4.435 | E16: 4.11 | F16: 3.87 | H16: 4.674 | I16: 4.32 | J16: 4.058 | L16: 5.857 | M16: 5.317 | N16: 4.917
A17: 2027 Q3 | B17: n.a. | D17: 4.309 | E17: 3.979 | F17: 3.737 | H17: 4.619 | I17: 4.244 | J17: 3.972 | L17: 5.816 | M17: 5.24 | N17: 4.818
A18: 2027 Q4 | B18: n.a. | D18: 4.177 | E18: 3.848 | F18: 3.611 | H18: 4.544 | I18: 4.158 | J18: 3.881 | L18: 5.734 | M18: 5.135 | N18: 4.7
A19: 2028 Q1 | B19: n.a. | D19: 4.059 | E19: 3.736 | F19: 3.506 | H19: 4.47 | I19: 4.077 | J19: 3.8 | L19: 5.634 | M19: 5.021 | N19: 4.582
A20: 2028 Q2 | B20: n.a. | D20: 3.959 | E20: 3.646 | F20: 3.426 | H20: 4.401 | I20: 4.006 | J20: 3.731 | L20: 5.524 | M20: 4.908 | N20: 4.472
A21: 2028 Q3 | B21: n.a. | D21: 3.873 | E21: 3.573 | F21: 3.365 | H21: 4.333 | I21: 3.941 | J21: 3.673 | L21: 5.409 | M21: 4.799 | N21: 4.371
A22: 2028 Q4 | B22: n.a. | D22: 3.797 | E22: 3.513 | F22: 3.32 | H22: 4.267 | I22: 3.883 | J22: 3.625 | L22: 5.29 | M22: 4.693 | N22: 4.281
A23: 2029 Q1 | B23: n.a. | D23: 3.73 | E23: 3.466 | F23: 3.29 | H23: 4.2 | I23: 3.83 | J23: 3.585 | L23: 5.168 | M23: 4.593 | N23: 4.2
A24: 2029 Q2 | B24: n.a. | D24: 3.67 | E24: 3.428 | F24: 3.271 | H24: 4.135 | I24: 3.782 | J24: 3.554 | L24: 5.044 | M24: 4.497 | N24: 4.128
